{
  "type": "Feature",
  "properties": {
    "iso:country":"ES",
    "sg:address":"Carrer de Sant Antoni, 1",
    "sg:city":"Espluga Francoli",
    "sg:orig_category":"Peluquer\u00cdas, Peluquer\u00cda Mixta",
    "sg:phone":"+34 977 87 00 02",
    "sg:postcode":"43440",
    "sg:province":"Tarragona",
    "wof:name":"Cots Cervello Montserrat",
    "wof:placetype":"venue"
},
  "geometry": {"coordinates":[1.1026639938,41.3967971802],"type":"Point"}
}