{
  "type": "Feature",
  "properties": {
    "addr:full":"Av Cas Saboners, S/n Palmanova Islas Baleares 07181",
    "addr:housenumber":"s / n",
    "addr:postcode":"07181",
    "addr:street":"Av Cas Saboners",
    "iso:country":"ES",
    "sg:address":"Av Cas Saboners, S/n",
    "sg:city":"Palmanova",
    "sg:orig_category":"Quincaller\u00cda (al Por Menor)",
    "sg:phone":"+34 971 68 28 67",
    "sg:postcode":"07181",
    "sg:province":"Islas Baleares",
    "wof:name":"Julian Trillo S.l.",
    "wof:placetype":"venue"
},
  "geometry": {"coordinates":[2.5350699425,39.5146522522],"type":"Point"}
}