{
  "type": "Feature",
  "properties": {
    "iso:country":"ES",
    "sg:address":"Calle de Salvador Escandon, 9",
    "sg:city":"Luanco",
    "sg:orig_category":"Ropa Para Se\u00d1oras Y Caballeros (al Por Menor)",
    "sg:phone":"+34 985 88 23 09",
    "sg:postcode":"33440",
    "sg:province":"Asturias",
    "wof:name":"Urrutia Pintado Jesus Jorge",
    "wof:placetype":"venue"
},
  "geometry": {"coordinates":[-5.7915887833,43.6161613464],"type":"Point"}
}