{
  "type": "Feature",
  "properties": {
    "addr:full":"Calle de General Sueiro, 41 Zaragoza Zaragoza 50008",
    "addr:housenumber":"41",
    "addr:postcode":"50008",
    "addr:street":"Calle De General Sueiro",
    "iso:country":"ES",
    "sg:address":"Calle de General Sueiro, 41",
    "sg:city":"Zaragoza",
    "sg:orig_category":"Centros De Coordinaci\u00d3n",
    "sg:phone":"+34 976 21 11 52",
    "sg:postcode":"50008",
    "sg:province":"Zaragoza",
    "sg:website":"www.terra.es/personal6/gestvillalba",
    "wof:name":"Villalba Lain Luis Antonio",
    "wof:placetype":"venue"
},
  "geometry": {"coordinates":[-0.8810300231,41.6441078186],"type":"Point"}
}