{
  "type": "Feature",
  "properties": {
    "iso:country":"ES",
    "sg:address":"Carrer de Muses, 1",
    "sg:city":"Hospitalet Llobregat",
    "sg:orig_category":"Herboristas (al Por Menor)",
    "sg:phone":"+34 934 40 10 48",
    "sg:postcode":"08905",
    "sg:province":"Barcelona",
    "wof:name":"Ripoll Lopez Maria Dolores",
    "wof:placetype":"venue"
},
  "geometry": {"coordinates":[2.1119420528,41.3697471619],"type":"Point"}
}