{
  "type": "Feature",
  "properties": {
    "iso:country":"ES",
    "sg:address":"Avda Manuel Llaneza, 58",
    "sg:city":"Gijon",
    "sg:orig_category":"Alquiler De V\u00cddeo",
    "sg:phone":"+34 985 39 05 02",
    "sg:postcode":"33208",
    "sg:province":"Asturias",
    "wof:name":"Kira Films",
    "wof:placetype":"venue"
},
  "geometry": {"coordinates":[-5.6664590836,43.5347213745],"type":"Point"}
}