{
  "type": "Feature",
  "properties": {
    "iso:country":"ES",
    "sg:address":"Gronzo, S/n",
    "sg:city":"Gronzo",
    "sg:orig_category":"Transportes En Cisternas",
    "sg:phone":"+34 981 88 71 97",
    "sg:postcode":"15865",
    "sg:province":"La Coru\u00f1a",
    "wof:name":"Lourido Perez Jose",
    "wof:placetype":"venue"
},
  "geometry": {"coordinates":[-8.6784410477,42.8665046692],"type":"Point"}
}