{
  "type": "Feature",
  "properties": {
    "iso:country":"ES",
    "sg:address":"Llanos Del Castillo, 2",
    "sg:city":"Llanos Castillo",
    "sg:orig_category":"Comercio De Cuadros, L\u00c1minas Y Reproducciones De Obras De Arte",
    "sg:phone":"+34 957 32 32 62",
    "sg:postcode":"14193",
    "sg:province":"C\u00f3rdoba",
    "wof:name":"Guillen Jimenez Cipriano",
    "wof:placetype":"venue"
},
  "geometry": {"coordinates":[-4.7791519165,37.884727478],"type":"Point"}
}