{
  "type": "Feature",
  "properties": {
    "addr:full":"Carrer de Sala Boadella, 3 Castellar Valles Barcelona 08211",
    "addr:housenumber":"3",
    "addr:postcode":"08211",
    "addr:street":"Carrer De Sala Boadella",
    "iso:country":"ES",
    "sg:address":"Carrer de Sala Boadella, 3",
    "sg:city":"Castellar Valles",
    "sg:orig_category":"Agencias De Viajes",
    "sg:phone":"+34 937 14 20 00",
    "sg:postcode":"08211",
    "sg:province":"Barcelona",
    "wof:name":"Masetur S.l.",
    "wof:placetype":"venue"
},
  "geometry": {"coordinates":[2.0875990391,41.6155967712],"type":"Point"}
}