{
  "type": "Feature",
  "properties": {
    "iso:country":"ES",
    "sg:address":"Calle de San Anton, 12",
    "sg:city":"Granada",
    "sg:orig_category":"Lencer\u00cda Femenina, Corseter\u00cda, Trajes De Ba\u00d1o (al Por Menor)",
    "sg:phone":"+34 958 52 32 19",
    "sg:postcode":"18005",
    "sg:province":"Granada",
    "wof:name":"Garcia Ortiz Purificacion",
    "wof:placetype":"venue"
},
  "geometry": {"coordinates":[-3.6001260281,37.1720466614],"type":"Point"}
}