{
  "type": "Feature",
  "properties": {
    "iso:country":"ES",
    "sg:address":"Calle de Gabriel Lobo, 9",
    "sg:city":"Madrid",
    "sg:orig_category":"Peluqueros: De Se\u00d1oras",
    "sg:phone":"+34 915 61 16 52",
    "sg:postcode":"28002",
    "sg:province":"Madrid",
    "wof:name":"Gl9 Peluqueria S.l.",
    "wof:placetype":"venue"
},
  "geometry": {"coordinates":[-3.6809461117,40.4428253174],"type":"Point"}
}