{
  "type": "Feature",
  "properties": {
    "addr:full":"Carrer de Doctor Presas, 49 S. Feliu Guixols Girona 17220",
    "addr:housenumber":"49",
    "addr:postcode":"17220",
    "addr:street":"Carrer De Doctor Presas;S. Feliu Guixols",
    "iso:country":"ES",
    "sg:address":"Carrer de Doctor Presas, 49",
    "sg:city":"S. Feliu Guixols",
    "sg:orig_category":"Semiller\u00cdas",
    "sg:phone":"+34 972 82 17 01",
    "sg:postcode":"17220",
    "sg:province":"Girona",
    "wof:name":"Masferrer Artigas Carlos",
    "wof:placetype":"venue"
},
  "geometry": {"coordinates":[3.0295579433,41.7879447937],"type":"Point"}
}