{
  "type": "Feature",
  "properties": {
    "addr:full":"Calle de Garcia Luna, 24 Madrid Madrid 28002",
    "addr:housenumber":"24",
    "addr:postcode":"madrid;28002",
    "addr:street":"Calle De Garcia Luna",
    "iso:country":"ES",
    "sg:address":"Calle de Garcia Luna, 24",
    "sg:city":"Madrid",
    "sg:orig_category":"Mec\u00c1nico Del Autom\u00d3vil",
    "sg:phone":"+34 914 15 93 86",
    "sg:postcode":"28002",
    "sg:province":"Madrid",
    "wof:name":"Gonzalez Velazquez Victor Manuel",
    "wof:placetype":"venue"
},
  "geometry": {"coordinates":[-3.6738991737,40.4463577271],"type":"Point"}
}