{
  "type": "Feature",
  "properties": {
    "iso:country":"ES",
    "sg:address":"Calle de Lepanto, 4",
    "sg:city":"Esquivias",
    "sg:orig_category":"Carnicer\u00cdas, Carnicer\u00cdas",
    "sg:phone":"+34 925 52 01 68",
    "sg:postcode":"45221",
    "sg:province":"Toledo",
    "wof:name":"Perez Portero Jose",
    "wof:placetype":"venue"
},
  "geometry": {"coordinates":[-3.766374588,40.1043357849],"type":"Point"}
}