{
  "type": "Feature",
  "properties": {
    "iso:country":"ES",
    "sg:address":"Carr Castelar, 17",
    "sg:city":"Eivissa",
    "sg:orig_category":"Prendas De Cuero Y De Piel (al Por Menor)",
    "sg:phone":"+34 971 31 09 19",
    "sg:postcode":"07800",
    "sg:province":"Islas Baleares",
    "wof:name":"Astruc  Marie Christine",
    "wof:placetype":"venue"
},
  "geometry": {"coordinates":[1.4363962412,38.9101295471],"type":"Point"}
}