{
  "type": "Feature",
  "properties": {
    "iso:country":"ES",
    "sg:address":"Avda Goya Francisco De Avenida, 8",
    "sg:city":"Zaragoza",
    "sg:orig_category":"Elementos Para Suelos Prefabricados",
    "sg:phone":"+34 976 23 46 96",
    "sg:postcode":"50006",
    "sg:province":"Zaragoza",
    "sg:website":"www.reycor.com",
    "wof:name":"Revestimientos Decorativos S.l.",
    "wof:placetype":"venue"
},
  "geometry": {"coordinates":[-0.8867840171,41.6426391602],"type":"Point"}
}