{
  "type": "Feature",
  "properties": {
    "iso:country":"ES",
    "sg:address":"Calle de Iglesia, 19",
    "sg:city":"Navas De Jorquera",
    "sg:orig_category":"Supermercados Y Hipermercados",
    "sg:phone":"+34 967 48 20 07",
    "sg:postcode":"02246",
    "sg:province":"Albacete",
    "wof:name":"Izquierdo Garcia Maribel",
    "wof:placetype":"venue"
},
  "geometry": {"coordinates":[-1.7183250189,39.2809715271],"type":"Point"}
}