{
  "type": "Feature",
  "properties": {
    "addr:full":"Calle de Ventas De Alcedo, 25 Alcedo Alba Le\u00f3n 24649",
    "addr:housenumber":"25",
    "addr:postcode":"24649",
    "addr:street":"Calle De Ventas De Alcedo",
    "iso:country":"ES",
    "sg:address":"Calle de Ventas De Alcedo, 25",
    "sg:city":"Alcedo Alba",
    "sg:orig_category":"Montaje (empresas De)",
    "sg:phone":"+34 987 57 04 89",
    "sg:postcode":"24649",
    "sg:province":"Le\u00f3n",
    "wof:name":"Augustyniak  Franz",
    "wof:placetype":"venue"
},
  "geometry": {"coordinates":[-5.6416988373,42.8057746887],"type":"Point"}
}