{
  "type": "Feature",
  "properties": {
    "addr:full":"Calle de Gumersindo, 33 Torrevieja Alicante 03180",
    "addr:housenumber":"33",
    "addr:postcode":"03180",
    "addr:street":"Calle De Gumersindo",
    "iso:country":"ES",
    "sg:address":"Calle de Gumersindo, 33",
    "sg:city":"Torrevieja",
    "sg:orig_category":"Art\u00cdculos De Decoraci\u00d3n",
    "sg:phone":"+34 965 71 90 51",
    "sg:postcode":"03180",
    "sg:province":"Alicante",
    "wof:name":"El Zaguan Muebles S.l.",
    "wof:placetype":"venue"
},
  "geometry": {"coordinates":[-0.676214993,37.9757270813],"type":"Point"}
}