{
  "type": "Feature",
  "properties": {
    "iso:country":"ES",
    "sg:address":"Avda Constitucion (la), S/n",
    "sg:city":"Pozo Guadalajara",
    "sg:orig_category":"Centros De Educaci\u00d3n Especial",
    "sg:phone":"+34 949 27 21 31",
    "sg:postcode":"19161",
    "sg:province":"Guadalajara",
    "wof:name":"Colegio Publico Santa Brigida",
    "wof:placetype":"venue"
},
  "geometry": {"coordinates":[-3.1794040203,40.4934768677],"type":"Point"}
}