{
  "type": "Feature",
  "properties": {
    "addr:full":"Rua Dr. Cadaval, 2 Vigo Pontevedra 36202",
    "addr:housenumber":"2",
    "addr:postcode":"36202",
    "addr:street":"Rua Dr.",
    "iso:country":"ES",
    "sg:address":"Rua Dr. Cadaval, 2",
    "sg:city":"Vigo",
    "sg:orig_category":"Centros Empresariales",
    "sg:phone":"+34 986 22 71 35",
    "sg:postcode":"36202",
    "sg:province":"Pontevedra",
    "wof:name":"Inova Consultores S.l.",
    "wof:placetype":"venue"
},
  "geometry": {"coordinates":[-8.7242040634,42.2363624573],"type":"Point"}
}