{
  "type": "Feature",
  "properties": {
    "iso:country":"ES",
    "sg:address":"Calle de Condado De Trevi\u00d1o, 17",
    "sg:city":"Miranda Ebro",
    "sg:orig_category":"Fabricaci\u00d3n De Productos Textiles Sin Tejer",
    "sg:phone":"+34 947 31 22 55",
    "sg:postcode":"09200",
    "sg:province":"Burgos",
    "wof:name":"Jimenez Gonzalez Abel",
    "wof:placetype":"venue"
},
  "geometry": {"coordinates":[-2.9460234642,42.68334198],"type":"Point"}
}