{
  "type": "Feature",
  "properties": {
    "addr:full":"Calle de Marcos Pe\u00d1a Royo, 1 Oviedo Asturias 33013",
    "addr:housenumber":"1",
    "addr:postcode":"33013",
    "addr:street":"Calle De Marcos Pen\u0303A Royo",
    "iso:country":"ES",
    "sg:address":"Calle de Marcos Pe\u00d1a Royo, 1",
    "sg:city":"Oviedo",
    "sg:orig_category":"Asesor\u00cda De Formaci\u00d3n Y Gesti\u00d3n De Personal",
    "sg:phone":"+34 985 23 07 08",
    "sg:postcode":"33013",
    "sg:province":"Asturias",
    "wof:name":"Asesoria Calleja S.l.",
    "wof:placetype":"venue"
},
  "geometry": {"coordinates":[-5.8629169464,43.3617668152],"type":"Point"}
}