{
  "type": "Feature",
  "properties": {
    "iso:country":"ES",
    "sg:address":"Calle de Los Morcelos, 9",
    "sg:city":"S. Bartolome Torre",
    "sg:orig_category":"Contenedores (mercanc\u00cdas)",
    "sg:phone":"+34 959 38 62 48",
    "sg:postcode":"21510",
    "sg:province":"Huelva",
    "wof:name":"Martinez Moral Magdalena",
    "wof:placetype":"venue"
},
  "geometry": {"coordinates":[-7.105738163,37.4437484741],"type":"Point"}
}