{
  "type": "Feature",
  "properties": {
    "addr:full":"Calle de Barbacana Baja, 12 Carmona Sevilla 41410",
    "addr:housenumber":"12",
    "addr:postcode":"41410",
    "addr:street":"Calle De Barbacana Baja",
    "iso:country":"ES",
    "sg:address":"Calle de Barbacana Baja, 12",
    "sg:city":"Carmona",
    "sg:orig_category":"Carnicer\u00cdas, Carnicer\u00cdas",
    "sg:phone":"+34 954 14 04 01",
    "sg:postcode":"41410",
    "sg:province":"Sevilla",
    "wof:name":"Diaz Gomez Antonio",
    "wof:placetype":"venue"
},
  "geometry": {"coordinates":[-5.6417102814,37.4720344543],"type":"Point"}
}