{
  "type": "Feature",
  "properties": {
    "addr:full":"Calle de Santisima Trinidad, 16 Antequera M\u00e1laga 29200",
    "addr:housenumber":"16",
    "addr:postcode":"29200",
    "addr:street":"Calle De Santisima Trinidad",
    "iso:country":"ES",
    "sg:address":"Calle de Santisima Trinidad, 16",
    "sg:city":"Antequera",
    "sg:orig_category":"Fabricaci\u00d3n, Venta, Instalaci\u00d3n De R\u00d3tulos, De R\u00d3tulos Luminosos",
    "sg:phone":"+34 952 70 20 90",
    "sg:postcode":"29200",
    "sg:province":"M\u00e1laga",
    "wof:name":"Garcia Ruz Antonio Miguel",
    "wof:placetype":"venue"
},
  "geometry": {"coordinates":[-4.5631861687,37.0184364319],"type":"Point"}
}