{
  "type": "Feature",
  "properties": {
    "addr:full":"Plaz San Blas, 1 Recas Toledo 45211",
    "addr:housenumber":"1",
    "addr:postcode":"45211",
    "addr:street":"Plaz San Blas",
    "iso:country":"ES",
    "sg:address":"Plaz San Blas, 1",
    "sg:city":"Recas",
    "sg:orig_category":"Estancos",
    "sg:phone":"+34 925 52 20 04",
    "sg:postcode":"45211",
    "sg:province":"Toledo",
    "wof:name":"Corbelle Bravo Urbana",
    "wof:placetype":"venue"
},
  "geometry": {"coordinates":[-3.9893109798,40.0538978577],"type":"Point"}
}