{
  "type": "Feature",
  "properties": {
    "iso:country":"ES",
    "sg:address":"Calle de Fuente (la), 18",
    "sg:city":"Burlada",
    "sg:orig_category":"Plomeros",
    "sg:phone":"+34 948 14 06 49",
    "sg:postcode":"31600",
    "sg:province":"Navarra",
    "wof:name":"Calefaccion Y Gas Merino S.l.",
    "wof:placetype":"venue"
},
  "geometry": {"coordinates":[-1.6185619831,42.826789856],"type":"Point"}
}