{
  "type": "Feature",
  "properties": {
    "iso:country":"ES",
    "sg:address":"Poli Mugitegi-b, 37",
    "sg:city":"Urretxu",
    "sg:orig_category":"Restaurantes",
    "sg:phone":"+34 943 72 51 65",
    "sg:postcode":"20700",
    "sg:province":"Guip\u00f9zcoa",
    "wof:name":"Zabaleta Betegui Lourdes",
    "wof:placetype":"venue"
},
  "geometry": {"coordinates":[-2.3134770393,43.086730957],"type":"Point"}
}