{
  "type": "Feature",
  "properties": {
    "iso:country":"ES",
    "sg:address":"Pl Jaume Balmes, 5",
    "sg:city":"Gava",
    "sg:orig_category":"Arreglo, Reparaci\u00d3n, Piezas Sueltas De Televisi\u00d3n, V\u00cddeo, Hi",
    "sg:phone":"+34 936 33 63 04",
    "sg:postcode":"08850",
    "sg:province":"Barcelona",
    "wof:name":"Arance Martin Vicente",
    "wof:placetype":"venue"
},
  "geometry": {"coordinates":[2.0233581066,41.317073822],"type":"Point"}
}