{
  "type": "Feature",
  "properties": {
    "iso:country":"ES",
    "sg:address":"Calle de Carretera Hurchillo-arneva, 9",
    "sg:city":"Arneva",
    "sg:orig_category":"Distribuci\u00d3n De Petr\u00d3leo Y Derivados",
    "sg:phone":"+34 965 30 13 89",
    "sg:postcode":"03312",
    "sg:province":"Alicante",
    "wof:name":"Estacion De Servicio El Tanque Arneva S.l.",
    "wof:placetype":"venue"
},
  "geometry": {"coordinates":[-0.9232022762,38.0591278076],"type":"Point"}
}