{
  "type": "Feature",
  "properties": {
    "iso:country":"ES",
    "sg:address":"Calle de Rafael Alberti, S/n",
    "sg:city":"Argamasilla Alba",
    "sg:orig_category":"Ense\u00d1anza, Formaci\u00d3n Profesional: Aprendizaje",
    "sg:phone":"+34 926 52 16 83",
    "sg:postcode":"13710",
    "sg:province":"Ciudad Real",
    "wof:name":"Ayuntamiento De Argamasilla De Alba",
    "wof:placetype":"venue"
},
  "geometry": {"coordinates":[-3.0946369171,39.1293449402],"type":"Point"}
}