{
  "type": "Feature",
  "properties": {
    "addr:full":"Calle de Godella, 34 Madrid Madrid 28021",
    "addr:housenumber":"34",
    "addr:postcode":"madrid;28021",
    "addr:street":"Calle De Godella",
    "iso:country":"ES",
    "sg:address":"Calle de Godella, 34",
    "sg:city":"Madrid",
    "sg:orig_category":"Obras Y Organismos Sociales",
    "sg:phone":"+34 915 05 40 13",
    "sg:postcode":"28021",
    "sg:province":"Madrid",
    "wof:name":"Hermanitas De La Asuncion",
    "wof:placetype":"venue"
},
  "geometry": {"coordinates":[-3.6884169579,40.3433532715],"type":"Point"}
}