{
  "type": "Feature",
  "properties": {
    "iso:country":"ES",
    "sg:address":"Calle de Santa Ana, S/n",
    "sg:city":"Albal",
    "sg:orig_category":"Goma: Materias Primas (producci\u00d3n, Distribuci\u00d3n)",
    "sg:phone":"+34 961 26 35 18",
    "sg:postcode":"46470",
    "sg:province":"Valencia",
    "wof:name":"Ortega Escusa Francisco Javier",
    "wof:placetype":"venue"
},
  "geometry": {"coordinates":[-0.4158740044,39.3979034424],"type":"Point"}
}