{
  "type": "Feature",
  "properties": {
    "addr:full":"Plaz Espa\u00d1a, 7 Madrid Madrid 28...",
    "addr:housenumber":"7;28 ...",
    "addr:postcode":"madrid",
    "addr:street":"Plaz Espan\u0303A;Madrid",
    "iso:country":"ES",
    "sg:address":"Plaz Espa\u00d1a, 7",
    "sg:city":"Madrid",
    "sg:orig_category":"Centros De Reservas Hoteleras",
    "sg:phone":"+34 914 54 46 00",
    "sg:postcode":"28...",
    "sg:province":"Madrid",
    "wof:name":"Comunidad De Propietarios Plaza Espa\u00d1a 7 Madrid",
    "wof:placetype":"venue"
},
  "geometry": {"coordinates":[-3.7124490738,40.4223213196],"type":"Point"}
}