{
  "type": "Feature",
  "properties": {
    "iso:country":"ES",
    "sg:address":"Calle de General Sueiro, 40",
    "sg:city":"Zaragoza",
    "sg:orig_category":"Mec\u00c1nico Del Autom\u00d3vil",
    "sg:phone":"+34 976 21 12 66",
    "sg:postcode":"50008",
    "sg:province":"Zaragoza",
    "wof:name":"Lalaguna Santafe Agustin",
    "wof:placetype":"venue"
},
  "geometry": {"coordinates":[-0.8814449906,41.6441078186],"type":"Point"}
}