{
  "type": "Feature",
  "properties": {
    "iso:country":"ES",
    "sg:address":"Calle de Alegria, 1",
    "sg:city":"Estrella",
    "sg:orig_category":"Negocio De Materiales De Construcci\u00d3n",
    "sg:phone":"+34 928 13 02 24",
    "sg:postcode":"35212",
    "sg:province":"Las Palmas",
    "wof:name":"Dominguez Dominguez Luis Jacinto",
    "wof:placetype":"venue"
},
  "geometry": {"coordinates":[-15.3880844116,28.0231990814],"type":"Point"}
}