{
  "type": "Feature",
  "properties": {
    "addr:full":"Calle de Urazurrutia, 2 Bilbao Vizcaya 48003",
    "addr:housenumber":"2",
    "addr:postcode":"48003",
    "addr:street":"Calle De Urazurrutia",
    "iso:country":"ES",
    "sg:address":"Calle de Urazurrutia, 2",
    "sg:city":"Bilbao",
    "sg:orig_category":"Farmacias",
    "sg:phone":"+34 944 15 62 50",
    "sg:postcode":"48003",
    "sg:province":"Vizcaya",
    "wof:name":"Bernas Uncilla Ana Rosa",
    "wof:placetype":"venue"
},
  "geometry": {"coordinates":[-2.9232289791,43.2540435791],"type":"Point"}
}