{
  "type": "Feature",
  "properties": {
    "iso:country":"ES",
    "sg:address":"Gayanes, 15",
    "sg:city":"Elche",
    "sg:orig_category":"Bordado, Marcado A Medida",
    "sg:phone":"+34 965 43 74 00",
    "sg:postcode":"03206",
    "sg:province":"Alicante",
    "wof:name":"Creaciones Artebor S.l.",
    "wof:placetype":"venue"
},
  "geometry": {"coordinates":[-0.7142999768,38.2850990295],"type":"Point"}
}