{
  "type": "Feature",
  "properties": {
    "addr:full":"Calle de Korreo Kalea, 23 Tolosa Guip\u00f9zcoa 20400",
    "addr:housenumber":"23",
    "addr:postcode":"20400",
    "addr:street":"Calle De Korreo Kalea;Guipu\u0300Zcoa",
    "iso:country":"ES",
    "sg:address":"Calle de Korreo Kalea, 23",
    "sg:city":"Tolosa",
    "sg:orig_category":"Ropa Para Se\u00d1oras (al Por Menor)",
    "sg:phone":"+34 943 67 41 97",
    "sg:postcode":"20400",
    "sg:province":"Guip\u00f9zcoa",
    "wof:name":"Azpiroz Astiz Milagros",
    "wof:placetype":"venue"
},
  "geometry": {"coordinates":[-2.0725851059,43.1383628845],"type":"Point"}
}