{
  "type": "Feature",
  "properties": {
    "addr:full":"Ocho De Mar\u00e7(p I Pla Del Conde), 9 Albaida Valencia 46860",
    "addr:housenumber":"9",
    "addr:postcode":"46860",
    "addr:street":"Ocho;P I Pla Del Conde",
    "iso:country":"ES",
    "sg:address":"Ocho De Mar\u00e7(p I Pla Del Conde), 9",
    "sg:city":"Albaida",
    "sg:orig_category":"Confecci\u00d3n (fabricaci\u00d3n, Al Por Mayor)",
    "sg:phone":"+34 962 91 31 36",
    "sg:postcode":"46860",
    "sg:province":"Valencia",
    "wof:name":"Textils Casandra S.l.",
    "wof:placetype":"venue"
},
  "geometry": {"coordinates":[-0.5262989998,38.8420715332],"type":"Point"}
}