{
  "type": "Feature",
  "properties": {
    "iso:country":"ES",
    "sg:address":"Avda Puente Del Pilar, 27",
    "sg:city":"Zaragoza",
    "sg:orig_category":"Inmobiliaria (agencias)",
    "sg:phone":"+34 976 29 06 83",
    "sg:postcode":"50014",
    "sg:province":"Zaragoza",
    "wof:name":"Euro Alcoraz Promociones S.l.",
    "wof:placetype":"venue"
},
  "geometry": {"coordinates":[-0.8691359758,41.6583709717],"type":"Point"}
}