{
  "type": "Feature",
  "properties": {
    "addr:full":"Calle de Real De Arganda, 18 Madrid Madrid 28031",
    "addr:housenumber":"18",
    "addr:postcode":"madrid;28031",
    "addr:street":"Calle De Real De Arganda",
    "iso:country":"ES",
    "sg:address":"Calle de Real De Arganda, 18",
    "sg:city":"Madrid",
    "sg:orig_category":"Inmobiliaria (agencias)",
    "sg:phone":"+34 913 32 20 96",
    "sg:postcode":"28031",
    "sg:province":"Madrid",
    "wof:name":"Fincas Mendel S.l.",
    "wof:placetype":"venue"
},
  "geometry": {"coordinates":[-3.6170740128,40.3793373108],"type":"Point"}
}