{
  "type": "Feature",
  "properties": {
    "iso:country":"ES",
    "sg:address":"Ctra Toledo Alcazar, Km. 0060,8",
    "sg:city":"Consuegra",
    "sg:orig_category":"Negocio De Madera",
    "sg:phone":"+34 925 48 14 94",
    "sg:postcode":"45700",
    "sg:province":"Toledo",
    "wof:name":"Domingo Barba S. L.",
    "wof:placetype":"venue"
},
  "geometry": {"coordinates":[-3.6055839062,39.4619865417],"type":"Point"}
}