{
  "type": "Feature",
  "properties": {
    "addr:full":"Carr Sant Sebastia, 24 Santa Coloma De Farners Girona 17430",
    "addr:housenumber":"24",
    "addr:postcode":"17430",
    "addr:street":"Carr Sant Sebastia",
    "iso:country":"ES",
    "sg:address":"Carr Sant Sebastia, 24",
    "sg:city":"Santa Coloma De Farners",
    "sg:orig_category":"Servicios Gsm",
    "sg:phone":"+34 972 84 02 58",
    "sg:postcode":"17430",
    "sg:province":"Girona",
    "wof:name":"Electro-pallicer Sl",
    "wof:placetype":"venue"
},
  "geometry": {"coordinates":[2.6646769047,41.8618087769],"type":"Point"}
}