{
  "type": "Feature",
  "properties": {
    "addr:full":"Calle de Santo Tomas, 5 Segovia Segovia 40002",
    "addr:housenumber":"5",
    "addr:postcode":"40002",
    "addr:street":"Calle De Santo Tomas",
    "iso:country":"ES",
    "sg:address":"Calle de Santo Tomas, 5",
    "sg:city":"Segovia",
    "sg:orig_category":"Farmacias",
    "sg:phone":"+34 921 43 50 06",
    "sg:postcode":"40002",
    "sg:province":"Segovia",
    "wof:name":"Jose Mariatamayo Barbero Farmacia",
    "wof:placetype":"venue"
},
  "geometry": {"coordinates":[-4.1180081367,40.9432601929],"type":"Point"}
}