{
  "type": "Feature",
  "properties": {
    "iso:country":"ES",
    "sg:address":"Carrer de Rec, 46",
    "sg:city":"Barcelona",
    "sg:orig_category":"Ropa Para Se\u00d1oras (al Por Menor)",
    "sg:phone":"+34 933 10 64 69",
    "sg:postcode":"08003",
    "sg:province":"Barcelona",
    "wof:name":"Menchen Tomas S.l.",
    "wof:placetype":"venue"
},
  "geometry": {"coordinates":[2.1834039688,41.3845977783],"type":"Point"}
}