{
  "type": "Feature",
  "properties": {
    "iso:country":"ES",
    "sg:address":"Calle de Canton, 6",
    "sg:city":"Santillana",
    "sg:orig_category":"Cer\u00c1mica Art\u00cdstica Y Decorativa",
    "sg:phone":"+34 942 81 83 61",
    "sg:postcode":"39330",
    "sg:province":"Cantabria",
    "wof:name":"Gonzalez Bengoechea Juan",
    "wof:placetype":"venue"
},
  "geometry": {"coordinates":[-4.1073703766,43.3905487061],"type":"Point"}
}