{
  "type": "Feature",
  "properties": {
    "iso:country":"ES",
    "sg:address":"Avda Lugo, S/n",
    "sg:city":"Palas Rei",
    "sg:orig_category":"Sanatorios M\u00c9dico",
    "sg:phone":"+34 982 37 41 32",
    "sg:postcode":"27200",
    "sg:province":"Lugo",
    "wof:name":"Sergas-atencion Primaria Lugo",
    "wof:placetype":"venue"
},
  "geometry": {"coordinates":[-7.8687338829,42.8742141724],"type":"Point"}
}