{
  "type": "Feature",
  "properties": {
    "iso:country":"ES",
    "sg:address":"Alamo Gris (pi Fuente Rey), 1",
    "sg:city":"Dos Hermanas",
    "sg:orig_category":"Artes Gr\u00c1ficas, Artes Pl\u00c1sticas (curso)",
    "sg:phone":"+34 954 69 03 82",
    "sg:postcode":"41700",
    "sg:province":"Sevilla",
    "wof:name":"Digicromo S.l.l.",
    "wof:placetype":"venue"
},
  "geometry": {"coordinates":[-5.9760780334,37.3074493408],"type":"Point"}
}