{
  "type": "Feature",
  "properties": {
    "addr:full":"Carr Comandant Hernandez, Del, 4 Carcaixent Valencia 46740",
    "addr:housenumber":"4",
    "addr:postcode":"46740",
    "addr:street":"Carr Comandant Hernandez Del",
    "iso:country":"ES",
    "sg:address":"Carr Comandant Hernandez, Del, 4",
    "sg:city":"Carcaixent",
    "sg:orig_category":"Inmobiliaria (agencias)",
    "sg:phone":"+34 962 43 05 56",
    "sg:postcode":"46740",
    "sg:province":"Valencia",
    "wof:name":"Inmosoler S.l.",
    "wof:placetype":"venue"
},
  "geometry": {"coordinates":[-0.4510976076,39.122379303],"type":"Point"}
}