{
  "type": "Feature",
  "properties": {
    "iso:country":"ES",
    "sg:address":"Crta Villaf-cabanes, Km. 0005,0",
    "sg:city":"Masia Pla Lluch",
    "sg:orig_category":"Explotaci\u00d3n De Minas",
    "sg:phone":"+34 964 65 72 16",
    "sg:postcode":"12130",
    "sg:province":"Castell\u00f3n",
    "wof:name":"Watts Blake Bearne Espana S.a.",
    "wof:placetype":"venue"
},
  "geometry": {"coordinates":[-0.0360242017,39.9860687256],"type":"Point"}
}