{
  "type": "Feature",
  "properties": {
    "iso:country":"ES",
    "sg:address":"Pol. Ind. Erletxes, S/n",
    "sg:city":"Gumuzio",
    "sg:orig_category":"Ingeniero",
    "sg:phone":"+34 944 57 07 90",
    "sg:postcode":"48960",
    "sg:province":"Vizcaya",
    "wof:name":"Ingelux S.a.",
    "wof:placetype":"venue"
},
  "geometry": {"coordinates":[-2.8470389843,43.2298049927],"type":"Point"}
}