{
  "type": "Feature",
  "properties": {
    "iso:country":"ES",
    "sg:address":"Calle de Alonso Alvarado, 16",
    "sg:city":"Palmas De Gran Canaria",
    "sg:orig_category":"Sales (al Por Mayor)",
    "sg:phone":"+34 928 37 17 10",
    "sg:postcode":"35003",
    "sg:province":"Las Palmas",
    "wof:name":"Delgado Gomez Vicente",
    "wof:placetype":"venue"
},
  "geometry": {"coordinates":[-15.4177188873,28.1103096008],"type":"Point"}
}