{
  "type": "Feature",
  "properties": {
    "iso:country":"ES",
    "sg:address":"Calle de Lepanto, 24",
    "sg:city":"Aspe",
    "sg:orig_category":"Asociaciones Y Clubs Deportivos",
    "sg:phone":"+34 965 49 03 28",
    "sg:postcode":"03680",
    "sg:province":"Alicante",
    "wof:name":"Deportes Marsan S.l.",
    "wof:placetype":"venue"
},
  "geometry": {"coordinates":[-0.7679690123,38.3486862183],"type":"Point"}
}