{
  "type": "Feature",
  "properties": {
    "iso:country":"ES",
    "sg:address":"Ctra. Arquillos-vilches, S/n",
    "sg:city":"Arquillos",
    "sg:orig_category":"Cr\u00cda De Animales",
    "sg:phone":"+34 953 12 51 66",
    "sg:postcode":"23230",
    "sg:province":"Ja\u00e9n",
    "wof:name":"Agropecuaria Guadalimar S.l.",
    "wof:placetype":"venue"
},
  "geometry": {"coordinates":[-3.4296445847,38.213924408],"type":"Point"}
}