{
  "type": "Feature",
  "properties": {
    "iso:country":"ES",
    "sg:address":"Calle de Pablo Neruda, 3",
    "sg:city":"Atarfe",
    "sg:orig_category":"Partidos Pol\u00cdticos",
    "sg:phone":"+34 958 43 83 68",
    "sg:postcode":"18230",
    "sg:province":"Granada",
    "wof:name":"Garcia Garcia Jose",
    "wof:placetype":"venue"
},
  "geometry": {"coordinates":[-3.6921889782,37.222530365],"type":"Point"}
}