{
  "type": "Feature",
  "properties": {
    "iso:country":"ES",
    "sg:address":"Calle de Isabela Saverana, 15",
    "sg:city":"Madrid",
    "sg:orig_category":"Fabricaci\u00d3n, Importaci\u00d3n De L\u00c1mparas Y Bombillas",
    "sg:phone":"+34 915 08 13 98",
    "sg:postcode":"28044",
    "sg:province":"Madrid",
    "wof:name":"Murillo Tena Pablo",
    "wof:placetype":"venue"
},
  "geometry": {"coordinates":[-3.7592940331,40.3687171936],"type":"Point"}
}