{
  "type": "Feature",
  "properties": {
    "addr:full":"Carrer de Trulls, 9 Vendrell Tarragona 43700",
    "addr:housenumber":"9",
    "addr:postcode":"43700",
    "addr:street":"Carrer De Trulls",
    "iso:country":"ES",
    "sg:address":"Carrer de Trulls, 9",
    "sg:city":"Vendrell",
    "sg:orig_category":"Charcuter\u00cdas (al Por Mayor)",
    "sg:phone":"+34 977 66 80 94",
    "sg:postcode":"43700",
    "sg:province":"Tarragona",
    "wof:name":"Arroyo Ramirez Pablo",
    "wof:placetype":"venue"
},
  "geometry": {"coordinates":[1.535249114,41.2192001343],"type":"Point"}
}