{
  "type": "Feature",
  "properties": {
    "addr:full":"Calle de Alcaudon, 58 Madrid Madrid 28019",
    "addr:housenumber":"58",
    "addr:postcode":"madrid;28019",
    "addr:street":"Calle De Alcaudon",
    "iso:country":"ES",
    "sg:address":"Calle de Alcaudon, 58",
    "sg:city":"Madrid",
    "sg:orig_category":"Alquiler De V\u00cddeo",
    "sg:phone":"+34 914 72 96 94",
    "sg:postcode":"28019",
    "sg:province":"Madrid",
    "wof:name":"Pardo San Vicente Santiago",
    "wof:placetype":"venue"
},
  "geometry": {"coordinates":[-3.7346026897,40.3946456909],"type":"Point"}
}