{
  "type": "Feature",
  "properties": {
    "addr:full":"Rua Pontedeume, 9 Sada A Coru\u00f1a 15160",
    "addr:housenumber":"9",
    "addr:postcode":"15160",
    "addr:street":"Pontedeume",
    "iso:country":"ES",
    "sg:address":"Rua Pontedeume, 9",
    "sg:city":"Sada",
    "sg:orig_category":"Bricolaje, Herramientas (al Por Menor)",
    "sg:phone":"+34 981 62 27 61",
    "sg:postcode":"15160",
    "sg:province":"A Coru\u00f1a",
    "wof:name":"Tocamadera Manualidades",
    "wof:placetype":"venue"
},
  "geometry": {"coordinates":[-8.2540836334,43.3491783142],"type":"Point"}
}