{
  "type": "Feature",
  "properties": {
    "addr:full":"Carrer de Radas, 34 Barcelona Barcelona 08004",
    "addr:housenumber":"34",
    "addr:postcode":"08004",
    "addr:street":"Carrer De Radas",
    "iso:country":"ES",
    "sg:address":"Carrer de Radas, 34",
    "sg:city":"Barcelona",
    "sg:orig_category":"Alimentaci\u00d3n General (al Por Menor)",
    "sg:phone":"+34 934 42 59 54",
    "sg:postcode":"08004",
    "sg:province":"Barcelona",
    "wof:name":"O. Ikpiha  Pince Lucky",
    "wof:placetype":"venue"
},
  "geometry": {"coordinates":[2.1603319645,41.372505188],"type":"Point"}
}