{
  "type": "Feature",
  "properties": {
    "iso:country":"ES",
    "sg:address":"Ctra Creu Negra, (de La), S/n",
    "sg:city":"Carlet",
    "sg:orig_category":"Bebidas",
    "sg:phone":"+34 962 53 11 00",
    "sg:postcode":"46240",
    "sg:province":"Valencia",
    "wof:name":"Monzo Luis S.l.",
    "wof:placetype":"venue"
},
  "geometry": {"coordinates":[-0.4967400134,39.2342414856],"type":"Point"}
}