{
  "type": "Feature",
  "properties": {
    "iso:country":"ES",
    "sg:address":"Rua Vazquez Portome\u00d1e, 16",
    "sg:city":"Xunqueira Espadanedo",
    "sg:orig_category":"Centros De Educaci\u00d3n Especial",
    "sg:phone":"+34 988 29 10 52",
    "sg:postcode":"32730",
    "sg:province":"Ourense",
    "wof:name":"Colegio Publico De E. G. B. Xunqueira De Espada\u00f1edo",
    "wof:placetype":"venue"
},
  "geometry": {"coordinates":[-7.6296949387,42.3187408447],"type":"Point"}
}