{
  "type": "Feature",
  "properties": {
    "iso:country":"ES",
    "sg:address":"Carr Sebastia Llorens, 11",
    "sg:city":"Blanes",
    "sg:orig_category":"Abogados",
    "sg:phone":"+34 972 33 51 60",
    "sg:postcode":"17300",
    "sg:province":"Girona",
    "sg:website":"www.advocats-blanes.com",
    "wof:name":"Bufet Advocats Blanes S.l.",
    "wof:placetype":"venue"
},
  "geometry": {"coordinates":[2.7871921062,41.6776237488],"type":"Point"}
}