{
  "type": "Feature",
  "properties": {
    "addr:full":"Cmno Detras Castillo, S/n Almenara Castell\u00f3n 12590",
    "addr:housenumber":"s / n",
    "addr:postcode":"12590",
    "addr:street":"Cmno Detras Castillo",
    "iso:country":"ES",
    "sg:address":"Cmno Detras Castillo, S/n",
    "sg:city":"Almenara",
    "sg:orig_category":"Ferreter\u00cda (diversos)",
    "sg:phone":"+34 962 61 11 97",
    "sg:postcode":"12590",
    "sg:province":"Castell\u00f3n",
    "wof:name":"Acemed S. A.",
    "wof:placetype":"venue"
},
  "geometry": {"coordinates":[-0.2291564941,39.7495727539],"type":"Point"}
}