{
  "type": "Feature",
  "properties": {
    "addr:full":"Transportes, S/n Pepino Toledo 45638",
    "addr:housenumber":"s / n",
    "addr:postcode":"45638",
    "iso:country":"ES",
    "sg:address":"Transportes, S/n",
    "sg:city":"Pepino",
    "sg:orig_category":"Cerrajer\u00cda, Ferrallista",
    "sg:phone":"+34 925 70 97 62",
    "sg:postcode":"45638",
    "sg:province":"Toledo",
    "wof:name":"Bealumet S.l",
    "wof:placetype":"venue"
},
  "geometry": {"coordinates":[-4.8258938789,40.0016593933],"type":"Point"}
}