{
  "type": "Feature",
  "properties": {
    "addr:full":"Calle de San Ildefonso, 9 Peligros Granada 18210",
    "addr:housenumber":"9",
    "addr:postcode":"18210",
    "addr:street":"Calle De San Ildefonso",
    "iso:country":"ES",
    "sg:address":"Calle de San Ildefonso, 9",
    "sg:city":"Peligros",
    "sg:orig_category":"Agencias De Viajes",
    "sg:phone":"+34 958 40 14 63",
    "sg:postcode":"18210",
    "sg:province":"Granada",
    "wof:name":"Viajes Informatour S.l.",
    "wof:placetype":"venue"
},
  "geometry": {"coordinates":[-3.6289849281,37.2322120667],"type":"Point"}
}