{
  "type": "Feature",
  "properties": {
    "iso:country":"ES",
    "sg:address":"Calle de Marisme\u00d1os De Los, 14",
    "sg:city":"Huelva",
    "sg:orig_category":"Cervecer\u00cdas",
    "sg:phone":"+34 959 22 56 54",
    "sg:postcode":"21004",
    "sg:province":"Huelva",
    "wof:name":"Rios Fernandez Manuela",
    "wof:placetype":"venue"
},
  "geometry": {"coordinates":[-6.9495940208,37.256313324],"type":"Point"}
}