{
  "type": "Feature",
  "properties": {
    "addr:full":"Calle de San Cosme, 15 Cuenca Cuenca 16003",
    "addr:housenumber":"15",
    "addr:postcode":"16003",
    "addr:street":"Calle De San Cosme",
    "iso:country":"ES",
    "sg:address":"Calle de San Cosme, 15",
    "sg:city":"Cuenca",
    "sg:orig_category":"Molduras, Junquillos, Listones Y Molduras Perforadas",
    "sg:phone":"+34 969 21 28 25",
    "sg:postcode":"16003",
    "sg:province":"Cuenca",
    "wof:name":"Garcia De La Torre Teofilo",
    "wof:placetype":"venue"
},
  "geometry": {"coordinates":[-2.1466441154,40.0708961487],"type":"Point"}
}