{
  "type": "Feature",
  "properties": {
    "addr:full":"Rond Outeiro, 284 Coru\u00d1a La Coru\u00f1a 15011",
    "addr:housenumber":"284",
    "addr:postcode":"15011",
    "addr:street":"Outeiro;La Corun\u0303A",
    "iso:country":"ES",
    "sg:address":"Rond Outeiro, 284",
    "sg:city":"Coru\u00d1a",
    "sg:orig_category":"Peluqueros: De Se\u00d1oras",
    "sg:phone":"+34 981 27 28 63",
    "sg:postcode":"15011",
    "sg:province":"La Coru\u00f1a",
    "wof:name":"Sanchez Souto Manuel",
    "wof:placetype":"venue"
},
  "geometry": {"coordinates":[-8.4253988266,43.372631073],"type":"Point"}
}