{
  "type": "Feature",
  "properties": {
    "iso:country":"ES",
    "sg:address":"Carr Soler, 25",
    "sg:city":"Sant Lloren\u00c7 Des Cardassar",
    "sg:classifiers":[
        {
            "category":"Manufacturing",
            "subcategory":"Building Materials",
            "type":"Manufacturing & Wholesale Goods"
        }
    ],
    "sg:phone":"+34 971 56 92 14",
    "sg:postcode":"07530",
    "sg:province":"Islas Baleares",
    "sg:tags":[
        "cemento",
        "y",
        "de",
        "fabricaci\u00d3n",
        "cal"
    ],
    "wof:name":"Santandreu Sanso Jose",
    "wof:placetype":"venue"
},
  "geometry": {"coordinates":[3.2828950882,39.6084442139],"type":"Point"}
}