{
  "type": "Feature",
  "properties": {
    "addr:full":"Calle de Caracolas, 58 Priego Cordoba C\u00f3rdoba 14800",
    "addr:housenumber":"58",
    "addr:postcode":"14800",
    "addr:street":"Calle De Caracolas;Cordoba Co\u0301Rdoba",
    "iso:country":"ES",
    "sg:address":"Calle de Caracolas, 58",
    "sg:city":"Priego Cordoba",
    "sg:orig_category":"Comunidades Religiosas",
    "sg:phone":"+34 957 70 00 08",
    "sg:postcode":"14800",
    "sg:province":"C\u00f3rdoba",
    "wof:name":"Sociedad Del Sagrado Corazon De Jesus Provincia Centro Sur Curia Provincial",
    "wof:placetype":"venue"
},
  "geometry": {"coordinates":[-4.1994519234,37.4331741333],"type":"Point"}
}