{
  "type": "Feature",
  "properties": {
    "iso:country":"ES",
    "sg:address":"Ctra Santa Maria De Nieva-olmedo, Km. 0001,0",
    "sg:city":"Nava Asuncion",
    "sg:orig_category":"Mec\u00c1nico Del Autom\u00d3vil",
    "sg:phone":"+34 921 58 00 38",
    "sg:postcode":"40450",
    "sg:province":"Segovia",
    "wof:name":"Juan Jose Garcia Martin S.l.",
    "wof:placetype":"venue"
},
  "geometry": {"coordinates":[-4.4882631302,41.1547355652],"type":"Point"}
}