{
  "type": "Feature",
  "properties": {
    "addr:full":"Calle de Doctor J.j. Domine, 6 Valencia Valencia 46011",
    "addr:housenumber":"6",
    "addr:postcode":"46011",
    "addr:street":"Calle De Doctor J.J. Domine",
    "iso:country":"ES",
    "sg:address":"Calle de Doctor J.j. Domine, 6",
    "sg:city":"Valencia",
    "sg:orig_category":"M\u00c9dicos: Estomatolog\u00cda",
    "sg:phone":"+34 963 67 53 51",
    "sg:postcode":"46011",
    "sg:province":"Valencia",
    "wof:name":"Plaza Costa Andres",
    "wof:placetype":"venue"
},
  "geometry": {"coordinates":[-0.3326615989,39.4609489441],"type":"Point"}
}