{
  "type": "Feature",
  "properties": {
    "addr:full":"Pl Sol, 15 Barcelona Barcelona 08012",
    "addr:housenumber":"15",
    "addr:postcode":"08012",
    "addr:street":"Pl Sol",
    "iso:country":"ES",
    "sg:address":"Pl Sol, 15",
    "sg:city":"Barcelona",
    "sg:orig_category":"Alimentaci\u00d3n General (al Por Menor)",
    "sg:phone":"+34 932 17 41 26",
    "sg:postcode":"08012",
    "sg:province":"Barcelona",
    "wof:name":"Novell Ricart Ricardo",
    "wof:placetype":"venue"
},
  "geometry": {"coordinates":[2.1565160751,41.4013710022],"type":"Point"}
}