{
  "type": "Feature",
  "properties": {
    "addr:full":"Calle de Teniente Alfonso Martinez, 4 Oviedo Asturias 33011",
    "addr:housenumber":"4",
    "addr:postcode":"33011",
    "addr:street":"Calle De Teniente Alfonso Martinez",
    "iso:country":"ES",
    "sg:address":"Calle de Teniente Alfonso Martinez, 4",
    "sg:city":"Oviedo",
    "sg:orig_category":"Seguridad Social",
    "sg:phone":"+34 985 11 87 45",
    "sg:postcode":"33011",
    "sg:province":"Asturias",
    "wof:name":"Mutua Universal Mugenat Matepss N 10",
    "wof:placetype":"venue"
},
  "geometry": {"coordinates":[-5.8382501602,43.3692626953],"type":"Point"}
}