{
  "type": "Feature",
  "properties": {
    "addr:full":"Pol Ind Quiebracostillas Dos, 10 Baena C\u00f3rdoba 14850",
    "addr:postcode":"14850",
    "addr:street":"Co\u0301Rdoba",
    "iso:country":"ES",
    "sg:address":"Pol Ind Quiebracostillas Dos, 10",
    "sg:city":"Baena",
    "sg:orig_category":"Empresas De Carpinter\u00cda Met\u00c1lica",
    "sg:phone":"+34 957 67 00 35",
    "sg:postcode":"14850",
    "sg:province":"C\u00f3rdoba",
    "wof:name":"Arcos De Las Morenas Francisco Javier",
    "wof:placetype":"venue"
},
  "geometry": {"coordinates":[-4.2948884964,37.6670646667],"type":"Point"}
}