{
  "type": "Feature",
  "properties": {
    "addr:full":"Pol Ind Rubiales, 97 Linares Ja\u00e9n 23700",
    "addr:housenumber":"97",
    "addr:postcode":"23700",
    "addr:street":"Jae\u0301N",
    "iso:country":"ES",
    "sg:address":"Pol Ind Rubiales, 97",
    "sg:city":"Linares",
    "sg:orig_category":"Muebles Y Accesorios Para Cocinas Y Cuartos De Ba\u00d1o (al Por Menor)",
    "sg:phone":"+34 953 69 13 71",
    "sg:postcode":"23700",
    "sg:province":"Ja\u00e9n",
    "wof:name":"Montanet Bruque Emilio",
    "wof:placetype":"venue"
},
  "geometry": {"coordinates":[-3.6356039047,38.093914032],"type":"Point"}
}