{
  "type": "Feature",
  "properties": {
    "iso:country":"ES",
    "sg:address":"Carrer de Doctor Ventallo, 7",
    "sg:city":"Terrassa",
    "sg:orig_category":"Agencias Y Agentes Comerciales, Representantes",
    "sg:phone":"+34 937 33 68 34",
    "sg:postcode":"08221",
    "sg:province":"Barcelona",
    "wof:name":"Caprire S.l",
    "wof:placetype":"venue"
},
  "geometry": {"coordinates":[2.0119459629,41.5581970215],"type":"Point"}
}