{
  "type": "Feature",
  "properties": {
    "iso:country":"ES",
    "sg:address":"Afores, S/n",
    "sg:city":"Vilallobent",
    "sg:orig_category":"Aguas (distribuci\u00d3n, Servicios)",
    "sg:phone":"+34 972 19 70 03",
    "sg:postcode":"17529",
    "sg:province":"Girona",
    "wof:name":"Ute S Y D Aguas Xxii",
    "wof:placetype":"venue"
},
  "geometry": {"coordinates":[1.9475530386,42.4185180664],"type":"Point"}
}