{
  "type": "Feature",
  "properties": {
    "iso:country":"ES",
    "sg:address":"Calle de Canarias, 7",
    "sg:city":"Madrid",
    "sg:orig_category":"Asociaciones Humanitarias, De Cooperaci\u00d3n, De Acci\u00d3n Social",
    "sg:phone":"+34 915 06 17 40",
    "sg:postcode":"28045",
    "sg:province":"Madrid",
    "wof:name":"Coordinadora De Minusvalidos Fisicos De La Comunidad De Madrid",
    "wof:placetype":"venue"
},
  "geometry": {"coordinates":[-3.6972448826,40.4020957947],"type":"Point"}
}