{
  "type": "Feature",
  "properties": {
    "addr:full":"Calle de Garcia De Hita, 2 Arrecife Las Palmas 35500",
    "addr:housenumber":"2",
    "addr:postcode":"35500",
    "addr:street":"Calle De Garcia De Hita",
    "iso:country":"ES",
    "sg:address":"Calle de Garcia De Hita, 2",
    "sg:city":"Arrecife",
    "sg:orig_category":"Ropa Para Se\u00d1oras Y Caballeros (al Por Menor)",
    "sg:phone":"+34 928 81 58 46",
    "sg:postcode":"35500",
    "sg:province":"Las Palmas",
    "wof:name":"Almacenes Ferrer S.a.",
    "wof:placetype":"venue"
},
  "geometry": {"coordinates":[-13.5481214523,28.9593429565],"type":"Point"}
}