{
  "type": "Feature",
  "properties": {
    "iso:country":"ES",
    "sg:address":"Calle de Parlamento Navarro, 6",
    "sg:city":"Ribaforada",
    "sg:orig_category":"Producci\u00d3n, Venta De Productos De Agricultura Biol\u00d3gica",
    "sg:phone":"+34 948 86 44 10",
    "sg:postcode":"31550",
    "sg:province":"Navarra",
    "wof:name":"Zardoya Sanz De Ayala Abelardo",
    "wof:placetype":"venue"
},
  "geometry": {"coordinates":[-1.5119193792,41.9971809387],"type":"Point"}
}