{
  "type": "Feature",
  "properties": {
    "addr:full":"Carrer de Unio (de La), 14 Tarragona Tarragona 43001",
    "addr:housenumber":"14",
    "addr:postcode":"43001",
    "addr:street":"Carrer De Unio De La",
    "iso:country":"ES",
    "sg:address":"Carrer de Unio (de La), 14",
    "sg:city":"Tarragona",
    "sg:orig_category":"Muebles, Minoristas",
    "sg:phone":"+34 977 22 51 00",
    "sg:postcode":"43001",
    "sg:province":"Tarragona",
    "sg:website":"www.ka-international.com",
    "wof:name":"Fernandez Delmas Yolanda",
    "wof:placetype":"venue"
},
  "geometry": {"coordinates":[1.2521500587,41.1149101257],"type":"Point"}
}