{
  "type": "Feature",
  "properties": {
    "iso:country":"ES",
    "sg:address":"Calle de Pandora, 3",
    "sg:city":"Madrid",
    "sg:orig_category":"Inform\u00c1tica: Mantenimiento Y Reparaci\u00d3n De Ordenadores",
    "sg:phone":"+34 913 20 80 08",
    "sg:postcode":"28037",
    "sg:province":"Madrid",
    "wof:name":"Lineservi S.l.",
    "wof:placetype":"venue"
},
  "geometry": {"coordinates":[-3.6165349483,40.4414825439],"type":"Point"}
}