{
  "type": "Feature",
  "properties": {
    "iso:country":"ES",
    "sg:address":"Calle de Progreso, 18",
    "sg:city":"Sevilla",
    "sg:orig_category":"M\u00c9dicos: Cirug\u00cda General",
    "sg:phone":"+34 954 62 78 74",
    "sg:postcode":"41013",
    "sg:province":"Sevilla",
    "wof:name":"Machuca Casanova Jose Maria",
    "wof:placetype":"venue"
},
  "geometry": {"coordinates":[-5.9847021103,37.3723258972],"type":"Point"}
}