{
  "type": "Feature",
  "properties": {
    "addr:full":"Carrer de Riera, 5 Pineda Mar Barcelona 08397",
    "addr:housenumber":"5",
    "addr:postcode":"08397",
    "addr:street":"Carrer De Riera;Barcelona",
    "iso:country":"ES",
    "sg:address":"Carrer de Riera, 5",
    "sg:city":"Pineda Mar",
    "sg:orig_category":"Puertas Y Portales",
    "sg:phone":"+34 937 62 92 03",
    "sg:postcode":"08397",
    "sg:province":"Barcelona",
    "wof:name":"Mecanofusta S.l.",
    "wof:placetype":"venue"
},
  "geometry": {"coordinates":[2.6878800392,41.6280593872],"type":"Point"}
}