{
  "type": "Feature",
  "properties": {
    "addr:full":"Calle de Cerezos (los), S/n Santa Fe Granada 18320",
    "addr:postcode":"18320",
    "addr:street":"Calle De Cerezos Los S / N",
    "iso:country":"ES",
    "sg:address":"Calle de Cerezos (los), S/n",
    "sg:city":"Santa Fe",
    "sg:orig_category":"Cerrajer\u00cda, Ferrallista",
    "sg:phone":"+34 958 44 12 23",
    "sg:postcode":"18320",
    "sg:province":"Granada",
    "wof:name":"Rodriguez Montes Jose Antonio",
    "wof:placetype":"venue"
},
  "geometry": {"coordinates":[-3.7200245857,37.1858024597],"type":"Point"}
}