{
  "type": "Feature",
  "properties": {
    "addr:full":"Plaz San Agustin, S/n Sevilla Sevilla 41003",
    "addr:housenumber":"/ n",
    "addr:postcode":"41003",
    "addr:street":"Plaz San Agustin S",
    "iso:country":"ES",
    "sg:address":"Plaz San Agustin, S/n",
    "sg:city":"Sevilla",
    "sg:orig_category":"Librer\u00cdas",
    "sg:phone":"+34 954 53 30 79",
    "sg:postcode":"41003",
    "sg:province":"Sevilla",
    "wof:name":"Melero Floristas S.l.",
    "wof:placetype":"venue"
},
  "geometry": {"coordinates":[-5.9845142365,37.3894386292],"type":"Point"}
}