{
  "type": "Feature",
  "properties": {
    "iso:country":"ES",
    "sg:address":"Calle de Santa Maria Magdalena, 10",
    "sg:city":"Madrid",
    "sg:orig_category":"Electricidad (montaje, Ensamblaje De Componentes)",
    "sg:phone":"+34 913 45 73 58",
    "sg:postcode":"28016",
    "sg:province":"Madrid",
    "wof:name":"Sethome Construccion Y Promocion S.a.",
    "wof:placetype":"venue"
},
  "geometry": {"coordinates":[-3.6701459885,40.4616088867],"type":"Point"}
}