{
  "type": "Feature",
  "properties": {
    "iso:country":"ES",
    "sg:address":"Carrer de Arago, 558",
    "sg:city":"Barcelona",
    "sg:orig_category":"Comerciantes Al Por Mayor De Vinos, Licores Y Alcoholes",
    "sg:phone":"+34 932 45 11 99",
    "sg:postcode":"08026",
    "sg:province":"Barcelona",
    "wof:name":"Castillo Beltran Manuel",
    "wof:placetype":"venue"
},
  "geometry": {"coordinates":[2.1847169399,41.4069404602],"type":"Point"}
}