{
  "type": "Feature",
  "properties": {
    "iso:country":"ES",
    "sg:address":"Calle de O\u00d1a, 131",
    "sg:city":"Madrid",
    "sg:orig_category":"Mercer\u00cda, Lencer\u00cda (al Por Menor)",
    "sg:phone":"+34 913 83 33 96",
    "sg:postcode":"28050",
    "sg:province":"Madrid",
    "wof:name":"Casta\u00f1o Cerezo Gines",
    "wof:placetype":"venue"
},
  "geometry": {"coordinates":[-3.6626620293,40.4894714355],"type":"Point"}
}