{
  "type": "Feature",
  "properties": {
    "iso:country":"ES",
    "sg:address":"Carrer de Amsterdam, 39",
    "sg:city":"Mas Oliva",
    "sg:orig_category":"Ropa Para Se\u00d1oras (al Por Menor)",
    "sg:phone":"+34 972 15 35 90",
    "sg:postcode":"17480",
    "sg:province":"Girona",
    "wof:name":"Castan  Jean Louis",
    "wof:placetype":"venue"
},
  "geometry": {"coordinates":[3.1663351059,42.2661399841],"type":"Point"}
}