{
  "type": "Feature",
  "properties": {
    "addr:full":"Calle de Doctor Valencia, 34 Barbate C\u00e1diz 11160",
    "addr:housenumber":"34",
    "addr:postcode":"11160",
    "addr:street":"Calle De Doctor Valencia",
    "iso:country":"ES",
    "sg:address":"Calle de Doctor Valencia, 34",
    "sg:city":"Barbate",
    "sg:orig_category":"Arquitectos",
    "sg:phone":"+34 956 43 21 80",
    "sg:postcode":"11160",
    "sg:province":"C\u00e1diz",
    "wof:name":"Daza Lobaton Jose Manuel",
    "wof:placetype":"venue"
},
  "geometry": {"coordinates":[-5.9209032059,36.1945648193],"type":"Point"}
}