{
  "type": "Feature",
  "properties": {
    "addr:full":"O Balado(cesullas), S/n Balado La Coru\u00f1a 15115",
    "addr:postcode":"15115",
    "addr:street":"Cesullas S / N Balado La Corun\u0303A",
    "iso:country":"ES",
    "sg:address":"O Balado(cesullas), S/n",
    "sg:city":"Balado",
    "sg:orig_category":"Comercio De Piezas De Recambio Y De Accesorios De Veh\u00cdculos, Veh\u00cdculos Industriales",
    "sg:phone":"+34 981 71 52 71",
    "sg:postcode":"15115",
    "sg:province":"La Coru\u00f1a",
    "wof:name":"Grille Santos Maria Celia",
    "wof:placetype":"venue"
},
  "geometry": {"coordinates":[-8.9220285416,43.222820282],"type":"Point"}
}