{
  "type": "Feature",
  "properties": {
    "addr:full":"C/ Ciutat De Lliria, 87 Paterna Valencia 46988",
    "addr:housenumber":"87",
    "addr:postcode":"46988",
    "addr:street":"C / Ciutat De Lliria",
    "iso:country":"ES",
    "sg:address":"C/ Ciutat De Lliria, 87",
    "sg:city":"Paterna",
    "sg:orig_category":"Molduras, Junquillos, Listones Y Molduras Perforadas",
    "sg:phone":"+34 961 34 09 07",
    "sg:postcode":"46988",
    "sg:province":"Valencia",
    "wof:name":"Thu Perfil S.l.",
    "wof:placetype":"venue"
},
  "geometry": {"coordinates":[-0.4649190009,39.5228118896],"type":"Point"}
}