{
  "type": "Feature",
  "properties": {
    "addr:full":"C/Rafael Alberti 13 A Coru\u00f1a 15008",
    "addr:housenumber":"13 a",
    "addr:postcode":"15008",
    "addr:street":"C / Rafael Alberti;Corun\u0303A",
    "iso:country":"ES",
    "sg:address":"C/Rafael Alberti 13",
    "sg:city":"A Coru\u00f1a",
    "sg:classifiers":[
        {
            "category":"Professional",
            "subcategory":"Computer Services",
            "type":"Services"
        }
    ],
    "sg:postcode":"15008",
    "sg:tags":[
        "control",
        "zigbee",
        "home",
        "domotics",
        "automation",
        "wireless",
        "franchise",
        "gsm",
        "sms",
        "lte"
    ],
    "sg:website":"http://www.domodesk.com",
    "wof:name":"DOMODESK",
    "wof:placetype":"venue"
},
  "geometry": {"coordinates":[-8.4069515,43.3484951],"type":"Point"}
}