{
  "type": "Feature",
  "properties": {
    "addr:full":"Pase Mu\u00d1oz Grandes, 27 Madrid Madrid 28025",
    "addr:housenumber":"27",
    "addr:postcode":"madrid;28025",
    "iso:country":"ES",
    "sg:address":"Pase Mu\u00d1oz Grandes, 27",
    "sg:city":"Madrid",
    "sg:orig_category":"Cajas De Ahorro",
    "sg:phone":"+34 914 65 33 20",
    "sg:postcode":"28025",
    "sg:province":"Madrid",
    "wof:name":"Caixa D'estalvis I Pensions De Barcelona",
    "wof:placetype":"venue"
},
  "geometry": {"coordinates":[-3.7417459488,40.386390686],"type":"Point"}
}