{
  "type": "Feature",
  "properties": {
    "iso:country":"ES",
    "sg:address":"Pase Alameda (de La), 20",
    "sg:city":"Alcala Henares",
    "sg:orig_category":"M\u00c9dicos: Estomatolog\u00cda",
    "sg:phone":"+34 918 81 05 59",
    "sg:postcode":"28804",
    "sg:province":"Madrid",
    "wof:name":"Rios Parra Antonio",
    "wof:placetype":"venue"
},
  "geometry": {"coordinates":[-3.3568930626,40.4833068848],"type":"Point"}
}