{
  "type": "Feature",
  "properties": {
    "addr:full":"Avda Paskual Abaroa Etorbidea, 15 Lekeitio Vizcaya 48280",
    "addr:housenumber":"15",
    "addr:postcode":"48280",
    "addr:street":"Avda Paskual Abaroa Etorbidea",
    "iso:country":"ES",
    "sg:address":"Avda Paskual Abaroa Etorbidea, 15",
    "sg:city":"Lekeitio",
    "sg:orig_category":"Molduras, Junquillos, Listones Y Molduras Perforadas",
    "sg:phone":"+34 946 84 06 60",
    "sg:postcode":"48280",
    "sg:province":"Vizcaya",
    "wof:name":"Maria Victoria Larreategi Akarregi",
    "wof:placetype":"venue"
},
  "geometry": {"coordinates":[-2.5050079823,43.3635101318],"type":"Point"}
}