{
  "type": "Feature",
  "properties": {
    "addr:full":"Rond San Francisco, 58 Almazan Soria 42200",
    "addr:housenumber":"58",
    "addr:postcode":"42200",
    "addr:street":"San Francisco",
    "iso:country":"ES",
    "sg:address":"Rond San Francisco, 58",
    "sg:city":"Almazan",
    "sg:orig_category":"Notarios",
    "sg:phone":"+34 975 30 01 17",
    "sg:postcode":"42200",
    "sg:province":"Soria",
    "wof:name":"Garzon Echevarria Susana",
    "wof:placetype":"venue"
},
  "geometry": {"coordinates":[-2.5283589363,41.4859199524],"type":"Point"}
}