{
  "type": "Feature",
  "properties": {
    "iso:country":"ES",
    "sg:address":"Albistur Kalea, 39",
    "sg:city":"Lesaka",
    "sg:orig_category":"Mec\u00c1nico Del Autom\u00d3vil",
    "sg:phone":"+34 948 63 75 54",
    "sg:postcode":"31770",
    "sg:province":"Navarra",
    "wof:name":"Tellechea Zozaya Juan Manuel",
    "wof:placetype":"venue"
},
  "geometry": {"coordinates":[-1.7008589506,43.2474784851],"type":"Point"}
}