{
  "type": "Feature",
  "properties": {
    "iso:country":"ES",
    "sg:address":"Avda Navarra De, 8",
    "sg:city":"Donostia-san Sebastian",
    "sg:orig_category":"Librer\u00cdas",
    "sg:phone":"+34 943 27 25 63",
    "sg:postcode":"20013",
    "sg:province":"Guip\u00f9zcoa",
    "wof:name":"Sasiain Alberdi Maria Teresa",
    "wof:placetype":"venue"
},
  "geometry": {"coordinates":[-1.9709099531,43.3257369995],"type":"Point"}
}