{
  "type": "Feature",
  "properties": {
    "addr:full":"Calle de Tormes, 9 Sevilla Sevilla 41008",
    "addr:housenumber":"9",
    "addr:postcode":"41008",
    "addr:street":"Calle De Tormes",
    "iso:country":"ES",
    "sg:address":"Calle de Tormes, 9",
    "sg:city":"Sevilla",
    "sg:orig_category":"Mec\u00c1nico Del Autom\u00d3vil",
    "sg:phone":"+34 954 36 02 01",
    "sg:postcode":"41008",
    "sg:province":"Sevilla",
    "wof:name":"Talleres Rafael Castro S.l.",
    "wof:placetype":"venue"
},
  "geometry": {"coordinates":[-5.9705262184,37.4039230347],"type":"Point"}
}