{
  "type": "Feature",
  "properties": {
    "addr:full":"Cami Santero (del), 9 San Vicente Del Raspeig-sant Vicent Del Raspeig Alicante 03690",
    "addr:postcode":"03690",
    "iso:country":"ES",
    "sg:address":"Cami Santero (del), 9",
    "sg:city":"San Vicente Del Raspeig-sant Vicent Del Raspeig",
    "sg:orig_category":"Torrefactado De Caf\u00c9",
    "sg:phone":"+34 965 66 54 99",
    "sg:postcode":"03690",
    "sg:province":"Alicante",
    "wof:name":"Sara Lee Southern Europe S.l.",
    "wof:placetype":"venue"
},
  "geometry": {"coordinates":[-0.4989260137,38.3921546936],"type":"Point"}
}