{
  "type": "Feature",
  "properties": {
    "addr:full":"Urb Ciudad Residencial Universitaria, S/n Alcala Henares Madrid 28805",
    "addr:housenumber":"s / n",
    "addr:postcode":"28805",
    "addr:street":"Urb Ciudad Residencial Universitaria",
    "iso:country":"ES",
    "sg:address":"Urb Ciudad Residencial Universitaria, S/n",
    "sg:city":"Alcala Henares",
    "sg:classifiers":[
        {
            "category":"Autos & Motor Vehicles",
            "subcategory":"Automobile Sales",
            "type":"Retail Goods"
        }
    ],
    "sg:phone":"+34 918 81 97 51",
    "sg:postcode":"28805",
    "sg:province":"Madrid",
    "sg:website":"www.autoescuelalopez.com",
    "wof:name":"Arjona Romero Antonio",
    "wof:placetype":"venue"
},
  "geometry": {"coordinates":[-3.7003455162,40.4166908264],"type":"Point"}
}