{
  "type": "Feature",
  "properties": {
    "addr:full":"Pase Ruise\u00d1ores, 9 Zaragoza Zaragoza 50006",
    "addr:housenumber":"9",
    "addr:postcode":"50006",
    "addr:street":"Ruisen\u0303Ores",
    "iso:country":"ES",
    "sg:address":"Pase Ruise\u00d1ores, 9",
    "sg:city":"Zaragoza",
    "sg:orig_category":"Arquitectos",
    "sg:phone":"+34 976 38 55 80",
    "sg:postcode":"50006",
    "sg:province":"Zaragoza",
    "wof:name":"Trama Arquitectura Y Urbanismo S.l.",
    "wof:placetype":"venue"
},
  "geometry": {"coordinates":[-0.8871150017,41.6377487183],"type":"Point"}
}