{
  "type": "Feature",
  "properties": {
    "iso:country":"ES",
    "sg:address":"Calle de San Felix, 2",
    "sg:city":"Castellon",
    "sg:orig_category":"Arquitectos",
    "sg:phone":"+34 964 22 31 14",
    "sg:postcode":"12004",
    "sg:province":"Castell\u00f3n",
    "wof:name":"Irureta - Janin C.b.",
    "wof:placetype":"venue"
},
  "geometry": {"coordinates":[-0.0368390009,39.989440918],"type":"Point"}
}