{
  "type": "Feature",
  "properties": {
    "iso:country":"ES",
    "sg:address":"Calle de Galileo, 90",
    "sg:city":"Madrid",
    "sg:orig_category":"Agencias Y Agentes Comerciales, Representantes",
    "sg:phone":"+34 915 34 88 99",
    "sg:postcode":"28015",
    "sg:province":"Madrid",
    "wof:name":"Comercial Artybay S. A.",
    "wof:placetype":"venue"
},
  "geometry": {"coordinates":[-3.7098250389,40.437877655],"type":"Point"}
}