{
  "type": "Feature",
  "properties": {
    "iso:country":"ES",
    "sg:address":"Nafarroa Kalea, 11",
    "sg:city":"Zarautz",
    "sg:orig_category":"Hormigonados",
    "sg:phone":"+34 943 83 41 15",
    "sg:postcode":"20800",
    "sg:province":"Guip\u00f9zcoa",
    "wof:name":"Azkune Olaizola Miguel Maria",
    "wof:placetype":"venue"
},
  "geometry": {"coordinates":[-2.171806097,43.2863960266],"type":"Point"}
}