{
  "type": "Feature",
  "properties": {
    "iso:country":"ES",
    "sg:address":"Calle de Capitan Dema, 7",
    "sg:city":"Alacant",
    "sg:orig_category":"Distribuci\u00d3n De Petr\u00d3leo Y Derivados",
    "sg:phone":"+34 965 10 51 34",
    "sg:postcode":"03007",
    "sg:province":"Alicante",
    "wof:name":"Maype Bahia S.l.",
    "wof:placetype":"venue"
},
  "geometry": {"coordinates":[-0.5004765987,38.3423233032],"type":"Point"}
}