{
  "type": "Feature",
  "properties": {
    "addr:full":"Pla\u00c7 Doctor Robert, 10 Camprodon Girona 17867",
    "addr:housenumber":"10",
    "addr:postcode":"17867",
    "addr:street":"Doctor Robert",
    "iso:country":"ES",
    "sg:address":"Pla\u00c7 Doctor Robert, 10",
    "sg:city":"Camprodon",
    "sg:orig_category":"Electrodom\u00c9sticos (al Por Menor)",
    "sg:phone":"+34 972 74 02 67",
    "sg:postcode":"17867",
    "sg:province":"Girona",
    "wof:name":"Collboni Pastoret Francesc Xabier",
    "wof:placetype":"venue"
},
  "geometry": {"coordinates":[2.364495039,42.3140678406],"type":"Point"}
}