{
  "type": "Feature",
  "properties": {
    "addr:full":"Calle de Chorro, 14 Molina Guadalajara 19300",
    "addr:housenumber":"14",
    "addr:postcode":"19300",
    "addr:street":"Calle De Chorro",
    "iso:country":"ES",
    "sg:address":"Calle de Chorro, 14",
    "sg:city":"Molina",
    "sg:orig_category":"\u00d3ptica: Instrumentos (fabricaci\u00d3n)",
    "sg:phone":"+34 949 83 25 89",
    "sg:postcode":"19300",
    "sg:province":"Guadalajara",
    "wof:name":"Martinez Bruna Beatriz",
    "wof:placetype":"venue"
},
  "geometry": {"coordinates":[-1.8863317966,40.839012146],"type":"Point"}
}