{
  "type": "Feature",
  "properties": {
    "iso:country":"ES",
    "sg:address":"Calle de Francisco Grande Covian (de), S/n",
    "sg:city":"Boadilla Del Monte",
    "sg:orig_category":"Mataderos Y Talleres De Despiezado",
    "sg:phone":"+34 916 32 90 84",
    "sg:postcode":"28660",
    "sg:province":"Madrid",
    "sg:website":"www.biocarnes.es",
    "wof:name":"Diocarnes S.l.",
    "wof:placetype":"venue"
},
  "geometry": {"coordinates":[-3.8948509693,40.4130210876],"type":"Point"}
}