{
  "type": "Feature",
  "properties": {
    "iso:country":"ES",
    "sg:address":"Avda Isabel Ii De, 6",
    "sg:city":"Donostia-san Sebastian",
    "sg:orig_category":"Psic\u00d3logos",
    "sg:phone":"+34 943 45 23 28",
    "sg:postcode":"20011",
    "sg:province":"Guip\u00f9zcoa",
    "wof:name":"Mendoza Navajas Maria",
    "wof:placetype":"venue"
},
  "geometry": {"coordinates":[-1.9760500193,43.3047103882],"type":"Point"}
}