{
  "type": "Feature",
  "properties": {
    "addr:full":"Avda Tejeda (de), 47 San Fernando Las Palmas 35100",
    "addr:housenumber":"47",
    "addr:postcode":"35100",
    "addr:street":"Avda Tejeda De",
    "iso:country":"ES",
    "sg:address":"Avda Tejeda (de), 47",
    "sg:city":"San Fernando",
    "sg:orig_category":"Confecci\u00d3n De Ropa Para Caballeros",
    "sg:phone":"+34 928 76 58 20",
    "sg:postcode":"35100",
    "sg:province":"Las Palmas",
    "wof:name":"Celestaing 85 S.l.",
    "wof:placetype":"venue"
},
  "geometry": {"coordinates":[-15.5842504501,28.0904903412],"type":"Point"}
}