{
  "type": "Feature",
  "properties": {
    "addr:full":"Calle de Union La, 19 Langreo Asturias 33930",
    "addr:housenumber":"19",
    "addr:postcode":"33930",
    "addr:street":"Calle De Union La",
    "iso:country":"ES",
    "sg:address":"Calle de Union La, 19",
    "sg:city":"Langreo",
    "sg:orig_category":"Inform\u00c1tica, Ofim\u00c1tica (estudios, Asesor\u00cda, Ingenier\u00cda, Formaci\u00d3n)",
    "sg:phone":"+34 985 67 44 74",
    "sg:postcode":"33930",
    "sg:province":"Asturias",
    "wof:name":"Asturbildung S.l.",
    "wof:placetype":"venue"
},
  "geometry": {"coordinates":[-5.686193943,43.3005332947],"type":"Point"}
}