{
  "type": "Feature",
  "properties": {
    "addr:full":"Calle de San Isidro, 2 Tejeda Tietar C\u00e1ceres 10420",
    "addr:housenumber":"2",
    "addr:postcode":"10420",
    "addr:street":"Calle De San Isidro;Ca\u0301Ceres",
    "iso:country":"ES",
    "sg:address":"Calle de San Isidro, 2",
    "sg:city":"Tejeda Tietar",
    "sg:orig_category":"Cerrajer\u00cda, Ferrallista",
    "sg:phone":"+34 927 46 92 86",
    "sg:postcode":"10420",
    "sg:province":"C\u00e1ceres",
    "wof:name":"Terron Paniagua Jose",
    "wof:placetype":"venue"
},
  "geometry": {"coordinates":[-5.8697929382,40.0175094604],"type":"Point"}
}