{
  "type": "Feature",
  "properties": {
    "addr:full":"Carrer de Baro S M Sepulcre, 7 Palma Islas Baleares 07012",
    "addr:housenumber":"7",
    "addr:postcode":"07012",
    "addr:street":"Carrer De Baro S;Sepulcre",
    "iso:country":"ES",
    "sg:address":"Carrer de Baro S M Sepulcre, 7",
    "sg:city":"Palma",
    "sg:orig_category":"Abogados",
    "sg:phone":"+34 971 71 22 48",
    "sg:postcode":"07012",
    "sg:province":"Islas Baleares",
    "wof:name":"Estrades Morell Juan",
    "wof:placetype":"venue"
},
  "geometry": {"coordinates":[2.6440589428,39.5731544495],"type":"Point"}
}