{
  "type": "Feature",
  "properties": {
    "iso:country":"ES",
    "sg:address":"Camino Campi\u00f1uelas, S/n",
    "sg:city":"Cordoba",
    "sg:orig_category":"Empresas De Carpinter\u00cda Met\u00c1lica",
    "sg:phone":"+34 957 43 61 26",
    "sg:postcode":"14014",
    "sg:province":"C\u00f3rdoba",
    "wof:name":"Silex M.i. S.l.",
    "wof:placetype":"venue"
},
  "geometry": {"coordinates":[-4.7448968887,37.9052085876],"type":"Point"}
}