{
  "type": "Feature",
  "properties": {
    "iso:country":"ES",
    "sg:address":"Carrer de Doctor Zamenhof, 12",
    "sg:city":"Barcelona",
    "sg:orig_category":"M\u00c1quinas De Coser Y De Hacer Punto (al Por Mayor)",
    "sg:phone":"+34 933 08 04 45",
    "sg:postcode":"08020",
    "sg:province":"Barcelona",
    "wof:name":"Martinez Cervera Pedro",
    "wof:placetype":"venue"
},
  "geometry": {"coordinates":[2.1955471039,41.4167098999],"type":"Point"}
}