{
  "type": "Feature",
  "properties": {
    "iso:country":"ES",
    "sg:address":"Avda Principal, 62",
    "sg:city":"Navas Del Marques",
    "sg:orig_category":"Inmobiliaria (alquileres Por Temporada Y Temporales)",
    "sg:phone":"+34 918 97 21 62",
    "sg:postcode":"05230",
    "sg:province":"\u00c1vila",
    "sg:website":"www.iln.esp.st",
    "wof:name":"Altea Funes Antonio",
    "wof:placetype":"venue"
},
  "geometry": {"coordinates":[-4.3337769508,40.6027336121],"type":"Point"}
}