{
  "type": "Feature",
  "properties": {
    "iso:country":"ES",
    "sg:address":"Calle de General Vives, 54",
    "sg:city":"Palmas De Gran Canaria",
    "sg:orig_category":"Inmobiliaria (agencias)",
    "sg:phone":"+34 928 26 00 25",
    "sg:postcode":"35007",
    "sg:province":"Las Palmas",
    "wof:name":"Tierra Inversiones Inmobiliaria S.l.",
    "wof:placetype":"venue"
},
  "geometry": {"coordinates":[-15.4315185547,28.1390781403],"type":"Point"}
}