{
  "type": "Feature",
  "properties": {
    "iso:country":"ES",
    "sg:address":"Calle de Treinta De Mayo, 50",
    "sg:city":"San Pedro De Bre\u00e7a Alta",
    "sg:orig_category":"Asociaciones Y Clubs Deportivos",
    "sg:phone":"+34 922 43 71 73",
    "sg:postcode":"38712",
    "sg:province":"Santa Cruz De Tenerife",
    "wof:name":"Comercial Fagonza S.l.",
    "wof:placetype":"venue"
},
  "geometry": {"coordinates":[-17.7672138214,28.6476554871],"type":"Point"}
}