{
  "type": "Feature",
  "properties": {
    "addr:full":"Avda Jacinto Benavente, 16 Valencia Valencia 46005",
    "addr:housenumber":"16",
    "addr:postcode":"46005",
    "addr:street":"Avda Jacinto Benavente",
    "iso:country":"ES",
    "sg:address":"Avda Jacinto Benavente, 16",
    "sg:city":"Valencia",
    "sg:orig_category":"Abogados",
    "sg:phone":"+34 963 33 38 43",
    "sg:postcode":"46005",
    "sg:province":"Valencia",
    "wof:name":"Soler Crespo Francisco",
    "wof:placetype":"venue"
},
  "geometry": {"coordinates":[-0.3628619909,39.4661750793],"type":"Point"}
}