{
  "type": "Feature",
  "properties": {
    "addr:full":"Psaj San Blas, S/n Baena C\u00f3rdoba 14850",
    "addr:housenumber":"s / n",
    "addr:postcode":"14850",
    "addr:street":"San Blas",
    "iso:country":"ES",
    "sg:address":"Psaj San Blas, S/n",
    "sg:city":"Baena",
    "sg:orig_category":"Agricultura: Abastecimiento Y Cosechado (negocio)",
    "sg:phone":"+34 957 67 08 91",
    "sg:postcode":"14850",
    "sg:province":"C\u00f3rdoba",
    "wof:name":"Prado Martinez De Anguita Andres De",
    "wof:placetype":"venue"
},
  "geometry": {"coordinates":[-4.3189191818,37.6182556152],"type":"Point"}
}