{
  "type": "Feature",
  "properties": {
    "iso:country":"ES",
    "sg:address":"Carrer de Josep Miret, 37",
    "sg:city":"Barcelona",
    "sg:orig_category":"Peluqueros: De Se\u00d1oras",
    "sg:phone":"+34 933 05 12 78",
    "sg:postcode":"08020",
    "sg:province":"Barcelona",
    "wof:name":"Mendez Perez Humildad",
    "wof:placetype":"venue"
},
  "geometry": {"coordinates":[2.1999750137,41.4233818054],"type":"Point"}
}