{
  "type": "Feature",
  "properties": {
    "addr:full":"Calle de Diario De Cordoba, 5 Cordoba C\u00f3rdoba 14002",
    "addr:housenumber":"5",
    "addr:postcode":"14002",
    "addr:street":"Calle De Diario;Cordoba;Co\u0301Rdoba",
    "iso:country":"ES",
    "sg:address":"Calle de Diario De Cordoba, 5",
    "sg:city":"Cordoba",
    "sg:orig_category":"Inform\u00c1tica, Ofim\u00c1tica (estudios, Asesor\u00cda, Ingenier\u00cda, Formaci\u00d3n)",
    "sg:phone":"+34 957 47 54 52",
    "sg:postcode":"14002",
    "sg:province":"C\u00f3rdoba",
    "sg:website":"www.infordrivers.com",
    "wof:name":"Infor Drivers Siglo Xxi,s.l.",
    "wof:placetype":"venue"
},
  "geometry": {"coordinates":[-4.776227951,37.8842697144],"type":"Point"}
}