{
  "type": "Feature",
  "properties": {
    "addr:full":"Pol Ind Tartessos, S/n Huelva Huelva 21006",
    "addr:housenumber":"s / n",
    "addr:postcode":"21006",
    "iso:country":"ES",
    "sg:address":"Pol Ind Tartessos, S/n",
    "sg:city":"Huelva",
    "sg:orig_category":"Promotores Constructores",
    "sg:phone":"+34 959 35 60 58",
    "sg:postcode":"21006",
    "sg:province":"Huelva",
    "wof:name":"Promovisa Odiel S.l.",
    "wof:placetype":"venue"
},
  "geometry": {"coordinates":[-6.9495940208,37.256313324],"type":"Point"}
}