{
  "type": "Feature",
  "properties": {
    "iso:country":"ES",
    "sg:address":"Calle de Padre Claret, 2",
    "sg:city":"Logro\u00f1o",
    "sg:orig_category":"Herboristas (al Por Menor)",
    "sg:phone":"+34 941 26 27 02",
    "sg:postcode":"26004",
    "sg:province":"La Rioja",
    "wof:name":"Herboristeria Los 5 Elementos S.cv.",
    "wof:placetype":"venue"
},
  "geometry": {"coordinates":[-2.4337100983,42.4639167786],"type":"Point"}
}