{
  "type": "Feature",
  "properties": {
    "addr:full":"Pase Colon De, 14 Donostia-san Sebastian Guip\u00f9zcoa 20002",
    "addr:housenumber":"14",
    "addr:postcode":"20002",
    "iso:country":"ES",
    "sg:address":"Pase Colon De, 14",
    "sg:city":"Donostia-san Sebastian",
    "sg:orig_category":"Peluqueros: De Se\u00d1oras",
    "sg:phone":"+34 943 29 37 78",
    "sg:postcode":"20002",
    "sg:province":"Guip\u00f9zcoa",
    "wof:name":"Lojo Fernandez Maria Del Mar",
    "wof:placetype":"venue"
},
  "geometry": {"coordinates":[-1.9794000387,43.3173789978],"type":"Point"}
}