{
  "type": "Feature",
  "properties": {
    "iso:country":"ES",
    "sg:address":"Calle de Legazpi, 5",
    "sg:city":"Zumarraga",
    "sg:orig_category":"Ense\u00d1anza: Profesiones Art\u00cdsticas",
    "sg:phone":"+34 943 72 11 55",
    "sg:postcode":"20700",
    "sg:province":"Guip\u00f9zcoa",
    "wof:name":"Vierb\u00fccher Fernandez Francisco",
    "wof:placetype":"venue"
},
  "geometry": {"coordinates":[-2.3152680397,43.0896492004],"type":"Point"}
}