{
  "type": "Feature",
  "properties": {
    "addr:full":"Carrer de Maragall, 8 Jardins Imperi Tarragona 43151",
    "addr:housenumber":"8",
    "addr:postcode":"43151",
    "addr:street":"Carrer De Maragall",
    "iso:country":"ES",
    "sg:address":"Carrer de Maragall, 8",
    "sg:city":"Jardins Imperi",
    "sg:orig_category":"T\u00c9cnicos Veterinarios",
    "sg:phone":"+34 977 61 05 59",
    "sg:postcode":"43151",
    "sg:province":"Tarragona",
    "wof:name":"Centre Veterinari Arbor S.l.",
    "wof:placetype":"venue"
},
  "geometry": {"coordinates":[1.2753549814,41.1753921509],"type":"Point"}
}