{
  "type": "Feature",
  "properties": {
    "addr:full":"Plza. Generalisimo, 3 Torres Albanchez Ja\u00e9n 23391",
    "addr:housenumber":"3",
    "addr:postcode":"23391",
    "addr:street":"Plza. Generalisimo",
    "iso:country":"ES",
    "sg:address":"Plza. Generalisimo, 3",
    "sg:city":"Torres Albanchez",
    "sg:orig_category":"Cajas De Ahorro",
    "sg:phone":"+34 953 49 40 04",
    "sg:postcode":"23391",
    "sg:province":"Ja\u00e9n",
    "wof:name":"Unicaja",
    "wof:placetype":"venue"
},
  "geometry": {"coordinates":[-2.6828589439,38.4163322449],"type":"Point"}
}