{
  "type": "Feature",
  "properties": {
    "iso:country":"ES",
    "sg:address":"Pg Maragall, 89",
    "sg:city":"Barcelona",
    "sg:orig_category":"Zapatos (al Por Menor)",
    "sg:phone":"+34 934 35 76 42",
    "sg:postcode":"08041",
    "sg:province":"Barcelona",
    "wof:name":"Manzanares Arroyo Carmen",
    "wof:placetype":"venue"
},
  "geometry": {"coordinates":[2.1804039478,41.4180221558],"type":"Point"}
}