{
  "type": "Feature",
  "properties": {
    "addr:full":"Avda Jose Ortiz, 108 Almazora Castell\u00f3n 12550",
    "addr:housenumber":"108",
    "addr:postcode":"12550",
    "addr:street":"Avda Jose Ortiz",
    "iso:country":"ES",
    "sg:address":"Avda Jose Ortiz, 108",
    "sg:city":"Almazora",
    "sg:orig_category":"Cer\u00c1micas: Material Y Suministros",
    "sg:phone":"+34 964 55 03 20",
    "sg:postcode":"12550",
    "sg:province":"Castell\u00f3n",
    "wof:name":"Tecno Diamant Iberica 2000 S.l.",
    "wof:placetype":"venue"
},
  "geometry": {"coordinates":[-0.0681739971,39.9553756714],"type":"Point"}
}