{
  "type": "Feature",
  "properties": {
    "iso:country":"ES",
    "sg:address":"Calle de Delicias, 5",
    "sg:city":"Logrosan",
    "sg:orig_category":"Plomeros",
    "sg:phone":"+34 927 36 01 31",
    "sg:postcode":"10120",
    "sg:province":"C\u00e1ceres",
    "wof:name":"Alonso Cano Juan",
    "wof:placetype":"venue"
},
  "geometry": {"coordinates":[-5.4927010536,39.3350219727],"type":"Point"}
}