{
  "type": "Feature",
  "properties": {
    "iso:country":"ES",
    "sg:address":"Avda Andalucia, 72",
    "sg:city":"Huetor-vega",
    "sg:orig_category":"Televisi\u00d3n, V\u00cddeo: Aparatos Y Accesorios (venta)",
    "sg:phone":"+34 958 30 31 49",
    "sg:postcode":"18198",
    "sg:province":"Granada",
    "wof:name":"Montijano Casado Guillermo",
    "wof:placetype":"venue"
},
  "geometry": {"coordinates":[-3.5767979622,37.1474609375],"type":"Point"}
}