{
  "type": "Feature",
  "properties": {
    "addr:full":"Ctra General, S/n Cerredo Asturias 33812",
    "addr:postcode":"33812",
    "addr:street":"Ctra General S / N Cerredo Asturias",
    "iso:country":"ES",
    "sg:address":"Ctra General, S/n",
    "sg:city":"Cerredo",
    "sg:orig_category":"Iglesia Cat\u00d3lica",
    "sg:phone":"+34 985 81 82 94",
    "sg:postcode":"33812",
    "sg:province":"Asturias",
    "wof:name":"Diocesis De Oviedo",
    "wof:placetype":"venue"
},
  "geometry": {"coordinates":[-6.5779118538,42.94165802],"type":"Point"}
}