{
  "type": "Feature",
  "properties": {
    "addr:full":"Avenida Del General Jordana, 40 Quintanar Sierra Burgos 09670",
    "addr:housenumber":"40",
    "addr:postcode":"09670",
    "addr:street":"Avenida Del General Jordana",
    "iso:country":"ES",
    "sg:address":"Avenida Del General Jordana, 40",
    "sg:city":"Quintanar Sierra",
    "sg:orig_category":"Serrer\u00cdas De Madera",
    "sg:phone":"+34 947 39 61 99",
    "sg:postcode":"09670",
    "sg:province":"Burgos",
    "wof:name":"Marcos Chicote Julian",
    "wof:placetype":"venue"
},
  "geometry": {"coordinates":[-3.0339701176,41.9844017029],"type":"Point"}
}