{
  "type": "Feature",
  "properties": {
    "iso:country":"ES",
    "sg:address":"Calle de Melrose, 10",
    "sg:city":"Teba",
    "sg:orig_category":"Delegados, Agentes De Tr\u00c1nsito, Auxiliares De Transporte Internacional",
    "sg:phone":"+34 952 74 85 17",
    "sg:postcode":"29327",
    "sg:province":"M\u00e1laga",
    "wof:name":"Guerrero Lopez Josefa",
    "wof:placetype":"venue"
},
  "geometry": {"coordinates":[-4.9169220924,36.9839134216],"type":"Point"}
}