{
  "type": "Feature",
  "properties": {
    "iso:country":"ES",
    "sg:address":"Carrer de Savina, 7",
    "sg:city":"Peguera",
    "sg:orig_category":"Cajas De Ahorro",
    "sg:phone":"+34 971 68 75 12",
    "sg:postcode":"07160",
    "sg:province":"Islas Baleares",
    "sg:website":"www.sanostra.es",
    "wof:name":"Caja De Ahorros Y Monte De Piedad De Las Baleares",
    "wof:placetype":"venue"
},
  "geometry": {"coordinates":[2.4351348877,39.5395202637],"type":"Point"}
}