{
  "type": "Feature",
  "properties": {
    "addr:full":"Calle de Alboraya, 74 Valencia Valencia 46010",
    "addr:housenumber":"74",
    "addr:postcode":"46010",
    "addr:street":"Calle De Alboraya",
    "iso:country":"ES",
    "sg:address":"Calle de Alboraya, 74",
    "sg:city":"Valencia",
    "sg:orig_category":"Electrodom\u00c9sticos (al Por Menor)",
    "sg:phone":"+34 963 62 49 60",
    "sg:postcode":"46010",
    "sg:province":"Valencia",
    "wof:name":"Mecanicas De Valencia S.l.",
    "wof:placetype":"venue"
},
  "geometry": {"coordinates":[-0.3679124117,39.4870872498],"type":"Point"}
}