{
  "type": "Feature",
  "properties": {
    "iso:country":"ES",
    "sg:address":"Calle de Riotinto, 1",
    "sg:city":"Malaga",
    "sg:orig_category":"Empresas De Carpinter\u00cda De Madera",
    "sg:phone":"+34 952 30 00 93",
    "sg:postcode":"29010",
    "sg:province":"M\u00e1laga",
    "wof:name":"Martinez Marquez Manuel",
    "wof:placetype":"venue"
},
  "geometry": {"coordinates":[-4.4513339996,36.7336997986],"type":"Point"}
}