{
  "type": "Feature",
  "properties": {
    "addr:full":"Calle de Presa (de La), 43 San Fernando De Henares Madrid 28830",
    "addr:housenumber":"43",
    "addr:postcode":"28830",
    "addr:street":"Calle De Presa De La",
    "iso:country":"ES",
    "sg:address":"Calle de Presa (de La), 43",
    "sg:city":"San Fernando De Henares",
    "sg:orig_category":"Molduras, Junquillos, Listones Y Molduras Perforadas",
    "sg:phone":"+34 916 73 90 10",
    "sg:postcode":"28830",
    "sg:province":"Madrid",
    "wof:name":"Ogalla Bautista Mariano",
    "wof:placetype":"venue"
},
  "geometry": {"coordinates":[-3.5302910805,40.4278717041],"type":"Point"}
}