{
  "type": "Feature",
  "properties": {
    "iso:country":"ES",
    "sg:address":"Calle de Zubiaurre Pintores, 2",
    "sg:city":"Bilbao",
    "sg:orig_category":"Bisuter\u00cda, Joyer\u00cda, Relojer\u00cda (al Por Menor)",
    "sg:phone":"+34 944 43 61 49",
    "sg:postcode":"48012",
    "sg:province":"Vizcaya",
    "wof:name":"Sergio Caba\u00f1es Lobon",
    "wof:placetype":"venue"
},
  "geometry": {"coordinates":[-2.9447009563,43.2567214966],"type":"Point"}
}