{
  "type": "Feature",
  "properties": {
    "iso:country":"ES",
    "sg:address":"Avda Nuestra Se\u00d1ora Del Carmen, 49",
    "sg:city":"Carlota",
    "sg:orig_category":"Transportes Por V\u00cdas Navegables",
    "sg:phone":"+34 957 30 10 11",
    "sg:postcode":"14100",
    "sg:province":"C\u00f3rdoba",
    "wof:name":"Rosa Gomez Manuel",
    "wof:placetype":"venue"
},
  "geometry": {"coordinates":[-4.9333691597,37.671459198],"type":"Point"}
}