{
  "type": "Feature",
  "properties": {
    "addr:full":"Av Catalunya, 7 Pobla Claramunt Barcelona 08787",
    "addr:housenumber":"7",
    "addr:postcode":"08787",
    "addr:street":"Av Catalunya",
    "iso:country":"ES",
    "sg:address":"Av Catalunya, 7",
    "sg:city":"Pobla Claramunt",
    "sg:orig_category":"Confecci\u00d3n De Paraguas, De Sombrillas Y De Bastones",
    "sg:phone":"+34 938 08 60 55",
    "sg:postcode":"08787",
    "sg:province":"Barcelona",
    "wof:name":"Manufacturas Clima S.a.",
    "wof:placetype":"venue"
},
  "geometry": {"coordinates":[1.675614953,41.5540313721],"type":"Point"}
}