{
  "type": "Feature",
  "properties": {
    "iso:country":"ES",
    "sg:address":"Calle de Larra, 16",
    "sg:city":"Madrid",
    "sg:orig_category":"Laboratorios",
    "sg:phone":"+34 914 48 31 44",
    "sg:postcode":"28004",
    "sg:province":"Madrid",
    "wof:name":"Laboratorios Ruiz Falco S.a.",
    "wof:placetype":"venue"
},
  "geometry": {"coordinates":[-3.7003996372,40.4282989502],"type":"Point"}
}