{
  "type": "Feature",
  "properties": {
    "iso:country":"ES",
    "sg:address":"Ctra. Huesca-gra\u00f1en, S/n",
    "sg:city":"Huesca",
    "sg:orig_category":"Asilos De Ancianos. Centros Privados",
    "sg:phone":"+34 974 23 84 51",
    "sg:postcode":"22196",
    "sg:province":"Huesca",
    "wof:name":"Instituto Aragones De Servicios Sociales",
    "wof:placetype":"venue"
},
  "geometry": {"coordinates":[-0.3825440109,42.074508667],"type":"Point"}
}