{
  "type": "Feature",
  "properties": {
    "addr:full":"Carr Paisos Baixos, 4 Igualada Barcelona 08700",
    "addr:housenumber":"4",
    "addr:postcode":"08700",
    "addr:street":"Carr Paisos Baixos",
    "iso:country":"ES",
    "sg:address":"Carr Paisos Baixos, 4",
    "sg:city":"Igualada",
    "sg:orig_category":"Confecci\u00d3n (fabricaci\u00d3n, Al Por Mayor)",
    "sg:phone":"+34 938 05 26 86",
    "sg:postcode":"08700",
    "sg:province":"Barcelona",
    "wof:name":"Diaz-guerra Blanes Juan",
    "wof:placetype":"venue"
},
  "geometry": {"coordinates":[1.629551053,41.5930023193],"type":"Point"}
}