{
  "type": "Feature",
  "properties": {
    "iso:country":"ES",
    "sg:address":"Rua Pascual Veiga, 21",
    "sg:city":"Ferrol",
    "sg:orig_category":"Institutos De Belleza",
    "sg:phone":"+34 981 35 07 39",
    "sg:postcode":"15403",
    "sg:province":"La Coru\u00f1a",
    "sg:website":"www.cellulemblock.com",
    "wof:name":"Penedo Romeu Jose Luis",
    "wof:placetype":"venue"
},
  "geometry": {"coordinates":[-8.2252759933,43.4839553833],"type":"Point"}
}