{
  "type": "Feature",
  "properties": {
    "addr:full":"Calle de Luque, 6 Lucena C\u00f3rdoba 14900",
    "addr:housenumber":"6",
    "addr:postcode":"14900",
    "addr:street":"Calle De Luque",
    "iso:country":"ES",
    "sg:address":"Calle de Luque, 6",
    "sg:city":"Lucena",
    "sg:orig_category":"Contenedores (mercanc\u00cdas)",
    "sg:phone":"+34 957 51 33 64",
    "sg:postcode":"14900",
    "sg:province":"C\u00f3rdoba",
    "wof:name":"Pino Ortega Salvador",
    "wof:placetype":"venue"
},
  "geometry": {"coordinates":[-4.4965391159,37.4095916748],"type":"Point"}
}