{
  "type": "Feature",
  "properties": {
    "iso:country":"ES",
    "sg:address":"Plaz Cauchiles (de), 4",
    "sg:city":"Granada",
    "sg:orig_category":"Relojer\u00cda (al Por Menor, Reparaci\u00d3n)",
    "sg:phone":"+34 958 26 56 65",
    "sg:postcode":"18001",
    "sg:province":"Granada",
    "wof:name":"Romerosa Guerrero Manuel",
    "wof:placetype":"venue"
},
  "geometry": {"coordinates":[-3.5998840332,37.1740226746],"type":"Point"}
}