{
  "type": "Feature",
  "properties": {
    "addr:full":"Avda Andalucia, S/n Castilleja Campo Sevilla 41810",
    "addr:housenumber":"/ n",
    "addr:postcode":"41810",
    "addr:street":"Avda Andalucia S",
    "iso:country":"ES",
    "sg:address":"Avda Andalucia, S/n",
    "sg:city":"Castilleja Campo",
    "sg:orig_category":"Institutos M\u00c9dicos",
    "sg:phone":"+34 954 75 49 06",
    "sg:postcode":"41810",
    "sg:province":"Sevilla",
    "wof:name":"Servicio Andaluz De Salud",
    "wof:placetype":"venue"
},
  "geometry": {"coordinates":[-6.3374037743,37.3878517151],"type":"Point"}
}