{
  "type": "Feature",
  "properties": {
    "addr:full":"Carrer de Socrates, 104 Barcelona Barcelona 08030",
    "addr:housenumber":"104",
    "addr:postcode":"08030",
    "addr:street":"Carrer De Socrates",
    "iso:country":"ES",
    "sg:address":"Carrer de Socrates, 104",
    "sg:city":"Barcelona",
    "sg:orig_category":"Agencias Y Agentes Comerciales, Representantes",
    "sg:phone":"+34 933 46 57 80",
    "sg:postcode":"08030",
    "sg:province":"Barcelona",
    "wof:name":"Coderch Codinachs Andres",
    "wof:placetype":"venue"
},
  "geometry": {"coordinates":[2.1837489605,41.4320907593],"type":"Point"}
}