{
  "type": "Feature",
  "properties": {
    "addr:full":"Avda Cerro Del Rubal, S/n Parla Madrid 28980",
    "addr:housenumber":"s",
    "addr:postcode":"28980",
    "addr:street":"Avda Cerro Del Rubal;/ N",
    "iso:country":"ES",
    "sg:address":"Avda Cerro Del Rubal, S/n",
    "sg:city":"Parla",
    "sg:orig_category":"Transportes Por Carretera: Lotes Completos, Mercanc\u00cdas Diversas",
    "sg:phone":"+34 914 66 55 23",
    "sg:postcode":"28980",
    "sg:province":"Madrid",
    "wof:name":"M & J Import Export Intercontinental",
    "wof:placetype":"venue"
},
  "geometry": {"coordinates":[-3.7734539509,40.237449646],"type":"Point"}
}