{
  "type": "Feature",
  "properties": {
    "iso:country":"ES",
    "sg:address":"Carrer de Can Blanch, 58",
    "sg:city":"Cabrils",
    "sg:orig_category":"\u00d3pticos Optometristas (al Por Menor)",
    "sg:phone":"+34 937 50 93 11",
    "sg:postcode":"08348",
    "sg:province":"Barcelona",
    "wof:name":"Sunglasses Bussines Factory S.l.",
    "wof:placetype":"venue"
},
  "geometry": {"coordinates":[2.3684079647,41.5219421387],"type":"Point"}
}