{
  "type": "Feature",
  "properties": {
    "addr:full":"Ctra Sevilla, S/n Badajoz Badajoz 06009",
    "addr:housenumber":"s",
    "addr:postcode":"06009",
    "addr:street":"Ctra Sevilla;/ N",
    "iso:country":"ES",
    "sg:address":"Ctra Sevilla, S/n",
    "sg:city":"Badajoz",
    "sg:orig_category":"Mercer\u00cda, Lencer\u00cda (al Por Menor)",
    "sg:phone":"+34 924 25 80 92",
    "sg:postcode":"06009",
    "sg:province":"Badajoz",
    "wof:name":"Soriano Rey Marciala",
    "wof:placetype":"venue"
},
  "geometry": {"coordinates":[-6.9593338966,38.8719367981],"type":"Point"}
}