{
  "type": "Feature",
  "properties": {
    "addr:full":"Rua Melchor De Velasco, 2 Ourense Ourense 32002",
    "addr:housenumber":"2",
    "addr:postcode":"32002",
    "addr:street":"Rua Melchor De Velasco",
    "iso:country":"ES",
    "sg:address":"Rua Melchor De Velasco, 2",
    "sg:city":"Ourense",
    "sg:orig_category":"Bazares, Art\u00cdculos De Limpieza Y De Cocina (al Por Menor)",
    "sg:phone":"+34 988 24 69 00",
    "sg:postcode":"32002",
    "sg:province":"Ourense",
    "wof:name":"Electronica Japon S.l.",
    "wof:placetype":"venue"
},
  "geometry": {"coordinates":[-7.8724770546,42.3399887085],"type":"Point"}
}