{
  "type": "Feature",
  "properties": {
    "iso:country":"ES",
    "sg:address":"Praj Ledua - A, 10",
    "sg:city":"Novelda",
    "sg:orig_category":"M\u00c1rmoles, Granitos Y Piedras Naturales",
    "sg:phone":"+34 965 60 07 32",
    "sg:postcode":"03660",
    "sg:province":"Alicante",
    "wof:name":"Ruiz Marcos Jose",
    "wof:placetype":"venue"
},
  "geometry": {"coordinates":[-0.7718489766,38.389251709],"type":"Point"}
}