{
  "type": "Feature",
  "properties": {
    "addr:full":"Pol Ind Pilas Sur, 77 Pilas Sevilla 41840",
    "addr:postcode":"41840",
    "iso:country":"ES",
    "sg:address":"Pol Ind Pilas Sur, 77",
    "sg:city":"Pilas",
    "sg:orig_category":"Imprenta",
    "sg:phone":"+34 954 75 02 95",
    "sg:postcode":"41840",
    "sg:province":"Sevilla",
    "wof:name":"Imprenta Ca\u00f1itas S.l.",
    "wof:placetype":"venue"
},
  "geometry": {"coordinates":[-6.3043088913,37.3053894043],"type":"Point"}
}