{
  "type": "Feature",
  "properties": {
    "iso:country":"ES",
    "sg:address":"Pg Pere Iii, 89",
    "sg:city":"Manresa",
    "sg:orig_category":"Ingenier\u00cda, Centros De Estudios (diversos)",
    "sg:phone":"+34 938 73 48 24",
    "sg:postcode":"08242",
    "sg:province":"Barcelona",
    "wof:name":"C.g. 4 Engineyeria S.l.",
    "wof:placetype":"venue"
},
  "geometry": {"coordinates":[1.8303450346,41.7300987244],"type":"Point"}
}