{
  "type": "Feature",
  "properties": {
    "iso:country":"ES",
    "sg:address":"Calle de Misericordia, 1",
    "sg:city":"Chozas Canales",
    "sg:orig_category":"Supermercados Y Hipermercados",
    "sg:phone":"+34 918 17 61 08",
    "sg:postcode":"45960",
    "sg:province":"Toledo",
    "wof:name":"Rodriguez Vivar Jacinto",
    "wof:placetype":"venue"
},
  "geometry": {"coordinates":[-4.0433659554,40.0983924866],"type":"Point"}
}