{
  "type": "Feature",
  "properties": {
    "iso:country":"ES",
    "sg:address":"Avda Perez Galdos, 45",
    "sg:city":"Logro\u00f1o",
    "sg:orig_category":"Complementos De Vestir (al Por Menor)",
    "sg:phone":"+34 941 22 62 13",
    "sg:postcode":"26002",
    "sg:province":"La Rioja",
    "sg:website":"www.glosscomplementos.com",
    "wof:name":"Abrego Blanco Tamara",
    "wof:placetype":"venue"
},
  "geometry": {"coordinates":[-2.452762,42.462448],"type":"Point"}
}