{
  "type": "Feature",
  "properties": {
    "iso:country":"ES",
    "sg:address":"Avgd Madrid, 30",
    "sg:city":"Lleida",
    "sg:orig_category":"Abogados",
    "sg:phone":"+34 973 26 78 69",
    "sg:postcode":"25002",
    "sg:province":"Lleida",
    "wof:name":"Domingo Forcada Mario",
    "wof:placetype":"venue"
},
  "geometry": {"coordinates":[0.6240580082,41.6120681763],"type":"Point"}
}