{
  "type": "Feature",
  "properties": {
    "iso:country":"ES",
    "sg:address":"Avda Rodriguez De Ledesma, 2",
    "sg:city":"Caceres",
    "sg:orig_category":"Asesor\u00cda Sobre Comunicaci\u00d3n De Empresas",
    "sg:phone":"+34 927 21 65 43",
    "sg:postcode":"10001",
    "sg:province":"C\u00e1ceres",
    "wof:name":"Benigno Barrero S.l.",
    "wof:placetype":"venue"
},
  "geometry": {"coordinates":[-6.382060051,39.4718551636],"type":"Point"}
}