{
  "type": "Feature",
  "properties": {
    "iso:country":"ES",
    "sg:address":"Calle de Bajondillo Del, 61",
    "sg:city":"Torremolinos",
    "sg:orig_category":"Alquiler De Veh\u00cdculos: Turismos Y Utilitarios",
    "sg:phone":"+34 952 38 09 44",
    "sg:postcode":"29620",
    "sg:province":"M\u00e1laga",
    "wof:name":"Costamar Rent A Car S. A.",
    "wof:placetype":"venue"
},
  "geometry": {"coordinates":[-4.4953670502,36.6266021729],"type":"Point"}
}