{
  "type": "Feature",
  "properties": {
    "addr:full":"Calle de Portada, 108 Estepona M\u00e1laga 29680",
    "addr:housenumber":"108",
    "addr:postcode":"29680",
    "addr:street":"Calle De Portada",
    "iso:country":"ES",
    "sg:address":"Calle de Portada, 108",
    "sg:city":"Estepona",
    "sg:orig_category":"Asociaciones Humanitarias, De Cooperaci\u00d3n, De Acci\u00d3n Social",
    "sg:phone":"+34 952 79 61 90",
    "sg:postcode":"29680",
    "sg:province":"M\u00e1laga",
    "wof:name":"Organizacion Nacional De Ciegos",
    "wof:placetype":"venue"
},
  "geometry": {"coordinates":[-5.1439790726,36.4262619019],"type":"Point"}
}