{
  "type": "Feature",
  "properties": {
    "iso:country":"ES",
    "sg:address":"Carrer de Santa Esperan\u00c7a, 8",
    "sg:city":"Granollers",
    "sg:orig_category":"Marroquiner\u00cda (confecci\u00d3n)",
    "sg:phone":"+34 938 79 20 89",
    "sg:postcode":"08401",
    "sg:province":"Barcelona",
    "wof:name":"Garcia Reus Fernando",
    "wof:placetype":"venue"
},
  "geometry": {"coordinates":[2.287967205,41.6076927185],"type":"Point"}
}