{
  "type": "Feature",
  "properties": {
    "addr:full":"Carrer de Bonavista, 76 S. Just Desvern Barcelona 08960",
    "addr:housenumber":"76",
    "addr:postcode":"08960",
    "addr:street":"Carrer De Bonavista",
    "iso:country":"ES",
    "sg:address":"Carrer de Bonavista, 76",
    "sg:city":"S. Just Desvern",
    "sg:orig_category":"Juegos Y Juguetes (al Por Menor)",
    "sg:phone":"+34 934 73 27 62",
    "sg:postcode":"08960",
    "sg:province":"Barcelona",
    "wof:name":"Lopez Muro Maria Dolores",
    "wof:placetype":"venue"
},
  "geometry": {"coordinates":[2.0772221088,41.3838996887],"type":"Point"}
}