{
  "type": "Feature",
  "properties": {
    "iso:country":"ES",
    "sg:address":"Avda Ogijares, 1",
    "sg:city":"Armilla",
    "sg:orig_category":"Cer\u00c1micas: Material Y Suministros",
    "sg:phone":"+34 958 57 02 97",
    "sg:postcode":"18100",
    "sg:province":"Granada",
    "wof:name":"El Tio Del Puro S.l.",
    "wof:placetype":"venue"
},
  "geometry": {"coordinates":[-3.6246109009,37.1380958557],"type":"Point"}
}