{
  "type": "Feature",
  "properties": {
    "iso:country":"ES",
    "sg:address":"Calle de Escultor Navascues, S/n",
    "sg:city":"Oviedo",
    "sg:orig_category":"Promotores Constructores",
    "sg:phone":"+34 985 11 89 12",
    "sg:postcode":"33011",
    "sg:province":"Asturias",
    "wof:name":"P. Y Construcciones Asturpando Sl",
    "wof:placetype":"venue"
},
  "geometry": {"coordinates":[-5.8440241814,43.3697090149],"type":"Point"}
}