{
  "type": "Feature",
  "properties": {
    "addr:full":"Calle de Juliana Larena, 8 Ejea De Los Caballeros Zaragoza 50600",
    "addr:housenumber":"8",
    "addr:postcode":"50600",
    "addr:street":"Calle De Juliana Larena",
    "iso:country":"ES",
    "sg:address":"Calle de Juliana Larena, 8",
    "sg:city":"Ejea De Los Caballeros",
    "sg:orig_category":"Tapicer\u00cdas",
    "sg:phone":"+34 976 66 38 42",
    "sg:postcode":"50600",
    "sg:province":"Zaragoza",
    "wof:name":"Burguete Navarro Jose Miguel",
    "wof:placetype":"venue"
},
  "geometry": {"coordinates":[-1.1397789717,42.1275787354],"type":"Point"}
}