{
  "type": "Feature",
  "properties": {
    "iso:country":"ES",
    "sg:address":"Calle de Ramon Franco, 4",
    "sg:city":"Arzua",
    "sg:orig_category":"Sociedades, Compa\u00d1\u00cdas Aseguradoras",
    "sg:phone":"+34 981 50 03 29",
    "sg:postcode":"15810",
    "sg:province":"La Coru\u00f1a",
    "wof:name":"Jose Formoso Codesido Y Otros S.c.",
    "wof:placetype":"venue"
},
  "geometry": {"coordinates":[-8.1636552811,42.9269256592],"type":"Point"}
}