{
  "type": "Feature",
  "properties": {
    "iso:country":"ES",
    "sg:address":"Ctra Taiala, S/n",
    "sg:city":"Girona",
    "sg:orig_category":"Empresarios",
    "sg:phone":"+34 972 21 44 71",
    "sg:postcode":"17007",
    "sg:province":"Girona",
    "wof:name":"Cruzado Cruz Luis",
    "wof:placetype":"venue"
},
  "geometry": {"coordinates":[2.806885004,41.9941711426],"type":"Point"}
}