{
  "type": "Feature",
  "properties": {
    "addr:full":"Carr Raval De Sant Roc, 84 Raval Valencia 46680",
    "addr:housenumber":"84",
    "addr:postcode":"46680",
    "addr:street":"Carr Raval De Sant Roc",
    "iso:country":"ES",
    "sg:address":"Carr Raval De Sant Roc, 84",
    "sg:city":"Raval",
    "sg:orig_category":"Molduras, Junquillos, Listones Y Molduras Perforadas",
    "sg:phone":"+34 962 42 44 34",
    "sg:postcode":"46680",
    "sg:province":"Valencia",
    "wof:name":"Eurotel Sur S L",
    "wof:placetype":"venue"
},
  "geometry": {"coordinates":[-0.4383490086,39.1962852478],"type":"Point"}
}