{
  "type": "Feature",
  "properties": {
    "iso:country":"ES",
    "sg:address":"Calle de Valparaiso, 18",
    "sg:city":"Sevilla",
    "sg:orig_category":"Agencias Y Asesores De Publicidad",
    "sg:phone":"+34 954 62 80 22",
    "sg:postcode":"41013",
    "sg:province":"Sevilla",
    "sg:website":"www.promofactor.com",
    "wof:name":"Promofactor S.l.",
    "wof:placetype":"venue"
},
  "geometry": {"coordinates":[-5.9837617874,37.3695297241],"type":"Point"}
}