{
  "type": "Feature",
  "properties": {
    "iso:country":"ES",
    "sg:address":"Avda Amsterdam (de), S/n",
    "sg:city":"Cristianos",
    "sg:orig_category":"Quincaller\u00cda (al Por Menor)",
    "sg:phone":"+34 922 79 48 69",
    "sg:postcode":"38650",
    "sg:province":"Santa Cruz De Tenerife",
    "wof:name":"Ferreteria Dos Hermanos S. L.",
    "wof:placetype":"venue"
},
  "geometry": {"coordinates":[-16.7098693848,28.0526103973],"type":"Point"}
}