{
  "type": "Feature",
  "properties": {
    "addr:full":"Calle de Cura, 6 Mata Toledo 45534",
    "addr:housenumber":"6",
    "addr:postcode":"45534",
    "addr:street":"Calle De Cura",
    "iso:country":"ES",
    "sg:address":"Calle de Cura, 6",
    "sg:city":"Mata",
    "sg:orig_category":"Iglesia Cat\u00d3lica",
    "sg:phone":"+34 925 74 72 08",
    "sg:postcode":"45534",
    "sg:province":"Toledo",
    "wof:name":"Parroquia San Juan Bautista",
    "wof:placetype":"venue"
},
  "geometry": {"coordinates":[-4.4372625351,39.9427070618],"type":"Point"}
}