{
  "type": "Feature",
  "properties": {
    "addr:full":"Carrer de Merceria (de La), 12 Tarragona Tarragona 43003",
    "addr:housenumber":"12",
    "addr:postcode":"43003",
    "addr:street":"Carrer De Merceria De La",
    "iso:country":"ES",
    "sg:address":"Carrer de Merceria (de La), 12",
    "sg:city":"Tarragona",
    "sg:orig_category":"Cajas De Ahorro",
    "sg:phone":"+34 977 23 84 12",
    "sg:postcode":"43003",
    "sg:province":"Tarragona",
    "wof:name":"Caixa D'estalvis De Tarragona",
    "wof:placetype":"venue"
},
  "geometry": {"coordinates":[1.2581160069,41.1181373596],"type":"Point"}
}