{
  "type": "Feature",
  "properties": {
    "addr:full":"Carrer de Sant Antoni Maria Claret, 148 Barcelona Barcelona 08025",
    "addr:housenumber":"148",
    "addr:postcode":"08025",
    "addr:street":"Carrer De Sant Antoni Maria Claret",
    "iso:country":"ES",
    "sg:address":"Carrer de Sant Antoni Maria Claret, 148",
    "sg:city":"Barcelona",
    "sg:orig_category":"Molduras, Junquillos, Listones Y Molduras Perforadas",
    "sg:phone":"+34 934 35 68 07",
    "sg:postcode":"08025",
    "sg:province":"Barcelona",
    "wof:name":"Esmel Mu\u00f1oz Antonia",
    "wof:placetype":"venue"
},
  "geometry": {"coordinates":[2.1708419323,41.4084091187],"type":"Point"}
}