{
  "type": "Feature",
  "properties": {
    "iso:country":"ES",
    "sg:address":"Calle de Paz (la), 5",
    "sg:city":"Portugalete",
    "sg:orig_category":"Empresas De Carpinter\u00cda De Madera",
    "sg:phone":"+34 944 96 51 78",
    "sg:postcode":"48920",
    "sg:province":"Vizcaya",
    "wof:name":"Navio Galey Nicolas",
    "wof:placetype":"venue"
},
  "geometry": {"coordinates":[-3.0172541142,43.317615509],"type":"Point"}
}