{
  "type": "Feature",
  "properties": {
    "iso:country":"ES",
    "sg:address":"Calle de Jabonerias, 4",
    "sg:city":"Cartagena",
    "sg:orig_category":"Tintorer\u00cdas, Limpieza En Seco",
    "sg:phone":"+34 968 50 57 05",
    "sg:postcode":"30201",
    "sg:province":"Murcia",
    "wof:name":"Jimenez Copete Narciso",
    "wof:placetype":"venue"
},
  "geometry": {"coordinates":[-0.9894269705,37.6035842896],"type":"Point"}
}