{
  "type": "Feature",
  "properties": {
    "addr:full":"Calle de Galileo, 71 Madrid Madrid 28015",
    "addr:housenumber":"71",
    "addr:postcode":"madrid;28015",
    "addr:street":"Calle De Galileo",
    "iso:country":"ES",
    "sg:address":"Calle de Galileo, 71",
    "sg:city":"Madrid",
    "sg:orig_category":"Molduras, Junquillos, Listones Y Molduras Perforadas",
    "sg:phone":"+34 914 46 21 56",
    "sg:postcode":"28015",
    "sg:province":"Madrid",
    "wof:name":"Ramimar C.b.",
    "wof:placetype":"venue"
},
  "geometry": {"coordinates":[-3.7102220058,40.437297821],"type":"Point"}
}