{
  "type": "Feature",
  "properties": {
    "iso:country":"ES",
    "sg:address":"Calle de Juan Ramon Jimenez, 19",
    "sg:city":"Alcala Rio",
    "sg:orig_category":"Arquitectos",
    "sg:phone":"+34 955 65 03 96",
    "sg:postcode":"41200",
    "sg:province":"Sevilla",
    "wof:name":"Soluciones De Arquitectura E Ingieneria Integregradas S.l.",
    "wof:placetype":"venue"
},
  "geometry": {"coordinates":[-5.8753418922,37.5525054932],"type":"Point"}
}