{
  "type": "Feature",
  "properties": {
    "iso:country":"ES",
    "sg:address":"Calle de Angel Barrios, 10",
    "sg:city":"Granada",
    "sg:orig_category":"Molduras, Junquillos, Listones Y Molduras Perforadas",
    "sg:phone":"+34 958 25 30 19",
    "sg:postcode":"18004",
    "sg:province":"Granada",
    "wof:name":"Almendros Guerrero Jose",
    "wof:placetype":"venue"
},
  "geometry": {"coordinates":[-3.6085474491,37.1722640991],"type":"Point"}
}