{
  "type": "Feature",
  "properties": {
    "addr:full":"Calle de Trocha De La Victoria, 38 Arahal Sevilla 41600",
    "addr:housenumber":"38",
    "addr:postcode":"41600",
    "addr:street":"Calle De Trocha De La Victoria",
    "iso:country":"ES",
    "sg:address":"Calle de Trocha De La Victoria, 38",
    "sg:city":"Arahal",
    "sg:orig_category":"Abogados",
    "sg:phone":"+34 955 84 05 03",
    "sg:postcode":"41600",
    "sg:province":"Sevilla",
    "wof:name":"Martinet Rodriguez Jose Antonio",
    "wof:placetype":"venue"
},
  "geometry": {"coordinates":[-5.5522179604,37.2580986023],"type":"Point"}
}