{
  "type": "Feature",
  "properties": {
    "iso:country":"ES",
    "sg:address":"Avda Castilla La Mancha, 38",
    "sg:city":"Illescas",
    "sg:orig_category":"Zapatos (al Por Menor)",
    "sg:phone":"+34 925 51 19 37",
    "sg:postcode":"45200",
    "sg:province":"Toledo",
    "wof:name":"Torrejon Garcia Santiago",
    "wof:placetype":"venue"
},
  "geometry": {"coordinates":[-3.8459279537,40.1229820251],"type":"Point"}
}