{
  "type": "Feature",
  "properties": {
    "addr:full":"Calle de Mejico, 16 Zamora Zamora 49022",
    "addr:housenumber":"16",
    "addr:postcode":"49022",
    "addr:street":"Calle De Mejico",
    "iso:country":"ES",
    "sg:address":"Calle de Mejico, 16",
    "sg:city":"Zamora",
    "sg:orig_category":"Artes Gr\u00c1ficas, Artes Pl\u00c1sticas (curso)",
    "sg:phone":"+34 980 51 42 77",
    "sg:postcode":"49022",
    "sg:province":"Zamora",
    "wof:name":"Artmo Bene S.l.",
    "wof:placetype":"venue"
},
  "geometry": {"coordinates":[-5.7271523476,41.512424469],"type":"Point"}
}