{
  "type": "Feature",
  "properties": {
    "addr:full":"Avda Corts Valencianes, 84 Tavernes Blanques Valencia 46016",
    "addr:housenumber":"84",
    "addr:postcode":"46016",
    "addr:street":"Avda Corts Valencianes",
    "iso:country":"ES",
    "sg:address":"Avda Corts Valencianes, 84",
    "sg:city":"Tavernes Blanques",
    "sg:orig_category":"Cajas De Ahorro",
    "sg:phone":"+34 961 85 41 17",
    "sg:postcode":"46016",
    "sg:province":"Valencia",
    "wof:name":"Caixa D'estalvis De Catalunya",
    "wof:placetype":"venue"
},
  "geometry": {"coordinates":[-0.3653660119,39.5072174072],"type":"Point"}
}