{
  "type": "Feature",
  "properties": {
    "addr:full":"Carrer de Madriguera, 31 Sitges Barcelona 08870",
    "addr:housenumber":"31",
    "addr:postcode":"08870",
    "addr:street":"Carrer De Madriguera",
    "iso:country":"ES",
    "sg:address":"Carrer de Madriguera, 31",
    "sg:city":"Sitges",
    "sg:orig_category":"Arquitectos",
    "sg:phone":"+34 938 11 31 49",
    "sg:postcode":"08870",
    "sg:province":"Barcelona",
    "wof:name":"Villena Martinez Antonio",
    "wof:placetype":"venue"
},
  "geometry": {"coordinates":[1.8043290377,41.2438316345],"type":"Point"}
}