{
  "type": "Feature",
  "properties": {
    "addr:full":"Calle de Pintor Francisco Carretero, 16 Tomelloso Ciudad Real 13700",
    "addr:housenumber":"16",
    "addr:postcode":"13700",
    "addr:street":"Calle De Pintor Francisco Carretero",
    "iso:country":"ES",
    "sg:address":"Calle de Pintor Francisco Carretero, 16",
    "sg:city":"Tomelloso",
    "sg:orig_category":"Muebles, Minoristas",
    "sg:phone":"+34 926 51 06 25",
    "sg:postcode":"13700",
    "sg:province":"Ciudad Real",
    "wof:name":"Losa Losa Cayo",
    "wof:placetype":"venue"
},
  "geometry": {"coordinates":[-3.0188961029,39.1559944153],"type":"Point"}
}