{
  "type": "Feature",
  "properties": {
    "iso:country":"ES",
    "sg:address":"Carrer de Marc Aureli, 4",
    "sg:city":"Barcelona",
    "sg:orig_category":"Radiocomunicaciones, Telefon\u00cda M\u00d3vil, Radiomensajer\u00cda: Servicios, Comercializaci\u00d3n",
    "sg:phone":"+34 932 00 27 14",
    "sg:postcode":"08006",
    "sg:province":"Barcelona",
    "wof:name":"Leutbecher Bonebold Ingrid",
    "wof:placetype":"venue"
},
  "geometry": {"coordinates":[2.1435620785,41.4000053406],"type":"Point"}
}