{
  "type": "Feature",
  "properties": {
    "iso:country":"ES",
    "sg:address":"Calle de Real, 11",
    "sg:city":"Valdepe\u00f1as",
    "sg:orig_category":"Perfumer\u00cda (al Por Menor)",
    "sg:phone":"+34 926 31 17 55",
    "sg:postcode":"13300",
    "sg:province":"Ciudad Real",
    "wof:name":"Aqua C-b",
    "wof:placetype":"venue"
},
  "geometry": {"coordinates":[-3.3837285042,38.7612190247],"type":"Point"}
}