{
  "type": "Feature",
  "properties": {
    "addr:full":"Carr Doctor Pascual I Prats, 3 Girona Girona 17004",
    "addr:housenumber":"3",
    "addr:postcode":"17004",
    "addr:street":"Carr Doctor Pascual I Prats",
    "iso:country":"ES",
    "sg:address":"Carr Doctor Pascual I Prats, 3",
    "sg:city":"Girona",
    "sg:orig_category":"Iglesia Cat\u00d3lica",
    "sg:phone":"+34 972 20 68 48",
    "sg:postcode":"17004",
    "sg:province":"Girona",
    "wof:name":"Bisbat De Girona",
    "wof:placetype":"venue"
},
  "geometry": {"coordinates":[2.8245999813,41.9770584106],"type":"Point"}
}