{
  "type": "Feature",
  "properties": {
    "addr:full":"Ctra. Barahona, 15 Medinaceli Soria 42240",
    "addr:housenumber":"15",
    "addr:postcode":"42240",
    "addr:street":"Ctra. Barahona",
    "iso:country":"ES",
    "sg:address":"Ctra. Barahona, 15",
    "sg:city":"Medinaceli",
    "sg:orig_category":"Farmacias",
    "sg:phone":"+34 975 32 63 54",
    "sg:postcode":"42240",
    "sg:province":"Soria",
    "wof:name":"Verges Lafuente Ana Isabel",
    "wof:placetype":"venue"
},
  "geometry": {"coordinates":[-2.4227039814,41.1657104492],"type":"Point"}
}