{
  "type": "Feature",
  "properties": {
    "iso:country":"ES",
    "sg:address":"Calle de Fueros, 6",
    "sg:city":"Jumilla",
    "sg:orig_category":"Abogados",
    "sg:phone":"+34 968 78 07 30",
    "sg:postcode":"30520",
    "sg:province":"Murcia",
    "wof:name":"Jimenez Diaz Herminio",
    "wof:placetype":"venue"
},
  "geometry": {"coordinates":[-1.3271466494,38.4731063843],"type":"Point"}
}