{
  "type": "Feature",
  "properties": {
    "iso:country":"ES",
    "sg:address":"Ere\u00d1otzu Auzoa, 101",
    "sg:city":"Ere\u00d1otzu",
    "sg:orig_category":"Fabricaci\u00d3n Y Comercio De M\u00c1quinas",
    "sg:phone":"+34 943 55 31 36",
    "sg:postcode":"20120",
    "sg:province":"Guip\u00f9zcoa",
    "wof:name":"Coniex S.a.",
    "wof:placetype":"venue"
},
  "geometry": {"coordinates":[-1.9798289537,43.2647514343],"type":"Point"}
}