{
  "type": "Feature",
  "properties": {
    "addr:full":"Avgd Valencia, 38 Massamagrell Valencia 46130",
    "addr:housenumber":"38",
    "addr:postcode":"46130",
    "addr:street":"Valencia",
    "iso:country":"ES",
    "sg:address":"Avgd Valencia, 38",
    "sg:city":"Massamagrell",
    "sg:orig_category":"Molduras, Junquillos, Listones Y Molduras Perforadas",
    "sg:phone":"+34 961 44 24 25",
    "sg:postcode":"46130",
    "sg:province":"Valencia",
    "wof:name":"Villanueva Galan Victorio",
    "wof:placetype":"venue"
},
  "geometry": {"coordinates":[-0.3360950053,39.5691299438],"type":"Point"}
}