{
  "type": "Feature",
  "properties": {
    "addr:full":"Calle de La Rioja, 11 Madrid Madrid 28042",
    "addr:housenumber":"11",
    "addr:postcode":"madrid;28042",
    "addr:street":"Calle De La Rioja",
    "iso:country":"ES",
    "sg:address":"Calle de La Rioja, 11",
    "sg:city":"Madrid",
    "sg:orig_category":"Centros De Coordinaci\u00d3n",
    "sg:phone":"+34 913 29 60 60",
    "sg:postcode":"28042",
    "sg:province":"Madrid",
    "wof:name":"Guaita Beneit Mercedes",
    "wof:placetype":"venue"
},
  "geometry": {"coordinates":[-3.5888979435,40.4572257996],"type":"Point"}
}