{
  "type": "Feature",
  "properties": {
    "iso:country":"ES",
    "sg:address":"Calle de Virgen Del Romeral, 22",
    "sg:city":"Binefar",
    "sg:orig_category":"Imprenta",
    "sg:phone":"+34 974 42 96 49",
    "sg:postcode":"22500",
    "sg:province":"Huesca",
    "wof:name":"Campo Rodriguez Jorge",
    "wof:placetype":"venue"
},
  "geometry": {"coordinates":[0.2980610132,41.8460769653],"type":"Point"}
}