{
  "type": "Feature",
  "properties": {
    "addr:full":"Calle de San Agustin, 26 Requena Valencia 46340",
    "addr:housenumber":"26",
    "addr:postcode":"46340",
    "addr:street":"Calle De San Agustin",
    "iso:country":"ES",
    "sg:address":"Calle de San Agustin, 26",
    "sg:city":"Requena",
    "sg:orig_category":"Agencias De Viajes",
    "sg:phone":"+34 962 30 19 67",
    "sg:postcode":"46340",
    "sg:province":"Valencia",
    "wof:name":"Viajes Altiplano S.l.",
    "wof:placetype":"venue"
},
  "geometry": {"coordinates":[-1.1022919416,39.4890136719],"type":"Point"}
}