{
  "type": "Feature",
  "properties": {
    "addr:full":"Avda Madrid De, 19 Fraga Huesca 22520",
    "addr:housenumber":"19",
    "addr:postcode":"22520",
    "addr:street":"Avda Madrid De",
    "iso:country":"ES",
    "sg:address":"Avda Madrid De, 19",
    "sg:city":"Fraga",
    "sg:orig_category":"Mec\u00c1nico Del Autom\u00d3vil",
    "sg:phone":"+34 974 47 12 90",
    "sg:postcode":"22520",
    "sg:province":"Huesca",
    "wof:name":"Talleres Hermanos Arellano S.c.",
    "wof:placetype":"venue"
},
  "geometry": {"coordinates":[0.3364729881,41.5208396912],"type":"Point"}
}