{
  "type": "Feature",
  "properties": {
    "iso:country":"ES",
    "sg:address":"Benet Messeguer Villaro, S/n",
    "sg:city":"Mora Ebre",
    "sg:orig_category":"M\u00c9dicos: Psiquiatr\u00cda",
    "sg:phone":"+34 977 40 24 60",
    "sg:postcode":"43740",
    "sg:province":"Tarragona",
    "wof:name":"Instituto Pedro Mata S. A.",
    "wof:placetype":"venue"
},
  "geometry": {"coordinates":[0.6372100115,41.0945587158],"type":"Point"}
}