{
  "type": "Feature",
  "properties": {
    "iso:country":"ES",
    "sg:address":"Calle de Calancha, 1",
    "sg:city":"Andujar",
    "sg:orig_category":"Inmobiliaria (agencias)",
    "sg:phone":"+34 953 51 54 52",
    "sg:postcode":"23740",
    "sg:province":"Ja\u00e9n",
    "wof:name":"The King House Grupo Inmobiliaria S.l.",
    "wof:placetype":"venue"
},
  "geometry": {"coordinates":[-4.0562992096,38.0398902893],"type":"Point"}
}