{
  "type": "Feature",
  "properties": {
    "addr:full":"Av. Scho Fuerte, 71 Iru\u00f1a Navarra 31007",
    "addr:housenumber":"71",
    "addr:postcode":"31007",
    "addr:street":"Av. Scho Fuerte",
    "iso:country":"ES",
    "sg:address":"Av. Scho Fuerte, 71",
    "sg:city":"Iru\u00f1a",
    "sg:orig_category":"Muebles, Minoristas",
    "sg:phone":"+34 948 26 70 22",
    "sg:postcode":"31007",
    "sg:province":"Navarra",
    "sg:website":"www.roche-bobois.com",
    "wof:name":"Sagaseta S.l.",
    "wof:placetype":"venue"
},
  "geometry": {"coordinates":[-1.6562490463,42.8099899292],"type":"Point"}
}