{
  "type": "Feature",
  "properties": {
    "addr:full":"Carrer de Colom, 230 Terrassa Barcelona 08223",
    "addr:housenumber":"230",
    "addr:postcode":"08223",
    "addr:street":"Carrer De Colom",
    "iso:country":"ES",
    "sg:address":"Carrer de Colom, 230",
    "sg:city":"Terrassa",
    "sg:orig_category":"Institutos De Belleza",
    "sg:phone":"+34 937 31 54 43",
    "sg:postcode":"08223",
    "sg:province":"Barcelona",
    "wof:name":"Carrillo Perez Flora",
    "wof:placetype":"venue"
},
  "geometry": {"coordinates":[2.0243120193,41.5571632385],"type":"Point"}
}