{
  "type": "Feature",
  "properties": {
    "iso:country":"ES",
    "sg:address":"Rbla S Ferran, 41",
    "sg:city":"Igualada",
    "sg:orig_category":"Arquitectos",
    "sg:phone":"+34 938 05 28 02",
    "sg:postcode":"08700",
    "sg:province":"Barcelona",
    "wof:name":"Projectes Tallercinc Sl",
    "wof:placetype":"venue"
},
  "geometry": {"coordinates":[1.6170699596,41.5795402527],"type":"Point"}
}