{
  "type": "Feature",
  "properties": {
    "iso:country":"ES",
    "sg:address":"Ctra. Valverde Fresno, Km. 0001,9",
    "sg:city":"Hervas",
    "sg:orig_category":"Ebanister\u00cda",
    "sg:phone":"+34 927 48 13 64",
    "sg:postcode":"10700",
    "sg:province":"C\u00e1ceres",
    "wof:name":"Peralejo Hernandez Jesus",
    "wof:placetype":"venue"
},
  "geometry": {"coordinates":[-5.863948822,40.2720451355],"type":"Point"}
}