{
  "type": "Feature",
  "properties": {
    "iso:country":"ES",
    "sg:address":"Urb Marques Del Duero, 82",
    "sg:city":"San Pedro Alcantara",
    "sg:orig_category":"Promotores Constructores",
    "sg:phone":"+34 952 85 30 58",
    "sg:postcode":"29670",
    "sg:province":"M\u00e1laga",
    "wof:name":"Rsp Gece S.l.",
    "wof:placetype":"venue"
},
  "geometry": {"coordinates":[-4.9890751839,36.4835395813],"type":"Point"}
}