{
  "type": "Feature",
  "properties": {
    "addr:full":"Calle de Vivaldi (urb Marbella Sierra Blanca), 19 Marbella M\u00e1laga 29600",
    "addr:housenumber":"19",
    "addr:postcode":"29600",
    "addr:street":"Calle De Vivaldi Urb Marbella Sierra Blanca;Ma\u0301Laga",
    "iso:country":"ES",
    "sg:address":"Calle de Vivaldi (urb Marbella Sierra Blanca), 19",
    "sg:city":"Marbella",
    "sg:orig_category":"Importaci\u00d3n",
    "sg:phone":"+34 952 76 64 49",
    "sg:postcode":"29600",
    "sg:province":"M\u00e1laga",
    "wof:name":"Malbrook Sierra S.l.",
    "wof:placetype":"venue"
},
  "geometry": {"coordinates":[-4.9133892059,36.5305595398],"type":"Point"}
}