{
  "type": "Feature",
  "properties": {
    "iso:country":"ES",
    "sg:address":"Av Comte De Sallent, 10",
    "sg:city":"Palma",
    "sg:orig_category":"M\u00c9dicos: Estomatolog\u00cda",
    "sg:phone":"+34 971 76 09 00",
    "sg:postcode":"07003",
    "sg:province":"Islas Baleares",
    "wof:name":"Salas Bauza Maria Antonia",
    "wof:placetype":"venue"
},
  "geometry": {"coordinates":[2.6509358883,39.5780258179],"type":"Point"}
}