{
  "type": "Feature",
  "properties": {
    "addr:full":"Sant Llorenc, 82 Mao Islas Baleares 07702",
    "addr:housenumber":"82",
    "addr:postcode":"07702",
    "addr:street":"Llorenc",
    "iso:country":"ES",
    "sg:address":"Sant Llorenc, 82",
    "sg:city":"Mao",
    "sg:orig_category":"Iglesia Cat\u00d3lica",
    "sg:phone":"+34 971 36 42 57",
    "sg:postcode":"07702",
    "sg:province":"Islas Baleares",
    "wof:name":"Parroquia De Santa Eulalia",
    "wof:placetype":"venue"
},
  "geometry": {"coordinates":[4.2663350105,39.8850631714],"type":"Point"}
}