{
  "type": "Feature",
  "properties": {
    "addr:full":"P. Marichal, 2 Arucas Las Palmas 35400",
    "addr:housenumber":"2",
    "addr:postcode":"35400",
    "addr:street":"P. Marichal",
    "iso:country":"ES",
    "sg:address":"P. Marichal, 2",
    "sg:city":"Arucas",
    "sg:orig_category":"Ense\u00d1anza: Idiomas",
    "sg:phone":"+34 928 62 25 44",
    "sg:postcode":"35400",
    "sg:province":"Las Palmas",
    "wof:name":"Santana Garcia Angel David",
    "wof:placetype":"venue"
},
  "geometry": {"coordinates":[-15.5152540207,28.1135654449],"type":"Point"}
}