{
  "type": "Feature",
  "properties": {
    "iso:country":"ES",
    "sg:address":"Ctra Errekalde-larraskitu, 35",
    "sg:city":"Bilbao",
    "sg:orig_category":"Electricidad: Instaladores",
    "sg:phone":"+34 944 43 88 89",
    "sg:postcode":"48002",
    "sg:province":"Vizcaya",
    "wof:name":"Joel Fernandez Lopez",
    "wof:placetype":"venue"
},
  "geometry": {"coordinates":[-2.939759016,43.2495307922],"type":"Point"}
}