{
  "type": "Feature",
  "properties": {
    "addr:full":"Calle de Labradores, 42 Logro\u00f1o La Rioja 26005",
    "addr:housenumber":"42",
    "addr:postcode":"26005",
    "addr:street":"Calle De Labradores;Rioja",
    "iso:country":"ES",
    "sg:address":"Calle de Labradores, 42",
    "sg:city":"Logro\u00f1o",
    "sg:orig_category":"Muebles, Minoristas",
    "sg:phone":"+34 941 21 29 28",
    "sg:postcode":"26005",
    "sg:province":"La Rioja",
    "wof:name":"Eusebio Muebles De Encargo S.c.",
    "wof:placetype":"venue"
},
  "geometry": {"coordinates":[-2.4564180374,42.4606552124],"type":"Point"}
}