{
  "type": "Feature",
  "properties": {
    "addr:full":"Ctra. Eivissa S. Antoni, Km. 0001,2 Eivissa Islas Baleares 07800",
    "addr:postcode":"07800",
    "addr:street":"Ctra. Eivissa S. Antoni Km. 0001,2",
    "iso:country":"ES",
    "sg:address":"Ctra. Eivissa S. Antoni, Km. 0001,2",
    "sg:city":"Eivissa",
    "sg:orig_category":"Ense\u00d1anza: Idiomas",
    "sg:phone":"+34 971 31 46 22",
    "sg:postcode":"07800",
    "sg:province":"Islas Baleares",
    "sg:website":"www.eoieivissa.com",
    "wof:name":"Ampliacion Escuela Oficial De Idiomas",
    "wof:placetype":"venue"
},
  "geometry": {"coordinates":[1.4363815784,38.9067573547],"type":"Point"}
}