{
  "type": "Feature",
  "properties": {
    "addr:full":"Calle de Palencia, 42 Madrid Madrid 28020",
    "addr:housenumber":"42",
    "addr:postcode":"madrid;28020",
    "addr:street":"Calle De Palencia",
    "iso:country":"ES",
    "sg:address":"Calle de Palencia, 42",
    "sg:city":"Madrid",
    "sg:orig_category":"Servicio De Salud",
    "sg:phone":"+34 915 33 39 31",
    "sg:postcode":"28020",
    "sg:province":"Madrid",
    "wof:name":"Garcia Ca\u00f1adas Manuel",
    "wof:placetype":"venue"
},
  "geometry": {"coordinates":[-3.6994268894,40.4494628906],"type":"Point"}
}