{
  "type": "Feature",
  "properties": {
    "addr:full":"C/ Sant Vicent, 6 Elche Alicante 03202",
    "addr:housenumber":"6",
    "addr:postcode":"03202",
    "addr:street":"C / Sant Vicent",
    "iso:country":"ES",
    "sg:address":"C/ Sant Vicent, 6",
    "sg:city":"Elche",
    "sg:orig_category":"Procuradores",
    "sg:phone":"+34 965 45 23 43",
    "sg:postcode":"03202",
    "sg:province":"Alicante",
    "wof:name":"Casta\u00f1o Lopez Vicente Jose",
    "wof:placetype":"venue"
},
  "geometry": {"coordinates":[-0.6956040263,38.2677764893],"type":"Point"}
}