{
  "type": "Feature",
  "properties": {
    "iso:country":"ES",
    "sg:address":"Afores, Km. 1229,5",
    "sg:city":"Vallirana",
    "sg:orig_category":"Hormigonados",
    "sg:phone":"+34 936 84 80 56",
    "sg:postcode":"08759",
    "sg:province":"Barcelona",
    "wof:name":"Lafarge Aridos Y Hormigones S.a.",
    "wof:placetype":"venue"
},
  "geometry": {"coordinates":[1.9328349829,41.3889045715],"type":"Point"}
}