{
  "type": "Feature",
  "properties": {
    "addr:full":"Carr Bages, 17 Solsona Lleida 25280",
    "addr:housenumber":"17",
    "addr:postcode":"25280",
    "addr:street":"Carr Bages",
    "iso:country":"ES",
    "sg:address":"Carr Bages, 17",
    "sg:city":"Solsona",
    "sg:orig_category":"Electricidad: Instaladores",
    "sg:phone":"+34 973 48 07 33",
    "sg:postcode":"25280",
    "sg:province":"Lleida",
    "wof:name":"Ramon Espuga Vilardell S.l.",
    "wof:placetype":"venue"
},
  "geometry": {"coordinates":[1.51879704,41.9992218018],"type":"Point"}
}