{
  "type": "Feature",
  "properties": {
    "iso:country":"ES",
    "sg:address":"Tiburzio Anitua Kalea, 1",
    "sg:city":"Eibar",
    "sg:orig_category":"Automatizaci\u00d3n De Procesos Industriales Y De Edificaci\u00d3n (estudios, Instalaci\u00d3n)",
    "sg:phone":"+34 943 70 28 63",
    "sg:postcode":"20600",
    "sg:province":"Guip\u00f9zcoa",
    "wof:name":"Dima Automation S.l.",
    "wof:placetype":"venue"
},
  "geometry": {"coordinates":[-2.4811599255,43.1844863892],"type":"Point"}
}