{
  "type": "Feature",
  "properties": {
    "addr:full":"Carrer de Jose Zorrilla, 9 Granollers Barcelona 08402",
    "addr:housenumber":"9",
    "addr:postcode":"08402",
    "addr:street":"Carrer De Jose Zorrilla",
    "iso:country":"ES",
    "sg:address":"Carrer de Jose Zorrilla, 9",
    "sg:city":"Granollers",
    "sg:orig_category":"Promotores Constructores",
    "sg:phone":"+34 938 46 39 30",
    "sg:postcode":"08402",
    "sg:province":"Barcelona",
    "wof:name":"Construcciones Casalderrey S.l.",
    "wof:placetype":"venue"
},
  "geometry": {"coordinates":[2.2948610783,41.6145591736],"type":"Point"}
}