{
  "type": "Feature",
  "properties": {
    "addr:full":"Avda Maria Auxiliadora, 23 Ecija Sevilla 41400",
    "addr:housenumber":"23",
    "addr:postcode":"41400",
    "addr:street":"Avda Maria Auxiliadora",
    "iso:country":"ES",
    "sg:address":"Avda Maria Auxiliadora, 23",
    "sg:city":"Ecija",
    "sg:orig_category":"Papeler\u00cdas, Librer\u00cdas",
    "sg:phone":"+34 955 90 45 86",
    "sg:postcode":"41400",
    "sg:province":"Sevilla",
    "wof:name":"Comercial Martin S.c.",
    "wof:placetype":"venue"
},
  "geometry": {"coordinates":[-5.0865340233,37.5425758362],"type":"Point"}
}