{
  "type": "Feature",
  "properties": {
    "iso:country":"ES",
    "sg:address":"Pg Circumval.lacio, 67",
    "sg:city":"Castelldefels",
    "sg:orig_category":"Ingenier\u00cda, Centros De Estudios (diversos)",
    "sg:phone":"+34 936 65 01 37",
    "sg:postcode":"08860",
    "sg:province":"Barcelona",
    "wof:name":"Vi\u00f1olas Vives Alberto",
    "wof:placetype":"venue"
},
  "geometry": {"coordinates":[1.9611378908,41.2782287598],"type":"Point"}
}