{
  "type": "Feature",
  "properties": {
    "iso:country":"ES",
    "sg:address":"Calle de Polvillo, 82",
    "sg:city":"Cantillana",
    "sg:orig_category":"Molduras, Junquillos, Listones Y Molduras Perforadas",
    "sg:phone":"+34 955 73 04 04",
    "sg:postcode":"41320",
    "sg:province":"Sevilla",
    "wof:name":"Lazaro Nunez Solis",
    "wof:placetype":"venue"
},
  "geometry": {"coordinates":[-5.8239889145,37.6094207764],"type":"Point"}
}