{
  "type": "Feature",
  "properties": {
    "iso:country":"ES",
    "sg:address":"Calle de Cestilla (la), 2",
    "sg:city":"Palencia",
    "sg:orig_category":"Abogados",
    "sg:phone":"+34 979 70 64 68",
    "sg:postcode":"34001",
    "sg:province":"Palencia",
    "wof:name":"Bueno Sebastian Eduardo",
    "wof:placetype":"venue"
},
  "geometry": {"coordinates":[-4.5330991745,42.009677887],"type":"Point"}
}