{
  "type": "Feature",
  "properties": {
    "iso:country":"ES",
    "sg:address":"Ctra Madrid-cadiz(p I Estacion), Km. 0325,0",
    "sg:city":"Andujar",
    "sg:orig_category":"Material Y Herramientas Agr\u00cdcolas",
    "sg:phone":"+34 953 51 50 44",
    "sg:postcode":"23740",
    "sg:province":"Ja\u00e9n",
    "wof:name":"Solano Horizonte S.l.",
    "wof:placetype":"venue"
},
  "geometry": {"coordinates":[-4.062543869,38.0306167603],"type":"Point"}
}