{
  "type": "Feature",
  "properties": {
    "addr:full":"Calle de Mercurio, 14 Poligono Ardoz Toledo 45200",
    "addr:housenumber":"14 poligono",
    "addr:postcode":"45200",
    "addr:street":"Calle De Mercurio",
    "iso:country":"ES",
    "sg:address":"Calle de Mercurio, 14",
    "sg:city":"Poligono Ardoz",
    "sg:orig_category":"Herboristas (al Por Menor)",
    "sg:phone":"+34 925 51 14 76",
    "sg:postcode":"45200",
    "sg:province":"Toledo",
    "wof:name":"Montejano Mata Maria Isabel",
    "wof:placetype":"venue"
},
  "geometry": {"coordinates":[-4.0244760513,39.8567771912],"type":"Point"}
}