{
  "type": "Feature",
  "properties": {
    "addr:full":"Calle de Goya, 24 Villarrobledo Albacete 02600",
    "addr:housenumber":"24",
    "addr:postcode":"02600",
    "addr:street":"Calle De Goya",
    "iso:country":"ES",
    "sg:address":"Calle de Goya, 24",
    "sg:city":"Villarrobledo",
    "sg:orig_category":"Promotores Constructores",
    "sg:phone":"+34 967 14 12 28",
    "sg:postcode":"02600",
    "sg:province":"Albacete",
    "wof:name":"Lozano Melero S.l.",
    "wof:placetype":"venue"
},
  "geometry": {"coordinates":[-2.6058781147,39.2737998962],"type":"Point"}
}