{
  "type": "Feature",
  "properties": {
    "addr:full":"Rua Espa\u00d1oleto, S/n Ferrol La Coru\u00f1a 15402",
    "addr:housenumber":"s / n",
    "addr:postcode":"15402",
    "addr:street":"Rua Espan\u0303Oleto;La Corun\u0303A",
    "iso:country":"ES",
    "sg:address":"Rua Espa\u00d1oleto, S/n",
    "sg:city":"Ferrol",
    "sg:orig_category":"Art\u00cdculos De Decoraci\u00d3n",
    "sg:phone":"+34 981 35 99 02",
    "sg:postcode":"15402",
    "sg:province":"La Coru\u00f1a",
    "wof:name":"Gama Decoracion Y Pinturas S.l.",
    "wof:placetype":"venue"
},
  "geometry": {"coordinates":[-8.2257289886,43.4822883606],"type":"Point"}
}