{
  "type": "Feature",
  "properties": {
    "addr:full":"Calle de Alfonso I, 33 Zaragoza Zaragoza 50003",
    "addr:housenumber":"33",
    "addr:postcode":"50003",
    "addr:street":"Calle De Alfonso I",
    "iso:country":"ES",
    "sg:address":"Calle de Alfonso I, 33",
    "sg:city":"Zaragoza",
    "sg:orig_category":"Importaci\u00d3n, Exportaci\u00d3n Y Comercios De Productos Textiles",
    "sg:phone":"+34 976 39 66 95",
    "sg:postcode":"50003",
    "sg:province":"Zaragoza",
    "wof:name":"Arsac Rodes Concepcion",
    "wof:placetype":"venue"
},
  "geometry": {"coordinates":[-0.8798915148,41.6553268433],"type":"Point"}
}