{
  "type": "Feature",
  "properties": {
    "iso:country":"ES",
    "sg:address":"Calle de Molinos, S/n",
    "sg:city":"Frias",
    "sg:classifiers":[
        {
            "category":"Taxi",
            "type":"Transportation"
        }
    ],
    "sg:phone":"+34 947 35 72 12",
    "sg:postcode":"09211",
    "sg:province":"Burgos",
    "wof:name":"Arranz Lopez Luis",
    "wof:placetype":"venue"
},
  "geometry": {"coordinates":[-3.2926385403,42.7611923218],"type":"Point"}
}