{
  "type": "Feature",
  "properties": {
    "iso:country":"ES",
    "sg:address":"Crt. Csta. Reina, Km. 0002,4",
    "sg:city":"Sese\u00f1a",
    "sg:orig_category":"Promotores Constructores",
    "sg:phone":"+34 918 08 87 72",
    "sg:postcode":"45223",
    "sg:province":"Toledo",
    "wof:name":"Rey Instalaciones Comerciales S.l.",
    "wof:placetype":"venue"
},
  "geometry": {"coordinates":[-3.6970739365,40.1043663025],"type":"Point"}
}