{
  "type": "Feature",
  "properties": {
    "addr:full":"Ctra San Martin, Km. 0004,5 Cadalso De Los Vidrios Madrid 28640",
    "addr:postcode":"28640",
    "addr:street":"Ctra San Martin Km. 0004,5 Cadalso",
    "iso:country":"ES",
    "sg:address":"Ctra San Martin, Km. 0004,5",
    "sg:city":"Cadalso De Los Vidrios",
    "sg:orig_category":"Perreras, Pensiones Para Perros, Gatos Y Otros Animales",
    "sg:phone":"+34 918 63 40 69",
    "sg:postcode":"28640",
    "sg:province":"Madrid",
    "wof:name":"Barroso Cornejo Angel Luis",
    "wof:placetype":"venue"
},
  "geometry": {"coordinates":[-4.4422230721,40.3078384399],"type":"Point"}
}