{
  "type": "Feature",
  "properties": {
    "iso:country":"ES",
    "sg:address":"Calle de Consulado, 7",
    "sg:city":"Burgos",
    "sg:orig_category":"Molduras, Junquillos, Listones Y Molduras Perforadas",
    "sg:phone":"+34 947 27 57 13",
    "sg:postcode":"09003",
    "sg:province":"Burgos",
    "wof:name":"Romero Ruiz Manuel",
    "wof:placetype":"venue"
},
  "geometry": {"coordinates":[-3.7024857998,42.3450660706],"type":"Point"}
}