{
  "type": "Feature",
  "properties": {
    "addr:full":"Cmno Hormigueras, 164 Madrid Madrid 28031",
    "addr:housenumber":"164",
    "addr:postcode":"28031",
    "addr:street":"Cmno Hormigueras",
    "iso:country":"ES",
    "sg:address":"Cmno Hormigueras, 164",
    "sg:city":"Madrid",
    "sg:orig_category":"Negocio De Materiales De Construcci\u00d3n",
    "sg:phone":"+34 917 78 73 41",
    "sg:postcode":"28031",
    "sg:province":"Madrid",
    "wof:name":"Diaz Melgares S.l.",
    "wof:placetype":"venue"
},
  "geometry": {"coordinates":[-3.6346840858,40.3768005371],"type":"Point"}
}