{
  "type": "Feature",
  "properties": {
    "addr:full":"Calle de Viteri, 32 Errenteria Guip\u00f9zcoa 20100",
    "addr:housenumber":"32",
    "addr:postcode":"20100",
    "addr:street":"Calle De Viteri;Guipu\u0300Zcoa",
    "iso:country":"ES",
    "sg:address":"Calle de Viteri, 32",
    "sg:city":"Errenteria",
    "sg:orig_category":"Estancos",
    "sg:phone":"+34 943 34 07 99",
    "sg:postcode":"20100",
    "sg:province":"Guip\u00f9zcoa",
    "wof:name":"Aguirreburualde Urquiaga Maria Nazareth",
    "wof:placetype":"venue"
},
  "geometry": {"coordinates":[-1.9021978378,43.3139457703],"type":"Point"}
}