{
  "type": "Feature",
  "properties": {
    "addr:full":"Calle de Rio Ebro, 19 Miranda Ebro Burgos 09200",
    "addr:housenumber":"19",
    "addr:postcode":"09200",
    "addr:street":"Calle De Rio Ebro",
    "iso:country":"ES",
    "sg:address":"Calle de Rio Ebro, 19",
    "sg:city":"Miranda Ebro",
    "sg:orig_category":"Comercio De Piezas De Recambio Y De Accesorios De Veh\u00cdculos, Veh\u00cdculos Industriales",
    "sg:phone":"+34 947 32 06 62",
    "sg:postcode":"09200",
    "sg:province":"Burgos",
    "wof:name":"Calzadal Sorrigueta Teodoro",
    "wof:placetype":"venue"
},
  "geometry": {"coordinates":[-2.9458711147,42.6832046509],"type":"Point"}
}