{
  "type": "Feature",
  "properties": {
    "iso:country":"ES",
    "sg:address":"Pol. Ind. San Jeronimo, S/n",
    "sg:city":"Sevilla",
    "sg:orig_category":"Chapister\u00cda",
    "sg:phone":"+34 954 37 02 97",
    "sg:postcode":"41015",
    "sg:province":"Sevilla",
    "wof:name":"Aceralia Distribucion S.l.",
    "wof:placetype":"venue"
},
  "geometry": {"coordinates":[-5.9753265381,37.4319877625],"type":"Point"}
}