{
  "type": "Feature",
  "properties": {
    "iso:country":"ES",
    "sg:address":"Calle de Estacion, 4",
    "sg:city":"Marbella",
    "sg:orig_category":"Bisuter\u00cda, Joyer\u00cda, Relojer\u00cda (al Por Menor)",
    "sg:phone":"+34 952 86 27 45",
    "sg:postcode":"29600",
    "sg:province":"M\u00e1laga",
    "wof:name":"Aranda Gimeno Bego\u00f1a",
    "wof:placetype":"venue"
},
  "geometry": {"coordinates":[-4.8856263161,36.5102348328],"type":"Point"}
}