{
  "type": "Feature",
  "properties": {
    "iso:country":"ES",
    "sg:address":"Carrer de Santa Barbara, 14",
    "sg:city":"Barbera Valles",
    "sg:orig_category":"Fotocopias, Reprograf\u00cda",
    "sg:phone":"+34 937 29 24 20",
    "sg:postcode":"08210",
    "sg:province":"Barcelona",
    "wof:name":"Bbr Grafistes S.l.",
    "wof:placetype":"venue"
},
  "geometry": {"coordinates":[2.1271760464,41.5150566101],"type":"Point"}
}