{
  "type": "Feature",
  "properties": {
    "iso:country":"ES",
    "sg:address":"Carrer de Major, 17",
    "sg:city":"Vall D'alba",
    "sg:orig_category":"Loter\u00cda Y T\u00d3mbola",
    "sg:phone":"+34 964 32 05 09",
    "sg:postcode":"12194",
    "sg:province":"Castell\u00f3n",
    "wof:name":"Valles Vidal Victor",
    "wof:placetype":"venue"
},
  "geometry": {"coordinates":[-0.0519389994,39.985408783],"type":"Point"}
}