{
  "type": "Feature",
  "properties": {
    "iso:country":"ES",
    "sg:address":"Ctra Canillas, 31",
    "sg:city":"Madrid",
    "sg:orig_category":"Farmacias",
    "sg:phone":"+34 913 88 34 17",
    "sg:postcode":"28043",
    "sg:province":"Madrid",
    "wof:name":"Santadreu Mu\u00f1oz Carlos",
    "wof:placetype":"venue"
},
  "geometry": {"coordinates":[-3.6488149166,40.463092804],"type":"Point"}
}