{
  "type": "Feature",
  "properties": {
    "iso:country":"ES",
    "sg:address":"Avda Miguel Hernandez, 31",
    "sg:city":"Denia",
    "sg:orig_category":"Asociaciones Y Clubs Deportivos",
    "sg:phone":"+34 966 42 43 16",
    "sg:postcode":"03700",
    "sg:province":"Alicante",
    "wof:name":"Denia-sport Gyn Europa S.l",
    "wof:placetype":"venue"
},
  "geometry": {"coordinates":[0.1012760028,38.8424873352],"type":"Point"}
}