{
  "type": "Feature",
  "properties": {
    "addr:full":"Av Sarria, 9 Barcelona Barcelona 08029",
    "addr:housenumber":"9",
    "addr:postcode":"08029",
    "addr:street":"Av Sarria",
    "iso:country":"ES",
    "sg:address":"Av Sarria, 9",
    "sg:city":"Barcelona",
    "sg:orig_category":"Comercio De Mobiliario De Oficina",
    "sg:phone":"+34 934 19 67 39",
    "sg:postcode":"08029",
    "sg:province":"Barcelona",
    "sg:website":"www.ofiprix.com",
    "wof:name":"Ofiprix S.l.",
    "wof:placetype":"venue"
},
  "geometry": {"coordinates":[2.1471209526,41.3898239136],"type":"Point"}
}