{
  "type": "Feature",
  "properties": {
    "addr:full":"Las Escuelas, Km. 0010,3 Las Escuelas Ja\u00e9n 23539",
    "addr:postcode":"23539",
    "addr:street":"Las Escuelas Km. 0010,3 Las Escuelas Jae\u0301N",
    "iso:country":"ES",
    "sg:address":"Las Escuelas, Km. 0010,3",
    "sg:city":"Las Escuelas",
    "sg:orig_category":"Aguas (distribuci\u00d3n, Servicios)",
    "sg:phone":"+34 953 12 70 78",
    "sg:postcode":"23539",
    "sg:province":"Ja\u00e9n",
    "wof:name":"Comunidad De Regantes Pajarejos",
    "wof:placetype":"venue"
},
  "geometry": {"coordinates":[-3.4601690769,37.8742332458],"type":"Point"}
}