{
  "type": "Feature",
  "properties": {
    "iso:country":"ES",
    "sg:address":"Calle de Montoro, 2",
    "sg:city":"Villanueva Cordoba",
    "sg:orig_category":"Peluqueros: De Se\u00d1oras",
    "sg:phone":"+34 957 12 16 51",
    "sg:postcode":"14440",
    "sg:province":"C\u00f3rdoba",
    "wof:name":"Exposito Romero Alfonsa",
    "wof:placetype":"venue"
},
  "geometry": {"coordinates":[-4.6296901703,38.3173027039],"type":"Point"}
}