{
  "type": "Feature",
  "properties": {
    "addr:full":"Avda Constitucion (de La), 46 Mostoles Madrid 28931",
    "addr:housenumber":"46",
    "addr:postcode":"28931",
    "addr:street":"Avda Constitucion De La",
    "iso:country":"ES",
    "sg:address":"Avda Constitucion (de La), 46",
    "sg:city":"Mostoles",
    "sg:orig_category":"Abogados",
    "sg:phone":"+34 916 13 53 55",
    "sg:postcode":"28931",
    "sg:province":"Madrid",
    "wof:name":"Beltran Marin Carlos",
    "wof:placetype":"venue"
},
  "geometry": {"coordinates":[-3.8616919518,40.3258171082],"type":"Point"}
}