{
  "type": "Feature",
  "properties": {
    "addr:full":"Calle de Magistral Luis Reyes, 18 Cuesta Santa Cruz De Tenerife 38320",
    "addr:housenumber":"18",
    "addr:postcode":"38320",
    "addr:street":"Calle De Magistral Luis Reyes",
    "iso:country":"ES",
    "sg:address":"Calle de Magistral Luis Reyes, 18",
    "sg:city":"Cuesta",
    "sg:orig_category":"Ambulancias",
    "sg:phone":"+34 922 64 72 88",
    "sg:postcode":"38320",
    "sg:province":"Santa Cruz De Tenerife",
    "wof:name":"Cooperativas De Ambulancias Canarias S.l.",
    "wof:placetype":"venue"
},
  "geometry": {"coordinates":[-16.2844104767,28.4657230377],"type":"Point"}
}