{
  "type": "Feature",
  "properties": {
    "addr:full":"Calle de Santiago, 4 Portugalete Vizcaya 48920",
    "addr:housenumber":"4",
    "addr:postcode":"48920",
    "addr:street":"Calle De Santiago",
    "iso:country":"ES",
    "sg:address":"Calle de Santiago, 4",
    "sg:city":"Portugalete",
    "sg:orig_category":"Peluquer\u00cdas, Peluquer\u00cda Mixta",
    "sg:phone":"+34 946 07 16 10",
    "sg:postcode":"48920",
    "sg:province":"Vizcaya",
    "wof:name":"Estibaliz Basabe",
    "wof:placetype":"venue"
},
  "geometry": {"coordinates":[-3.0211029053,43.3223075867],"type":"Point"}
}