{
  "type": "Feature",
  "properties": {
    "iso:country":"ES",
    "sg:address":"Calle de Prado, Del, 33",
    "sg:city":"Isla Cristina",
    "sg:orig_category":"Art\u00cdculos De Regalo (al Por Menor)",
    "sg:phone":"+34 959 33 28 93",
    "sg:postcode":"21410",
    "sg:province":"Huelva",
    "sg:website":"www.baarllobell.com",
    "wof:name":"Construcciones Manuel Alonso Martin S.l.",
    "wof:placetype":"venue"
},
  "geometry": {"coordinates":[-7.3203940392,37.2019615173],"type":"Point"}
}