{
  "type": "Feature",
  "properties": {
    "iso:country":"ES",
    "sg:address":"Ctra Maso, S/n",
    "sg:city":"Vallmoll",
    "sg:orig_category":"Cerrajer\u00cda, Ferrallista",
    "sg:phone":"+34 977 63 71 54",
    "sg:postcode":"43144",
    "sg:province":"Tarragona",
    "wof:name":"Garrido Garcia Antonio Luis",
    "wof:placetype":"venue"
},
  "geometry": {"coordinates":[1.249235034,41.2438163757],"type":"Point"}
}