{
  "type": "Feature",
  "properties": {
    "addr:full":"Calle de Crespas (las), 1 Consuegra Toledo 45700",
    "addr:housenumber":"1",
    "addr:postcode":"45700",
    "addr:street":"Calle De Crespas Las",
    "iso:country":"ES",
    "sg:address":"Calle de Crespas (las), 1",
    "sg:city":"Consuegra",
    "sg:orig_category":"Bazares, Art\u00cdculos De Limpieza Y De Cocina (al Por Menor)",
    "sg:phone":"+34 925 48 02 87",
    "sg:postcode":"45700",
    "sg:province":"Toledo",
    "wof:name":"Rodriguez Manzano Vicente",
    "wof:placetype":"venue"
},
  "geometry": {"coordinates":[-3.6104869843,39.4615058899],"type":"Point"}
}