{
  "type": "Feature",
  "properties": {
    "iso:country":"ES",
    "sg:address":"Luga Caserio Los Corralillos, 1",
    "sg:city":"Corralillos",
    "sg:orig_category":"Hielo Artificial (fabricaci\u00d3n, Distribuci\u00d3n)",
    "sg:phone":"+34 928 78 21 03",
    "sg:postcode":"35119",
    "sg:province":"Las Palmas",
    "wof:name":"Hielo En Cubitos De Canarias S. L.",
    "wof:placetype":"venue"
},
  "geometry": {"coordinates":[-15.4246292114,27.8233947754],"type":"Point"}
}