{
  "type": "Feature",
  "properties": {
    "addr:full":"Calle de Gonzalez Hontoria, 15 S. Fernando C\u00e1diz 11100",
    "addr:housenumber":"15",
    "addr:postcode":"11100",
    "addr:street":"Calle De Gonzalez Hontoria;S. Fernando Ca\u0301Diz",
    "iso:country":"ES",
    "sg:address":"Calle de Gonzalez Hontoria, 15",
    "sg:city":"S. Fernando",
    "sg:orig_category":"Peluqueros: De Se\u00d1oras",
    "sg:phone":"+34 956 59 28 52",
    "sg:postcode":"11100",
    "sg:province":"C\u00e1diz",
    "wof:name":"Sanchez Marquez Carmen Maria",
    "wof:placetype":"venue"
},
  "geometry": {"coordinates":[-6.1970992088,36.4669418335],"type":"Point"}
}