{
  "type": "Feature",
  "properties": {
    "addr:full":"Avda Samil, S/n Redondo Pontevedra 36212",
    "addr:housenumber":"s / n",
    "addr:postcode":"36212",
    "addr:street":"Avda Samil",
    "iso:country":"ES",
    "sg:address":"Avda Samil, S/n",
    "sg:city":"Redondo",
    "sg:orig_category":"Molduras, Junquillos, Listones Y Molduras Perforadas",
    "sg:phone":"+34 986 23 61 31",
    "sg:postcode":"36212",
    "sg:province":"Pontevedra",
    "wof:name":"Garcia Fernandez Alberto",
    "wof:placetype":"venue"
},
  "geometry": {"coordinates":[-8.7656679153,42.2123451233],"type":"Point"}
}