{
  "type": "Feature",
  "properties": {
    "addr:full":"Calle de Federico Grases, 40 Madrid Madrid 28025",
    "addr:housenumber":"40",
    "addr:postcode":"madrid;28025",
    "addr:street":"Calle De Federico Grases",
    "iso:country":"ES",
    "sg:address":"Calle de Federico Grases, 40",
    "sg:city":"Madrid",
    "sg:orig_category":"Venta, Instalaci\u00d3n De Cocinas",
    "sg:phone":"+34 914 61 00 52",
    "sg:postcode":"28025",
    "sg:province":"Madrid",
    "wof:name":"Saturnino Carrasco E Hijos S.l.",
    "wof:placetype":"venue"
},
  "geometry": {"coordinates":[-3.7456638813,40.3765106201],"type":"Point"}
}