{
  "type": "Feature",
  "properties": {
    "iso:country":"ES",
    "sg:address":"Cruces, 20",
    "sg:city":"Cruces",
    "sg:orig_category":"Promotores Constructores",
    "sg:phone":"+34 981 80 31 79",
    "sg:postcode":"15980",
    "sg:province":"La Coru\u00f1a",
    "wof:name":"Miguez Ramos Benigno",
    "wof:placetype":"venue"
},
  "geometry": {"coordinates":[-8.6362838745,42.7748756409],"type":"Point"}
}