{
  "type": "Feature",
  "properties": {
    "addr:full":"Calle de Libertad, 11 Campo Criptana Ciudad Real 13610",
    "addr:housenumber":"11",
    "addr:postcode":"13610",
    "addr:street":"Calle De Libertad;Criptana",
    "iso:country":"ES",
    "sg:address":"Calle de Libertad, 11",
    "sg:city":"Campo Criptana",
    "sg:orig_category":"Turismo: Lugares, Circuitos Y Curiosidades",
    "sg:phone":"+34 926 56 37 90",
    "sg:postcode":"13610",
    "sg:province":"Ciudad Real",
    "wof:name":"Turcrip S.l.",
    "wof:placetype":"venue"
},
  "geometry": {"coordinates":[-3.1250138283,39.4066925049],"type":"Point"}
}