{
  "type": "Feature",
  "properties": {
    "iso:country":"ES",
    "sg:address":"Calle de Guillem De Castro, 136",
    "sg:city":"Valencia",
    "sg:orig_category":"Asesor\u00cda De Formaci\u00d3n Y Gesti\u00d3n De Personal",
    "sg:phone":"+34 963 92 08 19",
    "sg:postcode":"46003",
    "sg:province":"Valencia",
    "wof:name":"Bokoko Asesores S.l.",
    "wof:placetype":"venue"
},
  "geometry": {"coordinates":[-0.3805640042,39.4812393188],"type":"Point"}
}