{
  "type": "Feature",
  "properties": {
    "iso:country":"ES",
    "sg:address":"Calle de San Jose, 4",
    "sg:city":"Zumaia",
    "sg:orig_category":"Vinos Y Licores (venta Al Por Menor)",
    "sg:phone":"+34 943 86 12 57",
    "sg:postcode":"20750",
    "sg:province":"Guip\u00f9zcoa",
    "wof:name":"Iraundegui Lopez Alfoso",
    "wof:placetype":"venue"
},
  "geometry": {"coordinates":[-2.2592060566,43.2957878113],"type":"Point"}
}