{
  "type": "Feature",
  "properties": {
    "iso:country":"ES",
    "sg:address":"Calle de Sgto Moragues Vida, 24",
    "sg:city":"Palma",
    "sg:orig_category":"Papeler\u00cdas, Librer\u00cdas",
    "sg:phone":"+34 971 28 40 87",
    "sg:postcode":"07013",
    "sg:province":"Islas Baleares",
    "wof:name":"Aroca Perales Angeles",
    "wof:placetype":"venue"
},
  "geometry": {"coordinates":[2.5941238403,39.5868263245],"type":"Point"}
}