{
  "type": "Feature",
  "properties": {
    "addr:full":"Ctra. Huelva-punta Umbria, Km. 0006,0 Aljaraque Huelva 21110",
    "addr:postcode":"21110",
    "addr:street":"Ctra. Huelva-Punta Umbria Km. 0006,0",
    "iso:country":"ES",
    "sg:address":"Ctra. Huelva-punta Umbria, Km. 0006,0",
    "sg:city":"Aljaraque",
    "sg:classifiers":[
        {
            "category":"Sports & Exercise",
            "subcategory":"Golf",
            "type":"Entertainment"
        }
    ],
    "sg:phone":"+34 959 31 90 17",
    "sg:postcode":"21110",
    "sg:province":"Huelva",
    "sg:tags":[
        "y",
        "de",
        "campos",
        "clases"
    ],
    "wof:name":"Club De Golf Bellavista",
    "wof:placetype":"venue"
},
  "geometry": {"coordinates":[-7.0241990089,37.2709159851],"type":"Point"}
}