{
  "type": "Feature",
  "properties": {
    "addr:full":"Calle de Santos Justo Y Pastor, 101 Valencia Valencia 46022",
    "addr:housenumber":"101",
    "addr:postcode":"46022",
    "addr:street":"Calle De Santos Justo Y Pastor",
    "iso:country":"ES",
    "sg:address":"Calle de Santos Justo Y Pastor, 101",
    "sg:city":"Valencia",
    "sg:orig_category":"Panader\u00cdas, Panader\u00cdas",
    "sg:phone":"+34 963 72 72 07",
    "sg:postcode":"46022",
    "sg:province":"Valencia",
    "wof:name":"Esteban Lopez Francisco",
    "wof:placetype":"venue"
},
  "geometry": {"coordinates":[-0.3429169953,39.4683074951],"type":"Point"}
}