{
  "type": "Feature",
  "properties": {
    "addr:full":"Prol. Alicante, 87 Alcoi Alicante 03801",
    "addr:housenumber":"87",
    "addr:postcode":"03801",
    "addr:street":"Prol. Alicante",
    "iso:country":"ES",
    "sg:address":"Prol. Alicante, 87",
    "sg:city":"Alcoi",
    "sg:orig_category":"Rectificaci\u00d3n, Mecanizado, Fresado",
    "sg:phone":"+34 965 54 92 05",
    "sg:postcode":"03801",
    "sg:province":"Alicante",
    "wof:name":"Mecanizados Dany S.l.",
    "wof:placetype":"venue"
},
  "geometry": {"coordinates":[-0.4732739925,38.6984100342],"type":"Point"}
}