{
  "type": "Feature",
  "properties": {
    "addr:full":"Carrer de Tapioles, 3 Barcelona Barcelona 08004",
    "addr:housenumber":"3",
    "addr:postcode":"08004",
    "addr:street":"Carrer De Tapioles",
    "iso:country":"ES",
    "sg:address":"Carrer de Tapioles, 3",
    "sg:city":"Barcelona",
    "sg:orig_category":"Puertas Y Portales",
    "sg:phone":"+34 934 41 90 05",
    "sg:postcode":"08004",
    "sg:province":"Barcelona",
    "wof:name":"Talleres Y Construcciones Torres S. A.",
    "wof:placetype":"venue"
},
  "geometry": {"coordinates":[2.1652970314,41.3747558594],"type":"Point"}
}