{
  "type": "Feature",
  "properties": {
    "iso:country":"ES",
    "sg:address":"Pase Cuesta Del Escudo, S/n",
    "sg:city":"Pinar Jardin",
    "sg:orig_category":"Promotores Constructores",
    "sg:phone":"+34 921 19 65 04",
    "sg:postcode":"40142",
    "sg:province":"Segovia",
    "wof:name":"Aguas Y Usos S.a.",
    "wof:placetype":"venue"
},
  "geometry": {"coordinates":[-4.1192092896,40.9494285583],"type":"Point"}
}