{
  "type": "Feature",
  "properties": {
    "addr:full":"Pg Josep Mundet, 41 S. Antoni Calonge Girona 17252",
    "addr:housenumber":"41",
    "addr:postcode":"17252",
    "addr:street":"Pg Josep Mundet",
    "iso:country":"ES",
    "sg:address":"Pg Josep Mundet, 41",
    "sg:city":"S. Antoni Calonge",
    "sg:orig_category":"Heladeros",
    "sg:phone":"+34 972 65 07 87",
    "sg:postcode":"17252",
    "sg:province":"Girona",
    "wof:name":"Mira Galiana Manuel",
    "wof:placetype":"venue"
},
  "geometry": {"coordinates":[3.1038219929,41.8461952209],"type":"Point"}
}