{
  "type": "Feature",
  "properties": {
    "addr:full":"Calle de Marques De Teverga, 8 Aviles Asturias 33401",
    "addr:housenumber":"8",
    "addr:postcode":"33401",
    "addr:street":"Calle De Marques De Teverga",
    "iso:country":"ES",
    "sg:address":"Calle de Marques De Teverga, 8",
    "sg:city":"Aviles",
    "sg:orig_category":"Frutas Y Legumbres Frescas (al Por Mayor)",
    "sg:phone":"+34 985 56 99 44",
    "sg:postcode":"33401",
    "sg:province":"Asturias",
    "wof:name":"Frutas San Agustin S.l.",
    "wof:placetype":"venue"
},
  "geometry": {"coordinates":[-5.9242320061,43.5710372925],"type":"Point"}
}