{
  "type": "Feature",
  "properties": {
    "addr:full":"Cami Trullols, 11 Manresa Barcelona 08243",
    "addr:housenumber":"11",
    "addr:postcode":"08243",
    "addr:street":"Trullols",
    "iso:country":"ES",
    "sg:address":"Cami Trullols, 11",
    "sg:city":"Manresa",
    "sg:orig_category":"Bazares, Art\u00cdculos De Limpieza Y De Cocina (al Por Menor)",
    "sg:phone":"+34 938 78 42 71",
    "sg:postcode":"08243",
    "sg:province":"Barcelona",
    "wof:name":"Esplasf Manresa S.l.",
    "wof:placetype":"venue"
},
  "geometry": {"coordinates":[1.839040041,41.7239074707],"type":"Point"}
}