{
  "type": "Feature",
  "properties": {
    "addr:full":"Calle de Reyes Leoneses, 50 Le\u00f3n Le\u00f3n 24008",
    "addr:housenumber":"50",
    "addr:postcode":"24008",
    "addr:street":"Calle De Reyes Leoneses;Leo\u0301N",
    "iso:country":"ES",
    "sg:address":"Calle de Reyes Leoneses, 50",
    "sg:city":"Le\u00f3n",
    "sg:orig_category":"Electricidad: Instaladores",
    "sg:phone":"+34 987 80 28 85",
    "sg:postcode":"24008",
    "sg:province":"Le\u00f3n",
    "wof:name":"Sociedad Espa\u00f1ola De Montajes Industriales S.a.",
    "wof:placetype":"venue"
},
  "geometry": {"coordinates":[-5.5896291733,42.6139602661],"type":"Point"}
}