{
  "type": "Feature",
  "properties": {
    "iso:country":"ES",
    "sg:address":"Carrer de Sant Pere D'ullastre, 3",
    "sg:city":"Castellar Valles",
    "sg:orig_category":"Zapatos (al Por Menor)",
    "sg:phone":"+34 937 14 22 52",
    "sg:postcode":"08211",
    "sg:province":"Barcelona",
    "wof:name":"Cal\u00e7ats Rodana Cdad",
    "wof:placetype":"venue"
},
  "geometry": {"coordinates":[2.176789999,41.3879394531],"type":"Point"}
}