{
  "type": "Feature",
  "properties": {
    "iso:country":"ES",
    "sg:address":"Ctra. Malpica, 4",
    "sg:city":"Cebolla",
    "sg:orig_category":"Metalurgia",
    "sg:phone":"+34 925 86 62 11",
    "sg:postcode":"45550",
    "sg:province":"Toledo",
    "wof:name":"Moldeal S.a",
    "wof:placetype":"venue"
},
  "geometry": {"coordinates":[-4.5676598549,39.9334411621],"type":"Point"}
}