{
  "type": "Feature",
  "properties": {
    "iso:country":"ES",
    "sg:address":"Carrer de Muntaner, 496",
    "sg:city":"Barcelona",
    "sg:orig_category":"Doctores En Medicina",
    "sg:phone":"+34 934 17 95 53",
    "sg:postcode":"08022",
    "sg:province":"Barcelona",
    "wof:name":"Moya Mitjans Angel",
    "wof:placetype":"venue"
},
  "geometry": {"coordinates":[2.1374230385,41.4034156799],"type":"Point"}
}