{
  "type": "Feature",
  "properties": {
    "addr:full":"Ctra. Circunvalacion, S/n Marbella M\u00e1laga 29600",
    "addr:postcode":"29600",
    "addr:street":"Ctra. Circunvalacion S / N;Ma\u0301Laga",
    "iso:country":"ES",
    "sg:address":"Ctra. Circunvalacion, S/n",
    "sg:city":"Marbella",
    "sg:orig_category":"Cajas De Ahorro",
    "sg:phone":"+34 952 82 61 62",
    "sg:postcode":"29600",
    "sg:province":"M\u00e1laga",
    "wof:name":"Unicaja",
    "wof:placetype":"venue"
},
  "geometry": {"coordinates":[-4.8833007812,36.5079956055],"type":"Point"}
}