{
  "type": "Feature",
  "properties": {
    "addr:full":"Calle de Ramon Y Cajal, 32 Cuarte Huerva Zaragoza 50410",
    "addr:housenumber":"32",
    "addr:postcode":"50410",
    "addr:street":"Calle De Ramon Y Cajal",
    "iso:country":"ES",
    "sg:address":"Calle de Ramon Y Cajal, 32",
    "sg:city":"Cuarte Huerva",
    "sg:orig_category":"Asesor\u00cda Sobre Comunicaci\u00d3n De Empresas",
    "sg:phone":"+34 976 50 33 32",
    "sg:postcode":"50410",
    "sg:province":"Zaragoza",
    "wof:name":"Gimenez Gonzalez Jose Luis",
    "wof:placetype":"venue"
},
  "geometry": {"coordinates":[-0.9289579988,41.5892753601],"type":"Point"}
}