{
  "type": "Feature",
  "properties": {
    "addr:full":"Carrer de Riu Ebre, 17 Prat Llobregat Barcelona 08820",
    "addr:housenumber":"17",
    "addr:postcode":"08820",
    "addr:street":"Carrer De Riu Ebre;Llobregat",
    "iso:country":"ES",
    "sg:address":"Carrer de Riu Ebre, 17",
    "sg:city":"Prat Llobregat",
    "sg:orig_category":"Asociaciones, Organismos Culturales Y Socioeducativos",
    "sg:phone":"+34 933 70 52 22",
    "sg:postcode":"08820",
    "sg:province":"Barcelona",
    "wof:name":"Penya Barcelonista Quarta Lliga",
    "wof:placetype":"venue"
},
  "geometry": {"coordinates":[2.0895600319,41.3188209534],"type":"Point"}
}