{
  "type": "Feature",
  "properties": {
    "addr:full":"Rua Arxentina, 1 Betanzos La Coru\u00f1a 15300",
    "addr:housenumber":"1",
    "addr:postcode":"15300",
    "addr:street":"Rua Arxentina;La",
    "iso:country":"ES",
    "sg:address":"Rua Arxentina, 1",
    "sg:city":"Betanzos",
    "sg:orig_category":"Centros Empresariales",
    "sg:phone":"+34 981 77 45 74",
    "sg:postcode":"15300",
    "sg:province":"La Coru\u00f1a",
    "wof:name":"Asociacion De Empresarios De Comercio De Betanzos",
    "wof:placetype":"venue"
},
  "geometry": {"coordinates":[-8.2150774002,43.2839660645],"type":"Point"}
}