{
  "type": "Feature",
  "properties": {
    "addr:full":"Ctra Sevilla, Km. 0002,4 Badajoz Badajoz 06009",
    "addr:postcode":"06009",
    "addr:street":"Ctra Sevilla Km. 0002,4",
    "iso:country":"ES",
    "sg:address":"Ctra Sevilla, Km. 0002,4",
    "sg:city":"Badajoz",
    "sg:orig_category":"Negocio De Materiales De Construcci\u00d3n",
    "sg:phone":"+34 924 24 50 06",
    "sg:postcode":"06009",
    "sg:province":"Badajoz",
    "wof:name":"Almacenes Nieto S.l.",
    "wof:placetype":"venue"
},
  "geometry": {"coordinates":[-6.9572467804,38.8701210022],"type":"Point"}
}