{
  "type": "Feature",
  "properties": {
    "addr:full":"Paduleta Kalea, 47 Jundiz \u00c1lava 01015",
    "addr:housenumber":"47",
    "addr:postcode":"01015",
    "addr:street":"Paduleta Kalea;A\u0301Lava",
    "iso:country":"ES",
    "sg:address":"Paduleta Kalea, 47",
    "sg:city":"Jundiz",
    "sg:orig_category":"Electricidad, Electr\u00d3nica: Suministros (al Por Menor)",
    "sg:phone":"+34 945 20 09 61",
    "sg:postcode":"01015",
    "sg:province":"\u00c1lava",
    "sg:website":"www.luznor.com",
    "wof:name":"Luznor Desarrollos Electronicos S L",
    "wof:placetype":"venue"
},
  "geometry": {"coordinates":[-6.1999697685,43.3617782593],"type":"Point"}
}