{
  "type": "Feature",
  "properties": {
    "iso:country":"ES",
    "sg:address":"Calle de Cebreros, 90",
    "sg:city":"Madrid",
    "sg:orig_category":"Asociaciones Y Clubs Deportivos",
    "sg:phone":"+34 915 26 51 68",
    "sg:postcode":"28011",
    "sg:province":"Madrid",
    "wof:name":"Ortega Ca\u00f1as Fernando",
    "wof:placetype":"venue"
},
  "geometry": {"coordinates":[-3.7496852875,40.4043312073],"type":"Point"}
}