{
  "type": "Feature",
  "properties": {
    "iso:country":"ES",
    "sg:address":"C/ Victoria (la), 1",
    "sg:city":"Elche",
    "sg:orig_category":"Ropa Para Se\u00d1oras (al Por Menor)",
    "sg:phone":"+34 965 42 07 79",
    "sg:postcode":"03202",
    "sg:province":"Alicante",
    "wof:name":"Ruescu Pret A Porter S. L.",
    "wof:placetype":"venue"
},
  "geometry": {"coordinates":[-0.6975809932,38.26587677],"type":"Point"}
}