{
  "type": "Feature",
  "properties": {
    "iso:country":"ES",
    "sg:address":"Pla\u00c7 Mn Segura, 1",
    "sg:city":"Igualada",
    "sg:orig_category":"Reciclaje, Tratamiento De Tejidos",
    "sg:phone":"+34 938 03 40 50",
    "sg:postcode":"08700",
    "sg:province":"Barcelona",
    "wof:name":"Acabatex S. A.",
    "wof:placetype":"venue"
},
  "geometry": {"coordinates":[1.612949,41.584919],"type":"Point"}
}