{
  "type": "Feature",
  "properties": {
    "addr:full":"Carrer de Antiquaris, 2 Reus Tarragona 43205",
    "addr:housenumber":"2",
    "addr:postcode":"43205",
    "addr:street":"Carrer De Antiquaris",
    "iso:country":"ES",
    "sg:address":"Carrer de Antiquaris, 2",
    "sg:city":"Reus",
    "sg:orig_category":"Confecci\u00d3n De Guantes",
    "sg:phone":"+34 977 75 43 67",
    "sg:postcode":"43205",
    "sg:province":"Tarragona",
    "wof:name":"Clavaguera Comas Eudald",
    "wof:placetype":"venue"
},
  "geometry": {"coordinates":[1.113361001,41.1446342468],"type":"Point"}
}