{
  "type": "Feature",
  "properties": {
    "iso:country":"ES",
    "sg:address":"Avda Europa, 3",
    "sg:city":"Sonseca",
    "sg:orig_category":"Fabricaci\u00d3n De Cortinas Y Visillos",
    "sg:phone":"+34 925 38 26 60",
    "sg:postcode":"45100",
    "sg:province":"Toledo",
    "wof:name":"Cortinas Sonseca S.l.l.",
    "wof:placetype":"venue"
},
  "geometry": {"coordinates":[-3.9731891155,39.6861381531],"type":"Point"}
}