{
  "type": "Feature",
  "properties": {
    "addr:full":"Rond Sancti Spiritus, 17 Salamanca Salamanca 37001",
    "addr:housenumber":"17",
    "addr:postcode":"37001",
    "addr:street":"Rond Sancti Spiritus",
    "iso:country":"ES",
    "sg:address":"Rond Sancti Spiritus, 17",
    "sg:city":"Salamanca",
    "sg:orig_category":"Venta, Localizaci\u00d3n, Reparaci\u00d3n De Material E Instrumental M\u00c9dico",
    "sg:phone":"+34 923 26 34 38",
    "sg:postcode":"37001",
    "sg:province":"Salamanca",
    "wof:name":"Acosta Piriz Emilio",
    "wof:placetype":"venue"
},
  "geometry": {"coordinates":[-5.6588439941,40.966468811],"type":"Point"}
}