{
  "type": "Feature",
  "properties": {
    "iso:country":"ES",
    "sg:address":"Calle de San Agustin, 27",
    "sg:city":"Palma Condado",
    "sg:orig_category":"Empresas De Carpinter\u00cda De Madera",
    "sg:phone":"+34 959 40 05 15",
    "sg:postcode":"21700",
    "sg:province":"Huelva",
    "wof:name":"Herrera Lagares Manuel",
    "wof:placetype":"venue"
},
  "geometry": {"coordinates":[-6.5514059067,37.3840560913],"type":"Point"}
}