{
  "type": "Feature",
  "properties": {
    "addr:full":"Carr Carme, 4 Badalona Barcelona 08911",
    "addr:housenumber":"4",
    "addr:postcode":"08911",
    "addr:street":"Carr Carme",
    "iso:country":"ES",
    "sg:address":"Carr Carme, 4",
    "sg:city":"Badalona",
    "sg:orig_category":"Centros De Salud",
    "sg:phone":"+34 934 64 48 01",
    "sg:postcode":"08911",
    "sg:province":"Barcelona",
    "wof:name":"Reflexologia Celular Aplicaciones Terapeuticas S.l.",
    "wof:placetype":"venue"
},
  "geometry": {"coordinates":[2.2488999367,41.4511375427],"type":"Point"}
}