{
  "type": "Feature",
  "properties": {
    "iso:country":"ES",
    "sg:address":"Calle de Padre Salvador Barri, 2",
    "sg:city":"Onda",
    "sg:orig_category":"Reposter\u00cdas",
    "sg:phone":"+34 964 60 05 90",
    "sg:postcode":"12200",
    "sg:province":"Castell\u00f3n",
    "wof:name":"Pi\u00f1on Ucher Emilia",
    "wof:placetype":"venue"
},
  "geometry": {"coordinates":[-0.2639429867,39.9629898071],"type":"Point"}
}