{
  "type": "Feature",
  "properties": {
    "iso:country":"ES",
    "sg:address":"Calle de San Pedro, 1",
    "sg:city":"Mojonera",
    "sg:orig_category":"Ingeniero",
    "sg:phone":"+34 950 33 17 42",
    "sg:postcode":"04745",
    "sg:province":"Almer\u00eda",
    "wof:name":"Proyectos Tecnicos Fuencarral S.l",
    "wof:placetype":"venue"
},
  "geometry": {"coordinates":[-2.6832389832,36.7550010681],"type":"Point"}
}