{
  "type": "Feature",
  "properties": {
    "iso:country":"ES",
    "sg:address":"Plaz Tenis, 1",
    "sg:city":"Rodalquilar",
    "sg:orig_category":"Publicidad (soportes Y Gesti\u00d3n)",
    "sg:phone":"+34 950 38 98 18",
    "sg:postcode":"04115",
    "sg:province":"Almer\u00eda",
    "wof:name":"Rodaquilates S.l.",
    "wof:placetype":"venue"
},
  "geometry": {"coordinates":[-2.0415949821,36.8465309143],"type":"Point"}
}