{
  "type": "Feature",
  "properties": {
    "addr:full":"Calle de Santo Domingo, 9 Astorga Le\u00f3n 24700",
    "addr:housenumber":"9",
    "addr:postcode":"24700",
    "addr:street":"Calle De Santo Domingo;Leo\u0301N",
    "iso:country":"ES",
    "sg:address":"Calle de Santo Domingo, 9",
    "sg:city":"Astorga",
    "sg:orig_category":"Patatas (al Por Mayor)",
    "sg:phone":"+34 987 61 63 56",
    "sg:postcode":"24700",
    "sg:province":"Le\u00f3n",
    "wof:name":"Rodriguez Alvarez Laurentino",
    "wof:placetype":"venue"
},
  "geometry": {"coordinates":[-6.0520291328,42.4573135376],"type":"Point"}
}