{
  "type": "Feature",
  "properties": {
    "iso:country":"ES",
    "sg:address":"Calle de Doctor Sancho (del), 9",
    "sg:city":"Segovia",
    "sg:orig_category":"Restaurantes",
    "sg:phone":"+34 921 42 06 46",
    "sg:postcode":"40001",
    "sg:province":"Segovia",
    "wof:name":"Moreno Vela Vicente",
    "wof:placetype":"venue"
},
  "geometry": {"coordinates":[-4.1181435585,40.946975708],"type":"Point"}
}