{
  "type": "Feature",
  "properties": {
    "addr:full":"Calle de Kareaga Goikoa, 113 Arizgoiti Vizcaya 48970",
    "addr:housenumber":"113",
    "addr:postcode":"48970",
    "addr:street":"Calle De Kareaga Goikoa",
    "iso:country":"ES",
    "sg:address":"Calle de Kareaga Goikoa, 113",
    "sg:city":"Arizgoiti",
    "sg:orig_category":"Inmobiliaria (agencias)",
    "sg:phone":"+34 944 26 49 33",
    "sg:postcode":"48970",
    "sg:province":"Vizcaya",
    "wof:name":"Servicios Inmobiliarios Otero S.l.",
    "wof:placetype":"venue"
},
  "geometry": {"coordinates":[-2.8911149502,43.2350578308],"type":"Point"}
}