{
  "type": "Feature",
  "properties": {
    "iso:country":"ES",
    "sg:address":"Calle de Pico Del Aguila (del), 22",
    "sg:city":"Humanes De Madrid",
    "sg:orig_category":"Mec\u00c1nico Del Autom\u00d3vil",
    "sg:phone":"+34 916 04 92 62",
    "sg:postcode":"28970",
    "sg:province":"Madrid",
    "wof:name":"Eurodireccion Paris S.l.",
    "wof:placetype":"venue"
},
  "geometry": {"coordinates":[-3.8130459785,40.2612609863],"type":"Point"}
}