{
  "type": "Feature",
  "properties": {
    "addr:full":"Ctra Madrid-coru\u00d1a, S/n Villardefrades Valladolid 47860",
    "addr:housenumber":"s",
    "addr:postcode":"47860",
    "addr:street":"Ctra Madrid-Corun\u0303A;/ N",
    "iso:country":"ES",
    "sg:address":"Ctra Madrid-coru\u00d1a, S/n",
    "sg:city":"Villardefrades",
    "sg:orig_category":"Venta, Instalaci\u00d3n De Cocinas",
    "sg:phone":"+34 983 72 35 12",
    "sg:postcode":"47860",
    "sg:province":"Valladolid",
    "wof:name":"Bar Restaurante Fruser",
    "wof:placetype":"venue"
},
  "geometry": {"coordinates":[-5.2534589767,41.724521637],"type":"Point"}
}