{
  "type": "Feature",
  "properties": {
    "addr:full":"Carr Santa Clara, 31 Girona Girona 17001",
    "addr:housenumber":"31",
    "addr:postcode":"17001",
    "addr:street":"Carr Santa Clara",
    "iso:country":"ES",
    "sg:address":"Carr Santa Clara, 31",
    "sg:city":"Girona",
    "sg:orig_category":"Complementos De Vestir (al Por Menor)",
    "sg:phone":"+34 972 20 14 20",
    "sg:postcode":"17001",
    "sg:province":"Girona",
    "wof:name":"Cal\u00e7ats Peacock S.l.",
    "wof:placetype":"venue"
},
  "geometry": {"coordinates":[2.8230929375,41.9842262268],"type":"Point"}
}