{
  "type": "Feature",
  "properties": {
    "addr:full":"Calle de Obispo Beltran, 12 Castellon Castell\u00f3n 12002",
    "addr:housenumber":"12",
    "addr:postcode":"12002",
    "addr:street":"Calle De Obispo Beltran",
    "iso:country":"ES",
    "sg:address":"Calle de Obispo Beltran, 12",
    "sg:city":"Castellon",
    "sg:orig_category":"Quiropr\u00c1cticos",
    "sg:phone":"+34 964 20 62 69",
    "sg:postcode":"12002",
    "sg:province":"Castell\u00f3n",
    "wof:name":"Brive  Gilles Alain",
    "wof:placetype":"venue"
},
  "geometry": {"coordinates":[-0.0410350002,39.9827766418],"type":"Point"}
}