{
  "type": "Feature",
  "properties": {
    "addr:full":"Rua Casimiro Gomez, 16 Pontevedra Pontevedra 36002",
    "addr:housenumber":"16",
    "addr:postcode":"36002",
    "addr:street":"Rua Casimiro Gomez",
    "iso:country":"ES",
    "sg:address":"Rua Casimiro Gomez, 16",
    "sg:city":"Pontevedra",
    "sg:orig_category":"Art\u00cdculos De Quincaller\u00cda, Herramientas Y Maquinaria",
    "sg:phone":"+34 986 86 35 06",
    "sg:postcode":"36002",
    "sg:province":"Pontevedra",
    "wof:name":"Daniel Araujo Mui\u00f1os S.l.",
    "wof:placetype":"venue"
},
  "geometry": {"coordinates":[-8.6349506378,42.430305481],"type":"Point"}
}