{
  "type": "Feature",
  "properties": {
    "addr:full":"Calle de Javier Merello, S/n Costa Oeste C\u00e1diz 11500",
    "addr:housenumber":"s / n",
    "addr:postcode":"11500",
    "addr:street":"Calle De Javier Merello;Costa Oeste Ca\u0301Diz",
    "iso:country":"ES",
    "sg:address":"Calle de Javier Merello, S/n",
    "sg:city":"Costa Oeste",
    "sg:orig_category":"Doctores En Medicina",
    "sg:phone":"+34 956 87 48 56",
    "sg:postcode":"11500",
    "sg:province":"C\u00e1diz",
    "wof:name":"Gonzalez Prada Fernando",
    "wof:placetype":"venue"
},
  "geometry": {"coordinates":[-6.2197542191,36.6056632996],"type":"Point"}
}