{
  "type": "Feature",
  "properties": {
    "addr:full":"Avda Francisco Sobrin, 129 Camponaraya Le\u00f3n 24410",
    "addr:housenumber":"129",
    "addr:postcode":"24410",
    "addr:street":"Avda Francisco Sobrin",
    "iso:country":"ES",
    "sg:address":"Avda Francisco Sobrin, 129",
    "sg:city":"Camponaraya",
    "sg:orig_category":"Supermercados Y Hipermercados",
    "sg:phone":"+34 987 46 31 42",
    "sg:postcode":"24410",
    "sg:province":"Le\u00f3n",
    "wof:name":"Moran Lombardia Anastasio",
    "wof:placetype":"venue"
},
  "geometry": {"coordinates":[-6.6785559654,42.6148796082],"type":"Point"}
}