{
  "type": "Feature",
  "properties": {
    "addr:full":"Carrer de Major, 63 Mora Nova Tarragona 43770",
    "addr:housenumber":"63",
    "addr:postcode":"43770",
    "addr:street":"Carrer De Major",
    "iso:country":"ES",
    "sg:address":"Carrer de Major, 63",
    "sg:city":"Mora Nova",
    "sg:orig_category":"Hoteles",
    "sg:phone":"+34 977 40 00 33",
    "sg:postcode":"43770",
    "sg:province":"Tarragona",
    "wof:name":"Font Sangenis Maria",
    "wof:placetype":"venue"
},
  "geometry": {"coordinates":[0.6511819959,41.1013069153],"type":"Point"}
}