{
  "type": "Feature",
  "properties": {
    "iso:country":"ES",
    "sg:address":"Carrer de Alhambra, 14",
    "sg:city":"Hospitalet Llobregat",
    "sg:orig_category":"Inmobiliaria (agencias)",
    "sg:phone":"+34 932 96 65 59",
    "sg:postcode":"08902",
    "sg:province":"Barcelona",
    "sg:website":"www.ibusa.com",
    "wof:name":"Comunidad De Propietarios",
    "wof:placetype":"venue"
},
  "geometry": {"coordinates":[2.1293120384,41.362663269],"type":"Point"}
}