{
  "type": "Feature",
  "properties": {
    "addr:full":"Mirador De Tagomago(es Canar), S/n Sta. Eularia Riu Islas Baleares 07840",
    "addr:housenumber":"/ n",
    "addr:postcode":"07840",
    "addr:street":"Canar S;Islas Baleares",
    "iso:country":"ES",
    "sg:address":"Mirador De Tagomago(es Canar), S/n",
    "sg:city":"Sta. Eularia Riu",
    "sg:orig_category":"Centro De Estudios",
    "sg:phone":"+34 971 33 26 57",
    "sg:postcode":"07840",
    "sg:province":"Islas Baleares",
    "wof:name":"Bonilla Aladid Maria Cristina",
    "wof:placetype":"venue"
},
  "geometry": {"coordinates":[1.5341850519,38.9850311279],"type":"Point"}
}