{
  "type": "Feature",
  "properties": {
    "addr:full":"Av Isabel La Catolica, 106 Hospitalet Llobregat Barcelona 08905",
    "addr:housenumber":"106",
    "addr:postcode":"08905",
    "addr:street":"Av Isabel La Catolica",
    "iso:country":"ES",
    "sg:address":"Av Isabel La Catolica, 106",
    "sg:city":"Hospitalet Llobregat",
    "sg:orig_category":"Zapatos (al Por Menor)",
    "sg:phone":"+34 934 37 11 69",
    "sg:postcode":"08905",
    "sg:province":"Barcelona",
    "wof:name":"Ros Garcia Hilario",
    "wof:placetype":"venue"
},
  "geometry": {"coordinates":[2.105494976,41.372177124],"type":"Point"}
}