{
  "type": "Feature",
  "properties": {
    "iso:country":"ES",
    "sg:address":"Pje. Los Patos, 1",
    "sg:city":"Villanueva Algaidas",
    "sg:orig_category":"Cajas Para Embalar",
    "sg:phone":"+34 952 74 31 87",
    "sg:postcode":"29310",
    "sg:province":"M\u00e1laga",
    "wof:name":"Cajamar",
    "wof:placetype":"venue"
},
  "geometry": {"coordinates":[-4.4497289658,37.1840057373],"type":"Point"}
}