{
  "type": "Feature",
  "properties": {
    "addr:full":"Carrer de Proven\u00c7a, 271 Barcelona Barcelona 08008",
    "addr:housenumber":"271",
    "addr:postcode":"08008",
    "addr:street":"Carrer De Provenc\u0327A",
    "iso:country":"ES",
    "sg:address":"Carrer de Proven\u00c7a, 271",
    "sg:city":"Barcelona",
    "sg:orig_category":"Colchones (fabricaci\u00d3n, Al Por Mayor, Al Por Menor)",
    "sg:phone":"+34 932 15 32 39",
    "sg:postcode":"08008",
    "sg:province":"Barcelona",
    "wof:name":"Mu\u00f1oz Marti Juan",
    "wof:placetype":"venue"
},
  "geometry": {"coordinates":[2.1624069214,41.3956451416],"type":"Point"}
}