{
  "type": "Feature",
  "properties": {
    "iso:country":"ES",
    "sg:address":"Generalisimo Franco, 6",
    "sg:city":"Avila",
    "sg:orig_category":"Estancos",
    "sg:phone":"+34 920 21 21 45",
    "sg:postcode":"05001",
    "sg:province":"\u00c1vila",
    "wof:name":"Alvarez Sanchez Carmen",
    "wof:placetype":"venue"
},
  "geometry": {"coordinates":[-4.6980571747,40.654800415],"type":"Point"}
}