{
  "type": "Feature",
  "properties": {
    "addr:full":"Pg Til.lers, 51 Corro D'avall Barcelona 08520",
    "addr:housenumber":"51",
    "addr:postcode":"08520",
    "addr:street":"Pg Til.Lers;D'Avall Barcelona",
    "iso:country":"ES",
    "sg:address":"Pg Til.lers, 51",
    "sg:city":"Corro D'avall",
    "sg:orig_category":"Ingenier\u00cda, Centros De Estudios (industria)",
    "sg:phone":"+34 938 40 19 05",
    "sg:postcode":"08520",
    "sg:province":"Barcelona",
    "wof:name":"Rull Serrano Enrique",
    "wof:placetype":"venue"
},
  "geometry": {"coordinates":[2.1196091175,41.3895378113],"type":"Point"}
}