{
  "type": "Feature",
  "properties": {
    "iso:country":"ES",
    "sg:address":"Pl Pati Del Castell, 14",
    "sg:city":"Valls",
    "sg:orig_category":"Abogados",
    "sg:phone":"+34 977 61 31 81",
    "sg:postcode":"43800",
    "sg:province":"Tarragona",
    "wof:name":"Guasch Cunillera Maria Elena",
    "wof:placetype":"venue"
},
  "geometry": {"coordinates":[1.2217458487,41.3045082092],"type":"Point"}
}