{
  "type": "Feature",
  "properties": {
    "iso:country":"ES",
    "sg:address":"Calle de Luis Del Valle, 11",
    "sg:city":"Zaragoza",
    "sg:orig_category":"Fotocopias, Reprograf\u00cda",
    "sg:phone":"+34 976 35 29 27",
    "sg:postcode":"50005",
    "sg:province":"Zaragoza",
    "wof:name":"Arrondo S.l.",
    "wof:placetype":"venue"
},
  "geometry": {"coordinates":[-0.8952693939,41.6432800293],"type":"Point"}
}