{
  "type": "Feature",
  "properties": {
    "iso:country":"ES",
    "sg:address":"Calle de Almendro, 22",
    "sg:city":"Leci\u00d1ena",
    "sg:orig_category":"Tapiceros Y Tapiceros",
    "sg:phone":"+34 976 16 60 96",
    "sg:postcode":"50160",
    "sg:province":"Zaragoza",
    "wof:name":"Letosa Marcen Esther",
    "wof:placetype":"venue"
},
  "geometry": {"coordinates":[-0.6145918965,41.797542572],"type":"Point"}
}