{
  "type": "Feature",
  "properties": {
    "iso:country":"ES",
    "sg:address":"Calle de Hernandez Rubin, 9",
    "sg:city":"Madrid",
    "sg:orig_category":"Cursos Particulares, Asistencia Escolar",
    "sg:phone":"+34 913 88 58 16",
    "sg:postcode":"28043",
    "sg:province":"Madrid",
    "wof:name":"Santano Leon Daniel",
    "wof:placetype":"venue"
},
  "geometry": {"coordinates":[-3.6498179436,40.4490699768],"type":"Point"}
}