{
  "type": "Feature",
  "properties": {
    "iso:country":"ES",
    "sg:address":"Calle de Campoamor, 16",
    "sg:city":"Orihuela",
    "sg:orig_category":"Frutos Y Legumbres",
    "sg:phone":"+34 965 30 41 54",
    "sg:postcode":"03300",
    "sg:province":"Alicante",
    "wof:name":"Agroservicios Paredes Sl",
    "wof:placetype":"venue"
},
  "geometry": {"coordinates":[-0.9432436824,38.0833244324],"type":"Point"}
}