{
  "type": "Feature",
  "properties": {
    "iso:country":"ES",
    "sg:address":"Calle de Avila, 15",
    "sg:city":"Mostoles",
    "sg:orig_category":"Inform\u00c1tica: Redes",
    "sg:phone":"+34 916 17 27 03",
    "sg:postcode":"28931",
    "sg:province":"Madrid",
    "wof:name":"Irca Comunicaciones S.l.",
    "wof:placetype":"venue"
},
  "geometry": {"coordinates":[-3.8593733311,40.3251686096],"type":"Point"}
}