{
  "type": "Feature",
  "properties": {
    "iso:country":"ES",
    "sg:address":"Avda Pe\u00d1ascales, 18",
    "sg:city":"Matas-pinar-monte Rozas",
    "sg:orig_category":"Puertas Y Portales",
    "sg:phone":"+34 916 30 08 37",
    "sg:postcode":"28290",
    "sg:province":"Madrid",
    "wof:name":"Lopez Y Ruescas S.l.",
    "wof:placetype":"venue"
},
  "geometry": {"coordinates":[-3.9152576923,40.5226135254],"type":"Point"}
}