{
  "type": "Feature",
  "properties": {
    "addr:full":"Calle de Ramon J.sender, 1 Zaragoza Zaragoza 50017",
    "addr:housenumber":"1",
    "addr:postcode":"50017",
    "addr:street":"Calle De Ramon J.Sender",
    "iso:country":"ES",
    "sg:address":"Calle de Ramon J.sender, 1",
    "sg:city":"Zaragoza",
    "sg:orig_category":"Electricidad: Instaladores",
    "sg:phone":"+34 976 53 48 10",
    "sg:postcode":"50017",
    "sg:province":"Zaragoza",
    "wof:name":"Instalaciones Y Montajes Electricos Imegal S.l.",
    "wof:placetype":"venue"
},
  "geometry": {"coordinates":[-0.9187110066,41.6560058594],"type":"Point"}
}