{
  "type": "Feature",
  "properties": {
    "iso:country":"ES",
    "sg:address":"Calle de Azafranal, 55",
    "sg:city":"Salamanca",
    "sg:orig_category":"Ropa Para Ni\u00d1os (al Por Menor)",
    "sg:phone":"+34 923 26 52 75",
    "sg:postcode":"37001",
    "sg:province":"Salamanca",
    "wof:name":"Almacenes Runi S.l.",
    "wof:placetype":"venue"
},
  "geometry": {"coordinates":[-5.6590876579,40.9679260254],"type":"Point"}
}