{
  "type": "Feature",
  "properties": {
    "addr:full":"Avda Italia, 44 Salamanca Salamanca 37006",
    "addr:housenumber":"44",
    "addr:postcode":"37006",
    "addr:street":"Avda Italia",
    "iso:country":"ES",
    "sg:address":"Avda Italia, 44",
    "sg:city":"Salamanca",
    "sg:orig_category":"Estancos",
    "sg:phone":"+34 923 25 71 88",
    "sg:postcode":"37006",
    "sg:province":"Salamanca",
    "wof:name":"Blanco Abril Maria Pilar",
    "wof:placetype":"venue"
},
  "geometry": {"coordinates":[-5.6666579247,40.9717903137],"type":"Point"}
}