{
  "type": "Feature",
  "properties": {
    "iso:country":"ES",
    "sg:address":"Arquitectura, 8",
    "sg:city":"Can Cuias",
    "sg:orig_category":"Grafistas",
    "sg:phone":"+34 935 75 28 76",
    "sg:postcode":"08110",
    "sg:province":"Barcelona",
    "wof:name":"Graficas S.cv.",
    "wof:placetype":"venue"
},
  "geometry": {"coordinates":[2.1683700085,41.4672966003],"type":"Point"}
}