{
  "type": "Feature",
  "properties": {
    "iso:country":"ES",
    "sg:address":"Calle de Elda, 7",
    "sg:city":"Villena",
    "sg:orig_category":"Estudios, Instalaci\u00d3n De Climatizaci\u00d3n",
    "sg:phone":"+34 965 80 00 67",
    "sg:postcode":"03400",
    "sg:province":"Alicante",
    "sg:website":"www.descals.com",
    "wof:name":"Carlos Descals S. L.",
    "wof:placetype":"venue"
},
  "geometry": {"coordinates":[-0.8643050194,38.6345787048],"type":"Point"}
}