{
  "type": "Feature",
  "properties": {
    "addr:full":"Ca\u00f1ada, S/n Belver Montes Zamora 49830",
    "addr:housenumber":"/ n",
    "addr:postcode":"49830",
    "addr:street":"Can\u0303Ada S",
    "iso:country":"ES",
    "sg:address":"Ca\u00f1ada, S/n",
    "sg:city":"Belver Montes",
    "sg:orig_category":"Producci\u00d3n, Comercio De Cereales",
    "sg:phone":"+34 980 58 31 12",
    "sg:postcode":"49830",
    "sg:province":"Zamora",
    "wof:name":"Almacenes Ceatrans S. A.",
    "wof:placetype":"venue"
},
  "geometry": {"coordinates":[-5.4546709061,41.7239227295],"type":"Point"}
}