{
  "type": "Feature",
  "properties": {
    "addr:full":"Carrer de Roger De Flor, 119 Barcelona Barcelona 08013",
    "addr:housenumber":"119",
    "addr:postcode":"08013",
    "addr:street":"Carrer De Roger De Flor",
    "iso:country":"ES",
    "sg:address":"Carrer de Roger De Flor, 119",
    "sg:city":"Barcelona",
    "sg:orig_category":"Laboratorios Y Trabajos De Fotograf\u00cda, V\u00cddeo Y Cine",
    "sg:phone":"+34 932 45 63 47",
    "sg:postcode":"08013",
    "sg:province":"Barcelona",
    "wof:name":"Multifoto S.l.",
    "wof:placetype":"venue"
},
  "geometry": {"coordinates":[2.1759560108,41.3960914612],"type":"Point"}
}