{
  "type": "Feature",
  "properties": {
    "iso:country":"ES",
    "sg:address":"Rond Europa, 52",
    "sg:city":"Vilanova I La Geltru",
    "sg:orig_category":"Caf\u00c9s, Bares, Cervecer\u00cdas",
    "sg:phone":"+34 938 11 56 13",
    "sg:postcode":"08800",
    "sg:province":"Barcelona",
    "wof:name":"Forns I Cafeteries De L'italia S.l.",
    "wof:placetype":"venue"
},
  "geometry": {"coordinates":[1.7394020557,41.2286186218],"type":"Point"}
}