{
  "type": "Feature",
  "properties": {
    "addr:full":"C. C. Monte Biarritz, 13 Estepona M\u00e1laga 29680",
    "addr:housenumber":"13",
    "addr:postcode":"29680",
    "addr:street":"Biarritz",
    "iso:country":"ES",
    "sg:address":"C. C. Monte Biarritz, 13",
    "sg:city":"Estepona",
    "sg:orig_category":"Asesor\u00cda Sobre Comunicaci\u00d3n De Empresas",
    "sg:phone":"+34 952 93 70 41",
    "sg:postcode":"29680",
    "sg:province":"M\u00e1laga",
    "wof:name":"Asegem Sl",
    "wof:placetype":"venue"
},
  "geometry": {"coordinates":[-5.014673233,36.4755210876],"type":"Point"}
}