{
  "type": "Feature",
  "properties": {
    "iso:country":"ES",
    "sg:address":"Calle de Genciana, 46",
    "sg:city":"Madrid",
    "sg:orig_category":"Arreglo, Reparaci\u00d3n, Piezas Sueltas De Televisi\u00d3n, V\u00cddeo, Hi",
    "sg:phone":"+34 913 23 26 69",
    "sg:postcode":"28039",
    "sg:province":"Madrid",
    "wof:name":"De La Calle Garcia Antonio",
    "wof:placetype":"venue"
},
  "geometry": {"coordinates":[-3.702796936,40.4661102295],"type":"Point"}
}