{
  "type": "Feature",
  "properties": {
    "addr:full":"Ctra. Sevilla, S/n Villalba Alcor Huelva 21860",
    "addr:housenumber":"s",
    "addr:postcode":"21860",
    "addr:street":"Ctra. Sevilla;/ N",
    "iso:country":"ES",
    "sg:address":"Ctra. Sevilla, S/n",
    "sg:city":"Villalba Alcor",
    "sg:orig_category":"Chapister\u00cda",
    "sg:phone":"+34 959 42 13 00",
    "sg:postcode":"21860",
    "sg:province":"Huelva",
    "wof:name":"Salhani  Mohamed",
    "wof:placetype":"venue"
},
  "geometry": {"coordinates":[-6.4754738808,37.397064209],"type":"Point"}
}