{
  "type": "Feature",
  "properties": {
    "iso:country":"ES",
    "sg:address":"Luga Mu\u00d1as De Arriba, S/n",
    "sg:city":"Mu\u00f1as",
    "sg:classifiers":[
        {
            "category":"Taxi",
            "type":"Transportation"
        }
    ],
    "sg:phone":"+34 985 47 70 87",
    "sg:postcode":"33784",
    "sg:province":"Asturias",
    "wof:name":"Pelaez Menendez Acelino",
    "wof:placetype":"venue"
},
  "geometry": {"coordinates":[-6.397436142,43.47498703],"type":"Point"}
}