{
  "type": "Feature",
  "properties": {
    "addr:full":"Avda Madrid, S/n Sotillo Adrada \u00c1vila 05420",
    "addr:housenumber":"s",
    "addr:postcode":"05420",
    "addr:street":"Avda Madrid;/ N Sotillo;A\u0301Vila",
    "iso:country":"ES",
    "sg:address":"Avda Madrid, S/n",
    "sg:city":"Sotillo Adrada",
    "sg:orig_category":"Comercio De Piezas De Recambio Y De Accesorios De Veh\u00cdculos, Veh\u00cdculos Industriales",
    "sg:phone":"+34 918 66 02 55",
    "sg:postcode":"05420",
    "sg:province":"\u00c1vila",
    "wof:name":"Rac Madrid S.l.l.",
    "wof:placetype":"venue"
},
  "geometry": {"coordinates":[-4.5871610641,40.2936058044],"type":"Point"}
}