{
  "type": "Feature",
  "properties": {
    "iso:country":"ES",
    "sg:address":"Calle de Garcia Moreno, 14",
    "sg:city":"Salamanca",
    "sg:orig_category":"Tapicer\u00cdas",
    "sg:phone":"+34 923 25 15 34",
    "sg:postcode":"37006",
    "sg:province":"Salamanca",
    "wof:name":"Blanco Limpiezas Tapicerias C.b.",
    "wof:placetype":"venue"
},
  "geometry": {"coordinates":[-5.6648430824,40.971786499],"type":"Point"}
}