{
  "type": "Feature",
  "properties": {
    "addr:full":"Calle de Salvador Ortiz Barragan, 19 Bailen Ja\u00e9n 23710",
    "addr:housenumber":"19",
    "addr:postcode":"23710",
    "addr:street":"Calle De Salvador Ortiz Barragan;Jae\u0301N",
    "iso:country":"ES",
    "sg:address":"Calle de Salvador Ortiz Barragan, 19",
    "sg:city":"Bailen",
    "sg:orig_category":"Arreglo, Reparaci\u00d3n, Piezas Sueltas De Televisi\u00d3n, V\u00cddeo, Hi",
    "sg:phone":"+34 953 67 15 60",
    "sg:postcode":"23710",
    "sg:province":"Ja\u00e9n",
    "wof:name":"Selgas Bao Carlos",
    "wof:placetype":"venue"
},
  "geometry": {"coordinates":[-3.7829298973,38.0962905884],"type":"Point"}
}