{
  "type": "Feature",
  "properties": {
    "iso:country":"ES",
    "sg:address":"Pase Ribalta, 10",
    "sg:city":"Castellon",
    "sg:orig_category":"M\u00c9dicos: Gastroenterolog\u00cda Y Hepatolog\u00cda (aparato Digestivo)",
    "sg:phone":"+34 964 21 20 31",
    "sg:postcode":"12004",
    "sg:province":"Castell\u00f3n",
    "wof:name":"Maqueda Martos Manuel",
    "wof:placetype":"venue"
},
  "geometry": {"coordinates":[-0.0279866997,40.0120239258],"type":"Point"}
}