{
  "type": "Feature",
  "properties": {
    "iso:country":"ES",
    "sg:address":"Carrer de Mallorca, 43",
    "sg:city":"Cardedeu",
    "sg:orig_category":"Asesor\u00cda Sobre Comunicaci\u00d3n De Empresas",
    "sg:phone":"+34 938 41 88 35",
    "sg:postcode":"08440",
    "sg:province":"Barcelona",
    "wof:name":"Estudi Comptable Empresarial S.l.",
    "wof:placetype":"venue"
},
  "geometry": {"coordinates":[2.3674030304,41.6404418945],"type":"Point"}
}