{
  "type": "Feature",
  "properties": {
    "iso:country":"ES",
    "sg:address":"Calle de Francisco Cabal, 1",
    "sg:city":"Muros",
    "sg:orig_category":"Empresas De Carpinter\u00cda",
    "sg:phone":"+34 985 58 34 20",
    "sg:postcode":"33138",
    "sg:province":"Asturias",
    "wof:name":"Alonso Rodriguez Ana Luz",
    "wof:placetype":"venue"
},
  "geometry": {"coordinates":[-6.1097531319,43.5422363281],"type":"Point"}
}