{
  "type": "Feature",
  "properties": {
    "addr:full":"Carrer de Cristobal De Moura, 118 Barcelona Barcelona 08019",
    "addr:housenumber":"118",
    "addr:postcode":"08019",
    "addr:street":"Carrer De Cristobal De Moura",
    "iso:country":"ES",
    "sg:address":"Carrer de Cristobal De Moura, 118",
    "sg:city":"Barcelona",
    "sg:orig_category":"Empresas De Carpinter\u00cda Met\u00c1lica",
    "sg:phone":"+34 933 08 04 41",
    "sg:postcode":"08019",
    "sg:province":"Barcelona",
    "wof:name":"Servitja Vives Elvira",
    "wof:placetype":"venue"
},
  "geometry": {"coordinates":[2.2076950073,41.4118347168],"type":"Point"}
}