{
  "type": "Feature",
  "properties": {
    "iso:country":"ES",
    "sg:address":"Plaz Fernando Beladiez, 2",
    "sg:city":"Guadalajara",
    "sg:orig_category":"Internados & Ense\u00d1anza Privada",
    "sg:phone":"+34 949 22 04 00",
    "sg:postcode":"19001",
    "sg:province":"Guadalajara",
    "wof:name":"Casa De Agustinos Recoletos-colegio Sagrado Corazon",
    "wof:placetype":"venue"
},
  "geometry": {"coordinates":[-3.1642420292,40.6328163147],"type":"Point"}
}