{
  "type": "Feature",
  "properties": {
    "iso:country":"ES",
    "sg:address":"Calle de Virrey Morcillo, 23",
    "sg:city":"Villarrobledo",
    "sg:orig_category":"Centros De Coordinaci\u00d3n",
    "sg:phone":"+34 967 14 02 47",
    "sg:postcode":"02600",
    "sg:province":"Albacete",
    "wof:name":"Losa Montejano Diega",
    "wof:placetype":"venue"
},
  "geometry": {"coordinates":[-2.5997619629,39.2665023804],"type":"Point"}
}