{
  "type": "Feature",
  "properties": {
    "addr:full":"Afueras, S/n Castejon Sos Huesca 22466",
    "addr:housenumber":"/ n",
    "addr:postcode":"22466",
    "addr:street":"Afueras S;Sos Huesca",
    "iso:country":"ES",
    "sg:address":"Afueras, S/n",
    "sg:city":"Castejon Sos",
    "sg:orig_category":"Distribuci\u00d3n De Petr\u00d3leo Y Derivados",
    "sg:phone":"+34 974 55 30 59",
    "sg:postcode":"22466",
    "sg:province":"Huesca",
    "wof:name":"More Barrabes Concepcion",
    "wof:placetype":"venue"
},
  "geometry": {"coordinates":[0.509468019,42.5239334106],"type":"Point"}
}