{
  "type": "Feature",
  "properties": {
    "iso:country":"ES",
    "sg:address":"Pla\u00c7 Pla\u00c7a, Sa, 17",
    "sg:city":"Sineu",
    "sg:orig_category":"Caf\u00c9s, Bares, Cervecer\u00cdas",
    "sg:phone":"+34 971 52 06 64",
    "sg:postcode":"07510",
    "sg:province":"Islas Baleares",
    "wof:name":"Cafeteria Zaplaza Cb",
    "wof:placetype":"venue"
},
  "geometry": {"coordinates":[3.0101060867,39.6430702209],"type":"Point"}
}