{
  "type": "Feature",
  "properties": {
    "iso:country":"ES",
    "sg:address":"Ptge Pins Melis, 11",
    "sg:city":"Garraf Ii Urbanitzacio",
    "sg:orig_category":"Contenedores (mercanc\u00cdas)",
    "sg:phone":"+34 936 45 80 61",
    "sg:postcode":"08870",
    "sg:province":"Barcelona",
    "wof:name":"Garcia Labrador Maria Jose",
    "wof:placetype":"venue"
},
  "geometry": {"coordinates":[1.9330810308,41.2650642395],"type":"Point"}
}