{
  "type": "Feature",
  "properties": {
    "iso:country":"ES",
    "sg:address":"Pda. Horta D'amunt, S/n",
    "sg:city":"Balaguer",
    "sg:orig_category":"Agricultura: Abastecimiento Y Cosechado (negocio)",
    "sg:phone":"+34 973 44 64 65",
    "sg:postcode":"25600",
    "sg:province":"Lleida",
    "wof:name":"Oliva Puigpelat Matias",
    "wof:placetype":"venue"
},
  "geometry": {"coordinates":[0.8071500063,41.7895889282],"type":"Point"}
}