{
  "type": "Feature",
  "properties": {
    "addr:full":"Calle de Centelles, Los, 58 Valencia Valencia 46006",
    "addr:housenumber":"58",
    "addr:postcode":"46006",
    "addr:street":"Calle De Centelles Los",
    "iso:country":"ES",
    "sg:address":"Calle de Centelles, Los, 58",
    "sg:city":"Valencia",
    "sg:orig_category":"Abogados",
    "sg:phone":"+34 963 73 69 62",
    "sg:postcode":"46006",
    "sg:province":"Valencia",
    "wof:name":"Herrero Medrano S.l.",
    "wof:placetype":"venue"
},
  "geometry": {"coordinates":[-0.3754388988,39.4582633972],"type":"Point"}
}