{
  "type": "Feature",
  "properties": {
    "iso:country":"ES",
    "sg:address":"Calle de Batalla Del Salado, 49",
    "sg:city":"Madrid",
    "sg:orig_category":"Mec\u00c1nico Del Autom\u00d3vil",
    "sg:phone":"+34 914 68 60 09",
    "sg:postcode":"28045",
    "sg:province":"Madrid",
    "wof:name":"Trejo Dominguez Francisco",
    "wof:placetype":"venue"
},
  "geometry": {"coordinates":[-3.696449995,40.3979873657],"type":"Point"}
}