{
  "type": "Feature",
  "properties": {
    "addr:full":"Calle de Angel Galindo, 31 Alcantarilla Murcia 30820",
    "addr:housenumber":"31",
    "addr:postcode":"30820",
    "addr:street":"Calle De Angel Galindo",
    "iso:country":"ES",
    "sg:address":"Calle de Angel Galindo, 31",
    "sg:city":"Alcantarilla",
    "sg:orig_category":"Administradores De Bienes Y Delegados De Comunidades De Propietarios",
    "sg:phone":"+34 968 89 46 13",
    "sg:postcode":"30820",
    "sg:province":"Murcia",
    "wof:name":"A.r.c.o.m Fincas S.l.",
    "wof:placetype":"venue"
},
  "geometry": {"coordinates":[-1.2173844576,37.9682998657],"type":"Point"}
}