{
  "type": "Feature",
  "properties": {
    "addr:full":"Calle de Real (del), 3 Colmenar Viejo Madrid 28770",
    "addr:postcode":"28770",
    "addr:street":"Calle De Real Del",
    "iso:country":"ES",
    "sg:address":"Calle de Real (del), 3",
    "sg:city":"Colmenar Viejo",
    "sg:orig_category":"Peluqueros: De Se\u00d1oras",
    "sg:phone":"+34 918 46 36 69",
    "sg:postcode":"28770",
    "sg:province":"Madrid",
    "wof:name":"Salon De Belleza Mar S.l.",
    "wof:placetype":"venue"
},
  "geometry": {"coordinates":[-3.7660489082,40.6593208313],"type":"Point"}
}