{
  "type": "Feature",
  "properties": {
    "addr:full":"Avda Comunidad De Madrid (de La), 3 Pozuelo De Alarcon Madrid 28224",
    "addr:postcode":"28224",
    "addr:street":"Avda Comunidad",
    "iso:country":"ES",
    "sg:address":"Avda Comunidad De Madrid (de La), 3",
    "sg:city":"Pozuelo De Alarcon",
    "sg:orig_category":"Caf\u00c9s, Bares, Cervecer\u00cdas",
    "sg:phone":"+34 913 52 23 79",
    "sg:postcode":"28224",
    "sg:province":"Madrid",
    "wof:name":"Gonzalez Perez Felix",
    "wof:placetype":"venue"
},
  "geometry": {"coordinates":[-3.7929079533,40.4388961792],"type":"Point"}
}