{
  "type": "Feature",
  "properties": {
    "iso:country":"ES",
    "sg:address":"Avda Sierra De Gata, 12",
    "sg:city":"Perales Del Puerto",
    "sg:orig_category":"Administraciones Regionales, Departamentales Y Locales",
    "sg:phone":"+34 927 51 41 64",
    "sg:postcode":"10896",
    "sg:province":"C\u00e1ceres",
    "wof:name":"Ayuntamiento De Perales Del Puerto",
    "wof:placetype":"venue"
},
  "geometry": {"coordinates":[-6.6819963455,40.1578521729],"type":"Point"}
}