{
  "type": "Feature",
  "properties": {
    "addr:full":"Calle de Clavo (del), S/n Barca De La Florida C\u00e1diz 11570",
    "addr:postcode":"11570",
    "addr:street":"Calle De Clavo Del S / N Barca De La;Ca\u0301Diz",
    "iso:country":"ES",
    "sg:address":"Calle de Clavo (del), S/n",
    "sg:city":"Barca De La Florida",
    "sg:orig_category":"Supermercados Y Hipermercados",
    "sg:phone":"+34 956 39 07 01",
    "sg:postcode":"11570",
    "sg:province":"C\u00e1diz",
    "wof:name":"Cirera Molina Jose Antonio",
    "wof:placetype":"venue"
},
  "geometry": {"coordinates":[-5.9355640411,36.6484107971],"type":"Point"}
}