{
  "type": "Feature",
  "properties": {
    "iso:country":"ES",
    "sg:address":"Pase Victoria (de La), 49",
    "sg:city":"Cordoba",
    "sg:orig_category":"M\u00c9dicos: Medicina Interna",
    "sg:phone":"+34 957 29 86 61",
    "sg:postcode":"14004",
    "sg:province":"C\u00f3rdoba",
    "wof:name":"Ballesteros Rodriguez Juan",
    "wof:placetype":"venue"
},
  "geometry": {"coordinates":[-4.7845849991,37.8822250366],"type":"Point"}
}