{
  "type": "Feature",
  "properties": {
    "iso:country":"ES",
    "sg:address":"Ctra. S'arraco, Km. 0001,5",
    "sg:city":"Sant Elm",
    "sg:orig_category":"Producci\u00d3n, Venta De Productos De Agricultura Biol\u00d3gica",
    "sg:phone":"+34 971 23 91 14",
    "sg:postcode":"07159",
    "sg:province":"Islas Baleares",
    "wof:name":"Schmidt  Edmund",
    "wof:placetype":"venue"
},
  "geometry": {"coordinates":[2.3936519623,39.5470657349],"type":"Point"}
}