{
  "type": "Feature",
  "properties": {
    "iso:country":"ES",
    "sg:address":"Villajoyosa(pol Ind Alberca), S/n",
    "sg:city":"La Nucia",
    "sg:orig_category":"Telas: Impresi\u00d3n, Tinte, Tratamiento, Transformaci\u00d3n",
    "sg:phone":"+34 965 87 04 47",
    "sg:postcode":"03530",
    "sg:province":"Alicante",
    "wof:name":"Domingo Villanueva Maria Carmen",
    "wof:placetype":"venue"
},
  "geometry": {"coordinates":[-0.1357720047,38.6007194519],"type":"Point"}
}