{
  "type": "Feature",
  "properties": {
    "addr:full":"Las Chafiras, 33 Las Chafiras Santa Cruz De Tenerife 38639",
    "addr:housenumber":"33",
    "addr:postcode":"38639",
    "addr:street":"Las Chafiras",
    "iso:country":"ES",
    "sg:address":"Las Chafiras, 33",
    "sg:city":"Las Chafiras",
    "sg:orig_category":"Muebles, Minoristas",
    "sg:phone":"+34 922 73 51 00",
    "sg:postcode":"38639",
    "sg:province":"Santa Cruz De Tenerife",
    "wof:name":"Hernandez Garcia Martin",
    "wof:placetype":"venue"
},
  "geometry": {"coordinates":[-16.6115474701,28.0350246429],"type":"Point"}
}