{
  "type": "Feature",
  "properties": {
    "iso:country":"ES",
    "sg:address":"Av Barcelona, 8",
    "sg:city":"Malgrat Mar",
    "sg:orig_category":"Bares, Piano",
    "sg:phone":"+34 937 65 36 72",
    "sg:postcode":"08380",
    "sg:province":"Barcelona",
    "wof:name":"Sola Vila Antonio",
    "wof:placetype":"venue"
},
  "geometry": {"coordinates":[2.736289978,41.6412887573],"type":"Point"}
}