{
  "type": "Feature",
  "properties": {
    "iso:country":"ES",
    "sg:address":"Calle de Pablo Iglesias, 2",
    "sg:city":"Marbella",
    "sg:orig_category":"Art\u00cdculos De Regalo (al Por Menor)",
    "sg:phone":"+34 952 77 50 84",
    "sg:postcode":"29600",
    "sg:province":"M\u00e1laga",
    "wof:name":"Parra Lares Maria Jesus",
    "wof:placetype":"venue"
},
  "geometry": {"coordinates":[-4.8771529198,36.5106811523],"type":"Point"}
}