{
  "type": "Feature",
  "properties": {
    "iso:country":"ES",
    "sg:address":"Calle de Bravo Murillo, 175",
    "sg:city":"Madrid",
    "sg:orig_category":"Parques De Atracciones Y Centros De Esparcimiento",
    "sg:phone":"+34 913 11 32 37",
    "sg:postcode":"28020",
    "sg:province":"Madrid",
    "wof:name":"Egasa Xxi S.a.",
    "wof:placetype":"venue"
},
  "geometry": {"coordinates":[-3.7030467987,40.4531936646],"type":"Point"}
}