{
  "type": "Feature",
  "properties": {
    "addr:full":"C/ Antonio Moya Albaladejo, 40 Elche Alicante 03204",
    "addr:housenumber":"40",
    "addr:postcode":"03204",
    "addr:street":"C / Antonio Moya Albaladejo",
    "iso:country":"ES",
    "sg:address":"C/ Antonio Moya Albaladejo, 40",
    "sg:city":"Elche",
    "sg:orig_category":"Supermercados Y Hipermercados",
    "sg:phone":"+34 966 63 18 66",
    "sg:postcode":"03204",
    "sg:province":"Alicante",
    "wof:name":"Hiperber Distribucion Y Logistica S.a.",
    "wof:placetype":"venue"
},
  "geometry": {"coordinates":[-0.7062960267,38.2559204102],"type":"Point"}
}