{
  "type": "Feature",
  "properties": {
    "addr:full":"Calle de San Francisco, 6 Donostia-san Sebastian Guip\u00f9zcoa 20001",
    "addr:housenumber":"6",
    "addr:postcode":"20001",
    "addr:street":"Calle De San Francisco",
    "iso:country":"ES",
    "sg:address":"Calle de San Francisco, 6",
    "sg:city":"Donostia-san Sebastian",
    "sg:orig_category":"Caf\u00c9s, Bares, Cervecer\u00cdas",
    "sg:phone":"+34 943 32 32 46",
    "sg:postcode":"20001",
    "sg:province":"Guip\u00f9zcoa",
    "wof:name":"Aldabar S.l.",
    "wof:placetype":"venue"
},
  "geometry": {"coordinates":[-1.975019455,43.3230247498],"type":"Point"}
}