{
  "type": "Feature",
  "properties": {
    "iso:country":"ES",
    "sg:address":"Carrer de Mar (la), 137",
    "sg:city":"Altea",
    "sg:orig_category":"Venta, Montaje De Neum\u00c1ticos",
    "sg:phone":"+34 965 84 40 07",
    "sg:postcode":"03590",
    "sg:province":"Alicante",
    "wof:name":"Puertas Rengel Bartolome",
    "wof:placetype":"venue"
},
  "geometry": {"coordinates":[-0.0530669987,38.5948486328],"type":"Point"}
}