{
  "type": "Feature",
  "properties": {
    "iso:country":"ES",
    "sg:address":"Av. Fisterra, 55",
    "sg:city":"Laracha",
    "sg:orig_category":"Caf\u00c9s, Bares, Cervecer\u00cdas",
    "sg:phone":"+34 981 60 55 02",
    "sg:postcode":"15145",
    "sg:province":"La Coru\u00f1a",
    "wof:name":"Campos Gonzalez Marta Maria",
    "wof:placetype":"venue"
},
  "geometry": {"coordinates":[-8.5783786774,43.2472114563],"type":"Point"}
}