{
  "type": "Feature",
  "properties": {
    "iso:country":"ES",
    "sg:address":"Carrer de Pelai, 1",
    "sg:city":"Barcelona",
    "sg:orig_category":"Psicoanalistas",
    "sg:phone":"+34 933 01 04 89",
    "sg:postcode":"08001",
    "sg:province":"Barcelona",
    "wof:name":"Uribe Visiedo Maria Isabel",
    "wof:placetype":"venue"
},
  "geometry": {"coordinates":[2.1654839516,41.3859863281],"type":"Point"}
}