{
  "type": "Feature",
  "properties": {
    "addr:full":"Plaz Campinos De Bego\u00d1a, 1 Gijon Asturias 33201",
    "addr:housenumber":"1",
    "addr:postcode":"33201",
    "iso:country":"ES",
    "sg:address":"Plaz Campinos De Bego\u00d1a, 1",
    "sg:city":"Gijon",
    "sg:orig_category":"Cl\u00cdnicas Dentales",
    "sg:phone":"+34 985 34 82 39",
    "sg:postcode":"33201",
    "sg:province":"Asturias",
    "wof:name":"Alvarez Vega Maria Rosa",
    "wof:placetype":"venue"
},
  "geometry": {"coordinates":[-5.6628856659,43.5467033386],"type":"Point"}
}