{
  "type": "Feature",
  "properties": {
    "iso:country":"ES",
    "sg:address":"Calle de Doctor J.j. Domine, 15",
    "sg:city":"Valencia",
    "sg:orig_category":"Molduras, Junquillos, Listones Y Molduras Perforadas",
    "sg:phone":"+34 963 67 55 75",
    "sg:postcode":"46011",
    "sg:province":"Valencia",
    "wof:name":"Barrenada Alvarez C.b.",
    "wof:placetype":"venue"
},
  "geometry": {"coordinates":[-0.3311780095,39.462272644],"type":"Point"}
}