{
  "type": "Feature",
  "properties": {
    "addr:full":"Calle de Ferrocarril, 22 Navalcarnero Madrid 28600",
    "addr:housenumber":"22",
    "addr:postcode":"28600",
    "addr:street":"Calle De Ferrocarril",
    "iso:country":"ES",
    "sg:address":"Calle de Ferrocarril, 22",
    "sg:city":"Navalcarnero",
    "sg:orig_category":"Adhesivos (fabricaci\u00d3n, Al Por Mayor)",
    "sg:phone":"+34 918 11 45 45",
    "sg:postcode":"28600",
    "sg:province":"Madrid",
    "wof:name":"Cyem Cintas Adhesivas S.a.",
    "wof:placetype":"venue"
},
  "geometry": {"coordinates":[-4.0025382042,40.2916374207],"type":"Point"}
}