{
  "type": "Feature",
  "properties": {
    "addr:full":"La Traviesa, 7 Oza La Coru\u00f1a 15380",
    "addr:housenumber":"7",
    "addr:postcode":"15380",
    "addr:street":"Traviesa;Oza La Corun\u0303A",
    "iso:country":"ES",
    "sg:address":"La Traviesa, 7",
    "sg:city":"Oza",
    "sg:orig_category":"Art\u00cdculos Funerarios (al Por Menor)",
    "sg:phone":"+34 981 79 20 28",
    "sg:postcode":"15380",
    "sg:province":"La Coru\u00f1a",
    "wof:name":"Perez Diaz Jose Manuel",
    "wof:placetype":"venue"
},
  "geometry": {"coordinates":[-8.1878890991,43.2155342102],"type":"Point"}
}