{
  "type": "Feature",
  "properties": {
    "iso:country":"ES",
    "sg:address":"Calle de Jenaro Oraa, 32",
    "sg:city":"Santurtzi",
    "sg:orig_category":"Fabricaci\u00d3n De Muebles",
    "sg:phone":"+34 944 61 47 77",
    "sg:postcode":"48980",
    "sg:province":"Vizcaya",
    "wof:name":"Sukalnor, S.l.",
    "wof:placetype":"venue"
},
  "geometry": {"coordinates":[-3.0296535492,43.3268966675],"type":"Point"}
}