{
  "type": "Feature",
  "properties": {
    "iso:country":"ES",
    "sg:address":"Calle de Rodrigo De Caro, 23",
    "sg:city":"Miranda",
    "sg:orig_category":"Asesor\u00cda Sobre Comunicaci\u00d3n De Empresas",
    "sg:phone":"+34 968 16 99 79",
    "sg:postcode":"30319",
    "sg:province":"Murcia",
    "wof:name":"Asesores De Empresas De Cartagena S.l.",
    "wof:placetype":"venue"
},
  "geometry": {"coordinates":[-1.024335146,37.6826782227],"type":"Point"}
}