{
  "type": "Feature",
  "properties": {
    "iso:country":"ES",
    "sg:address":"Avda Juan Carlos I, 54",
    "sg:city":"Zorita",
    "sg:orig_category":"Cooperativas Agr\u00cdcolas",
    "sg:phone":"+34 927 34 00 48",
    "sg:postcode":"10130",
    "sg:province":"C\u00e1ceres",
    "wof:name":"Cooperativa Comarcal De Consumo Fuensanta",
    "wof:placetype":"venue"
},
  "geometry": {"coordinates":[-5.6992521286,39.2874679565],"type":"Point"}
}