{
  "type": "Feature",
  "properties": {
    "iso:country":"ES",
    "sg:address":"Calle de Alejandro Moran, 22",
    "sg:city":"Madrid",
    "sg:orig_category":"Aparcamientos (infraestructuras, Accesorios)",
    "sg:phone":"+34 915 25 14 63",
    "sg:postcode":"28025",
    "sg:province":"Madrid",
    "wof:name":"Franco Grisales Jhon Fredy",
    "wof:placetype":"venue"
},
  "geometry": {"coordinates":[-3.731949091,40.3857383728],"type":"Point"}
}