{
  "type": "Feature",
  "properties": {
    "iso:country":"ES",
    "sg:address":"Calle de Clara Campoamor, 4",
    "sg:city":"Jerez De Los Caballeros",
    "sg:orig_category":"Peluquer\u00cdas, Peluquer\u00cda Mixta",
    "sg:phone":"+34 924 75 02 94",
    "sg:postcode":"06380",
    "sg:province":"Badajoz",
    "wof:name":"Rodriguez Rastrollo Aguasanta",
    "wof:placetype":"venue"
},
  "geometry": {"coordinates":[-6.7636680603,38.3236579895],"type":"Point"}
}