{
  "type": "Feature",
  "properties": {
    "iso:country":"ES",
    "sg:address":"Carr Prim, 5",
    "sg:city":"Caldes Malavella",
    "sg:orig_category":"Agentes Generales De Seguros",
    "sg:phone":"+34 972 47 20 27",
    "sg:postcode":"17455",
    "sg:province":"Girona",
    "wof:name":"Eboso Gestio S.l.",
    "wof:placetype":"venue"
},
  "geometry": {"coordinates":[2.8256690502,41.8730735779],"type":"Point"}
}