{
  "type": "Feature",
  "properties": {
    "addr:full":"Avda Principal, S/n Monte Colorado Valencia 46185",
    "addr:housenumber":"s",
    "addr:postcode":"46185",
    "addr:street":"Avda Principal;/ N",
    "iso:country":"ES",
    "sg:address":"Avda Principal, S/n",
    "sg:city":"Monte Colorado",
    "sg:orig_category":"Empresarios Y Productoras De Espect\u00c1culos",
    "sg:phone":"+34 962 76 03 19",
    "sg:postcode":"46185",
    "sg:province":"Valencia",
    "wof:name":"Muller  Eva",
    "wof:placetype":"venue"
},
  "geometry": {"coordinates":[-0.5534440279,39.5925750732],"type":"Point"}
}