{
  "type": "Feature",
  "properties": {
    "iso:country":"ES",
    "sg:address":"Carr Eduard Rodeja, 12",
    "sg:city":"Figueres",
    "sg:orig_category":"Agencias Y Agentes Comerciales, Representantes",
    "sg:phone":"+34 972 51 31 67",
    "sg:postcode":"17600",
    "sg:province":"Girona",
    "wof:name":"Ayats Ochoa S.cv.",
    "wof:placetype":"venue"
},
  "geometry": {"coordinates":[2.965457201,42.2600669861],"type":"Point"}
}