{
  "type": "Feature",
  "properties": {
    "iso:country":"ES",
    "sg:address":"Calle de Daoiz Y Velarde, 3",
    "sg:city":"Gijon",
    "sg:orig_category":"Costureras",
    "sg:phone":"+34 985 30 86 34",
    "sg:postcode":"33212",
    "sg:province":"Asturias",
    "wof:name":"Hinojal Sanz Roberto",
    "wof:placetype":"venue"
},
  "geometry": {"coordinates":[-5.6833248138,43.540058136],"type":"Point"}
}