{
  "type": "Feature",
  "properties": {
    "iso:country":"ES",
    "sg:address":"Carrer de Maria Aguilo, 30",
    "sg:city":"Sabadell",
    "sg:orig_category":"Empresas De Carpinter\u00cda",
    "sg:phone":"+34 937 12 06 71",
    "sg:postcode":"08205",
    "sg:province":"Barcelona",
    "wof:name":"Alfa Aluminios Y Fabricacion S.l.",
    "wof:placetype":"venue"
},
  "geometry": {"coordinates":[2.1027526855,41.5348968506],"type":"Point"}
}