{
  "type": "Feature",
  "properties": {
    "iso:country":"ES",
    "sg:address":"Carrer de Tudona, 19",
    "sg:city":"S. Just Desvern",
    "sg:orig_category":"Carnes De Carnicer\u00cda (al Por Mayor)",
    "sg:phone":"+34 933 71 81 53",
    "sg:postcode":"08960",
    "sg:province":"Barcelona",
    "wof:name":"Carns Desvern S.l.",
    "wof:placetype":"venue"
},
  "geometry": {"coordinates":[2.0724000931,41.3828811646],"type":"Point"}
}