{
  "type": "Feature",
  "properties": {
    "addr:full":"Carrer de Maresme, 123 Barcelona Barcelona 08019",
    "addr:housenumber":"123",
    "addr:postcode":"08019",
    "addr:street":"Carrer De Maresme",
    "iso:country":"ES",
    "sg:address":"Carrer de Maresme, 123",
    "sg:city":"Barcelona",
    "sg:orig_category":"Electricidad: Instaladores",
    "sg:phone":"+34 933 03 43 45",
    "sg:postcode":"08019",
    "sg:province":"Barcelona",
    "wof:name":"Suris S.a.",
    "wof:placetype":"venue"
},
  "geometry": {"coordinates":[2.2108230591,41.4158401489],"type":"Point"}
}