{
  "type": "Feature",
  "properties": {
    "addr:full":"Avda Lehendakari Agirre Etorbidea, 16 Elexalde Vizcaya 48140",
    "addr:housenumber":"16",
    "addr:postcode":"48140",
    "addr:street":"Avda Lehendakari Agirre Etorbidea",
    "iso:country":"ES",
    "sg:address":"Avda Lehendakari Agirre Etorbidea, 16",
    "sg:city":"Elexalde",
    "sg:orig_category":"Cajas De Ahorro",
    "sg:phone":"+34 946 73 60 21",
    "sg:postcode":"48140",
    "sg:province":"Vizcaya",
    "sg:website":"www.bbk.com",
    "wof:name":"Bilbao Bizkaia Kutxa",
    "wof:placetype":"venue"
},
  "geometry": {"coordinates":[-2.7782819271,43.1634979248],"type":"Point"}
}