{
  "type": "Feature",
  "properties": {
    "iso:country":"ES",
    "sg:address":"Avda Cameranos, 6",
    "sg:city":"Zafra",
    "sg:orig_category":"Centros P\u00dablicos De Formaci\u00d3n Profesional Y T\u00c9cnica",
    "sg:phone":"+34 924 55 54 50",
    "sg:postcode":"06300",
    "sg:province":"Badajoz",
    "wof:name":"Colegio Oficial De Peritos E Ingenieros Tecnicos Industriales De Badajoz",
    "wof:placetype":"venue"
},
  "geometry": {"coordinates":[-6.411149025,38.4197654724],"type":"Point"}
}