{
  "type": "Feature",
  "properties": {
    "iso:country":"ES",
    "sg:address":"Calle de Maqueda, 17",
    "sg:city":"Madrid",
    "sg:orig_category":"Peluqueros: De Se\u00d1oras",
    "sg:phone":"+34 917 17 37 68",
    "sg:postcode":"28024",
    "sg:province":"Madrid",
    "wof:name":"Fernandez Marin Francisco",
    "wof:placetype":"venue"
},
  "geometry": {"coordinates":[-3.7661910057,40.3939781189],"type":"Point"}
}