{
  "type": "Feature",
  "properties": {
    "addr:full":"Calle de Virgen Del Carmen, 54 Donostia-san Sebastian Guip\u00f9zcoa 20012",
    "addr:housenumber":"54",
    "addr:postcode":"20012",
    "addr:street":"Calle De Virgen Del Carmen",
    "iso:country":"ES",
    "sg:address":"Calle de Virgen Del Carmen, 54",
    "sg:city":"Donostia-san Sebastian",
    "sg:orig_category":"Peluqueros: De Se\u00d1oras",
    "sg:phone":"+34 943 28 96 55",
    "sg:postcode":"20012",
    "sg:province":"Guip\u00f9zcoa",
    "wof:name":"Rita Balbuena Vaquero-peluqueria",
    "wof:placetype":"venue"
},
  "geometry": {"coordinates":[-1.96727705,43.3183822632],"type":"Point"}
}