{
  "type": "Feature",
  "properties": {
    "iso:country":"ES",
    "sg:address":"Pase Alameda De Osuna, 71",
    "sg:city":"Madrid",
    "sg:orig_category":"Promotores Constructores",
    "sg:phone":"+34 917 47 12 62",
    "sg:postcode":"28042",
    "sg:province":"Madrid",
    "wof:name":"Jayc Lobato S.l.",
    "wof:placetype":"venue"
},
  "geometry": {"coordinates":[-3.5959415436,40.4252319336],"type":"Point"}
}