{
  "type": "Feature",
  "properties": {
    "iso:country":"ES",
    "sg:address":"Calle de Mendibile, 8",
    "sg:city":"Leioa",
    "sg:orig_category":"Piscinas, Accesorios, Suministros (fabricaci\u00d3n, Al Por Mayor)",
    "sg:phone":"+34 944 63 16 10",
    "sg:postcode":"48940",
    "sg:province":"Vizcaya",
    "sg:website":"www.vianor.com",
    "wof:name":"Tratamientos Aquanor S.l",
    "wof:placetype":"venue"
},
  "geometry": {"coordinates":[-2.9824061394,43.3238296509],"type":"Point"}
}