{
  "type": "Feature",
  "properties": {
    "iso:country":"ES",
    "sg:address":"Calle de Vea Murguia, 38",
    "sg:city":"Cadiz",
    "sg:orig_category":"Asilos De Ancianos. Centros Privados",
    "sg:phone":"+34 956 22 40 42",
    "sg:postcode":"11003",
    "sg:province":"C\u00e1diz",
    "wof:name":"Fundacion Sauce",
    "wof:placetype":"venue"
},
  "geometry": {"coordinates":[-6.299079895,36.5369415283],"type":"Point"}
}