{
  "type": "Feature",
  "properties": {
    "iso:country":"ES",
    "sg:address":"Calle de Tomas Romero De Castilla, 4",
    "sg:city":"Badajoz",
    "sg:orig_category":"Carnicer\u00cdas, Carnicer\u00cdas",
    "sg:phone":"+34 924 24 42 16",
    "sg:postcode":"06011",
    "sg:province":"Badajoz",
    "wof:name":"Norberto De Fuentes Jeronimo",
    "wof:placetype":"venue"
},
  "geometry": {"coordinates":[-6.9816670418,38.8707313538],"type":"Point"}
}