{
  "type": "Feature",
  "properties": {
    "iso:country":"ES",
    "sg:address":"Cm\u00d1o Romeu, 45",
    "sg:city":"Mui\u00d1os",
    "sg:orig_category":"Equipo De Refrigeraci\u00d3n Industrial",
    "sg:phone":"+34 986 20 88 05",
    "sg:postcode":"36213",
    "sg:province":"Pontevedra",
    "sg:website":"www.kinarca.com",
    "wof:name":"Kinarca S. A.",
    "wof:placetype":"venue"
},
  "geometry": {"coordinates":[-8.1446475983,42.5755195618],"type":"Point"}
}