{
  "type": "Feature",
  "properties": {
    "iso:country":"ES",
    "sg:address":"Calle de Agustin Rodriguez Correa, 15",
    "sg:city":"Palmas De Gran Canaria",
    "sg:orig_category":"Chapister\u00cda",
    "sg:phone":"+34 928 20 97 28",
    "sg:postcode":"35014",
    "sg:province":"Las Palmas",
    "wof:name":"Medina Quintana Roman Del Pino",
    "wof:placetype":"venue"
},
  "geometry": {"coordinates":[-15.4373807907,28.0955581665],"type":"Point"}
}