{
  "type": "Feature",
  "properties": {
    "addr:full":"Calle de Lorca, 61 Palmar  O Lugar De Don Juan Murcia 30120",
    "addr:housenumber":"61",
    "addr:postcode":"30120",
    "addr:street":"Calle De Lorca;Lugar",
    "iso:country":"ES",
    "sg:address":"Calle de Lorca, 61",
    "sg:city":"Palmar  O Lugar De Don Juan",
    "sg:orig_category":"Bisuter\u00cda, Joyer\u00cda, Relojer\u00cda (al Por Menor)",
    "sg:phone":"+34 968 88 48 09",
    "sg:postcode":"30120",
    "sg:province":"Murcia",
    "wof:name":"Bernabe Pascual Josefa",
    "wof:placetype":"venue"
},
  "geometry": {"coordinates":[-1.1302490234,37.9829597473],"type":"Point"}
}