{
  "type": "Feature",
  "properties": {
    "addr:full":"Calle de Explanada, 16 Madrid Madrid 28040",
    "addr:housenumber":"16",
    "addr:postcode":"madrid;28040",
    "addr:street":"Calle De Explanada",
    "iso:country":"ES",
    "sg:address":"Calle de Explanada, 16",
    "sg:city":"Madrid",
    "sg:orig_category":"Cl\u00cdnicas M\u00c9dicas",
    "sg:phone":"+34 915 54 54 05",
    "sg:postcode":"28040",
    "sg:province":"Madrid",
    "wof:name":"Investigacion Y Cirugia Ortopedica Dr. Galindo S.l.",
    "wof:placetype":"venue"
},
  "geometry": {"coordinates":[-3.7119693756,40.4484024048],"type":"Point"}
}