{
  "type": "Feature",
  "properties": {
    "iso:country":"ES",
    "sg:address":"Calle de Moritos, 2",
    "sg:city":"Medina-sidonia",
    "sg:orig_category":"Asociaciones Y Clubs Deportivos",
    "sg:phone":"+34 956 41 12 47",
    "sg:postcode":"11170",
    "sg:province":"C\u00e1diz",
    "wof:name":"Deportes Mabel S.l.",
    "wof:placetype":"venue"
},
  "geometry": {"coordinates":[-5.9283638,36.4589424133],"type":"Point"}
}