{
  "type": "Feature",
  "properties": {
    "iso:country":"ES",
    "sg:address":"Calle de Fernan Caballero, 10",
    "sg:city":"Carmona",
    "sg:orig_category":"Asesor\u00cda Sobre Comunicaci\u00d3n De Empresas",
    "sg:phone":"+34 954 14 23 08",
    "sg:postcode":"41410",
    "sg:province":"Sevilla",
    "wof:name":"Selius S.l.",
    "wof:placetype":"venue"
},
  "geometry": {"coordinates":[-5.6392250061,37.473487854],"type":"Point"}
}