{
  "type": "Feature",
  "properties": {
    "addr:full":"Calle de F(campollano), 11 Albacete Albacete 02006",
    "addr:housenumber":"11",
    "addr:postcode":"02006",
    "addr:street":"Calle De F Campollano",
    "iso:country":"ES",
    "sg:address":"Calle de F(campollano), 11",
    "sg:city":"Albacete",
    "sg:orig_category":"Adaptaciones, Acondicionamientos Especiales Para Veh\u00cdculos, Veh\u00cdculos Industriales",
    "sg:phone":"+34 967 21 28 26",
    "sg:postcode":"02006",
    "sg:province":"Albacete",
    "sg:website":"www.hidraulical.com",
    "wof:name":"Hidraulicos Albacete S.l.",
    "wof:placetype":"venue"
},
  "geometry": {"coordinates":[-1.9356930256,39.0582275391],"type":"Point"}
}