{
  "type": "Feature",
  "properties": {
    "iso:country":"ES",
    "sg:address":"Calle de Ramon Y Cajal, 1",
    "sg:city":"Alcazar S. Juan",
    "sg:orig_category":"Zapatos (al Por Menor)",
    "sg:phone":"+34 926 54 61 98",
    "sg:postcode":"13600",
    "sg:province":"Ciudad Real",
    "wof:name":"Calzado Lopez Maria Luz",
    "wof:placetype":"venue"
},
  "geometry": {"coordinates":[-3.2090489864,39.3915214539],"type":"Point"}
}