{
  "type": "Feature",
  "properties": {
    "addr:full":"Rbla Catalana, 1 Hospitalet Llobregat Barcelona 08903",
    "addr:housenumber":"1",
    "addr:postcode":"08903",
    "addr:street":"Rbla Catalana",
    "iso:country":"ES",
    "sg:address":"Rbla Catalana, 1",
    "sg:city":"Hospitalet Llobregat",
    "sg:orig_category":"Cajas De Ahorro",
    "sg:phone":"+34 934 32 10 34",
    "sg:postcode":"08903",
    "sg:province":"Barcelona",
    "wof:name":"Caixa D'estalvis De Catalunya",
    "wof:placetype":"venue"
},
  "geometry": {"coordinates":[2.1264870167,41.3720359802],"type":"Point"}
}