{
  "type": "Feature",
  "properties": {
    "addr:full":"Ctra Llagostera, 19 Caldes Malavella Girona 17455",
    "addr:housenumber":"19",
    "addr:postcode":"17455",
    "addr:street":"Ctra Llagostera",
    "iso:country":"ES",
    "sg:address":"Ctra Llagostera, 19",
    "sg:city":"Caldes Malavella",
    "sg:orig_category":"Muebles, Minoristas",
    "sg:phone":"+34 972 47 03 48",
    "sg:postcode":"17455",
    "sg:province":"Girona",
    "wof:name":"Figueras Simon Antonio",
    "wof:placetype":"venue"
},
  "geometry": {"coordinates":[2.807790041,41.8390197754],"type":"Point"}
}