{
  "type": "Feature",
  "properties": {
    "addr:full":"Plaz Mayor, 1 Nules Castell\u00f3n 12520",
    "addr:housenumber":"1",
    "addr:postcode":"12520",
    "addr:street":"Plaz Mayor",
    "iso:country":"ES",
    "sg:address":"Plaz Mayor, 1",
    "sg:city":"Nules",
    "sg:orig_category":"Ense\u00d1anza, Formaci\u00d3n Profesional: Aprendizaje",
    "sg:phone":"+34 964 67 46 20",
    "sg:postcode":"12520",
    "sg:province":"Castell\u00f3n",
    "wof:name":"Ayuntamiento De Nules",
    "wof:placetype":"venue"
},
  "geometry": {"coordinates":[-0.1542440057,39.852596283],"type":"Point"}
}