{
  "type": "Feature",
  "properties": {
    "addr:full":"Portalez, 27 Fuente Palmera C\u00f3rdoba 14120",
    "addr:housenumber":"27",
    "addr:postcode":"14120",
    "addr:street":"Portalez",
    "iso:country":"ES",
    "sg:address":"Portalez, 27",
    "sg:city":"Fuente Palmera",
    "sg:orig_category":"Farmacias",
    "sg:phone":"+34 957 63 80 85",
    "sg:postcode":"14120",
    "sg:province":"C\u00f3rdoba",
    "wof:name":"Sanchez Gasso Miguel",
    "wof:placetype":"venue"
},
  "geometry": {"coordinates":[-5.1020951271,37.7035217285],"type":"Point"}
}