{
  "type": "Feature",
  "properties": {
    "iso:country":"ES",
    "sg:address":"Cra Cirera (de), 35",
    "sg:city":"Mataro",
    "sg:orig_category":"Empresas De Carpinter\u00cda De Madera",
    "sg:phone":"+34 937 98 98 67",
    "sg:postcode":"08304",
    "sg:province":"Barcelona",
    "wof:name":"La Garlopa S.l.",
    "wof:placetype":"venue"
},
  "geometry": {"coordinates":[2.4380431175,41.5504226685],"type":"Point"}
}