{
  "type": "Feature",
  "properties": {
    "addr:full":"Plaz Carmelitas, 1 Salamanca Salamanca 37007",
    "addr:housenumber":"1",
    "addr:postcode":"37007",
    "addr:street":"Carmelitas",
    "iso:country":"ES",
    "sg:address":"Plaz Carmelitas, 1",
    "sg:city":"Salamanca",
    "sg:orig_category":"Centros De Coordinaci\u00d3n",
    "sg:phone":"+34 923 21 54 96",
    "sg:postcode":"37007",
    "sg:province":"Salamanca",
    "wof:name":"Robles Martin Julian",
    "wof:placetype":"venue"
},
  "geometry": {"coordinates":[-5.6674690247,40.9683303833],"type":"Point"}
}