{
  "type": "Feature",
  "properties": {
    "iso:country":"ES",
    "sg:address":"Av Angel Sallent, 157",
    "sg:city":"Terrassa",
    "sg:orig_category":"Aparatos, Sistemas De Tele",
    "sg:phone":"+34 937 89 43 41",
    "sg:postcode":"08224",
    "sg:province":"Barcelona",
    "wof:name":"Exber Seguridad S.l.",
    "wof:placetype":"venue"
},
  "geometry": {"coordinates":[1.9988620281,41.5602340698],"type":"Point"}
}