{
  "type": "Feature",
  "properties": {
    "addr:full":"Plaz Salvador (el), 9 Azagra Navarra 31560",
    "addr:postcode":"31560",
    "addr:street":"El",
    "iso:country":"ES",
    "sg:address":"Plaz Salvador (el), 9",
    "sg:city":"Azagra",
    "sg:orig_category":"Arquitectos",
    "sg:phone":"+34 948 69 28 08",
    "sg:postcode":"31560",
    "sg:province":"Navarra",
    "wof:name":"Arquitectura Azagra S.l.",
    "wof:placetype":"venue"
},
  "geometry": {"coordinates":[-1.8937474489,42.3084030151],"type":"Point"}
}