{
  "type": "Feature",
  "properties": {
    "addr:full":"Calle de Carlos Ruiz, 10 Madrid Madrid 28023",
    "addr:housenumber":"10",
    "addr:postcode":"madrid;28023",
    "addr:street":"Calle De Carlos Ruiz",
    "iso:country":"ES",
    "sg:address":"Calle de Carlos Ruiz, 10",
    "sg:city":"Madrid",
    "sg:orig_category":"Administradores De Bienes Y Delegados De Comunidades De Propietarios",
    "sg:phone":"+34 913 72 96 75",
    "sg:postcode":"28023",
    "sg:province":"Madrid",
    "wof:name":"Merac Gestion S.l.",
    "wof:placetype":"venue"
},
  "geometry": {"coordinates":[-3.8214862347,40.4708061218],"type":"Point"}
}