{
  "type": "Feature",
  "properties": {
    "iso:country":"ES",
    "sg:address":"Calle de La Rua, 42",
    "sg:city":"Villalon Campos",
    "sg:orig_category":"Peluqueros: De Se\u00d1oras",
    "sg:phone":"+34 983 74 00 61",
    "sg:postcode":"47600",
    "sg:province":"Valladolid",
    "wof:name":"Criado Collantes Manuela",
    "wof:placetype":"venue"
},
  "geometry": {"coordinates":[-5.0348992348,42.0987815857],"type":"Point"}
}