{
  "type": "Feature",
  "properties": {
    "iso:country":"ES",
    "sg:address":"Av. Via Lusitana, 47",
    "sg:city":"Madrid",
    "sg:orig_category":"Cajas De Ahorro",
    "sg:phone":"+34 913 41 78 53",
    "sg:postcode":"28025",
    "sg:province":"Madrid",
    "wof:name":"Caixa D'estalvis I Pensions De Barcelona",
    "wof:placetype":"venue"
},
  "geometry": {"coordinates":[-3.7057740688,40.42029953],"type":"Point"}
}