{
  "type": "Feature",
  "properties": {
    "addr:full":"Calle de Pardo, 25 Villanueva Serena Badajoz 06700",
    "addr:housenumber":"25",
    "addr:postcode":"06700",
    "addr:street":"Calle De Pardo",
    "iso:country":"ES",
    "sg:address":"Calle de Pardo, 25",
    "sg:city":"Villanueva Serena",
    "sg:orig_category":"Sociedades, Compa\u00d1\u00cdas Aseguradoras",
    "sg:phone":"+34 924 84 28 96",
    "sg:postcode":"06700",
    "sg:province":"Badajoz",
    "wof:name":"Chamizo Guisado Francisco",
    "wof:placetype":"venue"
},
  "geometry": {"coordinates":[-5.8053250313,38.9748077393],"type":"Point"}
}