{
  "type": "Feature",
  "properties": {
    "addr:full":"Ameal, 20 Ameal Pontevedra 36914",
    "addr:housenumber":"20",
    "addr:postcode":"36914",
    "addr:street":"Ameal",
    "iso:country":"ES",
    "sg:address":"Ameal, 20",
    "sg:city":"Ameal",
    "sg:orig_category":"Producci\u00d3n, Comercio De Cereales",
    "sg:phone":"+34 986 70 25 55",
    "sg:postcode":"36914",
    "sg:province":"Pontevedra",
    "wof:name":"Cereales Lopez S. L.",
    "wof:placetype":"venue"
},
  "geometry": {"coordinates":[-8.6920261383,42.3568344116],"type":"Point"}
}