{
  "type": "Feature",
  "properties": {
    "addr:full":"Ctra Madrid-irun(oeste), S/n Aranda Duero Burgos 09400",
    "addr:housenumber":"s / n",
    "addr:postcode":"09400",
    "addr:street":"Ctra Madrid-Irun Oeste",
    "iso:country":"ES",
    "sg:address":"Ctra Madrid-irun(oeste), S/n",
    "sg:city":"Aranda Duero",
    "sg:orig_category":"Fabricaci\u00d3n De Harinas, S\u00c9molas, Productos De Elaboraci\u00d3n Del Grano",
    "sg:phone":"+34 947 50 04 00",
    "sg:postcode":"09400",
    "sg:province":"Burgos",
    "wof:name":"Harinera Arandina S. A.",
    "wof:placetype":"venue"
},
  "geometry": {"coordinates":[-3.685338974,41.6884841919],"type":"Point"}
}