{
  "type": "Feature",
  "properties": {
    "addr:full":"Plaz Kraus Alfredo, 5 Bilbao Vizcaya 48002",
    "addr:postcode":"48002",
    "iso:country":"ES",
    "sg:address":"Plaz Kraus Alfredo, 5",
    "sg:city":"Bilbao",
    "sg:orig_category":"Asilos De Ancianos. Centros Privados",
    "sg:phone":"+34 944 21 12 05",
    "sg:postcode":"48002",
    "sg:province":"Vizcaya",
    "wof:name":"Gestora De Negocios Orice S.l.",
    "wof:placetype":"venue"
},
  "geometry": {"coordinates":[-2.9461190701,43.2686500549],"type":"Point"}
}