{
  "type": "Feature",
  "properties": {
    "iso:country":"ES",
    "sg:address":"Plaz Parres Pi\u00d1era, S/n",
    "sg:city":"Posada",
    "sg:orig_category":"Inmobiliaria (agencias)",
    "sg:phone":"+34 985 40 76 57",
    "sg:postcode":"33594",
    "sg:province":"Asturias",
    "wof:name":"Inmobiliaria Trasgu C B",
    "wof:placetype":"venue"
},
  "geometry": {"coordinates":[-4.8714389801,43.4239463806],"type":"Point"}
}