{
  "type": "Feature",
  "properties": {
    "addr:full":"Calle de Beato Tomas De Zumarraga, 64 Vitoria-gasteiz \u00c1lava 01009",
    "addr:housenumber":"64",
    "addr:postcode":"01009",
    "addr:street":"Calle De Beato Tomas De Zumarraga",
    "iso:country":"ES",
    "sg:address":"Calle de Beato Tomas De Zumarraga, 64",
    "sg:city":"Vitoria-gasteiz",
    "sg:orig_category":"Molduras, Junquillos, Listones Y Molduras Perforadas",
    "sg:phone":"+34 945 24 33 95",
    "sg:postcode":"01009",
    "sg:province":"\u00c1lava",
    "wof:name":"Perez Hernaez Manuel Maria",
    "wof:placetype":"venue"
},
  "geometry": {"coordinates":[-2.6848402023,42.8506851196],"type":"Point"}
}