{
  "type": "Feature",
  "properties": {
    "iso:country":"ES",
    "sg:address":"Calle de Miguel Ortiz, 11",
    "sg:city":"Tardienta",
    "sg:orig_category":"Alimentaci\u00d3n General (al Por Menor)",
    "sg:phone":"+34 974 25 31 65",
    "sg:postcode":"22240",
    "sg:province":"Huesca",
    "wof:name":"Cosano Alcubierre Antonio",
    "wof:placetype":"venue"
},
  "geometry": {"coordinates":[-0.5373839736,41.9793930054],"type":"Point"}
}