{
  "type": "Feature",
  "properties": {
    "addr:full":"Av. America, 7 Alcorcon Madrid 28922",
    "addr:housenumber":"7",
    "addr:postcode":"28922",
    "addr:street":"Av. America",
    "iso:country":"ES",
    "sg:address":"Av. America, 7",
    "sg:city":"Alcorcon",
    "sg:orig_category":"Asociaciones Y Clubs Deportivos",
    "sg:phone":"+34 916 10 44 43",
    "sg:postcode":"28922",
    "sg:province":"Madrid",
    "sg:website":"www.super-sport.net",
    "wof:name":"Milanesado S.l.",
    "wof:placetype":"venue"
},
  "geometry": {"coordinates":[-3.8312599659,40.3590583801],"type":"Point"}
}