{
  "type": "Feature",
  "properties": {
    "addr:full":"Calle de Placido Pe\u00d1a, 64 Vilalba Lugo 27800",
    "addr:housenumber":"64",
    "addr:postcode":"27800",
    "addr:street":"Calle De Placido Pen\u0303A",
    "iso:country":"ES",
    "sg:address":"Calle de Placido Pe\u00d1a, 64",
    "sg:city":"Vilalba",
    "sg:orig_category":"Material Y Herramientas Agr\u00cdcolas",
    "sg:phone":"+34 982 51 04 52",
    "sg:postcode":"27800",
    "sg:province":"Lugo",
    "wof:name":"Recambios Agromovil S.l.",
    "wof:placetype":"venue"
},
  "geometry": {"coordinates":[-7.6790380478,43.3012695312],"type":"Point"}
}