{
  "type": "Feature",
  "properties": {
    "iso:country":"ES",
    "sg:address":"Calle de Mosen Jose Martinez, 18",
    "sg:city":"Zaragoza",
    "sg:orig_category":"Organizaciones Internacionales",
    "sg:phone":"+34 976 53 31 84",
    "sg:postcode":"50011",
    "sg:province":"Zaragoza",
    "wof:name":"Mision Evangelica Urbana De Zaragoza",
    "wof:placetype":"venue"
},
  "geometry": {"coordinates":[-0.9235600233,41.6511383057],"type":"Point"}
}