{
  "type": "Feature",
  "properties": {
    "addr:full":"Calle de Joaquin Peralta, 5 Almeria Almer\u00eda 04004",
    "addr:housenumber":"5",
    "addr:postcode":"04004",
    "addr:street":"Calle De Joaquin Peralta",
    "iso:country":"ES",
    "sg:address":"Calle de Joaquin Peralta, 5",
    "sg:city":"Almeria",
    "sg:orig_category":"Carnicer\u00cdas, Carnicer\u00cdas",
    "sg:phone":"+34 950 27 52 07",
    "sg:postcode":"04004",
    "sg:province":"Almer\u00eda",
    "wof:name":"Mateu Escamilla Manuel",
    "wof:placetype":"venue"
},
  "geometry": {"coordinates":[-2.4591081142,36.8428077698],"type":"Point"}
}