{
  "type": "Feature",
  "properties": {
    "iso:country":"ES",
    "sg:address":"Pase Alameda, 7",
    "sg:city":"Arevalo",
    "sg:classifiers":[
        {
            "category":"Autos & Motor Vehicles",
            "subcategory":"Automobile Sales",
            "type":"Retail Goods"
        }
    ],
    "sg:phone":"+34 920 30 10 64",
    "sg:postcode":"05200",
    "sg:province":"\u00c1vila",
    "wof:name":"Lopez Saez Juan",
    "wof:placetype":"venue"
},
  "geometry": {"coordinates":[-4.7208380699,41.0582427979],"type":"Point"}
}