{
  "type": "Feature",
  "properties": {
    "iso:country":"ES",
    "sg:address":"Rua Oliva (la), 2",
    "sg:city":"Pontevedra",
    "sg:orig_category":"Fabricaci\u00d3n, Distribuci\u00d3n De Discos, V\u00cddeodiscos Y Musicassettes",
    "sg:phone":"+34 986 89 61 82",
    "sg:postcode":"36001",
    "sg:province":"Pontevedra",
    "sg:website":"www.tipo.es",
    "wof:name":"Landin-disc S.l.",
    "wof:placetype":"venue"
},
  "geometry": {"coordinates":[-8.6442260742,42.4307174683],"type":"Point"}
}