{
  "type": "Feature",
  "properties": {
    "addr:full":"Avda Pirineos (de Los), 13 San Sebastian De Los Reyes Madrid 28700",
    "addr:housenumber":"13",
    "addr:postcode":"28700",
    "addr:street":"Avda Pirineos De Los",
    "iso:country":"ES",
    "sg:address":"Avda Pirineos (de Los), 13",
    "sg:city":"San Sebastian De Los Reyes",
    "sg:orig_category":"Ingeniero",
    "sg:phone":"+34 916 51 12 98",
    "sg:postcode":"28700",
    "sg:province":"Madrid",
    "sg:website":"www.tryp.com",
    "wof:name":"Prieto Gracia Ana",
    "wof:placetype":"venue"
},
  "geometry": {"coordinates":[-3.6101861,40.5501823425],"type":"Point"}
}