{
  "type": "Feature",
  "properties": {
    "iso:country":"ES",
    "sg:address":"Avda Emilia Pardo Bazan, 1",
    "sg:city":"Sanxenxo",
    "sg:orig_category":"Hoteles",
    "sg:phone":"+34 986 72 43 40",
    "sg:postcode":"36960",
    "sg:province":"Pontevedra",
    "wof:name":"Hotel Floridamar C.b.",
    "wof:placetype":"venue"
},
  "geometry": {"coordinates":[-8.8017301559,42.4017944336],"type":"Point"}
}