{
  "type": "Feature",
  "properties": {
    "iso:country":"ES",
    "sg:address":"Calle de Rufas, 10",
    "sg:city":"Zaragoza",
    "sg:orig_category":"Higiene, Belleza: Art\u00cdculos (al Por Menor)",
    "sg:phone":"+34 976 22 94 07",
    "sg:postcode":"50001",
    "sg:province":"Zaragoza",
    "sg:website":"www.condonuria.com",
    "wof:name":"Campos Sancho Yolanda",
    "wof:placetype":"venue"
},
  "geometry": {"coordinates":[-0.8776860237,41.6507797241],"type":"Point"}
}