{
  "type": "Feature",
  "properties": {
    "addr:full":"Prol. Floranes, 50 Santander Cantabria 39010",
    "addr:housenumber":"50",
    "addr:postcode":"39010",
    "addr:street":"Prol. Floranes",
    "iso:country":"ES",
    "sg:address":"Prol. Floranes, 50",
    "sg:city":"Santander",
    "sg:orig_category":"Tapicer\u00cdas",
    "sg:phone":"+34 942 37 49 65",
    "sg:postcode":"39010",
    "sg:province":"Cantabria",
    "wof:name":"Illarregui Pascua Jesus",
    "wof:placetype":"venue"
},
  "geometry": {"coordinates":[-3.8239729404,43.460231781],"type":"Point"}
}