{
  "type": "Feature",
  "properties": {
    "iso:country":"ES",
    "sg:address":"Avda Jorge Vigon, 16",
    "sg:city":"Logro\u00f1o",
    "sg:orig_category":"Ropa Para Se\u00d1oras Y Caballeros (al Por Menor)",
    "sg:phone":"+34 941 24 24 27",
    "sg:postcode":"26003",
    "sg:province":"La Rioja",
    "wof:name":"Osaba Hermanas S.l.",
    "wof:placetype":"venue"
},
  "geometry": {"coordinates":[-2.4438378811,42.4621925354],"type":"Point"}
}