{
  "type": "Feature",
  "properties": {
    "addr:full":"Carr De Santa Margarida, 4 Benicarlo Castell\u00f3n 12580",
    "addr:housenumber":"4",
    "addr:postcode":"12580",
    "addr:street":"Carr De Santa Margarida",
    "iso:country":"ES",
    "sg:address":"Carr De Santa Margarida, 4",
    "sg:city":"Benicarlo",
    "sg:orig_category":"Inform\u00c1tica: Redes",
    "sg:phone":"+34 964 47 00 45",
    "sg:postcode":"12580",
    "sg:province":"Castell\u00f3n",
    "wof:name":"Redes Salom S.l.",
    "wof:placetype":"venue"
},
  "geometry": {"coordinates":[0.4042100012,40.4457893372],"type":"Point"}
}