{
  "type": "Feature",
  "properties": {
    "iso:country":"ES",
    "sg:address":"Plaza De Burgos, 9",
    "sg:city":"Motril",
    "sg:orig_category":"Camiser\u00cda Y Ropa Interior Masculina (al Por Menor)",
    "sg:phone":"+34 958 82 40 93",
    "sg:postcode":"18600",
    "sg:province":"Granada",
    "wof:name":"Cooperativa Industrial De Corte Y Confeccion",
    "wof:placetype":"venue"
},
  "geometry": {"coordinates":[-3.5152790546,36.7456130981],"type":"Point"}
}