{
  "type": "Feature",
  "properties": {
    "iso:country":"ES",
    "sg:address":"Calle de Jesus, 12",
    "sg:city":"Oviedo",
    "sg:orig_category":"Abogados",
    "sg:phone":"+34 985 20 42 39",
    "sg:postcode":"33009",
    "sg:province":"Asturias",
    "wof:name":"Escobedo Bailly Jose Carlos",
    "wof:placetype":"venue"
},
  "geometry": {"coordinates":[-5.8452510834,43.3604850769],"type":"Point"}
}