{
  "type": "Feature",
  "properties": {
    "addr:full":"Calle de Giralda, S/n Moron Frontera Sevilla 41530",
    "addr:housenumber":"s / n",
    "addr:postcode":"41530",
    "addr:street":"Calle De Giralda",
    "iso:country":"ES",
    "sg:address":"Calle de Giralda, S/n",
    "sg:city":"Moron Frontera",
    "sg:orig_category":"Librer\u00cdas",
    "sg:phone":"+34 955 85 47 38",
    "sg:postcode":"41530",
    "sg:province":"Sevilla",
    "wof:name":"Andujar Bautista Juan",
    "wof:placetype":"venue"
},
  "geometry": {"coordinates":[-5.4631562233,37.1242218018],"type":"Point"}
}