{
  "type": "Feature",
  "properties": {
    "iso:country":"ES",
    "sg:address":"Calle de Colon, 6",
    "sg:city":"Novelda",
    "sg:orig_category":"Art\u00cdculos De Regalo (al Por Menor)",
    "sg:phone":"+34 965 60 05 84",
    "sg:postcode":"03660",
    "sg:province":"Alicante",
    "wof:name":"Torregrosa Amoros German",
    "wof:placetype":"venue"
},
  "geometry": {"coordinates":[-0.7661905885,38.3847465515],"type":"Point"}
}