{
  "type": "Feature",
  "properties": {
    "addr:full":"Carrer de Castelao, 127 Hospitalet Llobregat Barcelona 08902",
    "addr:housenumber":"127",
    "addr:postcode":"08902",
    "addr:street":"Carrer De Castelao",
    "iso:country":"ES",
    "sg:address":"Carrer de Castelao, 127",
    "sg:city":"Hospitalet Llobregat",
    "sg:orig_category":"Fabricaci\u00d3n E Instalaci\u00d3n De Telef\u00c9ricos Y De Sistemas De Transporte Por Cable",
    "sg:phone":"+34 934 21 61 83",
    "sg:postcode":"08902",
    "sg:province":"Barcelona",
    "wof:name":"Beneyte Mayor Agustin",
    "wof:placetype":"venue"
},
  "geometry": {"coordinates":[2.1259660721,41.3614654541],"type":"Point"}
}