{
  "type": "Feature",
  "properties": {
    "addr:full":"Avda Brasil, S/n San Cristobal De La Laguna Santa Cruz De Tenerife 38202",
    "addr:housenumber":"/ n",
    "addr:postcode":"38202",
    "addr:street":"Avda Brasil S",
    "iso:country":"ES",
    "sg:address":"Avda Brasil, S/n",
    "sg:city":"San Cristobal De La Laguna",
    "sg:orig_category":"Distribuci\u00d3n De Petr\u00d3leo Y Derivados",
    "sg:phone":"+34 922 26 43 03",
    "sg:postcode":"38202",
    "sg:province":"Santa Cruz De Tenerife",
    "wof:name":"Humser S.a.",
    "wof:placetype":"venue"
},
  "geometry": {"coordinates":[-16.3233699799,28.4907398224],"type":"Point"}
}