{
  "type": "Feature",
  "properties": {
    "iso:country":"ES",
    "sg:address":"Pg Maragall, 47",
    "sg:city":"Barcelona",
    "sg:orig_category":"Bancos",
    "sg:phone":"+34 934 56 00 93",
    "sg:postcode":"08041",
    "sg:province":"Barcelona",
    "sg:website":"www.banesto.com",
    "wof:name":"Banco Espa\u00f1ol De Credito S.a.",
    "wof:placetype":"venue"
},
  "geometry": {"coordinates":[2.180421114,41.4159202576],"type":"Point"}
}