{
  "type": "Feature",
  "properties": {
    "iso:country":"ES",
    "sg:address":"Calle de Reina Sofia, 26",
    "sg:city":"Puerto Del Carmen",
    "sg:orig_category":"Molduras, Junquillos, Listones Y Molduras Perforadas",
    "sg:phone":"+34 928 51 60 56",
    "sg:postcode":"35510",
    "sg:province":"Las Palmas",
    "wof:name":"Stuart Grant  Watson",
    "wof:placetype":"venue"
},
  "geometry": {"coordinates":[-13.6714868546,28.9231243134],"type":"Point"}
}