{
  "type": "Feature",
  "properties": {
    "iso:country":"ES",
    "sg:address":"Calle de Santa Gema, 75",
    "sg:city":"S. Adrian",
    "sg:orig_category":"Ferreter\u00cda (diversos)",
    "sg:phone":"+34 948 67 03 38",
    "sg:postcode":"31570",
    "sg:province":"Navarra",
    "wof:name":"Chatarras Hermanos Leon Lorente S.c.",
    "wof:placetype":"venue"
},
  "geometry": {"coordinates":[-1.9371449947,42.3381118774],"type":"Point"}
}