{
  "type": "Feature",
  "properties": {
    "iso:country":"ES",
    "sg:address":"Calle de Mayor, 56",
    "sg:city":"Berrioplano",
    "sg:orig_category":"Ense\u00d1anza, Formaci\u00d3n Profesional: Aprendizaje",
    "sg:phone":"+34 948 30 31 29",
    "sg:postcode":"31195",
    "sg:province":"Navarra",
    "wof:name":"Ayuntamiento De Berrioplano",
    "wof:placetype":"venue"
},
  "geometry": {"coordinates":[-1.6924669743,42.8526420593],"type":"Point"}
}