{
  "type": "Feature",
  "properties": {
    "addr:full":"Calle de Poza De La Sal, 8 Madrid Madrid 28031",
    "addr:housenumber":"8",
    "addr:postcode":"28031",
    "addr:street":"Calle De Poza De La;Madrid",
    "iso:country":"ES",
    "sg:address":"Calle de Poza De La Sal, 8",
    "sg:city":"Madrid",
    "sg:orig_category":"Organizaci\u00d3n De Fiestas Infantiles (publi Informaci\u00d3n)",
    "sg:phone":"+34 913 32 67 63",
    "sg:postcode":"28031",
    "sg:province":"Madrid",
    "wof:name":"Espectaculos Infantiles Pin Y Pon S.l.",
    "wof:placetype":"venue"
},
  "geometry": {"coordinates":[-3.6038920879,40.3788909912],"type":"Point"}
}