{
  "type": "Feature",
  "properties": {
    "addr:full":"Calle de Mayor, 141 Garrucha Almer\u00eda 04630",
    "addr:housenumber":"141",
    "addr:postcode":"04630",
    "addr:street":"Calle De Mayor;Almeri\u0301A",
    "iso:country":"ES",
    "sg:address":"Calle de Mayor, 141",
    "sg:city":"Garrucha",
    "sg:orig_category":"Inmobiliaria (agencias)",
    "sg:phone":"+34 950 13 36 58",
    "sg:postcode":"04630",
    "sg:province":"Almer\u00eda",
    "wof:name":"Wrights Overse As Properties Uk S.l.",
    "wof:placetype":"venue"
},
  "geometry": {"coordinates":[-1.822052002,37.1795387268],"type":"Point"}
}