{
  "type": "Feature",
  "properties": {
    "addr:full":"Cami Ral, 552 Mataro Barcelona 08302",
    "addr:housenumber":"552",
    "addr:postcode":"08302",
    "addr:street":"Ral",
    "iso:country":"ES",
    "sg:address":"Cami Ral, 552",
    "sg:city":"Mataro",
    "sg:orig_category":"Psic\u00d3logos",
    "sg:phone":"+34 937 99 65 96",
    "sg:postcode":"08302",
    "sg:province":"Barcelona",
    "wof:name":"Vilana Campa Ramon",
    "wof:placetype":"venue"
},
  "geometry": {"coordinates":[2.440114975,41.5341377258],"type":"Point"}
}