{
  "type": "Feature",
  "properties": {
    "iso:country":"ES",
    "sg:address":"Ptda Cachapet, 48",
    "sg:city":"Crevillente",
    "sg:orig_category":"Promotores Constructores",
    "sg:phone":"+34 966 68 07 96",
    "sg:postcode":"03330",
    "sg:province":"Alicante",
    "wof:name":"Tomas Alfonso Cayetano",
    "wof:placetype":"venue"
},
  "geometry": {"coordinates":[-0.8163840175,38.2342567444],"type":"Point"}
}