{
  "type": "Feature",
  "properties": {
    "iso:country":"ES",
    "sg:address":"Carrer de Catalunya, S/n",
    "sg:city":"Santa Perpetua De Mogoda",
    "sg:orig_category":"Construcciones Met\u00c1licas",
    "sg:phone":"+34 935 44 84 58",
    "sg:postcode":"08130",
    "sg:province":"Barcelona",
    "wof:name":"Guirao Construcciones Metalicas S.a.",
    "wof:placetype":"venue"
},
  "geometry": {"coordinates":[2.1794500351,41.5390434265],"type":"Point"}
}