{
  "type": "Feature",
  "properties": {
    "iso:country":"ES",
    "sg:address":"Av Arraona, 35",
    "sg:city":"Barbera Valles",
    "sg:orig_category":"Maquinaria Neum\u00c1tica",
    "sg:phone":"+34 937 18 90 39",
    "sg:postcode":"08210",
    "sg:province":"Barcelona",
    "wof:name":"Manequip S.l.",
    "wof:placetype":"venue"
},
  "geometry": {"coordinates":[2.1480300426,41.5246238708],"type":"Point"}
}