{
  "type": "Feature",
  "properties": {
    "addr:full":"Calle de Rincon, S/n Sada La Coru\u00f1a 15160",
    "addr:housenumber":"/ n",
    "addr:postcode":"15160",
    "addr:street":"Calle De Rincon S;La",
    "iso:country":"ES",
    "sg:address":"Calle de Rincon, S/n",
    "sg:city":"Sada",
    "sg:orig_category":"Ropa Para Ni\u00d1os (al Por Menor)",
    "sg:phone":"+34 981 62 15 48",
    "sg:postcode":"15160",
    "sg:province":"La Coru\u00f1a",
    "wof:name":"Retacos S.c.",
    "wof:placetype":"venue"
},
  "geometry": {"coordinates":[-8.253528595,43.3509902954],"type":"Point"}
}