{
  "type": "Feature",
  "properties": {
    "iso:country":"ES",
    "sg:address":"Calle de Carcel, 21",
    "sg:city":"Puebla Sanabria",
    "sg:orig_category":"Bazares, Art\u00cdculos De Limpieza Y De Cocina (al Por Menor)",
    "sg:phone":"+34 980 62 09 26",
    "sg:postcode":"49300",
    "sg:province":"Zamora",
    "wof:name":"Vaquemar S.l.",
    "wof:placetype":"venue"
},
  "geometry": {"coordinates":[-6.6336560249,42.0530014038],"type":"Point"}
}