{
  "type": "Feature",
  "properties": {
    "addr:full":"Calle de Mayor, 18 Zaragoza Zaragoza 50011",
    "addr:housenumber":"18",
    "addr:postcode":"50011",
    "addr:street":"Calle De Mayor",
    "iso:country":"ES",
    "sg:address":"Calle de Mayor, 18",
    "sg:city":"Zaragoza",
    "sg:orig_category":"Electricidad: Instaladores",
    "sg:phone":"+34 976 53 84 83",
    "sg:postcode":"50011",
    "sg:province":"Zaragoza",
    "wof:name":"Montajes Electricos Vidao S.l.",
    "wof:placetype":"venue"
},
  "geometry": {"coordinates":[-0.9425899982,41.6600761414],"type":"Point"}
}