{
  "type": "Feature",
  "properties": {
    "addr:full":"Carr Bisbe Carrasco, 12 Eivissa Islas Baleares 07800",
    "addr:housenumber":"12",
    "addr:postcode":"07800",
    "addr:street":"Carr Bisbe Carrasco",
    "iso:country":"ES",
    "sg:address":"Carr Bisbe Carrasco, 12",
    "sg:city":"Eivissa",
    "sg:orig_category":"Ropa Para Caballeros (al Por Menor)",
    "sg:phone":"+34 971 30 73 55",
    "sg:postcode":"07800",
    "sg:province":"Islas Baleares",
    "wof:name":"Clemente Castellanos Juana",
    "wof:placetype":"venue"
},
  "geometry": {"coordinates":[1.4303369522,38.9095153809],"type":"Point"}
}