{
  "type": "Feature",
  "properties": {
    "addr:full":"Avda Paz, 59 Yecla Murcia 30510",
    "addr:housenumber":"59",
    "addr:postcode":"30510",
    "addr:street":"Avda Paz",
    "iso:country":"ES",
    "sg:address":"Avda Paz, 59",
    "sg:city":"Yecla",
    "sg:orig_category":"Fabricaci\u00d3n De Mobiliario De Oficina",
    "sg:phone":"+34 968 75 31 78",
    "sg:postcode":"30510",
    "sg:province":"Murcia",
    "wof:name":"Jimenez Garcia Carlos",
    "wof:placetype":"venue"
},
  "geometry": {"coordinates":[-1.1238310337,38.6156082153],"type":"Point"}
}