{
  "type": "Feature",
  "properties": {
    "addr:full":"Carrer de Moli Dels Frares, S/n Sant Vicen\u00c7 Dels Horts Barcelona 08620",
    "addr:housenumber":"s",
    "addr:postcode":"08620",
    "addr:street":"Carrer De Moli Dels Frares;/ N",
    "iso:country":"ES",
    "sg:address":"Carrer de Moli Dels Frares, S/n",
    "sg:city":"Sant Vicen\u00c7 Dels Horts",
    "sg:orig_category":"Distribuci\u00d3n De Petr\u00d3leo Y Derivados",
    "sg:phone":"+34 936 56 70 23",
    "sg:postcode":"08620",
    "sg:province":"Barcelona",
    "wof:name":"Estacio Servei Moli Dels Frares S.l",
    "wof:placetype":"venue"
},
  "geometry": {"coordinates":[1.9983279705,41.4035797119],"type":"Point"}
}