{
  "type": "Feature",
  "properties": {
    "iso:country":"ES",
    "sg:address":"Carr Francesc Layret, 10",
    "sg:city":"Badalona",
    "sg:orig_category":"Reposter\u00cdas",
    "sg:phone":"+34 933 84 29 01",
    "sg:postcode":"08911",
    "sg:province":"Barcelona",
    "wof:name":"Prats Santigosa Antoni",
    "wof:placetype":"venue"
},
  "geometry": {"coordinates":[2.2461879253,41.4494628906],"type":"Point"}
}