{
  "type": "Feature",
  "properties": {
    "iso:country":"ES",
    "sg:address":"Pasaje Alcor, 3",
    "sg:city":"Ciudad Real",
    "sg:orig_category":"Lencer\u00cda Femenina, Corseter\u00cda, Trajes De Ba\u00d1o (al Por Menor)",
    "sg:phone":"+34 926 23 11 49",
    "sg:postcode":"13001",
    "sg:province":"Ciudad Real",
    "wof:name":"Gomez Ruiz-flores Maria De Los Angeles",
    "wof:placetype":"venue"
},
  "geometry": {"coordinates":[-3.9279243946,38.9830245972],"type":"Point"}
}