{
  "type": "Feature",
  "properties": {
    "iso:country":"ES",
    "sg:address":"Av Rosas, 1",
    "sg:city":"Lepe",
    "sg:orig_category":"Turismo: Lugares, Circuitos Y Curiosidades",
    "sg:phone":"+34 959 38 22 12",
    "sg:postcode":"21440",
    "sg:province":"Huelva",
    "wof:name":"Fernandez Prieto Jose",
    "wof:placetype":"venue"
},
  "geometry": {"coordinates":[-7.1934142113,37.2580604553],"type":"Point"}
}