{
  "type": "Feature",
  "properties": {
    "iso:country":"ES",
    "sg:address":"Avda Felipe Iv De, 8",
    "sg:city":"Donostia-san Sebastian",
    "sg:orig_category":"Aparatos, Sistemas De Tele",
    "sg:phone":"+34 943 45 67 55",
    "sg:postcode":"20011",
    "sg:province":"Guip\u00f9zcoa",
    "sg:website":"www.cervera.com",
    "wof:name":"Cervera Comunicaciones S.l",
    "wof:placetype":"venue"
},
  "geometry": {"coordinates":[-1.9752869606,43.3053779602],"type":"Point"}
}