{
  "type": "Feature",
  "properties": {
    "iso:country":"ES",
    "sg:address":"Calle de Cartagena, 30",
    "sg:city":"Rozas De Madrid",
    "sg:orig_category":"Promotores Constructores",
    "sg:phone":"+34 916 39 27 31",
    "sg:postcode":"28230",
    "sg:province":"Madrid",
    "wof:name":"Aguayo Alvarez Tomas",
    "wof:placetype":"venue"
},
  "geometry": {"coordinates":[-3.889493227,40.4912109375],"type":"Point"}
}