{
  "type": "Feature",
  "properties": {
    "iso:country":"ES",
    "sg:address":"Calle de Carmen, 17",
    "sg:city":"Torremolinos",
    "sg:orig_category":"Estancos",
    "sg:phone":"+34 952 37 43 51",
    "sg:postcode":"29620",
    "sg:province":"M\u00e1laga",
    "wof:name":"Quesada Del Cid Maria",
    "wof:placetype":"venue"
},
  "geometry": {"coordinates":[-4.5024490356,36.6118354797],"type":"Point"}
}