{
  "type": "Feature",
  "properties": {
    "iso:country":"ES",
    "sg:address":"Calle de Paulino Mendivil, 15",
    "sg:city":"Arenas -areeta",
    "sg:orig_category":"Ropa Y Art\u00cdculos Pre",
    "sg:phone":"+34 944 80 03 93",
    "sg:postcode":"48930",
    "sg:province":"Vizcaya",
    "wof:name":"Bidea Epelde Fernando",
    "wof:placetype":"venue"
},
  "geometry": {"coordinates":[-3.0134649277,43.32629776],"type":"Point"}
}