{
  "type": "Feature",
  "properties": {
    "addr:full":"Avgd Ausias March, 57 Burjassot Valencia 46100",
    "addr:housenumber":"57",
    "addr:postcode":"46100",
    "addr:street":"March",
    "iso:country":"ES",
    "sg:address":"Avgd Ausias March, 57",
    "sg:city":"Burjassot",
    "sg:orig_category":"Centros De Educaci\u00d3n Especial",
    "sg:phone":"+34 963 64 62 82",
    "sg:postcode":"46100",
    "sg:province":"Valencia",
    "wof:name":"Escuela Infantil Villa Amparo S.l.",
    "wof:placetype":"venue"
},
  "geometry": {"coordinates":[-0.4108549953,39.5149345398],"type":"Point"}
}