{
  "type": "Feature",
  "properties": {
    "addr:full":"Calle de Jaime Casasus, 70 Pina De Ebro Zaragoza 50750",
    "addr:housenumber":"70",
    "addr:postcode":"50750",
    "addr:street":"Calle De Jaime Casasus",
    "iso:country":"ES",
    "sg:address":"Calle de Jaime Casasus, 70",
    "sg:city":"Pina De Ebro",
    "sg:orig_category":"Garajes De Veh\u00cdculos",
    "sg:phone":"+34 976 16 50 92",
    "sg:postcode":"50750",
    "sg:province":"Zaragoza",
    "wof:name":"Galligo Polo Delfin",
    "wof:placetype":"venue"
},
  "geometry": {"coordinates":[-0.5311689973,41.4894981384],"type":"Point"}
}