{
  "type": "Feature",
  "properties": {
    "addr:full":"Calle de Fray Ceferino Gonzalez, 6 Madrid Madrid 28005",
    "addr:housenumber":"6",
    "addr:postcode":"28005",
    "addr:street":"Calle De Fray Ceferino Gonzalez",
    "iso:country":"ES",
    "sg:address":"Calle de Fray Ceferino Gonzalez, 6",
    "sg:city":"Madrid",
    "sg:orig_category":"Teatro, Ballet, Danza (agrupaciones, Compa\u00d1\u00cdas)",
    "sg:phone":"+34 914 67 05 32",
    "sg:postcode":"28005",
    "sg:province":"Madrid",
    "wof:name":"Shaw  Stephan",
    "wof:placetype":"venue"
},
  "geometry": {"coordinates":[-3.7061800957,40.4089622498],"type":"Point"}
}