{
  "type": "Feature",
  "properties": {
    "addr:full":"Calle de Doctor Cajal, 16 Tomelloso Ciudad Real 13700",
    "addr:housenumber":"16",
    "addr:postcode":"13700",
    "addr:street":"Calle De Doctor Cajal",
    "iso:country":"ES",
    "sg:address":"Calle de Doctor Cajal, 16",
    "sg:city":"Tomelloso",
    "sg:orig_category":"Asesor\u00cda Fiscal Y Jur\u00cddica",
    "sg:phone":"+34 926 51 52 62",
    "sg:postcode":"13700",
    "sg:province":"Ciudad Real",
    "wof:name":"Lopez Lara Santos",
    "wof:placetype":"venue"
},
  "geometry": {"coordinates":[-3.0227322578,39.1513938904],"type":"Point"}
}