{
  "type": "Feature",
  "properties": {
    "addr:full":"F. Cerrillar, S/n Mandayona Guadalajara 19294",
    "addr:housenumber":"s",
    "addr:postcode":"19294",
    "addr:street":"F. Cerrillar;/ N Mandayona",
    "iso:country":"ES",
    "sg:address":"F. Cerrillar, S/n",
    "sg:city":"Mandayona",
    "sg:orig_category":"Cr\u00cda De Corderos Y De Cabras",
    "sg:phone":"+34 949 82 82 12",
    "sg:postcode":"19294",
    "sg:province":"Guadalajara",
    "wof:name":"Marquez Pati\u00f1o Maria Victoria",
    "wof:placetype":"venue"
},
  "geometry": {"coordinates":[-2.749174118,40.956401825],"type":"Point"}
}