{
  "type": "Feature",
  "properties": {
    "addr:full":"Carrer de Sureda, 6 Palma Islas Baleares 07007",
    "addr:housenumber":"6",
    "addr:postcode":"07007",
    "addr:street":"Carrer De Sureda",
    "iso:country":"ES",
    "sg:address":"Carrer de Sureda, 6",
    "sg:city":"Palma",
    "sg:orig_category":"Impuestos, Tesoro P\u00dablico",
    "sg:phone":"+34 971 24 95 12",
    "sg:postcode":"07007",
    "sg:province":"Islas Baleares",
    "wof:name":"Luis Arin Jose De",
    "wof:placetype":"venue"
},
  "geometry": {"coordinates":[2.6711978912,39.5715942383],"type":"Point"}
}