{
  "type": "Feature",
  "properties": {
    "iso:country":"ES",
    "sg:address":"Calle de Magnolios, 23",
    "sg:city":"Gri\u00f1on",
    "sg:orig_category":"Ingeniero",
    "sg:phone":"+34 918 14 02 58",
    "sg:postcode":"28971",
    "sg:province":"Madrid",
    "wof:name":"Segoviano Bueno Antonio",
    "wof:placetype":"venue"
},
  "geometry": {"coordinates":[-3.8633909225,40.2180290222],"type":"Point"}
}