{
  "type": "Feature",
  "properties": {
    "iso:country":"ES",
    "sg:address":"Calle de Antonio Machado, 1",
    "sg:city":"Chiva",
    "sg:orig_category":"Centros Empresariales",
    "sg:phone":"+34 962 52 26 13",
    "sg:postcode":"46370",
    "sg:province":"Valencia",
    "wof:name":"Vaproguis S.l.",
    "wof:placetype":"venue"
},
  "geometry": {"coordinates":[-0.7180860043,39.4728813171],"type":"Point"}
}