{
  "type": "Feature",
  "properties": {
    "iso:country":"ES",
    "sg:address":"Calle de Bartolome J. Gallardo, 1",
    "sg:city":"Badajoz",
    "sg:orig_category":"M\u00c9dicos: Ginecolog\u00cda Y Obstetricia",
    "sg:phone":"+34 924 22 49 11",
    "sg:postcode":"06001",
    "sg:province":"Badajoz",
    "wof:name":"Arbues Lacadena Jose",
    "wof:placetype":"venue"
},
  "geometry": {"coordinates":[-6.9747114182,38.8759078979],"type":"Point"}
}