{
  "type": "Feature",
  "properties": {
    "addr:full":"Del Medio, 46 S. Sebastian Gomera Santa Cruz De Tenerife 38800",
    "addr:housenumber":"46",
    "addr:postcode":"38800",
    "addr:street":"Del Medio;S. Sebastian Gomera",
    "iso:country":"ES",
    "sg:address":"Del Medio, 46",
    "sg:city":"S. Sebastian Gomera",
    "sg:orig_category":"Asociaciones Humanitarias, De Cooperaci\u00d3n, De Acci\u00d3n Social",
    "sg:phone":"+34 922 87 10 56",
    "sg:postcode":"38800",
    "sg:province":"Santa Cruz De Tenerife",
    "wof:name":"Organizacion Impulsora De Discapacitados",
    "wof:placetype":"venue"
},
  "geometry": {"coordinates":[-17.1105136871,28.0907344818],"type":"Point"}
}