{
  "type": "Feature",
  "properties": {
    "iso:country":"ES",
    "sg:address":"Carrer de Mestre Josep Recasens, 20",
    "sg:city":"Vilafranca Penedes",
    "sg:orig_category":"Centros Empresariales",
    "sg:phone":"+34 938 90 43 75",
    "sg:postcode":"08720",
    "sg:province":"Barcelona",
    "wof:name":"Nu\u00f1ez Ortega Maria Del Rosario",
    "wof:placetype":"venue"
},
  "geometry": {"coordinates":[1.6957509518,41.3416862488],"type":"Point"}
}