{
  "type": "Feature",
  "properties": {
    "addr:full":"Praz Martin Gomez Abal, 6 Vilagarcia Pontevedra 36600",
    "addr:housenumber":"6",
    "addr:postcode":"36600",
    "addr:street":"Praz Martin Gomez Abal",
    "iso:country":"ES",
    "sg:address":"Praz Martin Gomez Abal, 6",
    "sg:city":"Vilagarcia",
    "sg:orig_category":"Molduras, Junquillos, Listones Y Molduras Perforadas",
    "sg:phone":"+34 986 50 34 46",
    "sg:postcode":"36600",
    "sg:province":"Pontevedra",
    "wof:name":"Torres Mesego Amalia",
    "wof:placetype":"venue"
},
  "geometry": {"coordinates":[-8.7672948837,42.5951766968],"type":"Point"}
}