{
  "type": "Feature",
  "properties": {
    "addr:full":"Calle de Isa, S/n Argana Alta Las Palmas 35500",
    "addr:housenumber":"s / n",
    "addr:postcode":"35500",
    "addr:street":"Calle De Isa",
    "iso:country":"ES",
    "sg:address":"Calle de Isa, S/n",
    "sg:city":"Argana Alta",
    "sg:orig_category":"Lecher\u00cdas",
    "sg:phone":"+34 928 80 52 65",
    "sg:postcode":"35500",
    "sg:province":"Las Palmas",
    "wof:name":"Lanzarote Distribuciones S.c.p.",
    "wof:placetype":"venue"
},
  "geometry": {"coordinates":[-13.5708093643,28.9768295288],"type":"Point"}
}