{
  "type": "Feature",
  "properties": {
    "addr:full":"Calle de Javier Barkaiztegi, 17 Donostia-san Sebastian Guip\u00f9zcoa 20010",
    "addr:housenumber":"17",
    "addr:postcode":"20010",
    "addr:street":"Calle De Javier Barkaiztegi",
    "iso:country":"ES",
    "sg:address":"Calle de Javier Barkaiztegi, 17",
    "sg:city":"Donostia-san Sebastian",
    "sg:orig_category":"M\u00c9dicos: Foniatr\u00cda Y Logopedia",
    "sg:phone":"+34 943 47 15 00",
    "sg:postcode":"20010",
    "sg:province":"Guip\u00f9zcoa",
    "wof:name":"Marta Fernandez Barrutia",
    "wof:placetype":"venue"
},
  "geometry": {"coordinates":[-1.981801033,43.3055763245],"type":"Point"}
}