{
  "type": "Feature",
  "properties": {
    "addr:full":"Avda Bucaramanga, S/n Madrid Madrid 28033",
    "addr:housenumber":"s / n",
    "addr:postcode":"28033",
    "addr:street":"Avda Bucaramanga",
    "iso:country":"ES",
    "sg:address":"Avda Bucaramanga, S/n",
    "sg:city":"Madrid",
    "sg:orig_category":"Cl\u00cdnicas Dentales",
    "sg:phone":"+34 913 81 60 08",
    "sg:postcode":"28033",
    "sg:province":"Madrid",
    "wof:name":"Odontologia Integral Russo Delgado S.l.",
    "wof:placetype":"venue"
},
  "geometry": {"coordinates":[-3.6358640194,40.4722099304],"type":"Point"}
}