{
  "type": "Feature",
  "properties": {
    "addr:full":"Pl Major, 2 Montblanc Tarragona 43400",
    "addr:housenumber":"2",
    "addr:postcode":"43400",
    "addr:street":"Pl Major",
    "iso:country":"ES",
    "sg:address":"Pl Major, 2",
    "sg:city":"Montblanc",
    "sg:orig_category":"Estancos",
    "sg:phone":"+34 977 86 08 56",
    "sg:postcode":"43400",
    "sg:province":"Tarragona",
    "wof:name":"Farre Min Josefa",
    "wof:placetype":"venue"
},
  "geometry": {"coordinates":[1.1616799831,41.3764686584],"type":"Point"}
}