{
  "type": "Feature",
  "properties": {
    "addr:full":"Calle de Alberto Aguilera, 5 Madrid Madrid 28015",
    "addr:housenumber":"5",
    "addr:postcode":"28015",
    "addr:street":"Calle De Alberto Aguilera",
    "iso:country":"ES",
    "sg:address":"Calle de Alberto Aguilera, 5",
    "sg:city":"Madrid",
    "sg:orig_category":"Asesor\u00cdas En Comunicaci\u00d3n",
    "sg:phone":"+34 914 45 06 84",
    "sg:postcode":"28015",
    "sg:province":"Madrid",
    "wof:name":"Do It Comunicacion Y Marketing S.l.",
    "wof:placetype":"venue"
},
  "geometry": {"coordinates":[-3.7079269886,40.4297409058],"type":"Point"}
}