{
  "type": "Feature",
  "properties": {
    "iso:country":"ES",
    "sg:address":"Avda Constitucion, 164",
    "sg:city":"Torrejon Ardoz",
    "sg:orig_category":"Discotecas Y Salas De Baile",
    "sg:phone":"+34 916 77 03 73",
    "sg:postcode":"28850",
    "sg:province":"Madrid",
    "wof:name":"Importrop 2000 S.l.",
    "wof:placetype":"venue"
},
  "geometry": {"coordinates":[-3.4579238892,40.4598236084],"type":"Point"}
}