{
  "type": "Feature",
  "properties": {
    "addr:full":"Calle de Ausias March, 16 Paiporta Valencia 46200",
    "addr:housenumber":"16",
    "addr:postcode":"46200",
    "addr:street":"Calle De Ausias March",
    "iso:country":"ES",
    "sg:address":"Calle de Ausias March, 16",
    "sg:city":"Paiporta",
    "sg:orig_category":"Organizaciones Internacionales",
    "sg:phone":"+34 963 97 64 53",
    "sg:postcode":"46200",
    "sg:province":"Valencia",
    "wof:name":"Asociacion Humanitaria Apahu",
    "wof:placetype":"venue"
},
  "geometry": {"coordinates":[-0.4166001081,39.4295005798],"type":"Point"}
}