{
  "type": "Feature",
  "properties": {
    "iso:country":"ES",
    "sg:address":"Carrer de Salamanca, 11",
    "sg:city":"Monovar",
    "sg:orig_category":"Televisi\u00d3n, V\u00cddeo: Aparatos Y Accesorios (venta)",
    "sg:phone":"+34 965 47 25 28",
    "sg:postcode":"03640",
    "sg:province":"Alicante",
    "wof:name":"Electronica Corbi Hermanos S.l.",
    "wof:placetype":"venue"
},
  "geometry": {"coordinates":[-0.8412749767,38.4380187988],"type":"Point"}
}