{
  "type": "Feature",
  "properties": {
    "addr:full":"Calle de Kandela Zubieta Kalea, 21 Leioa Vizcaya 48940",
    "addr:housenumber":"21",
    "addr:postcode":"48940",
    "addr:street":"Calle De Kandela Zubieta Kalea",
    "iso:country":"ES",
    "sg:address":"Calle de Kandela Zubieta Kalea, 21",
    "sg:city":"Leioa",
    "sg:orig_category":"Asesor\u00cda Para La Organizaci\u00d3n Y Gesti\u00d3n Del Transporte",
    "sg:phone":"+34 944 80 31 12",
    "sg:postcode":"48940",
    "sg:province":"Vizcaya",
    "wof:name":"Euskorreo Servicio Postal Vasco",
    "wof:placetype":"venue"
},
  "geometry": {"coordinates":[-2.9852359295,43.3218650818],"type":"Point"}
}