{
  "type": "Feature",
  "properties": {
    "iso:country":"ES",
    "sg:address":"Ctra Camporrobles, Km. 0002,0",
    "sg:city":"Utiel",
    "sg:orig_category":"Productores Recolectores, Venta Directa De Vinos",
    "sg:phone":"+34 962 13 91 23",
    "sg:postcode":"46300",
    "sg:province":"Valencia",
    "wof:name":"Sat Ecovin 192 C.v.",
    "wof:placetype":"venue"
},
  "geometry": {"coordinates":[-1.2122290134,39.5694618225],"type":"Point"}
}