{
  "type": "Feature",
  "properties": {
    "addr:full":"Rua Pe\u00d1a, 4 Porri\u00f1o Pontevedra 36400",
    "addr:housenumber":"4",
    "addr:postcode":"36400",
    "addr:street":"Rua Pen\u0303A",
    "iso:country":"ES",
    "sg:address":"Rua Pe\u00d1a, 4",
    "sg:city":"Porri\u00f1o",
    "sg:orig_category":"Agencias De Viajes",
    "sg:phone":"+34 986 33 80 69",
    "sg:postcode":"36400",
    "sg:province":"Pontevedra",
    "sg:website":"www.marsans.es",
    "wof:name":"Viajes Marsans S.a.",
    "wof:placetype":"venue"
},
  "geometry": {"coordinates":[-8.6179990768,42.1610298157],"type":"Point"}
}