{
  "type": "Feature",
  "properties": {
    "iso:country":"ES",
    "sg:address":"Avda Daniel Feo Feo, 32",
    "sg:city":"Chafiras",
    "sg:orig_category":"Inform\u00c1tica (estudios, Servicios, Asesor\u00cda, Formaci\u00d3n)",
    "sg:phone":"+34 922 73 64 95",
    "sg:postcode":"38639",
    "sg:province":"Santa Cruz De Tenerife",
    "sg:website":"www.chafirasinformatica.com",
    "wof:name":"Donate Donate Pedro Jose",
    "wof:placetype":"venue"
},
  "geometry": {"coordinates":[-16.6115474701,28.0350246429],"type":"Point"}
}