{
  "type": "Feature",
  "properties": {
    "addr:full":"Avda Repelega, 5 Portugalete Vizcaya 48920",
    "addr:housenumber":"5",
    "addr:postcode":"48920",
    "addr:street":"Avda Repelega",
    "iso:country":"ES",
    "sg:address":"Avda Repelega, 5",
    "sg:city":"Portugalete",
    "sg:orig_category":"Talleres: Ropa A Medida",
    "sg:phone":"+34 944 95 51 42",
    "sg:postcode":"48920",
    "sg:province":"Vizcaya",
    "wof:name":"Mendez Cibreiro Manuel",
    "wof:placetype":"venue"
},
  "geometry": {"coordinates":[-3.0178859234,43.3150138855],"type":"Point"}
}