{
  "type": "Feature",
  "properties": {
    "iso:country":"ES",
    "sg:address":"Calle de Bembibre, 4",
    "sg:city":"Fuenlabrada",
    "sg:orig_category":"Molduras, Junquillos, Listones Y Molduras Perforadas",
    "sg:phone":"+34 916 42 07 18",
    "sg:postcode":"28947",
    "sg:province":"Madrid",
    "wof:name":"Tazonsy Desarrollo S.l.",
    "wof:placetype":"venue"
},
  "geometry": {"coordinates":[-3.746118784,40.2676811218],"type":"Point"}
}