{
  "type": "Feature",
  "properties": {
    "addr:full":"Av La Marina, 45 Benissa Alicante 03720",
    "addr:housenumber":"45",
    "addr:postcode":"03720",
    "addr:street":"Av La Marina",
    "iso:country":"ES",
    "sg:address":"Av La Marina, 45",
    "sg:city":"Benissa",
    "sg:orig_category":"T\u00c9cnicos Veterinarios",
    "sg:phone":"+34 965 74 84 58",
    "sg:postcode":"03720",
    "sg:province":"Alicante",
    "wof:name":"Molla Carrio Isidoro",
    "wof:placetype":"venue"
},
  "geometry": {"coordinates":[0.0841030031,38.6644058228],"type":"Point"}
}