{
  "type": "Feature",
  "properties": {
    "iso:country":"ES",
    "sg:address":"Pg Generalitat, 26",
    "sg:city":"Vic",
    "sg:orig_category":"\u00d3ptica: Instrumentos (fabricaci\u00d3n)",
    "sg:phone":"+34 938 85 46 52",
    "sg:postcode":"08500",
    "sg:province":"Barcelona",
    "wof:name":"Optica Vic S.cv.",
    "wof:placetype":"venue"
},
  "geometry": {"coordinates":[2.2531199455,41.9230384827],"type":"Point"}
}