{
  "type": "Feature",
  "properties": {
    "addr:full":"Calle de Real De Malaga, 49 Gabia Grande Granada 18110",
    "addr:housenumber":"49",
    "addr:postcode":"18110",
    "addr:street":"Calle De Real De Malaga",
    "iso:country":"ES",
    "sg:address":"Calle de Real De Malaga, 49",
    "sg:city":"Gabia Grande",
    "sg:orig_category":"Notarios",
    "sg:phone":"+34 958 58 19 76",
    "sg:postcode":"18110",
    "sg:province":"Granada",
    "wof:name":"Santos Sanchez Maria Victoria",
    "wof:placetype":"venue"
},
  "geometry": {"coordinates":[-3.6695349216,37.1342582703],"type":"Point"}
}