{
  "type": "Feature",
  "properties": {
    "addr:full":"Colegio, 1 Arija Burgos 09570",
    "addr:postcode":"09570",
    "iso:country":"ES",
    "sg:address":"Colegio, 1",
    "sg:city":"Arija",
    "sg:orig_category":"Iglesia Cat\u00d3lica",
    "sg:phone":"+34 942 77 31 20",
    "sg:postcode":"09570",
    "sg:province":"Burgos",
    "wof:name":"Parroquia De La Asuncion",
    "wof:placetype":"venue"
},
  "geometry": {"coordinates":[-3.9461290836,42.9917564392],"type":"Point"}
}