{
  "type": "Feature",
  "properties": {
    "iso:country":"ES",
    "sg:address":"Carrer de Figueres, 17",
    "sg:city":"Granollers",
    "sg:orig_category":"Droguer\u00cdas (al Por Menor)",
    "sg:phone":"+34 938 49 02 50",
    "sg:postcode":"08402",
    "sg:province":"Barcelona",
    "wof:name":"Martin Wic Antonio",
    "wof:placetype":"venue"
},
  "geometry": {"coordinates":[2.293366909,41.6150398254],"type":"Point"}
}