{
  "type": "Feature",
  "properties": {
    "iso:country":"ES",
    "sg:address":"Calle de Cristobal Colon, 39",
    "sg:city":"Ayamonte",
    "sg:orig_category":"Colchones (fabricaci\u00d3n, Al Por Mayor, Al Por Menor)",
    "sg:phone":"+34 959 32 05 73",
    "sg:postcode":"21400",
    "sg:province":"Huelva",
    "wof:name":"Rasco Duarte Rodolfo",
    "wof:placetype":"venue"
},
  "geometry": {"coordinates":[-7.4083447456,37.2140274048],"type":"Point"}
}