{
  "type": "Feature",
  "properties": {
    "iso:country":"ES",
    "sg:address":"Pol Ind El Rallat, 1",
    "sg:city":"Xeresa",
    "sg:orig_category":"Construcciones Met\u00c1licas",
    "sg:phone":"+34 962 89 56 90",
    "sg:postcode":"46790",
    "sg:province":"Valencia",
    "wof:name":"Metalicas Diaz Alcina S.l.",
    "wof:placetype":"venue"
},
  "geometry": {"coordinates":[-0.2175740004,39.0116996765],"type":"Point"}
}