{
  "type": "Feature",
  "properties": {
    "iso:country":"ES",
    "sg:address":"Calle de Bizkargi, 24",
    "sg:city":"Bilbao",
    "sg:orig_category":"Agencias Y Agentes Comerciales, Representantes",
    "sg:phone":"+34 944 44 64 49",
    "sg:postcode":"48002",
    "sg:province":"Vizcaya",
    "wof:name":"Roma\u00f1a Fernandez Juan Luis",
    "wof:placetype":"venue"
},
  "geometry": {"coordinates":[-2.9455962181,43.2488555908],"type":"Point"}
}