{
  "type": "Feature",
  "properties": {
    "addr:full":"Calle de Calvario, 6 Tomelloso Ciudad Real 13700",
    "addr:housenumber":"6",
    "addr:postcode":"13700",
    "addr:street":"Calle De Calvario",
    "iso:country":"ES",
    "sg:address":"Calle de Calvario, 6",
    "sg:city":"Tomelloso",
    "sg:orig_category":"M\u00c9dicos: An\u00c1lisis Cl\u00cdnicos",
    "sg:phone":"+34 926 50 67 14",
    "sg:postcode":"13700",
    "sg:province":"Ciudad Real",
    "wof:name":"Villasante Saez Jose Maria",
    "wof:placetype":"venue"
},
  "geometry": {"coordinates":[-3.024096489,39.1555671692],"type":"Point"}
}