{
  "type": "Feature",
  "properties": {
    "addr:full":"Urano, 19 Mijas Costa M\u00e1laga 29649",
    "addr:housenumber":"19",
    "addr:postcode":"29649",
    "addr:street":"Urano",
    "iso:country":"ES",
    "sg:address":"Urano, 19",
    "sg:city":"Mijas Costa",
    "sg:orig_category":"Inmobiliaria (agencias)",
    "sg:phone":"+34 952 93 02 64",
    "sg:postcode":"29649",
    "sg:province":"M\u00e1laga",
    "wof:name":"Cantor/,s.l.",
    "wof:placetype":"venue"
},
  "geometry": {"coordinates":[-4.704668045,36.4974250793],"type":"Point"}
}