{
  "type": "Feature",
  "properties": {
    "iso:country":"ES",
    "sg:address":"Pl Enric Morera, 17",
    "sg:city":"Sabadell",
    "sg:orig_category":"Molduras, Junquillos, Listones Y Molduras Perforadas",
    "sg:phone":"+34 937 11 00 99",
    "sg:postcode":"08203",
    "sg:province":"Barcelona",
    "wof:name":"2005 Miju .sc.p",
    "wof:placetype":"venue"
},
  "geometry": {"coordinates":[2.105464,41.529633],"type":"Point"}
}