{
  "type": "Feature",
  "properties": {
    "addr:full":"Av Pas D'arro, 25 Vielha Lleida 25530",
    "addr:housenumber":"25",
    "addr:postcode":"25530",
    "addr:street":"Av Pas D'Arro",
    "iso:country":"ES",
    "sg:address":"Av Pas D'arro, 25",
    "sg:city":"Vielha",
    "sg:orig_category":"Deportes Y Programas De Aventura",
    "sg:phone":"+34 973 64 24 44",
    "sg:postcode":"25530",
    "sg:province":"Lleida",
    "wof:name":"Mountain Quality S.l.",
    "wof:placetype":"venue"
},
  "geometry": {"coordinates":[0.7975779772,42.7008934021],"type":"Point"}
}