{
  "type": "Feature",
  "properties": {
    "addr:full":"Av Comtes De Pallars, 26 Sort Lleida 25560",
    "addr:housenumber":"26",
    "addr:postcode":"25560",
    "addr:street":"Av Comtes De Pallars",
    "iso:country":"ES",
    "sg:address":"Av Comtes De Pallars, 26",
    "sg:city":"Sort",
    "sg:classifiers":[
        {
            "category":"Tea Room",
            "subcategory":"None",
            "type":"Food & Drink"
        }
    ],
    "sg:phone":"+34 973 62 00 19",
    "sg:postcode":"25560",
    "sg:province":"Lleida",
    "sg:tags":[
        "snack"
    ],
    "wof:name":"Rodriguez Pelegrina Francisco Miguel",
    "wof:placetype":"venue"
},
  "geometry": {"coordinates":[1.1302969456,42.4113464355],"type":"Point"}
}