{
  "type": "Feature",
  "properties": {
    "iso:country":"ES",
    "sg:address":"Carrer de Josep Anselm Clave, 2",
    "sg:city":"Palma",
    "sg:orig_category":"M\u00c9dicos: Cardiolog\u00cda Y Afecciones Cardiovasculares",
    "sg:phone":"+34 971 71 43 50",
    "sg:postcode":"07002",
    "sg:province":"Islas Baleares",
    "wof:name":"Alberti Mulet Francisco",
    "wof:placetype":"venue"
},
  "geometry": {"coordinates":[2.6547660828,39.5738372803],"type":"Point"}
}