{
  "type": "Feature",
  "properties": {
    "addr:full":"Calle de Prudencio Alvaro, 60 Madrid Madrid 28027",
    "addr:housenumber":"60",
    "addr:postcode":"madrid;28027",
    "addr:street":"Calle De Prudencio Alvaro",
    "iso:country":"ES",
    "sg:address":"Calle de Prudencio Alvaro, 60",
    "sg:city":"Madrid",
    "sg:orig_category":"Mec\u00c1nico Del Autom\u00d3vil",
    "sg:phone":"+34 913 67 58 34",
    "sg:postcode":"28027",
    "sg:province":"Madrid",
    "wof:name":"Jebyr Motor S.l.",
    "wof:placetype":"venue"
},
  "geometry": {"coordinates":[-3.642772913,40.4389152527],"type":"Point"}
}