{
  "type": "Feature",
  "properties": {
    "iso:country":"ES",
    "sg:address":"Calle de Moreto, 5",
    "sg:city":"Madrid",
    "sg:orig_category":"Radiocomunicaciones, Telefon\u00cda M\u00d3vil, Radiomensajer\u00cda: Servicios, Comercializaci\u00d3n",
    "sg:phone":"+34 914 29 42 78",
    "sg:postcode":"28014",
    "sg:province":"Madrid",
    "wof:name":"May-day Radio S.l.",
    "wof:placetype":"venue"
},
  "geometry": {"coordinates":[-3.6902201176,40.4144287109],"type":"Point"}
}