{
  "type": "Feature",
  "properties": {
    "addr:full":"Eiras(san Amaro), 80 Eiras Ourense 32453",
    "addr:housenumber":"80",
    "addr:postcode":"32453",
    "addr:street":"Eiras San Amaro",
    "iso:country":"ES",
    "sg:address":"Eiras(san Amaro), 80",
    "sg:city":"Eiras",
    "sg:orig_category":"Aguas (distribuci\u00d3n, Servicios)",
    "sg:phone":"+34 988 28 03 36",
    "sg:postcode":"32453",
    "sg:province":"Ourense",
    "wof:name":"Paz Ameijeiras Alberto",
    "wof:placetype":"venue"
},
  "geometry": {"coordinates":[-8.0537939072,42.3529777527],"type":"Point"}
}