{
  "type": "Feature",
  "properties": {
    "iso:country":"ES",
    "sg:address":"Carrer de Mossen Joaquim Palet, 5",
    "sg:city":"Cornella Llobregat",
    "sg:orig_category":"Molduras, Junquillos, Listones Y Molduras Perforadas",
    "sg:phone":"+34 933 77 77 57",
    "sg:postcode":"08940",
    "sg:province":"Barcelona",
    "wof:name":"Callejas Barragan Mari Angeles",
    "wof:placetype":"venue"
},
  "geometry": {"coordinates":[2.0732319355,41.3593940735],"type":"Point"}
}