{
  "type": "Feature",
  "properties": {
    "iso:country":"ES",
    "sg:address":"Eusko Gudarien Kalea, 4",
    "sg:city":"Orio",
    "sg:orig_category":"Congelados: Productos Alimentarios (al Por Menor)",
    "sg:phone":"+34 943 83 00 24",
    "sg:postcode":"20810",
    "sg:province":"Guip\u00f9zcoa",
    "wof:name":"Eizaguirre Manterola Gabino",
    "wof:placetype":"venue"
},
  "geometry": {"coordinates":[-2.1281020641,43.2758255005],"type":"Point"}
}