{
  "type": "Feature",
  "properties": {
    "addr:full":"Ctra Pedroso, 5 Cazalla Sierra Sevilla 41370",
    "addr:housenumber":"5",
    "addr:postcode":"41370",
    "addr:street":"Ctra Pedroso",
    "iso:country":"ES",
    "sg:address":"Ctra Pedroso, 5",
    "sg:city":"Cazalla Sierra",
    "sg:orig_category":"Mec\u00c1nico Del Autom\u00d3vil",
    "sg:phone":"+34 954 88 41 66",
    "sg:postcode":"41370",
    "sg:province":"Sevilla",
    "wof:name":"Talleres Rafael Romero S.l.",
    "wof:placetype":"venue"
},
  "geometry": {"coordinates":[-5.7617869377,37.9298477173],"type":"Point"}
}