{
  "type": "Feature",
  "properties": {
    "addr:full":"Calle de Paseo Del Atlantico, S/n Conil De La Frontera C\u00e1diz 11140",
    "addr:housenumber":"s / n",
    "addr:postcode":"11140",
    "addr:street":"Calle De Paseo Del Atlantico",
    "iso:country":"ES",
    "sg:address":"Calle de Paseo Del Atlantico, S/n",
    "sg:city":"Conil De La Frontera",
    "sg:orig_category":"Molduras, Junquillos, Listones Y Molduras Perforadas",
    "sg:phone":"+34 956 44 01 97",
    "sg:postcode":"11140",
    "sg:province":"C\u00e1diz",
    "wof:name":"Ureba Vela Antonio",
    "wof:placetype":"venue"
},
  "geometry": {"coordinates":[-6.0870790482,36.2767066956],"type":"Point"}
}