{
  "type": "Feature",
  "properties": {
    "addr:full":"Avda Infantes De Lara, 34 Salas De Los Infantes Burgos 09600",
    "addr:housenumber":"34",
    "addr:postcode":"09600",
    "addr:street":"Avda Infantes De Lara",
    "iso:country":"ES",
    "sg:address":"Avda Infantes De Lara, 34",
    "sg:city":"Salas De Los Infantes",
    "sg:orig_category":"Arquitectos",
    "sg:phone":"+34 947 38 20 87",
    "sg:postcode":"09600",
    "sg:province":"Burgos",
    "wof:name":"Construcciones Axial 25 S.l.",
    "wof:placetype":"venue"
},
  "geometry": {"coordinates":[-3.2854158878,42.0222358704],"type":"Point"}
}