{
  "type": "Feature",
  "properties": {
    "addr:full":"C/ Casinos, 8 Terramelar Valencia 46980",
    "addr:housenumber":"8",
    "addr:postcode":"46980",
    "addr:street":"C / Casinos",
    "iso:country":"ES",
    "sg:address":"C/ Casinos, 8",
    "sg:city":"Terramelar",
    "sg:orig_category":"Contables",
    "sg:phone":"+34 961 37 17 59",
    "sg:postcode":"46980",
    "sg:province":"Valencia",
    "wof:name":"Viauno S.l.",
    "wof:placetype":"venue"
},
  "geometry": {"coordinates":[-0.4395389855,39.500629425],"type":"Point"}
}