{
  "type": "Feature",
  "properties": {
    "iso:country":"ES",
    "sg:address":"Calle de Salon Terraza, S/n",
    "sg:city":"Caravaca Cruz",
    "sg:orig_category":"Pintura Y Barniz (al Por Menor)",
    "sg:phone":"+34 968 70 78 26",
    "sg:postcode":"30400",
    "sg:province":"Murcia",
    "wof:name":"Toral Gomez Antonio",
    "wof:placetype":"venue"
},
  "geometry": {"coordinates":[-1.8604681492,38.1044921875],"type":"Point"}
}