{
  "type": "Feature",
  "properties": {
    "addr:full":"Calle de Eguiluz, 2 Jerez De La Frontera C\u00e1diz 11402",
    "addr:housenumber":"2",
    "addr:postcode":"11402",
    "addr:street":"Calle De Eguiluz",
    "iso:country":"ES",
    "sg:address":"Calle de Eguiluz, 2",
    "sg:city":"Jerez De La Frontera",
    "sg:orig_category":"Cr\u00cda De Animales",
    "sg:phone":"+34 956 32 32 60",
    "sg:postcode":"11402",
    "sg:province":"C\u00e1diz",
    "wof:name":"Vega Cruz Silvia",
    "wof:placetype":"venue"
},
  "geometry": {"coordinates":[-6.1360912323,36.6880264282],"type":"Point"}
}