{
  "type": "Feature",
  "properties": {
    "addr:full":"Fca. Pte. S. Albin, 1 Bejar Salamanca 37700",
    "addr:housenumber":"1",
    "addr:postcode":"37700",
    "addr:street":"Fca. Pte. S. Albin",
    "iso:country":"ES",
    "sg:address":"Fca. Pte. S. Albin, 1",
    "sg:city":"Bejar",
    "sg:orig_category":"Fabricaci\u00d3n De Telas Y Sedas",
    "sg:phone":"+34 923 40 13 53",
    "sg:postcode":"37700",
    "sg:province":"Salamanca",
    "wof:name":"Pablo Farras Faus S. A.",
    "wof:placetype":"venue"
},
  "geometry": {"coordinates":[-5.7728161812,40.3881263733],"type":"Point"}
}