{
  "type": "Feature",
  "properties": {
    "iso:country":"ES",
    "sg:address":"Carrer de Joan Riera, 19",
    "sg:city":"Barcelona",
    "sg:orig_category":"Reposter\u00cdas",
    "sg:phone":"+34 932 76 29 90",
    "sg:postcode":"08042",
    "sg:province":"Barcelona",
    "wof:name":"Forn Melgapa S.a.",
    "wof:placetype":"venue"
},
  "geometry": {"coordinates":[2.1743540764,41.4421768188],"type":"Point"}
}