{
  "type": "Feature",
  "properties": {
    "iso:country":"ES",
    "sg:address":"Carrer de General Prim, 29",
    "sg:city":"Cambrils",
    "sg:orig_category":"Empresas De Carpinter\u00cda De Madera",
    "sg:phone":"+34 977 36 68 40",
    "sg:postcode":"43850",
    "sg:province":"Tarragona",
    "wof:name":"Benavent Marles Teresa",
    "wof:placetype":"venue"
},
  "geometry": {"coordinates":[1.0533800125,41.0701599121],"type":"Point"}
}