{
  "type": "Feature",
  "properties": {
    "iso:country":"ES",
    "sg:address":"Calle de Doctor Barraquer, 22",
    "sg:city":"Almeria",
    "sg:orig_category":"Ense\u00d1anza Variada",
    "sg:phone":"+34 950 17 00 78",
    "sg:postcode":"04005",
    "sg:province":"Almer\u00eda",
    "wof:name":"Gestion Formacion Fremart Aulanobel S. C.",
    "wof:placetype":"venue"
},
  "geometry": {"coordinates":[-2.4542894363,36.8406562805],"type":"Point"}
}