{
  "type": "Feature",
  "properties": {
    "iso:country":"ES",
    "sg:address":"Av Generalitat, 24",
    "sg:city":"Campello",
    "sg:orig_category":"Ropa Para Se\u00d1oras Y Caballeros (al Por Menor)",
    "sg:phone":"+34 965 63 39 33",
    "sg:postcode":"03560",
    "sg:province":"Alicante",
    "wof:name":"Esteve Caturla Antonio",
    "wof:placetype":"venue"
},
  "geometry": {"coordinates":[-0.3971250057,38.4272842407],"type":"Point"}
}