{
  "type": "Feature",
  "properties": {
    "iso:country":"ES",
    "sg:address":"Calle de General Ricardos, 177",
    "sg:city":"Madrid",
    "sg:orig_category":"Ense\u00d1anza Secundaria: Colegios Y Escuelas Privadas",
    "sg:phone":"+34 914 62 86 00",
    "sg:postcode":"28025",
    "sg:province":"Madrid",
    "wof:name":"Instituto De Educacion Secundaria Vista Alegre",
    "wof:placetype":"venue"
},
  "geometry": {"coordinates":[-3.7341520786,40.3868141174],"type":"Point"}
}