{
  "type": "Feature",
  "properties": {
    "iso:country":"ES",
    "sg:address":"Calle de Magdalena De La, 86",
    "sg:city":"Aviles",
    "sg:orig_category":"Estancos",
    "sg:phone":"+34 985 54 45 29",
    "sg:postcode":"33402",
    "sg:province":"Asturias",
    "wof:name":"Gonzalez Rodriguez Florentina",
    "wof:placetype":"venue"
},
  "geometry": {"coordinates":[-5.9263877869,43.534324646],"type":"Point"}
}