{
  "type": "Feature",
  "properties": {
    "iso:country":"ES",
    "sg:address":"Calle de Federico Garcia Lorca, 12",
    "sg:city":"Rioja",
    "sg:orig_category":"Quincaller\u00cda (al Por Menor)",
    "sg:phone":"+34 950 31 05 67",
    "sg:postcode":"04260",
    "sg:province":"Almer\u00eda",
    "wof:name":"Gonzalez Sanchez Juan Jose",
    "wof:placetype":"venue"
},
  "geometry": {"coordinates":[-2.462677002,36.9438591003],"type":"Point"}
}