{
  "type": "Feature",
  "properties": {
    "addr:full":"Poblado, S/n Pontes Garcia Rodriguez La Coru\u00f1a 15320",
    "addr:housenumber":"s",
    "addr:postcode":"15320",
    "addr:street":"Poblado;/ N Pontes Garcia Rodriguez La Corun\u0303A",
    "iso:country":"ES",
    "sg:address":"Poblado, S/n",
    "sg:city":"Pontes Garcia Rodriguez",
    "sg:orig_category":"Asociaciones Y Clubs Deportivos",
    "sg:phone":"+34 981 45 10 68",
    "sg:postcode":"15320",
    "sg:province":"La Coru\u00f1a",
    "wof:name":"Club Deportivo Endesa",
    "wof:placetype":"venue"
},
  "geometry": {"coordinates":[-7.8627839088,43.4551887512],"type":"Point"}
}