{
  "type": "Feature",
  "properties": {
    "addr:full":"Trva Mendieta, 8 Moreaga Vizcaya 48600",
    "addr:housenumber":"8",
    "addr:postcode":"48600",
    "addr:street":"Trva Mendieta",
    "iso:country":"ES",
    "sg:address":"Trva Mendieta, 8",
    "sg:city":"Moreaga",
    "sg:orig_category":"Agencias Y Asesores De Publicidad",
    "sg:phone":"+34 946 76 09 50",
    "sg:postcode":"48600",
    "sg:province":"Vizcaya",
    "wof:name":"Lorente Maestre Diego",
    "wof:placetype":"venue"
},
  "geometry": {"coordinates":[-2.9786450863,43.3824806213],"type":"Point"}
}