{
  "type": "Feature",
  "properties": {
    "iso:country":"ES",
    "sg:address":"Carrer de Hercegovina, 1",
    "sg:city":"Barcelona",
    "sg:orig_category":"Molduras, Junquillos, Listones Y Molduras Perforadas",
    "sg:phone":"+34 932 12 77 52",
    "sg:postcode":"08021",
    "sg:province":"Barcelona",
    "wof:name":"Lozano Garcia Mercedes",
    "wof:placetype":"venue"
},
  "geometry": {"coordinates":[2.138299942,41.4015388489],"type":"Point"}
}