{
  "type": "Feature",
  "properties": {
    "addr:full":"Carrer de Ciencia, 19 Gava Barcelona 08850",
    "addr:housenumber":"19",
    "addr:postcode":"08850",
    "addr:street":"Carrer De Ciencia",
    "iso:country":"ES",
    "sg:address":"Carrer de Ciencia, 19",
    "sg:city":"Gava",
    "sg:orig_category":"Maquinaria Para Industrias Diversas",
    "sg:phone":"+34 936 33 30 13",
    "sg:postcode":"08850",
    "sg:province":"Barcelona",
    "wof:name":"Italpresse Hispania S.l.",
    "wof:placetype":"venue"
},
  "geometry": {"coordinates":[2.0163350105,41.3005142212],"type":"Point"}
}