{
  "type": "Feature",
  "properties": {
    "addr:full":"Calle de Derechos, 40 Valencia Valencia 46001",
    "addr:housenumber":"40",
    "addr:postcode":"46001",
    "addr:street":"Calle De Derechos",
    "iso:country":"ES",
    "sg:address":"Calle de Derechos, 40",
    "sg:city":"Valencia",
    "sg:orig_category":"Confecci\u00d3n De Alpargatas",
    "sg:phone":"+34 963 91 67 44",
    "sg:postcode":"46001",
    "sg:province":"Valencia",
    "wof:name":"Monzon Ma\u00f1ez Vicente",
    "wof:placetype":"venue"
},
  "geometry": {"coordinates":[-0.3770568967,39.4736442566],"type":"Point"}
}