{
  "type": "Feature",
  "properties": {
    "addr:full":"Ctra Girona, 24 S. Feliu Guixols Girona 17220",
    "addr:housenumber":"24",
    "addr:postcode":"17220",
    "addr:street":"Ctra Girona;S. Feliu Guixols",
    "iso:country":"ES",
    "sg:address":"Ctra Girona, 24",
    "sg:city":"S. Feliu Guixols",
    "sg:orig_category":"Ropa Para Se\u00d1oras Y Caballeros (al Por Menor)",
    "sg:phone":"+34 972 32 27 06",
    "sg:postcode":"17220",
    "sg:province":"Girona",
    "wof:name":"Asensio Mesas Angel",
    "wof:placetype":"venue"
},
  "geometry": {"coordinates":[3.0268337727,41.7832450867],"type":"Point"}
}