{
  "type": "Feature",
  "properties": {
    "addr:full":"Calle de Ollerias, 21 Ronda M\u00e1laga 29400",
    "addr:housenumber":"21",
    "addr:postcode":"29400",
    "addr:street":"Calle De Ollerias;Ronda Ma\u0301Laga",
    "iso:country":"ES",
    "sg:address":"Calle de Ollerias, 21",
    "sg:city":"Ronda",
    "sg:orig_category":"Cl\u00cdnicas M\u00c9dicas",
    "sg:phone":"+34 952 87 56 50",
    "sg:postcode":"29400",
    "sg:province":"M\u00e1laga",
    "wof:name":"Servicios Medicos Nocturnos S.l.",
    "wof:placetype":"venue"
},
  "geometry": {"coordinates":[-5.1664872169,36.747215271],"type":"Point"}
}