{
  "type": "Feature",
  "properties": {
    "iso:country":"ES",
    "sg:address":"Cra Nacional Ii, Km. 0651,0",
    "sg:city":"Mataro",
    "sg:orig_category":"Productos Qu\u00cdmicos (fabricaci\u00d3n, Al Por Mayor)",
    "sg:phone":"+34 937 57 91 49",
    "sg:postcode":"08301",
    "sg:province":"Barcelona",
    "wof:name":"Procter And Gamble Mataro S.l.",
    "wof:placetype":"venue"
},
  "geometry": {"coordinates":[2.4479300976,41.5427207947],"type":"Point"}
}