{
  "type": "Feature",
  "properties": {
    "iso:country":"ES",
    "sg:address":"Calle de Baldomero De Dios, 13",
    "sg:city":"Pego",
    "sg:orig_category":"Supermercados Y Hipermercados",
    "sg:phone":"+34 980 60 63 62",
    "sg:postcode":"49154",
    "sg:province":"Zamora",
    "wof:name":"Aparicio Guerra Carlos",
    "wof:placetype":"venue"
},
  "geometry": {"coordinates":[-5.7462787628,41.5033454895],"type":"Point"}
}