{
  "type": "Feature",
  "properties": {
    "addr:full":"Calle de Maria Antonia Jesus Tirado, 6 Jerez De La Frontera C\u00e1diz 11401",
    "addr:housenumber":"6",
    "addr:postcode":"11401",
    "addr:street":"Calle De Maria Antonia Jesus Tirado",
    "iso:country":"ES",
    "sg:address":"Calle de Maria Antonia Jesus Tirado, 6",
    "sg:city":"Jerez De La Frontera",
    "sg:orig_category":"Supermercados Y Hipermercados",
    "sg:phone":"+34 956 32 55 88",
    "sg:postcode":"11401",
    "sg:province":"C\u00e1diz",
    "sg:website":"www.mercadona.es",
    "wof:name":"Mercadona S.a.",
    "wof:placetype":"venue"
},
  "geometry": {"coordinates":[-6.1299571991,36.6827812195],"type":"Point"}
}