{
  "type": "Feature",
  "properties": {
    "iso:country":"ES",
    "sg:address":"Calle de Camino Del Rio, 23",
    "sg:city":"Bullas",
    "sg:orig_category":"Carpinteros",
    "sg:phone":"+34 968 65 25 37",
    "sg:postcode":"30180",
    "sg:province":"Murcia",
    "wof:name":"Juan De La Espina S.c.",
    "wof:placetype":"venue"
},
  "geometry": {"coordinates":[-1.6722127199,38.0405387878],"type":"Point"}
}