{
  "type": "Feature",
  "properties": {
    "addr:full":"Calle de Palafox, 7 Villanueva Gallego Zaragoza 50830",
    "addr:housenumber":"7",
    "addr:postcode":"50830",
    "addr:street":"Calle De Palafox",
    "iso:country":"ES",
    "sg:address":"Calle de Palafox, 7",
    "sg:city":"Villanueva Gallego",
    "sg:orig_category":"Supermercados Y Hipermercados",
    "sg:phone":"+34 976 18 53 68",
    "sg:postcode":"50830",
    "sg:province":"Zaragoza",
    "wof:name":"Palafox 7-9 S. L.",
    "wof:placetype":"venue"
},
  "geometry": {"coordinates":[-0.8256850243,41.7674865723],"type":"Point"}
}