{
  "type": "Feature",
  "properties": {
    "iso:country":"ES",
    "sg:address":"Calle de Gran Via, 65",
    "sg:city":"Salamanca",
    "sg:orig_category":"Promotores Constructores",
    "sg:phone":"+34 923 21 20 74",
    "sg:postcode":"37001",
    "sg:province":"Salamanca",
    "wof:name":"Hezar S.l.",
    "wof:placetype":"venue"
},
  "geometry": {"coordinates":[-5.6613078117,40.9637756348],"type":"Point"}
}