{
  "type": "Feature",
  "properties": {
    "iso:country":"ES",
    "sg:address":"Calle de Conde Garay, 3",
    "sg:city":"Salda\u00f1a",
    "sg:orig_category":"Bancos",
    "sg:phone":"+34 979 89 00 04",
    "sg:postcode":"34100",
    "sg:province":"Palencia",
    "wof:name":"Banco Espa\u00f1ol De Credito S.a.",
    "wof:placetype":"venue"
},
  "geometry": {"coordinates":[-4.7362241745,42.5218353271],"type":"Point"}
}