{
  "type": "Feature",
  "properties": {
    "addr:full":"Av Pla Del Vent, 11 S. Joan Despi Barcelona 08970",
    "addr:housenumber":"11",
    "addr:postcode":"08970",
    "addr:street":"Av Pla Del Vent;S. Joan Despi",
    "iso:country":"ES",
    "sg:address":"Av Pla Del Vent, 11",
    "sg:city":"S. Joan Despi",
    "sg:orig_category":"M\u00c9dicos: Medicina General",
    "sg:phone":"+34 934 34 21 24",
    "sg:postcode":"08970",
    "sg:province":"Barcelona",
    "wof:name":"Asesoria Y Consultoria Sanitaria S.l.",
    "wof:placetype":"venue"
},
  "geometry": {"coordinates":[2.0611560345,41.3770179749],"type":"Point"}
}