{
  "type": "Feature",
  "properties": {
    "iso:country":"ES",
    "sg:address":"Carrer de Florida (la), 7",
    "sg:city":"Cornella Llobregat",
    "sg:orig_category":"Venta Y Colocaci\u00d3n De Techos, Falsos Techos",
    "sg:phone":"+34 933 75 79 68",
    "sg:postcode":"08940",
    "sg:province":"Barcelona",
    "wof:name":"Obras Interiores Catalanas S.l:",
    "wof:placetype":"venue"
},
  "geometry": {"coordinates":[2.0744459629,41.3585548401],"type":"Point"}
}