{
  "type": "Feature",
  "properties": {
    "iso:country":"ES",
    "sg:address":"Calle de Pio Xii, 47",
    "sg:city":"Palmas De Gran Canaria",
    "sg:orig_category":"Asociaciones, Organismos Culturales Y Socioeducativos",
    "sg:phone":"+34 928 24 29 65",
    "sg:postcode":"35005",
    "sg:province":"Las Palmas",
    "wof:name":"Asociacion Banefico Cultural Gara",
    "wof:placetype":"venue"
},
  "geometry": {"coordinates":[-15.433016777,28.1269321442],"type":"Point"}
}