{
  "type": "Feature",
  "properties": {
    "addr:full":"Calle de Lobez Pueyo, 29 Zaragoza Zaragoza 50007",
    "addr:housenumber":"29",
    "addr:postcode":"50007",
    "addr:street":"Calle De Lobez Pueyo",
    "iso:country":"ES",
    "sg:address":"Calle de Lobez Pueyo, 29",
    "sg:city":"Zaragoza",
    "sg:orig_category":"Asociaciones Y Clubs Deportivos",
    "sg:phone":"+34 976 37 81 51",
    "sg:postcode":"50007",
    "sg:province":"Zaragoza",
    "wof:name":"Osuna Moral Miguel",
    "wof:placetype":"venue"
},
  "geometry": {"coordinates":[-0.884600997,41.6291122437],"type":"Point"}
}