{
  "type": "Feature",
  "properties": {
    "iso:country":"ES",
    "sg:address":"Calle de Mirasol Conde, 11",
    "sg:city":"Bilbao",
    "sg:orig_category":"Obras Y Organismos Sociales",
    "sg:phone":"+34 944 16 06 60",
    "sg:postcode":"48003",
    "sg:province":"Vizcaya",
    "wof:name":"Etorkinekin Elkartu",
    "wof:placetype":"venue"
},
  "geometry": {"coordinates":[-2.9268329144,43.2550811768],"type":"Point"}
}