{
  "type": "Feature",
  "properties": {
    "iso:country":"ES",
    "sg:address":"Carr Bisbe Lorenzana, 47",
    "sg:city":"Girona",
    "sg:orig_category":"Caf\u00c9s, Bares, Cervecer\u00cdas",
    "sg:phone":"+34 972 20 41 21",
    "sg:postcode":"17002",
    "sg:province":"Girona",
    "wof:name":"Cafeteria Restaurant La Mandarina S.l.",
    "wof:placetype":"venue"
},
  "geometry": {"coordinates":[2.8187599182,41.9787368774],"type":"Point"}
}