{
  "type": "Feature",
  "properties": {
    "iso:country":"ES",
    "sg:address":"Calle de Cuenca, 5",
    "sg:city":"Ibi",
    "sg:orig_category":"Galvanizaci\u00d3n, Esta\u00d1ado, Emplomado",
    "sg:phone":"+34 966 55 41 28",
    "sg:postcode":"03440",
    "sg:province":"Alicante",
    "wof:name":"Carlos Valero S. L.",
    "wof:placetype":"venue"
},
  "geometry": {"coordinates":[-0.5951941013,38.6124839783],"type":"Point"}
}