{
  "type": "Feature",
  "properties": {
    "iso:country":"ES",
    "sg:address":"Avda Buenos Aires, 109",
    "sg:city":"Lalin",
    "sg:orig_category":"Trabajos De Perforaciones, Sondeos, Construcci\u00d3n De Pozos",
    "sg:phone":"+34 986 78 18 04",
    "sg:postcode":"36500",
    "sg:province":"Pontevedra",
    "wof:name":"Otero Pereiro Jose",
    "wof:placetype":"venue"
},
  "geometry": {"coordinates":[-8.1131591797,42.6578407288],"type":"Point"}
}