{
  "type": "Feature",
  "properties": {
    "addr:full":"Carr Madrid, 26 Eivissa Islas Baleares 07800",
    "addr:housenumber":"26",
    "addr:postcode":"07800",
    "addr:street":"Carr Madrid",
    "iso:country":"ES",
    "sg:address":"Carr Madrid, 26",
    "sg:city":"Eivissa",
    "sg:orig_category":"Confecci\u00d3n (fabricaci\u00d3n, Al Por Mayor)",
    "sg:phone":"+34 971 39 97 77",
    "sg:postcode":"07800",
    "sg:province":"Islas Baleares",
    "wof:name":"Miguel Puig Prunes-maria Planells Guasch Cdad",
    "wof:placetype":"venue"
},
  "geometry": {"coordinates":[1.4188899994,38.9061164856],"type":"Point"}
}