{
  "type": "Feature",
  "properties": {
    "addr:full":"Carrer de Rossello, 68 Barcelona Barcelona 08029",
    "addr:housenumber":"68",
    "addr:postcode":"08029",
    "addr:street":"Carrer De Rossello",
    "iso:country":"ES",
    "sg:address":"Carrer de Rossello, 68",
    "sg:city":"Barcelona",
    "sg:orig_category":"M\u00c9dicos: Estomatolog\u00cda",
    "sg:phone":"+34 933 22 01 64",
    "sg:postcode":"08029",
    "sg:province":"Barcelona",
    "wof:name":"Alanis Arriagada Ricardo",
    "wof:placetype":"venue"
},
  "geometry": {"coordinates":[2.1483411789,41.3865280151],"type":"Point"}
}