{
  "type": "Feature",
  "properties": {
    "addr:full":"Barr Baular (el), 11 Mimetiz Vizcaya 48860",
    "addr:postcode":"48860",
    "addr:street":"Vizcaya",
    "iso:country":"ES",
    "sg:address":"Barr Baular (el), 11",
    "sg:city":"Mimetiz",
    "sg:orig_category":"Distribuci\u00d3n De Petr\u00d3leo Y Derivados",
    "sg:phone":"+34 946 67 01 29",
    "sg:postcode":"48860",
    "sg:province":"Vizcaya",
    "wof:name":"Jose Antonio Arechaga S. A.",
    "wof:placetype":"venue"
},
  "geometry": {"coordinates":[-3.1296989918,43.2133483887],"type":"Point"}
}