{
  "type": "Feature",
  "properties": {
    "iso:country":"ES",
    "sg:address":"Carrer de Pallars, 147",
    "sg:city":"Barcelona",
    "sg:orig_category":"Suministros Para Hoteles",
    "sg:phone":"+34 934 85 08 92",
    "sg:postcode":"08018",
    "sg:province":"Barcelona",
    "wof:name":"Mantenimiento Integral De Hosteleria S.coop.c.ltda.",
    "wof:placetype":"venue"
},
  "geometry": {"coordinates":[2.1938300133,41.3981513977],"type":"Point"}
}