{
  "type": "Feature",
  "properties": {
    "addr:full":"Calle de Aguilas, 20 Yecla Murcia 30510",
    "addr:housenumber":"20",
    "addr:postcode":"30510",
    "addr:street":"Calle De Aguilas",
    "iso:country":"ES",
    "sg:address":"Calle de Aguilas, 20",
    "sg:city":"Yecla",
    "sg:orig_category":"Promotores Constructores",
    "sg:phone":"+34 968 79 37 93",
    "sg:postcode":"30510",
    "sg:province":"Murcia",
    "wof:name":"Ortiz Panadero S.l.",
    "wof:placetype":"venue"
},
  "geometry": {"coordinates":[-1.126783371,38.6146812439],"type":"Point"}
}