{
  "type": "Feature",
  "properties": {
    "addr:full":"Calle de Martin De Luque, 18 Antequera M\u00e1laga 29200",
    "addr:housenumber":"18",
    "addr:postcode":"29200",
    "addr:street":"Calle De Martin De Luque",
    "iso:country":"ES",
    "sg:address":"Calle de Martin De Luque, 18",
    "sg:city":"Antequera",
    "sg:orig_category":"Charcuter\u00cdas (al Por Mayor)",
    "sg:phone":"+34 952 84 10 64",
    "sg:postcode":"29200",
    "sg:province":"M\u00e1laga",
    "wof:name":"Embutidos Olmedo S.l.",
    "wof:placetype":"venue"
},
  "geometry": {"coordinates":[-4.5574297905,37.0207901001],"type":"Point"}
}