{
  "type": "Feature",
  "properties": {
    "addr:full":"Carrer de Mossen A. Rodamilans, 223 Terrassa Barcelona 08222",
    "addr:housenumber":"223",
    "addr:postcode":"08222",
    "addr:street":"Carrer De Mossen A. Rodamilans",
    "iso:country":"ES",
    "sg:address":"Carrer de Mossen A. Rodamilans, 223",
    "sg:city":"Terrassa",
    "sg:orig_category":"Fisioterapia",
    "sg:phone":"+34 937 83 24 57",
    "sg:postcode":"08222",
    "sg:province":"Barcelona",
    "wof:name":"Associacio Malalts Necesitats De Fisioterapia I Rehabilitacio",
    "wof:placetype":"venue"
},
  "geometry": {"coordinates":[2.0278332233,41.5667800903],"type":"Point"}
}