{
  "type": "Feature",
  "properties": {
    "iso:country":"ES",
    "sg:address":"Carr Progres, 81",
    "sg:city":"Centre Urba",
    "sg:orig_category":"Hilaturas, Hilos Y Actividades Relacionadas",
    "sg:phone":"+34 972 70 39 62",
    "sg:postcode":"17500",
    "sg:province":"Girona",
    "wof:name":"Colorfil S.a.",
    "wof:placetype":"venue"
},
  "geometry": {"coordinates":[2.1959049702,42.1965866089],"type":"Point"}
}