{
  "type": "Feature",
  "properties": {
    "iso:country":"ES",
    "sg:address":"C/ Corredora, 36",
    "sg:city":"Elche",
    "sg:orig_category":"Papeler\u00cdas, Librer\u00cdas",
    "sg:phone":"+34 965 45 15 20",
    "sg:postcode":"03202",
    "sg:province":"Alicante",
    "wof:name":"Segarra Sanchez Rosa Maria",
    "wof:placetype":"venue"
},
  "geometry": {"coordinates":[-0.6959229708,38.2661323547],"type":"Point"}
}