{
  "type": "Feature",
  "properties": {
    "iso:country":"ES",
    "sg:address":"Carr Enginyer Balaguer, (de L'), 122",
    "sg:city":"Carlet",
    "sg:orig_category":"Negocio De Materiales De Construcci\u00d3n",
    "sg:phone":"+34 962 53 02 86",
    "sg:postcode":"46240",
    "sg:province":"Valencia",
    "wof:name":"Fabrich Garcia Alfonso",
    "wof:placetype":"venue"
},
  "geometry": {"coordinates":[-0.5188249946,39.2218513489],"type":"Point"}
}