{
  "type": "Feature",
  "properties": {
    "addr:full":"Calle de Virgen De La Cinta, 33 Sevilla Sevilla 41011",
    "addr:housenumber":"33",
    "addr:postcode":"41011",
    "addr:street":"Calle De Virgen De La Cinta",
    "iso:country":"ES",
    "sg:address":"Calle de Virgen De La Cinta, 33",
    "sg:city":"Sevilla",
    "sg:orig_category":"Asesor\u00cda Sobre Comunicaci\u00d3n De Empresas",
    "sg:phone":"+34 954 27 97 13",
    "sg:postcode":"41011",
    "sg:province":"Sevilla",
    "wof:name":"Surconsult Asesores S.l.",
    "wof:placetype":"venue"
},
  "geometry": {"coordinates":[-6.0005931854,37.3722801208],"type":"Point"}
}