{
  "type": "Feature",
  "properties": {
    "iso:country":"ES",
    "sg:address":"Calle de Rio Pilo\u00d1a, 1",
    "sg:city":"Arriondas",
    "sg:orig_category":"Turismo: Lugares, Circuitos Y Curiosidades",
    "sg:phone":"+34 985 84 10 02",
    "sg:postcode":"33540",
    "sg:province":"Asturias",
    "sg:website":"www.fade.es/asturiaventura",
    "wof:name":"Astur Aventura S.l.",
    "wof:placetype":"venue"
},
  "geometry": {"coordinates":[-5.1868767738,43.386013031],"type":"Point"}
}