{
  "type": "Feature",
  "properties": {
    "iso:country":"ES",
    "sg:address":"Avda Gernikako Arbola, 46",
    "sg:city":"San Vicente De Barakaldo",
    "sg:orig_category":"Cajas De Ahorro",
    "sg:phone":"+34 944 78 19 70",
    "sg:postcode":"48902",
    "sg:province":"Vizcaya",
    "wof:name":"Caixa D'estalvis I Pensions De Barcelona",
    "wof:placetype":"venue"
},
  "geometry": {"coordinates":[-2.9961669445,43.2943496704],"type":"Point"}
}