{
  "type": "Feature",
  "properties": {
    "addr:full":"Calle de Carcagente, 6 Valencia Valencia 46007",
    "addr:housenumber":"6",
    "addr:postcode":"46007",
    "addr:street":"Calle De Carcagente",
    "iso:country":"ES",
    "sg:address":"Calle de Carcagente, 6",
    "sg:city":"Valencia",
    "sg:orig_category":"Librer\u00cdas",
    "sg:phone":"+34 963 80 98 83",
    "sg:postcode":"46007",
    "sg:province":"Valencia",
    "wof:name":"Cano Mu\u00f1oz Fernanda",
    "wof:placetype":"venue"
},
  "geometry": {"coordinates":[-0.3864248991,39.4603309631],"type":"Point"}
}