{
  "type": "Feature",
  "properties": {
    "addr:full":"Poli Industrial Pineda 'calle D', S/n Sevilla Sevilla 41013",
    "addr:housenumber":"s / n",
    "addr:postcode":"41013",
    "addr:street":"Calle D '",
    "iso:country":"ES",
    "sg:address":"Poli Industrial Pineda 'calle D', S/n",
    "sg:city":"Sevilla",
    "sg:orig_category":"Zapatos: Material, Suministros, Accesorios (fabricaci\u00d3n, Al Por Mayor)",
    "sg:phone":"+34 954 68 03 34",
    "sg:postcode":"41013",
    "sg:province":"Sevilla",
    "wof:name":"Cascajosa Soriano Eduardo",
    "wof:placetype":"venue"
},
  "geometry": {"coordinates":[-5.9716711044,37.3525352478],"type":"Point"}
}