{
  "type": "Feature",
  "properties": {
    "addr:full":"Calle de Maria De Molina, 12 Valencia Valencia 46017",
    "addr:housenumber":"12",
    "addr:postcode":"46017",
    "addr:street":"Calle De Maria De Molina",
    "iso:country":"ES",
    "sg:address":"Calle de Maria De Molina, 12",
    "sg:city":"Valencia",
    "sg:orig_category":"Institutos De Belleza",
    "sg:phone":"+34 963 57 50 00",
    "sg:postcode":"46017",
    "sg:province":"Valencia",
    "wof:name":"Vitoboga S.l.u.",
    "wof:placetype":"venue"
},
  "geometry": {"coordinates":[-0.3900955915,39.4519309998],"type":"Point"}
}