{
  "type": "Feature",
  "properties": {
    "iso:country":"ES",
    "sg:address":"Carrer de Jaume Marti, 29",
    "sg:city":"Barcelona",
    "sg:orig_category":"Asociaciones Y Clubs Deportivos",
    "sg:phone":"+34 933 50 01 17",
    "sg:postcode":"08042",
    "sg:province":"Barcelona",
    "sg:website":"koverdun@telefonica.net",
    "wof:name":"Club De Boxa K.o. Verdun",
    "wof:placetype":"venue"
},
  "geometry": {"coordinates":[2.174806118,41.4428520203],"type":"Point"}
}