{
  "type": "Feature",
  "properties": {
    "iso:country":"ES",
    "sg:address":"Plaz Fernando Iii, S/n",
    "sg:city":"Zamora",
    "sg:orig_category":"Carnicer\u00cdas, Carnicer\u00cdas",
    "sg:phone":"+34 980 52 20 94",
    "sg:postcode":"49010",
    "sg:province":"Zamora",
    "wof:name":"Hijos De Angon S.l.",
    "wof:placetype":"venue"
},
  "geometry": {"coordinates":[-5.7412929535,41.5141639709],"type":"Point"}
}