{
  "type": "Feature",
  "properties": {
    "iso:country":"ES",
    "sg:address":"C/ Profesor Francisco Tomas Y Valiente, 74",
    "sg:city":"Elche",
    "sg:orig_category":"Caf\u00c9s, Bares, Cervecer\u00cdas",
    "sg:phone":"+34 965 44 72 40",
    "sg:postcode":"03206",
    "sg:province":"Alicante",
    "wof:name":"Rada Business S.l.",
    "wof:placetype":"venue"
},
  "geometry": {"coordinates":[-0.7092930079,38.2750587463],"type":"Point"}
}