{
  "type": "Feature",
  "properties": {
    "addr:full":"Calle de Garcia De Vinuesa, 22 Sevilla Sevilla 41001",
    "addr:housenumber":"22",
    "addr:postcode":"41001",
    "addr:street":"Calle De Garcia De Vinuesa",
    "iso:country":"ES",
    "sg:address":"Calle de Garcia De Vinuesa, 22",
    "sg:city":"Sevilla",
    "sg:orig_category":"Centros Empresariales",
    "sg:phone":"+34 954 22 20 37",
    "sg:postcode":"41001",
    "sg:province":"Sevilla",
    "wof:name":"Federacion Provincial De Empresarios De Industrias Y Comercio De Alimentacion",
    "wof:placetype":"venue"
},
  "geometry": {"coordinates":[-5.9952588081,37.3865585327],"type":"Point"}
}