{
  "type": "Feature",
  "properties": {
    "addr:full":"Avda Maestro Rodrigo (musico), 76 Valencia Valencia 46015",
    "addr:housenumber":"76",
    "addr:postcode":"46015",
    "addr:street":"Avda Maestro Rodrigo Musico",
    "iso:country":"ES",
    "sg:address":"Avda Maestro Rodrigo (musico), 76",
    "sg:city":"Valencia",
    "sg:orig_category":"Distribuci\u00d3n De Petr\u00d3leo Y Derivados",
    "sg:phone":"+34 963 46 28 33",
    "sg:postcode":"46015",
    "sg:province":"Valencia",
    "wof:name":"Markoil S.a.",
    "wof:placetype":"venue"
},
  "geometry": {"coordinates":[-0.404478997,39.4872703552],"type":"Point"}
}