{
  "type": "Feature",
  "properties": {
    "addr:full":"Rond Sancti Spiritus, 33 Salamanca Salamanca 37001",
    "addr:housenumber":"33",
    "addr:postcode":"37001",
    "addr:street":"Rond Sancti Spiritus",
    "iso:country":"ES",
    "sg:address":"Rond Sancti Spiritus, 33",
    "sg:city":"Salamanca",
    "sg:orig_category":"Promotores Constructores",
    "sg:phone":"+34 923 21 23 68",
    "sg:postcode":"37001",
    "sg:province":"Salamanca",
    "wof:name":"Serrano Y Escobar S.l.",
    "wof:placetype":"venue"
},
  "geometry": {"coordinates":[-5.6585230827,40.9656639099],"type":"Point"}
}