{
  "type": "Feature",
  "properties": {
    "iso:country":"ES",
    "sg:address":"Rio Guadalhorce (p I Antequera), 12",
    "sg:city":"Antequera",
    "sg:orig_category":"Electricidad, Electr\u00d3nica: Material Y Suministros (al Por Mayor)",
    "sg:phone":"+34 952 84 35 46",
    "sg:postcode":"29200",
    "sg:province":"M\u00e1laga",
    "wof:name":"Amasur S.l.",
    "wof:placetype":"venue"
},
  "geometry": {"coordinates":[-4.5211935043,36.9971008301],"type":"Point"}
}