{
  "type": "Feature",
  "properties": {
    "iso:country":"ES",
    "sg:address":"Av Paisos Catalans, 20",
    "sg:city":"Zona Educacional",
    "sg:orig_category":"Caf\u00c9s, Bares, Cervecer\u00cdas",
    "sg:phone":"+34 977 20 28 58",
    "sg:postcode":"43007",
    "sg:province":"Tarragona",
    "wof:name":"Talavera Ramirez Manuel",
    "wof:placetype":"venue"
},
  "geometry": {"coordinates":[1.2437289953,41.1306877136],"type":"Point"}
}