{
  "type": "Feature",
  "properties": {
    "addr:full":"Pl Angel Guimera, S/n Mura Barcelona 08279",
    "addr:housenumber":"s / n",
    "addr:postcode":"08279",
    "addr:street":"Pl Angel Guimera",
    "iso:country":"ES",
    "sg:address":"Pl Angel Guimera, S/n",
    "sg:city":"Mura",
    "sg:orig_category":"Oficinas De Turismo, Asociaciones De Iniciativa",
    "sg:phone":"+34 938 31 60 10",
    "sg:postcode":"08279",
    "sg:province":"Barcelona",
    "wof:name":"Consorci Per La Promocio Turisca De Les Valls Del Montcau",
    "wof:placetype":"venue"
},
  "geometry": {"coordinates":[1.97566998,41.6990966797],"type":"Point"}
}