{
  "type": "Feature",
  "properties": {
    "iso:country":"ES",
    "sg:address":"Calle de Toldilla, 1",
    "sg:city":"Playa Honda",
    "sg:orig_category":"Asociaciones Y Clubs Deportivos",
    "sg:phone":"+34 928 81 99 17",
    "sg:postcode":"35509",
    "sg:province":"Las Palmas",
    "wof:name":"Melian Suarez Jose Luis",
    "wof:placetype":"venue"
},
  "geometry": {"coordinates":[-13.5926437378,28.9527626038],"type":"Point"}
}