{
  "type": "Feature",
  "properties": {
    "iso:country":"ES",
    "sg:address":"Calle de Costa Brava, S/n",
    "sg:city":"Valladolid",
    "sg:orig_category":"Bisuter\u00cda, Joyer\u00cda, Relojer\u00cda (al Por Menor)",
    "sg:phone":"+34 983 26 60 33",
    "sg:postcode":"47010",
    "sg:province":"Valladolid",
    "wof:name":"Multijoyerias Merci S.l",
    "wof:placetype":"venue"
},
  "geometry": {"coordinates":[-4.7107229233,41.6693954468],"type":"Point"}
}