{
  "type": "Feature",
  "properties": {
    "addr:full":"Calle de Salvador De Madariaga, 1 Santa Maria De Gracia Murcia 30009",
    "addr:housenumber":"1",
    "addr:postcode":"30009",
    "addr:street":"Calle De Salvador De Madariaga",
    "iso:country":"ES",
    "sg:address":"Calle de Salvador De Madariaga, 1",
    "sg:city":"Santa Maria De Gracia",
    "sg:orig_category":"Panader\u00cdas, Panader\u00cdas",
    "sg:phone":"+34 968 29 27 69",
    "sg:postcode":"30009",
    "sg:province":"Murcia",
    "wof:name":"Aguilar Navarro Antonio",
    "wof:placetype":"venue"
},
  "geometry": {"coordinates":[-1.1385792494,37.9945144653],"type":"Point"}
}