{
  "type": "Feature",
  "properties": {
    "iso:country":"ES",
    "sg:address":"As Teixugueiras (pol. Navia), 11",
    "sg:city":"Vigo",
    "sg:orig_category":"Creaci\u00d3n De Sitios, Hosting Internet",
    "sg:phone":"+34 986 13 67 10",
    "sg:postcode":"36213",
    "sg:province":"Pontevedra",
    "wof:name":"Alen Multimedia S.l.l",
    "wof:placetype":"venue"
},
  "geometry": {"coordinates":[-8.7536239624,42.1922149658],"type":"Point"}
}