{
  "type": "Feature",
  "properties": {
    "iso:country":"ES",
    "sg:address":"Avda Montes De Oca (de Los), 7",
    "sg:city":"San Sebastian De Los Reyes",
    "sg:orig_category":"Artes Gr\u00c1ficas, Artes Pl\u00c1sticas (curso)",
    "sg:phone":"+34 916 53 37 21",
    "sg:postcode":"28700",
    "sg:province":"Madrid",
    "wof:name":"Graficas 82 S.l.",
    "wof:placetype":"venue"
},
  "geometry": {"coordinates":[-3.6151590347,40.5526504517],"type":"Point"}
}