{
  "type": "Feature",
  "properties": {
    "iso:country":"ES",
    "sg:address":"Calle de Hospital, S/n",
    "sg:city":"Olmedo",
    "sg:orig_category":"Asesor\u00cda Fiscal Y Jur\u00cddica",
    "sg:phone":"+34 983 60 00 26",
    "sg:postcode":"47410",
    "sg:province":"Valladolid",
    "wof:name":"M.a. Gutierrez Cia Asesores S.r.c.",
    "wof:placetype":"venue"
},
  "geometry": {"coordinates":[-4.6850633621,41.2873954773],"type":"Point"}
}