{
  "type": "Feature",
  "properties": {
    "addr:full":"Plaz Constitucion, S/n Pradena Segovia 40165",
    "addr:postcode":"40165",
    "addr:street":"Constitucion S / N",
    "iso:country":"ES",
    "sg:address":"Plaz Constitucion, S/n",
    "sg:city":"Pradena",
    "sg:orig_category":"Molduras, Junquillos, Listones Y Molduras Perforadas",
    "sg:phone":"+34 921 50 72 00",
    "sg:postcode":"40165",
    "sg:province":"Segovia",
    "wof:name":"Baeza Masedo Miguel",
    "wof:placetype":"venue"
},
  "geometry": {"coordinates":[-3.6889250278,41.1374855042],"type":"Point"}
}