{
  "type": "Feature",
  "properties": {
    "addr:full":"Calle de Deposito, 36 Puebla Alfinden Zaragoza 50171",
    "addr:housenumber":"36",
    "addr:postcode":"50171",
    "addr:street":"Calle De Deposito;Alfinden",
    "iso:country":"ES",
    "sg:address":"Calle de Deposito, 36",
    "sg:city":"Puebla Alfinden",
    "sg:orig_category":"Mec\u00c1nico Del Autom\u00d3vil",
    "sg:phone":"+34 976 10 81 38",
    "sg:postcode":"50171",
    "sg:province":"Zaragoza",
    "wof:name":"Talleres Alcolea Sc",
    "wof:placetype":"venue"
},
  "geometry": {"coordinates":[-0.7531189919,41.6323547363],"type":"Point"}
}