{
  "type": "Feature",
  "properties": {
    "iso:country":"ES",
    "sg:address":"Carrer de Rocafort, 152",
    "sg:city":"Barcelona",
    "sg:orig_category":"Agencias De Viajes",
    "sg:phone":"+34 932 26 03 87",
    "sg:postcode":"08015",
    "sg:province":"Barcelona",
    "wof:name":"Viajes Barcelo S L",
    "wof:placetype":"venue"
},
  "geometry": {"coordinates":[2.1493799686,41.3824424744],"type":"Point"}
}