{
  "type": "Feature",
  "properties": {
    "iso:country":"ES",
    "sg:address":"Queruas, 57",
    "sg:city":"Canero",
    "sg:orig_category":"T\u00c9cnicos Veterinarios",
    "sg:phone":"+34 985 47 50 31",
    "sg:postcode":"33785",
    "sg:province":"Asturias",
    "wof:name":"Vallejo Iba\u00f1ez Jose Modesto",
    "wof:placetype":"venue"
},
  "geometry": {"coordinates":[-6.4378910065,43.5342216492],"type":"Point"}
}