{
  "type": "Feature",
  "properties": {
    "addr:full":"Cra. Rellevo, S/n Castellsera Lleida 25334",
    "addr:housenumber":"s",
    "addr:postcode":"25334",
    "addr:street":"/ N Castellsera",
    "iso:country":"ES",
    "sg:address":"Cra. Rellevo, S/n",
    "sg:city":"Castellsera",
    "sg:orig_category":"Equipo De Refrigeraci\u00d3n Industrial",
    "sg:phone":"+34 973 61 01 25",
    "sg:postcode":"25334",
    "sg:province":"Lleida",
    "sg:website":"www.jympa.com",
    "wof:name":"Jympa 1971 S.l.",
    "wof:placetype":"venue"
},
  "geometry": {"coordinates":[0.9866899848,41.7461395264],"type":"Point"}
}