{
  "type": "Feature",
  "properties": {
    "addr:full":"Calle de Duquesa De Tamames, S/n Madrid Madrid 28044",
    "addr:housenumber":"s / n",
    "addr:postcode":"28044",
    "addr:street":"Calle De Duquesa De Tamames",
    "iso:country":"ES",
    "sg:address":"Calle de Duquesa De Tamames, S/n",
    "sg:city":"Madrid",
    "sg:orig_category":"Calefacci\u00d3n Central: Material (fabricaci\u00d3n, Al Por Mayor)",
    "sg:phone":"+34 915 08 59 76",
    "sg:postcode":"28044",
    "sg:province":"Madrid",
    "wof:name":"Tecnologia Termica S.a.",
    "wof:placetype":"venue"
},
  "geometry": {"coordinates":[-3.7495894432,40.371761322],"type":"Point"}
}