{
  "type": "Feature",
  "properties": {
    "iso:country":"ES",
    "sg:address":"Pl Cuba, 12",
    "sg:city":"Mataro",
    "sg:orig_category":"Perfumer\u00cda (al Por Menor)",
    "sg:phone":"+34 937 98 54 16",
    "sg:postcode":"08302",
    "sg:province":"Barcelona",
    "wof:name":"Miralles Lluria Asuncion",
    "wof:placetype":"venue"
},
  "geometry": {"coordinates":[2.4410359859,41.5377578735],"type":"Point"}
}