{
  "type": "Feature",
  "properties": {
    "iso:country":"ES",
    "sg:address":"Avda Tres De Agosto, 10",
    "sg:city":"Aspe",
    "sg:orig_category":"Vinos Y Licores (venta Al Por Menor)",
    "sg:phone":"+34 965 49 00 73",
    "sg:postcode":"03680",
    "sg:province":"Alicante",
    "wof:name":"Perez Garcia Juan Antonio",
    "wof:placetype":"venue"
},
  "geometry": {"coordinates":[-0.7728949785,38.3417510986],"type":"Point"}
}