{
  "type": "Feature",
  "properties": {
    "addr:full":"Rua Eduardo Vincenti, 4 Bueu Pontevedra 36930",
    "addr:housenumber":"4",
    "addr:postcode":"36930",
    "addr:street":"Rua Eduardo Vincenti",
    "iso:country":"ES",
    "sg:address":"Rua Eduardo Vincenti, 4",
    "sg:city":"Bueu",
    "sg:orig_category":"Caf\u00c9s, Bares, Cervecer\u00cdas",
    "sg:phone":"+34 986 32 28 97",
    "sg:postcode":"36930",
    "sg:province":"Pontevedra",
    "wof:name":"Otero Rodriguez Americo",
    "wof:placetype":"venue"
},
  "geometry": {"coordinates":[-8.7841453552,42.3265113831],"type":"Point"}
}