{
  "type": "Feature",
  "properties": {
    "addr:full":"Calle de Puerto Rico, 9 Madrid Madrid 28016",
    "addr:housenumber":"9",
    "addr:postcode":"madrid;28016",
    "addr:street":"Calle De Puerto Rico",
    "iso:country":"ES",
    "sg:address":"Calle de Puerto Rico, 9",
    "sg:city":"Madrid",
    "sg:orig_category":"\u00d3ptica: Instrumentos (fabricaci\u00d3n)",
    "sg:phone":"+34 915 19 85 43",
    "sg:postcode":"28016",
    "sg:province":"Madrid",
    "wof:name":"Ferrando Garcia Maria Angeles",
    "wof:placetype":"venue"
},
  "geometry": {"coordinates":[-3.6746730804,40.4531478882],"type":"Point"}
}