{
  "type": "Feature",
  "properties": {
    "addr:full":"Carrer de Ramon Y Cajal, 6 Deltebre Tarragona 43580",
    "addr:housenumber":"6",
    "addr:postcode":"43580",
    "addr:street":"Carrer De Ramon Y Cajal",
    "iso:country":"ES",
    "sg:address":"Carrer de Ramon Y Cajal, 6",
    "sg:city":"Deltebre",
    "sg:orig_category":"Desinfecci\u00d3n, Desinsectaci\u00d3n, Desratizaci\u00d3n",
    "sg:phone":"+34 977 48 06 17",
    "sg:postcode":"43580",
    "sg:province":"Tarragona",
    "wof:name":"Tratamientos Aereos Del Delta S.l.",
    "wof:placetype":"venue"
},
  "geometry": {"coordinates":[0.7359169722,40.7175102234],"type":"Point"}
}