{
  "type": "Feature",
  "properties": {
    "addr:full":"Carrer de Pare Fita, 42 Sabadell Barcelona 08203",
    "addr:housenumber":"42",
    "addr:postcode":"08203",
    "addr:street":"Carrer De Pare Fita",
    "iso:country":"ES",
    "sg:address":"Carrer de Pare Fita, 42",
    "sg:city":"Sabadell",
    "sg:orig_category":"Hilaturas, Hilos Y Actividades Relacionadas",
    "sg:phone":"+34 937 11 32 40",
    "sg:postcode":"08203",
    "sg:province":"Barcelona",
    "wof:name":"Manufacturas Textiles Corral S.l.",
    "wof:placetype":"venue"
},
  "geometry": {"coordinates":[2.1104259491,41.5328865051],"type":"Point"}
}