{
  "type": "Feature",
  "properties": {
    "iso:country":"ES",
    "sg:address":"Calle de Aniceto Marinas, 28",
    "sg:city":"Madrid",
    "sg:orig_category":"Arreglo, Reparaci\u00d3n, Piezas Sueltas De Televisi\u00d3n, V\u00cddeo, Hi",
    "sg:phone":"+34 915 48 71 36",
    "sg:postcode":"28008",
    "sg:province":"Madrid",
    "wof:name":"Electronica Gilmar S. L.",
    "wof:placetype":"venue"
},
  "geometry": {"coordinates":[-3.7222824097,40.4213676453],"type":"Point"}
}