{
  "type": "Feature",
  "properties": {
    "addr:full":"Calle de Sierra De Alquife, 4 Madrid Madrid 28053",
    "addr:housenumber":"4",
    "addr:postcode":"28053",
    "addr:street":"Calle De Sierra De Alquife",
    "iso:country":"ES",
    "sg:address":"Calle de Sierra De Alquife, 4",
    "sg:city":"Madrid",
    "sg:orig_category":"Loter\u00cda Y T\u00d3mbola",
    "sg:phone":"+34 914 78 13 39",
    "sg:postcode":"28053",
    "sg:province":"Madrid",
    "wof:name":"Diaz Perez Virginia",
    "wof:placetype":"venue"
},
  "geometry": {"coordinates":[-3.6671259403,40.3889122009],"type":"Point"}
}