{
  "type": "Feature",
  "properties": {
    "addr:full":"Urb. Guadacorte, 27 Cortijillos C\u00e1diz 11379",
    "addr:housenumber":"27",
    "addr:postcode":"11379",
    "addr:street":"Guadacorte;Ca\u0301Diz",
    "iso:country":"ES",
    "sg:address":"Urb. Guadacorte, 27",
    "sg:city":"Cortijillos",
    "sg:orig_category":"Agencias Y Agentes Comerciales, Representantes",
    "sg:phone":"+34 956 67 65 46",
    "sg:postcode":"11379",
    "sg:province":"C\u00e1diz",
    "wof:name":"Servera Mu\u00f1oz Maria Del Mar",
    "wof:placetype":"venue"
},
  "geometry": {"coordinates":[-5.4397439957,36.1761436462],"type":"Point"}
}