{
  "type": "Feature",
  "properties": {
    "iso:country":"ES",
    "sg:address":"Pase Castellana, 192",
    "sg:city":"Madrid",
    "sg:orig_category":"Maquinaria Para Industrias Diversas",
    "sg:phone":"+34 913 43 02 27",
    "sg:postcode":"28046",
    "sg:province":"Madrid",
    "wof:name":"Herrenknecht Iberica S.a.",
    "wof:placetype":"venue"
},
  "geometry": {"coordinates":[-3.6891665459,40.4615135193],"type":"Point"}
}