{
  "type": "Feature",
  "properties": {
    "addr:full":"Calle de Tenerife, S/n Alcazar S. Juan Ciudad Real 13600",
    "addr:housenumber":"s / n",
    "addr:postcode":"13600",
    "addr:street":"Calle De Tenerife;Alcazar S. Juan Ciudad Real",
    "iso:country":"ES",
    "sg:address":"Calle de Tenerife, S/n",
    "sg:city":"Alcazar S. Juan",
    "sg:orig_category":"Asociaciones Y Clubs Deportivos",
    "sg:phone":"+34 926 54 10 34",
    "sg:postcode":"13600",
    "sg:province":"Ciudad Real",
    "wof:name":"Club De Tenis De Alcazar",
    "wof:placetype":"venue"
},
  "geometry": {"coordinates":[-3.2025840282,39.3857841492],"type":"Point"}
}