{
  "type": "Feature",
  "properties": {
    "addr:full":"Pase Florida, 55 Madrid Madrid 28008",
    "addr:housenumber":"55",
    "addr:postcode":"madrid;28008",
    "addr:street":"Florida",
    "iso:country":"ES",
    "sg:address":"Pase Florida, 55",
    "sg:city":"Madrid",
    "sg:orig_category":"Retoques De Vestidos",
    "sg:phone":"+34 915 42 40 60",
    "sg:postcode":"28008",
    "sg:province":"Madrid",
    "wof:name":"Hernandez Martin Maria Teresa",
    "wof:placetype":"venue"
},
  "geometry": {"coordinates":[-3.7248249054,40.424041748],"type":"Point"}
}