{
  "type": "Feature",
  "properties": {
    "addr:full":"La Venta, 8 Hinojosa Cuenca 16750",
    "addr:postcode":"16750",
    "iso:country":"ES",
    "sg:address":"La Venta, 8",
    "sg:city":"Hinojosa",
    "sg:orig_category":"Desinfecci\u00d3n, Desinsectaci\u00d3n, Desratizaci\u00d3n",
    "sg:phone":"+34 969 19 44 70",
    "sg:postcode":"16750",
    "sg:province":"Cuenca",
    "wof:name":"Arangure Granero Angel",
    "wof:placetype":"venue"
},
  "geometry": {"coordinates":[-2.4158535004,39.7290000916],"type":"Point"}
}