{
  "type": "Feature",
  "properties": {
    "iso:country":"ES",
    "sg:address":"Carrer de Josep Ricart, 2",
    "sg:city":"Sant Feliu Llobregat",
    "sg:orig_category":"Muebles Y Accesorios Para Cocinas Y Cuartos De Ba\u00d1o (al Por Menor)",
    "sg:phone":"+34 936 85 49 53",
    "sg:postcode":"08980",
    "sg:province":"Barcelona",
    "wof:name":"Dibayco S.l.",
    "wof:placetype":"venue"
},
  "geometry": {"coordinates":[2.0538179874,41.3800125122],"type":"Point"}
}