{
  "type": "Feature",
  "properties": {
    "addr:full":"Pg Sant Joan, 28 Barcelona Barcelona 08010",
    "addr:housenumber":"28",
    "addr:postcode":"08010",
    "addr:street":"Pg Sant Joan",
    "iso:country":"ES",
    "sg:address":"Pg Sant Joan, 28",
    "sg:city":"Barcelona",
    "sg:orig_category":"Reposter\u00cdas",
    "sg:phone":"+34 932 32 81 08",
    "sg:postcode":"08010",
    "sg:province":"Barcelona",
    "wof:name":"Forn Oriol S.l.",
    "wof:placetype":"venue"
},
  "geometry": {"coordinates":[2.1784551144,41.3928871155],"type":"Point"}
}