{
  "type": "Feature",
  "properties": {
    "iso:country":"ES",
    "sg:address":"Avda Caceres, S/n",
    "sg:city":"Merida",
    "sg:orig_category":"Comercio De Piezas De Recambio Y De Accesorios De Veh\u00cdculos, Veh\u00cdculos Industriales",
    "sg:phone":"+34 924 30 35 57",
    "sg:postcode":"06800",
    "sg:province":"Badajoz",
    "wof:name":"Repuestos Avenida S.a.",
    "wof:placetype":"venue"
},
  "geometry": {"coordinates":[-6.3460941315,38.9207839966],"type":"Point"}
}