{
  "type": "Feature",
  "properties": {
    "iso:country":"ES",
    "sg:address":"Calle de Salvador Noriega, 7",
    "sg:city":"Malaga",
    "sg:orig_category":"Partidos Pol\u00cdticos",
    "sg:phone":"+34 952 34 52 45",
    "sg:postcode":"29006",
    "sg:province":"M\u00e1laga",
    "wof:name":"Izquierda Unida-los Verdes Convocatoria Por Andalucia",
    "wof:placetype":"venue"
},
  "geometry": {"coordinates":[-4.4431090355,36.7089500427],"type":"Point"}
}