{
  "type": "Feature",
  "properties": {
    "addr:full":"Ctra Villaviciosa-pinto, Km. 0015,7 Fuenlabrada Madrid 28946",
    "addr:postcode":"28946",
    "addr:street":"Ctra Villaviciosa-Pinto Km. 0015,7",
    "iso:country":"ES",
    "sg:address":"Ctra Villaviciosa-pinto, Km. 0015,7",
    "sg:city":"Fuenlabrada",
    "sg:orig_category":"Muebles, Minoristas",
    "sg:phone":"+34 916 06 22 68",
    "sg:postcode":"28946",
    "sg:province":"Madrid",
    "wof:name":"Valencia Muebles S. L.",
    "wof:placetype":"venue"
},
  "geometry": {"coordinates":[-3.7756888866,40.280002594],"type":"Point"}
}