{
  "type": "Feature",
  "properties": {
    "iso:country":"ES",
    "sg:address":"Rua Paseo (do), 24",
    "sg:city":"Ourense",
    "sg:orig_category":"Empresarios Y Productoras De Espect\u00c1culos",
    "sg:phone":"+34 988 22 99 44",
    "sg:postcode":"32003",
    "sg:province":"Ourense",
    "sg:website":"www.elite-eventos.net",
    "wof:name":"Feijoo Vidueira Ana Belen",
    "wof:placetype":"venue"
},
  "geometry": {"coordinates":[-7.8643641472,42.3399353027],"type":"Point"}
}