{
  "type": "Feature",
  "properties": {
    "addr:full":"Calle de Francisco Aritio, 156 Guadalajara Guadalajara 19004",
    "addr:housenumber":"156",
    "addr:postcode":"19004",
    "addr:street":"Calle De Francisco Aritio",
    "iso:country":"ES",
    "sg:address":"Calle de Francisco Aritio, 156",
    "sg:city":"Guadalajara",
    "sg:orig_category":"Pintura Industrial (trabajos De)",
    "sg:phone":"+34 949 20 14 11",
    "sg:postcode":"19004",
    "sg:province":"Guadalajara",
    "sg:website":"www.decoracionesjuanma.com",
    "wof:name":"Aplicaciones Y Decoraciones Juanma S.l.",
    "wof:placetype":"venue"
},
  "geometry": {"coordinates":[-3.1989834309,40.623878479],"type":"Point"}
}