{
  "type": "Feature",
  "properties": {
    "iso:country":"ES",
    "sg:address":"Avda Pola De Lena, 17",
    "sg:city":"Vega",
    "sg:orig_category":"Edici\u00d3n De Diarios, Revistas, Boletines",
    "sg:phone":"+34 985 76 66 90",
    "sg:postcode":"33160",
    "sg:province":"Asturias",
    "wof:name":"Nuevo Circulo S.l.",
    "wof:placetype":"venue"
},
  "geometry": {"coordinates":[-5.8822832108,43.2305450439],"type":"Point"}
}