{
  "type": "Feature",
  "properties": {
    "addr:full":"Calle de Francisco Diaz, 1 Torrelavega Cantabria 39300",
    "addr:housenumber":"1",
    "addr:postcode":"39300",
    "addr:street":"Calle De Francisco Diaz",
    "iso:country":"ES",
    "sg:address":"Calle de Francisco Diaz, 1",
    "sg:city":"Torrelavega",
    "sg:orig_category":"Zapatos (al Por Menor)",
    "sg:phone":"+34 942 89 20 95",
    "sg:postcode":"39300",
    "sg:province":"Cantabria",
    "wof:name":"Calle Fernandez Santos",
    "wof:placetype":"venue"
},
  "geometry": {"coordinates":[-4.0482301712,43.3499946594],"type":"Point"}
}