{
  "type": "Feature",
  "properties": {
    "iso:country":"ES",
    "sg:address":"Pastorcito, 11",
    "sg:city":"Bollullos Par Condado",
    "sg:orig_category":"Material Y Herramientas Agr\u00cdcolas",
    "sg:phone":"+34 959 41 05 84",
    "sg:postcode":"21710",
    "sg:province":"Huelva",
    "wof:name":"Carrasco Gonzalez Antonio",
    "wof:placetype":"venue"
},
  "geometry": {"coordinates":[-6.5402488708,37.3431892395],"type":"Point"}
}