{
  "type": "Feature",
  "properties": {
    "addr:full":"Calle de Condes De Bustillo, 11 Sevilla Sevilla 41005",
    "addr:housenumber":"11",
    "addr:postcode":"41005",
    "addr:street":"Calle De Condes De Bustillo",
    "iso:country":"ES",
    "sg:address":"Calle de Condes De Bustillo, 11",
    "sg:city":"Sevilla",
    "sg:orig_category":"Asociaciones Humanitarias, De Cooperaci\u00d3n, De Acci\u00d3n Social",
    "sg:phone":"+34 954 63 94 07",
    "sg:postcode":"41005",
    "sg:province":"Sevilla",
    "wof:name":"Asociacion De Enfermos De Crohn Y Colitis Ulcerosa",
    "wof:placetype":"venue"
},
  "geometry": {"coordinates":[-6.0076336861,37.380191803],"type":"Point"}
}