{
  "type": "Feature",
  "properties": {
    "addr:full":"Calle de Joaquin Moya Martinez, 1 Bigastro Alicante 03380",
    "addr:housenumber":"1",
    "addr:postcode":"03380",
    "addr:street":"Calle De Joaquin Moya Martinez",
    "iso:country":"ES",
    "sg:address":"Calle de Joaquin Moya Martinez, 1",
    "sg:city":"Bigastro",
    "sg:orig_category":"Piedra Natural",
    "sg:phone":"+34 965 35 00 94",
    "sg:postcode":"03380",
    "sg:province":"Alicante",
    "wof:name":"Esquiva Alcaina Jose",
    "wof:placetype":"venue"
},
  "geometry": {"coordinates":[-0.892031014,38.0618515015],"type":"Point"}
}