{
  "type": "Feature",
  "properties": {
    "iso:country":"ES",
    "sg:address":"Avda Sol (del), 5",
    "sg:city":"Alcolea Cinca",
    "sg:orig_category":"Quincaller\u00cda (al Por Menor)",
    "sg:phone":"+34 974 46 94 98",
    "sg:postcode":"22410",
    "sg:province":"Huesca",
    "wof:name":"Ferreteria Ibarz S.l.",
    "wof:placetype":"venue"
},
  "geometry": {"coordinates":[0.1151150018,41.7227058411],"type":"Point"}
}