{
  "type": "Feature",
  "properties": {
    "addr:full":"Calle de Rodil, 30 Donostia-san Sebastian Guip\u00f9zcoa 20013",
    "addr:housenumber":"30",
    "addr:postcode":"20013",
    "addr:street":"Calle De Rodil",
    "iso:country":"ES",
    "sg:address":"Calle de Rodil, 30",
    "sg:city":"Donostia-san Sebastian",
    "sg:orig_category":"Clases De M\u00dasica Y Canto",
    "sg:phone":"+34 943 28 03 10",
    "sg:postcode":"20013",
    "sg:province":"Guip\u00f9zcoa",
    "wof:name":"Gascue Serrano Jesus",
    "wof:placetype":"venue"
},
  "geometry": {"coordinates":[-1.9673800468,43.3252944946],"type":"Point"}
}