{
  "type": "Feature",
  "properties": {
    "iso:country":"ES",
    "sg:address":"Calle de Padre Caro, 2",
    "sg:city":"Chiclana De La Frontera",
    "sg:orig_category":"Pod\u00d3logos: Pedicuros",
    "sg:phone":"+34 956 40 40 08",
    "sg:postcode":"11130",
    "sg:province":"C\u00e1diz",
    "wof:name":"Ruiz Marabot Alvaro",
    "wof:placetype":"venue"
},
  "geometry": {"coordinates":[-6.1483249664,36.4207611084],"type":"Point"}
}