{
  "type": "Feature",
  "properties": {
    "iso:country":"ES",
    "sg:address":"Calle de Heroe De Sostoa, 35",
    "sg:city":"Malaga",
    "sg:orig_category":"Pod\u00d3logos: Pedicuros",
    "sg:phone":"+34 952 34 88 76",
    "sg:postcode":"29002",
    "sg:province":"M\u00e1laga",
    "wof:name":"Herrera Rodriguez Juan",
    "wof:placetype":"venue"
},
  "geometry": {"coordinates":[-4.4342260361,36.7087440491],"type":"Point"}
}