{
  "type": "Feature",
  "properties": {
    "addr:full":"Calle de Luis Montoto, 31 Sevilla Sevilla 41018",
    "addr:housenumber":"31",
    "addr:postcode":"41018",
    "addr:street":"Calle De Luis Montoto",
    "iso:country":"ES",
    "sg:address":"Calle de Luis Montoto, 31",
    "sg:city":"Sevilla",
    "sg:orig_category":"Servicios Gsm",
    "sg:phone":"+34 954 98 98 21",
    "sg:postcode":"41018",
    "sg:province":"Sevilla",
    "wof:name":"Planetel Comunicaciones S.l.",
    "wof:placetype":"venue"
},
  "geometry": {"coordinates":[-5.9803380966,37.3878059387],"type":"Point"}
}