{
  "type": "Feature",
  "properties": {
    "addr:full":"Cmno Indio (del), S/n Tauste Zaragoza 50660",
    "addr:housenumber":"/ n",
    "addr:postcode":"50660",
    "addr:street":"Cmno Indio Del S",
    "iso:country":"ES",
    "sg:address":"Cmno Indio (del), S/n",
    "sg:city":"Tauste",
    "sg:orig_category":"Empresas De Desmonte",
    "sg:phone":"+34 976 85 48 07",
    "sg:postcode":"50660",
    "sg:province":"Zaragoza",
    "wof:name":"Gabete S.l.",
    "wof:placetype":"venue"
},
  "geometry": {"coordinates":[-1.26078403,41.9216842651],"type":"Point"}
}