{
  "type": "Feature",
  "properties": {
    "iso:country":"ES",
    "sg:address":"Pol Ind P Treinta-el Florio, S/n",
    "sg:city":"Granada",
    "sg:orig_category":"Electricidad, Electr\u00d3nica: Suministros (al Por Menor)",
    "sg:phone":"+34 958 29 09 08",
    "sg:postcode":"18015",
    "sg:province":"Granada",
    "wof:name":"Electronica Gilabert S.l",
    "wof:placetype":"venue"
},
  "geometry": {"coordinates":[-3.6356139183,37.1961364746],"type":"Point"}
}