{
  "type": "Feature",
  "properties": {
    "iso:country":"ES",
    "sg:address":"Calle de Parroquia De Guisamo, S/n",
    "sg:city":"Poligono Industrial",
    "sg:orig_category":"Distribuci\u00d3n De Petr\u00d3leo Y Derivados",
    "sg:phone":"+34 981 79 57 59",
    "sg:postcode":"15166",
    "sg:province":"La Coru\u00f1a",
    "wof:name":"Elaboradora De Cefalopodos S.a.",
    "wof:placetype":"venue"
},
  "geometry": {"coordinates":[-8.2616682053,43.3274726868],"type":"Point"}
}