{
  "type": "Feature",
  "properties": {
    "addr:full":"Calle de Ramal (el), 27 Lodosa Navarra 31580",
    "addr:housenumber":"27",
    "addr:postcode":"31580",
    "addr:street":"Calle De Ramal El",
    "iso:country":"ES",
    "sg:address":"Calle de Ramal (el), 27",
    "sg:city":"Lodosa",
    "sg:orig_category":"Sales (al Por Mayor)",
    "sg:phone":"+34 948 69 32 97",
    "sg:postcode":"31580",
    "sg:province":"Navarra",
    "wof:name":"Baigorri De Luis Francisco Javier",
    "wof:placetype":"venue"
},
  "geometry": {"coordinates":[-2.0684840679,42.4162368774],"type":"Point"}
}