{
  "type": "Feature",
  "properties": {
    "addr:full":"Calle de Ramon Celma Bernal, 2 Zaragoza Zaragoza 50003",
    "addr:housenumber":"2",
    "addr:postcode":"50003",
    "addr:street":"Calle De Ramon Celma Bernal",
    "iso:country":"ES",
    "sg:address":"Calle de Ramon Celma Bernal, 2",
    "sg:city":"Zaragoza",
    "sg:orig_category":"Cervecer\u00cdas",
    "sg:phone":"+34 976 43 33 99",
    "sg:postcode":"50003",
    "sg:province":"Zaragoza",
    "wof:name":"Medina Andreu Francisco",
    "wof:placetype":"venue"
},
  "geometry": {"coordinates":[-0.8892869949,41.6586723328],"type":"Point"}
}