{
  "type": "Feature",
  "properties": {
    "iso:country":"ES",
    "sg:address":"Luga Paramo De San Isidro, 55",
    "sg:city":"Valladolid",
    "sg:orig_category":"Empresas De Carpinter\u00cda De Madera",
    "sg:phone":"+34 983 29 11 66",
    "sg:postcode":"47012",
    "sg:province":"Valladolid",
    "wof:name":"Velsan Puertas Y Armarios",
    "wof:placetype":"venue"
},
  "geometry": {"coordinates":[-4.7035489082,41.6360473633],"type":"Point"}
}