{
  "type": "Feature",
  "properties": {
    "iso:country":"ES",
    "sg:address":"Calle de Goya, 8",
    "sg:city":"Barakaldo",
    "sg:orig_category":"Bazares, Art\u00cdculos De Limpieza Y De Cocina (al Por Menor)",
    "sg:phone":"+34 944 00 95 91",
    "sg:postcode":"48902",
    "sg:province":"Vizcaya",
    "wof:name":"Pedro Uribarri Goirigolzarri",
    "wof:placetype":"venue"
},
  "geometry": {"coordinates":[-2.9940888882,43.2949676514],"type":"Point"}
}