{
  "type": "Feature",
  "properties": {
    "iso:country":"ES",
    "sg:address":"Calle de Gardoqui Cardenal, 2",
    "sg:city":"Bilbao",
    "sg:orig_category":"Sociedades, Compa\u00d1\u00cdas Aseguradoras",
    "sg:phone":"+34 944 15 28 00",
    "sg:postcode":"48008",
    "sg:province":"Vizcaya",
    "wof:name":"Elkarkidetza, E.p.s.v.",
    "wof:placetype":"venue"
},
  "geometry": {"coordinates":[-2.9308280945,43.2610321045],"type":"Point"}
}