{
  "type": "Feature",
  "properties": {
    "addr:full":"Carrer de Bosc, 36 Barbera Valles Barcelona 08210",
    "addr:housenumber":"36",
    "addr:postcode":"08210",
    "addr:street":"Carrer De Bosc",
    "iso:country":"ES",
    "sg:address":"Carrer de Bosc, 36",
    "sg:city":"Barbera Valles",
    "sg:orig_category":"Fisioterapia",
    "sg:phone":"+34 937 18 36 45",
    "sg:postcode":"08210",
    "sg:province":"Barcelona",
    "wof:name":"Tirado Jimenez Tomas",
    "wof:placetype":"venue"
},
  "geometry": {"coordinates":[2.1292099953,41.5184211731],"type":"Point"}
}