{
  "type": "Feature",
  "properties": {
    "iso:country":"ES",
    "sg:address":"Avda Constitucion, 5",
    "sg:city":"Bollullos Par Condado",
    "sg:orig_category":"Caf\u00c9s, Bares, Cervecer\u00cdas",
    "sg:phone":"+34 959 41 20 08",
    "sg:postcode":"21710",
    "sg:province":"Huelva",
    "wof:name":"Lopez Sanchez Juan",
    "wof:placetype":"venue"
},
  "geometry": {"coordinates":[-6.5369710922,37.3392601013],"type":"Point"}
}