{
  "type": "Feature",
  "properties": {
    "iso:country":"ES",
    "sg:address":"Pl Francesc Serres, 1",
    "sg:city":"Gandesa",
    "sg:orig_category":"Prendas Y Chalecos De Punto (al Por Menor)",
    "sg:phone":"+34 977 42 02 17",
    "sg:postcode":"43780",
    "sg:province":"Tarragona",
    "wof:name":"Punto Deza S.a.",
    "wof:placetype":"venue"
},
  "geometry": {"coordinates":[0.4392699897,41.0579147339],"type":"Point"}
}