{
  "type": "Feature",
  "properties": {
    "addr:full":"Calle de Serantes, 7 Bilbao Vizcaya 48002",
    "addr:housenumber":"7",
    "addr:postcode":"48002",
    "addr:street":"Calle De Serantes",
    "iso:country":"ES",
    "sg:address":"Calle de Serantes, 7",
    "sg:city":"Bilbao",
    "sg:orig_category":"Molduras, Junquillos, Listones Y Molduras Perforadas",
    "sg:phone":"+34 944 43 43 09",
    "sg:postcode":"48002",
    "sg:province":"Vizcaya",
    "wof:name":"Moreira Lopez Antonio",
    "wof:placetype":"venue"
},
  "geometry": {"coordinates":[-2.9459729195,43.2501411438],"type":"Point"}
}