{
  "type": "Feature",
  "properties": {
    "iso:country":"ES",
    "sg:address":"Mariano Benlliure, 1",
    "sg:city":"Playa Canet Berenguer",
    "sg:orig_category":"Enfermeras: Consultas, Atenci\u00d3n A Domicilio",
    "sg:phone":"+34 962 60 93 59",
    "sg:postcode":"46529",
    "sg:province":"Valencia",
    "wof:name":"Mira Montero Ursula",
    "wof:placetype":"venue"
},
  "geometry": {"coordinates":[-0.2112669945,39.6762161255],"type":"Point"}
}