{
  "type": "Feature",
  "properties": {
    "iso:country":"ES",
    "sg:address":"Calle de Fruta De La, 37",
    "sg:city":"Aviles",
    "sg:orig_category":"Ropa Para Se\u00d1oras (al Por Menor)",
    "sg:phone":"+34 985 56 99 36",
    "sg:postcode":"33402",
    "sg:province":"Asturias",
    "wof:name":"Melocotton Club S.l.",
    "wof:placetype":"venue"
},
  "geometry": {"coordinates":[-5.9263877869,43.534324646],"type":"Point"}
}