{
  "type": "Feature",
  "properties": {
    "iso:country":"ES",
    "sg:address":"Av Passeig (del), 28",
    "sg:city":"Ponts",
    "sg:orig_category":"Molduras, Junquillos, Listones Y Molduras Perforadas",
    "sg:phone":"+34 973 46 03 15",
    "sg:postcode":"25740",
    "sg:province":"Lleida",
    "wof:name":"Paris Tico Enrique",
    "wof:placetype":"venue"
},
  "geometry": {"coordinates":[1.1858650446,41.9147033691],"type":"Point"}
}