{
  "type": "Feature",
  "properties": {
    "addr:full":"Ctra Pego (de), 27 Oliva Valencia 46780",
    "addr:housenumber":"27",
    "addr:postcode":"46780",
    "addr:street":"Ctra Pego De",
    "iso:country":"ES",
    "sg:address":"Ctra Pego (de), 27",
    "sg:city":"Oliva",
    "sg:orig_category":"Molduras, Junquillos, Listones Y Molduras Perforadas",
    "sg:phone":"+34 962 85 57 82",
    "sg:postcode":"46780",
    "sg:province":"Valencia",
    "wof:name":"Garcia Maians Isabel",
    "wof:placetype":"venue"
},
  "geometry": {"coordinates":[-0.1143999994,38.9141349792],"type":"Point"}
}