{
  "type": "Feature",
  "properties": {
    "iso:country":"ES",
    "sg:address":"Calle de Arrabal, 7",
    "sg:city":"Azaila",
    "sg:orig_category":"Centros De Educaci\u00d3n Especial",
    "sg:phone":"+34 978 82 50 10",
    "sg:postcode":"44590",
    "sg:province":"Teruel",
    "wof:name":"Diputacion General De Aragon",
    "wof:placetype":"venue"
},
  "geometry": {"coordinates":[-0.4956179857,41.2907218933],"type":"Point"}
}