{
  "type": "Feature",
  "properties": {
    "addr:full":"Calle de Yebenes, 68 Madrid Madrid 28047",
    "addr:housenumber":"68",
    "addr:postcode":"madrid;28047",
    "addr:street":"Calle De Yebenes",
    "iso:country":"ES",
    "sg:address":"Calle de Yebenes, 68",
    "sg:city":"Madrid",
    "sg:orig_category":"Pescader\u00cdas (al Por Menor)",
    "sg:phone":"+34 917 17 71 62",
    "sg:postcode":"28047",
    "sg:province":"Madrid",
    "wof:name":"Alonso Busnadiego Carlos",
    "wof:placetype":"venue"
},
  "geometry": {"coordinates":[-3.7533175945,40.3939056396],"type":"Point"}
}