{
  "type": "Feature",
  "properties": {
    "iso:country":"ES",
    "sg:address":"Calle de Castillo (del), 9",
    "sg:city":"Barbastro",
    "sg:orig_category":"Escayola Y Productos De Escayola (fabricaci\u00d3n, Al Por Mayor)",
    "sg:phone":"+34 974 31 17 76",
    "sg:postcode":"22300",
    "sg:province":"Huesca",
    "wof:name":"Vinues Escuer Jose Maria",
    "wof:placetype":"venue"
},
  "geometry": {"coordinates":[0.1260499954,42.0339889526],"type":"Point"}
}