{
  "type": "Feature",
  "properties": {
    "addr:full":"Carr Sant Ermengol, 48 Seu D'urgell Lleida 25700",
    "addr:housenumber":"48",
    "addr:postcode":"25700",
    "addr:street":"Carr Sant Ermengol",
    "iso:country":"ES",
    "sg:address":"Carr Sant Ermengol, 48",
    "sg:city":"Seu D'urgell",
    "sg:orig_category":"Cooperativas Agr\u00cdcolas",
    "sg:phone":"+34 973 35 51 94",
    "sg:postcode":"25700",
    "sg:province":"Lleida",
    "wof:name":"Pirenaica Sociedad Cooperativa Limitada",
    "wof:placetype":"venue"
},
  "geometry": {"coordinates":[0.6457189918,41.6027946472],"type":"Point"}
}