{
  "type": "Feature",
  "properties": {
    "iso:country":"ES",
    "sg:address":"Calle de Cuernavaca, 20",
    "sg:city":"Malaga",
    "sg:orig_category":"Equipo De Refrigeraci\u00d3n Industrial",
    "sg:phone":"+34 952 31 77 16",
    "sg:postcode":"29006",
    "sg:province":"M\u00e1laga",
    "wof:name":"Componentes Ortega S.a.",
    "wof:placetype":"venue"
},
  "geometry": {"coordinates":[-4.4745378494,36.7037582397],"type":"Point"}
}