{
  "type": "Feature",
  "properties": {
    "addr:full":"Calle de Solera, 37 Mojonera Almer\u00eda 04745",
    "addr:housenumber":"37",
    "addr:postcode":"04745",
    "addr:street":"Calle De Solera",
    "iso:country":"ES",
    "sg:address":"Calle de Solera, 37",
    "sg:city":"Mojonera",
    "sg:orig_category":"Empresas De Carpinter\u00cda De Madera",
    "sg:phone":"+34 950 33 16 50",
    "sg:postcode":"04745",
    "sg:province":"Almer\u00eda",
    "wof:name":"Carpinteria Coreano S.l",
    "wof:placetype":"venue"
},
  "geometry": {"coordinates":[-2.6804440022,36.7539482117],"type":"Point"}
}