{
  "type": "Feature",
  "properties": {
    "addr:full":"Calle de Perez Vengut, 5 Alacant Alicante 03010",
    "addr:housenumber":"5",
    "addr:postcode":"03010",
    "addr:street":"Calle De Perez Vengut",
    "iso:country":"ES",
    "sg:address":"Calle de Perez Vengut, 5",
    "sg:city":"Alacant",
    "sg:orig_category":"Caf\u00c9s, Bares, Cervecer\u00cdas",
    "sg:phone":"+34 965 25 96 70",
    "sg:postcode":"03010",
    "sg:province":"Alicante",
    "wof:name":"Cafeteria Efemerides",
    "wof:placetype":"venue"
},
  "geometry": {"coordinates":[-0.4841800034,38.361492157],"type":"Point"}
}