{
  "type": "Feature",
  "properties": {
    "iso:country":"ES",
    "sg:address":"Calle de Murrieta, 17",
    "sg:city":"Barakaldo",
    "sg:orig_category":"Carnicer\u00cdas, Carnicer\u00cdas",
    "sg:phone":"+34 944 38 57 12",
    "sg:postcode":"48901",
    "sg:province":"Vizcaya",
    "wof:name":"Francisco Javier Gomez Crespo",
    "wof:placetype":"venue"
},
  "geometry": {"coordinates":[-2.9862339497,43.3002662659],"type":"Point"}
}