{
  "type": "Feature",
  "properties": {
    "iso:country":"ES",
    "sg:address":"Plaz Aragon, 5",
    "sg:city":"Ayerbe",
    "sg:orig_category":"Alimentaci\u00d3n General (al Por Menor)",
    "sg:phone":"+34 974 38 00 45",
    "sg:postcode":"22800",
    "sg:province":"Huesca",
    "wof:name":"Romero Vera Miguel Angel",
    "wof:placetype":"venue"
},
  "geometry": {"coordinates":[-0.6891490221,42.277217865],"type":"Point"}
}