{
  "type": "Feature",
  "properties": {
    "iso:country":"ES",
    "sg:address":"Carretera Paloma, 2",
    "sg:city":"Era Alta",
    "sg:orig_category":"Reparaciones Y Remolcado De Veh\u00cdculos",
    "sg:phone":"+34 968 25 51 32",
    "sg:postcode":"30168",
    "sg:province":"Murcia",
    "wof:name":"Merino Martinez Jose",
    "wof:placetype":"venue"
},
  "geometry": {"coordinates":[-1.1684839725,37.9631690979],"type":"Point"}
}