{
  "type": "Feature",
  "properties": {
    "iso:country":"ES",
    "sg:address":"Calle de General Franco, 21",
    "sg:city":"Portomarin",
    "sg:orig_category":"Supermercados Y Hipermercados",
    "sg:phone":"+34 982 54 50 18",
    "sg:postcode":"27170",
    "sg:province":"Lugo",
    "wof:name":"Castelo Fernandez Manuel",
    "wof:placetype":"venue"
},
  "geometry": {"coordinates":[-7.616232872,42.8068199158],"type":"Point"}
}