{
  "type": "Feature",
  "properties": {
    "iso:country":"ES",
    "sg:address":"Calle de Simon Garcia, 2",
    "sg:city":"San Juan",
    "sg:orig_category":"Peluqueros: De Se\u00d1oras",
    "sg:phone":"+34 968 21 10 16",
    "sg:postcode":"30003",
    "sg:province":"Murcia",
    "wof:name":"Martinez Crevillen Teresa",
    "wof:placetype":"venue"
},
  "geometry": {"coordinates":[-1.12609303,37.9837036133],"type":"Point"}
}