{
  "type": "Feature",
  "properties": {
    "addr:full":"Calle de Agricultura (de La), 5 Huesca Huesca 22006",
    "addr:housenumber":"5",
    "addr:postcode":"22006",
    "addr:street":"Calle De Agricultura De La",
    "iso:country":"ES",
    "sg:address":"Calle de Agricultura (de La), 5",
    "sg:city":"Huesca",
    "sg:orig_category":"Negocio De Materiales De Construcci\u00d3n",
    "sg:phone":"+34 974 22 05 05",
    "sg:postcode":"22006",
    "sg:province":"Huesca",
    "wof:name":"Mosaicos Y Decoracion S. A.",
    "wof:placetype":"venue"
},
  "geometry": {"coordinates":[-0.4082258046,42.145488739],"type":"Point"}
}