{
  "type": "Feature",
  "properties": {
    "addr:full":"Castillo San Fernando, S/n Alacant Alicante 03...",
    "addr:housenumber":"/ n;03 ...",
    "addr:street":"San Fernando S;Alicante",
    "iso:country":"ES",
    "sg:address":"Castillo San Fernando, S/n",
    "sg:city":"Alacant",
    "sg:orig_category":"Organismos De Turismo",
    "sg:phone":"+34 965 93 54 90",
    "sg:postcode":"03...",
    "sg:province":"Alicante",
    "wof:name":"Generalitat Valenciana",
    "wof:placetype":"venue"
},
  "geometry": {"coordinates":[-0.4910627007,38.3521003723],"type":"Point"}
}