{
  "type": "Feature",
  "properties": {
    "iso:country":"ES",
    "sg:address":"Calle de Miguel Servet, 43",
    "sg:city":"Zaragoza",
    "sg:orig_category":"Aparcamientos (infraestructuras, Accesorios)",
    "sg:phone":"+34 976 41 58 39",
    "sg:postcode":"50013",
    "sg:province":"Zaragoza",
    "wof:name":"Vallespin Fernando Francisco",
    "wof:placetype":"venue"
},
  "geometry": {"coordinates":[-0.8715770245,41.6457901001],"type":"Point"}
}