{
  "type": "Feature",
  "properties": {
    "addr:full":"Pase General Davila, 202 Santander Cantabria 39006",
    "addr:housenumber":"202",
    "addr:postcode":"39006",
    "iso:country":"ES",
    "sg:address":"Pase General Davila, 202",
    "sg:city":"Santander",
    "sg:orig_category":"Universidades",
    "sg:phone":"+34 942 37 02 34",
    "sg:postcode":"39006",
    "sg:province":"Cantabria",
    "sg:website":"www.jovellanos.com",
    "wof:name":"Colegio Universitario Melchor De Jovellanos S.l.",
    "wof:placetype":"venue"
},
  "geometry": {"coordinates":[-3.8109591007,43.4677047729],"type":"Point"}
}