{
  "type": "Feature",
  "properties": {
    "iso:country":"ES",
    "sg:address":"Calle de Pintor Manuel Medina, 22",
    "sg:city":"Gijon",
    "sg:orig_category":"Frutas Y Legumbres Frescas (al Por Mayor)",
    "sg:phone":"+34 985 39 21 17",
    "sg:postcode":"33210",
    "sg:province":"Asturias",
    "wof:name":"Castro Cuesta Maria Asuncion",
    "wof:placetype":"venue"
},
  "geometry": {"coordinates":[-5.6692790985,43.5209159851],"type":"Point"}
}