{
  "type": "Feature",
  "properties": {
    "addr:full":"Calle de Zamora, 56 Salamanca Salamanca 37002",
    "addr:housenumber":"56",
    "addr:postcode":"37002",
    "addr:street":"Calle De Zamora",
    "iso:country":"ES",
    "sg:address":"Calle de Zamora, 56",
    "sg:city":"Salamanca",
    "sg:orig_category":"Asociaciones, Instituciones De Consumidores Y Usuarios",
    "sg:phone":"+34 923 21 00 42",
    "sg:postcode":"37002",
    "sg:province":"Salamanca",
    "wof:name":"Asociacion De Amas De Casa Y Consumidores",
    "wof:placetype":"venue"
},
  "geometry": {"coordinates":[-5.6638140678,40.968082428],"type":"Point"}
}