{
  "type": "Feature",
  "properties": {
    "addr:full":"Avda Santiago, 69 Balazote Albacete 02320",
    "addr:housenumber":"69",
    "addr:postcode":"02320",
    "addr:street":"Avda Santiago",
    "iso:country":"ES",
    "sg:address":"Avda Santiago, 69",
    "sg:city":"Balazote",
    "sg:orig_category":"Condimentos, Especias, Vinagres, Salsas Preparadas (fabricaci\u00d3n, Al Por Mayor)",
    "sg:phone":"+34 967 36 03 03",
    "sg:postcode":"02320",
    "sg:province":"Albacete",
    "wof:name":"Ajos Padilla S.l.",
    "wof:placetype":"venue"
},
  "geometry": {"coordinates":[-2.1563391685,38.8846435547],"type":"Point"}
}