{
  "type": "Feature",
  "properties": {
    "iso:country":"ES",
    "sg:address":"Calle de Nieves Ravelo, 2",
    "sg:city":"Puerto Cruz",
    "sg:orig_category":"Herboristas (al Por Menor)",
    "sg:phone":"+34 922 36 86 26",
    "sg:postcode":"38400",
    "sg:province":"Santa Cruz De Tenerife",
    "sg:website":"www.solucionesnuevaera.com",
    "wof:name":"Frosterus Frosterus Carlos Emilio",
    "wof:placetype":"venue"
},
  "geometry": {"coordinates":[-16.5510978699,28.4150485992],"type":"Point"}
}