{
  "type": "Feature",
  "properties": {
    "addr:full":"Calle de Teowaldo Power, 11 Tias Las Palmas 35572",
    "addr:housenumber":"11",
    "addr:postcode":"35572",
    "addr:street":"Calle De Teowaldo Power",
    "iso:country":"ES",
    "sg:address":"Calle de Teowaldo Power, 11",
    "sg:city":"Tias",
    "sg:orig_category":"Bazares, Art\u00cdculos De Limpieza Y De Cocina (al Por Menor)",
    "sg:phone":"+34 928 83 37 10",
    "sg:postcode":"35572",
    "sg:province":"Las Palmas",
    "wof:name":"Brito Ramos Braulio",
    "wof:placetype":"venue"
},
  "geometry": {"coordinates":[-13.6470594406,28.9559497833],"type":"Point"}
}