{
  "type": "Feature",
  "properties": {
    "addr:full":"Avda Miguel Rodriguez Bautista, 8 Santa Uxia De Ribeira La Coru\u00f1a 15960",
    "addr:housenumber":"8",
    "addr:postcode":"15960",
    "addr:street":"Avda Miguel Rodriguez Bautista;Corun\u0303A",
    "iso:country":"ES",
    "sg:address":"Avda Miguel Rodriguez Bautista, 8",
    "sg:city":"Santa Uxia De Ribeira",
    "sg:orig_category":"Muebles, Minoristas",
    "sg:phone":"+34 981 87 35 69",
    "sg:postcode":"15960",
    "sg:province":"La Coru\u00f1a",
    "wof:name":"Martinez Del Campo Ricoy Beatriz",
    "wof:placetype":"venue"
},
  "geometry": {"coordinates":[-8.9945087433,42.5562782288],"type":"Point"}
}