{
  "type": "Feature",
  "properties": {
    "addr:full":"Calle de Alejandro Sanchez, 22 Madrid Madrid 28019",
    "addr:housenumber":"22",
    "addr:postcode":"madrid;28019",
    "addr:street":"Calle De Alejandro Sanchez",
    "iso:country":"ES",
    "sg:address":"Calle de Alejandro Sanchez, 22",
    "sg:city":"Madrid",
    "sg:orig_category":"Transportes Por Carretera: Lotes Completos, Mercanc\u00cdas Diversas",
    "sg:phone":"+34 914 71 15 02",
    "sg:postcode":"28019",
    "sg:province":"Madrid",
    "wof:name":"Sanchez Del Molino Esperanza",
    "wof:placetype":"venue"
},
  "geometry": {"coordinates":[-3.7254824638,40.3905906677],"type":"Point"}
}