{
  "type": "Feature",
  "properties": {
    "addr:full":"Joanot Martorell, 33 Massanassa Valencia 46470",
    "addr:housenumber":"33",
    "addr:postcode":"46470",
    "iso:country":"ES",
    "sg:address":"Joanot Martorell, 33",
    "sg:city":"Massanassa",
    "sg:orig_category":"Pintura, Barniz, Productos Asimilables (fabricaci\u00d3n, Al Por Mayor)",
    "sg:phone":"+34 961 25 17 44",
    "sg:postcode":"46470",
    "sg:province":"Valencia",
    "wof:name":"Porcar Valero S.l.",
    "wof:placetype":"venue"
},
  "geometry": {"coordinates":[-0.3999519944,39.4133300781],"type":"Point"}
}