{
  "type": "Feature",
  "properties": {
    "addr:full":"Venda Pi Catala, 2796 Pujols Islas Baleares 07871",
    "addr:postcode":"2796;07871",
    "iso:country":"ES",
    "sg:address":"Venda Pi Catala, 2796",
    "sg:city":"Pujols",
    "sg:orig_category":"Supermercados Y Hipermercados",
    "sg:phone":"+34 971 32 83 23",
    "sg:postcode":"07871",
    "sg:province":"Islas Baleares",
    "wof:name":"Mayans Mayans Isabel",
    "wof:placetype":"venue"
},
  "geometry": {"coordinates":[1.4565550089,38.7221031189],"type":"Point"}
}