{
  "type": "Feature",
  "properties": {
    "addr:full":"Avda Alcalde Gines De La Hoz, 12 Arrecife Las Palmas 35500",
    "addr:housenumber":"12",
    "addr:postcode":"35500",
    "addr:street":"Avda Alcalde Gines De La Hoz",
    "iso:country":"ES",
    "sg:address":"Avda Alcalde Gines De La Hoz, 12",
    "sg:city":"Arrecife",
    "sg:orig_category":"Ropa Para Se\u00d1oras (al Por Menor)",
    "sg:phone":"+34 928 81 61 30",
    "sg:postcode":"35500",
    "sg:province":"Las Palmas",
    "wof:name":"Lemes Martin Maria Teresa",
    "wof:placetype":"venue"
},
  "geometry": {"coordinates":[-13.5544929504,28.9643535614],"type":"Point"}
}