{
  "type": "Feature",
  "properties": {
    "addr:full":"Calle de Virgen De La Paloma, 7 Torrejon Ardoz Madrid 28850",
    "addr:housenumber":"7",
    "addr:postcode":"28850",
    "addr:street":"Calle De Virgen De La Paloma",
    "iso:country":"ES",
    "sg:address":"Calle de Virgen De La Paloma, 7",
    "sg:city":"Torrejon Ardoz",
    "sg:orig_category":"Equipo De Refrigeraci\u00d3n Industrial",
    "sg:phone":"+34 916 56 83 76",
    "sg:postcode":"28850",
    "sg:province":"Madrid",
    "wof:name":"Saez Gonzalez Antonio",
    "wof:placetype":"venue"
},
  "geometry": {"coordinates":[-3.4770400524,40.459564209],"type":"Point"}
}