{
  "type": "Feature",
  "properties": {
    "iso:country":"ES",
    "sg:address":"Trva Soledad, 1",
    "sg:city":"Casar",
    "sg:orig_category":"Ense\u00d1anza, Formaci\u00d3n Profesional: Aprendizaje",
    "sg:phone":"+34 949 33 55 58",
    "sg:postcode":"19170",
    "sg:province":"Guadalajara",
    "wof:name":"Ayuntamiento De El Casar De Talamanca",
    "wof:placetype":"venue"
},
  "geometry": {"coordinates":[-3.4273540974,40.7037086487],"type":"Point"}
}