{
  "type": "Feature",
  "properties": {
    "iso:country":"ES",
    "sg:address":"Masti-loidi, 21",
    "sg:city":"Errenteria",
    "sg:orig_category":"Minerales (al Por Mayor)",
    "sg:phone":"+34 943 51 58 11",
    "sg:postcode":"20100",
    "sg:province":"Guip\u00f9zcoa",
    "wof:name":"Birakomp S.a.",
    "wof:placetype":"venue"
},
  "geometry": {"coordinates":[-1.8970370293,43.3210067749],"type":"Point"}
}