{
  "type": "Feature",
  "properties": {
    "iso:country":"ES",
    "sg:address":"Calle de Mariano Benlliure, 1",
    "sg:city":"Alfafar",
    "sg:orig_category":"Inmobiliaria (agencias)",
    "sg:phone":"+34 963 96 46 94",
    "sg:postcode":"46910",
    "sg:province":"Valencia",
    "wof:name":"Servicios Inmobiliarios Abril S.l.",
    "wof:placetype":"venue"
},
  "geometry": {"coordinates":[-0.3916290104,39.4234886169],"type":"Point"}
}