{
  "type": "Feature",
  "properties": {
    "addr:full":"Calle de Mayor, 12 Casillas Murcia 30007",
    "addr:housenumber":"12",
    "addr:postcode":"30007",
    "addr:street":"Calle De Mayor",
    "iso:country":"ES",
    "sg:address":"Calle de Mayor, 12",
    "sg:city":"Casillas",
    "sg:orig_category":"Relojer\u00cda (al Por Menor, Reparaci\u00d3n)",
    "sg:phone":"+34 968 30 22 51",
    "sg:postcode":"30007",
    "sg:province":"Murcia",
    "wof:name":"Esteban Canovas Encarnacion",
    "wof:placetype":"venue"
},
  "geometry": {"coordinates":[-1.0905929804,38.00938797],"type":"Point"}
}