{
  "type": "Feature",
  "properties": {
    "addr:full":"Calle de Leon Y Castillo, 194 Palmas De Gran Canaria Las Palmas 35004",
    "addr:housenumber":"194",
    "addr:postcode":"35004",
    "addr:street":"Calle De Leon Y Castillo",
    "iso:country":"ES",
    "sg:address":"Calle de Leon Y Castillo, 194",
    "sg:city":"Palmas De Gran Canaria",
    "sg:orig_category":"Agencias Y Agentes Comerciales, Representantes",
    "sg:phone":"+34 928 24 14 28",
    "sg:postcode":"35004",
    "sg:province":"Las Palmas",
    "wof:name":"Medina Martin Agustin Prometeo",
    "wof:placetype":"venue"
},
  "geometry": {"coordinates":[-15.4237241745,28.1177558899],"type":"Point"}
}