{
  "type": "Feature",
  "properties": {
    "iso:country":"ES",
    "sg:address":"Ptda Mas De Don Pedro, 12",
    "sg:city":"Masia Del Juez",
    "sg:orig_category":"Restaurantes",
    "sg:phone":"+34 961 56 80 01",
    "sg:postcode":"46909",
    "sg:province":"Valencia",
    "wof:name":"Comis Lagun S.l.",
    "wof:placetype":"venue"
},
  "geometry": {"coordinates":[-0.5208799839,39.4396781921],"type":"Point"}
}