{
  "type": "Feature",
  "properties": {
    "addr:full":"Carr Canonigo Cebrian, 11 Xativa Valencia 46800",
    "addr:housenumber":"11",
    "addr:postcode":"46800",
    "addr:street":"Carr Canonigo Cebrian",
    "iso:country":"ES",
    "sg:address":"Carr Canonigo Cebrian, 11",
    "sg:city":"Xativa",
    "sg:orig_category":"Reposter\u00cdas",
    "sg:phone":"+34 962 27 53 29",
    "sg:postcode":"46800",
    "sg:province":"Valencia",
    "wof:name":"Rico Fayos Emilio",
    "wof:placetype":"venue"
},
  "geometry": {"coordinates":[-0.5230939984,38.9884300232],"type":"Point"}
}