{
  "type": "Feature",
  "properties": {
    "iso:country":"ES",
    "sg:address":"Calle de Darsena De La Batea, 4",
    "sg:city":"Almerimar",
    "sg:orig_category":"Deportes N\u00c1uticos, Acu\u00c1ticos Y Subacu\u00c1ticos: Art\u00cdculos Y Equipo (al Por Menor)",
    "sg:phone":"+34 950 49 72 41",
    "sg:postcode":"04711",
    "sg:province":"Almer\u00eda",
    "wof:name":"Ckv Boat Company S.l.",
    "wof:placetype":"venue"
},
  "geometry": {"coordinates":[-2.7920789719,36.6989707947],"type":"Point"}
}