{
  "type": "Feature",
  "properties": {
    "iso:country":"ES",
    "sg:address":"Carrer de Bellaire, 5",
    "sg:city":"Olot",
    "sg:orig_category":"Artes Gr\u00c1ficas, Artes Pl\u00c1sticas (curso)",
    "sg:phone":"+34 972 26 05 86",
    "sg:postcode":"17800",
    "sg:province":"Girona",
    "sg:website":"www.pigmentdeolot.com",
    "wof:name":"Vayreda Puigvert Marian",
    "wof:placetype":"venue"
},
  "geometry": {"coordinates":[2.4897220135,42.1821060181],"type":"Point"}
}