{
  "type": "Feature",
  "properties": {
    "addr:full":"Avda Pablo Ruiz Picasso, 18 Alora M\u00e1laga 29500",
    "addr:housenumber":"18",
    "addr:postcode":"29500",
    "addr:street":"Avda Pablo Ruiz Picasso;Ma\u0301Laga",
    "iso:country":"ES",
    "sg:address":"Avda Pablo Ruiz Picasso, 18",
    "sg:city":"Alora",
    "sg:orig_category":"Molduras, Junquillos, Listones Y Molduras Perforadas",
    "sg:phone":"+34 952 49 67 82",
    "sg:postcode":"29500",
    "sg:province":"M\u00e1laga",
    "wof:name":"Emprendedoras Valle Sol S.l.l.",
    "wof:placetype":"venue"
},
  "geometry": {"coordinates":[-4.7039217949,36.8309211731],"type":"Point"}
}