{
  "type": "Feature",
  "properties": {
    "addr:full":"Carrer de Murcia, 36 S. Boi Llobregat Barcelona 08830",
    "addr:housenumber":"36",
    "addr:postcode":"08830",
    "addr:street":"Carrer De Murcia",
    "iso:country":"ES",
    "sg:address":"Carrer de Murcia, 36",
    "sg:city":"S. Boi Llobregat",
    "sg:orig_category":"Fijaciones Industriales",
    "sg:phone":"+34 936 52 53 58",
    "sg:postcode":"08830",
    "sg:province":"Barcelona",
    "wof:name":"I.t.w.construction Products Espa\u00f1a S.a.",
    "wof:placetype":"venue"
},
  "geometry": {"coordinates":[2.0411920547,41.3280982971],"type":"Point"}
}