{
  "type": "Feature",
  "properties": {
    "iso:country":"ES",
    "sg:address":"Carr Jose Saez, 3",
    "sg:city":"Betera",
    "sg:orig_category":"Bisuter\u00cda, Joyer\u00cda, Relojer\u00cda (al Por Menor)",
    "sg:phone":"+34 961 60 17 20",
    "sg:postcode":"46117",
    "sg:province":"Valencia",
    "wof:name":"Arnal Fernandez Jose Luis",
    "wof:placetype":"venue"
},
  "geometry": {"coordinates":[-0.4570392966,39.5909004211],"type":"Point"}
}