{
  "type": "Feature",
  "properties": {
    "addr:full":"Avda Libertad, 15 S. Gines Murcia 30169",
    "addr:housenumber":"15",
    "addr:postcode":"30169",
    "addr:street":"Avda Libertad;S. Gines",
    "iso:country":"ES",
    "sg:address":"Avda Libertad, 15",
    "sg:city":"S. Gines",
    "sg:orig_category":"Transportes Por Carretera: Lotes Completos, Mercanc\u00cdas Diversas",
    "sg:phone":"+34 968 88 14 59",
    "sg:postcode":"30169",
    "sg:province":"Murcia",
    "wof:name":"Exani S.l.",
    "wof:placetype":"venue"
},
  "geometry": {"coordinates":[-1.1717859507,37.9537963867],"type":"Point"}
}