{
  "type": "Feature",
  "properties": {
    "iso:country":"ES",
    "sg:address":"Calle de Dolores Ibarruri (de), 16",
    "sg:city":"Alcobendas",
    "sg:orig_category":"Agencias Y Agentes Comerciales, Representantes",
    "sg:phone":"+34 916 62 72 18",
    "sg:postcode":"28100",
    "sg:province":"Madrid",
    "wof:name":"Tarodo Toys S.l.",
    "wof:placetype":"venue"
},
  "geometry": {"coordinates":[-3.6540920734,40.5503044128],"type":"Point"}
}