{
  "type": "Feature",
  "properties": {
    "addr:full":"Carr Canonge Oliver, De, S/n Port Islas Baleares 07108",
    "addr:postcode":"07108",
    "addr:street":"Carr Canonge Oliver De S / N",
    "iso:country":"ES",
    "sg:address":"Carr Canonge Oliver, De, S/n",
    "sg:city":"Port",
    "sg:orig_category":"Centros De Educaci\u00d3n Especial",
    "sg:phone":"+34 971 63 01 01",
    "sg:postcode":"07108",
    "sg:province":"Islas Baleares",
    "wof:name":"Ajuntament De Soller Escole Des Port",
    "wof:placetype":"venue"
},
  "geometry": {"coordinates":[2.6968967915,39.7976379395],"type":"Point"}
}