{
  "type": "Feature",
  "properties": {
    "iso:country":"ES",
    "sg:address":"Pase San Isidro, 22",
    "sg:city":"Alcazar S. Juan",
    "sg:orig_category":"Agencias Y Asesores De Publicidad",
    "sg:phone":"+34 926 55 00 13",
    "sg:postcode":"13600",
    "sg:province":"Ciudad Real",
    "wof:name":"Tomluy S.l.",
    "wof:placetype":"venue"
},
  "geometry": {"coordinates":[-3.210203886,39.3900718689],"type":"Point"}
}