{
  "type": "Feature",
  "properties": {
    "addr:full":"Calle de Santa Monica, 26 Tincer Santa Cruz De Tenerife 38010",
    "addr:housenumber":"26",
    "addr:postcode":"38010",
    "addr:street":"Calle De Santa Monica",
    "iso:country":"ES",
    "sg:address":"Calle de Santa Monica, 26",
    "sg:city":"Tincer",
    "sg:orig_category":"Asociaciones Humanitarias, De Cooperaci\u00d3n, De Acci\u00d3n Social",
    "sg:phone":"+34 922 65 45 79",
    "sg:postcode":"38010",
    "sg:province":"Santa Cruz De Tenerife",
    "wof:name":"Asociacion Espa\u00f1ola Contra El Cancer",
    "wof:placetype":"venue"
},
  "geometry": {"coordinates":[-16.2548561096,28.4698104858],"type":"Point"}
}