{
  "type": "Feature",
  "properties": {
    "addr:full":"Askizu Auzoa, 33 Askizu Guip\u00f9zcoa 20808",
    "addr:housenumber":"33",
    "addr:postcode":"20808",
    "addr:street":"Askizu Auzoa;Guipu\u0300Zcoa",
    "iso:country":"ES",
    "sg:address":"Askizu Auzoa, 33",
    "sg:city":"Askizu",
    "sg:orig_category":"Distribuci\u00d3n De Petr\u00d3leo Y Derivados",
    "sg:phone":"+34 943 14 06 67",
    "sg:postcode":"20808",
    "sg:province":"Guip\u00f9zcoa",
    "wof:name":"Orrua Itxasondo Arraiak S.a.",
    "wof:placetype":"venue"
},
  "geometry": {"coordinates":[-2.2049660683,43.3031158447],"type":"Point"}
}