{
  "type": "Feature",
  "properties": {
    "iso:country":"ES",
    "sg:address":"Calle de Martin Chamorro, 4",
    "sg:city":"Malpartida Plasencia",
    "sg:orig_category":"Carnicer\u00cdas, Carnicer\u00cdas",
    "sg:phone":"+34 927 40 46 73",
    "sg:postcode":"10680",
    "sg:province":"C\u00e1ceres",
    "wof:name":"Perez Fernandez Juan Carlos",
    "wof:placetype":"venue"
},
  "geometry": {"coordinates":[-6.0438508987,39.9806480408],"type":"Point"}
}