{
  "type": "Feature",
  "properties": {
    "addr:full":"Carrer de Mila I Fontanals, 111 Santa Coloma De Gramenet Barcelona 08922",
    "addr:housenumber":"111",
    "addr:postcode":"08922",
    "addr:street":"Carrer De Mila I Fontanals",
    "iso:country":"ES",
    "sg:address":"Carrer de Mila I Fontanals, 111",
    "sg:city":"Santa Coloma De Gramenet",
    "sg:orig_category":"Arreglo, Reparaci\u00d3n, Piezas Sueltas De Televisi\u00d3n, V\u00cddeo, Hi",
    "sg:phone":"+34 933 92 22 86",
    "sg:postcode":"08922",
    "sg:province":"Barcelona",
    "wof:name":"Hermanos Amate S.l.",
    "wof:placetype":"venue"
},
  "geometry": {"coordinates":[2.2181780338,41.4512252808],"type":"Point"}
}