{
  "type": "Feature",
  "properties": {
    "iso:country":"ES",
    "sg:address":"Calle de Menendez Pidal, 3",
    "sg:city":"Almoradi",
    "sg:orig_category":"Ense\u00d1anza Variada",
    "sg:phone":"+34 965 70 17 93",
    "sg:postcode":"03160",
    "sg:province":"Alicante",
    "wof:name":"Manzanera Rodriguez Juan Manuel",
    "wof:placetype":"venue"
},
  "geometry": {"coordinates":[-0.787711978,38.1076583862],"type":"Point"}
}