{
  "type": "Feature",
  "properties": {
    "addr:full":"Calle de Zubiaurre, 29 Donostia-san Sebastian Guip\u00f9zcoa 20013",
    "addr:housenumber":"29",
    "addr:postcode":"20013",
    "addr:street":"Calle De Zubiaurre",
    "iso:country":"ES",
    "sg:address":"Calle de Zubiaurre, 29",
    "sg:city":"Donostia-san Sebastian",
    "sg:orig_category":"Afiladoras, Pulidoras Y Bru\u00d1idoras",
    "sg:phone":"+34 943 29 15 04",
    "sg:postcode":"20013",
    "sg:province":"Guip\u00f9zcoa",
    "wof:name":"Juan Adajas Fernando",
    "wof:placetype":"venue"
},
  "geometry": {"coordinates":[-1.9622089863,43.3204689026],"type":"Point"}
}