{
  "type": "Feature",
  "properties": {
    "iso:country":"ES",
    "sg:address":"Calle de Azalea (de La), 219",
    "sg:city":"Alcobendas",
    "sg:orig_category":"Inmobiliaria (agencias)",
    "sg:phone":"+34 916 50 22 65",
    "sg:postcode":"28109",
    "sg:province":"Madrid",
    "wof:name":"Seneca Seis S.a.",
    "wof:placetype":"venue"
},
  "geometry": {"coordinates":[-3.6486859322,40.5219345093],"type":"Point"}
}