{
  "type": "Feature",
  "properties": {
    "addr:full":"Calle de Daoiz Y Velarde, 15 Le\u00f3n Le\u00f3n 24006",
    "addr:housenumber":"15",
    "addr:postcode":"24006",
    "addr:street":"Calle De Daoiz Y Velarde;Leo\u0301N",
    "iso:country":"ES",
    "sg:address":"Calle de Daoiz Y Velarde, 15",
    "sg:city":"Le\u00f3n",
    "sg:orig_category":"Carnicer\u00cdas, Carnicer\u00cdas",
    "sg:phone":"+34 987 21 25 65",
    "sg:postcode":"24006",
    "sg:province":"Le\u00f3n",
    "wof:name":"Panizo Abella Tomas",
    "wof:placetype":"venue"
},
  "geometry": {"coordinates":[-5.56397295,42.5964813232],"type":"Point"}
}