{
  "type": "Feature",
  "properties": {
    "iso:country":"ES",
    "sg:address":"Calle de Barquillo, 44",
    "sg:city":"Madrid",
    "sg:orig_category":"Asociaciones, Organismos Culturales Y Socioeducativos",
    "sg:phone":"+34 913 08 12 33",
    "sg:postcode":"28004",
    "sg:province":"Madrid",
    "wof:name":"Federacion De Organizaciones Feministas",
    "wof:placetype":"venue"
},
  "geometry": {"coordinates":[-3.6954948902,40.4243049622],"type":"Point"}
}