{
  "type": "Feature",
  "properties": {
    "iso:country":"ES",
    "sg:address":"Ctro Cial Campanario, 12",
    "sg:city":"Mijas Costa",
    "sg:orig_category":"Inmobiliaria (agencias)",
    "sg:phone":"+34 952 93 42 51",
    "sg:postcode":"29649",
    "sg:province":"M\u00e1laga",
    "wof:name":"Dream House Properties S.l.",
    "wof:placetype":"venue"
},
  "geometry": {"coordinates":[-4.6310629845,36.5238952637],"type":"Point"}
}