{
  "type": "Feature",
  "properties": {
    "iso:country":"ES",
    "sg:address":"Carrer de Ventura Gassol, 3",
    "sg:city":"Mora Nova",
    "sg:orig_category":"Alimentaci\u00d3n General (al Por Mayor)",
    "sg:phone":"+34 977 40 07 60",
    "sg:postcode":"43770",
    "sg:province":"Tarragona",
    "wof:name":"Graell Rodriguez Francisco",
    "wof:placetype":"venue"
},
  "geometry": {"coordinates":[0.6531451941,41.1016044617],"type":"Point"}
}