{
  "type": "Feature",
  "properties": {
    "iso:country":"ES",
    "sg:address":"Calle de Oto\u00d1o, S/n",
    "sg:city":"Benidorm",
    "sg:orig_category":"Mec\u00c1nico Del Autom\u00d3vil",
    "sg:phone":"+34 965 85 27 30",
    "sg:postcode":"03500",
    "sg:province":"Alicante",
    "wof:name":"Luan Auto Sport S.l.",
    "wof:placetype":"venue"
},
  "geometry": {"coordinates":[-0.1283340007,38.5384750366],"type":"Point"}
}