{
  "type": "Feature",
  "properties": {
    "iso:country":"ES",
    "sg:address":"Calle de Miguel Redondo, 35",
    "sg:city":"Huelva",
    "sg:orig_category":"Doctores En Medicina",
    "sg:phone":"+34 959 26 39 45",
    "sg:postcode":"21003",
    "sg:province":"Huelva",
    "wof:name":"Mendez Sangil Benito",
    "wof:placetype":"venue"
},
  "geometry": {"coordinates":[-6.9508137703,37.2543029785],"type":"Point"}
}