{
  "type": "Feature",
  "properties": {
    "addr:full":"Av Meridiana, 141 Barcelona Barcelona 08026",
    "addr:housenumber":"141",
    "addr:postcode":"08026",
    "addr:street":"Meridiana",
    "iso:country":"ES",
    "sg:address":"Av Meridiana, 141",
    "sg:city":"Barcelona",
    "sg:orig_category":"Gastronom\u00cda: Especialidades Regionales Y Extranjeras (producci\u00d3n, Al Por Mayor)",
    "sg:phone":"+34 932 45 14 97",
    "sg:postcode":"08026",
    "sg:province":"Barcelona",
    "wof:name":"Ulloa Ulloa Ana",
    "wof:placetype":"venue"
},
  "geometry": {"coordinates":[2.1866719723,41.4103622437],"type":"Point"}
}