{
  "type": "Feature",
  "properties": {
    "addr:full":"Calle de Real, 3 Pizarra M\u00e1laga 29560",
    "addr:housenumber":"3",
    "addr:postcode":"29560",
    "addr:street":"Calle De Real",
    "iso:country":"ES",
    "sg:address":"Calle de Real, 3",
    "sg:city":"Pizarra",
    "sg:orig_category":"Fotocopias, Reprograf\u00cda",
    "sg:phone":"+34 952 48 47 87",
    "sg:postcode":"29560",
    "sg:province":"M\u00e1laga",
    "wof:name":"Sanchez Navarro Almudena",
    "wof:placetype":"venue"
},
  "geometry": {"coordinates":[-4.707777977,36.7673988342],"type":"Point"}
}