{
  "type": "Feature",
  "properties": {
    "iso:country":"ES",
    "sg:address":"Pase Catalina De Ribera, S/n",
    "sg:city":"Sevilla",
    "sg:orig_category":"Aparcamientos (infraestructuras, Accesorios)",
    "sg:phone":"+34 954 41 73 35",
    "sg:postcode":"41004",
    "sg:province":"Sevilla",
    "wof:name":"Jocaral S.a.",
    "wof:placetype":"venue"
},
  "geometry": {"coordinates":[-5.9872140884,37.3854408264],"type":"Point"}
}