{
  "type": "Feature",
  "properties": {
    "addr:full":"Carr Jesus, 10 Badalona Barcelona 08911",
    "addr:housenumber":"10",
    "addr:postcode":"08911",
    "addr:street":"Carr Jesus",
    "iso:country":"ES",
    "sg:address":"Carr Jesus, 10",
    "sg:city":"Badalona",
    "sg:orig_category":"Ropa Para Se\u00d1oras Y Caballeros (al Por Menor)",
    "sg:phone":"+34 933 89 56 36",
    "sg:postcode":"08911",
    "sg:province":"Barcelona",
    "wof:name":"Villanueva Xufre Laura",
    "wof:placetype":"venue"
},
  "geometry": {"coordinates":[2.2491910458,41.4480514526],"type":"Point"}
}