{
  "type": "Feature",
  "properties": {
    "iso:country":"ES",
    "sg:address":"C/ Major (m.), 15",
    "sg:city":"Manacor",
    "sg:orig_category":"Empresarios",
    "sg:phone":"+34 971 55 94 24",
    "sg:postcode":"07500",
    "sg:province":"Islas Baleares",
    "wof:name":"Mascaro Riera Melchor",
    "wof:placetype":"venue"
},
  "geometry": {"coordinates":[3.2083950043,39.569103241],"type":"Point"}
}