{
  "type": "Feature",
  "properties": {
    "addr:full":"Carrer de Demostenes, 11 Sabadell Barcelona 08206",
    "addr:housenumber":"11",
    "addr:postcode":"08206",
    "addr:street":"Carrer De Demostenes",
    "iso:country":"ES",
    "sg:address":"Carrer de Demostenes, 11",
    "sg:city":"Sabadell",
    "sg:orig_category":"Art\u00cdculos De Regalo (al Por Menor)",
    "sg:phone":"+34 937 16 98 16",
    "sg:postcode":"08206",
    "sg:province":"Barcelona",
    "wof:name":"Hu  Lyian",
    "wof:placetype":"venue"
},
  "geometry": {"coordinates":[2.0865259171,41.554901123],"type":"Point"}
}