{
  "type": "Feature",
  "properties": {
    "addr:full":"Carrer de Iscle Soler, 1 Cornella Llobregat Barcelona 08940",
    "addr:housenumber":"1",
    "addr:postcode":"08940",
    "addr:street":"Carrer De Iscle Soler",
    "iso:country":"ES",
    "sg:address":"Carrer de Iscle Soler, 1",
    "sg:city":"Cornella Llobregat",
    "sg:orig_category":"Caf\u00c9s, Bares, Cervecer\u00cdas",
    "sg:phone":"+34 933 75 26 05",
    "sg:postcode":"08940",
    "sg:province":"Barcelona",
    "wof:name":"Hernandez Villena Inmaculada",
    "wof:placetype":"venue"
},
  "geometry": {"coordinates":[2.0761020184,41.3652191162],"type":"Point"}
}