{
  "type": "Feature",
  "properties": {
    "addr:full":"Calle de Sol, 3 Espinosa De Los Monteros Burgos 09560",
    "addr:housenumber":"3",
    "addr:postcode":"09560",
    "addr:street":"Calle De Sol",
    "iso:country":"ES",
    "sg:address":"Calle de Sol, 3",
    "sg:city":"Espinosa De Los Monteros",
    "sg:orig_category":"Panader\u00cdas, Panader\u00cdas",
    "sg:phone":"+34 947 12 00 40",
    "sg:postcode":"09560",
    "sg:province":"Burgos",
    "wof:name":"Arroyo Regules Maria Marcos",
    "wof:placetype":"venue"
},
  "geometry": {"coordinates":[-3.5521440506,43.0771598816],"type":"Point"}
}