{
  "type": "Feature",
  "properties": {
    "iso:country":"ES",
    "sg:address":"Julio Ruiz De Alda, 18",
    "sg:city":"Estella",
    "sg:orig_category":"Pescader\u00cdas (al Por Menor)",
    "sg:phone":"+34 948 55 34 61",
    "sg:postcode":"31200",
    "sg:province":"Navarra",
    "wof:name":"Barrueco Pazos Martina",
    "wof:placetype":"venue"
},
  "geometry": {"coordinates":[-2.0284268856,42.670501709],"type":"Point"}
}