{
  "type": "Feature",
  "properties": {
    "iso:country":"ES",
    "sg:address":"Av Doctor Vilaseca, 24",
    "sg:city":"Reus",
    "sg:orig_category":"Peluqueros: De Se\u00d1oras",
    "sg:phone":"+34 977 31 76 07",
    "sg:postcode":"43202",
    "sg:province":"Tarragona",
    "wof:name":"Torres Sanchez Juan Manuel",
    "wof:placetype":"venue"
},
  "geometry": {"coordinates":[1.097211957,41.1566963196],"type":"Point"}
}