{
  "type": "Feature",
  "properties": {
    "addr:full":"Calle de Gravina, 6 Almeria Almer\u00eda 04001",
    "addr:housenumber":"6",
    "addr:postcode":"04001",
    "addr:street":"Calle De Gravina",
    "iso:country":"ES",
    "sg:address":"Calle de Gravina, 6",
    "sg:city":"Almeria",
    "sg:orig_category":"Estancos",
    "sg:phone":"+34 950 24 27 08",
    "sg:postcode":"04001",
    "sg:province":"Almer\u00eda",
    "wof:name":"Andujar Castillo Angel",
    "wof:placetype":"venue"
},
  "geometry": {"coordinates":[-2.4655644894,36.8371963501],"type":"Point"}
}