{
  "type": "Feature",
  "properties": {
    "addr:full":"Ctra Mas Del Jutge, 12 P.i. Masia Del Juez Valencia 46900",
    "addr:housenumber":"12",
    "addr:postcode":"46900",
    "addr:street":"Ctra Mas Del Jutge;P.I. Masia Del Juez",
    "iso:country":"ES",
    "sg:address":"Ctra Mas Del Jutge, 12",
    "sg:city":"P.i. Masia Del Juez",
    "sg:orig_category":"Metales (labores, Pulido)",
    "sg:phone":"+34 961 58 03 09",
    "sg:postcode":"46900",
    "sg:province":"Valencia",
    "wof:name":"Merino Moreno Anselmo",
    "wof:placetype":"venue"
},
  "geometry": {"coordinates":[-0.4623290002,39.441619873],"type":"Point"}
}