{
  "type": "Feature",
  "properties": {
    "addr:full":"Escoles, S/n Vilanova De Segria Lleida 25133",
    "addr:housenumber":"s",
    "addr:postcode":"25133",
    "addr:street":"/ N",
    "iso:country":"ES",
    "sg:address":"Escoles, S/n",
    "sg:city":"Vilanova De Segria",
    "sg:orig_category":"Cooperativas Agr\u00cdcolas",
    "sg:phone":"+34 973 77 71 34",
    "sg:postcode":"25133",
    "sg:province":"Lleida",
    "wof:name":"Coop Del Campo De Traid",
    "wof:placetype":"venue"
},
  "geometry": {"coordinates":[0.617659986,41.7126579285],"type":"Point"}
}