{
  "type": "Feature",
  "properties": {
    "iso:country":"ES",
    "sg:address":"Carrer de Espalter, 28",
    "sg:city":"Sitges",
    "sg:orig_category":"Muebles",
    "sg:phone":"+34 938 94 44 90",
    "sg:postcode":"08870",
    "sg:province":"Barcelona",
    "wof:name":"Callado Moreno Manuel",
    "wof:placetype":"venue"
},
  "geometry": {"coordinates":[1.8062599897,41.2371063232],"type":"Point"}
}