{
  "type": "Feature",
  "properties": {
    "iso:country":"ES",
    "sg:address":"Calle de Obispo San Juan De Rivera, 9",
    "sg:city":"Badajoz",
    "sg:orig_category":"Arquitectos",
    "sg:phone":"+34 924 24 16 15",
    "sg:postcode":"06002",
    "sg:province":"Badajoz",
    "wof:name":"Gomez-coronado Leon Rafael",
    "wof:placetype":"venue"
},
  "geometry": {"coordinates":[-6.9709000587,38.8774337769],"type":"Point"}
}