{
  "type": "Feature",
  "properties": {
    "iso:country":"ES",
    "sg:address":"Calle de San Vicente Martir, 3",
    "sg:city":"Zaragoza",
    "sg:orig_category":"Fabricaci\u00d3n De Peines Y De Accesorios De Peluquer\u00cda",
    "sg:phone":"+34 976 21 07 02",
    "sg:postcode":"50008",
    "sg:province":"Zaragoza",
    "wof:name":"Antonio Fariza S.l.",
    "wof:placetype":"venue"
},
  "geometry": {"coordinates":[-0.8828549981,41.6439590454],"type":"Point"}
}