{
  "type": "Feature",
  "properties": {
    "addr:full":"Calle de Cerecilla, 4 Hervas C\u00e1ceres 10700",
    "addr:housenumber":"4",
    "addr:postcode":"10700",
    "addr:street":"Calle De Cerecilla;Ca\u0301Ceres",
    "iso:country":"ES",
    "sg:address":"Calle de Cerecilla, 4",
    "sg:city":"Hervas",
    "sg:orig_category":"Reposter\u00cdas",
    "sg:phone":"+34 927 47 31 08",
    "sg:postcode":"10700",
    "sg:province":"C\u00e1ceres",
    "wof:name":"Dulces Gayo S.c",
    "wof:placetype":"venue"
},
  "geometry": {"coordinates":[-5.863948822,40.2720451355],"type":"Point"}
}