{
  "type": "Feature",
  "properties": {
    "addr:full":"Ptda Frechinal, S/n Javea Alicante 03730",
    "addr:housenumber":"s",
    "addr:postcode":"03730",
    "addr:street":"Ptda Frechinal;/ N Javea Alicante",
    "iso:country":"ES",
    "sg:address":"Ptda Frechinal, S/n",
    "sg:city":"Javea",
    "sg:orig_category":"Ense\u00d1anza, Formaci\u00d3n Profesional: Aprendizaje",
    "sg:phone":"+34 965 79 17 03",
    "sg:postcode":"03730",
    "sg:province":"Alicante",
    "wof:name":"Generalitat Valenciana",
    "wof:placetype":"venue"
},
  "geometry": {"coordinates":[0.1648869962,38.7874183655],"type":"Point"}
}