{
  "type": "Feature",
  "properties": {
    "addr:full":"Calle de Regocijos, 9 Almeria Almer\u00eda 04003",
    "addr:housenumber":"9",
    "addr:postcode":"04003",
    "addr:street":"Calle De Regocijos",
    "iso:country":"ES",
    "sg:address":"Calle de Regocijos, 9",
    "sg:city":"Almeria",
    "sg:orig_category":"Ingeniero",
    "sg:phone":"+34 950 25 32 76",
    "sg:postcode":"04003",
    "sg:province":"Almer\u00eda",
    "wof:name":"Cruz Martinez Jose Diego",
    "wof:placetype":"venue"
},
  "geometry": {"coordinates":[-2.4646639824,36.8422012329],"type":"Point"}
}