{
  "type": "Feature",
  "properties": {
    "iso:country":"ES",
    "sg:address":"Calle de Merced La, 27",
    "sg:city":"Gijon",
    "sg:orig_category":"Promotores Constructores",
    "sg:phone":"+34 985 34 53 02",
    "sg:postcode":"33201",
    "sg:province":"Asturias",
    "wof:name":"Construcciones Unifamiliares S.a.",
    "wof:placetype":"venue"
},
  "geometry": {"coordinates":[-5.662211895,43.5419578552],"type":"Point"}
}