{
  "type": "Feature",
  "properties": {
    "addr:full":"Avda Terminal De Autobuses, 3 Osorno Palencia 34460",
    "addr:postcode":"34460",
    "addr:street":"Avda Terminal",
    "iso:country":"ES",
    "sg:address":"Avda Terminal De Autobuses, 3",
    "sg:city":"Osorno",
    "sg:orig_category":"Empresas De Demolici\u00d3n",
    "sg:phone":"+34 979 15 00 16",
    "sg:postcode":"34460",
    "sg:province":"Palencia",
    "wof:name":"Casta\u00f1eda Martinez Eloy",
    "wof:placetype":"venue"
},
  "geometry": {"coordinates":[-4.361468792,42.4103851318],"type":"Point"}
}