{
  "type": "Feature",
  "properties": {
    "iso:country":"ES",
    "sg:address":"Calle de Huerto, 2",
    "sg:city":"Torrevieja",
    "sg:orig_category":"Pensiones Familiares",
    "sg:phone":"+34 965 71 01 00",
    "sg:postcode":"03180",
    "sg:province":"Alicante",
    "wof:name":"Bernabe Mercader Leandro",
    "wof:placetype":"venue"
},
  "geometry": {"coordinates":[-0.6871299744,37.9773254395],"type":"Point"}
}