{
  "type": "Feature",
  "properties": {
    "addr:full":"Calle de Menendez Pelayo, 4 Valladolid Valladolid 47001",
    "addr:housenumber":"4",
    "addr:postcode":"47001",
    "addr:street":"Calle De Menendez Pelayo",
    "iso:country":"ES",
    "sg:address":"Calle de Menendez Pelayo, 4",
    "sg:city":"Valladolid",
    "sg:orig_category":"Ropa Para Se\u00d1oras (al Por Menor)",
    "sg:phone":"+34 983 34 37 60",
    "sg:postcode":"47001",
    "sg:province":"Valladolid",
    "wof:name":"Reguero Carrillo Aurea",
    "wof:placetype":"venue"
},
  "geometry": {"coordinates":[-4.7276549339,41.6504211426],"type":"Point"}
}