{
  "type": "Feature",
  "properties": {
    "addr:full":"Avda Emilio Castelar, 99 S. Pedro Pinatar Murcia 30740",
    "addr:housenumber":"99",
    "addr:postcode":"30740",
    "addr:street":"Avda Emilio Castelar",
    "iso:country":"ES",
    "sg:address":"Avda Emilio Castelar, 99",
    "sg:city":"S. Pedro Pinatar",
    "sg:orig_category":"Pintores",
    "sg:phone":"+34 968 18 23 69",
    "sg:postcode":"30740",
    "sg:province":"Murcia",
    "wof:name":"Artes Cova Mar Menor S.l.",
    "wof:placetype":"venue"
},
  "geometry": {"coordinates":[-0.7873644233,37.8283615112],"type":"Point"}
}