{
  "type": "Feature",
  "properties": {
    "addr:full":"Carrer de Teixidora (de La), 9 Mataro Barcelona 08302",
    "addr:postcode":"08302",
    "addr:street":"Carrer De Teixidora De La 9 Mataro Barcelona",
    "iso:country":"ES",
    "sg:address":"Carrer de Teixidora (de La), 9",
    "sg:city":"Mataro",
    "sg:orig_category":"Sociedades, Compa\u00d1\u00cdas Aseguradoras",
    "sg:phone":"+34 937 41 48 34",
    "sg:postcode":"08302",
    "sg:province":"Barcelona",
    "wof:name":"Mapfre Automoviles Sociedad Anonima De Seguros Y Reaseguros",
    "wof:placetype":"venue"
},
  "geometry": {"coordinates":[2.4298260212,41.527671814],"type":"Point"}
}