{
  "type": "Feature",
  "properties": {
    "addr:full":"Calle de Cruz De Caravaca, 2 Salamanca Salamanca 37003",
    "addr:housenumber":"2",
    "addr:postcode":"37003",
    "addr:street":"Calle De Cruz De Caravaca",
    "iso:country":"ES",
    "sg:address":"Calle de Cruz De Caravaca, 2",
    "sg:city":"Salamanca",
    "sg:orig_category":"Panader\u00cdas, Panader\u00cdas",
    "sg:phone":"+34 923 25 82 41",
    "sg:postcode":"37003",
    "sg:province":"Salamanca",
    "wof:name":"Tobias Y Joaquin Hernandez Martin C.b.",
    "wof:placetype":"venue"
},
  "geometry": {"coordinates":[-5.6524581909,40.9684066772],"type":"Point"}
}