{
  "type": "Feature",
  "properties": {
    "iso:country":"ES",
    "sg:address":"Union(s J La Vega), S/n",
    "sg:city":"Beniajan",
    "sg:orig_category":"Aluminio Y Aleaciones (producci\u00d3n, Transformaci\u00d3n, Negocio)",
    "sg:phone":"+34 968 82 15 58",
    "sg:postcode":"30570",
    "sg:province":"Murcia",
    "wof:name":"Marin Alcaraz Pedro",
    "wof:placetype":"venue"
},
  "geometry": {"coordinates":[-1.0809240341,37.9681243896],"type":"Point"}
}