{
  "type": "Feature",
  "properties": {
    "addr:full":"Avda Canela (de La), S/n Estepa Sevilla 41560",
    "addr:postcode":"41560",
    "addr:street":"Avda Canela De La S / N;Sevilla",
    "iso:country":"ES",
    "sg:address":"Avda Canela (de La), S/n",
    "sg:city":"Estepa",
    "sg:orig_category":"Agencias Y Agentes Comerciales, Representantes",
    "sg:phone":"+34 955 91 25 11",
    "sg:postcode":"41560",
    "sg:province":"Sevilla",
    "wof:name":"Jimenez Prieto Antonio",
    "wof:placetype":"venue"
},
  "geometry": {"coordinates":[-4.8818941116,37.3000946045],"type":"Point"}
}