{
  "type": "Feature",
  "properties": {
    "iso:country":"ES",
    "sg:address":"Luga Poligono Industrial, 18",
    "sg:city":"Camponaraya",
    "sg:orig_category":"Maquinaria Para Industrias Diversas",
    "sg:phone":"+34 987 45 55 04",
    "sg:postcode":"24410",
    "sg:province":"Le\u00f3n",
    "sg:website":"www.blumaq.es",
    "wof:name":"Blumaq S.a.",
    "wof:placetype":"venue"
},
  "geometry": {"coordinates":[-6.6667189598,42.5784492493],"type":"Point"}
}