{
  "type": "Feature",
  "properties": {
    "iso:country":"ES",
    "sg:address":"Ctra Arta, 137",
    "sg:city":"Platja D'alcudia",
    "sg:orig_category":"Supermercados Y Hipermercados",
    "sg:phone":"+34 971 89 26 26",
    "sg:postcode":"07408",
    "sg:province":"Islas Baleares",
    "wof:name":"Super Devisel Sl",
    "wof:placetype":"venue"
},
  "geometry": {"coordinates":[3.120937109,39.8396034241],"type":"Point"}
}