{
  "type": "Feature",
  "properties": {
    "addr:full":"Calle de Alar, 19 Torreblanca Castell\u00f3n 12596",
    "addr:housenumber":"19",
    "addr:postcode":"12596",
    "addr:street":"Calle De Alar;Castello\u0301N",
    "iso:country":"ES",
    "sg:address":"Calle de Alar, 19",
    "sg:city":"Torreblanca",
    "sg:orig_category":"Molduras, Junquillos, Listones Y Molduras Perforadas",
    "sg:phone":"+34 964 42 01 41",
    "sg:postcode":"12596",
    "sg:province":"Castell\u00f3n",
    "wof:name":"Lorena Soroya S.l.",
    "wof:placetype":"venue"
},
  "geometry": {"coordinates":[0.1955783069,40.221446991],"type":"Point"}
}