{
  "type": "Feature",
  "properties": {
    "iso:country":"ES",
    "sg:address":"Pl Dins (de), 6",
    "sg:city":"Alcoi",
    "sg:orig_category":"Hielo Artificial (fabricaci\u00d3n, Distribuci\u00d3n)",
    "sg:phone":"+34 965 54 51 94",
    "sg:postcode":"03801",
    "sg:province":"Alicante",
    "wof:name":"Helados Y Turrones Artesanos S.l.",
    "wof:placetype":"venue"
},
  "geometry": {"coordinates":[-0.4739370942,38.6979637146],"type":"Point"}
}