{
  "type": "Feature",
  "properties": {
    "iso:country":"ES",
    "sg:address":"Calle de Joaquin Jose Landazuri, 11",
    "sg:city":"Vitoria-gasteiz",
    "sg:orig_category":"Deportes Diversos",
    "sg:phone":"+34 945 14 46 26",
    "sg:postcode":"01008",
    "sg:province":"\u00c1lava",
    "sg:website":"www.fatb.net",
    "wof:name":"Federacion Alavesa De Baloncesto",
    "wof:placetype":"venue"
},
  "geometry": {"coordinates":[-2.6772520542,42.8474845886],"type":"Point"}
}