{
  "type": "Feature",
  "properties": {
    "addr:full":"Calle de Amargura, 3 S. Esteban Gormaz Soria 42330",
    "addr:housenumber":"3",
    "addr:postcode":"42330",
    "addr:street":"Calle De Amargura;S. Esteban Gormaz",
    "iso:country":"ES",
    "sg:address":"Calle de Amargura, 3",
    "sg:city":"S. Esteban Gormaz",
    "sg:orig_category":"Pescader\u00cdas (al Por Menor)",
    "sg:phone":"+34 975 35 00 33",
    "sg:postcode":"42330",
    "sg:province":"Soria",
    "wof:name":"Garcia Hernandez Juan Carlos",
    "wof:placetype":"venue"
},
  "geometry": {"coordinates":[-3.2634313107,41.6219367981],"type":"Point"}
}