{
  "type": "Feature",
  "properties": {
    "iso:country":"ES",
    "sg:address":"Calle de Socuellamos, 6",
    "sg:city":"Campo Criptana",
    "sg:orig_category":"Venta, Instalaci\u00d3n De Calefacci\u00d3n",
    "sg:phone":"+34 926 56 27 62",
    "sg:postcode":"13610",
    "sg:province":"Ciudad Real",
    "wof:name":"Cruz Perez Enrique",
    "wof:placetype":"venue"
},
  "geometry": {"coordinates":[-3.119122982,39.4004440308],"type":"Point"}
}