{
  "type": "Feature",
  "properties": {
    "addr:full":"Calle de Concepcion Bahamonde, 9 Madrid Madrid 28028",
    "addr:housenumber":"9",
    "addr:postcode":"madrid;28028",
    "addr:street":"Calle De Concepcion Bahamonde",
    "iso:country":"ES",
    "sg:address":"Calle de Concepcion Bahamonde, 9",
    "sg:city":"Madrid",
    "sg:orig_category":"Deportes Diversos",
    "sg:phone":"+34 915 42 83 84",
    "sg:postcode":"28028",
    "sg:province":"Madrid",
    "wof:name":"Federacion Espanola De Badminton",
    "wof:placetype":"venue"
},
  "geometry": {"coordinates":[-3.6660768986,40.426651001],"type":"Point"}
}