{
  "type": "Feature",
  "properties": {
    "iso:country":"ES",
    "sg:address":"Carrer de Dante Alighieri, 77",
    "sg:city":"Barcelona",
    "sg:orig_category":"Loter\u00cda Y T\u00d3mbola",
    "sg:phone":"+34 933 57 24 48",
    "sg:postcode":"08032",
    "sg:province":"Barcelona",
    "wof:name":"Maldonado Moline Salvador",
    "wof:placetype":"venue"
},
  "geometry": {"coordinates":[2.1577019691,41.4275016785],"type":"Point"}
}