{
  "type": "Feature",
  "properties": {
    "iso:country":"ES",
    "sg:address":"Carrer de Mallorca, 61",
    "sg:city":"Mas Rampinyo",
    "sg:orig_category":"Molduras, Junquillos, Listones Y Molduras Perforadas",
    "sg:phone":"+34 935 64 66 61",
    "sg:postcode":"08110",
    "sg:province":"Barcelona",
    "wof:name":"Arribas Garcia Angeles",
    "wof:placetype":"venue"
},
  "geometry": {"coordinates":[2.1863546371,41.4937477112],"type":"Point"}
}