{
  "type": "Feature",
  "properties": {
    "addr:full":"Pase Extremadura, 162 Monesterio Badajoz 06260",
    "addr:postcode":"06260",
    "addr:street":"Extremadura",
    "iso:country":"ES",
    "sg:address":"Pase Extremadura, 162",
    "sg:city":"Monesterio",
    "sg:classifiers":[
        {
            "category":"Taxi",
            "type":"Transportation"
        }
    ],
    "sg:phone":"+34 924 51 61 53",
    "sg:postcode":"06260",
    "sg:province":"Badajoz",
    "wof:name":"Sayago Iglesias Isidoro",
    "wof:placetype":"venue"
},
  "geometry": {"coordinates":[-6.2729921341,38.0889129639],"type":"Point"}
}