{
  "type": "Feature",
  "properties": {
    "addr:full":"Calle de Diputacion Provincial, 2 Chelva Valencia 46176",
    "addr:postcode":"46176",
    "addr:street":"Calle De Diputacion Provincial 2",
    "iso:country":"ES",
    "sg:address":"Calle de Diputacion Provincial, 2",
    "sg:city":"Chelva",
    "sg:orig_category":"Pirotecnia (espect\u00c1culos)",
    "sg:phone":"+34 962 10 05 88",
    "sg:postcode":"46176",
    "sg:province":"Valencia",
    "wof:name":"Pirotecnia El Gato Sl",
    "wof:placetype":"venue"
},
  "geometry": {"coordinates":[-0.9953837991,39.7502365112],"type":"Point"}
}