{
  "type": "Feature",
  "properties": {
    "addr:full":"Plaz Alameda De (la), 3 Coin M\u00e1laga 29100",
    "addr:housenumber":"3",
    "addr:postcode":"29100",
    "addr:street":"Alameda De La;Ma\u0301Laga",
    "iso:country":"ES",
    "sg:address":"Plaz Alameda De (la), 3",
    "sg:city":"Coin",
    "sg:orig_category":"Peluqueros: De Se\u00d1oras",
    "sg:phone":"+34 952 45 09 06",
    "sg:postcode":"29100",
    "sg:province":"M\u00e1laga",
    "wof:name":"Lopez Diaz Fuensanta",
    "wof:placetype":"venue"
},
  "geometry": {"coordinates":[-4.7601947784,36.6586380005],"type":"Point"}
}