{
  "type": "Feature",
  "properties": {
    "iso:country":"ES",
    "sg:address":"G.v. Corts Catalanes, 392",
    "sg:city":"Barcelona",
    "sg:orig_category":"Inform\u00c1tica (estudios, Servicios, Asesor\u00cda, Formaci\u00d3n)",
    "sg:phone":"+34 932 89 21 76",
    "sg:postcode":"08015",
    "sg:province":"Barcelona",
    "sg:website":"www.intersoft-business.com",
    "wof:name":"Intersoft Business S.l.",
    "wof:placetype":"venue"
},
  "geometry": {"coordinates":[2.1510090828,41.3760871887],"type":"Point"}
}