{
  "type": "Feature",
  "properties": {
    "iso:country":"ES",
    "sg:address":"Requeixo, S/n",
    "sg:city":"Requeixo",
    "sg:orig_category":"Caf\u00c9s (al Por Menor)",
    "sg:phone":"+34 986 64 20 24",
    "sg:postcode":"36867",
    "sg:province":"Pontevedra",
    "wof:name":"Distribuciones Moroy S.l.",
    "wof:placetype":"venue"
},
  "geometry": {"coordinates":[-8.5354852676,42.1620445251],"type":"Point"}
}