{
  "type": "Feature",
  "properties": {
    "iso:country":"ES",
    "sg:address":"Calle de Dionisio Guardiola, 25",
    "sg:city":"Albacete",
    "sg:orig_category":"Agentes Generales De Seguros",
    "sg:phone":"+34 967 22 70 26",
    "sg:postcode":"02003",
    "sg:province":"Albacete",
    "wof:name":"Moya Quintanilla Maria Del Pilar",
    "wof:placetype":"venue"
},
  "geometry": {"coordinates":[-1.8573774099,38.9919204712],"type":"Point"}
}