{
  "type": "Feature",
  "properties": {
    "addr:full":"Calle de Rua, 7 Le\u00f3n Le\u00f3n 24003",
    "addr:postcode":"24003",
    "addr:street":"Calle De Rua 7 Leo\u0301N Leo\u0301N",
    "iso:country":"ES",
    "sg:address":"Calle de Rua, 7",
    "sg:city":"Le\u00f3n",
    "sg:orig_category":"Armas Y Municiones (fabricaci\u00d3n, Al Por Mayor)",
    "sg:phone":"+34 987 25 70 20",
    "sg:postcode":"24003",
    "sg:province":"Le\u00f3n",
    "wof:name":"Castro Martinez Maria Del Carmen",
    "wof:placetype":"venue"
},
  "geometry": {"coordinates":[-5.5698962212,42.5977325439],"type":"Point"}
}