{
  "type": "Feature",
  "properties": {
    "iso:country":"ES",
    "sg:address":"Pg Pau Claris, 51",
    "sg:city":"Rubi",
    "sg:orig_category":"Madera Para Construcci\u00d3n E Industria",
    "sg:phone":"+34 935 86 10 17",
    "sg:postcode":"08191",
    "sg:province":"Barcelona",
    "wof:name":"Cuinapark S.m.r. S.l.",
    "wof:placetype":"venue"
},
  "geometry": {"coordinates":[2.0308389664,41.4958724976],"type":"Point"}
}