{
  "type": "Feature",
  "properties": {
    "addr:full":"Rond General Mitre, 95 Barcelona Barcelona 08022",
    "addr:housenumber":"95",
    "addr:postcode":"08022",
    "iso:country":"ES",
    "sg:address":"Rond General Mitre, 95",
    "sg:city":"Barcelona",
    "sg:orig_category":"M\u00c9dicos: Neurocirug\u00cda",
    "sg:phone":"+34 932 11 89 91",
    "sg:postcode":"08022",
    "sg:province":"Barcelona",
    "sg:website":"www.neurogroup.es",
    "wof:name":"Neurogrup Sl",
    "wof:placetype":"venue"
},
  "geometry": {"coordinates":[2.1343710423,41.3997879028],"type":"Point"}
}