{
  "type": "Feature",
  "properties": {
    "addr:full":"Calle de Eolo, 3 Chiclana De La Frontera C\u00e1diz 11130",
    "addr:housenumber":"3",
    "addr:postcode":"11130",
    "addr:street":"Calle De Eolo",
    "iso:country":"ES",
    "sg:address":"Calle de Eolo, 3",
    "sg:city":"Chiclana De La Frontera",
    "sg:orig_category":"Inmobiliaria (agencias)",
    "sg:phone":"+34 956 53 29 39",
    "sg:postcode":"11130",
    "sg:province":"C\u00e1diz",
    "wof:name":"Gestion Inmobiliaria La Salina S.l.",
    "wof:placetype":"venue"
},
  "geometry": {"coordinates":[-6.1653490067,36.4077911377],"type":"Point"}
}