{
  "type": "Feature",
  "properties": {
    "addr:full":"Carrer de Sant Jeroni, 9 Lloret Mar Girona 17310",
    "addr:housenumber":"9",
    "addr:postcode":"17310",
    "addr:street":"Carrer De Sant Jeroni",
    "iso:country":"ES",
    "sg:address":"Carrer de Sant Jeroni, 9",
    "sg:city":"Lloret Mar",
    "sg:orig_category":"Molduras, Junquillos, Listones Y Molduras Perforadas",
    "sg:phone":"+34 972 36 11 15",
    "sg:postcode":"17310",
    "sg:province":"Girona",
    "wof:name":"Mordoh  Alberto",
    "wof:placetype":"venue"
},
  "geometry": {"coordinates":[2.846834898,41.6981697083],"type":"Point"}
}