{
  "type": "Feature",
  "properties": {
    "iso:country":"ES",
    "sg:address":"Edif Espigon, 1",
    "sg:city":"Isla Moral",
    "sg:orig_category":"Centros Empresariales",
    "sg:phone":"+34 959 47 90 89",
    "sg:postcode":"21409",
    "sg:province":"Huelva",
    "wof:name":"Lopez Espinar Juan",
    "wof:placetype":"venue"
},
  "geometry": {"coordinates":[-7.3418722153,37.1882247925],"type":"Point"}
}