{
  "type": "Feature",
  "properties": {
    "addr:full":"Ctra Canovelles, 21 Granollers Barcelona 08403",
    "addr:housenumber":"21",
    "addr:postcode":"08403",
    "addr:street":"Ctra Canovelles",
    "iso:country":"ES",
    "sg:address":"Ctra Canovelles, 21",
    "sg:city":"Granollers",
    "sg:orig_category":"Artes Gr\u00c1ficas, Artes Pl\u00c1sticas (curso)",
    "sg:phone":"+34 938 40 13 83",
    "sg:postcode":"08403",
    "sg:province":"Barcelona",
    "wof:name":"Sola Medina Diego",
    "wof:placetype":"venue"
},
  "geometry": {"coordinates":[2.2768878937,41.6138763428],"type":"Point"}
}