{
  "type": "Feature",
  "properties": {
    "iso:country":"ES",
    "sg:address":"Plaz Mayor, 19",
    "sg:city":"Bembibre",
    "sg:orig_category":"Librer\u00cdas",
    "sg:phone":"+34 987 51 29 82",
    "sg:postcode":"24300",
    "sg:province":"Le\u00f3n",
    "wof:name":"Libreria Cobos C.b.",
    "wof:placetype":"venue"
},
  "geometry": {"coordinates":[-6.4167990685,42.614944458],"type":"Point"}
}