{
  "type": "Feature",
  "properties": {
    "addr:full":"Calle de Toledo, 83 Madrid Madrid 28005",
    "addr:housenumber":"83",
    "addr:postcode":"madrid;28005",
    "addr:street":"Calle De Toledo",
    "iso:country":"ES",
    "sg:address":"Calle de Toledo, 83",
    "sg:city":"Madrid",
    "sg:orig_category":"Inform\u00c1tica, Ofim\u00c1tica (estudios, Asesor\u00cda, Ingenier\u00cda, Formaci\u00d3n)",
    "sg:phone":"+34 913 65 40 69",
    "sg:postcode":"28005",
    "sg:province":"Madrid",
    "sg:website":"www.expocom.es",
    "wof:name":"Expocom Madrid S.l.",
    "wof:placetype":"venue"
},
  "geometry": {"coordinates":[-3.7093360424,40.4099845886],"type":"Point"}
}