{
  "type": "Feature",
  "properties": {
    "iso:country":"ES",
    "sg:address":"Carrer de Joaquim Sorolla, 45",
    "sg:city":"Sabadell",
    "sg:orig_category":"Alimentaci\u00d3n General (al Por Mayor)",
    "sg:phone":"+34 937 25 46 94",
    "sg:postcode":"08206",
    "sg:province":"Barcelona",
    "wof:name":"Comercial Grillo S.l.",
    "wof:placetype":"venue"
},
  "geometry": {"coordinates":[2.0869719982,41.5498161316],"type":"Point"}
}