{
  "type": "Feature",
  "properties": {
    "addr:full":"Carrer de Roser, 13 Barcelona Barcelona 08004",
    "addr:housenumber":"13",
    "addr:postcode":"08004",
    "addr:street":"Carrer De Roser",
    "iso:country":"ES",
    "sg:address":"Carrer de Roser, 13",
    "sg:city":"Barcelona",
    "sg:orig_category":"Ropa Para Ni\u00d1os (al Por Menor)",
    "sg:phone":"+34 934 41 70 53",
    "sg:postcode":"08004",
    "sg:province":"Barcelona",
    "wof:name":"Ferran Anto\u00f1ana Antonia",
    "wof:placetype":"venue"
},
  "geometry": {"coordinates":[2.1672320366,41.3739585876],"type":"Point"}
}