{
  "type": "Feature",
  "properties": {
    "addr:full":"Praz Anxo Fernandez Gomez, 5 Lugo Lugo 27001",
    "addr:housenumber":"5",
    "addr:postcode":"27001",
    "addr:street":"Praz Anxo Fernandez Gomez",
    "iso:country":"ES",
    "sg:address":"Praz Anxo Fernandez Gomez, 5",
    "sg:city":"Lugo",
    "sg:orig_category":"Confecci\u00d3n (fabricaci\u00d3n, Al Por Mayor)",
    "sg:phone":"+34 982 22 75 56",
    "sg:postcode":"27001",
    "sg:province":"Lugo",
    "wof:name":"Alonso Vazquez Manuel Javier",
    "wof:placetype":"venue"
},
  "geometry": {"coordinates":[-7.5558686256,43.0113105774],"type":"Point"}
}