{
  "type": "Feature",
  "properties": {
    "iso:country":"ES",
    "sg:address":"Calle de Valdivia, 5",
    "sg:city":"Villanueva Serena",
    "sg:orig_category":"Talleres: Ropa A Medida",
    "sg:phone":"+34 924 84 06 30",
    "sg:postcode":"06700",
    "sg:province":"Badajoz",
    "wof:name":"Diaz Nieto Antonio",
    "wof:placetype":"venue"
},
  "geometry": {"coordinates":[-5.7940292358,38.976108551],"type":"Point"}
}