{
  "type": "Feature",
  "properties": {
    "iso:country":"ES",
    "sg:address":"Avda Iparragirre, 70",
    "sg:city":"Elexalde",
    "sg:orig_category":"Bazares, Art\u00cdculos De Limpieza Y De Cocina (al Por Menor)",
    "sg:phone":"+34 944 80 17 96",
    "sg:postcode":"48940",
    "sg:province":"Vizcaya",
    "wof:name":"Rodriguez Gutierrez Bego\u00f1a",
    "wof:placetype":"venue"
},
  "geometry": {"coordinates":[-2.9866020679,43.3250541687],"type":"Point"}
}