{
  "type": "Feature",
  "properties": {
    "addr:full":"Calle de Santa Gema, 27 Quintanar Orden Toledo 45800",
    "addr:housenumber":"27",
    "addr:postcode":"45800",
    "addr:street":"Calle De Santa Gema",
    "iso:country":"ES",
    "sg:address":"Calle de Santa Gema, 27",
    "sg:city":"Quintanar Orden",
    "sg:orig_category":"Electricidad: Instaladores",
    "sg:phone":"+34 925 18 04 94",
    "sg:postcode":"45800",
    "sg:province":"Toledo",
    "wof:name":"Instalaciones Electricas Victorino Blanco S.l.",
    "wof:placetype":"venue"
},
  "geometry": {"coordinates":[-3.0427720547,39.5979690552],"type":"Point"}
}