{
  "type": "Feature",
  "properties": {
    "addr:full":"Calle de General Serrano Bedoya, 1 Quesada Ja\u00e9n 23480",
    "addr:housenumber":"1",
    "addr:postcode":"23480",
    "addr:street":"Calle De General Serrano Bedoya",
    "iso:country":"ES",
    "sg:address":"Calle de General Serrano Bedoya, 1",
    "sg:city":"Quesada",
    "sg:orig_category":"Restaurantes",
    "sg:phone":"+34 953 73 39 06",
    "sg:postcode":"23480",
    "sg:province":"Ja\u00e9n",
    "wof:name":"Gamez Gamez Luciano",
    "wof:placetype":"venue"
},
  "geometry": {"coordinates":[-3.0705211163,37.8409042358],"type":"Point"}
}