{
  "type": "Feature",
  "properties": {
    "iso:country":"ES",
    "sg:address":"Bidekurutzeta Kalea, 3",
    "sg:city":"Bergara",
    "sg:orig_category":"Asociaciones Y Clubs Deportivos",
    "sg:phone":"+34 943 76 70 51",
    "sg:postcode":"20570",
    "sg:province":"Guip\u00f9zcoa",
    "wof:name":"Club Deportivo Bergara",
    "wof:placetype":"venue"
},
  "geometry": {"coordinates":[-2.4133999348,43.1168861389],"type":"Point"}
}