{
  "type": "Feature",
  "properties": {
    "addr:full":"Av Meridiana, 564 Barcelona Barcelona 08030",
    "addr:housenumber":"564",
    "addr:postcode":"08030",
    "addr:street":"Meridiana",
    "iso:country":"ES",
    "sg:address":"Av Meridiana, 564",
    "sg:city":"Barcelona",
    "sg:orig_category":"Relojer\u00cda (al Por Menor, Reparaci\u00d3n)",
    "sg:phone":"+34 932 74 10 85",
    "sg:postcode":"08030",
    "sg:province":"Barcelona",
    "wof:name":"Enjuanes Fajarnes Mario",
    "wof:placetype":"venue"
},
  "geometry": {"coordinates":[2.186578989,41.4415626526],"type":"Point"}
}