{
  "type": "Feature",
  "properties": {
    "addr:full":"Calle de Valentu\u00d1ana, 5 Marbella M\u00e1laga 29600",
    "addr:housenumber":"5",
    "addr:postcode":"29600",
    "addr:street":"Calle De Valentun\u0303Ana;Ma\u0301Laga",
    "iso:country":"ES",
    "sg:address":"Calle de Valentu\u00d1ana, 5",
    "sg:city":"Marbella",
    "sg:orig_category":"Edici\u00d3n De Diarios, Revistas, Boletines",
    "sg:phone":"+34 952 92 40 86",
    "sg:postcode":"29600",
    "sg:province":"M\u00e1laga",
    "wof:name":"Athena Ediciones S.l",
    "wof:placetype":"venue"
},
  "geometry": {"coordinates":[-4.8883376122,36.5112686157],"type":"Point"}
}