{
  "type": "Feature",
  "properties": {
    "iso:country":"ES",
    "sg:address":"Trva Severo Ochoa, 5",
    "sg:city":"Parla",
    "sg:orig_category":"Asesor\u00cda Sobre Comunicaci\u00d3n De Empresas",
    "sg:phone":"+34 916 05 57 33",
    "sg:postcode":"28980",
    "sg:province":"Madrid",
    "wof:name":"Eadais Gestora Construccion S.l.",
    "wof:placetype":"venue"
},
  "geometry": {"coordinates":[-3.7728660107,40.2361907959],"type":"Point"}
}