{
  "type": "Feature",
  "properties": {
    "iso:country":"ES",
    "sg:address":"Calle de Monasterio De Poblet, 27",
    "sg:city":"Zaragoza",
    "sg:orig_category":"Reposter\u00cdas",
    "sg:phone":"+34 976 49 58 54",
    "sg:postcode":"50013",
    "sg:province":"Zaragoza",
    "wof:name":"Romero Serrano Paloma",
    "wof:placetype":"venue"
},
  "geometry": {"coordinates":[-0.8691380024,41.6419219971],"type":"Point"}
}