{
  "type": "Feature",
  "properties": {
    "addr:full":"Avda Astorga, 10 Ponferrada Le\u00f3n 24400",
    "addr:housenumber":"10",
    "addr:postcode":"24400",
    "addr:street":"Avda Astorga",
    "iso:country":"ES",
    "sg:address":"Avda Astorga, 10",
    "sg:city":"Ponferrada",
    "sg:orig_category":"Molduras, Junquillos, Listones Y Molduras Perforadas",
    "sg:phone":"+34 987 42 89 47",
    "sg:postcode":"24400",
    "sg:province":"Le\u00f3n",
    "wof:name":"Alfayete Alvarez Roberto",
    "wof:placetype":"venue"
},
  "geometry": {"coordinates":[-6.5823168755,42.5497436523],"type":"Point"}
}