{
  "type": "Feature",
  "properties": {
    "addr:full":"Carrer de Lugo, 11 Barcelona Barcelona 08032",
    "addr:housenumber":"11",
    "addr:postcode":"08032",
    "addr:street":"Carrer De Lugo",
    "iso:country":"ES",
    "sg:address":"Carrer de Lugo, 11",
    "sg:city":"Barcelona",
    "sg:orig_category":"Prot\u00c9sicos Dentales",
    "sg:phone":"+34 934 29 49 01",
    "sg:postcode":"08032",
    "sg:province":"Barcelona",
    "wof:name":"Cantador Cantarero Manuel",
    "wof:placetype":"venue"
},
  "geometry": {"coordinates":[2.1576209068,41.4238204956],"type":"Point"}
}