{
  "type": "Feature",
  "properties": {
    "addr:full":"Avda Carlos De Haya, 188 Malaga M\u00e1laga 29010",
    "addr:housenumber":"188",
    "addr:postcode":"29010",
    "addr:street":"Avda Carlos De Haya;Ma\u0301Laga",
    "iso:country":"ES",
    "sg:address":"Avda Carlos De Haya, 188",
    "sg:city":"Malaga",
    "sg:orig_category":"Estudios, Instalaci\u00d3n De Climatizaci\u00d3n",
    "sg:phone":"+34 952 39 95 18",
    "sg:postcode":"29010",
    "sg:province":"M\u00e1laga",
    "sg:website":"garridojs@eresmas.com",
    "wof:name":"J.garrido Refrigeracion S.l.",
    "wof:placetype":"venue"
},
  "geometry": {"coordinates":[-4.4512014389,36.7228240967],"type":"Point"}
}