{
  "type": "Feature",
  "properties": {
    "iso:country":"ES",
    "sg:address":"Cm\u00d1o Baltar, S/n",
    "sg:city":"Sanxenxo",
    "sg:orig_category":"Ense\u00d1anza Secundaria: Colegios Y Escuelas Privadas",
    "sg:phone":"+34 986 72 41 08",
    "sg:postcode":"36960",
    "sg:province":"Pontevedra",
    "wof:name":"Instituto Ensino Secundario De Sanxenxo",
    "wof:placetype":"venue"
},
  "geometry": {"coordinates":[-8.8059329987,42.4015274048],"type":"Point"}
}