{
  "type": "Feature",
  "properties": {
    "iso:country":"ES",
    "sg:address":"Calle de Nueva, 40",
    "sg:city":"Motril",
    "sg:orig_category":"M\u00c9dicos: Oftalmolog\u00cda",
    "sg:phone":"+34 958 82 48 66",
    "sg:postcode":"18600",
    "sg:province":"Granada",
    "wof:name":"Palomares Fernandez Juan Manuel",
    "wof:placetype":"venue"
},
  "geometry": {"coordinates":[-3.5179433823,36.7471580505],"type":"Point"}
}