{
  "type": "Feature",
  "properties": {
    "addr:full":"Cno. Polvoranca, 11 Leganes Madrid 28914",
    "addr:housenumber":"11",
    "addr:postcode":"28914",
    "addr:street":"Cno. Polvoranca",
    "iso:country":"ES",
    "sg:address":"Cno. Polvoranca, 11",
    "sg:city":"Leganes",
    "sg:orig_category":"Armarios Y Cuadros El\u00c9ctricos",
    "sg:phone":"+34 916 94 58 31",
    "sg:postcode":"28914",
    "sg:province":"Madrid",
    "wof:name":"Martin Se\u00f1or Carlos Javier",
    "wof:placetype":"venue"
},
  "geometry": {"coordinates":[-3.7763791084,40.3261413574],"type":"Point"}
}