{
  "type": "Feature",
  "properties": {
    "iso:country":"ES",
    "sg:address":"Bizkaia Kalea, 6",
    "sg:city":"Zarautz",
    "sg:orig_category":"Centros Empresariales",
    "sg:phone":"+34 943 83 43 28",
    "sg:postcode":"20800",
    "sg:province":"Guip\u00f9zcoa",
    "wof:name":"3efe Estudio Empresarial Sl",
    "wof:placetype":"venue"
},
  "geometry": {"coordinates":[-2.176295,43.283558],"type":"Point"}
}