{
  "type": "Feature",
  "properties": {
    "iso:country":"ES",
    "sg:address":"Calle de Leon Leal, 1",
    "sg:city":"Caceres",
    "sg:orig_category":"Abogados",
    "sg:phone":"+34 927 62 66 38",
    "sg:postcode":"10002",
    "sg:province":"C\u00e1ceres",
    "wof:name":"Exposito Rubio Juan Maria",
    "wof:placetype":"venue"
},
  "geometry": {"coordinates":[-6.375330925,39.4696769714],"type":"Point"}
}