{
  "type": "Feature",
  "properties": {
    "addr:full":"Calle de Iparragirre, 3 Gernika-lumo Vizcaya 48300",
    "addr:housenumber":"3",
    "addr:postcode":"48300",
    "addr:street":"Calle De Iparragirre",
    "iso:country":"ES",
    "sg:address":"Calle de Iparragirre, 3",
    "sg:city":"Gernika-lumo",
    "sg:orig_category":"Agentes Generales De Seguros",
    "sg:phone":"+34 946 25 35 90",
    "sg:postcode":"48300",
    "sg:province":"Vizcaya",
    "wof:name":"Humberto Zuazua Agencia De Seguros Sl",
    "wof:placetype":"venue"
},
  "geometry": {"coordinates":[-2.6766779423,43.313709259],"type":"Point"}
}