{
  "type": "Feature",
  "properties": {
    "iso:country":"ES",
    "sg:address":"Avda Sinforiano Madro\u00d1ero, 6",
    "sg:city":"Badajoz",
    "sg:orig_category":"M\u00c9dicos: Dermatolog\u00cda Y Venereolog\u00cda",
    "sg:phone":"+34 924 26 23 28",
    "sg:postcode":"06011",
    "sg:province":"Badajoz",
    "wof:name":"Gaderex S.l.",
    "wof:placetype":"venue"
},
  "geometry": {"coordinates":[-6.989511013,38.8711776733],"type":"Point"}
}