{
  "type": "Feature",
  "properties": {
    "addr:full":"Avda Extremadura, 39 Velada Toledo 45612",
    "addr:housenumber":"39",
    "addr:postcode":"45612",
    "addr:street":"Avda Extremadura",
    "iso:country":"ES",
    "sg:address":"Avda Extremadura, 39",
    "sg:city":"Velada",
    "sg:orig_category":"Electromec\u00c1nica",
    "sg:phone":"+34 925 89 24 74",
    "sg:postcode":"45612",
    "sg:province":"Toledo",
    "wof:name":"Delgado Pulido Javier",
    "wof:placetype":"venue"
},
  "geometry": {"coordinates":[-4.972304821,39.9785308838],"type":"Point"}
}