{
  "type": "Feature",
  "properties": {
    "addr:full":"Calle de Dec. Higueras Del Castillo, 54 Torremolinos M\u00e1laga 29620",
    "addr:housenumber":"54",
    "addr:postcode":"29620",
    "addr:street":"Calle De;Castillo;Ma\u0301Laga",
    "iso:country":"ES",
    "sg:address":"Calle de Dec. Higueras Del Castillo, 54",
    "sg:city":"Torremolinos",
    "sg:orig_category":"Peluquer\u00cdas, Peluquer\u00cda Mixta",
    "sg:phone":"+34 952 37 53 36",
    "sg:postcode":"29620",
    "sg:province":"M\u00e1laga",
    "wof:name":"Palomo Carmona Rafael",
    "wof:placetype":"venue"
},
  "geometry": {"coordinates":[-4.5160393715,36.6265563965],"type":"Point"}
}