{
  "type": "Feature",
  "properties": {
    "iso:country":"ES",
    "sg:address":"Calle de Santa Elena, 18",
    "sg:city":"Ba\u00d1eza",
    "sg:orig_category":"Empresas De Carpinter\u00cda Met\u00c1lica",
    "sg:phone":"+34 987 64 31 34",
    "sg:postcode":"24750",
    "sg:province":"Le\u00f3n",
    "wof:name":"Panero Gonzalez Francisco Javier",
    "wof:placetype":"venue"
},
  "geometry": {"coordinates":[-5.8916540146,42.2885437012],"type":"Point"}
}