{
  "type": "Feature",
  "properties": {
    "addr:full":"Carrer de Illes Canaries, 103 Pineda Mar Barcelona 08397",
    "addr:housenumber":"103",
    "addr:postcode":"08397",
    "addr:street":"Carrer De Illes Canaries;Barcelona",
    "iso:country":"ES",
    "sg:address":"Carrer de Illes Canaries, 103",
    "sg:city":"Pineda Mar",
    "sg:orig_category":"Inmobiliaria (agencias)",
    "sg:phone":"+34 937 67 20 12",
    "sg:postcode":"08397",
    "sg:province":"Barcelona",
    "wof:name":"P.g. 6 Can Bel S.l.",
    "wof:placetype":"venue"
},
  "geometry": {"coordinates":[2.6966519356,41.6271629333],"type":"Point"}
}