{
  "type": "Feature",
  "properties": {
    "iso:country":"ES",
    "sg:address":"Calle de Olivo, 35",
    "sg:city":"Puebla Alfinden",
    "sg:orig_category":"Suministros Y Materiales Industriales",
    "sg:phone":"+34 976 10 74 01",
    "sg:postcode":"50171",
    "sg:province":"Zaragoza",
    "wof:name":"Dilarvi S.l.",
    "wof:placetype":"venue"
},
  "geometry": {"coordinates":[-0.7617740035,41.639465332],"type":"Point"}
}