{
  "type": "Feature",
  "properties": {
    "addr:full":"Ctra Caldes, Km. 0032,5 Sentmenat Barcelona 08181",
    "addr:postcode":"08181",
    "addr:street":"Ctra Caldes Km. 0032,5",
    "iso:country":"ES",
    "sg:address":"Ctra Caldes, Km. 0032,5",
    "sg:city":"Sentmenat",
    "sg:orig_category":"Distribuci\u00d3n De Petr\u00d3leo Y Derivados",
    "sg:phone":"+34 937 15 05 57",
    "sg:postcode":"08181",
    "sg:province":"Barcelona",
    "wof:name":"Petrobert Sentmenat S.l.",
    "wof:placetype":"venue"
},
  "geometry": {"coordinates":[2.1349349022,41.6101417542],"type":"Point"}
}