{
  "type": "Feature",
  "properties": {
    "addr:full":"Calle de Hervas Y Buendia, 2 Ciudad Real Ciudad Real 13003",
    "addr:housenumber":"2",
    "addr:postcode":"13003",
    "addr:street":"Calle De Hervas Y Buendia",
    "iso:country":"ES",
    "sg:address":"Calle de Hervas Y Buendia, 2",
    "sg:city":"Ciudad Real",
    "sg:orig_category":"Deportes Diversos",
    "sg:phone":"+34 926 25 28 67",
    "sg:postcode":"13003",
    "sg:province":"Ciudad Real",
    "wof:name":"Club Deportivo Elemental Shotokan Ciudad Rea\u00f1",
    "wof:placetype":"venue"
},
  "geometry": {"coordinates":[-3.9276640415,38.9904327393],"type":"Point"}
}