{
  "type": "Feature",
  "properties": {
    "iso:country":"ES",
    "sg:address":"Rua Vicente Risco, S/n",
    "sg:city":"Ourense",
    "sg:orig_category":"Caf\u00c9s, Bares, Cervecer\u00cdas",
    "sg:phone":"+34 988 21 98 47",
    "sg:postcode":"32001",
    "sg:province":"Ourense",
    "wof:name":"Baamonde Viador Jose Benito",
    "wof:placetype":"venue"
},
  "geometry": {"coordinates":[-7.8661389351,42.3484840393],"type":"Point"}
}