{
  "type": "Feature",
  "properties": {
    "iso:country":"ES",
    "sg:address":"Carrer de Rossello, 227",
    "sg:city":"Barcelona",
    "sg:orig_category":"Compraventa De Antig\u00dcedades",
    "sg:phone":"+34 932 17 56 07",
    "sg:postcode":"08008",
    "sg:province":"Barcelona",
    "sg:website":"www.balclis.com",
    "wof:name":"Sacliba S. A.",
    "wof:placetype":"venue"
},
  "geometry": {"coordinates":[2.1576960087,41.3937835693],"type":"Point"}
}