{
  "type": "Feature",
  "properties": {
    "addr:full":"Carretera Anciles, 12 Anciles Huesca 22469",
    "addr:housenumber":"12",
    "addr:postcode":"22469",
    "addr:street":"Carretera Anciles",
    "iso:country":"ES",
    "sg:address":"Carretera Anciles, 12",
    "sg:city":"Anciles",
    "sg:orig_category":"Ense\u00d1ante, Direcci\u00d3n",
    "sg:phone":"+34 974 55 12 00",
    "sg:postcode":"22469",
    "sg:province":"Huesca",
    "wof:name":"Laguens Sahun Francisco Javier",
    "wof:placetype":"venue"
},
  "geometry": {"coordinates":[0.4906460047,42.5868186951],"type":"Point"}
}