{
  "type": "Feature",
  "properties": {
    "iso:country":"ES",
    "sg:address":"Estd Villaza (de), 8",
    "sg:city":"Pazos",
    "sg:orig_category":"Empresas De Pintura Y Revestimientos",
    "sg:phone":"+34 988 41 16 04",
    "sg:postcode":"32619",
    "sg:province":"Ourense",
    "wof:name":"Padron Crespo Valentin",
    "wof:placetype":"venue"
},
  "geometry": {"coordinates":[-7.4538340569,41.9393615723],"type":"Point"}
}