{
  "type": "Feature",
  "properties": {
    "addr:full":"Pg Maragall, 217 Barcelona Barcelona 08032",
    "addr:housenumber":"217",
    "addr:postcode":"08032",
    "addr:street":"Pg Maragall",
    "iso:country":"ES",
    "sg:address":"Pg Maragall, 217",
    "sg:city":"Barcelona",
    "sg:orig_category":"Confecci\u00d3n (fabricaci\u00d3n, Al Por Mayor)",
    "sg:phone":"+34 934 36 25 47",
    "sg:postcode":"08032",
    "sg:province":"Barcelona",
    "wof:name":"Pi\u00f1ol Heredia Dolores",
    "wof:placetype":"venue"
},
  "geometry": {"coordinates":[2.17614007,41.4253997803],"type":"Point"}
}