{
  "type": "Feature",
  "properties": {
    "addr:full":"Calle de Gabriel De Morales, 1 Melilla Melilla 52002",
    "addr:housenumber":"1",
    "addr:postcode":"52002",
    "addr:street":"Calle De Gabriel De Morales",
    "iso:country":"ES",
    "sg:address":"Calle de Gabriel De Morales, 1",
    "sg:city":"Melilla",
    "sg:orig_category":"Agencias De Viajes",
    "sg:phone":"+34 952 68 25 86",
    "sg:postcode":"52002",
    "sg:province":"Melilla",
    "wof:name":"Carlson Wagonlit S.a.",
    "wof:placetype":"venue"
},
  "geometry": {"coordinates":[-2.9436280727,35.2940940857],"type":"Point"}
}