{
  "type": "Feature",
  "properties": {
    "addr:full":"Plaz Moron, 8 Montehermoso C\u00e1ceres 10810",
    "addr:housenumber":"8",
    "addr:postcode":"10810",
    "addr:street":"Plaz Moron;Ca\u0301Ceres",
    "iso:country":"ES",
    "sg:address":"Plaz Moron, 8",
    "sg:city":"Montehermoso",
    "sg:orig_category":"Ense\u00d1anza, Formaci\u00d3n Profesional: Aprendizaje",
    "sg:phone":"+34 927 67 58 51",
    "sg:postcode":"10810",
    "sg:province":"C\u00e1ceres",
    "wof:name":"Sociedad Del Sagrado Corazon De Jesus Provincia Centro Sur Curia Provincial",
    "wof:placetype":"venue"
},
  "geometry": {"coordinates":[-6.3481211662,40.0888900757],"type":"Point"}
}