{
  "type": "Feature",
  "properties": {
    "addr:full":"Calle de Puerto Del Suspiro, 1 Sevilla Sevilla 41006",
    "addr:housenumber":"1",
    "addr:postcode":"41006",
    "addr:street":"Calle De Puerto Del Suspiro",
    "iso:country":"ES",
    "sg:address":"Calle de Puerto Del Suspiro, 1",
    "sg:city":"Sevilla",
    "sg:orig_category":"Zapatos (al Por Menor)",
    "sg:phone":"+34 954 65 67 56",
    "sg:postcode":"41006",
    "sg:province":"Sevilla",
    "wof:name":"Reig Selles Gerardo",
    "wof:placetype":"venue"
},
  "geometry": {"coordinates":[-5.9537649155,37.3755683899],"type":"Point"}
}