{
  "type": "Feature",
  "properties": {
    "addr:full":"La Pepina, S/n Nueva Andalucia M\u00e1laga 29660",
    "addr:housenumber":"/ n",
    "addr:postcode":"29660",
    "addr:street":"Pepina S;Ma\u0301Laga",
    "iso:country":"ES",
    "sg:address":"La Pepina, S/n",
    "sg:city":"Nueva Andalucia",
    "sg:orig_category":"Promotores Constructores",
    "sg:phone":"+34 952 81 92 81",
    "sg:postcode":"29660",
    "sg:province":"M\u00e1laga",
    "wof:name":"Comunidad De Propietarios El Embrujo De Marbella",
    "wof:placetype":"venue"
},
  "geometry": {"coordinates":[-4.9572491646,36.4902381897],"type":"Point"}
}