{
  "type": "Feature",
  "properties": {
    "addr:full":"Calle de Beato Florentino.obispo, 3 Barbastro Huesca 22300",
    "addr:housenumber":"3",
    "addr:postcode":"22300",
    "addr:street":"Calle De Beato Florentino.Obispo",
    "iso:country":"ES",
    "sg:address":"Calle de Beato Florentino.obispo, 3",
    "sg:city":"Barbastro",
    "sg:orig_category":"Plomeros",
    "sg:phone":"+34 974 31 44 45",
    "sg:postcode":"22300",
    "sg:province":"Huesca",
    "wof:name":"Arroyos Pallas Antonio",
    "wof:placetype":"venue"
},
  "geometry": {"coordinates":[0.1215535998,42.0329856873],"type":"Point"}
}