{
  "type": "Feature",
  "properties": {
    "iso:country":"ES",
    "sg:address":"Calle de Arroyo Belincoso, 40",
    "sg:city":"Madrid",
    "sg:orig_category":"Frutas, Legumbres Frescas Y Tempranas (al Por Menor)",
    "sg:phone":"+34 914 37 09 23",
    "sg:postcode":"28030",
    "sg:province":"Madrid",
    "wof:name":"De La Rosa Ruiz Francisco",
    "wof:placetype":"venue"
},
  "geometry": {"coordinates":[-3.6522927284,40.4106712341],"type":"Point"}
}