{
  "type": "Feature",
  "properties": {
    "addr:full":"Poli Congost (el), S/n Montornes Nord Barcelona 08170",
    "addr:postcode":"08170",
    "addr:street":"El S / N Montornes Nord Barcelona",
    "iso:country":"ES",
    "sg:address":"Poli Congost (el), S/n",
    "sg:city":"Montornes Nord",
    "sg:orig_category":"V\u00c1lvulas",
    "sg:phone":"+34 938 60 80 00",
    "sg:postcode":"08170",
    "sg:province":"Barcelona",
    "wof:name":"Productos Eaton Livia S.l.",
    "wof:placetype":"venue"
},
  "geometry": {"coordinates":[2.260299921,41.5587806702],"type":"Point"}
}