{
  "type": "Feature",
  "properties": {
    "addr:full":"Calle de Paso Nivel, 1 Portal C\u00e1diz 11596",
    "addr:housenumber":"nivel 1",
    "addr:postcode":"11596",
    "addr:street":"Calle De Paso",
    "iso:country":"ES",
    "sg:address":"Calle de Paso Nivel, 1",
    "sg:city":"Portal",
    "sg:orig_category":"Estudios, Instalaci\u00d3n De Climatizaci\u00d3n",
    "sg:phone":"+34 956 14 55 33",
    "sg:postcode":"11596",
    "sg:province":"C\u00e1diz",
    "wof:name":"Frialbasur Sl",
    "wof:placetype":"venue"
},
  "geometry": {"coordinates":[-6.1277089119,36.6511650085],"type":"Point"}
}