{
  "type": "Feature",
  "properties": {
    "addr:full":"Avda Constitucion, 43 Monroy C\u00e1ceres 10194",
    "addr:housenumber":"43",
    "addr:postcode":"10194",
    "addr:street":"Avda Constitucion;Ca\u0301Ceres",
    "iso:country":"ES",
    "sg:address":"Avda Constitucion, 43",
    "sg:city":"Monroy",
    "sg:orig_category":"Alquiler De Casas Y Habitaciones Amuebladas",
    "sg:phone":"+34 927 28 01 17",
    "sg:postcode":"10194",
    "sg:province":"C\u00e1ceres",
    "wof:name":"Martin Duran Maria Teresa",
    "wof:placetype":"venue"
},
  "geometry": {"coordinates":[-6.2084097862,39.6367797852],"type":"Point"}
}