{
  "type": "Feature",
  "properties": {
    "addr:full":"Av Marina Baixa, 20 Alfas Pi Alicante 03580",
    "addr:housenumber":"20",
    "addr:postcode":"03580",
    "addr:street":"Av Marina Baixa",
    "iso:country":"ES",
    "sg:address":"Av Marina Baixa, 20",
    "sg:city":"Alfas Pi",
    "sg:orig_category":"Panader\u00cdas, Panader\u00cdas",
    "sg:phone":"+34 965 88 86 74",
    "sg:postcode":"03580",
    "sg:province":"Alicante",
    "wof:name":"Compa\u00f1 Ferrer Esperanza",
    "wof:placetype":"venue"
},
  "geometry": {"coordinates":[-0.0998329967,38.5782012939],"type":"Point"}
}