{
  "type": "Feature",
  "properties": {
    "iso:country":"ES",
    "sg:address":"Calle de Nicaragua, S/n",
    "sg:city":"Alcantarilla",
    "sg:orig_category":"Quincaller\u00cda (al Por Menor)",
    "sg:phone":"+34 968 89 38 24",
    "sg:postcode":"30820",
    "sg:province":"Murcia",
    "wof:name":"Herrajes Alicante S.l.",
    "wof:placetype":"venue"
},
  "geometry": {"coordinates":[-1.1948139668,37.9567604065],"type":"Point"}
}