{
  "type": "Feature",
  "properties": {
    "addr:full":"Carrer de Galanes, 19 Reus Tarragona 43201",
    "addr:housenumber":"19",
    "addr:postcode":"43201",
    "addr:street":"Carrer De Galanes",
    "iso:country":"ES",
    "sg:address":"Carrer de Galanes, 19",
    "sg:city":"Reus",
    "sg:orig_category":"Art\u00cdculos De Regalo (al Por Menor)",
    "sg:phone":"+34 977 34 04 15",
    "sg:postcode":"43201",
    "sg:province":"Tarragona",
    "wof:name":"Montes Recio Antonio",
    "wof:placetype":"venue"
},
  "geometry": {"coordinates":[1.1099530458,41.155632019],"type":"Point"}
}