{
  "type": "Feature",
  "properties": {
    "addr:full":"Calle de Joaquin Arnau, 18 Teruel Teruel 44001",
    "addr:housenumber":"18",
    "addr:postcode":"44001",
    "addr:street":"Calle De Joaquin Arnau",
    "iso:country":"ES",
    "sg:address":"Calle de Joaquin Arnau, 18",
    "sg:city":"Teruel",
    "sg:orig_category":"Procuradores",
    "sg:phone":"+34 978 60 21 60",
    "sg:postcode":"44001",
    "sg:province":"Teruel",
    "wof:name":"Perez Fortea Maria Isabel",
    "wof:placetype":"venue"
},
  "geometry": {"coordinates":[-1.1074609756,40.3405570984],"type":"Point"}
}