{
  "type": "Feature",
  "properties": {
    "iso:country":"ES",
    "sg:address":"Rua Burgas (das), 10",
    "sg:city":"Ourense",
    "sg:orig_category":"Art\u00cdculos De Regalo (al Por Menor)",
    "sg:phone":"+34 988 22 27 39",
    "sg:postcode":"32005",
    "sg:province":"Ourense",
    "wof:name":"Guerra Enriquez Carlos",
    "wof:placetype":"venue"
},
  "geometry": {"coordinates":[-7.8648219109,42.3349113464],"type":"Point"}
}