{
  "type": "Feature",
  "properties": {
    "addr:full":"Avda Boliches De Los, 50 Fuengirola M\u00e1laga 29640",
    "addr:postcode":"29640",
    "addr:street":"Avda Boliches De Los;Ma\u0301Laga",
    "iso:country":"ES",
    "sg:address":"Avda Boliches De Los, 50",
    "sg:city":"Fuengirola",
    "sg:orig_category":"Fabricaci\u00d3n, Importaci\u00d3n De Material Y Sistemas De Telecomunicaciones",
    "sg:phone":"+34 952 58 70 18",
    "sg:postcode":"29640",
    "sg:province":"M\u00e1laga",
    "wof:name":"Terrasa Salazar Veronica",
    "wof:placetype":"venue"
},
  "geometry": {"coordinates":[-4.6142511368,36.5534362793],"type":"Point"}
}