{
  "type": "Feature",
  "properties": {
    "iso:country":"ES",
    "sg:address":"Carrer de Rafael Ll Blanes, 14",
    "sg:city":"Palma",
    "sg:orig_category":"Electricidad: Instaladores",
    "sg:phone":"+34 971 27 19 71",
    "sg:postcode":"07007",
    "sg:province":"Islas Baleares",
    "wof:name":"Electrica Tortella S.a.",
    "wof:placetype":"venue"
},
  "geometry": {"coordinates":[2.6683609486,39.5749664307],"type":"Point"}
}