{
  "type": "Feature",
  "properties": {
    "addr:full":"Calle de Alhondiga, 2 Huercal-overa Almer\u00eda 04600",
    "addr:housenumber":"2",
    "addr:postcode":"04600",
    "addr:street":"Calle De Alhondiga;Almeri\u0301A",
    "iso:country":"ES",
    "sg:address":"Calle de Alhondiga, 2",
    "sg:city":"Huercal-overa",
    "sg:orig_category":"Estancos",
    "sg:phone":"+34 950 47 02 65",
    "sg:postcode":"04600",
    "sg:province":"Almer\u00eda",
    "wof:name":"Sanchez Melgares Angela",
    "wof:placetype":"venue"
},
  "geometry": {"coordinates":[-1.9426350594,37.3882369995],"type":"Point"}
}