{
  "type": "Feature",
  "properties": {
    "iso:country":"ES",
    "sg:address":"Carrer de Cartagena, 343",
    "sg:city":"Barcelona",
    "sg:orig_category":"M\u00c9dicos: Medicina General",
    "sg:phone":"+34 934 36 47 34",
    "sg:postcode":"08025",
    "sg:province":"Barcelona",
    "wof:name":"Microdiagnostic S.l.",
    "wof:placetype":"venue"
},
  "geometry": {"coordinates":[2.1725358963,41.4123458862],"type":"Point"}
}