{
  "type": "Feature",
  "properties": {
    "iso:country":"ES",
    "sg:address":"Calle de Estacion (la), S/n",
    "sg:city":"Mataporquera",
    "sg:classifiers":[
        {
            "category":"Manufacturing",
            "subcategory":"Building Materials",
            "type":"Manufacturing & Wholesale Goods"
        }
    ],
    "sg:phone":"+34 942 77 03 53",
    "sg:postcode":"39410",
    "sg:province":"Cantabria",
    "sg:tags":[
        "cemento",
        "y",
        "de",
        "fabricaci\u00d3n",
        "cal"
    ],
    "wof:name":"Cemensilos S.a.",
    "wof:placetype":"venue"
},
  "geometry": {"coordinates":[-4.1668839455,42.8720054626],"type":"Point"}
}