{
  "type": "Feature",
  "properties": {
    "iso:country":"ES",
    "sg:address":"Regomil, 29",
    "sg:city":"Rejomil",
    "sg:orig_category":"Alimentaci\u00d3n General (al Por Menor)",
    "sg:phone":"+34 986 33 30 53",
    "sg:postcode":"36417",
    "sg:province":"Pontevedra",
    "wof:name":"Romero Alonso Julia",
    "wof:placetype":"venue"
},
  "geometry": {"coordinates":[-8.6178617477,42.2033996582],"type":"Point"}
}