{
  "type": "Feature",
  "properties": {
    "addr:full":"Calle de Alta, 9 Priego Cordoba C\u00f3rdoba 14800",
    "addr:housenumber":"9",
    "addr:postcode":"14800",
    "addr:street":"Calle De Alta;Cordoba Co\u0301Rdoba",
    "iso:country":"ES",
    "sg:address":"Calle de Alta, 9",
    "sg:city":"Priego Cordoba",
    "sg:orig_category":"Empresarios",
    "sg:phone":"+34 957 54 37 16",
    "sg:postcode":"14800",
    "sg:province":"C\u00f3rdoba",
    "wof:name":"Parroquia Nuestra Se\u00f1ora De La Asuncion",
    "wof:placetype":"venue"
},
  "geometry": {"coordinates":[-4.1469130516,37.5091514587],"type":"Point"}
}