{
  "type": "Feature",
  "properties": {
    "addr:full":"Calle de Almunia, 24 Zaragoza Zaragoza 50003",
    "addr:housenumber":"24",
    "addr:postcode":"50003",
    "addr:street":"Calle De Almunia",
    "iso:country":"ES",
    "sg:address":"Calle de Almunia, 24",
    "sg:city":"Zaragoza",
    "sg:orig_category":"Papeler\u00cdas, Librer\u00cdas",
    "sg:phone":"+34 976 43 84 59",
    "sg:postcode":"50003",
    "sg:province":"Zaragoza",
    "wof:name":"Aguilera Sanz Faustino",
    "wof:placetype":"venue"
},
  "geometry": {"coordinates":[-0.8982771039,41.6621589661],"type":"Point"}
}