{
  "type": "Feature",
  "properties": {
    "iso:country":"ES",
    "sg:address":"Calle de Pozoblanco, 7",
    "sg:city":"Villanueva Cordoba",
    "sg:orig_category":"Mec\u00c1nico Del Autom\u00d3vil",
    "sg:phone":"+34 957 12 00 69",
    "sg:postcode":"14440",
    "sg:province":"C\u00f3rdoba",
    "wof:name":"Cesar Motor S.c.",
    "wof:placetype":"venue"
},
  "geometry": {"coordinates":[-4.6299290657,38.3229560852],"type":"Point"}
}