{
  "type": "Feature",
  "properties": {
    "iso:country":"ES",
    "sg:address":"Plaz Mayor, 2",
    "sg:city":"Castrojeriz",
    "sg:orig_category":"Asociaciones De Vecinos, Centros De Juventud",
    "sg:phone":"+34 947 37 85 36",
    "sg:postcode":"09110",
    "sg:province":"Burgos",
    "sg:website":"www.adeco-camino.org",
    "wof:name":"Asociacion Adeco-camino Programa Leader",
    "wof:placetype":"venue"
},
  "geometry": {"coordinates":[-4.139008522,42.2881240845],"type":"Point"}
}