{
  "type": "Feature",
  "properties": {
    "iso:country":"ES",
    "sg:address":"Calle de San Francisco, 28",
    "sg:city":"Bollullos Par Condado",
    "sg:orig_category":"Procuradores",
    "sg:phone":"+34 959 41 07 70",
    "sg:postcode":"21710",
    "sg:province":"Huelva",
    "wof:name":"Garcia Espina Purificacion Maria",
    "wof:placetype":"venue"
},
  "geometry": {"coordinates":[-6.536714077,37.3375511169],"type":"Point"}
}