{
  "type": "Feature",
  "properties": {
    "iso:country":"ES",
    "sg:address":"Calle de Yeste, 1",
    "sg:city":"Castellon De La Plana",
    "sg:orig_category":"Iglesia Cat\u00d3lica",
    "sg:phone":"+34 964 20 00 17",
    "sg:postcode":"12005",
    "sg:province":"Castell\u00f3n",
    "wof:name":"Parroquia De Nuestra Se\u00f1ora De Los Angeles",
    "wof:placetype":"venue"
},
  "geometry": {"coordinates":[-0.0591429994,39.9569168091],"type":"Point"}
}