{
  "type": "Feature",
  "properties": {
    "iso:country":"ES",
    "sg:address":"Calle de Aguirre Maximo, 12",
    "sg:city":"Bilbao",
    "sg:orig_category":"Abogados",
    "sg:phone":"+34 944 43 57 50",
    "sg:postcode":"48011",
    "sg:province":"Vizcaya",
    "wof:name":"Gomez Garcia Juan Jacobo",
    "wof:placetype":"venue"
},
  "geometry": {"coordinates":[-2.9375298023,43.2641220093],"type":"Point"}
}