{
  "type": "Feature",
  "properties": {
    "iso:country":"ES",
    "sg:address":"Rua Cruce, 2",
    "sg:city":"Coruxo De Arriba",
    "sg:orig_category":"Molduras, Junquillos, Listones Y Molduras Perforadas",
    "sg:phone":"+34 981 61 47 17",
    "sg:postcode":"15179",
    "sg:province":"La Coru\u00f1a",
    "wof:name":"Gonzalez Bravo Miguel Alberto",
    "wof:placetype":"venue"
},
  "geometry": {"coordinates":[-8.3459596634,43.3464698792],"type":"Point"}
}