{
  "type": "Feature",
  "properties": {
    "iso:country":"ES",
    "sg:address":"Cami Ral, 108",
    "sg:city":"Mataro",
    "sg:orig_category":"Molduras, Junquillos, Listones Y Molduras Perforadas",
    "sg:phone":"+34 937 90 32 61",
    "sg:postcode":"08301",
    "sg:province":"Barcelona",
    "wof:name":"Pujol Floriach Francesc",
    "wof:placetype":"venue"
},
  "geometry": {"coordinates":[2.4527959824,41.5409164429],"type":"Point"}
}