{
  "type": "Feature",
  "properties": {
    "iso:country":"ES",
    "sg:address":"Calle de Aravaca, 7",
    "sg:city":"Madrid",
    "sg:orig_category":"Caf\u00c9s, Bares, Cervecer\u00cdas",
    "sg:phone":"+34 915 34 51 82",
    "sg:postcode":"28040",
    "sg:province":"Madrid",
    "wof:name":"Hosteleria Salco S.l.",
    "wof:placetype":"venue"
},
  "geometry": {"coordinates":[-3.7125360966,40.4480819702],"type":"Point"}
}