{
  "type": "Feature",
  "properties": {
    "addr:full":"Zubiarte, 20 Huarte Navarra 31620",
    "addr:housenumber":"20",
    "addr:postcode":"31620",
    "addr:street":"Zubiarte;Navarra",
    "iso:country":"ES",
    "sg:address":"Zubiarte, 20",
    "sg:city":"Huarte",
    "sg:orig_category":"Fotograf\u00cda Y Cine: Aparatos, Pel\u00cdculas Y Accesorios (al Por Menor)",
    "sg:phone":"+34 948 33 26 15",
    "sg:postcode":"31620",
    "sg:province":"Navarra",
    "wof:name":"Iriarte Rived Asuncion",
    "wof:placetype":"venue"
},
  "geometry": {"coordinates":[-1.5920490026,42.8314704895],"type":"Point"}
}