{
  "type": "Feature",
  "properties": {
    "iso:country":"ES",
    "sg:address":"Vred Yeguas (de Las), S/n",
    "sg:city":"Arganda",
    "sg:orig_category":"Productos Qu\u00cdmicos (fabricaci\u00d3n, Al Por Mayor)",
    "sg:phone":"+34 918 75 74 03",
    "sg:postcode":"28500",
    "sg:province":"Madrid",
    "wof:name":"Destilerias Requim S.a.",
    "wof:placetype":"venue"
},
  "geometry": {"coordinates":[-3.4406979084,40.2999954224],"type":"Point"}
}