{
  "type": "Feature",
  "properties": {
    "iso:country":"ES",
    "sg:address":"Calle de Minitas, 1",
    "sg:city":"Almendralejo",
    "sg:orig_category":"Chapister\u00cda",
    "sg:phone":"+34 924 66 04 51",
    "sg:postcode":"06200",
    "sg:province":"Badajoz",
    "wof:name":"Trinidad Trejo Felix",
    "wof:placetype":"venue"
},
  "geometry": {"coordinates":[-6.4061107635,38.6900444031],"type":"Point"}
}