{
  "type": "Feature",
  "properties": {
    "iso:country":"ES",
    "sg:address":"Calle de Zabalbide, 137",
    "sg:city":"Bilbao",
    "sg:orig_category":"Mec\u00c1nico Del Autom\u00d3vil",
    "sg:phone":"+34 944 46 12 42",
    "sg:postcode":"48007",
    "sg:province":"Vizcaya",
    "wof:name":"Talleres Lagun Bat Auto S.l.",
    "wof:placetype":"venue"
},
  "geometry": {"coordinates":[-2.9115788937,43.260848999],"type":"Point"}
}