{
  "type": "Feature",
  "properties": {
    "iso:country":"ES",
    "sg:address":"Calle de Marchenilla, 8",
    "sg:city":"Mairena Alcor",
    "sg:orig_category":"Agencias Y Asesor\u00cda En Marketing Directo",
    "sg:phone":"+34 955 74 66 31",
    "sg:postcode":"41510",
    "sg:province":"Sevilla",
    "wof:name":"Construcciones Y Reformas Morama S.l.",
    "wof:placetype":"venue"
},
  "geometry": {"coordinates":[-5.7529778481,37.3714675903],"type":"Point"}
}