{
  "type": "Feature",
  "properties": {
    "iso:country":"ES",
    "sg:address":"Calle de Hermanos Vilafa\u00d1a, 12",
    "sg:city":"Castellon",
    "sg:classifiers":[
        {
            "category":"Autos & Motor Vehicles",
            "subcategory":"Automobile Sales",
            "type":"Retail Goods"
        }
    ],
    "sg:phone":"+34 964 20 35 71",
    "sg:postcode":"12004",
    "sg:province":"Castell\u00f3n",
    "wof:name":"Carceller Guardiola Himerio",
    "wof:placetype":"venue"
},
  "geometry": {"coordinates":[-0.0257600006,40.0253791809],"type":"Point"}
}