{
  "type": "Feature",
  "properties": {
    "addr:full":"Riera Acata, 3 S. Andreu Llavaneres Barcelona 08392",
    "addr:housenumber":"3",
    "addr:postcode":"08392",
    "addr:street":"Riera Acata;S. Andreu Llavaneres Barcelona",
    "iso:country":"ES",
    "sg:address":"Riera Acata, 3",
    "sg:city":"S. Andreu Llavaneres",
    "sg:orig_category":"Promotores Constructores",
    "sg:phone":"+34 937 95 20 80",
    "sg:postcode":"08392",
    "sg:province":"Barcelona",
    "wof:name":"Profel S. A.",
    "wof:placetype":"venue"
},
  "geometry": {"coordinates":[2.4849700928,41.5697517395],"type":"Point"}
}