{
  "type": "Feature",
  "properties": {
    "iso:country":"ES",
    "sg:address":"Carr Dr Fleming, 21",
    "sg:city":"Balaguer",
    "sg:orig_category":"Promotores Constructores",
    "sg:phone":"+34 973 44 64 54",
    "sg:postcode":"25600",
    "sg:province":"Lleida",
    "wof:name":"Edilaplana S.l.",
    "wof:placetype":"venue"
},
  "geometry": {"coordinates":[0.810109973,41.7907180786],"type":"Point"}
}