{
  "type": "Feature",
  "properties": {
    "addr:full":"Calle de General Franco, S/n Tabanera Cerrato Palencia 34257",
    "addr:housenumber":"s / n",
    "addr:postcode":"34257",
    "addr:street":"Calle De General Franco",
    "iso:country":"ES",
    "sg:address":"Calle de General Franco, S/n",
    "sg:city":"Tabanera Cerrato",
    "sg:orig_category":"Promotores Constructores",
    "sg:phone":"+34 979 79 31 79",
    "sg:postcode":"34257",
    "sg:province":"Palencia",
    "wof:name":"Pradanos Merino Argimiro",
    "wof:placetype":"venue"
},
  "geometry": {"coordinates":[-4.1236338615,42.0243606567],"type":"Point"}
}