{
  "type": "Feature",
  "properties": {
    "iso:country":"ES",
    "sg:address":"Calle de Gascon De Gotor, 24",
    "sg:city":"Zaragoza",
    "sg:orig_category":"Centros Empresariales",
    "sg:phone":"+34 976 38 63 80",
    "sg:postcode":"50006",
    "sg:province":"Zaragoza",
    "wof:name":"Global Pqm S.l.u.",
    "wof:placetype":"venue"
},
  "geometry": {"coordinates":[-0.8887599707,41.6387367249],"type":"Point"}
}