{
  "type": "Feature",
  "properties": {
    "iso:country":"ES",
    "sg:address":"Avda Andalucia, 47",
    "sg:city":"Jaen",
    "sg:orig_category":"Empresas De Limpieza",
    "sg:phone":"+34 953 22 00 28",
    "sg:postcode":"23005",
    "sg:province":"Ja\u00e9n",
    "wof:name":"Limpiezas Gares S.l.",
    "wof:placetype":"venue"
},
  "geometry": {"coordinates":[-3.7969949245,37.7775764465],"type":"Point"}
}