{
  "type": "Feature",
  "properties": {
    "iso:country":"ES",
    "sg:address":"Avda Begonias, 4",
    "sg:city":"Bormujos",
    "sg:orig_category":"Centros Empresariales",
    "sg:phone":"+34 955 72 61 30",
    "sg:postcode":"41930",
    "sg:province":"Sevilla",
    "sg:website":"www.toldosincase.com",
    "wof:name":"Ortiz Perez Francisco",
    "wof:placetype":"venue"
},
  "geometry": {"coordinates":[-6.0611839294,37.365940094],"type":"Point"}
}