{
  "type": "Feature",
  "properties": {
    "addr:full":"Carr Santa Llogaia, 15 Figueres Girona 17600",
    "addr:housenumber":"15",
    "addr:postcode":"17600",
    "addr:street":"Carr Santa Llogaia",
    "iso:country":"ES",
    "sg:address":"Carr Santa Llogaia, 15",
    "sg:city":"Figueres",
    "sg:orig_category":"Int\u00c9rpretes",
    "sg:phone":"+34 972 67 65 52",
    "sg:postcode":"17600",
    "sg:province":"Girona",
    "wof:name":"Garcia Tomas Nuria",
    "wof:placetype":"venue"
},
  "geometry": {"coordinates":[2.9607589245,42.2627487183],"type":"Point"}
}