{
  "type": "Feature",
  "properties": {
    "addr:full":"Carr Santiago Rosinyol, 12 Hostalric Girona 17450",
    "addr:housenumber":"12",
    "addr:postcode":"17450",
    "addr:street":"Carr Santiago Rosinyol",
    "iso:country":"ES",
    "sg:address":"Carr Santiago Rosinyol, 12",
    "sg:city":"Hostalric",
    "sg:orig_category":"Electromec\u00c1nica",
    "sg:phone":"+34 972 86 51 86",
    "sg:postcode":"17450",
    "sg:province":"Girona",
    "wof:name":"Oficina Tecnica Tacc S.l.",
    "wof:placetype":"venue"
},
  "geometry": {"coordinates":[2.6304600239,41.7436599731],"type":"Point"}
}