{
  "type": "Feature",
  "properties": {
    "iso:country":"ES",
    "sg:address":"Rua San Marti\u00d1o, 1",
    "sg:city":"Carballo",
    "sg:orig_category":"Talleres De Corte Y Confecci\u00d3n",
    "sg:phone":"+34 981 70 30 95",
    "sg:postcode":"15100",
    "sg:province":"La Coru\u00f1a",
    "wof:name":"Confeccions Zynko's S.l.",
    "wof:placetype":"venue"
},
  "geometry": {"coordinates":[-8.6919393539,43.2094154358],"type":"Point"}
}