{
  "type": "Feature",
  "properties": {
    "iso:country":"ES",
    "sg:address":"Calle de Palma, 1",
    "sg:city":"Puebla Almoradiel",
    "sg:orig_category":"Promotores Constructores",
    "sg:phone":"+34 925 17 86 23",
    "sg:postcode":"45840",
    "sg:province":"Toledo",
    "wof:name":"Promociones Aribamac S.l.",
    "wof:placetype":"venue"
},
  "geometry": {"coordinates":[-3.1100478172,39.5987586975],"type":"Point"}
}