{
  "type": "Feature",
  "properties": {
    "addr:full":"Calle de Marques De Urquijo, 11 Gijon Asturias 33203",
    "addr:housenumber":"11",
    "addr:postcode":"33203",
    "addr:street":"Calle De Marques De Urquijo",
    "iso:country":"ES",
    "sg:address":"Calle de Marques De Urquijo, 11",
    "sg:city":"Gijon",
    "sg:orig_category":"Confecci\u00d3n De Trajes Para Se\u00d1oras",
    "sg:phone":"+34 985 36 33 23",
    "sg:postcode":"33203",
    "sg:province":"Asturias",
    "wof:name":"Hernandez Sanchez Ana Maria",
    "wof:placetype":"venue"
},
  "geometry": {"coordinates":[-5.6467618942,43.5383262634],"type":"Point"}
}