{
  "type": "Feature",
  "properties": {
    "addr:full":"Calle de Isaac Albeniz, 5 Fuensalida Toledo 45510",
    "addr:housenumber":"5",
    "addr:postcode":"45510",
    "addr:street":"Calle De Isaac Albeniz",
    "iso:country":"ES",
    "sg:address":"Calle de Isaac Albeniz, 5",
    "sg:city":"Fuensalida",
    "sg:orig_category":"Piedra Natural",
    "sg:phone":"+34 925 78 49 35",
    "sg:postcode":"45510",
    "sg:province":"Toledo",
    "wof:name":"Rodriguez Palmero Victoriano",
    "wof:placetype":"venue"
},
  "geometry": {"coordinates":[-4.2031002045,40.0522041321],"type":"Point"}
}