{
  "type": "Feature",
  "properties": {
    "iso:country":"ES",
    "sg:address":"Carrer de Casanova, 264",
    "sg:city":"Barcelona",
    "sg:orig_category":"M\u00c9dicos: Medicina General Orientada A La Acupuntura",
    "sg:phone":"+34 932 00 26 52",
    "sg:postcode":"08021",
    "sg:province":"Barcelona",
    "sg:website":"www.paginasamarillas.es",
    "wof:name":"Chuang Rafi Margarita",
    "wof:placetype":"venue"
},
  "geometry": {"coordinates":[2.1473100185,41.3942756653],"type":"Point"}
}