{
  "type": "Feature",
  "properties": {
    "iso:country":"ES",
    "sg:address":"Moldes, S/n",
    "sg:city":"Moldes",
    "sg:classifiers":[
        {
            "category":"Taxi",
            "type":"Transportation"
        }
    ],
    "sg:phone":"+34 986 55 80 34",
    "sg:postcode":"36645",
    "sg:province":"Pontevedra",
    "wof:name":"Taibo Tojo Jesus",
    "wof:placetype":"venue"
},
  "geometry": {"coordinates":[-8.6490335464,42.7007255554],"type":"Point"}
}