{
  "type": "Feature",
  "properties": {
    "addr:full":"Carrer de Verge De Montserrat, 6 Cambrils Tarragona 43850",
    "addr:housenumber":"6",
    "addr:postcode":"43850",
    "addr:street":"Carrer De Verge De Montserrat",
    "iso:country":"ES",
    "sg:address":"Carrer de Verge De Montserrat, 6",
    "sg:city":"Cambrils",
    "sg:orig_category":"Farmacias",
    "sg:phone":"+34 977 36 45 12",
    "sg:postcode":"43850",
    "sg:province":"Tarragona",
    "wof:name":"Guillen Lacue Nuria",
    "wof:placetype":"venue"
},
  "geometry": {"coordinates":[1.055243969,41.069393158],"type":"Point"}
}