{
  "type": "Feature",
  "properties": {
    "addr:full":"Calle de Pastor, 18 Playa De Salinetas Las Palmas 35214",
    "addr:housenumber":"18",
    "addr:postcode":"35214",
    "addr:street":"Calle De Pastor;Palmas",
    "iso:country":"ES",
    "sg:address":"Calle de Pastor, 18",
    "sg:city":"Playa De Salinetas",
    "sg:orig_category":"Promotores Constructores",
    "sg:phone":"+34 902 10 04 51",
    "sg:postcode":"35214",
    "sg:province":"Las Palmas",
    "wof:name":"Estructura Y Revestimientos Marsan S.l.",
    "wof:placetype":"venue"
},
  "geometry": {"coordinates":[-15.3882036209,27.9765491486],"type":"Point"}
}