{
  "type": "Feature",
  "properties": {
    "iso:country":"ES",
    "sg:address":"Calle de San Quintin, 1",
    "sg:city":"Valladolid",
    "sg:orig_category":"Alimentaci\u00d3n General (al Por Menor)",
    "sg:phone":"+34 983 29 10 17",
    "sg:postcode":"47005",
    "sg:province":"Valladolid",
    "wof:name":"Rivera Pinilla Jose Luis",
    "wof:placetype":"venue"
},
  "geometry": {"coordinates":[-4.7141680717,41.6540908813],"type":"Point"}
}