{
  "type": "Feature",
  "properties": {
    "addr:full":"Pol Ind Montes Del Cierzo, S/n Tudela Navarra 31500",
    "addr:housenumber":"s",
    "addr:postcode":"31500",
    "addr:street":"/ N",
    "iso:country":"ES",
    "sg:address":"Pol Ind Montes Del Cierzo, S/n",
    "sg:city":"Tudela",
    "sg:orig_category":"Fabricaci\u00d3n De Mobiliario Met\u00c1lico",
    "sg:phone":"+34 948 84 44 80",
    "sg:postcode":"31500",
    "sg:province":"Navarra",
    "sg:website":"www.arestant.com",
    "wof:name":"Arestant S.a.",
    "wof:placetype":"venue"
},
  "geometry": {"coordinates":[-1.4821481705,42.1872329712],"type":"Point"}
}