{
  "type": "Feature",
  "properties": {
    "iso:country":"ES",
    "sg:address":"Calle de Karmelo Etxegarai, 8",
    "sg:city":"Gernika-lumo",
    "sg:orig_category":"Abogados",
    "sg:phone":"+34 946 25 73 75",
    "sg:postcode":"48300",
    "sg:province":"Vizcaya",
    "wof:name":"Rafael Gainza Urrutia",
    "wof:placetype":"venue"
},
  "geometry": {"coordinates":[-2.6792669296,43.3124465942],"type":"Point"}
}