{
  "type": "Feature",
  "properties": {
    "iso:country":"ES",
    "sg:address":"Avda Marconi, S/n",
    "sg:city":"Madrid",
    "sg:orig_category":"Herramientas Y Suministros Para Plomeros",
    "sg:phone":"+34 915 05 37 81",
    "sg:postcode":"28021",
    "sg:province":"Madrid",
    "wof:name":"Faust Y Kammann S.a.",
    "wof:placetype":"venue"
},
  "geometry": {"coordinates":[-3.695168972,40.3340301514],"type":"Point"}
}