{
  "type": "Feature",
  "properties": {
    "addr:full":"Crt. G. Sevilla, 277 Almendralejo Badajoz 06200",
    "addr:housenumber":"277",
    "addr:postcode":"06200",
    "addr:street":"Crt. G. Sevilla",
    "iso:country":"ES",
    "sg:address":"Crt. G. Sevilla, 277",
    "sg:city":"Almendralejo",
    "sg:orig_category":"Chapister\u00cda",
    "sg:phone":"+34 924 66 68 45",
    "sg:postcode":"06200",
    "sg:province":"Badajoz",
    "wof:name":"Agumasa Cdad.",
    "wof:placetype":"venue"
},
  "geometry": {"coordinates":[-6.4017014503,38.6856002808],"type":"Point"}
}