{
  "type": "Feature",
  "properties": {
    "addr:full":"Calle de Asuncion, 46 Alcala Rio Sevilla 41200",
    "addr:housenumber":"46",
    "addr:postcode":"41200",
    "addr:street":"Calle De Asuncion",
    "iso:country":"ES",
    "sg:address":"Calle de Asuncion, 46",
    "sg:city":"Alcala Rio",
    "sg:orig_category":"Contables",
    "sg:phone":"+34 955 65 06 44",
    "sg:postcode":"41200",
    "sg:province":"Sevilla",
    "wof:name":"Garcia Gomez Maria De Los Angeles",
    "wof:placetype":"venue"
},
  "geometry": {"coordinates":[-5.9825425148,37.5209350586],"type":"Point"}
}