{
  "type": "Feature",
  "properties": {
    "iso:country":"ES",
    "sg:address":"Ctra Vilar De Barrio (de), 8",
    "sg:city":"Laza",
    "sg:orig_category":"Quincaller\u00cda (al Por Menor)",
    "sg:phone":"+34 988 42 20 26",
    "sg:postcode":"32620",
    "sg:province":"Ourense",
    "wof:name":"J.sobrino Dieguez E Hijos S.l.",
    "wof:placetype":"venue"
},
  "geometry": {"coordinates":[-7.4598069191,42.0580635071],"type":"Point"}
}