{
  "type": "Feature",
  "properties": {
    "addr:full":"Calle de Trespaderne, 29 Madrid Madrid 28042",
    "addr:housenumber":"29",
    "addr:postcode":"madrid;28042",
    "addr:street":"Calle De Trespaderne",
    "iso:country":"ES",
    "sg:address":"Calle de Trespaderne, 29",
    "sg:city":"Madrid",
    "sg:orig_category":"Transporte En General",
    "sg:phone":"+34 913 29 35 25",
    "sg:postcode":"28042",
    "sg:province":"Madrid",
    "wof:name":"Space Cargo Export",
    "wof:placetype":"venue"
},
  "geometry": {"coordinates":[-3.5841226578,40.4533424377],"type":"Point"}
}