{
  "type": "Feature",
  "properties": {
    "addr:full":"Pase Castellana, 121 Madrid Madrid 28046",
    "addr:housenumber":"121",
    "addr:postcode":"28046",
    "addr:street":"Castellana",
    "iso:country":"ES",
    "sg:address":"Pase Castellana, 121",
    "sg:city":"Madrid",
    "sg:orig_category":"Bisuteros (fabricaci\u00d3n, Al Por Mayor)",
    "sg:phone":"+34 914 17 05 58",
    "sg:postcode":"28046",
    "sg:province":"Madrid",
    "wof:name":"Sodomigliori S.l.",
    "wof:placetype":"venue"
},
  "geometry": {"coordinates":[-3.6906900406,40.4577178955],"type":"Point"}
}