{
  "type": "Feature",
  "properties": {
    "addr:full":"Bulandegi, 3 Aduna Guip\u00f9zcoa 20150",
    "addr:housenumber":"3",
    "addr:postcode":"20150",
    "addr:street":"Bulandegi;Guipu\u0300Zcoa",
    "iso:country":"ES",
    "sg:address":"Bulandegi, 3",
    "sg:city":"Aduna",
    "sg:orig_category":"Tubos Met\u00c1licos",
    "sg:phone":"+34 943 69 25 97",
    "sg:postcode":"20150",
    "sg:province":"Guip\u00f9zcoa",
    "wof:name":"Aceralia Distribucion S.l.",
    "wof:placetype":"venue"
},
  "geometry": {"coordinates":[-2.0564000607,43.1911964417],"type":"Point"}
}