{
  "type": "Feature",
  "properties": {
    "iso:country":"ES",
    "sg:address":"Ctra. B-motril, Km. 0343,4",
    "sg:city":"La Yuca",
    "sg:orig_category":"M\u00c9dicos: Ginecolog\u00cda Y Obstetricia",
    "sg:phone":"+34 953 32 23 00",
    "sg:postcode":"23001",
    "sg:province":"Ja\u00e9n",
    "wof:name":"Luque Marin Juan",
    "wof:placetype":"venue"
},
  "geometry": {"coordinates":[-3.7895176411,37.7657394409],"type":"Point"}
}