{
  "type": "Feature",
  "properties": {
    "iso:country":"ES",
    "sg:address":"Calle de Colombia, 12",
    "sg:city":"Pinto",
    "sg:orig_category":"Agencias Y Agentes Comerciales, Representantes",
    "sg:phone":"+34 916 92 58 14",
    "sg:postcode":"28320",
    "sg:province":"Madrid",
    "wof:name":"Soltero Paredes Demetrio",
    "wof:placetype":"venue"
},
  "geometry": {"coordinates":[-3.7024009228,40.2376327515],"type":"Point"}
}