{
  "type": "Feature",
  "properties": {
    "addr:full":"Pase Castellana, 201 Madrid Madrid 28046",
    "addr:housenumber":"201",
    "addr:postcode":"28046",
    "addr:street":"Castellana",
    "iso:country":"ES",
    "sg:address":"Pase Castellana, 201",
    "sg:city":"Madrid",
    "sg:orig_category":"Importaci\u00d3n",
    "sg:phone":"+34 913 15 32 27",
    "sg:postcode":"28046",
    "sg:province":"Madrid",
    "wof:name":"Spacomex S.l.",
    "wof:placetype":"venue"
},
  "geometry": {"coordinates":[-3.6890830994,40.468952179],"type":"Point"}
}