{
  "type": "Feature",
  "properties": {
    "iso:country":"ES",
    "sg:address":"Avda Neguri, 9",
    "sg:city":"Getxo",
    "sg:orig_category":"Panader\u00cdas, Panader\u00cdas",
    "sg:phone":"+34 944 60 24 49",
    "sg:postcode":"48990",
    "sg:province":"Vizcaya",
    "wof:name":"Jokin Garate Bayo",
    "wof:placetype":"venue"
},
  "geometry": {"coordinates":[-3.0073699951,43.3402404785],"type":"Point"}
}