{
  "type": "Feature",
  "properties": {
    "addr:full":"Calle de Humilladero, 7 Linares Riofrio Salamanca 37760",
    "addr:housenumber":"7",
    "addr:postcode":"37760",
    "addr:street":"Calle De Humilladero",
    "iso:country":"ES",
    "sg:address":"Calle de Humilladero, 7",
    "sg:city":"Linares Riofrio",
    "sg:orig_category":"Ense\u00d1anza, Formaci\u00d3n Profesional: Aprendizaje",
    "sg:phone":"+34 923 41 61 10",
    "sg:postcode":"37760",
    "sg:province":"Salamanca",
    "wof:name":"Centro Educacion De Adulto Mateo Hernandez",
    "wof:placetype":"venue"
},
  "geometry": {"coordinates":[-5.9242391586,40.5853805542],"type":"Point"}
}