{
  "type": "Feature",
  "properties": {
    "addr:full":"Arias De Miranda, S/n San Miguel Bernuy Segovia 40332",
    "addr:housenumber":"s / n",
    "addr:postcode":"40332",
    "iso:country":"ES",
    "sg:address":"Arias De Miranda, S/n",
    "sg:city":"San Miguel Bernuy",
    "sg:orig_category":"Distribuci\u00d3n De Petr\u00d3leo Y Derivados",
    "sg:phone":"+34 921 52 91 87",
    "sg:postcode":"40332",
    "sg:province":"Segovia",
    "wof:name":"Bravoil S.l.",
    "wof:placetype":"venue"
},
  "geometry": {"coordinates":[-3.9491159916,41.3999977112],"type":"Point"}
}