{
  "type": "Feature",
  "properties": {
    "iso:country":"ES",
    "sg:address":"Calle de Bravo Murillo, 207",
    "sg:city":"Madrid",
    "sg:orig_category":"Puertas Y Portales",
    "sg:phone":"+34 914 50 44 09",
    "sg:postcode":"28020",
    "sg:province":"Madrid",
    "sg:website":"www.graden-sl.com",
    "wof:name":"Graden S.l.",
    "wof:placetype":"venue"
},
  "geometry": {"coordinates":[-3.7025716305,40.4554862976],"type":"Point"}
}