{
  "type": "Feature",
  "properties": {
    "addr:full":"Calle de Mejico, 38 Coslada Madrid 28820",
    "addr:housenumber":"38",
    "addr:postcode":"28820",
    "addr:street":"Calle De Mejico",
    "iso:country":"ES",
    "sg:address":"Calle de Mejico, 38",
    "sg:city":"Coslada",
    "sg:orig_category":"Bancos",
    "sg:phone":"+34 916 60 11 95",
    "sg:postcode":"28820",
    "sg:province":"Madrid",
    "wof:name":"Auna Telecomunicaciones S.a.u.",
    "wof:placetype":"venue"
},
  "geometry": {"coordinates":[-3.5397911072,40.4282608032],"type":"Point"}
}