{
  "type": "Feature",
  "properties": {
    "addr:full":"Carrer de Casp, 55 Barcelona Barcelona 08010",
    "addr:housenumber":"55",
    "addr:postcode":"08010",
    "addr:street":"Carrer De Casp",
    "iso:country":"ES",
    "sg:address":"Carrer de Casp, 55",
    "sg:city":"Barcelona",
    "sg:orig_category":"Asesor\u00cda Fiscal Y Jur\u00cddica",
    "sg:phone":"+34 932 31 79 03",
    "sg:postcode":"08010",
    "sg:province":"Barcelona",
    "wof:name":"Molinero Mulas Maria Manuela",
    "wof:placetype":"venue"
},
  "geometry": {"coordinates":[2.1751708984,41.3929023743],"type":"Point"}
}