{
  "type": "Feature",
  "properties": {
    "addr:full":"Trva Coru\u00d1a, 2 Vigo Pontevedra 36211",
    "addr:housenumber":"2",
    "addr:postcode":"36211",
    "addr:street":"Trva Corun\u0303A",
    "iso:country":"ES",
    "sg:address":"Trva Coru\u00d1a, 2",
    "sg:city":"Vigo",
    "sg:orig_category":"Agencias Y Agentes Comerciales, Representantes",
    "sg:phone":"+34 986 21 16 20",
    "sg:postcode":"36211",
    "sg:province":"Pontevedra",
    "wof:name":"Soto Reboreda Carlos",
    "wof:placetype":"venue"
},
  "geometry": {"coordinates":[-8.7349185944,42.2229690552],"type":"Point"}
}