{
  "type": "Feature",
  "properties": {
    "iso:country":"ES",
    "sg:address":"Calle de Castillo, 37",
    "sg:city":"Santa Cruz De Tenerife",
    "sg:orig_category":"Asesor\u00cda Sobre Comunicaci\u00d3n De Empresas",
    "sg:phone":"+34 922 24 86 00",
    "sg:postcode":"38003",
    "sg:province":"Santa Cruz De Tenerife",
    "wof:name":"Corporacion 5 Analisis Y Estrategias S.l.",
    "wof:placetype":"venue"
},
  "geometry": {"coordinates":[-16.2512931824,28.4672107697],"type":"Point"}
}