{
  "type": "Feature",
  "properties": {
    "addr:full":"Calle de Rio, 43 Lominchar Toledo 45212",
    "addr:housenumber":"43",
    "addr:postcode":"45212",
    "addr:street":"Calle De Rio",
    "iso:country":"ES",
    "sg:address":"Calle de Rio, 43",
    "sg:city":"Lominchar",
    "sg:orig_category":"Bares, Piano",
    "sg:phone":"+34 925 55 84 88",
    "sg:postcode":"45212",
    "sg:province":"Toledo",
    "wof:name":"Dipri S.l.",
    "wof:placetype":"venue"
},
  "geometry": {"coordinates":[-3.9724340439,40.0933647156],"type":"Point"}
}