{
  "type": "Feature",
  "properties": {
    "iso:country":"ES",
    "sg:address":"Gta Quintiliano, 1",
    "sg:city":"Calahorra",
    "sg:orig_category":"Administraciones Regionales, Departamentales Y Locales",
    "sg:phone":"+34 941 13 09 32",
    "sg:postcode":"26500",
    "sg:province":"La Rioja",
    "sg:website":"www.ayto-calahorra.es",
    "wof:name":"Ayuntamiento De Calahorra",
    "wof:placetype":"venue"
},
  "geometry": {"coordinates":[-1.9615797997,42.3016014099],"type":"Point"}
}