{
  "type": "Feature",
  "properties": {
    "addr:full":"Calle de Urquijo Julio, 9 Bilbao Vizcaya 48014",
    "addr:housenumber":"9",
    "addr:postcode":"48014",
    "addr:street":"Calle De Urquijo Julio",
    "iso:country":"ES",
    "sg:address":"Calle de Urquijo Julio, 9",
    "sg:city":"Bilbao",
    "sg:orig_category":"Asesor\u00cda Sobre Comunicaci\u00d3n De Empresas",
    "sg:phone":"+34 944 47 37 69",
    "sg:postcode":"48014",
    "sg:province":"Vizcaya",
    "wof:name":"Miguel Angel Perez Y Otro, C.b.",
    "wof:placetype":"venue"
},
  "geometry": {"coordinates":[-2.9535779953,43.2696151733],"type":"Point"}
}