{
  "type": "Feature",
  "properties": {
    "addr:full":"Calle de San Antonio (de), 38 Aranjuez Madrid 28300",
    "addr:housenumber":"38",
    "addr:postcode":"28300",
    "addr:street":"Calle De San Antonio",
    "iso:country":"ES",
    "sg:address":"Calle de San Antonio (de), 38",
    "sg:city":"Aranjuez",
    "sg:orig_category":"Asociaciones Y Clubs Deportivos",
    "sg:phone":"+34 918 91 03 80",
    "sg:postcode":"28300",
    "sg:province":"Madrid",
    "wof:name":"Quintana Ortega Jesus Manuel",
    "wof:placetype":"venue"
},
  "geometry": {"coordinates":[-3.60699296,40.0335960388],"type":"Point"}
}