{
  "type": "Feature",
  "properties": {
    "iso:country":"ES",
    "sg:address":"Carrer de Pere Iv, 78",
    "sg:city":"Barcelona",
    "sg:orig_category":"Fabricaci\u00d3n, Distribuci\u00d3n De Discos, V\u00cddeodiscos Y Musicassettes",
    "sg:phone":"+34 934 85 38 60",
    "sg:postcode":"08005",
    "sg:province":"Barcelona",
    "wof:name":"Producciones Naimara S.l.",
    "wof:placetype":"venue"
},
  "geometry": {"coordinates":[2.1932981014,41.3971633911],"type":"Point"}
}