{
  "type": "Feature",
  "properties": {
    "iso:country":"ES",
    "sg:address":"Carrer de Arago, 1",
    "sg:city":"Barcelona",
    "sg:orig_category":"Farmacias",
    "sg:phone":"+34 932 29 60 70",
    "sg:postcode":"08015",
    "sg:province":"Barcelona",
    "wof:name":"Cortadella Ribera Rosa Maria",
    "wof:placetype":"venue"
},
  "geometry": {"coordinates":[2.1459019184,41.378162384],"type":"Point"}
}