{
  "type": "Feature",
  "properties": {
    "iso:country":"ES",
    "sg:address":"Rua Santiago, 50",
    "sg:city":"Lugo",
    "sg:orig_category":"Sociedades, Compa\u00d1\u00cdas Aseguradoras",
    "sg:phone":"+34 982 28 07 43",
    "sg:postcode":"27004",
    "sg:province":"Lugo",
    "wof:name":"Correduria De Seguros De Lico Corporacion S.a.",
    "wof:placetype":"venue"
},
  "geometry": {"coordinates":[-7.5641021729,42.9996643066],"type":"Point"}
}