{
  "type": "Feature",
  "properties": {
    "iso:country":"ES",
    "sg:address":"Calle de Ramon Y Cajal, 10",
    "sg:city":"Alcala Henares",
    "sg:orig_category":"Librer\u00cdas",
    "sg:phone":"+34 918 88 05 68",
    "sg:postcode":"28801",
    "sg:province":"Madrid",
    "wof:name":"Rodriguez Alvarez Francisco Javier",
    "wof:placetype":"venue"
},
  "geometry": {"coordinates":[-3.3652729988,40.4822616577],"type":"Point"}
}