{
  "type": "Feature",
  "properties": {
    "iso:country":"ES",
    "sg:address":"Carr De Ferreres Breto, 35",
    "sg:city":"Benicarlo",
    "sg:orig_category":"Peluquer\u00cdas, Peluquer\u00cda Mixta",
    "sg:phone":"+34 964 47 09 59",
    "sg:postcode":"12580",
    "sg:province":"Castell\u00f3n",
    "wof:name":"Arnamich S.l.",
    "wof:placetype":"venue"
},
  "geometry": {"coordinates":[0.4237649143,40.4179801941],"type":"Point"}
}