{
  "type": "Feature",
  "properties": {
    "addr:full":"Calle de Federico Tapia, 67 Coru\u00d1a La Coru\u00f1a 15005",
    "addr:housenumber":"67",
    "addr:postcode":"15005",
    "addr:street":"Calle De Federico Tapia;La Corun\u0303A",
    "iso:country":"ES",
    "sg:address":"Calle de Federico Tapia, 67",
    "sg:city":"Coru\u00d1a",
    "sg:orig_category":"Venta, Montaje De Neum\u00c1ticos",
    "sg:phone":"+34 981 23 27 26",
    "sg:postcode":"15005",
    "sg:province":"La Coru\u00f1a",
    "sg:website":"www.euromaster.com",
    "wof:name":"Euronet Spain S.a.",
    "wof:placetype":"venue"
},
  "geometry": {"coordinates":[-8.4063234329,43.3606452942],"type":"Point"}
}