{
  "type": "Feature",
  "properties": {
    "iso:country":"ES",
    "sg:address":"Carrer de Xiprer, 1",
    "sg:city":"Cornella Llobregat",
    "sg:orig_category":"Molduras, Junquillos, Listones Y Molduras Perforadas",
    "sg:phone":"+34 934 71 03 12",
    "sg:postcode":"08940",
    "sg:province":"Barcelona",
    "wof:name":"Oma\u00f1a Alvarez Piedad",
    "wof:placetype":"venue"
},
  "geometry": {"coordinates":[2.0865299702,41.3647422791],"type":"Point"}
}