{
  "type": "Feature",
  "properties": {
    "iso:country":"ES",
    "sg:address":"Cruceiro, 7",
    "sg:city":"Perlio",
    "sg:orig_category":"Carnicer\u00cdas, Carnicer\u00cdas",
    "sg:phone":"+34 981 34 27 01",
    "sg:postcode":"15500",
    "sg:province":"A Coru\u00f1a",
    "wof:name":"Vi\u00f1as Martinez Jose",
    "wof:placetype":"venue"
},
  "geometry": {"coordinates":[-8.3959693909,43.3714904785],"type":"Point"}
}