{
  "type": "Feature",
  "properties": {
    "iso:country":"ES",
    "sg:address":"Calle de Aguere, 15",
    "sg:city":"Santa Cruz De Tenerife",
    "sg:orig_category":"Abogados",
    "sg:phone":"+34 922 88 22 68",
    "sg:postcode":"38005",
    "sg:province":"Santa Cruz De Tenerife",
    "sg:website":"www.sirventygranados.com",
    "wof:name":"Sirvent-granados Asociados S.l.",
    "wof:placetype":"venue"
},
  "geometry": {"coordinates":[-16.2543754578,28.4647197723],"type":"Point"}
}