{
  "type": "Feature",
  "properties": {
    "addr:full":"Rua Salvador Allende, 5 Acea De Ama La Coru\u00f1a 15174",
    "addr:housenumber":"5",
    "addr:postcode":"15174",
    "addr:street":"Rua Salvador Allende;Corun\u0303A",
    "iso:country":"ES",
    "sg:address":"Rua Salvador Allende, 5",
    "sg:city":"Acea De Ama",
    "sg:orig_category":"Electricidad: Instaladores",
    "sg:phone":"+34 981 66 71 04",
    "sg:postcode":"15174",
    "sg:province":"La Coru\u00f1a",
    "wof:name":"Branelec S.l",
    "wof:placetype":"venue"
},
  "geometry": {"coordinates":[-8.3826389313,43.3110656738],"type":"Point"}
}