{
  "type": "Feature",
  "properties": {
    "addr:full":"Font De Lloscos, S/n Onda Castell\u00f3n 12200",
    "addr:housenumber":"s / n",
    "addr:postcode":"12200",
    "addr:street":"Castello\u0301N",
    "iso:country":"ES",
    "sg:address":"Font De Lloscos, S/n",
    "sg:city":"Onda",
    "sg:orig_category":"Delegados, Agentes De Tr\u00c1nsito, Auxiliares De Transporte Internacional",
    "sg:phone":"+34 964 60 26 56",
    "sg:postcode":"12200",
    "sg:province":"Castell\u00f3n",
    "wof:name":"Aepasa S.l.",
    "wof:placetype":"venue"
},
  "geometry": {"coordinates":[-0.2432307005,39.9604454041],"type":"Point"}
}