{
  "type": "Feature",
  "properties": {
    "iso:country":"ES",
    "sg:address":"Plaz Tula Ruiz Golluri, 12",
    "sg:city":"Puerto De Santa Maria",
    "sg:orig_category":"Farmacias",
    "sg:phone":"+34 956 87 10 86",
    "sg:postcode":"11500",
    "sg:province":"C\u00e1diz",
    "wof:name":"Herederos De Saralegui Echevarria",
    "wof:placetype":"venue"
},
  "geometry": {"coordinates":[-6.2159252167,36.610332489],"type":"Point"}
}