{
  "type": "Feature",
  "properties": {
    "addr:full":"Calle de General Mola, 11 Casas Puerto Villatoro \u00c1vila 05570",
    "addr:housenumber":"11",
    "addr:postcode":"05570",
    "addr:street":"Calle De General Mola",
    "iso:country":"ES",
    "sg:address":"Calle de General Mola, 11",
    "sg:city":"Casas Puerto Villatoro",
    "sg:orig_category":"Carnicer\u00cdas, Carnicer\u00cdas",
    "sg:phone":"+34 920 23 12 07",
    "sg:postcode":"05570",
    "sg:province":"\u00c1vila",
    "wof:name":"Hermanos Periba\u00f1ez C.b.",
    "wof:placetype":"venue"
},
  "geometry": {"coordinates":[-5.1987471581,40.5293006897],"type":"Point"}
}