{
  "type": "Feature",
  "properties": {
    "addr:full":"Calle de Jose Ortega Y Gasset, 80 Madrid Madrid 28006",
    "addr:housenumber":"80",
    "addr:postcode":"madrid;28006",
    "addr:street":"Calle De Jose Ortega Y Gasset",
    "iso:country":"ES",
    "sg:address":"Calle de Jose Ortega Y Gasset, 80",
    "sg:city":"Madrid",
    "sg:orig_category":"Inform\u00c1tica: Soportes De Informaci\u00d3n, Suministros & Accesorios",
    "sg:phone":"+34 914 02 79 40",
    "sg:postcode":"28006",
    "sg:province":"Madrid",
    "sg:website":"www.cleverimpresion.com",
    "wof:name":"Caserio De La Fruta S.a.",
    "wof:placetype":"venue"
},
  "geometry": {"coordinates":[-3.6733379364,40.4296913147],"type":"Point"}
}