{
  "type": "Feature",
  "properties": {
    "addr:full":"Pase Constitucion De (la), 128 Arnedo La Rioja 26580",
    "addr:housenumber":"128",
    "addr:postcode":"26580",
    "addr:street":"Arnedo;Rioja",
    "iso:country":"ES",
    "sg:address":"Pase Constitucion De (la), 128",
    "sg:city":"Arnedo",
    "sg:orig_category":"Ense\u00d1anza: Idiomas",
    "sg:phone":"+34 941 38 43 30",
    "sg:postcode":"26580",
    "sg:province":"La Rioja",
    "wof:name":"Herce Soldevilla Maria Julia",
    "wof:placetype":"venue"
},
  "geometry": {"coordinates":[-2.1070439816,42.2252502441],"type":"Point"}
}