{
  "type": "Feature",
  "properties": {
    "iso:country":"ES",
    "sg:address":"Calle de Claudio Moyano, 5",
    "sg:city":"Valladolid",
    "sg:orig_category":"Fabricaci\u00d3n De Ventanas",
    "sg:phone":"+34 983 35 39 03",
    "sg:postcode":"47001",
    "sg:province":"Valladolid",
    "wof:name":"Meer Lecha-marzo Alfonso De",
    "wof:placetype":"venue"
},
  "geometry": {"coordinates":[-4.7280726433,41.6489524841],"type":"Point"}
}