{
  "type": "Feature",
  "properties": {
    "addr:full":"Pol. Lacorzanilla, S/n Berantevilla \u00c1lava 01218",
    "addr:housenumber":"s",
    "addr:postcode":"01218",
    "addr:street":"/ N;A\u0301Lava",
    "iso:country":"ES",
    "sg:address":"Pol. Lacorzanilla, S/n",
    "sg:city":"Berantevilla",
    "sg:orig_category":"Rectificaci\u00d3n, Mecanizado, Fresado",
    "sg:phone":"+34 945 33 72 97",
    "sg:postcode":"01218",
    "sg:province":"\u00c1lava",
    "wof:name":"Tametyr S.l.",
    "wof:placetype":"venue"
},
  "geometry": {"coordinates":[-2.8839681149,42.682144165],"type":"Point"}
}