{
  "type": "Feature",
  "properties": {
    "addr:full":"Calle de Conde De Altea, 21 Valencia Valencia 46005",
    "addr:housenumber":"21",
    "addr:postcode":"46005",
    "addr:street":"Calle De Conde De Altea",
    "iso:country":"ES",
    "sg:address":"Calle de Conde De Altea, 21",
    "sg:city":"Valencia",
    "sg:orig_category":"Cl\u00cdnicas Dentales",
    "sg:phone":"+34 963 51 77 90",
    "sg:postcode":"46005",
    "sg:province":"Valencia",
    "wof:name":"Monlleo Pons Jose",
    "wof:placetype":"venue"
},
  "geometry": {"coordinates":[-0.3677358925,39.4661407471],"type":"Point"}
}