{
  "type": "Feature",
  "properties": {
    "addr:full":"Carrer de Llibertat, 8 Castelldefels Barcelona 08860",
    "addr:housenumber":"8",
    "addr:postcode":"08860",
    "addr:street":"Carrer De Llibertat",
    "iso:country":"ES",
    "sg:address":"Carrer de Llibertat, 8",
    "sg:city":"Castelldefels",
    "sg:orig_category":"Bancos",
    "sg:phone":"+34 936 64 47 58",
    "sg:postcode":"08860",
    "sg:province":"Barcelona",
    "wof:name":"Banco Popular Espa\u00f1ol S.a.",
    "wof:placetype":"venue"
},
  "geometry": {"coordinates":[1.9767409563,41.2789764404],"type":"Point"}
}