{
  "type": "Feature",
  "properties": {
    "iso:country":"ES",
    "sg:address":"Pol Ind Quiebra Cantaros, 7",
    "sg:city":"Jaen",
    "sg:orig_category":"Empresas De Carpinter\u00cda Met\u00c1lica",
    "sg:phone":"+34 953 23 76 24",
    "sg:postcode":"23001",
    "sg:province":"Ja\u00e9n",
    "wof:name":"Carpinteria Frademo S.l.",
    "wof:placetype":"venue"
},
  "geometry": {"coordinates":[-3.7729189396,37.7662277222],"type":"Point"}
}