{
  "type": "Feature",
  "properties": {
    "addr:full":"Carrer de Gran De Sant Andreu, 91 Barcelona Barcelona 08030",
    "addr:housenumber":"91",
    "addr:postcode":"08030",
    "addr:street":"Carrer De Gran De Sant Andreu",
    "iso:country":"ES",
    "sg:address":"Carrer de Gran De Sant Andreu, 91",
    "sg:city":"Barcelona",
    "sg:orig_category":"Farmacias",
    "sg:phone":"+34 933 45 90 58",
    "sg:postcode":"08030",
    "sg:province":"Barcelona",
    "wof:name":"Castellanos Llorens Francisco Javier",
    "wof:placetype":"venue"
},
  "geometry": {"coordinates":[2.1895310879,41.4302864075],"type":"Point"}
}