{
  "type": "Feature",
  "properties": {
    "addr:full":"Avda Fama, 58 Paz Murcia 30006",
    "addr:housenumber":"58",
    "addr:postcode":"30006",
    "addr:street":"Avda Fama",
    "iso:country":"ES",
    "sg:address":"Avda Fama, 58",
    "sg:city":"Paz",
    "sg:classifiers":[
        {
            "category":"Autos & Motor Vehicles",
            "subcategory":"Automobile Sales",
            "type":"Retail Goods"
        }
    ],
    "sg:phone":"+34 968 23 74 24",
    "sg:postcode":"30006",
    "sg:province":"Murcia",
    "wof:name":"Martinez Carcel Francisco",
    "wof:placetype":"venue"
},
  "geometry": {"coordinates":[-1.1008939743,37.9940185547],"type":"Point"}
}