{
  "type": "Feature",
  "properties": {
    "iso:country":"ES",
    "sg:address":"Av Principat D'andorra, 15",
    "sg:city":"Tarragona",
    "sg:orig_category":"Empresas De Pintura Y Revestimientos",
    "sg:phone":"+34 977 21 57 46",
    "sg:postcode":"43002",
    "sg:province":"Tarragona",
    "wof:name":"Arnuelos Andres Jose Vicente",
    "wof:placetype":"venue"
},
  "geometry": {"coordinates":[1.2441190481,41.122051239],"type":"Point"}
}