{
  "type": "Feature",
  "properties": {
    "iso:country":"ES",
    "sg:address":"Po. Ind Corts, 28",
    "sg:city":"Cabrera Mar",
    "sg:orig_category":"Comercio De Piezas De Recambio Y De Accesorios De Veh\u00cdculos, Veh\u00cdculos Industriales",
    "sg:phone":"+34 937 56 60 90",
    "sg:postcode":"08349",
    "sg:province":"Barcelona",
    "wof:name":"Euma S.l.",
    "wof:placetype":"venue"
},
  "geometry": {"coordinates":[2.3933050632,41.5273513794],"type":"Point"}
}