{
  "type": "Feature",
  "properties": {
    "iso:country":"ES",
    "sg:address":"Carrer de Gombau, 18",
    "sg:city":"Barcelona",
    "sg:orig_category":"Electrodom\u00c9sticos (fabricaci\u00d3n, Al Por Mayor)",
    "sg:phone":"+34 933 19 09 20",
    "sg:postcode":"08003",
    "sg:province":"Barcelona",
    "wof:name":"Electrodomesticos Carders S.l.",
    "wof:placetype":"venue"
},
  "geometry": {"coordinates":[2.1791200638,41.3870697021],"type":"Point"}
}