{
  "type": "Feature",
  "properties": {
    "iso:country":"ES",
    "sg:address":"Calle de Leda, 22",
    "sg:city":"Malaga",
    "sg:orig_category":"Fabricaci\u00d3n De Enlosados, Soler\u00cdas",
    "sg:phone":"+34 952 33 24 00",
    "sg:postcode":"29006",
    "sg:province":"M\u00e1laga",
    "wof:name":"Ceramicas Aparici S.a.",
    "wof:placetype":"venue"
},
  "geometry": {"coordinates":[-4.4664177895,36.7059364319],"type":"Point"}
}