{
  "type": "Feature",
  "properties": {
    "addr:full":"Carr Major, 17 Sort Lleida 25560",
    "addr:housenumber":"17",
    "addr:postcode":"25560",
    "addr:street":"Carr Major",
    "iso:country":"ES",
    "sg:address":"Carr Major, 17",
    "sg:city":"Sort",
    "sg:orig_category":"Alimentaci\u00d3n General (al Por Menor)",
    "sg:phone":"+34 973 62 01 55",
    "sg:postcode":"25560",
    "sg:province":"Lleida",
    "wof:name":"Marsan Colome Margarita",
    "wof:placetype":"venue"
},
  "geometry": {"coordinates":[1.1303659678,42.4118309021],"type":"Point"}
}