{
  "type": "Feature",
  "properties": {
    "iso:country":"ES",
    "sg:address":"Calle de Marques De Nervion, 116",
    "sg:city":"Sevilla",
    "sg:orig_category":"Empresas De Limpieza",
    "sg:phone":"+34 954 93 32 99",
    "sg:postcode":"41005",
    "sg:province":"Sevilla",
    "wof:name":"Auxilim S.l.",
    "wof:placetype":"venue"
},
  "geometry": {"coordinates":[-5.9695177078,37.3774147034],"type":"Point"}
}