{
  "type": "Feature",
  "properties": {
    "addr:full":"Poli Industrial Irurega\u00d1a, 7 Aizoain Navarra 31195",
    "addr:housenumber":"7",
    "addr:postcode":"31195",
    "addr:street":"Iruregan\u0303A",
    "iso:country":"ES",
    "sg:address":"Poli Industrial Irurega\u00d1a, 7",
    "sg:city":"Aizoain",
    "sg:orig_category":"Promotores Constructores",
    "sg:phone":"+34 948 26 06 95",
    "sg:postcode":"31195",
    "sg:province":"Navarra",
    "sg:website":"www.acr.es",
    "wof:name":"Construcciones Acr S.a.",
    "wof:placetype":"venue"
},
  "geometry": {"coordinates":[-1.6867979765,42.8470611572],"type":"Point"}
}