{
  "type": "Feature",
  "properties": {
    "iso:country":"ES",
    "sg:address":"Calle de Menendez Y Pelayo, 9",
    "sg:city":"Coru\u00d1a",
    "sg:orig_category":"Agencias De Viajes",
    "sg:phone":"+34 981 12 62 16",
    "sg:postcode":"15005",
    "sg:province":"A Coru\u00f1a",
    "sg:website":"www.viajesviloria.com",
    "wof:name":"Viajes Viloria S.a.",
    "wof:placetype":"venue"
},
  "geometry": {"coordinates":[-8.4076576233,43.362953186],"type":"Point"}
}