{
  "type": "Feature",
  "properties": {
    "addr:full":"Calle de Granja, 8 Madrid Madrid 28003",
    "addr:housenumber":"8",
    "addr:postcode":"madrid;28003",
    "addr:street":"Calle De Granja",
    "iso:country":"ES",
    "sg:address":"Calle de Granja, 8",
    "sg:city":"Madrid",
    "sg:orig_category":"M\u00c9dicos: Cirug\u00cda Ortop\u00c9dica Y Traumatolog\u00cda",
    "sg:phone":"+34 915 54 77 90",
    "sg:postcode":"28003",
    "sg:province":"Madrid",
    "wof:name":"Aguilar Rodriguez Luis",
    "wof:placetype":"venue"
},
  "geometry": {"coordinates":[-3.7171254158,40.4456634521],"type":"Point"}
}