{
  "type": "Feature",
  "properties": {
    "addr:full":"Cami Via, S/n Viladecans Barcelona 08840",
    "addr:postcode":"08840",
    "addr:street":"Via S / N",
    "iso:country":"ES",
    "sg:address":"Cami Via, S/n",
    "sg:city":"Viladecans",
    "sg:orig_category":"Empresas De Carpinter\u00cda De Madera",
    "sg:phone":"+34 936 33 45 70",
    "sg:postcode":"08840",
    "sg:province":"Barcelona",
    "wof:name":"Fusteria J. Pedrosa S.a.",
    "wof:placetype":"venue"
},
  "geometry": {"coordinates":[2.0139598846,41.3045043945],"type":"Point"}
}