{
  "type": "Feature",
  "properties": {
    "addr:full":"Avda Ciudad De Barcelona, 75 Madrid Madrid 28007",
    "addr:housenumber":"75",
    "addr:postcode":"madrid;28007",
    "addr:street":"Avda Ciudad De Barcelona",
    "iso:country":"ES",
    "sg:address":"Avda Ciudad De Barcelona, 75",
    "sg:city":"Madrid",
    "sg:orig_category":"Tapicer\u00cdas",
    "sg:phone":"+34 914 33 11 58",
    "sg:postcode":"28007",
    "sg:province":"Madrid",
    "wof:name":"Garcia Fernandez Aurelio",
    "wof:placetype":"venue"
},
  "geometry": {"coordinates":[-3.6752030849,40.4015197754],"type":"Point"}
}