{
  "type": "Feature",
  "properties": {
    "addr:full":"Calle de Bodegas, 1 Jerez De La Frontera C\u00e1diz 11402",
    "addr:housenumber":"1",
    "addr:postcode":"11402",
    "addr:street":"Calle De Bodegas",
    "iso:country":"ES",
    "sg:address":"Calle de Bodegas, 1",
    "sg:city":"Jerez De La Frontera",
    "sg:orig_category":"Art\u00cdculos Para Fumadores (al Por Menor)",
    "sg:phone":"+34 956 33 42 25",
    "sg:postcode":"11402",
    "sg:province":"C\u00e1diz",
    "sg:website":"www.doctorcogollo.com",
    "wof:name":"Hermanos Villegas Giraldez S.l.",
    "wof:placetype":"venue"
},
  "geometry": {"coordinates":[-6.1341247559,36.6825408936],"type":"Point"}
}