{
  "type": "Feature",
  "properties": {
    "iso:country":"ES",
    "sg:address":"Av J V Foix, 60",
    "sg:city":"Barcelona",
    "sg:orig_category":"Inmobiliaria (agencias)",
    "sg:phone":"+34 932 52 13 00",
    "sg:postcode":"08034",
    "sg:province":"Barcelona",
    "wof:name":"Lovipro Consulting S.l.",
    "wof:placetype":"venue"
},
  "geometry": {"coordinates":[2.1202430725,41.3954849243],"type":"Point"}
}