{
  "type": "Feature",
  "properties": {
    "addr:full":"La Torneria, 1 Llanes Asturias 33500",
    "addr:postcode":"33500",
    "iso:country":"ES",
    "sg:address":"La Torneria, 1",
    "sg:city":"Llanes",
    "sg:orig_category":"Reposter\u00cdas",
    "sg:phone":"+34 985 40 22 72",
    "sg:postcode":"33500",
    "sg:province":"Asturias",
    "wof:name":"Cozzo  Daniel Roberto",
    "wof:placetype":"venue"
},
  "geometry": {"coordinates":[-4.7549939156,43.4207191467],"type":"Point"}
}