{
  "type": "Feature",
  "properties": {
    "iso:country":"ES",
    "sg:address":"Lagoa, 1",
    "sg:city":"Cambre",
    "sg:orig_category":"Pescader\u00cdas (al Por Menor)",
    "sg:phone":"+34 981 67 42 70",
    "sg:postcode":"15660",
    "sg:province":"La Coru\u00f1a",
    "wof:name":"Pescaderia Dasairas",
    "wof:placetype":"venue"
},
  "geometry": {"coordinates":[-8.3437585831,43.2937660217],"type":"Point"}
}