{
  "type": "Feature",
  "properties": {
    "iso:country":"ES",
    "sg:address":"Av Independencia, 35",
    "sg:city":"Cambrils",
    "sg:orig_category":"Empresas De Pintura Y Revestimientos",
    "sg:phone":"+34 977 36 17 97",
    "sg:postcode":"43850",
    "sg:province":"Tarragona",
    "wof:name":"Ma\u00f1e Boronat Avelino",
    "wof:placetype":"venue"
},
  "geometry": {"coordinates":[1.0483659506,41.0754051208],"type":"Point"}
}