{
  "type": "Feature",
  "properties": {
    "iso:country":"ES",
    "sg:address":"Calle de Repeso, 6",
    "sg:city":"Coru\u00d1a",
    "sg:orig_category":"Comerciantes Al Por Mayor De Vinos, Licores Y Alcoholes",
    "sg:phone":"+34 981 21 32 04",
    "sg:postcode":"15001",
    "sg:province":"La Coru\u00f1a",
    "wof:name":"Amor Carnota Maria",
    "wof:placetype":"venue"
},
  "geometry": {"coordinates":[-8.3928918839,43.3703460693],"type":"Point"}
}