{
  "type": "Feature",
  "properties": {
    "iso:country":"ES",
    "sg:address":"Calle de Cueto, 11",
    "sg:city":"Cueto",
    "sg:orig_category":"Venta, Instalaci\u00d3n De Calefacci\u00d3n",
    "sg:phone":"+34 942 39 17 88",
    "sg:postcode":"39012",
    "sg:province":"Cantabria",
    "wof:name":"Camus Diaz Francisco",
    "wof:placetype":"venue"
},
  "geometry": {"coordinates":[-3.8138566017,43.4779281616],"type":"Point"}
}