{
  "type": "Feature",
  "properties": {
    "addr:full":"Carrer de Llevat, 2 Viladecans Barcelona 08840",
    "addr:housenumber":"2",
    "addr:postcode":"08840",
    "addr:street":"Carrer De Llevat",
    "iso:country":"ES",
    "sg:address":"Carrer de Llevat, 2",
    "sg:city":"Viladecans",
    "sg:orig_category":"Molduras, Junquillos, Listones Y Molduras Perforadas",
    "sg:phone":"+34 936 37 21 26",
    "sg:postcode":"08840",
    "sg:province":"Barcelona",
    "wof:name":"Rodriguez Bertran Miguel",
    "wof:placetype":"venue"
},
  "geometry": {"coordinates":[2.0206270218,41.3180770874],"type":"Point"}
}