{
  "type": "Feature",
  "properties": {
    "addr:full":"El Durazno, 78 Tacoronte Santa Cruz De Tenerife 38350",
    "addr:housenumber":"78",
    "addr:postcode":"38350",
    "addr:street":"El Durazno",
    "iso:country":"ES",
    "sg:address":"El Durazno, 78",
    "sg:city":"Tacoronte",
    "sg:orig_category":"Doctores En Medicina",
    "sg:phone":"+34 922 56 17 60",
    "sg:postcode":"38350",
    "sg:province":"Santa Cruz De Tenerife",
    "wof:name":"Ayala Hernandez Juan Jesus",
    "wof:placetype":"venue"
},
  "geometry": {"coordinates":[-16.4164505005,28.4796466827],"type":"Point"}
}