{
  "type": "Feature",
  "properties": {
    "iso:country":"ES",
    "sg:address":"Calle de Pio Xii (de), 2",
    "sg:city":"San Sebastian De Los Reyes",
    "sg:orig_category":"Supermercados Y Hipermercados",
    "sg:phone":"+34 916 53 75 20",
    "sg:postcode":"28700",
    "sg:province":"Madrid",
    "wof:name":"Salinero Garcia Quintin",
    "wof:placetype":"venue"
},
  "geometry": {"coordinates":[-3.6275839806,40.5458068848],"type":"Point"}
}