{
  "type": "Feature",
  "properties": {
    "addr:full":"Calle de San Pablo, 5 Cordoba C\u00f3rdoba 14002",
    "addr:housenumber":"5",
    "addr:postcode":"14002",
    "addr:street":"Calle De San Pablo;Co\u0301Rdoba",
    "iso:country":"ES",
    "sg:address":"Calle de San Pablo, 5",
    "sg:city":"Cordoba",
    "sg:orig_category":"Persianas Interiores, Exteriores",
    "sg:phone":"+34 957 48 51 11",
    "sg:postcode":"14002",
    "sg:province":"C\u00f3rdoba",
    "wof:name":"Estevez Perez Jose",
    "wof:placetype":"venue"
},
  "geometry": {"coordinates":[-4.7755899429,37.8858413696],"type":"Point"}
}