{
  "type": "Feature",
  "properties": {
    "iso:country":"ES",
    "sg:address":"Calle de Mariana De Pineda, S/n",
    "sg:city":"Dos Hermanas",
    "sg:orig_category":"Farmacias",
    "sg:phone":"+34 955 66 62 64",
    "sg:postcode":"41700",
    "sg:province":"Sevilla",
    "wof:name":"Cabello Cartelle Maria Del Carmen",
    "wof:placetype":"venue"
},
  "geometry": {"coordinates":[-5.9315290451,37.2839317322],"type":"Point"}
}