{
  "type": "Feature",
  "properties": {
    "addr:full":"Ctra M-501 (san Martin De Valdeiglesias), Km. 0004,5 Dehesa Del Sotillo Madrid 28670",
    "addr:postcode":"28670",
    "addr:street":"Ctra M-501;Valdeiglesias Km. 0004,5",
    "iso:country":"ES",
    "sg:address":"Ctra M-501 (san Martin De Valdeiglesias), Km. 0004,5",
    "sg:city":"Dehesa Del Sotillo",
    "sg:orig_category":"Casas Con Estructura De Madera",
    "sg:phone":"+34 916 16 23 83",
    "sg:postcode":"28670",
    "sg:province":"Madrid",
    "sg:website":"www.mcgarden.net",
    "wof:name":"Casas De Madera Mcgarden S.l.",
    "wof:placetype":"venue"
},
  "geometry": {"coordinates":[-3.9017140865,40.3512306213],"type":"Point"}
}