{
  "type": "Feature",
  "properties": {
    "iso:country":"ES",
    "sg:address":"Calle de Gando, 7",
    "sg:city":"Madrid",
    "sg:orig_category":"Molduras, Junquillos, Listones Y Molduras Perforadas",
    "sg:phone":"+34 915 09 33 73",
    "sg:postcode":"28044",
    "sg:province":"Madrid",
    "wof:name":"Explotacion Integral De Hosteleria S.l.",
    "wof:placetype":"venue"
},
  "geometry": {"coordinates":[-3.7671980858,40.3757514954],"type":"Point"}
}