{
  "type": "Feature",
  "properties": {
    "iso:country":"ES",
    "sg:address":"Calle de Leon Y Castillo, 270",
    "sg:city":"Palmas De Gran Canaria",
    "sg:orig_category":"Caf\u00c9s, Bares, Cervecer\u00cdas",
    "sg:phone":"+34 928 29 09 37",
    "sg:postcode":"35005",
    "sg:province":"Las Palmas",
    "wof:name":"Vanyera 3 S.l.",
    "wof:placetype":"venue"
},
  "geometry": {"coordinates":[-15.4281787872,28.1241188049],"type":"Point"}
}