{
  "type": "Feature",
  "properties": {
    "addr:full":"Pl Espanya (d'), 9 Callosa D'en Sarria Alicante 03510",
    "addr:postcode":"03510",
    "addr:street":"Pl",
    "iso:country":"ES",
    "sg:address":"Pl Espanya (d'), 9",
    "sg:city":"Callosa D'en Sarria",
    "sg:orig_category":"Farmacias",
    "sg:phone":"+34 965 88 60 02",
    "sg:postcode":"03510",
    "sg:province":"Alicante",
    "wof:name":"Savall Perez Maria Jesus",
    "wof:placetype":"venue"
},
  "geometry": {"coordinates":[-0.4846130013,38.351524353],"type":"Point"}
}