{
  "type": "Feature",
  "properties": {
    "addr:full":"Avda Montbenidorm, S/n Benidorm Alicante 03500",
    "addr:housenumber":"s / n",
    "addr:postcode":"03500",
    "addr:street":"Avda Montbenidorm",
    "iso:country":"ES",
    "sg:address":"Avda Montbenidorm, S/n",
    "sg:city":"Benidorm",
    "sg:orig_category":"Librer\u00cdas",
    "sg:phone":"+34 966 80 11 24",
    "sg:postcode":"03500",
    "sg:province":"Alicante",
    "wof:name":"Jimenez Gonzalez Romi",
    "wof:placetype":"venue"
},
  "geometry": {"coordinates":[-0.1628389955,38.5324554443],"type":"Point"}
}