{
  "type": "Feature",
  "properties": {
    "iso:country":"ES",
    "sg:address":"Gurutze Kalea, 9",
    "sg:city":"Lazkao",
    "sg:orig_category":"Frutas, Legumbres Frescas Y Tempranas (al Por Menor)",
    "sg:phone":"+34 943 88 15 40",
    "sg:postcode":"20210",
    "sg:province":"Guip\u00f9zcoa",
    "wof:name":"Rodriguez Fernandez Noemi",
    "wof:placetype":"venue"
},
  "geometry": {"coordinates":[-2.1830899715,43.0288391113],"type":"Point"}
}