{
  "type": "Feature",
  "properties": {
    "addr:full":"Plaz San Miguel, S/n Najera La Rioja 26300",
    "addr:housenumber":"s / n",
    "addr:postcode":"26300",
    "addr:street":"Plaz San Miguel;Najera La Rioja",
    "iso:country":"ES",
    "sg:address":"Plaz San Miguel, S/n",
    "sg:city":"Najera",
    "sg:orig_category":"Organismos De Turismo",
    "sg:phone":"+34 941 36 00 41",
    "sg:postcode":"26300",
    "sg:province":"La Rioja",
    "wof:name":"Asociacion Para El Desarrollo Y Promocion Turistica Del Valle Najera San Millan",
    "wof:placetype":"venue"
},
  "geometry": {"coordinates":[-2.7347602844,42.4177055359],"type":"Point"}
}