{
  "type": "Feature",
  "properties": {
    "addr:full":"Calle de Castillo General, 2 Bilbao Vizcaya 48003",
    "addr:housenumber":"2",
    "addr:postcode":"48003",
    "addr:street":"Calle De Castillo General",
    "iso:country":"ES",
    "sg:address":"Calle de Castillo General, 2",
    "sg:city":"Bilbao",
    "sg:orig_category":"Agencias Y Agentes Comerciales, Representantes",
    "sg:phone":"+34 944 15 46 56",
    "sg:postcode":"48003",
    "sg:province":"Vizcaya",
    "wof:name":"Moreno Azcarate Jesus Felix",
    "wof:placetype":"venue"
},
  "geometry": {"coordinates":[-2.9325785637,43.2291870117],"type":"Point"}
}