{
  "type": "Feature",
  "properties": {
    "iso:country":"ES",
    "sg:address":"Rua Oliva (la), 55",
    "sg:city":"Pontevedra",
    "sg:orig_category":"Cl\u00cdnicas Dentales",
    "sg:phone":"+34 986 86 00 89",
    "sg:postcode":"36001",
    "sg:province":"Pontevedra",
    "wof:name":"Himadent Arosa S.l.",
    "wof:placetype":"venue"
},
  "geometry": {"coordinates":[-8.6455593109,42.4295692444],"type":"Point"}
}