{
  "type": "Feature",
  "properties": {
    "addr:full":"Calle de Tiradores, 19 Corral De Calatrava Ciudad Real 13190",
    "addr:housenumber":"19",
    "addr:postcode":"13190",
    "addr:street":"Calle De Tiradores",
    "iso:country":"ES",
    "sg:address":"Calle de Tiradores, 19",
    "sg:city":"Corral De Calatrava",
    "sg:classifiers":[
        {
            "category":"Taxi",
            "type":"Transportation"
        }
    ],
    "sg:phone":"+34 926 83 03 53",
    "sg:postcode":"13190",
    "sg:province":"Ciudad Real",
    "wof:name":"Morales Encinas Francisco",
    "wof:placetype":"venue"
},
  "geometry": {"coordinates":[-4.0805029869,38.8598175049],"type":"Point"}
}