{
  "type": "Feature",
  "properties": {
    "iso:country":"ES",
    "sg:address":"Calle de General Mola, 16",
    "sg:city":"Polan",
    "sg:orig_category":"Cajas Para Embalar",
    "sg:phone":"+34 925 37 00 86",
    "sg:postcode":"45161",
    "sg:province":"Toledo",
    "wof:name":"Caja Rural Provincial De Toledo",
    "wof:placetype":"venue"
},
  "geometry": {"coordinates":[-4.1678490639,39.7888183594],"type":"Point"}
}