{
  "type": "Feature",
  "properties": {
    "addr:full":"Calle de Navas Del Rey, 44 Madrid Madrid 28011",
    "addr:housenumber":"44",
    "addr:postcode":"madrid;28011",
    "addr:street":"Calle De Navas Del Rey",
    "iso:country":"ES",
    "sg:address":"Calle de Navas Del Rey, 44",
    "sg:city":"Madrid",
    "sg:orig_category":"Electricidad, Electr\u00d3nica: Suministros (al Por Menor)",
    "sg:phone":"+34 914 63 11 59",
    "sg:postcode":"28011",
    "sg:province":"Madrid",
    "wof:name":"Comade Electronica Y Dise\u00d1o S.l",
    "wof:placetype":"venue"
},
  "geometry": {"coordinates":[-3.7369709015,40.4081993103],"type":"Point"}
}