{
  "type": "Feature",
  "properties": {
    "iso:country":"ES",
    "sg:address":"Calle de San Nicolas De Olabeaga, 10",
    "sg:city":"Bilbao",
    "sg:orig_category":"Sales (al Por Mayor)",
    "sg:phone":"+34 944 41 63 87",
    "sg:postcode":"48013",
    "sg:province":"Vizcaya",
    "wof:name":"Cafes Sarasola S.a.",
    "wof:placetype":"venue"
},
  "geometry": {"coordinates":[-2.9536070824,43.2649307251],"type":"Point"}
}