{
  "type": "Feature",
  "properties": {
    "addr:full":"Pase Reding, 43 Malaga M\u00e1laga 29016",
    "addr:housenumber":"43",
    "addr:postcode":"29016",
    "addr:street":"Reding;Ma\u0301Laga",
    "iso:country":"ES",
    "sg:address":"Pase Reding, 43",
    "sg:city":"Malaga",
    "sg:orig_category":"M\u00c9dicos: Evaluaci\u00d3n Y Tratamiento Del Dolor",
    "sg:phone":"+34 952 22 45 13",
    "sg:postcode":"29016",
    "sg:province":"M\u00e1laga",
    "wof:name":"Fernandez Martinez Leandro",
    "wof:placetype":"venue"
},
  "geometry": {"coordinates":[-4.4085650444,36.7210617065],"type":"Point"}
}