{
  "type": "Feature",
  "properties": {
    "addr:full":"Calle de Colon, 10 Valencia Valencia 46004",
    "addr:housenumber":"10",
    "addr:postcode":"46004",
    "addr:street":"Calle De Colon",
    "iso:country":"ES",
    "sg:address":"Calle de Colon, 10",
    "sg:city":"Valencia",
    "sg:orig_category":"Abogados",
    "sg:phone":"+34 963 51 86 93",
    "sg:postcode":"46004",
    "sg:province":"Valencia",
    "wof:name":"Guillen Grech Pedro",
    "wof:placetype":"venue"
},
  "geometry": {"coordinates":[-0.3741650879,39.4675865173],"type":"Point"}
}