{
  "type": "Feature",
  "properties": {
    "iso:country":"ES",
    "sg:address":"Avda Salvador Allende, 67",
    "sg:city":"Zaragoza",
    "sg:orig_category":"Art\u00cdculos De Regalo (al Por Menor)",
    "sg:phone":"+34 976 74 16 01",
    "sg:postcode":"50015",
    "sg:province":"Zaragoza",
    "wof:name":"Imagine Shop S.l.",
    "wof:placetype":"venue"
},
  "geometry": {"coordinates":[-0.8771340251,41.6751365662],"type":"Point"}
}