{
  "type": "Feature",
  "properties": {
    "addr:full":"Rua Igrexa, S/n Ferrol La Coru\u00f1a 15402",
    "addr:housenumber":"s / n",
    "addr:postcode":"15402",
    "addr:street":"Rua Igrexa;La Corun\u0303A",
    "iso:country":"ES",
    "sg:address":"Rua Igrexa, S/n",
    "sg:city":"Ferrol",
    "sg:orig_category":"Pescader\u00cdas (al Por Menor)",
    "sg:phone":"+34 981 35 87 40",
    "sg:postcode":"15402",
    "sg:province":"La Coru\u00f1a",
    "wof:name":"Bustabad Freire Juan Benigno",
    "wof:placetype":"venue"
},
  "geometry": {"coordinates":[-8.3034362793,43.5147666931],"type":"Point"}
}