{
  "type": "Feature",
  "properties": {
    "addr:full":"Calle de Clemente Beltran Heredia, 8 Arizgoiti Vizcaya 48970",
    "addr:housenumber":"8",
    "addr:postcode":"48970",
    "addr:street":"Calle De Clemente Beltran Heredia",
    "iso:country":"ES",
    "sg:address":"Calle de Clemente Beltran Heredia, 8",
    "sg:city":"Arizgoiti",
    "sg:orig_category":"Servicio De Salud",
    "sg:phone":"+34 944 40 76 38",
    "sg:postcode":"48970",
    "sg:province":"Vizcaya",
    "wof:name":"Altamira Rodriguez Miren Idoia",
    "wof:placetype":"venue"
},
  "geometry": {"coordinates":[-2.8874425888,43.2361412048],"type":"Point"}
}