{
  "type": "Feature",
  "properties": {
    "iso:country":"ES",
    "sg:address":"Ctra. Medina, Km. 0002,0",
    "sg:city":"Pto Real",
    "sg:orig_category":"Empresas De Carpinter\u00cda Met\u00c1lica",
    "sg:phone":"+34 956 47 49 93",
    "sg:postcode":"11510",
    "sg:province":"C\u00e1diz",
    "wof:name":"Espinosa Gutierrez Jesus",
    "wof:placetype":"venue"
},
  "geometry": {"coordinates":[-6.1980991364,36.5308990479],"type":"Point"}
}