{
  "type": "Feature",
  "properties": {
    "iso:country":"ES",
    "sg:address":"Palma, 40",
    "sg:city":"Montu\u00efri",
    "sg:orig_category":"M\u00c9dicos: Estomatolog\u00cda",
    "sg:phone":"+34 971 64 66 03",
    "sg:postcode":"07230",
    "sg:province":"Islas Baleares",
    "wof:name":"Derka  Alicia",
    "wof:placetype":"venue"
},
  "geometry": {"coordinates":[2.9813709259,39.568977356],"type":"Point"}
}