{
  "type": "Feature",
  "properties": {
    "addr:full":"Plaz Marques, 19 Gijon Asturias 33201",
    "addr:housenumber":"19",
    "addr:postcode":"33201",
    "addr:street":"Marques",
    "iso:country":"ES",
    "sg:address":"Plaz Marques, 19",
    "sg:city":"Gijon",
    "sg:orig_category":"Panader\u00cdas, Panader\u00cdas",
    "sg:phone":"+34 985 34 05 22",
    "sg:postcode":"33201",
    "sg:province":"Asturias",
    "wof:name":"Collada Y Sierra S.l.",
    "wof:placetype":"venue"
},
  "geometry": {"coordinates":[-5.6633501053,43.5448760986],"type":"Point"}
}