{
  "type": "Feature",
  "properties": {
    "addr:full":"Calle de Arca Real, 32 Valladolid Valladolid 47013",
    "addr:housenumber":"32",
    "addr:postcode":"47013",
    "addr:street":"Calle De;Real",
    "iso:country":"ES",
    "sg:address":"Calle de Arca Real, 32",
    "sg:city":"Valladolid",
    "sg:orig_category":"Molduras, Junquillos, Listones Y Molduras Perforadas",
    "sg:phone":"+34 983 27 17 26",
    "sg:postcode":"47013",
    "sg:province":"Valladolid",
    "wof:name":"Alonso Roldan Eliodoro",
    "wof:placetype":"venue"
},
  "geometry": {"coordinates":[-4.7239789963,41.6367034912],"type":"Point"}
}