{
  "type": "Feature",
  "properties": {
    "iso:country":"ES",
    "sg:address":"Carrer de Masia De Can Coll, 14",
    "sg:city":"Sant Vicen\u00c7 Dels Horts",
    "sg:orig_category":"Fabricaci\u00d3n De Moldes Y Modelos",
    "sg:phone":"+34 936 56 20 05",
    "sg:postcode":"08620",
    "sg:province":"Barcelona",
    "wof:name":"Models I Motlles S.l.",
    "wof:placetype":"venue"
},
  "geometry": {"coordinates":[2.009732008,41.3867034912],"type":"Point"}
}