{
  "type": "Feature",
  "properties": {
    "addr:full":"Calle de Gustavo Torner, 12 Alcazar S. Juan Ciudad Real 13600",
    "addr:housenumber":"12",
    "addr:postcode":"13600",
    "addr:street":"Calle De Gustavo Torner;Alcazar S. Juan Ciudad Real",
    "iso:country":"ES",
    "sg:address":"Calle de Gustavo Torner, 12",
    "sg:city":"Alcazar S. Juan",
    "sg:orig_category":"Inform\u00c1tica: Soportes De Informaci\u00d3n, Suministros & Accesorios",
    "sg:phone":"+34 926 55 09 66",
    "sg:postcode":"13600",
    "sg:province":"Ciudad Real",
    "wof:name":"Coremancha C.b.",
    "wof:placetype":"venue"
},
  "geometry": {"coordinates":[-3.1990189552,39.3860054016],"type":"Point"}
}