{
  "type": "Feature",
  "properties": {
    "addr:full":"Avda Terra Cha, 25 Feira Do Monte Lugo 27377",
    "addr:housenumber":"25",
    "addr:postcode":"27377",
    "addr:street":"Avda Terra Cha",
    "iso:country":"ES",
    "sg:address":"Avda Terra Cha, 25",
    "sg:city":"Feira Do Monte",
    "sg:orig_category":"Muebles, Minoristas",
    "sg:phone":"+34 982 52 00 77",
    "sg:postcode":"27377",
    "sg:province":"Lugo",
    "wof:name":"Muebles Lago Cospeito S.l.",
    "wof:placetype":"venue"
},
  "geometry": {"coordinates":[-7.5561051369,43.2364349365],"type":"Point"}
}