{
  "type": "Feature",
  "properties": {
    "addr:full":"Calle de Rosario (del), S/n Taco Santa Cruz De Tenerife 38108",
    "addr:housenumber":"/ n",
    "addr:postcode":"38108",
    "addr:street":"Calle De Rosario Del S",
    "iso:country":"ES",
    "sg:address":"Calle de Rosario (del), S/n",
    "sg:city":"Taco",
    "sg:orig_category":"Transportes A\u00c9reos",
    "sg:phone":"+34 922 61 09 22",
    "sg:postcode":"38108",
    "sg:province":"Santa Cruz De Tenerife",
    "wof:name":"Grupajes Insulares S. A.",
    "wof:placetype":"venue"
},
  "geometry": {"coordinates":[-16.2957706451,28.4491081238],"type":"Point"}
}