{
  "type": "Feature",
  "properties": {
    "addr:full":"Avda Victoria, 2 Madrid Madrid 28023",
    "addr:housenumber":"2",
    "addr:postcode":"28023",
    "addr:street":"Avda Victoria",
    "iso:country":"ES",
    "sg:address":"Avda Victoria, 2",
    "sg:city":"Madrid",
    "sg:orig_category":"Ropa Para Ni\u00d1os (al Por Menor)",
    "sg:phone":"+34 913 07 78 64",
    "sg:postcode":"28023",
    "sg:province":"Madrid",
    "wof:name":"Marisdan Riazor S.l.",
    "wof:placetype":"venue"
},
  "geometry": {"coordinates":[-3.8137290478,40.4670257568],"type":"Point"}
}