{
  "type": "Feature",
  "properties": {
    "iso:country":"ES",
    "sg:address":"Avda Antonio Trueba, 12",
    "sg:city":"San Juan De Muskiz",
    "sg:orig_category":"Talleres: Ropa A Medida",
    "sg:phone":"+34 946 70 68 52",
    "sg:postcode":"48550",
    "sg:province":"Vizcaya",
    "wof:name":"Pe\u00f1a Arran Jose Antonio De La",
    "wof:placetype":"venue"
},
  "geometry": {"coordinates":[-3.1159870625,43.3210525513],"type":"Point"}
}