{
  "type": "Feature",
  "properties": {
    "addr:full":"Calle de Doctor Calzada, 15 Navia Asturias 33710",
    "addr:housenumber":"15",
    "addr:postcode":"33710",
    "addr:street":"Calle De Doctor Calzada",
    "iso:country":"ES",
    "sg:address":"Calle de Doctor Calzada, 15",
    "sg:city":"Navia",
    "sg:orig_category":"Estancos",
    "sg:phone":"+34 985 63 05 14",
    "sg:postcode":"33710",
    "sg:province":"Asturias",
    "wof:name":"Martinez Manso Covadonga",
    "wof:placetype":"venue"
},
  "geometry": {"coordinates":[-6.7247900963,43.540145874],"type":"Point"}
}