{
  "type": "Feature",
  "properties": {
    "iso:country":"ES",
    "sg:address":"Calle de San Vicente Martir, 139",
    "sg:city":"Valencia",
    "sg:orig_category":"Librer\u00cdas",
    "sg:phone":"+34 963 42 26 94",
    "sg:postcode":"46007",
    "sg:province":"Valencia",
    "wof:name":"Libreria Polo S. L.",
    "wof:placetype":"venue"
},
  "geometry": {"coordinates":[-0.3820089996,39.4628715515],"type":"Point"}
}