{
  "type": "Feature",
  "properties": {
    "iso:country":"ES",
    "sg:address":"Carret. Medina-benalup, Km. 0005,5",
    "sg:city":"Malcocinado",
    "sg:orig_category":"Material Y Suministros Para Horticultura, Arboricultura",
    "sg:phone":"+34 956 41 71 88",
    "sg:postcode":"11179",
    "sg:province":"C\u00e1diz",
    "wof:name":"El Cortijo Bio S.l.",
    "wof:placetype":"venue"
},
  "geometry": {"coordinates":[-5.8768339157,36.2939758301],"type":"Point"}
}