{
  "type": "Feature",
  "properties": {
    "iso:country":"ES",
    "sg:address":"Carrer de Floridablanca, 138",
    "sg:city":"Barcelona",
    "sg:orig_category":"M\u00c9dicos: Estomatolog\u00cda",
    "sg:phone":"+34 934 23 25 44",
    "sg:postcode":"08011",
    "sg:province":"Barcelona",
    "wof:name":"Rivilla Palacio Miguel Angel",
    "wof:placetype":"venue"
},
  "geometry": {"coordinates":[2.1623809338,41.3812255859],"type":"Point"}
}