{
  "type": "Feature",
  "properties": {
    "addr:full":"Avgd Del Cami Nou, 28 Xirivella Valencia 46950",
    "addr:housenumber":"28",
    "addr:postcode":"46950",
    "addr:street":"Nou",
    "iso:country":"ES",
    "sg:address":"Avgd Del Cami Nou, 28",
    "sg:city":"Xirivella",
    "sg:orig_category":"Asociaciones Y Clubs Deportivos",
    "sg:phone":"+34 963 50 05 92",
    "sg:postcode":"46950",
    "sg:province":"Valencia",
    "wof:name":"Amachef S.l.",
    "wof:placetype":"venue"
},
  "geometry": {"coordinates":[-0.4267860949,39.467086792],"type":"Point"}
}