{
  "type": "Feature",
  "properties": {
    "iso:country":"ES",
    "sg:address":"Calle de Sebastian Garrido, 2",
    "sg:city":"Montemayor",
    "sg:orig_category":"Molduras, Junquillos, Listones Y Molduras Perforadas",
    "sg:phone":"+34 957 38 40 61",
    "sg:postcode":"14530",
    "sg:province":"C\u00f3rdoba",
    "wof:name":"Cordoba Jimenez Francisco",
    "wof:placetype":"venue"
},
  "geometry": {"coordinates":[-4.6982250214,37.6491699219],"type":"Point"}
}