{
  "type": "Feature",
  "properties": {
    "iso:country":"ES",
    "sg:address":"Calle de Infanta Mercedes, 39",
    "sg:city":"Madrid",
    "sg:orig_category":"Electricidad Veh\u00cdculo",
    "sg:phone":"+34 915 70 43 92",
    "sg:postcode":"28020",
    "sg:province":"Madrid",
    "wof:name":"Talleres V. Marquina S.l.",
    "wof:placetype":"venue"
},
  "geometry": {"coordinates":[-3.698371172,40.4559707642],"type":"Point"}
}