{
  "type": "Feature",
  "properties": {
    "addr:full":"Ctra Valencia, Km. 0018,8 Vilamarxant Valencia 46191",
    "addr:postcode":"46191",
    "addr:street":"Ctra Valencia Km. 0018,8",
    "iso:country":"ES",
    "sg:address":"Ctra Valencia, Km. 0018,8",
    "sg:city":"Vilamarxant",
    "sg:orig_category":"Refiner\u00cdas De Petr\u00d3leo",
    "sg:phone":"+34 962 71 51 06",
    "sg:postcode":"46191",
    "sg:province":"Valencia",
    "wof:name":"Petrolgainer S.l.",
    "wof:placetype":"venue"
},
  "geometry": {"coordinates":[-0.6206359863,39.5667228699],"type":"Point"}
}