{
  "type": "Feature",
  "properties": {
    "addr:full":"Calle de Beneficiados, 26 S. Clemente Cuenca 16600",
    "addr:housenumber":"26",
    "addr:postcode":"16600",
    "addr:street":"Calle De Beneficiados;S. Clemente Cuenca",
    "iso:country":"ES",
    "sg:address":"Calle de Beneficiados, 26",
    "sg:city":"S. Clemente",
    "sg:orig_category":"Producci\u00d3n, Venta De Productos De Agricultura Biol\u00d3gica",
    "sg:phone":"+34 969 30 03 77",
    "sg:postcode":"16600",
    "sg:province":"Cuenca",
    "wof:name":"Villarcantos S.l.",
    "wof:placetype":"venue"
},
  "geometry": {"coordinates":[-2.4322650433,39.4018135071],"type":"Point"}
}