{
  "type": "Feature",
  "properties": {
    "addr:full":"Calle de Bernarda Alba, 23 Granada Granada 18007",
    "addr:housenumber":"23",
    "addr:postcode":"18007",
    "addr:street":"Calle De Bernarda Alba",
    "iso:country":"ES",
    "sg:address":"Calle de Bernarda Alba, 23",
    "sg:city":"Granada",
    "sg:orig_category":"Agencias Y Agentes Comerciales, Representantes",
    "sg:phone":"+34 958 12 04 23",
    "sg:postcode":"18007",
    "sg:province":"Granada",
    "wof:name":"Sanchez Vargas Alberto",
    "wof:placetype":"venue"
},
  "geometry": {"coordinates":[-3.5981180668,37.1563606262],"type":"Point"}
}