{
  "type": "Feature",
  "properties": {
    "addr:full":"Pol Ind Martiartu I, S/n Arrigorriaga Vizcaya 48480",
    "addr:housenumber":"s",
    "addr:postcode":"48480",
    "addr:street":"/ N",
    "iso:country":"ES",
    "sg:address":"Pol Ind Martiartu I, S/n",
    "sg:city":"Arrigorriaga",
    "sg:orig_category":"Tapicer\u00cdas",
    "sg:phone":"+34 946 71 50 29",
    "sg:postcode":"48480",
    "sg:province":"Vizcaya",
    "wof:name":"Martinez Rodriguez Teodoro",
    "wof:placetype":"venue"
},
  "geometry": {"coordinates":[-2.8893239498,43.2034988403],"type":"Point"}
}