{
  "type": "Feature",
  "properties": {
    "iso:country":"ES",
    "sg:address":"Calle de Buztintxulo, 65",
    "sg:city":"Donostia-san Sebastian",
    "sg:orig_category":"Afiladoras, Pulidoras Y Bru\u00d1idoras",
    "sg:phone":"+34 943 32 27 42",
    "sg:postcode":"20015",
    "sg:province":"Guip\u00f9zcoa",
    "wof:name":"Lazaro Martinez Juncal",
    "wof:placetype":"venue"
},
  "geometry": {"coordinates":[-1.9511171579,43.3125305176],"type":"Point"}
}