{
  "type": "Feature",
  "properties": {
    "iso:country":"ES",
    "sg:address":"Ctra Bilbao-plentzia, 19",
    "sg:city":"Asua-lauroeta",
    "sg:orig_category":"Abrasivos Y Superabrasivos (fabricaci\u00d3n, Al Por Mayor)",
    "sg:phone":"+34 944 71 12 50",
    "sg:postcode":"48950",
    "sg:province":"Vizcaya",
    "sg:website":"www.abrasivosmendiola.com",
    "wof:name":"Abrasivos Mendiola S. L.",
    "wof:placetype":"venue"
},
  "geometry": {"coordinates":[-2.946861,43.302479],"type":"Point"}
}