{
  "type": "Feature",
  "properties": {
    "addr:full":"Calle de Maestro Serrano, 1 Almeria Almer\u00eda 04004",
    "addr:housenumber":"1",
    "addr:postcode":"04004",
    "addr:street":"Calle De Maestro Serrano",
    "iso:country":"ES",
    "sg:address":"Calle de Maestro Serrano, 1",
    "sg:city":"Almeria",
    "sg:orig_category":"Centros De Coordinaci\u00d3n",
    "sg:phone":"+34 950 28 18 62",
    "sg:postcode":"04004",
    "sg:province":"Almer\u00eda",
    "wof:name":"Ruiz Gesco S.l.",
    "wof:placetype":"venue"
},
  "geometry": {"coordinates":[-2.4615490437,36.83385849],"type":"Point"}
}