{
  "type": "Feature",
  "properties": {
    "addr:full":"Rufino Cano De Rueda, 10 Turegano Segovia 40370",
    "addr:housenumber":"10",
    "addr:postcode":"40370",
    "addr:street":"Turegano Segovia",
    "iso:country":"ES",
    "sg:address":"Rufino Cano De Rueda, 10",
    "sg:city":"Turegano",
    "sg:orig_category":"Cr\u00cda De Bovinos",
    "sg:phone":"+34 921 50 04 35",
    "sg:postcode":"40370",
    "sg:province":"Segovia",
    "wof:name":"C.b. Jacel",
    "wof:placetype":"venue"
},
  "geometry": {"coordinates":[-4.0088391304,41.1547203064],"type":"Point"}
}