{
  "type": "Feature",
  "properties": {
    "addr:full":"Avda Ejercito, 6 Villafranca De Los Barros Badajoz 06220",
    "addr:housenumber":"6",
    "addr:postcode":"06220",
    "addr:street":"Avda Ejercito",
    "iso:country":"ES",
    "sg:address":"Avda Ejercito, 6",
    "sg:city":"Villafranca De Los Barros",
    "sg:orig_category":"Art\u00cdculos Funerarios (al Por Menor)",
    "sg:phone":"+34 924 52 54 55",
    "sg:postcode":"06220",
    "sg:province":"Badajoz",
    "wof:name":"Lopez Martinez Elias",
    "wof:placetype":"venue"
},
  "geometry": {"coordinates":[-6.3463487625,38.5599708557],"type":"Point"}
}