{
  "type": "Feature",
  "properties": {
    "iso:country":"ES",
    "sg:address":"Carrer de Tuset, 36",
    "sg:city":"Barcelona",
    "sg:orig_category":"Publicidad (soportes Y Gesti\u00d3n)",
    "sg:phone":"+34 934 15 62 62",
    "sg:postcode":"08006",
    "sg:province":"Barcelona",
    "sg:website":"www.impart.es",
    "wof:name":"Gabinete De Prensa Y Agencia De Publicidad Impart S.l.",
    "wof:placetype":"venue"
},
  "geometry": {"coordinates":[2.1511220932,41.3967323303],"type":"Point"}
}