{
  "type": "Feature",
  "properties": {
    "addr:full":"Avda Reyes Catolicos, 25 Santa Cruz De Tenerife Santa Cruz De Tenerife 38005",
    "addr:housenumber":"25",
    "addr:postcode":"38005",
    "addr:street":"Avda Reyes Catolicos",
    "iso:country":"ES",
    "sg:address":"Avda Reyes Catolicos, 25",
    "sg:city":"Santa Cruz De Tenerife",
    "sg:orig_category":"Asesor\u00cda Sobre Comunicaci\u00d3n De Empresas",
    "sg:phone":"+34 922 22 84 29",
    "sg:postcode":"38005",
    "sg:province":"Santa Cruz De Tenerife",
    "wof:name":"Proyectos Asesoria Y Servicios S.a.",
    "wof:placetype":"venue"
},
  "geometry": {"coordinates":[-16.263551712,28.4596824646],"type":"Point"}
}