{
  "type": "Feature",
  "properties": {
    "addr:full":"Calle de Ca\u00d1izares, 1 Madrid Madrid 28012",
    "addr:housenumber":"1",
    "addr:postcode":"28012",
    "addr:street":"Calle De Can\u0303Izares",
    "iso:country":"ES",
    "sg:address":"Calle de Ca\u00d1izares, 1",
    "sg:city":"Madrid",
    "sg:orig_category":"Telas (al Por Mayor)",
    "sg:phone":"+34 914 29 66 63",
    "sg:postcode":"28012",
    "sg:province":"Madrid",
    "wof:name":"Tejidos Y Novedades Paredes S.l.",
    "wof:placetype":"venue"
},
  "geometry": {"coordinates":[-3.7014100552,40.413230896],"type":"Point"}
}