{
  "type": "Feature",
  "properties": {
    "addr:full":"Avda Vicente Aleixandre, 16 San Fernando De Henares Madrid 28830",
    "addr:housenumber":"16",
    "addr:postcode":"28830",
    "addr:street":"Avda Vicente Aleixandre",
    "iso:country":"ES",
    "sg:address":"Avda Vicente Aleixandre, 16",
    "sg:city":"San Fernando De Henares",
    "sg:orig_category":"Aparatos, Sistemas De Tele",
    "sg:phone":"+34 916 71 23 13",
    "sg:postcode":"28830",
    "sg:province":"Madrid",
    "wof:name":"Palatino Seguridad S.l.",
    "wof:placetype":"venue"
},
  "geometry": {"coordinates":[-3.5220439434,40.4189834595],"type":"Point"}
}