{
  "type": "Feature",
  "properties": {
    "iso:country":"ES",
    "sg:address":"Carrer de Balmes, 246",
    "sg:city":"Barcelona",
    "sg:orig_category":"M\u00c9dicos: Gastroenterolog\u00cda Y Hepatolog\u00cda (aparato Digestivo)",
    "sg:phone":"+34 932 18 81 31",
    "sg:postcode":"08006",
    "sg:province":"Barcelona",
    "wof:name":"Alba Berenguer Jose",
    "wof:placetype":"venue"
},
  "geometry": {"coordinates":[2.1500980854,41.3995094299],"type":"Point"}
}