{
  "type": "Feature",
  "properties": {
    "iso:country":"ES",
    "sg:address":"Calle de Doctor Prado Villapol, 32",
    "sg:city":"Vicedo",
    "sg:orig_category":"Supermercados Y Hipermercados",
    "sg:phone":"+34 982 59 03 88",
    "sg:postcode":"27860",
    "sg:province":"Lugo",
    "wof:name":"Pena Rodriguez Beatriz",
    "wof:placetype":"venue"
},
  "geometry": {"coordinates":[-7.6637530327,43.7321472168],"type":"Point"}
}