{
  "type": "Feature",
  "properties": {
    "iso:country":"ES",
    "sg:address":"Trva Cinco Villas, 8",
    "sg:city":"Avila",
    "sg:orig_category":"Venta, Instalaci\u00d3n De Calefacci\u00d3n",
    "sg:phone":"+34 920 25 58 69",
    "sg:postcode":"05003",
    "sg:province":"\u00c1vila",
    "wof:name":"Torres Diaz-guerra Jose Carlos",
    "wof:placetype":"venue"
},
  "geometry": {"coordinates":[-4.6972460747,40.6469497681],"type":"Point"}
}