{
  "type": "Feature",
  "properties": {
    "addr:full":"Carrer de Ribera D'ebre, 4 Hostalets Tarragona 43151",
    "addr:housenumber":"4",
    "addr:postcode":"43151",
    "addr:street":"Carrer De Ribera D'Ebre",
    "iso:country":"ES",
    "sg:address":"Carrer de Ribera D'ebre, 4",
    "sg:city":"Hostalets",
    "sg:orig_category":"Contenedores (mercanc\u00cdas)",
    "sg:phone":"+34 977 62 68 99",
    "sg:postcode":"43151",
    "sg:province":"Tarragona",
    "wof:name":"Ortega Sanchez Francisco",
    "wof:placetype":"venue"
},
  "geometry": {"coordinates":[1.2431160212,41.1229705811],"type":"Point"}
}