{
  "type": "Feature",
  "properties": {
    "iso:country":"ES",
    "sg:address":"Praz Victoriano Garcia Marti, 7",
    "sg:city":"Pobra Do Carami\u00e7al",
    "sg:orig_category":"Caf\u00c9s, Bares, Cervecer\u00cdas",
    "sg:phone":"+34 981 83 09 14",
    "sg:postcode":"15940",
    "sg:province":"A Coru\u00f1a",
    "wof:name":"Tele Renta S.l.",
    "wof:placetype":"venue"
},
  "geometry": {"coordinates":[-8.9380235672,42.6031036377],"type":"Point"}
}