{
  "type": "Feature",
  "properties": {
    "iso:country":"ES",
    "sg:address":"Plaz Cristo Rey, 1",
    "sg:city":"Zamora",
    "sg:orig_category":"Ingeniero",
    "sg:phone":"+34 980 51 09 71",
    "sg:postcode":"49018",
    "sg:province":"Zamora",
    "wof:name":"Martin Castre\u00f1o Faustino",
    "wof:placetype":"venue"
},
  "geometry": {"coordinates":[-5.7367630005,41.506603241],"type":"Point"}
}