{
  "type": "Feature",
  "properties": {
    "addr:full":"Calle de Francisco Navacerrada, 42 Madrid Madrid 28028",
    "addr:housenumber":"42",
    "addr:postcode":"madrid;28028",
    "addr:street":"Calle De Francisco Navacerrada",
    "iso:country":"ES",
    "sg:address":"Calle de Francisco Navacerrada, 42",
    "sg:city":"Madrid",
    "sg:orig_category":"Alimentaci\u00d3n General (al Por Menor)",
    "sg:phone":"+34 917 25 78 13",
    "sg:postcode":"28028",
    "sg:province":"Madrid",
    "wof:name":"Wu  Cheng Zhou",
    "wof:placetype":"venue"
},
  "geometry": {"coordinates":[-3.6676640511,40.4310874939],"type":"Point"}
}