{
  "type": "Feature",
  "properties": {
    "iso:country":"ES",
    "sg:address":"Carr Autonomia, 4",
    "sg:city":"Santa Margalida",
    "sg:orig_category":"Contables",
    "sg:phone":"+34 971 52 37 41",
    "sg:postcode":"07450",
    "sg:province":"Islas Baleares",
    "wof:name":"Pastor Perello Sebastian",
    "wof:placetype":"venue"
},
  "geometry": {"coordinates":[3.1049470901,39.7045783997],"type":"Point"}
}