{
  "type": "Feature",
  "properties": {
    "iso:country":"ES",
    "sg:address":"Calle de Sol (del), 11",
    "sg:city":"Linea De La Concepcion",
    "sg:orig_category":"Inmobiliaria (agencias)",
    "sg:phone":"+34 956 17 59 10",
    "sg:postcode":"11300",
    "sg:province":"C\u00e1diz",
    "wof:name":"V & V Gestion Inmobiliaria C.b.",
    "wof:placetype":"venue"
},
  "geometry": {"coordinates":[-5.3491616249,36.1619949341],"type":"Point"}
}