{
  "type": "Feature",
  "properties": {
    "iso:country":"ES",
    "sg:address":"Calle de Canciller Ayala, 3",
    "sg:city":"Vitoria-gasteiz",
    "sg:orig_category":"Perfumer\u00cda (al Por Menor)",
    "sg:phone":"+34 945 27 34 35",
    "sg:postcode":"01004",
    "sg:province":"\u00c1lava",
    "wof:name":"Gil Iturricha Maria Teresa",
    "wof:placetype":"venue"
},
  "geometry": {"coordinates":[-2.6670725346,42.8434524536],"type":"Point"}
}