{
  "type": "Feature",
  "properties": {
    "addr:full":"Calle de Profesor Jesus Neira, 4 Pola De Lena Asturias 33630",
    "addr:housenumber":"4",
    "addr:postcode":"33630",
    "addr:street":"Calle De Profesor Jesus Neira",
    "iso:country":"ES",
    "sg:address":"Calle de Profesor Jesus Neira, 4",
    "sg:city":"Pola De Lena",
    "sg:orig_category":"Cristaler\u00cdas",
    "sg:phone":"+34 985 49 16 49",
    "sg:postcode":"33630",
    "sg:province":"Asturias",
    "wof:name":"Oliveira Mateo Arturo",
    "wof:placetype":"venue"
},
  "geometry": {"coordinates":[-5.827398777,43.1620330811],"type":"Point"}
}