{
  "type": "Feature",
  "properties": {
    "iso:country":"ES",
    "sg:address":"Calle de Valladolid (de), 27",
    "sg:city":"Alcobendas",
    "sg:orig_category":"Chapa Y Pintura Veh\u00cdculos",
    "sg:phone":"+34 916 52 66 07",
    "sg:postcode":"28100",
    "sg:province":"Madrid",
    "wof:name":"Martinez Alocen Antonio",
    "wof:placetype":"venue"
},
  "geometry": {"coordinates":[-3.6328029633,40.5436210632],"type":"Point"}
}