{
  "type": "Feature",
  "properties": {
    "iso:country":"ES",
    "sg:address":"Granada, 6",
    "sg:city":"Montilla",
    "sg:orig_category":"Restaurantes",
    "sg:phone":"+34 957 65 62 61",
    "sg:postcode":"14550",
    "sg:province":"C\u00f3rdoba",
    "wof:name":"Aguayo Mu\u00f1oz Miguel Angel",
    "wof:placetype":"venue"
},
  "geometry": {"coordinates":[-4.6310343742,37.5867729187],"type":"Point"}
}