{
  "type": "Feature",
  "properties": {
    "iso:country":"ES",
    "sg:address":"Calle de Pintor Ribera, 1",
    "sg:city":"Alberic",
    "sg:orig_category":"Aguas (distribuci\u00d3n, Servicios)",
    "sg:phone":"+34 962 44 00 19",
    "sg:postcode":"46260",
    "sg:province":"Valencia",
    "wof:name":"Empresa General Valenciana Del Agua S.a.",
    "wof:placetype":"venue"
},
  "geometry": {"coordinates":[-0.5195519924,39.1152267456],"type":"Point"}
}