{
  "type": "Feature",
  "properties": {
    "iso:country":"ES",
    "sg:address":"Calle de San Vicente Martir, 58",
    "sg:city":"Valencia",
    "sg:orig_category":"\u00d3ptica: Instrumentos (fabricaci\u00d3n)",
    "sg:phone":"+34 963 52 09 34",
    "sg:postcode":"46002",
    "sg:province":"Valencia",
    "sg:website":"www.centroauditivoleones.com",
    "wof:name":"Optica Y Acustica Mencheta S.l.",
    "wof:placetype":"venue"
},
  "geometry": {"coordinates":[-0.3785839975,39.4701423645],"type":"Point"}
}