{
  "type": "Feature",
  "properties": {
    "iso:country":"ES",
    "sg:address":"Ctra Madrid, S/n",
    "sg:city":"Pe\u00e7aranda De Bracamonte",
    "sg:orig_category":"Molinos",
    "sg:phone":"+34 923 54 05 53",
    "sg:postcode":"37300",
    "sg:province":"Salamanca",
    "wof:name":"Manzano Martin Pedro",
    "wof:placetype":"venue"
},
  "geometry": {"coordinates":[-5.1915640831,40.9067497253],"type":"Point"}
}