{
  "type": "Feature",
  "properties": {
    "iso:country":"ES",
    "sg:address":"Calle de Canonigo Rafael Pastor, 11",
    "sg:city":"Tobarra",
    "sg:orig_category":"Transportes Frigor\u00cdficos",
    "sg:phone":"+34 967 32 53 23",
    "sg:postcode":"02500",
    "sg:province":"Albacete",
    "wof:name":"Alca\u00f1iz Honrubia Jose",
    "wof:placetype":"venue"
},
  "geometry": {"coordinates":[-1.6950726509,38.5954933167],"type":"Point"}
}