{
  "type": "Feature",
  "properties": {
    "addr:full":"Plaz Campo De La Iglesia, 32 Montijo Badajoz 06480",
    "addr:housenumber":"32",
    "addr:postcode":"06480",
    "addr:street":"Iglesia",
    "iso:country":"ES",
    "sg:address":"Plaz Campo De La Iglesia, 32",
    "sg:city":"Montijo",
    "sg:orig_category":"Zapatos (al Por Menor)",
    "sg:phone":"+34 924 45 45 71",
    "sg:postcode":"06480",
    "sg:province":"Badajoz",
    "wof:name":"Garay Bautista Andres",
    "wof:placetype":"venue"
},
  "geometry": {"coordinates":[-6.6062841415,38.9077644348],"type":"Point"}
}