{
  "type": "Feature",
  "properties": {
    "addr:full":"Avda Constitucion, 193 Valencia Valencia 46019",
    "addr:housenumber":"193",
    "addr:postcode":"46019",
    "addr:street":"Avda Constitucion",
    "iso:country":"ES",
    "sg:address":"Avda Constitucion, 193",
    "sg:city":"Valencia",
    "sg:orig_category":"Empresas De Carpinter\u00cda De Madera",
    "sg:phone":"+34 963 65 01 90",
    "sg:postcode":"46019",
    "sg:province":"Valencia",
    "wof:name":"Corell Rodrigo Jaime",
    "wof:placetype":"venue"
},
  "geometry": {"coordinates":[-0.3719530106,39.4947814941],"type":"Point"}
}