{
  "type": "Feature",
  "properties": {
    "iso:country":"ES",
    "sg:address":"Carr Sant Francesc, 83",
    "sg:city":"Picanya",
    "sg:orig_category":"Controles De Edificaci\u00d3n (construcci\u00d3n, Seguridad)",
    "sg:phone":"+34 961 59 25 11",
    "sg:postcode":"46210",
    "sg:province":"Valencia",
    "wof:name":"Tordera Tarazona Salvador",
    "wof:placetype":"venue"
},
  "geometry": {"coordinates":[-0.437011987,39.4335289001],"type":"Point"}
}