{
  "type": "Feature",
  "properties": {
    "addr:full":"Av Herois De 1808 (dels), 34 Arbo\u00e7 Tarragona 43720",
    "addr:housenumber":"34",
    "addr:postcode":"43720",
    "addr:street":"Av Herois De 1808 Dels",
    "iso:country":"ES",
    "sg:address":"Av Herois De 1808 (dels), 34",
    "sg:city":"Arbo\u00e7",
    "sg:orig_category":"Peleter\u00cdas",
    "sg:phone":"+34 977 67 05 03",
    "sg:postcode":"43720",
    "sg:province":"Tarragona",
    "wof:name":"Modas Serrano S.a.",
    "wof:placetype":"venue"
},
  "geometry": {"coordinates":[1.6022880077,41.264465332],"type":"Point"}
}