{
  "type": "Feature",
  "properties": {
    "iso:country":"ES",
    "sg:address":"Calle de Don Juan De Austria, 26",
    "sg:city":"Almeria",
    "sg:orig_category":"Cl\u00cdnicas M\u00c9dicas",
    "sg:phone":"+34 950 23 79 35",
    "sg:postcode":"04003",
    "sg:province":"Almer\u00eda",
    "wof:name":"Forte Lopez Inmaculada",
    "wof:placetype":"venue"
},
  "geometry": {"coordinates":[-2.4644839764,36.8456344604],"type":"Point"}
}