{
  "type": "Feature",
  "properties": {
    "addr:full":"Calle de Maestro Tomas Breton, S/n Churriana M\u00e1laga 29140",
    "addr:housenumber":"s",
    "addr:postcode":"29140",
    "addr:street":"Calle De Maestro Tomas Breton;/ N",
    "iso:country":"ES",
    "sg:address":"Calle de Maestro Tomas Breton, S/n",
    "sg:city":"Churriana",
    "sg:orig_category":"Promotores Constructores",
    "sg:phone":"+34 952 43 70 78",
    "sg:postcode":"29140",
    "sg:province":"M\u00e1laga",
    "sg:website":"www.meferbis.com",
    "wof:name":"Construcciones Meserbis S.l.",
    "wof:placetype":"venue"
},
  "geometry": {"coordinates":[-4.5045089722,36.6622009277],"type":"Point"}
}