{
  "type": "Feature",
  "properties": {
    "iso:country":"ES",
    "sg:address":"Parque De Roma, S/n",
    "sg:city":"Zaragoza",
    "sg:orig_category":"Centros Empresariales",
    "sg:phone":"+34 976 33 00 78",
    "sg:postcode":"50010",
    "sg:province":"Zaragoza",
    "wof:name":"Confederacion De La Peque\u00d1a Y Mediana Empresa Aragonesa",
    "wof:placetype":"venue"
},
  "geometry": {"coordinates":[-0.8985379934,41.6495132446],"type":"Point"}
}