{
  "type": "Feature",
  "properties": {
    "addr:full":"Calle de Santo Angel, 2 Madrid Madrid 28043",
    "addr:housenumber":"2",
    "addr:postcode":"28043",
    "addr:street":"Calle De Santo Angel",
    "iso:country":"ES",
    "sg:address":"Calle de Santo Angel, 2",
    "sg:city":"Madrid",
    "sg:orig_category":"Farmacias",
    "sg:phone":"+34 913 88 25 82",
    "sg:postcode":"28043",
    "sg:province":"Madrid",
    "wof:name":"Diaz Luengo Julia",
    "wof:placetype":"venue"
},
  "geometry": {"coordinates":[-3.6582510471,40.4581832886],"type":"Point"}
}