{
  "type": "Feature",
  "properties": {
    "addr:full":"Calle de Alfonso I, 27 Zaragoza Zaragoza 50003",
    "addr:housenumber":"27",
    "addr:postcode":"50003",
    "addr:street":"Calle De Alfonso I",
    "iso:country":"ES",
    "sg:address":"Calle de Alfonso I, 27",
    "sg:city":"Zaragoza",
    "sg:orig_category":"Abogados",
    "sg:phone":"+34 976 20 34 81",
    "sg:postcode":"50003",
    "sg:province":"Zaragoza",
    "wof:name":"Ortiz De Zarate Ortiz De Zarate Juan Pablo",
    "wof:placetype":"venue"
},
  "geometry": {"coordinates":[-0.8804398179,41.6547584534],"type":"Point"}
}