{
  "type": "Feature",
  "properties": {
    "iso:country":"ES",
    "sg:address":"Carr Ciutadans, 17",
    "sg:city":"Girona",
    "sg:orig_category":"Fotocopias, Reprograf\u00cda",
    "sg:phone":"+34 972 20 04 54",
    "sg:postcode":"17004",
    "sg:province":"Girona",
    "wof:name":"Campistol Gurt Gloria",
    "wof:placetype":"venue"
},
  "geometry": {"coordinates":[2.8254699707,41.984375],"type":"Point"}
}