{
  "type": "Feature",
  "properties": {
    "addr:full":"Calle de Castellanos, 41 Valdepe\u00f1as Ciudad Real 13300",
    "addr:housenumber":"41",
    "addr:postcode":"13300",
    "addr:street":"Calle De Castellanos",
    "iso:country":"ES",
    "sg:address":"Calle de Castellanos, 41",
    "sg:city":"Valdepe\u00f1as",
    "sg:orig_category":"M\u00c9dicos: Ginecolog\u00cda Y Obstetricia",
    "sg:phone":"+34 926 32 23 40",
    "sg:postcode":"13300",
    "sg:province":"Ciudad Real",
    "wof:name":"Aparicio Salmeron Jose Miguel",
    "wof:placetype":"venue"
},
  "geometry": {"coordinates":[-3.3846795559,38.7632255554],"type":"Point"}
}