{
  "type": "Feature",
  "properties": {
    "iso:country":"ES",
    "sg:address":"Ptge Nogues, 25",
    "sg:city":"Barcelona",
    "sg:orig_category":"Asilos De Ancianos. Centros Privados",
    "sg:phone":"+34 932 19 86 00",
    "sg:postcode":"08025",
    "sg:province":"Barcelona",
    "sg:website":"www.residenciasgeriatricas.com",
    "wof:name":"Geriatric Nogues S.l.",
    "wof:placetype":"venue"
},
  "geometry": {"coordinates":[2.1661670208,41.4079055786],"type":"Point"}
}