{
  "type": "Feature",
  "properties": {
    "addr:full":"Calle de Juan De La Cierva, S/n Estepona M\u00e1laga 29680",
    "addr:housenumber":"s / n",
    "addr:postcode":"29680",
    "addr:street":"Calle De Juan De La Cierva",
    "iso:country":"ES",
    "sg:address":"Calle de Juan De La Cierva, S/n",
    "sg:city":"Estepona",
    "sg:orig_category":"Mec\u00c1nico Del Autom\u00d3vil",
    "sg:phone":"+34 952 80 28 08",
    "sg:postcode":"29680",
    "sg:province":"M\u00e1laga",
    "wof:name":"Pacnoril S.l.",
    "wof:placetype":"venue"
},
  "geometry": {"coordinates":[-5.1662540436,36.4297218323],"type":"Point"}
}