{
  "type": "Feature",
  "properties": {
    "iso:country":"ES",
    "sg:address":"Calle de Narrica, 15",
    "sg:city":"Donostia-san Sebastian",
    "sg:orig_category":"Laboratorios Y Trabajos De Fotograf\u00cda, V\u00cddeo Y Cine",
    "sg:phone":"+34 943 42 21 26",
    "sg:postcode":"20003",
    "sg:province":"Guip\u00f9zcoa",
    "wof:name":"Aguirre Arratibel Jose Maria",
    "wof:placetype":"venue"
},
  "geometry": {"coordinates":[-1.9841046333,43.3231391907],"type":"Point"}
}