{
  "type": "Feature",
  "properties": {
    "iso:country":"ES",
    "sg:address":"Burgos, 5",
    "sg:city":"Ibi",
    "sg:orig_category":"Fabricaci\u00d3n, Venta De Cuadros, Accesorios Para Enmarcar",
    "sg:phone":"+34 965 55 22 72",
    "sg:postcode":"03440",
    "sg:province":"Alicante",
    "wof:name":"Decuadro Decoracion S.l.",
    "wof:placetype":"venue"
},
  "geometry": {"coordinates":[-0.601023972,38.6077651978],"type":"Point"}
}