{
  "type": "Feature",
  "properties": {
    "addr:full":"Ctra. Murcia-granada, Km. 0001,0 Velez-rubio Almer\u00eda 04820",
    "addr:postcode":"04820",
    "addr:street":"Ctra. Murcia-Granada Km. 0001,0 Velez-Rubio Almeri\u0301A",
    "iso:country":"ES",
    "sg:address":"Ctra. Murcia-granada, Km. 0001,0",
    "sg:city":"Velez-rubio",
    "sg:orig_category":"Negocio De Materiales De Construcci\u00d3n",
    "sg:phone":"+34 950 41 03 34",
    "sg:postcode":"04820",
    "sg:province":"Almer\u00eda",
    "wof:name":"Ramon Lopez Andres",
    "wof:placetype":"venue"
},
  "geometry": {"coordinates":[-2.0770230293,37.6492118835],"type":"Point"}
}