{
  "type": "Feature",
  "properties": {
    "iso:country":"ES",
    "sg:address":"Calle de Principe Alfonso, 8",
    "sg:city":"San Mateo",
    "sg:orig_category":"Librer\u00cdas",
    "sg:phone":"+34 968 47 05 43",
    "sg:postcode":"30800",
    "sg:province":"Murcia",
    "wof:name":"Papeleria Perez De Hita S.l.",
    "wof:placetype":"venue"
},
  "geometry": {"coordinates":[-1.6905640364,37.680557251],"type":"Point"}
}