{
  "type": "Feature",
  "properties": {
    "iso:country":"ES",
    "sg:address":"Calle de Nueva, 8",
    "sg:city":"Rozas De Madrid",
    "sg:orig_category":"Aparatos, Material Y Suministros Para Laboratorios",
    "sg:phone":"+34 916 37 60 71",
    "sg:postcode":"28231",
    "sg:province":"Madrid",
    "wof:name":"Biotech S.l.",
    "wof:placetype":"venue"
},
  "geometry": {"coordinates":[-3.8715810776,40.492980957],"type":"Point"}
}