{
  "type": "Feature",
  "properties": {
    "addr:full":"Carrer de Diputacio, 111 Barcelona Barcelona 08015",
    "addr:housenumber":"111",
    "addr:postcode":"08015",
    "addr:street":"Carrer De Diputacio",
    "iso:country":"ES",
    "sg:address":"Carrer de Diputacio, 111",
    "sg:city":"Barcelona",
    "sg:classifiers":[
        {
            "category":"Professional",
            "subcategory":"Management & Consulting",
            "type":"Services"
        }
    ],
    "sg:phone":"+34 934 51 23 35",
    "sg:postcode":"08015",
    "sg:province":"Barcelona",
    "sg:tags":[
        "asesor\u00cda",
        "en",
        "marketing"
    ],
    "wof:name":"Comisariado Europeo Del Automovil (cea",
    "wof:placetype":"venue"
},
  "geometry": {"coordinates":[2.1559309959,41.3822097778],"type":"Point"}
}