{
  "type": "Feature",
  "properties": {
    "addr:full":"Calle de Walia, 6 Madrid Madrid 28007",
    "addr:housenumber":"6",
    "addr:postcode":"28007",
    "addr:street":"Calle De Walia",
    "iso:country":"ES",
    "sg:address":"Calle de Walia, 6",
    "sg:city":"Madrid",
    "sg:orig_category":"Tapicer\u00cdas",
    "sg:phone":"+34 915 51 12 84",
    "sg:postcode":"28007",
    "sg:province":"Madrid",
    "wof:name":"Tapiceria Fersan S.l.",
    "wof:placetype":"venue"
},
  "geometry": {"coordinates":[-3.6711449623,40.4079704285],"type":"Point"}
}