{
  "type": "Feature",
  "properties": {
    "addr:full":"Calle de Portal De Bergara, 23 Vitoria-gasteiz \u00c1lava 01013",
    "addr:housenumber":"23",
    "addr:postcode":"01013",
    "addr:street":"Calle De Portal De Bergara",
    "iso:country":"ES",
    "sg:address":"Calle de Portal De Bergara, 23",
    "sg:city":"Vitoria-gasteiz",
    "sg:orig_category":"Acero: Productos Sider\u00dargicos Y Transformados (fabricaci\u00d3n, Negocio)",
    "sg:phone":"+34 945 25 73 00",
    "sg:postcode":"01013",
    "sg:province":"\u00c1lava",
    "wof:name":"Arcelor Distribucion Norte S.l.",
    "wof:placetype":"venue"
},
  "geometry": {"coordinates":[-2.6685736179,42.8814964294],"type":"Point"}
}