{
  "type": "Feature",
  "properties": {
    "addr:full":"Rua Sanchez Calvi\u00d1o, 78 Ferrol La Coru\u00f1a 15404",
    "addr:housenumber":"78",
    "addr:postcode":"15404",
    "addr:street":"Rua Sanchez Calvin\u0303O;La Corun\u0303A",
    "iso:country":"ES",
    "sg:address":"Rua Sanchez Calvi\u00d1o, 78",
    "sg:city":"Ferrol",
    "sg:orig_category":"Ense\u00d1anza: Peluquer\u00cda Est\u00c9tica",
    "sg:phone":"+34 981 32 14 84",
    "sg:postcode":"15404",
    "sg:province":"La Coru\u00f1a",
    "wof:name":"Carsan Academias De Peluqueria S.l.",
    "wof:placetype":"venue"
},
  "geometry": {"coordinates":[-8.2171440125,43.4874343872],"type":"Point"}
}