{
  "type": "Feature",
  "properties": {
    "iso:country":"ES",
    "sg:address":"Calle de Larga, 85",
    "sg:city":"Jerez De La Frontera",
    "sg:orig_category":"Abogados",
    "sg:phone":"+34 956 32 21 03",
    "sg:postcode":"11403",
    "sg:province":"C\u00e1diz",
    "wof:name":"Bufete Gonzalez De La Pe\u00d1a & Fernandez A.i.e.",
    "wof:placetype":"venue"
},
  "geometry": {"coordinates":[-6.1369571686,36.6857872009],"type":"Point"}
}