{
  "type": "Feature",
  "properties": {
    "addr:full":"Calle de Ntra Sra Loreto, 38 Garrapinillos Zaragoza 50190",
    "addr:housenumber":"38",
    "addr:postcode":"50190",
    "addr:street":"Calle De Ntra Sra Loreto",
    "iso:country":"ES",
    "sg:address":"Calle de Ntra Sra Loreto, 38",
    "sg:city":"Garrapinillos",
    "sg:orig_category":"Ense\u00d1anza, Formaci\u00d3n Profesional: Aprendizaje",
    "sg:phone":"+34 976 78 00 50",
    "sg:postcode":"50190",
    "sg:province":"Zaragoza",
    "wof:name":"Ayuntamiento De Zaragoza",
    "wof:placetype":"venue"
},
  "geometry": {"coordinates":[-1.0264190435,41.6822395325],"type":"Point"}
}