{
  "type": "Feature",
  "properties": {
    "addr:full":"Calle de Padre Antolin, 35 Paredes Nava Palencia 34300",
    "addr:housenumber":"35",
    "addr:postcode":"34300",
    "addr:street":"Calle De Padre Antolin",
    "iso:country":"ES",
    "sg:address":"Calle de Padre Antolin, 35",
    "sg:city":"Paredes Nava",
    "sg:orig_category":"Mec\u00c1nico Del Autom\u00d3vil",
    "sg:phone":"+34 979 83 03 32",
    "sg:postcode":"34300",
    "sg:province":"Palencia",
    "wof:name":"Velazquez Rivero Jose Maria",
    "wof:placetype":"venue"
},
  "geometry": {"coordinates":[-4.6880588531,42.1550292969],"type":"Point"}
}