{
  "type": "Feature",
  "properties": {
    "iso:country":"ES",
    "sg:address":"Rond Ferran Puig, 3",
    "sg:city":"Girona",
    "sg:orig_category":"Perfumer\u00cda (al Por Menor)",
    "sg:phone":"+34 972 22 67 45",
    "sg:postcode":"17001",
    "sg:province":"Girona",
    "wof:name":"Fort Torrents Dolores",
    "wof:placetype":"venue"
},
  "geometry": {"coordinates":[2.8185880184,41.982460022],"type":"Point"}
}