{
  "type": "Feature",
  "properties": {
    "addr:full":"Calle de Barrero De Capuchinos, 4 Velez-malaga M\u00e1laga 29700",
    "addr:housenumber":"4",
    "addr:postcode":"29700",
    "addr:street":"Calle De Barrero De Capuchinos",
    "iso:country":"ES",
    "sg:address":"Calle de Barrero De Capuchinos, 4",
    "sg:city":"Velez-malaga",
    "sg:orig_category":"Agentes, Concesionarios Y Sucursales De Veh\u00cdculos",
    "sg:phone":"+34 952 50 51 95",
    "sg:postcode":"29700",
    "sg:province":"M\u00e1laga",
    "wof:name":"Esca\u00f1o Nu\u00f1ez Jose Manuel",
    "wof:placetype":"venue"
},
  "geometry": {"coordinates":[-4.0998082161,36.7781028748],"type":"Point"}
}