{
  "type": "Feature",
  "properties": {
    "iso:country":"ES",
    "sg:address":"Ctra. Higuera, S/n",
    "sg:city":"Retamal De Llerena",
    "sg:orig_category":"Cr\u00cda De Animales",
    "sg:phone":"+34 924 14 60 28",
    "sg:postcode":"06442",
    "sg:province":"Badajoz",
    "wof:name":"Gonzalez Navarro Comunidad De Bienes",
    "wof:placetype":"venue"
},
  "geometry": {"coordinates":[-5.8417439461,38.5769538879],"type":"Point"}
}