{
  "type": "Feature",
  "properties": {
    "iso:country":"ES",
    "sg:address":"Carrer de Angel Guimera, 15",
    "sg:city":"Sant Vicen\u00c7 Dels Horts",
    "sg:orig_category":"Electricidad Veh\u00cdculo",
    "sg:phone":"+34 936 56 62 36",
    "sg:postcode":"08620",
    "sg:province":"Barcelona",
    "wof:name":"Garage Vives S.l.",
    "wof:placetype":"venue"
},
  "geometry": {"coordinates":[2.009649992,41.3960647583],"type":"Point"}
}