{
  "type": "Feature",
  "properties": {
    "addr:full":"Avda Habana (de La), 85 Ourense Ourense 32004",
    "addr:housenumber":"85",
    "addr:postcode":"32004",
    "addr:street":"Avda Habana De La",
    "iso:country":"ES",
    "sg:address":"Avda Habana (de La), 85",
    "sg:city":"Ourense",
    "sg:orig_category":"Congelados: Productos Alimentarios (al Por Menor)",
    "sg:phone":"+34 988 25 55 49",
    "sg:postcode":"32004",
    "sg:province":"Ourense",
    "wof:name":"Ya\u00f1ez Ferro Manuel",
    "wof:placetype":"venue"
},
  "geometry": {"coordinates":[-7.8617634773,42.3419151306],"type":"Point"}
}