{
  "type": "Feature",
  "properties": {
    "iso:country":"ES",
    "sg:address":"Calle de Eugenio Selles, 34",
    "sg:city":"Malaga",
    "sg:orig_category":"Ense\u00d1anza: Idiomas",
    "sg:phone":"+34 952 20 39 76",
    "sg:postcode":"29017",
    "sg:province":"M\u00e1laga",
    "wof:name":"Malaga Plus S.l.",
    "wof:placetype":"venue"
},
  "geometry": {"coordinates":[-4.3674688339,36.7212104797],"type":"Point"}
}