{
  "type": "Feature",
  "properties": {
    "iso:country":"ES",
    "sg:address":"Calle de Virgen Del Val, 16",
    "sg:city":"Madrid",
    "sg:orig_category":"Peluquer\u00cdas, Peluquer\u00cda Mixta",
    "sg:phone":"+34 914 04 19 52",
    "sg:postcode":"28027",
    "sg:province":"Madrid",
    "wof:name":"Mu\u00f1oz Hidalgo Gema Maria",
    "wof:placetype":"venue"
},
  "geometry": {"coordinates":[-3.654184103,40.4371147156],"type":"Point"}
}