{
  "type": "Feature",
  "properties": {
    "addr:full":"Carr Selva, 17 Biniamar Islas Baleares 07369",
    "addr:housenumber":"17",
    "addr:postcode":"07369",
    "addr:street":"Carr Selva;Islas",
    "iso:country":"ES",
    "sg:address":"Carr Selva, 17",
    "sg:city":"Biniamar",
    "sg:orig_category":"Centros De Educaci\u00d3n Especial",
    "sg:phone":"+34 971 51 47 28",
    "sg:postcode":"07369",
    "sg:province":"Islas Baleares",
    "wof:name":"Cp Es Torrentet",
    "wof:placetype":"venue"
},
  "geometry": {"coordinates":[2.8734409809,39.7324409485],"type":"Point"}
}