{
  "type": "Feature",
  "properties": {
    "addr:full":"Pol Ind La Espartera, 2 Benalua Guadix Granada 18510",
    "addr:housenumber":"2",
    "addr:postcode":"18510",
    "addr:street":"Benalua",
    "iso:country":"ES",
    "sg:address":"Pol Ind La Espartera, 2",
    "sg:city":"Benalua Guadix",
    "sg:orig_category":"Empresas De Carpinter\u00cda",
    "sg:phone":"+34 958 69 62 03",
    "sg:postcode":"18510",
    "sg:province":"Granada",
    "wof:name":"Metalisteria La Torre S.l.",
    "wof:placetype":"venue"
},
  "geometry": {"coordinates":[-3.1669239998,37.3522415161],"type":"Point"}
}