{
  "type": "Feature",
  "properties": {
    "iso:country":"ES",
    "sg:address":"Avda America, 63",
    "sg:city":"Santa Fe",
    "sg:orig_category":"Negocio De Granos Y Harinas",
    "sg:phone":"+34 958 44 01 50",
    "sg:postcode":"18320",
    "sg:province":"Granada",
    "wof:name":"Hijos De Manuel Rodriguez Garcia S. A.",
    "wof:placetype":"venue"
},
  "geometry": {"coordinates":[-3.7276439667,37.1891403198],"type":"Point"}
}