{
  "type": "Feature",
  "properties": {
    "iso:country":"ES",
    "sg:address":"Calle de Valladolid, 1",
    "sg:city":"Badajoz",
    "sg:orig_category":"Mec\u00c1nico Del Autom\u00d3vil",
    "sg:phone":"+34 924 27 32 01",
    "sg:postcode":"06006",
    "sg:province":"Badajoz",
    "wof:name":"Alvarez Del Viejo Jose Antonio",
    "wof:placetype":"venue"
},
  "geometry": {"coordinates":[-6.9831252098,38.8882255554],"type":"Point"}
}