{
  "type": "Feature",
  "properties": {
    "addr:full":"Pg Verdum, 28 Barcelona Barcelona 08016",
    "addr:housenumber":"28",
    "addr:postcode":"08016",
    "addr:street":"Pg Verdum",
    "iso:country":"ES",
    "sg:address":"Pg Verdum, 28",
    "sg:city":"Barcelona",
    "sg:orig_category":"Caf\u00c9s, Bares, Cervecer\u00cdas",
    "sg:phone":"+34 932 76 00 35",
    "sg:postcode":"08016",
    "sg:province":"Barcelona",
    "wof:name":"Anaxinamdro S.l.l",
    "wof:placetype":"venue"
},
  "geometry": {"coordinates":[2.1741800308,41.4377937317],"type":"Point"}
}