{
  "type": "Feature",
  "properties": {
    "iso:country":"ES",
    "sg:address":"Calle de Licurgo, 3",
    "sg:city":"Malaga",
    "sg:orig_category":"Muebles, Minoristas",
    "sg:phone":"+34 952 02 31 65",
    "sg:postcode":"29004",
    "sg:province":"M\u00e1laga",
    "wof:name":"La Estrella Del Sofa S.l.",
    "wof:placetype":"venue"
},
  "geometry": {"coordinates":[-4.4619522095,36.6935768127],"type":"Point"}
}