{
  "type": "Feature",
  "properties": {
    "iso:country":"ES",
    "sg:address":"Ctra. A\u00f1over, Km. 0029,2",
    "sg:city":"Pantoja",
    "sg:orig_category":"Distribuci\u00d3n De Petr\u00d3leo Y Derivados",
    "sg:phone":"+34 925 55 20 59",
    "sg:postcode":"45290",
    "sg:province":"Toledo",
    "wof:name":"Estacion De Servicio Los Llanos De Pantoja S.l.",
    "wof:placetype":"venue"
},
  "geometry": {"coordinates":[-3.8329589367,40.042175293],"type":"Point"}
}