{
  "type": "Feature",
  "properties": {
    "iso:country":"ES",
    "sg:address":"Avda Estacion, 7",
    "sg:city":"Ayerbe",
    "sg:orig_category":"Ebanister\u00cda",
    "sg:phone":"+34 974 38 04 78",
    "sg:postcode":"22800",
    "sg:province":"Huesca",
    "wof:name":"Industrias De La Madera Alvier S.l.",
    "wof:placetype":"venue"
},
  "geometry": {"coordinates":[-0.6871190071,42.2733039856],"type":"Point"}
}