{
  "type": "Feature",
  "properties": {
    "iso:country":"ES",
    "sg:address":"Calle de Guzmanes, 30",
    "sg:city":"Trebujena",
    "sg:orig_category":"Asesor\u00cda Fiscal Y Jur\u00cddica",
    "sg:phone":"+34 956 39 57 35",
    "sg:postcode":"11560",
    "sg:province":"C\u00e1diz",
    "wof:name":"Lopez Oliveros Cristobal",
    "wof:placetype":"venue"
},
  "geometry": {"coordinates":[-6.1770238876,36.8685913086],"type":"Point"}
}