{
  "type": "Feature",
  "properties": {
    "addr:full":"Rier Blanca, 13 Barcelona Barcelona 08028",
    "addr:housenumber":"13",
    "addr:postcode":"08028",
    "addr:street":"Rier Blanca",
    "iso:country":"ES",
    "sg:address":"Rier Blanca, 13",
    "sg:city":"Barcelona",
    "sg:orig_category":"Asesor\u00cda Fiscal Y Jur\u00cddica",
    "sg:phone":"+34 934 40 59 93",
    "sg:postcode":"08028",
    "sg:province":"Barcelona",
    "wof:name":"Folch Jordana Magdalena",
    "wof:placetype":"venue"
},
  "geometry": {"coordinates":[2.121696949,41.3766555786],"type":"Point"}
}