{
  "type": "Feature",
  "properties": {
    "addr:full":"Avda Amargacena, 9 Cordoba C\u00f3rdoba 14009",
    "addr:housenumber":"9",
    "addr:postcode":"14009",
    "addr:street":"Avda Amargacena;Co\u0301Rdoba",
    "iso:country":"ES",
    "sg:address":"Avda Amargacena, 9",
    "sg:city":"Cordoba",
    "sg:orig_category":"Mec\u00c1nico Del Autom\u00d3vil",
    "sg:phone":"+34 957 42 92 05",
    "sg:postcode":"14009",
    "sg:province":"C\u00f3rdoba",
    "wof:name":"Import Crevi Sl",
    "wof:placetype":"venue"
},
  "geometry": {"coordinates":[-4.7731189728,37.8720741272],"type":"Point"}
}