{
  "type": "Feature",
  "properties": {
    "addr:full":"Carrer de Arago, 76 Barcelona Barcelona 08015",
    "addr:housenumber":"76",
    "addr:postcode":"08015",
    "addr:street":"Carrer De Arago",
    "iso:country":"ES",
    "sg:address":"Carrer de Arago, 76",
    "sg:city":"Barcelona",
    "sg:orig_category":"Agencias Y Asesores De Publicidad",
    "sg:phone":"+34 934 25 16 50",
    "sg:postcode":"08015",
    "sg:province":"Barcelona",
    "wof:name":"Promotora De Servicios Y Regalos S.a.",
    "wof:placetype":"venue"
},
  "geometry": {"coordinates":[2.1523239613,41.3825302124],"type":"Point"}
}