{
  "type": "Feature",
  "properties": {
    "iso:country":"ES",
    "sg:address":"Calle de Club, 2",
    "sg:city":"Arenas -areeta",
    "sg:orig_category":"Inmobiliaria (agencias)",
    "sg:phone":"+34 944 80 40 69",
    "sg:postcode":"48930",
    "sg:province":"Vizcaya",
    "wof:name":"Deusto S.l.",
    "wof:placetype":"venue"
},
  "geometry": {"coordinates":[-3.0124490261,43.3270721436],"type":"Point"}
}