{
  "type": "Feature",
  "properties": {
    "addr:full":"Carrer de Llobregat, 6 Rubi Barcelona 08191",
    "addr:housenumber":"6",
    "addr:postcode":"08191",
    "addr:street":"Carrer De Llobregat",
    "iso:country":"ES",
    "sg:address":"Carrer de Llobregat, 6",
    "sg:city":"Rubi",
    "sg:orig_category":"Asesor\u00cda Sobre Comunicaci\u00d3n De Empresas",
    "sg:phone":"+34 935 88 63 89",
    "sg:postcode":"08191",
    "sg:province":"Barcelona",
    "wof:name":"Atimsa S.l.",
    "wof:placetype":"venue"
},
  "geometry": {"coordinates":[2.0408124924,41.488117218],"type":"Point"}
}