{
  "type": "Feature",
  "properties": {
    "iso:country":"ES",
    "sg:address":"Calle de Santa Engracia, 139",
    "sg:city":"Madrid",
    "sg:orig_category":"Arquitectos",
    "sg:phone":"+34 914 41 22 29",
    "sg:postcode":"28003",
    "sg:province":"Madrid",
    "wof:name":"Guzman Castro Ricardo",
    "wof:placetype":"venue"
},
  "geometry": {"coordinates":[-3.7023789883,40.4429321289],"type":"Point"}
}