{
  "type": "Feature",
  "properties": {
    "addr:full":"San Joan Plaza, S/n Olaberria Guip\u00f9zcoa 20212",
    "addr:housenumber":"s / n",
    "addr:postcode":"20212",
    "addr:street":"San Joan Plaza;Guipu\u0300Zcoa",
    "iso:country":"ES",
    "sg:address":"San Joan Plaza, S/n",
    "sg:city":"Olaberria",
    "sg:orig_category":"Ense\u00d1anza, Formaci\u00d3n Profesional: Aprendizaje",
    "sg:phone":"+34 943 88 26 40",
    "sg:postcode":"20212",
    "sg:province":"Guip\u00f9zcoa",
    "wof:name":"Gobierno Vasco-eusko Jaurlaritza",
    "wof:placetype":"venue"
},
  "geometry": {"coordinates":[-2.2021760941,43.0276527405],"type":"Point"}
}