{
  "type": "Feature",
  "properties": {
    "addr:full":"Carrer de Jaume Lluis Garau, 2 Palma Islas Baleares 07002",
    "addr:housenumber":"2",
    "addr:postcode":"07002",
    "addr:street":"Carrer De Jaume Lluis Garau",
    "iso:country":"ES",
    "sg:address":"Carrer de Jaume Lluis Garau, 2",
    "sg:city":"Palma",
    "sg:orig_category":"Agencias Y Agentes Comerciales, Representantes",
    "sg:phone":"+34 971 72 50 91",
    "sg:postcode":"07002",
    "sg:province":"Islas Baleares",
    "wof:name":"Gonzalez Devesa Joaquin",
    "wof:placetype":"venue"
},
  "geometry": {"coordinates":[2.6572499275,39.5675086975],"type":"Point"}
}