{
  "type": "Feature",
  "properties": {
    "addr:full":"Calle de Sandoval, 12 Madrid Madrid 28010",
    "addr:housenumber":"12",
    "addr:postcode":"madrid;28010",
    "addr:street":"Calle De Sandoval",
    "iso:country":"ES",
    "sg:address":"Calle de Sandoval, 12",
    "sg:city":"Madrid",
    "sg:orig_category":"Inform\u00c1tica, Ofim\u00c1tica (estudios, Asesor\u00cda, Ingenier\u00cda, Formaci\u00d3n)",
    "sg:phone":"+34 914 48 50 62",
    "sg:postcode":"28010",
    "sg:province":"Madrid",
    "sg:website":"www.pcbox.es",
    "wof:name":"Sistac-ils S.l.",
    "wof:placetype":"venue"
},
  "geometry": {"coordinates":[-3.7041399479,40.4301795959],"type":"Point"}
}