{
  "type": "Feature",
  "properties": {
    "iso:country":"ES",
    "sg:address":"Carr Independencia, 183",
    "sg:city":"Badalona",
    "sg:orig_category":"M\u00c9dicos: Estomatolog\u00cda",
    "sg:phone":"+34 933 83 74 74",
    "sg:postcode":"08915",
    "sg:province":"Barcelona",
    "wof:name":"Tort Ramos Jordi",
    "wof:placetype":"venue"
},
  "geometry": {"coordinates":[2.2416601181,41.4594230652],"type":"Point"}
}