{
  "type": "Feature",
  "properties": {
    "addr:full":"Calle de Fuentecilla, S/n Torrijos Toledo 45500",
    "addr:housenumber":"s",
    "addr:postcode":"45500",
    "addr:street":"Calle De Fuentecilla;/ N",
    "iso:country":"ES",
    "sg:address":"Calle de Fuentecilla, S/n",
    "sg:city":"Torrijos",
    "sg:orig_category":"Ense\u00d1anza Secundaria: Colegios Y Escuelas Privadas",
    "sg:phone":"+34 925 76 27 00",
    "sg:postcode":"45500",
    "sg:province":"Toledo",
    "wof:name":"I.e.s. Juan De Padilla",
    "wof:placetype":"venue"
},
  "geometry": {"coordinates":[-4.2880840302,39.9860916138],"type":"Point"}
}