{
  "type": "Feature",
  "properties": {
    "addr:full":"Avda Europa (de), 17 Gines Sevilla 41960",
    "addr:housenumber":"17",
    "addr:postcode":"41960",
    "addr:street":"Avda Europa De;Sevilla",
    "iso:country":"ES",
    "sg:address":"Avda Europa (de), 17",
    "sg:city":"Gines",
    "sg:orig_category":"Estancos",
    "sg:phone":"+34 954 71 35 40",
    "sg:postcode":"41960",
    "sg:province":"Sevilla",
    "wof:name":"Olivares Rodriguez Antonio Maria",
    "wof:placetype":"venue"
},
  "geometry": {"coordinates":[-6.0736870766,37.3846931458],"type":"Point"}
}