{
  "type": "Feature",
  "properties": {
    "addr:full":"Calle de Arroyazo, 16 Don Benito Badajoz 06400",
    "addr:housenumber":"16",
    "addr:postcode":"06400",
    "addr:street":"Calle De Arroyazo",
    "iso:country":"ES",
    "sg:address":"Calle de Arroyazo, 16",
    "sg:city":"Don Benito",
    "sg:orig_category":"Colchones (fabricaci\u00d3n, Al Por Mayor, Al Por Menor)",
    "sg:phone":"+34 924 80 36 05",
    "sg:postcode":"06400",
    "sg:province":"Badajoz",
    "wof:name":"Colchoneria Extreme\u00d1a S.l.",
    "wof:placetype":"venue"
},
  "geometry": {"coordinates":[-5.8659000397,38.9544448853],"type":"Point"}
}