{
  "type": "Feature",
  "properties": {
    "addr:full":"Arasoles, S/n Fisterra A Coru\u00f1a 15155",
    "addr:housenumber":"/ n",
    "addr:postcode":"15155",
    "addr:street":"Arasoles S;Corun\u0303A",
    "iso:country":"ES",
    "sg:address":"Arasoles, S/n",
    "sg:city":"Fisterra",
    "sg:orig_category":"Mercer\u00cda, Lencer\u00cda (al Por Menor)",
    "sg:phone":"+34 981 74 05 04",
    "sg:postcode":"15155",
    "sg:province":"A Coru\u00f1a",
    "wof:name":"Valnodo S.l.",
    "wof:placetype":"venue"
},
  "geometry": {"coordinates":[-9.2632236481,42.90467453],"type":"Point"}
}