{
  "type": "Feature",
  "properties": {
    "iso:country":"ES",
    "sg:address":"Calle de Rambla, 43",
    "sg:city":"Turquia",
    "sg:orig_category":"Alimentaci\u00d3n General (al Por Mayor)",
    "sg:phone":"+34 962 32 00 11",
    "sg:postcode":"46390",
    "sg:province":"Valencia",
    "wof:name":"Piensos Ampeco S.l.",
    "wof:placetype":"venue"
},
  "geometry": {"coordinates":[-1.1568851471,39.5207366943],"type":"Point"}
}