{
  "type": "Feature",
  "properties": {
    "iso:country":"ES",
    "sg:address":"Juan Viruela, 55",
    "sg:city":"Vall Uixo",
    "sg:orig_category":"Suministros Y Materiales Industriales",
    "sg:phone":"+34 964 66 53 41",
    "sg:postcode":"12600",
    "sg:province":"Castell\u00f3n",
    "wof:name":"Carrion Cases Sonia",
    "wof:placetype":"venue"
},
  "geometry": {"coordinates":[-0.2259490043,39.8183898926],"type":"Point"}
}