{
  "type": "Feature",
  "properties": {
    "addr:full":"Calle de Villaviciosa, 23 Mieres Asturias 33600",
    "addr:housenumber":"23",
    "addr:postcode":"33600",
    "addr:street":"Calle De Villaviciosa",
    "iso:country":"ES",
    "sg:address":"Calle de Villaviciosa, 23",
    "sg:city":"Mieres",
    "sg:classifiers":[
        {
            "category":"Taxi",
            "type":"Transportation"
        }
    ],
    "sg:phone":"+34 985 45 13 47",
    "sg:postcode":"33600",
    "sg:province":"Asturias",
    "wof:name":"Vega Viesca Manes",
    "wof:placetype":"venue"
},
  "geometry": {"coordinates":[-5.7810468674,43.2556152344],"type":"Point"}
}