{
  "type": "Feature",
  "properties": {
    "iso:country":"ES",
    "sg:address":"Calle de Vid (la), S/n",
    "sg:city":"Chiclana De La Frontera",
    "sg:orig_category":"Bares, Piano",
    "sg:phone":"+34 956 53 70 20",
    "sg:postcode":"11130",
    "sg:province":"C\u00e1diz",
    "wof:name":"Olive Tree Pub 2003 S.l.",
    "wof:placetype":"venue"
},
  "geometry": {"coordinates":[-6.1613078117,36.419631958],"type":"Point"}
}