{
  "type": "Feature",
  "properties": {
    "iso:country":"ES",
    "sg:address":"Calle de Santa Ana, 34",
    "sg:city":"Pozo Alcon",
    "sg:orig_category":"Bancos",
    "sg:phone":"+34 953 73 82 27",
    "sg:postcode":"23485",
    "sg:province":"Ja\u00e9n",
    "wof:name":"Banco Popular Espa\u00f1ol",
    "wof:placetype":"venue"
},
  "geometry": {"coordinates":[-2.9357390404,37.704460144],"type":"Point"}
}