{
  "type": "Feature",
  "properties": {
    "addr:full":"Calle de Pio Baroja, 9 Madrid Madrid 28009",
    "addr:housenumber":"9",
    "addr:postcode":"madrid;28009",
    "addr:street":"Calle De Pio Baroja",
    "iso:country":"ES",
    "sg:address":"Calle de Pio Baroja, 9",
    "sg:city":"Madrid",
    "sg:orig_category":"Caf\u00c9s, Bares, Cervecer\u00cdas",
    "sg:phone":"+34 915 74 50 99",
    "sg:postcode":"28009",
    "sg:province":"Madrid",
    "wof:name":"Luis Gonzalez Carlos",
    "wof:placetype":"venue"
},
  "geometry": {"coordinates":[-3.6744110584,40.4152908325],"type":"Point"}
}