{
  "type": "Feature",
  "properties": {
    "iso:country":"ES",
    "sg:address":"Ctra. Pedrizas, Km. 0161,0",
    "sg:city":"Malaga",
    "sg:orig_category":"Asociaciones Y Clubs Deportivos",
    "sg:phone":"+34 952 26 65 68",
    "sg:postcode":"29014",
    "sg:province":"M\u00e1laga",
    "wof:name":"Federacin Andaluz De Tito Olimpico.delgacin Malaga",
    "wof:placetype":"venue"
},
  "geometry": {"coordinates":[-4.423210144,36.765007019],"type":"Point"}
}