{
  "type": "Feature",
  "properties": {
    "addr:full":"Carrer de Pintor Coello, 16 Rubi Barcelona 08191",
    "addr:housenumber":"16",
    "addr:postcode":"08191",
    "addr:street":"Carrer De Pintor Coello",
    "iso:country":"ES",
    "sg:address":"Carrer de Pintor Coello, 16",
    "sg:city":"Rubi",
    "sg:orig_category":"Ropa Para Se\u00d1oras (al Por Menor)",
    "sg:phone":"+34 936 99 73 16",
    "sg:postcode":"08191",
    "sg:province":"Barcelona",
    "wof:name":"Torres Ruiz Juana",
    "wof:placetype":"venue"
},
  "geometry": {"coordinates":[2.0328280926,41.4886550903],"type":"Point"}
}