{
  "type": "Feature",
  "properties": {
    "iso:country":"ES",
    "sg:address":"Carr Rutlla, 5",
    "sg:city":"Girona",
    "sg:orig_category":"Comercio De Minerales, F\u00d3siles Y Conchas",
    "sg:phone":"+34 972 22 20 30",
    "sg:postcode":"17002",
    "sg:province":"Girona",
    "wof:name":"Estop Balfogon Montserrat",
    "wof:placetype":"venue"
},
  "geometry": {"coordinates":[2.823718071,41.9785118103],"type":"Point"}
}