{
  "type": "Feature",
  "properties": {
    "iso:country":"ES",
    "sg:address":"Calle de Alfonso I, 15",
    "sg:city":"Urbanizacion Prados Del Rey",
    "sg:orig_category":"Promotores Constructores",
    "sg:phone":"+34 976 61 76 67",
    "sg:postcode":"50298",
    "sg:province":"Zaragoza",
    "wof:name":"Vela Gallardo David",
    "wof:placetype":"venue"
},
  "geometry": {"coordinates":[-1.0601489544,41.7221908569],"type":"Point"}
}