{
  "type": "Feature",
  "properties": {
    "addr:full":"Calle de Marmoles, 24 Malaga M\u00e1laga 29007",
    "addr:housenumber":"24",
    "addr:postcode":"29007",
    "addr:street":"Calle De Marmoles;Ma\u0301Laga",
    "iso:country":"ES",
    "sg:address":"Calle de Marmoles, 24",
    "sg:city":"Malaga",
    "sg:orig_category":"Confecci\u00d3n (fabricaci\u00d3n, Al Por Mayor)",
    "sg:phone":"+34 952 30 73 98",
    "sg:postcode":"29007",
    "sg:province":"M\u00e1laga",
    "wof:name":"Del Pino Liranzo Manuel",
    "wof:placetype":"venue"
},
  "geometry": {"coordinates":[-4.4276809692,36.7217025757],"type":"Point"}
}