{
  "type": "Feature",
  "properties": {
    "iso:country":"ES",
    "sg:address":"Calle de Benavides, 91",
    "sg:city":"Matanza De Acentejo",
    "sg:orig_category":"Cables E Hilos De Acero",
    "sg:phone":"+34 922 57 73 22",
    "sg:postcode":"38370",
    "sg:province":"Santa Cruz De Tenerife",
    "wof:name":"Origgi  Roberto",
    "wof:placetype":"venue"
},
  "geometry": {"coordinates":[-16.4571647644,28.4495697021],"type":"Point"}
}