{
  "type": "Feature",
  "properties": {
    "iso:country":"ES",
    "sg:address":"Calle de Se\u00d1or De Aranzate, 14",
    "sg:city":"Irun",
    "sg:orig_category":"Asesor\u00cda De Formaci\u00d3n Y Gesti\u00d3n De Personal",
    "sg:phone":"+34 943 63 50 76",
    "sg:postcode":"20304",
    "sg:province":"Guip\u00f9zcoa",
    "wof:name":"Aselagun Aholkularitza S.l.",
    "wof:placetype":"venue"
},
  "geometry": {"coordinates":[-1.7905329466,43.3375167847],"type":"Point"}
}