{
  "type": "Feature",
  "properties": {
    "addr:full":"Av Rio De Janeiro, 42 Barcelona Barcelona 08016",
    "addr:housenumber":"42",
    "addr:postcode":"08016",
    "addr:street":"Av Rio De Janeiro",
    "iso:country":"ES",
    "sg:address":"Av Rio De Janeiro, 42",
    "sg:city":"Barcelona",
    "sg:orig_category":"Caf\u00c9s, Bares, Cervecer\u00cdas",
    "sg:phone":"+34 933 53 34 79",
    "sg:postcode":"08016",
    "sg:province":"Barcelona",
    "wof:name":"La Dolce Vita Cofee Shop Sl",
    "wof:placetype":"venue"
},
  "geometry": {"coordinates":[2.1803340912,41.4361839294],"type":"Point"}
}