{
  "type": "Feature",
  "properties": {
    "iso:country":"ES",
    "sg:address":"Calle de Ancha De Palomino, 1",
    "sg:city":"Bujalance",
    "sg:orig_category":"Asociaciones, Organismos Culturales Y Socioeducativos",
    "sg:phone":"+34 957 17 05 03",
    "sg:postcode":"14650",
    "sg:province":"C\u00f3rdoba",
    "wof:name":"Asociacion Gitana De Bujalance",
    "wof:placetype":"venue"
},
  "geometry": {"coordinates":[-4.3814940453,37.8963851929],"type":"Point"}
}