{
  "type": "Feature",
  "properties": {
    "iso:country":"ES",
    "sg:address":"Avda Praia America, 64",
    "sg:city":"Playa America",
    "sg:orig_category":"M\u00c9dicos: Neurolog\u00cda",
    "sg:phone":"+34 986 35 03 45",
    "sg:postcode":"36379",
    "sg:province":"Pontevedra",
    "wof:name":"Martinez Geijo Palmiro",
    "wof:placetype":"venue"
},
  "geometry": {"coordinates":[-8.8203887939,42.1245803833],"type":"Point"}
}