{
  "type": "Feature",
  "properties": {
    "addr:full":"Carr F Planas I Casals, 38 Badalona Barcelona 08911",
    "addr:housenumber":"38",
    "addr:postcode":"08911",
    "addr:street":"Carr F Planas I Casals",
    "iso:country":"ES",
    "sg:address":"Carr F Planas I Casals, 38",
    "sg:city":"Badalona",
    "sg:orig_category":"Promotores Constructores",
    "sg:phone":"+34 933 89 30 36",
    "sg:postcode":"08911",
    "sg:province":"Barcelona",
    "wof:name":"Sanchez Bosque Alex",
    "wof:placetype":"venue"
},
  "geometry": {"coordinates":[2.2537829876,41.4517860413],"type":"Point"}
}