{
  "type": "Feature",
  "properties": {
    "addr:full":"Calle de Cristo Del Mercado (del), 5 Segovia Segovia 40005",
    "addr:housenumber":"5",
    "addr:postcode":"40005",
    "addr:street":"Calle De Cristo Del Mercado Del",
    "iso:country":"ES",
    "sg:address":"Calle de Cristo Del Mercado (del), 5",
    "sg:city":"Segovia",
    "sg:orig_category":"Armas Y Municiones (fabricaci\u00d3n, Al Por Mayor)",
    "sg:phone":"+34 921 42 26 28",
    "sg:postcode":"40005",
    "sg:province":"Segovia",
    "wof:name":"San Miguel Gomez Enrique",
    "wof:placetype":"venue"
},
  "geometry": {"coordinates":[-4.1137781143,40.9383125305],"type":"Point"}
}