{
  "type": "Feature",
  "properties": {
    "iso:country":"ES",
    "sg:address":"Calle de Fermin Caballero, 32",
    "sg:city":"Madrid",
    "sg:orig_category":"Mutuas De Seguros",
    "sg:phone":"+34 917 30 38 91",
    "sg:postcode":"28034",
    "sg:province":"Madrid",
    "sg:website":"www.psn.es",
    "wof:name":"Prevision Sanitaria Nacional S.a.",
    "wof:placetype":"venue"
},
  "geometry": {"coordinates":[-3.7031788826,40.485458374],"type":"Point"}
}