{
  "type": "Feature",
  "properties": {
    "iso:country":"ES",
    "sg:address":"Rbla Badal, S/n",
    "sg:city":"Barcelona",
    "sg:orig_category":"Librer\u00cdas",
    "sg:phone":"+34 933 31 09 00",
    "sg:postcode":"08028",
    "sg:province":"Barcelona",
    "wof:name":"Ribera Perez Constantina",
    "wof:placetype":"venue"
},
  "geometry": {"coordinates":[2.1307621002,41.3750457764],"type":"Point"}
}