{
  "type": "Feature",
  "properties": {
    "addr:full":"Avda Albufera, 87 Madrid Madrid 28038",
    "addr:housenumber":"87",
    "addr:postcode":"madrid;28038",
    "addr:street":"Avda Albufera",
    "iso:country":"ES",
    "sg:address":"Avda Albufera, 87",
    "sg:city":"Madrid",
    "sg:orig_category":"Farmacias",
    "sg:phone":"+34 914 37 31 33",
    "sg:postcode":"28038",
    "sg:province":"Madrid",
    "wof:name":"Serrada Martinez De Pinillos Paloma",
    "wof:placetype":"venue"
},
  "geometry": {"coordinates":[-3.66197896,40.3945846558],"type":"Point"}
}