{
  "type": "Feature",
  "properties": {
    "addr:full":"Av Mare Deu De Montserrat, 58 Barcelona Barcelona 08024",
    "addr:housenumber":"58",
    "addr:postcode":"08024",
    "addr:street":"Av Mare;De Montserrat",
    "iso:country":"ES",
    "sg:address":"Av Mare Deu De Montserrat, 58",
    "sg:city":"Barcelona",
    "sg:orig_category":"Sociedades, Compa\u00d1\u00cdas Aseguradoras",
    "sg:phone":"+34 932 85 70 65",
    "sg:postcode":"08024",
    "sg:province":"Barcelona",
    "wof:name":"Irebag Correduria D'assegurances S.l.",
    "wof:placetype":"venue"
},
  "geometry": {"coordinates":[2.1639900208,41.4144592285],"type":"Point"}
}