{
  "type": "Feature",
  "properties": {
    "iso:country":"ES",
    "sg:address":"Calle de Julio Romero De Torres, 1",
    "sg:city":"Elda",
    "sg:orig_category":"Carnicer\u00cdas, Carnicer\u00cdas",
    "sg:phone":"+34 965 38 37 07",
    "sg:postcode":"03600",
    "sg:province":"Alicante",
    "wof:name":"Mellinas Mu\u00f1oz Pedro",
    "wof:placetype":"venue"
},
  "geometry": {"coordinates":[-0.7978770137,38.4713401794],"type":"Point"}
}