{
  "type": "Feature",
  "properties": {
    "addr:full":"Luga Lamas, Km. 0002,4 Lamas Ourense 32640",
    "addr:postcode":"32640",
    "addr:street":"0002,4",
    "iso:country":"ES",
    "sg:address":"Luga Lamas, Km. 0002,4",
    "sg:city":"Lamas",
    "sg:orig_category":"Empresas De Carpinter\u00cda",
    "sg:phone":"+34 988 46 71 16",
    "sg:postcode":"32640",
    "sg:province":"Ourense",
    "wof:name":"Construcciones Metalicas Limia S.l.",
    "wof:placetype":"venue"
},
  "geometry": {"coordinates":[-7.794110775,42.0433998108],"type":"Point"}
}