{
  "type": "Feature",
  "properties": {
    "addr:full":"Pla\u00c7 Pompeu Fabra, 9 Girona Girona 17002",
    "addr:housenumber":"9",
    "addr:postcode":"17002",
    "addr:street":"Fabra",
    "iso:country":"ES",
    "sg:address":"Pla\u00c7 Pompeu Fabra, 9",
    "sg:city":"Girona",
    "sg:orig_category":"Asesor\u00cda Fiscal Y Jur\u00cddica",
    "sg:phone":"+34 972 21 48 25",
    "sg:postcode":"17002",
    "sg:province":"Girona",
    "wof:name":"Capellas I Associats S.l.",
    "wof:placetype":"venue"
},
  "geometry": {"coordinates":[2.8221468925,41.9814224243],"type":"Point"}
}