{
  "type": "Feature",
  "properties": {
    "iso:country":"ES",
    "sg:address":"Calle de Felipe Ii, 1",
    "sg:city":"Valladolid",
    "sg:orig_category":"Electrodom\u00c9sticos (al Por Menor)",
    "sg:phone":"+34 983 35 46 21",
    "sg:postcode":"47003",
    "sg:province":"Valladolid",
    "wof:name":"Jose",
    "wof:placetype":"venue"
},
  "geometry": {"coordinates":[-4.7262010574,41.6543312073],"type":"Point"}
}