{
  "type": "Feature",
  "properties": {
    "addr:full":"Carr De Josep Melcior Gomis, 69 Ontinyent Valencia 46870",
    "addr:housenumber":"69",
    "addr:postcode":"46870",
    "addr:street":"Carr De Josep Melcior Gomis",
    "iso:country":"ES",
    "sg:address":"Carr De Josep Melcior Gomis, 69",
    "sg:city":"Ontinyent",
    "sg:orig_category":"Bancos",
    "sg:phone":"+34 962 38 45 11",
    "sg:postcode":"46870",
    "sg:province":"Valencia",
    "wof:name":"Bankinter S.a.",
    "wof:placetype":"venue"
},
  "geometry": {"coordinates":[-0.6030989885,38.8258895874],"type":"Point"}
}