{
  "type": "Feature",
  "properties": {
    "addr:full":"Carr Jovellanos, 26 Algemesi Valencia 46680",
    "addr:housenumber":"26",
    "addr:postcode":"46680",
    "addr:street":"Carr Jovellanos",
    "iso:country":"ES",
    "sg:address":"Carr Jovellanos, 26",
    "sg:city":"Algemesi",
    "sg:orig_category":"Agencias Y Agentes Comerciales, Representantes",
    "sg:phone":"+34 962 42 43 62",
    "sg:postcode":"46680",
    "sg:province":"Valencia",
    "wof:name":"Girbes Beltran Jose Vicente",
    "wof:placetype":"venue"
},
  "geometry": {"coordinates":[-0.4363442063,39.1921043396],"type":"Point"}
}