{
  "type": "Feature",
  "properties": {
    "iso:country":"ES",
    "sg:address":"Calle de Venerable Juan De Santiago, 13",
    "sg:city":"Cordoba",
    "sg:orig_category":"Asociaciones Y Clubs Deportivos",
    "sg:phone":"+34 957 75 04 00",
    "sg:postcode":"14010",
    "sg:province":"C\u00f3rdoba",
    "wof:name":"Poli Nova Sport S.l.",
    "wof:placetype":"venue"
},
  "geometry": {"coordinates":[-4.7657418251,37.8796844482],"type":"Point"}
}