{
  "type": "Feature",
  "properties": {
    "iso:country":"ES",
    "sg:address":"Pase Kafeko Atze, S/n",
    "sg:city":"Ondarroa",
    "sg:orig_category":"Peluqueros: De Se\u00d1oras",
    "sg:phone":"+34 946 83 21 83",
    "sg:postcode":"48700",
    "sg:province":"Vizcaya",
    "wof:name":"Txurruka Aspiazu Milagros",
    "wof:placetype":"venue"
},
  "geometry": {"coordinates":[-2.420058012,43.320980072],"type":"Point"}
}