{
  "type": "Feature",
  "properties": {
    "iso:country":"ES",
    "sg:address":"Urb Centro Internacional, S/n",
    "sg:city":"Algarrobo-costa",
    "sg:orig_category":"Ingeniero",
    "sg:phone":"+34 952 55 14 78",
    "sg:postcode":"29750",
    "sg:province":"M\u00e1laga",
    "wof:name":"Calderon Navas Angel",
    "wof:placetype":"venue"
},
  "geometry": {"coordinates":[-4.038918972,36.7717437744],"type":"Point"}
}