{
  "type": "Feature",
  "properties": {
    "iso:country":"ES",
    "sg:address":"Calle de Santa Teresa, 10",
    "sg:city":"Daimiel",
    "sg:orig_category":"Loter\u00cda Y T\u00d3mbola",
    "sg:phone":"+34 926 85 50 16",
    "sg:postcode":"13250",
    "sg:province":"Ciudad Real",
    "wof:name":"Garcia-retamero Dotor Marino",
    "wof:placetype":"venue"
},
  "geometry": {"coordinates":[-3.6123290062,39.069568634],"type":"Point"}
}