{
  "type": "Feature",
  "properties": {
    "iso:country":"ES",
    "sg:address":"Calle de General Ruiz, 15",
    "sg:city":"Arnedo",
    "sg:orig_category":"Carnicer\u00cdas, Carnicer\u00cdas",
    "sg:phone":"+34 941 38 06 54",
    "sg:postcode":"26580",
    "sg:province":"La Rioja",
    "wof:name":"Carnicas Gil De Gomez S.l.",
    "wof:placetype":"venue"
},
  "geometry": {"coordinates":[-2.1015388966,42.2279014587],"type":"Point"}
}