{
  "type": "Feature",
  "properties": {
    "addr:full":"Pg Sant Joan, 132 Barcelona Barcelona 08037",
    "addr:housenumber":"132",
    "addr:postcode":"08037",
    "addr:street":"Pg Sant Joan",
    "iso:country":"ES",
    "sg:address":"Pg Sant Joan, 132",
    "sg:city":"Barcelona",
    "sg:orig_category":"Librer\u00cdas",
    "sg:phone":"+34 934 57 14 45",
    "sg:postcode":"08037",
    "sg:province":"Barcelona",
    "wof:name":"Beron  Martha Susana",
    "wof:placetype":"venue"
},
  "geometry": {"coordinates":[2.1676580906,41.4011802673],"type":"Point"}
}