{
  "type": "Feature",
  "properties": {
    "addr:full":"Avda. J. Antonio, 11 La Lapa Badajoz 06391",
    "addr:housenumber":"11",
    "addr:postcode":"06391",
    "addr:street":"Avda. J. Antonio;La Lapa",
    "iso:country":"ES",
    "sg:address":"Avda. J. Antonio, 11",
    "sg:city":"La Lapa",
    "sg:orig_category":"Centros De Educaci\u00d3n Especial",
    "sg:phone":"+34 924 55 31 01",
    "sg:postcode":"06391",
    "sg:province":"Badajoz",
    "wof:name":"Colegio Publico San Pedro De Alcantara",
    "wof:placetype":"venue"
},
  "geometry": {"coordinates":[-6.5185341835,38.4546432495],"type":"Point"}
}