{
  "type": "Feature",
  "properties": {
    "addr:full":"Avda Andalucia, 35 Jaen Ja\u00e9n 23005",
    "addr:housenumber":"35;jae\u0301n",
    "addr:postcode":"23005",
    "addr:street":"Avda Andalucia",
    "iso:country":"ES",
    "sg:address":"Avda Andalucia, 35",
    "sg:city":"Jaen",
    "sg:classifiers":[
        {
            "category":"Autos & Motor Vehicles",
            "subcategory":"Automobile Sales",
            "type":"Retail Goods"
        }
    ],
    "sg:phone":"+34 953 27 65 35",
    "sg:postcode":"23005",
    "sg:province":"Ja\u00e9n",
    "wof:name":"Pareja Rivera Jose",
    "wof:placetype":"venue"
},
  "geometry": {"coordinates":[-3.7947399616,37.7773628235],"type":"Point"}
}