{
  "type": "Feature",
  "properties": {
    "iso:country":"ES",
    "sg:address":"Cno Llano, 1",
    "sg:city":"Durcal",
    "sg:orig_category":"Promotores Constructores",
    "sg:phone":"+34 958 78 03 34",
    "sg:postcode":"18650",
    "sg:province":"Granada",
    "wof:name":"Prieto Melguiso Jose",
    "wof:placetype":"venue"
},
  "geometry": {"coordinates":[-3.5704190731,36.9924316406],"type":"Point"}
}