{
  "type": "Feature",
  "properties": {
    "iso:country":"ES",
    "sg:address":"Calle de Camino Real, 6",
    "sg:city":"Gineta",
    "sg:orig_category":"Asilos De Ancianos. Centros Privados",
    "sg:phone":"+34 967 27 55 24",
    "sg:postcode":"02110",
    "sg:province":"Albacete",
    "wof:name":"Residencia Maria Del Buen Suceso S.l.",
    "wof:placetype":"venue"
},
  "geometry": {"coordinates":[-1.9962018728,39.1131401062],"type":"Point"}
}