{
  "type": "Feature",
  "properties": {
    "addr:full":"Rond Sant Pere, 28 Barcelona Barcelona 08010",
    "addr:housenumber":"28",
    "addr:postcode":"08010",
    "addr:street":"Sant Pere",
    "iso:country":"ES",
    "sg:address":"Rond Sant Pere, 28",
    "sg:city":"Barcelona",
    "sg:orig_category":"Promotores Constructores",
    "sg:phone":"+34 932 68 00 80",
    "sg:postcode":"08010",
    "sg:province":"Barcelona",
    "wof:name":"Espais Industrials Reus S.l.",
    "wof:placetype":"venue"
},
  "geometry": {"coordinates":[2.1743059158,41.3893928528],"type":"Point"}
}