{
  "type": "Feature",
  "properties": {
    "iso:country":"ES",
    "sg:address":"Avda Ronda De Los Tejares, 19",
    "sg:city":"Cordoba",
    "sg:orig_category":"Ropa Para Se\u00d1oras (al Por Menor)",
    "sg:phone":"+34 957 47 02 03",
    "sg:postcode":"14008",
    "sg:province":"C\u00f3rdoba",
    "wof:name":"Garcia-li\u00f1an Lopez Carmen",
    "wof:placetype":"venue"
},
  "geometry": {"coordinates":[-4.7821307182,37.8877868652],"type":"Point"}
}