{
  "type": "Feature",
  "properties": {
    "addr:full":"Calle de Serrano, 40 Madrid Madrid 28001",
    "addr:housenumber":"40",
    "addr:postcode":"madrid;28001",
    "addr:street":"Calle De Serrano",
    "iso:country":"ES",
    "sg:address":"Calle de Serrano, 40",
    "sg:city":"Madrid",
    "sg:orig_category":"Comit\u00c9s De Organizaci\u00d3n De Exposiciones, Ferias, Salones",
    "sg:phone":"+34 915 77 06 70",
    "sg:postcode":"28001",
    "sg:province":"Madrid",
    "wof:name":"Technology Consulting Management S.l.",
    "wof:placetype":"venue"
},
  "geometry": {"coordinates":[-3.6875379086,40.4260444641],"type":"Point"}
}