{
  "type": "Feature",
  "properties": {
    "addr:full":"Calle de Dulcinea, 2 Alcala Henares Madrid 28805",
    "addr:housenumber":"2",
    "addr:postcode":"28805",
    "addr:street":"Calle De Dulcinea",
    "iso:country":"ES",
    "sg:address":"Calle de Dulcinea, 2",
    "sg:city":"Alcala Henares",
    "sg:orig_category":"Revestimiento De Suelos Industriales",
    "sg:phone":"+34 918 81 42 08",
    "sg:postcode":"28805",
    "sg:province":"Madrid",
    "wof:name":"Castillo Ramirez Francisco",
    "wof:placetype":"venue"
},
  "geometry": {"coordinates":[-3.3563313484,40.4904899597],"type":"Point"}
}