{
  "type": "Feature",
  "properties": {
    "addr:full":"Calle de Baratzategi, 8 Donostia-san Sebastian Guip\u00f9zcoa 20015",
    "addr:housenumber":"8",
    "addr:postcode":"20015",
    "addr:street":"Calle De Baratzategi",
    "iso:country":"ES",
    "sg:address":"Calle de Baratzategi, 8",
    "sg:city":"Donostia-san Sebastian",
    "sg:orig_category":"Inform\u00c1tica Equipo Y Programas (al Por Mayor)",
    "sg:phone":"+34 943 32 30 39",
    "sg:postcode":"20015",
    "sg:province":"Guip\u00f9zcoa",
    "sg:website":"www.pclanak.com",
    "wof:name":"Pclanak Informatika S.l.",
    "wof:placetype":"venue"
},
  "geometry": {"coordinates":[-1.9585479498,43.3140640259],"type":"Point"}
}