{
  "type": "Feature",
  "properties": {
    "iso:country":"ES",
    "sg:address":"Av Juan Fuster Zaragoza, 16",
    "sg:city":"Benidorm",
    "sg:orig_category":"Alimentaci\u00d3n General (al Por Menor)",
    "sg:phone":"+34 965 85 92 49",
    "sg:postcode":"03500",
    "sg:province":"Alicante",
    "wof:name":"Five Star Imports S.l.",
    "wof:placetype":"venue"
},
  "geometry": {"coordinates":[-0.1079349965,38.5376396179],"type":"Point"}
}