{
  "type": "Feature",
  "properties": {
    "addr:full":"Avda Juan Ramon Jimenez, 121 Calasparra Murcia 30420",
    "addr:postcode":"30420",
    "addr:street":"Avda Juan Ramon Jimenez 121",
    "iso:country":"ES",
    "sg:address":"Avda Juan Ramon Jimenez, 121",
    "sg:city":"Calasparra",
    "sg:orig_category":"Distribuci\u00d3n De Petr\u00d3leo Y Derivados",
    "sg:phone":"+34 968 72 01 69",
    "sg:postcode":"30420",
    "sg:province":"Murcia",
    "wof:name":"Juan Valverde Garcia S.l.",
    "wof:placetype":"venue"
},
  "geometry": {"coordinates":[-1.7051119804,38.2276725769],"type":"Point"}
}