{
  "type": "Feature",
  "properties": {
    "iso:country":"ES",
    "sg:address":"Calle de San Miguel, 40",
    "sg:city":"Armilla",
    "sg:orig_category":"Empresas De Carpinter\u00cda Met\u00c1lica",
    "sg:phone":"+34 958 57 14 70",
    "sg:postcode":"18100",
    "sg:province":"Granada",
    "wof:name":"Molinero Rosales Jose",
    "wof:placetype":"venue"
},
  "geometry": {"coordinates":[-3.6219000816,37.1450958252],"type":"Point"}
}