{
  "type": "Feature",
  "properties": {
    "addr:full":"Calle de Torre De Sandoval, 2 Malaga M\u00e1laga 29015",
    "addr:housenumber":"2",
    "addr:postcode":"29015",
    "addr:street":"Calle De Torre De Sandoval;Ma\u0301Laga",
    "iso:country":"ES",
    "sg:address":"Calle de Torre De Sandoval, 2",
    "sg:city":"Malaga",
    "sg:orig_category":"Ropa Para Se\u00d1oras (al Por Menor)",
    "sg:phone":"+34 952 60 92 36",
    "sg:postcode":"29015",
    "sg:province":"M\u00e1laga",
    "wof:name":"Garcia-courtoy Lopez Maria De La Paz",
    "wof:placetype":"venue"
},
  "geometry": {"coordinates":[-4.4201588631,36.7183189392],"type":"Point"}
}