{
  "type": "Feature",
  "properties": {
    "iso:country":"ES",
    "sg:address":"Carrer de Rossello, 27",
    "sg:city":"Barcelona",
    "sg:orig_category":"Promotores Constructores",
    "sg:phone":"+34 933 57 18 32",
    "sg:postcode":"08029",
    "sg:province":"Barcelona",
    "sg:website":"www.grupoxxi.net",
    "wof:name":"Promociones Cristal Xxi S.l.",
    "wof:placetype":"venue"
},
  "geometry": {"coordinates":[2.1439640522,41.3834228516],"type":"Point"}
}