{
  "type": "Feature",
  "properties": {
    "addr:full":"Avda Mancha (la), 6 Madrigueras Albacete 02230",
    "addr:postcode":"02230",
    "addr:street":"Avda Mancha La 6",
    "iso:country":"ES",
    "sg:address":"Avda Mancha (la), 6",
    "sg:city":"Madrigueras",
    "sg:orig_category":"Mec\u00c1nico Del Autom\u00d3vil",
    "sg:phone":"+34 967 48 40 30",
    "sg:postcode":"02230",
    "sg:province":"Albacete",
    "wof:name":"Nieto Caba\u00f1ero Emilio",
    "wof:placetype":"venue"
},
  "geometry": {"coordinates":[-1.802760005,39.2332077026],"type":"Point"}
}