{
  "type": "Feature",
  "properties": {
    "addr:full":"Abejeras, 30 Iru\u00f1a Navarra 31007",
    "addr:housenumber":"30",
    "addr:postcode":"31007",
    "addr:street":"Abejeras",
    "iso:country":"ES",
    "sg:address":"Abejeras, 30",
    "sg:city":"Iru\u00f1a",
    "sg:orig_category":"Arquitectos",
    "sg:phone":"+34 948 26 99 42",
    "sg:postcode":"31007",
    "sg:province":"Navarra",
    "wof:name":"Flamarique Zubillaga Fermin Maria",
    "wof:placetype":"venue"
},
  "geometry": {"coordinates":[-1.6483999491,42.8037757874],"type":"Point"}
}