{
  "type": "Feature",
  "properties": {
    "iso:country":"ES",
    "sg:address":"Carr Historiador Josep Clapes, De L', S/n",
    "sg:city":"Eivissa",
    "sg:orig_category":"Turismo",
    "sg:phone":"+34 971 30 24 90",
    "sg:postcode":"07800",
    "sg:province":"Islas Baleares",
    "wof:name":"Fomento Del Turismo De Ibiza Y Formentera",
    "wof:placetype":"venue"
},
  "geometry": {"coordinates":[1.4304840565,38.9087257385],"type":"Point"}
}