{
  "type": "Feature",
  "properties": {
    "addr:full":"Av Pearson, 90 Barcelona Barcelona 08034",
    "addr:housenumber":"90",
    "addr:postcode":"08034",
    "addr:street":"Av Pearson",
    "iso:country":"ES",
    "sg:address":"Av Pearson, 90",
    "sg:city":"Barcelona",
    "sg:orig_category":"Organismos De Turismo",
    "sg:phone":"+34 932 05 45 00",
    "sg:postcode":"08034",
    "sg:province":"Barcelona",
    "wof:name":"Meeting Espectations S.l.",
    "wof:placetype":"venue"
},
  "geometry": {"coordinates":[2.1030468941,41.3940963745],"type":"Point"}
}