{
  "type": "Feature",
  "properties": {
    "iso:country":"ES",
    "sg:address":"Piragua(playasol), S/n",
    "sg:city":"Bolnuevo",
    "sg:orig_category":"Discotecas Y Salas De Baile",
    "sg:phone":"+34 968 15 08 83",
    "sg:postcode":"30877",
    "sg:province":"Murcia",
    "wof:name":"Mendez Garcia Francisco",
    "wof:placetype":"venue"
},
  "geometry": {"coordinates":[-1.308226943,37.5687179565],"type":"Point"}
}