{
  "type": "Feature",
  "properties": {
    "iso:country":"ES",
    "sg:address":"Cra. Dosrius, 165",
    "sg:city":"Cardedeu",
    "sg:orig_category":"Servicios De Higiene Y Peluquer\u00cda Para Perros Y Gatos",
    "sg:phone":"+34 938 71 24 16",
    "sg:postcode":"08440",
    "sg:province":"Barcelona",
    "wof:name":"Garcia Caballero Gemma",
    "wof:placetype":"venue"
},
  "geometry": {"coordinates":[2.3622779846,41.6308288574],"type":"Point"}
}