{
  "type": "Feature",
  "properties": {
    "iso:country":"ES",
    "sg:address":"Calle de Jorge Juan, 22",
    "sg:city":"Madrid",
    "sg:orig_category":"Comercio De Piezas De Recambio Y De Accesorios De Veh\u00cdculos, Veh\u00cdculos Industriales",
    "sg:phone":"+34 915 75 80 36",
    "sg:postcode":"28001",
    "sg:province":"Madrid",
    "wof:name":"Carrocerias Madrid S. A.",
    "wof:placetype":"venue"
},
  "geometry": {"coordinates":[-3.6847798824,40.4236793518],"type":"Point"}
}