{
  "type": "Feature",
  "properties": {
    "addr:full":"Abelendo, S/n Abelendo Pontevedra 36954",
    "addr:postcode":"36954",
    "addr:street":"Abelendo S / N",
    "iso:country":"ES",
    "sg:address":"Abelendo, S/n",
    "sg:city":"Abelendo",
    "sg:orig_category":"Fabricaci\u00d3n, Reparaci\u00d3n Y Mantenimiento De Construcciones Navales Y Fluviales",
    "sg:phone":"+34 986 31 22 56",
    "sg:postcode":"36954",
    "sg:province":"Pontevedra",
    "wof:name":"Chapela Gonzalez Jose",
    "wof:placetype":"venue"
},
  "geometry": {"coordinates":[-8.7417287827,42.2851715088],"type":"Point"}
}