{
  "type": "Feature",
  "properties": {
    "addr:full":"Ptge Garrigues, 1 Can Casablancas Barcelona 08192",
    "addr:housenumber":"1",
    "addr:postcode":"08192",
    "addr:street":"Ptge Garrigues",
    "iso:country":"ES",
    "sg:address":"Ptge Garrigues, 1",
    "sg:city":"Can Casablancas",
    "sg:orig_category":"Piscinas, Accesorios, Suministros (fabricaci\u00d3n, Al Por Mayor)",
    "sg:phone":"+34 937 21 57 82",
    "sg:postcode":"08192",
    "sg:province":"Barcelona",
    "wof:name":"Pico Garcia Salvador",
    "wof:placetype":"venue"
},
  "geometry": {"coordinates":[2.0748400688,41.5303916931],"type":"Point"}
}