{
  "type": "Feature",
  "properties": {
    "iso:country":"ES",
    "sg:address":"Union, 7",
    "sg:city":"Vecindario",
    "sg:orig_category":"Centros M\u00c9dicos Y Sociales, Dispensarios",
    "sg:phone":"+34 928 75 85 55",
    "sg:postcode":"35110",
    "sg:province":"Las Palmas",
    "wof:name":"Centro Medico Trebol S.l.",
    "wof:placetype":"venue"
},
  "geometry": {"coordinates":[-15.444396019,27.8476104736],"type":"Point"}
}