{
  "type": "Feature",
  "properties": {
    "iso:country":"ES",
    "sg:address":"Calle de Don Luis, 22",
    "sg:city":"Linares",
    "sg:orig_category":"Internados & Ense\u00d1anza Privada",
    "sg:phone":"+34 953 69 36 00",
    "sg:postcode":"23700",
    "sg:province":"Ja\u00e9n",
    "wof:name":"Colegio De La Presentacion",
    "wof:placetype":"venue"
},
  "geometry": {"coordinates":[-3.6353991032,38.0922813416],"type":"Point"}
}