{
  "type": "Feature",
  "properties": {
    "addr:full":"Carrer de Noguera, 18 Poligono Industrial Can Carner Barcelona 08211",
    "addr:housenumber":"18",
    "addr:postcode":"08211",
    "addr:street":"Carrer De Noguera;Poligono Industrial",
    "iso:country":"ES",
    "sg:address":"Carrer de Noguera, 18",
    "sg:city":"Poligono Industrial Can Carner",
    "sg:orig_category":"Maquinaria Para Industrias Diversas",
    "sg:phone":"+34 937 14 51 34",
    "sg:postcode":"08211",
    "sg:province":"Barcelona",
    "wof:name":"Subministraments Energetics Castellar S.a.",
    "wof:placetype":"venue"
},
  "geometry": {"coordinates":[2.0857300758,41.6151885986],"type":"Point"}
}