{
  "type": "Feature",
  "properties": {
    "addr:full":"Calle de Alfonso X El Sabio, 7 Avila \u00c1vila 05001",
    "addr:housenumber":"7",
    "addr:postcode":"05001",
    "addr:street":"Calle De Alfonso X El Sabio;A\u0301Vila",
    "iso:country":"ES",
    "sg:address":"Calle de Alfonso X El Sabio, 7",
    "sg:city":"Avila",
    "sg:orig_category":"Trajes Y Adornos De Boda (confecci\u00d3n, Al Por Menor)",
    "sg:phone":"+34 920 25 06 65",
    "sg:postcode":"05001",
    "sg:province":"\u00c1vila",
    "wof:name":"Martinez Sarralde Jose Antonio",
    "wof:placetype":"venue"
},
  "geometry": {"coordinates":[-4.6870164871,40.6533966064],"type":"Point"}
}