{
  "type": "Feature",
  "properties": {
    "iso:country":"ES",
    "sg:address":"Calle de Hornos (los), 4",
    "sg:city":"Ponferrada",
    "sg:orig_category":"Molduras, Junquillos, Listones Y Molduras Perforadas",
    "sg:phone":"+34 987 40 04 16",
    "sg:postcode":"24400",
    "sg:province":"Le\u00f3n",
    "wof:name":"Teldespa\u00d1a S.l.",
    "wof:placetype":"venue"
},
  "geometry": {"coordinates":[-6.5954608917,42.5461654663],"type":"Point"}
}