{
  "type": "Feature",
  "properties": {
    "addr:full":"Calle de Bermejeros, 48 Salamanca Salamanca 37001",
    "addr:housenumber":"48",
    "addr:postcode":"37001",
    "addr:street":"Calle De Bermejeros",
    "iso:country":"ES",
    "sg:address":"Calle de Bermejeros, 48",
    "sg:city":"Salamanca",
    "sg:orig_category":"Juegos Y Juguetes (al Por Menor)",
    "sg:phone":"+34 923 21 62 11",
    "sg:postcode":"37001",
    "sg:province":"Salamanca",
    "wof:name":"Sanchez Alonso Jorge",
    "wof:placetype":"venue"
},
  "geometry": {"coordinates":[-5.6601314545,40.9671630859],"type":"Point"}
}