{
  "type": "Feature",
  "properties": {
    "addr:full":"Av Arago, S/n Gandesa Tarragona 43780",
    "addr:housenumber":"s / n",
    "addr:postcode":"43780",
    "addr:street":"Av Arago",
    "iso:country":"ES",
    "sg:address":"Av Arago, S/n",
    "sg:city":"Gandesa",
    "sg:orig_category":"Artes Gr\u00c1ficas, Artes Pl\u00c1sticas (curso)",
    "sg:phone":"+34 977 42 06 32",
    "sg:postcode":"43780",
    "sg:province":"Tarragona",
    "wof:name":"Graficas Salaet S. A.",
    "wof:placetype":"venue"
},
  "geometry": {"coordinates":[0.4360649884,41.0538215637],"type":"Point"}
}