{
  "type": "Feature",
  "properties": {
    "iso:country":"ES",
    "sg:address":"Calle de San Agustin, 46",
    "sg:city":"Requena",
    "sg:orig_category":"Asesor\u00cda Sobre Comunicaci\u00d3n De Empresas",
    "sg:phone":"+34 962 30 39 12",
    "sg:postcode":"46340",
    "sg:province":"Valencia",
    "wof:name":"Asemfis Consultores S.l.",
    "wof:placetype":"venue"
},
  "geometry": {"coordinates":[-1.1047719717,39.4892234802],"type":"Point"}
}