{
  "type": "Feature",
  "properties": {
    "iso:country":"ES",
    "sg:address":"Calle de Arroka, 2",
    "sg:city":"Donostia-san Sebastian",
    "sg:orig_category":"Centros De Adelgazamiento Y De Est\u00c9tica",
    "sg:phone":"+34 943 45 53 69",
    "sg:postcode":"20006",
    "sg:province":"Guip\u00f9zcoa",
    "sg:website":"www.imak-peluqueros.com",
    "wof:name":"Imak G.m. S.l.",
    "wof:placetype":"venue"
},
  "geometry": {"coordinates":[-1.9825328588,43.3145751953],"type":"Point"}
}