{
  "type": "Feature",
  "properties": {
    "iso:country":"ES",
    "sg:address":"Carr San Carlos, 16",
    "sg:city":"Oliva",
    "sg:orig_category":"Peluqueros: De Se\u00d1oras",
    "sg:phone":"+34 962 85 56 46",
    "sg:postcode":"46780",
    "sg:province":"Valencia",
    "wof:name":"Torres Alemany Maria Vicenta",
    "wof:placetype":"venue"
},
  "geometry": {"coordinates":[-0.1177899987,38.9214859009],"type":"Point"}
}