{
  "type": "Feature",
  "properties": {
    "addr:full":"Carr Carlos Sarthou, 4 Xativa Valencia 46800",
    "addr:housenumber":"4",
    "addr:postcode":"46800",
    "addr:street":"Carr Carlos Sarthou",
    "iso:country":"ES",
    "sg:address":"Carr Carlos Sarthou, 4",
    "sg:city":"Xativa",
    "sg:orig_category":"Cobro De Pr\u00c9stamos",
    "sg:phone":"+34 962 27 31 36",
    "sg:postcode":"46800",
    "sg:province":"Valencia",
    "wof:name":"Parre\u00f1o Garcia Deogracias",
    "wof:placetype":"venue"
},
  "geometry": {"coordinates":[-0.5215700269,38.9907608032],"type":"Point"}
}