{
  "type": "Feature",
  "properties": {
    "addr:full":"Avda Alicante, 23 Agost Alicante 03698",
    "addr:housenumber":"23",
    "addr:postcode":"03698",
    "addr:street":"Avda Alicante",
    "iso:country":"ES",
    "sg:address":"Avda Alicante, 23",
    "sg:city":"Agost",
    "sg:orig_category":"Asociaciones, Organismos Culturales Y Socioeducativos",
    "sg:phone":"+34 965 69 10 36",
    "sg:postcode":"03698",
    "sg:province":"Alicante",
    "wof:name":"Escuela De Musica Santa Cecilia",
    "wof:placetype":"venue"
},
  "geometry": {"coordinates":[-0.637574017,38.437713623],"type":"Point"}
}