{
  "type": "Feature",
  "properties": {
    "iso:country":"ES",
    "sg:address":"Zaramaga Carrer de Carrer de Boulevard De Vitoria, 1",
    "sg:city":"Vitoria-gasteiz",
    "sg:orig_category":"Asociaciones Y Clubs Deportivos",
    "sg:phone":"+34 945 12 36 91",
    "sg:postcode":"01013",
    "sg:province":"\u00c1lava",
    "sg:website":"www.baskonia.com",
    "wof:name":"Saski Baskonia S.a.d.",
    "wof:placetype":"venue"
},
  "geometry": {"coordinates":[-2.6840889454,42.8761367798],"type":"Point"}
}