{
  "type": "Feature",
  "properties": {
    "iso:country":"ES",
    "sg:address":"Calle de Benito Perez Galdos, 10",
    "sg:city":"Cordoba",
    "sg:orig_category":"Organismos De Reclutamiento",
    "sg:phone":"+34 957 47 22 06",
    "sg:postcode":"14001",
    "sg:province":"C\u00f3rdoba",
    "wof:name":"Auditoria Y Proteccion De Datos S.l.",
    "wof:placetype":"venue"
},
  "geometry": {"coordinates":[-4.7820940018,37.8897476196],"type":"Point"}
}