{
  "type": "Feature",
  "properties": {
    "addr:full":"Calle de Santa Cruz, 25 Burgos Burgos 09002",
    "addr:housenumber":"25",
    "addr:postcode":"09002",
    "addr:street":"Calle De Santa Cruz",
    "iso:country":"ES",
    "sg:address":"Calle de Santa Cruz, 25",
    "sg:city":"Burgos",
    "sg:orig_category":"Procuradores",
    "sg:phone":"+34 947 20 60 86",
    "sg:postcode":"09002",
    "sg:province":"Burgos",
    "wof:name":"Gutierrez Benito Elias",
    "wof:placetype":"venue"
},
  "geometry": {"coordinates":[-3.6970849037,42.3366355896],"type":"Point"}
}