{
  "type": "Feature",
  "properties": {
    "addr:full":"Calle de Jose Simon De Lillo, 14 Pe\u00e7arroya-pueblonuevo C\u00f3rdoba 14200",
    "addr:housenumber":"14",
    "addr:postcode":"14200",
    "addr:street":"Calle De Jose Simon De Lillo;Co\u0301Rdoba",
    "iso:country":"ES",
    "sg:address":"Calle de Jose Simon De Lillo, 14",
    "sg:city":"Pe\u00e7arroya-pueblonuevo",
    "sg:orig_category":"Droguer\u00cdas (al Por Menor)",
    "sg:phone":"+34 957 56 29 26",
    "sg:postcode":"14200",
    "sg:province":"C\u00f3rdoba",
    "wof:name":"Guerrero Y Duran Droguerias S.l.",
    "wof:placetype":"venue"
},
  "geometry": {"coordinates":[-5.2662811279,38.2998962402],"type":"Point"}
}