{
  "type": "Feature",
  "properties": {
    "addr:full":"Carrer de Sant Josep, 13 Sabadell Barcelona 08202",
    "addr:housenumber":"13",
    "addr:postcode":"08202",
    "addr:street":"Carrer De Sant Josep",
    "iso:country":"ES",
    "sg:address":"Carrer de Sant Josep, 13",
    "sg:city":"Sabadell",
    "sg:orig_category":"Internados & Ense\u00d1anza Privada",
    "sg:phone":"+34 937 25 97 46",
    "sg:postcode":"08202",
    "sg:province":"Barcelona",
    "sg:website":"www.xtec.es/escolapiessabadell",
    "wof:name":"Colegio San Jose De Calasanz En Sabadell Hijas De Maria Rr Escuelas Pias Escolapias. Prov. Cataluna",
    "wof:placetype":"venue"
},
  "geometry": {"coordinates":[2.1104431152,41.5480308533],"type":"Point"}
}