{
  "type": "Feature",
  "properties": {
    "iso:country":"ES",
    "sg:address":"Calle de Obispo Rincon, 2",
    "sg:city":"Guadix",
    "sg:orig_category":"Internados & Ense\u00d1anza Privada",
    "sg:phone":"+34 958 66 07 45",
    "sg:postcode":"18500",
    "sg:province":"Granada",
    "wof:name":"Colegio De La Presentacion",
    "wof:placetype":"venue"
},
  "geometry": {"coordinates":[-3.1336278915,37.2968635559],"type":"Point"}
}