{
  "type": "Feature",
  "properties": {
    "iso:country":"ES",
    "sg:address":"Carre Miaja, 50",
    "sg:city":"Era Alta",
    "sg:orig_category":"Administradores De Bienes Y Delegados De Comunidades De Propietarios",
    "sg:phone":"+34 968 34 06 43",
    "sg:postcode":"30168",
    "sg:province":"Murcia",
    "wof:name":"Rosa Bou Daniel",
    "wof:placetype":"venue"
},
  "geometry": {"coordinates":[-1.1684839725,37.9631690979],"type":"Point"}
}