{
  "type": "Feature",
  "properties": {
    "addr:full":"Urba Lloma De La Verge, S/n Lloma De La Verge Valencia 46220",
    "addr:housenumber":"s",
    "addr:postcode":"46220",
    "addr:street":"/ N",
    "iso:country":"ES",
    "sg:address":"Urba Lloma De La Verge, S/n",
    "sg:city":"Lloma De La Verge",
    "sg:orig_category":"Internados & Ense\u00d1anza Privada",
    "sg:phone":"+34 961 23 29 00",
    "sg:postcode":"46220",
    "sg:province":"Valencia",
    "sg:website":"www.xpress.es/carolines",
    "wof:name":"Escola Les Carolines Coop.v.",
    "wof:placetype":"venue"
},
  "geometry": {"coordinates":[-0.4595290124,39.3631401062],"type":"Point"}
}