{
  "type": "Feature",
  "properties": {
    "iso:country":"ES",
    "sg:address":"Pg Francesc Macia, 47",
    "sg:city":"Rubi",
    "sg:orig_category":"Ense\u00d1anza Variada",
    "sg:phone":"+34 936 97 18 45",
    "sg:postcode":"08191",
    "sg:province":"Barcelona",
    "wof:name":"Alonso Alonso Raquel",
    "wof:placetype":"venue"
},
  "geometry": {"coordinates":[2.0314600468,41.4911422729],"type":"Point"}
}