{
  "type": "Feature",
  "properties": {
    "iso:country":"ES",
    "sg:address":"Calle de Hernani, 21",
    "sg:city":"Donostia-san Sebastian",
    "sg:orig_category":"Peleter\u00cdas",
    "sg:phone":"+34 943 42 16 57",
    "sg:postcode":"20004",
    "sg:province":"Guip\u00f9zcoa",
    "wof:name":"Peleteria Sanfor S. A.",
    "wof:placetype":"venue"
},
  "geometry": {"coordinates":[-1.9838329554,43.3201904297],"type":"Point"}
}