{
  "type": "Feature",
  "properties": {
    "addr:full":"Avda Andalucia, Km. 0011,4 Madrid Madrid 28021",
    "addr:postcode":"28021",
    "addr:street":"Avda Andalucia Km. 0011,4",
    "iso:country":"ES",
    "sg:address":"Avda Andalucia, Km. 0011,4",
    "sg:city":"Madrid",
    "sg:orig_category":"Refiner\u00cdas De Petr\u00d3leo",
    "sg:phone":"+34 917 98 30 08",
    "sg:postcode":"28021",
    "sg:province":"Madrid",
    "wof:name":"Dipesa Gestion S.l.",
    "wof:placetype":"venue"
},
  "geometry": {"coordinates":[-3.6927390099,40.3464660645],"type":"Point"}
}