{
  "type": "Feature",
  "properties": {
    "addr:full":"Pase Maritimo Bristol, S/n Corralejo Las Palmas 35660",
    "addr:housenumber":"/ n",
    "addr:postcode":"35660",
    "addr:street":"Bristol S",
    "iso:country":"ES",
    "sg:address":"Pase Maritimo Bristol, S/n",
    "sg:city":"Corralejo",
    "sg:orig_category":"Promotores Constructores",
    "sg:phone":"+34 928 53 78 48",
    "sg:postcode":"35660",
    "sg:province":"Las Palmas",
    "wof:name":"Morales Rodriguez Juan Francisco",
    "wof:placetype":"venue"
},
  "geometry": {"coordinates":[-13.8656949997,28.7451438904],"type":"Point"}
}