{
  "type": "Feature",
  "properties": {
    "addr:full":"Calle de Castilla Perez, 20 Nerja M\u00e1laga 29780",
    "addr:housenumber":"20",
    "addr:postcode":"29780",
    "addr:street":"Calle De Castilla Perez",
    "iso:country":"ES",
    "sg:address":"Calle de Castilla Perez, 20",
    "sg:city":"Nerja",
    "sg:orig_category":"Zapatos (al Por Menor)",
    "sg:phone":"+34 952 52 66 69",
    "sg:postcode":"29780",
    "sg:province":"M\u00e1laga",
    "wof:name":"Jimena Cid Francisco",
    "wof:placetype":"venue"
},
  "geometry": {"coordinates":[-3.8798573017,36.74559021],"type":"Point"}
}