{
  "type": "Feature",
  "properties": {
    "addr:full":"Plaz Durangoko Plateruen Plaza, 9 Durango Vizcaya 48200",
    "addr:housenumber":"9",
    "addr:postcode":"48200",
    "addr:street":"Plaz;Plateruen Plaza",
    "iso:country":"ES",
    "sg:address":"Plaz Durangoko Plateruen Plaza, 9",
    "sg:city":"Durango",
    "sg:orig_category":"Transportes Por V\u00cdas Navegables",
    "sg:phone":"+34 946 81 09 23",
    "sg:postcode":"48200",
    "sg:province":"Vizcaya",
    "wof:name":"Guillermo Alonso Izurza",
    "wof:placetype":"venue"
},
  "geometry": {"coordinates":[-2.6117420197,43.194644928],"type":"Point"}
}