{
  "type": "Feature",
  "properties": {
    "iso:country":"ES",
    "sg:address":"Cami Pont Del Moli, S/n",
    "sg:city":"Almenar",
    "sg:orig_category":"Asilos De Ancianos. Centros Privados",
    "sg:phone":"+34 973 77 00 09",
    "sg:postcode":"25126",
    "sg:province":"Lleida",
    "wof:name":"Residencia Bona Estada Almenar 2000 S.l.",
    "wof:placetype":"venue"
},
  "geometry": {"coordinates":[0.5701000094,41.7965431213],"type":"Point"}
}