{
  "type": "Feature",
  "properties": {
    "addr:full":"Avgd Francesc Tarrega, 57 Villarreal Castell\u00f3n 12540",
    "addr:housenumber":"57",
    "addr:postcode":"12540",
    "addr:street":"Tarrega",
    "iso:country":"ES",
    "sg:address":"Avgd Francesc Tarrega, 57",
    "sg:city":"Villarreal",
    "sg:orig_category":"Inform\u00c1tica: Soportes De Informaci\u00d3n, Suministros & Accesorios",
    "sg:phone":"+34 964 53 11 95",
    "sg:postcode":"12540",
    "sg:province":"Castell\u00f3n",
    "sg:website":"www.jump.es",
    "wof:name":"Jump Ordenadores S.l.",
    "wof:placetype":"venue"
},
  "geometry": {"coordinates":[-0.0952939987,39.9453048706],"type":"Point"}
}