{
  "type": "Feature",
  "properties": {
    "iso:country":"ES",
    "sg:address":"Calle de Salamanca, 4",
    "sg:city":"Arganda",
    "sg:orig_category":"Telas Para Tapizar, Cortinas, Pasamaner\u00cda (fabricaci\u00d3n, Al Por Mayor)",
    "sg:phone":"+34 918 70 42 53",
    "sg:postcode":"28500",
    "sg:province":"Madrid",
    "wof:name":"Garcia Gonzalez Cristina",
    "wof:placetype":"venue"
},
  "geometry": {"coordinates":[-3.4657609463,40.307434082],"type":"Point"}
}