{
  "type": "Feature",
  "properties": {
    "iso:country":"ES",
    "sg:address":"Avgd Vicent Mortes Alfonso, 62",
    "sg:city":"Paterna",
    "sg:orig_category":"Art\u00cdculos De Regalo (al Por Menor)",
    "sg:phone":"+34 961 38 81 03",
    "sg:postcode":"46980",
    "sg:province":"Valencia",
    "wof:name":"Montoliu Benita Jesus Vicente",
    "wof:placetype":"venue"
},
  "geometry": {"coordinates":[-0.4486190081,39.5074501038],"type":"Point"}
}