{
  "type": "Feature",
  "properties": {
    "addr:full":"Avda Alcalde Portanet, 29 Pereiro Pontevedra 36210",
    "addr:housenumber":"29",
    "addr:postcode":"36210",
    "addr:street":"Avda Alcalde Portanet",
    "iso:country":"ES",
    "sg:address":"Avda Alcalde Portanet, 29",
    "sg:city":"Pereiro",
    "sg:orig_category":"Peluquer\u00cdas, Peluquer\u00cda Mixta",
    "sg:phone":"+34 986 20 55 77",
    "sg:postcode":"36210",
    "sg:province":"Pontevedra",
    "wof:name":"Peluqueria Lucris S.l.",
    "wof:placetype":"venue"
},
  "geometry": {"coordinates":[-8.6428003311,42.4304618835],"type":"Point"}
}