{
  "type": "Feature",
  "properties": {
    "addr:full":"Calle de Luna (la), 6 Santa Cruz De Tenerife Santa Cruz De Tenerife 38002",
    "addr:housenumber":"6",
    "addr:postcode":"38002",
    "addr:street":"Calle De Luna La",
    "iso:country":"ES",
    "sg:address":"Calle de Luna (la), 6",
    "sg:city":"Santa Cruz De Tenerife",
    "sg:orig_category":"Turismo",
    "sg:phone":"+34 922 28 68 50",
    "sg:postcode":"38002",
    "sg:province":"Santa Cruz De Tenerife",
    "wof:name":"Bricarmarr Travel S. L.",
    "wof:placetype":"venue"
},
  "geometry": {"coordinates":[-16.2509822845,28.4697093964],"type":"Point"}
}