{
  "type": "Feature",
  "properties": {
    "addr:full":"Calle de Santa Ana, 4 Lagartera Toledo 45567",
    "addr:housenumber":"4",
    "addr:postcode":"45567",
    "addr:street":"Calle De Santa Ana",
    "iso:country":"ES",
    "sg:address":"Calle de Santa Ana, 4",
    "sg:city":"Lagartera",
    "sg:orig_category":"Bordado, Marcado A Medida",
    "sg:phone":"+34 925 43 08 62",
    "sg:postcode":"45567",
    "sg:province":"Toledo",
    "wof:name":"Amor Iglesias Antonio",
    "wof:placetype":"venue"
},
  "geometry": {"coordinates":[-5.2021698952,39.9054489136],"type":"Point"}
}