{
  "type": "Feature",
  "properties": {
    "iso:country":"ES",
    "sg:address":"Calle de Marcelo Macias, 3",
    "sg:city":"Villanueva Serena",
    "sg:orig_category":"Peleter\u00cdas",
    "sg:phone":"+34 924 84 13 97",
    "sg:postcode":"06700",
    "sg:province":"Badajoz",
    "wof:name":"Gallardo Garcia Alejo",
    "wof:placetype":"venue"
},
  "geometry": {"coordinates":[-5.7973589897,38.9725532532],"type":"Point"}
}