{
  "type": "Feature",
  "properties": {
    "addr:full":"Calle de Fuensanta, 38 Roda Albacete 02630",
    "addr:housenumber":"38",
    "addr:postcode":"02630",
    "addr:street":"Calle De Fuensanta",
    "iso:country":"ES",
    "sg:address":"Calle de Fuensanta, 38",
    "sg:city":"Roda",
    "sg:orig_category":"Fabricaci\u00d3n De Taburetes, Sillas Y Sillones",
    "sg:phone":"+34 967 44 20 23",
    "sg:postcode":"02630",
    "sg:province":"Albacete",
    "wof:name":"Mesas Parre\u00f1o Y Tebar S.l.",
    "wof:placetype":"venue"
},
  "geometry": {"coordinates":[-2.1487939358,39.2068634033],"type":"Point"}
}