{
  "type": "Feature",
  "properties": {
    "iso:country":"ES",
    "sg:address":"Avda Espa\u00d1a, S/n",
    "sg:city":"Pedraja Portillo",
    "sg:orig_category":"Asilos De Ancianos. Centros Privados",
    "sg:phone":"+34 983 55 31 85",
    "sg:postcode":"47196",
    "sg:province":"Valladolid",
    "wof:name":"Gil Hernandez Juan Jorge",
    "wof:placetype":"venue"
},
  "geometry": {"coordinates":[-4.6446948051,41.4725608826],"type":"Point"}
}