{
  "type": "Feature",
  "properties": {
    "addr:full":"Rua Tomas A Alonso, 16 Vigo Pontevedra 36208",
    "addr:housenumber":"16",
    "addr:postcode":"36208",
    "addr:street":"Rua Tomas A Alonso",
    "iso:country":"ES",
    "sg:address":"Rua Tomas A Alonso, 16",
    "sg:city":"Vigo",
    "sg:orig_category":"Inform\u00c1tica (estudios, Servicios, Asesor\u00cda, Formaci\u00d3n)",
    "sg:phone":"+34 986 20 17 02",
    "sg:postcode":"36208",
    "sg:province":"Pontevedra",
    "wof:name":"Sistac-ils S.l.",
    "wof:placetype":"venue"
},
  "geometry": {"coordinates":[-8.7333726883,42.2267608643],"type":"Point"}
}