{
  "type": "Feature",
  "properties": {
    "addr:full":"Avda. Pamplona, 39 Iru\u00f1a Navarra 31009",
    "addr:housenumber":"39",
    "addr:postcode":"31009",
    "addr:street":"Avda. Pamplona",
    "iso:country":"ES",
    "sg:address":"Avda. Pamplona, 39",
    "sg:city":"Iru\u00f1a",
    "sg:orig_category":"Farmacias",
    "sg:phone":"+34 948 18 15 68",
    "sg:postcode":"31009",
    "sg:province":"Navarra",
    "wof:name":"Morera Luzan Maria Teresa",
    "wof:placetype":"venue"
},
  "geometry": {"coordinates":[-1.6732770205,42.805141449],"type":"Point"}
}