{
  "type": "Feature",
  "properties": {
    "addr:full":"Calle de Doctor Nuez Aguilar, 42 Palmas De Gran Canaria Las Palmas 35001",
    "addr:housenumber":"42",
    "addr:postcode":"35001",
    "addr:street":"Calle De Doctor Nuez Aguilar",
    "iso:country":"ES",
    "sg:address":"Calle de Doctor Nuez Aguilar, 42",
    "sg:city":"Palmas De Gran Canaria",
    "sg:orig_category":"Procuradores",
    "sg:phone":"+34 928 31 69 72",
    "sg:postcode":"35001",
    "sg:province":"Las Palmas",
    "wof:name":"Ojeda Rodriguez Francisco",
    "wof:placetype":"venue"
},
  "geometry": {"coordinates":[-15.415813446,28.0963954926],"type":"Point"}
}