{
  "type": "Feature",
  "properties": {
    "iso:country":"ES",
    "sg:address":"Calle de Molino (el), 113",
    "sg:city":"Caudete",
    "sg:orig_category":"Asilos De Ancianos. Centros Privados",
    "sg:phone":"+34 965 82 70 76",
    "sg:postcode":"02660",
    "sg:province":"Albacete",
    "wof:name":"Fundacion Benefica Martinez-teresa Y Ruiz",
    "wof:placetype":"venue"
},
  "geometry": {"coordinates":[-0.9823499918,38.7081222534],"type":"Point"}
}