{
  "type": "Feature",
  "properties": {
    "iso:country":"ES",
    "sg:address":"Calle de San Juan, 25",
    "sg:city":"Gernika-lumo",
    "sg:orig_category":"Institutos De Belleza",
    "sg:phone":"+34 946 25 76 71",
    "sg:postcode":"48300",
    "sg:province":"Vizcaya",
    "wof:name":"Miren Garbi\u00f1e Amillategui Bidaguren",
    "wof:placetype":"venue"
},
  "geometry": {"coordinates":[-2.6769061089,43.3167457581],"type":"Point"}
}