{
  "type": "Feature",
  "properties": {
    "addr:full":"Carrer de Corsega, 544 Barcelona Barcelona 08025",
    "addr:housenumber":"544",
    "addr:postcode":"08025",
    "addr:street":"Carrer De Corsega",
    "iso:country":"ES",
    "sg:address":"Carrer de Corsega, 544",
    "sg:city":"Barcelona",
    "sg:orig_category":"Ense\u00d1anza, Formaci\u00d3n Profesional: Aprendizaje",
    "sg:phone":"+34 934 36 23 52",
    "sg:postcode":"08025",
    "sg:province":"Barcelona",
    "wof:name":"Institut Municipal D'educacio De Barcelona",
    "wof:placetype":"venue"
},
  "geometry": {"coordinates":[2.1727468967,41.4064712524],"type":"Point"}
}