{
  "type": "Feature",
  "properties": {
    "iso:country":"ES",
    "sg:address":"Cno. Relucido, S/n",
    "sg:city":"Malpica Tajo",
    "sg:orig_category":"Arenas, Guijarros Y Granulados",
    "sg:phone":"+34 925 87 65 78",
    "sg:postcode":"45692",
    "sg:province":"Toledo",
    "wof:name":"Aridos Toledo S.a.",
    "wof:placetype":"venue"
},
  "geometry": {"coordinates":[-4.0244760513,39.8567771912],"type":"Point"}
}