{
  "type": "Feature",
  "properties": {
    "addr:full":"Pase Alcobendas (de), 10 Alcobendas Madrid 28109",
    "addr:postcode":"28109",
    "iso:country":"ES",
    "sg:address":"Pase Alcobendas (de), 10",
    "sg:city":"Alcobendas",
    "sg:orig_category":"Confecci\u00d3n (fabricaci\u00d3n, Al Por Mayor)",
    "sg:phone":"+34 916 50 47 48",
    "sg:postcode":"28109",
    "sg:province":"Madrid",
    "wof:name":"Galbete Perez-pla Martin",
    "wof:placetype":"venue"
},
  "geometry": {"coordinates":[-3.6259670258,40.5268707275],"type":"Point"}
}