{
  "type": "Feature",
  "properties": {
    "addr:full":"Calle de Arene, 7 Getxo Vizcaya 48990",
    "addr:housenumber":"7",
    "addr:postcode":"48990",
    "addr:street":"Calle De Arene",
    "iso:country":"ES",
    "sg:address":"Calle de Arene, 7",
    "sg:city":"Getxo",
    "sg:orig_category":"Ense\u00d1anza Variada",
    "sg:phone":"+34 944 30 28 95",
    "sg:postcode":"48990",
    "sg:province":"Vizcaya",
    "sg:website":"www.escueladeteatrodegetxo.com",
    "wof:name":"Escuela De Teatro De Getxo- Getxoko Antzerki Eskola Sl",
    "wof:placetype":"venue"
},
  "geometry": {"coordinates":[-3.0037560463,43.347869873],"type":"Point"}
}