{
  "type": "Feature",
  "properties": {
    "addr:full":"Carrer de Sant Bartomeu, 51 Campello Alicante 03560",
    "addr:housenumber":"51",
    "addr:postcode":"03560",
    "addr:street":"Carrer De Sant Bartomeu",
    "iso:country":"ES",
    "sg:address":"Carrer de Sant Bartomeu, 51",
    "sg:city":"Campello",
    "sg:orig_category":"Caf\u00c9s, Bares, Cervecer\u00cdas",
    "sg:phone":"+34 965 63 23 91",
    "sg:postcode":"03560",
    "sg:province":"Alicante",
    "wof:name":"Bernabeu Planelles Jose",
    "wof:placetype":"venue"
},
  "geometry": {"coordinates":[-0.3911089897,38.4261322021],"type":"Point"}
}