{
  "type": "Feature",
  "properties": {
    "addr:full":"Pla\u00c7 Jacint Verdaguer, 5 Bisbal D'emporda Girona 17100",
    "addr:housenumber":"5",
    "addr:postcode":"17100",
    "addr:street":"Verdaguer",
    "iso:country":"ES",
    "sg:address":"Pla\u00c7 Jacint Verdaguer, 5",
    "sg:city":"Bisbal D'emporda",
    "sg:orig_category":"Ense\u00d1anza: Profesiones Art\u00cdsticas",
    "sg:phone":"+34 972 64 03 95",
    "sg:postcode":"17100",
    "sg:province":"Girona",
    "wof:name":"Tor Prunell Quim",
    "wof:placetype":"venue"
},
  "geometry": {"coordinates":[2.8187398911,41.9808616638],"type":"Point"}
}