{
  "type": "Feature",
  "properties": {
    "iso:country":"ES",
    "sg:address":"Calle de Borrull, 24",
    "sg:city":"Valencia",
    "sg:orig_category":"Fabricaci\u00d3n De Su\u00c9ters Y Chalecos De Punto",
    "sg:phone":"+34 963 91 27 77",
    "sg:postcode":"46008",
    "sg:province":"Valencia",
    "wof:name":"Saldos Canarias S.l.",
    "wof:placetype":"venue"
},
  "geometry": {"coordinates":[-0.3860855103,39.4746322632],"type":"Point"}
}