{
  "type": "Feature",
  "properties": {
    "addr:full":"Calle de Santos Justo Y Pastor, 63 Valencia Valencia 46022",
    "addr:housenumber":"63",
    "addr:postcode":"46022",
    "addr:street":"Calle De Santos Justo Y Pastor",
    "iso:country":"ES",
    "sg:address":"Calle de Santos Justo Y Pastor, 63",
    "sg:city":"Valencia",
    "sg:orig_category":"Cerrajer\u00cda, Ferrallista",
    "sg:phone":"+34 963 72 78 64",
    "sg:postcode":"46022",
    "sg:province":"Valencia",
    "sg:website":"www.ferreteriacollado.com",
    "wof:name":"Collado Lopez Francisco",
    "wof:placetype":"venue"
},
  "geometry": {"coordinates":[-0.3466930091,39.469379425],"type":"Point"}
}