{
  "type": "Feature",
  "properties": {
    "addr:full":"Rond Roca Blanca, 34 Mataro Barcelona 08303",
    "addr:housenumber":"34",
    "addr:postcode":"08303",
    "addr:street":"Blanca",
    "iso:country":"ES",
    "sg:address":"Rond Roca Blanca, 34",
    "sg:city":"Mataro",
    "sg:orig_category":"Internados & Ense\u00d1anza Privada",
    "sg:phone":"+34 937 98 19 06",
    "sg:postcode":"08303",
    "sg:province":"Barcelona",
    "wof:name":"Fundacio Eduard Trens Berenguer",
    "wof:placetype":"venue"
},
  "geometry": {"coordinates":[2.4275770187,41.5444450378],"type":"Point"}
}