{
  "type": "Feature",
  "properties": {
    "addr:full":"Carr Jaume Ribo, 32 Badalona Barcelona 08911",
    "addr:housenumber":"32",
    "addr:postcode":"08911",
    "addr:street":"Carr Jaume Ribo",
    "iso:country":"ES",
    "sg:address":"Carr Jaume Ribo, 32",
    "sg:city":"Badalona",
    "sg:orig_category":"Transportes Por V\u00cdas Navegables",
    "sg:phone":"+34 933 89 32 35",
    "sg:postcode":"08911",
    "sg:province":"Barcelona",
    "wof:name":"Transervicios Morros S.a.",
    "wof:placetype":"venue"
},
  "geometry": {"coordinates":[2.2581601143,41.4584465027],"type":"Point"}
}