{
  "type": "Feature",
  "properties": {
    "addr:full":"Carrer de Can Sans, 77 S. Andreu Llavaneres Barcelona 08392",
    "addr:housenumber":"77",
    "addr:postcode":"08392",
    "addr:street":"Carrer De Can Sans;S. Andreu Llavaneres Barcelona",
    "iso:country":"ES",
    "sg:address":"Carrer de Can Sans, 77",
    "sg:city":"S. Andreu Llavaneres",
    "sg:orig_category":"Organismos De Reclutamiento",
    "sg:phone":"+34 937 92 71 72",
    "sg:postcode":"08392",
    "sg:province":"Barcelona",
    "wof:name":"Servicios De Consultoria Sermas S.l.",
    "wof:placetype":"venue"
},
  "geometry": {"coordinates":[2.4849700928,41.5697517395],"type":"Point"}
}