{
  "type": "Feature",
  "properties": {
    "iso:country":"ES",
    "sg:address":"Calle de Madre De Dios, 56",
    "sg:city":"Logro\u00f1o",
    "sg:orig_category":"Frutas, Legumbres Frescas Y Tempranas (al Por Menor)",
    "sg:phone":"+34 941 24 87 53",
    "sg:postcode":"26004",
    "sg:province":"La Rioja",
    "wof:name":"Martinez Pascual Daniel",
    "wof:placetype":"venue"
},
  "geometry": {"coordinates":[-2.431180954,42.468296051],"type":"Point"}
}