{
  "type": "Feature",
  "properties": {
    "addr:full":"Calle de Conde Vallellano, 8 Cevico De La Torre Palencia 34218",
    "addr:housenumber":"8",
    "addr:postcode":"34218",
    "addr:street":"Calle De Conde Vallellano",
    "iso:country":"ES",
    "sg:address":"Calle de Conde Vallellano, 8",
    "sg:city":"Cevico De La Torre",
    "sg:orig_category":"Carnicer\u00cdas, Carnicer\u00cdas",
    "sg:phone":"+34 979 78 30 25",
    "sg:postcode":"34218",
    "sg:province":"Palencia",
    "wof:name":"Medina Calleja Vicente",
    "wof:placetype":"venue"
},
  "geometry": {"coordinates":[-4.4671144485,41.7978477478],"type":"Point"}
}