{
  "type": "Feature",
  "properties": {
    "iso:country":"ES",
    "sg:address":"Calle de Jose Benlliure, 115",
    "sg:city":"Valencia",
    "sg:orig_category":"Zapatos (al Por Menor)",
    "sg:phone":"+34 963 55 03 61",
    "sg:postcode":"46011",
    "sg:province":"Valencia",
    "wof:name":"Calzados Amparo Zamora S.l.",
    "wof:placetype":"venue"
},
  "geometry": {"coordinates":[-0.3308039904,39.4673805237],"type":"Point"}
}