{
  "type": "Feature",
  "properties": {
    "iso:country":"ES",
    "sg:address":"Rua San Froilan, 23",
    "sg:city":"Lugo",
    "sg:orig_category":"Art\u00cdculos De Decoraci\u00d3n",
    "sg:phone":"+34 982 22 35 20",
    "sg:postcode":"27001",
    "sg:province":"Lugo",
    "wof:name":"Vazquez Diaz Carlos",
    "wof:placetype":"venue"
},
  "geometry": {"coordinates":[-7.5599999428,43.0134887695],"type":"Point"}
}