{
  "type": "Feature",
  "properties": {
    "iso:country":"ES",
    "sg:address":"La Ballena, S/n",
    "sg:city":"Antas",
    "sg:orig_category":"Producci\u00d3n, Venta De Productos De Agricultura Biol\u00d3gica",
    "sg:phone":"+34 950 52 85 42",
    "sg:postcode":"04628",
    "sg:province":"Almer\u00eda",
    "wof:name":"Sat 9053 Hermanos Jimenez",
    "wof:placetype":"venue"
},
  "geometry": {"coordinates":[-1.9216589928,37.2441215515],"type":"Point"}
}