{
  "type": "Feature",
  "properties": {
    "iso:country":"ES",
    "sg:address":"Carr Albesa, S/n",
    "sg:city":"Portella",
    "sg:orig_category":"Cooperativas Agr\u00cdcolas",
    "sg:phone":"+34 973 18 65 56",
    "sg:postcode":"25134",
    "sg:province":"Lleida",
    "wof:name":"Sdad.coop.sant Domenec",
    "wof:placetype":"venue"
},
  "geometry": {"coordinates":[0.6398419738,41.7387123108],"type":"Point"}
}