{
  "type": "Feature",
  "properties": {
    "iso:country":"ES",
    "sg:address":"Carrer de Trinxant, 130",
    "sg:city":"Barcelona",
    "sg:orig_category":"Carnicer\u00cdas, Carnicer\u00cdas",
    "sg:phone":"+34 933 40 50 48",
    "sg:postcode":"08041",
    "sg:province":"Barcelona",
    "wof:name":"Arjona Pabon Juan",
    "wof:placetype":"venue"
},
  "geometry": {"coordinates":[2.1817736626,41.41746521],"type":"Point"}
}