{
  "type": "Feature",
  "properties": {
    "addr:full":"C/ Montduber, 21 Alcoi Alicante 03802",
    "addr:housenumber":"21",
    "addr:postcode":"03802",
    "addr:street":"C / Montduber",
    "iso:country":"ES",
    "sg:address":"C/ Montduber, 21",
    "sg:city":"Alcoi",
    "sg:orig_category":"Electricidad, Electr\u00d3nica: Material Y Suministros (al Por Mayor)",
    "sg:phone":"+34 965 33 40 31",
    "sg:postcode":"03802",
    "sg:province":"Alicante",
    "wof:name":"Tarkin Trade S. L.",
    "wof:placetype":"venue"
},
  "geometry": {"coordinates":[-0.5725259781,38.6851272583],"type":"Point"}
}