{
  "type": "Feature",
  "properties": {
    "iso:country":"ES",
    "sg:address":"Calle de Hospital De San Jose, 59",
    "sg:city":"Getafe",
    "sg:orig_category":"Molduras, Junquillos, Listones Y Molduras Perforadas",
    "sg:phone":"+34 916 95 95 38",
    "sg:postcode":"28901",
    "sg:province":"Madrid",
    "wof:name":"Fernandez Bermejo Jose",
    "wof:placetype":"venue"
},
  "geometry": {"coordinates":[-3.7271308899,40.3054924011],"type":"Point"}
}