{
  "type": "Feature",
  "properties": {
    "iso:country":"ES",
    "sg:address":"Calle de Cid (del), 5",
    "sg:city":"Alcorcon",
    "sg:orig_category":"Impresores",
    "sg:phone":"+34 916 19 02 76",
    "sg:postcode":"28921",
    "sg:province":"Madrid",
    "wof:name":"Dsi Nieto Asesoramiento Informatico Sll",
    "wof:placetype":"venue"
},
  "geometry": {"coordinates":[-3.8291590214,40.3499336243],"type":"Point"}
}