{
  "type": "Feature",
  "properties": {
    "addr:full":"Calle de Larga, 67 Navalvillar Pela Badajoz 06760",
    "addr:housenumber":"67",
    "addr:postcode":"06760",
    "addr:street":"Calle De Larga",
    "iso:country":"ES",
    "sg:address":"Calle de Larga, 67",
    "sg:city":"Navalvillar Pela",
    "sg:classifiers":[
        {
            "category":"Taxi",
            "type":"Transportation"
        }
    ],
    "sg:phone":"+34 924 86 04 21",
    "sg:postcode":"06760",
    "sg:province":"Badajoz",
    "wof:name":"Rodriguez Gomez Anselmo",
    "wof:placetype":"venue"
},
  "geometry": {"coordinates":[-5.4720492363,39.0930976868],"type":"Point"}
}