{
  "type": "Feature",
  "properties": {
    "addr:full":"Carrer de Doctor Fleming, 1 Riudoms Tarragona 43330",
    "addr:housenumber":"1",
    "addr:postcode":"43330",
    "addr:street":"Carrer De Doctor Fleming",
    "iso:country":"ES",
    "sg:address":"Carrer de Doctor Fleming, 1",
    "sg:city":"Riudoms",
    "sg:orig_category":"Farmacias",
    "sg:phone":"+34 977 85 01 91",
    "sg:postcode":"43330",
    "sg:province":"Tarragona",
    "wof:name":"Pallissa 98 S.l.",
    "wof:placetype":"venue"
},
  "geometry": {"coordinates":[1.0512200594,41.1397399902],"type":"Point"}
}