{
  "type": "Feature",
  "properties": {
    "iso:country":"ES",
    "sg:address":"Calle de Mizar, 3",
    "sg:city":"Madrid",
    "sg:orig_category":"Ingenier\u00cda, Centros De Estudios (diversos)",
    "sg:phone":"+34 913 57 20 71",
    "sg:postcode":"28023",
    "sg:province":"Madrid",
    "sg:website":"www.ingeser.es",
    "wof:name":"Servicios De Ingenieria Y Gestion S. A.",
    "wof:placetype":"venue"
},
  "geometry": {"coordinates":[-3.7848041058,40.456703186],"type":"Point"}
}