{
  "type": "Feature",
  "properties": {
    "addr:full":"Calle de Cruz De Candelaria, 15 San Cristobal De La Laguna Santa Cruz De Tenerife 38203",
    "addr:housenumber":"15",
    "addr:postcode":"38203",
    "addr:street":"Calle De Cruz De Candelaria",
    "iso:country":"ES",
    "sg:address":"Calle de Cruz De Candelaria, 15",
    "sg:city":"San Cristobal De La Laguna",
    "sg:orig_category":"Inform\u00c1tica: Mini Y Grandes Sistemas (venta, Instalaci\u00d3n, Mantenimiento)",
    "sg:phone":"+34 922 26 41 33",
    "sg:postcode":"38203",
    "sg:province":"Santa Cruz De Tenerife",
    "wof:name":"Mantenimientos Informaticos De Tenerife S.l.",
    "wof:placetype":"venue"
},
  "geometry": {"coordinates":[-16.32264328,28.4871311188],"type":"Point"}
}