{
  "type": "Feature",
  "properties": {
    "iso:country":"ES",
    "sg:address":"Carr Major, 76",
    "sg:city":"Seu D'urgell",
    "sg:orig_category":"Confecci\u00d3n (fabricaci\u00d3n, Al Por Mayor)",
    "sg:phone":"+34 973 35 29 68",
    "sg:postcode":"25700",
    "sg:province":"Lleida",
    "wof:name":"Isern Soldevila Pilar",
    "wof:placetype":"venue"
},
  "geometry": {"coordinates":[0.6243339777,41.6133575439],"type":"Point"}
}