{
  "type": "Feature",
  "properties": {
    "addr:full":"Calle de Moral, 2 Villanueva Cordoba C\u00f3rdoba 14440",
    "addr:housenumber":"2;cordoba co\u0301rdoba",
    "addr:postcode":"14440",
    "addr:street":"Calle De Moral",
    "iso:country":"ES",
    "sg:address":"Calle de Moral, 2",
    "sg:city":"Villanueva Cordoba",
    "sg:orig_category":"Centros Empresariales",
    "sg:phone":"+34 957 12 19 83",
    "sg:postcode":"14440",
    "sg:province":"C\u00f3rdoba",
    "wof:name":"Feryga S.l.",
    "wof:placetype":"venue"
},
  "geometry": {"coordinates":[-4.627518177,38.3235168457],"type":"Point"}
}