{
  "type": "Feature",
  "properties": {
    "iso:country":"ES",
    "sg:address":"Carr Lluis Companys, S/n",
    "sg:city":"Borges Blanques",
    "sg:orig_category":"Maquinaria Para Industrias Diversas",
    "sg:phone":"+34 973 14 25 25",
    "sg:postcode":"25400",
    "sg:province":"Lleida",
    "wof:name":"Marti Roig Jaime",
    "wof:placetype":"venue"
},
  "geometry": {"coordinates":[0.8739200234,41.5184555054],"type":"Point"}
}