{
  "type": "Feature",
  "properties": {
    "addr:full":"Carrer de Neptu, 85 Terrassa Barcelona 08228",
    "addr:housenumber":"85",
    "addr:postcode":"08228",
    "addr:street":"Carrer De Neptu",
    "iso:country":"ES",
    "sg:address":"Carrer de Neptu, 85",
    "sg:city":"Terrassa",
    "sg:orig_category":"Negocio De Madera",
    "sg:phone":"+34 937 31 01 78",
    "sg:postcode":"08228",
    "sg:province":"Barcelona",
    "wof:name":"Tarrasa Cocinas S.l.",
    "wof:placetype":"venue"
},
  "geometry": {"coordinates":[2.037981987,41.5400924683],"type":"Point"}
}