{
  "type": "Feature",
  "properties": {
    "addr:full":"Calle de Zaragoza, 6 Arganda Madrid 28500",
    "addr:housenumber":"6",
    "addr:postcode":"28500",
    "addr:street":"Calle De Zaragoza",
    "iso:country":"ES",
    "sg:address":"Calle de Zaragoza, 6",
    "sg:city":"Arganda",
    "sg:orig_category":"Fabricaci\u00d3n, Distribuci\u00d3n De Material Para La Climatizaci\u00d3n, Aireaci\u00d3n Y Ventilaci\u00d3n",
    "sg:phone":"+34 918 71 09 41",
    "sg:postcode":"28500",
    "sg:province":"Madrid",
    "wof:name":"Airdiru S.l.",
    "wof:placetype":"venue"
},
  "geometry": {"coordinates":[-3.4558289051,40.3069000244],"type":"Point"}
}