{
  "type": "Feature",
  "properties": {
    "iso:country":"ES",
    "sg:address":"Calle de Dos Hermanas, 6",
    "sg:city":"Le\u00f3n",
    "sg:orig_category":"Comercio De Mobiliario De Oficina",
    "sg:phone":"+34 987 21 33 54",
    "sg:postcode":"24005",
    "sg:province":"Le\u00f3n",
    "wof:name":"3 C Equipamientos Integrales De Oficina Y Colectividades S-l.",
    "wof:placetype":"venue"
},
  "geometry": {"coordinates":[-5.566356,42.589241],"type":"Point"}
}