{
  "type": "Feature",
  "properties": {
    "addr:full":"Calle de Antillas, 2 Puerto De Santa Maria C\u00e1diz 11500",
    "addr:housenumber":"2",
    "addr:postcode":"11500",
    "addr:street":"Calle De Antillas;Ca\u0301Diz",
    "iso:country":"ES",
    "sg:address":"Calle de Antillas, 2",
    "sg:city":"Puerto De Santa Maria",
    "sg:orig_category":"Institutos De Belleza",
    "sg:phone":"+34 956 54 13 28",
    "sg:postcode":"11500",
    "sg:province":"C\u00e1diz",
    "wof:name":"Galan Monta\u00f1o Maria Del Carmen",
    "wof:placetype":"venue"
},
  "geometry": {"coordinates":[-6.2447977066,36.59375],"type":"Point"}
}