{
  "type": "Feature",
  "properties": {
    "addr:full":"Carrer de Jesus, 48 Calafell Tarragona 43820",
    "addr:housenumber":"48",
    "addr:postcode":"43820",
    "addr:street":"Carrer De Jesus",
    "iso:country":"ES",
    "sg:address":"Carrer de Jesus, 48",
    "sg:city":"Calafell",
    "sg:orig_category":"Contenedores (mercanc\u00cdas)",
    "sg:phone":"+34 977 69 40 12",
    "sg:postcode":"43820",
    "sg:province":"Tarragona",
    "wof:name":"Pedro Romagosa Jose",
    "wof:placetype":"venue"
},
  "geometry": {"coordinates":[1.5698159933,41.1968803406],"type":"Point"}
}