{
  "type": "Feature",
  "properties": {
    "iso:country":"ES",
    "sg:address":"Calle de Ametzaga\u00d1a, 20",
    "sg:city":"Donostia-san Sebastian",
    "sg:orig_category":"Carnicer\u00cdas, Carnicer\u00cdas",
    "sg:phone":"+34 943 29 07 47",
    "sg:postcode":"20012",
    "sg:province":"Guip\u00f9zcoa",
    "wof:name":"Olaizola Pe\u00f1a Jose Antonio",
    "wof:placetype":"venue"
},
  "geometry": {"coordinates":[-1.9702757597,43.3165893555],"type":"Point"}
}