{
  "type": "Feature",
  "properties": {
    "addr:full":"Calle de Junco, 7 Madrid Madrid 28021",
    "addr:housenumber":"7",
    "addr:postcode":"madrid;28021",
    "addr:street":"Calle De Junco",
    "iso:country":"ES",
    "sg:address":"Calle de Junco, 7",
    "sg:city":"Madrid",
    "sg:orig_category":"Cristaler\u00cdas",
    "sg:phone":"+34 915 05 09 07",
    "sg:postcode":"28021",
    "sg:province":"Madrid",
    "wof:name":"Vidrio Crismol S.l.",
    "wof:placetype":"venue"
},
  "geometry": {"coordinates":[-3.7046220303,40.348072052],"type":"Point"}
}