{
  "type": "Feature",
  "properties": {
    "addr:full":"Atvia De Logro\u00f1o, Km. 0006,5 Zaragoza Zaragoza 50011",
    "addr:postcode":"50011",
    "addr:street":"Logron\u0303O Km. 0006,5",
    "iso:country":"ES",
    "sg:address":"Atvia De Logro\u00f1o, Km. 0006,5",
    "sg:city":"Zaragoza",
    "sg:orig_category":"Ingeniero",
    "sg:phone":"+34 976 34 96 00",
    "sg:postcode":"50011",
    "sg:province":"Zaragoza",
    "wof:name":"Nebra Alvarez Jose",
    "wof:placetype":"venue"
},
  "geometry": {"coordinates":[-0.9913589954,41.662853241],"type":"Point"}
}