{
  "type": "Feature",
  "properties": {
    "addr:full":"Altamira Bidea, 5 Iturriotz Guip\u00f9zcoa 20180",
    "addr:housenumber":"5",
    "addr:postcode":"20180",
    "addr:street":"Altamira Bidea;Guipu\u0300Zcoa",
    "iso:country":"ES",
    "sg:address":"Altamira Bidea, 5",
    "sg:city":"Iturriotz",
    "sg:orig_category":"Empresas De Limpieza",
    "sg:phone":"+34 943 49 16 00",
    "sg:postcode":"20180",
    "sg:province":"Guip\u00f9zcoa",
    "wof:name":"Limpiezas Etxegar S.l.",
    "wof:placetype":"venue"
},
  "geometry": {"coordinates":[-1.8629590273,43.2992401123],"type":"Point"}
}