{
  "type": "Feature",
  "properties": {
    "addr:full":"Calle de Ataulfo Argenta, 28 Palmas De Gran Canaria Las Palmas 35013",
    "addr:housenumber":"28",
    "addr:postcode":"35013",
    "addr:street":"Calle De Ataulfo Argenta",
    "iso:country":"ES",
    "sg:address":"Calle de Ataulfo Argenta, 28",
    "sg:city":"Palmas De Gran Canaria",
    "sg:orig_category":"Supermercados Y Hipermercados",
    "sg:phone":"+34 928 41 55 22",
    "sg:postcode":"35013",
    "sg:province":"Las Palmas",
    "wof:name":"Hercada S. L.",
    "wof:placetype":"venue"
},
  "geometry": {"coordinates":[-15.448225975,28.0938568115],"type":"Point"}
}