{
  "type": "Feature",
  "properties": {
    "iso:country":"ES",
    "sg:address":"Calle de Batalla De Brunete, 29",
    "sg:city":"Palmas De Gran Canaria",
    "sg:orig_category":"Asociaciones Y Clubs Deportivos",
    "sg:phone":"+34 928 41 18 10",
    "sg:postcode":"35013",
    "sg:province":"Las Palmas",
    "wof:name":"Rodriguez Dominguez Manuel",
    "wof:placetype":"venue"
},
  "geometry": {"coordinates":[-15.4485502243,28.0985965729],"type":"Point"}
}