{
  "type": "Feature",
  "properties": {
    "addr:full":"Carrer de Pardo, 65 Barcelona Barcelona 08016",
    "addr:housenumber":"65",
    "addr:postcode":"08016",
    "addr:street":"Carrer De Pardo",
    "iso:country":"ES",
    "sg:address":"Carrer de Pardo, 65",
    "sg:city":"Barcelona",
    "sg:orig_category":"Asociaciones Y Clubs Deportivos",
    "sg:phone":"+34 933 46 71 07",
    "sg:postcode":"08016",
    "sg:province":"Barcelona",
    "wof:name":"Gimnasio Sport Club S.l.",
    "wof:placetype":"venue"
},
  "geometry": {"coordinates":[2.1824090481,41.4297485352],"type":"Point"}
}