{
  "type": "Feature",
  "properties": {
    "iso:country":"ES",
    "sg:address":"Calle de Cirilo Santos, 27",
    "sg:city":"Santa Maria Del Paramo",
    "sg:orig_category":"Cajas Para Embalar",
    "sg:phone":"+34 987 35 09 29",
    "sg:postcode":"24240",
    "sg:province":"Le\u00f3n",
    "wof:name":"Caja Rural De Zamora",
    "wof:placetype":"venue"
},
  "geometry": {"coordinates":[-5.7493438721,42.3546447754],"type":"Point"}
}