{
  "type": "Feature",
  "properties": {
    "iso:country":"ES",
    "sg:address":"Avgd Marina, 10",
    "sg:city":"Alcudia",
    "sg:orig_category":"T\u00c9cnicos Veterinarios",
    "sg:phone":"+34 971 54 79 76",
    "sg:postcode":"07400",
    "sg:province":"Islas Baleares",
    "wof:name":"Bergas Quetglas Margarita",
    "wof:placetype":"venue"
},
  "geometry": {"coordinates":[3.1149499416,39.852180481],"type":"Point"}
}