{
  "type": "Feature",
  "properties": {
    "addr:full":"Av Mediterrani, 37 Poblenou Barcelona 08397",
    "addr:housenumber":"37",
    "addr:postcode":"08397",
    "addr:street":"Av Mediterrani",
    "iso:country":"ES",
    "sg:address":"Av Mediterrani, 37",
    "sg:city":"Poblenou",
    "sg:orig_category":"Ropa Para Se\u00d1oras Y Caballeros (al Por Menor)",
    "sg:phone":"+34 937 66 28 18",
    "sg:postcode":"08397",
    "sg:province":"Barcelona",
    "wof:name":"Olmo Garcia Manuel",
    "wof:placetype":"venue"
},
  "geometry": {"coordinates":[2.6727180481,41.6188735962],"type":"Point"}
}