{
  "type": "Feature",
  "properties": {
    "addr:full":"Plaz General Vara De Rey, 7 Madrid Madrid 28005",
    "addr:housenumber":"7",
    "addr:postcode":"madrid;28005",
    "addr:street":"Vara;Rey",
    "iso:country":"ES",
    "sg:address":"Plaz General Vara De Rey, 7",
    "sg:city":"Madrid",
    "sg:orig_category":"Obras Y Organismos Sociales",
    "sg:phone":"+34 913 66 05 98",
    "sg:postcode":"28005",
    "sg:province":"Madrid",
    "wof:name":"Mensajeros De La Paz Scp",
    "wof:placetype":"venue"
},
  "geometry": {"coordinates":[-3.7086250782,40.4091491699],"type":"Point"}
}