{
  "type": "Feature",
  "properties": {
    "iso:country":"ES",
    "sg:address":"Calle de Maestro Rodrigo, 2",
    "sg:city":"Olivares",
    "sg:orig_category":"Florister\u00cdas",
    "sg:phone":"+34 954 11 07 46",
    "sg:postcode":"41804",
    "sg:province":"Sevilla",
    "wof:name":"Olea Mu\u00f1oz Manuel",
    "wof:placetype":"venue"
},
  "geometry": {"coordinates":[-6.1501312256,37.3973121643],"type":"Point"}
}