{
  "type": "Feature",
  "properties": {
    "addr:full":"Don Carlos Sanchez La Fuente, 40 Archidona M\u00e1laga 29300",
    "addr:housenumber":"40",
    "addr:postcode":"29300",
    "addr:street":"La Fuente;Ma\u0301Laga",
    "iso:country":"ES",
    "sg:address":"Don Carlos Sanchez La Fuente, 40",
    "sg:city":"Archidona",
    "sg:orig_category":"Sociedades, Compa\u00d1\u00cdas Aseguradoras",
    "sg:phone":"+34 952 71 62 39",
    "sg:postcode":"29300",
    "sg:province":"M\u00e1laga",
    "wof:name":"Santa Lucia S. A.",
    "wof:placetype":"venue"
},
  "geometry": {"coordinates":[-4.3892679214,37.0961380005],"type":"Point"}
}