{
  "type": "Feature",
  "properties": {
    "iso:country":"ES",
    "sg:address":"Calle de Vicente Espinel, 1",
    "sg:city":"Madrid",
    "sg:orig_category":"Postigos, Persianas Y Celos\u00cdas",
    "sg:phone":"+34 914 07 39 90",
    "sg:postcode":"28017",
    "sg:province":"Madrid",
    "wof:name":"Vicar C.b",
    "wof:placetype":"venue"
},
  "geometry": {"coordinates":[-3.6410369873,40.4362602234],"type":"Point"}
}