{
  "type": "Feature",
  "properties": {
    "addr:full":"Calle de Morro Cubas, 10 Galletas Santa Cruz De Tenerife 38631",
    "addr:housenumber":"10",
    "addr:postcode":"38631",
    "addr:street":"Calle De Morro Cubas",
    "iso:country":"ES",
    "sg:address":"Calle de Morro Cubas, 10",
    "sg:city":"Galletas",
    "sg:orig_category":"Quincaller\u00cda (al Por Menor)",
    "sg:phone":"+34 922 78 52 52",
    "sg:postcode":"38631",
    "sg:province":"Santa Cruz De Tenerife",
    "wof:name":"Dominguez Diaz Inocencia",
    "wof:placetype":"venue"
},
  "geometry": {"coordinates":[-16.6552505493,28.0073356628],"type":"Point"}
}