{
  "type": "Feature",
  "properties": {
    "iso:country":"ES",
    "sg:address":"Calle de Lopez De Hoyos, 286",
    "sg:city":"Madrid",
    "sg:orig_category":"Edici\u00d3n De Diarios, Revistas, Boletines",
    "sg:phone":"+34 914 13 57 08",
    "sg:postcode":"28043",
    "sg:province":"Madrid",
    "sg:website":"www.edicioneselviso.com",
    "wof:name":"Gonzalez Sanchez Heredero Maria Teresa",
    "wof:placetype":"venue"
},
  "geometry": {"coordinates":[-3.6625540257,40.4548187256],"type":"Point"}
}