{
  "type": "Feature",
  "properties": {
    "addr:full":"Carrer de Major, 39 Santa Barbara Tarragona 43570",
    "addr:housenumber":"39",
    "addr:postcode":"43570",
    "addr:street":"Carrer De Major",
    "iso:country":"ES",
    "sg:address":"Carrer de Major, 39",
    "sg:city":"Santa Barbara",
    "sg:orig_category":"Molduras, Junquillos, Listones Y Molduras Perforadas",
    "sg:phone":"+34 977 71 81 26",
    "sg:postcode":"43570",
    "sg:province":"Tarragona",
    "wof:name":"Jove Molist Daniel",
    "wof:placetype":"venue"
},
  "geometry": {"coordinates":[0.4932639897,40.7147064209],"type":"Point"}
}