{
  "type": "Feature",
  "properties": {
    "iso:country":"ES",
    "sg:address":"Calle de Belizalde, 3",
    "sg:city":"Donostia-san Sebastian",
    "sg:orig_category":"Agencias Y Agentes Comerciales, Representantes",
    "sg:phone":"+34 943 46 43 42",
    "sg:postcode":"20009",
    "sg:province":"Guip\u00f9zcoa",
    "wof:name":"Representaciones Turper S.l.",
    "wof:placetype":"venue"
},
  "geometry": {"coordinates":[-1.9875340462,43.3112258911],"type":"Point"}
}