{
  "type": "Feature",
  "properties": {
    "iso:country":"ES",
    "sg:address":"Calle de Barrio Nuevo, 21",
    "sg:city":"Torrecilla De Los Angeles",
    "sg:orig_category":"Maquinaria Para Industrias Diversas",
    "sg:phone":"+34 927 67 70 18",
    "sg:postcode":"10869",
    "sg:province":"C\u00e1ceres",
    "wof:name":"Excavaciones Y Transportes El Guerra S.l.",
    "wof:placetype":"venue"
},
  "geometry": {"coordinates":[-6.413629055,40.2478294373],"type":"Point"}
}