{
  "type": "Feature",
  "properties": {
    "addr:full":"Carrer de Cura Fenoll, 18 Mutxamel Alicante 03110",
    "addr:housenumber":"18",
    "addr:postcode":"03110",
    "addr:street":"Carrer De Cura Fenoll",
    "iso:country":"ES",
    "sg:address":"Carrer de Cura Fenoll, 18",
    "sg:city":"Mutxamel",
    "sg:orig_category":"Cajas De Ahorro",
    "sg:phone":"+34 965 95 40 11",
    "sg:postcode":"03110",
    "sg:province":"Alicante",
    "sg:website":"www.bancaja.es",
    "wof:name":"Caja De Ahorros De Valencia Castellon Y Alicante",
    "wof:placetype":"venue"
},
  "geometry": {"coordinates":[-0.4456509948,38.4151763916],"type":"Point"}
}