{
  "type": "Feature",
  "properties": {
    "addr:full":"Calle de Matas, S/n Fuentes Nuevas Le\u00f3n 24411",
    "addr:housenumber":"s / n",
    "addr:postcode":"24411",
    "addr:street":"Calle De Matas",
    "iso:country":"ES",
    "sg:address":"Calle de Matas, S/n",
    "sg:city":"Fuentes Nuevas",
    "sg:orig_category":"Cortadoras, Tronzadoras, Cosechadoras (al Por Menor)",
    "sg:phone":"+34 987 45 57 14",
    "sg:postcode":"24411",
    "sg:province":"Le\u00f3n",
    "wof:name":"Industrias Cordero S.l.",
    "wof:placetype":"venue"
},
  "geometry": {"coordinates":[-6.6395339966,42.574180603],"type":"Point"}
}