{
  "type": "Feature",
  "properties": {
    "addr:full":"Javier-xabier Kalea, 2 Iru\u00f1a Navarra 31001",
    "addr:housenumber":"2",
    "addr:postcode":"31001",
    "addr:street":"Javier-Xabier Kalea",
    "iso:country":"ES",
    "sg:address":"Javier-xabier Kalea, 2",
    "sg:city":"Iru\u00f1a",
    "sg:orig_category":"Fabricaci\u00d3n De Art\u00cdculos Y Ornamentos Religiosos",
    "sg:phone":"+34 948 22 06 72",
    "sg:postcode":"31001",
    "sg:province":"Navarra",
    "wof:name":"Martinez Erro Alejandro",
    "wof:placetype":"venue"
},
  "geometry": {"coordinates":[-1.6418540478,42.8174057007],"type":"Point"}
}