{
  "type": "Feature",
  "properties": {
    "iso:country":"ES",
    "sg:address":"S. Dali, S/n",
    "sg:city":"S. Hilari Sacalm",
    "sg:orig_category":"Madera Para Construcci\u00d3n E Industria",
    "sg:phone":"+34 972 86 91 28",
    "sg:postcode":"17403",
    "sg:province":"Girona",
    "sg:website":"www.sinto.net",
    "wof:name":"Maiquez Timoneda Francesc",
    "wof:placetype":"venue"
},
  "geometry": {"coordinates":[2.524502039,41.7791442871],"type":"Point"}
}