{
  "type": "Feature",
  "properties": {
    "iso:country":"ES",
    "sg:address":"Calle de Tetuan, 1",
    "sg:city":"Union",
    "sg:orig_category":"Fisioterapia",
    "sg:phone":"+34 968 54 06 25",
    "sg:postcode":"30360",
    "sg:province":"Murcia",
    "wof:name":"Garcia Martinez Nerea",
    "wof:placetype":"venue"
},
  "geometry": {"coordinates":[-0.8840990067,37.6215133667],"type":"Point"}
}