{
  "type": "Feature",
  "properties": {
    "addr:full":"Carr Major, 6 Sarroca De Lleida Lleida 25175",
    "addr:housenumber":"6",
    "addr:postcode":"25175",
    "addr:street":"Carr Major",
    "iso:country":"ES",
    "sg:address":"Carr Major, 6",
    "sg:city":"Sarroca De Lleida",
    "sg:orig_category":"Empresarios",
    "sg:phone":"+34 973 12 60 17",
    "sg:postcode":"25175",
    "sg:province":"Lleida",
    "wof:name":"Salo Font Francisco",
    "wof:placetype":"venue"
},
  "geometry": {"coordinates":[0.5617930293,41.458114624],"type":"Point"}
}