{
  "type": "Feature",
  "properties": {
    "iso:country":"ES",
    "sg:address":"Carrer de Higini Angles, 2",
    "sg:city":"Tarragona",
    "sg:orig_category":"Alquiler De Casas Y Habitaciones Amuebladas",
    "sg:phone":"+34 977 22 75 54",
    "sg:postcode":"43001",
    "sg:province":"Tarragona",
    "wof:name":"Terroba Vives Josefa",
    "wof:placetype":"venue"
},
  "geometry": {"coordinates":[1.2458540201,41.1173324585],"type":"Point"}
}