{
  "type": "Feature",
  "properties": {
    "iso:country":"ES",
    "sg:address":"Avda Mexico De, 18",
    "sg:city":"Llanes",
    "sg:orig_category":"Peluquer\u00cdas, Peluquer\u00cda Mixta",
    "sg:phone":"+34 985 40 24 05",
    "sg:postcode":"33500",
    "sg:province":"Asturias",
    "wof:name":"Maria Teresa Lopez Mere Y Reyes Decos Miron Cdad",
    "wof:placetype":"venue"
},
  "geometry": {"coordinates":[-4.7568941116,43.4221076965],"type":"Point"}
}