{
  "type": "Feature",
  "properties": {
    "addr:full":"Calle de Iglesia, 17 Hontoria Del Pinar Burgos 09660",
    "addr:housenumber":"17",
    "addr:postcode":"09660",
    "addr:street":"Calle De Iglesia",
    "iso:country":"ES",
    "sg:address":"Calle de Iglesia, 17",
    "sg:city":"Hontoria Del Pinar",
    "sg:orig_category":"Iglesia Cat\u00d3lica",
    "sg:phone":"+34 947 38 60 55",
    "sg:postcode":"09660",
    "sg:province":"Burgos",
    "wof:name":"Parroquia De La Asuncion",
    "wof:placetype":"venue"
},
  "geometry": {"coordinates":[-3.1636867523,41.8486709595],"type":"Point"}
}