{
  "type": "Feature",
  "properties": {
    "addr:full":"B (p I Store), 21 Sevilla Sevilla 41008",
    "addr:housenumber":"21",
    "addr:postcode":"41008",
    "iso:country":"ES",
    "sg:address":"B (p I Store), 21",
    "sg:city":"Sevilla",
    "sg:orig_category":"Electricidad: Instaladores",
    "sg:phone":"+34 954 35 19 09",
    "sg:postcode":"41008",
    "sg:province":"Sevilla",
    "wof:name":"Cobra Instalaciones Y Servicios S.a.",
    "wof:placetype":"venue"
},
  "geometry": {"coordinates":[-5.9555239677,37.3941268921],"type":"Point"}
}