{
  "type": "Feature",
  "properties": {
    "addr:full":"Carr Ripollet, S/n Sarria Ter Girona 17840",
    "addr:housenumber":"s / n",
    "addr:postcode":"17840",
    "addr:street":"Carr Ripollet;Ter",
    "iso:country":"ES",
    "sg:address":"Carr Ripollet, S/n",
    "sg:city":"Sarria Ter",
    "sg:orig_category":"Mec\u00c1nico Del Autom\u00d3vil",
    "sg:phone":"+34 972 17 08 12",
    "sg:postcode":"17840",
    "sg:province":"Girona",
    "wof:name":"Bosch Llauger Juan",
    "wof:placetype":"venue"
},
  "geometry": {"coordinates":[2.8208498955,42.0173606873],"type":"Point"}
}