{
  "type": "Feature",
  "properties": {
    "addr:full":"Calle de Almirante Antonio De Aguilar, 7 San Mateo Murcia 30800",
    "addr:housenumber":"7",
    "addr:postcode":"30800",
    "addr:street":"Calle De Almirante Antonio De Aguilar",
    "iso:country":"ES",
    "sg:address":"Calle de Almirante Antonio De Aguilar, 7",
    "sg:city":"San Mateo",
    "sg:orig_category":"Molduras, Junquillos, Listones Y Molduras Perforadas",
    "sg:phone":"+34 968 46 22 54",
    "sg:postcode":"30800",
    "sg:province":"Murcia",
    "wof:name":"Valewnti Garcia Modesto",
    "wof:placetype":"venue"
},
  "geometry": {"coordinates":[-1.1298867464,37.9834747314],"type":"Point"}
}