{
  "type": "Feature",
  "properties": {
    "addr:full":"Avda Paz, 6 Palma Rio C\u00f3rdoba 14700",
    "addr:housenumber":"6",
    "addr:postcode":"14700",
    "addr:street":"Avda Paz;Rio Co\u0301Rdoba",
    "iso:country":"ES",
    "sg:address":"Avda Paz, 6",
    "sg:city":"Palma Rio",
    "sg:orig_category":"Cajas De Ahorro",
    "sg:phone":"+34 957 64 90 84",
    "sg:postcode":"14700",
    "sg:province":"C\u00f3rdoba",
    "wof:name":"Caja San Fernando De Sevilla Y Jerez",
    "wof:placetype":"venue"
},
  "geometry": {"coordinates":[-5.2769789696,37.6985740662],"type":"Point"}
}