{
  "type": "Feature",
  "properties": {
    "iso:country":"ES",
    "sg:address":"Calle de Comunidad Valenciana, 28",
    "sg:city":"Almoradi",
    "sg:orig_category":"Inmobiliaria (agencias)",
    "sg:phone":"+34 966 78 26 61",
    "sg:postcode":"03160",
    "sg:province":"Alicante",
    "wof:name":"Gestiones Financieras Almoradi S.l.",
    "wof:placetype":"venue"
},
  "geometry": {"coordinates":[-0.7885650992,38.1095962524],"type":"Point"}
}