{
  "type": "Feature",
  "properties": {
    "addr:full":"Plaz Avelino Vicente, 85 Guarda Pontevedra 36780",
    "addr:housenumber":"85",
    "addr:postcode":"36780",
    "addr:street":"Plaz Avelino Vicente",
    "iso:country":"ES",
    "sg:address":"Plaz Avelino Vicente, 85",
    "sg:city":"Guarda",
    "sg:orig_category":"Caf\u00c9s, Bares, Cervecer\u00cdas",
    "sg:phone":"+34 986 61 31 38",
    "sg:postcode":"36780",
    "sg:province":"Pontevedra",
    "wof:name":"Coello Gonzalez Agustin",
    "wof:placetype":"venue"
},
  "geometry": {"coordinates":[-8.8713140488,41.9025039673],"type":"Point"}
}