{
  "type": "Feature",
  "properties": {
    "addr:full":"Carrer de Sagrera, 76 Barcelona Barcelona 08027",
    "addr:housenumber":"76",
    "addr:postcode":"08027",
    "addr:street":"Carrer De Sagrera",
    "iso:country":"ES",
    "sg:address":"Carrer de Sagrera, 76",
    "sg:city":"Barcelona",
    "sg:orig_category":"Asesor\u00cda Sobre Comunicaci\u00d3n De Empresas",
    "sg:phone":"+34 934 08 58 06",
    "sg:postcode":"08027",
    "sg:province":"Barcelona",
    "wof:name":"Push Management S.l.",
    "wof:placetype":"venue"
},
  "geometry": {"coordinates":[2.1913189888,41.4231834412],"type":"Point"}
}