{
  "type": "Feature",
  "properties": {
    "iso:country":"ES",
    "sg:address":"Calle de General Diaz Porlier, 14",
    "sg:city":"Madrid",
    "sg:orig_category":"Poller\u00cda Y Caza (al Por Menor)",
    "sg:phone":"+34 915 75 84 37",
    "sg:postcode":"28001",
    "sg:province":"Madrid",
    "wof:name":"Hernanz Sanz Julio",
    "wof:placetype":"venue"
},
  "geometry": {"coordinates":[-3.6771101952,40.426361084],"type":"Point"}
}