{
  "type": "Feature",
  "properties": {
    "iso:country":"ES",
    "sg:address":"Carr Sant Pere, 8",
    "sg:city":"Gandia",
    "sg:orig_category":"M\u00c9dicos: Psiquiatr\u00cda",
    "sg:phone":"+34 962 86 38 54",
    "sg:postcode":"46700",
    "sg:province":"Valencia",
    "wof:name":"Andreu Perez Vicente",
    "wof:placetype":"venue"
},
  "geometry": {"coordinates":[-0.1535612047,38.9359817505],"type":"Point"}
}