{
  "type": "Feature",
  "properties": {
    "iso:country":"ES",
    "sg:address":"Calle de Postas, 19",
    "sg:city":"Ciudad Real",
    "sg:orig_category":"Confecci\u00d3n De Alpargatas",
    "sg:phone":"+34 926 21 21 53",
    "sg:postcode":"13001",
    "sg:province":"Ciudad Real",
    "wof:name":"Garcia Gomez Caraballo Diana Maria",
    "wof:placetype":"venue"
},
  "geometry": {"coordinates":[-3.930038929,38.9846878052],"type":"Point"}
}