{
  "type": "Feature",
  "properties": {
    "addr:full":"Calle de Monta\u00d1a Chica, S/n Cristianos Santa Cruz De Tenerife 38650",
    "addr:housenumber":"s / n",
    "addr:postcode":"38650",
    "addr:street":"Calle De Montan\u0303A Chica",
    "iso:country":"ES",
    "sg:address":"Calle de Monta\u00d1a Chica, S/n",
    "sg:city":"Cristianos",
    "sg:orig_category":"Reposter\u00cdas",
    "sg:phone":"+34 922 75 04 74",
    "sg:postcode":"38650",
    "sg:province":"Santa Cruz De Tenerife",
    "wof:name":"De La Rosa Adrian Luis",
    "wof:placetype":"venue"
},
  "geometry": {"coordinates":[-16.7171134949,28.0532512665],"type":"Point"}
}