{
  "type": "Feature",
  "properties": {
    "iso:country":"ES",
    "sg:address":"Calle de Miguel Yuste, 31",
    "sg:city":"Madrid",
    "sg:orig_category":"Porcelanas, Azulejos (fabricaci\u00d3n, Al Por Mayor)",
    "sg:phone":"+34 913 04 63 31",
    "sg:postcode":"28037",
    "sg:province":"Madrid",
    "wof:name":"Borras Escriva S. L.",
    "wof:placetype":"venue"
},
  "geometry": {"coordinates":[-3.6237440109,40.4375152588],"type":"Point"}
}