{
  "type": "Feature",
  "properties": {
    "addr:full":"Calle de Fueros De Navarra, 1 Cortes Navarra 31530",
    "addr:housenumber":"1",
    "addr:postcode":"31530",
    "addr:street":"Calle De Fueros De Navarra",
    "iso:country":"ES",
    "sg:address":"Calle de Fueros De Navarra, 1",
    "sg:city":"Cortes",
    "sg:orig_category":"Asesor\u00cda Sobre Comunicaci\u00d3n De Empresas",
    "sg:phone":"+34 948 81 07 02",
    "sg:postcode":"31530",
    "sg:province":"Navarra",
    "wof:name":"Mendia Marques Juan",
    "wof:placetype":"venue"
},
  "geometry": {"coordinates":[-1.4200450182,41.9211082458],"type":"Point"}
}