{
  "type": "Feature",
  "properties": {
    "addr:full":"Calle de Francia, 51 Elda Alicante 03600",
    "addr:housenumber":"51",
    "addr:postcode":"03600",
    "addr:street":"Calle De Francia",
    "iso:country":"ES",
    "sg:address":"Calle de Francia, 51",
    "sg:city":"Elda",
    "sg:orig_category":"Zapatos: Material, Suministros, Accesorios (fabricaci\u00d3n, Al Por Mayor)",
    "sg:phone":"+34 965 38 43 54",
    "sg:postcode":"03600",
    "sg:province":"Alicante",
    "wof:name":"Uniplan S. Coop. Valenciana L.",
    "wof:placetype":"venue"
},
  "geometry": {"coordinates":[-0.814627707,38.462146759],"type":"Point"}
}