{
  "type": "Feature",
  "properties": {
    "iso:country":"ES",
    "sg:address":"Avda General Lopez Dominguez, 19",
    "sg:city":"Marbella",
    "sg:orig_category":"Mec\u00c1nico Del Autom\u00d3vil",
    "sg:phone":"+34 952 77 24 86",
    "sg:postcode":"29600",
    "sg:province":"M\u00e1laga",
    "wof:name":"Taller Urbano S.l.",
    "wof:placetype":"venue"
},
  "geometry": {"coordinates":[-4.8769021034,36.5137634277],"type":"Point"}
}