{
  "type": "Feature",
  "properties": {
    "iso:country":"ES",
    "sg:address":"Pl Pau Casals, S/n",
    "sg:city":"Prat Llobregat",
    "sg:orig_category":"M\u00dasica Diversa",
    "sg:phone":"+34 933 70 80 90",
    "sg:postcode":"08820",
    "sg:province":"Barcelona",
    "wof:name":"Asociacion Musical Del Prat De Llobregat",
    "wof:placetype":"venue"
},
  "geometry": {"coordinates":[2.0941643715,41.3255653381],"type":"Point"}
}