{
  "type": "Feature",
  "properties": {
    "iso:country":"ES",
    "sg:address":"Avda Bierzo (el), 452",
    "sg:city":"Dehesas",
    "sg:orig_category":"Negocio De Madera",
    "sg:phone":"+34 987 42 00 69",
    "sg:postcode":"24390",
    "sg:province":"Le\u00f3n",
    "wof:name":"Maderas Aquilino S.l.",
    "wof:placetype":"venue"
},
  "geometry": {"coordinates":[-6.685280323,42.5241165161],"type":"Point"}
}