{
  "type": "Feature",
  "properties": {
    "addr:full":"Calle de Canal De Suez, 2 Madrid Madrid 28042",
    "addr:housenumber":"2",
    "addr:postcode":"28042",
    "addr:street":"Calle De Canal De Suez",
    "iso:country":"ES",
    "sg:address":"Calle de Canal De Suez, 2",
    "sg:city":"Madrid",
    "sg:orig_category":"Bares, Piano",
    "sg:phone":"+34 917 47 25 58",
    "sg:postcode":"28042",
    "sg:province":"Madrid",
    "wof:name":"Irel S.l.",
    "wof:placetype":"venue"
},
  "geometry": {"coordinates":[-3.5810804367,40.4708938599],"type":"Point"}
}