{
  "type": "Feature",
  "properties": {
    "addr:full":"Carrer de Sant Jaume (de), 17 Vilassar De Mar Barcelona 08340",
    "addr:housenumber":"17",
    "addr:postcode":"08340",
    "addr:street":"Carrer De Sant Jaume De",
    "iso:country":"ES",
    "sg:address":"Carrer de Sant Jaume (de), 17",
    "sg:city":"Vilassar De Mar",
    "sg:orig_category":"M\u00c9dicos: Neumolog\u00cda",
    "sg:phone":"+34 937 59 42 49",
    "sg:postcode":"08340",
    "sg:province":"Barcelona",
    "wof:name":"Vargas Medina Maida",
    "wof:placetype":"venue"
},
  "geometry": {"coordinates":[2.3901569843,41.5010414124],"type":"Point"}
}