{
  "type": "Feature",
  "properties": {
    "addr:full":"Calle de Fernando Gabriel, 20 Madrid Madrid 28017",
    "addr:housenumber":"20",
    "addr:postcode":"madrid;28017",
    "addr:street":"Calle De Fernando Gabriel",
    "iso:country":"ES",
    "sg:address":"Calle de Fernando Gabriel, 20",
    "sg:city":"Madrid",
    "sg:orig_category":"Inform\u00c1tica (estudios, Servicios, Asesor\u00cda, Formaci\u00d3n)",
    "sg:phone":"+34 913 04 15 04",
    "sg:postcode":"28017",
    "sg:province":"Madrid",
    "wof:name":"Martin Mu\u00f1oz Juan Carlos",
    "wof:placetype":"venue"
},
  "geometry": {"coordinates":[-3.6372020245,40.4249763489],"type":"Point"}
}