{
  "type": "Feature",
  "properties": {
    "addr:full":"Calle de Doctor Verneau, 4 Palmas De Gran Canaria Las Palmas 35001",
    "addr:housenumber":"4",
    "addr:postcode":"35001",
    "addr:street":"Calle De Doctor Verneau",
    "iso:country":"ES",
    "sg:address":"Calle de Doctor Verneau, 4",
    "sg:city":"Palmas De Gran Canaria",
    "sg:orig_category":"Abogados",
    "sg:phone":"+34 928 31 09 93",
    "sg:postcode":"35001",
    "sg:province":"Las Palmas",
    "wof:name":"Macias Del Toro Francisco",
    "wof:placetype":"venue"
},
  "geometry": {"coordinates":[-15.4151945114,28.0995845795],"type":"Point"}
}