{
  "type": "Feature",
  "properties": {
    "iso:country":"ES",
    "sg:address":"Ramil, 10",
    "sg:city":"Ramil",
    "sg:orig_category":"Venta, Instalaci\u00d3n De Cocinas",
    "sg:phone":"+34 982 54 80 24",
    "sg:postcode":"27630",
    "sg:province":"Lugo",
    "wof:name":"Fernandez Lopez Luis Angel",
    "wof:placetype":"venue"
},
  "geometry": {"coordinates":[-7.2405390739,42.7565994263],"type":"Point"}
}