{
  "type": "Feature",
  "properties": {
    "iso:country":"ES",
    "sg:address":"Carrer de Periodista Grane, 129",
    "sg:city":"Terrassa",
    "sg:orig_category":"Peluqueros: De Se\u00d1oras",
    "sg:phone":"+34 937 85 03 36",
    "sg:postcode":"08226",
    "sg:province":"Barcelona",
    "wof:name":"Nedin Figuero Beatriz",
    "wof:placetype":"venue"
},
  "geometry": {"coordinates":[2.0269811153,41.5736465454],"type":"Point"}
}