{
  "type": "Feature",
  "properties": {
    "addr:full":"Calle de Consolacion, 9 Torrelavega Cantabria 39300",
    "addr:housenumber":"9",
    "addr:postcode":"39300",
    "addr:street":"Calle De Consolacion",
    "iso:country":"ES",
    "sg:address":"Calle de Consolacion, 9",
    "sg:city":"Torrelavega",
    "sg:orig_category":"\u00d3ptica: Instrumentos (fabricaci\u00d3n)",
    "sg:phone":"+34 942 80 78 81",
    "sg:postcode":"39300",
    "sg:province":"Cantabria",
    "wof:name":"Bettschen Del Olmo Monica",
    "wof:placetype":"venue"
},
  "geometry": {"coordinates":[-4.0483021736,43.3491821289],"type":"Point"}
}