{
  "type": "Feature",
  "properties": {
    "addr:full":"Ctra Santa Creu De Calafell, Km. 0009,1 S. Boi Llobregat Barcelona 08830",
    "addr:postcode":"08830",
    "addr:street":"Ctra Santa Creu De Calafell Km. 0009,1 S.",
    "iso:country":"ES",
    "sg:address":"Ctra Santa Creu De Calafell, Km. 0009,1",
    "sg:city":"S. Boi Llobregat",
    "sg:orig_category":"Suministros Para Exposiciones, Ferias, Salones",
    "sg:phone":"+34 936 30 55 11",
    "sg:postcode":"08830",
    "sg:province":"Barcelona",
    "sg:website":"www.m30stands.com",
    "wof:name":"2003 S.a.",
    "wof:placetype":"venue"
},
  "geometry": {"coordinates":[2.048185,41.340012],"type":"Point"}
}