{
  "type": "Feature",
  "properties": {
    "iso:country":"ES",
    "sg:address":"Avda Juan Carlos I, S/n",
    "sg:city":"Velez-malaga",
    "sg:orig_category":"Negocio De Materiales De Construcci\u00d3n",
    "sg:phone":"+34 952 50 15 98",
    "sg:postcode":"29700",
    "sg:province":"M\u00e1laga",
    "wof:name":"Materiales De Construccion El Rancho, S.c.",
    "wof:placetype":"venue"
},
  "geometry": {"coordinates":[-4.0988202095,36.7621307373],"type":"Point"}
}