{
  "type": "Feature",
  "properties": {
    "iso:country":"ES",
    "sg:address":"Calle de Alcazaba, 3",
    "sg:city":"Zafra",
    "sg:orig_category":"Seguridad Social",
    "sg:phone":"+34 924 55 35 51",
    "sg:postcode":"06300",
    "sg:province":"Badajoz",
    "sg:website":"www.fremap.es",
    "wof:name":"Fremap Mutua De Accidentes De Trabajo Y Enferm.profes.de S.s.61",
    "wof:placetype":"venue"
},
  "geometry": {"coordinates":[-6.4139957428,38.4297790527],"type":"Point"}
}