{
  "type": "Feature",
  "properties": {
    "addr:full":"Calle de Enmedio, 23 Calamocha Teruel 44200",
    "addr:housenumber":"23",
    "addr:postcode":"44200",
    "addr:street":"Calle De Enmedio",
    "iso:country":"ES",
    "sg:address":"Calle de Enmedio, 23",
    "sg:city":"Calamocha",
    "sg:orig_category":"Empresas De Pintura Y Revestimientos",
    "sg:phone":"+34 978 73 23 43",
    "sg:postcode":"44200",
    "sg:province":"Teruel",
    "wof:name":"Rando Adame Jose Luis",
    "wof:placetype":"venue"
},
  "geometry": {"coordinates":[-1.2983490229,40.9162940979],"type":"Point"}
}