{
  "type": "Feature",
  "properties": {
    "iso:country":"ES",
    "sg:address":"Calle de Cartagena, 127",
    "sg:city":"Madrid",
    "sg:orig_category":"Caf\u00c9s, Bares, Cervecer\u00cdas",
    "sg:phone":"+34 915 62 30 28",
    "sg:postcode":"28002",
    "sg:province":"Madrid",
    "wof:name":"Sanchez Cobacho S.l.",
    "wof:placetype":"venue"
},
  "geometry": {"coordinates":[-3.675465107,40.4421005249],"type":"Point"}
}