{
  "type": "Feature",
  "properties": {
    "addr:full":"Avda Bierzo (do), 98 Barco Ourense 32300",
    "addr:housenumber":"98",
    "addr:postcode":"32300",
    "addr:street":"Avda Bierzo Do",
    "iso:country":"ES",
    "sg:address":"Avda Bierzo (do), 98",
    "sg:city":"Barco",
    "sg:orig_category":"Promotores Constructores",
    "sg:phone":"+34 988 32 04 27",
    "sg:postcode":"32300",
    "sg:province":"Ourense",
    "wof:name":"Construcciones Quico Barco S.l.",
    "wof:placetype":"venue"
},
  "geometry": {"coordinates":[-6.9807138443,42.4184112549],"type":"Point"}
}