{
  "type": "Feature",
  "properties": {
    "iso:country":"ES",
    "sg:address":"Carrer de Sant Jaume, 26",
    "sg:city":"Castellar Valles",
    "sg:orig_category":"Talleres: Ropa A Medida",
    "sg:phone":"+34 937 14 54 20",
    "sg:postcode":"08211",
    "sg:province":"Barcelona",
    "wof:name":"Romeu Torrella Juan",
    "wof:placetype":"venue"
},
  "geometry": {"coordinates":[2.0824050903,41.6135673523],"type":"Point"}
}