{
  "type": "Feature",
  "properties": {
    "addr:full":"Calle de Doctor Ma\u00d1as Bernabeu, 2 Malaga M\u00e1laga 29006",
    "addr:housenumber":"2",
    "addr:postcode":"29006",
    "addr:street":"Calle De Doctor Man\u0303As Bernabeu;Ma\u0301Laga",
    "iso:country":"ES",
    "sg:address":"Calle de Doctor Ma\u00d1as Bernabeu, 2",
    "sg:city":"Malaga",
    "sg:orig_category":"Molduras, Junquillos, Listones Y Molduras Perforadas",
    "sg:phone":"+34 952 32 29 32",
    "sg:postcode":"29006",
    "sg:province":"M\u00e1laga",
    "wof:name":"Sanchez Robles Jose",
    "wof:placetype":"venue"
},
  "geometry": {"coordinates":[-4.4427924156,36.7108879089],"type":"Point"}
}