{
  "type": "Feature",
  "properties": {
    "iso:country":"ES",
    "sg:address":"Avda Pinos (los), 58",
    "sg:city":"Guardamar Segura",
    "sg:orig_category":"Bares, Piano",
    "sg:phone":"+34 965 72 82 81",
    "sg:postcode":"03140",
    "sg:province":"Alicante",
    "wof:name":"Inza C.b.",
    "wof:placetype":"venue"
},
  "geometry": {"coordinates":[-0.6518819928,38.0870018005],"type":"Point"}
}