{
  "type": "Feature",
  "properties": {
    "iso:country":"ES",
    "sg:address":"Calle de Pinos Alta, 132",
    "sg:city":"Madrid",
    "sg:orig_category":"Abogados",
    "sg:phone":"+34 913 23 12 87",
    "sg:postcode":"28029",
    "sg:province":"Madrid",
    "wof:name":"Numeros Y Datos S.l.",
    "wof:placetype":"venue"
},
  "geometry": {"coordinates":[-3.7020785809,40.4711265564],"type":"Point"}
}