{
  "type": "Feature",
  "properties": {
    "iso:country":"ES",
    "sg:address":"Carrer de Madrazo, 41",
    "sg:city":"Barcelona",
    "sg:orig_category":"Cl\u00cdnicas M\u00c9dicas",
    "sg:phone":"+34 932 17 32 70",
    "sg:postcode":"08006",
    "sg:province":"Barcelona",
    "wof:name":"Medicina De Diagnostico Y Control S.a.",
    "wof:placetype":"venue"
},
  "geometry": {"coordinates":[2.1489610672,41.4000701904],"type":"Point"}
}