{
  "type": "Feature",
  "properties": {
    "addr:full":"Carrer de Trafalgar, 1 Barcelona Barcelona 08010",
    "addr:housenumber":"1",
    "addr:postcode":"08010",
    "addr:street":"Carrer De Trafalgar",
    "iso:country":"ES",
    "sg:address":"Carrer de Trafalgar, 1",
    "sg:city":"Barcelona",
    "sg:orig_category":"Confecci\u00d3n De Trajes Para Se\u00d1oras",
    "sg:phone":"+34 932 68 02 42",
    "sg:postcode":"08010",
    "sg:province":"Barcelona",
    "wof:name":"Petra S.l.",
    "wof:placetype":"venue"
},
  "geometry": {"coordinates":[2.1740078926,41.389087677],"type":"Point"}
}