{
  "type": "Feature",
  "properties": {
    "addr:full":"Avda Ntra Sra Rosario, 18 Navahermosa Toledo 45150",
    "addr:housenumber":"18",
    "addr:postcode":"45150",
    "addr:street":"Avda Ntra Sra Rosario",
    "iso:country":"ES",
    "sg:address":"Avda Ntra Sra Rosario, 18",
    "sg:city":"Navahermosa",
    "sg:classifiers":[
        {
            "category":"Taxi",
            "type":"Transportation"
        }
    ],
    "sg:phone":"+34 925 42 86 32",
    "sg:postcode":"45150",
    "sg:province":"Toledo",
    "wof:name":"Esteban-manzanares Del Cerro Maria Jose",
    "wof:placetype":"venue"
},
  "geometry": {"coordinates":[-4.4679350853,39.6365280151],"type":"Point"}
}