{
  "type": "Feature",
  "properties": {
    "addr:full":"Carrer de Reus, 24 Barcelona Barcelona 08022",
    "addr:housenumber":"24",
    "addr:postcode":"08022",
    "addr:street":"Carrer De Reus",
    "iso:country":"ES",
    "sg:address":"Carrer de Reus, 24",
    "sg:city":"Barcelona",
    "sg:orig_category":"Edici\u00d3n De Diarios, Revistas, Boletines",
    "sg:phone":"+34 934 18 61 78",
    "sg:postcode":"08022",
    "sg:province":"Barcelona",
    "wof:name":"Mateu Puig Montserrat",
    "wof:placetype":"venue"
},
  "geometry": {"coordinates":[2.1342871189,41.404964447],"type":"Point"}
}