{
  "type": "Feature",
  "properties": {
    "addr:full":"Calle de Luis De Peralta, S/n San Cristobal Murcia 30800",
    "addr:housenumber":"s / n",
    "addr:postcode":"30800",
    "addr:street":"Calle De Luis De Peralta",
    "iso:country":"ES",
    "sg:address":"Calle de Luis De Peralta, S/n",
    "sg:city":"San Cristobal",
    "sg:orig_category":"Servicios De Telecomunicaciones",
    "sg:phone":"+34 968 47 19 70",
    "sg:postcode":"30800",
    "sg:province":"Murcia",
    "wof:name":"Rojo Garcia Antonio",
    "wof:placetype":"venue"
},
  "geometry": {"coordinates":[-1.6905640364,37.680557251],"type":"Point"}
}