{
  "type": "Feature",
  "properties": {
    "addr:full":"Pl Comtat Rossello, 2 Palma Islas Baleares 07002",
    "addr:housenumber":"2",
    "addr:postcode":"07002",
    "addr:street":"Pl Comtat Rossello",
    "iso:country":"ES",
    "sg:address":"Pl Comtat Rossello, 2",
    "sg:city":"Palma",
    "sg:orig_category":"Cajas De Ahorro",
    "sg:phone":"+34 971 71 88 50",
    "sg:postcode":"07002",
    "sg:province":"Islas Baleares",
    "wof:name":"Caixa D'estalvis De Catalunya",
    "wof:placetype":"venue"
},
  "geometry": {"coordinates":[2.6545860767,39.5743751526],"type":"Point"}
}