{
  "type": "Feature",
  "properties": {
    "addr:full":"Pg Joan Borbo Comte Barcelo, 46 Barcelona Barcelona 08003",
    "addr:housenumber":"46",
    "addr:postcode":"08003",
    "addr:street":"Pg Joan Borbo Comte Barcelo",
    "iso:country":"ES",
    "sg:address":"Pg Joan Borbo Comte Barcelo, 46",
    "sg:city":"Barcelona",
    "sg:orig_category":"Molduras, Junquillos, Listones Y Molduras Perforadas",
    "sg:phone":"+34 932 25 64 10",
    "sg:postcode":"08003",
    "sg:province":"Barcelona",
    "wof:name":"El Rey De La Gamba S. A.",
    "wof:placetype":"venue"
},
  "geometry": {"coordinates":[2.188421011,41.3776855469],"type":"Point"}
}