{
  "type": "Feature",
  "properties": {
    "iso:country":"ES",
    "sg:address":"Erletokieta, 10",
    "sg:city":"Iru\u00f1a",
    "sg:orig_category":"Estancos",
    "sg:phone":"+34 948 26 83 56",
    "sg:postcode":"31007",
    "sg:province":"Navarra",
    "wof:name":"Valles Martinez Ana Maria",
    "wof:placetype":"venue"
},
  "geometry": {"coordinates":[-1.6466269493,42.8069458008],"type":"Point"}
}