{
  "type": "Feature",
  "properties": {
    "iso:country":"ES",
    "sg:address":"Ca Avanzada, 30",
    "sg:city":"Erandio-goikoa",
    "sg:orig_category":"Construcci\u00d3n, Mantenimiento De Piscinas",
    "sg:phone":"+34 944 17 09 66",
    "sg:postcode":"48950",
    "sg:province":"Vizcaya",
    "wof:name":"Gestion Y Construccion Gesco 14 S.l.",
    "wof:placetype":"venue"
},
  "geometry": {"coordinates":[-2.964548111,43.3126144409],"type":"Point"}
}