{
  "type": "Feature",
  "properties": {
    "addr:full":"Calle de Jacinto Benavente, 11 Marbella M\u00e1laga 29600",
    "addr:housenumber":"11",
    "addr:postcode":"29600",
    "addr:street":"Calle De Jacinto Benavente;Ma\u0301Laga",
    "iso:country":"ES",
    "sg:address":"Calle de Jacinto Benavente, 11",
    "sg:city":"Marbella",
    "sg:orig_category":"Asesor\u00cda Fiscal Y Jur\u00cddica",
    "sg:phone":"+34 952 77 23 32",
    "sg:postcode":"29600",
    "sg:province":"M\u00e1laga",
    "sg:website":"www.atema-asesores.es",
    "wof:name":"Ruiz Escalona Antonio",
    "wof:placetype":"venue"
},
  "geometry": {"coordinates":[-4.8880581856,36.5108451843],"type":"Point"}
}