{
  "type": "Feature",
  "properties": {
    "iso:country":"ES",
    "sg:address":"Carr Vidal I Codina, 7",
    "sg:city":"Lleida",
    "sg:orig_category":"Alimentaci\u00d3n General (al Por Menor)",
    "sg:phone":"+34 973 23 10 37",
    "sg:postcode":"25005",
    "sg:province":"Lleida",
    "wof:name":"Serrado Canal Marcelino",
    "wof:placetype":"venue"
},
  "geometry": {"coordinates":[0.6322450042,41.6277122498],"type":"Point"}
}