{
  "type": "Feature",
  "properties": {
    "iso:country":"ES",
    "sg:address":"Calle de Carlos Martin Alvarez, 104",
    "sg:city":"Madrid",
    "sg:orig_category":"Zapatos (al Por Menor)",
    "sg:phone":"+34 914 77 31 07",
    "sg:postcode":"28018",
    "sg:province":"Madrid",
    "wof:name":"Peque\u00f1o Cubero Francisco",
    "wof:placetype":"venue"
},
  "geometry": {"coordinates":[-3.666711092,40.3855209351],"type":"Point"}
}