{
  "type": "Feature",
  "properties": {
    "addr:full":"Calle de Federico Garcia Lorca, 28 S. Juan Puerto Huelva 21610",
    "addr:housenumber":"28",
    "addr:postcode":"21610",
    "addr:street":"Calle De Federico Garcia Lorca;S. Juan Puerto",
    "iso:country":"ES",
    "sg:address":"Calle de Federico Garcia Lorca, 28",
    "sg:city":"S. Juan Puerto",
    "sg:orig_category":"Promotores Constructores",
    "sg:phone":"+34 959 35 60 92",
    "sg:postcode":"21610",
    "sg:province":"Huelva",
    "wof:name":"Construcciones Jm Alonso Beltran S.l.",
    "wof:placetype":"venue"
},
  "geometry": {"coordinates":[-6.8471927643,37.3163948059],"type":"Point"}
}