{
  "type": "Feature",
  "properties": {
    "addr:full":"Calle de Azahar, 15 Valladolid Valladolid 47012",
    "addr:housenumber":"15",
    "addr:postcode":"47012",
    "addr:street":"Calle De Azahar",
    "iso:country":"ES",
    "sg:address":"Calle de Azahar, 15",
    "sg:city":"Valladolid",
    "sg:orig_category":"Armarios Y Cuadros El\u00c9ctricos",
    "sg:phone":"+34 983 20 86 25",
    "sg:postcode":"47012",
    "sg:province":"Valladolid",
    "wof:name":"Cuadrillero Cabrero Jose Eduardo",
    "wof:placetype":"venue"
},
  "geometry": {"coordinates":[-4.6987752914,41.6419944763],"type":"Point"}
}