{
  "type": "Feature",
  "properties": {
    "iso:country":"ES",
    "sg:address":"Carrer de Doctor Marti I Julia, 61",
    "sg:city":"Hospitalet Llobregat",
    "sg:orig_category":"Confecci\u00d3n De Trajes Para Se\u00d1oras",
    "sg:phone":"+34 934 49 72 62",
    "sg:postcode":"08903",
    "sg:province":"Barcelona",
    "wof:name":"Poveda Ortiz Isabel Del Carmen",
    "wof:placetype":"venue"
},
  "geometry": {"coordinates":[2.1224930286,41.3737640381],"type":"Point"}
}