{
  "type": "Feature",
  "properties": {
    "addr:full":"Mayor, 31 Naquera Valencia 46119",
    "addr:housenumber":"31",
    "addr:postcode":"46119",
    "addr:street":"Mayor",
    "iso:country":"ES",
    "sg:address":"Mayor, 31",
    "sg:city":"Naquera",
    "sg:orig_category":"Barcos",
    "sg:phone":"+34 961 68 00 25",
    "sg:postcode":"46119",
    "sg:province":"Valencia",
    "wof:name":"Hinzpeter  Gerd",
    "wof:placetype":"venue"
},
  "geometry": {"coordinates":[-0.4311749935,39.6599731445],"type":"Point"}
}