{
  "type": "Feature",
  "properties": {
    "addr:full":"Trva Casas Nuevas, 1 Burguillos Toledo Toledo 45112",
    "addr:housenumber":"1",
    "addr:postcode":"45112",
    "addr:street":"Trva Casas Nuevas",
    "iso:country":"ES",
    "sg:address":"Trva Casas Nuevas, 1",
    "sg:city":"Burguillos Toledo",
    "sg:orig_category":"Molduras, Junquillos, Listones Y Molduras Perforadas",
    "sg:phone":"+34 925 39 35 59",
    "sg:postcode":"45112",
    "sg:province":"Toledo",
    "wof:name":"Cytasa Comunicaciones S.l.",
    "wof:placetype":"venue"
},
  "geometry": {"coordinates":[-3.9912641048,39.7966957092],"type":"Point"}
}