{
  "type": "Feature",
  "properties": {
    "iso:country":"ES",
    "sg:address":"Carrer de Santa Maria (de), 93",
    "sg:city":"Vilassar De Mar",
    "sg:orig_category":"Farmacias",
    "sg:phone":"+34 937 59 59 58",
    "sg:postcode":"08340",
    "sg:province":"Barcelona",
    "wof:name":"Altirriba Pertegaz Juan",
    "wof:placetype":"venue"
},
  "geometry": {"coordinates":[2.384665966,41.5016021729],"type":"Point"}
}