{
  "type": "Feature",
  "properties": {
    "iso:country":"ES",
    "sg:address":"Carr Ultonia, 10",
    "sg:city":"Girona",
    "sg:orig_category":"M\u00c9dicos: Neumolog\u00cda",
    "sg:phone":"+34 972 22 27 01",
    "sg:postcode":"17002",
    "sg:province":"Girona",
    "wof:name":"Escuder Llado Joan",
    "wof:placetype":"venue"
},
  "geometry": {"coordinates":[2.8217670918,41.97864151],"type":"Point"}
}