{
  "type": "Feature",
  "properties": {
    "iso:country":"ES",
    "sg:address":"Calle de Sauce, 2",
    "sg:city":"Puebla Alfinden",
    "sg:orig_category":"Agentes, Concesionarios Y Sucursales De Veh\u00cdculos",
    "sg:phone":"+34 976 10 84 24",
    "sg:postcode":"50171",
    "sg:province":"Zaragoza",
    "wof:name":"Ortiz Vehiculos Comerciales S.l.",
    "wof:placetype":"venue"
},
  "geometry": {"coordinates":[-0.7636179924,41.6454696655],"type":"Point"}
}