{
  "type": "Feature",
  "properties": {
    "iso:country":"ES",
    "sg:address":"Carrer de Onze De Setembre, 77",
    "sg:city":"Viladecans",
    "sg:orig_category":"Fabricaci\u00d3n De Juguetes Autom\u00c1ticos",
    "sg:phone":"+34 936 59 36 70",
    "sg:postcode":"08840",
    "sg:province":"Barcelona",
    "wof:name":"Magdaleno Villegas Jose",
    "wof:placetype":"venue"
},
  "geometry": {"coordinates":[2.0112469196,41.3192863464],"type":"Point"}
}