{
  "type": "Feature",
  "properties": {
    "iso:country":"ES",
    "sg:address":"Calle de Agustin Salido, 1",
    "sg:city":"Moral Calatrava",
    "sg:orig_category":"Productores Recolectores, Venta Directa De Vinos",
    "sg:phone":"+34 926 33 00 21",
    "sg:postcode":"13350",
    "sg:province":"Ciudad Real",
    "wof:name":"Sanchez Ordonez Ramon",
    "wof:placetype":"venue"
},
  "geometry": {"coordinates":[-3.5790247917,38.8292961121],"type":"Point"}
}