{
  "type": "Feature",
  "properties": {
    "addr:full":"Calle de Santa Isabel, 11 Segovia Segovia 40001",
    "addr:housenumber":"11",
    "addr:postcode":"40001",
    "addr:street":"Calle De Santa Isabel",
    "iso:country":"ES",
    "sg:address":"Calle de Santa Isabel, 11",
    "sg:city":"Segovia",
    "sg:orig_category":"Institutos De Belleza",
    "sg:phone":"+34 921 42 74 93",
    "sg:postcode":"40001",
    "sg:province":"Segovia",
    "wof:name":"Calvo Tovar Teresa",
    "wof:placetype":"venue"
},
  "geometry": {"coordinates":[-4.113409996,40.9450950623],"type":"Point"}
}