{
  "type": "Feature",
  "properties": {
    "iso:country":"ES",
    "sg:address":"Rond Shimizu, 2",
    "sg:city":"Poligon Industrial Can Torrella",
    "sg:orig_category":"Empresas De Empaquetado, Embalajes Por Encargo",
    "sg:phone":"+34 938 35 93 14",
    "sg:postcode":"08233",
    "sg:province":"Barcelona",
    "sg:website":"egarvac.com",
    "wof:name":"Envasadoras Egarvac S.l.",
    "wof:placetype":"venue"
},
  "geometry": {"coordinates":[1.9185849428,41.6062583923],"type":"Point"}
}