{
  "type": "Feature",
  "properties": {
    "iso:country":"ES",
    "sg:address":"Calle de Santa Teresa De Jesus, 45",
    "sg:city":"Zaragoza",
    "sg:orig_category":"M\u00c9dicos: Radioterapia (radioterapia Como Opci\u00d3n Oncol\u00d3gica)",
    "sg:phone":"+34 976 35 51 11",
    "sg:postcode":"50006",
    "sg:province":"Zaragoza",
    "wof:name":"Centro De Diagnostico Radiologico S. A.",
    "wof:placetype":"venue"
},
  "geometry": {"coordinates":[-0.8944659829,41.6389465332],"type":"Point"}
}