{
  "type": "Feature",
  "properties": {
    "addr:full":"Calle de Ba\u00d1os, 6 Albacete Albacete 02004",
    "addr:housenumber":"6",
    "addr:postcode":"02004",
    "addr:street":"Calle De Ban\u0303Os",
    "iso:country":"ES",
    "sg:address":"Calle de Ba\u00d1os, 6",
    "sg:city":"Albacete",
    "sg:orig_category":"Electricidad, Electr\u00d3nica: Suministros (al Por Menor)",
    "sg:phone":"+34 967 24 89 32",
    "sg:postcode":"02004",
    "sg:province":"Albacete",
    "wof:name":"Ferreteria Herlo S.l.",
    "wof:placetype":"venue"
},
  "geometry": {"coordinates":[-1.8601464033,38.9955253601],"type":"Point"}
}