{
  "type": "Feature",
  "properties": {
    "iso:country":"ES",
    "sg:address":"Calle de San Manuel, 1",
    "sg:city":"Madrid",
    "sg:orig_category":"Frutas, Legumbres Frescas Y Tempranas (al Por Menor)",
    "sg:phone":"+34 917 11 40 24",
    "sg:postcode":"28011",
    "sg:province":"Madrid",
    "wof:name":"Mayoral Hernandez Jose Luis",
    "wof:placetype":"venue"
},
  "geometry": {"coordinates":[-3.7601981163,40.4016799927],"type":"Point"}
}