{
  "type": "Feature",
  "properties": {
    "addr:full":"Calle de Medio (del), 5 Navaleno Soria 42149",
    "addr:housenumber":"5",
    "addr:postcode":"42149",
    "addr:street":"Calle De Medio Del",
    "iso:country":"ES",
    "sg:address":"Calle de Medio (del), 5",
    "sg:city":"Navaleno",
    "sg:orig_category":"Iglesia Cat\u00d3lica",
    "sg:phone":"+34 975 37 40 33",
    "sg:postcode":"42149",
    "sg:province":"Soria",
    "wof:name":"Parroquia De San Esteban Protomartir",
    "wof:placetype":"venue"
},
  "geometry": {"coordinates":[-3.0044350624,41.8378944397],"type":"Point"}
}