{
  "type": "Feature",
  "properties": {
    "iso:country":"ES",
    "sg:address":"Carr Artrutx, 11",
    "sg:city":"Poima",
    "sg:orig_category":"Metales (labores, Pulido)",
    "sg:phone":"+34 971 36 23 12",
    "sg:postcode":"07714",
    "sg:province":"Islas Baleares",
    "wof:name":"Estampadora Mahonesa S.l.",
    "wof:placetype":"venue"
},
  "geometry": {"coordinates":[2.9117100239,39.6136398315],"type":"Point"}
}