{
  "type": "Feature",
  "properties": {
    "addr:full":"Calle de Fe, S/n Cogeces Monte Valladolid 47313",
    "addr:housenumber":"s / n",
    "addr:postcode":"47313",
    "addr:street":"Calle De Fe",
    "iso:country":"ES",
    "sg:address":"Calle de Fe, S/n",
    "sg:city":"Cogeces Monte",
    "sg:orig_category":"Supermercados Y Hipermercados",
    "sg:phone":"+34 983 69 92 43",
    "sg:postcode":"47313",
    "sg:province":"Valladolid",
    "wof:name":"Martin Cuellar Francisco",
    "wof:placetype":"venue"
},
  "geometry": {"coordinates":[-4.3158841133,41.5109634399],"type":"Point"}
}