{
  "type": "Feature",
  "properties": {
    "iso:country":"ES",
    "sg:address":"Calle de Lagartera, 9",
    "sg:city":"Villaluenga Sagra",
    "sg:orig_category":"Estudios, Instalaci\u00d3n De Climatizaci\u00d3n",
    "sg:phone":"+34 925 53 04 21",
    "sg:postcode":"45520",
    "sg:province":"Toledo",
    "wof:name":"Gomez Garcia Conrado",
    "wof:placetype":"venue"
},
  "geometry": {"coordinates":[-3.9086260796,40.0281448364],"type":"Point"}
}