{
  "type": "Feature",
  "properties": {
    "iso:country":"ES",
    "sg:address":"Avda Doctor Artero Guirao, S/n",
    "sg:city":"S. Pedro Pinatar",
    "sg:orig_category":"Autob\u00das (explotaci\u00d3n Y Servicios De)",
    "sg:phone":"+34 968 18 00 19",
    "sg:postcode":"30740",
    "sg:province":"Murcia",
    "wof:name":"Autocares La Inmaculada S.l.",
    "wof:placetype":"venue"
},
  "geometry": {"coordinates":[-0.7965312004,37.8320655823],"type":"Point"}
}