{
  "type": "Feature",
  "properties": {
    "addr:full":"Carrer de Muntaner, 456 Barcelona Barcelona 08006",
    "addr:housenumber":"456",
    "addr:postcode":"08006",
    "addr:street":"Carrer De Muntaner",
    "iso:country":"ES",
    "sg:address":"Carrer de Muntaner, 456",
    "sg:city":"Barcelona",
    "sg:orig_category":"Estancos",
    "sg:phone":"+34 932 02 26 60",
    "sg:postcode":"08006",
    "sg:province":"Barcelona",
    "wof:name":"Bores Abadal Maria Antonia",
    "wof:placetype":"venue"
},
  "geometry": {"coordinates":[2.1394529343,41.4018669128],"type":"Point"}
}