{
  "type": "Feature",
  "properties": {
    "addr:full":"Traginers, 43 Alaquas Valencia 46970",
    "addr:housenumber":"43",
    "addr:postcode":"46970",
    "addr:street":"Traginers",
    "iso:country":"ES",
    "sg:address":"Traginers, 43",
    "sg:city":"Alaquas",
    "sg:orig_category":"Encuadernaci\u00d3n E Impresi\u00d3n De Folletos",
    "sg:phone":"+34 961 50 03 66",
    "sg:postcode":"46970",
    "sg:province":"Valencia",
    "wof:name":"Manipulados Fonval S.l.",
    "wof:placetype":"venue"
},
  "geometry": {"coordinates":[-0.4770039916,39.4492111206],"type":"Point"}
}