{
  "type": "Feature",
  "properties": {
    "addr:full":"Calle de Vista Bella, 4 San Lorenzo De El Escorial Madrid 28200",
    "addr:housenumber":"4",
    "addr:postcode":"28200",
    "addr:street":"Calle De Vista Bella",
    "iso:country":"ES",
    "sg:address":"Calle de Vista Bella, 4",
    "sg:city":"San Lorenzo De El Escorial",
    "sg:orig_category":"Clases De M\u00dasica Y Canto",
    "sg:phone":"+34 918 90 49 16",
    "sg:postcode":"28200",
    "sg:province":"Madrid",
    "wof:name":"Ayuntamiento De San Lorenzo De El Escorial",
    "wof:placetype":"venue"
},
  "geometry": {"coordinates":[-4.1348772049,40.5981178284],"type":"Point"}
}