{
  "type": "Feature",
  "properties": {
    "addr:full":"Aios, 95 Aios Pontevedra 36990",
    "addr:housenumber":"95",
    "addr:postcode":"36990",
    "addr:street":"Aios",
    "iso:country":"ES",
    "sg:address":"Aios, 95",
    "sg:city":"Aios",
    "sg:orig_category":"Cerrajer\u00cda, Ferrallista",
    "sg:phone":"+34 986 69 11 48",
    "sg:postcode":"36990",
    "sg:province":"Pontevedra",
    "wof:name":"Dobalo Vidal Marcos",
    "wof:placetype":"venue"
},
  "geometry": {"coordinates":[-8.8508090973,42.4159317017],"type":"Point"}
}