{
  "type": "Feature",
  "properties": {
    "iso:country":"ES",
    "sg:address":"Calle de Eloy Gonzalo, 21",
    "sg:city":"Madrid",
    "sg:orig_category":"M\u00c9dicos: Medicina General",
    "sg:phone":"+34 914 46 73 59",
    "sg:postcode":"28010",
    "sg:province":"Madrid",
    "wof:name":"Mestesa Asesoria Sanitaria S.l.",
    "wof:placetype":"venue"
},
  "geometry": {"coordinates":[-3.7011120319,40.4344863892],"type":"Point"}
}