{
  "type": "Feature",
  "properties": {
    "iso:country":"ES",
    "sg:address":"Calle de Roberto Cano, 2",
    "sg:city":"Melilla",
    "sg:orig_category":"Ense\u00d1anza, Formaci\u00d3n Profesional: Aprendizaje",
    "sg:phone":"+34 952 68 22 49",
    "sg:postcode":"52001",
    "sg:province":"Melilla",
    "wof:name":"Ciudad Autonoma De Melilla",
    "wof:placetype":"venue"
},
  "geometry": {"coordinates":[-2.9400010109,35.2942008972],"type":"Point"}
}