{
  "type": "Feature",
  "properties": {
    "iso:country":"ES",
    "sg:address":"Carr Albereda, 16",
    "sg:city":"Girona",
    "sg:orig_category":"Inform\u00c1tica, Ofim\u00c1tica (estudios, Asesor\u00cda, Ingenier\u00cda, Formaci\u00d3n)",
    "sg:phone":"+34 972 22 46 17",
    "sg:postcode":"17004",
    "sg:province":"Girona",
    "wof:name":"Rovira Batlle Jordi",
    "wof:placetype":"venue"
},
  "geometry": {"coordinates":[2.8237900734,41.9819755554],"type":"Point"}
}