{
  "type": "Feature",
  "properties": {
    "addr:full":"C/ Tamarinde, 6 Son Veri Nou Islas Baleares 07600",
    "addr:housenumber":"6",
    "addr:postcode":"07600",
    "addr:street":"C / Tamarinde;Islas",
    "iso:country":"ES",
    "sg:address":"C/ Tamarinde, 6",
    "sg:city":"Son Veri Nou",
    "sg:orig_category":"Alimentaci\u00d3n General (al Por Menor)",
    "sg:phone":"+34 971 44 20 93",
    "sg:postcode":"07600",
    "sg:province":"Islas Baleares",
    "wof:name":"Muntaner Serra Juan",
    "wof:placetype":"venue"
},
  "geometry": {"coordinates":[2.752327919,39.5086097717],"type":"Point"}
}