{
  "type": "Feature",
  "properties": {
    "iso:country":"ES",
    "sg:address":"Avda Juan Gris (de), 2",
    "sg:city":"Mejorada Campo",
    "sg:orig_category":"Fabricaci\u00d3n, Importaci\u00d3n De L\u00c1mparas Y Bombillas",
    "sg:phone":"+34 916 68 06 70",
    "sg:postcode":"28840",
    "sg:province":"Madrid",
    "wof:name":"Ziarat Servicios Sl",
    "wof:placetype":"venue"
},
  "geometry": {"coordinates":[-3.4838635921,40.3951454163],"type":"Point"}
}