{
  "type": "Feature",
  "properties": {
    "iso:country":"ES",
    "sg:address":"Calle de Principe De Vergara, 36",
    "sg:city":"Madrid",
    "sg:orig_category":"Embajadas, Consulados Y Otras Representaciones Diplom\u00c1ticas",
    "sg:phone":"+34 914 31 42 42",
    "sg:postcode":"28001",
    "sg:province":"Madrid",
    "wof:name":"Embajada Del Peru",
    "wof:placetype":"venue"
},
  "geometry": {"coordinates":[-3.6798670292,40.4267234802],"type":"Point"}
}