{
  "type": "Feature",
  "properties": {
    "iso:country":"ES",
    "sg:address":"Calle de Tolosa Latour, 2",
    "sg:city":"Cartagena",
    "sg:orig_category":"Centros De Educaci\u00d3n Especial",
    "sg:phone":"+34 968 12 18 14",
    "sg:postcode":"30201",
    "sg:province":"Murcia",
    "wof:name":"Colegio San Isidoro Y Santa Florentina",
    "wof:placetype":"venue"
},
  "geometry": {"coordinates":[-0.9914870262,37.6047515869],"type":"Point"}
}