{
  "type": "Feature",
  "properties": {
    "iso:country":"ES",
    "sg:address":"Carrer de Girfalc, 5",
    "sg:city":"Son Ferrer",
    "sg:orig_category":"Mec\u00c1nico Del Autom\u00d3vil",
    "sg:phone":"+34 971 23 02 06",
    "sg:postcode":"07182",
    "sg:province":"Islas Baleares",
    "wof:name":"Talleres M Riera S.l.",
    "wof:placetype":"venue"
},
  "geometry": {"coordinates":[2.5054340363,39.4959449768],"type":"Point"}
}