{
  "type": "Feature",
  "properties": {
    "addr:full":"Calle de Rafael De Frutos, 2 Pozuelo De Alarcon Madrid 28224",
    "addr:housenumber":"2",
    "addr:postcode":"28224",
    "addr:street":"Calle De Rafael De Frutos",
    "iso:country":"ES",
    "sg:address":"Calle de Rafael De Frutos, 2",
    "sg:city":"Pozuelo De Alarcon",
    "sg:orig_category":"Agentes, Concesionarios Y Sucursales De Veh\u00cdculos",
    "sg:phone":"+34 913 51 52 94",
    "sg:postcode":"28224",
    "sg:province":"Madrid",
    "wof:name":"Armesto S.l.",
    "wof:placetype":"venue"
},
  "geometry": {"coordinates":[-3.8004646301,40.4482383728],"type":"Point"}
}