{
  "type": "Feature",
  "properties": {
    "iso:country":"ES",
    "sg:address":"Carrer de Ramon Moncada, 25",
    "sg:city":"Santa Pon\u00c7a",
    "sg:orig_category":"Discotecas Y Salas De Baile",
    "sg:phone":"+34 971 69 33 16",
    "sg:postcode":"07180",
    "sg:province":"Islas Baleares",
    "wof:name":"Inversiones Bauza S.l.",
    "wof:placetype":"venue"
},
  "geometry": {"coordinates":[2.4766147137,39.5075454712],"type":"Point"}
}