{
  "type": "Feature",
  "properties": {
    "addr:full":"Avda Nueve De Octubre, 41 Puerto Valencia 46520",
    "addr:housenumber":"41",
    "addr:postcode":"46520",
    "addr:street":"Avda Nueve De Octubre",
    "iso:country":"ES",
    "sg:address":"Avda Nueve De Octubre, 41",
    "sg:city":"Puerto",
    "sg:orig_category":"Reposter\u00cdas",
    "sg:phone":"+34 962 67 15 45",
    "sg:postcode":"46520",
    "sg:province":"Valencia",
    "wof:name":"Garrido Montesinos Rafael",
    "wof:placetype":"venue"
},
  "geometry": {"coordinates":[-0.2269220054,39.661857605],"type":"Point"}
}