{
  "type": "Feature",
  "properties": {
    "iso:country":"ES",
    "sg:address":"Calle de Santa Teresa De Jesus, 34",
    "sg:city":"Talavera Reina",
    "sg:orig_category":"Centros Empresariales",
    "sg:phone":"+34 925 80 35 13",
    "sg:postcode":"45600",
    "sg:province":"Toledo",
    "wof:name":"Eco Servicios Prado S.l",
    "wof:placetype":"venue"
},
  "geometry": {"coordinates":[-4.8282089233,39.9642105103],"type":"Point"}
}