{
  "type": "Feature",
  "properties": {
    "addr:full":"Pg L'exposicio, 66 Barcelona Barcelona 08004",
    "addr:housenumber":"66",
    "addr:postcode":"08004",
    "addr:street":"Pg L'Exposicio",
    "iso:country":"ES",
    "sg:address":"Pg L'exposicio, 66",
    "sg:city":"Barcelona",
    "sg:orig_category":"Agencias Y Agentes Comerciales, Representantes",
    "sg:phone":"+34 933 29 56 52",
    "sg:postcode":"08004",
    "sg:province":"Barcelona",
    "wof:name":"Lucas Llop Nemesio",
    "wof:placetype":"venue"
},
  "geometry": {"coordinates":[2.1593134403,41.3711013794],"type":"Point"}
}