{
  "type": "Feature",
  "properties": {
    "iso:country":"ES",
    "sg:address":"Calle de Nueva, 22",
    "sg:city":"Motril",
    "sg:orig_category":"M\u00c9dicos: An\u00c1lisis Cl\u00cdnicos",
    "sg:phone":"+34 958 60 60 30",
    "sg:postcode":"18600",
    "sg:province":"Granada",
    "wof:name":"Fito Torres Maria Josefa",
    "wof:placetype":"venue"
},
  "geometry": {"coordinates":[-3.5183489323,36.7474784851],"type":"Point"}
}