{
  "type": "Feature",
  "properties": {
    "addr:full":"Llorens Trias, S/n Arenys Munt Barcelona 08358",
    "addr:housenumber":"s / n",
    "addr:postcode":"08358",
    "addr:street":"Munt Barcelona",
    "iso:country":"ES",
    "sg:address":"Llorens Trias, S/n",
    "sg:city":"Arenys Munt",
    "sg:orig_category":"Suministros Para Hoteles",
    "sg:phone":"+34 937 95 13 26",
    "sg:postcode":"08358",
    "sg:province":"Barcelona",
    "wof:name":"Matas Pulido Juan",
    "wof:placetype":"venue"
},
  "geometry": {"coordinates":[2.5462930202,41.5972747803],"type":"Point"}
}