{
  "type": "Feature",
  "properties": {
    "iso:country":"ES",
    "sg:address":"Carr President Macia, 62",
    "sg:city":"Palamos",
    "sg:orig_category":"Farmacias",
    "sg:phone":"+34 972 31 48 41",
    "sg:postcode":"17230",
    "sg:province":"Girona",
    "wof:name":"Clares Vigo Victoria",
    "wof:placetype":"venue"
},
  "geometry": {"coordinates":[3.1241919994,41.8494606018],"type":"Point"}
}