{
  "type": "Feature",
  "properties": {
    "addr:full":"Calle de Nicolas Guillen, 6 Zaragoza Zaragoza 50015",
    "addr:housenumber":"6",
    "addr:postcode":"50015",
    "addr:street":"Calle De Nicolas Guillen",
    "iso:country":"ES",
    "sg:address":"Calle de Nicolas Guillen, 6",
    "sg:city":"Zaragoza",
    "sg:orig_category":"Impuestos, Tesoro P\u00dablico",
    "sg:phone":"+34 976 51 60 07",
    "sg:postcode":"50015",
    "sg:province":"Zaragoza",
    "wof:name":"Jimenez Y Karag S.c.",
    "wof:placetype":"venue"
},
  "geometry": {"coordinates":[-0.884509027,41.6668243408],"type":"Point"}
}