{
  "type": "Feature",
  "properties": {
    "addr:full":"Praz Rafael Dieste, 1 Rianxo La Coru\u00f1a 15920",
    "addr:housenumber":"1",
    "addr:postcode":"15920",
    "addr:street":"Rafael Dieste;La Corun\u0303A",
    "iso:country":"ES",
    "sg:address":"Praz Rafael Dieste, 1",
    "sg:city":"Rianxo",
    "sg:orig_category":"Bibliotecas, Mediatecas",
    "sg:phone":"+34 981 86 02 72",
    "sg:postcode":"15920",
    "sg:province":"La Coru\u00f1a",
    "wof:name":"Concello De Rianxo",
    "wof:placetype":"venue"
},
  "geometry": {"coordinates":[-8.8191785812,42.6503791809],"type":"Point"}
}