{
  "type": "Feature",
  "properties": {
    "iso:country":"ES",
    "sg:address":"Calle de Naval La, 162",
    "sg:city":"Palmas De Gran Canaria",
    "sg:orig_category":"Bisuter\u00cda, Joyer\u00cda, Relojer\u00cda (al Por Menor)",
    "sg:phone":"+34 928 46 10 74",
    "sg:postcode":"35008",
    "sg:province":"Las Palmas",
    "wof:name":"Rodriguez Hernandez Eliseo",
    "wof:placetype":"venue"
},
  "geometry": {"coordinates":[-15.4196434021,28.1505336761],"type":"Point"}
}