{
  "type": "Feature",
  "properties": {
    "addr:full":"Av Llibertat, 1 Mollet Valles Barcelona 08100",
    "addr:housenumber":"1",
    "addr:postcode":"08100",
    "addr:street":"Av Llibertat",
    "iso:country":"ES",
    "sg:address":"Av Llibertat, 1",
    "sg:city":"Mollet Valles",
    "sg:orig_category":"Pod\u00d3logos: Pedicuros",
    "sg:phone":"+34 935 70 16 29",
    "sg:postcode":"08100",
    "sg:province":"Barcelona",
    "wof:name":"Bertran Fernandez Nuria",
    "wof:placetype":"venue"
},
  "geometry": {"coordinates":[2.212954998,41.5374832153],"type":"Point"}
}