{
  "type": "Feature",
  "properties": {
    "addr:full":"Pelota, 6 Aldaia Valencia 46960",
    "addr:housenumber":"6",
    "addr:postcode":"46960",
    "addr:street":"Pelota",
    "iso:country":"ES",
    "sg:address":"Pelota, 6",
    "sg:city":"Aldaia",
    "sg:orig_category":"M\u00c1rmoles, Granitos Y Piedras Naturales",
    "sg:phone":"+34 961 51 90 21",
    "sg:postcode":"46960",
    "sg:province":"Valencia",
    "wof:name":"Marmoles Barranquet S.l.",
    "wof:placetype":"venue"
},
  "geometry": {"coordinates":[-0.4730339944,39.4667015076],"type":"Point"}
}