{
  "type": "Feature",
  "properties": {
    "addr:full":"C/ Antonio Machado, 70 Elche Alicante 03201",
    "addr:housenumber":"70",
    "addr:postcode":"03201",
    "addr:street":"C / Antonio Machado",
    "iso:country":"ES",
    "sg:address":"C/ Antonio Machado, 70",
    "sg:city":"Elche",
    "sg:orig_category":"Cajas De Ahorro",
    "sg:phone":"+34 965 43 20 52",
    "sg:postcode":"03201",
    "sg:province":"Alicante",
    "wof:name":"Caja De Ahorros Del Mediterraneo",
    "wof:placetype":"venue"
},
  "geometry": {"coordinates":[-0.7112450004,38.2617607117],"type":"Point"}
}