{
  "type": "Feature",
  "properties": {
    "iso:country":"ES",
    "sg:address":"Calle de Granada, 26",
    "sg:city":"Alameda",
    "sg:orig_category":"\u00d3ptica: Instrumentos (fabricaci\u00d3n)",
    "sg:phone":"+34 952 71 03 09",
    "sg:postcode":"29530",
    "sg:province":"M\u00e1laga",
    "wof:name":"Aguilar Morillo Rafael",
    "wof:placetype":"venue"
},
  "geometry": {"coordinates":[-4.6570210457,37.2074623108],"type":"Point"}
}