{
  "type": "Feature",
  "properties": {
    "iso:country":"ES",
    "sg:address":"Calle de Rodriguez Arias, 23",
    "sg:city":"Bilbao",
    "sg:orig_category":"Agencias Y Agentes Comerciales, Representantes",
    "sg:phone":"+34 944 22 36 30",
    "sg:postcode":"48013",
    "sg:province":"Vizcaya",
    "wof:name":"Davimar S.l.",
    "wof:placetype":"venue"
},
  "geometry": {"coordinates":[-2.9415988922,43.2632904053],"type":"Point"}
}