{
  "type": "Feature",
  "properties": {
    "addr:full":"Calle de Santiago Rusi\u00d1ol, 32 Valencia Valencia 46019",
    "addr:housenumber":"32",
    "addr:postcode":"46019",
    "addr:street":"Calle De Santiago Rusin\u0303Ol",
    "iso:country":"ES",
    "sg:address":"Calle de Santiago Rusi\u00d1ol, 32",
    "sg:city":"Valencia",
    "sg:orig_category":"Reposter\u00cdas",
    "sg:phone":"+34 963 66 74 29",
    "sg:postcode":"46019",
    "sg:province":"Valencia",
    "wof:name":"Alberich Terencio Rosa",
    "wof:placetype":"venue"
},
  "geometry": {"coordinates":[-0.3625429869,39.4923477173],"type":"Point"}
}