{
  "type": "Feature",
  "properties": {
    "addr:full":"Carrer de Nou, 5 Almoster Tarragona 43393",
    "addr:housenumber":"5",
    "addr:postcode":"43393",
    "addr:street":"Carrer De Nou",
    "iso:country":"ES",
    "sg:address":"Carrer de Nou, 5",
    "sg:city":"Almoster",
    "sg:orig_category":"Delegados, Agentes De Tr\u00c1nsito, Auxiliares De Transporte Internacional",
    "sg:phone":"+34 977 85 52 08",
    "sg:postcode":"43393",
    "sg:province":"Tarragona",
    "wof:name":"Salvado Martin Emilio",
    "wof:placetype":"venue"
},
  "geometry": {"coordinates":[1.1126669645,41.197467804],"type":"Point"}
}