{
  "type": "Feature",
  "properties": {
    "iso:country":"ES",
    "sg:address":"Carrer de Cervantes, 35",
    "sg:city":"Reus",
    "sg:orig_category":"Fabricaci\u00d3n De Moldes Y Modelos",
    "sg:phone":"+34 977 31 16 61",
    "sg:postcode":"43201",
    "sg:province":"Tarragona",
    "wof:name":"Precision Mecanica Reus S.a.",
    "wof:placetype":"venue"
},
  "geometry": {"coordinates":[1.1047899723,41.1642913818],"type":"Point"}
}