{
  "type": "Feature",
  "properties": {
    "iso:country":"ES",
    "sg:address":"Rua Alfonso X O Sabio, 3",
    "sg:city":"Vigo",
    "sg:orig_category":"Centros P\u00dablicos De Formaci\u00d3n Profesional Y T\u00c9cnica",
    "sg:phone":"+34 986 20 09 18",
    "sg:postcode":"36211",
    "sg:province":"Pontevedra",
    "wof:name":"Colegio Oficial De Graduados Sociales",
    "wof:placetype":"venue"
},
  "geometry": {"coordinates":[-8.73021698,42.2215270996],"type":"Point"}
}