{
  "type": "Feature",
  "properties": {
    "addr:full":"Calle de I\u00d1aki Deuna, 38 Ondarroa Vizcaya 48700",
    "addr:housenumber":"38",
    "addr:postcode":"48700",
    "addr:street":"Calle De In\u0303Aki Deuna",
    "iso:country":"ES",
    "sg:address":"Calle de I\u00d1aki Deuna, 38",
    "sg:city":"Ondarroa",
    "sg:orig_category":"Mec\u00c1nico Del Autom\u00d3vil",
    "sg:phone":"+34 946 83 04 89",
    "sg:postcode":"48700",
    "sg:province":"Vizcaya",
    "wof:name":"Zaldibia Garate I\u00f1aki",
    "wof:placetype":"venue"
},
  "geometry": {"coordinates":[-2.4276709557,43.3200874329],"type":"Point"}
}