{
  "type": "Feature",
  "properties": {
    "addr:full":"Calle de San Blas, 60 Zaragoza Zaragoza 50003",
    "addr:housenumber":"60",
    "addr:postcode":"50003",
    "addr:street":"Calle De San Blas",
    "iso:country":"ES",
    "sg:address":"Calle de San Blas, 60",
    "sg:city":"Zaragoza",
    "sg:orig_category":"Asociaciones, Organismos Culturales Y Socioeducativos",
    "sg:phone":"+34 976 28 52 48",
    "sg:postcode":"50003",
    "sg:province":"Zaragoza",
    "wof:name":"Federacion Aragonesa De Solidaridad",
    "wof:placetype":"venue"
},
  "geometry": {"coordinates":[-0.886236012,41.6564979553],"type":"Point"}
}