{
  "type": "Feature",
  "properties": {
    "addr:full":"Hta. Peralta, 3 Arroyo Miel M\u00e1laga 29631",
    "addr:housenumber":"3",
    "addr:postcode":"29631",
    "addr:street":"Peralta;Ma\u0301Laga",
    "iso:country":"ES",
    "sg:address":"Hta. Peralta, 3",
    "sg:city":"Arroyo Miel",
    "sg:orig_category":"Serigraf\u00cda (material Y Suministros)",
    "sg:phone":"+34 952 56 60 47",
    "sg:postcode":"29631",
    "sg:province":"M\u00e1laga",
    "wof:name":"Gonzalez Guerrero Ana",
    "wof:placetype":"venue"
},
  "geometry": {"coordinates":[-4.5482521057,36.6017608643],"type":"Point"}
}