{
  "type": "Feature",
  "properties": {
    "addr:full":"Av Loygorri, 1 Oliva Valencia 46780",
    "addr:housenumber":"1",
    "addr:postcode":"46780",
    "addr:street":"Av Loygorri",
    "iso:country":"ES",
    "sg:address":"Av Loygorri, 1",
    "sg:city":"Oliva",
    "sg:orig_category":"Abogados",
    "sg:phone":"+34 962 85 16 73",
    "sg:postcode":"46780",
    "sg:province":"Valencia",
    "wof:name":"Just Rodriguez Josep Vicente",
    "wof:placetype":"venue"
},
  "geometry": {"coordinates":[-0.117504999,38.9192657471],"type":"Point"}
}