{
  "type": "Feature",
  "properties": {
    "addr:full":"Calle de Creu (la), 47 Banyeres Mariola Alicante 03450",
    "addr:housenumber":"47",
    "addr:postcode":"03450",
    "addr:street":"Calle De Creu La",
    "iso:country":"ES",
    "sg:address":"Calle de Creu (la), 47",
    "sg:city":"Banyeres Mariola",
    "sg:orig_category":"Ense\u00d1anza: Profesiones Art\u00cdsticas",
    "sg:phone":"+34 965 56 64 95",
    "sg:postcode":"03450",
    "sg:province":"Alicante",
    "wof:name":"Foto-video Morenet C.b.",
    "wof:placetype":"venue"
},
  "geometry": {"coordinates":[-0.656175375,38.7181777954],"type":"Point"}
}