{
  "type": "Feature",
  "properties": {
    "iso:country":"ES",
    "sg:address":"Valle Oro, 3",
    "sg:city":"Madrid",
    "sg:orig_category":"Tiendas De Grano, Frutas Y Legumbres Secas (al Por Menor)",
    "sg:phone":"+34 914 71 90 85",
    "sg:postcode":"28019",
    "sg:province":"Madrid",
    "wof:name":"Valleoporto S.l.",
    "wof:placetype":"venue"
},
  "geometry": {"coordinates":[-3.7297289371,40.3882598877],"type":"Point"}
}