{
  "type": "Feature",
  "properties": {
    "iso:country":"ES",
    "sg:address":"Calle de Velazquez, 26",
    "sg:city":"Madrid",
    "sg:orig_category":"Agentes Generales De Seguros",
    "sg:phone":"+34 915 77 17 45",
    "sg:postcode":"28001",
    "sg:province":"Madrid",
    "wof:name":"Martinez Rodriguez Javier",
    "wof:placetype":"venue"
},
  "geometry": {"coordinates":[-3.6840209961,40.4243927002],"type":"Point"}
}