{
  "type": "Feature",
  "properties": {
    "addr:full":"Carr Concordia, 3 Sineu Islas Baleares 07510",
    "addr:housenumber":"3",
    "addr:postcode":"07510",
    "addr:street":"Carr Concordia",
    "iso:country":"ES",
    "sg:address":"Carr Concordia, 3",
    "sg:city":"Sineu",
    "sg:orig_category":"Empresas De Pintura Y Revestimientos",
    "sg:phone":"+34 971 85 51 79",
    "sg:postcode":"07510",
    "sg:province":"Islas Baleares",
    "wof:name":"Pinturas Ramis Cifre S.r.l.",
    "wof:placetype":"venue"
},
  "geometry": {"coordinates":[3.0117640495,39.6465873718],"type":"Point"}
}