{
  "type": "Feature",
  "properties": {
    "iso:country":"ES",
    "sg:address":"Calle de Gil De Fuentes, 2",
    "sg:city":"Palencia",
    "sg:orig_category":"Tintorer\u00cdas, Limpieza En Seco",
    "sg:phone":"+34 979 74 11 50",
    "sg:postcode":"34001",
    "sg:province":"Palencia",
    "wof:name":"Rascon Capillas Jose Maria",
    "wof:placetype":"venue"
},
  "geometry": {"coordinates":[-4.5339570045,42.0097618103],"type":"Point"}
}