{
  "type": "Feature",
  "properties": {
    "addr:full":"Calle de Ciscar, 65 Valencia Valencia 46005",
    "addr:housenumber":"65",
    "addr:postcode":"46005",
    "addr:street":"Calle De Ciscar",
    "iso:country":"ES",
    "sg:address":"Calle de Ciscar, 65",
    "sg:city":"Valencia",
    "sg:orig_category":"Florister\u00cdas",
    "sg:phone":"+34 963 34 00 58",
    "sg:postcode":"46005",
    "sg:province":"Valencia",
    "wof:name":"Ceres Floristas S.l.",
    "wof:placetype":"venue"
},
  "geometry": {"coordinates":[-0.363481313,39.4629249573],"type":"Point"}
}