{
  "type": "Feature",
  "properties": {
    "addr:full":"Ctra. B-granada, Km. 0003,0 Badajoz Badajoz 06009",
    "addr:postcode":"06009",
    "addr:street":"Ctra. B-Granada Km. 0003,0",
    "iso:country":"ES",
    "sg:address":"Ctra. B-granada, Km. 0003,0",
    "sg:city":"Badajoz",
    "sg:orig_category":"Material Y Herramientas Agr\u00cdcolas",
    "sg:phone":"+34 924 25 00 91",
    "sg:postcode":"06009",
    "sg:province":"Badajoz",
    "wof:name":"Nieto Marcelo S.l.",
    "wof:placetype":"venue"
},
  "geometry": {"coordinates":[-6.8764038086,38.8433265686],"type":"Point"}
}