{
  "type": "Feature",
  "properties": {
    "addr:full":"Ctra Cabo De Palos, 1 Palma Murcia 30593",
    "addr:housenumber":"1",
    "addr:postcode":"30593",
    "addr:street":"Ctra Cabo De Palos",
    "iso:country":"ES",
    "sg:address":"Ctra Cabo De Palos, 1",
    "sg:city":"Palma",
    "sg:orig_category":"Fabricaci\u00d3n, Importaci\u00d3n De Material Y Sistemas De Telecomunicaciones",
    "sg:phone":"+34 968 16 50 00",
    "sg:postcode":"30593",
    "sg:province":"Murcia",
    "sg:website":"www.electronicamartinez.com",
    "wof:name":"Electronica Martinez De Cartagena S.l.",
    "wof:placetype":"venue"
},
  "geometry": {"coordinates":[-0.9635639787,37.689781189],"type":"Point"}
}