{
  "type": "Feature",
  "properties": {
    "iso:country":"ES",
    "sg:address":"Carrer de Riera De Clara, 5",
    "sg:city":"Clara",
    "sg:orig_category":"Cerrajer\u00cda, Ferrallista",
    "sg:phone":"+34 937 97 17 73",
    "sg:postcode":"08310",
    "sg:province":"Barcelona",
    "wof:name":"Llallaroli S.l.",
    "wof:placetype":"venue"
},
  "geometry": {"coordinates":[2.4036650658,41.5564155579],"type":"Point"}
}