{
  "type": "Feature",
  "properties": {
    "addr:full":"Carr Valencia, 32 Camprodon Girona 17867",
    "addr:housenumber":"32",
    "addr:postcode":"17867",
    "addr:street":"Carr Valencia",
    "iso:country":"ES",
    "sg:address":"Carr Valencia, 32",
    "sg:city":"Camprodon",
    "sg:orig_category":"Cajas De Ahorro",
    "sg:phone":"+34 972 74 03 31",
    "sg:postcode":"17867",
    "sg:province":"Girona",
    "wof:name":"Caixa De Girona",
    "wof:placetype":"venue"
},
  "geometry": {"coordinates":[2.3666450977,42.3134918213],"type":"Point"}
}