{
  "type": "Feature",
  "properties": {
    "iso:country":"ES",
    "sg:address":"Cllj Franciscas, S/n",
    "sg:city":"Salamanca",
    "sg:orig_category":"Alimentaci\u00d3n General (al Por Menor)",
    "sg:phone":"+34 923 21 70 14",
    "sg:postcode":"37001",
    "sg:province":"Salamanca",
    "wof:name":"Acera Acera Jose",
    "wof:placetype":"venue"
},
  "geometry": {"coordinates":[-5.6602406502,40.9678916931],"type":"Point"}
}