{
  "type": "Feature",
  "properties": {
    "iso:country":"ES",
    "sg:address":"Av Garrovers, 31",
    "sg:city":"Pont D'inca",
    "sg:orig_category":"Parafarmacias",
    "sg:phone":"+34 971 79 61 13",
    "sg:postcode":"07141",
    "sg:province":"Islas Baleares",
    "wof:name":"Cer S.l.",
    "wof:placetype":"venue"
},
  "geometry": {"coordinates":[2.9090559483,39.7211036682],"type":"Point"}
}