{
  "type": "Feature",
  "properties": {
    "addr:full":"Tollo, S/n Tollo Pontevedra 36750",
    "addr:postcode":"36750",
    "addr:street":"Tollo S / N",
    "iso:country":"ES",
    "sg:address":"Tollo, S/n",
    "sg:city":"Tollo",
    "sg:orig_category":"Plomeros",
    "sg:phone":"+34 986 62 03 37",
    "sg:postcode":"36750",
    "sg:province":"Pontevedra",
    "wof:name":"Pi\u00f1eiro Gonzalez Jose",
    "wof:placetype":"venue"
},
  "geometry": {"coordinates":[-8.7706012726,41.9454116821],"type":"Point"}
}