{
  "type": "Feature",
  "properties": {
    "addr:full":"Calle de Abesua, 11 Markina-xemein Vizcaya 48270",
    "addr:housenumber":"11",
    "addr:postcode":"48270",
    "addr:street":"Calle De Abesua",
    "iso:country":"ES",
    "sg:address":"Calle de Abesua, 11",
    "sg:city":"Markina-xemein",
    "sg:orig_category":"Zapatos (al Por Menor)",
    "sg:phone":"+34 946 16 63 42",
    "sg:postcode":"48270",
    "sg:province":"Vizcaya",
    "wof:name":"Arechabaleta Aguinaga Natividad",
    "wof:placetype":"venue"
},
  "geometry": {"coordinates":[-2.4966597557,43.2656478882],"type":"Point"}
}