{
  "type": "Feature",
  "properties": {
    "iso:country":"ES",
    "sg:address":"Plaz Moguer De, 5",
    "sg:city":"Huelva",
    "sg:orig_category":"Agencias Y Agentes Comerciales, Representantes",
    "sg:phone":"+34 959 15 56 76",
    "sg:postcode":"21007",
    "sg:province":"Huelva",
    "sg:website":"www.esp.ag.dupont.com",
    "wof:name":"Dupont Asturias S.l.",
    "wof:placetype":"venue"
},
  "geometry": {"coordinates":[-6.9495940208,37.256313324],"type":"Point"}
}