{
  "type": "Feature",
  "properties": {
    "addr:full":"Pg Maragall, 207 Barcelona Barcelona 08041",
    "addr:housenumber":"207",
    "addr:postcode":"08041",
    "addr:street":"Pg Maragall",
    "iso:country":"ES",
    "sg:address":"Pg Maragall, 207",
    "sg:city":"Barcelona",
    "sg:orig_category":"Cl\u00cdnicas M\u00c9dicas",
    "sg:phone":"+34 933 49 25 96",
    "sg:postcode":"08041",
    "sg:province":"Barcelona",
    "sg:website":"www.topcondom.com",
    "wof:name":"Gautex Medica S.l.",
    "wof:placetype":"venue"
},
  "geometry": {"coordinates":[2.176774025,41.424571991],"type":"Point"}
}