{
  "type": "Feature",
  "properties": {
    "addr:full":"Pase Cuellar, 9 Zaragoza Zaragoza 50007",
    "addr:housenumber":"9",
    "addr:postcode":"50007",
    "addr:street":"Cuellar",
    "iso:country":"ES",
    "sg:address":"Pase Cuellar, 9",
    "sg:city":"Zaragoza",
    "sg:orig_category":"Telas Y Sedas (al Por Menor)",
    "sg:phone":"+34 976 27 97 32",
    "sg:postcode":"50007",
    "sg:province":"Zaragoza",
    "wof:name":"Textiles Torcal S.l.",
    "wof:placetype":"venue"
},
  "geometry": {"coordinates":[-0.8849660158,41.6386184692],"type":"Point"}
}