{
  "type": "Feature",
  "properties": {
    "addr:full":"Calle de Alberto Aguilera, 9 Madrid Madrid 28015",
    "addr:housenumber":"9",
    "addr:postcode":"madrid;28015",
    "addr:street":"Calle De Alberto Aguilera",
    "iso:country":"ES",
    "sg:address":"Calle de Alberto Aguilera, 9",
    "sg:city":"Madrid",
    "sg:orig_category":"Distribuci\u00d3n De Petr\u00d3leo Y Derivados",
    "sg:phone":"+34 914 47 39 16",
    "sg:postcode":"28015",
    "sg:province":"Madrid",
    "wof:name":"Repsol Ypf S.a.",
    "wof:placetype":"venue"
},
  "geometry": {"coordinates":[-3.7085921764,40.4298057556],"type":"Point"}
}