{
  "type": "Feature",
  "properties": {
    "iso:country":"ES",
    "sg:address":"Avda Garcia Si\u00d1eriz, 70",
    "sg:city":"Miajadas",
    "sg:orig_category":"Molduras, Junquillos, Listones Y Molduras Perforadas",
    "sg:phone":"+34 927 34 76 71",
    "sg:postcode":"10100",
    "sg:province":"C\u00e1ceres",
    "wof:name":"Masa Sanchez Pedro Maria",
    "wof:placetype":"venue"
},
  "geometry": {"coordinates":[-5.9140958786,39.1525115967],"type":"Point"}
}