{
  "type": "Feature",
  "properties": {
    "iso:country":"ES",
    "sg:address":"Av Emerencia Roig I Raventos, 6",
    "sg:city":"Sitges",
    "sg:orig_category":"Agencias Y Agentes Comerciales, Representantes",
    "sg:phone":"+34 938 94 57 33",
    "sg:postcode":"08870",
    "sg:province":"Barcelona",
    "wof:name":"Borbolla Ruiz Maria Del Carmen",
    "wof:placetype":"venue"
},
  "geometry": {"coordinates":[1.8196510077,41.237121582],"type":"Point"}
}