{
  "type": "Feature",
  "properties": {
    "addr:full":"Calle de Brezo (del), 18 Arganda Madrid 28500",
    "addr:housenumber":"18",
    "addr:postcode":"28500",
    "addr:street":"Calle De Brezo Del",
    "iso:country":"ES",
    "sg:address":"Calle de Brezo (del), 18",
    "sg:city":"Arganda",
    "sg:orig_category":"Torneros Sobre Madera",
    "sg:phone":"+34 918 71 00 83",
    "sg:postcode":"28500",
    "sg:province":"Madrid",
    "wof:name":"Garcia Bermejo Vicente",
    "wof:placetype":"venue"
},
  "geometry": {"coordinates":[-3.4666662216,40.3160018921],"type":"Point"}
}