{
  "type": "Feature",
  "properties": {
    "iso:country":"ES",
    "sg:address":"Carrer de Anselm Clave, 34",
    "sg:city":"Molins Rei",
    "sg:orig_category":"Alquiler De Gr\u00daas",
    "sg:phone":"+34 936 68 58 06",
    "sg:postcode":"08750",
    "sg:province":"Barcelona",
    "wof:name":"Gruas Corbera S.l.",
    "wof:placetype":"venue"
},
  "geometry": {"coordinates":[2.0150859356,41.4161338806],"type":"Point"}
}