{
  "type": "Feature",
  "properties": {
    "addr:full":"Ctra Madridejos, 32 Villaca\u00f1as Toledo 45860",
    "addr:housenumber":"32",
    "addr:postcode":"45860",
    "addr:street":"Ctra Madridejos",
    "iso:country":"ES",
    "sg:address":"Ctra Madridejos, 32",
    "sg:city":"Villaca\u00f1as",
    "sg:orig_category":"Droguer\u00cdas (al Por Menor)",
    "sg:phone":"+34 925 16 05 69",
    "sg:postcode":"45860",
    "sg:province":"Toledo",
    "wof:name":"Lopez Osuna Juan Antonio",
    "wof:placetype":"venue"
},
  "geometry": {"coordinates":[-3.3348448277,39.6200714111],"type":"Point"}
}