{
  "type": "Feature",
  "properties": {
    "iso:country":"ES",
    "sg:address":"Avda Alicante, 25",
    "sg:city":"Denia",
    "sg:orig_category":"Servicios De Telecomunicaciones",
    "sg:phone":"+34 966 43 54 13",
    "sg:postcode":"03700",
    "sg:province":"Alicante",
    "wof:name":"Teleconcept S.l.",
    "wof:placetype":"venue"
},
  "geometry": {"coordinates":[0.0999569967,38.8387832642],"type":"Point"}
}