{
  "type": "Feature",
  "properties": {
    "iso:country":"ES",
    "sg:address":"Urb. Las Joyas, 20",
    "sg:city":"Estepona",
    "sg:orig_category":"Transportes A\u00c9reos",
    "sg:phone":"+34 952 79 11 89",
    "sg:postcode":"29680",
    "sg:province":"M\u00e1laga",
    "sg:website":"www.aerotopvision.com",
    "wof:name":"Artmural Costa S.l.",
    "wof:placetype":"venue"
},
  "geometry": {"coordinates":[-5.1744904518,36.4435119629],"type":"Point"}
}