{
  "type": "Feature",
  "properties": {
    "addr:full":"Carrer de Gran De Sant Andreu, 435 Barcelona Barcelona 08030",
    "addr:housenumber":"435",
    "addr:postcode":"08030",
    "addr:street":"Carrer De Gran De Sant Andreu",
    "iso:country":"ES",
    "sg:address":"Carrer de Gran De Sant Andreu, 435",
    "sg:city":"Barcelona",
    "sg:orig_category":"Farmacias",
    "sg:phone":"+34 933 45 22 07",
    "sg:postcode":"08030",
    "sg:province":"Barcelona",
    "wof:name":"Ros Berger Concepcion",
    "wof:placetype":"venue"
},
  "geometry": {"coordinates":[2.1883471012,41.4406356812],"type":"Point"}
}