{
  "type": "Feature",
  "properties": {
    "addr:full":"Calle de Mayor, 16 Barrachina Teruel 44220",
    "addr:housenumber":"16",
    "addr:postcode":"44220",
    "addr:street":"Calle De Mayor",
    "iso:country":"ES",
    "sg:address":"Calle de Mayor, 16",
    "sg:city":"Barrachina",
    "sg:orig_category":"Cajas De Ahorro",
    "sg:phone":"+34 978 73 29 15",
    "sg:postcode":"44220",
    "sg:province":"Teruel",
    "wof:name":"Caja De Ahorros Y Monte De Piedad De Zaragoza Aragon Y Rioja",
    "wof:placetype":"venue"
},
  "geometry": {"coordinates":[-1.139359951,40.8971557617],"type":"Point"}
}