{
  "type": "Feature",
  "properties": {
    "addr:full":"Calle de Caballeros, 31 Valencia Valencia 46001",
    "addr:housenumber":"31",
    "addr:postcode":"46001",
    "addr:street":"Calle De Caballeros",
    "iso:country":"ES",
    "sg:address":"Calle de Caballeros, 31",
    "sg:city":"Valencia",
    "sg:orig_category":"Cajas De Ahorro",
    "sg:phone":"+34 963 15 62 45",
    "sg:postcode":"46001",
    "sg:province":"Valencia",
    "wof:name":"Caja De Ahorros De Valencia Castellon Y Alicante",
    "wof:placetype":"venue"
},
  "geometry": {"coordinates":[-0.3781433105,39.4766235352],"type":"Point"}
}