{
  "type": "Feature",
  "properties": {
    "addr:full":"Calle de Quintana, 15 Campanario Badajoz 06460",
    "addr:housenumber":"15",
    "addr:postcode":"06460",
    "addr:street":"Calle De Quintana",
    "iso:country":"ES",
    "sg:address":"Calle de Quintana, 15",
    "sg:city":"Campanario",
    "sg:orig_category":"Sales (al Por Mayor)",
    "sg:phone":"+34 924 85 17 86",
    "sg:postcode":"06460",
    "sg:province":"Badajoz",
    "wof:name":"Comercial Royca Comunidad Bienes",
    "wof:placetype":"venue"
},
  "geometry": {"coordinates":[-5.6177210808,38.8618736267],"type":"Point"}
}