{
  "type": "Feature",
  "properties": {
    "iso:country":"ES",
    "sg:address":"Plaz Baja, 6",
    "sg:city":"Monachil",
    "sg:orig_category":"Caf\u00c9s, Bares, Cervecer\u00cdas",
    "sg:phone":"+34 958 50 27 62",
    "sg:postcode":"18193",
    "sg:province":"Granada",
    "wof:name":"Ramirez Arias Jose",
    "wof:placetype":"venue"
},
  "geometry": {"coordinates":[-3.5402770042,37.1322402954],"type":"Point"}
}