{
  "type": "Feature",
  "properties": {
    "addr:full":"Calle de San Erasmo, 42 Madrid Madrid 28021",
    "addr:housenumber":"42",
    "addr:postcode":"madrid;28021",
    "addr:street":"Calle De San Erasmo",
    "iso:country":"ES",
    "sg:address":"Calle de San Erasmo, 42",
    "sg:city":"Madrid",
    "sg:orig_category":"Fabricaci\u00d3n De Banderas Y De Banderines",
    "sg:phone":"+34 917 23 02 42",
    "sg:postcode":"28021",
    "sg:province":"Madrid",
    "wof:name":"Graficas Roces Sl",
    "wof:placetype":"venue"
},
  "geometry": {"coordinates":[-3.7065799236,40.3333969116],"type":"Point"}
}