{
  "type": "Feature",
  "properties": {
    "iso:country":"ES",
    "sg:address":"Calle de Juan De Soto, 4",
    "sg:city":"Alcala Henares",
    "sg:orig_category":"Contenedores (mercanc\u00cdas)",
    "sg:phone":"+34 918 80 69 36",
    "sg:postcode":"28804",
    "sg:province":"Madrid",
    "wof:name":"Amo Arriola Angel Del",
    "wof:placetype":"venue"
},
  "geometry": {"coordinates":[-3.354203701,40.4846992493],"type":"Point"}
}