{
  "type": "Feature",
  "properties": {
    "iso:country":"ES",
    "sg:address":"Carr Major, 75",
    "sg:city":"Seu D'urgell",
    "sg:orig_category":"Carnicer\u00cdas, Carnicer\u00cdas",
    "sg:phone":"+34 973 35 06 91",
    "sg:postcode":"25700",
    "sg:province":"Lleida",
    "wof:name":"Navines Font Pedro",
    "wof:placetype":"venue"
},
  "geometry": {"coordinates":[0.6244090199,41.613407135],"type":"Point"}
}