{
  "type": "Feature",
  "properties": {
    "addr:full":"Calle de Rio Duero, 12 Mostoles Madrid 28935",
    "addr:housenumber":"12",
    "addr:postcode":"28935",
    "addr:street":"Calle De Rio Duero",
    "iso:country":"ES",
    "sg:address":"Calle de Rio Duero, 12",
    "sg:city":"Mostoles",
    "sg:orig_category":"Iglesia Cat\u00d3lica",
    "sg:phone":"+34 916 45 98 84",
    "sg:postcode":"28935",
    "sg:province":"Madrid",
    "wof:name":"Obispado De Getafe",
    "wof:placetype":"venue"
},
  "geometry": {"coordinates":[-3.8759739399,40.3153114319],"type":"Point"}
}