{
  "type": "Feature",
  "properties": {
    "iso:country":"ES",
    "sg:address":"Calle de Ferrocarril, 23",
    "sg:city":"Madrid",
    "sg:orig_category":"Servicios De Telecomunicaciones",
    "sg:phone":"+34 915 28 20 13",
    "sg:postcode":"28045",
    "sg:province":"Madrid",
    "wof:name":"Outworld Comunication Sl",
    "wof:placetype":"venue"
},
  "geometry": {"coordinates":[-3.6968369484,40.4007797241],"type":"Point"}
}