{
  "type": "Feature",
  "properties": {
    "addr:full":"Calle de Virgen De Los Reyes, 7 Madrid Madrid 28027",
    "addr:housenumber":"7",
    "addr:postcode":"madrid;28027",
    "addr:street":"Calle De Virgen De Los Reyes",
    "iso:country":"ES",
    "sg:address":"Calle de Virgen De Los Reyes, 7",
    "sg:city":"Madrid",
    "sg:orig_category":"Ense\u00d1anza: Profesiones Art\u00cdsticas",
    "sg:phone":"+34 914 04 49 41",
    "sg:postcode":"28027",
    "sg:province":"Madrid",
    "wof:name":"Zavala Guerra Carlos Alberto",
    "wof:placetype":"venue"
},
  "geometry": {"coordinates":[-3.6526172161,40.4379730225],"type":"Point"}
}