{
  "type": "Feature",
  "properties": {
    "addr:full":"Ctra Catro Cami\u00d1os, S/n Maceda Ourense 32700",
    "addr:housenumber":"s / n",
    "addr:postcode":"32700",
    "addr:street":"Ctra Catro Camin\u0303Os",
    "iso:country":"ES",
    "sg:address":"Ctra Catro Cami\u00d1os, S/n",
    "sg:city":"Maceda",
    "sg:orig_category":"Poller\u00cda Y Caza (al Por Menor)",
    "sg:phone":"+34 988 46 32 15",
    "sg:postcode":"32700",
    "sg:province":"Ourense",
    "wof:name":"Fontela Quintas Jose",
    "wof:placetype":"venue"
},
  "geometry": {"coordinates":[-7.6509618759,42.2707633972],"type":"Point"}
}