{
  "type": "Feature",
  "properties": {
    "iso:country":"ES",
    "sg:address":"Avda Arcadio Pardi\u00d1as, 193",
    "sg:city":"Burela",
    "sg:orig_category":"Contenedores (mercanc\u00cdas)",
    "sg:phone":"+34 982 58 04 52",
    "sg:postcode":"27880",
    "sg:province":"Lugo",
    "wof:name":"Dean Rouco Cesareo",
    "wof:placetype":"venue"
},
  "geometry": {"coordinates":[-7.354060173,43.6509895325],"type":"Point"}
}