{
  "type": "Feature",
  "properties": {
    "iso:country":"ES",
    "sg:address":"Carrer de Sant Antoni Maria Claret, 424",
    "sg:city":"Barcelona",
    "sg:orig_category":"Centros Empresariales",
    "sg:phone":"+34 933 51 02 84",
    "sg:postcode":"08027",
    "sg:province":"Barcelona",
    "wof:name":"Aginse S.l.",
    "wof:placetype":"venue"
},
  "geometry": {"coordinates":[2.0835642815,41.3691749573],"type":"Point"}
}