{
  "type": "Feature",
  "properties": {
    "iso:country":"ES",
    "sg:address":"Calle de Fray Ceferino, 12",
    "sg:city":"Oviedo",
    "sg:orig_category":"Restaurantes",
    "sg:phone":"+34 985 22 00 25",
    "sg:postcode":"33001",
    "sg:province":"Asturias",
    "wof:name":"Lorenzo Garcia Vicente",
    "wof:placetype":"venue"
},
  "geometry": {"coordinates":[-5.8520979881,43.3655700684],"type":"Point"}
}