{
  "type": "Feature",
  "properties": {
    "addr:full":"Zahara, 3 Barbate Franco C\u00e1diz 11160",
    "addr:postcode":"11160",
    "iso:country":"ES",
    "sg:address":"Zahara, 3",
    "sg:city":"Barbate Franco",
    "sg:orig_category":"Producci\u00d3n, Venta De Productos De Agricultura Biol\u00d3gica",
    "sg:phone":"+34 956 43 13 84",
    "sg:postcode":"11160",
    "sg:province":"C\u00e1diz",
    "wof:name":"Praena Montero Antonio",
    "wof:placetype":"venue"
},
  "geometry": {"coordinates":[-5.9163188934,36.1932830811],"type":"Point"}
}