{
  "type": "Feature",
  "properties": {
    "iso:country":"ES",
    "sg:address":"Calle de Alberto Palacios, 8",
    "sg:city":"Madrid",
    "sg:orig_category":"Papeler\u00cdas: Art\u00cdculos (al Por Mayor)",
    "sg:phone":"+34 917 98 10 02",
    "sg:postcode":"28021",
    "sg:province":"Madrid",
    "wof:name":"Fernandez Lozano Eusebio",
    "wof:placetype":"venue"
},
  "geometry": {"coordinates":[-3.7126190662,40.3440895081],"type":"Point"}
}