{
  "type": "Feature",
  "properties": {
    "addr:full":"Calle de Jorge Juan, 77 Madrid Madrid 28009",
    "addr:housenumber":"77",
    "addr:postcode":"madrid;28009",
    "addr:street":"Calle De Jorge Juan",
    "iso:country":"ES",
    "sg:address":"Calle de Jorge Juan, 77",
    "sg:city":"Madrid",
    "sg:orig_category":"Papeler\u00cdas, Librer\u00cdas",
    "sg:phone":"+34 914 31 98 98",
    "sg:postcode":"28009",
    "sg:province":"Madrid",
    "wof:name":"Sanz More Angel Jorge",
    "wof:placetype":"venue"
},
  "geometry": {"coordinates":[-3.6760780811,40.4235191345],"type":"Point"}
}