{
  "type": "Feature",
  "properties": {
    "iso:country":"ES",
    "sg:address":"Calle de Via (la), 32",
    "sg:city":"Zaragoza",
    "sg:orig_category":"Colchones (fabricaci\u00d3n, Al Por Mayor, Al Por Menor)",
    "sg:phone":"+34 976 35 33 20",
    "sg:postcode":"50009",
    "sg:province":"Zaragoza",
    "wof:name":"Rubio Carreras Enrique",
    "wof:placetype":"venue"
},
  "geometry": {"coordinates":[-0.9079470038,41.6317596436],"type":"Point"}
}