{
  "type": "Feature",
  "properties": {
    "iso:country":"ES",
    "sg:address":"Calle de Leopoldo Romeo, 31",
    "sg:city":"Zaragoza",
    "sg:orig_category":"Venta, Instalaci\u00d3n De Calefacci\u00d3n",
    "sg:phone":"+34 976 42 59 48",
    "sg:postcode":"50002",
    "sg:province":"Zaragoza",
    "wof:name":"Talleres Forcen S. L.",
    "wof:placetype":"venue"
},
  "geometry": {"coordinates":[-0.865842998,41.64686203],"type":"Point"}
}