{
  "type": "Feature",
  "properties": {
    "iso:country":"ES",
    "sg:address":"Avda Pueyo, S/n",
    "sg:city":"Monzon",
    "sg:orig_category":"Poller\u00cda Y Caza (al Por Menor)",
    "sg:phone":"+34 974 41 68 96",
    "sg:postcode":"22400",
    "sg:province":"Huesca",
    "wof:name":"Canal Espa\u00f1ol Maria Lourdes",
    "wof:placetype":"venue"
},
  "geometry": {"coordinates":[0.1864700019,41.9066047668],"type":"Point"}
}