{
  "type": "Feature",
  "properties": {
    "addr:full":"Calle de Valencia, 1 Xirivella Valencia 46950",
    "addr:housenumber":"1",
    "addr:postcode":"46950",
    "addr:street":"Calle De Valencia",
    "iso:country":"ES",
    "sg:address":"Calle de Valencia, 1",
    "sg:city":"Xirivella",
    "sg:orig_category":"Bisuter\u00cda, Joyer\u00cda, Relojer\u00cda (al Por Menor)",
    "sg:phone":"+34 963 70 88 35",
    "sg:postcode":"46950",
    "sg:province":"Valencia",
    "wof:name":"Almarche Navarro Rosario",
    "wof:placetype":"venue"
},
  "geometry": {"coordinates":[-0.4246765077,39.4643859863],"type":"Point"}
}