{
  "type": "Feature",
  "properties": {
    "addr:full":"Calle de Perez Galdos, 29 Arcos Frontera C\u00e1diz 11630",
    "addr:housenumber":"29",
    "addr:postcode":"11630",
    "addr:street":"Calle De Perez Galdos",
    "iso:country":"ES",
    "sg:address":"Calle de Perez Galdos, 29",
    "sg:city":"Arcos Frontera",
    "sg:orig_category":"Reposter\u00cdas",
    "sg:phone":"+34 956 70 05 57",
    "sg:postcode":"11630",
    "sg:province":"C\u00e1diz",
    "wof:name":"Carrera Tellez S.l.",
    "wof:placetype":"venue"
},
  "geometry": {"coordinates":[-5.8115739822,36.7515716553],"type":"Point"}
}