{
  "type": "Feature",
  "properties": {
    "addr:full":"Las Huesas, S/n Telde Las Palmas 35200",
    "addr:housenumber":"s",
    "addr:postcode":"35200",
    "addr:street":"/ N",
    "iso:country":"ES",
    "sg:address":"Las Huesas, S/n",
    "sg:city":"Telde",
    "sg:orig_category":"Comercio De Piezas De Recambio Y De Accesorios De Veh\u00cdculos, Veh\u00cdculos Industriales",
    "sg:phone":"+34 928 69 89 59",
    "sg:postcode":"35200",
    "sg:province":"Las Palmas",
    "wof:name":"Juan Armas S. A.",
    "wof:placetype":"venue"
},
  "geometry": {"coordinates":[-15.3937635422,27.9836597443],"type":"Point"}
}