{
  "type": "Feature",
  "properties": {
    "iso:country":"ES",
    "sg:address":"Rbla Joaquim Vayreda, 40",
    "sg:city":"Gava",
    "sg:orig_category":"Comercio, Reparaci\u00d3n De Bicicletas, De Motocicletas, De Accesorios",
    "sg:phone":"+34 936 62 59 52",
    "sg:postcode":"08850",
    "sg:province":"Barcelona",
    "wof:name":"Subira Tintore Salvador",
    "wof:placetype":"venue"
},
  "geometry": {"coordinates":[2.0087509155,41.3048362732],"type":"Point"}
}