{
  "type": "Feature",
  "properties": {
    "iso:country":"ES",
    "sg:address":"Calle de Carrera De Las Monjas, 5",
    "sg:city":"Priego Cordoba",
    "sg:orig_category":"Panader\u00cdas, Panader\u00cdas",
    "sg:phone":"+34 957 54 07 93",
    "sg:postcode":"14800",
    "sg:province":"C\u00f3rdoba",
    "wof:name":"Duran Alcala Mari Carmen",
    "wof:placetype":"venue"
},
  "geometry": {"coordinates":[-4.1948838234,37.4385223389],"type":"Point"}
}