{
  "type": "Feature",
  "properties": {
    "addr:full":"Calle de Escolta Real, 10 Donostia-san Sebastian Guip\u00f9zcoa 20008",
    "addr:housenumber":"10",
    "addr:postcode":"20008",
    "addr:street":"Calle De Escolta Real",
    "iso:country":"ES",
    "sg:address":"Calle de Escolta Real, 10",
    "sg:city":"Donostia-san Sebastian",
    "sg:orig_category":"Peluquer\u00cdas, Peluquer\u00cda Mixta",
    "sg:phone":"+34 943 21 99 13",
    "sg:postcode":"20008",
    "sg:province":"Guip\u00f9zcoa",
    "sg:website":"www.udospeluqueros.com",
    "wof:name":"Udos Peluqueria Y Belleza S.l.",
    "wof:placetype":"venue"
},
  "geometry": {"coordinates":[-2.001529932,43.3132019043],"type":"Point"}
}