{
  "type": "Feature",
  "properties": {
    "iso:country":"ES",
    "sg:address":"Plaz Granada, 1",
    "sg:city":"Avila",
    "sg:orig_category":"Comunidades Religiosas",
    "sg:phone":"+34 920 22 04 00",
    "sg:postcode":"05003",
    "sg:province":"\u00c1vila",
    "wof:name":"Padres Dominicos Del Santisimo Rosario",
    "wof:placetype":"venue"
},
  "geometry": {"coordinates":[-4.6891450882,40.6508483887],"type":"Point"}
}