{
  "type": "Feature",
  "properties": {
    "addr:full":"Carr Balears, 24 Eivissa Islas Baleares 07800",
    "addr:housenumber":"24",
    "addr:postcode":"07800",
    "addr:street":"Carr Balears",
    "iso:country":"ES",
    "sg:address":"Carr Balears, 24",
    "sg:city":"Eivissa",
    "sg:orig_category":"M\u00c9dicos: Cirug\u00cda Pl\u00c1stica, Reconstructiva Y Est\u00c9tica",
    "sg:phone":"+34 971 19 27 30",
    "sg:postcode":"07800",
    "sg:province":"Islas Baleares",
    "wof:name":"Puig Julia Jose Maria",
    "wof:placetype":"venue"
},
  "geometry": {"coordinates":[1.4245380163,38.9097976685],"type":"Point"}
}