{
  "type": "Feature",
  "properties": {
    "addr:full":"Calle de Simancas, 15 Cordoba C\u00f3rdoba 14001",
    "addr:housenumber":"15",
    "addr:postcode":"14001",
    "addr:street":"Calle De Simancas;Co\u0301Rdoba",
    "iso:country":"ES",
    "sg:address":"Calle de Simancas, 15",
    "sg:city":"Cordoba",
    "sg:orig_category":"Bisuter\u00cda, Joyer\u00cda, Relojer\u00cda (al Por Menor)",
    "sg:phone":"+34 957 48 25 03",
    "sg:postcode":"14001",
    "sg:province":"C\u00f3rdoba",
    "wof:name":"Sanz Ramirez Francisco",
    "wof:placetype":"venue"
},
  "geometry": {"coordinates":[-4.7703680992,37.890712738],"type":"Point"}
}