{
  "type": "Feature",
  "properties": {
    "iso:country":"ES",
    "sg:address":"Avda Ausias March, 42",
    "sg:city":"Alaquas",
    "sg:orig_category":"Librer\u00cdas",
    "sg:phone":"+34 961 51 00 76",
    "sg:postcode":"46970",
    "sg:province":"Valencia",
    "wof:name":"Serrano Gomez Maria Soraya",
    "wof:placetype":"venue"
},
  "geometry": {"coordinates":[-0.4580059946,39.4546852112],"type":"Point"}
}