{
  "type": "Feature",
  "properties": {
    "addr:full":"Avda Aeroporto, 513 Vigo Pontevedra 36318",
    "addr:housenumber":"513",
    "addr:postcode":"36318",
    "addr:street":"Avda Aeroporto",
    "iso:country":"ES",
    "sg:address":"Avda Aeroporto, 513",
    "sg:city":"Vigo",
    "sg:orig_category":"Quincaller\u00cda (al Por Menor)",
    "sg:phone":"+34 986 48 72 40",
    "sg:postcode":"36318",
    "sg:province":"Pontevedra",
    "wof:name":"Rinxela S.l.",
    "wof:placetype":"venue"
},
  "geometry": {"coordinates":[-8.6474990845,42.23387146],"type":"Point"}
}