{
  "type": "Feature",
  "properties": {
    "iso:country":"ES",
    "sg:address":"Ctra Sadaba, S/n",
    "sg:city":"Ejea De Los Caballeros",
    "sg:orig_category":"Muebles, Minoristas",
    "sg:phone":"+34 976 66 21 61",
    "sg:postcode":"50600",
    "sg:province":"Zaragoza",
    "wof:name":"Dimusaga S.l.",
    "wof:placetype":"venue"
},
  "geometry": {"coordinates":[-1.1521539688,42.1332817078],"type":"Point"}
}