{
  "type": "Feature",
  "properties": {
    "iso:country":"ES",
    "sg:address":"Avda Portugal, 73",
    "sg:city":"Ba\u00d1eza",
    "sg:orig_category":"Mec\u00c1nico Del Autom\u00d3vil",
    "sg:phone":"+34 987 64 11 54",
    "sg:postcode":"24750",
    "sg:province":"Le\u00f3n",
    "wof:name":"Automoviles Ba?ezanos S. A.",
    "wof:placetype":"venue"
},
  "geometry": {"coordinates":[-5.9105162621,42.2928009033],"type":"Point"}
}