{
  "type": "Feature",
  "properties": {
    "addr:full":"Avda Alpujarras (de Las), 63 Canjayar Almer\u00eda 04450",
    "addr:housenumber":"63",
    "addr:postcode":"04450",
    "addr:street":"Avda Alpujarras De Las;Almeri\u0301A",
    "iso:country":"ES",
    "sg:address":"Avda Alpujarras (de Las), 63",
    "sg:city":"Canjayar",
    "sg:orig_category":"Transportes Por V\u00cdas Navegables",
    "sg:phone":"+34 950 51 02 76",
    "sg:postcode":"04450",
    "sg:province":"Almer\u00eda",
    "wof:name":"Ortiz Pastor Antonio",
    "wof:placetype":"venue"
},
  "geometry": {"coordinates":[-2.7406830788,37.0073013306],"type":"Point"}
}