{
  "type": "Feature",
  "properties": {
    "addr:full":"Calle de Ministro Luis Mayans, 55 Valencia Valencia 46009",
    "addr:housenumber":"55",
    "addr:postcode":"46009",
    "addr:street":"Calle De Ministro Luis Mayans",
    "iso:country":"ES",
    "sg:address":"Calle de Ministro Luis Mayans, 55",
    "sg:city":"Valencia",
    "sg:orig_category":"Electricidad, Electr\u00d3nica: Material Y Suministros (al Por Mayor)",
    "sg:phone":"+34 963 65 09 61",
    "sg:postcode":"46009",
    "sg:province":"Valencia",
    "wof:name":"Ocean Winds S.l.",
    "wof:placetype":"venue"
},
  "geometry": {"coordinates":[-0.3704240024,39.489238739],"type":"Point"}
}