{
  "type": "Feature",
  "properties": {
    "addr:full":"Ctra Estacion, 40 Zamora Zamora 49010",
    "addr:housenumber":"40",
    "addr:postcode":"49010",
    "addr:street":"Ctra Estacion",
    "iso:country":"ES",
    "sg:address":"Ctra Estacion, 40",
    "sg:city":"Zamora",
    "sg:orig_category":"Chapister\u00cda",
    "sg:phone":"+34 980 51 63 81",
    "sg:postcode":"49010",
    "sg:province":"Zamora",
    "wof:name":"Lopez Merchan Manuel",
    "wof:placetype":"venue"
},
  "geometry": {"coordinates":[-5.742413044,41.5143928528],"type":"Point"}
}