{
  "type": "Feature",
  "properties": {
    "addr:full":"Plaz Conquistadores, 2 Badajoz Badajoz 06005",
    "addr:housenumber":"2",
    "addr:postcode":"06005",
    "addr:street":"Plaz Conquistadores",
    "iso:country":"ES",
    "sg:address":"Plaz Conquistadores, 2",
    "sg:city":"Badajoz",
    "sg:orig_category":"Agentes De Seguros",
    "sg:phone":"+34 924 23 49 50",
    "sg:postcode":"06005",
    "sg:province":"Badajoz",
    "wof:name":"Desarrollo Extreme\u00f1o Correduria De Seguros S.l.",
    "wof:placetype":"venue"
},
  "geometry": {"coordinates":[-6.9749488831,38.873336792],"type":"Point"}
}