{
  "type": "Feature",
  "properties": {
    "addr:full":"Carrer de Navas De Tolosa, 328 Barcelona Barcelona 08027",
    "addr:housenumber":"328",
    "addr:postcode":"08027",
    "addr:street":"Carrer De Navas De Tolosa",
    "iso:country":"ES",
    "sg:address":"Carrer de Navas De Tolosa, 328",
    "sg:city":"Barcelona",
    "sg:orig_category":"Carnicer\u00cdas, Carnicer\u00cdas",
    "sg:phone":"+34 934 08 36 34",
    "sg:postcode":"08027",
    "sg:province":"Barcelona",
    "wof:name":"Jamones El Charro S. A.",
    "wof:placetype":"venue"
},
  "geometry": {"coordinates":[2.1833250523,41.4181900024],"type":"Point"}
}