{
  "type": "Feature",
  "properties": {
    "iso:country":"ES",
    "sg:address":"Carrer de Enric Granados, 147",
    "sg:city":"Barcelona",
    "sg:orig_category":"Peluqueros: De Se\u00d1oras",
    "sg:phone":"+34 934 14 76 80",
    "sg:postcode":"08008",
    "sg:province":"Barcelona",
    "wof:name":"Plaza Notario Guillermina",
    "wof:placetype":"venue"
},
  "geometry": {"coordinates":[2.1535909176,41.39427948],"type":"Point"}
}