{
  "type": "Feature",
  "properties": {
    "addr:full":"Pol Ind Plasencia, S/n Plasencia C\u00e1ceres 10600",
    "addr:housenumber":"s / n",
    "addr:postcode":"10600",
    "addr:street":"Ca\u0301Ceres",
    "iso:country":"ES",
    "sg:address":"Pol Ind Plasencia, S/n",
    "sg:city":"Plasencia",
    "sg:orig_category":"Veh\u00cdculos De Ocasi\u00d3n",
    "sg:phone":"+34 927 42 00 02",
    "sg:postcode":"10600",
    "sg:province":"C\u00e1ceres",
    "wof:name":"Automoviles Martin E Hijos S.l.",
    "wof:placetype":"venue"
},
  "geometry": {"coordinates":[-6.0649971962,40.014591217],"type":"Point"}
}