{
  "type": "Feature",
  "properties": {
    "iso:country":"ES",
    "sg:address":"Carrer de Ramon J. Sender, 17",
    "sg:city":"Reus",
    "sg:orig_category":"Comercio De Piezas De Recambio Y De Accesorios De Veh\u00cdculos, Veh\u00cdculos Industriales",
    "sg:phone":"+34 977 75 70 49",
    "sg:postcode":"43204",
    "sg:province":"Tarragona",
    "wof:name":"Recambios Aicrag S. A.",
    "wof:placetype":"venue"
},
  "geometry": {"coordinates":[1.1121610403,41.1495628357],"type":"Point"}
}