{
  "type": "Feature",
  "properties": {
    "addr:full":"Calle de Noviembre, 15 Madrid Madrid 28022",
    "addr:housenumber":"15",
    "addr:postcode":"madrid;28022",
    "addr:street":"Calle De Noviembre",
    "iso:country":"ES",
    "sg:address":"Calle de Noviembre, 15",
    "sg:city":"Madrid",
    "sg:orig_category":"Escaparatistas, Decoradores",
    "sg:phone":"+34 917 48 03 83",
    "sg:postcode":"28022",
    "sg:province":"Madrid",
    "wof:name":"Zona Viva S.l.",
    "wof:placetype":"venue"
},
  "geometry": {"coordinates":[-3.5683321953,40.446308136],"type":"Point"}
}