{
  "type": "Feature",
  "properties": {
    "addr:full":"Plaz Polo De Bernabe, 3 Valencia Valencia 46010",
    "addr:housenumber":"3",
    "addr:postcode":"46010",
    "addr:street":"Valencia",
    "iso:country":"ES",
    "sg:address":"Plaz Polo De Bernabe, 3",
    "sg:city":"Valencia",
    "sg:orig_category":"Abogados",
    "sg:phone":"+34 963 69 40 06",
    "sg:postcode":"46010",
    "sg:province":"Valencia",
    "wof:name":"Aranegui Gasco Maria Del Rosario",
    "wof:placetype":"venue"
},
  "geometry": {"coordinates":[-0.3629963994,39.4750976562],"type":"Point"}
}