{
  "type": "Feature",
  "properties": {
    "addr:full":"Luga Parada (a), 4 Parada Ourense 32930",
    "addr:postcode":"32930",
    "iso:country":"ES",
    "sg:address":"Luga Parada (a), 4",
    "sg:city":"Parada",
    "sg:orig_category":"Molduras, Junquillos, Listones Y Molduras Perforadas",
    "sg:phone":"+34 988 38 22 04",
    "sg:postcode":"32930",
    "sg:province":"Ourense",
    "wof:name":"Conde Gallego Nicanor",
    "wof:placetype":"venue"
},
  "geometry": {"coordinates":[-7.9522171021,42.3144187927],"type":"Point"}
}