{
  "type": "Feature",
  "properties": {
    "addr:full":"Calle de Obispo Quesada, 5 Daimiel Ciudad Real 13250",
    "addr:housenumber":"5",
    "addr:postcode":"13250",
    "addr:street":"Calle De Obispo Quesada",
    "iso:country":"ES",
    "sg:address":"Calle de Obispo Quesada, 5",
    "sg:city":"Daimiel",
    "sg:orig_category":"Persianas Interiores, Exteriores",
    "sg:phone":"+34 926 85 07 74",
    "sg:postcode":"13250",
    "sg:province":"Ciudad Real",
    "wof:name":"Colado Campos Angel",
    "wof:placetype":"venue"
},
  "geometry": {"coordinates":[-3.6144399643,39.0689544678],"type":"Point"}
}