{
  "type": "Feature",
  "properties": {
    "iso:country":"ES",
    "sg:address":"Plaz Libertad, 3",
    "sg:city":"Valladolid",
    "sg:orig_category":"M\u00c9dicos: Foniatr\u00cda Y Logopedia",
    "sg:phone":"+34 983 30 81 03",
    "sg:postcode":"47002",
    "sg:province":"Valladolid",
    "wof:name":"Redondo Araoz Luis",
    "wof:placetype":"venue"
},
  "geometry": {"coordinates":[-4.7256851196,41.6523551941],"type":"Point"}
}