{
  "type": "Feature",
  "properties": {
    "iso:country":"ES",
    "sg:address":"Calle de Tirujon, 1",
    "sg:city":"Miranda Arga",
    "sg:orig_category":"Asilos De Ancianos. Centros Privados",
    "sg:phone":"+34 948 71 74 27",
    "sg:postcode":"31253",
    "sg:province":"Navarra",
    "wof:name":"Residencia De Ancianos Virgen Del Castillo",
    "wof:placetype":"venue"
},
  "geometry": {"coordinates":[-1.8264750242,42.4827919006],"type":"Point"}
}