{
  "type": "Feature",
  "properties": {
    "addr:full":"Avda Caceres, 56 Merida Badajoz 06800",
    "addr:housenumber":"56",
    "addr:postcode":"06800",
    "addr:street":"Avda Caceres",
    "iso:country":"ES",
    "sg:address":"Avda Caceres, 56",
    "sg:city":"Merida",
    "sg:orig_category":"Mec\u00c1nico Del Autom\u00d3vil",
    "sg:phone":"+34 924 33 06 76",
    "sg:postcode":"06800",
    "sg:province":"Badajoz",
    "wof:name":"Sanchez Nova Jose",
    "wof:placetype":"venue"
},
  "geometry": {"coordinates":[-6.3464288712,38.9208984375],"type":"Point"}
}