{
  "type": "Feature",
  "properties": {
    "iso:country":"ES",
    "sg:address":"Carrer de Santiago Rusi\u00d1ol, 7",
    "sg:city":"Sant Feliu Llobregat",
    "sg:orig_category":"Equipo De Refrigeraci\u00d3n Industrial",
    "sg:phone":"+34 936 66 07 72",
    "sg:postcode":"08980",
    "sg:province":"Barcelona",
    "wof:name":"Gallardo Gonzalez Jose",
    "wof:placetype":"venue"
},
  "geometry": {"coordinates":[2.0528120995,41.380607605],"type":"Point"}
}