{
  "type": "Feature",
  "properties": {
    "iso:country":"ES",
    "sg:address":"Avda Blasco Iba\u00d1ez, 25",
    "sg:city":"Valencia",
    "sg:orig_category":"Promotores Constructores",
    "sg:phone":"+34 963 39 42 40",
    "sg:postcode":"46010",
    "sg:province":"Valencia",
    "wof:name":"Fcc Construccion S.a.",
    "wof:placetype":"venue"
},
  "geometry": {"coordinates":[-0.3576599956,39.4773330688],"type":"Point"}
}