{
  "type": "Feature",
  "properties": {
    "iso:country":"ES",
    "sg:address":"Calle de Astros, 4",
    "sg:city":"Consuegra",
    "sg:classifiers":[
        {
            "category":"Taxi",
            "type":"Transportation"
        }
    ],
    "sg:phone":"+34 925 47 52 81",
    "sg:postcode":"45700",
    "sg:province":"Toledo",
    "wof:name":"Ca\u00f1adilla De La Cruz Paulino",
    "wof:placetype":"venue"
},
  "geometry": {"coordinates":[-3.614328146,39.460319519],"type":"Point"}
}