{
  "type": "Feature",
  "properties": {
    "addr:full":"Carr Havana, L', 20 Vilanova I La Geltru Barcelona 08800",
    "addr:housenumber":"20",
    "addr:postcode":"08800",
    "addr:street":"Carr Havana L '",
    "iso:country":"ES",
    "sg:address":"Carr Havana, L', 20",
    "sg:city":"Vilanova I La Geltru",
    "sg:orig_category":"M\u00c9dicos: Ginecolog\u00cda Y Obstetricia",
    "sg:phone":"+34 938 15 03 92",
    "sg:postcode":"08800",
    "sg:province":"Barcelona",
    "wof:name":"Vicens Banus Jose",
    "wof:placetype":"venue"
},
  "geometry": {"coordinates":[1.724421978,41.2213134766],"type":"Point"}
}