{
  "type": "Feature",
  "properties": {
    "iso:country":"ES",
    "sg:address":"Plaz Regentes (los), 1",
    "sg:city":"Carrion De Los Condes",
    "sg:orig_category":"Arquitectos",
    "sg:phone":"+34 979 88 07 41",
    "sg:postcode":"34120",
    "sg:province":"Palencia",
    "wof:name":"Irache Varona I\u00f1igo",
    "wof:placetype":"venue"
},
  "geometry": {"coordinates":[-4.6025371552,42.3382453918],"type":"Point"}
}