{
  "type": "Feature",
  "properties": {
    "iso:country":"ES",
    "sg:address":"Calle de Cuesta, 24",
    "sg:city":"Milagro",
    "sg:orig_category":"Florister\u00cdas",
    "sg:phone":"+34 948 86 15 72",
    "sg:postcode":"31320",
    "sg:province":"Navarra",
    "wof:name":"Romanos Vi\u00f1aras Jose",
    "wof:placetype":"venue"
},
  "geometry": {"coordinates":[-1.7637341022,42.243019104],"type":"Point"}
}