{
  "type": "Feature",
  "properties": {
    "addr:full":"Calle de Beethoven, 7 Valencia Valencia 46017",
    "addr:housenumber":"7",
    "addr:postcode":"46017",
    "addr:street":"Calle De Beethoven",
    "iso:country":"ES",
    "sg:address":"Calle de Beethoven, 7",
    "sg:city":"Valencia",
    "sg:orig_category":"Retoques De Vestidos",
    "sg:phone":"+34 963 57 05 20",
    "sg:postcode":"46017",
    "sg:province":"Valencia",
    "wof:name":"Cabrelles Faustino Maria Amparo",
    "wof:placetype":"venue"
},
  "geometry": {"coordinates":[-0.3897866011,39.4495811462],"type":"Point"}
}