{
  "type": "Feature",
  "properties": {
    "iso:country":"ES",
    "sg:address":"Carrer de Princep De Bergara, 54",
    "sg:city":"Hospitalet Llobregat",
    "sg:orig_category":"Agencias De Trabajo Temporal",
    "sg:phone":"+34 932 60 02 21",
    "sg:postcode":"08901",
    "sg:province":"Barcelona",
    "sg:website":"www.alliancesp.com",
    "wof:name":"Especialistas En Trabajo Temporal S.a.",
    "wof:placetype":"venue"
},
  "geometry": {"coordinates":[2.09938097,41.3575782776],"type":"Point"}
}