{
  "type": "Feature",
  "properties": {
    "addr:full":"Carrer de Sant Pau, 100 Caldes Montbui Barcelona 08140",
    "addr:housenumber":"100",
    "addr:postcode":"08140",
    "addr:street":"Carrer De Sant Pau;Montbui Barcelona",
    "iso:country":"ES",
    "sg:address":"Carrer de Sant Pau, 100",
    "sg:city":"Caldes Montbui",
    "sg:orig_category":"Laboratorios Farmac\u00c9uticos",
    "sg:phone":"+34 938 65 54 52",
    "sg:postcode":"08140",
    "sg:province":"Barcelona",
    "wof:name":"A.m.c. Cosmetics Caldes S.l.",
    "wof:placetype":"venue"
},
  "geometry": {"coordinates":[2.1669070721,41.6275672913],"type":"Point"}
}