{
  "type": "Feature",
  "properties": {
    "addr:full":"Avda Adoratrices, 47 Huelva Huelva 21004",
    "addr:housenumber":"47",
    "addr:postcode":"21004",
    "addr:street":"Avda Adoratrices",
    "iso:country":"ES",
    "sg:address":"Avda Adoratrices, 47",
    "sg:city":"Huelva",
    "sg:classifiers":[
        {
            "category":"Personal",
            "subcategory":"Barber",
            "type":"Services"
        }
    ],
    "sg:phone":"+34 959 25 65 01",
    "sg:postcode":"21004",
    "sg:province":"Huelva",
    "sg:tags":[
        "caballeros",
        "de",
        "peluqueros"
    ],
    "wof:name":"Dominguez Vazquez Antonio",
    "wof:placetype":"venue"
},
  "geometry": {"coordinates":[-6.9429178238,37.2657585144],"type":"Point"}
}