{
  "type": "Feature",
  "properties": {
    "iso:country":"ES",
    "sg:address":"Calle de Secretario Artiles, 50",
    "sg:city":"Palmas De Gran Canaria",
    "sg:orig_category":"Fisioterapia",
    "sg:phone":"+34 928 22 27 13",
    "sg:postcode":"35007",
    "sg:province":"Las Palmas",
    "wof:name":"Barrera Barrero Cristina Aleida",
    "wof:placetype":"venue"
},
  "geometry": {"coordinates":[-15.4321146011,28.1396999359],"type":"Point"}
}