{
  "type": "Feature",
  "properties": {
    "addr:full":"Av Vidal I Barraquer, 8 Cambrils Tarragona 43850",
    "addr:housenumber":"8",
    "addr:postcode":"43850",
    "addr:street":"Av Vidal I Barraquer",
    "iso:country":"ES",
    "sg:address":"Av Vidal I Barraquer, 8",
    "sg:city":"Cambrils",
    "sg:orig_category":"Zapater\u00cdas",
    "sg:phone":"+34 977 36 02 18",
    "sg:postcode":"43850",
    "sg:province":"Tarragona",
    "wof:name":"Pedrola Massague Maria Lluisa",
    "wof:placetype":"venue"
},
  "geometry": {"coordinates":[1.0522739887,41.0740127563],"type":"Point"}
}