{
  "type": "Feature",
  "properties": {
    "addr:full":"Calle de Juan Ramon Jimenez, 8 Sanlucar De Barrameda C\u00e1diz 11540",
    "addr:housenumber":"8",
    "addr:postcode":"11540",
    "addr:street":"Calle De Juan Ramon Jimenez;Ca\u0301Diz",
    "iso:country":"ES",
    "sg:address":"Calle de Juan Ramon Jimenez, 8",
    "sg:city":"Sanlucar De Barrameda",
    "sg:orig_category":"Panader\u00cdas, Panader\u00cdas",
    "sg:phone":"+34 956 36 39 17",
    "sg:postcode":"11540",
    "sg:province":"C\u00e1diz",
    "wof:name":"Nu\u00f1ez Humanes Manuel",
    "wof:placetype":"venue"
},
  "geometry": {"coordinates":[-6.3545398712,36.7829437256],"type":"Point"}
}