{
  "type": "Feature",
  "properties": {
    "iso:country":"ES",
    "sg:address":"Carr Ruiz I Pablo, 13",
    "sg:city":"Ciutadella Menorca",
    "sg:orig_category":"Confecci\u00d3n De Zapatos",
    "sg:phone":"+34 971 38 36 72",
    "sg:postcode":"07760",
    "sg:province":"Islas Baleares",
    "wof:name":"Trujillo Sarabia Jose Luis",
    "wof:placetype":"venue"
},
  "geometry": {"coordinates":[3.8324320316,39.9984397888],"type":"Point"}
}