{
  "type": "Feature",
  "properties": {
    "iso:country":"ES",
    "sg:address":"Calle de Serra Mariola, 6",
    "sg:city":"Paiporta",
    "sg:orig_category":"Molduras, Junquillos, Listones Y Molduras Perforadas",
    "sg:phone":"+34 963 97 48 76",
    "sg:postcode":"46200",
    "sg:province":"Valencia",
    "wof:name":"Sanchez Carrillo S. L.",
    "wof:placetype":"venue"
},
  "geometry": {"coordinates":[-0.4191040099,39.4182929993],"type":"Point"}
}