{
  "type": "Feature",
  "properties": {
    "addr:full":"Plaz Virgencilla, 5 Aranda Duero Burgos 09400",
    "addr:housenumber":"5",
    "addr:postcode":"09400",
    "addr:street":"Plaz Virgencilla",
    "iso:country":"ES",
    "sg:address":"Plaz Virgencilla, 5",
    "sg:city":"Aranda Duero",
    "sg:classifiers":[
        {
            "category":"Autos & Motor Vehicles",
            "subcategory":"Automobile Sales",
            "type":"Retail Goods"
        }
    ],
    "sg:phone":"+34 947 50 96 61",
    "sg:postcode":"09400",
    "sg:province":"Burgos",
    "wof:name":"Rojo De Frutos Jesus",
    "wof:placetype":"venue"
},
  "geometry": {"coordinates":[-3.6889948845,41.6699256897],"type":"Point"}
}