{
  "type": "Feature",
  "properties": {
    "addr:full":"Calle de Perez Galdos, 2 Santa Cruz De Tenerife Santa Cruz De Tenerife 38002",
    "addr:housenumber":"2",
    "addr:postcode":"38002",
    "addr:street":"Calle De Perez Galdos",
    "iso:country":"ES",
    "sg:address":"Calle de Perez Galdos, 2",
    "sg:city":"Santa Cruz De Tenerife",
    "sg:orig_category":"Agencias De Viajes",
    "sg:phone":"+34 922 20 20 80",
    "sg:postcode":"38002",
    "sg:province":"Santa Cruz De Tenerife",
    "wof:name":"Viajes 5 Oceanos Canarias, S.l.",
    "wof:placetype":"venue"
},
  "geometry": {"coordinates":[-16.2516822815,28.4677906036],"type":"Point"}
}