{
  "type": "Feature",
  "properties": {
    "iso:country":"ES",
    "sg:address":"Carrer de Melilla, 7",
    "sg:city":"Amposta",
    "sg:orig_category":"Goma: Productos De Uso Industrial (fabricaci\u00d3n, Al Por Mayor)",
    "sg:phone":"+34 977 70 32 62",
    "sg:postcode":"43870",
    "sg:province":"Tarragona",
    "wof:name":"Germans Ca\u00f1ellas Comunidad De Bienes",
    "wof:placetype":"venue"
},
  "geometry": {"coordinates":[0.5840839744,40.711894989],"type":"Point"}
}