{
  "type": "Feature",
  "properties": {
    "iso:country":"ES",
    "sg:address":"Rua Parroco Alonso Alvarez, 5",
    "sg:city":"Fonsagrada",
    "sg:orig_category":"Autob\u00das (explotaci\u00d3n Y Servicios De)",
    "sg:phone":"+34 982 34 00 55",
    "sg:postcode":"27100",
    "sg:province":"Lugo",
    "wof:name":"Alferher S.l.",
    "wof:placetype":"venue"
},
  "geometry": {"coordinates":[-7.0707244873,43.1259613037],"type":"Point"}
}