{
  "type": "Feature",
  "properties": {
    "addr:full":"Plaz Valle Del Nalon (del), 4 Partija-santa Monica Madrid 28529",
    "addr:postcode":"28529",
    "iso:country":"ES",
    "sg:address":"Plaz Valle Del Nalon (del), 4",
    "sg:city":"Partija-santa Monica",
    "sg:orig_category":"Filtros Y Elementos Filtradores",
    "sg:phone":"+34 914 99 20 27",
    "sg:postcode":"28529",
    "sg:province":"Madrid",
    "wof:name":"Domnick Hunter Iberica Limited Sucursal",
    "wof:placetype":"venue"
},
  "geometry": {"coordinates":[-3.5102670193,40.314289093],"type":"Point"}
}