{
  "type": "Feature",
  "properties": {
    "iso:country":"ES",
    "sg:address":"Calle de Ca\u00d1ada, 22",
    "sg:city":"Pumarejo Tera",
    "sg:orig_category":"Promotores Constructores",
    "sg:phone":"+34 980 64 95 65",
    "sg:postcode":"49626",
    "sg:province":"Zamora",
    "wof:name":"Vega Colino Esteban",
    "wof:placetype":"venue"
},
  "geometry": {"coordinates":[-6.0345578194,41.9697723389],"type":"Point"}
}