{
  "type": "Feature",
  "properties": {
    "iso:country":"ES",
    "sg:address":"Sierra Segura(urb Nueva Cartagena), S/n",
    "sg:city":"Cartagena",
    "sg:orig_category":"Inform\u00c1tica: Material Y Suministros",
    "sg:phone":"+34 968 33 00 91",
    "sg:postcode":"30205",
    "sg:province":"Murcia",
    "wof:name":"Vicar Informatica S.l.",
    "wof:placetype":"venue"
},
  "geometry": {"coordinates":[-1.0092389584,37.6218910217],"type":"Point"}
}