{
  "type": "Feature",
  "properties": {
    "iso:country":"ES",
    "sg:address":"Calle de Alonso De Burgos, 6",
    "sg:city":"Cordoba",
    "sg:orig_category":"Agricultura: Abastecimiento Y Cosechado (negocio)",
    "sg:phone":"+34 957 49 81 18",
    "sg:postcode":"14008",
    "sg:province":"C\u00f3rdoba",
    "wof:name":"Agronova Sistemas Integrales Agricolas S.l",
    "wof:placetype":"venue"
},
  "geometry": {"coordinates":[-4.783967,37.88625],"type":"Point"}
}