{
  "type": "Feature",
  "properties": {
    "addr:full":"Avda Mahia, 58 Bertamirans La Coru\u00f1a 15220",
    "addr:housenumber":"58",
    "addr:postcode":"15220",
    "addr:street":"Avda Mahia;La Corun\u0303A",
    "iso:country":"ES",
    "sg:address":"Avda Mahia, 58",
    "sg:city":"Bertamirans",
    "sg:orig_category":"Asesor\u00cda Fiscal Y Jur\u00cddica",
    "sg:phone":"+34 981 89 19 72",
    "sg:postcode":"15220",
    "sg:province":"La Coru\u00f1a",
    "wof:name":"Lamela Barral Aurora",
    "wof:placetype":"venue"
},
  "geometry": {"coordinates":[-8.6535749435,42.8590164185],"type":"Point"}
}