{
  "type": "Feature",
  "properties": {
    "iso:country":"ES",
    "sg:address":"Calle de Loma Hermosa, 6",
    "sg:city":"Alacant",
    "sg:orig_category":"Inmobiliaria (agencias)",
    "sg:phone":"+34 965 26 50 50",
    "sg:postcode":"03559",
    "sg:province":"Alicante",
    "wof:name":"Sala Y Monfort S.l.",
    "wof:placetype":"venue"
},
  "geometry": {"coordinates":[-0.4424389899,38.3899841309],"type":"Point"}
}