{
  "type": "Feature",
  "properties": {
    "iso:country":"ES",
    "sg:address":"Polo Y Bernabe, 33",
    "sg:city":"Quartell",
    "sg:orig_category":"Arboricultura Y Producci\u00d3n De Frutas",
    "sg:phone":"+34 962 63 61 32",
    "sg:postcode":"46510",
    "sg:province":"Valencia",
    "wof:name":"Tamasa 2005 S.l.",
    "wof:placetype":"venue"
},
  "geometry": {"coordinates":[-0.2625359893,39.7384567261],"type":"Point"}
}