{
  "type": "Feature",
  "properties": {
    "iso:country":"ES",
    "sg:address":"Ctra. Port Des Torrent, S/n",
    "sg:city":"S. Agusti Vedra",
    "sg:orig_category":"Fabricaci\u00d3n De Bicicletas, Motocicletas Y Piezas Sueltas",
    "sg:phone":"+34 971 34 30 68",
    "sg:postcode":"07839",
    "sg:province":"Islas Baleares",
    "wof:name":"Nichols  James Martin",
    "wof:placetype":"venue"
},
  "geometry": {"coordinates":[1.3025970459,38.8642692566],"type":"Point"}
}