{
  "type": "Feature",
  "properties": {
    "addr:full":"Carr Seix I Faya, 24 Tremp Lleida 25620",
    "addr:housenumber":"24",
    "addr:postcode":"25620",
    "addr:street":"Carr Seix I Faya",
    "iso:country":"ES",
    "sg:address":"Carr Seix I Faya, 24",
    "sg:city":"Tremp",
    "sg:orig_category":"M\u00c9dicos: Estomatolog\u00cda",
    "sg:phone":"+34 973 65 13 03",
    "sg:postcode":"25620",
    "sg:province":"Lleida",
    "wof:name":"Garcia De La Chica Parache Montserrat",
    "wof:placetype":"venue"
},
  "geometry": {"coordinates":[0.8952310085,42.1695861816],"type":"Point"}
}