{
  "type": "Feature",
  "properties": {
    "iso:country":"ES",
    "sg:address":"Carrer de Menendez Pelayo, 27",
    "sg:city":"Vilafranca Penedes",
    "sg:orig_category":"Tapicer\u00cdas",
    "sg:phone":"+34 938 90 46 01",
    "sg:postcode":"08720",
    "sg:province":"Barcelona",
    "wof:name":"Salvador Coll I Fill S.c.c.l.",
    "wof:placetype":"venue"
},
  "geometry": {"coordinates":[1.6995199919,41.3405685425],"type":"Point"}
}