{
  "type": "Feature",
  "properties": {
    "addr:full":"Carrer de Bigai, 4 Barcelona Barcelona 08022",
    "addr:housenumber":"4",
    "addr:postcode":"08022",
    "addr:street":"Carrer De Bigai",
    "iso:country":"ES",
    "sg:address":"Carrer de Bigai, 4",
    "sg:city":"Barcelona",
    "sg:orig_category":"Inmobiliaria (agencias)",
    "sg:phone":"+34 932 11 41 99",
    "sg:postcode":"08022",
    "sg:province":"Barcelona",
    "wof:name":"Bonanova 2000 S.l.",
    "wof:placetype":"venue"
},
  "geometry": {"coordinates":[2.1327030659,41.4048156738],"type":"Point"}
}