{
  "type": "Feature",
  "properties": {
    "iso:country":"ES",
    "sg:address":"Avda Libertad (la), 24",
    "sg:city":"San Vicente Del Raspeig-sant Vicent Del Raspeig",
    "sg:orig_category":"Asesor\u00cda De Formaci\u00d3n Y Gesti\u00d3n De Personal",
    "sg:phone":"+34 965 66 88 01",
    "sg:postcode":"03690",
    "sg:province":"Alicante",
    "sg:website":"www.coem-asesores.es",
    "wof:name":"Garcia Lillo Miguel Angel",
    "wof:placetype":"venue"
},
  "geometry": {"coordinates":[-0.5227479935,38.3971176147],"type":"Point"}
}