{
  "type": "Feature",
  "properties": {
    "iso:country":"ES",
    "sg:address":"Calle de Alvarez De Lugo, 52",
    "sg:city":"Santa Cruz De Tenerife",
    "sg:orig_category":"Inform\u00c1tica Equipo Y Programas (al Por Mayor)",
    "sg:phone":"+34 922 29 37 73",
    "sg:postcode":"38004",
    "sg:province":"Santa Cruz De Tenerife",
    "sg:website":"www.ofertasdia.com",
    "wof:name":"Atlantico Nuevas Tecnologias S.l.",
    "wof:placetype":"venue"
},
  "geometry": {"coordinates":[-16.258310318,28.4660682678],"type":"Point"}
}