{
  "type": "Feature",
  "properties": {
    "iso:country":"ES",
    "sg:address":"Calle de Santa Maria De Gracia, 5",
    "sg:city":"Carmona",
    "sg:orig_category":"Reposter\u00cdas",
    "sg:phone":"+34 954 14 21 12",
    "sg:postcode":"41410",
    "sg:province":"Sevilla",
    "wof:name":"Horno San Teodomiro S.c",
    "wof:placetype":"venue"
},
  "geometry": {"coordinates":[-5.6370477676,37.4742355347],"type":"Point"}
}