{
  "type": "Feature",
  "properties": {
    "iso:country":"ES",
    "sg:address":"Avda Isaac Peral, 15",
    "sg:city":"Malaga",
    "sg:orig_category":"Ropa Para Se\u00d1oras Y Caballeros (al Por Menor)",
    "sg:phone":"+34 952 24 23 47",
    "sg:postcode":"29004",
    "sg:province":"M\u00e1laga",
    "wof:name":"Gorga Garijo Maria Del Carmen",
    "wof:placetype":"venue"
},
  "geometry": {"coordinates":[-4.4558768272,36.6964607239],"type":"Point"}
}