{
  "type": "Feature",
  "properties": {
    "iso:country":"ES",
    "sg:address":"Calle de Camino Del Pijorro, S/n",
    "sg:city":"Navalcarnero",
    "sg:orig_category":"Semiller\u00cdas",
    "sg:phone":"+34 918 11 10 58",
    "sg:postcode":"28600",
    "sg:province":"Madrid",
    "wof:name":"Mundo Jardin S.l",
    "wof:placetype":"venue"
},
  "geometry": {"coordinates":[-4.0082564354,40.3008613586],"type":"Point"}
}