{
  "type": "Feature",
  "properties": {
    "addr:full":"Ctra Valdepe\u00d1as, 17 Ciudad Real Ciudad Real 13004",
    "addr:housenumber":"17",
    "addr:postcode":"13004",
    "addr:street":"Ctra Valdepen\u0303As",
    "iso:country":"ES",
    "sg:address":"Ctra Valdepe\u00d1as, 17",
    "sg:city":"Ciudad Real",
    "sg:orig_category":"Montaje (empresas De)",
    "sg:phone":"+34 926 22 33 34",
    "sg:postcode":"13004",
    "sg:province":"Ciudad Real",
    "wof:name":"Eulen S.a.",
    "wof:placetype":"venue"
},
  "geometry": {"coordinates":[-3.9193470478,38.982170105],"type":"Point"}
}