{
  "type": "Feature",
  "properties": {
    "iso:country":"ES",
    "sg:address":"Calle de Huertas, 72",
    "sg:city":"Madrid",
    "sg:orig_category":"Abogados",
    "sg:phone":"+34 913 69 27 57",
    "sg:postcode":"28014",
    "sg:province":"Madrid",
    "wof:name":"Abad Panadero Alvaro",
    "wof:placetype":"venue"
},
  "geometry": {"coordinates":[-3.695403,40.412979],"type":"Point"}
}