{
  "type": "Feature",
  "properties": {
    "iso:country":"ES",
    "sg:address":"Carr Argenteria, 10",
    "sg:city":"Girona",
    "sg:orig_category":"Papeler\u00cdas, Librer\u00cdas",
    "sg:phone":"+34 972 22 17 06",
    "sg:postcode":"17004",
    "sg:province":"Girona",
    "wof:name":"Borras Montserrat Nuria",
    "wof:placetype":"venue"
},
  "geometry": {"coordinates":[2.8247029781,41.9847831726],"type":"Point"}
}