{
  "type": "Feature",
  "properties": {
    "addr:full":"Calle de Juan Carlos I, 2 Aznalcazar Sevilla 41849",
    "addr:housenumber":"2",
    "addr:postcode":"41849",
    "addr:street":"Calle De Juan Carlos I",
    "iso:country":"ES",
    "sg:address":"Calle de Juan Carlos I, 2",
    "sg:city":"Aznalcazar",
    "sg:orig_category":"Cajas Para Embalar",
    "sg:phone":"+34 955 75 04 27",
    "sg:postcode":"41849",
    "sg:province":"Sevilla",
    "wof:name":"Caja Rural Del Sur Sociedad Cooperativa",
    "wof:placetype":"venue"
},
  "geometry": {"coordinates":[-6.2504820824,37.3043060303],"type":"Point"}
}