{
  "type": "Feature",
  "properties": {
    "addr:full":"Ronda Fuensanta, 20 Lucena C\u00f3rdoba 14900",
    "addr:housenumber":"20",
    "addr:postcode":"14900",
    "addr:street":"Fuensanta",
    "iso:country":"ES",
    "sg:address":"Ronda Fuensanta, 20",
    "sg:city":"Lucena",
    "sg:orig_category":"Fabricaci\u00d3n De Muebles",
    "sg:phone":"+34 957 51 10 40",
    "sg:postcode":"14900",
    "sg:province":"C\u00f3rdoba",
    "wof:name":"Ramirez Rivera Araceli",
    "wof:placetype":"venue"
},
  "geometry": {"coordinates":[-4.4815850258,37.4124603271],"type":"Point"}
}