{
  "type": "Feature",
  "properties": {
    "addr:full":"Calle de Manuel Gonzalez Martin, 24 Palmas De Gran Canaria Las Palmas 35005",
    "addr:postcode":"35005",
    "addr:street":"Calle De Manuel Gonzalez Martin 24",
    "iso:country":"ES",
    "sg:address":"Calle de Manuel Gonzalez Martin, 24",
    "sg:city":"Palmas De Gran Canaria",
    "sg:orig_category":"Molduras, Junquillos, Listones Y Molduras Perforadas",
    "sg:phone":"+34 928 24 02 27",
    "sg:postcode":"35005",
    "sg:province":"Las Palmas",
    "wof:name":"Sistelcom-telemensaje S.a.",
    "wof:placetype":"venue"
},
  "geometry": {"coordinates":[-15.4307909012,28.1293678284],"type":"Point"}
}