{
  "type": "Feature",
  "properties": {
    "addr:full":"Avda Felix Rodriguez De La Fuente, S/n Mancha Real Ja\u00e9n 23100",
    "addr:housenumber":"s / n",
    "addr:postcode":"23100",
    "addr:street":"Avda Felix Rodriguez De La Fuente",
    "iso:country":"ES",
    "sg:address":"Avda Felix Rodriguez De La Fuente, S/n",
    "sg:city":"Mancha Real",
    "sg:orig_category":"Venta, Montaje De Neum\u00c1ticos",
    "sg:phone":"+34 953 35 05 50",
    "sg:postcode":"23100",
    "sg:province":"Ja\u00e9n",
    "wof:name":"Sanchez Jimenez Luis",
    "wof:placetype":"venue"
},
  "geometry": {"coordinates":[-3.6102991104,37.7823104858],"type":"Point"}
}