{
  "type": "Feature",
  "properties": {
    "addr:full":"Avda Baron De Carcer, 39 Valencia Valencia 46001",
    "addr:housenumber":"39",
    "addr:postcode":"46001",
    "addr:street":"Avda Baron De Carcer",
    "iso:country":"ES",
    "sg:address":"Avda Baron De Carcer, 39",
    "sg:city":"Valencia",
    "sg:orig_category":"Listas De Boda, Menaje De Mesa Y Cocina",
    "sg:phone":"+34 963 52 83 61",
    "sg:postcode":"46001",
    "sg:province":"Valencia",
    "wof:name":"Herederos Sanz Bonacho.cb.",
    "wof:placetype":"venue"
},
  "geometry": {"coordinates":[-0.3795180023,39.4702949524],"type":"Point"}
}