{
  "type": "Feature",
  "properties": {
    "addr:full":"Avda Damian Tellez Lafuente, 4 Badajoz Badajoz 06010",
    "addr:housenumber":"4",
    "addr:postcode":"06010",
    "addr:street":"Avda Damian Tellez Lafuente",
    "iso:country":"ES",
    "sg:address":"Avda Damian Tellez Lafuente, 4",
    "sg:city":"Badajoz",
    "sg:orig_category":"\u00d3ptica: Instrumentos (fabricaci\u00d3n)",
    "sg:phone":"+34 924 26 11 97",
    "sg:postcode":"06010",
    "sg:province":"Badajoz",
    "wof:name":"Optica Luz C.b.",
    "wof:placetype":"venue"
},
  "geometry": {"coordinates":[-6.973151207,38.8688964844],"type":"Point"}
}