{
  "type": "Feature",
  "properties": {
    "iso:country":"ES",
    "sg:address":"Calle de Calvario, 66",
    "sg:city":"Gineta",
    "sg:orig_category":"Mec\u00c1nico Del Autom\u00d3vil",
    "sg:phone":"+34 967 27 60 63",
    "sg:postcode":"02110",
    "sg:province":"Albacete",
    "wof:name":"Talleres La Gineta",
    "wof:placetype":"venue"
},
  "geometry": {"coordinates":[-1.9977790117,39.1163902283],"type":"Point"}
}