{
  "type": "Feature",
  "properties": {
    "addr:full":"Calle de Ermita La, S/n S. Roque C\u00e1diz 11360",
    "addr:postcode":"11360",
    "addr:street":"Calle De Ermita La S / N S. Roque Ca\u0301Diz",
    "iso:country":"ES",
    "sg:address":"Calle de Ermita La, S/n",
    "sg:city":"S. Roque",
    "sg:orig_category":"Bibliotecas, Mediatecas",
    "sg:phone":"+34 956 78 01 01",
    "sg:postcode":"11360",
    "sg:province":"C\u00e1diz",
    "wof:name":"Ayuntamiento De San Roque-biblioteca Mpal.",
    "wof:placetype":"venue"
},
  "geometry": {"coordinates":[-5.3944654465,36.209564209],"type":"Point"}
}