{
  "type": "Feature",
  "properties": {
    "addr:full":"Calle de Nueva, 30 Villabona Guip\u00f9zcoa 20150",
    "addr:housenumber":"30",
    "addr:postcode":"20150",
    "addr:street":"Calle De Nueva;Guipu\u0300Zcoa",
    "iso:country":"ES",
    "sg:address":"Calle de Nueva, 30",
    "sg:city":"Villabona",
    "sg:orig_category":"Confecci\u00d3n De Trajes Para Se\u00d1oras",
    "sg:phone":"+34 943 69 25 98",
    "sg:postcode":"20150",
    "sg:province":"Guip\u00f9zcoa",
    "wof:name":"Hometotown S.l.",
    "wof:placetype":"venue"
},
  "geometry": {"coordinates":[-2.0528209209,43.1883583069],"type":"Point"}
}