{
  "type": "Feature",
  "properties": {
    "iso:country":"ES",
    "sg:address":"Carrer de Princesa, 56",
    "sg:city":"Granollers",
    "sg:orig_category":"Fabricaci\u00d3n De Telas Y Sedas",
    "sg:phone":"+34 938 79 42 05",
    "sg:postcode":"08401",
    "sg:province":"Barcelona",
    "wof:name":"Parmatex S.l.",
    "wof:placetype":"venue"
},
  "geometry": {"coordinates":[2.2842450142,41.6043548584],"type":"Point"}
}