{
  "type": "Feature",
  "properties": {
    "iso:country":"ES",
    "sg:address":"Calle de Beatriz Galindo, 5",
    "sg:city":"Alcala Henares",
    "sg:orig_category":"Organismos Y Centros De Vacaciones Y Esparcimiento Para Ni\u00d1os Y Adolescentes",
    "sg:phone":"+34 918 82 53 70",
    "sg:postcode":"28803",
    "sg:province":"Madrid",
    "wof:name":"Arias Diez Rosa Mary",
    "wof:placetype":"venue"
},
  "geometry": {"coordinates":[-3.3694760799,40.4766807556],"type":"Point"}
}