{
  "type": "Feature",
  "properties": {
    "addr:full":"San Juan Kalea O\u00f1ati Guip\u00f9zcoa 20560",
    "addr:housenumber":"on\u0303ati",
    "addr:postcode":"20560",
    "addr:street":"San Juan Kalea",
    "iso:country":"ES",
    "sg:address":"San Juan Kalea",
    "sg:city":"O\u00f1ati",
    "sg:orig_category":"Sanatorios M\u00c9dico",
    "sg:phone":"+34 943 03 54 30",
    "sg:postcode":"20560",
    "sg:province":"Guip\u00f9zcoa",
    "wof:name":"Osakidetza",
    "wof:placetype":"venue"
},
  "geometry": {"coordinates":[-2.4159910679,43.0324745178],"type":"Point"}
}