{
  "type": "Feature",
  "properties": {
    "iso:country":"ES",
    "sg:address":"Calle de Pedro Martin, 20",
    "sg:city":"Candias",
    "sg:orig_category":"Electricidad: Instaladores",
    "sg:phone":"+34 922 32 50 07",
    "sg:postcode":"38312",
    "sg:province":"Santa Cruz De Tenerife",
    "wof:name":"Martin Lima Jose Miguel",
    "wof:placetype":"venue"
},
  "geometry": {"coordinates":[-16.5438785553,28.3875236511],"type":"Point"}
}