{
  "type": "Feature",
  "properties": {
    "addr:full":"La Cadena, 4 Viver Castell\u00f3n 12460",
    "addr:postcode":"12460",
    "addr:street":"Cadena",
    "iso:country":"ES",
    "sg:address":"La Cadena, 4",
    "sg:city":"Viver",
    "sg:orig_category":"Transportes De Material De Construcci\u00d3n",
    "sg:phone":"+34 964 14 10 64",
    "sg:postcode":"12460",
    "sg:province":"Castell\u00f3n",
    "wof:name":"Aridos Ma\u00f1es S.l.",
    "wof:placetype":"venue"
},
  "geometry": {"coordinates":[-0.6298921704,39.9281768799],"type":"Point"}
}