{
  "type": "Feature",
  "properties": {
    "iso:country":"ES",
    "sg:address":"Rond Sant Antoni, 100",
    "sg:city":"Barcelona",
    "sg:orig_category":"Estancos",
    "sg:phone":"+34 933 17 91 38",
    "sg:postcode":"08001",
    "sg:province":"Barcelona",
    "wof:name":"Jaume Junca Lluis",
    "wof:placetype":"venue"
},
  "geometry": {"coordinates":[2.1635665894,41.3817405701],"type":"Point"}
}