{
  "type": "Feature",
  "properties": {
    "iso:country":"ES",
    "sg:address":"Avda Marques De Los Velez, 9",
    "sg:city":"Vista Alegre",
    "sg:orig_category":"\u00d3ptica: Instrumentos (fabricaci\u00d3n)",
    "sg:phone":"+34 968 27 15 11",
    "sg:postcode":"30008",
    "sg:province":"Murcia",
    "sg:website":"www.masvision.es",
    "wof:name":"Del Olmo Lopez Y Marin S.l.",
    "wof:placetype":"venue"
},
  "geometry": {"coordinates":[-1.1286000013,37.993270874],"type":"Point"}
}