{
  "type": "Feature",
  "properties": {
    "iso:country":"ES",
    "sg:address":"Calle de Boticas, 43",
    "sg:city":"Villamartin",
    "sg:orig_category":"Zapatos (al Por Menor)",
    "sg:phone":"+34 956 73 34 71",
    "sg:postcode":"11650",
    "sg:province":"C\u00e1diz",
    "wof:name":"Calzados Carretero S.l.",
    "wof:placetype":"venue"
},
  "geometry": {"coordinates":[-5.6399950981,36.8594017029],"type":"Point"}
}