{
  "type": "Feature",
  "properties": {
    "addr:full":"Ctra. Lasarte, S/n Vitoria-gasteiz \u00c1lava 01007",
    "addr:housenumber":"s / n",
    "addr:postcode":"01007",
    "addr:street":"Ctra. Lasarte",
    "iso:country":"ES",
    "sg:address":"Ctra. Lasarte, S/n",
    "sg:city":"Vitoria-gasteiz",
    "sg:orig_category":"Deportes Diversos",
    "sg:phone":"+34 945 13 99 30",
    "sg:postcode":"01007",
    "sg:province":"\u00c1lava",
    "wof:name":"Federacion Vasca De Atletismo",
    "wof:placetype":"venue"
},
  "geometry": {"coordinates":[-2.6851940155,42.8370018005],"type":"Point"}
}