{
  "type": "Feature",
  "properties": {
    "iso:country":"ES",
    "sg:address":"Carrer de Bosch I Gimpera, 19",
    "sg:city":"Terrassa",
    "sg:orig_category":"Maquinaria Para Industrias Diversas",
    "sg:phone":"+34 937 85 63 60",
    "sg:postcode":"08223",
    "sg:province":"Barcelona",
    "wof:name":"Sereng Y Mantei S.a.",
    "wof:placetype":"venue"
},
  "geometry": {"coordinates":[2.0086250305,41.5609169006],"type":"Point"}
}