{
  "type": "Feature",
  "properties": {
    "addr:full":"Av Republica Argentina, 280 Barcelona Barcelona 08023",
    "addr:housenumber":"280",
    "addr:postcode":"08023",
    "addr:street":"Av Republica Argentina",
    "iso:country":"ES",
    "sg:address":"Av Republica Argentina, 280",
    "sg:city":"Barcelona",
    "sg:orig_category":"Cr\u00cda De Animales",
    "sg:phone":"+34 932 12 68 81",
    "sg:postcode":"08023",
    "sg:province":"Barcelona",
    "wof:name":"Corbella Torres Jose",
    "wof:placetype":"venue"
},
  "geometry": {"coordinates":[2.138240099,41.4139633179],"type":"Point"}
}