{
  "type": "Feature",
  "properties": {
    "addr:full":"G.v. Corts Catalanes, 498 Barcelona Barcelona 08015",
    "addr:housenumber":"498",
    "addr:postcode":"08015",
    "addr:street":"Catalanes",
    "iso:country":"ES",
    "sg:address":"G.v. Corts Catalanes, 498",
    "sg:city":"Barcelona",
    "sg:orig_category":"Estudios De Grabaci\u00d3n Sonora",
    "sg:phone":"+34 934 52 99 80",
    "sg:postcode":"08015",
    "sg:province":"Barcelona",
    "wof:name":"Sonorizacion Y Doblajes S.a.",
    "wof:placetype":"venue"
},
  "geometry": {"coordinates":[2.1572620869,41.3807258606],"type":"Point"}
}