{
  "type": "Feature",
  "properties": {
    "addr:full":"Carr Arago, 12 Grau I Platja Valencia 46730",
    "addr:housenumber":"12",
    "addr:postcode":"46730",
    "addr:street":"Carr Arago",
    "iso:country":"ES",
    "sg:address":"Carr Arago, 12",
    "sg:city":"Grau I Platja",
    "sg:orig_category":"Relojer\u00cda (al Por Menor, Reparaci\u00d3n)",
    "sg:phone":"+34 962 84 36 88",
    "sg:postcode":"46730",
    "sg:province":"Valencia",
    "wof:name":"Faus Pastor Tomas Rafael",
    "wof:placetype":"venue"
},
  "geometry": {"coordinates":[-0.173476994,39.0120925903],"type":"Point"}
}