{
  "type": "Feature",
  "properties": {
    "iso:country":"ES",
    "sg:address":"Calle de Trinidad, 12",
    "sg:city":"Ubeda",
    "sg:orig_category":"Empresas De Pintura Y Revestimientos",
    "sg:phone":"+34 953 75 78 34",
    "sg:postcode":"23400",
    "sg:province":"Ja\u00e9n",
    "wof:name":"Pinturas I Rehabilitaciones Vt S.l",
    "wof:placetype":"venue"
},
  "geometry": {"coordinates":[-3.3709249496,38.0144462585],"type":"Point"}
}