{
  "type": "Feature",
  "properties": {
    "addr:full":"Ctra Solchaga, S/n Garinoain Navarra 31395",
    "addr:housenumber":"s",
    "addr:postcode":"31395",
    "addr:street":"Ctra Solchaga;/ N Garinoain Navarra",
    "iso:country":"ES",
    "sg:address":"Ctra Solchaga, S/n",
    "sg:city":"Garinoain",
    "sg:orig_category":"Distribuci\u00d3n De Petr\u00d3leo Y Derivados",
    "sg:phone":"+34 948 72 00 05",
    "sg:postcode":"31395",
    "sg:province":"Navarra",
    "wof:name":"Talleres Arrubla S.l.",
    "wof:placetype":"venue"
},
  "geometry": {"coordinates":[-1.6455440521,42.6051712036],"type":"Point"}
}