{
  "type": "Feature",
  "properties": {
    "iso:country":"ES",
    "sg:address":"Calle de Berna, 6",
    "sg:city":"Caceres",
    "sg:orig_category":"Administradores De Bienes Y Delegados De Comunidades De Propietarios",
    "sg:phone":"+34 927 23 70 38",
    "sg:postcode":"10005",
    "sg:province":"C\u00e1ceres",
    "wof:name":"Comunidad De Propietarios Berna",
    "wof:placetype":"venue"
},
  "geometry": {"coordinates":[-6.3818840981,39.4584350586],"type":"Point"}
}