{
  "type": "Feature",
  "properties": {
    "addr:full":"Rua Ameas (das), S/n Santiago De Compostela A Coru\u00f1a 15704",
    "addr:housenumber":"/ n",
    "addr:postcode":"15704",
    "addr:street":"Rua Ameas Das S;Corun\u0303A",
    "iso:country":"ES",
    "sg:address":"Rua Ameas (das), S/n",
    "sg:city":"Santiago De Compostela",
    "sg:orig_category":"Pescader\u00cdas (al Por Menor)",
    "sg:phone":"+34 981 57 38 45",
    "sg:postcode":"15704",
    "sg:province":"A Coru\u00f1a",
    "wof:name":"Tubio Mu\u00f1iz Agustin",
    "wof:placetype":"venue"
},
  "geometry": {"coordinates":[-8.5413541794,42.8805656433],"type":"Point"}
}