{
  "type": "Feature",
  "properties": {
    "addr:full":"Calle de Corona De Aragon, 15 Barbastro Huesca 22300",
    "addr:housenumber":"15",
    "addr:postcode":"22300",
    "addr:street":"Calle De Corona De Aragon",
    "iso:country":"ES",
    "sg:address":"Calle de Corona De Aragon, 15",
    "sg:city":"Barbastro",
    "sg:orig_category":"Doctores En Medicina",
    "sg:phone":"+34 974 31 51 19",
    "sg:postcode":"22300",
    "sg:province":"Huesca",
    "wof:name":"Gomez Azqueta Maria Jesus",
    "wof:placetype":"venue"
},
  "geometry": {"coordinates":[0.1282366067,42.0360641479],"type":"Point"}
}