{
  "type": "Feature",
  "properties": {
    "addr:full":"Calle de San Jorge, 2 Aldea Rey Ciudad Real 13380",
    "addr:housenumber":"2",
    "addr:postcode":"13380",
    "addr:street":"Calle De San Jorge;Real",
    "iso:country":"ES",
    "sg:address":"Calle de San Jorge, 2",
    "sg:city":"Aldea Rey",
    "sg:orig_category":"Iglesia Cat\u00d3lica",
    "sg:phone":"+34 926 86 50 43",
    "sg:postcode":"13380",
    "sg:province":"Ciudad Real",
    "wof:name":"Parroquia San Jorge",
    "wof:placetype":"venue"
},
  "geometry": {"coordinates":[-3.8395779133,38.7420921326],"type":"Point"}
}