{
  "type": "Feature",
  "properties": {
    "iso:country":"ES",
    "sg:address":"Pase Berbegal, 3",
    "sg:city":"Utebo",
    "sg:orig_category":"Asesor\u00cda De Formaci\u00d3n Y Gesti\u00d3n De Personal",
    "sg:phone":"+34 976 77 51 49",
    "sg:postcode":"50180",
    "sg:province":"Zaragoza",
    "wof:name":"Asesoria Y Gestion Temar Sl",
    "wof:placetype":"venue"
},
  "geometry": {"coordinates":[-0.9970682859,41.7111244202],"type":"Point"}
}