{
  "type": "Feature",
  "properties": {
    "iso:country":"ES",
    "sg:address":"Calle de Ignacio Aldecoa, 10",
    "sg:city":"Malaga",
    "sg:orig_category":"Electricidad: Equipos Industriales, Componentes (fabricaci\u00d3n)",
    "sg:phone":"+34 952 23 95 20",
    "sg:postcode":"29006",
    "sg:province":"M\u00e1laga",
    "wof:name":"Surdema S.a.",
    "wof:placetype":"venue"
},
  "geometry": {"coordinates":[-4.4667201042,36.6934204102],"type":"Point"}
}