{
  "type": "Feature",
  "properties": {
    "iso:country":"ES",
    "sg:address":"Avda Andalucia, 56",
    "sg:city":"Jaen",
    "sg:orig_category":"Electricidad: Instaladores",
    "sg:phone":"+34 953 19 13 15",
    "sg:postcode":"23006",
    "sg:province":"Ja\u00e9n",
    "wof:name":"Alvarez Montajes Electricos S.a.",
    "wof:placetype":"venue"
},
  "geometry": {"coordinates":[-3.8007884026,37.7780189514],"type":"Point"}
}