{
  "type": "Feature",
  "properties": {
    "iso:country":"ES",
    "sg:address":"Carrer de Valencia, 508",
    "sg:city":"Barcelona",
    "sg:orig_category":"Fiesta: Art\u00cdculos De (al Por Menor)",
    "sg:phone":"+34 932 45 99 85",
    "sg:postcode":"08013",
    "sg:province":"Barcelona",
    "wof:name":"Fernandez Fernandez Carlos Javier",
    "wof:placetype":"venue"
},
  "geometry": {"coordinates":[2.1798739433,41.4049453735],"type":"Point"}
}