{
  "type": "Feature",
  "properties": {
    "iso:country":"ES",
    "sg:address":"Calle de Albal, 7",
    "sg:city":"Paiporta",
    "sg:orig_category":"Quincaller\u00cda (al Por Menor)",
    "sg:phone":"+34 963 97 66 15",
    "sg:postcode":"46200",
    "sg:province":"Valencia",
    "wof:name":"Ferreteria Garcia Simarro S.l.",
    "wof:placetype":"venue"
},
  "geometry": {"coordinates":[-0.4182384014,39.4296607971],"type":"Point"}
}