{
  "type": "Feature",
  "properties": {
    "iso:country":"ES",
    "sg:address":"Calle de Minerva, S/n",
    "sg:city":"Costa Del Silencio",
    "sg:orig_category":"Alquiler De Veh\u00cdculos: Turismos Y Utilitarios",
    "sg:phone":"+34 922 73 00 37",
    "sg:postcode":"38630",
    "sg:province":"Santa Cruz De Tenerife",
    "wof:name":"Peyrot Des Gachons  Patrick",
    "wof:placetype":"venue"
},
  "geometry": {"coordinates":[-16.6419887543,28.0123100281],"type":"Point"}
}