{
  "type": "Feature",
  "properties": {
    "iso:country":"ES",
    "sg:address":"Carrer de Castillo, 1",
    "sg:city":"Vilanova Cami",
    "sg:classifiers":[
        {
            "category":"Communications",
            "type":"Services"
        }
    ],
    "sg:phone":"+34 938 05 44 22",
    "sg:postcode":"08788",
    "sg:province":"Barcelona",
    "sg:tags":[
        "televisiones",
        "y",
        "radio"
    ],
    "wof:name":"Ajuntament De Vilanova Del Cami",
    "wof:placetype":"venue"
},
  "geometry": {"coordinates":[1.6341471672,41.5719451904],"type":"Point"}
}