{
  "type": "Feature",
  "properties": {
    "iso:country":"ES",
    "sg:address":"Calle de San Sebastian, 19",
    "sg:city":"Mijas",
    "sg:orig_category":"Molduras, Junquillos, Listones Y Molduras Perforadas",
    "sg:phone":"+34 952 48 57 22",
    "sg:postcode":"29650",
    "sg:province":"M\u00e1laga",
    "wof:name":"Boeta Santana Juan",
    "wof:placetype":"venue"
},
  "geometry": {"coordinates":[-4.6393880844,36.5952453613],"type":"Point"}
}