{
  "type": "Feature",
  "properties": {
    "iso:country":"ES",
    "sg:address":"Carrer de Nicaragua, 1",
    "sg:city":"Mollet Valles",
    "sg:orig_category":"Fabricaci\u00d3n, Importaci\u00d3n De L\u00c1mparas Y Bombillas",
    "sg:phone":"+34 935 70 29 69",
    "sg:postcode":"08100",
    "sg:province":"Barcelona",
    "wof:name":"Excelsor Illuminacio S.l.",
    "wof:placetype":"venue"
},
  "geometry": {"coordinates":[2.2051110268,41.5489883423],"type":"Point"}
}