{
  "type": "Feature",
  "properties": {
    "iso:country":"ES",
    "sg:address":"Bona Sort, S/n",
    "sg:city":"Prats Llu\u00e7anes",
    "sg:orig_category":"Reciclaje, Tratamiento De Pl\u00c1sticos",
    "sg:phone":"+34 938 56 04 95",
    "sg:postcode":"08513",
    "sg:province":"Barcelona",
    "wof:name":"Reciclajes El Llu\u00e7anes S.l.",
    "wof:placetype":"venue"
},
  "geometry": {"coordinates":[2.029225111,42.0056648254],"type":"Point"}
}