{
  "type": "Feature",
  "properties": {
    "iso:country":"ES",
    "sg:address":"Carrer de Arq.puig I Cadafalch, 10",
    "sg:city":"Terrassa",
    "sg:orig_category":"Electricidad: Equipos Industriales, Componentes (fabricaci\u00d3n)",
    "sg:phone":"+34 937 31 17 24",
    "sg:postcode":"08222",
    "sg:province":"Barcelona",
    "wof:name":"Comercial D'electricitat Industrial S.a.",
    "wof:placetype":"venue"
},
  "geometry": {"coordinates":[2.0193479061,41.5686035156],"type":"Point"}
}