{
  "type": "Feature",
  "properties": {
    "iso:country":"ES",
    "sg:address":"Ctra Novelda, 3",
    "sg:city":"Monovar",
    "sg:orig_category":"Zapatos: Material, Suministros, Accesorios (fabricaci\u00d3n, Al Por Mayor)",
    "sg:phone":"+34 965 47 15 99",
    "sg:postcode":"03640",
    "sg:province":"Alicante",
    "wof:name":"Vifama S.l.",
    "wof:placetype":"venue"
},
  "geometry": {"coordinates":[-0.8400509953,38.432926178],"type":"Point"}
}