{
  "type": "Feature",
  "properties": {
    "addr:full":"Calle de Gavilanes, 2 Madrid Madrid 28035",
    "addr:housenumber":"2",
    "addr:postcode":"28035",
    "addr:street":"Calle De Gavilanes",
    "iso:country":"ES",
    "sg:address":"Calle de Gavilanes, 2",
    "sg:city":"Madrid",
    "sg:orig_category":"Abogados",
    "sg:phone":"+34 913 16 99 39",
    "sg:postcode":"28035",
    "sg:province":"Madrid",
    "wof:name":"Jimenez Lopez Rafael",
    "wof:placetype":"venue"
},
  "geometry": {"coordinates":[-3.7387509346,40.477722168],"type":"Point"}
}