{
  "type": "Feature",
  "properties": {
    "iso:country":"ES",
    "sg:address":"Carrer de Cordova, 44",
    "sg:city":"Terrassa",
    "sg:orig_category":"Electricidad: Instaladores",
    "sg:phone":"+34 937 84 39 19",
    "sg:postcode":"08226",
    "sg:province":"Barcelona",
    "wof:name":"Talleres Dobleaislamiento S.l.",
    "wof:placetype":"venue"
},
  "geometry": {"coordinates":[2.0312120914,41.5686340332],"type":"Point"}
}