{
  "type": "Feature",
  "properties": {
    "addr:full":"Avgd Marques De Montroig, 147 Badalona Barcelona 08918",
    "addr:housenumber":"147",
    "addr:postcode":"08918",
    "iso:country":"ES",
    "sg:address":"Avgd Marques De Montroig, 147",
    "sg:city":"Badalona",
    "sg:orig_category":"Mec\u00c1nico Del Autom\u00d3vil",
    "sg:phone":"+34 933 83 66 30",
    "sg:postcode":"08918",
    "sg:province":"Barcelona",
    "wof:name":"Repar Jose S.l.",
    "wof:placetype":"venue"
},
  "geometry": {"coordinates":[2.2450649738,41.4503440857],"type":"Point"}
}