{
  "type": "Feature",
  "properties": {
    "addr:full":"Calle de Joaquin Ruano, 20 Linares Ja\u00e9n 23700",
    "addr:housenumber":"20",
    "addr:postcode":"23700",
    "addr:street":"Calle De Joaquin Ruano;Jae\u0301N",
    "iso:country":"ES",
    "sg:address":"Calle de Joaquin Ruano, 20",
    "sg:city":"Linares",
    "sg:orig_category":"Reposter\u00cdas",
    "sg:phone":"+34 953 69 35 25",
    "sg:postcode":"23700",
    "sg:province":"Ja\u00e9n",
    "wof:name":"Medina Sanchez Cristobal",
    "wof:placetype":"venue"
},
  "geometry": {"coordinates":[-3.6335949898,38.0954589844],"type":"Point"}
}