{
  "type": "Feature",
  "properties": {
    "iso:country":"ES",
    "sg:address":"Avda Mejico, S/n",
    "sg:city":"Huelva",
    "sg:orig_category":"Electrodom\u00c9sticos (al Por Menor)",
    "sg:phone":"+34 959 35 90 22",
    "sg:postcode":"21001",
    "sg:province":"Huelva",
    "wof:name":"Singer Distribucion S.a.",
    "wof:placetype":"venue"
},
  "geometry": {"coordinates":[-6.9495940208,37.256313324],"type":"Point"}
}