{
  "type": "Feature",
  "properties": {
    "addr:full":"Calle de Caba\u00d1ales, 26 Zamora Zamora 49027",
    "addr:housenumber":"26",
    "addr:postcode":"49027",
    "addr:street":"Calle De Caban\u0303Ales",
    "iso:country":"ES",
    "sg:address":"Calle de Caba\u00d1ales, 26",
    "sg:city":"Zamora",
    "sg:orig_category":"Carnicer\u00cdas, Carnicer\u00cdas",
    "sg:phone":"+34 980 53 30 18",
    "sg:postcode":"49027",
    "sg:province":"Zamora",
    "wof:name":"Gallego Alonso Porfirio",
    "wof:placetype":"venue"
},
  "geometry": {"coordinates":[-5.7472486496,41.4968299866],"type":"Point"}
}