{
  "type": "Feature",
  "properties": {
    "iso:country":"ES",
    "sg:address":"Calle de Rio Cea, 7",
    "sg:city":"Avila",
    "sg:orig_category":"Promotores Constructores",
    "sg:phone":"+34 920 21 57 00",
    "sg:postcode":"05004",
    "sg:province":"\u00c1vila",
    "wof:name":"Firmes Ecologicos Soltec S.a.",
    "wof:placetype":"venue"
},
  "geometry": {"coordinates":[-4.6840720177,40.6693496704],"type":"Point"}
}