{
  "type": "Feature",
  "properties": {
    "addr:full":"Carrer de Navarra, 54 Granollers Barcelona 08401",
    "addr:housenumber":"54",
    "addr:postcode":"08401",
    "addr:street":"Carrer De Navarra",
    "iso:country":"ES",
    "sg:address":"Carrer de Navarra, 54",
    "sg:city":"Granollers",
    "sg:orig_category":"Ense\u00d1anza: Peluquer\u00cda Est\u00c9tica",
    "sg:phone":"+34 938 79 69 86",
    "sg:postcode":"08401",
    "sg:province":"Barcelona",
    "wof:name":"Centre De Formacio Profesional De L'imatge S.cv.p.",
    "wof:placetype":"venue"
},
  "geometry": {"coordinates":[2.2846260071,41.6041183472],"type":"Point"}
}