{
  "type": "Feature",
  "properties": {
    "addr:full":"Calle de Espeluy, 28 Jaen Ja\u00e9n 23009",
    "addr:housenumber":"28;jae\u0301n",
    "addr:postcode":"23009",
    "addr:street":"Calle De Espeluy",
    "iso:country":"ES",
    "sg:address":"Calle de Espeluy, 28",
    "sg:city":"Jaen",
    "sg:orig_category":"Material Y Herramientas Agr\u00cdcolas",
    "sg:phone":"+34 953 28 14 99",
    "sg:postcode":"23009",
    "sg:province":"Ja\u00e9n",
    "sg:website":"www.agroforestaljaen.com",
    "wof:name":"Agroforestal Jaen S.l.",
    "wof:placetype":"venue"
},
  "geometry": {"coordinates":[-3.782538414,37.7983932495],"type":"Point"}
}