{
  "type": "Feature",
  "properties": {
    "iso:country":"ES",
    "sg:address":"Rua Greco (el), 10",
    "sg:city":"Ourense",
    "sg:orig_category":"Ropa De Trabajo Y Profesionales (fabricaci\u00d3n, Al Por Mayor)",
    "sg:phone":"+34 988 22 30 05",
    "sg:postcode":"32002",
    "sg:province":"Ourense",
    "wof:name":"Igdos Orense S.l.",
    "wof:placetype":"venue"
},
  "geometry": {"coordinates":[-7.8725337982,42.3420410156],"type":"Point"}
}