{
  "type": "Feature",
  "properties": {
    "iso:country":"ES",
    "sg:address":"Calle de Ramon Gallud, 22",
    "sg:city":"Torrevieja",
    "sg:orig_category":"Peluquer\u00cdas, Peluquer\u00cda Mixta",
    "sg:phone":"+34 965 70 33 30",
    "sg:postcode":"03180",
    "sg:province":"Alicante",
    "wof:name":"Sanchez Marcos Jose Antonio",
    "wof:placetype":"venue"
},
  "geometry": {"coordinates":[-0.6836900115,37.9770774841],"type":"Point"}
}