{
  "type": "Feature",
  "properties": {
    "iso:country":"ES",
    "sg:address":"Calle de San Torcuato, 2",
    "sg:city":"Zamora",
    "sg:orig_category":"Trajes Y Adornos De Boda (confecci\u00d3n, Al Por Menor)",
    "sg:phone":"+34 980 53 52 15",
    "sg:postcode":"49004",
    "sg:province":"Zamora",
    "wof:name":"Zamorano C.b",
    "wof:placetype":"venue"
},
  "geometry": {"coordinates":[-5.745028019,41.5046615601],"type":"Point"}
}