{
  "type": "Feature",
  "properties": {
    "iso:country":"ES",
    "sg:address":"Rua Dos Pereiros(vigovidin), S/n",
    "sg:city":"Culleredo",
    "sg:orig_category":"Asociaciones, Organismos Culturales Y Socioeducativos",
    "sg:phone":"+34 981 66 07 03",
    "sg:postcode":"15180",
    "sg:province":"La Coru\u00f1a",
    "wof:name":"Centro Escolar Y Social San Julian De Almeiras",
    "wof:placetype":"venue"
},
  "geometry": {"coordinates":[-8.3642091751,43.304523468],"type":"Point"}
}