{
  "type": "Feature",
  "properties": {
    "iso:country":"ES",
    "sg:address":"A Poligono Landaben, S/n",
    "sg:city":"Iru\u00f1a",
    "sg:orig_category":"Electricidad (montaje, Ensamblaje De Componentes)",
    "sg:phone":"+34 948 28 15 00",
    "sg:postcode":"31012",
    "sg:province":"Navarra",
    "wof:name":"Hierros Y Suministros Landaben S.l.",
    "wof:placetype":"venue"
},
  "geometry": {"coordinates":[-1.6437540054,42.81275177],"type":"Point"}
}