{
  "type": "Feature",
  "properties": {
    "iso:country":"ES",
    "sg:address":"Calle de Antonino Vera, 51",
    "sg:city":"Elda",
    "sg:orig_category":"Tintorer\u00cdas, Limpieza En Seco",
    "sg:phone":"+34 965 39 94 53",
    "sg:postcode":"03600",
    "sg:province":"Alicante",
    "wof:name":"Servicio De Lavanderia Pasmin S.l.",
    "wof:placetype":"venue"
},
  "geometry": {"coordinates":[-0.7923539877,38.4786682129],"type":"Point"}
}