{
  "type": "Feature",
  "properties": {
    "iso:country":"ES",
    "sg:address":"Pl Generalitat, 20",
    "sg:city":"S. Boi Llobregat",
    "sg:orig_category":"Entrega Y Recogida (servicios)",
    "sg:phone":"+34 936 52 56 08",
    "sg:postcode":"08830",
    "sg:province":"Barcelona",
    "wof:name":"Puzles Y Peluches Licenciados Sl",
    "wof:placetype":"venue"
},
  "geometry": {"coordinates":[2.0321490765,41.3486671448],"type":"Point"}
}