{
  "type": "Feature",
  "properties": {
    "iso:country":"ES",
    "sg:address":"Plaz Pintor Inocencio Medina Vera, 5",
    "sg:city":"Vista Alegre",
    "sg:orig_category":"Ense\u00d1anza, Formaci\u00d3n Profesional: Aprendizaje",
    "sg:phone":"+34 968 23 08 58",
    "sg:postcode":"30007",
    "sg:province":"Murcia",
    "wof:name":"Telefonica Data Espa\u00f1a S.a.",
    "wof:placetype":"venue"
},
  "geometry": {"coordinates":[-1.1142389774,37.9970092773],"type":"Point"}
}