{
  "type": "Feature",
  "properties": {
    "iso:country":"ES",
    "sg:address":"Cmno Ancho, S/n",
    "sg:city":"Puebla Almoradiel",
    "sg:orig_category":"Productores Recolectores, Venta Directa De Vinos",
    "sg:phone":"+34 925 20 56 58",
    "sg:postcode":"45840",
    "sg:province":"Toledo",
    "wof:name":"Guillermo Mendieta Juan Antonio",
    "wof:placetype":"venue"
},
  "geometry": {"coordinates":[-3.1186289787,39.5983505249],"type":"Point"}
}