{
  "type": "Feature",
  "properties": {
    "iso:country":"ES",
    "sg:address":"Carrer de Doctor Reig, 31",
    "sg:city":"Viladecans",
    "sg:orig_category":"Flores Y Plantas Naturales (al Por Mayor)",
    "sg:phone":"+34 936 37 68 24",
    "sg:postcode":"08840",
    "sg:province":"Barcelona",
    "wof:name":"Mundijofra S.l.",
    "wof:placetype":"venue"
},
  "geometry": {"coordinates":[2.0152659416,41.3172035217],"type":"Point"}
}