{
  "type": "Feature",
  "properties": {
    "addr:full":"Pase Buenos Aires De, 23 Huelva Huelva 21002",
    "addr:postcode":"21002",
    "iso:country":"ES",
    "sg:address":"Pase Buenos Aires De, 23",
    "sg:city":"Huelva",
    "sg:orig_category":"Internados & Ense\u00d1anza Privada",
    "sg:phone":"+34 959 24 29 99",
    "sg:postcode":"21002",
    "sg:province":"Huelva",
    "wof:name":"Compa\u00d1ia Hijas De La Caridad De S Vicente De Paul Prov De Sevilla Cdad Casa S Vicente De Paul Sevill",
    "wof:placetype":"venue"
},
  "geometry": {"coordinates":[-6.9511852264,37.2618293762],"type":"Point"}
}