{
  "type": "Feature",
  "properties": {
    "iso:country":"ES",
    "sg:address":"Calle de Hernan Cortes, S/n",
    "sg:city":"Motilla Palancar",
    "sg:orig_category":"\u00d3ptica: Instrumentos (fabricaci\u00d3n)",
    "sg:phone":"+34 969 33 21 87",
    "sg:postcode":"16200",
    "sg:province":"Cuenca",
    "wof:name":"Optica Croma S.l.",
    "wof:placetype":"venue"
},
  "geometry": {"coordinates":[-1.90832901,39.5618591309],"type":"Point"}
}