{
  "type": "Feature",
  "properties": {
    "iso:country":"ES",
    "sg:address":"Pase General Davila, 38",
    "sg:city":"Santander",
    "sg:orig_category":"Mantenimiento Industrial",
    "sg:phone":"+34 942 27 04 03",
    "sg:postcode":"39005",
    "sg:province":"Cantabria",
    "wof:name":"Clece S.a.",
    "wof:placetype":"venue"
},
  "geometry": {"coordinates":[-3.7930810452,43.468624115],"type":"Point"}
}