{
  "type": "Feature",
  "properties": {
    "iso:country":"ES",
    "sg:address":"Carr Prat De La Riba, 151",
    "sg:city":"Juneda",
    "sg:orig_category":"Acondicionamiento, Mantenimiento De Jardines Y Parques",
    "sg:phone":"+34 973 15 01 72",
    "sg:postcode":"25430",
    "sg:province":"Lleida",
    "wof:name":"Roig Torrent Joana Magdalena",
    "wof:placetype":"venue"
},
  "geometry": {"coordinates":[0.8235800266,41.5466690063],"type":"Point"}
}