{
  "type": "Feature",
  "properties": {
    "iso:country":"ES",
    "sg:address":"Av Bartomeu De Rosello, 11",
    "sg:city":"Eivissa",
    "sg:orig_category":"Restaurantes",
    "sg:phone":"+34 971 31 42 70",
    "sg:postcode":"07800",
    "sg:province":"Islas Baleares",
    "wof:name":"Roig Planells Vicente",
    "wof:placetype":"venue"
},
  "geometry": {"coordinates":[1.4329459667,38.9104499817],"type":"Point"}
}