{
  "type": "Feature",
  "properties": {
    "iso:country":"ES",
    "sg:address":"Calle de Feijoo, 89",
    "sg:city":"Gijon",
    "sg:orig_category":"Ebanister\u00cda",
    "sg:phone":"+34 985 33 20 20",
    "sg:postcode":"33204",
    "sg:province":"Asturias",
    "wof:name":"Puerto Basante Alfredo",
    "wof:placetype":"venue"
},
  "geometry": {"coordinates":[-5.6481070518,43.5318527222],"type":"Point"}
}