{
  "type": "Feature",
  "properties": {
    "addr:full":"Carretera Girona-angles, Km. 0112,0 Bescano Girona 17162",
    "addr:postcode":"17162",
    "addr:street":"Carretera Girona-Angles Km. 0112,0 Bescano",
    "iso:country":"ES",
    "sg:address":"Carretera Girona-angles, Km. 0112,0",
    "sg:city":"Bescano",
    "sg:orig_category":"Aguas (distribuci\u00d3n, Servicios)",
    "sg:phone":"+34 972 44 27 70",
    "sg:postcode":"17162",
    "sg:province":"Girona",
    "wof:name":"Isolux Wat S.a.",
    "wof:placetype":"venue"
},
  "geometry": {"coordinates":[2.7542419434,41.9702148438],"type":"Point"}
}