{
  "type": "Feature",
  "properties": {
    "iso:country":"ES",
    "sg:address":"Calle de Novia Salcedo, 21",
    "sg:city":"Bilbao",
    "sg:orig_category":"Frutas, Legumbres Frescas Y Tempranas (al Por Menor)",
    "sg:phone":"+34 944 27 18 29",
    "sg:postcode":"48012",
    "sg:province":"Vizcaya",
    "wof:name":"Juan Carlos Saenz Jordan",
    "wof:placetype":"venue"
},
  "geometry": {"coordinates":[-2.9495670795,43.2569160461],"type":"Point"}
}