{
  "type": "Feature",
  "properties": {
    "iso:country":"ES",
    "sg:address":"Elkano Kalea, 19",
    "sg:city":"Hernani",
    "sg:orig_category":"Alimentaci\u00d3n General (al Por Menor)",
    "sg:phone":"+34 943 33 01 84",
    "sg:postcode":"20120",
    "sg:province":"Guip\u00f9zcoa",
    "sg:website":"www.eroski.es",
    "wof:name":"Eroski Sociedad Cooperativa",
    "wof:placetype":"venue"
},
  "geometry": {"coordinates":[-1.9769140482,43.266582489],"type":"Point"}
}