{
  "type": "Feature",
  "properties": {
    "addr:full":"Calle de Tintes, 15 Cuenca Cuenca 16001",
    "addr:housenumber":"15",
    "addr:postcode":"16001",
    "addr:street":"Calle De Tintes",
    "iso:country":"ES",
    "sg:address":"Calle de Tintes, 15",
    "sg:city":"Cuenca",
    "sg:orig_category":"Funcionario",
    "sg:phone":"+34 969 23 44 59",
    "sg:postcode":"16001",
    "sg:province":"Cuenca",
    "wof:name":"Colegio Oficial De Peritos E Ingenieros Tecnicos Industriales",
    "wof:placetype":"venue"
},
  "geometry": {"coordinates":[-2.1332418919,40.0739326477],"type":"Point"}
}