{
  "type": "Feature",
  "properties": {
    "iso:country":"ES",
    "sg:address":"Avda Kansas City, 23",
    "sg:city":"Sevilla",
    "sg:orig_category":"Estudios, Instalaci\u00d3n De Climatizaci\u00d3n",
    "sg:phone":"+34 954 54 03 07",
    "sg:postcode":"41007",
    "sg:province":"Sevilla",
    "wof:name":"Sistemas Integrales Climalar",
    "wof:placetype":"venue"
},
  "geometry": {"coordinates":[-5.974170208,37.3895797729],"type":"Point"}
}