{
  "type": "Feature",
  "properties": {
    "addr:full":"Carrer de Modern, 12 Hospitalet Llobregat Barcelona 08902",
    "addr:housenumber":"12",
    "addr:postcode":"08902",
    "addr:street":"Carrer De Modern",
    "iso:country":"ES",
    "sg:address":"Carrer de Modern, 12",
    "sg:city":"Hospitalet Llobregat",
    "sg:orig_category":"Agencias Y Asesores De Publicidad",
    "sg:phone":"+34 934 22 50 80",
    "sg:postcode":"08902",
    "sg:province":"Barcelona",
    "wof:name":"Sagala Molist Josep Maria",
    "wof:placetype":"venue"
},
  "geometry": {"coordinates":[2.1279408932,41.3627204895],"type":"Point"}
}