{
  "type": "Feature",
  "properties": {
    "iso:country":"ES",
    "sg:address":"Avda Virgen Del Carmen, S/n",
    "sg:city":"Algeciras",
    "sg:orig_category":"Ense\u00d1anza, Formaci\u00d3n Profesional: Aprendizaje",
    "sg:phone":"+34 956 58 73 99",
    "sg:postcode":"11204",
    "sg:province":"C\u00e1diz",
    "wof:name":"Empresa Municipal De Aguas De Algeciras",
    "wof:placetype":"venue"
},
  "geometry": {"coordinates":[-5.453663826,36.1419258118],"type":"Point"}
}