{
  "type": "Feature",
  "properties": {
    "iso:country":"ES",
    "sg:address":"Calle de Princesa Teseida, 56",
    "sg:city":"Cruce De Arinaga",
    "sg:orig_category":"Cerrajer\u00cda, Ferrallista",
    "sg:phone":"+34 928 18 09 04",
    "sg:postcode":"35118",
    "sg:province":"Las Palmas",
    "wof:name":"Aluminios Diaz Lorenzo",
    "wof:placetype":"venue"
},
  "geometry": {"coordinates":[-15.4290733337,27.8753433228],"type":"Point"}
}