{
  "type": "Feature",
  "properties": {
    "iso:country":"ES",
    "sg:address":"Madera, S/n",
    "sg:city":"Carranque",
    "sg:orig_category":"Cerrajer\u00cda, Ferrallista",
    "sg:phone":"+34 925 54 43 81",
    "sg:postcode":"45216",
    "sg:province":"Toledo",
    "wof:name":"Electromecanicas Femasa S.l.",
    "wof:placetype":"venue"
},
  "geometry": {"coordinates":[-3.8871788979,40.1836738586],"type":"Point"}
}