{
  "type": "Feature",
  "properties": {
    "addr:full":"Calle de Cincel (del), 14 Fuenlabrada Madrid 28947",
    "addr:housenumber":"14",
    "addr:postcode":"28947",
    "addr:street":"Calle De Cincel Del",
    "iso:country":"ES",
    "sg:address":"Calle de Cincel (del), 14",
    "sg:city":"Fuenlabrada",
    "sg:orig_category":"Electricidad, Electr\u00d3nica: Material Y Suministros (al Por Mayor)",
    "sg:phone":"+34 916 42 02 68",
    "sg:postcode":"28947",
    "sg:province":"Madrid",
    "wof:name":"Lineas Tc S.a.",
    "wof:placetype":"venue"
},
  "geometry": {"coordinates":[-3.7598974705,40.2718811035],"type":"Point"}
}