{
  "type": "Feature",
  "properties": {
    "iso:country":"ES",
    "sg:address":"Carrer de Cartella, 175",
    "sg:city":"Barcelona",
    "sg:orig_category":"Asociaciones Humanitarias, De Cooperaci\u00d3n, De Acci\u00d3n Social",
    "sg:phone":"+34 934 20 66 67",
    "sg:postcode":"08031",
    "sg:province":"Barcelona",
    "wof:name":"Taller Escuela Para Subnormales Grupdem",
    "wof:placetype":"venue"
},
  "geometry": {"coordinates":[2.1646690369,41.4303321838],"type":"Point"}
}