{
  "type": "Feature",
  "properties": {
    "iso:country":"ES",
    "sg:address":"Calle de Santa Matilde, 4",
    "sg:city":"Madrid",
    "sg:orig_category":"Energ\u00cda Solar Y Nuevas Energ\u00cdas (equipo, Estudios)",
    "sg:phone":"+34 914 59 43 82",
    "sg:postcode":"28039",
    "sg:province":"Madrid",
    "sg:website":"www.tausolar.com",
    "wof:name":"Tau Consultora Ambiental S.l.",
    "wof:placetype":"venue"
},
  "geometry": {"coordinates":[-3.707983017,40.4497871399],"type":"Point"}
}