{
  "type": "Feature",
  "properties": {
    "iso:country":"ES",
    "sg:address":"Calle de Hermanos Herreros, 2",
    "sg:city":"San Carlos Del Valle",
    "sg:orig_category":"Fabricaci\u00d3n De Quesos",
    "sg:phone":"+34 926 63 02 45",
    "sg:postcode":"13247",
    "sg:province":"Ciudad Real",
    "wof:name":"Palacios Pacheco Amalio",
    "wof:placetype":"venue"
},
  "geometry": {"coordinates":[-3.2436234951,38.845199585],"type":"Point"}
}