{
  "type": "Feature",
  "properties": {
    "addr:full":"Rbla General Franco, 114 Santa Cruz De Tenerife Santa Cruz De Tenerife 38001",
    "addr:housenumber":"114",
    "addr:postcode":"38001",
    "addr:street":"Rbla General Franco",
    "iso:country":"ES",
    "sg:address":"Rbla General Franco, 114",
    "sg:city":"Santa Cruz De Tenerife",
    "sg:orig_category":"Inform\u00c1tica, Ofim\u00c1tica (estudios, Asesor\u00cda, Ingenier\u00cda, Formaci\u00d3n)",
    "sg:phone":"+34 922 27 22 80",
    "sg:postcode":"38001",
    "sg:province":"Santa Cruz De Tenerife",
    "wof:name":"Magna Computer S.l.",
    "wof:placetype":"venue"
},
  "geometry": {"coordinates":[-16.2530841827,28.4738445282],"type":"Point"}
}