{
  "type": "Feature",
  "properties": {
    "iso:country":"ES",
    "sg:address":"Avda Granja (la), 3",
    "sg:city":"Jerez De La Frontera",
    "sg:orig_category":"Electricidad: Instaladores",
    "sg:phone":"+34 956 18 38 45",
    "sg:postcode":"11405",
    "sg:province":"C\u00e1diz",
    "wof:name":"Instalaciones Y Montajes Electricos Y Saneamiento S.a.",
    "wof:placetype":"venue"
},
  "geometry": {"coordinates":[-6.0998120308,36.7029647827],"type":"Point"}
}