{
  "type": "Feature",
  "properties": {
    "iso:country":"ES",
    "sg:address":"Calle de Jalon, 2",
    "sg:city":"Majadahonda",
    "sg:orig_category":"Entrega Y Recogida (servicios)",
    "sg:phone":"+34 916 38 53 05",
    "sg:postcode":"28220",
    "sg:province":"Madrid",
    "wof:name":"Consorcio De Los Quesos Tradicionales De Espa\u00f1a S.a.",
    "wof:placetype":"venue"
},
  "geometry": {"coordinates":[-3.867016077,40.4790077209],"type":"Point"}
}