{
  "type": "Feature",
  "properties": {
    "iso:country":"ES",
    "sg:address":"Calle de Cooperativa, 23",
    "sg:city":"Horcajo Santiago",
    "sg:orig_category":"Productores Recolectores, Venta Directa De Vinos",
    "sg:phone":"+34 969 12 70 97",
    "sg:postcode":"16410",
    "sg:province":"Cuenca",
    "wof:name":"Cooperativa Del Campo El Vitor",
    "wof:placetype":"venue"
},
  "geometry": {"coordinates":[-3.0015203953,39.848400116],"type":"Point"}
}