{
  "type": "Feature",
  "properties": {
    "addr:full":"Plaz Arriba, 6 Burgohondo \u00c1vila 05113",
    "addr:housenumber":"6",
    "addr:postcode":"05113",
    "addr:street":"Plaz Arriba;A\u0301Vila",
    "iso:country":"ES",
    "sg:address":"Plaz Arriba, 6",
    "sg:city":"Burgohondo",
    "sg:orig_category":"Carnicer\u00cdas, Carnicer\u00cdas",
    "sg:phone":"+34 920 28 31 98",
    "sg:postcode":"05113",
    "sg:province":"\u00c1vila",
    "wof:name":"Garcia Rollon Francisco",
    "wof:placetype":"venue"
},
  "geometry": {"coordinates":[-4.7795147896,40.3836555481],"type":"Point"}
}