{
  "type": "Feature",
  "properties": {
    "addr:full":"Calle de Matematico Pedrayes, 2 Oviedo Asturias 33004",
    "addr:housenumber":"2",
    "addr:postcode":"33004",
    "addr:street":"Calle De Matematico Pedrayes",
    "iso:country":"ES",
    "sg:address":"Calle de Matematico Pedrayes, 2",
    "sg:city":"Oviedo",
    "sg:orig_category":"Abogados",
    "sg:phone":"+34 985 21 44 40",
    "sg:postcode":"33004",
    "sg:province":"Asturias",
    "wof:name":"Veritas Abogados Cb",
    "wof:placetype":"venue"
},
  "geometry": {"coordinates":[-5.8555598259,43.36328125],"type":"Point"}
}