{
  "type": "Feature",
  "properties": {
    "iso:country":"ES",
    "sg:address":"Avda Baron De Carcer, 21",
    "sg:city":"Valencia",
    "sg:classifiers":[
        {
            "category":"Personal",
            "subcategory":"Barber",
            "type":"Services"
        }
    ],
    "sg:phone":"+34 963 52 99 36",
    "sg:postcode":"46001",
    "sg:province":"Valencia",
    "sg:tags":[
        "caballeros",
        "de",
        "peluqueros"
    ],
    "wof:name":"Gimenez De La Rosa Horacio",
    "wof:placetype":"venue"
},
  "geometry": {"coordinates":[-0.3796440065,39.472492218],"type":"Point"}
}