{
  "type": "Feature",
  "properties": {
    "iso:country":"ES",
    "sg:address":"Avda Carlos De Haya, 60",
    "sg:city":"Malaga",
    "sg:orig_category":"Supermercados Y Hipermercados",
    "sg:phone":"+34 952 30 86 62",
    "sg:postcode":"29010",
    "sg:province":"M\u00e1laga",
    "wof:name":"Dinosol Supermercados S.l.",
    "wof:placetype":"venue"
},
  "geometry": {"coordinates":[-4.4461450577,36.7221069336],"type":"Point"}
}