{
  "type": "Feature",
  "properties": {
    "iso:country":"ES",
    "sg:address":"Calle de Jose Antonio, 8",
    "sg:city":"Gallegos De Arga\u00e7an",
    "sg:orig_category":"T\u00c9cnicos Veterinarios",
    "sg:phone":"+34 923 47 70 32",
    "sg:postcode":"37484",
    "sg:province":"Salamanca",
    "wof:name":"Diego Hernandez Jose Benito De",
    "wof:placetype":"venue"
},
  "geometry": {"coordinates":[-6.7025880814,40.6298751831],"type":"Point"}
}