{
  "type": "Feature",
  "properties": {
    "addr:full":"Luga Era Del Cardon, 2 Sardina Las Palmas 35110",
    "addr:housenumber":"2",
    "addr:postcode":"35110",
    "addr:street":"Sardina Las",
    "iso:country":"ES",
    "sg:address":"Luga Era Del Cardon, 2",
    "sg:city":"Sardina",
    "sg:orig_category":"Alimentaci\u00d3n General (al Por Mayor)",
    "sg:phone":"+34 928 17 21 72",
    "sg:postcode":"35110",
    "sg:province":"Las Palmas",
    "wof:name":"Martel Perdomo Luis",
    "wof:placetype":"venue"
},
  "geometry": {"coordinates":[-15.4485340118,27.8392906189],"type":"Point"}
}