{
  "type": "Feature",
  "properties": {
    "addr:full":"Calle de Korreo Kalea, 18 Tolosa Guip\u00f9zcoa 20400",
    "addr:housenumber":"18",
    "addr:postcode":"20400",
    "addr:street":"Calle De Korreo Kalea;Guipu\u0300Zcoa",
    "iso:country":"ES",
    "sg:address":"Calle de Korreo Kalea, 18",
    "sg:city":"Tolosa",
    "sg:orig_category":"Centros Comerciales Y Grandes Tiendas",
    "sg:phone":"+34 943 67 54 85",
    "sg:postcode":"20400",
    "sg:province":"Guip\u00f9zcoa",
    "wof:name":"Distribucciones Europariak S.l.",
    "wof:placetype":"venue"
},
  "geometry": {"coordinates":[-2.0731260777,43.1379241943],"type":"Point"}
}