{
  "type": "Feature",
  "properties": {
    "addr:full":"Telleriarte Diseminado, 49 Telleriarte Guip\u00f9zcoa 20220",
    "addr:housenumber":"49",
    "addr:postcode":"20220",
    "addr:street":"Telleriarte Diseminado;Guipu\u0300Zcoa",
    "iso:country":"ES",
    "sg:address":"Telleriarte Diseminado, 49",
    "sg:city":"Telleriarte",
    "sg:orig_category":"Reciclaje, Desguace De Veh\u00cdculos",
    "sg:phone":"+34 943 73 36 26",
    "sg:postcode":"20220",
    "sg:province":"Guip\u00f9zcoa",
    "wof:name":"Yun Bereciartua Juan Jose",
    "wof:placetype":"venue"
},
  "geometry": {"coordinates":[-2.3463411331,43.028137207],"type":"Point"}
}