{
  "type": "Feature",
  "properties": {
    "iso:country":"ES",
    "sg:address":"Calle de Cincho, 27",
    "sg:city":"Santovenia Pisuerga",
    "sg:orig_category":"Muebles",
    "sg:phone":"+34 983 26 23 54",
    "sg:postcode":"47155",
    "sg:province":"Valladolid",
    "wof:name":"Ba\u00f1os Del Duero 2000 S.l.",
    "wof:placetype":"venue"
},
  "geometry": {"coordinates":[-4.6879892349,41.6882209778],"type":"Point"}
}