{
  "type": "Feature",
  "properties": {
    "addr:full":"Rua Monte Penama, 2 Ourense Ourense 32005",
    "addr:housenumber":"2",
    "addr:postcode":"32005",
    "addr:street":"Rua Monte Penama",
    "iso:country":"ES",
    "sg:address":"Rua Monte Penama, 2",
    "sg:city":"Ourense",
    "sg:orig_category":"Molduras, Junquillos, Listones Y Molduras Perforadas",
    "sg:phone":"+34 988 22 30 82",
    "sg:postcode":"32005",
    "sg:province":"Ourense",
    "wof:name":"Mendez Del Campo Jose Angel",
    "wof:placetype":"venue"
},
  "geometry": {"coordinates":[-7.8592557907,42.3346786499],"type":"Point"}
}