{
  "type": "Feature",
  "properties": {
    "iso:country":"ES",
    "sg:address":"Rua Alameda (da), 2",
    "sg:city":"Carballi\u00f1o",
    "sg:orig_category":"Bisuter\u00cda, Joyer\u00cda, Relojer\u00cda (al Por Menor)",
    "sg:phone":"+34 988 27 41 63",
    "sg:postcode":"32500",
    "sg:province":"Ourense",
    "wof:name":"Dominguez Fernandez Monica",
    "wof:placetype":"venue"
},
  "geometry": {"coordinates":[-8.0778837204,42.4304733276],"type":"Point"}
}