{
  "type": "Feature",
  "properties": {
    "iso:country":"ES",
    "sg:address":"Calle de Antonio Toscano Palacios, S/n",
    "sg:city":"Posadas",
    "sg:orig_category":"Heladeros",
    "sg:phone":"+34 957 63 22 25",
    "sg:postcode":"14730",
    "sg:province":"C\u00f3rdoba",
    "wof:name":"Candela Alcaraz Alberto",
    "wof:placetype":"venue"
},
  "geometry": {"coordinates":[-5.1061062813,37.80260849],"type":"Point"}
}