{
  "type": "Feature",
  "properties": {
    "iso:country":"ES",
    "sg:address":"Carrer de Juan De La Cierva, 16",
    "sg:city":"Castelldefels",
    "sg:orig_category":"Bazares, Art\u00cdculos De Limpieza Y De Cocina (al Por Menor)",
    "sg:phone":"+34 936 36 12 62",
    "sg:postcode":"08860",
    "sg:province":"Barcelona",
    "wof:name":"Abellan Vega Helena",
    "wof:placetype":"venue"
},
  "geometry": {"coordinates":[1.982718,41.28434],"type":"Point"}
}