{
  "type": "Feature",
  "properties": {
    "iso:country":"ES",
    "sg:address":"Cra. Corbera, Km. 0000,4",
    "sg:city":"La Palma De Cervello",
    "sg:orig_category":"Artes Gr\u00c1ficas, Artes Pl\u00c1sticas: Material Y Suministros (al Por Menor)",
    "sg:phone":"+34 936 72 09 44",
    "sg:postcode":"08756",
    "sg:province":"Barcelona",
    "sg:website":"www.becagrafic.com",
    "wof:name":"Beca Grafic S. A.",
    "wof:placetype":"venue"
},
  "geometry": {"coordinates":[1.9652750492,41.4137763977],"type":"Point"}
}