{
  "type": "Feature",
  "properties": {
    "iso:country":"ES",
    "sg:address":"Pl Del Mar, S/n",
    "sg:city":"Barcelona",
    "sg:orig_category":"Asociaciones Y Clubs Deportivos",
    "sg:phone":"+34 932 21 88 44",
    "sg:postcode":"08005",
    "sg:province":"Barcelona",
    "wof:name":"Club Natacio Atletic-barceloneta",
    "wof:placetype":"venue"
},
  "geometry": {"coordinates":[2.1883020401,41.3739814758],"type":"Point"}
}