{
  "type": "Feature",
  "properties": {
    "iso:country":"ES",
    "sg:address":"Barr Herves, 5",
    "sg:city":"Herves",
    "sg:orig_category":"Serrer\u00cdas De Madera",
    "sg:phone":"+34 986 54 81 72",
    "sg:postcode":"36675",
    "sg:province":"Pontevedra",
    "wof:name":"Casal Guerra Ramiro",
    "wof:placetype":"venue"
},
  "geometry": {"coordinates":[-8.5886192322,42.62682724],"type":"Point"}
}