{
  "type": "Feature",
  "properties": {
    "iso:country":"ES",
    "sg:address":"Las Cuevas, S/n",
    "sg:city":"Quintana Redonda",
    "sg:orig_category":"Charcuter\u00cdas (al Por Mayor)",
    "sg:phone":"+34 975 30 80 60",
    "sg:postcode":"42291",
    "sg:province":"Soria",
    "wof:name":"Embutidos Garcia Recio S.l.",
    "wof:placetype":"venue"
},
  "geometry": {"coordinates":[-2.6153988838,41.6408348083],"type":"Point"}
}