{
  "type": "Feature",
  "properties": {
    "iso:country":"ES",
    "sg:address":"Carrer de Mexic, 62",
    "sg:city":"Mataro",
    "sg:orig_category":"Molduras, Junquillos, Listones Y Molduras Perforadas",
    "sg:phone":"+34 937 90 53 94",
    "sg:postcode":"08304",
    "sg:province":"Barcelona",
    "wof:name":"Alvarez Alvarez Eduardo",
    "wof:placetype":"venue"
},
  "geometry": {"coordinates":[2.4493134022,41.5500450134],"type":"Point"}
}