{
  "type": "Feature",
  "properties": {
    "addr:full":"Rua Luis Antonio Mestre, 75 Grove Pontevedra 36980",
    "addr:housenumber":"75",
    "addr:postcode":"36980",
    "addr:street":"Rua Luis Antonio Mestre;Grove Pontevedra",
    "iso:country":"ES",
    "sg:address":"Rua Luis Antonio Mestre, 75",
    "sg:city":"Grove",
    "sg:orig_category":"Cristaler\u00cdas",
    "sg:phone":"+34 986 73 30 37",
    "sg:postcode":"36980",
    "sg:province":"Pontevedra",
    "wof:name":"Cristaleria Lucar S.l.",
    "wof:placetype":"venue"
},
  "geometry": {"coordinates":[-8.8658390045,42.4876899719],"type":"Point"}
}