{
  "type": "Feature",
  "properties": {
    "addr:full":"Carrer de Mila I Fontanals, 2 Reus Tarragona 43205",
    "addr:housenumber":"2",
    "addr:postcode":"43205",
    "addr:street":"Carrer De Mila I Fontanals",
    "iso:country":"ES",
    "sg:address":"Carrer de Mila I Fontanals, 2",
    "sg:city":"Reus",
    "sg:orig_category":"Farmacias",
    "sg:phone":"+34 977 75 47 75",
    "sg:postcode":"43205",
    "sg:province":"Tarragona",
    "wof:name":"Borras Cabaces Blanca",
    "wof:placetype":"venue"
},
  "geometry": {"coordinates":[1.1130720377,41.1419754028],"type":"Point"}
}