{
  "type": "Feature",
  "properties": {
    "addr:full":"Calle de Carretera De Belver, 14 Albalate Cinca Huesca 22534",
    "addr:housenumber":"14",
    "addr:postcode":"22534",
    "addr:street":"Calle De Carretera De Belver",
    "iso:country":"ES",
    "sg:address":"Calle de Carretera De Belver, 14",
    "sg:city":"Albalate Cinca",
    "sg:orig_category":"Refiner\u00cdas De Petr\u00d3leo",
    "sg:phone":"+34 974 46 93 21",
    "sg:postcode":"22534",
    "sg:province":"Huesca",
    "sg:website":"www.jaimei.com",
    "wof:name":"Estacion De Servicio Jaime I S.a.",
    "wof:placetype":"venue"
},
  "geometry": {"coordinates":[0.2257198989,42.1413002014],"type":"Point"}
}