{
  "type": "Feature",
  "properties": {
    "addr:full":"Calle de Musica (de La), S/n Manzanares Ciudad Real 13200",
    "addr:postcode":"13200",
    "addr:street":"Calle De Musica De La S / N",
    "iso:country":"ES",
    "sg:address":"Calle de Musica (de La), S/n",
    "sg:city":"Manzanares",
    "sg:orig_category":"Aguas (distribuci\u00d3n, Servicios)",
    "sg:phone":"+34 926 61 33 03",
    "sg:postcode":"13200",
    "sg:province":"Ciudad Real",
    "wof:name":"Pridesa Proyectos Y Servicios S.a.",
    "wof:placetype":"venue"
},
  "geometry": {"coordinates":[-3.3782041073,38.9958114624],"type":"Point"}
}