{
  "type": "Feature",
  "properties": {
    "addr:full":"Calle de Antonio Rubio Torres, 2 Fuengirola M\u00e1laga 29640",
    "addr:housenumber":"2",
    "addr:postcode":"29640",
    "addr:street":"Calle De Antonio Rubio Torres;Ma\u0301Laga",
    "iso:country":"ES",
    "sg:address":"Calle de Antonio Rubio Torres, 2",
    "sg:city":"Fuengirola",
    "sg:orig_category":"M\u00c9dicos: Estomatolog\u00cda",
    "sg:phone":"+34 952 46 40 68",
    "sg:postcode":"29640",
    "sg:province":"M\u00e1laga",
    "wof:name":"Ota\u00f1o  Carlos Antonio",
    "wof:placetype":"venue"
},
  "geometry": {"coordinates":[-4.6226773262,36.5422554016],"type":"Point"}
}