{
  "type": "Feature",
  "properties": {
    "iso:country":"ES",
    "sg:address":"Rua Cruceiro (o), 14",
    "sg:city":"Cruceiro",
    "sg:orig_category":"Comercio, Reparaci\u00d3n De Motocicletas, Bicicletas Y Piezas Sueltas",
    "sg:phone":"+34 986 74 30 41",
    "sg:postcode":"36990",
    "sg:province":"Pontevedra",
    "wof:name":"Abeijon Cami\u00f1a Victor",
    "wof:placetype":"venue"
},
  "geometry": {"coordinates":[-8.635116,42.450924],"type":"Point"}
}