{
  "type": "Feature",
  "properties": {
    "iso:country":"ES",
    "sg:address":"Calle de Juan Sebastian Elcano, 12",
    "sg:city":"Fuengirola",
    "sg:orig_category":"Promotores Constructores",
    "sg:phone":"+34 952 46 55 91",
    "sg:postcode":"29640",
    "sg:province":"M\u00e1laga",
    "wof:name":"Realistic Spain S.l.",
    "wof:placetype":"venue"
},
  "geometry": {"coordinates":[-4.6188840866,36.5448608398],"type":"Point"}
}