{
  "type": "Feature",
  "properties": {
    "iso:country":"ES",
    "sg:address":"Pase Fueros De Aragon, 22",
    "sg:city":"Tarazona",
    "sg:orig_category":"Centros Empresariales",
    "sg:phone":"+34 976 64 05 36",
    "sg:postcode":"50500",
    "sg:province":"Zaragoza",
    "wof:name":"Calavia Guerra Susana",
    "wof:placetype":"venue"
},
  "geometry": {"coordinates":[-1.7316739559,41.8999633789],"type":"Point"}
}