{
  "type": "Feature",
  "properties": {
    "addr:full":"Ctra Alfonso Xiii, 40 Melilla Melilla 52005",
    "addr:housenumber":"40",
    "addr:postcode":"52005",
    "addr:street":"Ctra Alfonso Xiii",
    "iso:country":"ES",
    "sg:address":"Ctra Alfonso Xiii, 40",
    "sg:city":"Melilla",
    "sg:orig_category":"Aparcamientos (infraestructuras, Accesorios)",
    "sg:phone":"+34 952 67 95 21",
    "sg:postcode":"52005",
    "sg:province":"Melilla",
    "wof:name":"Garage Estrada Arroyo C.b.",
    "wof:placetype":"venue"
},
  "geometry": {"coordinates":[-2.9538879395,35.2896347046],"type":"Point"}
}