{
  "type": "Feature",
  "properties": {
    "addr:full":"Calle de Portal De Beto\u00d1o, 24 Vitoria-gasteiz \u00c1lava 01013",
    "addr:housenumber":"24",
    "addr:postcode":"01013",
    "addr:street":"Calle De Portal De Beton\u0303O",
    "iso:country":"ES",
    "sg:address":"Calle de Portal De Beto\u00d1o, 24",
    "sg:city":"Vitoria-gasteiz",
    "sg:orig_category":"Maquinaria Para Industrias Diversas",
    "sg:phone":"+34 945 27 44 08",
    "sg:postcode":"01013",
    "sg:province":"\u00c1lava",
    "sg:website":"www.alquileresrubel.com",
    "wof:name":"Rubel Maquinaria Y Herramientas S.l.",
    "wof:placetype":"venue"
},
  "geometry": {"coordinates":[-2.6580541134,42.8606681824],"type":"Point"}
}