{
  "type": "Feature",
  "properties": {
    "addr:full":"Ctra. La Ventilla, Km. 0002,8 Fuente Palmera C\u00f3rdoba 14120",
    "addr:postcode":"14120",
    "addr:street":"Ctra. La Ventilla Km. 0002,8;Co\u0301Rdoba",
    "iso:country":"ES",
    "sg:address":"Ctra. La Ventilla, Km. 0002,8",
    "sg:city":"Fuente Palmera",
    "sg:orig_category":"Grabados Y Decoraci\u00d3n De Metales",
    "sg:phone":"+34 957 63 85 32",
    "sg:postcode":"14120",
    "sg:province":"C\u00f3rdoba",
    "sg:website":"www.terra.es/personal/est.met",
    "wof:name":"Hierros Fuente Palmera S.l.",
    "wof:placetype":"venue"
},
  "geometry": {"coordinates":[-5.0817894936,37.7288970947],"type":"Point"}
}