{
  "type": "Feature",
  "properties": {
    "addr:full":"Carr Blasco Iba\u00d1ez, 42 Pu\u00e7ol Valencia 46530",
    "addr:housenumber":"42",
    "addr:postcode":"46530",
    "addr:street":"Carr Blasco Iban\u0303Ez",
    "iso:country":"ES",
    "sg:address":"Carr Blasco Iba\u00d1ez, 42",
    "sg:city":"Pu\u00e7ol",
    "sg:orig_category":"Agencias Y Agentes Comerciales, Representantes",
    "sg:phone":"+34 961 42 27 96",
    "sg:postcode":"46530",
    "sg:province":"Valencia",
    "wof:name":"Juan A.munoz Martinez S.l.",
    "wof:placetype":"venue"
},
  "geometry": {"coordinates":[-0.3088729978,39.6217765808],"type":"Point"}
}