{
  "type": "Feature",
  "properties": {
    "addr:full":"Carrer de Gracia, 78 Sabadell Barcelona 08201",
    "addr:housenumber":"78",
    "addr:postcode":"08201",
    "addr:street":"Carrer De Gracia",
    "iso:country":"ES",
    "sg:address":"Carrer de Gracia, 78",
    "sg:city":"Sabadell",
    "sg:orig_category":"M\u00c9dicos: Radiolog\u00cda (radiodiagn\u00d3stico E Im\u00c1genes En Medicina)",
    "sg:phone":"+34 937 26 16 66",
    "sg:postcode":"08201",
    "sg:province":"Barcelona",
    "wof:name":"Centro De Radiologia Diagnsotica Dr. Duran, S.l.",
    "wof:placetype":"venue"
},
  "geometry": {"coordinates":[2.1060490608,41.5491943359],"type":"Point"}
}