{
  "type": "Feature",
  "properties": {
    "addr:full":"Avda Ruta De La Plata, 44 Caceres C\u00e1ceres 10001",
    "addr:housenumber":"44",
    "addr:postcode":"10001",
    "addr:street":"Avda Ruta De La Plata;Ca\u0301Ceres",
    "iso:country":"ES",
    "sg:address":"Avda Ruta De La Plata, 44",
    "sg:city":"Caceres",
    "sg:orig_category":"Peluquer\u00cdas, Peluquer\u00cda Mixta",
    "sg:phone":"+34 927 23 32 33",
    "sg:postcode":"10001",
    "sg:province":"C\u00e1ceres",
    "wof:name":"De Sande Hernandez Julia",
    "wof:placetype":"venue"
},
  "geometry": {"coordinates":[-6.3877391815,39.4711799622],"type":"Point"}
}