{
  "type": "Feature",
  "properties": {
    "iso:country":"ES",
    "sg:address":"Calle de Castello, 115",
    "sg:city":"Madrid",
    "sg:orig_category":"Transportes Mar\u00cdtimos",
    "sg:phone":"+34 914 11 07 77",
    "sg:postcode":"28006",
    "sg:province":"Madrid",
    "wof:name":"Rigel Representaciones S.l.",
    "wof:placetype":"venue"
},
  "geometry": {"coordinates":[-3.6806483269,40.4364624023],"type":"Point"}
}