{
  "type": "Feature",
  "properties": {
    "addr:full":"Fermin Calbeton Kalea, 1 Eibar Guip\u00f9zcoa 20600",
    "addr:housenumber":"1",
    "addr:postcode":"20600",
    "addr:street":"Fermin Calbeton Kalea;Guipu\u0300Zcoa",
    "iso:country":"ES",
    "sg:address":"Fermin Calbeton Kalea, 1",
    "sg:city":"Eibar",
    "sg:orig_category":"Agencias Y Asesores De Publicidad",
    "sg:phone":"+34 943 70 14 66",
    "sg:postcode":"20600",
    "sg:province":"Guip\u00f9zcoa",
    "sg:website":"www.ikatz.es",
    "wof:name":"Ikatz, S.a.",
    "wof:placetype":"venue"
},
  "geometry": {"coordinates":[-2.4727339745,43.1842842102],"type":"Point"}
}