{
  "type": "Feature",
  "properties": {
    "iso:country":"ES",
    "sg:address":"Carrer de Tarragones, 5",
    "sg:city":"Lloret Blau",
    "sg:orig_category":"Promotores Constructores",
    "sg:phone":"+34 972 37 82 03",
    "sg:postcode":"17310",
    "sg:province":"Girona",
    "wof:name":"Delta Word S.l.",
    "wof:placetype":"venue"
},
  "geometry": {"coordinates":[2.8453071117,41.7054214478],"type":"Point"}
}