{
  "type": "Feature",
  "properties": {
    "iso:country":"ES",
    "sg:address":"Souto, 2",
    "sg:city":"Souto",
    "sg:orig_category":"Cooperativas Agr\u00cdcolas",
    "sg:phone":"+34 981 62 04 07",
    "sg:postcode":"15160",
    "sg:province":"A Coru\u00f1a",
    "wof:name":"Taibo Souto Joaquin",
    "wof:placetype":"venue"
},
  "geometry": {"coordinates":[-8.2676887512,43.3610687256],"type":"Point"}
}