{
  "type": "Feature",
  "properties": {
    "addr:full":"Calle de Veraza, 59 Mendavia Navarra 31587",
    "addr:housenumber":"59",
    "addr:postcode":"31587",
    "addr:street":"Calle De Veraza",
    "iso:country":"ES",
    "sg:address":"Calle de Veraza, 59",
    "sg:city":"Mendavia",
    "sg:orig_category":"Aluminio Y Aleaciones (producci\u00d3n, Transformaci\u00d3n, Negocio)",
    "sg:phone":"+34 948 68 52 27",
    "sg:postcode":"31587",
    "sg:province":"Navarra",
    "wof:name":"Manufacturas Mendavia S. A.",
    "wof:placetype":"venue"
},
  "geometry": {"coordinates":[-2.1972789764,42.4501495361],"type":"Point"}
}