{
  "type": "Feature",
  "properties": {
    "iso:country":"ES",
    "sg:address":"Calle de Villajoyosa, 73",
    "sg:city":"Madrid",
    "sg:orig_category":"Papeler\u00cdas: Art\u00cdculos (al Por Mayor)",
    "sg:phone":"+34 917 98 67 82",
    "sg:postcode":"28041",
    "sg:province":"Madrid",
    "wof:name":"Gallego Leon Antonia",
    "wof:placetype":"venue"
},
  "geometry": {"coordinates":[-3.6908938885,40.3551979065],"type":"Point"}
}