{
  "type": "Feature",
  "properties": {
    "iso:country":"ES",
    "sg:address":"Calle de Hermosilla, 83",
    "sg:city":"Madrid",
    "sg:orig_category":"Producci\u00d3n, Distribuci\u00d3n De Electricidad",
    "sg:phone":"+34 915 76 20 84",
    "sg:postcode":"28001",
    "sg:province":"Madrid",
    "wof:name":"Lopez Sulla Enrique",
    "wof:placetype":"venue"
},
  "geometry": {"coordinates":[-3.6773951054,40.4261436462],"type":"Point"}
}