{
  "type": "Feature",
  "properties": {
    "iso:country":"ES",
    "sg:address":"Calle de Alicante (de), 14",
    "sg:city":"Humanes De Madrid",
    "sg:orig_category":"Frutas, Legumbres Frescas Y Tempranas (al Por Menor)",
    "sg:phone":"+34 916 90 09 92",
    "sg:postcode":"28970",
    "sg:province":"Madrid",
    "wof:name":"Vifrusa S.l.",
    "wof:placetype":"venue"
},
  "geometry": {"coordinates":[-3.8141059875,40.2769355774],"type":"Point"}
}