{
  "type": "Feature",
  "properties": {
    "iso:country":"ES",
    "sg:address":"Cmno Portal (del), S/n",
    "sg:city":"Movera",
    "sg:orig_category":"Lecher\u00cdas",
    "sg:phone":"+34 976 58 62 47",
    "sg:postcode":"50194",
    "sg:province":"Zaragoza",
    "wof:name":"Sainz-aja S.c.",
    "wof:placetype":"venue"
},
  "geometry": {"coordinates":[-0.822224021,41.6489944458],"type":"Point"}
}