{
  "type": "Feature",
  "properties": {
    "addr:full":"Calle de Periodista Jose L. De Cordoba, 6 Cordoba C\u00f3rdoba 14010",
    "addr:housenumber":"6",
    "addr:postcode":"14010",
    "addr:street":"Calle De Periodista Jose L. De Cordoba;Co\u0301Rdoba",
    "iso:country":"ES",
    "sg:address":"Calle de Periodista Jose L. De Cordoba, 6",
    "sg:city":"Cordoba",
    "sg:orig_category":"Electricidad: Instaladores",
    "sg:phone":"+34 957 75 22 28",
    "sg:postcode":"14010",
    "sg:province":"C\u00f3rdoba",
    "wof:name":"Montajes Electricos Insur S.l.",
    "wof:placetype":"venue"
},
  "geometry": {"coordinates":[-4.7645440102,37.8760032654],"type":"Point"}
}