{
  "type": "Feature",
  "properties": {
    "addr:full":"Calle de Fuertes Acevedo, 1 Oviedo Asturias 33006",
    "addr:housenumber":"1",
    "addr:postcode":"33006",
    "addr:street":"Calle De Fuertes Acevedo",
    "iso:country":"ES",
    "sg:address":"Calle de Fuertes Acevedo, 1",
    "sg:city":"Oviedo",
    "sg:orig_category":"Librer\u00cdas",
    "sg:phone":"+34 985 24 16 03",
    "sg:postcode":"33006",
    "sg:province":"Asturias",
    "wof:name":"Garcia Vazquez Jorge Luis",
    "wof:placetype":"venue"
},
  "geometry": {"coordinates":[-5.8627839088,43.3600845337],"type":"Point"}
}