{
  "type": "Feature",
  "properties": {
    "iso:country":"ES",
    "sg:address":"Calle de Rodio, 2",
    "sg:city":"Sevilla",
    "sg:orig_category":"Molduras, Junquillos, Listones Y Molduras Perforadas",
    "sg:phone":"+34 954 35 81 92",
    "sg:postcode":"41007",
    "sg:province":"Sevilla",
    "wof:name":"Navas Troncoso Enrique",
    "wof:placetype":"venue"
},
  "geometry": {"coordinates":[-5.9557538033,37.4075813293],"type":"Point"}
}