{
  "type": "Feature",
  "properties": {
    "addr:full":"C/ Oscar Espla, 65 Elche Alicante 03201",
    "addr:housenumber":"/;65",
    "addr:postcode":"03201",
    "addr:street":"C;Espla",
    "iso:country":"ES",
    "sg:address":"C/ Oscar Espla, 65",
    "sg:city":"Elche",
    "sg:orig_category":"Caf\u00c9s, Bares, Cervecer\u00cdas",
    "sg:phone":"+34 965 46 70 25",
    "sg:postcode":"03201",
    "sg:province":"Alicante",
    "wof:name":"Priego Sabariego Jose",
    "wof:placetype":"venue"
},
  "geometry": {"coordinates":[-0.706348002,38.2688331604],"type":"Point"}
}