{
  "type": "Feature",
  "properties": {
    "iso:country":"ES",
    "sg:address":"Avda Portugal (de), 128",
    "sg:city":"Verin",
    "sg:orig_category":"Producci\u00d3n De Abonos Y De Fertilizantes",
    "sg:phone":"+34 988 41 03 19",
    "sg:postcode":"32600",
    "sg:province":"Ourense",
    "wof:name":"Rojo Suarez Jose",
    "wof:placetype":"venue"
},
  "geometry": {"coordinates":[-7.4404392242,41.9313583374],"type":"Point"}
}