{
  "type": "Feature",
  "properties": {
    "addr:full":"Carrer de Monestir De Poblet, 4 Reus Tarragona 43205",
    "addr:housenumber":"4",
    "addr:postcode":"43205",
    "addr:street":"Carrer De Monestir De Poblet",
    "iso:country":"ES",
    "sg:address":"Carrer de Monestir De Poblet, 4",
    "sg:city":"Reus",
    "sg:orig_category":"Centros De Coordinaci\u00d3n",
    "sg:phone":"+34 977 77 19 43",
    "sg:postcode":"43205",
    "sg:province":"Tarragona",
    "wof:name":"Serveis Administratius Baix Camp S.l.",
    "wof:placetype":"venue"
},
  "geometry": {"coordinates":[1.1054439545,41.1484069824],"type":"Point"}
}