{
  "type": "Feature",
  "properties": {
    "addr:full":"Plaz Don Pedro, 6 Olula Rio Almer\u00eda 04860",
    "addr:housenumber":"6",
    "addr:postcode":"04860",
    "addr:street":"Pedro;Almeri\u0301A",
    "iso:country":"ES",
    "sg:address":"Plaz Don Pedro, 6",
    "sg:city":"Olula Rio",
    "sg:orig_category":"Ropa Y Accesorios",
    "sg:phone":"+34 950 44 15 47",
    "sg:postcode":"04860",
    "sg:province":"Almer\u00eda",
    "sg:website":"www.luismarti.hotmail.com",
    "wof:name":"Martinez Ramos Luis",
    "wof:placetype":"venue"
},
  "geometry": {"coordinates":[-2.2987639904,37.3577842712],"type":"Point"}
}