{
  "type": "Feature",
  "properties": {
    "addr:full":"Carrer de Mar, 6 Pobla De Montornes Tarragona 43761",
    "addr:housenumber":"6",
    "addr:postcode":"43761",
    "addr:street":"Carrer De Mar",
    "iso:country":"ES",
    "sg:address":"Carrer de Mar, 6",
    "sg:city":"Pobla De Montornes",
    "sg:orig_category":"Producci\u00d3n, Venta De Productos De Agricultura Biol\u00d3gica",
    "sg:phone":"+34 977 64 81 12",
    "sg:postcode":"43761",
    "sg:province":"Tarragona",
    "wof:name":"Recasens Gibert Mario",
    "wof:placetype":"venue"
},
  "geometry": {"coordinates":[1.41505301,41.1762237549],"type":"Point"}
}