{
  "type": "Feature",
  "properties": {
    "iso:country":"ES",
    "sg:address":"Avda De Espa\u00f1a, S/n",
    "sg:city":"Mengibar",
    "sg:orig_category":"Muebles, Minoristas",
    "sg:phone":"+34 953 37 25 96",
    "sg:postcode":"23620",
    "sg:province":"Ja\u00e9n",
    "wof:name":"Muebles Antonio Beltran S.l.",
    "wof:placetype":"venue"
},
  "geometry": {"coordinates":[-3.7980339527,37.9727096558],"type":"Point"}
}