{
  "type": "Feature",
  "properties": {
    "addr:full":"Carrer de Sant Miquel Xic, S/n Vic Barcelona 08500",
    "addr:housenumber":"s",
    "addr:postcode":"08500",
    "addr:street":"Carrer De Sant Miquel Xic;/ N",
    "iso:country":"ES",
    "sg:address":"Carrer de Sant Miquel Xic, S/n",
    "sg:city":"Vic",
    "sg:orig_category":"Centros De Educaci\u00d3n Especial",
    "sg:phone":"+34 938 89 26 88",
    "sg:postcode":"08500",
    "sg:province":"Barcelona",
    "wof:name":"Ceip Guillem De Montrodon-sant Miquel De",
    "wof:placetype":"venue"
},
  "geometry": {"coordinates":[2.2643549442,41.9365959167],"type":"Point"}
}