{
  "type": "Feature",
  "properties": {
    "iso:country":"ES",
    "sg:address":"Cra Nac Carrer de Cinq-dos, Km. 0120,0",
    "sg:city":"Ribes Freser",
    "sg:orig_category":"Empresas De Carpinter\u00cda De Madera",
    "sg:phone":"+34 972 72 77 78",
    "sg:postcode":"17534",
    "sg:province":"Girona",
    "wof:name":"Fusteria Del Freser S.l.",
    "wof:placetype":"venue"
},
  "geometry": {"coordinates":[2.1643021107,42.3507347107],"type":"Point"}
}