{
  "type": "Feature",
  "properties": {
    "iso:country":"ES",
    "sg:address":"Calle de Artes Graficas, 28",
    "sg:city":"Valencia",
    "sg:orig_category":"Laboratorios Farmac\u00c9uticos",
    "sg:phone":"+34 963 69 45 05",
    "sg:postcode":"46010",
    "sg:province":"Valencia",
    "sg:website":"www.lacer.es",
    "wof:name":"Lacer S. A.",
    "wof:placetype":"venue"
},
  "geometry": {"coordinates":[-0.3605642021,39.4761505127],"type":"Point"}
}