{
  "type": "Feature",
  "properties": {
    "addr:full":"Carr Sant Francesc, 3 Alcudia Valencia 46250",
    "addr:housenumber":"3",
    "addr:postcode":"46250",
    "addr:street":"Carr Sant Francesc",
    "iso:country":"ES",
    "sg:address":"Carr Sant Francesc, 3",
    "sg:city":"Alcudia",
    "sg:classifiers":[
        {
            "category":"Personal",
            "subcategory":"Barber",
            "type":"Services"
        }
    ],
    "sg:phone":"+34 962 54 02 94",
    "sg:postcode":"46250",
    "sg:province":"Valencia",
    "sg:tags":[
        "caballeros",
        "de",
        "peluqueros"
    ],
    "wof:name":"Simo Amat Jose Antonio",
    "wof:placetype":"venue"
},
  "geometry": {"coordinates":[-0.5070289969,39.1940689087],"type":"Point"}
}