{
  "type": "Feature",
  "properties": {
    "addr:full":"Calle de El Cristo, 16 Balmaseda Vizcaya 48800",
    "addr:housenumber":"16",
    "addr:postcode":"48800",
    "addr:street":"Calle De El Cristo",
    "iso:country":"ES",
    "sg:address":"Calle de El Cristo, 16",
    "sg:city":"Balmaseda",
    "sg:orig_category":"Agentes Generales De Seguros",
    "sg:phone":"+34 946 80 28 40",
    "sg:postcode":"48800",
    "sg:province":"Vizcaya",
    "wof:name":"Casta\u00f1os Lizeaga Jose Maria",
    "wof:placetype":"venue"
},
  "geometry": {"coordinates":[-3.1955940723,43.1921234131],"type":"Point"}
}