{
  "type": "Feature",
  "properties": {
    "addr:full":"Calle de Pintor Vilar, 1 Valencia Valencia 46010",
    "addr:housenumber":"1",
    "addr:postcode":"46010",
    "addr:street":"Calle De Pintor Vilar",
    "iso:country":"ES",
    "sg:address":"Calle de Pintor Vilar, 1",
    "sg:city":"Valencia",
    "sg:orig_category":"Reposter\u00cdas",
    "sg:phone":"+34 963 62 85 66",
    "sg:postcode":"46010",
    "sg:province":"Valencia",
    "wof:name":"Perez Pons Vicente",
    "wof:placetype":"venue"
},
  "geometry": {"coordinates":[-0.3709963858,39.4822349548],"type":"Point"}
}