{
  "type": "Feature",
  "properties": {
    "iso:country":"ES",
    "sg:address":"Rua Canabal (do), 1",
    "sg:city":"Burela",
    "sg:classifiers":[
        {
            "category":"Recreation",
            "type":"Entertainment"
        }
    ],
    "sg:phone":"+34 982 58 05 51",
    "sg:postcode":"27880",
    "sg:province":"Lugo",
    "sg:tags":[
        "caza",
        "pr\u00c1ctica",
        "la",
        "de",
        "pesca",
        "y"
    ],
    "wof:name":"Basanta Fra Hermanos C.b.",
    "wof:placetype":"venue"
},
  "geometry": {"coordinates":[-7.3597187996,43.6565284729],"type":"Point"}
}