{
  "type": "Feature",
  "properties": {
    "iso:country":"ES",
    "sg:address":"Carrer de Concordia, 33",
    "sg:city":"Barcelona",
    "sg:orig_category":"Organizaciones Internacionales",
    "sg:phone":"+34 933 24 85 38",
    "sg:postcode":"08004",
    "sg:province":"Barcelona",
    "wof:name":"Coordinadora",
    "wof:placetype":"venue"
},
  "geometry": {"coordinates":[2.1597249508,41.3727798462],"type":"Point"}
}