{
  "type": "Feature",
  "properties": {
    "addr:full":"Calle de Mayor, 24 Burgohondo \u00c1vila 05113",
    "addr:housenumber":"24",
    "addr:postcode":"05113",
    "addr:street":"Calle De Mayor;A\u0301Vila",
    "iso:country":"ES",
    "sg:address":"Calle de Mayor, 24",
    "sg:city":"Burgohondo",
    "sg:orig_category":"Estancos",
    "sg:phone":"+34 920 28 33 13",
    "sg:postcode":"05113",
    "sg:province":"\u00c1vila",
    "wof:name":"Delgado Martin Jose Maria",
    "wof:placetype":"venue"
},
  "geometry": {"coordinates":[-4.7860970497,40.4135017395],"type":"Point"}
}