{
  "type": "Feature",
  "properties": {
    "iso:country":"ES",
    "sg:address":"Carrer de Vapor Gordils, 24",
    "sg:city":"Mataro",
    "sg:orig_category":"Chapister\u00cda",
    "sg:phone":"+34 937 55 60 72",
    "sg:postcode":"08304",
    "sg:province":"Barcelona",
    "wof:name":"Cebrero Garcia Jose",
    "wof:placetype":"venue"
},
  "geometry": {"coordinates":[2.4544079304,41.5515632629],"type":"Point"}
}