{
  "type": "Feature",
  "properties": {
    "iso:country":"ES",
    "sg:address":"Carrer de Bac De Roda, 50",
    "sg:city":"Roda Ter",
    "sg:orig_category":"Quincaller\u00cda (al Por Menor)",
    "sg:phone":"+34 938 54 07 37",
    "sg:postcode":"08510",
    "sg:province":"Barcelona",
    "wof:name":"Vilalta Casadella Marina",
    "wof:placetype":"venue"
},
  "geometry": {"coordinates":[2.3098399639,41.9842300415],"type":"Point"}
}