{
  "type": "Feature",
  "properties": {
    "addr:full":"Calle de Pintor Ribalta, 18 Alcora Castell\u00f3n 12110",
    "addr:housenumber":"18",
    "addr:postcode":"12110",
    "addr:street":"Calle De Pintor Ribalta;Castello\u0301N",
    "iso:country":"ES",
    "sg:address":"Calle de Pintor Ribalta, 18",
    "sg:city":"Alcora",
    "sg:orig_category":"Cerrajer\u00cda, Ferrallista",
    "sg:phone":"+34 964 36 02 37",
    "sg:postcode":"12110",
    "sg:province":"Castell\u00f3n",
    "wof:name":"Taller Miguel Artero S.l.",
    "wof:placetype":"venue"
},
  "geometry": {"coordinates":[-0.2178789973,40.0734786987],"type":"Point"}
}