{
  "type": "Feature",
  "properties": {
    "iso:country":"ES",
    "sg:address":"Carrer de Robrenyo, 11",
    "sg:city":"Barcelona",
    "sg:orig_category":"Empresas De Portes Y Mensajer\u00cda",
    "sg:phone":"+34 934 11 11 54",
    "sg:postcode":"08014",
    "sg:province":"Barcelona",
    "wof:name":"Telecomunicaciones Concel S.l.",
    "wof:placetype":"venue"
},
  "geometry": {"coordinates":[2.1369268894,41.381401062],"type":"Point"}
}