{
  "type": "Feature",
  "properties": {
    "addr:full":"Carrer de Gambo, 6 Benidorm Alicante 03500",
    "addr:housenumber":"6",
    "addr:postcode":"03500",
    "addr:street":"Carrer De Gambo",
    "iso:country":"ES",
    "sg:address":"Carrer de Gambo, 6",
    "sg:city":"Benidorm",
    "sg:classifiers":[
        {
            "category":"Cinema",
            "subcategory":"Movie Theater",
            "type":"Entertainment"
        }
    ],
    "sg:phone":"+34 965 85 68 53",
    "sg:postcode":"03500",
    "sg:province":"Alicante",
    "sg:tags":[
        "salas",
        "de",
        "cine"
    ],
    "sg:website":"www.cinesimf.com",
    "wof:name":"Cines Mediterraneo S.l.",
    "wof:placetype":"venue"
},
  "geometry": {"coordinates":[-0.1279319972,38.5369796753],"type":"Point"}
}