{
  "type": "Feature",
  "properties": {
    "iso:country":"ES",
    "sg:address":"Calle de Godofredo Ortega Y Mu\u00d1oz, 15",
    "sg:city":"Badajoz",
    "sg:orig_category":"Electrodom\u00c9sticos (fabricaci\u00d3n, Al Por Mayor)",
    "sg:phone":"+34 924 20 76 44",
    "sg:postcode":"06011",
    "sg:province":"Badajoz",
    "wof:name":"T-systems Itc Services Espa\u00d1a S.a.",
    "wof:placetype":"venue"
},
  "geometry": {"coordinates":[-6.9863348007,38.8665084839],"type":"Point"}
}