{
  "type": "Feature",
  "properties": {
    "addr:full":"Calle de Ausias March, 1 Alberic Valencia 46260",
    "addr:housenumber":"1",
    "addr:postcode":"46260",
    "addr:street":"Calle De Ausias March",
    "iso:country":"ES",
    "sg:address":"Calle de Ausias March, 1",
    "sg:city":"Alberic",
    "sg:orig_category":"Peluqueros: De Se\u00d1oras",
    "sg:phone":"+34 962 44 09 41",
    "sg:postcode":"46260",
    "sg:province":"Valencia",
    "wof:name":"Climent Calatayud Camelia",
    "wof:placetype":"venue"
},
  "geometry": {"coordinates":[-0.52017349,39.1156158447],"type":"Point"}
}