{
  "type": "Feature",
  "properties": {
    "iso:country":"ES",
    "sg:address":"Pase Habana, 206",
    "sg:city":"Madrid",
    "sg:orig_category":"Arquitectos",
    "sg:phone":"+34 913 50 37 96",
    "sg:postcode":"28036",
    "sg:province":"Madrid",
    "wof:name":"Presas Castilla Antonio",
    "wof:placetype":"venue"
},
  "geometry": {"coordinates":[-3.67937994,40.4650268555],"type":"Point"}
}