{
  "type": "Feature",
  "properties": {
    "addr:full":"Avda Juan Carlos I, Rey, 2 Melilla Melilla 52001",
    "addr:housenumber":"2",
    "addr:postcode":"52001",
    "addr:street":"Avda Juan Carlos I Rey",
    "iso:country":"ES",
    "sg:address":"Avda Juan Carlos I, Rey, 2",
    "sg:city":"Melilla",
    "sg:orig_category":"M\u00c9dicos: Cardiolog\u00cda Y Afecciones Cardiovasculares",
    "sg:phone":"+34 952 67 25 69",
    "sg:postcode":"52001",
    "sg:province":"Melilla",
    "wof:name":"Birbe Oliva Jose Maria",
    "wof:placetype":"venue"
},
  "geometry": {"coordinates":[-2.9388511181,35.2926216125],"type":"Point"}
}