{
  "type": "Feature",
  "properties": {
    "iso:country":"ES",
    "sg:address":"Calle de Mayor, 86",
    "sg:city":"Madrid",
    "sg:orig_category":"Librer\u00cdas",
    "sg:phone":"+34 915 42 62 48",
    "sg:postcode":"28013",
    "sg:province":"Madrid",
    "wof:name":"Libreria Kilate S.l.",
    "wof:placetype":"venue"
},
  "geometry": {"coordinates":[-3.7127141953,40.4151649475],"type":"Point"}
}