{
  "type": "Feature",
  "properties": {
    "iso:country":"ES",
    "sg:address":"Avgd Prat De La Riba, 21",
    "sg:city":"Badalona",
    "sg:orig_category":"Fisioterapia",
    "sg:phone":"+34 933 95 09 45",
    "sg:postcode":"08915",
    "sg:province":"Barcelona",
    "wof:name":"Acros S.c.p.",
    "wof:placetype":"venue"
},
  "geometry": {"coordinates":[2.2480471134,41.4587135315],"type":"Point"}
}