{
  "type": "Feature",
  "properties": {
    "addr:full":"Calle de Doctor Fleming, 16 Onda Castell\u00f3n 12200",
    "addr:housenumber":"16",
    "addr:postcode":"12200",
    "addr:street":"Calle De Doctor Fleming;Castello\u0301N",
    "iso:country":"ES",
    "sg:address":"Calle de Doctor Fleming, 16",
    "sg:city":"Onda",
    "sg:orig_category":"Asociaciones Y Clubs Deportivos",
    "sg:phone":"+34 964 77 00 70",
    "sg:postcode":"12200",
    "sg:province":"Castell\u00f3n",
    "wof:name":"Rubio Gil Sonia",
    "wof:placetype":"venue"
},
  "geometry": {"coordinates":[-0.2663550079,39.96459198],"type":"Point"}
}