{
  "type": "Feature",
  "properties": {
    "addr:full":"Calle de Mayor, 17 Murchante Navarra 31521",
    "addr:housenumber":"17",
    "addr:postcode":"31521",
    "addr:street":"Calle De Mayor",
    "iso:country":"ES",
    "sg:address":"Calle de Mayor, 17",
    "sg:city":"Murchante",
    "sg:orig_category":"Pescader\u00cdas (al Por Menor)",
    "sg:phone":"+34 948 83 83 54",
    "sg:postcode":"31521",
    "sg:province":"Navarra",
    "wof:name":"Bonilla Sanchez Eugenio",
    "wof:placetype":"venue"
},
  "geometry": {"coordinates":[-1.6604349613,42.0292854309],"type":"Point"}
}