{
  "type": "Feature",
  "properties": {
    "iso:country":"ES",
    "sg:address":"Calle de Nueva De La Virgen, 3",
    "sg:city":"Granada",
    "sg:orig_category":"M\u00c9dicos: Pediatr\u00cda. Enfermedades De Los Ni\u00d1os",
    "sg:phone":"+34 958 25 09 13",
    "sg:postcode":"18005",
    "sg:province":"Granada",
    "wof:name":"Arroyave Valencia Gustavo",
    "wof:placetype":"venue"
},
  "geometry": {"coordinates":[-3.5974652767,37.1693115234],"type":"Point"}
}