{
  "type": "Feature",
  "properties": {
    "addr:full":"Calle de Marques De Quintanar, 37 Baiona Pontevedra 36300",
    "addr:housenumber":"37",
    "addr:postcode":"36300",
    "addr:street":"Calle De Marques De Quintanar",
    "iso:country":"ES",
    "sg:address":"Calle de Marques De Quintanar, 37",
    "sg:city":"Baiona",
    "sg:orig_category":"Comerciantes Al Por Mayor De Vinos, Licores Y Alcoholes",
    "sg:phone":"+34 986 35 53 06",
    "sg:postcode":"36300",
    "sg:province":"Pontevedra",
    "wof:name":"Rodriguez Comesa\u00f1a Jose",
    "wof:placetype":"venue"
},
  "geometry": {"coordinates":[-97.78224945069999,45.7040786743],"type":"Point"}
}