{
  "type": "Feature",
  "properties": {
    "addr:full":"Calle de Jose Antonio Agirre Lehendakaria Kalea, 6 Durango Vizcaya 48200",
    "addr:housenumber":"6",
    "addr:postcode":"48200",
    "addr:street":"Calle De Jose Antonio Agirre Lehendakaria Kalea",
    "iso:country":"ES",
    "sg:address":"Calle de Jose Antonio Agirre Lehendakaria Kalea, 6",
    "sg:city":"Durango",
    "sg:orig_category":"Ense\u00d1anza Variada",
    "sg:phone":"+34 946 81 41 43",
    "sg:postcode":"48200",
    "sg:province":"Vizcaya",
    "wof:name":"Lakotkera C.b.",
    "wof:placetype":"venue"
},
  "geometry": {"coordinates":[-2.6327190399,43.1716842651],"type":"Point"}
}