{
  "type": "Feature",
  "properties": {
    "iso:country":"ES",
    "sg:address":"Poli Mugitegi-b, 26",
    "sg:city":"Urretxu",
    "sg:orig_category":"Frutas, Legumbres Frescas Y Tempranas (al Por Menor)",
    "sg:phone":"+34 943 72 14 71",
    "sg:postcode":"20700",
    "sg:province":"Guip\u00f9zcoa",
    "wof:name":"Rueda Rueda Juan",
    "wof:placetype":"venue"
},
  "geometry": {"coordinates":[-2.3134770393,43.086730957],"type":"Point"}
}