{
  "type": "Feature",
  "properties": {
    "addr:full":"Rua Xesus Taboada Chivite, 7 Verin Ourense 32600",
    "addr:housenumber":"7",
    "addr:postcode":"32600",
    "addr:street":"Rua Xesus Taboada Chivite",
    "iso:country":"ES",
    "sg:address":"Rua Xesus Taboada Chivite, 7",
    "sg:city":"Verin",
    "sg:orig_category":"Bazares, Art\u00cdculos De Limpieza Y De Cocina (al Por Menor)",
    "sg:phone":"+34 988 41 09 48",
    "sg:postcode":"32600",
    "sg:province":"Ourense",
    "wof:name":"Perez Rodriguez Jose Antonio",
    "wof:placetype":"venue"
},
  "geometry": {"coordinates":[-7.4401040077,41.9377593994],"type":"Point"}
}