{
  "type": "Feature",
  "properties": {
    "addr:full":"Carr Atzaro, 8 Eivissa Islas Baleares 07800",
    "addr:housenumber":"8",
    "addr:postcode":"07800",
    "addr:street":"Carr Atzaro",
    "iso:country":"ES",
    "sg:address":"Carr Atzaro, 8",
    "sg:city":"Eivissa",
    "sg:orig_category":"Panader\u00cdas, Panader\u00cdas",
    "sg:phone":"+34 971 30 49 61",
    "sg:postcode":"07800",
    "sg:province":"Islas Baleares",
    "wof:name":"Rodado Pozo Felix",
    "wof:placetype":"venue"
},
  "geometry": {"coordinates":[1.4121060371,38.9057350159],"type":"Point"}
}