{
  "type": "Feature",
  "properties": {
    "addr:full":"Calle de Blas Infante, 23 Lora Rio Sevilla 41440",
    "addr:housenumber":"23",
    "addr:postcode":"41440",
    "addr:street":"Calle De Blas Infante;Rio Sevilla",
    "iso:country":"ES",
    "sg:address":"Calle de Blas Infante, 23",
    "sg:city":"Lora Rio",
    "sg:orig_category":"Molduras, Junquillos, Listones Y Molduras Perforadas",
    "sg:phone":"+34 955 80 17 28",
    "sg:postcode":"41440",
    "sg:province":"Sevilla",
    "wof:name":"Fernandez Martin Alfonso",
    "wof:placetype":"venue"
},
  "geometry": {"coordinates":[-5.5307216644,37.6552581787],"type":"Point"}
}