{
  "type": "Feature",
  "properties": {
    "addr:full":"Av Salle (la), 45 Reus Tarragona 43205",
    "addr:housenumber":"45",
    "addr:postcode":"43205",
    "addr:street":"Av Salle La",
    "iso:country":"ES",
    "sg:address":"Av Salle (la), 45",
    "sg:city":"Reus",
    "sg:orig_category":"Estancos",
    "sg:phone":"+34 977 77 47 80",
    "sg:postcode":"43205",
    "sg:province":"Tarragona",
    "wof:name":"Niubo Caldero Ramon",
    "wof:placetype":"venue"
},
  "geometry": {"coordinates":[1.107943058,41.1481361389],"type":"Point"}
}