{
  "type": "Feature",
  "properties": {
    "iso:country":"ES",
    "sg:address":"Calle de Fuentes Carrionas, 26",
    "sg:city":"Cervera Pisuerga",
    "sg:orig_category":"Promotores Constructores",
    "sg:phone":"+34 979 87 07 51",
    "sg:postcode":"34840",
    "sg:province":"Palencia",
    "wof:name":"Merino Calvo Carlos",
    "wof:placetype":"venue"
},
  "geometry": {"coordinates":[-4.5000290871,42.8671112061],"type":"Point"}
}