{
  "type": "Feature",
  "properties": {
    "iso:country":"ES",
    "sg:address":"Carrer de Andrea Doria, 9",
    "sg:city":"Palma",
    "sg:orig_category":"Carnicer\u00cdas, Carnicer\u00cdas",
    "sg:phone":"+34 971 78 00 50",
    "sg:postcode":"07014",
    "sg:province":"Islas Baleares",
    "wof:name":"Lledo Monfort Jose David",
    "wof:placetype":"venue"
},
  "geometry": {"coordinates":[2.631403923,39.5704689026],"type":"Point"}
}