{
  "type": "Feature",
  "properties": {
    "addr:full":"Calle de Zaragoza, 14 Pe\u00e7arroya De Tastavins Teruel 44709",
    "addr:housenumber":"14",
    "addr:postcode":"44709",
    "addr:street":"Calle De Zaragoza",
    "iso:country":"ES",
    "sg:address":"Calle de Zaragoza, 14",
    "sg:city":"Pe\u00e7arroya De Tastavins",
    "sg:orig_category":"Lecher\u00cdas",
    "sg:phone":"+34 978 89 67 27",
    "sg:postcode":"44709",
    "sg:province":"Teruel",
    "wof:name":"Andreu Grau Alfredo",
    "wof:placetype":"venue"
},
  "geometry": {"coordinates":[-1.1069096327,40.3441085815],"type":"Point"}
}