{
  "type": "Feature",
  "properties": {
    "addr:full":"Carrer de Barcelona, 86 Hospitalet Llobregat Barcelona 08901",
    "addr:housenumber":"86",
    "addr:postcode":"08901",
    "addr:street":"Carrer De Barcelona",
    "iso:country":"ES",
    "sg:address":"Carrer de Barcelona, 86",
    "sg:city":"Hospitalet Llobregat",
    "sg:orig_category":"Negocio De Madera",
    "sg:phone":"+34 933 37 04 64",
    "sg:postcode":"08901",
    "sg:province":"Barcelona",
    "wof:name":"Fustes Busquets Mares S. L.",
    "wof:placetype":"venue"
},
  "geometry": {"coordinates":[2.1009190083,41.3606948853],"type":"Point"}
}