{
  "type": "Feature",
  "properties": {
    "addr:full":"Calle de Julian Cirilo Moreno, 29 S. Pedro Martir Ii Las Palmas 35110",
    "addr:housenumber":"29",
    "addr:postcode":"35110",
    "addr:street":"Calle De Julian Cirilo Moreno",
    "iso:country":"ES",
    "sg:address":"Calle de Julian Cirilo Moreno, 29",
    "sg:city":"S. Pedro Martir Ii",
    "sg:orig_category":"Promotores Constructores",
    "sg:phone":"+34 928 75 57 31",
    "sg:postcode":"35110",
    "sg:province":"Las Palmas",
    "wof:name":"Martin Gonzalez Manuel Ignacio",
    "wof:placetype":"venue"
},
  "geometry": {"coordinates":[-15.4485340118,27.8392906189],"type":"Point"}
}