{
  "type": "Feature",
  "properties": {
    "addr:full":"Calle de Carlos Maurras, 4 Madrid Madrid 28036",
    "addr:housenumber":"4",
    "addr:postcode":"28036",
    "addr:street":"Calle De Carlos Maurras",
    "iso:country":"ES",
    "sg:address":"Calle de Carlos Maurras, 4",
    "sg:city":"Madrid",
    "sg:orig_category":"Bazares, Art\u00cdculos De Limpieza Y De Cocina (al Por Menor)",
    "sg:phone":"+34 913 59 23 64",
    "sg:postcode":"28036",
    "sg:province":"Madrid",
    "wof:name":"Cacaca S.a.",
    "wof:placetype":"venue"
},
  "geometry": {"coordinates":[-3.6881554127,40.4619255066],"type":"Point"}
}