{
  "type": "Feature",
  "properties": {
    "iso:country":"ES",
    "sg:address":"Carrer de Rius I Carrio, 9",
    "sg:city":"Hospitalet Llobregat",
    "sg:orig_category":"Fabricaci\u00d3n De Ropa De Deportes",
    "sg:phone":"+34 933 33 82 51",
    "sg:postcode":"08904",
    "sg:province":"Barcelona",
    "wof:name":"Traditex S.a.",
    "wof:placetype":"venue"
},
  "geometry": {"coordinates":[2.1141328812,41.3740081787],"type":"Point"}
}