{
  "type": "Feature",
  "properties": {
    "iso:country":"ES",
    "sg:address":"Pg Comte De Vilardaga, 158",
    "sg:city":"Sant Feliu Llobregat",
    "sg:classifiers":[
        {
            "category":"Casinos & Gambling",
            "type":"Entertainment"
        }
    ],
    "sg:phone":"+34 936 85 55 00",
    "sg:postcode":"08980",
    "sg:province":"Barcelona",
    "sg:tags":[
        "locale",
        "de",
        "juego"
    ],
    "wof:name":"Emepejotate S.l",
    "wof:placetype":"venue"
},
  "geometry": {"coordinates":[2.0519099236,41.3860206604],"type":"Point"}
}