{
  "type": "Feature",
  "properties": {
    "addr:full":"Plaz San Francisco Javier/san Frantzisko Xabier Plaza, 4 Noain Navarra 31110",
    "addr:housenumber":"4",
    "addr:postcode":"31110",
    "addr:street":"Plaz;Frantzisko Xabier Plaza",
    "iso:country":"ES",
    "sg:address":"Plaz San Francisco Javier/san Frantzisko Xabier Plaza, 4",
    "sg:city":"Noain",
    "sg:orig_category":"Ropa Para Se\u00d1oras Y Caballeros (al Por Menor)",
    "sg:phone":"+34 948 31 71 55",
    "sg:postcode":"31110",
    "sg:province":"Navarra",
    "wof:name":"Jimenez Jimenez Ramon",
    "wof:placetype":"venue"
},
  "geometry": {"coordinates":[-1.6338239908,42.7598800659],"type":"Point"}
}