{
  "type": "Feature",
  "properties": {
    "iso:country":"ES",
    "sg:address":"Afueras, S/n",
    "sg:city":"Zaidin",
    "sg:orig_category":"Frutas Y Legumbres Frescas (al Por Mayor)",
    "sg:phone":"+34 974 47 85 29",
    "sg:postcode":"22530",
    "sg:province":"Huesca",
    "wof:name":"Frutas Ibarz E Hijos S.l.",
    "wof:placetype":"venue"
},
  "geometry": {"coordinates":[0.2638930082,41.6048355103],"type":"Point"}
}