{
  "type": "Feature",
  "properties": {
    "iso:country":"ES",
    "sg:address":"Carrer de Mossen Jacint Verdaguer, 205",
    "sg:city":"Sant Vicen\u00c7 Dels Horts",
    "sg:orig_category":"Zapatos (al Por Menor)",
    "sg:phone":"+34 936 76 99 41",
    "sg:postcode":"08620",
    "sg:province":"Barcelona",
    "wof:name":"Juan Gambin Dolores",
    "wof:placetype":"venue"
},
  "geometry": {"coordinates":[2.0068519115,41.3986091614],"type":"Point"}
}