{
  "type": "Feature",
  "properties": {
    "iso:country":"ES",
    "sg:address":"Pase Espolon, 18",
    "sg:city":"Burgos",
    "sg:orig_category":"Ropa Para Se\u00d1oras (al Por Menor)",
    "sg:phone":"+34 947 20 37 64",
    "sg:postcode":"09003",
    "sg:province":"Burgos",
    "wof:name":"Hijos De Simeon Garcia Y Compa\u00f1ia S. L.",
    "wof:placetype":"venue"
},
  "geometry": {"coordinates":[-3.7027568817,42.3401260376],"type":"Point"}
}