{
  "type": "Feature",
  "properties": {
    "iso:country":"ES",
    "sg:address":"Calle de Lepanto, 13",
    "sg:city":"Teulada",
    "sg:orig_category":"Supermercados Y Hipermercados",
    "sg:phone":"+34 965 74 02 97",
    "sg:postcode":"03725",
    "sg:province":"Alicante",
    "wof:name":"Buigues Salas Maria Rosa",
    "wof:placetype":"venue"
},
  "geometry": {"coordinates":[0.1061199978,38.7296104431],"type":"Point"}
}