{
  "type": "Feature",
  "properties": {
    "addr:full":"Carr Santa Eugenia, 75 Girona Girona 17006",
    "addr:housenumber":"75",
    "addr:postcode":"17006",
    "addr:street":"Carr Santa Eugenia",
    "iso:country":"ES",
    "sg:address":"Carr Santa Eugenia, 75",
    "sg:city":"Girona",
    "sg:orig_category":"Muebles Y Accesorios Para Cocinas Y Cuartos De Ba\u00d1o (al Por Menor)",
    "sg:phone":"+34 972 24 57 48",
    "sg:postcode":"17006",
    "sg:province":"Girona",
    "wof:name":"Prestener S.l.",
    "wof:placetype":"venue"
},
  "geometry": {"coordinates":[2.8097798824,41.978427887],"type":"Point"}
}