{
  "type": "Feature",
  "properties": {
    "iso:country":"ES",
    "sg:address":"Calle de Marcenado, 2",
    "sg:city":"Madrid",
    "sg:orig_category":"Asesor\u00cda Fiscal Y Jur\u00cddica",
    "sg:phone":"+34 914 13 77 60",
    "sg:postcode":"28002",
    "sg:province":"Madrid",
    "wof:name":"Yang  Mingde",
    "wof:placetype":"venue"
},
  "geometry": {"coordinates":[-3.6725509167,40.4453125],"type":"Point"}
}