{
  "type": "Feature",
  "properties": {
    "iso:country":"ES",
    "sg:address":"Rbla Doctor Pearson, 30",
    "sg:city":"Tremp",
    "sg:orig_category":"Bares, Piano",
    "sg:phone":"+34 973 65 18 68",
    "sg:postcode":"25620",
    "sg:province":"Lleida",
    "wof:name":"Castells Gaitano Isabel",
    "wof:placetype":"venue"
},
  "geometry": {"coordinates":[0.8936669827,42.1645278931],"type":"Point"}
}