{
  "type": "Feature",
  "properties": {
    "addr:full":"Calle de Andres Lopez Palmeiro, 28 Ferreira Lugo 27770",
    "addr:housenumber":"28",
    "addr:postcode":"27770",
    "addr:street":"Calle De Andres Lopez Palmeiro",
    "iso:country":"ES",
    "sg:address":"Calle de Andres Lopez Palmeiro, 28",
    "sg:city":"Ferreira",
    "sg:orig_category":"Loter\u00cda Y T\u00d3mbola",
    "sg:phone":"+34 982 57 44 15",
    "sg:postcode":"27770",
    "sg:province":"Lugo",
    "wof:name":"Arca Cela Marta",
    "wof:placetype":"venue"
},
  "geometry": {"coordinates":[-7.4817819595,43.5736885071],"type":"Point"}
}