{
  "type": "Feature",
  "properties": {
    "iso:country":"ES",
    "sg:address":"Avda Valentin Masip, 36",
    "sg:city":"Oviedo",
    "sg:orig_category":"Agencias Y Agentes Comerciales, Representantes",
    "sg:phone":"+34 985 23 23 97",
    "sg:postcode":"33013",
    "sg:province":"Asturias",
    "wof:name":"Laguna Fernandez Angel",
    "wof:placetype":"venue"
},
  "geometry": {"coordinates":[-5.8632779121,43.362663269],"type":"Point"}
}