{
  "type": "Feature",
  "properties": {
    "addr:full":"Av Costa Brava, 18 Sils Girona 17410",
    "addr:housenumber":"18",
    "addr:postcode":"17410",
    "addr:street":"Av Costa Brava",
    "iso:country":"ES",
    "sg:address":"Av Costa Brava, 18",
    "sg:city":"Sils",
    "sg:orig_category":"M\u00c9dicos: Estomatolog\u00cda",
    "sg:phone":"+34 972 16 84 34",
    "sg:postcode":"17410",
    "sg:province":"Girona",
    "wof:name":"Sole Santoll Neus",
    "wof:placetype":"venue"
},
  "geometry": {"coordinates":[2.7462980747,41.8086929321],"type":"Point"}
}