{
  "type": "Feature",
  "properties": {
    "addr:full":"Calle de Ricardo De La Cierva, 16 Poligono Industrial Los Villares Salamanca 37184",
    "addr:housenumber":"16",
    "addr:postcode":"37184",
    "addr:street":"Calle De Ricardo De La Cierva;Industrial",
    "iso:country":"ES",
    "sg:address":"Calle de Ricardo De La Cierva, 16",
    "sg:city":"Poligono Industrial Los Villares",
    "sg:orig_category":"Transportes Por Carretera: Lotes Completos, Mercanc\u00cdas Diversas",
    "sg:phone":"+34 923 23 50 35",
    "sg:postcode":"37184",
    "sg:province":"Salamanca",
    "wof:name":"Snack Ventures S.a.",
    "wof:placetype":"venue"
},
  "geometry": {"coordinates":[-5.6357440948,40.9907913208],"type":"Point"}
}