{
  "type": "Feature",
  "properties": {
    "addr:full":"Av Cardenal Vidal I Barraquer, 15 Tarragona Tarragona 43005",
    "addr:housenumber":"15",
    "addr:postcode":"43005",
    "addr:street":"Av Cardenal Vidal I Barraquer",
    "iso:country":"ES",
    "sg:address":"Av Cardenal Vidal I Barraquer, 15",
    "sg:city":"Tarragona",
    "sg:orig_category":"Medias Y Calcetines (al Por Menor)",
    "sg:phone":"+34 977 22 15 05",
    "sg:postcode":"43005",
    "sg:province":"Tarragona",
    "wof:name":"Sitoks S. L.",
    "wof:placetype":"venue"
},
  "geometry": {"coordinates":[1.2393440008,41.1172103882],"type":"Point"}
}