{
  "type": "Feature",
  "properties": {
    "iso:country":"ES",
    "sg:address":"Calle de Calvario, 13",
    "sg:city":"Pozuelo De Alarcon",
    "sg:orig_category":"Carnicer\u00cdas, Carnicer\u00cdas",
    "sg:phone":"+34 913 51 55 26",
    "sg:postcode":"28223",
    "sg:province":"Madrid",
    "wof:name":"Alvarez Cerde\u00f1o Cesar",
    "wof:placetype":"venue"
},
  "geometry": {"coordinates":[-3.8113732338,40.4343147278],"type":"Point"}
}