{
  "type": "Feature",
  "properties": {
    "iso:country":"ES",
    "sg:address":"Bda Viladecols, 3",
    "sg:city":"Barcelona",
    "sg:orig_category":"Ropa Para Se\u00d1oras Y Caballeros (al Por Menor)",
    "sg:phone":"+34 933 19 01 82",
    "sg:postcode":"08002",
    "sg:province":"Barcelona",
    "sg:website":"www.farm4.com",
    "wof:name":"Grau Santamaria Laura",
    "wof:placetype":"venue"
},
  "geometry": {"coordinates":[2.1796450615,41.3821220398],"type":"Point"}
}