{
  "type": "Feature",
  "properties": {
    "iso:country":"ES",
    "sg:address":"Calle de Franco Y Lopez, 32",
    "sg:city":"Zaragoza",
    "sg:orig_category":"Cristaler\u00cdas",
    "sg:phone":"+34 976 55 08 65",
    "sg:postcode":"50005",
    "sg:province":"Zaragoza",
    "wof:name":"Gracia Gracia Juan",
    "wof:placetype":"venue"
},
  "geometry": {"coordinates":[-0.9015740156,41.6477622986],"type":"Point"}
}