{
  "type": "Feature",
  "properties": {
    "iso:country":"ES",
    "sg:address":"Calle de Horno, 4",
    "sg:city":"Villamayor",
    "sg:orig_category":"Inform\u00c1tica, Ofim\u00c1tica (estudios, Asesor\u00cda, Ingenier\u00cda, Formaci\u00d3n)",
    "sg:phone":"+34 923 28 97 72",
    "sg:postcode":"37185",
    "sg:province":"Salamanca",
    "wof:name":"Zorita Viota Sanchez Francisco Javier",
    "wof:placetype":"venue"
},
  "geometry": {"coordinates":[-5.6962141991,40.9994735718],"type":"Point"}
}