{
  "type": "Feature",
  "properties": {
    "iso:country":"ES",
    "sg:address":"Carrer de Garganes, 1",
    "sg:city":"Altea",
    "sg:orig_category":"Institutos De Belleza",
    "sg:phone":"+34 966 88 18 73",
    "sg:postcode":"03590",
    "sg:province":"Alicante",
    "wof:name":"Perfect Siluete Altea S.l.",
    "wof:placetype":"venue"
},
  "geometry": {"coordinates":[-0.0469839983,38.6040687561],"type":"Point"}
}