{
  "type": "Feature",
  "properties": {
    "iso:country":"ES",
    "sg:address":"Ctra. Alqueria Condesa-piles, Km. 0005,0",
    "sg:city":"Piles",
    "sg:orig_category":"Poller\u00cda Y Caza (al Por Menor)",
    "sg:phone":"+34 962 83 15 74",
    "sg:postcode":"46712",
    "sg:province":"Valencia",
    "wof:name":"Marti Pru\u00f1onosa C.b.",
    "wof:placetype":"venue"
},
  "geometry": {"coordinates":[-0.1321340054,38.9415550232],"type":"Point"}
}