{
  "type": "Feature",
  "properties": {
    "iso:country":"ES",
    "sg:address":"Avda Vigo, S/n",
    "sg:city":"Pontevedra",
    "sg:orig_category":"Veh\u00cdculos De Ocasi\u00d3n",
    "sg:phone":"+34 986 84 14 61",
    "sg:postcode":"36003",
    "sg:province":"Pontevedra",
    "wof:name":"Fidauto S.l.",
    "wof:placetype":"venue"
},
  "geometry": {"coordinates":[-8.6395263672,42.4245681763],"type":"Point"}
}