{
  "type": "Feature",
  "properties": {
    "addr:full":"Calle de Iparraguirre, 4 Arrigorriaga Vizcaya 48480",
    "addr:housenumber":"4",
    "addr:postcode":"48480",
    "addr:street":"Calle De Iparraguirre",
    "iso:country":"ES",
    "sg:address":"Calle de Iparraguirre, 4",
    "sg:city":"Arrigorriaga",
    "sg:orig_category":"Lencer\u00cda Femenina, Corseter\u00cda, Trajes De Ba\u00d1o (al Por Menor)",
    "sg:phone":"+34 944 05 86 07",
    "sg:postcode":"48480",
    "sg:province":"Vizcaya",
    "wof:name":"Maria Bego\u00f1a Loro\u00f1o Izaguirre",
    "wof:placetype":"venue"
},
  "geometry": {"coordinates":[-2.8870620728,43.2079925537],"type":"Point"}
}