{
  "type": "Feature",
  "properties": {
    "addr:full":"Calle de Benahavis, 6 Malaga M\u00e1laga 29004",
    "addr:housenumber":"6",
    "addr:postcode":"29004",
    "addr:street":"Calle De Benahavis;Ma\u0301Laga",
    "iso:country":"ES",
    "sg:address":"Calle de Benahavis, 6",
    "sg:city":"Malaga",
    "sg:orig_category":"Condimentos, Especias, Vinagres, Salsas Preparadas (fabricaci\u00d3n, Al Por Mayor)",
    "sg:phone":"+34 952 24 05 70",
    "sg:postcode":"29004",
    "sg:province":"M\u00e1laga",
    "wof:name":"Manufacturas Ceylan S.l.",
    "wof:placetype":"venue"
},
  "geometry": {"coordinates":[-4.4650378227,36.6831169128],"type":"Point"}
}