{
  "type": "Feature",
  "properties": {
    "iso:country":"ES",
    "sg:address":"Calle de San Vicente Martir, 184",
    "sg:city":"Valencia",
    "sg:orig_category":"Expertos Contables Pasantes Autorizados",
    "sg:phone":"+34 963 41 83 26",
    "sg:postcode":"46007",
    "sg:province":"Valencia",
    "wof:name":"Palomar Cervello Jose Luis",
    "wof:placetype":"venue"
},
  "geometry": {"coordinates":[-0.3829489946,39.4602546692],"type":"Point"}
}