{
  "type": "Feature",
  "properties": {
    "addr:full":"Calle de Pavaneras, 3 Granada Granada 18009",
    "addr:housenumber":"3",
    "addr:postcode":"18009",
    "addr:street":"Calle De Pavaneras",
    "iso:country":"ES",
    "sg:address":"Calle de Pavaneras, 3",
    "sg:city":"Granada",
    "sg:orig_category":"Cajas De Ahorro",
    "sg:phone":"+34 958 22 34 04",
    "sg:postcode":"18009",
    "sg:province":"Granada",
    "wof:name":"Caixa D'estalvis I Pensions De Barcelona",
    "wof:placetype":"venue"
},
  "geometry": {"coordinates":[-3.5962278843,37.1754875183],"type":"Point"}
}