{
  "type": "Feature",
  "properties": {
    "iso:country":"ES",
    "sg:address":"Ctra General Mao - Ciutadella, 28",
    "sg:city":"Tudons",
    "sg:orig_category":"Zootecnia",
    "sg:phone":"+34 971 38 63 22",
    "sg:postcode":"07760",
    "sg:province":"Islas Baleares",
    "sg:website":"www.gobmenorca.com",
    "wof:name":"Grupo De Ornitologia Balear",
    "wof:placetype":"venue"
},
  "geometry": {"coordinates":[3.8382499218,39.9930915833],"type":"Point"}
}