{
  "type": "Feature",
  "properties": {
    "addr:full":"Camino De La Serradilla, S/n Plasencia C\u00e1ceres 10600",
    "addr:housenumber":"s",
    "addr:postcode":"10600",
    "addr:street":"Camino De La Serradilla;/ N;Ca\u0301Ceres",
    "iso:country":"ES",
    "sg:address":"Camino De La Serradilla, S/n",
    "sg:city":"Plasencia",
    "sg:orig_category":"Sales (al Por Mayor)",
    "sg:phone":"+34 927 42 37 96",
    "sg:postcode":"10600",
    "sg:province":"C\u00e1ceres",
    "wof:name":"Sediaco Scl",
    "wof:placetype":"venue"
},
  "geometry": {"coordinates":[-6.1000890732,40.0146064758],"type":"Point"}
}