{
  "type": "Feature",
  "properties": {
    "iso:country":"ES",
    "sg:address":"Avda Pardaleras, 18",
    "sg:city":"Badajoz",
    "sg:orig_category":"Farmacias",
    "sg:phone":"+34 924 20 50 81",
    "sg:postcode":"06003",
    "sg:province":"Badajoz",
    "wof:name":"Moreno Soler Antonia",
    "wof:placetype":"venue"
},
  "geometry": {"coordinates":[-6.9689688683,38.8733940125],"type":"Point"}
}