{
  "type": "Feature",
  "properties": {
    "iso:country":"ES",
    "sg:address":"Calle de Francisco Sempere, 2",
    "sg:city":"Valencia",
    "sg:orig_category":"Ense\u00d1ante, Direcci\u00d3n",
    "sg:phone":"+34 963 34 02 83",
    "sg:postcode":"46006",
    "sg:province":"Valencia",
    "wof:name":"Guillen Guillen Victor Manuel",
    "wof:placetype":"venue"
},
  "geometry": {"coordinates":[-0.3705640137,39.4604721069],"type":"Point"}
}