{
  "type": "Feature",
  "properties": {
    "iso:country":"ES",
    "sg:address":"Carrer de Emporda, 19",
    "sg:city":"S. Quirze Valles",
    "sg:orig_category":"Accesorios Para Operaciones Portuarias Y Stockage",
    "sg:phone":"+34 937 21 40 09",
    "sg:postcode":"08192",
    "sg:province":"Barcelona",
    "wof:name":"Dinalager S.l.",
    "wof:placetype":"venue"
},
  "geometry": {"coordinates":[2.0799469948,41.5400543213],"type":"Point"}
}