{
  "type": "Feature",
  "properties": {
    "iso:country":"ES",
    "sg:address":"Avda Rioja De (la), S/n",
    "sg:city":"Igea",
    "sg:orig_category":"Poller\u00cda Y Caza (al Por Menor)",
    "sg:phone":"+34 941 17 60 88",
    "sg:postcode":"26525",
    "sg:province":"La Rioja",
    "wof:name":"Saez Benito Saez De Guinda Manuel Santiago",
    "wof:placetype":"venue"
},
  "geometry": {"coordinates":[-2.009198904,42.0681915283],"type":"Point"}
}