{
  "type": "Feature",
  "properties": {
    "addr:full":"Calle de Galizia, 4 Arizgoiti Vizcaya 48970",
    "addr:housenumber":"4",
    "addr:postcode":"48970",
    "addr:street":"Calle De Galizia",
    "iso:country":"ES",
    "sg:address":"Calle de Galizia, 4",
    "sg:city":"Arizgoiti",
    "sg:orig_category":"Carnicer\u00cdas, Carnicer\u00cdas",
    "sg:phone":"+34 944 40 03 57",
    "sg:postcode":"48970",
    "sg:province":"Vizcaya",
    "wof:name":"Angulo Hermosilla Francisco Javier",
    "wof:placetype":"venue"
},
  "geometry": {"coordinates":[-2.8819983006,43.2359619141],"type":"Point"}
}