{
  "type": "Feature",
  "properties": {
    "iso:country":"ES",
    "sg:address":"Avgd Comte Serrallo, S/n",
    "sg:city":"Alcudia",
    "sg:orig_category":"Material Y Herramientas Agr\u00cdcolas",
    "sg:phone":"+34 962 99 75 59",
    "sg:postcode":"46250",
    "sg:province":"Valencia",
    "wof:name":"Herbas Mancho Jaime",
    "wof:placetype":"venue"
},
  "geometry": {"coordinates":[-0.5017077923,39.204334259],"type":"Point"}
}