{
  "type": "Feature",
  "properties": {
    "iso:country":"ES",
    "sg:address":"Calle de Monte (del), 13",
    "sg:city":"Alcorcon",
    "sg:orig_category":"Afilado",
    "sg:phone":"+34 916 12 95 58",
    "sg:postcode":"28921",
    "sg:province":"Madrid",
    "wof:name":"Sanz Hernanz Hortensia",
    "wof:placetype":"venue"
},
  "geometry": {"coordinates":[-3.8241629601,40.3479194641],"type":"Point"}
}