{
  "type": "Feature",
  "properties": {
    "addr:full":"Calle de Santa Maria De Gracia, 24 Camas Sevilla 41900",
    "addr:housenumber":"24",
    "addr:postcode":"41900",
    "addr:street":"Calle De Santa",
    "iso:country":"ES",
    "sg:address":"Calle de Santa Maria De Gracia, 24",
    "sg:city":"Camas",
    "sg:orig_category":"Ropa Para Se\u00d1oras Y Caballeros (al Por Menor)",
    "sg:phone":"+34 954 39 23 94",
    "sg:postcode":"41900",
    "sg:province":"Sevilla",
    "wof:name":"Garrido Torres Ana Beatriz",
    "wof:placetype":"venue"
},
  "geometry": {"coordinates":[-6.0350427628,37.4030456543],"type":"Point"}
}