{
  "type": "Feature",
  "properties": {
    "iso:country":"ES",
    "sg:address":"Pase Doctor Fleming Del, S/n",
    "sg:city":"Gijon",
    "sg:orig_category":"Ense\u00d1anza, Formaci\u00d3n Profesional: Aprendizaje",
    "sg:phone":"+34 985 37 04 94",
    "sg:postcode":"33203",
    "sg:province":"Asturias",
    "wof:name":"Patronato Deportivo Municipal De Gijon",
    "wof:placetype":"venue"
},
  "geometry": {"coordinates":[-5.6343650818,43.5359954834],"type":"Point"}
}