{
  "type": "Feature",
  "properties": {
    "iso:country":"ES",
    "sg:address":"Ctra Mara\u00d1osa (la), Km. 0004,8",
    "sg:city":"Pinto",
    "sg:orig_category":"Reciclaje Y Tratamiento De Desechos Varios",
    "sg:phone":"+34 916 92 43 03",
    "sg:postcode":"28320",
    "sg:province":"Madrid",
    "wof:name":"Gestion Y Desarrollo Del Medio Ambiente De Madrid S.a.",
    "wof:placetype":"venue"
},
  "geometry": {"coordinates":[-3.6894741058,40.2468147278],"type":"Point"}
}