{
  "type": "Feature",
  "properties": {
    "addr:full":"Pg Ribera, 23 Barriada Nova Barcelona 08420",
    "addr:housenumber":"23",
    "addr:postcode":"08420",
    "addr:street":"Ribera;Nova Barcelona",
    "iso:country":"ES",
    "sg:address":"Pg Ribera, 23",
    "sg:city":"Barriada Nova",
    "sg:orig_category":"Tapicer\u00cdas",
    "sg:phone":"+34 938 49 13 60",
    "sg:postcode":"08420",
    "sg:province":"Barcelona",
    "wof:name":"Mas De Interiorismo Granollerense S.l.",
    "wof:placetype":"venue"
},
  "geometry": {"coordinates":[2.2780098915,41.6220703125],"type":"Point"}
}