{
  "type": "Feature",
  "properties": {
    "iso:country":"ES",
    "sg:address":"Plaza Gurutzeko",
    "sg:city":"Galdakao",
    "sg:orig_category":"Ense\u00d1anza, Formaci\u00d3n Profesional: Aprendizaje",
    "sg:phone":"+34 944 01 05 00",
    "sg:postcode":"48960",
    "sg:province":"Vizcaya",
    "wof:name":"Ayuntamiento De Galdakao",
    "wof:placetype":"venue"
},
  "geometry": {"coordinates":[-2.8398373127,43.2313308716],"type":"Point"}
}