{
  "type": "Feature",
  "properties": {
    "iso:country":"ES",
    "sg:address":"Calle de Ruda, 11",
    "sg:city":"Madrid",
    "sg:orig_category":"Ropa Para Ni\u00d1os (al Por Menor)",
    "sg:phone":"+34 913 65 00 86",
    "sg:postcode":"28005",
    "sg:province":"Madrid",
    "wof:name":"Ahmed Khan Tahir",
    "wof:placetype":"venue"
},
  "geometry": {"coordinates":[-3.7080452442,40.4104804993],"type":"Point"}
}