{
  "type": "Feature",
  "properties": {
    "addr:full":"Carrer de Congost, 10 Barcelona Barcelona 08024",
    "addr:housenumber":"10",
    "addr:postcode":"08024",
    "addr:street":"Carrer De Congost",
    "iso:country":"ES",
    "sg:address":"Carrer de Congost, 10",
    "sg:city":"Barcelona",
    "sg:orig_category":"Peluquer\u00cdas, Peluquer\u00cda Mixta",
    "sg:phone":"+34 932 19 27 39",
    "sg:postcode":"08024",
    "sg:province":"Barcelona",
    "wof:name":"Alca\u00f1iz Zapater Teresa Maria",
    "wof:placetype":"venue"
},
  "geometry": {"coordinates":[2.1579477787,41.4059677124],"type":"Point"}
}