{
  "type": "Feature",
  "properties": {
    "addr:full":"Rua Principe, 13 Cambados Pontevedra 36630",
    "addr:housenumber":"13",
    "addr:postcode":"36630",
    "addr:street":"Rua Principe",
    "iso:country":"ES",
    "sg:address":"Rua Principe, 13",
    "sg:city":"Cambados",
    "sg:orig_category":"Alquiler De V\u00cddeo",
    "sg:phone":"+34 986 54 36 22",
    "sg:postcode":"36630",
    "sg:province":"Pontevedra",
    "wof:name":"Pi\u00f1eiro Duran Manuel",
    "wof:placetype":"venue"
},
  "geometry": {"coordinates":[-8.8144350052,42.5170707703],"type":"Point"}
}