{
  "type": "Feature",
  "properties": {
    "iso:country":"ES",
    "sg:address":"Ctra Prat, 32",
    "sg:city":"Almeda Mercader",
    "sg:orig_category":"Mec\u00c1nica General",
    "sg:phone":"+34 902 25 22 09",
    "sg:postcode":"08940",
    "sg:province":"Barcelona",
    "sg:website":"www.ascensoreseninter.com",
    "wof:name":"Ascensores Eninter S.l.",
    "wof:placetype":"venue"
},
  "geometry": {"coordinates":[2.0771648884,41.3512535095],"type":"Point"}
}