{
  "type": "Feature",
  "properties": {
    "iso:country":"ES",
    "sg:address":"Avda Pasaje, 5",
    "sg:city":"Coru\u00d1a",
    "sg:orig_category":"Empresas De Carpinter\u00cda De Madera",
    "sg:phone":"+34 981 13 23 49",
    "sg:postcode":"15006",
    "sg:province":"La Coru\u00f1a",
    "wof:name":"Mendez Vazquez Dionisio Eloy",
    "wof:placetype":"venue"
},
  "geometry": {"coordinates":[-8.3844385147,43.3317222595],"type":"Point"}
}