{
  "type": "Feature",
  "properties": {
    "addr:full":"Luga Paul Diseminado (la), S/n Abadilla Cantabria 39694",
    "addr:postcode":"39694",
    "addr:street":"Diseminado La S / N",
    "iso:country":"ES",
    "sg:address":"Luga Paul Diseminado (la), S/n",
    "sg:city":"Abadilla",
    "sg:orig_category":"Cr\u00cda De Animales",
    "sg:phone":"+34 942 56 36 64",
    "sg:postcode":"39694",
    "sg:province":"Cantabria",
    "wof:name":"S.a.t. Saype-la Paul",
    "wof:placetype":"venue"
},
  "geometry": {"coordinates":[-3.8536090851,43.3093032837],"type":"Point"}
}