{
  "type": "Feature",
  "properties": {
    "iso:country":"ES",
    "sg:address":"Avda Constitucion, 26",
    "sg:city":"Onil",
    "sg:orig_category":"Electricidad, Electr\u00d3nica: Suministros (al Por Menor)",
    "sg:phone":"+34 965 56 50 25",
    "sg:postcode":"03430",
    "sg:province":"Alicante",
    "wof:name":"Electronica Onil S.l.",
    "wof:placetype":"venue"
},
  "geometry": {"coordinates":[-0.6756309867,38.623840332],"type":"Point"}
}