{
  "type": "Feature",
  "properties": {
    "iso:country":"ES",
    "sg:address":"Calle de Viena, 2",
    "sg:city":"Caceres",
    "sg:orig_category":"Abogados",
    "sg:phone":"+34 927 24 19 34",
    "sg:postcode":"10001",
    "sg:province":"C\u00e1ceres",
    "wof:name":"Velazquez Garcia Jaime",
    "wof:placetype":"venue"
},
  "geometry": {"coordinates":[-6.381939888,39.4725532532],"type":"Point"}
}