{
  "type": "Feature",
  "properties": {
    "iso:country":"ES",
    "sg:address":"Calle de Valencia, 56",
    "sg:city":"Quintanar Orden",
    "sg:orig_category":"Licores (fabricaci\u00d3n, Al Por Mayor)",
    "sg:phone":"+34 925 18 01 54",
    "sg:postcode":"45800",
    "sg:province":"Toledo",
    "wof:name":"Hijos De Francisco Serrano S. A.",
    "wof:placetype":"venue"
},
  "geometry": {"coordinates":[-3.0380020142,39.5880737305],"type":"Point"}
}