{
  "type": "Feature",
  "properties": {
    "iso:country":"ES",
    "sg:address":"Rua Paz, 19",
    "sg:city":"Pobra Do Carami\u00e7al",
    "sg:orig_category":"Panader\u00cdas, Panader\u00cdas",
    "sg:phone":"+34 981 83 13 73",
    "sg:postcode":"15940",
    "sg:province":"La Coru\u00f1a",
    "wof:name":"Mui\u00f1os Casais Juan Manuel",
    "wof:placetype":"venue"
},
  "geometry": {"coordinates":[-8.9384536743,42.6052474976],"type":"Point"}
}