{
  "type": "Feature",
  "properties": {
    "iso:country":"ES",
    "sg:address":"Rbla Sant Nebridi, 45",
    "sg:city":"Terrassa",
    "sg:orig_category":"Caf\u00c9s, Bares, Cervecer\u00cdas",
    "sg:phone":"+34 937 31 19 73",
    "sg:postcode":"08222",
    "sg:province":"Barcelona",
    "wof:name":"Arcadia Futura S.l.",
    "wof:placetype":"venue"
},
  "geometry": {"coordinates":[2.0212318897,41.5604286194],"type":"Point"}
}