{
  "type": "Feature",
  "properties": {
    "addr:full":"Ventas, S/n Muniesa Teruel 44780",
    "addr:housenumber":"/ n",
    "addr:postcode":"44780",
    "addr:street":"S",
    "iso:country":"ES",
    "sg:address":"Ventas, S/n",
    "sg:city":"Muniesa",
    "sg:orig_category":"Producci\u00d3n, Venta De Productos De Agricultura Biol\u00d3gica",
    "sg:phone":"+34 978 72 90 01",
    "sg:postcode":"44780",
    "sg:province":"Teruel",
    "wof:name":"Soginland Cinegetica S.l.",
    "wof:placetype":"venue"
},
  "geometry": {"coordinates":[-0.8121939898,41.032623291],"type":"Point"}
}