{
  "type": "Feature",
  "properties": {
    "iso:country":"ES",
    "sg:address":"Pl Virreina, S/n",
    "sg:city":"Barcelona",
    "sg:orig_category":"Iglesia Cat\u00d3lica",
    "sg:phone":"+34 932 37 73 58",
    "sg:postcode":"08024",
    "sg:province":"Barcelona",
    "wof:name":"Parroquia De San Juan De Gracia",
    "wof:placetype":"venue"
},
  "geometry": {"coordinates":[2.1574149132,41.4050216675],"type":"Point"}
}