{
  "type": "Feature",
  "properties": {
    "addr:full":"Plaz Hipolito Bitrian, 1 Binefar Huesca 22500",
    "addr:housenumber":"1",
    "addr:postcode":"22500",
    "addr:street":"Bitrian",
    "iso:country":"ES",
    "sg:address":"Plaz Hipolito Bitrian, 1",
    "sg:city":"Binefar",
    "sg:orig_category":"Ense\u00d1anza Secundaria: Colegios Y Escuelas Privadas",
    "sg:phone":"+34 974 42 82 95",
    "sg:postcode":"22500",
    "sg:province":"Huesca",
    "wof:name":"Ies Sierra De San Quilez",
    "wof:placetype":"venue"
},
  "geometry": {"coordinates":[0.2891890109,41.8544387817],"type":"Point"}
}