{
  "type": "Feature",
  "properties": {
    "addr:full":"Av Sant Vicen\u00c7, 49 Vendrell Tarragona 43700",
    "addr:housenumber":"49",
    "addr:postcode":"43700",
    "addr:street":"Av Sant Vicenc\u0327",
    "iso:country":"ES",
    "sg:address":"Av Sant Vicen\u00c7, 49",
    "sg:city":"Vendrell",
    "sg:orig_category":"Art\u00cdculos De Decoraci\u00d3n",
    "sg:phone":"+34 977 66 81 93",
    "sg:postcode":"43700",
    "sg:province":"Tarragona",
    "wof:name":"Botigues Punt De Les Pintures S.l.",
    "wof:placetype":"venue"
},
  "geometry": {"coordinates":[1.5344270468,41.214641571],"type":"Point"}
}