{
  "type": "Feature",
  "properties": {
    "addr:full":"Via Augusta, 253 Barcelona Barcelona 08017",
    "addr:housenumber":"253",
    "addr:postcode":"08017",
    "addr:street":"Via Augusta",
    "iso:country":"ES",
    "sg:address":"Via Augusta, 253",
    "sg:city":"Barcelona",
    "sg:orig_category":"Centros Empresariales",
    "sg:phone":"+34 932 00 83 40",
    "sg:postcode":"08017",
    "sg:province":"Barcelona",
    "wof:name":"Tobias Lopez Jose",
    "wof:placetype":"venue"
},
  "geometry": {"coordinates":[2.1336970329,41.3976402283],"type":"Point"}
}