{
  "type": "Feature",
  "properties": {
    "addr:full":"Calle de San Amado, 32 Fortuna Madrid 28917",
    "addr:housenumber":"32",
    "addr:postcode":"28917",
    "addr:street":"Calle De San Amado",
    "iso:country":"ES",
    "sg:address":"Calle de San Amado, 32",
    "sg:city":"Fortuna",
    "sg:orig_category":"Revestimiento De Suelos Industriales",
    "sg:phone":"+34 916 42 71 27",
    "sg:postcode":"28917",
    "sg:province":"Madrid",
    "wof:name":"Soleras Vela S.l.l.",
    "wof:placetype":"venue"
},
  "geometry": {"coordinates":[-3.7790985107,40.356967926],"type":"Point"}
}