{
  "type": "Feature",
  "properties": {
    "addr:full":"Carr Vall, 60 Cullera Valencia 46400",
    "addr:housenumber":"60",
    "addr:postcode":"46400",
    "addr:street":"Carr Vall",
    "iso:country":"ES",
    "sg:address":"Carr Vall, 60",
    "sg:city":"Cullera",
    "sg:orig_category":"Audiovisuales: Material Y Accesorios (al Por Menor)",
    "sg:phone":"+34 961 72 37 35",
    "sg:postcode":"46400",
    "sg:province":"Valencia",
    "sg:website":"www.gafasdesol.cc",
    "wof:name":"Argente Sancho Jose Vicente",
    "wof:placetype":"venue"
},
  "geometry": {"coordinates":[-0.2501558065,39.1627845764],"type":"Point"}
}