{
  "type": "Feature",
  "properties": {
    "addr:full":"Calle de San Salvador, 5 Huelva Huelva 21003",
    "addr:housenumber":"5",
    "addr:postcode":"21003",
    "addr:street":"Calle De San Salvador",
    "iso:country":"ES",
    "sg:address":"Calle de San Salvador, 5",
    "sg:city":"Huelva",
    "sg:orig_category":"Administradores De Bienes Y Delegados De Comunidades De Propietarios",
    "sg:phone":"+34 959 28 12 75",
    "sg:postcode":"21003",
    "sg:province":"Huelva",
    "wof:name":"Jimeno Rodriguez Jesus",
    "wof:placetype":"venue"
},
  "geometry": {"coordinates":[-6.9481258392,37.2561073303],"type":"Point"}
}