{
  "type": "Feature",
  "properties": {
    "addr:full":"Crt. Albacete, Km. 0098,5 Villapalacios Albacete 02350",
    "addr:postcode":"02350",
    "addr:street":"Albacete Km. 0098,5",
    "iso:country":"ES",
    "sg:address":"Crt. Albacete, Km. 0098,5",
    "sg:city":"Villapalacios",
    "sg:orig_category":"Albergues",
    "sg:phone":"+34 967 39 81 34",
    "sg:postcode":"02350",
    "sg:province":"Albacete",
    "wof:name":"Rodenas Rodriguez Juan Pedro",
    "wof:placetype":"venue"
},
  "geometry": {"coordinates":[-2.6283359528,38.5771026611],"type":"Point"}
}