{
  "type": "Feature",
  "properties": {
    "iso:country":"ES",
    "sg:address":"Avgd Alcalde Areny, 30",
    "sg:city":"Lleida",
    "sg:orig_category":"Centros Empresariales",
    "sg:phone":"+34 973 28 80 97",
    "sg:postcode":"25002",
    "sg:province":"Lleida",
    "wof:name":"Baxi Roca Calefaccion S.l.",
    "wof:placetype":"venue"
},
  "geometry": {"coordinates":[0.6190320253,41.6078224182],"type":"Point"}
}