{
  "type": "Feature",
  "properties": {
    "iso:country":"ES",
    "sg:address":"Calle de Camichi, 33",
    "sg:city":"Madrid",
    "sg:orig_category":"Arreglo, Reparaci\u00d3n, Piezas Sueltas De Televisi\u00d3n, V\u00cddeo, Hi",
    "sg:phone":"+34 914 61 56 91",
    "sg:postcode":"28025",
    "sg:province":"Madrid",
    "wof:name":"Alonso Fra Jose Vicente",
    "wof:placetype":"venue"
},
  "geometry": {"coordinates":[-3.7425966263,40.3904762268],"type":"Point"}
}