{
  "type": "Feature",
  "properties": {
    "addr:full":"Calle de Majadahonda, 5 Ventorro Del Cano Madrid 28925",
    "addr:housenumber":"5",
    "addr:postcode":"28925",
    "addr:street":"Calle De Majadahonda",
    "iso:country":"ES",
    "sg:address":"Calle de Majadahonda, 5",
    "sg:city":"Ventorro Del Cano",
    "sg:orig_category":"Cerrajer\u00cda, Ferrallista",
    "sg:phone":"+34 916 32 19 36",
    "sg:postcode":"28925",
    "sg:province":"Madrid",
    "wof:name":"Espaseme S. A.",
    "wof:placetype":"venue"
},
  "geometry": {"coordinates":[-3.8364980221,40.3946647644],"type":"Point"}
}