{
  "type": "Feature",
  "properties": {
    "iso:country":"ES",
    "sg:address":"Rua Rio Arnoia, S/n",
    "sg:city":"Xinzo De Limia",
    "sg:orig_category":"Equipo De Refrigeraci\u00d3n Industrial",
    "sg:phone":"+34 988 46 29 38",
    "sg:postcode":"32630",
    "sg:province":"Ourense",
    "wof:name":"Dalama Blanco Jose Francisco",
    "wof:placetype":"venue"
},
  "geometry": {"coordinates":[-7.7259988785,42.0600204468],"type":"Point"}
}