{
  "type": "Feature",
  "properties": {
    "iso:country":"ES",
    "sg:address":"Rua Campo De La Compa\u00d1ia, 14",
    "sg:city":"Monforte De Lemos",
    "sg:orig_category":"Asesor\u00cda Fiscal Y Jur\u00cddica",
    "sg:phone":"+34 982 41 05 29",
    "sg:postcode":"27400",
    "sg:province":"Lugo",
    "wof:name":"Asesoria Eiriz S.l.",
    "wof:placetype":"venue"
},
  "geometry": {"coordinates":[-7.5030670166,42.5207214355],"type":"Point"}
}