{
  "type": "Feature",
  "properties": {
    "addr:full":"Carrer de Dolors Masferrer I Bosch, 36 Barcelona Barcelona 08028",
    "addr:housenumber":"36",
    "addr:postcode":"08028",
    "addr:street":"Carrer De Dolors Masferrer I Bosch",
    "iso:country":"ES",
    "sg:address":"Carrer de Dolors Masferrer I Bosch, 36",
    "sg:city":"Barcelona",
    "sg:orig_category":"Fabricaci\u00d3n De Art\u00cdculos Y Equipos Deportivos Y De Ocio",
    "sg:phone":"+34 934 09 10 20",
    "sg:postcode":"08028",
    "sg:province":"Barcelona",
    "wof:name":"Llinas Ferrer Jose Maria",
    "wof:placetype":"venue"
},
  "geometry": {"coordinates":[2.1277329922,41.3850593567],"type":"Point"}
}