{
  "type": "Feature",
  "properties": {
    "addr:full":"Calle de Farones, 1 Pe\u00f1iscola Castell\u00f3n 12598",
    "addr:housenumber":"1",
    "addr:postcode":"12598",
    "addr:street":"Calle De Farones;Castello\u0301N",
    "iso:country":"ES",
    "sg:address":"Calle de Farones, 1",
    "sg:city":"Pe\u00f1iscola",
    "sg:orig_category":"Art\u00cdculos De Regalo (al Por Menor)",
    "sg:phone":"+34 964 48 09 89",
    "sg:postcode":"12598",
    "sg:province":"Castell\u00f3n",
    "wof:name":"Roig Martinez Francisca",
    "wof:placetype":"venue"
},
  "geometry": {"coordinates":[-0.0456800014,39.9851417542],"type":"Point"}
}