{
  "type": "Feature",
  "properties": {
    "iso:country":"ES",
    "sg:address":"Carr Pio Xii, 2",
    "sg:city":"Quart Poblet",
    "sg:orig_category":"Puertas Y Portales",
    "sg:phone":"+34 961 54 89 52",
    "sg:postcode":"46930",
    "sg:province":"Valencia",
    "wof:name":"Miras Gallego Juan",
    "wof:placetype":"venue"
},
  "geometry": {"coordinates":[-0.4407519996,39.4814033508],"type":"Point"}
}