{
  "type": "Feature",
  "properties": {
    "iso:country":"ES",
    "sg:address":"Calle de Coso, 180",
    "sg:city":"Zaragoza",
    "sg:orig_category":"Papeler\u00cdas, Librer\u00cdas",
    "sg:phone":"+34 976 20 19 54",
    "sg:postcode":"50002",
    "sg:province":"Zaragoza",
    "wof:name":"Iba\u00f1ez Albiol Maria Jesus",
    "wof:placetype":"venue"
},
  "geometry": {"coordinates":[-0.8725876212,41.6524581909],"type":"Point"}
}