{
  "type": "Feature",
  "properties": {
    "iso:country":"ES",
    "sg:address":"Avda Baron De Carcer, 17",
    "sg:city":"Valencia",
    "sg:orig_category":"Centros Empresariales",
    "sg:phone":"+34 963 52 21 76",
    "sg:postcode":"46001",
    "sg:province":"Valencia",
    "sg:website":"www.fvet.es",
    "wof:name":"Federacion Valenciana De Empresarios Transportistas De Servico Publico",
    "wof:placetype":"venue"
},
  "geometry": {"coordinates":[-0.3796600103,39.472694397],"type":"Point"}
}