{
  "type": "Feature",
  "properties": {
    "addr:full":"Calle de Serrano, 82 Madrid Madrid 28006",
    "addr:housenumber":"82",
    "addr:postcode":"madrid;28006",
    "addr:street":"Calle De Serrano",
    "iso:country":"ES",
    "sg:address":"Calle de Serrano, 82",
    "sg:city":"Madrid",
    "sg:orig_category":"Centros De Coordinaci\u00d3n",
    "sg:phone":"+34 917 81 10 99",
    "sg:postcode":"28006",
    "sg:province":"Madrid",
    "wof:name":"Jm Cainzos & Asociados S.l.",
    "wof:placetype":"venue"
},
  "geometry": {"coordinates":[-3.6868104935,40.4312820435],"type":"Point"}
}