{
  "type": "Feature",
  "properties": {
    "addr:full":"Calle de San Jeronimo, 17 Donostia-san Sebastian Guip\u00f9zcoa 20003",
    "addr:housenumber":"17",
    "addr:postcode":"20003",
    "addr:street":"Calle De San Jeronimo",
    "iso:country":"ES",
    "sg:address":"Calle de San Jeronimo, 17",
    "sg:city":"Donostia-san Sebastian",
    "sg:orig_category":"Telas Y Sedas (al Por Menor)",
    "sg:phone":"+34 943 43 02 55",
    "sg:postcode":"20003",
    "sg:province":"Guip\u00f9zcoa",
    "wof:name":"Irune Lasa  Rementeria",
    "wof:placetype":"venue"
},
  "geometry": {"coordinates":[-1.9854960442,43.323135376],"type":"Point"}
}