{
  "type": "Feature",
  "properties": {
    "iso:country":"ES",
    "sg:address":"Carr Jerez De La Frontera, 7",
    "sg:city":"Badalona",
    "sg:orig_category":"Carnicer\u00cdas, Carnicer\u00cdas",
    "sg:phone":"+34 933 88 17 83",
    "sg:postcode":"08918",
    "sg:province":"Barcelona",
    "wof:name":"Barranco Vasco Antonio",
    "wof:placetype":"venue"
},
  "geometry": {"coordinates":[2.2249679565,41.4339561462],"type":"Point"}
}