{
  "type": "Feature",
  "properties": {
    "iso:country":"ES",
    "sg:address":"Calle de Obispo Rocamora, 13",
    "sg:city":"Orihuela",
    "sg:orig_category":"Procuradores",
    "sg:phone":"+34 966 74 26 75",
    "sg:postcode":"03300",
    "sg:province":"Alicante",
    "wof:name":"Esquer Montoya Francisco Luis",
    "wof:placetype":"venue"
},
  "geometry": {"coordinates":[-0.9439719915,38.0839080811],"type":"Point"}
}