{
  "type": "Feature",
  "properties": {
    "iso:country":"ES",
    "sg:address":"Chapitela-txapitela Kalea, 13",
    "sg:city":"Iru\u00f1a",
    "sg:orig_category":"Abogados",
    "sg:phone":"+34 948 21 30 63",
    "sg:postcode":"31001",
    "sg:province":"Navarra",
    "wof:name":"Diaz De Cerio Diez Maria Carmen",
    "wof:placetype":"venue"
},
  "geometry": {"coordinates":[-1.6429009438,42.8179702759],"type":"Point"}
}