{
  "type": "Feature",
  "properties": {
    "iso:country":"ES",
    "sg:address":"Calle de Sevilla, S/n",
    "sg:city":"Bailen",
    "sg:orig_category":"Empresas De Carpinter\u00cda Met\u00c1lica",
    "sg:phone":"+34 953 67 11 20",
    "sg:postcode":"23710",
    "sg:province":"Ja\u00e9n",
    "wof:name":"Olias Escuin Francisco",
    "wof:placetype":"venue"
},
  "geometry": {"coordinates":[-3.7789280415,38.0936584473],"type":"Point"}
}