{
  "type": "Feature",
  "properties": {
    "addr:full":"Calle de Marroquina, 51 Madrid Madrid 28030",
    "addr:housenumber":"51",
    "addr:postcode":"madrid;28030",
    "addr:street":"Calle De Marroquina",
    "iso:country":"ES",
    "sg:address":"Calle de Marroquina, 51",
    "sg:city":"Madrid",
    "sg:orig_category":"Empresarios Y Productoras De Espect\u00c1culos",
    "sg:phone":"+34 914 39 92 84",
    "sg:postcode":"28030",
    "sg:province":"Madrid",
    "wof:name":"Teruel Gonzalez Jose Augusto",
    "wof:placetype":"venue"
},
  "geometry": {"coordinates":[-3.6470050812,40.4098510742],"type":"Point"}
}