{
  "type": "Feature",
  "properties": {
    "iso:country":"ES",
    "sg:address":"Urb. Golf Girona, 9",
    "sg:city":"S. Julia Ramis",
    "sg:orig_category":"Productos Qu\u00cdmicos (fabricaci\u00d3n, Al Por Mayor)",
    "sg:phone":"+34 972 17 27 88",
    "sg:postcode":"17481",
    "sg:province":"Girona",
    "wof:name":"Entwasser Comercial Productos Quimicos S.l.",
    "wof:placetype":"venue"
},
  "geometry": {"coordinates":[2.8267281055,42.0239982605],"type":"Point"}
}