{
  "type": "Feature",
  "properties": {
    "iso:country":"ES",
    "sg:address":"Calle de San Gregorio (de), 26",
    "sg:city":"Galapagar",
    "sg:orig_category":"Peleter\u00cdas",
    "sg:phone":"+34 918 58 52 68",
    "sg:postcode":"28260",
    "sg:province":"Madrid",
    "wof:name":"Hervas Bustamante Isabel",
    "wof:placetype":"venue"
},
  "geometry": {"coordinates":[-4.0028557777,40.5795478821],"type":"Point"}
}