{
  "type": "Feature",
  "properties": {
    "iso:country":"ES",
    "sg:address":"Calle de Francisco De Goya, 14",
    "sg:city":"Velez-malaga",
    "sg:orig_category":"Inform\u00c1tica Equipo Y Programas (al Por Mayor)",
    "sg:phone":"+34 952 54 92 30",
    "sg:postcode":"29700",
    "sg:province":"M\u00e1laga",
    "wof:name":"Grupo Informatico Ragus S.l.",
    "wof:placetype":"venue"
},
  "geometry": {"coordinates":[-4.0971889496,36.7648696899],"type":"Point"}
}