{
  "type": "Feature",
  "properties": {
    "addr:full":"Barr Iglesia (la), S/n Hazas Cesto Cantabria 39738",
    "addr:housenumber":"s",
    "addr:postcode":"39738",
    "addr:street":"/ N",
    "iso:country":"ES",
    "sg:address":"Barr Iglesia (la), S/n",
    "sg:city":"Hazas Cesto",
    "sg:orig_category":"T\u00c9cnicos Veterinarios",
    "sg:phone":"+34 942 63 50 65",
    "sg:postcode":"39738",
    "sg:province":"Cantabria",
    "wof:name":"Alonso Fernandez Calixto",
    "wof:placetype":"venue"
},
  "geometry": {"coordinates":[-3.9878427982,43.1828384399],"type":"Point"}
}