{
  "type": "Feature",
  "properties": {
    "addr:full":"Ctra Montcada, 664 Terrassa Barcelona 08223",
    "addr:housenumber":"664",
    "addr:postcode":"08223",
    "addr:street":"Ctra Montcada",
    "iso:country":"ES",
    "sg:address":"Ctra Montcada, 664",
    "sg:city":"Terrassa",
    "sg:orig_category":"Iglesias Evang\u00c9licas",
    "sg:phone":"+34 937 31 71 23",
    "sg:postcode":"08223",
    "sg:province":"Barcelona",
    "wof:name":"Garcia Tomas Jose",
    "wof:placetype":"venue"
},
  "geometry": {"coordinates":[2.0325798988,41.5578956604],"type":"Point"}
}