{
  "type": "Feature",
  "properties": {
    "iso:country":"ES",
    "sg:address":"Rua Corporaciones Municipales, 22",
    "sg:city":"Foz",
    "sg:orig_category":"Molduras, Junquillos, Listones Y Molduras Perforadas",
    "sg:phone":"+34 982 14 17 70",
    "sg:postcode":"27780",
    "sg:province":"Lugo",
    "wof:name":"Veiga Rey Angeles",
    "wof:placetype":"venue"
},
  "geometry": {"coordinates":[-7.2566461563,43.5715522766],"type":"Point"}
}