{
  "type": "Feature",
  "properties": {
    "addr:full":"Calle de Real, 5 San Sebastian De Los Reyes Madrid 28700",
    "addr:housenumber":"5",
    "addr:postcode":"28700",
    "addr:street":"Calle De Real",
    "iso:country":"ES",
    "sg:address":"Calle de Real, 5",
    "sg:city":"San Sebastian De Los Reyes",
    "sg:orig_category":"Pescader\u00cdas (al Por Menor)",
    "sg:phone":"+34 916 54 16 64",
    "sg:postcode":"28700",
    "sg:province":"Madrid",
    "wof:name":"Geijo Casado Francisco",
    "wof:placetype":"venue"
},
  "geometry": {"coordinates":[-3.6282999516,40.5447387695],"type":"Point"}
}