{
  "type": "Feature",
  "properties": {
    "addr:full":"Av Catalunya, 44 Cerdanyola Valles Barcelona 08290",
    "addr:housenumber":"44",
    "addr:postcode":"08290",
    "addr:street":"Av Catalunya;Valles Barcelona",
    "iso:country":"ES",
    "sg:address":"Av Catalunya, 44",
    "sg:city":"Cerdanyola Valles",
    "sg:orig_category":"Zapatos (al Por Menor)",
    "sg:phone":"+34 935 80 74 84",
    "sg:postcode":"08290",
    "sg:province":"Barcelona",
    "wof:name":"Romero Ripolles S.l.",
    "wof:placetype":"venue"
},
  "geometry": {"coordinates":[2.1470150948,41.4924812317],"type":"Point"}
}