{
  "type": "Feature",
  "properties": {
    "addr:full":"Estda. De Vilardevos, 80 Rios Ourense 32611",
    "addr:housenumber":"80",
    "addr:postcode":"32611",
    "addr:street":"Rios Ourense",
    "iso:country":"ES",
    "sg:address":"Estda. De Vilardevos, 80",
    "sg:city":"Rios",
    "sg:orig_category":"Asilos De Ancianos. Centros Privados",
    "sg:phone":"+34 988 42 52 13",
    "sg:postcode":"32611",
    "sg:province":"Ourense",
    "wof:name":"Blanco Barja Maria Teresa",
    "wof:placetype":"venue"
},
  "geometry": {"coordinates":[-7.2824020386,41.9763145447],"type":"Point"}
}