{
  "type": "Feature",
  "properties": {
    "iso:country":"ES",
    "sg:address":"Calle de Ambite, 2",
    "sg:city":"Alcala Henares",
    "sg:orig_category":"Abogados",
    "sg:phone":"+34 918 82 81 45",
    "sg:postcode":"28806",
    "sg:province":"Madrid",
    "wof:name":"Mu\u00f1oz Mu\u00f1oz Sebastian-ezequiel",
    "wof:placetype":"venue"
},
  "geometry": {"coordinates":[-3.3682880402,40.490436554],"type":"Point"}
}