{
  "type": "Feature",
  "properties": {
    "iso:country":"ES",
    "sg:address":"C/ Gregori Casasempere Juan, 8",
    "sg:city":"Alcoi",
    "sg:orig_category":"Molduras, Junquillos, Listones Y Molduras Perforadas",
    "sg:phone":"+34 965 33 10 56",
    "sg:postcode":"03802",
    "sg:province":"Alicante",
    "wof:name":"Quintanilla Lopez Diego",
    "wof:placetype":"venue"
},
  "geometry": {"coordinates":[-0.4854040146,38.6930885315],"type":"Point"}
}