{
  "type": "Feature",
  "properties": {
    "addr:full":"C/ Rector Caldentey, 2 Manacor Islas Baleares 07500",
    "addr:housenumber":"2",
    "addr:postcode":"07500",
    "addr:street":"C / Rector Caldentey",
    "iso:country":"ES",
    "sg:address":"C/ Rector Caldentey, 2",
    "sg:city":"Manacor",
    "sg:orig_category":"Organizaciones Internacionales",
    "sg:phone":"+34 971 84 56 00",
    "sg:postcode":"07500",
    "sg:province":"Islas Baleares",
    "wof:name":"Caritas Diocesana",
    "wof:placetype":"venue"
},
  "geometry": {"coordinates":[3.2107379436,39.5681304932],"type":"Point"}
}