{
  "type": "Feature",
  "properties": {
    "addr:full":"Vred Guijar (del), 29 Arganda Madrid 28500",
    "addr:postcode":"28500",
    "iso:country":"ES",
    "sg:address":"Vred Guijar (del), 29",
    "sg:city":"Arganda",
    "sg:orig_category":"Muebles, Minoristas",
    "sg:phone":"+34 918 70 42 59",
    "sg:postcode":"28500",
    "sg:province":"Madrid",
    "wof:name":"X Y Z Factoria Creativa S.l.u.",
    "wof:placetype":"venue"
},
  "geometry": {"coordinates":[-3.4615387917,40.3143730164],"type":"Point"}
}