{
  "type": "Feature",
  "properties": {
    "iso:country":"ES",
    "sg:address":"Rua Transportes (dos), S/n",
    "sg:city":"Lugo",
    "sg:orig_category":"Equitaci\u00d3n Y Centros De H\u00cdpica",
    "sg:phone":"+34 982 20 93 15",
    "sg:postcode":"27003",
    "sg:province":"Lugo",
    "wof:name":"Gonzalez Martinez Jose",
    "wof:placetype":"venue"
},
  "geometry": {"coordinates":[-7.5627131462,43.0460700989],"type":"Point"}
}