{
  "type": "Feature",
  "properties": {
    "addr:full":"Ctra Oca\u00d1a, 38 Alacant Alicante 03006",
    "addr:housenumber":"38",
    "addr:postcode":"03006",
    "addr:street":"Ctra Ocan\u0303A",
    "iso:country":"ES",
    "sg:address":"Ctra Oca\u00d1a, 38",
    "sg:city":"Alacant",
    "sg:orig_category":"Ferreter\u00cda (diversos)",
    "sg:phone":"+34 965 28 56 03",
    "sg:postcode":"03006",
    "sg:province":"Alicante",
    "sg:website":"www.lyrsa.es",
    "wof:name":"Lajo Y Rodriguez S. A.",
    "wof:placetype":"venue"
},
  "geometry": {"coordinates":[-0.5250790119,38.3448104858],"type":"Point"}
}