{
  "type": "Feature",
  "properties": {
    "iso:country":"ES",
    "sg:address":"Ctra Campomayor, 23",
    "sg:city":"Badajoz",
    "sg:orig_category":"Farmacias",
    "sg:phone":"+34 924 27 53 54",
    "sg:postcode":"06007",
    "sg:province":"Badajoz",
    "wof:name":"Farmacia Llorente Llorente C.b.",
    "wof:placetype":"venue"
},
  "geometry": {"coordinates":[-6.9843788147,38.896938324],"type":"Point"}
}