{
  "type": "Feature",
  "properties": {
    "addr:full":"Cmno Goleta (de La), 59 Almeria Almer\u00eda 04006",
    "addr:housenumber":"59",
    "addr:postcode":"04006",
    "addr:street":"Cmno Goleta De La",
    "iso:country":"ES",
    "sg:address":"Cmno Goleta (de La), 59",
    "sg:city":"Almeria",
    "sg:orig_category":"Mec\u00c1nico Del Autom\u00d3vil",
    "sg:phone":"+34 950 22 94 12",
    "sg:postcode":"04006",
    "sg:province":"Almer\u00eda",
    "wof:name":"Juan Jose Rojas Y Otros Cdad.",
    "wof:placetype":"venue"
},
  "geometry": {"coordinates":[-2.4608390331,36.8422698975],"type":"Point"}
}