{
  "type": "Feature",
  "properties": {
    "addr:full":"Avda Pepita Duran, 5 Malaga M\u00e1laga 29010",
    "addr:housenumber":"5",
    "addr:postcode":"29010",
    "addr:street":"Avda Pepita Duran;Ma\u0301Laga",
    "iso:country":"ES",
    "sg:address":"Avda Pepita Duran, 5",
    "sg:city":"Malaga",
    "sg:orig_category":"Centros De Educaci\u00d3n Especial",
    "sg:phone":"+34 952 61 89 34",
    "sg:postcode":"29010",
    "sg:province":"M\u00e1laga",
    "wof:name":"Escuela Infantil Mama Oca S.l.",
    "wof:placetype":"venue"
},
  "geometry": {"coordinates":[-4.4713721275,36.7226219177],"type":"Point"}
}