{
  "type": "Feature",
  "properties": {
    "iso:country":"ES",
    "sg:address":"Pg Marti Pujol, 1",
    "sg:city":"Manlleu",
    "sg:orig_category":"Frutas, Legumbres Frescas Y Tempranas (al Por Menor)",
    "sg:phone":"+34 938 51 09 78",
    "sg:postcode":"08560",
    "sg:province":"Barcelona",
    "wof:name":"Escale Masegu Dolores",
    "wof:placetype":"venue"
},
  "geometry": {"coordinates":[2.2826099396,42.0020446777],"type":"Point"}
}