{
  "type": "Feature",
  "properties": {
    "addr:full":"Calle de San Lorenzo, 8 Toledo Toledo 45001",
    "addr:housenumber":"8",
    "addr:postcode":"45001",
    "addr:street":"Calle De San Lorenzo",
    "iso:country":"ES",
    "sg:address":"Calle de San Lorenzo, 8",
    "sg:city":"Toledo",
    "sg:orig_category":"Arquitectos",
    "sg:phone":"+34 925 25 09 54",
    "sg:postcode":"45001",
    "sg:province":"Toledo",
    "wof:name":"Gomez-escalonilla Sanchez-infante Jesus",
    "wof:placetype":"venue"
},
  "geometry": {"coordinates":[-4.0219907761,39.85496521],"type":"Point"}
}