{
  "type": "Feature",
  "properties": {
    "iso:country":"ES",
    "sg:address":"Pg Estacio (de L'), 6",
    "sg:city":"Torredembarra",
    "sg:orig_category":"Promotores Constructores",
    "sg:phone":"+34 977 64 24 11",
    "sg:postcode":"43830",
    "sg:province":"Tarragona",
    "wof:name":"Electro Torredembarra S.l.",
    "wof:placetype":"venue"
},
  "geometry": {"coordinates":[1.4051220417,41.1440963745],"type":"Point"}
}