{
  "type": "Feature",
  "properties": {
    "iso:country":"ES",
    "sg:address":"Calle de Narrica, 1",
    "sg:city":"Donostia-san Sebastian",
    "sg:orig_category":"Asesor\u00cda Fiscal Y Jur\u00cddica",
    "sg:phone":"+34 943 42 68 66",
    "sg:postcode":"20003",
    "sg:province":"Guip\u00f9zcoa",
    "wof:name":"Xibur C.b.",
    "wof:placetype":"venue"
},
  "geometry": {"coordinates":[-1.9839589596,43.3225440979],"type":"Point"}
}