{
  "type": "Feature",
  "properties": {
    "iso:country":"ES",
    "sg:address":"Calle de Marcos Zapata, 8",
    "sg:city":"Zaragoza",
    "sg:orig_category":"Zapatos (al Por Menor)",
    "sg:phone":"+34 976 33 41 93",
    "sg:postcode":"50010",
    "sg:province":"Zaragoza",
    "wof:name":"Morales Merino Maria Esmeralda",
    "wof:placetype":"venue"
},
  "geometry": {"coordinates":[-0.9061359763,41.6537055969],"type":"Point"}
}