{
  "type": "Feature",
  "properties": {
    "addr:full":"Muelle Navio-p I Pto De Algeciras, S/n Algeciras C\u00e1diz 11201",
    "addr:housenumber":"s / n;ca\u0301diz",
    "addr:postcode":"11201",
    "iso:country":"ES",
    "sg:address":"Muelle Navio-p I Pto De Algeciras, S/n",
    "sg:city":"Algeciras",
    "sg:orig_category":"Agencias De Aduana",
    "sg:phone":"+34 956 66 81 90",
    "sg:postcode":"11201",
    "sg:province":"C\u00e1diz",
    "sg:website":"www.europeaexpediciones.com",
    "wof:name":"Europea De Expediciones S.l.",
    "wof:placetype":"venue"
},
  "geometry": {"coordinates":[-5.4526491165,36.1276016235],"type":"Point"}
}