{
  "type": "Feature",
  "properties": {
    "addr:full":"Calle de Rafael Altamira, 4 Alacant Alicante 03002",
    "addr:housenumber":"4",
    "addr:postcode":"03002",
    "addr:street":"Calle De Rafael Altamira",
    "iso:country":"ES",
    "sg:address":"Calle de Rafael Altamira, 4",
    "sg:city":"Alacant",
    "sg:orig_category":"Centros P\u00dablicos De Formaci\u00d3n Profesional Y T\u00c9cnica",
    "sg:phone":"+34 965 21 48 82",
    "sg:postcode":"03002",
    "sg:province":"Alicante",
    "wof:name":"Colegio Oficial Agentes De Aduanas",
    "wof:placetype":"venue"
},
  "geometry": {"coordinates":[-0.4826920033,38.3442497253],"type":"Point"}
}