{
  "type": "Feature",
  "properties": {
    "addr:full":"Calle de Palencia, 32 Granada Granada 18008",
    "addr:housenumber":"32",
    "addr:postcode":"18008",
    "addr:street":"Calle De Palencia",
    "iso:country":"ES",
    "sg:address":"Calle de Palencia, 32",
    "sg:city":"Granada",
    "sg:orig_category":"Peluqueros: De Se\u00d1oras",
    "sg:phone":"+34 958 12 99 13",
    "sg:postcode":"18008",
    "sg:province":"Granada",
    "wof:name":"Shandong  Avellidoyuan",
    "wof:placetype":"venue"
},
  "geometry": {"coordinates":[-3.5922980309,37.1595230103],"type":"Point"}
}