{
  "type": "Feature",
  "properties": {
    "iso:country":"ES",
    "sg:address":"Carrer de Pere Martell (de), 4",
    "sg:city":"Tarragona",
    "sg:orig_category":"Peluqueros: De Se\u00d1oras",
    "sg:phone":"+34 977 21 45 64",
    "sg:postcode":"43001",
    "sg:province":"Tarragona",
    "wof:name":"Jofre Espa\u00f1ol Rosa",
    "wof:placetype":"venue"
},
  "geometry": {"coordinates":[1.2448819876,41.1174163818],"type":"Point"}
}