{
  "type": "Feature",
  "properties": {
    "iso:country":"ES",
    "sg:address":"Calle de Pozo De La Nieve, 5",
    "sg:city":"Iscar",
    "sg:orig_category":"Trajes Y Adornos De Boda (confecci\u00d3n, Al Por Menor)",
    "sg:phone":"+34 983 62 05 08",
    "sg:postcode":"47420",
    "sg:province":"Valladolid",
    "wof:name":"Costura Nupcial Alicia C.b.",
    "wof:placetype":"venue"
},
  "geometry": {"coordinates":[-4.5364718437,41.3622665405],"type":"Point"}
}