{
  "type": "Feature",
  "properties": {
    "iso:country":"ES",
    "sg:address":"Calle de Liberacion, 37",
    "sg:city":"Madrid",
    "sg:orig_category":"Peluquer\u00cdas, Peluquer\u00cda Mixta",
    "sg:phone":"+34 913 81 34 33",
    "sg:postcode":"28033",
    "sg:province":"Madrid",
    "wof:name":"Trazzas Estetica Del Cabello S.l.",
    "wof:placetype":"venue"
},
  "geometry": {"coordinates":[-3.6429927349,40.4717178345],"type":"Point"}
}