{
  "type": "Feature",
  "properties": {
    "addr:full":"Ctra Cadiz-malaga, Km. 0030,2 Santa Lucia C\u00e1diz 11150",
    "addr:postcode":"11150",
    "addr:street":"Ctra Cadiz-Malaga Km. 0030,2;Ca\u0301Diz",
    "iso:country":"ES",
    "sg:address":"Ctra Cadiz-malaga, Km. 0030,2",
    "sg:city":"Santa Lucia",
    "sg:orig_category":"Distribuci\u00d3n De Petr\u00d3leo Y Derivados",
    "sg:phone":"+34 956 23 26 12",
    "sg:postcode":"11150",
    "sg:province":"C\u00e1diz",
    "wof:name":"Espinosa Ceballos Jose Antonio",
    "wof:placetype":"venue"
},
  "geometry": {"coordinates":[-5.9644298553,36.2545776367],"type":"Point"}
}