{
  "type": "Feature",
  "properties": {
    "addr:full":"O Barreiro, S/n Ribadumia Pontevedra 36635",
    "addr:housenumber":"s",
    "addr:postcode":"36635",
    "addr:street":"/ N",
    "iso:country":"ES",
    "sg:address":"O Barreiro, S/n",
    "sg:city":"Ribadumia",
    "sg:orig_category":"Invernaderos Y Semilleros",
    "sg:phone":"+34 986 71 05 13",
    "sg:postcode":"36635",
    "sg:province":"Pontevedra",
    "wof:name":"Agrociencia Aplicada S.l",
    "wof:placetype":"venue"
},
  "geometry": {"coordinates":[-8.8152294159,42.5089950562],"type":"Point"}
}