{
  "type": "Feature",
  "properties": {
    "addr:full":"Calle de Quevedo, 1 Denia Alicante 03700",
    "addr:housenumber":"1",
    "addr:postcode":"03700",
    "addr:street":"Calle De Quevedo",
    "iso:country":"ES",
    "sg:address":"Calle de Quevedo, 1",
    "sg:city":"Denia",
    "sg:orig_category":"Peluquer\u00cdas, Peluquer\u00cda Mixta",
    "sg:phone":"+34 965 78 88 53",
    "sg:postcode":"03700",
    "sg:province":"Alicante",
    "wof:name":"Suret Cuatro S.l.",
    "wof:placetype":"venue"
},
  "geometry": {"coordinates":[0.1066130027,38.8384742737],"type":"Point"}
}