{
  "type": "Feature",
  "properties": {
    "iso:country":"ES",
    "sg:address":"Avda Jesus Santos Rein, S/n",
    "sg:city":"Fuengirola",
    "sg:orig_category":"Pescader\u00cdas (al Por Menor)",
    "sg:phone":"+34 952 46 40 65",
    "sg:postcode":"29640",
    "sg:province":"M\u00e1laga",
    "wof:name":"Garcia Serrano Vicente",
    "wof:placetype":"venue"
},
  "geometry": {"coordinates":[-4.6171970367,36.5507926941],"type":"Point"}
}