{
  "type": "Feature",
  "properties": {
    "addr:full":"Carrer de Esparreguera, 4 Martorell Barcelona 08760",
    "addr:housenumber":"4",
    "addr:postcode":"08760",
    "addr:street":"Carrer De Esparreguera",
    "iso:country":"ES",
    "sg:address":"Carrer de Esparreguera, 4",
    "sg:city":"Martorell",
    "sg:orig_category":"Promotores Constructores",
    "sg:phone":"+34 937 74 05 18",
    "sg:postcode":"08760",
    "sg:province":"Barcelona",
    "wof:name":"Comunidad De Propietarios Esparraguera 4",
    "wof:placetype":"venue"
},
  "geometry": {"coordinates":[1.9146889448,41.4746551514],"type":"Point"}
}