{
  "type": "Feature",
  "properties": {
    "iso:country":"ES",
    "sg:address":"Calle de Sol, 1",
    "sg:city":"Totana",
    "sg:orig_category":"Cajas De Ahorro",
    "sg:phone":"+34 968 42 07 01",
    "sg:postcode":"30850",
    "sg:province":"Murcia",
    "wof:name":"Caja De Ahorros De Murcia",
    "wof:placetype":"venue"
},
  "geometry": {"coordinates":[-1.5031729937,37.7686691284],"type":"Point"}
}