{
  "type": "Feature",
  "properties": {
    "iso:country":"ES",
    "sg:address":"Rond O'donnell, 3",
    "sg:city":"Mataro",
    "sg:orig_category":"Caf\u00c9s, Bares, Cervecer\u00cdas",
    "sg:phone":"+34 937 98 00 27",
    "sg:postcode":"08303",
    "sg:province":"Barcelona",
    "wof:name":"Noe Calafell Montserrat",
    "wof:placetype":"venue"
},
  "geometry": {"coordinates":[2.4311690331,41.5369491577],"type":"Point"}
}