{
  "type": "Feature",
  "properties": {
    "addr:full":"Carr Doctor Moliner, 40 Burjassot Valencia 46100",
    "addr:housenumber":"40",
    "addr:postcode":"46100",
    "addr:street":"Carr Doctor Moliner",
    "iso:country":"ES",
    "sg:address":"Carr Doctor Moliner, 40",
    "sg:city":"Burjassot",
    "sg:orig_category":"Artes Gr\u00c1ficas, Artes Pl\u00c1sticas (curso)",
    "sg:phone":"+34 963 90 37 35",
    "sg:postcode":"46100",
    "sg:province":"Valencia",
    "wof:name":"Gomez Coll S.l.",
    "wof:placetype":"venue"
},
  "geometry": {"coordinates":[-0.4162290096,39.5084571838],"type":"Point"}
}