{
  "type": "Feature",
  "properties": {
    "addr:full":"Calle de Perez (los), S/n Torre-pacheco Murcia 30700",
    "addr:postcode":"30700",
    "addr:street":"Calle De Perez Los S / N",
    "iso:country":"ES",
    "sg:address":"Calle de Perez (los), S/n",
    "sg:city":"Torre-pacheco",
    "sg:orig_category":"Frutos Y Legumbres",
    "sg:phone":"+34 968 58 56 11",
    "sg:postcode":"30700",
    "sg:province":"Murcia",
    "wof:name":"Gregal Sociedad Cooperativa",
    "wof:placetype":"venue"
},
  "geometry": {"coordinates":[-1.0606139898,37.9763412476],"type":"Point"}
}