{
  "type": "Feature",
  "properties": {
    "addr:full":"Avda Republica Argentina, 58 Sevilla Sevilla 41011",
    "addr:housenumber":"58",
    "addr:postcode":"41011",
    "addr:street":"Avda Republica Argentina",
    "iso:country":"ES",
    "sg:address":"Avda Republica Argentina, 58",
    "sg:city":"Sevilla",
    "sg:orig_category":"M\u00c9dicos: Ginecolog\u00cda M\u00c9dica, Obstetricia",
    "sg:phone":"+34 954 28 62 74",
    "sg:postcode":"41011",
    "sg:province":"Sevilla",
    "sg:website":"www.ivi.es",
    "wof:name":"Ivi Sevilla S.l.",
    "wof:placetype":"venue"
},
  "geometry": {"coordinates":[-6.0047187805,37.3763618469],"type":"Point"}
}