{
  "type": "Feature",
  "properties": {
    "addr:full":"Rua Zurbaran, 11 Ourense Ourense 32002",
    "addr:housenumber":"11",
    "addr:postcode":"32002",
    "addr:street":"Rua Zurbaran",
    "iso:country":"ES",
    "sg:address":"Rua Zurbaran, 11",
    "sg:city":"Ourense",
    "sg:orig_category":"Molduras, Junquillos, Listones Y Molduras Perforadas",
    "sg:phone":"+34 988 22 55 76",
    "sg:postcode":"32002",
    "sg:province":"Ourense",
    "wof:name":"Macia Garcia Eva",
    "wof:placetype":"venue"
},
  "geometry": {"coordinates":[-7.8721280098,42.3396224976],"type":"Point"}
}