{
  "type": "Feature",
  "properties": {
    "addr:full":"Gazta\u00d1adui Kalea, 42 Eskoriatza Guip\u00f9zcoa 20540",
    "addr:housenumber":"42",
    "addr:postcode":"20540",
    "addr:street":"Gaztan\u0303Adui Kalea;Guipu\u0300Zcoa",
    "iso:country":"ES",
    "sg:address":"Gazta\u00d1adui Kalea, 42",
    "sg:city":"Eskoriatza",
    "sg:classifiers":[
        {
            "category":"Manufacturing",
            "subcategory":"Metals",
            "type":"Manufacturing & Wholesale Goods"
        }
    ],
    "sg:phone":"+34 943 71 42 00",
    "sg:postcode":"20540",
    "sg:province":"Guip\u00f9zcoa",
    "sg:tags":[
        "en",
        "fundiciones"
    ],
    "sg:website":"www.fagor.ederlan.es",
    "wof:name":"Ederlan S.c.i.",
    "wof:placetype":"venue"
},
  "geometry": {"coordinates":[-2.5130069256,43.0247077942],"type":"Point"}
}