{
  "type": "Feature",
  "properties": {
    "addr:full":"Zubitxo Kalea, 15 Lezo Guip\u00f9zcoa 20100",
    "addr:housenumber":"15",
    "addr:postcode":"20100",
    "addr:street":"Zubitxo Kalea;Guipu\u0300Zcoa",
    "iso:country":"ES",
    "sg:address":"Zubitxo Kalea, 15",
    "sg:city":"Lezo",
    "sg:classifiers":[
        {
            "category":"Personal",
            "subcategory":"Barber",
            "type":"Services"
        }
    ],
    "sg:phone":"+34 943 34 03 96",
    "sg:postcode":"20100",
    "sg:province":"Guip\u00f9zcoa",
    "sg:tags":[
        "caballeros",
        "de",
        "peluqueros"
    ],
    "wof:name":"Vizuete Valencia Lucia",
    "wof:placetype":"venue"
},
  "geometry": {"coordinates":[-1.8970490694,43.3213272095],"type":"Point"}
}