{
  "type": "Feature",
  "properties": {
    "iso:country":"ES",
    "sg:address":"Afores, S/n",
    "sg:city":"S. Andreu Salou",
    "sg:orig_category":"Edici\u00d3n De Diarios, Revistas, Boletines",
    "sg:phone":"+34 972 46 36 73",
    "sg:postcode":"17457",
    "sg:province":"Girona",
    "wof:name":"International Publishers Consultant S.l.",
    "wof:placetype":"venue"
},
  "geometry": {"coordinates":[2.8040299416,41.8944282532],"type":"Point"}
}