{
  "type": "Feature",
  "properties": {
    "iso:country":"ES",
    "sg:address":"Carrer de Muntanya, 79",
    "sg:city":"Viladecans",
    "sg:orig_category":"Molduras, Junquillos, Listones Y Molduras Perforadas",
    "sg:phone":"+34 936 58 54 36",
    "sg:postcode":"08840",
    "sg:province":"Barcelona",
    "wof:name":"Vadillo Ortega Francisco",
    "wof:placetype":"venue"
},
  "geometry": {"coordinates":[2.0152590275,41.3202095032],"type":"Point"}
}