{
  "type": "Feature",
  "properties": {
    "addr:full":"Calle de Inspector Juan Antonio Bueno, 13 Alcorcon Madrid 28924",
    "addr:housenumber":"13",
    "addr:postcode":"28924",
    "addr:street":"Calle De Inspector Juan Antonio Bueno",
    "iso:country":"ES",
    "sg:address":"Calle de Inspector Juan Antonio Bueno, 13",
    "sg:city":"Alcorcon",
    "sg:orig_category":"Ense\u00d1anza Variada",
    "sg:phone":"+34 916 19 80 74",
    "sg:postcode":"28924",
    "sg:province":"Madrid",
    "wof:name":"Asociacion Ocio Y Tiempo Libre Dism.psiq.club Amigos",
    "wof:placetype":"venue"
},
  "geometry": {"coordinates":[-3.8129746914,40.3491592407],"type":"Point"}
}