{
  "type": "Feature",
  "properties": {
    "iso:country":"ES",
    "sg:address":"Calle de General Pardi\u00d1as, 69",
    "sg:city":"Madrid",
    "sg:orig_category":"Asociaciones Y Clubs Deportivos",
    "sg:phone":"+34 914 11 90 51",
    "sg:postcode":"28006",
    "sg:province":"Madrid",
    "wof:name":"Laly Ruiz",
    "wof:placetype":"venue"
},
  "geometry": {"coordinates":[-3.6781349182,40.4331245422],"type":"Point"}
}