{
  "type": "Feature",
  "properties": {
    "iso:country":"ES",
    "sg:address":"Plaz San Juan Bosco, 2",
    "sg:city":"Cieza",
    "sg:orig_category":"Cristaler\u00cdas",
    "sg:phone":"+34 968 76 03 58",
    "sg:postcode":"30530",
    "sg:province":"Murcia",
    "wof:name":"Angosto Morcillo Jose",
    "wof:placetype":"venue"
},
  "geometry": {"coordinates":[-1.416518569,38.2402153015],"type":"Point"}
}