{
  "type": "Feature",
  "properties": {
    "iso:country":"ES",
    "sg:address":"Ctra Font Roja, 14",
    "sg:city":"Alcoi",
    "sg:orig_category":"M\u00c1rmoles, Granitos Y Piedras Naturales",
    "sg:phone":"+34 965 54 23 05",
    "sg:postcode":"03801",
    "sg:province":"Alicante",
    "wof:name":"Paya Sebastia Jorge",
    "wof:placetype":"venue"
},
  "geometry": {"coordinates":[-0.4762549996,38.6785926819],"type":"Point"}
}