{
  "type": "Feature",
  "properties": {
    "iso:country":"ES",
    "sg:address":"Calle de Cervantes, 2",
    "sg:city":"Umbrete",
    "sg:orig_category":"Asociaciones Y Clubs Deportivos",
    "sg:phone":"+34 955 71 61 51",
    "sg:postcode":"41806",
    "sg:province":"Sevilla",
    "wof:name":"Pe\u00f1a Sevillista Luis Cuervas",
    "wof:placetype":"venue"
},
  "geometry": {"coordinates":[-6.1572341919,37.3698692322],"type":"Point"}
}