{
  "type": "Feature",
  "properties": {
    "iso:country":"ES",
    "sg:address":"Carretera Mutilva Baja, 8",
    "sg:city":"Mutiloabeiti",
    "sg:orig_category":"Productos Qu\u00cdmicos (fabricaci\u00d3n, Al Por Mayor)",
    "sg:phone":"+34 948 29 15 42",
    "sg:postcode":"31192",
    "sg:province":"Navarra",
    "wof:name":"Agrolab Analitica S.l.",
    "wof:placetype":"venue"
},
  "geometry": {"coordinates":[-1.6344386339,42.8068733215],"type":"Point"}
}