{
  "type": "Feature",
  "properties": {
    "addr:full":"Carrer de Cerdans, 7 Lloret Mar Girona 17310",
    "addr:housenumber":"7",
    "addr:postcode":"17310",
    "addr:street":"Carrer De Cerdans",
    "iso:country":"ES",
    "sg:address":"Carrer de Cerdans, 7",
    "sg:city":"Lloret Mar",
    "sg:orig_category":"Promotores Constructores",
    "sg:phone":"+34 972 36 74 74",
    "sg:postcode":"17310",
    "sg:province":"Girona",
    "wof:name":"Orva Lloret S.l.",
    "wof:placetype":"venue"
},
  "geometry": {"coordinates":[2.8462760448,41.7093582153],"type":"Point"}
}