{
  "type": "Feature",
  "properties": {
    "iso:country":"ES",
    "sg:address":"Plaz Euskadi, 3",
    "sg:city":"Irun",
    "sg:orig_category":"Transportes Internacionales",
    "sg:phone":"+34 943 63 24 81",
    "sg:postcode":"20305",
    "sg:province":"Guip\u00f9zcoa",
    "wof:name":"Safetruck Forwarding S.l.",
    "wof:placetype":"venue"
},
  "geometry": {"coordinates":[-1.758630991,43.3432693481],"type":"Point"}
}