{
  "type": "Feature",
  "properties": {
    "addr:full":"Carrer de Rubi, 7 Palma Islas Baleares 07002",
    "addr:housenumber":"7",
    "addr:postcode":"07002",
    "addr:street":"Carrer De Rubi",
    "iso:country":"ES",
    "sg:address":"Carrer de Rubi, 7",
    "sg:city":"Palma",
    "sg:orig_category":"Centros P\u00dablicos De Formaci\u00d3n Profesional Y T\u00c9cnica",
    "sg:phone":"+34 971 72 75 72",
    "sg:postcode":"07002",
    "sg:province":"Islas Baleares",
    "wof:name":"Colegio De Ingenieros Tecnicos De Obras Publicas.",
    "wof:placetype":"venue"
},
  "geometry": {"coordinates":[2.6524159908,39.5712432861],"type":"Point"}
}