{
  "type": "Feature",
  "properties": {
    "iso:country":"ES",
    "sg:address":"Av Diagonal, 686",
    "sg:city":"Barcelona",
    "sg:orig_category":"Asociaciones, Organismos Culturales Y Socioeducativos",
    "sg:phone":"+34 932 05 27 61",
    "sg:postcode":"08034",
    "sg:province":"Barcelona",
    "sg:website":"www.estudidelmoble.com",
    "wof:name":"Associacio Per A L'estudi Del Moble",
    "wof:placetype":"venue"
},
  "geometry": {"coordinates":[2.1189570427,41.3862533569],"type":"Point"}
}