{
  "type": "Feature",
  "properties": {
    "iso:country":"ES",
    "sg:address":"Avda Sanlucar (de), 2",
    "sg:city":"Puerto De Santa Maria",
    "sg:orig_category":"Laboratorios Y Cl\u00cdnicas Veterinarias",
    "sg:phone":"+34 956 87 65 93",
    "sg:postcode":"11500",
    "sg:province":"C\u00e1diz",
    "sg:website":"www.univeto.com",
    "wof:name":"Univeto Sur S.l.",
    "wof:placetype":"venue"
},
  "geometry": {"coordinates":[-6.2295098305,36.6044769287],"type":"Point"}
}