{
  "type": "Feature",
  "properties": {
    "iso:country":"ES",
    "sg:address":"Calle de Montenegro, 22",
    "sg:city":"Teruel",
    "sg:orig_category":"Arquitectos",
    "sg:phone":"+34 978 60 95 52",
    "sg:postcode":"44002",
    "sg:province":"Teruel",
    "wof:name":"Laredo Nu\u00f1ez Fernando",
    "wof:placetype":"venue"
},
  "geometry": {"coordinates":[-1.0977189541,40.3291091919],"type":"Point"}
}