{
  "type": "Feature",
  "properties": {
    "iso:country":"ES",
    "sg:address":"Calle de Virgen De Africa, 1",
    "sg:city":"Ibi",
    "sg:orig_category":"Negocio De Metales No Ferrosos",
    "sg:phone":"+34 965 55 07 24",
    "sg:postcode":"03440",
    "sg:province":"Alicante",
    "wof:name":"Metalizados Gines S.l.",
    "wof:placetype":"venue"
},
  "geometry": {"coordinates":[-0.5816389918,38.6188201904],"type":"Point"}
}