{
  "type": "Feature",
  "properties": {
    "addr:full":"Calle de Adarve Del Padre Rosalio, 14 Caceres C\u00e1ceres 10003",
    "addr:housenumber":"14",
    "addr:postcode":"10003",
    "addr:street":"Calle De Adarve Del;Rosalio;Ca\u0301Ceres",
    "iso:country":"ES",
    "sg:address":"Calle de Adarve Del Padre Rosalio, 14",
    "sg:city":"Caceres",
    "sg:orig_category":"Art\u00cdculos De Decoraci\u00d3n",
    "sg:phone":"+34 927 24 46 92",
    "sg:postcode":"10003",
    "sg:province":"C\u00e1ceres",
    "wof:name":"Rodriguez Moran Benito Damian",
    "wof:placetype":"venue"
},
  "geometry": {"coordinates":[-6.3722753525,39.4732170105],"type":"Point"}
}