{
  "type": "Feature",
  "properties": {
    "iso:country":"ES",
    "sg:address":"Calle de Colon, 10",
    "sg:city":"Venta De Ba\u00e7os",
    "sg:orig_category":"Contenedores (mercanc\u00cdas)",
    "sg:phone":"+34 979 77 08 92",
    "sg:postcode":"34200",
    "sg:province":"Palencia",
    "wof:name":"Nieto Perez Sebastian",
    "wof:placetype":"venue"
},
  "geometry": {"coordinates":[-4.4977011681,41.9209289551],"type":"Point"}
}