{
  "type": "Feature",
  "properties": {
    "addr:full":"Calle de Arroyo, 19 Marmolejo Ja\u00e9n 23770",
    "addr:housenumber":"19",
    "addr:postcode":"23770",
    "addr:street":"Calle De Arroyo;Jae\u0301N",
    "iso:country":"ES",
    "sg:address":"Calle de Arroyo, 19",
    "sg:city":"Marmolejo",
    "sg:orig_category":"Fabricaci\u00d3n De Muebles",
    "sg:phone":"+34 953 54 02 06",
    "sg:postcode":"23770",
    "sg:province":"Ja\u00e9n",
    "wof:name":"Ruiz Sanz Jose Manuel",
    "wof:placetype":"venue"
},
  "geometry": {"coordinates":[-4.171210289,38.0463104248],"type":"Point"}
}