{
  "type": "Feature",
  "properties": {
    "iso:country":"ES",
    "sg:address":"C/ Major, 278",
    "sg:city":"Salt",
    "sg:orig_category":"Carnicer\u00cdas, Carnicer\u00cdas",
    "sg:phone":"+34 972 23 55 57",
    "sg:postcode":"17190",
    "sg:province":"Girona",
    "wof:name":"Marco Batista Jose",
    "wof:placetype":"venue"
},
  "geometry": {"coordinates":[2.7968840599,41.9758110046],"type":"Point"}
}