{
  "type": "Feature",
  "properties": {
    "addr:full":"Carr Pau (la), 14 Figueres Girona 17600",
    "addr:housenumber":"14",
    "addr:postcode":"17600",
    "addr:street":"Carr Pau La",
    "iso:country":"ES",
    "sg:address":"Carr Pau (la), 14",
    "sg:city":"Figueres",
    "sg:orig_category":"M\u00c9dicos: Naturistas",
    "sg:phone":"+34 972 51 35 92",
    "sg:postcode":"17600",
    "sg:province":"Girona",
    "sg:website":"www.fundacioncarme-enric.org",
    "wof:name":"Fundacio Privada Carme-enric",
    "wof:placetype":"venue"
},
  "geometry": {"coordinates":[2.961286068,42.2653503418],"type":"Point"}
}