{
  "type": "Feature",
  "properties": {
    "addr:full":"Calvario(celeiro), 2 Viveiro Lugo 27863",
    "addr:housenumber":"2",
    "addr:postcode":"27863",
    "addr:street":"Celeiro",
    "iso:country":"ES",
    "sg:address":"Calvario(celeiro), 2",
    "sg:city":"Viveiro",
    "sg:orig_category":"Caf\u00c9s, Bares, Cervecer\u00cdas",
    "sg:phone":"+34 982 56 34 95",
    "sg:postcode":"27863",
    "sg:province":"Lugo",
    "wof:name":"Galtelcom",
    "wof:placetype":"venue"
},
  "geometry": {"coordinates":[-7.5347719193,43.6102027893],"type":"Point"}
}