{
  "type": "Feature",
  "properties": {
    "addr:full":"Plaz San Sebastian, 5 Almeria Almer\u00eda 04003",
    "addr:housenumber":"5",
    "addr:postcode":"04003",
    "addr:street":"Plaz San Sebastian",
    "iso:country":"ES",
    "sg:address":"Plaz San Sebastian, 5",
    "sg:city":"Almeria",
    "sg:orig_category":"M\u00c9dicos: Radioterapia (radioterapia Como Opci\u00d3n Oncol\u00d3gica)",
    "sg:phone":"+34 950 23 65 55",
    "sg:postcode":"04003",
    "sg:province":"Almer\u00eda",
    "wof:name":"Sanchez Herrera Pablo Mario",
    "wof:placetype":"venue"
},
  "geometry": {"coordinates":[-2.4608390331,36.8422698975],"type":"Point"}
}