{
  "type": "Feature",
  "properties": {
    "iso:country":"ES",
    "sg:address":"Carrer de Sant Antoni, 5",
    "sg:city":"Pobla De Montornes",
    "sg:orig_category":"Administraciones Regionales, Departamentales Y Locales",
    "sg:phone":"+34 977 64 80 12",
    "sg:postcode":"43761",
    "sg:province":"Tarragona",
    "wof:name":"Ajuntament De La Pobla De Montornes",
    "wof:placetype":"venue"
},
  "geometry": {"coordinates":[1.4143549204,41.1789703369],"type":"Point"}
}