{
  "type": "Feature",
  "properties": {
    "addr:full":"Carrer de Proven\u00c7a, 598 Barcelona Barcelona 08026",
    "addr:housenumber":"598",
    "addr:postcode":"08026",
    "addr:street":"Carrer De Provenc\u0327A",
    "iso:country":"ES",
    "sg:address":"Carrer de Proven\u00c7a, 598",
    "sg:city":"Barcelona",
    "sg:orig_category":"Ropa Para Se\u00d1oras (al Por Menor)",
    "sg:phone":"+34 934 55 21 68",
    "sg:postcode":"08026",
    "sg:province":"Barcelona",
    "wof:name":"Sanchez Lopez Luisa S.c.p.",
    "wof:placetype":"venue"
},
  "geometry": {"coordinates":[2.182790041,41.410358429],"type":"Point"}
}