{
  "type": "Feature",
  "properties": {
    "iso:country":"ES",
    "sg:address":"Avda Moratalaz, 139",
    "sg:city":"Madrid",
    "sg:orig_category":"Ense\u00d1anza: Idiomas",
    "sg:phone":"+34 914 30 55 45",
    "sg:postcode":"28030",
    "sg:province":"Madrid",
    "sg:website":"www.lacadeintop.com",
    "wof:name":"Aparicio Fernandez Ana",
    "wof:placetype":"venue"
},
  "geometry": {"coordinates":[-3.6482167244,40.406867981],"type":"Point"}
}