{
  "type": "Feature",
  "properties": {
    "iso:country":"ES",
    "sg:address":"Av Sant Vicen\u00c7, 8",
    "sg:city":"Vendrell",
    "sg:orig_category":"Empresas De Carpinter\u00cda Met\u00c1lica",
    "sg:phone":"+34 977 66 80 69",
    "sg:postcode":"43700",
    "sg:province":"Tarragona",
    "wof:name":"Aluminis Calmet S.l.",
    "wof:placetype":"venue"
},
  "geometry": {"coordinates":[1.5314509869,41.2161331177],"type":"Point"}
}