{
  "type": "Feature",
  "properties": {
    "iso:country":"ES",
    "sg:address":"C/ Herrera 70 M8",
    "sg:city":"Matar\u00f3",
    "sg:classifiers":[
        {
            "category":"Professional",
            "subcategory":"Computer Services",
            "type":"Services"
        }
    ],
    "sg:postcode":"08301",
    "sg:tags":[
        "open-innovation",
        "innovation",
        "open-innovation-marketplace",
        "innovation-intermediaries",
        "internet",
        "rd",
        "scientitsts",
        "research"
    ],
    "sg:website":"http://www.innoget.com",
    "wof:name":"Innoget",
    "wof:placetype":"venue"
},
  "geometry": {"coordinates":[2.4526426,41.5433892],"type":"Point"}
}