{
  "type": "Feature",
  "properties": {
    "addr:full":"Carr Sant Ignaci, 22 Castell Islas Baleares 07720",
    "addr:housenumber":"22",
    "addr:postcode":"07720",
    "addr:street":"Carr Sant Ignaci",
    "iso:country":"ES",
    "sg:address":"Carr Sant Ignaci, 22",
    "sg:city":"Castell",
    "sg:orig_category":"Art\u00cdculos De Regalo (al Por Menor)",
    "sg:phone":"+34 971 35 49 24",
    "sg:postcode":"07720",
    "sg:province":"Islas Baleares",
    "wof:name":"Autos Punta Prima S.l.",
    "wof:placetype":"venue"
},
  "geometry": {"coordinates":[4.292494297,39.8807296753],"type":"Point"}
}