{
  "type": "Feature",
  "properties": {
    "iso:country":"ES",
    "sg:address":"Mayorazgo, 11",
    "sg:city":"Sta Cruz Tenerife",
    "sg:orig_category":"Transporte En General",
    "sg:phone":"+34 922 23 16 33",
    "sg:postcode":"38010",
    "sg:province":"Santa Cruz De Tenerife",
    "wof:name":"Comercial Jesuman",
    "wof:placetype":"venue"
},
  "geometry": {"coordinates":[-16.2832794189,28.4460105896],"type":"Point"}
}