{
  "type": "Feature",
  "properties": {
    "iso:country":"ES",
    "sg:address":"Rua Benito Corbal, 64",
    "sg:city":"Pontevedra",
    "sg:orig_category":"Peluqueros: De Se\u00d1oras",
    "sg:phone":"+34 986 85 93 37",
    "sg:postcode":"36001",
    "sg:province":"Pontevedra",
    "wof:name":"Hair Brother S.l.",
    "wof:placetype":"venue"
},
  "geometry": {"coordinates":[-8.6382408142,42.429359436],"type":"Point"}
}