{
  "type": "Feature",
  "properties": {
    "iso:country":"ES",
    "sg:address":"Calle de Zu\u00d1iga, 6",
    "sg:city":"Salamanca",
    "sg:orig_category":"Fabricaci\u00d3n, Importaci\u00d3n De Material Y Sistemas De Telecomunicaciones",
    "sg:phone":"+34 923 23 11 81",
    "sg:postcode":"37004",
    "sg:province":"Salamanca",
    "wof:name":"Gesalco S.l.l.",
    "wof:placetype":"venue"
},
  "geometry": {"coordinates":[-5.6512408257,40.9719543457],"type":"Point"}
}