{
  "type": "Feature",
  "properties": {
    "addr:full":"Calle de Canario, 4 Almensilla Sevilla 41111",
    "addr:housenumber":"4",
    "addr:postcode":"41111",
    "addr:street":"Calle De Canario",
    "iso:country":"ES",
    "sg:address":"Calle de Canario, 4",
    "sg:city":"Almensilla",
    "sg:orig_category":"Empresas De Hormig\u00d3n, Hormig\u00d3n Armado Y Pretensado",
    "sg:phone":"+34 955 76 79 02",
    "sg:postcode":"41111",
    "sg:province":"Sevilla",
    "wof:name":"Ballesteros Arriaza Felix",
    "wof:placetype":"venue"
},
  "geometry": {"coordinates":[-6.1145038605,37.3108177185],"type":"Point"}
}