{
  "type": "Feature",
  "properties": {
    "iso:country":"ES",
    "sg:address":"Calle de Niceto Cuenca, 61",
    "sg:city":"Almansa",
    "sg:orig_category":"Alimentaci\u00d3n General (al Por Menor)",
    "sg:phone":"+34 967 34 10 47",
    "sg:postcode":"02640",
    "sg:province":"Albacete",
    "wof:name":"Gandia Martinez Miguel",
    "wof:placetype":"venue"
},
  "geometry": {"coordinates":[-1.1035790443,38.8686103821],"type":"Point"}
}