{
  "type": "Feature",
  "properties": {
    "addr:full":"Carr Mercat (del), 2 Seros Lleida 25183",
    "addr:housenumber":"2",
    "addr:postcode":"25183",
    "addr:street":"Carr Mercat Del",
    "iso:country":"ES",
    "sg:address":"Carr Mercat (del), 2",
    "sg:city":"Seros",
    "sg:orig_category":"Centros De Educaci\u00d3n Especial",
    "sg:phone":"+34 973 78 01 02",
    "sg:postcode":"25183",
    "sg:province":"Lleida",
    "wof:name":"Ajuntament De Seros",
    "wof:placetype":"venue"
},
  "geometry": {"coordinates":[0.4110156,41.4654922485],"type":"Point"}
}