{
  "type": "Feature",
  "properties": {
    "iso:country":"ES",
    "sg:address":"Carr Degollador, Es, 63",
    "sg:city":"Ciutadella Menorca",
    "sg:orig_category":"Sonorizaci\u00d3n, Iluminaci\u00d3n Para Cine, Teatro Y Discotecas (al Por Mayor, Al Por Menor)",
    "sg:phone":"+34 971 48 43 39",
    "sg:postcode":"07760",
    "sg:province":"Islas Baleares",
    "wof:name":"Acustic Menorca S.l.",
    "wof:placetype":"venue"
},
  "geometry": {"coordinates":[3.8377597332,39.9972953796],"type":"Point"}
}