{
  "type": "Feature",
  "properties": {
    "iso:country":"ES",
    "sg:address":"Doctor Gonzalez De Quevedo, 20",
    "sg:city":"Prado Del Rey",
    "sg:orig_category":"Electrodom\u00c9sticos (al Por Menor)",
    "sg:phone":"+34 956 72 44 56",
    "sg:postcode":"11660",
    "sg:province":"C\u00e1diz",
    "wof:name":"Hipercine S.l.",
    "wof:placetype":"venue"
},
  "geometry": {"coordinates":[-5.5550069809,36.7885551453],"type":"Point"}
}