{
  "type": "Feature",
  "properties": {
    "iso:country":"ES",
    "sg:address":"Pl. Arcedianos, 1",
    "sg:city":"Tarazona",
    "sg:orig_category":"Albergues",
    "sg:phone":"+34 976 64 23 03",
    "sg:postcode":"50500",
    "sg:province":"Zaragoza",
    "wof:name":"Aparicio Pellicer Beatriz",
    "wof:placetype":"venue"
},
  "geometry": {"coordinates":[-1.7269128561,41.9046478271],"type":"Point"}
}