{
  "type": "Feature",
  "properties": {
    "iso:country":"ES",
    "sg:address":"Calle de Visconti, 4",
    "sg:city":"Tarazona",
    "sg:orig_category":"Art\u00cdculos De Decoraci\u00d3n",
    "sg:phone":"+34 976 64 49 29",
    "sg:postcode":"50500",
    "sg:province":"Zaragoza",
    "wof:name":"Sesma Lorente Eva",
    "wof:placetype":"venue"
},
  "geometry": {"coordinates":[-1.7244590521,41.9044876099],"type":"Point"}
}