{
  "type": "Feature",
  "properties": {
    "addr:full":"Paraje De Las Chozas, S/n Ejido Almer\u00eda 04700",
    "addr:housenumber":"s",
    "addr:postcode":"04700",
    "addr:street":"Paraje De Las Chozas;/ N Ejido Almeri\u0301A",
    "iso:country":"ES",
    "sg:address":"Paraje De Las Chozas, S/n",
    "sg:city":"Ejido",
    "sg:orig_category":"Producci\u00d3n De Abonos Y De Fertilizantes",
    "sg:phone":"+34 950 52 23 16",
    "sg:postcode":"04700",
    "sg:province":"Almer\u00eda",
    "wof:name":"Dicalite Espa\u00f1ola S.a.",
    "wof:placetype":"venue"
},
  "geometry": {"coordinates":[-2.8057060242,36.760974884],"type":"Point"}
}