{
  "type": "Feature",
  "properties": {
    "addr:full":"Calle de Serrerias, 9 Molina Segura Murcia 30500",
    "addr:housenumber":"9",
    "addr:postcode":"30500",
    "addr:street":"Calle De Serrerias",
    "iso:country":"ES",
    "sg:address":"Calle de Serrerias, 9",
    "sg:city":"Molina Segura",
    "sg:orig_category":"Florister\u00cdas",
    "sg:phone":"+34 968 64 17 29",
    "sg:postcode":"30500",
    "sg:province":"Murcia",
    "wof:name":"Manzano Martinez Emilia",
    "wof:placetype":"venue"
},
  "geometry": {"coordinates":[-1.2145810127,38.0571708679],"type":"Point"}
}