{
  "type": "Feature",
  "properties": {
    "addr:full":"Calle de Castellote, 3 Zaragoza Zaragoza 50017",
    "addr:housenumber":"3",
    "addr:postcode":"50017",
    "addr:street":"Calle De Castellote",
    "iso:country":"ES",
    "sg:address":"Calle de Castellote, 3",
    "sg:city":"Zaragoza",
    "sg:orig_category":"Centros De Educaci\u00d3n Especial",
    "sg:phone":"+34 976 31 31 99",
    "sg:postcode":"50017",
    "sg:province":"Zaragoza",
    "wof:name":"Colegio Publico Juan Jose Lorente",
    "wof:placetype":"venue"
},
  "geometry": {"coordinates":[-0.9142022729,41.6455612183],"type":"Point"}
}