{
  "type": "Feature",
  "properties": {
    "addr:full":"Avda Castelao, 59 Vigo Pontevedra 36209",
    "addr:housenumber":"59",
    "addr:postcode":"36209",
    "addr:street":"Avda Castelao",
    "iso:country":"ES",
    "sg:address":"Avda Castelao, 59",
    "sg:city":"Vigo",
    "sg:orig_category":"Centros De Educaci\u00d3n Especial",
    "sg:phone":"+34 986 29 12 65",
    "sg:postcode":"36209",
    "sg:province":"Pontevedra",
    "wof:name":"Colexio Publico Doctor Eijo Garay",
    "wof:placetype":"venue"
},
  "geometry": {"coordinates":[-8.7433624268,42.2182617188],"type":"Point"}
}