{
  "type": "Feature",
  "properties": {
    "addr:full":"Calle de Anton Garcia Abril, 21 Zaragoza Zaragoza 50018",
    "addr:housenumber":"21",
    "addr:postcode":"50018",
    "addr:street":"Calle De Anton Garcia Abril",
    "iso:country":"ES",
    "sg:address":"Calle de Anton Garcia Abril, 21",
    "sg:city":"Zaragoza",
    "sg:orig_category":"Empresas De Limpieza",
    "sg:phone":"+34 976 52 18 52",
    "sg:postcode":"50018",
    "sg:province":"Zaragoza",
    "wof:name":"Limcamar S.l.",
    "wof:placetype":"venue"
},
  "geometry": {"coordinates":[-0.8860980272,41.6781959534],"type":"Point"}
}