{
  "type": "Feature",
  "properties": {
    "iso:country":"ES",
    "sg:address":"Carrer de Morey, 4",
    "sg:city":"Palma",
    "sg:orig_category":"Arquitectos",
    "sg:phone":"+34 971 72 44 05",
    "sg:postcode":"07001",
    "sg:province":"Islas Baleares",
    "wof:name":"Canalis Hernandez Oscar",
    "wof:placetype":"venue"
},
  "geometry": {"coordinates":[2.6505749226,39.5685501099],"type":"Point"}
}