{
  "type": "Feature",
  "properties": {
    "iso:country":"ES",
    "sg:address":"R. Burguera, 15",
    "sg:city":"Manilva",
    "sg:orig_category":"Peluquer\u00cdas, Peluquer\u00cda Mixta",
    "sg:phone":"+34 952 89 07 31",
    "sg:postcode":"29692",
    "sg:province":"M\u00e1laga",
    "wof:name":"Peluqueria Karmele S.a",
    "wof:placetype":"venue"
},
  "geometry": {"coordinates":[-5.2259931564,36.3674697876],"type":"Point"}
}