{
  "type": "Feature",
  "properties": {
    "iso:country":"ES",
    "sg:address":"Carr Baro De Maials, 88",
    "sg:city":"Lleida",
    "sg:orig_category":"Agencias De Viajes",
    "sg:phone":"+34 973 22 29 65",
    "sg:postcode":"25005",
    "sg:province":"Lleida",
    "wof:name":"Marti Marketing Grup S.l.",
    "wof:placetype":"venue"
},
  "geometry": {"coordinates":[0.6281139851,41.6282615662],"type":"Point"}
}