{
  "type": "Feature",
  "properties": {
    "addr:full":"Calle de Olite, 48 Madrid Madrid 28039",
    "addr:housenumber":"48",
    "addr:postcode":"madrid;28039",
    "addr:street":"Calle De Olite",
    "iso:country":"ES",
    "sg:address":"Calle de Olite, 48",
    "sg:city":"Madrid",
    "sg:orig_category":"Farmacias",
    "sg:phone":"+34 914 59 64 90",
    "sg:postcode":"28039",
    "sg:province":"Madrid",
    "wof:name":"Yague Agueda Pedro",
    "wof:placetype":"venue"
},
  "geometry": {"coordinates":[-3.7068543434,40.4525756836],"type":"Point"}
}