{
  "type": "Feature",
  "properties": {
    "iso:country":"ES",
    "sg:address":"Avda Juan De Herrera, S/n",
    "sg:city":"Madrid",
    "sg:orig_category":"Restaurantes",
    "sg:phone":"+34 915 49 00 41",
    "sg:postcode":"28040",
    "sg:province":"Madrid",
    "wof:name":"Bokado Madrid S.l.",
    "wof:placetype":"venue"
},
  "geometry": {"coordinates":[-3.7315139771,40.4385757446],"type":"Point"}
}