{
  "type": "Feature",
  "properties": {
    "addr:full":"Calle de Doctor Civera, 26 Jaen Ja\u00e9n 23003",
    "addr:housenumber":"26;jae\u0301n",
    "addr:postcode":"23003",
    "addr:street":"Calle De Doctor Civera",
    "iso:country":"ES",
    "sg:address":"Calle de Doctor Civera, 26",
    "sg:city":"Jaen",
    "sg:orig_category":"Deportes Diversos",
    "sg:phone":"+34 953 24 39 03",
    "sg:postcode":"23003",
    "sg:province":"Ja\u00e9n",
    "wof:name":"Federacion Andaluza De Futbol",
    "wof:placetype":"venue"
},
  "geometry": {"coordinates":[-3.7891075611,37.768081665],"type":"Point"}
}