{
  "type": "Feature",
  "properties": {
    "iso:country":"ES",
    "sg:address":"Carr Sant Pere, 77",
    "sg:city":"Badalona",
    "sg:orig_category":"Confecci\u00d3n De Trajes Para Se\u00d1oras",
    "sg:phone":"+34 933 84 31 81",
    "sg:postcode":"08911",
    "sg:province":"Barcelona",
    "wof:name":"Lopez Trigo Ascension",
    "wof:placetype":"venue"
},
  "geometry": {"coordinates":[2.2506830692,41.4494743347],"type":"Point"}
}