{
  "type": "Feature",
  "properties": {
    "addr:full":"Calle de German Alonso, 1 Le\u00f3n Le\u00f3n 24008",
    "addr:housenumber":"1",
    "addr:postcode":"24008",
    "addr:street":"Calle De German Alonso;Leo\u0301N",
    "iso:country":"ES",
    "sg:address":"Calle de German Alonso, 1",
    "sg:city":"Le\u00f3n",
    "sg:orig_category":"Molduras, Junquillos, Listones Y Molduras Perforadas",
    "sg:phone":"+34 987 80 77 26",
    "sg:postcode":"24008",
    "sg:province":"Le\u00f3n",
    "wof:name":"Garcia Valladares Rafael",
    "wof:placetype":"venue"
},
  "geometry": {"coordinates":[-5.5852026939,42.607208252],"type":"Point"}
}