{
  "type": "Feature",
  "properties": {
    "iso:country":"ES",
    "sg:address":"Avda Jose Luis Arrese, 1",
    "sg:city":"Valladolid",
    "sg:orig_category":"Fotocopias, Reprograf\u00cda",
    "sg:phone":"+34 983 33 63 48",
    "sg:postcode":"47014",
    "sg:province":"Valladolid",
    "wof:name":"Indacoechea Miquelarena Pedro Maria",
    "wof:placetype":"venue"
},
  "geometry": {"coordinates":[-4.7367048264,41.6499824524],"type":"Point"}
}