{
  "type": "Feature",
  "properties": {
    "addr:full":"Oyambre, 26 Comillas Cantabria 39520",
    "addr:housenumber":"26",
    "addr:postcode":"39520",
    "addr:street":"Oyambre",
    "iso:country":"ES",
    "sg:address":"Oyambre, 26",
    "sg:city":"Comillas",
    "sg:orig_category":"Hoteles",
    "sg:phone":"+34 942 72 09 17",
    "sg:postcode":"39520",
    "sg:province":"Cantabria",
    "wof:name":"Palacio De Diego Nelly",
    "wof:placetype":"venue"
},
  "geometry": {"coordinates":[-4.2923278809,43.3905715942],"type":"Point"}
}