{
  "type": "Feature",
  "properties": {
    "addr:full":"Calle de Cerrada Santa Cruz, 39 Benavente Zamora 49600",
    "addr:housenumber":"39",
    "addr:postcode":"49600",
    "addr:street":"Calle De Cerrada Santa Cruz",
    "iso:country":"ES",
    "sg:address":"Calle de Cerrada Santa Cruz, 39",
    "sg:city":"Benavente",
    "sg:orig_category":"Imprenta",
    "sg:phone":"+34 980 63 02 33",
    "sg:postcode":"49600",
    "sg:province":"Zamora",
    "wof:name":"Imprenta Libreria Ma\u00f1anes S.l.",
    "wof:placetype":"venue"
},
  "geometry": {"coordinates":[-5.6741995811,42.0031280518],"type":"Point"}
}