{
  "type": "Feature",
  "properties": {
    "iso:country":"ES",
    "sg:address":"Plaz 2 De Mayo, 3",
    "sg:city":"Yeles",
    "sg:orig_category":"Partidos Pol\u00cdticos",
    "sg:phone":"+34 925 51 01 88",
    "sg:postcode":"45220",
    "sg:province":"Toledo",
    "wof:name":"Asociacion Cultural Deportiva Y De Juventud Amigos De Yeles",
    "wof:placetype":"venue"
},
  "geometry": {"coordinates":[-3.8037252426,40.12059021],"type":"Point"}
}