{
  "type": "Feature",
  "properties": {
    "addr:full":"Calle de Serrano Morales, 4 Valencia Valencia 46004",
    "addr:housenumber":"4",
    "addr:postcode":"46004",
    "addr:street":"Calle De Serrano Morales",
    "iso:country":"ES",
    "sg:address":"Calle de Serrano Morales, 4",
    "sg:city":"Valencia",
    "sg:classifiers":[
        {
            "category":"Professional",
            "subcategory":"Management & Consulting",
            "type":"Services"
        }
    ],
    "sg:phone":"+34 963 74 96 99",
    "sg:postcode":"46004",
    "sg:province":"Valencia",
    "sg:tags":[
        "asesor\u00cda",
        "en",
        "marketing"
    ],
    "wof:name":"Expertia Marketing Estrategico S.l.",
    "wof:placetype":"venue"
},
  "geometry": {"coordinates":[-0.3653489947,39.4690322876],"type":"Point"}
}