{
  "type": "Feature",
  "properties": {
    "addr:full":"Pase Gran Capitan, 2 Salamanca Salamanca 37006",
    "addr:housenumber":"2",
    "addr:postcode":"37006",
    "addr:street":"Capitan",
    "iso:country":"ES",
    "sg:address":"Pase Gran Capitan, 2",
    "sg:city":"Salamanca",
    "sg:orig_category":"Mercer\u00cda, Lencer\u00cda (al Por Menor)",
    "sg:phone":"+34 923 25 64 13",
    "sg:postcode":"37006",
    "sg:province":"Salamanca",
    "wof:name":"Coll Nova",
    "wof:placetype":"venue"
},
  "geometry": {"coordinates":[-5.663848877,40.964225769],"type":"Point"}
}