{
  "type": "Feature",
  "properties": {
    "iso:country":"ES",
    "sg:address":"Calle de Escultor Marinas (del), 6",
    "sg:city":"Segovia",
    "sg:orig_category":"Asesor\u00cda Fiscal Y Jur\u00cddica",
    "sg:phone":"+34 921 41 30 64",
    "sg:postcode":"40002",
    "sg:province":"Segovia",
    "wof:name":"Castrillo Calvo Alberto",
    "wof:placetype":"venue"
},
  "geometry": {"coordinates":[-4.1197500229,40.9448127747],"type":"Point"}
}