{
  "type": "Feature",
  "properties": {
    "iso:country":"ES",
    "sg:address":"Carr Alemanya, 33",
    "sg:city":"Badalona",
    "sg:orig_category":"Confecci\u00d3n De Trajes Para Se\u00d1oras",
    "sg:phone":"+34 934 65 30 24",
    "sg:postcode":"08917",
    "sg:province":"Barcelona",
    "wof:name":"Hip-hop S.l.",
    "wof:placetype":"venue"
},
  "geometry": {"coordinates":[2.2213900089,41.4587669373],"type":"Point"}
}