{
  "type": "Feature",
  "properties": {
    "addr:full":"Pg Mar, 1 Palamos Girona 17230",
    "addr:housenumber":"1",
    "addr:postcode":"17230",
    "addr:street":"Pg Mar",
    "iso:country":"ES",
    "sg:address":"Pg Mar, 1",
    "sg:city":"Palamos",
    "sg:orig_category":"Estancos",
    "sg:phone":"+34 972 60 21 96",
    "sg:postcode":"17230",
    "sg:province":"Girona",
    "wof:name":"Comas Oliveras Isabel",
    "wof:placetype":"venue"
},
  "geometry": {"coordinates":[3.1254398823,41.84815979],"type":"Point"}
}