{
  "type": "Feature",
  "properties": {
    "addr:full":"Carrer de Independencia, 99 Hospitalet Llobregat Barcelona 08902",
    "addr:housenumber":"99",
    "addr:postcode":"08902",
    "addr:street":"Carrer De Independencia",
    "iso:country":"ES",
    "sg:address":"Carrer de Independencia, 99",
    "sg:city":"Hospitalet Llobregat",
    "sg:orig_category":"Fotograf\u00cda Y Cine: Aparatos, Pel\u00cdculas Y Accesorios (fabricaci\u00d3n, Al Por Mayor)",
    "sg:phone":"+34 933 35 87 45",
    "sg:postcode":"08902",
    "sg:province":"Barcelona",
    "wof:name":"Aranda Catalan Domingo Oswaldo",
    "wof:placetype":"venue"
},
  "geometry": {"coordinates":[2.1243774891,41.3608398438],"type":"Point"}
}