{
  "type": "Feature",
  "properties": {
    "iso:country":"ES",
    "sg:address":"Carrer de Enric Granados, 44",
    "sg:city":"Premia Mar",
    "sg:orig_category":"Sociedades, Compa\u00d1\u00cdas Aseguradoras",
    "sg:phone":"+34 937 52 15 97",
    "sg:postcode":"08330",
    "sg:province":"Barcelona",
    "wof:name":"Agencia De Seguros Benamat S.c.p.",
    "wof:placetype":"venue"
},
  "geometry": {"coordinates":[2.3567025661,41.4933013916],"type":"Point"}
}