{
  "type": "Feature",
  "properties": {
    "iso:country":"ES",
    "sg:address":"Av Francesc Riera, 11",
    "sg:city":"Martorell",
    "sg:orig_category":"Frutas, Legumbres Frescas Y Tempranas (al Por Menor)",
    "sg:phone":"+34 937 74 24 60",
    "sg:postcode":"08760",
    "sg:province":"Barcelona",
    "wof:name":"Tio Martinez Pere",
    "wof:placetype":"venue"
},
  "geometry": {"coordinates":[1.9136660099,41.4806785583],"type":"Point"}
}