{
  "type": "Feature",
  "properties": {
    "addr:full":"Calle de Cabeza, 3 Baza Granada 18800",
    "addr:housenumber":"3",
    "addr:postcode":"18800",
    "addr:street":"Calle De Cabeza",
    "iso:country":"ES",
    "sg:address":"Calle de Cabeza, 3",
    "sg:city":"Baza",
    "sg:orig_category":"Ropa Para Ni\u00d1os (al Por Menor)",
    "sg:phone":"+34 958 70 14 17",
    "sg:postcode":"18800",
    "sg:province":"Granada",
    "wof:name":"Robles Navarro Antonio",
    "wof:placetype":"venue"
},
  "geometry": {"coordinates":[-2.7730603218,37.4898262024],"type":"Point"}
}