{
  "type": "Feature",
  "properties": {
    "addr:full":"Calle de Canales, 5 Malaga M\u00e1laga 29002",
    "addr:housenumber":"5",
    "addr:postcode":"29002",
    "addr:street":"Calle De Canales;Ma\u0301Laga",
    "iso:country":"ES",
    "sg:address":"Calle de Canales, 5",
    "sg:city":"Malaga",
    "sg:orig_category":"Abogados",
    "sg:phone":"+34 952 35 73 42",
    "sg:postcode":"29002",
    "sg:province":"M\u00e1laga",
    "wof:name":"Gomez Luque Juana Jose",
    "wof:placetype":"venue"
},
  "geometry": {"coordinates":[-4.4273090363,36.7113456726],"type":"Point"}
}