{
  "type": "Feature",
  "properties": {
    "iso:country":"ES",
    "sg:address":"Calle de Isilla, 30",
    "sg:city":"Aranda Duero",
    "sg:orig_category":"Farmacias",
    "sg:phone":"+34 947 50 01 85",
    "sg:postcode":"09400",
    "sg:province":"Burgos",
    "wof:name":"Heras Molinos Juan Andres De Las",
    "wof:placetype":"venue"
},
  "geometry": {"coordinates":[-3.6853690147,41.671421051],"type":"Point"}
}