{
  "type": "Feature",
  "properties": {
    "addr:full":"Rua Ramon Basanta Ben, 20 Burela Lugo 27880",
    "addr:housenumber":"20",
    "addr:postcode":"27880",
    "addr:street":"Rua Ramon Basanta Ben",
    "iso:country":"ES",
    "sg:address":"Rua Ramon Basanta Ben, 20",
    "sg:city":"Burela",
    "sg:classifiers":[
        {
            "category":"Recreation",
            "type":"Entertainment"
        }
    ],
    "sg:phone":"+34 982 58 09 21",
    "sg:postcode":"27880",
    "sg:province":"Lugo",
    "sg:tags":[
        "caza",
        "pr\u00c1ctica",
        "la",
        "de",
        "pesca",
        "y"
    ],
    "wof:name":"Nuevo Hermanos Casina C.b.",
    "wof:placetype":"venue"
},
  "geometry": {"coordinates":[-7.3572740555,43.6630096436],"type":"Point"}
}