{
  "type": "Feature",
  "properties": {
    "addr:full":"La Ermita, S/n Almenar Soria Soria 42130",
    "addr:housenumber":"/ n",
    "addr:postcode":"42130",
    "addr:street":"S",
    "iso:country":"ES",
    "sg:address":"La Ermita, S/n",
    "sg:city":"Almenar Soria",
    "sg:orig_category":"Carnicer\u00cdas, Carnicer\u00cdas",
    "sg:phone":"+34 975 39 00 11",
    "sg:postcode":"42130",
    "sg:province":"Soria",
    "wof:name":"Carrami\u00f1ana Perez Carmen",
    "wof:placetype":"venue"
},
  "geometry": {"coordinates":[-2.2005889416,41.6823883057],"type":"Point"}
}