{
  "type": "Feature",
  "properties": {
    "iso:country":"ES",
    "sg:address":"Calle de Alustante, 33",
    "sg:city":"Madrid",
    "sg:orig_category":"Peluquer\u00cdas, Peluquer\u00cda Mixta",
    "sg:phone":"+34 915 10 03 96",
    "sg:postcode":"28002",
    "sg:province":"Madrid",
    "wof:name":"Dombriz Zafra Jesus Francisco",
    "wof:placetype":"venue"
},
  "geometry": {"coordinates":[-3.6712427139,40.4438018799],"type":"Point"}
}