{
  "type": "Feature",
  "properties": {
    "addr:full":"Calle de Juan Fernandez, 41 Cartagena Murcia 30204",
    "addr:housenumber":"41",
    "addr:postcode":"30204",
    "addr:street":"Calle De Juan Fernandez",
    "iso:country":"ES",
    "sg:address":"Calle de Juan Fernandez, 41",
    "sg:city":"Cartagena",
    "sg:orig_category":"Cajas De Ahorro",
    "sg:phone":"+34 968 53 66 53",
    "sg:postcode":"30204",
    "sg:province":"Murcia",
    "sg:website":"www.cam.es",
    "wof:name":"Caja De Ahorros Del Mediterraneo",
    "wof:placetype":"venue"
},
  "geometry": {"coordinates":[-0.9881880283,37.6123847961],"type":"Point"}
}