{
  "type": "Feature",
  "properties": {
    "addr:full":"Calle de Reyes Catolicos, 5 Portugalete Vizcaya 48920",
    "addr:housenumber":"5",
    "addr:postcode":"48920",
    "addr:street":"Calle De Reyes Catolicos",
    "iso:country":"ES",
    "sg:address":"Calle de Reyes Catolicos, 5",
    "sg:city":"Portugalete",
    "sg:orig_category":"Empresarios",
    "sg:phone":"+34 944 61 83 96",
    "sg:postcode":"48920",
    "sg:province":"Vizcaya",
    "wof:name":"Ruiz Tobar Fermin",
    "wof:placetype":"venue"
},
  "geometry": {"coordinates":[-3.0265219212,43.3228607178],"type":"Point"}
}