{
  "type": "Feature",
  "properties": {
    "addr:full":"Avda Ricardo Curtoys Gotarredona, S/n Santa Eulalia Islas Baleares 07840",
    "addr:housenumber":"s / n",
    "addr:postcode":"07840",
    "addr:street":"Avda Ricardo Curtoys Gotarredona",
    "iso:country":"ES",
    "sg:address":"Avda Ricardo Curtoys Gotarredona, S/n",
    "sg:city":"Santa Eulalia",
    "sg:orig_category":"Ense\u00d1anza Variada",
    "sg:phone":"+34 971 33 91 33",
    "sg:postcode":"07840",
    "sg:province":"Islas Baleares",
    "wof:name":"Planells Cardona Juan",
    "wof:placetype":"venue"
},
  "geometry": {"coordinates":[1.5296820402,38.9818534851],"type":"Point"}
}