{
  "type": "Feature",
  "properties": {
    "addr:full":"Calle de Carretera, 1 Torrevelilla Teruel 44641",
    "addr:housenumber":"1",
    "addr:postcode":"44641",
    "addr:street":"Calle De Carretera",
    "iso:country":"ES",
    "sg:address":"Calle de Carretera, 1",
    "sg:city":"Torrevelilla",
    "sg:orig_category":"Inmobiliaria (agencias)",
    "sg:phone":"+34 978 85 23 58",
    "sg:postcode":"44641",
    "sg:province":"Teruel",
    "wof:name":"N.g. Servicios Juridicos S.l.",
    "wof:placetype":"venue"
},
  "geometry": {"coordinates":[-0.1079292968,40.9016914368],"type":"Point"}
}