{
  "type": "Feature",
  "properties": {
    "addr:full":"D. Cortes, 16 Ejido Almer\u00eda 04700",
    "addr:housenumber":"16 ejido",
    "addr:postcode":"04700",
    "addr:street":"Cortes;Almeri\u0301A",
    "iso:country":"ES",
    "sg:address":"D. Cortes, 16",
    "sg:city":"Ejido",
    "sg:orig_category":"Producci\u00d3n De Abonos Y De Fertilizantes",
    "sg:phone":"+34 950 57 02 00",
    "sg:postcode":"04700",
    "sg:province":"Almer\u00eda",
    "wof:name":"Horti-imber S.l.",
    "wof:placetype":"venue"
},
  "geometry": {"coordinates":[-2.7980144024,36.7726593018],"type":"Point"}
}