{
  "type": "Feature",
  "properties": {
    "iso:country":"ES",
    "sg:address":"Tv. Rio Alberche, 2",
    "sg:city":"Toledo",
    "sg:orig_category":"Alimentaci\u00d3n General (al Por Menor)",
    "sg:phone":"+34 925 24 01 53",
    "sg:postcode":"45007",
    "sg:province":"Toledo",
    "wof:name":"Asador Garcia S.l.",
    "wof:placetype":"venue"
},
  "geometry": {"coordinates":[-3.9164586067,39.8639602661],"type":"Point"}
}