{
  "type": "Feature",
  "properties": {
    "iso:country":"ES",
    "sg:address":"Av Maresme (del), 119",
    "sg:city":"Mataro",
    "sg:orig_category":"Fabricaci\u00d3n De Harinas, S\u00c9molas, Productos De Elaboraci\u00d3n Del Grano",
    "sg:phone":"+34 937 98 04 47",
    "sg:postcode":"08302",
    "sg:province":"Barcelona",
    "sg:website":"www.ylla1878.com",
    "wof:name":"Ylla 1878 S. L.",
    "wof:placetype":"venue"
},
  "geometry": {"coordinates":[2.441344738,41.5313491821],"type":"Point"}
}