{
  "type": "Feature",
  "properties": {
    "addr:full":"Filipineta Kalea, 17 Ordizia Guip\u00f9zcoa 20240",
    "addr:housenumber":"17",
    "addr:postcode":"20240",
    "addr:street":"Filipineta Kalea;Guipu\u0300Zcoa",
    "iso:country":"ES",
    "sg:address":"Filipineta Kalea, 17",
    "sg:city":"Ordizia",
    "sg:orig_category":"Asociaciones Y Clubs Deportivos",
    "sg:phone":"+34 943 88 04 80",
    "sg:postcode":"20240",
    "sg:province":"Guip\u00f9zcoa",
    "wof:name":"Sociedad Boxing Ciclo Club",
    "wof:placetype":"venue"
},
  "geometry": {"coordinates":[-2.1743121147,43.057220459],"type":"Point"}
}