{
  "type": "Feature",
  "properties": {
    "addr:full":"C/ Fila Verds, 32 Alcoi Alicante 03801",
    "addr:housenumber":"32",
    "addr:postcode":"03801",
    "addr:street":"C /;Verds",
    "iso:country":"ES",
    "sg:address":"C/ Fila Verds, 32",
    "sg:city":"Alcoi",
    "sg:orig_category":"Transportes Por V\u00cdas Navegables",
    "sg:phone":"+34 965 54 38 77",
    "sg:postcode":"03801",
    "sg:province":"Alicante",
    "wof:name":"Pamor, S.l.",
    "wof:placetype":"venue"
},
  "geometry": {"coordinates":[-0.4732739925,38.6984100342],"type":"Point"}
}