{
  "type": "Feature",
  "properties": {
    "addr:full":"Calle de Larrakotorre, 24 Bilbao Vizcaya 48015",
    "addr:housenumber":"24",
    "addr:postcode":"48015",
    "addr:street":"Calle De Larrakotorre",
    "iso:country":"ES",
    "sg:address":"Calle de Larrakotorre, 24",
    "sg:city":"Bilbao",
    "sg:orig_category":"Ense\u00d1anza: Idiomas",
    "sg:phone":"+34 944 47 02 24",
    "sg:postcode":"48015",
    "sg:province":"Vizcaya",
    "wof:name":"Euskaraz Koop. E.",
    "wof:placetype":"venue"
},
  "geometry": {"coordinates":[-2.9624269009,43.279094696],"type":"Point"}
}