{
  "type": "Feature",
  "properties": {
    "iso:country":"ES",
    "sg:address":"Pla\u00c7 Rafael Casanova I Comes, 6",
    "sg:city":"Girona",
    "sg:orig_category":"Asesor\u00cda Fiscal Y Jur\u00cddica",
    "sg:phone":"+34 972 20 01 84",
    "sg:postcode":"17003",
    "sg:province":"Girona",
    "wof:name":"Grup Decta Assessors S.l.",
    "wof:placetype":"venue"
},
  "geometry": {"coordinates":[2.8246150017,41.9734191895],"type":"Point"}
}