{
  "type": "Feature",
  "properties": {
    "addr:full":"Carrer de Joan Miro, 7 Mora Nova Tarragona 43770",
    "addr:housenumber":"7",
    "addr:postcode":"43770",
    "addr:street":"Carrer De Joan Miro",
    "iso:country":"ES",
    "sg:address":"Carrer de Joan Miro, 7",
    "sg:city":"Mora Nova",
    "sg:orig_category":"Empresas De Carpinter\u00cda De Madera",
    "sg:phone":"+34 977 40 02 76",
    "sg:postcode":"43770",
    "sg:province":"Tarragona",
    "wof:name":"Anson Monta\u00f1es Domingo",
    "wof:placetype":"venue"
},
  "geometry": {"coordinates":[0.6348158717,41.0883979797],"type":"Point"}
}