{
  "type": "Feature",
  "properties": {
    "iso:country":"ES",
    "sg:address":"Calle de Alonso Quijano, S/n",
    "sg:city":"Albacete",
    "sg:orig_category":"Agencias Y Agentes Comerciales, Representantes",
    "sg:phone":"+34 967 50 60 83",
    "sg:postcode":"02006",
    "sg:province":"Albacete",
    "wof:name":"Cebrian Sanchez Luis",
    "wof:placetype":"venue"
},
  "geometry": {"coordinates":[-1.8611391783,38.9814567566],"type":"Point"}
}