{
  "type": "Feature",
  "properties": {
    "addr:full":"Pe\u00f1aullan, 220 Pravia Asturias 33127",
    "addr:housenumber":"220",
    "addr:postcode":"33127",
    "addr:street":"Pen\u0303Aullan",
    "iso:country":"ES",
    "sg:address":"Pe\u00f1aullan, 220",
    "sg:city":"Pravia",
    "sg:orig_category":"Materias Pl\u00c1sticas: Art\u00cdculos Para La Industria",
    "sg:phone":"+34 985 82 27 21",
    "sg:postcode":"33127",
    "sg:province":"Asturias",
    "sg:website":"www.linpac-plastics.es",
    "wof:name":"Linpac Plastics Pravia S.a.",
    "wof:placetype":"venue"
},
  "geometry": {"coordinates":[-6.0685720444,43.5057067871],"type":"Point"}
}