{
  "type": "Feature",
  "properties": {
    "addr:full":"Avda Santa Barbara, 13 Toledo Toledo 45006",
    "addr:housenumber":"13",
    "addr:postcode":"45006",
    "addr:street":"Avda Santa Barbara",
    "iso:country":"ES",
    "sg:address":"Avda Santa Barbara, 13",
    "sg:city":"Toledo",
    "sg:orig_category":"Copas, Insignias, Trofeos",
    "sg:phone":"+34 925 25 24 91",
    "sg:postcode":"45006",
    "sg:province":"Toledo",
    "wof:name":"Molina Fernandez Marta",
    "wof:placetype":"venue"
},
  "geometry": {"coordinates":[-4.0079369545,39.8615531921],"type":"Point"}
}