{
  "type": "Feature",
  "properties": {
    "iso:country":"ES",
    "sg:address":"Av. Clot Dels Franquets Nord, 3",
    "sg:city":"Roses",
    "sg:orig_category":"Alfarer\u00cda",
    "sg:phone":"+34 972 25 74 10",
    "sg:postcode":"17480",
    "sg:province":"Girona",
    "wof:name":"Noguer Vicens Jaume",
    "wof:placetype":"venue"
},
  "geometry": {"coordinates":[3.1663351059,42.2661399841],"type":"Point"}
}