{
  "type": "Feature",
  "properties": {
    "iso:country":"ES",
    "sg:address":"Calle de Bethencourt Alfonso, 18",
    "sg:city":"Santa Cruz De Tenerife",
    "sg:classifiers":[
        {
            "category":"Personal",
            "subcategory":"Barber",
            "type":"Services"
        }
    ],
    "sg:phone":"+34 922 24 35 10",
    "sg:postcode":"38002",
    "sg:province":"Santa Cruz De Tenerife",
    "sg:tags":[
        "caballeros",
        "de",
        "peluqueros"
    ],
    "wof:name":"Delgado Garcia Agustin",
    "wof:placetype":"venue"
},
  "geometry": {"coordinates":[-16.2494735718,28.4674873352],"type":"Point"}
}