{
  "type": "Feature",
  "properties": {
    "addr:full":"C/ Joan Xxiii, 12 Tarrega Lleida 25300",
    "addr:housenumber":"12",
    "addr:postcode":"25300",
    "addr:street":"C / Joan Xxiii",
    "iso:country":"ES",
    "sg:address":"C/ Joan Xxiii, 12",
    "sg:city":"Tarrega",
    "sg:orig_category":"Promotores Constructores",
    "sg:phone":"+34 973 50 03 17",
    "sg:postcode":"25300",
    "sg:province":"Lleida",
    "wof:name":"Promobras Caro S.l.",
    "wof:placetype":"venue"
},
  "geometry": {"coordinates":[1.1464740038,41.6510505676],"type":"Point"}
}