{
  "type": "Feature",
  "properties": {
    "addr:full":"Calle de Argentina, 20 Vitoria-gasteiz \u00c1lava 01009",
    "addr:housenumber":"20",
    "addr:postcode":"01009",
    "addr:street":"Calle De Argentina",
    "iso:country":"ES",
    "sg:address":"Calle de Argentina, 20",
    "sg:city":"Vitoria-gasteiz",
    "sg:orig_category":"Cursos Particulares, Asistencia Escolar",
    "sg:phone":"+34 945 22 23 70",
    "sg:postcode":"01009",
    "sg:province":"\u00c1lava",
    "wof:name":"Navarro Albaina Juan Jose",
    "wof:placetype":"venue"
},
  "geometry": {"coordinates":[-2.6840641499,42.8528175354],"type":"Point"}
}