{
  "type": "Feature",
  "properties": {
    "iso:country":"ES",
    "sg:address":"Carrer de Balcans, 8",
    "sg:city":"Sabadell",
    "sg:orig_category":"Mec\u00c1nico Del Autom\u00d3vil",
    "sg:phone":"+34 937 16 71 52",
    "sg:postcode":"08207",
    "sg:province":"Barcelona",
    "wof:name":"Taller Ducras S.l.",
    "wof:placetype":"venue"
},
  "geometry": {"coordinates":[2.0922410488,41.5727310181],"type":"Point"}
}