{
  "type": "Feature",
  "properties": {
    "addr:full":"Rua Romero Ortiz, 22 Vilagarcia Pontevedra 36600",
    "addr:housenumber":"22",
    "addr:postcode":"36600",
    "addr:street":"Rua Romero Ortiz",
    "iso:country":"ES",
    "sg:address":"Rua Romero Ortiz, 22",
    "sg:city":"Vilagarcia",
    "sg:orig_category":"Centros De Educaci\u00d3n Especial",
    "sg:phone":"+34 986 50 51 72",
    "sg:postcode":"36600",
    "sg:province":"Pontevedra",
    "wof:name":"Asociacion Bata",
    "wof:placetype":"venue"
},
  "geometry": {"coordinates":[-8.7655162811,42.5971374512],"type":"Point"}
}