{
  "type": "Feature",
  "properties": {
    "iso:country":"ES",
    "sg:address":"Rua Caldeireria (da), 37",
    "sg:city":"Santiago De Compostela",
    "sg:orig_category":"Ropa Para Ni\u00d1os (al Por Menor)",
    "sg:phone":"+34 981 57 49 22",
    "sg:postcode":"15703",
    "sg:province":"La Coru\u00f1a",
    "wof:name":"Moda Zasnieto S L",
    "wof:placetype":"venue"
},
  "geometry": {"coordinates":[-8.5428009033,42.8786659241],"type":"Point"}
}