{
  "type": "Feature",
  "properties": {
    "iso:country":"ES",
    "sg:address":"Calle de Corredera Baja De San Pablo, 53",
    "sg:city":"Madrid",
    "sg:orig_category":"Alimentaci\u00d3n General (al Por Menor)",
    "sg:phone":"+34 915 21 48 89",
    "sg:postcode":"28004",
    "sg:province":"Madrid",
    "wof:name":"Cui Cui Chen",
    "wof:placetype":"venue"
},
  "geometry": {"coordinates":[-3.702403307,40.4237365723],"type":"Point"}
}