{
  "type": "Feature",
  "properties": {
    "addr:full":"Calle de Miguel Iscar, 17 Valladolid Valladolid 47001",
    "addr:housenumber":"17",
    "addr:postcode":"47001",
    "addr:street":"Calle De Miguel Iscar",
    "iso:country":"ES",
    "sg:address":"Calle de Miguel Iscar, 17",
    "sg:city":"Valladolid",
    "sg:orig_category":"Bancos",
    "sg:phone":"+34 983 30 88 99",
    "sg:postcode":"47001",
    "sg:province":"Valladolid",
    "sg:website":"www.bes.es",
    "wof:name":"Banco Espirito Santo S.a.",
    "wof:placetype":"venue"
},
  "geometry": {"coordinates":[-4.7267360687,41.6486320496],"type":"Point"}
}