{
  "type": "Feature",
  "properties": {
    "iso:country":"ES",
    "sg:address":"Calle de Mayor, 11",
    "sg:city":"Santa Cruz Del Valle",
    "sg:orig_category":"Alimentaci\u00d3n General (al Por Menor)",
    "sg:phone":"+34 920 38 62 53",
    "sg:postcode":"05411",
    "sg:province":"\u00c1vila",
    "wof:name":"Gonzalez Martin Jacinto",
    "wof:placetype":"venue"
},
  "geometry": {"coordinates":[-5.0023941994,40.2520599365],"type":"Point"}
}