{
  "type": "Feature",
  "properties": {
    "iso:country":"ES",
    "sg:address":"Calle de Molino De Viento, 18",
    "sg:city":"Villares Saz",
    "sg:orig_category":"Reparaciones Y Remolcado De Veh\u00cdculos",
    "sg:phone":"+34 969 29 81 62",
    "sg:postcode":"16442",
    "sg:province":"Cuenca",
    "wof:name":"Torres Lopez Jose Maria",
    "wof:placetype":"venue"
},
  "geometry": {"coordinates":[-2.5037429333,39.8377723694],"type":"Point"}
}