{
  "type": "Feature",
  "properties": {
    "iso:country":"ES",
    "sg:address":"Plaz Espa\u00d1a, 15",
    "sg:city":"Herrera",
    "sg:orig_category":"Ropa Para Se\u00d1oras Y Caballeros (al Por Menor)",
    "sg:phone":"+34 954 01 31 28",
    "sg:postcode":"41567",
    "sg:province":"Sevilla",
    "wof:name":"Ortiz Benjumea Encarnacion",
    "wof:placetype":"venue"
},
  "geometry": {"coordinates":[-4.8502187729,37.3662567139],"type":"Point"}
}