{
  "type": "Feature",
  "properties": {
    "iso:country":"ES",
    "sg:address":"Calle de Gobelaurre, 35",
    "sg:city":"Getxo",
    "sg:orig_category":"Inmobiliaria (agencias)",
    "sg:phone":"+34 944 31 63 03",
    "sg:postcode":"48930",
    "sg:province":"Vizcaya",
    "wof:name":"Inmobiliaria Y Servicios Del Duranguesado, S.l.",
    "wof:placetype":"venue"
},
  "geometry": {"coordinates":[-3.0056085587,43.3286132812],"type":"Point"}
}