{
  "type": "Feature",
  "properties": {
    "iso:country":"ES",
    "sg:address":"Carrer de Castillejos, 381",
    "sg:city":"Barcelona",
    "sg:orig_category":"Loter\u00cda Y T\u00d3mbola",
    "sg:phone":"+34 934 56 94 85",
    "sg:postcode":"08025",
    "sg:province":"Barcelona",
    "wof:name":"Sanchez Rovira Juan",
    "wof:placetype":"venue"
},
  "geometry": {"coordinates":[2.1714010239,41.4115524292],"type":"Point"}
}