{
  "type": "Feature",
  "properties": {
    "iso:country":"ES",
    "sg:address":"Calle de San Venancio, 19",
    "sg:city":"Casas Nuevas",
    "sg:orig_category":"Fabricaci\u00d3n, Importaci\u00d3n, Venta De Material De Telefon\u00cda, Peritelefon\u00cda",
    "sg:phone":"+34 928 13 19 60",
    "sg:postcode":"35214",
    "sg:province":"Las Palmas",
    "wof:name":"Canarias De Explotacion De Telefonia S.l.",
    "wof:placetype":"venue"
},
  "geometry": {"coordinates":[-15.3887634277,27.9937648773],"type":"Point"}
}