{
  "type": "Feature",
  "properties": {
    "iso:country":"ES",
    "sg:address":"Zurbano Kalea, 15",
    "sg:city":"Segura",
    "sg:orig_category":"Librer\u00cdas",
    "sg:phone":"+34 943 80 10 49",
    "sg:postcode":"20214",
    "sg:province":"Guip\u00f9zcoa",
    "wof:name":"Izaguirre Inchausti Prudencio",
    "wof:placetype":"venue"
},
  "geometry": {"coordinates":[-2.2527520657,43.0084342957],"type":"Point"}
}