{
  "type": "Feature",
  "properties": {
    "addr:full":"Calle de General Asensio, 17 Fuensalida Toledo 45510",
    "addr:housenumber":"17",
    "addr:postcode":"45510",
    "addr:street":"Calle De General Asensio",
    "iso:country":"ES",
    "sg:address":"Calle de General Asensio, 17",
    "sg:city":"Fuensalida",
    "sg:orig_category":"Cerrajer\u00cda, Ferrallista",
    "sg:phone":"+34 925 78 43 27",
    "sg:postcode":"45510",
    "sg:province":"Toledo",
    "wof:name":"Perez Perez Concordio",
    "wof:placetype":"venue"
},
  "geometry": {"coordinates":[-4.2104110718,40.0573577881],"type":"Point"}
}