{
  "type": "Feature",
  "properties": {
    "addr:full":"Plaz San Martin De Abenda\u00d1o, 5 Vitoria-gasteiz \u00c1lava 01009",
    "addr:housenumber":"5",
    "addr:postcode":"01009",
    "addr:street":"Plaz;Abendan\u0303O",
    "iso:country":"ES",
    "sg:address":"Plaz San Martin De Abenda\u00d1o, 5",
    "sg:city":"Vitoria-gasteiz",
    "sg:orig_category":"Florister\u00cdas",
    "sg:phone":"+34 945 24 16 38",
    "sg:postcode":"01009",
    "sg:province":"\u00c1lava",
    "wof:name":"Eulalia Mendoza Cintado",
    "wof:placetype":"venue"
},
  "geometry": {"coordinates":[-2.68759799,42.8514518738],"type":"Point"}
}