{
  "type": "Feature",
  "properties": {
    "addr:full":"Resid Pque S Nicolas, S/n Sevilla Sevilla 41008",
    "addr:housenumber":"/ n",
    "addr:postcode":"41008",
    "addr:street":"Nicolas S",
    "iso:country":"ES",
    "sg:address":"Resid Pque S Nicolas, S/n",
    "sg:city":"Sevilla",
    "sg:orig_category":"Fotograf\u00cda Art\u00cdstica Y Retratos",
    "sg:phone":"+34 954 35 60 21",
    "sg:postcode":"41008",
    "sg:province":"Sevilla",
    "wof:name":"Gallardo Ruiz Juan Carlos",
    "wof:placetype":"venue"
},
  "geometry": {"coordinates":[-5.9647536278,37.405921936],"type":"Point"}
}