{
  "type": "Feature",
  "properties": {
    "addr:full":"Iturrama, 15 Iru\u00f1a Navarra 31007",
    "addr:housenumber":"15",
    "addr:postcode":"31007",
    "addr:street":"Iturrama",
    "iso:country":"ES",
    "sg:address":"Iturrama, 15",
    "sg:city":"Iru\u00f1a",
    "sg:orig_category":"Organismos Y Centros De Vacaciones Y Esparcimiento Para Ni\u00d1os Y Adolescentes",
    "sg:phone":"+34 948 25 10 65",
    "sg:postcode":"31007",
    "sg:province":"Navarra",
    "sg:website":"www.mteducacionyformacion.com",
    "wof:name":"Mt Servicios De Formacion S.l.",
    "wof:placetype":"venue"
},
  "geometry": {"coordinates":[-1.6520609856,42.8044395447],"type":"Point"}
}