{
  "type": "Feature",
  "properties": {
    "addr:full":"Calle de San Rafael (de), 6 Alcobendas Madrid 28108",
    "addr:postcode":"28108",
    "addr:street":"Calle De San Rafael",
    "iso:country":"ES",
    "sg:address":"Calle de San Rafael (de), 6",
    "sg:city":"Alcobendas",
    "sg:orig_category":"Maquinaria Para Industrias Diversas",
    "sg:phone":"+34 914 90 03 00",
    "sg:postcode":"28108",
    "sg:province":"Madrid",
    "sg:website":"www.castolin.es",
    "wof:name":"Castolin Iberica S.a.",
    "wof:placetype":"venue"
},
  "geometry": {"coordinates":[-3.6592600346,40.5250244141],"type":"Point"}
}