{
  "type": "Feature",
  "properties": {
    "addr:full":"Buiguetes (pol Torrentfondo), 5 S. Lloren\u00e7 Hortons Barcelona 08791",
    "addr:housenumber":"5",
    "addr:postcode":"08791",
    "addr:street":"Torrentfondo;S. Llorenc\u0327",
    "iso:country":"ES",
    "sg:address":"Buiguetes (pol Torrentfondo), 5",
    "sg:city":"S. Lloren\u00e7 Hortons",
    "sg:orig_category":"Delineantes",
    "sg:phone":"+34 937 71 67 54",
    "sg:postcode":"08791",
    "sg:province":"Barcelona",
    "wof:name":"Semitecnic S.l",
    "wof:placetype":"venue"
},
  "geometry": {"coordinates":[1.8232129812,41.4656524658],"type":"Point"}
}