{
  "type": "Feature",
  "properties": {
    "addr:full":"Avda Orense, 72 Puente De Domingo Florez Le\u00f3n 24380",
    "addr:housenumber":"72",
    "addr:postcode":"24380",
    "addr:street":"Avda Orense;Leo\u0301N",
    "iso:country":"ES",
    "sg:address":"Avda Orense, 72",
    "sg:city":"Puente De Domingo Florez",
    "sg:classifiers":[
        {
            "category":"Manufacturing",
            "subcategory":"Building Materials",
            "type":"Manufacturing & Wholesale Goods"
        }
    ],
    "sg:phone":"+34 987 46 06 76",
    "sg:postcode":"24380",
    "sg:province":"Le\u00f3n",
    "sg:tags":[
        "bebidas",
        "para",
        "la",
        "de",
        "y",
        "equipo",
        "industria"
    ],
    "wof:name":"Licores Y Productos Las Medulas S.l.",
    "wof:placetype":"venue"
},
  "geometry": {"coordinates":[-6.8216991425,42.4133415222],"type":"Point"}
}