{
  "type": "Feature",
  "properties": {
    "iso:country":"ES",
    "sg:address":"Calle de Celso Amieva, 28",
    "sg:city":"Llanes",
    "sg:orig_category":"Centros Empresariales",
    "sg:phone":"+34 985 40 00 34",
    "sg:postcode":"33500",
    "sg:province":"Asturias",
    "wof:name":"Dematurpo S.l",
    "wof:placetype":"venue"
},
  "geometry": {"coordinates":[-4.7592349052,43.4242858887],"type":"Point"}
}