{
  "type": "Feature",
  "properties": {
    "iso:country":"ES",
    "sg:address":"Av Catalunya, 421",
    "sg:city":"Palau-solita I Plegamans",
    "sg:orig_category":"Carnicer\u00cdas, Carnicer\u00cdas",
    "sg:phone":"+34 938 64 52 02",
    "sg:postcode":"08184",
    "sg:province":"Barcelona",
    "wof:name":"Sampera Carol Jaume",
    "wof:placetype":"venue"
},
  "geometry": {"coordinates":[2.1803660393,41.5992469788],"type":"Point"}
}