{
  "type": "Feature",
  "properties": {
    "addr:full":"Calle de Galicia, 32 Palmas De Gran Canaria Las Palmas 35007",
    "addr:postcode":"35007",
    "addr:street":"Calle De Galicia 32",
    "iso:country":"ES",
    "sg:address":"Calle de Galicia, 32",
    "sg:city":"Palmas De Gran Canaria",
    "sg:orig_category":"Inmobiliaria (agencias)",
    "sg:phone":"+34 928 26 40 58",
    "sg:postcode":"35007",
    "sg:province":"Las Palmas",
    "wof:name":"Ogarit S.a.",
    "wof:placetype":"venue"
},
  "geometry": {"coordinates":[-15.4334688187,28.1357440948],"type":"Point"}
}