{
  "type": "Feature",
  "properties": {
    "iso:country":"ES",
    "sg:address":"Carrer de Miquel Biada, 119",
    "sg:city":"Mataro",
    "sg:orig_category":"Centros M\u00c9dicos Y Sociales, Dispensarios",
    "sg:phone":"+34 937 98 41 62",
    "sg:postcode":"08302",
    "sg:province":"Barcelona",
    "wof:name":"Meditrauma S.l.",
    "wof:placetype":"venue"
},
  "geometry": {"coordinates":[2.4335539341,41.5371398926],"type":"Point"}
}