{
  "type": "Feature",
  "properties": {
    "iso:country":"ES",
    "sg:address":"Pase Marques De Zafra, 31",
    "sg:city":"Madrid",
    "sg:orig_category":"Peluqueros: De Se\u00d1oras",
    "sg:phone":"+34 913 56 38 75",
    "sg:postcode":"28028",
    "sg:province":"Madrid",
    "wof:name":"Alira Peluqueros S.l.",
    "wof:placetype":"venue"
},
  "geometry": {"coordinates":[-3.6647102833,40.4259376526],"type":"Point"}
}