{
  "type": "Feature",
  "properties": {
    "iso:country":"ES",
    "sg:address":"Avda Monte Igueldo, 39",
    "sg:city":"Madrid",
    "sg:orig_category":"Zapatos (al Por Menor)",
    "sg:phone":"+34 914 77 06 37",
    "sg:postcode":"28053",
    "sg:province":"Madrid",
    "wof:name":"Calzados Mesina S.c.",
    "wof:placetype":"venue"
},
  "geometry": {"coordinates":[-3.6688129902,40.3952713013],"type":"Point"}
}