{
  "type": "Feature",
  "properties": {
    "addr:full":"Avda Conde Campomanes, 21 Tineo Asturias 33870",
    "addr:housenumber":"21",
    "addr:postcode":"33870",
    "addr:street":"Avda Conde Campomanes",
    "iso:country":"ES",
    "sg:address":"Avda Conde Campomanes, 21",
    "sg:city":"Tineo",
    "sg:orig_category":"Cajas Para Embalar",
    "sg:phone":"+34 985 80 14 80",
    "sg:postcode":"33870",
    "sg:province":"Asturias",
    "sg:website":"www.ruralvia.com",
    "wof:name":"Caja Rural De Asturias",
    "wof:placetype":"venue"
},
  "geometry": {"coordinates":[-6.4146389961,43.3345184326],"type":"Point"}
}