{
  "type": "Feature",
  "properties": {
    "addr:full":"Trav Corts, 284 Barcelona Barcelona 08029",
    "addr:housenumber":"284",
    "addr:postcode":"08029",
    "addr:street":"Trav Corts",
    "iso:country":"ES",
    "sg:address":"Trav Corts, 284",
    "sg:city":"Barcelona",
    "sg:orig_category":"Agencias De Viajes",
    "sg:phone":"+34 934 30 23 90",
    "sg:postcode":"08029",
    "sg:province":"Barcelona",
    "wof:name":"Viatges Les Corts S.l.",
    "wof:placetype":"venue"
},
  "geometry": {"coordinates":[2.135874033,41.3871574402],"type":"Point"}
}