{
  "type": "Feature",
  "properties": {
    "iso:country":"ES",
    "sg:address":"Ctra. Girona, 92",
    "sg:city":"Quart",
    "sg:orig_category":"Charcuter\u00cdas (al Por Menor)",
    "sg:phone":"+34 972 46 82 01",
    "sg:postcode":"17242",
    "sg:province":"Girona",
    "wof:name":"Eduardo Planaguma S.a.",
    "wof:placetype":"venue"
},
  "geometry": {"coordinates":[2.8420550823,41.9365539551],"type":"Point"}
}