{
  "type": "Feature",
  "properties": {
    "addr:full":"Calle de Argentina, 23 Coru\u00d1a La Coru\u00f1a 15011",
    "addr:housenumber":"23",
    "addr:postcode":"15011",
    "addr:street":"Calle De Argentina;La Corun\u0303A",
    "iso:country":"ES",
    "sg:address":"Calle de Argentina, 23",
    "sg:city":"Coru\u00d1a",
    "sg:orig_category":"Perfumer\u00cda Y Cosm\u00c9tica (fabricaci\u00d3n, Al Por Mayor)",
    "sg:phone":"+34 981 14 43 12",
    "sg:postcode":"15011",
    "sg:province":"La Coru\u00f1a",
    "wof:name":"Rizzola Cosmetics S.l.",
    "wof:placetype":"venue"
},
  "geometry": {"coordinates":[-8.4207687378,43.3717269897],"type":"Point"}
}