{
  "type": "Feature",
  "properties": {
    "addr:full":"Autovia(p Campollano), 40 Albacete Albacete 02006",
    "addr:housenumber":"40",
    "addr:postcode":"02006",
    "addr:street":"Autovia P Campollano",
    "iso:country":"ES",
    "sg:address":"Autovia(p Campollano), 40",
    "sg:city":"Albacete",
    "sg:orig_category":"Producci\u00d3n, Venta De Productos De Agricultura Biol\u00d3gica",
    "sg:phone":"+34 967 52 07 26",
    "sg:postcode":"02006",
    "sg:province":"Albacete",
    "wof:name":"Alcaliber S. A.",
    "wof:placetype":"venue"
},
  "geometry": {"coordinates":[-1.9490209818,39.013168335],"type":"Point"}
}