{
  "type": "Feature",
  "properties": {
    "addr:full":"Calle de Jorde, 1 Palmas De Gran Canaria Las Palmas 35005",
    "addr:housenumber":"1",
    "addr:postcode":"35005",
    "addr:street":"Calle De Jorde",
    "iso:country":"ES",
    "sg:address":"Calle de Jorde, 1",
    "sg:city":"Palmas De Gran Canaria",
    "sg:orig_category":"Arquitectos",
    "sg:phone":"+34 928 24 02 44",
    "sg:postcode":"35005",
    "sg:province":"Las Palmas",
    "wof:name":"Naranjo Marrero Ana Rosa",
    "wof:placetype":"venue"
},
  "geometry": {"coordinates":[-15.4287538528,28.1262512207],"type":"Point"}
}