{
  "type": "Feature",
  "properties": {
    "addr:full":"Av Primavera, 7 Cerdanyola Valles Barcelona 08290",
    "addr:housenumber":"7",
    "addr:postcode":"08290",
    "addr:street":"Av Primavera;Valles Barcelona",
    "iso:country":"ES",
    "sg:address":"Av Primavera, 7",
    "sg:city":"Cerdanyola Valles",
    "sg:orig_category":"Ropa Para Ni\u00d1os (al Por Menor)",
    "sg:phone":"+34 936 91 41 56",
    "sg:postcode":"08290",
    "sg:province":"Barcelona",
    "wof:name":"Comercial De Confecciones Romar S.l.",
    "wof:placetype":"venue"
},
  "geometry": {"coordinates":[2.1467359066,41.4920043945],"type":"Point"}
}