{
  "type": "Feature",
  "properties": {
    "addr:full":"Calle de Marques De Larios, 6 Malaga M\u00e1laga 29005",
    "addr:housenumber":"6",
    "addr:postcode":"29005",
    "addr:street":"Calle De Marques De Larios;Ma\u0301Laga",
    "iso:country":"ES",
    "sg:address":"Calle de Marques De Larios, 6",
    "sg:city":"Malaga",
    "sg:orig_category":"Ropa Para Caballeros (al Por Menor)",
    "sg:phone":"+34 952 21 17 28",
    "sg:postcode":"29005",
    "sg:province":"M\u00e1laga",
    "wof:name":"Comercio Exportacion E Importacion",
    "wof:placetype":"venue"
},
  "geometry": {"coordinates":[-4.4217658043,36.7196426392],"type":"Point"}
}