{
  "type": "Feature",
  "properties": {
    "iso:country":"ES",
    "sg:address":"Rua Ferradal, S/n",
    "sg:city":"Viana Do Bolo",
    "sg:orig_category":"Asistencia Social",
    "sg:phone":"+34 988 32 91 86",
    "sg:postcode":"32550",
    "sg:province":"Ourense",
    "wof:name":"Xunta De Galicia",
    "wof:placetype":"venue"
},
  "geometry": {"coordinates":[-7.1114602089,42.1794433594],"type":"Point"}
}