{
  "type": "Feature",
  "properties": {
    "iso:country":"ES",
    "sg:address":"Calle de Tercio, S/n",
    "sg:city":"Villalmanzo",
    "sg:orig_category":"Centros De Educaci\u00d3n Especial",
    "sg:phone":"+34 947 17 10 38",
    "sg:postcode":"09390",
    "sg:province":"Burgos",
    "wof:name":"Cra Montearlanza",
    "wof:placetype":"venue"
},
  "geometry": {"coordinates":[-3.7401740551,42.0481300354],"type":"Point"}
}