{
  "type": "Feature",
  "properties": {
    "addr:full":"Avda Literato Azorin, 34 Yecla Murcia 30510",
    "addr:housenumber":"34",
    "addr:postcode":"30510",
    "addr:street":"Avda Literato Azorin",
    "iso:country":"ES",
    "sg:address":"Avda Literato Azorin, 34",
    "sg:city":"Yecla",
    "sg:orig_category":"Hoteles",
    "sg:phone":"+34 968 79 29 08",
    "sg:postcode":"30510",
    "sg:province":"Murcia",
    "wof:name":"Valverde Juarez Emilio",
    "wof:placetype":"venue"
},
  "geometry": {"coordinates":[-1.1080180407,38.613494873],"type":"Point"}
}