{
  "type": "Feature",
  "properties": {
    "iso:country":"ES",
    "sg:address":"Calle de Isla Del Aire, 8",
    "sg:city":"Humanes De Madrid",
    "sg:orig_category":"Guarder\u00cdas",
    "sg:phone":"+34 916 04 09 44",
    "sg:postcode":"28970",
    "sg:province":"Madrid",
    "wof:name":"Salas Blanco Carolina",
    "wof:placetype":"venue"
},
  "geometry": {"coordinates":[-3.8234519958,40.2533798218],"type":"Point"}
}