{
  "type": "Feature",
  "properties": {
    "iso:country":"ES",
    "sg:address":"Avda Elvas, S/n",
    "sg:city":"Badajoz",
    "sg:orig_category":"Bares, Piano",
    "sg:phone":"+34 924 27 54 07",
    "sg:postcode":"06006",
    "sg:province":"Badajoz",
    "wof:name":"Badajoz Charlot S.l.",
    "wof:placetype":"venue"
},
  "geometry": {"coordinates":[-7.0079622269,38.8818092346],"type":"Point"}
}