{
  "type": "Feature",
  "properties": {
    "iso:country":"ES",
    "sg:address":"Carrer de Raimon Casellas, 120",
    "sg:city":"Sabadell",
    "sg:orig_category":"Perfumer\u00cda Y Cosm\u00c9tica (fabricaci\u00d3n, Al Por Mayor)",
    "sg:phone":"+34 937 12 00 24",
    "sg:postcode":"08205",
    "sg:province":"Barcelona",
    "wof:name":"Trigasa S. A.",
    "wof:placetype":"venue"
},
  "geometry": {"coordinates":[2.102560997,41.5311164856],"type":"Point"}
}