{
  "type": "Feature",
  "properties": {
    "addr:full":"Teresitas, S/n San Andres Santa Cruz De Tenerife 38120",
    "addr:housenumber":"/ n",
    "addr:postcode":"38120",
    "addr:street":"Teresitas S",
    "iso:country":"ES",
    "sg:address":"Teresitas, S/n",
    "sg:city":"San Andres",
    "sg:classifiers":[
        {
            "category":"Recreation",
            "type":"Entertainment"
        }
    ],
    "sg:phone":"+34 922 54 94 36",
    "sg:postcode":"38120",
    "sg:province":"Santa Cruz De Tenerife",
    "sg:tags":[
        "caza",
        "pr\u00c1ctica",
        "la",
        "de",
        "pesca",
        "y"
    ],
    "wof:name":"Cofradia De Pescadores De San Andres",
    "wof:placetype":"venue"
},
  "geometry": {"coordinates":[-16.1991291046,28.498884201],"type":"Point"}
}