{
  "type": "Feature",
  "properties": {
    "iso:country":"ES",
    "sg:address":"Carr Cervantes, 16",
    "sg:city":"Picassent",
    "sg:orig_category":"Quincaller\u00cda (al Por Menor)",
    "sg:phone":"+34 961 23 01 38",
    "sg:postcode":"46220",
    "sg:province":"Valencia",
    "wof:name":"Lopez Garcia Jose",
    "wof:placetype":"venue"
},
  "geometry": {"coordinates":[-0.4610910118,39.3612327576],"type":"Point"}
}