{
  "type": "Feature",
  "properties": {
    "iso:country":"ES",
    "sg:address":"Ctra. Matalasca\u00f1as, S/n",
    "sg:city":"El Rocio",
    "sg:orig_category":"Productos Qu\u00cdmicos (fabricaci\u00d3n, Al Por Mayor)",
    "sg:phone":"+34 959 44 24 54",
    "sg:postcode":"21750",
    "sg:province":"Huelva",
    "wof:name":"Petroleum Oil Y Gas Espa\u00d1a S.a.",
    "wof:placetype":"venue"
},
  "geometry": {"coordinates":[-6.4842190742,37.1334342957],"type":"Point"}
}