{
  "type": "Feature",
  "properties": {
    "iso:country":"ES",
    "sg:address":"Calle de General Vives, 28",
    "sg:city":"Ponferrada",
    "sg:orig_category":"Asesor\u00cda De Formaci\u00d3n Y Gesti\u00d3n De Personal",
    "sg:phone":"+34 987 42 81 12",
    "sg:postcode":"24400",
    "sg:province":"Le\u00f3n",
    "wof:name":"Asesores Reunidos Del Bierzo S.l.",
    "wof:placetype":"venue"
},
  "geometry": {"coordinates":[-6.5888915062,42.5482063293],"type":"Point"}
}