{
  "type": "Feature",
  "properties": {
    "iso:country":"ES",
    "sg:address":"Carrer de Carmen Desvalls, 10",
    "sg:city":"Segur Calafell",
    "sg:orig_category":"Inmobiliaria (agencias)",
    "sg:phone":"+34 977 16 43 93",
    "sg:postcode":"43882",
    "sg:province":"Tarragona",
    "wof:name":"Murillo Fondevila Jose Maria",
    "wof:placetype":"venue"
},
  "geometry": {"coordinates":[1.6028029919,41.1905212402],"type":"Point"}
}