{
  "type": "Feature",
  "properties": {
    "iso:country":"ES",
    "sg:address":"Calle de Fuentelahiguera, S/n",
    "sg:city":"Madrid",
    "sg:orig_category":"Negocio De Materiales De Construcci\u00d3n",
    "sg:phone":"+34 917 47 67 20",
    "sg:postcode":"28022",
    "sg:province":"Madrid",
    "wof:name":"Elola S.l.",
    "wof:placetype":"venue"
},
  "geometry": {"coordinates":[-3.5690040588,40.4491844177],"type":"Point"}
}