{
  "type": "Feature",
  "properties": {
    "addr:full":"Calle de Rio Aragon, 7 Cuarte Huerva Zaragoza 50410",
    "addr:housenumber":"7",
    "addr:postcode":"50410",
    "addr:street":"Calle De Rio Aragon",
    "iso:country":"ES",
    "sg:address":"Calle de Rio Aragon, 7",
    "sg:city":"Cuarte Huerva",
    "sg:orig_category":"Artes Gr\u00c1ficas, Artes Pl\u00c1sticas (curso)",
    "sg:phone":"+34 976 50 31 58",
    "sg:postcode":"50410",
    "sg:province":"Zaragoza",
    "wof:name":"Grafimarca S.l.",
    "wof:placetype":"venue"
},
  "geometry": {"coordinates":[-0.9286869764,41.5977249146],"type":"Point"}
}