{
  "type": "Feature",
  "properties": {
    "iso:country":"ES",
    "sg:address":"Calle de Federico Carlos Sainz De Robles, 7",
    "sg:city":"Madrid",
    "sg:classifiers":[
        {
            "category":"Arts & Performance",
            "subcategory":"Art Gallery",
            "type":"Entertainment"
        }
    ],
    "sg:phone":"+34 913 73 78 13",
    "sg:postcode":"28035",
    "sg:province":"Madrid",
    "sg:tags":[
        "obras",
        "de",
        "coleccionismo",
        "compraventa",
        "arte",
        "y"
    ],
    "wof:name":"Pueche Cervera Manuel",
    "wof:placetype":"venue"
},
  "geometry": {"coordinates":[-3.7209839821,40.464630127],"type":"Point"}
}