{
  "type": "Feature",
  "properties": {
    "addr:full":"Avda San Carlos De Chile, 143 Baena C\u00f3rdoba 14850",
    "addr:housenumber":"143",
    "addr:postcode":"14850",
    "addr:street":"Avda San Carlos De Chile",
    "iso:country":"ES",
    "sg:address":"Avda San Carlos De Chile, 143",
    "sg:city":"Baena",
    "sg:orig_category":"Electricidad: Equipos Industriales, Componentes (fabricaci\u00d3n)",
    "sg:phone":"+34 957 69 09 95",
    "sg:postcode":"14850",
    "sg:province":"C\u00f3rdoba",
    "wof:name":"Electro Baena S.l.",
    "wof:placetype":"venue"
},
  "geometry": {"coordinates":[-4.3166890144,37.6225700378],"type":"Point"}
}