{
  "type": "Feature",
  "properties": {
    "iso:country":"ES",
    "sg:address":"Ctra Cardona, 4",
    "sg:city":"Manresa",
    "sg:orig_category":"Molduras, Junquillos, Listones Y Molduras Perforadas",
    "sg:phone":"+34 938 72 43 43",
    "sg:postcode":"08242",
    "sg:province":"Barcelona",
    "wof:name":"Sorinas Ari\u00f1o Jose",
    "wof:placetype":"venue"
},
  "geometry": {"coordinates":[1.8228210211,41.7255477905],"type":"Point"}
}