{
  "type": "Feature",
  "properties": {
    "iso:country":"ES",
    "sg:address":"Carrer de Can Viloca, 85",
    "sg:city":"Sabadell",
    "sg:orig_category":"Molduras, Junquillos, Listones Y Molduras Perforadas",
    "sg:phone":"+34 937 10 64 35",
    "sg:postcode":"08204",
    "sg:province":"Barcelona",
    "wof:name":"Garcia Herrador Ana Maria",
    "wof:placetype":"venue"
},
  "geometry": {"coordinates":[2.122590065,41.5271492004],"type":"Point"}
}