{
  "type": "Feature",
  "properties": {
    "addr:full":"Carr Joaquin Sorolla, S/n Aldaia Valencia 46960",
    "addr:housenumber":"s / n",
    "addr:postcode":"46960",
    "addr:street":"Carr Joaquin Sorolla",
    "iso:country":"ES",
    "sg:address":"Carr Joaquin Sorolla, S/n",
    "sg:city":"Aldaia",
    "sg:orig_category":"Carnicer\u00cdas, Carnicer\u00cdas",
    "sg:phone":"+34 961 51 85 46",
    "sg:postcode":"46960",
    "sg:province":"Valencia",
    "wof:name":"Duran Perez Ana",
    "wof:placetype":"venue"
},
  "geometry": {"coordinates":[-0.459724009,39.4639091492],"type":"Point"}
}