{
  "type": "Feature",
  "properties": {
    "addr:full":"Calle de Jerez, 12 Burgos Burgos 09006",
    "addr:housenumber":"12",
    "addr:postcode":"09006",
    "addr:street":"Calle De Jerez",
    "iso:country":"ES",
    "sg:address":"Calle de Jerez, 12",
    "sg:city":"Burgos",
    "sg:orig_category":"Peluquer\u00cdas, Peluquer\u00cda Mixta",
    "sg:phone":"+34 947 22 43 94",
    "sg:postcode":"09006",
    "sg:province":"Burgos",
    "wof:name":"Vacas Abad Marta",
    "wof:placetype":"venue"
},
  "geometry": {"coordinates":[-3.692843914,42.3548088074],"type":"Point"}
}