{
  "type": "Feature",
  "properties": {
    "iso:country":"ES",
    "sg:address":"Calle de Rego Da Ra\u00d1a, S/n",
    "sg:city":"Arzua",
    "sg:orig_category":"Plomeros",
    "sg:phone":"+34 981 50 03 32",
    "sg:postcode":"15810",
    "sg:province":"La Coru\u00f1a",
    "wof:name":"Rodriguez Rivadulla Jose Luis",
    "wof:placetype":"venue"
},
  "geometry": {"coordinates":[-8.1603536606,42.9272232056],"type":"Point"}
}