{
  "type": "Feature",
  "properties": {
    "iso:country":"ES",
    "sg:address":"Calle de Granada, 32",
    "sg:city":"Albolote",
    "sg:orig_category":"Telas Y Sedas (al Por Menor)",
    "sg:phone":"+34 958 46 56 21",
    "sg:postcode":"18220",
    "sg:province":"Granada",
    "wof:name":"Hijos De Perez Heras S.l",
    "wof:placetype":"venue"
},
  "geometry": {"coordinates":[-3.656111002,37.2295532227],"type":"Point"}
}