{
  "type": "Feature",
  "properties": {
    "iso:country":"ES",
    "sg:address":"Calle de Virgen De Magaceda, 3",
    "sg:city":"Villamayor Santiago",
    "sg:orig_category":"Construcciones Met\u00c1licas",
    "sg:phone":"+34 969 13 96 21",
    "sg:postcode":"16415",
    "sg:province":"Cuenca",
    "wof:name":"Rubio Rodrigo Antonio",
    "wof:placetype":"venue"
},
  "geometry": {"coordinates":[-2.923746109,39.7327957153],"type":"Point"}
}