{
  "type": "Feature",
  "properties": {
    "iso:country":"ES",
    "sg:address":"Calle de Rafael Calvo, 21",
    "sg:city":"Madrid",
    "sg:orig_category":"Electricidad: Instaladores",
    "sg:phone":"+34 913 08 21 38",
    "sg:postcode":"28010",
    "sg:province":"Madrid",
    "wof:name":"Rajado Romero Victoriano",
    "wof:placetype":"venue"
},
  "geometry": {"coordinates":[-3.6930561066,40.4341049194],"type":"Point"}
}