{
  "type": "Feature",
  "properties": {
    "addr:full":"Av. Principe Espa\u00f1a, 64 Tanque Santa Cruz De Tenerife 38435",
    "addr:housenumber":"64",
    "addr:postcode":"38435",
    "addr:street":"Av. Principe Espan\u0303A",
    "iso:country":"ES",
    "sg:address":"Av. Principe Espa\u00f1a, 64",
    "sg:city":"Tanque",
    "sg:orig_category":"Bazares, Art\u00cdculos De Limpieza Y De Cocina (al Por Menor)",
    "sg:phone":"+34 922 13 68 77",
    "sg:postcode":"38435",
    "sg:province":"Santa Cruz De Tenerife",
    "wof:name":"Palgoya S.l.",
    "wof:placetype":"venue"
},
  "geometry": {"coordinates":[-16.7826023102,28.3555679321],"type":"Point"}
}