{
  "type": "Feature",
  "properties": {
    "addr:full":"L. Bravo, 36 Villalonquejar Burgos 09001",
    "addr:housenumber":"36",
    "addr:postcode":"09001",
    "addr:street":"L. Bravo",
    "iso:country":"ES",
    "sg:address":"L. Bravo, 36",
    "sg:city":"Villalonquejar",
    "sg:orig_category":"Panader\u00cdas, Panader\u00cdas",
    "sg:phone":"+34 947 47 32 92",
    "sg:postcode":"09001",
    "sg:province":"Burgos",
    "wof:name":"Berlys Alimentacion S. A.",
    "wof:placetype":"venue"
},
  "geometry": {"coordinates":[-3.7341520786,42.3700256348],"type":"Point"}
}