{
  "type": "Feature",
  "properties": {
    "iso:country":"ES",
    "sg:address":"Calle de Jose Maria Mu\u00d1oz, 44",
    "sg:city":"Cabezuela Valle",
    "sg:orig_category":"Alimentaci\u00d3n General (al Por Menor)",
    "sg:phone":"+34 927 47 23 13",
    "sg:postcode":"10610",
    "sg:province":"C\u00e1ceres",
    "wof:name":"Mahillo Galayo Amador",
    "wof:placetype":"venue"
},
  "geometry": {"coordinates":[-5.8060040474,40.194278717],"type":"Point"}
}