{
  "type": "Feature",
  "properties": {
    "addr:full":"Calle de Ramon Montalvillo, 17 Cuellar Segovia 40200",
    "addr:housenumber":"17",
    "addr:postcode":"40200",
    "addr:street":"Calle De Ramon Montalvillo",
    "iso:country":"ES",
    "sg:address":"Calle de Ramon Montalvillo, 17",
    "sg:city":"Cuellar",
    "sg:orig_category":"Carnicer\u00cdas, Carnicer\u00cdas",
    "sg:phone":"+34 921 14 16 91",
    "sg:postcode":"40200",
    "sg:province":"Segovia",
    "wof:name":"Garcia Zarzuela Pedro",
    "wof:placetype":"venue"
},
  "geometry": {"coordinates":[-4.3199691772,41.4057884216],"type":"Point"}
}