{
  "type": "Feature",
  "properties": {
    "addr:full":"Rua Purificacion Saavedra, 110 Vigo Pontevedra 36207",
    "addr:housenumber":"110",
    "addr:postcode":"36207",
    "addr:street":"Rua Purificacion Saavedra",
    "iso:country":"ES",
    "sg:address":"Rua Purificacion Saavedra, 110",
    "sg:city":"Vigo",
    "sg:orig_category":"Molduras, Junquillos, Listones Y Molduras Perforadas",
    "sg:phone":"+34 986 37 41 68",
    "sg:postcode":"36207",
    "sg:province":"Pontevedra",
    "wof:name":"Catalan Bouzon Maria Vitoria",
    "wof:placetype":"venue"
},
  "geometry": {"coordinates":[-8.6989307404,42.2506103516],"type":"Point"}
}