{
  "type": "Feature",
  "properties": {
    "addr:full":"Calle de San Luis, 3 Alcorcon Madrid 28921",
    "addr:housenumber":"3",
    "addr:postcode":"28921",
    "addr:street":"Calle De San Luis",
    "iso:country":"ES",
    "sg:address":"Calle de San Luis, 3",
    "sg:city":"Alcorcon",
    "sg:orig_category":"Centros Empresariales",
    "sg:phone":"+34 916 44 47 39",
    "sg:postcode":"28921",
    "sg:province":"Madrid",
    "wof:name":"Diaz Gonzalez Maria Del Carmen De La Paz",
    "wof:placetype":"venue"
},
  "geometry": {"coordinates":[-3.8245949745,40.3455123901],"type":"Point"}
}