{
  "type": "Feature",
  "properties": {
    "iso:country":"ES",
    "sg:address":"Calle de Alamedilla, S/n",
    "sg:city":"Cuatro Higueras",
    "sg:orig_category":"Arboricultura Y Producci\u00d3n De Frutas",
    "sg:phone":"+34 950 56 82 36",
    "sg:postcode":"04770",
    "sg:province":"Almer\u00eda",
    "wof:name":"Ranil Fruit Sl",
    "wof:placetype":"venue"
},
  "geometry": {"coordinates":[-2.968752861,36.7574081421],"type":"Point"}
}