{
  "type": "Feature",
  "properties": {
    "iso:country":"ES",
    "sg:address":"Calle de Alfonso Perez, 2",
    "sg:city":"Santander",
    "sg:orig_category":"Distribuci\u00d3n De Petr\u00d3leo Y Derivados",
    "sg:phone":"+34 942 32 04 86",
    "sg:postcode":"39009",
    "sg:province":"Cantabria",
    "wof:name":"Rivero Gonzalez Eduardo",
    "wof:placetype":"venue"
},
  "geometry": {"coordinates":[-3.8245670795,43.4498977661],"type":"Point"}
}