{
  "type": "Feature",
  "properties": {
    "addr:full":"Pl Molina, 5 Barcelona Barcelona 08006",
    "addr:housenumber":"5",
    "addr:postcode":"08006",
    "addr:street":"Pl Molina",
    "iso:country":"ES",
    "sg:address":"Pl Molina, 5",
    "sg:city":"Barcelona",
    "sg:orig_category":"Lencer\u00cda Femenina, Corseter\u00cda, Trajes De Ba\u00d1o (al Por Menor)",
    "sg:phone":"+34 932 00 71 31",
    "sg:postcode":"08006",
    "sg:province":"Barcelona",
    "wof:name":"Lopez Isiegas Felix",
    "wof:placetype":"venue"
},
  "geometry": {"coordinates":[2.1468029022,41.4014091492],"type":"Point"}
}