{
  "type": "Feature",
  "properties": {
    "addr:full":"Calle de Ingeniero Torres Quevedo, 16 Cordoba C\u00f3rdoba 14013",
    "addr:housenumber":"16",
    "addr:postcode":"14013",
    "addr:street":"Calle De Ingeniero Torres Quevedo;Co\u0301Rdoba",
    "iso:country":"ES",
    "sg:address":"Calle de Ingeniero Torres Quevedo, 16",
    "sg:city":"Cordoba",
    "sg:orig_category":"Agencias Y Agentes Comerciales, Representantes",
    "sg:phone":"+34 957 29 57 34",
    "sg:postcode":"14013",
    "sg:province":"C\u00f3rdoba",
    "wof:name":"Santos Cuenca Jose",
    "wof:placetype":"venue"
},
  "geometry": {"coordinates":[-4.7947859764,37.8538742065],"type":"Point"}
}