{
  "type": "Feature",
  "properties": {
    "addr:full":"Rua Travesia, S/n Noia La Coru\u00f1a 15200",
    "addr:housenumber":"s",
    "addr:postcode":"15200",
    "addr:street":"Rua Travesia;/ N;La Corun\u0303A",
    "iso:country":"ES",
    "sg:address":"Rua Travesia, S/n",
    "sg:city":"Noia",
    "sg:orig_category":"Plomeros",
    "sg:phone":"+34 981 82 11 22",
    "sg:postcode":"15200",
    "sg:province":"La Coru\u00f1a",
    "wof:name":"Fontaneria Noyesa S.l.",
    "wof:placetype":"venue"
},
  "geometry": {"coordinates":[-8.8883037567,42.788608551],"type":"Point"}
}