{
  "type": "Feature",
  "properties": {
    "addr:full":"Plaz Espa\u00d1a, 1 Cala\u00f1as Huelva 21300",
    "addr:housenumber":"1",
    "addr:postcode":"21300",
    "addr:street":"Plaz Espan\u0303A",
    "iso:country":"ES",
    "sg:address":"Plaz Espa\u00d1a, 1",
    "sg:city":"Cala\u00f1as",
    "sg:orig_category":"Ense\u00d1anza, Formaci\u00d3n Profesional: Aprendizaje",
    "sg:phone":"+34 959 56 50 00",
    "sg:postcode":"21300",
    "sg:province":"Huelva",
    "wof:name":"Ayuntamiento De Cala\u00f1as",
    "wof:placetype":"venue"
},
  "geometry": {"coordinates":[-6.8994493484,37.6284637451],"type":"Point"}
}