{
  "type": "Feature",
  "properties": {
    "iso:country":"ES",
    "sg:address":"Calle de Castellon De La Plana, 21",
    "sg:city":"Getafe",
    "sg:orig_category":"Ropa Para Ni\u00d1os (al Por Menor)",
    "sg:phone":"+34 916 96 93 59",
    "sg:postcode":"28903",
    "sg:province":"Madrid",
    "wof:name":"Fernandez Simon Julio",
    "wof:placetype":"venue"
},
  "geometry": {"coordinates":[-3.7177703381,40.3122444153],"type":"Point"}
}