{
  "type": "Feature",
  "properties": {
    "iso:country":"ES",
    "sg:address":"Pla\u00c7 Pau Casals, 6",
    "sg:city":"Balaguer",
    "sg:orig_category":"Agentes Generales De Seguros",
    "sg:phone":"+34 973 45 08 09",
    "sg:postcode":"25600",
    "sg:province":"Lleida",
    "wof:name":"Cudos I S.l.",
    "wof:placetype":"venue"
},
  "geometry": {"coordinates":[0.8071600199,41.7896003723],"type":"Point"}
}