{
  "type": "Feature",
  "properties": {
    "addr:full":"Carrer de Pompeu Fabra, 129 Terrassa Barcelona 08226",
    "addr:housenumber":"129",
    "addr:postcode":"08226",
    "addr:street":"Carrer De Pompeu Fabra",
    "iso:country":"ES",
    "sg:address":"Carrer de Pompeu Fabra, 129",
    "sg:city":"Terrassa",
    "sg:orig_category":"Mec\u00c1nico Del Autom\u00d3vil",
    "sg:phone":"+34 937 35 53 07",
    "sg:postcode":"08226",
    "sg:province":"Barcelona",
    "sg:website":"www.garauto.net",
    "wof:name":"T.r.v. Garauto S.l.",
    "wof:placetype":"venue"
},
  "geometry": {"coordinates":[2.023542881,41.5770950317],"type":"Point"}
}