{
  "type": "Feature",
  "properties": {
    "iso:country":"ES",
    "sg:address":"Calle de Fortaleza, 10",
    "sg:city":"Cieza",
    "sg:orig_category":"Delegados, Agentes De Tr\u00c1nsito, Auxiliares De Transporte Internacional",
    "sg:phone":"+34 968 76 06 05",
    "sg:postcode":"30530",
    "sg:province":"Murcia",
    "wof:name":"Morales Garcia Juan",
    "wof:placetype":"venue"
},
  "geometry": {"coordinates":[-1.4297389984,38.2366905212],"type":"Point"}
}