{
  "type": "Feature",
  "properties": {
    "addr:full":"Ctra Nal Trescientos Cuarenta, Km. 0025,4 Mogente Valencia 46640",
    "addr:postcode":"46640",
    "addr:street":"Ctra Nal Trescientos Cuarenta Km. 0025,4",
    "iso:country":"ES",
    "sg:address":"Ctra Nal Trescientos Cuarenta, Km. 0025,4",
    "sg:city":"Mogente",
    "sg:orig_category":"Cajas Y Embalajes De Madera",
    "sg:phone":"+34 962 26 14 57",
    "sg:postcode":"46640",
    "sg:province":"Valencia",
    "wof:name":"Fondos Fomosa S.l.",
    "wof:placetype":"venue"
},
  "geometry": {"coordinates":[-0.7532950044,38.8755226135],"type":"Point"}
}