{
  "type": "Feature",
  "properties": {
    "addr:full":"Carrer de Santa Joana D'arc, 38 Barcelona Barcelona 08032",
    "addr:housenumber":"38",
    "addr:postcode":"08032",
    "addr:street":"Carrer De Santa Joana D'Arc",
    "iso:country":"ES",
    "sg:address":"Carrer de Santa Joana D'arc, 38",
    "sg:city":"Barcelona",
    "sg:orig_category":"Prendas Y Chalecos De Punto (al Por Menor)",
    "sg:phone":"+34 934 20 84 09",
    "sg:postcode":"08032",
    "sg:province":"Barcelona",
    "wof:name":"Granada Bachero Maria Soledad",
    "wof:placetype":"venue"
},
  "geometry": {"coordinates":[2.1585268974,41.428478241],"type":"Point"}
}