{
  "type": "Feature",
  "properties": {
    "addr:full":"Av Onze De Setembre (de L'), 35 Montornes Centre Barcelona 08170",
    "addr:housenumber":"35",
    "addr:postcode":"08170",
    "addr:street":"Av Onze De Setembre De L ';Centre Barcelona",
    "iso:country":"ES",
    "sg:address":"Av Onze De Setembre (de L'), 35",
    "sg:city":"Montornes Centre",
    "sg:orig_category":"Laboratorios Y Trabajos De Fotograf\u00cda, V\u00cddeo Y Cine",
    "sg:phone":"+34 935 68 68 78",
    "sg:postcode":"08170",
    "sg:province":"Barcelona",
    "sg:website":"www.fotoprix.es",
    "wof:name":"Ticubat S.l.",
    "wof:placetype":"venue"
},
  "geometry": {"coordinates":[2.2647869587,41.5435752869],"type":"Point"}
}