{
  "type": "Feature",
  "properties": {
    "addr:full":"Calle de Murgis, 99 Ejido Almer\u00eda 04700",
    "addr:housenumber":"99 ejido",
    "addr:postcode":"04700",
    "addr:street":"Calle De Murgis;Almeri\u0301A",
    "iso:country":"ES",
    "sg:address":"Calle de Murgis, 99",
    "sg:city":"Ejido",
    "sg:orig_category":"Ingenier\u00cda, Centros De Estudios (diversos)",
    "sg:phone":"+34 950 48 29 89",
    "sg:postcode":"04700",
    "sg:province":"Almer\u00eda",
    "wof:name":"C.v. Ingenieria De Iniciativas Y Gestion S.l.",
    "wof:placetype":"venue"
},
  "geometry": {"coordinates":[-2.8045539856,36.7790794373],"type":"Point"}
}