{
  "type": "Feature",
  "properties": {
    "iso:country":"ES",
    "sg:address":"Avda Pio Xii, 32",
    "sg:city":"Sig\u00fcenza",
    "sg:orig_category":"Empresarios",
    "sg:phone":"+34 949 39 03 97",
    "sg:postcode":"19250",
    "sg:province":"Guadalajara",
    "wof:name":"Larriba Yubero Angel",
    "wof:placetype":"venue"
},
  "geometry": {"coordinates":[-2.6447989941,41.0684318542],"type":"Point"}
}