{
  "type": "Feature",
  "properties": {
    "iso:country":"ES",
    "sg:address":"Calle de Alcalde Fernandez Mesa Porras, 6",
    "sg:city":"Cordoba",
    "sg:orig_category":"Molduras, Junquillos, Listones Y Molduras Perforadas",
    "sg:phone":"+34 957 45 45 77",
    "sg:postcode":"14005",
    "sg:province":"C\u00f3rdoba",
    "wof:name":"Navarro Montes Fernando",
    "wof:placetype":"venue"
},
  "geometry": {"coordinates":[-4.7926402092,37.8846168518],"type":"Point"}
}