{
  "type": "Feature",
  "properties": {
    "iso:country":"ES",
    "sg:address":"Calle de Maria De Zapata, 19",
    "sg:city":"Ba\u00d1eza",
    "sg:orig_category":"Electrodom\u00c9sticos (al Por Menor)",
    "sg:phone":"+34 987 65 58 58",
    "sg:postcode":"24750",
    "sg:province":"Le\u00f3n",
    "wof:name":"La Ba\u00f1eza Dotachi S.l.",
    "wof:placetype":"venue"
},
  "geometry": {"coordinates":[-5.9242091179,42.3069114685],"type":"Point"}
}