{
  "type": "Feature",
  "properties": {
    "addr:full":"Calle de Lagasca, 81 Madrid Madrid 28006",
    "addr:housenumber":"81",
    "addr:postcode":"madrid;28006",
    "addr:street":"Calle De Lagasca",
    "iso:country":"ES",
    "sg:address":"Calle de Lagasca, 81",
    "sg:city":"Madrid",
    "sg:orig_category":"Deportes Y Programas De Aventura",
    "sg:phone":"+34 914 31 57 20",
    "sg:postcode":"28006",
    "sg:province":"Madrid",
    "wof:name":"Arivi Trading & Sports S.l.",
    "wof:placetype":"venue"
},
  "geometry": {"coordinates":[-3.6847653389,40.4309883118],"type":"Point"}
}