{
  "type": "Feature",
  "properties": {
    "addr:full":"Calle de Bailen, 9 Chiclana De La Frontera C\u00e1diz 11130",
    "addr:housenumber":"9",
    "addr:postcode":"11130",
    "addr:street":"Calle De Bailen",
    "iso:country":"ES",
    "sg:address":"Calle de Bailen, 9",
    "sg:city":"Chiclana De La Frontera",
    "sg:orig_category":"Plomeros",
    "sg:phone":"+34 956 40 02 68",
    "sg:postcode":"11130",
    "sg:province":"C\u00e1diz",
    "wof:name":"Fontaneria Y Saneamiento Epi S.l.",
    "wof:placetype":"venue"
},
  "geometry": {"coordinates":[-6.1469874382,36.4164733887],"type":"Point"}
}