{
  "type": "Feature",
  "properties": {
    "addr:full":"Pg Cordelles, 29 Cerdanyola Valles Barcelona 08290",
    "addr:housenumber":"29",
    "addr:postcode":"08290",
    "addr:street":"Pg Cordelles;Valles Barcelona",
    "iso:country":"ES",
    "sg:address":"Pg Cordelles, 29",
    "sg:city":"Cerdanyola Valles",
    "sg:orig_category":"Promotores Constructores",
    "sg:phone":"+34 935 80 59 34",
    "sg:postcode":"08290",
    "sg:province":"Barcelona",
    "wof:name":"Construccion E Inmobiliaria Aselco S.a.",
    "wof:placetype":"venue"
},
  "geometry": {"coordinates":[2.1382410526,41.4931221008],"type":"Point"}
}