{
  "type": "Feature",
  "properties": {
    "iso:country":"ES",
    "sg:address":"Carr Lluis Companys, 26",
    "sg:city":"Lleida",
    "sg:orig_category":"Perfumer\u00cda (al Por Menor)",
    "sg:phone":"+34 973 26 47 74",
    "sg:postcode":"25003",
    "sg:province":"Lleida",
    "wof:name":"Garsaball Pizarre Divina",
    "wof:placetype":"venue"
},
  "geometry": {"coordinates":[0.6157823801,41.6118125916],"type":"Point"}
}