{
  "type": "Feature",
  "properties": {
    "addr:full":"Carrer de Fiveller, 141 Sabadell Barcelona 08205",
    "addr:housenumber":"141",
    "addr:postcode":"08205",
    "addr:street":"Carrer De Fiveller",
    "iso:country":"ES",
    "sg:address":"Carrer de Fiveller, 141",
    "sg:city":"Sabadell",
    "sg:orig_category":"Empresas De Desmonte",
    "sg:phone":"+34 937 12 42 59",
    "sg:postcode":"08205",
    "sg:province":"Barcelona",
    "wof:name":"Pujol Esquius Vicente",
    "wof:placetype":"venue"
},
  "geometry": {"coordinates":[2.1005349159,41.5380554199],"type":"Point"}
}