{
  "type": "Feature",
  "properties": {
    "iso:country":"ES",
    "sg:address":"Carr Jonquera, 6",
    "sg:city":"Figueres",
    "sg:orig_category":"Comerciantes Al Por Mayor De Vinos, Licores Y Alcoholes",
    "sg:phone":"+34 972 50 92 06",
    "sg:postcode":"17600",
    "sg:province":"Girona",
    "wof:name":"Castillo Lara Jose",
    "wof:placetype":"venue"
},
  "geometry": {"coordinates":[2.9608430862,42.2677764893],"type":"Point"}
}