{
  "type": "Feature",
  "properties": {
    "addr:full":"Pase Maritimo Rey De Espa\u00d1a, 158 Fuengirola M\u00e1laga 29640",
    "addr:housenumber":"158",
    "addr:postcode":"29640",
    "addr:street":"Ma\u0301Laga",
    "iso:country":"ES",
    "sg:address":"Pase Maritimo Rey De Espa\u00d1a, 158",
    "sg:city":"Fuengirola",
    "sg:orig_category":"Importaci\u00d3n",
    "sg:phone":"+34 952 66 17 17",
    "sg:postcode":"29640",
    "sg:province":"M\u00e1laga",
    "wof:name":"Van Velzen Development B.v.",
    "wof:placetype":"venue"
},
  "geometry": {"coordinates":[-4.6115760803,36.5555305481],"type":"Point"}
}