{
  "type": "Feature",
  "properties": {
    "iso:country":"ES",
    "sg:address":"Avda Palanquinos, S/n",
    "sg:city":"Valencia De Don Juan",
    "sg:orig_category":"Mec\u00c1nico Del Autom\u00d3vil",
    "sg:phone":"+34 987 75 04 46",
    "sg:postcode":"24200",
    "sg:province":"Le\u00f3n",
    "wof:name":"Perez Qui\u00f1ones Eustaqio",
    "wof:placetype":"venue"
},
  "geometry": {"coordinates":[-5.5190520287,42.3010063171],"type":"Point"}
}