{
  "type": "Feature",
  "properties": {
    "iso:country":"ES",
    "sg:address":"Cmno Esgaravita (de La), 32",
    "sg:city":"Alcala Henares",
    "sg:orig_category":"Fabricaci\u00d3n, Venta, Instalaci\u00d3n De R\u00d3tulos, De R\u00d3tulos Luminosos",
    "sg:phone":"+34 918 89 37 90",
    "sg:postcode":"28805",
    "sg:province":"Madrid",
    "wof:name":"Pena Travesi Jose Luis",
    "wof:placetype":"venue"
},
  "geometry": {"coordinates":[-3.3508410454,40.4905967712],"type":"Point"}
}