{
  "type": "Feature",
  "properties": {
    "iso:country":"ES",
    "sg:address":"Calle de Industria, 17",
    "sg:city":"Valencia",
    "sg:orig_category":"Cerrajer\u00cda, Ferrallista",
    "sg:phone":"+34 963 30 35 14",
    "sg:postcode":"46022",
    "sg:province":"Valencia",
    "wof:name":"Navarro Muriach Jose Manuel",
    "wof:placetype":"venue"
},
  "geometry": {"coordinates":[-0.3436169922,39.4645500183],"type":"Point"}
}