{
  "type": "Feature",
  "properties": {
    "addr:full":"Pl Triomf, S/n Terrassa Barcelona 08225",
    "addr:housenumber":"s / n",
    "addr:postcode":"08225",
    "addr:street":"Pl Triomf",
    "iso:country":"ES",
    "sg:address":"Pl Triomf, S/n",
    "sg:city":"Terrassa",
    "sg:orig_category":"Carnicer\u00cdas, Carnicer\u00cdas",
    "sg:phone":"+34 937 35 21 09",
    "sg:postcode":"08225",
    "sg:province":"Barcelona",
    "wof:name":"Sole Pareta Filomena",
    "wof:placetype":"venue"
},
  "geometry": {"coordinates":[2.0134649277,41.5724563599],"type":"Point"}
}