{
  "type": "Feature",
  "properties": {
    "iso:country":"ES",
    "sg:address":"Calle de Caja De Ahorros Municipal, 2",
    "sg:city":"Burgos",
    "sg:orig_category":"Molduras, Junquillos, Listones Y Molduras Perforadas",
    "sg:phone":"+34 947 20 59 52",
    "sg:postcode":"09001",
    "sg:province":"Burgos",
    "wof:name":"Miguel Angel Martinez Rubio Y Otros C.b.",
    "wof:placetype":"venue"
},
  "geometry": {"coordinates":[-3.6993486881,42.3350067139],"type":"Point"}
}