{
  "type": "Feature",
  "properties": {
    "addr:full":"Calle de Alcalde De Zalamea, 36 Algar Murcia 30366",
    "addr:housenumber":"36",
    "addr:postcode":"30366",
    "addr:street":"Calle De Alcalde De Zalamea",
    "iso:country":"ES",
    "sg:address":"Calle de Alcalde De Zalamea, 36",
    "sg:city":"Algar",
    "sg:orig_category":"Inform\u00c1tica, Ofim\u00c1tica (estudios, Asesor\u00cda, Ingenier\u00cda, Formaci\u00d3n)",
    "sg:phone":"+34 968 13 63 93",
    "sg:postcode":"30366",
    "sg:province":"Murcia",
    "wof:name":"Fructuoso Saez Jeronimo",
    "wof:placetype":"venue"
},
  "geometry": {"coordinates":[-0.8680765033,37.6454849243],"type":"Point"}
}