{
  "type": "Feature",
  "properties": {
    "iso:country":"ES",
    "sg:address":"Ctra Murcia-alicante, Km. 0053,0",
    "sg:city":"Elche",
    "sg:orig_category":"Fabricaci\u00d3n De Etiquetas",
    "sg:phone":"+34 966 67 40 52",
    "sg:postcode":"03205",
    "sg:province":"Alicante",
    "wof:name":"Etinsa S.l.",
    "wof:placetype":"venue"
},
  "geometry": {"coordinates":[-0.7237690091,38.2598762512],"type":"Point"}
}