{
  "type": "Feature",
  "properties": {
    "iso:country":"ES",
    "sg:address":"Calle de Jose Maria Osborne, S/n",
    "sg:city":"Sevilla",
    "sg:orig_category":"Autob\u00das (explotaci\u00d3n Y Servicios De)",
    "sg:phone":"+34 954 54 17 95",
    "sg:postcode":"41004",
    "sg:province":"Sevilla",
    "wof:name":"Asintra Andalucia Extremadura A.c.",
    "wof:placetype":"venue"
},
  "geometry": {"coordinates":[-5.9861140251,37.3810081482],"type":"Point"}
}