{
  "type": "Feature",
  "properties": {
    "addr:full":"Carrer de Ferran, 37 Barcelona Barcelona 08002",
    "addr:housenumber":"37",
    "addr:postcode":"08002",
    "addr:street":"Carrer De Ferran",
    "iso:country":"ES",
    "sg:address":"Carrer de Ferran, 37",
    "sg:city":"Barcelona",
    "sg:orig_category":"Zapatos (al Por Menor)",
    "sg:phone":"+34 933 17 81 93",
    "sg:postcode":"08002",
    "sg:province":"Barcelona",
    "wof:name":"Manuel Torremorell Luis",
    "wof:placetype":"venue"
},
  "geometry": {"coordinates":[2.1758489609,41.3817481995],"type":"Point"}
}