{
  "type": "Feature",
  "properties": {
    "iso:country":"ES",
    "sg:address":"Avda Primado Reig, 80",
    "sg:city":"Valencia",
    "sg:orig_category":"Doctores En Medicina",
    "sg:phone":"+34 963 62 91 94",
    "sg:postcode":"46010",
    "sg:province":"Valencia",
    "wof:name":"Merino Gonzalez Angel Luis",
    "wof:placetype":"venue"
},
  "geometry": {"coordinates":[-0.3595229983,39.4811935425],"type":"Point"}
}