{
  "type": "Feature",
  "properties": {
    "iso:country":"ES",
    "sg:address":"Urba Llac Del Cigne, 209",
    "sg:city":"Urbanitzacio Llac Del Cigne",
    "sg:orig_category":"Venta, Instalaci\u00d3n De Calefacci\u00d3n",
    "sg:phone":"+34 972 47 20 99",
    "sg:postcode":"17455",
    "sg:province":"Girona",
    "wof:name":"Insta%acions Carbonell Sl",
    "wof:placetype":"venue"
},
  "geometry": {"coordinates":[2.8018240929,41.8385505676],"type":"Point"}
}