{
  "type": "Feature",
  "properties": {
    "iso:country":"ES",
    "sg:address":"Calle de San Jose Baja, 33",
    "sg:city":"Granada",
    "sg:orig_category":"Venta, Instalaci\u00d3n, Reparaci\u00d3n De Antenas Para Televisi\u00d3n",
    "sg:phone":"+34 958 52 08 80",
    "sg:postcode":"18005",
    "sg:province":"Granada",
    "wof:name":"Cara Ferres Maria Paz",
    "wof:placetype":"venue"
},
  "geometry": {"coordinates":[-3.6011250019,37.1706771851],"type":"Point"}
}