{
  "type": "Feature",
  "properties": {
    "addr:full":"Carrer de Godua, 24 Sant Cristofol Les Fonts Girona 17800",
    "addr:housenumber":"24",
    "addr:postcode":"17800",
    "addr:street":"Carrer De Godua;Cristofol",
    "iso:country":"ES",
    "sg:address":"Carrer de Godua, 24",
    "sg:city":"Sant Cristofol Les Fonts",
    "sg:orig_category":"Trabajos De Aislamiento T\u00c9rmico Y Ac\u00dastico",
    "sg:phone":"+34 972 26 17 40",
    "sg:postcode":"17800",
    "sg:province":"Girona",
    "wof:name":"Lara Garcia Antonio",
    "wof:placetype":"venue"
},
  "geometry": {"coordinates":[2.4893848896,42.1809463501],"type":"Point"}
}