{
  "type": "Feature",
  "properties": {
    "addr:full":"Psaj San Sebastian, 1 Villarrobledo Albacete 02600",
    "addr:housenumber":"1",
    "addr:postcode":"02600",
    "addr:street":"San Sebastian",
    "iso:country":"ES",
    "sg:address":"Psaj San Sebastian, 1",
    "sg:city":"Villarrobledo",
    "sg:orig_category":"Promotores Constructores",
    "sg:phone":"+34 967 14 58 33",
    "sg:postcode":"02600",
    "sg:province":"Albacete",
    "wof:name":"Construcciones Martinez Y Castillo S.b.",
    "wof:placetype":"venue"
},
  "geometry": {"coordinates":[-2.6014010906,39.2680206299],"type":"Point"}
}