{
  "type": "Feature",
  "properties": {
    "iso:country":"ES",
    "sg:address":"Carr Rdo Marc Comes, 8",
    "sg:city":"Balaguer",
    "sg:orig_category":"Florister\u00cdas",
    "sg:phone":"+34 973 45 01 38",
    "sg:postcode":"25600",
    "sg:province":"Lleida",
    "wof:name":"Castell Espasa Marcelo",
    "wof:placetype":"venue"
},
  "geometry": {"coordinates":[0.8102210164,41.7922592163],"type":"Point"}
}