{
  "type": "Feature",
  "properties": {
    "addr:full":"Avda Deportista Isabel Fernandez, 20 Alacant Alicante 03005",
    "addr:housenumber":"20",
    "addr:postcode":"03005",
    "addr:street":"Avda Deportista Isabel Fernandez",
    "iso:country":"ES",
    "sg:address":"Avda Deportista Isabel Fernandez, 20",
    "sg:city":"Alacant",
    "sg:orig_category":"Dise\u00d1o Industrial",
    "sg:phone":"+34 965 17 10 12",
    "sg:postcode":"03005",
    "sg:province":"Alicante",
    "wof:name":"Lopez Miguel Carlos",
    "wof:placetype":"venue"
},
  "geometry": {"coordinates":[-0.5047870278,38.3581085205],"type":"Point"}
}