{
  "type": "Feature",
  "properties": {
    "addr:full":"Calle de Explanada De La Estacion, S/n Malaga M\u00e1laga 29002",
    "addr:postcode":"29002",
    "addr:street":"Calle De Explanada De La Estacion S / N;Ma\u0301Laga",
    "iso:country":"ES",
    "sg:address":"Calle de Explanada De La Estacion, S/n",
    "sg:city":"Malaga",
    "sg:orig_category":"Farmacias",
    "sg:phone":"+34 952 32 05 92",
    "sg:postcode":"29002",
    "sg:province":"M\u00e1laga",
    "wof:name":"Mi\u00f1ana Laliga Jose Victor",
    "wof:placetype":"venue"
},
  "geometry": {"coordinates":[-4.4314541817,36.7128334045],"type":"Point"}
}