{
  "type": "Feature",
  "properties": {
    "addr:full":"Plaz Inmaculada (la), 10 Tamarite Litera Huesca 22550",
    "addr:postcode":"22550",
    "iso:country":"ES",
    "sg:address":"Plaz Inmaculada (la), 10",
    "sg:city":"Tamarite Litera",
    "sg:orig_category":"Fabricaci\u00d3n, Importaci\u00d3n De L\u00c1mparas Y Bombillas",
    "sg:phone":"+34 974 42 00 68",
    "sg:postcode":"22550",
    "sg:province":"Huesca",
    "wof:name":"Puyalto Pocino Emilio",
    "wof:placetype":"venue"
},
  "geometry": {"coordinates":[0.4240469933,41.8659324646],"type":"Point"}
}