{
  "type": "Feature",
  "properties": {
    "addr:full":"Av Coll Del Portell, 59 Barcelona Barcelona 08024",
    "addr:housenumber":"59",
    "addr:postcode":"08024",
    "addr:street":"Av Coll Del Portell",
    "iso:country":"ES",
    "sg:address":"Av Coll Del Portell, 59",
    "sg:city":"Barcelona",
    "sg:orig_category":"Artesan\u00cda",
    "sg:phone":"+34 932 84 47 56",
    "sg:postcode":"08024",
    "sg:province":"Barcelona",
    "wof:name":"Amics De L'espectacle I L'artesania",
    "wof:placetype":"venue"
},
  "geometry": {"coordinates":[2.1522812843,41.4116363525],"type":"Point"}
}