{
  "type": "Feature",
  "properties": {
    "addr:full":"Herradura, 7 Villamayor Salamanca 37185",
    "addr:housenumber":"7",
    "addr:postcode":"37185",
    "addr:street":"Herradura",
    "iso:country":"ES",
    "sg:address":"Herradura, 7",
    "sg:city":"Villamayor",
    "sg:orig_category":"Ingenier\u00cda, Centros De Estudios (diversos)",
    "sg:phone":"+34 923 20 55 07",
    "sg:postcode":"37185",
    "sg:province":"Salamanca",
    "wof:name":"Delgado Terron Carlos",
    "wof:placetype":"venue"
},
  "geometry": {"coordinates":[-5.7186989784,41.0089492798],"type":"Point"}
}