{
  "type": "Feature",
  "properties": {
    "addr:full":"Calle de Antonio Diaz-ca\u00d1abate, 33 Madrid Madrid 28007",
    "addr:housenumber":"33",
    "addr:postcode":"madrid;28007",
    "addr:street":"Calle De Antonio Diaz-Can\u0303Abate",
    "iso:country":"ES",
    "sg:address":"Calle de Antonio Diaz-ca\u00d1abate, 33",
    "sg:city":"Madrid",
    "sg:orig_category":"Arquitectos",
    "sg:phone":"+34 914 33 63 86",
    "sg:postcode":"28007",
    "sg:province":"Madrid",
    "wof:name":"Alvarez Lopez Luis",
    "wof:placetype":"venue"
},
  "geometry": {"coordinates":[-3.6735725403,40.4072952271],"type":"Point"}
}