{
  "type": "Feature",
  "properties": {
    "addr:full":"Pol. Ind. Valle G\u00fcimar, 13 Pol.ind. Guimar Santa Cruz De Tenerife 38509",
    "addr:housenumber":"13",
    "addr:postcode":"38509",
    "addr:street":"Gueimar;Guimar",
    "iso:country":"ES",
    "sg:address":"Pol. Ind. Valle G\u00fcimar, 13",
    "sg:city":"Pol.ind. Guimar",
    "sg:orig_category":"Muebles, Minoristas",
    "sg:phone":"+34 922 50 54 30",
    "sg:postcode":"38509",
    "sg:province":"Santa Cruz De Tenerife",
    "wof:name":"Pikolin S.a.",
    "wof:placetype":"venue"
},
  "geometry": {"coordinates":[-16.3740177155,28.3587932587],"type":"Point"}
}