{
  "type": "Feature",
  "properties": {
    "addr:full":"Calle de Gomez Marin, 1 Villanueva Serena Badajoz 06700",
    "addr:housenumber":"1",
    "addr:postcode":"06700",
    "addr:street":"Calle De Gomez Marin",
    "iso:country":"ES",
    "sg:address":"Calle de Gomez Marin, 1",
    "sg:city":"Villanueva Serena",
    "sg:orig_category":"Abogados",
    "sg:phone":"+34 924 84 34 52",
    "sg:postcode":"06700",
    "sg:province":"Badajoz",
    "wof:name":"Hidalgo Merino Antonio",
    "wof:placetype":"venue"
},
  "geometry": {"coordinates":[-5.7977800369,38.9745445251],"type":"Point"}
}