{
  "type": "Feature",
  "properties": {
    "iso:country":"ES",
    "sg:address":"Rua Ramon Gonzalez, 21",
    "sg:city":"Porri\u00f1o",
    "sg:orig_category":"Droguer\u00cdas (al Por Menor)",
    "sg:phone":"+34 986 33 33 41",
    "sg:postcode":"36400",
    "sg:province":"Pontevedra",
    "wof:name":"Decogar S.a.",
    "wof:placetype":"venue"
},
  "geometry": {"coordinates":[-8.6211442947,42.1612434387],"type":"Point"}
}