{
  "type": "Feature",
  "properties": {
    "iso:country":"ES",
    "sg:address":"Trva Safont, 1",
    "sg:city":"Vinaros",
    "sg:orig_category":"Zapater\u00cdas",
    "sg:phone":"+34 964 45 01 75",
    "sg:postcode":"12500",
    "sg:province":"Castell\u00f3n",
    "wof:name":"Guillot Hospitaler Antonio",
    "wof:placetype":"venue"
},
  "geometry": {"coordinates":[0.4749450088,40.4711990356],"type":"Point"}
}