{
  "type": "Feature",
  "properties": {
    "iso:country":"ES",
    "sg:address":"Carrer de Narcis Monturiol, 19",
    "sg:city":"S. Just Desvern",
    "sg:orig_category":"Alquiler De Veh\u00cdculos: Turismos Y Utilitarios",
    "sg:phone":"+34 934 73 17 04",
    "sg:postcode":"08960",
    "sg:province":"Barcelona",
    "sg:website":"www.fualsa.com",
    "wof:name":"Furgonetas De Alquiler S.a.",
    "wof:placetype":"venue"
},
  "geometry": {"coordinates":[2.0645880699,41.3813858032],"type":"Point"}
}