{
  "type": "Feature",
  "properties": {
    "addr:full":"Calle de Suecia, 1 Pozuelo De Alarcon Madrid 28224",
    "addr:housenumber":"1",
    "addr:postcode":"28224",
    "addr:street":"Calle De Suecia",
    "iso:country":"ES",
    "sg:address":"Calle de Suecia, 1",
    "sg:city":"Pozuelo De Alarcon",
    "sg:orig_category":"Inform\u00c1tica: Consultores",
    "sg:phone":"+34 913 51 30 54",
    "sg:postcode":"28224",
    "sg:province":"Madrid",
    "sg:website":"www.forbes-sinclair.com",
    "wof:name":"Prc.sprategic Tecnologic S.l.",
    "wof:placetype":"venue"
},
  "geometry": {"coordinates":[-3.796585083,40.4374237061],"type":"Point"}
}