{
  "type": "Feature",
  "properties": {
    "iso:country":"ES",
    "sg:address":"Calle de Palencia (de), 4",
    "sg:city":"Fuenlabrada",
    "sg:orig_category":"Zapatos (al Por Menor)",
    "sg:phone":"+34 916 06 68 26",
    "sg:postcode":"28941",
    "sg:province":"Madrid",
    "wof:name":"Sanchez Gonzalez Manuel",
    "wof:placetype":"venue"
},
  "geometry": {"coordinates":[-3.8008890152,40.2952423096],"type":"Point"}
}