{
  "type": "Feature",
  "properties": {
    "iso:country":"ES",
    "sg:address":"Rond Segovia, 79",
    "sg:city":"Madrid",
    "sg:orig_category":"Prot\u00c9sicos Dentales",
    "sg:phone":"+34 913 64 17 28",
    "sg:postcode":"28005",
    "sg:province":"Madrid",
    "wof:name":"Salinas Adeva Juan Manuel",
    "wof:placetype":"venue"
},
  "geometry": {"coordinates":[-3.7133610249,40.4075584412],"type":"Point"}
}