{
  "type": "Feature",
  "properties": {
    "addr:full":"Aviles, 3 Oviedo Asturias 33012",
    "addr:housenumber":"3",
    "addr:postcode":"33012",
    "addr:street":"Aviles",
    "iso:country":"ES",
    "sg:address":"Aviles, 3",
    "sg:city":"Oviedo",
    "sg:orig_category":"Abogados",
    "sg:phone":"+34 985 23 41 13",
    "sg:postcode":"33012",
    "sg:province":"Asturias",
    "wof:name":"Yeguas Garcia Jose",
    "wof:placetype":"venue"
},
  "geometry": {"coordinates":[-5.866622448,43.366859436],"type":"Point"}
}