{
  "type": "Feature",
  "properties": {
    "iso:country":"ES",
    "sg:address":"Ctra. Arenal, 13",
    "sg:city":"Les Meravelles",
    "sg:orig_category":"Ropa Para Se\u00d1oras Y Caballeros (al Por Menor)",
    "sg:phone":"+34 971 26 08 29",
    "sg:postcode":"07610",
    "sg:province":"Islas Baleares",
    "wof:name":"Caballero De Segovia Sanchez Andres",
    "wof:placetype":"venue"
},
  "geometry": {"coordinates":[2.7243249416,39.5336914062],"type":"Point"}
}