{
  "type": "Feature",
  "properties": {
    "addr:full":"Calle de Granada, 2 Monte Lope-alvarez Ja\u00e9n 23615",
    "addr:housenumber":"2",
    "addr:postcode":"23615",
    "addr:street":"Calle De Granada;Jae\u0301N",
    "iso:country":"ES",
    "sg:address":"Calle de Granada, 2",
    "sg:city":"Monte Lope-alvarez",
    "sg:orig_category":"Estancos",
    "sg:phone":"+34 953 57 00 31",
    "sg:postcode":"23615",
    "sg:province":"Ja\u00e9n",
    "wof:name":"Gomez Torres Juan",
    "wof:placetype":"venue"
},
  "geometry": {"coordinates":[-4.1144142151,37.7047233582],"type":"Point"}
}