{
  "type": "Feature",
  "properties": {
    "iso:country":"ES",
    "sg:address":"Avda Vera, 23",
    "sg:city":"Plasencia",
    "sg:orig_category":"Peluqueros: De Se\u00d1oras",
    "sg:phone":"+34 927 42 25 94",
    "sg:postcode":"10600",
    "sg:province":"C\u00e1ceres",
    "wof:name":"Alcon Dominguez Ascension",
    "wof:placetype":"venue"
},
  "geometry": {"coordinates":[-6.0831975937,40.0318260193],"type":"Point"}
}