{
  "type": "Feature",
  "properties": {
    "addr:full":"Avda Carolina Coronado, 21 Badajoz Badajoz 06007",
    "addr:housenumber":"21",
    "addr:postcode":"06007",
    "addr:street":"Avda Carolina Coronado",
    "iso:country":"ES",
    "sg:address":"Avda Carolina Coronado, 21",
    "sg:city":"Badajoz",
    "sg:orig_category":"Ropa Para Caballeros (al Por Menor)",
    "sg:phone":"+34 924 27 07 46",
    "sg:postcode":"06007",
    "sg:province":"Badajoz",
    "wof:name":"Antonelo Moda C.b",
    "wof:placetype":"venue"
},
  "geometry": {"coordinates":[-6.981798172,38.8877334595],"type":"Point"}
}