{
  "type": "Feature",
  "properties": {
    "addr:full":"Calle de Santisima Trinidad, 38 Vall D'uixo Castell\u00f3n 12600",
    "addr:housenumber":"38",
    "addr:postcode":"12600",
    "addr:street":"Calle De Santisima Trinidad",
    "iso:country":"ES",
    "sg:address":"Calle de Santisima Trinidad, 38",
    "sg:city":"Vall D'uixo",
    "sg:orig_category":"Peluqueros: De Se\u00d1oras",
    "sg:phone":"+34 964 66 09 17",
    "sg:postcode":"12600",
    "sg:province":"Castell\u00f3n",
    "wof:name":"Andres Y Pascuala S.l.",
    "wof:placetype":"venue"
},
  "geometry": {"coordinates":[-0.0360242017,39.9860687256],"type":"Point"}
}