{
  "type": "Feature",
  "properties": {
    "iso:country":"ES",
    "sg:address":"Avda Vera, 18",
    "sg:city":"Plasencia",
    "sg:orig_category":"Ropa De Hogar (al Por Menor)",
    "sg:phone":"+34 927 41 19 77",
    "sg:postcode":"10600",
    "sg:province":"C\u00e1ceres",
    "wof:name":"Tejeda Perez Maria Yolanda",
    "wof:placetype":"venue"
},
  "geometry": {"coordinates":[-6.0832571983,40.0317001343],"type":"Point"}
}