{
  "type": "Feature",
  "properties": {
    "addr:full":"Calle de Armada Espa\u00d1ola, 37 Huescar Granada 18830",
    "addr:housenumber":"37",
    "addr:postcode":"18830",
    "addr:street":"Calle De Armada Espan\u0303Ola",
    "iso:country":"ES",
    "sg:address":"Calle de Armada Espa\u00d1ola, 37",
    "sg:city":"Huescar",
    "sg:orig_category":"Molduras, Junquillos, Listones Y Molduras Perforadas",
    "sg:phone":"+34 958 74 26 04",
    "sg:postcode":"18830",
    "sg:province":"Granada",
    "wof:name":"Ujaque Chillon Andres",
    "wof:placetype":"venue"
},
  "geometry": {"coordinates":[-2.5429360867,37.8127288818],"type":"Point"}
}