{
  "type": "Feature",
  "properties": {
    "iso:country":"ES",
    "sg:address":"Avgd Segre, 10",
    "sg:city":"Lleida",
    "sg:classifiers":[
        {
            "category":"Banks & Credit Unions",
            "subcategory":"Bureau De Change",
            "type":"Services"
        }
    ],
    "sg:phone":"+34 973 22 07 77",
    "sg:postcode":"25007",
    "sg:province":"Lleida",
    "sg:tags":[
        "organismos",
        "control"
    ],
    "wof:name":"Icict S.a.",
    "wof:placetype":"venue"
},
  "geometry": {"coordinates":[0.6335679889,41.6172065735],"type":"Point"}
}