{
  "type": "Feature",
  "properties": {
    "addr:full":"Carrer de Besalu, 18 Poligon Industrial Pla De La Bruguera Barcelona 08211",
    "addr:housenumber":"18",
    "addr:postcode":"08211",
    "addr:street":"Carrer De Besalu;Industrial;De",
    "iso:country":"ES",
    "sg:address":"Carrer de Besalu, 18",
    "sg:city":"Poligon Industrial Pla De La Bruguera",
    "sg:orig_category":"Carnicer\u00cdas, Carnicer\u00cdas",
    "sg:phone":"+34 937 14 26 70",
    "sg:postcode":"08211",
    "sg:province":"Barcelona",
    "wof:name":"Productos Javalcon S.l.",
    "wof:placetype":"venue"
},
  "geometry": {"coordinates":[2.0824799538,41.6114387512],"type":"Point"}
}