{
  "type": "Feature",
  "properties": {
    "iso:country":"ES",
    "sg:address":"Av. Leclerc, 1",
    "sg:city":"Carbajosa Sagrada",
    "sg:orig_category":"Tintorer\u00cdas, Limpieza En Seco",
    "sg:phone":"+34 923 20 14 41",
    "sg:postcode":"37188",
    "sg:province":"Salamanca",
    "sg:website":"www.pressto.com",
    "wof:name":"Garcia Valverde Alfonso",
    "wof:placetype":"venue"
},
  "geometry": {"coordinates":[-5.6511440277,40.934211731],"type":"Point"}
}