{
  "type": "Feature",
  "properties": {
    "iso:country":"ES",
    "sg:address":"Calle de Antonio Salado, 8",
    "sg:city":"Sevilla",
    "sg:orig_category":"Sindicatos De Trabajadores",
    "sg:phone":"+34 954 90 84 06",
    "sg:postcode":"41002",
    "sg:province":"Sevilla",
    "wof:name":"Federacion De Servicios Publicos De Ugt",
    "wof:placetype":"venue"
},
  "geometry": {"coordinates":[-6.0011234283,37.393863678],"type":"Point"}
}