{
  "type": "Feature",
  "properties": {
    "iso:country":"ES",
    "sg:address":"Carrer de Navarra (de), 9",
    "sg:city":"Salou",
    "sg:orig_category":"Molduras, Junquillos, Listones Y Molduras Perforadas",
    "sg:phone":"+34 977 38 26 12",
    "sg:postcode":"43840",
    "sg:province":"Tarragona",
    "wof:name":"Bar Xamos C.b.",
    "wof:placetype":"venue"
},
  "geometry": {"coordinates":[1.1465909481,41.075717926],"type":"Point"}
}