{
  "type": "Feature",
  "properties": {
    "iso:country":"ES",
    "sg:address":"Plaz Mayor, 14",
    "sg:city":"Alba Tormes",
    "sg:orig_category":"Electricidad (montaje, Ensamblaje De Componentes)",
    "sg:phone":"+34 923 30 01 66",
    "sg:postcode":"37800",
    "sg:province":"Salamanca",
    "wof:name":"Mu\u00f1oz Diaz Lucas",
    "wof:placetype":"venue"
},
  "geometry": {"coordinates":[-5.5114722252,40.8238334656],"type":"Point"}
}