{
  "type": "Feature",
  "properties": {
    "addr:full":"Calle de Batan, 42 Pinos-puente Granada 18240",
    "addr:housenumber":"42",
    "addr:postcode":"18240",
    "addr:street":"Calle De Batan",
    "iso:country":"ES",
    "sg:address":"Calle de Batan, 42",
    "sg:city":"Pinos-puente",
    "sg:orig_category":"Comercio De Piezas De Recambio Y De Accesorios De Veh\u00cdculos, Veh\u00cdculos Industriales",
    "sg:phone":"+34 958 45 24 57",
    "sg:postcode":"18240",
    "sg:province":"Granada",
    "wof:name":"Royce Autorecambios S.l.",
    "wof:placetype":"venue"
},
  "geometry": {"coordinates":[-3.7436964512,37.2480201721],"type":"Point"}
}