{
  "type": "Feature",
  "properties": {
    "addr:full":"Cno Vi\u00f1azos, 1 Casariche Sevilla 41580",
    "addr:housenumber":"1",
    "addr:postcode":"41580",
    "addr:street":"Cno Vin\u0303Azos",
    "iso:country":"ES",
    "sg:address":"Cno Vi\u00f1azos, 1",
    "sg:city":"Casariche",
    "sg:orig_category":"Producci\u00d3n De Abonos Y De Fertilizantes",
    "sg:phone":"+34 954 01 18 52",
    "sg:postcode":"41580",
    "sg:province":"Sevilla",
    "sg:website":"www.agroquimicosborrego.com",
    "wof:name":"Agroquimicos Borrego S.l.",
    "wof:placetype":"venue"
},
  "geometry": {"coordinates":[-4.7573308945,37.2992210388],"type":"Point"}
}