{
  "type": "Feature",
  "properties": {
    "addr:full":"Riera (la), 74 Mataro Barcelona 08301",
    "addr:postcode":"08301",
    "addr:street":"Riera",
    "iso:country":"ES",
    "sg:address":"Riera (la), 74",
    "sg:city":"Mataro",
    "sg:orig_category":"Ropa Para Se\u00d1oras Y Caballeros (al Por Menor)",
    "sg:phone":"+34 937 96 22 53",
    "sg:postcode":"08301",
    "sg:province":"Barcelona",
    "wof:name":"Masramon Vilaro Ramon",
    "wof:placetype":"venue"
},
  "geometry": {"coordinates":[2.4439051151,41.5415153503],"type":"Point"}
}