{
  "type": "Feature",
  "properties": {
    "iso:country":"ES",
    "sg:address":"Rudaguera, 35",
    "sg:city":"Rudaguera",
    "sg:orig_category":"T\u00c9cnicos Veterinarios",
    "sg:phone":"+34 942 71 90 76",
    "sg:postcode":"39539",
    "sg:province":"Cantabria",
    "wof:name":"Crespo Garcia Maria Jesus",
    "wof:placetype":"venue"
},
  "geometry": {"coordinates":[-4.1089868546,43.3644638062],"type":"Point"}
}