{
  "type": "Feature",
  "properties": {
    "addr:full":"Calle de Pintor Rosales, 41 Roquetas Mar Almer\u00eda 04740",
    "addr:housenumber":"41",
    "addr:postcode":"04740",
    "addr:street":"Calle De Pintor Rosales;Mar Almeri\u0301A",
    "iso:country":"ES",
    "sg:address":"Calle de Pintor Rosales, 41",
    "sg:city":"Roquetas Mar",
    "sg:orig_category":"Asesor\u00cda Fiscal Y Jur\u00cddica",
    "sg:phone":"+34 950 32 56 19",
    "sg:postcode":"04740",
    "sg:province":"Almer\u00eda",
    "wof:name":"Andujar Rodriguez Gabriel",
    "wof:placetype":"venue"
},
  "geometry": {"coordinates":[-2.6167168617,36.7609519958],"type":"Point"}
}