{
  "type": "Feature",
  "properties": {
    "iso:country":"ES",
    "sg:address":"Ctra Santander, S/n",
    "sg:city":"Monzon De Campos",
    "sg:orig_category":"Hoteles",
    "sg:phone":"+34 979 80 82 81",
    "sg:postcode":"34410",
    "sg:province":"Palencia",
    "wof:name":"Afanus S.l.",
    "wof:placetype":"venue"
},
  "geometry": {"coordinates":[-4.4900159836,42.1168251038],"type":"Point"}
}