{
  "type": "Feature",
  "properties": {
    "addr:full":"Calle de Gobernador Fernandez Jimenez (del), 6 Segovia Segovia 40001",
    "addr:housenumber":"6",
    "addr:postcode":"40001",
    "addr:street":"Calle De Gobernador Fernandez Jimenez Del",
    "iso:country":"ES",
    "sg:address":"Calle de Gobernador Fernandez Jimenez (del), 6",
    "sg:city":"Segovia",
    "sg:orig_category":"Herboristas (al Por Menor)",
    "sg:phone":"+34 921 43 13 59",
    "sg:postcode":"40001",
    "sg:province":"Segovia",
    "wof:name":"Isabel Blanco Jesus Miguel",
    "wof:placetype":"venue"
},
  "geometry": {"coordinates":[-4.1191496849,40.9460754395],"type":"Point"}
}