{
  "type": "Feature",
  "properties": {
    "addr:full":"Calle de Andres Segovia, 35 Granada Granada 18008",
    "addr:housenumber":"35",
    "addr:postcode":"18008",
    "addr:street":"Calle De Andres Segovia",
    "iso:country":"ES",
    "sg:address":"Calle de Andres Segovia, 35",
    "sg:city":"Granada",
    "sg:orig_category":"Administradores De Bienes Y Delegados De Comunidades De Propietarios",
    "sg:phone":"+34 958 13 55 74",
    "sg:postcode":"18008",
    "sg:province":"Granada",
    "wof:name":"Santiago Huertes Jose",
    "wof:placetype":"venue"
},
  "geometry": {"coordinates":[-3.5943489075,37.1633796692],"type":"Point"}
}