{
  "type": "Feature",
  "properties": {
    "addr:full":"Zona Bacone, S/n L'ampolla Tarragona 43895",
    "addr:housenumber":"s / n",
    "addr:postcode":"43895",
    "iso:country":"ES",
    "sg:address":"Zona Bacone, S/n",
    "sg:city":"L'ampolla",
    "sg:orig_category":"Bebidas",
    "sg:phone":"+34 977 46 03 63",
    "sg:postcode":"43895",
    "sg:province":"Tarragona",
    "wof:name":"Colomines S.l.",
    "wof:placetype":"venue"
},
  "geometry": {"coordinates":[0.7183210254,40.8147468567],"type":"Point"}
}