{
  "type": "Feature",
  "properties": {
    "addr:full":"C/ Emilio Sala Hernandez, 38 Elche Alicante 03205",
    "addr:housenumber":"38",
    "addr:postcode":"03205",
    "addr:street":"C / Emilio Sala Hernandez",
    "iso:country":"ES",
    "sg:address":"C/ Emilio Sala Hernandez, 38",
    "sg:city":"Elche",
    "sg:orig_category":"Electrodom\u00c9sticos (al Por Menor)",
    "sg:phone":"+34 965 43 19 39",
    "sg:postcode":"03205",
    "sg:province":"Alicante",
    "wof:name":"Rico Ruiz David",
    "wof:placetype":"venue"
},
  "geometry": {"coordinates":[-0.7154170275,38.272315979],"type":"Point"}
}