{
  "type": "Feature",
  "properties": {
    "iso:country":"ES",
    "sg:address":"Carr Major, 1",
    "sg:city":"Angles",
    "sg:orig_category":"Clases De M\u00dasica Y Canto",
    "sg:phone":"+34 972 42 02 01",
    "sg:postcode":"17160",
    "sg:province":"Girona",
    "wof:name":"Aula De Musica De Angles S.c.",
    "wof:placetype":"venue"
},
  "geometry": {"coordinates":[2.639786005,41.9570503235],"type":"Point"}
}