{
  "type": "Feature",
  "properties": {
    "iso:country":"ES",
    "sg:address":"Avda Jose Luis Arrese, 6",
    "sg:city":"Valladolid",
    "sg:orig_category":"Mec\u00c1nico Del Autom\u00d3vil",
    "sg:phone":"+34 983 37 90 11",
    "sg:postcode":"47014",
    "sg:province":"Valladolid",
    "wof:name":"Champiuon-car S.l.",
    "wof:placetype":"venue"
},
  "geometry": {"coordinates":[-4.7358880043,41.6499977112],"type":"Point"}
}