{
  "type": "Feature",
  "properties": {
    "addr:full":"Calle de Universidad, 36 Burgo Osma Soria 42300",
    "addr:housenumber":"36",
    "addr:postcode":"42300",
    "addr:street":"Calle De Universidad",
    "iso:country":"ES",
    "sg:address":"Calle de Universidad, 36",
    "sg:city":"Burgo Osma",
    "sg:orig_category":"Arenas, Guijarros Y Granulados",
    "sg:phone":"+34 975 34 07 04",
    "sg:postcode":"42300",
    "sg:province":"Soria",
    "wof:name":"Del Pino Y Mateo S.l.",
    "wof:placetype":"venue"
},
  "geometry": {"coordinates":[-3.062928915,41.5874137878],"type":"Point"}
}