{
  "type": "Feature",
  "properties": {
    "addr:full":"Calle de Puente Colgante, 37 Valladolid Valladolid 47007",
    "addr:housenumber":"37",
    "addr:postcode":"47007",
    "addr:street":"Calle De Puente Colgante",
    "iso:country":"ES",
    "sg:address":"Calle de Puente Colgante, 37",
    "sg:city":"Valladolid",
    "sg:orig_category":"Molduras, Junquillos, Listones Y Molduras Perforadas",
    "sg:phone":"+34 983 23 03 62",
    "sg:postcode":"47007",
    "sg:province":"Valladolid",
    "wof:name":"Bar Cerveceria Malaga C.b.",
    "wof:placetype":"venue"
},
  "geometry": {"coordinates":[-4.7355461121,41.6407699585],"type":"Point"}
}