{
  "type": "Feature",
  "properties": {
    "addr:full":"Ctra. Burgos-portugal, S/n Espeja Salamanca 37497",
    "addr:housenumber":"s / n",
    "addr:postcode":"37497",
    "addr:street":"Ctra. Burgos-Portugal",
    "iso:country":"ES",
    "sg:address":"Ctra. Burgos-portugal, S/n",
    "sg:city":"Espeja",
    "sg:orig_category":"Distribuci\u00d3n De Petr\u00d3leo Y Derivados",
    "sg:phone":"+34 923 48 38 31",
    "sg:postcode":"37497",
    "sg:province":"Salamanca",
    "sg:website":"www.cepsa.es",
    "wof:name":"Cedipsa Compa\u00d1ia Espa\u00d1ola Distribuidora De Petroleos S.a.",
    "wof:placetype":"venue"
},
  "geometry": {"coordinates":[-6.719645977,40.6734466553],"type":"Point"}
}