{
  "type": "Feature",
  "properties": {
    "addr:full":"Av Enric Benet, 6 Vila-rodona Tarragona 43814",
    "addr:housenumber":"6",
    "addr:postcode":"43814",
    "addr:street":"Av Enric Benet",
    "iso:country":"ES",
    "sg:address":"Av Enric Benet, 6",
    "sg:city":"Vila-rodona",
    "sg:orig_category":"Asociaciones, Organismos Culturales Y Socioeducativos",
    "sg:phone":"+34 977 63 80 78",
    "sg:postcode":"43814",
    "sg:province":"Tarragona",
    "wof:name":"Casal De Vilarrodona",
    "wof:placetype":"venue"
},
  "geometry": {"coordinates":[1.3581440449,41.3097610474],"type":"Point"}
}