{
  "type": "Feature",
  "properties": {
    "iso:country":"ES",
    "sg:address":"Calle de Agramunt, 2",
    "sg:city":"Madrid",
    "sg:orig_category":"Bisuteros (fabricaci\u00d3n, Al Por Mayor)",
    "sg:phone":"+34 913 29 59 33",
    "sg:postcode":"28042",
    "sg:province":"Madrid",
    "wof:name":"Carrasco Y Vazquez Joyeros S.l.",
    "wof:placetype":"venue"
},
  "geometry": {"coordinates":[-3.5885221958,40.4704933167],"type":"Point"}
}