{
  "type": "Feature",
  "properties": {
    "addr:full":"Pla\u00c7 Pla\u00c7a Del Regne, 1 Alzira Valencia 46600",
    "addr:housenumber":"1",
    "addr:postcode":"46600",
    "addr:street":"Regne",
    "iso:country":"ES",
    "sg:address":"Pla\u00c7 Pla\u00c7a Del Regne, 1",
    "sg:city":"Alzira",
    "sg:orig_category":"Abogados",
    "sg:phone":"+34 962 41 78 87",
    "sg:postcode":"46600",
    "sg:province":"Valencia",
    "wof:name":"Despacho De Abogados Ferrer Y Dolz C.b.",
    "wof:placetype":"venue"
},
  "geometry": {"coordinates":[-0.4378489852,39.1517295837],"type":"Point"}
}