{
  "type": "Feature",
  "properties": {
    "iso:country":"ES",
    "sg:address":"Cra Jerez-los Barrios, S/n",
    "sg:city":"A. Gazules",
    "sg:classifiers":[
        {
            "category":"Banks & Credit Unions",
            "subcategory":"Bureau De Change",
            "type":"Services"
        }
    ],
    "sg:phone":"+34 956 42 02 13",
    "sg:postcode":"11180",
    "sg:province":"C\u00e1diz",
    "sg:tags":[
        "organismos",
        "control"
    ],
    "sg:website":"www.euroconsult.es",
    "wof:name":"Euroconsult S. A.",
    "wof:placetype":"venue"
},
  "geometry": {"coordinates":[-5.7211689949,36.4625244141],"type":"Point"}
}