{
  "type": "Feature",
  "properties": {
    "iso:country":"ES",
    "sg:address":"Calle de Capuchinas, 16",
    "sg:city":"Granada",
    "sg:orig_category":"Cl\u00cdnicas M\u00c9dicas",
    "sg:phone":"+34 958 25 52 24",
    "sg:postcode":"18001",
    "sg:province":"Granada",
    "wof:name":"Sanchez Rodriguez Margarita",
    "wof:placetype":"venue"
},
  "geometry": {"coordinates":[-3.6003684998,37.1763191223],"type":"Point"}
}