{
  "type": "Feature",
  "properties": {
    "iso:country":"ES",
    "sg:address":"Calle de Acera Del Darro, 74",
    "sg:city":"Granada",
    "sg:orig_category":"Cervecer\u00cdas",
    "sg:phone":"+34 958 25 57 96",
    "sg:postcode":"18005",
    "sg:province":"Granada",
    "wof:name":"Cerveceros De Wisconsin S.l.",
    "wof:placetype":"venue"
},
  "geometry": {"coordinates":[-3.5978302956,37.1700172424],"type":"Point"}
}