{
  "type": "Feature",
  "properties": {
    "iso:country":"ES",
    "sg:address":"Calle de Portal De Gamarra, 1",
    "sg:city":"Vitoria-gasteiz",
    "sg:orig_category":"Inform\u00c1tica (estudios, Servicios, Asesor\u00cda, Formaci\u00d3n)",
    "sg:phone":"+34 945 12 26 68",
    "sg:postcode":"01013",
    "sg:province":"\u00c1lava",
    "sg:website":"www.profit.com",
    "wof:name":"Sopra Profit S.a.u.",
    "wof:placetype":"venue"
},
  "geometry": {"coordinates":[-2.6631970406,42.8582687378],"type":"Point"}
}