{
  "type": "Feature",
  "properties": {
    "iso:country":"ES",
    "sg:address":"Ctra Toledo Alcazar, Km. 0061,3",
    "sg:city":"Consuegra",
    "sg:orig_category":"Mec\u00c1nico Del Autom\u00d3vil",
    "sg:phone":"+34 925 48 15 72",
    "sg:postcode":"45700",
    "sg:province":"Toledo",
    "wof:name":"Galvez Moreno Luis",
    "wof:placetype":"venue"
},
  "geometry": {"coordinates":[-3.5563373566,39.4645881653],"type":"Point"}
}