{
  "type": "Feature",
  "properties": {
    "addr:full":"Pol. Ind. Rio Do Pozo, S/n Naron La Coru\u00f1a 15578",
    "addr:housenumber":"s",
    "addr:postcode":"15578",
    "addr:street":"/ N;La Corun\u0303A",
    "iso:country":"ES",
    "sg:address":"Pol. Ind. Rio Do Pozo, S/n",
    "sg:city":"Naron",
    "sg:orig_category":"Hormigonados",
    "sg:phone":"+34 981 38 55 59",
    "sg:postcode":"15578",
    "sg:province":"La Coru\u00f1a",
    "wof:name":"Prebetong Galicia S.a.",
    "wof:placetype":"venue"
},
  "geometry": {"coordinates":[-8.1806354523,43.5493278503],"type":"Point"}
}