{
  "type": "Feature",
  "properties": {
    "addr:full":"Ctra Crevillente, Km. 0002,0 Elche Alicante 03205",
    "addr:postcode":"03205",
    "addr:street":"Ctra Crevillente Km. 0002,0",
    "iso:country":"ES",
    "sg:address":"Ctra Crevillente, Km. 0002,0",
    "sg:city":"Elche",
    "sg:orig_category":"Artes Gr\u00c1ficas, Artes Pl\u00c1sticas (curso)",
    "sg:phone":"+34 965 43 13 13",
    "sg:postcode":"03205",
    "sg:province":"Alicante",
    "wof:name":"Graficas Rocamora S.l.",
    "wof:placetype":"venue"
},
  "geometry": {"coordinates":[-0.7338123918,38.2586402893],"type":"Point"}
}