{
  "type": "Feature",
  "properties": {
    "iso:country":"ES",
    "sg:address":"Calle de Antonio Oliver, 2",
    "sg:city":"San Antonio Abad",
    "sg:orig_category":"Agencias Y Agentes Comerciales, Representantes",
    "sg:phone":"+34 968 51 43 23",
    "sg:postcode":"30204",
    "sg:province":"Murcia",
    "wof:name":"Campos Calderon Jose Gabriel",
    "wof:placetype":"venue"
},
  "geometry": {"coordinates":[-0.9906253219,37.6168823242],"type":"Point"}
}