{
  "type": "Feature",
  "properties": {
    "addr:full":"Pase Castellana, 265 Madrid Madrid 28046",
    "addr:housenumber":"265",
    "addr:postcode":"28046",
    "addr:street":"Castellana",
    "iso:country":"ES",
    "sg:address":"Pase Castellana, 265",
    "sg:city":"Madrid",
    "sg:orig_category":"Aparcamientos (infraestructuras, Accesorios)",
    "sg:phone":"+34 917 29 00 50",
    "sg:postcode":"28046",
    "sg:province":"Madrid",
    "wof:name":"Metropark Aparcamientos S.a.",
    "wof:placetype":"venue"
},
  "geometry": {"coordinates":[-3.6893663406,40.4541549683],"type":"Point"}
}