{
  "type": "Feature",
  "properties": {
    "addr:full":"Ptge Marco Polo, 13 Sabadell Barcelona 08208",
    "addr:housenumber":"13",
    "addr:postcode":"08208",
    "addr:street":"Ptge Marco Polo",
    "iso:country":"ES",
    "sg:address":"Ptge Marco Polo, 13",
    "sg:city":"Sabadell",
    "sg:orig_category":"Reposter\u00cdas",
    "sg:phone":"+34 937 16 68 71",
    "sg:postcode":"08208",
    "sg:province":"Barcelona",
    "wof:name":"Panificadora Valero S.a.",
    "wof:placetype":"venue"
},
  "geometry": {"coordinates":[2.1052548885,41.5658378601],"type":"Point"}
}