{
  "type": "Feature",
  "properties": {
    "iso:country":"ES",
    "sg:address":"Luis Morondo Urra, 10",
    "sg:city":"Iru\u00f1a",
    "sg:orig_category":"Asociaciones Humanitarias, De Cooperaci\u00d3n, De Acci\u00d3n Social",
    "sg:phone":"+34 948 24 20 07",
    "sg:postcode":"31006",
    "sg:province":"Navarra",
    "wof:name":"Leoz Telleria Maria Jose",
    "wof:placetype":"venue"
},
  "geometry": {"coordinates":[-1.646132946,42.8012275696],"type":"Point"}
}