{
  "type": "Feature",
  "properties": {
    "iso:country":"ES",
    "sg:address":"Calle de Francisco Garcia, 40",
    "sg:city":"Langreo",
    "sg:orig_category":"Abogados",
    "sg:phone":"+34 985 69 57 99",
    "sg:postcode":"33934",
    "sg:province":"Asturias",
    "wof:name":"Alonso Garcia Arguelles Sara",
    "wof:placetype":"venue"
},
  "geometry": {"coordinates":[-5.7064862251,43.3025093079],"type":"Point"}
}