{
  "type": "Feature",
  "properties": {
    "iso:country":"ES",
    "sg:address":"Calle de Fuencarral, 82",
    "sg:city":"Madrid",
    "sg:orig_category":"Asesor\u00cda Sobre Comunicaci\u00d3n De Empresas",
    "sg:phone":"+34 915 22 37 55",
    "sg:postcode":"28004",
    "sg:province":"Madrid",
    "wof:name":"Gonzalez Martin Jose Clemente",
    "wof:placetype":"venue"
},
  "geometry": {"coordinates":[-3.7011950016,40.4263916016],"type":"Point"}
}