{
  "type": "Feature",
  "properties": {
    "iso:country":"ES",
    "sg:address":"Carrer de Bizet, 18",
    "sg:city":"Rubi",
    "sg:orig_category":"Contenedores (mercanc\u00cdas)",
    "sg:phone":"+34 936 99 16 11",
    "sg:postcode":"08191",
    "sg:province":"Barcelona",
    "sg:website":"www.ldi.extndno.com",
    "wof:name":"Long Distance Intercontinental S.l.",
    "wof:placetype":"venue"
},
  "geometry": {"coordinates":[2.0232539177,41.4722747803],"type":"Point"}
}