{
  "type": "Feature",
  "properties": {
    "addr:full":"Carr Pere Iii, 2 Villarreal Castell\u00f3n 12540",
    "addr:housenumber":"2",
    "addr:postcode":"12540",
    "addr:street":"Carr Pere Iii",
    "iso:country":"ES",
    "sg:address":"Carr Pere Iii, 2",
    "sg:city":"Villarreal",
    "sg:orig_category":"Partidos Pol\u00cdticos",
    "sg:phone":"+34 964 52 63 15",
    "sg:postcode":"12540",
    "sg:province":"Castell\u00f3n",
    "wof:name":"Partit Carlista Del Pais Valencia",
    "wof:placetype":"venue"
},
  "geometry": {"coordinates":[-0.0952939987,39.9453048706],"type":"Point"}
}