{
  "type": "Feature",
  "properties": {
    "addr:full":"Calle de Princesa, 27 Alcorcon Madrid 28921",
    "addr:housenumber":"27",
    "addr:postcode":"28921",
    "addr:street":"Calle De Princesa",
    "iso:country":"ES",
    "sg:address":"Calle de Princesa, 27",
    "sg:city":"Alcorcon",
    "sg:orig_category":"Lencer\u00cda Femenina, Corseter\u00cda, Trajes De Ba\u00d1o (al Por Menor)",
    "sg:phone":"+34 916 44 20 18",
    "sg:postcode":"28921",
    "sg:province":"Madrid",
    "wof:name":"Estevez Lozano Patricia",
    "wof:placetype":"venue"
},
  "geometry": {"coordinates":[-3.830988884,40.347038269],"type":"Point"}
}