{
  "type": "Feature",
  "properties": {
    "iso:country":"ES",
    "sg:address":"Rua Guizamonde, 5",
    "sg:city":"Ourense",
    "sg:orig_category":"Promotores Constructores",
    "sg:phone":"+34 988 51 01 80",
    "sg:postcode":"32001",
    "sg:province":"Ourense",
    "wof:name":"Alicatados Y Revestimientos Gomez Crespo S.l.",
    "wof:placetype":"venue"
},
  "geometry": {"coordinates":[-7.8722214699,42.355556488],"type":"Point"}
}