{
  "type": "Feature",
  "properties": {
    "addr:full":"Calle de Campomanes, 5 Madrid Madrid 28013",
    "addr:housenumber":"5",
    "addr:postcode":"28013",
    "addr:street":"Calle De Campomanes",
    "iso:country":"ES",
    "sg:address":"Calle de Campomanes, 5",
    "sg:city":"Madrid",
    "sg:orig_category":"Confiter\u00cdas, Chocolater\u00cdas (al Por Menor)",
    "sg:phone":"+34 915 41 83 07",
    "sg:postcode":"28013",
    "sg:province":"Madrid",
    "wof:name":"Whatever Hosteleria S.l.",
    "wof:placetype":"venue"
},
  "geometry": {"coordinates":[-3.7094414234,40.4188537598],"type":"Point"}
}