{
  "type": "Feature",
  "properties": {
    "addr:full":"Calle de Fuerteventura, 11 Gabia Grande Granada 18110",
    "addr:housenumber":"11",
    "addr:postcode":"18110",
    "addr:street":"Calle De Fuerteventura",
    "iso:country":"ES",
    "sg:address":"Calle de Fuerteventura, 11",
    "sg:city":"Gabia Grande",
    "sg:orig_category":"T\u00c9cnicos Veterinarios",
    "sg:phone":"+34 958 58 28 86",
    "sg:postcode":"18110",
    "sg:province":"Granada",
    "wof:name":"Segura Rodriguez Maria Jose",
    "wof:placetype":"venue"
},
  "geometry": {"coordinates":[-3.6696970463,37.1383934021],"type":"Point"}
}