{
  "type": "Feature",
  "properties": {
    "addr:full":"Calle de Zafra (la), 15 Caudete Albacete 02660",
    "addr:housenumber":"15",
    "addr:postcode":"02660",
    "addr:street":"Calle De Zafra La",
    "iso:country":"ES",
    "sg:address":"Calle de Zafra (la), 15",
    "sg:city":"Caudete",
    "sg:orig_category":"Agentes Generales De Seguros",
    "sg:phone":"+34 965 82 73 02",
    "sg:postcode":"02660",
    "sg:province":"Albacete",
    "wof:name":"Mapfre Servicios De Informatica S.a.",
    "wof:placetype":"venue"
},
  "geometry": {"coordinates":[-0.9855189919,38.7047576904],"type":"Point"}
}