{
  "type": "Feature",
  "properties": {
    "iso:country":"ES",
    "sg:address":"Calle de Maskuribai Kalea, 21",
    "sg:city":"Amurrio",
    "sg:orig_category":"Asociaciones Y Clubs Deportivos",
    "sg:phone":"+34 945 89 34 10",
    "sg:postcode":"01470",
    "sg:province":"\u00c1lava",
    "wof:name":"Kasikagorri Amurrioko Futbol Taldea",
    "wof:placetype":"venue"
},
  "geometry": {"coordinates":[-3.000467062,43.0477561951],"type":"Point"}
}