{
  "type": "Feature",
  "properties": {
    "iso:country":"ES",
    "sg:address":"Calle de Genova, 11",
    "sg:city":"Madrid",
    "sg:orig_category":"Bancos",
    "sg:phone":"+34 913 08 41 50",
    "sg:postcode":"28004",
    "sg:province":"Madrid",
    "sg:website":"www.bancosimeon.es",
    "wof:name":"Banco Caixa Geral S.a.",
    "wof:placetype":"venue"
},
  "geometry": {"coordinates":[-3.6944029331,40.4271392822],"type":"Point"}
}