{
  "type": "Feature",
  "properties": {
    "iso:country":"ES",
    "sg:address":"Calle de Viriato, 47",
    "sg:city":"Arrecife",
    "sg:orig_category":"Peluquer\u00cdas",
    "sg:phone":"+34 928 80 52 08",
    "sg:postcode":"35500",
    "sg:province":"Las Palmas",
    "wof:name":"Cabrera Toribio Marta Elena",
    "wof:placetype":"venue"
},
  "geometry": {"coordinates":[-13.5659456253,28.9656505585],"type":"Point"}
}