{
  "type": "Feature",
  "properties": {
    "iso:country":"ES",
    "sg:address":"Pl Carles Iii (de), 15",
    "sg:city":"S. Carles Rapita",
    "sg:orig_category":"Laboratorios Y Trabajos De Fotograf\u00cda, V\u00cddeo Y Cine",
    "sg:phone":"+34 977 74 10 68",
    "sg:postcode":"43540",
    "sg:province":"Tarragona",
    "wof:name":"Dassoy Carcelle Pedro Javier",
    "wof:placetype":"venue"
},
  "geometry": {"coordinates":[0.5924829841,40.6199531555],"type":"Point"}
}