{
  "type": "Feature",
  "properties": {
    "iso:country":"ES",
    "sg:address":"Calle de Badajoz, 1",
    "sg:city":"Malaga",
    "sg:orig_category":"Plomeros",
    "sg:phone":"+34 952 25 62 39",
    "sg:postcode":"29014",
    "sg:province":"M\u00e1laga",
    "wof:name":"Montero Conejero Manuel",
    "wof:placetype":"venue"
},
  "geometry": {"coordinates":[-4.420363903,36.7513999939],"type":"Point"}
}