{
  "type": "Feature",
  "properties": {
    "iso:country":"ES",
    "sg:address":"El Castillo, S/n",
    "sg:city":"Caspe",
    "sg:orig_category":"Ropa Y Art\u00cdculos Pre",
    "sg:phone":"+34 976 63 04 37",
    "sg:postcode":"50700",
    "sg:province":"Zaragoza",
    "sg:website":"www.babin.es",
    "wof:name":"Babin Iberbaby S.l",
    "wof:placetype":"venue"
},
  "geometry": {"coordinates":[-0.0378182009,41.2311553955],"type":"Point"}
}