{
  "type": "Feature",
  "properties": {
    "iso:country":"ES",
    "sg:address":"Ctra Campillo, 44",
    "sg:city":"Guijuelo",
    "sg:orig_category":"Reposter\u00cdas",
    "sg:phone":"+34 923 58 02 42",
    "sg:postcode":"37770",
    "sg:province":"Salamanca",
    "wof:name":"Aveleira Casillas Clementina",
    "wof:placetype":"venue"
},
  "geometry": {"coordinates":[-5.6728668213,40.5594177246],"type":"Point"}
}