{
  "type": "Feature",
  "properties": {
    "iso:country":"ES",
    "sg:address":"Rua Asorei (escultor), 5",
    "sg:city":"Lugo",
    "sg:orig_category":"Transporte En General",
    "sg:phone":"+34 982 21 75 45",
    "sg:postcode":"27004",
    "sg:province":"Lugo",
    "wof:name":"Vazquez Fernandez Alfredo",
    "wof:placetype":"venue"
},
  "geometry": {"coordinates":[-7.569381237,43.0095176697],"type":"Point"}
}