{
  "type": "Feature",
  "properties": {
    "iso:country":"ES",
    "sg:address":"Calle de Juan Xxiii, 22",
    "sg:city":"Castalla",
    "sg:orig_category":"Asesor\u00cda Sobre Comunicaci\u00d3n De Empresas",
    "sg:phone":"+34 965 56 10 43",
    "sg:postcode":"03420",
    "sg:province":"Alicante",
    "wof:name":"Assintem S.c.",
    "wof:placetype":"venue"
},
  "geometry": {"coordinates":[-0.6735123992,38.5929527283],"type":"Point"}
}