{
  "type": "Feature",
  "properties": {
    "iso:country":"ES",
    "sg:address":"Carrer de Arago, 342",
    "sg:city":"Barcelona",
    "sg:orig_category":"Muebles, Minoristas",
    "sg:phone":"+34 932 65 34 44",
    "sg:postcode":"08009",
    "sg:province":"Barcelona",
    "wof:name":"Mobex S.a.",
    "wof:placetype":"venue"
},
  "geometry": {"coordinates":[2.1704399586,41.3961601257],"type":"Point"}
}