{
  "type": "Feature",
  "properties": {
    "addr:full":"Plaz Constitucion(manjiron) (de La), 1 Manjiron Madrid 28754",
    "addr:housenumber":"1",
    "addr:postcode":"28754",
    "iso:country":"ES",
    "sg:address":"Plaz Constitucion(manjiron) (de La), 1",
    "sg:city":"Manjiron",
    "sg:orig_category":"Administraciones Regionales, Departamentales Y Locales",
    "sg:phone":"+34 918 68 02 67",
    "sg:postcode":"28754",
    "sg:province":"Madrid",
    "wof:name":"Ayuntamiento De Puentesviejas",
    "wof:placetype":"venue"
},
  "geometry": {"coordinates":[-3.584633112,40.9653282166],"type":"Point"}
}