{
  "type": "Feature",
  "properties": {
    "addr:full":"Calle de Perez Galdos, 10 Madrid Madrid 28004",
    "addr:housenumber":"10",
    "addr:postcode":"madrid;28004",
    "addr:street":"Calle De Perez Galdos",
    "iso:country":"ES",
    "sg:address":"Calle de Perez Galdos, 10",
    "sg:city":"Madrid",
    "sg:classifiers":[
        {
            "category":"Arts & Performance",
            "subcategory":"Art Gallery",
            "type":"Entertainment"
        }
    ],
    "sg:phone":"+34 915 22 07 17",
    "sg:postcode":"28004",
    "sg:province":"Madrid",
    "sg:tags":[
        "arte",
        "de",
        "galer\u00cdas"
    ],
    "wof:name":"Bellas Artes S. L.",
    "wof:placetype":"venue"
},
  "geometry": {"coordinates":[-3.6999630928,40.4221878052],"type":"Point"}
}