{
  "type": "Feature",
  "properties": {
    "addr:full":"Avda Blas Infante, 8 Arroyo De La Miel-benalmadena Costa M\u00e1laga 29631",
    "addr:housenumber":"8",
    "addr:postcode":"29631",
    "addr:street":"Avda Blas Infante;Arroyo De La Miel-Benalmadena Costa Ma\u0301Laga",
    "iso:country":"ES",
    "sg:address":"Avda Blas Infante, 8",
    "sg:city":"Arroyo De La Miel-benalmadena Costa",
    "sg:orig_category":"Loter\u00cda Y T\u00d3mbola",
    "sg:phone":"+34 952 44 03 68",
    "sg:postcode":"29631",
    "sg:province":"M\u00e1laga",
    "wof:name":"Garcia Zaragoza Ana Maria",
    "wof:placetype":"venue"
},
  "geometry": {"coordinates":[-4.5350675583,36.5986633301],"type":"Point"}
}