{
  "type": "Feature",
  "properties": {
    "addr:full":"Calle de Gutierrez Herrero De, 52 Aviles Asturias 33402",
    "addr:housenumber":"52",
    "addr:postcode":"33402",
    "addr:street":"Calle De Gutierrez Herrero De",
    "iso:country":"ES",
    "sg:address":"Calle de Gutierrez Herrero De, 52",
    "sg:city":"Aviles",
    "sg:orig_category":"Centros Empresariales",
    "sg:phone":"+34 985 12 97 67",
    "sg:postcode":"33402",
    "sg:province":"Asturias",
    "sg:website":"www.aitoa-aviles.es",
    "wof:name":"Ayuntamiento De Aviles",
    "wof:placetype":"venue"
},
  "geometry": {"coordinates":[-5.9145007133,43.5472450256],"type":"Point"}
}