{
  "type": "Feature",
  "properties": {
    "iso:country":"ES",
    "sg:address":"Pl. Ayuntamiento, 4",
    "sg:city":"Pola De Siero",
    "sg:orig_category":"Producci\u00d3n, Distribuci\u00d3n De Gas Butano Y Propano",
    "sg:phone":"+34 985 72 51 94",
    "sg:postcode":"33510",
    "sg:province":"Asturias",
    "wof:name":"Ma\u00f1ana Vazquez Abel",
    "wof:placetype":"venue"
},
  "geometry": {"coordinates":[-5.6603240967,43.3924789429],"type":"Point"}
}