{
  "type": "Feature",
  "properties": {
    "iso:country":"ES",
    "sg:address":"Calle de Estacion, S/n",
    "sg:city":"Bercedo",
    "sg:orig_category":"Empresas De Carpinter\u00cda",
    "sg:phone":"+34 947 14 01 60",
    "sg:postcode":"09569",
    "sg:province":"Burgos",
    "wof:name":"Martinez Gutierrez Angel",
    "wof:placetype":"venue"
},
  "geometry": {"coordinates":[-3.4740591049,43.0654754639],"type":"Point"}
}