{
  "type": "Feature",
  "properties": {
    "iso:country":"ES",
    "sg:address":"Calle de Uruguay, S/n",
    "sg:city":"Alcantarilla",
    "sg:orig_category":"Ropa Para Beb\u00c9s Y Ni\u00d1os (confecci\u00d3n, Al Por Mayor)",
    "sg:phone":"+34 968 89 84 71",
    "sg:postcode":"30820",
    "sg:province":"Murcia",
    "wof:name":"Confecciones Evaristo Gonzalez S.l.",
    "wof:placetype":"venue"
},
  "geometry": {"coordinates":[-1.1980240345,37.9597854614],"type":"Point"}
}