{
  "type": "Feature",
  "properties": {
    "iso:country":"ES",
    "sg:address":"Ipertegi, 18",
    "sg:city":"Orkoien",
    "sg:orig_category":"Limpieza Con Chorro De Arena Y Con Granalla, Pulido",
    "sg:phone":"+34 948 32 52 27",
    "sg:postcode":"31160",
    "sg:province":"Navarra",
    "wof:name":"Perez Onieva A Y J A",
    "wof:placetype":"venue"
},
  "geometry": {"coordinates":[-1.6964370012,42.8195114136],"type":"Point"}
}