{
  "type": "Feature",
  "properties": {
    "iso:country":"ES",
    "sg:address":"Ctra Santpedor, 157",
    "sg:city":"Manresa",
    "sg:orig_category":"Vinos Y Licores (venta Al Por Menor)",
    "sg:phone":"+34 938 73 06 73",
    "sg:postcode":"08242",
    "sg:province":"Barcelona",
    "wof:name":"Alsivins S.l.",
    "wof:placetype":"venue"
},
  "geometry": {"coordinates":[1.8325837851,41.73802948],"type":"Point"}
}