{
  "type": "Feature",
  "properties": {
    "iso:country":"ES",
    "sg:address":"Calle de Constitucion (de La), 48",
    "sg:city":"Fuenlabrada",
    "sg:orig_category":"Comercio De Piezas De Recambio Y De Accesorios De Veh\u00cdculos, Veh\u00cdculos Industriales",
    "sg:phone":"+34 916 90 43 14",
    "sg:postcode":"28946",
    "sg:province":"Madrid",
    "wof:name":"Recambios Fuenlabrada S.l.",
    "wof:placetype":"venue"
},
  "geometry": {"coordinates":[-3.7871441841,40.2813453674],"type":"Point"}
}