{
  "type": "Feature",
  "properties": {
    "iso:country":"ES",
    "sg:address":"Perez Galdos, 17",
    "sg:city":"Quart Poblet",
    "sg:orig_category":"Electricidad: Instaladores",
    "sg:phone":"+34 961 53 22 17",
    "sg:postcode":"46930",
    "sg:province":"Valencia",
    "wof:name":"Cordoba Sanchez Jose Manuel",
    "wof:placetype":"venue"
},
  "geometry": {"coordinates":[-0.4648680091,39.4764595032],"type":"Point"}
}