{
  "type": "Feature",
  "properties": {
    "addr:full":"Carril Nevero, S/n Congo Almer\u00eda 04738",
    "addr:housenumber":"s / n",
    "addr:postcode":"04738",
    "addr:street":"Carril Nevero;Almeri\u0301A",
    "iso:country":"ES",
    "sg:address":"Carril Nevero, S/n",
    "sg:city":"Congo",
    "sg:orig_category":"Comercio De Hierro",
    "sg:phone":"+34 950 53 95 32",
    "sg:postcode":"04738",
    "sg:province":"Almer\u00eda",
    "wof:name":"Fercom Ferralla S.l.",
    "wof:placetype":"venue"
},
  "geometry": {"coordinates":[-2.6420009136,36.8316612244],"type":"Point"}
}