{
  "type": "Feature",
  "properties": {
    "addr:full":"Crri Palmeral, S/n Casas De Cementerio De Nuestro Padre Jesus Murcia 30100",
    "addr:housenumber":"s",
    "addr:postcode":"30100",
    "addr:street":"/ N Casas De Cementerio",
    "iso:country":"ES",
    "sg:address":"Crri Palmeral, S/n",
    "sg:city":"Casas De Cementerio De Nuestro Padre Jesus",
    "sg:orig_category":"Ferreter\u00cda (diversos)",
    "sg:phone":"+34 968 83 37 33",
    "sg:postcode":"30100",
    "sg:province":"Murcia",
    "wof:name":"Hermanos Ingles-vidal S.l.",
    "wof:placetype":"venue"
},
  "geometry": {"coordinates":[-1.153594017,38.0103034973],"type":"Point"}
}