{
  "type": "Feature",
  "properties": {
    "addr:full":"Avda Alicante, 25 Biar Alicante 03410",
    "addr:housenumber":"25",
    "addr:postcode":"03410",
    "addr:street":"Avda Alicante",
    "iso:country":"ES",
    "sg:address":"Avda Alicante, 25",
    "sg:city":"Biar",
    "sg:orig_category":"Abogados",
    "sg:phone":"+34 965 81 14 33",
    "sg:postcode":"03410",
    "sg:province":"Alicante",
    "wof:name":"Vicedo Molina Antonio",
    "wof:placetype":"venue"
},
  "geometry": {"coordinates":[-0.7616930008,38.6288261414],"type":"Point"}
}