{
  "type": "Feature",
  "properties": {
    "addr:full":"Ctra Fuente, S/n Tarancon Cuenca 16400",
    "addr:housenumber":"s",
    "addr:postcode":"16400",
    "addr:street":"Ctra Fuente;/ N",
    "iso:country":"ES",
    "sg:address":"Ctra Fuente, S/n",
    "sg:city":"Tarancon",
    "sg:orig_category":"Electricidad Veh\u00cdculo",
    "sg:phone":"+34 969 32 14 09",
    "sg:postcode":"16400",
    "sg:province":"Cuenca",
    "wof:name":"Dioni Y Jesus C.b",
    "wof:placetype":"venue"
},
  "geometry": {"coordinates":[-3.0033218861,40.0092163086],"type":"Point"}
}