{
  "type": "Feature",
  "properties": {
    "addr:full":"Avda Reina Sofia, S/n Peligros Granada 18210",
    "addr:housenumber":"s / n",
    "addr:postcode":"18210",
    "addr:street":"Avda Reina Sofia",
    "iso:country":"ES",
    "sg:address":"Avda Reina Sofia, S/n",
    "sg:city":"Peligros",
    "sg:orig_category":"Asilos De Ancianos. Centros Privados",
    "sg:phone":"+34 958 40 18 94",
    "sg:postcode":"18210",
    "sg:province":"Granada",
    "wof:name":"Lozano Aracil S.l.",
    "wof:placetype":"venue"
},
  "geometry": {"coordinates":[-3.632463932,37.2329788208],"type":"Point"}
}