{
  "type": "Feature",
  "properties": {
    "addr:full":"Calle de Alcala, 127 Madrid Madrid 28009",
    "addr:housenumber":"127",
    "addr:postcode":"28009",
    "addr:street":"Calle De Alcala",
    "iso:country":"ES",
    "sg:address":"Calle de Alcala, 127",
    "sg:city":"Madrid",
    "sg:orig_category":"Arquitectos",
    "sg:phone":"+34 914 31 53 78",
    "sg:postcode":"28009",
    "sg:province":"Madrid",
    "wof:name":"Avello Villaverde Maria Pilar",
    "wof:placetype":"venue"
},
  "geometry": {"coordinates":[-3.6795632839,40.4231109619],"type":"Point"}
}