{
  "type": "Feature",
  "properties": {
    "iso:country":"ES",
    "sg:address":"Carrer de L'aurora, 12",
    "sg:city":"Barcelona",
    "sg:orig_category":"Empresas De Carpinter\u00cda De Madera",
    "sg:phone":"+34 934 41 72 72",
    "sg:postcode":"08001",
    "sg:province":"Barcelona",
    "wof:name":"Alemany Frauca Carlos",
    "wof:placetype":"venue"
},
  "geometry": {"coordinates":[2.1680355072,41.3786811829],"type":"Point"}
}