{
  "type": "Feature",
  "properties": {
    "addr:full":"Calle de Martinez Vargas, 3 Zaragoza Zaragoza 50007",
    "addr:housenumber":"3",
    "addr:postcode":"50007",
    "addr:street":"Calle De Martinez Vargas",
    "iso:country":"ES",
    "sg:address":"Calle de Martinez Vargas, 3",
    "sg:city":"Zaragoza",
    "sg:orig_category":"Molduras, Junquillos, Listones Y Molduras Perforadas",
    "sg:phone":"+34 976 27 51 52",
    "sg:postcode":"50007",
    "sg:province":"Zaragoza",
    "wof:name":"Gregorio Uribarri Juan Salvador",
    "wof:placetype":"venue"
},
  "geometry": {"coordinates":[-0.8863800168,41.6291656494],"type":"Point"}
}