{
  "type": "Feature",
  "properties": {
    "iso:country":"ES",
    "sg:address":"Calle de Cortijo, 6",
    "sg:city":"Aldeanueva Ebro",
    "sg:orig_category":"Comunidades Religiosas",
    "sg:phone":"+34 941 16 30 84",
    "sg:postcode":"26559",
    "sg:province":"La Rioja",
    "wof:name":"Parroquia De San Bartolome",
    "wof:placetype":"venue"
},
  "geometry": {"coordinates":[-1.8877393007,42.2298469543],"type":"Point"}
}