{
  "type": "Feature",
  "properties": {
    "iso:country":"ES",
    "sg:address":"Calle de Puente Colgante, 34",
    "sg:city":"Valladolid",
    "sg:orig_category":"Arquitectos",
    "sg:phone":"+34 983 47 61 12",
    "sg:postcode":"47007",
    "sg:province":"Valladolid",
    "wof:name":"Lar Edificacion Urbanismo Y Medio Ambiente S.l.",
    "wof:placetype":"venue"
},
  "geometry": {"coordinates":[-4.7369952202,41.6409454346],"type":"Point"}
}