{
  "type": "Feature",
  "properties": {
    "iso:country":"ES",
    "sg:address":"Calle de Palos De La Frontera, 15",
    "sg:city":"Huelva",
    "sg:orig_category":"Alimentaci\u00d3n General (al Por Menor)",
    "sg:phone":"+34 959 26 24 32",
    "sg:postcode":"21003",
    "sg:province":"Huelva",
    "wof:name":"Botello Perez Rafael",
    "wof:placetype":"venue"
},
  "geometry": {"coordinates":[-6.9495902061,37.2575759888],"type":"Point"}
}