{
  "type": "Feature",
  "properties": {
    "addr:full":"Av. Dr. Gomez Ferrer, 9 Sedavi Valencia 46910",
    "addr:housenumber":"9",
    "addr:postcode":"46910",
    "addr:street":"Av. Dr. Gomez Ferrer",
    "iso:country":"ES",
    "sg:address":"Av. Dr. Gomez Ferrer, 9",
    "sg:city":"Sedavi",
    "sg:orig_category":"Bancos",
    "sg:phone":"+34 963 75 00 99",
    "sg:postcode":"46910",
    "sg:province":"Valencia",
    "wof:name":"Banco De Valencia S.a.",
    "wof:placetype":"venue"
},
  "geometry": {"coordinates":[-0.3869949877,39.4253616333],"type":"Point"}
}