{
  "type": "Feature",
  "properties": {
    "addr:full":"Rua Castelao, 4 Covas Lugo 27861",
    "addr:housenumber":"4",
    "addr:postcode":"27861",
    "addr:street":"Rua Castelao",
    "iso:country":"ES",
    "sg:address":"Rua Castelao, 4",
    "sg:city":"Covas",
    "sg:orig_category":"Alumbrados",
    "sg:phone":"+34 982 55 03 55",
    "sg:postcode":"27861",
    "sg:province":"Lugo",
    "wof:name":"Miguel Pascual Sociedad Coop.",
    "wof:placetype":"venue"
},
  "geometry": {"coordinates":[-7.6583218575,43.691734314],"type":"Point"}
}