{
  "type": "Feature",
  "properties": {
    "addr:full":"Calle de San Miguel, 25 Nerja M\u00e1laga 29780",
    "addr:housenumber":"25",
    "addr:postcode":"29780",
    "addr:street":"Calle De San Miguel",
    "iso:country":"ES",
    "sg:address":"Calle de San Miguel, 25",
    "sg:city":"Nerja",
    "sg:orig_category":"Ense\u00d1anza: Idiomas",
    "sg:phone":"+34 952 52 37 88",
    "sg:postcode":"29780",
    "sg:province":"M\u00e1laga",
    "sg:website":"www.quorumspain.com",
    "wof:name":"Centro De Idiomas Quorum S.c.",
    "wof:placetype":"venue"
},
  "geometry": {"coordinates":[-3.8775780201,36.7502288818],"type":"Point"}
}