{
  "type": "Feature",
  "properties": {
    "iso:country":"ES",
    "sg:address":"Calle de Delfin, 1",
    "sg:city":"Madrid",
    "sg:orig_category":"Molduras, Junquillos, Listones Y Molduras Perforadas",
    "sg:phone":"+34 913 14 23 51",
    "sg:postcode":"28029",
    "sg:province":"Madrid",
    "wof:name":"Pascual Y Alfonso Vedia Jimenez C.b.",
    "wof:placetype":"venue"
},
  "geometry": {"coordinates":[-3.694258213,40.4671058655],"type":"Point"}
}