{
  "type": "Feature",
  "properties": {
    "iso:country":"ES",
    "sg:address":"Calle de Fernandez De Los Rios, 79",
    "sg:city":"Madrid",
    "sg:orig_category":"M\u00c9dicos: Estomatolog\u00cda",
    "sg:phone":"+34 915 49 02 72",
    "sg:postcode":"28015",
    "sg:province":"Madrid",
    "wof:name":"Barros Feijoo Juan Jose",
    "wof:placetype":"venue"
},
  "geometry": {"coordinates":[-3.7138769627,40.4352073669],"type":"Point"}
}