{
  "type": "Feature",
  "properties": {
    "iso:country":"ES",
    "sg:address":"Rua Pravia (da), 46",
    "sg:city":"Vilalba",
    "sg:orig_category":"Zapatos (al Por Menor)",
    "sg:phone":"+34 982 51 03 61",
    "sg:postcode":"27800",
    "sg:province":"Lugo",
    "wof:name":"Rouco Lamela Ramon",
    "wof:placetype":"venue"
},
  "geometry": {"coordinates":[-7.6789598465,43.2990684509],"type":"Point"}
}