{
  "type": "Feature",
  "properties": {
    "iso:country":"ES",
    "sg:address":"Calle de Juan Alvarez Mendizabal, 23",
    "sg:city":"Madrid",
    "sg:orig_category":"Expertos Contables, Revisores De Cuentas",
    "sg:phone":"+34 914 47 92 16",
    "sg:postcode":"28008",
    "sg:province":"Madrid",
    "wof:name":"Cln Auditores Consultores S.l.",
    "wof:placetype":"venue"
},
  "geometry": {"coordinates":[-3.7153680325,40.425113678],"type":"Point"}
}