{
  "type": "Feature",
  "properties": {
    "addr:full":"Carrer de Eduard Alcoy, 30 Mataro Barcelona 08304",
    "addr:housenumber":"30",
    "addr:postcode":"08304",
    "addr:street":"Carrer De Eduard Alcoy",
    "iso:country":"ES",
    "sg:address":"Carrer de Eduard Alcoy, 30",
    "sg:city":"Mataro",
    "sg:orig_category":"Fabricaci\u00d3n De Su\u00c9ters Y Chalecos De Punto",
    "sg:phone":"+34 937 90 61 43",
    "sg:postcode":"08304",
    "sg:province":"Barcelona",
    "wof:name":"Gonzalez Manjon Juana",
    "wof:placetype":"venue"
},
  "geometry": {"coordinates":[2.4470999241,41.5536384583],"type":"Point"}
}