{
  "type": "Feature",
  "properties": {
    "iso:country":"ES",
    "sg:address":"Calle de Calvario, 2",
    "sg:city":"Cazalegas",
    "sg:orig_category":"Forjas Y Altos Hornos",
    "sg:phone":"+34 925 87 25 79",
    "sg:postcode":"45553",
    "sg:province":"Toledo",
    "wof:name":"Lopez Aguilera Jose Leon",
    "wof:placetype":"venue"
},
  "geometry": {"coordinates":[-4.67598629,40.0084342957],"type":"Point"}
}