{
  "type": "Feature",
  "properties": {
    "addr:full":"Mayor, 6 Alfondeguilla Castell\u00f3n 12609",
    "addr:housenumber":"6",
    "addr:postcode":"12609",
    "addr:street":"Mayor;Castello\u0301N",
    "iso:country":"ES",
    "sg:address":"Mayor, 6",
    "sg:city":"Alfondeguilla",
    "sg:orig_category":"Iglesia Cat\u00d3lica",
    "sg:phone":"+34 964 66 19 30",
    "sg:postcode":"12609",
    "sg:province":"Castell\u00f3n",
    "wof:name":"Iglesia Parroquial San Bartolome",
    "wof:placetype":"venue"
},
  "geometry": {"coordinates":[-0.2694379985,39.8376846313],"type":"Point"}
}