{
  "type": "Feature",
  "properties": {
    "addr:full":"Rua Robleda, 51 Vigo Pontevedra 36207",
    "addr:housenumber":"51",
    "addr:postcode":"36207",
    "addr:street":"Rua Robleda",
    "iso:country":"ES",
    "sg:address":"Rua Robleda, 51",
    "sg:city":"Vigo",
    "sg:orig_category":"Material Y Suministros Para Veterinarios",
    "sg:phone":"+34 986 28 04 38",
    "sg:postcode":"36207",
    "sg:province":"Pontevedra",
    "wof:name":"Del Jeque S.l.",
    "wof:placetype":"venue"
},
  "geometry": {"coordinates":[-8.6982946396,42.246837616],"type":"Point"}
}