{
  "type": "Feature",
  "properties": {
    "iso:country":"ES",
    "sg:address":"Carrer de Gran, 50",
    "sg:city":"S. Vicen\u00e7 Castellet",
    "sg:orig_category":"Confiter\u00cdas, Chocolater\u00cdas (al Por Menor)",
    "sg:phone":"+34 938 33 16 50",
    "sg:postcode":"08295",
    "sg:province":"Barcelona",
    "wof:name":"Casajuana Anglarill Juan",
    "wof:placetype":"venue"
},
  "geometry": {"coordinates":[1.863468051,41.6652870178],"type":"Point"}
}