{
  "type": "Feature",
  "properties": {
    "addr:full":"Calle de Canteras Recias, 1 Villamayor Salamanca 37185",
    "addr:housenumber":"1",
    "addr:postcode":"37185",
    "addr:street":"Calle De Canteras Recias",
    "iso:country":"ES",
    "sg:address":"Calle de Canteras Recias, 1",
    "sg:city":"Villamayor",
    "sg:orig_category":"Reposter\u00cdas",
    "sg:phone":"+34 923 28 63 71",
    "sg:postcode":"37185",
    "sg:province":"Salamanca",
    "wof:name":"Jomasan Villamayor S.l.",
    "wof:placetype":"venue"
},
  "geometry": {"coordinates":[-5.6956477165,40.9987564087],"type":"Point"}
}