{
  "type": "Feature",
  "properties": {
    "iso:country":"ES",
    "sg:address":"Calle de Sajonia, 23",
    "sg:city":"Madrid",
    "sg:orig_category":"Electrodom\u00c9sticos (fabricaci\u00d3n, Al Por Mayor)",
    "sg:phone":"+34 917 75 79 09",
    "sg:postcode":"28022",
    "sg:province":"Madrid",
    "sg:website":"www.mepamsa.es",
    "wof:name":"Mepamsa Centro S.l.",
    "wof:placetype":"venue"
},
  "geometry": {"coordinates":[-3.6061029434,40.4213447571],"type":"Point"}
}