{
  "type": "Feature",
  "properties": {
    "iso:country":"ES",
    "sg:address":"Calle de Ramon Y Cajal, 11",
    "sg:city":"Piedralaves",
    "sg:orig_category":"Papeler\u00cdas, Librer\u00cdas",
    "sg:phone":"+34 918 66 53 63",
    "sg:postcode":"05440",
    "sg:province":"\u00c1vila",
    "wof:name":"Sanchez Sanchez Pedro Daniel",
    "wof:placetype":"venue"
},
  "geometry": {"coordinates":[-4.6993350983,40.3179702759],"type":"Point"}
}