{
  "type": "Feature",
  "properties": {
    "iso:country":"ES",
    "sg:address":"Rua Progreso, 79",
    "sg:city":"Portonovo",
    "sg:orig_category":"Rectificaci\u00d3n, Mecanizado, Fresado",
    "sg:phone":"+34 986 69 01 42",
    "sg:postcode":"36970",
    "sg:province":"Pontevedra",
    "wof:name":"Distribuciones Lourada S.l.",
    "wof:placetype":"venue"
},
  "geometry": {"coordinates":[-8.8250999451,42.3949356079],"type":"Point"}
}