{
  "type": "Feature",
  "properties": {
    "addr:full":"Pl America, 9 Senia Tarragona 43560",
    "addr:housenumber":"9",
    "addr:postcode":"43560",
    "addr:street":"Pl America",
    "iso:country":"ES",
    "sg:address":"Pl America, 9",
    "sg:city":"Senia",
    "sg:orig_category":"Grafistas",
    "sg:phone":"+34 977 57 50 96",
    "sg:postcode":"43560",
    "sg:province":"Tarragona",
    "wof:name":"Batec Comunicacio S.l.l.",
    "wof:placetype":"venue"
},
  "geometry": {"coordinates":[0.2795960009,40.6385574341],"type":"Point"}
}