{
  "type": "Feature",
  "properties": {
    "iso:country":"ES",
    "sg:address":"Avda Filiberto Villalobos, 119",
    "sg:city":"Salamanca",
    "sg:orig_category":"Centros De Educaci\u00d3n Especial",
    "sg:phone":"+34 923 23 06 17",
    "sg:postcode":"37007",
    "sg:province":"Salamanca",
    "wof:name":"Colegio Publico De Practicas Villar Y Macias",
    "wof:placetype":"venue"
},
  "geometry": {"coordinates":[-5.6755900383,40.9711112976],"type":"Point"}
}