{
  "type": "Feature",
  "properties": {
    "iso:country":"ES",
    "sg:address":"Carrer de Tres Creus, 213",
    "sg:city":"Sabadell",
    "sg:orig_category":"Comercio De Piezas De Recambio Y De Accesorios De Veh\u00cdculos, Veh\u00cdculos Industriales",
    "sg:phone":"+34 937 27 57 38",
    "sg:postcode":"08202",
    "sg:province":"Barcelona",
    "wof:name":"J.m. Experta S.l.",
    "wof:placetype":"venue"
},
  "geometry": {"coordinates":[2.1185400486,41.5462112427],"type":"Point"}
}