{
  "type": "Feature",
  "properties": {
    "iso:country":"ES",
    "sg:address":"Avda Madrid, 42",
    "sg:city":"Torrejon Ardoz",
    "sg:orig_category":"Tiendas De Grano, Frutas Y Legumbres Secas (al Por Menor)",
    "sg:phone":"+34 916 74 95 19",
    "sg:postcode":"28850",
    "sg:province":"Madrid",
    "wof:name":"Ruiz Ramirez Antonio",
    "wof:placetype":"venue"
},
  "geometry": {"coordinates":[-3.4657230377,40.4639358521],"type":"Point"}
}