{
  "type": "Feature",
  "properties": {
    "addr:full":"Calle de Arrabal Bajo, 43 Malon Zaragoza 50511",
    "addr:housenumber":"43",
    "addr:postcode":"50511",
    "addr:street":"Calle De Arrabal Bajo",
    "iso:country":"ES",
    "sg:address":"Calle de Arrabal Bajo, 43",
    "sg:city":"Malon",
    "sg:orig_category":"Panader\u00cdas, Panader\u00cdas",
    "sg:phone":"+34 976 19 81 04",
    "sg:postcode":"50511",
    "sg:province":"Zaragoza",
    "wof:name":"Panaderia Boni S.l.",
    "wof:placetype":"venue"
},
  "geometry": {"coordinates":[-1.6726433039,41.9528923035],"type":"Point"}
}