{
  "type": "Feature",
  "properties": {
    "addr:full":"Calle de Barcelona, 11 Mostoles Madrid 28931",
    "addr:housenumber":"11",
    "addr:postcode":"28931",
    "addr:street":"Calle De Barcelona",
    "iso:country":"ES",
    "sg:address":"Calle de Barcelona, 11",
    "sg:city":"Mostoles",
    "sg:orig_category":"Inmobiliaria (agencias)",
    "sg:phone":"+34 916 47 71 34",
    "sg:postcode":"28931",
    "sg:province":"Madrid",
    "sg:website":"www.tratohechobolsainmobiliaria.com",
    "wof:name":"Trati Hecho Bolsa Inmobiliaria S.l.",
    "wof:placetype":"venue"
},
  "geometry": {"coordinates":[-3.8571984768,40.3248100281],"type":"Point"}
}