{
  "type": "Feature",
  "properties": {
    "iso:country":"ES",
    "sg:address":"Carrer de Sant Pere Alt, 10",
    "sg:city":"Roses",
    "sg:orig_category":"Alimentaci\u00d3n General (al Por Menor)",
    "sg:phone":"+34 972 25 70 84",
    "sg:postcode":"17480",
    "sg:province":"Girona",
    "wof:name":"Brunet Fontdecaba Esteban",
    "wof:placetype":"venue"
},
  "geometry": {"coordinates":[3.1786460876,42.2607421875],"type":"Point"}
}