{
  "type": "Feature",
  "properties": {
    "addr:full":"Avda Mediterraneo, S/n Benidorm Alicante 03500",
    "addr:postcode":"03500",
    "addr:street":"Avda Mediterraneo S / N",
    "iso:country":"ES",
    "sg:address":"Avda Mediterraneo, S/n",
    "sg:city":"Benidorm",
    "sg:orig_category":"Zapatos (al Por Menor)",
    "sg:phone":"+34 966 80 06 32",
    "sg:postcode":"03500",
    "sg:province":"Alicante",
    "wof:name":"Yang  Xiaofeng",
    "wof:placetype":"venue"
},
  "geometry": {"coordinates":[-0.1162523031,38.5363731384],"type":"Point"}
}