{
  "type": "Feature",
  "properties": {
    "addr:full":"Calle de Constitucion, 2 Graja Iniesta Cuenca 16251",
    "addr:housenumber":"2",
    "addr:postcode":"16251",
    "addr:street":"Calle De Constitucion",
    "iso:country":"ES",
    "sg:address":"Calle de Constitucion, 2",
    "sg:city":"Graja Iniesta",
    "sg:orig_category":"Farmacias",
    "sg:phone":"+34 962 16 10 03",
    "sg:postcode":"16251",
    "sg:province":"Cuenca",
    "wof:name":"Ramiro Felix Gema",
    "wof:placetype":"venue"
},
  "geometry": {"coordinates":[-1.6717280149,39.5165901184],"type":"Point"}
}