{
  "type": "Feature",
  "properties": {
    "iso:country":"ES",
    "sg:address":"G.v. Corts Catalanes, 677",
    "sg:city":"Barcelona",
    "sg:orig_category":"Juegos Y Juguetes (al Por Menor)",
    "sg:phone":"+34 932 46 11 98",
    "sg:postcode":"08013",
    "sg:province":"Barcelona",
    "wof:name":"Fa-sol S.a.",
    "wof:placetype":"venue"
},
  "geometry": {"coordinates":[2.1769020557,41.3963546753],"type":"Point"}
}