{
  "type": "Feature",
  "properties": {
    "iso:country":"ES",
    "sg:address":"Calle de Sepulveda, 162",
    "sg:city":"Madrid",
    "sg:orig_category":"Comercio, Reparaci\u00d3n De Motocicletas, Bicicletas Y Piezas Sueltas",
    "sg:phone":"+34 914 79 33 48",
    "sg:postcode":"28011",
    "sg:province":"Madrid",
    "wof:name":"Medina Reina Javier",
    "wof:placetype":"venue"
},
  "geometry": {"coordinates":[-3.7435469627,40.4047927856],"type":"Point"}
}