{
  "type": "Feature",
  "properties": {
    "iso:country":"ES",
    "sg:address":"Calle de Elizkale, 9",
    "sg:city":"Zumarraga",
    "sg:orig_category":"Peluqueros: De Se\u00d1oras",
    "sg:phone":"+34 943 72 38 53",
    "sg:postcode":"20700",
    "sg:province":"Guip\u00f9zcoa",
    "wof:name":"Charro Garcia Amaya",
    "wof:placetype":"venue"
},
  "geometry": {"coordinates":[-2.3128869534,43.0886230469],"type":"Point"}
}