{
  "type": "Feature",
  "properties": {
    "addr:full":"Cra Laurea Miro, 140 Sant Feliu Llobregat Barcelona 08980",
    "addr:housenumber":"140",
    "addr:postcode":"08980",
    "iso:country":"ES",
    "sg:address":"Cra Laurea Miro, 140",
    "sg:city":"Sant Feliu Llobregat",
    "sg:orig_category":"Dietistas",
    "sg:phone":"+34 936 85 09 12",
    "sg:postcode":"08980",
    "sg:province":"Barcelona",
    "wof:name":"Amigo Carbonell Maria Teresa",
    "wof:placetype":"venue"
},
  "geometry": {"coordinates":[2.0401105881,41.3865318298],"type":"Point"}
}