{
  "type": "Feature",
  "properties": {
    "iso:country":"ES",
    "sg:address":"Huerta Epifanio, 3",
    "sg:city":"Sanlucar Mayor",
    "sg:orig_category":"Venta, Alquiler De Toldos",
    "sg:phone":"+34 955 70 09 60",
    "sg:postcode":"41800",
    "sg:province":"Sevilla",
    "sg:website":"www.tejadosrusticos.com",
    "wof:name":"Kwazulu S.l.",
    "wof:placetype":"venue"
},
  "geometry": {"coordinates":[-6.1956338882,37.3855361938],"type":"Point"}
}