{
  "type": "Feature",
  "properties": {
    "addr:full":"Po Ind Petroquimico, S/n Palos Frontera Huelva 21810",
    "addr:housenumber":"s / n",
    "addr:postcode":"21810",
    "addr:street":"Palos Frontera",
    "iso:country":"ES",
    "sg:address":"Po Ind Petroquimico, S/n",
    "sg:city":"Palos Frontera",
    "sg:orig_category":"Molduras, Junquillos, Listones Y Molduras Perforadas",
    "sg:phone":"+34 959 36 93 33",
    "sg:postcode":"21810",
    "sg:province":"Huelva",
    "wof:name":"Rodriguez Velez Jose Antonio",
    "wof:placetype":"venue"
},
  "geometry": {"coordinates":[-6.8923411369,37.2240829468],"type":"Point"}
}