{
  "type": "Feature",
  "properties": {
    "iso:country":"ES",
    "sg:address":"Avda Canteros, 12",
    "sg:city":"Gerena",
    "sg:orig_category":"M\u00c9dicos: Naturistas",
    "sg:phone":"+34 955 78 23 94",
    "sg:postcode":"41860",
    "sg:province":"Sevilla",
    "wof:name":"Martinez Florindo Jose",
    "wof:placetype":"venue"
},
  "geometry": {"coordinates":[-6.1523089409,37.5285301208],"type":"Point"}
}