{
  "type": "Feature",
  "properties": {
    "iso:country":"ES",
    "sg:address":"Calle de Guadix, 3",
    "sg:city":"Lucena",
    "sg:orig_category":"Enfermeras: Consultas, Atenci\u00d3n A Domicilio",
    "sg:phone":"+34 957 50 31 02",
    "sg:postcode":"14900",
    "sg:province":"C\u00f3rdoba",
    "wof:name":"Asociacion De Minusvalidos Frasquito Espada",
    "wof:placetype":"venue"
},
  "geometry": {"coordinates":[-4.4981374741,37.4086112976],"type":"Point"}
}