{
  "type": "Feature",
  "properties": {
    "addr:full":"Pase Cristobal Colon (de), 1 Santiago Ribera Murcia 30720",
    "addr:housenumber":"1",
    "addr:postcode":"30720",
    "addr:street":"Cristobal Colon De",
    "iso:country":"ES",
    "sg:address":"Pase Cristobal Colon (de), 1",
    "sg:city":"Santiago Ribera",
    "sg:orig_category":"Gastronom\u00cda: Especialidades Regionales (al Por Menor)",
    "sg:phone":"+34 968 57 01 37",
    "sg:postcode":"30720",
    "sg:province":"Murcia",
    "wof:name":"Mariche E Hijos S.l.",
    "wof:placetype":"venue"
},
  "geometry": {"coordinates":[-0.8042219877,37.7974205017],"type":"Point"}
}