{
  "type": "Feature",
  "properties": {
    "addr:full":"Avda Iglesia, 6 Humera-somosaguas-prado Del Rey Madrid 28223",
    "addr:housenumber":"6",
    "addr:postcode":"28223",
    "addr:street":"Avda Iglesia",
    "iso:country":"ES",
    "sg:address":"Avda Iglesia, 6",
    "sg:city":"Humera-somosaguas-prado Del Rey",
    "sg:orig_category":"Inmobiliaria (agencias)",
    "sg:phone":"+34 913 51 43 75",
    "sg:postcode":"28223",
    "sg:province":"Madrid",
    "wof:name":"Tongres S.l.",
    "wof:placetype":"venue"
},
  "geometry": {"coordinates":[-3.784799099,40.4286117554],"type":"Point"}
}