{
  "type": "Feature",
  "properties": {
    "addr:full":"Calle de Emeterio Cuadrado, 15 Mula Murcia 30170",
    "addr:housenumber":"15",
    "addr:postcode":"30170",
    "addr:street":"Calle De Emeterio Cuadrado",
    "iso:country":"ES",
    "sg:address":"Calle de Emeterio Cuadrado, 15",
    "sg:city":"Mula",
    "sg:orig_category":"Florister\u00cdas",
    "sg:phone":"+34 968 66 16 82",
    "sg:postcode":"30170",
    "sg:province":"Murcia",
    "wof:name":"Creaciones Hydria Noroeste S.l.",
    "wof:placetype":"venue"
},
  "geometry": {"coordinates":[-1.4942250252,38.0397109985],"type":"Point"}
}