{
  "type": "Feature",
  "properties": {
    "addr:full":"Calle de Pitagoras, 12 Fuensanta -villa Ines Almer\u00eda 04230",
    "addr:housenumber":"12",
    "addr:postcode":"04230",
    "addr:street":"Calle De Pitagoras;Almeri\u0301A",
    "iso:country":"ES",
    "sg:address":"Calle de Pitagoras, 12",
    "sg:city":"Fuensanta -villa Ines",
    "sg:orig_category":"Empresas De Desmonte",
    "sg:phone":"+34 950 60 08 76",
    "sg:postcode":"04230",
    "sg:province":"Almer\u00eda",
    "wof:name":"Excavaciones Manuel Bueno Sanchez S.l",
    "wof:placetype":"venue"
},
  "geometry": {"coordinates":[-2.4386088848,36.8789749146],"type":"Point"}
}