{
  "type": "Feature",
  "properties": {
    "addr:full":"Calle de Gonzalez Aurioles, 27 Cordoba C\u00f3rdoba 14005",
    "addr:housenumber":"27",
    "addr:postcode":"14005",
    "addr:street":"Calle De Gonzalez Aurioles;Co\u0301Rdoba",
    "iso:country":"ES",
    "sg:address":"Calle de Gonzalez Aurioles, 27",
    "sg:city":"Cordoba",
    "sg:orig_category":"Empresarios",
    "sg:phone":"+34 957 23 16 38",
    "sg:postcode":"14005",
    "sg:province":"C\u00f3rdoba",
    "wof:name":"Santiago Antequera Rosario",
    "wof:placetype":"venue"
},
  "geometry": {"coordinates":[-4.8006677628,37.8832015991],"type":"Point"}
}