{
  "type": "Feature",
  "properties": {
    "iso:country":"ES",
    "sg:address":"Calle de Carlos V, 21",
    "sg:city":"Melilla",
    "sg:orig_category":"Alimentaci\u00d3n General (al Por Menor)",
    "sg:phone":"+34 952 67 80 42",
    "sg:postcode":"52006",
    "sg:province":"Melilla",
    "wof:name":"Pi\u00f1ero Delgado Diego",
    "wof:placetype":"venue"
},
  "geometry": {"coordinates":[-2.9399325848,35.2825241089],"type":"Point"}
}