{
  "type": "Feature",
  "properties": {
    "iso:country":"ES",
    "sg:address":"Calle de Perete, 15",
    "sg:city":"Malaga",
    "sg:orig_category":"Muebles Y Accesorios Para Cocinas Y Cuartos De Ba\u00d1o (al Por Menor)",
    "sg:phone":"+34 952 34 00 86",
    "sg:postcode":"29006",
    "sg:province":"M\u00e1laga",
    "wof:name":"Mosaico Muebles De Cocina S.l.",
    "wof:placetype":"venue"
},
  "geometry": {"coordinates":[-4.4846382141,36.7088775635],"type":"Point"}
}