{
  "type": "Feature",
  "properties": {
    "iso:country":"ES",
    "sg:address":"Carrer de Sepulveda, 155",
    "sg:city":"Barcelona",
    "sg:orig_category":"Inform\u00c1tica, Ofim\u00c1tica (estudios, Asesor\u00cda, Ingenier\u00cda, Formaci\u00d3n)",
    "sg:phone":"+34 934 51 29 03",
    "sg:postcode":"08011",
    "sg:province":"Barcelona",
    "sg:website":"www.fsb-extreme.com",
    "wof:name":"Fsb Extreme Scp",
    "wof:placetype":"venue"
},
  "geometry": {"coordinates":[2.1613430977,41.3825263977],"type":"Point"}
}