{
  "type": "Feature",
  "properties": {
    "addr:full":"Calle de General Barroso, 68 Valencia Valencia 46017",
    "addr:housenumber":"68",
    "addr:postcode":"46017",
    "addr:street":"Calle De General Barroso",
    "iso:country":"ES",
    "sg:address":"Calle de General Barroso, 68",
    "sg:city":"Valencia",
    "sg:orig_category":"Inform\u00c1tica: Mantenimiento Y Reparaci\u00d3n De Ordenadores",
    "sg:phone":"+34 963 17 03 26",
    "sg:postcode":"46017",
    "sg:province":"Valencia",
    "wof:name":"Computer Servicios & Mantenimientos S.l.l.",
    "wof:placetype":"venue"
},
  "geometry": {"coordinates":[-0.3922609985,39.4501266479],"type":"Point"}
}