{
  "type": "Feature",
  "properties": {
    "addr:full":"Calle de Vazquez Ayllon, 12 San Jose Rinconada Sevilla 41300",
    "addr:housenumber":"12",
    "addr:postcode":"41300",
    "addr:street":"Calle De Vazquez Ayllon",
    "iso:country":"ES",
    "sg:address":"Calle de Vazquez Ayllon, 12",
    "sg:city":"San Jose Rinconada",
    "sg:orig_category":"Tapicer\u00cdas",
    "sg:phone":"+34 955 79 15 47",
    "sg:postcode":"41300",
    "sg:province":"Sevilla",
    "wof:name":"Tapizados Joyfa S.cv.",
    "wof:placetype":"venue"
},
  "geometry": {"coordinates":[-5.9498152733,37.4780273438],"type":"Point"}
}