{
  "type": "Feature",
  "properties": {
    "iso:country":"ES",
    "sg:address":"Via Augusta, 58",
    "sg:city":"Hospitalet Infant",
    "sg:orig_category":"Servicios Gsm",
    "sg:phone":"+34 977 82 06 25",
    "sg:postcode":"43890",
    "sg:province":"Tarragona",
    "sg:website":"www.movilandia.net",
    "wof:name":"Trenza Soto Juan",
    "wof:placetype":"venue"
},
  "geometry": {"coordinates":[0.9196389914,40.9906463623],"type":"Point"}
}