{
  "type": "Feature",
  "properties": {
    "addr:full":"Calle de Retama, 7 Madrid Madrid 28...",
    "addr:housenumber":"7;28 ...",
    "addr:postcode":"madrid",
    "addr:street":"Calle De Retama;Madrid",
    "iso:country":"ES",
    "sg:address":"Calle de Retama, 7",
    "sg:city":"Madrid",
    "sg:orig_category":"Inform\u00c1tica (estudios, Servicios, Asesor\u00cda, Formaci\u00d3n)",
    "sg:phone":"+34 913 83 11 23",
    "sg:postcode":"28...",
    "sg:province":"Madrid",
    "sg:website":"www.comstor.es",
    "wof:name":"Comstor Networking S.l.",
    "wof:placetype":"venue"
},
  "geometry": {"coordinates":[-3.6460568905,40.4579353333],"type":"Point"}
}