{
  "type": "Feature",
  "properties": {
    "addr:full":"Urba Icomar, S/n Icomar Tarragona 43006",
    "addr:housenumber":"s",
    "addr:postcode":"43006",
    "addr:street":"/ N Icomar",
    "iso:country":"ES",
    "sg:address":"Urba Icomar, S/n",
    "sg:city":"Icomar",
    "sg:orig_category":"Desinfecci\u00d3n, Desinsectaci\u00d3n, Desratizaci\u00d3n",
    "sg:phone":"+34 977 54 81 18",
    "sg:postcode":"43006",
    "sg:province":"Tarragona",
    "wof:name":"Quiminet 2001 S.l.",
    "wof:placetype":"venue"
},
  "geometry": {"coordinates":[1.2209249735,41.1154441833],"type":"Point"}
}