{
  "type": "Feature",
  "properties": {
    "iso:country":"ES",
    "sg:address":"Avda Antones (los), 68",
    "sg:city":"Pulpi",
    "sg:orig_category":"Empresas De Carpinter\u00cda De Madera",
    "sg:phone":"+34 950 46 42 91",
    "sg:postcode":"04640",
    "sg:province":"Almer\u00eda",
    "wof:name":"Sanchez Haro Luis",
    "wof:placetype":"venue"
},
  "geometry": {"coordinates":[-1.7513240576,37.4025840759],"type":"Point"}
}