{
  "type": "Feature",
  "properties": {
    "addr:full":"Carretera, Km. 0333,0 Lanjaron Granada 18420",
    "addr:postcode":"18420",
    "addr:street":"Carretera Km. 0333,0",
    "iso:country":"ES",
    "sg:address":"Carretera, Km. 0333,0",
    "sg:city":"Lanjaron",
    "sg:orig_category":"Aceites Y Grasas Alimentarias (fabricaci\u00d3n, Al Por Mayor)",
    "sg:phone":"+34 958 77 11 07",
    "sg:postcode":"18420",
    "sg:province":"Granada",
    "wof:name":"Molino De Casares S.l.",
    "wof:placetype":"venue"
},
  "geometry": {"coordinates":[-3.4771339893,36.9187583923],"type":"Point"}
}