{
  "type": "Feature",
  "properties": {
    "iso:country":"ES",
    "sg:address":"Calle de Vicente Gradaille, 1",
    "sg:city":"Celeiro",
    "sg:orig_category":"Navegaci\u00d3n (equipos Fluviales)",
    "sg:phone":"+34 982 55 02 41",
    "sg:postcode":"27863",
    "sg:province":"Lugo",
    "wof:name":"Antonio Santos Alonso S.l.",
    "wof:placetype":"venue"
},
  "geometry": {"coordinates":[-7.0615258217,42.6895484924],"type":"Point"}
}