{
  "type": "Feature",
  "properties": {
    "iso:country":"ES",
    "sg:address":"Calle de Martires, 13",
    "sg:city":"Daimiel",
    "sg:orig_category":"Venta, Alquiler Y Mantenimiento De Juegos De Sal\u00d3n O Casinos",
    "sg:phone":"+34 926 85 29 89",
    "sg:postcode":"13250",
    "sg:province":"Ciudad Real",
    "wof:name":"Recreativos Barrajon S.l.",
    "wof:placetype":"venue"
},
  "geometry": {"coordinates":[-3.6121490002,39.070148468],"type":"Point"}
}