{
  "type": "Feature",
  "properties": {
    "addr:full":"Ptge. Arcadia, 13 Barcelona Barcelona 08006",
    "addr:housenumber":"13",
    "addr:postcode":"08006",
    "addr:street":"Arcadia",
    "iso:country":"ES",
    "sg:address":"Ptge. Arcadia, 13",
    "sg:city":"Barcelona",
    "sg:orig_category":"Almacenes Para Venta: Muebles Y Varios",
    "sg:phone":"+34 932 18 44 17",
    "sg:postcode":"08006",
    "sg:province":"Barcelona",
    "wof:name":"Azpeitia Diaz Leticia",
    "wof:placetype":"venue"
},
  "geometry": {"coordinates":[2.1532995701,41.3964309692],"type":"Point"}
}