{
  "type": "Feature",
  "properties": {
    "iso:country":"ES",
    "sg:address":"Av Saloria, 93",
    "sg:city":"Seu D'urgell",
    "sg:orig_category":"Peluquer\u00cdas, Peluquer\u00cda Mixta",
    "sg:phone":"+34 973 35 30 00",
    "sg:postcode":"25700",
    "sg:province":"Lleida",
    "wof:name":"Martinez Ortiz Maria Carmen",
    "wof:placetype":"venue"
},
  "geometry": {"coordinates":[0.6457189918,41.6027946472],"type":"Point"}
}