{
  "type": "Feature",
  "properties": {
    "iso:country":"ES",
    "sg:address":"Calle de Matilde Diez, 6",
    "sg:city":"Madrid",
    "sg:orig_category":"Prot\u00c9sicos Dentales",
    "sg:phone":"+34 915 19 23 04",
    "sg:postcode":"28002",
    "sg:province":"Madrid",
    "wof:name":"Perera Briones Pablo",
    "wof:placetype":"venue"
},
  "geometry": {"coordinates":[-3.6738500595,40.4457969666],"type":"Point"}
}