{
  "type": "Feature",
  "properties": {
    "iso:country":"ES",
    "sg:address":"Calle de Virgen De La Capilla, 6",
    "sg:city":"Jaen",
    "sg:orig_category":"Ropa Para Ni\u00d1os (al Por Menor)",
    "sg:phone":"+34 953 24 11 09",
    "sg:postcode":"23001",
    "sg:province":"Ja\u00e9n",
    "sg:website":"www.torero.com",
    "wof:name":"Torero Franquicias S.l.",
    "wof:placetype":"venue"
},
  "geometry": {"coordinates":[-3.786771059,37.7685165405],"type":"Point"}
}