{
  "type": "Feature",
  "properties": {
    "addr:full":"Avda Juan Carlos I, 38 Totana Murcia 30850",
    "addr:housenumber":"38",
    "addr:postcode":"30850",
    "addr:street":"Avda Juan Carlos I",
    "iso:country":"ES",
    "sg:address":"Avda Juan Carlos I, 38",
    "sg:city":"Totana",
    "sg:orig_category":"Mec\u00c1nico Del Autom\u00d3vil",
    "sg:phone":"+34 968 42 73 20",
    "sg:postcode":"30850",
    "sg:province":"Murcia",
    "wof:name":"Valero Mu\u00f1oz Juan Antonio",
    "wof:placetype":"venue"
},
  "geometry": {"coordinates":[-1.5000590086,37.7640419006],"type":"Point"}
}