{
  "type": "Feature",
  "properties": {
    "addr:full":"Avda Alto Del Leon, 55 San Rafael Segovia 40410",
    "addr:housenumber":"55",
    "addr:postcode":"40410",
    "addr:street":"Avda Alto Del Leon",
    "iso:country":"ES",
    "sg:address":"Avda Alto Del Leon, 55",
    "sg:city":"San Rafael",
    "sg:orig_category":"Sanatorios M\u00c9dico",
    "sg:phone":"+34 921 17 19 49",
    "sg:postcode":"40410",
    "sg:province":"Segovia",
    "wof:name":"Ayuntamiento De El Espinar",
    "wof:placetype":"venue"
},
  "geometry": {"coordinates":[-4.1845850945,40.7123947144],"type":"Point"}
}