{
  "type": "Feature",
  "properties": {
    "iso:country":"ES",
    "sg:address":"Avda 16, 17",
    "sg:city":"Vaciasilos",
    "sg:orig_category":"Bordado, Marcado A Medida",
    "sg:phone":"+34 918 16 09 61",
    "sg:postcode":"28991",
    "sg:province":"Madrid",
    "wof:name":"Victoria Martin Blanco Vibor S.l.",
    "wof:placetype":"venue"
},
  "geometry": {"coordinates":[-3.8020849228,40.1848869324],"type":"Point"}
}