{
  "type": "Feature",
  "properties": {
    "addr:full":"Calle de Ayora, 10 Enguera Valencia 46810",
    "addr:housenumber":"10",
    "addr:postcode":"46810",
    "addr:street":"Calle De Ayora",
    "iso:country":"ES",
    "sg:address":"Calle de Ayora, 10",
    "sg:city":"Enguera",
    "sg:orig_category":"Confecci\u00d3n De Ropa Interior",
    "sg:phone":"+34 962 22 55 98",
    "sg:postcode":"46810",
    "sg:province":"Valencia",
    "wof:name":"Confecciones Orsatex S.l.",
    "wof:placetype":"venue"
},
  "geometry": {"coordinates":[-0.690752387,38.9772262573],"type":"Point"}
}