{
  "type": "Feature",
  "properties": {
    "iso:country":"ES",
    "sg:address":"Ctra. Salamanca, 8",
    "sg:city":"Pe\u00f1aranda Bracamonte",
    "sg:orig_category":"Ense\u00d1anza, Formaci\u00d3n Profesional: Aprendizaje",
    "sg:phone":"+34 923 54 11 50",
    "sg:postcode":"37300",
    "sg:province":"Salamanca",
    "wof:name":"Instituto Nacional De Bachillerato Mixto",
    "wof:placetype":"venue"
},
  "geometry": {"coordinates":[-5.2044801712,40.9013977051],"type":"Point"}
}