{
  "type": "Feature",
  "properties": {
    "addr:full":"Rua Velazquez Moreno, 44 Vigo Pontevedra 36202",
    "addr:housenumber":"44",
    "addr:postcode":"36202",
    "addr:street":"Rua Velazquez Moreno",
    "iso:country":"ES",
    "sg:address":"Rua Velazquez Moreno, 44",
    "sg:city":"Vigo",
    "sg:orig_category":"Frutas Y Legumbres Frescas (al Por Mayor)",
    "sg:phone":"+34 986 43 99 23",
    "sg:postcode":"36202",
    "sg:province":"Pontevedra",
    "wof:name":"Frutas Nieves S. L.",
    "wof:placetype":"venue"
},
  "geometry": {"coordinates":[-8.7219676971,42.235294342],"type":"Point"}
}