{
  "type": "Feature",
  "properties": {
    "iso:country":"ES",
    "sg:address":"Calle de Serrano, 110",
    "sg:city":"Madrid",
    "sg:orig_category":"Ropa Para Se\u00d1oras (al Por Menor)",
    "sg:phone":"+34 914 11 48 36",
    "sg:postcode":"28006",
    "sg:province":"Madrid",
    "sg:website":"www.liola.it",
    "wof:name":"Paima 2000 Servicios S.l.",
    "wof:placetype":"venue"
},
  "geometry": {"coordinates":[-3.6863229275,40.43567276],"type":"Point"}
}