{
  "type": "Feature",
  "properties": {
    "addr:full":"Ctra Daimiel, S/n Bola\u00e7os De Calatrava Ciudad Real 13260",
    "addr:housenumber":"s",
    "addr:postcode":"13260",
    "addr:street":"Ctra Daimiel;/ N",
    "iso:country":"ES",
    "sg:address":"Ctra Daimiel, S/n",
    "sg:city":"Bola\u00e7os De Calatrava",
    "sg:orig_category":"Ingenier\u00cda, Centros De Estudios (diversos)",
    "sg:phone":"+34 926 87 05 62",
    "sg:postcode":"13260",
    "sg:province":"Ciudad Real",
    "wof:name":"Menchero Marquez Pedro",
    "wof:placetype":"venue"
},
  "geometry": {"coordinates":[-3.6648440361,38.9122161865],"type":"Point"}
}