{
  "type": "Feature",
  "properties": {
    "addr:full":"Calle de Elisa Cendrero, 9 Ciudad Real Ciudad Real 13004",
    "addr:housenumber":"9",
    "addr:postcode":"13004",
    "addr:street":"Calle De Elisa Cendrero",
    "iso:country":"ES",
    "sg:address":"Calle de Elisa Cendrero, 9",
    "sg:city":"Ciudad Real",
    "sg:orig_category":"Sociedades, Compa\u00d1\u00cdas Aseguradoras",
    "sg:phone":"+34 926 25 58 70",
    "sg:postcode":"13004",
    "sg:province":"Ciudad Real",
    "wof:name":"Ocaso S.a. Compa\u00f1ia De Seguros Y Reaseguros",
    "wof:placetype":"venue"
},
  "geometry": {"coordinates":[-3.9272890091,38.9873199463],"type":"Point"}
}