{
  "type": "Feature",
  "properties": {
    "iso:country":"ES",
    "sg:address":"Luga Huertecilla La, S/n",
    "sg:city":"Churriana",
    "sg:orig_category":"Negocio De Materiales De Construcci\u00d3n",
    "sg:phone":"+34 952 62 22 69",
    "sg:postcode":"29140",
    "sg:province":"M\u00e1laga",
    "wof:name":"Polveros La Noria Hermanos Campos S.l.",
    "wof:placetype":"venue"
},
  "geometry": {"coordinates":[-4.5087790489,36.6753311157],"type":"Point"}
}