{
  "type": "Feature",
  "properties": {
    "addr:full":"Carrer de Sant Quirze, 10 Terrassa Barcelona 08221",
    "addr:housenumber":"10",
    "addr:postcode":"08221",
    "addr:street":"Carrer De Sant Quirze",
    "iso:country":"ES",
    "sg:address":"Carrer de Sant Quirze, 10",
    "sg:city":"Terrassa",
    "sg:orig_category":"Decoradores",
    "sg:phone":"+34 937 31 20 20",
    "sg:postcode":"08221",
    "sg:province":"Barcelona",
    "wof:name":"Ordeix Jimenez Jose Luis",
    "wof:placetype":"venue"
},
  "geometry": {"coordinates":[2.0152409077,41.5607414246],"type":"Point"}
}