{
  "type": "Feature",
  "properties": {
    "iso:country":"ES",
    "sg:address":"Carrer de Wenceslao Guadall, 22",
    "sg:city":"Matadepera",
    "sg:orig_category":"Contables",
    "sg:phone":"+34 937 87 10 33",
    "sg:postcode":"08230",
    "sg:province":"Barcelona",
    "wof:name":"Vidal Ca\u00f1ameras Jose",
    "wof:placetype":"venue"
},
  "geometry": {"coordinates":[2.0308279991,41.5991325378],"type":"Point"}
}