{
  "type": "Feature",
  "properties": {
    "iso:country":"ES",
    "sg:address":"Carr Carles Salvador, 7",
    "sg:city":"Benicasim",
    "sg:orig_category":"Promotores Constructores",
    "sg:phone":"+34 964 30 46 44",
    "sg:postcode":"12560",
    "sg:province":"Castell\u00f3n",
    "wof:name":"Constravel S.l.",
    "wof:placetype":"venue"
},
  "geometry": {"coordinates":[0.0595020019,40.0510635376],"type":"Point"}
}