{
  "type": "Feature",
  "properties": {
    "iso:country":"ES",
    "sg:address":"Calle de Salesianos, 11",
    "sg:city":"Badajoz",
    "sg:orig_category":"Electrodom\u00c9sticos (al Por Menor)",
    "sg:phone":"+34 924 24 81 67",
    "sg:postcode":"06011",
    "sg:province":"Badajoz",
    "wof:name":"Reja Cabeza Jose Antonio",
    "wof:placetype":"venue"
},
  "geometry": {"coordinates":[-6.9826178551,38.8684616089],"type":"Point"}
}