{
  "type": "Feature",
  "properties": {
    "iso:country":"ES",
    "sg:address":"Calle de Periodista Ramon Resa, 41",
    "sg:city":"Sevilla",
    "sg:orig_category":"Administraci\u00d3n En Agricultura",
    "sg:phone":"+34 954 62 15 61",
    "sg:postcode":"41012",
    "sg:province":"Sevilla",
    "wof:name":"Kinlo S.a.",
    "wof:placetype":"venue"
},
  "geometry": {"coordinates":[-5.9830942154,37.3586502075],"type":"Point"}
}