{
  "type": "Feature",
  "properties": {
    "addr:full":"G.v. Corts Catalanes, 524 Barcelona Barcelona 08011",
    "addr:housenumber":"524",
    "addr:postcode":"08011",
    "addr:street":"Catalanes",
    "iso:country":"ES",
    "sg:address":"G.v. Corts Catalanes, 524",
    "sg:city":"Barcelona",
    "sg:orig_category":"M\u00c9dicos: Naturistas",
    "sg:phone":"+34 934 51 46 15",
    "sg:postcode":"08011",
    "sg:province":"Barcelona",
    "wof:name":"Sanhara Asociacio Desenvolupament Personal I Terapia Natural",
    "wof:placetype":"venue"
},
  "geometry": {"coordinates":[2.1590080261,41.3820419312],"type":"Point"}
}