{
  "type": "Feature",
  "properties": {
    "iso:country":"ES",
    "sg:address":"Carrer de Consell De Cent, 271",
    "sg:city":"Barcelona",
    "sg:orig_category":"Frutas Y Legumbres Frescas (al Por Mayor)",
    "sg:phone":"+34 934 51 53 33",
    "sg:postcode":"08011",
    "sg:province":"Barcelona",
    "wof:name":"Alcaley Scp",
    "wof:placetype":"venue"
},
  "geometry": {"coordinates":[2.1608877182,41.3874931335],"type":"Point"}
}