{
  "type": "Feature",
  "properties": {
    "addr:full":"Calle de Rivero Del, 14 Aviles Asturias 33402",
    "addr:housenumber":"14",
    "addr:postcode":"33402",
    "addr:street":"Calle De Rivero Del",
    "iso:country":"ES",
    "sg:address":"Calle de Rivero Del, 14",
    "sg:city":"Aviles",
    "sg:orig_category":"Carnicer\u00cdas, Carnicer\u00cdas",
    "sg:phone":"+34 985 54 13 30",
    "sg:postcode":"33402",
    "sg:province":"Asturias",
    "wof:name":"Cueto Alvarez Marcelino Vicente",
    "wof:placetype":"venue"
},
  "geometry": {"coordinates":[-5.9213762283,43.5547599792],"type":"Point"}
}