{
  "type": "Feature",
  "properties": {
    "iso:country":"ES",
    "sg:address":"Avda Castilla Y Leon, 13",
    "sg:city":"Guardo",
    "sg:orig_category":"Frutas, Legumbres Frescas Y Tempranas (al Por Menor)",
    "sg:phone":"+34 979 85 18 00",
    "sg:postcode":"34880",
    "sg:province":"Palencia",
    "wof:name":"Frutas Ba\u00f1os Loma S.l",
    "wof:placetype":"venue"
},
  "geometry": {"coordinates":[-4.8495569229,42.7891540527],"type":"Point"}
}