{
  "type": "Feature",
  "properties": {
    "iso:country":"ES",
    "sg:address":"Carrer de Colombia, S/n",
    "sg:city":"Crevillent",
    "sg:orig_category":"Producci\u00d3n De Abonos Y De Fertilizantes",
    "sg:phone":"+34 965 40 16 88",
    "sg:postcode":"03330",
    "sg:province":"Alicante",
    "wof:name":"Cooperativa De Labradores Y Ganaderos",
    "wof:placetype":"venue"
},
  "geometry": {"coordinates":[-0.8132389784,38.243309021],"type":"Point"}
}