{
  "type": "Feature",
  "properties": {
    "addr:full":"Calle de Rualasal, 15 Santander Cantabria 39001",
    "addr:housenumber":"15",
    "addr:postcode":"39001",
    "addr:street":"Calle De Rualasal",
    "iso:country":"ES",
    "sg:address":"Calle de Rualasal, 15",
    "sg:city":"Santander",
    "sg:orig_category":"Lencer\u00cda Femenina, Corseter\u00cda, Trajes De Ba\u00d1o (al Por Menor)",
    "sg:phone":"+34 942 22 58 36",
    "sg:postcode":"39001",
    "sg:province":"Cantabria",
    "wof:name":"Campos Bustamante Manuel",
    "wof:placetype":"venue"
},
  "geometry": {"coordinates":[-3.8063220978,43.4629211426],"type":"Point"}
}