{
  "type": "Feature",
  "properties": {
    "addr:full":"Carrer de Roserar, 21 S. Cugat Valles Barcelona 08173",
    "addr:housenumber":"21",
    "addr:postcode":"08173",
    "addr:street":"Carrer De Roserar;S. Cugat Valles Barcelona",
    "iso:country":"ES",
    "sg:address":"Carrer de Roserar, 21",
    "sg:city":"S. Cugat Valles",
    "sg:orig_category":"Ingeniero",
    "sg:phone":"+34 936 75 38 71",
    "sg:postcode":"08173",
    "sg:province":"Barcelona",
    "wof:name":"Pfacomunicacion Y Eventig S.l",
    "wof:placetype":"venue"
},
  "geometry": {"coordinates":[2.0743119717,41.4678192139],"type":"Point"}
}