{
  "type": "Feature",
  "properties": {
    "addr:full":"Carrer de Pedrosa B, 42 Hospitalet Llobregat Barcelona 08908",
    "addr:housenumber":"b 42",
    "addr:postcode":"08908",
    "addr:street":"Carrer De Pedrosa",
    "iso:country":"ES",
    "sg:address":"Carrer de Pedrosa B, 42",
    "sg:city":"Hospitalet Llobregat",
    "sg:orig_category":"Empresas De Carpinter\u00cda De Madera",
    "sg:phone":"+34 933 36 00 88",
    "sg:postcode":"08908",
    "sg:province":"Barcelona",
    "wof:name":"Parkestil Disseny S.l.",
    "wof:placetype":"venue"
},
  "geometry": {"coordinates":[2.1317000389,41.3561592102],"type":"Point"}
}