{
  "type": "Feature",
  "properties": {
    "addr:full":"Calle de Ferial, 1 Soria Soria 42001",
    "addr:housenumber":"1",
    "addr:postcode":"42001",
    "addr:street":"Calle De Ferial",
    "iso:country":"ES",
    "sg:address":"Calle de Ferial, 1",
    "sg:city":"Soria",
    "sg:orig_category":"Asociaciones Y Clubs Deportivos",
    "sg:phone":"+34 975 22 71 54",
    "sg:postcode":"42001",
    "sg:province":"Soria",
    "wof:name":"Barron Dominguez Jose Maria",
    "wof:placetype":"venue"
},
  "geometry": {"coordinates":[-2.4693551064,41.764503479],"type":"Point"}
}