{
  "type": "Feature",
  "properties": {
    "iso:country":"ES",
    "sg:address":"Calle de Carretera, 8",
    "sg:city":"Tordillos",
    "sg:orig_category":"Cerrajer\u00cda, Ferrallista",
    "sg:phone":"+34 923 56 47 20",
    "sg:postcode":"37840",
    "sg:province":"Salamanca",
    "wof:name":"Perez Hernandez Gregorio",
    "wof:placetype":"venue"
},
  "geometry": {"coordinates":[-5.3533315659,40.8547592163],"type":"Point"}
}