{
  "type": "Feature",
  "properties": {
    "addr:full":"Carrer de Major, 6 S. Pere Ribes Barcelona 08810",
    "addr:housenumber":"6",
    "addr:postcode":"08810",
    "addr:street":"Carrer De Major;S. Pere Ribes Barcelona",
    "iso:country":"ES",
    "sg:address":"Carrer de Major, 6",
    "sg:city":"S. Pere Ribes",
    "sg:orig_category":"Electricidad: Instaladores",
    "sg:phone":"+34 938 96 35 25",
    "sg:postcode":"08810",
    "sg:province":"Barcelona",
    "wof:name":"Aselectric S.l.",
    "wof:placetype":"venue"
},
  "geometry": {"coordinates":[1.7708997726,41.2619438171],"type":"Point"}
}