{
  "type": "Feature",
  "properties": {
    "iso:country":"ES",
    "sg:address":"Calle de Calderon De La Barca, S/n",
    "sg:city":"S. Fernando",
    "sg:orig_category":"Aparcamientos (infraestructuras, Accesorios)",
    "sg:phone":"+34 956 59 49 44",
    "sg:postcode":"11100",
    "sg:province":"C\u00e1diz",
    "wof:name":"Estacionamientos Isle\u00f1os S.l.",
    "wof:placetype":"venue"
},
  "geometry": {"coordinates":[-6.1985888481,36.4651412964],"type":"Point"}
}