{
  "type": "Feature",
  "properties": {
    "addr:full":"Rua Eduardo Vincenti, 21 Bueu Pontevedra 36930",
    "addr:housenumber":"21",
    "addr:postcode":"36930",
    "addr:street":"Rua Eduardo Vincenti",
    "iso:country":"ES",
    "sg:address":"Rua Eduardo Vincenti, 21",
    "sg:city":"Bueu",
    "sg:orig_category":"Quincaller\u00cda (al Por Menor)",
    "sg:phone":"+34 986 32 00 55",
    "sg:postcode":"36930",
    "sg:province":"Pontevedra",
    "wof:name":"Novas Pi\u00f1eiro Maria Del Carmen",
    "wof:placetype":"venue"
},
  "geometry": {"coordinates":[-8.7845888138,42.3271217346],"type":"Point"}
}