{
  "type": "Feature",
  "properties": {
    "addr:full":"Calle de Santa Isabel, 13 Vitoria-gasteiz \u00c1lava 01013",
    "addr:housenumber":"13",
    "addr:postcode":"01013",
    "addr:street":"Calle De Santa Isabel",
    "iso:country":"ES",
    "sg:address":"Calle de Santa Isabel, 13",
    "sg:city":"Vitoria-gasteiz",
    "sg:orig_category":"Guarda",
    "sg:phone":"+34 945 28 11 13",
    "sg:postcode":"01013",
    "sg:province":"\u00c1lava",
    "wof:name":"Ramos Perez Jose Melitino",
    "wof:placetype":"venue"
},
  "geometry": {"coordinates":[-2.6723139286,42.8564338684],"type":"Point"}
}