{
  "type": "Feature",
  "properties": {
    "iso:country":"ES",
    "sg:address":"Calle de Real, 62",
    "sg:city":"Yunquera Henares",
    "sg:orig_category":"Art\u00cdculos De Regalo (al Por Menor)",
    "sg:phone":"+34 949 33 07 04",
    "sg:postcode":"19210",
    "sg:province":"Guadalajara",
    "wof:name":"Ven Y Ves C.b.",
    "wof:placetype":"venue"
},
  "geometry": {"coordinates":[-3.1659588814,40.7519607544],"type":"Point"}
}