{
  "type": "Feature",
  "properties": {
    "iso:country":"ES",
    "sg:address":"Calle de Cristo Del Valle, 52",
    "sg:city":"Membrilla",
    "sg:orig_category":"Escayola Y Productos De Escayola (fabricaci\u00d3n, Al Por Mayor)",
    "sg:phone":"+34 926 63 65 84",
    "sg:postcode":"13230",
    "sg:province":"Ciudad Real",
    "wof:name":"Nu\u00f1ez Roncero Blas",
    "wof:placetype":"venue"
},
  "geometry": {"coordinates":[-3.3448483944,38.966632843],"type":"Point"}
}