{
  "type": "Feature",
  "properties": {
    "addr:full":"Ctra. Villargordo, S/n Mengibar Ja\u00e9n 23620",
    "addr:housenumber":"s / n",
    "addr:postcode":"23620",
    "addr:street":"Ctra. Villargordo;Mengibar Jae\u0301N",
    "iso:country":"ES",
    "sg:address":"Ctra. Villargordo, S/n",
    "sg:city":"Mengibar",
    "sg:orig_category":"Reparaciones Y Remolcado De Veh\u00cdculos",
    "sg:phone":"+34 953 37 13 11",
    "sg:postcode":"23620",
    "sg:province":"Ja\u00e9n",
    "wof:name":"De La Chica Ruiz Victor Manuel",
    "wof:placetype":"venue"
},
  "geometry": {"coordinates":[-3.8033540249,37.970615387],"type":"Point"}
}