{
  "type": "Feature",
  "properties": {
    "iso:country":"ES",
    "sg:address":"Carr Teixidors, 16",
    "sg:city":"Cabaneta",
    "sg:orig_category":"Promotores Constructores",
    "sg:phone":"+34 971 60 57 76",
    "sg:postcode":"07141",
    "sg:province":"Islas Baleares",
    "wof:name":"Franormi S.l.",
    "wof:placetype":"venue"
},
  "geometry": {"coordinates":[2.7445349693,39.6195487976],"type":"Point"}
}