{
  "type": "Feature",
  "properties": {
    "iso:country":"ES",
    "sg:address":"Calle de Cirilo Amoros, 58",
    "sg:city":"Valencia",
    "sg:orig_category":"Ropa Para Ni\u00d1os (al Por Menor)",
    "sg:phone":"+34 963 10 68 38",
    "sg:postcode":"46004",
    "sg:province":"Valencia",
    "sg:website":"www.gocco.es",
    "wof:name":"Gocco Confeg S.a.",
    "wof:placetype":"venue"
},
  "geometry": {"coordinates":[-0.3689877987,39.4683532715],"type":"Point"}
}