{
  "type": "Feature",
  "properties": {
    "iso:country":"ES",
    "sg:address":"Calle de San Delfin, 8",
    "sg:city":"Madrid",
    "sg:orig_category":"Molduras, Junquillos, Listones Y Molduras Perforadas",
    "sg:phone":"+34 914 69 57 40",
    "sg:postcode":"28019",
    "sg:province":"Madrid",
    "wof:name":"Cabeza Gutierrez Jose Luis",
    "wof:placetype":"venue"
},
  "geometry": {"coordinates":[-3.7075970173,40.3950042725],"type":"Point"}
}