{
  "type": "Feature",
  "properties": {
    "iso:country":"ES",
    "sg:address":"Calle de Benisa, 27",
    "sg:city":"Denia",
    "sg:orig_category":"Chapister\u00cda",
    "sg:phone":"+34 965 78 61 47",
    "sg:postcode":"03700",
    "sg:province":"Alicante",
    "wof:name":"Asuncion Avargues Miguel",
    "wof:placetype":"venue"
},
  "geometry": {"coordinates":[0.0916972011,38.7272186279],"type":"Point"}
}