{
  "type": "Feature",
  "properties": {
    "iso:country":"ES",
    "sg:address":"Ptda Alberca (l'), 7",
    "sg:city":"Nucia",
    "sg:orig_category":"Cristaler\u00cdas",
    "sg:phone":"+34 965 87 00 31",
    "sg:postcode":"03530",
    "sg:province":"Alicante",
    "wof:name":"Cristaleria Amores S.l",
    "wof:placetype":"venue"
},
  "geometry": {"coordinates":[-0.1213990003,38.594619751],"type":"Point"}
}