{
  "type": "Feature",
  "properties": {
    "iso:country":"ES",
    "sg:address":"Avda Villamayor, 78",
    "sg:city":"Salamanca",
    "sg:orig_category":"Cr\u00cda De Animales",
    "sg:phone":"+34 923 25 83 46",
    "sg:postcode":"37007",
    "sg:province":"Salamanca",
    "wof:name":"Alcanher S.l.",
    "wof:placetype":"venue"
},
  "geometry": {"coordinates":[-5.6713204384,40.9724464417],"type":"Point"}
}