{
  "type": "Feature",
  "properties": {
    "addr:full":"Plaz Pontevedra, 17 Coru\u00d1a La Coru\u00f1a 15003",
    "addr:housenumber":"17",
    "addr:postcode":"15003",
    "addr:street":"Pontevedra;La Corun\u0303A",
    "iso:country":"ES",
    "sg:address":"Plaz Pontevedra, 17",
    "sg:city":"Coru\u00d1a",
    "sg:orig_category":"Sociedades, Compa\u00d1\u00cdas Aseguradoras",
    "sg:phone":"+34 981 26 78 90",
    "sg:postcode":"15003",
    "sg:province":"La Coru\u00f1a",
    "wof:name":"Sanchez Lopez Luis Alvaro",
    "wof:placetype":"venue"
},
  "geometry": {"coordinates":[-8.4063863754,43.3679389954],"type":"Point"}
}