{
  "type": "Feature",
  "properties": {
    "iso:country":"ES",
    "sg:address":"Poligono De El Raposal, S/n",
    "sg:city":"Arnedo",
    "sg:orig_category":"Zapatos: Material, Suministros, Accesorios (fabricaci\u00d3n, Al Por Mayor)",
    "sg:phone":"+34 941 38 24 38",
    "sg:postcode":"26580",
    "sg:province":"La Rioja",
    "wof:name":"Ruiz-alejos Martinez-losa Jose Antonio",
    "wof:placetype":"venue"
},
  "geometry": {"coordinates":[-2.0899488926,42.2300453186],"type":"Point"}
}