{
  "type": "Feature",
  "properties": {
    "addr:full":"O Mosteiro, S/n Mosteiro Pontevedra 36740",
    "addr:housenumber":"s / n",
    "addr:postcode":"36740",
    "addr:street":"Mosteiro",
    "iso:country":"ES",
    "sg:address":"O Mosteiro, S/n",
    "sg:city":"Mosteiro",
    "sg:orig_category":"Centros De Educaci\u00d3n Especial",
    "sg:phone":"+34 986 62 21 53",
    "sg:postcode":"36740",
    "sg:province":"Pontevedra",
    "wof:name":"Colexio Publico Concentracion Escolar",
    "wof:placetype":"venue"
},
  "geometry": {"coordinates":[-8.731048584,41.9869499207],"type":"Point"}
}