{
  "type": "Feature",
  "properties": {
    "addr:full":"Calle de Albert Einstein, 44 Vitoria-gasteiz \u00c1lava 01510",
    "addr:housenumber":"44",
    "addr:postcode":"01510",
    "addr:street":"Calle De Albert Einstein",
    "iso:country":"ES",
    "sg:address":"Calle de Albert Einstein, 44",
    "sg:city":"Vitoria-gasteiz",
    "sg:orig_category":"Electricidad: Equipos Industriales, Componentes (fabricaci\u00d3n)",
    "sg:phone":"+34 945 29 81 21",
    "sg:postcode":"01510",
    "sg:province":"\u00c1lava",
    "sg:website":"www.spcnet.info",
    "wof:name":"Spcnet Soluciones De Negocio Electronico S.l.",
    "wof:placetype":"venue"
},
  "geometry": {"coordinates":[-2.6646089554,42.9120941162],"type":"Point"}
}