{
  "type": "Feature",
  "properties": {
    "iso:country":"ES",
    "sg:address":"Avda Hispanidad, 3",
    "sg:city":"Quintana Serena",
    "sg:orig_category":"Contenedores (mercanc\u00cdas)",
    "sg:phone":"+34 924 78 65 88",
    "sg:postcode":"06450",
    "sg:province":"Badajoz",
    "wof:name":"Hermueraex S.l.",
    "wof:placetype":"venue"
},
  "geometry": {"coordinates":[-5.6732192039,38.7394485474],"type":"Point"}
}