{
  "type": "Feature",
  "properties": {
    "addr:full":"Calle de Cardenal Cisneros, 22 Le\u00f3n Le\u00f3n 24010",
    "addr:housenumber":"22",
    "addr:postcode":"24010",
    "addr:street":"Calle De Cardenal Cisneros;Leo\u0301N",
    "iso:country":"ES",
    "sg:address":"Calle de Cardenal Cisneros, 22",
    "sg:city":"Le\u00f3n",
    "sg:orig_category":"Sanatorios M\u00c9dico",
    "sg:phone":"+34 987 23 26 00",
    "sg:postcode":"24010",
    "sg:province":"Le\u00f3n",
    "wof:name":"Gerencia De Atencion Primaria De Leon",
    "wof:placetype":"venue"
},
  "geometry": {"coordinates":[-5.5896039009,42.5997467041],"type":"Point"}
}