{
  "type": "Feature",
  "properties": {
    "iso:country":"ES",
    "sg:address":"La Fragua, S/n",
    "sg:city":"Galleguillos De Campos",
    "sg:orig_category":"Agricultura: Abastecimiento Y Cosechado (negocio)",
    "sg:phone":"+34 987 78 55 33",
    "sg:postcode":"24329",
    "sg:province":"Le\u00f3n",
    "wof:name":"Antolin Gutierrez Garcia Y Otro Cdad",
    "wof:placetype":"venue"
},
  "geometry": {"coordinates":[-5.06665802,42.3064422607],"type":"Point"}
}