{
  "type": "Feature",
  "properties": {
    "addr:full":"Calle de Caminos, 7 Madrid Madrid 28043",
    "addr:housenumber":"7",
    "addr:postcode":"madrid;28043",
    "addr:street":"Calle De Caminos",
    "iso:country":"ES",
    "sg:address":"Calle de Caminos, 7",
    "sg:city":"Madrid",
    "sg:orig_category":"Abogados",
    "sg:phone":"+34 913 88 49 62",
    "sg:postcode":"28043",
    "sg:province":"Madrid",
    "wof:name":"Asistencialegal Sl",
    "wof:placetype":"venue"
},
  "geometry": {"coordinates":[-3.653721571,40.4598922729],"type":"Point"}
}