{
  "type": "Feature",
  "properties": {
    "addr:full":"Barr Picota (la), S/n Renedo Cantabria 39470",
    "addr:housenumber":"s",
    "addr:postcode":"39470",
    "addr:street":"/ N",
    "iso:country":"ES",
    "sg:address":"Barr Picota (la), S/n",
    "sg:city":"Renedo",
    "sg:orig_category":"Fabrica, Negocio De Vidrieras, Productos Vidriados Y Espejos",
    "sg:phone":"+34 942 57 03 77",
    "sg:postcode":"39470",
    "sg:province":"Cantabria",
    "wof:name":"Pardo Cebada Angel",
    "wof:placetype":"venue"
},
  "geometry": {"coordinates":[-3.9566299915,43.3515968323],"type":"Point"}
}