{
  "type": "Feature",
  "properties": {
    "iso:country":"ES",
    "sg:address":"Calle de Pilar (el), 16",
    "sg:city":"Santa Cruz De Tenerife",
    "sg:orig_category":"Abogados",
    "sg:phone":"+34 922 24 60 00",
    "sg:postcode":"38002",
    "sg:province":"Santa Cruz De Tenerife",
    "wof:name":"Bufete Campuzano S.l.",
    "wof:placetype":"venue"
},
  "geometry": {"coordinates":[-16.2520542145,28.4694366455],"type":"Point"}
}