{
  "type": "Feature",
  "properties": {
    "addr:full":"Ctra Valdepe\u00d1as, 5 Ciudad Real Ciudad Real 13004",
    "addr:housenumber":"5",
    "addr:postcode":"13004",
    "addr:street":"Ctra Valdepen\u0303As",
    "iso:country":"ES",
    "sg:address":"Ctra Valdepe\u00d1as, 5",
    "sg:city":"Ciudad Real",
    "sg:orig_category":"Cr\u00cda De Animales De Caza Menor",
    "sg:phone":"+34 926 27 02 49",
    "sg:postcode":"13004",
    "sg:province":"Ciudad Real",
    "wof:name":"Agrocinegetica Borbon S.l",
    "wof:placetype":"venue"
},
  "geometry": {"coordinates":[-3.9195888042,38.9824905396],"type":"Point"}
}