{
  "type": "Feature",
  "properties": {
    "addr:full":"Calle de Santa Rosa, 5 Valencia Valencia 46021",
    "addr:housenumber":"5",
    "addr:postcode":"46021",
    "addr:street":"Calle De Santa Rosa",
    "iso:country":"ES",
    "sg:address":"Calle de Santa Rosa, 5",
    "sg:city":"Valencia",
    "sg:orig_category":"Organismos De Turismo",
    "sg:phone":"+34 963 16 90 83",
    "sg:postcode":"46021",
    "sg:province":"Valencia",
    "wof:name":"Travelplan S.a.",
    "wof:placetype":"venue"
},
  "geometry": {"coordinates":[-0.3583320081,39.4687461853],"type":"Point"}
}