{
  "type": "Feature",
  "properties": {
    "addr:full":"Calle de Mercedes (las), S/n Loja Granada 18300",
    "addr:housenumber":"loja",
    "addr:postcode":"18300",
    "addr:street":"Calle De Mercedes Las S / N",
    "iso:country":"ES",
    "sg:address":"Calle de Mercedes (las), S/n",
    "sg:city":"Loja",
    "sg:orig_category":"Asesor\u00cda Fiscal Y Jur\u00cddica",
    "sg:phone":"+34 958 32 12 89",
    "sg:postcode":"18300",
    "sg:province":"Granada",
    "wof:name":"Asesoria Antonio Jimenez Lopez C.b.",
    "wof:placetype":"venue"
},
  "geometry": {"coordinates":[-4.1457476616,37.1644821167],"type":"Point"}
}