{
  "type": "Feature",
  "properties": {
    "iso:country":"ES",
    "sg:address":"Calle de San Sebastian (de), 35",
    "sg:city":"Colmenar Viejo",
    "sg:orig_category":"Psic\u00d3logos",
    "sg:phone":"+34 918 46 47 42",
    "sg:postcode":"28770",
    "sg:province":"Madrid",
    "wof:name":"Garcia Medina Maria Isabel",
    "wof:placetype":"venue"
},
  "geometry": {"coordinates":[-3.7689080238,40.6633872986],"type":"Point"}
}