{
  "type": "Feature",
  "properties": {
    "iso:country":"ES",
    "sg:address":"Carrer de Alvarado, 20",
    "sg:city":"Barcelona",
    "sg:orig_category":"Chapister\u00cda",
    "sg:phone":"+34 933 59 34 83",
    "sg:postcode":"08042",
    "sg:province":"Barcelona",
    "wof:name":"Bachiller Miro Juan Martin",
    "wof:placetype":"venue"
},
  "geometry": {"coordinates":[2.177339077,41.4476585388],"type":"Point"}
}