{
  "type": "Feature",
  "properties": {
    "addr:full":"Calle de Dulcinea, 36 Pto. Rosario Las Palmas 35600",
    "addr:housenumber":"36",
    "addr:postcode":"35600",
    "addr:street":"Calle De Dulcinea;Pto. Rosario Las",
    "iso:country":"ES",
    "sg:address":"Calle de Dulcinea, 36",
    "sg:city":"Pto. Rosario",
    "sg:orig_category":"Persianas Interiores, Exteriores",
    "sg:phone":"+34 928 85 27 30",
    "sg:postcode":"35600",
    "sg:province":"Las Palmas",
    "wof:name":"Toldos Puerto Cabra S.l.",
    "wof:placetype":"venue"
},
  "geometry": {"coordinates":[-13.8659963608,28.4986114502],"type":"Point"}
}