{
  "type": "Feature",
  "properties": {
    "iso:country":"ES",
    "sg:address":"Calle de Tomas Rodriguez Puertas (de), 1",
    "sg:city":"Alcobendas",
    "sg:orig_category":"Asociaciones Y Clubs Deportivos",
    "sg:phone":"+34 916 51 68 62",
    "sg:postcode":"28100",
    "sg:province":"Madrid",
    "wof:name":"Paz Delgado Antonio Felipe",
    "wof:placetype":"venue"
},
  "geometry": {"coordinates":[-3.6345720291,40.5423583984],"type":"Point"}
}