{
  "type": "Feature",
  "properties": {
    "addr:full":"Carrer de Pagesia Catalana, 22 Vendrell Tarragona 43700",
    "addr:housenumber":"22",
    "addr:postcode":"43700",
    "addr:street":"Carrer De Pagesia Catalana",
    "iso:country":"ES",
    "sg:address":"Carrer de Pagesia Catalana, 22",
    "sg:city":"Vendrell",
    "sg:orig_category":"Cerrajer\u00cda, Ferrallista",
    "sg:phone":"+34 977 66 06 65",
    "sg:postcode":"43700",
    "sg:province":"Tarragona",
    "wof:name":"Pastor Palau David",
    "wof:placetype":"venue"
},
  "geometry": {"coordinates":[1.5367289782,41.222782135],"type":"Point"}
}