{
  "type": "Feature",
  "properties": {
    "addr:full":"Calle de Mariano Vela, 46 Madrid Madrid 28026",
    "addr:housenumber":"46",
    "addr:postcode":"madrid;28026",
    "addr:street":"Calle De Mariano Vela",
    "iso:country":"ES",
    "sg:address":"Calle de Mariano Vela, 46",
    "sg:city":"Madrid",
    "sg:orig_category":"Cerrajer\u00cda, Ferrallista",
    "sg:phone":"+34 914 69 25 64",
    "sg:postcode":"28026",
    "sg:province":"Madrid",
    "wof:name":"Salvador Granados S.l.",
    "wof:placetype":"venue"
},
  "geometry": {"coordinates":[-3.7104139328,40.3837203979],"type":"Point"}
}