{
  "type": "Feature",
  "properties": {
    "iso:country":"ES",
    "sg:address":"Carr Sant Anastasi, 31",
    "sg:city":"Badalona",
    "sg:orig_category":"Alimentaci\u00d3n General (al Por Menor)",
    "sg:phone":"+34 933 89 52 22",
    "sg:postcode":"08911",
    "sg:province":"Barcelona",
    "wof:name":"Estela Gonzalez Vicente",
    "wof:placetype":"venue"
},
  "geometry": {"coordinates":[2.2469909191,41.4504356384],"type":"Point"}
}