{
  "type": "Feature",
  "properties": {
    "addr:full":"Psj. Los Arcos, 1 S. Clemente Cuenca 16600",
    "addr:housenumber":"1",
    "addr:postcode":"16600",
    "addr:street":"Los Arcos;S. Clemente Cuenca",
    "iso:country":"ES",
    "sg:address":"Psj. Los Arcos, 1",
    "sg:city":"S. Clemente",
    "sg:orig_category":"Carnicer\u00cdas, Carnicer\u00cdas",
    "sg:phone":"+34 969 30 21 62",
    "sg:postcode":"16600",
    "sg:province":"Cuenca",
    "wof:name":"Carnes Rejas S.l.",
    "wof:placetype":"venue"
},
  "geometry": {"coordinates":[-2.4270188808,39.3993186951],"type":"Point"}
}