{
  "type": "Feature",
  "properties": {
    "iso:country":"ES",
    "sg:address":"Avgd Ausias March, 27",
    "sg:city":"Burjassot",
    "sg:orig_category":"Mec\u00c1nico Del Autom\u00d3vil",
    "sg:phone":"+34 963 64 37 45",
    "sg:postcode":"46100",
    "sg:province":"Valencia",
    "wof:name":"Garcia Moreno Lorenzo",
    "wof:placetype":"venue"
},
  "geometry": {"coordinates":[-0.4114229977,39.5119438171],"type":"Point"}
}