{
  "type": "Feature",
  "properties": {
    "iso:country":"ES",
    "sg:address":"Ctra Villalpando, S/n",
    "sg:city":"Castroverde De Campos",
    "sg:orig_category":"Comunidades Religiosas",
    "sg:phone":"+34 980 66 46 17",
    "sg:postcode":"49110",
    "sg:province":"Zamora",
    "wof:name":"Padres Franciscanos",
    "wof:placetype":"venue"
},
  "geometry": {"coordinates":[-5.3141918182,41.9721031189],"type":"Point"}
}