{
  "type": "Feature",
  "properties": {
    "addr:full":"Calle de Benito Mas Y Prat, 5 Sevilla Sevilla 41005",
    "addr:housenumber":"5",
    "addr:postcode":"41005",
    "addr:street":"Calle De Benito Mas Y Prat",
    "iso:country":"ES",
    "sg:address":"Calle de Benito Mas Y Prat, 5",
    "sg:city":"Sevilla",
    "sg:orig_category":"Asesor\u00cda Sobre Comunicaci\u00d3n De Empresas",
    "sg:phone":"+34 954 57 24 61",
    "sg:postcode":"41005",
    "sg:province":"Sevilla",
    "wof:name":"Nervion Asesores S.l.",
    "wof:placetype":"venue"
},
  "geometry": {"coordinates":[-5.9709873199,37.3863487244],"type":"Point"}
}