{
  "type": "Feature",
  "properties": {
    "addr:full":"Ctra Castellar, 2 Sentmenat Barcelona 08181",
    "addr:housenumber":"2",
    "addr:postcode":"08181",
    "addr:street":"Ctra Castellar",
    "iso:country":"ES",
    "sg:address":"Ctra Castellar, 2",
    "sg:city":"Sentmenat",
    "sg:orig_category":"Internados & Ense\u00d1anza Privada",
    "sg:phone":"+34 937 15 34 08",
    "sg:postcode":"08181",
    "sg:province":"Barcelona",
    "wof:name":"Fundacion Padre Piulachs",
    "wof:placetype":"venue"
},
  "geometry": {"coordinates":[2.1349349022,41.6101417542],"type":"Point"}
}