{
  "type": "Feature",
  "properties": {
    "iso:country":"ES",
    "sg:address":"Calle de Puerto Real, S/n",
    "sg:city":"Cadiz",
    "sg:orig_category":"Agentes, Concesionarios Y Sucursales De Veh\u00cdculos",
    "sg:phone":"+34 956 27 13 00",
    "sg:postcode":"11011",
    "sg:province":"C\u00e1diz",
    "wof:name":"Motores Cadiz S.a.",
    "wof:placetype":"venue"
},
  "geometry": {"coordinates":[-6.2652201653,36.4947814941],"type":"Point"}
}