{
  "type": "Feature",
  "properties": {
    "iso:country":"ES",
    "sg:address":"Calle de Riego De Agua, 16",
    "sg:city":"Coru\u00d1a",
    "sg:orig_category":"Publicidad (soportes Y Gesti\u00d3n)",
    "sg:phone":"+34 981 22 20 64",
    "sg:postcode":"15001",
    "sg:province":"La Coru\u00f1a",
    "wof:name":"Intermediarios De Comunicaciones S.l.",
    "wof:placetype":"venue"
},
  "geometry": {"coordinates":[-8.3973379135,43.3707962036],"type":"Point"}
}