{
  "type": "Feature",
  "properties": {
    "iso:country":"ES",
    "sg:address":"Calle de Mendaro, 5",
    "sg:city":"Chiclana De La Frontera",
    "sg:orig_category":"Sociedades, Compa\u00d1\u00cdas Aseguradoras",
    "sg:phone":"+34 956 40 17 42",
    "sg:postcode":"11130",
    "sg:province":"C\u00e1diz",
    "wof:name":"La Janda Asesoria S.l.",
    "wof:placetype":"venue"
},
  "geometry": {"coordinates":[-6.1519842148,36.4190826416],"type":"Point"}
}