{
  "type": "Feature",
  "properties": {
    "iso:country":"ES",
    "sg:address":"Calle de Ruperto Chapi (de), 8",
    "sg:city":"Alcobendas",
    "sg:orig_category":"Peluquer\u00cdas, Peluquer\u00cda Mixta",
    "sg:phone":"+34 916 54 84 56",
    "sg:postcode":"28100",
    "sg:province":"Madrid",
    "wof:name":"Mora Ortega Leonor",
    "wof:placetype":"venue"
},
  "geometry": {"coordinates":[-3.6451809406,40.5475082397],"type":"Point"}
}