{
  "type": "Feature",
  "properties": {
    "addr:full":"Avda Zaragoza, 22 Cadrete Zaragoza 50420",
    "addr:housenumber":"22",
    "addr:postcode":"50420",
    "addr:street":"Avda Zaragoza",
    "iso:country":"ES",
    "sg:address":"Avda Zaragoza, 22",
    "sg:city":"Cadrete",
    "sg:orig_category":"Tapicer\u00cdas",
    "sg:phone":"+34 976 12 52 11",
    "sg:postcode":"50420",
    "sg:province":"Zaragoza",
    "wof:name":"Tapigrama S.l.",
    "wof:placetype":"venue"
},
  "geometry": {"coordinates":[-0.9644399881,41.5597305298],"type":"Point"}
}