{
  "type": "Feature",
  "properties": {
    "addr:full":"Avgd Prat De La Riba, 18 Lleida Lleida 25004",
    "addr:housenumber":"18",
    "addr:postcode":"25004",
    "addr:street":"La Riba",
    "iso:country":"ES",
    "sg:address":"Avgd Prat De La Riba, 18",
    "sg:city":"Lleida",
    "sg:orig_category":"Cajas De Ahorro",
    "sg:phone":"+34 973 24 81 50",
    "sg:postcode":"25004",
    "sg:province":"Lleida",
    "sg:website":"www.caixamanresa.es",
    "wof:name":"Caixa D'estalvis De Manresa",
    "wof:placetype":"venue"
},
  "geometry": {"coordinates":[0.6206279993,41.6195983887],"type":"Point"}
}