{
  "type": "Feature",
  "properties": {
    "iso:country":"ES",
    "sg:address":"Carrer de Pare Llaurador, 102",
    "sg:city":"Terrassa",
    "sg:orig_category":"Laboratorios Y Trabajos De Fotograf\u00cda, V\u00cddeo Y Cine",
    "sg:phone":"+34 937 80 77 26",
    "sg:postcode":"08224",
    "sg:province":"Barcelona",
    "wof:name":"Torres Margarit Alberto",
    "wof:placetype":"venue"
},
  "geometry": {"coordinates":[2.0044300556,41.5642166138],"type":"Point"}
}