{
  "type": "Feature",
  "properties": {
    "addr:full":"Calle de Americo Vespucio, 91 Clavellinas Las Palmas 35214",
    "addr:housenumber":"91",
    "addr:postcode":"35214",
    "addr:street":"Calle De Americo Vespucio;Las Palmas",
    "iso:country":"ES",
    "sg:address":"Calle de Americo Vespucio, 91",
    "sg:city":"Clavellinas",
    "sg:orig_category":"Ense\u00d1anza Variada",
    "sg:phone":"+34 928 13 12 07",
    "sg:postcode":"35214",
    "sg:province":"Las Palmas",
    "wof:name":"Villalba Ruiz Monserrat",
    "wof:placetype":"venue"
},
  "geometry": {"coordinates":[-15.3887634277,27.9937648773],"type":"Point"}
}