{
  "type": "Feature",
  "properties": {
    "iso:country":"ES",
    "sg:address":"Carr Padua, 4",
    "sg:city":"Vilanova I La Geltru",
    "sg:orig_category":"Inmobiliaria (agencias)",
    "sg:phone":"+34 938 14 71 07",
    "sg:postcode":"08800",
    "sg:province":"Barcelona",
    "sg:website":"www.inmobiliariaroma.com",
    "wof:name":"Asesoria Inmobiliaria Roma",
    "wof:placetype":"venue"
},
  "geometry": {"coordinates":[1.7263958454,41.2267379761],"type":"Point"}
}