{
  "type": "Feature",
  "properties": {
    "iso:country":"ES",
    "sg:address":"Pl Espanya, 1",
    "sg:city":"Palma",
    "sg:orig_category":"Comercios E Industrias (cesi\u00d3n Y Reactivaci\u00d3n)",
    "sg:phone":"+34 971 72 32 05",
    "sg:postcode":"07002",
    "sg:province":"Islas Baleares",
    "wof:name":"De Lapresa Rodriguez-contreras Jose Luis",
    "wof:placetype":"venue"
},
  "geometry": {"coordinates":[2.6531000137,39.5758781433],"type":"Point"}
}