{
  "type": "Feature",
  "properties": {
    "iso:country":"ES",
    "sg:address":"Calle de Pico Pasapan, 2",
    "sg:city":"Madrid",
    "sg:orig_category":"Laboratorios Farmac\u00c9uticos",
    "sg:phone":"+34 917 34 79 28",
    "sg:postcode":"28034",
    "sg:province":"Madrid",
    "wof:name":"Gaubil  Jean Claude",
    "wof:placetype":"venue"
},
  "geometry": {"coordinates":[-3.7075219154,40.4919013977],"type":"Point"}
}