{
  "type": "Feature",
  "properties": {
    "addr:full":"Calle de Mayor, 15 Villaconejos Trabaque Cuenca 16860",
    "addr:housenumber":"15",
    "addr:postcode":"16860",
    "addr:street":"Calle De Mayor",
    "iso:country":"ES",
    "sg:address":"Calle de Mayor, 15",
    "sg:city":"Villaconejos Trabaque",
    "sg:orig_category":"Quincaller\u00cda (al Por Menor)",
    "sg:phone":"+34 969 31 56 22",
    "sg:postcode":"16860",
    "sg:province":"Cuenca",
    "wof:name":"Lopez Gomez Rosa Maria",
    "wof:placetype":"venue"
},
  "geometry": {"coordinates":[-2.3179199696,40.4001197815],"type":"Point"}
}