{
  "type": "Feature",
  "properties": {
    "iso:country":"ES",
    "sg:address":"Avda Sebastian Molina, 8",
    "sg:city":"Pedro\u00d1eras",
    "sg:orig_category":"Veh\u00cdculos De Ocasi\u00d3n",
    "sg:phone":"+34 967 16 05 15",
    "sg:postcode":"16660",
    "sg:province":"Cuenca",
    "wof:name":"Melero Lopez Eusebio",
    "wof:placetype":"venue"
},
  "geometry": {"coordinates":[-2.6725988388,39.4450721741],"type":"Point"}
}