{
  "type": "Feature",
  "properties": {
    "iso:country":"ES",
    "sg:address":"Avda Juan Carlos I, 17",
    "sg:city":"Monforte Cid",
    "sg:orig_category":"Asesor\u00cda De Formaci\u00d3n Y Gesti\u00d3n De Personal",
    "sg:phone":"+34 965 62 15 30",
    "sg:postcode":"03670",
    "sg:province":"Alicante",
    "wof:name":"Ramirez Cremades Francisco Jose",
    "wof:placetype":"venue"
},
  "geometry": {"coordinates":[-0.7296299934,38.3807296753],"type":"Point"}
}