{
  "type": "Feature",
  "properties": {
    "addr:full":"Plaz Jose Maria Orense, 11 Valencia Valencia 46022",
    "addr:housenumber":"11",
    "addr:postcode":"46022",
    "addr:street":"Maria Orense",
    "iso:country":"ES",
    "sg:address":"Plaz Jose Maria Orense, 11",
    "sg:city":"Valencia",
    "sg:orig_category":"Librer\u00cdas",
    "sg:phone":"+34 963 71 66 91",
    "sg:postcode":"46022",
    "sg:province":"Valencia",
    "wof:name":"Chulia Belenguer Mariano",
    "wof:placetype":"venue"
},
  "geometry": {"coordinates":[-0.3392930031,39.4724082947],"type":"Point"}
}