{
  "type": "Feature",
  "properties": {
    "iso:country":"ES",
    "sg:address":"Madanela, S/n",
    "sg:city":"Melide",
    "sg:orig_category":"Quincaller\u00cda (al Por Menor)",
    "sg:phone":"+34 981 50 77 18",
    "sg:postcode":"15800",
    "sg:province":"La Coru\u00f1a",
    "wof:name":"Centro Comercial Ares S.l.",
    "wof:placetype":"venue"
},
  "geometry": {"coordinates":[-8.0129041672,42.9135894775],"type":"Point"}
}