{
  "type": "Feature",
  "properties": {
    "iso:country":"ES",
    "sg:address":"Calle de Naciones, 19",
    "sg:city":"Madrid",
    "sg:orig_category":"M\u00c9dicos: Medicina Manual",
    "sg:phone":"+34 915 78 32 58",
    "sg:postcode":"28006",
    "sg:province":"Madrid",
    "wof:name":"Fisioterapia Naciones S.l.",
    "wof:placetype":"venue"
},
  "geometry": {"coordinates":[-3.6736440659,40.4265518188],"type":"Point"}
}