{
  "type": "Feature",
  "properties": {
    "addr:full":"Calle de Lopez De Gomara, 35 Sevilla Sevilla 41010",
    "addr:housenumber":"35",
    "addr:postcode":"41010",
    "addr:street":"Calle De Lopez De Gomara",
    "iso:country":"ES",
    "sg:address":"Calle de Lopez De Gomara, 35",
    "sg:city":"Sevilla",
    "sg:orig_category":"Librer\u00cdas",
    "sg:phone":"+34 954 45 56 59",
    "sg:postcode":"41010",
    "sg:province":"Sevilla",
    "wof:name":"Gabriel Salinas Ramon",
    "wof:placetype":"venue"
},
  "geometry": {"coordinates":[-6.0071911812,37.3782806396],"type":"Point"}
}