{
  "type": "Feature",
  "properties": {
    "iso:country":"ES",
    "sg:address":"Huerva, 5",
    "sg:city":"Cadrete",
    "sg:orig_category":"Productos Qu\u00cdmicos (fabricaci\u00d3n, Al Por Mayor)",
    "sg:phone":"+34 976 12 53 33",
    "sg:postcode":"50420",
    "sg:province":"Zaragoza",
    "wof:name":"Calvo Cabal Jose",
    "wof:placetype":"venue"
},
  "geometry": {"coordinates":[-0.9663630128,41.549823761],"type":"Point"}
}