{
  "type": "Feature",
  "properties": {
    "addr:full":"Calle de Impresores, 1 Getafe Madrid 28906",
    "addr:housenumber":"1",
    "addr:postcode":"28906",
    "addr:street":"Calle De Impresores",
    "iso:country":"ES",
    "sg:address":"Calle de Impresores, 1",
    "sg:city":"Getafe",
    "sg:orig_category":"Negocio De Granos Y Harinas",
    "sg:phone":"+34 916 81 91 88",
    "sg:postcode":"28906",
    "sg:province":"Madrid",
    "wof:name":"Harineras Villamayor S.a.",
    "wof:placetype":"venue"
},
  "geometry": {"coordinates":[-3.7010269165,40.3105773926],"type":"Point"}
}