{
  "type": "Feature",
  "properties": {
    "addr:full":"Calle de Veinte Metros, 27 Valladolid Valladolid 47005",
    "addr:housenumber":"27",
    "addr:postcode":"47005",
    "addr:street":"Calle De Veinte Metros",
    "iso:country":"ES",
    "sg:address":"Calle de Veinte Metros, 27",
    "sg:city":"Valladolid",
    "sg:orig_category":"Carpinteros",
    "sg:phone":"+34 983 20 39 35",
    "sg:postcode":"47005",
    "sg:province":"Valladolid",
    "wof:name":"Deteco Ventanas S.l",
    "wof:placetype":"venue"
},
  "geometry": {"coordinates":[-4.7154111862,41.6488723755],"type":"Point"}
}