{
  "type": "Feature",
  "properties": {
    "iso:country":"ES",
    "sg:address":"Avda Maria De Las Mercedes, 2",
    "sg:city":"Alovera",
    "sg:orig_category":"Electricidad: Instaladores",
    "sg:phone":"+34 949 27 57 10",
    "sg:postcode":"19208",
    "sg:province":"Guadalajara",
    "wof:name":"Gonzalez Carvajal Julio",
    "wof:placetype":"venue"
},
  "geometry": {"coordinates":[-3.2416350842,40.5986785889],"type":"Point"}
}