{
  "type": "Feature",
  "properties": {
    "iso:country":"ES",
    "sg:address":"Calle de Esteban Mora, 51",
    "sg:city":"Madrid",
    "sg:orig_category":"Publicidad (soportes Y Gesti\u00d3n)",
    "sg:phone":"+34 914 04 31 08",
    "sg:postcode":"28027",
    "sg:province":"Madrid",
    "wof:name":"Cafe Majo S.l.",
    "wof:placetype":"venue"
},
  "geometry": {"coordinates":[-3.6530179977,40.4395065308],"type":"Point"}
}