{
  "type": "Feature",
  "properties": {
    "addr:full":"Ctra. Jaen, S/n Puente Obispo Ja\u00e9n 23529",
    "addr:housenumber":"s / n",
    "addr:postcode":"23529",
    "addr:street":"Ctra. Jaen;Obispo Jae\u0301N",
    "iso:country":"ES",
    "sg:address":"Ctra. Jaen, S/n",
    "sg:city":"Puente Obispo",
    "sg:orig_category":"Museos",
    "sg:phone":"+34 953 76 51 42",
    "sg:postcode":"23529",
    "sg:province":"Ja\u00e9n",
    "sg:website":"www.baezamonumental.com",
    "wof:name":"Populo Servicios Turisticos S.l.",
    "wof:placetype":"venue"
},
  "geometry": {"coordinates":[-3.5354540348,37.9567832947],"type":"Point"}
}