{
  "type": "Feature",
  "properties": {
    "iso:country":"ES",
    "sg:address":"Calle de Venecia, 7",
    "sg:city":"Monte Vedat",
    "sg:orig_category":"Delegados, Agentes De Tr\u00c1nsito, Auxiliares De Transporte Internacional",
    "sg:phone":"+34 961 56 29 83",
    "sg:postcode":"46901",
    "sg:province":"Valencia",
    "wof:name":"Trans. Brosel",
    "wof:placetype":"venue"
},
  "geometry": {"coordinates":[-0.4875670075,39.4059486389],"type":"Point"}
}