{
  "type": "Feature",
  "properties": {
    "addr:full":"Carrer de Riera De Premia, 33 Premia Mar Barcelona 08330",
    "addr:housenumber":"33",
    "addr:postcode":"08330",
    "addr:street":"Carrer De Riera De Premia",
    "iso:country":"ES",
    "sg:address":"Carrer de Riera De Premia, 33",
    "sg:city":"Premia Mar",
    "sg:orig_category":"Molduras, Junquillos, Listones Y Molduras Perforadas",
    "sg:phone":"+34 937 52 11 96",
    "sg:postcode":"08330",
    "sg:province":"Barcelona",
    "wof:name":"Garcia Rodriguez Rafael",
    "wof:placetype":"venue"
},
  "geometry": {"coordinates":[2.3538448811,41.4903182983],"type":"Point"}
}