{
  "type": "Feature",
  "properties": {
    "addr:full":"Calle de Eras, 5 Villarejo Segovia 40590",
    "addr:housenumber":"5",
    "addr:postcode":"40590",
    "addr:street":"Calle De Eras",
    "iso:country":"ES",
    "sg:address":"Calle de Eras, 5",
    "sg:city":"Villarejo",
    "sg:orig_category":"Carnicer\u00cdas, Carnicer\u00cdas",
    "sg:phone":"+34 921 55 72 30",
    "sg:postcode":"40590",
    "sg:province":"Segovia",
    "wof:name":"Garcia San Juan Maria Del Carmen",
    "wof:placetype":"venue"
},
  "geometry": {"coordinates":[-3.5782938004,41.1951446533],"type":"Point"}
}