{
  "type": "Feature",
  "properties": {
    "addr:full":"Calle de Coru\u00d1a (la), 1 Salamanca Salamanca 37003",
    "addr:housenumber":"1",
    "addr:postcode":"37003",
    "addr:street":"Calle De Corun\u0303A La",
    "iso:country":"ES",
    "sg:address":"Calle de Coru\u00d1a (la), 1",
    "sg:city":"Salamanca",
    "sg:orig_category":"Molduras, Junquillos, Listones Y Molduras Perforadas",
    "sg:phone":"+34 923 18 28 58",
    "sg:postcode":"37003",
    "sg:province":"Salamanca",
    "wof:name":"Hosteleria Garbaya S.l.",
    "wof:placetype":"venue"
},
  "geometry": {"coordinates":[-5.6489973068,40.9664535522],"type":"Point"}
}