{
  "type": "Feature",
  "properties": {
    "iso:country":"ES",
    "sg:address":"Ctra Vic, 47",
    "sg:city":"Manresa",
    "sg:orig_category":"Importaci\u00d3n, Exportaci\u00d3n Y Comercios De Productos Textiles",
    "sg:phone":"+34 938 73 16 18",
    "sg:postcode":"08241",
    "sg:province":"Barcelona",
    "wof:name":"Moncunill Torne Jorge",
    "wof:placetype":"venue"
},
  "geometry": {"coordinates":[1.827671051,41.7275238037],"type":"Point"}
}