{
  "type": "Feature",
  "properties": {
    "iso:country":"ES",
    "sg:address":"Avda Novelda, 209",
    "sg:city":"Alacant",
    "sg:orig_category":"Escayola Y Productos De Escayola (fabricaci\u00d3n, Al Por Mayor)",
    "sg:phone":"+34 965 17 34 54",
    "sg:postcode":"03009",
    "sg:province":"Alicante",
    "wof:name":"Aislamientos Acusticos Levante S.l.",
    "wof:placetype":"venue"
},
  "geometry": {"coordinates":[-0.4969969094,38.3693199158],"type":"Point"}
}