{
  "type": "Feature",
  "properties": {
    "iso:country":"ES",
    "sg:address":"Calle de Fernando Guanarteme, 46",
    "sg:city":"Palmas De Gran Canaria",
    "sg:orig_category":"Farmacias",
    "sg:phone":"+34 928 26 06 65",
    "sg:postcode":"35010",
    "sg:province":"Las Palmas",
    "wof:name":"De La Coba Ros Maria Jesus",
    "wof:placetype":"venue"
},
  "geometry": {"coordinates":[-15.4369316101,28.1358795166],"type":"Point"}
}