{
  "type": "Feature",
  "properties": {
    "iso:country":"ES",
    "sg:address":"Calle de Fuengirola, 23",
    "sg:city":"Madrid",
    "sg:orig_category":"Confecci\u00d3n De Trajes Para Se\u00d1oras",
    "sg:phone":"+34 917 78 06 22",
    "sg:postcode":"28018",
    "sg:province":"Madrid",
    "wof:name":"Serrano Sanchez Gregoria",
    "wof:placetype":"venue"
},
  "geometry": {"coordinates":[-3.640789032,40.3837394714],"type":"Point"}
}