{
  "type": "Feature",
  "properties": {
    "addr:full":"Rua Terra (da), 166 Lugo Lugo 27003",
    "addr:housenumber":"166",
    "addr:postcode":"27003",
    "addr:street":"Rua Terra Da",
    "iso:country":"ES",
    "sg:address":"Rua Terra (da), 166",
    "sg:city":"Lugo",
    "sg:orig_category":"Promotores Constructores",
    "sg:phone":"+34 982 20 90 04",
    "sg:postcode":"27003",
    "sg:province":"Lugo",
    "wof:name":"Obras Y Constucciones Cortizo S.l.",
    "wof:placetype":"venue"
},
  "geometry": {"coordinates":[-7.5625290871,43.0420608521],"type":"Point"}
}