{
  "type": "Feature",
  "properties": {
    "addr:full":"Pase Federico Garcia Lorca, 11 Madrid Madrid 28031",
    "addr:housenumber":"11",
    "addr:postcode":"madrid;28031",
    "addr:street":"Federico Garcia Lorca",
    "iso:country":"ES",
    "sg:address":"Pase Federico Garcia Lorca, 11",
    "sg:city":"Madrid",
    "sg:orig_category":"Perfumer\u00cda (al Por Menor)",
    "sg:phone":"+34 913 32 87 74",
    "sg:postcode":"28031",
    "sg:province":"Madrid",
    "sg:website":"www.marionnaud.es",
    "wof:name":"Marionnaud Perfumeries Iberica S.l.",
    "wof:placetype":"venue"
},
  "geometry": {"coordinates":[-3.6210160255,40.3783493042],"type":"Point"}
}