{
  "type": "Feature",
  "properties": {
    "iso:country":"ES",
    "sg:address":"Avda Dos De Mayo (del), 18",
    "sg:city":"Mostoles",
    "sg:orig_category":"Reciclaje, Tratamiento De Tejidos",
    "sg:phone":"+34 916 64 08 38",
    "sg:postcode":"28934",
    "sg:province":"Madrid",
    "wof:name":"Duran Mena Jose",
    "wof:placetype":"venue"
},
  "geometry": {"coordinates":[-3.8659670353,40.3213386536],"type":"Point"}
}