{
  "type": "Feature",
  "properties": {
    "addr:full":"Trva Pilar, 33 Altura Castell\u00f3n 12410",
    "addr:housenumber":"33",
    "addr:postcode":"12410",
    "addr:street":"Trva Pilar",
    "iso:country":"ES",
    "sg:address":"Trva Pilar, 33",
    "sg:city":"Altura",
    "sg:orig_category":"Arenas, Guijarros Y Granulados",
    "sg:phone":"+34 964 14 63 95",
    "sg:postcode":"12410",
    "sg:province":"Castell\u00f3n",
    "wof:name":"Aridos Carot Selles S.l.",
    "wof:placetype":"venue"
},
  "geometry": {"coordinates":[-0.5825359225,39.8358764648],"type":"Point"}
}