{
  "type": "Feature",
  "properties": {
    "addr:full":"Trva Madrid, 6 Brihuega Guadalajara 19400",
    "addr:housenumber":"6",
    "addr:postcode":"19400",
    "addr:street":"Trva Madrid",
    "iso:country":"ES",
    "sg:address":"Trva Madrid, 6",
    "sg:city":"Brihuega",
    "sg:orig_category":"Electricidad: Instaladores",
    "sg:phone":"+34 949 28 02 72",
    "sg:postcode":"19400",
    "sg:province":"Guadalajara",
    "wof:name":"Tabernera De Andres C.b.",
    "wof:placetype":"venue"
},
  "geometry": {"coordinates":[-2.8710069656,40.7622108459],"type":"Point"}
}