{
  "type": "Feature",
  "properties": {
    "addr:full":"Bard Caja Rural, 16 Fregenal Sierra Badajoz 06340",
    "addr:housenumber":"16",
    "addr:postcode":"06340",
    "addr:street":"Fregenal Sierra",
    "iso:country":"ES",
    "sg:address":"Bard Caja Rural, 16",
    "sg:city":"Fregenal Sierra",
    "sg:orig_category":"Empresas De Carpinter\u00cda De Madera",
    "sg:phone":"+34 924 70 07 27",
    "sg:postcode":"06340",
    "sg:province":"Badajoz",
    "wof:name":"Lanchazo Bada Joaquin",
    "wof:placetype":"venue"
},
  "geometry": {"coordinates":[-6.6505317688,38.1659088135],"type":"Point"}
}