{
  "type": "Feature",
  "properties": {
    "iso:country":"ES",
    "sg:address":"Carrer de Sant Crispi, 19",
    "sg:city":"Barcelona",
    "sg:orig_category":"Fabricaci\u00d3n De Pastas Alimentarias",
    "sg:phone":"+34 934 29 21 43",
    "sg:postcode":"08035",
    "sg:province":"Barcelona",
    "wof:name":"Prados Rojas Nuria",
    "wof:placetype":"venue"
},
  "geometry": {"coordinates":[2.1473789215,41.4227981567],"type":"Point"}
}