{
  "type": "Feature",
  "properties": {
    "iso:country":"ES",
    "sg:address":"Carrer de Diputacio, 471",
    "sg:city":"Barcelona",
    "sg:orig_category":"Peluqueros: De Se\u00d1oras",
    "sg:phone":"+34 932 31 03 06",
    "sg:postcode":"08013",
    "sg:province":"Barcelona",
    "wof:name":"Pascual Gascon Nieves",
    "wof:placetype":"venue"
},
  "geometry": {"coordinates":[2.180918932,41.4009819031],"type":"Point"}
}