{
  "type": "Feature",
  "properties": {
    "addr:full":"Poli Industrial Autopista Sur, S/n Castellon De La Plana Castell\u00f3n 12006",
    "addr:housenumber":"s / n",
    "addr:postcode":"12006",
    "iso:country":"ES",
    "sg:address":"Poli Industrial Autopista Sur, S/n",
    "sg:city":"Castellon De La Plana",
    "sg:orig_category":"Piedra, Vidrio, Cer\u00c1mica Y Porcelana",
    "sg:phone":"+34 964 34 11 40",
    "sg:postcode":"12006",
    "sg:province":"Castell\u00f3n",
    "wof:name":"Matex Interdis S.l.",
    "wof:placetype":"venue"
},
  "geometry": {"coordinates":[-0.1404139996,40.0213813782],"type":"Point"}
}