{
  "type": "Feature",
  "properties": {
    "addr:full":"Avda Ntra. Sra. De Valvanera, 46 Calahorra La Rioja 26500",
    "addr:housenumber":"46",
    "addr:postcode":"26500",
    "addr:street":"Avda Ntra. Sra. De Valvanera",
    "iso:country":"ES",
    "sg:address":"Avda Ntra. Sra. De Valvanera, 46",
    "sg:city":"Calahorra",
    "sg:orig_category":"Cl\u00cdnicas Dentales",
    "sg:phone":"+34 941 14 83 31",
    "sg:postcode":"26500",
    "sg:province":"La Rioja",
    "wof:name":"Clinica Dental Valvanera S.l.",
    "wof:placetype":"venue"
},
  "geometry": {"coordinates":[-1.9620640278,42.3058395386],"type":"Point"}
}