{
  "type": "Feature",
  "properties": {
    "iso:country":"ES",
    "sg:address":"Carretera De Mendigorria, 2",
    "sg:city":"Gares",
    "sg:orig_category":"Electricidad: Instaladores",
    "sg:phone":"+34 948 34 00 79",
    "sg:postcode":"31100",
    "sg:province":"Navarra",
    "wof:name":"Electricidad Irurtia S.l.l.",
    "wof:placetype":"venue"
},
  "geometry": {"coordinates":[-1.8155030012,42.6704597473],"type":"Point"}
}