{
  "type": "Feature",
  "properties": {
    "addr:full":"Rua Xeneral Gutierrez Mellado, 4 Pontevedra Pontevedra 36001",
    "addr:housenumber":"4",
    "addr:postcode":"36001",
    "addr:street":"Rua Xeneral;Mellado",
    "iso:country":"ES",
    "sg:address":"Rua Xeneral Gutierrez Mellado, 4",
    "sg:city":"Pontevedra",
    "sg:orig_category":"Mercer\u00cda, Lencer\u00cda (al Por Menor)",
    "sg:phone":"+34 986 85 29 66",
    "sg:postcode":"36001",
    "sg:province":"Pontevedra",
    "wof:name":"Sanchez Verez Emerita",
    "wof:placetype":"venue"
},
  "geometry": {"coordinates":[-8.6459732056,42.431022644],"type":"Point"}
}