{
  "type": "Feature",
  "properties": {
    "iso:country":"ES",
    "sg:address":"Pl Vila, 1",
    "sg:city":"Santa Perpetua De Mogoda",
    "sg:orig_category":"Cajas De Ahorro",
    "sg:phone":"+34 935 60 00 07",
    "sg:postcode":"08130",
    "sg:province":"Barcelona",
    "sg:website":"www.caixasabadell.es",
    "wof:name":"Caixa D'estalvis Sabadell",
    "wof:placetype":"venue"
},
  "geometry": {"coordinates":[2.1829140186,41.5350341797],"type":"Point"}
}