{
  "type": "Feature",
  "properties": {
    "addr:full":"Calle de Zubeztia, 21 Alsasua Navarra 31800",
    "addr:housenumber":"21",
    "addr:postcode":"31800",
    "addr:street":"Calle De Zubeztia",
    "iso:country":"ES",
    "sg:address":"Calle de Zubeztia, 21",
    "sg:city":"Alsasua",
    "sg:orig_category":"Inmobiliaria (agencias)",
    "sg:phone":"+34 948 56 27 45",
    "sg:postcode":"31800",
    "sg:province":"Navarra",
    "wof:name":"Construcciones Alzate S.l.",
    "wof:placetype":"venue"
},
  "geometry": {"coordinates":[-2.16711092,42.8961791992],"type":"Point"}
}