{
  "type": "Feature",
  "properties": {
    "iso:country":"ES",
    "sg:address":"Avda Constitucion, 21",
    "sg:city":"Miranda Del Casta\u00e7ar",
    "sg:orig_category":"Transportes Por Carretera: Lotes Completos, Mercanc\u00cdas Diversas",
    "sg:phone":"+34 923 43 20 17",
    "sg:postcode":"37660",
    "sg:province":"Salamanca",
    "wof:name":"Jamones Benito Perez S.l.",
    "wof:placetype":"venue"
},
  "geometry": {"coordinates":[-5.9989438057,40.4845161438],"type":"Point"}
}