{
  "type": "Feature",
  "properties": {
    "addr:full":"Calle de Imeldo Seris, 50 Santa Cruz De Tenerife Santa Cruz De Tenerife 38003",
    "addr:housenumber":"50",
    "addr:postcode":"38003",
    "addr:street":"Calle De Imeldo Seris",
    "iso:country":"ES",
    "sg:address":"Calle de Imeldo Seris, 50",
    "sg:city":"Santa Cruz De Tenerife",
    "sg:orig_category":"Zapatos (al Por Menor)",
    "sg:phone":"+34 922 53 33 27",
    "sg:postcode":"38003",
    "sg:province":"Santa Cruz De Tenerife",
    "wof:name":"Tinerfam S.l.",
    "wof:placetype":"venue"
},
  "geometry": {"coordinates":[-16.2512722015,28.4663448334],"type":"Point"}
}