{
  "type": "Feature",
  "properties": {
    "addr:full":"Carrer de Sant Rafel, 27 Olot Girona 17800",
    "addr:housenumber":"27",
    "addr:postcode":"17800",
    "addr:street":"Carrer De Sant Rafel",
    "iso:country":"ES",
    "sg:address":"Carrer de Sant Rafel, 27",
    "sg:city":"Olot",
    "sg:orig_category":"Estilistas Y Estudios De Estilo De Corte Y Confecci\u00d3n",
    "sg:phone":"+34 972 26 10 70",
    "sg:postcode":"17800",
    "sg:province":"Girona",
    "wof:name":"Soler Nogue S.l.",
    "wof:placetype":"venue"
},
  "geometry": {"coordinates":[2.4867939949,42.1812362671],"type":"Point"}
}