{
  "type": "Feature",
  "properties": {
    "addr:full":"Carrer de Villarroel, 181 Barcelona Barcelona 08036",
    "addr:housenumber":"181",
    "addr:postcode":"08036",
    "addr:street":"Carrer De Villarroel",
    "iso:country":"ES",
    "sg:address":"Carrer de Villarroel, 181",
    "sg:city":"Barcelona",
    "sg:orig_category":"Cine (producci\u00d3n, Realizaci\u00d3n)",
    "sg:phone":"+34 934 53 00 70",
    "sg:postcode":"08036",
    "sg:province":"Barcelona",
    "wof:name":"Herrera Torrent Francisco",
    "wof:placetype":"venue"
},
  "geometry": {"coordinates":[2.1519401073,41.3886566162],"type":"Point"}
}