{
  "type": "Feature",
  "properties": {
    "addr:full":"Calle de Berastegui, 40 Madrid Madrid 28017",
    "addr:housenumber":"40",
    "addr:postcode":"madrid;28017",
    "addr:street":"Calle De Berastegui",
    "iso:country":"ES",
    "sg:address":"Calle de Berastegui, 40",
    "sg:city":"Madrid",
    "sg:orig_category":"Perfumer\u00cda (al Por Menor)",
    "sg:phone":"+34 914 08 14 72",
    "sg:postcode":"28017",
    "sg:province":"Madrid",
    "sg:website":"www.bodybell.com",
    "wof:name":"Iberica De Drogueria Y Perfumeria S.a.",
    "wof:placetype":"venue"
},
  "geometry": {"coordinates":[-3.6412246227,40.4279670715],"type":"Point"}
}