{
  "type": "Feature",
  "properties": {
    "iso:country":"ES",
    "sg:address":"Avda Madariaga, 7",
    "sg:city":"Bilbao",
    "sg:orig_category":"Fabricaci\u00d3n De Ventanas",
    "sg:phone":"+34 944 75 75 04",
    "sg:postcode":"48014",
    "sg:province":"Vizcaya",
    "wof:name":"Carbajo Quiros Elisa",
    "wof:placetype":"venue"
},
  "geometry": {"coordinates":[-2.9451398849,43.2709693909],"type":"Point"}
}