{
  "type": "Feature",
  "properties": {
    "iso:country":"ES",
    "sg:address":"Carrer de Sardenya, 229",
    "sg:city":"Barcelona",
    "sg:orig_category":"Inform\u00c1tica (estudios, Servicios, Asesor\u00cda, Formaci\u00d3n)",
    "sg:phone":"+34 932 44 06 20",
    "sg:postcode":"08013",
    "sg:province":"Barcelona",
    "sg:website":"www.neogrup.com",
    "wof:name":"Neo Grup Management S.l.",
    "wof:placetype":"venue"
},
  "geometry": {"coordinates":[2.177241087,41.4002571106],"type":"Point"}
}