{
  "type": "Feature",
  "properties": {
    "addr:full":"Calle de Padre Pandelo, 14 Linea De La Concepcion C\u00e1diz 11300",
    "addr:housenumber":"14",
    "addr:postcode":"11300",
    "addr:street":"Calle De Padre Pandelo;Ca\u0301Diz",
    "iso:country":"ES",
    "sg:address":"Calle de Padre Pandelo, 14",
    "sg:city":"Linea De La Concepcion",
    "sg:orig_category":"Quincaller\u00cda (al Por Menor)",
    "sg:phone":"+34 956 17 22 67",
    "sg:postcode":"11300",
    "sg:province":"C\u00e1diz",
    "wof:name":"Curro Mena Francisco",
    "wof:placetype":"venue"
},
  "geometry": {"coordinates":[-5.3458619118,36.1679573059],"type":"Point"}
}