{
  "type": "Feature",
  "properties": {
    "addr:full":"Avda Ocho De Agosto, 50 Santo Domingo Santa Cruz De Tenerife 38437",
    "addr:housenumber":"50",
    "addr:postcode":"38437",
    "addr:street":"Avda Ocho De Agosto",
    "iso:country":"ES",
    "sg:address":"Avda Ocho De Agosto, 50",
    "sg:city":"Santo Domingo",
    "sg:orig_category":"Electrodom\u00c9sticos (al Por Menor)",
    "sg:phone":"+34 922 36 08 93",
    "sg:postcode":"38437",
    "sg:province":"Santa Cruz De Tenerife",
    "wof:name":"Gonzalez Mesa Emilio",
    "wof:placetype":"venue"
},
  "geometry": {"coordinates":[-16.6965293884,28.3614616394],"type":"Point"}
}