{
  "type": "Feature",
  "properties": {
    "addr:full":"Carrer de Can Noguera, 11 Poligon Barcelones Barcelona 08630",
    "addr:housenumber":"11",
    "addr:postcode":"08630",
    "addr:street":"Carrer De Can Noguera",
    "iso:country":"ES",
    "sg:address":"Carrer de Can Noguera, 11",
    "sg:city":"Poligon Barcelones",
    "sg:orig_category":"Fabricaci\u00d3n, Venta, Instalaci\u00d3n De R\u00d3tulos, De R\u00d3tulos Luminosos",
    "sg:phone":"+34 937 72 19 54",
    "sg:postcode":"08630",
    "sg:province":"Barcelona",
    "wof:name":"Nou Retol S.l.",
    "wof:placetype":"venue"
},
  "geometry": {"coordinates":[1.9044500589,41.5177497864],"type":"Point"}
}