{
  "type": "Feature",
  "properties": {
    "iso:country":"ES",
    "sg:address":"Plaz Enrique Granados, 5",
    "sg:city":"Valencia",
    "sg:orig_category":"M\u00c9dicos: An\u00c1lisis Cl\u00cdnicos",
    "sg:phone":"+34 963 77 97 11",
    "sg:postcode":"46018",
    "sg:province":"Valencia",
    "wof:name":"Clinica El Mar S.l.",
    "wof:placetype":"venue"
},
  "geometry": {"coordinates":[-0.3952290118,39.4625015259],"type":"Point"}
}