{
  "type": "Feature",
  "properties": {
    "addr:full":"Plaz San Juan, 14 Valladolid Valladolid 47002",
    "addr:housenumber":"14",
    "addr:postcode":"47002",
    "addr:street":"Plaz San Juan",
    "iso:country":"ES",
    "sg:address":"Plaz San Juan, 14",
    "sg:city":"Valladolid",
    "sg:orig_category":"Abogados",
    "sg:phone":"+34 983 39 25 84",
    "sg:postcode":"47002",
    "sg:province":"Valladolid",
    "wof:name":"Pose Garcia Miguel Angel",
    "wof:placetype":"venue"
},
  "geometry": {"coordinates":[-4.7177348137,41.6506881714],"type":"Point"}
}