{
  "type": "Feature",
  "properties": {
    "addr:full":"Avda Jose Antonio, 45 Pe\u00f1iscola Castell\u00f3n 12598",
    "addr:housenumber":"45",
    "addr:postcode":"12598",
    "addr:street":"Avda Jose Antonio;Castello\u0301N",
    "iso:country":"ES",
    "sg:address":"Avda Jose Antonio, 45",
    "sg:city":"Pe\u00f1iscola",
    "sg:orig_category":"Caf\u00c9s, Bares, Cervecer\u00cdas",
    "sg:phone":"+34 964 48 98 23",
    "sg:postcode":"12598",
    "sg:province":"Castell\u00f3n",
    "wof:name":"Ayza Roca Vicenta",
    "wof:placetype":"venue"
},
  "geometry": {"coordinates":[0.4006190002,40.3590240479],"type":"Point"}
}