{
  "type": "Feature",
  "properties": {
    "iso:country":"ES",
    "sg:address":"Urb Recreo (el), 70",
    "sg:city":"Tarifa",
    "sg:orig_category":"Producci\u00d3n, Distribuci\u00d3n De Gas Butano Y Propano",
    "sg:phone":"+34 956 68 22 36",
    "sg:postcode":"11380",
    "sg:province":"C\u00e1diz",
    "wof:name":"Gas Plus S.l.",
    "wof:placetype":"venue"
},
  "geometry": {"coordinates":[-5.6030340195,36.0151596069],"type":"Point"}
}