{
  "type": "Feature",
  "properties": {
    "addr:full":"Plaz Virgen Del Carmen, S/n Isleta Del Moro Almer\u00eda 04118",
    "addr:housenumber":"s / n",
    "addr:postcode":"04118",
    "addr:street":"Plaz Virgen Del Carmen",
    "iso:country":"ES",
    "sg:address":"Plaz Virgen Del Carmen, S/n",
    "sg:city":"Isleta Del Moro",
    "sg:orig_category":"Aguas (distribuci\u00d3n, Servicios)",
    "sg:phone":"+34 950 38 98 21",
    "sg:postcode":"04118",
    "sg:province":"Almer\u00eda",
    "wof:name":"Aqualia Gestion Integral Del Agua S.a.",
    "wof:placetype":"venue"
},
  "geometry": {"coordinates":[-2.4679217339,36.8401641846],"type":"Point"}
}