{
  "type": "Feature",
  "properties": {
    "addr:full":"Av. Constitucion, S/n \u00d1ora Murcia 30830",
    "addr:postcode":"30830",
    "addr:street":"Av. Constitucion S / N",
    "iso:country":"ES",
    "sg:address":"Av. Constitucion, S/n",
    "sg:city":"\u00d1ora",
    "sg:orig_category":"Cajas Para Embalar",
    "sg:phone":"+34 968 80 28 66",
    "sg:postcode":"30830",
    "sg:province":"Murcia",
    "sg:website":"www.cajamar.es",
    "wof:name":"Cajamar",
    "wof:placetype":"venue"
},
  "geometry": {"coordinates":[-1.1951429844,37.9897003174],"type":"Point"}
}