{
  "type": "Feature",
  "properties": {
    "iso:country":"ES",
    "sg:address":"Carrer de Montserrat, 41",
    "sg:city":"Mataro",
    "sg:orig_category":"Abogados",
    "sg:phone":"+34 937 41 01 21",
    "sg:postcode":"08302",
    "sg:province":"Barcelona",
    "wof:name":"Costilla Merino Jorge",
    "wof:placetype":"venue"
},
  "geometry": {"coordinates":[2.443187952,41.5370864868],"type":"Point"}
}