{
  "type": "Feature",
  "properties": {
    "iso:country":"ES",
    "sg:address":"Cami Cami Del Bony - Poligono Industrial, S/n",
    "sg:city":"Catarroja",
    "sg:orig_category":"Tapicer\u00cdas",
    "sg:phone":"+34 961 27 00 06",
    "sg:postcode":"46470",
    "sg:province":"Valencia",
    "wof:name":"Tapicerias Ruiz S.l.",
    "wof:placetype":"venue"
},
  "geometry": {"coordinates":[-0.414440006,39.3972015381],"type":"Point"}
}