{
  "type": "Feature",
  "properties": {
    "addr:full":"Calle de Portal De Gamarra, 60 Vitoria-gasteiz \u00c1lava 01013",
    "addr:housenumber":"60",
    "addr:postcode":"01013",
    "addr:street":"Calle De Portal De Gamarra",
    "iso:country":"ES",
    "sg:address":"Calle de Portal De Gamarra, 60",
    "sg:city":"Vitoria-gasteiz",
    "sg:orig_category":"Embalajes",
    "sg:phone":"+34 945 26 94 21",
    "sg:postcode":"01013",
    "sg:province":"\u00c1lava",
    "wof:name":"Embaleser S.l.",
    "wof:placetype":"venue"
},
  "geometry": {"coordinates":[-2.6576840878,42.8735733032],"type":"Point"}
}