{
  "type": "Feature",
  "properties": {
    "addr:full":"Gali\u00f1ans, 10 Lores Pontevedra 36969",
    "addr:housenumber":"10",
    "addr:postcode":"36969",
    "addr:street":"Galin\u0303Ans",
    "iso:country":"ES",
    "sg:address":"Gali\u00f1ans, 10",
    "sg:city":"Lores",
    "sg:orig_category":"Productores Recolectores, Venta Directa De Vinos",
    "sg:phone":"+34 986 74 70 46",
    "sg:postcode":"36969",
    "sg:province":"Pontevedra",
    "wof:name":"Bodegas Gerardo Mendez S.l.",
    "wof:placetype":"venue"
},
  "geometry": {"coordinates":[-8.8211641312,42.4239959717],"type":"Point"}
}