{
  "type": "Feature",
  "properties": {
    "addr:full":"Calle de Gran Via, 38 Blanca Murcia 30540",
    "addr:housenumber":"38",
    "addr:postcode":"30540",
    "addr:street":"Calle De Gran Via",
    "iso:country":"ES",
    "sg:address":"Calle de Gran Via, 38",
    "sg:city":"Blanca",
    "sg:orig_category":"Farmacias",
    "sg:phone":"+34 968 77 83 48",
    "sg:postcode":"30540",
    "sg:province":"Murcia",
    "wof:name":"Gonzalez Jordan Josefa",
    "wof:placetype":"venue"
},
  "geometry": {"coordinates":[-1.372549057,38.1792373657],"type":"Point"}
}