{
  "type": "Feature",
  "properties": {
    "iso:country":"ES",
    "sg:address":"Rio Mula(p Ind), 1",
    "sg:city":"Bullas",
    "sg:orig_category":"Plomeros",
    "sg:phone":"+34 968 65 41 24",
    "sg:postcode":"30180",
    "sg:province":"Murcia",
    "wof:name":"Juan Enrique Sandoval S.l",
    "wof:placetype":"venue"
},
  "geometry": {"coordinates":[-1.6694370508,38.0509681702],"type":"Point"}
}