{
  "type": "Feature",
  "properties": {
    "addr:full":"Ctr El Bonillo, 109 Socuellamos Ciudad Real 13630",
    "addr:housenumber":"109",
    "addr:postcode":"13630",
    "addr:street":"El Bonillo",
    "iso:country":"ES",
    "sg:address":"Ctr El Bonillo, 109",
    "sg:city":"Socuellamos",
    "sg:orig_category":"Chapister\u00cda",
    "sg:phone":"+34 926 50 04 38",
    "sg:postcode":"13630",
    "sg:province":"Ciudad Real",
    "wof:name":"Reparauto Sport S.l.",
    "wof:placetype":"venue"
},
  "geometry": {"coordinates":[-2.7867488861,39.2787971497],"type":"Point"}
}