{
  "type": "Feature",
  "properties": {
    "iso:country":"ES",
    "sg:address":"Calle de Ansar, 11",
    "sg:city":"Madrid",
    "sg:orig_category":"Molduras, Junquillos, Listones Y Molduras Perforadas",
    "sg:phone":"+34 914 64 12 81",
    "sg:postcode":"28047",
    "sg:province":"Madrid",
    "wof:name":"Millan Guallar Elisea",
    "wof:placetype":"venue"
},
  "geometry": {"coordinates":[-3.7396268845,40.4038887024],"type":"Point"}
}