{
  "type": "Feature",
  "properties": {
    "addr:full":"Alam Antso Estegiz Zumardia, 11 Durango Vizcaya 48200",
    "addr:housenumber":"11",
    "addr:postcode":"48200",
    "addr:street":"Alam Antso Estegiz Zumardia",
    "iso:country":"ES",
    "sg:address":"Alam Antso Estegiz Zumardia, 11",
    "sg:city":"Durango",
    "sg:orig_category":"Ense\u00d1anza Variada",
    "sg:phone":"+34 946 21 60 19",
    "sg:postcode":"48200",
    "sg:province":"Vizcaya",
    "wof:name":"Sasoia Educacion Para La Salud Y Prevencion De Drogodependencias S.l.",
    "wof:placetype":"venue"
},
  "geometry": {"coordinates":[-2.6287600994,43.1662101746],"type":"Point"}
}