{
  "type": "Feature",
  "properties": {
    "addr:full":"Calle de Nu\u00d1ez De Balboa, 98 Madrid Madrid 28006",
    "addr:housenumber":"98",
    "addr:postcode":"madrid;28006",
    "addr:street":"Calle De Nun\u0303Ez De Balboa",
    "iso:country":"ES",
    "sg:address":"Calle de Nu\u00d1ez De Balboa, 98",
    "sg:city":"Madrid",
    "sg:orig_category":"Fabricaci\u00d3n, Venta De Cuadros, Accesorios Para Enmarcar",
    "sg:phone":"+34 915 61 92 54",
    "sg:postcode":"28006",
    "sg:province":"Madrid",
    "wof:name":"Montejano Alvarez Rocio",
    "wof:placetype":"venue"
},
  "geometry": {"coordinates":[-3.6818289757,40.4344482422],"type":"Point"}
}