{
  "type": "Feature",
  "properties": {
    "addr:full":"Carr Duc De Lliria (del), 132 Lliria Valencia 46160",
    "addr:housenumber":"132",
    "addr:postcode":"46160",
    "addr:street":"Carr Duc De Lliria Del",
    "iso:country":"ES",
    "sg:address":"Carr Duc De Lliria (del), 132",
    "sg:city":"Lliria",
    "sg:orig_category":"Distribuci\u00d3n De Petr\u00d3leo Y Derivados",
    "sg:phone":"+34 962 78 11 32",
    "sg:postcode":"46160",
    "sg:province":"Valencia",
    "wof:name":"Gasolinera San Miguel S.l.",
    "wof:placetype":"venue"
},
  "geometry": {"coordinates":[-0.602026403,39.6297302246],"type":"Point"}
}