{
  "type": "Feature",
  "properties": {
    "iso:country":"ES",
    "sg:address":"Carrer de Son Muntaner, 2",
    "sg:city":"Vileta -son Rapinya",
    "sg:orig_category":"Inmobiliaria (agencias)",
    "sg:phone":"+34 971 79 86 92",
    "sg:postcode":"07013",
    "sg:province":"Islas Baleares",
    "wof:name":"Promocions Calma Blanca S.l.",
    "wof:placetype":"venue"
},
  "geometry": {"coordinates":[2.6169118881,39.5862884521],"type":"Point"}
}