{
  "type": "Feature",
  "properties": {
    "addr:full":"Calle de Ramon Y Cajal, 2 Coria C\u00e1ceres 10800",
    "addr:housenumber":"2",
    "addr:postcode":"10800",
    "addr:street":"Calle De Ramon Y Cajal;Ca\u0301Ceres",
    "iso:country":"ES",
    "sg:address":"Calle de Ramon Y Cajal, 2",
    "sg:city":"Coria",
    "sg:orig_category":"Perfumer\u00cda (al Por Menor)",
    "sg:phone":"+34 927 50 31 42",
    "sg:postcode":"10800",
    "sg:province":"C\u00e1ceres",
    "wof:name":"Hernandez Montero Yolanda",
    "wof:placetype":"venue"
},
  "geometry": {"coordinates":[-6.5371670723,39.9869880676],"type":"Point"}
}