{
  "type": "Feature",
  "properties": {
    "iso:country":"ES",
    "sg:address":"Pg Florida, 28",
    "sg:city":"Santa Perpetua De Mogoda",
    "sg:orig_category":"Colchones (fabricaci\u00d3n, Al Por Mayor, Al Por Menor)",
    "sg:phone":"+34 935 60 33 99",
    "sg:postcode":"08130",
    "sg:province":"Barcelona",
    "wof:name":"Soley Olivera Francesc",
    "wof:placetype":"venue"
},
  "geometry": {"coordinates":[2.1844100952,41.531879425],"type":"Point"}
}