{
  "type": "Feature",
  "properties": {
    "addr:full":"Cami Hort Sirera, 5 Barbera Conca Tarragona 43422",
    "addr:housenumber":"5",
    "addr:postcode":"43422",
    "addr:street":"Barbera Conca",
    "iso:country":"ES",
    "sg:address":"Cami Hort Sirera, 5",
    "sg:city":"Barbera Conca",
    "sg:orig_category":"Creaci\u00d3n De Sitios, Hosting Internet",
    "sg:phone":"+34 977 88 72 31",
    "sg:postcode":"43422",
    "sg:province":"Tarragona",
    "sg:website":"www.interfacilnet.com",
    "wof:name":"Fabregas Iba\u00f1ez Jose Maria",
    "wof:placetype":"venue"
},
  "geometry": {"coordinates":[1.2277359962,41.4105987549],"type":"Point"}
}