{
  "type": "Feature",
  "properties": {
    "iso:country":"ES",
    "sg:address":"Raval Coll Arbo\u00e7, 4",
    "sg:city":"S. Salvador Guardiola",
    "sg:orig_category":"Cables Y Hilos El\u00c9ctricos (fabricaci\u00d3n, Al Por Mayor)",
    "sg:phone":"+34 938 35 80 44",
    "sg:postcode":"08253",
    "sg:province":"Barcelona",
    "wof:name":"Trenats Guardiola S.l.",
    "wof:placetype":"venue"
},
  "geometry": {"coordinates":[1.7656999826,41.6832809448],"type":"Point"}
}