{
  "type": "Feature",
  "properties": {
    "iso:country":"ES",
    "sg:address":"Calle de Doctor Espina, 18",
    "sg:city":"Madrid",
    "sg:orig_category":"Farmacias",
    "sg:phone":"+34 914 71 57 51",
    "sg:postcode":"28019",
    "sg:province":"Madrid",
    "wof:name":"Martin De Hijas Martin De Hijas Concepcion",
    "wof:placetype":"venue"
},
  "geometry": {"coordinates":[-3.727855444,40.3895378113],"type":"Point"}
}