{
  "type": "Feature",
  "properties": {
    "addr:full":"Ctra Vic, 61 Manresa Barcelona 08241",
    "addr:housenumber":"61",
    "addr:postcode":"08241",
    "addr:street":"Ctra Vic",
    "iso:country":"ES",
    "sg:address":"Ctra Vic, 61",
    "sg:city":"Manresa",
    "sg:orig_category":"Inmobiliaria (agencias)",
    "sg:phone":"+34 938 75 72 30",
    "sg:postcode":"08241",
    "sg:province":"Barcelona",
    "wof:name":"Sol-nou S.l.",
    "wof:placetype":"venue"
},
  "geometry": {"coordinates":[1.8283480406,41.7281112671],"type":"Point"}
}