{
  "type": "Feature",
  "properties": {
    "iso:country":"ES",
    "sg:address":"Calle de Pedro Coca, 85",
    "sg:city":"Albacete",
    "sg:orig_category":"Molduras, Junquillos, Listones Y Molduras Perforadas",
    "sg:phone":"+34 967 51 19 59",
    "sg:postcode":"02003",
    "sg:province":"Albacete",
    "wof:name":"Rico Ruiz Ricardo",
    "wof:placetype":"venue"
},
  "geometry": {"coordinates":[-1.8650250435,38.9882736206],"type":"Point"}
}