{
  "type": "Feature",
  "properties": {
    "addr:full":"Pol Ind Sta Ana, 12 Guardamar Segura Alicante 03140",
    "addr:housenumber":"12",
    "addr:postcode":"03140",
    "addr:street":"Sta Ana",
    "iso:country":"ES",
    "sg:address":"Pol Ind Sta Ana, 12",
    "sg:city":"Guardamar Segura",
    "sg:orig_category":"Agentes, Concesionarios Y Sucursales De Veh\u00cdculos",
    "sg:phone":"+34 966 72 64 46",
    "sg:postcode":"03140",
    "sg:province":"Alicante",
    "wof:name":"Jumacar Autos S.l",
    "wof:placetype":"venue"
},
  "geometry": {"coordinates":[-0.6540290117,38.086681366],"type":"Point"}
}