{
  "type": "Feature",
  "properties": {
    "addr:full":"Carrer de Escipio, 17 Barcelona Barcelona 08023",
    "addr:housenumber":"17",
    "addr:postcode":"08023",
    "addr:street":"Carrer De Escipio",
    "iso:country":"ES",
    "sg:address":"Carrer de Escipio, 17",
    "sg:city":"Barcelona",
    "sg:orig_category":"Asilos De Ancianos. Centros Privados",
    "sg:phone":"+34 934 17 05 82",
    "sg:postcode":"08023",
    "sg:province":"Barcelona",
    "wof:name":"Residencia De Ancianos San Miguel Arcangel S. A.",
    "wof:placetype":"venue"
},
  "geometry": {"coordinates":[2.1462609768,41.4076118469],"type":"Point"}
}