{
  "type": "Feature",
  "properties": {
    "addr:full":"Pol Ind Tartessos, 86 Huelva Huelva 21006",
    "addr:housenumber":"86",
    "addr:postcode":"21006",
    "addr:street":"Tartessos",
    "iso:country":"ES",
    "sg:address":"Pol Ind Tartessos, 86",
    "sg:city":"Huelva",
    "sg:orig_category":"Empresas De Carpinter\u00cda De Madera",
    "sg:phone":"+34 959 35 61 94",
    "sg:postcode":"21006",
    "sg:province":"Huelva",
    "wof:name":"Pelaez Raposo Alfonso",
    "wof:placetype":"venue"
},
  "geometry": {"coordinates":[-6.9495940208,37.256313324],"type":"Point"}
}