{
  "type": "Feature",
  "properties": {
    "iso:country":"ES",
    "sg:address":"Calle de Yuncos, 33",
    "sg:city":"Estacion",
    "sg:orig_category":"Centros Empresariales",
    "sg:phone":"+34 925 54 50 84",
    "sg:postcode":"45220",
    "sg:province":"Toledo",
    "wof:name":"Eseisa Audiovisuales",
    "wof:placetype":"venue"
},
  "geometry": {"coordinates":[-3.8059339523,40.1223945618],"type":"Point"}
}