{
  "type": "Feature",
  "properties": {
    "iso:country":"ES",
    "sg:address":"Rua Zamora, 7",
    "sg:city":"Vigo",
    "sg:orig_category":"Electromec\u00c1nica",
    "sg:phone":"+34 986 41 47 93",
    "sg:postcode":"36203",
    "sg:province":"Pontevedra",
    "wof:name":"Romero Dominguez Jaime",
    "wof:placetype":"venue"
},
  "geometry": {"coordinates":[-8.7207546234,42.2279281616],"type":"Point"}
}