{
  "type": "Feature",
  "properties": {
    "iso:country":"ES",
    "sg:address":"Carrer de Rios Rosas, 44",
    "sg:city":"Barcelona",
    "sg:orig_category":"Tapicer\u00cdas",
    "sg:phone":"+34 932 11 48 06",
    "sg:postcode":"08006",
    "sg:province":"Barcelona",
    "wof:name":"Fortuna Garrido Antonio",
    "wof:placetype":"venue"
},
  "geometry": {"coordinates":[2.1428360939,41.4045448303],"type":"Point"}
}