{
  "type": "Feature",
  "properties": {
    "iso:country":"ES",
    "sg:address":"Carrer de Convent, 19",
    "sg:city":"Cocentaina",
    "sg:orig_category":"Asociaciones Y Clubs Deportivos",
    "sg:phone":"+34 965 59 00 49",
    "sg:postcode":"03820",
    "sg:province":"Alicante",
    "wof:name":"Llinares Colomina Mario",
    "wof:placetype":"venue"
},
  "geometry": {"coordinates":[-0.4409579933,38.7404708862],"type":"Point"}
}