{
  "type": "Feature",
  "properties": {
    "addr:full":"Calle de Cordoba, 2 Almodovar Del Rio C\u00f3rdoba 14720",
    "addr:housenumber":"2",
    "addr:postcode":"14720",
    "addr:street":"Calle De Cordoba;Co\u0301Rdoba",
    "iso:country":"ES",
    "sg:address":"Calle de Cordoba, 2",
    "sg:city":"Almodovar Del Rio",
    "sg:orig_category":"Electricidad: Instaladores",
    "sg:phone":"+34 957 71 35 82",
    "sg:postcode":"14720",
    "sg:province":"C\u00f3rdoba",
    "wof:name":"Guzman Camacho Jose",
    "wof:placetype":"venue"
},
  "geometry": {"coordinates":[-5.0203967094,37.8102226257],"type":"Point"}
}