{
  "type": "Feature",
  "properties": {
    "iso:country":"ES",
    "sg:address":"Monasterio De La Oliva, 1",
    "sg:city":"Iru\u00f1a",
    "sg:orig_category":"Procuradores",
    "sg:phone":"+34 948 26 19 95",
    "sg:postcode":"31011",
    "sg:province":"Navarra",
    "wof:name":"Lopez Pardo Maria Jesus",
    "wof:placetype":"venue"
},
  "geometry": {"coordinates":[-1.6566618681,42.816192627],"type":"Point"}
}