{
  "type": "Feature",
  "properties": {
    "addr:full":"Carr Pi I Margall, 28 Lleida Lleida 25004",
    "addr:housenumber":"28",
    "addr:postcode":"25004",
    "addr:street":"Carr Pi I Margall",
    "iso:country":"ES",
    "sg:address":"Carr Pi I Margall, 28",
    "sg:city":"Lleida",
    "sg:orig_category":"Peluquer\u00cdas, Peluquer\u00cda Mixta",
    "sg:phone":"+34 973 23 42 65",
    "sg:postcode":"25004",
    "sg:province":"Lleida",
    "wof:name":"Montero Melero Elena",
    "wof:placetype":"venue"
},
  "geometry": {"coordinates":[0.6279969811,41.621055603],"type":"Point"}
}