{
  "type": "Feature",
  "properties": {
    "addr:full":"Av Catalunya, 2 Soses Lleida 25181",
    "addr:housenumber":"2",
    "addr:postcode":"25181",
    "addr:street":"Av Catalunya",
    "iso:country":"ES",
    "sg:address":"Av Catalunya, 2",
    "sg:city":"Soses",
    "sg:orig_category":"Frutas Y Legumbres Frescas (al Por Mayor)",
    "sg:phone":"+34 973 79 74 71",
    "sg:postcode":"25181",
    "sg:province":"Lleida",
    "wof:name":"Peregrin Martinez Jose",
    "wof:placetype":"venue"
},
  "geometry": {"coordinates":[0.4877789915,41.5351524353],"type":"Point"}
}