{
  "type": "Feature",
  "properties": {
    "iso:country":"ES",
    "sg:address":"Calle de Valle Guadalix (del), 12",
    "sg:city":"San Sebastian De Los Reyes",
    "sg:orig_category":"Rectificaci\u00d3n, Mecanizado, Fresado",
    "sg:phone":"+34 916 52 83 11",
    "sg:postcode":"28700",
    "sg:province":"Madrid",
    "wof:name":"Rectificados Josima S.r.l",
    "wof:placetype":"venue"
},
  "geometry": {"coordinates":[-3.6249120235,40.5554275513],"type":"Point"}
}