{
  "type": "Feature",
  "properties": {
    "iso:country":"ES",
    "sg:address":"Calle de Erribera, 4",
    "sg:city":"Zumaia",
    "sg:orig_category":"Art\u00cdculos De Regalo (al Por Menor)",
    "sg:phone":"+34 943 86 23 98",
    "sg:postcode":"20750",
    "sg:province":"Guip\u00f9zcoa",
    "wof:name":"Isasti Amallobieta Maria Jose",
    "wof:placetype":"venue"
},
  "geometry": {"coordinates":[-2.2577044964,43.2960700989],"type":"Point"}
}