{
  "type": "Feature",
  "properties": {
    "iso:country":"ES",
    "sg:address":"Praia De Beluso, S/n",
    "sg:city":"Praia De Beluso",
    "sg:orig_category":"Congelados: Productos Alimentarios (fabricaci\u00d3n, Al Por Mayor)",
    "sg:phone":"+34 986 32 07 13",
    "sg:postcode":"36939",
    "sg:province":"Pontevedra",
    "wof:name":"Frigorificos De Bueu S. L.",
    "wof:placetype":"venue"
},
  "geometry": {"coordinates":[-8.7823858261,42.3033218384],"type":"Point"}
}