{
  "type": "Feature",
  "properties": {
    "addr:full":"Av S'agaro, 3 Platja D'aro Girona 17250",
    "addr:housenumber":"3",
    "addr:postcode":"17250",
    "addr:street":"Av S'Agaro",
    "iso:country":"ES",
    "sg:address":"Av S'agaro, 3",
    "sg:city":"Platja D'aro",
    "sg:orig_category":"Venta, Instalaci\u00d3n De Cocinas",
    "sg:phone":"+34 972 81 72 09",
    "sg:postcode":"17250",
    "sg:province":"Girona",
    "wof:name":"Olivera Brugat Jose",
    "wof:placetype":"venue"
},
  "geometry": {"coordinates":[2.8163490295,41.9701499939],"type":"Point"}
}