{
  "type": "Feature",
  "properties": {
    "iso:country":"ES",
    "sg:address":"Carrer de Carles Buhigas, S/n",
    "sg:city":"Can Castells",
    "sg:orig_category":"Comercio, Reparaci\u00d3n De Motocicletas, Bicicletas Y Piezas Sueltas",
    "sg:phone":"+34 938 49 35 04",
    "sg:postcode":"08420",
    "sg:province":"Barcelona",
    "wof:name":"Motoplastic S. A.",
    "wof:placetype":"venue"
},
  "geometry": {"coordinates":[2.2783401012,41.6220207214],"type":"Point"}
}