{
  "type": "Feature",
  "properties": {
    "iso:country":"ES",
    "sg:address":"Calle de San Atilano, 5",
    "sg:city":"Zamora",
    "sg:orig_category":"Caf\u00c9s, Bares, Cervecer\u00cdas",
    "sg:phone":"+34 980 53 23 30",
    "sg:postcode":"49003",
    "sg:province":"Zamora",
    "wof:name":"Hosteleria Zamorana La Alcazaba S.l.",
    "wof:placetype":"venue"
},
  "geometry": {"coordinates":[-5.7436709404,41.503993988],"type":"Point"}
}