{
  "type": "Feature",
  "properties": {
    "iso:country":"ES",
    "sg:address":"Pg Maritim, 11",
    "sg:city":"Estartit",
    "sg:orig_category":"Deportes Diversos",
    "sg:phone":"+34 972 75 17 68",
    "sg:postcode":"17258",
    "sg:province":"Girona",
    "sg:website":"www.unisub.es",
    "wof:name":"Unisub Estartit S.l.",
    "wof:placetype":"venue"
},
  "geometry": {"coordinates":[3.2089619637,42.0533561707],"type":"Point"}
}