{
  "type": "Feature",
  "properties": {
    "addr:full":"Calle de Camarena, 251 Madrid Madrid 28047",
    "addr:housenumber":"251",
    "addr:postcode":"28047",
    "addr:street":"Calle De Camarena",
    "iso:country":"ES",
    "sg:address":"Calle de Camarena, 251",
    "sg:city":"Madrid",
    "sg:orig_category":"Peluqueros: De Se\u00d1oras",
    "sg:phone":"+34 917 19 34 59",
    "sg:postcode":"28047",
    "sg:province":"Madrid",
    "wof:name":"De Tena Moreno Maria Del Pilar",
    "wof:placetype":"venue"
},
  "geometry": {"coordinates":[-3.7561619282,40.3876838684],"type":"Point"}
}