{
  "type": "Feature",
  "properties": {
    "addr:full":"Avda Bilbao, 159 Torrelavega Cantabria 39300",
    "addr:housenumber":"159",
    "addr:postcode":"39300",
    "addr:street":"Avda Bilbao",
    "iso:country":"ES",
    "sg:address":"Avda Bilbao, 159",
    "sg:city":"Torrelavega",
    "sg:orig_category":"Asociaciones Y Clubs Deportivos",
    "sg:phone":"+34 942 88 17 99",
    "sg:postcode":"39300",
    "sg:province":"Cantabria",
    "wof:name":"Dobra S. L.",
    "wof:placetype":"venue"
},
  "geometry": {"coordinates":[-4.039208889,43.3456115723],"type":"Point"}
}