{
  "type": "Feature",
  "properties": {
    "addr:full":"Carrer de Pont, 33 Manlleu Barcelona 08560",
    "addr:housenumber":"33",
    "addr:postcode":"08560",
    "addr:street":"Carrer De Pont",
    "iso:country":"ES",
    "sg:address":"Carrer de Pont, 33",
    "sg:city":"Manlleu",
    "sg:orig_category":"Quincaller\u00cda (fabricaci\u00d3n)",
    "sg:phone":"+34 938 50 62 00",
    "sg:postcode":"08560",
    "sg:province":"Barcelona",
    "wof:name":"Suministros Industriales Rifa S. A.",
    "wof:placetype":"venue"
},
  "geometry": {"coordinates":[2.2851829529,41.9993667603],"type":"Point"}
}