{
  "type": "Feature",
  "properties": {
    "addr:full":"Calle de Cadenas, 8 Espera C\u00e1diz 11648",
    "addr:housenumber":"8",
    "addr:postcode":"11648",
    "addr:street":"Calle De Cadenas",
    "iso:country":"ES",
    "sg:address":"Calle de Cadenas, 8",
    "sg:city":"Espera",
    "sg:orig_category":"Aceites Y Grasas Alimentarias (fabricaci\u00d3n, Al Por Mayor)",
    "sg:phone":"+34 956 72 00 69",
    "sg:postcode":"11648",
    "sg:province":"C\u00e1diz",
    "wof:name":"Vega Garrido Vicente",
    "wof:placetype":"venue"
},
  "geometry": {"coordinates":[-5.8069729805,36.8721656799],"type":"Point"}
}