{
  "type": "Feature",
  "properties": {
    "addr:full":"Ctra Norte, 9 Ba\u00f1aderos-san Andres Las Palmas 35414",
    "addr:housenumber":"9",
    "addr:postcode":"35414",
    "addr:street":"Ctra Norte;Andres Las",
    "iso:country":"ES",
    "sg:address":"Ctra Norte, 9",
    "sg:city":"Ba\u00f1aderos-san Andres",
    "sg:orig_category":"Promotores Constructores",
    "sg:phone":"+34 928 62 63 77",
    "sg:postcode":"35414",
    "sg:province":"Las Palmas",
    "wof:name":"General Traving Sl.",
    "wof:placetype":"venue"
},
  "geometry": {"coordinates":[-15.5525026321,28.145488739],"type":"Point"}
}