{
  "type": "Feature",
  "properties": {
    "addr:full":"Rua Vigo, 34 Sanxenxo Pontevedra 36960",
    "addr:housenumber":"34",
    "addr:postcode":"36960",
    "addr:street":"Rua Vigo",
    "iso:country":"ES",
    "sg:address":"Rua Vigo, 34",
    "sg:city":"Sanxenxo",
    "sg:orig_category":"Inmobiliaria (agencias)",
    "sg:phone":"+34 986 72 35 66",
    "sg:postcode":"36960",
    "sg:province":"Pontevedra",
    "wof:name":"Rdp 98 S.l.",
    "wof:placetype":"venue"
},
  "geometry": {"coordinates":[-8.8137025833,42.4016952515],"type":"Point"}
}