{
  "type": "Feature",
  "properties": {
    "addr:full":"El Pedroso, S/n Cabra C\u00f3rdoba 14940",
    "addr:postcode":"14940",
    "addr:street":"El Pedroso S / N",
    "iso:country":"ES",
    "sg:address":"El Pedroso, S/n",
    "sg:city":"Cabra",
    "sg:orig_category":"Contenedores (mercanc\u00cdas)",
    "sg:phone":"+34 957 52 49 99",
    "sg:postcode":"14940",
    "sg:province":"C\u00f3rdoba",
    "wof:name":"Egaroper S.l.",
    "wof:placetype":"venue"
},
  "geometry": {"coordinates":[-4.438999176,37.4669494629],"type":"Point"}
}