{
  "type": "Feature",
  "properties": {
    "iso:country":"ES",
    "sg:address":"Avda Hermanos Fernandez Perdigon, 1",
    "sg:city":"Puerto Cruz",
    "sg:orig_category":"Inmobiliaria (agencias)",
    "sg:phone":"+34 922 38 69 41",
    "sg:postcode":"38400",
    "sg:province":"Santa Cruz De Tenerife",
    "wof:name":"Mickel Lopez Alfredo Romualdo",
    "wof:placetype":"venue"
},
  "geometry": {"coordinates":[-16.5473842621,28.4141807556],"type":"Point"}
}