{
  "type": "Feature",
  "properties": {
    "iso:country":"ES",
    "sg:address":"Carrer de Robrenyo, 76",
    "sg:city":"Barcelona",
    "sg:orig_category":"\u00d3ptica: Instrumentos (fabricaci\u00d3n)",
    "sg:phone":"+34 934 90 92 37",
    "sg:postcode":"08014",
    "sg:province":"Barcelona",
    "wof:name":"Chistian Optica S. A.",
    "wof:placetype":"venue"
},
  "geometry": {"coordinates":[2.1398179531,41.3822097778],"type":"Point"}
}