{
  "type": "Feature",
  "properties": {
    "iso:country":"ES",
    "sg:address":"Avda Playas (las), 73",
    "sg:city":"Puerto Del Carmen",
    "sg:orig_category":"Cl\u00cdnicas M\u00c9dicas",
    "sg:phone":"+34 928 51 40 77",
    "sg:postcode":"35510",
    "sg:province":"Las Palmas",
    "wof:name":"Ceasme Lanzarote S.l.",
    "wof:placetype":"venue"
},
  "geometry": {"coordinates":[-13.6543092728,28.9192905426],"type":"Point"}
}