{
  "type": "Feature",
  "properties": {
    "addr:full":"Avda Pablo Iglesias, 10 Errenteria Guip\u00f9zcoa 20100",
    "addr:housenumber":"10",
    "addr:postcode":"20100",
    "addr:street":"Avda Pablo Iglesias;Guipu\u0300Zcoa",
    "iso:country":"ES",
    "sg:address":"Avda Pablo Iglesias, 10",
    "sg:city":"Errenteria",
    "sg:orig_category":"Producci\u00d3n De Abonos Y De Fertilizantes",
    "sg:phone":"+34 943 52 64 44",
    "sg:postcode":"20100",
    "sg:province":"Guip\u00f9zcoa",
    "wof:name":"Garcia Prieto,feliciano",
    "wof:placetype":"venue"
},
  "geometry": {"coordinates":[-1.8994612694,43.3118743896],"type":"Point"}
}