{
  "type": "Feature",
  "properties": {
    "addr:full":"La Linea, 2 Huercal-overa Almer\u00eda 04600",
    "addr:postcode":"04600",
    "addr:street":"Linea;Huercal-Overa Almeri\u0301A",
    "iso:country":"ES",
    "sg:address":"La Linea, 2",
    "sg:city":"Huercal-overa",
    "sg:orig_category":"Muebles, Minoristas",
    "sg:phone":"+34 950 47 03 53",
    "sg:postcode":"04600",
    "sg:province":"Almer\u00eda",
    "wof:name":"Blesa Bonillo Manuel",
    "wof:placetype":"venue"
},
  "geometry": {"coordinates":[-1.9389539957,37.3985977173],"type":"Point"}
}