{
  "type": "Feature",
  "properties": {
    "iso:country":"ES",
    "sg:address":"Carrer de Sant Miquel, 16",
    "sg:city":"Benidorm",
    "sg:orig_category":"Molduras, Junquillos, Listones Y Molduras Perforadas",
    "sg:phone":"+34 965 85 10 75",
    "sg:postcode":"03500",
    "sg:province":"Alicante",
    "wof:name":"Bar Campany",
    "wof:placetype":"venue"
},
  "geometry": {"coordinates":[-0.1306339949,38.5358428955],"type":"Point"}
}