{
  "type": "Feature",
  "properties": {
    "iso:country":"ES",
    "sg:address":"Carrer de Bisbe Lorenzana, 6",
    "sg:city":"Olot",
    "sg:orig_category":"Procuradores",
    "sg:phone":"+34 972 26 60 22",
    "sg:postcode":"17800",
    "sg:province":"Girona",
    "wof:name":"Pascual Agusti Maria Lluisa",
    "wof:placetype":"venue"
},
  "geometry": {"coordinates":[2.4898209572,42.1809234619],"type":"Point"}
}