{
  "type": "Feature",
  "properties": {
    "iso:country":"ES",
    "sg:address":"Plaz Obispo Soldevila, S/n",
    "sg:city":"Cascante",
    "sg:orig_category":"Panader\u00cdas, Panader\u00cdas",
    "sg:phone":"+34 948 85 16 69",
    "sg:postcode":"31520",
    "sg:province":"Navarra",
    "wof:name":"Jimenez Arnede Felipe",
    "wof:placetype":"venue"
},
  "geometry": {"coordinates":[-1.6789289713,41.9988555908],"type":"Point"}
}