{
  "type": "Feature",
  "properties": {
    "addr:full":"Calle de San Francisco, 2 Mogente Valencia 46640",
    "addr:housenumber":"2",
    "addr:postcode":"46640",
    "addr:street":"Calle De San Francisco",
    "iso:country":"ES",
    "sg:address":"Calle de San Francisco, 2",
    "sg:city":"Mogente",
    "sg:orig_category":"Muebles Y Accesorios Para Cocinas Y Cuartos De Ba\u00d1o (al Por Menor)",
    "sg:phone":"+34 962 26 02 00",
    "sg:postcode":"46640",
    "sg:province":"Valencia",
    "wof:name":"Ruiz Alvarado Francisco",
    "wof:placetype":"venue"
},
  "geometry": {"coordinates":[-0.74861902,38.8746604919],"type":"Point"}
}