{
  "type": "Feature",
  "properties": {
    "addr:full":"Cno. Fus, S/n Massanassa Valencia 46470",
    "addr:housenumber":"/ n",
    "addr:postcode":"46470",
    "addr:street":"Fus S",
    "iso:country":"ES",
    "sg:address":"Cno. Fus, S/n",
    "sg:city":"Massanassa",
    "sg:orig_category":"Suministros Y Materiales Industriales",
    "sg:phone":"+34 961 25 30 55",
    "sg:postcode":"46470",
    "sg:province":"Valencia",
    "wof:name":"Tecniman S.a.",
    "wof:placetype":"venue"
},
  "geometry": {"coordinates":[-0.4032689929,39.4032859802],"type":"Point"}
}