{
  "type": "Feature",
  "properties": {
    "addr:full":"Calle de Gran Via, 69 Madrid Madrid 28013",
    "addr:housenumber":"69",
    "addr:postcode":"madrid;28013",
    "addr:street":"Calle De Gran Via",
    "iso:country":"ES",
    "sg:address":"Calle de Gran Via, 69",
    "sg:city":"Madrid",
    "sg:orig_category":"Radiocomunicaciones, Telefon\u00cda M\u00d3vil, Radiomensajer\u00cda: Servicios, Comercializaci\u00d3n",
    "sg:phone":"+34 915 47 02 78",
    "sg:postcode":"28013",
    "sg:province":"Madrid",
    "wof:name":"Lu  Jian",
    "wof:placetype":"venue"
},
  "geometry": {"coordinates":[-3.7103259563,40.4229354858],"type":"Point"}
}