{
  "type": "Feature",
  "properties": {
    "addr:full":"Calle de Iglesia (la), 16 Caldas De Reis Pontevedra 36650",
    "addr:housenumber":"16",
    "addr:postcode":"36650",
    "addr:street":"Calle De Iglesia La",
    "iso:country":"ES",
    "sg:address":"Calle de Iglesia (la), 16",
    "sg:city":"Caldas De Reis",
    "sg:orig_category":"Supermercados Y Hipermercados",
    "sg:phone":"+34 986 54 00 30",
    "sg:postcode":"36650",
    "sg:province":"Pontevedra",
    "wof:name":"Supermercados Clemente S.l",
    "wof:placetype":"venue"
},
  "geometry": {"coordinates":[-8.6427726746,42.604724884],"type":"Point"}
}