{
  "type": "Feature",
  "properties": {
    "addr:full":"Avda Madrid (de), S/n Alamo Madrid 28607",
    "addr:housenumber":"/ n",
    "addr:postcode":"28607",
    "addr:street":"Avda Madrid De S",
    "iso:country":"ES",
    "sg:address":"Avda Madrid (de), S/n",
    "sg:city":"Alamo",
    "sg:orig_category":"Mudanzas",
    "sg:phone":"+34 918 12 13 92",
    "sg:postcode":"28607",
    "sg:province":"Madrid",
    "sg:website":"www.chorpos.com",
    "wof:name":"Chorpos Martinez Domingo",
    "wof:placetype":"venue"
},
  "geometry": {"coordinates":[-3.9855349064,40.2318878174],"type":"Point"}
}