{
  "type": "Feature",
  "properties": {
    "iso:country":"ES",
    "sg:address":"Calle de Manuel Lora Tamayo, 10",
    "sg:city":"Constantina",
    "sg:orig_category":"Reposter\u00cdas",
    "sg:phone":"+34 955 88 07 85",
    "sg:postcode":"41450",
    "sg:province":"Sevilla",
    "wof:name":"Morilla Garcia Rosario",
    "wof:placetype":"venue"
},
  "geometry": {"coordinates":[-5.6184930801,37.875087738],"type":"Point"}
}