{
  "type": "Feature",
  "properties": {
    "iso:country":"ES",
    "sg:address":"Calle de Cerrada, 12",
    "sg:city":"Velles",
    "sg:orig_category":"Panader\u00cdas, Panader\u00cdas",
    "sg:phone":"+34 923 35 43 54",
    "sg:postcode":"37427",
    "sg:province":"Salamanca",
    "wof:name":"Macias Martin Evergislo",
    "wof:placetype":"venue"
},
  "geometry": {"coordinates":[-5.5680408478,41.0727157593],"type":"Point"}
}