{
  "type": "Feature",
  "properties": {
    "addr:full":"Avda Monforte, 20 Chantada Lugo 27500",
    "addr:housenumber":"20",
    "addr:postcode":"27500",
    "addr:street":"Avda Monforte",
    "iso:country":"ES",
    "sg:address":"Avda Monforte, 20",
    "sg:city":"Chantada",
    "sg:orig_category":"Inmobiliaria (agencias)",
    "sg:phone":"+34 982 44 08 87",
    "sg:postcode":"27500",
    "sg:province":"Lugo",
    "wof:name":"Valdes Bautista Mayte",
    "wof:placetype":"venue"
},
  "geometry": {"coordinates":[-7.7590432167,42.6081466675],"type":"Point"}
}