{
  "type": "Feature",
  "properties": {
    "addr:full":"Calle de Jose Melgar, 2 Herrera Sevilla 41567",
    "addr:housenumber":"2",
    "addr:postcode":"41567",
    "addr:street":"Calle De Jose Melgar",
    "iso:country":"ES",
    "sg:address":"Calle de Jose Melgar, 2",
    "sg:city":"Herrera",
    "sg:orig_category":"Transportes Por Carretera: Lotes Completos, Mercanc\u00cdas Diversas",
    "sg:phone":"+34 954 01 36 15",
    "sg:postcode":"41567",
    "sg:province":"Sevilla",
    "wof:name":"Alvarez Fernandez Manuel",
    "wof:placetype":"venue"
},
  "geometry": {"coordinates":[-4.8537392616,37.3640899658],"type":"Point"}
}