{
  "type": "Feature",
  "properties": {
    "addr:full":"Calle de Perez Galdos, 13 Bilbao Vizcaya 48010",
    "addr:housenumber":"13",
    "addr:postcode":"48010",
    "addr:street":"Calle De Perez Galdos",
    "iso:country":"ES",
    "sg:address":"Calle de Perez Galdos, 13",
    "sg:city":"Bilbao",
    "sg:orig_category":"Molduras, Junquillos, Listones Y Molduras Perforadas",
    "sg:phone":"+34 944 21 29 43",
    "sg:postcode":"48010",
    "sg:province":"Vizcaya",
    "wof:name":"Boado Taboada Manuel",
    "wof:placetype":"venue"
},
  "geometry": {"coordinates":[-2.9427130222,43.2589797974],"type":"Point"}
}