{
  "type": "Feature",
  "properties": {
    "addr:full":"Calle de Lucena, 22 Antequera M\u00e1laga 29200",
    "addr:housenumber":"22",
    "addr:postcode":"29200",
    "addr:street":"Calle De Lucena",
    "iso:country":"ES",
    "sg:address":"Calle de Lucena, 22",
    "sg:city":"Antequera",
    "sg:orig_category":"Fotograf\u00cda Y Cine: Aparatos, Pel\u00cdculas Y Accesorios (al Por Menor)",
    "sg:phone":"+34 952 70 51 39",
    "sg:postcode":"29200",
    "sg:province":"M\u00e1laga",
    "wof:name":"Lopez Moreno Juan Antonio",
    "wof:placetype":"venue"
},
  "geometry": {"coordinates":[-4.5599241257,37.0187034607],"type":"Point"}
}