{
  "type": "Feature",
  "properties": {
    "iso:country":"ES",
    "sg:address":"Carrer de Maria Fortuny, 18",
    "sg:city":"Santa Perpetua De Mogoda",
    "sg:orig_category":"Comercio, Reparaci\u00d3n De Bicicletas, De Motocicletas, De Accesorios",
    "sg:phone":"+34 935 60 62 62",
    "sg:postcode":"08130",
    "sg:province":"Barcelona",
    "wof:name":"Soley Garcia Pere",
    "wof:placetype":"venue"
},
  "geometry": {"coordinates":[2.1825931072,41.5335922241],"type":"Point"}
}