{
  "type": "Feature",
  "properties": {
    "iso:country":"ES",
    "sg:address":"Avda Zaragoza, 16",
    "sg:city":"Utebo",
    "sg:orig_category":"Abogados",
    "sg:phone":"+34 976 77 35 99",
    "sg:postcode":"50180",
    "sg:province":"Zaragoza",
    "wof:name":"Guallar Ari\u00f1o Ana Teresa",
    "wof:placetype":"venue"
},
  "geometry": {"coordinates":[-0.9998360276,41.7031135559],"type":"Point"}
}