{
  "type": "Feature",
  "properties": {
    "addr:full":"Calle de Miguel De Cervantes, 20 Rabade Lugo 27370",
    "addr:housenumber":"20",
    "addr:postcode":"27370",
    "addr:street":"Calle De Miguel De Cervantes",
    "iso:country":"ES",
    "sg:address":"Calle de Miguel De Cervantes, 20",
    "sg:city":"Rabade",
    "sg:orig_category":"Empresarios",
    "sg:phone":"+34 982 39 11 27",
    "sg:postcode":"27370",
    "sg:province":"Lugo",
    "wof:name":"Freire Hermida Emilio",
    "wof:placetype":"venue"
},
  "geometry": {"coordinates":[-7.6279511452,43.1205711365],"type":"Point"}
}