{
  "type": "Feature",
  "properties": {
    "addr:full":"Calle de Rabal (el), 20 Hellin Albacete 02400",
    "addr:housenumber":"20",
    "addr:postcode":"02400",
    "addr:street":"Calle De Rabal El",
    "iso:country":"ES",
    "sg:address":"Calle de Rabal (el), 20",
    "sg:city":"Hellin",
    "sg:orig_category":"Caf\u00c9s, Bares, Cervecer\u00cdas",
    "sg:phone":"+34 967 30 14 83",
    "sg:postcode":"02400",
    "sg:province":"Albacete",
    "wof:name":"Mu\u00f1oz Jimenez Rafael",
    "wof:placetype":"venue"
},
  "geometry": {"coordinates":[-1.7017948627,38.5125312805],"type":"Point"}
}