{
  "type": "Feature",
  "properties": {
    "iso:country":"ES",
    "sg:address":"Avda. Andalucia, 9",
    "sg:city":"Torreperogil",
    "sg:orig_category":"Cl\u00cdnicas Dentales",
    "sg:phone":"+34 953 77 80 05",
    "sg:postcode":"23320",
    "sg:province":"Ja\u00e9n",
    "wof:name":"Villar-medina Odontoestomatologia S.l.",
    "wof:placetype":"venue"
},
  "geometry": {"coordinates":[-3.290555954,38.0352745056],"type":"Point"}
}