{
  "type": "Feature",
  "properties": {
    "addr:full":"Calle de Caleruega, 67 Madrid Madrid 28033",
    "addr:housenumber":"67",
    "addr:postcode":"madrid;28033",
    "addr:street":"Calle De Caleruega",
    "iso:country":"ES",
    "sg:address":"Calle de Caleruega, 67",
    "sg:city":"Madrid",
    "sg:classifiers":[
        {
            "category":"Cinema",
            "subcategory":"Movie Theater",
            "type":"Entertainment"
        }
    ],
    "sg:phone":"+34 915 26 81 30",
    "sg:postcode":"28033",
    "sg:province":"Madrid",
    "sg:tags":[
        "salas",
        "de",
        "cine"
    ],
    "wof:name":"Cinebox Exhibicion S.l.",
    "wof:placetype":"venue"
},
  "geometry": {"coordinates":[-3.6706035137,40.4824371338],"type":"Point"}
}