{
  "type": "Feature",
  "properties": {
    "addr:full":"Trav Dalt, 108 Barcelona Barcelona 08024",
    "addr:housenumber":"108",
    "addr:postcode":"08024",
    "addr:street":"Trav Dalt",
    "iso:country":"ES",
    "sg:address":"Trav Dalt, 108",
    "sg:city":"Barcelona",
    "sg:orig_category":"Fotocopias, Reprograf\u00cda",
    "sg:phone":"+34 932 13 12 11",
    "sg:postcode":"08024",
    "sg:province":"Barcelona",
    "wof:name":"Gil Gallart Juan",
    "wof:placetype":"venue"
},
  "geometry": {"coordinates":[2.158205986,41.4113121033],"type":"Point"}
}