{
  "type": "Feature",
  "properties": {
    "iso:country":"ES",
    "sg:address":"Calle de Sevilla, S/n",
    "sg:city":"Jimena Frontera",
    "sg:orig_category":"Alimentaci\u00d3n General (al Por Menor)",
    "sg:phone":"+34 956 64 00 57",
    "sg:postcode":"11330",
    "sg:province":"C\u00e1diz",
    "wof:name":"Jimenez Delgado Maria",
    "wof:placetype":"venue"
},
  "geometry": {"coordinates":[-5.4515137672,36.432346344],"type":"Point"}
}