{
  "type": "Feature",
  "properties": {
    "iso:country":"ES",
    "sg:address":"Carrer de Montfar, 8",
    "sg:city":"Barcelona",
    "sg:orig_category":"Agentes Generales De Seguros",
    "sg:phone":"+34 933 25 78 36",
    "sg:postcode":"08004",
    "sg:province":"Barcelona",
    "wof:name":"Fort Antolin Antonio",
    "wof:placetype":"venue"
},
  "geometry": {"coordinates":[2.1494579315,41.3709526062],"type":"Point"}
}