{
  "type": "Feature",
  "properties": {
    "addr:full":"Avda Ernesto Sarti, S/n Torviscas Bajo Santa Cruz De Tenerife 38660",
    "addr:housenumber":"s / n",
    "addr:postcode":"38660",
    "addr:street":"Avda Ernesto Sarti",
    "iso:country":"ES",
    "sg:address":"Avda Ernesto Sarti, S/n",
    "sg:city":"Torviscas Bajo",
    "sg:orig_category":"Bazares, Art\u00cdculos De Limpieza Y De Cocina (al Por Menor)",
    "sg:phone":"+34 922 71 31 02",
    "sg:postcode":"38660",
    "sg:province":"Santa Cruz De Tenerife",
    "wof:name":"Bazares Gomez S.l.",
    "wof:placetype":"venue"
},
  "geometry": {"coordinates":[-16.7311515808,28.0861644745],"type":"Point"}
}