{
  "type": "Feature",
  "properties": {
    "iso:country":"ES",
    "sg:address":"Calle de Lekaenea, 4",
    "sg:city":"Irun",
    "sg:orig_category":"Sexshops",
    "sg:phone":"+34 943 01 79 99",
    "sg:postcode":"20301",
    "sg:province":"Guip\u00f9zcoa",
    "wof:name":"David Corral Medina",
    "wof:placetype":"venue"
},
  "geometry": {"coordinates":[-1.7978479862,43.34167099],"type":"Point"}
}