{
  "type": "Feature",
  "properties": {
    "iso:country":"ES",
    "sg:address":"Calle de Londres, 60",
    "sg:city":"Torres Alameda",
    "sg:orig_category":"Fabricaci\u00d3n De Jabones, Detergentes Y Lej\u00cdas",
    "sg:phone":"+34 918 85 87 55",
    "sg:postcode":"28813",
    "sg:province":"Madrid",
    "wof:name":"Ibersol Quimica S.l.",
    "wof:placetype":"venue"
},
  "geometry": {"coordinates":[-3.3209240437,40.3653335571],"type":"Point"}
}