{
  "type": "Feature",
  "properties": {
    "addr:full":"Carrer de Berenguer De Palou, 37 Barcelona Barcelona 08027",
    "addr:housenumber":"37",
    "addr:postcode":"08027",
    "addr:street":"Carrer De Berenguer De Palou",
    "iso:country":"ES",
    "sg:address":"Carrer de Berenguer De Palou, 37",
    "sg:city":"Barcelona",
    "sg:orig_category":"Farmacias",
    "sg:phone":"+34 933 49 24 28",
    "sg:postcode":"08027",
    "sg:province":"Barcelona",
    "wof:name":"Martinez-quintanilla Garcia Juan",
    "wof:placetype":"venue"
},
  "geometry": {"coordinates":[2.1915700436,41.4237289429],"type":"Point"}
}