{
  "type": "Feature",
  "properties": {
    "addr:full":"Avda Portugal, 38 Martina Le\u00f3n 24400",
    "addr:housenumber":"38",
    "addr:postcode":"24400",
    "addr:street":"Avda Portugal;Leo\u0301N",
    "iso:country":"ES",
    "sg:address":"Avda Portugal, 38",
    "sg:city":"Martina",
    "sg:orig_category":"M\u00c9dicos: Estomatolog\u00cda",
    "sg:phone":"+34 987 42 66 69",
    "sg:postcode":"24400",
    "sg:province":"Le\u00f3n",
    "wof:name":"Gonzalez Perez Maria Jesus",
    "wof:placetype":"venue"
},
  "geometry": {"coordinates":[-6.5983390808,42.5483360291],"type":"Point"}
}