{
  "type": "Feature",
  "properties": {
    "addr:full":"Avda Gaviotas, 175 Perellonet Valencia 46012",
    "addr:housenumber":"175",
    "addr:postcode":"46012",
    "addr:street":"Avda Gaviotas",
    "iso:country":"ES",
    "sg:address":"Avda Gaviotas, 175",
    "sg:city":"Perellonet",
    "sg:orig_category":"Agencias Y Agentes Comerciales, Representantes",
    "sg:phone":"+34 961 77 70 32",
    "sg:postcode":"46012",
    "sg:province":"Valencia",
    "wof:name":"Tarancon Gomez Vicente",
    "wof:placetype":"venue"
},
  "geometry": {"coordinates":[-0.2866109908,39.2934303284],"type":"Point"}
}