{
  "type": "Feature",
  "properties": {
    "iso:country":"ES",
    "sg:address":"Avda Madrid, 42",
    "sg:city":"Adrada",
    "sg:orig_category":"Mec\u00c1nico Del Autom\u00d3vil",
    "sg:phone":"+34 918 67 11 31",
    "sg:postcode":"05430",
    "sg:province":"\u00c1vila",
    "wof:name":"Talleres L.g.trinidad S.l.",
    "wof:placetype":"venue"
},
  "geometry": {"coordinates":[-4.6368670464,40.3029823303],"type":"Point"}
}