{
  "type": "Feature",
  "properties": {
    "addr:full":"Plaz Constitucion (la), 5 Sant Joan D'alacant Alicante 03550",
    "addr:postcode":"03550",
    "addr:street":"Constitucion La 5",
    "iso:country":"ES",
    "sg:address":"Plaz Constitucion (la), 5",
    "sg:city":"Sant Joan D'alacant",
    "sg:orig_category":"Heladeros",
    "sg:phone":"+34 965 65 73 72",
    "sg:postcode":"03550",
    "sg:province":"Alicante",
    "wof:name":"Planelles Martinez Maria Del Mar",
    "wof:placetype":"venue"
},
  "geometry": {"coordinates":[-0.4857670069,38.3471755981],"type":"Point"}
}