{
  "type": "Feature",
  "properties": {
    "iso:country":"ES",
    "sg:address":"Calle de Castilla, 8",
    "sg:city":"Tordesillas",
    "sg:orig_category":"Molduras, Junquillos, Listones Y Molduras Perforadas",
    "sg:phone":"+34 983 77 16 93",
    "sg:postcode":"47100",
    "sg:province":"Valladolid",
    "wof:name":"Escudero De La Cruz Rosario",
    "wof:placetype":"venue"
},
  "geometry": {"coordinates":[-4.9990000725,41.5068511963],"type":"Point"}
}