{
  "type": "Feature",
  "properties": {
    "iso:country":"ES",
    "sg:address":"Calle de Isabel La Catolica, 3",
    "sg:city":"San Juan",
    "sg:orig_category":"Organizaciones Internacionales",
    "sg:phone":"+34 968 21 49 46",
    "sg:postcode":"30003",
    "sg:province":"Murcia",
    "wof:name":"Hospitalidad Murciana De Nuestra Se\u00f1ora De Lourdes",
    "wof:placetype":"venue"
},
  "geometry": {"coordinates":[-1.1254940033,37.9831924438],"type":"Point"}
}