{
  "type": "Feature",
  "properties": {
    "addr:full":"Grauer E. Aunos, 24 Bossost Lleida 25550",
    "addr:housenumber":"24",
    "addr:postcode":"25550",
    "addr:street":"Grauer;Aunos",
    "iso:country":"ES",
    "sg:address":"Grauer E. Aunos, 24",
    "sg:city":"Bossost",
    "sg:orig_category":"Art\u00cdculos De Regalo (al Por Menor)",
    "sg:phone":"+34 973 64 82 37",
    "sg:postcode":"25550",
    "sg:province":"Lleida",
    "wof:name":"Vizcarra Elbaile Maria Teresa",
    "wof:placetype":"venue"
},
  "geometry": {"coordinates":[0.6915392876,42.7787971497],"type":"Point"}
}