{
  "type": "Feature",
  "properties": {
    "iso:country":"ES",
    "sg:address":"Fleming, 1",
    "sg:city":"La Carolina",
    "sg:orig_category":"Agencias De Viajes",
    "sg:phone":"+34 953 68 09 33",
    "sg:postcode":"23200",
    "sg:province":"Ja\u00e9n",
    "wof:name":"Perez Sueza Francisco Javier",
    "wof:placetype":"venue"
},
  "geometry": {"coordinates":[-3.6110711098,38.2749061584],"type":"Point"}
}