{
  "type": "Feature",
  "properties": {
    "iso:country":"ES",
    "sg:address":"Avda Portugal (de), 20",
    "sg:city":"Avila",
    "sg:orig_category":"Fabricaci\u00d3n, Importaci\u00d3n, Venta De Material De Telefon\u00cda, Peritelefon\u00cda",
    "sg:phone":"+34 920 35 23 26",
    "sg:postcode":"05001",
    "sg:province":"\u00c1vila",
    "wof:name":"Telestant S.a.",
    "wof:placetype":"venue"
},
  "geometry": {"coordinates":[-4.6932411194,40.6574935913],"type":"Point"}
}