{
  "type": "Feature",
  "properties": {
    "iso:country":"ES",
    "sg:address":"Calle de Parra (la), 1",
    "sg:city":"Jaen",
    "sg:orig_category":"Fabricaci\u00d3n De Cortinas Y Visillos",
    "sg:phone":"+34 953 23 37 03",
    "sg:postcode":"23003",
    "sg:province":"Ja\u00e9n",
    "wof:name":"Mendez De La Casa Luis Miguel",
    "wof:placetype":"venue"
},
  "geometry": {"coordinates":[-3.7269899845,37.7898101807],"type":"Point"}
}