{
  "type": "Feature",
  "properties": {
    "iso:country":"ES",
    "sg:address":"Calle de Camino De Los Enamorados, 10",
    "sg:city":"Puerto De Santa Maria",
    "sg:orig_category":"Transportes Por V\u00cdas Navegables",
    "sg:phone":"+34 956 87 03 56",
    "sg:postcode":"11500",
    "sg:province":"C\u00e1diz",
    "wof:name":"Luque Rivera Fernando Luis",
    "wof:placetype":"venue"
},
  "geometry": {"coordinates":[-6.2379655838,36.5933647156],"type":"Point"}
}