{
  "type": "Feature",
  "properties": {
    "addr:full":"Calle de Raimundo Fernandez Villaverde, 9 Madrid Madrid 28003",
    "addr:housenumber":"9",
    "addr:postcode":"madrid;28003",
    "addr:street":"Calle De Raimundo Fernandez Villaverde",
    "iso:country":"ES",
    "sg:address":"Calle de Raimundo Fernandez Villaverde, 9",
    "sg:city":"Madrid",
    "sg:orig_category":"M\u00c9dicos: Oftalmolog\u00cda",
    "sg:phone":"+34 915 34 82 12",
    "sg:postcode":"28003",
    "sg:province":"Madrid",
    "wof:name":"Lorenzo Ingles Jose",
    "wof:placetype":"venue"
},
  "geometry": {"coordinates":[-3.7023139,40.4469604492],"type":"Point"}
}