{
  "type": "Feature",
  "properties": {
    "iso:country":"ES",
    "sg:address":"Calle de Angel Embil, 1",
    "sg:city":"Pola De Siero",
    "sg:orig_category":"Art\u00cdculos Funerarios (al Por Menor)",
    "sg:phone":"+34 985 72 13 65",
    "sg:postcode":"33510",
    "sg:province":"Asturias",
    "wof:name":"Funeraria Meana S.l.",
    "wof:placetype":"venue"
},
  "geometry": {"coordinates":[-5.657099247,43.3936538696],"type":"Point"}
}