{
  "type": "Feature",
  "properties": {
    "iso:country":"ES",
    "sg:address":"Avda Americas (de Las), S/n",
    "sg:city":"Alcantarilla",
    "sg:orig_category":"Muebles, Minoristas",
    "sg:phone":"+34 968 89 04 83",
    "sg:postcode":"30820",
    "sg:province":"Murcia",
    "wof:name":"Lax Sofa Tapiceros S.l.",
    "wof:placetype":"venue"
},
  "geometry": {"coordinates":[-1.2070939541,37.9575767517],"type":"Point"}
}