{
  "type": "Feature",
  "properties": {
    "addr:full":"Carr Doctor Robert, 43 Albatarrec Lleida 25171",
    "addr:housenumber":"43",
    "addr:postcode":"25171",
    "addr:street":"Carr Doctor Robert",
    "iso:country":"ES",
    "sg:address":"Carr Doctor Robert, 43",
    "sg:city":"Albatarrec",
    "sg:orig_category":"Estancos",
    "sg:phone":"+34 973 72 00 44",
    "sg:postcode":"25171",
    "sg:province":"Lleida",
    "wof:name":"Oriol Ane Pilar",
    "wof:placetype":"venue"
},
  "geometry": {"coordinates":[0.6070230007,41.5737991333],"type":"Point"}
}