{
  "type": "Feature",
  "properties": {
    "iso:country":"ES",
    "sg:address":"Calle de Medico Pascual Perez, 8",
    "sg:city":"Alacant",
    "sg:orig_category":"Asesor\u00cda Fiscal Y Jur\u00cddica",
    "sg:phone":"+34 965 21 04 64",
    "sg:postcode":"03001",
    "sg:province":"Alicante",
    "wof:name":"Francisco Requena Y Amparo Amat S.c.",
    "wof:placetype":"venue"
},
  "geometry": {"coordinates":[-0.4862610102,38.3466262817],"type":"Point"}
}