{
  "type": "Feature",
  "properties": {
    "addr:full":"Carrer de Major De Sarria, 49 Barcelona Barcelona 08017",
    "addr:housenumber":"49",
    "addr:postcode":"08017",
    "addr:street":"Carrer De Major De Sarria",
    "iso:country":"ES",
    "sg:address":"Carrer de Major De Sarria, 49",
    "sg:city":"Barcelona",
    "sg:orig_category":"Molduras, Junquillos, Listones Y Molduras Perforadas",
    "sg:phone":"+34 932 03 10 77",
    "sg:postcode":"08017",
    "sg:province":"Barcelona",
    "wof:name":"Betorz Betorz Antonio",
    "wof:placetype":"venue"
},
  "geometry": {"coordinates":[2.1230220795,41.3975410461],"type":"Point"}
}