{
  "type": "Feature",
  "properties": {
    "addr:full":"Calle de Curtidors, 25 Alzira Valencia 46600",
    "addr:housenumber":"25",
    "addr:postcode":"46600",
    "addr:street":"Calle De Curtidors",
    "iso:country":"ES",
    "sg:address":"Calle de Curtidors, 25",
    "sg:city":"Alzira",
    "sg:orig_category":"Sindicatos De Trabajadores",
    "sg:phone":"+34 962 40 06 38",
    "sg:postcode":"46600",
    "sg:province":"Valencia",
    "wof:name":"Federacion Agroalimentaria Ugt-pv",
    "wof:placetype":"venue"
},
  "geometry": {"coordinates":[-0.4376955926,39.1498146057],"type":"Point"}
}