{
  "type": "Feature",
  "properties": {
    "iso:country":"ES",
    "sg:address":"Calle de Tejeras, 1",
    "sg:city":"Yecla",
    "sg:orig_category":"Muebles",
    "sg:phone":"+34 968 75 20 82",
    "sg:postcode":"30510",
    "sg:province":"Murcia",
    "wof:name":"Roster Tapizados S.l.",
    "wof:placetype":"venue"
},
  "geometry": {"coordinates":[-1.1399890184,38.6119117737],"type":"Point"}
}