{
  "type": "Feature",
  "properties": {
    "addr:full":"Calle de Palafox, 1 Madrid Madrid 28010",
    "addr:housenumber":"1",
    "addr:postcode":"28010",
    "addr:street":"Calle De Palafox",
    "iso:country":"ES",
    "sg:address":"Calle de Palafox, 1",
    "sg:city":"Madrid",
    "sg:classifiers":[
        {
            "category":"Cinema",
            "subcategory":"Movie Theater",
            "type":"Entertainment"
        }
    ],
    "sg:phone":"+34 914 44 30 14",
    "sg:postcode":"28010",
    "sg:province":"Madrid",
    "sg:tags":[
        "salas",
        "de",
        "cine"
    ],
    "wof:name":"Cine Palafox S.a.",
    "wof:placetype":"venue"
},
  "geometry": {"coordinates":[-3.7009599209,40.4301376343],"type":"Point"}
}