{
  "type": "Feature",
  "properties": {
    "iso:country":"ES",
    "sg:address":"Pg Urrutia, 59",
    "sg:city":"Barcelona",
    "sg:orig_category":"Venta, Instalaci\u00d3n, Reparaci\u00d3n De Antenas Para Televisi\u00d3n",
    "sg:phone":"+34 934 20 88 63",
    "sg:postcode":"08042",
    "sg:province":"Barcelona",
    "wof:name":"Tele-electron S.l.",
    "wof:placetype":"venue"
},
  "geometry": {"coordinates":[2.1664400101,41.4357185364],"type":"Point"}
}