{
  "type": "Feature",
  "properties": {
    "iso:country":"ES",
    "sg:address":"Calle de Vadillo, 17",
    "sg:city":"Dosbarrios",
    "sg:orig_category":"Sanatorios M\u00c9dico",
    "sg:phone":"+34 925 12 22 41",
    "sg:postcode":"45311",
    "sg:province":"Toledo",
    "wof:name":"Ayuntamiento De Dosbarrios Consultorio Medico",
    "wof:placetype":"venue"
},
  "geometry": {"coordinates":[-3.4855189323,39.8816490173],"type":"Point"}
}