{
  "type": "Feature",
  "properties": {
    "addr:full":"Carrer de Sant Francesc, 3 Lloren\u00e7 Penedes Tarragona 43712",
    "addr:housenumber":"3",
    "addr:postcode":"43712",
    "addr:street":"Carrer De Sant Francesc",
    "iso:country":"ES",
    "sg:address":"Carrer de Sant Francesc, 3",
    "sg:city":"Lloren\u00e7 Penedes",
    "sg:orig_category":"Plomeros",
    "sg:phone":"+34 977 67 88 41",
    "sg:postcode":"43712",
    "sg:province":"Tarragona",
    "wof:name":"Jane Raventos Josep Anton",
    "wof:placetype":"venue"
},
  "geometry": {"coordinates":[1.5538510084,41.2812690735],"type":"Point"}
}