{
  "type": "Feature",
  "properties": {
    "iso:country":"ES",
    "sg:address":"Calle de Martires (de Los), 3",
    "sg:city":"Boadilla Del Monte",
    "sg:orig_category":"Reposter\u00cdas",
    "sg:phone":"+34 916 32 31 79",
    "sg:postcode":"28660",
    "sg:province":"Madrid",
    "wof:name":"Weiss  Olinda Marta",
    "wof:placetype":"venue"
},
  "geometry": {"coordinates":[-3.8758044243,40.40675354],"type":"Point"}
}