{
  "type": "Feature",
  "properties": {
    "addr:full":"Calle de Amparo, 81 Madrid Madrid 28012",
    "addr:housenumber":"81",
    "addr:postcode":"madrid;28012",
    "addr:street":"Calle De Amparo",
    "iso:country":"ES",
    "sg:address":"Calle de Amparo, 81",
    "sg:city":"Madrid",
    "sg:orig_category":"Complementos De Vestir (al Por Menor)",
    "sg:phone":"+34 914 68 77 09",
    "sg:postcode":"28012",
    "sg:province":"Madrid",
    "wof:name":"Rahman Nazir  Mohd Mahbubur",
    "wof:placetype":"venue"
},
  "geometry": {"coordinates":[-3.7012791634,40.4075813293],"type":"Point"}
}