{
  "type": "Feature",
  "properties": {
    "iso:country":"ES",
    "sg:address":"Calle de General Elorza, 34",
    "sg:city":"Oviedo",
    "sg:orig_category":"Control T\u00c9cnico De Veh\u00cdculos",
    "sg:phone":"+34 985 11 05 95",
    "sg:postcode":"33001",
    "sg:province":"Asturias",
    "wof:name":"Inspeccion Tecnica De Vehiculos De Asturias S.a.",
    "wof:placetype":"venue"
},
  "geometry": {"coordinates":[-5.8443470001,43.3664245605],"type":"Point"}
}