{
  "type": "Feature",
  "properties": {
    "addr:full":"Calle de Progreso, 28 Burgos Burgos 09002",
    "addr:housenumber":"28",
    "addr:postcode":"09002",
    "addr:street":"Calle De Progreso",
    "iso:country":"ES",
    "sg:address":"Calle de Progreso, 28",
    "sg:city":"Burgos",
    "sg:orig_category":"Supermercados Y Hipermercados",
    "sg:phone":"+34 947 20 12 49",
    "sg:postcode":"09002",
    "sg:province":"Burgos",
    "wof:name":"Eroski Sociedad Cooperativa",
    "wof:placetype":"venue"
},
  "geometry": {"coordinates":[-3.6978299618,42.3370933533],"type":"Point"}
}