{
  "type": "Feature",
  "properties": {
    "iso:country":"ES",
    "sg:address":"Carrer de Caresmar, 73",
    "sg:city":"Sabadell",
    "sg:orig_category":"Electricidad: Instaladores",
    "sg:phone":"+34 937 45 95 27",
    "sg:postcode":"08205",
    "sg:province":"Barcelona",
    "wof:name":"Insta%acions Fervi S.l.",
    "wof:placetype":"venue"
},
  "geometry": {"coordinates":[2.0959310532,41.5440177917],"type":"Point"}
}