{
  "type": "Feature",
  "properties": {
    "addr:full":"Calle de Hernando De Acu\u00d1a, 47 Valladolid Valladolid 47014",
    "addr:housenumber":"47",
    "addr:postcode":"47014",
    "addr:street":"Calle De Hernando De Acun\u0303A",
    "iso:country":"ES",
    "sg:address":"Calle de Hernando De Acu\u00d1a, 47",
    "sg:city":"Valladolid",
    "sg:orig_category":"Molduras, Junquillos, Listones Y Molduras Perforadas",
    "sg:phone":"+34 983 33 95 07",
    "sg:postcode":"47014",
    "sg:province":"Valladolid",
    "wof:name":"Alvafres Cb",
    "wof:placetype":"venue"
},
  "geometry": {"coordinates":[-4.7627444267,41.6379776001],"type":"Point"}
}