{
  "type": "Feature",
  "properties": {
    "addr:full":"Avda Carabanchel Alto, 12 Madrid Madrid 28044",
    "addr:housenumber":"12",
    "addr:postcode":"madrid;28044",
    "addr:street":"Avda Carabanchel Alto",
    "iso:country":"ES",
    "sg:address":"Avda Carabanchel Alto, 12",
    "sg:city":"Madrid",
    "sg:orig_category":"Estancos",
    "sg:phone":"+34 915 08 58 33",
    "sg:postcode":"28044",
    "sg:province":"Madrid",
    "wof:name":"Rodriguez Cibarra Maria Del Carmen",
    "wof:placetype":"venue"
},
  "geometry": {"coordinates":[-3.7518010139,40.3728599548],"type":"Point"}
}