{
  "type": "Feature",
  "properties": {
    "iso:country":"ES",
    "sg:address":"Calle de General Rey, 8",
    "sg:city":"Ciudad Real",
    "sg:orig_category":"Centros Empresariales",
    "sg:phone":"+34 926 22 41 49",
    "sg:postcode":"13001",
    "sg:province":"Ciudad Real",
    "wof:name":"Asociacion Provincial De Fabricantes Y Expendendores De Pan",
    "wof:placetype":"venue"
},
  "geometry": {"coordinates":[-3.9260418415,38.9844741821],"type":"Point"}
}