{
  "type": "Feature",
  "properties": {
    "addr:full":"Calle de Zamora, 17 Puerto Cruz Santa Cruz De Tenerife 38400",
    "addr:housenumber":"17",
    "addr:postcode":"38400",
    "addr:street":"Calle De Zamora;Puerto Cruz",
    "iso:country":"ES",
    "sg:address":"Calle de Zamora, 17",
    "sg:city":"Puerto Cruz",
    "sg:orig_category":"Inmobiliaria (agencias)",
    "sg:phone":"+34 922 37 48 52",
    "sg:postcode":"38400",
    "sg:province":"Santa Cruz De Tenerife",
    "wof:name":"Peregon Puerto De La Cruz S.l.",
    "wof:placetype":"venue"
},
  "geometry": {"coordinates":[-16.5470256805,28.4153518677],"type":"Point"}
}