{
  "type": "Feature",
  "properties": {
    "iso:country":"ES",
    "sg:address":"Carrer de Antoni Gaudi, 39",
    "sg:city":"Gava",
    "sg:orig_category":"Dietistas",
    "sg:phone":"+34 936 62 00 55",
    "sg:postcode":"08850",
    "sg:province":"Barcelona",
    "wof:name":"Pilmon Associats 2002 S.l.l.",
    "wof:placetype":"venue"
},
  "geometry": {"coordinates":[2.0012850761,41.3040237427],"type":"Point"}
}