{
  "type": "Feature",
  "properties": {
    "iso:country":"ES",
    "sg:address":"Calle de Guadalete, 14",
    "sg:city":"Jerez De La Frontera",
    "sg:orig_category":"Asesor\u00cda Fiscal Y Jur\u00cddica",
    "sg:phone":"+34 956 33 74 78",
    "sg:postcode":"11403",
    "sg:province":"C\u00e1diz",
    "wof:name":"Slf S.l.",
    "wof:placetype":"venue"
},
  "geometry": {"coordinates":[-6.1386089325,36.6891098022],"type":"Point"}
}