{
  "type": "Feature",
  "properties": {
    "iso:country":"ES",
    "sg:address":"Pase Pintor Rosales, 50",
    "sg:city":"Madrid",
    "sg:orig_category":"Edici\u00d3n De Diarios, Revistas, Boletines",
    "sg:phone":"+34 915 41 68 21",
    "sg:postcode":"28008",
    "sg:province":"Madrid",
    "wof:name":"Strategic Planning Assoxiates Srl",
    "wof:placetype":"venue"
},
  "geometry": {"coordinates":[-3.7218430042,40.4292488098],"type":"Point"}
}