{
  "type": "Feature",
  "properties": {
    "iso:country":"ES",
    "sg:address":"Carr Josep Maria Quadrado, S/n",
    "sg:city":"Eivissa",
    "sg:orig_category":"Ropa Para Se\u00d1oras Y Caballeros (al Por Menor)",
    "sg:phone":"+34 971 31 88 97",
    "sg:postcode":"07800",
    "sg:province":"Islas Baleares",
    "wof:name":"Hernandez Zaragoza Vicente",
    "wof:placetype":"venue"
},
  "geometry": {"coordinates":[1.4333549738,38.911895752],"type":"Point"}
}