{
  "type": "Feature",
  "properties": {
    "addr:full":"Avda Cristo De Las Cadenas, 5 Oviedo Asturias 33006",
    "addr:housenumber":"5",
    "addr:postcode":"33006",
    "addr:street":"Avda Cristo De Las Cadenas",
    "iso:country":"ES",
    "sg:address":"Avda Cristo De Las Cadenas, 5",
    "sg:city":"Oviedo",
    "sg:orig_category":"Administradores De Bienes Y Delegados De Comunidades De Propietarios",
    "sg:phone":"+34 985 23 91 73",
    "sg:postcode":"33006",
    "sg:province":"Asturias",
    "wof:name":"Marguada S.l.",
    "wof:placetype":"venue"
},
  "geometry": {"coordinates":[-5.8580360413,43.3562965393],"type":"Point"}
}