{
  "type": "Feature",
  "properties": {
    "iso:country":"ES",
    "sg:address":"Calle de Galicia, 4",
    "sg:city":"Getafe",
    "sg:classifiers":[
        {
            "category":"Autos & Motor Vehicles",
            "subcategory":"Automobile Sales",
            "type":"Retail Goods"
        }
    ],
    "sg:phone":"+34 916 81 99 55",
    "sg:postcode":"28903",
    "sg:province":"Madrid",
    "wof:name":"Zurita Lopez Maria Elena",
    "wof:placetype":"venue"
},
  "geometry": {"coordinates":[-3.7210617065,40.3114547729],"type":"Point"}
}