{
  "type": "Feature",
  "properties": {
    "addr:full":"Calle de Ca\u00d1ada Real De Toledo (de La), 4 Pinto Madrid 28320",
    "addr:housenumber":"4",
    "addr:postcode":"28320",
    "addr:street":"Calle De Can\u0303Ada Real De Toledo De La;Pinto",
    "iso:country":"ES",
    "sg:address":"Calle de Ca\u00d1ada Real De Toledo (de La), 4",
    "sg:city":"Pinto",
    "sg:orig_category":"Panader\u00cdas, Panader\u00cdas",
    "sg:phone":"+34 916 92 28 45",
    "sg:postcode":"28320",
    "sg:province":"Madrid",
    "wof:name":"Pozo Jodra Javier Del",
    "wof:placetype":"venue"
},
  "geometry": {"coordinates":[-3.700397253,40.2376022339],"type":"Point"}
}