{
  "type": "Feature",
  "properties": {
    "iso:country":"ES",
    "sg:address":"Calle de Julio Cervera, 13",
    "sg:city":"Segorbe",
    "sg:orig_category":"Transportes Por Carretera: Lotes Completos, Mercanc\u00cdas Diversas",
    "sg:phone":"+34 964 71 04 81",
    "sg:postcode":"12400",
    "sg:province":"Castell\u00f3n",
    "wof:name":"Rodriguez Villar Vicente",
    "wof:placetype":"venue"
},
  "geometry": {"coordinates":[-0.4890049994,39.8517417908],"type":"Point"}
}