{
  "type": "Feature",
  "properties": {
    "iso:country":"ES",
    "sg:address":"Doctor Sanz De Frutos, 2",
    "sg:city":"Huelva",
    "sg:orig_category":"Arquitectos",
    "sg:phone":"+34 959 28 53 02",
    "sg:postcode":"21004",
    "sg:province":"Huelva",
    "wof:name":"Promociones Y Urbanismo Onubenses S.l.",
    "wof:placetype":"venue"
},
  "geometry": {"coordinates":[-6.9502520561,37.2640228271],"type":"Point"}
}