{
  "type": "Feature",
  "properties": {
    "iso:country":"ES",
    "sg:address":"Calle de Bravo Murillo, 122",
    "sg:city":"Madrid",
    "sg:orig_category":"Confecci\u00d3n (fabricaci\u00d3n, Al Por Mayor)",
    "sg:phone":"+34 915 33 67 48",
    "sg:postcode":"28020",
    "sg:province":"Madrid",
    "wof:name":"Perez Y Abad C.b",
    "wof:placetype":"venue"
},
  "geometry": {"coordinates":[-3.7036573887,40.4489326477],"type":"Point"}
}