{
  "type": "Feature",
  "properties": {
    "iso:country":"ES",
    "sg:address":"Calle de Historiador Bernardo Mundina, 1",
    "sg:city":"Onda",
    "sg:classifiers":[
        {
            "category":"Personal",
            "subcategory":"Barber",
            "type":"Services"
        }
    ],
    "sg:phone":"+34 964 77 17 92",
    "sg:postcode":"12200",
    "sg:province":"Castell\u00f3n",
    "sg:tags":[
        "caballeros",
        "de",
        "peluqueros"
    ],
    "wof:name":"Mallenco Garcia Miguel",
    "wof:placetype":"venue"
},
  "geometry": {"coordinates":[-0.2620640099,39.9651794434],"type":"Point"}
}