{
  "type": "Feature",
  "properties": {
    "addr:full":"Avda Gavilanes (los), 44 Sevilla Sevilla 41006",
    "addr:housenumber":"44",
    "addr:postcode":"41006",
    "addr:street":"Avda Gavilanes Los",
    "iso:country":"ES",
    "sg:address":"Avda Gavilanes (los), 44",
    "sg:city":"Sevilla",
    "sg:orig_category":"Comercio De Piezas De Recambio Y De Accesorios De Veh\u00cdculos, Veh\u00cdculos Industriales",
    "sg:phone":"+34 954 65 57 42",
    "sg:postcode":"41006",
    "sg:province":"Sevilla",
    "wof:name":"Autorecambios Avenida S.c",
    "wof:placetype":"venue"
},
  "geometry": {"coordinates":[-5.9517250061,37.3712425232],"type":"Point"}
}