{
  "type": "Feature",
  "properties": {
    "addr:full":"Pol Ind La Salina, S/n Rute C\u00f3rdoba 14960",
    "addr:housenumber":"s / n",
    "addr:postcode":"14960",
    "addr:street":"Salina;Co\u0301Rdoba",
    "iso:country":"ES",
    "sg:address":"Pol Ind La Salina, S/n",
    "sg:city":"Rute",
    "sg:orig_category":"Agentes, Concesionarios Y Sucursales De Camiones Y Veh\u00cdculos Industriales",
    "sg:phone":"+34 957 53 87 43",
    "sg:postcode":"14960",
    "sg:province":"C\u00f3rdoba",
    "sg:website":"www.proquisur.com",
    "wof:name":"Proquisur S.l.",
    "wof:placetype":"venue"
},
  "geometry": {"coordinates":[-4.3883838654,37.3373146057],"type":"Point"}
}