{
  "type": "Feature",
  "properties": {
    "addr:full":"Carr Carta Pobla, 22 Onda Castell\u00f3n 12200",
    "addr:housenumber":"22",
    "addr:postcode":"12200",
    "addr:street":"Carr Carta Pobla;Castello\u0301N",
    "iso:country":"ES",
    "sg:address":"Carr Carta Pobla, 22",
    "sg:city":"Onda",
    "sg:orig_category":"Frutas, Legumbres Frescas Y Tempranas (al Por Menor)",
    "sg:phone":"+34 964 60 31 29",
    "sg:postcode":"12200",
    "sg:province":"Castell\u00f3n",
    "wof:name":"Servicios Tecnicos La Dama S.l.",
    "wof:placetype":"venue"
},
  "geometry": {"coordinates":[-0.2584269941,39.9672546387],"type":"Point"}
}