{
  "type": "Feature",
  "properties": {
    "iso:country":"ES",
    "sg:address":"Plaz Sagasta, 2",
    "sg:city":"Zamora",
    "sg:orig_category":"Peleter\u00cdas",
    "sg:phone":"+34 980 53 15 08",
    "sg:postcode":"49002",
    "sg:province":"Zamora",
    "wof:name":"Prieto Cirac Raul",
    "wof:placetype":"venue"
},
  "geometry": {"coordinates":[-5.7454981804,41.5037879944],"type":"Point"}
}