{
  "type": "Feature",
  "properties": {
    "addr:full":"Calle de Prevision (la), 2 Cordoba C\u00f3rdoba 14004",
    "addr:housenumber":"2",
    "addr:postcode":"14004",
    "addr:street":"Calle De Prevision La;Co\u0301Rdoba",
    "iso:country":"ES",
    "sg:address":"Calle de Prevision (la), 2",
    "sg:city":"Cordoba",
    "sg:orig_category":"Asociaciones Y Clubs Deportivos",
    "sg:phone":"+34 957 45 44 71",
    "sg:postcode":"14004",
    "sg:province":"C\u00f3rdoba",
    "wof:name":"Gimnasio Gym C.b",
    "wof:placetype":"venue"
},
  "geometry": {"coordinates":[-4.7882218361,37.8801651001],"type":"Point"}
}