{
  "type": "Feature",
  "properties": {
    "iso:country":"ES",
    "sg:address":"Avgd Jaime I, 12",
    "sg:city":"Canals",
    "sg:orig_category":"Notarios",
    "sg:phone":"+34 962 24 32 06",
    "sg:postcode":"46650",
    "sg:province":"Valencia",
    "wof:name":"Estevan Gordo Rafael",
    "wof:placetype":"venue"
},
  "geometry": {"coordinates":[-0.5837259889,38.9641151428],"type":"Point"}
}