{
  "type": "Feature",
  "properties": {
    "iso:country":"ES",
    "sg:address":"Calle de Tercia, 2",
    "sg:city":"Urda",
    "sg:classifiers":[
        {
            "category":"Manufacturing",
            "subcategory":"Building Materials",
            "type":"Manufacturing & Wholesale Goods"
        }
    ],
    "sg:phone":"+34 925 47 23 41",
    "sg:postcode":"45480",
    "sg:province":"Toledo",
    "sg:tags":[
        "cemento",
        "y",
        "de",
        "fabricaci\u00d3n",
        "cal"
    ],
    "wof:name":"Rabagom S.l.",
    "wof:placetype":"venue"
},
  "geometry": {"coordinates":[-3.7142329216,39.4104232788],"type":"Point"}
}