{
  "type": "Feature",
  "properties": {
    "addr:full":"Calle de Reyes De Navarra, 47 Vitoria-gasteiz \u00c1lava 01013",
    "addr:housenumber":"47",
    "addr:postcode":"01013",
    "addr:street":"Calle De Reyes De Navarra",
    "iso:country":"ES",
    "sg:address":"Calle de Reyes De Navarra, 47",
    "sg:city":"Vitoria-gasteiz",
    "sg:orig_category":"Dise\u00d1o Industrial",
    "sg:phone":"+34 945 25 88 94",
    "sg:postcode":"01013",
    "sg:province":"\u00c1lava",
    "sg:website":"www.cadelimp.com",
    "wof:name":"Pedro M\u00aa Lopez Susunaga - Cadelims",
    "wof:placetype":"venue"
},
  "geometry": {"coordinates":[-2.6697928905,42.8603973389],"type":"Point"}
}