{
  "type": "Feature",
  "properties": {
    "addr:full":"Calle de Andres Segovia, 28 Mora Toledo 45400",
    "addr:housenumber":"28",
    "addr:postcode":"45400",
    "addr:street":"Calle De Andres Segovia",
    "iso:country":"ES",
    "sg:address":"Calle de Andres Segovia, 28",
    "sg:city":"Mora",
    "sg:orig_category":"Promotores Constructores",
    "sg:phone":"+34 925 34 10 93",
    "sg:postcode":"45400",
    "sg:province":"Toledo",
    "wof:name":"Sanchez Cervantes Nicolas",
    "wof:placetype":"venue"
},
  "geometry": {"coordinates":[-3.7661385536,39.6834793091],"type":"Point"}
}