{
  "type": "Feature",
  "properties": {
    "addr:full":"Pol Ind La Trocha, 32 Coin M\u00e1laga 29100",
    "addr:housenumber":"32",
    "addr:postcode":"29100",
    "addr:street":"Trocha;Ma\u0301Laga",
    "iso:country":"ES",
    "sg:address":"Pol Ind La Trocha, 32",
    "sg:city":"Coin",
    "sg:orig_category":"Bricolaje, Herramientas (al Por Menor)",
    "sg:phone":"+34 952 45 24 94",
    "sg:postcode":"29100",
    "sg:province":"M\u00e1laga",
    "wof:name":"Lucena Sanchez Jose",
    "wof:placetype":"venue"
},
  "geometry": {"coordinates":[-4.7576842308,36.659740448],"type":"Point"}
}