{
  "type": "Feature",
  "properties": {
    "addr:full":"Calle de Nuestra Se\u00d1ora De Belen, 2 Burgos Burgos 09001",
    "addr:housenumber":"2",
    "addr:postcode":"09001",
    "addr:street":"Calle De Nuestra Sen\u0303Ora;Belen",
    "iso:country":"ES",
    "sg:address":"Calle de Nuestra Se\u00d1ora De Belen, 2",
    "sg:city":"Burgos",
    "sg:orig_category":"T\u00c9cnicos Veterinarios",
    "sg:phone":"+34 947 20 92 39",
    "sg:postcode":"09001",
    "sg:province":"Burgos",
    "wof:name":"Guijarro Colliga Graciliano",
    "wof:placetype":"venue"
},
  "geometry": {"coordinates":[-3.7000699043,42.3324317932],"type":"Point"}
}