{
  "type": "Feature",
  "properties": {
    "addr:full":"Carrer de Puerto Principe, 14 Barcelona Barcelona 08027",
    "addr:housenumber":"14",
    "addr:postcode":"08027",
    "addr:street":"Carrer De Puerto Principe",
    "iso:country":"ES",
    "sg:address":"Carrer de Puerto Principe, 14",
    "sg:city":"Barcelona",
    "sg:orig_category":"Aparcamientos (infraestructuras, Accesorios)",
    "sg:phone":"+34 933 51 84 16",
    "sg:postcode":"08027",
    "sg:province":"Barcelona",
    "wof:name":"Jordana Domingo Emilia",
    "wof:placetype":"venue"
},
  "geometry": {"coordinates":[2.1811339855,41.4213218689],"type":"Point"}
}