{
  "type": "Feature",
  "properties": {
    "iso:country":"ES",
    "sg:address":"Albariza, S/n",
    "sg:city":"Noia",
    "sg:orig_category":"Promotores Constructores",
    "sg:phone":"+34 981 87 71 50",
    "sg:postcode":"15200",
    "sg:province":"La Coru\u00f1a",
    "wof:name":"Construcciones Rapida Y Buena Ejecucion S.l.",
    "wof:placetype":"venue"
},
  "geometry": {"coordinates":[-8.8883037567,42.788608551],"type":"Point"}
}