{
  "type": "Feature",
  "properties": {
    "iso:country":"ES",
    "sg:address":"Calle de Sebastian Elcano, 36",
    "sg:city":"Madrid",
    "sg:orig_category":"Fabricaci\u00d3n De Pernos, Tornillos Y Clavos",
    "sg:phone":"+34 915 27 22 68",
    "sg:postcode":"28012",
    "sg:province":"Madrid",
    "wof:name":"Tornicalvo S.l.",
    "wof:placetype":"venue"
},
  "geometry": {"coordinates":[-3.6967320442,40.4050445557],"type":"Point"}
}