{
  "type": "Feature",
  "properties": {
    "addr:full":"Florencio Ansoleaga, 26 Iru\u00f1a Navarra 31001",
    "addr:housenumber":"26",
    "addr:postcode":"31001",
    "addr:street":"Florencio Ansoleaga",
    "iso:country":"ES",
    "sg:address":"Florencio Ansoleaga, 26",
    "sg:city":"Iru\u00f1a",
    "sg:orig_category":"Peluqueros: De Se\u00d1oras",
    "sg:phone":"+34 948 22 72 32",
    "sg:postcode":"31001",
    "sg:province":"Navarra",
    "wof:name":"Delgado Cenzano Laura",
    "wof:placetype":"venue"
},
  "geometry": {"coordinates":[-1.6465320587,42.8171272278],"type":"Point"}
}