{
  "type": "Feature",
  "properties": {
    "iso:country":"ES",
    "sg:address":"Carrer de Castanyer, 3",
    "sg:city":"Barcelona",
    "sg:orig_category":"M\u00c9dicos: Ginecolog\u00cda Y Obstetricia",
    "sg:phone":"+34 934 18 96 24",
    "sg:postcode":"08022",
    "sg:province":"Barcelona",
    "wof:name":"Bataller Sanchez Eduardo",
    "wof:placetype":"venue"
},
  "geometry": {"coordinates":[2.1362490654,41.4062652588],"type":"Point"}
}