{
  "type": "Feature",
  "properties": {
    "addr:full":"Calle de Velez, 7 Puertollano Ciudad Real 13500",
    "addr:housenumber":"7",
    "addr:postcode":"13500",
    "addr:street":"Calle De Velez",
    "iso:country":"ES",
    "sg:address":"Calle de Velez, 7",
    "sg:city":"Puertollano",
    "sg:orig_category":"Molduras, Junquillos, Listones Y Molduras Perforadas",
    "sg:phone":"+34 926 42 46 60",
    "sg:postcode":"13500",
    "sg:province":"Ciudad Real",
    "wof:name":"Mingo Moraleda Carlos De",
    "wof:placetype":"venue"
},
  "geometry": {"coordinates":[-4.1079921722,38.6887283325],"type":"Point"}
}