{
  "type": "Feature",
  "properties": {
    "addr:full":"Calle de Martinez Molina, 10 Jaen Ja\u00e9n 23004",
    "addr:housenumber":"10;jae\u0301n",
    "addr:postcode":"23004",
    "addr:street":"Calle De Martinez Molina",
    "iso:country":"ES",
    "sg:address":"Calle de Martinez Molina, 10",
    "sg:city":"Jaen",
    "sg:orig_category":"Sindicatos De Trabajadores",
    "sg:phone":"+34 953 24 02 98",
    "sg:postcode":"23004",
    "sg:province":"Ja\u00e9n",
    "wof:name":"Astisa",
    "wof:placetype":"venue"
},
  "geometry": {"coordinates":[-3.7927858829,37.768901825],"type":"Point"}
}