{
  "type": "Feature",
  "properties": {
    "iso:country":"ES",
    "sg:address":"Calle de Polvorin (el), 2",
    "sg:city":"Reinosa",
    "sg:orig_category":"Comadronas",
    "sg:phone":"+34 942 75 11 44",
    "sg:postcode":"39200",
    "sg:province":"Cantabria",
    "wof:name":"Perez Mu\u00f1oz Angela",
    "wof:placetype":"venue"
},
  "geometry": {"coordinates":[-4.1350240707,43.0031661987],"type":"Point"}
}