{
  "type": "Feature",
  "properties": {
    "addr:full":"Calle de Adriano Vi, 20 Vitoria-gasteiz \u00c1lava 01008",
    "addr:housenumber":"20",
    "addr:postcode":"01008",
    "addr:street":"Calle De Adriano Vi",
    "iso:country":"ES",
    "sg:address":"Calle de Adriano Vi, 20",
    "sg:city":"Vitoria-gasteiz",
    "sg:orig_category":"Bisuter\u00cda, Joyer\u00cda, Relojer\u00cda (al Por Menor)",
    "sg:phone":"+34 945 24 48 47",
    "sg:postcode":"01008",
    "sg:province":"\u00c1lava",
    "wof:name":"Garin Joyeros, S.l.",
    "wof:placetype":"venue"
},
  "geometry": {"coordinates":[-2.6820673943,42.8473815918],"type":"Point"}
}