{
  "type": "Feature",
  "properties": {
    "addr:full":"Calle de Poeta Altet, 9 Valencia Valencia 46020",
    "addr:housenumber":"9",
    "addr:postcode":"46020",
    "addr:street":"Calle De Poeta Altet",
    "iso:country":"ES",
    "sg:address":"Calle de Poeta Altet, 9",
    "sg:city":"Valencia",
    "sg:orig_category":"Cristaler\u00cdas",
    "sg:phone":"+34 963 93 41 44",
    "sg:postcode":"46020",
    "sg:province":"Valencia",
    "wof:name":"Suliran S.l.",
    "wof:placetype":"venue"
},
  "geometry": {"coordinates":[-0.3645690978,39.4864425659],"type":"Point"}
}