{
  "type": "Feature",
  "properties": {
    "addr:full":"Casillas, Km. 0037,0 Casillas A Coru\u00f1a 15680",
    "addr:postcode":"15680",
    "addr:street":"Casillas Km. 0037,0 Casillas A Corun\u0303A",
    "iso:country":"ES",
    "sg:address":"Casillas, Km. 0037,0",
    "sg:city":"Casillas",
    "sg:orig_category":"Ense\u00d1anza, Formaci\u00d3n Profesional: Aprendizaje",
    "sg:phone":"+34 981 68 83 86",
    "sg:postcode":"15680",
    "sg:province":"A Coru\u00f1a",
    "wof:name":"Xunta De Galicia",
    "wof:placetype":"venue"
},
  "geometry": {"coordinates":[-8.4139986038,43.0610275269],"type":"Point"}
}