{
  "type": "Feature",
  "properties": {
    "addr:full":"Calle de Compa\u00d1ia, 10 Marchena Sevilla 41620",
    "addr:housenumber":"10",
    "addr:postcode":"41620",
    "addr:street":"Calle De Compan\u0303Ia",
    "iso:country":"ES",
    "sg:address":"Calle de Compa\u00d1ia, 10",
    "sg:city":"Marchena",
    "sg:orig_category":"Internados & Ense\u00d1anza Privada",
    "sg:phone":"+34 955 84 74 65",
    "sg:postcode":"41620",
    "sg:province":"Sevilla",
    "wof:name":"Religiosas Terciarias Franciscanas",
    "wof:placetype":"venue"
},
  "geometry": {"coordinates":[-5.411924839,37.3304672241],"type":"Point"}
}