{
  "type": "Feature",
  "properties": {
    "iso:country":"ES",
    "sg:address":"Carrer de Major, 19",
    "sg:city":"Sitges",
    "sg:orig_category":"Agencias De Viajes",
    "sg:phone":"+34 938 94 08 67",
    "sg:postcode":"08870",
    "sg:province":"Barcelona",
    "wof:name":"Gorgas Vives Maria Angeles",
    "wof:placetype":"venue"
},
  "geometry": {"coordinates":[1.8108559847,41.2359275818],"type":"Point"}
}