{
  "type": "Feature",
  "properties": {
    "addr:full":"Carrer de Marques De Tamarit, 13 Altafulla Tarragona 43893",
    "addr:housenumber":"13",
    "addr:postcode":"43893",
    "addr:street":"Carrer De Marques De Tamarit",
    "iso:country":"ES",
    "sg:address":"Carrer de Marques De Tamarit, 13",
    "sg:city":"Altafulla",
    "sg:orig_category":"Molduras, Junquillos, Listones Y Molduras Perforadas",
    "sg:phone":"+34 977 65 28 39",
    "sg:postcode":"43893",
    "sg:province":"Tarragona",
    "wof:name":"Tello Balleste Alberto",
    "wof:placetype":"venue"
},
  "geometry": {"coordinates":[1.3763699532,41.1403808594],"type":"Point"}
}