{
  "type": "Feature",
  "properties": {
    "iso:country":"ES",
    "sg:address":"Romeral, S/n",
    "sg:city":"Casas De Eufemia",
    "sg:orig_category":"Productores Recolectores, Venta Directa De Vinos",
    "sg:phone":"+34 962 33 40 75",
    "sg:postcode":"46352",
    "sg:province":"Valencia",
    "wof:name":"Cooperativa Agricola La Inmaculada",
    "wof:placetype":"venue"
},
  "geometry": {"coordinates":[-1.2094240189,39.448299408],"type":"Point"}
}