{
  "type": "Feature",
  "properties": {
    "addr:full":"Ctra Tafira Alta De, 189 Tafira Alta Las Palmas 35017",
    "addr:housenumber":"189",
    "addr:postcode":"35017",
    "addr:street":"Ctra Tafira Alta De;Alta",
    "iso:country":"ES",
    "sg:address":"Ctra Tafira Alta De, 189",
    "sg:city":"Tafira Alta",
    "sg:orig_category":"Agencias Y Agentes Comerciales, Representantes",
    "sg:phone":"+34 928 35 11 57",
    "sg:postcode":"35017",
    "sg:province":"Las Palmas",
    "wof:name":"Suarez Diaz Jeronimo",
    "wof:placetype":"venue"
},
  "geometry": {"coordinates":[-15.4672966003,28.0528583527],"type":"Point"}
}