{
  "type": "Feature",
  "properties": {
    "iso:country":"ES",
    "sg:address":"Rua Tui, 1",
    "sg:city":"Lugo",
    "sg:orig_category":"Peluqueros: De Se\u00d1oras",
    "sg:phone":"+34 982 24 46 08",
    "sg:postcode":"27004",
    "sg:province":"Lugo",
    "wof:name":"Rodriguez Portome\u00f1e Maria Del Carmen",
    "wof:placetype":"venue"
},
  "geometry": {"coordinates":[-7.5625548363,43.016242981],"type":"Point"}
}