{
  "type": "Feature",
  "properties": {
    "addr:full":"Avda Alisas (cavada), 39 Cavada Cantabria 39720",
    "addr:housenumber":"39",
    "addr:postcode":"39720",
    "addr:street":"Avda Alisas Cavada",
    "iso:country":"ES",
    "sg:address":"Avda Alisas (cavada), 39",
    "sg:city":"Cavada",
    "sg:orig_category":"Farmacias",
    "sg:phone":"+34 942 53 92 91",
    "sg:postcode":"39720",
    "sg:province":"Cantabria",
    "wof:name":"Sainz De La Maza Gutierrez Pilar",
    "wof:placetype":"venue"
},
  "geometry": {"coordinates":[-3.70499897,43.3520584106],"type":"Point"}
}