{
  "type": "Feature",
  "properties": {
    "addr:full":"Rua Paraguai, 11 Meicende La Coru\u00f1a 15140",
    "addr:housenumber":"11",
    "addr:postcode":"15140",
    "addr:street":"Rua Paraguai;La Corun\u0303A",
    "iso:country":"ES",
    "sg:address":"Rua Paraguai, 11",
    "sg:city":"Meicende",
    "sg:orig_category":"Garajes De Veh\u00cdculos",
    "sg:phone":"+34 981 26 25 64",
    "sg:postcode":"15140",
    "sg:province":"La Coru\u00f1a",
    "wof:name":"Rofer Equipos Automocion S.l.l.",
    "wof:placetype":"venue"
},
  "geometry": {"coordinates":[-8.46671772,43.3288497925],"type":"Point"}
}