{
  "type": "Feature",
  "properties": {
    "iso:country":"ES",
    "sg:address":"Calle de Orotava (la), S/n",
    "sg:city":"Santa Cruz De Tenerife",
    "sg:orig_category":"Alimentaci\u00d3n General (al Por Menor)",
    "sg:phone":"+34 922 22 08 03",
    "sg:postcode":"38008",
    "sg:province":"Santa Cruz De Tenerife",
    "wof:name":"Cabrera Morales Esteban",
    "wof:placetype":"venue"
},
  "geometry": {"coordinates":[-16.2745418549,28.4732151031],"type":"Point"}
}