{
  "type": "Feature",
  "properties": {
    "addr:full":"Calle de San Julian, 7 Ororbia Navarra 31171",
    "addr:housenumber":"7",
    "addr:postcode":"31171",
    "addr:street":"Calle De San Julian",
    "iso:country":"ES",
    "sg:address":"Calle de San Julian, 7",
    "sg:city":"Ororbia",
    "sg:orig_category":"Carb\u00d3n, Carb\u00d3n De Madera (al Por Mayor)",
    "sg:phone":"+34 948 32 12 38",
    "sg:postcode":"31171",
    "sg:province":"Navarra",
    "wof:name":"Hermanos Sanmartin Beloki S.i",
    "wof:placetype":"venue"
},
  "geometry": {"coordinates":[-1.7458289862,42.817150116],"type":"Point"}
}