{
  "type": "Feature",
  "properties": {
    "iso:country":"ES",
    "sg:address":"Urb El Pilar, 6",
    "sg:city":"Motril",
    "sg:orig_category":"Agencias Y Agentes Comerciales, Representantes",
    "sg:phone":"+34 958 60 86 19",
    "sg:postcode":"18600",
    "sg:province":"Granada",
    "wof:name":"Ciudad 2010 S.a.",
    "wof:placetype":"venue"
},
  "geometry": {"coordinates":[-3.5250589848,36.7525444031],"type":"Point"}
}