{
  "type": "Feature",
  "properties": {
    "iso:country":"ES",
    "sg:address":"Carrer de Ramon Rocafull, 92",
    "sg:city":"Barcelona",
    "sg:orig_category":"Molduras, Junquillos, Listones Y Molduras Perforadas",
    "sg:phone":"+34 934 20 40 55",
    "sg:postcode":"08032",
    "sg:province":"Barcelona",
    "wof:name":"Amaro Seara Manuel",
    "wof:placetype":"venue"
},
  "geometry": {"coordinates":[2.1546154022,41.422290802],"type":"Point"}
}