{
  "type": "Feature",
  "properties": {
    "addr:full":"El Puerto, S/n Colindres Cantabria 39750",
    "addr:housenumber":"/ n",
    "addr:postcode":"39750",
    "addr:street":"S",
    "iso:country":"ES",
    "sg:address":"El Puerto, S/n",
    "sg:city":"Colindres",
    "sg:orig_category":"Navegaci\u00d3n (equipos Fluviales)",
    "sg:phone":"+34 942 65 22 62",
    "sg:postcode":"39750",
    "sg:province":"Cantabria",
    "wof:name":"Revuelta Cuesta Juan Jose",
    "wof:placetype":"venue"
},
  "geometry": {"coordinates":[-3.4410049915,43.3926849365],"type":"Point"}
}