{
  "type": "Feature",
  "properties": {
    "iso:country":"ES",
    "sg:address":"Plaz Universidad (de La), 2",
    "sg:city":"Granada",
    "sg:orig_category":"Abogados",
    "sg:phone":"+34 958 80 05 45",
    "sg:postcode":"18001",
    "sg:province":"Granada",
    "wof:name":"Contreras Hervas Victoria Eugenia",
    "wof:placetype":"venue"
},
  "geometry": {"coordinates":[-3.6016340256,37.1783218384],"type":"Point"}
}