{
  "type": "Feature",
  "properties": {
    "addr:full":"Sant Antoni, 36 Corbera Valencia 46612",
    "addr:housenumber":"36",
    "addr:postcode":"46612",
    "addr:street":"Sant Antoni",
    "iso:country":"ES",
    "sg:address":"Sant Antoni, 36",
    "sg:city":"Corbera",
    "sg:orig_category":"Arquitectos",
    "sg:phone":"+34 962 56 05 20",
    "sg:postcode":"46612",
    "sg:province":"Valencia",
    "wof:name":"Marrades Climent Concha",
    "wof:placetype":"venue"
},
  "geometry": {"coordinates":[-0.3554689884,39.1597709656],"type":"Point"}
}