{
  "type": "Feature",
  "properties": {
    "addr:full":"Calle de Lopez De Hoyos, 327 Madrid Madrid 28043",
    "addr:housenumber":"327",
    "addr:postcode":"28043",
    "addr:street":"Calle De Lopez De Hoyos",
    "iso:country":"ES",
    "sg:address":"Calle de Lopez De Hoyos, 327",
    "sg:city":"Madrid",
    "sg:orig_category":"Centros Empresariales",
    "sg:phone":"+34 917 16 05 00",
    "sg:postcode":"28043",
    "sg:province":"Madrid",
    "sg:website":"www.technip.com",
    "wof:name":"Technip Benelux Espana B.v.",
    "wof:placetype":"venue"
},
  "geometry": {"coordinates":[-3.6565001011,40.4646148682],"type":"Point"}
}