{
  "type": "Feature",
  "properties": {
    "iso:country":"ES",
    "sg:address":"Pla\u00c7 Sant Miquel, 6",
    "sg:city":"Cervera",
    "sg:orig_category":"Pescader\u00cdas (al Por Menor)",
    "sg:phone":"+34 973 53 00 39",
    "sg:postcode":"25200",
    "sg:province":"Lleida",
    "wof:name":"Alvaro Vidal Porta S.l.",
    "wof:placetype":"venue"
},
  "geometry": {"coordinates":[1.2794743776,41.6838417053],"type":"Point"}
}