{
  "type": "Feature",
  "properties": {
    "addr:full":"Avda Deporte, 10 Santander Cantabria 39012",
    "addr:housenumber":"10",
    "addr:postcode":"39012",
    "addr:street":"Avda Deporte",
    "iso:country":"ES",
    "sg:address":"Avda Deporte, 10",
    "sg:city":"Santander",
    "sg:orig_category":"Peluqueros: De Se\u00d1oras",
    "sg:phone":"+34 942 32 49 62",
    "sg:postcode":"39012",
    "sg:province":"Cantabria",
    "wof:name":"Malanda Saiz Evangelina",
    "wof:placetype":"venue"
},
  "geometry": {"coordinates":[-3.8468520641,43.4615592957],"type":"Point"}
}