{
  "type": "Feature",
  "properties": {
    "addr:full":"Calle de San Eloy, 7 Cordoba C\u00f3rdoba 14002",
    "addr:housenumber":"7",
    "addr:postcode":"14002",
    "addr:street":"Calle De San Eloy;Co\u0301Rdoba",
    "iso:country":"ES",
    "sg:address":"Calle de San Eloy, 7",
    "sg:city":"Cordoba",
    "sg:orig_category":"Electricidad, Electr\u00d3nica: Material Y Suministros (al Por Mayor)",
    "sg:phone":"+34 957 48 40 35",
    "sg:postcode":"14002",
    "sg:province":"C\u00f3rdoba",
    "wof:name":"Montero Roldan Jose R.",
    "wof:placetype":"venue"
},
  "geometry": {"coordinates":[-4.7704482079,37.8837394714],"type":"Point"}
}