{
  "type": "Feature",
  "properties": {
    "addr:full":"A, S/n P. I. El Romeral Valencia 46340",
    "addr:housenumber":"s / n",
    "addr:postcode":"46340",
    "addr:street":"A;P. I. El Romeral",
    "iso:country":"ES",
    "sg:address":"A, S/n",
    "sg:city":"P. I. El Romeral",
    "sg:orig_category":"Cooperativas Agr\u00cdcolas",
    "sg:phone":"+34 962 30 17 72",
    "sg:postcode":"46340",
    "sg:province":"Valencia",
    "wof:name":"Almazara Cooperativa Requena Agricola",
    "wof:placetype":"venue"
},
  "geometry": {"coordinates":[-1.1218831539,39.5044364929],"type":"Point"}
}