{
  "type": "Feature",
  "properties": {
    "addr:full":"Calle de Aldamar, 22 Donostia-san Sebastian Guip\u00f9zcoa 20003",
    "addr:housenumber":"22",
    "addr:postcode":"20003",
    "addr:street":"Calle De Aldamar",
    "iso:country":"ES",
    "sg:address":"Calle de Aldamar, 22",
    "sg:city":"Donostia-san Sebastian",
    "sg:orig_category":"Heladeros",
    "sg:phone":"+34 943 42 82 54",
    "sg:postcode":"20003",
    "sg:province":"Guip\u00f9zcoa",
    "wof:name":"Arin Zabala Jose Maria",
    "wof:placetype":"venue"
},
  "geometry": {"coordinates":[-1.982811451,43.3240318298],"type":"Point"}
}