{
  "type": "Feature",
  "properties": {
    "iso:country":"ES",
    "sg:address":"Calle de Perez De Ayala, 32",
    "sg:city":"Gijon",
    "sg:classifiers":[
        {
            "category":"Autos & Motor Vehicles",
            "subcategory":"Automobile Sales",
            "type":"Retail Goods"
        }
    ],
    "sg:phone":"+34 985 38 16 88",
    "sg:postcode":"33208",
    "sg:province":"Asturias",
    "wof:name":"Castro Otero Benigno",
    "wof:placetype":"venue"
},
  "geometry": {"coordinates":[-5.6630420685,43.5319671631],"type":"Point"}
}