{
  "type": "Feature",
  "properties": {
    "addr:full":"Calle de Real, 93 Montehermoso C\u00e1ceres 10810",
    "addr:housenumber":"93",
    "addr:postcode":"10810",
    "addr:street":"Calle De Real;Ca\u0301Ceres",
    "iso:country":"ES",
    "sg:address":"Calle de Real, 93",
    "sg:city":"Montehermoso",
    "sg:orig_category":"Lavado, Limpieza De Veh\u00cdculos",
    "sg:phone":"+34 927 67 53 42",
    "sg:postcode":"10810",
    "sg:province":"C\u00e1ceres",
    "wof:name":"Garrido Vicente Julio",
    "wof:placetype":"venue"
},
  "geometry": {"coordinates":[-6.3439350128,40.086681366],"type":"Point"}
}