{
  "type": "Feature",
  "properties": {
    "iso:country":"ES",
    "sg:address":"Calle de Real, 93",
    "sg:city":"Montehermoso",
    "sg:orig_category":"Lavado, Limpieza De Veh\u00cdculos",
    "sg:phone":"+34 927 67 53 42",
    "sg:postcode":"10810",
    "sg:province":"C\u00e1ceres",
    "wof:name":"Garrido Vicente Julio",
    "wof:placetype":"venue"
},
  "geometry": {"coordinates":[-6.3439350128,40.086681366],"type":"Point"}
}