{
  "type": "Feature",
  "properties": {
    "addr:full":"Ctra. Valencia, S/n Alacant Alicante 03016",
    "addr:housenumber":"s / n",
    "addr:postcode":"03016",
    "addr:street":"Ctra. Valencia",
    "iso:country":"ES",
    "sg:address":"Ctra. Valencia, S/n",
    "sg:city":"Alacant",
    "sg:orig_category":"Cajas De Ahorro",
    "sg:phone":"+34 965 26 39 29",
    "sg:postcode":"03016",
    "sg:province":"Alicante",
    "sg:website":"www.cam.es",
    "wof:name":"Caja De Ahorros Del Mediterraneo",
    "wof:placetype":"venue"
},
  "geometry": {"coordinates":[-0.4836539924,38.354888916],"type":"Point"}
}