{
  "type": "Feature",
  "properties": {
    "iso:country":"ES",
    "sg:address":"Calle de Mayor, 45",
    "sg:city":"Alcala Henares",
    "sg:orig_category":"Cervecer\u00cdas",
    "sg:phone":"+34 918 83 15 95",
    "sg:postcode":"28801",
    "sg:province":"Madrid",
    "wof:name":"Kneipe S.l.",
    "wof:placetype":"venue"
},
  "geometry": {"coordinates":[-3.366558075,40.4821128845],"type":"Point"}
}