{
  "type": "Feature",
  "properties": {
    "iso:country":"ES",
    "sg:address":"Pase Castellana, 91",
    "sg:city":"Madrid",
    "sg:orig_category":"Parques De Atracciones Y Centros De Esparcimiento",
    "sg:phone":"+34 915 55 68 03",
    "sg:postcode":"28046",
    "sg:province":"Madrid",
    "wof:name":"Casas Y Locales S.a.",
    "wof:placetype":"venue"
},
  "geometry": {"coordinates":[-3.6914720535,40.4502182007],"type":"Point"}
}