{
  "type": "Feature",
  "properties": {
    "addr:full":"Calle de Sor Angela De La Cruz, 2 Moguer Huelva 21800",
    "addr:housenumber":"2",
    "addr:postcode":"21800",
    "addr:street":"Calle De Sor Angela De La Cruz",
    "iso:country":"ES",
    "sg:address":"Calle de Sor Angela De La Cruz, 2",
    "sg:city":"Moguer",
    "sg:orig_category":"Ropa Para Se\u00d1oras (al Por Menor)",
    "sg:phone":"+34 959 37 02 06",
    "sg:postcode":"21800",
    "sg:province":"Huelva",
    "wof:name":"Rodriguez-thorices Dominguez Patricia",
    "wof:placetype":"venue"
},
  "geometry": {"coordinates":[-6.837790966,37.2765884399],"type":"Point"}
}