{
  "type": "Feature",
  "properties": {
    "iso:country":"ES",
    "sg:address":"Rbla Egara, 273",
    "sg:city":"Terrassa",
    "sg:orig_category":"Librer\u00cdas",
    "sg:phone":"+34 937 88 71 88",
    "sg:postcode":"08224",
    "sg:province":"Barcelona",
    "wof:name":"Llibreria La Rambla S.c.p",
    "wof:placetype":"venue"
},
  "geometry": {"coordinates":[2.0071229935,41.5649261475],"type":"Point"}
}