{
  "type": "Feature",
  "properties": {
    "iso:country":"ES",
    "sg:address":"Carrer de Balmes, 208",
    "sg:city":"Barcelona",
    "sg:orig_category":"Internados & Ense\u00d1anza Privada",
    "sg:phone":"+34 932 17 86 12",
    "sg:postcode":"08006",
    "sg:province":"Barcelona",
    "wof:name":"Escola Pia Balmes",
    "wof:placetype":"venue"
},
  "geometry": {"coordinates":[2.1519010067,41.397731781],"type":"Point"}
}