{
  "type": "Feature",
  "properties": {
    "iso:country":"ES",
    "sg:address":"Calle de Camara La, 32",
    "sg:city":"Aviles",
    "sg:classifiers":[
        {
            "category":"Personal",
            "subcategory":"Barber",
            "type":"Services"
        }
    ],
    "sg:phone":"+34 985 56 43 35",
    "sg:postcode":"33402",
    "sg:province":"Asturias",
    "sg:tags":[
        "caballeros",
        "de",
        "peluqueros"
    ],
    "wof:name":"Rufino Solis Galan Y Otros Cb",
    "wof:placetype":"venue"
},
  "geometry": {"coordinates":[-5.9240159988,43.5571060181],"type":"Point"}
}