{
  "type": "Feature",
  "properties": {
    "iso:country":"ES",
    "sg:address":"Pase Doce Estrellas, 2",
    "sg:city":"Madrid",
    "sg:orig_category":"Inform\u00c1tica (estudios, Servicios, Asesor\u00cda, Formaci\u00d3n)",
    "sg:phone":"+34 917 21 06 02",
    "sg:postcode":"28042",
    "sg:province":"Madrid",
    "sg:website":"www.bull.es",
    "wof:name":"Bull Espa\u00f1a S.a.",
    "wof:placetype":"venue"
},
  "geometry": {"coordinates":[-3.6164829731,40.4613647461],"type":"Point"}
}