{
  "type": "Feature",
  "properties": {
    "iso:country":"ES",
    "sg:address":"Rio Ti\u00e9tar, 15",
    "sg:city":"Pedro Bernardo",
    "sg:orig_category":"Reposter\u00cdas",
    "sg:phone":"+34 920 38 73 13",
    "sg:postcode":"05470",
    "sg:province":"\u00c1vila",
    "wof:name":"Martinez Blazquez Joaquin",
    "wof:placetype":"venue"
},
  "geometry": {"coordinates":[-4.9132680893,40.2427902222],"type":"Point"}
}