{
  "type": "Feature",
  "properties": {
    "iso:country":"ES",
    "sg:address":"Calle de Gurutzegi, 11",
    "sg:city":"Donostia-san Sebastian",
    "sg:orig_category":"Ingenier\u00cda, Centros De Estudios (diversos)",
    "sg:phone":"+34 943 36 48 36",
    "sg:postcode":"20018",
    "sg:province":"Guip\u00f9zcoa",
    "wof:name":"Ingenieria Bost Mega S.l.",
    "wof:placetype":"venue"
},
  "geometry": {"coordinates":[-2.0116219521,43.2793197632],"type":"Point"}
}