{
  "type": "Feature",
  "properties": {
    "iso:country":"ES",
    "sg:address":"Avda Ruta De La Plata, 42",
    "sg:city":"Caceres",
    "sg:orig_category":"Arquitectos",
    "sg:phone":"+34 927 23 81 05",
    "sg:postcode":"10001",
    "sg:province":"C\u00e1ceres",
    "sg:website":"www.comprarcasa.com",
    "wof:name":"Barca Saez Asociados S.l.",
    "wof:placetype":"venue"
},
  "geometry": {"coordinates":[-6.3877391815,39.4711799622],"type":"Point"}
}