{
  "type": "Feature",
  "properties": {
    "addr:full":"M. Evaristo Churruca, S/n Portugalete Vizcaya 48920",
    "addr:housenumber":"s / n",
    "addr:postcode":"48920",
    "addr:street":"M. Evaristo Churruca",
    "iso:country":"ES",
    "sg:address":"M. Evaristo Churruca, S/n",
    "sg:city":"Portugalete",
    "sg:orig_category":"Piscinas (establecimientos)",
    "sg:phone":"+34 944 95 24 55",
    "sg:postcode":"48920",
    "sg:province":"Vizcaya",
    "wof:name":"Deportiva Municipal De Portugalete S. A.",
    "wof:placetype":"venue"
},
  "geometry": {"coordinates":[-3.0176839828,43.3219337463],"type":"Point"}
}