{
  "type": "Feature",
  "properties": {
    "iso:country":"ES",
    "sg:address":"Calle de Virgen (de La), 1",
    "sg:city":"Baltanas",
    "sg:orig_category":"Alimentaci\u00d3n General (al Por Menor)",
    "sg:phone":"+34 979 79 00 22",
    "sg:postcode":"34240",
    "sg:province":"Palencia",
    "wof:name":"Espina Fombellida Javier",
    "wof:placetype":"venue"
},
  "geometry": {"coordinates":[-4.2485389709,41.9345397949],"type":"Point"}
}