{
  "type": "Feature",
  "properties": {
    "addr:full":"Carrer de Manuel Aza\u00d1a, 3 Palma Islas Baleares 07006",
    "addr:housenumber":"3",
    "addr:postcode":"07006",
    "addr:street":"Carrer De Manuel Azan\u0303A",
    "iso:country":"ES",
    "sg:address":"Carrer de Manuel Aza\u00d1a, 3",
    "sg:city":"Palma",
    "sg:classifiers":[
        {
            "category":"Autos & Motor Vehicles",
            "subcategory":"Automobile Sales",
            "type":"Retail Goods"
        }
    ],
    "sg:phone":"+34 971 77 47 72",
    "sg:postcode":"07006",
    "sg:province":"Islas Baleares",
    "wof:name":"Autoescoles Confederades De Balears S.l.",
    "wof:placetype":"venue"
},
  "geometry": {"coordinates":[2.6636786461,39.5668029785],"type":"Point"}
}