{
  "type": "Feature",
  "properties": {
    "iso:country":"ES",
    "sg:address":"Av Pere Matutes Noguera, 80",
    "sg:city":"Eivissa",
    "sg:orig_category":"Abogados",
    "sg:phone":"+34 971 39 20 12",
    "sg:postcode":"07800",
    "sg:province":"Islas Baleares",
    "wof:name":"Planells Guasch Angela",
    "wof:placetype":"venue"
},
  "geometry": {"coordinates":[1.4097479582,38.8937187195],"type":"Point"}
}