{
  "type": "Feature",
  "properties": {
    "addr:full":"Calle de Valencia, S/n S. Isidro Alicante 03349",
    "addr:housenumber":"s",
    "addr:postcode":"03349",
    "addr:street":"Calle De Valencia;/ N S. Isidro Alicante",
    "iso:country":"ES",
    "sg:address":"Calle de Valencia, S/n",
    "sg:city":"S. Isidro",
    "sg:orig_category":"Aceites Y Grasas Alimentarias (fabricaci\u00d3n, Al Por Mayor)",
    "sg:phone":"+34 965 48 55 06",
    "sg:postcode":"03349",
    "sg:province":"Alicante",
    "wof:name":"Reserva Olivarera Del Sureste S.l.",
    "wof:placetype":"venue"
},
  "geometry": {"coordinates":[-0.8370940089,38.1786766052],"type":"Point"}
}