{
  "type": "Feature",
  "properties": {
    "iso:country":"ES",
    "sg:address":"Torre De Moncatar, S/n",
    "sg:city":"Ca\u00f1izal",
    "sg:orig_category":"Agricultura: Abastecimiento Y Cosechado (negocio)",
    "sg:phone":"+34 980 56 60 03",
    "sg:postcode":"49440",
    "sg:province":"Zamora",
    "wof:name":"Alvaro Ferrero Del Corral Y Otro C.b.",
    "wof:placetype":"venue"
},
  "geometry": {"coordinates":[-5.3730177879,41.1758651733],"type":"Point"}
}