{
  "type": "Feature",
  "properties": {
    "addr:full":"Avda Hercules, 96 Coru\u00d1a La Coru\u00f1a 15002",
    "addr:housenumber":"96",
    "addr:postcode":"15002",
    "addr:street":"Avda Hercules;Corun\u0303A",
    "iso:country":"ES",
    "sg:address":"Avda Hercules, 96",
    "sg:city":"Coru\u00d1a",
    "sg:orig_category":"Servicios Diversos",
    "sg:phone":"+34 981 22 99 06",
    "sg:postcode":"15002",
    "sg:province":"La Coru\u00f1a",
    "wof:name":"Comunidad De Propietarios Hercules 96",
    "wof:placetype":"venue"
},
  "geometry": {"coordinates":[-8.4036092758,43.3785133362],"type":"Point"}
}