{
  "type": "Feature",
  "properties": {
    "iso:country":"ES",
    "sg:address":"Av Sant Esteve, 7",
    "sg:city":"Castellar Valles",
    "sg:orig_category":"Bazares, Art\u00cdculos De Limpieza Y De Cocina (al Por Menor)",
    "sg:phone":"+34 937 47 23 12",
    "sg:postcode":"08211",
    "sg:province":"Barcelona",
    "wof:name":"Dayun  Wang",
    "wof:placetype":"venue"
},
  "geometry": {"coordinates":[2.0867578983,41.6132087708],"type":"Point"}
}