{
  "type": "Feature",
  "properties": {
    "addr:full":"Ctra. Loeches-torrejon Ardoz, Km. 0015,7 Loeches Madrid 28890",
    "addr:postcode":"28890",
    "addr:street":"Ctra. Loeches-Torrejon Ardoz Km. 0015,7",
    "iso:country":"ES",
    "sg:address":"Ctra. Loeches-torrejon Ardoz, Km. 0015,7",
    "sg:city":"Loeches",
    "sg:orig_category":"Ferreter\u00cda (diversos)",
    "sg:phone":"+34 918 86 20 75",
    "sg:postcode":"28890",
    "sg:province":"Madrid",
    "wof:name":"Pretensados Y Armados Para La Construcci",
    "wof:placetype":"venue"
},
  "geometry": {"coordinates":[-3.4122691154,40.3848457336],"type":"Point"}
}