{
  "type": "Feature",
  "properties": {
    "iso:country":"ES",
    "sg:address":"Avda Taramundi, 11",
    "sg:city":"Vegadeo",
    "sg:orig_category":"Ropa Para Se\u00d1oras (al Por Menor)",
    "sg:phone":"+34 985 63 45 45",
    "sg:postcode":"33770",
    "sg:province":"Asturias",
    "wof:name":"Abuin Sanjulian Pilar",
    "wof:placetype":"venue"
},
  "geometry": {"coordinates":[-7.050078,43.463409],"type":"Point"}
}