{
  "type": "Feature",
  "properties": {
    "addr:full":"Avgd Alameda Jaume I, 17 Xativa Valencia 46800",
    "addr:housenumber":"17",
    "addr:postcode":"46800",
    "addr:street":"Alameda Jaume I",
    "iso:country":"ES",
    "sg:address":"Avgd Alameda Jaume I, 17",
    "sg:city":"Xativa",
    "sg:orig_category":"Ense\u00d1anza: Idiomas",
    "sg:phone":"+34 962 28 06 33",
    "sg:postcode":"46800",
    "sg:province":"Valencia",
    "wof:name":"Baillie  Darren Lee",
    "wof:placetype":"venue"
},
  "geometry": {"coordinates":[-0.5237929821,38.9893226624],"type":"Point"}
}