{
  "type": "Feature",
  "properties": {
    "addr:full":"Mercado De Abastos, S/n Aspe Alicante 03680",
    "addr:housenumber":"s / n",
    "addr:postcode":"03680",
    "iso:country":"ES",
    "sg:address":"Mercado De Abastos, S/n",
    "sg:city":"Aspe",
    "sg:orig_category":"Carnicer\u00cdas, Carnicer\u00cdas",
    "sg:phone":"+34 965 49 14 31",
    "sg:postcode":"03680",
    "sg:province":"Alicante",
    "wof:name":"Galva\u00f1 Puerto Vicente",
    "wof:placetype":"venue"
},
  "geometry": {"coordinates":[-0.7747089863,38.3399810791],"type":"Point"}
}