{
  "type": "Feature",
  "properties": {
    "iso:country":"ES",
    "sg:address":"Calle de Alcantara, 49",
    "sg:city":"Madrid",
    "sg:orig_category":"Caf\u00c9s, Bares, Cervecer\u00cdas",
    "sg:phone":"+34 914 01 28 96",
    "sg:postcode":"28006",
    "sg:province":"Madrid",
    "wof:name":"Gomez Sanz Juan Jose",
    "wof:placetype":"venue"
},
  "geometry": {"coordinates":[-3.6736307144,40.4306907654],"type":"Point"}
}