{
  "type": "Feature",
  "properties": {
    "iso:country":"ES",
    "sg:address":"Carrer de Rafael Rodriguez M, 5",
    "sg:city":"Palma",
    "sg:orig_category":"Abogados",
    "sg:phone":"+34 971 28 54 17",
    "sg:postcode":"07011",
    "sg:province":"Islas Baleares",
    "wof:name":"Covas Vidal Juan Francisco",
    "wof:placetype":"venue"
},
  "geometry": {"coordinates":[2.642414093,39.5765266418],"type":"Point"}
}