{
  "type": "Feature",
  "properties": {
    "iso:country":"ES",
    "sg:address":"Carrer de Perez Galdos, 47",
    "sg:city":"Barcelona",
    "sg:orig_category":"Fabricaci\u00d3n, Importaci\u00d3n De L\u00c1mparas Y Bombillas",
    "sg:phone":"+34 934 15 05 63",
    "sg:postcode":"08012",
    "sg:province":"Barcelona",
    "wof:name":"Luque Gonzalez Antonio",
    "wof:placetype":"venue"
},
  "geometry": {"coordinates":[2.1507589817,41.4066772461],"type":"Point"}
}