{
  "type": "Feature",
  "properties": {
    "iso:country":"ES",
    "sg:address":"Calle de Doctor Alejandro Garcia, 25",
    "sg:city":"Utiel",
    "sg:orig_category":"Organizaci\u00d3n De Actos, Seminarios Y Congresos",
    "sg:phone":"+34 962 17 44 39",
    "sg:postcode":"46300",
    "sg:province":"Valencia",
    "wof:name":"Servicios Hoteleros Reyes Catolicos S.a",
    "wof:placetype":"venue"
},
  "geometry": {"coordinates":[-1.2026690245,39.5653114319],"type":"Point"}
}