{
  "type": "Feature",
  "properties": {
    "iso:country":"ES",
    "sg:address":"Carrer de Muntaner, 239",
    "sg:city":"Barcelona",
    "sg:orig_category":"Notarios",
    "sg:phone":"+34 932 38 43 30",
    "sg:postcode":"08021",
    "sg:province":"Barcelona",
    "wof:name":"Valverde Garcia Lorenzo",
    "wof:placetype":"venue"
},
  "geometry": {"coordinates":[2.1486930847,41.3945617676],"type":"Point"}
}