{
  "type": "Feature",
  "properties": {
    "addr:full":"Calle de Rusia, 30 Torre-pacheco Murcia 30700",
    "addr:housenumber":"30",
    "addr:postcode":"30700",
    "addr:street":"Calle De Rusia",
    "iso:country":"ES",
    "sg:address":"Calle de Rusia, 30",
    "sg:city":"Torre-pacheco",
    "sg:orig_category":"Suministros Y Materiales Industriales",
    "sg:phone":"+34 968 33 63 24",
    "sg:postcode":"30700",
    "sg:province":"Murcia",
    "wof:name":"Suministros Manolo S.l.",
    "wof:placetype":"venue"
},
  "geometry": {"coordinates":[-0.9433124065,37.7364883423],"type":"Point"}
}