{
  "type": "Feature",
  "properties": {
    "iso:country":"ES",
    "sg:address":"Plzla. De Pati\u00f1o, 6",
    "sg:city":"Chiclana",
    "sg:orig_category":"Zapatos (al Por Menor)",
    "sg:phone":"+34 956 40 18 46",
    "sg:postcode":"11130",
    "sg:province":"C\u00e1diz",
    "wof:name":"Diaz Peri\u00f1an Federico",
    "wof:placetype":"venue"
},
  "geometry": {"coordinates":[-6.1447038651,36.4212188721],"type":"Point"}
}