{
  "type": "Feature",
  "properties": {
    "iso:country":"ES",
    "sg:address":"Calle de De Las Eras, 9",
    "sg:city":"Aldeamayor S. Martin",
    "sg:orig_category":"Promotores Constructores",
    "sg:phone":"+34 983 55 84 95",
    "sg:postcode":"47162",
    "sg:province":"Valladolid",
    "wof:name":"Construcciones El Tablao S.l.",
    "wof:placetype":"venue"
},
  "geometry": {"coordinates":[-4.6420454979,41.5197753906],"type":"Point"}
}