{
  "type": "Feature",
  "properties": {
    "iso:country":"ES",
    "sg:address":"Pase San Julian, 6",
    "sg:city":"Najera",
    "sg:orig_category":"Institutos De Belleza",
    "sg:phone":"+34 941 36 36 08",
    "sg:postcode":"26300",
    "sg:province":"La Rioja",
    "wof:name":"Martinez Iba\u00f1ez Maria Blanca",
    "wof:placetype":"venue"
},
  "geometry": {"coordinates":[-2.7312951088,42.4155693054],"type":"Point"}
}