{
  "type": "Feature",
  "properties": {
    "addr:full":"Calle de Esteban Palacios, 6 Madrid Madrid 28043",
    "addr:housenumber":"6",
    "addr:postcode":"28043",
    "addr:street":"Calle De Esteban Palacios",
    "iso:country":"ES",
    "sg:address":"Calle de Esteban Palacios, 6",
    "sg:city":"Madrid",
    "sg:orig_category":"Asesor\u00cda Sobre Comunicaci\u00d3n De Empresas",
    "sg:phone":"+34 917 21 98 16",
    "sg:postcode":"28043",
    "sg:province":"Madrid",
    "wof:name":"Gomez-acebo Llanes International Group S.l.",
    "wof:placetype":"venue"
},
  "geometry": {"coordinates":[-3.6234717369,40.4581832886],"type":"Point"}
}