{
  "type": "Feature",
  "properties": {
    "addr:full":"Calle de A (poligono Industrial La Dehesa), 43 Hinojosa Del Duque C\u00f3rdoba 14270",
    "addr:housenumber":"43",
    "addr:postcode":"14270",
    "addr:street":"Calle De A Poligono Industrial La Dehesa;Co\u0301Rdoba",
    "iso:country":"ES",
    "sg:address":"Calle de A (poligono Industrial La Dehesa), 43",
    "sg:city":"Hinojosa Del Duque",
    "sg:orig_category":"Carnicer\u00cdas, Carnicer\u00cdas",
    "sg:phone":"+34 957 14 31 57",
    "sg:postcode":"14270",
    "sg:province":"C\u00f3rdoba",
    "wof:name":"Bravo Gonzalez Jesus",
    "wof:placetype":"venue"
},
  "geometry": {"coordinates":[-5.1483325958,38.5009918213],"type":"Point"}
}