{
  "type": "Feature",
  "properties": {
    "iso:country":"ES",
    "sg:address":"Calle de Rosario, 2",
    "sg:city":"Albacete",
    "sg:orig_category":"Ropa Para Se\u00d1oras (al Por Menor)",
    "sg:phone":"+34 967 21 68 26",
    "sg:postcode":"02001",
    "sg:province":"Albacete",
    "sg:website":"www.induyco.es/sintesis",
    "wof:name":"Valcarcel Gomez Luis",
    "wof:placetype":"venue"
},
  "geometry": {"coordinates":[-1.8552720547,38.9956626892],"type":"Point"}
}