{
  "type": "Feature",
  "properties": {
    "iso:country":"ES",
    "sg:address":"Carrer de Montblanc, 41",
    "sg:city":"Vilafranca Penedes",
    "sg:orig_category":"Complementos De Vestir (al Por Menor)",
    "sg:phone":"+34 938 17 28 82",
    "sg:postcode":"08720",
    "sg:province":"Barcelona",
    "wof:name":"Detalles Y Complementos Fusta S.l.",
    "wof:placetype":"venue"
},
  "geometry": {"coordinates":[1.6970440149,41.3390350342],"type":"Point"}
}