{
  "type": "Feature",
  "properties": {
    "addr:full":"Panta S. Antoni, S/n Tremp Lleida 25620",
    "addr:housenumber":"/ n",
    "addr:postcode":"25620",
    "addr:street":"Panta;Antoni S",
    "iso:country":"ES",
    "sg:address":"Panta S. Antoni, S/n",
    "sg:city":"Tremp",
    "sg:orig_category":"Zonas De Acampada, Aparcamiento Para Caravanas",
    "sg:phone":"+34 973 65 07 37",
    "sg:postcode":"25620",
    "sg:province":"Lleida",
    "wof:name":"Gaset Gomez Jose",
    "wof:placetype":"venue"
},
  "geometry": {"coordinates":[0.8948950171,42.1686935425],"type":"Point"}
}