{
  "type": "Feature",
  "properties": {
    "addr:full":"Avd Poeta M. Reina, 11 Puente-genil C\u00f3rdoba 14500",
    "addr:housenumber":"11",
    "addr:postcode":"14500",
    "addr:street":"Avd Poeta M. Reina;Co\u0301Rdoba",
    "iso:country":"ES",
    "sg:address":"Avd Poeta M. Reina, 11",
    "sg:city":"Puente-genil",
    "sg:orig_category":"Confecci\u00d3n (fabricaci\u00d3n, Al Por Mayor)",
    "sg:phone":"+34 957 60 45 02",
    "sg:postcode":"14500",
    "sg:province":"C\u00f3rdoba",
    "wof:name":"Jurado Genil Maria Jose Fabiola",
    "wof:placetype":"venue"
},
  "geometry": {"coordinates":[-4.7680630684,37.3911743164],"type":"Point"}
}