{
  "type": "Feature",
  "properties": {
    "addr:full":"Calle de Badajoz, 9 Villafranca De Los Barros Badajoz 06220",
    "addr:housenumber":"9",
    "addr:postcode":"06220",
    "addr:street":"Calle De Badajoz",
    "iso:country":"ES",
    "sg:address":"Calle de Badajoz, 9",
    "sg:city":"Villafranca De Los Barros",
    "sg:orig_category":"Mec\u00c1nico Del Autom\u00d3vil",
    "sg:phone":"+34 924 52 38 48",
    "sg:postcode":"06220",
    "sg:province":"Badajoz",
    "wof:name":"Automocion Todoauto S.l.",
    "wof:placetype":"venue"
},
  "geometry": {"coordinates":[-6.3455343246,38.5643424988],"type":"Point"}
}