{
  "type": "Feature",
  "properties": {
    "addr:full":"Calle de Justiniano, 1 Madrid Madrid 28004",
    "addr:housenumber":"1",
    "addr:postcode":"28004",
    "addr:street":"Calle De Justiniano",
    "iso:country":"ES",
    "sg:address":"Calle de Justiniano, 1",
    "sg:city":"Madrid",
    "sg:orig_category":"Arquitectos",
    "sg:phone":"+34 913 91 00 78",
    "sg:postcode":"28004",
    "sg:province":"Madrid",
    "wof:name":"Gomez Ortu\u00f1o Jesus",
    "wof:placetype":"venue"
},
  "geometry": {"coordinates":[-3.6955049038,40.4257545471],"type":"Point"}
}