{
  "type": "Feature",
  "properties": {
    "iso:country":"ES",
    "sg:address":"Disseminat, S/n",
    "sg:city":"Polinya",
    "sg:orig_category":"Agricultores, Agricultores",
    "sg:phone":"+34 937 13 32 12",
    "sg:postcode":"08213",
    "sg:province":"Barcelona",
    "wof:name":"Pladevall Prims Antonio",
    "wof:placetype":"venue"
},
  "geometry": {"coordinates":[2.157804966,41.5574531555],"type":"Point"}
}