{
  "type": "Feature",
  "properties": {
    "iso:country":"ES",
    "sg:address":"Pase San Illan, 39",
    "sg:city":"Madrid",
    "sg:orig_category":"Suministros Para Hoteles",
    "sg:phone":"+34 914 69 30 40",
    "sg:postcode":"28019",
    "sg:province":"Madrid",
    "wof:name":"Jemasat S. A.",
    "wof:placetype":"venue"
},
  "geometry": {"coordinates":[-3.7222049236,40.3998756409],"type":"Point"}
}