{
  "type": "Feature",
  "properties": {
    "addr:full":"Calle de Rio Segura, 14 Mostoles Madrid 28935",
    "addr:housenumber":"14",
    "addr:postcode":"28935",
    "addr:street":"Calle De Rio Segura",
    "iso:country":"ES",
    "sg:address":"Calle de Rio Segura, 14",
    "sg:city":"Mostoles",
    "sg:orig_category":"Inmobiliaria (agencias)",
    "sg:phone":"+34 916 85 23 46",
    "sg:postcode":"28935",
    "sg:province":"Madrid",
    "wof:name":"Centro Inmobiliario Casmar S.l.",
    "wof:placetype":"venue"
},
  "geometry": {"coordinates":[-3.8773450851,40.3147697449],"type":"Point"}
}