{
  "type": "Feature",
  "properties": {
    "addr:full":"Calle de Mezquides, 4 Aduanas Alicante 03730",
    "addr:housenumber":"4",
    "addr:postcode":"03730",
    "addr:street":"Calle De Mezquides",
    "iso:country":"ES",
    "sg:address":"Calle de Mezquides, 4",
    "sg:city":"Aduanas",
    "sg:orig_category":"Ense\u00d1anza, Formaci\u00d3n Profesional: Aprendizaje",
    "sg:phone":"+34 965 79 32 23",
    "sg:postcode":"03730",
    "sg:province":"Alicante",
    "wof:name":"Ayuntamiento De Javea",
    "wof:placetype":"venue"
},
  "geometry": {"coordinates":[0.1784244031,38.796005249],"type":"Point"}
}