{
  "type": "Feature",
  "properties": {
    "iso:country":"ES",
    "sg:address":"Ctra General, S/n",
    "sg:city":"San Mateo",
    "sg:orig_category":"Cr\u00cda De Animales",
    "sg:phone":"+34 942 83 13 36",
    "sg:postcode":"39408",
    "sg:province":"Cantabria",
    "wof:name":"Ribao Fernandez Jose",
    "wof:placetype":"venue"
},
  "geometry": {"coordinates":[-4.0770049095,43.279712677],"type":"Point"}
}