{
  "type": "Feature",
  "properties": {
    "iso:country":"ES",
    "sg:address":"Pg Valldaura, 172",
    "sg:city":"Barcelona",
    "sg:orig_category":"Mec\u00c1nico Del Autom\u00d3vil",
    "sg:phone":"+34 932 76 51 34",
    "sg:postcode":"08042",
    "sg:province":"Barcelona",
    "wof:name":"Fernandez Sanchez Luis",
    "wof:placetype":"venue"
},
  "geometry": {"coordinates":[2.1682479382,41.4389419556],"type":"Point"}
}