{
  "type": "Feature",
  "properties": {
    "iso:country":"ES",
    "sg:address":"Calle de Carrera Chica, 9",
    "sg:city":"Villafranca De Los Barros",
    "sg:orig_category":"Bisuter\u00cda, Joyer\u00cda, Relojer\u00cda (al Por Menor)",
    "sg:phone":"+34 924 52 48 70",
    "sg:postcode":"06220",
    "sg:province":"Badajoz",
    "wof:name":"Rodriguez Morales Jose",
    "wof:placetype":"venue"
},
  "geometry": {"coordinates":[-6.3415212631,38.5607299805],"type":"Point"}
}