{
  "type": "Feature",
  "properties": {
    "iso:country":"ES",
    "sg:address":"Calle de Amezketa De Los, 11",
    "sg:city":"Donostia-san Sebastian",
    "sg:orig_category":"Art\u00cdculos De Decoraci\u00d3n",
    "sg:phone":"+34 943 46 58 52",
    "sg:postcode":"20010",
    "sg:province":"Guip\u00f9zcoa",
    "wof:name":"Oleaga Zufiria Maria Luisa",
    "wof:placetype":"venue"
},
  "geometry": {"coordinates":[-1.98090446,43.3036422729],"type":"Point"}
}