{
  "type": "Feature",
  "properties": {
    "iso:country":"ES",
    "sg:address":"Calle de Mayor, 15",
    "sg:city":"Guadalajara",
    "sg:orig_category":"Asesor\u00cda De Formaci\u00d3n Y Gesti\u00d3n De Personal",
    "sg:phone":"+34 949 21 36 64",
    "sg:postcode":"19001",
    "sg:province":"Guadalajara",
    "wof:name":"Lopez Escamilla Luis Alberto",
    "wof:placetype":"venue"
},
  "geometry": {"coordinates":[-3.1661839485,40.6331291199],"type":"Point"}
}