{
  "type": "Feature",
  "properties": {
    "iso:country":"ES",
    "sg:address":"Calle de San Pancracio, S/n",
    "sg:city":"Fuengirola",
    "sg:orig_category":"Promotores Constructores",
    "sg:phone":"+34 952 47 63 37",
    "sg:postcode":"29640",
    "sg:province":"M\u00e1laga",
    "wof:name":"Fraframa S.a.",
    "wof:placetype":"venue"
},
  "geometry": {"coordinates":[-4.6242041588,36.5402755737],"type":"Point"}
}