{
  "type": "Feature",
  "properties": {
    "iso:country":"ES",
    "sg:address":"Calle de Antonio Lopez, 30",
    "sg:city":"Santander",
    "sg:orig_category":"Agencias De Aduana",
    "sg:phone":"+34 942 22 79 43",
    "sg:postcode":"39009",
    "sg:province":"Cantabria",
    "wof:name":"Lopez Corral Felix",
    "wof:placetype":"venue"
},
  "geometry": {"coordinates":[-3.8113186359,43.4559707642],"type":"Point"}
}