{
  "type": "Feature",
  "properties": {
    "addr:full":"Calle de San Juan Bosco, 21 Archena Murcia 30600",
    "addr:housenumber":"21",
    "addr:postcode":"30600",
    "addr:street":"Calle De San Juan Bosco",
    "iso:country":"ES",
    "sg:address":"Calle de San Juan Bosco, 21",
    "sg:city":"Archena",
    "sg:orig_category":"Aparatos E Instalaci\u00d3n De Regad\u00cdos",
    "sg:phone":"+34 968 67 30 54",
    "sg:postcode":"30600",
    "sg:province":"Murcia",
    "wof:name":"Sociedad Agraria De Transformacion Num. 7432 Los Rodeos",
    "wof:placetype":"venue"
},
  "geometry": {"coordinates":[-1.2979520559,38.114692688],"type":"Point"}
}