{
  "type": "Feature",
  "properties": {
    "addr:full":"Calle de Cami Real, 38 Sagunt Valencia 46500",
    "addr:housenumber":"38",
    "addr:postcode":"46500",
    "addr:street":"Calle De;Real",
    "iso:country":"ES",
    "sg:address":"Calle de Cami Real, 38",
    "sg:city":"Sagunt",
    "sg:orig_category":"Caf\u00c9s, Bares, Cervecer\u00cdas",
    "sg:phone":"+34 962 66 51 38",
    "sg:postcode":"46500",
    "sg:province":"Valencia",
    "sg:website":"www.larmeler.com",
    "wof:name":"Palacios Fernandez Laura",
    "wof:placetype":"venue"
},
  "geometry": {"coordinates":[-0.2765288949,39.6796455383],"type":"Point"}
}