{
  "type": "Feature",
  "properties": {
    "addr:full":"Carrer de Pere Dezcallar I Net, 13 Islas Baleares 07003",
    "addr:postcode":"07003",
    "addr:street":"Carrer De Pere Dezcallar;Net;Islas",
    "iso:country":"ES",
    "sg:address":"Carrer de Pere Dezcallar I Net, 13",
    "sg:orig_category":"Sociedades, Compa\u00d1\u00cdas Aseguradoras",
    "sg:phone":"+34 971 72 12 99",
    "sg:postcode":"07003",
    "sg:province":"Islas Baleares",
    "wof:name":"Jodar Jodar Barbara",
    "wof:placetype":"venue"
},
  "geometry": {"coordinates":[2.6494801044,39.5768623352],"type":"Point"}
}