{
  "type": "Feature",
  "properties": {
    "addr:full":"Calle de Encomienda, 4 Madrid Madrid 28012",
    "addr:housenumber":"4",
    "addr:postcode":"28012",
    "addr:street":"Calle De Encomienda",
    "iso:country":"ES",
    "sg:address":"Calle de Encomienda, 4",
    "sg:city":"Madrid",
    "sg:orig_category":"Bazares, Art\u00cdculos De Limpieza Y De Cocina (al Por Menor)",
    "sg:phone":"+34 915 39 50 22",
    "sg:postcode":"28012",
    "sg:province":"Madrid",
    "wof:name":"Wang  Shao Guan",
    "wof:placetype":"venue"
},
  "geometry": {"coordinates":[-3.7050154209,40.4109153748],"type":"Point"}
}