{
  "type": "Feature",
  "properties": {
    "addr:full":"Ctra Teulada-benimarco, 94 Benissa Alicante 03720",
    "addr:housenumber":"94",
    "addr:postcode":"03720",
    "addr:street":"Ctra Teulada-Benimarco",
    "iso:country":"ES",
    "sg:address":"Ctra Teulada-benimarco, 94",
    "sg:city":"Benissa",
    "sg:orig_category":"Electricidad: Instaladores",
    "sg:phone":"+34 966 49 84 56",
    "sg:postcode":"03720",
    "sg:province":"Alicante",
    "wof:name":"Judoblas",
    "wof:placetype":"venue"
},
  "geometry": {"coordinates":[0.050774999,38.7144584656],"type":"Point"}
}