{
  "type": "Feature",
  "properties": {
    "addr:full":"Avda Antonio Mairena, 10 Alcala Guadaira Sevilla 41500",
    "addr:housenumber":"10",
    "addr:postcode":"41500",
    "addr:street":"Avda Antonio Mairena",
    "iso:country":"ES",
    "sg:address":"Avda Antonio Mairena, 10",
    "sg:city":"Alcala Guadaira",
    "sg:orig_category":"Servicio De Salud",
    "sg:phone":"+34 955 68 70 40",
    "sg:postcode":"41500",
    "sg:province":"Sevilla",
    "wof:name":"Cristalerias Del Guadaira S.l.",
    "wof:placetype":"venue"
},
  "geometry": {"coordinates":[-5.8404340744,37.3373947144],"type":"Point"}
}