{
  "type": "Feature",
  "properties": {
    "iso:country":"ES",
    "sg:address":"Pl Major, 16",
    "sg:city":"Montblanc",
    "sg:orig_category":"Carnicer\u00cdas, Carnicer\u00cdas",
    "sg:phone":"+34 977 86 00 95",
    "sg:postcode":"43400",
    "sg:province":"Tarragona",
    "wof:name":"Soler Maideu Joan",
    "wof:placetype":"venue"
},
  "geometry": {"coordinates":[1.1613160372,41.376499176],"type":"Point"}
}