{
  "type": "Feature",
  "properties": {
    "iso:country":"ES",
    "sg:address":"Espunyola, 28",
    "sg:city":"Oliana",
    "sg:orig_category":"Transportes De Material De Construcci\u00d3n",
    "sg:phone":"+34 973 46 30 25",
    "sg:postcode":"25790",
    "sg:province":"Lleida",
    "wof:name":"Lluch Balague Jaime",
    "wof:placetype":"venue"
},
  "geometry": {"coordinates":[1.3102560043,42.0727043152],"type":"Point"}
}