{
  "type": "Feature",
  "properties": {
    "addr:full":"Luga Laxas (as), S/n Irixo Ourense 32530",
    "addr:housenumber":"/ n",
    "addr:postcode":"32530",
    "addr:street":"S",
    "iso:country":"ES",
    "sg:address":"Luga Laxas (as), S/n",
    "sg:city":"Irixo",
    "sg:orig_category":"Carnicer\u00cdas, Carnicer\u00cdas",
    "sg:phone":"+34 988 28 75 79",
    "sg:postcode":"32530",
    "sg:province":"Ourense",
    "wof:name":"Ferradas Covelo Antonio",
    "wof:placetype":"venue"
},
  "geometry": {"coordinates":[-8.1125917435,42.5129394531],"type":"Point"}
}