{
  "type": "Feature",
  "properties": {
    "iso:country":"ES",
    "sg:address":"Avda Industria (la), 12",
    "sg:city":"Sevilla",
    "sg:orig_category":"Material Y Herramientas Agr\u00cdcolas",
    "sg:phone":"+34 954 51 15 44",
    "sg:postcode":"41007",
    "sg:province":"Sevilla",
    "wof:name":"Tenias S.a.",
    "wof:placetype":"venue"
},
  "geometry": {"coordinates":[-5.9515109062,37.3882255554],"type":"Point"}
}