{
  "type": "Feature",
  "properties": {
    "addr:full":"Avda Industria (la), 11 Sevilla Sevilla 41007",
    "addr:housenumber":"11",
    "addr:postcode":"41007",
    "addr:street":"Avda Industria La",
    "iso:country":"ES",
    "sg:address":"Avda Industria (la), 11",
    "sg:city":"Sevilla",
    "sg:orig_category":"Asistencia Social",
    "sg:phone":"+34 954 99 94 80",
    "sg:postcode":"41007",
    "sg:province":"Sevilla",
    "wof:name":"Remar Espa\u00f1a",
    "wof:placetype":"venue"
},
  "geometry": {"coordinates":[-5.9568090439,37.3887901306],"type":"Point"}
}