{
  "type": "Feature",
  "properties": {
    "addr:full":"Calle de Carpinteros, S/n Poligono Industrial Alicante 03130",
    "addr:housenumber":"s",
    "addr:postcode":"03130",
    "addr:street":"Calle De Carpinteros;/ N;Industrial Alicante",
    "iso:country":"ES",
    "sg:address":"Calle de Carpinteros, S/n",
    "sg:city":"Poligono Industrial",
    "sg:orig_category":"Carb\u00d3n, Carb\u00d3n De Madera (al Por Mayor)",
    "sg:phone":"+34 966 69 03 70",
    "sg:postcode":"03130",
    "sg:province":"Alicante",
    "wof:name":"Tarmac Iberia S.a.u.",
    "wof:placetype":"venue"
},
  "geometry": {"coordinates":[-0.5565090179,38.190448761],"type":"Point"}
}