{
  "type": "Feature",
  "properties": {
    "addr:full":"Calle de Antonia Rodriguez Sacristan, 41 Madrid Madrid 28044",
    "addr:housenumber":"41",
    "addr:postcode":"madrid;28044",
    "addr:street":"Calle De Antonia Rodriguez Sacristan",
    "iso:country":"ES",
    "sg:address":"Calle de Antonia Rodriguez Sacristan, 41",
    "sg:city":"Madrid",
    "sg:orig_category":"Inmobiliaria (agencias)",
    "sg:phone":"+34 915 25 84 77",
    "sg:postcode":"28044",
    "sg:province":"Madrid",
    "wof:name":"Gonzalez Vaquero Gonzalo",
    "wof:placetype":"venue"
},
  "geometry": {"coordinates":[-3.7445006371,40.3727645874],"type":"Point"}
}