{
  "type": "Feature",
  "properties": {
    "addr:full":"Carrer de Historiador Cardus, 93 Terrassa Barcelona 08226",
    "addr:housenumber":"93",
    "addr:postcode":"08226",
    "addr:street":"Carrer De Historiador Cardus",
    "iso:country":"ES",
    "sg:address":"Carrer de Historiador Cardus, 93",
    "sg:city":"Terrassa",
    "sg:orig_category":"Institutos De Belleza",
    "sg:phone":"+34 937 31 06 75",
    "sg:postcode":"08226",
    "sg:province":"Barcelona",
    "wof:name":"Ortiz Mata Montse",
    "wof:placetype":"venue"
},
  "geometry": {"coordinates":[2.0227780342,41.5750999451],"type":"Point"}
}