{
  "type": "Feature",
  "properties": {
    "iso:country":"ES",
    "sg:address":"Calle de Maestro Azorin, 16",
    "sg:city":"Albatera",
    "sg:orig_category":"Quincaller\u00cda (al Por Menor)",
    "sg:phone":"+34 965 48 82 13",
    "sg:postcode":"03340",
    "sg:province":"Alicante",
    "wof:name":"Juan Berna Avelino",
    "wof:placetype":"venue"
},
  "geometry": {"coordinates":[-0.8669530153,38.1807098389],"type":"Point"}
}