{
  "type": "Feature",
  "properties": {
    "iso:country":"ES",
    "sg:address":"Carrer de Julio Cortazar, 14",
    "sg:city":"Castell Bendinat",
    "sg:orig_category":"Electricidad: Instaladores",
    "sg:phone":"+34 971 70 13 78",
    "sg:postcode":"07181",
    "sg:province":"Islas Baleares",
    "sg:website":"www.monclusasociados.com",
    "wof:name":"Monclus Y Asociados S.l.",
    "wof:placetype":"venue"
},
  "geometry": {"coordinates":[2.5352098942,39.5245780945],"type":"Point"}
}