{
  "type": "Feature",
  "properties": {
    "addr:full":"Carrer de Blesa, 24 Barcelona Barcelona 08004",
    "addr:housenumber":"24",
    "addr:postcode":"08004",
    "addr:street":"Carrer De Blesa",
    "iso:country":"ES",
    "sg:address":"Carrer de Blesa, 24",
    "sg:city":"Barcelona",
    "sg:orig_category":"Albergues",
    "sg:phone":"+34 934 41 61 91",
    "sg:postcode":"08004",
    "sg:province":"Barcelona",
    "wof:name":"Barna Gadgets S. A.",
    "wof:placetype":"venue"
},
  "geometry": {"coordinates":[2.1675000191,41.3725395203],"type":"Point"}
}