{
  "type": "Feature",
  "properties": {
    "addr:full":"Rulador, 1 Cuevas Almanzora Almer\u00eda 04610",
    "addr:housenumber":"1",
    "addr:postcode":"04610",
    "addr:street":"Rulador;Almeri\u0301A",
    "iso:country":"ES",
    "sg:address":"Rulador, 1",
    "sg:city":"Cuevas Almanzora",
    "sg:orig_category":"Frutas Y Legumbres Frescas (al Por Mayor)",
    "sg:phone":"+34 950 45 61 98",
    "sg:postcode":"04610",
    "sg:province":"Almer\u00eda",
    "wof:name":"Sanchez Lopez Andres",
    "wof:placetype":"venue"
},
  "geometry": {"coordinates":[-1.8831189871,37.2955703735],"type":"Point"}
}