{
  "type": "Feature",
  "properties": {
    "iso:country":"ES",
    "sg:address":"Calle de Luis Velez De Guevara, 7",
    "sg:city":"Madrid",
    "sg:orig_category":"Encuadernaci\u00d3n E Impresi\u00d3n De Folletos",
    "sg:phone":"+34 913 69 42 29",
    "sg:postcode":"28012",
    "sg:province":"Madrid",
    "wof:name":"Curtidos Divigar S. A.",
    "wof:placetype":"venue"
},
  "geometry": {"coordinates":[-3.7022540569,40.4129600525],"type":"Point"}
}