{
  "type": "Feature",
  "properties": {
    "iso:country":"ES",
    "sg:address":"Calle de Alicante, 7",
    "sg:city":"Barrio De La Vega",
    "sg:orig_category":"Droguer\u00cdas (al Por Menor)",
    "sg:phone":"+34 958 50 09 94",
    "sg:postcode":"18193",
    "sg:province":"Granada",
    "wof:name":"Distribuciones Monachil J.r S.l.",
    "wof:placetype":"venue"
},
  "geometry": {"coordinates":[-3.5585474968,37.1341094971],"type":"Point"}
}