{
  "type": "Feature",
  "properties": {
    "iso:country":"ES",
    "sg:address":"Carrer de Conveni, 49",
    "sg:city":"Barcelona",
    "sg:orig_category":"Aparatos, Sistemas De Tele",
    "sg:phone":"+34 933 53 55 09",
    "sg:postcode":"08016",
    "sg:province":"Barcelona",
    "wof:name":"M.p. Sistemas De Seguridad S.l.",
    "wof:placetype":"venue"
},
  "geometry": {"coordinates":[2.1834909916,41.4435119629],"type":"Point"}
}