{
  "type": "Feature",
  "properties": {
    "iso:country":"ES",
    "sg:address":"Ctra Nacional Iia, S/n",
    "sg:city":"Figueres",
    "sg:orig_category":"Librer\u00cdas",
    "sg:phone":"+34 972 50 13 73",
    "sg:postcode":"17600",
    "sg:province":"Girona",
    "wof:name":"Guerrero Alemany Marc",
    "wof:placetype":"venue"
},
  "geometry": {"coordinates":[2.9581100941,42.2656898499],"type":"Point"}
}