{
  "type": "Feature",
  "properties": {
    "addr:full":"Ctra. Mojados-aldea De San Miguel, S/n Portillo Valladolid 47160",
    "addr:housenumber":"s / n",
    "addr:postcode":"47160",
    "addr:street":"Ctra. Mojados-Aldea De San Miguel",
    "iso:country":"ES",
    "sg:address":"Ctra. Mojados-aldea De San Miguel, S/n",
    "sg:city":"Portillo",
    "sg:orig_category":"Alimentaci\u00d3n General (al Por Mayor)",
    "sg:phone":"+34 983 55 61 06",
    "sg:postcode":"47160",
    "sg:province":"Valladolid",
    "wof:name":"Iberica De Tecnologia Avicola S.a.",
    "wof:placetype":"venue"
},
  "geometry": {"coordinates":[-4.5854678154,41.4795455933],"type":"Point"}
}