{
  "type": "Feature",
  "properties": {
    "iso:country":"ES",
    "sg:address":"Calle de San Francisco, 16",
    "sg:city":"Bilbao",
    "sg:orig_category":"Servicios De Telecomunicaciones",
    "sg:phone":"+34 944 15 09 11",
    "sg:postcode":"48003",
    "sg:province":"Vizcaya",
    "wof:name":"Amar Belaidi - Khalid Sebti C.b",
    "wof:placetype":"venue"
},
  "geometry": {"coordinates":[-2.9292747974,43.2561836243],"type":"Point"}
}