{
  "type": "Feature",
  "properties": {
    "addr:full":"Pou, 3 El Vendrell Tarragona 43700",
    "addr:housenumber":"3",
    "addr:postcode":"43700",
    "addr:street":"Pou",
    "iso:country":"ES",
    "sg:address":"Pou, 3",
    "sg:city":"El Vendrell",
    "sg:orig_category":"Venta, Alquiler De Instrumentos Y Accesorios De M\u00dasica",
    "sg:phone":"+34 977 66 46 89",
    "sg:postcode":"43700",
    "sg:province":"Tarragona",
    "wof:name":"Music & Lights Productions & Bussines S.l.",
    "wof:placetype":"venue"
},
  "geometry": {"coordinates":[1.5153399706,41.2038574219],"type":"Point"}
}