{
  "type": "Feature",
  "properties": {
    "addr:full":"Carrer de Gaiarre, 50 Barcelona Barcelona 08014",
    "addr:housenumber":"50",
    "addr:postcode":"08014",
    "addr:street":"Carrer De Gaiarre",
    "iso:country":"ES",
    "sg:address":"Carrer de Gaiarre, 50",
    "sg:city":"Barcelona",
    "sg:orig_category":"Molduras, Junquillos, Listones Y Molduras Perforadas",
    "sg:phone":"+34 934 32 37 41",
    "sg:postcode":"08014",
    "sg:province":"Barcelona",
    "wof:name":"Baena Lopez Juan Carlos",
    "wof:placetype":"venue"
},
  "geometry": {"coordinates":[2.1403405666,41.3733711243],"type":"Point"}
}