{
  "type": "Feature",
  "properties": {
    "addr:full":"Carrer de Extremadura, 1 S. Joan Despi Barcelona 08970",
    "addr:housenumber":"1",
    "addr:postcode":"08970",
    "addr:street":"Carrer De Extremadura;S. Joan Despi",
    "iso:country":"ES",
    "sg:address":"Carrer de Extremadura, 1",
    "sg:city":"S. Joan Despi",
    "sg:orig_category":"Confecci\u00d3n De Trajes Para Se\u00d1oras",
    "sg:phone":"+34 933 73 23 13",
    "sg:postcode":"08970",
    "sg:province":"Barcelona",
    "wof:name":"Comelec Scp",
    "wof:placetype":"venue"
},
  "geometry": {"coordinates":[2.074131012,41.3684425354],"type":"Point"}
}