{
  "type": "Feature",
  "properties": {
    "addr:full":"Libertad, 10 Aljucer Murcia 30152",
    "addr:housenumber":"10",
    "addr:postcode":"30152",
    "addr:street":"Libertad",
    "iso:country":"ES",
    "sg:address":"Libertad, 10",
    "sg:city":"Aljucer",
    "sg:orig_category":"Peluqueros: De Se\u00d1oras",
    "sg:phone":"+34 968 34 48 48",
    "sg:postcode":"30152",
    "sg:province":"Murcia",
    "wof:name":"Corbalan Zambudio Maria Dolores",
    "wof:placetype":"venue"
},
  "geometry": {"coordinates":[-1.1546750069,37.9574661255],"type":"Point"}
}