{
  "type": "Feature",
  "properties": {
    "addr:full":"Calle de Ribera De Curtidores, 8 Madrid Madrid 28005",
    "addr:housenumber":"8",
    "addr:postcode":"madrid;28005",
    "addr:street":"Calle De Ribera De Curtidores",
    "iso:country":"ES",
    "sg:address":"Calle de Ribera De Curtidores, 8",
    "sg:city":"Madrid",
    "sg:orig_category":"Asociaciones Y Clubs Deportivos",
    "sg:phone":"+34 915 27 04 37",
    "sg:postcode":"28005",
    "sg:province":"Madrid",
    "wof:name":"Ribera De Curtidores 8 S.l.",
    "wof:placetype":"venue"
},
  "geometry": {"coordinates":[-3.7074539661,40.408744812],"type":"Point"}
}