{
  "type": "Feature",
  "properties": {
    "iso:country":"ES",
    "sg:address":"Leon-santander, 6",
    "sg:city":"Villanueva Del Arbol",
    "sg:orig_category":"Chapister\u00cda",
    "sg:phone":"+34 987 28 15 41",
    "sg:postcode":"24197",
    "sg:province":"Le\u00f3n",
    "wof:name":"Fernandez Fernandez Luis",
    "wof:placetype":"venue"
},
  "geometry": {"coordinates":[-5.5188531876,42.66147995],"type":"Point"}
}