{
  "type": "Feature",
  "properties": {
    "iso:country":"ES",
    "sg:address":"Rio Estenilla, 14",
    "sg:city":"Toledo",
    "sg:orig_category":"Aguas (distribuci\u00d3n, Servicios)",
    "sg:phone":"+34 925 23 09 00",
    "sg:postcode":"45007",
    "sg:province":"Toledo",
    "wof:name":"Astral Pool Espa\u00d1a S.a.u.",
    "wof:placetype":"venue"
},
  "geometry": {"coordinates":[-3.9595196247,39.86901474],"type":"Point"}
}