{
  "type": "Feature",
  "properties": {
    "addr:full":"Carr Figuerola, 47 Girona Girona 17001",
    "addr:housenumber":"47",
    "addr:postcode":"17001",
    "addr:street":"Carr Figuerola",
    "iso:country":"ES",
    "sg:address":"Carr Figuerola, 47",
    "sg:city":"Girona",
    "sg:orig_category":"Abogados",
    "sg:phone":"+34 972 22 22 43",
    "sg:postcode":"17001",
    "sg:province":"Girona",
    "wof:name":"Oliva Sala Joaquin",
    "wof:placetype":"venue"
},
  "geometry": {"coordinates":[2.8180909157,41.9848594666],"type":"Point"}
}