{
  "type": "Feature",
  "properties": {
    "iso:country":"ES",
    "sg:address":"Avda Juan Melgarejo, 1",
    "sg:city":"Costa Oeste",
    "sg:orig_category":"Arquitectos",
    "sg:phone":"+34 956 87 41 43",
    "sg:postcode":"11500",
    "sg:province":"C\u00e1diz",
    "wof:name":"Puerto Arquitectura S.l.",
    "wof:placetype":"venue"
},
  "geometry": {"coordinates":[-6.2197542191,36.6056632996],"type":"Point"}
}