{
  "type": "Feature",
  "properties": {
    "addr:full":"Carrer de Carme, 20 Lloret Mar Girona 17310",
    "addr:housenumber":"20",
    "addr:postcode":"17310",
    "addr:street":"Carrer De Carme",
    "iso:country":"ES",
    "sg:address":"Carrer de Carme, 20",
    "sg:city":"Lloret Mar",
    "sg:orig_category":"Artesan\u00cda Y Trabajos Manuales: Suministros (al Por Menor)",
    "sg:phone":"+34 972 36 01 70",
    "sg:postcode":"17310",
    "sg:province":"Girona",
    "sg:website":"www.artedetoledo.com",
    "wof:name":"Rpg Videojuegos Y Rol S.c.",
    "wof:placetype":"venue"
},
  "geometry": {"coordinates":[2.847769022,41.7008171082],"type":"Point"}
}