{
  "type": "Feature",
  "properties": {
    "iso:country":"ES",
    "sg:address":"Calle de Amor Hermoso, 35",
    "sg:city":"Cedeira",
    "sg:orig_category":"Reposter\u00cdas",
    "sg:phone":"+34 981 48 04 95",
    "sg:postcode":"15350",
    "sg:province":"La Coru\u00f1a",
    "wof:name":"O Forno De Gonzalo S.l.",
    "wof:placetype":"venue"
},
  "geometry": {"coordinates":[-8.0509853363,43.661026001],"type":"Point"}
}