{
  "type": "Feature",
  "properties": {
    "addr:full":"Canella Cega, 40 Verin Ourense 32600",
    "addr:housenumber":"40",
    "addr:postcode":"32600",
    "addr:street":"Cega",
    "iso:country":"ES",
    "sg:address":"Canella Cega, 40",
    "sg:city":"Verin",
    "sg:orig_category":"Electrodom\u00c9sticos (al Por Menor)",
    "sg:phone":"+34 988 41 06 66",
    "sg:postcode":"32600",
    "sg:province":"Ourense",
    "wof:name":"Electrodomesticos Feijoo S.l.",
    "wof:placetype":"venue"
},
  "geometry": {"coordinates":[-7.4276337624,41.9353141785],"type":"Point"}
}