{
  "type": "Feature",
  "properties": {
    "iso:country":"ES",
    "sg:address":"Carrer de Sere, 3",
    "sg:city":"Riudoms",
    "sg:orig_category":"Empresarios",
    "sg:phone":"+34 977 85 02 31",
    "sg:postcode":"43330",
    "sg:province":"Tarragona",
    "wof:name":"Garcia Teruel Jose Antonio",
    "wof:placetype":"venue"
},
  "geometry": {"coordinates":[1.0501329899,41.1342201233],"type":"Point"}
}