{
  "type": "Feature",
  "properties": {
    "iso:country":"ES",
    "sg:address":"Avda Boliches De Los, 68",
    "sg:city":"Fuengirola",
    "sg:orig_category":"Agencias Y Agentes Comerciales, Representantes",
    "sg:phone":"+34 952 66 45 11",
    "sg:postcode":"29640",
    "sg:province":"M\u00e1laga",
    "wof:name":"Yrjonen  Pentti Juhani",
    "wof:placetype":"venue"
},
  "geometry": {"coordinates":[-4.6148142815,36.5527191162],"type":"Point"}
}