{
  "type": "Feature",
  "properties": {
    "iso:country":"ES",
    "sg:address":"Calle de Concepcion Jeronima, 24",
    "sg:city":"Madrid",
    "sg:orig_category":"Edici\u00d3n De Diarios, Revistas, Boletines",
    "sg:phone":"+34 913 66 65 67",
    "sg:postcode":"28012",
    "sg:province":"Madrid",
    "wof:name":"Asesores De Publicaciones S.l.",
    "wof:placetype":"venue"
},
  "geometry": {"coordinates":[-3.7069785595,40.4137763977],"type":"Point"}
}