{
  "type": "Feature",
  "properties": {
    "iso:country":"ES",
    "sg:address":"Pl Font (de La), 4",
    "sg:city":"Montornes Centre",
    "sg:orig_category":"Laboratorios Y Trabajos De Fotograf\u00cda, V\u00cddeo Y Cine",
    "sg:phone":"+34 935 72 19 63",
    "sg:postcode":"08170",
    "sg:province":"Barcelona",
    "wof:name":"Jimenez Garrido Jose Antonio",
    "wof:placetype":"venue"
},
  "geometry": {"coordinates":[2.2639100552,41.541934967],"type":"Point"}
}