{
  "type": "Feature",
  "properties": {
    "iso:country":"ES",
    "sg:address":"Pl Font (de La), 1",
    "sg:city":"Montornes Centre",
    "sg:orig_category":"Papeler\u00cdas, Librer\u00cdas",
    "sg:phone":"+34 935 68 43 05",
    "sg:postcode":"08170",
    "sg:province":"Barcelona",
    "wof:name":"Lozano Quintanilla Tomas",
    "wof:placetype":"venue"
},
  "geometry": {"coordinates":[2.2639100552,41.541934967],"type":"Point"}
}