{
  "type": "Feature",
  "properties": {
    "addr:full":"Calle de Rascafria, 61 Villaviciosa Odon Madrid 28670",
    "addr:housenumber":"61",
    "addr:postcode":"28670",
    "addr:street":"Calle De Rascafria;Odon",
    "iso:country":"ES",
    "sg:address":"Calle de Rascafria, 61",
    "sg:city":"Villaviciosa Odon",
    "sg:orig_category":"Teatro, Ballet, Danza (agrupaciones, Compa\u00d1\u00cdas)",
    "sg:phone":"+34 916 16 14 26",
    "sg:postcode":"28670",
    "sg:province":"Madrid",
    "wof:name":"Iniciativa De Danza Andaluza S.l.",
    "wof:placetype":"venue"
},
  "geometry": {"coordinates":[-3.9017140865,40.3512306213],"type":"Point"}
}