{
  "type": "Feature",
  "properties": {
    "addr:full":"Carrer de Santa Eulalia, 240 Hospitalet Llobregat Barcelona 08902",
    "addr:housenumber":"240",
    "addr:postcode":"08902",
    "addr:street":"Carrer De Santa Eulalia",
    "iso:country":"ES",
    "sg:address":"Carrer de Santa Eulalia, 240",
    "sg:city":"Hospitalet Llobregat",
    "sg:orig_category":"Asesor\u00cda Sobre Comunicaci\u00d3n De Empresas",
    "sg:phone":"+34 932 31 08 29",
    "sg:postcode":"08902",
    "sg:province":"Barcelona",
    "wof:name":"Rovira Mascort Nuria",
    "wof:placetype":"venue"
},
  "geometry": {"coordinates":[2.1180920601,41.365486145],"type":"Point"}
}