{
  "type": "Feature",
  "properties": {
    "addr:full":"P. Sta. Isabel, 4 Malaga M\u00e1laga 29005",
    "addr:housenumber":"4",
    "addr:postcode":"29005",
    "addr:street":"P.;Isabel;Ma\u0301Laga",
    "iso:country":"ES",
    "sg:address":"P. Sta. Isabel, 4",
    "sg:city":"Malaga",
    "sg:orig_category":"Imprenta",
    "sg:phone":"+34 952 21 52 37",
    "sg:postcode":"29005",
    "sg:province":"M\u00e1laga",
    "wof:name":"Garcia Castro Rafael",
    "wof:placetype":"venue"
},
  "geometry": {"coordinates":[-4.4249110222,36.7208175659],"type":"Point"}
}