{
  "type": "Feature",
  "properties": {
    "iso:country":"ES",
    "sg:address":"Avda Juan Carlos I, 4",
    "sg:city":"Costa Ballena",
    "sg:orig_category":"Quincaller\u00cda (al Por Menor)",
    "sg:phone":"+34 956 84 74 13",
    "sg:postcode":"11520",
    "sg:province":"C\u00e1diz",
    "wof:name":"Lopez Ruiz Melchor",
    "wof:placetype":"venue"
},
  "geometry": {"coordinates":[-6.4085407257,36.692401886],"type":"Point"}
}