{
  "type": "Feature",
  "properties": {
    "iso:country":"ES",
    "sg:address":"Plaza Del Teniente Castro, 9",
    "sg:city":"Zambra",
    "sg:orig_category":"Cajas Para Embalar",
    "sg:phone":"+34 957 59 86 86",
    "sg:postcode":"14950",
    "sg:province":"C\u00f3rdoba",
    "wof:name":"Caja Rural De Cordoba",
    "wof:placetype":"venue"
},
  "geometry": {"coordinates":[-4.3845357895,37.3871269226],"type":"Point"}
}