{
  "type": "Feature",
  "properties": {
    "addr:full":"Plaz Espa\u00d1a, 3 Getafe Madrid 28903",
    "addr:housenumber":"3",
    "addr:postcode":"28903",
    "addr:street":"Plaz Espan\u0303A",
    "iso:country":"ES",
    "sg:address":"Plaz Espa\u00d1a, 3",
    "sg:city":"Getafe",
    "sg:orig_category":"Reposter\u00cdas",
    "sg:phone":"+34 916 83 74 61",
    "sg:postcode":"28903",
    "sg:province":"Madrid",
    "wof:name":"Aguilera Burgo Jose",
    "wof:placetype":"venue"
},
  "geometry": {"coordinates":[-3.7181246281,40.3156242371],"type":"Point"}
}