{
  "type": "Feature",
  "properties": {
    "iso:country":"ES",
    "sg:address":"Avda Andalucia, 37",
    "sg:city":"Guarroman",
    "sg:orig_category":"Molduras, Junquillos, Listones Y Molduras Perforadas",
    "sg:phone":"+34 953 61 60 01",
    "sg:postcode":"23210",
    "sg:province":"Ja\u00e9n",
    "wof:name":"Exposito Y Parra S.l.l.",
    "wof:placetype":"venue"
},
  "geometry": {"coordinates":[-3.6878108978,38.1827125549],"type":"Point"}
}