{
  "type": "Feature",
  "properties": {
    "iso:country":"ES",
    "sg:address":"Calle de San Blas, 4",
    "sg:city":"Valladolid",
    "sg:orig_category":"M\u00c9dicos: Pediatr\u00cda. Enfermedades De Los Ni\u00d1os",
    "sg:phone":"+34 983 33 51 82",
    "sg:postcode":"47003",
    "sg:province":"Valladolid",
    "wof:name":"Hernando Mayor Jose Carlos Teodoro",
    "wof:placetype":"venue"
},
  "geometry": {"coordinates":[-4.7263598442,41.6548805237],"type":"Point"}
}