{
  "type": "Feature",
  "properties": {
    "iso:country":"ES",
    "sg:address":"Calle de Carrera, 53",
    "sg:city":"Herrera Duque",
    "sg:orig_category":"Carnicer\u00cdas, Carnicer\u00cdas",
    "sg:phone":"+34 924 64 22 08",
    "sg:postcode":"06670",
    "sg:province":"Badajoz",
    "wof:name":"Mu\u00f1oz Prieto Antonio",
    "wof:placetype":"venue"
},
  "geometry": {"coordinates":[-5.0501503944,39.1674423218],"type":"Point"}
}