{
  "type": "Feature",
  "properties": {
    "iso:country":"ES",
    "sg:address":"Carrer de Frederic Mistral, 51",
    "sg:city":"Terrassa",
    "sg:orig_category":"Empresas De Pintura Y Revestimientos",
    "sg:phone":"+34 937 85 18 44",
    "sg:postcode":"08226",
    "sg:province":"Barcelona",
    "wof:name":"Lopez Pareja Jaime",
    "wof:placetype":"venue"
},
  "geometry": {"coordinates":[2.0263009071,41.575176239],"type":"Point"}
}