{
  "type": "Feature",
  "properties": {
    "addr:full":"Avda Parque (del), 19 Chauchina Granada 18330",
    "addr:housenumber":"19",
    "addr:postcode":"18330",
    "addr:street":"Avda Parque Del",
    "iso:country":"ES",
    "sg:address":"Avda Parque (del), 19",
    "sg:city":"Chauchina",
    "sg:orig_category":"Empresas De Pintura Y Revestimientos",
    "sg:phone":"+34 958 44 60 90",
    "sg:postcode":"18330",
    "sg:province":"Granada",
    "wof:name":"Garrido Madrid Jesus",
    "wof:placetype":"venue"
},
  "geometry": {"coordinates":[-3.7754230499,37.198299408],"type":"Point"}
}