{
  "type": "Feature",
  "properties": {
    "addr:full":"Calle de Real, 12 Ventosa Pisuerga Palencia 34405",
    "addr:housenumber":"12",
    "addr:postcode":"34405",
    "addr:street":"Calle De Real",
    "iso:country":"ES",
    "sg:address":"Calle de Real, 12",
    "sg:city":"Ventosa Pisuerga",
    "sg:orig_category":"Centros Empresariales",
    "sg:phone":"+34 979 13 02 01",
    "sg:postcode":"34405",
    "sg:province":"Palencia",
    "wof:name":"Alcalde Mat Desiderio",
    "wof:placetype":"venue"
},
  "geometry": {"coordinates":[-4.2986431122,42.5411491394],"type":"Point"}
}