{
  "type": "Feature",
  "properties": {
    "iso:country":"ES",
    "sg:address":"Altzola Kalea, 5",
    "sg:city":"Zarautz",
    "sg:orig_category":"T\u00c9cnicos Veterinarios",
    "sg:phone":"+34 943 01 32 44",
    "sg:postcode":"20800",
    "sg:province":"Guip\u00f9zcoa",
    "wof:name":"Xabier Genua Goena (clinica Veterinaria Lagun)",
    "wof:placetype":"venue"
},
  "geometry": {"coordinates":[-2.1724720001,43.2822570801],"type":"Point"}
}