{
  "type": "Feature",
  "properties": {
    "addr:full":"Pl Mossen Pere Batlle, 12 Casc Antic Barcelona 08150",
    "addr:housenumber":"12",
    "addr:postcode":"08150",
    "addr:street":"Pl Mossen Pere Batlle",
    "iso:country":"ES",
    "sg:address":"Pl Mossen Pere Batlle, 12",
    "sg:city":"Casc Antic",
    "sg:orig_category":"Cajas De Ahorro",
    "sg:phone":"+34 935 62 26 11",
    "sg:postcode":"08150",
    "sg:province":"Barcelona",
    "sg:website":"www.bancaja.es",
    "wof:name":"Caja De Ahorros De Valencia Castellon Y Alicante",
    "wof:placetype":"venue"
},
  "geometry": {"coordinates":[2.2293000221,41.5678787231],"type":"Point"}
}