{
  "type": "Feature",
  "properties": {
    "addr:full":"Carr Convent, Des, 4 Campos Islas Baleares 07630",
    "addr:postcode":"07630",
    "addr:street":"Carr Convent",
    "iso:country":"ES",
    "sg:address":"Carr Convent, Des, 4",
    "sg:city":"Campos",
    "sg:orig_category":"Ense\u00d1anza, Formaci\u00d3n Profesional: Aprendizaje",
    "sg:phone":"+34 971 65 29 31",
    "sg:postcode":"07630",
    "sg:province":"Islas Baleares",
    "sg:website":"www.a-campos.es",
    "wof:name":"Ajuntament De Campos",
    "wof:placetype":"venue"
},
  "geometry": {"coordinates":[2.997559309,39.4272499084],"type":"Point"}
}