{
  "type": "Feature",
  "properties": {
    "addr:full":"Calle de Melchor Fernandez Almagro, 54 Madrid Madrid 28029",
    "addr:housenumber":"54",
    "addr:postcode":"madrid;28029",
    "addr:street":"Calle De Melchor Fernandez Almagro",
    "iso:country":"ES",
    "sg:address":"Calle de Melchor Fernandez Almagro, 54",
    "sg:city":"Madrid",
    "sg:orig_category":"Lencer\u00cda Femenina, Corseter\u00cda, Trajes De Ba\u00d1o (al Por Menor)",
    "sg:phone":"+34 917 39 48 94",
    "sg:postcode":"28029",
    "sg:province":"Madrid",
    "wof:name":"Garcia Risco Maria Del Carmen",
    "wof:placetype":"venue"
},
  "geometry": {"coordinates":[-3.705534935,40.4766197205],"type":"Point"}
}