{
  "type": "Feature",
  "properties": {
    "iso:country":"ES",
    "sg:address":"Calle de Guadalupe, 14",
    "sg:city":"Aguadulce",
    "sg:orig_category":"Traductores",
    "sg:phone":"+34 950 34 96 03",
    "sg:postcode":"04720",
    "sg:province":"Almer\u00eda",
    "sg:website":"www.turneralvarez.com",
    "wof:name":"Turner  Richard Hartley Corten",
    "wof:placetype":"venue"
},
  "geometry": {"coordinates":[-2.569288969,36.8170814514],"type":"Point"}
}