{
  "type": "Feature",
  "properties": {
    "addr:full":"Plaz Mayor, 3 Valladolid Valladolid 47001",
    "addr:housenumber":"3",
    "addr:postcode":"47001",
    "addr:street":"Plaz Mayor",
    "iso:country":"ES",
    "sg:address":"Plaz Mayor, 3",
    "sg:city":"Valladolid",
    "sg:orig_category":"M\u00c9dicos: An\u00c1lisis Cl\u00cdnicos",
    "sg:phone":"+34 983 37 04 06",
    "sg:postcode":"47001",
    "sg:province":"Valladolid",
    "wof:name":"Martin Pedraza Luisa Maria",
    "wof:placetype":"venue"
},
  "geometry": {"coordinates":[-4.7277178764,41.6524734497],"type":"Point"}
}