{
  "type": "Feature",
  "properties": {
    "iso:country":"ES",
    "sg:address":"Calle de Pe\u00d1as, 44",
    "sg:city":"Tobarra",
    "sg:orig_category":"Papeler\u00cdas, Librer\u00cdas",
    "sg:phone":"+34 967 32 80 06",
    "sg:postcode":"02500",
    "sg:province":"Albacete",
    "wof:name":"Martinez Bleda Agueda",
    "wof:placetype":"venue"
},
  "geometry": {"coordinates":[-1.6924699545,38.5950279236],"type":"Point"}
}