{
  "type": "Feature",
  "properties": {
    "iso:country":"ES",
    "sg:address":"Carrer de Gran, 86",
    "sg:city":"Esparreguera",
    "sg:orig_category":"Fabricaci\u00d3n De Sobres, Bolsas Y Fundas",
    "sg:phone":"+34 937 70 88 05",
    "sg:postcode":"08292",
    "sg:province":"Barcelona",
    "wof:name":"Corinto Bolsos S.l.",
    "wof:placetype":"venue"
},
  "geometry": {"coordinates":[1.8686389923,41.5407180786],"type":"Point"}
}