{
  "type": "Feature",
  "properties": {
    "iso:country":"ES",
    "sg:address":"Calle de Perez Zamora, 16",
    "sg:city":"Santa Cruz De Tenerife",
    "sg:orig_category":"Importaci\u00d3n",
    "sg:phone":"+34 922 20 11 01",
    "sg:postcode":"38005",
    "sg:province":"Santa Cruz De Tenerife",
    "wof:name":"Chulani  Washedu Jauhermal",
    "wof:placetype":"venue"
},
  "geometry": {"coordinates":[-16.2547626495,28.4612541199],"type":"Point"}
}