{
  "type": "Feature",
  "properties": {
    "iso:country":"ES",
    "sg:address":"Calle de Pozo, 24",
    "sg:city":"Carcaboso",
    "sg:orig_category":"Ropa Para Se\u00d1oras Y Caballeros (al Por Menor)",
    "sg:phone":"+34 927 40 21 65",
    "sg:postcode":"10670",
    "sg:province":"C\u00e1ceres",
    "wof:name":"Sanabria Rojas Antonio Maria",
    "wof:placetype":"venue"
},
  "geometry": {"coordinates":[-6.2128472328,40.0501937866],"type":"Point"}
}