{
  "type": "Feature",
  "properties": {
    "iso:country":"ES",
    "sg:address":"Calle de Pintor Lopez, 1",
    "sg:city":"Valencia",
    "sg:orig_category":"Elementos Para Suelos Prefabricados",
    "sg:phone":"+34 963 92 44 04",
    "sg:postcode":"46003",
    "sg:province":"Valencia",
    "sg:website":"www.elparquet.com",
    "wof:name":"Especialistas En Pavimentos De Madera S.l.",
    "wof:placetype":"venue"
},
  "geometry": {"coordinates":[-0.3714540005,39.4770965576],"type":"Point"}
}