{
  "type": "Feature",
  "properties": {
    "addr:full":"Calle de Dionisio Guardiola, 4 Albacete Albacete 02002",
    "addr:housenumber":"4",
    "addr:postcode":"02002",
    "addr:street":"Calle De Dionisio Guardiola",
    "iso:country":"ES",
    "sg:address":"Calle de Dionisio Guardiola, 4",
    "sg:city":"Albacete",
    "sg:orig_category":"Abogados",
    "sg:phone":"+34 967 24 01 29",
    "sg:postcode":"02002",
    "sg:province":"Albacete",
    "wof:name":"Serrano Siquier Jose Francisco",
    "wof:placetype":"venue"
},
  "geometry": {"coordinates":[-1.854820013,38.9914016724],"type":"Point"}
}