{
  "type": "Feature",
  "properties": {
    "addr:full":"Avda Espa\u00d1a (de), 7 San Eugenio Bajo Santa Cruz De Tenerife 38660",
    "addr:postcode":"38660",
    "addr:street":"Avda Espan\u0303A De 7 San Eugenio",
    "iso:country":"ES",
    "sg:address":"Avda Espa\u00d1a (de), 7",
    "sg:city":"San Eugenio Bajo",
    "sg:orig_category":"Bazares, Art\u00cdculos De Limpieza Y De Cocina (al Por Menor)",
    "sg:phone":"+34 922 71 78 85",
    "sg:postcode":"38660",
    "sg:province":"Santa Cruz De Tenerife",
    "wof:name":"Lalfon's Watch Company S.l.",
    "wof:placetype":"venue"
},
  "geometry": {"coordinates":[-16.2645397186,28.4603843689],"type":"Point"}
}