{
  "type": "Feature",
  "properties": {
    "addr:full":"Calle de Valladolid, 18 Avila \u00c1vila 05005",
    "addr:housenumber":"18",
    "addr:postcode":"05005",
    "addr:street":"Calle De Valladolid;A\u0301Vila",
    "iso:country":"ES",
    "sg:address":"Calle de Valladolid, 18",
    "sg:city":"Avila",
    "sg:orig_category":"Fabrica, Negocio De Vidrieras, Productos Vidriados Y Espejos",
    "sg:phone":"+34 920 22 63 19",
    "sg:postcode":"05005",
    "sg:province":"\u00c1vila",
    "wof:name":"Miguel Martin Martin Y Victorio Galan Galan Cdad",
    "wof:placetype":"venue"
},
  "geometry": {"coordinates":[-4.6936769485,40.6585655212],"type":"Point"}
}