{
  "type": "Feature",
  "properties": {
    "addr:full":"Calle de Apolo, 104 Torrevieja Alicante 03180",
    "addr:housenumber":"104",
    "addr:postcode":"03180",
    "addr:street":"Calle De Apolo",
    "iso:country":"ES",
    "sg:address":"Calle de Apolo, 104",
    "sg:city":"Torrevieja",
    "sg:orig_category":"Alquiler De Veh\u00cdculos: Turismos Y Utilitarios",
    "sg:phone":"+34 966 70 35 34",
    "sg:postcode":"03180",
    "sg:province":"Alicante",
    "sg:website":"www.centauro.net",
    "wof:name":"Centauro Renta-car S.l.",
    "wof:placetype":"venue"
},
  "geometry": {"coordinates":[-0.6787559986,37.9793395996],"type":"Point"}
}