{
  "type": "Feature",
  "properties": {
    "addr:full":"Ctra Puerto Estaca, S/n Puerto De La Estaca Santa Cruz De Tenerife 38910",
    "addr:housenumber":"s / n",
    "addr:postcode":"38910",
    "addr:street":"Ctra Puerto Estaca",
    "iso:country":"ES",
    "sg:address":"Ctra Puerto Estaca, S/n",
    "sg:city":"Puerto De La Estaca",
    "sg:orig_category":"Explosivos",
    "sg:phone":"+34 922 55 07 58",
    "sg:postcode":"38910",
    "sg:province":"Santa Cruz De Tenerife",
    "wof:name":"Canarias Explosivos S. A.",
    "wof:placetype":"venue"
},
  "geometry": {"coordinates":[-17.8970718384,27.8238143921],"type":"Point"}
}