{
  "type": "Feature",
  "properties": {
    "addr:full":"Cra Sant Joan, 21 Camprodon Girona 17867",
    "addr:housenumber":"21",
    "addr:postcode":"17867",
    "addr:street":"Joan",
    "iso:country":"ES",
    "sg:address":"Cra Sant Joan, 21",
    "sg:city":"Camprodon",
    "sg:orig_category":"Muebles, Minoristas",
    "sg:phone":"+34 972 74 01 81",
    "sg:postcode":"17867",
    "sg:province":"Girona",
    "wof:name":"Martin Magret S.a.",
    "wof:placetype":"venue"
},
  "geometry": {"coordinates":[2.3646419048,42.3104515076],"type":"Point"}
}