{
  "type": "Feature",
  "properties": {
    "iso:country":"ES",
    "sg:address":"Calle de Marques De Santa Cruz, 11",
    "sg:city":"Oviedo",
    "sg:orig_category":"M\u00c9dicos: Ginecolog\u00cda Y Obstetricia",
    "sg:phone":"+34 985 21 11 41",
    "sg:postcode":"33007",
    "sg:province":"Asturias",
    "wof:name":"Sanchez Del Rio Angel",
    "wof:placetype":"venue"
},
  "geometry": {"coordinates":[-5.8489499092,43.3608932495],"type":"Point"}
}