{
  "type": "Feature",
  "properties": {
    "iso:country":"ES",
    "sg:address":"Av Catalunya, 18",
    "sg:city":"Puigcerda",
    "sg:classifiers":[
        {
            "category":"Banks & Credit Unions",
            "subcategory":"Bank",
            "type":"Services"
        }
    ],
    "sg:phone":"+34 972 88 18 19",
    "sg:postcode":"17520",
    "sg:province":"Girona",
    "sg:tags":[
        "interior",
        "arquitectos",
        "de"
    ],
    "wof:name":"Alvaro Garcia Susana",
    "wof:placetype":"venue"
},
  "geometry": {"coordinates":[1.9296734333,42.4302482605],"type":"Point"}
}