{
  "type": "Feature",
  "properties": {
    "iso:country":"ES",
    "sg:address":"Calle de Mayor Principal, 16",
    "sg:city":"Palencia",
    "sg:orig_category":"Zapater\u00cdas",
    "sg:phone":"+34 979 74 27 58",
    "sg:postcode":"34001",
    "sg:province":"Palencia",
    "wof:name":"Triana Manchado Marino",
    "wof:placetype":"venue"
},
  "geometry": {"coordinates":[-4.5327916145,42.0124015808],"type":"Point"}
}