{
  "type": "Feature",
  "properties": {
    "addr:full":"Avda Libertad, 30 Laguna Duero Valladolid 47140",
    "addr:housenumber":"30",
    "addr:postcode":"47140",
    "addr:street":"Avda Libertad",
    "iso:country":"ES",
    "sg:address":"Avda Libertad, 30",
    "sg:city":"Laguna Duero",
    "sg:orig_category":"Molduras, Junquillos, Listones Y Molduras Perforadas",
    "sg:phone":"+34 983 54 03 43",
    "sg:postcode":"47140",
    "sg:province":"Valladolid",
    "wof:name":"Zarzosa Martin Laureano",
    "wof:placetype":"venue"
},
  "geometry": {"coordinates":[-4.7236409187,41.5895080566],"type":"Point"}
}