{
  "type": "Feature",
  "properties": {
    "addr:full":"Calle de San Marcelo, 5 Madrid Madrid 28017",
    "addr:housenumber":"5",
    "addr:postcode":"28017",
    "addr:street":"Calle De San Marcelo",
    "iso:country":"ES",
    "sg:address":"Calle de San Marcelo, 5",
    "sg:city":"Madrid",
    "sg:orig_category":"M\u00c9dicos: Ortopedia Dento",
    "sg:phone":"+34 913 55 29 57",
    "sg:postcode":"28017",
    "sg:province":"Madrid",
    "wof:name":"Centro Altatorre De Sordos De Madrid",
    "wof:placetype":"venue"
},
  "geometry": {"coordinates":[-3.6559720039,40.4277038574],"type":"Point"}
}