{
  "type": "Feature",
  "properties": {
    "addr:full":"Cno. Asadero, 21 Cenes Vega Granada 18190",
    "addr:housenumber":"21",
    "addr:postcode":"18190",
    "addr:street":"Cno. Asadero",
    "iso:country":"ES",
    "sg:address":"Cno. Asadero, 21",
    "sg:city":"Cenes Vega",
    "sg:orig_category":"Arquitectos",
    "sg:phone":"+34 958 48 74 73",
    "sg:postcode":"18190",
    "sg:province":"Granada",
    "wof:name":"Sanchez Garcia Manuel Jose",
    "wof:placetype":"venue"
},
  "geometry": {"coordinates":[-3.5423738956,37.1603355408],"type":"Point"}
}