{
  "type": "Feature",
  "properties": {
    "iso:country":"ES",
    "sg:address":"Rua Romana Baixa, S/n",
    "sg:city":"Ramallosa",
    "sg:orig_category":"Centros Empresariales",
    "sg:phone":"+34 986 35 20 00",
    "sg:postcode":"36379",
    "sg:province":"Pontevedra",
    "wof:name":"Zig-zag S.c",
    "wof:placetype":"venue"
},
  "geometry": {"coordinates":[-8.8112125397,42.1177787781],"type":"Point"}
}