{
  "type": "Feature",
  "properties": {
    "iso:country":"ES",
    "sg:address":"Calle de Udiarraga, 7",
    "sg:city":"Ugao-miraballes",
    "sg:orig_category":"Molduras, Junquillos, Listones Y Molduras Perforadas",
    "sg:phone":"+34 946 48 14 53",
    "sg:postcode":"48490",
    "sg:province":"Vizcaya",
    "wof:name":"Redondo Reyes Lourdes",
    "wof:placetype":"venue"
},
  "geometry": {"coordinates":[-2.9011909962,43.1826095581],"type":"Point"}
}