{
  "type": "Feature",
  "properties": {
    "addr:full":"Calle de Mayor, 54 Zuera Zaragoza 50800",
    "addr:housenumber":"54",
    "addr:postcode":"50800",
    "addr:street":"Calle De Mayor",
    "iso:country":"ES",
    "sg:address":"Calle de Mayor, 54",
    "sg:city":"Zuera",
    "sg:orig_category":"Molduras, Junquillos, Listones Y Molduras Perforadas",
    "sg:phone":"+34 976 68 05 34",
    "sg:postcode":"50800",
    "sg:province":"Zaragoza",
    "wof:name":"Nerester S.l.",
    "wof:placetype":"venue"
},
  "geometry": {"coordinates":[-0.7876179814,41.8684272766],"type":"Point"}
}