{
  "type": "Feature",
  "properties": {
    "iso:country":"ES",
    "sg:address":"Carr Riu Ser, 5",
    "sg:city":"Girona",
    "sg:orig_category":"Agencias Y Agentes Comerciales, Representantes",
    "sg:phone":"+34 972 20 93 62",
    "sg:postcode":"17003",
    "sg:province":"Girona",
    "wof:name":"Comunidad De Propietarios Riu Ser 5",
    "wof:placetype":"venue"
},
  "geometry": {"coordinates":[2.8135819435,41.9667930603],"type":"Point"}
}