{
  "type": "Feature",
  "properties": {
    "addr:full":"Calle de Pez Volador, 5 Madrid Madrid 28007",
    "addr:housenumber":"5",
    "addr:postcode":"28007",
    "addr:street":"Calle De Pez Volador",
    "iso:country":"ES",
    "sg:address":"Calle de Pez Volador, 5",
    "sg:city":"Madrid",
    "sg:orig_category":"Centros De Reservas Hoteleras",
    "sg:phone":"+34 915 74 93 49",
    "sg:postcode":"28007",
    "sg:province":"Madrid",
    "sg:website":"www.coloncostaballena.com",
    "wof:name":"Lamaro Inversiones Inmouno S.l.",
    "wof:placetype":"venue"
},
  "geometry": {"coordinates":[-3.6688990593,40.4129753113],"type":"Point"}
}