{
  "type": "Feature",
  "properties": {
    "addr:full":"Calle de Joaquin Paya, 5 Orcera Ja\u00e9n 23370",
    "addr:housenumber":"5",
    "addr:postcode":"23370",
    "addr:street":"Calle De Joaquin Paya;Jae\u0301N",
    "iso:country":"ES",
    "sg:address":"Calle de Joaquin Paya, 5",
    "sg:city":"Orcera",
    "sg:orig_category":"Ense\u00d1anza, Formaci\u00d3n Profesional: Aprendizaje",
    "sg:phone":"+34 953 48 01 43",
    "sg:postcode":"23370",
    "sg:province":"Ja\u00e9n",
    "wof:name":"Junta De Andalucia",
    "wof:placetype":"venue"
},
  "geometry": {"coordinates":[-2.6641321182,38.317691803],"type":"Point"}
}