{
  "type": "Feature",
  "properties": {
    "addr:full":"Gral. Yague, 17 Abejar Soria 42146",
    "addr:housenumber":"17",
    "addr:postcode":"42146",
    "addr:street":"Gral. Yague",
    "iso:country":"ES",
    "sg:address":"Gral. Yague, 17",
    "sg:city":"Abejar",
    "sg:orig_category":"Reposter\u00cdas",
    "sg:phone":"+34 975 37 31 38",
    "sg:postcode":"42146",
    "sg:province":"Soria",
    "wof:name":"Teresa Romero Jaime",
    "wof:placetype":"venue"
},
  "geometry": {"coordinates":[-2.8498749733,41.7982330322],"type":"Point"}
}