{
  "type": "Feature",
  "properties": {
    "iso:country":"ES",
    "sg:address":"Calle de Francia, 2",
    "sg:city":"Pozuelo De Alarcon",
    "sg:orig_category":"Empresas De Portes Y Mensajer\u00cda",
    "sg:phone":"+34 917 15 94 59",
    "sg:postcode":"28224",
    "sg:province":"Madrid",
    "wof:name":"3nr Servicios S.l.",
    "wof:placetype":"venue"
},
  "geometry": {"coordinates":[-3.808263,40.432758],"type":"Point"}
}