{
  "type": "Feature",
  "properties": {
    "addr:full":"Ortega Y Gasset(las Lumbreras), 3 Monteagudo Murcia 30160",
    "addr:housenumber":"3",
    "addr:postcode":"30160",
    "addr:street":"Ortega Y Gasset Las Lumbreras",
    "iso:country":"ES",
    "sg:address":"Ortega Y Gasset(las Lumbreras), 3",
    "sg:city":"Monteagudo",
    "sg:orig_category":"Electricidad: Instalaciones Industriales",
    "sg:phone":"+34 968 85 12 15",
    "sg:postcode":"30160",
    "sg:province":"Murcia",
    "wof:name":"Apitelec S.l.",
    "wof:placetype":"venue"
},
  "geometry": {"coordinates":[-1.0901294947,38.0297546387],"type":"Point"}
}