{
  "type": "Feature",
  "properties": {
    "iso:country":"ES",
    "sg:address":"Aut. A-set, Km. 0144,1",
    "sg:city":"Sta. Perpetua Mogoda",
    "sg:orig_category":"Distribuci\u00d3n De Petr\u00d3leo Y Derivados",
    "sg:phone":"+34 935 74 05 59",
    "sg:postcode":"08130",
    "sg:province":"Barcelona",
    "wof:name":"Areas S.a.",
    "wof:placetype":"venue"
},
  "geometry": {"coordinates":[2.1893494129,41.5224227905],"type":"Point"}
}