{
  "type": "Feature",
  "properties": {
    "iso:country":"ES",
    "sg:address":"Carrer de Santa Joana D'arc, 15",
    "sg:city":"Barcelona",
    "sg:orig_category":"Electrodom\u00c9sticos (al Por Menor)",
    "sg:phone":"+34 934 07 22 33",
    "sg:postcode":"08032",
    "sg:province":"Barcelona",
    "wof:name":"Electrodomesticos Hogar 2004 S.l.",
    "wof:placetype":"venue"
},
  "geometry": {"coordinates":[2.1587762833,41.4275283813],"type":"Point"}
}