{
  "type": "Feature",
  "properties": {
    "addr:full":"Avda Peruleiro, 49 Coru\u00d1a La Coru\u00f1a 15011",
    "addr:housenumber":"49",
    "addr:postcode":"15011",
    "addr:street":"Avda Peruleiro;Corun\u0303A",
    "iso:country":"ES",
    "sg:address":"Avda Peruleiro, 49",
    "sg:city":"Coru\u00d1a",
    "sg:orig_category":"Electrodom\u00c9sticos (al Por Menor)",
    "sg:phone":"+34 981 27 47 04",
    "sg:postcode":"15011",
    "sg:province":"La Coru\u00f1a",
    "wof:name":"Mallo Alonso Antonio",
    "wof:placetype":"venue"
},
  "geometry": {"coordinates":[-8.4238128662,43.3665161133],"type":"Point"}
}