{
  "type": "Feature",
  "properties": {
    "addr:full":"Calle de Veintidos De Julio, 2 Andujar Ja\u00e9n 23740",
    "addr:housenumber":"2",
    "addr:postcode":"23740",
    "addr:street":"Calle De Veintidos De Julio",
    "iso:country":"ES",
    "sg:address":"Calle de Veintidos De Julio, 2",
    "sg:city":"Andujar",
    "sg:orig_category":"Ropa Para Se\u00d1oras (al Por Menor)",
    "sg:phone":"+34 953 51 40 59",
    "sg:postcode":"23740",
    "sg:province":"Ja\u00e9n",
    "wof:name":"Gomez Gonzalez Juana",
    "wof:placetype":"venue"
},
  "geometry": {"coordinates":[-4.0519862175,38.0366744995],"type":"Point"}
}