{
  "type": "Feature",
  "properties": {
    "iso:country":"ES",
    "sg:address":"Calle de Calderon De La Barca, 19",
    "sg:city":"Santander",
    "sg:orig_category":"Mensajer\u00cda Express, Portes Internacionales",
    "sg:phone":"+34 942 31 30 11",
    "sg:postcode":"39002",
    "sg:province":"Cantabria",
    "wof:name":"Catraur S.l.",
    "wof:placetype":"venue"
},
  "geometry": {"coordinates":[-3.8079912663,43.4594726562],"type":"Point"}
}