{
  "type": "Feature",
  "properties": {
    "iso:country":"ES",
    "sg:address":"Calle de Jimenez E Iglesias, 3",
    "sg:city":"Getafe",
    "sg:orig_category":"Inmobiliaria (agencias)",
    "sg:phone":"+34 916 83 03 42",
    "sg:postcode":"28903",
    "sg:province":"Madrid",
    "wof:name":"F.s.consultores Inmobiliarios S.l.",
    "wof:placetype":"venue"
},
  "geometry": {"coordinates":[-3.7250618935,40.3110809326],"type":"Point"}
}