{
  "type": "Feature",
  "properties": {
    "iso:country":"ES",
    "sg:address":"Calle de Central, 29",
    "sg:city":"Estacion",
    "sg:orig_category":"Grafistas",
    "sg:phone":"+34 918 51 56 78",
    "sg:postcode":"28400",
    "sg:province":"Madrid",
    "wof:name":"Del Prado Romero Aurora",
    "wof:placetype":"venue"
},
  "geometry": {"coordinates":[-4.3302307129,40.5954627991],"type":"Point"}
}