{
  "type": "Feature",
  "properties": {
    "addr:full":"Carrer de Montalt, 11 Mataro Barcelona 08304",
    "addr:housenumber":"11",
    "addr:postcode":"08304",
    "addr:street":"Carrer De Montalt",
    "iso:country":"ES",
    "sg:address":"Carrer de Montalt, 11",
    "sg:city":"Mataro",
    "sg:orig_category":"Electricidad: Instaladores",
    "sg:phone":"+34 937 96 43 98",
    "sg:postcode":"08304",
    "sg:province":"Barcelona",
    "wof:name":"Instalaciones Cantano S.l.",
    "wof:placetype":"venue"
},
  "geometry": {"coordinates":[2.4460868835,41.5528411865],"type":"Point"}
}