{
  "type": "Feature",
  "properties": {
    "addr:full":"Plaz Luis Gonzaga, S/n Tijola Almer\u00eda 04880",
    "addr:postcode":"04880",
    "addr:street":"Plaz Luis Gonzaga S / N;Almeri\u0301A",
    "iso:country":"ES",
    "sg:address":"Plaz Luis Gonzaga, S/n",
    "sg:city":"Tijola",
    "sg:orig_category":"Zapatos (al Por Menor)",
    "sg:phone":"+34 950 42 06 07",
    "sg:postcode":"04880",
    "sg:province":"Almer\u00eda",
    "wof:name":"Martinez Segura Jose",
    "wof:placetype":"venue"
},
  "geometry": {"coordinates":[-2.4346039295,37.3460693359],"type":"Point"}
}