{
  "type": "Feature",
  "properties": {
    "iso:country":"ES",
    "sg:address":"Calle de Hernan Cortes, 48",
    "sg:city":"Andenes",
    "sg:orig_category":"Agencias Y Agentes Comerciales, Representantes",
    "sg:phone":"+34 922 61 43 05",
    "sg:postcode":"38108",
    "sg:province":"Santa Cruz De Tenerife",
    "wof:name":"Rodriguez Villar Andres",
    "wof:placetype":"venue"
},
  "geometry": {"coordinates":[-16.2957706451,28.4491081238],"type":"Point"}
}