{
  "type": "Feature",
  "properties": {
    "addr:full":"Plaz Rafael Cano, 9 Valladolid Valladolid 47005",
    "addr:postcode":"47005",
    "iso:country":"ES",
    "sg:address":"Plaz Rafael Cano, 9",
    "sg:city":"Valladolid",
    "sg:orig_category":"Frutas Y Legumbres Frescas (al Por Mayor)",
    "sg:phone":"+34 983 39 50 50",
    "sg:postcode":"47005",
    "sg:province":"Valladolid",
    "wof:name":"Perez Trabadelo Laurentino",
    "wof:placetype":"venue"
},
  "geometry": {"coordinates":[-4.7103209496,41.6521873474],"type":"Point"}
}