{
  "type": "Feature",
  "properties": {
    "addr:full":"Avda Cruz Roja (de La), 1 Puerto De Santa Maria C\u00e1diz 11500",
    "addr:postcode":"11500",
    "addr:street":"Avda Cruz Roja De La 1;Ca\u0301Diz",
    "iso:country":"ES",
    "sg:address":"Avda Cruz Roja (de La), 1",
    "sg:city":"Puerto De Santa Maria",
    "sg:orig_category":"M\u00c9dicos: Cirug\u00cda Pl\u00c1stica, Reconstructiva Y Est\u00c9tica",
    "sg:phone":"+34 956 87 23 99",
    "sg:postcode":"11500",
    "sg:province":"C\u00e1diz",
    "wof:name":"Clinica Medica Laser Bahia",
    "wof:placetype":"venue"
},
  "geometry": {"coordinates":[-6.2396087646,36.5969009399],"type":"Point"}
}