{
  "type": "Feature",
  "properties": {
    "addr:full":"C/ Cami (el), 49 Alcoi Alicante 03801",
    "addr:postcode":"03801",
    "addr:street":"C /;El",
    "iso:country":"ES",
    "sg:address":"C/ Cami (el), 49",
    "sg:city":"Alcoi",
    "sg:orig_category":"Carros Elevadores, Carros De Operaciones Portuarias",
    "sg:phone":"+34 965 54 49 70",
    "sg:postcode":"03801",
    "sg:province":"Alicante",
    "wof:name":"Tebar Molina Jorge",
    "wof:placetype":"venue"
},
  "geometry": {"coordinates":[-0.4754369855,38.6927452087],"type":"Point"}
}