{
  "type": "Feature",
  "properties": {
    "iso:country":"ES",
    "sg:address":"Calle de Cayetano Gil, 67",
    "sg:city":"Cazalla Sierra",
    "sg:orig_category":"Cooperativas Agr\u00cdcolas",
    "sg:phone":"+34 954 88 43 38",
    "sg:postcode":"41370",
    "sg:province":"Sevilla",
    "wof:name":"Cooperativa Obrera Panadera San Leonardo",
    "wof:placetype":"venue"
},
  "geometry": {"coordinates":[-5.7605638504,37.9321289062],"type":"Point"}
}