{
  "type": "Feature",
  "properties": {
    "addr:full":"Avda Aragon, 31 Sang\u00fcesa Navarra 31400",
    "addr:housenumber":"31",
    "addr:postcode":"31400",
    "addr:street":"Avda Aragon",
    "iso:country":"ES",
    "sg:address":"Avda Aragon, 31",
    "sg:city":"Sang\u00fcesa",
    "sg:orig_category":"Reposter\u00cdas",
    "sg:phone":"+34 948 87 02 25",
    "sg:postcode":"31400",
    "sg:province":"Navarra",
    "wof:name":"Compa\u00f1ia Panificadora Sang\u00fcesina S. L.",
    "wof:placetype":"venue"
},
  "geometry": {"coordinates":[-1.2804640532,42.5710983276],"type":"Point"}
}