{
  "type": "Feature",
  "properties": {
    "iso:country":"ES",
    "sg:address":"Carrer de Arquitectura, 22",
    "sg:city":"Hospitalet Llobregat",
    "sg:orig_category":"Agentes, Concesionarios Y Sucursales De Veh\u00cdculos",
    "sg:phone":"+34 932 96 53 94",
    "sg:postcode":"08908",
    "sg:province":"Barcelona",
    "wof:name":"Nova Korea S.a.",
    "wof:placetype":"venue"
},
  "geometry": {"coordinates":[2.1321389675,41.3600120544],"type":"Point"}
}