{
  "type": "Feature",
  "properties": {
    "addr:full":"Av Torrent Gornal, 53 Hospitalet Llobregat Barcelona 08905",
    "addr:housenumber":"53",
    "addr:postcode":"08905",
    "addr:street":"Av;Gornal",
    "iso:country":"ES",
    "sg:address":"Av Torrent Gornal, 53",
    "sg:city":"Hospitalet Llobregat",
    "sg:orig_category":"Caf\u00c9s, Bares, Cervecer\u00cdas",
    "sg:phone":"+34 933 33 60 10",
    "sg:postcode":"08905",
    "sg:province":"Barcelona",
    "wof:name":"Romero Cuesta Antonio",
    "wof:placetype":"venue"
},
  "geometry": {"coordinates":[2.1113231182,41.3742752075],"type":"Point"}
}