{
  "type": "Feature",
  "properties": {
    "iso:country":"ES",
    "sg:address":"Carrer de Orient, 2",
    "sg:city":"Hospitalet Llobregat",
    "sg:orig_category":"T\u00c9cnicos Veterinarios",
    "sg:phone":"+34 934 48 10 26",
    "sg:postcode":"08904",
    "sg:province":"Barcelona",
    "wof:name":"Fuentes Fernandez Nuria",
    "wof:placetype":"venue"
},
  "geometry": {"coordinates":[2.1182610989,41.3730239868],"type":"Point"}
}