{
  "type": "Feature",
  "properties": {
    "addr:full":"Pase Adarves (los), 6 Molina Guadalajara 19300",
    "addr:housenumber":"6",
    "addr:postcode":"19300",
    "addr:street":"Pase Adarves Los",
    "iso:country":"ES",
    "sg:address":"Pase Adarves (los), 6",
    "sg:city":"Molina",
    "sg:classifiers":[
        {
            "category":"Personal",
            "subcategory":"Barber",
            "type":"Services"
        }
    ],
    "sg:phone":"+34 949 83 22 32",
    "sg:postcode":"19300",
    "sg:province":"Guadalajara",
    "sg:tags":[
        "caballeros",
        "de",
        "peluqueros"
    ],
    "wof:name":"Escolano Otero Vicente",
    "wof:placetype":"venue"
},
  "geometry": {"coordinates":[-1.8168599606,40.8542098999],"type":"Point"}
}