{
  "type": "Feature",
  "properties": {
    "addr:full":"Bard Milagros De Los, 15 Zona De Los Principes Huelva 21810",
    "addr:housenumber":"zona",
    "addr:postcode":"21810",
    "iso:country":"ES",
    "sg:address":"Bard Milagros De Los, 15",
    "sg:city":"Zona De Los Principes",
    "sg:orig_category":"Zapatos (al Por Menor)",
    "sg:phone":"+34 959 35 00 08",
    "sg:postcode":"21810",
    "sg:province":"Huelva",
    "wof:name":"Perez Dominguez Vicenta",
    "wof:placetype":"venue"
},
  "geometry": {"coordinates":[-6.8923411369,37.2240829468],"type":"Point"}
}