{
  "type": "Feature",
  "properties": {
    "iso:country":"ES",
    "sg:address":"Calle de Arrufat Alonso, 11",
    "sg:city":"Castellon",
    "sg:orig_category":"Fabricaci\u00d3n De Enlosados, Soler\u00cdas",
    "sg:phone":"+34 964 24 52 49",
    "sg:postcode":"12001",
    "sg:province":"Castell\u00f3n",
    "wof:name":"Intermediaria Azulejera S.l.",
    "wof:placetype":"venue"
},
  "geometry": {"coordinates":[-0.0395967998,39.9894866943],"type":"Point"}
}