{
  "type": "Feature",
  "properties": {
    "addr:full":"Avda. Julian Valverde, 86 A Ramallosa Pontevedra 36393",
    "addr:housenumber":"86 a",
    "addr:postcode":"36393",
    "addr:street":"Avda. Julian Valverde",
    "iso:country":"ES",
    "sg:address":"Avda. Julian Valverde, 86",
    "sg:city":"A Ramallosa",
    "sg:orig_category":"Centros Empresariales",
    "sg:phone":"+34 986 35 47 75",
    "sg:postcode":"36393",
    "sg:province":"Pontevedra",
    "wof:name":"Conde Gestido Natalia",
    "wof:placetype":"venue"
},
  "geometry": {"coordinates":[-8.8274269104,42.1040344238],"type":"Point"}
}