{
  "type": "Feature",
  "properties": {
    "iso:country":"ES",
    "sg:address":"Carrer de Cami Ral, 54",
    "sg:city":"Tordera",
    "sg:orig_category":"Cajas De Ahorro",
    "sg:phone":"+34 937 65 08 58",
    "sg:postcode":"08490",
    "sg:province":"Barcelona",
    "wof:name":"Caixa D'estalvis Del Penedes",
    "wof:placetype":"venue"
},
  "geometry": {"coordinates":[2.7179350853,41.6998901367],"type":"Point"}
}