{
  "type": "Feature",
  "properties": {
    "iso:country":"ES",
    "sg:address":"Calle de Doctor Joaquin Artiles, S/n",
    "sg:city":"Ag\u00fcimes",
    "sg:orig_category":"Pescader\u00cdas (al Por Menor)",
    "sg:phone":"+34 928 12 41 85",
    "sg:postcode":"35260",
    "sg:province":"Las Palmas",
    "wof:name":"Macias Quintana Francisco",
    "wof:placetype":"venue"
},
  "geometry": {"coordinates":[-15.4485244751,27.9038333893],"type":"Point"}
}