{
  "type": "Feature",
  "properties": {
    "iso:country":"ES",
    "sg:address":"Calle de Mayor, 12",
    "sg:city":"Montalban",
    "sg:orig_category":"Carnicer\u00cdas, Carnicer\u00cdas",
    "sg:phone":"+34 978 75 01 80",
    "sg:postcode":"44700",
    "sg:province":"Teruel",
    "wof:name":"Salas Alegre Manuel",
    "wof:placetype":"venue"
},
  "geometry": {"coordinates":[-0.7996879816,40.8325195312],"type":"Point"}
}