{
  "type": "Feature",
  "properties": {
    "addr:full":"Carrer de Manso, 30 Barcelona Barcelona 08015",
    "addr:housenumber":"30",
    "addr:postcode":"08015",
    "addr:street":"Carrer De Manso",
    "iso:country":"ES",
    "sg:address":"Carrer de Manso, 30",
    "sg:city":"Barcelona",
    "sg:orig_category":"Juegos Y Juguetes (al Por Menor)",
    "sg:phone":"+34 934 26 74 06",
    "sg:postcode":"08015",
    "sg:province":"Barcelona",
    "wof:name":"Barreiro Avalos Alfonso",
    "wof:placetype":"venue"
},
  "geometry": {"coordinates":[2.1604969501,41.3764266968],"type":"Point"}
}