{
  "type": "Feature",
  "properties": {
    "addr:full":"Calle de Doctor Fleming, 19 Langreo Asturias 33930",
    "addr:housenumber":"19",
    "addr:postcode":"33930",
    "addr:street":"Calle De Doctor Fleming",
    "iso:country":"ES",
    "sg:address":"Calle de Doctor Fleming, 19",
    "sg:city":"Langreo",
    "sg:orig_category":"Comercio De Piezas De Recambio Y De Accesorios De Veh\u00cdculos, Veh\u00cdculos Industriales",
    "sg:phone":"+34 985 69 41 52",
    "sg:postcode":"33930",
    "sg:province":"Asturias",
    "wof:name":"Repuestos Del Nalon S. A.",
    "wof:placetype":"venue"
},
  "geometry": {"coordinates":[-5.6948890686,43.309337616],"type":"Point"}
}