{
  "type": "Feature",
  "properties": {
    "addr:full":"Avda Nuestra Se\u00d1ora De Fatima, 25 Madrid Madrid 28047",
    "addr:housenumber":"25",
    "addr:postcode":"madrid;28047",
    "addr:street":"Avda Nuestra Sen\u0303Ora De Fatima",
    "iso:country":"ES",
    "sg:address":"Avda Nuestra Se\u00d1ora De Fatima, 25",
    "sg:city":"Madrid",
    "sg:orig_category":"Ropa De Hogar (al Por Menor)",
    "sg:phone":"+34 914 65 59 03",
    "sg:postcode":"28047",
    "sg:province":"Madrid",
    "wof:name":"Pritex S.a",
    "wof:placetype":"venue"
},
  "geometry": {"coordinates":[-3.7450919151,40.3853988647],"type":"Point"}
}