{
  "type": "Feature",
  "properties": {
    "iso:country":"ES",
    "sg:address":"Pase Ramon Y Cajal, S/n",
    "sg:city":"Calatayud",
    "sg:orig_category":"Refiner\u00cdas De Petr\u00d3leo",
    "sg:phone":"+34 976 88 16 88",
    "sg:postcode":"50300",
    "sg:province":"Zaragoza",
    "wof:name":"Repsol Ypf S.a.",
    "wof:placetype":"venue"
},
  "geometry": {"coordinates":[-1.6448210478,41.350151062],"type":"Point"}
}