{
  "type": "Feature",
  "properties": {
    "iso:country":"ES",
    "sg:address":"Pla\u00c7 Ajuntament, 3",
    "sg:city":"Oliva",
    "sg:orig_category":"Fabricaci\u00d3n, Venta De Productos Base Farmac\u00c9uticos",
    "sg:phone":"+34 962 85 01 05",
    "sg:postcode":"46780",
    "sg:province":"Valencia",
    "wof:name":"Ronda-catala C.b",
    "wof:placetype":"venue"
},
  "geometry": {"coordinates":[-0.1191760004,38.9200553894],"type":"Point"}
}