{
  "type": "Feature",
  "properties": {
    "addr:full":"Calle de Marques De La Cadena, 40 Zaragoza Zaragoza 50014",
    "addr:housenumber":"40",
    "addr:postcode":"50014",
    "addr:street":"Calle De Marques De La Cadena",
    "iso:country":"ES",
    "sg:address":"Calle de Marques De La Cadena, 40",
    "sg:city":"Zaragoza",
    "sg:orig_category":"Cajas De Ahorro",
    "sg:phone":"+34 976 29 15 88",
    "sg:postcode":"50014",
    "sg:province":"Zaragoza",
    "wof:name":"Caja De Ahorros De La Inmaculada",
    "wof:placetype":"venue"
},
  "geometry": {"coordinates":[-0.8637210131,41.6606788635],"type":"Point"}
}