{
  "type": "Feature",
  "properties": {
    "iso:country":"ES",
    "sg:address":"San Caetano, Km. 0004,3",
    "sg:city":"San Caetano",
    "sg:orig_category":"Centros Empresariales",
    "sg:phone":"+34 986 87 25 52",
    "sg:postcode":"36099",
    "sg:province":"Pontevedra",
    "wof:name":"Centro De Compras E Instalaciones Especiales De Galicia S.a.",
    "wof:placetype":"venue"
},
  "geometry": {"coordinates":[-8.6489601135,42.4695892334],"type":"Point"}
}