{
  "type": "Feature",
  "properties": {
    "addr:full":"Calle de Manuel Echevarria, 1 Cistierna Le\u00f3n 24800",
    "addr:housenumber":"1",
    "addr:postcode":"24800",
    "addr:street":"Calle De Manuel Echevarria;Leo\u0301N",
    "iso:country":"ES",
    "sg:address":"Calle de Manuel Echevarria, 1",
    "sg:city":"Cistierna",
    "sg:classifiers":[
        {
            "category":"Taxi",
            "type":"Transportation"
        }
    ],
    "sg:phone":"+34 987 70 14 23",
    "sg:postcode":"24800",
    "sg:province":"Le\u00f3n",
    "wof:name":"Rodriguez Rodriguez Fernando",
    "wof:placetype":"venue"
},
  "geometry": {"coordinates":[-5.1285719872,42.8067588806],"type":"Point"}
}