{
  "type": "Feature",
  "properties": {
    "addr:full":"Plaz Gernikako Arbola, 4 Urretxu Guip\u00f9zcoa 20700",
    "addr:housenumber":"4",
    "addr:postcode":"20700",
    "addr:street":"Plaz Gernikako Arbola;Guipu\u0300Zcoa",
    "iso:country":"ES",
    "sg:address":"Plaz Gernikako Arbola, 4",
    "sg:city":"Urretxu",
    "sg:orig_category":"Caf\u00c9s, Bares, Cervecer\u00cdas",
    "sg:phone":"+34 943 03 65 10",
    "sg:postcode":"20700",
    "sg:province":"Guip\u00f9zcoa",
    "wof:name":"Jesus Maria Ramos Martinez",
    "wof:placetype":"venue"
},
  "geometry": {"coordinates":[-2.3146340847,43.0914649963],"type":"Point"}
}