{
  "type": "Feature",
  "properties": {
    "addr:full":"Calle de Almirante Ferrandiz, 114 Nerja M\u00e1laga 29780",
    "addr:housenumber":"114",
    "addr:postcode":"29780",
    "addr:street":"Calle De Almirante Ferrandiz",
    "iso:country":"ES",
    "sg:address":"Calle de Almirante Ferrandiz, 114",
    "sg:city":"Nerja",
    "sg:orig_category":"M\u00c9dicos: Estomatolog\u00cda",
    "sg:phone":"+34 952 52 83 74",
    "sg:postcode":"29780",
    "sg:province":"M\u00e1laga",
    "wof:name":"Kullberg  Lars",
    "wof:placetype":"venue"
},
  "geometry": {"coordinates":[-3.8755366802,36.7489814758],"type":"Point"}
}