{
  "type": "Feature",
  "properties": {
    "addr:full":"Carr Guixeres, 53 Badalona Barcelona 08912",
    "addr:housenumber":"53",
    "addr:postcode":"08912",
    "addr:street":"Carr Guixeres",
    "iso:country":"ES",
    "sg:address":"Carr Guixeres, 53",
    "sg:city":"Badalona",
    "sg:orig_category":"Electrodom\u00c9sticos (al Por Menor)",
    "sg:phone":"+34 934 60 03 36",
    "sg:postcode":"08912",
    "sg:province":"Barcelona",
    "wof:name":"Asensio Cervantes Manuel",
    "wof:placetype":"venue"
},
  "geometry": {"coordinates":[2.2397384644,41.4477043152],"type":"Point"}
}