{
  "type": "Feature",
  "properties": {
    "iso:country":"ES",
    "sg:address":"Cami Vell Del Grau, S/n",
    "sg:city":"Grau I Platja",
    "sg:orig_category":"Cajas Y Embalajes De Cart\u00d3n Y Papel",
    "sg:phone":"+34 962 84 03 50",
    "sg:postcode":"46730",
    "sg:province":"Valencia",
    "wof:name":"Cartonajes Union S.l.",
    "wof:placetype":"venue"
},
  "geometry": {"coordinates":[-0.1643390059,38.992805481],"type":"Point"}
}