{
  "type": "Feature",
  "properties": {
    "addr:full":"Calle de Viena, S/n Torreciega Murcia 30392",
    "addr:housenumber":"s",
    "addr:postcode":"30392",
    "addr:street":"Calle De Viena;/ N",
    "iso:country":"ES",
    "sg:address":"Calle de Viena, S/n",
    "sg:city":"Torreciega",
    "sg:orig_category":"Asesor\u00cda Fiscal Y Jur\u00cddica",
    "sg:phone":"+34 968 50 99 58",
    "sg:postcode":"30392",
    "sg:province":"Murcia",
    "wof:name":"Asesoria Maika Coop",
    "wof:placetype":"venue"
},
  "geometry": {"coordinates":[-0.9625045061,37.6242980957],"type":"Point"}
}