{
  "type": "Feature",
  "properties": {
    "iso:country":"ES",
    "sg:address":"Av Llibertat, 85",
    "sg:city":"Elche",
    "sg:orig_category":"Marketing Directo",
    "sg:phone":"+34 966 67 03 09",
    "sg:postcode":"03201",
    "sg:province":"Alicante",
    "wof:name":"Tramites 2000 Coop.valenciana",
    "wof:placetype":"venue"
},
  "geometry": {"coordinates":[-0.7101029754,38.2663154602],"type":"Point"}
}