{
  "type": "Feature",
  "properties": {
    "addr:full":"G.v. Alfonso X El Sabio, S/n San Lorenzo Murcia 30008",
    "addr:housenumber":"s / n",
    "addr:postcode":"30008",
    "addr:street":"Alfonso X El Sabio",
    "iso:country":"ES",
    "sg:address":"G.v. Alfonso X El Sabio, S/n",
    "sg:city":"San Lorenzo",
    "sg:orig_category":"Molduras, Junquillos, Listones Y Molduras Perforadas",
    "sg:phone":"+34 968 23 10 27",
    "sg:postcode":"30008",
    "sg:province":"Murcia",
    "wof:name":"Pesave S.l.",
    "wof:placetype":"venue"
},
  "geometry": {"coordinates":[-1.1302499771,37.9829597473],"type":"Point"}
}