{
  "type": "Feature",
  "properties": {
    "addr:full":"Calle de Fuente De Don Diego, 19 Jaen Ja\u00e9n 23001",
    "addr:housenumber":"19;jae\u0301n",
    "addr:postcode":"23001",
    "addr:street":"Calle De Fuente De Don Diego",
    "iso:country":"ES",
    "sg:address":"Calle de Fuente De Don Diego, 19",
    "sg:city":"Jaen",
    "sg:orig_category":"Arreglo, Reparaci\u00d3n, Piezas Sueltas De Televisi\u00d3n, V\u00cddeo, Hi",
    "sg:phone":"+34 953 23 86 48",
    "sg:postcode":"23001",
    "sg:province":"Ja\u00e9n",
    "wof:name":"Troya Cobo Manuel",
    "wof:placetype":"venue"
},
  "geometry": {"coordinates":[-3.7888329029,37.7634963989],"type":"Point"}
}