{
  "type": "Feature",
  "properties": {
    "addr:full":"Ctra Villablanca-lepe, 8 Villablanca Huelva 21590",
    "addr:housenumber":"8",
    "addr:postcode":"21590",
    "addr:street":"Ctra Villablanca-Lepe",
    "iso:country":"ES",
    "sg:address":"Ctra Villablanca-lepe, 8",
    "sg:city":"Villablanca",
    "sg:orig_category":"Centros Empresariales",
    "sg:phone":"+34 959 34 03 50",
    "sg:postcode":"21590",
    "sg:province":"Huelva",
    "wof:name":"Rafael Morales S.a.",
    "wof:placetype":"venue"
},
  "geometry": {"coordinates":[-7.3429589272,37.3055267334],"type":"Point"}
}