{
  "type": "Feature",
  "properties": {
    "addr:full":"Carrer de Alegria, 18 Premia Mar Barcelona 08330",
    "addr:housenumber":"18",
    "addr:postcode":"08330",
    "addr:street":"Carrer De Alegria",
    "iso:country":"ES",
    "sg:address":"Carrer de Alegria, 18",
    "sg:city":"Premia Mar",
    "sg:classifiers":[
        {
            "category":"Autos & Motor Vehicles",
            "subcategory":"Automobile Sales",
            "type":"Retail Goods"
        }
    ],
    "sg:phone":"+34 937 52 33 28",
    "sg:postcode":"08330",
    "sg:province":"Barcelona",
    "wof:name":"Centre D'ensenyament Integral De La Conduccio S.l.",
    "wof:placetype":"venue"
},
  "geometry": {"coordinates":[2.357640028,41.4919395447],"type":"Point"}
}