{
  "type": "Feature",
  "properties": {
    "iso:country":"ES",
    "sg:address":"Avda Pio Xii, S/n",
    "sg:city":"Valencia",
    "sg:orig_category":"Art\u00cdculos De Regalo (al Por Menor)",
    "sg:phone":"+34 963 46 06 08",
    "sg:postcode":"46015",
    "sg:province":"Valencia",
    "wof:name":"Grasvac S.l.",
    "wof:placetype":"venue"
},
  "geometry": {"coordinates":[-0.3958959877,39.4850387573],"type":"Point"}
}