{
  "type": "Feature",
  "properties": {
    "iso:country":"ES",
    "sg:address":"Polig. De Zies(fragosi\u00f1o), 34",
    "sg:city":"Vigo",
    "sg:orig_category":"Equipo De Refrigeraci\u00d3n Industrial",
    "sg:phone":"+34 986 37 52 11",
    "sg:postcode":"36214",
    "sg:province":"Pontevedra",
    "sg:website":"www.picusmark.es",
    "wof:name":"Picusmark S.l.",
    "wof:placetype":"venue"
},
  "geometry": {"coordinates":[-8.7059106827,42.2124443054],"type":"Point"}
}