{
  "type": "Feature",
  "properties": {
    "iso:country":"ES",
    "sg:address":"Calle de San Juan De La Cruz, 3",
    "sg:city":"Pozuelo De Alarcon",
    "sg:orig_category":"Centros Empresariales",
    "sg:phone":"+34 917 15 21 56",
    "sg:postcode":"28223",
    "sg:province":"Madrid",
    "wof:name":"Martinez Achata Jose Armando",
    "wof:placetype":"venue"
},
  "geometry": {"coordinates":[-3.8172049522,40.4298400879],"type":"Point"}
}