{
  "type": "Feature",
  "properties": {
    "iso:country":"ES",
    "sg:address":"Calle de Dallas, 1",
    "sg:city":"Aguadulce",
    "sg:orig_category":"Guarder\u00cdas",
    "sg:phone":"+34 950 34 89 13",
    "sg:postcode":"04720",
    "sg:province":"Almer\u00eda",
    "wof:name":"Escuela Infantil El Rancho S.l.",
    "wof:placetype":"venue"
},
  "geometry": {"coordinates":[-2.5761330128,36.8178367615],"type":"Point"}
}