{
  "type": "Feature",
  "properties": {
    "iso:country":"ES",
    "sg:address":"Calle de Carril Del Conde, 120",
    "sg:city":"Madrid",
    "sg:orig_category":"Muebles, Minoristas",
    "sg:phone":"+34 913 88 94 88",
    "sg:postcode":"28043",
    "sg:province":"Madrid",
    "wof:name":"Doria Mobiliario S.l.",
    "wof:placetype":"venue"
},
  "geometry": {"coordinates":[-3.6525580883,40.4629020691],"type":"Point"}
}