{
  "type": "Feature",
  "properties": {
    "iso:country":"ES",
    "sg:address":"Calle de Rafael Alberti, 14",
    "sg:city":"Almeria",
    "sg:orig_category":"Venta, Reparaci\u00d3n, Localizaci\u00d3n De Balanzas Y De B\u00c1sculas",
    "sg:phone":"+34 950 27 71 92",
    "sg:postcode":"04004",
    "sg:province":"Almer\u00eda",
    "wof:name":"Rojas Sogorb Alberto",
    "wof:placetype":"venue"
},
  "geometry": {"coordinates":[-2.4603230953,36.8345336914],"type":"Point"}
}