{
  "type": "Feature",
  "properties": {
    "iso:country":"ES",
    "sg:address":"Ctra. Carolina, S/n",
    "sg:city":"Vilches",
    "sg:orig_category":"Cr\u00cda De Cerdos",
    "sg:phone":"+34 953 63 01 07",
    "sg:postcode":"23220",
    "sg:province":"Ja\u00e9n",
    "wof:name":"Sociedad Agraria De Transformacion 5006",
    "wof:placetype":"venue"
},
  "geometry": {"coordinates":[-3.5158240795,38.2159385681],"type":"Point"}
}