{
  "type": "Feature",
  "properties": {
    "iso:country":"ES",
    "sg:address":"Calle de Maestro Gabriel, 11",
    "sg:city":"Valencina Concepcion",
    "sg:orig_category":"Metalurgia",
    "sg:phone":"+34 955 72 76 57",
    "sg:postcode":"41907",
    "sg:province":"Sevilla",
    "wof:name":"Ruiz Salas Francisco",
    "wof:placetype":"venue"
},
  "geometry": {"coordinates":[-6.0742201805,37.4190979004],"type":"Point"}
}