{
  "type": "Feature",
  "properties": {
    "addr:full":"Ctra Pe\u00f1acerrada, S/n Briones La Rioja 26330",
    "addr:housenumber":"s / n",
    "addr:postcode":"26330",
    "addr:street":"Ctra Pen\u0303Acerrada;Briones;Rioja",
    "iso:country":"ES",
    "sg:address":"Ctra Pe\u00f1acerrada, S/n",
    "sg:city":"Briones",
    "sg:orig_category":"Centros De Educaci\u00d3n Especial",
    "sg:phone":"+34 941 32 22 01",
    "sg:postcode":"26330",
    "sg:province":"La Rioja",
    "wof:name":"Comunidad Autonoma De La Rioja",
    "wof:placetype":"venue"
},
  "geometry": {"coordinates":[-2.7845389843,42.5411911011],"type":"Point"}
}