{
  "type": "Feature",
  "properties": {
    "iso:country":"ES",
    "sg:address":"Carrer de Galvani, 49",
    "sg:city":"Terrassa",
    "sg:orig_category":"Venta, Montaje De Neum\u00c1ticos",
    "sg:phone":"+34 937 88 83 45",
    "sg:postcode":"08224",
    "sg:province":"Barcelona",
    "wof:name":"Sans Rodes Enric",
    "wof:placetype":"venue"
},
  "geometry": {"coordinates":[2.0033099651,41.5572013855],"type":"Point"}
}