{
  "type": "Feature",
  "properties": {
    "iso:country":"ES",
    "sg:address":"Avda Campana (la), 20",
    "sg:city":"Lora Rio",
    "sg:orig_category":"Electricidad: Instaladores",
    "sg:phone":"+34 955 80 00 56",
    "sg:postcode":"41440",
    "sg:province":"Sevilla",
    "wof:name":"Antonio Alcantara Luna S.l.",
    "wof:placetype":"venue"
},
  "geometry": {"coordinates":[-5.5249190331,37.6566047668],"type":"Point"}
}