{
  "type": "Feature",
  "properties": {
    "addr:full":"Carr Mallorca, 27 Andratx Islas Baleares 07150",
    "addr:housenumber":"27",
    "addr:postcode":"07150",
    "addr:street":"Carr Mallorca",
    "iso:country":"ES",
    "sg:address":"Carr Mallorca, 27",
    "sg:city":"Andratx",
    "sg:orig_category":"Loter\u00cda Y T\u00d3mbola",
    "sg:phone":"+34 971 13 67 89",
    "sg:postcode":"07150",
    "sg:province":"Islas Baleares",
    "wof:name":"Gomila Soriano Sandra",
    "wof:placetype":"venue"
},
  "geometry": {"coordinates":[2.4185500145,39.5747337341],"type":"Point"}
}