{
  "type": "Feature",
  "properties": {
    "iso:country":"ES",
    "sg:address":"Carr Angeles (los), 38",
    "sg:city":"Aldaia",
    "sg:orig_category":"Molduras, Junquillos, Listones Y Molduras Perforadas",
    "sg:phone":"+34 961 50 64 94",
    "sg:postcode":"46960",
    "sg:province":"Valencia",
    "wof:name":"Ferrandiz Marti Vicente Jesus",
    "wof:placetype":"venue"
},
  "geometry": {"coordinates":[-0.460878998,39.4649238586],"type":"Point"}
}