{
  "type": "Feature",
  "properties": {
    "addr:full":"Calle de Amposta, 18 Madrid Madrid 28037",
    "addr:housenumber":"18",
    "addr:postcode":"madrid;28037",
    "addr:street":"Calle De Amposta",
    "iso:country":"ES",
    "sg:address":"Calle de Amposta, 18",
    "sg:city":"Madrid",
    "sg:orig_category":"Reposter\u00cdas",
    "sg:phone":"+34 913 06 26 80",
    "sg:postcode":"28037",
    "sg:province":"Madrid",
    "wof:name":"Pacheco Calvo Purificacion",
    "wof:placetype":"venue"
},
  "geometry": {"coordinates":[-3.6216988564,40.4265327454],"type":"Point"}
}