{
  "type": "Feature",
  "properties": {
    "iso:country":"ES",
    "sg:address":"Calle de Fuente (la), 3",
    "sg:city":"Navarres",
    "sg:orig_category":"Asociaciones Ecologistas",
    "sg:phone":"+34 962 26 60 52",
    "sg:postcode":"46823",
    "sg:province":"Valencia",
    "wof:name":"Comunidad De Regantesde Navarres",
    "wof:placetype":"venue"
},
  "geometry": {"coordinates":[-0.6937770247,39.1006851196],"type":"Point"}
}