{
  "type": "Feature",
  "properties": {
    "iso:country":"ES",
    "sg:address":"Calle de General Vara De Rey, 9",
    "sg:city":"Logro\u00f1o",
    "sg:orig_category":"Bisuter\u00cda, Joyer\u00cda, Relojer\u00cda (al Por Menor)",
    "sg:phone":"+34 941 24 49 20",
    "sg:postcode":"26002",
    "sg:province":"La Rioja",
    "wof:name":"El Almacen De Cotisol Cb",
    "wof:placetype":"venue"
},
  "geometry": {"coordinates":[-2.4466691017,42.4585189819],"type":"Point"}
}