{
  "type": "Feature",
  "properties": {
    "iso:country":"ES",
    "sg:address":"Carrer de Granada Del Penedes, 18",
    "sg:city":"Barcelona",
    "sg:orig_category":"Inmobiliaria (agencias)",
    "sg:phone":"+34 932 37 43 01",
    "sg:postcode":"08006",
    "sg:province":"Barcelona",
    "sg:website":"www.fincasturo.com",
    "wof:name":"Gestion Inmobiliaria Turo S. L.",
    "wof:placetype":"venue"
},
  "geometry": {"coordinates":[2.1528019905,41.3971557617],"type":"Point"}
}