{
  "type": "Feature",
  "properties": {
    "addr:full":"Calle de Anaya, 10 Barajas Melo Cuenca 16460",
    "addr:housenumber":"10",
    "addr:postcode":"16460",
    "addr:street":"Calle De Anaya",
    "iso:country":"ES",
    "sg:address":"Calle de Anaya, 10",
    "sg:city":"Barajas Melo",
    "sg:orig_category":"Alimentaci\u00d3n General (al Por Menor)",
    "sg:phone":"+34 969 12 10 57",
    "sg:postcode":"16460",
    "sg:province":"Cuenca",
    "wof:name":"Gallego Oliva Alfredo",
    "wof:placetype":"venue"
},
  "geometry": {"coordinates":[-2.9181585312,40.1229629517],"type":"Point"}
}