{
  "type": "Feature",
  "properties": {
    "addr:full":"Calle de San Nicolas, 28 Ubeda Ja\u00e9n 23400",
    "addr:housenumber":"28",
    "addr:postcode":"23400",
    "addr:street":"Calle De San;Ubeda Jae\u0301N",
    "iso:country":"ES",
    "sg:address":"Calle de San Nicolas, 28",
    "sg:city":"Ubeda",
    "sg:orig_category":"Iglesia Cat\u00d3lica",
    "sg:phone":"+34 953 75 05 56",
    "sg:postcode":"23400",
    "sg:province":"Ja\u00e9n",
    "wof:name":"Parroquia San Nicolas",
    "wof:placetype":"venue"
},
  "geometry": {"coordinates":[-3.3689219952,38.0145301819],"type":"Point"}
}