{
  "type": "Feature",
  "properties": {
    "iso:country":"ES",
    "sg:address":"Rua Parque De San Lazaro, 14",
    "sg:city":"Ourense",
    "sg:orig_category":"Panader\u00cdas, Pasteler\u00cdas, Boller\u00cda Industriale (fabricaci\u00d3n, Al Por Mayor)",
    "sg:phone":"+34 988 24 69 71",
    "sg:postcode":"32003",
    "sg:province":"Ourense",
    "wof:name":"Iglesias Martinez Senen",
    "wof:placetype":"venue"
},
  "geometry": {"coordinates":[-7.8628091812,42.3413887024],"type":"Point"}
}