{
  "type": "Feature",
  "properties": {
    "addr:full":"Av. Cruz, 1 Museros Valencia 46136",
    "addr:housenumber":"1",
    "addr:postcode":"46136",
    "addr:street":"Av. Cruz",
    "iso:country":"ES",
    "sg:address":"Av. Cruz, 1",
    "sg:city":"Museros",
    "sg:orig_category":"Prensas Industriales",
    "sg:phone":"+34 961 44 38 34",
    "sg:postcode":"46136",
    "sg:province":"Valencia",
    "wof:name":"Ferruses Perez Ines",
    "wof:placetype":"venue"
},
  "geometry": {"coordinates":[-0.3392310143,39.5616722107],"type":"Point"}
}