{
  "type": "Feature",
  "properties": {
    "addr:full":"Eziago Poligonoa, 25 Eziago Guip\u00f9zcoa 20120",
    "addr:housenumber":"25",
    "addr:postcode":"20120",
    "addr:street":"Eziago Poligonoa;Guipu\u0300Zcoa",
    "iso:country":"ES",
    "sg:address":"Eziago Poligonoa, 25",
    "sg:city":"Eziago",
    "sg:orig_category":"Fabricaci\u00d3n Y Comercio De M\u00c1quinas",
    "sg:phone":"+34 943 55 79 13",
    "sg:postcode":"20120",
    "sg:province":"Guip\u00f9zcoa",
    "wof:name":"Accesorios Industriales Loar S. A.",
    "wof:placetype":"venue"
},
  "geometry": {"coordinates":[-1.9798289537,43.2647514343],"type":"Point"}
}