{
  "type": "Feature",
  "properties": {
    "iso:country":"ES",
    "sg:address":"Carrer de Serra Barona (de La), S/n",
    "sg:city":"Sentmenat",
    "sg:orig_category":"Producci\u00d3n De Abonos Y De Fertilizantes",
    "sg:phone":"+34 937 15 02 37",
    "sg:postcode":"08181",
    "sg:province":"Barcelona",
    "wof:name":"Sadnaco S. A. T.",
    "wof:placetype":"venue"
},
  "geometry": {"coordinates":[2.1174359322,41.6246185303],"type":"Point"}
}