{
  "type": "Feature",
  "properties": {
    "addr:full":"Calle de San Antonio Abad, 34 Zaragoza Zaragoza 50010",
    "addr:housenumber":"34",
    "addr:postcode":"50010",
    "addr:street":"Calle De San Antonio Abad",
    "iso:country":"ES",
    "sg:address":"Calle de San Antonio Abad, 34",
    "sg:city":"Zaragoza",
    "sg:orig_category":"Artes Gr\u00c1ficas, Artes Pl\u00c1sticas (curso)",
    "sg:phone":"+34 976 53 38 78",
    "sg:postcode":"50010",
    "sg:province":"Zaragoza",
    "wof:name":"Gomez Monterde Imprenta Clasica S.l.",
    "wof:placetype":"venue"
},
  "geometry": {"coordinates":[-0.9061819911,41.6546821594],"type":"Point"}
}