{
  "type": "Feature",
  "properties": {
    "iso:country":"ES",
    "sg:address":"C/ Antoni Garcias, 53",
    "sg:city":"Llucmajor",
    "sg:orig_category":"Electricidad: Instalaciones Industriales",
    "sg:phone":"+34 971 12 04 18",
    "sg:postcode":"07620",
    "sg:province":"Islas Baleares",
    "wof:name":"Tecman-llucmajor S.l.",
    "wof:placetype":"venue"
},
  "geometry": {"coordinates":[2.8930580616,39.4857940674],"type":"Point"}
}