{
  "type": "Feature",
  "properties": {
    "addr:full":"Calle de Bristol, 14 Madrid Madrid 28028",
    "addr:housenumber":"14",
    "addr:postcode":"madrid;28028",
    "addr:street":"Calle De Bristol",
    "iso:country":"ES",
    "sg:address":"Calle de Bristol, 14",
    "sg:city":"Madrid",
    "sg:orig_category":"Abogados",
    "sg:phone":"+34 917 25 47 04",
    "sg:postcode":"28028",
    "sg:province":"Madrid",
    "wof:name":"Fernandez Luna Ana",
    "wof:placetype":"venue"
},
  "geometry": {"coordinates":[-3.6619300842,40.4408493042],"type":"Point"}
}