{
  "type": "Feature",
  "properties": {
    "iso:country":"ES",
    "sg:address":"Calle de Genil, S/n",
    "sg:city":"Cotos De Monterrey",
    "sg:orig_category":"Contenedores Para Dep\u00d3sito De Sustancias Peligrosas (fabricaci\u00d3n, Al Por Mayor)",
    "sg:phone":"+34 918 43 86 37",
    "sg:postcode":"28729",
    "sg:province":"Madrid",
    "wof:name":"Inver Contact S.l.",
    "wof:placetype":"venue"
},
  "geometry": {"coordinates":[-3.595733881,40.7999305725],"type":"Point"}
}