{
  "type": "Feature",
  "properties": {
    "addr:full":"Vilaude(s. Pedro De Mor), S/n Vilaude Lugo 27775",
    "addr:housenumber":"s",
    "addr:postcode":"27775",
    "addr:street":"Vilaude;/ N",
    "iso:country":"ES",
    "sg:address":"Vilaude(s. Pedro De Mor), S/n",
    "sg:city":"Vilaude",
    "sg:orig_category":"Material Y Herramientas Agr\u00cdcolas",
    "sg:phone":"+34 982 55 83 82",
    "sg:postcode":"27775",
    "sg:province":"Lugo",
    "wof:name":"Lorenzo Guerreiro Juan Ramon",
    "wof:placetype":"venue"
},
  "geometry": {"coordinates":[-7.4185237885,43.5365905762],"type":"Point"}
}