{
  "type": "Feature",
  "properties": {
    "addr:full":"Calle de Antonio Eulate, 1 Lucena C\u00f3rdoba 14900",
    "addr:housenumber":"1",
    "addr:postcode":"14900",
    "addr:street":"Calle De Antonio Eulate",
    "iso:country":"ES",
    "sg:address":"Calle de Antonio Eulate, 1",
    "sg:city":"Lucena",
    "sg:orig_category":"Abogados",
    "sg:phone":"+34 957 50 94 88",
    "sg:postcode":"14900",
    "sg:province":"C\u00f3rdoba",
    "wof:name":"Barea Ecija Concepcion",
    "wof:placetype":"venue"
},
  "geometry": {"coordinates":[-4.4849500656,37.4073295593],"type":"Point"}
}