{
  "type": "Feature",
  "properties": {
    "iso:country":"ES",
    "sg:address":"Carr Felip Ii, 19",
    "sg:city":"Eivissa",
    "sg:orig_category":"Panader\u00cdas, Panader\u00cdas",
    "sg:phone":"+34 971 31 63 17",
    "sg:postcode":"07800",
    "sg:province":"Islas Baleares",
    "wof:name":"Torres Riera Catalina",
    "wof:placetype":"venue"
},
  "geometry": {"coordinates":[1.432379961,38.9113883972],"type":"Point"}
}