{
  "type": "Feature",
  "properties": {
    "addr:full":"El Muelle, S/n Vegadeo Asturias 33770",
    "addr:housenumber":"s",
    "addr:postcode":"33770",
    "addr:street":"/ N",
    "iso:country":"ES",
    "sg:address":"El Muelle, S/n",
    "sg:city":"Vegadeo",
    "sg:orig_category":"Electricidad Veh\u00cdculo",
    "sg:phone":"+34 985 47 64 46",
    "sg:postcode":"33770",
    "sg:province":"Asturias",
    "wof:name":"Garcia Fernandez Ramon",
    "wof:placetype":"venue"
},
  "geometry": {"coordinates":[-7.0508408546,43.4658813477],"type":"Point"}
}