{
  "type": "Feature",
  "properties": {
    "iso:country":"ES",
    "sg:address":"Carrer de Monestir D'escala Dei, 1",
    "sg:city":"Cambrils Badia",
    "sg:orig_category":"Pintores",
    "sg:phone":"+34 977 36 53 62",
    "sg:postcode":"43850",
    "sg:province":"Tarragona",
    "wof:name":"Vazquez Maceira Antonio",
    "wof:placetype":"venue"
},
  "geometry": {"coordinates":[1.0688710213,41.069229126],"type":"Point"}
}