{
  "type": "Feature",
  "properties": {
    "iso:country":"ES",
    "sg:address":"Plaz Poeta Salvador Rueda, 3",
    "sg:city":"Valencia",
    "sg:orig_category":"Promotores Constructores",
    "sg:phone":"+34 963 48 77 36",
    "sg:postcode":"46009",
    "sg:province":"Valencia",
    "wof:name":"Progalzar S.l.",
    "wof:placetype":"venue"
},
  "geometry": {"coordinates":[-0.3891659975,39.4865837097],"type":"Point"}
}