{
  "type": "Feature",
  "properties": {
    "addr:full":"Avda Virgen De Fatima (de), 2 Cordoba C\u00f3rdoba 14014",
    "addr:postcode":"14014",
    "addr:street":"Avda Virgen;Co\u0301Rdoba",
    "iso:country":"ES",
    "sg:address":"Avda Virgen De Fatima (de), 2",
    "sg:city":"Cordoba",
    "sg:orig_category":"Fabricaci\u00d3n, Importaci\u00d3n, Venta De Material De Telefon\u00cda, Peritelefon\u00cda",
    "sg:phone":"+34 957 43 66 88",
    "sg:postcode":"14014",
    "sg:province":"C\u00f3rdoba",
    "wof:name":"Tirado Armenteros Federico",
    "wof:placetype":"venue"
},
  "geometry": {"coordinates":[-4.7615451813,37.8983039856],"type":"Point"}
}