{
  "type": "Feature",
  "properties": {
    "addr:full":"Carrer de Teodor Gonzalez (de), 6 Tortosa Tarragona 43500",
    "addr:postcode":"43500",
    "addr:street":"Carrer De Teodor Gonzalez De",
    "iso:country":"ES",
    "sg:address":"Carrer de Teodor Gonzalez (de), 6",
    "sg:city":"Tortosa",
    "sg:orig_category":"Centros De Coordinaci\u00d3n",
    "sg:phone":"+34 977 44 00 62",
    "sg:postcode":"43500",
    "sg:province":"Tarragona",
    "wof:name":"Mauri Gestions S.l.",
    "wof:placetype":"venue"
},
  "geometry": {"coordinates":[0.5196099877,40.8099021912],"type":"Point"}
}