{
  "type": "Feature",
  "properties": {
    "addr:full":"Carrer de Roca, 2 Sabadell Barcelona 08208",
    "addr:housenumber":"2",
    "addr:postcode":"08208",
    "addr:street":"Carrer De Roca",
    "iso:country":"ES",
    "sg:address":"Carrer de Roca, 2",
    "sg:city":"Sabadell",
    "sg:orig_category":"Agencias Y Agentes Comerciales, Representantes",
    "sg:phone":"+34 937 25 29 79",
    "sg:postcode":"08208",
    "sg:province":"Barcelona",
    "wof:name":"Casas Flaque Armando",
    "wof:placetype":"venue"
},
  "geometry": {"coordinates":[2.1017169952,41.5511016846],"type":"Point"}
}