{
  "type": "Feature",
  "properties": {
    "iso:country":"ES",
    "sg:address":"Carrer de Armenteres, 18",
    "sg:city":"Sant Feliu Llobregat",
    "sg:orig_category":"Peluqueros: De Se\u00d1oras",
    "sg:phone":"+34 936 66 61 53",
    "sg:postcode":"08980",
    "sg:province":"Barcelona",
    "wof:name":"Daban Jordan Maria Luisa",
    "wof:placetype":"venue"
},
  "geometry": {"coordinates":[2.0436201096,41.3797492981],"type":"Point"}
}