{
  "type": "Feature",
  "properties": {
    "addr:full":"Calle de Nicolas Arguelles, 4 Entrego Asturias 33940",
    "addr:housenumber":"4",
    "addr:postcode":"33940",
    "addr:street":"Calle De Nicolas Arguelles",
    "iso:country":"ES",
    "sg:address":"Calle de Nicolas Arguelles, 4",
    "sg:city":"Entrego",
    "sg:orig_category":"Perfumer\u00cda, Art\u00cdculos De Ba\u00d1o (fabricaci\u00d3n, Al Por Mayor)",
    "sg:phone":"+34 985 66 09 42",
    "sg:postcode":"33940",
    "sg:province":"Asturias",
    "wof:name":"Drofel S.l.",
    "wof:placetype":"venue"
},
  "geometry": {"coordinates":[-5.6435742378,43.2864112854],"type":"Point"}
}