{
  "type": "Feature",
  "properties": {
    "addr:full":"Outeiro, 30 Outeiro La Coru\u00f1a 15578",
    "addr:housenumber":"30",
    "addr:postcode":"15578",
    "addr:street":"Outeiro;La Corun\u0303A",
    "iso:country":"ES",
    "sg:address":"Outeiro, 30",
    "sg:city":"Outeiro",
    "sg:orig_category":"Molduras, Junquillos, Listones Y Molduras Perforadas",
    "sg:phone":"+34 981 38 32 28",
    "sg:postcode":"15578",
    "sg:province":"La Coru\u00f1a",
    "wof:name":"Blanco Sierra Antonio",
    "wof:placetype":"venue"
},
  "geometry": {"coordinates":[-8.1806354523,43.5493278503],"type":"Point"}
}