{
  "type": "Feature",
  "properties": {
    "iso:country":"ES",
    "sg:address":"Carrer de Sant Joan, 7",
    "sg:city":"Centelles",
    "sg:orig_category":"Perfumer\u00cda Y Cosm\u00c9tica (fabricaci\u00d3n, Al Por Mayor)",
    "sg:phone":"+34 938 81 20 04",
    "sg:postcode":"08540",
    "sg:province":"Barcelona",
    "wof:name":"Perez Marsal Maria Jose",
    "wof:placetype":"venue"
},
  "geometry": {"coordinates":[2.2188611031,41.7957458496],"type":"Point"}
}