{
  "type": "Feature",
  "properties": {
    "addr:full":"Rua Padre Feijoo, 17 Ourense Ourense 32005",
    "addr:housenumber":"17",
    "addr:postcode":"32005",
    "addr:street":"Rua Padre Feijoo",
    "iso:country":"ES",
    "sg:address":"Rua Padre Feijoo, 17",
    "sg:city":"Ourense",
    "sg:orig_category":"Caf\u00c9s, Bares, Cervecer\u00cdas",
    "sg:phone":"+34 988 24 03 85",
    "sg:postcode":"32005",
    "sg:province":"Ourense",
    "wof:name":"Galtelcom",
    "wof:placetype":"venue"
},
  "geometry": {"coordinates":[-7.8585562706,42.3233680725],"type":"Point"}
}