{
  "type": "Feature",
  "properties": {
    "addr:full":"Calle de Eras, S/n Venialbo Zamora 49153",
    "addr:housenumber":"s",
    "addr:postcode":"49153",
    "addr:street":"Calle De Eras;/ N Venialbo Zamora",
    "iso:country":"ES",
    "sg:address":"Calle de Eras, S/n",
    "sg:city":"Venialbo",
    "sg:orig_category":"Centros De Educaci\u00d3n Especial",
    "sg:phone":"+34 980 57 31 33",
    "sg:postcode":"49153",
    "sg:province":"Zamora",
    "wof:name":"Colegio Rural Agrupado De Moraleja Del Vino",
    "wof:placetype":"venue"
},
  "geometry": {"coordinates":[-5.5345492363,41.3901138306],"type":"Point"}
}