{
  "type": "Feature",
  "properties": {
    "iso:country":"ES",
    "sg:address":"Camino Viejo Simancas, Km. 0004,0",
    "sg:city":"Valladolid",
    "sg:orig_category":"Escuela De Arte Dram\u00c1tico",
    "sg:phone":"+34 983 23 60 40",
    "sg:postcode":"47008",
    "sg:province":"Valladolid",
    "wof:name":"Forum Escuela-promocion S.l.",
    "wof:placetype":"venue"
},
  "geometry": {"coordinates":[-4.7445249557,41.6281471252],"type":"Point"}
}