{
  "type": "Feature",
  "properties": {
    "addr:full":"Calle de Ramon Y Cajal, 11 Miranda Ebro Burgos 09200",
    "addr:housenumber":"11",
    "addr:postcode":"09200",
    "addr:street":"Calle De Ramon Y Cajal",
    "iso:country":"ES",
    "sg:address":"Calle de Ramon Y Cajal, 11",
    "sg:city":"Miranda Ebro",
    "sg:orig_category":"Farmacias",
    "sg:phone":"+34 947 31 11 44",
    "sg:postcode":"09200",
    "sg:province":"Burgos",
    "wof:name":"Pe\u00f1a Valbuena Maria Mercedes",
    "wof:placetype":"venue"
},
  "geometry": {"coordinates":[-2.9434919357,42.6872138977],"type":"Point"}
}