{
  "type": "Feature",
  "properties": {
    "addr:full":"Carrer de Corsega, 74 Barcelona Barcelona 08029",
    "addr:housenumber":"74",
    "addr:postcode":"08029",
    "addr:street":"Carrer De Corsega",
    "iso:country":"ES",
    "sg:address":"Carrer de Corsega, 74",
    "sg:city":"Barcelona",
    "sg:orig_category":"Farmacias",
    "sg:phone":"+34 934 39 68 66",
    "sg:postcode":"08029",
    "sg:province":"Barcelona",
    "wof:name":"Puig Domingo Maria",
    "wof:placetype":"venue"
},
  "geometry": {"coordinates":[2.1446020603,41.3852272034],"type":"Point"}
}