{
  "type": "Feature",
  "properties": {
    "addr:full":"Carrer de Raimon D'abadal, 12 Vic Barcelona 08500",
    "addr:housenumber":"12",
    "addr:postcode":"08500",
    "addr:street":"Carrer De Raimon D'Abadal",
    "iso:country":"ES",
    "sg:address":"Carrer de Raimon D'abadal, 12",
    "sg:city":"Vic",
    "sg:orig_category":"Agentes, Concesionarios Y Sucursales De Veh\u00cdculos",
    "sg:phone":"+34 938 83 36 26",
    "sg:postcode":"08500",
    "sg:province":"Barcelona",
    "wof:name":"Daniel Rovira S. A.",
    "wof:placetype":"venue"
},
  "geometry": {"coordinates":[2.2517991066,41.9217948914],"type":"Point"}
}