{
  "type": "Feature",
  "properties": {
    "iso:country":"ES",
    "sg:address":"Carrer de Consolat De Mar, 36",
    "sg:city":"Cambrils",
    "sg:orig_category":"Bazares, Art\u00cdculos De Limpieza Y De Cocina (al Por Menor)",
    "sg:phone":"+34 977 36 03 79",
    "sg:postcode":"43850",
    "sg:province":"Tarragona",
    "wof:name":"Tutusaus Costa Rosa Maria",
    "wof:placetype":"venue"
},
  "geometry": {"coordinates":[1.0612800121,41.065700531],"type":"Point"}
}