{
  "type": "Feature",
  "properties": {
    "addr:full":"Carr Sant Sebastia, 94 Santa Coloma De Farners Girona 17430",
    "addr:housenumber":"94",
    "addr:postcode":"17430",
    "addr:street":"Carr Sant Sebastia",
    "iso:country":"ES",
    "sg:address":"Carr Sant Sebastia, 94",
    "sg:city":"Santa Coloma De Farners",
    "sg:orig_category":"Doctores En Medicina",
    "sg:phone":"+34 972 84 08 37",
    "sg:postcode":"17430",
    "sg:province":"Girona",
    "wof:name":"Gonzalez Escarda Fermin",
    "wof:placetype":"venue"
},
  "geometry": {"coordinates":[2.6672899723,41.8610839844],"type":"Point"}
}