{
  "type": "Feature",
  "properties": {
    "addr:full":"Calle de Serrano, 15 Alacant Alicante 03003",
    "addr:housenumber":"15",
    "addr:postcode":"03003",
    "addr:street":"Calle De Serrano",
    "iso:country":"ES",
    "sg:address":"Calle de Serrano, 15",
    "sg:city":"Alacant",
    "sg:orig_category":"M\u00c9dicos: Neurolog\u00cda",
    "sg:phone":"+34 965 92 11 39",
    "sg:postcode":"03003",
    "sg:province":"Alicante",
    "wof:name":"Leiva Santana Carlos",
    "wof:placetype":"venue"
},
  "geometry": {"coordinates":[-0.4938459992,38.3446464539],"type":"Point"}
}