{
  "type": "Feature",
  "properties": {
    "iso:country":"ES",
    "sg:address":"Calle de Zocotin, 9",
    "sg:city":"Jaca",
    "sg:classifiers":[
        {
            "category":"Personal",
            "subcategory":"Barber",
            "type":"Services"
        }
    ],
    "sg:phone":"+34 974 36 37 30",
    "sg:postcode":"22700",
    "sg:province":"Huesca",
    "sg:tags":[
        "caballeros",
        "de",
        "peluqueros"
    ],
    "wof:name":"Lacasta Gracia Ricardo",
    "wof:placetype":"venue"
},
  "geometry": {"coordinates":[-0.5489265919,42.5699539185],"type":"Point"}
}