{
  "type": "Feature",
  "properties": {
    "addr:full":"Calle de Delicias, 101 Madrid Madrid 28045",
    "addr:housenumber":"101",
    "addr:postcode":"28045",
    "addr:street":"Calle De Delicias",
    "iso:country":"ES",
    "sg:address":"Calle de Delicias, 101",
    "sg:city":"Madrid",
    "sg:orig_category":"Abogados",
    "sg:phone":"+34 915 28 84 25",
    "sg:postcode":"28045",
    "sg:province":"Madrid",
    "wof:name":"Centro De Formacion De Abogados De Madrid S.l",
    "wof:placetype":"venue"
},
  "geometry": {"coordinates":[-3.6945948601,40.3948631287],"type":"Point"}
}