{
  "type": "Feature",
  "properties": {
    "iso:country":"ES",
    "sg:address":"Carrer de Montflorit, 57",
    "sg:city":"Gava",
    "sg:orig_category":"Promotores Constructores",
    "sg:phone":"+34 936 33 69 41",
    "sg:postcode":"08850",
    "sg:province":"Barcelona",
    "wof:name":"Fretispa S.l.",
    "wof:placetype":"venue"
},
  "geometry": {"coordinates":[2.0010249615,41.3015556335],"type":"Point"}
}