{
  "type": "Feature",
  "properties": {
    "addr:full":"Calle de Porra (la), 2 Arrecife Las Palmas 35500",
    "addr:housenumber":"2",
    "addr:postcode":"35500",
    "addr:street":"Calle De Porra La",
    "iso:country":"ES",
    "sg:address":"Calle de Porra (la), 2",
    "sg:city":"Arrecife",
    "sg:orig_category":"Asociaciones Humanitarias, De Cooperaci\u00d3n, De Acci\u00d3n Social",
    "sg:phone":"+34 928 81 11 10",
    "sg:postcode":"35500",
    "sg:province":"Las Palmas",
    "wof:name":"Organizacion Nacional De Ciegos",
    "wof:placetype":"venue"
},
  "geometry": {"coordinates":[-13.5507898331,28.9592342377],"type":"Point"}
}