{
  "type": "Feature",
  "properties": {
    "addr:full":"Plaz Jesus Nazareno, 19 Cadiz C\u00e1diz 11002",
    "addr:housenumber":"19",
    "addr:postcode":"11002",
    "addr:street":"Cadiz Ca\u0301Diz",
    "iso:country":"ES",
    "sg:address":"Plaz Jesus Nazareno, 19",
    "sg:city":"Cadiz",
    "sg:orig_category":"Supermercados Y Hipermercados",
    "sg:phone":"+34 956 22 12 12",
    "sg:postcode":"11002",
    "sg:province":"C\u00e1diz",
    "wof:name":"Torres Vera Jose",
    "wof:placetype":"venue"
},
  "geometry": {"coordinates":[-6.3025679588,36.5315856934],"type":"Point"}
}