{
  "type": "Feature",
  "properties": {
    "addr:full":"Ptda Brasals, S/n Sueca Valencia 46410",
    "addr:housenumber":"s",
    "addr:postcode":"46410",
    "addr:street":"Ptda Brasals;/ N",
    "iso:country":"ES",
    "sg:address":"Ptda Brasals, S/n",
    "sg:city":"Sueca",
    "sg:orig_category":"Negocio De Madera",
    "sg:phone":"+34 961 70 18 17",
    "sg:postcode":"46410",
    "sg:province":"Valencia",
    "wof:name":"Bonet Llopis Guillermo",
    "wof:placetype":"venue"
},
  "geometry": {"coordinates":[-0.3076440096,39.2027435303],"type":"Point"}
}