{
  "type": "Feature",
  "properties": {
    "addr:full":"Calle de Maestro Vives, 2 Castellon Castell\u00f3n 12005",
    "addr:housenumber":"2",
    "addr:postcode":"12005",
    "addr:street":"Calle De Maestro Vives;Castello\u0301N",
    "iso:country":"ES",
    "sg:address":"Calle de Maestro Vives, 2",
    "sg:city":"Castellon",
    "sg:orig_category":"Asesor\u00cda Sobre Comunicaci\u00d3n De Empresas",
    "sg:phone":"+34 964 22 97 21",
    "sg:postcode":"12005",
    "sg:province":"Castell\u00f3n",
    "wof:name":"Malo Maldonado Angel",
    "wof:placetype":"venue"
},
  "geometry": {"coordinates":[-0.0359219983,39.9814567566],"type":"Point"}
}