{
  "type": "Feature",
  "properties": {
    "iso:country":"ES",
    "sg:address":"Ctra Alcala, Km. 0008,7",
    "sg:city":"Daganzo Arriba",
    "sg:orig_category":"Panader\u00cdas, Panader\u00cdas",
    "sg:phone":"+34 918 84 12 50",
    "sg:postcode":"28814",
    "sg:province":"Madrid",
    "wof:name":"Fresh Start Bakeries S.l.",
    "wof:placetype":"venue"
},
  "geometry": {"coordinates":[-3.4572339058,40.5436286926],"type":"Point"}
}