{
  "type": "Feature",
  "properties": {
    "addr:full":"Ronda, S/n Benifairo Valldigna Valencia 46791",
    "addr:postcode":"46791",
    "addr:street":"Ronda S / N",
    "iso:country":"ES",
    "sg:address":"Ronda, S/n",
    "sg:city":"Benifairo Valldigna",
    "sg:orig_category":"Arboricultura Y Producci\u00d3n De Frutas",
    "sg:phone":"+34 962 81 03 26",
    "sg:postcode":"46791",
    "sg:province":"Valencia",
    "wof:name":"Frutas Tono S.l.",
    "wof:placetype":"venue"
},
  "geometry": {"coordinates":[-0.3047139943,39.0570259094],"type":"Point"}
}