{
  "type": "Feature",
  "properties": {
    "iso:country":"ES",
    "sg:address":"Mercat Proven\u00e7als, S/n",
    "sg:city":"Barcelona",
    "sg:orig_category":"Frutas, Legumbres Frescas Y Tempranas (al Por Menor)",
    "sg:phone":"+34 933 14 06 92",
    "sg:postcode":"08005",
    "sg:province":"Barcelona",
    "wof:name":"Bajo Cerro Alcarrer S.l.",
    "wof:placetype":"venue"
},
  "geometry": {"coordinates":[2.2015347481,41.3977355957],"type":"Point"}
}