{
  "type": "Feature",
  "properties": {
    "iso:country":"ES",
    "sg:address":"Avda Italia (de), 24",
    "sg:city":"Granada",
    "sg:orig_category":"Electricidad: Instaladores",
    "sg:phone":"+34 958 81 69 58",
    "sg:postcode":"18007",
    "sg:province":"Granada",
    "wof:name":"Gonzalez Remacho Maria Del Carmen",
    "wof:placetype":"venue"
},
  "geometry": {"coordinates":[-3.5976569653,37.1576652527],"type":"Point"}
}