{
  "type": "Feature",
  "properties": {
    "addr:full":"Avda Iparralde, 59 Irun Guip\u00f9zcoa 20304",
    "addr:housenumber":"59",
    "addr:postcode":"20304",
    "addr:street":"Avda Iparralde;Guipu\u0300Zcoa",
    "iso:country":"ES",
    "sg:address":"Avda Iparralde, 59",
    "sg:city":"Irun",
    "sg:orig_category":"Albergues",
    "sg:phone":"+34 943 62 24 08",
    "sg:postcode":"20304",
    "sg:province":"Guip\u00f9zcoa",
    "wof:name":"Blanco Sosa Alfonso",
    "wof:placetype":"venue"
},
  "geometry": {"coordinates":[-1.7859899998,43.349521637],"type":"Point"}
}