{
  "type": "Feature",
  "properties": {
    "addr:full":"Calle de Honorio Lozano, 51 Estacion Madrid 28400",
    "addr:housenumber":"51",
    "addr:postcode":"28400",
    "addr:street":"Calle De Honorio Lozano",
    "iso:country":"ES",
    "sg:address":"Calle de Honorio Lozano, 51",
    "sg:city":"Estacion",
    "sg:orig_category":"Administradores De Bienes Y Delegados De Comunidades De Propietarios",
    "sg:phone":"+34 918 50 28 38",
    "sg:postcode":"28400",
    "sg:province":"Madrid",
    "wof:name":"Lopez Merino Y Rozas Consultores S.l.l.",
    "wof:placetype":"venue"
},
  "geometry": {"coordinates":[-3.7003455162,40.4166908264],"type":"Point"}
}