{
  "type": "Feature",
  "properties": {
    "iso:country":"ES",
    "sg:address":"Calle de Don Pio Coronado, 204",
    "sg:city":"Palmas De Gran Canaria",
    "sg:orig_category":"Alimentaci\u00d3n General (al Por Menor)",
    "sg:phone":"+34 928 20 10 55",
    "sg:postcode":"35012",
    "sg:province":"Las Palmas",
    "wof:name":"Quintana Rodriguez Oscar",
    "wof:placetype":"venue"
},
  "geometry": {"coordinates":[-15.4387931824,28.1067867279],"type":"Point"}
}