{
  "type": "Feature",
  "properties": {
    "addr:full":"Avda Doctor Oloriz, 11 Granada Granada 18012",
    "addr:housenumber":"11",
    "addr:postcode":"18012",
    "addr:street":"Avda Doctor Oloriz",
    "iso:country":"ES",
    "sg:address":"Avda Doctor Oloriz, 11",
    "sg:city":"Granada",
    "sg:orig_category":"Bisuter\u00cda, Joyer\u00cda, Relojer\u00cda (al Por Menor)",
    "sg:phone":"+34 958 28 46 02",
    "sg:postcode":"18012",
    "sg:province":"Granada",
    "wof:name":"Rodriguez Iba\u00f1ez Maria Del Carmen",
    "wof:placetype":"venue"
},
  "geometry": {"coordinates":[-3.6078369617,37.1872787476],"type":"Point"}
}