{
  "type": "Feature",
  "properties": {
    "iso:country":"ES",
    "sg:address":"El Molinillo, S/n",
    "sg:city":"Retuerta Bullaque",
    "sg:orig_category":"Cr\u00cda De Animales",
    "sg:phone":"+34 925 59 10 25",
    "sg:postcode":"13194",
    "sg:province":"Ciudad Real",
    "wof:name":"Pecuaria Concertada El Molinillo S. A.",
    "wof:placetype":"venue"
},
  "geometry": {"coordinates":[-4.2126998901,39.4660987854],"type":"Point"}
}