{
  "type": "Feature",
  "properties": {
    "addr:full":"Calle de Fanega, 1 Valladolid Valladolid 47009",
    "addr:housenumber":"1",
    "addr:postcode":"47009",
    "addr:street":"Calle De Fanega",
    "iso:country":"ES",
    "sg:address":"Calle de Fanega, 1",
    "sg:city":"Valladolid",
    "sg:orig_category":"Centros Empresariales",
    "sg:phone":"+34 983 35 57 25",
    "sg:postcode":"47009",
    "sg:province":"Valladolid",
    "sg:website":"www.aprosi.net",
    "wof:name":"Asesora Y Proovedora De Servicios De Internet S.l.",
    "wof:placetype":"venue"
},
  "geometry": {"coordinates":[-4.7438621521,41.654460907],"type":"Point"}
}