{
  "type": "Feature",
  "properties": {
    "addr:full":"Calle de Iglesia, 14 Polan Toledo 45161",
    "addr:housenumber":"14",
    "addr:postcode":"45161",
    "addr:street":"Calle De Iglesia",
    "iso:country":"ES",
    "sg:address":"Calle de Iglesia, 14",
    "sg:city":"Polan",
    "sg:orig_category":"Promotores Constructores",
    "sg:phone":"+34 925 37 01 04",
    "sg:postcode":"45161",
    "sg:province":"Toledo",
    "wof:name":"Urbiter S.l.",
    "wof:placetype":"venue"
},
  "geometry": {"coordinates":[-4.169271946,39.7880363464],"type":"Point"}
}