{
  "type": "Feature",
  "properties": {
    "iso:country":"ES",
    "sg:address":"Rbla Guipuscoa, 98",
    "sg:city":"Barcelona",
    "sg:orig_category":"Mercer\u00cda, Lencer\u00cda (al Por Menor)",
    "sg:phone":"+34 933 14 33 19",
    "sg:postcode":"08020",
    "sg:province":"Barcelona",
    "wof:name":"Sanjaume Carbonell Carmen",
    "wof:placetype":"venue"
},
  "geometry": {"coordinates":[2.2009599209,41.4188957214],"type":"Point"}
}