{
  "type": "Feature",
  "properties": {
    "iso:country":"ES",
    "sg:address":"Av Parc, 1",
    "sg:city":"Granollers",
    "sg:orig_category":"Fotocopias, Reprograf\u00cda",
    "sg:phone":"+34 938 79 18 87",
    "sg:postcode":"08402",
    "sg:province":"Barcelona",
    "wof:name":"Buitrago Torres Alba Ines",
    "wof:placetype":"venue"
},
  "geometry": {"coordinates":[2.290405035,41.6061019897],"type":"Point"}
}