{
  "type": "Feature",
  "properties": {
    "iso:country":"ES",
    "sg:address":"Calle de Tres Forques, 116",
    "sg:city":"Valencia",
    "sg:orig_category":"Importaci\u00d3n",
    "sg:phone":"+34 963 50 17 94",
    "sg:postcode":"46014",
    "sg:province":"Valencia",
    "wof:name":"Tinexco S.l.",
    "wof:placetype":"venue"
},
  "geometry": {"coordinates":[-0.4064129889,39.4637413025],"type":"Point"}
}