{
  "type": "Feature",
  "properties": {
    "iso:country":"ES",
    "sg:address":"Calle de Convento, 30",
    "sg:city":"Cartaya",
    "sg:orig_category":"Abogados",
    "sg:phone":"+34 959 39 07 53",
    "sg:postcode":"21450",
    "sg:province":"Huelva",
    "wof:name":"Arduan Perez Gustavo Enrique",
    "wof:placetype":"venue"
},
  "geometry": {"coordinates":[-7.1525239944,37.2830200195],"type":"Point"}
}