{
  "type": "Feature",
  "properties": {
    "addr:full":"Calle de Londres, S/n Torrejon Ardoz Madrid 28850",
    "addr:housenumber":"s / n",
    "addr:postcode":"28850",
    "addr:street":"Calle De Londres",
    "iso:country":"ES",
    "sg:address":"Calle de Londres, S/n",
    "sg:city":"Torrejon Ardoz",
    "sg:orig_category":"Cajas De Ahorro",
    "sg:phone":"+34 916 76 07 62",
    "sg:postcode":"28850",
    "sg:province":"Madrid",
    "sg:website":"www.lacaixa.es",
    "wof:name":"Caixa D'estalvis I Pensions De Barcelona",
    "wof:placetype":"venue"
},
  "geometry": {"coordinates":[-3.4629039764,40.4618988037],"type":"Point"}
}