{
  "type": "Feature",
  "properties": {
    "iso:country":"ES",
    "sg:address":"Calle de Mayor, 3",
    "sg:city":"Alagon",
    "sg:orig_category":"Confecci\u00d3n (fabricaci\u00d3n, Al Por Mayor)",
    "sg:phone":"+34 976 61 01 88",
    "sg:postcode":"50630",
    "sg:province":"Zaragoza",
    "wof:name":"Larrode Lara Maria Del Carmen",
    "wof:placetype":"venue"
},
  "geometry": {"coordinates":[-1.119732976,41.7692489624],"type":"Point"}
}