{
  "type": "Feature",
  "properties": {
    "addr:full":"Carrer de Moli Dels Lledo, 23 Cardedeu Barcelona 08440",
    "addr:housenumber":"23",
    "addr:postcode":"08440",
    "addr:street":"Carrer De Moli Dels Lledo",
    "iso:country":"ES",
    "sg:address":"Carrer de Moli Dels Lledo, 23",
    "sg:city":"Cardedeu",
    "sg:orig_category":"Sociedades, Compa\u00d1\u00cdas Aseguradoras",
    "sg:phone":"+34 938 44 42 16",
    "sg:postcode":"08440",
    "sg:province":"Barcelona",
    "wof:name":"Camps I Bataller S.l.",
    "wof:placetype":"venue"
},
  "geometry": {"coordinates":[2.353687048,41.6400947571],"type":"Point"}
}