{
  "type": "Feature",
  "properties": {
    "addr:full":"Calle de San Francisco De Sales, S/n Cordoba C\u00f3rdoba 14010",
    "addr:housenumber":"s / n",
    "addr:postcode":"14010",
    "addr:street":"Calle De San Francisco De Sales;Co\u0301Rdoba",
    "iso:country":"ES",
    "sg:address":"Calle de San Francisco De Sales, S/n",
    "sg:city":"Cordoba",
    "sg:orig_category":"Centros De Educaci\u00d3n Especial",
    "sg:phone":"+34 957 76 45 98",
    "sg:postcode":"14010",
    "sg:province":"C\u00f3rdoba",
    "wof:name":"Junta De Andalucia",
    "wof:placetype":"venue"
},
  "geometry": {"coordinates":[-4.7658638954,37.8879585266],"type":"Point"}
}