{
  "type": "Feature",
  "properties": {
    "iso:country":"ES",
    "sg:address":"Calle de Rafael Argeles, 15",
    "sg:city":"Algeciras",
    "sg:orig_category":"Farmacias",
    "sg:phone":"+34 956 66 27 48",
    "sg:postcode":"11202",
    "sg:province":"C\u00e1diz",
    "wof:name":"Jimenez Lopez Maria De Los Angeles",
    "wof:placetype":"venue"
},
  "geometry": {"coordinates":[-5.4518909454,36.1353149414],"type":"Point"}
}