{
  "type": "Feature",
  "properties": {
    "iso:country":"ES",
    "sg:address":"Calle de Portillejo, 45",
    "sg:city":"Logro\u00f1o",
    "sg:orig_category":"Trabajos De Topograf\u00cda",
    "sg:phone":"+34 941 51 91 29",
    "sg:postcode":"26006",
    "sg:province":"La Rioja",
    "wof:name":"Itc Vertice S.c.",
    "wof:placetype":"venue"
},
  "geometry": {"coordinates":[-2.4665369987,42.46717453],"type":"Point"}
}