{
  "type": "Feature",
  "properties": {
    "iso:country":"ES",
    "sg:address":"Calle de Garcia Lorca, 2",
    "sg:city":"Onil",
    "sg:orig_category":"Asociaciones Y Clubs Deportivos",
    "sg:phone":"+34 965 56 59 48",
    "sg:postcode":"03430",
    "sg:province":"Alicante",
    "wof:name":"Sempere Sanchez S.l.",
    "wof:placetype":"venue"
},
  "geometry": {"coordinates":[-0.6756309867,38.623840332],"type":"Point"}
}