{
  "type": "Feature",
  "properties": {
    "iso:country":"ES",
    "sg:address":"Carrer de Perot Rocaguinarda, 14",
    "sg:city":"Vic",
    "sg:orig_category":"Maquinaria Para Industrias Diversas",
    "sg:phone":"+34 938 85 04 96",
    "sg:postcode":"08500",
    "sg:province":"Barcelona",
    "sg:website":"www.macoinvic.com",
    "wof:name":"Macoinvic S.l.",
    "wof:placetype":"venue"
},
  "geometry": {"coordinates":[2.2467939854,41.9289703369],"type":"Point"}
}