{
  "type": "Feature",
  "properties": {
    "iso:country":"ES",
    "sg:address":"Carrer de Periodista Grane, 24",
    "sg:city":"Terrassa",
    "sg:orig_category":"Fabricaci\u00d3n De Su\u00c9ters Y Chalecos De Punto",
    "sg:phone":"+34 937 85 37 01",
    "sg:postcode":"08226",
    "sg:province":"Barcelona",
    "sg:website":"www.intermode.net/empresa/illsa",
    "wof:name":"Ignacio Lloveras S.a.",
    "wof:placetype":"venue"
},
  "geometry": {"coordinates":[2.0242049694,41.5699195862],"type":"Point"}
}