{
  "type": "Feature",
  "properties": {
    "iso:country":"ES",
    "sg:address":"Rua Rai\u00d1a (da), 6",
    "sg:city":"Lugo",
    "sg:orig_category":"Porcelanas, Azulejos (fabricaci\u00d3n, Al Por Mayor)",
    "sg:phone":"+34 982 24 18 08",
    "sg:postcode":"27001",
    "sg:province":"Lugo",
    "wof:name":"Blanco Cando Maria Luisa",
    "wof:placetype":"venue"
},
  "geometry": {"coordinates":[-7.5558209419,43.0110092163],"type":"Point"}
}