{
  "type": "Feature",
  "properties": {
    "iso:country":"ES",
    "sg:address":"Calle de Labradores, 47",
    "sg:city":"Valladolid",
    "sg:orig_category":"Carnicer\u00cdas, Carnicer\u00cdas",
    "sg:phone":"+34 983 29 42 67",
    "sg:postcode":"47004",
    "sg:province":"Valladolid",
    "wof:name":"Lopez Villanueva Sergio",
    "wof:placetype":"venue"
},
  "geometry": {"coordinates":[-4.7205209732,41.6450386047],"type":"Point"}
}