{
  "type": "Feature",
  "properties": {
    "addr:full":"Send Garres, 112 Infante Juan Manuel Murcia 30012",
    "addr:housenumber":"112",
    "addr:postcode":"30012",
    "addr:street":"Send Garres",
    "iso:country":"ES",
    "sg:address":"Send Garres, 112",
    "sg:city":"Infante Juan Manuel",
    "sg:orig_category":"Electricidad, Electr\u00d3nica: Suministros (al Por Menor)",
    "sg:phone":"+34 968 26 33 11",
    "sg:postcode":"30012",
    "sg:province":"Murcia",
    "wof:name":"Electronica Llorga S.l.",
    "wof:placetype":"venue"
},
  "geometry": {"coordinates":[-1.1206640005,37.9650650024],"type":"Point"}
}