{
  "type": "Feature",
  "properties": {
    "addr:full":"Carrer de Sant Quirze, 5 Sabadell Barcelona 08201",
    "addr:housenumber":"5",
    "addr:postcode":"08201",
    "addr:street":"Carrer De Sant Quirze",
    "iso:country":"ES",
    "sg:address":"Carrer de Sant Quirze, 5",
    "sg:city":"Sabadell",
    "sg:orig_category":"Lencer\u00cda Femenina, Corseter\u00cda, Trajes De Ba\u00d1o (al Por Menor)",
    "sg:phone":"+34 937 25 59 50",
    "sg:postcode":"08201",
    "sg:province":"Barcelona",
    "wof:name":"Serra Trenchs Carmen",
    "wof:placetype":"venue"
},
  "geometry": {"coordinates":[2.1076700687,41.5466003418],"type":"Point"}
}