{
  "type": "Feature",
  "properties": {
    "iso:country":"ES",
    "sg:address":"Avda Libertad De La, 27",
    "sg:city":"Donostia-san Sebastian",
    "sg:orig_category":"Sociedades, Compa\u00d1\u00cdas Aseguradoras",
    "sg:phone":"+34 943 42 88 21",
    "sg:postcode":"20004",
    "sg:province":"Guip\u00f9zcoa",
    "wof:name":"Nortehispana De Seguros Y Reaseguros S.a.",
    "wof:placetype":"venue"
},
  "geometry": {"coordinates":[-1.9828929901,43.3190879822],"type":"Point"}
}