{
  "type": "Feature",
  "properties": {
    "iso:country":"ES",
    "sg:address":"Avda Ciclista Mariano Rojas, 7",
    "sg:city":"Ranero",
    "sg:orig_category":"Caf\u00c9s, Bares, Cervecer\u00cdas",
    "sg:phone":"+34 968 28 44 05",
    "sg:postcode":"30009",
    "sg:province":"Murcia",
    "wof:name":"Jose Antonio Y Pedro Andres Miras Heredia Cdad",
    "wof:placetype":"venue"
},
  "geometry": {"coordinates":[-1.1528439522,37.9883460999],"type":"Point"}
}