{
  "type": "Feature",
  "properties": {
    "addr:full":"Avda Andalucia, 5 Montejicar Granada 18561",
    "addr:housenumber":"5",
    "addr:postcode":"18561",
    "addr:street":"Avda Andalucia",
    "iso:country":"ES",
    "sg:address":"Avda Andalucia, 5",
    "sg:city":"Montejicar",
    "sg:orig_category":"Delegados, Agentes De Tr\u00c1nsito, Auxiliares De Transporte Internacional",
    "sg:phone":"+34 958 39 31 51",
    "sg:postcode":"18561",
    "sg:province":"Granada",
    "wof:name":"Lopez Palma Juan Carlos",
    "wof:placetype":"venue"
},
  "geometry": {"coordinates":[-3.5020339489,37.5723228455],"type":"Point"}
}