{
  "type": "Feature",
  "properties": {
    "addr:full":"Ctra Villar De Torre, S/n Badaran La Rioja 26310",
    "addr:housenumber":"s / n",
    "addr:postcode":"26310",
    "addr:street":"Ctra Villar De Torre;Rioja",
    "iso:country":"ES",
    "sg:address":"Ctra Villar De Torre, S/n",
    "sg:city":"Badaran",
    "sg:orig_category":"Bebidas",
    "sg:phone":"+34 941 36 73 38",
    "sg:postcode":"26310",
    "sg:province":"La Rioja",
    "wof:name":"Moreno Pe\u00f1a David",
    "wof:placetype":"venue"
},
  "geometry": {"coordinates":[-2.811852932,42.3680076599],"type":"Point"}
}