{
  "type": "Feature",
  "properties": {
    "iso:country":"ES",
    "sg:address":"Calle de Betania, 15",
    "sg:city":"Sevilla",
    "sg:orig_category":"Semiller\u00cdas",
    "sg:phone":"+34 954 58 22 19",
    "sg:postcode":"41007",
    "sg:province":"Sevilla",
    "wof:name":"Betica De Parque S. A.",
    "wof:placetype":"venue"
},
  "geometry": {"coordinates":[-5.9709339142,37.3908462524],"type":"Point"}
}