{
  "type": "Feature",
  "properties": {
    "iso:country":"ES",
    "sg:address":"Calle de Roque Barcia, 5",
    "sg:city":"Huelva",
    "sg:orig_category":"Abogados",
    "sg:phone":"+34 959 23 44 70",
    "sg:postcode":"21003",
    "sg:province":"Huelva",
    "wof:name":"Garcia Perez Jesus Maria",
    "wof:placetype":"venue"
},
  "geometry": {"coordinates":[-6.9374709129,37.2560882568],"type":"Point"}
}