{
  "type": "Feature",
  "properties": {
    "iso:country":"ES",
    "sg:address":"Calle de Conde Rebolledo, 1",
    "sg:city":"Le\u00f3n",
    "sg:orig_category":"Droguer\u00cdas (al Por Menor)",
    "sg:phone":"+34 987 25 92 24",
    "sg:postcode":"24003",
    "sg:province":"Le\u00f3n",
    "wof:name":"Lopez Vizan Maria Teresa",
    "wof:placetype":"venue"
},
  "geometry": {"coordinates":[-5.5688886642,42.5970306396],"type":"Point"}
}