{
  "type": "Feature",
  "properties": {
    "addr:full":"Calle de Arte, 1 Madrid Madrid 28033",
    "addr:housenumber":"1",
    "addr:postcode":"28033",
    "addr:street":"Calle De Arte",
    "iso:country":"ES",
    "sg:address":"Calle de Arte, 1",
    "sg:city":"Madrid",
    "sg:orig_category":"Centros Empresariales",
    "sg:phone":"+34 917 67 01 30",
    "sg:postcode":"28033",
    "sg:province":"Madrid",
    "wof:name":"Bicker And Banyan S.l.",
    "wof:placetype":"venue"
},
  "geometry": {"coordinates":[-3.671487093,40.482093811],"type":"Point"}
}