{
  "type": "Feature",
  "properties": {
    "addr:full":"Calle de Fernando Moline, 13 Puebla Alfinden Zaragoza 50171",
    "addr:housenumber":"13",
    "addr:postcode":"50171",
    "addr:street":"Calle De Fernando Moline;Alfinden",
    "iso:country":"ES",
    "sg:address":"Calle de Fernando Moline, 13",
    "sg:city":"Puebla Alfinden",
    "sg:orig_category":"Molduras, Junquillos, Listones Y Molduras Perforadas",
    "sg:phone":"+34 976 10 85 45",
    "sg:postcode":"50171",
    "sg:province":"Zaragoza",
    "wof:name":"Explotaciones Hosteleras La Sabina 2004 S.l.l.",
    "wof:placetype":"venue"
},
  "geometry": {"coordinates":[-0.7537472844,41.6321296692],"type":"Point"}
}