{
  "type": "Feature",
  "properties": {
    "addr:full":"Fondal, 7 Carballo La Coru\u00f1a 15105",
    "addr:housenumber":"7",
    "addr:postcode":"15105",
    "addr:street":"Fondal;La Corun\u0303A",
    "iso:country":"ES",
    "sg:address":"Fondal, 7",
    "sg:city":"Carballo",
    "sg:orig_category":"Ebanister\u00cda",
    "sg:phone":"+34 981 70 09 72",
    "sg:postcode":"15105",
    "sg:province":"La Coru\u00f1a",
    "wof:name":"Pena Canedo Manuel",
    "wof:placetype":"venue"
},
  "geometry": {"coordinates":[-8.605348587,43.3203735352],"type":"Point"}
}