{
  "type": "Feature",
  "properties": {
    "iso:country":"ES",
    "sg:address":"Calle de Villardondiego, 22",
    "sg:city":"Madrid",
    "sg:orig_category":"Panader\u00cdas, Panader\u00cdas",
    "sg:phone":"+34 913 71 95 25",
    "sg:postcode":"28032",
    "sg:province":"Madrid",
    "wof:name":"Artesanos Dieteticos S.l.l.",
    "wof:placetype":"venue"
},
  "geometry": {"coordinates":[-3.6082675457,40.4069328308],"type":"Point"}
}