{
  "type": "Feature",
  "properties": {
    "addr:full":"Carrer de Santalo, 101 Barcelona Barcelona 08021",
    "addr:housenumber":"101",
    "addr:postcode":"08021",
    "addr:street":"Carrer De Santalo",
    "iso:country":"ES",
    "sg:address":"Carrer de Santalo, 101",
    "sg:city":"Barcelona",
    "sg:orig_category":"Restaurantes",
    "sg:phone":"+34 932 41 40 31",
    "sg:postcode":"08021",
    "sg:province":"Barcelona",
    "wof:name":"Willimar S.c.p.",
    "wof:placetype":"venue"
},
  "geometry": {"coordinates":[2.1424195766,41.3983001709],"type":"Point"}
}