{
  "type": "Feature",
  "properties": {
    "iso:country":"ES",
    "sg:address":"Roldan, 1",
    "sg:city":"Torre-pacheco",
    "sg:orig_category":"Muebles, Minoristas",
    "sg:phone":"+34 968 57 78 11",
    "sg:postcode":"30700",
    "sg:province":"Murcia",
    "wof:name":"Olmo Soto Pedro Jose",
    "wof:placetype":"venue"
},
  "geometry": {"coordinates":[-0.9614830017,37.8189468384],"type":"Point"}
}