{
  "type": "Feature",
  "properties": {
    "iso:country":"ES",
    "sg:address":"Calle de Carretas, 14",
    "sg:city":"Madrid",
    "sg:orig_category":"Empresarios Y Productoras De Espect\u00c1culos",
    "sg:phone":"+34 915 23 46 22",
    "sg:postcode":"28012",
    "sg:province":"Madrid",
    "sg:website":"www.nbeflamenco.com",
    "wof:name":"Gp Management Y Distribucion De Espectaculos S.l.u",
    "wof:placetype":"venue"
},
  "geometry": {"coordinates":[-3.7033650875,40.4147796631],"type":"Point"}
}