{
  "type": "Feature",
  "properties": {
    "iso:country":"ES",
    "sg:address":"Avda Filiberto Villalobos, 71",
    "sg:city":"Salamanca",
    "sg:orig_category":"Art\u00cdculos De Regalo (al Por Menor)",
    "sg:phone":"+34 923 22 65 50",
    "sg:postcode":"37007",
    "sg:province":"Salamanca",
    "wof:name":"Merchan Martin Margarita",
    "wof:placetype":"venue"
},
  "geometry": {"coordinates":[-5.674405098,40.9701385498],"type":"Point"}
}