{
  "type": "Feature",
  "properties": {
    "iso:country":"ES",
    "sg:address":"Pla\u00c7 Escorxador, 1",
    "sg:city":"Figueres",
    "sg:orig_category":"Carnicer\u00cdas, Carnicer\u00cdas",
    "sg:phone":"+34 972 50 96 71",
    "sg:postcode":"17600",
    "sg:province":"Girona",
    "wof:name":"Diaz Roibas Manuel",
    "wof:placetype":"venue"
},
  "geometry": {"coordinates":[2.9581100941,42.2656898499],"type":"Point"}
}