{
  "type": "Feature",
  "properties": {
    "addr:full":"Moll De Evaristo Fernandez, 2 Barcelona Barcelona 08039",
    "addr:housenumber":"2",
    "addr:postcode":"08039",
    "addr:street":"Moll De Evaristo Fernandez",
    "iso:country":"ES",
    "sg:address":"Moll De Evaristo Fernandez, 2",
    "sg:city":"Barcelona",
    "sg:orig_category":"Delegados, Agentes De Tr\u00c1nsito, Auxiliares De Transporte Internacional",
    "sg:phone":"+34 932 23 49 53",
    "sg:postcode":"08039",
    "sg:province":"Barcelona",
    "wof:name":"Dojitrans S.l.",
    "wof:placetype":"venue"
},
  "geometry": {"coordinates":[2.1540350914,41.3469161987],"type":"Point"}
}