{
  "type": "Feature",
  "properties": {
    "addr:full":"Carrer de Muralla Del Carme, 12 Manresa Barcelona 08241",
    "addr:housenumber":"12",
    "addr:postcode":"08241",
    "addr:street":"Carrer De Muralla Del Carme",
    "iso:country":"ES",
    "sg:address":"Carrer de Muralla Del Carme, 12",
    "sg:city":"Manresa",
    "sg:orig_category":"Electrodom\u00c9sticos (al Por Menor)",
    "sg:phone":"+34 938 72 26 44",
    "sg:postcode":"08241",
    "sg:province":"Barcelona",
    "sg:website":"www.e-marquez.com",
    "wof:name":"Electrodomestics Marquez S. A.",
    "wof:placetype":"venue"
},
  "geometry": {"coordinates":[1.8251930475,41.725440979],"type":"Point"}
}