{
  "type": "Feature",
  "properties": {
    "iso:country":"ES",
    "sg:address":"Calle de Perez Galdos, 1",
    "sg:city":"Porzuna",
    "sg:orig_category":"Molduras, Junquillos, Listones Y Molduras Perforadas",
    "sg:phone":"+34 926 78 05 93",
    "sg:postcode":"13120",
    "sg:province":"Ciudad Real",
    "wof:name":"Plaza Astilleros Vicente",
    "wof:placetype":"venue"
},
  "geometry": {"coordinates":[-4.1537690163,39.1484985352],"type":"Point"}
}