{
  "type": "Feature",
  "properties": {
    "addr:full":"Calle de Gabriel Ramos Bejarano, 118 Cordoba C\u00f3rdoba 14014",
    "addr:housenumber":"118",
    "addr:postcode":"14014",
    "addr:street":"Calle De Gabriel Ramos Bejarano;Co\u0301Rdoba",
    "iso:country":"ES",
    "sg:address":"Calle de Gabriel Ramos Bejarano, 118",
    "sg:city":"Cordoba",
    "sg:orig_category":"Tapicer\u00cdas",
    "sg:phone":"+34 957 32 65 78",
    "sg:postcode":"14014",
    "sg:province":"C\u00f3rdoba",
    "wof:name":"Zafra Garcia Juan",
    "wof:placetype":"venue"
},
  "geometry": {"coordinates":[-4.7180733681,37.9006958008],"type":"Point"}
}