{
  "type": "Feature",
  "properties": {
    "iso:country":"ES",
    "sg:address":"Plaz Ruperto Chapi, 6",
    "sg:city":"Alacant",
    "sg:orig_category":"M\u00c9dicos: Pediatr\u00cda. Enfermedades De Los Ni\u00d1os",
    "sg:phone":"+34 965 20 09 42",
    "sg:postcode":"03001",
    "sg:province":"Alicante",
    "wof:name":"Valdes Rodriguez Jose",
    "wof:placetype":"venue"
},
  "geometry": {"coordinates":[-0.4859000146,38.3462944031],"type":"Point"}
}