{
  "type": "Feature",
  "properties": {
    "addr:full":"Carrer de Bruguera, 190 Calella Barcelona 08370",
    "addr:housenumber":"190",
    "addr:postcode":"08370",
    "addr:street":"Carrer De Bruguera",
    "iso:country":"ES",
    "sg:address":"Carrer de Bruguera, 190",
    "sg:city":"Calella",
    "sg:orig_category":"Electricidad: Instaladores",
    "sg:phone":"+34 937 66 21 39",
    "sg:postcode":"08370",
    "sg:province":"Barcelona",
    "wof:name":"Ginesta Torredeflo Antonio",
    "wof:placetype":"venue"
},
  "geometry": {"coordinates":[2.6647770405,41.6162185669],"type":"Point"}
}