{
  "type": "Feature",
  "properties": {
    "addr:full":"Avda Salesianos, 70 Giles Las Palmas 35018",
    "addr:housenumber":"70",
    "addr:postcode":"35018",
    "addr:street":"Avda Salesianos;Giles Las Palmas",
    "iso:country":"ES",
    "sg:address":"Avda Salesianos, 70",
    "sg:city":"Giles",
    "sg:orig_category":"Puros, Cigarrillos Y Tabaco (al Por Menor)",
    "sg:phone":"+34 928 67 34 14",
    "sg:postcode":"35018",
    "sg:province":"Las Palmas",
    "wof:name":"Guillermo Vervliet S.l.",
    "wof:placetype":"venue"
},
  "geometry": {"coordinates":[-15.4758281708,28.1144542694],"type":"Point"}
}