{
  "type": "Feature",
  "properties": {
    "iso:country":"ES",
    "sg:address":"Elizaurre, 1",
    "sg:city":"Zarautz",
    "sg:orig_category":"Iglesia Cat\u00d3lica",
    "sg:phone":"+34 943 83 21 61",
    "sg:postcode":"20800",
    "sg:province":"Guip\u00f9zcoa",
    "wof:name":"Parroquia De Santa Maria La Real",
    "wof:placetype":"venue"
},
  "geometry": {"coordinates":[-2.1774220467,43.2865715027],"type":"Point"}
}