{
  "type": "Feature",
  "properties": {
    "addr:full":"Calle de Mayor, 26 Alcocer Guadalajara 19125",
    "addr:housenumber":"26",
    "addr:postcode":"19125",
    "addr:street":"Calle De Mayor",
    "iso:country":"ES",
    "sg:address":"Calle de Mayor, 26",
    "sg:city":"Alcocer",
    "sg:orig_category":"Negocio De Materiales De Construcci\u00d3n",
    "sg:phone":"+34 949 35 52 06",
    "sg:postcode":"19125",
    "sg:province":"Guadalajara",
    "wof:name":"Jimenez Peiro Esteban",
    "wof:placetype":"venue"
},
  "geometry": {"coordinates":[-2.6123149395,40.4701461792],"type":"Point"}
}