{
  "type": "Feature",
  "properties": {
    "addr:full":"Calle de Serranos, 35 Salamanca Salamanca 37008",
    "addr:housenumber":"35",
    "addr:postcode":"37008",
    "addr:street":"Calle De Serranos",
    "iso:country":"ES",
    "sg:address":"Calle de Serranos, 35",
    "sg:city":"Salamanca",
    "sg:orig_category":"Agencias De Viajes",
    "sg:phone":"+34 923 21 07 28",
    "sg:postcode":"37008",
    "sg:province":"Salamanca",
    "sg:website":"www.halconviajes.com",
    "wof:name":"Viajes Halcon S.a.",
    "wof:placetype":"venue"
},
  "geometry": {"coordinates":[-5.6679210663,40.9622077942],"type":"Point"}
}