{
  "type": "Feature",
  "properties": {
    "addr:full":"Calle de Vall De Crist, 5 Valencia Valencia 46003",
    "addr:housenumber":"5",
    "addr:postcode":"46003",
    "addr:street":"Calle De Vall De Crist",
    "iso:country":"ES",
    "sg:address":"Calle de Vall De Crist, 5",
    "sg:city":"Valencia",
    "sg:orig_category":"Papel, Reciclaje",
    "sg:phone":"+34 963 91 18 22",
    "sg:postcode":"46003",
    "sg:province":"Valencia",
    "wof:name":"Polo Domingo Jaime",
    "wof:placetype":"venue"
},
  "geometry": {"coordinates":[-0.3769659996,39.4779701233],"type":"Point"}
}