{
  "type": "Feature",
  "properties": {
    "addr:full":"Calle de Virgen De Setefilla, 4 Sevilla Sevilla 41011",
    "addr:housenumber":"4",
    "addr:postcode":"41011",
    "addr:street":"Calle De Virgen De Setefilla",
    "iso:country":"ES",
    "sg:address":"Calle de Virgen De Setefilla, 4",
    "sg:city":"Sevilla",
    "sg:orig_category":"Arquitectos",
    "sg:phone":"+34 954 99 07 01",
    "sg:postcode":"41011",
    "sg:province":"Sevilla",
    "wof:name":"Pedro Rodriguez De Pineda Arquitectos Asociados S.l.",
    "wof:placetype":"venue"
},
  "geometry": {"coordinates":[-5.9995689392,37.378452301],"type":"Point"}
}