{
  "type": "Feature",
  "properties": {
    "iso:country":"ES",
    "sg:address":"Poli Cortijo Real - Plg.indust., 30",
    "sg:city":"Algeciras",
    "sg:orig_category":"Alimentaci\u00d3n Animal (fabricaci\u00d3n, Al Por Mayor)",
    "sg:phone":"+34 956 58 03 88",
    "sg:postcode":"11206",
    "sg:province":"C\u00e1diz",
    "wof:name":"Agricentro Cortijo Real S.l",
    "wof:placetype":"venue"
},
  "geometry": {"coordinates":[-5.4882678986,36.1051139832],"type":"Point"}
}