{
  "type": "Feature",
  "properties": {
    "addr:full":"Calle de Mayor, 7 Yunquera Henares Guadalajara 19210",
    "addr:housenumber":"7",
    "addr:postcode":"19210",
    "addr:street":"Calle De Mayor",
    "iso:country":"ES",
    "sg:address":"Calle de Mayor, 7",
    "sg:city":"Yunquera Henares",
    "sg:orig_category":"Carnicer\u00cdas, Carnicer\u00cdas",
    "sg:phone":"+34 949 33 00 43",
    "sg:postcode":"19210",
    "sg:province":"Guadalajara",
    "wof:name":"Pastor Lozano Luis Miguel",
    "wof:placetype":"venue"
},
  "geometry": {"coordinates":[-3.165268898,40.7531585693],"type":"Point"}
}