{
  "type": "Feature",
  "properties": {
    "iso:country":"ES",
    "sg:address":"Calle de Doctor Fleming, 17",
    "sg:city":"Mieres",
    "sg:orig_category":"Molduras, Junquillos, Listones Y Molduras Perforadas",
    "sg:phone":"+34 985 46 33 84",
    "sg:postcode":"33600",
    "sg:province":"Asturias",
    "wof:name":"Hernandez Alvaredo Tomas",
    "wof:placetype":"venue"
},
  "geometry": {"coordinates":[-5.7790484428,43.248664856],"type":"Point"}
}