{
  "type": "Feature",
  "properties": {
    "addr:full":"Carrer de Doctor Marti I Julia, 87 Hospitalet Llobregat Barcelona 08903",
    "addr:housenumber":"87",
    "addr:postcode":"08903",
    "addr:street":"Carrer De Doctor Marti I Julia",
    "iso:country":"ES",
    "sg:address":"Carrer de Doctor Marti I Julia, 87",
    "sg:city":"Hospitalet Llobregat",
    "sg:orig_category":"Ropa Para Se\u00d1oras Y Caballeros (al Por Menor)",
    "sg:phone":"+34 934 49 42 57",
    "sg:postcode":"08903",
    "sg:province":"Barcelona",
    "wof:name":"Villegas Peramo Dolores Soledad",
    "wof:placetype":"venue"
},
  "geometry": {"coordinates":[2.1235589981,41.3727111816],"type":"Point"}
}