{
  "type": "Feature",
  "properties": {
    "iso:country":"ES",
    "sg:address":"Carrer de Proven\u00c7a, 112",
    "sg:city":"Barcelona",
    "sg:orig_category":"Arte, Cultura, Edici\u00d3n",
    "sg:phone":"+34 933 63 36 00",
    "sg:postcode":"08029",
    "sg:province":"Barcelona",
    "sg:website":"www.montuno.com",
    "wof:name":"Montuno Producciones Y Eventos S.l.",
    "wof:placetype":"venue"
},
  "geometry": {"coordinates":[2.1492800713,41.3853530884],"type":"Point"}
}