{
  "type": "Feature",
  "properties": {
    "addr:full":"Avda Miguel De Cervantes, 77 Entrepinos Valladolid 47130",
    "addr:housenumber":"77",
    "addr:postcode":"47130",
    "addr:street":"Avda Miguel De Cervantes",
    "iso:country":"ES",
    "sg:address":"Avda Miguel De Cervantes, 77",
    "sg:city":"Entrepinos",
    "sg:orig_category":"Doctores En Medicina",
    "sg:phone":"+34 983 59 13 78",
    "sg:postcode":"47130",
    "sg:province":"Valladolid",
    "wof:name":"Gil Ruiz Jose Antonio",
    "wof:placetype":"venue"
},
  "geometry": {"coordinates":[-4.8235812187,41.5907974243],"type":"Point"}
}