{
  "type": "Feature",
  "properties": {
    "iso:country":"ES",
    "sg:address":"Calle de Tarub, 40",
    "sg:city":"Cordoba",
    "sg:orig_category":"Ingeniero",
    "sg:phone":"+34 957 46 06 47",
    "sg:postcode":"14005",
    "sg:province":"C\u00f3rdoba",
    "wof:name":"Barragan Carmona Manuel",
    "wof:placetype":"venue"
},
  "geometry": {"coordinates":[-4.8089261055,37.880355835],"type":"Point"}
}