{
  "type": "Feature",
  "properties": {
    "iso:country":"ES",
    "sg:address":"Calle de Alejandro Bell, 18",
    "sg:city":"Zaragoza",
    "sg:orig_category":"Comercio De Piezas De Recambio Y De Accesorios De Veh\u00cdculos, Veh\u00cdculos Industriales",
    "sg:phone":"+34 976 46 40 18",
    "sg:postcode":"50014",
    "sg:province":"Zaragoza",
    "wof:name":"Suministros Blariz S.a.",
    "wof:placetype":"venue"
},
  "geometry": {"coordinates":[-0.861066103,41.6671905518],"type":"Point"}
}