{
  "type": "Feature",
  "properties": {
    "addr:full":"Calle de Milanos, 8 Pinto Madrid 28320",
    "addr:housenumber":"8",
    "addr:postcode":"28320",
    "addr:street":"Calle De Milanos;Pinto",
    "iso:country":"ES",
    "sg:address":"Calle de Milanos, 8",
    "sg:city":"Pinto",
    "sg:orig_category":"Pintura Y Barniz (al Por Menor)",
    "sg:phone":"+34 916 92 14 21",
    "sg:postcode":"28320",
    "sg:province":"Madrid",
    "wof:name":"Carrasco Borges Efrain",
    "wof:placetype":"venue"
},
  "geometry": {"coordinates":[-3.7054920197,40.2492256165],"type":"Point"}
}