{
  "type": "Feature",
  "properties": {
    "iso:country":"ES",
    "sg:address":"Calle de Huerfanas, 21",
    "sg:city":"Almeria",
    "sg:classifiers":[
        {
            "category":"Autos & Motor Vehicles",
            "subcategory":"Automobile Sales",
            "type":"Retail Goods"
        }
    ],
    "sg:phone":"+34 950 23 21 94",
    "sg:postcode":"04004",
    "sg:province":"Almer\u00eda",
    "wof:name":"Autoescuela Enrique S.l.",
    "wof:placetype":"venue"
},
  "geometry": {"coordinates":[-2.4607496262,36.8442077637],"type":"Point"}
}