{
  "type": "Feature",
  "properties": {
    "addr:full":"Carr Major, 57 Rossello Lleida 25124",
    "addr:housenumber":"57",
    "addr:postcode":"25124",
    "addr:street":"Carr Major",
    "iso:country":"ES",
    "sg:address":"Carr Major, 57",
    "sg:city":"Rossello",
    "sg:orig_category":"Grafistas",
    "sg:phone":"+34 973 73 05 67",
    "sg:postcode":"25124",
    "sg:province":"Lleida",
    "wof:name":"Ara Produccions S.l.",
    "wof:placetype":"venue"
},
  "geometry": {"coordinates":[0.5950623751,41.6935348511],"type":"Point"}
}