{
  "type": "Feature",
  "properties": {
    "iso:country":"ES",
    "sg:address":"Carrer de Major, 74",
    "sg:city":"Castellar Valles",
    "sg:orig_category":"Clubes, Asociaciones De Ocio",
    "sg:phone":"+34 937 14 53 64",
    "sg:postcode":"08211",
    "sg:province":"Barcelona",
    "wof:name":"Aeri Model Club Castellar",
    "wof:placetype":"venue"
},
  "geometry": {"coordinates":[2.086155653,41.6163101196],"type":"Point"}
}