{
  "type": "Feature",
  "properties": {
    "iso:country":"ES",
    "sg:address":"Calle de Profesor Lozano, 17",
    "sg:city":"Palmas De Gran Canaria",
    "sg:orig_category":"Electricidad: Equipos Industriales, Componentes (fabricaci\u00d3n)",
    "sg:phone":"+34 928 47 53 97",
    "sg:postcode":"35008",
    "sg:province":"Las Palmas",
    "wof:name":"Distribuidora Electrica Canaria S.a.",
    "wof:placetype":"venue"
},
  "geometry": {"coordinates":[-15.4210786819,28.1545696259],"type":"Point"}
}