{
  "type": "Feature",
  "properties": {
    "addr:full":"Carrer de Torres Jordi (de), 10 Tarragona Tarragona 43005",
    "addr:housenumber":"10",
    "addr:postcode":"43005",
    "addr:street":"Carrer De Torres Jordi De",
    "iso:country":"ES",
    "sg:address":"Carrer de Torres Jordi (de), 10",
    "sg:city":"Tarragona",
    "sg:orig_category":"Alimentaci\u00d3n General (al Por Menor)",
    "sg:phone":"+34 977 22 89 84",
    "sg:postcode":"43005",
    "sg:province":"Tarragona",
    "wof:name":"Martinez Gonzalez Encarnacion",
    "wof:placetype":"venue"
},
  "geometry": {"coordinates":[1.2413270473,41.1120376587],"type":"Point"}
}