{
  "type": "Feature",
  "properties": {
    "iso:country":"ES",
    "sg:address":"Rua Marquesa Do Pazo, S/n",
    "sg:city":"Neves",
    "sg:orig_category":"Electrodom\u00c9sticos (al Por Menor)",
    "sg:phone":"+34 986 64 80 75",
    "sg:postcode":"36440",
    "sg:province":"Pontevedra",
    "wof:name":"Gonzalez Ubeira Manuel",
    "wof:placetype":"venue"
},
  "geometry": {"coordinates":[-8.411822319,42.0887565613],"type":"Point"}
}