{
  "type": "Feature",
  "properties": {
    "addr:full":"Calle de Merced, 9 San Lorenzo Murcia 30001",
    "addr:housenumber":"9",
    "addr:postcode":"30001",
    "addr:street":"Calle De Merced",
    "iso:country":"ES",
    "sg:address":"Calle de Merced, 9",
    "sg:city":"San Lorenzo",
    "sg:orig_category":"Librer\u00cdas",
    "sg:phone":"+34 968 24 28 29",
    "sg:postcode":"30001",
    "sg:province":"Murcia",
    "wof:name":"Diego Marin Librero-editor S.l.",
    "wof:placetype":"venue"
},
  "geometry": {"coordinates":[-1.1281189919,37.9873008728],"type":"Point"}
}