{
  "type": "Feature",
  "properties": {
    "iso:country":"ES",
    "sg:address":"Poli Paz (la), S/n",
    "sg:city":"Teruel",
    "sg:orig_category":"Fabrica De Cer\u00c1micas",
    "sg:phone":"+34 978 60 69 07",
    "sg:postcode":"44195",
    "sg:province":"Teruel",
    "sg:website":"www.turolgres.com",
    "wof:name":"Turolgres S.a.",
    "wof:placetype":"venue"
},
  "geometry": {"coordinates":[-1.1755470037,40.358417511],"type":"Point"}
}