{
  "type": "Feature",
  "properties": {
    "addr:full":"Calle de Marques Del Riscal, 11 Madrid Madrid 28010",
    "addr:housenumber":"11",
    "addr:postcode":"madrid;28010",
    "addr:street":"Calle De Marques Del Riscal",
    "iso:country":"ES",
    "sg:address":"Calle de Marques Del Riscal, 11",
    "sg:city":"Madrid",
    "sg:orig_category":"Asesor\u00cdas Y Estudios Financieros",
    "sg:phone":"+34 917 00 43 50",
    "sg:postcode":"28010",
    "sg:province":"Madrid",
    "wof:name":"Fruhbeck Abogados",
    "wof:placetype":"venue"
},
  "geometry": {"coordinates":[-3.6903560162,40.4307785034],"type":"Point"}
}