{
  "type": "Feature",
  "properties": {
    "addr:full":"Calle de Luis Alonso Otero, 1 Ramales Victoria Cantabria 39800",
    "addr:housenumber":"1",
    "addr:postcode":"39800",
    "addr:street":"Calle De Luis Alonso Otero",
    "iso:country":"ES",
    "sg:address":"Calle de Luis Alonso Otero, 1",
    "sg:city":"Ramales Victoria",
    "sg:orig_category":"Asesor\u00cda Fiscal Y Jur\u00cddica",
    "sg:phone":"+34 942 67 83 36",
    "sg:postcode":"39800",
    "sg:province":"Cantabria",
    "wof:name":"Laun S.cv.",
    "wof:placetype":"venue"
},
  "geometry": {"coordinates":[-3.442991972,43.2613754272],"type":"Point"}
}