{
  "type": "Feature",
  "properties": {
    "iso:country":"ES",
    "sg:address":"Calle de San Sebastian, 11",
    "sg:city":"Dos Hermanas",
    "sg:orig_category":"Perfumer\u00cda (al Por Menor)",
    "sg:phone":"+34 954 72 04 32",
    "sg:postcode":"41700",
    "sg:province":"Sevilla",
    "wof:name":"Manuel Giraldo Tornay S.l.",
    "wof:placetype":"venue"
},
  "geometry": {"coordinates":[-5.9206290245,37.2808914185],"type":"Point"}
}