{
  "type": "Feature",
  "properties": {
    "addr:full":"Pase Estacion, 7 Illescas Toledo 45200",
    "addr:housenumber":"7",
    "addr:postcode":"45200",
    "addr:street":"Estacion",
    "iso:country":"ES",
    "sg:address":"Pase Estacion, 7",
    "sg:city":"Illescas",
    "sg:orig_category":"Peluquer\u00cdas, Peluquer\u00cda Mixta",
    "sg:phone":"+34 925 51 39 87",
    "sg:postcode":"45200",
    "sg:province":"Toledo",
    "wof:name":"Arenas Martinez Maria Jose",
    "wof:placetype":"venue"
},
  "geometry": {"coordinates":[-3.8442957401,40.1226196289],"type":"Point"}
}