{
  "type": "Feature",
  "properties": {
    "addr:full":"Carrer de Major (sant Celoni), 59 S. Celoni Barcelona 08470",
    "addr:housenumber":"59",
    "addr:postcode":"08470",
    "addr:street":"Carrer De Major Sant Celoni;S. Celoni Barcelona",
    "iso:country":"ES",
    "sg:address":"Carrer de Major (sant Celoni), 59",
    "sg:city":"S. Celoni",
    "sg:orig_category":"Reposter\u00cdas",
    "sg:phone":"+34 938 67 10 94",
    "sg:postcode":"08470",
    "sg:province":"Barcelona",
    "wof:name":"Torres Pimas Jaume",
    "wof:placetype":"venue"
},
  "geometry": {"coordinates":[2.4893081188,41.6890945435],"type":"Point"}
}