{
  "type": "Feature",
  "properties": {
    "iso:country":"ES",
    "sg:address":"Carrer de Ample, 20",
    "sg:city":"Reus",
    "sg:orig_category":"Carnicer\u00cdas, Carnicer\u00cdas",
    "sg:phone":"+34 977 31 63 50",
    "sg:postcode":"43202",
    "sg:province":"Tarragona",
    "wof:name":"Pamies Comella Javier",
    "wof:placetype":"venue"
},
  "geometry": {"coordinates":[1.1044820547,41.1585197449],"type":"Point"}
}