{
  "type": "Feature",
  "properties": {
    "iso:country":"ES",
    "sg:address":"Calle de Miguel Moreno Masson, 1",
    "sg:city":"Malaga",
    "sg:orig_category":"Tapicer\u00cdas",
    "sg:phone":"+34 952 33 15 90",
    "sg:postcode":"29007",
    "sg:province":"M\u00e1laga",
    "wof:name":"Perez Escalona Antonio",
    "wof:placetype":"venue"
},
  "geometry": {"coordinates":[-4.4425020218,36.7151222229],"type":"Point"}
}