{
  "type": "Feature",
  "properties": {
    "iso:country":"ES",
    "sg:address":"Av. Pio Xii, 6",
    "sg:city":"Iru\u00f1a",
    "sg:orig_category":"Quiropr\u00c1cticos",
    "sg:phone":"+34 948 17 14 29",
    "sg:postcode":"31008",
    "sg:province":"Navarra",
    "wof:name":"Monreal Lecuona Ascension",
    "wof:placetype":"venue"
},
  "geometry": {"coordinates":[-1.6554820538,42.8121147156],"type":"Point"}
}