{
  "type": "Feature",
  "properties": {
    "addr:full":"Calle de Serafin De Asis, 9 Madrid Madrid 28011",
    "addr:housenumber":"9",
    "addr:postcode":"madrid;28011",
    "addr:street":"Calle De Serafin De Asis",
    "iso:country":"ES",
    "sg:address":"Calle de Serafin De Asis, 9",
    "sg:city":"Madrid",
    "sg:orig_category":"Asociaciones Humanitarias, De Cooperaci\u00d3n, De Acci\u00d3n Social",
    "sg:phone":"+34 914 79 22 14",
    "sg:postcode":"28011",
    "sg:province":"Madrid",
    "wof:name":"Sociedad San Vicente De Paul En Espa\u00f1a",
    "wof:placetype":"venue"
},
  "geometry": {"coordinates":[-3.7522037029,40.4050559998],"type":"Point"}
}