{
  "type": "Feature",
  "properties": {
    "addr:full":"Avda Gasteiz, 53 Vitoria-gasteiz \u00c1lava 01008",
    "addr:housenumber":"53",
    "addr:postcode":"01008",
    "addr:street":"Avda Gasteiz",
    "iso:country":"ES",
    "sg:address":"Avda Gasteiz, 53",
    "sg:city":"Vitoria-gasteiz",
    "sg:orig_category":"Abogados",
    "sg:phone":"+34 945 24 07 19",
    "sg:postcode":"01008",
    "sg:province":"\u00c1lava",
    "wof:name":"Alonso Diego Maria Angeles",
    "wof:placetype":"venue"
},
  "geometry": {"coordinates":[-2.6815629005,42.8485450745],"type":"Point"}
}