{
  "type": "Feature",
  "properties": {
    "iso:country":"ES",
    "sg:address":"Calle de Ricardo Montes, 3",
    "sg:city":"Oviedo",
    "sg:orig_category":"Molduras, Junquillos, Listones Y Molduras Perforadas",
    "sg:phone":"+34 985 11 46 41",
    "sg:postcode":"33012",
    "sg:province":"Asturias",
    "wof:name":"Lama Llanes Vicente",
    "wof:placetype":"venue"
},
  "geometry": {"coordinates":[-5.8533420563,43.3696022034],"type":"Point"}
}