{
  "type": "Feature",
  "properties": {
    "addr:full":"Calle de Alcalde Lopez Casero, 6 Madrid Madrid 28027",
    "addr:housenumber":"6",
    "addr:postcode":"28027",
    "addr:street":"Calle De Alcalde Lopez Casero",
    "iso:country":"ES",
    "sg:address":"Calle de Alcalde Lopez Casero, 6",
    "sg:city":"Madrid",
    "sg:orig_category":"Relojer\u00cda (al Por Menor, Reparaci\u00d3n)",
    "sg:phone":"+34 914 03 57 91",
    "sg:postcode":"28027",
    "sg:province":"Madrid",
    "wof:name":"Diaz Vazquez Manuel",
    "wof:placetype":"venue"
},
  "geometry": {"coordinates":[-3.6554677486,40.4326095581],"type":"Point"}
}