{
  "type": "Feature",
  "properties": {
    "addr:full":"Calle de Fernando Garrido, 12 Madrid Madrid 28015",
    "addr:housenumber":"12",
    "addr:postcode":"madrid;28015",
    "addr:street":"Calle De Fernando Garrido",
    "iso:country":"ES",
    "sg:address":"Calle de Fernando Garrido, 12",
    "sg:city":"Madrid",
    "sg:orig_category":"Centros Empresariales",
    "sg:phone":"+34 914 46 49 81",
    "sg:postcode":"28015",
    "sg:province":"Madrid",
    "wof:name":"Vilatax Abogados Y Consultores S.l.",
    "wof:placetype":"venue"
},
  "geometry": {"coordinates":[-3.7096369267,40.4336967468],"type":"Point"}
}