{
  "type": "Feature",
  "properties": {
    "addr:full":"Avda Torrecardenas, 59 Almeria Almer\u00eda 04009",
    "addr:housenumber":"59",
    "addr:postcode":"04009",
    "addr:street":"Avda Torrecardenas",
    "iso:country":"ES",
    "sg:address":"Avda Torrecardenas, 59",
    "sg:city":"Almeria",
    "sg:orig_category":"Empresas De Limpieza",
    "sg:phone":"+34 950 62 43 07",
    "sg:postcode":"04009",
    "sg:province":"Almer\u00eda",
    "wof:name":"Eulen S.a.",
    "wof:placetype":"venue"
},
  "geometry": {"coordinates":[-2.4417290688,36.8604393005],"type":"Point"}
}