{
  "type": "Feature",
  "properties": {
    "addr:full":"Carril Se\u00f1orita, S/n Camas Sevilla 41900",
    "addr:housenumber":"s / n",
    "addr:postcode":"41900",
    "addr:street":"Carril Sen\u0303Orita",
    "iso:country":"ES",
    "sg:address":"Carril Se\u00f1orita, S/n",
    "sg:city":"Camas",
    "sg:orig_category":"Cementerios",
    "sg:phone":"+34 955 98 10 18",
    "sg:postcode":"41900",
    "sg:province":"Sevilla",
    "wof:name":"Ayuntamiento De Camas",
    "wof:placetype":"venue"
},
  "geometry": {"coordinates":[-6.0289406776,37.3439064026],"type":"Point"}
}