{
  "type": "Feature",
  "properties": {
    "addr:full":"Pla\u00c7 Major, S/n Alins Lleida 25574",
    "addr:housenumber":"s / n",
    "addr:postcode":"25574",
    "iso:country":"ES",
    "sg:address":"Pla\u00c7 Major, S/n",
    "sg:city":"Alins",
    "sg:classifiers":[
        {
            "category":"Taxi",
            "type":"Transportation"
        }
    ],
    "sg:phone":"+34 973 62 44 11",
    "sg:postcode":"25574",
    "sg:province":"Lleida",
    "wof:name":"Monta\u00f1a Caselles Josefa Buenaventura",
    "wof:placetype":"venue"
},
  "geometry": {"coordinates":[1.3175899982,42.5482940674],"type":"Point"}
}