{
  "type": "Feature",
  "properties": {
    "iso:country":"ES",
    "sg:address":"Plaz Orce\u00d1a, 3",
    "sg:city":"Navas Oro",
    "sg:orig_category":"Cr\u00cda De Animales",
    "sg:phone":"+34 921 59 11 23",
    "sg:postcode":"40470",
    "sg:province":"Segovia",
    "wof:name":"Pardo Martin Emiliano",
    "wof:placetype":"venue"
},
  "geometry": {"coordinates":[-4.4386892319,41.1965408325],"type":"Point"}
}