{
  "type": "Feature",
  "properties": {
    "iso:country":"ES",
    "sg:address":"Carr Sant Crist, 8",
    "sg:city":"Balaguer",
    "sg:orig_category":"Molduras, Junquillos, Listones Y Molduras Perforadas",
    "sg:phone":"+34 973 44 84 58",
    "sg:postcode":"25600",
    "sg:province":"Lleida",
    "wof:name":"Bosch Arnau Francisco",
    "wof:placetype":"venue"
},
  "geometry": {"coordinates":[0.8091430068,41.7931098938],"type":"Point"}
}