{
  "type": "Feature",
  "properties": {
    "iso:country":"ES",
    "sg:address":"Calle de Venerable Palafox, 7",
    "sg:city":"Soria",
    "sg:orig_category":"M\u00c9dicos: Estomatolog\u00cda",
    "sg:phone":"+34 975 22 65 09",
    "sg:postcode":"42001",
    "sg:province":"Soria",
    "wof:name":"Hernandez Cestero Jesus Manuel",
    "wof:placetype":"venue"
},
  "geometry": {"coordinates":[-2.4718379974,41.7663764954],"type":"Point"}
}