{
  "type": "Feature",
  "properties": {
    "addr:full":"Iglesia, S/n Iglesia Asturias 33491",
    "addr:housenumber":"s / n",
    "addr:postcode":"33491",
    "addr:street":"Asturias",
    "iso:country":"ES",
    "sg:address":"Iglesia, S/n",
    "sg:city":"Iglesia",
    "sg:orig_category":"Iglesia Cat\u00d3lica",
    "sg:phone":"+34 985 88 47 01",
    "sg:postcode":"33491",
    "sg:province":"Asturias",
    "wof:name":"Diocesis De Oviedo",
    "wof:placetype":"venue"
},
  "geometry": {"coordinates":[-5.7523698807,43.581363678],"type":"Point"}
}