{
  "type": "Feature",
  "properties": {
    "addr:full":"Calle de Pablo Neruda, 74 Merida Badajoz 06800",
    "addr:housenumber":"74",
    "addr:postcode":"06800",
    "addr:street":"Calle De Pablo Neruda",
    "iso:country":"ES",
    "sg:address":"Calle de Pablo Neruda, 74",
    "sg:city":"Merida",
    "sg:orig_category":"Molduras, Junquillos, Listones Y Molduras Perforadas",
    "sg:phone":"+34 924 30 14 62",
    "sg:postcode":"06800",
    "sg:province":"Badajoz",
    "wof:name":"Caldera Gomez Antonio",
    "wof:placetype":"venue"
},
  "geometry": {"coordinates":[-6.3306689262,38.8965682983],"type":"Point"}
}