{
  "type": "Feature",
  "properties": {
    "addr:full":"Urb Polig Ind La Ermita, 28 Poligono Industrial La Ermita Toledo 45215",
    "addr:housenumber":"28",
    "addr:postcode":"45215",
    "addr:street":"Urb Polig;La Ermita;Poligono Industrial",
    "iso:country":"ES",
    "sg:address":"Urb Polig Ind La Ermita, 28",
    "sg:city":"Poligono Industrial La Ermita",
    "sg:orig_category":"Cerrajer\u00cda, Ferrallista",
    "sg:phone":"+34 925 55 93 28",
    "sg:postcode":"45215",
    "sg:province":"Toledo",
    "wof:name":"Estructuras Hermes S.l.",
    "wof:placetype":"venue"
},
  "geometry": {"coordinates":[-3.9173390865,40.1418914795],"type":"Point"}
}