{
  "type": "Feature",
  "properties": {
    "iso:country":"ES",
    "sg:address":"Avda Jose Maria Lopez Montes, 7",
    "sg:city":"Linares",
    "sg:orig_category":"Iglesia Cat\u00d3lica",
    "sg:phone":"+34 953 69 34 57",
    "sg:postcode":"23700",
    "sg:province":"Ja\u00e9n",
    "wof:name":"Parroquia De San Jose",
    "wof:placetype":"venue"
},
  "geometry": {"coordinates":[-3.6413390636,38.0944519043],"type":"Point"}
}