{
  "type": "Feature",
  "properties": {
    "addr:full":"Calle de Bergantin, S/n Palmones C\u00e1diz 11379",
    "addr:housenumber":"s / n",
    "addr:postcode":"11379",
    "addr:street":"Calle De Bergantin;Ca\u0301Diz",
    "iso:country":"ES",
    "sg:address":"Calle de Bergantin, S/n",
    "sg:city":"Palmones",
    "sg:orig_category":"Rectificaci\u00d3n, Mecanizado, Fresado",
    "sg:phone":"+34 956 67 81 15",
    "sg:postcode":"11379",
    "sg:province":"C\u00e1diz",
    "wof:name":"Mecanizados Campo De Gibraltar S.l.",
    "wof:placetype":"venue"
},
  "geometry": {"coordinates":[-5.4437775612,36.1784667969],"type":"Point"}
}