{
  "type": "Feature",
  "properties": {
    "addr:full":"Ctra. Salamanca-zamora, Km. 0330,0 Castellanos De Villiquera Salamanca 37797",
    "addr:postcode":"37797",
    "addr:street":"Ctra. Salamanca-Zamora Km. 0330,0;De",
    "iso:country":"ES",
    "sg:address":"Ctra. Salamanca-zamora, Km. 0330,0",
    "sg:city":"Castellanos De Villiquera",
    "sg:orig_category":"Asilos De Ancianos. Centros Privados",
    "sg:phone":"+34 923 32 03 94",
    "sg:postcode":"37797",
    "sg:province":"Salamanca",
    "wof:name":"Belver Gelado Maria Angeles",
    "wof:placetype":"venue"
},
  "geometry": {"coordinates":[-5.7011990547,41.0868110657],"type":"Point"}
}