{
  "type": "Feature",
  "properties": {
    "addr:full":"Calle de Portillo Del Prado, 3 Valladolid Valladolid 47011",
    "addr:housenumber":"3",
    "addr:postcode":"47011",
    "addr:street":"Calle De Portillo Del Prado",
    "iso:country":"ES",
    "sg:address":"Calle de Portillo Del Prado, 3",
    "sg:city":"Valladolid",
    "sg:orig_category":"Molduras, Junquillos, Listones Y Molduras Perforadas",
    "sg:phone":"+34 983 26 11 01",
    "sg:postcode":"47011",
    "sg:province":"Valladolid",
    "wof:name":"Villegas Fraile Desiderio",
    "wof:placetype":"venue"
},
  "geometry": {"coordinates":[-4.718542099,41.6591148376],"type":"Point"}
}