{
  "type": "Feature",
  "properties": {
    "addr:full":"Olite-erriberri Kalea, 42 Iru\u00f1a Navarra 31004",
    "addr:housenumber":"42",
    "addr:postcode":"31004",
    "addr:street":"Olite-Erriberri Kalea",
    "iso:country":"ES",
    "sg:address":"Olite-erriberri Kalea, 42",
    "sg:city":"Iru\u00f1a",
    "sg:orig_category":"Asesor\u00cda Sobre Comunicaci\u00d3n De Empresas",
    "sg:phone":"+34 948 23 17 46",
    "sg:postcode":"31004",
    "sg:province":"Navarra",
    "wof:name":"Noain Perez Ignacio",
    "wof:placetype":"venue"
},
  "geometry": {"coordinates":[-1.633466959,42.8103141785],"type":"Point"}
}