{
  "type": "Feature",
  "properties": {
    "addr:full":"Avda Roma, 19 Le\u00f3n Le\u00f3n 24001",
    "addr:housenumber":"19",
    "addr:postcode":"24001",
    "addr:street":"Avda Roma;Leo\u0301N",
    "iso:country":"ES",
    "sg:address":"Avda Roma, 19",
    "sg:city":"Le\u00f3n",
    "sg:orig_category":"\u00d3ptica: Instrumentos (fabricaci\u00d3n)",
    "sg:phone":"+34 987 22 33 91",
    "sg:postcode":"24001",
    "sg:province":"Le\u00f3n",
    "sg:website":"www.visionlab.es",
    "wof:name":"Visionlab S.a.",
    "wof:placetype":"venue"
},
  "geometry": {"coordinates":[-5.5769128799,42.5978775024],"type":"Point"}
}