{
  "type": "Feature",
  "properties": {
    "iso:country":"ES",
    "sg:address":"Carrer de Arquimedes, 121",
    "sg:city":"Terrassa",
    "sg:orig_category":"Organizaciones Profesionales",
    "sg:phone":"+34 937 88 14 35",
    "sg:postcode":"08224",
    "sg:province":"Barcelona",
    "wof:name":"Casas Santa-olalla Jaime",
    "wof:placetype":"venue"
},
  "geometry": {"coordinates":[2.0062570572,41.5597457886],"type":"Point"}
}