{
  "type": "Feature",
  "properties": {
    "iso:country":"ES",
    "sg:address":"Av Mestre Gari, Del, S/n",
    "sg:city":"Mercadal",
    "sg:orig_category":"Centros De Educaci\u00d3n Especial",
    "sg:phone":"+34 971 37 53 38",
    "sg:postcode":"07740",
    "sg:province":"Islas Baleares",
    "wof:name":"C.p. Mare De Deu Del Toro",
    "wof:placetype":"venue"
},
  "geometry": {"coordinates":[4.0941047668,39.9855690002],"type":"Point"}
}