{
  "type": "Feature",
  "properties": {
    "addr:full":"Calle de Alhucemas, 1 Burgos Burgos 09006",
    "addr:housenumber":"1",
    "addr:postcode":"09006",
    "addr:street":"Calle De Alhucemas",
    "iso:country":"ES",
    "sg:address":"Calle de Alhucemas, 1",
    "sg:city":"Burgos",
    "sg:orig_category":"Asesor\u00cda Fiscal Y Jur\u00cddica",
    "sg:phone":"+34 947 23 63 03",
    "sg:postcode":"09006",
    "sg:province":"Burgos",
    "wof:name":"Martinez Perez Maria Angeles",
    "wof:placetype":"venue"
},
  "geometry": {"coordinates":[-3.6832578182,42.3450660706],"type":"Point"}
}