{
  "type": "Feature",
  "properties": {
    "addr:full":"Teide, 4 Palmanova Islas Baleares 07181",
    "addr:housenumber":"4",
    "addr:postcode":"07181",
    "addr:street":"Teide",
    "iso:country":"ES",
    "sg:address":"Teide, 4",
    "sg:city":"Palmanova",
    "sg:orig_category":"Caf\u00c9s, Bares, Cervecer\u00cdas",
    "sg:phone":"+34 971 68 25 26",
    "sg:postcode":"07181",
    "sg:province":"Islas Baleares",
    "wof:name":"Sainsbury Carroll Estates C.b",
    "wof:placetype":"venue"
},
  "geometry": {"coordinates":[2.5434710979,39.5263595581],"type":"Point"}
}