{
  "type": "Feature",
  "properties": {
    "addr:full":"Pase Rosales, 26 Zaragoza Zaragoza 50008",
    "addr:housenumber":"26",
    "addr:postcode":"50008",
    "addr:street":"Rosales",
    "iso:country":"ES",
    "sg:address":"Pase Rosales, 26",
    "sg:city":"Zaragoza",
    "sg:orig_category":"Frutas, Legumbres Frescas Y Tempranas (al Por Menor)",
    "sg:phone":"+34 976 49 58 53",
    "sg:postcode":"50008",
    "sg:province":"Zaragoza",
    "wof:name":"San Vicente Iba\u00f1ez Ana Rosa",
    "wof:placetype":"venue"
},
  "geometry": {"coordinates":[-0.878929019,41.6420288086],"type":"Point"}
}