{
  "type": "Feature",
  "properties": {
    "addr:full":"Calle de Alamos, 23 Jerez De La Frontera C\u00e1diz 11401",
    "addr:housenumber":"23",
    "addr:postcode":"11401",
    "addr:street":"Calle De Alamos",
    "iso:country":"ES",
    "sg:address":"Calle de Alamos, 23",
    "sg:city":"Jerez De La Frontera",
    "sg:orig_category":"Productores Recolectores, Venta Directa De Vinos",
    "sg:phone":"+34 956 34 04 02",
    "sg:postcode":"11401",
    "sg:province":"C\u00e1diz",
    "sg:website":"www.alvarodomecq.com",
    "wof:name":"Bodegas Pilar Aranda S.l.",
    "wof:placetype":"venue"
},
  "geometry": {"coordinates":[-6.1283969879,36.6775817871],"type":"Point"}
}