{
  "type": "Feature",
  "properties": {
    "iso:country":"ES",
    "sg:address":"Pase Ribalta, 7",
    "sg:city":"Castellon",
    "sg:orig_category":"Lencer\u00cda Femenina, Corseter\u00cda, Trajes De Ba\u00d1o (al Por Menor)",
    "sg:phone":"+34 964 24 60 26",
    "sg:postcode":"12001",
    "sg:province":"Castell\u00f3n",
    "wof:name":"Serret Segura Carmen",
    "wof:placetype":"venue"
},
  "geometry": {"coordinates":[-0.0390900001,39.9866714478],"type":"Point"}
}