{
  "type": "Feature",
  "properties": {
    "iso:country":"ES",
    "sg:address":"Calle de Enmedio, 18",
    "sg:city":"Nava Santiago",
    "sg:orig_category":"Confecci\u00d3n (fabricaci\u00d3n, Al Por Mayor)",
    "sg:phone":"+34 924 32 11 62",
    "sg:postcode":"06486",
    "sg:province":"Badajoz",
    "wof:name":"Moreno Cerezo Alonso",
    "wof:placetype":"venue"
},
  "geometry": {"coordinates":[-6.5049462318,39.0620689392],"type":"Point"}
}