{
  "type": "Feature",
  "properties": {
    "addr:full":"C/ Capdepera, 37 Manacor Islas Baleares 07500",
    "addr:housenumber":"37",
    "addr:postcode":"07500",
    "addr:street":"C / Capdepera",
    "iso:country":"ES",
    "sg:address":"C/ Capdepera, 37",
    "sg:city":"Manacor",
    "sg:orig_category":"Empresas De Limpieza",
    "sg:phone":"+34 971 55 54 67",
    "sg:postcode":"07500",
    "sg:province":"Islas Baleares",
    "wof:name":"Grup De Serveis I Manteniments S. A",
    "wof:placetype":"venue"
},
  "geometry": {"coordinates":[3.227793932,39.5640945435],"type":"Point"}
}