{
  "type": "Feature",
  "properties": {
    "addr:full":"Avda Villamayor, 89 Salamanca Salamanca 37007",
    "addr:housenumber":"89",
    "addr:postcode":"37007",
    "addr:street":"Avda Villamayor",
    "iso:country":"ES",
    "sg:address":"Avda Villamayor, 89",
    "sg:city":"Salamanca",
    "sg:orig_category":"Instalaci\u00d3n De Sanitarios",
    "sg:phone":"+34 923 24 89 70",
    "sg:postcode":"37007",
    "sg:province":"Salamanca",
    "wof:name":"Pao D'arco S.l.",
    "wof:placetype":"venue"
},
  "geometry": {"coordinates":[-5.6714191437,40.9723892212],"type":"Point"}
}