{
  "type": "Feature",
  "properties": {
    "iso:country":"ES",
    "sg:address":"Calle de Nicolasa Gomez, 70",
    "sg:city":"Madrid",
    "sg:orig_category":"Muebles, Minoristas",
    "sg:phone":"+34 913 93 06 97",
    "sg:postcode":"28022",
    "sg:province":"Madrid",
    "wof:name":"Montajes Y Muebles Quero S.l.",
    "wof:placetype":"venue"
},
  "geometry": {"coordinates":[-3.6125969887,40.4395332336],"type":"Point"}
}