{
  "type": "Feature",
  "properties": {
    "iso:country":"ES",
    "sg:address":"Calle de Calzada La, S/n",
    "sg:city":"Llanes",
    "sg:orig_category":"Caf\u00c9s, Bares, Cervecer\u00cdas",
    "sg:phone":"+34 985 40 07 89",
    "sg:postcode":"33500",
    "sg:province":"Asturias",
    "wof:name":"Martinez Villar Claudio",
    "wof:placetype":"venue"
},
  "geometry": {"coordinates":[-4.7552905083,43.418762207],"type":"Point"}
}