{
  "type": "Feature",
  "properties": {
    "addr:full":"Plaz Mejico, S/n Valladolid Valladolid 47014",
    "addr:housenumber":"s / n",
    "addr:postcode":"47014",
    "addr:street":"Plaz Mejico",
    "iso:country":"ES",
    "sg:address":"Plaz Mejico, S/n",
    "sg:city":"Valladolid",
    "sg:orig_category":"Molduras, Junquillos, Listones Y Molduras Perforadas",
    "sg:phone":"+34 983 22 06 64",
    "sg:postcode":"47014",
    "sg:province":"Valladolid",
    "wof:name":"Plasencia Velez Jose Antonio",
    "wof:placetype":"venue"
},
  "geometry": {"coordinates":[-4.7321238518,41.6541938782],"type":"Point"}
}