{
  "type": "Feature",
  "properties": {
    "addr:full":"Calle de Universidad, 1 Valencia Valencia 46003",
    "addr:housenumber":"1",
    "addr:postcode":"46003",
    "addr:street":"Calle De Universidad",
    "iso:country":"ES",
    "sg:address":"Calle de Universidad, 1",
    "sg:city":"Valencia",
    "sg:orig_category":"Cl\u00cdnicas Dentales",
    "sg:phone":"+34 963 52 79 32",
    "sg:postcode":"46003",
    "sg:province":"Valencia",
    "wof:name":"Dr.e.segarra Martinez Clinica Dental S.l.",
    "wof:placetype":"venue"
},
  "geometry": {"coordinates":[-0.3723529875,39.4720649719],"type":"Point"}
}