{
  "type": "Feature",
  "properties": {
    "addr:full":"Carr Florenci Valls, 4 Igualada Barcelona 08700",
    "addr:housenumber":"4",
    "addr:postcode":"08700",
    "addr:street":"Carr Florenci Valls",
    "iso:country":"ES",
    "sg:address":"Carr Florenci Valls, 4",
    "sg:city":"Igualada",
    "sg:orig_category":"Motocicletas (agentes, Concesionarios)",
    "sg:phone":"+34 938 03 51 10",
    "sg:postcode":"08700",
    "sg:province":"Barcelona",
    "wof:name":"Motos Julius S.l.",
    "wof:placetype":"venue"
},
  "geometry": {"coordinates":[1.6212689877,41.5841751099],"type":"Point"}
}