{
  "type": "Feature",
  "properties": {
    "addr:full":"Calle de Angel Gonzalez, S/n Cacabelos Le\u00f3n 24540",
    "addr:postcode":"24540",
    "addr:street":"Calle De Angel Gonzalez S / N",
    "iso:country":"ES",
    "sg:address":"Calle de Angel Gonzalez, S/n",
    "sg:city":"Cacabelos",
    "sg:orig_category":"T\u00c9cnicos Veterinarios",
    "sg:phone":"+34 987 54 73 27",
    "sg:postcode":"24540",
    "sg:province":"Le\u00f3n",
    "wof:name":"Armesto Gomez Francisca",
    "wof:placetype":"venue"
},
  "geometry": {"coordinates":[-6.723511219,42.598865509],"type":"Point"}
}