{
  "type": "Feature",
  "properties": {
    "addr:full":"Pl. Palomas, 13 Deifontes Granada 18570",
    "addr:housenumber":"13",
    "addr:postcode":"18570",
    "addr:street":"Palomas",
    "iso:country":"ES",
    "sg:address":"Pl. Palomas, 13",
    "sg:city":"Deifontes",
    "sg:orig_category":"C\u00c1maras De Comercio E Industria, Oficios, Agricultura",
    "sg:phone":"+34 958 40 70 06",
    "sg:postcode":"18570",
    "sg:province":"Granada",
    "wof:name":"Camara Agraria Local",
    "wof:placetype":"venue"
},
  "geometry": {"coordinates":[-3.5920140743,37.3296203613],"type":"Point"}
}