{
  "type": "Feature",
  "properties": {
    "addr:full":"Calle de Bizkaia, 47 Barakaldo Vizcaya 48902",
    "addr:housenumber":"47",
    "addr:postcode":"48902",
    "addr:street":"Calle De Bizkaia",
    "iso:country":"ES",
    "sg:address":"Calle de Bizkaia, 47",
    "sg:city":"Barakaldo",
    "sg:orig_category":"Material Y Suministros Para Imprenta E Industrias Gr\u00c1ficas",
    "sg:phone":"+34 944 37 66 04",
    "sg:postcode":"48902",
    "sg:province":"Vizcaya",
    "wof:name":"Natividad Orrantia",
    "wof:placetype":"venue"
},
  "geometry": {"coordinates":[-2.9837503433,43.2940979004],"type":"Point"}
}