{
  "type": "Feature",
  "properties": {
    "iso:country":"ES",
    "sg:address":"Calle de San Matias, S/n",
    "sg:city":"Talavera Reina",
    "sg:orig_category":"Asilos De Ancianos. Centros Privados",
    "sg:phone":"+34 925 72 19 00",
    "sg:postcode":"45600",
    "sg:province":"Toledo",
    "wof:name":"Ute Gedeco-aser Talavera De La Reina",
    "wof:placetype":"venue"
},
  "geometry": {"coordinates":[-4.857052803,39.9551353455],"type":"Point"}
}