{
  "type": "Feature",
  "properties": {
    "addr:full":"Escouredo, S/n Escouredo Lugo 27410",
    "addr:postcode":"27410",
    "addr:street":"Escouredo S / N",
    "iso:country":"ES",
    "sg:address":"Escouredo, S/n",
    "sg:city":"Escouredo",
    "sg:orig_category":"Reciclaje, Desguace De Veh\u00cdculos",
    "sg:phone":"+34 982 40 26 92",
    "sg:postcode":"27410",
    "sg:province":"Lugo",
    "wof:name":"Gunti\u00f1as Gunti\u00f1as Manuel",
    "wof:placetype":"venue"
},
  "geometry": {"coordinates":[-7.4832320213,42.5721588135],"type":"Point"}
}