{
  "type": "Feature",
  "properties": {
    "addr:full":"Calle de Loteria, 23 Aguilas Murcia 30880",
    "addr:housenumber":"23",
    "addr:postcode":"30880",
    "addr:street":"Calle De Loteria",
    "iso:country":"ES",
    "sg:address":"Calle de Loteria, 23",
    "sg:city":"Aguilas",
    "sg:orig_category":"Molduras, Junquillos, Listones Y Molduras Perforadas",
    "sg:phone":"+34 968 41 14 50",
    "sg:postcode":"30880",
    "sg:province":"Murcia",
    "wof:name":"Lopez Zapata Juan",
    "wof:placetype":"venue"
},
  "geometry": {"coordinates":[-1.5797630548,37.4105453491],"type":"Point"}
}