{
  "type": "Feature",
  "properties": {
    "iso:country":"ES",
    "sg:address":"Plaz Constitucion, 7",
    "sg:city":"Vitoria-gasteiz",
    "sg:orig_category":"Frutas, Legumbres Frescas Y Tempranas (al Por Menor)",
    "sg:phone":"+34 945 22 26 41",
    "sg:postcode":"01012",
    "sg:province":"\u00c1lava",
    "wof:name":"Naharro Moreno Emilio",
    "wof:placetype":"venue"
},
  "geometry": {"coordinates":[-2.6775500774,42.8551483154],"type":"Point"}
}