{
  "type": "Feature",
  "properties": {
    "addr:full":"Carrer de Alemanya, 60 Sabadell Barcelona 08201",
    "addr:housenumber":"60",
    "addr:postcode":"08201",
    "addr:street":"Carrer De Alemanya",
    "iso:country":"ES",
    "sg:address":"Carrer de Alemanya, 60",
    "sg:city":"Sabadell",
    "sg:orig_category":"Fabricaci\u00d3n De Telas Y Sedas",
    "sg:phone":"+34 937 27 76 45",
    "sg:postcode":"08201",
    "sg:province":"Barcelona",
    "wof:name":"Kolmertex S.a.",
    "wof:placetype":"venue"
},
  "geometry": {"coordinates":[2.1072580814,41.5420837402],"type":"Point"}
}