{
  "type": "Feature",
  "properties": {
    "iso:country":"ES",
    "sg:address":"Avda Doctor Mara\u00d1on, 33",
    "sg:city":"Malaga",
    "sg:orig_category":"Ingenier\u00cda, Centros De Estudios (diversos)",
    "sg:phone":"+34 952 07 09 62",
    "sg:postcode":"29009",
    "sg:province":"M\u00e1laga",
    "wof:name":"Ingema 2001 S.l.",
    "wof:placetype":"venue"
},
  "geometry": {"coordinates":[-4.4285721779,36.7307510376],"type":"Point"}
}