{
  "type": "Feature",
  "properties": {
    "iso:country":"ES",
    "sg:address":"Cmno San Marcial, 83",
    "sg:city":"Tudela",
    "sg:orig_category":"Guarder\u00cdas",
    "sg:phone":"+34 948 82 00 64",
    "sg:postcode":"31500",
    "sg:province":"Navarra",
    "wof:name":"Carrera Lorente Raquel",
    "wof:placetype":"venue"
},
  "geometry": {"coordinates":[-1.5944960117,42.0595474243],"type":"Point"}
}