{
  "type": "Feature",
  "properties": {
    "iso:country":"ES",
    "sg:address":"Plaz Hermano Ramon Quiroga (del), 11",
    "sg:city":"Valdemoro",
    "sg:orig_category":"Frutas, Legumbres Frescas Y Tempranas (al Por Menor)",
    "sg:phone":"+34 918 01 90 80",
    "sg:postcode":"28340",
    "sg:province":"Madrid",
    "wof:name":"Marbra C.b.",
    "wof:placetype":"venue"
},
  "geometry": {"coordinates":[-3.6738090515,40.1909751892],"type":"Point"}
}