{
  "type": "Feature",
  "properties": {
    "addr:full":"Calle de Coli Escalona, Leonardo, 53 Sabi\u00f1anigo Huesca 22600",
    "addr:housenumber":"53",
    "addr:postcode":"22600",
    "addr:street":"Calle De Coli Escalona Leonardo",
    "iso:country":"ES",
    "sg:address":"Calle de Coli Escalona, Leonardo, 53",
    "sg:city":"Sabi\u00f1anigo",
    "sg:orig_category":"Institutos De Belleza",
    "sg:phone":"+34 974 48 25 06",
    "sg:postcode":"22600",
    "sg:province":"Huesca",
    "wof:name":"Mimbrera Arevalo Maria Dolores",
    "wof:placetype":"venue"
},
  "geometry": {"coordinates":[-0.3660863936,42.5188369751],"type":"Point"}
}