{
  "type": "Feature",
  "properties": {
    "iso:country":"ES",
    "sg:address":"Calle de Consolacion, 20",
    "sg:city":"Torrelavega",
    "sg:orig_category":"Bisuter\u00cda, Joyer\u00cda, Relojer\u00cda (al Por Menor)",
    "sg:phone":"+34 942 89 27 45",
    "sg:postcode":"39300",
    "sg:province":"Cantabria",
    "wof:name":"Becerril San Justo Manuel",
    "wof:placetype":"venue"
},
  "geometry": {"coordinates":[-4.0478029251,43.3496246338],"type":"Point"}
}