{
  "type": "Feature",
  "properties": {
    "addr:full":"Real, 30 Pontedeume La Coru\u00f1a 15600",
    "addr:housenumber":"30",
    "addr:postcode":"15600",
    "addr:street":"Real;La Corun\u0303A",
    "iso:country":"ES",
    "sg:address":"Real, 30",
    "sg:city":"Pontedeume",
    "sg:orig_category":"Estancos",
    "sg:phone":"+34 981 43 14 53",
    "sg:postcode":"15600",
    "sg:province":"La Coru\u00f1a",
    "wof:name":"Gomez Vazquez Elena",
    "wof:placetype":"venue"
},
  "geometry": {"coordinates":[-8.1708097458,43.4059448242],"type":"Point"}
}