{
  "type": "Feature",
  "properties": {
    "iso:country":"ES",
    "sg:address":"Markos Deunaren Enparantza, 1",
    "sg:city":"Hondarribia",
    "sg:orig_category":"Tapiceros Y Tapiceros",
    "sg:phone":"+34 943 11 08 60",
    "sg:postcode":"20280",
    "sg:province":"Guip\u00f9zcoa",
    "wof:name":"Hamaika Interiorismo, S.l.",
    "wof:placetype":"venue"
},
  "geometry": {"coordinates":[-1.7871340513,43.3619766235],"type":"Point"}
}