{
  "type": "Feature",
  "properties": {
    "iso:country":"ES",
    "sg:address":"Prol. Floranes, 57",
    "sg:city":"Santander",
    "sg:orig_category":"Reposter\u00cdas",
    "sg:phone":"+34 942 23 00 36",
    "sg:postcode":"39010",
    "sg:province":"Cantabria",
    "wof:name":"Ruiz Lavin Emilio",
    "wof:placetype":"venue"
},
  "geometry": {"coordinates":[-3.8246290684,43.4597625732],"type":"Point"}
}