{
  "type": "Feature",
  "properties": {
    "addr:full":"Calle de Luis Oliver, 19 Marbella M\u00e1laga 29600",
    "addr:housenumber":"19",
    "addr:postcode":"29600",
    "addr:street":"Calle De Luis Oliver;Ma\u0301Laga",
    "iso:country":"ES",
    "sg:address":"Calle de Luis Oliver, 19",
    "sg:city":"Marbella",
    "sg:orig_category":"Molduras, Junquillos, Listones Y Molduras Perforadas",
    "sg:phone":"+34 952 77 90 98",
    "sg:postcode":"29600",
    "sg:province":"M\u00e1laga",
    "wof:name":"Fernandez Sanz Gaspar",
    "wof:placetype":"venue"
},
  "geometry": {"coordinates":[-4.8883318901,36.5085296631],"type":"Point"}
}