{
  "type": "Feature",
  "properties": {
    "addr:full":"Avda Santander, S/n Valladolid Valladolid 47010",
    "addr:housenumber":"s / n",
    "addr:postcode":"47010",
    "addr:street":"Avda Santander",
    "iso:country":"ES",
    "sg:address":"Avda Santander, S/n",
    "sg:city":"Valladolid",
    "sg:orig_category":"Molduras, Junquillos, Listones Y Molduras Perforadas",
    "sg:phone":"+34 983 25 22 74",
    "sg:postcode":"47010",
    "sg:province":"Valladolid",
    "wof:name":"Hermanos Rodrigo C.b.",
    "wof:placetype":"venue"
},
  "geometry": {"coordinates":[-4.7109036446,41.6661148071],"type":"Point"}
}