{
  "type": "Feature",
  "properties": {
    "addr:full":"Calle de Carrera La, 9 Ojen M\u00e1laga 29610",
    "addr:housenumber":"9",
    "addr:postcode":"29610",
    "addr:street":"Calle De Carrera La;Ma\u0301Laga",
    "iso:country":"ES",
    "sg:address":"Calle de Carrera La, 9",
    "sg:city":"Ojen",
    "sg:orig_category":"Cajas Para Embalar",
    "sg:phone":"+34 952 88 10 75",
    "sg:postcode":"29610",
    "sg:province":"M\u00e1laga",
    "wof:name":"Cajamar",
    "wof:placetype":"venue"
},
  "geometry": {"coordinates":[-4.8557491302,36.5643081665],"type":"Point"}
}