{
  "type": "Feature",
  "properties": {
    "addr:full":"Ctra S Andres, S/n San Andres Santa Cruz De Tenerife 38120",
    "addr:housenumber":"s / n",
    "addr:postcode":"38120",
    "addr:street":"Ctra S Andres",
    "iso:country":"ES",
    "sg:address":"Ctra S Andres, S/n",
    "sg:city":"San Andres",
    "sg:orig_category":"Alquiler De V\u00cddeo",
    "sg:phone":"+34 922 54 92 22",
    "sg:postcode":"38120",
    "sg:province":"Santa Cruz De Tenerife",
    "wof:name":"Pewy Y Goldo S.l.",
    "wof:placetype":"venue"
},
  "geometry": {"coordinates":[-16.1991291046,28.498884201],"type":"Point"}
}