{
  "type": "Feature",
  "properties": {
    "iso:country":"ES",
    "sg:address":"Calle de Canal De Suez, 17",
    "sg:city":"Madrid",
    "sg:orig_category":"Farmacias",
    "sg:phone":"+34 917 47 61 44",
    "sg:postcode":"28042",
    "sg:province":"Madrid",
    "wof:name":"Ortiz Gonzalez Trinidad",
    "wof:placetype":"venue"
},
  "geometry": {"coordinates":[-3.5798318386,40.4726142883],"type":"Point"}
}