{
  "type": "Feature",
  "properties": {
    "addr:full":"Calle de Capitan Perez De Sevilla, 1 Sevilla Sevilla 41002",
    "addr:housenumber":"1",
    "addr:postcode":"41002",
    "addr:street":"Calle De Capitan Perez De Sevilla",
    "iso:country":"ES",
    "sg:address":"Calle de Capitan Perez De Sevilla, 1",
    "sg:city":"Sevilla",
    "sg:orig_category":"Fabricaci\u00d3n De Art\u00cdculos Y Ornamentos Religiosos",
    "sg:phone":"+34 954 37 09 74",
    "sg:postcode":"41002",
    "sg:province":"Sevilla",
    "wof:name":"Mejias Cuellar S.l.",
    "wof:placetype":"venue"
},
  "geometry": {"coordinates":[-5.9992785454,37.3984298706],"type":"Point"}
}