{
  "type": "Feature",
  "properties": {
    "iso:country":"ES",
    "sg:address":"Talleres, 13",
    "sg:city":"Puerto Sagunto",
    "sg:orig_category":"Limpieza Con Chorro De Arena Y Con Granalla, Pulido",
    "sg:phone":"+34 962 67 08 51",
    "sg:postcode":"46520",
    "sg:province":"Valencia",
    "sg:website":"www.sandblasting.es",
    "wof:name":"Sand Blasting S.l.",
    "wof:placetype":"venue"
},
  "geometry": {"coordinates":[-0.2278539985,39.6646537781],"type":"Point"}
}