{
  "type": "Feature",
  "properties": {
    "addr:full":"Calle de Mosquera De Figueroa, 8 Sevilla Sevilla 41010",
    "addr:housenumber":"8",
    "addr:postcode":"41010",
    "addr:street":"Calle De Mosquera De Figueroa",
    "iso:country":"ES",
    "sg:address":"Calle de Mosquera De Figueroa, 8",
    "sg:city":"Sevilla",
    "sg:orig_category":"Cerrajer\u00cda, Ferrallista",
    "sg:phone":"+34 954 33 11 42",
    "sg:postcode":"41010",
    "sg:province":"Sevilla",
    "wof:name":"Viveros Diaz Fernando",
    "wof:placetype":"venue"
},
  "geometry": {"coordinates":[-6.0132274628,37.3852081299],"type":"Point"}
}