{
  "type": "Feature",
  "properties": {
    "addr:full":"Luga Birloque, 24 Coru\u00d1a La Coru\u00f1a 15008",
    "addr:housenumber":"24",
    "addr:postcode":"15008",
    "addr:street":"Birloque;La Corun\u0303A",
    "iso:country":"ES",
    "sg:address":"Luga Birloque, 24",
    "sg:city":"Coru\u00d1a",
    "sg:orig_category":"Sociedades, Compa\u00d1\u00cdas Aseguradoras",
    "sg:phone":"+34 981 28 79 34",
    "sg:postcode":"15008",
    "sg:province":"La Coru\u00f1a",
    "wof:name":"Fito & Asociados, Gestion De Riesgos S.l.",
    "wof:placetype":"venue"
},
  "geometry": {"coordinates":[-8.4155778885,43.3414840698],"type":"Point"}
}