{
  "type": "Feature",
  "properties": {
    "iso:country":"ES",
    "sg:address":"Calle de Serrano, 33",
    "sg:city":"Madrid",
    "sg:classifiers":[
        {
            "category":"Professional",
            "subcategory":"Management & Consulting",
            "type":"Services"
        }
    ],
    "sg:phone":"+34 917 26 98 70",
    "sg:postcode":"28001",
    "sg:province":"Madrid",
    "sg:tags":[
        "asesor\u00cda",
        "en",
        "marketing"
    ],
    "sg:website":"www.grupospmarketing.com",
    "wof:name":"Sist Y Procedim De Marketing S.l.",
    "wof:placetype":"venue"
},
  "geometry": {"coordinates":[-3.6875910759,40.4276542664],"type":"Point"}
}