{
  "type": "Feature",
  "properties": {
    "addr:full":"Calle de Jesus Y Maria, 26 Valencia Valencia 46008",
    "addr:housenumber":"26",
    "addr:postcode":"46008",
    "addr:street":"Calle De Jesus Y Maria",
    "iso:country":"ES",
    "sg:address":"Calle de Jesus Y Maria, 26",
    "sg:city":"Valencia",
    "sg:orig_category":"Andamiajes Y Escaleras De Mano (fabricaci\u00d3n, Al Por Mayor)",
    "sg:phone":"+34 963 85 54 72",
    "sg:postcode":"46008",
    "sg:province":"Valencia",
    "wof:name":"Comercial Montajes De Andamios Y Cimbras S.l.",
    "wof:placetype":"venue"
},
  "geometry": {"coordinates":[-0.3890300095,39.473903656],"type":"Point"}
}