{
  "type": "Feature",
  "properties": {
    "addr:full":"Calle de Marmoles, 9 Ecija Sevilla 41400",
    "addr:housenumber":"9",
    "addr:postcode":"41400",
    "addr:street":"Calle De Marmoles",
    "iso:country":"ES",
    "sg:address":"Calle de Marmoles, 9",
    "sg:city":"Ecija",
    "sg:orig_category":"Producci\u00d3n, Venta De Productos De Agricultura Biol\u00d3gica",
    "sg:phone":"+34 954 83 15 92",
    "sg:postcode":"41400",
    "sg:province":"Sevilla",
    "wof:name":"Hens Reyes Jose Maria",
    "wof:placetype":"venue"
},
  "geometry": {"coordinates":[-5.0782589912,37.539932251],"type":"Point"}
}