{
  "type": "Feature",
  "properties": {
    "iso:country":"ES",
    "sg:address":"Calle de Hornos Caleros (de Los), 16",
    "sg:city":"Avila",
    "sg:orig_category":"Centros Empresariales",
    "sg:phone":"+34 920 22 46 12",
    "sg:postcode":"05001",
    "sg:province":"\u00c1vila",
    "wof:name":"Federacion De Empresas De La Construccion Y Obras Publicas",
    "wof:placetype":"venue"
},
  "geometry": {"coordinates":[-4.6856417656,40.654750824],"type":"Point"}
}