{
  "type": "Feature",
  "properties": {
    "addr:full":"Calle de Alonso Alvarado, 2 Palmas De Gran Canaria Las Palmas 35003",
    "addr:housenumber":"2",
    "addr:postcode":"35003",
    "addr:street":"Calle De Alonso Alvarado",
    "iso:country":"ES",
    "sg:address":"Calle de Alonso Alvarado, 2",
    "sg:city":"Palmas De Gran Canaria",
    "sg:orig_category":"Cer\u00c1micas: Material Y Suministros",
    "sg:phone":"+34 928 38 46 89",
    "sg:postcode":"35003",
    "sg:province":"Las Palmas",
    "wof:name":"Revestican S.l.",
    "wof:placetype":"venue"
},
  "geometry": {"coordinates":[-15.4172945023,28.1093921661],"type":"Point"}
}