{
  "type": "Feature",
  "properties": {
    "iso:country":"ES",
    "sg:address":"Calle de Ramon Ortiz De Zarate, 1",
    "sg:city":"Vitoria-gasteiz",
    "sg:orig_category":"Centros De Coordinaci\u00d3n",
    "sg:phone":"+34 945 14 40 10",
    "sg:postcode":"01005",
    "sg:province":"\u00c1lava",
    "sg:website":"www.gestoriapilargurruchaga.es",
    "wof:name":"Gestoria Pilar Gurruchaga S.l.",
    "wof:placetype":"venue"
},
  "geometry": {"coordinates":[-2.6709508896,42.843132019],"type":"Point"}
}