{
  "type": "Feature",
  "properties": {
    "addr:full":"Carrer de Agusti Domingo, 16 Sant Feliu Llobregat Barcelona 08980",
    "addr:housenumber":"16",
    "addr:postcode":"08980",
    "addr:street":"Carrer De Agusti Domingo",
    "iso:country":"ES",
    "sg:address":"Carrer de Agusti Domingo, 16",
    "sg:city":"Sant Feliu Llobregat",
    "sg:orig_category":"Estancos",
    "sg:phone":"+34 936 66 29 59",
    "sg:postcode":"08980",
    "sg:province":"Barcelona",
    "wof:name":"Salda\u00f1a Salda\u00f1a Bienvenida",
    "wof:placetype":"venue"
},
  "geometry": {"coordinates":[2.0473930836,41.3862113953],"type":"Point"}
}