{
  "type": "Feature",
  "properties": {
    "iso:country":"ES",
    "sg:address":"Ctra. Barig, 31",
    "sg:city":"Marchuquera",
    "sg:orig_category":"Fabricaci\u00d3n, Venta, Instalaci\u00d3n De R\u00d3tulos, De R\u00d3tulos Luminosos",
    "sg:phone":"+34 962 87 07 98",
    "sg:postcode":"46728",
    "sg:province":"Valencia",
    "wof:name":"Altas Rotulaciones S.l.",
    "wof:placetype":"venue"
},
  "geometry": {"coordinates":[-0.2476495057,38.9682884216],"type":"Point"}
}