{
  "type": "Feature",
  "properties": {
    "addr:full":"Calle de Sancho Davila, 35 Madrid Madrid 28028",
    "addr:housenumber":"35",
    "addr:postcode":"madrid;28028",
    "addr:street":"Calle De Sancho Davila",
    "iso:country":"ES",
    "sg:address":"Calle de Sancho Davila, 35",
    "sg:city":"Madrid",
    "sg:orig_category":"Bancos",
    "sg:phone":"+34 917 25 47 50",
    "sg:postcode":"28028",
    "sg:province":"Madrid",
    "wof:name":"Banco Espa\u00f1ol De Credito S.a.",
    "wof:placetype":"venue"
},
  "geometry": {"coordinates":[-3.6615159512,40.4252586365],"type":"Point"}
}