{
  "type": "Feature",
  "properties": {
    "addr:full":"Barr Pardi\u00d1o, S/n Sameiro Pontevedra 36633",
    "addr:housenumber":"s / n",
    "addr:postcode":"36633",
    "iso:country":"ES",
    "sg:address":"Barr Pardi\u00d1o, S/n",
    "sg:city":"Sameiro",
    "sg:orig_category":"Poller\u00cda Y Caza (al Por Menor)",
    "sg:phone":"+34 986 52 03 48",
    "sg:postcode":"36633",
    "sg:province":"Pontevedra",
    "wof:name":"Martinez Miguens Jose Luis",
    "wof:placetype":"venue"
},
  "geometry": {"coordinates":[-8.7952222824,42.2552261353],"type":"Point"}
}