{
  "type": "Feature",
  "properties": {
    "addr:full":"Calle de Armengual De La Mota, 17 Malaga M\u00e1laga 29007",
    "addr:housenumber":"17",
    "addr:postcode":"29007",
    "addr:street":"Calle De Armengual De La Mota;Ma\u0301Laga",
    "iso:country":"ES",
    "sg:address":"Calle de Armengual De La Mota, 17",
    "sg:city":"Malaga",
    "sg:orig_category":"Administradores De Bienes Y Delegados De Comunidades De Propietarios",
    "sg:phone":"+34 952 27 22 51",
    "sg:postcode":"29007",
    "sg:province":"M\u00e1laga",
    "wof:name":"Luque Cantero Jesus Isidoro",
    "wof:placetype":"venue"
},
  "geometry": {"coordinates":[-4.42927742,36.7194519043],"type":"Point"}
}