{
  "type": "Feature",
  "properties": {
    "iso:country":"ES",
    "sg:address":"Crt. G. Sevilla, Km. 0312,0",
    "sg:city":"Almendralejo",
    "sg:orig_category":"Agentes, Concesionarios Y Sucursales De Veh\u00cdculos",
    "sg:phone":"+34 924 67 12 58",
    "sg:postcode":"06200",
    "sg:province":"Badajoz",
    "wof:name":"Auto Sur C.b.",
    "wof:placetype":"venue"
},
  "geometry": {"coordinates":[-6.4068241119,38.6845092773],"type":"Point"}
}