{
  "type": "Feature",
  "properties": {
    "iso:country":"ES",
    "sg:address":"Pol Ind Norte, S/n",
    "sg:city":"Alginet",
    "sg:orig_category":"Reciclaje Y Tratamiento De Desechos Varios",
    "sg:phone":"+34 961 75 91 70",
    "sg:postcode":"46230",
    "sg:province":"Valencia",
    "wof:name":"Cespa Gestion De Ressiduos S.a.",
    "wof:placetype":"venue"
},
  "geometry": {"coordinates":[-0.470043987,39.2614898682],"type":"Point"}
}