{
  "type": "Feature",
  "properties": {
    "addr:full":"Calle de Mayor, 45 Pe\u00e7as De San Pedro Albacete 02120",
    "addr:housenumber":"45",
    "addr:postcode":"02120",
    "addr:street":"Calle De Mayor",
    "iso:country":"ES",
    "sg:address":"Calle de Mayor, 45",
    "sg:city":"Pe\u00e7as De San Pedro",
    "sg:orig_category":"Centros Empresariales",
    "sg:phone":"+34 967 29 81 13",
    "sg:postcode":"02120",
    "sg:province":"Albacete",
    "wof:name":"Lloret Velando Jose Luis",
    "wof:placetype":"venue"
},
  "geometry": {"coordinates":[-2.0043799877,38.7274627686],"type":"Point"}
}