{
  "type": "Feature",
  "properties": {
    "addr:full":"Calle de Vidal De Canellas, 17 Zaragoza Zaragoza 50005",
    "addr:housenumber":"17",
    "addr:postcode":"50005",
    "addr:street":"Calle De Vidal De Canellas",
    "iso:country":"ES",
    "sg:address":"Calle de Vidal De Canellas, 17",
    "sg:city":"Zaragoza",
    "sg:orig_category":"Artes Gr\u00c1ficas, Artes Pl\u00c1sticas (curso)",
    "sg:phone":"+34 976 55 66 72",
    "sg:postcode":"50005",
    "sg:province":"Zaragoza",
    "wof:name":"Martin Rutia Jesus",
    "wof:placetype":"venue"
},
  "geometry": {"coordinates":[-0.899726212,41.6476669312],"type":"Point"}
}