{
  "type": "Feature",
  "properties": {
    "iso:country":"ES",
    "sg:address":"Carrer de Roc Boronat, 46",
    "sg:city":"Barcelona",
    "sg:orig_category":"Iglesias Cristianas Diversas",
    "sg:phone":"+34 933 00 37 01",
    "sg:postcode":"08005",
    "sg:province":"Barcelona",
    "wof:name":"Asociacion De Los Testigos Cristianos De Jehova",
    "wof:placetype":"venue"
},
  "geometry": {"coordinates":[2.1993093491,41.3991584778],"type":"Point"}
}