{
  "type": "Feature",
  "properties": {
    "addr:full":"Avda Oasis, 65 Ejido Almer\u00eda 04700",
    "addr:housenumber":"65 ejido",
    "addr:postcode":"04700",
    "addr:street":"Avda Oasis;Almeri\u0301A",
    "iso:country":"ES",
    "sg:address":"Avda Oasis, 65",
    "sg:city":"Ejido",
    "sg:orig_category":"Venta, Instalaci\u00d3n, Mantenimiento De Chimeneas De Interior Y Accesorios",
    "sg:phone":"+34 950 57 13 18",
    "sg:postcode":"04700",
    "sg:province":"Almer\u00eda",
    "sg:website":"www.chimeneasorus.com",
    "wof:name":"Comercial Medina Conejero S.l.",
    "wof:placetype":"venue"
},
  "geometry": {"coordinates":[-2.8005490303,36.7705802917],"type":"Point"}
}