{
  "type": "Feature",
  "properties": {
    "addr:full":"Calle de Capitan Esponera, 18 Zaragoza Zaragoza 50004",
    "addr:housenumber":"18",
    "addr:postcode":"50004",
    "addr:street":"Calle De Capitan Esponera",
    "iso:country":"ES",
    "sg:address":"Calle de Capitan Esponera, 18",
    "sg:city":"Zaragoza",
    "sg:orig_category":"Asociaciones Y Clubs Deportivos",
    "sg:phone":"+34 976 22 41 46",
    "sg:postcode":"50004",
    "sg:province":"Zaragoza",
    "wof:name":"Pedro Ferrer Jose Ignacio De",
    "wof:placetype":"venue"
},
  "geometry": {"coordinates":[-0.8900594115,41.6492843628],"type":"Point"}
}