{
  "type": "Feature",
  "properties": {
    "iso:country":"ES",
    "sg:address":"Ptd. Closa, 6",
    "sg:city":"Vinaros",
    "sg:orig_category":"Abogados",
    "sg:phone":"+34 964 40 72 58",
    "sg:postcode":"12500",
    "sg:province":"Castell\u00f3n",
    "wof:name":"Rottgers  Fritz",
    "wof:placetype":"venue"
},
  "geometry": {"coordinates":[0.4749450088,40.4711990356],"type":"Point"}
}