{
  "type": "Feature",
  "properties": {
    "iso:country":"ES",
    "sg:address":"Av Alcoi, S/n",
    "sg:city":"Benidorm",
    "sg:orig_category":"Bazares, Art\u00cdculos De Limpieza Y De Cocina (al Por Menor)",
    "sg:phone":"+34 965 85 40 22",
    "sg:postcode":"03500",
    "sg:province":"Alicante",
    "wof:name":"Hemnani Thakwani Ishwar",
    "wof:placetype":"venue"
},
  "geometry": {"coordinates":[-0.1210739985,38.535785675],"type":"Point"}
}