{
  "type": "Feature",
  "properties": {
    "addr:full":"Calle de Jose Zorrilla, 7 Fernan Nu\u00e7ez C\u00f3rdoba 14520",
    "addr:housenumber":"7",
    "addr:postcode":"14520",
    "addr:street":"Calle De Jose Zorrilla;Co\u0301Rdoba",
    "iso:country":"ES",
    "sg:address":"Calle de Jose Zorrilla, 7",
    "sg:city":"Fernan Nu\u00e7ez",
    "sg:orig_category":"Delegados, Agentes De Tr\u00c1nsito, Auxiliares De Transporte Internacional",
    "sg:phone":"+34 957 38 11 83",
    "sg:postcode":"14520",
    "sg:province":"C\u00f3rdoba",
    "wof:name":"Toro Blancat Francisco",
    "wof:placetype":"venue"
},
  "geometry": {"coordinates":[-4.723941803,37.6695404053],"type":"Point"}
}