{
  "type": "Feature",
  "properties": {
    "iso:country":"ES",
    "sg:address":"Calle de Alfonso X El Sabio, 30",
    "sg:city":"Alcala Guadaira",
    "sg:orig_category":"Chapister\u00cda",
    "sg:phone":"+34 955 61 05 22",
    "sg:postcode":"41500",
    "sg:province":"Sevilla",
    "wof:name":"Mayoral Herranz Maria Del Carmen",
    "wof:placetype":"venue"
},
  "geometry": {"coordinates":[-5.8397502899,37.3445205688],"type":"Point"}
}