{
  "type": "Feature",
  "properties": {
    "addr:full":"Larga, 69 Betera Valencia 46117",
    "addr:housenumber":"69",
    "addr:postcode":"46117",
    "addr:street":"Larga",
    "iso:country":"ES",
    "sg:address":"Larga, 69",
    "sg:city":"Betera",
    "sg:orig_category":"Prot\u00c9sicos Dentales",
    "sg:phone":"+34 961 69 82 03",
    "sg:postcode":"46117",
    "sg:province":"Valencia",
    "wof:name":"Dentipak",
    "wof:placetype":"venue"
},
  "geometry": {"coordinates":[-0.4648790061,39.5908317566],"type":"Point"}
}