{
  "type": "Feature",
  "properties": {
    "addr:full":"Calle de Nueva, 12 Moron Frontera Sevilla 41530",
    "addr:housenumber":"12",
    "addr:postcode":"41530",
    "addr:street":"Calle De Nueva",
    "iso:country":"ES",
    "sg:address":"Calle de Nueva, 12",
    "sg:city":"Moron Frontera",
    "sg:orig_category":"Parques De Atracciones Y Centros De Esparcimiento",
    "sg:phone":"+34 954 85 08 91",
    "sg:postcode":"41530",
    "sg:province":"Sevilla",
    "wof:name":"Eurotel-sur S.l.",
    "wof:placetype":"venue"
},
  "geometry": {"coordinates":[-5.4515171051,37.1218261719],"type":"Point"}
}