{
  "type": "Feature",
  "properties": {
    "addr:full":"Ctra Villar Del Humo, 10 Cardenete Cuenca 16373",
    "addr:housenumber":"10",
    "addr:postcode":"16373",
    "addr:street":"Ctra Villar Del Humo",
    "iso:country":"ES",
    "sg:address":"Ctra Villar Del Humo, 10",
    "sg:city":"Cardenete",
    "sg:orig_category":"Mec\u00c1nico Del Autom\u00d3vil",
    "sg:phone":"+34 969 34 80 31",
    "sg:postcode":"16373",
    "sg:province":"Cuenca",
    "wof:name":"Lorente Pino S.l.",
    "wof:placetype":"venue"
},
  "geometry": {"coordinates":[-1.6915240288,39.7678604126],"type":"Point"}
}