{
  "type": "Feature",
  "properties": {
    "addr:full":"Calle de San Jeronimo, 4 Donostia-san Sebastian Guip\u00f9zcoa 20003",
    "addr:housenumber":"4",
    "addr:postcode":"20003",
    "addr:street":"Calle De San Jeronimo",
    "iso:country":"ES",
    "sg:address":"Calle de San Jeronimo, 4",
    "sg:city":"Donostia-san Sebastian",
    "sg:orig_category":"Art\u00cdculos De Regalo (al Por Menor)",
    "sg:phone":"+34 943 42 29 97",
    "sg:postcode":"20003",
    "sg:province":"Guip\u00f9zcoa",
    "wof:name":"Perez-muga Perez Miguel Angel",
    "wof:placetype":"venue"
},
  "geometry": {"coordinates":[-1.9850590229,43.3225784302],"type":"Point"}
}