{
  "type": "Feature",
  "properties": {
    "iso:country":"ES",
    "sg:address":"Avda Villanueva, 9",
    "sg:city":"Badajoz",
    "sg:orig_category":"Florister\u00cdas",
    "sg:phone":"+34 924 23 16 06",
    "sg:postcode":"06005",
    "sg:province":"Badajoz",
    "wof:name":"Boraita Hermosell Maria Soledad",
    "wof:placetype":"venue"
},
  "geometry": {"coordinates":[-6.9778981209,38.870891571],"type":"Point"}
}