{
  "type": "Feature",
  "properties": {
    "addr:full":"Ptda Quatre Pilans, 15 Lleida Lleida 25197",
    "addr:housenumber":"15",
    "addr:postcode":"25197",
    "addr:street":"Ptda Quatre Pilans",
    "iso:country":"ES",
    "sg:address":"Ptda Quatre Pilans, 15",
    "sg:city":"Lleida",
    "sg:orig_category":"Hielo Artificial (fabricaci\u00d3n, Distribuci\u00d3n)",
    "sg:phone":"+34 973 20 03 00",
    "sg:postcode":"25197",
    "sg:province":"Lleida",
    "wof:name":"Buenaventura Borras S.a.",
    "wof:placetype":"venue"
},
  "geometry": {"coordinates":[0.6469299793,41.6021995544],"type":"Point"}
}