{
  "type": "Feature",
  "properties": {
    "iso:country":"ES",
    "sg:address":"Carrer de Mare De Deu Del Coll, 8",
    "sg:city":"Barcelona",
    "sg:orig_category":"Reposter\u00cdas",
    "sg:phone":"+34 932 17 25 82",
    "sg:postcode":"08023",
    "sg:province":"Barcelona",
    "wof:name":"Puig Baraut Lluis",
    "wof:placetype":"venue"
},
  "geometry": {"coordinates":[2.1505200863,41.4082946777],"type":"Point"}
}