{
  "type": "Feature",
  "properties": {
    "addr:full":"Av Corts Catalanes, 13 S. Cugat Valles Barcelona 08173",
    "addr:housenumber":"13",
    "addr:postcode":"08173",
    "addr:street":"Av Corts Catalanes;S. Cugat Valles Barcelona",
    "iso:country":"ES",
    "sg:address":"Av Corts Catalanes, 13",
    "sg:city":"S. Cugat Valles",
    "sg:orig_category":"Agentes, Concesionarios Y Sucursales De Veh\u00cdculos",
    "sg:phone":"+34 935 90 21 90",
    "sg:postcode":"08173",
    "sg:province":"Barcelona",
    "sg:website":"www.motorklasse.mercedes-benz.es",
    "wof:name":"Motor Klasse S.l.",
    "wof:placetype":"venue"
},
  "geometry": {"coordinates":[2.0974609852,41.4741325378],"type":"Point"}
}