{
  "type": "Feature",
  "properties": {
    "iso:country":"ES",
    "sg:address":"Calle de Islas Bermudas, 3",
    "sg:city":"Madrid",
    "sg:orig_category":"Colchones (fabricaci\u00d3n, Al Por Mayor, Al Por Menor)",
    "sg:phone":"+34 917 34 08 48",
    "sg:postcode":"28034",
    "sg:province":"Madrid",
    "wof:name":"Crespo Alonso Yolanda",
    "wof:placetype":"venue"
},
  "geometry": {"coordinates":[-3.6871869564,40.4927597046],"type":"Point"}
}