{
  "type": "Feature",
  "properties": {
    "iso:country":"ES",
    "sg:address":"Carr Ramon Argiles, 22",
    "sg:city":"Lleida",
    "sg:orig_category":"Textil",
    "sg:phone":"+34 973 23 67 06",
    "sg:postcode":"25005",
    "sg:province":"Lleida",
    "wof:name":"Toldos Giralt S.c.c.l.",
    "wof:placetype":"venue"
},
  "geometry": {"coordinates":[0.6383280158,41.6263465881],"type":"Point"}
}