{
  "type": "Feature",
  "properties": {
    "iso:country":"ES",
    "sg:address":"Calle de San Maximiliano, 31",
    "sg:city":"Madrid",
    "sg:orig_category":"Mec\u00c1nico Del Autom\u00d3vil",
    "sg:phone":"+34 914 04 81 93",
    "sg:postcode":"28017",
    "sg:province":"Madrid",
    "wof:name":"Suarez Vega Pedro",
    "wof:placetype":"venue"
},
  "geometry": {"coordinates":[-3.6536388397,40.4249191284],"type":"Point"}
}