{
  "type": "Feature",
  "properties": {
    "addr:full":"Carr Jose Gascon, 29 Betera Valencia 46117",
    "addr:housenumber":"29",
    "addr:postcode":"46117",
    "addr:street":"Carr Jose Gascon",
    "iso:country":"ES",
    "sg:address":"Carr Jose Gascon, 29",
    "sg:city":"Betera",
    "sg:orig_category":"Inmobiliaria (agencias)",
    "sg:phone":"+34 961 69 84 84",
    "sg:postcode":"46117",
    "sg:province":"Valencia",
    "wof:name":"Fayos Verdiguier Carlos",
    "wof:placetype":"venue"
},
  "geometry": {"coordinates":[-0.4612770081,39.5912399292],"type":"Point"}
}