{
  "type": "Feature",
  "properties": {
    "addr:full":"Rio Altzania, 29 Iru\u00f1a Navarra 31005",
    "addr:housenumber":"29",
    "addr:postcode":"31005",
    "addr:street":"Rio Altzania",
    "iso:country":"ES",
    "sg:address":"Rio Altzania, 29",
    "sg:city":"Iru\u00f1a",
    "sg:orig_category":"Asesor\u00cda Sobre Comunicaci\u00d3n De Empresas",
    "sg:phone":"+34 948 24 16 50",
    "sg:postcode":"31005",
    "sg:province":"Navarra",
    "wof:name":"Applus Norcontrol S.l.u.",
    "wof:placetype":"venue"
},
  "geometry": {"coordinates":[-1.6475813389,42.801109314],"type":"Point"}
}