{
  "type": "Feature",
  "properties": {
    "addr:full":"Ctra Sevilla, Km. 0156,0 Antequera M\u00e1laga 29200",
    "addr:postcode":"29200",
    "addr:street":"Ctra Sevilla Km. 0156,0;Ma\u0301Laga",
    "iso:country":"ES",
    "sg:address":"Ctra Sevilla, Km. 0156,0",
    "sg:city":"Antequera",
    "sg:orig_category":"Asociaciones Y Clubs Deportivos",
    "sg:phone":"+34 952 70 51 21",
    "sg:postcode":"29200",
    "sg:province":"M\u00e1laga",
    "wof:name":"Quintana Soto Manuel",
    "wof:placetype":"venue"
},
  "geometry": {"coordinates":[-4.5657992363,37.0221099854],"type":"Point"}
}