{
  "type": "Feature",
  "properties": {
    "iso:country":"ES",
    "sg:address":"Valilongo, Km. 0015,0",
    "sg:city":"Pte. Domingo Florez",
    "sg:orig_category":"Maquinaria Para Industrias Diversas",
    "sg:phone":"+34 987 46 04 04",
    "sg:postcode":"24380",
    "sg:province":"Le\u00f3n",
    "wof:name":"Talleres Jupa El Puente S.l.",
    "wof:placetype":"venue"
},
  "geometry": {"coordinates":[-6.8208842278,42.411655426],"type":"Point"}
}