{
  "type": "Feature",
  "properties": {
    "iso:country":"ES",
    "sg:address":"Calle de Doctor Sanchis Sivera, 24",
    "sg:city":"Valencia",
    "sg:orig_category":"Psic\u00d3logos",
    "sg:phone":"+34 963 85 08 63",
    "sg:postcode":"46008",
    "sg:province":"Valencia",
    "wof:name":"Campoy Camacho Celia",
    "wof:placetype":"venue"
},
  "geometry": {"coordinates":[-0.3873828053,39.4684906006],"type":"Point"}
}