{
  "type": "Feature",
  "properties": {
    "addr:full":"Carrer de Nou, 3 Falset Tarragona 43730",
    "addr:housenumber":"3",
    "addr:postcode":"43730",
    "addr:street":"Carrer De Nou",
    "iso:country":"ES",
    "sg:address":"Carrer de Nou, 3",
    "sg:city":"Falset",
    "sg:orig_category":"Restaurantes",
    "sg:phone":"+34 977 83 04 81",
    "sg:postcode":"43730",
    "sg:province":"Tarragona",
    "wof:name":"Mestre Cardona Juli",
    "wof:placetype":"venue"
},
  "geometry": {"coordinates":[0.8203870058,41.1456947327],"type":"Point"}
}