{
  "type": "Feature",
  "properties": {
    "addr:full":"Carretera, Km. 0004,7 Alcoletge Lleida 25660",
    "addr:postcode":"25660",
    "addr:street":"Carretera Km. 0004,7",
    "iso:country":"ES",
    "sg:address":"Carretera, Km. 0004,7",
    "sg:city":"Alcoletge",
    "sg:orig_category":"Artesan\u00cda",
    "sg:phone":"+34 973 19 71 17",
    "sg:postcode":"25660",
    "sg:province":"Lleida",
    "wof:name":"Carvajal Corredera S.l.",
    "wof:placetype":"venue"
},
  "geometry": {"coordinates":[0.694265008,41.649433136],"type":"Point"}
}