{
  "type": "Feature",
  "properties": {
    "iso:country":"ES",
    "sg:address":"Calle de Santa Tecla, 42",
    "sg:city":"Madrid",
    "sg:orig_category":"Importaci\u00d3n",
    "sg:phone":"+34 913 20 93 81",
    "sg:postcode":"28022",
    "sg:province":"Madrid",
    "wof:name":"Agc Artesania Grafica Comercio S.l.",
    "wof:placetype":"venue"
},
  "geometry": {"coordinates":[-3.6126759052,40.4435119629],"type":"Point"}
}