{
  "type": "Feature",
  "properties": {
    "iso:country":"ES",
    "sg:address":"Barr Gallardi, 12",
    "sg:city":"Sollano-llantada",
    "sg:orig_category":"Material Y Herramientas Agr\u00cdcolas",
    "sg:phone":"+34 946 39 01 30",
    "sg:postcode":"48860",
    "sg:province":"Vizcaya",
    "sg:website":"hergasa@euskalnet.net",
    "wof:name":"Hermanos Garcia De Andoin Sarachaga S. L.",
    "wof:placetype":"venue"
},
  "geometry": {"coordinates":[-3.1296989918,43.2133483887],"type":"Point"}
}