{
  "type": "Feature",
  "properties": {
    "iso:country":"ES",
    "sg:address":"Avda Principe De Asturias, 31",
    "sg:city":"Zamora",
    "sg:orig_category":"Asesor\u00cda De Formaci\u00d3n Y Gesti\u00d3n De Personal",
    "sg:phone":"+34 980 51 11 94",
    "sg:postcode":"49011",
    "sg:province":"Zamora",
    "wof:name":"Punto Zamora S.l.",
    "wof:placetype":"venue"
},
  "geometry": {"coordinates":[-5.7376661301,41.5109214783],"type":"Point"}
}