{
  "type": "Feature",
  "properties": {
    "iso:country":"ES",
    "sg:address":"Carrer de Sardenya, 213",
    "sg:city":"Barcelona",
    "sg:orig_category":"Bisuteros (fabricaci\u00d3n, Al Por Mayor)",
    "sg:phone":"+34 932 65 30 80",
    "sg:postcode":"08013",
    "sg:province":"Barcelona",
    "sg:website":"www.microfusionsolsona.com",
    "wof:name":"Microfusion Solsona S.l.",
    "wof:placetype":"venue"
},
  "geometry": {"coordinates":[2.1783130169,41.3994407654],"type":"Point"}
}