{
  "type": "Feature",
  "properties": {
    "iso:country":"ES",
    "sg:address":"Calle de Magdalena, 2",
    "sg:city":"Rafelbunyol",
    "sg:orig_category":"Electrodom\u00c9sticos (al Por Menor)",
    "sg:phone":"+34 961 41 01 15",
    "sg:postcode":"46138",
    "sg:province":"Valencia",
    "wof:name":"Borras Mestre Jose Manuel",
    "wof:placetype":"venue"
},
  "geometry": {"coordinates":[-0.3346120119,39.5886497498],"type":"Point"}
}