{
  "type": "Feature",
  "properties": {
    "iso:country":"ES",
    "sg:address":"Calle de Larga, 1",
    "sg:city":"Chiclana De La Frontera",
    "sg:orig_category":"Farmacias",
    "sg:phone":"+34 956 40 02 03",
    "sg:postcode":"11130",
    "sg:province":"C\u00e1diz",
    "wof:name":"Farmacia Galan Optica",
    "wof:placetype":"venue"
},
  "geometry": {"coordinates":[-6.1456289291,36.414100647],"type":"Point"}
}