{
  "type": "Feature",
  "properties": {
    "iso:country":"ES",
    "sg:address":"Avda Marinas (las), 96",
    "sg:city":"Marinas",
    "sg:orig_category":"Fabricaci\u00d3n De Art\u00cdculos Para Papeler\u00cdas",
    "sg:phone":"+34 950 33 33 62",
    "sg:postcode":"04740",
    "sg:province":"Almer\u00eda",
    "wof:name":"Tricio Gomez Jorge J.",
    "wof:placetype":"venue"
},
  "geometry": {"coordinates":[-2.6339890957,36.7305793762],"type":"Point"}
}