{
  "type": "Feature",
  "properties": {
    "iso:country":"ES",
    "sg:address":"Carr Les Roses, 32",
    "sg:city":"Lleida",
    "sg:orig_category":"Plomeros",
    "sg:phone":"+34 973 20 66 02",
    "sg:postcode":"25001",
    "sg:province":"Lleida",
    "wof:name":"Huguet Baque Antonio Salvador",
    "wof:placetype":"venue"
},
  "geometry": {"coordinates":[0.6414020061,41.604057312],"type":"Point"}
}