{
  "type": "Feature",
  "properties": {
    "iso:country":"ES",
    "sg:address":"Cno. Angel, 4",
    "sg:city":"Nueva Andalucia",
    "sg:orig_category":"Asesor\u00cda Fiscal Y Jur\u00cddica",
    "sg:phone":"+34 952 76 40 65",
    "sg:postcode":"29660",
    "sg:province":"M\u00e1laga",
    "wof:name":"Fay And Co.auditores S.l.",
    "wof:placetype":"venue"
},
  "geometry": {"coordinates":[-4.95921278,36.5132675171],"type":"Point"}
}