{
  "type": "Feature",
  "properties": {
    "addr:full":"Avda Los Huetos, 20 Vitoria-gasteiz \u00c1lava 01010",
    "addr:housenumber":"20",
    "addr:postcode":"01010",
    "addr:street":"Avda Los Huetos",
    "iso:country":"ES",
    "sg:address":"Avda Los Huetos, 20",
    "sg:city":"Vitoria-gasteiz",
    "sg:orig_category":"Peluquer\u00cdas, Peluquer\u00cda Mixta",
    "sg:phone":"+34 945 24 68 23",
    "sg:postcode":"01010",
    "sg:province":"\u00c1lava",
    "wof:name":"Elisa Lopez Fondo",
    "wof:placetype":"venue"
},
  "geometry": {"coordinates":[-2.7029910088,42.8545722961],"type":"Point"}
}