{
  "type": "Feature",
  "properties": {
    "addr:full":"El Rebollar, S/n Santiago Asturias 33518",
    "addr:housenumber":"s / n",
    "addr:postcode":"33518",
    "addr:street":"El Rebollar",
    "iso:country":"ES",
    "sg:address":"El Rebollar, S/n",
    "sg:city":"Santiago",
    "sg:orig_category":"Producci\u00d3n De Sidra",
    "sg:phone":"+34 985 74 82 56",
    "sg:postcode":"33518",
    "sg:province":"Asturias",
    "wof:name":"Pomaradas Y Lagares De Sariego S.l.",
    "wof:placetype":"venue"
},
  "geometry": {"coordinates":[-5.5597882271,43.4101409912],"type":"Point"}
}