{
  "type": "Feature",
  "properties": {
    "addr:full":"Calle de Joaquin Coronel, 35 Elda Alicante 03600",
    "addr:housenumber":"35",
    "addr:postcode":"03600",
    "addr:street":"Calle De Joaquin Coronel",
    "iso:country":"ES",
    "sg:address":"Calle de Joaquin Coronel, 35",
    "sg:city":"Elda",
    "sg:orig_category":"Cl\u00cdnicas Dentales",
    "sg:phone":"+34 965 38 22 38",
    "sg:postcode":"03600",
    "sg:province":"Alicante",
    "wof:name":"Centro Dentral Castelar S.l.",
    "wof:placetype":"venue"
},
  "geometry": {"coordinates":[-0.7885090113,38.4784088135],"type":"Point"}
}