{
  "type": "Feature",
  "properties": {
    "addr:full":"Rua Calvo Sotelo, 59 Cea Ourense 32130",
    "addr:housenumber":"59",
    "addr:postcode":"32130",
    "addr:street":"Rua Calvo Sotelo",
    "iso:country":"ES",
    "sg:address":"Rua Calvo Sotelo, 59",
    "sg:city":"Cea",
    "sg:orig_category":"Bancos",
    "sg:phone":"+34 988 28 35 00",
    "sg:postcode":"32130",
    "sg:province":"Ourense",
    "wof:name":"R Cable Y Telecomunicaciones Galicia S.a.",
    "wof:placetype":"venue"
},
  "geometry": {"coordinates":[-7.9867691994,42.475818634],"type":"Point"}
}