{
  "type": "Feature",
  "properties": {
    "addr:full":"Calle de Guzman El Bueno, 115 Madrid Madrid 28003",
    "addr:housenumber":"115",
    "addr:postcode":"28003",
    "addr:street":"Calle De Guzman El Bueno",
    "iso:country":"ES",
    "sg:address":"Calle de Guzman El Bueno, 115",
    "sg:city":"Madrid",
    "sg:orig_category":"Institutos De Belleza",
    "sg:phone":"+34 914 41 08 63",
    "sg:postcode":"28003",
    "sg:province":"Madrid",
    "wof:name":"Ramos Gonzalez Sixta",
    "wof:placetype":"venue"
},
  "geometry": {"coordinates":[-3.712884903,40.4406547546],"type":"Point"}
}