{
  "type": "Feature",
  "properties": {
    "iso:country":"ES",
    "sg:address":"Luga Xan Faba-castrobo, 26",
    "sg:city":"Castrobo",
    "sg:orig_category":"Jardiner\u00cdas, Vegetales, Art\u00cdculos De Jardiner\u00cda (al Por Menor)",
    "sg:phone":"+34 981 67 63 40",
    "sg:postcode":"15181",
    "sg:province":"La Coru\u00f1a",
    "wof:name":"Ramos Vaquez Enrique",
    "wof:placetype":"venue"
},
  "geometry": {"coordinates":[-8.3443889618,43.291721344],"type":"Point"}
}