{
  "type": "Feature",
  "properties": {
    "addr:full":"C/ Alfonso Xii, 31 Elche Alicante 03203",
    "addr:housenumber":"31",
    "addr:postcode":"03203",
    "addr:street":"C / Alfonso Xii",
    "iso:country":"ES",
    "sg:address":"C/ Alfonso Xii, 31",
    "sg:city":"Elche",
    "sg:orig_category":"Agencias Y Agentes Comerciales, Representantes",
    "sg:phone":"+34 965 45 17 74",
    "sg:postcode":"03203",
    "sg:province":"Alicante",
    "wof:name":"Bravo Amat Francisco",
    "wof:placetype":"venue"
},
  "geometry": {"coordinates":[-0.6989470124,38.2640380859],"type":"Point"}
}