{
  "type": "Feature",
  "properties": {
    "iso:country":"ES",
    "sg:address":"Calle de Batalla Del Salado, 28",
    "sg:city":"Madrid",
    "sg:orig_category":"Agencias Y Agentes Comerciales, Representantes",
    "sg:phone":"+34 914 67 05 18",
    "sg:postcode":"28045",
    "sg:province":"Madrid",
    "wof:name":"Maza Lara Francisco",
    "wof:placetype":"venue"
},
  "geometry": {"coordinates":[-3.6962304115,40.4004592896],"type":"Point"}
}