{
  "type": "Feature",
  "properties": {
    "addr:full":"Carr Sant Lluis Gonzaga, 15 Villarreal Castell\u00f3n 12540",
    "addr:housenumber":"15",
    "addr:postcode":"12540",
    "addr:street":"Carr Sant Lluis Gonzaga",
    "iso:country":"ES",
    "sg:address":"Carr Sant Lluis Gonzaga, 15",
    "sg:city":"Villarreal",
    "sg:classifiers":[
        {
            "category":"Arts & Performance",
            "subcategory":"Art Gallery",
            "type":"Entertainment"
        }
    ],
    "sg:phone":"+34 964 52 53 42",
    "sg:postcode":"12540",
    "sg:province":"Castell\u00f3n",
    "sg:tags":[
        "arte",
        "de",
        "galer\u00cdas"
    ],
    "wof:name":"Galeria Estudi S.l.",
    "wof:placetype":"venue"
},
  "geometry": {"coordinates":[-0.0989099964,39.9376564026],"type":"Point"}
}