{
  "type": "Feature",
  "properties": {
    "addr:full":"Barr Mendieta, S/n Mendieta Vizcaya 48330",
    "addr:housenumber":"s / n",
    "addr:postcode":"48330",
    "addr:street":"Mendieta",
    "iso:country":"ES",
    "sg:address":"Barr Mendieta, S/n",
    "sg:city":"Mendieta",
    "sg:orig_category":"Metalurgia",
    "sg:phone":"+34 946 31 33 19",
    "sg:postcode":"48330",
    "sg:province":"Vizcaya",
    "wof:name":"Percu S.l.",
    "wof:placetype":"venue"
},
  "geometry": {"coordinates":[-2.7691090107,43.2078361511],"type":"Point"}
}