{
  "type": "Feature",
  "properties": {
    "addr:full":"Pol. Ind. Riambau, 3 Tarrega Lleida 25300",
    "addr:housenumber":"3",
    "addr:postcode":"25300",
    "addr:street":"Riambau",
    "iso:country":"ES",
    "sg:address":"Pol. Ind. Riambau, 3",
    "sg:city":"Tarrega",
    "sg:orig_category":"Instalaci\u00d3n, Reparaci\u00d3n De Ascensores Y Montacargas",
    "sg:phone":"+34 973 50 10 37",
    "sg:postcode":"25300",
    "sg:province":"Lleida",
    "wof:name":"Xip D'or S.l.",
    "wof:placetype":"venue"
},
  "geometry": {"coordinates":[1.144898057,41.6653251648],"type":"Point"}
}