{
  "type": "Feature",
  "properties": {
    "addr:full":"Calle de San Antonio, S/n Villalpardo Cuenca 16270",
    "addr:housenumber":"s / n",
    "addr:postcode":"16270",
    "addr:street":"Calle De San Antonio",
    "iso:country":"ES",
    "sg:address":"Calle de San Antonio, S/n",
    "sg:city":"Villalpardo",
    "sg:orig_category":"Aceites Y Grasas Alimentarias (fabricaci\u00d3n, Al Por Mayor)",
    "sg:phone":"+34 962 31 10 46",
    "sg:postcode":"16270",
    "sg:province":"Cuenca",
    "wof:name":"Cooperativa Del Campo San Antonio De Padua",
    "wof:placetype":"venue"
},
  "geometry": {"coordinates":[-1.6254190207,39.4689331055],"type":"Point"}
}