{
  "type": "Feature",
  "properties": {
    "iso:country":"ES",
    "sg:address":"Calle de San Luis, 9",
    "sg:city":"Montilla",
    "sg:orig_category":"Peluqueros: De Se\u00d1oras",
    "sg:phone":"+34 957 65 29 04",
    "sg:postcode":"14550",
    "sg:province":"C\u00f3rdoba",
    "wof:name":"Dominguez Torres Rafaela",
    "wof:placetype":"venue"
},
  "geometry": {"coordinates":[-4.6366968155,37.589389801],"type":"Point"}
}