{
  "type": "Feature",
  "properties": {
    "iso:country":"ES",
    "sg:address":"Avda General Luxan, 8",
    "sg:city":"Castuera",
    "sg:orig_category":"Ingenier\u00cda, Centros De Estudios (diversos)",
    "sg:phone":"+34 924 76 07 46",
    "sg:postcode":"06420",
    "sg:province":"Badajoz",
    "wof:name":"Lopez Gallego Juan Manuel",
    "wof:placetype":"venue"
},
  "geometry": {"coordinates":[-5.5445752144,38.7262153625],"type":"Point"}
}