{
  "type": "Feature",
  "properties": {
    "addr:full":"Avda Ordesa, 24 Broto Huesca 22370",
    "addr:housenumber":"24",
    "addr:postcode":"22370",
    "addr:street":"Avda Ordesa",
    "iso:country":"ES",
    "sg:address":"Avda Ordesa, 24",
    "sg:city":"Broto",
    "sg:orig_category":"Farmacias",
    "sg:phone":"+34 974 48 61 01",
    "sg:postcode":"22370",
    "sg:province":"Huesca",
    "wof:name":"De Santiago Y Nocito Luis Ignacio",
    "wof:placetype":"venue"
},
  "geometry": {"coordinates":[-0.1227530017,42.6042366028],"type":"Point"}
}