{
  "type": "Feature",
  "properties": {
    "iso:country":"ES",
    "sg:address":"Calle de Faro, 101",
    "sg:city":"Palmas De Gran Canaria",
    "sg:orig_category":"Suministros Para Hoteles",
    "sg:phone":"+34 928 46 60 50",
    "sg:postcode":"35009",
    "sg:province":"Las Palmas",
    "wof:name":"Delgado Delgado Domingo Julio",
    "wof:placetype":"venue"
},
  "geometry": {"coordinates":[-15.4307136536,28.1531734467],"type":"Point"}
}