{
  "type": "Feature",
  "properties": {
    "addr:full":"Carrer de Cervantes, 120 Terrassa Barcelona 08221",
    "addr:housenumber":"120",
    "addr:postcode":"08221",
    "addr:street":"Carrer De Cervantes",
    "iso:country":"ES",
    "sg:address":"Carrer de Cervantes, 120",
    "sg:city":"Terrassa",
    "sg:orig_category":"M\u00c9dicos: An\u00c1lisis Cl\u00cdnicos",
    "sg:phone":"+34 937 80 41 94",
    "sg:postcode":"08221",
    "sg:province":"Barcelona",
    "wof:name":"Bayo Boada Miguel",
    "wof:placetype":"venue"
},
  "geometry": {"coordinates":[2.0073409081,41.5682144165],"type":"Point"}
}