{
  "type": "Feature",
  "properties": {
    "addr:full":"Calle de Julian Romea, 19 S. Gines Murcia 30169",
    "addr:housenumber":"19",
    "addr:postcode":"30169",
    "addr:street":"Calle De Julian Romea;S. Gines",
    "iso:country":"ES",
    "sg:address":"Calle de Julian Romea, 19",
    "sg:city":"S. Gines",
    "sg:orig_category":"Mec\u00c1nico Del Autom\u00d3vil",
    "sg:phone":"+34 968 89 59 25",
    "sg:postcode":"30169",
    "sg:province":"Murcia",
    "wof:name":"Tuning Sport Bernabe S.l.",
    "wof:placetype":"venue"
},
  "geometry": {"coordinates":[-1.1958299875,37.9518737793],"type":"Point"}
}