{
  "type": "Feature",
  "properties": {
    "addr:full":"Carrer de Consell De Cent, 171 Barcelona Barcelona 08015",
    "addr:housenumber":"171",
    "addr:postcode":"08015",
    "addr:street":"Carrer De Consell De Cent",
    "iso:country":"ES",
    "sg:address":"Carrer de Consell De Cent, 171",
    "sg:city":"Barcelona",
    "sg:orig_category":"Promotores Constructores",
    "sg:phone":"+34 934 54 21 72",
    "sg:postcode":"08015",
    "sg:province":"Barcelona",
    "wof:name":"Puig Tapias Jose Maria",
    "wof:placetype":"venue"
},
  "geometry": {"coordinates":[2.155092001,41.3833045959],"type":"Point"}
}