{
  "type": "Feature",
  "properties": {
    "addr:full":"Calle de Hermanos Machado, 11 Pto. Rosario Las Palmas 35600",
    "addr:housenumber":"11",
    "addr:postcode":"35600",
    "addr:street":"Calle De Hermanos Machado;Pto. Rosario Las",
    "iso:country":"ES",
    "sg:address":"Calle de Hermanos Machado, 11",
    "sg:city":"Pto. Rosario",
    "sg:orig_category":"Panader\u00cdas, Panader\u00cdas",
    "sg:phone":"+34 928 53 26 50",
    "sg:postcode":"35600",
    "sg:province":"Las Palmas",
    "wof:name":"Mikes Canasta Del Pan S.l.",
    "wof:placetype":"venue"
},
  "geometry": {"coordinates":[-13.861989975,28.4958896637],"type":"Point"}
}