{
  "type": "Feature",
  "properties": {
    "addr:full":"Rua Nueva, 4 Coru\u00d1a La Coru\u00f1a 15003",
    "addr:housenumber":"4",
    "addr:postcode":"15003",
    "addr:street":"Rua Nueva;La Corun\u0303A",
    "iso:country":"ES",
    "sg:address":"Rua Nueva, 4",
    "sg:city":"Coru\u00d1a",
    "sg:orig_category":"Bisuter\u00cda, Joyer\u00cda, Relojer\u00cda (al Por Menor)",
    "sg:phone":"+34 981 20 38 98",
    "sg:postcode":"15003",
    "sg:province":"La Coru\u00f1a",
    "wof:name":"Mar De La Fuente Y Otro",
    "wof:placetype":"venue"
},
  "geometry": {"coordinates":[-8.4023532867,43.3692131042],"type":"Point"}
}