{
  "type": "Feature",
  "properties": {
    "iso:country":"ES",
    "sg:address":"Calle de Granada, 7",
    "sg:city":"Madrid",
    "sg:orig_category":"Peleter\u00cdas",
    "sg:phone":"+34 914 33 71 04",
    "sg:postcode":"28007",
    "sg:province":"Madrid",
    "wof:name":"Ortega Romero Maria Jose",
    "wof:placetype":"venue"
},
  "geometry": {"coordinates":[-3.6799929142,40.4052505493],"type":"Point"}
}