{
  "type": "Feature",
  "properties": {
    "addr:full":"Carrer de Miguel De Cervantes, 29 Ametlla Mar Tarragona 43860",
    "addr:housenumber":"29",
    "addr:postcode":"43860",
    "addr:street":"Carrer De Miguel De Cervantes",
    "iso:country":"ES",
    "sg:address":"Carrer de Miguel De Cervantes, 29",
    "sg:city":"Ametlla Mar",
    "sg:orig_category":"Fabricaci\u00d3n Y Comercio De M\u00c1quinas",
    "sg:phone":"+34 977 45 64 34",
    "sg:postcode":"43860",
    "sg:province":"Tarragona",
    "wof:name":"Taller Mecanic Fort S.l.",
    "wof:placetype":"venue"
},
  "geometry": {"coordinates":[0.8042749763,40.8854522705],"type":"Point"}
}