{
  "type": "Feature",
  "properties": {
    "addr:full":"Ctra Del Rocio, 206 Almonte Huelva 21730",
    "addr:housenumber":"206",
    "addr:postcode":"21730",
    "addr:street":"Ctra Del Rocio",
    "iso:country":"ES",
    "sg:address":"Ctra Del Rocio, 206",
    "sg:city":"Almonte",
    "sg:orig_category":"Mec\u00c1nico Del Autom\u00d3vil",
    "sg:phone":"+34 959 40 66 22",
    "sg:postcode":"21730",
    "sg:province":"Huelva",
    "wof:name":"Tecnicas Almendros S.l.",
    "wof:placetype":"venue"
},
  "geometry": {"coordinates":[-6.520198822,37.2557907104],"type":"Point"}
}