{
  "type": "Feature",
  "properties": {
    "addr:full":"Rio Huit, 2298 Torrox-costa M\u00e1laga 29793",
    "addr:housenumber":"2298",
    "addr:postcode":"29793",
    "addr:street":"Torrox-Costa Ma\u0301Laga",
    "iso:country":"ES",
    "sg:address":"Rio Huit, 2298",
    "sg:city":"Torrox-costa",
    "sg:orig_category":"Empresas De Carpinter\u00cda De Madera",
    "sg:phone":"+34 952 53 21 98",
    "sg:postcode":"29793",
    "sg:province":"M\u00e1laga",
    "wof:name":"Carpisur Sc",
    "wof:placetype":"venue"
},
  "geometry": {"coordinates":[-3.9633140564,36.7310066223],"type":"Point"}
}