{
  "type": "Feature",
  "properties": {
    "addr:full":"Calle de Alboraya, 26 Valencia Valencia 46010",
    "addr:housenumber":"26",
    "addr:postcode":"46010",
    "addr:street":"Calle De Alboraya",
    "iso:country":"ES",
    "sg:address":"Calle de Alboraya, 26",
    "sg:city":"Valencia",
    "sg:orig_category":"Farmacias",
    "sg:phone":"+34 963 61 03 65",
    "sg:postcode":"46010",
    "sg:province":"Valencia",
    "wof:name":"Farmacia Roig-domingue C.b.",
    "wof:placetype":"venue"
},
  "geometry": {"coordinates":[-0.3706957102,39.4817657471],"type":"Point"}
}