{
  "type": "Feature",
  "properties": {
    "addr:full":"Carrer de Sabadell, 18 Manresa Barcelona 08243",
    "addr:housenumber":"18",
    "addr:postcode":"08243",
    "addr:street":"Carrer De Sabadell",
    "iso:country":"ES",
    "sg:address":"Carrer de Sabadell, 18",
    "sg:city":"Manresa",
    "sg:orig_category":"Mec\u00c1nico Del Autom\u00d3vil",
    "sg:phone":"+34 938 73 60 43",
    "sg:postcode":"08243",
    "sg:province":"Barcelona",
    "wof:name":"Diesel Giralt-mas S.l.",
    "wof:placetype":"venue"
},
  "geometry": {"coordinates":[1.8368730545,41.7301025391],"type":"Point"}
}