{
  "type": "Feature",
  "properties": {
    "iso:country":"ES",
    "sg:address":"Calle de Gimeno Vizarra, 23",
    "sg:city":"Zaragoza",
    "sg:orig_category":"Muebles Y Accesorios Para Cocinas Y Cuartos De Ba\u00d1o (al Por Menor)",
    "sg:phone":"+34 976 37 22 29",
    "sg:postcode":"50007",
    "sg:province":"Zaragoza",
    "wof:name":"Cortes Millan Juan Jesus",
    "wof:placetype":"venue"
},
  "geometry": {"coordinates":[-0.8847209811,41.6286735535],"type":"Point"}
}