{
  "type": "Feature",
  "properties": {
    "addr:full":"Av Gaudi, 14 Barcelona Barcelona 08025",
    "addr:housenumber":"14",
    "addr:postcode":"08025",
    "addr:street":"Av Gaudi",
    "iso:country":"ES",
    "sg:address":"Av Gaudi, 14",
    "sg:city":"Barcelona",
    "sg:orig_category":"Ropa Para Se\u00d1oras (al Por Menor)",
    "sg:phone":"+34 933 47 30 46",
    "sg:postcode":"08025",
    "sg:province":"Barcelona",
    "wof:name":"Prima Textil S.l.",
    "wof:placetype":"venue"
},
  "geometry": {"coordinates":[2.1746790409,41.4054412842],"type":"Point"}
}