{
  "type": "Feature",
  "properties": {
    "addr:full":"Carrer de Esglesia, 20 S. Climent Llobregat Barcelona 08849",
    "addr:housenumber":"20",
    "addr:postcode":"08849",
    "addr:street":"Carrer De Esglesia;S. Climent Llobregat Barcelona",
    "iso:country":"ES",
    "sg:address":"Carrer de Esglesia, 20",
    "sg:city":"S. Climent Llobregat",
    "sg:orig_category":"Museos",
    "sg:phone":"+34 936 58 12 41",
    "sg:postcode":"08849",
    "sg:province":"Barcelona",
    "wof:name":"Parroquia De Sant Climent",
    "wof:placetype":"venue"
},
  "geometry": {"coordinates":[1.9955199957,41.3360137939],"type":"Point"}
}