{
  "type": "Feature",
  "properties": {
    "addr:full":"Carr Lleida, 39 Alpicat Lleida 25110",
    "addr:housenumber":"39",
    "addr:postcode":"25110",
    "addr:street":"Carr Lleida",
    "iso:country":"ES",
    "sg:address":"Carr Lleida, 39",
    "sg:city":"Alpicat",
    "sg:orig_category":"Carnicer\u00cdas, Carnicer\u00cdas",
    "sg:phone":"+34 973 73 61 41",
    "sg:postcode":"25110",
    "sg:province":"Lleida",
    "wof:name":"Roca Goixart Carmen",
    "wof:placetype":"venue"
},
  "geometry": {"coordinates":[0.5558850169,41.6661834717],"type":"Point"}
}