{
  "type": "Feature",
  "properties": {
    "iso:country":"ES",
    "sg:address":"Calle de Doctor Velez, 17",
    "sg:city":"S. Martin Camino",
    "sg:orig_category":"Contenedores (mercanc\u00cdas)",
    "sg:phone":"+34 987 37 89 00",
    "sg:postcode":"24393",
    "sg:province":"Le\u00f3n",
    "wof:name":"Transportes Sanmarle S.l.",
    "wof:placetype":"venue"
},
  "geometry": {"coordinates":[-5.858394146,42.5119247437],"type":"Point"}
}