{
  "type": "Feature",
  "properties": {
    "iso:country":"ES",
    "sg:address":"Calle de Sevilla, 2",
    "sg:city":"S. Fernando",
    "sg:orig_category":"Molduras, Junquillos, Listones Y Molduras Perforadas",
    "sg:phone":"+34 956 59 70 03",
    "sg:postcode":"11100",
    "sg:province":"C\u00e1diz",
    "wof:name":"Mateo Guerrero C.b.",
    "wof:placetype":"venue"
},
  "geometry": {"coordinates":[-6.2075338364,36.4609107971],"type":"Point"}
}