{
  "type": "Feature",
  "properties": {
    "iso:country":"ES",
    "sg:address":"Carrer de Tomas Ortu\u00d1o, 84",
    "sg:city":"Benidorm",
    "sg:orig_category":"Zapatos (al Por Menor)",
    "sg:phone":"+34 965 85 52 93",
    "sg:postcode":"03500",
    "sg:province":"Alicante",
    "wof:name":"Fragoso Rubio Dolores",
    "wof:placetype":"venue"
},
  "geometry": {"coordinates":[-0.1743289977,38.5408058167],"type":"Point"}
}