{
  "type": "Feature",
  "properties": {
    "iso:country":"ES",
    "sg:address":"Avda Carril (del), 38",
    "sg:city":"Archena",
    "sg:orig_category":"Supermercados Y Hipermercados",
    "sg:phone":"+34 968 67 35 61",
    "sg:postcode":"30600",
    "sg:province":"Murcia",
    "wof:name":"Ruiz Navarro Tomas",
    "wof:placetype":"venue"
},
  "geometry": {"coordinates":[-1.2985370159,38.1158599854],"type":"Point"}
}