{
  "type": "Feature",
  "properties": {
    "iso:country":"ES",
    "sg:address":"Avda Ecuador, El, 55",
    "sg:city":"Valencia",
    "sg:orig_category":"Peluqueros: De Se\u00d1oras",
    "sg:phone":"+34 963 48 93 31",
    "sg:postcode":"46025",
    "sg:province":"Valencia",
    "wof:name":"Nava Sanchez Francisca",
    "wof:placetype":"venue"
},
  "geometry": {"coordinates":[-0.3895039856,39.4935340881],"type":"Point"}
}