{
  "type": "Feature",
  "properties": {
    "addr:full":"Calle de Escolta Real, 57 Donostia-san Sebastian Guip\u00f9zcoa 20008",
    "addr:housenumber":"57",
    "addr:postcode":"20008",
    "addr:street":"Calle De Escolta Real",
    "iso:country":"ES",
    "sg:address":"Calle de Escolta Real, 57",
    "sg:city":"Donostia-san Sebastian",
    "sg:orig_category":"Mec\u00c1nico Del Autom\u00d3vil",
    "sg:phone":"+34 943 21 28 33",
    "sg:postcode":"20008",
    "sg:province":"Guip\u00f9zcoa",
    "wof:name":"Talleres Amara (julen Barandika Fernandez Y Otra, C.b.)",
    "wof:placetype":"venue"
},
  "geometry": {"coordinates":[-1.9997099638,43.3109397888],"type":"Point"}
}