{
  "type": "Feature",
  "properties": {
    "addr:full":"Ctra De Castellon, S/n Pe\u00f1iscola Castell\u00f3n 12598",
    "addr:housenumber":"s",
    "addr:postcode":"12598",
    "addr:street":"Ctra De Castellon;/ N Pen\u0303Iscola Castello\u0301N",
    "iso:country":"ES",
    "sg:address":"Ctra De Castellon, S/n",
    "sg:city":"Pe\u00f1iscola",
    "sg:orig_category":"Karting",
    "sg:phone":"+34 964 48 13 39",
    "sg:postcode":"12598",
    "sg:province":"Castell\u00f3n",
    "wof:name":"Evrard  Claude",
    "wof:placetype":"venue"
},
  "geometry": {"coordinates":[-0.0456800014,39.9851417542],"type":"Point"}
}