{
  "type": "Feature",
  "properties": {
    "addr:full":"C/ Nord, 18 Ripollet Barcelona 08291",
    "addr:housenumber":"18",
    "addr:postcode":"08291",
    "addr:street":"C / Nord",
    "iso:country":"ES",
    "sg:address":"C/ Nord, 18",
    "sg:city":"Ripollet",
    "sg:orig_category":"Promotores Constructores",
    "sg:phone":"+34 935 80 62 30",
    "sg:postcode":"08291",
    "sg:province":"Barcelona",
    "wof:name":"Comunidad Propietarios Nord 18-20",
    "wof:placetype":"venue"
},
  "geometry": {"coordinates":[2.155919075,41.5007591248],"type":"Point"}
}