{
  "type": "Feature",
  "properties": {
    "addr:full":"Camino Las Huertas, S/n Almazan Soria 42200",
    "addr:housenumber":"/ n",
    "addr:postcode":"42200",
    "addr:street":"Camino Las Huertas S",
    "iso:country":"ES",
    "sg:address":"Camino Las Huertas, S/n",
    "sg:city":"Almazan",
    "sg:orig_category":"Torrefactado De Caf\u00c9",
    "sg:phone":"+34 975 30 07 54",
    "sg:postcode":"42200",
    "sg:province":"Soria",
    "wof:name":"J.beltran Distribuciones S.l.",
    "wof:placetype":"venue"
},
  "geometry": {"coordinates":[-2.5311539173,41.4859352112],"type":"Point"}
}