{
  "type": "Feature",
  "properties": {
    "iso:country":"ES",
    "sg:address":"Calle de Jose De Echegaray, 8",
    "sg:city":"Merida",
    "sg:orig_category":"Electricidad, Electr\u00d3nica: Suministros (al Por Menor)",
    "sg:phone":"+34 924 30 41 20",
    "sg:postcode":"06800",
    "sg:province":"Badajoz",
    "wof:name":"Guillen Ortiz Leopoldo",
    "wof:placetype":"venue"
},
  "geometry": {"coordinates":[-6.3422570229,38.9129180908],"type":"Point"}
}