{
  "type": "Feature",
  "properties": {
    "iso:country":"ES",
    "sg:address":"Calle de Vicente Aleixandre, 16",
    "sg:city":"Vegas",
    "sg:orig_category":"Florister\u00cdas",
    "sg:phone":"+34 985 51 59 46",
    "sg:postcode":"33404",
    "sg:province":"Asturias",
    "wof:name":"Maria Del Pilar Alvarez De La Riva Y Jose Manuel Arias Rodriguez C.b.",
    "wof:placetype":"venue"
},
  "geometry": {"coordinates":[-5.9240369797,43.5455207825],"type":"Point"}
}