{
  "type": "Feature",
  "properties": {
    "iso:country":"ES",
    "sg:address":"Ctra. Pobladura, S/n",
    "sg:city":"Villabrazaro",
    "sg:orig_category":"Cr\u00cda De Animales",
    "sg:phone":"+34 980 56 30 04",
    "sg:postcode":"49770",
    "sg:province":"Zamora",
    "wof:name":"Navarro Pallares S.l.",
    "wof:placetype":"venue"
},
  "geometry": {"coordinates":[-5.7289009094,42.0528335571],"type":"Point"}
}