{
  "type": "Feature",
  "properties": {
    "iso:country":"ES",
    "sg:address":"Calle de Carpinteros, 18",
    "sg:city":"Almansa",
    "sg:orig_category":"Zapatos: Material, Suministros, Accesorios (fabricaci\u00d3n, Al Por Mayor)",
    "sg:phone":"+34 967 34 44 30",
    "sg:postcode":"02640",
    "sg:province":"Albacete",
    "wof:name":"Tersolex S.a.l.",
    "wof:placetype":"venue"
},
  "geometry": {"coordinates":[-1.1119799614,38.8767929077],"type":"Point"}
}