{
  "type": "Feature",
  "properties": {
    "iso:country":"ES",
    "sg:address":"Luga Laguneta (la), 30",
    "sg:city":"Laguneta",
    "sg:orig_category":"Panader\u00cdas, Panader\u00cdas",
    "sg:phone":"+34 928 84 01 64",
    "sg:postcode":"35560",
    "sg:province":"Las Palmas",
    "wof:name":"Pacheco Mesa Juan Jose",
    "wof:placetype":"venue"
},
  "geometry": {"coordinates":[-13.676823616,29.0662899017],"type":"Point"}
}