{
  "type": "Feature",
  "properties": {
    "addr:full":"Carrer de Major, 43 Montblanc Tarragona 43400",
    "addr:housenumber":"43",
    "addr:postcode":"43400",
    "addr:street":"Carrer De Major",
    "iso:country":"ES",
    "sg:address":"Carrer de Major, 43",
    "sg:city":"Montblanc",
    "sg:orig_category":"Ropa Para Ni\u00d1os (al Por Menor)",
    "sg:phone":"+34 977 86 32 13",
    "sg:postcode":"43400",
    "sg:province":"Tarragona",
    "wof:name":"Farres Torres Maria Montserrat",
    "wof:placetype":"venue"
},
  "geometry": {"coordinates":[1.1620049477,41.3763618469],"type":"Point"}
}