{
  "type": "Feature",
  "properties": {
    "addr:full":"Cami De La Estacio, 11 El Morell Tarragona 43760",
    "addr:housenumber":"11",
    "addr:postcode":"43760",
    "addr:street":"Cami De La Estacio;El Morell",
    "iso:country":"ES",
    "sg:address":"Cami De La Estacio, 11",
    "sg:city":"El Morell",
    "sg:orig_category":"Promotores Constructores",
    "sg:phone":"+34 977 84 16 93",
    "sg:postcode":"43760",
    "sg:province":"Tarragona",
    "wof:name":"Dedicom Instalacions Scp",
    "wof:placetype":"venue"
},
  "geometry": {"coordinates":[1.2078649998,41.1901359558],"type":"Point"}
}