{
  "type": "Feature",
  "properties": {
    "addr:full":"Avda Blas De Otero, 25 Maracena Granada 18200",
    "addr:housenumber":"25",
    "addr:postcode":"18200",
    "addr:street":"Avda Blas De Otero",
    "iso:country":"ES",
    "sg:address":"Avda Blas De Otero, 25",
    "sg:city":"Maracena",
    "sg:orig_category":"Molduras, Junquillos, Listones Y Molduras Perforadas",
    "sg:phone":"+34 958 41 21 10",
    "sg:postcode":"18200",
    "sg:province":"Granada",
    "wof:name":"Romera Martinez Emilio",
    "wof:placetype":"venue"
},
  "geometry": {"coordinates":[-3.6332190037,37.2105712891],"type":"Point"}
}