{
  "type": "Feature",
  "properties": {
    "addr:full":"Calle de Barrau, 1 Sevilla Sevilla 41018",
    "addr:housenumber":"1",
    "addr:postcode":"41018",
    "addr:street":"Calle De Barrau",
    "iso:country":"ES",
    "sg:address":"Calle de Barrau, 1",
    "sg:city":"Sevilla",
    "sg:orig_category":"Agencias Y Agentes Comerciales, Representantes",
    "sg:phone":"+34 954 93 28 35",
    "sg:postcode":"41018",
    "sg:province":"Sevilla",
    "wof:name":"Haro Ramos Antonio",
    "wof:placetype":"venue"
},
  "geometry": {"coordinates":[-5.975467205,37.3828430176],"type":"Point"}
}