{
  "type": "Feature",
  "properties": {
    "addr:full":"Calle de San Vicente, 31 Castellon Castell\u00f3n 12002",
    "addr:housenumber":"31",
    "addr:postcode":"12002",
    "addr:street":"Calle De San Vicente",
    "iso:country":"ES",
    "sg:address":"Calle de San Vicente, 31",
    "sg:city":"Castellon",
    "sg:orig_category":"Ropa Para Ni\u00d1os (al Por Menor)",
    "sg:phone":"+34 964 25 76 88",
    "sg:postcode":"12002",
    "sg:province":"Castell\u00f3n",
    "wof:name":"Burbujas Castellon Cb",
    "wof:placetype":"venue"
},
  "geometry": {"coordinates":[-0.0416969992,39.985660553],"type":"Point"}
}