{
  "type": "Feature",
  "properties": {
    "addr:full":"Avda Orense, 25 Marin Pontevedra 36900",
    "addr:housenumber":"25",
    "addr:postcode":"36900",
    "addr:street":"Avda Orense",
    "iso:country":"ES",
    "sg:address":"Avda Orense, 25",
    "sg:city":"Marin",
    "sg:orig_category":"Construcciones Navales Y Fluviales",
    "sg:phone":"+34 986 88 06 02",
    "sg:postcode":"36900",
    "sg:province":"Pontevedra",
    "wof:name":"Nodosa S.l.",
    "wof:placetype":"venue"
},
  "geometry": {"coordinates":[-8.6914491653,42.398273468],"type":"Point"}
}