{
  "type": "Feature",
  "properties": {
    "addr:full":"Calle de Cervantes, 15 Le\u00f3n Le\u00f3n 24003",
    "addr:housenumber":"15",
    "addr:postcode":"24003",
    "addr:street":"Calle De Cervantes;Leo\u0301N",
    "iso:country":"ES",
    "sg:address":"Calle de Cervantes, 15",
    "sg:city":"Le\u00f3n",
    "sg:classifiers":[
        {
            "category":"Arts & Performance",
            "subcategory":"Art Gallery",
            "type":"Entertainment"
        }
    ],
    "sg:phone":"+34 987 23 28 11",
    "sg:postcode":"24003",
    "sg:province":"Le\u00f3n",
    "sg:tags":[
        "arte",
        "de",
        "galer\u00cdas"
    ],
    "wof:name":"Juarez Perez Jose Manuel",
    "wof:placetype":"venue"
},
  "geometry": {"coordinates":[-5.569413662,42.5993652344],"type":"Point"}
}