{
  "type": "Feature",
  "properties": {
    "addr:full":"Avda Pontevedra, 47 Congostra Pontevedra 36619",
    "addr:housenumber":"47",
    "addr:postcode":"36619",
    "addr:street":"Avda Pontevedra",
    "iso:country":"ES",
    "sg:address":"Avda Pontevedra, 47",
    "sg:city":"Congostra",
    "sg:orig_category":"Distribuci\u00d3n De Petr\u00d3leo Y Derivados",
    "sg:phone":"+34 986 51 00 21",
    "sg:postcode":"36619",
    "sg:province":"Pontevedra",
    "sg:website":"www.cepsa.es",
    "wof:name":"Cedipsa Compa\u00d1ia Espa\u00d1ola Distribuidora De Petroleos S.a.",
    "wof:placetype":"venue"
},
  "geometry": {"coordinates":[-8.7645044327,42.5797958374],"type":"Point"}
}