{
  "type": "Feature",
  "properties": {
    "addr:full":"Av Princep D'asturies, 55 Barcelona Barcelona 08012",
    "addr:housenumber":"55",
    "addr:postcode":"08012",
    "addr:street":"Av Princep D'Asturies",
    "iso:country":"ES",
    "sg:address":"Av Princep D'asturies, 55",
    "sg:city":"Barcelona",
    "sg:orig_category":"Ense\u00d1anza: Profesiones Art\u00cdsticas",
    "sg:phone":"+34 932 17 60 59",
    "sg:postcode":"08012",
    "sg:province":"Barcelona",
    "wof:name":"Verges Amor Marc",
    "wof:placetype":"venue"
},
  "geometry": {"coordinates":[2.1499826908,41.4053382874],"type":"Point"}
}