{
  "type": "Feature",
  "properties": {
    "iso:country":"ES",
    "sg:address":"Calle de Filiberto Villalobos, 70",
    "sg:city":"Guijuelo",
    "sg:orig_category":"Carnicer\u00cdas, Carnicer\u00cdas",
    "sg:phone":"+34 923 58 10 69",
    "sg:postcode":"37770",
    "sg:province":"Salamanca",
    "wof:name":"Hermanos Campos C.b.",
    "wof:placetype":"venue"
},
  "geometry": {"coordinates":[-5.6733989716,40.5556716919],"type":"Point"}
}