{
  "type": "Feature",
  "properties": {
    "iso:country":"ES",
    "sg:address":"Avda Blanca Paloma, 2",
    "sg:city":"Puebla Del Rio",
    "sg:orig_category":"Ense\u00d1anza, Formaci\u00d3n Profesional: Aprendizaje",
    "sg:phone":"+34 955 77 05 50",
    "sg:postcode":"41130",
    "sg:province":"Sevilla",
    "wof:name":"Ayuntamiento De La Puebla Del Rio",
    "wof:placetype":"venue"
},
  "geometry": {"coordinates":[-6.0624775887,37.267250061],"type":"Point"}
}