{
  "type": "Feature",
  "properties": {
    "addr:full":"Calle de Ba\u00d1os Los, 3 Sestao Vizcaya 48910",
    "addr:housenumber":"3",
    "addr:postcode":"48910",
    "addr:street":"Calle De Ban\u0303Os Los",
    "iso:country":"ES",
    "sg:address":"Calle de Ba\u00d1os Los, 3",
    "sg:city":"Sestao",
    "sg:orig_category":"Perfumer\u00cda (al Por Menor)",
    "sg:phone":"+34 944 96 54 73",
    "sg:postcode":"48910",
    "sg:province":"Vizcaya",
    "wof:name":"Aurora Romo Lazcano (perfumeria Amara)",
    "wof:placetype":"venue"
},
  "geometry": {"coordinates":[-3.0049242973,43.3091545105],"type":"Point"}
}