{
  "type": "Feature",
  "properties": {
    "addr:full":"Plaz Guerande (de), 17 Almagro Ciudad Real 13270",
    "addr:postcode":"13270",
    "addr:street":"Plaz",
    "iso:country":"ES",
    "sg:address":"Plaz Guerande (de), 17",
    "sg:city":"Almagro",
    "sg:orig_category":"Relojer\u00cda (al Por Menor, Reparaci\u00d3n)",
    "sg:phone":"+34 926 86 00 50",
    "sg:postcode":"13270",
    "sg:province":"Ciudad Real",
    "wof:name":"Guerra Oliva Jose Ignacio",
    "wof:placetype":"venue"
},
  "geometry": {"coordinates":[-3.7195370197,38.8863601685],"type":"Point"}
}