{
  "type": "Feature",
  "properties": {
    "iso:country":"ES",
    "sg:address":"Plaz Concepcion, S/n",
    "sg:city":"Zuera",
    "sg:orig_category":"Iglesia Cat\u00d3lica",
    "sg:phone":"+34 976 68 00 63",
    "sg:postcode":"50800",
    "sg:province":"Zaragoza",
    "wof:name":"Parroquia De San Pedro Apostol",
    "wof:placetype":"venue"
},
  "geometry": {"coordinates":[-0.7864480019,41.8690681458],"type":"Point"}
}