{
  "type": "Feature",
  "properties": {
    "addr:full":"Calle de Mar (del), 26 Torre Mar M\u00e1laga 29740",
    "addr:housenumber":"26",
    "addr:postcode":"29740",
    "addr:street":"Calle De;Del;Ma\u0301Laga",
    "iso:country":"ES",
    "sg:address":"Calle de Mar (del), 26",
    "sg:city":"Torre Mar",
    "sg:orig_category":"Ropa Para Se\u00d1oras (al Por Menor)",
    "sg:phone":"+34 952 54 74 29",
    "sg:postcode":"29740",
    "sg:province":"M\u00e1laga",
    "wof:name":"Garcia Perez Antonio",
    "wof:placetype":"venue"
},
  "geometry": {"coordinates":[-4.3591089249,36.7191734314],"type":"Point"}
}