{
  "type": "Feature",
  "properties": {
    "iso:country":"ES",
    "sg:address":"Avda Reina Maria Cristina, 14",
    "sg:city":"Candas",
    "sg:orig_category":"Organismos De Reclutamiento",
    "sg:phone":"+34 985 88 50 42",
    "sg:postcode":"33430",
    "sg:province":"Asturias",
    "wof:name":"Bernardo Y Diaz, S.c.",
    "wof:placetype":"venue"
},
  "geometry": {"coordinates":[-5.7674508095,43.590133667],"type":"Point"}
}