{
  "type": "Feature",
  "properties": {
    "iso:country":"ES",
    "sg:address":"Carrer de Sant Vicen\u00c7, 2",
    "sg:city":"Riudoms",
    "sg:orig_category":"Enfermeras: Consultas, Atenci\u00d3n A Domicilio",
    "sg:phone":"+34 977 85 07 23",
    "sg:postcode":"43330",
    "sg:province":"Tarragona",
    "wof:name":"Castillo Moral Antonia",
    "wof:placetype":"venue"
},
  "geometry": {"coordinates":[1.0505839586,41.1364822388],"type":"Point"}
}