{
  "type": "Feature",
  "properties": {
    "iso:country":"ES",
    "sg:address":"Rua Aragon, 20",
    "sg:city":"Vigo",
    "sg:orig_category":"Ense\u00d1anza Secundaria: Colegios Y Escuelas Privadas",
    "sg:phone":"+34 986 27 40 50",
    "sg:postcode":"36206",
    "sg:province":"Pontevedra",
    "wof:name":"Xunta De Galicia-cons.educacion Institut",
    "wof:placetype":"venue"
},
  "geometry": {"coordinates":[-8.7006893158,42.236782074],"type":"Point"}
}