{
  "type": "Feature",
  "properties": {
    "iso:country":"ES",
    "sg:address":"Urdaneta Bidea, 5",
    "sg:city":"Zarautz",
    "sg:orig_category":"Ense\u00d1anza: Turismo, Cocina, Hosteler\u00cda",
    "sg:phone":"+34 943 13 49 68",
    "sg:postcode":"20800",
    "sg:province":"Guip\u00f9zcoa",
    "wof:name":"Academia De Cocina Aiala S.l.",
    "wof:placetype":"venue"
},
  "geometry": {"coordinates":[-2.174066,43.282619],"type":"Point"}
}