{
  "type": "Feature",
  "properties": {
    "addr:full":"Cno Valle, 56 Santaella C\u00f3rdoba 14546",
    "addr:housenumber":"56",
    "addr:postcode":"14546",
    "addr:street":"Cno Valle;Co\u0301Rdoba",
    "iso:country":"ES",
    "sg:address":"Cno Valle, 56",
    "sg:city":"Santaella",
    "sg:orig_category":"Ense\u00d1anza Variada",
    "sg:phone":"+34 957 31 33 02",
    "sg:postcode":"14546",
    "sg:province":"C\u00f3rdoba",
    "wof:name":"Academia Forsan S.l.",
    "wof:placetype":"venue"
},
  "geometry": {"coordinates":[-4.839869976,37.5627708435],"type":"Point"}
}