{
  "type": "Feature",
  "properties": {
    "addr:full":"Rua Presa, 20 Presa Pontevedra 36216",
    "addr:housenumber":"20",
    "addr:postcode":"36216",
    "addr:street":"Rua Presa",
    "iso:country":"ES",
    "sg:address":"Rua Presa, 20",
    "sg:city":"Presa",
    "sg:orig_category":"Tapiceros Y Tapiceros",
    "sg:phone":"+34 986 37 20 07",
    "sg:postcode":"36216",
    "sg:province":"Pontevedra",
    "wof:name":"Soutullo Chaves Miguel",
    "wof:placetype":"venue"
},
  "geometry": {"coordinates":[-8.6428003311,42.4304618835],"type":"Point"}
}