{
  "type": "Feature",
  "properties": {
    "iso:country":"ES",
    "sg:address":"Calle de Pe\u00d1a Gorbea, 17",
    "sg:city":"Madrid",
    "sg:orig_category":"Parques De Atracciones Y Centros De Esparcimiento",
    "sg:phone":"+34 915 01 00 13",
    "sg:postcode":"28053",
    "sg:province":"Madrid",
    "wof:name":"Rank Centro S.a.",
    "wof:placetype":"venue"
},
  "geometry": {"coordinates":[-3.6669540405,40.3957824707],"type":"Point"}
}