{
  "type": "Feature",
  "properties": {
    "addr:full":"Carr Mossen Cinto Verdaguer, 11 Platja D'aro Girona 17250",
    "addr:housenumber":"11",
    "addr:postcode":"17250",
    "addr:street":"Carr Mossen Cinto Verdaguer",
    "iso:country":"ES",
    "sg:address":"Carr Mossen Cinto Verdaguer, 11",
    "sg:city":"Platja D'aro",
    "sg:orig_category":"Librer\u00cdas",
    "sg:phone":"+34 972 82 70 06",
    "sg:postcode":"17250",
    "sg:province":"Girona",
    "wof:name":"Traver Martinez Rosario",
    "wof:placetype":"venue"
},
  "geometry": {"coordinates":[2.8163490295,41.9701499939],"type":"Point"}
}