{
  "type": "Feature",
  "properties": {
    "iso:country":"ES",
    "sg:address":"Isla De La Toja, 10",
    "sg:city":"Valdepastores",
    "sg:orig_category":"Agencias Y Agentes Comerciales, Representantes",
    "sg:phone":"+34 916 32 15 29",
    "sg:postcode":"28660",
    "sg:province":"Madrid",
    "wof:name":"Garcia Jimenez Cesar",
    "wof:placetype":"venue"
},
  "geometry": {"coordinates":[-3.8857300282,40.4309654236],"type":"Point"}
}