{
  "type": "Feature",
  "properties": {
    "iso:country":"ES",
    "sg:address":"Calle de Clara Del Rey, 41",
    "sg:city":"Madrid",
    "sg:orig_category":"Administradores De Bienes Y Delegados De Comunidades De Propietarios",
    "sg:phone":"+34 915 19 00 95",
    "sg:postcode":"28002",
    "sg:province":"Madrid",
    "wof:name":"Matarranz Moro Carmen",
    "wof:placetype":"venue"
},
  "geometry": {"coordinates":[-3.6696536541,40.4428672791],"type":"Point"}
}