{
  "type": "Feature",
  "properties": {
    "addr:full":"Avda Palomeras, 74 Madrid Madrid 28018",
    "addr:housenumber":"74",
    "addr:postcode":"madrid;28018",
    "addr:street":"Avda Palomeras",
    "iso:country":"ES",
    "sg:address":"Avda Palomeras, 74",
    "sg:city":"Madrid",
    "sg:orig_category":"Molduras, Junquillos, Listones Y Molduras Perforadas",
    "sg:phone":"+34 917 78 83 76",
    "sg:postcode":"28018",
    "sg:province":"Madrid",
    "wof:name":"Lebrosan Santos Dioni",
    "wof:placetype":"venue"
},
  "geometry": {"coordinates":[-3.656785965,40.3877334595],"type":"Point"}
}