{
  "type": "Feature",
  "properties": {
    "addr:full":"Avda Ramon Y Cajal, 5 Ayamonte Huelva 21400",
    "addr:housenumber":"5",
    "addr:postcode":"21400",
    "addr:street":"Avda Ramon Y Cajal",
    "iso:country":"ES",
    "sg:address":"Avda Ramon Y Cajal, 5",
    "sg:city":"Ayamonte",
    "sg:orig_category":"Alimentaci\u00d3n General (al Por Menor)",
    "sg:phone":"+34 959 32 01 19",
    "sg:postcode":"21400",
    "sg:province":"Huelva",
    "wof:name":"Alonso Beltran Isabel",
    "wof:placetype":"venue"
},
  "geometry": {"coordinates":[-7.4023222923,37.2131538391],"type":"Point"}
}