{
  "type": "Feature",
  "properties": {
    "addr:full":"Calle de Cervantes, 26 Bola\u00e7os De Calatrava Ciudad Real 13260",
    "addr:housenumber":"26",
    "addr:postcode":"13260",
    "addr:street":"Calle De Cervantes",
    "iso:country":"ES",
    "sg:address":"Calle de Cervantes, 26",
    "sg:city":"Bola\u00e7os De Calatrava",
    "sg:orig_category":"M\u00c9dicos: Estomatolog\u00cda",
    "sg:phone":"+34 926 88 43 95",
    "sg:postcode":"13260",
    "sg:province":"Ciudad Real",
    "wof:name":"Fernandez De Toro Jesus",
    "wof:placetype":"venue"
},
  "geometry": {"coordinates":[-3.9272627831,38.9860954285],"type":"Point"}
}