{
  "type": "Feature",
  "properties": {
    "addr:full":"Calle de Italia, 6 Ciudad Real Ciudad Real 13005",
    "addr:housenumber":"6",
    "addr:postcode":"13005",
    "addr:street":"Calle De Italia",
    "iso:country":"ES",
    "sg:address":"Calle de Italia, 6",
    "sg:city":"Ciudad Real",
    "sg:orig_category":"Detectives, Agentes Investigadores Privados",
    "sg:phone":"+34 926 23 15 59",
    "sg:postcode":"13005",
    "sg:province":"Ciudad Real",
    "wof:name":"Lopez Arenas Jose Luis",
    "wof:placetype":"venue"
},
  "geometry": {"coordinates":[-3.9133789539,38.9809494019],"type":"Point"}
}