{
  "type": "Feature",
  "properties": {
    "addr:full":"Pg Sant Joan, 157 Barcelona Barcelona 08037",
    "addr:housenumber":"157",
    "addr:postcode":"08037",
    "addr:street":"Pg Sant Joan",
    "iso:country":"ES",
    "sg:address":"Pg Sant Joan, 157",
    "sg:city":"Barcelona",
    "sg:orig_category":"Institutos De Belleza",
    "sg:phone":"+34 934 59 15 10",
    "sg:postcode":"08037",
    "sg:province":"Barcelona",
    "wof:name":"Meler Faiget Maria Teresa",
    "wof:placetype":"venue"
},
  "geometry": {"coordinates":[2.1655480862,41.4020500183],"type":"Point"}
}