{
  "type": "Feature",
  "properties": {
    "addr:full":"Carrer de Ferlandina, 57 Barcelona Barcelona 08001",
    "addr:housenumber":"57",
    "addr:postcode":"08001",
    "addr:street":"Carrer De Ferlandina",
    "iso:country":"ES",
    "sg:address":"Carrer de Ferlandina, 57",
    "sg:city":"Barcelona",
    "sg:orig_category":"Radiocomunicaciones, Telefon\u00cda M\u00d3vil, Radiomensajer\u00cda: Servicios, Comercializaci\u00d3n",
    "sg:phone":"+34 933 29 06 57",
    "sg:postcode":"08001",
    "sg:province":"Barcelona",
    "wof:name":"Chianwali Sct",
    "wof:placetype":"venue"
},
  "geometry": {"coordinates":[2.1649289131,41.381603241],"type":"Point"}
}