{
  "type": "Feature",
  "properties": {
    "iso:country":"ES",
    "sg:address":"Carr Raval, 17",
    "sg:city":"Blanes",
    "sg:orig_category":"Ropa Para Se\u00d1oras Y Caballeros (al Por Menor)",
    "sg:phone":"+34 972 35 29 95",
    "sg:postcode":"17300",
    "sg:province":"Girona",
    "wof:name":"Ramani S.a.",
    "wof:placetype":"venue"
},
  "geometry": {"coordinates":[2.7922790051,41.676109314],"type":"Point"}
}