{
  "type": "Feature",
  "properties": {
    "addr:full":"Calle de Simon Ortiz, 4 Valencia Valencia 46008",
    "addr:housenumber":"4",
    "addr:postcode":"46008",
    "addr:street":"Calle De Simon Ortiz",
    "iso:country":"ES",
    "sg:address":"Calle de Simon Ortiz, 4",
    "sg:city":"Valencia",
    "sg:orig_category":"Alimentaci\u00d3n General (al Por Menor)",
    "sg:phone":"+34 963 91 12 43",
    "sg:postcode":"46008",
    "sg:province":"Valencia",
    "wof:name":"Salcedo Ruiz Vicente",
    "wof:placetype":"venue"
},
  "geometry": {"coordinates":[-0.3861170113,39.4729614258],"type":"Point"}
}