{
  "type": "Feature",
  "properties": {
    "addr:full":"Carr Estrella, 7 Felanitx Islas Baleares 07200",
    "addr:housenumber":"7",
    "addr:postcode":"07200",
    "addr:street":"Carr Estrella",
    "iso:country":"ES",
    "sg:address":"Carr Estrella, 7",
    "sg:city":"Felanitx",
    "sg:orig_category":"Contenedores (mercanc\u00cdas)",
    "sg:phone":"+34 971 58 29 95",
    "sg:postcode":"07200",
    "sg:province":"Islas Baleares",
    "wof:name":"Transcarti S.l.",
    "wof:placetype":"venue"
},
  "geometry": {"coordinates":[3.1523449421,39.4752311707],"type":"Point"}
}