{
  "type": "Feature",
  "properties": {
    "iso:country":"ES",
    "sg:address":"Carrer de Tomas Ortu\u00d1o, 8",
    "sg:city":"Benidorm",
    "sg:orig_category":"Art\u00cdculos De Regalo (al Por Menor)",
    "sg:phone":"+34 965 85 03 48",
    "sg:postcode":"03500",
    "sg:province":"Alicante",
    "wof:name":"Euromil Cb.",
    "wof:placetype":"venue"
},
  "geometry": {"coordinates":[-0.1743289977,38.5408058167],"type":"Point"}
}