{
  "type": "Feature",
  "properties": {
    "addr:full":"Avda Virgen De La Palma, S/n Algeciras C\u00e1diz 11203",
    "addr:housenumber":"s / n;ca\u0301diz",
    "addr:postcode":"11203",
    "addr:street":"Avda Virgen De La Palma",
    "iso:country":"ES",
    "sg:address":"Avda Virgen De La Palma, S/n",
    "sg:city":"Algeciras",
    "sg:orig_category":"Asesor\u00cdas",
    "sg:phone":"+34 956 65 24 20",
    "sg:postcode":"11203",
    "sg:province":"C\u00e1diz",
    "sg:website":"www.diga33.es",
    "wof:name":"Alta Gestion De La Salud Laboral S.l.",
    "wof:placetype":"venue"
},
  "geometry": {"coordinates":[-5.458589077,36.1356391907],"type":"Point"}
}