{
  "type": "Feature",
  "properties": {
    "iso:country":"ES",
    "sg:address":"Avda Murcia, 22",
    "sg:city":"Alcantarilla",
    "sg:orig_category":"Electricidad: Instaladores",
    "sg:phone":"+34 968 89 47 57",
    "sg:postcode":"30820",
    "sg:province":"Murcia",
    "wof:name":"Elecviza S.l.",
    "wof:placetype":"venue"
},
  "geometry": {"coordinates":[-1.2051229477,37.9732666016],"type":"Point"}
}