{
  "type": "Feature",
  "properties": {
    "addr:full":"El Esquilo, S/n Castropol Asturias 33760",
    "addr:housenumber":"s / n",
    "addr:postcode":"33760",
    "iso:country":"ES",
    "sg:address":"El Esquilo, S/n",
    "sg:city":"Castropol",
    "sg:orig_category":"Armas Y Municiones (fabricaci\u00d3n, Al Por Mayor)",
    "sg:phone":"+34 985 63 50 34",
    "sg:postcode":"33760",
    "sg:province":"Asturias",
    "wof:name":"Armeria Valea C.b.",
    "wof:placetype":"venue"
},
  "geometry": {"coordinates":[-7.0048246384,43.5288276672],"type":"Point"}
}