{
  "type": "Feature",
  "properties": {
    "iso:country":"ES",
    "sg:address":"Carrer de Joan Guell, 153",
    "sg:city":"Barcelona",
    "sg:classifiers":[
        {
            "category":"Autos & Motor Vehicles",
            "subcategory":"Automobile Sales",
            "type":"Retail Goods"
        }
    ],
    "sg:phone":"+34 933 30 32 50",
    "sg:postcode":"08028",
    "sg:province":"Barcelona",
    "wof:name":"Sociedad Cooperativa Limitada De Trabajadores De Autoescuela",
    "wof:placetype":"venue"
},
  "geometry": {"coordinates":[2.1314060688,41.3827323914],"type":"Point"}
}