{
  "type": "Feature",
  "properties": {
    "addr:full":"Calle de Padre Castrillon, 23 Barbate C\u00e1diz 11160",
    "addr:housenumber":"23",
    "addr:postcode":"11160",
    "addr:street":"Calle De Padre Castrillon",
    "iso:country":"ES",
    "sg:address":"Calle de Padre Castrillon, 23",
    "sg:city":"Barbate",
    "sg:orig_category":"Arquitectos",
    "sg:phone":"+34 956 43 22 17",
    "sg:postcode":"11160",
    "sg:province":"C\u00e1diz",
    "wof:name":"Rivera Pareja Manuel",
    "wof:placetype":"venue"
},
  "geometry": {"coordinates":[-5.9171910286,36.1902809143],"type":"Point"}
}