{
  "type": "Feature",
  "properties": {
    "iso:country":"ES",
    "sg:address":"C/ D'allemand, 37",
    "sg:city":"Sant Lluis",
    "sg:orig_category":"Bisuteros (fabricaci\u00d3n, Al Por Mayor)",
    "sg:phone":"+34 971 15 17 47",
    "sg:postcode":"07710",
    "sg:province":"Islas Baleares",
    "wof:name":"Artesanal Menorquina S.a.",
    "wof:placetype":"venue"
},
  "geometry": {"coordinates":[4.2384619713,39.8372612],"type":"Point"}
}