{
  "type": "Feature",
  "properties": {
    "iso:country":"ES",
    "sg:address":"Avda Escandinavia, 23",
    "sg:city":"Gran Alacant",
    "sg:orig_category":"Administradores De Bienes Y Delegados De Comunidades De Propietarios",
    "sg:phone":"+34 966 69 91 29",
    "sg:postcode":"03130",
    "sg:province":"Alicante",
    "wof:name":"Administracion De Fincas Gran Alacant S.l.",
    "wof:placetype":"venue"
},
  "geometry": {"coordinates":[-0.5257930756,38.2289390564],"type":"Point"}
}