{
  "type": "Feature",
  "properties": {
    "iso:country":"ES",
    "sg:address":"Calle de Virgen De Lourdes, 36",
    "sg:city":"Madrid",
    "sg:orig_category":"Promotores Constructores",
    "sg:phone":"+34 913 26 07 15",
    "sg:postcode":"28027",
    "sg:province":"Madrid",
    "wof:name":"Moreno Esteban Hector",
    "wof:placetype":"venue"
},
  "geometry": {"coordinates":[-3.6561939716,40.4357032776],"type":"Point"}
}