{
  "type": "Feature",
  "properties": {
    "iso:country":"ES",
    "sg:address":"Carrer de Angel Guimera, 138",
    "sg:city":"Esplugues Llobregat",
    "sg:orig_category":"Notarios",
    "sg:phone":"+34 933 72 62 61",
    "sg:postcode":"08950",
    "sg:province":"Barcelona",
    "wof:name":"Galdon-rodriguez S.c.p.",
    "wof:placetype":"venue"
},
  "geometry": {"coordinates":[2.0794739723,41.3750495911],"type":"Point"}
}