{
  "type": "Feature",
  "properties": {
    "iso:country":"ES",
    "sg:address":"Calle de Mu\u00d1oz Vazquez, S/n",
    "sg:city":"Arcos Frontera",
    "sg:orig_category":"Molduras, Junquillos, Listones Y Molduras Perforadas",
    "sg:phone":"+34 956 70 06 68",
    "sg:postcode":"11630",
    "sg:province":"C\u00e1diz",
    "wof:name":"Gil Garrucho Francisco",
    "wof:placetype":"venue"
},
  "geometry": {"coordinates":[-5.8145241737,36.7509918213],"type":"Point"}
}