{
  "type": "Feature",
  "properties": {
    "addr:full":"Carrer de Santa Agnes, 6 Cardedeu Barcelona 08440",
    "addr:housenumber":"6",
    "addr:postcode":"08440",
    "addr:street":"Carrer De Santa Agnes",
    "iso:country":"ES",
    "sg:address":"Carrer de Santa Agnes, 6",
    "sg:city":"Cardedeu",
    "sg:orig_category":"Impresiones Sobre Tela",
    "sg:phone":"+34 938 45 49 78",
    "sg:postcode":"08440",
    "sg:province":"Barcelona",
    "wof:name":"Estampados Sanmar S.l.",
    "wof:placetype":"venue"
},
  "geometry": {"coordinates":[2.3608849049,41.6244735718],"type":"Point"}
}