{
  "type": "Feature",
  "properties": {
    "iso:country":"ES",
    "sg:address":"Carolina Coronado, 14",
    "sg:city":"Parla",
    "sg:orig_category":"Carnicer\u00cdas, Carnicer\u00cdas",
    "sg:phone":"+34 916 98 65 27",
    "sg:postcode":"28980",
    "sg:province":"Madrid",
    "wof:name":"Carnicerias Alonso Hermanos S.l.",
    "wof:placetype":"venue"
},
  "geometry": {"coordinates":[-3.769824028,40.237121582],"type":"Point"}
}