{
  "type": "Feature",
  "properties": {
    "iso:country":"ES",
    "sg:address":"Cmno Coin, 39",
    "sg:city":"Fuengirola",
    "sg:orig_category":"Bricolaje, Herramientas (al Por Menor)",
    "sg:phone":"+34 952 46 21 86",
    "sg:postcode":"29640",
    "sg:province":"M\u00e1laga",
    "wof:name":"Fabricados Guerrero S.l.",
    "wof:placetype":"venue"
},
  "geometry": {"coordinates":[-4.6330537796,36.5426368713],"type":"Point"}
}