{
  "type": "Feature",
  "properties": {
    "iso:country":"ES",
    "sg:address":"Cra Piera, 35",
    "sg:city":"Martorell",
    "sg:orig_category":"Mec\u00c1nico Del Autom\u00d3vil",
    "sg:phone":"+34 937 75 58 55",
    "sg:postcode":"08760",
    "sg:province":"Barcelona",
    "wof:name":"Kits",
    "wof:placetype":"venue"
},
  "geometry": {"coordinates":[1.9265979528,41.474105835],"type":"Point"}
}