{
  "type": "Feature",
  "properties": {
    "addr:full":"Calle de San Gerardo, 37 Madrid Madrid 28035",
    "addr:housenumber":"37",
    "addr:postcode":"madrid;28035",
    "addr:street":"Calle De San Gerardo",
    "iso:country":"ES",
    "sg:address":"Calle de San Gerardo, 37",
    "sg:city":"Madrid",
    "sg:orig_category":"Laboratorios Farmac\u00c9uticos",
    "sg:phone":"+34 913 16 35 91",
    "sg:postcode":"28035",
    "sg:province":"Madrid",
    "wof:name":"Vicente Gonzalez Jose De",
    "wof:placetype":"venue"
},
  "geometry": {"coordinates":[-3.7236189842,40.4689064026],"type":"Point"}
}