{
  "type": "Feature",
  "properties": {
    "iso:country":"ES",
    "sg:address":"Avda. Arteixo, 73",
    "sg:city":"A Coru\u00f1a",
    "sg:orig_category":"Agencias Y Agentes Comerciales, Representantes",
    "sg:phone":"+34 981 24 35 30",
    "sg:postcode":"15007",
    "sg:province":"La Coru\u00f1a",
    "wof:name":"Barbeito Sanchez Jose Ramon",
    "wof:placetype":"venue"
},
  "geometry": {"coordinates":[-8.4124202728,43.3576965332],"type":"Point"}
}