{
  "type": "Feature",
  "properties": {
    "iso:country":"ES",
    "sg:address":"Calle de Mijail Gorbachov, 1",
    "sg:city":"Dos Hermanas",
    "sg:orig_category":"Supermercados Y Hipermercados",
    "sg:phone":"+34 955 67 92 47",
    "sg:postcode":"41700",
    "sg:province":"Sevilla",
    "wof:name":"Supermercados Codi S.l.",
    "wof:placetype":"venue"
},
  "geometry": {"coordinates":[-5.9105129242,37.2852287292],"type":"Point"}
}