{
  "type": "Feature",
  "properties": {
    "addr:full":"Calle de Jose Roman Marti, 28 Torres Cotillas Murcia 30565",
    "addr:housenumber":"28",
    "addr:postcode":"30565",
    "addr:street":"Calle De Jose Roman Marti",
    "iso:country":"ES",
    "sg:address":"Calle de Jose Roman Marti, 28",
    "sg:city":"Torres Cotillas",
    "sg:orig_category":"Muebles Y Accesorios Para Cocinas Y Cuartos De Ba\u00d1o (al Por Menor)",
    "sg:phone":"+34 968 62 67 36",
    "sg:postcode":"30565",
    "sg:province":"Murcia",
    "wof:name":"Morell Sandoval Joaquin",
    "wof:placetype":"venue"
},
  "geometry": {"coordinates":[-1.242732048,38.0227279663],"type":"Point"}
}