{
  "type": "Feature",
  "properties": {
    "addr:full":"Carrer de Joan Maragall, 1 S. Just Desvern Barcelona 08960",
    "addr:housenumber":"1",
    "addr:postcode":"08960",
    "addr:street":"Carrer De Joan Maragall",
    "iso:country":"ES",
    "sg:address":"Carrer de Joan Maragall, 1",
    "sg:city":"S. Just Desvern",
    "sg:orig_category":"Muebles, Minoristas",
    "sg:phone":"+34 933 71 14 86",
    "sg:postcode":"08960",
    "sg:province":"Barcelona",
    "wof:name":"Catalan Homedes Juan",
    "wof:placetype":"venue"
},
  "geometry": {"coordinates":[2.0810599327,41.3819198608],"type":"Point"}
}