{
  "type": "Feature",
  "properties": {
    "iso:country":"ES",
    "sg:address":"Azkarruntz Auzoa, 22",
    "sg:city":"Bergara",
    "sg:orig_category":"Fijaciones Industriales",
    "sg:phone":"+34 943 76 16 46",
    "sg:postcode":"20570",
    "sg:province":"Guip\u00f9zcoa",
    "wof:name":"Estampaciones Torber S.l.",
    "wof:placetype":"venue"
},
  "geometry": {"coordinates":[-2.4298410416,43.1015281677],"type":"Point"}
}