{
  "type": "Feature",
  "properties": {
    "iso:country":"ES",
    "sg:address":"Poli Poligon 2, S/n",
    "sg:city":"Manacor",
    "sg:orig_category":"Cooperativas Agr\u00cdcolas",
    "sg:phone":"+34 971 55 23 41",
    "sg:postcode":"07500",
    "sg:province":"Islas Baleares",
    "wof:name":"S.a.t. Sa Cova",
    "wof:placetype":"venue"
},
  "geometry": {"coordinates":[3.2279529572,39.564037323],"type":"Point"}
}