{
  "type": "Feature",
  "properties": {
    "addr:full":"Calle de Levante, 4 Cadiz C\u00e1diz 11007",
    "addr:housenumber":"4",
    "addr:postcode":"11007",
    "addr:street":"Calle De Levante",
    "iso:country":"ES",
    "sg:address":"Calle de Levante, 4",
    "sg:city":"Cadiz",
    "sg:orig_category":"Internados & Ense\u00d1anza Privada",
    "sg:phone":"+34 956 25 04 20",
    "sg:postcode":"11007",
    "sg:province":"C\u00e1diz",
    "wof:name":"Escuelas Profesionales Sagrada Familia",
    "wof:placetype":"venue"
},
  "geometry": {"coordinates":[-6.2775878906,36.5201072693],"type":"Point"}
}