{
  "type": "Feature",
  "properties": {
    "iso:country":"ES",
    "sg:address":"Avda Lirios (de Los), 18",
    "sg:city":"Villa Rio",
    "sg:orig_category":"Art\u00cdculos De Decoraci\u00d3n",
    "sg:phone":"+34 957 17 68 29",
    "sg:postcode":"14640",
    "sg:province":"C\u00f3rdoba",
    "wof:name":"Gamiz Navarro Marta",
    "wof:placetype":"venue"
},
  "geometry": {"coordinates":[-4.2846040726,37.9836082458],"type":"Point"}
}