{
  "type": "Feature",
  "properties": {
    "iso:country":"ES",
    "sg:address":"A Gandara, 144",
    "sg:city":"Mos",
    "sg:orig_category":"Farmacias",
    "sg:phone":"+34 986 33 60 13",
    "sg:postcode":"36415",
    "sg:province":"Pontevedra",
    "wof:name":"Lorenzo Outom Carlos",
    "wof:placetype":"venue"
},
  "geometry": {"coordinates":[-8.5992593765,42.1983985901],"type":"Point"}
}