{
  "type": "Feature",
  "properties": {
    "addr:full":"Calle de Arroyo De Las Pilillas, 22 Madrid Madrid 28030",
    "addr:housenumber":"22",
    "addr:postcode":"madrid;28030",
    "addr:street":"Calle De Arroyo De Las Pilillas",
    "iso:country":"ES",
    "sg:address":"Calle de Arroyo De Las Pilillas, 22",
    "sg:city":"Madrid",
    "sg:orig_category":"Carnicer\u00cdas, Carnicer\u00cdas",
    "sg:phone":"+34 914 30 80 12",
    "sg:postcode":"28030",
    "sg:province":"Madrid",
    "wof:name":"Granizo Granizo Vicente",
    "wof:placetype":"venue"
},
  "geometry": {"coordinates":[-3.650472641,40.4081840515],"type":"Point"}
}