{
  "type": "Feature",
  "properties": {
    "iso:country":"ES",
    "sg:address":"Calle de Colon, 20",
    "sg:city":"Le\u00f3n",
    "sg:orig_category":"Asesor\u00cda Fiscal Y Jur\u00cddica",
    "sg:phone":"+34 987 24 59 20",
    "sg:postcode":"24001",
    "sg:province":"Le\u00f3n",
    "wof:name":"Santiago Chamorro C.b.",
    "wof:placetype":"venue"
},
  "geometry": {"coordinates":[-5.5788888931,42.5994529724],"type":"Point"}
}