{
  "type": "Feature",
  "properties": {
    "iso:country":"ES",
    "sg:address":"Trav Dalt, 29",
    "sg:city":"Barcelona",
    "sg:orig_category":"Asesor\u00cda De Comercio Exterior",
    "sg:phone":"+34 932 10 07 43",
    "sg:postcode":"08024",
    "sg:province":"Barcelona",
    "wof:name":"Euroasia Inter-trading, S.l.",
    "wof:placetype":"venue"
},
  "geometry": {"coordinates":[2.1524989605,41.4087562561],"type":"Point"}
}