{
  "type": "Feature",
  "properties": {
    "addr:full":"Calle de Puerto De Las Pilas, 25 Madrid Madrid 28031",
    "addr:housenumber":"25",
    "addr:postcode":"madrid;28031",
    "addr:street":"Calle De Puerto De Las Pilas",
    "iso:country":"ES",
    "sg:address":"Calle de Puerto De Las Pilas, 25",
    "sg:city":"Madrid",
    "sg:orig_category":"Aluminio Y Aleaciones (producci\u00d3n, Transformaci\u00d3n, Negocio)",
    "sg:phone":"+34 913 03 52 39",
    "sg:postcode":"28031",
    "sg:province":"Madrid",
    "wof:name":"Martin De La Fuente Miguel",
    "wof:placetype":"venue"
},
  "geometry": {"coordinates":[-3.6254498959,40.377872467],"type":"Point"}
}