{
  "type": "Feature",
  "properties": {
    "iso:country":"ES",
    "sg:address":"Calle de Carmen, 5",
    "sg:city":"Cabezo Torres",
    "sg:orig_category":"\u00d3ptica: Instrumentos (fabricaci\u00d3n)",
    "sg:phone":"+34 968 30 81 64",
    "sg:postcode":"30110",
    "sg:province":"Murcia",
    "wof:name":"Antonio Ponce Y Josefa Cano C.b.",
    "wof:placetype":"venue"
},
  "geometry": {"coordinates":[-1.123664856,38.0242271423],"type":"Point"}
}