{
  "type": "Feature",
  "properties": {
    "iso:country":"ES",
    "sg:address":"Calle de Catalina Suarez, 6",
    "sg:city":"Madrid",
    "sg:orig_category":"Arquitectos",
    "sg:phone":"+34 915 51 88 43",
    "sg:postcode":"28007",
    "sg:province":"Madrid",
    "wof:name":"Alcalde Ruiz Concepcion",
    "wof:placetype":"venue"
},
  "geometry": {"coordinates":[-3.6725037098,40.4004020691],"type":"Point"}
}