{
  "type": "Feature",
  "properties": {
    "addr:full":"Afores, S/n Roda De Bara Tarragona 43883",
    "addr:housenumber":"s / n",
    "addr:postcode":"43883",
    "addr:street":"Afores",
    "iso:country":"ES",
    "sg:address":"Afores, S/n",
    "sg:city":"Roda De Bara",
    "sg:orig_category":"Asilos De Ancianos. Centros Privados",
    "sg:phone":"+34 977 65 75 42",
    "sg:postcode":"43883",
    "sg:province":"Tarragona",
    "wof:name":"Comadengall S.a.",
    "wof:placetype":"venue"
},
  "geometry": {"coordinates":[1.4600640535,41.1879272461],"type":"Point"}
}