{
  "type": "Feature",
  "properties": {
    "addr:full":"Calle de Antonio Maria Manrique, 3 Palmas De Gran Canaria Las Palmas 35011",
    "addr:housenumber":"3",
    "addr:postcode":"35011",
    "addr:street":"Calle De Antonio Maria Manrique",
    "iso:country":"ES",
    "sg:address":"Calle de Antonio Maria Manrique, 3",
    "sg:city":"Palmas De Gran Canaria",
    "sg:orig_category":"Asesor\u00cda Sobre Comunicaci\u00d3n De Empresas",
    "sg:phone":"+34 928 29 99 42",
    "sg:postcode":"35011",
    "sg:province":"Las Palmas",
    "wof:name":"Insiste 21 S.l.",
    "wof:placetype":"venue"
},
  "geometry": {"coordinates":[-15.4372320175,28.1257038116],"type":"Point"}
}