{
  "type": "Feature",
  "properties": {
    "iso:country":"ES",
    "sg:address":"Calle de Mercurio, 14",
    "sg:city":"Madrid",
    "sg:orig_category":"Lencer\u00cda Femenina, Corseter\u00cda, Trajes De Ba\u00d1o (al Por Menor)",
    "sg:phone":"+34 913 71 86 30",
    "sg:postcode":"28032",
    "sg:province":"Madrid",
    "wof:name":"Perez Noales Maria Soledad",
    "wof:placetype":"venue"
},
  "geometry": {"coordinates":[-3.6065831184,40.4052391052],"type":"Point"}
}