{
  "type": "Feature",
  "properties": {
    "iso:country":"ES",
    "sg:address":"Calle de Manuel Bartolome Cossio, 10",
    "sg:city":"Madrid",
    "sg:orig_category":"M\u00c9dicos: Medicina Nuclear",
    "sg:phone":"+34 915 34 48 96",
    "sg:postcode":"28040",
    "sg:province":"Madrid",
    "wof:name":"Centro Pet Complutense S.a.",
    "wof:placetype":"venue"
},
  "geometry": {"coordinates":[-3.7201859951,40.4391326904],"type":"Point"}
}