{
  "type": "Feature",
  "properties": {
    "addr:full":"Rua Reboredo, 56 Monforte De Lemos Lugo 27400",
    "addr:housenumber":"56",
    "addr:postcode":"27400",
    "addr:street":"Rua Reboredo",
    "iso:country":"ES",
    "sg:address":"Rua Reboredo, 56",
    "sg:city":"Monforte De Lemos",
    "sg:orig_category":"Carnicer\u00cdas, Carnicer\u00cdas",
    "sg:phone":"+34 982 40 08 69",
    "sg:postcode":"27400",
    "sg:province":"Lugo",
    "wof:name":"Prieto Cabo Manuel",
    "wof:placetype":"venue"
},
  "geometry": {"coordinates":[-7.5179672241,42.5135993958],"type":"Point"}
}