{
  "type": "Feature",
  "properties": {
    "iso:country":"ES",
    "sg:address":"Calle de Zaragoza, 1",
    "sg:city":"San Fernando De Henares",
    "sg:orig_category":"Farmacias",
    "sg:phone":"+34 916 73 53 83",
    "sg:postcode":"28830",
    "sg:province":"Madrid",
    "wof:name":"Menargez Florenciano Francisco",
    "wof:placetype":"venue"
},
  "geometry": {"coordinates":[-3.5336709023,40.4290466309],"type":"Point"}
}