{
  "type": "Feature",
  "properties": {
    "addr:full":"Alza, 8 Ribadeo Lugo 27700",
    "addr:housenumber":"8",
    "addr:postcode":"27700",
    "addr:street":"Alza",
    "iso:country":"ES",
    "sg:address":"Alza, 8",
    "sg:city":"Ribadeo",
    "sg:orig_category":"Agencias De Prensa E Informaci\u00d3n",
    "sg:phone":"+34 982 12 83 11",
    "sg:postcode":"27700",
    "sg:province":"Lugo",
    "wof:name":"La Voz De Galicia",
    "wof:placetype":"venue"
},
  "geometry": {"coordinates":[-7.0423488617,43.5343093872],"type":"Point"}
}