{
  "type": "Feature",
  "properties": {
    "addr:full":"Pase Castellana, 194 Madrid Madrid 28046",
    "addr:housenumber":"194",
    "addr:postcode":"28046",
    "addr:street":"Castellana",
    "iso:country":"ES",
    "sg:address":"Pase Castellana, 194",
    "sg:city":"Madrid",
    "sg:orig_category":"Inform\u00c1tica (estudios, Servicios, Asesor\u00cda, Formaci\u00d3n)",
    "sg:phone":"+34 917 03 03 00",
    "sg:postcode":"28046",
    "sg:province":"Madrid",
    "wof:name":"Allegro Systems International S.l.",
    "wof:placetype":"venue"
},
  "geometry": {"coordinates":[-3.6892263889,40.4615364075],"type":"Point"}
}