{
  "type": "Feature",
  "properties": {
    "iso:country":"ES",
    "sg:address":"Calle de Ramon Y Cajal, 6",
    "sg:city":"Novallas",
    "sg:orig_category":"Asociaciones Ecologistas",
    "sg:phone":"+34 976 19 84 47",
    "sg:postcode":"50510",
    "sg:province":"Zaragoza",
    "wof:name":"Comunidad De Regantes San Marcial",
    "wof:placetype":"venue"
},
  "geometry": {"coordinates":[-1.6937589645,41.9473114014],"type":"Point"}
}