{
  "type": "Feature",
  "properties": {
    "addr:full":"Calle de Diego Velazquez, 5 Fraga Huesca 22520",
    "addr:housenumber":"5",
    "addr:postcode":"22520",
    "addr:street":"Calle De Diego Velazquez",
    "iso:country":"ES",
    "sg:address":"Calle de Diego Velazquez, 5",
    "sg:city":"Fraga",
    "sg:orig_category":"Papeler\u00cdas, Librer\u00cdas",
    "sg:phone":"+34 974 47 35 79",
    "sg:postcode":"22520",
    "sg:province":"Huesca",
    "sg:website":"www.carlin.es",
    "wof:name":"Carlin Fraga S.l.",
    "wof:placetype":"venue"
},
  "geometry": {"coordinates":[0.3390156925,41.5237197876],"type":"Point"}
}