{
  "type": "Feature",
  "properties": {
    "addr:full":"Calle de Ramon Esteban (de), 32 San Sebastian De Los Reyes Madrid 28700",
    "addr:housenumber":"32",
    "addr:postcode":"28700",
    "addr:street":"Calle De Ramon Esteban De",
    "iso:country":"ES",
    "sg:address":"Calle de Ramon Esteban (de), 32",
    "sg:city":"San Sebastian De Los Reyes",
    "sg:orig_category":"M\u00c9dicos: Estomatolog\u00cda",
    "sg:phone":"+34 916 54 31 73",
    "sg:postcode":"28700",
    "sg:province":"Madrid",
    "wof:name":"Bravo Llompart Jose Antonio",
    "wof:placetype":"venue"
},
  "geometry": {"coordinates":[-3.6293900013,40.5446929932],"type":"Point"}
}