{
  "type": "Feature",
  "properties": {
    "addr:full":"Pantano, S/n Lorca Murcia 30817",
    "addr:housenumber":"s / n",
    "addr:postcode":"30817",
    "addr:street":"Pantano",
    "iso:country":"ES",
    "sg:address":"Pantano, S/n",
    "sg:city":"Lorca",
    "sg:orig_category":"Lavado, Limpieza De Veh\u00cdculos",
    "sg:phone":"+34 968 46 50 73",
    "sg:postcode":"30817",
    "sg:province":"Murcia",
    "wof:name":"Periago Rosa Juan",
    "wof:placetype":"venue"
},
  "geometry": {"coordinates":[-1.7245190144,37.6462936401],"type":"Point"}
}