{
  "type": "Feature",
  "properties": {
    "addr:full":"Pol Ind La Ventilla, S/n Prado Del Rey C\u00e1diz 11660",
    "addr:housenumber":"s / n",
    "addr:postcode":"11660",
    "addr:street":"Ventilla",
    "iso:country":"ES",
    "sg:address":"Pol Ind La Ventilla, S/n",
    "sg:city":"Prado Del Rey",
    "sg:orig_category":"Fabricaci\u00d3n De Taburetes, Sillas Y Sillones",
    "sg:phone":"+34 956 72 34 02",
    "sg:postcode":"11660",
    "sg:province":"C\u00e1diz",
    "wof:name":"Lorenzo Castro S.l.",
    "wof:placetype":"venue"
},
  "geometry": {"coordinates":[-5.5512280464,36.7711105347],"type":"Point"}
}