{
  "type": "Feature",
  "properties": {
    "iso:country":"ES",
    "sg:address":"Av Comte De Sallent, 29",
    "sg:city":"Palma",
    "sg:orig_category":"Molduras, Junquillos, Listones Y Molduras Perforadas",
    "sg:phone":"+34 971 71 16 91",
    "sg:postcode":"07003",
    "sg:province":"Islas Baleares",
    "wof:name":"Nieto Castello Fructuoso",
    "wof:placetype":"venue"
},
  "geometry": {"coordinates":[2.64904809,39.5784683228],"type":"Point"}
}