{
  "type": "Feature",
  "properties": {
    "addr:full":"Calle de Silvio Abad, 74 Madrid Madrid 28026",
    "addr:housenumber":"74",
    "addr:postcode":"madrid;28026",
    "addr:street":"Calle De Silvio Abad",
    "iso:country":"ES",
    "sg:address":"Calle de Silvio Abad, 74",
    "sg:city":"Madrid",
    "sg:orig_category":"Cerrajer\u00cda, Ferrallista",
    "sg:phone":"+34 915 69 82 48",
    "sg:postcode":"28026",
    "sg:province":"Madrid",
    "wof:name":"Sierra Blanco Manuel",
    "wof:placetype":"venue"
},
  "geometry": {"coordinates":[-3.7119679451,40.3807907104],"type":"Point"}
}