{
  "type": "Feature",
  "properties": {
    "addr:full":"Calle de Antina, 18 Santa Pola Alicante 03130",
    "addr:housenumber":"18",
    "addr:postcode":"03130",
    "addr:street":"Calle De Antina",
    "iso:country":"ES",
    "sg:address":"Calle de Antina, 18",
    "sg:city":"Santa Pola",
    "sg:orig_category":"Electrodom\u00c9sticos (al Por Menor)",
    "sg:phone":"+34 965 41 59 15",
    "sg:postcode":"03130",
    "sg:province":"Alicante",
    "wof:name":"Gonzalez Perez Francisco Javier",
    "wof:placetype":"venue"
},
  "geometry": {"coordinates":[-0.5540639758,38.1911468506],"type":"Point"}
}