{
  "type": "Feature",
  "properties": {
    "addr:full":"Calle de Arlanzon, 3 Sevilla Sevilla 41005",
    "addr:housenumber":"3",
    "addr:postcode":"41005",
    "addr:street":"Calle De Arlanzon",
    "iso:country":"ES",
    "sg:address":"Calle de Arlanzon, 3",
    "sg:city":"Sevilla",
    "sg:orig_category":"Mercer\u00cda, Lencer\u00cda (al Por Menor)",
    "sg:phone":"+34 954 63 85 36",
    "sg:postcode":"41005",
    "sg:province":"Sevilla",
    "wof:name":"Garrido Fernandez Luis",
    "wof:placetype":"venue"
},
  "geometry": {"coordinates":[-5.9647536278,37.3793106079],"type":"Point"}
}