{
  "type": "Feature",
  "properties": {
    "iso:country":"ES",
    "sg:address":"Calle de Torres Quevedo, 3",
    "sg:city":"Mostoles",
    "sg:orig_category":"Fabricaci\u00d3n De Juguetes Autom\u00c1ticos",
    "sg:phone":"+34 916 47 66 25",
    "sg:postcode":"28936",
    "sg:province":"Madrid",
    "wof:name":"Cresmatic S.l.",
    "wof:placetype":"venue"
},
  "geometry": {"coordinates":[-3.8472640514,40.3173942566],"type":"Point"}
}