{
  "type": "Feature",
  "properties": {
    "iso:country":"ES",
    "sg:address":"A Poligono Landaben, S/n",
    "sg:city":"Iru\u00f1a",
    "sg:orig_category":"Pintura, Barniz, Productos Asimilables (fabricaci\u00d3n, Al Por Mayor)",
    "sg:phone":"+34 948 18 85 19",
    "sg:postcode":"31012",
    "sg:province":"Navarra",
    "wof:name":"A.auxiliar Carrocera S.a.",
    "wof:placetype":"venue"
},
  "geometry": {"coordinates":[-1.680928,42.827122],"type":"Point"}
}