{
  "type": "Feature",
  "properties": {
    "iso:country":"ES",
    "sg:address":"Calle de Filiberto Rodrigo, 14",
    "sg:city":"Catarroja",
    "sg:orig_category":"Promotores Constructores",
    "sg:phone":"+34 961 26 14 06",
    "sg:postcode":"46470",
    "sg:province":"Valencia",
    "wof:name":"Construcciones Blas Ramon S.l.",
    "wof:placetype":"venue"
},
  "geometry": {"coordinates":[-0.4041689932,39.4075241089],"type":"Point"}
}