{
  "type": "Feature",
  "properties": {
    "addr:full":"Los Ciruelos, 24 Santander Cantabria 39011",
    "addr:housenumber":"24",
    "addr:postcode":"39011",
    "addr:street":"Los Ciruelos",
    "iso:country":"ES",
    "sg:address":"Los Ciruelos, 24",
    "sg:city":"Santander",
    "sg:orig_category":"Peluquer\u00cdas, Peluquer\u00cda Mixta",
    "sg:phone":"+34 942 34 59 66",
    "sg:postcode":"39011",
    "sg:province":"Cantabria",
    "wof:name":"Garcia Fernandez Ines",
    "wof:placetype":"venue"
},
  "geometry": {"coordinates":[-3.8521389961,43.4584693909],"type":"Point"}
}