{
  "type": "Feature",
  "properties": {
    "iso:country":"ES",
    "sg:address":"Calle de Portugal, 21",
    "sg:city":"Malaga",
    "sg:orig_category":"Asesor\u00cda Sobre Comunicaci\u00d3n De Empresas",
    "sg:phone":"+34 952 29 43 36",
    "sg:postcode":"29017",
    "sg:province":"M\u00e1laga",
    "wof:name":"Arroyo Y Perez-padilla Consultores S.l.",
    "wof:placetype":"venue"
},
  "geometry": {"coordinates":[-4.3735389709,36.7269859314],"type":"Point"}
}