{
  "type": "Feature",
  "properties": {
    "addr:full":"Calle de Jose Sanz, 33 Binefar Huesca 22500",
    "addr:housenumber":"33",
    "addr:postcode":"22500",
    "addr:street":"Calle De Jose Sanz",
    "iso:country":"ES",
    "sg:address":"Calle de Jose Sanz, 33",
    "sg:city":"Binefar",
    "sg:orig_category":"Fabricaci\u00d3n, Importaci\u00d3n, Venta De Material De Telefon\u00cda, Peritelefon\u00cda",
    "sg:phone":"+34 974 42 83 56",
    "sg:postcode":"22500",
    "sg:province":"Huesca",
    "wof:name":"Torres Sancho Jose Modesto",
    "wof:placetype":"venue"
},
  "geometry": {"coordinates":[0.2938340008,41.8497161865],"type":"Point"}
}