{
  "type": "Feature",
  "properties": {
    "iso:country":"ES",
    "sg:address":"Calle de Mendez Alvaro, 66",
    "sg:city":"Madrid",
    "sg:orig_category":"Asesor\u00cda Sobre Comunicaci\u00d3n De Empresas",
    "sg:phone":"+34 914 67 59 93",
    "sg:postcode":"28045",
    "sg:province":"Madrid",
    "wof:name":"Royba Asesores S.l.",
    "wof:placetype":"venue"
},
  "geometry": {"coordinates":[-3.6806459427,40.3957443237],"type":"Point"}
}