{
  "type": "Feature",
  "properties": {
    "addr:full":"Calle de Calexa, S/n Arzua La Coru\u00f1a 15810",
    "addr:housenumber":"s",
    "addr:postcode":"15810",
    "addr:street":"Calle De Calexa;/ N;La Corun\u0303A",
    "iso:country":"ES",
    "sg:address":"Calle de Calexa, S/n",
    "sg:city":"Arzua",
    "sg:orig_category":"Promotores Constructores",
    "sg:phone":"+34 981 50 07 12",
    "sg:postcode":"15810",
    "sg:province":"La Coru\u00f1a",
    "wof:name":"Ramos Rey Construccions S.l.",
    "wof:placetype":"venue"
},
  "geometry": {"coordinates":[-8.1620836258,42.9287147522],"type":"Point"}
}