{
  "type": "Feature",
  "properties": {
    "iso:country":"ES",
    "sg:address":"Calle de Fontan, 19",
    "sg:city":"Oviedo",
    "sg:orig_category":"Inmobiliaria (agencias)",
    "sg:phone":"+34 985 20 08 39",
    "sg:postcode":"33009",
    "sg:province":"Asturias",
    "wof:name":"Mu\u00d1iz Mu\u00d1iz Maria Aurora",
    "wof:placetype":"venue"
},
  "geometry": {"coordinates":[-5.8463931084,43.3599243164],"type":"Point"}
}