{
  "type": "Feature",
  "properties": {
    "iso:country":"ES",
    "sg:address":"Calle de Pelayo, 9",
    "sg:city":"Zamora",
    "sg:orig_category":"Telas Y Sedas (al Por Menor)",
    "sg:phone":"+34 980 53 22 06",
    "sg:postcode":"49014",
    "sg:province":"Zamora",
    "wof:name":"Pascual Perez Delia",
    "wof:placetype":"venue"
},
  "geometry": {"coordinates":[-5.7432370186,41.5067405701],"type":"Point"}
}