{
  "type": "Feature",
  "properties": {
    "iso:country":"ES",
    "sg:address":"Rua Republica Argentina, 20",
    "sg:city":"Vigo",
    "sg:orig_category":"Abogados",
    "sg:phone":"+34 986 43 69 59",
    "sg:postcode":"36201",
    "sg:province":"Pontevedra",
    "wof:name":"Cobas Abogados C.b.",
    "wof:placetype":"venue"
},
  "geometry": {"coordinates":[-8.7188310623,42.2360458374],"type":"Point"}
}