{
  "type": "Feature",
  "properties": {
    "addr:full":"Calle de Florida, 6 Alovera Guadalajara 19208",
    "addr:housenumber":"6",
    "addr:postcode":"19208",
    "addr:street":"Calle De Florida",
    "iso:country":"ES",
    "sg:address":"Calle de Florida, 6",
    "sg:city":"Alovera",
    "sg:orig_category":"Ense\u00d1anza Variada",
    "sg:phone":"+34 949 29 78 30",
    "sg:postcode":"19208",
    "sg:province":"Guadalajara",
    "wof:name":"Verderas Casado Virginia",
    "wof:placetype":"venue"
},
  "geometry": {"coordinates":[-3.2468221188,40.5970649719],"type":"Point"}
}