{
  "type": "Feature",
  "properties": {
    "addr:full":"Carretera, 1 Maslloren\u00e7 Tarragona 43718",
    "addr:housenumber":"1",
    "addr:postcode":"43718",
    "addr:street":"Carretera",
    "iso:country":"ES",
    "sg:address":"Carretera, 1",
    "sg:city":"Maslloren\u00e7",
    "sg:orig_category":"Muebles, Minoristas",
    "sg:phone":"+34 977 62 81 10",
    "sg:postcode":"43718",
    "sg:province":"Tarragona",
    "wof:name":"Mobles Guell S. A.",
    "wof:placetype":"venue"
},
  "geometry": {"coordinates":[1.4523650408,41.3147735596],"type":"Point"}
}