{
  "type": "Feature",
  "properties": {
    "iso:country":"ES",
    "sg:address":"Carrer de Post, 9",
    "sg:city":"Gava",
    "sg:orig_category":"Empresas De Carpinter\u00cda De Madera",
    "sg:phone":"+34 936 62 71 61",
    "sg:postcode":"08850",
    "sg:province":"Barcelona",
    "wof:name":"Pena Lara Gregorio",
    "wof:placetype":"venue"
},
  "geometry": {"coordinates":[1.9997220039,41.2961502075],"type":"Point"}
}