{
  "type": "Feature",
  "properties": {
    "iso:country":"ES",
    "sg:address":"Hurtado De Mendoza, 5",
    "sg:city":"Almu\u00f1ecar",
    "sg:orig_category":"Asesor\u00cda Sobre Comunicaci\u00d3n De Empresas",
    "sg:phone":"+34 958 63 27 57",
    "sg:postcode":"18690",
    "sg:province":"Granada",
    "wof:name":"Mateos Sanchez-chaves Manuel",
    "wof:placetype":"venue"
},
  "geometry": {"coordinates":[-3.682338953,36.7323913574],"type":"Point"}
}