{
  "type": "Feature",
  "properties": {
    "iso:country":"ES",
    "sg:address":"Calle de Pepe Luces, 2",
    "sg:city":"Alcala Guadaira",
    "sg:orig_category":"Confecci\u00d3n De Zapatos",
    "sg:phone":"+34 955 62 03 29",
    "sg:postcode":"41500",
    "sg:province":"Sevilla",
    "wof:name":"Malmo Calzados S.l.",
    "wof:placetype":"venue"
},
  "geometry": {"coordinates":[-5.839017868,37.3397369385],"type":"Point"}
}