{
  "type": "Feature",
  "properties": {
    "iso:country":"ES",
    "sg:address":"Calle de Garay Juan De, 53",
    "sg:city":"Bilbao",
    "sg:orig_category":"Molduras, Junquillos, Listones Y Molduras Perforadas",
    "sg:phone":"+34 944 43 50 84",
    "sg:postcode":"48003",
    "sg:province":"Vizcaya",
    "wof:name":"Hidalgo Ria\u00f1o Eva",
    "wof:placetype":"venue"
},
  "geometry": {"coordinates":[-2.9340469837,43.2510261536],"type":"Point"}
}