{
  "type": "Feature",
  "properties": {
    "iso:country":"ES",
    "sg:address":"Ctra Santomera, Km. 2500,0",
    "sg:city":"Huerta Del Raal",
    "sg:orig_category":"Molduras, Junquillos, Listones Y Molduras Perforadas",
    "sg:phone":"+34 968 86 59 03",
    "sg:postcode":"30139",
    "sg:province":"Murcia",
    "wof:name":"Juarez Sanchez Pedro",
    "wof:placetype":"venue"
},
  "geometry": {"coordinates":[-1.0326590538,38.0375366211],"type":"Point"}
}