{
  "type": "Feature",
  "properties": {
    "addr:full":"C/ Sant Tomas, 2 Alcoi Alicante 03801",
    "addr:housenumber":"2",
    "addr:postcode":"03801",
    "addr:street":"C / Sant Tomas",
    "iso:country":"ES",
    "sg:address":"C/ Sant Tomas, 2",
    "sg:city":"Alcoi",
    "sg:orig_category":"Supermercados Y Hipermercados",
    "sg:phone":"+34 965 54 41 82",
    "sg:postcode":"03801",
    "sg:province":"Alicante",
    "sg:website":"www.mercadona.es",
    "wof:name":"Mercadona S.a.",
    "wof:placetype":"venue"
},
  "geometry": {"coordinates":[-0.473578006,38.698677063],"type":"Point"}
}