{
  "type": "Feature",
  "properties": {
    "iso:country":"ES",
    "sg:address":"Calle de Mulhacen, S/n",
    "sg:city":"Galapagar",
    "sg:orig_category":"Pizzer\u00cdas",
    "sg:phone":"+34 918 58 39 15",
    "sg:postcode":"28260",
    "sg:province":"Madrid",
    "wof:name":"Castillo Carpintero Leoncio",
    "wof:placetype":"venue"
},
  "geometry": {"coordinates":[-4.0075640678,40.5820045471],"type":"Point"}
}