{
  "type": "Feature",
  "properties": {
    "iso:country":"ES",
    "sg:address":"Carr Sant Jordi, S/n",
    "sg:city":"Portbou",
    "sg:orig_category":"Centros De Educaci\u00d3n Especial",
    "sg:phone":"+34 972 39 04 94",
    "sg:postcode":"17497",
    "sg:province":"Girona",
    "wof:name":"C.e.i.p Sant Jaume",
    "wof:placetype":"venue"
},
  "geometry": {"coordinates":[3.1601309776,42.4302597046],"type":"Point"}
}