{
  "type": "Feature",
  "properties": {
    "iso:country":"ES",
    "sg:address":"Calle de Malaga, 8",
    "sg:city":"Polan",
    "sg:orig_category":"Agencias Y Agentes Comerciales, Representantes",
    "sg:phone":"+34 925 37 06 36",
    "sg:postcode":"45161",
    "sg:province":"Toledo",
    "wof:name":"Illan Paniagua Eduardo",
    "wof:placetype":"venue"
},
  "geometry": {"coordinates":[-4.1642589569,39.7913017273],"type":"Point"}
}