{
  "type": "Feature",
  "properties": {
    "iso:country":"ES",
    "sg:address":"Carrer de Pau Casals, 10",
    "sg:city":"Manresa",
    "sg:orig_category":"Molduras, Junquillos, Listones Y Molduras Perforadas",
    "sg:phone":"+34 938 73 30 60",
    "sg:postcode":"08243",
    "sg:province":"Barcelona",
    "wof:name":"Bar Tres J S.l.",
    "wof:placetype":"venue"
},
  "geometry": {"coordinates":[1.8338439465,41.7387886047],"type":"Point"}
}