{
  "type": "Feature",
  "properties": {
    "iso:country":"ES",
    "sg:address":"Carrer de Puigmal, S/n",
    "sg:city":"Mira-sol",
    "sg:orig_category":"Restaurantes",
    "sg:phone":"+34 936 74 02 67",
    "sg:postcode":"08195",
    "sg:province":"Barcelona",
    "wof:name":"Casta\u00f1o Lopez Domingo",
    "wof:placetype":"venue"
},
  "geometry": {"coordinates":[2.0623049736,41.4687767029],"type":"Point"}
}