{
  "type": "Feature",
  "properties": {
    "addr:full":"Calle de Francisco De Goya (de), 8 Mejorada Campo Madrid 28840",
    "addr:housenumber":"8",
    "addr:postcode":"28840",
    "addr:street":"Calle De Francisco De Goya De",
    "iso:country":"ES",
    "sg:address":"Calle de Francisco De Goya (de), 8",
    "sg:city":"Mejorada Campo",
    "sg:orig_category":"Animales (al Por Menor)",
    "sg:phone":"+34 916 79 03 46",
    "sg:postcode":"28840",
    "sg:province":"Madrid",
    "wof:name":"Lizcano Lopez Maria Concepcion",
    "wof:placetype":"venue"
},
  "geometry": {"coordinates":[-3.7003455162,40.4166908264],"type":"Point"}
}