{
  "type": "Feature",
  "properties": {
    "addr:full":"Calle de Elcano, 14 Bilbao Vizcaya 48008",
    "addr:housenumber":"14",
    "addr:postcode":"48008",
    "addr:street":"Calle De Elcano",
    "iso:country":"ES",
    "sg:address":"Calle de Elcano, 14",
    "sg:city":"Bilbao",
    "sg:orig_category":"Restaurantes",
    "sg:phone":"+34 944 10 23 75",
    "sg:postcode":"48008",
    "sg:province":"Vizcaya",
    "wof:name":"Sodexho Espa\u00f1a S.a.",
    "wof:placetype":"venue"
},
  "geometry": {"coordinates":[-2.9341351986,43.2614707947],"type":"Point"}
}