{
  "type": "Feature",
  "properties": {
    "iso:country":"ES",
    "sg:address":"Calle de Salzillo, S/n",
    "sg:city":"Archena",
    "sg:orig_category":"Pescader\u00cdas (al Por Menor)",
    "sg:phone":"+34 968 67 01 16",
    "sg:postcode":"30600",
    "sg:province":"Murcia",
    "wof:name":"Luna Garcia Eugenio",
    "wof:placetype":"venue"
},
  "geometry": {"coordinates":[-1.3013240099,38.1143455505],"type":"Point"}
}