{
  "type": "Feature",
  "properties": {
    "iso:country":"ES",
    "sg:address":"Calle de Larga, 4",
    "sg:city":"Paradas",
    "sg:orig_category":"Administraciones Regionales, Departamentales Y Locales",
    "sg:phone":"+34 955 84 49 10",
    "sg:postcode":"41610",
    "sg:province":"Sevilla",
    "wof:name":"Ayuntamiento De Paradas",
    "wof:placetype":"venue"
},
  "geometry": {"coordinates":[-5.496609211,37.2904014587],"type":"Point"}
}