{
  "type": "Feature",
  "properties": {
    "addr:full":"Ctra. Turegano, S/n Navas Oro Segovia 40470",
    "addr:housenumber":"s",
    "addr:postcode":"40470",
    "addr:street":"Ctra. Turegano;/ N",
    "iso:country":"ES",
    "sg:address":"Ctra. Turegano, S/n",
    "sg:city":"Navas Oro",
    "sg:orig_category":"Cr\u00cda De Cerdos",
    "sg:phone":"+34 921 12 41 35",
    "sg:postcode":"40470",
    "sg:province":"Segovia",
    "wof:name":"Granja Porcino Omalu S.l.",
    "wof:placetype":"venue"
},
  "geometry": {"coordinates":[-4.4386892319,41.1965408325],"type":"Point"}
}