{
  "type": "Feature",
  "properties": {
    "iso:country":"ES",
    "sg:address":"Calle de Gainza, 37",
    "sg:city":"Madrid",
    "sg:orig_category":"Contenedores (mercanc\u00cdas)",
    "sg:phone":"+34 913 41 25 78",
    "sg:postcode":"28041",
    "sg:province":"Madrid",
    "wof:name":"Jimenez Moreno Victoriano",
    "wof:placetype":"venue"
},
  "geometry": {"coordinates":[-3.718734026,40.3713378906],"type":"Point"}
}