{
  "type": "Feature",
  "properties": {
    "iso:country":"ES",
    "sg:address":"Carr Cimentera, De Sa, 38",
    "sg:city":"Campos",
    "sg:orig_category":"M\u00c1rmoles, Granitos Y Piedras Naturales",
    "sg:phone":"+34 971 65 08 73",
    "sg:postcode":"07630",
    "sg:province":"Islas Baleares",
    "wof:name":"Sa Cimentera S.a.",
    "wof:placetype":"venue"
},
  "geometry": {"coordinates":[2.998032093,39.4063224792],"type":"Point"}
}