{
  "type": "Feature",
  "properties": {
    "iso:country":"ES",
    "sg:address":"Calle de Reina, 126",
    "sg:city":"Valencia",
    "sg:orig_category":"Agencias Y Agentes Comerciales, Representantes",
    "sg:phone":"+34 963 71 49 15",
    "sg:postcode":"46011",
    "sg:province":"Valencia",
    "wof:name":"Prats Pedro Alfredo",
    "wof:placetype":"venue"
},
  "geometry": {"coordinates":[-0.3285579979,39.4687576294],"type":"Point"}
}