{
  "type": "Feature",
  "properties": {
    "addr:full":"Calle de Maria De Molina, 1 Valladolid Valladolid 47001",
    "addr:housenumber":"1",
    "addr:postcode":"47001",
    "addr:street":"Calle De Maria De Molina",
    "iso:country":"ES",
    "sg:address":"Calle de Maria De Molina, 1",
    "sg:city":"Valladolid",
    "sg:orig_category":"Deportes Y Ocio: Art\u00cdculos Y Ropas (al Por Menor Y Accesorios)",
    "sg:phone":"+34 983 35 99 86",
    "sg:postcode":"47001",
    "sg:province":"Valladolid",
    "sg:website":"www.coroneltapiocca.com",
    "wof:name":"Coronel Tapioca S.a.",
    "wof:placetype":"venue"
},
  "geometry": {"coordinates":[-4.7305822372,41.650592804],"type":"Point"}
}