{
  "type": "Feature",
  "properties": {
    "iso:country":"ES",
    "sg:address":"Calle de Brillante, 4",
    "sg:city":"Sevilla",
    "sg:orig_category":"Asociaciones, Organismos Culturales Y Socioeducativos",
    "sg:phone":"+34 954 37 15 26",
    "sg:postcode":"41009",
    "sg:province":"Sevilla",
    "wof:name":"Centro Cultural Recreativo San Francisco De Asis",
    "wof:placetype":"venue"
},
  "geometry": {"coordinates":[-5.9853019714,37.4106369019],"type":"Point"}
}