{
  "type": "Feature",
  "properties": {
    "addr:full":"La Union, S/n Mijas Costa M\u00e1laga 29649",
    "addr:housenumber":"/ n",
    "addr:postcode":"29649",
    "addr:street":"La Union S",
    "iso:country":"ES",
    "sg:address":"La Union, S/n",
    "sg:city":"Mijas Costa",
    "sg:orig_category":"Bancos",
    "sg:phone":"+34 952 47 48 12",
    "sg:postcode":"29649",
    "sg:province":"M\u00e1laga",
    "wof:name":"Banco De Andalucia",
    "wof:placetype":"venue"
},
  "geometry": {"coordinates":[-4.6310629845,36.5238952637],"type":"Point"}
}