{
  "type": "Feature",
  "properties": {
    "iso:country":"ES",
    "sg:address":"Avda Ricardo Soriano, 57",
    "sg:city":"Marbella",
    "sg:orig_category":"Colchones (fabricaci\u00d3n, Al Por Mayor, Al Por Menor)",
    "sg:phone":"+34 952 82 44 20",
    "sg:postcode":"29600",
    "sg:province":"M\u00e1laga",
    "sg:website":"www.noctalia.es",
    "wof:name":"Noctalia",
    "wof:placetype":"venue"
},
  "geometry": {"coordinates":[-4.8984827995,36.5102272034],"type":"Point"}
}