{
  "type": "Feature",
  "properties": {
    "addr:full":"Calle de Alcala De Henares, 1 Guadalajara Guadalajara 19003",
    "addr:housenumber":"1",
    "addr:postcode":"19003",
    "addr:street":"Calle De Alcala De Henares",
    "iso:country":"ES",
    "sg:address":"Calle de Alcala De Henares, 1",
    "sg:city":"Guadalajara",
    "sg:orig_category":"Empresas De Pintura Y Revestimientos",
    "sg:phone":"+34 949 22 30 19",
    "sg:postcode":"19003",
    "sg:province":"Guadalajara",
    "wof:name":"Prieto Calvo Tomas",
    "wof:placetype":"venue"
},
  "geometry": {"coordinates":[-3.1746430397,40.6301345825],"type":"Point"}
}