{
  "type": "Feature",
  "properties": {
    "addr:full":"Calle de Sorvilan, S/n Albolote Granada 18220",
    "addr:housenumber":"s / n",
    "addr:postcode":"18220",
    "addr:street":"Calle De Sorvilan",
    "iso:country":"ES",
    "sg:address":"Calle de Sorvilan, S/n",
    "sg:city":"Albolote",
    "sg:orig_category":"Pintura, Barniz, Productos Asimilables (fabricaci\u00d3n, Al Por Mayor)",
    "sg:phone":"+34 958 46 75 68",
    "sg:postcode":"18220",
    "sg:province":"Granada",
    "wof:name":"Pifranto S.l.",
    "wof:placetype":"venue"
},
  "geometry": {"coordinates":[-3.6467139721,37.2250938416],"type":"Point"}
}