{
  "type": "Feature",
  "properties": {
    "addr:full":"Calle de San Andres, 35 Zamora Zamora 49003",
    "addr:housenumber":"35",
    "addr:postcode":"49003",
    "addr:street":"Calle De San Andres",
    "iso:country":"ES",
    "sg:address":"Calle de San Andres, 35",
    "sg:city":"Zamora",
    "sg:orig_category":"Torrefactado De Caf\u00c9",
    "sg:phone":"+34 980 53 21 64",
    "sg:postcode":"49003",
    "sg:province":"Zamora",
    "wof:name":"Cafes Y Solubles La Flor De America S.l.",
    "wof:placetype":"venue"
},
  "geometry": {"coordinates":[-5.7428097725,41.503780365],"type":"Point"}
}