{
  "type": "Feature",
  "properties": {
    "iso:country":"ES",
    "sg:address":"Calle de Tribaldos, 56",
    "sg:city":"Madrid",
    "sg:orig_category":"Inmobiliaria (agencias)",
    "sg:phone":"+34 917 64 28 59",
    "sg:postcode":"28043",
    "sg:province":"Madrid",
    "wof:name":"Lafuente Arias Rafael",
    "wof:placetype":"venue"
},
  "geometry": {"coordinates":[-3.6396389008,40.4673271179],"type":"Point"}
}