{
  "type": "Feature",
  "properties": {
    "iso:country":"ES",
    "sg:address":"Avda Montgo, 244",
    "sg:city":"Denia",
    "sg:orig_category":"Agentes, Concesionarios Y Sucursales De Camiones Y Veh\u00cdculos Industriales",
    "sg:phone":"+34 966 43 53 49",
    "sg:postcode":"03700",
    "sg:province":"Alicante",
    "sg:website":"www.industriasconejero.com",
    "wof:name":"Ruedas Industrias Conejero C.b.",
    "wof:placetype":"venue"
},
  "geometry": {"coordinates":[0.1023079976,38.8347892761],"type":"Point"}
}