{
  "type": "Feature",
  "properties": {
    "iso:country":"ES",
    "sg:address":"Calle de Adelardo Covarsi, 17",
    "sg:city":"Badajoz",
    "sg:orig_category":"Ingenier\u00cda, Centros De Estudios (diversos)",
    "sg:phone":"+34 924 24 04 22",
    "sg:postcode":"06005",
    "sg:province":"Badajoz",
    "wof:name":"Albarran Molina Jose Maria",
    "wof:placetype":"venue"
},
  "geometry": {"coordinates":[-6.9778170586,38.8738136292],"type":"Point"}
}