{
  "type": "Feature",
  "properties": {
    "addr:full":"Calle de Luis Guedea, 21 Calatayud Zaragoza 50300",
    "addr:housenumber":"21",
    "addr:postcode":"50300",
    "addr:street":"Calle De Luis Guedea",
    "iso:country":"ES",
    "sg:address":"Calle de Luis Guedea, 21",
    "sg:city":"Calatayud",
    "sg:orig_category":"Complementos De Vestir (al Por Menor)",
    "sg:phone":"+34 976 88 75 10",
    "sg:postcode":"50300",
    "sg:province":"Zaragoza",
    "wof:name":"Herrero Jaraba Azuzena",
    "wof:placetype":"venue"
},
  "geometry": {"coordinates":[-1.640961051,41.352394104],"type":"Point"}
}