{
  "type": "Feature",
  "properties": {
    "iso:country":"ES",
    "sg:address":"Avda Valladolid, 19",
    "sg:city":"Tudela Duero",
    "sg:orig_category":"Notarios",
    "sg:phone":"+34 983 52 00 72",
    "sg:postcode":"47320",
    "sg:province":"Valladolid",
    "wof:name":"Gutierrez Enriquez Jose Antonio",
    "wof:placetype":"venue"
},
  "geometry": {"coordinates":[-4.5832128525,41.5870437622],"type":"Point"}
}