{
  "type": "Feature",
  "properties": {
    "addr:full":"Calle de Larga, 32 Almodovar Del Pinar Cuenca 16130",
    "addr:housenumber":"32",
    "addr:postcode":"16130",
    "addr:street":"Calle De Larga",
    "iso:country":"ES",
    "sg:address":"Calle de Larga, 32",
    "sg:city":"Almodovar Del Pinar",
    "sg:orig_category":"Iglesia Cat\u00d3lica",
    "sg:phone":"+34 969 33 60 00",
    "sg:postcode":"16130",
    "sg:province":"Cuenca",
    "wof:name":"Parroquia Nuestra Se\u00f1ora De La Asuncion",
    "wof:placetype":"venue"
},
  "geometry": {"coordinates":[-1.8992860317,39.7282180786],"type":"Point"}
}