{
  "type": "Feature",
  "properties": {
    "iso:country":"ES",
    "sg:address":"Calle de Apodaca, 16",
    "sg:city":"Madrid",
    "sg:orig_category":"Confecci\u00d3n De Trajes De Ba\u00d1o Y De Ropa De Playa",
    "sg:phone":"+34 914 46 99 88",
    "sg:postcode":"28004",
    "sg:province":"Madrid",
    "wof:name":"Baquero  Julio",
    "wof:placetype":"venue"
},
  "geometry": {"coordinates":[-3.700193882,40.4272422791],"type":"Point"}
}