{
  "type": "Feature",
  "properties": {
    "addr:full":"Ardia, 172 Grove Pontevedra 36989",
    "addr:housenumber":"172",
    "addr:postcode":"36989",
    "addr:street":"Ardia;Grove Pontevedra",
    "iso:country":"ES",
    "sg:address":"Ardia, 172",
    "sg:city":"Grove",
    "sg:orig_category":"Estudios Y Construcci\u00d3n De Acuarios Y Viveros",
    "sg:phone":"+34 986 73 12 79",
    "sg:postcode":"36989",
    "sg:province":"Pontevedra",
    "wof:name":"Insui\u00f1a S.l.",
    "wof:placetype":"venue"
},
  "geometry": {"coordinates":[-8.8617591858,42.4770011902],"type":"Point"}
}