{
  "type": "Feature",
  "properties": {
    "addr:full":"Calle de Encinas Del Paular, 6 Pozuelo De Alarcon Madrid 28224",
    "addr:housenumber":"6",
    "addr:postcode":"28224",
    "addr:street":"Calle De Encinas Del Paular",
    "iso:country":"ES",
    "sg:address":"Calle de Encinas Del Paular, 6",
    "sg:city":"Pozuelo De Alarcon",
    "sg:classifiers":[
        {
            "category":"Manufacturing",
            "subcategory":"Building Materials",
            "type":"Manufacturing & Wholesale Goods"
        }
    ],
    "sg:phone":"+34 917 99 09 81",
    "sg:postcode":"28224",
    "sg:province":"Madrid",
    "sg:tags":[
        "cemento",
        "y",
        "de",
        "fabricaci\u00d3n",
        "cal"
    ],
    "wof:name":"Tradeland Commodities S.l.",
    "wof:placetype":"venue"
},
  "geometry": {"coordinates":[-3.8057539463,40.4555358887],"type":"Point"}
}