{
  "type": "Feature",
  "properties": {
    "addr:full":"Urb Zarza (la), 14 Zarza Toledo 45215",
    "addr:postcode":"45215",
    "iso:country":"ES",
    "sg:address":"Urb Zarza (la), 14",
    "sg:city":"Zarza",
    "sg:orig_category":"Molduras, Junquillos, Listones Y Molduras Perforadas",
    "sg:phone":"+34 925 53 50 32",
    "sg:postcode":"45215",
    "sg:province":"Toledo",
    "wof:name":"Gomez Donaire Juana",
    "wof:placetype":"venue"
},
  "geometry": {"coordinates":[-4.0004172325,40.1393318176],"type":"Point"}
}