{
  "type": "Feature",
  "properties": {
    "addr:full":"Ctra Aznalcazar-villafranco, S/n Aznalcazar Sevilla 41849",
    "addr:housenumber":"s",
    "addr:postcode":"41849",
    "addr:street":"Ctra Aznalcazar-Villafranco;/ N Aznalcazar",
    "iso:country":"ES",
    "sg:address":"Ctra Aznalcazar-villafranco, S/n",
    "sg:city":"Aznalcazar",
    "sg:orig_category":"Producci\u00d3n, Comercio De Cereales",
    "sg:phone":"+34 955 75 00 60",
    "sg:postcode":"41849",
    "sg:province":"Sevilla",
    "wof:name":"Cereales Margoisa S.l.",
    "wof:placetype":"venue"
},
  "geometry": {"coordinates":[-6.2510838509,37.303768158],"type":"Point"}
}