{
  "type": "Feature",
  "properties": {
    "addr:full":"Calle de Murillo, 9 San Mateo Murcia 30800",
    "addr:housenumber":"9",
    "addr:postcode":"30800",
    "addr:street":"Calle De Murillo",
    "iso:country":"ES",
    "sg:address":"Calle de Murillo, 9",
    "sg:city":"San Mateo",
    "sg:orig_category":"Ropa Para Se\u00d1oras (al Por Menor)",
    "sg:phone":"+34 968 46 17 07",
    "sg:postcode":"30800",
    "sg:province":"Murcia",
    "wof:name":"Correas Romera Emilio",
    "wof:placetype":"venue"
},
  "geometry": {"coordinates":[-1.6905640364,37.680557251],"type":"Point"}
}