{
  "type": "Feature",
  "properties": {
    "addr:full":"Matricers(p I La Closa), 36 Meliana Valencia 46133",
    "addr:housenumber":"36",
    "addr:postcode":"46133",
    "addr:street":"Matricers",
    "iso:country":"ES",
    "sg:address":"Matricers(p I La Closa), 36",
    "sg:city":"Meliana",
    "sg:orig_category":"Plomeros",
    "sg:phone":"+34 961 49 49 56",
    "sg:postcode":"46133",
    "sg:province":"Valencia",
    "wof:name":"Suministros Stil S.l.",
    "wof:placetype":"venue"
},
  "geometry": {"coordinates":[-0.3542670012,39.5257148743],"type":"Point"}
}