{
  "type": "Feature",
  "properties": {
    "iso:country":"ES",
    "sg:address":"Cami Termens, S/n",
    "sg:city":"Bellvis",
    "sg:orig_category":"Textil",
    "sg:phone":"+34 973 56 56 17",
    "sg:postcode":"25142",
    "sg:province":"Lleida",
    "wof:name":"Vilsi S. A.",
    "wof:placetype":"venue"
},
  "geometry": {"coordinates":[0.8160060048,41.6747169495],"type":"Point"}
}