{
  "type": "Feature",
  "properties": {
    "addr:full":"Avda Constitucion (de La), 31 Gran Tarajal Las Palmas 35620",
    "addr:housenumber":"31",
    "addr:postcode":"35620",
    "addr:street":"Avda Constitucion De La;Palmas",
    "iso:country":"ES",
    "sg:address":"Avda Constitucion (de La), 31",
    "sg:city":"Gran Tarajal",
    "sg:orig_category":"Bancos",
    "sg:phone":"+34 928 87 00 25",
    "sg:postcode":"35620",
    "sg:province":"Las Palmas",
    "sg:website":"www.gruposantander.com",
    "wof:name":"Bt Espa\u00d1a Compa\u00d1ia De Servicios Globales De Telecomunicaciones S.a.u.",
    "wof:placetype":"venue"
},
  "geometry": {"coordinates":[-14.0201587677,28.2145900726],"type":"Point"}
}