{
  "type": "Feature",
  "properties": {
    "iso:country":"ES",
    "sg:address":"Avda Finisterre, 83",
    "sg:city":"Laracha",
    "sg:orig_category":"Promotores Constructores",
    "sg:phone":"+34 981 64 30 34",
    "sg:postcode":"15145",
    "sg:province":"La Coru\u00f1a",
    "wof:name":"Construcciones Santiago Rey Rodriguez S.l.",
    "wof:placetype":"venue"
},
  "geometry": {"coordinates":[-8.5822992325,43.2485618591],"type":"Point"}
}