{
  "type": "Feature",
  "properties": {
    "iso:country":"ES",
    "sg:address":"Calle de Caracas De, 4",
    "sg:city":"Fraga",
    "sg:orig_category":"Bisuter\u00cda, Joyer\u00cda, Relojer\u00cda (al Por Menor)",
    "sg:phone":"+34 974 45 35 98",
    "sg:postcode":"22520",
    "sg:province":"Huesca",
    "wof:name":"Joyeria Luzuriaga S.cv.",
    "wof:placetype":"venue"
},
  "geometry": {"coordinates":[0.338717103,41.5220108032],"type":"Point"}
}