{
  "type": "Feature",
  "properties": {
    "iso:country":"ES",
    "sg:address":"Calle de Pez Volador, 20",
    "sg:city":"Madrid",
    "sg:orig_category":"Abogados",
    "sg:phone":"+34 915 74 34 45",
    "sg:postcode":"28007",
    "sg:province":"Madrid",
    "wof:name":"Alberto Blanco Abru\u00f1a S.l.u.",
    "wof:placetype":"venue"
},
  "geometry": {"coordinates":[-3.6671423912,40.4137229919],"type":"Point"}
}