{
  "type": "Feature",
  "properties": {
    "iso:country":"ES",
    "sg:address":"Calle de Atocha, 63",
    "sg:city":"Madrid",
    "sg:orig_category":"Lencer\u00cda Femenina, Corseter\u00cda, Trajes De Ba\u00d1o (al Por Menor)",
    "sg:phone":"+34 914 29 27 60",
    "sg:postcode":"28012",
    "sg:province":"Madrid",
    "wof:name":"Tiendas Conexion S.l.",
    "wof:placetype":"venue"
},
  "geometry": {"coordinates":[-3.6992678642,40.4124641418],"type":"Point"}
}