{
  "type": "Feature",
  "properties": {
    "addr:full":"Calle de Torre Del Oro, 8 Camas Sevilla 41900",
    "addr:housenumber":"8",
    "addr:postcode":"41900",
    "addr:street":"Calle De Torre Del Oro",
    "iso:country":"ES",
    "sg:address":"Calle de Torre Del Oro, 8",
    "sg:city":"Camas",
    "sg:orig_category":"Bisuter\u00cda, Joyer\u00cda, Relojer\u00cda (al Por Menor)",
    "sg:phone":"+34 955 98 06 25",
    "sg:postcode":"41900",
    "sg:province":"Sevilla",
    "wof:name":"Nu\u00f1ez Trapero Francisco",
    "wof:placetype":"venue"
},
  "geometry": {"coordinates":[-6.0326838493,37.3983840942],"type":"Point"}
}