{
  "type": "Feature",
  "properties": {
    "iso:country":"ES",
    "sg:address":"Avda Barrax, 26",
    "sg:city":"Villarrobledo",
    "sg:orig_category":"Empresas De Carpinter\u00cda Met\u00c1lica",
    "sg:phone":"+34 967 14 40 66",
    "sg:postcode":"02600",
    "sg:province":"Albacete",
    "wof:name":"Garcia Moya Antonio Damian",
    "wof:placetype":"venue"
},
  "geometry": {"coordinates":[-2.5945379734,39.2636260986],"type":"Point"}
}