{
  "type": "Feature",
  "properties": {
    "addr:full":"Carr Santissima Trinitat, 12 Silla Valencia 46460",
    "addr:housenumber":"12",
    "addr:postcode":"46460",
    "addr:street":"Carr Santissima Trinitat",
    "iso:country":"ES",
    "sg:address":"Carr Santissima Trinitat, 12",
    "sg:city":"Silla",
    "sg:orig_category":"Mec\u00c1nico Del Autom\u00d3vil",
    "sg:phone":"+34 961 20 06 57",
    "sg:postcode":"46460",
    "sg:province":"Valencia",
    "wof:name":"Palomares Gastaldo Tomas",
    "wof:placetype":"venue"
},
  "geometry": {"coordinates":[-0.4076290131,39.3633613586],"type":"Point"}
}