{
  "type": "Feature",
  "properties": {
    "addr:full":"Zerrajera Kalea, 1 Arrasate Guip\u00f9zcoa 20500",
    "addr:housenumber":"1",
    "addr:postcode":"20500",
    "addr:street":"Zerrajera Kalea;Guipu\u0300Zcoa",
    "iso:country":"ES",
    "sg:address":"Zerrajera Kalea, 1",
    "sg:city":"Arrasate",
    "sg:orig_category":"Peluquer\u00cdas, Peluquer\u00cda Mixta",
    "sg:phone":"+34 943 79 81 79",
    "sg:postcode":"20500",
    "sg:province":"Guip\u00f9zcoa",
    "wof:name":"Ines Andres Valentin",
    "wof:placetype":"venue"
},
  "geometry": {"coordinates":[-2.4945991039,43.060295105],"type":"Point"}
}