{
  "type": "Feature",
  "properties": {
    "addr:full":"Pino Azul (p I El Pino), S/n Sevilla Sevilla 41017",
    "addr:housenumber":"/ n",
    "addr:postcode":"41017",
    "addr:street":"Pino S",
    "iso:country":"ES",
    "sg:address":"Pino Azul (p I El Pino), S/n",
    "sg:city":"Sevilla",
    "sg:orig_category":"Centros De Adelgazamiento Y De Est\u00c9tica",
    "sg:phone":"+34 954 26 07 96",
    "sg:postcode":"41017",
    "sg:province":"Sevilla",
    "sg:website":"www.tecnobelleza.com",
    "wof:name":"Tecnobelleza S.l.l",
    "wof:placetype":"venue"
},
  "geometry": {"coordinates":[-5.9251937866,37.3835258484],"type":"Point"}
}