{
  "type": "Feature",
  "properties": {
    "addr:full":"Luga Lomas (las), 45 Lomas De Abajo Murcia 30858",
    "addr:postcode":"30858",
    "addr:street":"Las;Lomas",
    "iso:country":"ES",
    "sg:address":"Luga Lomas (las), 45",
    "sg:city":"Lomas De Abajo",
    "sg:orig_category":"Negocio De Materiales De Construcci\u00d3n",
    "sg:phone":"+34 968 42 90 24",
    "sg:postcode":"30858",
    "sg:province":"Murcia",
    "wof:name":"Andres Mu\u00f1oz Martinez S.l.",
    "wof:placetype":"venue"
},
  "geometry": {"coordinates":[-1.1298867464,37.9834747314],"type":"Point"}
}