{
  "type": "Feature",
  "properties": {
    "iso:country":"ES",
    "sg:address":"Calle de Mayor, 24",
    "sg:city":"Noblejas",
    "sg:orig_category":"Productores Recolectores, Venta Directa De Vinos",
    "sg:phone":"+34 925 14 11 06",
    "sg:postcode":"45350",
    "sg:province":"Toledo",
    "wof:name":"Diaz-rega\u00f1on Sanchez Isidoro",
    "wof:placetype":"venue"
},
  "geometry": {"coordinates":[-3.4395821095,39.9802818298],"type":"Point"}
}