{
  "type": "Feature",
  "properties": {
    "iso:country":"ES",
    "sg:address":"Calle de Comandante Janariz, 10",
    "sg:city":"Oviedo",
    "sg:orig_category":"Mec\u00c1nico Del Autom\u00d3vil",
    "sg:phone":"+34 985 20 23 41",
    "sg:postcode":"33010",
    "sg:province":"Asturias",
    "wof:name":"Gutierrez Prado Jesus",
    "wof:placetype":"venue"
},
  "geometry": {"coordinates":[-5.8353147507,43.3639297485],"type":"Point"}
}