{
  "type": "Feature",
  "properties": {
    "addr:full":"Avda Playa Paraiso, 2 Playa Paraiso Santa Cruz De Tenerife 38678",
    "addr:housenumber":"2",
    "addr:postcode":"38678",
    "addr:street":"Avda Playa Paraiso",
    "iso:country":"ES",
    "sg:address":"Avda Playa Paraiso, 2",
    "sg:city":"Playa Paraiso",
    "sg:orig_category":"Centros De Coordinaci\u00d3n",
    "sg:phone":"+34 922 74 19 79",
    "sg:postcode":"38678",
    "sg:province":"Santa Cruz De Tenerife",
    "wof:name":"Batista Mederos Antonio",
    "wof:placetype":"venue"
},
  "geometry": {"coordinates":[-16.7669334412,28.1203994751],"type":"Point"}
}