{
  "type": "Feature",
  "properties": {
    "addr:full":"Calle de Sanchoenea, 15 Errenteria Guip\u00f9zcoa 20100",
    "addr:housenumber":"15",
    "addr:postcode":"20100",
    "addr:street":"Calle De Sanchoenea;Guipu\u0300Zcoa",
    "iso:country":"ES",
    "sg:address":"Calle de Sanchoenea, 15",
    "sg:city":"Errenteria",
    "sg:orig_category":"Perfumer\u00cda, Art\u00cdculos De Ba\u00d1o (fabricaci\u00d3n, Al Por Mayor)",
    "sg:phone":"+34 943 51 69 90",
    "sg:postcode":"20100",
    "sg:province":"Guip\u00f9zcoa",
    "wof:name":"Natural Body, Maria Rosario Sanchez Oraa",
    "wof:placetype":"venue"
},
  "geometry": {"coordinates":[-1.8996230364,43.3127632141],"type":"Point"}
}