{
  "type": "Feature",
  "properties": {
    "iso:country":"ES",
    "sg:address":"Ctra Campamento, Km. 0009,2",
    "sg:city":"Huercal Almeria",
    "sg:orig_category":"Mayoristas E Intermediarios En Alcoholes",
    "sg:phone":"+34 950 30 17 73",
    "sg:postcode":"04230",
    "sg:province":"Almer\u00eda",
    "wof:name":"Dijago S.l",
    "wof:placetype":"venue"
},
  "geometry": {"coordinates":[-2.4370388985,36.8798294067],"type":"Point"}
}