{
  "type": "Feature",
  "properties": {
    "addr:full":"Calle de Terriza, 29 Almeria Almer\u00eda 04001",
    "addr:housenumber":"29",
    "addr:postcode":"04001",
    "addr:street":"Calle De Terriza",
    "iso:country":"ES",
    "sg:address":"Calle de Terriza, 29",
    "sg:city":"Almeria",
    "sg:orig_category":"Muebles, Minoristas",
    "sg:phone":"+34 950 23 10 69",
    "sg:postcode":"04001",
    "sg:province":"Almer\u00eda",
    "wof:name":"Muebles La Vitrina S.l.",
    "wof:placetype":"venue"
},
  "geometry": {"coordinates":[-2.4606471062,36.8412361145],"type":"Point"}
}