{
  "type": "Feature",
  "properties": {
    "addr:full":"Rua Salto Do Can (do), S/n Ourense Ourense 32002",
    "addr:housenumber":"s / n",
    "addr:postcode":"32002",
    "addr:street":"Rua Salto Do Can Do",
    "iso:country":"ES",
    "sg:address":"Rua Salto Do Can (do), S/n",
    "sg:city":"Ourense",
    "sg:orig_category":"Centros De Educaci\u00d3n Especial",
    "sg:phone":"+34 988 24 37 51",
    "sg:postcode":"32002",
    "sg:province":"Ourense",
    "wof:name":"Colexio Publico De E.x.b.manuel Luis Acu\u00f1a",
    "wof:placetype":"venue"
},
  "geometry": {"coordinates":[-7.8661170006,42.3389396667],"type":"Point"}
}