{
  "type": "Feature",
  "properties": {
    "iso:country":"ES",
    "sg:address":"Ctra Vilallobent, 18",
    "sg:city":"Sant Marc",
    "sg:orig_category":"Alimentaci\u00d3n General (al Por Menor)",
    "sg:phone":"+34 972 14 07 50",
    "sg:postcode":"17520",
    "sg:province":"Girona",
    "wof:name":"Eregal S. L.",
    "wof:placetype":"venue"
},
  "geometry": {"coordinates":[1.9278999567,42.4336547852],"type":"Point"}
}