{
  "type": "Feature",
  "properties": {
    "iso:country":"ES",
    "sg:address":"Calle de Cortijo, S/n",
    "sg:city":"Marbella",
    "sg:orig_category":"Farmacias",
    "sg:phone":"+34 952 77 19 85",
    "sg:postcode":"29600",
    "sg:province":"M\u00e1laga",
    "wof:name":"Gomez Morales Salvador",
    "wof:placetype":"venue"
},
  "geometry": {"coordinates":[-4.728767395,36.4972763062],"type":"Point"}
}