{
  "type": "Feature",
  "properties": {
    "iso:country":"ES",
    "sg:address":"Calle de General Sanjurjo, 56",
    "sg:city":"Beniel",
    "sg:orig_category":"Confecci\u00d3n De Trajes Para Se\u00d1oras",
    "sg:phone":"+34 968 60 02 31",
    "sg:postcode":"30130",
    "sg:province":"Murcia",
    "wof:name":"Guillen Martinez Maria Teresa",
    "wof:placetype":"venue"
},
  "geometry": {"coordinates":[-1.0032490492,38.0485496521],"type":"Point"}
}