{
  "type": "Feature",
  "properties": {
    "addr:full":"Iturriotz Kalea, 8 Arrasate Guip\u00f9zcoa 20500",
    "addr:housenumber":"8",
    "addr:postcode":"20500",
    "addr:street":"Iturriotz Kalea;Guipu\u0300Zcoa",
    "iso:country":"ES",
    "sg:address":"Iturriotz Kalea, 8",
    "sg:city":"Arrasate",
    "sg:orig_category":"Laboratorios Y Trabajos De Fotograf\u00cda, V\u00cddeo Y Cine",
    "sg:phone":"+34 943 77 04 01",
    "sg:postcode":"20500",
    "sg:province":"Guip\u00f9zcoa",
    "wof:name":"Ikatz S.a.",
    "wof:placetype":"venue"
},
  "geometry": {"coordinates":[-2.4894309044,43.0656356812],"type":"Point"}
}