{
  "type": "Feature",
  "properties": {
    "addr:full":"Carr Esplanada Del Port, 11 Blanes Girona 17300",
    "addr:housenumber":"11",
    "addr:postcode":"17300",
    "addr:street":"Carr Esplanada Del Port",
    "iso:country":"ES",
    "sg:address":"Carr Esplanada Del Port, 11",
    "sg:city":"Blanes",
    "sg:orig_category":"Molduras, Junquillos, Listones Y Molduras Perforadas",
    "sg:phone":"+34 972 33 48 19",
    "sg:postcode":"17300",
    "sg:province":"Girona",
    "wof:name":"Artiola Vallespi Jorge",
    "wof:placetype":"venue"
},
  "geometry": {"coordinates":[2.8003935814,41.6757659912],"type":"Point"}
}