{
  "type": "Feature",
  "properties": {
    "iso:country":"ES",
    "sg:address":"Cala Finestrat, 33",
    "sg:city":"Finestrat",
    "sg:orig_category":"Tintorer\u00cdas, Limpieza En Seco",
    "sg:phone":"+34 966 80 02 76",
    "sg:postcode":"03509",
    "sg:province":"Alicante",
    "wof:name":"Ruiz Gutierrez Gregorio",
    "wof:placetype":"venue"
},
  "geometry": {"coordinates":[-0.1988539994,38.5523109436],"type":"Point"}
}