{
  "type": "Feature",
  "properties": {
    "addr:full":"Calle de Sierra De Tornavacas, 5 Madrid Madrid 28031",
    "addr:housenumber":"5",
    "addr:postcode":"28031",
    "addr:street":"Calle De Sierra De Tornavacas",
    "iso:country":"ES",
    "sg:address":"Calle de Sierra De Tornavacas, 5",
    "sg:city":"Madrid",
    "sg:orig_category":"Inform\u00c1tica Equipo Y Programas (al Por Mayor)",
    "sg:phone":"+34 913 80 66 02",
    "sg:postcode":"28031",
    "sg:province":"Madrid",
    "wof:name":"Softlock S.l.",
    "wof:placetype":"venue"
},
  "geometry": {"coordinates":[-3.6281352043,40.378578186],"type":"Point"}
}