{
  "type": "Feature",
  "properties": {
    "iso:country":"ES",
    "sg:address":"Carr Caputxins, 10",
    "sg:city":"Vilanova I La Geltru",
    "sg:orig_category":"Cajas De Ahorro",
    "sg:phone":"+34 938 93 01 12",
    "sg:postcode":"08800",
    "sg:province":"Barcelona",
    "wof:name":"Caixa D'estalvis Del Penedes",
    "wof:placetype":"venue"
},
  "geometry": {"coordinates":[1.7253819704,41.2259597778],"type":"Point"}
}