{
  "type": "Feature",
  "properties": {
    "addr:full":"Carrer de Avi Campas, 6 Santa Maria De Palautordera Barcelona 08460",
    "addr:housenumber":"6",
    "addr:postcode":"08460",
    "addr:street":"Carrer De Avi Campas",
    "iso:country":"ES",
    "sg:address":"Carrer de Avi Campas, 6",
    "sg:city":"Santa Maria De Palautordera",
    "sg:orig_category":"Escayola Y Productos De Escayola (fabricaci\u00d3n, Al Por Mayor)",
    "sg:phone":"+34 938 48 30 20",
    "sg:postcode":"08460",
    "sg:province":"Barcelona",
    "wof:name":"Tejera Santiago Jose",
    "wof:placetype":"venue"
},
  "geometry": {"coordinates":[-97.78224945069999,45.7040786743],"type":"Point"}
}