{
  "type": "Feature",
  "properties": {
    "iso:country":"ES",
    "sg:address":"Rua Lopez Mora, 5",
    "sg:city":"Vigo",
    "sg:orig_category":"Abogados",
    "sg:phone":"+34 986 29 30 15",
    "sg:postcode":"36211",
    "sg:province":"Pontevedra",
    "wof:name":"Galovart Garcia Jose Luis",
    "wof:placetype":"venue"
},
  "geometry": {"coordinates":[-8.7320365906,42.2278175354],"type":"Point"}
}