{
  "type": "Feature",
  "properties": {
    "addr:full":"Calle de Hospital, 4 Marmolejo Ja\u00e9n 23770",
    "addr:housenumber":"4",
    "addr:postcode":"23770",
    "addr:street":"Calle De Hospital;Jae\u0301N",
    "iso:country":"ES",
    "sg:address":"Calle de Hospital, 4",
    "sg:city":"Marmolejo",
    "sg:orig_category":"Ense\u00d1ante, Direcci\u00d3n",
    "sg:phone":"+34 953 52 70 18",
    "sg:postcode":"23770",
    "sg:province":"Ja\u00e9n",
    "wof:name":"Asesoria Anton Y Martinez S.l",
    "wof:placetype":"venue"
},
  "geometry": {"coordinates":[-4.1719689369,38.0446052551],"type":"Point"}
}