{
  "type": "Feature",
  "properties": {
    "addr:full":"Plaz Calvo Sotelo, 18 Alacant Alicante 03001",
    "addr:housenumber":"18",
    "addr:postcode":"03001",
    "addr:street":"Plaz Calvo Sotelo",
    "iso:country":"ES",
    "sg:address":"Plaz Calvo Sotelo, 18",
    "sg:city":"Alacant",
    "sg:orig_category":"Herboristas (al Por Menor)",
    "sg:phone":"+34 965 21 14 68",
    "sg:postcode":"03001",
    "sg:province":"Alicante",
    "wof:name":"Nadin Internacional Dietetica S.l.",
    "wof:placetype":"venue"
},
  "geometry": {"coordinates":[-0.4879890084,38.3439292908],"type":"Point"}
}