{
  "type": "Feature",
  "properties": {
    "iso:country":"ES",
    "sg:address":"Calle de Almeria, 18",
    "sg:city":"Campamento",
    "sg:orig_category":"Casas Con Estructura De Madera",
    "sg:phone":"+34 956 69 83 17",
    "sg:postcode":"11314",
    "sg:province":"C\u00e1diz",
    "wof:name":"Eddy Junior S.l. 2003",
    "wof:placetype":"venue"
},
  "geometry": {"coordinates":[-5.3693780899,36.1734580994],"type":"Point"}
}