{
  "type": "Feature",
  "properties": {
    "addr:full":"Calle de Mesonero Mayor, 21 Coca Segovia 40480",
    "addr:housenumber":"21",
    "addr:postcode":"40480",
    "addr:street":"Calle De Mesonero Mayor",
    "iso:country":"ES",
    "sg:address":"Calle de Mesonero Mayor, 21",
    "sg:city":"Coca",
    "sg:orig_category":"Alimentaci\u00d3n General (al Por Menor)",
    "sg:phone":"+34 921 58 61 33",
    "sg:postcode":"40480",
    "sg:province":"Segovia",
    "wof:name":"Autoservicio Carrion",
    "wof:placetype":"venue"
},
  "geometry": {"coordinates":[-4.5207228661,41.2179222107],"type":"Point"}
}