{
  "type": "Feature",
  "properties": {
    "addr:full":"Calle de Doctor Bonafonte, 1 Cadrete Zaragoza 50420",
    "addr:housenumber":"1",
    "addr:postcode":"50420",
    "addr:street":"Calle De Doctor Bonafonte",
    "iso:country":"ES",
    "sg:address":"Calle de Doctor Bonafonte, 1",
    "sg:city":"Cadrete",
    "sg:orig_category":"Carnicer\u00cdas, Carnicer\u00cdas",
    "sg:phone":"+34 976 12 50 27",
    "sg:postcode":"50420",
    "sg:province":"Zaragoza",
    "wof:name":"Buil Y Benito Sc",
    "wof:placetype":"venue"
},
  "geometry": {"coordinates":[-0.9612929821,41.5539970398],"type":"Point"}
}