{
  "type": "Feature",
  "properties": {
    "addr:full":"Madrid-alicante, Km. 0136,5 Mota Cuervo Cuenca 16630",
    "addr:postcode":"16630",
    "addr:street":"Madrid-Alicante Km. 0136,5 Mota",
    "iso:country":"ES",
    "sg:address":"Madrid-alicante, Km. 0136,5",
    "sg:city":"Mota Cuervo",
    "sg:orig_category":"Explotaci\u00d3n De Canteras",
    "sg:phone":"+34 967 57 31 37",
    "sg:postcode":"16630",
    "sg:province":"Cuenca",
    "wof:name":"Triturados La Mota S.a.",
    "wof:placetype":"venue"
},
  "geometry": {"coordinates":[-2.871309042,39.503036499],"type":"Point"}
}