{
  "type": "Feature",
  "properties": {
    "addr:full":"Calle de Santa Teresa, 25 Zamora Zamora 49013",
    "addr:housenumber":"25",
    "addr:postcode":"49013",
    "addr:street":"Calle De Santa Teresa",
    "iso:country":"ES",
    "sg:address":"Calle de Santa Teresa, 25",
    "sg:city":"Zamora",
    "sg:orig_category":"Alquiler De Casas Y Habitaciones Amuebladas",
    "sg:phone":"+34 980 51 16 10",
    "sg:postcode":"49013",
    "sg:province":"Zamora",
    "wof:name":"Operarias Misioneras Del Sagrado Corazon",
    "wof:placetype":"venue"
},
  "geometry": {"coordinates":[-5.7405481339,41.5107803345],"type":"Point"}
}