{
  "type": "Feature",
  "properties": {
    "addr:full":"Calle de Jose Maluquer, 26 Sevilla Sevilla 41008",
    "addr:housenumber":"26",
    "addr:postcode":"41008",
    "addr:street":"Calle De Jose Maluquer",
    "iso:country":"ES",
    "sg:address":"Calle de Jose Maluquer, 26",
    "sg:city":"Sevilla",
    "sg:orig_category":"Frutas, Legumbres Frescas Y Tempranas (al Por Menor)",
    "sg:phone":"+34 954 35 08 04",
    "sg:postcode":"41008",
    "sg:province":"Sevilla",
    "wof:name":"Bascon Caballero Manuel",
    "wof:placetype":"venue"
},
  "geometry": {"coordinates":[-5.9807491302,37.4039497375],"type":"Point"}
}