{
  "type": "Feature",
  "properties": {
    "addr:full":"Calle de Santa Amalia, 2 Valencia Valencia 46009",
    "addr:housenumber":"2",
    "addr:postcode":"46009",
    "addr:street":"Calle De Santa Amalia",
    "iso:country":"ES",
    "sg:address":"Calle de Santa Amalia, 2",
    "sg:city":"Valencia",
    "sg:orig_category":"Molduras, Junquillos, Listones Y Molduras Perforadas",
    "sg:phone":"+34 963 69 26 50",
    "sg:postcode":"46009",
    "sg:province":"Valencia",
    "wof:name":"Sanchez Ramon Vicente",
    "wof:placetype":"venue"
},
  "geometry": {"coordinates":[-0.3730730116,39.4810256958],"type":"Point"}
}