{
  "type": "Feature",
  "properties": {
    "addr:full":"Pg Illetes, 6 Cas Catala-illetes Islas Baleares 07181",
    "addr:housenumber":"6",
    "addr:postcode":"07181",
    "addr:street":"Illetes;Islas",
    "iso:country":"ES",
    "sg:address":"Pg Illetes, 6",
    "sg:city":"Cas Catala-illetes",
    "sg:orig_category":"Peluqueros: De Se\u00d1oras",
    "sg:phone":"+34 971 40 13 78",
    "sg:postcode":"07181",
    "sg:province":"Islas Baleares",
    "wof:name":"Roza Garcia Jose Luis",
    "wof:placetype":"venue"
},
  "geometry": {"coordinates":[2.5954489708,39.544418335],"type":"Point"}
}