{
  "type": "Feature",
  "properties": {
    "addr:full":"Plaz Mayor De La Hispanidad, 14 Medina Campo Valladolid 47400",
    "addr:housenumber":"14",
    "addr:postcode":"47400",
    "addr:street":"Plaz;Hispanidad",
    "iso:country":"ES",
    "sg:address":"Plaz Mayor De La Hispanidad, 14",
    "sg:city":"Medina Campo",
    "sg:classifiers":[
        {
            "category":"Communications",
            "type":"Services"
        }
    ],
    "sg:phone":"+34 983 81 12 50",
    "sg:postcode":"47400",
    "sg:province":"Valladolid",
    "sg:tags":[
        "televisiones",
        "y",
        "radio"
    ],
    "wof:name":"Antena 3 De Radio S.a.",
    "wof:placetype":"venue"
},
  "geometry": {"coordinates":[-4.7283878326,41.6529464722],"type":"Point"}
}