{
  "type": "Feature",
  "properties": {
    "iso:country":"ES",
    "sg:address":"Ctra General Tf-6237, S/n",
    "sg:city":"Playa San Juan",
    "sg:orig_category":"Reposter\u00cdas",
    "sg:phone":"+34 922 86 56 00",
    "sg:postcode":"38687",
    "sg:province":"Santa Cruz De Tenerife",
    "wof:name":"Surpan S.l.",
    "wof:placetype":"venue"
},
  "geometry": {"coordinates":[-16.7886390686,28.1805458069],"type":"Point"}
}