{
  "type": "Feature",
  "properties": {
    "iso:country":"ES",
    "sg:address":"Carrer de Industria, 5",
    "sg:city":"Valls De Torruella",
    "sg:orig_category":"V\u00c1lvulas",
    "sg:phone":"+34 938 69 61 51",
    "sg:postcode":"08269",
    "sg:province":"Barcelona",
    "sg:website":"www.vsafor.com",
    "wof:name":"Mecanica Safor Sl",
    "wof:placetype":"venue"
},
  "geometry": {"coordinates":[1.7162590027,41.8694648743],"type":"Point"}
}