{
  "type": "Feature",
  "properties": {
    "addr:full":"Leon, Km. 0038,0 Felmin Le\u00f3n 24837",
    "addr:postcode":"24837",
    "addr:street":"Leon Km. 0038,0 Felmin Leo\u0301N",
    "iso:country":"ES",
    "sg:address":"Leon, Km. 0038,0",
    "sg:city":"Felmin",
    "sg:orig_category":"Albergues",
    "sg:phone":"+34 987 57 66 23",
    "sg:postcode":"24837",
    "sg:province":"Le\u00f3n",
    "wof:name":"Gonzalez Gonzalez Maria Isolina",
    "wof:placetype":"venue"
},
  "geometry": {"coordinates":[-5.4925990105,42.9511375427],"type":"Point"}
}