{
  "type": "Feature",
  "properties": {
    "addr:full":"Calle de Carpio, 5 Carmena Toledo 45531",
    "addr:housenumber":"5",
    "addr:postcode":"45531",
    "addr:street":"Calle De Carpio",
    "iso:country":"ES",
    "sg:address":"Calle de Carpio, 5",
    "sg:city":"Carmena",
    "sg:orig_category":"Aceites Y Grasas Alimentarias (fabricaci\u00d3n, Al Por Mayor)",
    "sg:phone":"+34 925 74 21 55",
    "sg:postcode":"45531",
    "sg:province":"Toledo",
    "wof:name":"Mayo Aguilera Federico",
    "wof:placetype":"venue"
},
  "geometry": {"coordinates":[-4.4023213387,39.9544563293],"type":"Point"}
}