{
  "type": "Feature",
  "properties": {
    "iso:country":"ES",
    "sg:address":"San Juan Auzoa, 47",
    "sg:city":"Bergara",
    "sg:orig_category":"Metalurgia: Maquinaria Y Equipos",
    "sg:phone":"+34 943 76 71 11",
    "sg:postcode":"20570",
    "sg:province":"Guip\u00f9zcoa",
    "wof:name":"Mecanizados Markiegi S.l.",
    "wof:placetype":"venue"
},
  "geometry": {"coordinates":[-2.4337089062,43.1292419434],"type":"Point"}
}