{
  "type": "Feature",
  "properties": {
    "iso:country":"ES",
    "sg:address":"Real, 50",
    "sg:city":"S. Esteban Gormaz",
    "sg:orig_category":"Carnicer\u00cdas, Carnicer\u00cdas",
    "sg:phone":"+34 975 35 00 28",
    "sg:postcode":"42330",
    "sg:province":"Soria",
    "wof:name":"Carazo Romera Eutiquio",
    "wof:placetype":"venue"
},
  "geometry": {"coordinates":[-3.1995689869,41.5723457336],"type":"Point"}
}