{
  "type": "Feature",
  "properties": {
    "iso:country":"ES",
    "sg:address":"Calle de Mediterraneo, 24",
    "sg:city":"Valencia",
    "sg:orig_category":"Bisuter\u00cda, Joyer\u00cda, Relojer\u00cda (al Por Menor)",
    "sg:phone":"+34 963 72 34 61",
    "sg:postcode":"46011",
    "sg:province":"Valencia",
    "wof:name":"Barcelo Santiago Amelia",
    "wof:placetype":"venue"
},
  "geometry": {"coordinates":[-0.329993993,39.4676361084],"type":"Point"}
}