{
  "type": "Feature",
  "properties": {
    "iso:country":"ES",
    "sg:address":"Carrer de Major, 9",
    "sg:city":"Hospitalet Llobregat",
    "sg:orig_category":"Servicio De Salud",
    "sg:phone":"+34 932 61 24 49",
    "sg:postcode":"08901",
    "sg:province":"Barcelona",
    "wof:name":"Calvis Calpe Jose",
    "wof:placetype":"venue"
},
  "geometry": {"coordinates":[2.1010940075,41.35962677],"type":"Point"}
}