{
  "type": "Feature",
  "properties": {
    "addr:full":"Calle de Princesa Do\u00d1a Sofia, 5 Alcorcon Madrid 28924",
    "addr:housenumber":"5",
    "addr:postcode":"28924",
    "addr:street":"Calle De Princesa Don\u0303A Sofia",
    "iso:country":"ES",
    "sg:address":"Calle de Princesa Do\u00d1a Sofia, 5",
    "sg:city":"Alcorcon",
    "sg:orig_category":"Reposter\u00cdas",
    "sg:phone":"+34 916 19 71 80",
    "sg:postcode":"28924",
    "sg:province":"Madrid",
    "wof:name":"Corredera Velazquez Emiliano",
    "wof:placetype":"venue"
},
  "geometry": {"coordinates":[-3.8184258938,40.3499145508],"type":"Point"}
}