{
  "type": "Feature",
  "properties": {
    "iso:country":"ES",
    "sg:address":"Avda Balneario, 41",
    "sg:city":"Arteixo",
    "sg:orig_category":"Tintorer\u00cdas, Limpieza En Seco",
    "sg:phone":"+34 981 63 34 29",
    "sg:postcode":"15142",
    "sg:province":"La Coru\u00f1a",
    "wof:name":"Alonso Abeleira Evangelino Jose",
    "wof:placetype":"venue"
},
  "geometry": {"coordinates":[-8.5080871582,43.3048362732],"type":"Point"}
}