{
  "type": "Feature",
  "properties": {
    "iso:country":"ES",
    "sg:address":"Carrer de Tordera, 28",
    "sg:city":"Barcelona",
    "sg:orig_category":"Molduras, Junquillos, Listones Y Molduras Perforadas",
    "sg:phone":"+34 932 10 77 19",
    "sg:postcode":"08012",
    "sg:province":"Barcelona",
    "wof:name":"Hermanos Cercos S.cp.",
    "wof:placetype":"venue"
},
  "geometry": {"coordinates":[2.1609818935,41.4011650085],"type":"Point"}
}