{
  "type": "Feature",
  "properties": {
    "addr:full":"Calle de Lain Calvo, 20 Burgos Burgos 09003",
    "addr:housenumber":"20",
    "addr:postcode":"09003",
    "addr:street":"Calle De Lain Calvo",
    "iso:country":"ES",
    "sg:address":"Calle de Lain Calvo, 20",
    "sg:city":"Burgos",
    "sg:orig_category":"Abogados",
    "sg:phone":"+34 947 27 88 50",
    "sg:postcode":"09003",
    "sg:province":"Burgos",
    "wof:name":"Alvarez Atienza Mariano",
    "wof:placetype":"venue"
},
  "geometry": {"coordinates":[-3.7020578384,42.3420066833],"type":"Point"}
}