{
  "type": "Feature",
  "properties": {
    "iso:country":"ES",
    "sg:address":"Emilio Arrieta, 5",
    "sg:city":"Iru\u00f1a",
    "sg:orig_category":"Arquitectos",
    "sg:phone":"+34 948 22 98 25",
    "sg:postcode":"31002",
    "sg:province":"Navarra",
    "wof:name":"Bernaola Iturbe Juan",
    "wof:placetype":"venue"
},
  "geometry": {"coordinates":[-1.6375730038,42.8157615662],"type":"Point"}
}