{
  "type": "Feature",
  "properties": {
    "iso:country":"ES",
    "sg:address":"Carrer de Manacor, 171",
    "sg:city":"Palma",
    "sg:orig_category":"Asociaciones Y Clubs Deportivos",
    "sg:phone":"+34 971 24 83 93",
    "sg:postcode":"07007",
    "sg:province":"Islas Baleares",
    "wof:name":"Federacion Balear De Futbol",
    "wof:placetype":"venue"
},
  "geometry": {"coordinates":[2.6769900322,39.5707702637],"type":"Point"}
}