{
  "type": "Feature",
  "properties": {
    "addr:full":"Trav De Gracia, 45 Barcelona Barcelona 08021",
    "addr:housenumber":"45",
    "addr:postcode":"08021",
    "addr:street":"Trav De Gracia",
    "iso:country":"ES",
    "sg:address":"Trav De Gracia, 45",
    "sg:city":"Barcelona",
    "sg:orig_category":"Caf\u00c9s, Bares, Cervecer\u00cdas",
    "sg:phone":"+34 932 00 62 88",
    "sg:postcode":"08021",
    "sg:province":"Barcelona",
    "wof:name":"Rodriguez Macia Carlos",
    "wof:placetype":"venue"
},
  "geometry": {"coordinates":[2.1484000683,41.3955459595],"type":"Point"}
}