{
  "type": "Feature",
  "properties": {
    "iso:country":"ES",
    "sg:address":"Carrer de L'agricultura, 242",
    "sg:city":"Barcelona",
    "sg:orig_category":"Panader\u00cdas, Panader\u00cdas",
    "sg:phone":"+34 933 14 30 19",
    "sg:postcode":"08020",
    "sg:province":"Barcelona",
    "wof:name":"Perostes Vitales Jesus",
    "wof:placetype":"venue"
},
  "geometry": {"coordinates":[2.201372385,41.4180717468],"type":"Point"}
}