{
  "type": "Feature",
  "properties": {
    "addr:full":"Calle de Orihuela Grande, 76 Fregenal Sierra Badajoz 06340",
    "addr:housenumber":"76",
    "addr:postcode":"06340",
    "addr:street":"Calle De Orihuela Grande",
    "iso:country":"ES",
    "sg:address":"Calle de Orihuela Grande, 76",
    "sg:city":"Fregenal Sierra",
    "sg:orig_category":"Molduras, Junquillos, Listones Y Molduras Perforadas",
    "sg:phone":"+34 924 70 00 74",
    "sg:postcode":"06340",
    "sg:province":"Badajoz",
    "wof:name":"Vazquez Diaz Jose Luis",
    "wof:placetype":"venue"
},
  "geometry": {"coordinates":[-6.6490921974,38.1644210815],"type":"Point"}
}