{
  "type": "Feature",
  "properties": {
    "iso:country":"ES",
    "sg:address":"Carrer de Reig I Bonet, 24",
    "sg:city":"Barcelona",
    "sg:orig_category":"Peluqueros: De Se\u00d1oras",
    "sg:phone":"+34 932 19 58 45",
    "sg:postcode":"08024",
    "sg:province":"Barcelona",
    "wof:name":"Diaz Vega Estrella",
    "wof:placetype":"venue"
},
  "geometry": {"coordinates":[2.1607530117,41.4075737],"type":"Point"}
}