{
  "type": "Feature",
  "properties": {
    "addr:full":"Calle de Tenderina, 68 Oviedo Asturias 33010",
    "addr:housenumber":"68",
    "addr:postcode":"33010",
    "addr:street":"Calle De Tenderina",
    "iso:country":"ES",
    "sg:address":"Calle de Tenderina, 68",
    "sg:city":"Oviedo",
    "sg:orig_category":"Cajas De Ahorro",
    "sg:phone":"+34 985 20 05 67",
    "sg:postcode":"33010",
    "sg:province":"Asturias",
    "sg:website":"www.cajastur.es",
    "wof:name":"Caja De Ahorros De Asturias",
    "wof:placetype":"venue"
},
  "geometry": {"coordinates":[-5.8323969841,43.3652687073],"type":"Point"}
}