{
  "type": "Feature",
  "properties": {
    "iso:country":"ES",
    "sg:address":"Calle de Reina, 123",
    "sg:city":"Valencia",
    "sg:orig_category":"Armas Y Municiones (fabricaci\u00d3n, Al Por Mayor)",
    "sg:phone":"+34 963 71 21 04",
    "sg:postcode":"46011",
    "sg:province":"Valencia",
    "wof:name":"Lopez Gallego Francisco",
    "wof:placetype":"venue"
},
  "geometry": {"coordinates":[-0.3286440969,39.4690513611],"type":"Point"}
}