{
  "type": "Feature",
  "properties": {
    "addr:full":"Avda Toreros (de Los), 6 Puerto De Santa Maria C\u00e1diz 11500",
    "addr:postcode":"11500",
    "addr:street":"Avda Toreros De Los 6;Ca\u0301Diz",
    "iso:country":"ES",
    "sg:address":"Avda Toreros (de Los), 6",
    "sg:city":"Puerto De Santa Maria",
    "sg:orig_category":"Pintura, Barniz, Productos Asimilables (fabricaci\u00d3n, Al Por Mayor)",
    "sg:phone":"+34 956 87 03 67",
    "sg:postcode":"11500",
    "sg:province":"C\u00e1diz",
    "wof:name":"Pinturas Brico S.l.",
    "wof:placetype":"venue"
},
  "geometry": {"coordinates":[-6.2362799644,36.5971870422],"type":"Point"}
}