{
  "type": "Feature",
  "properties": {
    "iso:country":"ES",
    "sg:address":"Carr Major, 23",
    "sg:city":"Hostalric",
    "sg:orig_category":"Asesor\u00cdas Y Estudios Financieros",
    "sg:phone":"+34 972 86 40 35",
    "sg:postcode":"17450",
    "sg:province":"Girona",
    "wof:name":"Tusell Puigbert Narciso",
    "wof:placetype":"venue"
},
  "geometry": {"coordinates":[2.6382129192,41.7458610535],"type":"Point"}
}