{
  "type": "Feature",
  "properties": {
    "iso:country":"ES",
    "sg:address":"Calle de Jose Del Hierro, 48",
    "sg:city":"Madrid",
    "sg:orig_category":"Peluqueros: De Se\u00d1oras",
    "sg:phone":"+34 913 67 90 86",
    "sg:postcode":"28027",
    "sg:province":"Madrid",
    "wof:name":"Instituto De Belleza Kares S.l",
    "wof:placetype":"venue"
},
  "geometry": {"coordinates":[-3.6448020935,40.439704895],"type":"Point"}
}