{
  "type": "Feature",
  "properties": {
    "addr:full":"Calle de Concepcion, 2 Zeneta Murcia 30588",
    "addr:postcode":"30588",
    "addr:street":"Calle De Concepcion",
    "iso:country":"ES",
    "sg:address":"Calle de Concepcion, 2",
    "sg:city":"Zeneta",
    "sg:orig_category":"Iglesia Cat\u00d3lica",
    "sg:phone":"+34 968 85 43 01",
    "sg:postcode":"30588",
    "sg:province":"Murcia",
    "wof:name":"Obispado De Cartagena",
    "wof:placetype":"venue"
},
  "geometry": {"coordinates":[-0.9965599775,38.0111503601],"type":"Point"}
}