{
  "type": "Feature",
  "properties": {
    "addr:full":"Calle de Don Gumersindo Diaz Cordoves, 13 Consuegra Toledo 45700",
    "addr:housenumber":"13",
    "addr:postcode":"45700",
    "addr:street":"Calle De Don Gumersindo Diaz Cordoves",
    "iso:country":"ES",
    "sg:address":"Calle de Don Gumersindo Diaz Cordoves, 13",
    "sg:city":"Consuegra",
    "sg:orig_category":"Productores Recolectores, Venta Directa De Vinos",
    "sg:phone":"+34 925 48 00 38",
    "sg:postcode":"45700",
    "sg:province":"Toledo",
    "wof:name":"Casanova Garcia Marcelino",
    "wof:placetype":"venue"
},
  "geometry": {"coordinates":[-3.6059982777,39.4608039856],"type":"Point"}
}