{
  "type": "Feature",
  "properties": {
    "addr:full":"Bo Fatima, S/n Daimus Valencia 46710",
    "addr:postcode":"46710",
    "addr:street":"S / N",
    "iso:country":"ES",
    "sg:address":"Bo Fatima, S/n",
    "sg:city":"Daimus",
    "sg:orig_category":"Marroquiner\u00cda (confecci\u00d3n)",
    "sg:phone":"+34 962 81 93 16",
    "sg:postcode":"46710",
    "sg:province":"Valencia",
    "wof:name":"Ruiz Villar Buenaventura",
    "wof:placetype":"venue"
},
  "geometry": {"coordinates":[-0.1430740058,38.9734954834],"type":"Point"}
}