{
  "type": "Feature",
  "properties": {
    "addr:full":"Carrer de Rossello, 69 Granollers Barcelona 08401",
    "addr:housenumber":"69",
    "addr:postcode":"08401",
    "addr:street":"Carrer De Rossello",
    "iso:country":"ES",
    "sg:address":"Carrer de Rossello, 69",
    "sg:city":"Granollers",
    "sg:orig_category":"Pescader\u00cdas (al Por Menor)",
    "sg:phone":"+34 938 46 68 17",
    "sg:postcode":"08401",
    "sg:province":"Barcelona",
    "wof:name":"Peixos Martinez Costan Scp",
    "wof:placetype":"venue"
},
  "geometry": {"coordinates":[2.2893550396,41.6168556213],"type":"Point"}
}