{
  "type": "Feature",
  "properties": {
    "addr:full":"Calle de Santa Maria Soledad, 13 Cadiz C\u00e1diz 11008",
    "addr:housenumber":"13",
    "addr:postcode":"11008",
    "addr:street":"Calle De Santa;Soledad",
    "iso:country":"ES",
    "sg:address":"Calle de Santa Maria Soledad, 13",
    "sg:city":"Cadiz",
    "sg:orig_category":"Arquitectos",
    "sg:phone":"+34 956 20 00 61",
    "sg:postcode":"11008",
    "sg:province":"C\u00e1diz",
    "wof:name":"Gumersindo Fernandez Arquitectos S,l.",
    "wof:placetype":"venue"
},
  "geometry": {"coordinates":[-6.2863688469,36.5214920044],"type":"Point"}
}