{
  "type": "Feature",
  "properties": {
    "iso:country":"ES",
    "sg:address":"Carrer de Mare Eterna, 15",
    "sg:city":"Barcelona",
    "sg:orig_category":"Peluquer\u00cdas, Peluquer\u00cda Mixta",
    "sg:phone":"+34 932 78 27 62",
    "sg:postcode":"08030",
    "sg:province":"Barcelona",
    "wof:name":"Olorons De Dios Elena",
    "wof:placetype":"venue"
},
  "geometry": {"coordinates":[2.2040801048,41.434803009],"type":"Point"}
}