{
  "type": "Feature",
  "properties": {
    "addr:full":"Calle de Marques De Nervion, 91 Sevilla Sevilla 41005",
    "addr:housenumber":"91",
    "addr:postcode":"41005",
    "addr:street":"Calle De Marques De Nervion",
    "iso:country":"ES",
    "sg:address":"Calle de Marques De Nervion, 91",
    "sg:city":"Sevilla",
    "sg:orig_category":"Farmacias",
    "sg:phone":"+34 954 92 44 22",
    "sg:postcode":"41005",
    "sg:province":"Sevilla",
    "wof:name":"Farmacia Prensa C.b.",
    "wof:placetype":"venue"
},
  "geometry": {"coordinates":[-5.9690499306,37.3780441284],"type":"Point"}
}