{
  "type": "Feature",
  "properties": {
    "addr:full":"Eliz Kalea, 1 Azpeitia Guip\u00f9zcoa 20730",
    "addr:housenumber":"1",
    "addr:postcode":"20730",
    "addr:street":"Eliz Kalea;Guipu\u0300Zcoa",
    "iso:country":"ES",
    "sg:address":"Eliz Kalea, 1",
    "sg:city":"Azpeitia",
    "sg:orig_category":"Pintura Y Barniz (al Por Menor)",
    "sg:phone":"+34 943 81 22 68",
    "sg:postcode":"20730",
    "sg:province":"Guip\u00f9zcoa",
    "wof:name":"Odriozola Azpiazu S.l.",
    "wof:placetype":"venue"
},
  "geometry": {"coordinates":[-2.2656280994,43.1842269897],"type":"Point"}
}