{
  "type": "Feature",
  "properties": {
    "iso:country":"ES",
    "sg:address":"Calle de Rubi, S/n",
    "sg:city":"Cordoba",
    "sg:orig_category":"Contenedores (mercanc\u00cdas)",
    "sg:phone":"+34 957 25 13 89",
    "sg:postcode":"14014",
    "sg:province":"C\u00f3rdoba",
    "wof:name":"Christian Salvensen Gerposa S.a.",
    "wof:placetype":"venue"
},
  "geometry": {"coordinates":[-4.7497739792,37.8902740479],"type":"Point"}
}