{
  "type": "Feature",
  "properties": {
    "addr:full":"Calle de Carmelo Betore Bergua, 2 Zaragoza Zaragoza 50014",
    "addr:housenumber":"2",
    "addr:postcode":"50014",
    "addr:street":"Calle De Carmelo Betore Bergua",
    "iso:country":"ES",
    "sg:address":"Calle de Carmelo Betore Bergua, 2",
    "sg:city":"Zaragoza",
    "sg:orig_category":"Farmacias",
    "sg:phone":"+34 976 39 86 76",
    "sg:postcode":"50014",
    "sg:province":"Zaragoza",
    "wof:name":"Navarro Jimenez Felix",
    "wof:placetype":"venue"
},
  "geometry": {"coordinates":[-0.8583052158,41.6554222107],"type":"Point"}
}