{
  "type": "Feature",
  "properties": {
    "iso:country":"ES",
    "sg:address":"Carrer de Sant Pau, 6",
    "sg:city":"Terrassa",
    "sg:orig_category":"Asesor\u00cda Sobre Comunicaci\u00d3n De Empresas",
    "sg:phone":"+34 937 85 30 30",
    "sg:postcode":"08221",
    "sg:province":"Barcelona",
    "wof:name":"Institut Industrial S.l.",
    "wof:placetype":"venue"
},
  "geometry": {"coordinates":[2.013833046,41.5637512207],"type":"Point"}
}