{
  "type": "Feature",
  "properties": {
    "iso:country":"ES",
    "sg:address":"Calle de Marques De Larios, 7",
    "sg:city":"Malaga",
    "sg:orig_category":"Bisuter\u00cda, Joyer\u00cda, Relojer\u00cda (al Por Menor)",
    "sg:phone":"+34 952 22 58 84",
    "sg:postcode":"29015",
    "sg:province":"M\u00e1laga",
    "wof:name":"Fernando Joyeros S.cv.",
    "wof:placetype":"venue"
},
  "geometry": {"coordinates":[-4.4213838577,36.7190895081],"type":"Point"}
}