{
  "type": "Feature",
  "properties": {
    "addr:full":"Calle de Bailen, 11 Madrid Madrid 28013",
    "addr:housenumber":"11",
    "addr:postcode":"madrid;28013",
    "addr:street":"Calle De Bailen",
    "iso:country":"ES",
    "sg:address":"Calle de Bailen, 11",
    "sg:city":"Madrid",
    "sg:orig_category":"Tapiceros Y Tapiceros",
    "sg:phone":"+34 915 59 48 08",
    "sg:postcode":"28013",
    "sg:province":"Madrid",
    "wof:name":"Uno-uno Proyectos De Arquitectura Interior S.l.",
    "wof:placetype":"venue"
},
  "geometry": {"coordinates":[-3.7128889561,40.4203186035],"type":"Point"}
}