{
  "type": "Feature",
  "properties": {
    "addr:full":"Calle de Fernan Gonzalez, 27 Aranda Duero Burgos 09400",
    "addr:housenumber":"27",
    "addr:postcode":"09400",
    "addr:street":"Calle De Fernan Gonzalez",
    "iso:country":"ES",
    "sg:address":"Calle de Fernan Gonzalez, 27",
    "sg:city":"Aranda Duero",
    "sg:orig_category":"Art\u00cdculos De Decoraci\u00d3n",
    "sg:phone":"+34 947 50 65 35",
    "sg:postcode":"09400",
    "sg:province":"Burgos",
    "wof:name":"Gonzalez Castrillo Tomas",
    "wof:placetype":"venue"
},
  "geometry": {"coordinates":[-3.6768980026,41.6716766357],"type":"Point"}
}