{
  "type": "Feature",
  "properties": {
    "iso:country":"ES",
    "sg:address":"Pla\u00c7 Turers, 11",
    "sg:city":"Banyoles",
    "sg:orig_category":"Lencer\u00cda Femenina, Corseter\u00cda, Trajes De Ba\u00d1o (al Por Menor)",
    "sg:phone":"+34 972 57 54 76",
    "sg:postcode":"17820",
    "sg:province":"Girona",
    "wof:name":"Ribas Badosa Concha",
    "wof:placetype":"venue"
},
  "geometry": {"coordinates":[2.7649800777,42.1169548035],"type":"Point"}
}