{
  "type": "Feature",
  "properties": {
    "addr:full":"Calle de Baldomero Villegas, 36 Santo\u00f1a Cantabria 39740",
    "addr:housenumber":"36",
    "addr:postcode":"39740",
    "addr:street":"Calle De Baldomero Villegas",
    "iso:country":"ES",
    "sg:address":"Calle de Baldomero Villegas, 36",
    "sg:city":"Santo\u00f1a",
    "sg:orig_category":"Cajas Y Embalajes Met\u00c1licos",
    "sg:phone":"+34 942 67 11 11",
    "sg:postcode":"39740",
    "sg:province":"Cantabria",
    "sg:website":"www.emecansa.com",
    "wof:name":"Estampaciones Metalicas Del Cantabrico S.a.",
    "wof:placetype":"venue"
},
  "geometry": {"coordinates":[-3.4595649242,43.4458808899],"type":"Point"}
}