{
  "type": "Feature",
  "properties": {
    "iso:country":"ES",
    "sg:address":"Via Edison (de), 1",
    "sg:city":"Boisaca",
    "sg:orig_category":"Centros Empresariales",
    "sg:phone":"+34 981 55 28 50",
    "sg:postcode":"15890",
    "sg:province":"La Coru\u00f1a",
    "wof:name":"Asociacion De Empresarios Del Poligono Industrial Del Tambre",
    "wof:placetype":"venue"
},
  "geometry": {"coordinates":[-8.3959693909,43.3714904785],"type":"Point"}
}