{
  "type": "Feature",
  "properties": {
    "addr:full":"Calle de Alcalde Suarez Franchy, 19 Arucas Las Palmas 35400",
    "addr:housenumber":"19",
    "addr:postcode":"35400",
    "addr:street":"Calle De Alcalde Suarez Franchy",
    "iso:country":"ES",
    "sg:address":"Calle de Alcalde Suarez Franchy, 19",
    "sg:city":"Arucas",
    "sg:orig_category":"Farmacias",
    "sg:phone":"+34 928 60 14 91",
    "sg:postcode":"35400",
    "sg:province":"Las Palmas",
    "wof:name":"Perez Santana Moises",
    "wof:placetype":"venue"
},
  "geometry": {"coordinates":[-15.5246744156,28.1181297302],"type":"Point"}
}