{
  "type": "Feature",
  "properties": {
    "addr:full":"Carr Sant Jordi, 7 Mao Islas Baleares 07702",
    "addr:housenumber":"7",
    "addr:postcode":"07702",
    "addr:street":"Carr Sant Jordi",
    "iso:country":"ES",
    "sg:address":"Carr Sant Jordi, 7",
    "sg:city":"Mao",
    "sg:orig_category":"Institutos De Belleza",
    "sg:phone":"+34 971 35 19 61",
    "sg:postcode":"07702",
    "sg:province":"Islas Baleares",
    "wof:name":"Rada Pino Josefa",
    "wof:placetype":"venue"
},
  "geometry": {"coordinates":[4.2629928589,39.8879127502],"type":"Point"}
}