{
  "type": "Feature",
  "properties": {
    "addr:full":"Calle de Isabelita Usera, 41 Madrid Madrid 28026",
    "addr:housenumber":"41",
    "addr:postcode":"madrid;28026",
    "addr:street":"Calle De Isabelita Usera",
    "iso:country":"ES",
    "sg:address":"Calle de Isabelita Usera, 41",
    "sg:city":"Madrid",
    "sg:orig_category":"Papeler\u00cdas, Librer\u00cdas",
    "sg:phone":"+34 914 75 49 49",
    "sg:postcode":"28026",
    "sg:province":"Madrid",
    "wof:name":"Herrero Cavero Jose",
    "wof:placetype":"venue"
},
  "geometry": {"coordinates":[-3.707556963,40.3825302124],"type":"Point"}
}