{
  "type": "Feature",
  "properties": {
    "iso:country":"ES",
    "sg:address":"Carr Catalunya, 27",
    "sg:city":"Vidreres",
    "sg:orig_category":"Distribuci\u00d3n De Petr\u00d3leo Y Derivados",
    "sg:phone":"+34 972 85 12 00",
    "sg:postcode":"17411",
    "sg:province":"Girona",
    "wof:name":"Moner Llora Ramon",
    "wof:placetype":"venue"
},
  "geometry": {"coordinates":[2.7802190781,41.7896766663],"type":"Point"}
}