{
  "type": "Feature",
  "properties": {
    "addr:full":"Pase Padre Orkolaga, 44 Igeldo Guip\u00f9zcoa 20008",
    "addr:housenumber":"44",
    "addr:postcode":"20008",
    "addr:street":"Orkolaga;Guipu\u0300Zcoa",
    "iso:country":"ES",
    "sg:address":"Pase Padre Orkolaga, 44",
    "sg:city":"Igeldo",
    "sg:orig_category":"Estaciones Y Oficinas De Meteorolog\u00cda",
    "sg:phone":"+34 943 21 07 59",
    "sg:postcode":"20008",
    "sg:province":"Guip\u00f9zcoa",
    "sg:website":"www.inm.es",
    "wof:name":"Direccion General Del Instituto Nacional De Meteorologia",
    "wof:placetype":"venue"
},
  "geometry": {"coordinates":[-2.0392899513,43.3088798523],"type":"Point"}
}