{
  "type": "Feature",
  "properties": {
    "iso:country":"ES",
    "sg:address":"Catorce C, 2",
    "sg:city":"Nueva Andalucia",
    "sg:orig_category":"Contenedores (mercanc\u00cdas)",
    "sg:phone":"+34 952 81 00 14",
    "sg:postcode":"29660",
    "sg:province":"M\u00e1laga",
    "wof:name":"Montano Zarco Diego",
    "wof:placetype":"venue"
},
  "geometry": {"coordinates":[-4.9540901184,36.4891586304],"type":"Point"}
}