{
  "type": "Feature",
  "properties": {
    "iso:country":"ES",
    "sg:address":"Ctra. Vilobi, Km. 0001,0",
    "sg:city":"Vilobi Onyar",
    "sg:orig_category":"Contenedores (mercanc\u00cdas)",
    "sg:phone":"+34 972 47 45 44",
    "sg:postcode":"17185",
    "sg:province":"Girona",
    "wof:name":"Airtir-trans S.l.",
    "wof:placetype":"venue"
},
  "geometry": {"coordinates":[2.7387294769,41.8752365112],"type":"Point"}
}