{
  "type": "Feature",
  "properties": {
    "iso:country":"ES",
    "sg:address":"Calle de Candelaria, 9",
    "sg:city":"Cordoba",
    "sg:orig_category":"Discapacitados",
    "sg:phone":"+34 957 48 34 53",
    "sg:postcode":"14002",
    "sg:province":"C\u00f3rdoba",
    "wof:name":"Hogar Frater S.l.",
    "wof:placetype":"venue"
},
  "geometry": {"coordinates":[-4.773730278,37.8819465637],"type":"Point"}
}