{
  "type": "Feature",
  "properties": {
    "iso:country":"ES",
    "sg:address":"Carrer de Joan Estelrich Art, 41",
    "sg:city":"Palma",
    "sg:orig_category":"Empresas De Carpinter\u00cda De Madera",
    "sg:phone":"+34 971 47 21 00",
    "sg:postcode":"07008",
    "sg:province":"Islas Baleares",
    "wof:name":"Costa Ferrer Florencio",
    "wof:placetype":"venue"
},
  "geometry": {"coordinates":[2.6766119003,39.5824279785],"type":"Point"}
}