{
  "type": "Feature",
  "properties": {
    "iso:country":"ES",
    "sg:address":"Calle de Huerta Camara, S/n",
    "sg:city":"Barcarrota",
    "sg:orig_category":"Cooperativas Agr\u00cdcolas",
    "sg:phone":"+34 924 73 60 55",
    "sg:postcode":"06160",
    "sg:province":"Badajoz",
    "wof:name":"Videlso Sociedad Cooperativa Limitada De Trabajo Asociado",
    "wof:placetype":"venue"
},
  "geometry": {"coordinates":[-6.8528189659,38.5205001831],"type":"Point"}
}