{
  "type": "Feature",
  "properties": {
    "addr:full":"Calle de Azafranales, 1 Coca Segovia 40480",
    "addr:housenumber":"1",
    "addr:postcode":"40480",
    "addr:street":"Calle De Azafranales",
    "iso:country":"ES",
    "sg:address":"Calle de Azafranales, 1",
    "sg:city":"Coca",
    "sg:orig_category":"Escayola Y Productos De Escayola (fabricaci\u00d3n, Al Por Mayor)",
    "sg:phone":"+34 921 58 61 16",
    "sg:postcode":"40480",
    "sg:province":"Segovia",
    "wof:name":"Sanz Alvarez Jose Manuel",
    "wof:placetype":"venue"
},
  "geometry": {"coordinates":[-4.5216941833,41.2152137756],"type":"Point"}
}