{
  "type": "Feature",
  "properties": {
    "addr:full":"Calle de Angel, 42 Camas Sevilla 41900",
    "addr:housenumber":"42",
    "addr:postcode":"41900",
    "addr:street":"Calle De Angel",
    "iso:country":"ES",
    "sg:address":"Calle de Angel, 42",
    "sg:city":"Camas",
    "sg:orig_category":"Transportes Por V\u00cdas Navegables",
    "sg:phone":"+34 954 39 32 66",
    "sg:postcode":"41900",
    "sg:province":"Sevilla",
    "wof:name":"Garcia Asensio Maximino",
    "wof:placetype":"venue"
},
  "geometry": {"coordinates":[-6.0346798897,37.4041252136],"type":"Point"}
}