{
  "type": "Feature",
  "properties": {
    "iso:country":"ES",
    "sg:address":"Calle de Garcia Alix, 10",
    "sg:city":"San Antolin",
    "sg:orig_category":"Ropa Para Se\u00d1oras Y Caballeros (al Por Menor)",
    "sg:phone":"+34 968 29 32 05",
    "sg:postcode":"30005",
    "sg:province":"Murcia",
    "wof:name":"Martinez Blaquez Pedro",
    "wof:placetype":"venue"
},
  "geometry": {"coordinates":[-1.1376780272,37.9858207703],"type":"Point"}
}