{
  "type": "Feature",
  "properties": {
    "iso:country":"ES",
    "sg:address":"Calle de Finlandia, 10",
    "sg:city":"Almoradi",
    "sg:orig_category":"Contenedores (mercanc\u00cdas)",
    "sg:phone":"+34 965 70 26 51",
    "sg:postcode":"03160",
    "sg:province":"Alicante",
    "wof:name":"Promociones Y Proyectos Jecarmi Sl",
    "wof:placetype":"venue"
},
  "geometry": {"coordinates":[-0.796472013,38.0980606079],"type":"Point"}
}