{
  "type": "Feature",
  "properties": {
    "iso:country":"ES",
    "sg:address":"G.v. Corts Catalanes, 608",
    "sg:city":"Barcelona",
    "sg:orig_category":"Ense\u00d1ante, Direcci\u00d3n",
    "sg:phone":"+34 933 01 08 28",
    "sg:postcode":"08007",
    "sg:province":"Barcelona",
    "wof:name":"Associacio Per A La Difusio De La Cultura Popular En El Sector Turistic",
    "wof:placetype":"venue"
},
  "geometry": {"coordinates":[2.165694952,41.3872184753],"type":"Point"}
}