{
  "type": "Feature",
  "properties": {
    "addr:full":"Avda Miramar, 14 S. Vicente Barquera Cantabria 39540",
    "addr:housenumber":"14",
    "addr:postcode":"39540",
    "addr:street":"Avda Miramar;S. Vicente",
    "iso:country":"ES",
    "sg:address":"Avda Miramar, 14",
    "sg:city":"S. Vicente Barquera",
    "sg:orig_category":"Fotograf\u00cda Y Cine: Aparatos, Pel\u00cdculas Y Accesorios (fabricaci\u00d3n, Al Por Mayor)",
    "sg:phone":"+34 942 71 07 35",
    "sg:postcode":"39540",
    "sg:province":"Cantabria",
    "wof:name":"Garcia Ortega Angel",
    "wof:placetype":"venue"
},
  "geometry": {"coordinates":[-4.3975257874,43.3819084167],"type":"Point"}
}