{
  "type": "Feature",
  "properties": {
    "iso:country":"ES",
    "sg:address":"Calle de Pinto, 15",
    "sg:city":"Parla",
    "sg:orig_category":"Carnicer\u00cdas, Carnicer\u00cdas",
    "sg:phone":"+34 916 99 33 63",
    "sg:postcode":"28980",
    "sg:province":"Madrid",
    "wof:name":"Martinez Alcazar Jesus",
    "wof:placetype":"venue"
},
  "geometry": {"coordinates":[-3.7687904835,40.2387390137],"type":"Point"}
}