{
  "type": "Feature",
  "properties": {
    "addr:full":"Avda Maria Auxiliadora (de), 35 Montilla C\u00f3rdoba 14550",
    "addr:housenumber":"35",
    "addr:postcode":"14550",
    "addr:street":"Avda Maria Auxiliadora De;Co\u0301Rdoba",
    "iso:country":"ES",
    "sg:address":"Avda Maria Auxiliadora (de), 35",
    "sg:city":"Montilla",
    "sg:orig_category":"Agencias De Viajes",
    "sg:phone":"+34 957 66 40 13",
    "sg:postcode":"14550",
    "sg:province":"C\u00f3rdoba",
    "wof:name":"Reina Tour Cordoba Vision S.l.",
    "wof:placetype":"venue"
},
  "geometry": {"coordinates":[-4.64498806,37.580116272],"type":"Point"}
}