{
  "type": "Feature",
  "properties": {
    "addr:full":"Urb Diaz Casanova, 13 Palmas De Gran Canaria Las Palmas 35010",
    "addr:housenumber":"13",
    "addr:postcode":"35010",
    "addr:street":"Urb Diaz Casanova",
    "iso:country":"ES",
    "sg:address":"Urb Diaz Casanova, 13",
    "sg:city":"Palmas De Gran Canaria",
    "sg:orig_category":"Empresas De Trabajos P\u00dablicos",
    "sg:phone":"+34 928 49 26 40",
    "sg:postcode":"35010",
    "sg:province":"Las Palmas",
    "wof:name":"Compa\u00f1ia Canaria De Piensos S. A.",
    "wof:placetype":"venue"
},
  "geometry": {"coordinates":[-15.4397087097,28.1302242279],"type":"Point"}
}