{
  "type": "Feature",
  "properties": {
    "iso:country":"ES",
    "sg:address":"Calle de Ferraz, 61",
    "sg:city":"Madrid",
    "sg:orig_category":"Peluqueros: De Se\u00d1oras",
    "sg:phone":"+34 915 44 12 20",
    "sg:postcode":"28008",
    "sg:province":"Madrid",
    "wof:name":"Rodriguez Martinez Antonio",
    "wof:placetype":"venue"
},
  "geometry": {"coordinates":[-3.7216389179,40.4304161072],"type":"Point"}
}