{
  "type": "Feature",
  "properties": {
    "addr:full":"Carrer de Chopin, 10 Santa Pon\u00c7a Islas Baleares 07180",
    "addr:housenumber":"10",
    "addr:postcode":"07180",
    "addr:street":"Carrer De Chopin",
    "iso:country":"ES",
    "sg:address":"Carrer de Chopin, 10",
    "sg:city":"Santa Pon\u00c7a",
    "sg:orig_category":"Inmobiliaria (agencias)",
    "sg:phone":"+34 971 12 60 75",
    "sg:postcode":"07180",
    "sg:province":"Islas Baleares",
    "wof:name":"Punta Des Pi S.l.",
    "wof:placetype":"venue"
},
  "geometry": {"coordinates":[2.475935936,39.4959182739],"type":"Point"}
}