{
  "type": "Feature",
  "properties": {
    "addr:full":"Calle de Gaztelu, 5 Donostia-san Sebastian Guip\u00f9zcoa 20013",
    "addr:housenumber":"5",
    "addr:postcode":"20013",
    "addr:street":"Calle De Gaztelu",
    "iso:country":"ES",
    "sg:address":"Calle de Gaztelu, 5",
    "sg:city":"Donostia-san Sebastian",
    "sg:orig_category":"Talleres De Corte Y Confecci\u00d3n",
    "sg:phone":"+34 943 27 82 04",
    "sg:postcode":"20013",
    "sg:province":"Guip\u00f9zcoa",
    "wof:name":"Alejos Martin Maria Luz",
    "wof:placetype":"venue"
},
  "geometry": {"coordinates":[-1.9576083422,43.3186912537],"type":"Point"}
}