{
  "type": "Feature",
  "properties": {
    "addr:full":"Calle de Imeldo Seris, 50 Santa Cruz De Tenerife Santa Cruz De Tenerife 38003",
    "addr:housenumber":"50",
    "addr:postcode":"38003",
    "addr:street":"Calle De Imeldo Seris",
    "iso:country":"ES",
    "sg:address":"Calle de Imeldo Seris, 50",
    "sg:city":"Santa Cruz De Tenerife",
    "sg:orig_category":"Asociaciones Y Clubs Deportivos",
    "sg:phone":"+34 922 24 49 19",
    "sg:postcode":"38003",
    "sg:province":"Santa Cruz De Tenerife",
    "wof:name":"Arranz Carrascal Alejandro",
    "wof:placetype":"venue"
},
  "geometry": {"coordinates":[-16.250951767,28.4662704468],"type":"Point"}
}