{
  "type": "Feature",
  "properties": {
    "iso:country":"ES",
    "sg:address":"Avda Tecnica (de La), 4",
    "sg:city":"Azuqueca Henares",
    "sg:orig_category":"Guarder\u00cdas",
    "sg:phone":"+34 949 26 49 49",
    "sg:postcode":"19200",
    "sg:province":"Guadalajara",
    "wof:name":"Barcena Ordierez Lidia",
    "wof:placetype":"venue"
},
  "geometry": {"coordinates":[-3.2643489838,40.5579986572],"type":"Point"}
}