{
  "type": "Feature",
  "properties": {
    "addr:full":"Ctra Madrid-coru\u00d1a, Km. 0326,0 Astorga Le\u00f3n 24700",
    "addr:postcode":"24700",
    "addr:street":"Ctra Madrid-Corun\u0303A Km. 0326,0;Leo\u0301N",
    "iso:country":"ES",
    "sg:address":"Ctra Madrid-coru\u00d1a, Km. 0326,0",
    "sg:city":"Astorga",
    "sg:orig_category":"Mec\u00c1nico Del Autom\u00d3vil",
    "sg:phone":"+34 987 60 24 41",
    "sg:postcode":"24700",
    "sg:province":"Le\u00f3n",
    "wof:name":"Talleres Mecanicos Unidos, S.l.",
    "wof:placetype":"venue"
},
  "geometry": {"coordinates":[-6.0637350082,42.4592437744],"type":"Point"}
}