{
  "type": "Feature",
  "properties": {
    "iso:country":"ES",
    "sg:address":"Calle de Guatemala, 4",
    "sg:city":"Vitoria-gasteiz",
    "sg:orig_category":"Venta, Instalaci\u00d3n De Calefacci\u00d3n",
    "sg:phone":"+34 945 12 28 23",
    "sg:postcode":"01012",
    "sg:province":"\u00c1lava",
    "wof:name":"Giroa S.a.",
    "wof:placetype":"venue"
},
  "geometry": {"coordinates":[-2.6775500774,42.8551483154],"type":"Point"}
}