{
  "type": "Feature",
  "properties": {
    "addr:full":"Carrer de Estel (l'), 38 Amposta Tarragona 43870",
    "addr:housenumber":"38",
    "addr:postcode":"43870",
    "addr:street":"Carrer De Estel L '",
    "iso:country":"ES",
    "sg:address":"Carrer de Estel (l'), 38",
    "sg:city":"Amposta",
    "sg:orig_category":"Ropa Para Se\u00d1oras Y Caballeros (al Por Menor)",
    "sg:phone":"+34 977 70 38 74",
    "sg:postcode":"43870",
    "sg:province":"Tarragona",
    "wof:name":"Armengol Estorach Jose Luis",
    "wof:placetype":"venue"
},
  "geometry": {"coordinates":[0.6298921704,40.683719635],"type":"Point"}
}