{
  "type": "Feature",
  "properties": {
    "iso:country":"ES",
    "sg:address":"Av Portell De Granyana, 6",
    "sg:city":"Elche",
    "sg:orig_category":"Abogados",
    "sg:phone":"+34 965 45 70 41",
    "sg:postcode":"03202",
    "sg:province":"Alicante",
    "wof:name":"Casta\u00f1o Garcia Juan Bautista",
    "wof:placetype":"venue"
},
  "geometry": {"coordinates":[-0.6963589787,38.2682762146],"type":"Point"}
}