{
  "type": "Feature",
  "properties": {
    "addr:full":"Calle de San Lazaro, 1 Valladolid Valladolid 47009",
    "addr:housenumber":"1",
    "addr:postcode":"47009",
    "addr:street":"Calle De San Lazaro",
    "iso:country":"ES",
    "sg:address":"Calle de San Lazaro, 1",
    "sg:city":"Valladolid",
    "sg:orig_category":"Molduras, Junquillos, Listones Y Molduras Perforadas",
    "sg:phone":"+34 983 35 63 59",
    "sg:postcode":"47009",
    "sg:province":"Valladolid",
    "wof:name":"Bermejo Gonzalez Julio",
    "wof:placetype":"venue"
},
  "geometry": {"coordinates":[-4.7330441475,41.6620597839],"type":"Point"}
}