{
  "type": "Feature",
  "properties": {
    "iso:country":"ES",
    "sg:address":"Carr Del Dos De Maig, 31",
    "sg:city":"Ontinyent",
    "sg:orig_category":"Promotores Constructores",
    "sg:phone":"+34 962 38 03 90",
    "sg:postcode":"46870",
    "sg:province":"Valencia",
    "wof:name":"Sucesores De Bautista Chafer S.l.",
    "wof:placetype":"venue"
},
  "geometry": {"coordinates":[-0.603745997,38.8245506287],"type":"Point"}
}