{
  "type": "Feature",
  "properties": {
    "addr:full":"Calle de Juan Canalejo, 71 Coru\u00d1a La Coru\u00f1a 15003",
    "addr:housenumber":"71",
    "addr:postcode":"15003",
    "addr:street":"Calle De Juan Canalejo;Corun\u0303A",
    "iso:country":"ES",
    "sg:address":"Calle de Juan Canalejo, 71",
    "sg:city":"Coru\u00d1a",
    "sg:orig_category":"Centros De Coordinaci\u00d3n",
    "sg:phone":"+34 981 22 24 33",
    "sg:postcode":"15003",
    "sg:province":"La Coru\u00f1a",
    "wof:name":"Marti Mendez Enrique",
    "wof:placetype":"venue"
},
  "geometry": {"coordinates":[-8.4042005539,43.370639801],"type":"Point"}
}