{
  "type": "Feature",
  "properties": {
    "addr:full":"Calle de Vigia, 2 Coru\u00d1a La Coru\u00f1a 15002",
    "addr:housenumber":"2",
    "addr:postcode":"15002",
    "addr:street":"Calle De Vigia;La Corun\u0303A",
    "iso:country":"ES",
    "sg:address":"Calle de Vigia, 2",
    "sg:city":"Coru\u00d1a",
    "sg:orig_category":"Marketing Directo",
    "sg:phone":"+34 981 21 00 09",
    "sg:postcode":"15002",
    "sg:province":"La Coru\u00f1a",
    "wof:name":"Informarket Sistemas De Gestion S.l.",
    "wof:placetype":"venue"
},
  "geometry": {"coordinates":[-8.4043836594,43.379196167],"type":"Point"}
}