{
  "type": "Feature",
  "properties": {
    "addr:full":"Avda Salazar Y Torres, 2 Almazan Soria 42200",
    "addr:housenumber":"2",
    "addr:postcode":"42200",
    "addr:street":"Avda Salazar Y Torres",
    "iso:country":"ES",
    "sg:address":"Avda Salazar Y Torres, 2",
    "sg:city":"Almazan",
    "sg:orig_category":"Cajas De Ahorro",
    "sg:phone":"+34 975 30 13 13",
    "sg:postcode":"42200",
    "sg:province":"Soria",
    "sg:website":"www.lacaixa.es",
    "wof:name":"Caixa D'estalvis I Pensions De Barcelona",
    "wof:placetype":"venue"
},
  "geometry": {"coordinates":[-2.5310590267,41.4851379395],"type":"Point"}
}