{
  "type": "Feature",
  "properties": {
    "iso:country":"ES",
    "sg:address":"Avda Coru\u00d1a (da), 6",
    "sg:city":"Santiago De Compostela",
    "sg:orig_category":"Ingenier\u00cda, Centros De Estudios (diversos)",
    "sg:phone":"+34 981 58 08 48",
    "sg:postcode":"15706",
    "sg:province":"La Coru\u00f1a",
    "wof:name":"Rey Lama Gonzalo",
    "wof:placetype":"venue"
},
  "geometry": {"coordinates":[-8.5504713058,42.8758049011],"type":"Point"}
}