{
  "type": "Feature",
  "properties": {
    "iso:country":"ES",
    "sg:address":"Calle de Fragata Cervantes, 26",
    "sg:city":"Calahonda",
    "sg:orig_category":"Administradores De Bienes Y Delegados De Comunidades De Propietarios",
    "sg:phone":"+34 958 62 39 56",
    "sg:postcode":"18730",
    "sg:province":"Granada",
    "wof:name":"Dawid Milner Jose Miguel",
    "wof:placetype":"venue"
},
  "geometry": {"coordinates":[-3.4161479473,36.7013244629],"type":"Point"}
}