{
  "type": "Feature",
  "properties": {
    "addr:full":"Plaz Santa Barbara, 4 Vitoria-gasteiz \u00c1lava 01004",
    "addr:housenumber":"4",
    "addr:postcode":"01004",
    "addr:street":"Santa Barbara",
    "iso:country":"ES",
    "sg:address":"Plaz Santa Barbara, 4",
    "sg:city":"Vitoria-gasteiz",
    "sg:orig_category":"Radiocomunicaciones, Telefon\u00cda M\u00d3vil, Radiomensajer\u00cda: Servicios, Comercializaci\u00d3n",
    "sg:phone":"+34 945 12 21 09",
    "sg:postcode":"01004",
    "sg:province":"\u00c1lava",
    "wof:name":"Globamas, S.l.",
    "wof:placetype":"venue"
},
  "geometry": {"coordinates":[-2.6661159992,42.8447685242],"type":"Point"}
}