{
  "type": "Feature",
  "properties": {
    "iso:country":"ES",
    "sg:address":"Calle de Alonso Perez Diaz, 5",
    "sg:city":"Sauces",
    "sg:orig_category":"Inmobiliaria (agencias)",
    "sg:phone":"+34 922 45 12 86",
    "sg:postcode":"38720",
    "sg:province":"Santa Cruz De Tenerife",
    "wof:name":"Marasangil S.l.",
    "wof:placetype":"venue"
},
  "geometry": {"coordinates":[-17.7742061615,28.8036022186],"type":"Point"}
}