{
  "type": "Feature",
  "properties": {
    "addr:full":"Carr Caputxins, 46 Vilanova I La Geltru Barcelona 08800",
    "addr:housenumber":"46",
    "addr:postcode":"08800",
    "addr:street":"Carr Caputxins",
    "iso:country":"ES",
    "sg:address":"Carr Caputxins, 46",
    "sg:city":"Vilanova I La Geltru",
    "sg:orig_category":"Ropa Para Caballeros (al Por Menor)",
    "sg:phone":"+34 938 93 08 41",
    "sg:postcode":"08800",
    "sg:province":"Barcelona",
    "wof:name":"Guarch S.l.",
    "wof:placetype":"venue"
},
  "geometry": {"coordinates":[1.7258720398,41.2250976562],"type":"Point"}
}