{
  "type": "Feature",
  "properties": {
    "addr:full":"Calle de Venezuela, 32 Valencia Valencia 46007",
    "addr:housenumber":"32",
    "addr:postcode":"46007",
    "addr:street":"Calle De Venezuela",
    "iso:country":"ES",
    "sg:address":"Calle de Venezuela, 32",
    "sg:city":"Valencia",
    "sg:orig_category":"Suministros Para Hoteles",
    "sg:phone":"+34 963 58 12 71",
    "sg:postcode":"46007",
    "sg:province":"Valencia",
    "wof:name":"Almacenes Lago S.l.",
    "wof:placetype":"venue"
},
  "geometry": {"coordinates":[-0.3883841932,39.4554023743],"type":"Point"}
}