{
  "type": "Feature",
  "properties": {
    "addr:full":"Plaz Santa Adela, S/n Huescar Granada 18830",
    "addr:housenumber":"s / n",
    "addr:postcode":"18830",
    "iso:country":"ES",
    "sg:address":"Plaz Santa Adela, S/n",
    "sg:city":"Huescar",
    "sg:orig_category":"Telas Y Sedas (al Por Menor)",
    "sg:phone":"+34 958 74 22 27",
    "sg:postcode":"18830",
    "sg:province":"Granada",
    "wof:name":"Eras Caceres Jose",
    "wof:placetype":"venue"
},
  "geometry": {"coordinates":[-2.5432739258,37.8076705933],"type":"Point"}
}