{
  "type": "Feature",
  "properties": {
    "addr:full":"Ctra Almazora, S/n Castellon De La Plana Castell\u00f3n 12005",
    "addr:housenumber":"s / n",
    "addr:postcode":"12005",
    "addr:street":"Ctra Almazora",
    "iso:country":"ES",
    "sg:address":"Ctra Almazora, S/n",
    "sg:city":"Castellon De La Plana",
    "sg:orig_category":"Fabricaci\u00d3n, Venta, Instalaci\u00d3n De R\u00d3tulos, De R\u00d3tulos Luminosos",
    "sg:phone":"+34 964 20 72 58",
    "sg:postcode":"12005",
    "sg:province":"Castell\u00f3n",
    "wof:name":"Chencho Rotulos S.l.",
    "wof:placetype":"venue"
},
  "geometry": {"coordinates":[0.000192,39.9661827087],"type":"Point"}
}