{
  "type": "Feature",
  "properties": {
    "addr:full":"Avda Romero Donallo (de), 33 Santiago De Compostela La Coru\u00f1a 15706",
    "addr:housenumber":"33",
    "addr:postcode":"15706",
    "addr:street":"Avda Romero Donallo De;Corun\u0303A",
    "iso:country":"ES",
    "sg:address":"Avda Romero Donallo (de), 33",
    "sg:city":"Santiago De Compostela",
    "sg:orig_category":"Inform\u00c1tica: Mantenimiento Y Reparaci\u00d3n De Ordenadores",
    "sg:phone":"+34 981 59 65 65",
    "sg:postcode":"15706",
    "sg:province":"La Coru\u00f1a",
    "wof:name":"Consultoria Informatica Proinsys S.l.",
    "wof:placetype":"venue"
},
  "geometry": {"coordinates":[-8.5501441956,42.8710517883],"type":"Point"}
}