{
  "type": "Feature",
  "properties": {
    "iso:country":"ES",
    "sg:address":"Rua Manuel Lemos, S/n",
    "sg:city":"Ramallosa",
    "sg:orig_category":"Centros De Educaci\u00d3n Especial",
    "sg:phone":"+34 986 35 28 59",
    "sg:postcode":"36379",
    "sg:province":"Pontevedra",
    "wof:name":"Ayuntamiento De Nigran",
    "wof:placetype":"venue"
},
  "geometry": {"coordinates":[-8.8125343323,42.1196670532],"type":"Point"}
}