{
  "type": "Feature",
  "properties": {
    "addr:full":"Calle de Gabiria, 2 Irun Guip\u00f9zcoa 20305",
    "addr:housenumber":"2",
    "addr:postcode":"20305",
    "addr:street":"Calle De Gabiria;Guipu\u0300Zcoa",
    "iso:country":"ES",
    "sg:address":"Calle de Gabiria, 2",
    "sg:city":"Irun",
    "sg:orig_category":"Asesor\u00cda Fiscal Y Jur\u00cddica",
    "sg:phone":"+34 943 53 71 28",
    "sg:postcode":"20305",
    "sg:province":"Guip\u00f9zcoa",
    "wof:name":"Grupo Asesoramiento San Juan Arri S.c.",
    "wof:placetype":"venue"
},
  "geometry": {"coordinates":[-1.8253079653,43.3286094666],"type":"Point"}
}