{
  "type": "Feature",
  "properties": {
    "addr:full":"Calle de Diego Maria Crehuet, 21 Sierra Fuentes C\u00e1ceres 10181",
    "addr:housenumber":"21",
    "addr:postcode":"10181",
    "addr:street":"Calle De Diego Maria Crehuet;Sierra Fuentes Ca\u0301Ceres",
    "iso:country":"ES",
    "sg:address":"Calle de Diego Maria Crehuet, 21",
    "sg:city":"Sierra Fuentes",
    "sg:orig_category":"Mec\u00c1nico Del Autom\u00d3vil",
    "sg:phone":"+34 927 20 02 99",
    "sg:postcode":"10181",
    "sg:province":"C\u00e1ceres",
    "wof:name":"Vidal Bejar Miguel Angel",
    "wof:placetype":"venue"
},
  "geometry": {"coordinates":[-6.2727131844,39.4384231567],"type":"Point"}
}