{
  "type": "Feature",
  "properties": {
    "addr:full":"Avda Juan Carlos I, 106 Aguilas Murcia 30880",
    "addr:housenumber":"106",
    "addr:postcode":"30880",
    "addr:street":"Avda Juan Carlos I",
    "iso:country":"ES",
    "sg:address":"Avda Juan Carlos I, 106",
    "sg:city":"Aguilas",
    "sg:orig_category":"Comercio, Reparaci\u00d3n De Motocicletas, Bicicletas Y Piezas Sueltas",
    "sg:phone":"+34 968 41 14 79",
    "sg:postcode":"30880",
    "sg:province":"Murcia",
    "wof:name":"Miras Pi\u00f1ero Ana",
    "wof:placetype":"venue"
},
  "geometry": {"coordinates":[-1.5829370022,37.4098739624],"type":"Point"}
}