{
  "type": "Feature",
  "properties": {
    "addr:full":"Ptda Cotes Baixes, 10 Alcoi Alicante 03804",
    "addr:housenumber":"10",
    "addr:postcode":"03804",
    "addr:street":"Ptda Cotes Baixes",
    "iso:country":"ES",
    "sg:address":"Ptda Cotes Baixes, 10",
    "sg:city":"Alcoi",
    "sg:orig_category":"Empresas De Limpieza",
    "sg:phone":"+34 965 52 59 11",
    "sg:postcode":"03804",
    "sg:province":"Alicante",
    "wof:name":"U.t.e. Rbu-lv Alcoy",
    "wof:placetype":"venue"
},
  "geometry": {"coordinates":[-0.4650489986,38.712688446],"type":"Point"}
}