{
  "type": "Feature",
  "properties": {
    "iso:country":"ES",
    "sg:address":"C\u00f1o Subida San Amaro, 9",
    "sg:city":"Camposancos",
    "sg:orig_category":"Art\u00cdculos De Decoraci\u00d3n (fabricaci\u00d3n Y Al Por Mayor)",
    "sg:phone":"+34 986 62 72 16",
    "sg:postcode":"36788",
    "sg:province":"Pontevedra",
    "wof:name":"Savariz Diaz Jose Ramon",
    "wof:placetype":"venue"
},
  "geometry": {"coordinates":[-8.8786001205,41.8876190186],"type":"Point"}
}