{
  "type": "Feature",
  "properties": {
    "addr:full":"Calle de Plazas, 1 Trigueros Huelva 21620",
    "addr:housenumber":"1",
    "addr:postcode":"21620",
    "addr:street":"Calle De Plazas",
    "iso:country":"ES",
    "sg:address":"Calle de Plazas, 1",
    "sg:city":"Trigueros",
    "sg:orig_category":"Fotograf\u00cda Art\u00cdstica Y Retratos",
    "sg:phone":"+34 959 30 53 01",
    "sg:postcode":"21620",
    "sg:province":"Huelva",
    "wof:name":"Alba Fotografia Trigueros S.l.",
    "wof:placetype":"venue"
},
  "geometry": {"coordinates":[-6.8338856697,37.3830108643],"type":"Point"}
}