{
  "type": "Feature",
  "properties": {
    "iso:country":"ES",
    "sg:address":"Rua San Mamede, 25",
    "sg:city":"Montederramo",
    "sg:orig_category":"Supermercados Y Hipermercados",
    "sg:phone":"+34 988 29 20 38",
    "sg:postcode":"32750",
    "sg:province":"Ourense",
    "wof:name":"Perez Gonzalez Aurelio",
    "wof:placetype":"venue"
},
  "geometry": {"coordinates":[-7.5010929108,42.2744293213],"type":"Point"}
}