{
  "type": "Feature",
  "properties": {
    "addr:full":"Avda Cristobal Colon, 209 Guadalajara Guadalajara 19004",
    "addr:postcode":"19004",
    "addr:street":"Avda Cristobal Colon 209",
    "iso:country":"ES",
    "sg:address":"Avda Cristobal Colon, 209",
    "sg:city":"Guadalajara",
    "sg:orig_category":"Empresarios",
    "sg:phone":"+34 949 22 60 49",
    "sg:postcode":"19004",
    "sg:province":"Guadalajara",
    "wof:name":"Fundacion Hercesa Inmobiliaria",
    "wof:placetype":"venue"
},
  "geometry": {"coordinates":[-3.179625988,40.6574630737],"type":"Point"}
}