{
  "type": "Feature",
  "properties": {
    "addr:full":"Calle de Cochabamba, 23 Madrid Madrid 28016",
    "addr:housenumber":"23",
    "addr:postcode":"madrid;28016",
    "addr:street":"Calle De Cochabamba",
    "iso:country":"ES",
    "sg:address":"Calle de Cochabamba, 23",
    "sg:city":"Madrid",
    "sg:orig_category":"M\u00c9dicos: An\u00c1lisis Cl\u00cdnicos",
    "sg:phone":"+34 914 58 25 20",
    "sg:postcode":"28016",
    "sg:province":"Madrid",
    "wof:name":"Tormo Perez Pedro",
    "wof:placetype":"venue"
},
  "geometry": {"coordinates":[-3.6784622669,40.4562187195],"type":"Point"}
}