{
  "type": "Feature",
  "properties": {
    "iso:country":"ES",
    "sg:address":"Ntra. Sra. Rosario, 1",
    "sg:city":"Atarrabia",
    "sg:orig_category":"Fabricaci\u00d3n, Venta De Cuadros, Accesorios Para Enmarcar",
    "sg:phone":"+34 948 13 17 53",
    "sg:postcode":"31610",
    "sg:province":"Navarra",
    "wof:name":"Larumbe Medrano Joaquin",
    "wof:placetype":"venue"
},
  "geometry": {"coordinates":[-1.6102390289,42.8317489624],"type":"Point"}
}