{
  "type": "Feature",
  "properties": {
    "addr:full":"Praj Albares, 32 Fuensantilla Murcia 30530",
    "addr:housenumber":"32",
    "addr:postcode":"30530",
    "addr:street":"Albares",
    "iso:country":"ES",
    "sg:address":"Praj Albares, 32",
    "sg:city":"Fuensantilla",
    "sg:orig_category":"Promotores Constructores",
    "sg:phone":"+34 968 45 61 11",
    "sg:postcode":"30530",
    "sg:province":"Murcia",
    "wof:name":"Estructuras Jr S.l.",
    "wof:placetype":"venue"
},
  "geometry": {"coordinates":[-1.4241739511,38.2379302979],"type":"Point"}
}