{
  "type": "Feature",
  "properties": {
    "addr:full":"Pl Venus (de), 4 Salou Tarragona 43840",
    "addr:postcode":"43840",
    "addr:street":"Pl",
    "iso:country":"ES",
    "sg:address":"Pl Venus (de), 4",
    "sg:city":"Salou",
    "sg:orig_category":"Regalos, Souvenires (fabricaci\u00d3n, Al Por Mayor)",
    "sg:phone":"+34 977 38 01 80",
    "sg:postcode":"43840",
    "sg:province":"Tarragona",
    "wof:name":"Kumar  Vinod",
    "wof:placetype":"venue"
},
  "geometry": {"coordinates":[1.1191040277,41.0746612549],"type":"Point"}
}