{
  "type": "Feature",
  "properties": {
    "addr:full":"Calle de Moratines, 13 Madrid Madrid 28005",
    "addr:housenumber":"13",
    "addr:postcode":"madrid;28005",
    "addr:street":"Calle De Moratines",
    "iso:country":"ES",
    "sg:address":"Calle de Moratines, 13",
    "sg:city":"Madrid",
    "sg:orig_category":"Frutas, Legumbres Frescas Y Tempranas (al Por Menor)",
    "sg:phone":"+34 915 17 07 37",
    "sg:postcode":"28005",
    "sg:province":"Madrid",
    "wof:name":"Distribucion Horticola S.l.",
    "wof:placetype":"venue"
},
  "geometry": {"coordinates":[-3.7027869225,40.4030952454],"type":"Point"}
}