{
  "type": "Feature",
  "properties": {
    "iso:country":"ES",
    "sg:address":"Avda Libertad (de La), 9",
    "sg:city":"Jumilla",
    "sg:orig_category":"Molduras, Junquillos, Listones Y Molduras Perforadas",
    "sg:phone":"+34 968 75 70 04",
    "sg:postcode":"30520",
    "sg:province":"Murcia",
    "wof:name":"Madifra S L",
    "wof:placetype":"venue"
},
  "geometry": {"coordinates":[-1.3274589777,38.4710159302],"type":"Point"}
}