{
  "type": "Feature",
  "properties": {
    "addr:full":"Calle de Juan Carlos I, S/n Casar Guadalajara 19170",
    "addr:housenumber":"s / n",
    "addr:postcode":"19170",
    "addr:street":"Calle De Juan Carlos I",
    "iso:country":"ES",
    "sg:address":"Calle de Juan Carlos I, S/n",
    "sg:city":"Casar",
    "sg:orig_category":"Bazares, Art\u00cdculos De Limpieza Y De Cocina (al Por Menor)",
    "sg:phone":"+34 949 33 61 12",
    "sg:postcode":"19170",
    "sg:province":"Guadalajara",
    "wof:name":"Faucha Garcia Santiago",
    "wof:placetype":"venue"
},
  "geometry": {"coordinates":[-3.428260088,40.7036399841],"type":"Point"}
}