{
  "type": "Feature",
  "properties": {
    "addr:full":"Calle de Patrocinio Gomez, 1 Madrid Madrid 28022",
    "addr:housenumber":"1",
    "addr:postcode":"28022",
    "addr:street":"Calle De Patrocinio Gomez",
    "iso:country":"ES",
    "sg:address":"Calle de Patrocinio Gomez, 1",
    "sg:city":"Madrid",
    "sg:orig_category":"Inmobiliaria (agencias)",
    "sg:phone":"+34 913 20 57 20",
    "sg:postcode":"28022",
    "sg:province":"Madrid",
    "wof:name":"Calan S.a.",
    "wof:placetype":"venue"
},
  "geometry": {"coordinates":[-3.6154649258,40.4467163086],"type":"Point"}
}