{
  "type": "Feature",
  "properties": {
    "addr:full":"Alam Recalde, 20 Bilbao Vizcaya 48009",
    "addr:housenumber":"20",
    "addr:postcode":"48009",
    "addr:street":"Alam Recalde",
    "iso:country":"ES",
    "sg:address":"Alam Recalde, 20",
    "sg:city":"Bilbao",
    "sg:classifiers":[
        {
            "category":"Sports & Exercise",
            "subcategory":"Golf",
            "type":"Entertainment"
        }
    ],
    "sg:phone":"+34 944 35 22 20",
    "sg:postcode":"48009",
    "sg:province":"Vizcaya",
    "sg:tags":[
        "y",
        "de",
        "campos",
        "clases"
    ],
    "sg:website":"clubdegolfartxanda.com",
    "wof:name":"Club De Golf Archanda S.l.",
    "wof:placetype":"venue"
},
  "geometry": {"coordinates":[-2.9341719151,43.2654380798],"type":"Point"}
}