{
  "type": "Feature",
  "properties": {
    "iso:country":"ES",
    "sg:address":"Calle de Bohemios, 2",
    "sg:city":"Madrid",
    "sg:orig_category":"Fotocopias, Reprograf\u00cda",
    "sg:phone":"+34 913 17 98 34",
    "sg:postcode":"28041",
    "sg:province":"Madrid",
    "wof:name":"Gutierrez Briones Pedro",
    "wof:placetype":"venue"
},
  "geometry": {"coordinates":[-3.6937932968,40.3564872742],"type":"Point"}
}