{
  "type": "Feature",
  "properties": {
    "iso:country":"ES",
    "sg:address":"Calle de Mejico, 4",
    "sg:city":"Bargas",
    "sg:orig_category":"Complementos Para Pasteler\u00cdas, Confiter\u00cdas Y Chocolater\u00cdas",
    "sg:phone":"+34 925 35 82 90",
    "sg:postcode":"45593",
    "sg:province":"Toledo",
    "wof:name":"Bravo Molero Manuel",
    "wof:placetype":"venue"
},
  "geometry": {"coordinates":[-4.0109891891,39.9386711121],"type":"Point"}
}