{
  "type": "Feature",
  "properties": {
    "iso:country":"ES",
    "sg:address":"Calle de Ramon Franco, S/n",
    "sg:city":"Calvario",
    "sg:orig_category":"Sanatorios M\u00c9dico",
    "sg:phone":"+34 986 62 60 35",
    "sg:postcode":"36770",
    "sg:province":"Pontevedra",
    "wof:name":"Sergas - Gerencia De Atencion Primaria Pontevedra Sur",
    "wof:placetype":"venue"
},
  "geometry": {"coordinates":[-8.8362493515,41.9370346069],"type":"Point"}
}