{
  "type": "Feature",
  "properties": {
    "iso:country":"ES",
    "sg:address":"Avda Tomas Dominguez, 4",
    "sg:city":"Huelva",
    "sg:orig_category":"Farmacias",
    "sg:phone":"+34 959 24 23 80",
    "sg:postcode":"21001",
    "sg:province":"Huelva",
    "wof:name":"Cazenave Alvarez Aurelio",
    "wof:placetype":"venue"
},
  "geometry": {"coordinates":[-6.9552121162,37.2546920776],"type":"Point"}
}