{
  "type": "Feature",
  "properties": {
    "addr:full":"Mas Del Jutge, 118 P.i. Masia Del Juez Valencia 46900",
    "addr:housenumber":"118",
    "addr:postcode":"46900",
    "addr:street":"P.I. Masia Del Juez",
    "iso:country":"ES",
    "sg:address":"Mas Del Jutge, 118",
    "sg:city":"P.i. Masia Del Juez",
    "sg:orig_category":"Panader\u00cdas, Panader\u00cdas",
    "sg:phone":"+34 961 55 51 25",
    "sg:postcode":"46900",
    "sg:province":"Valencia",
    "wof:name":"Moreno Culebras Pedro",
    "wof:placetype":"venue"
},
  "geometry": {"coordinates":[-0.4623290002,39.441619873],"type":"Point"}
}