{
  "type": "Feature",
  "properties": {
    "iso:country":"ES",
    "sg:address":"Rua Morin, 122",
    "sg:city":"Monforte De Lemos",
    "sg:orig_category":"Zapatos: Material, Suministros, Accesorios (fabricaci\u00d3n, Al Por Mayor)",
    "sg:phone":"+34 982 40 14 82",
    "sg:postcode":"27400",
    "sg:province":"Lugo",
    "wof:name":"Calzados Kuski S.l.",
    "wof:placetype":"venue"
},
  "geometry": {"coordinates":[-7.5048780441,42.5350494385],"type":"Point"}
}