{
  "type": "Feature",
  "properties": {
    "iso:country":"ES",
    "sg:address":"Carrer de Vinya (de La), 5",
    "sg:city":"Mataro",
    "sg:orig_category":"Electricidad: Instaladores",
    "sg:phone":"+34 937 57 92 13",
    "sg:postcode":"08303",
    "sg:province":"Barcelona",
    "wof:name":"Electro Alvaro S.l.",
    "wof:placetype":"venue"
},
  "geometry": {"coordinates":[2.4270501137,41.5466308594],"type":"Point"}
}