{
  "type": "Feature",
  "properties": {
    "addr:full":"Avda Hispanidad De La, S/n Puente Mayorga C\u00e1diz 11313",
    "addr:postcode":"11313",
    "addr:street":"Avda Hispanidad De La S / N Puente Mayorga Ca\u0301Diz",
    "iso:country":"ES",
    "sg:address":"Avda Hispanidad De La, S/n",
    "sg:city":"Puente Mayorga",
    "sg:orig_category":"Navegaci\u00d3n (equipos Fluviales)",
    "sg:phone":"+34 956 69 91 58",
    "sg:postcode":"11313",
    "sg:province":"C\u00e1diz",
    "wof:name":"Aguaservi S. A.",
    "wof:placetype":"venue"
},
  "geometry": {"coordinates":[-5.3850450516,36.1823730469],"type":"Point"}
}