{
  "type": "Feature",
  "properties": {
    "iso:country":"ES",
    "sg:address":"Carrer de Pintor Murillo, 78",
    "sg:city":"Rubi",
    "sg:classifiers":[
        {
            "category":"Home & Garden",
            "subcategory":"Household Appliances",
            "type":"Retail Goods"
        }
    ],
    "sg:phone":"+34 936 99 98 27",
    "sg:postcode":"08191",
    "sg:province":"Barcelona",
    "sg:tags":[
        "bodega",
        "de",
        "vino",
        "acondicionamiento"
    ],
    "wof:name":"Aris Casanovas Antonio",
    "wof:placetype":"venue"
},
  "geometry": {"coordinates":[2.0322775841,41.4879302979],"type":"Point"}
}