{
  "type": "Feature",
  "properties": {
    "iso:country":"ES",
    "sg:address":"Plaz Paola Blasco, 2",
    "sg:city":"Alca\u00f1iz",
    "sg:orig_category":"Maquinaria Para Industrias Diversas",
    "sg:phone":"+34 978 83 02 63",
    "sg:postcode":"44600",
    "sg:province":"Teruel",
    "wof:name":"Vera Ruiz Manuel",
    "wof:placetype":"venue"
},
  "geometry": {"coordinates":[-0.1302859932,41.0518798828],"type":"Point"}
}