{
  "type": "Feature",
  "properties": {
    "addr:full":"Calle de Calera, Km. 0001,2 Talavera Reina Toledo 45600",
    "addr:postcode":"45600",
    "addr:street":"Calle De Calera Km. 0001,2",
    "iso:country":"ES",
    "sg:address":"Calle de Calera, Km. 0001,2",
    "sg:city":"Talavera Reina",
    "sg:orig_category":"Transportes Por Carretera: Lotes Completos, Mercanc\u00cdas Diversas",
    "sg:phone":"+34 925 82 58 04",
    "sg:postcode":"45600",
    "sg:province":"Toledo",
    "wof:name":"Bodas Mancillas Maria Mercedes",
    "wof:placetype":"venue"
},
  "geometry": {"coordinates":[-4.8326292038,39.9584884644],"type":"Point"}
}