{
  "type": "Feature",
  "properties": {
    "addr:full":"Calle de Pedro Antonio De Alarcon, 7 Granada Granada 18005",
    "addr:housenumber":"7",
    "addr:postcode":"18005",
    "addr:street":"Calle De Pedro Antonio De Alarcon",
    "iso:country":"ES",
    "sg:address":"Calle de Pedro Antonio De Alarcon, 7",
    "sg:city":"Granada",
    "sg:orig_category":"Estudios, Instalaci\u00d3n De Climatizaci\u00d3n",
    "sg:phone":"+34 958 52 35 72",
    "sg:postcode":"18005",
    "sg:province":"Granada",
    "wof:name":"Climaroa S.l.",
    "wof:placetype":"venue"
},
  "geometry": {"coordinates":[-3.6035981178,37.169418335],"type":"Point"}
}