{
  "type": "Feature",
  "properties": {
    "iso:country":"ES",
    "sg:address":"Calle de Iglesia, 18",
    "sg:city":"Granja Torrehermosa",
    "sg:orig_category":"Supermercados Y Hipermercados",
    "sg:phone":"+34 924 89 53 50",
    "sg:postcode":"06910",
    "sg:province":"Badajoz",
    "wof:name":"Expenred S.l.",
    "wof:placetype":"venue"
},
  "geometry": {"coordinates":[-5.5954008102,38.3101768494],"type":"Point"}
}