{
  "type": "Feature",
  "properties": {
    "iso:country":"ES",
    "sg:address":"Carrer de Roger De Flor, 148",
    "sg:city":"Barcelona",
    "sg:orig_category":"Veh\u00cdculos De Ocasi\u00d3n",
    "sg:phone":"+34 932 45 44 14",
    "sg:postcode":"08013",
    "sg:province":"Barcelona",
    "sg:website":"wwww.autocental.es",
    "wof:name":"Auto Central S.a.",
    "wof:placetype":"venue"
},
  "geometry": {"coordinates":[2.1753799915,41.396900177],"type":"Point"}
}