{
  "type": "Feature",
  "properties": {
    "addr:full":"Cra. Molins Rei, S/n S. Quirze Valles Barcelona 08192",
    "addr:postcode":"08192",
    "addr:street":"Rei S / N S.;Valles Barcelona",
    "iso:country":"ES",
    "sg:address":"Cra. Molins Rei, S/n",
    "sg:city":"S. Quirze Valles",
    "sg:orig_category":"Lencer\u00cda Femenina, Corseter\u00cda, Trajes De Ba\u00d1o (al Por Menor)",
    "sg:phone":"+34 937 21 32 69",
    "sg:postcode":"08192",
    "sg:province":"Barcelona",
    "wof:name":"Nara Gestion De Franquicias S.l.",
    "wof:placetype":"venue"
},
  "geometry": {"coordinates":[2.0770950317,41.535243988],"type":"Point"}
}