{
  "type": "Feature",
  "properties": {
    "addr:full":"Carrer de Ricardo Villa, 9 Barcelona Barcelona 08017",
    "addr:housenumber":"9",
    "addr:postcode":"08017",
    "addr:street":"Carrer De Ricardo Villa",
    "iso:country":"ES",
    "sg:address":"Carrer de Ricardo Villa, 9",
    "sg:city":"Barcelona",
    "sg:orig_category":"Bancos",
    "sg:phone":"+34 932 05 65 71",
    "sg:postcode":"08017",
    "sg:province":"Barcelona",
    "wof:name":"Banco Finantia Sofinloc",
    "wof:placetype":"venue"
},
  "geometry": {"coordinates":[2.1329369545,41.3922843933],"type":"Point"}
}