{
  "type": "Feature",
  "properties": {
    "addr:full":"Granada, Km. 0014,5 Alcantarilla Murcia 30820",
    "addr:postcode":"30820",
    "addr:street":"Granada Km. 0014,5",
    "iso:country":"ES",
    "sg:address":"Granada, Km. 0014,5",
    "sg:city":"Alcantarilla",
    "sg:orig_category":"Delegados, Agentes De Tr\u00c1nsito, Auxiliares De Transporte Internacional",
    "sg:phone":"+34 968 89 33 77",
    "sg:postcode":"30820",
    "sg:province":"Murcia",
    "sg:website":"www.trapiser.com",
    "wof:name":"Trapiser S.l.",
    "wof:placetype":"venue"
},
  "geometry": {"coordinates":[-1.2226799726,37.9636726379],"type":"Point"}
}