{
  "type": "Feature",
  "properties": {
    "addr:full":"Ctra Telde Gando, 77 Goro Las Palmas 35215",
    "addr:housenumber":"77",
    "addr:postcode":"35215",
    "addr:street":"Ctra Telde Gando",
    "iso:country":"ES",
    "sg:address":"Ctra Telde Gando, 77",
    "sg:city":"Goro",
    "sg:orig_category":"Alquiler De Gr\u00daas",
    "sg:phone":"+34 928 57 43 34",
    "sg:postcode":"35215",
    "sg:province":"Las Palmas",
    "wof:name":"Sertemac S. L.",
    "wof:placetype":"venue"
},
  "geometry": {"coordinates":[-15.398223877,27.9939899445],"type":"Point"}
}