{
  "type": "Feature",
  "properties": {
    "iso:country":"ES",
    "sg:address":"Calle de Mayor, 16",
    "sg:city":"Calahorra",
    "sg:orig_category":"Electrodom\u00c9sticos (al Por Menor)",
    "sg:phone":"+34 941 13 08 84",
    "sg:postcode":"26500",
    "sg:province":"La Rioja",
    "wof:name":"Perez Gonzalez Felix Manuel",
    "wof:placetype":"venue"
},
  "geometry": {"coordinates":[-1.9602689743,42.3010597229],"type":"Point"}
}