{
  "type": "Feature",
  "properties": {
    "iso:country":"ES",
    "sg:address":"Avgd Ausias March, 72",
    "sg:city":"Burjassot",
    "sg:orig_category":"Centros Empresariales",
    "sg:phone":"+34 963 64 22 27",
    "sg:postcode":"46100",
    "sg:province":"Valencia",
    "wof:name":"Alenar Consultoria Y Proyectos S.l.",
    "wof:placetype":"venue"
},
  "geometry": {"coordinates":[-0.4111813903,39.5126152039],"type":"Point"}
}