{
  "type": "Feature",
  "properties": {
    "iso:country":"ES",
    "sg:address":"Calle de Sagunto, 11",
    "sg:city":"Olvega",
    "sg:orig_category":"Plomeros",
    "sg:phone":"+34 976 64 56 41",
    "sg:postcode":"42110",
    "sg:province":"Soria",
    "wof:name":"Salvador Lamata Juan-jesus",
    "wof:placetype":"venue"
},
  "geometry": {"coordinates":[-1.9871480465,41.7799873352],"type":"Point"}
}