{
  "type": "Feature",
  "properties": {
    "iso:country":"ES",
    "sg:address":"Praz Canido, 3",
    "sg:city":"Ferrol",
    "sg:orig_category":"Abogados",
    "sg:phone":"+34 981 35 93 74",
    "sg:postcode":"15402",
    "sg:province":"La Coru\u00f1a",
    "wof:name":"Pena Leal Jose",
    "wof:placetype":"venue"
},
  "geometry": {"coordinates":[-8.2273387909,43.4868507385],"type":"Point"}
}