{
  "type": "Feature",
  "properties": {
    "addr:full":"Calle de Jose Maria Pereda, 55 Torrelavega Cantabria 39300",
    "addr:housenumber":"55",
    "addr:postcode":"39300",
    "addr:street":"Calle De Jose Maria Pereda",
    "iso:country":"ES",
    "sg:address":"Calle de Jose Maria Pereda, 55",
    "sg:city":"Torrelavega",
    "sg:orig_category":"M\u00c9dicos: Medicina Y Biolog\u00cda Del Deporte",
    "sg:phone":"+34 942 88 39 92",
    "sg:postcode":"39300",
    "sg:province":"Cantabria",
    "wof:name":"Garcia Corona Juan Jose",
    "wof:placetype":"venue"
},
  "geometry": {"coordinates":[-4.0490908623,43.3523826599],"type":"Point"}
}