{
  "type": "Feature",
  "properties": {
    "iso:country":"ES",
    "sg:address":"Calle de Doctor Fleming, 11",
    "sg:city":"Arrecife",
    "sg:orig_category":"Loter\u00cda Y T\u00d3mbola",
    "sg:phone":"+34 928 81 52 01",
    "sg:postcode":"35500",
    "sg:province":"Las Palmas",
    "wof:name":"Romero Ortega Celia Maria",
    "wof:placetype":"venue"
},
  "geometry": {"coordinates":[-13.5533838272,28.9617996216],"type":"Point"}
}