{
  "type": "Feature",
  "properties": {
    "iso:country":"ES",
    "sg:address":"Barr Usila, 4",
    "sg:city":"Ugao-miraballes",
    "sg:orig_category":"V\u00c1lvulas",
    "sg:phone":"+34 946 48 03 29",
    "sg:postcode":"48490",
    "sg:province":"Vizcaya",
    "wof:name":"Ballvugaokdx21 S.l",
    "wof:placetype":"venue"
},
  "geometry": {"coordinates":[-2.9032590389,43.1841812134],"type":"Point"}
}