{
  "type": "Feature",
  "properties": {
    "iso:country":"ES",
    "sg:address":"Carrer de Miguel De Cervantes, 11",
    "sg:city":"Lloret Mar",
    "sg:orig_category":"Asesor\u00cda Fiscal Y Jur\u00cddica",
    "sg:phone":"+34 972 36 10 55",
    "sg:postcode":"17310",
    "sg:province":"Girona",
    "wof:name":"R A Lloret Assessors S.l.",
    "wof:placetype":"venue"
},
  "geometry": {"coordinates":[2.8470880985,41.699131012],"type":"Point"}
}