{
  "type": "Feature",
  "properties": {
    "iso:country":"ES",
    "sg:address":"Calle de Meson De Paredes, 72",
    "sg:city":"Madrid",
    "sg:orig_category":"Transportes Por Carretera: Lotes Completos, Mercanc\u00cdas Diversas",
    "sg:phone":"+34 915 27 00 35",
    "sg:postcode":"28012",
    "sg:province":"Madrid",
    "wof:name":"Panaderia Boupan S.l",
    "wof:placetype":"venue"
},
  "geometry": {"coordinates":[-3.7027449608,40.4075317383],"type":"Point"}
}