{
  "type": "Feature",
  "properties": {
    "iso:country":"ES",
    "sg:address":"Avda Burgos, 12",
    "sg:city":"Logro\u00f1o",
    "sg:orig_category":"Agentes, Concesionarios Y Sucursales De Veh\u00cdculos",
    "sg:phone":"+34 941 20 17 15",
    "sg:postcode":"26006",
    "sg:province":"La Rioja",
    "wof:name":"Master Auto Rioja S.l.",
    "wof:placetype":"venue"
},
  "geometry": {"coordinates":[-2.4036989212,42.46043396],"type":"Point"}
}