{
  "type": "Feature",
  "properties": {
    "addr:full":"Carrer de Navarra, 66 Masnou Barcelona 08320",
    "addr:housenumber":"66",
    "addr:postcode":"08320",
    "addr:street":"Carrer De Navarra",
    "iso:country":"ES",
    "sg:address":"Carrer de Navarra, 66",
    "sg:city":"Masnou",
    "sg:orig_category":"Peluqueros: De Se\u00d1oras",
    "sg:phone":"+34 935 55 40 86",
    "sg:postcode":"08320",
    "sg:province":"Barcelona",
    "wof:name":"Ortiz Rodriguez Luciana",
    "wof:placetype":"venue"
},
  "geometry": {"coordinates":[2.3148519993,41.4809303284],"type":"Point"}
}