{
  "type": "Feature",
  "properties": {
    "addr:full":"Cmno Puente Virrey, 49 Zaragoza Zaragoza 50008",
    "addr:housenumber":"49",
    "addr:postcode":"50008",
    "addr:street":"Cmno Puente Virrey",
    "iso:country":"ES",
    "sg:address":"Cmno Puente Virrey, 49",
    "sg:city":"Zaragoza",
    "sg:orig_category":"Papeler\u00cdas, Librer\u00cdas",
    "sg:phone":"+34 976 13 47 12",
    "sg:postcode":"50008",
    "sg:province":"Zaragoza",
    "wof:name":"Sanz Gimenez Maria Elba",
    "wof:placetype":"venue"
},
  "geometry": {"coordinates":[-0.8744810224,41.6367912292],"type":"Point"}
}