{
  "type": "Feature",
  "properties": {
    "iso:country":"ES",
    "sg:address":"Carrer de Estacio, 7",
    "sg:city":"Palau-solita I Plegamans",
    "sg:orig_category":"Loter\u00cda Y T\u00d3mbola",
    "sg:phone":"+34 938 64 50 95",
    "sg:postcode":"08184",
    "sg:province":"Barcelona",
    "wof:name":"Torras Casajoana Francesca",
    "wof:placetype":"venue"
},
  "geometry": {"coordinates":[2.179142952,41.5876541138],"type":"Point"}
}