{
  "type": "Feature",
  "properties": {
    "addr:full":"Eraga Etorbidea, 1 Etxarri-aranatz Navarra 31820",
    "addr:housenumber":"1",
    "addr:postcode":"31820",
    "addr:street":"Eraga Etorbidea",
    "iso:country":"ES",
    "sg:address":"Eraga Etorbidea, 1",
    "sg:city":"Etxarri-aranatz",
    "sg:orig_category":"\u00d3ptica: Instrumentos (fabricaci\u00d3n)",
    "sg:phone":"+34 948 46 12 52",
    "sg:postcode":"31820",
    "sg:province":"Navarra",
    "wof:name":"Argiro Optika S.l.",
    "wof:placetype":"venue"
},
  "geometry": {"coordinates":[-2.0638492107,42.9063072205],"type":"Point"}
}