{
  "type": "Feature",
  "properties": {
    "addr:full":"Calle de Veintiseis De Diciembre, 6 Cuesta Santa Cruz De Tenerife 38320",
    "addr:housenumber":"6",
    "addr:postcode":"38320",
    "addr:street":"Calle De Veintiseis De Diciembre",
    "iso:country":"ES",
    "sg:address":"Calle de Veintiseis De Diciembre, 6",
    "sg:city":"Cuesta",
    "sg:orig_category":"Inform\u00c1tica (estudios, Servicios, Asesor\u00cda, Formaci\u00d3n)",
    "sg:phone":"+34 922 65 48 67",
    "sg:postcode":"38320",
    "sg:province":"Santa Cruz De Tenerife",
    "sg:website":"www.jeldigital.com",
    "wof:name":"Ferrer Cabrera Elias",
    "wof:placetype":"venue"
},
  "geometry": {"coordinates":[-16.2858257294,28.4699440002],"type":"Point"}
}