{
  "type": "Feature",
  "properties": {
    "addr:full":"Calle de Alonso Fernandez, 1 Madrid Madrid 28011",
    "addr:housenumber":"1",
    "addr:postcode":"28011",
    "addr:street":"Calle De Alonso Fernandez",
    "iso:country":"ES",
    "sg:address":"Calle de Alonso Fernandez, 1",
    "sg:city":"Madrid",
    "sg:orig_category":"Muebles Y Accesorios Para Cocinas Y Cuartos De Ba\u00d1o (al Por Menor)",
    "sg:phone":"+34 915 26 40 20",
    "sg:postcode":"28011",
    "sg:province":"Madrid",
    "wof:name":"Cocinas Racar S.l.l.",
    "wof:placetype":"venue"
},
  "geometry": {"coordinates":[-3.7258784771,40.4141044617],"type":"Point"}
}