{
  "type": "Feature",
  "properties": {
    "addr:full":"Carr Grecia, S/n Figueres Girona 17600",
    "addr:housenumber":"s",
    "addr:postcode":"17600",
    "addr:street":"Carr Grecia;/ N",
    "iso:country":"ES",
    "sg:address":"Carr Grecia, S/n",
    "sg:city":"Figueres",
    "sg:orig_category":"Agencias Y Agentes Comerciales, Representantes",
    "sg:phone":"+34 972 67 87 87",
    "sg:postcode":"17600",
    "sg:province":"Girona",
    "wof:name":"Representaciones Burgas S. L.",
    "wof:placetype":"venue"
},
  "geometry": {"coordinates":[2.9803550243,42.2646446228],"type":"Point"}
}