{
  "type": "Feature",
  "properties": {
    "iso:country":"ES",
    "sg:address":"Calle de Espiritu Santo, 15",
    "sg:city":"Coin",
    "sg:orig_category":"Promotores Constructores",
    "sg:phone":"+34 952 45 22 00",
    "sg:postcode":"29100",
    "sg:province":"M\u00e1laga",
    "wof:name":"Construcciones Torae S.l.",
    "wof:placetype":"venue"
},
  "geometry": {"coordinates":[-4.7553539276,36.6616249084],"type":"Point"}
}