{
  "type": "Feature",
  "properties": {
    "addr:full":"Calle de Arrayanes, 5 Badajoz Badajoz 06010",
    "addr:housenumber":"5",
    "addr:postcode":"06010",
    "addr:street":"Calle De Arrayanes",
    "iso:country":"ES",
    "sg:address":"Calle de Arrayanes, 5",
    "sg:city":"Badajoz",
    "sg:orig_category":"Asociaciones Y Clubs Deportivos",
    "sg:phone":"+34 924 23 36 49",
    "sg:postcode":"06010",
    "sg:province":"Badajoz",
    "wof:name":"Diaz Hinchado Yolanda",
    "wof:placetype":"venue"
},
  "geometry": {"coordinates":[-6.9694943428,38.8639831543],"type":"Point"}
}