{
  "type": "Feature",
  "properties": {
    "addr:full":"Calle de Pintor Berrueta, 9 Irun Guip\u00f9zcoa 20305",
    "addr:housenumber":"9",
    "addr:postcode":"20305",
    "addr:street":"Calle De Pintor Berrueta;Guipu\u0300Zcoa",
    "iso:country":"ES",
    "sg:address":"Calle de Pintor Berrueta, 9",
    "sg:city":"Irun",
    "sg:orig_category":"Estancos",
    "sg:phone":"+34 943 63 15 93",
    "sg:postcode":"20305",
    "sg:province":"Guip\u00f9zcoa",
    "wof:name":"Yolanda Silva Lopez.-estanco",
    "wof:placetype":"venue"
},
  "geometry": {"coordinates":[-1.776211977,43.3406982422],"type":"Point"}
}