{
  "type": "Feature",
  "properties": {
    "iso:country":"ES",
    "sg:address":"Carrer de Tres Senyores, 24",
    "sg:city":"Barcelona",
    "sg:orig_category":"Ebanister\u00cda",
    "sg:phone":"+34 932 13 23 23",
    "sg:postcode":"08024",
    "sg:province":"Barcelona",
    "wof:name":"Bofarull Gil Esteban",
    "wof:placetype":"venue"
},
  "geometry": {"coordinates":[2.1582629681,41.4064598083],"type":"Point"}
}