{
  "type": "Feature",
  "properties": {
    "addr:full":"Calle de Ancha, 25 Medina Rioseco Valladolid 47800",
    "addr:housenumber":"25",
    "addr:postcode":"47800",
    "addr:street":"Calle De Ancha",
    "iso:country":"ES",
    "sg:address":"Calle de Ancha, 25",
    "sg:city":"Medina Rioseco",
    "sg:orig_category":"Transportes Por V\u00cdas Navegables",
    "sg:phone":"+34 983 70 08 82",
    "sg:postcode":"47800",
    "sg:province":"Valladolid",
    "wof:name":"Liebana Martin Ubaldo",
    "wof:placetype":"venue"
},
  "geometry": {"coordinates":[-5.0444259644,41.8847808838],"type":"Point"}
}