{
  "type": "Feature",
  "properties": {
    "iso:country":"ES",
    "sg:address":"Calle de Barcelona, 19",
    "sg:city":"Flores Del Sil",
    "sg:orig_category":"Droguer\u00cdas (al Por Menor)",
    "sg:phone":"+34 987 41 64 19",
    "sg:postcode":"24400",
    "sg:province":"Le\u00f3n",
    "wof:name":"Prada Granja Pedro",
    "wof:placetype":"venue"
},
  "geometry": {"coordinates":[-6.6263666153,42.5504417419],"type":"Point"}
}