{
  "type": "Feature",
  "properties": {
    "iso:country":"ES",
    "sg:address":"Calle de Progreso, 1",
    "sg:city":"Algezares",
    "sg:orig_category":"Reposter\u00cdas",
    "sg:phone":"+34 968 84 10 19",
    "sg:postcode":"30157",
    "sg:province":"Murcia",
    "wof:name":"Diaz Noguera Antonio",
    "wof:placetype":"venue"
},
  "geometry": {"coordinates":[-1.1174570322,37.9413871765],"type":"Point"}
}