{
  "type": "Feature",
  "properties": {
    "iso:country":"ES",
    "sg:address":"Calle de Logro\u00d1o, S/n",
    "sg:city":"Aranda Duero",
    "sg:classifiers":[
        {
            "category":"Manufacturing",
            "subcategory":"Metals",
            "type":"Manufacturing & Wholesale Goods"
        }
    ],
    "sg:phone":"+34 947 50 22 80",
    "sg:postcode":"09400",
    "sg:province":"Burgos",
    "sg:tags":[
        "en",
        "fundiciones"
    ],
    "wof:name":"Fundiciones Y Talleres Abad S. A.",
    "wof:placetype":"venue"
},
  "geometry": {"coordinates":[-3.7060389519,41.664768219],"type":"Point"}
}