{
  "type": "Feature",
  "properties": {
    "addr:full":"Calle de Sobrarbe, 25 Huesca Huesca 22001",
    "addr:housenumber":"25",
    "addr:postcode":"22001",
    "addr:street":"Calle De Sobrarbe",
    "iso:country":"ES",
    "sg:address":"Calle de Sobrarbe, 25",
    "sg:city":"Huesca",
    "sg:orig_category":"Peluqueros: De Se\u00d1oras",
    "sg:phone":"+34 974 22 66 71",
    "sg:postcode":"22001",
    "sg:province":"Huesca",
    "wof:name":"Arnalda Lasierra Ana Maria",
    "wof:placetype":"venue"
},
  "geometry": {"coordinates":[-0.4039945006,42.1379165649],"type":"Point"}
}