{
  "type": "Feature",
  "properties": {
    "iso:country":"ES",
    "sg:address":"Calle de Isla Cabrera, 13",
    "sg:city":"Valencia",
    "sg:orig_category":"Suministros Y Materiales Industriales",
    "sg:phone":"+34 963 95 09 94",
    "sg:postcode":"46026",
    "sg:province":"Valencia",
    "sg:website":"www.valshue.com",
    "wof:name":"Valsuhe S. L.",
    "wof:placetype":"venue"
},
  "geometry": {"coordinates":[-0.3800652027,39.4491920471],"type":"Point"}
}