{
  "type": "Feature",
  "properties": {
    "iso:country":"ES",
    "sg:address":"Avda Juventudes Musicales, S/n",
    "sg:city":"Sevilla",
    "sg:orig_category":"Caf\u00c9s, Bares, Cervecer\u00cdas",
    "sg:phone":"+34 954 90 39 13",
    "sg:postcode":"41009",
    "sg:province":"Sevilla",
    "wof:name":"Via Italica S.l.",
    "wof:placetype":"venue"
},
  "geometry": {"coordinates":[-5.9843540192,37.413444519],"type":"Point"}
}