{
  "type": "Feature",
  "properties": {
    "iso:country":"ES",
    "sg:address":"Carrer de Balmes, 313",
    "sg:city":"Barcelona",
    "sg:orig_category":"Ingenier\u00cda, Centros De Estudios (diversos)",
    "sg:phone":"+34 932 09 83 36",
    "sg:postcode":"08006",
    "sg:province":"Barcelona",
    "wof:name":"Mare Masso Jaime Ramon",
    "wof:placetype":"venue"
},
  "geometry": {"coordinates":[2.1447370052,41.4026603699],"type":"Point"}
}