{
  "type": "Feature",
  "properties": {
    "iso:country":"ES",
    "sg:address":"Rua Calvo Sotelo, 12",
    "sg:city":"Sarria",
    "sg:orig_category":"Caf\u00c9s, Bares, Cervecer\u00cdas",
    "sg:phone":"+34 982 53 00 21",
    "sg:postcode":"27600",
    "sg:province":"Lugo",
    "wof:name":"Cafeteria Polo S.l.",
    "wof:placetype":"venue"
},
  "geometry": {"coordinates":[-7.4169430733,42.7830085754],"type":"Point"}
}