{
  "type": "Feature",
  "properties": {
    "addr:full":"Carr Sorrall, 9 Arbucies Girona 17401",
    "addr:housenumber":"9",
    "addr:postcode":"17401",
    "addr:street":"Carr Sorrall",
    "iso:country":"ES",
    "sg:address":"Carr Sorrall, 9",
    "sg:city":"Arbucies",
    "sg:orig_category":"Fisioterapia",
    "sg:phone":"+34 972 16 27 28",
    "sg:postcode":"17401",
    "sg:province":"Girona",
    "wof:name":"Fisio Girona S.a.",
    "wof:placetype":"venue"
},
  "geometry": {"coordinates":[2.5148448944,41.8163795471],"type":"Point"}
}