{
  "type": "Feature",
  "properties": {
    "iso:country":"ES",
    "sg:address":"Carrer de Forners (dels), 43",
    "sg:city":"Reus",
    "sg:orig_category":"Suministros Y Materiales Industriales",
    "sg:phone":"+34 977 77 25 80",
    "sg:postcode":"43206",
    "sg:province":"Tarragona",
    "wof:name":"Indauto Subministres Industrials S.l.",
    "wof:placetype":"venue"
},
  "geometry": {"coordinates":[1.1090600491,41.1406517029],"type":"Point"}
}