{
  "type": "Feature",
  "properties": {
    "addr:full":"Calle de Santa Maria, S/n Torres Ja\u00e9n 23540",
    "addr:housenumber":"/ n",
    "addr:postcode":"23540",
    "addr:street":"Calle De Santa;S;Jae\u0301N",
    "iso:country":"ES",
    "sg:address":"Calle de Santa Maria, S/n",
    "sg:city":"Torres",
    "sg:orig_category":"Centros De Educaci\u00d3n Especial",
    "sg:phone":"+34 953 36 32 23",
    "sg:postcode":"23540",
    "sg:province":"Ja\u00e9n",
    "wof:name":"Junta De Andalucia",
    "wof:placetype":"venue"
},
  "geometry": {"coordinates":[-3.510931015,37.7846832275],"type":"Point"}
}