{
  "type": "Feature",
  "properties": {
    "iso:country":"ES",
    "sg:address":"Calle de Afan De Ribera, 121",
    "sg:city":"Sevilla",
    "sg:orig_category":"Internados & Ense\u00d1anza Privada",
    "sg:phone":"+34 954 63 42 92",
    "sg:postcode":"41006",
    "sg:province":"Sevilla",
    "wof:name":"Colegio De Egb Ruiz Elias",
    "wof:placetype":"venue"
},
  "geometry": {"coordinates":[-5.9583158493,37.3725814819],"type":"Point"}
}