{
  "type": "Feature",
  "properties": {
    "iso:country":"ES",
    "sg:address":"Plaz Caudillo, S/n",
    "sg:city":"Balsa De Ves",
    "sg:orig_category":"Centros De Salud",
    "sg:phone":"+34 967 47 62 16",
    "sg:postcode":"02214",
    "sg:province":"Albacete",
    "wof:name":"Ayuntamiento De Balsa De Ves-centro Sanitario De Higiene",
    "wof:placetype":"venue"
},
  "geometry": {"coordinates":[-1.1956340075,39.2642593384],"type":"Point"}
}