{
  "type": "Feature",
  "properties": {
    "addr:full":"Calle de Del Medio, S/n Navianos De Valverde Zamora 49697",
    "addr:housenumber":"s",
    "addr:postcode":"49697",
    "addr:street":"Calle De Del Medio;/ N",
    "iso:country":"ES",
    "sg:address":"Calle de Del Medio, S/n",
    "sg:city":"Navianos De Valverde",
    "sg:orig_category":"Asociaciones Ecologistas",
    "sg:phone":"+34 980 64 60 13",
    "sg:postcode":"49697",
    "sg:province":"Zamora",
    "wof:name":"Asociacion De Regantes De La Margen Derecha Del Tera",
    "wof:placetype":"venue"
},
  "geometry": {"coordinates":[-5.8180971146,41.9535713196],"type":"Point"}
}