{
  "type": "Feature",
  "properties": {
    "addr:full":"C/ Al\u00c7amora (els), 44 Alcoi Alicante 03802",
    "addr:postcode":"03802",
    "addr:street":"C /;Els",
    "iso:country":"ES",
    "sg:address":"C/ Al\u00c7amora (els), 44",
    "sg:city":"Alcoi",
    "sg:orig_category":"Juegos Y Juguetes (al Por Menor)",
    "sg:phone":"+34 965 33 32 27",
    "sg:postcode":"03802",
    "sg:province":"Alicante",
    "wof:name":"Explotaciones De Bowling S.l.",
    "wof:placetype":"venue"
},
  "geometry": {"coordinates":[-0.4811719954,38.6976852417],"type":"Point"}
}