{
  "type": "Feature",
  "properties": {
    "addr:full":"Abdo Mundi, 9 Figueres Girona 17600",
    "addr:postcode":"17600",
    "iso:country":"ES",
    "sg:address":"Abdo Mundi, 9",
    "sg:city":"Figueres",
    "sg:orig_category":"Inform\u00c1tica, Ofim\u00c1tica (estudios, Asesor\u00cda, Ingenier\u00cda, Formaci\u00d3n)",
    "sg:phone":"+34 972 67 28 59",
    "sg:postcode":"17600",
    "sg:province":"Girona",
    "wof:name":"Garre Olmo S.l.",
    "wof:placetype":"venue"
},
  "geometry": {"coordinates":[2.9666719437,42.2711029053],"type":"Point"}
}