{
  "type": "Feature",
  "properties": {
    "addr:full":"Calle de Afan, 2 Sevilla Sevilla 41006",
    "addr:housenumber":"2",
    "addr:postcode":"41006",
    "addr:street":"Calle De Afan",
    "iso:country":"ES",
    "sg:address":"Calle de Afan, 2",
    "sg:city":"Sevilla",
    "sg:orig_category":"Asociaciones Humanitarias, De Cooperaci\u00d3n, De Acci\u00d3n Social",
    "sg:phone":"+34 954 67 03 80",
    "sg:postcode":"41006",
    "sg:province":"Sevilla",
    "wof:name":"Hermanas De La Caridad De Santa Ana",
    "wof:placetype":"venue"
},
  "geometry": {"coordinates":[-5.9330868721,37.3760452271],"type":"Point"}
}