{
  "type": "Feature",
  "properties": {
    "addr:full":"Carrer de Tajo, 56 Barcelona Barcelona 08032",
    "addr:housenumber":"56",
    "addr:postcode":"08032",
    "addr:street":"Carrer De Tajo",
    "iso:country":"ES",
    "sg:address":"Carrer de Tajo, 56",
    "sg:city":"Barcelona",
    "sg:orig_category":"Bisuter\u00cda, Joyer\u00cda, Relojer\u00cda (al Por Menor)",
    "sg:phone":"+34 934 29 02 70",
    "sg:postcode":"08032",
    "sg:province":"Barcelona",
    "wof:name":"Cardias S.l.",
    "wof:placetype":"venue"
},
  "geometry": {"coordinates":[2.1602010727,41.4298057556],"type":"Point"}
}