{
  "type": "Feature",
  "properties": {
    "iso:country":"ES",
    "sg:address":"Ctra. Picanya, 43",
    "sg:city":"Torrent",
    "sg:orig_category":"Mec\u00c1nico Del Autom\u00d3vil",
    "sg:phone":"+34 961 56 19 91",
    "sg:postcode":"46900",
    "sg:province":"Valencia",
    "wof:name":"Movil-torrent S.l.",
    "wof:placetype":"venue"
},
  "geometry": {"coordinates":[-0.4579589963,39.4411354065],"type":"Point"}
}