{
  "type": "Feature",
  "properties": {
    "iso:country":"ES",
    "sg:address":"Carretera Larrabide, 7",
    "sg:city":"Pasai Donibane",
    "sg:classifiers":[
        {
            "category":"Taxi",
            "type":"Transportation"
        }
    ],
    "sg:phone":"+34 943 34 06 60",
    "sg:postcode":"20110",
    "sg:province":"Guip\u00f9zcoa",
    "wof:name":"Asociacion De Taxistas Autonomos De Errenteria",
    "wof:placetype":"venue"
},
  "geometry": {"coordinates":[-1.910931468,43.3274116516],"type":"Point"}
}