{
  "type": "Feature",
  "properties": {
    "addr:full":"Calle de Cristo De La Epidemia, 54 Malaga M\u00e1laga 29013",
    "addr:housenumber":"54",
    "addr:postcode":"29013",
    "addr:street":"Calle De Cristo De La Epidemia;Ma\u0301Laga",
    "iso:country":"ES",
    "sg:address":"Calle de Cristo De La Epidemia, 54",
    "sg:city":"Malaga",
    "sg:orig_category":"\u00d3ptica: Instrumentos (fabricaci\u00d3n)",
    "sg:phone":"+34 952 26 87 27",
    "sg:postcode":"29013",
    "sg:province":"M\u00e1laga",
    "wof:name":"Alboy S..",
    "wof:placetype":"venue"
},
  "geometry": {"coordinates":[-4.4148626328,36.7299385071],"type":"Point"}
}