{
  "type": "Feature",
  "properties": {
    "iso:country":"ES",
    "sg:address":"Carrer de Sant Vicen\u00c7, 30",
    "sg:city":"Barcelona",
    "sg:orig_category":"Ingeniero",
    "sg:phone":"+34 933 18 25 85",
    "sg:postcode":"08001",
    "sg:province":"Barcelona",
    "wof:name":"Lerison Electronica S. C.",
    "wof:placetype":"venue"
},
  "geometry": {"coordinates":[2.1646900177,41.3819503784],"type":"Point"}
}