{
  "type": "Feature",
  "properties": {
    "addr:full":"Calle de Sangenis, 68 Zaragoza Zaragoza 50010",
    "addr:housenumber":"68",
    "addr:postcode":"50010",
    "addr:street":"Calle De Sangenis",
    "iso:country":"ES",
    "sg:address":"Calle de Sangenis, 68",
    "sg:city":"Zaragoza",
    "sg:orig_category":"Institutos De Belleza (productos Y Aparatos)",
    "sg:phone":"+34 976 53 12 62",
    "sg:postcode":"50010",
    "sg:province":"Zaragoza",
    "wof:name":"Magallon Magallon Belen",
    "wof:placetype":"venue"
},
  "geometry": {"coordinates":[-0.9034510255,41.649936676],"type":"Point"}
}