{
  "type": "Feature",
  "properties": {
    "iso:country":"ES",
    "sg:address":"Barreiros, S/n",
    "sg:city":"Rante",
    "sg:orig_category":"Congelados: Productos Alimentarios (al Por Menor)",
    "sg:phone":"+34 988 23 60 13",
    "sg:postcode":"32910",
    "sg:province":"Ourense",
    "wof:name":"Hermanos Alvarez Benito Y Maria S.l.",
    "wof:placetype":"venue"
},
  "geometry": {"coordinates":[-7.8773641586,42.2747917175],"type":"Point"}
}