{
  "type": "Feature",
  "properties": {
    "iso:country":"ES",
    "sg:address":"Calle de Diamante, 37",
    "sg:city":"Madrid",
    "sg:orig_category":"Administradores De Bienes Y Delegados De Comunidades De Propietarios",
    "sg:phone":"+34 915 05 15 01",
    "sg:postcode":"28021",
    "sg:province":"Madrid",
    "wof:name":"Ferrero Antolin Jose Alberto",
    "wof:placetype":"venue"
},
  "geometry": {"coordinates":[-3.686239481,40.3508720398],"type":"Point"}
}