{
  "type": "Feature",
  "properties": {
    "addr:full":"Calle de Don Juan Carlos I, 19 Muela Zaragoza 50196",
    "addr:housenumber":"19",
    "addr:postcode":"50196",
    "addr:street":"Calle De Don Juan Carlos I",
    "iso:country":"ES",
    "sg:address":"Calle de Don Juan Carlos I, 19",
    "sg:city":"Muela",
    "sg:orig_category":"Alimentaci\u00d3n General (al Por Menor)",
    "sg:phone":"+34 976 14 40 31",
    "sg:postcode":"50196",
    "sg:province":"Zaragoza",
    "wof:name":"Casanova Raimundo Jesus Angel",
    "wof:placetype":"venue"
},
  "geometry": {"coordinates":[-1.1180605888,41.5803489685],"type":"Point"}
}