{
  "type": "Feature",
  "properties": {
    "addr:full":"Pase Urgoiti, 32 Arrigorriaga Vizcaya 48480",
    "addr:housenumber":"32",
    "addr:postcode":"48480",
    "addr:street":"Urgoiti",
    "iso:country":"ES",
    "sg:address":"Pase Urgoiti, 32",
    "sg:city":"Arrigorriaga",
    "sg:orig_category":"Venta, Instalaci\u00d3n De Calefacci\u00d3n",
    "sg:phone":"+34 946 71 34 58",
    "sg:postcode":"48480",
    "sg:province":"Vizcaya",
    "wof:name":"Jose Roberto Casta\u00f1on Mantilla",
    "wof:placetype":"venue"
},
  "geometry": {"coordinates":[-2.8891849518,43.2053527832],"type":"Point"}
}