{
  "type": "Feature",
  "properties": {
    "addr:full":"Calle de Sorias, 13 Salamanca Salamanca 37002",
    "addr:housenumber":"13",
    "addr:postcode":"37002",
    "addr:street":"Calle De Sorias",
    "iso:country":"ES",
    "sg:address":"Calle de Sorias, 13",
    "sg:city":"Salamanca",
    "sg:orig_category":"M\u00c9dicos: Fisioterapia Y Rehabilitaci\u00d3n",
    "sg:phone":"+34 923 21 34 64",
    "sg:postcode":"37002",
    "sg:province":"Salamanca",
    "wof:name":"Rehabilitacion Alaejos C.b.",
    "wof:placetype":"venue"
},
  "geometry": {"coordinates":[-5.6674289703,40.9666557312],"type":"Point"}
}