{
  "type": "Feature",
  "properties": {
    "addr:full":"Calle de Logro\u00d1o (de), 1 Humanes De Madrid Madrid 28970",
    "addr:postcode":"28970",
    "addr:street":"Calle De Logron\u0303O De 1",
    "iso:country":"ES",
    "sg:address":"Calle de Logro\u00d1o (de), 1",
    "sg:city":"Humanes De Madrid",
    "sg:orig_category":"Tapicer\u00cdas",
    "sg:phone":"+34 916 06 35 09",
    "sg:postcode":"28970",
    "sg:province":"Madrid",
    "wof:name":"Tapicerias Y Poliuretanos S. A.",
    "wof:placetype":"venue"
},
  "geometry": {"coordinates":[-3.8118391037,40.2747802734],"type":"Point"}
}