{
  "type": "Feature",
  "properties": {
    "addr:full":"Cmno Sestas, S/n Bali\u00d1os Pontevedra 36780",
    "addr:housenumber":"s",
    "addr:postcode":"36780",
    "addr:street":"Cmno Sestas;/ N",
    "iso:country":"ES",
    "sg:address":"Cmno Sestas, S/n",
    "sg:city":"Bali\u00d1os",
    "sg:orig_category":"Autob\u00das (explotaci\u00d3n Y Servicios De)",
    "sg:phone":"+34 986 61 07 33",
    "sg:postcode":"36780",
    "sg:province":"Pontevedra",
    "wof:name":"Automoviles De Tuy S. A.",
    "wof:placetype":"venue"
},
  "geometry": {"coordinates":[-8.6480531693,42.4336204529],"type":"Point"}
}