{
  "type": "Feature",
  "properties": {
    "addr:full":"Carrer de Sant Marc, 18 Terrassa Barcelona 08224",
    "addr:housenumber":"18",
    "addr:postcode":"08224",
    "addr:street":"Carrer De Sant Marc",
    "iso:country":"ES",
    "sg:address":"Carrer de Sant Marc, 18",
    "sg:city":"Terrassa",
    "sg:orig_category":"M\u00c9dicos: Estomatolog\u00cda",
    "sg:phone":"+34 937 89 54 27",
    "sg:postcode":"08224",
    "sg:province":"Barcelona",
    "wof:name":"Acevedo Barrientos Juan",
    "wof:placetype":"venue"
},
  "geometry": {"coordinates":[2.0015459061,41.563117981],"type":"Point"}
}