{
  "type": "Feature",
  "properties": {
    "addr:full":"Carrer de Cicero, 12 Barcelona Barcelona 08014",
    "addr:housenumber":"12",
    "addr:postcode":"08014",
    "addr:street":"Carrer De Cicero",
    "iso:country":"ES",
    "sg:address":"Carrer de Cicero, 12",
    "sg:city":"Barcelona",
    "sg:orig_category":"Laboratorios Farmac\u00c9uticos",
    "sg:phone":"+34 934 31 45 70",
    "sg:postcode":"08014",
    "sg:province":"Barcelona",
    "wof:name":"Lopez Vargas Maria Rosario",
    "wof:placetype":"venue"
},
  "geometry": {"coordinates":[2.1382288933,41.3763008118],"type":"Point"}
}