{
  "type": "Feature",
  "properties": {
    "iso:country":"ES",
    "sg:address":"Rua Principe, 17",
    "sg:city":"Vigo",
    "sg:orig_category":"Estancos",
    "sg:phone":"+34 986 43 41 15",
    "sg:postcode":"36202",
    "sg:province":"Pontevedra",
    "wof:name":"Fernandez Vazquez Juan Antonio",
    "wof:placetype":"venue"
},
  "geometry": {"coordinates":[-8.7230443954,42.2371292114],"type":"Point"}
}