{
  "type": "Feature",
  "properties": {
    "iso:country":"ES",
    "sg:address":"Avgd Alacant, 7",
    "sg:city":"Lleida",
    "sg:orig_category":"Mec\u00c1nico Del Autom\u00d3vil",
    "sg:phone":"+34 973 20 10 93",
    "sg:postcode":"25001",
    "sg:province":"Lleida",
    "wof:name":"Guiu Estangui Carlos",
    "wof:placetype":"venue"
},
  "geometry": {"coordinates":[0.632257998,41.6124229431],"type":"Point"}
}