{
  "type": "Feature",
  "properties": {
    "addr:full":"Calle de Ramon Y Cajal, S/n Turre Almer\u00eda 04639",
    "addr:housenumber":"s",
    "addr:postcode":"04639",
    "addr:street":"Calle De Ramon Y Cajal;/ N Turre Almeri\u0301A",
    "iso:country":"ES",
    "sg:address":"Calle de Ramon Y Cajal, S/n",
    "sg:city":"Turre",
    "sg:orig_category":"Doctores En Medicina",
    "sg:phone":"+34 950 46 80 80",
    "sg:postcode":"04639",
    "sg:province":"Almer\u00eda",
    "wof:name":"Esteban Lopez Ramon",
    "wof:placetype":"venue"
},
  "geometry": {"coordinates":[-1.8911839724,37.1535949707],"type":"Point"}
}