{
  "type": "Feature",
  "properties": {
    "iso:country":"ES",
    "sg:address":"Urb Carteya, S/n",
    "sg:city":"Algeciras",
    "sg:orig_category":"Trabajos De Topograf\u00cda",
    "sg:phone":"+34 956 66 81 44",
    "sg:postcode":"11202",
    "sg:province":"C\u00e1diz",
    "wof:name":"Sphinx Tecnologias Constructivas S.l",
    "wof:placetype":"venue"
},
  "geometry": {"coordinates":[-5.4526848793,36.1349105835],"type":"Point"}
}