{
  "type": "Feature",
  "properties": {
    "iso:country":"ES",
    "sg:address":"Carr Juan Xxiii, 16",
    "sg:city":"Puerto De Pollen\u00c7a",
    "sg:orig_category":"Bancos",
    "sg:phone":"+34 971 86 66 11",
    "sg:postcode":"07470",
    "sg:province":"Islas Baleares",
    "sg:website":"www.bancodecreditobalear.es",
    "wof:name":"Banco De Credito Balear",
    "wof:placetype":"venue"
},
  "geometry": {"coordinates":[3.0826599598,39.9063415527],"type":"Point"}
}