{
  "type": "Feature",
  "properties": {
    "addr:full":"Calle de Iglesia, 24 Solosancho \u00c1vila 05130",
    "addr:housenumber":"24",
    "addr:postcode":"05130",
    "addr:street":"Calle De Iglesia;A\u0301Vila",
    "iso:country":"ES",
    "sg:address":"Calle de Iglesia, 24",
    "sg:city":"Solosancho",
    "sg:orig_category":"Molduras, Junquillos, Listones Y Molduras Perforadas",
    "sg:phone":"+34 920 29 10 35",
    "sg:postcode":"05130",
    "sg:province":"\u00c1vila",
    "wof:name":"Jimenez Hernandez Juan",
    "wof:placetype":"venue"
},
  "geometry": {"coordinates":[-4.9061980247,40.5536384583],"type":"Point"}
}