{
  "type": "Feature",
  "properties": {
    "addr:full":"Carrer de Alarcon, 168 S. Adria Besos Barcelona 08930",
    "addr:housenumber":"168",
    "addr:postcode":"08930",
    "addr:street":"Carrer De Alarcon;S. Adria Besos Barcelona",
    "iso:country":"ES",
    "sg:address":"Carrer de Alarcon, 168",
    "sg:city":"S. Adria Besos",
    "sg:orig_category":"Artes Gr\u00c1ficas, Artes Pl\u00c1sticas (curso)",
    "sg:phone":"+34 933 81 32 66",
    "sg:postcode":"08930",
    "sg:province":"Barcelona",
    "wof:name":"Vertice Grafico S.l.u",
    "wof:placetype":"venue"
},
  "geometry": {"coordinates":[2.2083089352,41.428440094],"type":"Point"}
}