{
  "type": "Feature",
  "properties": {
    "iso:country":"ES",
    "sg:address":"Carrer de Marques De Campo, 42",
    "sg:city":"Denia",
    "sg:orig_category":"Administradores De Bienes Y Delegados De Comunidades De Propietarios",
    "sg:phone":"+34 966 42 13 48",
    "sg:postcode":"03700",
    "sg:province":"Alicante",
    "wof:name":"Sala I Reig Administradors S.c",
    "wof:placetype":"venue"
},
  "geometry": {"coordinates":[0.1094020009,38.8404884338],"type":"Point"}
}