{
  "type": "Feature",
  "properties": {
    "addr:full":"Plaz Mayor, 14 Lliber Alicante 03729",
    "addr:housenumber":"14",
    "addr:postcode":"03729",
    "addr:street":"Plaz Mayor",
    "iso:country":"ES",
    "sg:address":"Plaz Mayor, 14",
    "sg:city":"Lliber",
    "sg:orig_category":"Cajas Para Embalar",
    "sg:phone":"+34 965 73 15 29",
    "sg:postcode":"03729",
    "sg:province":"Alicante",
    "sg:website":"www.ruralcaja.com",
    "wof:name":"Caja Rural Del Mediterraneo Ruralcaja S Coop De Credito",
    "wof:placetype":"venue"
},
  "geometry": {"coordinates":[0.0062370002,38.7433357239],"type":"Point"}
}