{
  "type": "Feature",
  "properties": {
    "iso:country":"ES",
    "sg:address":"Rua Bo Xesus, 4",
    "sg:city":"Lugo",
    "sg:orig_category":"Artesanado",
    "sg:phone":"+34 982 24 68 66",
    "sg:postcode":"27001",
    "sg:province":"Lugo",
    "wof:name":"Gonzalez Diaz-becerra Maria Luisa",
    "wof:placetype":"venue"
},
  "geometry": {"coordinates":[-7.5582499504,43.0095405579],"type":"Point"}
}