{
  "type": "Feature",
  "properties": {
    "iso:country":"ES",
    "sg:address":"Conj Rincon Del Mar, S/n",
    "sg:city":"Mijas Costa",
    "sg:orig_category":"Molduras, Junquillos, Listones Y Molduras Perforadas",
    "sg:phone":"+34 952 93 54 56",
    "sg:postcode":"29649",
    "sg:province":"M\u00e1laga",
    "wof:name":"Bar Los Rumbos S.l.",
    "wof:placetype":"venue"
},
  "geometry": {"coordinates":[-4.7184290886,36.4927597046],"type":"Point"}
}