{
  "type": "Feature",
  "properties": {
    "iso:country":"ES",
    "sg:address":"Plaz Villafranca De Los Barros, 1",
    "sg:city":"Madrid",
    "sg:orig_category":"Electricidad: Instaladores",
    "sg:phone":"+34 917 39 63 84",
    "sg:postcode":"28034",
    "sg:province":"Madrid",
    "wof:name":"Principe Pendolero Ramon",
    "wof:placetype":"venue"
},
  "geometry": {"coordinates":[-3.7123880386,40.4810409546],"type":"Point"}
}