{
  "type": "Feature",
  "properties": {
    "iso:country":"ES",
    "sg:address":"Carr Sant Lluc, 25",
    "sg:city":"Badalona",
    "sg:orig_category":"Electromec\u00c1nica",
    "sg:phone":"+34 933 97 33 79",
    "sg:postcode":"08918",
    "sg:province":"Barcelona",
    "wof:name":"Dragon Asia S.l.",
    "wof:placetype":"venue"
},
  "geometry": {"coordinates":[2.2360680103,41.4346313477],"type":"Point"}
}