{
  "type": "Feature",
  "properties": {
    "iso:country":"ES",
    "sg:address":"Calle de Cristobal Colon, 22",
    "sg:city":"Algeciras",
    "sg:orig_category":"Art\u00cdculos De Regalo (al Por Menor)",
    "sg:phone":"+34 956 66 30 23",
    "sg:postcode":"11201",
    "sg:province":"C\u00e1diz",
    "wof:name":"Lopez Lucuix Emilio",
    "wof:placetype":"venue"
},
  "geometry": {"coordinates":[-5.4474878311,36.1294937134],"type":"Point"}
}