{
  "type": "Feature",
  "properties": {
    "iso:country":"ES",
    "sg:address":"Plaz Castellini, 12",
    "sg:city":"Cartagena",
    "sg:orig_category":"Oficinas Y Gesti\u00d3n De Inmuebles",
    "sg:phone":"+34 968 50 09 15",
    "sg:postcode":"30201",
    "sg:province":"Murcia",
    "wof:name":"Anthema Gestion S.l.",
    "wof:placetype":"venue"
},
  "geometry": {"coordinates":[-0.9856517911,37.6039543152],"type":"Point"}
}