{
  "type": "Feature",
  "properties": {
    "iso:country":"ES",
    "sg:address":"Bule Jose Prat, 7",
    "sg:city":"Madrid",
    "sg:orig_category":"Guarder\u00cdas",
    "sg:phone":"+34 913 05 12 71",
    "sg:postcode":"28032",
    "sg:province":"Madrid",
    "wof:name":"Moreno Vega Ascension",
    "wof:placetype":"venue"
},
  "geometry": {"coordinates":[-3.6243600845,40.3984680176],"type":"Point"}
}