{
  "type": "Feature",
  "properties": {
    "addr:full":"Av Conqueridor, 102 Ciutadella Menorca Islas Baleares 07760",
    "addr:housenumber":"102",
    "addr:postcode":"07760",
    "addr:street":"Av Conqueridor",
    "iso:country":"ES",
    "sg:address":"Av Conqueridor, 102",
    "sg:city":"Ciutadella Menorca",
    "sg:orig_category":"Asesor\u00cdas Y Estudios Financieros",
    "sg:phone":"+34 971 38 00 20",
    "sg:postcode":"07760",
    "sg:province":"Islas Baleares",
    "wof:name":"Cavaller Gener Antonio",
    "wof:placetype":"venue"
},
  "geometry": {"coordinates":[3.8394780159,39.9995155334],"type":"Point"}
}