{
  "type": "Feature",
  "properties": {
    "addr:full":"Calle de Vereda Mas De Tous, S/n Pobla Vallbona Valencia 46185",
    "addr:housenumber":"/ n",
    "addr:postcode":"46185",
    "addr:street":"Calle De Vereda Mas De Tous S",
    "iso:country":"ES",
    "sg:address":"Calle de Vereda Mas De Tous, S/n",
    "sg:city":"Pobla Vallbona",
    "sg:orig_category":"Venta, Instalaci\u00d3n De Calefacci\u00d3n",
    "sg:phone":"+34 961 66 30 17",
    "sg:postcode":"46185",
    "sg:province":"Valencia",
    "wof:name":"Montajes E Instalaciones Industriales Pec S.l.",
    "wof:placetype":"venue"
},
  "geometry": {"coordinates":[-0.3768048882,39.4702377319],"type":"Point"}
}