{
  "type": "Feature",
  "properties": {
    "iso:country":"ES",
    "sg:address":"Av Rei En Jaume, 147",
    "sg:city":"Cardedeu",
    "sg:orig_category":"Agentes Generales De Seguros",
    "sg:phone":"+34 938 71 16 11",
    "sg:postcode":"08440",
    "sg:province":"Barcelona",
    "wof:name":"De Haro Forns Santiago",
    "wof:placetype":"venue"
},
  "geometry": {"coordinates":[2.3579499722,41.6369781494],"type":"Point"}
}