{
  "type": "Feature",
  "properties": {
    "addr:full":"Calle de Santa Rosalia, 11 Cabra C\u00f3rdoba 14940",
    "addr:housenumber":"11",
    "addr:postcode":"14940",
    "addr:street":"Calle De Santa Rosalia;Co\u0301Rdoba",
    "iso:country":"ES",
    "sg:address":"Calle de Santa Rosalia, 11",
    "sg:city":"Cabra",
    "sg:orig_category":"Lencer\u00cda Femenina, Corseter\u00cda, Trajes De Ba\u00d1o (al Por Menor)",
    "sg:phone":"+34 957 52 59 54",
    "sg:postcode":"14940",
    "sg:province":"C\u00f3rdoba",
    "wof:name":"Cantero Carpio Laura",
    "wof:placetype":"venue"
},
  "geometry": {"coordinates":[-4.443379879,37.4726066589],"type":"Point"}
}