{
  "type": "Feature",
  "properties": {
    "addr:full":"Calle de Treboles, 3 Malaga M\u00e1laga 29014",
    "addr:housenumber":"3",
    "addr:postcode":"29014",
    "addr:street":"Calle De Treboles;Ma\u0301Laga",
    "iso:country":"ES",
    "sg:address":"Calle de Treboles, 3",
    "sg:city":"Malaga",
    "sg:orig_category":"Ropa Para Se\u00d1oras (al Por Menor)",
    "sg:phone":"+34 952 26 37 75",
    "sg:postcode":"29014",
    "sg:province":"M\u00e1laga",
    "wof:name":"Sanchez Blanco Jose",
    "wof:placetype":"venue"
},
  "geometry": {"coordinates":[-4.412402153,36.7393989563],"type":"Point"}
}