{
  "type": "Feature",
  "properties": {
    "iso:country":"ES",
    "sg:address":"Calle de Virgen De La Soledad, 23",
    "sg:city":"Badajoz",
    "sg:orig_category":"Art\u00cdculos De Regalo (al Por Menor)",
    "sg:phone":"+34 924 22 00 79",
    "sg:postcode":"06001",
    "sg:province":"Badajoz",
    "wof:name":"Sanchez Vallejo Carlos",
    "wof:placetype":"venue"
},
  "geometry": {"coordinates":[-6.9711308479,38.8798141479],"type":"Point"}
}