{
  "type": "Feature",
  "properties": {
    "iso:country":"ES",
    "sg:address":"Calle de Zubiaurre, 11",
    "sg:city":"Iurreta",
    "sg:orig_category":"Iglesia Cat\u00d3lica",
    "sg:phone":"+34 946 20 20 74",
    "sg:postcode":"48215",
    "sg:province":"Vizcaya",
    "wof:name":"Obispado De Bilbao",
    "wof:placetype":"venue"
},
  "geometry": {"coordinates":[-2.6371548176,43.1742477417],"type":"Point"}
}