{
  "type": "Feature",
  "properties": {
    "iso:country":"ES",
    "sg:address":"Calle de Juan Bautista Escudero, S/n",
    "sg:city":"Cordoba",
    "sg:orig_category":"Fabricaci\u00d3n De Bicicletas, Motocicletas Y Piezas Sueltas",
    "sg:phone":"+34 957 32 65 14",
    "sg:postcode":"14014",
    "sg:province":"C\u00f3rdoba",
    "wof:name":"Andaluza De Bicicletas S.l.",
    "wof:placetype":"venue"
},
  "geometry": {"coordinates":[-4.7191562653,37.9099845886],"type":"Point"}
}