{
  "type": "Feature",
  "properties": {
    "iso:country":"ES",
    "sg:address":"Calle de Isla Bonita, S/n",
    "sg:city":"Playa San Juan",
    "sg:orig_category":"Insecticidas, Fumigaci\u00d3n",
    "sg:phone":"+34 922 86 61 35",
    "sg:postcode":"38687",
    "sg:province":"Santa Cruz De Tenerife",
    "wof:name":"Inca Islas Canarias S. A.",
    "wof:placetype":"venue"
},
  "geometry": {"coordinates":[-16.7886390686,28.1805458069],"type":"Point"}
}