{
  "type": "Feature",
  "properties": {
    "addr:full":"Carr Poeta Miguel Hernandez, 14 Sant Rafel Alicante 03580",
    "addr:housenumber":"14",
    "addr:postcode":"03580",
    "addr:street":"Carr Poeta Miguel Hernandez",
    "iso:country":"ES",
    "sg:address":"Carr Poeta Miguel Hernandez, 14",
    "sg:city":"Sant Rafel",
    "sg:orig_category":"Guarda",
    "sg:phone":"+34 966 87 48 90",
    "sg:postcode":"03580",
    "sg:province":"Alicante",
    "wof:name":"Gonzalez Juarez Jose Ignacio",
    "wof:placetype":"venue"
},
  "geometry": {"coordinates":[-0.1017019972,38.5834732056],"type":"Point"}
}