{
  "type": "Feature",
  "properties": {
    "iso:country":"ES",
    "sg:address":"Avda Portugal, 59",
    "sg:city":"Salamanca",
    "sg:orig_category":"Inform\u00c1tica (estudios, Servicios, Asesor\u00cda, Formaci\u00d3n)",
    "sg:phone":"+34 923 23 15 10",
    "sg:postcode":"37005",
    "sg:province":"Salamanca",
    "wof:name":"Multilogos S.l.",
    "wof:placetype":"venue"
},
  "geometry": {"coordinates":[-5.6580491066,40.9712905884],"type":"Point"}
}