{
  "type": "Feature",
  "properties": {
    "addr:full":"Calle de Mejorada, 10 Torrejon Ardoz Madrid 28850",
    "addr:housenumber":"10",
    "addr:postcode":"28850",
    "addr:street":"Calle De Mejorada",
    "iso:country":"ES",
    "sg:address":"Calle de Mejorada, 10",
    "sg:city":"Torrejon Ardoz",
    "sg:orig_category":"Armas Y Municiones (fabricaci\u00d3n, Al Por Mayor)",
    "sg:phone":"+34 912 27 97 84",
    "sg:postcode":"28850",
    "sg:province":"Madrid",
    "sg:website":"www.ballestascarlos.com",
    "wof:name":"Ballestas Carlos Ruiz S.l.",
    "wof:placetype":"venue"
},
  "geometry": {"coordinates":[-3.4878001213,40.4492988586],"type":"Point"}
}