{
  "type": "Feature",
  "properties": {
    "iso:country":"ES",
    "sg:address":"Calle de Italia, 11",
    "sg:city":"Begijar",
    "sg:classifiers":[
        {
            "category":"Taxi",
            "type":"Transportation"
        }
    ],
    "sg:phone":"+34 953 76 35 65",
    "sg:postcode":"23520",
    "sg:province":"Ja\u00e9n",
    "wof:name":"Garate Lopez Lucas",
    "wof:placetype":"venue"
},
  "geometry": {"coordinates":[-3.5256810188,37.9862136841],"type":"Point"}
}