{
  "type": "Feature",
  "properties": {
    "addr:full":"Calle de Real, 9 Sanlucar Mayor Sevilla 41800",
    "addr:housenumber":"9",
    "addr:postcode":"41800",
    "addr:street":"Calle De Real",
    "iso:country":"ES",
    "sg:address":"Calle de Real, 9",
    "sg:city":"Sanlucar Mayor",
    "sg:orig_category":"Pod\u00d3logos: Pedicuros",
    "sg:phone":"+34 955 70 14 26",
    "sg:postcode":"41800",
    "sg:province":"Sevilla",
    "wof:name":"Fernandez Robles Mercedes",
    "wof:placetype":"venue"
},
  "geometry": {"coordinates":[-6.2006049156,37.3859481812],"type":"Point"}
}