{
  "type": "Feature",
  "properties": {
    "iso:country":"ES",
    "sg:address":"Carrer de Gotic, 8",
    "sg:city":"Ardiaca",
    "sg:orig_category":"Agentes, Concesionarios Y Sucursales De Camiones Y Veh\u00cdculos Industriales",
    "sg:phone":"+34 977 79 33 71",
    "sg:postcode":"43850",
    "sg:province":"Tarragona",
    "sg:website":"www.coluer.com",
    "wof:name":"Bike Import Mayoral S.l.",
    "wof:placetype":"venue"
},
  "geometry": {"coordinates":[1.0611100197,41.0672683716],"type":"Point"}
}