{
  "type": "Feature",
  "properties": {
    "addr:full":"Av Mare Deu De Montserrat, 103 Barcelona Barcelona 08024",
    "addr:housenumber":"103",
    "addr:postcode":"08024",
    "addr:street":"Av Mare;De Montserrat",
    "iso:country":"ES",
    "sg:address":"Av Mare Deu De Montserrat, 103",
    "sg:city":"Barcelona",
    "sg:orig_category":"Metales (labores, Pulido)",
    "sg:phone":"+34 934 35 89 08",
    "sg:postcode":"08024",
    "sg:province":"Barcelona",
    "wof:name":"Matriceria Y Estampaciones Hercules S. A.",
    "wof:placetype":"venue"
},
  "geometry": {"coordinates":[2.168006897,41.4158554077],"type":"Point"}
}