{
  "type": "Feature",
  "properties": {
    "iso:country":"ES",
    "sg:address":"Guimarans, S/n",
    "sg:city":"Guimarans",
    "sg:orig_category":"Marmolistas Funerarios",
    "sg:phone":"+34 981 89 04 64",
    "sg:postcode":"15866",
    "sg:province":"La Coru\u00f1a",
    "wof:name":"Lopez Framil Jose",
    "wof:placetype":"venue"
},
  "geometry": {"coordinates":[-8.6062335968,42.8256759644],"type":"Point"}
}