{
  "type": "Feature",
  "properties": {
    "iso:country":"ES",
    "sg:address":"Calle de Trobika, 17",
    "sg:city":"Mungia",
    "sg:orig_category":"Muebles Y Accesorios Para Cocinas Y Cuartos De Ba\u00d1o (al Por Menor)",
    "sg:phone":"+34 946 74 05 30",
    "sg:postcode":"48100",
    "sg:province":"Vizcaya",
    "wof:name":"Ibinarriaga, S.l.",
    "wof:placetype":"venue"
},
  "geometry": {"coordinates":[-2.8437840939,43.3545036316],"type":"Point"}
}