{
  "type": "Feature",
  "properties": {
    "addr:full":"Avda Talamanca (de), 15 Fuente Del Fresno Madrid 28708",
    "addr:housenumber":"15",
    "addr:postcode":"28708",
    "addr:street":"Avda Talamanca De",
    "iso:country":"ES",
    "sg:address":"Avda Talamanca (de), 15",
    "sg:city":"Fuente Del Fresno",
    "sg:orig_category":"Fabricaci\u00d3n De Distribuidores Autom\u00c1ticos",
    "sg:phone":"+34 916 23 60 08",
    "sg:postcode":"28708",
    "sg:province":"Madrid",
    "wof:name":"Business Service Managment Iberia, S.l.",
    "wof:placetype":"venue"
},
  "geometry": {"coordinates":[-3.6008551121,40.5881538391],"type":"Point"}
}