{
  "type": "Feature",
  "properties": {
    "addr:full":"Calle de Letra G, 22 Puebla Alfinden Zaragoza 50171",
    "addr:postcode":"50171",
    "addr:street":"Calle De Letra;Alfinden",
    "iso:country":"ES",
    "sg:address":"Calle de Letra G, 22",
    "sg:city":"Puebla Alfinden",
    "sg:orig_category":"Maquinaria Para Industrias Diversas",
    "sg:phone":"+34 976 10 86 57",
    "sg:postcode":"50171",
    "sg:province":"Zaragoza",
    "sg:website":"www.aum.es",
    "wof:name":"Automatismos Utillajes Y Maquinas S.l.",
    "wof:placetype":"venue"
},
  "geometry": {"coordinates":[-0.7562590241,41.6385154724],"type":"Point"}
}