{
  "type": "Feature",
  "properties": {
    "addr:full":"Calle de Rio Jarama (de), 3 Humanes De Madrid Madrid 28970",
    "addr:postcode":"28970",
    "addr:street":"Calle De Rio Jarama De 3",
    "iso:country":"ES",
    "sg:address":"Calle de Rio Jarama (de), 3",
    "sg:city":"Humanes De Madrid",
    "sg:orig_category":"Muebles, Minoristas",
    "sg:phone":"+34 916 04 84 50",
    "sg:postcode":"28970",
    "sg:province":"Madrid",
    "wof:name":"Cantos Humanes S.l.",
    "wof:placetype":"venue"
},
  "geometry": {"coordinates":[-3.8145871162,40.2651786804],"type":"Point"}
}