{
  "type": "Feature",
  "properties": {
    "iso:country":"ES",
    "sg:address":"Carrer de Mar, 52",
    "sg:city":"Malgrat Mar",
    "sg:orig_category":"Ropa Y Art\u00cdculos Pre",
    "sg:phone":"+34 937 65 38 13",
    "sg:postcode":"08380",
    "sg:province":"Barcelona",
    "wof:name":"Lopez Pou Susanna",
    "wof:placetype":"venue"
},
  "geometry": {"coordinates":[2.7432119846,41.6444587708],"type":"Point"}
}