{
  "type": "Feature",
  "properties": {
    "addr:full":"Carr Frederic Mistral, 9 Figueres Girona 17600",
    "addr:housenumber":"9",
    "addr:postcode":"17600",
    "addr:street":"Carr Frederic Mistral",
    "iso:country":"ES",
    "sg:address":"Carr Frederic Mistral, 9",
    "sg:city":"Figueres",
    "sg:orig_category":"Carnicer\u00cdas, Carnicer\u00cdas",
    "sg:phone":"+34 972 50 41 55",
    "sg:postcode":"17600",
    "sg:province":"Girona",
    "wof:name":"Ginjaume S.l.",
    "wof:placetype":"venue"
},
  "geometry": {"coordinates":[2.9581780434,42.2609405518],"type":"Point"}
}