{
  "type": "Feature",
  "properties": {
    "addr:full":"Calle de Alejandro Barreiro Noya, 1 Coru\u00d1a A Coru\u00f1a 15006",
    "addr:housenumber":"1",
    "addr:postcode":"15006",
    "addr:street":"Calle De Alejandro Barreiro Noya;Corun\u0303A",
    "iso:country":"ES",
    "sg:address":"Calle de Alejandro Barreiro Noya, 1",
    "sg:city":"Coru\u00d1a",
    "sg:orig_category":"Asesor\u00cda Sobre Comunicaci\u00d3n De Empresas",
    "sg:phone":"+34 981 29 78 14",
    "sg:postcode":"15006",
    "sg:province":"A Coru\u00f1a",
    "wof:name":"Vazquez Fernandez Gumersindo",
    "wof:placetype":"venue"
},
  "geometry": {"coordinates":[-8.3958730698,43.3544082642],"type":"Point"}
}