{
  "type": "Feature",
  "properties": {
    "addr:full":"Calle de Don Pedro Infinito, 111 Palmas De Gran Canaria Las Palmas 35012",
    "addr:housenumber":"111",
    "addr:postcode":"35012",
    "addr:street":"Calle De Don;Infinito",
    "iso:country":"ES",
    "sg:address":"Calle de Don Pedro Infinito, 111",
    "sg:city":"Palmas De Gran Canaria",
    "sg:orig_category":"Madera Para Construcci\u00d3n E Industria",
    "sg:phone":"+34 928 25 41 56",
    "sg:postcode":"35012",
    "sg:province":"Las Palmas",
    "wof:name":"Abimir S.l.",
    "wof:placetype":"venue"
},
  "geometry": {"coordinates":[-15.435118,28.108154],"type":"Point"}
}