{
  "type": "Feature",
  "properties": {
    "addr:full":"Calle de General Franco, 2 Caparroso Navarra 31380",
    "addr:housenumber":"2",
    "addr:postcode":"31380",
    "addr:street":"Calle De General Franco",
    "iso:country":"ES",
    "sg:address":"Calle de General Franco, 2",
    "sg:city":"Caparroso",
    "sg:orig_category":"Molduras, Junquillos, Listones Y Molduras Perforadas",
    "sg:phone":"+34 948 73 04 04",
    "sg:postcode":"31380",
    "sg:province":"Navarra",
    "wof:name":"Sociedad Recreativa La Prevision",
    "wof:placetype":"venue"
},
  "geometry": {"coordinates":[-1.6522876024,42.3411407471],"type":"Point"}
}