{
  "type": "Feature",
  "properties": {
    "iso:country":"ES",
    "sg:address":"Carrer de Vint-i-dos, 12",
    "sg:city":"Bonavista",
    "sg:orig_category":"Agentes Generales De Seguros",
    "sg:phone":"+34 977 54 49 12",
    "sg:postcode":"43100",
    "sg:province":"Tarragona",
    "wof:name":"Ramon Assessors Scp",
    "wof:placetype":"venue"
},
  "geometry": {"coordinates":[1.1918940544,41.1184005737],"type":"Point"}
}