{
  "type": "Feature",
  "properties": {
    "iso:country":"ES",
    "sg:address":"Carrer de Sant Miquel, 52",
    "sg:city":"Masnou",
    "sg:orig_category":"Electricidad: Instaladores",
    "sg:phone":"+34 935 55 36 91",
    "sg:postcode":"08320",
    "sg:province":"Barcelona",
    "wof:name":"Vinardell Espinasa Domingo",
    "wof:placetype":"venue"
},
  "geometry": {"coordinates":[2.315459013,41.4807167053],"type":"Point"}
}