{
  "type": "Feature",
  "properties": {
    "iso:country":"ES",
    "sg:address":"Calle de Sol, 7",
    "sg:city":"Plasencia",
    "sg:orig_category":"Reposter\u00cdas",
    "sg:phone":"+34 927 41 58 65",
    "sg:postcode":"10600",
    "sg:province":"C\u00e1ceres",
    "wof:name":"Industrias Panaderas Placentinas S.a.",
    "wof:placetype":"venue"
},
  "geometry": {"coordinates":[-6.0892839432,40.0300254822],"type":"Point"}
}