{
  "type": "Feature",
  "properties": {
    "iso:country":"ES",
    "sg:address":"Ctra Alicante, Km. 0003,0",
    "sg:city":"Aspe",
    "sg:orig_category":"M\u00c1rmoles, Granitos Y Piedras Naturales",
    "sg:phone":"+34 965 49 41 68",
    "sg:postcode":"03680",
    "sg:province":"Alicante",
    "wof:name":"Cerdan Pavia Sergio",
    "wof:placetype":"venue"
},
  "geometry": {"coordinates":[-0.7590780258,38.3451805115],"type":"Point"}
}