{
  "type": "Feature",
  "properties": {
    "iso:country":"ES",
    "sg:address":"Carrer de Pompeu Fabra, 31",
    "sg:city":"Castelldefels",
    "sg:orig_category":"M\u00c9dicos: Pediatr\u00cda. Enfermedades De Los Ni\u00d1os",
    "sg:phone":"+34 936 45 24 62",
    "sg:postcode":"08860",
    "sg:province":"Barcelona",
    "wof:name":"Policlinic General De Castelldefels",
    "wof:placetype":"venue"
},
  "geometry": {"coordinates":[1.978474021,41.2805023193],"type":"Point"}
}