{
  "type": "Feature",
  "properties": {
    "addr:full":"Plaz Reyna Manescau, 1 Malaga M\u00e1laga 29002",
    "addr:housenumber":"1",
    "addr:postcode":"29002",
    "addr:street":"Malaga Ma\u0301Laga",
    "iso:country":"ES",
    "sg:address":"Plaz Reyna Manescau, 1",
    "sg:city":"Malaga",
    "sg:orig_category":"Asesor\u00cda Fiscal Y Jur\u00cddica",
    "sg:phone":"+34 952 32 85 67",
    "sg:postcode":"29002",
    "sg:province":"M\u00e1laga",
    "wof:name":"Herrero Quintana Antonio Jesus",
    "wof:placetype":"venue"
},
  "geometry": {"coordinates":[-4.4343781471,36.7058105469],"type":"Point"}
}