{
  "type": "Feature",
  "properties": {
    "addr:full":"Cno. Vjo. Alcorcon, S/n La Fortuna Madrid 28917",
    "addr:housenumber":"s / n",
    "addr:postcode":"28917",
    "addr:street":"Vjo. Alcorcon",
    "iso:country":"ES",
    "sg:address":"Cno. Vjo. Alcorcon, S/n",
    "sg:city":"La Fortuna",
    "sg:orig_category":"Parques De Atracciones Y Centros De Esparcimiento",
    "sg:phone":"+34 914 96 31 78",
    "sg:postcode":"28917",
    "sg:province":"Madrid",
    "sg:website":"www.ilusiona.com",
    "wof:name":"Inverexpan",
    "wof:placetype":"venue"
},
  "geometry": {"coordinates":[-3.7789890766,40.3557281494],"type":"Point"}
}