{
  "type": "Feature",
  "properties": {
    "iso:country":"ES",
    "sg:address":"Pase Castellana, 178",
    "sg:city":"Madrid",
    "sg:orig_category":"Asesor\u00cda Sobre Comunicaci\u00d3n De Empresas",
    "sg:phone":"+34 913 43 01 77",
    "sg:postcode":"28046",
    "sg:province":"Madrid",
    "wof:name":"Tegecovi S.a.",
    "wof:placetype":"venue"
},
  "geometry": {"coordinates":[-3.6891849041,40.4606742859],"type":"Point"}
}