{
  "type": "Feature",
  "properties": {
    "addr:full":"Calle de Matias Barrio Y Mier, 3 Aguilar Campoo Palencia 34800",
    "addr:housenumber":"3",
    "addr:postcode":"34800",
    "addr:street":"Calle De Matias Barrio Y Mier",
    "iso:country":"ES",
    "sg:address":"Calle de Matias Barrio Y Mier, 3",
    "sg:city":"Aguilar Campoo",
    "sg:orig_category":"Cueros Y Pieles (al Por Mayor)",
    "sg:phone":"+34 979 12 28 49",
    "sg:postcode":"34800",
    "sg:province":"Palencia",
    "wof:name":"Martin Lerena Jaime",
    "wof:placetype":"venue"
},
  "geometry": {"coordinates":[-4.2574658394,42.7935333252],"type":"Point"}
}