{
  "type": "Feature",
  "properties": {
    "addr:full":"Calle de Urarka, 14 Elorrio Vizcaya 48230",
    "addr:housenumber":"14",
    "addr:postcode":"48230",
    "addr:street":"Calle De Urarka",
    "iso:country":"ES",
    "sg:address":"Calle de Urarka, 14",
    "sg:city":"Elorrio",
    "sg:orig_category":"Peluquer\u00cdas, Peluquer\u00cda Mixta",
    "sg:phone":"+34 946 82 04 62",
    "sg:postcode":"48230",
    "sg:province":"Vizcaya",
    "wof:name":"Alfredo Urien Irisarri",
    "wof:placetype":"venue"
},
  "geometry": {"coordinates":[-2.5457959175,43.1326255798],"type":"Point"}
}