{
  "type": "Feature",
  "properties": {
    "addr:full":"Carr Tapers, 10 Bisbal D'emporda Girona 17100",
    "addr:housenumber":"10",
    "addr:postcode":"17100",
    "addr:street":"Carr Tapers",
    "iso:country":"ES",
    "sg:address":"Carr Tapers, 10",
    "sg:city":"Bisbal D'emporda",
    "sg:orig_category":"Inform\u00c1tica (estudios, Servicios, Asesor\u00cda, Formaci\u00d3n)",
    "sg:phone":"+34 972 64 32 04",
    "sg:postcode":"17100",
    "sg:province":"Girona",
    "wof:name":"Xarxa Control S.l.",
    "wof:placetype":"venue"
},
  "geometry": {"coordinates":[3.0347661972,41.9612884521],"type":"Point"}
}