{
  "type": "Feature",
  "properties": {
    "addr:full":"Cmno Alto De La Carrera, 15 Fuenlabrada Madrid 28942",
    "addr:postcode":"28942",
    "addr:street":"Cmno Alto De La Carrera 15",
    "iso:country":"ES",
    "sg:address":"Cmno Alto De La Carrera, 15",
    "sg:city":"Fuenlabrada",
    "sg:orig_category":"Chapister\u00cda",
    "sg:phone":"+34 916 07 94 79",
    "sg:postcode":"28942",
    "sg:province":"Madrid",
    "wof:name":"Lorancar 2003 S.l.",
    "wof:placetype":"venue"
},
  "geometry": {"coordinates":[-3.8370990753,40.2988739014],"type":"Point"}
}