{
  "type": "Feature",
  "properties": {
    "iso:country":"ES",
    "sg:address":"Pla\u00c7 Peiro, 7",
    "sg:city":"Tremp",
    "sg:orig_category":"Empresas De Carpinter\u00cda De Madera",
    "sg:phone":"+34 973 65 11 16",
    "sg:postcode":"25620",
    "sg:province":"Lleida",
    "wof:name":"Albert Arpa Ferran",
    "wof:placetype":"venue"
},
  "geometry": {"coordinates":[0.8103569746,42.2136611938],"type":"Point"}
}