{
  "type": "Feature",
  "properties": {
    "addr:full":"Calle de Antonino Vera, 63 Elda Alicante 03600",
    "addr:housenumber":"63",
    "addr:postcode":"03600",
    "addr:street":"Calle De Antonino Vera",
    "iso:country":"ES",
    "sg:address":"Calle de Antonino Vera, 63",
    "sg:city":"Elda",
    "sg:orig_category":"Peluquer\u00cdas, Peluquer\u00cda Mixta",
    "sg:phone":"+34 965 38 91 70",
    "sg:postcode":"03600",
    "sg:province":"Alicante",
    "wof:name":"Mati Ortin Peluqueria S.l.",
    "wof:placetype":"venue"
},
  "geometry": {"coordinates":[-0.7914313078,38.4762954712],"type":"Point"}
}