{
  "type": "Feature",
  "properties": {
    "addr:full":"Plaz Carlos Trias Bertran, 7 Madrid Madrid 28020",
    "addr:housenumber":"7",
    "addr:postcode":"madrid;28020",
    "addr:street":"Bertran",
    "iso:country":"ES",
    "sg:address":"Plaz Carlos Trias Bertran, 7",
    "sg:city":"Madrid",
    "sg:orig_category":"Formaci\u00d3n Continuada (variada)",
    "sg:phone":"+34 915 55 96 97",
    "sg:postcode":"28020",
    "sg:province":"Madrid",
    "sg:website":"www.redesdecampo.com",
    "wof:name":"Madrid Redes De Campo S.a.",
    "wof:placetype":"venue"
},
  "geometry": {"coordinates":[-3.6946210861,40.4513092041],"type":"Point"}
}