{
  "type": "Feature",
  "properties": {
    "addr:full":"Calle de Carboneras, 11 Madrid Madrid 28047",
    "addr:housenumber":"11",
    "addr:postcode":"madrid;28047",
    "addr:street":"Calle De Carboneras",
    "iso:country":"ES",
    "sg:address":"Calle de Carboneras, 11",
    "sg:city":"Madrid",
    "sg:orig_category":"Producci\u00d3n, Distribuci\u00d3n De Electricidad",
    "sg:phone":"+34 914 63 19 60",
    "sg:postcode":"28047",
    "sg:province":"Madrid",
    "wof:name":"Mellado Ramos Antonio",
    "wof:placetype":"venue"
},
  "geometry": {"coordinates":[-3.7501103878,40.4005012512],"type":"Point"}
}