{
  "type": "Feature",
  "properties": {
    "iso:country":"ES",
    "sg:address":"Carrer de Valencia, 14",
    "sg:city":"S. Joan Despi",
    "sg:orig_category":"Laboratorios Y Cl\u00cdnicas Veterinarias",
    "sg:phone":"+34 934 77 23 56",
    "sg:postcode":"08970",
    "sg:province":"Barcelona",
    "wof:name":"Reyes Rivera Cristina Belen",
    "wof:placetype":"venue"
},
  "geometry": {"coordinates":[2.0703430176,41.3661575317],"type":"Point"}
}