{
  "type": "Feature",
  "properties": {
    "addr:full":"Cmno Ronda (de), 63 Granada Granada 18004",
    "addr:housenumber":"63",
    "addr:postcode":"18004",
    "addr:street":"Cmno Ronda De",
    "iso:country":"ES",
    "sg:address":"Cmno Ronda (de), 63",
    "sg:city":"Granada",
    "sg:orig_category":"M\u00c9dicos: An\u00c1lisis Cl\u00cdnicos",
    "sg:phone":"+34 958 26 00 81",
    "sg:postcode":"18004",
    "sg:province":"Granada",
    "wof:name":"Samaniego Mu\u00f1oz Francisco",
    "wof:placetype":"venue"
},
  "geometry": {"coordinates":[-3.6051669121,37.1687507629],"type":"Point"}
}