{
  "type": "Feature",
  "properties": {
    "iso:country":"ES",
    "sg:address":"Calle de Francisco Vitoria, 1",
    "sg:city":"Zaragoza",
    "sg:orig_category":"Caf\u00c9s, Bares, Cervecer\u00cdas",
    "sg:phone":"+34 976 22 79 83",
    "sg:postcode":"50008",
    "sg:province":"Zaragoza",
    "wof:name":"Aragonesa De Sistemas Telefonicos S.l.",
    "wof:placetype":"venue"
},
  "geometry": {"coordinates":[-0.8802531958,41.6461601257],"type":"Point"}
}