{
  "type": "Feature",
  "properties": {
    "iso:country":"ES",
    "sg:address":"Calle de Diego De Los Reyes, 121",
    "sg:city":"Castilleja Cuesta",
    "sg:orig_category":"Tintes (fabricaci\u00d3n, Al Por Mayor)",
    "sg:phone":"+34 954 16 00 10",
    "sg:postcode":"41950",
    "sg:province":"Sevilla",
    "wof:name":"Vizcaino Rodriguez Emilio Jose",
    "wof:placetype":"venue"
},
  "geometry": {"coordinates":[-6.0558390617,37.3843803406],"type":"Point"}
}