{
  "type": "Feature",
  "properties": {
    "iso:country":"ES",
    "sg:address":"Ibai-ondo Bailara, 11",
    "sg:city":"Irura",
    "sg:orig_category":"Mec\u00c1nico Del Autom\u00d3vil",
    "sg:phone":"+34 943 69 22 05",
    "sg:postcode":"20271",
    "sg:province":"Guip\u00f9zcoa",
    "wof:name":"Leunda Imaz Martin",
    "wof:placetype":"venue"
},
  "geometry": {"coordinates":[-2.066286087,43.1691474915],"type":"Point"}
}