{
  "type": "Feature",
  "properties": {
    "iso:country":"ES",
    "sg:address":"Carr Sant Gervasi, 36",
    "sg:city":"Vilanova I La Geltru",
    "sg:orig_category":"Librer\u00cdas",
    "sg:phone":"+34 938 14 20 63",
    "sg:postcode":"08800",
    "sg:province":"Barcelona",
    "wof:name":"La Mulassa Vilanova S.l.",
    "wof:placetype":"venue"
},
  "geometry": {"coordinates":[1.7244369984,41.2260437012],"type":"Point"}
}