{
  "type": "Feature",
  "properties": {
    "iso:country":"ES",
    "sg:address":"Carrer de Llevant, 6",
    "sg:city":"Premia Mar",
    "sg:orig_category":"Zapatos (al Por Menor)",
    "sg:phone":"+34 937 51 03 93",
    "sg:postcode":"08330",
    "sg:province":"Barcelona",
    "wof:name":"Miralles Velis Concepcion",
    "wof:placetype":"venue"
},
  "geometry": {"coordinates":[2.3642120361,41.4908714294],"type":"Point"}
}