{
  "type": "Feature",
  "properties": {
    "addr:full":"Carr Germanias, 1 Xativa Valencia 46800",
    "addr:housenumber":"1",
    "addr:postcode":"46800",
    "addr:street":"Carr Germanias",
    "iso:country":"ES",
    "sg:address":"Carr Germanias, 1",
    "sg:city":"Xativa",
    "sg:orig_category":"Arquitectos",
    "sg:phone":"+34 962 28 05 57",
    "sg:postcode":"46800",
    "sg:province":"Valencia",
    "wof:name":"Benito Suay Jose Miguel",
    "wof:placetype":"venue"
},
  "geometry": {"coordinates":[-0.5200830102,38.9934272766],"type":"Point"}
}