{
  "type": "Feature",
  "properties": {
    "iso:country":"ES",
    "sg:address":"Calle de Conde De Altea, 40",
    "sg:city":"Valencia",
    "sg:orig_category":"M\u00c9dicos: Otorrinolaringolog\u00cda",
    "sg:phone":"+34 963 95 56 20",
    "sg:postcode":"46005",
    "sg:province":"Valencia",
    "wof:name":"Miro Perez Hilario",
    "wof:placetype":"venue"
},
  "geometry": {"coordinates":[-0.3660399914,39.4668197632],"type":"Point"}
}