{
  "type": "Feature",
  "properties": {
    "addr:full":"Av Ports D'europa, S/n Barcelona Barcelona 08040",
    "addr:housenumber":"s / n",
    "addr:postcode":"08040",
    "addr:street":"Av Ports D'Europa",
    "iso:country":"ES",
    "sg:address":"Av Ports D'europa, S/n",
    "sg:city":"Barcelona",
    "sg:orig_category":"Fabricaci\u00d3n De Productos L\u00c1cteos Y Derivados",
    "sg:phone":"+34 932 62 30 33",
    "sg:postcode":"08040",
    "sg:province":"Barcelona",
    "wof:name":"Corporacion Alimentaria Pe\u00f1asanta S.a.",
    "wof:placetype":"venue"
},
  "geometry": {"coordinates":[2.1338551044,41.3221168518],"type":"Point"}
}