{
  "type": "Feature",
  "properties": {
    "iso:country":"ES",
    "sg:address":"Plaz San Pedro, 10",
    "sg:city":"Jaca",
    "sg:orig_category":"Autob\u00das (explotaci\u00d3n Y Servicios De)",
    "sg:phone":"+34 974 36 00 88",
    "sg:postcode":"22700",
    "sg:province":"Huesca",
    "wof:name":"Irigoyen Lamarca Luis Alberto",
    "wof:placetype":"venue"
},
  "geometry": {"coordinates":[-0.5519520044,42.5658493042],"type":"Point"}
}