{
  "type": "Feature",
  "properties": {
    "iso:country":"ES",
    "sg:address":"Rond Barcelona, 2",
    "sg:city":"Figueres",
    "sg:orig_category":"Consultor\u00cdas Diversas",
    "sg:phone":"+34 972 67 42 85",
    "sg:postcode":"17600",
    "sg:province":"Girona",
    "wof:name":"Herrera Puente Alicia",
    "wof:placetype":"venue"
},
  "geometry": {"coordinates":[2.9582180977,42.263168335],"type":"Point"}
}