{
  "type": "Feature",
  "properties": {
    "addr:full":"Ctra. Madrid, 6 Villalpando Zamora 49630",
    "addr:housenumber":"6",
    "addr:postcode":"49630",
    "addr:street":"Ctra. Madrid",
    "iso:country":"ES",
    "sg:address":"Ctra. Madrid, 6",
    "sg:city":"Villalpando",
    "sg:classifiers":[
        {
            "category":"Taxi",
            "type":"Transportation"
        }
    ],
    "sg:phone":"+34 980 66 03 29",
    "sg:postcode":"49630",
    "sg:province":"Zamora",
    "wof:name":"Gonzalez Zamorano Ismael",
    "wof:placetype":"venue"
},
  "geometry": {"coordinates":[-5.4135689735,41.8648910522],"type":"Point"}
}