{
  "type": "Feature",
  "properties": {
    "iso:country":"ES",
    "sg:address":"Calle de Rector Martin Villa, 7",
    "sg:city":"Almonte",
    "sg:orig_category":"Fisioterapia",
    "sg:phone":"+34 959 40 72 10",
    "sg:postcode":"21730",
    "sg:province":"Huelva",
    "wof:name":"Marquez Rodriguez Francisco",
    "wof:placetype":"venue"
},
  "geometry": {"coordinates":[-6.5183391571,37.262878418],"type":"Point"}
}