{
  "type": "Feature",
  "properties": {
    "addr:full":"Calle de Santiago Fernandez Portoles, 34 Tudela Navarra 31500",
    "addr:housenumber":"34",
    "addr:postcode":"31500",
    "addr:street":"Calle De Santiago;Portoles",
    "iso:country":"ES",
    "sg:address":"Calle de Santiago Fernandez Portoles, 34",
    "sg:city":"Tudela",
    "sg:orig_category":"\u00d3ptica: Instrumentos (fabricaci\u00d3n)",
    "sg:phone":"+34 948 41 20 91",
    "sg:postcode":"31500",
    "sg:province":"Navarra",
    "wof:name":"Pascual Ramirez Jesus Miguel",
    "wof:placetype":"venue"
},
  "geometry": {"coordinates":[-1.6020280123,42.0553703308],"type":"Point"}
}