{
  "type": "Feature",
  "properties": {
    "addr:full":"Calle de Joaquin Blume, 3 Veguellina Orbigo Le\u00f3n 24350",
    "addr:housenumber":"3",
    "addr:postcode":"24350",
    "addr:street":"Calle De Joaquin Blume;Leo\u0301N",
    "iso:country":"ES",
    "sg:address":"Calle de Joaquin Blume, 3",
    "sg:city":"Veguellina Orbigo",
    "sg:orig_category":"Peluqueros: De Se\u00d1oras",
    "sg:phone":"+34 987 37 62 44",
    "sg:postcode":"24350",
    "sg:province":"Le\u00f3n",
    "wof:name":"Alvarez Badeso Rosa Maria",
    "wof:placetype":"venue"
},
  "geometry": {"coordinates":[-5.8866043091,42.4362182617],"type":"Point"}
}