{
  "type": "Feature",
  "properties": {
    "addr:full":"Pl Santiago Russinyol, 4 Tarragona Tarragona 43003",
    "addr:housenumber":"4",
    "addr:postcode":"43003",
    "addr:street":"Pl Santiago Russinyol",
    "iso:country":"ES",
    "sg:address":"Pl Santiago Russinyol, 4",
    "sg:city":"Tarragona",
    "sg:orig_category":"Molduras, Junquillos, Listones Y Molduras Perforadas",
    "sg:phone":"+34 977 22 88 67",
    "sg:postcode":"43003",
    "sg:province":"Tarragona",
    "wof:name":"Valdivieso Espinosa Olinda",
    "wof:placetype":"venue"
},
  "geometry": {"coordinates":[1.2541049719,41.1169281006],"type":"Point"}
}