{
  "type": "Feature",
  "properties": {
    "addr:full":"Carr Gran, 39 Castell Islas Baleares 07720",
    "addr:housenumber":"39",
    "addr:postcode":"07720",
    "addr:street":"Carr Gran",
    "iso:country":"ES",
    "sg:address":"Carr Gran, 39",
    "sg:city":"Castell",
    "sg:orig_category":"\u00d3ptica: Instrumentos (fabricaci\u00d3n)",
    "sg:phone":"+34 971 35 10 56",
    "sg:postcode":"07720",
    "sg:province":"Islas Baleares",
    "wof:name":"Carreras Fiol Maria Gracia",
    "wof:placetype":"venue"
},
  "geometry": {"coordinates":[4.2858448029,39.879650116],"type":"Point"}
}