{
  "type": "Feature",
  "properties": {
    "iso:country":"ES",
    "sg:address":"C/ Sabadell, 18",
    "sg:city":"Alcoi",
    "sg:orig_category":"M\u00c9dicos: Cirug\u00cda Pl\u00c1stica, Reconstructiva Y Est\u00c9tica",
    "sg:phone":"+34 966 52 16 89",
    "sg:postcode":"03804",
    "sg:province":"Alicante",
    "wof:name":"Gasta\u00f1aga Egusquiza Juan Vicente",
    "wof:placetype":"venue"
},
  "geometry": {"coordinates":[-0.4672499895,38.7088241577],"type":"Point"}
}