{
  "type": "Feature",
  "properties": {
    "addr:full":"Pla\u00c7 Espanya, 13 Mao Islas Baleares 07701",
    "addr:postcode":"13;07701",
    "iso:country":"ES",
    "sg:address":"Pla\u00c7 Espanya, 13",
    "sg:city":"Mao",
    "sg:orig_category":"Alquiler De Veh\u00cdculos: Turismos Y Utilitarios",
    "sg:phone":"+34 971 36 84 65",
    "sg:postcode":"07701",
    "sg:province":"Islas Baleares",
    "sg:website":"www.autosvalls.com",
    "wof:name":"Autos Punta Prima S.l.",
    "wof:placetype":"venue"
},
  "geometry": {"coordinates":[4.2435894012,39.9345855713],"type":"Point"}
}