{
  "type": "Feature",
  "properties": {
    "iso:country":"ES",
    "sg:address":"Calle de Lerida, 8",
    "sg:city":"Puertollano",
    "sg:orig_category":"Mantenimiento Industrial",
    "sg:phone":"+34 926 44 14 09",
    "sg:postcode":"13500",
    "sg:province":"Ciudad Real",
    "wof:name":"Siemsa Centro S.a.",
    "wof:placetype":"venue"
},
  "geometry": {"coordinates":[-4.0933790207,38.6824417114],"type":"Point"}
}