{
  "type": "Feature",
  "properties": {
    "addr:full":"Av Bejar, 45 Terrassa Barcelona 08225",
    "addr:housenumber":"45",
    "addr:postcode":"08225",
    "addr:street":"Av Bejar",
    "iso:country":"ES",
    "sg:address":"Av Bejar, 45",
    "sg:city":"Terrassa",
    "sg:orig_category":"Abogados",
    "sg:phone":"+34 937 35 66 98",
    "sg:postcode":"08225",
    "sg:province":"Barcelona",
    "wof:name":"Gestoria Administrativa Amela S.l.",
    "wof:placetype":"venue"
},
  "geometry": {"coordinates":[2.0105059147,41.5800247192],"type":"Point"}
}