{
  "type": "Feature",
  "properties": {
    "iso:country":"ES",
    "sg:address":"Castellar (pol Ind Gavarra), 5",
    "sg:city":"Centelles",
    "sg:orig_category":"Aparatos De Medida, Control, Regulaci\u00d3n Y Detecci\u00d3n",
    "sg:phone":"+34 938 81 36 00",
    "sg:postcode":"08540",
    "sg:province":"Barcelona",
    "sg:website":"www.pimecsa.com",
    "wof:name":"Pimec S.l.",
    "wof:placetype":"venue"
},
  "geometry": {"coordinates":[2.2250359058,41.7881851196],"type":"Point"}
}