{
  "type": "Feature",
  "properties": {
    "addr:full":"Ctra Corredoria Baja, 122 Corredoria Asturias 33011",
    "addr:housenumber":"122",
    "addr:postcode":"33011",
    "addr:street":"Ctra Corredoria Baja;Asturias",
    "iso:country":"ES",
    "sg:address":"Ctra Corredoria Baja, 122",
    "sg:city":"Corredoria",
    "sg:orig_category":"Empresas De Carpinter\u00cda De Madera",
    "sg:phone":"+34 985 29 48 77",
    "sg:postcode":"33011",
    "sg:province":"Asturias",
    "wof:name":"Vazquez Lago Jose Luis",
    "wof:placetype":"venue"
},
  "geometry": {"coordinates":[-5.8311891556,43.3788986206],"type":"Point"}
}