{
  "type": "Feature",
  "properties": {
    "addr:full":"Ctr Toledo-tlvra., Km. 0023,0 Burujon Toledo 45519",
    "addr:postcode":"45519",
    "addr:street":"Toledo-Tlvra. Km. 0023,0",
    "iso:country":"ES",
    "sg:address":"Ctr Toledo-tlvra., Km. 0023,0",
    "sg:city":"Burujon",
    "sg:orig_category":"Producci\u00d3n, Venta De Productos De Agricultura Biol\u00d3gica",
    "sg:phone":"+34 925 78 90 98",
    "sg:postcode":"45519",
    "sg:province":"Toledo",
    "wof:name":"Bosques Naturales S.a.",
    "wof:placetype":"venue"
},
  "geometry": {"coordinates":[-97.78224945069999,45.7040786743],"type":"Point"}
}