{
  "type": "Feature",
  "properties": {
    "addr:full":"Calle de Ruzafa, 28 Valencia Valencia 46004",
    "addr:housenumber":"28",
    "addr:postcode":"46004",
    "addr:street":"Calle De Ruzafa",
    "iso:country":"ES",
    "sg:address":"Calle de Ruzafa, 28",
    "sg:city":"Valencia",
    "sg:orig_category":"Arquitectos",
    "sg:phone":"+34 963 52 21 88",
    "sg:postcode":"46004",
    "sg:province":"Valencia",
    "wof:name":"Vila Ferrer Salvador",
    "wof:placetype":"venue"
},
  "geometry": {"coordinates":[-0.3741930127,39.4652938843],"type":"Point"}
}