{
  "type": "Feature",
  "properties": {
    "iso:country":"ES",
    "sg:address":"Calle de Esperanza, 103",
    "sg:city":"Dos Hermanas",
    "sg:orig_category":"Farmacias",
    "sg:phone":"+34 954 72 05 22",
    "sg:postcode":"41700",
    "sg:province":"Sevilla",
    "wof:name":"Cabezuelo E Hijos C.b",
    "wof:placetype":"venue"
},
  "geometry": {"coordinates":[-5.917318821,37.2915534973],"type":"Point"}
}