{
  "type": "Feature",
  "properties": {
    "iso:country":"ES",
    "sg:address":"Calle de Azucena, 16",
    "sg:city":"Azuqueca Henares",
    "sg:orig_category":"Mensajer\u00cda Express, Portes Internacionales",
    "sg:phone":"+34 949 26 51 81",
    "sg:postcode":"19200",
    "sg:province":"Guadalajara",
    "wof:name":"Ceyco Multiservicios Sll",
    "wof:placetype":"venue"
},
  "geometry": {"coordinates":[-3.2642951012,40.5662689209],"type":"Point"}
}