{
  "type": "Feature",
  "properties": {
    "addr:full":"O Souto, 5 Vilari\u00f1o Conso Ourense 32557",
    "addr:housenumber":"5",
    "addr:postcode":"32557",
    "addr:street":"Vilarin\u0303O Conso",
    "iso:country":"ES",
    "sg:address":"O Souto, 5",
    "sg:city":"Vilari\u00f1o Conso",
    "sg:orig_category":"Carnicer\u00cdas, Carnicer\u00cdas",
    "sg:phone":"+34 988 34 02 65",
    "sg:postcode":"32557",
    "sg:province":"Ourense",
    "wof:name":"Vaz Cota Graciano",
    "wof:placetype":"venue"
},
  "geometry": {"coordinates":[-7.1768798828,42.166103363],"type":"Point"}
}