{
  "type": "Feature",
  "properties": {
    "iso:country":"ES",
    "sg:address":"Calle de Gil De Jasa, 22",
    "sg:city":"Zaragoza",
    "sg:orig_category":"Cr\u00cda De Animales",
    "sg:phone":"+34 976 23 46 05",
    "sg:postcode":"50006",
    "sg:province":"Zaragoza",
    "wof:name":"Valles Marti Juan",
    "wof:placetype":"venue"
},
  "geometry": {"coordinates":[-0.886951983,41.6430892944],"type":"Point"}
}