{
  "type": "Feature",
  "properties": {
    "addr:full":"Calle de Dulcinea, 30 Madrid Madrid 28020",
    "addr:housenumber":"30",
    "addr:postcode":"madrid;28020",
    "addr:street":"Calle De Dulcinea",
    "iso:country":"ES",
    "sg:address":"Calle de Dulcinea, 30",
    "sg:city":"Madrid",
    "sg:orig_category":"Promotores Constructores",
    "sg:phone":"+34 915 35 12 36",
    "sg:postcode":"28020",
    "sg:province":"Madrid",
    "wof:name":"Construcciones M.montero Pascual S.l.",
    "wof:placetype":"venue"
},
  "geometry": {"coordinates":[-3.6998705864,40.4492912292],"type":"Point"}
}