{
  "type": "Feature",
  "properties": {
    "iso:country":"ES",
    "sg:address":"Carr Moli, 44",
    "sg:city":"Cassa Selva",
    "sg:orig_category":"Florister\u00cdas",
    "sg:phone":"+34 972 46 18 83",
    "sg:postcode":"17244",
    "sg:province":"Girona",
    "wof:name":"Art Floral M.d. S.l.",
    "wof:placetype":"venue"
},
  "geometry": {"coordinates":[2.8740253448,41.8892326355],"type":"Point"}
}