{
  "type": "Feature",
  "properties": {
    "iso:country":"ES",
    "sg:address":"Ctra Miralcamp, 2",
    "sg:city":"Mollerussa",
    "sg:orig_category":"Empresarios",
    "sg:phone":"+34 973 71 28 71",
    "sg:postcode":"25230",
    "sg:province":"Lleida",
    "wof:name":"Mollo Saball Albert",
    "wof:placetype":"venue"
},
  "geometry": {"coordinates":[0.8930749893,41.6239814758],"type":"Point"}
}