{
  "type": "Feature",
  "properties": {
    "iso:country":"ES",
    "sg:address":"Benjamin Franklin, 3",
    "sg:city":"Gijon",
    "sg:orig_category":"Cristaler\u00cdas",
    "sg:phone":"+34 985 16 77 90",
    "sg:postcode":"33211",
    "sg:province":"Asturias",
    "wof:name":"Cristal Norte S.l.",
    "wof:placetype":"venue"
},
  "geometry": {"coordinates":[-5.6911811829,43.5075683594],"type":"Point"}
}