{
  "type": "Feature",
  "properties": {
    "iso:country":"ES",
    "sg:address":"Calle de Antequera Y Bobadilla, 73",
    "sg:city":"Cuesta",
    "sg:orig_category":"Quincaller\u00cda (al Por Menor)",
    "sg:phone":"+34 922 22 53 21",
    "sg:postcode":"38320",
    "sg:province":"Santa Cruz De Tenerife",
    "wof:name":"Gonzalez Feo Josefa Benita",
    "wof:placetype":"venue"
},
  "geometry": {"coordinates":[-16.2793331146,28.4715938568],"type":"Point"}
}