{
  "type": "Feature",
  "properties": {
    "iso:country":"ES",
    "sg:address":"Rbla Salvador Lluch, 8",
    "sg:city":"Gava",
    "sg:orig_category":"Cer\u00c1micas: Material Y Suministros",
    "sg:phone":"+34 936 62 34 19",
    "sg:postcode":"08850",
    "sg:province":"Barcelona",
    "wof:name":"Material Del Baix S.l.",
    "wof:placetype":"venue"
},
  "geometry": {"coordinates":[2.0053420067,41.3054618835],"type":"Point"}
}