{
  "type": "Feature",
  "properties": {
    "addr:full":"Calle de Trinidad, 3 Lebrija Sevilla 41740",
    "addr:housenumber":"3",
    "addr:postcode":"41740",
    "addr:street":"Calle De Trinidad",
    "iso:country":"ES",
    "sg:address":"Calle de Trinidad, 3",
    "sg:city":"Lebrija",
    "sg:orig_category":"Arquitectos",
    "sg:phone":"+34 955 97 18 19",
    "sg:postcode":"41740",
    "sg:province":"Sevilla",
    "wof:name":"Arteces S.l.",
    "wof:placetype":"venue"
},
  "geometry": {"coordinates":[-6.0798201561,36.917881012],"type":"Point"}
}