{
  "type": "Feature",
  "properties": {
    "addr:full":"Calle de General Franco, 7 Montefrio Granada 18270",
    "addr:housenumber":"7",
    "addr:postcode":"18270",
    "addr:street":"Calle De General Franco",
    "iso:country":"ES",
    "sg:address":"Calle de General Franco, 7",
    "sg:city":"Montefrio",
    "sg:orig_category":"Ingeniero",
    "sg:phone":"+34 958 33 65 41",
    "sg:postcode":"18270",
    "sg:province":"Granada",
    "wof:name":"Osuna Lopez Francisco",
    "wof:placetype":"venue"
},
  "geometry": {"coordinates":[-4.0089788437,37.3199958801],"type":"Point"}
}