{
  "type": "Feature",
  "properties": {
    "iso:country":"ES",
    "sg:address":"Calle de Martin Ferrador, S/n",
    "sg:city":"Jerez De La Frontera",
    "sg:orig_category":"Venta, Instalaci\u00d3n De Calefacci\u00d3n",
    "sg:phone":"+34 956 31 27 48",
    "sg:postcode":"11405",
    "sg:province":"C\u00e1diz",
    "wof:name":"Garrido Mateo Juan",
    "wof:placetype":"venue"
},
  "geometry": {"coordinates":[-6.1275792122,36.6903343201],"type":"Point"}
}