{
  "type": "Feature",
  "properties": {
    "iso:country":"ES",
    "sg:address":"Avda Minero (el), 3",
    "sg:city":"Abanto",
    "sg:orig_category":"Farmacias",
    "sg:phone":"+34 946 36 22 04",
    "sg:postcode":"48500",
    "sg:province":"Vizcaya",
    "wof:name":"Maria Elvira Loizaga Casta\u00f1os",
    "wof:placetype":"venue"
},
  "geometry": {"coordinates":[-3.0746810436,43.3154182434],"type":"Point"}
}