{
  "type": "Feature",
  "properties": {
    "addr:full":"Carrer de Riera Can Pahissa, S/n Molins Rei Barcelona 08750",
    "addr:housenumber":"s",
    "addr:postcode":"08750",
    "addr:street":"Carrer De Riera Can Pahissa;/ N Molins",
    "iso:country":"ES",
    "sg:address":"Carrer de Riera Can Pahissa, S/n",
    "sg:city":"Molins Rei",
    "sg:orig_category":"Otros Trabajos De Limpieza Y Mantenimiento (extracci\u00d3n De Polvo, Recogida De Amianto Y Desespumado)",
    "sg:phone":"+34 936 80 24 84",
    "sg:postcode":"08750",
    "sg:province":"Barcelona",
    "wof:name":"Nova Tecnologia De Maquinaria S.l.",
    "wof:placetype":"venue"
},
  "geometry": {"coordinates":[2.0308890343,41.3982048035],"type":"Point"}
}