{
  "type": "Feature",
  "properties": {
    "iso:country":"ES",
    "sg:address":"Calle de San Isidro, 34",
    "sg:city":"Tafalla",
    "sg:orig_category":"Farmacias",
    "sg:phone":"+34 948 70 32 23",
    "sg:postcode":"31300",
    "sg:province":"Navarra",
    "wof:name":"Arrondo Arbea Felisa",
    "wof:placetype":"venue"
},
  "geometry": {"coordinates":[-1.6793607473,42.5244827271],"type":"Point"}
}