{
  "type": "Feature",
  "properties": {
    "iso:country":"ES",
    "sg:address":"Calle de Alcalde Jose Maria De Llanos, 11",
    "sg:city":"Malaga",
    "sg:orig_category":"Material Y Suministros Para Imprenta E Industrias Gr\u00c1ficas",
    "sg:phone":"+34 952 34 48 49",
    "sg:postcode":"29003",
    "sg:province":"M\u00e1laga",
    "wof:name":"Graficas Lahoz S.l.",
    "wof:placetype":"venue"
},
  "geometry": {"coordinates":[-4.4502897263,36.6979255676],"type":"Point"}
}