{
  "type": "Feature",
  "properties": {
    "iso:country":"ES",
    "sg:address":"Carrer de Mallorca, 330",
    "sg:city":"Barcelona",
    "sg:orig_category":"Arquitectos",
    "sg:phone":"+34 932 07 57 01",
    "sg:postcode":"08037",
    "sg:province":"Barcelona",
    "wof:name":"Foguet Castells Juan",
    "wof:placetype":"venue"
},
  "geometry": {"coordinates":[2.1686170101,41.3982009888],"type":"Point"}
}