{
  "type": "Feature",
  "properties": {
    "iso:country":"ES",
    "sg:address":"Rua Icaro, 26",
    "sg:city":"Pazo Do Rio",
    "sg:orig_category":"Electricidad: Instaladores",
    "sg:phone":"+34 981 63 88 12",
    "sg:postcode":"15172",
    "sg:province":"La Coru\u00f1a",
    "wof:name":"Electricidad Encinas S.l.",
    "wof:placetype":"venue"
},
  "geometry": {"coordinates":[-8.3740053177,43.3324584961],"type":"Point"}
}