{
  "type": "Feature",
  "properties": {
    "addr:full":"Calle de Oca\u00d1a, 45 Horcajo Santiago Cuenca 16410",
    "addr:housenumber":"45",
    "addr:postcode":"16410",
    "addr:street":"Calle De Ocan\u0303A;Cuenca",
    "iso:country":"ES",
    "sg:address":"Calle de Oca\u00d1a, 45",
    "sg:city":"Horcajo Santiago",
    "sg:orig_category":"Empresas De Limpieza",
    "sg:phone":"+34 969 12 77 01",
    "sg:postcode":"16410",
    "sg:province":"Cuenca",
    "wof:name":"Lopez Roldan Julian",
    "wof:placetype":"venue"
},
  "geometry": {"coordinates":[-3.0044369698,39.8429145813],"type":"Point"}
}