{
  "type": "Feature",
  "properties": {
    "addr:full":"Calle de Uruguay, 29 Coslada Madrid 28820",
    "addr:housenumber":"29",
    "addr:postcode":"28820",
    "addr:street":"Calle De Uruguay",
    "iso:country":"ES",
    "sg:address":"Calle de Uruguay, 29",
    "sg:city":"Coslada",
    "sg:orig_category":"Empresas De Pintura Y Revestimientos",
    "sg:phone":"+34 916 71 00 14",
    "sg:postcode":"28820",
    "sg:province":"Madrid",
    "wof:name":"Garcia Viana Luis",
    "wof:placetype":"venue"
},
  "geometry": {"coordinates":[-3.5499820709,40.4251022339],"type":"Point"}
}