{
  "type": "Feature",
  "properties": {
    "addr:full":"Ctra Botanico (del), 17 Puerto Cruz Santa Cruz De Tenerife 38400",
    "addr:postcode":"38400",
    "addr:street":"Ctra Botanico Del 17 Puerto Cruz",
    "iso:country":"ES",
    "sg:address":"Ctra Botanico (del), 17",
    "sg:city":"Puerto Cruz",
    "sg:orig_category":"Inmobiliaria (agencias)",
    "sg:phone":"+34 922 37 80 04",
    "sg:postcode":"38400",
    "sg:province":"Santa Cruz De Tenerife",
    "sg:website":"www.optima-tenerife.com",
    "wof:name":"Inmobiliaria Optima Canarias S.l.",
    "wof:placetype":"venue"
},
  "geometry": {"coordinates":[-16.5455913544,28.4136734009],"type":"Point"}
}