{
  "type": "Feature",
  "properties": {
    "iso:country":"ES",
    "sg:address":"Cust Aldapeta De, 59",
    "sg:city":"Donostia-san Sebastian",
    "sg:orig_category":"Masajes",
    "sg:phone":"+34 943 46 19 17",
    "sg:postcode":"20009",
    "sg:province":"Guip\u00f9zcoa",
    "wof:name":"Echeverria Echevestre Maria Cristina",
    "wof:placetype":"venue"
},
  "geometry": {"coordinates":[-1.9794000387,43.3173789978],"type":"Point"}
}