{
  "type": "Feature",
  "properties": {
    "addr:full":"Cno. Rinconada, S/n Solana De Rioalmar \u00c1vila 05144",
    "addr:housenumber":"s / n",
    "addr:postcode":"05144",
    "addr:street":"Cno. Rinconada",
    "iso:country":"ES",
    "sg:address":"Cno. Rinconada, S/n",
    "sg:city":"Solana De Rioalmar",
    "sg:orig_category":"Fabricaci\u00d3n De Quesos",
    "sg:phone":"+34 920 23 93 09",
    "sg:postcode":"05144",
    "sg:province":"\u00c1vila",
    "wof:name":"S.a.t.cabreros De La Sierra De Avila",
    "wof:placetype":"venue"
},
  "geometry": {"coordinates":[-5.0112290382,40.7376441956],"type":"Point"}
}