{
  "type": "Feature",
  "properties": {
    "addr:full":"Cmno Via Sacra, 3 Osuna Sevilla 41640",
    "addr:housenumber":"3",
    "addr:postcode":"41640",
    "addr:street":"Cmno Via Sacra",
    "iso:country":"ES",
    "sg:address":"Cmno Via Sacra, 3",
    "sg:city":"Osuna",
    "sg:orig_category":"Escultores, Estatuarios E Imagineros",
    "sg:phone":"+34 954 81 11 17",
    "sg:postcode":"41640",
    "sg:province":"Sevilla",
    "wof:name":"Valdivia Gomez Jose Luis",
    "wof:placetype":"venue"
},
  "geometry": {"coordinates":[-5.1028141975,37.2371253967],"type":"Point"}
}