{
  "type": "Feature",
  "properties": {
    "iso:country":"ES",
    "sg:address":"Calle de Chindia (de), 2",
    "sg:city":"Valle S. Lorenzo",
    "sg:orig_category":"Textil",
    "sg:phone":"+34 922 76 57 40",
    "sg:postcode":"38626",
    "sg:province":"Santa Cruz De Tenerife",
    "wof:name":"Hernandez Y Cabrera E Hijas S.l.",
    "wof:placetype":"venue"
},
  "geometry": {"coordinates":[-16.6575222015,28.0909309387],"type":"Point"}
}