{
  "type": "Feature",
  "properties": {
    "iso:country":"ES",
    "sg:address":"Ctra. C. Guardas, S/n",
    "sg:city":"Zufre",
    "sg:orig_category":"Inmobiliaria (agencias)",
    "sg:phone":"+34 959 50 70 42",
    "sg:postcode":"21210",
    "sg:province":"Huelva",
    "wof:name":"Ramos Gonzalez Antonio",
    "wof:placetype":"venue"
},
  "geometry": {"coordinates":[-6.3382301331,37.8345527649],"type":"Point"}
}