{
  "type": "Feature",
  "properties": {
    "addr:full":"Calle de Rosita, S/n Fuensanta -villa Ines Almer\u00eda 04230",
    "addr:housenumber":"/ n",
    "addr:postcode":"04230",
    "addr:street":"Calle De Rosita S;Fuensanta Villa;Almeri\u0301A",
    "iso:country":"ES",
    "sg:address":"Calle de Rosita, S/n",
    "sg:city":"Fuensanta -villa Ines",
    "sg:orig_category":"Agencias Y Asesores De Publicidad",
    "sg:phone":"+34 950 14 51 12",
    "sg:postcode":"04230",
    "sg:province":"Almer\u00eda",
    "wof:name":"Rotulos Luminosos Plastisol S.l.",
    "wof:placetype":"venue"
},
  "geometry": {"coordinates":[-2.4443490505,36.8670310974],"type":"Point"}
}