{
  "type": "Feature",
  "properties": {
    "addr:full":"Matxinporta Kalea, 34 Urretxu Guip\u00f9zcoa 20700",
    "addr:housenumber":"34",
    "addr:postcode":"20700",
    "addr:street":"Matxinporta Kalea;Guipu\u0300Zcoa",
    "iso:country":"ES",
    "sg:address":"Matxinporta Kalea, 34",
    "sg:city":"Urretxu",
    "sg:orig_category":"Autob\u00das (explotaci\u00d3n Y Servicios De)",
    "sg:phone":"+34 943 72 15 57",
    "sg:postcode":"20700",
    "sg:province":"Guip\u00f9zcoa",
    "wof:name":"J. Apaolaza Autobusak S.l.",
    "wof:placetype":"venue"
},
  "geometry": {"coordinates":[-2.3165919781,43.0972747803],"type":"Point"}
}