{
  "type": "Feature",
  "properties": {
    "iso:country":"ES",
    "sg:address":"Avda Salamanca, 66",
    "sg:city":"Ciudad Rodrigo",
    "sg:orig_category":"Construcciones Met\u00c1licas",
    "sg:phone":"+34 923 46 25 37",
    "sg:postcode":"37500",
    "sg:province":"Salamanca",
    "wof:name":"Corsa Regalado S.l.",
    "wof:placetype":"venue"
},
  "geometry": {"coordinates":[-6.5284590721,40.6041183472],"type":"Point"}
}