{
  "type": "Feature",
  "properties": {
    "iso:country":"ES",
    "sg:address":"Carrer de Terra Alta, 40",
    "sg:city":"Poligono Industrial Can Carner",
    "sg:orig_category":"Organizaciones Profesionales",
    "sg:phone":"+34 937 14 87 78",
    "sg:postcode":"08211",
    "sg:province":"Barcelona",
    "wof:name":"Planchisteria Industrial Salgar S.l.",
    "wof:placetype":"venue"
},
  "geometry": {"coordinates":[2.0857300758,41.6151885986],"type":"Point"}
}