{
  "type": "Feature",
  "properties": {
    "addr:full":"Calle de Alejandro Seiquer, 1 San Lorenzo Murcia 30001",
    "addr:housenumber":"1",
    "addr:postcode":"30001",
    "addr:street":"Calle De Alejandro Seiquer",
    "iso:country":"ES",
    "sg:address":"Calle de Alejandro Seiquer, 1",
    "sg:city":"San Lorenzo",
    "sg:orig_category":"Confecci\u00d3n De Trajes Para Se\u00d1oras",
    "sg:phone":"+34 968 21 96 23",
    "sg:postcode":"30001",
    "sg:province":"Murcia",
    "wof:name":"Salvador Clares Peligros",
    "wof:placetype":"venue"
},
  "geometry": {"coordinates":[-1.1298867464,37.9834747314],"type":"Point"}
}