{
  "type": "Feature",
  "properties": {
    "iso:country":"ES",
    "sg:address":"Calle de Olimpico Francisco Fernandez Ochoa, 18",
    "sg:city":"Alcorcon",
    "sg:orig_category":"Ingeniero",
    "sg:phone":"+34 916 44 93 22",
    "sg:postcode":"28923",
    "sg:province":"Madrid",
    "sg:website":"www.tekniker.es",
    "wof:name":"Fundacion Tekniker",
    "wof:placetype":"venue"
},
  "geometry": {"coordinates":[-3.8127510548,40.3444252014],"type":"Point"}
}