{
  "type": "Feature",
  "properties": {
    "addr:full":"Autovia Del 92, Km. 0228,0 Chauchina Granada 18330",
    "addr:postcode":"18330",
    "addr:street":"Autovia Del 92 Km. 0228,0",
    "iso:country":"ES",
    "sg:address":"Autovia Del 92, Km. 0228,0",
    "sg:city":"Chauchina",
    "sg:orig_category":"Arboricultura Y Producci\u00d3n De Frutas",
    "sg:phone":"+34 958 45 50 28",
    "sg:postcode":"18330",
    "sg:province":"Granada",
    "wof:name":"A.v.t.nevafrio S.l.",
    "wof:placetype":"venue"
},
  "geometry": {"coordinates":[-3.7862064838,37.1918411255],"type":"Point"}
}