{
  "type": "Feature",
  "properties": {
    "iso:country":"ES",
    "sg:address":"Calle de Tribulete, 7",
    "sg:city":"Madrid",
    "sg:orig_category":"Zapatos (al Por Menor)",
    "sg:phone":"+34 915 28 10 78",
    "sg:postcode":"28012",
    "sg:province":"Madrid",
    "wof:name":"Gonzalez Fernandez Maria Jesus",
    "wof:placetype":"venue"
},
  "geometry": {"coordinates":[-3.7020380497,40.4078445435],"type":"Point"}
}