{
  "type": "Feature",
  "properties": {
    "iso:country":"ES",
    "sg:address":"Cust Loreto, 5",
    "sg:city":"Tudela",
    "sg:orig_category":"Comercio De Piezas De Recambio Y De Accesorios De Veh\u00cdculos, Veh\u00cdculos Industriales",
    "sg:phone":"+34 948 40 22 01",
    "sg:postcode":"31500",
    "sg:province":"Navarra",
    "wof:name":"Luis Miguel Alonso Mayor",
    "wof:placetype":"venue"
},
  "geometry": {"coordinates":[-1.6075140238,42.0591659546],"type":"Point"}
}