{
  "type": "Feature",
  "properties": {
    "iso:country":"ES",
    "sg:address":"Calle de Herreria, 3",
    "sg:city":"Caldas De Reis",
    "sg:orig_category":"Molduras, Junquillos, Listones Y Molduras Perforadas",
    "sg:phone":"+34 986 54 08 40",
    "sg:postcode":"36650",
    "sg:province":"Pontevedra",
    "wof:name":"Fuentes Cayo Amparo",
    "wof:placetype":"venue"
},
  "geometry": {"coordinates":[-8.6427059174,42.6019744873],"type":"Point"}
}