{
  "type": "Feature",
  "properties": {
    "addr:full":"Calle de Pelayo, 13 Gijon Asturias 33205",
    "addr:housenumber":"13",
    "addr:postcode":"33205",
    "addr:street":"Calle De Pelayo",
    "iso:country":"ES",
    "sg:address":"Calle de Pelayo, 13",
    "sg:city":"Gijon",
    "sg:orig_category":"Zapatos (al Por Menor)",
    "sg:phone":"+34 985 17 60 68",
    "sg:postcode":"33205",
    "sg:province":"Asturias",
    "wof:name":"Zapaterias Alcala S.l.",
    "wof:placetype":"venue"
},
  "geometry": {"coordinates":[-5.6627016068,43.5385971069],"type":"Point"}
}