{
  "type": "Feature",
  "properties": {
    "iso:country":"ES",
    "sg:address":"Plaz Espa\u00d1a, 1",
    "sg:city":"Pinos-genil",
    "sg:orig_category":"Electrodom\u00c9sticos (fabricaci\u00d3n, Al Por Mayor)",
    "sg:phone":"+34 958 48 86 50",
    "sg:postcode":"18191",
    "sg:province":"Granada",
    "wof:name":"Grupo Cea Andaluz S.l.",
    "wof:placetype":"venue"
},
  "geometry": {"coordinates":[-3.5053992271,37.1545639038],"type":"Point"}
}