{
  "type": "Feature",
  "properties": {
    "iso:country":"ES",
    "sg:address":"Calle de Ceferino Rodriguez, 8",
    "sg:city":"Madrid",
    "sg:orig_category":"Alumbrados",
    "sg:phone":"+34 917 33 68 69",
    "sg:postcode":"28029",
    "sg:province":"Madrid",
    "sg:website":"www.personal3.iddeo.es/aryanmad",
    "wof:name":"Arte Y Antiguedades S.l.",
    "wof:placetype":"venue"
},
  "geometry": {"coordinates":[-3.6970551014,40.4665374756],"type":"Point"}
}