{
  "type": "Feature",
  "properties": {
    "iso:country":"ES",
    "sg:address":"Avda Rosalia Castro, 71",
    "sg:city":"Milladoiro",
    "sg:orig_category":"Servicios Gsm",
    "sg:phone":"+34 981 55 31 30",
    "sg:postcode":"15895",
    "sg:province":"La Coru\u00f1a",
    "wof:name":"Galicia Moviles Y Sistemas S.l.",
    "wof:placetype":"venue"
},
  "geometry": {"coordinates":[-8.5523767471,42.8739089966],"type":"Point"}
}