{
  "type": "Feature",
  "properties": {
    "iso:country":"ES",
    "sg:address":"Calle de San Juan De La Palma, 5",
    "sg:city":"Sevilla",
    "sg:orig_category":"Electricidad: Instaladores",
    "sg:phone":"+34 954 22 83 60",
    "sg:postcode":"41003",
    "sg:province":"Sevilla",
    "wof:name":"Insoran Instalaciones S.l.",
    "wof:placetype":"venue"
},
  "geometry": {"coordinates":[-5.9911527634,37.3950881958],"type":"Point"}
}