{
  "type": "Feature",
  "properties": {
    "addr:full":"Calle de Real, 15 Velada Toledo 45612",
    "addr:housenumber":"15",
    "addr:postcode":"45612",
    "addr:street":"Calle De Real",
    "iso:country":"ES",
    "sg:address":"Calle de Real, 15",
    "sg:city":"Velada",
    "sg:orig_category":"Cajas De Ahorro",
    "sg:phone":"+34 925 89 20 01",
    "sg:postcode":"45612",
    "sg:province":"Toledo",
    "wof:name":"Caja De Ahorros De Castilla La Mancha",
    "wof:placetype":"venue"
},
  "geometry": {"coordinates":[-4.9775190353,39.9789505005],"type":"Point"}
}