{
  "type": "Feature",
  "properties": {
    "addr:full":"Plaz Constitucion, 1 Badajoz Badajoz 06004",
    "addr:housenumber":"1",
    "addr:postcode":"06004",
    "addr:street":"Constitucion",
    "iso:country":"ES",
    "sg:address":"Plaz Constitucion, 1",
    "sg:city":"Badajoz",
    "sg:orig_category":"Sociedades Y Organismos Burs\u00c1tiles",
    "sg:phone":"+34 924 20 05 96",
    "sg:postcode":"06004",
    "sg:province":"Badajoz",
    "sg:website":"www.r4.com",
    "wof:name":"Renta-4 Sociedad De Valores De Bolsa",
    "wof:placetype":"venue"
},
  "geometry": {"coordinates":[-6.9726238251,38.874835968],"type":"Point"}
}