{
  "type": "Feature",
  "properties": {
    "iso:country":"ES",
    "sg:address":"Calle de Santa Lucia, 1",
    "sg:city":"Santander",
    "sg:orig_category":"Abogados",
    "sg:phone":"+34 942 36 01 36",
    "sg:postcode":"39003",
    "sg:province":"Cantabria",
    "wof:name":"Sebrango Moratinos Rafael",
    "wof:placetype":"venue"
},
  "geometry": {"coordinates":[-3.8039140701,43.4638786316],"type":"Point"}
}