{
  "type": "Feature",
  "properties": {
    "iso:country":"ES",
    "sg:address":"Calle de Ceramista Godofredo Buenosaires, 6",
    "sg:city":"Castellon",
    "sg:orig_category":"Electrodom\u00c9sticos (al Por Menor)",
    "sg:phone":"+34 964 26 04 98",
    "sg:postcode":"12005",
    "sg:province":"Castell\u00f3n",
    "wof:name":"Pascual Marti S.a.",
    "wof:placetype":"venue"
},
  "geometry": {"coordinates":[-0.0365362987,39.9786071777],"type":"Point"}
}