{
  "type": "Feature",
  "properties": {
    "iso:country":"ES",
    "sg:address":"Carrer de Berruguete, 84",
    "sg:city":"Barcelona",
    "sg:orig_category":"Ingenier\u00cda, Centros De Estudios (diversos)",
    "sg:phone":"+34 934 28 61 18",
    "sg:postcode":"08035",
    "sg:province":"Barcelona",
    "wof:name":"Cetres Enginyers S.l.",
    "wof:placetype":"venue"
},
  "geometry": {"coordinates":[2.1488549709,41.4334220886],"type":"Point"}
}