{
  "type": "Feature",
  "properties": {
    "iso:country":"ES",
    "sg:address":"Calle de Derecha, 1",
    "sg:city":"Zalamea Serena",
    "sg:orig_category":"Caf\u00c9s, Bares, Cervecer\u00cdas",
    "sg:phone":"+34 924 77 55 05",
    "sg:postcode":"06430",
    "sg:province":"Badajoz",
    "wof:name":"Rodriguez Pozo Melchor",
    "wof:placetype":"venue"
},
  "geometry": {"coordinates":[-5.660050869,38.6497764587],"type":"Point"}
}