{
  "type": "Feature",
  "properties": {
    "addr:full":"Pol Ind Cornicabral, 107 Beas Segura Ja\u00e9n 23280",
    "addr:housenumber":"107",
    "addr:postcode":"23280",
    "addr:street":"Cornicabral",
    "iso:country":"ES",
    "sg:address":"Pol Ind Cornicabral, 107",
    "sg:city":"Beas Segura",
    "sg:orig_category":"Bebidas",
    "sg:phone":"+34 953 42 41 63",
    "sg:postcode":"23280",
    "sg:province":"Ja\u00e9n",
    "wof:name":"Alamacenes Mayolara S.l.",
    "wof:placetype":"venue"
},
  "geometry": {"coordinates":[-2.6515130997,38.2977561951],"type":"Point"}
}