{
  "type": "Feature",
  "properties": {
    "iso:country":"ES",
    "sg:address":"Calle de Joaquina De Vedruna, 8",
    "sg:city":"Le\u00f3n",
    "sg:orig_category":"Fabricaci\u00d3n De Juegos Y Juguetes",
    "sg:phone":"+34 987 22 86 25",
    "sg:postcode":"24002",
    "sg:province":"Le\u00f3n",
    "wof:name":"Tecnitoys Juguetes S.a.",
    "wof:placetype":"venue"
},
  "geometry": {"coordinates":[-5.5738201141,42.5993614197],"type":"Point"}
}