{
  "type": "Feature",
  "properties": {
    "iso:country":"ES",
    "sg:address":"Avda Rosalia De Castro, 121",
    "sg:city":"Vilagarcia",
    "sg:orig_category":"Inmobiliaria (agencias)",
    "sg:phone":"+34 986 50 93 08",
    "sg:postcode":"36600",
    "sg:province":"Pontevedra",
    "wof:name":"Gexpa Gestion S.l.",
    "wof:placetype":"venue"
},
  "geometry": {"coordinates":[-8.7660074234,42.6039657593],"type":"Point"}
}