{
  "type": "Feature",
  "properties": {
    "iso:country":"ES",
    "sg:address":"Carrer de Anselm Clave, 8",
    "sg:city":"Molins Rei",
    "sg:orig_category":"Inmobiliaria (agencias)",
    "sg:phone":"+34 936 80 45 41",
    "sg:postcode":"08750",
    "sg:province":"Barcelona",
    "wof:name":"Invergestion Patrimonial S.l.",
    "wof:placetype":"venue"
},
  "geometry": {"coordinates":[2.0157279968,41.4152793884],"type":"Point"}
}