{
  "type": "Feature",
  "properties": {
    "addr:full":"Calle de Marques De Pickman, 31 Sevilla Sevilla 41005",
    "addr:housenumber":"31",
    "addr:postcode":"41005",
    "addr:street":"Calle De Marques De Pickman",
    "iso:country":"ES",
    "sg:address":"Calle de Marques De Pickman, 31",
    "sg:city":"Sevilla",
    "sg:orig_category":"Confecci\u00d3n (fabricaci\u00d3n, Al Por Mayor)",
    "sg:phone":"+34 954 57 84 57",
    "sg:postcode":"41005",
    "sg:province":"Sevilla",
    "wof:name":"Pi\u00f1ar Ruiz Pedro Jose",
    "wof:placetype":"venue"
},
  "geometry": {"coordinates":[-5.9625492096,37.3813667297],"type":"Point"}
}