{
  "type": "Feature",
  "properties": {
    "iso:country":"ES",
    "sg:address":"Calle de Mar, 23",
    "sg:city":"Valencia",
    "sg:orig_category":"Metalurgia",
    "sg:phone":"+34 963 92 44 67",
    "sg:postcode":"46003",
    "sg:province":"Valencia",
    "wof:name":"White Cap Espa\u00f1a S.l.",
    "wof:placetype":"venue"
},
  "geometry": {"coordinates":[-0.373814702,39.4738922119],"type":"Point"}
}