{
  "type": "Feature",
  "properties": {
    "addr:full":"Avda Reina Victoria, 129 Santander Cantabria 39005",
    "addr:housenumber":"129",
    "addr:postcode":"39005",
    "addr:street":"Avda Reina Victoria",
    "iso:country":"ES",
    "sg:address":"Avda Reina Victoria, 129",
    "sg:city":"Santander",
    "sg:orig_category":"Abogados",
    "sg:phone":"+34 942 27 51 40",
    "sg:postcode":"39005",
    "sg:province":"Cantabria",
    "wof:name":"Dominguez Guilarte Luis",
    "wof:placetype":"venue"
},
  "geometry": {"coordinates":[-3.7785310745,43.4708366394],"type":"Point"}
}