{
  "type": "Feature",
  "properties": {
    "iso:country":"ES",
    "sg:address":"Plaz Villa (de La), 1",
    "sg:city":"Navas Del Marques",
    "sg:orig_category":"Administraciones Regionales, Departamentales Y Locales",
    "sg:phone":"+34 918 97 07 72",
    "sg:postcode":"05230",
    "sg:province":"\u00c1vila",
    "wof:name":"Ayuntamiento De Las Navas Del Marques",
    "wof:placetype":"venue"
},
  "geometry": {"coordinates":[-4.3334889412,40.6027450562],"type":"Point"}
}