{
  "type": "Feature",
  "properties": {
    "iso:country":"ES",
    "sg:address":"Toribio Etxebarria Kalea, 17",
    "sg:city":"Eibar",
    "sg:orig_category":"Muebles, Minoristas",
    "sg:phone":"+34 943 20 38 68",
    "sg:postcode":"20600",
    "sg:province":"Guip\u00f9zcoa",
    "wof:name":"Eizagaetxeberria Solozabal Rosa Maria",
    "wof:placetype":"venue"
},
  "geometry": {"coordinates":[-2.4718840122,43.1853027344],"type":"Point"}
}