{
  "type": "Feature",
  "properties": {
    "iso:country":"ES",
    "sg:address":"Calle de Pacita Vigil La Guaxa, 8",
    "sg:city":"Pola De Siero",
    "sg:orig_category":"Ropa Para Se\u00d1oras (al Por Menor)",
    "sg:phone":"+34 985 72 52 79",
    "sg:postcode":"33510",
    "sg:province":"Asturias",
    "wof:name":"Corral Fernandez Ana Maria",
    "wof:placetype":"venue"
},
  "geometry": {"coordinates":[-5.6608700752,43.3908615112],"type":"Point"}
}