{
  "type": "Feature",
  "properties": {
    "iso:country":"ES",
    "sg:address":"Calle de Rincon De San Nicolas, 2",
    "sg:city":"Plasencia",
    "sg:orig_category":"Procuradores",
    "sg:phone":"+34 927 42 39 09",
    "sg:postcode":"10600",
    "sg:province":"C\u00e1ceres",
    "wof:name":"Hornero Rodriguez Victoria",
    "wof:placetype":"venue"
},
  "geometry": {"coordinates":[-6.0929059982,40.0286865234],"type":"Point"}
}