{
  "type": "Feature",
  "properties": {
    "iso:country":"ES",
    "sg:address":"Calle de Andorra, 115",
    "sg:city":"Madrid",
    "sg:orig_category":"Papeler\u00cdas, Librer\u00cdas",
    "sg:phone":"+34 913 88 70 89",
    "sg:postcode":"28043",
    "sg:province":"Madrid",
    "wof:name":"Lopez Montealegre Emilio",
    "wof:placetype":"venue"
},
  "geometry": {"coordinates":[-3.6426932812,40.4622077942],"type":"Point"}
}