{
  "type": "Feature",
  "properties": {
    "addr:full":"Calle de Teniente General Gutierrez Mellado, S/n Fama Murcia 30008",
    "addr:housenumber":"s / n",
    "addr:postcode":"30008",
    "addr:street":"Calle De Teniente General Gutierrez Mellado",
    "iso:country":"ES",
    "sg:address":"Calle de Teniente General Gutierrez Mellado, S/n",
    "sg:city":"Fama",
    "sg:orig_category":"Librer\u00cdas",
    "sg:phone":"+34 968 43 09 39",
    "sg:postcode":"30008",
    "sg:province":"Murcia",
    "wof:name":"Sojo Galvan Manuel",
    "wof:placetype":"venue"
},
  "geometry": {"coordinates":[-1.1298867464,37.9834747314],"type":"Point"}
}