{
  "type": "Feature",
  "properties": {
    "iso:country":"ES",
    "sg:address":"Calle de Menacho, 14",
    "sg:city":"Badajoz",
    "sg:orig_category":"Centros Comerciales Y Grandes Tiendas",
    "sg:phone":"+34 924 22 19 15",
    "sg:postcode":"06001",
    "sg:province":"Badajoz",
    "wof:name":"Joyeria Gomvetia S.l.",
    "wof:placetype":"venue"
},
  "geometry": {"coordinates":[-6.9738588333,38.8774757385],"type":"Point"}
}