{
  "type": "Feature",
  "properties": {
    "iso:country":"ES",
    "sg:address":"Calle de Julian Ceballos, 14",
    "sg:city":"Torrelavega",
    "sg:orig_category":"M\u00c9dicos: An\u00c1lisis Cl\u00cdnicos",
    "sg:phone":"+34 942 80 62 35",
    "sg:postcode":"39300",
    "sg:province":"Cantabria",
    "wof:name":"Laboratorio Dr Mazo S.a.",
    "wof:placetype":"venue"
},
  "geometry": {"coordinates":[-4.0499691963,43.3486061096],"type":"Point"}
}