{
  "type": "Feature",
  "properties": {
    "iso:country":"ES",
    "sg:address":"Flassaders, 5",
    "sg:city":"Pol. Ind. Santiga",
    "sg:orig_category":"Ferreter\u00cda (diversos)",
    "sg:phone":"+34 937 19 00 62",
    "sg:postcode":"08130",
    "sg:province":"Barcelona",
    "wof:name":"Juan Ca\u00f1izares S.l.",
    "wof:placetype":"venue"
},
  "geometry": {"coordinates":[2.1802799702,41.5371818542],"type":"Point"}
}