{
  "type": "Feature",
  "properties": {
    "iso:country":"ES",
    "sg:address":"Calle de Vicente Mu\u00d1oz Calero, 2",
    "sg:city":"Pe\u00f1afiel",
    "sg:orig_category":"Materiales De Construcci\u00d3n (en General)",
    "sg:phone":"+34 983 88 04 46",
    "sg:postcode":"47300",
    "sg:province":"Valladolid",
    "wof:name":"Piedras De Castilla",
    "wof:placetype":"venue"
},
  "geometry": {"coordinates":[-4.114923954,41.6004753113],"type":"Point"}
}