{
  "type": "Feature",
  "properties": {
    "addr:full":"Ctra Barcelona, 22 Viladecans Barcelona 08840",
    "addr:housenumber":"22",
    "addr:postcode":"08840",
    "addr:street":"Ctra Barcelona",
    "iso:country":"ES",
    "sg:address":"Ctra Barcelona, 22",
    "sg:city":"Viladecans",
    "sg:orig_category":"Alumbrados",
    "sg:phone":"+34 936 58 93 50",
    "sg:postcode":"08840",
    "sg:province":"Barcelona",
    "wof:name":"Diego Medina Jose De",
    "wof:placetype":"venue"
},
  "geometry": {"coordinates":[2.0234019756,41.3180503845],"type":"Point"}
}