{
  "type": "Feature",
  "properties": {
    "iso:country":"ES",
    "sg:address":"Calle de Renocal, 44",
    "sg:city":"Arnedo",
    "sg:orig_category":"Agencias Y Agentes Comerciales, Representantes",
    "sg:phone":"+34 941 38 44 49",
    "sg:postcode":"26580",
    "sg:province":"La Rioja",
    "wof:name":"Gil De Gomez Hernandez Miguel Angel",
    "wof:placetype":"venue"
},
  "geometry": {"coordinates":[-2.0889809132,42.2264404297],"type":"Point"}
}