{
  "type": "Feature",
  "properties": {
    "iso:country":"ES",
    "sg:address":"Calle de Gabriel Ramos Bejarano, S/n",
    "sg:city":"Cordoba",
    "sg:orig_category":"Puros, Cigarrillos Y Tabaco (fabricaci\u00d3n, Al Por Mayor)",
    "sg:phone":"+34 957 20 22 66",
    "sg:postcode":"14014",
    "sg:province":"C\u00f3rdoba",
    "wof:name":"Egea Vega Alfonso",
    "wof:placetype":"venue"
},
  "geometry": {"coordinates":[-4.7196440697,37.9004745483],"type":"Point"}
}