{
  "type": "Feature",
  "properties": {
    "addr:full":"Avda Portugal, 32 Salamanca Salamanca 37004",
    "addr:housenumber":"32",
    "addr:postcode":"37004",
    "addr:street":"Avda Portugal",
    "iso:country":"ES",
    "sg:address":"Avda Portugal, 32",
    "sg:city":"Salamanca",
    "sg:orig_category":"Fabricaci\u00d3n De Mobiliario De Oficina",
    "sg:phone":"+34 923 22 62 21",
    "sg:postcode":"37004",
    "sg:province":"Salamanca",
    "wof:name":"Doval Salgado Laureano",
    "wof:placetype":"venue"
},
  "geometry": {"coordinates":[-5.6555070877,40.9708442688],"type":"Point"}
}