{
  "type": "Feature",
  "properties": {
    "addr:full":"Calle de Ramon Gomez De La Serna, 66 Madrid Madrid 28035",
    "addr:housenumber":"66",
    "addr:postcode":"madrid;28035",
    "addr:street":"Calle De Ramon Gomez De La Serna",
    "iso:country":"ES",
    "sg:address":"Calle de Ramon Gomez De La Serna, 66",
    "sg:city":"Madrid",
    "sg:orig_category":"Publicidad (soportes Y Gesti\u00d3n)",
    "sg:phone":"+34 913 73 12 52",
    "sg:postcode":"28035",
    "sg:province":"Madrid",
    "wof:name":"Aryal Regalos S.l.",
    "wof:placetype":"venue"
},
  "geometry": {"coordinates":[-3.7242450714,40.4808349609],"type":"Point"}
}