{
  "type": "Feature",
  "properties": {
    "addr:full":"Calle de Acera Del Darro, 12 Granada Granada 18005",
    "addr:housenumber":"12",
    "addr:postcode":"18005",
    "addr:street":"Calle De Acera Del Darro",
    "iso:country":"ES",
    "sg:address":"Calle de Acera Del Darro, 12",
    "sg:city":"Granada",
    "sg:orig_category":"Zapatos (al Por Menor)",
    "sg:phone":"+34 958 52 00 43",
    "sg:postcode":"18005",
    "sg:province":"Granada",
    "wof:name":"Villanueva Y Rios S.l.",
    "wof:placetype":"venue"
},
  "geometry": {"coordinates":[-3.5995140076,37.1728248596],"type":"Point"}
}