{
  "type": "Feature",
  "properties": {
    "iso:country":"ES",
    "sg:address":"Carr Sta Caterina, 21",
    "sg:city":"Igualada",
    "sg:orig_category":"Clases De M\u00dasica Y Canto",
    "sg:phone":"+34 938 04 89 32",
    "sg:postcode":"08700",
    "sg:province":"Barcelona",
    "sg:website":"www.musicalanoia/akords/",
    "wof:name":"Produccions Musicals Akord's S.l.",
    "wof:placetype":"venue"
},
  "geometry": {"coordinates":[1.6150079966,41.5807876587],"type":"Point"}
}