{
  "type": "Feature",
  "properties": {
    "addr:full":"Avda Luis Braille, 2 San Pedro Alcantara M\u00e1laga 29670",
    "addr:housenumber":"2",
    "addr:postcode":"29670",
    "addr:street":"Avda Luis Braille",
    "iso:country":"ES",
    "sg:address":"Avda Luis Braille, 2",
    "sg:city":"San Pedro Alcantara",
    "sg:orig_category":"Veh\u00cdculos De Ocasi\u00d3n",
    "sg:phone":"+34 952 78 88 60",
    "sg:postcode":"29670",
    "sg:province":"M\u00e1laga",
    "wof:name":"Veldmart Automoviles S.l.",
    "wof:placetype":"venue"
},
  "geometry": {"coordinates":[-4.9889588356,36.4821815491],"type":"Point"}
}