{
  "type": "Feature",
  "properties": {
    "addr:full":"Rua Rio Eo, 84 Lugo Lugo 27003",
    "addr:housenumber":"84",
    "addr:postcode":"27003",
    "addr:street":"Rua;Eo",
    "iso:country":"ES",
    "sg:address":"Rua Rio Eo, 84",
    "sg:city":"Lugo",
    "sg:orig_category":"Molduras, Junquillos, Listones Y Molduras Perforadas",
    "sg:phone":"+34 982 22 69 03",
    "sg:postcode":"27003",
    "sg:province":"Lugo",
    "wof:name":"Losada Lopez Maria Purificacion",
    "wof:placetype":"venue"
},
  "geometry": {"coordinates":[-7.559484005,43.0184211731],"type":"Point"}
}