{
  "type": "Feature",
  "properties": {
    "addr:full":"Barr Rubin, 9 Gijon Asturias 33213",
    "addr:postcode":"33213",
    "iso:country":"ES",
    "sg:address":"Barr Rubin, 9",
    "sg:city":"Gijon",
    "sg:orig_category":"Promotores Constructores",
    "sg:phone":"+34 985 32 46 08",
    "sg:postcode":"33213",
    "sg:province":"Asturias",
    "wof:name":"Construcciones Sietenco S.l.",
    "wof:placetype":"venue"
},
  "geometry": {"coordinates":[-5.706469059,43.5418624878],"type":"Point"}
}