{
  "type": "Feature",
  "properties": {
    "iso:country":"ES",
    "sg:address":"Luga Lomas (las), 97",
    "sg:city":"Lomas De Abajo",
    "sg:orig_category":"Transportes Por Carretera: Lotes Completos, Mercanc\u00cdas Diversas",
    "sg:phone":"+34 968 48 40 09",
    "sg:postcode":"30858",
    "sg:province":"Murcia",
    "wof:name":"Comestibles Fuentes S.l.",
    "wof:placetype":"venue"
},
  "geometry": {"coordinates":[-1.4096640348,37.7164802551],"type":"Point"}
}