{
  "type": "Feature",
  "properties": {
    "addr:full":"Mercado De Abastos, S/n Zamora Zamora 49001",
    "addr:housenumber":"s / n",
    "addr:postcode":"49001",
    "iso:country":"ES",
    "sg:address":"Mercado De Abastos, S/n",
    "sg:city":"Zamora",
    "sg:orig_category":"Carnicer\u00cdas, Carnicer\u00cdas",
    "sg:phone":"+34 980 53 20 33",
    "sg:postcode":"49001",
    "sg:province":"Zamora",
    "wof:name":"Huertos Moralejo Jose Luis",
    "wof:placetype":"venue"
},
  "geometry": {"coordinates":[-5.7457342148,41.5033302307],"type":"Point"}
}