{
  "type": "Feature",
  "properties": {
    "iso:country":"ES",
    "sg:address":"Pla\u00c7 Pompeu Fabra, 12",
    "sg:city":"Girona",
    "sg:orig_category":"Inmobiliaria (agencias)",
    "sg:phone":"+34 872 08 11 62",
    "sg:postcode":"17002",
    "sg:province":"Girona",
    "wof:name":"Giroinver S.l.",
    "wof:placetype":"venue"
},
  "geometry": {"coordinates":[2.8190748692,41.9780960083],"type":"Point"}
}