{
  "type": "Feature",
  "properties": {
    "iso:country":"ES",
    "sg:address":"Calle de Rozabella, 2",
    "sg:city":"Matas-pinar-monte Rozas",
    "sg:orig_category":"Control T\u00c9cnico De Veh\u00cdculos",
    "sg:phone":"+34 916 40 44 29",
    "sg:postcode":"28290",
    "sg:province":"Madrid",
    "sg:website":"www.itevelesa.com",
    "wof:name":"Grupo Itevelesa S.a.",
    "wof:placetype":"venue"
},
  "geometry": {"coordinates":[-3.8935050964,40.540561676],"type":"Point"}
}