{
  "type": "Feature",
  "properties": {
    "addr:full":"Calle de General Lasheras, 9 Huesca Huesca 22003",
    "addr:housenumber":"9",
    "addr:postcode":"22003",
    "addr:street":"Calle De General Lasheras",
    "iso:country":"ES",
    "sg:address":"Calle de General Lasheras, 9",
    "sg:city":"Huesca",
    "sg:orig_category":"Quincaller\u00cda (al Por Menor)",
    "sg:phone":"+34 974 24 03 84",
    "sg:postcode":"22003",
    "sg:province":"Huesca",
    "wof:name":"Santolaria Castrillo Alejandro",
    "wof:placetype":"venue"
},
  "geometry": {"coordinates":[-0.4144699872,42.138584137],"type":"Point"}
}