{
  "type": "Feature",
  "properties": {
    "iso:country":"ES",
    "sg:address":"Carrer de Foc, 28",
    "sg:city":"Barcelona",
    "sg:orig_category":"Empresas De Portes Y Mensajer\u00cda",
    "sg:phone":"+34 933 38 28 95",
    "sg:postcode":"08038",
    "sg:province":"Barcelona",
    "wof:name":"Galilea Transworld S.l.",
    "wof:placetype":"venue"
},
  "geometry": {"coordinates":[2.1364049911,41.3539505005],"type":"Point"}
}