{
  "type": "Feature",
  "properties": {
    "addr:full":"Carr Pla\u00c7a, 11 Felanitx Islas Baleares 07200",
    "addr:housenumber":"11",
    "addr:postcode":"07200",
    "addr:street":"Carr Plac\u0327A",
    "iso:country":"ES",
    "sg:address":"Carr Pla\u00c7a, 11",
    "sg:city":"Felanitx",
    "sg:orig_category":"Papeler\u00cdas, Librer\u00cdas",
    "sg:phone":"+34 971 58 01 20",
    "sg:postcode":"07200",
    "sg:province":"Islas Baleares",
    "wof:name":"Obrador Taberner Catalina",
    "wof:placetype":"venue"
},
  "geometry": {"coordinates":[3.148722887,39.4699783325],"type":"Point"}
}