{
  "type": "Feature",
  "properties": {
    "addr:full":"Ctra Icod Santa Cruz, 39 Vera Santa Cruz De Tenerife 38400",
    "addr:housenumber":"39",
    "addr:postcode":"38400",
    "addr:street":"Ctra Icod;Cruz",
    "iso:country":"ES",
    "sg:address":"Ctra Icod Santa Cruz, 39",
    "sg:city":"Vera",
    "sg:orig_category":"Muebles, Minoristas",
    "sg:phone":"+34 922 38 51 58",
    "sg:postcode":"38400",
    "sg:province":"Santa Cruz De Tenerife",
    "wof:name":"Artemadera Insular S.l.",
    "wof:placetype":"venue"
},
  "geometry": {"coordinates":[-16.5623435974,28.3969097137],"type":"Point"}
}