{
  "type": "Feature",
  "properties": {
    "addr:full":"Carrer de Granollers, 76 Cardedeu Barcelona 08440",
    "addr:housenumber":"76",
    "addr:postcode":"08440",
    "addr:street":"Carrer De Granollers",
    "iso:country":"ES",
    "sg:address":"Carrer de Granollers, 76",
    "sg:city":"Cardedeu",
    "sg:orig_category":"Empresas De Carpinter\u00cda Met\u00c1lica",
    "sg:phone":"+34 938 71 22 20",
    "sg:postcode":"08440",
    "sg:province":"Barcelona",
    "wof:name":"Garcia Coderch Pere",
    "wof:placetype":"venue"
},
  "geometry": {"coordinates":[2.363795042,41.6416168213],"type":"Point"}
}