{
  "type": "Feature",
  "properties": {
    "iso:country":"ES",
    "sg:address":"Cami Ca N'ubach, 25",
    "sg:city":"Sant Vicen\u00c7 Dels Horts",
    "sg:classifiers":[
        {
            "category":"Manufacturing",
            "subcategory":"Metals",
            "type":"Manufacturing & Wholesale Goods"
        }
    ],
    "sg:phone":"+34 936 56 01 04",
    "sg:postcode":"08620",
    "sg:province":"Barcelona",
    "sg:tags":[
        "en",
        "fundiciones"
    ],
    "sg:website":"www.info.es",
    "wof:name":"Infun S.a.",
    "wof:placetype":"venue"
},
  "geometry": {"coordinates":[1.9939601421,41.4034690857],"type":"Point"}
}