{
  "type": "Feature",
  "properties": {
    "iso:country":"ES",
    "sg:address":"Kale Nagusia, 9",
    "sg:city":"Hernani",
    "sg:orig_category":"Fabricaci\u00d3n De Sobres, Bolsas Y Fundas",
    "sg:phone":"+34 943 55 30 91",
    "sg:postcode":"20120",
    "sg:province":"Guip\u00f9zcoa",
    "wof:name":"Manchado Hueso Juliana",
    "wof:placetype":"venue"
},
  "geometry": {"coordinates":[-1.9489586353,43.2805671692],"type":"Point"}
}