{
  "type": "Feature",
  "properties": {
    "addr:full":"Calle de Baron De San Petrillo, 17 Valencia Valencia 46020",
    "addr:housenumber":"17",
    "addr:postcode":"46020",
    "addr:street":"Calle De Baron De San Petrillo",
    "iso:country":"ES",
    "sg:address":"Calle de Baron De San Petrillo, 17",
    "sg:city":"Valencia",
    "sg:orig_category":"Bancos",
    "sg:phone":"+34 963 60 18 66",
    "sg:postcode":"46020",
    "sg:province":"Valencia",
    "wof:name":"Banco De Valencia S.a.",
    "wof:placetype":"venue"
},
  "geometry": {"coordinates":[-0.3604579866,39.485408783],"type":"Point"}
}