{
  "type": "Feature",
  "properties": {
    "iso:country":"ES",
    "sg:address":"Carrer de Londres, 22",
    "sg:city":"Barcelona",
    "sg:orig_category":"Cer\u00c1micas: Material Y Suministros",
    "sg:phone":"+34 934 30 05 25",
    "sg:postcode":"08029",
    "sg:province":"Barcelona",
    "wof:name":"Comalex S.l.",
    "wof:placetype":"venue"
},
  "geometry": {"coordinates":[2.1446828842,41.3887062073],"type":"Point"}
}