{
  "type": "Feature",
  "properties": {
    "addr:full":"Avda Profesor Perez Pimentel, 1141 Gijon Asturias 33203",
    "addr:housenumber":"1141",
    "addr:postcode":"33203",
    "addr:street":"Avda Profesor Perez Pimentel",
    "iso:country":"ES",
    "sg:address":"Avda Profesor Perez Pimentel, 1141",
    "sg:city":"Gijon",
    "sg:orig_category":"Asociaciones, Organismos Culturales Y Socioeducativos",
    "sg:phone":"+34 985 36 43 50",
    "sg:postcode":"33203",
    "sg:province":"Asturias",
    "wof:name":"Sociedad Recreativa El Llar",
    "wof:placetype":"venue"
},
  "geometry": {"coordinates":[-5.6310391426,43.5330696106],"type":"Point"}
}