{
  "type": "Feature",
  "properties": {
    "addr:full":"Avda General Peron, 8 Madrid Madrid 28020",
    "addr:housenumber":"8",
    "addr:postcode":"madrid;28020",
    "addr:street":"Avda General Peron",
    "iso:country":"ES",
    "sg:address":"Avda General Peron, 8",
    "sg:city":"Madrid",
    "sg:orig_category":"Agencias De Viajes",
    "sg:phone":"+34 914 49 21 30",
    "sg:postcode":"28020",
    "sg:province":"Madrid",
    "sg:website":"www.viajesiberia.com",
    "wof:name":"Viajes Iberia S.a.",
    "wof:placetype":"venue"
},
  "geometry": {"coordinates":[-3.698292017,40.452419281],"type":"Point"}
}