{
  "type": "Feature",
  "properties": {
    "addr:full":"Av Mare Deu De Montserrat, 1 Barcelona Barcelona 08024",
    "addr:housenumber":"1",
    "addr:postcode":"08024",
    "addr:street":"Av Mare;De Montserrat",
    "iso:country":"ES",
    "sg:address":"Av Mare Deu De Montserrat, 1",
    "sg:city":"Barcelona",
    "sg:orig_category":"Cl\u00cdnicas M\u00c9dicas",
    "sg:phone":"+34 932 19 73 43",
    "sg:postcode":"08024",
    "sg:province":"Barcelona",
    "wof:name":"Vilardell Vi\u00f1as Francisco",
    "wof:placetype":"venue"
},
  "geometry": {"coordinates":[2.1596369743,41.4126853943],"type":"Point"}
}