{
  "type": "Feature",
  "properties": {
    "iso:country":"ES",
    "sg:address":"Avda Palencia, 9",
    "sg:city":"Burgos",
    "sg:orig_category":"Distribuci\u00d3n De Petr\u00d3leo Y Derivados",
    "sg:phone":"+34 947 20 81 41",
    "sg:postcode":"09001",
    "sg:province":"Burgos",
    "wof:name":"Villarce S.l.",
    "wof:placetype":"venue"
},
  "geometry": {"coordinates":[-3.7118990421,42.3378295898],"type":"Point"}
}