{
  "type": "Feature",
  "properties": {
    "addr:full":"Calle de Real De Motril, 5 Armilla Granada 18100",
    "addr:housenumber":"5",
    "addr:postcode":"18100",
    "addr:street":"Calle De Real De Motril",
    "iso:country":"ES",
    "sg:address":"Calle de Real De Motril, 5",
    "sg:city":"Armilla",
    "sg:orig_category":"Formaci\u00d3n A Distancia, Por Correspondencia",
    "sg:phone":"+34 958 57 32 96",
    "sg:postcode":"18100",
    "sg:province":"Granada",
    "wof:name":"Rosa Maria Ruiz Obispo-teresa Franco Castro Cdad",
    "wof:placetype":"venue"
},
  "geometry": {"coordinates":[-3.6254150867,37.1435394287],"type":"Point"}
}