{
  "type": "Feature",
  "properties": {
    "iso:country":"ES",
    "sg:address":"Cno. Matasdeporras, S/n",
    "sg:city":"Guadiana Caudillo",
    "sg:orig_category":"Alimentaci\u00d3n General (al Por Mayor)",
    "sg:phone":"+34 924 47 12 23",
    "sg:postcode":"06186",
    "sg:province":"Badajoz",
    "wof:name":"Agroguadiana S.l.",
    "wof:placetype":"venue"
},
  "geometry": {"coordinates":[-6.9702835083,38.8785972595],"type":"Point"}
}