{
  "type": "Feature",
  "properties": {
    "addr:full":"Av Miramar, 68 Pujols Islas Baleares 07871",
    "addr:housenumber":"68",
    "addr:postcode":"07871",
    "addr:street":"Av Miramar",
    "iso:country":"ES",
    "sg:address":"Av Miramar, 68",
    "sg:city":"Pujols",
    "sg:orig_category":"Librer\u00cdas",
    "sg:phone":"+34 971 32 80 15",
    "sg:postcode":"07871",
    "sg:province":"Islas Baleares",
    "wof:name":"Distribuidora Ibicenca De Ediciones S.a.",
    "wof:placetype":"venue"
},
  "geometry": {"coordinates":[1.4571059942,38.7227897644],"type":"Point"}
}