{
  "type": "Feature",
  "properties": {
    "addr:full":"Rosario, 17 Taco Santa Cruz De Tenerife 38108",
    "addr:housenumber":"17",
    "addr:postcode":"38108",
    "addr:street":"Rosario",
    "iso:country":"ES",
    "sg:address":"Rosario, 17",
    "sg:city":"Taco",
    "sg:orig_category":"Electrodom\u00c9sticos (al Por Menor)",
    "sg:phone":"+34 922 61 54 53",
    "sg:postcode":"38108",
    "sg:province":"Santa Cruz De Tenerife",
    "wof:name":"Organizacion Martinez S. A.",
    "wof:placetype":"venue"
},
  "geometry": {"coordinates":[-16.2957706451,28.4491081238],"type":"Point"}
}