{
  "type": "Feature",
  "properties": {
    "addr:full":"Carrer de Jaume Balmes, 48 Palma Islas Baleares 07004",
    "addr:housenumber":"48",
    "addr:postcode":"07004",
    "addr:street":"Carrer De Jaume Balmes",
    "iso:country":"ES",
    "sg:address":"Carrer de Jaume Balmes, 48",
    "sg:city":"Palma",
    "sg:orig_category":"Electricidad: Instaladores",
    "sg:phone":"+34 971 75 90 75",
    "sg:postcode":"07004",
    "sg:province":"Islas Baleares",
    "wof:name":"Nyegos Installacions S.l.",
    "wof:placetype":"venue"
},
  "geometry": {"coordinates":[2.6586399078,39.5802345276],"type":"Point"}
}