{
  "type": "Feature",
  "properties": {
    "iso:country":"ES",
    "sg:address":"Alameda Tra-lo Rio, 8",
    "sg:city":"Arcade",
    "sg:orig_category":"Promotores Constructores",
    "sg:phone":"+34 986 70 10 44",
    "sg:postcode":"36690",
    "sg:province":"Pontevedra",
    "wof:name":"Construcciones Hermanos Veiga Reboreda S.l.",
    "wof:placetype":"venue"
},
  "geometry": {"coordinates":[-8.6055440903,42.3392410278],"type":"Point"}
}