{
  "type": "Feature",
  "properties": {
    "iso:country":"ES",
    "sg:address":"Calle de Lersundi, 3",
    "sg:city":"Bilbao",
    "sg:orig_category":"Inmobiliaria (agencias)",
    "sg:phone":"+34 944 23 32 73",
    "sg:postcode":"48009",
    "sg:province":"Vizcaya",
    "wof:name":"Fosidek S.l.",
    "wof:placetype":"venue"
},
  "geometry": {"coordinates":[-2.931235075,43.266368866],"type":"Point"}
}