{
  "type": "Feature",
  "properties": {
    "addr:full":"Calle de Mairena, 42 Alcala Guadaira Sevilla 41500",
    "addr:housenumber":"42",
    "addr:postcode":"41500",
    "addr:street":"Calle De Mairena",
    "iso:country":"ES",
    "sg:address":"Calle de Mairena, 42",
    "sg:city":"Alcala Guadaira",
    "sg:orig_category":"Ingenier\u00cda, Centros De Estudios (diversos)",
    "sg:phone":"+34 955 68 72 53",
    "sg:postcode":"41500",
    "sg:province":"Sevilla",
    "wof:name":"Geinco Obras Civiles S.l.",
    "wof:placetype":"venue"
},
  "geometry": {"coordinates":[-5.8412470818,37.3383750916],"type":"Point"}
}