{
  "type": "Feature",
  "properties": {
    "addr:full":"Avda Jose Garcia Santos, 56 Villares Reina Salamanca 37184",
    "addr:housenumber":"56",
    "addr:postcode":"37184",
    "addr:street":"Avda Jose Garcia Santos",
    "iso:country":"ES",
    "sg:address":"Avda Jose Garcia Santos, 56",
    "sg:city":"Villares Reina",
    "sg:orig_category":"Asociaciones Y Clubs Deportivos",
    "sg:phone":"+34 923 28 74 54",
    "sg:postcode":"37184",
    "sg:province":"Salamanca",
    "wof:name":"Fitness Darco S.l.",
    "wof:placetype":"venue"
},
  "geometry": {"coordinates":[-5.6470689774,41.0068397522],"type":"Point"}
}