{
  "type": "Feature",
  "properties": {
    "iso:country":"ES",
    "sg:address":"Calle de Doktor Jose Garai, 1",
    "sg:city":"Arizgoiti",
    "sg:orig_category":"Artes Gr\u00c1ficas, Artes Pl\u00c1sticas (curso)",
    "sg:phone":"+34 944 49 01 93",
    "sg:postcode":"48970",
    "sg:province":"Vizcaya",
    "wof:name":"Tipografia Basauri S. L.",
    "wof:placetype":"venue"
},
  "geometry": {"coordinates":[-2.886122942,43.2359809875],"type":"Point"}
}