{
  "type": "Feature",
  "properties": {
    "addr:full":"Carr Joan Maragall, 11 Alcarras Lleida 25180",
    "addr:housenumber":"11",
    "addr:postcode":"25180",
    "addr:street":"Carr Joan Maragall",
    "iso:country":"ES",
    "sg:address":"Carr Joan Maragall, 11",
    "sg:city":"Alcarras",
    "sg:orig_category":"Cajas De Ahorro",
    "sg:phone":"+34 973 79 18 05",
    "sg:postcode":"25180",
    "sg:province":"Lleida",
    "wof:name":"Caixa D'estalvis Del Penedes",
    "wof:placetype":"venue"
},
  "geometry": {"coordinates":[0.5264639854,41.5644264221],"type":"Point"}
}