{
  "type": "Feature",
  "properties": {
    "addr:full":"Calle de Donantes De Sangre, 15 Ubeda Ja\u00e9n 23400",
    "addr:housenumber":"15",
    "addr:postcode":"23400",
    "addr:street":"Calle De Donantes De Sangre;Jae\u0301N",
    "iso:country":"ES",
    "sg:address":"Calle de Donantes De Sangre, 15",
    "sg:city":"Ubeda",
    "sg:orig_category":"Abogados",
    "sg:phone":"+34 953 79 33 60",
    "sg:postcode":"23400",
    "sg:province":"Ja\u00e9n",
    "sg:website":"www.tecnosegura.com/laserranadigital",
    "wof:name":"Martinez Lopez Ignacio",
    "wof:placetype":"venue"
},
  "geometry": {"coordinates":[-3.3834235668,38.0164756775],"type":"Point"}
}