{
  "type": "Feature",
  "properties": {
    "iso:country":"ES",
    "sg:address":"Avda Vivar Tellez, 95",
    "sg:city":"Velez-malaga",
    "sg:orig_category":"Parafarmacias",
    "sg:phone":"+34 952 50 59 58",
    "sg:postcode":"29700",
    "sg:province":"M\u00e1laga",
    "wof:name":"Sarmiento Lopez Maria Sonia",
    "wof:placetype":"venue"
},
  "geometry": {"coordinates":[-4.0994539261,36.77110672],"type":"Point"}
}