{
  "type": "Feature",
  "properties": {
    "iso:country":"ES",
    "sg:address":"Plaz Constitucion De La, S/n",
    "sg:city":"Pola De Siero",
    "sg:orig_category":"Administraciones De Trabajo Y Empleo",
    "sg:phone":"+34 985 72 65 40",
    "sg:postcode":"33510",
    "sg:province":"Asturias",
    "wof:name":"Servicio Publico De Empleo Estatal-dron. Prov. Asturias",
    "wof:placetype":"venue"
},
  "geometry": {"coordinates":[-5.6607718468,43.3928604126],"type":"Point"}
}