{
  "type": "Feature",
  "properties": {
    "addr:full":"G.v. Corts Catalanes, 431 Barcelona Barcelona 08015",
    "addr:housenumber":"431",
    "addr:postcode":"08015",
    "addr:street":"Catalanes",
    "iso:country":"ES",
    "sg:address":"G.v. Corts Catalanes, 431",
    "sg:city":"Barcelona",
    "sg:orig_category":"Fabricaci\u00d3n, Importaci\u00d3n, Venta De Material De Telefon\u00cda, Peritelefon\u00cda",
    "sg:phone":"+34 932 89 05 00",
    "sg:postcode":"08015",
    "sg:province":"Barcelona",
    "wof:name":"Fermar Comunicacions S.l.",
    "wof:placetype":"venue"
},
  "geometry": {"coordinates":[2.1528580189,41.3782806396],"type":"Point"}
}