{
  "type": "Feature",
  "properties": {
    "addr:full":"Calle de San Antonio, 31 Marbella M\u00e1laga 29600",
    "addr:housenumber":"31",
    "addr:postcode":"29600",
    "addr:street":"Calle De San Antonio;Ma\u0301Laga",
    "iso:country":"ES",
    "sg:address":"Calle de San Antonio, 31",
    "sg:city":"Marbella",
    "sg:orig_category":"Confecci\u00d3n (fabricaci\u00d3n, Al Por Mayor)",
    "sg:phone":"+34 952 76 49 92",
    "sg:postcode":"29600",
    "sg:province":"M\u00e1laga",
    "sg:website":"www.lapazaerobic.com",
    "wof:name":"Ruiz Santiago Mercedes",
    "wof:placetype":"venue"
},
  "geometry": {"coordinates":[-4.8820009232,36.5139045715],"type":"Point"}
}