{
  "type": "Feature",
  "properties": {
    "iso:country":"ES",
    "sg:address":"Avda Jose Mesa Y Lopez, 58",
    "sg:city":"Palmas De Gran Canaria",
    "sg:orig_category":"Supermercados Y Hipermercados",
    "sg:phone":"+34 928 47 29 32",
    "sg:postcode":"35010",
    "sg:province":"Las Palmas",
    "wof:name":"Lomena Canarias S.l.",
    "wof:placetype":"venue"
},
  "geometry": {"coordinates":[-15.4360599518,28.133430481],"type":"Point"}
}