{
  "type": "Feature",
  "properties": {
    "iso:country":"ES",
    "sg:address":"Tabardo, 4",
    "sg:city":"Beniparrell",
    "sg:orig_category":"Suministros Para Exposiciones, Ferias, Salones",
    "sg:phone":"+34 961 21 19 57",
    "sg:postcode":"46469",
    "sg:province":"Valencia",
    "wof:name":"Angel Carrasco Saiz S.l.",
    "wof:placetype":"venue"
},
  "geometry": {"coordinates":[-0.4127092063,39.3871536255],"type":"Point"}
}