{
  "type": "Feature",
  "properties": {
    "addr:full":"Carr Llevant, 42 Puerto De Pollen\u00c7a Islas Baleares 07470",
    "addr:housenumber":"42",
    "addr:postcode":"07470",
    "addr:street":"Carr Llevant",
    "iso:country":"ES",
    "sg:address":"Carr Llevant, 42",
    "sg:city":"Puerto De Pollen\u00c7a",
    "sg:orig_category":"Caf\u00c9s, Bares, Cervecer\u00cdas",
    "sg:phone":"+34 971 86 66 33",
    "sg:postcode":"07470",
    "sg:province":"Islas Baleares",
    "wof:name":"Bauza Vila Bernardo",
    "wof:placetype":"venue"
},
  "geometry": {"coordinates":[3.0821900368,39.9063034058],"type":"Point"}
}