{
  "type": "Feature",
  "properties": {
    "addr:full":"Carrer de Oms, 7 Palma Islas Baleares 07003",
    "addr:housenumber":"7",
    "addr:postcode":"07003",
    "addr:street":"Carrer De Oms",
    "iso:country":"ES",
    "sg:address":"Carrer de Oms, 7",
    "sg:city":"Palma",
    "sg:orig_category":"Complementos De Vestir (al Por Menor)",
    "sg:phone":"+34 971 72 83 58",
    "sg:postcode":"07003",
    "sg:province":"Islas Baleares",
    "wof:name":"Corbi Silvestre Maria Dolores",
    "wof:placetype":"venue"
},
  "geometry": {"coordinates":[2.6517329216,39.5750808716],"type":"Point"}
}