{
  "type": "Feature",
  "properties": {
    "addr:full":"Carr Pau Claris, 9 Linyola Lleida 25240",
    "addr:housenumber":"9",
    "addr:postcode":"25240",
    "addr:street":"Carr Pau Claris",
    "iso:country":"ES",
    "sg:address":"Carr Pau Claris, 9",
    "sg:city":"Linyola",
    "sg:orig_category":"Forjas Y Altos Hornos",
    "sg:phone":"+34 973 57 51 11",
    "sg:postcode":"25240",
    "sg:province":"Lleida",
    "wof:name":"Agusti Barque Jose",
    "wof:placetype":"venue"
},
  "geometry": {"coordinates":[0.9065272808,41.7101669312],"type":"Point"}
}