{
  "type": "Feature",
  "properties": {
    "iso:country":"ES",
    "sg:address":"Crta. Murcia, S/n",
    "sg:city":"Hellin",
    "sg:orig_category":"Hoteles",
    "sg:phone":"+34 967 30 01 42",
    "sg:postcode":"02400",
    "sg:province":"Albacete",
    "wof:name":"Fernandez Lopez Carlos Javier",
    "wof:placetype":"venue"
},
  "geometry": {"coordinates":[-1.6889439821,38.5373268127],"type":"Point"}
}