{
  "type": "Feature",
  "properties": {
    "iso:country":"ES",
    "sg:address":"Av Mar, 26",
    "sg:city":"El Campello",
    "sg:orig_category":"Mercer\u00cda, Lencer\u00cda (al Por Menor)",
    "sg:phone":"+34 965 63 43 82",
    "sg:postcode":"03560",
    "sg:province":"Alicante",
    "wof:name":"Esteban Fuentes Francisca",
    "wof:placetype":"venue"
},
  "geometry": {"coordinates":[-0.3791939914,38.4384422302],"type":"Point"}
}