{
  "type": "Feature",
  "properties": {
    "iso:country":"ES",
    "sg:address":"Calle de Jose Mara\u00d1on, 13",
    "sg:city":"Madrid",
    "sg:orig_category":"Ense\u00d1anza: Idiomas",
    "sg:phone":"+34 915 94 44 99",
    "sg:postcode":"28010",
    "sg:province":"Madrid",
    "wof:name":"Nash  John Vernon",
    "wof:placetype":"venue"
},
  "geometry": {"coordinates":[-3.6971640587,40.4292831421],"type":"Point"}
}