{
  "type": "Feature",
  "properties": {
    "iso:country":"ES",
    "sg:address":"Calle de Leguizamon Tristan De, 5",
    "sg:city":"Bilbao",
    "sg:orig_category":"Fabricaci\u00d3n, Distribuci\u00d3n De Material Para La Climatizaci\u00d3n, Aireaci\u00d3n Y Ventilaci\u00d3n",
    "sg:phone":"+34 944 45 50 12",
    "sg:postcode":"48007",
    "sg:province":"Vizcaya",
    "wof:name":"Pedro Aparicio Sanchez",
    "wof:placetype":"venue"
},
  "geometry": {"coordinates":[-2.9293720722,43.2689056396],"type":"Point"}
}