{
  "type": "Feature",
  "properties": {
    "addr:full":"Calle de Azafran, 5 Majadahonda Madrid 28220",
    "addr:housenumber":"5",
    "addr:postcode":"28220",
    "addr:street":"Calle De Azafran",
    "iso:country":"ES",
    "sg:address":"Calle de Azafran, 5",
    "sg:city":"Majadahonda",
    "sg:orig_category":"Diplomas Diversos",
    "sg:phone":"+34 916 39 22 69",
    "sg:postcode":"28220",
    "sg:province":"Madrid",
    "wof:name":"Carbo Fite Rafael",
    "wof:placetype":"venue"
},
  "geometry": {"coordinates":[-3.8684661388,40.4557151794],"type":"Point"}
}