{
  "type": "Feature",
  "properties": {
    "addr:full":"Calle de Canoa, 16 Madrid Madrid 28042",
    "addr:housenumber":"16",
    "addr:postcode":"madrid;28042",
    "addr:street":"Calle De Canoa",
    "iso:country":"ES",
    "sg:address":"Calle de Canoa, 16",
    "sg:city":"Madrid",
    "sg:orig_category":"Puertas Y Portales",
    "sg:phone":"+34 913 20 00 67",
    "sg:postcode":"28042",
    "sg:province":"Madrid",
    "wof:name":"Lobato Perez Jose",
    "wof:placetype":"venue"
},
  "geometry": {"coordinates":[-3.5913391113,40.4532699585],"type":"Point"}
}