{
  "type": "Feature",
  "properties": {
    "addr:full":"Av Diagonal, 534 Barcelona Barcelona 08006",
    "addr:housenumber":"534",
    "addr:postcode":"08006",
    "addr:street":"Av Diagonal",
    "iso:country":"ES",
    "sg:address":"Av Diagonal, 534",
    "sg:city":"Barcelona",
    "sg:orig_category":"Abogados",
    "sg:phone":"+34 934 14 62 04",
    "sg:postcode":"08006",
    "sg:province":"Barcelona",
    "wof:name":"Angles Buxeda Advocats S.l.",
    "wof:placetype":"venue"
},
  "geometry": {"coordinates":[2.1519474983,41.3948249817],"type":"Point"}
}