{
  "type": "Feature",
  "properties": {
    "addr:full":"Sect Literatos, 21 Tres Cantos Madrid 28760",
    "addr:housenumber":"21",
    "addr:postcode":"28760",
    "addr:street":"Literatos",
    "iso:country":"ES",
    "sg:address":"Sect Literatos, 21",
    "sg:city":"Tres Cantos",
    "sg:orig_category":"Cl\u00cdnicas Dentales",
    "sg:phone":"+34 918 04 70 18",
    "sg:postcode":"28760",
    "sg:province":"Madrid",
    "wof:name":"Pejara Asociados S.l.v.",
    "wof:placetype":"venue"
},
  "geometry": {"coordinates":[-3.7128260136,40.6074752808],"type":"Point"}
}