{
  "type": "Feature",
  "properties": {
    "iso:country":"ES",
    "sg:address":"Calle de Canovas Del Castillo, 39",
    "sg:city":"Jumilla",
    "sg:orig_category":"Agencias Y Agentes Comerciales, Representantes",
    "sg:phone":"+34 968 78 11 81",
    "sg:postcode":"30520",
    "sg:province":"Murcia",
    "wof:name":"Abarca Lopez Jose",
    "wof:placetype":"venue"
},
  "geometry": {"coordinates":[-1.328631,38.474537],"type":"Point"}
}