{
  "type": "Feature",
  "properties": {
    "iso:country":"ES",
    "sg:address":"Plaz Espa\u00d1a, 2",
    "sg:city":"Piedrahita",
    "sg:orig_category":"Caf\u00c9s, Bares, Cervecer\u00cdas",
    "sg:phone":"+34 920 36 01 02",
    "sg:postcode":"05500",
    "sg:province":"\u00c1vila",
    "wof:name":"Hernandez Courreira Marcelino",
    "wof:placetype":"venue"
},
  "geometry": {"coordinates":[-5.3273978233,40.4630775452],"type":"Point"}
}