{
  "type": "Feature",
  "properties": {
    "iso:country":"ES",
    "sg:address":"Calle de Arcos, 1",
    "sg:city":"Jerez De La Frontera",
    "sg:orig_category":"Centros Comerciales Y Grandes Tiendas",
    "sg:phone":"+34 956 32 54 84",
    "sg:postcode":"11402",
    "sg:province":"C\u00e1diz",
    "wof:name":"Ventura Jerez S.l.",
    "wof:placetype":"venue"
},
  "geometry": {"coordinates":[-6.1352500916,36.683380127],"type":"Point"}
}