{
  "type": "Feature",
  "properties": {
    "addr:full":"Pase Maritimo Ciudad De Melilla, 9 Malaga M\u00e1laga 29016",
    "addr:housenumber":"9",
    "addr:postcode":"29016",
    "addr:street":"Melilla;Ma\u0301Laga",
    "iso:country":"ES",
    "sg:address":"Pase Maritimo Ciudad De Melilla, 9",
    "sg:city":"Malaga",
    "sg:orig_category":"Abogados",
    "sg:phone":"+34 952 22 25 21",
    "sg:postcode":"29016",
    "sg:province":"M\u00e1laga",
    "wof:name":"Rodriguez Sanchez Justo Agustin",
    "wof:placetype":"venue"
},
  "geometry": {"coordinates":[-4.4123668671,36.7161102295],"type":"Point"}
}