{
  "type": "Feature",
  "properties": {
    "iso:country":"ES",
    "sg:address":"Calle de Basotxiki, 9",
    "sg:city":"Donostia-san Sebastian",
    "sg:orig_category":"Perfumer\u00cda (al Por Menor)",
    "sg:phone":"+34 943 28 09 97",
    "sg:postcode":"20015",
    "sg:province":"Guip\u00f9zcoa",
    "wof:name":"Aristizabal Echeverria Celestina",
    "wof:placetype":"venue"
},
  "geometry": {"coordinates":[-1.9531414509,43.3155326843],"type":"Point"}
}