{
  "type": "Feature",
  "properties": {
    "iso:country":"ES",
    "sg:address":"Avda Severino Fernandez, 62",
    "sg:city":"Tafalla",
    "sg:orig_category":"Comercio, Reparaci\u00d3n De Bicicletas, De Motocicletas, De Accesorios",
    "sg:phone":"+34 948 70 00 22",
    "sg:postcode":"31300",
    "sg:province":"Navarra",
    "wof:name":"Arrazubi Gainza Carlos",
    "wof:placetype":"venue"
},
  "geometry": {"coordinates":[-1.6735869646,42.5286026001],"type":"Point"}
}