{
  "type": "Feature",
  "properties": {
    "addr:full":"Calle de Ferrocarril, 18 Zafra Badajoz 06300",
    "addr:housenumber":"18",
    "addr:postcode":"06300",
    "addr:street":"Calle De Ferrocarril",
    "iso:country":"ES",
    "sg:address":"Calle de Ferrocarril, 18",
    "sg:city":"Zafra",
    "sg:orig_category":"Bebidas",
    "sg:phone":"+34 924 55 16 83",
    "sg:postcode":"06300",
    "sg:province":"Badajoz",
    "wof:name":"Ruiz Sanchez E Hijos S.l.",
    "wof:placetype":"venue"
},
  "geometry": {"coordinates":[-6.4078788757,38.4100494385],"type":"Point"}
}