{
  "type": "Feature",
  "properties": {
    "iso:country":"ES",
    "sg:address":"Calle de Jose Antonio Primo De Rivera, 54",
    "sg:city":"Arrecife",
    "sg:orig_category":"Bares, Piano",
    "sg:phone":"+34 928 81 68 29",
    "sg:postcode":"35500",
    "sg:province":"Las Palmas",
    "wof:name":"Saal S.l.",
    "wof:placetype":"venue"
},
  "geometry": {"coordinates":[-13.5528078079,28.9596595764],"type":"Point"}
}