{
  "type": "Feature",
  "properties": {
    "addr:full":"Calle de Fuengirola, 16 Marbella M\u00e1laga 29600",
    "addr:housenumber":"16",
    "addr:postcode":"29600",
    "addr:street":"Calle De Fuengirola;Ma\u0301Laga",
    "iso:country":"ES",
    "sg:address":"Calle de Fuengirola, 16",
    "sg:city":"Marbella",
    "sg:orig_category":"Restaurantes",
    "sg:phone":"+34 952 77 14 47",
    "sg:postcode":"29600",
    "sg:province":"M\u00e1laga",
    "wof:name":"Tarifa Carrion Alfonso",
    "wof:placetype":"venue"
},
  "geometry": {"coordinates":[-4.8756971359,36.5080757141],"type":"Point"}
}