{
  "type": "Feature",
  "properties": {
    "addr:full":"Carrer de Bruc, 19 S. Celoni Barcelona 08470",
    "addr:housenumber":"19",
    "addr:postcode":"08470",
    "addr:street":"Carrer De Bruc;S. Celoni Barcelona",
    "iso:country":"ES",
    "sg:address":"Carrer de Bruc, 19",
    "sg:city":"S. Celoni",
    "sg:orig_category":"Inform\u00c1tica: Material Y Suministros",
    "sg:phone":"+34 938 67 32 67",
    "sg:postcode":"08470",
    "sg:province":"Barcelona",
    "wof:name":"Aplicacions Informatiques Del Valles S.a.",
    "wof:placetype":"venue"
},
  "geometry": {"coordinates":[2.4962377548,41.6934089661],"type":"Point"}
}