{
  "type": "Feature",
  "properties": {
    "addr:full":"Rond San Francisco, S/n Caceres C\u00e1ceres 10005",
    "addr:postcode":"10005",
    "addr:street":"San Francisco S / N;Ca\u0301Ceres",
    "iso:country":"ES",
    "sg:address":"Rond San Francisco, S/n",
    "sg:city":"Caceres",
    "sg:orig_category":"M\u00c9dicos: Cirug\u00cda General",
    "sg:phone":"+34 927 24 37 35",
    "sg:postcode":"10005",
    "sg:province":"C\u00e1ceres",
    "wof:name":"Rodriguez Duran Francisco",
    "wof:placetype":"venue"
},
  "geometry": {"coordinates":[-6.3663191795,39.454246521],"type":"Point"}
}