{
  "type": "Feature",
  "properties": {
    "iso:country":"ES",
    "sg:address":"C(pol Talluntxe), 44",
    "sg:city":"Noain",
    "sg:orig_category":"Mec\u00c1nico Del Autom\u00d3vil",
    "sg:phone":"+34 948 31 63 97",
    "sg:postcode":"31110",
    "sg:province":"Navarra",
    "wof:name":"Electromecanica San Juan S.l.",
    "wof:placetype":"venue"
},
  "geometry": {"coordinates":[-1.6327550411,42.7709388733],"type":"Point"}
}