{
  "type": "Feature",
  "properties": {
    "addr:full":"Plaz San Nicolas, 3 Valencia Valencia 46001",
    "addr:postcode":"46001",
    "addr:street":"Plaz",
    "iso:country":"ES",
    "sg:address":"Plaz San Nicolas, 3",
    "sg:city":"Valencia",
    "sg:orig_category":"Edici\u00d3n De Diarios, Revistas, Boletines",
    "sg:phone":"+34 963 15 37 24",
    "sg:postcode":"46001",
    "sg:province":"Valencia",
    "wof:name":"Molins Ediciones S.l",
    "wof:placetype":"venue"
},
  "geometry": {"coordinates":[-0.3793140054,39.4757881165],"type":"Point"}
}