{
  "type": "Feature",
  "properties": {
    "addr:full":"Pol. Panama, S/n Torres Segre Lleida 25170",
    "addr:housenumber":"s / n",
    "addr:postcode":"25170",
    "addr:street":"Pol. Panama",
    "iso:country":"ES",
    "sg:address":"Pol. Panama, S/n",
    "sg:city":"Torres Segre",
    "sg:orig_category":"Empresas De Pintura Y Revestimientos",
    "sg:phone":"+34 973 79 23 33",
    "sg:postcode":"25170",
    "sg:province":"Lleida",
    "wof:name":"Duomin S.l.",
    "wof:placetype":"venue"
},
  "geometry": {"coordinates":[0.5142099857,41.5340461731],"type":"Point"}
}