{
  "type": "Feature",
  "properties": {
    "addr:full":"Calle de Clara Campoamor, 14 Almansa Albacete 02640",
    "addr:housenumber":"14",
    "addr:postcode":"02640",
    "addr:street":"Calle De Clara Campoamor",
    "iso:country":"ES",
    "sg:address":"Calle de Clara Campoamor, 14",
    "sg:city":"Almansa",
    "sg:orig_category":"Confecci\u00d3n De Zapatos",
    "sg:phone":"+34 967 34 46 10",
    "sg:postcode":"02640",
    "sg:province":"Albacete",
    "wof:name":"Calzados Monzo S.l.",
    "wof:placetype":"venue"
},
  "geometry": {"coordinates":[-1.1059590578,38.8763999939],"type":"Point"}
}