{
  "type": "Feature",
  "properties": {
    "addr:full":"Calle de Sibelius, 16 Malaga M\u00e1laga 29016",
    "addr:housenumber":"16",
    "addr:postcode":"29016",
    "addr:street":"Calle De Sibelius;Ma\u0301Laga",
    "iso:country":"ES",
    "sg:address":"Calle de Sibelius, 16",
    "sg:city":"Malaga",
    "sg:orig_category":"Maquinaria Para Industrias Diversas",
    "sg:phone":"+34 952 29 71 76",
    "sg:postcode":"29016",
    "sg:province":"M\u00e1laga",
    "wof:name":"I T Global Trading",
    "wof:placetype":"venue"
},
  "geometry": {"coordinates":[-4.3915739059,36.7262001038],"type":"Point"}
}