{
  "type": "Feature",
  "properties": {
    "addr:full":"Calle de Jose Antonio, 5 Ahigal C\u00e1ceres 10650",
    "addr:housenumber":"5",
    "addr:postcode":"10650",
    "addr:street":"Calle De Jose Antonio;Ca\u0301Ceres",
    "iso:country":"ES",
    "sg:address":"Calle de Jose Antonio, 5",
    "sg:city":"Ahigal",
    "sg:orig_category":"Arreglo, Reparaci\u00d3n, Piezas Sueltas De Televisi\u00d3n, V\u00cddeo, Hi",
    "sg:phone":"+34 927 43 92 05",
    "sg:postcode":"10650",
    "sg:province":"C\u00e1ceres",
    "wof:name":"Lino Antunez Herminia",
    "wof:placetype":"venue"
},
  "geometry": {"coordinates":[-6.1874728203,40.1898231506],"type":"Point"}
}