{
  "type": "Feature",
  "properties": {
    "addr:full":"Calle de Tomas Salvador, 17 Villada Palencia 34340",
    "addr:housenumber":"17",
    "addr:postcode":"34340",
    "addr:street":"Calle De Tomas Salvador",
    "iso:country":"ES",
    "sg:address":"Calle de Tomas Salvador, 17",
    "sg:city":"Villada",
    "sg:orig_category":"Caf\u00c9s, Bares, Cervecer\u00cdas",
    "sg:phone":"+34 979 84 41 25",
    "sg:postcode":"34340",
    "sg:province":"Palencia",
    "wof:name":"Fernandez Perez Miguel Angel",
    "wof:placetype":"venue"
},
  "geometry": {"coordinates":[-4.9679460526,42.2523956299],"type":"Point"}
}