{
  "type": "Feature",
  "properties": {
    "addr:full":"Avda Regueral, 25 Navia Asturias 33710",
    "addr:housenumber":"25",
    "addr:postcode":"33710",
    "addr:street":"Avda Regueral",
    "iso:country":"ES",
    "sg:address":"Avda Regueral, 25",
    "sg:city":"Navia",
    "sg:orig_category":"Agencias De Viajes",
    "sg:phone":"+34 985 47 41 07",
    "sg:postcode":"33710",
    "sg:province":"Asturias",
    "wof:name":"Viajes Muralbu S.l.",
    "wof:placetype":"venue"
},
  "geometry": {"coordinates":[-6.7245287895,43.5409584045],"type":"Point"}
}