{
  "type": "Feature",
  "properties": {
    "iso:country":"ES",
    "sg:address":"Mayor, 16",
    "sg:city":"Playa Honda",
    "sg:orig_category":"Agencias Y Agentes Comerciales, Representantes",
    "sg:phone":"+34 928 82 09 07",
    "sg:postcode":"35509",
    "sg:province":"Las Palmas",
    "wof:name":"Garpalanz S.l.",
    "wof:placetype":"venue"
},
  "geometry": {"coordinates":[-13.5915079117,28.9548130035],"type":"Point"}
}