{
  "type": "Feature",
  "properties": {
    "iso:country":"ES",
    "sg:address":"Carrer de Rossello, 33",
    "sg:city":"Terrassa",
    "sg:orig_category":"Montaje (empresas De)",
    "sg:phone":"+34 937 88 19 21",
    "sg:postcode":"08224",
    "sg:province":"Barcelona",
    "wof:name":"Auting Automatismos S.l.u.",
    "wof:placetype":"venue"
},
  "geometry": {"coordinates":[2.0010969639,41.553352356],"type":"Point"}
}