{
  "type": "Feature",
  "properties": {
    "iso:country":"ES",
    "sg:address":"Ctra. V-alquian, 4",
    "sg:city":"Alquian",
    "sg:orig_category":"Ingenier\u00cda, Centros De Estudios (diversos)",
    "sg:phone":"+34 950 29 77 21",
    "sg:postcode":"04130",
    "sg:province":"Almer\u00eda",
    "wof:name":"Diaz Pardo Maria",
    "wof:placetype":"venue"
},
  "geometry": {"coordinates":[-2.3529150486,36.8523406982],"type":"Point"}
}