{
  "type": "Feature",
  "properties": {
    "iso:country":"ES",
    "sg:address":"Carrer de Comtessa De Pardo Bazan, 10",
    "sg:city":"Barcelona",
    "sg:orig_category":"Mec\u00c1nico Del Autom\u00d3vil",
    "sg:phone":"+34 933 40 28 98",
    "sg:postcode":"08027",
    "sg:province":"Barcelona",
    "wof:name":"Rayo Marjalizo Aurelio",
    "wof:placetype":"venue"
},
  "geometry": {"coordinates":[2.1848869324,41.4249763489],"type":"Point"}
}