{
  "type": "Feature",
  "properties": {
    "addr:full":"Carrer de Creu, 76 S. Just Desvern Barcelona 08960",
    "addr:housenumber":"76",
    "addr:postcode":"08960",
    "addr:street":"Carrer De Creu",
    "iso:country":"ES",
    "sg:address":"Carrer de Creu, 76",
    "sg:city":"S. Just Desvern",
    "sg:orig_category":"M\u00c9dicos: Estomatolog\u00cda",
    "sg:phone":"+34 933 72 44 44",
    "sg:postcode":"08960",
    "sg:province":"Barcelona",
    "wof:name":"Diez Pablos Juan Luis",
    "wof:placetype":"venue"
},
  "geometry": {"coordinates":[2.0746839046,41.3821105957],"type":"Point"}
}