{
  "type": "Feature",
  "properties": {
    "iso:country":"ES",
    "sg:address":"La Barqui\u00f1a, S/n",
    "sg:city":"Negreira",
    "sg:orig_category":"Agentes Generales De Seguros",
    "sg:phone":"+34 981 88 54 77",
    "sg:postcode":"15830",
    "sg:province":"La Coru\u00f1a",
    "wof:name":"Mari\u00f1o Torreira Manuel",
    "wof:placetype":"venue"
},
  "geometry": {"coordinates":[-8.7368841171,42.9089660645],"type":"Point"}
}