{
  "type": "Feature",
  "properties": {
    "iso:country":"ES",
    "sg:address":"Calle de Doctor Lazarraga, S/n",
    "sg:city":"Malaga",
    "sg:orig_category":"Internados & Ense\u00d1anza Privada",
    "sg:phone":"+34 952 27 16 00",
    "sg:postcode":"29010",
    "sg:province":"M\u00e1laga",
    "wof:name":"Hijas De Jesus Prov Mediterranea Curia Provincial",
    "wof:placetype":"venue"
},
  "geometry": {"coordinates":[-4.4397110939,36.7240066528],"type":"Point"}
}