{
  "type": "Feature",
  "properties": {
    "addr:full":"Carrer de Girona, 29 Lloret Mar Girona 17310",
    "addr:housenumber":"29",
    "addr:postcode":"17310",
    "addr:street":"Carrer De Girona",
    "iso:country":"ES",
    "sg:address":"Carrer de Girona, 29",
    "sg:city":"Lloret Mar",
    "sg:orig_category":"Dietistas",
    "sg:phone":"+34 972 36 97 47",
    "sg:postcode":"17310",
    "sg:province":"Girona",
    "wof:name":"Lisitano Caraballo Alba",
    "wof:placetype":"venue"
},
  "geometry": {"coordinates":[2.8444049358,41.7041931152],"type":"Point"}
}