{
  "type": "Feature",
  "properties": {
    "addr:full":"Pla\u00c7 Castell, 1 Alcasser Valencia 46290",
    "addr:housenumber":"1",
    "addr:postcode":"46290",
    "addr:street":"Castell",
    "iso:country":"ES",
    "sg:address":"Pla\u00c7 Castell, 1",
    "sg:city":"Alcasser",
    "sg:orig_category":"Ense\u00d1anza, Formaci\u00d3n Profesional: Aprendizaje",
    "sg:phone":"+34 961 24 03 47",
    "sg:postcode":"46290",
    "sg:province":"Valencia",
    "wof:name":"Ayuntamiento De Alcasser",
    "wof:placetype":"venue"
},
  "geometry": {"coordinates":[-0.4453490078,39.3651695251],"type":"Point"}
}