{
  "type": "Feature",
  "properties": {
    "addr:full":"Calle de Cordoba, 10 Jerez De La Frontera C\u00e1diz 11405",
    "addr:housenumber":"10",
    "addr:postcode":"11405",
    "addr:street":"Calle De Cordoba",
    "iso:country":"ES",
    "sg:address":"Calle de Cordoba, 10",
    "sg:city":"Jerez De La Frontera",
    "sg:orig_category":"Empresas De Limpieza",
    "sg:phone":"+34 956 18 56 76",
    "sg:postcode":"11405",
    "sg:province":"C\u00e1diz",
    "wof:name":"Iss Facility Services S.a.",
    "wof:placetype":"venue"
},
  "geometry": {"coordinates":[-6.1270909309,36.6915092468],"type":"Point"}
}