{
  "type": "Feature",
  "properties": {
    "iso:country":"ES",
    "sg:address":"Plaz Santiago Bernabeu, 14",
    "sg:city":"Almansa",
    "sg:orig_category":"Promotores Constructores",
    "sg:phone":"+34 967 31 21 58",
    "sg:postcode":"02640",
    "sg:province":"Albacete",
    "wof:name":"Sanchez Jumial Empresa Constructora S.a.",
    "wof:placetype":"venue"
},
  "geometry": {"coordinates":[-1.0988930464,38.8663711548],"type":"Point"}
}