{
  "type": "Feature",
  "properties": {
    "addr:full":"Avda Mediterraneo, 14 Madrid Madrid 28007",
    "addr:housenumber":"14",
    "addr:postcode":"madrid;28007",
    "addr:street":"Avda Mediterraneo",
    "iso:country":"ES",
    "sg:address":"Avda Mediterraneo, 14",
    "sg:city":"Madrid",
    "sg:orig_category":"Negocio De Materiales De Construcci\u00d3n",
    "sg:phone":"+34 914 33 77 78",
    "sg:postcode":"28007",
    "sg:province":"Madrid",
    "wof:name":"Julio Vazquez S. A.",
    "wof:placetype":"venue"
},
  "geometry": {"coordinates":[-3.6755158901,40.4070739746],"type":"Point"}
}