{
  "type": "Feature",
  "properties": {
    "iso:country":"ES",
    "sg:address":"Don Garcia El Restaurador, 5",
    "sg:city":"Estella",
    "sg:orig_category":"Molduras, Junquillos, Listones Y Molduras Perforadas",
    "sg:phone":"+34 948 55 69 16",
    "sg:postcode":"31200",
    "sg:province":"Navarra",
    "wof:name":"Lara Esparza Jose Luis",
    "wof:placetype":"venue"
},
  "geometry": {"coordinates":[-2.0353488922,42.6726417542],"type":"Point"}
}