{
  "type": "Feature",
  "properties": {
    "addr:full":"Avda Libertad, 6 San Miguel Murcia 30009",
    "addr:housenumber":"6",
    "addr:postcode":"30009",
    "addr:street":"Avda Libertad",
    "iso:country":"ES",
    "sg:address":"Avda Libertad, 6",
    "sg:city":"San Miguel",
    "sg:orig_category":"Peluqueros: De Se\u00d1oras",
    "sg:phone":"+34 968 24 96 52",
    "sg:postcode":"30009",
    "sg:province":"Murcia",
    "wof:name":"Carrillo Moreno Maria Dolores",
    "wof:placetype":"venue"
},
  "geometry": {"coordinates":[-1.1334389448,37.9899215698],"type":"Point"}
}