{
  "type": "Feature",
  "properties": {
    "iso:country":"ES",
    "sg:address":"Calle de Toledo, 40",
    "sg:city":"Madrid",
    "sg:orig_category":"Productos Qu\u00cdmicos (fabricaci\u00d3n, Al Por Mayor)",
    "sg:phone":"+34 913 65 02 34",
    "sg:postcode":"28005",
    "sg:province":"Madrid",
    "wof:name":"Tecnicas Y Montaje De Laboratorio S.a.l.",
    "wof:placetype":"venue"
},
  "geometry": {"coordinates":[-3.7037959099,40.4050598145],"type":"Point"}
}