{
  "type": "Feature",
  "properties": {
    "iso:country":"ES",
    "sg:address":"Calle de Artabide, 46",
    "sg:city":"Ondarroa",
    "sg:orig_category":"Asociaciones, Organismos Culturales Y Socioeducativos",
    "sg:phone":"+34 946 83 22 24",
    "sg:postcode":"48700",
    "sg:province":"Vizcaya",
    "wof:name":"Sociedad Cultural Recreativa Beti-bardi\u00d1",
    "wof:placetype":"venue"
},
  "geometry": {"coordinates":[-2.4235420227,43.3232688904],"type":"Point"}
}