{
  "type": "Feature",
  "properties": {
    "addr:full":"Calle de Darro, 24 Almodovar Campo Ciudad Real 13580",
    "addr:housenumber":"24",
    "addr:postcode":"13580",
    "addr:street":"Calle De Darro",
    "iso:country":"ES",
    "sg:address":"Calle de Darro, 24",
    "sg:city":"Almodovar Campo",
    "sg:orig_category":"Pr\u00c9stamos Personales E Hipotecarios",
    "sg:phone":"+34 926 48 37 13",
    "sg:postcode":"13580",
    "sg:province":"Ciudad Real",
    "wof:name":"Registro De La Propiedad",
    "wof:placetype":"venue"
},
  "geometry": {"coordinates":[-3.1221497059,39.4022865295],"type":"Point"}
}