{
  "type": "Feature",
  "properties": {
    "addr:full":"Carrer de Sant Carles, 57 Santa Coloma De Gramenet Barcelona 08922",
    "addr:housenumber":"57",
    "addr:postcode":"08922",
    "addr:street":"Carrer De Sant Carles",
    "iso:country":"ES",
    "sg:address":"Carrer de Sant Carles, 57",
    "sg:city":"Santa Coloma De Gramenet",
    "sg:orig_category":"Inmobiliaria (agencias)",
    "sg:phone":"+34 934 66 28 28",
    "sg:postcode":"08922",
    "sg:province":"Barcelona",
    "wof:name":"Fincas Mirafer Sl",
    "wof:placetype":"venue"
},
  "geometry": {"coordinates":[2.2092170715,41.4494094849],"type":"Point"}
}