{
  "type": "Feature",
  "properties": {
    "addr:full":"Calle de Roquenublo (de), 1 Humanes De Madrid Madrid 28970",
    "addr:postcode":"28970",
    "addr:street":"Calle De Roquenublo De 1",
    "iso:country":"ES",
    "sg:address":"Calle de Roquenublo (de), 1",
    "sg:city":"Humanes De Madrid",
    "sg:orig_category":"Fabricaci\u00d3n De Moldes Y Modelos",
    "sg:phone":"+34 916 04 88 69",
    "sg:postcode":"28970",
    "sg:province":"Madrid",
    "wof:name":"Francisco Barayon Alonso Y Leonard Hans Kern C.b.",
    "wof:placetype":"venue"
},
  "geometry": {"coordinates":[-3.8348920345,40.2416038513],"type":"Point"}
}