{
  "type": "Feature",
  "properties": {
    "addr:full":"Avgd Balmes, 61 Igualada Barcelona 08700",
    "addr:housenumber":"61",
    "addr:postcode":"08700",
    "addr:street":"Avgd Balmes",
    "iso:country":"ES",
    "sg:address":"Avgd Balmes, 61",
    "sg:city":"Igualada",
    "sg:orig_category":"Asesor\u00cda Fiscal Y Jur\u00cddica",
    "sg:phone":"+34 938 05 36 60",
    "sg:postcode":"08700",
    "sg:province":"Barcelona",
    "wof:name":"Tarafa Cuadras Jaime Jose",
    "wof:placetype":"venue"
},
  "geometry": {"coordinates":[1.6141619682,41.5868377686],"type":"Point"}
}