{
  "type": "Feature",
  "properties": {
    "iso:country":"ES",
    "sg:address":"Carrer de Sant Domingo, 6",
    "sg:city":"Palma",
    "sg:orig_category":"Arquitectos",
    "sg:phone":"+34 971 72 34 40",
    "sg:postcode":"07001",
    "sg:province":"Islas Baleares",
    "wof:name":"Palmer Caldes Mateo",
    "wof:placetype":"venue"
},
  "geometry": {"coordinates":[2.6493179798,39.5698661804],"type":"Point"}
}