{
  "type": "Feature",
  "properties": {
    "iso:country":"ES",
    "sg:address":"Plaz Carmen Abela, 15",
    "sg:city":"Ronda",
    "sg:orig_category":"Abogados",
    "sg:phone":"+34 952 19 09 16",
    "sg:postcode":"29400",
    "sg:province":"M\u00e1laga",
    "wof:name":"Garcia Gonzalez Jorge",
    "wof:placetype":"venue"
},
  "geometry": {"coordinates":[-5.1644058228,36.7430534363],"type":"Point"}
}