{
  "type": "Feature",
  "properties": {
    "addr:full":"Avda Cadiz (de), 56 Cordoba C\u00f3rdoba 14009",
    "addr:housenumber":"56",
    "addr:postcode":"14009",
    "addr:street":"Avda Cadiz De;Co\u0301Rdoba",
    "iso:country":"ES",
    "sg:address":"Avda Cadiz (de), 56",
    "sg:city":"Cordoba",
    "sg:orig_category":"Bancos",
    "sg:phone":"+34 957 29 97 44",
    "sg:postcode":"14009",
    "sg:province":"C\u00f3rdoba",
    "sg:website":"www.bancoandalucia.es",
    "wof:name":"Banco De Andalucia",
    "wof:placetype":"venue"
},
  "geometry": {"coordinates":[-4.7784290314,37.8709411621],"type":"Point"}
}