{
  "type": "Feature",
  "properties": {
    "addr:full":"Calle de Gijon, S/n Pola De Laviana Asturias 33980",
    "addr:postcode":"33980",
    "addr:street":"Calle De Gijon S / N",
    "iso:country":"ES",
    "sg:address":"Calle de Gijon, S/n",
    "sg:city":"Pola De Laviana",
    "sg:orig_category":"Mutuas De Seguros",
    "sg:phone":"+34 985 61 04 22",
    "sg:postcode":"33980",
    "sg:province":"Asturias",
    "wof:name":"Montepio De La Mineria Asturiana Del Car",
    "wof:placetype":"venue"
},
  "geometry": {"coordinates":[-5.5637440681,43.2415542603],"type":"Point"}
}