{
  "type": "Feature",
  "properties": {
    "iso:country":"ES",
    "sg:address":"Calle de San Roque, 4",
    "sg:city":"Calamocha",
    "sg:orig_category":"Farmacias",
    "sg:phone":"+34 978 73 22 43",
    "sg:postcode":"44200",
    "sg:province":"Teruel",
    "wof:name":"Garcia Luengo Silvia",
    "wof:placetype":"venue"
},
  "geometry": {"coordinates":[-1.2945430279,40.9237861633],"type":"Point"}
}