{
  "type": "Feature",
  "properties": {
    "iso:country":"ES",
    "sg:address":"Calle de Juan Ramon Jimenez, 6",
    "sg:city":"Madrid",
    "sg:orig_category":"Peluquer\u00cdas, Peluquer\u00cda Mixta",
    "sg:phone":"+34 914 57 44 07",
    "sg:postcode":"28036",
    "sg:province":"Madrid",
    "wof:name":"Futuro Mirache S.l.",
    "wof:placetype":"venue"
},
  "geometry": {"coordinates":[-3.6866281033,40.4582862854],"type":"Point"}
}