{
  "type": "Feature",
  "properties": {
    "iso:country":"ES",
    "sg:address":"Av Diagonal, 347",
    "sg:city":"Barcelona",
    "sg:orig_category":"M\u00c9dicos: Alergolog\u00cda",
    "sg:phone":"+34 932 07 28 55",
    "sg:postcode":"08037",
    "sg:province":"Barcelona",
    "wof:name":"Jaime Botey Elisabeth Botey Elena Botey Scp",
    "wof:placetype":"venue"
},
  "geometry": {"coordinates":[2.1662559509,41.3979034424],"type":"Point"}
}