{
  "type": "Feature",
  "properties": {
    "iso:country":"ES",
    "sg:address":"Carrer de Cardener, 1",
    "sg:city":"Terrassa",
    "sg:orig_category":"Pararrayos, Tomas De Tierra (fabricaci\u00d3n, Colocaci\u00d3n)",
    "sg:phone":"+34 937 85 07 46",
    "sg:postcode":"08223",
    "sg:province":"Barcelona",
    "wof:name":"Quibac S. A.",
    "wof:placetype":"venue"
},
  "geometry": {"coordinates":[2.0310549736,41.5574188232],"type":"Point"}
}