{
  "type": "Feature",
  "properties": {
    "iso:country":"ES",
    "sg:address":"Rua Campo Da Barreira, S/n",
    "sg:city":"Allariz",
    "sg:orig_category":"Peluqueros: De Se\u00d1oras",
    "sg:phone":"+34 988 44 01 36",
    "sg:postcode":"32660",
    "sg:province":"Ourense",
    "wof:name":"Conde Prol Nieves",
    "wof:placetype":"venue"
},
  "geometry": {"coordinates":[-7.799243927,42.1880989075],"type":"Point"}
}