{
  "type": "Feature",
  "properties": {
    "iso:country":"ES",
    "sg:address":"Barr Cueto, S/n",
    "sg:city":"Santurtzi",
    "sg:orig_category":"Centros De Educaci\u00d3n Especial",
    "sg:phone":"+34 944 62 90 88",
    "sg:postcode":"48980",
    "sg:province":"Vizcaya",
    "wof:name":"Gobierno Vasco-eusko Jaurlaritza",
    "wof:placetype":"venue"
},
  "geometry": {"coordinates":[-3.0402638912,43.3327636719],"type":"Point"}
}