{
  "type": "Feature",
  "properties": {
    "addr:full":"Carr Major, 144 Manises Valencia 46940",
    "addr:housenumber":"144",
    "addr:postcode":"46940",
    "addr:street":"Carr Major",
    "iso:country":"ES",
    "sg:address":"Carr Major, 144",
    "sg:city":"Manises",
    "sg:orig_category":"Cervecer\u00cdas",
    "sg:phone":"+34 961 54 09 56",
    "sg:postcode":"46940",
    "sg:province":"Valencia",
    "wof:name":"Cuesta Lopez Jose",
    "wof:placetype":"venue"
},
  "geometry": {"coordinates":[-0.4657509923,39.4946594238],"type":"Point"}
}