{
  "type": "Feature",
  "properties": {
    "iso:country":"ES",
    "sg:address":"Calle de Belgica, S/n",
    "sg:city":"Caceres",
    "sg:orig_category":"Caf\u00c9s, Bares, Cervecer\u00cdas",
    "sg:phone":"+34 927 23 88 29",
    "sg:postcode":"10005",
    "sg:province":"C\u00e1ceres",
    "wof:name":"Perez Garcia Francisco",
    "wof:placetype":"venue"
},
  "geometry": {"coordinates":[-6.3824629784,39.4623146057],"type":"Point"}
}