{
  "type": "Feature",
  "properties": {
    "addr:full":"Pelegrin Lamuedra, S/n Derro\u00f1adas Soria 42153",
    "addr:housenumber":"s",
    "addr:postcode":"42153",
    "addr:street":"/ N",
    "iso:country":"ES",
    "sg:address":"Pelegrin Lamuedra, S/n",
    "sg:city":"Derro\u00f1adas",
    "sg:orig_category":"Internados & Ense\u00d1anza Privada",
    "sg:phone":"+34 975 27 12 63",
    "sg:postcode":"42153",
    "sg:province":"Soria",
    "wof:name":"Colegio San Rafael",
    "wof:placetype":"venue"
},
  "geometry": {"coordinates":[-2.6456439495,41.9093551636],"type":"Point"}
}