{
  "type": "Feature",
  "properties": {
    "iso:country":"ES",
    "sg:address":"Pg Pau Claris, 27",
    "sg:city":"Rubi",
    "sg:orig_category":"Cer\u00c1micas: Material Y Suministros",
    "sg:phone":"+34 935 88 89 99",
    "sg:postcode":"08191",
    "sg:province":"Barcelona",
    "wof:name":"Garcia Ruiz Maria Dolores",
    "wof:placetype":"venue"
},
  "geometry": {"coordinates":[2.0309100151,41.4947509766],"type":"Point"}
}