{
  "type": "Feature",
  "properties": {
    "iso:country":"ES",
    "sg:address":"Plaz Mayor, 27",
    "sg:city":"Alcadozo",
    "sg:orig_category":"Cajas De Ahorro",
    "sg:phone":"+34 967 29 13 72",
    "sg:postcode":"02124",
    "sg:province":"Albacete",
    "wof:name":"Caja De Ahorros De Castilla La Mancha",
    "wof:placetype":"venue"
},
  "geometry": {"coordinates":[-1.9807540178,38.6492195129],"type":"Point"}
}