{
  "type": "Feature",
  "properties": {
    "addr:full":"Calle de Tejadillo, 20 Ba\u00d1eza Le\u00f3n 24750",
    "addr:housenumber":"20",
    "addr:postcode":"24750",
    "addr:street":"Calle De Tejadillo;Leo\u0301N",
    "iso:country":"ES",
    "sg:address":"Calle de Tejadillo, 20",
    "sg:city":"Ba\u00d1eza",
    "sg:orig_category":"Perfumer\u00cda, Art\u00cdculos De Ba\u00d1o (fabricaci\u00d3n, Al Por Mayor)",
    "sg:phone":"+34 987 65 67 49",
    "sg:postcode":"24750",
    "sg:province":"Le\u00f3n",
    "wof:name":"Rio Rio Natalia",
    "wof:placetype":"venue"
},
  "geometry": {"coordinates":[-5.9242091179,42.3069114685],"type":"Point"}
}