{
  "type": "Feature",
  "properties": {
    "iso:country":"ES",
    "sg:address":"Calle de Ventura Rodriguez, 4",
    "sg:city":"Oviedo",
    "sg:orig_category":"Arquitectos",
    "sg:phone":"+34 985 23 50 31",
    "sg:postcode":"33004",
    "sg:province":"Asturias",
    "wof:name":"Fernandez Molina Jose Ramon",
    "wof:placetype":"venue"
},
  "geometry": {"coordinates":[-5.8541879654,43.3643074036],"type":"Point"}
}