{
  "type": "Feature",
  "properties": {
    "addr:full":"Avda Garcia Barbon, 133 Vigo Pontevedra 36201",
    "addr:housenumber":"133",
    "addr:postcode":"36201",
    "addr:street":"Avda Garcia Barbon",
    "iso:country":"ES",
    "sg:address":"Avda Garcia Barbon, 133",
    "sg:city":"Vigo",
    "sg:orig_category":"Ense\u00d1anza: Comercio, Gesti\u00d3n, Inform\u00c1tica",
    "sg:phone":"+34 986 22 77 23",
    "sg:postcode":"36201",
    "sg:province":"Pontevedra",
    "sg:website":"www.seresco.es",
    "wof:name":"Seresco S.a.",
    "wof:placetype":"venue"
},
  "geometry": {"coordinates":[-8.7095842361,42.2386474609],"type":"Point"}
}