{
  "type": "Feature",
  "properties": {
    "iso:country":"ES",
    "sg:address":"Avda Provincias (de Las), 18",
    "sg:city":"Fuenlabrada",
    "sg:orig_category":"Fabricaci\u00d3n De Productos Textiles Sin Tejer",
    "sg:phone":"+34 916 15 01 83",
    "sg:postcode":"28941",
    "sg:province":"Madrid",
    "wof:name":"Almacenes Chavero S.l.",
    "wof:placetype":"venue"
},
  "geometry": {"coordinates":[-3.8012344837,40.2968673706],"type":"Point"}
}