{
  "type": "Feature",
  "properties": {
    "iso:country":"ES",
    "sg:address":"La Pe\u00f1a, 16",
    "sg:city":"Capella",
    "sg:orig_category":"Ense\u00d1anza Secundaria: Colegios Y Escuelas Privadas",
    "sg:phone":"+34 974 54 04 32",
    "sg:postcode":"22480",
    "sg:province":"Huesca",
    "wof:name":"Cra Baja Ribagorza - Capella - D.g.a.",
    "wof:placetype":"venue"
},
  "geometry": {"coordinates":[0.3962210119,42.1971931458],"type":"Point"}
}