{
  "type": "Feature",
  "properties": {
    "iso:country":"ES",
    "sg:address":"Calle de Juan Jimenez Cuenca, 20",
    "sg:city":"Lucena",
    "sg:orig_category":"Notarios",
    "sg:phone":"+34 957 50 39 74",
    "sg:postcode":"14900",
    "sg:province":"C\u00f3rdoba",
    "wof:name":"Garcia Pe\u00f1a Y Zejalbo Martin C.b.",
    "wof:placetype":"venue"
},
  "geometry": {"coordinates":[-4.4862370491,37.4104804993],"type":"Point"}
}