{
  "type": "Feature",
  "properties": {
    "iso:country":"ES",
    "sg:address":"Baltasar Gracian, 9",
    "sg:city":"Zubia",
    "sg:orig_category":"Promotores Constructores",
    "sg:phone":"+34 958 89 11 60",
    "sg:postcode":"18140",
    "sg:province":"Granada",
    "wof:name":"Alixares De Aljaima S.l.",
    "wof:placetype":"venue"
},
  "geometry": {"coordinates":[-3.5840637684,37.1213111877],"type":"Point"}
}