{
  "type": "Feature",
  "properties": {
    "iso:country":"ES",
    "sg:address":"Monte Lakartxela, 2",
    "sg:city":"Iru\u00f1a",
    "sg:orig_category":"Audiovisuales: Material Y Accesorios (al Por Menor)",
    "sg:phone":"+34 948 23 58 95",
    "sg:postcode":"31006",
    "sg:province":"Navarra",
    "wof:name":"Ostiz Audiovisuales S.l.",
    "wof:placetype":"venue"
},
  "geometry": {"coordinates":[-1.6347090006,42.8057098389],"type":"Point"}
}