{
  "type": "Feature",
  "properties": {
    "addr:full":"Pg Pere Iii, 48 Manresa Barcelona 08242",
    "addr:housenumber":"48",
    "addr:postcode":"08242",
    "addr:street":"Pg Pere Iii",
    "iso:country":"ES",
    "sg:address":"Pg Pere Iii, 48",
    "sg:city":"Manresa",
    "sg:orig_category":"Centros Empresariales",
    "sg:phone":"+34 938 77 14 41",
    "sg:postcode":"08242",
    "sg:province":"Barcelona",
    "sg:website":"www.faura-casas.com",
    "wof:name":"Faura Casas Auditors Consultors S.l.",
    "wof:placetype":"venue"
},
  "geometry": {"coordinates":[1.82457304,41.7290115356],"type":"Point"}
}