{
  "type": "Feature",
  "properties": {
    "addr:full":"Carrer de Corsega, 540 Barcelona Barcelona 08025",
    "addr:housenumber":"540",
    "addr:postcode":"08025",
    "addr:street":"Carrer De Corsega",
    "iso:country":"ES",
    "sg:address":"Carrer de Corsega, 540",
    "sg:city":"Barcelona",
    "sg:orig_category":"Asilos De Ancianos. Centros Privados",
    "sg:phone":"+34 933 47 67 16",
    "sg:postcode":"08025",
    "sg:province":"Barcelona",
    "wof:name":"Aviswitt S.l.",
    "wof:placetype":"venue"
},
  "geometry": {"coordinates":[2.1726260185,41.4063796997],"type":"Point"}
}