{
  "type": "Feature",
  "properties": {
    "addr:full":"Calle de Constitucion, 23 Albuera Badajoz 06170",
    "addr:housenumber":"23",
    "addr:postcode":"06170",
    "addr:street":"Calle De Constitucion",
    "iso:country":"ES",
    "sg:address":"Calle de Constitucion, 23",
    "sg:city":"Albuera",
    "sg:orig_category":"Quincaller\u00cda (al Por Menor)",
    "sg:phone":"+34 924 48 04 07",
    "sg:postcode":"06170",
    "sg:province":"Badajoz",
    "wof:name":"Torres Vera Estrella",
    "wof:placetype":"venue"
},
  "geometry": {"coordinates":[-6.8242850304,38.7181854248],"type":"Point"}
}