{
  "type": "Feature",
  "properties": {
    "addr:full":"Eix-ample, 107 Albal Valencia 46470",
    "addr:housenumber":"107",
    "addr:postcode":"46470",
    "addr:street":"Eix-Ample",
    "iso:country":"ES",
    "sg:address":"Eix-ample, 107",
    "sg:city":"Albal",
    "sg:orig_category":"Empresas De Carpinter\u00cda De Madera",
    "sg:phone":"+34 961 26 81 50",
    "sg:postcode":"46470",
    "sg:province":"Valencia",
    "wof:name":"Carpinteria Jordan Sanchez S.l.",
    "wof:placetype":"venue"
},
  "geometry": {"coordinates":[-0.418738991,39.3972816467],"type":"Point"}
}