{
  "type": "Feature",
  "properties": {
    "addr:full":"P. Industrial, 7 Rota C\u00e1diz 11520",
    "addr:postcode":"11520",
    "addr:street":"P.;Ca\u0301Diz",
    "iso:country":"ES",
    "sg:address":"P. Industrial, 7",
    "sg:city":"Rota",
    "sg:orig_category":"Muebles Y Accesorios Para Cocinas Y Cuartos De Ba\u00d1o (al Por Menor)",
    "sg:phone":"+34 956 81 14 26",
    "sg:postcode":"11520",
    "sg:province":"C\u00e1diz",
    "wof:name":"Cocinas Avila Garcia S.l.u.",
    "wof:placetype":"venue"
},
  "geometry": {"coordinates":[-6.3688821793,36.6247940063],"type":"Point"}
}