{
  "type": "Feature",
  "properties": {
    "iso:country":"ES",
    "sg:address":"Carrer de Sant Lluis, 84",
    "sg:city":"Barcelona",
    "sg:orig_category":"Empresas De Carpinter\u00cda De Madera",
    "sg:phone":"+34 932 19 79 46",
    "sg:postcode":"08024",
    "sg:province":"Barcelona",
    "wof:name":"Ramon Martinez Juan",
    "wof:placetype":"venue"
},
  "geometry": {"coordinates":[2.1625249386,41.4066886902],"type":"Point"}
}