{
  "type": "Feature",
  "properties": {
    "addr:full":"Calle de Convento, 81 Alhaurin El Grande M\u00e1laga 29120",
    "addr:housenumber":"81",
    "addr:postcode":"29120",
    "addr:street":"Calle De Convento",
    "iso:country":"ES",
    "sg:address":"Calle de Convento, 81",
    "sg:city":"Alhaurin El Grande",
    "sg:orig_category":"Reposter\u00cdas",
    "sg:phone":"+34 952 59 46 27",
    "sg:postcode":"29120",
    "sg:province":"M\u00e1laga",
    "wof:name":"Gallego Bravo Josefa",
    "wof:placetype":"venue"
},
  "geometry": {"coordinates":[-4.6922388077,36.6404762268],"type":"Point"}
}