{
  "type": "Feature",
  "properties": {
    "addr:full":"C/ Balears, 10 Arenal Islas Baleares 07600",
    "addr:housenumber":"10",
    "addr:postcode":"07600",
    "addr:street":"C / Balears",
    "iso:country":"ES",
    "sg:address":"C/ Balears, 10",
    "sg:city":"Arenal",
    "sg:orig_category":"Florister\u00cdas",
    "sg:phone":"+34 971 44 19 22",
    "sg:postcode":"07600",
    "sg:province":"Islas Baleares",
    "wof:name":"Arias Montserrat Manuela",
    "wof:placetype":"venue"
},
  "geometry": {"coordinates":[2.7544968128,39.5008735657],"type":"Point"}
}