{
  "type": "Feature",
  "properties": {
    "iso:country":"ES",
    "sg:address":"C/ Alfonso Xii, 31",
    "sg:city":"Elche",
    "sg:orig_category":"Centros M\u00c9dicos Y Sociales, Dispensarios",
    "sg:phone":"+34 965 45 94 65",
    "sg:postcode":"03203",
    "sg:province":"Alicante",
    "wof:name":"Centro Medico Psicotecnico Para Conductores",
    "wof:placetype":"venue"
},
  "geometry": {"coordinates":[-0.6989470124,38.2640380859],"type":"Point"}
}