{
  "type": "Feature",
  "properties": {
    "iso:country":"ES",
    "sg:address":"Calle de Mayor, 50",
    "sg:city":"Zaidin",
    "sg:orig_category":"Asesor\u00cda Para La Organizaci\u00d3n Y Gesti\u00d3n Del Transporte",
    "sg:phone":"+34 974 47 84 58",
    "sg:postcode":"22530",
    "sg:province":"Huesca",
    "wof:name":"Rumar Transportes S.a.",
    "wof:placetype":"venue"
},
  "geometry": {"coordinates":[0.2646999955,41.6032981873],"type":"Point"}
}