{
  "type": "Feature",
  "properties": {
    "iso:country":"ES",
    "sg:address":"Calle de Soraluce, 7",
    "sg:city":"Zumarraga",
    "sg:orig_category":"Molduras, Junquillos, Listones Y Molduras Perforadas",
    "sg:phone":"+34 943 72 25 26",
    "sg:postcode":"20700",
    "sg:province":"Guip\u00f9zcoa",
    "wof:name":"Ortiz Conde Faustino",
    "wof:placetype":"venue"
},
  "geometry": {"coordinates":[-2.3139350414,43.0906448364],"type":"Point"}
}