{
  "type": "Feature",
  "properties": {
    "addr:full":"Calle de Atarazanilla, 5 Carmona Sevilla 41410",
    "addr:housenumber":"5",
    "addr:postcode":"41410",
    "addr:street":"Calle De Atarazanilla",
    "iso:country":"ES",
    "sg:address":"Calle de Atarazanilla, 5",
    "sg:city":"Carmona",
    "sg:orig_category":"Transportes Por V\u00cdas Navegables",
    "sg:phone":"+34 954 14 13 88",
    "sg:postcode":"41410",
    "sg:province":"Sevilla",
    "wof:name":"Casta\u00f1eda Fernandez Felix",
    "wof:placetype":"venue"
},
  "geometry": {"coordinates":[-5.6486740112,37.4693870544],"type":"Point"}
}