{
  "type": "Feature",
  "properties": {
    "iso:country":"ES",
    "sg:address":"Calle de Arturo Rubinstein, 8",
    "sg:city":"Marbella",
    "sg:orig_category":"Asociaciones Ecologistas",
    "sg:phone":"+34 952 82 75 31",
    "sg:postcode":"29600",
    "sg:province":"M\u00e1laga",
    "wof:name":"Comunidad Propietarios Gran Marbella",
    "wof:placetype":"venue"
},
  "geometry": {"coordinates":[-4.900015831,36.5081825256],"type":"Point"}
}