{
  "type": "Feature",
  "properties": {
    "addr:full":"Calle de Bosquecillo, 1 Velada Toledo 45612",
    "addr:housenumber":"1",
    "addr:postcode":"45612",
    "addr:street":"Calle De Bosquecillo",
    "iso:country":"ES",
    "sg:address":"Calle de Bosquecillo, 1",
    "sg:city":"Velada",
    "sg:orig_category":"Asilos De Ancianos. Centros Privados",
    "sg:phone":"+34 925 89 22 57",
    "sg:postcode":"45612",
    "sg:province":"Toledo",
    "wof:name":"Asesores Geriatricos De Castilla Y Leon S.l.",
    "wof:placetype":"venue"
},
  "geometry": {"coordinates":[-4.9758205414,39.9780464172],"type":"Point"}
}