{
  "type": "Feature",
  "properties": {
    "iso:country":"ES",
    "sg:address":"Avda Vincenti, 12",
    "sg:city":"Cangas",
    "sg:orig_category":"Centros De Coordinaci\u00d3n",
    "sg:phone":"+34 986 30 32 72",
    "sg:postcode":"36940",
    "sg:province":"Pontevedra",
    "wof:name":"Gescom Pontevedra S.l.l.",
    "wof:placetype":"venue"
},
  "geometry": {"coordinates":[-8.8184690475,42.2741928101],"type":"Point"}
}