{
  "type": "Feature",
  "properties": {
    "addr:full":"Cjon. Luna, S/n Villanueva Arzobispo Ja\u00e9n 23330",
    "addr:housenumber":"s",
    "addr:postcode":"23330",
    "addr:street":"Cjon. Luna;/ N;Arzobispo Jae\u0301N",
    "iso:country":"ES",
    "sg:address":"Cjon. Luna, S/n",
    "sg:city":"Villanueva Arzobispo",
    "sg:orig_category":"Caf\u00c9s, Bares, Cervecer\u00cdas",
    "sg:phone":"+34 953 45 31 76",
    "sg:postcode":"23330",
    "sg:province":"Ja\u00e9n",
    "wof:name":"Aparicio Calvo Yolanda",
    "wof:placetype":"venue"
},
  "geometry": {"coordinates":[-3.0096395016,38.1684303284],"type":"Point"}
}