{
  "type": "Feature",
  "properties": {
    "addr:full":"Calle de Collado, S/n Monroyo Teruel 44652",
    "addr:housenumber":"s / n",
    "addr:postcode":"44652",
    "addr:street":"Calle De Collado",
    "iso:country":"ES",
    "sg:address":"Calle de Collado, S/n",
    "sg:city":"Monroyo",
    "sg:orig_category":"Cajas De Ahorro",
    "sg:phone":"+34 978 85 62 86",
    "sg:postcode":"44652",
    "sg:province":"Teruel",
    "wof:name":"Caja De Ahorros Y Monte De Piedad De Zaragoza Aragon Y Rioja",
    "wof:placetype":"venue"
},
  "geometry": {"coordinates":[-0.0342275985,40.7876815796],"type":"Point"}
}