{
  "type": "Feature",
  "properties": {
    "addr:full":"Cmno Vereda Del Reino, 46 Beniel Murcia 30130",
    "addr:housenumber":"46",
    "addr:postcode":"30130",
    "addr:street":"Cmno Vereda Del Reino",
    "iso:country":"ES",
    "sg:address":"Cmno Vereda Del Reino, 46",
    "sg:city":"Beniel",
    "sg:orig_category":"Revestimiento De Suelos Industriales",
    "sg:phone":"+34 968 60 04 34",
    "sg:postcode":"30130",
    "sg:province":"Murcia",
    "wof:name":"Valero Sanchez Jose Joaquin",
    "wof:placetype":"venue"
},
  "geometry": {"coordinates":[-1.0019739866,38.045753479],"type":"Point"}
}