{
  "type": "Feature",
  "properties": {
    "iso:country":"ES",
    "sg:address":"Vidangoz, 5",
    "sg:city":"Iru\u00f1a",
    "sg:orig_category":"Ense\u00d1anza Variada",
    "sg:phone":"+34 948 38 44 48",
    "sg:postcode":"31014",
    "sg:province":"Navarra",
    "wof:name":"Coopropietarios Calle Vidangoz 5",
    "wof:placetype":"venue"
},
  "geometry": {"coordinates":[-1.6471250057,42.8282432556],"type":"Point"}
}