{
  "type": "Feature",
  "properties": {
    "addr:full":"Poife, 9 Ferreries Islas Baleares 07750",
    "addr:housenumber":"9",
    "addr:postcode":"07750",
    "addr:street":"Poife",
    "iso:country":"ES",
    "sg:address":"Poife, 9",
    "sg:city":"Ferreries",
    "sg:orig_category":"Empresas De Carpinter\u00cda De Madera",
    "sg:phone":"+34 971 37 30 15",
    "sg:postcode":"07750",
    "sg:province":"Islas Baleares",
    "wof:name":"Fusteria Sa Garlopa S.l.",
    "wof:placetype":"venue"
},
  "geometry": {"coordinates":[4.0079188347,39.9823875427],"type":"Point"}
}