{
  "type": "Feature",
  "properties": {
    "iso:country":"ES",
    "sg:address":"Plaz Tenerias, 8",
    "sg:city":"Valladolid",
    "sg:orig_category":"Inmobiliaria (agencias)",
    "sg:phone":"+34 983 37 31 82",
    "sg:postcode":"47006",
    "sg:province":"Valladolid",
    "wof:name":"Pardo Conde Luis Adolfo",
    "wof:placetype":"venue"
},
  "geometry": {"coordinates":[-4.7334518433,41.648021698],"type":"Point"}
}