{
  "type": "Feature",
  "properties": {
    "iso:country":"ES",
    "sg:address":"Calle de Echegaray, 4",
    "sg:city":"Madrid",
    "sg:orig_category":"Inmobiliaria (agencias)",
    "sg:phone":"+34 914 29 88 11",
    "sg:postcode":"28014",
    "sg:province":"Madrid",
    "wof:name":"Pefer Inmobiliaria S.a",
    "wof:placetype":"venue"
},
  "geometry": {"coordinates":[-3.699631691,40.4163665771],"type":"Point"}
}