{
  "type": "Feature",
  "properties": {
    "addr:full":"Calle de Progreso, 88 Rua De Valdeorras Ourense 32350",
    "addr:housenumber":"88",
    "addr:postcode":"32350",
    "addr:street":"Calle De Progreso;Rua De",
    "iso:country":"ES",
    "sg:address":"Calle de Progreso, 88",
    "sg:city":"Rua De Valdeorras",
    "sg:orig_category":"Droguer\u00cdas (al Por Menor)",
    "sg:phone":"+34 988 31 06 14",
    "sg:postcode":"32350",
    "sg:province":"Ourense",
    "wof:name":"Dieguez Escuredo Rogelio",
    "wof:placetype":"venue"
},
  "geometry": {"coordinates":[-7.1205739975,42.392490387],"type":"Point"}
}