{
  "type": "Feature",
  "properties": {
    "addr:full":"Czad Egia De, 9 Donostia-san Sebastian Guip\u00f9zcoa 20012",
    "addr:postcode":"20012",
    "iso:country":"ES",
    "sg:address":"Czad Egia De, 9",
    "sg:city":"Donostia-san Sebastian",
    "sg:orig_category":"Carnicer\u00cdas, Carnicer\u00cdas",
    "sg:phone":"+34 943 28 34 36",
    "sg:postcode":"20012",
    "sg:province":"Guip\u00f9zcoa",
    "wof:name":"Indo Roteta , Ignacio",
    "wof:placetype":"venue"
},
  "geometry": {"coordinates":[-1.9794000387,43.3173789978],"type":"Point"}
}