{
  "type": "Feature",
  "properties": {
    "addr:full":"Calle de San Miguel, 7 Panticosa Huesca 22661",
    "addr:housenumber":"7",
    "addr:postcode":"22661",
    "addr:street":"Calle De San Miguel",
    "iso:country":"ES",
    "sg:address":"Calle de San Miguel, 7",
    "sg:city":"Panticosa",
    "sg:orig_category":"Caf\u00c9s, Bares, Cervecer\u00cdas",
    "sg:phone":"+34 974 48 74 41",
    "sg:postcode":"22661",
    "sg:province":"Huesca",
    "wof:name":"Cafeteria O'tochal",
    "wof:placetype":"venue"
},
  "geometry": {"coordinates":[-0.2850880027,42.7237815857],"type":"Point"}
}