{
  "type": "Feature",
  "properties": {
    "addr:full":"Calle de Martin Cortes, 23 Zaragoza Zaragoza 50005",
    "addr:housenumber":"23",
    "addr:postcode":"50005",
    "addr:street":"Calle De Martin Cortes",
    "iso:country":"ES",
    "sg:address":"Calle de Martin Cortes, 23",
    "sg:city":"Zaragoza",
    "sg:orig_category":"Frutas, Legumbres Frescas Y Tempranas (al Por Menor)",
    "sg:phone":"+34 976 56 28 30",
    "sg:postcode":"50005",
    "sg:province":"Zaragoza",
    "wof:name":"Sanchez Gonzalo Oscar",
    "wof:placetype":"venue"
},
  "geometry": {"coordinates":[-0.8994320035,41.6486091614],"type":"Point"}
}