{
  "type": "Feature",
  "properties": {
    "addr:full":"Ctra Salteras-olivares, 1 Salteras Sevilla 41909",
    "addr:housenumber":"1",
    "addr:postcode":"41909",
    "addr:street":"Ctra Salteras-Olivares",
    "iso:country":"ES",
    "sg:address":"Ctra Salteras-olivares, 1",
    "sg:city":"Salteras",
    "sg:orig_category":"Artes Gr\u00c1ficas, Artes Pl\u00c1sticas (curso)",
    "sg:phone":"+34 955 70 77 67",
    "sg:postcode":"41909",
    "sg:province":"Sevilla",
    "wof:name":"Graficas Virgen De La Oliva S.l.",
    "wof:placetype":"venue"
},
  "geometry": {"coordinates":[-6.1071691513,37.4179992676],"type":"Point"}
}