{
  "type": "Feature",
  "properties": {
    "addr:full":"Calle de Eria Del Hospital, 15 Pola De Siero Asturias 33510",
    "addr:housenumber":"15",
    "addr:postcode":"33510",
    "addr:street":"Calle De Eria Del Hospital",
    "iso:country":"ES",
    "sg:address":"Calle de Eria Del Hospital, 15",
    "sg:city":"Pola De Siero",
    "sg:orig_category":"Quincaller\u00cda (al Por Menor)",
    "sg:phone":"+34 985 72 44 77",
    "sg:postcode":"33510",
    "sg:province":"Asturias",
    "wof:name":"Ferreteria Piquero S.l.",
    "wof:placetype":"venue"
},
  "geometry": {"coordinates":[-5.6607718468,43.3928604126],"type":"Point"}
}