{
  "type": "Feature",
  "properties": {
    "iso:country":"ES",
    "sg:address":"Calle de Rosa De Caleya, 53",
    "sg:city":"Taco",
    "sg:orig_category":"Importaci\u00d3n",
    "sg:phone":"+34 922 62 31 84",
    "sg:postcode":"38108",
    "sg:province":"Santa Cruz De Tenerife",
    "wof:name":"Silencars Canarias S.l.",
    "wof:placetype":"venue"
},
  "geometry": {"coordinates":[-16.3008384705,28.4486904144],"type":"Point"}
}