{
  "type": "Feature",
  "properties": {
    "addr:full":"Pl Vella, 14 Terrassa Barcelona 08221",
    "addr:housenumber":"14",
    "addr:postcode":"08221",
    "addr:street":"Vella",
    "iso:country":"ES",
    "sg:address":"Pl Vella, 14",
    "sg:city":"Terrassa",
    "sg:orig_category":"Inmobiliaria (agencias)",
    "sg:phone":"+34 937 33 23 23",
    "sg:postcode":"08221",
    "sg:province":"Barcelona",
    "wof:name":"Metrocasa S.l.",
    "wof:placetype":"venue"
},
  "geometry": {"coordinates":[2.0114219189,41.5619049072],"type":"Point"}
}