{
  "type": "Feature",
  "properties": {
    "iso:country":"ES",
    "sg:address":"Carrer de President Lluis Companys, 7",
    "sg:city":"S. Hipolit Voltrega",
    "sg:orig_category":"Cuchiller\u00cda (al Por Menor)",
    "sg:phone":"+34 938 57 13 57",
    "sg:postcode":"08512",
    "sg:province":"Barcelona",
    "wof:name":"Molist Munta\u00f1a Eudaldo",
    "wof:placetype":"venue"
},
  "geometry": {"coordinates":[2.2398729324,42.0147476196],"type":"Point"}
}