{
  "type": "Feature",
  "properties": {
    "addr:full":"Calle de Posadillas, 12 S. Esteban Gormaz Soria 42330",
    "addr:housenumber":"12",
    "addr:postcode":"42330",
    "addr:street":"Calle De Posadillas;S. Esteban Gormaz",
    "iso:country":"ES",
    "sg:address":"Calle de Posadillas, 12",
    "sg:city":"S. Esteban Gormaz",
    "sg:orig_category":"Abogados",
    "sg:phone":"+34 975 35 09 00",
    "sg:postcode":"42330",
    "sg:province":"Soria",
    "wof:name":"Alonso Aguilera Juan",
    "wof:placetype":"venue"
},
  "geometry": {"coordinates":[-3.2037680149,41.5737113953],"type":"Point"}
}