{
  "type": "Feature",
  "properties": {
    "iso:country":"ES",
    "sg:address":"Calle de Murcia, 37",
    "sg:city":"Rambla",
    "sg:classifiers":[
        {
            "category":"Taxi",
            "type":"Transportation"
        }
    ],
    "sg:phone":"+34 957 68 42 21",
    "sg:postcode":"14540",
    "sg:province":"C\u00f3rdoba",
    "wof:name":"Raigon Garcia Miguel",
    "wof:placetype":"venue"
},
  "geometry": {"coordinates":[-4.7411131859,37.6042518616],"type":"Point"}
}