{
  "type": "Feature",
  "properties": {
    "iso:country":"ES",
    "sg:address":"Calle de Mina (la), 12",
    "sg:city":"Dos Hermanas",
    "sg:orig_category":"Estilistas Y Estudios De Estilo De Corte Y Confecci\u00d3n",
    "sg:phone":"+34 954 72 16 59",
    "sg:postcode":"41700",
    "sg:province":"Sevilla",
    "wof:name":"Valle Prieto Miguel Angel",
    "wof:placetype":"venue"
},
  "geometry": {"coordinates":[-5.9214348793,37.2826309204],"type":"Point"}
}