{
  "type": "Feature",
  "properties": {
    "iso:country":"ES",
    "sg:address":"Calle de San Luis Gonzaga, 4",
    "sg:city":"Alaquas",
    "sg:orig_category":"Electrodom\u00c9sticos (al Por Menor)",
    "sg:phone":"+34 961 50 00 48",
    "sg:postcode":"46970",
    "sg:province":"Valencia",
    "wof:name":"Martinez Lazaro Victoriano",
    "wof:placetype":"venue"
},
  "geometry": {"coordinates":[-0.4649490118,39.4571762085],"type":"Point"}
}