{
  "type": "Feature",
  "properties": {
    "iso:country":"ES",
    "sg:address":"Ctra Alicante, Km. 0006,5",
    "sg:city":"Elche",
    "sg:orig_category":"Fabricaci\u00d3n Y Venta De Volquetes Y Remolques",
    "sg:phone":"+34 965 42 45 05",
    "sg:postcode":"03202",
    "sg:province":"Alicante",
    "wof:name":"Pleguin Metal S.l.",
    "wof:placetype":"venue"
},
  "geometry": {"coordinates":[-0.672706008,38.2721786499],"type":"Point"}
}