{
  "type": "Feature",
  "properties": {
    "iso:country":"ES",
    "sg:address":"Plaz Espa\u00d1a, 7",
    "sg:city":"Gines",
    "sg:orig_category":"Iglesia Cat\u00d3lica",
    "sg:phone":"+34 954 71 42 22",
    "sg:postcode":"41960",
    "sg:province":"Sevilla",
    "wof:name":"Parroquia Nuestra Se\u00f1ora De Belen",
    "wof:placetype":"venue"
},
  "geometry": {"coordinates":[-6.0781011581,37.3872718811],"type":"Point"}
}