{
  "type": "Feature",
  "properties": {
    "iso:country":"ES",
    "sg:address":"Estd Catabois, 245",
    "sg:city":"Ferrol",
    "sg:orig_category":"Quincaller\u00cda (al Por Menor)",
    "sg:phone":"+34 981 32 78 54",
    "sg:postcode":"15405",
    "sg:province":"La Coru\u00f1a",
    "wof:name":"Galtelcom",
    "wof:placetype":"venue"
},
  "geometry": {"coordinates":[-8.2299976349,43.4968910217],"type":"Point"}
}