{
  "type": "Feature",
  "properties": {
    "addr:full":"Calle de Juan Rejon, 127 Palmas De Gran Canaria Las Palmas 35008",
    "addr:housenumber":"127",
    "addr:postcode":"35008",
    "addr:street":"Calle De Juan Rejon",
    "iso:country":"ES",
    "sg:address":"Calle de Juan Rejon, 127",
    "sg:city":"Palmas De Gran Canaria",
    "sg:orig_category":"Fabricaci\u00d3n De Motores El\u00c9ctricos",
    "sg:phone":"+34 928 46 37 27",
    "sg:postcode":"35008",
    "sg:province":"Las Palmas",
    "wof:name":"Comercial Naval Canaria S.l.",
    "wof:placetype":"venue"
},
  "geometry": {"coordinates":[-15.4195947647,28.1501598358],"type":"Point"}
}