{
  "type": "Feature",
  "properties": {
    "iso:country":"ES",
    "sg:address":"Calle de San Francisco, 34",
    "sg:city":"Donostia-san Sebastian",
    "sg:orig_category":"Librer\u00cdas",
    "sg:phone":"+34 943 28 52 32",
    "sg:postcode":"20002",
    "sg:province":"Guip\u00f9zcoa",
    "wof:name":"Colina Manso Maria Angeles",
    "wof:placetype":"venue"
},
  "geometry": {"coordinates":[-1.9726649523,43.324508667],"type":"Point"}
}