{
  "type": "Feature",
  "properties": {
    "iso:country":"ES",
    "sg:address":"Calle de Mayor, 61",
    "sg:city":"Monreal Campo",
    "sg:orig_category":"Reposter\u00cdas",
    "sg:phone":"+34 978 86 40 50",
    "sg:postcode":"44300",
    "sg:province":"Teruel",
    "wof:name":"Panaderia Lorente Sanz Cdad.",
    "wof:placetype":"venue"
},
  "geometry": {"coordinates":[-1.3545110226,40.7867965698],"type":"Point"}
}