{
  "type": "Feature",
  "properties": {
    "addr:full":"Carrer de Mayor, 22 Guardamar Segura Alicante 03140",
    "addr:housenumber":"22",
    "addr:postcode":"03140",
    "addr:street":"Carrer De Mayor",
    "iso:country":"ES",
    "sg:address":"Carrer de Mayor, 22",
    "sg:city":"Guardamar Segura",
    "sg:orig_category":"Papeler\u00cdas, Librer\u00cdas",
    "sg:phone":"+34 965 72 86 15",
    "sg:postcode":"03140",
    "sg:province":"Alicante",
    "wof:name":"Valero Espinosa Maria Teresa",
    "wof:placetype":"venue"
},
  "geometry": {"coordinates":[-0.6540290117,38.086681366],"type":"Point"}
}