{
  "type": "Feature",
  "properties": {
    "iso:country":"ES",
    "sg:address":"Avda Castilla La Mancha, 3",
    "sg:city":"Illescas",
    "sg:orig_category":"Importaci\u00d3n",
    "sg:phone":"+34 925 51 37 39",
    "sg:postcode":"45200",
    "sg:province":"Toledo",
    "wof:name":"Esmer Import S.l.",
    "wof:placetype":"venue"
},
  "geometry": {"coordinates":[-3.8444130421,40.1289672852],"type":"Point"}
}