{
  "type": "Feature",
  "properties": {
    "addr:full":"Calle de Juan Talero, 1 Arjona Ja\u00e9n 23760",
    "addr:housenumber":"1",
    "addr:postcode":"23760",
    "addr:street":"Calle De Juan Talero;Jae\u0301N",
    "iso:country":"ES",
    "sg:address":"Calle de Juan Talero, 1",
    "sg:city":"Arjona",
    "sg:orig_category":"Perfumer\u00cda, Art\u00cdculos De Ba\u00d1o (fabricaci\u00d3n, Al Por Mayor)",
    "sg:phone":"+34 953 51 88 43",
    "sg:postcode":"23760",
    "sg:province":"Ja\u00e9n",
    "wof:name":"Distribuciones Cubero Paradelo S.l.l.",
    "wof:placetype":"venue"
},
  "geometry": {"coordinates":[-4.0597839355,37.9378128052],"type":"Point"}
}