{
  "type": "Feature",
  "properties": {
    "addr:full":"Calle de Campomanes, 20 Oviedo Asturias 33008",
    "addr:housenumber":"20",
    "addr:postcode":"33008",
    "addr:street":"Calle De Campomanes",
    "iso:country":"ES",
    "sg:address":"Calle de Campomanes, 20",
    "sg:city":"Oviedo",
    "sg:orig_category":"Asesor\u00cda Fiscal Y Jur\u00cddica",
    "sg:phone":"+34 985 22 10 58",
    "sg:postcode":"33008",
    "sg:province":"Asturias",
    "wof:name":"Viena Asesores S.l.",
    "wof:placetype":"venue"
},
  "geometry": {"coordinates":[-5.8465809822,43.3580818176],"type":"Point"}
}