{
  "type": "Feature",
  "properties": {
    "addr:full":"Rua Mondariz, 39 Vigo Pontevedra 36209",
    "addr:housenumber":"39",
    "addr:postcode":"36209",
    "addr:street":"Rua Mondariz",
    "iso:country":"ES",
    "sg:address":"Rua Mondariz, 39",
    "sg:city":"Vigo",
    "sg:orig_category":"Pescader\u00cdas (al Por Menor)",
    "sg:phone":"+34 986 20 19 09",
    "sg:postcode":"36209",
    "sg:province":"Pontevedra",
    "wof:name":"Gonzalez Mera Maria Dolores",
    "wof:placetype":"venue"
},
  "geometry": {"coordinates":[-8.7472686768,42.2168998718],"type":"Point"}
}