{
  "type": "Feature",
  "properties": {
    "addr:full":"Calle de Donoso Cortes, 83 Azuaga Badajoz 06920",
    "addr:housenumber":"83",
    "addr:postcode":"06920",
    "addr:street":"Calle De Donoso Cortes",
    "iso:country":"ES",
    "sg:address":"Calle de Donoso Cortes, 83",
    "sg:city":"Azuaga",
    "sg:orig_category":"Arreglo, Reparaci\u00d3n, Piezas Sueltas De Televisi\u00d3n, V\u00cddeo, Hi",
    "sg:phone":"+34 924 89 00 08",
    "sg:postcode":"06920",
    "sg:province":"Badajoz",
    "wof:name":"Moyano Naranjo Modesto",
    "wof:placetype":"venue"
},
  "geometry": {"coordinates":[-5.6809124947,38.2638626099],"type":"Point"}
}