{
  "type": "Feature",
  "properties": {
    "addr:full":"Avda Tirajana (de), 10 Playa Del Ingles Las Palmas 35100",
    "addr:housenumber":"10",
    "addr:postcode":"35100",
    "addr:street":"Avda Tirajana De",
    "iso:country":"ES",
    "sg:address":"Avda Tirajana (de), 10",
    "sg:city":"Playa Del Ingles",
    "sg:orig_category":"M\u00c1rmoles, Granitos Y Piedras Naturales",
    "sg:phone":"+34 928 76 60 33",
    "sg:postcode":"35100",
    "sg:province":"Las Palmas",
    "wof:name":"Saneamientos Noroeste S.l.",
    "wof:placetype":"venue"
},
  "geometry": {"coordinates":[-15.5756196976,27.759519577],"type":"Point"}
}