{
  "type": "Feature",
  "properties": {
    "iso:country":"ES",
    "sg:address":"Desierto De Las Palmas, 1",
    "sg:city":"Desierto De Las Palmas",
    "sg:orig_category":"Empresarios",
    "sg:phone":"+34 964 30 10 10",
    "sg:postcode":"12560",
    "sg:province":"Castell\u00f3n",
    "wof:name":"Miguel Asin S.l.",
    "wof:placetype":"venue"
},
  "geometry": {"coordinates":[-0.0360242017,39.9860687256],"type":"Point"}
}