{
  "type": "Feature",
  "properties": {
    "iso:country":"ES",
    "sg:address":"Can Manyoles, 1",
    "sg:city":"Alaro",
    "sg:orig_category":"Promotores Constructores",
    "sg:phone":"+34 971 51 85 73",
    "sg:postcode":"07340",
    "sg:province":"Islas Baleares",
    "wof:name":"Hijos De Pedro Jimenez S.l.",
    "wof:placetype":"venue"
},
  "geometry": {"coordinates":[2.7906699181,39.706829071],"type":"Point"}
}