{
  "type": "Feature",
  "properties": {
    "iso:country":"ES",
    "sg:address":"Carrer de Metge Carreras, 80",
    "sg:city":"Olesa Montserrat",
    "sg:orig_category":"Asociaciones Y Clubs Deportivos",
    "sg:phone":"+34 937 78 31 82",
    "sg:postcode":"08640",
    "sg:province":"Barcelona",
    "wof:name":"Gimsal Centre Esports S.l.",
    "wof:placetype":"venue"
},
  "geometry": {"coordinates":[1.894340992,41.5407676697],"type":"Point"}
}