{
  "type": "Feature",
  "properties": {
    "iso:country":"ES",
    "sg:address":"Calle de Bristol, 14",
    "sg:city":"Madrid",
    "sg:orig_category":"M\u00c9dicos: Cirug\u00cda Ortop\u00c9dica Y Traumatolog\u00cda",
    "sg:phone":"+34 917 25 96 62",
    "sg:postcode":"28028",
    "sg:province":"Madrid",
    "wof:name":"Wang\u00fcemert De La Fuente Jose",
    "wof:placetype":"venue"
},
  "geometry": {"coordinates":[-3.6619300842,40.4408493042],"type":"Point"}
}