{
  "type": "Feature",
  "properties": {
    "iso:country":"ES",
    "sg:address":"Calle de Ciceron, 8",
    "sg:city":"Madrid",
    "sg:orig_category":"Puertas Autom\u00c1ticas, Puertas De Garaje",
    "sg:phone":"+34 915 53 54 02",
    "sg:postcode":"28020",
    "sg:province":"Madrid",
    "wof:name":"Teleacceso S.l.",
    "wof:placetype":"venue"
},
  "geometry": {"coordinates":[-3.7008619308,40.4475402832],"type":"Point"}
}