{
  "type": "Feature",
  "properties": {
    "addr:full":"Ctra Madrid, Km. 0300,0 Ba\u00d1eza Le\u00f3n 24750",
    "addr:postcode":"24750",
    "addr:street":"Ctra Madrid Km. 0300,0 Ban\u0303Eza Leo\u0301N",
    "iso:country":"ES",
    "sg:address":"Ctra Madrid, Km. 0300,0",
    "sg:city":"Ba\u00d1eza",
    "sg:orig_category":"Cr\u00cda De Animales",
    "sg:phone":"+34 987 65 57 21",
    "sg:postcode":"24750",
    "sg:province":"Le\u00f3n",
    "wof:name":"Maragata De Vacuno S.c.l",
    "wof:placetype":"venue"
},
  "geometry": {"coordinates":[-5.8960561752,42.304019928],"type":"Point"}
}