{
  "type": "Feature",
  "properties": {
    "addr:full":"Ctra. Militar, 185 Espillari Islas Baleares 07608",
    "addr:housenumber":"185",
    "addr:postcode":"07608",
    "addr:street":"Ctra. Militar;Islas",
    "iso:country":"ES",
    "sg:address":"Ctra. Militar, 185",
    "sg:city":"Espillari",
    "sg:orig_category":"Fabricaci\u00d3n De Equipos Y Piezas Para Veh\u00cdculos, Veh\u00cdculos Industriales",
    "sg:phone":"+34 971 26 81 11",
    "sg:postcode":"07608",
    "sg:province":"Islas Baleares",
    "wof:name":"Serviauto Arenal S.a.",
    "wof:placetype":"venue"
},
  "geometry": {"coordinates":[2.7556099892,39.5265617371],"type":"Point"}
}