{
  "type": "Feature",
  "properties": {
    "iso:country":"ES",
    "sg:address":"Calle de Berlin, 3",
    "sg:city":"Toledo",
    "sg:orig_category":"Farmacias",
    "sg:phone":"+34 925 22 19 98",
    "sg:postcode":"45005",
    "sg:province":"Toledo",
    "wof:name":"Garcia Rodriguez Maria Mercedes",
    "wof:placetype":"venue"
},
  "geometry": {"coordinates":[-4.0277876854,39.8732795715],"type":"Point"}
}