{
  "type": "Feature",
  "properties": {
    "addr:full":"Merilla, S/n Merilla Cantabria 39728",
    "addr:postcode":"39728",
    "addr:street":"Merilla S / N",
    "iso:country":"ES",
    "sg:address":"Merilla, S/n",
    "sg:city":"Merilla",
    "sg:orig_category":"Centros De Educaci\u00d3n Especial",
    "sg:phone":"+34 942 53 96 64",
    "sg:postcode":"39728",
    "sg:province":"Cantabria",
    "wof:name":"Centro Rural Agrupado De Miera",
    "wof:placetype":"venue"
},
  "geometry": {"coordinates":[-3.7020359039,43.2373046875],"type":"Point"}
}