{
  "type": "Feature",
  "properties": {
    "iso:country":"ES",
    "sg:address":"Carrer de Enric Delaris, 28",
    "sg:city":"Manlleu",
    "sg:orig_category":"Molduras, Junquillos, Listones Y Molduras Perforadas",
    "sg:phone":"+34 938 50 62 73",
    "sg:postcode":"08560",
    "sg:province":"Barcelona",
    "wof:name":"Ruiz Perea Julio",
    "wof:placetype":"venue"
},
  "geometry": {"coordinates":[2.283205986,41.9996986389],"type":"Point"}
}