{
  "type": "Feature",
  "properties": {
    "addr:full":"Mayor, 82 Monta\u00d1ana Zaragoza 50059",
    "addr:housenumber":"82",
    "addr:postcode":"50059",
    "addr:street":"Mayor",
    "iso:country":"ES",
    "sg:address":"Mayor, 82",
    "sg:city":"Monta\u00d1ana",
    "sg:orig_category":"Aguas (distribuci\u00d3n, Servicios)",
    "sg:phone":"+34 976 57 51 66",
    "sg:postcode":"50059",
    "sg:province":"Zaragoza",
    "wof:name":"Sindicato De Riegos De Termino Mamblas",
    "wof:placetype":"venue"
},
  "geometry": {"coordinates":[-0.8242189884,41.6850395203],"type":"Point"}
}