{
  "type": "Feature",
  "properties": {
    "iso:country":"ES",
    "sg:address":"Calle de Porto Cristo, 7",
    "sg:city":"Alcorcon",
    "sg:orig_category":"Panader\u00cdas, Panader\u00cdas",
    "sg:phone":"+34 916 10 78 76",
    "sg:postcode":"28924",
    "sg:province":"Madrid",
    "wof:name":"Garcia Garcia Victor",
    "wof:placetype":"venue"
},
  "geometry": {"coordinates":[-3.8181400299,40.3518409729],"type":"Point"}
}