{
  "type": "Feature",
  "properties": {
    "addr:full":"Calle de Comestibles, 8 Poligono Industrial Los Villares Salamanca 37184",
    "addr:housenumber":"8",
    "addr:postcode":"37184",
    "addr:street":"Calle De Comestibles;Poligono Industrial",
    "iso:country":"ES",
    "sg:address":"Calle de Comestibles, 8",
    "sg:city":"Poligono Industrial Los Villares",
    "sg:orig_category":"Negocio De Materiales De Construcci\u00d3n",
    "sg:phone":"+34 923 22 94 93",
    "sg:postcode":"37184",
    "sg:province":"Salamanca",
    "wof:name":"Ceramicas Y Construcciones La Corona De Los Villares S.l.",
    "wof:placetype":"venue"
},
  "geometry": {"coordinates":[-5.6476120949,41.0065116882],"type":"Point"}
}