{
  "type": "Feature",
  "properties": {
    "addr:full":"Pg Mare De Deu Del Coll, 75 Barcelona Barcelona 08023",
    "addr:housenumber":"75",
    "addr:postcode":"08023",
    "addr:street":"Pg Mare De Deu Del Coll",
    "iso:country":"ES",
    "sg:address":"Pg Mare De Deu Del Coll, 75",
    "sg:city":"Barcelona",
    "sg:classifiers":[
        {
            "category":"Autos & Motor Vehicles",
            "subcategory":"Automobile Sales",
            "type":"Retail Goods"
        }
    ],
    "sg:phone":"+34 932 10 85 52",
    "sg:postcode":"08023",
    "sg:province":"Barcelona",
    "wof:name":"Varona Villanueva Jose Maria",
    "wof:placetype":"venue"
},
  "geometry": {"coordinates":[2.1475880146,41.418094635],"type":"Point"}
}