{
  "type": "Feature",
  "properties": {
    "iso:country":"ES",
    "sg:address":"Carrer de Ignasi Barraquer, 17",
    "sg:city":"Palma",
    "sg:orig_category":"Cerrajer\u00cda, Ferrallista",
    "sg:phone":"+34 971 75 15 07",
    "sg:postcode":"07004",
    "sg:province":"Islas Baleares",
    "wof:name":"Jv Seguridad Palma S.l.",
    "wof:placetype":"venue"
},
  "geometry": {"coordinates":[2.6573779583,39.5910415649],"type":"Point"}
}