{
  "type": "Feature",
  "properties": {
    "addr:full":"Avda Luis Gonzalez Taboada, 53 Lalin Pontevedra 36500",
    "addr:housenumber":"53",
    "addr:postcode":"36500",
    "addr:street":"Avda Luis Gonzalez Taboada",
    "iso:country":"ES",
    "sg:address":"Avda Luis Gonzalez Taboada, 53",
    "sg:city":"Lalin",
    "sg:orig_category":"M\u00c9dicos: Pediatr\u00cda. Enfermedades De Los Ni\u00d1os",
    "sg:phone":"+34 986 78 48 47",
    "sg:postcode":"36500",
    "sg:province":"Pontevedra",
    "wof:name":"Vazquez Donsion Manuel",
    "wof:placetype":"venue"
},
  "geometry": {"coordinates":[-8.1112470627,42.6601676941],"type":"Point"}
}