{
  "type": "Feature",
  "properties": {
    "addr:full":"Calle de Maestro Guridi, 6 Castellon De La Plana Castell\u00f3n 12006",
    "addr:housenumber":"6",
    "addr:postcode":"12006",
    "addr:street":"Calle De Maestro Guridi",
    "iso:country":"ES",
    "sg:address":"Calle de Maestro Guridi, 6",
    "sg:city":"Castellon De La Plana",
    "sg:orig_category":"Sanatorios M\u00c9dico",
    "sg:phone":"+34 964 25 23 06",
    "sg:postcode":"12006",
    "sg:province":"Castell\u00f3n",
    "wof:name":"Generalitat Valenciana",
    "wof:placetype":"venue"
},
  "geometry": {"coordinates":[-0.1404139996,40.0213813782],"type":"Point"}
}