{
  "type": "Feature",
  "properties": {
    "addr:full":"Carrer de Berlines, 37 Barcelona Barcelona 08022",
    "addr:housenumber":"37",
    "addr:postcode":"08022",
    "addr:street":"Carrer De Berlines",
    "iso:country":"ES",
    "sg:address":"Carrer de Berlines, 37",
    "sg:city":"Barcelona",
    "sg:orig_category":"Inmobiliaria (agencias)",
    "sg:phone":"+34 932 54 04 42",
    "sg:postcode":"08022",
    "sg:province":"Barcelona",
    "wof:name":"Unoalcubo S.l.",
    "wof:placetype":"venue"
},
  "geometry": {"coordinates":[2.1378109455,41.404460907],"type":"Point"}
}