{
  "type": "Feature",
  "properties": {
    "iso:country":"ES",
    "sg:address":"Calle de Parque, 25",
    "sg:city":"Errenteria",
    "sg:orig_category":"Farmacias",
    "sg:phone":"+34 943 34 45 03",
    "sg:postcode":"20100",
    "sg:province":"Guip\u00f9zcoa",
    "wof:name":"Irigoyen Lasa Ana Eloisa",
    "wof:placetype":"venue"
},
  "geometry": {"coordinates":[-1.9081360102,43.3118553162],"type":"Point"}
}