{
  "type": "Feature",
  "properties": {
    "iso:country":"ES",
    "sg:address":"Carrer de Sant Joaquim, 123",
    "sg:city":"Santa Coloma De Gramenet",
    "sg:orig_category":"Ropa Para Beb\u00c9s Y Ni\u00d1os (confecci\u00d3n, Al Por Mayor)",
    "sg:phone":"+34 933 86 02 60",
    "sg:postcode":"08922",
    "sg:province":"Barcelona",
    "wof:name":"Comercial De Confecciones Romar S.l",
    "wof:placetype":"venue"
},
  "geometry": {"coordinates":[2.2077140808,41.4461288452],"type":"Point"}
}