{
  "type": "Feature",
  "properties": {
    "addr:full":"Calle de Ronda, 7 Aranda Duero Burgos 09400",
    "addr:housenumber":"7",
    "addr:postcode":"09400",
    "addr:street":"Calle De Ronda",
    "iso:country":"ES",
    "sg:address":"Calle de Ronda, 7",
    "sg:city":"Aranda Duero",
    "sg:orig_category":"\u00d3ptica: Instrumentos (fabricaci\u00d3n)",
    "sg:phone":"+34 947 51 03 49",
    "sg:postcode":"09400",
    "sg:province":"Burgos",
    "wof:name":"Frutos Herrero Edelmira",
    "wof:placetype":"venue"
},
  "geometry": {"coordinates":[-3.6889948845,41.6699256897],"type":"Point"}
}