{
  "type": "Feature",
  "properties": {
    "iso:country":"ES",
    "sg:address":"Carrer de Josep Torras I Bages, 5",
    "sg:city":"S. Boi Llobregat",
    "sg:orig_category":"Molduras, Junquillos, Listones Y Molduras Perforadas",
    "sg:phone":"+34 936 61 39 50",
    "sg:postcode":"08830",
    "sg:province":"Barcelona",
    "wof:name":"Prat Munarriz Jose Luis",
    "wof:placetype":"venue"
},
  "geometry": {"coordinates":[2.0433208942,41.3477668762],"type":"Point"}
}