{
  "type": "Feature",
  "properties": {
    "addr:full":"Ctra. Lorca-baza, Km. 0064,7 Cantoria Almer\u00eda 04850",
    "addr:housenumber":"cantoria",
    "addr:postcode":"04850",
    "addr:street":"Ctra. Lorca-Baza Km. 0064,7",
    "iso:country":"ES",
    "sg:address":"Ctra. Lorca-baza, Km. 0064,7",
    "sg:city":"Cantoria",
    "sg:orig_category":"Delegados, Agentes De Tr\u00c1nsito, Auxiliares De Transporte Internacional",
    "sg:phone":"+34 950 43 64 79",
    "sg:postcode":"04850",
    "sg:province":"Almer\u00eda",
    "wof:name":"Estela Trans S.l.",
    "wof:placetype":"venue"
},
  "geometry": {"coordinates":[-2.192759037,37.3531112671],"type":"Point"}
}