{
  "type": "Feature",
  "properties": {
    "iso:country":"ES",
    "sg:address":"Carrer de Topete, 106",
    "sg:city":"Terrassa",
    "sg:orig_category":"Herboristas (al Por Menor)",
    "sg:phone":"+34 937 31 51 38",
    "sg:postcode":"08221",
    "sg:province":"Barcelona",
    "wof:name":"Maga\u00f1a Guirado Luisa",
    "wof:placetype":"venue"
},
  "geometry": {"coordinates":[2.0172519684,41.559715271],"type":"Point"}
}