{
  "type": "Feature",
  "properties": {
    "addr:full":"Calle de Torre Del Aguila, 6 Utrera Sevilla 41710",
    "addr:housenumber":"6",
    "addr:postcode":"41710",
    "addr:street":"Calle De Torre Del Aguila",
    "iso:country":"ES",
    "sg:address":"Calle de Torre Del Aguila, 6",
    "sg:city":"Utrera",
    "sg:orig_category":"Construcciones Met\u00c1licas",
    "sg:phone":"+34 954 86 45 87",
    "sg:postcode":"41710",
    "sg:province":"Sevilla",
    "wof:name":"Talleres Mellizo S.l.",
    "wof:placetype":"venue"
},
  "geometry": {"coordinates":[-5.7814512253,37.1921272278],"type":"Point"}
}