{
  "type": "Feature",
  "properties": {
    "iso:country":"ES",
    "sg:address":"Cost Brossa, 3",
    "sg:city":"Palma",
    "sg:orig_category":"Ropa Para Ni\u00d1os (al Por Menor)",
    "sg:phone":"+34 971 71 46 45",
    "sg:postcode":"07001",
    "sg:province":"Islas Baleares",
    "wof:name":"Red Orange S.l.",
    "wof:placetype":"venue"
},
  "geometry": {"coordinates":[2.6493439674,39.5699577332],"type":"Point"}
}