{
  "type": "Feature",
  "properties": {
    "iso:country":"ES",
    "sg:address":"Pg Maritim, 267",
    "sg:city":"Castelldefels",
    "sg:orig_category":"Empresarios",
    "sg:phone":"+34 936 35 01 05",
    "sg:postcode":"08860",
    "sg:province":"Barcelona",
    "wof:name":"Alta Reforma Sl",
    "wof:placetype":"venue"
},
  "geometry": {"coordinates":[1.9645484686,41.2657737732],"type":"Point"}
}