{
  "type": "Feature",
  "properties": {
    "iso:country":"ES",
    "sg:address":"Calle de Eguia General, 16",
    "sg:city":"Bilbao",
    "sg:orig_category":"Arquitectos",
    "sg:phone":"+34 944 21 26 48",
    "sg:postcode":"48010",
    "sg:province":"Vizcaya",
    "wof:name":"Echavarri De Miguel Juan Andres",
    "wof:placetype":"venue"
},
  "geometry": {"coordinates":[-2.943187952,43.2586593628],"type":"Point"}
}