{
  "type": "Feature",
  "properties": {
    "addr:full":"Barr Azurleku, 19 Bilbao Vizcaya 48004",
    "addr:housenumber":"19",
    "addr:postcode":"48004",
    "addr:street":"Azurleku",
    "iso:country":"ES",
    "sg:address":"Barr Azurleku, 19",
    "sg:city":"Bilbao",
    "sg:orig_category":"Trabajos De Soldaduras",
    "sg:phone":"+34 944 73 01 94",
    "sg:postcode":"48004",
    "sg:province":"Vizcaya",
    "wof:name":"Neira Vidal Manuel",
    "wof:placetype":"venue"
},
  "geometry": {"coordinates":[-2.9101750851,43.25],"type":"Point"}
}