{
  "type": "Feature",
  "properties": {
    "addr:full":"Urb Nuevo Alamin, S/n Guadalajara Guadalajara 19005",
    "addr:housenumber":"s",
    "addr:postcode":"19005",
    "addr:street":"Urb;Alamin;/ N",
    "iso:country":"ES",
    "sg:address":"Urb Nuevo Alamin, S/n",
    "sg:city":"Guadalajara",
    "sg:orig_category":"Centros De Educaci\u00d3n Especial",
    "sg:phone":"+34 949 23 17 51",
    "sg:postcode":"19005",
    "sg:province":"Guadalajara",
    "wof:name":"Colegio Publico Rio Henares",
    "wof:placetype":"venue"
},
  "geometry": {"coordinates":[-3.159555912,40.6370239258],"type":"Point"}
}