{
  "type": "Feature",
  "properties": {
    "addr:full":"Cami Ca La Madrona (de), 24 Mataro Barcelona 08304",
    "addr:postcode":"08304",
    "addr:street":"Ca La;De 24 Mataro Barcelona",
    "iso:country":"ES",
    "sg:address":"Cami Ca La Madrona (de), 24",
    "sg:city":"Mataro",
    "sg:orig_category":"Fabricaci\u00d3n De Su\u00c9ters Y Chalecos De Punto",
    "sg:phone":"+34 937 90 82 47",
    "sg:postcode":"08304",
    "sg:province":"Barcelona",
    "wof:name":"Marini Monta\u00f1a Juan",
    "wof:placetype":"venue"
},
  "geometry": {"coordinates":[2.4539210796,41.5542297363],"type":"Point"}
}