{
  "type": "Feature",
  "properties": {
    "addr:full":"Calle de Penelope, 5 Madrid Madrid 28042",
    "addr:housenumber":"5",
    "addr:postcode":"28042",
    "addr:street":"Calle De Penelope",
    "iso:country":"ES",
    "sg:address":"Calle de Penelope, 5",
    "sg:city":"Madrid",
    "sg:orig_category":"Electricidad: Equipos Industriales, Componentes (fabricaci\u00d3n)",
    "sg:phone":"+34 913 01 00 35",
    "sg:postcode":"28042",
    "sg:province":"Madrid",
    "wof:name":"Tecnosistemas Estructurales S.l.",
    "wof:placetype":"venue"
},
  "geometry": {"coordinates":[-3.5793509483,40.4754219055],"type":"Point"}
}