{
  "type": "Feature",
  "properties": {
    "addr:full":"Carrer de Jaume Ii, 33 Palma Islas Baleares 07001",
    "addr:housenumber":"33",
    "addr:postcode":"07001",
    "addr:street":"Carrer De Jaume Ii",
    "iso:country":"ES",
    "sg:address":"Carrer de Jaume Ii, 33",
    "sg:city":"Palma",
    "sg:orig_category":"Ropa Para Se\u00d1oras (al Por Menor)",
    "sg:phone":"+34 971 22 86 09",
    "sg:postcode":"07001",
    "sg:province":"Islas Baleares",
    "wof:name":"La Tienda De Lolin S. L.",
    "wof:placetype":"venue"
},
  "geometry": {"coordinates":[2.6511130333,39.570766449],"type":"Point"}
}