{
  "type": "Feature",
  "properties": {
    "iso:country":"ES",
    "sg:address":"Calle de Carlos Martin Alvarez, 57",
    "sg:city":"Madrid",
    "sg:orig_category":"Cl\u00cdnicas Dentales",
    "sg:phone":"+34 914 78 47 64",
    "sg:postcode":"28018",
    "sg:province":"Madrid",
    "wof:name":"Obando Y Fonseca Asociados S.l.",
    "wof:placetype":"venue"
},
  "geometry": {"coordinates":[-3.6654663086,40.3868904114],"type":"Point"}
}