{
  "type": "Feature",
  "properties": {
    "iso:country":"ES",
    "sg:address":"Disseminat, 2",
    "sg:city":"Teia",
    "sg:orig_category":"Florister\u00cdas",
    "sg:phone":"+34 933 97 12 53",
    "sg:postcode":"08329",
    "sg:province":"Barcelona",
    "wof:name":"Mosimoll S. A.",
    "wof:placetype":"venue"
},
  "geometry": {"coordinates":[2.3216049671,41.4981689453],"type":"Point"}
}