{
  "type": "Feature",
  "properties": {
    "addr:full":"Calle de Rabal (el), 31 Hellin Albacete 02400",
    "addr:housenumber":"31",
    "addr:postcode":"02400",
    "addr:street":"Calle De Rabal El",
    "iso:country":"ES",
    "sg:address":"Calle de Rabal (el), 31",
    "sg:city":"Hellin",
    "sg:orig_category":"Ropa Para Se\u00d1oras Y Caballeros (al Por Menor)",
    "sg:phone":"+34 967 30 71 14",
    "sg:postcode":"02400",
    "sg:province":"Albacete",
    "wof:name":"Fernandez Lopez Francisco",
    "wof:placetype":"venue"
},
  "geometry": {"coordinates":[-1.7013390064,38.5131072998],"type":"Point"}
}