{
  "type": "Feature",
  "properties": {
    "iso:country":"ES",
    "sg:address":"Ptda Sant Antoni, S/n",
    "sg:city":"Oliva",
    "sg:orig_category":"Fabricaci\u00d3n De Pastas Alimentarias",
    "sg:phone":"+34 962 96 32 47",
    "sg:postcode":"46780",
    "sg:province":"Valencia",
    "wof:name":"Falgas Soler Evaristo",
    "wof:placetype":"venue"
},
  "geometry": {"coordinates":[-0.1247489974,38.9110946655],"type":"Point"}
}