{
  "type": "Feature",
  "properties": {
    "iso:country":"ES",
    "sg:address":"Calle de Obispo Miranda, 7",
    "sg:city":"Tamarite Litera",
    "sg:orig_category":"Producci\u00d3n, Distribuci\u00d3n De Electricidad",
    "sg:phone":"+34 974 42 02 77",
    "sg:postcode":"22550",
    "sg:province":"Huesca",
    "wof:name":"Meler Gascon Joaquin",
    "wof:placetype":"venue"
},
  "geometry": {"coordinates":[0.4211759865,41.8694801331],"type":"Point"}
}