{
  "type": "Feature",
  "properties": {
    "iso:country":"ES",
    "sg:address":"Plaz Mayor, 13",
    "sg:city":"Elda",
    "sg:orig_category":"Papeler\u00cdas, Librer\u00cdas",
    "sg:phone":"+34 965 38 05 75",
    "sg:postcode":"03600",
    "sg:province":"Alicante",
    "wof:name":"Verdejo Rubio S.l.",
    "wof:placetype":"venue"
},
  "geometry": {"coordinates":[-0.7941610217,38.478351593],"type":"Point"}
}