{
  "type": "Feature",
  "properties": {
    "iso:country":"ES",
    "sg:address":"Carrer de Muntaner, 143",
    "sg:city":"Barcelona",
    "sg:orig_category":"Molduras, Junquillos, Listones Y Molduras Perforadas",
    "sg:phone":"+34 934 51 89 01",
    "sg:postcode":"08036",
    "sg:province":"Barcelona",
    "wof:name":"Wang  Zhehui",
    "wof:placetype":"venue"
},
  "geometry": {"coordinates":[2.1541597843,41.3905754089],"type":"Point"}
}