{
  "type": "Feature",
  "properties": {
    "iso:country":"ES",
    "sg:address":"Av Mare De Deu De Montserrat, 41",
    "sg:city":"S. Joan Despi",
    "sg:orig_category":"Confecci\u00d3n De Trajes Para Se\u00d1oras",
    "sg:phone":"+34 933 73 67 62",
    "sg:postcode":"08970",
    "sg:province":"Barcelona",
    "wof:name":"Confecciones Rams S. A.",
    "wof:placetype":"venue"
},
  "geometry": {"coordinates":[2.0652120113,41.3704986572],"type":"Point"}
}