{
  "type": "Feature",
  "properties": {
    "iso:country":"ES",
    "sg:address":"Calle de Uria, 72",
    "sg:city":"Oviedo",
    "sg:orig_category":"M\u00c9dicos: Medicina Interna",
    "sg:phone":"+34 985 22 33 45",
    "sg:postcode":"33003",
    "sg:province":"Asturias",
    "wof:name":"Figueroa Fabregas Edgardo Javier",
    "wof:placetype":"venue"
},
  "geometry": {"coordinates":[-5.8526887894,43.3649597168],"type":"Point"}
}