{
  "type": "Feature",
  "properties": {
    "addr:full":"Calle de Arenal, S/n S. Vicente Barquera Cantabria 39540",
    "addr:housenumber":"s",
    "addr:postcode":"39540",
    "addr:street":"Calle De Arenal;/ N S. Vicente",
    "iso:country":"ES",
    "sg:address":"Calle de Arenal, S/n",
    "sg:city":"S. Vicente Barquera",
    "sg:classifiers":[
        {
            "category":"Autos & Motor Vehicles",
            "subcategory":"Automobile Sales",
            "type":"Retail Goods"
        }
    ],
    "sg:phone":"+34 942 71 07 24",
    "sg:postcode":"39540",
    "sg:province":"Cantabria",
    "wof:name":"Saavedra Sanchez Felipe",
    "wof:placetype":"venue"
},
  "geometry": {"coordinates":[-4.3993735313,43.3827552795],"type":"Point"}
}