{
  "type": "Feature",
  "properties": {
    "iso:country":"ES",
    "sg:address":"Calle de Veinte De Febrero, 6",
    "sg:city":"Valladolid",
    "sg:orig_category":"Electrodom\u00c9sticos (al Por Menor)",
    "sg:phone":"+34 983 34 25 89",
    "sg:postcode":"47001",
    "sg:province":"Valladolid",
    "wof:name":"Hermanos Dominguez Sanchez C.b.",
    "wof:placetype":"venue"
},
  "geometry": {"coordinates":[-4.731883049,41.6503639221],"type":"Point"}
}