{
  "type": "Feature",
  "properties": {
    "addr:full":"Calle de Jose Miguel Barandiaran, 6 Santurtzi Vizcaya 48980",
    "addr:housenumber":"6",
    "addr:postcode":"48980",
    "addr:street":"Calle De Jose Miguel Barandiaran",
    "iso:country":"ES",
    "sg:address":"Calle de Jose Miguel Barandiaran, 6",
    "sg:city":"Santurtzi",
    "sg:orig_category":"Complementos De Vestir (al Por Menor)",
    "sg:phone":"+34 944 93 77 13",
    "sg:postcode":"48980",
    "sg:province":"Vizcaya",
    "wof:name":"Dounis Orihuela Niki",
    "wof:placetype":"venue"
},
  "geometry": {"coordinates":[-3.0331659317,43.3283996582],"type":"Point"}
}