{
  "type": "Feature",
  "properties": {
    "iso:country":"ES",
    "sg:address":"Plaz San Manuel, S/n",
    "sg:city":"Beires",
    "sg:orig_category":"Administraciones Regionales, Departamentales Y Locales",
    "sg:phone":"+34 950 51 00 34",
    "sg:postcode":"04458",
    "sg:province":"Almer\u00eda",
    "wof:name":"Ayuntamiento De Beires",
    "wof:placetype":"venue"
},
  "geometry": {"coordinates":[-2.7909276485,37.0120010376],"type":"Point"}
}