{
  "type": "Feature",
  "properties": {
    "addr:full":"Calle de Gutierre De Cetina, 11 Madrid Madrid 28017",
    "addr:housenumber":"11",
    "addr:postcode":"madrid;28017",
    "addr:street":"Calle De Gutierre De Cetina",
    "iso:country":"ES",
    "sg:address":"Calle de Gutierre De Cetina, 11",
    "sg:city":"Madrid",
    "sg:orig_category":"Ropa De Trabajo Y Profesionales (al Por Menor)",
    "sg:phone":"+34 913 68 13 71",
    "sg:postcode":"28017",
    "sg:province":"Madrid",
    "wof:name":"Tejero Peromingo Juan",
    "wof:placetype":"venue"
},
  "geometry": {"coordinates":[-3.6442770958,40.4340934753],"type":"Point"}
}