{
  "type": "Feature",
  "properties": {
    "addr:full":"Calle de Rio, 7 Belmez C\u00f3rdoba 14240",
    "addr:housenumber":"7",
    "addr:postcode":"14240",
    "addr:street":"Calle De Rio",
    "iso:country":"ES",
    "sg:address":"Calle de Rio, 7",
    "sg:city":"Belmez",
    "sg:orig_category":"Empresas De Desmonte",
    "sg:phone":"+34 957 58 07 11",
    "sg:postcode":"14240",
    "sg:province":"C\u00f3rdoba",
    "wof:name":"Vera Ruiz Luisa Maria",
    "wof:placetype":"venue"
},
  "geometry": {"coordinates":[-5.208340168,38.271648407],"type":"Point"}
}