{
  "type": "Feature",
  "properties": {
    "iso:country":"ES",
    "sg:address":"De El Vagon, 16",
    "sg:city":"La Solana",
    "sg:orig_category":"Mec\u00c1nico Del Autom\u00d3vil",
    "sg:phone":"+34 926 64 85 02",
    "sg:postcode":"13240",
    "sg:province":"Ciudad Real",
    "wof:name":"Hermanos Dominguez Solera S.l.",
    "wof:placetype":"venue"
},
  "geometry": {"coordinates":[-3.2267649174,38.9411964417],"type":"Point"}
}