{
  "type": "Feature",
  "properties": {
    "iso:country":"ES",
    "sg:address":"Alam Revilla Gregorio De La, 29",
    "sg:city":"Bilbao",
    "sg:orig_category":"Tapicer\u00cdas",
    "sg:phone":"+34 944 44 90 65",
    "sg:postcode":"48010",
    "sg:province":"Vizcaya",
    "wof:name":"Jara Etxebarria Javier",
    "wof:placetype":"venue"
},
  "geometry": {"coordinates":[-2.940787077,43.2595443726],"type":"Point"}
}