{
  "type": "Feature",
  "properties": {
    "iso:country":"ES",
    "sg:address":"Calle de Pintor Matias Moreno, 2",
    "sg:city":"Toledo",
    "sg:orig_category":"Comisarios",
    "sg:phone":"+34 925 22 30 92",
    "sg:postcode":"45002",
    "sg:province":"Toledo",
    "wof:name":"Sanguino Arrellano Pablo Aquilino",
    "wof:placetype":"venue"
},
  "geometry": {"coordinates":[-4.0300989151,39.8591041565],"type":"Point"}
}