{
  "type": "Feature",
  "properties": {
    "addr:full":"Calle de Santiago, 43 Albacete Albacete 02005",
    "addr:housenumber":"43",
    "addr:postcode":"02005",
    "addr:street":"Calle De Santiago",
    "iso:country":"ES",
    "sg:address":"Calle de Santiago, 43",
    "sg:city":"Albacete",
    "sg:orig_category":"Electricidad Veh\u00cdculo",
    "sg:phone":"+34 967 23 41 27",
    "sg:postcode":"02005",
    "sg:province":"Albacete",
    "wof:name":"Romero Garcia Fernando",
    "wof:placetype":"venue"
},
  "geometry": {"coordinates":[-1.8667960167,39.0010528564],"type":"Point"}
}