{
  "type": "Feature",
  "properties": {
    "iso:country":"ES",
    "sg:address":"Avda Ferrol, 1",
    "sg:city":"Pontedeume",
    "sg:orig_category":"Art\u00cdculos Funerarios (al Por Menor)",
    "sg:phone":"+34 981 43 07 02",
    "sg:postcode":"15600",
    "sg:province":"La Coru\u00f1a",
    "wof:name":"Fraga Perez Y Otro C.b.",
    "wof:placetype":"venue"
},
  "geometry": {"coordinates":[-8.1731290817,43.4077415466],"type":"Point"}
}