{
  "type": "Feature",
  "properties": {
    "iso:country":"ES",
    "sg:address":"Calle de Gutierrez Herrero De, 50",
    "sg:city":"Aviles",
    "sg:orig_category":"Promotores Constructores",
    "sg:phone":"+34 985 54 17 66",
    "sg:postcode":"33402",
    "sg:province":"Asturias",
    "wof:name":"Casado Prieto Emiliano",
    "wof:placetype":"venue"
},
  "geometry": {"coordinates":[-5.9162077904,43.548625946],"type":"Point"}
}