{
  "type": "Feature",
  "properties": {
    "addr:full":"Avgd Garrigues, 91 Lleida Lleida 25001",
    "addr:housenumber":"91",
    "addr:postcode":"25001",
    "iso:country":"ES",
    "sg:address":"Avgd Garrigues, 91",
    "sg:city":"Lleida",
    "sg:orig_category":"Molduras, Junquillos, Listones Y Molduras Perforadas",
    "sg:phone":"+34 973 20 48 13",
    "sg:postcode":"25001",
    "sg:province":"Lleida",
    "wof:name":"Vazquez Camacho Encarnacion",
    "wof:placetype":"venue"
},
  "geometry": {"coordinates":[0.6414020061,41.604057312],"type":"Point"}
}