{
  "type": "Feature",
  "properties": {
    "addr:full":"Avda Manuel Barnuevo, 5 Villarrobledo Albacete 02600",
    "addr:housenumber":"5",
    "addr:postcode":"02600",
    "addr:street":"Avda Manuel Barnuevo",
    "iso:country":"ES",
    "sg:address":"Avda Manuel Barnuevo, 5",
    "sg:city":"Villarrobledo",
    "sg:orig_category":"Producci\u00d3n, Venta De Productos De Agricultura Biol\u00d3gica",
    "sg:phone":"+34 967 14 01 91",
    "sg:postcode":"02600",
    "sg:province":"Albacete",
    "wof:name":"Arbeor S.l.",
    "wof:placetype":"venue"
},
  "geometry": {"coordinates":[-2.5981218815,39.2619476318],"type":"Point"}
}