{
  "type": "Feature",
  "properties": {
    "iso:country":"ES",
    "sg:address":"Rua Cami\u00d1o Verde, 58",
    "sg:city":"Lugo",
    "sg:orig_category":"Venta, Instalaci\u00d3n De Calefacci\u00d3n",
    "sg:phone":"+34 982 21 36 21",
    "sg:postcode":"27004",
    "sg:province":"Lugo",
    "wof:name":"Nieto Nu\u00f1ez Jose",
    "wof:placetype":"venue"
},
  "geometry": {"coordinates":[-7.5713610649,43.0195083618],"type":"Point"}
}