{
  "type": "Feature",
  "properties": {
    "addr:full":"Pase Libertad (de La), 35 Chio Santa Cruz De Tenerife 38689",
    "addr:postcode":"38689",
    "iso:country":"ES",
    "sg:address":"Pase Libertad (de La), 35",
    "sg:city":"Chio",
    "sg:orig_category":"Peluquer\u00cdas, Peluquer\u00cda Mixta",
    "sg:phone":"+34 922 85 19 95",
    "sg:postcode":"38689",
    "sg:province":"Santa Cruz De Tenerife",
    "wof:name":"Martin Perez Laura",
    "wof:placetype":"venue"
},
  "geometry": {"coordinates":[-16.7970409393,28.240688324],"type":"Point"}
}