{
  "type": "Feature",
  "properties": {
    "addr:full":"Calle de Perez Galdos, 2 Sevilla Sevilla 41004",
    "addr:housenumber":"2",
    "addr:postcode":"41004",
    "addr:street":"Calle De Perez Galdos",
    "iso:country":"ES",
    "sg:address":"Calle de Perez Galdos, 2",
    "sg:city":"Sevilla",
    "sg:orig_category":"Confecci\u00d3n (fabricaci\u00d3n, Al Por Mayor)",
    "sg:phone":"+34 954 21 82 65",
    "sg:postcode":"41004",
    "sg:province":"Sevilla",
    "wof:name":"Mu\u00f1oz Moreno Andres",
    "wof:placetype":"venue"
},
  "geometry": {"coordinates":[-5.9910650253,37.3913879395],"type":"Point"}
}