{
  "type": "Feature",
  "properties": {
    "addr:full":"Afueras, S/n Garg\u00fcera C\u00e1ceres 10696",
    "addr:postcode":"10696",
    "addr:street":"Afueras S / N Gargueera Ca\u0301Ceres",
    "iso:country":"ES",
    "sg:address":"Afueras, S/n",
    "sg:city":"Garg\u00fcera",
    "sg:orig_category":"Cr\u00cda De Animales",
    "sg:phone":"+34 927 19 40 60",
    "sg:postcode":"10696",
    "sg:province":"C\u00e1ceres",
    "wof:name":"Hermanos Moreno Alcalde",
    "wof:placetype":"venue"
},
  "geometry": {"coordinates":[-5.8816847801,40.0855484009],"type":"Point"}
}