{
  "type": "Feature",
  "properties": {
    "iso:country":"ES",
    "sg:address":"Avda Ruta De La Plata, 26",
    "sg:city":"Caceres",
    "sg:classifiers":[
        {
            "category":"Taxi",
            "type":"Transportation"
        }
    ],
    "sg:phone":"+34 927 23 80 21",
    "sg:postcode":"10001",
    "sg:province":"C\u00e1ceres",
    "wof:name":"Roman Santos Francisco",
    "wof:placetype":"venue"
},
  "geometry": {"coordinates":[-6.3877391815,39.4711799622],"type":"Point"}
}