{
  "type": "Feature",
  "properties": {
    "addr:full":"C/ Santa Anna, 82 Cerdanyola Valles Barcelona 08290",
    "addr:housenumber":"82",
    "addr:postcode":"08290",
    "addr:street":"C / Santa Anna;Valles Barcelona",
    "iso:country":"ES",
    "sg:address":"C/ Santa Anna, 82",
    "sg:city":"Cerdanyola Valles",
    "sg:orig_category":"Agentes, Concesionarios Y Sucursales De Veh\u00cdculos",
    "sg:phone":"+34 936 91 77 99",
    "sg:postcode":"08290",
    "sg:province":"Barcelona",
    "wof:name":"Antonio Sierra Aranda S.l.",
    "wof:placetype":"venue"
},
  "geometry": {"coordinates":[2.1379876137,41.496761322],"type":"Point"}
}