{
  "type": "Feature",
  "properties": {
    "addr:full":"Calle de Begastri, 2 Cehegin Murcia 30430",
    "addr:housenumber":"2",
    "addr:postcode":"30430",
    "addr:street":"Calle De Begastri",
    "iso:country":"ES",
    "sg:address":"Calle de Begastri, 2",
    "sg:city":"Cehegin",
    "sg:orig_category":"Inmobiliaria (agencias)",
    "sg:phone":"+34 968 74 33 72",
    "sg:postcode":"30430",
    "sg:province":"Murcia",
    "wof:name":"Perez Garcia-ripoll Jose Carlos",
    "wof:placetype":"venue"
},
  "geometry": {"coordinates":[-1.796408534,38.0914878845],"type":"Point"}
}