{
  "type": "Feature",
  "properties": {
    "addr:full":"Calle de Gabriel Matute, 4 Cadiz C\u00e1diz 11008",
    "addr:housenumber":"4",
    "addr:postcode":"11008",
    "addr:street":"Calle De Gabriel Matute",
    "iso:country":"ES",
    "sg:address":"Calle de Gabriel Matute, 4",
    "sg:city":"Cadiz",
    "sg:orig_category":"Producci\u00d3n, Distribuci\u00d3n De Electricidad",
    "sg:phone":"+34 956 25 09 19",
    "sg:postcode":"11008",
    "sg:province":"C\u00e1diz",
    "wof:name":"Alvarez Beltran S.a.",
    "wof:placetype":"venue"
},
  "geometry": {"coordinates":[-6.2840123177,36.5166740417],"type":"Point"}
}