{
  "type": "Feature",
  "properties": {
    "iso:country":"ES",
    "sg:address":"Calle de Polvoranca, 21",
    "sg:city":"Alcorcon",
    "sg:orig_category":"Peluqueros: De Se\u00d1oras",
    "sg:phone":"+34 916 19 10 43",
    "sg:postcode":"28921",
    "sg:province":"Madrid",
    "wof:name":"Oliveira Roman Antonio",
    "wof:placetype":"venue"
},
  "geometry": {"coordinates":[-3.8252360821,40.348274231],"type":"Point"}
}