{
  "type": "Feature",
  "properties": {
    "iso:country":"ES",
    "sg:address":"Avgd Cami Real (del), 94",
    "sg:city":"Castello Rugat",
    "sg:orig_category":"Productores Recolectores, Venta Directa De Vinos",
    "sg:phone":"+34 962 81 30 17",
    "sg:postcode":"46841",
    "sg:province":"Valencia",
    "wof:name":"Bodegas Bataller S.a.",
    "wof:placetype":"venue"
},
  "geometry": {"coordinates":[-0.3831990063,38.8734703064],"type":"Point"}
}