{
  "type": "Feature",
  "properties": {
    "iso:country":"ES",
    "sg:address":"Avda Carde\u00d1a (de), 3",
    "sg:city":"Villanueva Cordoba",
    "sg:orig_category":"Molduras, Junquillos, Listones Y Molduras Perforadas",
    "sg:phone":"+34 957 12 00 70",
    "sg:postcode":"14440",
    "sg:province":"C\u00f3rdoba",
    "wof:name":"Chaparro Gomez Francisco",
    "wof:placetype":"venue"
},
  "geometry": {"coordinates":[-4.6221370697,38.3222465515],"type":"Point"}
}