{
  "type": "Feature",
  "properties": {
    "iso:country":"ES",
    "sg:address":"Jaun De Altzate Plaza, 2",
    "sg:city":"Bera",
    "sg:orig_category":"Carnicer\u00cdas, Carnicer\u00cdas",
    "sg:phone":"+34 948 63 00 54",
    "sg:postcode":"31780",
    "sg:province":"Navarra",
    "wof:name":"Pagola Igoa Jose Angel",
    "wof:placetype":"venue"
},
  "geometry": {"coordinates":[-1.6767289639,43.2817077637],"type":"Point"}
}