{
  "type": "Feature",
  "properties": {
    "iso:country":"ES",
    "sg:address":"Ctra. Girona, 77",
    "sg:city":"Quart",
    "sg:orig_category":"Trajes Y Adornos De Boda (confecci\u00d3n, Al Por Menor)",
    "sg:phone":"+34 972 46 93 40",
    "sg:postcode":"17242",
    "sg:province":"Girona",
    "sg:website":"www.stellamatutinanuvias.com",
    "wof:name":"Duran Pi Maria Josep",
    "wof:placetype":"venue"
},
  "geometry": {"coordinates":[2.8420550823,41.9365539551],"type":"Point"}
}