{
  "type": "Feature",
  "properties": {
    "iso:country":"ES",
    "sg:address":"Avda Juan Carlos I, 135",
    "sg:city":"Totana",
    "sg:orig_category":"Alquiler De V\u00cddeo",
    "sg:phone":"+34 968 42 21 00",
    "sg:postcode":"30850",
    "sg:province":"Murcia",
    "wof:name":"Perez Heredia Benito",
    "wof:placetype":"venue"
},
  "geometry": {"coordinates":[-1.4947479963,37.7717704773],"type":"Point"}
}