{
  "type": "Feature",
  "properties": {
    "addr:full":"Plaz Campo De La Feria, 28 Guitiriz Lugo 27300",
    "addr:housenumber":"28",
    "addr:postcode":"27300",
    "addr:street":"La Feria",
    "iso:country":"ES",
    "sg:address":"Plaz Campo De La Feria, 28",
    "sg:city":"Guitiriz",
    "sg:orig_category":"Asesor\u00cda Fiscal Y Jur\u00cddica",
    "sg:phone":"+34 982 37 00 74",
    "sg:postcode":"27300",
    "sg:province":"Lugo",
    "wof:name":"Alvarez Real S.l.",
    "wof:placetype":"venue"
},
  "geometry": {"coordinates":[-7.8952274323,43.1827850342],"type":"Point"}
}