{
  "type": "Feature",
  "properties": {
    "iso:country":"ES",
    "sg:address":"Calle de Rafael Alberti, 42",
    "sg:city":"Bollullos Par Condado",
    "sg:orig_category":"Bisuter\u00cda, Joyer\u00cda, Relojer\u00cda (al Por Menor)",
    "sg:phone":"+34 959 40 84 03",
    "sg:postcode":"21710",
    "sg:province":"Huelva",
    "wof:name":"Rubio Carretero Angel",
    "wof:placetype":"venue"
},
  "geometry": {"coordinates":[-6.5370488167,37.3379402161],"type":"Point"}
}