{
  "type": "Feature",
  "properties": {
    "addr:full":"Rond Alzira, 60 Algemesi Valencia 46680",
    "addr:housenumber":"60",
    "addr:postcode":"46680",
    "addr:street":"Alzira",
    "iso:country":"ES",
    "sg:address":"Rond Alzira, 60",
    "sg:city":"Algemesi",
    "sg:orig_category":"Asesores De Gesti\u00d3n Del Patrimonio",
    "sg:phone":"+34 962 48 11 81",
    "sg:postcode":"46680",
    "sg:province":"Valencia",
    "wof:name":"Pascual Verdeguer S.l.",
    "wof:placetype":"venue"
},
  "geometry": {"coordinates":[-0.4383490086,39.1962852478],"type":"Point"}
}