{
  "type": "Feature",
  "properties": {
    "iso:country":"ES",
    "sg:address":"Carr Teodoro Llorente, 7",
    "sg:city":"Aldaia",
    "sg:orig_category":"Peluquer\u00cdas, Peluquer\u00cda Mixta",
    "sg:phone":"+34 961 50 85 82",
    "sg:postcode":"46960",
    "sg:province":"Valencia",
    "wof:name":"Era's 4 S.l.",
    "wof:placetype":"venue"
},
  "geometry": {"coordinates":[-0.4601179957,39.4644432068],"type":"Point"}
}