{
  "type": "Feature",
  "properties": {
    "iso:country":"ES",
    "sg:address":"Calle de Sarasate, 11",
    "sg:city":"Majadahonda",
    "sg:orig_category":"Centros Empresariales",
    "sg:phone":"+34 916 02 82 36",
    "sg:postcode":"28220",
    "sg:province":"Madrid",
    "wof:name":"Akila  Sofian Dawood",
    "wof:placetype":"venue"
},
  "geometry": {"coordinates":[-3.8591375351,40.4486656189],"type":"Point"}
}