{
  "type": "Feature",
  "properties": {
    "iso:country":"ES",
    "sg:address":"Cadiz-malaga, Km. 0171,0",
    "sg:city":"San Pedro Alcantara",
    "sg:orig_category":"Quincaller\u00cda (al Por Menor)",
    "sg:phone":"+34 952 78 83 88",
    "sg:postcode":"29670",
    "sg:province":"M\u00e1laga",
    "wof:name":"Ferreteria El Store S.l.",
    "wof:placetype":"venue"
},
  "geometry": {"coordinates":[-4.9902391434,36.4866333008],"type":"Point"}
}