{
  "type": "Feature",
  "properties": {
    "addr:full":"Carrer de Peixateria (de La), 17 Valls Tarragona 43800",
    "addr:housenumber":"17",
    "addr:postcode":"43800",
    "addr:street":"Carrer De Peixateria De La",
    "iso:country":"ES",
    "sg:address":"Carrer de Peixateria (de La), 17",
    "sg:city":"Valls",
    "sg:orig_category":"Ropa De Trabajo Y Profesionales (al Por Menor)",
    "sg:phone":"+34 977 60 63 64",
    "sg:postcode":"43800",
    "sg:province":"Tarragona",
    "wof:name":"Cubos Serra Maria Victoria",
    "wof:placetype":"venue"
},
  "geometry": {"coordinates":[1.2490259409,41.2844810486],"type":"Point"}
}