{
  "type": "Feature",
  "properties": {
    "iso:country":"ES",
    "sg:address":"Calle de Principe De Vergara, 269",
    "sg:city":"Madrid",
    "sg:orig_category":"Parques De Atracciones Y Centros De Esparcimiento",
    "sg:phone":"+34 914 58 86 02",
    "sg:postcode":"28016",
    "sg:province":"Madrid",
    "wof:name":"Salones Vergara S. A.",
    "wof:placetype":"venue"
},
  "geometry": {"coordinates":[-3.67709589,40.4576835632],"type":"Point"}
}