{
  "type": "Feature",
  "properties": {
    "iso:country":"ES",
    "sg:address":"Carr Prat De La Riba, 30",
    "sg:city":"Albatarrec",
    "sg:orig_category":"Doctores En Medicina",
    "sg:phone":"+34 973 72 00 71",
    "sg:postcode":"25171",
    "sg:province":"Lleida",
    "wof:name":"Nistal Rispa Josefa",
    "wof:placetype":"venue"
},
  "geometry": {"coordinates":[0.6064419746,41.5726280212],"type":"Point"}
}