{
  "type": "Feature",
  "properties": {
    "iso:country":"ES",
    "sg:address":"Rua Cardenal Quiroga, 21",
    "sg:city":"Ourense",
    "sg:classifiers":[
        {
            "category":"Professional",
            "subcategory":"Management & Consulting",
            "type":"Services"
        }
    ],
    "sg:phone":"+34 988 23 11 25",
    "sg:postcode":"32003",
    "sg:province":"Ourense",
    "sg:tags":[
        "asesor\u00cda",
        "en",
        "marketing"
    ],
    "wof:name":"Alvarez Paradela Juan Luis",
    "wof:placetype":"venue"
},
  "geometry": {"coordinates":[-7.8643140793,42.3381652832],"type":"Point"}
}