{
  "type": "Feature",
  "properties": {
    "iso:country":"ES",
    "sg:address":"Carrer de Rossello, 440",
    "sg:city":"Barcelona",
    "sg:orig_category":"Carnicer\u00cdas, Carnicer\u00cdas",
    "sg:phone":"+34 934 36 12 98",
    "sg:postcode":"08025",
    "sg:province":"Barcelona",
    "wof:name":"Tamayo Calderon Julian",
    "wof:placetype":"venue"
},
  "geometry": {"coordinates":[2.1757891178,41.4070129395],"type":"Point"}
}