{
  "type": "Feature",
  "properties": {
    "iso:country":"ES",
    "sg:address":"Calle de Lain Calvo, 32",
    "sg:city":"Burgos",
    "sg:orig_category":"Bordado, Marcado A Medida",
    "sg:phone":"+34 947 20 41 94",
    "sg:postcode":"09003",
    "sg:province":"Burgos",
    "wof:name":"Quintanilla Diez Mercedes",
    "wof:placetype":"venue"
},
  "geometry": {"coordinates":[-3.7016870975,42.3421707153],"type":"Point"}
}