{
  "type": "Feature",
  "properties": {
    "iso:country":"ES",
    "sg:address":"Calle de Crisanta (do\u00d1a), 4",
    "sg:city":"Tomelloso",
    "sg:orig_category":"Arquitectos",
    "sg:phone":"+34 926 51 39 16",
    "sg:postcode":"13700",
    "sg:province":"Ciudad Real",
    "wof:name":"Mateo Cuesta Victor",
    "wof:placetype":"venue"
},
  "geometry": {"coordinates":[-3.0205504894,39.1580352783],"type":"Point"}
}