{
  "type": "Feature",
  "properties": {
    "addr:full":"Calle de Soto Hidalgo, 24 Madrid Madrid 28042",
    "addr:housenumber":"24",
    "addr:postcode":"madrid;28042",
    "addr:street":"Calle De Soto Hidalgo",
    "iso:country":"ES",
    "sg:address":"Calle de Soto Hidalgo, 24",
    "sg:city":"Madrid",
    "sg:orig_category":"Alquiler De Veh\u00cdculos: Turismos Y Utilitarios",
    "sg:phone":"+34 913 29 02 35",
    "sg:postcode":"28042",
    "sg:province":"Madrid",
    "wof:name":"Vehiculo De Abono Special Car Service Sociedad Coop.ltda.",
    "wof:placetype":"venue"
},
  "geometry": {"coordinates":[-3.5811240673,40.461063385],"type":"Point"}
}