{
  "type": "Feature",
  "properties": {
    "iso:country":"ES",
    "sg:address":"Carr Ruperto Chapi, 2",
    "sg:city":"Pla Parcial Platja",
    "sg:orig_category":"Comerciantes Al Por Mayor De Vinos, Licores Y Alcoholes",
    "sg:phone":"+34 966 86 49 26",
    "sg:postcode":"03580",
    "sg:province":"Alicante",
    "wof:name":"Barajas Gallegos Raul",
    "wof:placetype":"venue"
},
  "geometry": {"coordinates":[-0.1033039987,38.5793037415],"type":"Point"}
}