{
  "type": "Feature",
  "properties": {
    "addr:full":"Pl Josep Freixa I Argemi, 3 Terrassa Barcelona 08224",
    "addr:housenumber":"3",
    "addr:postcode":"08224",
    "addr:street":"Pl;Argemi",
    "iso:country":"ES",
    "sg:address":"Pl Josep Freixa I Argemi, 3",
    "sg:city":"Terrassa",
    "sg:orig_category":"Peluquer\u00cdas, Peluquer\u00cda Mixta",
    "sg:phone":"+34 937 88 93 15",
    "sg:postcode":"08224",
    "sg:province":"Barcelona",
    "wof:name":"Andres Andres Maria Angeles",
    "wof:placetype":"venue"
},
  "geometry": {"coordinates":[2.005248785,41.5631141663],"type":"Point"}
}