{
  "type": "Feature",
  "properties": {
    "iso:country":"ES",
    "sg:address":"Calle de Infanta Mercedes, 115",
    "sg:city":"Madrid",
    "sg:orig_category":"Restaurantes",
    "sg:phone":"+34 915 79 25 07",
    "sg:postcode":"28020",
    "sg:province":"Madrid",
    "wof:name":"Domiguez Fernandez Francisco Julian",
    "wof:placetype":"venue"
},
  "geometry": {"coordinates":[-3.6926689148,40.4642601013],"type":"Point"}
}