{
  "type": "Feature",
  "properties": {
    "addr:full":"Calle de Santiago, 95 Elizondo Navarra 31700",
    "addr:housenumber":"95",
    "addr:postcode":"31700",
    "addr:street":"Calle De Santiago;Navarra",
    "iso:country":"ES",
    "sg:address":"Calle de Santiago, 95",
    "sg:city":"Elizondo",
    "sg:orig_category":"Art\u00cdculos De Regalo (al Por Menor)",
    "sg:phone":"+34 948 45 24 27",
    "sg:postcode":"31700",
    "sg:province":"Navarra",
    "wof:name":"Petricorena Sagaseta Leandro",
    "wof:placetype":"venue"
},
  "geometry": {"coordinates":[-1.5234800577,43.1406097412],"type":"Point"}
}