{
  "type": "Feature",
  "properties": {
    "addr:full":"Calle de Arcipreste Fernandez Casado, S/n Montilla C\u00f3rdoba 14550",
    "addr:housenumber":"s / n",
    "addr:postcode":"14550",
    "addr:street":"Calle De Arcipreste Fernandez Casado;Co\u0301Rdoba",
    "iso:country":"ES",
    "sg:address":"Calle de Arcipreste Fernandez Casado, S/n",
    "sg:city":"Montilla",
    "sg:orig_category":"Ense\u00d1anza, Formaci\u00d3n Profesional: Aprendizaje",
    "sg:phone":"+34 957 65 01 91",
    "sg:postcode":"14550",
    "sg:province":"C\u00f3rdoba",
    "wof:name":"Junta De Andalucia-consejeria De Gobernacion Y Justicia",
    "wof:placetype":"venue"
},
  "geometry": {"coordinates":[-4.6243748665,37.5696258545],"type":"Point"}
}