{
  "type": "Feature",
  "properties": {
    "iso:country":"ES",
    "sg:address":"Calle de Veinte De Octubre, 3",
    "sg:city":"Marmolejo",
    "sg:orig_category":"Alimentaci\u00d3n General (al Por Menor)",
    "sg:phone":"+34 953 54 05 94",
    "sg:postcode":"23770",
    "sg:province":"Ja\u00e9n",
    "wof:name":"Pe\u00f1a Membrives Dolores",
    "wof:placetype":"venue"
},
  "geometry": {"coordinates":[-4.1686739922,38.0476646423],"type":"Point"}
}