{
  "type": "Feature",
  "properties": {
    "iso:country":"ES",
    "sg:address":"Calle de Cruz Del Estudiante, 32",
    "sg:city":"Puente-genil",
    "sg:orig_category":"Relojer\u00cda (al Por Menor, Reparaci\u00d3n)",
    "sg:phone":"+34 957 60 07 32",
    "sg:postcode":"14500",
    "sg:province":"C\u00f3rdoba",
    "wof:name":"Reyes Torrus Miguel Angel",
    "wof:placetype":"venue"
},
  "geometry": {"coordinates":[-4.7695245743,37.3894462585],"type":"Point"}
}