{
  "type": "Feature",
  "properties": {
    "iso:country":"ES",
    "sg:address":"Avda Carlos De Haya, 53",
    "sg:city":"Malaga",
    "sg:classifiers":[
        {
            "category":"Autos & Motor Vehicles",
            "subcategory":"Automobile Sales",
            "type":"Retail Goods"
        }
    ],
    "sg:phone":"+34 952 27 11 00",
    "sg:postcode":"29010",
    "sg:province":"M\u00e1laga",
    "wof:name":"Autoescuelas Torcal S.l.",
    "wof:placetype":"venue"
},
  "geometry": {"coordinates":[-4.4476652145,36.7221832275],"type":"Point"}
}