{
  "type": "Feature",
  "properties": {
    "iso:country":"ES",
    "sg:address":"Av Tres-cents Cinc, 17",
    "sg:city":"Castelldefels",
    "sg:orig_category":"Electrodom\u00c9sticos (al Por Menor)",
    "sg:phone":"+34 936 65 13 66",
    "sg:postcode":"08860",
    "sg:province":"Barcelona",
    "wof:name":"Garcia Parra Juan Francisco",
    "wof:placetype":"venue"
},
  "geometry": {"coordinates":[1.9767744541,41.2803878784],"type":"Point"}
}