{
  "type": "Feature",
  "properties": {
    "iso:country":"ES",
    "sg:address":"Carrer de Baix, 48",
    "sg:city":"Esparreguera",
    "sg:orig_category":"Asociaciones, Organismos Culturales Y Socioeducativos",
    "sg:phone":"+34 937 77 36 06",
    "sg:postcode":"08292",
    "sg:province":"Barcelona",
    "wof:name":"Pe\u00f1a Madridista El Alba",
    "wof:placetype":"venue"
},
  "geometry": {"coordinates":[1.8698949814,41.5376739502],"type":"Point"}
}