{
  "type": "Feature",
  "properties": {
    "addr:full":"Pregal, 37 Redondela Pontevedra 36814",
    "addr:housenumber":"37",
    "addr:postcode":"36814",
    "addr:street":"Pregal",
    "iso:country":"ES",
    "sg:address":"Pregal, 37",
    "sg:city":"Redondela",
    "sg:orig_category":"Alquiler De Veh\u00cdculos: Turismos Y Utilitarios",
    "sg:phone":"+34 986 40 28 30",
    "sg:postcode":"36814",
    "sg:province":"Pontevedra",
    "wof:name":"Villanueva Boullosa Maria Isabel",
    "wof:placetype":"venue"
},
  "geometry": {"coordinates":[-8.6044063568,42.2630767822],"type":"Point"}
}