{
  "type": "Feature",
  "properties": {
    "iso:country":"ES",
    "sg:address":"Urdaneta Kalea, 6",
    "sg:city":"Zarautz",
    "sg:orig_category":"Arreglo E Instalaci\u00d3n De Caf\u00c9s, Hoteles Y Restaurantes",
    "sg:phone":"+34 943 13 12 07",
    "sg:postcode":"20800",
    "sg:province":"Guip\u00f9zcoa",
    "wof:name":"Maria Lourdes Mendizabal Illarramendi",
    "wof:placetype":"venue"
},
  "geometry": {"coordinates":[-2.174608469,43.2806930542],"type":"Point"}
}