{
  "type": "Feature",
  "properties": {
    "addr:full":"Calle de Mota Del Cuervo, 19 Madrid Madrid 28043",
    "addr:housenumber":"19",
    "addr:postcode":"madrid;28043",
    "addr:street":"Calle De Mota Del Cuervo",
    "iso:country":"ES",
    "sg:address":"Calle de Mota Del Cuervo, 19",
    "sg:city":"Madrid",
    "sg:orig_category":"Ense\u00d1anza: Idiomas",
    "sg:phone":"+34 913 88 72 72",
    "sg:postcode":"28043",
    "sg:province":"Madrid",
    "wof:name":"Alonso Cabrero Gema",
    "wof:placetype":"venue"
},
  "geometry": {"coordinates":[-3.6308438778,40.4652328491],"type":"Point"}
}