{
  "type": "Feature",
  "properties": {
    "addr:full":"Plaz Serrano Berges (santa Isabel), 11 Zaragoza Zaragoza 50016",
    "addr:housenumber":"11",
    "addr:postcode":"50016",
    "addr:street":"Plaz Serrano Berges Santa Isabel",
    "iso:country":"ES",
    "sg:address":"Plaz Serrano Berges (santa Isabel), 11",
    "sg:city":"Zaragoza",
    "sg:orig_category":"Herboristas (al Por Menor)",
    "sg:phone":"+34 976 57 48 33",
    "sg:postcode":"50016",
    "sg:province":"Zaragoza",
    "wof:name":"Bes Monforte Bego\u00f1a",
    "wof:placetype":"venue"
},
  "geometry": {"coordinates":[-0.830968976,41.6675300598],"type":"Point"}
}