{
  "type": "Feature",
  "properties": {
    "iso:country":"ES",
    "sg:address":"Calle de Prosperidad, 32",
    "sg:city":"Santa Cruz De Tenerife",
    "sg:orig_category":"Retoques De Vestidos",
    "sg:phone":"+34 922 27 83 14",
    "sg:postcode":"38006",
    "sg:province":"Santa Cruz De Tenerife",
    "wof:name":"C.b. Composturas Avisan",
    "wof:placetype":"venue"
},
  "geometry": {"coordinates":[-16.2636356354,28.4688835144],"type":"Point"}
}