{
  "type": "Feature",
  "properties": {
    "addr:full":"Calle de Fotografo Rafael, 3 Cuellar Segovia 40200",
    "addr:housenumber":"3",
    "addr:postcode":"40200",
    "addr:street":"Calle De Fotografo Rafael",
    "iso:country":"ES",
    "sg:address":"Calle de Fotografo Rafael, 3",
    "sg:city":"Cuellar",
    "sg:orig_category":"Molduras, Junquillos, Listones Y Molduras Perforadas",
    "sg:phone":"+34 921 14 27 50",
    "sg:postcode":"40200",
    "sg:province":"Segovia",
    "wof:name":"Comunidad De Bienes Los Angeles De Cuellar",
    "wof:placetype":"venue"
},
  "geometry": {"coordinates":[-4.3097639084,41.4048309326],"type":"Point"}
}