{
  "type": "Feature",
  "properties": {
    "addr:full":"Avda Camilo Alonso Vega, 9 Santander Cantabria 39007",
    "addr:housenumber":"9",
    "addr:postcode":"39007",
    "addr:street":"Avda Camilo Alonso Vega",
    "iso:country":"ES",
    "sg:address":"Avda Camilo Alonso Vega, 9",
    "sg:city":"Santander",
    "sg:orig_category":"Cajas De Ahorro",
    "sg:phone":"+34 942 33 56 22",
    "sg:postcode":"39007",
    "sg:province":"Cantabria",
    "sg:website":"www.lacaixa.es",
    "wof:name":"Caixa D'estalvis I Pensions De Barcelona",
    "wof:placetype":"venue"
},
  "geometry": {"coordinates":[-3.8265399933,43.4593429565],"type":"Point"}
}