{
  "type": "Feature",
  "properties": {
    "iso:country":"ES",
    "sg:address":"Calle de Hermano Tomas Bengoa, 8",
    "sg:city":"Jerez De La Frontera",
    "sg:orig_category":"Empresas De Portes Y Mensajer\u00cda",
    "sg:phone":"+34 956 33 30 69",
    "sg:postcode":"11401",
    "sg:province":"C\u00e1diz",
    "wof:name":"Unipost S.a.",
    "wof:placetype":"venue"
},
  "geometry": {"coordinates":[-6.1258049011,36.6771774292],"type":"Point"}
}