{
  "type": "Feature",
  "properties": {
    "addr:full":"Calle de Vega Del Mar, S/n San Pedro Alcantara M\u00e1laga 29670",
    "addr:housenumber":"/ n",
    "addr:postcode":"29670",
    "addr:street":"Calle De Vega Del Mar S",
    "iso:country":"ES",
    "sg:address":"Calle de Vega Del Mar, S/n",
    "sg:city":"San Pedro Alcantara",
    "sg:orig_category":"Florister\u00cdas",
    "sg:phone":"+34 952 78 92 19",
    "sg:postcode":"29670",
    "sg:province":"M\u00e1laga",
    "wof:name":"Biedma Jaime Cristobal",
    "wof:placetype":"venue"
},
  "geometry": {"coordinates":[-4.9935789108,36.4894599915],"type":"Point"}
}