{
  "type": "Feature",
  "properties": {
    "iso:country":"ES",
    "sg:address":"Calle de Galileo (de), 2",
    "sg:city":"Fuenlabrada",
    "sg:orig_category":"Instalaci\u00d3n, Reparaci\u00d3n De Ascensores Y Montacargas",
    "sg:phone":"+34 916 85 63 20",
    "sg:postcode":"28946",
    "sg:province":"Madrid",
    "wof:name":"Suministros Y Componentes De Elevadores S.l.",
    "wof:placetype":"venue"
},
  "geometry": {"coordinates":[-3.7837369442,40.2847137451],"type":"Point"}
}