{
  "type": "Feature",
  "properties": {
    "addr:full":"Calle de Fika, 58 Bilbao Vizcaya 48004",
    "addr:housenumber":"58",
    "addr:postcode":"48004",
    "addr:street":"Calle De Fika",
    "iso:country":"ES",
    "sg:address":"Calle de Fika, 58",
    "sg:city":"Bilbao",
    "sg:orig_category":"Molduras, Junquillos, Listones Y Molduras Perforadas",
    "sg:phone":"+34 944 33 94 36",
    "sg:postcode":"48004",
    "sg:province":"Vizcaya",
    "wof:name":"Guemes Martin Iker",
    "wof:placetype":"venue"
},
  "geometry": {"coordinates":[-2.9169929028,43.2529792786],"type":"Point"}
}