{
  "type": "Feature",
  "properties": {
    "iso:country":"ES",
    "sg:address":"Ctra. Rota-puerto, Km. 0014,0",
    "sg:city":"Rota",
    "sg:orig_category":"Producci\u00d3n, Venta De Productos De Agricultura Biol\u00d3gica",
    "sg:phone":"+34 956 23 00 51",
    "sg:postcode":"11520",
    "sg:province":"C\u00e1diz",
    "wof:name":"Sociedad Cooperativa Andaluza Fuente De Oro",
    "wof:placetype":"venue"
},
  "geometry": {"coordinates":[-6.3688821793,36.6247940063],"type":"Point"}
}