{
  "type": "Feature",
  "properties": {
    "addr:full":"Carrer de Carles Altes, 48 Viladecans Barcelona 08840",
    "addr:housenumber":"48",
    "addr:postcode":"08840",
    "addr:street":"Carrer De Carles Altes",
    "iso:country":"ES",
    "sg:address":"Carrer de Carles Altes, 48",
    "sg:city":"Viladecans",
    "sg:orig_category":"Equipo De Refrigeraci\u00d3n Industrial",
    "sg:phone":"+34 936 59 12 09",
    "sg:postcode":"08840",
    "sg:province":"Barcelona",
    "wof:name":"Instalacion De Frio Industrial Refred S.l.",
    "wof:placetype":"venue"
},
  "geometry": {"coordinates":[2.0105268955,41.3202476501],"type":"Point"}
}