{
  "type": "Feature",
  "properties": {
    "iso:country":"ES",
    "sg:address":"Carr Santa Maria, 32",
    "sg:city":"Badalona",
    "sg:orig_category":"Florister\u00cdas",
    "sg:phone":"+34 933 89 29 67",
    "sg:postcode":"08911",
    "sg:province":"Barcelona",
    "wof:name":"Delgado Martin Antonio",
    "wof:placetype":"venue"
},
  "geometry": {"coordinates":[2.2538249493,41.4511985779],"type":"Point"}
}