{
  "type": "Feature",
  "properties": {
    "iso:country":"ES",
    "sg:address":"Carr Francisco Carbonell, 30",
    "sg:city":"Rocafort",
    "sg:classifiers":[
        {
            "category":"Personal",
            "subcategory":"Barber",
            "type":"Services"
        }
    ],
    "sg:phone":"+34 961 31 04 77",
    "sg:postcode":"46111",
    "sg:province":"Valencia",
    "sg:tags":[
        "caballeros",
        "de",
        "peluqueros"
    ],
    "wof:name":"Aguilar Beltran Juan Luis",
    "wof:placetype":"venue"
},
  "geometry": {"coordinates":[-0.4101605117,39.5307846069],"type":"Point"}
}