{
  "type": "Feature",
  "properties": {
    "addr:full":"Calle de Lord Byron, 14 Palmas De Gran Canaria Las Palmas 35005",
    "addr:housenumber":"14",
    "addr:postcode":"35005",
    "addr:street":"Calle De Lord Byron",
    "iso:country":"ES",
    "sg:address":"Calle de Lord Byron, 14",
    "sg:city":"Palmas De Gran Canaria",
    "sg:orig_category":"Procuradores",
    "sg:phone":"+34 928 23 17 72",
    "sg:postcode":"35005",
    "sg:province":"Las Palmas",
    "wof:name":"Cavallero Grillo Carmen",
    "wof:placetype":"venue"
},
  "geometry": {"coordinates":[-15.4291419983,28.1237945557],"type":"Point"}
}