{
  "type": "Feature",
  "properties": {
    "addr:full":"Calle de Felipe Ii, 4 Yuncos Toledo 45210",
    "addr:housenumber":"4",
    "addr:postcode":"45210",
    "addr:street":"Calle De Felipe Ii",
    "iso:country":"ES",
    "sg:address":"Calle de Felipe Ii, 4",
    "sg:city":"Yuncos",
    "sg:orig_category":"Electricidad: Instaladores",
    "sg:phone":"+34 925 53 31 34",
    "sg:postcode":"45210",
    "sg:province":"Toledo",
    "wof:name":"Spin Construcciones Y Reformas S.l.",
    "wof:placetype":"venue"
},
  "geometry": {"coordinates":[-3.8708043098,40.0939331055],"type":"Point"}
}