{
  "type": "Feature",
  "properties": {
    "iso:country":"ES",
    "sg:address":"Calle de San Sebastian, 12",
    "sg:city":"Palma Condado",
    "sg:orig_category":"Grafistas",
    "sg:phone":"+34 959 40 06 26",
    "sg:postcode":"21700",
    "sg:province":"Huelva",
    "wof:name":"Gil Perez Jose Maria",
    "wof:placetype":"venue"
},
  "geometry": {"coordinates":[-6.5544910431,37.3872413635],"type":"Point"}
}