{
  "type": "Feature",
  "properties": {
    "addr:full":"Carrer de Pau Piferrer, 20 Palma Islas Baleares 07011",
    "addr:housenumber":"20",
    "addr:postcode":"07011",
    "addr:street":"Carrer De Pau Piferrer",
    "iso:country":"ES",
    "sg:address":"Carrer de Pau Piferrer, 20",
    "sg:city":"Palma",
    "sg:orig_category":"Chapister\u00cda",
    "sg:phone":"+34 971 28 46 82",
    "sg:postcode":"07011",
    "sg:province":"Islas Baleares",
    "wof:name":"Ramon Jaume Miguel",
    "wof:placetype":"venue"
},
  "geometry": {"coordinates":[2.6432108879,39.5781745911],"type":"Point"}
}