{
  "type": "Feature",
  "properties": {
    "addr:full":"Avda Espa\u00d1a, 166 Estepona M\u00e1laga 29680",
    "addr:housenumber":"166",
    "addr:postcode":"29680",
    "addr:street":"Avda Espan\u0303A",
    "iso:country":"ES",
    "sg:address":"Avda Espa\u00d1a, 166",
    "sg:city":"Estepona",
    "sg:orig_category":"Inmobiliaria (agencias)",
    "sg:phone":"+34 952 80 59 65",
    "sg:postcode":"29680",
    "sg:province":"M\u00e1laga",
    "sg:website":"www.inmobiliariaveracruz.com",
    "wof:name":"Inmobiliaria Veracruz S.l.",
    "wof:placetype":"venue"
},
  "geometry": {"coordinates":[-5.1465101242,36.4233398438],"type":"Point"}
}