{
  "type": "Feature",
  "properties": {
    "iso:country":"ES",
    "sg:address":"Plaz Mayor, 2",
    "sg:city":"Sahagun",
    "sg:orig_category":"Farmacias",
    "sg:phone":"+34 987 78 00 66",
    "sg:postcode":"24320",
    "sg:province":"Le\u00f3n",
    "wof:name":"Acero Fernandez Maria Del Rosario",
    "wof:placetype":"venue"
},
  "geometry": {"coordinates":[-5.0078449249,42.3731536865],"type":"Point"}
}