{
  "type": "Feature",
  "properties": {
    "addr:full":"Calle de Virgen De Nuria, 19 Madrid Madrid 28027",
    "addr:housenumber":"19",
    "addr:postcode":"madrid;28027",
    "addr:street":"Calle De Virgen De Nuria",
    "iso:country":"ES",
    "sg:address":"Calle de Virgen De Nuria, 19",
    "sg:city":"Madrid",
    "sg:orig_category":"Complementos De Vestir (al Por Menor)",
    "sg:phone":"+34 914 03 91 78",
    "sg:postcode":"28027",
    "sg:province":"Madrid",
    "wof:name":"Benito Beltran Maria Luisa",
    "wof:placetype":"venue"
},
  "geometry": {"coordinates":[-3.6513168812,40.4370117188],"type":"Point"}
}