{
  "type": "Feature",
  "properties": {
    "addr:full":"Calle de Castilla La Nueva (de), 39 Fuenlabrada Madrid 28941",
    "addr:housenumber":"39",
    "addr:postcode":"28941",
    "addr:street":"Calle De Castilla La Nueva De",
    "iso:country":"ES",
    "sg:address":"Calle de Castilla La Nueva (de), 39",
    "sg:city":"Fuenlabrada",
    "sg:orig_category":"Tapicer\u00cdas",
    "sg:phone":"+34 916 06 86 44",
    "sg:postcode":"28941",
    "sg:province":"Madrid",
    "wof:name":"Alarcon Saez Mamerto",
    "wof:placetype":"venue"
},
  "geometry": {"coordinates":[-3.7969605923,40.2953834534],"type":"Point"}
}