{
  "type": "Feature",
  "properties": {
    "addr:full":"Bosquecillo, S/n Iru\u00f1a Navarra 31002",
    "addr:housenumber":"s / n",
    "addr:postcode":"31002",
    "addr:street":"Bosquecillo",
    "iso:country":"ES",
    "sg:address":"Bosquecillo, S/n",
    "sg:city":"Iru\u00f1a",
    "sg:orig_category":"Electrodom\u00c9sticos (al Por Menor)",
    "sg:phone":"+34 948 21 19 12",
    "sg:postcode":"31002",
    "sg:province":"Navarra",
    "wof:name":"Iyurbain S.a.",
    "wof:placetype":"venue"
},
  "geometry": {"coordinates":[-1.650349021,42.8162117004],"type":"Point"}
}