{
  "type": "Feature",
  "properties": {
    "addr:full":"Avda Villajoyosa, 97 Alacant Alicante 03016",
    "addr:housenumber":"97",
    "addr:postcode":"03016",
    "addr:street":"Avda Villajoyosa",
    "iso:country":"ES",
    "sg:address":"Avda Villajoyosa, 97",
    "sg:city":"Alacant",
    "sg:orig_category":"Asesor\u00cda Sobre Comunicaci\u00d3n De Empresas",
    "sg:phone":"+34 965 26 15 90",
    "sg:postcode":"03016",
    "sg:province":"Alicante",
    "wof:name":"Asesoria Frontera S.l.",
    "wof:placetype":"venue"
},
  "geometry": {"coordinates":[-0.4057897031,38.4130058289],"type":"Point"}
}