{
  "type": "Feature",
  "properties": {
    "iso:country":"ES",
    "sg:address":"Avda Miguel Manche\u00d1o, 22",
    "sg:city":"Arcos Frontera",
    "sg:orig_category":"Quincaller\u00cda (al Por Menor)",
    "sg:phone":"+34 956 70 00 10",
    "sg:postcode":"11630",
    "sg:province":"C\u00e1diz",
    "wof:name":"Reynaldo Vazquez Jose",
    "wof:placetype":"venue"
},
  "geometry": {"coordinates":[-5.818007946,36.7506942749],"type":"Point"}
}