{
  "type": "Feature",
  "properties": {
    "iso:country":"ES",
    "sg:address":"Calle de Obispo Marrodan, 7",
    "sg:city":"Tudelilla",
    "sg:orig_category":"Farmacias",
    "sg:phone":"+34 941 15 21 26",
    "sg:postcode":"26512",
    "sg:province":"La Rioja",
    "wof:name":"Blanco Mateos Sara",
    "wof:placetype":"venue"
},
  "geometry": {"coordinates":[-2.1177489758,42.2999916077],"type":"Point"}
}