{
  "type": "Feature",
  "properties": {
    "addr:full":"Avda Maria Auxiliadora, 46 Rota C\u00e1diz 11520",
    "addr:housenumber":"46",
    "addr:postcode":"11520",
    "addr:street":"Avda Maria Auxiliadora;Ca\u0301Diz",
    "iso:country":"ES",
    "sg:address":"Avda Maria Auxiliadora, 46",
    "sg:city":"Rota",
    "sg:orig_category":"Fabricaci\u00d3n De Art\u00cdculos Y Equipos Deportivos Y De Ocio",
    "sg:phone":"+34 956 81 14 10",
    "sg:postcode":"11520",
    "sg:province":"C\u00e1diz",
    "wof:name":"Retama Sports C.b.",
    "wof:placetype":"venue"
},
  "geometry": {"coordinates":[-6.3613290787,36.620891571],"type":"Point"}
}