{
  "type": "Feature",
  "properties": {
    "addr:full":"Av Reis Catolics, 20 Olot Girona 17800",
    "addr:housenumber":"20",
    "addr:postcode":"17800",
    "addr:street":"Av Reis Catolics",
    "iso:country":"ES",
    "sg:address":"Av Reis Catolics, 20",
    "sg:city":"Olot",
    "sg:orig_category":"Animales (al Por Menor)",
    "sg:phone":"+34 972 27 13 41",
    "sg:postcode":"17800",
    "sg:province":"Girona",
    "wof:name":"Minifauna-olot S.c.",
    "wof:placetype":"venue"
},
  "geometry": {"coordinates":[2.4820570946,42.1827812195],"type":"Point"}
}