{
  "type": "Feature",
  "properties": {
    "iso:country":"ES",
    "sg:address":"V. Dels Garrofers (p. Ind Garrofers), 65",
    "sg:city":"Vilassar",
    "sg:orig_category":"Fabricaci\u00d3n De Mobiliario De Oficina",
    "sg:phone":"+34 937 59 36 00",
    "sg:postcode":"08340",
    "sg:province":"Barcelona",
    "sg:website":"www.shetug.com",
    "wof:name":"Industrial Shetug S. A.",
    "wof:placetype":"venue"
},
  "geometry": {"coordinates":[2.3907299042,41.5019264221],"type":"Point"}
}