{
  "type": "Feature",
  "properties": {
    "iso:country":"ES",
    "sg:address":"Zubieta Kalea, 14",
    "sg:city":"Bergara",
    "sg:orig_category":"Empresas De Carpinter\u00cda De Madera",
    "sg:phone":"+34 943 76 17 53",
    "sg:postcode":"20570",
    "sg:province":"Guip\u00f9zcoa",
    "wof:name":"Ayastuy Igarzabal Juan Maria",
    "wof:placetype":"venue"
},
  "geometry": {"coordinates":[-2.4173810482,43.1218338013],"type":"Point"}
}