{
  "type": "Feature",
  "properties": {
    "addr:full":"Plaz San Francisco, 5 Zaragoza Zaragoza 50006",
    "addr:housenumber":"5",
    "addr:postcode":"50006",
    "addr:street":"Plaz San Francisco",
    "iso:country":"ES",
    "sg:address":"Plaz San Francisco, 5",
    "sg:city":"Zaragoza",
    "sg:orig_category":"Administradores De Bienes Y Delegados De Comunidades De Propietarios",
    "sg:phone":"+34 976 56 78 05",
    "sg:postcode":"50006",
    "sg:province":"Zaragoza",
    "wof:name":"Martin Mareca Luis",
    "wof:placetype":"venue"
},
  "geometry": {"coordinates":[-0.8939219713,41.6406211853],"type":"Point"}
}