{
  "type": "Feature",
  "properties": {
    "addr:full":"Cra. Borges-cornudella, S/n Alforja Tarragona 43365",
    "addr:housenumber":"s / n",
    "addr:postcode":"43365",
    "iso:country":"ES",
    "sg:address":"Cra. Borges-cornudella, S/n",
    "sg:city":"Alforja",
    "sg:orig_category":"Explotaci\u00d3n De Canteras",
    "sg:phone":"+34 977 81 65 36",
    "sg:postcode":"43365",
    "sg:province":"Tarragona",
    "wof:name":"Cuarcitas Del Mediterraneo S.a.",
    "wof:placetype":"venue"
},
  "geometry": {"coordinates":[0.9777849913,41.2123184204],"type":"Point"}
}