{
  "type": "Feature",
  "properties": {
    "iso:country":"ES",
    "sg:address":"Ctra Villalba/madrid, S/n",
    "sg:city":"San Ildefonso O La Granja",
    "sg:orig_category":"Comisarios",
    "sg:phone":"+34 921 47 21 44",
    "sg:postcode":"40100",
    "sg:province":"Segovia",
    "wof:name":"Arte Segovia S.l.",
    "wof:placetype":"venue"
},
  "geometry": {"coordinates":[-4.0124049187,40.8926734924],"type":"Point"}
}