{
  "type": "Feature",
  "properties": {
    "addr:full":"Carr Font(la), 27 Guissona Lleida 25210",
    "addr:housenumber":"27",
    "addr:postcode":"25210",
    "addr:street":"Carr Font La",
    "iso:country":"ES",
    "sg:address":"Carr Font(la), 27",
    "sg:city":"Guissona",
    "sg:orig_category":"Agencias De Viajes",
    "sg:phone":"+34 973 55 13 53",
    "sg:postcode":"25210",
    "sg:province":"Lleida",
    "wof:name":"Viatges Gris Expres S.l.",
    "wof:placetype":"venue"
},
  "geometry": {"coordinates":[1.2887649536,41.7873535156],"type":"Point"}
}