{
  "type": "Feature",
  "properties": {
    "iso:country":"ES",
    "sg:address":"Av. Pau Casals, 10",
    "sg:city":"Mora Nova",
    "sg:orig_category":"Empresas De Carpinter\u00cda De Madera",
    "sg:phone":"+34 977 40 21 52",
    "sg:postcode":"43770",
    "sg:province":"Tarragona",
    "wof:name":"Crespillo Velasco Lorenzo",
    "wof:placetype":"venue"
},
  "geometry": {"coordinates":[0.6538370252,41.1030960083],"type":"Point"}
}