{
  "type": "Feature",
  "properties": {
    "addr:full":"Carrer de Diputacio, 174 Barcelona Barcelona 08011",
    "addr:housenumber":"174",
    "addr:postcode":"08011",
    "addr:street":"Carrer De Diputacio",
    "iso:country":"ES",
    "sg:address":"Carrer de Diputacio, 174",
    "sg:city":"Barcelona",
    "sg:orig_category":"Quiropr\u00c1cticos",
    "sg:phone":"+34 934 51 19 69",
    "sg:postcode":"08011",
    "sg:province":"Barcelona",
    "sg:website":"www.naturaiment.com",
    "wof:name":"Natura I Ment Terapies I Estetica Naturals S.l.",
    "wof:placetype":"venue"
},
  "geometry": {"coordinates":[2.1592330933,41.3843231201],"type":"Point"}
}