{
  "type": "Feature",
  "properties": {
    "addr:full":"Carrer de Benet Mercade, 3 Barcelona Barcelona 08012",
    "addr:housenumber":"3",
    "addr:postcode":"08012",
    "addr:street":"Carrer De Benet Mercade",
    "iso:country":"ES",
    "sg:address":"Carrer de Benet Mercade, 3",
    "sg:city":"Barcelona",
    "sg:orig_category":"Relojer\u00cda Industrial",
    "sg:phone":"+34 932 17 97 98",
    "sg:postcode":"08012",
    "sg:province":"Barcelona",
    "wof:name":"Ber Climent Jose Maria",
    "wof:placetype":"venue"
},
  "geometry": {"coordinates":[2.1527190208,41.3999786377],"type":"Point"}
}