{
  "type": "Feature",
  "properties": {
    "iso:country":"ES",
    "sg:address":"Poligono Ind. Silvota, S/n",
    "sg:city":"Lugo",
    "sg:orig_category":"Cajas Y Embalajes Met\u00c1licos",
    "sg:phone":"+34 985 73 20 30",
    "sg:postcode":"33192",
    "sg:province":"Asturias",
    "sg:website":"www.mivisa.com",
    "wof:name":"Mivisa Envases S.a.",
    "wof:placetype":"venue"
},
  "geometry": {"coordinates":[-5.7745718956,43.4596939087],"type":"Point"}
}