{
  "type": "Feature",
  "properties": {
    "addr:full":"Calle de Canillas, 102 Madrid Madrid 28002",
    "addr:housenumber":"102",
    "addr:postcode":"28002",
    "addr:street":"Calle De Canillas",
    "iso:country":"ES",
    "sg:address":"Calle de Canillas, 102",
    "sg:city":"Madrid",
    "sg:orig_category":"Tapicer\u00cdas",
    "sg:phone":"+34 914 13 00 56",
    "sg:postcode":"28002",
    "sg:province":"Madrid",
    "wof:name":"Epora Textil S L",
    "wof:placetype":"venue"
},
  "geometry": {"coordinates":[-3.6685173512,40.4437408447],"type":"Point"}
}