{
  "type": "Feature",
  "properties": {
    "iso:country":"ES",
    "sg:address":"Calle de Polvoranca (de), 18",
    "sg:city":"Fuenlabrada",
    "sg:orig_category":"Asesor\u00cda Sobre Comunicaci\u00d3n De Empresas",
    "sg:phone":"+34 916 15 63 49",
    "sg:postcode":"28945",
    "sg:province":"Madrid",
    "wof:name":"Ceyma C.b.",
    "wof:placetype":"venue"
},
  "geometry": {"coordinates":[-3.7944180965,40.2877120972],"type":"Point"}
}