{
  "type": "Feature",
  "properties": {
    "addr:full":"Plaz Mayor, S/n Moreruela De Tabara Zamora 49148",
    "addr:housenumber":"s",
    "addr:postcode":"49148",
    "addr:street":"Plaz Mayor;/ N",
    "iso:country":"ES",
    "sg:address":"Plaz Mayor, S/n",
    "sg:city":"Moreruela De Tabara",
    "sg:orig_category":"Centros De Educaci\u00d3n Especial",
    "sg:phone":"+34 980 59 53 65",
    "sg:postcode":"49148",
    "sg:province":"Zamora",
    "wof:name":"Colegio Rural Agrupado De Tabara",
    "wof:placetype":"venue"
},
  "geometry": {"coordinates":[-5.8690562248,41.7991104126],"type":"Point"}
}