{
  "type": "Feature",
  "properties": {
    "addr:full":"Disseminat, S/n Folgueroles Barcelona 08519",
    "addr:postcode":"08519",
    "addr:street":"Disseminat S / N",
    "iso:country":"ES",
    "sg:address":"Disseminat, S/n",
    "sg:city":"Folgueroles",
    "sg:orig_category":"Agricultores, Agricultores",
    "sg:phone":"+34 938 86 41 43",
    "sg:postcode":"08519",
    "sg:province":"Barcelona",
    "wof:name":"Raurell S.l.",
    "wof:placetype":"venue"
},
  "geometry": {"coordinates":[-97.78224945069999,45.7040786743],"type":"Point"}
}