{
  "type": "Feature",
  "properties": {
    "iso:country":"ES",
    "sg:address":"Av Isabel La Catolica, 12",
    "sg:city":"Hospitalet Llobregat",
    "sg:orig_category":"M\u00c9dicos: Estomatolog\u00cda",
    "sg:phone":"+34 932 60 23 73",
    "sg:postcode":"08901",
    "sg:province":"Barcelona",
    "wof:name":"Granollers Torrens Montserrat",
    "wof:placetype":"venue"
},
  "geometry": {"coordinates":[2.1058549881,41.3623962402],"type":"Point"}
}