{
  "type": "Feature",
  "properties": {
    "iso:country":"ES",
    "sg:address":"Avda Rey Don Jaime I, S/n",
    "sg:city":"Sax",
    "sg:orig_category":"Cristaler\u00cdas",
    "sg:phone":"+34 965 47 43 21",
    "sg:postcode":"03630",
    "sg:province":"Alicante",
    "wof:name":"Murcia Mazon Modesto",
    "wof:placetype":"venue"
},
  "geometry": {"coordinates":[-0.816043973,38.5371284485],"type":"Point"}
}