{
  "type": "Feature",
  "properties": {
    "iso:country":"ES",
    "sg:address":"Calle de Dos De Mayo, 1",
    "sg:city":"Piedrabuena",
    "sg:orig_category":"Reposter\u00cdas",
    "sg:phone":"+34 926 76 01 14",
    "sg:postcode":"13100",
    "sg:province":"Ciudad Real",
    "wof:name":"Sanchez Paredes Antonio",
    "wof:placetype":"venue"
},
  "geometry": {"coordinates":[-4.1716189384,39.0333557129],"type":"Point"}
}