{
  "type": "Feature",
  "properties": {
    "addr:full":"Calle de Juan Emilio Fernandez Mora, 3 Espartinas Sevilla 41807",
    "addr:housenumber":"3",
    "addr:postcode":"41807",
    "addr:street":"Calle De Juan Emilio Fernandez Mora",
    "iso:country":"ES",
    "sg:address":"Calle de Juan Emilio Fernandez Mora, 3",
    "sg:city":"Espartinas",
    "sg:orig_category":"Cajas Para Embalar",
    "sg:phone":"+34 954 11 44 72",
    "sg:postcode":"41807",
    "sg:province":"Sevilla",
    "wof:name":"Caja Rural Del Sur Sociedad Cooperativa",
    "wof:placetype":"venue"
},
  "geometry": {"coordinates":[-6.1265010834,37.3789978027],"type":"Point"}
}