{
  "type": "Feature",
  "properties": {
    "addr:full":"Calle de Maestro Vitoria, 5 Madrid Madrid 28013",
    "addr:housenumber":"5",
    "addr:postcode":"28013",
    "addr:street":"Calle De Maestro Vitoria",
    "iso:country":"ES",
    "sg:address":"Calle de Maestro Vitoria, 5",
    "sg:city":"Madrid",
    "sg:orig_category":"Fabricaci\u00d3n De Sobres, Bolsas Y Fundas",
    "sg:phone":"+34 915 22 36 42",
    "sg:postcode":"28013",
    "sg:province":"Madrid",
    "wof:name":"Galeote Callejas Jose",
    "wof:placetype":"venue"
},
  "geometry": {"coordinates":[-3.7054049969,40.4185523987],"type":"Point"}
}