{
  "type": "Feature",
  "properties": {
    "addr:full":"Calle de Quintana, 27 Madrid Madrid 28008",
    "addr:housenumber":"27",
    "addr:postcode":"madrid;28008",
    "addr:street":"Calle De Quintana",
    "iso:country":"ES",
    "sg:address":"Calle de Quintana, 27",
    "sg:city":"Madrid",
    "sg:orig_category":"Teatro, Ballet, Danza (agrupaciones, Compa\u00d1\u00cdas)",
    "sg:phone":"+34 915 47 58 30",
    "sg:postcode":"28008",
    "sg:province":"Madrid",
    "sg:website":"www.elviraherrera.com",
    "wof:name":"Mucho Mas Que Dos S.l.",
    "wof:placetype":"venue"
},
  "geometry": {"coordinates":[-3.7191181183,40.4269714355],"type":"Point"}
}