{
  "type": "Feature",
  "properties": {
    "iso:country":"ES",
    "sg:address":"Calle de Panorama, 10",
    "sg:city":"Malaga",
    "sg:orig_category":"Ense\u00d1anza: Idiomas",
    "sg:phone":"+34 952 29 34 50",
    "sg:postcode":"29018",
    "sg:province":"M\u00e1laga",
    "wof:name":"Escuela De Espa\u00f1ol Dialogo S.l.",
    "wof:placetype":"venue"
},
  "geometry": {"coordinates":[-4.3797211647,36.7328643799],"type":"Point"}
}