{
  "type": "Feature",
  "properties": {
    "iso:country":"ES",
    "sg:address":"Ctra. Santander-torrelavega, S/n",
    "sg:city":"Requejada",
    "sg:orig_category":"Transporte En General",
    "sg:phone":"+34 942 84 51 14",
    "sg:postcode":"39312",
    "sg:province":"Cantabria",
    "wof:name":"Norteva S.l.",
    "wof:placetype":"venue"
},
  "geometry": {"coordinates":[-4.0284891129,43.3888206482],"type":"Point"}
}