{
  "type": "Feature",
  "properties": {
    "addr:full":"Pase Chopera (de La), 45 Alcobendas Madrid 28100",
    "addr:postcode":"28100",
    "iso:country":"ES",
    "sg:address":"Pase Chopera (de La), 45",
    "sg:city":"Alcobendas",
    "sg:orig_category":"Promotores Constructores",
    "sg:phone":"+34 916 61 37 95",
    "sg:postcode":"28100",
    "sg:province":"Madrid",
    "wof:name":"Mgi-95 S.l.",
    "wof:placetype":"venue"
},
  "geometry": {"coordinates":[-3.6424920559,40.542137146],"type":"Point"}
}