{
  "type": "Feature",
  "properties": {
    "iso:country":"ES",
    "sg:address":"Avda Montgo, 8",
    "sg:city":"Denia",
    "sg:orig_category":"\u00d3ptica: Instrumentos (fabricaci\u00d3n)",
    "sg:phone":"+34 966 42 55 84",
    "sg:postcode":"03700",
    "sg:province":"Alicante",
    "wof:name":"Optica Perez Buigues S.l.",
    "wof:placetype":"venue"
},
  "geometry": {"coordinates":[0.1025509983,38.8365325928],"type":"Point"}
}