{
  "type": "Feature",
  "properties": {
    "addr:full":"Balcaide, 8 Balcaide La Coru\u00f1a 15895",
    "addr:housenumber":"8",
    "addr:postcode":"15895",
    "addr:street":"Balcaide;La Corun\u0303A",
    "iso:country":"ES",
    "sg:address":"Balcaide, 8",
    "sg:city":"Balcaide",
    "sg:orig_category":"Alimentaci\u00d3n General (al Por Menor)",
    "sg:phone":"+34 981 54 80 82",
    "sg:postcode":"15895",
    "sg:province":"La Coru\u00f1a",
    "wof:name":"Gomez Furelos Amelia Alcira",
    "wof:placetype":"venue"
},
  "geometry": {"coordinates":[-8.5794343948,42.8416137695],"type":"Point"}
}