{
  "type": "Feature",
  "properties": {
    "iso:country":"ES",
    "sg:address":"Urb Marinasol, 3",
    "sg:city":"Manga Mar Menor",
    "sg:orig_category":"Inmobiliaria (agencias)",
    "sg:phone":"+34 968 14 06 56",
    "sg:postcode":"30380",
    "sg:province":"Murcia",
    "wof:name":"Inmobiliaria Mavina Alonso S.l.",
    "wof:placetype":"venue"
},
  "geometry": {"coordinates":[-0.7281540036,37.6686553955],"type":"Point"}
}