{
  "type": "Feature",
  "properties": {
    "iso:country":"ES",
    "sg:address":"Ctra Villalengua, S/n",
    "sg:city":"Cervera De La Ca\u00e7ada",
    "sg:orig_category":"Productores Recolectores, Venta Directa De Vinos",
    "sg:phone":"+34 976 89 92 06",
    "sg:postcode":"50312",
    "sg:province":"Zaragoza",
    "wof:name":"Cooperativa Del Campo San Gregorio",
    "wof:placetype":"venue"
},
  "geometry": {"coordinates":[-1.7341270447,41.4341430664],"type":"Point"}
}