{
  "type": "Feature",
  "properties": {
    "iso:country":"ES",
    "sg:address":"Calle de Alamillos (de Los), 11",
    "sg:city":"San Sebastian De Los Reyes",
    "sg:orig_category":"Empresas De Carpinter\u00cda Met\u00c1lica",
    "sg:phone":"+34 916 52 59 05",
    "sg:postcode":"28700",
    "sg:province":"Madrid",
    "wof:name":"Hernandez Perez Tomas",
    "wof:placetype":"venue"
},
  "geometry": {"coordinates":[-3.6268484592,40.5571136475],"type":"Point"}
}