{
  "type": "Feature",
  "properties": {
    "addr:full":"Avda Estacion, 73 Benimamet-beniferri Valencia 46035",
    "addr:housenumber":"73",
    "addr:postcode":"46035",
    "addr:street":"Avda Estacion",
    "iso:country":"ES",
    "sg:address":"Avda Estacion, 73",
    "sg:city":"Benimamet-beniferri",
    "sg:orig_category":"Estudios, Instalaci\u00d3n De Climatizaci\u00d3n",
    "sg:phone":"+34 963 46 07 16",
    "sg:postcode":"46035",
    "sg:province":"Valencia",
    "wof:name":"Air Tecnic C. B.",
    "wof:placetype":"venue"
},
  "geometry": {"coordinates":[-0.3768048882,39.4702377319],"type":"Point"}
}