{
  "type": "Feature",
  "properties": {
    "addr:full":"Ctra Sos, S/n Sadaba Zaragoza 50670",
    "addr:postcode":"50670",
    "addr:street":"Ctra Sos S / N Sadaba",
    "iso:country":"ES",
    "sg:address":"Ctra Sos, S/n",
    "sg:city":"Sadaba",
    "sg:orig_category":"Hospitales",
    "sg:phone":"+34 976 67 54 79",
    "sg:postcode":"50670",
    "sg:province":"Zaragoza",
    "wof:name":"Ejea Sociedad Cooperativa Ltda",
    "wof:placetype":"venue"
},
  "geometry": {"coordinates":[-1.2746690512,42.2855453491],"type":"Point"}
}