{
  "type": "Feature",
  "properties": {
    "iso:country":"ES",
    "sg:address":"Calle de Muelle, 6",
    "sg:city":"Puertollano",
    "sg:orig_category":"Sociedades, Compa\u00d1\u00cdas Aseguradoras",
    "sg:phone":"+34 926 41 08 18",
    "sg:postcode":"13500",
    "sg:province":"Ciudad Real",
    "wof:name":"Ocaso S.a. Compa\u00f1ia De Seguros Y Reaseguros",
    "wof:placetype":"venue"
},
  "geometry": {"coordinates":[-4.1097240448,38.6912155151],"type":"Point"}
}