{
  "type": "Feature",
  "properties": {
    "addr:full":"Ctra Nal Trescientos Cuarenta, S/n Xativa Valencia 46800",
    "addr:housenumber":"s",
    "addr:postcode":"46800",
    "addr:street":"Ctra Nal Trescientos Cuarenta;/ N",
    "iso:country":"ES",
    "sg:address":"Ctra Nal Trescientos Cuarenta, S/n",
    "sg:city":"Xativa",
    "sg:orig_category":"Agentes, Concesionarios Y Sucursales De Veh\u00cdculos",
    "sg:phone":"+34 962 28 70 41",
    "sg:postcode":"46800",
    "sg:province":"Valencia",
    "wof:name":"Comercial Stabense S.a.",
    "wof:placetype":"venue"
},
  "geometry": {"coordinates":[-0.5200830102,38.9934272766],"type":"Point"}
}