{
  "type": "Feature",
  "properties": {
    "iso:country":"ES",
    "sg:address":"Carrer de Anselm Clave, 141",
    "sg:city":"Pla",
    "sg:orig_category":"Panader\u00cdas, Panader\u00cdas",
    "sg:phone":"+34 938 41 43 11",
    "sg:postcode":"08186",
    "sg:province":"Barcelona",
    "wof:name":"Sociedad General De Aperitivos S.l.",
    "wof:placetype":"venue"
},
  "geometry": {"coordinates":[2.2382690907,41.612449646],"type":"Point"}
}