{
  "type": "Feature",
  "properties": {
    "iso:country":"ES",
    "sg:address":"Avda Palmeras Las, 3",
    "sg:city":"Arroyo De La Miel-benalmadena Costa",
    "sg:orig_category":"Cr\u00cda De Animales",
    "sg:phone":"+34 952 96 47 83",
    "sg:postcode":"29630",
    "sg:province":"M\u00e1laga",
    "wof:name":"Martin Moreno Cristina",
    "wof:placetype":"venue"
},
  "geometry": {"coordinates":[-4.521381855,36.5971374512],"type":"Point"}
}