{
  "type": "Feature",
  "properties": {
    "addr:full":"Avda Pio Xii, 10 Logro\u00f1o La Rioja 26003",
    "addr:housenumber":"10",
    "addr:postcode":"26003",
    "addr:street":"Avda Pio Xii;Rioja",
    "iso:country":"ES",
    "sg:address":"Avda Pio Xii, 10",
    "sg:city":"Logro\u00f1o",
    "sg:orig_category":"Asociaciones Humanitarias, De Cooperaci\u00d3n, De Acci\u00d3n Social",
    "sg:phone":"+34 941 24 78 76",
    "sg:postcode":"26003",
    "sg:province":"La Rioja",
    "wof:name":"Arpa",
    "wof:placetype":"venue"
},
  "geometry": {"coordinates":[-2.4447436333,42.4605903625],"type":"Point"}
}