{
  "type": "Feature",
  "properties": {
    "addr:full":"Carrer de Sant Antoni Maria Claret, 65 Barcelona Barcelona 08025",
    "addr:housenumber":"65",
    "addr:postcode":"08025",
    "addr:street":"Carrer De Sant Antoni Maria Claret",
    "iso:country":"ES",
    "sg:address":"Carrer de Sant Antoni Maria Claret, 65",
    "sg:city":"Barcelona",
    "sg:orig_category":"Servicios De Higiene Y Peluquer\u00cda Para Perros Y Gatos",
    "sg:phone":"+34 934 56 53 49",
    "sg:postcode":"08025",
    "sg:province":"Barcelona",
    "wof:name":"Mallat Alorda Lourdes",
    "wof:placetype":"venue"
},
  "geometry": {"coordinates":[2.168694973,41.4071922302],"type":"Point"}
}