{
  "type": "Feature",
  "properties": {
    "addr:full":"Calle de Mussol, 2 Terrassa Barcelona 08224",
    "addr:housenumber":"2",
    "addr:postcode":"08224",
    "addr:street":"Calle De Mussol",
    "iso:country":"ES",
    "sg:address":"Calle de Mussol, 2",
    "sg:city":"Terrassa",
    "sg:orig_category":"Comerciantes Al Por Mayor De Vinos, Licores Y Alcoholes",
    "sg:phone":"+34 937 88 40 00",
    "sg:postcode":"08224",
    "sg:province":"Barcelona",
    "wof:name":"Rivas Gonzalez Ismael",
    "wof:placetype":"venue"
},
  "geometry": {"coordinates":[1.9838910103,41.5381393433],"type":"Point"}
}