{
  "type": "Feature",
  "properties": {
    "iso:country":"ES",
    "sg:address":"Calle de Real, 94",
    "sg:city":"Castilleja Cuesta",
    "sg:orig_category":"Cajas Para Embalar",
    "sg:phone":"+34 954 16 03 11",
    "sg:postcode":"41950",
    "sg:province":"Sevilla",
    "wof:name":"Caja Rural Del Sur Sociedad Cooperativa",
    "wof:placetype":"venue"
},
  "geometry": {"coordinates":[-6.0546522141,37.386089325],"type":"Point"}
}