{
  "type": "Feature",
  "properties": {
    "iso:country":"ES",
    "sg:address":"Calle de Benigaslo, 14",
    "sg:city":"Vall D'uixo",
    "sg:orig_category":"Ingeniero",
    "sg:phone":"+34 964 69 63 11",
    "sg:postcode":"12600",
    "sg:province":"Castell\u00f3n",
    "wof:name":"Molina Sebastian Joaquin",
    "wof:placetype":"venue"
},
  "geometry": {"coordinates":[-0.2238661945,39.8229293823],"type":"Point"}
}