{
  "type": "Feature",
  "properties": {
    "addr:full":"Calle de La Isla, 20 Villasana Mena Burgos 09580",
    "addr:housenumber":"20",
    "addr:postcode":"09580",
    "addr:street":"Calle De La Isla;Villasana Mena",
    "iso:country":"ES",
    "sg:address":"Calle de La Isla, 20",
    "sg:city":"Villasana Mena",
    "sg:orig_category":"Institutos De Belleza",
    "sg:phone":"+34 947 12 62 90",
    "sg:postcode":"09580",
    "sg:province":"Burgos",
    "wof:name":"Fernandez Saiz Maria Juana",
    "wof:placetype":"venue"
},
  "geometry": {"coordinates":[-3.2830290794,43.1012382507],"type":"Point"}
}