{
  "type": "Feature",
  "properties": {
    "addr:full":"Calle de Ferradal (el), 45 Toral De Los Vados Le\u00f3n 24560",
    "addr:housenumber":"45",
    "addr:postcode":"24560",
    "addr:street":"Calle De Ferradal El",
    "iso:country":"ES",
    "sg:address":"Calle de Ferradal (el), 45",
    "sg:city":"Toral De Los Vados",
    "sg:orig_category":"M\u00c1rmoles, Granitos Y Piedras Naturales",
    "sg:phone":"+34 987 54 46 81",
    "sg:postcode":"24560",
    "sg:province":"Le\u00f3n",
    "wof:name":"Vidal Vidal Jose",
    "wof:placetype":"venue"
},
  "geometry": {"coordinates":[-6.7791590691,42.5411300659],"type":"Point"}
}