{
  "type": "Feature",
  "properties": {
    "iso:country":"ES",
    "sg:address":"Pase Conde De Sepulveda (del), 30",
    "sg:city":"Segovia",
    "sg:orig_category":"Promotores Constructores",
    "sg:phone":"+34 921 42 35 17",
    "sg:postcode":"40006",
    "sg:province":"Segovia",
    "wof:name":"Marcos Bravo Pedro Luis",
    "wof:placetype":"venue"
},
  "geometry": {"coordinates":[-4.1145300865,40.9377479553],"type":"Point"}
}