{
  "type": "Feature",
  "properties": {
    "iso:country":"ES",
    "sg:address":"Avda Mahia, S/n",
    "sg:city":"Bertamirans",
    "sg:orig_category":"Florister\u00cdas",
    "sg:phone":"+34 981 89 10 29",
    "sg:postcode":"15220",
    "sg:province":"La Coru\u00f1a",
    "wof:name":"Lucio Raris Garcia Y Otro S.c.",
    "wof:placetype":"venue"
},
  "geometry": {"coordinates":[-8.6523752213,42.8594512939],"type":"Point"}
}