{
  "type": "Feature",
  "properties": {
    "iso:country":"ES",
    "sg:address":"Carrer de Museu, 17",
    "sg:city":"Granollers",
    "sg:orig_category":"Abogados",
    "sg:phone":"+34 938 70 46 89",
    "sg:postcode":"08401",
    "sg:province":"Barcelona",
    "wof:name":"Col.lectiu Aide S.a.",
    "wof:placetype":"venue"
},
  "geometry": {"coordinates":[2.2859129906,41.607170105],"type":"Point"}
}