{
  "type": "Feature",
  "properties": {
    "iso:country":"ES",
    "sg:address":"Carrer de Cardo, 11",
    "sg:city":"Barcelona",
    "sg:orig_category":"Empresarios Y Productoras De Espect\u00c1culos",
    "sg:phone":"+34 933 30 42 53",
    "sg:postcode":"08028",
    "sg:province":"Barcelona",
    "wof:name":"Jingo Music Sl",
    "wof:placetype":"venue"
},
  "geometry": {"coordinates":[2.1325900555,41.3767204285],"type":"Point"}
}