{
  "type": "Feature",
  "properties": {
    "iso:country":"ES",
    "sg:address":"Poli Vega De Arriba, S/n",
    "sg:city":"Mieres",
    "sg:orig_category":"Venta, Montaje De Neum\u00c1ticos",
    "sg:phone":"+34 985 46 24 56",
    "sg:postcode":"33600",
    "sg:province":"Asturias",
    "sg:website":"www.neumaticosfanjul-servirueda.com",
    "wof:name":"Neumaticos Fanjul S.l.",
    "wof:placetype":"venue"
},
  "geometry": {"coordinates":[-5.7791390419,43.2342262268],"type":"Point"}
}