{
  "type": "Feature",
  "properties": {
    "addr:full":"Calle de Balsa, 9 Bullas Murcia 30180",
    "addr:housenumber":"9",
    "addr:postcode":"30180",
    "addr:street":"Calle De Balsa",
    "iso:country":"ES",
    "sg:address":"Calle de Balsa, 9",
    "sg:city":"Bullas",
    "sg:orig_category":"Peluqueros: De Se\u00d1oras",
    "sg:phone":"+34 968 65 21 12",
    "sg:postcode":"30180",
    "sg:province":"Murcia",
    "wof:name":"Lopez Sanchez Miguel",
    "wof:placetype":"venue"
},
  "geometry": {"coordinates":[-1.6699306965,38.0505409241],"type":"Point"}
}