{
  "type": "Feature",
  "properties": {
    "iso:country":"ES",
    "sg:address":"Calle de Garcilaso De La Vega, 15",
    "sg:city":"Santa Cruz De Tenerife",
    "sg:orig_category":"Muebles, Minoristas",
    "sg:phone":"+34 922 21 84 18",
    "sg:postcode":"38005",
    "sg:province":"Santa Cruz De Tenerife",
    "wof:name":"Aleman Rodrigo Francisco",
    "wof:placetype":"venue"
},
  "geometry": {"coordinates":[-16.2580566406,28.4614944458],"type":"Point"}
}