{
  "type": "Feature",
  "properties": {
    "addr:full":"Carrer de Alfou, 18 Cardedeu Barcelona 08440",
    "addr:housenumber":"18",
    "addr:postcode":"08440",
    "addr:street":"Carrer De Alfou",
    "iso:country":"ES",
    "sg:address":"Carrer de Alfou, 18",
    "sg:city":"Cardedeu",
    "sg:orig_category":"Comercio, Reparaci\u00d3n De Motocicletas, Bicicletas Y Piezas Sueltas",
    "sg:phone":"+34 938 71 20 30",
    "sg:postcode":"08440",
    "sg:province":"Barcelona",
    "wof:name":"Casanovas Vicens Juan",
    "wof:placetype":"venue"
},
  "geometry": {"coordinates":[2.3624520302,41.6418571472],"type":"Point"}
}