{
  "type": "Feature",
  "properties": {
    "iso:country":"ES",
    "sg:address":"Av Madrid, 197",
    "sg:city":"Barcelona",
    "sg:orig_category":"Ense\u00d1anza: Profesiones Art\u00cdsticas",
    "sg:phone":"+34 934 91 04 94",
    "sg:postcode":"08014",
    "sg:province":"Barcelona",
    "wof:name":"Foto Grup S.l.",
    "wof:placetype":"venue"
},
  "geometry": {"coordinates":[2.1339330673,41.3813858032],"type":"Point"}
}