{
  "type": "Feature",
  "properties": {
    "iso:country":"ES",
    "sg:address":"Calle de Felipe Orlando, 4",
    "sg:city":"Benalmadena",
    "sg:orig_category":"Droguer\u00cdas (al Por Menor)",
    "sg:phone":"+34 952 44 89 18",
    "sg:postcode":"29639",
    "sg:province":"M\u00e1laga",
    "wof:name":"Villalba Zaragoza Jesus",
    "wof:placetype":"venue"
},
  "geometry": {"coordinates":[-4.5734891891,36.5959014893],"type":"Point"}
}