{
  "type": "Feature",
  "properties": {
    "addr:full":"Ptge Toledo, 14 Barcelona Barcelona 08014",
    "addr:housenumber":"14",
    "addr:postcode":"08014",
    "addr:street":"Ptge Toledo",
    "iso:country":"ES",
    "sg:address":"Ptge Toledo, 14",
    "sg:city":"Barcelona",
    "sg:orig_category":"Asilos De Ancianos. Centros Privados",
    "sg:phone":"+34 934 22 77 93",
    "sg:postcode":"08014",
    "sg:province":"Barcelona",
    "wof:name":"Parroquia De Sant Medir",
    "wof:placetype":"venue"
},
  "geometry": {"coordinates":[2.1362299919,41.3702125549],"type":"Point"}
}