{
  "type": "Feature",
  "properties": {
    "iso:country":"ES",
    "sg:address":"Calle de Vicente Alexandre, 2",
    "sg:city":"Cieza",
    "sg:orig_category":"Artesan\u00cda",
    "sg:phone":"+34 968 76 03 59",
    "sg:postcode":"30530",
    "sg:province":"Murcia",
    "wof:name":"Penalva Lopez Diego",
    "wof:placetype":"venue"
},
  "geometry": {"coordinates":[-1.4117729664,38.2349014282],"type":"Point"}
}