{
  "type": "Feature",
  "properties": {
    "addr:full":"C/ Jose Bernad Amoros, 118 Elche Alicante 03205",
    "addr:housenumber":"118",
    "addr:postcode":"03205",
    "addr:street":"C / Jose Bernad Amoros",
    "iso:country":"ES",
    "sg:address":"C/ Jose Bernad Amoros, 118",
    "sg:city":"Elche",
    "sg:orig_category":"Fisioterapia",
    "sg:phone":"+34 966 67 00 08",
    "sg:postcode":"03205",
    "sg:province":"Alicante",
    "wof:name":"Mora Pastor Carmen",
    "wof:placetype":"venue"
},
  "geometry": {"coordinates":[-0.7132239938,38.2659034729],"type":"Point"}
}