{
  "type": "Feature",
  "properties": {
    "addr:full":"Itziar Bidea, 8 Deba Guip\u00f9zcoa 20820",
    "addr:housenumber":"8",
    "addr:postcode":"20820",
    "addr:street":"Itziar Bidea;Guipu\u0300Zcoa",
    "iso:country":"ES",
    "sg:address":"Itziar Bidea, 8",
    "sg:city":"Deba",
    "sg:classifiers":[
        {
            "category":"Food & Beverages",
            "subcategory":"Candy",
            "type":"Retail Goods"
        }
    ],
    "sg:phone":"+34 943 19 24 18",
    "sg:postcode":"20820",
    "sg:province":"Guip\u00f9zcoa",
    "sg:tags":[
        "confiter\u00cdas",
        "y",
        "de",
        "fabricaci\u00d3n",
        "chocolate"
    ],
    "wof:name":"Aldalur Lazcano Jose Luis",
    "wof:placetype":"venue"
},
  "geometry": {"coordinates":[-2.3537120819,43.2911949158],"type":"Point"}
}