{
  "type": "Feature",
  "properties": {
    "addr:full":"Juan Perez De Zurita, 3 La Golondrina C\u00f3rdoba 14710",
    "addr:housenumber":"3",
    "addr:postcode":"14710",
    "addr:street":"La Golondrina Co\u0301Rdoba",
    "iso:country":"ES",
    "sg:address":"Juan Perez De Zurita, 3",
    "sg:city":"La Golondrina",
    "sg:orig_category":"Molduras, Junquillos, Listones Y Molduras Perforadas",
    "sg:phone":"+34 957 32 45 06",
    "sg:postcode":"14710",
    "sg:province":"C\u00f3rdoba",
    "wof:name":"Garcia Sanchez Enrique",
    "wof:placetype":"venue"
},
  "geometry": {"coordinates":[-4.9146289825,37.8490753174],"type":"Point"}
}