{
  "type": "Feature",
  "properties": {
    "addr:full":"Disseminats, 12 Palafolls Barcelona 08389",
    "addr:housenumber":"12",
    "addr:postcode":"08389",
    "addr:street":"Disseminats",
    "iso:country":"ES",
    "sg:address":"Disseminats, 12",
    "sg:city":"Palafolls",
    "sg:orig_category":"Material Y Suministros Para Horticultura, Arboricultura",
    "sg:phone":"+34 937 64 10 00",
    "sg:postcode":"08389",
    "sg:province":"Barcelona",
    "wof:name":"Aldrufeu Casas Juan",
    "wof:placetype":"venue"
},
  "geometry": {"coordinates":[2.7331926823,41.6734924316],"type":"Point"}
}