{
  "type": "Feature",
  "properties": {
    "iso:country":"ES",
    "sg:address":"Calle de Jose Maria Pereda, 15",
    "sg:city":"Madrid",
    "sg:orig_category":"Andamiajes Y Escaleras De Mano (fabricaci\u00d3n, Al Por Mayor)",
    "sg:phone":"+34 914 08 83 52",
    "sg:postcode":"28017",
    "sg:province":"Madrid",
    "wof:name":"Feito Garcia Felipe",
    "wof:placetype":"venue"
},
  "geometry": {"coordinates":[-3.6481189728,40.4319610596],"type":"Point"}
}