{
  "type": "Feature",
  "properties": {
    "addr:full":"Calle de Fromista, 6 Fuenlabrada Madrid 28941",
    "addr:housenumber":"6",
    "addr:postcode":"28941",
    "addr:street":"Calle De Fromista",
    "iso:country":"ES",
    "sg:address":"Calle de Fromista, 6",
    "sg:city":"Fuenlabrada",
    "sg:orig_category":"Caf\u00c9s, Bares, Cervecer\u00cdas",
    "sg:phone":"+34 916 15 76 18",
    "sg:postcode":"28941",
    "sg:province":"Madrid",
    "wof:name":"Sanchez Casillas Sebastian",
    "wof:placetype":"venue"
},
  "geometry": {"coordinates":[-3.8043019772,40.2952461243],"type":"Point"}
}