{
  "type": "Feature",
  "properties": {
    "iso:country":"ES",
    "sg:address":"C/ Santa Rosa, 4",
    "sg:city":"Alcoi",
    "sg:orig_category":"Cajas De Ahorro",
    "sg:phone":"+34 965 33 10 67",
    "sg:postcode":"03802",
    "sg:province":"Alicante",
    "wof:name":"Caja De Ahorros De Valencia Castellon Y Alicante",
    "wof:placetype":"venue"
},
  "geometry": {"coordinates":[-0.4839929938,38.6984100342],"type":"Point"}
}