{
  "type": "Feature",
  "properties": {
    "iso:country":"ES",
    "sg:address":"Avda Europa, 8",
    "sg:city":"Coslada",
    "sg:orig_category":"Mensajer\u00cda Express, Portes Internacionales",
    "sg:phone":"+34 902 11 10 21",
    "sg:postcode":"28820",
    "sg:province":"Madrid",
    "sg:website":"www.chronoexpres.com",
    "wof:name":"Chronoexpres S.a.",
    "wof:placetype":"venue"
},
  "geometry": {"coordinates":[-3.5622689724,40.4341888428],"type":"Point"}
}