{
  "type": "Feature",
  "properties": {
    "addr:full":"Carrer de Camp, 23 Barcelona Barcelona 08022",
    "addr:housenumber":"23",
    "addr:postcode":"08022",
    "addr:street":"Carrer De Camp",
    "iso:country":"ES",
    "sg:address":"Carrer de Camp, 23",
    "sg:city":"Barcelona",
    "sg:orig_category":"Urbanistas",
    "sg:phone":"+34 932 53 14 07",
    "sg:postcode":"08022",
    "sg:province":"Barcelona",
    "wof:name":"Guillen & Associats S.l.",
    "wof:placetype":"venue"
},
  "geometry": {"coordinates":[2.1370038986,41.402507782],"type":"Point"}
}