{
  "type": "Feature",
  "properties": {
    "iso:country":"ES",
    "sg:address":"Calle de Brujula, 32",
    "sg:city":"Madrid",
    "sg:orig_category":"Inmobiliaria (agencias)",
    "sg:phone":"+34 917 40 05 33",
    "sg:postcode":"28023",
    "sg:province":"Madrid",
    "wof:name":"Casal Consulting Inmobiliario S.l.",
    "wof:placetype":"venue"
},
  "geometry": {"coordinates":[-3.7868206501,40.4549636841],"type":"Point"}
}