{
  "type": "Feature",
  "properties": {
    "iso:country":"ES",
    "sg:address":"Pase Ramon Y Cajal, 55",
    "sg:city":"Huesca",
    "sg:orig_category":"Alquiler De V\u00cddeo",
    "sg:phone":"+34 974 24 61 49",
    "sg:postcode":"22006",
    "sg:province":"Huesca",
    "wof:name":"Osca All-shops S.l.",
    "wof:placetype":"venue"
},
  "geometry": {"coordinates":[-0.3984000087,42.1398277283],"type":"Point"}
}