{
  "type": "Feature",
  "properties": {
    "iso:country":"ES",
    "sg:address":"Avda. Arteixo, 11",
    "sg:city":"A Coru\u00f1a",
    "sg:orig_category":"M\u00c9dicos: Otorrinolaringolog\u00cda",
    "sg:phone":"+34 981 26 16 07",
    "sg:postcode":"15004",
    "sg:province":"La Coru\u00f1a",
    "wof:name":"Alvarez Calle Pablo",
    "wof:placetype":"venue"
},
  "geometry": {"coordinates":[-8.4095659256,43.3630256653],"type":"Point"}
}