{
  "type": "Feature",
  "properties": {
    "addr:full":"Avda Marques De Paterna, 2 Merida Badajoz 06800",
    "addr:housenumber":"2",
    "addr:postcode":"06800",
    "addr:street":"Avda Marques De Paterna",
    "iso:country":"ES",
    "sg:address":"Avda Marques De Paterna, 2",
    "sg:city":"Merida",
    "sg:orig_category":"Farmacias",
    "sg:phone":"+34 924 31 28 09",
    "sg:postcode":"06800",
    "sg:province":"Badajoz",
    "wof:name":"Hernandez Fernandez Fernando",
    "wof:placetype":"venue"
},
  "geometry": {"coordinates":[-6.3320841789,38.9216270447],"type":"Point"}
}