{
  "type": "Feature",
  "properties": {
    "addr:full":"Eztegara Pasealekua, 26 Bera Navarra 31780",
    "addr:housenumber":"26",
    "addr:postcode":"31780",
    "addr:street":"Eztegara Pasealekua",
    "iso:country":"ES",
    "sg:address":"Eztegara Pasealekua, 26",
    "sg:city":"Bera",
    "sg:orig_category":"Fotocopias, Reprograf\u00cda",
    "sg:phone":"+34 948 63 15 21",
    "sg:postcode":"31780",
    "sg:province":"Navarra",
    "wof:name":"Sarasola Salegui Xabier",
    "wof:placetype":"venue"
},
  "geometry": {"coordinates":[-1.6813839674,43.2808914185],"type":"Point"}
}