{
  "type": "Feature",
  "properties": {
    "addr:full":"Calle de Carrera, 28 Villanueva Serena Badajoz 06700",
    "addr:postcode":"06700",
    "addr:street":"Calle De Carrera 28",
    "iso:country":"ES",
    "sg:address":"Calle de Carrera, 28",
    "sg:city":"Villanueva Serena",
    "sg:orig_category":"Abogados",
    "sg:phone":"+34 924 84 78 05",
    "sg:postcode":"06700",
    "sg:province":"Badajoz",
    "wof:name":"Dominguez Cidoncha Jose Manuel",
    "wof:placetype":"venue"
},
  "geometry": {"coordinates":[-5.7995071411,38.9749526978],"type":"Point"}
}