{
  "type": "Feature",
  "properties": {
    "addr:full":"Carr Terri (del), S/n Cornella Terri Girona 17844",
    "addr:housenumber":"terri",
    "addr:postcode":"17844",
    "addr:street":"Carr Terri Del S / N Cornella",
    "iso:country":"ES",
    "sg:address":"Carr Terri (del), S/n",
    "sg:city":"Cornella Terri",
    "sg:orig_category":"Congelados: Productos Alimentarios (al Por Menor)",
    "sg:phone":"+34 972 59 42 00",
    "sg:postcode":"17844",
    "sg:province":"Girona",
    "wof:name":"Congelats Olot S.l.",
    "wof:placetype":"venue"
},
  "geometry": {"coordinates":[2.8163619041,42.0891227722],"type":"Point"}
}