{
  "type": "Feature",
  "properties": {
    "addr:full":"Calle de Comedias, 11 Malaga M\u00e1laga 29008",
    "addr:housenumber":"11",
    "addr:postcode":"29008",
    "addr:street":"Calle De Comedias;Ma\u0301Laga",
    "iso:country":"ES",
    "sg:address":"Calle de Comedias, 11",
    "sg:city":"Malaga",
    "sg:orig_category":"Asesor\u00cda Sobre Comunicaci\u00d3n De Empresas",
    "sg:phone":"+34 952 22 06 04",
    "sg:postcode":"29008",
    "sg:province":"M\u00e1laga",
    "wof:name":"Diaz Pineda Antonio",
    "wof:placetype":"venue"
},
  "geometry": {"coordinates":[-4.4214878082,36.7229347229],"type":"Point"}
}