{
  "type": "Feature",
  "properties": {
    "addr:full":"Ronda Del Lejio, 55 Zarza Granadilla C\u00e1ceres 10710",
    "addr:housenumber":"55;granadilla",
    "addr:postcode":"10710",
    "addr:street":"Ronda Del Lejio;Ca\u0301Ceres",
    "iso:country":"ES",
    "sg:address":"Ronda Del Lejio, 55",
    "sg:city":"Zarza Granadilla",
    "sg:orig_category":"Cerrajer\u00cda, Ferrallista",
    "sg:phone":"+34 927 48 60 78",
    "sg:postcode":"10710",
    "sg:province":"C\u00e1ceres",
    "wof:name":"Hijos De Luciano Benito C.b.",
    "wof:placetype":"venue"
},
  "geometry": {"coordinates":[-6.0491437912,40.2362861633],"type":"Point"}
}