{
  "type": "Feature",
  "properties": {
    "addr:full":"Rua Republica Arxentina, 30 Ferrol A Coru\u00f1a 15404",
    "addr:housenumber":"30",
    "addr:postcode":"15404",
    "addr:street":"Rua Republica Arxentina;A Corun\u0303A",
    "iso:country":"ES",
    "sg:address":"Rua Republica Arxentina, 30",
    "sg:city":"Ferrol",
    "sg:orig_category":"Comercio De Mobiliario De Oficina",
    "sg:phone":"+34 981 31 03 54",
    "sg:postcode":"15404",
    "sg:province":"A Coru\u00f1a",
    "sg:website":"www.tecnicadeoficina.com",
    "wof:name":"Tecnica De Oficina S.l.",
    "wof:placetype":"venue"
},
  "geometry": {"coordinates":[-8.2173185349,43.4892921448],"type":"Point"}
}