{
  "type": "Feature",
  "properties": {
    "iso:country":"ES",
    "sg:address":"Calle de Partamunt, 2",
    "sg:city":"Rafales",
    "sg:orig_category":"Centros De Educaci\u00d3n Especial",
    "sg:phone":"+34 978 85 61 00",
    "sg:postcode":"44589",
    "sg:province":"Teruel",
    "wof:name":"C.r.a.de La Fresneda-d.g.a.-rafales",
    "wof:placetype":"venue"
},
  "geometry": {"coordinates":[0.0196839999,40.8376350403],"type":"Point"}
}