{
  "type": "Feature",
  "properties": {
    "addr:full":"Carr Occitania, S/n Badalona Barcelona 08911",
    "addr:housenumber":"s / n",
    "addr:postcode":"08911",
    "addr:street":"Carr Occitania",
    "iso:country":"ES",
    "sg:address":"Carr Occitania, S/n",
    "sg:city":"Badalona",
    "sg:orig_category":"Fabricaci\u00d3n De Muebles",
    "sg:phone":"+34 934 64 12 59",
    "sg:postcode":"08911",
    "sg:province":"Barcelona",
    "wof:name":"Armarios Closed S.l.",
    "wof:placetype":"venue"
},
  "geometry": {"coordinates":[2.2540593147,41.4585838318],"type":"Point"}
}