{
  "type": "Feature",
  "properties": {
    "addr:full":"Avda Cantabria, 39 Madrid Madrid 28042",
    "addr:housenumber":"39",
    "addr:postcode":"madrid;28042",
    "addr:street":"Avda Cantabria",
    "iso:country":"ES",
    "sg:address":"Avda Cantabria, 39",
    "sg:city":"Madrid",
    "sg:orig_category":"Frutas, Legumbres Frescas Y Tempranas (al Por Menor)",
    "sg:phone":"+34 917 47 07 78",
    "sg:postcode":"28042",
    "sg:province":"Madrid",
    "wof:name":"Silvestre Nu\u00f1ez Mateo",
    "wof:placetype":"venue"
},
  "geometry": {"coordinates":[-3.5851099491,40.4577140808],"type":"Point"}
}