{
  "type": "Feature",
  "properties": {
    "addr:full":"Calle de Joaquin Ballester, 2 Valencia Valencia 46009",
    "addr:housenumber":"2",
    "addr:postcode":"46009",
    "addr:street":"Calle De Joaquin Ballester",
    "iso:country":"ES",
    "sg:address":"Calle de Joaquin Ballester, 2",
    "sg:city":"Valencia",
    "sg:orig_category":"Laboratorios Y Trabajos De Fotograf\u00cda, V\u00cddeo Y Cine",
    "sg:phone":"+34 963 49 07 44",
    "sg:postcode":"46009",
    "sg:province":"Valencia",
    "wof:name":"Diago Rojas Jannet",
    "wof:placetype":"venue"
},
  "geometry": {"coordinates":[-0.3854349852,39.4850578308],"type":"Point"}
}