{
  "type": "Feature",
  "properties": {
    "iso:country":"ES",
    "sg:address":"Laureano Fernandez Martos, 56",
    "sg:city":"Baena",
    "sg:orig_category":"Comercio, Reparaci\u00d3n De Motocicletas, Bicicletas Y Piezas Sueltas",
    "sg:phone":"+34 957 67 19 85",
    "sg:postcode":"14850",
    "sg:province":"C\u00f3rdoba",
    "wof:name":"Palmero Triguero Antonio",
    "wof:placetype":"venue"
},
  "geometry": {"coordinates":[-4.3243288994,37.6172218323],"type":"Point"}
}