{
  "type": "Feature",
  "properties": {
    "iso:country":"ES",
    "sg:address":"Ctra. La Ca\u00f1ada, S/n",
    "sg:city":"Rociana Condado",
    "sg:orig_category":"Empresas De Carpinter\u00cda Met\u00c1lica",
    "sg:phone":"+34 959 41 64 73",
    "sg:postcode":"21720",
    "sg:province":"Huelva",
    "wof:name":"Hermanos Padilla Bando S.l.",
    "wof:placetype":"venue"
},
  "geometry": {"coordinates":[-6.598587513,37.3130302429],"type":"Point"}
}