{
  "type": "Feature",
  "properties": {
    "iso:country":"ES",
    "sg:address":"Avda Portugal, 9",
    "sg:city":"Ciudad Rodrigo",
    "sg:orig_category":"Carnicer\u00cdas, Carnicer\u00cdas",
    "sg:phone":"+34 923 46 13 77",
    "sg:postcode":"37500",
    "sg:province":"Salamanca",
    "wof:name":"Martin Robleda Jose Luis",
    "wof:placetype":"venue"
},
  "geometry": {"coordinates":[-6.5330848694,40.6024971008],"type":"Point"}
}