{
  "type": "Feature",
  "properties": {
    "addr:full":"Calle de Constitucion, S/n Union Murcia 30360",
    "addr:housenumber":"/ n",
    "addr:postcode":"30360",
    "addr:street":"Calle De Constitucion S",
    "iso:country":"ES",
    "sg:address":"Calle de Constitucion, S/n",
    "sg:city":"Union",
    "sg:orig_category":"Promotores Constructores",
    "sg:phone":"+34 968 54 20 45",
    "sg:postcode":"30360",
    "sg:province":"Murcia",
    "wof:name":"Martinez Alcaraz S.l.",
    "wof:placetype":"venue"
},
  "geometry": {"coordinates":[-0.8756362796,37.6198387146],"type":"Point"}
}