{
  "type": "Feature",
  "properties": {
    "iso:country":"ES",
    "sg:address":"Carrer de Alcalde Baeza Santamaria, 13",
    "sg:city":"Campello",
    "sg:orig_category":"Electricidad: Instaladores",
    "sg:phone":"+34 965 63 49 99",
    "sg:postcode":"03560",
    "sg:province":"Alicante",
    "wof:name":"Rodriguez Lopez Francisco",
    "wof:placetype":"venue"
},
  "geometry": {"coordinates":[-0.3934780061,38.4303092957],"type":"Point"}
}