{
  "type": "Feature",
  "properties": {
    "addr:full":"Calle de Larga, 37 Sahugo Salamanca 37514",
    "addr:housenumber":"37",
    "addr:postcode":"37514",
    "addr:street":"Calle De Larga",
    "iso:country":"ES",
    "sg:address":"Calle de Larga, 37",
    "sg:city":"Sahugo",
    "sg:orig_category":"Madera (al Por Menor)",
    "sg:phone":"+34 923 48 73 10",
    "sg:postcode":"37514",
    "sg:province":"Salamanca",
    "wof:name":"Vegas Ramajo Jose Maria",
    "wof:placetype":"venue"
},
  "geometry": {"coordinates":[-6.5717668533,40.4254188538],"type":"Point"}
}