{
  "type": "Feature",
  "properties": {
    "iso:country":"ES",
    "sg:address":"Calle de Eras, 2",
    "sg:city":"San Miguel Bernuy",
    "sg:orig_category":"Empresas De Vigilancia, Guardia Y Protecci\u00d3n",
    "sg:phone":"+34 921 52 93 74",
    "sg:postcode":"40332",
    "sg:province":"Segovia",
    "wof:name":"Marquina Mate Enrique",
    "wof:placetype":"venue"
},
  "geometry": {"coordinates":[-3.951417923,41.3954658508],"type":"Point"}
}