{
  "type": "Feature",
  "properties": {
    "iso:country":"ES",
    "sg:address":"Parque Tecnolog. Logist. De Vigo, 3",
    "sg:city":"Vigo",
    "sg:orig_category":"Delegados, Agentes De Tr\u00c1nsito, Auxiliares De Transporte Internacional",
    "sg:phone":"+34 986 25 24 22",
    "sg:postcode":"36312",
    "sg:province":"Pontevedra",
    "wof:name":"Transportes Bravo Otero S.l.",
    "wof:placetype":"venue"
},
  "geometry": {"coordinates":[-8.7040929794,42.1925163269],"type":"Point"}
}