{
  "type": "Feature",
  "properties": {
    "iso:country":"ES",
    "sg:address":"Carrer de Calabria, 38",
    "sg:city":"Barcelona",
    "sg:classifiers":[
        {
            "category":"Cinema",
            "subcategory":"Movie Theater",
            "type":"Entertainment"
        }
    ],
    "sg:phone":"+34 934 23 23 02",
    "sg:postcode":"08015",
    "sg:province":"Barcelona",
    "sg:tags":[
        "salas",
        "de",
        "cine"
    ],
    "wof:name":"River S.l",
    "wof:placetype":"venue"
},
  "geometry": {"coordinates":[2.1592299938,41.3767127991],"type":"Point"}
}