{
  "type": "Feature",
  "properties": {
    "iso:country":"ES",
    "sg:address":"Avda Garcia Barbon, 81",
    "sg:city":"Vigo",
    "sg:orig_category":"\u00d3ptica: Instrumentos (fabricaci\u00d3n)",
    "sg:phone":"+34 986 22 02 93",
    "sg:postcode":"36201",
    "sg:province":"Pontevedra",
    "wof:name":"Ojos Optica S.l.",
    "wof:placetype":"venue"
},
  "geometry": {"coordinates":[-8.7138843536,42.237033844],"type":"Point"}
}