{
  "type": "Feature",
  "properties": {
    "iso:country":"ES",
    "sg:address":"Calle de Benjamin Ballester, 3",
    "sg:city":"Ludiente",
    "sg:orig_category":"Administraciones Regionales, Departamentales Y Locales",
    "sg:phone":"+34 964 37 50 31",
    "sg:postcode":"12123",
    "sg:province":"Castell\u00f3n",
    "wof:name":"Ayuntamiento De Ludiente",
    "wof:placetype":"venue"
},
  "geometry": {"coordinates":[-0.3717519939,40.0865364075],"type":"Point"}
}