{
  "type": "Feature",
  "properties": {
    "iso:country":"ES",
    "sg:address":"Avda Portugal, 19",
    "sg:city":"Logro\u00f1o",
    "sg:orig_category":"Ropa Para Caballeros (al Por Menor)",
    "sg:phone":"+34 941 22 10 07",
    "sg:postcode":"26001",
    "sg:province":"La Rioja",
    "wof:name":"Vamar Representaciones S.l.",
    "wof:placetype":"venue"
},
  "geometry": {"coordinates":[-2.4495580196,42.4645500183],"type":"Point"}
}