{
  "type": "Feature",
  "properties": {
    "addr:full":"Calle de Morronguilleta, 26 Errenteria Guip\u00f9zcoa 20100",
    "addr:housenumber":"26",
    "addr:postcode":"20100",
    "addr:street":"Calle De Morronguilleta;Guipu\u0300Zcoa",
    "iso:country":"ES",
    "sg:address":"Calle de Morronguilleta, 26",
    "sg:city":"Errenteria",
    "sg:orig_category":"Fabricaci\u00d3n De Juguetes Autom\u00c1ticos",
    "sg:phone":"+34 943 34 45 45",
    "sg:postcode":"20100",
    "sg:province":"Guip\u00f9zcoa",
    "wof:name":"Recreativos Easo, S.l.",
    "wof:placetype":"venue"
},
  "geometry": {"coordinates":[-1.9022589922,43.3121604919],"type":"Point"}
}