{
  "type": "Feature",
  "properties": {
    "iso:country":"ES",
    "sg:address":"Plaza Nueva, 6",
    "sg:city":"Albox",
    "sg:orig_category":"Cl\u00cdnicas Dentales",
    "sg:phone":"+34 950 43 14 11",
    "sg:postcode":"04800",
    "sg:province":"Almer\u00eda",
    "wof:name":"Rodriguez Navarro Manuel",
    "wof:placetype":"venue"
},
  "geometry": {"coordinates":[-2.1454439163,37.3878860474],"type":"Point"}
}