{
  "type": "Feature",
  "properties": {
    "iso:country":"ES",
    "sg:address":"Puerto De Garrucha, S/n",
    "sg:city":"Garrucha",
    "sg:orig_category":"Construcciones Navales Y Fluviales",
    "sg:phone":"+34 950 13 36 42",
    "sg:postcode":"04630",
    "sg:province":"Almer\u00eda",
    "wof:name":"Astilleros Y Varaderos De Garrucha S.l.",
    "wof:placetype":"venue"
},
  "geometry": {"coordinates":[-1.8227686882,37.1791648865],"type":"Point"}
}