{
  "type": "Feature",
  "properties": {
    "addr:full":"Ctra Villavieja, 48 Nules Castell\u00f3n 12520",
    "addr:housenumber":"48",
    "addr:postcode":"12520",
    "addr:street":"Ctra Villavieja",
    "iso:country":"ES",
    "sg:address":"Ctra Villavieja, 48",
    "sg:city":"Nules",
    "sg:orig_category":"Reciclaje Y Tratamiento De Desechos Varios",
    "sg:phone":"+34 964 67 45 25",
    "sg:postcode":"12520",
    "sg:province":"Castell\u00f3n",
    "wof:name":"Noulas Resevi S.l.",
    "wof:placetype":"venue"
},
  "geometry": {"coordinates":[-0.1741040051,39.8578834534],"type":"Point"}
}