{
  "type": "Feature",
  "properties": {
    "iso:country":"ES",
    "sg:address":"Carrer de Tres D'abril, 2",
    "sg:city":"S. Boi Llobregat",
    "sg:orig_category":"Molduras, Junquillos, Listones Y Molduras Perforadas",
    "sg:phone":"+34 936 54 35 85",
    "sg:postcode":"08830",
    "sg:province":"Barcelona",
    "wof:name":"Grima Grima Miguel",
    "wof:placetype":"venue"
},
  "geometry": {"coordinates":[2.0456049442,41.3423843384],"type":"Point"}
}