{
  "type": "Feature",
  "properties": {
    "iso:country":"ES",
    "sg:address":"Calle de Celestino Cabeza, 27",
    "sg:city":"Langreo",
    "sg:orig_category":"Muebles, Minoristas",
    "sg:phone":"+34 985 69 03 64",
    "sg:postcode":"33900",
    "sg:province":"Asturias",
    "wof:name":"Garcia Garcia Medita",
    "wof:placetype":"venue"
},
  "geometry": {"coordinates":[-5.694334507,43.3097496033],"type":"Point"}
}