{
  "type": "Feature",
  "properties": {
    "iso:country":"ES",
    "sg:address":"Arangas, S/n",
    "sg:city":"Las Arenas",
    "sg:orig_category":"Alimentaci\u00d3n General (al Por Mayor)",
    "sg:phone":"+34 985 84 67 15",
    "sg:postcode":"33554",
    "sg:province":"Asturias",
    "wof:name":"Anton Gonzalo Santos",
    "wof:placetype":"venue"
},
  "geometry": {"coordinates":[-4.8149704933,43.3040084839],"type":"Point"}
}