{
  "type": "Feature",
  "properties": {
    "iso:country":"ES",
    "sg:address":"Carrer de Major, 4",
    "sg:city":"Gandesa",
    "sg:orig_category":"Laboratorios Y Trabajos De Fotograf\u00cda, V\u00cddeo Y Cine",
    "sg:phone":"+34 977 42 15 02",
    "sg:postcode":"43780",
    "sg:province":"Tarragona",
    "wof:name":"Crescenti Todo Raimon",
    "wof:placetype":"venue"
},
  "geometry": {"coordinates":[0.4379749894,41.0528488159],"type":"Point"}
}