{
  "type": "Feature",
  "properties": {
    "iso:country":"ES",
    "sg:address":"Plaz San Vicente De Paul, 5",
    "sg:city":"Madrid",
    "sg:orig_category":"Asesor\u00cda Fiscal Y Jur\u00cddica",
    "sg:phone":"+34 915 65 01 41",
    "sg:postcode":"28025",
    "sg:province":"Madrid",
    "wof:name":"Molinero Nu\u00f1ez Eduardo",
    "wof:placetype":"venue"
},
  "geometry": {"coordinates":[-3.7262010574,40.3855133057],"type":"Point"}
}