{
  "type": "Feature",
  "properties": {
    "iso:country":"ES",
    "sg:address":"Carrer de Sant Isidre, 7",
    "sg:city":"Molins Rei",
    "sg:orig_category":"Talleres De Corte Y Confecci\u00d3n",
    "sg:phone":"+34 936 68 56 71",
    "sg:postcode":"08750",
    "sg:province":"Barcelona",
    "wof:name":"Castilla Gutierrez Angel",
    "wof:placetype":"venue"
},
  "geometry": {"coordinates":[2.02135396,41.4070358276],"type":"Point"}
}