{
  "type": "Feature",
  "properties": {
    "iso:country":"ES",
    "sg:address":"Carrer de Mallorca, 272",
    "sg:city":"Barcelona",
    "sg:orig_category":"Importaci\u00d3n",
    "sg:phone":"+34 934 67 72 83",
    "sg:postcode":"08037",
    "sg:province":"Barcelona",
    "wof:name":"China Certification & Inspection Group Co. Ltd Sucursal En Espa\u00f1a",
    "wof:placetype":"venue"
},
  "geometry": {"coordinates":[2.164495945,41.3950958252],"type":"Point"}
}