{
  "type": "Feature",
  "properties": {
    "addr:full":"Pase Rosales, 26 Zaragoza Zaragoza 50008",
    "addr:housenumber":"26",
    "addr:postcode":"50008",
    "addr:street":"Rosales",
    "iso:country":"ES",
    "sg:address":"Pase Rosales, 26",
    "sg:city":"Zaragoza",
    "sg:orig_category":"Ingenier\u00cda, Centros De Estudios (diversos)",
    "sg:phone":"+34 976 59 93 13",
    "sg:postcode":"50008",
    "sg:province":"Zaragoza",
    "wof:name":"Asein Consultores Industriales S.l.",
    "wof:placetype":"venue"
},
  "geometry": {"coordinates":[-0.8783608079,41.6398887634],"type":"Point"}
}