{
  "type": "Feature",
  "properties": {
    "addr:full":"Carr Major Sant Domenec, 6 Villarreal Castell\u00f3n 12540",
    "addr:housenumber":"6",
    "addr:postcode":"12540",
    "addr:street":"Carr Major Sant Domenec",
    "iso:country":"ES",
    "sg:address":"Carr Major Sant Domenec, 6",
    "sg:city":"Villarreal",
    "sg:orig_category":"Fabricaci\u00d3n De Cortinas Y Visillos",
    "sg:phone":"+34 964 52 08 90",
    "sg:postcode":"12540",
    "sg:province":"Castell\u00f3n",
    "wof:name":"Cortinajes Pedro C.d.",
    "wof:placetype":"venue"
},
  "geometry": {"coordinates":[-0.1019119993,39.9367141724],"type":"Point"}
}