{
  "type": "Feature",
  "properties": {
    "addr:full":"Csta. Olmillo, 1 Sacedon Guadalajara 19120",
    "addr:housenumber":"1",
    "addr:postcode":"19120",
    "addr:street":"Olmillo",
    "iso:country":"ES",
    "sg:address":"Csta. Olmillo, 1",
    "sg:city":"Sacedon",
    "sg:orig_category":"Art\u00cdculos De Regalo (al Por Menor)",
    "sg:phone":"+34 949 35 03 74",
    "sg:postcode":"19120",
    "sg:province":"Guadalajara",
    "wof:name":"Vena Moreno Lourdes",
    "wof:placetype":"venue"
},
  "geometry": {"coordinates":[-2.7353289127,40.4822349548],"type":"Point"}
}