{
  "type": "Feature",
  "properties": {
    "addr:full":"Rua Tomas Paredes, 1 Vigo Pontevedra 36208",
    "addr:housenumber":"1",
    "addr:postcode":"36208",
    "addr:street":"Rua Tomas Paredes",
    "iso:country":"ES",
    "sg:address":"Rua Tomas Paredes, 1",
    "sg:city":"Vigo",
    "sg:orig_category":"Farmacias",
    "sg:phone":"+34 986 23 28 90",
    "sg:postcode":"36208",
    "sg:province":"Pontevedra",
    "wof:name":"Suarez Martinez Maria Esther",
    "wof:placetype":"venue"
},
  "geometry": {"coordinates":[-8.7529230118,42.2220802307],"type":"Point"}
}