{
  "type": "Feature",
  "properties": {
    "iso:country":"ES",
    "sg:address":"Els Llibrers, 7",
    "sg:city":"P.i. Masia Del Juez",
    "sg:orig_category":"Transportes Por Carretera: Lotes Completos, Mercanc\u00cdas Diversas",
    "sg:phone":"+34 961 56 43 43",
    "sg:postcode":"46900",
    "sg:province":"Valencia",
    "wof:name":"Marnova Valencia S.l.",
    "wof:placetype":"venue"
},
  "geometry": {"coordinates":[-0.4623290002,39.441619873],"type":"Point"}
}