{
  "type": "Feature",
  "properties": {
    "addr:full":"Pla\u00c7 Angel, 26 Inca Islas Baleares 07300",
    "addr:housenumber":"26",
    "addr:postcode":"07300",
    "addr:street":"Angel",
    "iso:country":"ES",
    "sg:address":"Pla\u00c7 Angel, 26",
    "sg:city":"Inca",
    "sg:orig_category":"Radiocomunicaciones, Telefon\u00cda M\u00d3vil, Radiomensajer\u00cda: Servicios, Comercializaci\u00d3n",
    "sg:phone":"+34 971 88 13 88",
    "sg:postcode":"07300",
    "sg:province":"Islas Baleares",
    "wof:name":"Mubitel S.l.",
    "wof:placetype":"venue"
},
  "geometry": {"coordinates":[2.9105000496,39.7193832397],"type":"Point"}
}