{
  "type": "Feature",
  "properties": {
    "iso:country":"ES",
    "sg:address":"Calle de Rojo Hermogenes, 2",
    "sg:city":"Bilbao",
    "sg:classifiers":[
        {
            "category":"Personal",
            "subcategory":"Barber",
            "type":"Services"
        }
    ],
    "sg:phone":"+34 944 99 66 53",
    "sg:postcode":"48013",
    "sg:province":"Vizcaya",
    "sg:tags":[
        "caballeros",
        "de",
        "peluqueros"
    ],
    "wof:name":"Laureano Garcia De Galdeano Rabasa",
    "wof:placetype":"venue"
},
  "geometry": {"coordinates":[-2.9732511044,43.2775268555],"type":"Point"}
}