{
  "type": "Feature",
  "properties": {
    "iso:country":"ES",
    "sg:address":"Carr Alemanya, 4",
    "sg:city":"Badalona",
    "sg:orig_category":"Textil",
    "sg:phone":"+34 933 95 09 55",
    "sg:postcode":"08917",
    "sg:province":"Barcelona",
    "wof:name":"Anchal S.l.",
    "wof:placetype":"venue"
},
  "geometry": {"coordinates":[2.2202601433,41.457485199],"type":"Point"}
}