{
  "type": "Feature",
  "properties": {
    "iso:country":"ES",
    "sg:address":"Avda Orbigo (el), 30",
    "sg:city":"Benavides De Orbigo",
    "sg:orig_category":"Zapatos (al Por Menor)",
    "sg:phone":"+34 987 37 02 18",
    "sg:postcode":"24280",
    "sg:province":"Le\u00f3n",
    "wof:name":"Alija Carbajo Pilar",
    "wof:placetype":"venue"
},
  "geometry": {"coordinates":[-5.8943762779,42.5051574707],"type":"Point"}
}