{
  "type": "Feature",
  "properties": {
    "iso:country":"ES",
    "sg:address":"Calle de Miralsol, 19",
    "sg:city":"Coslada",
    "sg:orig_category":"Armas Y Municiones (fabricaci\u00d3n, Al Por Mayor)",
    "sg:phone":"+34 916 71 37 41",
    "sg:postcode":"28820",
    "sg:province":"Madrid",
    "wof:name":"Lozano Palacios Felix",
    "wof:placetype":"venue"
},
  "geometry": {"coordinates":[-3.5374319553,40.4247665405],"type":"Point"}
}