{
  "type": "Feature",
  "properties": {
    "iso:country":"ES",
    "sg:address":"Cmno Circunvalacion, 26",
    "sg:city":"Honrubia",
    "sg:orig_category":"Charcuter\u00cdas (al Por Mayor)",
    "sg:phone":"+34 969 29 26 30",
    "sg:postcode":"16730",
    "sg:province":"Cuenca",
    "wof:name":"Inaldyn S.l.",
    "wof:placetype":"venue"
},
  "geometry": {"coordinates":[-2.2846488953,39.6151657104],"type":"Point"}
}