{
  "type": "Feature",
  "properties": {
    "addr:full":"Carrer de Urgell, S/n Santa Perpetua De Mogoda Barcelona 08130",
    "addr:postcode":"08130",
    "addr:street":"Carrer De Urgell S / N",
    "iso:country":"ES",
    "sg:address":"Carrer de Urgell, S/n",
    "sg:city":"Santa Perpetua De Mogoda",
    "sg:orig_category":"Productos Qu\u00cdmicos (fabricaci\u00d3n, Al Por Mayor)",
    "sg:phone":"+34 935 74 43 00",
    "sg:postcode":"08130",
    "sg:province":"Barcelona",
    "wof:name":"Chemplate Iberica S. A.",
    "wof:placetype":"venue"
},
  "geometry": {"coordinates":[2.1802799702,41.5371818542],"type":"Point"}
}