{
  "type": "Feature",
  "properties": {
    "addr:full":"Calle de Oriente, 154 Villanueva Serena Badajoz 06700",
    "addr:housenumber":"154",
    "addr:postcode":"06700",
    "addr:street":"Calle De Oriente",
    "iso:country":"ES",
    "sg:address":"Calle de Oriente, 154",
    "sg:city":"Villanueva Serena",
    "sg:orig_category":"Persianas Interiores, Exteriores",
    "sg:phone":"+34 924 84 00 04",
    "sg:postcode":"06700",
    "sg:province":"Badajoz",
    "wof:name":"Ferreira Roman Eladio",
    "wof:placetype":"venue"
},
  "geometry": {"coordinates":[-5.7921690941,38.9784584045],"type":"Point"}
}