{
  "type": "Feature",
  "properties": {
    "addr:full":"Plaz Callao, 19 Olivenza Badajoz 06100",
    "addr:housenumber":"19",
    "addr:postcode":"06100",
    "addr:street":"Callao",
    "iso:country":"ES",
    "sg:address":"Plaz Callao, 19",
    "sg:city":"Olivenza",
    "sg:orig_category":"Aceites Y Grasas Alimentarias (fabricaci\u00d3n, Al Por Mayor)",
    "sg:phone":"+34 924 49 01 58",
    "sg:postcode":"06100",
    "sg:province":"Badajoz",
    "wof:name":"Aceites Bonet Sociedad Limitada",
    "wof:placetype":"venue"
},
  "geometry": {"coordinates":[-7.0995779037,38.6818237305],"type":"Point"}
}