{
  "type": "Feature",
  "properties": {
    "addr:full":"Calle de Ginzo De Limia, 51 Madrid Madrid 28034",
    "addr:housenumber":"51",
    "addr:postcode":"madrid;28034",
    "addr:street":"Calle De Ginzo De Limia",
    "iso:country":"ES",
    "sg:address":"Calle de Ginzo De Limia, 51",
    "sg:city":"Madrid",
    "sg:orig_category":"Farmacias",
    "sg:phone":"+34 917 39 02 21",
    "sg:postcode":"28034",
    "sg:province":"Madrid",
    "wof:name":"Sanz Donaire Maria Jose",
    "wof:placetype":"venue"
},
  "geometry": {"coordinates":[-3.707818985,40.4845581055],"type":"Point"}
}