{
  "type": "Feature",
  "properties": {
    "iso:country":"ES",
    "sg:address":"Avda Jose Antonio, 2",
    "sg:city":"Medina Pomar",
    "sg:orig_category":"M\u00c9dicos: Estomatolog\u00cda",
    "sg:phone":"+34 947 19 04 48",
    "sg:postcode":"09500",
    "sg:province":"Burgos",
    "wof:name":"Ortega Gomez Ana Carmen",
    "wof:placetype":"venue"
},
  "geometry": {"coordinates":[-3.4873740673,42.9318466187],"type":"Point"}
}