{
  "type": "Feature",
  "properties": {
    "addr:full":"Av Jaume Iii, 20 Palma Islas Baleares 07012",
    "addr:housenumber":"20",
    "addr:postcode":"07012",
    "addr:street":"Av Jaume Iii",
    "iso:country":"ES",
    "sg:address":"Av Jaume Iii, 20",
    "sg:city":"Palma",
    "sg:orig_category":"Caf\u00c9s, Bares, Cervecer\u00cdas",
    "sg:phone":"+34 971 72 16 35",
    "sg:postcode":"07012",
    "sg:province":"Islas Baleares",
    "wof:name":"Sistelcom-telemensaje S.a.",
    "wof:placetype":"venue"
},
  "geometry": {"coordinates":[2.6435511112,39.572555542],"type":"Point"}
}