{
  "type": "Feature",
  "properties": {
    "iso:country":"ES",
    "sg:address":"Avda Pastora, S/n",
    "sg:city":"Cambados",
    "sg:orig_category":"Doctores En Medicina",
    "sg:phone":"+34 986 54 24 14",
    "sg:postcode":"36630",
    "sg:province":"Pontevedra",
    "wof:name":"Guede Rivas Manuel",
    "wof:placetype":"venue"
},
  "geometry": {"coordinates":[-8.8084964752,42.5131225586],"type":"Point"}
}