{
  "type": "Feature",
  "properties": {
    "addr:full":"Avda Santiago Lapuente, 51 Fuentes Ebro Zaragoza 50740",
    "addr:housenumber":"51",
    "addr:postcode":"50740",
    "addr:street":"Avda Santiago Lapuente",
    "iso:country":"ES",
    "sg:address":"Avda Santiago Lapuente, 51",
    "sg:city":"Fuentes Ebro",
    "sg:orig_category":"Contenedores (mercanc\u00cdas)",
    "sg:phone":"+34 976 16 00 57",
    "sg:postcode":"50740",
    "sg:province":"Zaragoza",
    "wof:name":"Lapuente Sari\u00f1ena Jose Luis",
    "wof:placetype":"venue"
},
  "geometry": {"coordinates":[-0.6274390221,41.5107917786],"type":"Point"}
}