{
  "type": "Feature",
  "properties": {
    "addr:full":"Ctra. Nal. 340, Km. 0243,0 Vila-seca Tarragona 43480",
    "addr:postcode":"43480",
    "addr:street":"Ctra. Nal. 340 Km. 0243,0",
    "iso:country":"ES",
    "sg:address":"Ctra. Nal. 340, Km. 0243,0",
    "sg:city":"Vila-seca",
    "sg:orig_category":"Transportes Internacionales",
    "sg:phone":"+34 977 39 33 12",
    "sg:postcode":"43480",
    "sg:province":"Tarragona",
    "wof:name":"Schmidt Iberica S.a.",
    "wof:placetype":"venue"
},
  "geometry": {"coordinates":[1.1441899538,41.1080245972],"type":"Point"}
}