{
  "type": "Feature",
  "properties": {
    "addr:full":"Mina Concepcion, S/n Concepcion Huelva 21350",
    "addr:housenumber":"s / n",
    "addr:postcode":"21350",
    "addr:street":"Mina Concepcion",
    "iso:country":"ES",
    "sg:address":"Mina Concepcion, S/n",
    "sg:city":"Concepcion",
    "sg:orig_category":"Centros De Educaci\u00d3n Especial",
    "sg:phone":"+34 959 14 60 14",
    "sg:postcode":"21350",
    "sg:province":"Huelva",
    "wof:name":"Junta De Andalucia",
    "wof:placetype":"venue"
},
  "geometry": {"coordinates":[-6.7878918648,37.8736572266],"type":"Point"}
}