{
  "type": "Feature",
  "properties": {
    "addr:full":"Avda Doctor Federico Rubio Y Gali, 104 Madrid Madrid 28040",
    "addr:housenumber":"104",
    "addr:postcode":"28040",
    "addr:street":"Avda Doctor Federico Rubio Y Gali",
    "iso:country":"ES",
    "sg:address":"Avda Doctor Federico Rubio Y Gali, 104",
    "sg:city":"Madrid",
    "sg:orig_category":"Electrodom\u00c9sticos (al Por Menor)",
    "sg:phone":"+34 914 50 56 01",
    "sg:postcode":"28040",
    "sg:province":"Madrid",
    "wof:name":"Duran Pizarro Manuel",
    "wof:placetype":"venue"
},
  "geometry": {"coordinates":[-3.7139420509,40.4560432434],"type":"Point"}
}