{
  "type": "Feature",
  "properties": {
    "addr:full":"Calle de Valmojado, 275 Madrid Madrid 28047",
    "addr:housenumber":"275",
    "addr:postcode":"28047",
    "addr:street":"Calle De Valmojado",
    "iso:country":"ES",
    "sg:address":"Calle de Valmojado, 275",
    "sg:city":"Madrid",
    "sg:orig_category":"M\u00c1quinas De Coser Y De Hacer Punto (al Por Mayor)",
    "sg:phone":"+34 917 17 39 48",
    "sg:postcode":"28047",
    "sg:province":"Madrid",
    "sg:website":"www.acoser.com",
    "wof:name":"Alfa Hogar S.l.",
    "wof:placetype":"venue"
},
  "geometry": {"coordinates":[-3.7585999966,40.3872756958],"type":"Point"}
}