{
  "type": "Feature",
  "properties": {
    "iso:country":"ES",
    "sg:address":"Ptge Flaugier, 42",
    "sg:city":"Barcelona",
    "sg:orig_category":"Mec\u00c1nico Del Autom\u00d3vil",
    "sg:phone":"+34 933 47 29 39",
    "sg:postcode":"08041",
    "sg:province":"Barcelona",
    "wof:name":"Puig Elias Ramon",
    "wof:placetype":"venue"
},
  "geometry": {"coordinates":[2.1765139103,41.4159660339],"type":"Point"}
}