{
  "type": "Feature",
  "properties": {
    "iso:country":"ES",
    "sg:address":"Carr Nou, 134",
    "sg:city":"Vilanova Bellpuig",
    "sg:orig_category":"Ebanister\u00cda",
    "sg:phone":"+34 973 32 42 22",
    "sg:postcode":"25264",
    "sg:province":"Lleida",
    "wof:name":"Fusteria Ebanisteria Vilanova S.l.",
    "wof:placetype":"venue"
},
  "geometry": {"coordinates":[0.9609649777,41.6147232056],"type":"Point"}
}