{
  "type": "Feature",
  "properties": {
    "iso:country":"ES",
    "sg:address":"Calle de Jose Arcones Gil, 13",
    "sg:city":"Madrid",
    "sg:orig_category":"Electrodom\u00c9sticos (al Por Menor)",
    "sg:phone":"+34 914 08 69 95",
    "sg:postcode":"28017",
    "sg:province":"Madrid",
    "wof:name":"Alonso Toha Ramon",
    "wof:placetype":"venue"
},
  "geometry": {"coordinates":[-3.639043808,40.4361763],"type":"Point"}
}