{
  "type": "Feature",
  "properties": {
    "addr:full":"Avda Somosierra (de), 22 San Sebastian De Los Reyes Madrid 28700",
    "addr:housenumber":"22",
    "addr:postcode":"28700",
    "addr:street":"Avda Somosierra De",
    "iso:country":"ES",
    "sg:address":"Avda Somosierra (de), 22",
    "sg:city":"San Sebastian De Los Reyes",
    "sg:orig_category":"Vinos (agentes)",
    "sg:phone":"+34 916 59 28 23",
    "sg:postcode":"28700",
    "sg:province":"Madrid",
    "wof:name":"Vindima S.l.",
    "wof:placetype":"venue"
},
  "geometry": {"coordinates":[-3.6158521175,40.5544471741],"type":"Point"}
}