{
  "type": "Feature",
  "properties": {
    "iso:country":"ES",
    "sg:address":"Arnados, S/n",
    "sg:city":"Arnados",
    "sg:orig_category":"Restaurantes Para Recepciones, Banquetes, Conferencias",
    "sg:phone":"+34 981 75 23 33",
    "sg:postcode":"15107",
    "sg:province":"La Coru\u00f1a",
    "wof:name":"Fernandez Lista Jesus Leonardo",
    "wof:placetype":"venue"
},
  "geometry": {"coordinates":[-8.7382974625,43.2469902039],"type":"Point"}
}