{
  "type": "Feature",
  "properties": {
    "addr:full":"Consistorio Viejo, S/n Rianxo La Coru\u00f1a 15920",
    "addr:housenumber":"s / n",
    "addr:postcode":"15920",
    "addr:street":"La Corun\u0303A",
    "iso:country":"ES",
    "sg:address":"Consistorio Viejo, S/n",
    "sg:city":"Rianxo",
    "sg:orig_category":"Molduras, Junquillos, Listones Y Molduras Perforadas",
    "sg:phone":"+34 981 86 04 50",
    "sg:postcode":"15920",
    "sg:province":"La Coru\u00f1a",
    "wof:name":"Ordo\u00f1ez Comojo Alvaro",
    "wof:placetype":"venue"
},
  "geometry": {"coordinates":[-8.8193740845,42.6502113342],"type":"Point"}
}