{
  "type": "Feature",
  "properties": {
    "addr:full":"C/ Antonio Mora Ferrandez, 26 Elche Alicante 03202",
    "addr:housenumber":"26",
    "addr:postcode":"03202",
    "addr:street":"C / Antonio Mora Ferrandez",
    "iso:country":"ES",
    "sg:address":"C/ Antonio Mora Ferrandez, 26",
    "sg:city":"Elche",
    "sg:orig_category":"Rejas Y Cortinas Met\u00c1licas",
    "sg:phone":"+34 966 61 18 63",
    "sg:postcode":"03202",
    "sg:province":"Alicante",
    "wof:name":"Toy Sistemas S.l.",
    "wof:placetype":"venue"
},
  "geometry": {"coordinates":[-0.6845520139,38.2716827393],"type":"Point"}
}