{
  "type": "Feature",
  "properties": {
    "addr:full":"Calle de Badajoz, 4 Alcorcon Madrid 28921",
    "addr:housenumber":"4",
    "addr:postcode":"28921",
    "addr:street":"Calle De Badajoz",
    "iso:country":"ES",
    "sg:address":"Calle de Badajoz, 4",
    "sg:city":"Alcorcon",
    "sg:orig_category":"Transportes Por Carretera: Lotes Completos, Mercanc\u00cdas Diversas",
    "sg:phone":"+34 916 19 62 28",
    "sg:postcode":"28921",
    "sg:province":"Madrid",
    "wof:name":"Camacho Arroyo Juan",
    "wof:placetype":"venue"
},
  "geometry": {"coordinates":[-3.8308210373,40.3479804993],"type":"Point"}
}