{
  "type": "Feature",
  "properties": {
    "addr:full":"Calle de Gredos, 13 Candeleda \u00c1vila 05480",
    "addr:housenumber":"13",
    "addr:postcode":"05480",
    "addr:street":"Calle De Gredos",
    "iso:country":"ES",
    "sg:address":"Calle de Gredos, 13",
    "sg:city":"Candeleda",
    "sg:orig_category":"Empresas De Hormig\u00d3n, Hormig\u00d3n Armado Y Pretensado",
    "sg:phone":"+34 920 38 07 97",
    "sg:postcode":"05480",
    "sg:province":"\u00c1vila",
    "wof:name":"Mu\u00f1oz Blazquez Jose",
    "wof:placetype":"venue"
},
  "geometry": {"coordinates":[-5.2411499023,40.1559257507],"type":"Point"}
}