{
  "type": "Feature",
  "properties": {
    "iso:country":"ES",
    "sg:address":"Calle de Lertegi, 8",
    "sg:city":"Arenas -areeta",
    "sg:orig_category":"Asesor\u00cda Sobre Comunicaci\u00d3n De Empresas",
    "sg:phone":"+34 944 80 23 62",
    "sg:postcode":"48930",
    "sg:province":"Vizcaya",
    "wof:name":"North World S. L.",
    "wof:placetype":"venue"
},
  "geometry": {"coordinates":[-3.0105900764,43.3307304382],"type":"Point"}
}