{
  "type": "Feature",
  "properties": {
    "addr:full":"Calle de Jeronimo Gonzalez, 4 Gijon Asturias 33206",
    "addr:housenumber":"4",
    "addr:postcode":"33206",
    "addr:street":"Calle De Jeronimo Gonzalez",
    "iso:country":"ES",
    "sg:address":"Calle de Jeronimo Gonzalez, 4",
    "sg:city":"Gijon",
    "sg:orig_category":"Abogados",
    "sg:phone":"+34 985 17 62 82",
    "sg:postcode":"33206",
    "sg:province":"Asturias",
    "wof:name":"Telenti Alvargonzalez Jorge",
    "wof:placetype":"venue"
},
  "geometry": {"coordinates":[-5.664996624,43.5391540527],"type":"Point"}
}