{
  "type": "Feature",
  "properties": {
    "addr:full":"Calle de Aaiun, 4 Valladolid Valladolid 47013",
    "addr:housenumber":"4",
    "addr:postcode":"47013",
    "addr:street":"Calle De Aaiun",
    "iso:country":"ES",
    "sg:address":"Calle de Aaiun, 4",
    "sg:city":"Valladolid",
    "sg:orig_category":"Peluqueros: De Se\u00d1oras",
    "sg:phone":"+34 983 47 80 21",
    "sg:postcode":"47013",
    "sg:province":"Valladolid",
    "wof:name":"Miguel Pelaez Maria Luisa",
    "wof:placetype":"venue"
},
  "geometry": {"coordinates":[-4.724152565,41.6345291138],"type":"Point"}
}