{
  "type": "Feature",
  "properties": {
    "addr:full":"Av Josep Molins, 54 Hospitalet Llobregat Barcelona 08906",
    "addr:housenumber":"54",
    "addr:postcode":"08906",
    "addr:street":"Av Josep Molins",
    "iso:country":"ES",
    "sg:address":"Av Josep Molins, 54",
    "sg:city":"Hospitalet Llobregat",
    "sg:orig_category":"Ropa Para Se\u00d1oras (al Por Menor)",
    "sg:phone":"+34 934 49 19 05",
    "sg:postcode":"08906",
    "sg:province":"Barcelona",
    "wof:name":"Casado Gomez Jose Maria",
    "wof:placetype":"venue"
},
  "geometry": {"coordinates":[2.1060140133,41.3734016418],"type":"Point"}
}