{
  "type": "Feature",
  "properties": {
    "addr:full":"Pque Usategi, 1 Algorta Vizcaya 48993",
    "addr:housenumber":"1",
    "addr:postcode":"48993",
    "iso:country":"ES",
    "sg:address":"Pque Usategi, 1",
    "sg:city":"Algorta",
    "sg:orig_category":"Inmobiliaria (agencias)",
    "sg:phone":"+34 944 60 76 52",
    "sg:postcode":"48993",
    "sg:province":"Vizcaya",
    "wof:name":"Aniuna S.l.",
    "wof:placetype":"venue"
},
  "geometry": {"coordinates":[-3.0172798634,43.351474762],"type":"Point"}
}