{
  "type": "Feature",
  "properties": {
    "addr:full":"Carr Germans Masferrer, 29 Escala Girona 17130",
    "addr:housenumber":"29",
    "addr:postcode":"17130",
    "addr:street":"Carr Germans Masferrer",
    "iso:country":"ES",
    "sg:address":"Carr Germans Masferrer, 29",
    "sg:city":"Escala",
    "sg:classifiers":[
        {
            "category":"Personal",
            "subcategory":"Barber",
            "type":"Services"
        }
    ],
    "sg:phone":"+34 972 77 06 17",
    "sg:postcode":"17130",
    "sg:province":"Girona",
    "sg:tags":[
        "caballeros",
        "de",
        "peluqueros"
    ],
    "wof:name":"Alfonso Nu\u00f1ez Maria Cinta",
    "wof:placetype":"venue"
},
  "geometry": {"coordinates":[3.1335961819,42.1245040894],"type":"Point"}
}