{
  "type": "Feature",
  "properties": {
    "addr:full":"Calle de Fernando De Cordoba, 8 Cordoba C\u00f3rdoba 14008",
    "addr:housenumber":"8",
    "addr:postcode":"14008",
    "addr:street":"Calle De Fernando De Cordoba;Co\u0301Rdoba",
    "iso:country":"ES",
    "sg:address":"Calle de Fernando De Cordoba, 8",
    "sg:city":"Cordoba",
    "sg:orig_category":"Ense\u00d1anza, Formaci\u00d3n Profesional: Aprendizaje",
    "sg:phone":"+34 957 48 45 64",
    "sg:postcode":"14008",
    "sg:province":"C\u00f3rdoba",
    "wof:name":"Fundacion Formacion Y Empleo De Andalucia",
    "wof:placetype":"venue"
},
  "geometry": {"coordinates":[-4.7840747833,37.8893203735],"type":"Point"}
}