{
  "type": "Feature",
  "properties": {
    "addr:full":"Zamora, 2738 Congo Almer\u00eda 04738",
    "addr:housenumber":"2738",
    "addr:postcode":"04738",
    "addr:street":"Zamora;Almeri\u0301A",
    "iso:country":"ES",
    "sg:address":"Zamora, 2738",
    "sg:city":"Congo",
    "sg:orig_category":"Formaci\u00d3n Continuada (variada)",
    "sg:phone":"+34 950 53 95 78",
    "sg:postcode":"04738",
    "sg:province":"Almer\u00eda",
    "wof:name":"Etifa S.l.",
    "wof:placetype":"venue"
},
  "geometry": {"coordinates":[-2.6420009136,36.8316612244],"type":"Point"}
}