{
  "type": "Feature",
  "properties": {
    "iso:country":"ES",
    "sg:address":"Carrer de Sant Francesc (de), 14",
    "sg:city":"Tarragona",
    "sg:orig_category":"Comidas Por Encargo, Organizaci\u00d3n De Recepciones",
    "sg:phone":"+34 977 22 92 04",
    "sg:postcode":"43003",
    "sg:province":"Tarragona",
    "wof:name":"Anton Avila Luis",
    "wof:placetype":"venue"
},
  "geometry": {"coordinates":[1.2531652451,41.1163711548],"type":"Point"}
}