{
  "type": "Feature",
  "properties": {
    "iso:country":"ES",
    "sg:address":"Carrer de Calderon De La Barca, 8",
    "sg:city":"Hospitalet Llobregat",
    "sg:orig_category":"Mec\u00c1nico Del Autom\u00d3vil",
    "sg:phone":"+34 934 37 89 70",
    "sg:postcode":"08906",
    "sg:province":"Barcelona",
    "wof:name":"Ruiz Granado Manuel",
    "wof:placetype":"venue"
},
  "geometry": {"coordinates":[2.1026959419,41.3729896545],"type":"Point"}
}