{
  "type": "Feature",
  "properties": {
    "addr:full":"Calle de Batalla Del Ebro, 50 Palmas De Gran Canaria Las Palmas 35013",
    "addr:housenumber":"50",
    "addr:postcode":"35013",
    "addr:street":"Calle De Batalla Del Ebro",
    "iso:country":"ES",
    "sg:address":"Calle de Batalla Del Ebro, 50",
    "sg:city":"Palmas De Gran Canaria",
    "sg:orig_category":"Comunidades Religiosas",
    "sg:phone":"+34 928 41 78 82",
    "sg:postcode":"35013",
    "sg:province":"Las Palmas",
    "wof:name":"Compa\u00f1ia Sta. Teresa De Jesus",
    "wof:placetype":"venue"
},
  "geometry": {"coordinates":[-15.4483594894,28.0975170135],"type":"Point"}
}