{
  "type": "Feature",
  "properties": {
    "iso:country":"ES",
    "sg:address":"Calle de General Gallarza, 18",
    "sg:city":"Calahorra",
    "sg:orig_category":"Asesor\u00cda Fiscal Y Jur\u00cddica",
    "sg:phone":"+34 941 14 51 11",
    "sg:postcode":"26500",
    "sg:province":"La Rioja",
    "wof:name":"Asesoria Felipe Muro S.l.",
    "wof:placetype":"venue"
},
  "geometry": {"coordinates":[-1.9659552574,42.3046607971],"type":"Point"}
}