{
  "type": "Feature",
  "properties": {
    "addr:full":"Calle de Cartagena, 4 Valencia Valencia 46018",
    "addr:housenumber":"4",
    "addr:postcode":"46018",
    "addr:street":"Calle De Cartagena",
    "iso:country":"ES",
    "sg:address":"Calle de Cartagena, 4",
    "sg:city":"Valencia",
    "sg:orig_category":"Supermercados Y Hipermercados",
    "sg:phone":"+34 963 82 27 37",
    "sg:postcode":"46018",
    "sg:province":"Valencia",
    "wof:name":"Supermercados Sabeco S.a.",
    "wof:placetype":"venue"
},
  "geometry": {"coordinates":[-0.3941850066,39.4707832336],"type":"Point"}
}