{
  "type": "Feature",
  "properties": {
    "addr:full":"Calle de Olivo, 49 Jaen Ja\u00e9n 23006",
    "addr:housenumber":"49;jae\u0301n",
    "addr:postcode":"23006",
    "addr:street":"Calle De Olivo",
    "iso:country":"ES",
    "sg:address":"Calle de Olivo, 49",
    "sg:city":"Jaen",
    "sg:orig_category":"Procuradores",
    "sg:phone":"+34 953 25 49 63",
    "sg:postcode":"23006",
    "sg:province":"Ja\u00e9n",
    "wof:name":"Balzo Parra Leonardo",
    "wof:placetype":"venue"
},
  "geometry": {"coordinates":[-3.8147768974,37.7802200317],"type":"Point"}
}