{
  "type": "Feature",
  "properties": {
    "iso:country":"ES",
    "sg:address":"Carrer de Ramon Batlle, 34",
    "sg:city":"Barcelona",
    "sg:orig_category":"Molduras, Junquillos, Listones Y Molduras Perforadas",
    "sg:phone":"+34 933 11 36 59",
    "sg:postcode":"08030",
    "sg:province":"Barcelona",
    "wof:name":"Saumell Ventura Magin",
    "wof:placetype":"venue"
},
  "geometry": {"coordinates":[2.1909210682,41.4318733215],"type":"Point"}
}