{
  "type": "Feature",
  "properties": {
    "addr:full":"Urb Jaizkibel, Urbanizacion, S/n Irun Guip\u00f9zcoa 20305",
    "addr:housenumber":"s",
    "addr:postcode":"20305",
    "addr:street":"Jaizkibel Urbanizacion;/ N;Guipu\u0300Zcoa",
    "iso:country":"ES",
    "sg:address":"Urb Jaizkibel, Urbanizacion, S/n",
    "sg:city":"Irun",
    "sg:orig_category":"M\u00dasica, Direcci\u00d3n",
    "sg:phone":"+34 943 63 09 12",
    "sg:postcode":"20305",
    "sg:province":"Guip\u00f9zcoa",
    "sg:website":"www.illarramendi.com",
    "wof:name":"Mahatssare Producciones S.l.",
    "wof:placetype":"venue"
},
  "geometry": {"coordinates":[-1.7637690306,43.3425445557],"type":"Point"}
}