{
  "type": "Feature",
  "properties": {
    "iso:country":"ES",
    "sg:address":"Calle de Prim, 4",
    "sg:city":"Donostia-san Sebastian",
    "sg:orig_category":"Molduras, Junquillos, Listones Y Molduras Perforadas",
    "sg:phone":"+34 943 42 98 50",
    "sg:postcode":"20006",
    "sg:province":"Guip\u00f9zcoa",
    "wof:name":"Yuguero Arrieta Jesus Maria",
    "wof:placetype":"venue"
},
  "geometry": {"coordinates":[-1.9799312353,43.3158340454],"type":"Point"}
}