{
  "type": "Feature",
  "properties": {
    "iso:country":"ES",
    "sg:address":"Avda Buenos Aires-estacion De Guadix, 40",
    "sg:city":"Estacion De Guadix",
    "sg:orig_category":"Cr\u00cda De Animales",
    "sg:phone":"+34 958 66 21 62",
    "sg:postcode":"18500",
    "sg:province":"Granada",
    "wof:name":"Martinez Berbel Manuel",
    "wof:placetype":"venue"
},
  "geometry": {"coordinates":[-3.1343569756,37.3039131165],"type":"Point"}
}