{
  "type": "Feature",
  "properties": {
    "addr:full":"Calle de Acequia, 15 Socuellamos Ciudad Real 13630",
    "addr:housenumber":"15",
    "addr:postcode":"13630",
    "addr:street":"Calle De Acequia",
    "iso:country":"ES",
    "sg:address":"Calle de Acequia, 15",
    "sg:city":"Socuellamos",
    "sg:orig_category":"Arquitectos",
    "sg:phone":"+34 926 53 09 99",
    "sg:postcode":"13630",
    "sg:province":"Ciudad Real",
    "wof:name":"Caba\u00f1as Paez Serapio",
    "wof:placetype":"venue"
},
  "geometry": {"coordinates":[-2.7941315174,39.2906112671],"type":"Point"}
}