{
  "type": "Feature",
  "properties": {
    "addr:full":"Cno. Vjo. Elche, 14 Alacant Alicante 03008",
    "addr:housenumber":"14",
    "addr:postcode":"03008",
    "addr:street":"Vjo. Elche",
    "iso:country":"ES",
    "sg:address":"Cno. Vjo. Elche, 14",
    "sg:city":"Alacant",
    "sg:orig_category":"Muebles, Minoristas",
    "sg:phone":"+34 965 28 00 77",
    "sg:postcode":"03008",
    "sg:province":"Alicante",
    "wof:name":"Importaciones Deorigen Sl",
    "wof:placetype":"venue"
},
  "geometry": {"coordinates":[-0.5224840045,38.2840309143],"type":"Point"}
}