{
  "type": "Feature",
  "properties": {
    "addr:full":"Rua Oriente, 1 Ca\u00f1iza Pontevedra 36880",
    "addr:housenumber":"1",
    "addr:postcode":"36880",
    "addr:street":"Rua Oriente",
    "iso:country":"ES",
    "sg:address":"Rua Oriente, 1",
    "sg:city":"Ca\u00f1iza",
    "sg:orig_category":"Asesor\u00cda Fiscal Y Jur\u00cddica",
    "sg:phone":"+34 986 65 20 79",
    "sg:postcode":"36880",
    "sg:province":"Pontevedra",
    "wof:name":"Mera Ranca\u00f1o Manuel",
    "wof:placetype":"venue"
},
  "geometry": {"coordinates":[-8.272693634,42.2125015259],"type":"Point"}
}