{
  "type": "Feature",
  "properties": {
    "addr:full":"Carrer de Manlleu, 42 Vic Barcelona 08500",
    "addr:housenumber":"42",
    "addr:postcode":"08500",
    "addr:street":"Carrer De Manlleu",
    "iso:country":"ES",
    "sg:address":"Carrer de Manlleu, 42",
    "sg:city":"Vic",
    "sg:orig_category":"Ropa Para Se\u00d1oras (al Por Menor)",
    "sg:phone":"+34 938 89 18 75",
    "sg:postcode":"08500",
    "sg:province":"Barcelona",
    "sg:website":"www.etxartpanno.com",
    "wof:name":"Carme Elia Pol S.l.",
    "wof:placetype":"venue"
},
  "geometry": {"coordinates":[2.2555849552,41.9327278137],"type":"Point"}
}