{
  "type": "Feature",
  "properties": {
    "addr:full":"Mandubite Bidea, 1 Etxarri-aranatz Navarra 31820",
    "addr:housenumber":"1",
    "addr:postcode":"31820",
    "addr:street":"Mandubite Bidea",
    "iso:country":"ES",
    "sg:address":"Mandubite Bidea, 1",
    "sg:city":"Etxarri-aranatz",
    "sg:orig_category":"Peluqueros: De Se\u00d1oras",
    "sg:phone":"+34 948 46 10 40",
    "sg:postcode":"31820",
    "sg:province":"Navarra",
    "wof:name":"Garciandia Dominguez Eva",
    "wof:placetype":"venue"
},
  "geometry": {"coordinates":[-2.0959429741,42.9323043823],"type":"Point"}
}