{
  "type": "Feature",
  "properties": {
    "addr:full":"Calle de Venezuela, 122 Llanos Las Palmas 35110",
    "addr:housenumber":"122",
    "addr:postcode":"35110",
    "addr:street":"Calle De Venezuela",
    "iso:country":"ES",
    "sg:address":"Calle de Venezuela, 122",
    "sg:city":"Llanos",
    "sg:orig_category":"Molduras, Junquillos, Listones Y Molduras Perforadas",
    "sg:phone":"+34 928 75 93 27",
    "sg:postcode":"35110",
    "sg:province":"Las Palmas",
    "wof:name":"Ortega Santana Juana Maria",
    "wof:placetype":"venue"
},
  "geometry": {"coordinates":[-15.4485340118,27.8392906189],"type":"Point"}
}