{
  "type": "Feature",
  "properties": {
    "addr:full":"Crri Castell, S/n Malaga M\u00e1laga 29016",
    "addr:housenumber":"s / n",
    "addr:postcode":"29016",
    "addr:street":"Ma\u0301Laga",
    "iso:country":"ES",
    "sg:address":"Crri Castell, S/n",
    "sg:city":"Malaga",
    "sg:orig_category":"Librer\u00cdas",
    "sg:phone":"+34 952 22 05 52",
    "sg:postcode":"29016",
    "sg:province":"M\u00e1laga",
    "wof:name":"Pinazo Robles Maria Jesus",
    "wof:placetype":"venue"
},
  "geometry": {"coordinates":[-4.4036607742,36.7266273499],"type":"Point"}
}