{
  "type": "Feature",
  "properties": {
    "iso:country":"ES",
    "sg:address":"Calle de Gibraltar, 30",
    "sg:city":"Huesca",
    "sg:orig_category":"Organizaciones Internacionales",
    "sg:phone":"+34 974 22 35 00",
    "sg:postcode":"22006",
    "sg:province":"Huesca",
    "wof:name":"Caritas Diocesana De Huesca",
    "wof:placetype":"venue"
},
  "geometry": {"coordinates":[-0.3971219957,42.1438217163],"type":"Point"}
}