{
  "type": "Feature",
  "properties": {
    "addr:full":"C/ Plana (la), 2 Tarrega Lleida 25300",
    "addr:housenumber":"2",
    "addr:postcode":"25300",
    "addr:street":"C / Plana La",
    "iso:country":"ES",
    "sg:address":"C/ Plana (la), 2",
    "sg:city":"Tarrega",
    "sg:orig_category":"Centros Empresariales",
    "sg:phone":"+34 973 31 44 44",
    "sg:postcode":"25300",
    "sg:province":"Lleida",
    "wof:name":"Jimenez Ortiz Pilar",
    "wof:placetype":"venue"
},
  "geometry": {"coordinates":[1.1405249834,41.6427497864],"type":"Point"}
}