{
  "type": "Feature",
  "properties": {
    "addr:full":"Carrer de Diputacio, 455 Barcelona Barcelona 08013",
    "addr:housenumber":"455",
    "addr:postcode":"08013",
    "addr:street":"Carrer De Diputacio",
    "iso:country":"ES",
    "sg:address":"Carrer de Diputacio, 455",
    "sg:city":"Barcelona",
    "sg:orig_category":"Comercio De Piezas De Recambio Y De Accesorios De Veh\u00cdculos, Veh\u00cdculos Industriales",
    "sg:phone":"+34 932 31 03 12",
    "sg:postcode":"08013",
    "sg:province":"Barcelona",
    "wof:name":"Castellon S. A.",
    "wof:placetype":"venue"
},
  "geometry": {"coordinates":[2.1802690029,41.4004859924],"type":"Point"}
}