{
  "type": "Feature",
  "properties": {
    "addr:full":"Ctra. Montuiri, Km. 0001,0 Porreres Islas Baleares 07260",
    "addr:postcode":"07260",
    "addr:street":"Ctra. Montuiri Km. 0001,0",
    "iso:country":"ES",
    "sg:address":"Ctra. Montuiri, Km. 0001,0",
    "sg:city":"Porreres",
    "sg:orig_category":"Empresas De Carpinter\u00cda De Madera",
    "sg:phone":"+34 971 64 77 00",
    "sg:postcode":"07260",
    "sg:province":"Islas Baleares",
    "wof:name":"Barcelo Bauza Mateo",
    "wof:placetype":"venue"
},
  "geometry": {"coordinates":[3.0226650238,39.5170059204],"type":"Point"}
}