{
  "type": "Feature",
  "properties": {
    "addr:full":"Calle de Sal, 3 Aranda Duero Burgos 09400",
    "addr:housenumber":"3",
    "addr:postcode":"09400",
    "addr:street":"Calle De Sal",
    "iso:country":"ES",
    "sg:address":"Calle de Sal, 3",
    "sg:city":"Aranda Duero",
    "sg:orig_category":"Cuchiller\u00cda (al Por Menor)",
    "sg:phone":"+34 947 50 19 20",
    "sg:postcode":"09400",
    "sg:province":"Burgos",
    "wof:name":"Alvarez Rodriguez Antonio",
    "wof:placetype":"venue"
},
  "geometry": {"coordinates":[-3.6896255016,41.6707191467],"type":"Point"}
}