{
  "type": "Feature",
  "properties": {
    "iso:country":"ES",
    "sg:address":"Calle de Pano Y Ruata, 4",
    "sg:city":"Zaragoza",
    "sg:orig_category":"Peleter\u00cdas",
    "sg:phone":"+34 976 51 64 69",
    "sg:postcode":"50015",
    "sg:province":"Zaragoza",
    "wof:name":"Confecciones Arapigam S.cv.",
    "wof:placetype":"venue"
},
  "geometry": {"coordinates":[-0.8753470182,41.6612548828],"type":"Point"}
}