{
  "type": "Feature",
  "properties": {
    "iso:country":"ES",
    "sg:address":"Ctra. Cadiz-algeciras, Km. 0018,0",
    "sg:city":"Barrio Nuevo",
    "sg:classifiers":[
        {
            "category":"Autos & Motor Vehicles",
            "subcategory":"Automobile Sales",
            "type":"Retail Goods"
        }
    ],
    "sg:phone":"+34 956 44 50 06",
    "sg:postcode":"11149",
    "sg:province":"C\u00e1diz",
    "wof:name":"Alba Garcia Francisco De",
    "wof:placetype":"venue"
},
  "geometry": {"coordinates":[-6.0872106552,36.3372688293],"type":"Point"}
}