{
  "type": "Feature",
  "properties": {
    "iso:country":"ES",
    "sg:address":"Calle de Sanchez Llevot, 3",
    "sg:city":"Alba Tormes",
    "sg:orig_category":"Chocolater\u00cda Y Exquisiteces",
    "sg:phone":"+34 923 37 05 73",
    "sg:postcode":"37800",
    "sg:province":"Salamanca",
    "sg:website":"www.ibericoscarlosreyes.com",
    "wof:name":"Embutidos Y Jamones Carlos Reyes S.l.",
    "wof:placetype":"venue"
},
  "geometry": {"coordinates":[-5.5139889717,40.8272628784],"type":"Point"}
}