{
  "type": "Feature",
  "properties": {
    "addr:full":"Carrer de Riu-sec, 73 Sabadell Barcelona 08205",
    "addr:housenumber":"73",
    "addr:postcode":"08205",
    "addr:street":"Carrer De Riu-Sec",
    "iso:country":"ES",
    "sg:address":"Carrer de Riu-sec, 73",
    "sg:city":"Sabadell",
    "sg:orig_category":"Revestimiento De Suelos Industriales",
    "sg:phone":"+34 902 19 41 87",
    "sg:postcode":"08205",
    "sg:province":"Barcelona",
    "wof:name":"Terres Industrials I Esportius S.l.",
    "wof:placetype":"venue"
},
  "geometry": {"coordinates":[2.09897995,41.541229248],"type":"Point"}
}