{
  "type": "Feature",
  "properties": {
    "iso:country":"ES",
    "sg:address":"Afueras, S/n",
    "sg:city":"Cristina",
    "sg:orig_category":"Muebles",
    "sg:phone":"+34 924 35 03 57",
    "sg:postcode":"06479",
    "sg:province":"Badajoz",
    "wof:name":"Garcia Morcillo Marcelino",
    "wof:placetype":"venue"
},
  "geometry": {"coordinates":[-6.0996975899,38.8182678223],"type":"Point"}
}