{
  "type": "Feature",
  "properties": {
    "addr:full":"Av Catalunya, 5 Vendrell Tarragona 43700",
    "addr:housenumber":"5",
    "addr:postcode":"43700",
    "addr:street":"Av Catalunya",
    "iso:country":"ES",
    "sg:address":"Av Catalunya, 5",
    "sg:city":"Vendrell",
    "sg:orig_category":"Peluqueros: De Se\u00d1oras",
    "sg:phone":"+34 977 66 71 47",
    "sg:postcode":"43700",
    "sg:province":"Tarragona",
    "wof:name":"Nin Prieto Maria Isabel",
    "wof:placetype":"venue"
},
  "geometry": {"coordinates":[1.5319839716,41.2202072144],"type":"Point"}
}