{
  "type": "Feature",
  "properties": {
    "addr:full":"Calle de Zamakoa, 8 Galdakao Vizcaya 48960",
    "addr:housenumber":"8",
    "addr:postcode":"48960",
    "addr:street":"Calle De Zamakoa",
    "iso:country":"ES",
    "sg:address":"Calle de Zamakoa, 8",
    "sg:city":"Galdakao",
    "sg:orig_category":"Librer\u00cdas",
    "sg:phone":"+34 944 56 60 26",
    "sg:postcode":"48960",
    "sg:province":"Vizcaya",
    "wof:name":"Susana Arzamendi Abenda\u00f1o",
    "wof:placetype":"venue"
},
  "geometry": {"coordinates":[-2.8425190449,43.2314338684],"type":"Point"}
}