{
  "type": "Feature",
  "properties": {
    "iso:country":"ES",
    "sg:address":"La Iglesia, S/n",
    "sg:city":"Setiles",
    "sg:orig_category":"Iglesia Cat\u00d3lica",
    "sg:phone":"+34 949 84 10 35",
    "sg:postcode":"19324",
    "sg:province":"Guadalajara",
    "wof:name":"Obispado De Siguenza-guadalajara",
    "wof:placetype":"venue"
},
  "geometry": {"coordinates":[-1.6181390285,40.7347373962],"type":"Point"}
}