{
  "type": "Feature",
  "properties": {
    "iso:country":"ES",
    "sg:address":"Avda Alcoy, 129",
    "sg:city":"Alacant",
    "sg:orig_category":"Cooperativas Agr\u00cdcolas",
    "sg:phone":"+34 965 24 24 08",
    "sg:postcode":"03009",
    "sg:province":"Alicante",
    "wof:name":"Acais Sociedad Cooperativa",
    "wof:placetype":"venue"
},
  "geometry": {"coordinates":[-0.4893271923,38.3572502136],"type":"Point"}
}