{
  "type": "Feature",
  "properties": {
    "addr:full":"Avda Constitucion, 90 Torrejon Ardoz Madrid 28850",
    "addr:housenumber":"90",
    "addr:postcode":"28850",
    "addr:street":"Avda Constitucion",
    "iso:country":"ES",
    "sg:address":"Avda Constitucion, 90",
    "sg:city":"Torrejon Ardoz",
    "sg:orig_category":"Farmacias",
    "sg:phone":"+34 916 55 51 63",
    "sg:postcode":"28850",
    "sg:province":"Madrid",
    "wof:name":"Jaime Guijarro Maria De",
    "wof:placetype":"venue"
},
  "geometry": {"coordinates":[-3.4732880592,40.4571342468],"type":"Point"}
}