{
  "type": "Feature",
  "properties": {
    "addr:full":"Calle de San Bernardo, 23 Onda Castell\u00f3n 12200",
    "addr:housenumber":"23",
    "addr:postcode":"12200",
    "addr:street":"Calle De San Bernardo;Castello\u0301N",
    "iso:country":"ES",
    "sg:address":"Calle de San Bernardo, 23",
    "sg:city":"Onda",
    "sg:orig_category":"Laboratorios Farmac\u00c9uticos",
    "sg:phone":"+34 964 77 08 50",
    "sg:postcode":"12200",
    "sg:province":"Castell\u00f3n",
    "wof:name":"Sancho Rovira Rosario Maria",
    "wof:placetype":"venue"
},
  "geometry": {"coordinates":[-0.2648200095,39.9636230469],"type":"Point"}
}