{
  "type": "Feature",
  "properties": {
    "addr:full":"Calle de San Nicolas, S/n Coru\u00d1a La Coru\u00f1a 15001",
    "addr:housenumber":"s",
    "addr:postcode":"15001",
    "addr:street":"Calle De San;/ N Corun\u0303A La Corun\u0303A",
    "iso:country":"ES",
    "sg:address":"Calle de San Nicolas, S/n",
    "sg:city":"Coru\u00d1a",
    "sg:orig_category":"Librer\u00cdas",
    "sg:phone":"+34 981 20 27 58",
    "sg:postcode":"15001",
    "sg:province":"La Coru\u00f1a",
    "wof:name":"Salgado Gomez Maria Teresa",
    "wof:placetype":"venue"
},
  "geometry": {"coordinates":[-8.3990268707,43.3710174561],"type":"Point"}
}