{
  "type": "Feature",
  "properties": {
    "iso:country":"ES",
    "sg:address":"Pol Ind Quiebracostilla, 73",
    "sg:city":"Baena",
    "sg:orig_category":"Soldadura Y Recortado A L\u00c1ser",
    "sg:phone":"+34 957 69 09 24",
    "sg:postcode":"14850",
    "sg:province":"C\u00f3rdoba",
    "wof:name":"Ordo\u00f1ez Y Castilla S.l.",
    "wof:placetype":"venue"
},
  "geometry": {"coordinates":[-4.323964119,37.6170043945],"type":"Point"}
}