{
  "type": "Feature",
  "properties": {
    "addr:full":"Ctra N-432 Badajoz-granada, Km. 0232,0 Villaharta C\u00f3rdoba 14210",
    "addr:housenumber":"villaharta",
    "addr:postcode":"14210",
    "addr:street":"Ctra N-432 Badajoz-Granada Km. 0232,0",
    "iso:country":"ES",
    "sg:address":"Ctra N-432 Badajoz-granada, Km. 0232,0",
    "sg:city":"Villaharta",
    "sg:orig_category":"Arenas, Guijarros Y Granulados",
    "sg:phone":"+34 957 36 71 65",
    "sg:postcode":"14210",
    "sg:province":"C\u00f3rdoba",
    "wof:name":"Aridos Yusber S.l.",
    "wof:placetype":"venue"
},
  "geometry": {"coordinates":[-4.8987522125,38.1355934143],"type":"Point"}
}