{
  "type": "Feature",
  "properties": {
    "iso:country":"ES",
    "sg:address":"Calle de Pedro Iii El Grande, 21",
    "sg:city":"Valencia",
    "sg:orig_category":"Peluquer\u00cdas",
    "sg:phone":"+34 963 95 25 76",
    "sg:postcode":"46005",
    "sg:province":"Valencia",
    "wof:name":"Pla Martinez Maria Jose",
    "wof:placetype":"venue"
},
  "geometry": {"coordinates":[-0.3674609959,39.4633827209],"type":"Point"}
}