{
  "type": "Feature",
  "properties": {
    "addr:full":"Carrer de Torras I Bages, 3 S. Celoni Barcelona 08470",
    "addr:housenumber":"3",
    "addr:postcode":"08470",
    "addr:street":"Carrer De Torras I Bages",
    "iso:country":"ES",
    "sg:address":"Carrer de Torras I Bages, 3",
    "sg:city":"S. Celoni",
    "sg:orig_category":"Agencias De Viajes",
    "sg:phone":"+34 938 67 31 25",
    "sg:postcode":"08470",
    "sg:province":"Barcelona",
    "wof:name":"Viatges Iberplan S.a.",
    "wof:placetype":"venue"
},
  "geometry": {"coordinates":[2.4917240143,41.6912536621],"type":"Point"}
}