{
  "type": "Feature",
  "properties": {
    "addr:full":"Calle de Valladolid, 7 Fuenlabrada Madrid 28941",
    "addr:housenumber":"7",
    "addr:postcode":"28941",
    "addr:street":"Calle De Valladolid",
    "iso:country":"ES",
    "sg:address":"Calle de Valladolid, 7",
    "sg:city":"Fuenlabrada",
    "sg:orig_category":"Ense\u00d1anza: Idiomas",
    "sg:phone":"+34 916 97 67 08",
    "sg:postcode":"28941",
    "sg:province":"Madrid",
    "wof:name":"Ortega Carpio Ana Maria",
    "wof:placetype":"venue"
},
  "geometry": {"coordinates":[-3.8042290211,40.2933578491],"type":"Point"}
}