{
  "type": "Feature",
  "properties": {
    "addr:full":"Carrer de Angela Roca, 2 Gava Barcelona 08850",
    "addr:housenumber":"2",
    "addr:postcode":"08850",
    "addr:street":"Carrer De Angela Roca",
    "iso:country":"ES",
    "sg:address":"Carrer de Angela Roca, 2",
    "sg:city":"Gava",
    "sg:orig_category":"Asociaciones, Organismos Culturales Y Socioeducativos",
    "sg:phone":"+34 936 62 09 63",
    "sg:postcode":"08850",
    "sg:province":"Barcelona",
    "wof:name":"Fundacio Viure I Conviure",
    "wof:placetype":"venue"
},
  "geometry": {"coordinates":[2.0040550232,41.3029327393],"type":"Point"}
}