{
  "type": "Feature",
  "properties": {
    "iso:country":"ES",
    "sg:address":"Calle de Gerona, 3",
    "sg:city":"Mairena Aljarafe",
    "sg:orig_category":"Asesor\u00cda Fiscal Y Jur\u00cddica",
    "sg:phone":"+34 954 17 13 76",
    "sg:postcode":"41927",
    "sg:province":"Sevilla",
    "wof:name":"Miguel Rincon Emilio De",
    "wof:placetype":"venue"
},
  "geometry": {"coordinates":[-6.0373978615,37.3556137085],"type":"Point"}
}