{
  "type": "Feature",
  "properties": {
    "iso:country":"ES",
    "sg:address":"La Raya, S/n",
    "sg:city":"Pilar Horadada",
    "sg:orig_category":"Artesan\u00cda",
    "sg:phone":"+34 965 35 12 82",
    "sg:postcode":"03190",
    "sg:province":"Alicante",
    "wof:name":"Gimenez Perez Maria Dolores",
    "wof:placetype":"venue"
},
  "geometry": {"coordinates":[-0.7898390293,37.8640213013],"type":"Point"}
}