{
  "type": "Feature",
  "properties": {
    "addr:full":"Calle de San Martin, 9 Donostia-san Sebastian Guip\u00f9zcoa 20005",
    "addr:housenumber":"9",
    "addr:postcode":"20005",
    "addr:street":"Calle De San Martin",
    "iso:country":"ES",
    "sg:address":"Calle de San Martin, 9",
    "sg:city":"Donostia-san Sebastian",
    "sg:orig_category":"Psicoterapeutas",
    "sg:phone":"+34 943 42 66 57",
    "sg:postcode":"20005",
    "sg:province":"Guip\u00f9zcoa",
    "wof:name":"Ezpeleta Pradera Juan",
    "wof:placetype":"venue"
},
  "geometry": {"coordinates":[-1.9805710316,43.3178291321],"type":"Point"}
}