{
  "type": "Feature",
  "properties": {
    "iso:country":"ES",
    "sg:address":"Pg Independencia (de La), 10",
    "sg:city":"Tarragona",
    "sg:orig_category":"Molduras, Junquillos, Listones Y Molduras Perforadas",
    "sg:phone":"+34 977 24 00 04",
    "sg:postcode":"43005",
    "sg:province":"Tarragona",
    "wof:name":"Quilez Morales Jose",
    "wof:placetype":"venue"
},
  "geometry": {"coordinates":[1.2384779453,41.1131629944],"type":"Point"}
}