{
  "type": "Feature",
  "properties": {
    "iso:country":"ES",
    "sg:address":"Cmno Valderribas, 115",
    "sg:city":"Madrid",
    "sg:orig_category":"Empresarios",
    "sg:phone":"+34 917 77 55 44",
    "sg:postcode":"28038",
    "sg:province":"Madrid",
    "sg:website":"www.medula.org",
    "wof:name":"Fundacion Para La Rehabilitacion Del Lesionado Medular",
    "wof:placetype":"venue"
},
  "geometry": {"coordinates":[-3.6546640396,40.3976173401],"type":"Point"}
}