{
  "type": "Feature",
  "properties": {
    "addr:full":"Calle de San Ignacio De Loyola, 6 Zaragoza Zaragoza 50008",
    "addr:housenumber":"6",
    "addr:postcode":"50008",
    "addr:street":"Calle De San Ignacio De Loyola",
    "iso:country":"ES",
    "sg:address":"Calle de San Ignacio De Loyola, 6",
    "sg:city":"Zaragoza",
    "sg:orig_category":"Fabricaci\u00d3n De Sobres, Bolsas Y Fundas",
    "sg:phone":"+34 976 21 35 50",
    "sg:postcode":"50008",
    "sg:province":"Zaragoza",
    "wof:name":"Frag Comercio Internacional S.l.",
    "wof:placetype":"venue"
},
  "geometry": {"coordinates":[-0.882750988,41.6475448608],"type":"Point"}
}