{
  "type": "Feature",
  "properties": {
    "addr:full":"Avda Xemein, 19 Markina-xemein Vizcaya 48270",
    "addr:housenumber":"19",
    "addr:postcode":"48270",
    "addr:street":"Avda Xemein",
    "iso:country":"ES",
    "sg:address":"Avda Xemein, 19",
    "sg:city":"Markina-xemein",
    "sg:orig_category":"Ense\u00d1anza, Formaci\u00d3n Profesional: Aprendizaje",
    "sg:phone":"+34 946 16 90 02",
    "sg:postcode":"48270",
    "sg:province":"Vizcaya",
    "wof:name":"Escuela Profesional Comarcal Lea-artibai",
    "wof:placetype":"venue"
},
  "geometry": {"coordinates":[-2.4941339493,43.2699432373],"type":"Point"}
}