{
  "type": "Feature",
  "properties": {
    "iso:country":"ES",
    "sg:address":"Disseminat, S/n",
    "sg:city":"Ametlla Valles",
    "sg:orig_category":"Agricultores, Agricultores",
    "sg:phone":"+34 937 44 50 49",
    "sg:postcode":"08480",
    "sg:province":"Barcelona",
    "wof:name":"Granja El Prat S. A. T.",
    "wof:placetype":"venue"
},
  "geometry": {"coordinates":[2.2651150227,41.665851593],"type":"Point"}
}