{
  "type": "Feature",
  "properties": {
    "addr:full":"Calle de Font Nova, 1 Alcora Castell\u00f3n 12110",
    "addr:housenumber":"1",
    "addr:postcode":"12110",
    "addr:street":"Calle De Font Nova;Castello\u0301N",
    "iso:country":"ES",
    "sg:address":"Calle de Font Nova, 1",
    "sg:city":"Alcora",
    "sg:orig_category":"Electricidad: Instaladores",
    "sg:phone":"+34 964 36 08 24",
    "sg:postcode":"12110",
    "sg:province":"Castell\u00f3n",
    "wof:name":"Iserte Badenas S.l.",
    "wof:placetype":"venue"
},
  "geometry": {"coordinates":[-0.2104018033,40.079662323],"type":"Point"}
}