{
  "type": "Feature",
  "properties": {
    "iso:country":"ES",
    "sg:address":"Avda Medina Azahara (de), 37",
    "sg:city":"Cordoba",
    "sg:orig_category":"Ropa Para Se\u00d1oras Y Caballeros (al Por Menor)",
    "sg:phone":"+34 957 23 23 79",
    "sg:postcode":"14005",
    "sg:province":"C\u00f3rdoba",
    "wof:name":"Tejidos Ulises S.l.",
    "wof:placetype":"venue"
},
  "geometry": {"coordinates":[-4.7920160294,37.8851776123],"type":"Point"}
}