{
  "type": "Feature",
  "properties": {
    "iso:country":"ES",
    "sg:address":"Calle de Parras, S/n",
    "sg:city":"Ogijares",
    "sg:orig_category":"Centros De Educaci\u00d3n Especial",
    "sg:phone":"+34 958 50 71 66",
    "sg:postcode":"18151",
    "sg:province":"Granada",
    "wof:name":"Delegacion Provincial De La Consejeria De Educacion Y Ciencia De La Junta De Andalucia",
    "wof:placetype":"venue"
},
  "geometry": {"coordinates":[-3.6064229012,37.1237487793],"type":"Point"}
}