{
  "type": "Feature",
  "properties": {
    "iso:country":"ES",
    "sg:address":"Calle de Alameda Del Fresno, 12",
    "sg:city":"Valmojado",
    "sg:orig_category":"Productores Recolectores, Venta Directa De Vinos",
    "sg:phone":"+34 918 17 04 39",
    "sg:postcode":"45940",
    "sg:province":"Toledo",
    "wof:name":"Distrimor S.l.",
    "wof:placetype":"venue"
},
  "geometry": {"coordinates":[-4.0928378105,40.2077636719],"type":"Point"}
}