{
  "type": "Feature",
  "properties": {
    "addr:full":"Av Pompeu Fabra, 122 Palafrugell Girona 17200",
    "addr:housenumber":"122",
    "addr:postcode":"17200",
    "addr:street":"Av Pompeu Fabra",
    "iso:country":"ES",
    "sg:address":"Av Pompeu Fabra, 122",
    "sg:city":"Palafrugell",
    "sg:orig_category":"Centros Comerciales Y Grandes Tiendas",
    "sg:phone":"+34 972 30 31 97",
    "sg:postcode":"17200",
    "sg:province":"Girona",
    "wof:name":"Platja Ferro Josep",
    "wof:placetype":"venue"
},
  "geometry": {"coordinates":[3.1712698936,41.9208335876],"type":"Point"}
}