{
  "type": "Feature",
  "properties": {
    "addr:full":"Avgd Alcalde Porqueres, 2 Lleida Lleida 25008",
    "addr:housenumber":"2",
    "addr:postcode":"25008",
    "addr:street":"Alcalde Porqueres",
    "iso:country":"ES",
    "sg:address":"Avgd Alcalde Porqueres, 2",
    "sg:city":"Lleida",
    "sg:orig_category":"Peluquer\u00cdas, Peluquer\u00cda Mixta",
    "sg:phone":"+34 973 22 42 33",
    "sg:postcode":"25008",
    "sg:province":"Lleida",
    "wof:name":"Estil Propi S.c.m.",
    "wof:placetype":"venue"
},
  "geometry": {"coordinates":[0.622780025,41.6215705872],"type":"Point"}
}