{
  "type": "Feature",
  "properties": {
    "addr:full":"Avda Gregorio Diego, S/n Malaga M\u00e1laga 29004",
    "addr:postcode":"29004",
    "addr:street":"Avda Gregorio Diego S / N;Ma\u0301Laga",
    "iso:country":"ES",
    "sg:address":"Avda Gregorio Diego, S/n",
    "sg:city":"Malaga",
    "sg:orig_category":"Carnicer\u00cdas, Carnicer\u00cdas",
    "sg:phone":"+34 952 23 21 92",
    "sg:postcode":"29004",
    "sg:province":"M\u00e1laga",
    "wof:name":"Juan Diaz Guerrero S.l.",
    "wof:placetype":"venue"
},
  "geometry": {"coordinates":[-4.4516100883,36.6897659302],"type":"Point"}
}