{
  "type": "Feature",
  "properties": {
    "addr:full":"Calle de Larramendi Kalea, 11 Tolosa Guip\u00f9zcoa 20400",
    "addr:housenumber":"11",
    "addr:postcode":"20400",
    "addr:street":"Calle De Larramendi Kalea;Guipu\u0300Zcoa",
    "iso:country":"ES",
    "sg:address":"Calle de Larramendi Kalea, 11",
    "sg:city":"Tolosa",
    "sg:orig_category":"Asociaciones Y Clubs Deportivos",
    "sg:phone":"+34 943 01 62 03",
    "sg:postcode":"20400",
    "sg:province":"Guip\u00f9zcoa",
    "wof:name":"Francisco Jose Lopez Juarez Y Otro Cb",
    "wof:placetype":"venue"
},
  "geometry": {"coordinates":[-2.0712060928,43.1439933777],"type":"Point"}
}