{
  "type": "Feature",
  "properties": {
    "addr:full":"Calle de Felipe Asenjo, 23 Fuenlabrada Madrid 28947",
    "addr:housenumber":"23",
    "addr:postcode":"28947",
    "addr:street":"Calle De Felipe Asenjo",
    "iso:country":"ES",
    "sg:address":"Calle de Felipe Asenjo, 23",
    "sg:city":"Fuenlabrada",
    "sg:orig_category":"Marroquiner\u00cda (confecci\u00d3n)",
    "sg:phone":"+34 916 42 03 48",
    "sg:postcode":"28947",
    "sg:province":"Madrid",
    "wof:name":"Charex Modas S.l.",
    "wof:placetype":"venue"
},
  "geometry": {"coordinates":[-3.7437589169,40.2631378174],"type":"Point"}
}