{
  "type": "Feature",
  "properties": {
    "addr:full":"Ctra San Bartolome, Km. 0000,9 Argana Baja Las Palmas 35500",
    "addr:postcode":"35500",
    "addr:street":"Ctra San Bartolome Km. 0000,9",
    "iso:country":"ES",
    "sg:address":"Ctra San Bartolome, Km. 0000,9",
    "sg:city":"Argana Baja",
    "sg:orig_category":"Transportes Por Carretera: Lotes Completos, Mercanc\u00cdas Diversas",
    "sg:phone":"+34 928 81 66 00",
    "sg:postcode":"35500",
    "sg:province":"Las Palmas",
    "wof:name":"Lancelot Distribuciones S. A.",
    "wof:placetype":"venue"
},
  "geometry": {"coordinates":[-13.5490036011,28.9582099915],"type":"Point"}
}