{
  "type": "Feature",
  "properties": {
    "addr:full":"Ctra. Lluc, Km. 0003,8 Pollen\u00e7a Islas Baleares 07460",
    "addr:postcode":"07460",
    "addr:street":"Ctra. Lluc Km. 0003,8",
    "iso:country":"ES",
    "sg:address":"Ctra. Lluc, Km. 0003,8",
    "sg:city":"Pollen\u00e7a",
    "sg:orig_category":"Cr\u00cda De Animales",
    "sg:phone":"+34 971 53 13 66",
    "sg:postcode":"07460",
    "sg:province":"Islas Baleares",
    "wof:name":"L'eresta S.l.",
    "wof:placetype":"venue"
},
  "geometry": {"coordinates":[3.00364995,39.8785095215],"type":"Point"}
}