{
  "type": "Feature",
  "properties": {
    "iso:country":"ES",
    "sg:address":"Plaz Generalisimo, 11",
    "sg:city":"Fuenllana",
    "sg:orig_category":"Transportes Por Carretera: Lotes Completos, Mercanc\u00cdas Diversas",
    "sg:phone":"+34 926 35 00 08",
    "sg:postcode":"13333",
    "sg:province":"Ciudad Real",
    "wof:name":"Aguado Ruiz Luisa",
    "wof:placetype":"venue"
},
  "geometry": {"coordinates":[-2.9589061737,38.7566452026],"type":"Point"}
}