{
  "type": "Feature",
  "properties": {
    "iso:country":"ES",
    "sg:address":"Calle de Cruz Blanca, 2",
    "sg:city":"Vitoria-gasteiz",
    "sg:orig_category":"Muebles Y Accesorios Para Cocinas Y Cuartos De Ba\u00d1o (al Por Menor)",
    "sg:phone":"+34 945 22 54 68",
    "sg:postcode":"01012",
    "sg:province":"\u00c1lava",
    "wof:name":"Gil Y Hernandez Cocinas S.l.",
    "wof:placetype":"venue"
},
  "geometry": {"coordinates":[-2.6775891781,42.8522796631],"type":"Point"}
}