{
  "type": "Feature",
  "properties": {
    "addr:full":"Calle de Nuestra Se\u00d1ora Del Carmen, S/n S. Pedro Pinatar Murcia 30740",
    "addr:housenumber":"s",
    "addr:postcode":"30740",
    "addr:street":"Calle De Nuestra Sen\u0303Ora Del Carmen;/ N S. Pedro",
    "iso:country":"ES",
    "sg:address":"Calle de Nuestra Se\u00d1ora Del Carmen, S/n",
    "sg:city":"S. Pedro Pinatar",
    "sg:orig_category":"Alimentaci\u00d3n General (al Por Menor)",
    "sg:phone":"+34 968 18 22 59",
    "sg:postcode":"30740",
    "sg:province":"Murcia",
    "wof:name":"Saez Escudero Jose Luis",
    "wof:placetype":"venue"
},
  "geometry": {"coordinates":[-0.7937290072,37.8368759155],"type":"Point"}
}