{
  "type": "Feature",
  "properties": {
    "addr:full":"Calle de Karmelo Etxegarai, 51 Billela Vizcaya 48100",
    "addr:housenumber":"51",
    "addr:postcode":"48100",
    "addr:street":"Calle De Karmelo Etxegarai",
    "iso:country":"ES",
    "sg:address":"Calle de Karmelo Etxegarai, 51",
    "sg:city":"Billela",
    "sg:orig_category":"Rectificaci\u00d3n, Mecanizado, Fresado",
    "sg:phone":"+34 946 15 56 65",
    "sg:postcode":"48100",
    "sg:province":"Vizcaya",
    "wof:name":"Llona Uriarte Juan Jose",
    "wof:placetype":"venue"
},
  "geometry": {"coordinates":[-2.852679491,43.3640518188],"type":"Point"}
}