{
  "type": "Feature",
  "properties": {
    "addr:full":"Calle de Cervantes, 4 Merida Badajoz 06800",
    "addr:housenumber":"4",
    "addr:postcode":"06800",
    "addr:street":"Calle De Cervantes",
    "iso:country":"ES",
    "sg:address":"Calle de Cervantes, 4",
    "sg:city":"Merida",
    "sg:orig_category":"Trajes Y Adornos De Boda (confecci\u00d3n, Al Por Menor)",
    "sg:phone":"+34 924 33 05 91",
    "sg:postcode":"06800",
    "sg:province":"Badajoz",
    "wof:name":"Garcia Morcillo Petra",
    "wof:placetype":"venue"
},
  "geometry": {"coordinates":[-6.385225296,38.8869476318],"type":"Point"}
}