{
  "type": "Feature",
  "properties": {
    "addr:full":"Calle de Pintor Clemente Arraiz, 12 Vitoria-gasteiz \u00c1lava 01008",
    "addr:housenumber":"12",
    "addr:postcode":"01008",
    "addr:street":"Calle De Pintor Clemente Arraiz",
    "iso:country":"ES",
    "sg:address":"Calle de Pintor Clemente Arraiz, 12",
    "sg:city":"Vitoria-gasteiz",
    "sg:orig_category":"Servicios Gsm",
    "sg:phone":"+34 945 21 33 72",
    "sg:postcode":"01008",
    "sg:province":"\u00c1lava",
    "sg:website":"www.stelsmobile.com",
    "wof:name":"Stels Mobile S.l.",
    "wof:placetype":"venue"
},
  "geometry": {"coordinates":[-2.6856079102,42.8505973816],"type":"Point"}
}