{
  "type": "Feature",
  "properties": {
    "iso:country":"ES",
    "sg:address":"Calle de Do\u00d1a Perfecta, 103",
    "sg:city":"Palmas De Gran Canaria",
    "sg:orig_category":"Empresas De Carpinter\u00cda Met\u00c1lica",
    "sg:phone":"+34 928 25 01 61",
    "sg:postcode":"35012",
    "sg:province":"Las Palmas",
    "wof:name":"Medie Dominguez Jose",
    "wof:placetype":"venue"
},
  "geometry": {"coordinates":[-15.4346513748,28.1094551086],"type":"Point"}
}