{
  "type": "Feature",
  "properties": {
    "addr:full":"Carrer de M D Montserrat, 97 Viladecans Barcelona 08840",
    "addr:housenumber":"97",
    "addr:postcode":"08840",
    "addr:street":"Carrer De M;Montserrat",
    "iso:country":"ES",
    "sg:address":"Carrer de M D Montserrat, 97",
    "sg:city":"Viladecans",
    "sg:orig_category":"Quincaller\u00cda (al Por Menor)",
    "sg:phone":"+34 936 58 45 12",
    "sg:postcode":"08840",
    "sg:province":"Barcelona",
    "wof:name":"Aragon Gil Miguel",
    "wof:placetype":"venue"
},
  "geometry": {"coordinates":[2.0119290352,41.3184585571],"type":"Point"}
}