{
  "type": "Feature",
  "properties": {
    "iso:country":"ES",
    "sg:address":"Ctra Cenicientos, S/n",
    "sg:city":"Cadalso De Los Vidrios",
    "sg:orig_category":"Fabricaci\u00d3n De Productos L\u00c1cteos Y Derivados",
    "sg:phone":"+34 918 64 13 18",
    "sg:postcode":"28640",
    "sg:province":"Madrid",
    "wof:name":"Victorio Gonzalez S.l.",
    "wof:placetype":"venue"
},
  "geometry": {"coordinates":[-4.4458889961,40.2999038696],"type":"Point"}
}