{
  "type": "Feature",
  "properties": {
    "iso:country":"ES",
    "sg:address":"Plaz Constitucion (de La), 3",
    "sg:city":"Humanes De Madrid",
    "sg:orig_category":"Alimentaci\u00d3n General (al Por Menor)",
    "sg:phone":"+34 916 04 01 04",
    "sg:postcode":"28970",
    "sg:province":"Madrid",
    "wof:name":"Zazo Varela Juan",
    "wof:placetype":"venue"
},
  "geometry": {"coordinates":[-3.8299105167,40.2507858276],"type":"Point"}
}