{
  "type": "Feature",
  "properties": {
    "iso:country":"ES",
    "sg:address":"Avda Madrid (de), Km. 0332,0",
    "sg:city":"Jaen",
    "sg:orig_category":"Organizaci\u00d3n De Actos, Seminarios Y Congresos",
    "sg:phone":"+34 953 28 05 92",
    "sg:postcode":"23008",
    "sg:province":"Ja\u00e9n",
    "wof:name":"Restaurante Ruta Del Sol",
    "wof:placetype":"venue"
},
  "geometry": {"coordinates":[-3.7850589752,37.7785797119],"type":"Point"}
}