{
  "type": "Feature",
  "properties": {
    "addr:full":"Av Diputacio, 175 Cambrils Tarragona 43850",
    "addr:housenumber":"175",
    "addr:postcode":"43850",
    "addr:street":"Av Diputacio",
    "iso:country":"ES",
    "sg:address":"Av Diputacio, 175",
    "sg:city":"Cambrils",
    "sg:orig_category":"Alquiler De Veh\u00cdculos: Turismos Y Utilitarios",
    "sg:phone":"+34 977 35 02 74",
    "sg:postcode":"43850",
    "sg:province":"Tarragona",
    "wof:name":"Pineda Carfil Group S.l.",
    "wof:placetype":"venue"
},
  "geometry": {"coordinates":[1.0737299919,41.0664405823],"type":"Point"}
}