{
  "type": "Feature",
  "properties": {
    "iso:country":"ES",
    "sg:address":"Ctra. Cazalilla, S/n",
    "sg:city":"Mengibar",
    "sg:orig_category":"Reposter\u00cdas",
    "sg:phone":"+34 953 37 09 11",
    "sg:postcode":"23620",
    "sg:province":"Ja\u00e9n",
    "wof:name":"Sociedad Cooperativa San Anton",
    "wof:placetype":"venue"
},
  "geometry": {"coordinates":[-3.8147990704,37.9722213745],"type":"Point"}
}