{
  "type": "Feature",
  "properties": {
    "addr:full":"Calle de Labayru, 23 Bilbao Vizcaya 48012",
    "addr:housenumber":"23",
    "addr:postcode":"48012",
    "addr:street":"Calle De Labayru",
    "iso:country":"ES",
    "sg:address":"Calle de Labayru, 23",
    "sg:city":"Bilbao",
    "sg:orig_category":"Suministros Y Materiales Industriales",
    "sg:phone":"+34 944 21 62 59",
    "sg:postcode":"48012",
    "sg:province":"Vizcaya",
    "wof:name":"Suministros Labayru, S.l.",
    "wof:placetype":"venue"
},
  "geometry": {"coordinates":[-2.939428091,43.2565574646],"type":"Point"}
}