{
  "type": "Feature",
  "properties": {
    "addr:full":"Carrer de Menorca, 20 Palma Islas Baleares 07011",
    "addr:housenumber":"20",
    "addr:postcode":"07011",
    "addr:street":"Carrer De Menorca",
    "iso:country":"ES",
    "sg:address":"Carrer de Menorca, 20",
    "sg:city":"Palma",
    "sg:orig_category":"Peluqueros: De Se\u00d1oras",
    "sg:phone":"+34 971 45 73 64",
    "sg:postcode":"07011",
    "sg:province":"Islas Baleares",
    "wof:name":"Pedrero Morey Barbara",
    "wof:placetype":"venue"
},
  "geometry": {"coordinates":[2.642334938,39.5753211975],"type":"Point"}
}