{
  "type": "Feature",
  "properties": {
    "iso:country":"ES",
    "sg:address":"Calle de Mayor, 1",
    "sg:city":"S. Pedro Manrique",
    "sg:orig_category":"Frutas, Legumbres Frescas Y Tempranas (al Por Menor)",
    "sg:phone":"+34 975 38 10 07",
    "sg:postcode":"42174",
    "sg:province":"Soria",
    "wof:name":"Rincon Ruiz Sergio Del",
    "wof:placetype":"venue"
},
  "geometry": {"coordinates":[-2.2316548824,42.0306663513],"type":"Point"}
}