{
  "type": "Feature",
  "properties": {
    "addr:full":"Carrer de Josep Umbert, 57 Granollers Barcelona 08402",
    "addr:housenumber":"57",
    "addr:postcode":"08402",
    "addr:street":"Carrer De Josep Umbert",
    "iso:country":"ES",
    "sg:address":"Carrer de Josep Umbert, 57",
    "sg:city":"Granollers",
    "sg:orig_category":"Peluquer\u00cdas",
    "sg:phone":"+34 938 79 36 64",
    "sg:postcode":"08402",
    "sg:province":"Barcelona",
    "wof:name":"Pineda Estiban Inma",
    "wof:placetype":"venue"
},
  "geometry": {"coordinates":[2.2920980453,41.6050643921],"type":"Point"}
}