{
  "type": "Feature",
  "properties": {
    "iso:country":"ES",
    "sg:address":"Calle de Compostela, 2",
    "sg:city":"Tui",
    "sg:orig_category":"Sociedades, Compa\u00d1\u00cdas Aseguradoras",
    "sg:phone":"+34 986 60 07 86",
    "sg:postcode":"36700",
    "sg:province":"Pontevedra",
    "wof:name":"Seguros Catalana Occidente S.a. De Seguros Y Reaseguros",
    "wof:placetype":"venue"
},
  "geometry": {"coordinates":[-8.6465854645,42.0506286621],"type":"Point"}
}