{
  "type": "Feature",
  "properties": {
    "addr:full":"Calle de Camino, 4 Donostia-san Sebastian Guip\u00f9zcoa 20004",
    "addr:housenumber":"4",
    "addr:postcode":"20004",
    "addr:street":"Calle De Camino",
    "iso:country":"ES",
    "sg:address":"Calle de Camino, 4",
    "sg:city":"Donostia-san Sebastian",
    "sg:orig_category":"Molduras, Junquillos, Listones Y Molduras Perforadas",
    "sg:phone":"+34 943 42 62 84",
    "sg:postcode":"20004",
    "sg:province":"Guip\u00f9zcoa",
    "wof:name":"Alejandro Legarda Iturrioz",
    "wof:placetype":"venue"
},
  "geometry": {"coordinates":[-1.9809875488,43.321056366],"type":"Point"}
}