{
  "type": "Feature",
  "properties": {
    "addr:full":"Avda Mediterraneo, 2 Santiago Ribera Murcia 30720",
    "addr:housenumber":"2",
    "addr:postcode":"30720",
    "addr:street":"Avda Mediterraneo",
    "iso:country":"ES",
    "sg:address":"Avda Mediterraneo, 2",
    "sg:city":"Santiago Ribera",
    "sg:orig_category":"Oficinas Y Gesti\u00d3n De Inmuebles",
    "sg:phone":"+34 968 57 29 04",
    "sg:postcode":"30720",
    "sg:province":"Murcia",
    "wof:name":"Peinsa 97 S.l.",
    "wof:placetype":"venue"
},
  "geometry": {"coordinates":[-0.8093990088,37.8024864197],"type":"Point"}
}