{
  "type": "Feature",
  "properties": {
    "iso:country":"ES",
    "sg:address":"Avda Pablo Neruda, 100",
    "sg:city":"Madrid",
    "sg:orig_category":"Molduras, Junquillos, Listones Y Molduras Perforadas",
    "sg:phone":"+34 913 03 09 08",
    "sg:postcode":"28018",
    "sg:province":"Madrid",
    "wof:name":"Sanchez Garcia Juana",
    "wof:placetype":"venue"
},
  "geometry": {"coordinates":[-3.653660059,40.3816452026],"type":"Point"}
}