{
  "type": "Feature",
  "properties": {
    "iso:country":"ES",
    "sg:address":"Calle de Masustegi, 19",
    "sg:city":"Bilbao",
    "sg:orig_category":"Electricidad: Instaladores",
    "sg:phone":"+34 944 15 93 04",
    "sg:postcode":"48006",
    "sg:province":"Vizcaya",
    "wof:name":"Siscom Empresas S.l.",
    "wof:placetype":"venue"
},
  "geometry": {"coordinates":[-2.9136788845,43.2574424744],"type":"Point"}
}