{
  "type": "Feature",
  "properties": {
    "addr:full":"Pl Porta Pintada, 1 Palma Islas Baleares 07002",
    "addr:housenumber":"1",
    "addr:postcode":"07002",
    "addr:street":"Pl Porta Pintada",
    "iso:country":"ES",
    "sg:address":"Pl Porta Pintada, 1",
    "sg:city":"Palma",
    "sg:orig_category":"Abogados",
    "sg:phone":"+34 971 21 35 12",
    "sg:postcode":"07002",
    "sg:province":"Islas Baleares",
    "wof:name":"Lopez Clapes Carlos",
    "wof:placetype":"venue"
},
  "geometry": {"coordinates":[2.6524689198,39.575138092],"type":"Point"}
}