{
  "type": "Feature",
  "properties": {
    "addr:full":"Carr Gracia, 132 Mao Islas Baleares 07702",
    "addr:housenumber":"132",
    "addr:postcode":"07702",
    "addr:street":"Carr Gracia",
    "iso:country":"ES",
    "sg:address":"Carr Gracia, 132",
    "sg:city":"Mao",
    "sg:classifiers":[
        {
            "category":"Personal",
            "subcategory":"Barber",
            "type":"Services"
        }
    ],
    "sg:phone":"+34 971 36 02 05",
    "sg:postcode":"07702",
    "sg:province":"Islas Baleares",
    "sg:tags":[
        "caballeros",
        "de",
        "peluqueros"
    ],
    "wof:name":"Pons Sintes Antonio",
    "wof:placetype":"venue"
},
  "geometry": {"coordinates":[4.2631430626,39.8853225708],"type":"Point"}
}