{
  "type": "Feature",
  "properties": {
    "addr:full":"Calle de Perez Vaquero, 4 Pozuelo De Alarcon Madrid 28223",
    "addr:housenumber":"4",
    "addr:postcode":"28223",
    "addr:street":"Calle De Perez Vaquero",
    "iso:country":"ES",
    "sg:address":"Calle de Perez Vaquero, 4",
    "sg:city":"Pozuelo De Alarcon",
    "sg:orig_category":"Revestimientos Industriales",
    "sg:phone":"+34 913 52 61 87",
    "sg:postcode":"28223",
    "sg:province":"Madrid",
    "wof:name":"Gravin Monocapas S.l.",
    "wof:placetype":"venue"
},
  "geometry": {"coordinates":[-3.8192379475,40.4378433228],"type":"Point"}
}