{
  "type": "Feature",
  "properties": {
    "addr:full":"Calle de Ca\u00d1ada Real De La Mesta (de La), S/n Pinto Madrid 28320",
    "addr:postcode":"28320",
    "addr:street":"Calle De Can\u0303Ada Real De La Mesta De La S / N Pinto",
    "iso:country":"ES",
    "sg:address":"Calle de Ca\u00d1ada Real De La Mesta (de La), S/n",
    "sg:city":"Pinto",
    "sg:orig_category":"Molduras, Junquillos, Listones Y Molduras Perforadas",
    "sg:phone":"+34 916 91 22 99",
    "sg:postcode":"28320",
    "sg:province":"Madrid",
    "wof:name":"Rodriguez Sanz Antonio",
    "wof:placetype":"venue"
},
  "geometry": {"coordinates":[-3.6924619675,40.2477302551],"type":"Point"}
}