{
  "type": "Feature",
  "properties": {
    "iso:country":"ES",
    "sg:address":"Calle de Covadonga, S/n",
    "sg:city":"Caridad",
    "sg:orig_category":"Prot\u00c9sicos Dentales",
    "sg:phone":"+34 985 63 77 71",
    "sg:postcode":"33750",
    "sg:province":"Asturias",
    "wof:name":"Garcia Carbajal Jose Manuel",
    "wof:placetype":"venue"
},
  "geometry": {"coordinates":[-6.8292870522,43.5492095947],"type":"Point"}
}