{
  "type": "Feature",
  "properties": {
    "iso:country":"ES",
    "sg:address":"Plaz Espa\u00d1a, 5",
    "sg:city":"Salamanca",
    "sg:orig_category":"Lencer\u00cda Femenina, Corseter\u00cda, Trajes De Ba\u00d1o (al Por Menor)",
    "sg:phone":"+34 923 12 05 25",
    "sg:postcode":"37004",
    "sg:province":"Salamanca",
    "wof:name":"Villa Taboada Ana Maria",
    "wof:placetype":"venue"
},
  "geometry": {"coordinates":[-5.6583662033,40.9686698914],"type":"Point"}
}