{
  "type": "Feature",
  "properties": {
    "iso:country":"ES",
    "sg:address":"Avda Paz, 207",
    "sg:city":"Yecla",
    "sg:orig_category":"Fabricaci\u00d3n De Taburetes, Sillas Y Sillones",
    "sg:phone":"+34 968 79 10 26",
    "sg:postcode":"30510",
    "sg:province":"Murcia",
    "wof:name":"Funcional Mobiliario S.l.",
    "wof:placetype":"venue"
},
  "geometry": {"coordinates":[-1.1341376305,38.6130447388],"type":"Point"}
}