{
  "type": "Feature",
  "properties": {
    "iso:country":"ES",
    "sg:address":"Carr Calvario, 36",
    "sg:city":"Betera",
    "sg:orig_category":"Reposter\u00cdas",
    "sg:phone":"+34 961 60 04 35",
    "sg:postcode":"46117",
    "sg:province":"Valencia",
    "wof:name":"Ricart Aloy Salvador",
    "wof:placetype":"venue"
},
  "geometry": {"coordinates":[-0.4610889852,39.5907173157],"type":"Point"}
}