{
  "type": "Feature",
  "properties": {
    "iso:country":"ES",
    "sg:address":"Av S'agaro, 77",
    "sg:city":"Platja D'aro",
    "sg:orig_category":"Molduras, Junquillos, Listones Y Molduras Perforadas",
    "sg:phone":"+34 972 81 84 24",
    "sg:postcode":"17250",
    "sg:province":"Girona",
    "wof:name":"Arodome S. L.",
    "wof:placetype":"venue"
},
  "geometry": {"coordinates":[3.0555799007,41.8058815002],"type":"Point"}
}