{
  "type": "Feature",
  "properties": {
    "addr:full":"Carrer de Riudoms, 18 Barcelona Barcelona 08038",
    "addr:housenumber":"18",
    "addr:postcode":"08038",
    "addr:street":"Carrer De Riudoms",
    "iso:country":"ES",
    "sg:address":"Carrer de Riudoms, 18",
    "sg:city":"Barcelona",
    "sg:orig_category":"Poller\u00cda Y Caza (al Por Menor)",
    "sg:phone":"+34 932 23 28 46",
    "sg:postcode":"08038",
    "sg:province":"Barcelona",
    "wof:name":"Martinez Cantabella Francisco",
    "wof:placetype":"venue"
},
  "geometry": {"coordinates":[2.1422269344,41.3526535034],"type":"Point"}
}