{
  "type": "Feature",
  "properties": {
    "addr:full":"Carrer de Cobalt, 62 Hospitalet Llobregat Barcelona 08907",
    "addr:housenumber":"62",
    "addr:postcode":"08907",
    "addr:street":"Carrer De Cobalt",
    "iso:country":"ES",
    "sg:address":"Carrer de Cobalt, 62",
    "sg:city":"Hospitalet Llobregat",
    "sg:orig_category":"Puertas Y Portales",
    "sg:phone":"+34 932 61 18 30",
    "sg:postcode":"08907",
    "sg:province":"Barcelona",
    "wof:name":"Decoracion Muebles Monte S.l.",
    "wof:placetype":"venue"
},
  "geometry": {"coordinates":[2.1101009846,41.3590011597],"type":"Point"}
}