{
  "type": "Feature",
  "properties": {
    "iso:country":"ES",
    "sg:address":"Calle de Martinez Villergas, 49",
    "sg:city":"Madrid",
    "sg:orig_category":"Electrodom\u00c9sticos (al Por Menor)",
    "sg:phone":"+34 914 05 31 08",
    "sg:postcode":"28027",
    "sg:province":"Madrid",
    "wof:name":"Empletien S.l.",
    "wof:placetype":"venue"
},
  "geometry": {"coordinates":[-3.6574730873,40.4448890686],"type":"Point"}
}