{
  "type": "Feature",
  "properties": {
    "iso:country":"ES",
    "sg:address":"Calle de Nogal, 18",
    "sg:city":"Jaen",
    "sg:orig_category":"Agricultura: Abastecimiento Y Cosechado (negocio)",
    "sg:phone":"+34 953 25 86 06",
    "sg:postcode":"23006",
    "sg:province":"Ja\u00e9n",
    "wof:name":"Explotaciones Agricolas Jaen S.l.",
    "wof:placetype":"venue"
},
  "geometry": {"coordinates":[-3.8123090267,37.7802848816],"type":"Point"}
}