{
  "type": "Feature",
  "properties": {
    "addr:full":"Pase San Eugenio, 29 Toledo Toledo 45003",
    "addr:housenumber":"29",
    "addr:postcode":"45003",
    "addr:street":"San Eugenio",
    "iso:country":"ES",
    "sg:address":"Pase San Eugenio, 29",
    "sg:city":"Toledo",
    "sg:orig_category":"M\u00c1rmoles, Granitos Y Piedras Naturales",
    "sg:phone":"+34 925 22 62 05",
    "sg:postcode":"45003",
    "sg:province":"Toledo",
    "wof:name":"Granitos Dorado S.l.l.",
    "wof:placetype":"venue"
},
  "geometry": {"coordinates":[-4.0229306221,39.8718833923],"type":"Point"}
}