{
  "type": "Feature",
  "properties": {
    "iso:country":"ES",
    "sg:address":"Avd Ii (p Salvador), 44",
    "sg:city":"Roda",
    "sg:orig_category":"Empresas De Carpinter\u00cda De Madera",
    "sg:phone":"+34 967 44 33 74",
    "sg:postcode":"02630",
    "sg:province":"Albacete",
    "wof:name":"Puertas Arpicasa S.c.l.",
    "wof:placetype":"venue"
},
  "geometry": {"coordinates":[-2.1636590958,39.1957206726],"type":"Point"}
}