{
  "type": "Feature",
  "properties": {
    "iso:country":"ES",
    "sg:address":"Rond Garay, 5",
    "sg:city":"San Juan",
    "sg:orig_category":"Mutuas De Seguros",
    "sg:phone":"+34 968 21 30 59",
    "sg:postcode":"30003",
    "sg:province":"Murcia",
    "wof:name":"Mutualidad General Judicial",
    "wof:placetype":"venue"
},
  "geometry": {"coordinates":[-1.1241329908,37.981918335],"type":"Point"}
}