{
  "type": "Feature",
  "properties": {
    "iso:country":"ES",
    "sg:address":"Calle de Barcelona, 8",
    "sg:city":"Caspe",
    "sg:orig_category":"Chapister\u00cda",
    "sg:phone":"+34 976 63 05 46",
    "sg:postcode":"50700",
    "sg:province":"Zaragoza",
    "wof:name":"Abadia Guiu Luis",
    "wof:placetype":"venue"
},
  "geometry": {"coordinates":[-0.039083,41.232632],"type":"Point"}
}