{
  "type": "Feature",
  "properties": {
    "iso:country":"ES",
    "sg:address":"Calle de Jose Marti, 2",
    "sg:city":"Malaga",
    "sg:classifiers":[
        {
            "category":"Communications",
            "type":"Services"
        }
    ],
    "sg:phone":"+34 952 28 78 89",
    "sg:postcode":"29007",
    "sg:province":"M\u00e1laga",
    "sg:tags":[
        "televisiones",
        "y",
        "radio"
    ],
    "wof:name":"Andalucia Directo S.l.",
    "wof:placetype":"venue"
},
  "geometry": {"coordinates":[-4.4542360306,36.7204170227],"type":"Point"}
}