{
  "type": "Feature",
  "properties": {
    "addr:full":"Carrer de Muntaner, 231 Barcelona Barcelona 08021",
    "addr:housenumber":"231",
    "addr:postcode":"08021",
    "addr:street":"Carrer De Muntaner",
    "iso:country":"ES",
    "sg:address":"Carrer de Muntaner, 231",
    "sg:city":"Barcelona",
    "sg:orig_category":"Art\u00cdculos De Decoraci\u00d3n",
    "sg:phone":"+34 932 00 53 53",
    "sg:postcode":"08021",
    "sg:province":"Barcelona",
    "wof:name":"Sahun Roldos Jose",
    "wof:placetype":"venue"
},
  "geometry": {"coordinates":[2.1490039825,41.394329071],"type":"Point"}
}