{
  "type": "Feature",
  "properties": {
    "addr:full":"Calle de Donato Arguelles, 16 Gijon Asturias 33206",
    "addr:housenumber":"16",
    "addr:postcode":"33206",
    "addr:street":"Calle De Donato Arguelles",
    "iso:country":"ES",
    "sg:address":"Calle de Donato Arguelles, 16",
    "sg:city":"Gijon",
    "sg:orig_category":"Loter\u00cda Y T\u00d3mbola",
    "sg:phone":"+34 985 17 09 81",
    "sg:postcode":"33206",
    "sg:province":"Asturias",
    "wof:name":"Suarez Diaz Maria Victoria",
    "wof:placetype":"venue"
},
  "geometry": {"coordinates":[-5.6646084785,43.5395050049],"type":"Point"}
}