{
  "type": "Feature",
  "properties": {
    "iso:country":"ES",
    "sg:address":"Pase Sagastieder De, 20",
    "sg:city":"Donostia-san Sebastian",
    "sg:orig_category":"Molduras, Junquillos, Listones Y Molduras Perforadas",
    "sg:phone":"+34 943 28 20 40",
    "sg:postcode":"20015",
    "sg:province":"Guip\u00f9zcoa",
    "wof:name":"Martikorena Y Otra C.b.",
    "wof:placetype":"venue"
},
  "geometry": {"coordinates":[-1.9578590393,43.3124465942],"type":"Point"}
}