{
  "type": "Feature",
  "properties": {
    "addr:full":"Tvsa. Asomadillas, 8 Hornachos Badajoz 06228",
    "addr:housenumber":"8",
    "addr:postcode":"06228",
    "addr:street":"Asomadillas",
    "iso:country":"ES",
    "sg:address":"Tvsa. Asomadillas, 8",
    "sg:city":"Hornachos",
    "sg:orig_category":"Carnicer\u00cdas, Carnicer\u00cdas",
    "sg:phone":"+34 924 53 31 09",
    "sg:postcode":"06228",
    "sg:province":"Badajoz",
    "sg:website":"www.farcedo.com",
    "wof:name":"Embutidos Farcedo S.l.",
    "wof:placetype":"venue"
},
  "geometry": {"coordinates":[-6.0721697807,38.5533332825],"type":"Point"}
}