{
  "type": "Feature",
  "properties": {
    "iso:country":"ES",
    "sg:address":"Av En Joan Carles I, 20",
    "sg:city":"Elche",
    "sg:orig_category":"Arquitectos",
    "sg:phone":"+34 965 45 60 66",
    "sg:postcode":"03203",
    "sg:province":"Alicante",
    "wof:name":"A.i.a. Arquitectura S.l.",
    "wof:placetype":"venue"
},
  "geometry": {"coordinates":[-0.6914646029,38.2672729492],"type":"Point"}
}