{
  "type": "Feature",
  "properties": {
    "addr:full":"Ctra Agost, 59 San Vicente Del Raspeig-sant Vicent Del Raspeig Alicante 03690",
    "addr:housenumber":"59",
    "addr:postcode":"03690",
    "addr:street":"Ctra Agost",
    "iso:country":"ES",
    "sg:address":"Ctra Agost, 59",
    "sg:city":"San Vicente Del Raspeig-sant Vicent Del Raspeig",
    "sg:orig_category":"Fabricaci\u00d3n Y Distribuci\u00d3n De Colas, Masillas Y Encoladoras",
    "sg:phone":"+34 965 66 30 13",
    "sg:postcode":"03690",
    "sg:province":"Alicante",
    "wof:name":"Composan Adhesivos S.a.",
    "wof:placetype":"venue"
},
  "geometry": {"coordinates":[-0.5379920006,38.4021377563],"type":"Point"}
}