{
  "type": "Feature",
  "properties": {
    "addr:full":"Pase Doctor Torres Villarroel, 4 Salamanca Salamanca 37005",
    "addr:housenumber":"4",
    "addr:postcode":"37005",
    "addr:street":"Doctor Torres Villarroel",
    "iso:country":"ES",
    "sg:address":"Pase Doctor Torres Villarroel, 4",
    "sg:city":"Salamanca",
    "sg:orig_category":"Frutas, Legumbres Frescas Y Tempranas (al Por Menor)",
    "sg:phone":"+34 923 22 46 65",
    "sg:postcode":"37005",
    "sg:province":"Salamanca",
    "wof:name":"Oliva Santa Martina Feliciana",
    "wof:placetype":"venue"
},
  "geometry": {"coordinates":[-5.6633272171,40.9707374573],"type":"Point"}
}