{
  "type": "Feature",
  "properties": {
    "iso:country":"ES",
    "sg:address":"Calle de Antonio Machado, 5",
    "sg:city":"Arnedo",
    "sg:orig_category":"Televisi\u00d3n, V\u00cddeo: Aparatos Y Accesorios (venta)",
    "sg:phone":"+34 941 38 71 21",
    "sg:postcode":"26580",
    "sg:province":"La Rioja",
    "wof:name":"Triunfo Telecomunicaciones S.l.",
    "wof:placetype":"venue"
},
  "geometry": {"coordinates":[-2.0992820263,42.2265319824],"type":"Point"}
}