{
  "type": "Feature",
  "properties": {
    "addr:full":"Calle de Arce, 47 Poligono Industrial De Arinaga Las Palmas 35118",
    "addr:housenumber":"47",
    "addr:postcode":"35118",
    "addr:street":"Calle De Arce;Industrial",
    "iso:country":"ES",
    "sg:address":"Calle de Arce, 47",
    "sg:city":"Poligono Industrial De Arinaga",
    "sg:orig_category":"Fabricaci\u00d3n, Reparaci\u00d3n Y Mantenimiento De Construcciones Navales Y Fluviales",
    "sg:phone":"+34 928 75 65 83",
    "sg:postcode":"35118",
    "sg:province":"Las Palmas",
    "wof:name":"Clavel Allievi Luis",
    "wof:placetype":"venue"
},
  "geometry": {"coordinates":[-15.3927698135,27.8557987213],"type":"Point"}
}