{
  "type": "Feature",
  "properties": {
    "addr:full":"Carrer de Madrazo, 130 Barcelona Barcelona 08021",
    "addr:housenumber":"130",
    "addr:postcode":"08021",
    "addr:street":"Carrer De Madrazo",
    "iso:country":"ES",
    "sg:address":"Carrer de Madrazo, 130",
    "sg:city":"Barcelona",
    "sg:orig_category":"Confecci\u00d3n De Trajes Para Se\u00d1oras",
    "sg:phone":"+34 932 00 31 21",
    "sg:postcode":"08021",
    "sg:province":"Barcelona",
    "wof:name":"Mercadel Grupo Textil De Moda S.l",
    "wof:placetype":"venue"
},
  "geometry": {"coordinates":[2.1426959038,41.3957214355],"type":"Point"}
}