{
  "type": "Feature",
  "properties": {
    "addr:full":"Calle de Timoneda, 6 Valencia Valencia 46008",
    "addr:housenumber":"6",
    "addr:postcode":"46008",
    "addr:street":"Calle De Timoneda",
    "iso:country":"ES",
    "sg:address":"Calle de Timoneda, 6",
    "sg:city":"Valencia",
    "sg:orig_category":"Promotores Constructores",
    "sg:phone":"+34 963 85 17 05",
    "sg:postcode":"46008",
    "sg:province":"Valencia",
    "wof:name":"Construcciones Inmobiliarias Tyris S.a.",
    "wof:placetype":"venue"
},
  "geometry": {"coordinates":[-0.3874439895,39.4692115784],"type":"Point"}
}