{
  "type": "Feature",
  "properties": {
    "addr:full":"Calle de Manuel Lasala, 4 Zaragoza Zaragoza 50006",
    "addr:housenumber":"4",
    "addr:postcode":"50006",
    "addr:street":"Calle De Manuel Lasala",
    "iso:country":"ES",
    "sg:address":"Calle de Manuel Lasala, 4",
    "sg:city":"Zaragoza",
    "sg:orig_category":"Ense\u00d1anza Variada",
    "sg:phone":"+34 976 40 03 77",
    "sg:postcode":"50006",
    "sg:province":"Zaragoza",
    "wof:name":"Romero Rando Angel",
    "wof:placetype":"venue"
},
  "geometry": {"coordinates":[-0.8906379938,41.6403770447],"type":"Point"}
}