{
  "type": "Feature",
  "properties": {
    "iso:country":"ES",
    "sg:address":"Calle de Blas Larrayad, S/n",
    "sg:city":"Fuentes Ebro",
    "sg:orig_category":"Empresas De Carpinter\u00cda De Madera",
    "sg:phone":"+34 976 16 11 52",
    "sg:postcode":"50740",
    "sg:province":"Zaragoza",
    "wof:name":"Carpinteria M. Herrero S.l.",
    "wof:placetype":"venue"
},
  "geometry": {"coordinates":[-0.6253150105,41.5118789673],"type":"Point"}
}