{
  "type": "Feature",
  "properties": {
    "addr:full":"P Muelle(sta Lucia), S/n Cartagena Murcia 30202",
    "addr:housenumber":"/ n",
    "addr:postcode":"30202",
    "addr:street":"S",
    "iso:country":"ES",
    "sg:address":"P Muelle(sta Lucia), S/n",
    "sg:city":"Cartagena",
    "sg:classifiers":[
        {
            "category":"Recreation",
            "type":"Entertainment"
        }
    ],
    "sg:phone":"+34 968 50 64 30",
    "sg:postcode":"30202",
    "sg:province":"Murcia",
    "sg:tags":[
        "caza",
        "pr\u00c1ctica",
        "la",
        "de",
        "pesca",
        "y"
    ],
    "wof:name":"Cofradia De Pescadores De Cartagena",
    "wof:placetype":"venue"
},
  "geometry": {"coordinates":[-0.9706040025,37.5960159302],"type":"Point"}
}