{
  "type": "Feature",
  "properties": {
    "addr:full":"Rua Domingo Garcia Sabell, 5 Ferrol La Coru\u00f1a 15406",
    "addr:housenumber":"5",
    "addr:postcode":"15406",
    "addr:street":"Rua Domingo Garcia Sabell;La Corun\u0303A",
    "iso:country":"ES",
    "sg:address":"Rua Domingo Garcia Sabell, 5",
    "sg:city":"Ferrol",
    "sg:orig_category":"Restaurantes",
    "sg:phone":"+34 981 31 26 27",
    "sg:postcode":"15406",
    "sg:province":"La Coru\u00f1a",
    "wof:name":"Catering Carranza S.l.",
    "wof:placetype":"venue"
},
  "geometry": {"coordinates":[-8.2030229568,43.4826278687],"type":"Point"}
}