{
  "type": "Feature",
  "properties": {
    "addr:full":"Carrer de Santa Creu, 13 Sant Feliu Llobregat Barcelona 08980",
    "addr:housenumber":"13",
    "addr:postcode":"08980",
    "addr:street":"Carrer De Santa Creu",
    "iso:country":"ES",
    "sg:address":"Carrer de Santa Creu, 13",
    "sg:city":"Sant Feliu Llobregat",
    "sg:orig_category":"Art\u00cdculos De Regalo (al Por Menor)",
    "sg:phone":"+34 936 66 06 24",
    "sg:postcode":"08980",
    "sg:province":"Barcelona",
    "wof:name":"Casado Guerrero Isabel",
    "wof:placetype":"venue"
},
  "geometry": {"coordinates":[2.0464670658,41.3855934143],"type":"Point"}
}