{
  "type": "Feature",
  "properties": {
    "addr:full":"Avda Ciudad De Barcelona, 57 Madrid Madrid 28007",
    "addr:housenumber":"57",
    "addr:postcode":"madrid;28007",
    "addr:street":"Avda Ciudad De Barcelona",
    "iso:country":"ES",
    "sg:address":"Avda Ciudad De Barcelona, 57",
    "sg:city":"Madrid",
    "sg:orig_category":"Comerciantes Al Por Mayor De Vinos, Licores Y Alcoholes",
    "sg:phone":"+34 914 33 84 77",
    "sg:postcode":"28007",
    "sg:province":"Madrid",
    "wof:name":"Casas Sainz De Aja Gregorio",
    "wof:placetype":"venue"
},
  "geometry": {"coordinates":[-3.6767098904,40.4024047852],"type":"Point"}
}