{
  "type": "Feature",
  "properties": {
    "iso:country":"ES",
    "sg:address":"Rua Roberto Baamonde, 9",
    "sg:city":"Monforte De Lemos",
    "sg:orig_category":"Suministros Para Hoteles",
    "sg:phone":"+34 982 41 15 68",
    "sg:postcode":"27400",
    "sg:province":"Lugo",
    "wof:name":"Martinez Perez Manuela",
    "wof:placetype":"venue"
},
  "geometry": {"coordinates":[-7.5103988647,42.5206413269],"type":"Point"}
}