{
  "type": "Feature",
  "properties": {
    "addr:full":"Calle de Virgen De Guadalupe, 1 Badajoz Badajoz 06004",
    "addr:housenumber":"1",
    "addr:postcode":"06004",
    "addr:street":"Calle De Virgen De Guadalupe",
    "iso:country":"ES",
    "sg:address":"Calle de Virgen De Guadalupe, 1",
    "sg:city":"Badajoz",
    "sg:orig_category":"Encuadernaci\u00d3n E Impresi\u00d3n De Folletos",
    "sg:phone":"+34 924 24 37 80",
    "sg:postcode":"06004",
    "sg:province":"Badajoz",
    "wof:name":"Caldera Fuertes Eulogio",
    "wof:placetype":"venue"
},
  "geometry": {"coordinates":[-6.9726190567,38.8709449768],"type":"Point"}
}