{
  "type": "Feature",
  "properties": {
    "addr:full":"Carr Consolacio, 28 Villarreal Castell\u00f3n 12540",
    "addr:housenumber":"28",
    "addr:postcode":"12540",
    "addr:street":"Carr Consolacio",
    "iso:country":"ES",
    "sg:address":"Carr Consolacio, 28",
    "sg:city":"Villarreal",
    "sg:orig_category":"Centros De Educaci\u00d3n Especial",
    "sg:phone":"+34 964 52 63 49",
    "sg:postcode":"12540",
    "sg:province":"Castell\u00f3n",
    "wof:name":"Generalitat Valenciana",
    "wof:placetype":"venue"
},
  "geometry": {"coordinates":[-0.1019670963,39.9309768677],"type":"Point"}
}