{
  "type": "Feature",
  "properties": {
    "addr:full":"Carrer de Valencia, 461 Barcelona Barcelona 08013",
    "addr:housenumber":"461",
    "addr:postcode":"08013",
    "addr:street":"Carrer De Valencia",
    "iso:country":"ES",
    "sg:address":"Carrer de Valencia, 461",
    "sg:city":"Barcelona",
    "sg:orig_category":"Ropa Para Se\u00d1oras (al Por Menor)",
    "sg:phone":"+34 932 32 37 79",
    "sg:postcode":"08013",
    "sg:province":"Barcelona",
    "wof:name":"Cortacans Naranjo S.c.p.",
    "wof:placetype":"venue"
},
  "geometry": {"coordinates":[2.1774768829,41.4035186768],"type":"Point"}
}