{
  "type": "Feature",
  "properties": {
    "iso:country":"ES",
    "sg:address":"Coruxo De Arriba, 7",
    "sg:city":"Lians",
    "sg:orig_category":"Ense\u00d1anza Variada",
    "sg:phone":"+34 981 62 70 17",
    "sg:postcode":"15179",
    "sg:province":"La Coru\u00f1a",
    "wof:name":"C 5 Centro De Estudios S.l.",
    "wof:placetype":"venue"
},
  "geometry": {"coordinates":[-8.3459596634,43.3464698792],"type":"Point"}
}