{
  "type": "Feature",
  "properties": {
    "iso:country":"ES",
    "sg:address":"Bjad Don Alonso, 7",
    "sg:city":"Avila",
    "sg:orig_category":"Elementos Para Suelos Prefabricados",
    "sg:phone":"+34 920 22 38 55",
    "sg:postcode":"05003",
    "sg:province":"\u00c1vila",
    "wof:name":"Martinez Malvar Obdon",
    "wof:placetype":"venue"
},
  "geometry": {"coordinates":[-4.6898651123,40.6524543762],"type":"Point"}
}