{
  "type": "Feature",
  "properties": {
    "iso:country":"ES",
    "sg:address":"Avda Ciudades (de Las), 86",
    "sg:city":"Getafe",
    "sg:orig_category":"Art\u00cdculos De Regalo (al Por Menor)",
    "sg:phone":"+34 916 82 22 24",
    "sg:postcode":"28903",
    "sg:province":"Madrid",
    "wof:name":"Mu\u00f1oz Sanchez Marcelina",
    "wof:placetype":"venue"
},
  "geometry": {"coordinates":[-3.7161500454,40.3137702942],"type":"Point"}
}