{
  "type": "Feature",
  "properties": {
    "iso:country":"ES",
    "sg:address":"Carr Gausac, 2",
    "sg:city":"Vielha",
    "sg:orig_category":"Deportes Y Programas De Aventura",
    "sg:phone":"+34 973 64 01 76",
    "sg:postcode":"25530",
    "sg:province":"Lleida",
    "wof:name":"Altisport S.l.",
    "wof:placetype":"venue"
},
  "geometry": {"coordinates":[0.7929785252,42.7033576965],"type":"Point"}
}