{
  "type": "Feature",
  "properties": {
    "iso:country":"ES",
    "sg:address":"Calle de Antonio Tarraga, 30",
    "sg:city":"Pagan",
    "sg:orig_category":"Reposter\u00cdas",
    "sg:phone":"+34 968 18 68 11",
    "sg:postcode":"30740",
    "sg:province":"Murcia",
    "wof:name":"Patriher S.l.",
    "wof:placetype":"venue"
},
  "geometry": {"coordinates":[-0.7874851227,37.8159141541],"type":"Point"}
}