{
  "type": "Feature",
  "properties": {
    "addr:full":"Alam Recalde, 12 Bilbao Vizcaya 48009",
    "addr:housenumber":"12",
    "addr:postcode":"48009",
    "addr:street":"Alam Recalde",
    "iso:country":"ES",
    "sg:address":"Alam Recalde, 12",
    "sg:city":"Bilbao",
    "sg:orig_category":"Art\u00cdculos Funerarios (al Por Menor)",
    "sg:phone":"+34 944 24 10 65",
    "sg:postcode":"48009",
    "sg:province":"Vizcaya",
    "wof:name":"Funeraria Bilbaina S. A.",
    "wof:placetype":"venue"
},
  "geometry": {"coordinates":[-2.9338274002,43.2666053772],"type":"Point"}
}