{
  "type": "Feature",
  "properties": {
    "iso:country":"ES",
    "sg:address":"Rua Senra, S/n",
    "sg:city":"Esgos",
    "sg:orig_category":"Producci\u00d3n, Venta De Productos De Agricultura Biol\u00d3gica",
    "sg:phone":"+34 988 29 00 05",
    "sg:postcode":"32720",
    "sg:province":"Ourense",
    "wof:name":"Manuel Angel Rodriguez Fernandez Y Cinco Mas C.b.",
    "wof:placetype":"venue"
},
  "geometry": {"coordinates":[-7.6974630356,42.3250007629],"type":"Point"}
}