{
  "type": "Feature",
  "properties": {
    "iso:country":"ES",
    "sg:address":"Carrer de Sola, 19",
    "sg:city":"Barcelona",
    "sg:orig_category":"Inform\u00c1tica: Consultores",
    "sg:phone":"+34 934 10 80 19",
    "sg:postcode":"08014",
    "sg:province":"Barcelona",
    "wof:name":"Xotet S.l.",
    "wof:placetype":"venue"
},
  "geometry": {"coordinates":[2.1329448223,41.3873291016],"type":"Point"}
}