{
  "type": "Feature",
  "properties": {
    "addr:full":"Calle de Naves, 5 Madrid Madrid 28005",
    "addr:housenumber":"5",
    "addr:postcode":"28005",
    "addr:street":"Calle De Naves",
    "iso:country":"ES",
    "sg:address":"Calle de Naves, 5",
    "sg:city":"Madrid",
    "sg:orig_category":"Arreglo, Reparaci\u00d3n, Piezas Sueltas De Televisi\u00d3n, V\u00cddeo, Hi",
    "sg:phone":"+34 914 74 81 56",
    "sg:postcode":"28005",
    "sg:province":"Madrid",
    "wof:name":"Bustos Ubeda Jose Ramon",
    "wof:placetype":"venue"
},
  "geometry": {"coordinates":[-3.7068989277,40.3980293274],"type":"Point"}
}