{
  "type": "Feature",
  "properties": {
    "addr:full":"Carrer de Esglesia, 23 Hostalets Pierola Barcelona 08781",
    "addr:housenumber":"23",
    "addr:postcode":"08781",
    "addr:street":"Carrer De Esglesia;Pierola Barcelona",
    "iso:country":"ES",
    "sg:address":"Carrer de Esglesia, 23",
    "sg:city":"Hostalets Pierola",
    "sg:orig_category":"Mercer\u00cda, Lencer\u00cda (al Por Menor)",
    "sg:phone":"+34 937 71 22 39",
    "sg:postcode":"08781",
    "sg:province":"Barcelona",
    "wof:name":"Cursellas Valls Maria Asuncion",
    "wof:placetype":"venue"
},
  "geometry": {"coordinates":[1.7691509724,41.5347595215],"type":"Point"}
}