{
  "type": "Feature",
  "properties": {
    "iso:country":"ES",
    "sg:address":"Calle de Piedad, 6",
    "sg:city":"Cabezamesada",
    "sg:orig_category":"Cooperativas Agr\u00cdcolas",
    "sg:phone":"+34 925 20 91 10",
    "sg:postcode":"45890",
    "sg:province":"Toledo",
    "wof:name":"Asociacion Agraria De Propietarios Y Labradores De Fincas Rusticas",
    "wof:placetype":"venue"
},
  "geometry": {"coordinates":[-3.1024367809,39.8171730042],"type":"Point"}
}