{
  "type": "Feature",
  "properties": {
    "addr:full":"Calle de Pablo Iglesias, 22 Zaragoza Zaragoza 50018",
    "addr:housenumber":"22",
    "addr:postcode":"50018",
    "addr:street":"Calle De Pablo Iglesias",
    "iso:country":"ES",
    "sg:address":"Calle de Pablo Iglesias, 22",
    "sg:city":"Zaragoza",
    "sg:orig_category":"Maquinaria Para Industrias Diversas",
    "sg:phone":"+34 976 73 54 31",
    "sg:postcode":"50018",
    "sg:province":"Zaragoza",
    "wof:name":"Hernandez Bernad Antonio",
    "wof:placetype":"venue"
},
  "geometry": {"coordinates":[-0.8844439983,41.6772499084],"type":"Point"}
}