{
  "type": "Feature",
  "properties": {
    "addr:full":"Calle de Colon, 22 Le\u00f3n Le\u00f3n 24001",
    "addr:housenumber":"22",
    "addr:postcode":"24001",
    "addr:street":"Calle De Colon;Leo\u0301N",
    "iso:country":"ES",
    "sg:address":"Calle de Colon, 22",
    "sg:city":"Le\u00f3n",
    "sg:orig_category":"Centros Empresariales",
    "sg:phone":"+34 987 22 08 26",
    "sg:postcode":"24001",
    "sg:province":"Le\u00f3n",
    "wof:name":"Alvarez Villa Cristina",
    "wof:placetype":"venue"
},
  "geometry": {"coordinates":[-5.5793557167,42.5994720459],"type":"Point"}
}