{
  "type": "Feature",
  "properties": {
    "addr:full":"Calle de Junquera, 3 Vilanova Arousa Pontevedra 36620",
    "addr:housenumber":"3",
    "addr:postcode":"36620",
    "addr:street":"Calle De Junquera",
    "iso:country":"ES",
    "sg:address":"Calle de Junquera, 3",
    "sg:city":"Vilanova Arousa",
    "sg:orig_category":"Conservas De Carnes (fabricaci\u00d3n, Al Por Mayor)",
    "sg:phone":"+34 986 55 40 45",
    "sg:postcode":"36620",
    "sg:province":"Pontevedra",
    "wof:name":"Conservas Antonio Perez Lafuente S.a.",
    "wof:placetype":"venue"
},
  "geometry": {"coordinates":[-8.8285036087,42.5618782043],"type":"Point"}
}