{
  "type": "Feature",
  "properties": {
    "addr:full":"Kale Barria, 47 O\u00f1ati Guip\u00f9zcoa 20560",
    "addr:housenumber":"47",
    "addr:postcode":"20560",
    "addr:street":"Kale Barria;Guipu\u0300Zcoa",
    "iso:country":"ES",
    "sg:address":"Kale Barria, 47",
    "sg:city":"O\u00f1ati",
    "sg:orig_category":"Pintura Y Barniz (al Por Menor)",
    "sg:phone":"+34 943 78 19 99",
    "sg:postcode":"20560",
    "sg:province":"Guip\u00f9zcoa",
    "wof:name":"Aramburu Ruiz Juan Carlos",
    "wof:placetype":"venue"
},
  "geometry": {"coordinates":[-2.4106314182,43.0315284729],"type":"Point"}
}