{
  "type": "Feature",
  "properties": {
    "addr:full":"S. Andres Apostol, 18 Yepes Toledo 45313",
    "addr:housenumber":"18",
    "addr:postcode":"45313",
    "addr:street":"S.;Apostol",
    "iso:country":"ES",
    "sg:address":"S. Andres Apostol, 18",
    "sg:city":"Yepes",
    "sg:orig_category":"Promotores Constructores",
    "sg:phone":"+34 925 15 41 53",
    "sg:postcode":"45313",
    "sg:province":"Toledo",
    "wof:name":"Amosac S.l.",
    "wof:placetype":"venue"
},
  "geometry": {"coordinates":[-3.6927530766,39.9123535156],"type":"Point"}
}