{
  "type": "Feature",
  "properties": {
    "addr:full":"Ibaiondo Poligonoa, 2 Hernani Guip\u00f9zcoa 20120",
    "addr:housenumber":"2",
    "addr:postcode":"20120",
    "addr:street":"Ibaiondo Poligonoa;Guipu\u0300Zcoa",
    "iso:country":"ES",
    "sg:address":"Ibaiondo Poligonoa, 2",
    "sg:city":"Hernani",
    "sg:orig_category":"Caf\u00c9s (al Por Menor)",
    "sg:phone":"+34 943 33 64 26",
    "sg:postcode":"20120",
    "sg:province":"Guip\u00f9zcoa",
    "wof:name":"Desojo Iba\u00d1ez S.l.",
    "wof:placetype":"venue"
},
  "geometry": {"coordinates":[-1.9798289537,43.2647514343],"type":"Point"}
}