{
  "type": "Feature",
  "properties": {
    "addr:full":"Carrer de Juli Garreta, 28 Can Rial Barcelona 08292",
    "addr:housenumber":"28",
    "addr:postcode":"08292",
    "addr:street":"Carrer De Juli Garreta;Barcelona",
    "iso:country":"ES",
    "sg:address":"Carrer de Juli Garreta, 28",
    "sg:city":"Can Rial",
    "sg:orig_category":"Inform\u00c1tica: Consultores",
    "sg:phone":"+34 937 77 46 39",
    "sg:postcode":"08292",
    "sg:province":"Barcelona",
    "wof:name":"J2m Consultores Informaticos S.l.",
    "wof:placetype":"venue"
},
  "geometry": {"coordinates":[1.8648079634,41.5239601135],"type":"Point"}
}