{
  "type": "Feature",
  "properties": {
    "addr:full":"Carrer de Pare Palau (del), 7 Tarragona Tarragona 43001",
    "addr:housenumber":"7",
    "addr:postcode":"43001",
    "addr:street":"Carrer De Pare Palau Del",
    "iso:country":"ES",
    "sg:address":"Carrer de Pare Palau (del), 7",
    "sg:city":"Tarragona",
    "sg:orig_category":"Psic\u00d3logos",
    "sg:phone":"+34 977 21 98 56",
    "sg:postcode":"43001",
    "sg:province":"Tarragona",
    "wof:name":"Descarrega Font Jaume",
    "wof:placetype":"venue"
},
  "geometry": {"coordinates":[1.2463469505,41.1176376343],"type":"Point"}
}