{
  "type": "Feature",
  "properties": {
    "addr:full":"Calle de Maestro Falla, 73 Sevilla Sevilla 41006",
    "addr:housenumber":"73",
    "addr:postcode":"41006",
    "addr:street":"Calle De Maestro Falla",
    "iso:country":"ES",
    "sg:address":"Calle de Maestro Falla, 73",
    "sg:city":"Sevilla",
    "sg:orig_category":"Fabricaci\u00d3n De Juguetes Autom\u00c1ticos",
    "sg:phone":"+34 954 63 03 19",
    "sg:postcode":"41006",
    "sg:province":"Sevilla",
    "wof:name":"Big-game S.l.",
    "wof:placetype":"venue"
},
  "geometry": {"coordinates":[-5.9586939812,37.3743209839],"type":"Point"}
}