{
  "type": "Feature",
  "properties": {
    "addr:full":"Pg Fabra I Puig, 14 Barcelona Barcelona 08030",
    "addr:housenumber":"14",
    "addr:postcode":"08030",
    "addr:street":"Pg Fabra I Puig",
    "iso:country":"ES",
    "sg:address":"Pg Fabra I Puig, 14",
    "sg:city":"Barcelona",
    "sg:orig_category":"Lencer\u00cda Femenina, Corseter\u00cda, Trajes De Ba\u00d1o (al Por Menor)",
    "sg:phone":"+34 933 46 98 09",
    "sg:postcode":"08030",
    "sg:province":"Barcelona",
    "wof:name":"Montagut Sola Maria Dolores",
    "wof:placetype":"venue"
},
  "geometry": {"coordinates":[2.1887550354,41.4303398132],"type":"Point"}
}