{
  "type": "Feature",
  "properties": {
    "iso:country":"ES",
    "sg:address":"Carrer de Mare De Deu De La Salut, 16",
    "sg:city":"Barcelona",
    "sg:orig_category":"Fabricaci\u00d3n De Muebles",
    "sg:phone":"+34 932 84 68 83",
    "sg:postcode":"08024",
    "sg:province":"Barcelona",
    "wof:name":"Coleccion Modulo S.l.",
    "wof:placetype":"venue"
},
  "geometry": {"coordinates":[2.1551880836,41.410320282],"type":"Point"}
}