{
  "type": "Feature",
  "properties": {
    "addr:full":"Casal, 28 Pereiras Pontevedra 36419",
    "addr:housenumber":"28",
    "addr:postcode":"36419",
    "addr:street":"Casal",
    "iso:country":"ES",
    "sg:address":"Casal, 28",
    "sg:city":"Pereiras",
    "sg:orig_category":"Tapiceros Y Tapiceros",
    "sg:phone":"+34 986 33 21 22",
    "sg:postcode":"36419",
    "sg:province":"Pontevedra",
    "wof:name":"Pampillon Freiria Manuel",
    "wof:placetype":"venue"
},
  "geometry": {"coordinates":[-8.6284589767,42.1718101501],"type":"Point"}
}