{
  "type": "Feature",
  "properties": {
    "addr:full":"Plaz Egido, S/n Diego Alvaro \u00c1vila 05151",
    "addr:housenumber":"s",
    "addr:postcode":"05151",
    "addr:street":"Plaz Egido;/ N Diego Alvaro A\u0301Vila",
    "iso:country":"ES",
    "sg:address":"Plaz Egido, S/n",
    "sg:city":"Diego Alvaro",
    "sg:orig_category":"Farmacias",
    "sg:phone":"+34 920 36 50 72",
    "sg:postcode":"05151",
    "sg:province":"\u00c1vila",
    "wof:name":"Marcos Gajate Francisca",
    "wof:placetype":"venue"
},
  "geometry": {"coordinates":[-5.3243842125,40.6646385193],"type":"Point"}
}