{
  "type": "Feature",
  "properties": {
    "iso:country":"ES",
    "sg:address":"Calle de Rosario, 102",
    "sg:city":"Albacete",
    "sg:orig_category":"M\u00c9dicos: Ginecolog\u00cda Y Obstetricia",
    "sg:phone":"+34 967 21 21 31",
    "sg:postcode":"02003",
    "sg:province":"Albacete",
    "wof:name":"Guerrero Labrador Armando",
    "wof:placetype":"venue"
},
  "geometry": {"coordinates":[-1.8612070084,38.9874801636],"type":"Point"}
}