{
  "type": "Feature",
  "properties": {
    "addr:full":"Calle de Capitan Diego Urbina, 3 Guadalajara Guadalajara 19002",
    "addr:housenumber":"3",
    "addr:postcode":"19002",
    "addr:street":"Calle De Capitan Diego Urbina",
    "iso:country":"ES",
    "sg:address":"Calle de Capitan Diego Urbina, 3",
    "sg:city":"Guadalajara",
    "sg:orig_category":"Organizaciones Profesionales",
    "sg:phone":"+34 949 21 92 32",
    "sg:postcode":"19002",
    "sg:province":"Guadalajara",
    "wof:name":"Centro De Fisioterapia Biosalud S.l.",
    "wof:placetype":"venue"
},
  "geometry": {"coordinates":[-3.1607189178,40.6270561218],"type":"Point"}
}