{
  "type": "Feature",
  "properties": {
    "addr:full":"Industrials, 93 Ciutadella Menorca Islas Baleares 07760",
    "addr:housenumber":"93",
    "addr:postcode":"07760",
    "addr:street":"Industrials",
    "iso:country":"ES",
    "sg:address":"Industrials, 93",
    "sg:city":"Ciutadella Menorca",
    "sg:orig_category":"Fabricaci\u00d3n De Juguetes Autom\u00c1ticos",
    "sg:phone":"+34 971 38 58 52",
    "sg:postcode":"07760",
    "sg:province":"Islas Baleares",
    "wof:name":"Jok I Jocs S.l.",
    "wof:placetype":"venue"
},
  "geometry": {"coordinates":[3.8548500538,40.006729126],"type":"Point"}
}