{
  "type": "Feature",
  "properties": {
    "iso:country":"ES",
    "sg:address":"Calle de Rector Garcia Duarte, 3",
    "sg:city":"Granada",
    "sg:orig_category":"Inmobiliaria (alquileres Por Temporada Y Temporales)",
    "sg:phone":"+34 958 20 75 25",
    "sg:postcode":"18002",
    "sg:province":"Granada",
    "wof:name":"Suarez Garcia Maria Del Carmen",
    "wof:placetype":"venue"
},
  "geometry": {"coordinates":[-3.6050727367,37.1770858765],"type":"Point"}
}