{
  "type": "Feature",
  "properties": {
    "addr:full":"Avda Palafox, 39 Pastriz Zaragoza 50195",
    "addr:housenumber":"39",
    "addr:postcode":"50195",
    "addr:street":"Avda Palafox",
    "iso:country":"ES",
    "sg:address":"Avda Palafox, 39",
    "sg:city":"Pastriz",
    "sg:orig_category":"Cerrajer\u00cda, Ferrallista",
    "sg:phone":"+34 976 58 31 63",
    "sg:postcode":"50195",
    "sg:province":"Zaragoza",
    "wof:name":"Gallego Lafuente Alberto",
    "wof:placetype":"venue"
},
  "geometry": {"coordinates":[-0.7821670175,41.6181983948],"type":"Point"}
}