{
  "type": "Feature",
  "properties": {
    "addr:full":"Ctra Zamora, Km. 0010,4 Onzonilla Le\u00f3n 24231",
    "addr:postcode":"24231",
    "addr:street":"Ctra Zamora Km. 0010,4;Leo\u0301N",
    "iso:country":"ES",
    "sg:address":"Ctra Zamora, Km. 0010,4",
    "sg:city":"Onzonilla",
    "sg:orig_category":"Muebles, Minoristas",
    "sg:phone":"+34 987 28 20 89",
    "sg:postcode":"24231",
    "sg:province":"Le\u00f3n",
    "wof:name":"Rodriguez Santamarta Teresa",
    "wof:placetype":"venue"
},
  "geometry": {"coordinates":[-5.5841889381,42.5260047913],"type":"Point"}
}