{
  "type": "Feature",
  "properties": {
    "iso:country":"ES",
    "sg:address":"Calle de Doctor Ferran, 6",
    "sg:city":"Xirivella",
    "sg:orig_category":"Cr\u00cda De Animales",
    "sg:phone":"+34 963 70 54 70",
    "sg:postcode":"46950",
    "sg:province":"Valencia",
    "wof:name":"Salon Perez Fidelia",
    "wof:placetype":"venue"
},
  "geometry": {"coordinates":[-0.4288559854,39.4639511108],"type":"Point"}
}