{
  "type": "Feature",
  "properties": {
    "iso:country":"ES",
    "sg:address":"Calle de Balmes, S/n",
    "sg:city":"Linea De La Concepcion",
    "sg:orig_category":"Asociaciones Y Clubs Deportivos",
    "sg:phone":"+34 956 17 41 89",
    "sg:postcode":"11300",
    "sg:province":"C\u00e1diz",
    "wof:name":"Recreativo Linense C.f",
    "wof:placetype":"venue"
},
  "geometry": {"coordinates":[-5.3544931412,36.1643714905],"type":"Point"}
}