{
  "type": "Feature",
  "properties": {
    "addr:full":"Carr Bautista Riera, 26 Burjassot Valencia 46100",
    "addr:housenumber":"26",
    "addr:postcode":"46100",
    "addr:street":"Carr Bautista Riera",
    "iso:country":"ES",
    "sg:address":"Carr Bautista Riera, 26",
    "sg:city":"Burjassot",
    "sg:orig_category":"Mec\u00c1nico Del Autom\u00d3vil",
    "sg:phone":"+34 963 63 17 41",
    "sg:postcode":"46100",
    "sg:province":"Valencia",
    "wof:name":"Lagares Morillo Jorge",
    "wof:placetype":"venue"
},
  "geometry": {"coordinates":[-0.4088369906,39.5058631897],"type":"Point"}
}