{
  "type": "Feature",
  "properties": {
    "iso:country":"ES",
    "sg:address":"C/ Lepanto, 10",
    "sg:city":"Elche",
    "sg:orig_category":"Promotores Constructores",
    "sg:phone":"+34 965 46 88 10",
    "sg:postcode":"03201",
    "sg:province":"Alicante",
    "wof:name":"Produlcasa S.l.",
    "wof:placetype":"venue"
},
  "geometry": {"coordinates":[-0.7012360096,38.2657966614],"type":"Point"}
}