{
  "type": "Feature",
  "properties": {
    "addr:full":"Calle de Rambla Baja, 12 Tarazona Mancha Albacete 02100",
    "addr:housenumber":"12",
    "addr:postcode":"02100",
    "addr:street":"Calle De Rambla Baja",
    "iso:country":"ES",
    "sg:address":"Calle de Rambla Baja, 12",
    "sg:city":"Tarazona Mancha",
    "sg:orig_category":"Asesor\u00cda Sobre Comunicaci\u00d3n De Empresas",
    "sg:phone":"+34 967 48 00 65",
    "sg:postcode":"02100",
    "sg:province":"Albacete",
    "wof:name":"Escribano Trigo Francisco Jose",
    "wof:placetype":"venue"
},
  "geometry": {"coordinates":[-1.9094289541,39.2639389038],"type":"Point"}
}