{
  "type": "Feature",
  "properties": {
    "addr:full":"Calle de Francisco Pizarro, 3 Casas De Fernando Alonso Cuenca 16610",
    "addr:housenumber":"3",
    "addr:postcode":"16610",
    "addr:street":"Calle De Francisco Pizarro",
    "iso:country":"ES",
    "sg:address":"Calle de Francisco Pizarro, 3",
    "sg:city":"Casas De Fernando Alonso",
    "sg:orig_category":"Producci\u00d3n, Venta De Productos De Agricultura Biol\u00d3gica",
    "sg:phone":"+34 969 38 30 87",
    "sg:postcode":"16610",
    "sg:province":"Cuenca",
    "wof:name":"Alarcon Pa\u00f1os Eduardo",
    "wof:placetype":"venue"
},
  "geometry": {"coordinates":[-2.3242287636,39.3481788635],"type":"Point"}
}