{
  "type": "Feature",
  "properties": {
    "addr:full":"Calle de Adrian Pulido, 7 Madrid Madrid 28039",
    "addr:housenumber":"7",
    "addr:postcode":"madrid;28039",
    "addr:street":"Calle De Adrian Pulido",
    "iso:country":"ES",
    "sg:address":"Calle de Adrian Pulido, 7",
    "sg:city":"Madrid",
    "sg:orig_category":"Masajistas Kinesiterapeutas",
    "sg:phone":"+34 913 11 10 73",
    "sg:postcode":"28039",
    "sg:province":"Madrid",
    "wof:name":"Dominguez Miron Julio",
    "wof:placetype":"venue"
},
  "geometry": {"coordinates":[-3.7059311867,40.4538002014],"type":"Point"}
}