{
  "type": "Feature",
  "properties": {
    "addr:full":"Carrer de Bobiles, 38 Hospitalet Llobregat Barcelona 08905",
    "addr:housenumber":"38",
    "addr:postcode":"08905",
    "addr:street":"Carrer De Bobiles",
    "iso:country":"ES",
    "sg:address":"Carrer de Bobiles, 38",
    "sg:city":"Hospitalet Llobregat",
    "sg:orig_category":"Empresas De Carpinter\u00cda De Madera",
    "sg:phone":"+34 934 47 08 08",
    "sg:postcode":"08905",
    "sg:province":"Barcelona",
    "wof:name":"Escalante Oliva Juan",
    "wof:placetype":"venue"
},
  "geometry": {"coordinates":[2.112541914,41.3704185486],"type":"Point"}
}