{
  "type": "Feature",
  "properties": {
    "iso:country":"ES",
    "sg:address":"Vidangoz, 1",
    "sg:city":"Iru\u00f1a",
    "sg:orig_category":"Molduras, Junquillos, Listones Y Molduras Perforadas",
    "sg:phone":"+34 948 14 47 02",
    "sg:postcode":"31014",
    "sg:province":"Navarra",
    "wof:name":"Lizondo Jimenez Celia",
    "wof:placetype":"venue"
},
  "geometry": {"coordinates":[-1.6475410461,42.8280944824],"type":"Point"}
}