{
  "type": "Feature",
  "properties": {
    "addr:full":"Av Diputacio, 22 Roquetes Tarragona 43520",
    "addr:housenumber":"22",
    "addr:postcode":"43520",
    "addr:street":"Av Diputacio",
    "iso:country":"ES",
    "sg:address":"Av Diputacio, 22",
    "sg:city":"Roquetes",
    "sg:orig_category":"Mec\u00c1nico Del Autom\u00d3vil",
    "sg:phone":"+34 977 58 01 16",
    "sg:postcode":"43520",
    "sg:province":"Tarragona",
    "wof:name":"Escoda Blanquet Ramon",
    "wof:placetype":"venue"
},
  "geometry": {"coordinates":[0.5049350262,40.8175201416],"type":"Point"}
}