{
  "type": "Feature",
  "properties": {
    "addr:full":"Calle de Labrador, 13 Madrid Madrid 28005",
    "addr:housenumber":"13",
    "addr:postcode":"madrid;28005",
    "addr:street":"Calle De Labrador",
    "iso:country":"ES",
    "sg:address":"Calle de Labrador, 13",
    "sg:city":"Madrid",
    "sg:orig_category":"Cervecer\u00cdas",
    "sg:phone":"+34 914 73 75 38",
    "sg:postcode":"28005",
    "sg:province":"Madrid",
    "wof:name":"Hernando Ojosnegros David",
    "wof:placetype":"venue"
},
  "geometry": {"coordinates":[-3.7020220757,40.401473999],"type":"Point"}
}