{
  "type": "Feature",
  "properties": {
    "addr:full":"Calle de Jacarandas Las, 16 Arroyo De La Miel-benalmadena Costa M\u00e1laga 29630",
    "addr:housenumber":"16",
    "addr:postcode":"29630",
    "addr:street":"Calle De Jacarandas Las;Ma\u0301Laga",
    "iso:country":"ES",
    "sg:address":"Calle de Jacarandas Las, 16",
    "sg:city":"Arroyo De La Miel-benalmadena Costa",
    "sg:orig_category":"Asilos De Ancianos. Centros Privados",
    "sg:phone":"+34 952 57 81 75",
    "sg:postcode":"29630",
    "sg:province":"M\u00e1laga",
    "wof:name":"Gomez Terroba Vicente",
    "wof:placetype":"venue"
},
  "geometry": {"coordinates":[-4.521381855,36.5971374512],"type":"Point"}
}