{
  "type": "Feature",
  "properties": {
    "iso:country":"ES",
    "sg:address":"Calle de Maestro Martinez, S/n",
    "sg:city":"Ceuti",
    "sg:orig_category":"Peluqueros: De Se\u00d1oras",
    "sg:phone":"+34 968 69 03 66",
    "sg:postcode":"30562",
    "sg:province":"Murcia",
    "wof:name":"Torrano Martinez Mariano",
    "wof:placetype":"venue"
},
  "geometry": {"coordinates":[-1.272034049,38.0783538818],"type":"Point"}
}