{
  "type": "Feature",
  "properties": {
    "addr:full":"Huerga, 10 Navatejera Le\u00f3n 24008",
    "addr:housenumber":"10",
    "addr:postcode":"24008",
    "addr:street":"Huerga;Leo\u0301N",
    "iso:country":"ES",
    "sg:address":"Huerga, 10",
    "sg:city":"Navatejera",
    "sg:orig_category":"Ingenier\u00cda, Centros De Estudios (industria)",
    "sg:phone":"+34 987 21 11 54",
    "sg:postcode":"24008",
    "sg:province":"Le\u00f3n",
    "wof:name":"Oxigenio Montajes",
    "wof:placetype":"venue"
},
  "geometry": {"coordinates":[-5.5550928116,42.6448745728],"type":"Point"}
}