{
  "type": "Feature",
  "properties": {
    "iso:country":"ES",
    "sg:address":"Carr Reverend Rafael Juan Vidal (del), 67",
    "sg:city":"Aielo Malferit",
    "sg:orig_category":"Cester\u00cda (fabricaci\u00d3n)",
    "sg:phone":"+34 962 36 03 33",
    "sg:postcode":"46812",
    "sg:province":"Valencia",
    "wof:name":"Domenech Martinez Mercedes",
    "wof:placetype":"venue"
},
  "geometry": {"coordinates":[-0.5859770179,38.8795967102],"type":"Point"}
}