{
  "type": "Feature",
  "properties": {
    "iso:country":"ES",
    "sg:address":"Carrer de Sol, 21",
    "sg:city":"Sabadell",
    "sg:orig_category":"Motocicletas (agentes, Concesionarios)",
    "sg:phone":"+34 937 26 09 68",
    "sg:postcode":"08201",
    "sg:province":"Barcelona",
    "wof:name":"Basoli Sabadell S.a.",
    "wof:placetype":"venue"
},
  "geometry": {"coordinates":[2.1091120243,41.5453872681],"type":"Point"}
}