{
  "type": "Feature",
  "properties": {
    "addr:full":"Avda Obispo Perez Caceres, 15 G\u00fcimar Santa Cruz De Tenerife 38500",
    "addr:housenumber":"15",
    "addr:postcode":"38500",
    "addr:street":"Avda Obispo Perez Caceres",
    "iso:country":"ES",
    "sg:address":"Avda Obispo Perez Caceres, 15",
    "sg:city":"G\u00fcimar",
    "sg:orig_category":"Inmobiliaria (agencias)",
    "sg:phone":"+34 922 52 41 77",
    "sg:postcode":"38500",
    "sg:province":"Santa Cruz De Tenerife",
    "wof:name":"Benavides Llorente Fidel",
    "wof:placetype":"venue"
},
  "geometry": {"coordinates":[-16.4101791382,28.3148498535],"type":"Point"}
}