{
  "type": "Feature",
  "properties": {
    "iso:country":"ES",
    "sg:address":"Calle de Feria, 118",
    "sg:city":"Sevilla",
    "sg:orig_category":"Estancos",
    "sg:phone":"+34 954 37 50 23",
    "sg:postcode":"41002",
    "sg:province":"Sevilla",
    "wof:name":"Paradas Roja Maria Josefa",
    "wof:placetype":"venue"
},
  "geometry": {"coordinates":[-5.9917554855,37.4003601074],"type":"Point"}
}