{
  "type": "Feature",
  "properties": {
    "iso:country":"ES",
    "sg:address":"Avda Redondela, 34",
    "sg:city":"Igrexa",
    "sg:orig_category":"Restaurantes",
    "sg:phone":"+34 986 45 30 40",
    "sg:postcode":"36320",
    "sg:province":"Pontevedra",
    "wof:name":"Serunion S.a.",
    "wof:placetype":"venue"
},
  "geometry": {"coordinates":[-8.6428003311,42.4304618835],"type":"Point"}
}