{
  "type": "Feature",
  "properties": {
    "addr:full":"Calle de Isla De Arriaran, 1 Malaga M\u00e1laga 29014",
    "addr:housenumber":"1",
    "addr:postcode":"29014",
    "addr:street":"Calle De Isla De Arriaran;Ma\u0301Laga",
    "iso:country":"ES",
    "sg:address":"Calle de Isla De Arriaran, 1",
    "sg:city":"Malaga",
    "sg:orig_category":"Ropa De Casa (fabricaci\u00d3n, Al Por Mayor)",
    "sg:phone":"+34 952 26 52 71",
    "sg:postcode":"29014",
    "sg:province":"M\u00e1laga",
    "wof:name":"Atmosfera Wear S.l.",
    "wof:placetype":"venue"
},
  "geometry": {"coordinates":[-4.3667907715,36.8204078674],"type":"Point"}
}