{
  "type": "Feature",
  "properties": {
    "addr:full":"Avda Condes De San Isidro, 52 Fuengirola M\u00e1laga 29640",
    "addr:housenumber":"52",
    "addr:postcode":"29640",
    "addr:street":"Avda Condes De San Isidro;Ma\u0301Laga",
    "iso:country":"ES",
    "sg:address":"Avda Condes De San Isidro, 52",
    "sg:city":"Fuengirola",
    "sg:orig_category":"Hielo Artificial (fabricaci\u00d3n, Distribuci\u00d3n)",
    "sg:phone":"+34 952 47 45 95",
    "sg:postcode":"29640",
    "sg:province":"M\u00e1laga",
    "wof:name":"Verdu Mira Julio",
    "wof:placetype":"venue"
},
  "geometry": {"coordinates":[-4.6257901192,36.5369873047],"type":"Point"}
}