{
  "type": "Feature",
  "properties": {
    "iso:country":"ES",
    "sg:address":"Calle de Domingo J Navarro, 6",
    "sg:city":"Palmas De Gran Canaria",
    "sg:orig_category":"Muebles, Minoristas",
    "sg:phone":"+34 928 36 07 04",
    "sg:postcode":"35002",
    "sg:province":"Las Palmas",
    "sg:website":"www.roche-bobois.com",
    "wof:name":"Arcane S.l.",
    "wof:placetype":"venue"
},
  "geometry": {"coordinates":[-15.4172773361,28.107219696],"type":"Point"}
}