{
  "type": "Feature",
  "properties": {
    "addr:full":"Luga Altamira, 6 Altamira La Coru\u00f1a 15181",
    "addr:postcode":"15181",
    "addr:street":"Altamira;Corun\u0303A",
    "iso:country":"ES",
    "sg:address":"Luga Altamira, 6",
    "sg:city":"Altamira",
    "sg:orig_category":"Empresas De Carpinter\u00cda",
    "sg:phone":"+34 981 65 62 76",
    "sg:postcode":"15181",
    "sg:province":"La Coru\u00f1a",
    "wof:name":"Aluminios Santos S.l.",
    "wof:placetype":"venue"
},
  "geometry": {"coordinates":[-8.3688650131,43.2641944885],"type":"Point"}
}