{
  "type": "Feature",
  "properties": {
    "addr:full":"Santa Marina, S/n S. Cristobal Entrevi\u00f1as Zamora 49690",
    "addr:housenumber":"s",
    "addr:postcode":"49690",
    "addr:street":"Santa Marina;/ N S. Cristobal Entrevin\u0303As Zamora",
    "iso:country":"ES",
    "sg:address":"Santa Marina, S/n",
    "sg:city":"S. Cristobal Entrevi\u00f1as",
    "sg:orig_category":"Transportes De Animales Vivos",
    "sg:phone":"+34 980 64 41 03",
    "sg:postcode":"49690",
    "sg:province":"Zamora",
    "wof:name":"Garcia Llorden Pedro",
    "wof:placetype":"venue"
},
  "geometry": {"coordinates":[-5.6349887848,42.0465202332],"type":"Point"}
}