{
  "type": "Feature",
  "properties": {
    "addr:full":"Calle de Mejico, 4 Guadalajara Guadalajara 19004",
    "addr:housenumber":"4",
    "addr:postcode":"19004",
    "addr:street":"Calle De Mejico",
    "iso:country":"ES",
    "sg:address":"Calle de Mejico, 4",
    "sg:city":"Guadalajara",
    "sg:orig_category":"Copas, Insignias, Trofeos",
    "sg:phone":"+34 949 20 11 00",
    "sg:postcode":"19004",
    "sg:province":"Guadalajara",
    "sg:website":"www.jdeluz.com",
    "wof:name":"J. De Luz Placas Figuras Y Trofeos S.l.",
    "wof:placetype":"venue"
},
  "geometry": {"coordinates":[-3.1842041016,40.6304092407],"type":"Point"}
}