{
  "type": "Feature",
  "properties": {
    "iso:country":"ES",
    "sg:address":"Calle de Visconti, 18",
    "sg:city":"Tarazona",
    "sg:orig_category":"Ense\u00d1anza, Formaci\u00d3n Profesional: Aprendizaje",
    "sg:phone":"+34 976 64 11 25",
    "sg:postcode":"50500",
    "sg:province":"Zaragoza",
    "wof:name":"Comunidad Sindicato Y Jurados De Aguas De Tarazona",
    "wof:placetype":"venue"
},
  "geometry": {"coordinates":[-1.7261329889,41.9051551819],"type":"Point"}
}