{
  "type": "Feature",
  "properties": {
    "iso:country":"ES",
    "sg:address":"Del Metal(p I La Vi\u00f1uela), 15",
    "sg:city":"Lucena",
    "sg:orig_category":"Electricidad: Instaladores",
    "sg:phone":"+34 957 51 46 66",
    "sg:postcode":"14900",
    "sg:province":"C\u00f3rdoba",
    "wof:name":"Instalaciones Lucentinas Electrisur S.l.",
    "wof:placetype":"venue"
},
  "geometry": {"coordinates":[-4.4731202126,37.4168205261],"type":"Point"}
}