{
  "type": "Feature",
  "properties": {
    "addr:full":"Ctra Arcos, S/n Villagonzalo-pedernales Burgos 09195",
    "addr:housenumber":"s",
    "addr:postcode":"09195",
    "addr:street":"Ctra Arcos;/ N Villagonzalo-Pedernales",
    "iso:country":"ES",
    "sg:address":"Ctra Arcos, S/n",
    "sg:city":"Villagonzalo-pedernales",
    "sg:orig_category":"Granos Y Semillas (producci\u00d3n, Al Por Mayor)",
    "sg:phone":"+34 947 29 41 87",
    "sg:postcode":"09195",
    "sg:province":"Burgos",
    "wof:name":"Perez Garcia Pablo",
    "wof:placetype":"venue"
},
  "geometry": {"coordinates":[-3.7340149879,42.3022918701],"type":"Point"}
}