{
  "type": "Feature",
  "properties": {
    "addr:full":"Calle de San Juan, 2 Robledo De La Valdoncina Le\u00f3n 24391",
    "addr:housenumber":"2",
    "addr:postcode":"24391",
    "addr:street":"Calle De San Juan;Leo\u0301N",
    "iso:country":"ES",
    "sg:address":"Calle de San Juan, 2",
    "sg:city":"Robledo De La Valdoncina",
    "sg:orig_category":"Molduras, Junquillos, Listones Y Molduras Perforadas",
    "sg:phone":"+34 987 30 32 70",
    "sg:postcode":"24391",
    "sg:province":"Le\u00f3n",
    "wof:name":"Hermanas Perez Leon C B",
    "wof:placetype":"venue"
},
  "geometry": {"coordinates":[-5.682929039,42.5689697266],"type":"Point"}
}