{
  "type": "Feature",
  "properties": {
    "iso:country":"ES",
    "sg:address":"Calle de Ana Benitez, 4",
    "sg:city":"Palmas De Gran Canaria",
    "sg:orig_category":"Asilos De Ancianos. Centros Privados",
    "sg:phone":"+34 928 25 12 80",
    "sg:postcode":"35014",
    "sg:province":"Las Palmas",
    "wof:name":"Compa\u00d1ia De Las Hijas De La Caridad De San Vicente De Paul",
    "wof:placetype":"venue"
},
  "geometry": {"coordinates":[-15.4368877411,28.0981712341],"type":"Point"}
}