{
  "type": "Feature",
  "properties": {
    "addr:full":"Los Barriales, 4 Valverde Santa Cruz De Tenerife 38910",
    "addr:housenumber":"4",
    "addr:postcode":"38910",
    "addr:street":"Los Barriales",
    "iso:country":"ES",
    "sg:address":"Los Barriales, 4",
    "sg:city":"Valverde",
    "sg:orig_category":"Electricidad: Equipos Industriales, Componentes (fabricaci\u00d3n)",
    "sg:phone":"+34 922 55 20 43",
    "sg:postcode":"38910",
    "sg:province":"Santa Cruz De Tenerife",
    "wof:name":"Comercial Electrica Canarias S.a.",
    "wof:placetype":"venue"
},
  "geometry": {"coordinates":[-17.8970718384,27.8238143921],"type":"Point"}
}