{
  "type": "Feature",
  "properties": {
    "addr:full":"Ctra. Camari\u00f1as, S/n Vimianzo La Coru\u00f1a 15120",
    "addr:housenumber":"s / n",
    "addr:postcode":"15120",
    "addr:street":"Ctra. Camarin\u0303As;La Corun\u0303A",
    "iso:country":"ES",
    "sg:address":"Ctra. Camari\u00f1as, S/n",
    "sg:city":"Vimianzo",
    "sg:orig_category":"Mec\u00c1nico Del Autom\u00d3vil",
    "sg:phone":"+34 981 71 62 16",
    "sg:postcode":"15120",
    "sg:province":"La Coru\u00f1a",
    "wof:name":"Ameijeiras Gandara Jose",
    "wof:placetype":"venue"
},
  "geometry": {"coordinates":[-9.1109714508,43.1417236328],"type":"Point"}
}