{
  "type": "Feature",
  "properties": {
    "addr:full":"Calle de Haza De Acosta, 82 Almeria Almer\u00eda 04009",
    "addr:housenumber":"82",
    "addr:postcode":"04009",
    "addr:street":"Calle De Haza De Acosta",
    "iso:country":"ES",
    "sg:address":"Calle de Haza De Acosta, 82",
    "sg:city":"Almeria",
    "sg:orig_category":"Chapister\u00cda",
    "sg:phone":"+34 950 22 46 96",
    "sg:postcode":"04009",
    "sg:province":"Almer\u00eda",
    "wof:name":"Oliver Guirado Ramon",
    "wof:placetype":"venue"
},
  "geometry": {"coordinates":[-2.4499409199,36.8481559753],"type":"Point"}
}