{
  "type": "Feature",
  "properties": {
    "addr:full":"Calle de Castro Urdiales, 1 Vitoria-gasteiz \u00c1lava 01006",
    "addr:housenumber":"1",
    "addr:postcode":"01006",
    "addr:street":"Calle De Castro Urdiales",
    "iso:country":"ES",
    "sg:address":"Calle de Castro Urdiales, 1",
    "sg:city":"Vitoria-gasteiz",
    "sg:orig_category":"Mec\u00c1nico Del Autom\u00d3vil",
    "sg:phone":"+34 945 13 74 23",
    "sg:postcode":"01006",
    "sg:province":"\u00c1lava",
    "wof:name":"Ayerbe Palacios Jorge",
    "wof:placetype":"venue"
},
  "geometry": {"coordinates":[-2.6660859585,42.8390045166],"type":"Point"}
}