{
  "type": "Feature",
  "properties": {
    "addr:full":"Calle de Pozo Del Amor, 54 Villaca\u00f1as Toledo 45860",
    "addr:housenumber":"54",
    "addr:postcode":"45860",
    "addr:street":"Calle De Pozo Del Amor",
    "iso:country":"ES",
    "sg:address":"Calle de Pozo Del Amor, 54",
    "sg:city":"Villaca\u00f1as",
    "sg:orig_category":"Empresas De Pintura Y Revestimientos",
    "sg:phone":"+34 925 20 12 86",
    "sg:postcode":"45860",
    "sg:province":"Toledo",
    "wof:name":"Casas Angel Valentin",
    "wof:placetype":"venue"
},
  "geometry": {"coordinates":[-3.3416891098,39.6236686707],"type":"Point"}
}