{
  "type": "Feature",
  "properties": {
    "addr:full":"Calle de Real, 13 Santovenia Segovia 40135",
    "addr:housenumber":"13",
    "addr:postcode":"40135",
    "addr:street":"Calle De Real",
    "iso:country":"ES",
    "sg:address":"Calle de Real, 13",
    "sg:city":"Santovenia",
    "sg:orig_category":"Producci\u00d3n, Venta De Productos De Agricultura Biol\u00d3gica",
    "sg:phone":"+34 921 17 70 61",
    "sg:postcode":"40135",
    "sg:province":"Segovia",
    "wof:name":"Chamorro Pe\u00f1alosa Florencio",
    "wof:placetype":"venue"
},
  "geometry": {"coordinates":[-4.4744820595,40.967250824],"type":"Point"}
}