{
  "type": "Feature",
  "properties": {
    "iso:country":"ES",
    "sg:address":"Calle de Elda, 1",
    "sg:city":"Alacant",
    "sg:orig_category":"Perfumer\u00cda (al Por Menor)",
    "sg:phone":"+34 965 20 38 26",
    "sg:postcode":"03012",
    "sg:province":"Alicante",
    "wof:name":"Brotons Aliaga Josefa",
    "wof:placetype":"venue"
},
  "geometry": {"coordinates":[-0.4828749895,38.3548431396],"type":"Point"}
}