{
  "type": "Feature",
  "properties": {
    "iso:country":"ES",
    "sg:address":"Calle de Belchite, 8",
    "sg:city":"Logro\u00f1o",
    "sg:orig_category":"Comercio De Mobiliario De Oficina",
    "sg:phone":"+34 941 23 58 22",
    "sg:postcode":"26003",
    "sg:province":"La Rioja",
    "sg:website":"www.phuc.es",
    "wof:name":"Pancorbo Rodriguez Jose Luis",
    "wof:placetype":"venue"
},
  "geometry": {"coordinates":[-2.443546772,42.4611930847],"type":"Point"}
}