{
  "type": "Feature",
  "properties": {
    "iso:country":"ES",
    "sg:address":"Pase Colon, 10",
    "sg:city":"Irun",
    "sg:orig_category":"\u00d3ptica: Instrumentos (fabricaci\u00d3n)",
    "sg:phone":"+34 943 62 07 54",
    "sg:postcode":"20302",
    "sg:province":"Guip\u00f9zcoa",
    "wof:name":"M.pagalday S.l.",
    "wof:placetype":"venue"
},
  "geometry": {"coordinates":[-1.7905039787,43.339679718],"type":"Point"}
}