{
  "type": "Feature",
  "properties": {
    "addr:full":"Avda San Pantaleon (de), 5 Huercanos La Rioja 26314",
    "addr:postcode":"26314",
    "addr:street":"Avda San Pantaleon De 5 Huercanos;Rioja",
    "iso:country":"ES",
    "sg:address":"Avda San Pantaleon (de), 5",
    "sg:city":"Huercanos",
    "sg:orig_category":"Supermercados Y Hipermercados",
    "sg:phone":"+34 941 37 10 61",
    "sg:postcode":"26314",
    "sg:province":"La Rioja",
    "wof:name":"Ruiz Iruzubieta Victoriano",
    "wof:placetype":"venue"
},
  "geometry": {"coordinates":[-2.6950080395,42.4287910461],"type":"Point"}
}