{
  "type": "Feature",
  "properties": {
    "addr:full":"Avda Constitucion, 51 Torredelcampo Ja\u00e9n 23640",
    "addr:housenumber":"51",
    "addr:postcode":"23640",
    "addr:street":"Avda Constitucion;Jae\u0301N",
    "iso:country":"ES",
    "sg:address":"Avda Constitucion, 51",
    "sg:city":"Torredelcampo",
    "sg:orig_category":"Asesor\u00cdas Y Estudios Financieros",
    "sg:phone":"+34 953 41 11 65",
    "sg:postcode":"23640",
    "sg:province":"Ja\u00e9n",
    "wof:name":"Blanco Gomez Joaquina",
    "wof:placetype":"venue"
},
  "geometry": {"coordinates":[-3.8986558914,37.7699279785],"type":"Point"}
}