{
  "type": "Feature",
  "properties": {
    "iso:country":"ES",
    "sg:address":"Calle de Jaime I El Conquistador, 7",
    "sg:city":"San Miguel",
    "sg:orig_category":"Financiaci\u00d3n Y Cr\u00c9ditos",
    "sg:phone":"+34 968 23 92 12",
    "sg:postcode":"30008",
    "sg:province":"Murcia",
    "wof:name":"Hispania Rentygestion S.l.",
    "wof:placetype":"venue"
},
  "geometry": {"coordinates":[-1.1318589449,37.9894676208],"type":"Point"}
}