{
  "type": "Feature",
  "properties": {
    "addr:full":"Calle de Sargia, 5 Irun Guip\u00f9zcoa 20304",
    "addr:housenumber":"5",
    "addr:postcode":"20304",
    "addr:street":"Calle De Sargia;Guipu\u0300Zcoa",
    "iso:country":"ES",
    "sg:address":"Calle de Sargia, 5",
    "sg:city":"Irun",
    "sg:orig_category":"Asociaciones, Organismos Culturales Y Socioeducativos",
    "sg:phone":"+34 943 62 14 28",
    "sg:postcode":"20304",
    "sg:province":"Guip\u00f9zcoa",
    "wof:name":"Aldabe Sociedad Gastronomica",
    "wof:placetype":"venue"
},
  "geometry": {"coordinates":[-1.7877060175,43.3376426697],"type":"Point"}
}