{
  "type": "Feature",
  "properties": {
    "addr:full":"Ctra Plantio, 96 Majadahonda Madrid 28220",
    "addr:housenumber":"96",
    "addr:postcode":"28220",
    "addr:street":"Ctra Plantio",
    "iso:country":"ES",
    "sg:address":"Ctra Plantio, 96",
    "sg:city":"Majadahonda",
    "sg:orig_category":"Inform\u00c1tica Equipo Y Programas (al Por Mayor)",
    "sg:phone":"+34 913 07 60 25",
    "sg:postcode":"28220",
    "sg:province":"Madrid",
    "sg:website":"www.tym.es",
    "wof:name":"Teclas Y Monitores Optimizacion De Recursos S.l.",
    "wof:placetype":"venue"
},
  "geometry": {"coordinates":[-3.8430099487,40.4743881226],"type":"Point"}
}