{
  "type": "Feature",
  "properties": {
    "addr:full":"La Vega, 5 Sama De Grado Asturias 33829",
    "addr:housenumber":"5",
    "addr:postcode":"33829",
    "addr:street":"La Vega",
    "iso:country":"ES",
    "sg:address":"La Vega, 5",
    "sg:city":"Sama De Grado",
    "sg:orig_category":"Complementos De Vestir (al Por Menor)",
    "sg:phone":"+34 985 75 68 13",
    "sg:postcode":"33829",
    "sg:province":"Asturias",
    "wof:name":"Alvarez Fernandez Maria Teresa",
    "wof:placetype":"venue"
},
  "geometry": {"coordinates":[-6.0697302818,43.3885498047],"type":"Point"}
}