{
  "type": "Feature",
  "properties": {
    "addr:full":"El Crucero, 12 Sta Eulalia Asturias 33877",
    "addr:housenumber":"12",
    "addr:postcode":"33877",
    "addr:street":"El Crucero;Sta Eulalia Asturias",
    "iso:country":"ES",
    "sg:address":"El Crucero, 12",
    "sg:city":"Sta Eulalia",
    "sg:classifiers":[
        {
            "category":"Taxi",
            "type":"Transportation"
        }
    ],
    "sg:phone":"+34 985 80 03 12",
    "sg:postcode":"33877",
    "sg:province":"Asturias",
    "wof:name":"Gonzalez Linde Jovino",
    "wof:placetype":"venue"
},
  "geometry": {"coordinates":[-6.3802819252,43.4050369263],"type":"Point"}
}