{
  "type": "Feature",
  "properties": {
    "addr:full":"Plaz General Llopis, 5 Dolores Alicante 03150",
    "addr:housenumber":"5",
    "addr:postcode":"03150",
    "addr:street":"Llopis",
    "iso:country":"ES",
    "sg:address":"Plaz General Llopis, 5",
    "sg:city":"Dolores",
    "sg:orig_category":"Cajas De Ahorro",
    "sg:phone":"+34 965 72 62 65",
    "sg:postcode":"03150",
    "sg:province":"Alicante",
    "sg:website":"www.cajamurcia.es",
    "wof:name":"Caja De Ahorros De Murcia",
    "wof:placetype":"venue"
},
  "geometry": {"coordinates":[-0.7697039843,38.1368637085],"type":"Point"}
}