{
  "type": "Feature",
  "properties": {
    "addr:full":"Carrer de Corsega, 537 Barcelona Barcelona 08025",
    "addr:housenumber":"537",
    "addr:postcode":"08025",
    "addr:street":"Carrer De Corsega",
    "iso:country":"ES",
    "sg:address":"Carrer de Corsega, 537",
    "sg:city":"Barcelona",
    "sg:orig_category":"Fabricaci\u00d3n De Mantequilla (al Por Mayor)",
    "sg:phone":"+34 934 35 80 48",
    "sg:postcode":"08025",
    "sg:province":"Barcelona",
    "wof:name":"Mantequeria Yaya Amelia S.l.",
    "wof:placetype":"venue"
},
  "geometry": {"coordinates":[2.1712520123,41.405708313],"type":"Point"}
}