{
  "type": "Feature",
  "properties": {
    "addr:full":"Lomo La Palma (siete Palmas), 28 Las Palmas Las Palmas 35019",
    "addr:housenumber":"28",
    "addr:postcode":"35019",
    "addr:street":"Siete Palmas",
    "iso:country":"ES",
    "sg:address":"Lomo La Palma (siete Palmas), 28",
    "sg:city":"Las Palmas",
    "sg:orig_category":"Asesor\u00cda, Estudio Y Control Medioambiental",
    "sg:phone":"+34 928 42 45 93",
    "sg:postcode":"35019",
    "sg:province":"Las Palmas",
    "wof:name":"Applus Norcontrol S.l.u.",
    "wof:placetype":"venue"
},
  "geometry": {"coordinates":[-15.4865779877,27.9993572235],"type":"Point"}
}