{
  "type": "Feature",
  "properties": {
    "addr:full":"Calle de Cervantes, 31 Martos Ja\u00e9n 23600",
    "addr:housenumber":"31",
    "addr:postcode":"23600",
    "addr:street":"Calle De Cervantes;Jae\u0301N",
    "iso:country":"ES",
    "sg:address":"Calle de Cervantes, 31",
    "sg:city":"Martos",
    "sg:orig_category":"Promotores Constructores",
    "sg:phone":"+34 953 70 20 96",
    "sg:postcode":"23600",
    "sg:province":"Ja\u00e9n",
    "wof:name":"Rizquez Castellano Antonio",
    "wof:placetype":"venue"
},
  "geometry": {"coordinates":[-3.9711942673,37.7160720825],"type":"Point"}
}