{
  "type": "Feature",
  "properties": {
    "iso:country":"ES",
    "sg:address":"Calle de Abad Vi\u00d1ayo, 2",
    "sg:city":"Le\u00f3n",
    "sg:orig_category":"Caf\u00c9s, Bares, Cervecer\u00cdas",
    "sg:phone":"+34 987 80 62 03",
    "sg:postcode":"24008",
    "sg:province":"Le\u00f3n",
    "wof:name":"Sanchez Martin Miguel",
    "wof:placetype":"venue"
},
  "geometry": {"coordinates":[-5.5839977264,42.6062355042],"type":"Point"}
}