{
  "type": "Feature",
  "properties": {
    "addr:full":"Pl. Esglesia, S/n Selva Mar Girona 17489",
    "addr:housenumber":"s / n",
    "addr:postcode":"17489",
    "addr:street":"Pl. Esglesia",
    "iso:country":"ES",
    "sg:address":"Pl. Esglesia, S/n",
    "sg:city":"Selva Mar",
    "sg:orig_category":"Ense\u00d1anza, Formaci\u00d3n Profesional: Aprendizaje",
    "sg:phone":"+34 972 38 72 28",
    "sg:postcode":"17489",
    "sg:province":"Girona",
    "wof:name":"Ajuntament De La Selva De Mar",
    "wof:placetype":"venue"
},
  "geometry": {"coordinates":[3.2042434216,42.3381500244],"type":"Point"}
}