{
  "type": "Feature",
  "properties": {
    "iso:country":"ES",
    "sg:address":"Carrer de Amer, 2",
    "sg:city":"Olot",
    "sg:orig_category":"Panader\u00cdas, Panader\u00cdas",
    "sg:phone":"+34 972 27 16 81",
    "sg:postcode":"17800",
    "sg:province":"Girona",
    "wof:name":"Luque Lopez Juan",
    "wof:placetype":"venue"
},
  "geometry": {"coordinates":[2.4734590054,42.1708564758],"type":"Point"}
}