{
  "type": "Feature",
  "properties": {
    "iso:country":"ES",
    "sg:address":"Praj Quince Socios (los), S/n",
    "sg:city":"Huecija",
    "sg:orig_category":"Poli\u00c9ster",
    "sg:phone":"+34 950 64 14 24",
    "sg:postcode":"04409",
    "sg:province":"Almer\u00eda",
    "wof:name":"Poliester Andarax S.l.",
    "wof:placetype":"venue"
},
  "geometry": {"coordinates":[-2.6010990143,36.9648094177],"type":"Point"}
}