{
  "type": "Feature",
  "properties": {
    "addr:full":"Avda Xunqueira (a), 5 Reibon Pontevedra 36955",
    "addr:housenumber":"5",
    "addr:postcode":"36955",
    "addr:street":"Avda Xunqueira A",
    "iso:country":"ES",
    "sg:address":"Avda Xunqueira (a), 5",
    "sg:city":"Reibon",
    "sg:orig_category":"Artes Gr\u00c1ficas, Artes Pl\u00c1sticas: Material Y Suministros (al Por Menor)",
    "sg:phone":"+34 986 31 52 59",
    "sg:postcode":"36955",
    "sg:province":"Pontevedra",
    "wof:name":"Gonzalez Cortegoso Carlos",
    "wof:placetype":"venue"
},
  "geometry": {"coordinates":[-8.7202234268,42.2883415222],"type":"Point"}
}