{
  "type": "Feature",
  "properties": {
    "addr:full":"Bda Paz, 8 Utrera Sevilla 41710",
    "addr:housenumber":"8",
    "addr:postcode":"41710",
    "addr:street":"Bda Paz",
    "iso:country":"ES",
    "sg:address":"Bda Paz, 8",
    "sg:city":"Utrera",
    "sg:orig_category":"Reposter\u00cdas",
    "sg:phone":"+34 955 86 49 89",
    "sg:postcode":"41710",
    "sg:province":"Sevilla",
    "wof:name":"Obando Lopez Francisco De Paula",
    "wof:placetype":"venue"
},
  "geometry": {"coordinates":[-5.7763791084,37.1779022217],"type":"Point"}
}