{
  "type": "Feature",
  "properties": {
    "iso:country":"ES",
    "sg:address":"Calle de Ingeniero Torres Quevedo, S/n",
    "sg:city":"Cordoba",
    "sg:orig_category":"Adaptaciones, Acondicionamientos Especiales Para Veh\u00cdculos, Veh\u00cdculos Industriales",
    "sg:phone":"+34 957 42 91 98",
    "sg:postcode":"14013",
    "sg:province":"C\u00f3rdoba",
    "wof:name":"Reparaciones Y Rectificados Indust. S.l.l.",
    "wof:placetype":"venue"
},
  "geometry": {"coordinates":[-4.7939939499,37.853515625],"type":"Point"}
}