{
  "type": "Feature",
  "properties": {
    "addr:full":"Musakola Auzoa, 18 Arrasate Guip\u00f9zcoa 20500",
    "addr:housenumber":"18",
    "addr:postcode":"20500",
    "addr:street":"Musakola Auzoa;Guipu\u0300Zcoa",
    "iso:country":"ES",
    "sg:address":"Musakola Auzoa, 18",
    "sg:city":"Arrasate",
    "sg:orig_category":"Sistemas De Mando A Distancia",
    "sg:phone":"+34 943 79 10 20",
    "sg:postcode":"20500",
    "sg:province":"Guip\u00f9zcoa",
    "wof:name":"Jubar Ateak S.l",
    "wof:placetype":"venue"
},
  "geometry": {"coordinates":[-2.4945991039,43.060295105],"type":"Point"}
}