{
  "type": "Feature",
  "properties": {
    "addr:full":"El Palmero, 27 Fuente Alamo Murcia 30320",
    "addr:housenumber":"27",
    "addr:postcode":"30320",
    "addr:street":"El Palmero",
    "iso:country":"ES",
    "sg:address":"El Palmero, 27",
    "sg:city":"Fuente Alamo",
    "sg:orig_category":"Quincaller\u00cda (al Por Menor)",
    "sg:phone":"+34 968 59 60 00",
    "sg:postcode":"30320",
    "sg:province":"Murcia",
    "wof:name":"Ferreteria Fuentealamo S.l.",
    "wof:placetype":"venue"
},
  "geometry": {"coordinates":[-1.1687190533,37.7235946655],"type":"Point"}
}