{
  "type": "Feature",
  "properties": {
    "iso:country":"ES",
    "sg:address":"Pase Juan Casas (de), 13",
    "sg:city":"Jadraque",
    "sg:orig_category":"Promotores Constructores",
    "sg:phone":"+34 949 89 02 20",
    "sg:postcode":"19240",
    "sg:province":"Guadalajara",
    "wof:name":"Construcciones Ranz E Hijos S.l.",
    "wof:placetype":"venue"
},
  "geometry": {"coordinates":[-2.9257690907,40.9234886169],"type":"Point"}
}