{
  "type": "Feature",
  "properties": {
    "iso:country":"ES",
    "sg:address":"La Cogolla, S/n",
    "sg:city":"Cogolla",
    "sg:orig_category":"Mec\u00c1nico Del Autom\u00d3vil",
    "sg:phone":"+34 985 81 12 69",
    "sg:postcode":"33800",
    "sg:province":"Asturias",
    "wof:name":"Fontaniella Rojas Jose Luis",
    "wof:placetype":"venue"
},
  "geometry": {"coordinates":[-6.5502290726,43.1801643372],"type":"Point"}
}