{
  "type": "Feature",
  "properties": {
    "addr:full":"Carrer de Doctor Ferran, S/n Reus Tarragona 43202",
    "addr:housenumber":"s / n",
    "addr:postcode":"43202",
    "addr:street":"Carrer De Doctor Ferran",
    "iso:country":"ES",
    "sg:address":"Carrer de Doctor Ferran, S/n",
    "sg:city":"Reus",
    "sg:orig_category":"Centros De Educaci\u00d3n Especial",
    "sg:phone":"+34 977 31 25 93",
    "sg:postcode":"43202",
    "sg:province":"Tarragona",
    "wof:name":"Co%egi Public General Prim",
    "wof:placetype":"venue"
},
  "geometry": {"coordinates":[1.0976849794,41.1542739868],"type":"Point"}
}