{
  "type": "Feature",
  "properties": {
    "iso:country":"ES",
    "sg:address":"Plgno Ind Poniente, 4",
    "sg:city":"Catral",
    "sg:orig_category":"Muebles, Minoristas",
    "sg:phone":"+34 965 72 37 91",
    "sg:postcode":"03158",
    "sg:province":"Alicante",
    "wof:name":"Antiguos Ambientes S.l.",
    "wof:placetype":"venue"
},
  "geometry": {"coordinates":[-0.801499486,38.160949707],"type":"Point"}
}