{
  "type": "Feature",
  "properties": {
    "iso:country":"ES",
    "sg:address":"Calle de Ricardo Calvo, 39",
    "sg:city":"Malaga",
    "sg:orig_category":"Iglesia Cat\u00d3lica",
    "sg:phone":"+34 952 25 85 44",
    "sg:postcode":"29014",
    "sg:province":"M\u00e1laga",
    "wof:name":"Obispado De Malaga",
    "wof:placetype":"venue"
},
  "geometry": {"coordinates":[-4.4206571579,36.7415771484],"type":"Point"}
}