{
  "type": "Feature",
  "properties": {
    "addr:full":"Avda Roquetas, 34 Roquetas Mar Almer\u00eda 04740",
    "addr:housenumber":"34",
    "addr:postcode":"04740",
    "addr:street":"Avda Roquetas;Mar Almeri\u0301A",
    "iso:country":"ES",
    "sg:address":"Avda Roquetas, 34",
    "sg:city":"Roquetas Mar",
    "sg:orig_category":"Costureras",
    "sg:phone":"+34 950 32 09 14",
    "sg:postcode":"04740",
    "sg:province":"Almer\u00eda",
    "wof:name":"Tenorio Herrera Ramona",
    "wof:placetype":"venue"
},
  "geometry": {"coordinates":[-2.6124989986,36.7638435364],"type":"Point"}
}