{
  "type": "Feature",
  "properties": {
    "iso:country":"ES",
    "sg:address":"Calle de Hernan Cortes, 26",
    "sg:city":"Siruela",
    "sg:orig_category":"Art\u00cdculos De Decoraci\u00d3n",
    "sg:phone":"+34 924 62 61 77",
    "sg:postcode":"06650",
    "sg:province":"Badajoz",
    "wof:name":"Armeria Parasole Sl",
    "wof:placetype":"venue"
},
  "geometry": {"coordinates":[-5.0466747284,38.9752960205],"type":"Point"}
}