{
  "type": "Feature",
  "properties": {
    "iso:country":"ES",
    "sg:address":"Calle de Moreno De Vargas, 3",
    "sg:city":"Merida",
    "sg:orig_category":"Heladeros",
    "sg:phone":"+34 924 31 69 50",
    "sg:postcode":"06800",
    "sg:province":"Badajoz",
    "wof:name":"Diexsa Audiovisuales S.l.",
    "wof:placetype":"venue"
},
  "geometry": {"coordinates":[-6.3464841843,38.916053772],"type":"Point"}
}