{
  "type": "Feature",
  "properties": {
    "iso:country":"ES",
    "sg:address":"Calle de Malva, 1",
    "sg:city":"Quinto",
    "sg:orig_category":"Fisioterapia",
    "sg:phone":"+34 954 12 26 35",
    "sg:postcode":"41089",
    "sg:province":"Sevilla",
    "wof:name":"Andrade Higueras Juan Antonio",
    "wof:placetype":"venue"
},
  "geometry": {"coordinates":[-5.9962949753,37.3826408386],"type":"Point"}
}