{
  "type": "Feature",
  "properties": {
    "addr:full":"Calle de Mundaiz, 30 Donostia-san Sebastian Guip\u00f9zcoa 20012",
    "addr:housenumber":"30",
    "addr:postcode":"20012",
    "addr:street":"Calle De Mundaiz",
    "iso:country":"ES",
    "sg:address":"Calle de Mundaiz, 30",
    "sg:city":"Donostia-san Sebastian",
    "sg:orig_category":"Internados & Ense\u00d1anza Privada",
    "sg:phone":"+34 943 32 70 02",
    "sg:postcode":"20012",
    "sg:province":"Guip\u00f9zcoa",
    "wof:name":"Instituto Hermanos Del Sagrado Corazon",
    "wof:placetype":"venue"
},
  "geometry": {"coordinates":[-1.9770720005,43.3104896545],"type":"Point"}
}