{
  "type": "Feature",
  "properties": {
    "addr:full":"Carrer de Francesc De P. Bove, 2 Vilafranca Penedes Barcelona 08720",
    "addr:housenumber":"2",
    "addr:postcode":"08720",
    "addr:street":"Carrer De Francesc De P. Bove;Penedes Barcelona",
    "iso:country":"ES",
    "sg:address":"Carrer de Francesc De P. Bove, 2",
    "sg:city":"Vilafranca Penedes",
    "sg:orig_category":"Librer\u00cdas",
    "sg:phone":"+34 938 90 26 90",
    "sg:postcode":"08720",
    "sg:province":"Barcelona",
    "wof:name":"Olle Fito Monserrat",
    "wof:placetype":"venue"
},
  "geometry": {"coordinates":[1.6926829815,41.3445510864],"type":"Point"}
}