{
  "type": "Feature",
  "properties": {
    "iso:country":"ES",
    "sg:address":"Calle de Doctor Vaca Castro, 2",
    "sg:city":"Granada",
    "sg:orig_category":"Fabricaci\u00d3n De Juguetes Autom\u00c1ticos",
    "sg:phone":"+34 958 29 25 13",
    "sg:postcode":"18015",
    "sg:province":"Granada",
    "wof:name":"Marin Y Rodriguez S.l.",
    "wof:placetype":"venue"
},
  "geometry": {"coordinates":[-3.6248033047,37.1930122375],"type":"Point"}
}