{
  "type": "Feature",
  "properties": {
    "iso:country":"ES",
    "sg:address":"Avda. Finisterre, 270",
    "sg:city":"A Coru\u00f1a",
    "sg:orig_category":"Carnicer\u00cdas, Carnicer\u00cdas",
    "sg:phone":"+34 981 26 16 62",
    "sg:postcode":"15010",
    "sg:province":"La Coru\u00f1a",
    "wof:name":"Leston Cantari\u00f1o Raul",
    "wof:placetype":"venue"
},
  "geometry": {"coordinates":[-8.4191455841,43.3595199585],"type":"Point"}
}