{
  "type": "Feature",
  "properties": {
    "iso:country":"ES",
    "sg:address":"Calle de Iba\u00d1ez De Bilbao, 4",
    "sg:city":"Bilbao",
    "sg:orig_category":"Grabados",
    "sg:phone":"+34 944 23 60 42",
    "sg:postcode":"48001",
    "sg:province":"Vizcaya",
    "wof:name":"Angel Lazaro Llorente",
    "wof:placetype":"venue"
},
  "geometry": {"coordinates":[-2.9257466793,43.2628440857],"type":"Point"}
}