{
  "type": "Feature",
  "properties": {
    "iso:country":"ES",
    "sg:address":"Av Poal, 8",
    "sg:city":"Castelldefels",
    "sg:orig_category":"Limpieza Industrial",
    "sg:phone":"+34 936 36 60 91",
    "sg:postcode":"08860",
    "sg:province":"Barcelona",
    "sg:website":"www.neteges-roter.com",
    "wof:name":"Serveis I Neteja Roter S.l.",
    "wof:placetype":"venue"
},
  "geometry": {"coordinates":[1.9446790218,41.2685279846],"type":"Point"}
}