{
  "type": "Feature",
  "properties": {
    "iso:country":"ES",
    "sg:address":"Gta Luis Braille, 4",
    "sg:city":"Burgos",
    "sg:orig_category":"Empresas De Limpieza",
    "sg:phone":"+34 947 48 98 94",
    "sg:postcode":"09007",
    "sg:province":"Burgos",
    "wof:name":"Herrera Martin Jesus Santos",
    "wof:placetype":"venue"
},
  "geometry": {"coordinates":[-3.6637070179,42.3514633179],"type":"Point"}
}