{
  "type": "Feature",
  "properties": {
    "addr:full":"Psaj Sandalo (del), 2 Cuenca Cuenca 16004",
    "addr:postcode":"16004",
    "iso:country":"ES",
    "sg:address":"Psaj Sandalo (del), 2",
    "sg:city":"Cuenca",
    "sg:orig_category":"Partidos Pol\u00cdticos",
    "sg:phone":"+34 969 21 26 31",
    "sg:postcode":"16004",
    "sg:province":"Cuenca",
    "wof:name":"Partido Popular",
    "wof:placetype":"venue"
},
  "geometry": {"coordinates":[-2.1309819221,40.063873291],"type":"Point"}
}