{
  "type": "Feature",
  "properties": {
    "iso:country":"ES",
    "sg:address":"Plaz Pintor Caneja, 1",
    "sg:city":"Palencia",
    "sg:orig_category":"Ingenieros Asesor\u00cda",
    "sg:phone":"+34 979 75 15 47",
    "sg:postcode":"34001",
    "sg:province":"Palencia",
    "wof:name":"Pastor Cuesta Jesus",
    "wof:placetype":"venue"
},
  "geometry": {"coordinates":[-4.5304951668,42.0125350952],"type":"Point"}
}