{
  "type": "Feature",
  "properties": {
    "iso:country":"ES",
    "sg:address":"Carrer de Montseny, 22",
    "sg:city":"Sabadell",
    "sg:orig_category":"Promotores Constructores",
    "sg:phone":"+34 937 23 89 28",
    "sg:postcode":"08208",
    "sg:province":"Barcelona",
    "wof:name":"Dracma Greek S.l",
    "wof:placetype":"venue"
},
  "geometry": {"coordinates":[2.1053369045,41.5549430847],"type":"Point"}
}