{
  "type": "Feature",
  "properties": {
    "iso:country":"ES",
    "sg:address":"P Ind Risco Prieto, S/n",
    "sg:city":"Pto. Rosario",
    "sg:orig_category":"Delegados, Agentes De Tr\u00c1nsito, Auxiliares De Transporte Internacional",
    "sg:phone":"+34 928 53 07 15",
    "sg:postcode":"35600",
    "sg:province":"Las Palmas",
    "wof:name":"Via Gregorio S.l.",
    "wof:placetype":"venue"
},
  "geometry": {"coordinates":[-13.8644685745,28.5023498535],"type":"Point"}
}