{
  "type": "Feature",
  "properties": {
    "iso:country":"ES",
    "sg:address":"Plaz Tagores, 5",
    "sg:city":"Huelva",
    "sg:orig_category":"Costureras",
    "sg:phone":"+34 959 15 11 01",
    "sg:postcode":"21005",
    "sg:province":"Huelva",
    "wof:name":"Pereira Hidalgo Adelina",
    "wof:placetype":"venue"
},
  "geometry": {"coordinates":[-6.9404568672,37.2804069519],"type":"Point"}
}