{
  "type": "Feature",
  "properties": {
    "iso:country":"ES",
    "sg:address":"Calle de Santos Justo Y Pastor, 59",
    "sg:city":"Valencia",
    "sg:orig_category":"Institutos De Belleza",
    "sg:phone":"+34 963 55 43 24",
    "sg:postcode":"46022",
    "sg:province":"Valencia",
    "wof:name":"Salon De Belleza Noema",
    "wof:placetype":"venue"
},
  "geometry": {"coordinates":[-0.3473049998,39.4695549011],"type":"Point"}
}