{
  "type": "Feature",
  "properties": {
    "iso:country":"ES",
    "sg:address":"Calle de Ruiz De Alarcon, 22",
    "sg:city":"Burgos",
    "sg:orig_category":"Delegados, Agentes De Tr\u00c1nsito, Auxiliares De Transporte Internacional",
    "sg:phone":"+34 947 27 96 01",
    "sg:postcode":"09002",
    "sg:province":"Burgos",
    "wof:name":"Santillan Pedrosa Jesus",
    "wof:placetype":"venue"
},
  "geometry": {"coordinates":[-3.694453001,42.331993103],"type":"Point"}
}