{
  "type": "Feature",
  "properties": {
    "iso:country":"ES",
    "sg:address":"Calle de Magdalena, 16",
    "sg:city":"Dos-torres",
    "sg:orig_category":"Asilos De Ancianos. Centros Privados",
    "sg:phone":"+34 957 13 41 28",
    "sg:postcode":"14460",
    "sg:province":"C\u00f3rdoba",
    "wof:name":"Fundacion San Andres Y La Magdalena",
    "wof:placetype":"venue"
},
  "geometry": {"coordinates":[-4.8940501213,38.4459838867],"type":"Point"}
}