{
  "type": "Feature",
  "properties": {
    "iso:country":"ES",
    "sg:address":"Avda Mediterraneo, 10",
    "sg:city":"Gran Alacant",
    "sg:orig_category":"Caf\u00c9s, Bares, Cervecer\u00cdas",
    "sg:phone":"+34 966 69 76 35",
    "sg:postcode":"03130",
    "sg:province":"Alicante",
    "wof:name":"Almansa Collado Angelita",
    "wof:placetype":"venue"
},
  "geometry": {"coordinates":[-0.5362058878,38.2310066223],"type":"Point"}
}