{
  "type": "Feature",
  "properties": {
    "addr:full":"Av Rapita (de La), 30 Amposta Tarragona 43870",
    "addr:housenumber":"30",
    "addr:postcode":"43870",
    "addr:street":"Av Rapita De La",
    "iso:country":"ES",
    "sg:address":"Av Rapita (de La), 30",
    "sg:city":"Amposta",
    "sg:orig_category":"Asociaciones Y Clubs Deportivos",
    "sg:phone":"+34 977 70 22 22",
    "sg:postcode":"43870",
    "sg:province":"Tarragona",
    "wof:name":"Ferreres Cases Jesus",
    "wof:placetype":"venue"
},
  "geometry": {"coordinates":[0.5799080133,40.7111091614],"type":"Point"}
}