{
  "type": "Feature",
  "properties": {
    "addr:full":"Calle de Padre Damian, 10 Sevilla Sevilla 41011",
    "addr:housenumber":"10",
    "addr:postcode":"41011",
    "addr:street":"Calle De Padre Damian",
    "iso:country":"ES",
    "sg:address":"Calle de Padre Damian, 10",
    "sg:city":"Sevilla",
    "sg:orig_category":"Fotocopias, Reprograf\u00cda",
    "sg:phone":"+34 954 45 36 49",
    "sg:postcode":"41011",
    "sg:province":"Sevilla",
    "wof:name":"Rodado Garcia Jose Manuel",
    "wof:placetype":"venue"
},
  "geometry": {"coordinates":[-5.9999670982,37.3742408752],"type":"Point"}
}