{
  "type": "Feature",
  "properties": {
    "iso:country":"ES",
    "sg:address":"Moss\u00e9n Cinto Verdaguer, 1",
    "sg:city":"S. Esteve Sesrovires",
    "sg:orig_category":"Ropa De Trabajo Y Profesionales (al Por Menor)",
    "sg:phone":"+34 937 71 46 93",
    "sg:postcode":"08635",
    "sg:province":"Barcelona",
    "wof:name":"Vestuario Laboral Marcatex S.l.",
    "wof:placetype":"venue"
},
  "geometry": {"coordinates":[1.8729660511,41.4926376343],"type":"Point"}
}