{
  "type": "Feature",
  "properties": {
    "addr:full":"Pase General Davila, 41 Santander Cantabria 39006",
    "addr:housenumber":"41",
    "addr:postcode":"39006",
    "addr:street":"Davila",
    "iso:country":"ES",
    "sg:address":"Pase General Davila, 41",
    "sg:city":"Santander",
    "sg:orig_category":"Limpieza De Alfombras",
    "sg:phone":"+34 942 21 65 68",
    "sg:postcode":"39006",
    "sg:province":"Cantabria",
    "wof:name":"Pozuelo Lucio Martin",
    "wof:placetype":"venue"
},
  "geometry": {"coordinates":[-3.8018410206,43.4674453735],"type":"Point"}
}