{
  "type": "Feature",
  "properties": {
    "addr:full":"Carrer de Santa Marta, 2 Terrassa Barcelona 08222",
    "addr:housenumber":"2",
    "addr:postcode":"08222",
    "addr:street":"Carrer De Santa Marta",
    "iso:country":"ES",
    "sg:address":"Carrer de Santa Marta, 2",
    "sg:city":"Terrassa",
    "sg:orig_category":"Peleter\u00cdas",
    "sg:phone":"+34 937 85 61 87",
    "sg:postcode":"08222",
    "sg:province":"Barcelona",
    "wof:name":"Prieto Plaza Miguel Angel",
    "wof:placetype":"venue"
},
  "geometry": {"coordinates":[2.0303299427,41.558921814],"type":"Point"}
}