{
  "type": "Feature",
  "properties": {
    "addr:full":"Ctra Gijon-sevilla, S/n Villafranca De Los Barros Badajoz 06220",
    "addr:housenumber":"s / n",
    "addr:postcode":"06220",
    "addr:street":"Ctra Gijon-Sevilla",
    "iso:country":"ES",
    "sg:address":"Ctra Gijon-sevilla, S/n",
    "sg:city":"Villafranca De Los Barros",
    "sg:orig_category":"Muebles, Minoristas",
    "sg:phone":"+34 924 52 32 85",
    "sg:postcode":"06220",
    "sg:province":"Badajoz",
    "wof:name":"Lavado Gaspar Rafaela Francisca",
    "wof:placetype":"venue"
},
  "geometry": {"coordinates":[-6.3426737785,38.5613861084],"type":"Point"}
}