{
  "type": "Feature",
  "properties": {
    "iso:country":"ES",
    "sg:address":"Calle de Blas Infante, 7",
    "sg:city":"Villa Rio",
    "sg:orig_category":"Cajas De Ahorro",
    "sg:phone":"+34 957 17 61 71",
    "sg:postcode":"14640",
    "sg:province":"C\u00f3rdoba",
    "sg:website":"www.cajasur.es",
    "wof:name":"Caja De Ahorros Y Monte De Piedad De Cordoba",
    "wof:placetype":"venue"
},
  "geometry": {"coordinates":[-4.2917289734,37.9820480347],"type":"Point"}
}