{
  "type": "Feature",
  "properties": {
    "addr:full":"Calle de Zacatin, 16 Granada Granada 18001",
    "addr:housenumber":"16",
    "addr:postcode":"18001",
    "addr:street":"Calle De Zacatin",
    "iso:country":"ES",
    "sg:address":"Calle de Zacatin, 16",
    "sg:city":"Granada",
    "sg:orig_category":"Bisuter\u00cda, Joyer\u00cda, Relojer\u00cda (al Por Menor)",
    "sg:phone":"+34 958 21 53 70",
    "sg:postcode":"18001",
    "sg:province":"Granada",
    "wof:name":"Six Shop S.l.",
    "wof:placetype":"venue"
},
  "geometry": {"coordinates":[-3.5988988876,37.1751976013],"type":"Point"}
}