{
  "type": "Feature",
  "properties": {
    "iso:country":"ES",
    "sg:address":"Calle de Zarza, 29",
    "sg:city":"Villanueva Cordoba",
    "sg:orig_category":"Imprenta",
    "sg:phone":"+34 957 12 16 57",
    "sg:postcode":"14440",
    "sg:province":"C\u00f3rdoba",
    "wof:name":"Impresiones Doble A Sl",
    "wof:placetype":"venue"
},
  "geometry": {"coordinates":[-4.6214590073,38.3229827881],"type":"Point"}
}