{
  "type": "Feature",
  "properties": {
    "addr:full":"Calle de Granados, 20 Le\u00f3n Le\u00f3n 24006",
    "addr:housenumber":"20",
    "addr:postcode":"24006",
    "addr:street":"Calle De Granados;Leo\u0301N",
    "iso:country":"ES",
    "sg:address":"Calle de Granados, 20",
    "sg:city":"Le\u00f3n",
    "sg:orig_category":"Suministros Para Hoteles",
    "sg:phone":"+34 987 20 84 78",
    "sg:postcode":"24006",
    "sg:province":"Le\u00f3n",
    "sg:website":"www.seral-service.com",
    "wof:name":"Servicios Renovados De Alimentacion S.a.",
    "wof:placetype":"venue"
},
  "geometry": {"coordinates":[-5.5606098175,42.5928459167],"type":"Point"}
}