{
  "type": "Feature",
  "properties": {
    "addr:full":"Calle de Linares, 21 Velez-malaga M\u00e1laga 29700",
    "addr:housenumber":"21",
    "addr:postcode":"29700",
    "addr:street":"Calle De Linares",
    "iso:country":"ES",
    "sg:address":"Calle de Linares, 21",
    "sg:city":"Velez-malaga",
    "sg:orig_category":"Pintura Y Barniz (al Por Menor)",
    "sg:phone":"+34 952 50 24 54",
    "sg:postcode":"29700",
    "sg:province":"M\u00e1laga",
    "wof:name":"Gallego Bueno Francisco",
    "wof:placetype":"venue"
},
  "geometry": {"coordinates":[-4.0992588997,36.7717094421],"type":"Point"}
}