{
  "type": "Feature",
  "properties": {
    "iso:country":"ES",
    "sg:address":"Cmno Soparda Bidea, 10",
    "sg:city":"Baserri-santa Ana",
    "sg:orig_category":"Internados & Ense\u00d1anza Privada",
    "sg:phone":"+34 946 68 02 60",
    "sg:postcode":"48640",
    "sg:province":"Vizcaya",
    "sg:website":"www.sarenet.es/asb",
    "wof:name":"American School Of Bilbao",
    "wof:placetype":"venue"
},
  "geometry": {"coordinates":[-2.9867544174,43.3549461365],"type":"Point"}
}