{
  "type": "Feature",
  "properties": {
    "addr:full":"Cuadro, S/n Pillarno Asturias 33456",
    "addr:housenumber":"s",
    "addr:postcode":"33456",
    "addr:street":"Cuadro;/ N Pillarno Asturias",
    "iso:country":"ES",
    "sg:address":"Cuadro, S/n",
    "sg:city":"Pillarno",
    "sg:orig_category":"Iglesia Cat\u00d3lica",
    "sg:phone":"+34 985 53 25 10",
    "sg:postcode":"33456",
    "sg:province":"Asturias",
    "wof:name":"Diocesis De Oviedo",
    "wof:placetype":"venue"
},
  "geometry": {"coordinates":[-5.9890618324,43.5465087891],"type":"Point"}
}