{
  "type": "Feature",
  "properties": {
    "iso:country":"ES",
    "sg:address":"Carr Mariano Amigo, 29",
    "sg:city":"Pu\u00e7ol",
    "sg:orig_category":"Fabricaci\u00d3n De Bebidas No Alcoh\u00d3licas",
    "sg:phone":"+34 961 42 40 42",
    "sg:postcode":"46530",
    "sg:province":"Valencia",
    "wof:name":"Solete Spania S.a.",
    "wof:placetype":"venue"
},
  "geometry": {"coordinates":[-0.3009139895,39.6173057556],"type":"Point"}
}