{
  "type": "Feature",
  "properties": {
    "addr:full":"Calle de Abadia Del Rosario, 1 Valencia Valencia 46011",
    "addr:housenumber":"1",
    "addr:postcode":"46011",
    "addr:street":"Calle De Abadia Del Rosario",
    "iso:country":"ES",
    "sg:address":"Calle de Abadia Del Rosario, 1",
    "sg:city":"Valencia",
    "sg:orig_category":"Electrodom\u00c9sticos (al Por Menor)",
    "sg:phone":"+34 963 16 50 20",
    "sg:postcode":"46011",
    "sg:province":"Valencia",
    "wof:name":"Aa General Electric Asistencia Tecnica A",
    "wof:placetype":"venue"
},
  "geometry": {"coordinates":[-0.330134,39.473034],"type":"Point"}
}