{
  "type": "Feature",
  "properties": {
    "addr:full":"Salbe Auzunea, 35 Azpeitia Guip\u00f9zcoa 20730",
    "addr:housenumber":"35",
    "addr:postcode":"20730",
    "addr:street":"Salbe Auzunea;Guipu\u0300Zcoa",
    "iso:country":"ES",
    "sg:address":"Salbe Auzunea, 35",
    "sg:city":"Azpeitia",
    "sg:orig_category":"Pintura Y Barniz (al Por Menor)",
    "sg:phone":"+34 943 08 00 49",
    "sg:postcode":"20730",
    "sg:province":"Guip\u00f9zcoa",
    "wof:name":"Sorkunde Urbistondo Artetxe (urbistondo Margoak)",
    "wof:placetype":"venue"
},
  "geometry": {"coordinates":[-2.2638750076,43.1857795715],"type":"Point"}
}