{
  "type": "Feature",
  "properties": {
    "addr:full":"Major, 53 Bossost Lleida 25550",
    "addr:housenumber":"53",
    "addr:postcode":"25550",
    "addr:street":"Major",
    "iso:country":"ES",
    "sg:address":"Major, 53",
    "sg:city":"Bossost",
    "sg:orig_category":"Art\u00cdculos De Regalo (al Por Menor)",
    "sg:phone":"+34 973 64 82 60",
    "sg:postcode":"25550",
    "sg:province":"Lleida",
    "wof:name":"Pena Huguet Francisco",
    "wof:placetype":"venue"
},
  "geometry": {"coordinates":[0.6936190128,42.7876586914],"type":"Point"}
}