{
  "type": "Feature",
  "properties": {
    "addr:full":"Avda Guardia Civil, 9 Tobarra Albacete 02500",
    "addr:housenumber":"9",
    "addr:postcode":"02500",
    "addr:street":"Avda Guardia Civil",
    "iso:country":"ES",
    "sg:address":"Avda Guardia Civil, 9",
    "sg:city":"Tobarra",
    "sg:orig_category":"Confecci\u00d3n De Zapatos",
    "sg:phone":"+34 967 32 53 43",
    "sg:postcode":"02500",
    "sg:province":"Albacete",
    "wof:name":"Aparados Ontur S.l.",
    "wof:placetype":"venue"
},
  "geometry": {"coordinates":[-1.6903936863,38.5858917236],"type":"Point"}
}