{
  "type": "Feature",
  "properties": {
    "addr:full":"Calle de Utrera, 12 Velez-malaga M\u00e1laga 29700",
    "addr:housenumber":"12",
    "addr:postcode":"29700",
    "addr:street":"Calle De Utrera",
    "iso:country":"ES",
    "sg:address":"Calle de Utrera, 12",
    "sg:city":"Velez-malaga",
    "sg:orig_category":"Institutos De Belleza",
    "sg:phone":"+34 952 50 01 85",
    "sg:postcode":"29700",
    "sg:province":"M\u00e1laga",
    "wof:name":"Manuela E Isabel Perez Labao S.c",
    "wof:placetype":"venue"
},
  "geometry": {"coordinates":[-4.1051659584,36.7810134888],"type":"Point"}
}