{
  "type": "Feature",
  "properties": {
    "addr:full":"Avda Constitucion (de La), 194 Poligono Industrial Monte Boyal Toledo 45950",
    "addr:housenumber":"194",
    "addr:postcode":"45950",
    "addr:street":"Avda Constitucion De La;Poligono Industrial Monte Boyal",
    "iso:country":"ES",
    "sg:address":"Avda Constitucion (de La), 194",
    "sg:city":"Poligono Industrial Monte Boyal",
    "sg:orig_category":"Molduras, Junquillos, Listones Y Molduras Perforadas",
    "sg:phone":"+34 918 18 32 88",
    "sg:postcode":"45950",
    "sg:province":"Toledo",
    "wof:name":"V-cut Europe S.l.",
    "wof:placetype":"venue"
},
  "geometry": {"coordinates":[-4.0531868935,40.2130241394],"type":"Point"}
}