{
  "type": "Feature",
  "properties": {
    "addr:full":"Calle de Almudena, 48 Torrevieja Alicante 03180",
    "addr:housenumber":"48",
    "addr:postcode":"03180",
    "addr:street":"Calle De Almudena",
    "iso:country":"ES",
    "sg:address":"Calle de Almudena, 48",
    "sg:city":"Torrevieja",
    "sg:orig_category":"Molduras, Junquillos, Listones Y Molduras Perforadas",
    "sg:phone":"+34 965 70 33 21",
    "sg:postcode":"03180",
    "sg:province":"Alicante",
    "wof:name":"Oliveros Gimenez Francisco",
    "wof:placetype":"venue"
},
  "geometry": {"coordinates":[-0.6733070016,37.980922699],"type":"Point"}
}