{
  "type": "Feature",
  "properties": {
    "iso:country":"ES",
    "sg:address":"Av Prat De La Riba, 37",
    "sg:city":"Reus",
    "sg:orig_category":"Abogados",
    "sg:phone":"+34 977 31 80 22",
    "sg:postcode":"43201",
    "sg:province":"Tarragona",
    "wof:name":"Curto Calbet Anna Maria",
    "wof:placetype":"venue"
},
  "geometry": {"coordinates":[1.1031960249,41.1574935913],"type":"Point"}
}