{
  "type": "Feature",
  "properties": {
    "addr:full":"Cmno Viejo De Velez, 75 Torre Benagalbon M\u00e1laga 29738",
    "addr:housenumber":"75",
    "addr:postcode":"29738",
    "addr:street":"Cmno Viejo De Velez;Ma\u0301Laga",
    "iso:country":"ES",
    "sg:address":"Cmno Viejo De Velez, 75",
    "sg:city":"Torre Benagalbon",
    "sg:orig_category":"Construcciones Met\u00c1licas",
    "sg:phone":"+34 952 97 08 20",
    "sg:postcode":"29738",
    "sg:province":"M\u00e1laga",
    "wof:name":"Benametal S.l.",
    "wof:placetype":"venue"
},
  "geometry": {"coordinates":[-4.2545151711,36.7120399475],"type":"Point"}
}