{
  "type": "Feature",
  "properties": {
    "iso:country":"ES",
    "sg:address":"Plaz Mayor, 9",
    "sg:city":"Solana",
    "sg:orig_category":"Laboratorios Y Trabajos De Fotograf\u00cda, V\u00cddeo Y Cine",
    "sg:phone":"+34 926 63 31 52",
    "sg:postcode":"13240",
    "sg:province":"Ciudad Real",
    "wof:name":"Chacon Fumes Juan Felix",
    "wof:placetype":"venue"
},
  "geometry": {"coordinates":[-3.2367699146,38.9386825562],"type":"Point"}
}