{
  "type": "Feature",
  "properties": {
    "iso:country":"ES",
    "sg:address":"Avda Daroca, 40",
    "sg:city":"Madrid",
    "sg:orig_category":"Mec\u00c1nico Del Autom\u00d3vil",
    "sg:phone":"+34 917 25 78 99",
    "sg:postcode":"28017",
    "sg:province":"Madrid",
    "wof:name":"Fernandez Hernandez Gonzalo Maria",
    "wof:placetype":"venue"
},
  "geometry": {"coordinates":[-3.6555950642,40.4296875],"type":"Point"}
}