{
  "type": "Feature",
  "properties": {
    "iso:country":"ES",
    "sg:address":"Pg Jose Canalejas, 2",
    "sg:city":"Girona",
    "sg:orig_category":"Arquitectos",
    "sg:phone":"+34 972 20 88 65",
    "sg:postcode":"17001",
    "sg:province":"Girona",
    "wof:name":"Pla Torres Juan",
    "wof:placetype":"venue"
},
  "geometry": {"coordinates":[2.8233890533,41.9867935181],"type":"Point"}
}