{
  "type": "Feature",
  "properties": {
    "addr:full":"Calle de Bizkai, 77 Galdakao Vizcaya 48960",
    "addr:housenumber":"77",
    "addr:postcode":"48960",
    "addr:street":"Calle De Bizkai",
    "iso:country":"ES",
    "sg:address":"Calle de Bizkai, 77",
    "sg:city":"Galdakao",
    "sg:orig_category":"Molduras, Junquillos, Listones Y Molduras Perforadas",
    "sg:phone":"+34 944 56 82 06",
    "sg:postcode":"48960",
    "sg:province":"Vizcaya",
    "wof:name":"Juan Manuel Chaparro Romero (bar Rioja)",
    "wof:placetype":"venue"
},
  "geometry": {"coordinates":[-2.8479349613,43.2339897156],"type":"Point"}
}