{
  "type": "Feature",
  "properties": {
    "addr:full":"Avda Callejuela, 8 Trijueque Guadalajara 19192",
    "addr:housenumber":"8",
    "addr:postcode":"19192",
    "addr:street":"Avda Callejuela",
    "iso:country":"ES",
    "sg:address":"Avda Callejuela, 8",
    "sg:city":"Trijueque",
    "sg:orig_category":"Iglesia Cat\u00d3lica",
    "sg:phone":"+34 949 32 01 34",
    "sg:postcode":"19192",
    "sg:province":"Guadalajara",
    "wof:name":"Obispado De Sig\u00fcenza - Guadalajara",
    "wof:placetype":"venue"
},
  "geometry": {"coordinates":[-2.9958291054,40.7765884399],"type":"Point"}
}