{
  "type": "Feature",
  "properties": {
    "addr:full":"Calle de Nueva, 23 Teruel Teruel 44001",
    "addr:housenumber":"23",
    "addr:postcode":"44001",
    "addr:street":"Calle De Nueva",
    "iso:country":"ES",
    "sg:address":"Calle de Nueva, 23",
    "sg:city":"Teruel",
    "sg:orig_category":"Artesan\u00cda",
    "sg:phone":"+34 978 60 49 04",
    "sg:postcode":"44001",
    "sg:province":"Teruel",
    "wof:name":"Lopez Olivas Asuncion",
    "wof:placetype":"venue"
},
  "geometry": {"coordinates":[-1.1079130173,40.3415489197],"type":"Point"}
}