{
  "type": "Feature",
  "properties": {
    "addr:full":"Carr Camp Roig, 25 Alaro Islas Baleares 07340",
    "addr:housenumber":"25",
    "addr:postcode":"07340",
    "addr:street":"Carr Camp Roig",
    "iso:country":"ES",
    "sg:address":"Carr Camp Roig, 25",
    "sg:city":"Alaro",
    "sg:orig_category":"Compraventa De Antig\u00dcedades",
    "sg:phone":"+34 971 51 06 06",
    "sg:postcode":"07340",
    "sg:province":"Islas Baleares",
    "wof:name":"Homar Ferragut Gabriel",
    "wof:placetype":"venue"
},
  "geometry": {"coordinates":[2.7899799347,39.7058296204],"type":"Point"}
}