{
  "type": "Feature",
  "properties": {
    "iso:country":"ES",
    "sg:address":"Calle de Jerez, 2",
    "sg:city":"Maracena",
    "sg:orig_category":"Ense\u00d1anza: Idiomas",
    "sg:phone":"+34 958 41 17 49",
    "sg:postcode":"18200",
    "sg:province":"Granada",
    "wof:name":"Martinez Guirado Maria Dolores",
    "wof:placetype":"venue"
},
  "geometry": {"coordinates":[-3.6292660236,37.2056236267],"type":"Point"}
}