{
  "type": "Feature",
  "properties": {
    "addr:full":"Calle de Pedro Ruiz, 4 Rambla C\u00f3rdoba 14540",
    "addr:housenumber":"4",
    "addr:postcode":"14540",
    "addr:street":"Calle De Pedro Ruiz;Rambla Co\u0301Rdoba",
    "iso:country":"ES",
    "sg:address":"Calle de Pedro Ruiz, 4",
    "sg:city":"Rambla",
    "sg:orig_category":"Asesor\u00cda Fiscal Y Jur\u00cddica",
    "sg:phone":"+34 957 68 40 56",
    "sg:postcode":"14540",
    "sg:province":"C\u00f3rdoba",
    "wof:name":"Lucena Asesores S.l.",
    "wof:placetype":"venue"
},
  "geometry": {"coordinates":[-4.7417740822,37.6074180603],"type":"Point"}
}