{
  "type": "Feature",
  "properties": {
    "addr:full":"Calle de Francos Rodriguez, 82 Madrid Madrid 28039",
    "addr:housenumber":"82",
    "addr:postcode":"madrid;28039",
    "addr:street":"Calle De Francos Rodriguez",
    "iso:country":"ES",
    "sg:address":"Calle de Francos Rodriguez, 82",
    "sg:city":"Madrid",
    "sg:orig_category":"Promotores Constructores",
    "sg:phone":"+34 913 11 49 20",
    "sg:postcode":"28039",
    "sg:province":"Madrid",
    "wof:name":"Comunidad De Propietarios Franco Rodriguez 82",
    "wof:placetype":"venue"
},
  "geometry": {"coordinates":[-3.7099280357,40.4574661255],"type":"Point"}
}