{
  "type": "Feature",
  "properties": {
    "iso:country":"ES",
    "sg:address":"Calle de Fernando Moran, 15",
    "sg:city":"Aviles",
    "sg:orig_category":"Caf\u00c9s, Bares, Cervecer\u00cdas",
    "sg:phone":"+34 985 52 27 58",
    "sg:postcode":"33401",
    "sg:province":"Asturias",
    "wof:name":"Miranda Mesa Ana Maria",
    "wof:placetype":"venue"
},
  "geometry": {"coordinates":[-5.9324836731,43.5562515259],"type":"Point"}
}