{
  "type": "Feature",
  "properties": {
    "addr:full":"Rua Corzas, 6 Mugardos La Coru\u00f1a 15620",
    "addr:housenumber":"6",
    "addr:postcode":"15620",
    "addr:street":"Rua Corzas;La Corun\u0303A",
    "iso:country":"ES",
    "sg:address":"Rua Corzas, 6",
    "sg:city":"Mugardos",
    "sg:orig_category":"Asesor\u00cda De Formaci\u00d3n Y Gesti\u00d3n De Personal",
    "sg:phone":"+34 981 47 01 82",
    "sg:postcode":"15620",
    "sg:province":"La Coru\u00f1a",
    "wof:name":"Asesoria Socime S.c.",
    "wof:placetype":"venue"
},
  "geometry": {"coordinates":[-8.2537755966,43.4594116211],"type":"Point"}
}