{
  "type": "Feature",
  "properties": {
    "addr:full":"Calle de Tomas Borras, 8 Madrid Madrid 28045",
    "addr:housenumber":"8",
    "addr:postcode":"madrid;28045",
    "addr:street":"Calle De Tomas Borras",
    "iso:country":"ES",
    "sg:address":"Calle de Tomas Borras, 8",
    "sg:city":"Madrid",
    "sg:orig_category":"Farmacias",
    "sg:phone":"+34 914 73 76 89",
    "sg:postcode":"28045",
    "sg:province":"Madrid",
    "wof:name":"Pe\u00f1a Manjon Rafael",
    "wof:placetype":"venue"
},
  "geometry": {"coordinates":[-3.6971969604,40.3954658508],"type":"Point"}
}