{
  "type": "Feature",
  "properties": {
    "iso:country":"ES",
    "sg:address":"Carr Sant Joan Baptista La Salle, 6",
    "sg:city":"Palamos",
    "sg:orig_category":"Platos Preparados Refrigerados (fabricaci\u00d3n, Al Por Mayor)",
    "sg:phone":"+34 972 60 06 52",
    "sg:postcode":"17230",
    "sg:province":"Girona",
    "wof:name":"Can Vidal S.l.l.",
    "wof:placetype":"venue"
},
  "geometry": {"coordinates":[3.1313710213,41.8486366272],"type":"Point"}
}