{
  "type": "Feature",
  "properties": {
    "iso:country":"ES",
    "sg:address":"Rbla Passeig, 45",
    "sg:city":"Vic",
    "sg:orig_category":"Bisuter\u00cda, Joyer\u00cda, Relojer\u00cda (al Por Menor)",
    "sg:phone":"+34 938 89 14 84",
    "sg:postcode":"08500",
    "sg:province":"Barcelona",
    "wof:name":"Subi D'or Sccl",
    "wof:placetype":"venue"
},
  "geometry": {"coordinates":[2.2573120594,41.9301185608],"type":"Point"}
}