{
  "type": "Feature",
  "properties": {
    "iso:country":"ES",
    "sg:address":"Calle de Guadalete, 2",
    "sg:city":"Valladolid",
    "sg:orig_category":"Asociaciones, Organismos Culturales Y Socioeducativos",
    "sg:phone":"+34 983 29 69 41",
    "sg:postcode":"47005",
    "sg:province":"Valladolid",
    "wof:name":"Asociacion Juvenil Ecam",
    "wof:placetype":"venue"
},
  "geometry": {"coordinates":[-4.712272644,41.6543045044],"type":"Point"}
}