{
  "type": "Feature",
  "properties": {
    "iso:country":"ES",
    "sg:address":"Pase Habana, 14",
    "sg:city":"Madrid",
    "sg:orig_category":"Asesor\u00cda De Comercio Exterior",
    "sg:phone":"+34 917 45 01 21",
    "sg:postcode":"28036",
    "sg:province":"Madrid",
    "wof:name":"Global Trade & Investment S.a.",
    "wof:placetype":"venue"
},
  "geometry": {"coordinates":[-3.6897149086,40.4480400085],"type":"Point"}
}