{
  "type": "Feature",
  "properties": {
    "addr:full":"Zona Autovia Castelldefels, Km. 0008,6 Prat Llobregat Barcelona 08820",
    "addr:postcode":"08820",
    "addr:street":"Autovia Castelldefels Km. 0008,6",
    "iso:country":"ES",
    "sg:address":"Zona Autovia Castelldefels, Km. 0008,6",
    "sg:city":"Prat Llobregat",
    "sg:orig_category":"Materiales De Aislamiento T\u00c9rmico Y Ac\u00dastico",
    "sg:phone":"+34 934 74 47 47",
    "sg:postcode":"08820",
    "sg:province":"Barcelona",
    "sg:website":"www.idaglas.com",
    "wof:name":"Idaglas S.l.",
    "wof:placetype":"venue"
},
  "geometry": {"coordinates":[2.0864720345,41.3289909363],"type":"Point"}
}