{
  "type": "Feature",
  "properties": {
    "iso:country":"ES",
    "sg:address":"Calle de Virgen Del Rosario, S/n",
    "sg:city":"Ayora",
    "sg:orig_category":"Pintores",
    "sg:phone":"+34 962 19 14 69",
    "sg:postcode":"46620",
    "sg:province":"Valencia",
    "wof:name":"Camara Gozalvez Pedro",
    "wof:placetype":"venue"
},
  "geometry": {"coordinates":[-1.0537240505,39.0609741211],"type":"Point"}
}