{
  "type": "Feature",
  "properties": {
    "iso:country":"ES",
    "sg:address":"Plaz Siete Villas (de Las), 13",
    "sg:city":"Pedroche",
    "sg:orig_category":"Cajas De Ahorro",
    "sg:phone":"+34 957 13 70 32",
    "sg:postcode":"14412",
    "sg:province":"C\u00f3rdoba",
    "wof:name":"Caja De Ahorros Y Monte De Piedad De Cordoba",
    "wof:placetype":"venue"
},
  "geometry": {"coordinates":[-4.7630019188,38.4286766052],"type":"Point"}
}