{
  "type": "Feature",
  "properties": {
    "addr:full":"Carrer de Unio (de La), 4 Tarragona Tarragona 43001",
    "addr:housenumber":"4",
    "addr:postcode":"43001",
    "addr:street":"Carrer De Unio De La",
    "iso:country":"ES",
    "sg:address":"Carrer de Unio (de La), 4",
    "sg:city":"Tarragona",
    "sg:orig_category":"Zapatos (al Por Menor)",
    "sg:phone":"+34 977 24 27 03",
    "sg:postcode":"43001",
    "sg:province":"Tarragona",
    "wof:name":"Sacha S.c.p.",
    "wof:placetype":"venue"
},
  "geometry": {"coordinates":[1.2524980307,41.1152534485],"type":"Point"}
}