{
  "type": "Feature",
  "properties": {
    "addr:full":"Calle de Agua (el), 6 Lucena C\u00f3rdoba 14900",
    "addr:housenumber":"6",
    "addr:postcode":"14900",
    "addr:street":"Calle De Agua El",
    "iso:country":"ES",
    "sg:address":"Calle de Agua (el), 6",
    "sg:city":"Lucena",
    "sg:orig_category":"M\u00c9dicos: Evaluaci\u00d3n Y Tratamiento Del Dolor",
    "sg:phone":"+34 957 59 18 57",
    "sg:postcode":"14900",
    "sg:province":"C\u00f3rdoba",
    "wof:name":"Dental Lucena S.c.",
    "wof:placetype":"venue"
},
  "geometry": {"coordinates":[-4.4875788689,37.4084739685],"type":"Point"}
}