{
  "type": "Feature",
  "properties": {
    "addr:full":"Jose M.arizmendiarrieta, 2 Arrasate Guip\u00f9zcoa 20500",
    "addr:housenumber":"2",
    "addr:postcode":"20500",
    "addr:street":"Jose M.Arizmendiarrieta;Guipu\u0300Zcoa",
    "iso:country":"ES",
    "sg:address":"Jose M.arizmendiarrieta, 2",
    "sg:city":"Arrasate",
    "sg:orig_category":"Servicios De Telecomunicaciones",
    "sg:phone":"+34 943 71 10 20",
    "sg:postcode":"20500",
    "sg:province":"Guip\u00f9zcoa",
    "wof:name":"Euronet Spain S.a.",
    "wof:placetype":"venue"
},
  "geometry": {"coordinates":[-2.4945991039,43.060295105],"type":"Point"}
}