{
  "type": "Feature",
  "properties": {
    "addr:full":"Rua Urzaiz, 192 Vigo Pontevedra 36205",
    "addr:housenumber":"192",
    "addr:postcode":"36205",
    "addr:street":"Rua Urzaiz",
    "iso:country":"ES",
    "sg:address":"Rua Urzaiz, 192",
    "sg:city":"Vigo",
    "sg:orig_category":"Frutas Y Legumbres Frescas (al Por Mayor)",
    "sg:phone":"+34 986 27 41 62",
    "sg:postcode":"36205",
    "sg:province":"Pontevedra",
    "wof:name":"Frutas Katusa S.l.",
    "wof:placetype":"venue"
},
  "geometry": {"coordinates":[-8.7016067505,42.2308654785],"type":"Point"}
}