{
  "type": "Feature",
  "properties": {
    "addr:full":"Ctra. Toledo-avila, Km. 0151,5 Carpio Tajo Toledo 45533",
    "addr:postcode":"45533",
    "addr:street":"Ctra. Toledo-Avila Km. 0151,5",
    "iso:country":"ES",
    "sg:address":"Ctra. Toledo-avila, Km. 0151,5",
    "sg:city":"Carpio Tajo",
    "sg:orig_category":"Distribuci\u00d3n De Petr\u00d3leo Y Derivados",
    "sg:phone":"+34 925 75 75 93",
    "sg:postcode":"45533",
    "sg:province":"Toledo",
    "wof:name":"Farruco S.a.",
    "wof:placetype":"venue"
},
  "geometry": {"coordinates":[-4.4543619156,39.8877754211],"type":"Point"}
}