{
  "type": "Feature",
  "properties": {
    "addr:full":"Calle de Rosa De Los Vientos, 25 Malaga M\u00e1laga 29006",
    "addr:housenumber":"25",
    "addr:postcode":"29006",
    "addr:street":"Calle De Rosa De Los Vientos;Ma\u0301Laga",
    "iso:country":"ES",
    "sg:address":"Calle de Rosa De Los Vientos, 25",
    "sg:city":"Malaga",
    "sg:orig_category":"Mec\u00c1nico Del Autom\u00d3vil",
    "sg:phone":"+34 952 36 22 87",
    "sg:postcode":"29006",
    "sg:province":"M\u00e1laga",
    "wof:name":"Talleres Fervauto S.c.",
    "wof:placetype":"venue"
},
  "geometry": {"coordinates":[-4.4848031998,36.7096710205],"type":"Point"}
}