{
  "type": "Feature",
  "properties": {
    "iso:country":"ES",
    "sg:address":"Avda General Mola, 3",
    "sg:city":"Pozuelo De Alarcon",
    "sg:orig_category":"Arreglo, Reparaci\u00d3n, Piezas Sueltas De Televisi\u00d3n, V\u00cddeo, Hi",
    "sg:phone":"+34 917 15 83 34",
    "sg:postcode":"28224",
    "sg:province":"Madrid",
    "wof:name":"Pozuelo Cama\u00f1o Jose Luis",
    "wof:placetype":"venue"
},
  "geometry": {"coordinates":[-3.7978990078,40.4500999451],"type":"Point"}
}