{
  "type": "Feature",
  "properties": {
    "addr:full":"Cmno Vallalope, S/n Arnedo La Rioja 26580",
    "addr:housenumber":"s / n",
    "addr:postcode":"26580",
    "addr:street":"Cmno Vallalope;Rioja",
    "iso:country":"ES",
    "sg:address":"Cmno Vallalope, S/n",
    "sg:city":"Arnedo",
    "sg:orig_category":"Cr\u00cda De Bovinos",
    "sg:phone":"+34 941 38 34 65",
    "sg:postcode":"26580",
    "sg:province":"La Rioja",
    "wof:name":"Hermanos Gil De Gomez A.c.",
    "wof:placetype":"venue"
},
  "geometry": {"coordinates":[-2.0760250092,42.2255249023],"type":"Point"}
}