{
  "type": "Feature",
  "properties": {
    "iso:country":"ES",
    "sg:address":"Calle de Rio Guadalquivir, 7",
    "sg:city":"Atalayuela",
    "sg:orig_category":"Ropa Para Ni\u00d1os (al Por Menor)",
    "sg:phone":"+34 916 21 20 63",
    "sg:postcode":"28906",
    "sg:province":"Madrid",
    "wof:name":"Vecopri Espa\u00d1a S.l.",
    "wof:placetype":"venue"
},
  "geometry": {"coordinates":[-3.7021615505,40.2710952759],"type":"Point"}
}