{
  "type": "Feature",
  "properties": {
    "iso:country":"ES",
    "sg:address":"Calle de Picasso, 4",
    "sg:city":"Oviedo",
    "sg:orig_category":"Costureras",
    "sg:phone":"+34 985 29 95 52",
    "sg:postcode":"33001",
    "sg:province":"Asturias",
    "wof:name":"Herrera Pereiro Encarnacion",
    "wof:placetype":"venue"
},
  "geometry": {"coordinates":[-5.8460469246,43.3671722412],"type":"Point"}
}