{
  "type": "Feature",
  "properties": {
    "iso:country":"ES",
    "sg:address":"Calle de Francisco De Goya (de), 48",
    "sg:city":"Mejorada Campo",
    "sg:orig_category":"Fabricaci\u00d3n, Venta, Instalaci\u00d3n De R\u00d3tulos, De R\u00d3tulos Luminosos",
    "sg:phone":"+34 916 68 09 21",
    "sg:postcode":"28840",
    "sg:province":"Madrid",
    "wof:name":"Ruiz Ca\u00f1ada Francisco",
    "wof:placetype":"venue"
},
  "geometry": {"coordinates":[-3.4816958904,40.3919143677],"type":"Point"}
}