{
  "type": "Feature",
  "properties": {
    "addr:full":"Rbla Egara, 235 Terrassa Barcelona 08224",
    "addr:housenumber":"235",
    "addr:postcode":"08224",
    "addr:street":"Rbla Egara",
    "iso:country":"ES",
    "sg:address":"Rbla Egara, 235",
    "sg:city":"Terrassa",
    "sg:orig_category":"Cajas De Ahorro",
    "sg:phone":"+34 937 33 70 55",
    "sg:postcode":"08224",
    "sg:province":"Barcelona",
    "wof:name":"Caixa D'estalvis Laietana",
    "wof:placetype":"venue"
},
  "geometry": {"coordinates":[2.0076899529,41.5638694763],"type":"Point"}
}