{
  "type": "Feature",
  "properties": {
    "addr:full":"Avda Plaza De Toros, 12 Madrid Madrid 28025",
    "addr:housenumber":"12",
    "addr:postcode":"madrid;28025",
    "addr:street":"Avda Plaza De Toros",
    "iso:country":"ES",
    "sg:address":"Avda Plaza De Toros, 12",
    "sg:city":"Madrid",
    "sg:orig_category":"Cajas De Ahorro",
    "sg:phone":"+34 914 22 07 40",
    "sg:postcode":"28025",
    "sg:province":"Madrid",
    "sg:website":"www.cajaespana.es",
    "wof:name":"Caja Espa\u00f1a De Inversiones Caja De Ahorros Y Monte De Piedad",
    "wof:placetype":"venue"
},
  "geometry": {"coordinates":[-3.7399590015,40.3859291077],"type":"Point"}
}