{
  "type": "Feature",
  "properties": {
    "addr:full":"Plaz San Pedro De Alcantara, 4 Plasencia C\u00e1ceres 10600",
    "addr:housenumber":"4",
    "addr:postcode":"10600",
    "addr:street":"Plaz;Alcantara;Ca\u0301Ceres",
    "iso:country":"ES",
    "sg:address":"Plaz San Pedro De Alcantara, 4",
    "sg:city":"Plasencia",
    "sg:orig_category":"Electrodom\u00c9sticos (fabricaci\u00d3n, Al Por Mayor)",
    "sg:phone":"+34 927 42 63 94",
    "sg:postcode":"10600",
    "sg:province":"C\u00e1ceres",
    "wof:name":"Hermon Materiales Electricos Y Proyectos S.l.",
    "wof:placetype":"venue"
},
  "geometry": {"coordinates":[-6.0861949921,40.0310173035],"type":"Point"}
}