{
  "type": "Feature",
  "properties": {
    "iso:country":"ES",
    "sg:address":"Carrer de Ramon Llull, S/n",
    "sg:city":"Molins Rei",
    "sg:orig_category":"Comercio De Piezas De Recambio Y De Accesorios De Veh\u00cdculos, Veh\u00cdculos Industriales",
    "sg:phone":"+34 936 68 17 94",
    "sg:postcode":"08750",
    "sg:province":"Barcelona",
    "sg:website":"www.guilera.com",
    "wof:name":"Guilera S. A.",
    "wof:placetype":"venue"
},
  "geometry": {"coordinates":[2.0167839527,41.417339325],"type":"Point"}
}