{
  "type": "Feature",
  "properties": {
    "iso:country":"ES",
    "sg:address":"Calle de Inmaculada Concepcion, 5",
    "sg:city":"Puente-genil",
    "sg:orig_category":"Arquitectos",
    "sg:phone":"+34 957 60 16 55",
    "sg:postcode":"14500",
    "sg:province":"C\u00f3rdoba",
    "wof:name":"Aleman Marquez Rafael",
    "wof:placetype":"venue"
},
  "geometry": {"coordinates":[-4.7689418793,37.3913955688],"type":"Point"}
}