{
  "type": "Feature",
  "properties": {
    "addr:full":"Plaz Almudaina, 2 Cadiz C\u00e1diz 11008",
    "addr:housenumber":"2",
    "addr:postcode":"11008",
    "addr:street":"Plaz Almudaina",
    "iso:country":"ES",
    "sg:address":"Plaz Almudaina, 2",
    "sg:city":"Cadiz",
    "sg:orig_category":"Arquitectos",
    "sg:phone":"+34 956 27 47 84",
    "sg:postcode":"11008",
    "sg:province":"C\u00e1diz",
    "wof:name":"Cortes Lizcano Mariano",
    "wof:placetype":"venue"
},
  "geometry": {"coordinates":[-6.2857551575,36.5197753906],"type":"Point"}
}