{
  "type": "Feature",
  "properties": {
    "iso:country":"ES",
    "sg:address":"Rua Victor Velasco, 3",
    "sg:city":"Carral",
    "sg:orig_category":"Molduras, Junquillos, Listones Y Molduras Perforadas",
    "sg:phone":"+34 981 67 05 46",
    "sg:postcode":"15175",
    "sg:province":"La Coru\u00f1a",
    "wof:name":"Orgeira Garcia Manuel",
    "wof:placetype":"venue"
},
  "geometry": {"coordinates":[-8.3565835953,43.2287826538],"type":"Point"}
}