{
  "type": "Feature",
  "properties": {
    "addr:full":"De La Corte, 8 Montanchez C\u00e1ceres 10170",
    "addr:postcode":"10170",
    "addr:street":"Ca\u0301Ceres",
    "iso:country":"ES",
    "sg:address":"De La Corte, 8",
    "sg:city":"Montanchez",
    "sg:orig_category":"Asesor\u00cda De Formaci\u00d3n Y Gesti\u00d3n De Personal",
    "sg:phone":"+34 927 38 04 15",
    "sg:postcode":"10170",
    "sg:province":"C\u00e1ceres",
    "wof:name":"Gefisvae S.a.",
    "wof:placetype":"venue"
},
  "geometry": {"coordinates":[-6.1525287628,39.2250938416],"type":"Point"}
}