{
  "type": "Feature",
  "properties": {
    "addr:full":"Calle de Juan De Oca\u00d1a, 4 Mostoles Madrid 28931",
    "addr:housenumber":"4",
    "addr:postcode":"28931",
    "addr:street":"Calle De Juan De Ocan\u0303A",
    "iso:country":"ES",
    "sg:address":"Calle de Juan De Oca\u00d1a, 4",
    "sg:city":"Mostoles",
    "sg:orig_category":"Cerrajer\u00cda, Ferrallista",
    "sg:phone":"+34 916 13 12 18",
    "sg:postcode":"28931",
    "sg:province":"Madrid",
    "wof:name":"El Herrero De 1808 S.l.",
    "wof:placetype":"venue"
},
  "geometry": {"coordinates":[-3.8672869205,40.3235282898],"type":"Point"}
}