{
  "type": "Feature",
  "properties": {
    "iso:country":"ES",
    "sg:address":"Carrer de Comte D'urgell, 143",
    "sg:city":"Barcelona",
    "sg:classifiers":[
        {
            "category":"Manufacturing",
            "subcategory":"Building Materials",
            "type":"Manufacturing & Wholesale Goods"
        }
    ],
    "sg:phone":"+34 933 22 56 11",
    "sg:postcode":"08036",
    "sg:province":"Barcelona",
    "sg:tags":[
        "cemento",
        "y",
        "de",
        "fabricaci\u00d3n",
        "cal"
    ],
    "sg:website":"ww.rodio.com",
    "wof:name":"Rodio Cimentaciones Especiales S.a.",
    "wof:placetype":"venue"
},
  "geometry": {"coordinates":[2.1524071693,41.3867874146],"type":"Point"}
}