{
  "type": "Feature",
  "properties": {
    "addr:full":"Carrer de Pujol, 13 Barcelona Barcelona 08022",
    "addr:housenumber":"13",
    "addr:postcode":"08022",
    "addr:street":"Carrer De Pujol",
    "iso:country":"ES",
    "sg:address":"Carrer de Pujol, 13",
    "sg:city":"Barcelona",
    "sg:orig_category":"Arquitectos",
    "sg:phone":"+34 934 18 92 84",
    "sg:postcode":"08022",
    "sg:province":"Barcelona",
    "wof:name":"Batalla Olive Marcel",
    "wof:placetype":"venue"
},
  "geometry": {"coordinates":[2.1364569664,41.4047698975],"type":"Point"}
}