{
  "type": "Feature",
  "properties": {
    "addr:full":"Torrenova, 46 Palmanova Islas Baleares 07181",
    "addr:housenumber":"46",
    "addr:postcode":"07181",
    "addr:street":"Torrenova",
    "iso:country":"ES",
    "sg:address":"Torrenova, 46",
    "sg:city":"Palmanova",
    "sg:orig_category":"Molduras, Junquillos, Listones Y Molduras Perforadas",
    "sg:phone":"+34 971 68 04 28",
    "sg:postcode":"07181",
    "sg:province":"Islas Baleares",
    "wof:name":"Bristol Ii C.b.",
    "wof:placetype":"venue"
},
  "geometry": {"coordinates":[2.5352098942,39.5245780945],"type":"Point"}
}