{
  "type": "Feature",
  "properties": {
    "addr:full":"Las Caba\u00f1as, S/n Nore\u00f1a Asturias 33180",
    "addr:postcode":"33180",
    "addr:street":"Caban\u0303As S / N Noren\u0303A Asturias",
    "iso:country":"ES",
    "sg:address":"Las Caba\u00f1as, S/n",
    "sg:city":"Nore\u00f1a",
    "sg:orig_category":"Fabricaci\u00d3n, Venta De Cuadros, Accesorios Para Enmarcar",
    "sg:phone":"+34 985 74 03 16",
    "sg:postcode":"33180",
    "sg:province":"Asturias",
    "wof:name":"Almacenes Lelo S.l.",
    "wof:placetype":"venue"
},
  "geometry": {"coordinates":[-5.7055926323,43.400226593],"type":"Point"}
}