{
  "type": "Feature",
  "properties": {
    "iso:country":"ES",
    "sg:address":"Av Rei En Jaume, 20",
    "sg:city":"Cardedeu",
    "sg:orig_category":"Comerciantes Al Por Mayor De Vinos, Licores Y Alcoholes",
    "sg:phone":"+34 938 41 80 05",
    "sg:postcode":"08440",
    "sg:province":"Barcelona",
    "wof:name":"El Celler Del Bon Vi S.l.",
    "wof:placetype":"venue"
},
  "geometry": {"coordinates":[2.3571989536,41.6368026733],"type":"Point"}
}