{
  "type": "Feature",
  "properties": {
    "iso:country":"ES",
    "sg:address":"Calle de Meson (el), 29",
    "sg:city":"Villalobon",
    "sg:orig_category":"M\u00c1quinas De Jardiner\u00cda",
    "sg:phone":"+34 979 76 50 10",
    "sg:postcode":"34191",
    "sg:province":"Palencia",
    "wof:name":"Casa De Campo Palencia S.l.",
    "wof:placetype":"venue"
},
  "geometry": {"coordinates":[-4.7797989845,41.9148826599],"type":"Point"}
}