{
  "type": "Feature",
  "properties": {
    "iso:country":"ES",
    "sg:address":"Galileo (z. Ind Cami Ral), 12",
    "sg:city":"Gava",
    "sg:orig_category":"Transportes Por Carretera: Lotes Completos, Mercanc\u00cdas Diversas",
    "sg:phone":"+34 936 62 96 83",
    "sg:postcode":"08850",
    "sg:province":"Barcelona",
    "wof:name":"Hispana 98 S.l.",
    "wof:placetype":"venue"
},
  "geometry": {"coordinates":[1.9930466413,41.298789978],"type":"Point"}
}