{
  "type": "Feature",
  "properties": {
    "iso:country":"ES",
    "sg:address":"Plaz Real, Del, 1",
    "sg:city":"Castellon",
    "sg:orig_category":"Art\u00cdculos De Regalo (al Por Menor)",
    "sg:phone":"+34 964 24 14 00",
    "sg:postcode":"12001",
    "sg:province":"Castell\u00f3n",
    "wof:name":"Regalo Y Complementos S.a.",
    "wof:placetype":"venue"
},
  "geometry": {"coordinates":[-0.0390199982,39.9866409302],"type":"Point"}
}