{
  "type": "Feature",
  "properties": {
    "addr:full":"Av Catalunya, 3 Vendrell Tarragona 43700",
    "addr:housenumber":"3",
    "addr:postcode":"43700",
    "addr:street":"Av Catalunya",
    "iso:country":"ES",
    "sg:address":"Av Catalunya, 3",
    "sg:city":"Vendrell",
    "sg:orig_category":"Tapicer\u00cdas",
    "sg:phone":"+34 977 66 06 40",
    "sg:postcode":"43700",
    "sg:province":"Tarragona",
    "wof:name":"Cordero Fernandez David",
    "wof:placetype":"venue"
},
  "geometry": {"coordinates":[1.5320429802,41.219909668],"type":"Point"}
}