{
  "type": "Feature",
  "properties": {
    "addr:full":"Av Catalunya, S/n Cervia Ter Girona 17464",
    "addr:housenumber":"s / n",
    "addr:postcode":"17464",
    "addr:street":"Av Catalunya;Ter",
    "iso:country":"ES",
    "sg:address":"Av Catalunya, S/n",
    "sg:city":"Cervia Ter",
    "sg:orig_category":"Fabricaci\u00d3n, Venta De Productos Base Farmac\u00c9uticos",
    "sg:phone":"+34 972 49 60 14",
    "sg:postcode":"17464",
    "sg:province":"Girona",
    "wof:name":"Isern Finazzi Maria Angels",
    "wof:placetype":"venue"
},
  "geometry": {"coordinates":[2.9044299126,42.0652885437],"type":"Point"}
}