{
  "type": "Feature",
  "properties": {
    "addr:full":"Rua Areal, 78 Vigo Pontevedra 36201",
    "addr:housenumber":"78",
    "addr:postcode":"36201",
    "addr:street":"Rua Areal",
    "iso:country":"ES",
    "sg:address":"Rua Areal, 78",
    "sg:city":"Vigo",
    "sg:orig_category":"Modelistas",
    "sg:phone":"+34 986 22 78 93",
    "sg:postcode":"36201",
    "sg:province":"Pontevedra",
    "wof:name":"Rodriguez Perez Francisco",
    "wof:placetype":"venue"
},
  "geometry": {"coordinates":[-8.714556694,42.238735199],"type":"Point"}
}