{
  "type": "Feature",
  "properties": {
    "addr:full":"Carrer de Manacor, 160 Palma Islas Baleares 07007",
    "addr:housenumber":"160",
    "addr:postcode":"07007",
    "addr:street":"Carrer De Manacor",
    "iso:country":"ES",
    "sg:address":"Carrer de Manacor, 160",
    "sg:city":"Palma",
    "sg:orig_category":"Muebles, Minoristas",
    "sg:phone":"+34 971 25 64 53",
    "sg:postcode":"07007",
    "sg:province":"Islas Baleares",
    "sg:website":"www.moblerone.com",
    "wof:name":"Muebles Mallorca S.l.",
    "wof:placetype":"venue"
},
  "geometry": {"coordinates":[2.6716499329,39.5712585449],"type":"Point"}
}