{
  "type": "Feature",
  "properties": {
    "iso:country":"ES",
    "sg:address":"Rua Travesia De Vigo, 4",
    "sg:city":"Roris",
    "sg:orig_category":"Cl\u00cdnicas Dentales",
    "sg:phone":"+34 986 26 03 09",
    "sg:postcode":"36206",
    "sg:province":"Pontevedra",
    "wof:name":"A3 Vigodental S.l.",
    "wof:placetype":"venue"
},
  "geometry": {"coordinates":[-7.146372,42.385574],"type":"Point"}
}