{
  "type": "Feature",
  "properties": {
    "iso:country":"ES",
    "sg:address":"La Fuente, 75",
    "sg:city":"Torredonjimeno",
    "sg:orig_category":"Ebanister\u00cda",
    "sg:phone":"+34 953 57 26 91",
    "sg:postcode":"23650",
    "sg:province":"Ja\u00e9n",
    "wof:name":"Ure\u00f1a Damas Jose Felipe",
    "wof:placetype":"venue"
},
  "geometry": {"coordinates":[-3.9544389248,37.7630805969],"type":"Point"}
}