{
  "type": "Feature",
  "properties": {
    "iso:country":"ES",
    "sg:address":"Santuiturri Plaza, 8",
    "sg:city":"Zarautz",
    "sg:orig_category":"Tapicer\u00cdas",
    "sg:phone":"+34 943 83 25 73",
    "sg:postcode":"20800",
    "sg:province":"Guip\u00f9zcoa",
    "wof:name":"Isaac Alonso Regidor",
    "wof:placetype":"venue"
},
  "geometry": {"coordinates":[-2.1662490368,43.2798500061],"type":"Point"}
}