{
  "type": "Feature",
  "properties": {
    "iso:country":"ES",
    "sg:address":"Ctra Villaselan, 1",
    "sg:city":"Ribadeo",
    "sg:orig_category":"Asilos De Ancianos. Centros Privados",
    "sg:phone":"+34 982 12 00 75",
    "sg:postcode":"27700",
    "sg:province":"Lugo",
    "wof:name":"Grupo Gonzalez De La Gusta S.l.",
    "wof:placetype":"venue"
},
  "geometry": {"coordinates":[-7.042096138,43.539440155],"type":"Point"}
}