{
  "type": "Feature",
  "properties": {
    "iso:country":"ES",
    "sg:address":"Calle de Colon, 12",
    "sg:city":"Caceres",
    "sg:orig_category":"Venta, Alquiler De Instrumentos Y Accesorios De M\u00dasica",
    "sg:phone":"+34 927 22 61 69",
    "sg:postcode":"10004",
    "sg:province":"C\u00e1ceres",
    "sg:website":"www.musicalbarragan.com",
    "wof:name":"Barragan Martinez Francisco",
    "wof:placetype":"venue"
},
  "geometry": {"coordinates":[-6.3735160828,39.4697189331],"type":"Point"}
}