{
  "type": "Feature",
  "properties": {
    "iso:country":"ES",
    "sg:address":"C/ Musics Perez Monllor, 6",
    "sg:city":"Alcoi",
    "sg:orig_category":"Empresas De Carpinter\u00cda",
    "sg:phone":"+34 965 54 68 76",
    "sg:postcode":"03801",
    "sg:province":"Alicante",
    "wof:name":"Canales Martinez Manuel",
    "wof:placetype":"venue"
},
  "geometry": {"coordinates":[-0.4749900103,38.6914024353],"type":"Point"}
}