{
  "type": "Feature",
  "properties": {
    "addr:full":"Urb Gransol, S/n Rincon Victoria M\u00e1laga 29730",
    "addr:housenumber":"s / n",
    "addr:postcode":"29730",
    "addr:street":"Urb Gransol;Ma\u0301Laga",
    "iso:country":"ES",
    "sg:address":"Urb Gransol, S/n",
    "sg:city":"Rincon Victoria",
    "sg:orig_category":"Muebles, Minoristas",
    "sg:phone":"+34 952 40 14 14",
    "sg:postcode":"29730",
    "sg:province":"M\u00e1laga",
    "wof:name":"Muebles Alba Navarrete S.l.",
    "wof:placetype":"venue"
},
  "geometry": {"coordinates":[-4.2807641029,36.714641571],"type":"Point"}
}