{
  "type": "Feature",
  "properties": {
    "iso:country":"ES",
    "sg:address":"Ctra Cadiz Carretera A, Km. 0108,0",
    "sg:city":"Algeciras",
    "sg:orig_category":"Equipo De Refrigeraci\u00d3n Industrial",
    "sg:phone":"+34 956 65 48 87",
    "sg:postcode":"11206",
    "sg:province":"C\u00e1diz",
    "sg:website":"www.campoglass.com",
    "wof:name":"Campoglass S.l.",
    "wof:placetype":"venue"
},
  "geometry": {"coordinates":[-5.5359191895,36.1193008423],"type":"Point"}
}