{
  "type": "Feature",
  "properties": {
    "addr:full":"Avda Arlanzon, 9 Burgos Burgos 09004",
    "addr:housenumber":"9",
    "addr:postcode":"09004",
    "addr:street":"Avda Arlanzon",
    "iso:country":"ES",
    "sg:address":"Avda Arlanzon, 9",
    "sg:city":"Burgos",
    "sg:orig_category":"Cl\u00cdnicas Dentales",
    "sg:phone":"+34 947 20 68 82",
    "sg:postcode":"09004",
    "sg:province":"Burgos",
    "wof:name":"Clinica Dental Elena Arnaiz S.l.",
    "wof:placetype":"venue"
},
  "geometry": {"coordinates":[-3.6964199543,42.3411636353],"type":"Point"}
}