{
  "type": "Feature",
  "properties": {
    "addr:full":"Ctra Sentmenat, Km. 0001,8 Poligono Barcelona 08213",
    "addr:postcode":"08213",
    "addr:street":"Ctra Sentmenat Km. 0001,8 Poligono Barcelona",
    "iso:country":"ES",
    "sg:address":"Ctra Sentmenat, Km. 0001,8",
    "sg:city":"Poligono",
    "sg:orig_category":"Carros Elevadores, Carros De Operaciones Portuarias",
    "sg:phone":"+34 937 13 24 64",
    "sg:postcode":"08213",
    "sg:province":"Barcelona",
    "wof:name":"Elecar Carretillas Elevadoras S.l.",
    "wof:placetype":"venue"
},
  "geometry": {"coordinates":[2.1571440697,41.5534934998],"type":"Point"}
}