{
  "type": "Feature",
  "properties": {
    "addr:full":"Carr Maria Auxiliadora, 3 Ciutadella Menorca Islas Baleares 07760",
    "addr:housenumber":"3",
    "addr:postcode":"07760",
    "addr:street":"Carr Maria Auxiliadora",
    "iso:country":"ES",
    "sg:address":"Carr Maria Auxiliadora, 3",
    "sg:city":"Ciutadella Menorca",
    "sg:orig_category":"Electricidad: Instaladores",
    "sg:phone":"+34 971 38 11 98",
    "sg:postcode":"07760",
    "sg:province":"Islas Baleares",
    "wof:name":"Faner Bagur Antonia",
    "wof:placetype":"venue"
},
  "geometry": {"coordinates":[3.8395550251,40.0039558411],"type":"Point"}
}