{
  "type": "Feature",
  "properties": {
    "iso:country":"ES",
    "sg:address":"C/ Victoria Kent, 7",
    "sg:city":"Elche",
    "sg:orig_category":"M\u00c9dicos: Cirug\u00cda Maxilofacial",
    "sg:phone":"+34 965 44 05 47",
    "sg:postcode":"03206",
    "sg:province":"Alicante",
    "wof:name":"Romero Perez Jose",
    "wof:placetype":"venue"
},
  "geometry": {"coordinates":[-0.7036340237,38.275718689],"type":"Point"}
}