{
  "type": "Feature",
  "properties": {
    "addr:full":"Calle de Santiago, 20 Valladolid Valladolid 47001",
    "addr:housenumber":"20",
    "addr:postcode":"47001",
    "addr:street":"Calle De Santiago",
    "iso:country":"ES",
    "sg:address":"Calle de Santiago, 20",
    "sg:city":"Valladolid",
    "sg:orig_category":"Ropa Para Se\u00d1oras (al Por Menor)",
    "sg:phone":"+34 983 35 28 53",
    "sg:postcode":"47001",
    "sg:province":"Valladolid",
    "wof:name":"Cuesta Gutierrez Irene De La",
    "wof:placetype":"venue"
},
  "geometry": {"coordinates":[-4.7291789055,41.6496047974],"type":"Point"}
}