{
  "type": "Feature",
  "properties": {
    "addr:full":"Ctra. Riaza, Km. 0001,0 Cuellar Segovia 40200",
    "addr:postcode":"40200",
    "addr:street":"Ctra. Riaza Km. 0001,0;Segovia",
    "iso:country":"ES",
    "sg:address":"Ctra. Riaza, Km. 0001,0",
    "sg:city":"Cuellar",
    "sg:orig_category":"Empresas De Hormig\u00d3n, Hormig\u00d3n Armado Y Pretensado",
    "sg:phone":"+34 921 14 30 10",
    "sg:postcode":"40200",
    "sg:province":"Segovia",
    "wof:name":"Forsan S.a.",
    "wof:placetype":"venue"
},
  "geometry": {"coordinates":[-4.3119688034,41.4013137817],"type":"Point"}
}