{
  "type": "Feature",
  "properties": {
    "iso:country":"ES",
    "sg:address":"Calle de Francisco Cantera, 17",
    "sg:city":"Miranda Ebro",
    "sg:orig_category":"Agentes Generales De Seguros",
    "sg:phone":"+34 947 33 13 91",
    "sg:postcode":"09200",
    "sg:province":"Burgos",
    "wof:name":"Angulo Montoya Maria Teresa",
    "wof:placetype":"venue"
},
  "geometry": {"coordinates":[-2.9439337254,42.6845779419],"type":"Point"}
}