{
  "type": "Feature",
  "properties": {
    "iso:country":"ES",
    "sg:address":"Carrer de Sastre, 2",
    "sg:city":"Granollers",
    "sg:orig_category":"Materias Pl\u00c1sticas: Art\u00cdculos Para La Industria",
    "sg:phone":"+34 938 70 65 96",
    "sg:postcode":"08401",
    "sg:province":"Barcelona",
    "wof:name":"Albert Arimany Eduardo",
    "wof:placetype":"venue"
},
  "geometry": {"coordinates":[2.2880270481,41.6083908081],"type":"Point"}
}