{
  "type": "Feature",
  "properties": {
    "iso:country":"ES",
    "sg:address":"Calle de Leoncio Bautista, 1",
    "sg:city":"Madrid",
    "sg:orig_category":"Electricidad: Instaladores",
    "sg:phone":"+34 914 72 05 24",
    "sg:postcode":"28019",
    "sg:province":"Madrid",
    "wof:name":"M.b. S.l.",
    "wof:placetype":"venue"
},
  "geometry": {"coordinates":[-3.7320120335,40.3971176147],"type":"Point"}
}