{
  "type": "Feature",
  "properties": {
    "addr:full":"Carrer de L'escorial, 180 Barcelona Barcelona 08024",
    "addr:housenumber":"180",
    "addr:postcode":"08024",
    "addr:street":"Carrer De L'Escorial",
    "iso:country":"ES",
    "sg:address":"Carrer de L'escorial, 180",
    "sg:city":"Barcelona",
    "sg:orig_category":"Empresas De Vigilancia, Guardia Y Protecci\u00d3n",
    "sg:phone":"+34 932 19 61 12",
    "sg:postcode":"08024",
    "sg:province":"Barcelona",
    "wof:name":"Valldeperas Burrel Santiago",
    "wof:placetype":"venue"
},
  "geometry": {"coordinates":[2.1580109596,41.4108047485],"type":"Point"}
}