{
  "type": "Feature",
  "properties": {
    "addr:full":"Calle de Doctor Fleming, 35 Bormujos Sevilla 41930",
    "addr:housenumber":"35",
    "addr:postcode":"41930",
    "addr:street":"Calle De Doctor Fleming",
    "iso:country":"ES",
    "sg:address":"Calle de Doctor Fleming, 35",
    "sg:city":"Bormujos",
    "sg:orig_category":"Escultores, Estatuarios E Imagineros",
    "sg:phone":"+34 954 78 98 31",
    "sg:postcode":"41930",
    "sg:province":"Sevilla",
    "wof:name":"Rodriguez  Mayra Edith",
    "wof:placetype":"venue"
},
  "geometry": {"coordinates":[-6.071665287,37.368598938],"type":"Point"}
}