{
  "type": "Feature",
  "properties": {
    "addr:full":"Carrer de Manila, 49 Barcelona Barcelona 08034",
    "addr:housenumber":"49",
    "addr:postcode":"08034",
    "addr:street":"Carrer De Manila",
    "iso:country":"ES",
    "sg:address":"Carrer de Manila, 49",
    "sg:city":"Barcelona",
    "sg:orig_category":"Cajas De Ahorro",
    "sg:phone":"+34 932 80 16 15",
    "sg:postcode":"08034",
    "sg:province":"Barcelona",
    "sg:website":"www.lacaixa.es",
    "wof:name":"Caixa D'estalvis I Pensions De Barcelona",
    "wof:placetype":"venue"
},
  "geometry": {"coordinates":[2.1256968975,41.3900337219],"type":"Point"}
}