{
  "type": "Feature",
  "properties": {
    "addr:full":"Bule Luciano Demetrio Herrero, 8 Torrelavega Cantabria 39300",
    "addr:housenumber":"8",
    "addr:postcode":"39300",
    "iso:country":"ES",
    "sg:address":"Bule Luciano Demetrio Herrero, 8",
    "sg:city":"Torrelavega",
    "sg:orig_category":"M\u00c9dicos: Oftalmolog\u00cda",
    "sg:phone":"+34 942 88 13 19",
    "sg:postcode":"39300",
    "sg:province":"Cantabria",
    "wof:name":"Herrero Fernandez-abascal Luciano",
    "wof:placetype":"venue"
},
  "geometry": {"coordinates":[-4.0504021645,43.3490753174],"type":"Point"}
}