{
  "type": "Feature",
  "properties": {
    "addr:full":"Calle de Mata Linares, 29 S. Vicente Barquera Cantabria 39540",
    "addr:housenumber":"29",
    "addr:postcode":"39540",
    "addr:street":"Calle De Mata Linares;S. Vicente",
    "iso:country":"ES",
    "sg:address":"Calle de Mata Linares, 29",
    "sg:city":"S. Vicente Barquera",
    "sg:orig_category":"Peluquer\u00cdas, Peluquer\u00cda Mixta",
    "sg:phone":"+34 942 71 15 16",
    "sg:postcode":"39540",
    "sg:province":"Cantabria",
    "wof:name":"Gomez Pinto Maria Cruz",
    "wof:placetype":"venue"
},
  "geometry": {"coordinates":[-4.3995471001,43.3842964172],"type":"Point"}
}