{
  "type": "Feature",
  "properties": {
    "addr:full":"Carrer de Clot, 173 Barcelona Barcelona 08027",
    "addr:housenumber":"173",
    "addr:postcode":"08027",
    "addr:street":"Carrer De Clot",
    "iso:country":"ES",
    "sg:address":"Carrer de Clot, 173",
    "sg:city":"Barcelona",
    "sg:orig_category":"Zapatos (al Por Menor)",
    "sg:phone":"+34 933 40 30 54",
    "sg:postcode":"08027",
    "sg:province":"Barcelona",
    "wof:name":"Barlet Calzados S. A.",
    "wof:placetype":"venue"
},
  "geometry": {"coordinates":[2.1902110577,41.4135513306],"type":"Point"}
}