{
  "type": "Feature",
  "properties": {
    "iso:country":"ES",
    "sg:address":"Carrer de Joan Miro (de), 4",
    "sg:city":"Riudoms",
    "sg:orig_category":"Centros De Coordinaci\u00d3n",
    "sg:phone":"+34 977 85 01 92",
    "sg:postcode":"43330",
    "sg:province":"Tarragona",
    "wof:name":"Papio Fontgivell Sonia",
    "wof:placetype":"venue"
},
  "geometry": {"coordinates":[1.0520999432,41.1417007446],"type":"Point"}
}