{
  "type": "Feature",
  "properties": {
    "addr:full":"Carr Isern, 1 Lleida Lleida 25001",
    "addr:housenumber":"1",
    "addr:postcode":"25001",
    "addr:street":"Carr Isern",
    "iso:country":"ES",
    "sg:address":"Carr Isern, 1",
    "sg:city":"Lleida",
    "sg:orig_category":"Energ\u00cda Solar Y Nuevas Energ\u00cdas (equipo, Estudios)",
    "sg:phone":"+34 973 21 12 68",
    "sg:postcode":"25001",
    "sg:province":"Lleida",
    "wof:name":"Insta%aciones I Manteniment Gomez I Morell S.l.",
    "wof:placetype":"venue"
},
  "geometry": {"coordinates":[0.6431379914,41.6003608704],"type":"Point"}
}