{
  "type": "Feature",
  "properties": {
    "iso:country":"ES",
    "sg:address":"Atseden Kalea, 3",
    "sg:city":"Hondarribia",
    "sg:orig_category":"Promotores Constructores",
    "sg:phone":"+34 943 64 40 23",
    "sg:postcode":"20280",
    "sg:province":"Guip\u00f9zcoa",
    "wof:name":"Comunidad De Propietarios Atseden 3",
    "wof:placetype":"venue"
},
  "geometry": {"coordinates":[-1.80192101,43.3681983948],"type":"Point"}
}