{
  "type": "Feature",
  "properties": {
    "addr:full":"Rua Alameda San Tome, 25 Cambados Pontevedra 36630",
    "addr:housenumber":"25",
    "addr:postcode":"36630",
    "addr:street":"Rua Alameda San Tome",
    "iso:country":"ES",
    "sg:address":"Rua Alameda San Tome, 25",
    "sg:city":"Cambados",
    "sg:orig_category":"Empresarios",
    "sg:phone":"+34 986 54 27 88",
    "sg:postcode":"36630",
    "sg:province":"Pontevedra",
    "wof:name":"Prado Acha Jose",
    "wof:placetype":"venue"
},
  "geometry": {"coordinates":[-8.8161487579,42.5099105835],"type":"Point"}
}