{
  "type": "Feature",
  "properties": {
    "iso:country":"ES",
    "sg:address":"Pase Alberto Palacios, 82",
    "sg:city":"Madrid",
    "sg:orig_category":"Estancos",
    "sg:phone":"+34 917 97 79 10",
    "sg:postcode":"28021",
    "sg:province":"Madrid",
    "wof:name":"Arenas Gonzalez Julia",
    "wof:placetype":"venue"
},
  "geometry": {"coordinates":[-3.7163720131,40.3434143066],"type":"Point"}
}