{
  "type": "Feature",
  "properties": {
    "addr:full":"Calle de Cadena (la), 25 Zaragoza Zaragoza 50001",
    "addr:housenumber":"25",
    "addr:postcode":"50001",
    "addr:street":"Calle De Cadena La",
    "iso:country":"ES",
    "sg:address":"Calle de Cadena (la), 25",
    "sg:city":"Zaragoza",
    "sg:orig_category":"Agencias Y Agentes Comerciales, Representantes",
    "sg:phone":"+34 976 39 96 72",
    "sg:postcode":"50001",
    "sg:province":"Zaragoza",
    "wof:name":"Rivas Diaz Santiago",
    "wof:placetype":"venue"
},
  "geometry": {"coordinates":[-0.8752874732,41.6498336792],"type":"Point"}
}