{
  "type": "Feature",
  "properties": {
    "addr:full":"Avda Doctor Villa (circunvalacion Del Real), 14 Carmona Sevilla 41410",
    "addr:housenumber":"14",
    "addr:postcode":"41410",
    "addr:street":"Avda Doctor Villa Circunvalacion Del Real",
    "iso:country":"ES",
    "sg:address":"Avda Doctor Villa (circunvalacion Del Real), 14",
    "sg:city":"Carmona",
    "sg:orig_category":"Zapatos (al Por Menor)",
    "sg:phone":"+34 954 14 09 80",
    "sg:postcode":"41410",
    "sg:province":"Sevilla",
    "wof:name":"Perez Salcedo Manuela",
    "wof:placetype":"venue"
},
  "geometry": {"coordinates":[-5.6433792114,37.4708709717],"type":"Point"}
}