{
  "type": "Feature",
  "properties": {
    "iso:country":"ES",
    "sg:address":"Calle de Lisboa, 1",
    "sg:city":"Torres Alameda",
    "sg:orig_category":"Reposter\u00cdas",
    "sg:phone":"+34 918 86 82 53",
    "sg:postcode":"28813",
    "sg:province":"Madrid",
    "wof:name":"Seis H S.a.",
    "wof:placetype":"venue"
},
  "geometry": {"coordinates":[-3.3734929562,40.4081039429],"type":"Point"}
}