{
  "type": "Feature",
  "properties": {
    "addr:full":"Pase Castellana, 245 Madrid Madrid 28046",
    "addr:housenumber":"245",
    "addr:postcode":"28046",
    "addr:street":"Castellana",
    "iso:country":"ES",
    "sg:address":"Pase Castellana, 245",
    "sg:city":"Madrid",
    "sg:orig_category":"Farmacias",
    "sg:phone":"+34 913 15 36 66",
    "sg:postcode":"28046",
    "sg:province":"Madrid",
    "wof:name":"Fernandez Bernal Alfonso",
    "wof:placetype":"venue"
},
  "geometry": {"coordinates":[-3.6879270077,40.4733085632],"type":"Point"}
}