{
  "type": "Feature",
  "properties": {
    "addr:full":"Calle de Beato Tomas De Zumarraga, 56 Vitoria-gasteiz \u00c1lava 01009",
    "addr:housenumber":"56",
    "addr:postcode":"01009",
    "addr:street":"Calle De Beato Tomas De Zumarraga",
    "iso:country":"ES",
    "sg:address":"Calle de Beato Tomas De Zumarraga, 56",
    "sg:city":"Vitoria-gasteiz",
    "sg:orig_category":"Estancos",
    "sg:phone":"+34 945 22 85 49",
    "sg:postcode":"01009",
    "sg:province":"\u00c1lava",
    "wof:name":"Garcia Rodriguez Maria Del Carmen",
    "wof:placetype":"venue"
},
  "geometry": {"coordinates":[-2.684019804,42.8505477905],"type":"Point"}
}