{
  "type": "Feature",
  "properties": {
    "addr:full":"Plaz Doctor Gonzalez Gramage, 6 Sevilla Sevilla 41005",
    "addr:housenumber":"6",
    "addr:postcode":"41005",
    "addr:street":"Doctor;Gramage",
    "iso:country":"ES",
    "sg:address":"Plaz Doctor Gonzalez Gramage, 6",
    "sg:city":"Sevilla",
    "sg:orig_category":"M\u00c9dicos: Ginecolog\u00cda Y Obstetricia",
    "sg:phone":"+34 954 63 22 45",
    "sg:postcode":"41005",
    "sg:province":"Sevilla",
    "wof:name":"Diaz Romero Elena",
    "wof:placetype":"venue"
},
  "geometry": {"coordinates":[-6.0018129349,37.3876953125],"type":"Point"}
}