{
  "type": "Feature",
  "properties": {
    "iso:country":"ES",
    "sg:address":"Calle de Alcalde Segalerva Sierra, 2",
    "sg:city":"Malaga",
    "sg:orig_category":"Carnes De Carnicer\u00cda (al Por Mayor)",
    "sg:phone":"+34 952 35 03 11",
    "sg:postcode":"29006",
    "sg:province":"M\u00e1laga",
    "wof:name":"Discarsol S.l.",
    "wof:placetype":"venue"
},
  "geometry": {"coordinates":[-4.4736256599,36.708114624],"type":"Point"}
}