{
  "type": "Feature",
  "properties": {
    "iso:country":"ES",
    "sg:address":"Calle de Alvaro De Bazan, 10",
    "sg:city":"Valencia",
    "sg:orig_category":"Reposter\u00cdas",
    "sg:phone":"+34 963 62 23 74",
    "sg:postcode":"46010",
    "sg:province":"Valencia",
    "wof:name":"Bisbal Alca\u00f1iz Vicente",
    "wof:placetype":"venue"
},
  "geometry": {"coordinates":[-0.3630309999,39.481098175],"type":"Point"}
}