{
  "type": "Feature",
  "properties": {
    "addr:full":"Avda Camilo Jose Cela, 37 Padron La Coru\u00f1a 15900",
    "addr:housenumber":"37",
    "addr:postcode":"15900",
    "addr:street":"Avda Camilo Jose Cela;Padron La Corun\u0303A",
    "iso:country":"ES",
    "sg:address":"Avda Camilo Jose Cela, 37",
    "sg:city":"Padron",
    "sg:orig_category":"Transporte En General",
    "sg:phone":"+34 981 81 24 45",
    "sg:postcode":"15900",
    "sg:province":"La Coru\u00f1a",
    "wof:name":"Garcia Tojo Ricardo",
    "wof:placetype":"venue"
},
  "geometry": {"coordinates":[-8.6590499878,42.7391700745],"type":"Point"}
}