{
  "type": "Feature",
  "properties": {
    "iso:country":"ES",
    "sg:address":"Calle de Cristobal Colon, 5",
    "sg:city":"Zaragoza",
    "sg:orig_category":"Mec\u00c1nico Del Autom\u00d3vil",
    "sg:phone":"+34 976 27 70 02",
    "sg:postcode":"50007",
    "sg:province":"Zaragoza",
    "wof:name":"Gracia Genzor Jose Maria",
    "wof:placetype":"venue"
},
  "geometry": {"coordinates":[-0.8850402236,41.6412658691],"type":"Point"}
}