{
  "type": "Feature",
  "properties": {
    "iso:country":"ES",
    "sg:address":"Av Francesc Marimon, 94",
    "sg:city":"Esparreguera",
    "sg:orig_category":"Colchones (fabricaci\u00d3n, Al Por Mayor, Al Por Menor)",
    "sg:phone":"+34 937 77 18 91",
    "sg:postcode":"08292",
    "sg:province":"Barcelona",
    "wof:name":"Alavedra Marti Teresa",
    "wof:placetype":"venue"
},
  "geometry": {"coordinates":[1.8716038465,41.5342674255],"type":"Point"}
}