{
  "type": "Feature",
  "properties": {
    "addr:full":"Ctra. Zolina, 18 Tajonar Navarra 31192",
    "addr:housenumber":"18",
    "addr:postcode":"31192",
    "addr:street":"Ctra. Zolina",
    "iso:country":"ES",
    "sg:address":"Ctra. Zolina, 18",
    "sg:city":"Tajonar",
    "sg:orig_category":"Empresas De Carpinter\u00cda De Madera",
    "sg:phone":"+34 948 24 77 19",
    "sg:postcode":"31192",
    "sg:province":"Navarra",
    "wof:name":"Echandi Jimenez Francisco Javier",
    "wof:placetype":"venue"
},
  "geometry": {"coordinates":[-1.6151809692,42.7892303467],"type":"Point"}
}