{
  "type": "Feature",
  "properties": {
    "iso:country":"ES",
    "sg:address":"Aralar Kalea, 11",
    "sg:city":"Lekunberri",
    "sg:orig_category":"T\u00c9cnicos Veterinarios",
    "sg:phone":"+34 948 60 46 69",
    "sg:postcode":"31870",
    "sg:province":"Navarra",
    "wof:name":"Consultorio Veterinario S.i.",
    "wof:placetype":"venue"
},
  "geometry": {"coordinates":[-1.8947119713,43.0054626465],"type":"Point"}
}