{
  "type": "Feature",
  "properties": {
    "iso:country":"ES",
    "sg:address":"Plaz Ribadeo, 4",
    "sg:city":"Madrid",
    "sg:orig_category":"Peluqueros: De Se\u00d1oras",
    "sg:phone":"+34 917 40 55 11",
    "sg:postcode":"28029",
    "sg:province":"Madrid",
    "wof:name":"Geronimo De Arias Colasita",
    "wof:placetype":"venue"
},
  "geometry": {"coordinates":[-3.7105879784,40.4776153564],"type":"Point"}
}