{
  "type": "Feature",
  "properties": {
    "iso:country":"ES",
    "sg:address":"Carrer de Santa Teresa, 12",
    "sg:city":"Rubi",
    "sg:orig_category":"Asesor\u00cda, Estudio Y Control Medioambiental",
    "sg:phone":"+34 936 97 49 90",
    "sg:postcode":"08191",
    "sg:province":"Barcelona",
    "wof:name":"Jacas Massana Pedro",
    "wof:placetype":"venue"
},
  "geometry": {"coordinates":[2.0272660255,41.4930496216],"type":"Point"}
}