{
  "type": "Feature",
  "properties": {
    "iso:country":"ES",
    "sg:address":"Cno. Garrofera, S/n",
    "sg:city":"Guadassuar",
    "sg:orig_category":"Fabricaci\u00d3n De Moldes Y Modelos",
    "sg:phone":"+34 962 44 33 04",
    "sg:postcode":"46610",
    "sg:province":"Valencia",
    "wof:name":"Hijos De Joaquin Domenech S. L.",
    "wof:placetype":"venue"
},
  "geometry": {"coordinates":[-0.4772289991,39.1835365295],"type":"Point"}
}