{
  "type": "Feature",
  "properties": {
    "addr:full":"Calle de Juan Duque, 40 Madrid Madrid 28005",
    "addr:housenumber":"40",
    "addr:postcode":"madrid;28005",
    "addr:street":"Calle De Juan Duque",
    "iso:country":"ES",
    "sg:address":"Calle de Juan Duque, 40",
    "sg:city":"Madrid",
    "sg:orig_category":"Alquiler De V\u00cddeo",
    "sg:phone":"+34 913 65 85 25",
    "sg:postcode":"28005",
    "sg:province":"Madrid",
    "wof:name":"Garcia Hernandez Francisco Javier",
    "wof:placetype":"venue"
},
  "geometry": {"coordinates":[-3.7197589874,40.4094924927],"type":"Point"}
}