{
  "type": "Feature",
  "properties": {
    "iso:country":"ES",
    "sg:address":"Rua Fernando Iii O Santo (de), 18",
    "sg:city":"Santiago De Compostela",
    "sg:orig_category":"Alimentaci\u00d3n General (al Por Menor)",
    "sg:phone":"+34 981 59 20 13",
    "sg:postcode":"15706",
    "sg:province":"La Coru\u00f1a",
    "wof:name":"C. P.fdo Iii 18",
    "wof:placetype":"venue"
},
  "geometry": {"coordinates":[-8.5486421585,42.8713874817],"type":"Point"}
}