{
  "type": "Feature",
  "properties": {
    "iso:country":"ES",
    "sg:address":"Prol San Francisco, 65",
    "sg:city":"Mutxamel",
    "sg:orig_category":"Empresas De Carpinter\u00cda De Madera",
    "sg:phone":"+34 965 95 40 46",
    "sg:postcode":"03110",
    "sg:province":"Alicante",
    "wof:name":"Martinez Forner Rafael",
    "wof:placetype":"venue"
},
  "geometry": {"coordinates":[-0.4448040128,38.4151039124],"type":"Point"}
}