{
  "type": "Feature",
  "properties": {
    "addr:full":"Avgd Segre, 4 Lleida Lleida 25007",
    "addr:housenumber":"4",
    "addr:postcode":"25007",
    "addr:street":"Avgd Segre",
    "iso:country":"ES",
    "sg:address":"Avgd Segre, 4",
    "sg:city":"Lleida",
    "sg:orig_category":"M\u00c9dicos: Ginecolog\u00cda Y Obstetricia",
    "sg:phone":"+34 973 22 32 15",
    "sg:postcode":"25007",
    "sg:province":"Lleida",
    "wof:name":"Estadella Serrat Jose Ramon",
    "wof:placetype":"venue"
},
  "geometry": {"coordinates":[0.6310120225,41.6164550781],"type":"Point"}
}