{
  "type": "Feature",
  "properties": {
    "iso:country":"ES",
    "sg:address":"Mas Figueras, S/n",
    "sg:city":"Caldes Malavella",
    "sg:orig_category":"Cr\u00cda De Cerdos",
    "sg:phone":"+34 972 19 01 53",
    "sg:postcode":"17455",
    "sg:province":"Girona",
    "wof:name":"Grupfe S.a.",
    "wof:placetype":"venue"
},
  "geometry": {"coordinates":[2.8018240929,41.8385505676],"type":"Point"}
}