{
  "type": "Feature",
  "properties": {
    "addr:full":"Calle de Gran Via, 37 Zaragoza Zaragoza 50006",
    "addr:housenumber":"37",
    "addr:postcode":"50006",
    "addr:street":"Calle De Gran Via",
    "iso:country":"ES",
    "sg:address":"Calle de Gran Via, 37",
    "sg:city":"Zaragoza",
    "sg:orig_category":"Agentes Generales De Seguros",
    "sg:phone":"+34 976 22 39 26",
    "sg:postcode":"50006",
    "sg:province":"Zaragoza",
    "wof:name":"Foncillas Cistue Nicolas",
    "wof:placetype":"venue"
},
  "geometry": {"coordinates":[-0.891358614,41.6445274353],"type":"Point"}
}