{
  "type": "Feature",
  "properties": {
    "iso:country":"ES",
    "sg:address":"Monta\u00f1ana, 57",
    "sg:city":"Miranda Ebro",
    "sg:orig_category":"Delegados, Agentes De Tr\u00c1nsito, Auxiliares De Transporte Internacional",
    "sg:phone":"+34 947 31 07 50",
    "sg:postcode":"09200",
    "sg:province":"Burgos",
    "wof:name":"Transportes Luis Alberto Gonzalez Diez",
    "wof:placetype":"venue"
},
  "geometry": {"coordinates":[-2.9165899754,42.6908988953],"type":"Point"}
}