{
  "type": "Feature",
  "properties": {
    "addr:full":"Carrer de Montserrat, 3 S. Feliu Guixols Girona 17220",
    "addr:housenumber":"3",
    "addr:postcode":"17220",
    "addr:street":"Carrer De Montserrat;Feliu",
    "iso:country":"ES",
    "sg:address":"Carrer de Montserrat, 3",
    "sg:city":"S. Feliu Guixols",
    "sg:orig_category":"Mec\u00c1nico Del Autom\u00d3vil",
    "sg:phone":"+34 972 32 31 69",
    "sg:postcode":"17220",
    "sg:province":"Girona",
    "wof:name":"Rojas Ortega Manuel",
    "wof:placetype":"venue"
},
  "geometry": {"coordinates":[3.0264201164,41.7940063477],"type":"Point"}
}