{
  "type": "Feature",
  "properties": {
    "addr:full":"Aeropuerto, S/n Chauchina Granada 18330",
    "addr:housenumber":"s",
    "addr:postcode":"18330",
    "addr:street":"/ N",
    "iso:country":"ES",
    "sg:address":"Aeropuerto, S/n",
    "sg:city":"Chauchina",
    "sg:orig_category":"Aeropuertos Y Servicios Aeroportuarios",
    "sg:phone":"+34 958 45 51 42",
    "sg:postcode":"18330",
    "sg:province":"Granada",
    "wof:name":"Ryanair Ltd",
    "wof:placetype":"venue"
},
  "geometry": {"coordinates":[-3.7680261135,37.2010955811],"type":"Point"}
}