{
  "type": "Feature",
  "properties": {
    "iso:country":"ES",
    "sg:address":"Avda Orbigo (el), 29",
    "sg:city":"Benavides De Orbigo",
    "sg:orig_category":"Agricultura: Abastecimiento Y Cosechado (negocio)",
    "sg:phone":"+34 987 37 04 85",
    "sg:postcode":"24280",
    "sg:province":"Le\u00f3n",
    "wof:name":"Fernandez Castrillo Emilio Juan",
    "wof:placetype":"venue"
},
  "geometry": {"coordinates":[-5.8943762779,42.5051574707],"type":"Point"}
}