{
  "type": "Feature",
  "properties": {
    "iso:country":"ES",
    "sg:address":"Ctra Valladolid, S/n",
    "sg:city":"Villalbilla De Burgos",
    "sg:orig_category":"Metalurgia",
    "sg:phone":"+34 947 29 11 06",
    "sg:postcode":"09197",
    "sg:province":"Burgos",
    "wof:name":"Vigas Armadas Y Pretensadas S. A.",
    "wof:placetype":"venue"
},
  "geometry": {"coordinates":[-3.7720661163,42.3419456482],"type":"Point"}
}