{
  "type": "Feature",
  "properties": {
    "addr:full":"Calle de Castillo Alcadima, 5 Bormujos Sevilla 41930",
    "addr:housenumber":"5",
    "addr:postcode":"41930",
    "addr:street":"Calle De Castillo Alcadima",
    "iso:country":"ES",
    "sg:address":"Calle de Castillo Alcadima, 5",
    "sg:city":"Bormujos",
    "sg:orig_category":"Agencias Y Agentes Comerciales, Representantes",
    "sg:phone":"+34 954 78 92 41",
    "sg:postcode":"41930",
    "sg:province":"Sevilla",
    "wof:name":"Exposito Moreno Maria Angeles",
    "wof:placetype":"venue"
},
  "geometry": {"coordinates":[-6.0640587807,37.3770637512],"type":"Point"}
}