{
  "type": "Feature",
  "properties": {
    "addr:full":"Carrer de Rosa De Alejandria, 35 Hospitalet Llobregat Barcelona 08906",
    "addr:housenumber":"35",
    "addr:postcode":"08906",
    "addr:street":"Carrer De Rosa De Alejandria",
    "iso:country":"ES",
    "sg:address":"Carrer de Rosa De Alejandria, 35",
    "sg:city":"Hospitalet Llobregat",
    "sg:orig_category":"T\u00c9cnicos Veterinarios",
    "sg:phone":"+34 934 37 84 73",
    "sg:postcode":"08906",
    "sg:province":"Barcelona",
    "wof:name":"Naves Vi\u00f1as Julian Maria",
    "wof:placetype":"venue"
},
  "geometry": {"coordinates":[12.4903001785,51.6163101196],"type":"Point"}
}