{
  "type": "Feature",
  "properties": {
    "addr:full":"Carr Historiador Parassols I Pi, 9 Sant Joan De Les Abadesses Girona 17860",
    "addr:housenumber":"9",
    "addr:postcode":"17860",
    "addr:street":"Carr Historiador Parassols;Pi",
    "iso:country":"ES",
    "sg:address":"Carr Historiador Parassols I Pi, 9",
    "sg:city":"Sant Joan De Les Abadesses",
    "sg:orig_category":"Institutos De Belleza",
    "sg:phone":"+34 972 72 01 71",
    "sg:postcode":"17860",
    "sg:province":"Girona",
    "wof:name":"Bertran Font Montserrat",
    "wof:placetype":"venue"
},
  "geometry": {"coordinates":[2.2854809761,42.2338752747],"type":"Point"}
}