{
  "type": "Feature",
  "properties": {
    "iso:country":"ES",
    "sg:address":"Calle de Pollo Martin, 37",
    "sg:city":"Salamanca",
    "sg:orig_category":"Asilos De Ancianos. Centros Privados",
    "sg:phone":"+34 923 22 85 04",
    "sg:postcode":"37005",
    "sg:province":"Salamanca",
    "wof:name":"Hermanas Mercedarias De La Caridad Provincia De Madrid Curia Provincial",
    "wof:placetype":"venue"
},
  "geometry": {"coordinates":[-5.6590108871,40.9713516235],"type":"Point"}
}