{
  "type": "Feature",
  "properties": {
    "iso:country":"ES",
    "sg:address":"Rua Industria (da), 87",
    "sg:city":"Lugo",
    "sg:orig_category":"Mec\u00c1nico Del Autom\u00d3vil",
    "sg:phone":"+34 982 20 91 57",
    "sg:postcode":"27003",
    "sg:province":"Lugo",
    "wof:name":"Paco Mendez S.l.",
    "wof:placetype":"venue"
},
  "geometry": {"coordinates":[-7.5691690445,43.0469284058],"type":"Point"}
}