{
  "type": "Feature",
  "properties": {
    "addr:full":"Ctra Puente Genil, 5 Herrera Sevilla 41567",
    "addr:housenumber":"5",
    "addr:postcode":"41567",
    "addr:street":"Ctra Puente Genil",
    "iso:country":"ES",
    "sg:address":"Ctra Puente Genil, 5",
    "sg:city":"Herrera",
    "sg:orig_category":"Mec\u00c1nico Del Autom\u00d3vil",
    "sg:phone":"+34 954 01 32 79",
    "sg:postcode":"41567",
    "sg:province":"Sevilla",
    "wof:name":"Talleres Mu\u00f1oz C.b.",
    "wof:placetype":"venue"
},
  "geometry": {"coordinates":[-4.8506789207,37.3627128601],"type":"Point"}
}