{
  "type": "Feature",
  "properties": {
    "iso:country":"ES",
    "sg:address":"Calle de Juan Boscan, 11",
    "sg:city":"Madrid",
    "sg:orig_category":"Carnicer\u00cdas, Carnicer\u00cdas",
    "sg:phone":"+34 914 07 05 90",
    "sg:postcode":"28017",
    "sg:province":"Madrid",
    "wof:name":"Rebe-mar S.l.",
    "wof:placetype":"venue"
},
  "geometry": {"coordinates":[-3.6416540146,40.426235199],"type":"Point"}
}