{
  "type": "Feature",
  "properties": {
    "addr:full":"Calle de Perez Galdos, 23 Santa Cruz De Tenerife Santa Cruz De Tenerife 38002",
    "addr:housenumber":"23",
    "addr:postcode":"38002",
    "addr:street":"Calle De Perez Galdos",
    "iso:country":"ES",
    "sg:address":"Calle de Perez Galdos, 23",
    "sg:city":"Santa Cruz De Tenerife",
    "sg:orig_category":"Art\u00cdculos De Regalo (al Por Menor)",
    "sg:phone":"+34 922 29 09 81",
    "sg:postcode":"38002",
    "sg:province":"Santa Cruz De Tenerife",
    "wof:name":"Montblanc Wiese Espa\u00d1a S.l.",
    "wof:placetype":"venue"
},
  "geometry": {"coordinates":[-16.25258255,28.4681797028],"type":"Point"}
}