{
  "type": "Feature",
  "properties": {
    "iso:country":"ES",
    "sg:address":"Carrer de Canaries, S/n",
    "sg:city":"S. Celoni",
    "sg:orig_category":"Compraventa De Antig\u00dcedades",
    "sg:phone":"+34 938 48 45 35",
    "sg:postcode":"08470",
    "sg:province":"Barcelona",
    "sg:website":"www.planantic.com",
    "wof:name":"Plan Antic S.c.p",
    "wof:placetype":"venue"
},
  "geometry": {"coordinates":[2.4965701103,41.6892662048],"type":"Point"}
}