{
  "type": "Feature",
  "properties": {
    "addr:full":"Calle de Francisco Garcia Ballester, 2 Bu\u00f1ol Valencia 46360",
    "addr:housenumber":"2",
    "addr:postcode":"46360",
    "addr:street":"Calle De Francisco Garcia Ballester",
    "iso:country":"ES",
    "sg:address":"Calle de Francisco Garcia Ballester, 2",
    "sg:city":"Bu\u00f1ol",
    "sg:orig_category":"Comercio De Piezas De Recambio Y De Accesorios De Veh\u00cdculos, Veh\u00cdculos Industriales",
    "sg:phone":"+34 962 50 25 52",
    "sg:postcode":"46360",
    "sg:province":"Valencia",
    "wof:name":"Recambios Colon-catarroja S.a.",
    "wof:placetype":"venue"
},
  "geometry": {"coordinates":[-0.7843170762,39.4270401001],"type":"Point"}
}