{
  "type": "Feature",
  "properties": {
    "iso:country":"ES",
    "sg:address":"Avda Goya, S/n",
    "sg:city":"Torres Berrellen",
    "sg:orig_category":"Art\u00cdculos Funerarios (al Por Menor)",
    "sg:phone":"+34 976 65 37 81",
    "sg:postcode":"50693",
    "sg:province":"Zaragoza",
    "wof:name":"Funerarias Valle Del Ebro S.l.l.",
    "wof:placetype":"venue"
},
  "geometry": {"coordinates":[-1.0671668053,41.7552680969],"type":"Point"}
}