{
  "type": "Feature",
  "properties": {
    "addr:full":"Carrer de Ramon Casas, 23 Cunit Tarragona 43881",
    "addr:housenumber":"23",
    "addr:postcode":"43881",
    "addr:street":"Carrer De Ramon Casas",
    "iso:country":"ES",
    "sg:address":"Carrer de Ramon Casas, 23",
    "sg:city":"Cunit",
    "sg:orig_category":"Zapatos (al Por Menor)",
    "sg:phone":"+34 977 67 55 86",
    "sg:postcode":"43881",
    "sg:province":"Tarragona",
    "wof:name":"Calzados Mari-son S.l.",
    "wof:placetype":"venue"
},
  "geometry": {"coordinates":[1.6357480288,41.1971740723],"type":"Point"}
}