{
  "type": "Feature",
  "properties": {
    "addr:full":"Pintor Sixto Marco, 5 Elche Alicante 03203",
    "addr:housenumber":"5",
    "addr:postcode":"03203",
    "addr:street":"Pintor Sixto Marco",
    "iso:country":"ES",
    "sg:address":"Pintor Sixto Marco, 5",
    "sg:city":"Elche",
    "sg:orig_category":"Par\u00cds",
    "sg:phone":"+34 965 42 17 43",
    "sg:postcode":"03203",
    "sg:province":"Alicante",
    "wof:name":"Ferri Martinez Asuncion Trinidad",
    "wof:placetype":"venue"
},
  "geometry": {"coordinates":[-0.6784489751,38.267906189],"type":"Point"}
}