{
  "type": "Feature",
  "properties": {
    "addr:full":"Carrer de Raval Santa Coloma, 11 Santa Coloma De Queralt Tarragona 43420",
    "addr:housenumber":"11",
    "addr:postcode":"43420",
    "addr:street":"Carrer De Raval Santa Coloma",
    "iso:country":"ES",
    "sg:address":"Carrer de Raval Santa Coloma, 11",
    "sg:city":"Santa Coloma De Queralt",
    "sg:orig_category":"Estancos",
    "sg:phone":"+34 977 88 15 91",
    "sg:postcode":"43420",
    "sg:province":"Tarragona",
    "wof:name":"Corbella Alemany Joaquim",
    "wof:placetype":"venue"
},
  "geometry": {"coordinates":[1.3818399906,41.5321388245],"type":"Point"}
}