{
  "type": "Feature",
  "properties": {
    "addr:full":"Rua Mari\u00d1eira (da), 9 Santiago De Compostela La Coru\u00f1a 15891",
    "addr:housenumber":"9",
    "addr:postcode":"15891",
    "addr:street":"Rua Marin\u0303Eira Da;Corun\u0303A",
    "iso:country":"ES",
    "sg:address":"Rua Mari\u00d1eira (da), 9",
    "sg:city":"Santiago De Compostela",
    "sg:orig_category":"Molduras, Junquillos, Listones Y Molduras Perforadas",
    "sg:phone":"+34 981 56 28 86",
    "sg:postcode":"15891",
    "sg:province":"La Coru\u00f1a",
    "wof:name":"Andrade Vazquez Luis",
    "wof:placetype":"venue"
},
  "geometry": {"coordinates":[-8.510345459,42.8921966553],"type":"Point"}
}