{
  "type": "Feature",
  "properties": {
    "addr:full":"Carr Federico Garcia Lorca, 33 Alfas Pi Alicante 03580",
    "addr:housenumber":"33",
    "addr:postcode":"03580",
    "addr:street":"Carr Federico Garcia Lorca",
    "iso:country":"ES",
    "sg:address":"Carr Federico Garcia Lorca, 33",
    "sg:city":"Alfas Pi",
    "sg:orig_category":"Inform\u00c1tica, Ofim\u00c1tica (estudios, Asesor\u00cda, Ingenier\u00cda, Formaci\u00d3n)",
    "sg:phone":"+34 965 88 75 68",
    "sg:postcode":"03580",
    "sg:province":"Alicante",
    "wof:name":"Jobcontrol S.l.",
    "wof:placetype":"venue"
},
  "geometry": {"coordinates":[-0.1009420007,38.5784225464],"type":"Point"}
}