{
  "type": "Feature",
  "properties": {
    "addr:full":"Urb Mas D'en Pares, 1 Les Pobles Tarragona 43815",
    "addr:housenumber":"1",
    "addr:postcode":"43815",
    "addr:street":"Urb;Les Pobles",
    "iso:country":"ES",
    "sg:address":"Urb Mas D'en Pares, 1",
    "sg:city":"Les Pobles",
    "sg:orig_category":"Centros De Educaci\u00d3n Especial",
    "sg:phone":"+34 977 63 91 63",
    "sg:postcode":"43815",
    "sg:province":"Tarragona",
    "wof:name":"Ajuntament De Aiguamurcia",
    "wof:placetype":"venue"
},
  "geometry": {"coordinates":[1.402553916,41.3620262146],"type":"Point"}
}