{
  "type": "Feature",
  "properties": {
    "addr:full":"Cno Ermita Sta Llucia, 10 Denia Alicante 03700",
    "addr:housenumber":"10",
    "addr:postcode":"03700",
    "addr:street":"Cno Ermita Sta Llucia",
    "iso:country":"ES",
    "sg:address":"Cno Ermita Sta Llucia, 10",
    "sg:city":"Denia",
    "sg:orig_category":"Promotores Constructores",
    "sg:phone":"+34 965 78 50 10",
    "sg:postcode":"03700",
    "sg:province":"Alicante",
    "wof:name":"Construcciones Duque Y Tres Hijos S.l.",
    "wof:placetype":"venue"
},
  "geometry": {"coordinates":[0.1201400012,38.8268814087],"type":"Point"}
}