{
  "type": "Feature",
  "properties": {
    "addr:full":"Calle de Donoso Cortes, 47 Don Benito Badajoz 06400",
    "addr:housenumber":"47",
    "addr:postcode":"06400",
    "addr:street":"Calle De Donoso Cortes",
    "iso:country":"ES",
    "sg:address":"Calle de Donoso Cortes, 47",
    "sg:city":"Don Benito",
    "sg:orig_category":"Abogados",
    "sg:phone":"+34 924 80 03 60",
    "sg:postcode":"06400",
    "sg:province":"Badajoz",
    "wof:name":"Gomez Fernandez Emilio",
    "wof:placetype":"venue"
},
  "geometry": {"coordinates":[-5.8584537506,38.955116272],"type":"Point"}
}