{
  "type": "Feature",
  "properties": {
    "addr:full":"Calle de Siervo De Dios, 34 Icod De Los Vinos Santa Cruz De Tenerife 38430",
    "addr:housenumber":"34",
    "addr:postcode":"38430",
    "addr:street":"Calle De Siervo;Dios",
    "iso:country":"ES",
    "sg:address":"Calle de Siervo De Dios, 34",
    "sg:city":"Icod De Los Vinos",
    "sg:orig_category":"Agencias De Viajes",
    "sg:phone":"+34 922 81 50 00",
    "sg:postcode":"38430",
    "sg:province":"Santa Cruz De Tenerife",
    "sg:website":"www.halconviajes.com",
    "wof:name":"Viajes Halcon S.a.",
    "wof:placetype":"venue"
},
  "geometry": {"coordinates":[-16.7181186676,28.367767334],"type":"Point"}
}