{
  "type": "Feature",
  "properties": {
    "addr:full":"Calle de Sierra De Cazorla, 22 Baza Granada 18800",
    "addr:housenumber":"22",
    "addr:postcode":"18800",
    "addr:street":"Calle De Sierra De Cazorla",
    "iso:country":"ES",
    "sg:address":"Calle de Sierra De Cazorla, 22",
    "sg:city":"Baza",
    "sg:orig_category":"Ingeniero",
    "sg:phone":"+34 958 71 23 68",
    "sg:postcode":"18800",
    "sg:province":"Granada",
    "wof:name":"Gavilan Sanchez Jesus",
    "wof:placetype":"venue"
},
  "geometry": {"coordinates":[-2.7669389248,37.4901542664],"type":"Point"}
}