{
  "type": "Feature",
  "properties": {
    "addr:full":"Del Rio, S/n Vadocondes Burgos 09491",
    "addr:postcode":"09491",
    "addr:street":"Del Rio S / N",
    "iso:country":"ES",
    "sg:address":"Del Rio, S/n",
    "sg:city":"Vadocondes",
    "sg:orig_category":"Cr\u00cda De Animales",
    "sg:phone":"+34 947 56 10 32",
    "sg:postcode":"09491",
    "sg:province":"Burgos",
    "wof:name":"Alcubilla Lopez Antonio",
    "wof:placetype":"venue"
},
  "geometry": {"coordinates":[-3.5702044964,41.6405830383],"type":"Point"}
}