{
  "type": "Feature",
  "properties": {
    "addr:full":"Calle de Rosal, 3 Humanes De Madrid Madrid 28970",
    "addr:housenumber":"3",
    "addr:postcode":"28970",
    "addr:street":"Calle De Rosal",
    "iso:country":"ES",
    "sg:address":"Calle de Rosal, 3",
    "sg:city":"Humanes De Madrid",
    "sg:orig_category":"Publicidad (soportes Y Gesti\u00d3n)",
    "sg:phone":"+34 916 97 64 33",
    "sg:postcode":"28970",
    "sg:province":"Madrid",
    "sg:website":"www.com-fabric.com",
    "wof:name":"Comercializacion Y Fabricacion Metalica",
    "wof:placetype":"venue"
},
  "geometry": {"coordinates":[-3.8400919437,40.2670097351],"type":"Point"}
}