{
  "type": "Feature",
  "properties": {
    "iso:country":"ES",
    "sg:address":"Calle de Gandia, S/n",
    "sg:city":"Alzira",
    "sg:orig_category":"Ense\u00d1anza Secundaria: Colegios Y Escuelas Privadas",
    "sg:phone":"+34 962 41 08 08",
    "sg:postcode":"46600",
    "sg:province":"Valencia",
    "wof:name":"Generalitat Valenciana",
    "wof:placetype":"venue"
},
  "geometry": {"coordinates":[-0.4261229932,39.1428947449],"type":"Point"}
}