{
  "type": "Feature",
  "properties": {
    "iso:country":"ES",
    "sg:address":"Pase Aixin Zolua Ibilbidea, 3",
    "sg:city":"Irun",
    "sg:orig_category":"Servicios De Higiene Y Peluquer\u00cda Para Perros Y Gatos",
    "sg:phone":"+34 943 63 30 34",
    "sg:postcode":"20304",
    "sg:province":"Guip\u00f9zcoa",
    "wof:name":"Gonjar Arias Ainara",
    "wof:placetype":"venue"
},
  "geometry": {"coordinates":[-1.7847739458,43.3386039734],"type":"Point"}
}