{
  "type": "Feature",
  "properties": {
    "iso:country":"ES",
    "sg:address":"Calle de General Chamorro Martinez, 11",
    "sg:city":"Sevilla",
    "sg:orig_category":"Molduras, Junquillos, Listones Y Molduras Perforadas",
    "sg:phone":"+34 954 35 71 86",
    "sg:postcode":"41008",
    "sg:province":"Sevilla",
    "wof:name":"Jimenez Blanco Antonio",
    "wof:placetype":"venue"
},
  "geometry": {"coordinates":[-5.9702987671,37.4061317444],"type":"Point"}
}