{
  "type": "Feature",
  "properties": {
    "addr:full":"Ambito Portuario, 999 Pasai Antxo Guip\u00f9zcoa 20110",
    "addr:housenumber":"999",
    "addr:postcode":"20110",
    "addr:street":"Ambito Portuario;Guipu\u0300Zcoa",
    "iso:country":"ES",
    "sg:address":"Ambito Portuario, 999",
    "sg:city":"Pasai Antxo",
    "sg:orig_category":"Peritos Mar\u00cdtimos",
    "sg:phone":"+34 943 35 02 55",
    "sg:postcode":"20110",
    "sg:province":"Guip\u00f9zcoa",
    "wof:name":"Agencia Maritima Sea Spain S.a.",
    "wof:placetype":"venue"
},
  "geometry": {"coordinates":[-1.9217879772,43.3260040283],"type":"Point"}
}