{
  "type": "Feature",
  "properties": {
    "addr:full":"Ausias March, 43 Montroy Valencia 46193",
    "addr:housenumber":"43",
    "addr:postcode":"46193",
    "addr:street":"March",
    "iso:country":"ES",
    "sg:address":"Ausias March, 43",
    "sg:city":"Montroy",
    "sg:classifiers":[
        {
            "category":"Professional",
            "subcategory":"Management & Consulting",
            "type":"Services"
        }
    ],
    "sg:phone":"+34 962 55 56 10",
    "sg:postcode":"46193",
    "sg:province":"Valencia",
    "sg:tags":[
        "asesor\u00cda",
        "en",
        "marketing"
    ],
    "wof:name":"Centro Profesional Luis San Jaume",
    "wof:placetype":"venue"
},
  "geometry": {"coordinates":[-0.6125090122,39.3400306702],"type":"Point"}
}