{
  "type": "Feature",
  "properties": {
    "addr:full":"Ctra Moron-pruna, Km. 0002,0 Moron Frontera Sevilla 41530",
    "addr:postcode":"41530",
    "addr:street":"Ctra Moron-Pruna Km. 0002,0 Moron",
    "iso:country":"ES",
    "sg:address":"Ctra Moron-pruna, Km. 0002,0",
    "sg:city":"Moron Frontera",
    "sg:orig_category":"Escayola Y Productos De Escayola (fabricaci\u00d3n, Al Por Mayor)",
    "sg:phone":"+34 954 85 03 37",
    "sg:postcode":"41530",
    "sg:province":"Sevilla",
    "wof:name":"Fabrica De Yesos La Atalaya S.l.",
    "wof:placetype":"venue"
},
  "geometry": {"coordinates":[-5.4528231621,37.1294212341],"type":"Point"}
}