{
  "type": "Feature",
  "properties": {
    "iso:country":"ES",
    "sg:address":"Calle de Pablo Picasso, 13",
    "sg:city":"Alcala Guadaira",
    "sg:orig_category":"Peluquer\u00cdas, Peluquer\u00cda Mixta",
    "sg:phone":"+34 955 61 28 88",
    "sg:postcode":"41500",
    "sg:province":"Sevilla",
    "wof:name":"Toro De Leyva Ana Maria",
    "wof:placetype":"venue"
},
  "geometry": {"coordinates":[-5.8453941345,37.3501472473],"type":"Point"}
}