{
  "type": "Feature",
  "properties": {
    "iso:country":"ES",
    "sg:address":"Calle de Ildefonso Serrano, 2",
    "sg:city":"Segura Leon",
    "sg:orig_category":"Iglesia Cat\u00d3lica",
    "sg:phone":"+34 924 70 30 54",
    "sg:postcode":"06270",
    "sg:province":"Badajoz",
    "wof:name":"Parroquia Nuestra Se\u00f1ora De La Asuncion",
    "wof:placetype":"venue"
},
  "geometry": {"coordinates":[-6.5285511017,38.1197853088],"type":"Point"}
}