{
  "type": "Feature",
  "properties": {
    "addr:full":"Brixeo(santa Maria), S/n Brixeo La Coru\u00f1a 15320",
    "addr:postcode":"15320",
    "addr:street":"S / N Brixeo La Corun\u0303A",
    "iso:country":"ES",
    "sg:address":"Brixeo(santa Maria), S/n",
    "sg:city":"Brixeo",
    "sg:orig_category":"Ense\u00d1anza, Formaci\u00d3n Profesional: Aprendizaje",
    "sg:phone":"+34 981 45 18 66",
    "sg:postcode":"15320",
    "sg:province":"La Coru\u00f1a",
    "wof:name":"Instituto De Educacion Secundaria Castro Da Uz",
    "wof:placetype":"venue"
},
  "geometry": {"coordinates":[-7.8519802094,43.4437828064],"type":"Point"}
}