{
  "type": "Feature",
  "properties": {
    "addr:full":"Carrer de Gran Canaria, 2 Granja Tarragona 43006",
    "addr:housenumber":"2",
    "addr:postcode":"43006",
    "addr:street":"Carrer De Gran Canaria",
    "iso:country":"ES",
    "sg:address":"Carrer de Gran Canaria, 2",
    "sg:city":"Granja",
    "sg:orig_category":"Deportes N\u00c1uticos, Acu\u00c1ticos Y Subacu\u00c1ticos: Art\u00cdculos Y Equipo (al Por Menor)",
    "sg:phone":"+34 977 54 46 52",
    "sg:postcode":"43006",
    "sg:province":"Tarragona",
    "wof:name":"Sebastian Dolz Ricardo",
    "wof:placetype":"venue"
},
  "geometry": {"coordinates":[1.2209249735,41.1154441833],"type":"Point"}
}