{
  "type": "Feature",
  "properties": {
    "addr:full":"Carrer de Josep Torras I Bages, 7 S. Boi Llobregat Barcelona 08830",
    "addr:housenumber":"7",
    "addr:postcode":"08830",
    "addr:street":"Carrer De Josep Torras I Bages",
    "iso:country":"ES",
    "sg:address":"Carrer de Josep Torras I Bages, 7",
    "sg:city":"S. Boi Llobregat",
    "sg:orig_category":"Alimentaci\u00d3n General (al Por Menor)",
    "sg:phone":"+34 936 40 12 20",
    "sg:postcode":"08830",
    "sg:province":"Barcelona",
    "wof:name":"Supervia-95 S.l.",
    "wof:placetype":"venue"
},
  "geometry": {"coordinates":[2.0432710648,41.3478240967],"type":"Point"}
}