{
  "type": "Feature",
  "properties": {
    "addr:full":"Carrer de Emporda, 35 Prat Llobregat Barcelona 08820",
    "addr:housenumber":"35",
    "addr:postcode":"08820",
    "addr:street":"Carrer De Emporda;Llobregat",
    "iso:country":"ES",
    "sg:address":"Carrer de Emporda, 35",
    "sg:city":"Prat Llobregat",
    "sg:orig_category":"Mec\u00c1nico Del Autom\u00d3vil",
    "sg:phone":"+34 934 78 61 00",
    "sg:postcode":"08820",
    "sg:province":"Barcelona",
    "wof:name":"Talleres Ros S.a.",
    "wof:placetype":"venue"
},
  "geometry": {"coordinates":[2.0891010761,41.3280296326],"type":"Point"}
}