{
  "type": "Feature",
  "properties": {
    "addr:full":"Calle de Real, 36 Campillos M\u00e1laga 29320",
    "addr:housenumber":"36",
    "addr:postcode":"29320",
    "addr:street":"Calle De Real",
    "iso:country":"ES",
    "sg:address":"Calle de Real, 36",
    "sg:city":"Campillos",
    "sg:orig_category":"Albergues",
    "sg:phone":"+34 952 72 20 56",
    "sg:postcode":"29320",
    "sg:province":"M\u00e1laga",
    "wof:name":"Aguilar Romero Jesus",
    "wof:placetype":"venue"
},
  "geometry": {"coordinates":[-4.8613495827,37.0485305786],"type":"Point"}
}