{
  "type": "Feature",
  "properties": {
    "iso:country":"ES",
    "sg:address":"Rbla Generalitat, 8",
    "sg:city":"Almacelles",
    "sg:orig_category":"Trabajos De Perforaciones, Sondeos, Construcci\u00d3n De Pozos",
    "sg:phone":"+34 973 74 02 21",
    "sg:postcode":"25100",
    "sg:province":"Lleida",
    "wof:name":"Fernandez Martinez Jesus",
    "wof:placetype":"venue"
},
  "geometry": {"coordinates":[0.4405150115,41.7275161743],"type":"Point"}
}