{
  "type": "Feature",
  "properties": {
    "addr:full":"Calle de Castilla (de), 10 Mejorada Campo Madrid 28840",
    "addr:housenumber":"10",
    "addr:postcode":"28840",
    "addr:street":"Calle De Castilla De",
    "iso:country":"ES",
    "sg:address":"Calle de Castilla (de), 10",
    "sg:city":"Mejorada Campo",
    "sg:orig_category":"Rectificaci\u00d3n, Mecanizado, Fresado",
    "sg:phone":"+34 916 79 00 79",
    "sg:postcode":"28840",
    "sg:province":"Madrid",
    "wof:name":"Vianvi S.a.",
    "wof:placetype":"venue"
},
  "geometry": {"coordinates":[-3.4839110374,40.3875846863],"type":"Point"}
}