{
  "type": "Feature",
  "properties": {
    "iso:country":"ES",
    "sg:address":"Avda Agirre Lehendakaria, 91",
    "sg:city":"Urbi",
    "sg:orig_category":"Carnicer\u00cdas, Carnicer\u00cdas",
    "sg:phone":"+34 944 49 23 11",
    "sg:postcode":"48970",
    "sg:province":"Vizcaya",
    "wof:name":"Gonzalez Rodriguez Serafina",
    "wof:placetype":"venue"
},
  "geometry": {"coordinates":[-2.8795049191,43.2356376648],"type":"Point"}
}