{
  "type": "Feature",
  "properties": {
    "addr:full":"Calle de Alhambra, 2 Santiago El Mayor Murcia 30011",
    "addr:housenumber":"2",
    "addr:postcode":"30011",
    "addr:street":"Calle De Alhambra",
    "iso:country":"ES",
    "sg:address":"Calle de Alhambra, 2",
    "sg:city":"Santiago El Mayor",
    "sg:orig_category":"Prot\u00c9sicos Dentales",
    "sg:phone":"+34 968 25 75 44",
    "sg:postcode":"30011",
    "sg:province":"Murcia",
    "wof:name":"Ortiz Garcia Rafael",
    "wof:placetype":"venue"
},
  "geometry": {"coordinates":[-1.1298867464,37.9834747314],"type":"Point"}
}