{
  "type": "Feature",
  "properties": {
    "iso:country":"ES",
    "sg:address":"Carr Eliseu Meifren, 8",
    "sg:city":"Badalona",
    "sg:orig_category":"Alimentaci\u00d3n General (al Por Menor)",
    "sg:phone":"+34 933 95 15 56",
    "sg:postcode":"08915",
    "sg:province":"Barcelona",
    "wof:name":"Mu\u00f1oz Del Paso Carmen",
    "wof:placetype":"venue"
},
  "geometry": {"coordinates":[2.2383019924,41.466217041],"type":"Point"}
}