{
  "type": "Feature",
  "properties": {
    "addr:full":"Ctra. Torrijos, S/n Gerindote Toledo 45518",
    "addr:housenumber":"s / n",
    "addr:postcode":"45518",
    "addr:street":"Ctra. Torrijos",
    "iso:country":"ES",
    "sg:address":"Ctra. Torrijos, S/n",
    "sg:city":"Gerindote",
    "sg:orig_category":"Distribuci\u00d3n De Petr\u00d3leo Y Derivados",
    "sg:phone":"+34 925 77 22 05",
    "sg:postcode":"45518",
    "sg:province":"Toledo",
    "wof:name":"Dagas Auto S.l.",
    "wof:placetype":"venue"
},
  "geometry": {"coordinates":[-4.3027181625,39.9676551819],"type":"Point"}
}