{
  "type": "Feature",
  "properties": {
    "iso:country":"ES",
    "sg:address":"Calle de Luz (de La), 4",
    "sg:city":"Arevalo",
    "sg:orig_category":"Transporte En General",
    "sg:phone":"+34 920 30 33 27",
    "sg:postcode":"05200",
    "sg:province":"\u00c1vila",
    "wof:name":"Distribuidora Internacional De Alimentacion S.a.",
    "wof:placetype":"venue"
},
  "geometry": {"coordinates":[-4.7203741074,41.0579719543],"type":"Point"}
}