{
  "type": "Feature",
  "properties": {
    "addr:full":"Pase Goya (de), 7 Mostoles Madrid 28932",
    "addr:postcode":"28932",
    "addr:street":"Mostoles",
    "iso:country":"ES",
    "sg:address":"Pase Goya (de), 7",
    "sg:city":"Mostoles",
    "sg:orig_category":"Alimentaci\u00d3n General (al Por Menor)",
    "sg:phone":"+34 916 13 35 55",
    "sg:postcode":"28932",
    "sg:province":"Madrid",
    "wof:name":"Gonzalez Garcia Ulises",
    "wof:placetype":"venue"
},
  "geometry": {"coordinates":[-3.8649389744,40.3230667114],"type":"Point"}
}