{
  "type": "Feature",
  "properties": {
    "addr:full":"Calle de Santa Maria, 9 Logro\u00f1o La Rioja 26006",
    "addr:housenumber":"9",
    "addr:postcode":"26006",
    "addr:street":"Calle De Santa Maria;Rioja",
    "iso:country":"ES",
    "sg:address":"Calle de Santa Maria, 9",
    "sg:city":"Logro\u00f1o",
    "sg:orig_category":"Electricidad, Electr\u00d3nica: Material Y Suministros (al Por Mayor)",
    "sg:phone":"+34 941 23 06 85",
    "sg:postcode":"26006",
    "sg:province":"La Rioja",
    "wof:name":"Sumelec Rioja S.l.",
    "wof:placetype":"venue"
},
  "geometry": {"coordinates":[-2.4148659706,42.4511184692],"type":"Point"}
}