{
  "type": "Feature",
  "properties": {
    "addr:full":"Calle de Chaparil (el), 2 Nerja M\u00e1laga 29780",
    "addr:housenumber":"2",
    "addr:postcode":"29780",
    "addr:street":"Calle De Chaparil El",
    "iso:country":"ES",
    "sg:address":"Calle de Chaparil (el), 2",
    "sg:city":"Nerja",
    "sg:orig_category":"Peluquer\u00cdas, Peluquer\u00cda Mixta",
    "sg:phone":"+34 952 52 31 58",
    "sg:postcode":"29780",
    "sg:province":"M\u00e1laga",
    "wof:name":"Cayro S.c.",
    "wof:placetype":"venue"
},
  "geometry": {"coordinates":[-3.8798971176,36.7474746704],"type":"Point"}
}