{
  "type": "Feature",
  "properties": {
    "addr:full":"Calle de Guadiamar, 17 Palomares Rio Sevilla 41928",
    "addr:housenumber":"17",
    "addr:postcode":"41928",
    "addr:street":"Calle De Guadiamar;Rio Sevilla",
    "iso:country":"ES",
    "sg:address":"Calle de Guadiamar, 17",
    "sg:city":"Palomares Rio",
    "sg:orig_category":"Asesor\u00cda Sobre Comunicaci\u00d3n De Empresas",
    "sg:phone":"+34 955 76 42 76",
    "sg:postcode":"41928",
    "sg:province":"Sevilla",
    "wof:name":"Asesoramiento Y Gestion Sanfer S.l.",
    "wof:placetype":"venue"
},
  "geometry": {"coordinates":[-6.05742836,37.2803535461],"type":"Point"}
}