{
  "type": "Feature",
  "properties": {
    "addr:full":"Alam Colon, 21 Carmen Murcia 30002",
    "addr:housenumber":"21",
    "addr:postcode":"30002",
    "addr:street":"Alam Colon",
    "iso:country":"ES",
    "sg:address":"Alam Colon, 21",
    "sg:city":"Carmen",
    "sg:orig_category":"Cajas De Ahorro",
    "sg:phone":"+34 968 21 44 10",
    "sg:postcode":"30002",
    "sg:province":"Murcia",
    "wof:name":"Caja De Ahorros Del Mediterraneo",
    "wof:placetype":"venue"
},
  "geometry": {"coordinates":[-1.1302499771,37.9829597473],"type":"Point"}
}