{
  "type": "Feature",
  "properties": {
    "addr:full":"Avda Valencia, 9 Viver Castell\u00f3n 12460",
    "addr:housenumber":"9",
    "addr:postcode":"12460",
    "addr:street":"Avda Valencia",
    "iso:country":"ES",
    "sg:address":"Avda Valencia, 9",
    "sg:city":"Viver",
    "sg:orig_category":"Alimentaci\u00d3n General (al Por Menor)",
    "sg:phone":"+34 964 14 10 58",
    "sg:postcode":"12460",
    "sg:province":"Castell\u00f3n",
    "wof:name":"Bovihel Los Chaneros S.l",
    "wof:placetype":"venue"
},
  "geometry": {"coordinates":[-0.5982480049,39.9199256897],"type":"Point"}
}