{
  "type": "Feature",
  "properties": {
    "addr:full":"Av Argentina, 93 S. Andreu Barca Barcelona 08740",
    "addr:housenumber":"93",
    "addr:postcode":"08740",
    "addr:street":"Av Argentina;S. Andreu;Barcelona",
    "iso:country":"ES",
    "sg:address":"Av Argentina, 93",
    "sg:city":"S. Andreu Barca",
    "sg:orig_category":"Suministros Y Materiales Industriales",
    "sg:phone":"+34 936 53 54 45",
    "sg:postcode":"08740",
    "sg:province":"Barcelona",
    "sg:website":"www.ibermax.net",
    "wof:name":"Ibermax Suministradora Tecnica Industrial S.l.",
    "wof:placetype":"venue"
},
  "geometry": {"coordinates":[1.979755044,41.445148468],"type":"Point"}
}