{
  "type": "Feature",
  "properties": {
    "iso:country":"ES",
    "sg:address":"Calle de Juan Bravo, 2",
    "sg:city":"Madrid",
    "sg:orig_category":"Laboratorios",
    "sg:phone":"+34 914 31 24 80",
    "sg:postcode":"28006",
    "sg:province":"Madrid",
    "wof:name":"Cordlife S.l.",
    "wof:placetype":"venue"
},
  "geometry": {"coordinates":[-3.6866259575,40.4330635071],"type":"Point"}
}