{
  "type": "Feature",
  "properties": {
    "iso:country":"ES",
    "sg:address":"Avgd Blondel, 14",
    "sg:city":"Lleida",
    "sg:orig_category":"Confiter\u00cdas, Chocolater\u00cdas (al Por Menor)",
    "sg:phone":"+34 973 23 79 03",
    "sg:postcode":"25002",
    "sg:province":"Lleida",
    "wof:name":"Farre Serveto Jose",
    "wof:placetype":"venue"
},
  "geometry": {"coordinates":[0.6258569956,41.6138496399],"type":"Point"}
}