{
  "type": "Feature",
  "properties": {
    "iso:country":"ES",
    "sg:address":"Ctra Alcaparrosa, Km. 0002,8",
    "sg:city":"Pe\u00f1allana",
    "sg:orig_category":"Florister\u00cdas",
    "sg:phone":"+34 953 54 90 50",
    "sg:postcode":"23740",
    "sg:province":"Ja\u00e9n",
    "wof:name":"Cantudo Chamocho Pedro",
    "wof:placetype":"venue"
},
  "geometry": {"coordinates":[-4.057518959,38.0386962891],"type":"Point"}
}