{
  "type": "Feature",
  "properties": {
    "addr:full":"Carrer de Granada Del Penedes, 19 Barcelona Barcelona 08006",
    "addr:housenumber":"19",
    "addr:postcode":"08006",
    "addr:street":"Carrer De Granada Del Penedes",
    "iso:country":"ES",
    "sg:address":"Carrer de Granada Del Penedes, 19",
    "sg:city":"Barcelona",
    "sg:orig_category":"Arquitectos",
    "sg:phone":"+34 932 18 53 92",
    "sg:postcode":"08006",
    "sg:province":"Barcelona",
    "wof:name":"Corbin Ogallar Cecilia",
    "wof:placetype":"venue"
},
  "geometry": {"coordinates":[2.1526129246,41.3967170715],"type":"Point"}
}