{
  "type": "Feature",
  "properties": {
    "iso:country":"ES",
    "sg:address":"Ctra Alcoy, Km. 0016,0",
    "sg:city":"Ibi",
    "sg:orig_category":"Restaurantes",
    "sg:phone":"+34 966 55 40 91",
    "sg:postcode":"03440",
    "sg:province":"Alicante",
    "wof:name":"Restaurante Serafines S.l.",
    "wof:placetype":"venue"
},
  "geometry": {"coordinates":[-0.5780689716,38.6202316284],"type":"Point"}
}