{
  "type": "Feature",
  "properties": {
    "addr:full":"Trva Laurel, 3 Logro\u00f1o La Rioja 26001",
    "addr:housenumber":"3",
    "addr:postcode":"26001",
    "addr:street":"Trva Laurel;Rioja",
    "iso:country":"ES",
    "sg:address":"Trva Laurel, 3",
    "sg:city":"Logro\u00f1o",
    "sg:orig_category":"Molduras, Junquillos, Listones Y Molduras Perforadas",
    "sg:phone":"+34 941 22 00 67",
    "sg:postcode":"26001",
    "sg:province":"La Rioja",
    "wof:name":"Olivan Saenz Vicente",
    "wof:placetype":"venue"
},
  "geometry": {"coordinates":[-2.4492740631,42.4654998779],"type":"Point"}
}