{
  "type": "Feature",
  "properties": {
    "iso:country":"ES",
    "sg:address":"Calle de Angeles, 40",
    "sg:city":"Villafranco Guadiana",
    "sg:orig_category":"Alimentaci\u00d3n General (al Por Menor)",
    "sg:phone":"+34 924 44 37 15",
    "sg:postcode":"06195",
    "sg:province":"Badajoz",
    "wof:name":"La Casa Naranja C.b.",
    "wof:placetype":"venue"
},
  "geometry": {"coordinates":[-6.8606920242,38.8842544556],"type":"Point"}
}