{
  "type": "Feature",
  "properties": {
    "iso:country":"ES",
    "sg:address":"Avda D Rguez Aragon, 3",
    "sg:city":"Malaga",
    "sg:classifiers":[
        {
            "category":"Banks & Credit Unions",
            "subcategory":"Bureau De Change",
            "type":"Services"
        }
    ],
    "sg:phone":"+34 952 33 40 74",
    "sg:postcode":"29010",
    "sg:province":"M\u00e1laga",
    "sg:tags":[
        "organismos",
        "control"
    ],
    "sg:website":"www.eurocontrol.es",
    "wof:name":"Eurocontrol S.a.",
    "wof:placetype":"venue"
},
  "geometry": {"coordinates":[-4.4831008911,36.75157547],"type":"Point"}
}