{
  "type": "Feature",
  "properties": {
    "iso:country":"ES",
    "sg:address":"Pernaviva, 47",
    "sg:city":"Pernaviva",
    "sg:orig_category":"Art\u00cdculos De Madera (fabricaci\u00d3n Y Al Por Mayor)",
    "sg:phone":"+34 986 57 28 99",
    "sg:postcode":"36687",
    "sg:province":"Pontevedra",
    "wof:name":"Fabrica De Muebles Jofer S.l.",
    "wof:placetype":"venue"
},
  "geometry": {"coordinates":[-8.4347791672,42.6690101624],"type":"Point"}
}