{
  "type": "Feature",
  "properties": {
    "addr:full":"Avda Tenor Fleta, 19 Zaragoza Zaragoza 50008",
    "addr:housenumber":"19",
    "addr:postcode":"50008",
    "addr:street":"Avda Tenor Fleta",
    "iso:country":"ES",
    "sg:address":"Avda Tenor Fleta, 19",
    "sg:city":"Zaragoza",
    "sg:orig_category":"Farmacias",
    "sg:phone":"+34 976 21 34 69",
    "sg:postcode":"50008",
    "sg:province":"Zaragoza",
    "wof:name":"Aznar Doblado Irene",
    "wof:placetype":"venue"
},
  "geometry": {"coordinates":[-0.8841500282,41.6412773132],"type":"Point"}
}