{
  "type": "Feature",
  "properties": {
    "addr:full":"Calle de Santa Lucia, 34 Haro La Rioja 26200",
    "addr:housenumber":"34",
    "addr:postcode":"26200",
    "addr:street":"Calle De Santa Lucia",
    "iso:country":"ES",
    "sg:address":"Calle de Santa Lucia, 34",
    "sg:city":"Haro",
    "sg:orig_category":"Comercio De Piezas De Recambio Y De Accesorios De Veh\u00cdculos, Veh\u00cdculos Industriales",
    "sg:phone":"+34 941 30 34 39",
    "sg:postcode":"26200",
    "sg:province":"La Rioja",
    "wof:name":"Tubilleja Garcia Milagros",
    "wof:placetype":"venue"
},
  "geometry": {"coordinates":[-2.847574234,42.573890686],"type":"Point"}
}