{
  "type": "Feature",
  "properties": {
    "addr:full":"Calle de Palma (de La), 6 Pto Real C\u00e1diz 11510",
    "addr:housenumber":"6",
    "addr:postcode":"11510",
    "addr:street":"Calle De Palma De La;Ca\u0301Diz",
    "iso:country":"ES",
    "sg:address":"Calle de Palma (de La), 6",
    "sg:city":"Pto Real",
    "sg:orig_category":"M\u00c9dicos: Estomatolog\u00cda",
    "sg:phone":"+34 956 83 42 47",
    "sg:postcode":"11510",
    "sg:province":"C\u00e1diz",
    "wof:name":"Bragado Dominguez Miguel Angel",
    "wof:placetype":"venue"
},
  "geometry": {"coordinates":[-6.1898407936,36.5265045166],"type":"Point"}
}