{
  "type": "Feature",
  "properties": {
    "iso:country":"ES",
    "sg:address":"Calle de Palma (de La), 6",
    "sg:city":"Pto Real",
    "sg:orig_category":"M\u00c9dicos: Estomatolog\u00cda",
    "sg:phone":"+34 956 83 42 47",
    "sg:postcode":"11510",
    "sg:province":"C\u00e1diz",
    "wof:name":"Bragado Dominguez Miguel Angel",
    "wof:placetype":"venue"
},
  "geometry": {"coordinates":[-6.1898407936,36.5265045166],"type":"Point"}
}