{
  "type": "Feature",
  "properties": {
    "iso:country":"ES",
    "sg:address":"Cmno Traviesa, 39",
    "sg:city":"Pinar De Antequera",
    "sg:orig_category":"Artes Gr\u00c1ficas, Artes Pl\u00c1sticas (curso)",
    "sg:phone":"+34 983 24 95 71",
    "sg:postcode":"47153",
    "sg:province":"Valladolid",
    "wof:name":"Simon Martinez Jesus",
    "wof:placetype":"venue"
},
  "geometry": {"coordinates":[-4.75248909,41.5910186768],"type":"Point"}
}