{
  "type": "Feature",
  "properties": {
    "addr:full":"Avda Juan Carlos I, 29 Estacion Madrid 28400",
    "addr:housenumber":"29",
    "addr:postcode":"28400",
    "addr:street":"Avda Juan Carlos I",
    "iso:country":"ES",
    "sg:address":"Avda Juan Carlos I, 29",
    "sg:city":"Estacion",
    "sg:orig_category":"Papeler\u00cdas: Art\u00cdculos (al Por Mayor)",
    "sg:phone":"+34 918 49 32 34",
    "sg:postcode":"28400",
    "sg:province":"Madrid",
    "sg:website":"www.carlin.es",
    "wof:name":"Ofimarket De La Sierra S.l.",
    "wof:placetype":"venue"
},
  "geometry": {"coordinates":[-3.9919650555,40.6455612183],"type":"Point"}
}