{
  "type": "Feature",
  "properties": {
    "addr:full":"Carrer de Guadiana, 14 Torre-romeu Barcelona 08202",
    "addr:housenumber":"14",
    "addr:postcode":"08202",
    "addr:street":"Carrer De Guadiana;Barcelona",
    "iso:country":"ES",
    "sg:address":"Carrer de Guadiana, 14",
    "sg:city":"Torre-romeu",
    "sg:orig_category":"Peluquer\u00cdas, Peluquer\u00cda Mixta",
    "sg:phone":"+34 937 25 98 17",
    "sg:postcode":"08202",
    "sg:province":"Barcelona",
    "wof:name":"Casanova Ruz Sandra",
    "wof:placetype":"venue"
},
  "geometry": {"coordinates":[2.1390559673,41.3745880127],"type":"Point"}
}