{
  "type": "Feature",
  "properties": {
    "addr:full":"Calle de Rufino Blanco, 7 Guadalajara Guadalajara 19002",
    "addr:housenumber":"7",
    "addr:postcode":"19002",
    "addr:street":"Calle De Rufino Blanco",
    "iso:country":"ES",
    "sg:address":"Calle de Rufino Blanco, 7",
    "sg:city":"Guadalajara",
    "sg:orig_category":"Ropa Y Art\u00cdculos Pre",
    "sg:phone":"+34 949 24 89 73",
    "sg:postcode":"19002",
    "sg:province":"Guadalajara",
    "sg:website":"www.somospapas.com",
    "wof:name":"Somos Papas C.b.",
    "wof:placetype":"venue"
},
  "geometry": {"coordinates":[-3.1657314301,40.626373291],"type":"Point"}
}