{
  "type": "Feature",
  "properties": {
    "addr:full":"Avda Orense (de), 80 Forte Pontevedra 36940",
    "addr:housenumber":"80",
    "addr:postcode":"36940",
    "addr:street":"Avda Orense De",
    "iso:country":"ES",
    "sg:address":"Avda Orense (de), 80",
    "sg:city":"Forte",
    "sg:orig_category":"Molduras, Junquillos, Listones Y Molduras Perforadas",
    "sg:phone":"+34 986 30 46 65",
    "sg:postcode":"36940",
    "sg:province":"Pontevedra",
    "wof:name":"Chapela Santos Maria Cristina",
    "wof:placetype":"venue"
},
  "geometry": {"coordinates":[-8.8184690475,42.2742500305],"type":"Point"}
}