{
  "type": "Feature",
  "properties": {
    "addr:full":"Calle de Lerida, 1 Logro\u00f1o La Rioja 26006",
    "addr:housenumber":"1",
    "addr:postcode":"26006",
    "addr:street":"Calle De Lerida;Rioja",
    "iso:country":"ES",
    "sg:address":"Calle de Lerida, 1",
    "sg:city":"Logro\u00f1o",
    "sg:orig_category":"Lencer\u00cda Femenina, Corseter\u00cda, Trajes De Ba\u00d1o (al Por Menor)",
    "sg:phone":"+34 941 25 32 59",
    "sg:postcode":"26006",
    "sg:province":"La Rioja",
    "wof:name":"Oysho Espa\u00d1a S.a.",
    "wof:placetype":"venue"
},
  "geometry": {"coordinates":[-2.4207389355,42.4621391296],"type":"Point"}
}