{
  "type": "Feature",
  "properties": {
    "iso:country":"ES",
    "sg:address":"Calle de Cruz De Los Angeles, 3",
    "sg:city":"Trujillo",
    "sg:orig_category":"Florister\u00cdas",
    "sg:phone":"+34 927 32 23 42",
    "sg:postcode":"10200",
    "sg:province":"C\u00e1ceres",
    "wof:name":"Salcedo Rubio Eva",
    "wof:placetype":"venue"
},
  "geometry": {"coordinates":[-5.8763194084,39.4645767212],"type":"Point"}
}