{
  "type": "Feature",
  "properties": {
    "addr:full":"Olite-erriberri Kalea, 1 Iru\u00f1a Navarra 31002",
    "addr:housenumber":"1",
    "addr:postcode":"31002",
    "addr:street":"Olite-Erriberri Kalea",
    "iso:country":"ES",
    "sg:address":"Olite-erriberri Kalea, 1",
    "sg:city":"Iru\u00f1a",
    "sg:orig_category":"Internados & Ense\u00d1anza Privada",
    "sg:phone":"+34 948 22 85 30",
    "sg:postcode":"31002",
    "sg:province":"Navarra",
    "wof:name":"Colegio Calasanz",
    "wof:placetype":"venue"
},
  "geometry": {"coordinates":[-1.6437540054,42.81275177],"type":"Point"}
}