{
  "type": "Feature",
  "properties": {
    "addr:full":"Avda Libertad, S/n San Miguel Murcia 30009",
    "addr:housenumber":"s / n",
    "addr:postcode":"30009",
    "addr:street":"Avda Libertad",
    "iso:country":"ES",
    "sg:address":"Avda Libertad, S/n",
    "sg:city":"San Miguel",
    "sg:orig_category":"M\u00c9dicos: An\u00c1lisis Cl\u00cdnicos",
    "sg:phone":"+34 968 29 52 15",
    "sg:postcode":"30009",
    "sg:province":"Murcia",
    "wof:name":"Hernandez Cardona Jose Luis",
    "wof:placetype":"venue"
},
  "geometry": {"coordinates":[-1.1324989796,37.989315033],"type":"Point"}
}