{
  "type": "Feature",
  "properties": {
    "addr:full":"Carrer de Balmes, 357 Barcelona Barcelona 08006",
    "addr:housenumber":"357",
    "addr:postcode":"08006",
    "addr:street":"Carrer De Balmes",
    "iso:country":"ES",
    "sg:address":"Carrer de Balmes, 357",
    "sg:city":"Barcelona",
    "sg:orig_category":"Administradores De Bienes Y Delegados De Comunidades De Propietarios",
    "sg:phone":"+34 932 12 86 58",
    "sg:postcode":"08006",
    "sg:province":"Barcelona",
    "wof:name":"Administracion De Fincas Layes S.l.",
    "wof:placetype":"venue"
},
  "geometry": {"coordinates":[2.1416933537,41.4040565491],"type":"Point"}
}