{
  "type": "Feature",
  "properties": {
    "addr:full":"Calle de Hermanos Velasco Lopez, 2 Torrelodones Madrid 28250",
    "addr:housenumber":"2",
    "addr:postcode":"28250",
    "addr:street":"Calle De Hermanos Velasco Lopez",
    "iso:country":"ES",
    "sg:address":"Calle de Hermanos Velasco Lopez, 2",
    "sg:city":"Torrelodones",
    "sg:orig_category":"Ropa Para Beb\u00c9s Y Ni\u00d1os (confecci\u00d3n, Al Por Mayor)",
    "sg:phone":"+34 918 59 44 02",
    "sg:postcode":"28250",
    "sg:province":"Madrid",
    "wof:name":"Ense\u00f1at Alvarez Almudena",
    "wof:placetype":"venue"
},
  "geometry": {"coordinates":[-3.9281380177,40.5758705139],"type":"Point"}
}