{
  "type": "Feature",
  "properties": {
    "addr:full":"Ptge Llobateras, S/n Rubi Barcelona 08191",
    "addr:housenumber":"s",
    "addr:postcode":"08191",
    "addr:street":"Ptge Llobateras;/ N",
    "iso:country":"ES",
    "sg:address":"Ptge Llobateras, S/n",
    "sg:city":"Rubi",
    "sg:orig_category":"Molduras, Junquillos, Listones Y Molduras Perforadas",
    "sg:phone":"+34 936 99 97 00",
    "sg:postcode":"08191",
    "sg:province":"Barcelona",
    "wof:name":"Mar Manel  Scp",
    "wof:placetype":"venue"
},
  "geometry": {"coordinates":[2.0353660583,41.4896392822],"type":"Point"}
}