{
  "type": "Feature",
  "properties": {
    "iso:country":"ES",
    "sg:address":"Carr Sta Paula, 3",
    "sg:city":"Igualada",
    "sg:orig_category":"Talleres De Corte Y Confecci\u00d3n",
    "sg:phone":"+34 938 04 39 30",
    "sg:postcode":"08700",
    "sg:province":"Barcelona",
    "wof:name":"Gemelvix Tall S.l.",
    "wof:placetype":"venue"
},
  "geometry": {"coordinates":[1.621860981,41.5818557739],"type":"Point"}
}