{
  "type": "Feature",
  "properties": {
    "addr:full":"Calle de Joaquin Costa, 13 Gra\u00f1en Huesca 22260",
    "addr:housenumber":"13",
    "addr:postcode":"22260",
    "addr:street":"Calle De Joaquin Costa",
    "iso:country":"ES",
    "sg:address":"Calle de Joaquin Costa, 13",
    "sg:city":"Gra\u00f1en",
    "sg:orig_category":"Fabricaci\u00d3n De Productos Textiles Sin Tejer",
    "sg:phone":"+34 974 39 00 72",
    "sg:postcode":"22260",
    "sg:province":"Huesca",
    "wof:name":"Lacruz Esteban Montserrat",
    "wof:placetype":"venue"
},
  "geometry": {"coordinates":[-0.3652279973,41.9419555664],"type":"Point"}
}