{
  "type": "Feature",
  "properties": {
    "addr:full":"Rua Pereira, S/n Cambre La Coru\u00f1a 15660",
    "addr:housenumber":"s / n",
    "addr:postcode":"15660",
    "addr:street":"Rua Pereira;La Corun\u0303A",
    "iso:country":"ES",
    "sg:address":"Rua Pereira, S/n",
    "sg:city":"Cambre",
    "sg:orig_category":"Promotores Constructores",
    "sg:phone":"+34 981 67 51 41",
    "sg:postcode":"15660",
    "sg:province":"La Coru\u00f1a",
    "wof:name":"Garrido Martinez Alberto",
    "wof:placetype":"venue"
},
  "geometry": {"coordinates":[-8.3696193695,43.3152694702],"type":"Point"}
}