{
  "type": "Feature",
  "properties": {
    "addr:full":"Pase Infanta Isabel, 15 Madrid Madrid 28014",
    "addr:housenumber":"15",
    "addr:postcode":"madrid;28014",
    "iso:country":"ES",
    "sg:address":"Pase Infanta Isabel, 15",
    "sg:city":"Madrid",
    "sg:orig_category":"Caf\u00c9s, Bares, Cervecer\u00cdas",
    "sg:phone":"+34 915 28 27 65",
    "sg:postcode":"28014",
    "sg:province":"Madrid",
    "wof:name":"Abella Fernandez Pedro",
    "wof:placetype":"venue"
},
  "geometry": {"coordinates":[-3.687499,40.406662],"type":"Point"}
}