{
  "type": "Feature",
  "properties": {
    "addr:full":"Calle de Pizarro, 1 Alba Tormes Salamanca 37800",
    "addr:housenumber":"1",
    "addr:postcode":"37800",
    "addr:street":"Calle De Pizarro",
    "iso:country":"ES",
    "sg:address":"Calle de Pizarro, 1",
    "sg:city":"Alba Tormes",
    "sg:orig_category":"Albergues",
    "sg:phone":"+34 923 30 00 89",
    "sg:postcode":"37800",
    "sg:province":"Salamanca",
    "wof:name":"Sanchez Gonzalez Jose",
    "wof:placetype":"venue"
},
  "geometry": {"coordinates":[-5.514026165,40.8264083862],"type":"Point"}
}