{
  "type": "Feature",
  "properties": {
    "addr:full":"Ctra. Arcos-jerez, Km. 0004,0 Arcos Frontera C\u00e1diz 11630",
    "addr:postcode":"11630",
    "addr:street":"Ctra. Arcos-Jerez Km. 0004,0 Arcos;Ca\u0301Diz",
    "iso:country":"ES",
    "sg:address":"Ctra. Arcos-jerez, Km. 0004,0",
    "sg:city":"Arcos Frontera",
    "sg:orig_category":"Promotores Constructores",
    "sg:phone":"+34 956 70 26 01",
    "sg:postcode":"11630",
    "sg:province":"C\u00e1diz",
    "wof:name":"Construcciones Francisco Manzano S.l.",
    "wof:placetype":"venue"
},
  "geometry": {"coordinates":[-5.8115739822,36.7515716553],"type":"Point"}
}