{
  "type": "Feature",
  "properties": {
    "addr:full":"Carrer de Santa Maria, 30 Mataro Barcelona 08301",
    "addr:housenumber":"30",
    "addr:postcode":"08301",
    "addr:street":"Carrer De Santa Maria",
    "iso:country":"ES",
    "sg:address":"Carrer de Santa Maria, 30",
    "sg:city":"Mataro",
    "sg:orig_category":"Transportes Por Carretera: Lotes Completos, Mercanc\u00cdas Diversas",
    "sg:phone":"+34 937 96 22 15",
    "sg:postcode":"08301",
    "sg:province":"Barcelona",
    "wof:name":"Camp Gras Marta",
    "wof:placetype":"venue"
},
  "geometry": {"coordinates":[2.4465699196,41.5402412415],"type":"Point"}
}