{
  "type": "Feature",
  "properties": {
    "iso:country":"ES",
    "sg:address":"Calle de Ubeda, S/n",
    "sg:city":"Martos",
    "sg:orig_category":"Rectificaci\u00d3n, Mecanizado, Fresado",
    "sg:phone":"+34 953 70 27 55",
    "sg:postcode":"23600",
    "sg:province":"Ja\u00e9n",
    "wof:name":"Metalter Sur S.l.",
    "wof:placetype":"venue"
},
  "geometry": {"coordinates":[-3.9686689377,37.7080993652],"type":"Point"}
}