{
  "type": "Feature",
  "properties": {
    "iso:country":"ES",
    "sg:address":"Calle de Martires, 13",
    "sg:city":"Torrelavega",
    "sg:orig_category":"Psic\u00d3logos",
    "sg:phone":"+34 942 80 15 83",
    "sg:postcode":"39300",
    "sg:province":"Cantabria",
    "wof:name":"Gonzalez Mediavilla Juan Jose",
    "wof:placetype":"venue"
},
  "geometry": {"coordinates":[-4.0484690666,43.3521728516],"type":"Point"}
}