{
  "type": "Feature",
  "properties": {
    "iso:country":"ES",
    "sg:address":"Avda El Ferrol, 2",
    "sg:city":"Madrid",
    "sg:orig_category":"Cl\u00cdnicas M\u00c9dicas",
    "sg:phone":"+34 913 23 55 56",
    "sg:postcode":"28029",
    "sg:province":"Madrid",
    "wof:name":"C.c.b.world S.l.",
    "wof:placetype":"venue"
},
  "geometry": {"coordinates":[-3.7031259537,40.4746551514],"type":"Point"}
}