{
  "type": "Feature",
  "properties": {
    "addr:full":"Calle de San Benito, 19 Cazalla Sierra Sevilla 41370",
    "addr:housenumber":"19",
    "addr:postcode":"41370",
    "addr:street":"Calle De San Benito",
    "iso:country":"ES",
    "sg:address":"Calle de San Benito, 19",
    "sg:city":"Cazalla Sierra",
    "sg:orig_category":"Agentes, Concesionarios Y Sucursales De Veh\u00cdculos",
    "sg:phone":"+34 954 88 33 54",
    "sg:postcode":"41370",
    "sg:province":"Sevilla",
    "wof:name":"Mayo Cabrera Dolores",
    "wof:placetype":"venue"
},
  "geometry": {"coordinates":[-5.7614941597,37.9278259277],"type":"Point"}
}