{
  "type": "Feature",
  "properties": {
    "addr:full":"Calle de Guillermo Vizcaino, 6 Pozoblanco C\u00f3rdoba 14400",
    "addr:housenumber":"6",
    "addr:postcode":"14400",
    "addr:street":"Calle De Guillermo Vizcaino",
    "iso:country":"ES",
    "sg:address":"Calle de Guillermo Vizcaino, 6",
    "sg:city":"Pozoblanco",
    "sg:orig_category":"Agencias De Viajes",
    "sg:phone":"+34 957 13 20 00",
    "sg:postcode":"14400",
    "sg:province":"C\u00f3rdoba",
    "sg:website":"www.marsans.es",
    "wof:name":"Viajes Marsans S.a.",
    "wof:placetype":"venue"
},
  "geometry": {"coordinates":[-4.8492288589,38.3810462952],"type":"Point"}
}