{
  "type": "Feature",
  "properties": {
    "iso:country":"ES",
    "sg:address":"Carr Comer\u00c7, 20",
    "sg:city":"Angles",
    "sg:orig_category":"Ropa Para Caballeros (al Por Menor)",
    "sg:phone":"+34 972 42 03 11",
    "sg:postcode":"17160",
    "sg:province":"Girona",
    "wof:name":"Rigau Caballe Isabel",
    "wof:placetype":"venue"
},
  "geometry": {"coordinates":[2.6347820759,41.9582252502],"type":"Point"}
}