{
  "type": "Feature",
  "properties": {
    "iso:country":"ES",
    "sg:address":"Poli Industrial, 50",
    "sg:city":"Guarnizo",
    "sg:orig_category":"Sales (al Por Mayor)",
    "sg:phone":"+34 942 54 41 16",
    "sg:postcode":"39611",
    "sg:province":"Cantabria",
    "wof:name":"Herreros Puenter Javier",
    "wof:placetype":"venue"
},
  "geometry": {"coordinates":[-3.8271050453,43.4014930725],"type":"Point"}
}