{
  "type": "Feature",
  "properties": {
    "iso:country":"ES",
    "sg:address":"Carrer de Handbol, 38",
    "sg:city":"Rubi",
    "sg:orig_category":"Delegados, Agentes De Tr\u00c1nsito, Auxiliares De Transporte Internacional",
    "sg:phone":"+34 936 99 06 91",
    "sg:postcode":"08191",
    "sg:province":"Barcelona",
    "wof:name":"Moreno Pardillos Gerardo",
    "wof:placetype":"venue"
},
  "geometry": {"coordinates":[2.0400440693,41.5009765625],"type":"Point"}
}