{
  "type": "Feature",
  "properties": {
    "addr:full":"Calle de General Luque, 42 Almeria Almer\u00eda 04002",
    "addr:housenumber":"42",
    "addr:postcode":"04002",
    "addr:street":"Calle De General Luque",
    "iso:country":"ES",
    "sg:address":"Calle de General Luque, 42",
    "sg:city":"Almeria",
    "sg:orig_category":"Publicidad (soportes Y Gesti\u00d3n)",
    "sg:phone":"+34 950 26 44 15",
    "sg:postcode":"04002",
    "sg:province":"Almer\u00eda",
    "wof:name":"Gil Martinez Manuel",
    "wof:placetype":"venue"
},
  "geometry": {"coordinates":[-2.4738709927,36.8382987976],"type":"Point"}
}