{
  "type": "Feature",
  "properties": {
    "addr:full":"Plaz Doctor Sanchez Ca\u00d1as, S/n Alguazas Murcia 30560",
    "addr:housenumber":"/ n",
    "addr:postcode":"30560",
    "addr:street":"Can\u0303As S",
    "iso:country":"ES",
    "sg:address":"Plaz Doctor Sanchez Ca\u00d1as, S/n",
    "sg:city":"Alguazas",
    "sg:orig_category":"Cajas De Ahorro",
    "sg:phone":"+34 968 62 06 78",
    "sg:postcode":"30560",
    "sg:province":"Murcia",
    "sg:website":"www.cajamurcia.es",
    "wof:name":"Caja De Ahorros De Murcia",
    "wof:placetype":"venue"
},
  "geometry": {"coordinates":[-1.2447190285,38.0499610901],"type":"Point"}
}