{
  "type": "Feature",
  "properties": {
    "addr:full":"Carrer de Villarroel, 113 Barcelona Barcelona 08011",
    "addr:housenumber":"113",
    "addr:postcode":"08011",
    "addr:street":"Carrer De Villarroel",
    "iso:country":"ES",
    "sg:address":"Carrer de Villarroel, 113",
    "sg:city":"Barcelona",
    "sg:orig_category":"Promotores Constructores",
    "sg:phone":"+34 934 53 42 17",
    "sg:postcode":"08011",
    "sg:province":"Barcelona",
    "wof:name":"Carbonell Reverter Eduardo",
    "wof:placetype":"venue"
},
  "geometry": {"coordinates":[2.1562950611,41.3853721619],"type":"Point"}
}