{
  "type": "Feature",
  "properties": {
    "iso:country":"ES",
    "sg:address":"Carrer de Rambla (la), 15",
    "sg:city":"Vendrell",
    "sg:orig_category":"Agentes Generales De Seguros",
    "sg:phone":"+34 977 66 76 66",
    "sg:postcode":"43700",
    "sg:province":"Tarragona",
    "wof:name":"Anfer Assegurances S.c.p.",
    "wof:placetype":"venue"
},
  "geometry": {"coordinates":[1.5367361307,41.2208366394],"type":"Point"}
}