{
  "type": "Feature",
  "properties": {
    "iso:country":"ES",
    "sg:address":"Carrer de Urgell, 2",
    "sg:city":"Manresa",
    "sg:orig_category":"Relojer\u00cda (al Por Menor, Reparaci\u00d3n)",
    "sg:phone":"+34 938 72 47 78",
    "sg:postcode":"08241",
    "sg:province":"Barcelona",
    "wof:name":"Font Morlans Acisclo",
    "wof:placetype":"venue"
},
  "geometry": {"coordinates":[1.8244639635,41.7240715027],"type":"Point"}
}