{
  "type": "Feature",
  "properties": {
    "iso:country":"ES",
    "sg:address":"Carrer de Salvador Segui, 7",
    "sg:city":"Vilafranca Penedes",
    "sg:orig_category":"Cajas De Ahorro",
    "sg:phone":"+34 938 92 38 53",
    "sg:postcode":"08720",
    "sg:province":"Barcelona",
    "wof:name":"Caixa D'estalvis Del Penedes",
    "wof:placetype":"venue"
},
  "geometry": {"coordinates":[1.7029629946,41.354839325],"type":"Point"}
}