{
  "type": "Feature",
  "properties": {
    "addr:full":"Calle de Cura, 17 Quintanar Rey Cuenca 16220",
    "addr:housenumber":"17",
    "addr:postcode":"16220",
    "addr:street":"Calle De Cura;Rey",
    "iso:country":"ES",
    "sg:address":"Calle de Cura, 17",
    "sg:city":"Quintanar Rey",
    "sg:orig_category":"Iglesia Cat\u00d3lica",
    "sg:phone":"+34 967 49 51 72",
    "sg:postcode":"16220",
    "sg:province":"Cuenca",
    "wof:name":"Parroquia San Marcos Evangelista",
    "wof:placetype":"venue"
},
  "geometry": {"coordinates":[-1.9282191992,39.3437423706],"type":"Point"}
}