{
  "type": "Feature",
  "properties": {
    "iso:country":"ES",
    "sg:address":"Avda Juan Carlos I, 41",
    "sg:city":"Ibi",
    "sg:orig_category":"Asesor\u00cda Fiscal Y Jur\u00cddica",
    "sg:phone":"+34 966 55 12 83",
    "sg:postcode":"03440",
    "sg:province":"Alicante",
    "wof:name":"Reche Salvador Asesores S.l.",
    "wof:placetype":"venue"
},
  "geometry": {"coordinates":[-0.5738019943,38.6229248047],"type":"Point"}
}