{
  "type": "Feature",
  "properties": {
    "iso:country":"ES",
    "sg:address":"Av Paisos Catalans, 32",
    "sg:city":"Zona Educacional",
    "sg:orig_category":"Muebles Y Accesorios Para Cocinas Y Cuartos De Ba\u00d1o (al Por Menor)",
    "sg:phone":"+34 977 20 05 15",
    "sg:postcode":"43007",
    "sg:province":"Tarragona",
    "wof:name":"Quesada Parra Manuel",
    "wof:placetype":"venue"
},
  "geometry": {"coordinates":[1.247262001,41.1339263916],"type":"Point"}
}