{
  "type": "Feature",
  "properties": {
    "iso:country":"ES",
    "sg:address":"Calle de Navarra, 12",
    "sg:city":"Bilbao",
    "sg:orig_category":"Abogados Especialistas En Derecho Mercantil",
    "sg:phone":"+34 944 23 01 50",
    "sg:postcode":"48001",
    "sg:province":"Vizcaya",
    "wof:name":"Aduanas Calvo S.a.l.",
    "wof:placetype":"venue"
},
  "geometry": {"coordinates":[-2.9268770218,43.2611618042],"type":"Point"}
}