{
  "type": "Feature",
  "properties": {
    "iso:country":"ES",
    "sg:address":"C/ Coves, 61",
    "sg:city":"Inca",
    "sg:orig_category":"Internados & Ense\u00d1anza Privada",
    "sg:phone":"+34 971 50 03 65",
    "sg:postcode":"07300",
    "sg:province":"Islas Baleares",
    "wof:name":"Escuelas Cristianas Hermanos De Las Residencia Provincial La Salle De Paterna",
    "wof:placetype":"venue"
},
  "geometry": {"coordinates":[2.909580946,39.7233848572],"type":"Point"}
}