{
  "type": "Feature",
  "properties": {
    "addr:full":"Calle de Iglesia, 1 Casas Lazaro Albacete 02329",
    "addr:housenumber":"1",
    "addr:postcode":"02329",
    "addr:street":"Calle De Iglesia",
    "iso:country":"ES",
    "sg:address":"Calle de Iglesia, 1",
    "sg:city":"Casas Lazaro",
    "sg:orig_category":"Iglesia Cat\u00d3lica",
    "sg:phone":"+34 967 36 32 40",
    "sg:postcode":"02329",
    "sg:province":"Albacete",
    "wof:name":"Obispado De Albacete",
    "wof:placetype":"venue"
},
  "geometry": {"coordinates":[-2.239262104,38.7706680298],"type":"Point"}
}