{
  "type": "Feature",
  "properties": {
    "addr:full":"Avda Plutarco, 6 Malaga M\u00e1laga 29010",
    "addr:housenumber":"6",
    "addr:postcode":"29010",
    "addr:street":"Avda Plutarco;Ma\u0301Laga",
    "iso:country":"ES",
    "sg:address":"Avda Plutarco, 6",
    "sg:city":"Malaga",
    "sg:orig_category":"Reposter\u00cdas",
    "sg:phone":"+34 952 39 24 94",
    "sg:postcode":"29010",
    "sg:province":"M\u00e1laga",
    "wof:name":"Boutique Del Pan Juan Pablo S.l.",
    "wof:placetype":"venue"
},
  "geometry": {"coordinates":[-4.4833750725,36.7201652527],"type":"Point"}
}