{
  "type": "Feature",
  "properties": {
    "addr:full":"Calle de Zaragoza, 67 Massamagrell Valencia 46130",
    "addr:housenumber":"67",
    "addr:postcode":"46130",
    "addr:street":"Calle De Zaragoza",
    "iso:country":"ES",
    "sg:address":"Calle de Zaragoza, 67",
    "sg:city":"Massamagrell",
    "sg:orig_category":"Artes Gr\u00c1ficas, Artes Pl\u00c1sticas (curso)",
    "sg:phone":"+34 961 44 54 48",
    "sg:postcode":"46130",
    "sg:province":"Valencia",
    "wof:name":"Dogabo S.l.",
    "wof:placetype":"venue"
},
  "geometry": {"coordinates":[-0.3287239969,39.5714797974],"type":"Point"}
}