{
  "type": "Feature",
  "properties": {
    "iso:country":"ES",
    "sg:address":"Car. Arbo\u00e7, S/n",
    "sg:city":"Vilanova Geltru",
    "sg:orig_category":"M\u00c1rmoles, Granitos Y Piedras Naturales",
    "sg:phone":"+34 938 14 05 17",
    "sg:postcode":"08800",
    "sg:province":"Barcelona",
    "wof:name":"Marmoles Hermanos Sanchez S.c.",
    "wof:placetype":"venue"
},
  "geometry": {"coordinates":[1.7268999815,41.2211303711],"type":"Point"}
}