{
  "type": "Feature",
  "properties": {
    "addr:full":"Rond Sant Antoni, 54 Barcelona Barcelona 08001",
    "addr:housenumber":"54",
    "addr:postcode":"08001",
    "addr:street":"Sant Antoni",
    "iso:country":"ES",
    "sg:address":"Rond Sant Antoni, 54",
    "sg:city":"Barcelona",
    "sg:orig_category":"Cer\u00c1micas: Material Y Suministros",
    "sg:phone":"+34 934 42 92 00",
    "sg:postcode":"08001",
    "sg:province":"Barcelona",
    "sg:website":"www.magrina-sa.com",
    "wof:name":"Aparatos Magri\u00f1a Y Cia S.a.",
    "wof:placetype":"venue"
},
  "geometry": {"coordinates":[2.1635284424,41.3812980652],"type":"Point"}
}