{
  "type": "Feature",
  "properties": {
    "addr:full":"Pol Ind La Zarzuela, S/n Linares Ja\u00e9n 23700",
    "addr:housenumber":"s / n",
    "addr:postcode":"23700",
    "addr:street":"Jae\u0301N",
    "iso:country":"ES",
    "sg:address":"Pol Ind La Zarzuela, S/n",
    "sg:city":"Linares",
    "sg:orig_category":"Reciclaje Y Tratamiento De Desechos Varios",
    "sg:phone":"+34 953 69 90 39",
    "sg:postcode":"23700",
    "sg:province":"Ja\u00e9n",
    "wof:name":"Retraoil S.l.",
    "wof:placetype":"venue"
},
  "geometry": {"coordinates":[-3.6356039047,38.093914032],"type":"Point"}
}