{
  "type": "Feature",
  "properties": {
    "addr:full":"Calle de Tartaneros, 8 Sanlucar De Barrameda C\u00e1diz 11540",
    "addr:housenumber":"8",
    "addr:postcode":"11540",
    "addr:street":"Calle De Tartaneros;Ca\u0301Diz",
    "iso:country":"ES",
    "sg:address":"Calle de Tartaneros, 8",
    "sg:city":"Sanlucar De Barrameda",
    "sg:orig_category":"Hoteles",
    "sg:phone":"+34 956 38 53 94",
    "sg:postcode":"11540",
    "sg:province":"C\u00e1diz",
    "wof:name":"Atalante Tres S.l.",
    "wof:placetype":"venue"
},
  "geometry": {"coordinates":[-6.3551001549,36.7797279358],"type":"Point"}
}