{
  "type": "Feature",
  "properties": {
    "iso:country":"ES",
    "sg:address":"Plaza Lehendakari Agirre, 2",
    "sg:city":"Galdakao",
    "sg:orig_category":"Ropa De Hogar (al Por Menor)",
    "sg:phone":"+34 944 57 03 22",
    "sg:postcode":"48960",
    "sg:province":"Vizcaya",
    "wof:name":"Leire Tellez Merino",
    "wof:placetype":"venue"
},
  "geometry": {"coordinates":[-2.8443589211,43.2320175171],"type":"Point"}
}