{
  "type": "Feature",
  "properties": {
    "addr:full":"Calle de Principe, 1 Gijon Asturias 33205",
    "addr:housenumber":"1",
    "addr:postcode":"33205",
    "addr:street":"Calle De Principe",
    "iso:country":"ES",
    "sg:address":"Calle de Principe, 1",
    "sg:city":"Gijon",
    "sg:orig_category":"Frutas, Legumbres Frescas Y Tempranas (al Por Menor)",
    "sg:phone":"+34 985 36 37 25",
    "sg:postcode":"33205",
    "sg:province":"Asturias",
    "wof:name":"Fernandez Ramos Maria Eva",
    "wof:placetype":"venue"
},
  "geometry": {"coordinates":[-5.6585597992,43.5370826721],"type":"Point"}
}