{
  "type": "Feature",
  "properties": {
    "addr:full":"Avda America (de), 25 Cordoba C\u00f3rdoba 14008",
    "addr:housenumber":"25",
    "addr:postcode":"14008",
    "addr:street":"Avda America De;Co\u0301Rdoba",
    "iso:country":"ES",
    "sg:address":"Avda America (de), 25",
    "sg:city":"Cordoba",
    "sg:orig_category":"C\u00c1maras De Comercio E Industria, Oficios, Agricultura",
    "sg:phone":"+34 957 47 67 10",
    "sg:postcode":"14008",
    "sg:province":"C\u00f3rdoba",
    "wof:name":"Camara Agraria Provincial",
    "wof:placetype":"venue"
},
  "geometry": {"coordinates":[-4.7846689224,37.8898086548],"type":"Point"}
}