{
  "type": "Feature",
  "properties": {
    "iso:country":"ES",
    "sg:address":"Calle de Doctor Luis Prieto, 19",
    "sg:city":"Aguilas",
    "sg:orig_category":"Reposter\u00cdas",
    "sg:phone":"+34 968 41 12 86",
    "sg:postcode":"30880",
    "sg:province":"Murcia",
    "wof:name":"Perez Rodriguez Jose Maria",
    "wof:placetype":"venue"
},
  "geometry": {"coordinates":[-1.5830088854,37.4074821472],"type":"Point"}
}