{
  "type": "Feature",
  "properties": {
    "iso:country":"ES",
    "sg:address":"Calle de Veronicas, 4",
    "sg:city":"San Pedro",
    "sg:orig_category":"Confecci\u00d3n : Material, Suministros Y Accesorios",
    "sg:phone":"+34 968 21 37 23",
    "sg:postcode":"30004",
    "sg:province":"Murcia",
    "wof:name":"Fages Garrido Silvestre",
    "wof:placetype":"venue"
},
  "geometry": {"coordinates":[-1.1343950033,37.9838943481],"type":"Point"}
}