{
  "type": "Feature",
  "properties": {
    "addr:full":"Calle de Cuenca, 5 Albacete Albacete 02002",
    "addr:housenumber":"5",
    "addr:postcode":"02002",
    "addr:street":"Calle De Cuenca",
    "iso:country":"ES",
    "sg:address":"Calle de Cuenca, 5",
    "sg:city":"Albacete",
    "sg:orig_category":"Agentes Generales De Seguros",
    "sg:phone":"+34 967 50 36 58",
    "sg:postcode":"02002",
    "sg:province":"Albacete",
    "wof:name":"Corcoles Quesada Maria",
    "wof:placetype":"venue"
},
  "geometry": {"coordinates":[-1.8573609591,38.9849510193],"type":"Point"}
}