{
  "type": "Feature",
  "properties": {
    "addr:full":"Calle de Villamediana, 26 Logro\u00f1o La Rioja 26003",
    "addr:housenumber":"26",
    "addr:postcode":"26003",
    "addr:street":"Calle De Villamediana;Rioja",
    "iso:country":"ES",
    "sg:address":"Calle de Villamediana, 26",
    "sg:city":"Logro\u00f1o",
    "sg:orig_category":"Reposter\u00cdas",
    "sg:phone":"+34 941 25 91 70",
    "sg:postcode":"26003",
    "sg:province":"La Rioja",
    "wof:name":"Panificadora Rubio S.cv.",
    "wof:placetype":"venue"
},
  "geometry": {"coordinates":[-2.4405069351,42.4606895447],"type":"Point"}
}