{
  "type": "Feature",
  "properties": {
    "addr:full":"Ctra Vizcaina, 34 Gijon Asturias 33207",
    "addr:housenumber":"34",
    "addr:postcode":"33207",
    "addr:street":"Ctra Vizcaina",
    "iso:country":"ES",
    "sg:address":"Ctra Vizcaina, 34",
    "sg:city":"Gijon",
    "sg:orig_category":"Escaparatistas, Decoradores",
    "sg:phone":"+34 985 35 23 28",
    "sg:postcode":"33207",
    "sg:province":"Asturias",
    "wof:name":"Pi\u00f1era Suarez Luis Gonzalo",
    "wof:placetype":"venue"
},
  "geometry": {"coordinates":[-5.67085886,43.5393218994],"type":"Point"}
}