{
  "type": "Feature",
  "properties": {
    "addr:full":"Carretera De Torremayor Montijo, Km. 0001,5 Torremayor Badajoz 06880",
    "addr:postcode":"06880",
    "addr:street":"Carretera De Torremayor Montijo Km. 0001,5",
    "iso:country":"ES",
    "sg:address":"Carretera De Torremayor Montijo, Km. 0001,5",
    "sg:city":"Torremayor",
    "sg:orig_category":"Florister\u00cdas",
    "sg:phone":"+34 924 45 03 15",
    "sg:postcode":"06880",
    "sg:province":"Badajoz",
    "wof:name":"Viveros Guadiana S.l.",
    "wof:placetype":"venue"
},
  "geometry": {"coordinates":[-6.6012554169,38.9089736938],"type":"Point"}
}