{
  "type": "Feature",
  "properties": {
    "addr:full":"Camino De Las Canteras, 13 Jamilena Ja\u00e9n 23658",
    "addr:housenumber":"13",
    "addr:postcode":"23658",
    "addr:street":"Camino De Las Canteras",
    "iso:country":"ES",
    "sg:address":"Camino De Las Canteras, 13",
    "sg:city":"Jamilena",
    "sg:orig_category":"Empresas De Carpinter\u00cda De Madera",
    "sg:phone":"+34 953 56 61 13",
    "sg:postcode":"23658",
    "sg:province":"Ja\u00e9n",
    "wof:name":"Martinez Moreno Manuel",
    "wof:placetype":"venue"
},
  "geometry": {"coordinates":[-3.9169139862,37.749080658],"type":"Point"}
}