{
  "type": "Feature",
  "properties": {
    "iso:country":"ES",
    "sg:address":"Calle de Plomo, 3",
    "sg:city":"Valladolid",
    "sg:orig_category":"Transportes Por V\u00cdas Navegables",
    "sg:phone":"+34 983 34 05 74",
    "sg:postcode":"47012",
    "sg:province":"Valladolid",
    "wof:name":"Giraud Iberica S.a.",
    "wof:placetype":"venue"
},
  "geometry": {"coordinates":[-4.7069649696,41.6094703674],"type":"Point"}
}