{
  "type": "Feature",
  "properties": {
    "iso:country":"ES",
    "sg:address":"Carrer de Botanica, 39",
    "sg:city":"Hospitalet Llobregat",
    "sg:orig_category":"Ferreter\u00cda (diversos)",
    "sg:phone":"+34 932 64 36 30",
    "sg:postcode":"08908",
    "sg:province":"Barcelona",
    "sg:website":"www.ribafarre.com",
    "wof:name":"Comercial Riba Farre S. A.",
    "wof:placetype":"venue"
},
  "geometry": {"coordinates":[2.1301000118,41.3514099121],"type":"Point"}
}