{
  "type": "Feature",
  "properties": {
    "iso:country":"ES",
    "sg:address":"Ctra. De Jaen, S/n",
    "sg:city":"Baeza",
    "sg:orig_category":"Restaurantes",
    "sg:phone":"+34 953 74 01 26",
    "sg:postcode":"23440",
    "sg:province":"Ja\u00e9n",
    "wof:name":"Perales Jimenez Matias",
    "wof:placetype":"venue"
},
  "geometry": {"coordinates":[-3.475249052,37.9983596802],"type":"Point"}
}