{
  "type": "Feature",
  "properties": {
    "iso:country":"ES",
    "sg:address":"Avda Alcalde Cantos Ropero, S/n",
    "sg:city":"Jerez De La Frontera",
    "sg:orig_category":"Ense\u00d1anza Variada",
    "sg:phone":"+34 956 14 71 35",
    "sg:postcode":"11408",
    "sg:province":"C\u00e1diz",
    "wof:name":"Centro De Formacion Profesional Abisur S.l.",
    "wof:placetype":"venue"
},
  "geometry": {"coordinates":[-6.1276321411,36.6497344971],"type":"Point"}
}