{
  "type": "Feature",
  "properties": {
    "iso:country":"ES",
    "sg:address":"Calle de Colon, 26",
    "sg:city":"Vilamarxant",
    "sg:orig_category":"\u00d3ptica: Instrumentos (fabricaci\u00d3n)",
    "sg:phone":"+34 962 71 11 25",
    "sg:postcode":"46191",
    "sg:province":"Valencia",
    "wof:name":"Instituto Valenciano De La Vision S.l.",
    "wof:placetype":"venue"
},
  "geometry": {"coordinates":[-0.6228517294,39.5684890747],"type":"Point"}
}