{
  "type": "Feature",
  "properties": {
    "addr:full":"Calle de Cordillera De Cuera, 13 Madrid Madrid 28053",
    "addr:housenumber":"13",
    "addr:postcode":"madrid;28053",
    "addr:street":"Calle De Cordillera De Cuera",
    "iso:country":"ES",
    "sg:address":"Calle de Cordillera De Cuera, 13",
    "sg:city":"Madrid",
    "sg:orig_category":"Ropa Para Se\u00d1oras Y Caballeros (al Por Menor)",
    "sg:phone":"+34 914 77 36 68",
    "sg:postcode":"28053",
    "sg:province":"Madrid",
    "wof:name":"Perez De Rojas Campos Enrique",
    "wof:placetype":"venue"
},
  "geometry": {"coordinates":[-3.6683092117,40.3880882263],"type":"Point"}
}