{
  "type": "Feature",
  "properties": {
    "iso:country":"ES",
    "sg:address":"Avda Madrigueras, S/n",
    "sg:city":"Tarazona Mancha",
    "sg:orig_category":"C\u00c1maras De Comercio E Industria, Oficios, Agricultura",
    "sg:phone":"+34 967 48 00 13",
    "sg:postcode":"02100",
    "sg:province":"Albacete",
    "wof:name":"Junta De Comunidades Castilla-la Mancha",
    "wof:placetype":"venue"
},
  "geometry": {"coordinates":[-1.9072569609,39.2594718933],"type":"Point"}
}