{
  "type": "Feature",
  "properties": {
    "iso:country":"ES",
    "sg:address":"Avda Constitucion, 4",
    "sg:city":"Torrejon Ardoz",
    "sg:orig_category":"Quincaller\u00cda (al Por Menor)",
    "sg:phone":"+34 916 75 66 16",
    "sg:postcode":"28850",
    "sg:province":"Madrid",
    "wof:name":"Abastecimientos Conde S.a.",
    "wof:placetype":"venue"
},
  "geometry": {"coordinates":[-3.488581,40.454823],"type":"Point"}
}