{
  "type": "Feature",
  "properties": {
    "iso:country":"ES",
    "sg:address":"Calle de Caravaca, 11",
    "sg:city":"Valencia",
    "sg:orig_category":"M\u00c9dicos: Gastroenterolog\u00cda Y Hepatolog\u00cda (aparato Digestivo)",
    "sg:phone":"+34 963 93 30 62",
    "sg:postcode":"46021",
    "sg:province":"Valencia",
    "wof:name":"Bel Albors Francisco Javier",
    "wof:placetype":"venue"
},
  "geometry": {"coordinates":[-0.354775995,39.4732055664],"type":"Point"}
}