{
  "type": "Feature",
  "properties": {
    "iso:country":"ES",
    "sg:address":"Plaz Maestro Mateo, 3",
    "sg:city":"Coru\u00d1a",
    "sg:orig_category":"Clases De M\u00dasica Y Canto",
    "sg:phone":"+34 981 25 36 45",
    "sg:postcode":"15004",
    "sg:province":"La Coru\u00f1a",
    "wof:name":"Gil Cuesta Carlos",
    "wof:placetype":"venue"
},
  "geometry": {"coordinates":[-8.4113006592,43.3664970398],"type":"Point"}
}