{
  "type": "Feature",
  "properties": {
    "iso:country":"ES",
    "sg:address":"Calle de Ferraz, 25",
    "sg:city":"Madrid",
    "sg:orig_category":"Fabricaci\u00d3n De Muebles",
    "sg:phone":"+34 915 42 31 35",
    "sg:postcode":"28008",
    "sg:province":"Madrid",
    "wof:name":"Ares Gomez Angel Maria",
    "wof:placetype":"venue"
},
  "geometry": {"coordinates":[-3.7187790871,40.4276161194],"type":"Point"}
}