{
  "type": "Feature",
  "properties": {
    "addr:full":"Rua Bravo, 26 Devesa Pontevedra 36212",
    "addr:housenumber":"26",
    "addr:postcode":"36212",
    "addr:street":"Rua Bravo",
    "iso:country":"ES",
    "sg:address":"Rua Bravo, 26",
    "sg:city":"Devesa",
    "sg:orig_category":"Sales (al Por Mayor)",
    "sg:phone":"+34 986 24 15 97",
    "sg:postcode":"36212",
    "sg:province":"Pontevedra",
    "wof:name":"Bargiela Bargiela Cesar",
    "wof:placetype":"venue"
},
  "geometry": {"coordinates":[-8.7656679153,42.2123451233],"type":"Point"}
}