{
  "type": "Feature",
  "properties": {
    "iso:country":"ES",
    "sg:address":"Calle de Arrabal (el), Km. 0035,2",
    "sg:city":"Cedrillas",
    "sg:orig_category":"Empresarios",
    "sg:phone":"+34 978 77 40 89",
    "sg:postcode":"44147",
    "sg:province":"Teruel",
    "wof:name":"Cedrillas Construcciones S. L.",
    "wof:placetype":"venue"
},
  "geometry": {"coordinates":[-0.8582394719,40.4354667664],"type":"Point"}
}