{
  "type": "Feature",
  "properties": {
    "iso:country":"ES",
    "sg:address":"Rbla Marina, 371",
    "sg:city":"Hospitalet Llobregat",
    "sg:orig_category":"Flores Y Plantas Naturales (al Por Mayor)",
    "sg:phone":"+34 932 63 45 65",
    "sg:postcode":"08907",
    "sg:province":"Barcelona",
    "sg:website":"www.plameca.com",
    "wof:name":"Plantas Medicinales De Catalu\u00f1a S.a.",
    "wof:placetype":"venue"
},
  "geometry": {"coordinates":[2.1073100567,41.352519989],"type":"Point"}
}