{
  "type": "Feature",
  "properties": {
    "addr:full":"Carrer de Olot, S/n Terrassa Barcelona 08227",
    "addr:housenumber":"s / n",
    "addr:postcode":"08227",
    "addr:street":"Carrer De Olot",
    "iso:country":"ES",
    "sg:address":"Carrer de Olot, S/n",
    "sg:city":"Terrassa",
    "sg:orig_category":"Negocio De Materiales De Construcci\u00d3n",
    "sg:phone":"+34 937 86 11 09",
    "sg:postcode":"08227",
    "sg:province":"Barcelona",
    "wof:name":"Hortal Moreno Juan Jose",
    "wof:placetype":"venue"
},
  "geometry": {"coordinates":[2.038310051,41.5759468079],"type":"Point"}
}