{
  "type": "Feature",
  "properties": {
    "iso:country":"ES",
    "sg:address":"Calle de Lope De Vega, 10",
    "sg:city":"Fuengirola",
    "sg:orig_category":"Regalos, Souvenires (fabricaci\u00d3n, Al Por Mayor)",
    "sg:phone":"+34 952 46 80 28",
    "sg:postcode":"29640",
    "sg:province":"M\u00e1laga",
    "wof:name":"Barros  Nadir",
    "wof:placetype":"venue"
},
  "geometry": {"coordinates":[-4.6154580116,36.5501098633],"type":"Point"}
}