{
  "type": "Feature",
  "properties": {
    "iso:country":"ES",
    "sg:address":"Carrer de Londres, 5",
    "sg:city":"Rubi",
    "sg:orig_category":"Calderer\u00cda",
    "sg:phone":"+34 935 88 10 77",
    "sg:postcode":"08191",
    "sg:province":"Barcelona",
    "wof:name":"Caldereria Caiber S.c.p.",
    "wof:placetype":"venue"
},
  "geometry": {"coordinates":[2.0253629684,41.4765892029],"type":"Point"}
}