{
  "type": "Feature",
  "properties": {
    "iso:country":"ES",
    "sg:address":"Barr San Roman La Gloria, 72",
    "sg:city":"San Roman",
    "sg:orig_category":"Abogados",
    "sg:phone":"+34 942 34 67 93",
    "sg:postcode":"39012",
    "sg:province":"Cantabria",
    "wof:name":"Lopez Roldan Miguel Angel",
    "wof:placetype":"venue"
},
  "geometry": {"coordinates":[-3.8465120792,43.4617462158],"type":"Point"}
}