{
  "type": "Feature",
  "properties": {
    "iso:country":"ES",
    "sg:address":"Carrer de Pallars, 111",
    "sg:city":"Barcelona",
    "sg:orig_category":"Reparaciones Y Remolcado De Veh\u00cdculos",
    "sg:phone":"+34 934 85 53 29",
    "sg:postcode":"08018",
    "sg:province":"Barcelona",
    "wof:name":"Gruas Avila S.l.",
    "wof:placetype":"venue"
},
  "geometry": {"coordinates":[2.1915869713,41.3967781067],"type":"Point"}
}