{
  "type": "Feature",
  "properties": {
    "iso:country":"ES",
    "sg:address":"Calle de Trabajo (del), 17",
    "sg:city":"Zaragoza",
    "sg:orig_category":"Flores Y Plantas Naturales (al Por Mayor)",
    "sg:phone":"+34 976 41 74 25",
    "sg:postcode":"50008",
    "sg:province":"Zaragoza",
    "wof:name":"G. Litago Ruiz S.l.",
    "wof:placetype":"venue"
},
  "geometry": {"coordinates":[-0.8750789762,41.6432991028],"type":"Point"}
}