{
  "type": "Feature",
  "properties": {
    "addr:full":"Calle de Alberto Aguilera, 11 Madrid Madrid 28015",
    "addr:housenumber":"11",
    "addr:postcode":"madrid;28015",
    "addr:street":"Calle De Alberto Aguilera",
    "iso:country":"ES",
    "sg:address":"Calle de Alberto Aguilera, 11",
    "sg:city":"Madrid",
    "sg:orig_category":"Organismos De Turismo",
    "sg:phone":"+34 915 48 14 35",
    "sg:postcode":"28015",
    "sg:province":"Madrid",
    "sg:website":"www.tourismtunisia.com",
    "wof:name":"Oficina Nacional Tunecina Del Turismo",
    "wof:placetype":"venue"
},
  "geometry": {"coordinates":[-3.7088432312,40.4298248291],"type":"Point"}
}