{
  "type": "Feature",
  "properties": {
    "iso:country":"ES",
    "sg:address":"Errebal Kalea, 6",
    "sg:city":"Eibar",
    "sg:orig_category":"Procuradores",
    "sg:phone":"+34 943 20 60 00",
    "sg:postcode":"20600",
    "sg:province":"Guip\u00f9zcoa",
    "wof:name":"Gabilondo Lapeyra Cristina",
    "wof:placetype":"venue"
},
  "geometry": {"coordinates":[-2.4696118832,43.1859359741],"type":"Point"}
}