{
  "type": "Feature",
  "properties": {
    "iso:country":"ES",
    "sg:address":"Ctra Utrera, S/n",
    "sg:city":"Dos Hermanas",
    "sg:orig_category":"Supermercados Y Hipermercados",
    "sg:phone":"+34 955 66 56 44",
    "sg:postcode":"41700",
    "sg:province":"Sevilla",
    "wof:name":"Chacon Mu\u00d1oz Elisa",
    "wof:placetype":"venue"
},
  "geometry": {"coordinates":[-5.9174690247,37.2798805237],"type":"Point"}
}