{
  "type": "Feature",
  "properties": {
    "iso:country":"ES",
    "sg:address":"Carrer de Cardenal Tedeschini, 86",
    "sg:city":"Barcelona",
    "sg:orig_category":"Reposter\u00cdas",
    "sg:phone":"+34 932 43 16 58",
    "sg:postcode":"08027",
    "sg:province":"Barcelona",
    "wof:name":"Dase Pan S.l.",
    "wof:placetype":"venue"
},
  "geometry": {"coordinates":[2.180054903,41.4273757935],"type":"Point"}
}