{
  "type": "Feature",
  "properties": {
    "iso:country":"ES",
    "sg:address":"Calle de Real Del Arrabal, 16",
    "sg:city":"Toledo",
    "sg:orig_category":"Farmacias",
    "sg:phone":"+34 925 22 07 93",
    "sg:postcode":"45003",
    "sg:province":"Toledo",
    "wof:name":"Garcia Sancho Jose",
    "wof:placetype":"venue"
},
  "geometry": {"coordinates":[-4.0250368118,39.8617095947],"type":"Point"}
}