{
  "type": "Feature",
  "properties": {
    "iso:country":"ES",
    "sg:address":"Calle de Campoamor, 18",
    "sg:city":"Orihuela",
    "sg:orig_category":"M\u00c9dicos: Medicina General",
    "sg:phone":"+34 965 30 68 47",
    "sg:postcode":"03300",
    "sg:province":"Alicante",
    "wof:name":"Cereco Cdad",
    "wof:placetype":"venue"
},
  "geometry": {"coordinates":[-0.9430850148,38.0833587646],"type":"Point"}
}