{
  "type": "Feature",
  "properties": {
    "addr:full":"Casa Camp, 87 Vilassar Barcelona 08340",
    "addr:postcode":"08340",
    "addr:street":"Barcelona",
    "iso:country":"ES",
    "sg:address":"Casa Camp, 87",
    "sg:city":"Vilassar",
    "sg:orig_category":"Flores Y Plantas Naturales (al Por Mayor)",
    "sg:phone":"+34 937 59 18 90",
    "sg:postcode":"08340",
    "sg:province":"Barcelona",
    "wof:name":"J.serra Y Giro S.l.",
    "wof:placetype":"venue"
},
  "geometry": {"coordinates":[2.3907299042,41.5019264221],"type":"Point"}
}