{
  "type": "Feature",
  "properties": {
    "addr:full":"Ctra Alicante (de), Km. 0015,6 Santomera Murcia 30140",
    "addr:postcode":"30140",
    "addr:street":"Ctra Alicante De Km. 0015,6",
    "iso:country":"ES",
    "sg:address":"Ctra Alicante (de), Km. 0015,6",
    "sg:city":"Santomera",
    "sg:orig_category":"Empresas De Carpinter\u00cda De Madera",
    "sg:phone":"+34 968 86 45 22",
    "sg:postcode":"30140",
    "sg:province":"Murcia",
    "wof:name":"Formadera Carpinteria Lopez Y Campillo S.l.l.",
    "wof:placetype":"venue"
},
  "geometry": {"coordinates":[-1.0543140173,38.0592765808],"type":"Point"}
}