{
  "type": "Feature",
  "properties": {
    "iso:country":"ES",
    "sg:address":"Pase San Antonio (de), 10",
    "sg:city":"Cuenca",
    "sg:orig_category":"Asociaciones, Organismos Culturales Y Socioeducativos",
    "sg:phone":"+34 969 23 06 32",
    "sg:postcode":"16003",
    "sg:province":"Cuenca",
    "wof:name":"Asociacion Cultural Y Deportiva De Minusvalidos Conquenses Roosevelt",
    "wof:placetype":"venue"
},
  "geometry": {"coordinates":[-2.1375939846,40.0681915283],"type":"Point"}
}