{
  "type": "Feature",
  "properties": {
    "iso:country":"ES",
    "sg:address":"Calle de Monasterio De Samos, 32",
    "sg:city":"Zaragoza",
    "sg:orig_category":"Panader\u00cdas, Panader\u00cdas",
    "sg:phone":"+34 976 13 32 12",
    "sg:postcode":"50013",
    "sg:province":"Zaragoza",
    "wof:name":"Luna De Nata Sl",
    "wof:placetype":"venue"
},
  "geometry": {"coordinates":[-0.8717529774,41.6439476013],"type":"Point"}
}