{
  "type": "Feature",
  "properties": {
    "addr:full":"Or (poligon Ind Clota), 10 Cerdanyola Valles Barcelona 08290",
    "addr:housenumber":"10",
    "addr:postcode":"08290",
    "addr:street":"Clota;Valles Barcelona",
    "iso:country":"ES",
    "sg:address":"Or (poligon Ind Clota), 10",
    "sg:city":"Cerdanyola Valles",
    "sg:orig_category":"Tratamiento De Metales",
    "sg:phone":"+34 936 91 85 52",
    "sg:postcode":"08290",
    "sg:province":"Barcelona",
    "wof:name":"Industrias De Transformaciones Metalicas S. A.",
    "wof:placetype":"venue"
},
  "geometry": {"coordinates":[2.1325199604,41.5000114441],"type":"Point"}
}