{
  "type": "Feature",
  "properties": {
    "iso:country":"ES",
    "sg:address":"Robledal, 135",
    "sg:city":"Rivas Vaciamadrid",
    "sg:orig_category":"Edici\u00d3n De Diarios, Revistas, Boletines",
    "sg:phone":"+34 914 99 13 64",
    "sg:postcode":"28529",
    "sg:province":"Madrid",
    "wof:name":"Netalia S.l.",
    "wof:placetype":"venue"
},
  "geometry": {"coordinates":[-3.5192101002,40.3589172363],"type":"Point"}
}