{
  "type": "Feature",
  "properties": {
    "addr:full":"Carrer de Domenech, 4 Barcelona Barcelona 08012",
    "addr:housenumber":"4",
    "addr:postcode":"08012",
    "addr:street":"Carrer De Domenech",
    "iso:country":"ES",
    "sg:address":"Carrer de Domenech, 4",
    "sg:city":"Barcelona",
    "sg:orig_category":"Ense\u00d1anza: Profesiones Art\u00cdsticas",
    "sg:phone":"+34 934 15 52 02",
    "sg:postcode":"08012",
    "sg:province":"Barcelona",
    "wof:name":"Casanelles Rahola Miguel",
    "wof:placetype":"venue"
},
  "geometry": {"coordinates":[2.158602953,41.3985786438],"type":"Point"}
}