{
  "type": "Feature",
  "properties": {
    "addr:full":"Alegria, 8 Peraleda Mata C\u00e1ceres 10335",
    "addr:housenumber":"8",
    "addr:postcode":"10335",
    "addr:street":"Alegria;Ca\u0301Ceres",
    "iso:country":"ES",
    "sg:address":"Alegria, 8",
    "sg:city":"Peraleda Mata",
    "sg:classifiers":[
        {
            "category":"Taxi",
            "type":"Transportation"
        }
    ],
    "sg:phone":"+34 927 55 90 37",
    "sg:postcode":"10335",
    "sg:province":"C\u00e1ceres",
    "wof:name":"Encinas Parra Rosario",
    "wof:placetype":"venue"
},
  "geometry": {"coordinates":[-5.4591789246,39.8533592224],"type":"Point"}
}