{
  "type": "Feature",
  "properties": {
    "iso:country":"ES",
    "sg:address":"Ctra Almazora, Km. 0008,8",
    "sg:city":"Castellon De La Plana",
    "sg:orig_category":"Equipo De Refrigeraci\u00d3n Industrial",
    "sg:phone":"+34 964 25 36 51",
    "sg:postcode":"12005",
    "sg:province":"Castell\u00f3n",
    "wof:name":"Instalaciones Martorell S.l.",
    "wof:placetype":"venue"
},
  "geometry": {"coordinates":[-0.0570270009,39.9575424194],"type":"Point"}
}