{
  "type": "Feature",
  "properties": {
    "addr:full":"Avda Portugal, 44 Gijon Asturias 33207",
    "addr:housenumber":"44",
    "addr:postcode":"33207",
    "addr:street":"Avda Portugal",
    "iso:country":"ES",
    "sg:address":"Avda Portugal, 44",
    "sg:city":"Gijon",
    "sg:orig_category":"Distribuci\u00d3n De Petr\u00d3leo Y Derivados",
    "sg:phone":"+34 985 34 77 09",
    "sg:postcode":"33207",
    "sg:province":"Asturias",
    "wof:name":"Gestora Vasca De Estaciones S.a.",
    "wof:placetype":"venue"
},
  "geometry": {"coordinates":[-5.6704897881,43.5378799438],"type":"Point"}
}