{
  "type": "Feature",
  "properties": {
    "iso:country":"ES",
    "sg:address":"Calle de O'donnell, 32",
    "sg:city":"Madrid",
    "sg:orig_category":"Venta, Localizaci\u00d3n, Reparaci\u00d3n De Material E Instrumental M\u00c9dico",
    "sg:phone":"+34 914 09 50 85",
    "sg:postcode":"28009",
    "sg:province":"Madrid",
    "wof:name":"Quermed S. A.",
    "wof:placetype":"venue"
},
  "geometry": {"coordinates":[-3.674880743,40.4214363098],"type":"Point"}
}