{
  "type": "Feature",
  "properties": {
    "addr:full":"Barr Inmaculada (la), 5 Aranguren Vizcaya 48850",
    "addr:postcode":"48850",
    "addr:street":"La 5",
    "iso:country":"ES",
    "sg:address":"Barr Inmaculada (la), 5",
    "sg:city":"Aranguren",
    "sg:orig_category":"Edici\u00d3n De Diarios, Revistas, Boletines",
    "sg:phone":"+34 946 67 10 83",
    "sg:postcode":"48850",
    "sg:province":"Vizcaya",
    "wof:name":"Maxi Press Comunicacion S.a.",
    "wof:placetype":"venue"
},
  "geometry": {"coordinates":[-3.1183822155,43.2103843689],"type":"Point"}
}