{
  "type": "Feature",
  "properties": {
    "iso:country":"ES",
    "sg:address":"Avda Pedro San Martin, 2",
    "sg:city":"Santander",
    "sg:orig_category":"Art\u00cdculos De Decoraci\u00d3n",
    "sg:phone":"+34 942 34 27 52",
    "sg:postcode":"39010",
    "sg:province":"Cantabria",
    "sg:website":"www.grupojosemaria.com",
    "wof:name":"Jose Maria Muebles Decoracion S.a.",
    "wof:placetype":"venue"
},
  "geometry": {"coordinates":[-3.8269529343,43.4585952759],"type":"Point"}
}