{
  "type": "Feature",
  "properties": {
    "addr:full":"Avda Carmen Miranda, 27 Pravia Asturias 33120",
    "addr:housenumber":"27",
    "addr:postcode":"33120",
    "addr:street":"Avda Carmen Miranda",
    "iso:country":"ES",
    "sg:address":"Avda Carmen Miranda, 27",
    "sg:city":"Pravia",
    "sg:orig_category":"Sociedades, Compa\u00d1\u00cdas Aseguradoras",
    "sg:phone":"+34 985 82 27 57",
    "sg:postcode":"33120",
    "sg:province":"Asturias",
    "sg:website":"www.garsl.es",
    "wof:name":"G.a.r. Correduria De Seguros S.l.",
    "wof:placetype":"venue"
},
  "geometry": {"coordinates":[-6.1116704941,43.4881706238],"type":"Point"}
}