{
  "type": "Feature",
  "properties": {
    "addr:full":"Rua Luis Seoane (pintor), 3 Lugo Lugo 27003",
    "addr:housenumber":"3",
    "addr:postcode":"27003",
    "addr:street":"Rua Luis Seoane Pintor",
    "iso:country":"ES",
    "sg:address":"Rua Luis Seoane (pintor), 3",
    "sg:city":"Lugo",
    "sg:orig_category":"Molduras, Junquillos, Listones Y Molduras Perforadas",
    "sg:phone":"+34 982 24 60 08",
    "sg:postcode":"27003",
    "sg:province":"Lugo",
    "wof:name":"Rivas Reija Emilio",
    "wof:placetype":"venue"
},
  "geometry": {"coordinates":[-7.5604910851,43.0169677734],"type":"Point"}
}