{
  "type": "Feature",
  "properties": {
    "iso:country":"ES",
    "sg:address":"Calle de Sueca, 18",
    "sg:city":"Alzira",
    "sg:orig_category":"Veh\u00cdculos De Ocasi\u00d3n",
    "sg:phone":"+34 962 40 15 28",
    "sg:postcode":"46600",
    "sg:province":"Valencia",
    "wof:name":"Hyundai De Alzira Corbemovil S.l.",
    "wof:placetype":"venue"
},
  "geometry": {"coordinates":[-0.4302189946,39.1586151123],"type":"Point"}
}