{
  "type": "Feature",
  "properties": {
    "iso:country":"ES",
    "sg:address":"Calle de Constantino, 11",
    "sg:city":"Ejido",
    "sg:orig_category":"Empresas De Pintura Y Revestimientos",
    "sg:phone":"+34 950 48 13 31",
    "sg:postcode":"04700",
    "sg:province":"Almer\u00eda",
    "wof:name":"Sanchez Rodriguez Tomas Manuel",
    "wof:placetype":"venue"
},
  "geometry": {"coordinates":[-2.8116729259,36.7740402222],"type":"Point"}
}