{
  "type": "Feature",
  "properties": {
    "addr:full":"Barr Plaza (la), S/n Plaza Cantabria 39592",
    "addr:housenumber":"s / n",
    "addr:postcode":"39592",
    "iso:country":"ES",
    "sg:address":"Barr Plaza (la), S/n",
    "sg:city":"Plaza",
    "sg:orig_category":"Quincaller\u00cda (al Por Menor)",
    "sg:phone":"+34 942 70 50 31",
    "sg:postcode":"39592",
    "sg:province":"Cantabria",
    "wof:name":"Amieva Gutierrez Carlos",
    "wof:placetype":"venue"
},
  "geometry": {"coordinates":[-3.9878427982,43.1828384399],"type":"Point"}
}