{
  "type": "Feature",
  "properties": {
    "addr:full":"Rinaldi, 25 Iru\u00f1a Navarra 31007",
    "addr:housenumber":"25",
    "addr:postcode":"31007",
    "addr:street":"Rinaldi",
    "iso:country":"ES",
    "sg:address":"Rinaldi, 25",
    "sg:city":"Iru\u00f1a",
    "sg:orig_category":"Farmacias",
    "sg:phone":"+34 948 26 93 58",
    "sg:postcode":"31007",
    "sg:province":"Navarra",
    "wof:name":"Eduardo Y Martina Vilari\u00f1o Ariz",
    "wof:placetype":"venue"
},
  "geometry": {"coordinates":[-1.6480380297,42.8065605164],"type":"Point"}
}