{
  "type": "Feature",
  "properties": {
    "addr:full":"Esglesia, S/n Llampaies Girona 17465",
    "addr:housenumber":"s / n",
    "addr:postcode":"17465",
    "iso:country":"ES",
    "sg:address":"Esglesia, S/n",
    "sg:city":"Llampaies",
    "sg:orig_category":"Ense\u00d1anza: Profesiones Art\u00cdsticas",
    "sg:phone":"+34 972 79 41 72",
    "sg:postcode":"17465",
    "sg:province":"Girona",
    "wof:name":"Dogbuli S.l.",
    "wof:placetype":"venue"
},
  "geometry": {"coordinates":[2.9621100426,42.1228141785],"type":"Point"}
}