{
  "type": "Feature",
  "properties": {
    "iso:country":"ES",
    "sg:address":"Carrer de Santa Teresa, 3",
    "sg:city":"S. Just Desvern",
    "sg:orig_category":"Industria Qu\u00cdmica",
    "sg:phone":"+34 933 71 14 57",
    "sg:postcode":"08960",
    "sg:province":"Barcelona",
    "wof:name":"Ribe Florensa Jose",
    "wof:placetype":"venue"
},
  "geometry": {"coordinates":[2.0732560158,41.3793563843],"type":"Point"}
}