{
  "type": "Feature",
  "properties": {
    "addr:full":"Ctra Pont De Vilomara, S/n Manresa Barcelona 08240",
    "addr:housenumber":"s / n",
    "addr:postcode":"08240",
    "addr:street":"Ctra Pont De Vilomara",
    "iso:country":"ES",
    "sg:address":"Ctra Pont De Vilomara, S/n",
    "sg:city":"Manresa",
    "sg:orig_category":"Ebanister\u00cda",
    "sg:phone":"+34 938 74 53 53",
    "sg:postcode":"08240",
    "sg:province":"Barcelona",
    "sg:website":"www.ebancreati.com",
    "wof:name":"Ebanisteria D'en Botifoll Pubill S.l.",
    "wof:placetype":"venue"
},
  "geometry": {"coordinates":[1.8328150511,41.7287597656],"type":"Point"}
}