{
  "type": "Feature",
  "properties": {
    "addr:full":"Avda Virgen De Gracia, 2 Caudete Albacete 02660",
    "addr:housenumber":"2",
    "addr:postcode":"02660",
    "addr:street":"Avda Virgen De Gracia",
    "iso:country":"ES",
    "sg:address":"Avda Virgen De Gracia, 2",
    "sg:city":"Caudete",
    "sg:orig_category":"Reposter\u00cdas",
    "sg:phone":"+34 965 82 59 75",
    "sg:postcode":"02660",
    "sg:province":"Albacete",
    "wof:name":"Perez Sivo Francisco",
    "wof:placetype":"venue"
},
  "geometry": {"coordinates":[-0.9888730049,38.7036743164],"type":"Point"}
}