{
  "type": "Feature",
  "properties": {
    "iso:country":"ES",
    "sg:address":"Calle de Antonio Torres, 20",
    "sg:city":"Talavera Reina",
    "sg:orig_category":"Sociedades, Compa\u00d1\u00cdas Aseguradoras",
    "sg:phone":"+34 925 80 20 90",
    "sg:postcode":"45600",
    "sg:province":"Toledo",
    "wof:name":"Soliss Agencia De Seguros S.l.",
    "wof:placetype":"venue"
},
  "geometry": {"coordinates":[-4.8258142471,39.960773468],"type":"Point"}
}