{
  "type": "Feature",
  "properties": {
    "iso:country":"ES",
    "sg:address":"Calle de Isla Corcega, 10",
    "sg:city":"Puerto",
    "sg:orig_category":"Postigos, Persianas Y Celos\u00cdas",
    "sg:phone":"+34 962 68 16 58",
    "sg:postcode":"46520",
    "sg:province":"Valencia",
    "wof:name":"Toldos Y Persianas Mare Nostrum",
    "wof:placetype":"venue"
},
  "geometry": {"coordinates":[-0.2141163051,39.6632270813],"type":"Point"}
}