{
  "type": "Feature",
  "properties": {
    "addr:full":"Carrer de Costa I Llobera, 1 Palma Islas Baleares 07005",
    "addr:housenumber":"1",
    "addr:postcode":"07005",
    "addr:street":"Carrer De Costa I Llobera",
    "iso:country":"ES",
    "sg:address":"Carrer de Costa I Llobera, 1",
    "sg:city":"Palma",
    "sg:orig_category":"Abogados",
    "sg:phone":"+34 971 46 85 01",
    "sg:postcode":"07005",
    "sg:province":"Islas Baleares",
    "wof:name":"Estudio Juridico Balear S.l.",
    "wof:placetype":"venue"
},
  "geometry": {"coordinates":[2.6558880806,39.5738945007],"type":"Point"}
}