{
  "type": "Feature",
  "properties": {
    "addr:full":"Calle de Santa Brigida, 16 Camas Sevilla 41900",
    "addr:housenumber":"16",
    "addr:postcode":"41900",
    "addr:street":"Calle De Santa Brigida",
    "iso:country":"ES",
    "sg:address":"Calle de Santa Brigida, 16",
    "sg:city":"Camas",
    "sg:orig_category":"Librer\u00cdas",
    "sg:phone":"+34 954 39 54 64",
    "sg:postcode":"41900",
    "sg:province":"Sevilla",
    "wof:name":"Manuel Alvarez Cadena S.l.",
    "wof:placetype":"venue"
},
  "geometry": {"coordinates":[-6.034869194,37.4021987915],"type":"Point"}
}