{
  "type": "Feature",
  "properties": {
    "iso:country":"ES",
    "sg:address":"Calle de Sanguino Michel, 3",
    "sg:city":"Caceres",
    "sg:orig_category":"Administradores De Bienes Y Delegados De Comunidades De Propietarios",
    "sg:phone":"+34 927 26 02 27",
    "sg:postcode":"10001",
    "sg:province":"C\u00e1ceres",
    "wof:name":"Administracion Brias-martin S.l.",
    "wof:placetype":"venue"
},
  "geometry": {"coordinates":[-6.3812837601,39.4685707092],"type":"Point"}
}