{
  "type": "Feature",
  "properties": {
    "addr:full":"Via Augusta, 78 Barcelona Barcelona 08006",
    "addr:housenumber":"78",
    "addr:postcode":"08006",
    "addr:street":"Via Augusta",
    "iso:country":"ES",
    "sg:address":"Via Augusta, 78",
    "sg:city":"Barcelona",
    "sg:orig_category":"Tintorer\u00cdas, Limpieza En Seco",
    "sg:phone":"+34 932 17 95 69",
    "sg:postcode":"08006",
    "sg:province":"Barcelona",
    "wof:name":"Lopez Rodriguez Manuel",
    "wof:placetype":"venue"
},
  "geometry": {"coordinates":[2.1515090466,41.4004135132],"type":"Point"}
}