{
  "type": "Feature",
  "properties": {
    "addr:full":"Pl. Escuelas, S/n Maestu \u00c1lava 01120",
    "addr:housenumber":"s",
    "addr:postcode":"01120",
    "addr:street":"Pl. Escuelas;/ N Maestu A\u0301Lava",
    "iso:country":"ES",
    "sg:address":"Pl. Escuelas, S/n",
    "sg:city":"Maestu",
    "sg:orig_category":"Centros De Educaci\u00d3n Especial",
    "sg:phone":"+34 945 41 01 41",
    "sg:postcode":"01120",
    "sg:province":"\u00c1lava",
    "sg:website":"www.euskadi.net",
    "wof:name":"Gobierno Vasco-eusko Jaurlaritza",
    "wof:placetype":"venue"
},
  "geometry": {"coordinates":[-2.4471390247,42.7383117676],"type":"Point"}
}