{
  "type": "Feature",
  "properties": {
    "addr:full":"Ctra Coru\u00d1a, 17 San Cidre La Coru\u00f1a 15165",
    "addr:housenumber":"17",
    "addr:postcode":"15165",
    "addr:street":"Ctra Corun\u0303A;San Cidre La Corun\u0303A",
    "iso:country":"ES",
    "sg:address":"Ctra Coru\u00d1a, 17",
    "sg:city":"San Cidre",
    "sg:orig_category":"Agencias Y Agentes Comerciales, Representantes",
    "sg:phone":"+34 981 79 10 48",
    "sg:postcode":"15165",
    "sg:province":"La Coru\u00f1a",
    "wof:name":"Lopez Franco Manuel",
    "wof:placetype":"venue"
},
  "geometry": {"coordinates":[-8.2309961319,43.3134422302],"type":"Point"}
}