{
  "type": "Feature",
  "properties": {
    "iso:country":"ES",
    "sg:address":"Calle de Bartolome Benitez Romero, 29",
    "sg:city":"Montoro",
    "sg:orig_category":"Transporte En General",
    "sg:phone":"+34 957 16 01 08",
    "sg:postcode":"14600",
    "sg:province":"C\u00f3rdoba",
    "wof:name":"Perez Sanchez Maria",
    "wof:placetype":"venue"
},
  "geometry": {"coordinates":[-4.3853387833,38.0199050903],"type":"Point"}
}