{
  "type": "Feature",
  "properties": {
    "addr:full":"Calle de Mendivil, 35 Madrid Madrid 28038",
    "addr:housenumber":"35",
    "addr:postcode":"madrid;28038",
    "addr:street":"Calle De Mendivil",
    "iso:country":"ES",
    "sg:address":"Calle de Mendivil, 35",
    "sg:city":"Madrid",
    "sg:orig_category":"Ingenier\u00cda, Centros De Estudios (diversos)",
    "sg:phone":"+34 915 52 06 15",
    "sg:postcode":"28038",
    "sg:province":"Madrid",
    "wof:name":"Blancar Estudios Y Proyectos S.l.",
    "wof:placetype":"venue"
},
  "geometry": {"coordinates":[-3.6637849808,40.399684906],"type":"Point"}
}