{
  "type": "Feature",
  "properties": {
    "iso:country":"ES",
    "sg:address":"Calle de Greco, 28",
    "sg:city":"Salamanca",
    "sg:orig_category":"Frutas, Legumbres Frescas Y Tempranas (al Por Menor)",
    "sg:phone":"+34 923 22 03 66",
    "sg:postcode":"37004",
    "sg:province":"Salamanca",
    "wof:name":"Del Arco Garcia Manuel",
    "wof:placetype":"venue"
},
  "geometry": {"coordinates":[-5.6513228416,40.9724464417],"type":"Point"}
}