{
  "type": "Feature",
  "properties": {
    "addr:full":"Calle de Alhondiga, 37 Granada Granada 18001",
    "addr:housenumber":"37",
    "addr:postcode":"18001",
    "addr:street":"Calle De Alhondiga",
    "iso:country":"ES",
    "sg:address":"Calle de Alhondiga, 37",
    "sg:city":"Granada",
    "sg:orig_category":"Inform\u00c1tica, Ofim\u00c1tica (estudios, Asesor\u00cda, Ingenier\u00cda, Formaci\u00d3n)",
    "sg:phone":"+34 958 26 50 59",
    "sg:postcode":"18001",
    "sg:province":"Granada",
    "wof:name":"Rodriguez Leyva Antonio",
    "wof:placetype":"venue"
},
  "geometry": {"coordinates":[-3.6016931534,37.1754760742],"type":"Point"}
}