{
  "type": "Feature",
  "properties": {
    "iso:country":"ES",
    "sg:address":"Calle de Montevideo, 41",
    "sg:city":"Huelva",
    "sg:orig_category":"Alimentaci\u00d3n General (al Por Menor)",
    "sg:phone":"+34 959 15 38 55",
    "sg:postcode":"21005",
    "sg:province":"Huelva",
    "wof:name":"Morano Gomez Juan Andres",
    "wof:placetype":"venue"
},
  "geometry": {"coordinates":[-6.9441370964,37.2832489014],"type":"Point"}
}