{
  "type": "Feature",
  "properties": {
    "iso:country":"ES",
    "sg:address":"Calle de Carlos Iv, 25",
    "sg:city":"Madrid",
    "sg:orig_category":"Sociedades, Compa\u00d1\u00cdas Aseguradoras",
    "sg:phone":"+34 913 27 26 24",
    "sg:postcode":"28037",
    "sg:province":"Madrid",
    "wof:name":"V & J Javil Intermediacion S.l.",
    "wof:placetype":"venue"
},
  "geometry": {"coordinates":[-3.6174900532,40.4345741272],"type":"Point"}
}