{
  "type": "Feature",
  "properties": {
    "iso:country":"ES",
    "sg:address":"Calle de Hermosilla, 5",
    "sg:city":"Madrid",
    "sg:orig_category":"Agencias Y Agentes Comerciales, Representantes",
    "sg:phone":"+34 915 76 60 12",
    "sg:postcode":"28001",
    "sg:province":"Madrid",
    "wof:name":"Belac S.l.",
    "wof:placetype":"venue"
},
  "geometry": {"coordinates":[-3.6884040833,40.4266815186],"type":"Point"}
}