{
  "type": "Feature",
  "properties": {
    "addr:full":"Calle de Palloza, S/n Coru\u00d1a La Coru\u00f1a 15006",
    "addr:housenumber":"s",
    "addr:postcode":"15006",
    "addr:street":"Calle De Palloza;/ N Corun\u0303A La Corun\u0303A",
    "iso:country":"ES",
    "sg:address":"Calle de Palloza, S/n",
    "sg:city":"Coru\u00d1a",
    "sg:orig_category":"Distribuci\u00d3n De Petr\u00d3leo Y Derivados",
    "sg:phone":"+34 981 13 07 02",
    "sg:postcode":"15006",
    "sg:province":"La Coru\u00f1a",
    "sg:website":"www.fernandoreyero.com",
    "wof:name":"Fernando Reyero S.l.",
    "wof:placetype":"venue"
},
  "geometry": {"coordinates":[-8.4036769867,43.3587379456],"type":"Point"}
}