{
  "type": "Feature",
  "properties": {
    "iso:country":"ES",
    "sg:address":"Calle de Caceres, 18",
    "sg:city":"Madrid",
    "sg:orig_category":"Librer\u00cdas",
    "sg:phone":"+34 914 67 49 36",
    "sg:postcode":"28045",
    "sg:province":"Madrid",
    "wof:name":"Aguado Rubira Ascension",
    "wof:placetype":"venue"
},
  "geometry": {"coordinates":[-3.6964931488,40.3986854553],"type":"Point"}
}