{
  "type": "Feature",
  "properties": {
    "addr:full":"Calle de Silla Del Rey, 35 Oviedo Asturias 33013",
    "addr:housenumber":"35",
    "addr:postcode":"33013",
    "addr:street":"Calle De Silla Del Rey",
    "iso:country":"ES",
    "sg:address":"Calle de Silla Del Rey, 35",
    "sg:city":"Oviedo",
    "sg:orig_category":"Electrodom\u00c9sticos (al Por Menor)",
    "sg:phone":"+34 985 27 18 99",
    "sg:postcode":"33013",
    "sg:province":"Asturias",
    "wof:name":"Vazquez Rodriguez Pelayo",
    "wof:placetype":"venue"
},
  "geometry": {"coordinates":[-5.862349987,43.3626594543],"type":"Point"}
}