{
  "type": "Feature",
  "properties": {
    "addr:full":"Cami Mar (la), 1 Alfas Pi Alicante 03580",
    "addr:housenumber":"1",
    "addr:postcode":"03580",
    "addr:street":"Mar La",
    "iso:country":"ES",
    "sg:address":"Cami Mar (la), 1",
    "sg:city":"Alfas Pi",
    "sg:orig_category":"Asociaciones, Organismos Culturales Y Socioeducativos",
    "sg:phone":"+34 965 88 94 23",
    "sg:postcode":"03580",
    "sg:province":"Alicante",
    "sg:website":"www.lalfas.com",
    "wof:name":"Ayuntamiento De Alfaz Del Pi",
    "wof:placetype":"venue"
},
  "geometry": {"coordinates":[-0.0981089994,38.578868866],"type":"Point"}
}