{
  "type": "Feature",
  "properties": {
    "addr:full":"Riera Argentona, S/n Cabrera Mar Barcelona 08349",
    "addr:housenumber":"s",
    "addr:postcode":"08349",
    "addr:street":"Argentona;/ N Cabrera Mar Barcelona",
    "iso:country":"ES",
    "sg:address":"Riera Argentona, S/n",
    "sg:city":"Cabrera Mar",
    "sg:orig_category":"Impresiones Sobre Tela",
    "sg:phone":"+34 937 59 09 34",
    "sg:postcode":"08349",
    "sg:province":"Barcelona",
    "wof:name":"Estampunt S.l.",
    "wof:placetype":"venue"
},
  "geometry": {"coordinates":[2.4211249352,41.5273857117],"type":"Point"}
}