{
  "type": "Feature",
  "properties": {
    "addr:full":"Leyre-leire Kalea, 7 Iru\u00f1a Navarra 31002",
    "addr:housenumber":"7",
    "addr:postcode":"31002",
    "addr:street":"Leyre-Leire Kalea",
    "iso:country":"ES",
    "sg:address":"Leyre-leire Kalea, 7",
    "sg:city":"Iru\u00f1a",
    "sg:orig_category":"Restaurantes",
    "sg:phone":"+34 948 22 78 42",
    "sg:postcode":"31002",
    "sg:province":"Navarra",
    "wof:name":"Distribucion Hostelera Los Fueros S.l.",
    "wof:placetype":"venue"
},
  "geometry": {"coordinates":[-1.6390850544,42.8139762878],"type":"Point"}
}