{
  "type": "Feature",
  "properties": {
    "addr:full":"Cmno Fabrica De Loza, 16 Gijon Asturias 33212",
    "addr:housenumber":"16",
    "addr:postcode":"33212",
    "addr:street":"Cmno Fabrica De Loza",
    "iso:country":"ES",
    "sg:address":"Cmno Fabrica De Loza, 16",
    "sg:city":"Gijon",
    "sg:orig_category":"Empresas De Pintura Y Revestimientos",
    "sg:phone":"+34 985 32 37 23",
    "sg:postcode":"33212",
    "sg:province":"Asturias",
    "wof:name":"Dominguez Alcon Felipe",
    "wof:placetype":"venue"
},
  "geometry": {"coordinates":[-5.6838917732,43.5393486023],"type":"Point"}
}