{
  "type": "Feature",
  "properties": {
    "addr:full":"Ctra Huecija, S/n Alicun Almer\u00eda 04409",
    "addr:housenumber":"s",
    "addr:postcode":"04409",
    "addr:street":"Ctra Huecija;/ N Alicun Almeri\u0301A",
    "iso:country":"ES",
    "sg:address":"Ctra Huecija, S/n",
    "sg:city":"Alicun",
    "sg:orig_category":"Delegados, Agentes De Tr\u00c1nsito, Auxiliares De Transporte Internacional",
    "sg:phone":"+34 950 64 08 65",
    "sg:postcode":"04409",
    "sg:province":"Almer\u00eda",
    "wof:name":"Martinez Lopez Antonio",
    "wof:placetype":"venue"
},
  "geometry": {"coordinates":[-2.6026990414,36.9668540955],"type":"Point"}
}