{
  "type": "Feature",
  "properties": {
    "addr:full":"Carrer de Marsans I Rof, 5 Barcelona Barcelona 08032",
    "addr:housenumber":"5",
    "addr:postcode":"08032",
    "addr:street":"Carrer De Marsans;Rof",
    "iso:country":"ES",
    "sg:address":"Carrer de Marsans I Rof, 5",
    "sg:city":"Barcelona",
    "sg:orig_category":"Artesan\u00cda",
    "sg:phone":"+34 934 29 09 95",
    "sg:postcode":"08032",
    "sg:province":"Barcelona",
    "wof:name":"Torrens Rodriguez Sergi",
    "wof:placetype":"venue"
},
  "geometry": {"coordinates":[2.1546020508,41.4193267822],"type":"Point"}
}