{
  "type": "Feature",
  "properties": {
    "addr:full":"Calle de Torre, 44 Coru\u00d1a La Coru\u00f1a 15002",
    "addr:housenumber":"44",
    "addr:postcode":"15002",
    "addr:street":"Calle De Torre;Corun\u0303A",
    "iso:country":"ES",
    "sg:address":"Calle de Torre, 44",
    "sg:city":"Coru\u00d1a",
    "sg:orig_category":"Asociaciones Y Clubs Deportivos",
    "sg:phone":"+34 981 22 49 96",
    "sg:postcode":"15002",
    "sg:province":"La Coru\u00f1a",
    "wof:name":"Mi\u00f1an Garcia Pedro Alfonso",
    "wof:placetype":"venue"
},
  "geometry": {"coordinates":[-8.5979213715,42.8414230347],"type":"Point"}
}