{
  "type": "Feature",
  "properties": {
    "iso:country":"ES",
    "sg:address":"Calle de Jose Bernardo, 17",
    "sg:city":"Langreo",
    "sg:orig_category":"Vinos Y Licores (venta Al Por Menor)",
    "sg:phone":"+34 985 67 55 44",
    "sg:postcode":"33900",
    "sg:province":"Asturias",
    "wof:name":"Casta\u00f1o Menendez Marcelino",
    "wof:placetype":"venue"
},
  "geometry": {"coordinates":[-5.6692090034,43.2883987427],"type":"Point"}
}