{
  "type": "Feature",
  "properties": {
    "addr:full":"Calle de Real, S/n Charilla Ja\u00e9n 23687",
    "addr:housenumber":"s / n",
    "addr:postcode":"23687",
    "addr:street":"Calle De Real;Jae\u0301N",
    "iso:country":"ES",
    "sg:address":"Calle de Real, S/n",
    "sg:city":"Charilla",
    "sg:orig_category":"Empresas De Carpinter\u00cda",
    "sg:phone":"+34 953 58 20 25",
    "sg:postcode":"23687",
    "sg:province":"Ja\u00e9n",
    "wof:name":"Metalisteria Y Aluminios J.diaz S.l.",
    "wof:placetype":"venue"
},
  "geometry": {"coordinates":[-3.9071879387,37.4954071045],"type":"Point"}
}