{
  "type": "Feature",
  "properties": {
    "addr:full":"Calle de Ancha, 6 Mairena Alcor Sevilla 41510",
    "addr:housenumber":"6",
    "addr:postcode":"41510",
    "addr:street":"Calle De Ancha",
    "iso:country":"ES",
    "sg:address":"Calle de Ancha, 6",
    "sg:city":"Mairena Alcor",
    "sg:orig_category":"Mercer\u00cda, Lencer\u00cda (al Por Menor)",
    "sg:phone":"+34 955 94 24 03",
    "sg:postcode":"41510",
    "sg:province":"Sevilla",
    "wof:name":"Madro\u00f1al Sanchez Jose",
    "wof:placetype":"venue"
},
  "geometry": {"coordinates":[-5.7472319603,37.3731117249],"type":"Point"}
}