{
  "type": "Feature",
  "properties": {
    "iso:country":"ES",
    "sg:address":"Avda Fragoso, 69",
    "sg:city":"Vigo",
    "sg:orig_category":"Postigos, Persianas Y Celos\u00cdas",
    "sg:phone":"+34 986 23 87 17",
    "sg:postcode":"36210",
    "sg:province":"Pontevedra",
    "wof:name":"Persianas Roma S. L.",
    "wof:placetype":"venue"
},
  "geometry": {"coordinates":[-8.7357053757,42.2155952454],"type":"Point"}
}