{
  "type": "Feature",
  "properties": {
    "addr:full":"Privada, 1 Puerto Sagunto Valencia 46520",
    "addr:postcode":"46520",
    "addr:street":"Privada 1 Puerto",
    "iso:country":"ES",
    "sg:address":"Privada, 1",
    "sg:city":"Puerto Sagunto",
    "sg:orig_category":"Institutos De Belleza",
    "sg:phone":"+34 962 68 39 68",
    "sg:postcode":"46520",
    "sg:province":"Valencia",
    "wof:name":"Merlos Boria Amparo",
    "wof:placetype":"venue"
},
  "geometry": {"coordinates":[-0.2278539985,39.6646537781],"type":"Point"}
}