{
  "type": "Feature",
  "properties": {
    "addr:full":"Calle de Arroka, 6 Donostia-san Sebastian Guip\u00f9zcoa 20006",
    "addr:housenumber":"6",
    "addr:postcode":"20006",
    "addr:street":"Calle De Arroka",
    "iso:country":"ES",
    "sg:address":"Calle de Arroka, 6",
    "sg:city":"Donostia-san Sebastian",
    "sg:orig_category":"Asociaciones Y Clubs Deportivos",
    "sg:phone":"+34 943 46 67 45",
    "sg:postcode":"20006",
    "sg:province":"Guip\u00f9zcoa",
    "wof:name":"Club Deportivo Vasconia",
    "wof:placetype":"venue"
},
  "geometry": {"coordinates":[-1.9829814434,43.3143692017],"type":"Point"}
}