{
  "type": "Feature",
  "properties": {
    "addr:full":"Calle de Kalebarria, 4 Durango Vizcaya 48200",
    "addr:housenumber":"4",
    "addr:postcode":"48200",
    "addr:street":"Calle De Kalebarria",
    "iso:country":"ES",
    "sg:address":"Calle de Kalebarria, 4",
    "sg:city":"Durango",
    "sg:orig_category":"Art\u00cdculos De Decoraci\u00d3n",
    "sg:phone":"+34 944 66 86 60",
    "sg:postcode":"48200",
    "sg:province":"Vizcaya",
    "wof:name":"Maria Arroyo Ruiz",
    "wof:placetype":"venue"
},
  "geometry": {"coordinates":[-2.6303918362,43.1677360535],"type":"Point"}
}