{
  "type": "Feature",
  "properties": {
    "addr:full":"Calle de Bulgaria, 2 Madrid Madrid 28032",
    "addr:housenumber":"2",
    "addr:postcode":"28032",
    "addr:street":"Calle De Bulgaria",
    "iso:country":"ES",
    "sg:address":"Calle de Bulgaria, 2",
    "sg:city":"Madrid",
    "sg:orig_category":"Muebles Y Accesorios Para Cocinas Y Cuartos De Ba\u00d1o (al Por Menor)",
    "sg:phone":"+34 913 13 50 87",
    "sg:postcode":"28032",
    "sg:province":"Madrid",
    "sg:website":"www.industriaslodi.com",
    "wof:name":"Industrias Lodi S.l",
    "wof:placetype":"venue"
},
  "geometry": {"coordinates":[-3.6197025776,40.4195175171],"type":"Point"}
}