{
  "type": "Feature",
  "properties": {
    "iso:country":"ES",
    "sg:address":"Avda Carabancheles (de Los), 15",
    "sg:city":"Alcorcon",
    "sg:orig_category":"Administradores De Bienes Y Delegados De Comunidades De Propietarios",
    "sg:phone":"+34 916 19 08 24",
    "sg:postcode":"28921",
    "sg:province":"Madrid",
    "wof:name":"Fernandez Cano Miguel",
    "wof:placetype":"venue"
},
  "geometry": {"coordinates":[-3.8261437416,40.3510093689],"type":"Point"}
}