{
  "type": "Feature",
  "properties": {
    "addr:full":"Carr Sant Pau, 170 Figueres Girona 17600",
    "addr:housenumber":"170",
    "addr:postcode":"17600",
    "addr:street":"Carr Sant Pau",
    "iso:country":"ES",
    "sg:address":"Carr Sant Pau, 170",
    "sg:city":"Figueres",
    "sg:orig_category":"Consultor\u00cdas Diversas",
    "sg:phone":"+34 972 51 31 10",
    "sg:postcode":"17600",
    "sg:province":"Girona",
    "wof:name":"Ma Consultors Sc",
    "wof:placetype":"venue"
},
  "geometry": {"coordinates":[2.9581100941,42.2656898499],"type":"Point"}
}