{
  "type": "Feature",
  "properties": {
    "iso:country":"ES",
    "sg:address":"Calle de Romero Pozo, 11",
    "sg:city":"Velez-malaga",
    "sg:orig_category":"Asesor\u00cda Sobre Comunicaci\u00d3n De Empresas",
    "sg:phone":"+34 952 50 53 66",
    "sg:postcode":"29700",
    "sg:province":"M\u00e1laga",
    "wof:name":"Gestoria Administrativa Villar Y Burgos S.l.",
    "wof:placetype":"venue"
},
  "geometry": {"coordinates":[-4.1039838791,36.7818374634],"type":"Point"}
}