{
  "type": "Feature",
  "properties": {
    "addr:full":"Calle de Arriba, 6 Tejina Santa Cruz De Tenerife 38260",
    "addr:housenumber":"6",
    "addr:postcode":"38260",
    "addr:street":"Calle De Arriba",
    "iso:country":"ES",
    "sg:address":"Calle de Arriba, 6",
    "sg:city":"Tejina",
    "sg:orig_category":"M\u00c9dicos: Estomatolog\u00cda",
    "sg:phone":"+34 922 54 54 17",
    "sg:postcode":"38260",
    "sg:province":"Santa Cruz De Tenerife",
    "wof:name":"Marrero Cano Gabriel",
    "wof:placetype":"venue"
},
  "geometry": {"coordinates":[-16.36186409,28.5334415436],"type":"Point"}
}