{
  "type": "Feature",
  "properties": {
    "addr:full":"Calle de Fari\u00d1a (la), 4 Orotava Santa Cruz De Tenerife 38300",
    "addr:housenumber":"4",
    "addr:postcode":"38300",
    "addr:street":"Calle De Farin\u0303A La",
    "iso:country":"ES",
    "sg:address":"Calle de Fari\u00d1a (la), 4",
    "sg:city":"Orotava",
    "sg:orig_category":"Chapister\u00cda",
    "sg:phone":"+34 922 33 15 44",
    "sg:postcode":"38300",
    "sg:province":"Santa Cruz De Tenerife",
    "wof:name":"Aguilar Perdigon Domingo",
    "wof:placetype":"venue"
},
  "geometry": {"coordinates":[-16.5250225067,28.3843784332],"type":"Point"}
}