{
  "type": "Feature",
  "properties": {
    "addr:full":"Pol Ind El Barrial, 5 Trebujena C\u00e1diz 11560",
    "addr:housenumber":"5",
    "addr:postcode":"11560",
    "addr:street":"El Barrial;Ca\u0301Diz",
    "iso:country":"ES",
    "sg:address":"Pol Ind El Barrial, 5",
    "sg:city":"Trebujena",
    "sg:orig_category":"Escayola Y Productos De Escayola (fabricaci\u00d3n, Al Por Mayor)",
    "sg:phone":"+34 956 16 55 79",
    "sg:postcode":"11560",
    "sg:province":"C\u00e1diz",
    "wof:name":"Decoraciones En Escayola Pepin S.l.",
    "wof:placetype":"venue"
},
  "geometry": {"coordinates":[-6.1715888977,36.8716392517],"type":"Point"}
}