{
  "type": "Feature",
  "properties": {
    "iso:country":"ES",
    "sg:address":"Calle de Mar De Bering, 1",
    "sg:city":"Madrid",
    "sg:orig_category":"Bricolaje, Herramientas (al Por Menor)",
    "sg:phone":"+34 917 63 51 74",
    "sg:postcode":"28033",
    "sg:province":"Madrid",
    "wof:name":"Tejedor Tejedor Maria Milagrosa",
    "wof:placetype":"venue"
},
  "geometry": {"coordinates":[-3.6426727772,40.4731864929],"type":"Point"}
}