{
  "type": "Feature",
  "properties": {
    "iso:country":"ES",
    "sg:address":"Av Portossaler, 28",
    "sg:city":"S. Francesc Formentera",
    "sg:orig_category":"Frutas Y Legumbres Frescas (al Por Mayor)",
    "sg:phone":"+34 971 32 33 03",
    "sg:postcode":"07860",
    "sg:province":"Islas Baleares",
    "wof:name":"Frufor S.l.",
    "wof:placetype":"venue"
},
  "geometry": {"coordinates":[1.425992012,38.7072257996],"type":"Point"}
}