{
  "type": "Feature",
  "properties": {
    "addr:full":"Calle de Jacques Cousteau, 8 Salobre\u00f1a Granada 18680",
    "addr:housenumber":"8",
    "addr:postcode":"18680",
    "addr:street":"Calle De Jacques Cousteau",
    "iso:country":"ES",
    "sg:address":"Calle de Jacques Cousteau, 8",
    "sg:city":"Salobre\u00f1a",
    "sg:orig_category":"Cl\u00cdnicas Dentales",
    "sg:phone":"+34 958 61 06 74",
    "sg:postcode":"18680",
    "sg:province":"Granada",
    "wof:name":"Julian Dalvit Jorge Eduardo",
    "wof:placetype":"venue"
},
  "geometry": {"coordinates":[-3.5850639343,36.7401542664],"type":"Point"}
}