{
  "type": "Feature",
  "properties": {
    "addr:full":"Av Comte De Sallent, 22 Palma Islas Baleares 07003",
    "addr:housenumber":"22",
    "addr:postcode":"07003",
    "iso:country":"ES",
    "sg:address":"Av Comte De Sallent, 22",
    "sg:city":"Palma",
    "sg:orig_category":"Transportes Internacionales",
    "sg:phone":"+34 971 29 69 11",
    "sg:postcode":"07003",
    "sg:province":"Islas Baleares",
    "sg:website":"www.transadu.com",
    "wof:name":"Transitos Y Aduanas Palma S.l.",
    "wof:placetype":"venue"
},
  "geometry": {"coordinates":[2.6493029594,39.5786628723],"type":"Point"}
}