{
  "type": "Feature",
  "properties": {
    "iso:country":"ES",
    "sg:address":"Avda Constitucio (la), 2",
    "sg:city":"Sant Mateu",
    "sg:orig_category":"Negocio De Materiales De Construcci\u00d3n",
    "sg:phone":"+34 964 41 65 16",
    "sg:postcode":"12170",
    "sg:province":"Castell\u00f3n",
    "wof:name":"Sospedra Gil S.l.",
    "wof:placetype":"venue"
},
  "geometry": {"coordinates":[0.1785899997,40.4668502808],"type":"Point"}
}