{
  "type": "Feature",
  "properties": {
    "addr:full":"Calle de Mayor, 16 Jaca Huesca 22700",
    "addr:housenumber":"16",
    "addr:postcode":"22700",
    "addr:street":"Calle De Mayor",
    "iso:country":"ES",
    "sg:address":"Calle de Mayor, 16",
    "sg:city":"Jaca",
    "sg:orig_category":"Colocaci\u00d3n, Mantenimiento De Canalizaciones",
    "sg:phone":"+34 974 36 20 25",
    "sg:postcode":"22700",
    "sg:province":"Huesca",
    "wof:name":"Biec Sanchez Antonio",
    "wof:placetype":"venue"
},
  "geometry": {"coordinates":[-0.5498690009,42.5695762634],"type":"Point"}
}