{
  "type": "Feature",
  "properties": {
    "iso:country":"ES",
    "sg:address":"Avda Espa\u00d1a, 4",
    "sg:city":"Algeciras",
    "sg:orig_category":"Mec\u00c1nico Del Autom\u00d3vil",
    "sg:phone":"+34 956 66 71 02",
    "sg:postcode":"11205",
    "sg:province":"C\u00e1diz",
    "wof:name":"Espinosa Amaya Francisco Javier",
    "wof:placetype":"venue"
},
  "geometry": {"coordinates":[-5.4506669044,36.1471977234],"type":"Point"}
}