{
  "type": "Feature",
  "properties": {
    "addr:full":"Calle de San Miguel, 5 Fortanete Teruel 44143",
    "addr:housenumber":"5",
    "addr:postcode":"44143",
    "addr:street":"Calle De San Miguel",
    "iso:country":"ES",
    "sg:address":"Calle de San Miguel, 5",
    "sg:city":"Fortanete",
    "sg:orig_category":"Cajas De Ahorro",
    "sg:phone":"+34 978 77 80 87",
    "sg:postcode":"44143",
    "sg:province":"Teruel",
    "wof:name":"Caja De Ahorros Y Monte De Piedad De Zaragoza Aragon Y Rioja",
    "wof:placetype":"venue"
},
  "geometry": {"coordinates":[-0.5219789743,40.5054702759],"type":"Point"}
}