{
  "type": "Feature",
  "properties": {
    "addr:full":"Carrer de Flassaders, 21 Barcelona Barcelona 08003",
    "addr:housenumber":"21",
    "addr:postcode":"08003",
    "addr:street":"Carrer De Flassaders",
    "iso:country":"ES",
    "sg:address":"Carrer de Flassaders, 21",
    "sg:city":"Barcelona",
    "sg:orig_category":"Art\u00cdculos De Decoraci\u00d3n (fabricaci\u00d3n Y Al Por Mayor)",
    "sg:phone":"+34 932 68 21 81",
    "sg:postcode":"08003",
    "sg:province":"Barcelona",
    "wof:name":"Matutes Juan Maria Teresa",
    "wof:placetype":"venue"
},
  "geometry": {"coordinates":[2.1819601059,41.3855552673],"type":"Point"}
}