{
  "type": "Feature",
  "properties": {
    "addr:full":"C/ Olegario Domarco Seller, 79 Elche Alicante 03206",
    "addr:housenumber":"79",
    "addr:postcode":"03206",
    "addr:street":"C / Olegario Domarco Seller",
    "iso:country":"ES",
    "sg:address":"C/ Olegario Domarco Seller, 79",
    "sg:city":"Elche",
    "sg:orig_category":"Papeler\u00cdas, Librer\u00cdas",
    "sg:phone":"+34 965 46 06 25",
    "sg:postcode":"03206",
    "sg:province":"Alicante",
    "wof:name":"Montalban Cava Angel",
    "wof:placetype":"venue"
},
  "geometry": {"coordinates":[-0.7080429792,38.2716751099],"type":"Point"}
}