{
  "type": "Feature",
  "properties": {
    "addr:full":"O Casal, 110 Casal Pontevedra 36416",
    "addr:housenumber":"110",
    "addr:postcode":"36416",
    "addr:street":"O Casal",
    "iso:country":"ES",
    "sg:address":"O Casal, 110",
    "sg:city":"Casal",
    "sg:orig_category":"Muebles, Minoristas",
    "sg:phone":"+34 986 33 43 99",
    "sg:postcode":"36416",
    "sg:province":"Pontevedra",
    "wof:name":"Sergio Muebless.l.",
    "wof:placetype":"venue"
},
  "geometry": {"coordinates":[-8.6403799057,42.1906967163],"type":"Point"}
}