{
  "type": "Feature",
  "properties": {
    "addr:full":"Carrer de Felip Ii, 224 Barcelona Barcelona 08027",
    "addr:housenumber":"224",
    "addr:postcode":"08027",
    "addr:street":"Carrer De Felip Ii",
    "iso:country":"ES",
    "sg:address":"Carrer de Felip Ii, 224",
    "sg:city":"Barcelona",
    "sg:orig_category":"Farmacias",
    "sg:phone":"+34 933 52 79 57",
    "sg:postcode":"08027",
    "sg:province":"Barcelona",
    "wof:name":"Pi\u00f1as Maso Loreto",
    "wof:placetype":"venue"
},
  "geometry": {"coordinates":[2.1777288914,41.4275283813],"type":"Point"}
}