{
  "type": "Feature",
  "properties": {
    "addr:full":"Calle de San Antonio, 29 Almodovar Campo Ciudad Real 13580",
    "addr:housenumber":"29",
    "addr:postcode":"13580",
    "addr:street":"Calle De San Antonio;Campo",
    "iso:country":"ES",
    "sg:address":"Calle de San Antonio, 29",
    "sg:city":"Almodovar Campo",
    "sg:orig_category":"Transportes Por V\u00cdas Navegables",
    "sg:phone":"+34 926 48 32 06",
    "sg:postcode":"13580",
    "sg:province":"Ciudad Real",
    "wof:name":"Serrano Anguita Jose Angel",
    "wof:placetype":"venue"
},
  "geometry": {"coordinates":[-4.1802458763,38.7078552246],"type":"Point"}
}