{
  "type": "Feature",
  "properties": {
    "addr:full":"Avda Mediterraneo (del), 248 Almeria Almer\u00eda 04006",
    "addr:housenumber":"248",
    "addr:postcode":"04006",
    "addr:street":"Avda Mediterraneo Del",
    "iso:country":"ES",
    "sg:address":"Avda Mediterraneo (del), 248",
    "sg:city":"Almeria",
    "sg:orig_category":"Peluqueros: De Se\u00d1oras",
    "sg:phone":"+34 950 22 01 11",
    "sg:postcode":"04006",
    "sg:province":"Almer\u00eda",
    "wof:name":"Martin Gazquez Encarnacion",
    "wof:placetype":"venue"
},
  "geometry": {"coordinates":[-2.4471359253,36.8421096802],"type":"Point"}
}