{
  "type": "Feature",
  "properties": {
    "iso:country":"ES",
    "sg:address":"Av Diagonal, 41",
    "sg:city":"Palau-solita I Plegamans",
    "sg:orig_category":"Peluquer\u00cdas, Peluquer\u00cda Mixta",
    "sg:phone":"+34 938 64 41 73",
    "sg:postcode":"08184",
    "sg:province":"Barcelona",
    "wof:name":"Fernandez Moreda Olga",
    "wof:placetype":"venue"
},
  "geometry": {"coordinates":[2.1756300926,41.5884590149],"type":"Point"}
}