{
  "type": "Feature",
  "properties": {
    "addr:full":"Calle de Zocotin, 6 Jaca Huesca 22700",
    "addr:housenumber":"6",
    "addr:postcode":"22700",
    "addr:street":"Calle De Zocotin",
    "iso:country":"ES",
    "sg:address":"Calle de Zocotin, 6",
    "sg:city":"Jaca",
    "sg:orig_category":"Alimentaci\u00d3n General (al Por Menor)",
    "sg:phone":"+34 974 36 06 48",
    "sg:postcode":"22700",
    "sg:province":"Huesca",
    "wof:name":"Vizcaino Gonzalez Basilia",
    "wof:placetype":"venue"
},
  "geometry": {"coordinates":[-0.5489199758,42.5695343018],"type":"Point"}
}