{
  "type": "Feature",
  "properties": {
    "iso:country":"ES",
    "sg:address":"Calle de Berenisa, 12",
    "sg:city":"Madrid",
    "sg:orig_category":"Carb\u00d3n, Carb\u00d3n De Madera (al Por Mayor)",
    "sg:phone":"+34 913 07 00 60",
    "sg:postcode":"28023",
    "sg:province":"Madrid",
    "wof:name":"Carla Mansilla Gregorio",
    "wof:placetype":"venue"
},
  "geometry": {"coordinates":[-3.7807586193,40.4581413269],"type":"Point"}
}