{
  "type": "Feature",
  "properties": {
    "iso:country":"ES",
    "sg:address":"Calle de Llanito, 8",
    "sg:city":"Alberca",
    "sg:orig_category":"Bisuter\u00cda, Joyer\u00cda, Relojer\u00cda (al Por Menor)",
    "sg:phone":"+34 923 41 53 87",
    "sg:postcode":"37624",
    "sg:province":"Salamanca",
    "wof:name":"A.mendez Vieira C.b.",
    "wof:placetype":"venue"
},
  "geometry": {"coordinates":[-6.1115140915,40.4885253906],"type":"Point"}
}