{
  "type": "Feature",
  "properties": {
    "addr:full":"Calle de Telegrafia (de La), S/n Alcobendas Madrid 28100",
    "addr:postcode":"28100",
    "addr:street":"Calle De Telegrafia De La S / N",
    "iso:country":"ES",
    "sg:address":"Calle de Telegrafia (de La), S/n",
    "sg:city":"Alcobendas",
    "sg:orig_category":"M\u00c9dicos: Foniatr\u00cda Y Logopedia",
    "sg:phone":"+34 916 62 31 10",
    "sg:postcode":"28100",
    "sg:province":"Madrid",
    "wof:name":"Garcia Ramiro Marta",
    "wof:placetype":"venue"
},
  "geometry": {"coordinates":[-3.6381940842,40.5419616699],"type":"Point"}
}