{
  "type": "Feature",
  "properties": {
    "iso:country":"ES",
    "sg:address":"Ctra Bacarot, 72",
    "sg:city":"Bacarot",
    "sg:orig_category":"Molduras, Junquillos, Listones Y Molduras Perforadas",
    "sg:phone":"+34 965 18 91 10",
    "sg:postcode":"03114",
    "sg:province":"Alicante",
    "wof:name":"Sistelcom-telemensaje S.a.",
    "wof:placetype":"venue"
},
  "geometry": {"coordinates":[-0.5577290058,38.3202285767],"type":"Point"}
}