{
  "type": "Feature",
  "properties": {
    "addr:full":"Pla\u00c7 Major, 13 Olot Girona 17800",
    "addr:housenumber":"13",
    "addr:postcode":"17800",
    "iso:country":"ES",
    "sg:address":"Pla\u00c7 Major, 13",
    "sg:city":"Olot",
    "sg:orig_category":"Cajas De Ahorro",
    "sg:phone":"+34 972 26 02 65",
    "sg:postcode":"17800",
    "sg:province":"Girona",
    "sg:website":"www.lacaixa.es",
    "wof:name":"Caixa D'estalvis I Pensions De Barcelona",
    "wof:placetype":"venue"
},
  "geometry": {"coordinates":[2.4904549122,42.1826972961],"type":"Point"}
}