{
  "type": "Feature",
  "properties": {
    "iso:country":"ES",
    "sg:address":"Rua Corredoira, 33",
    "sg:city":"Monforte De Lemos",
    "sg:orig_category":"Servicios De Higiene Y Peluquer\u00cda Para Perros Y Gatos",
    "sg:phone":"+34 982 40 23 99",
    "sg:postcode":"27400",
    "sg:province":"Lugo",
    "wof:name":"Balboa Fernandez Goreti",
    "wof:placetype":"venue"
},
  "geometry": {"coordinates":[-7.5193271637,42.526096344],"type":"Point"}
}