{
  "type": "Feature",
  "properties": {
    "addr:full":"Plaz Patio Del Pintor Juan Miro, 14 Cordoba C\u00f3rdoba 14011",
    "addr:housenumber":"14",
    "addr:postcode":"14011",
    "addr:street":"Plaz;Juan Miro;Co\u0301Rdoba",
    "iso:country":"ES",
    "sg:address":"Plaz Patio Del Pintor Juan Miro, 14",
    "sg:city":"Cordoba",
    "sg:orig_category":"Molduras, Junquillos, Listones Y Molduras Perforadas",
    "sg:phone":"+34 957 40 38 49",
    "sg:postcode":"14011",
    "sg:province":"C\u00f3rdoba",
    "wof:name":"Bejarano Rodriguez Manuela",
    "wof:placetype":"venue"
},
  "geometry": {"coordinates":[-4.7911791801,37.893951416],"type":"Point"}
}