{
  "type": "Feature",
  "properties": {
    "addr:full":"Cartagena, Km. 0004,0 Manga Mar Menor Murcia 30380",
    "addr:postcode":"30380",
    "addr:street":"Cartagena Km. 0004,0",
    "iso:country":"ES",
    "sg:address":"Cartagena, Km. 0004,0",
    "sg:city":"Manga Mar Menor",
    "sg:orig_category":"Cajas Para Embalar",
    "sg:phone":"+34 968 33 72 87",
    "sg:postcode":"30380",
    "sg:province":"Murcia",
    "wof:name":"Cajamar",
    "wof:placetype":"venue"
},
  "geometry": {"coordinates":[-0.7281540036,37.6686553955],"type":"Point"}
}