{
  "type": "Feature",
  "properties": {
    "iso:country":"ES",
    "sg:address":"Avda Americas (las), S/n",
    "sg:city":"Playa Americas",
    "sg:orig_category":"T\u00c9cnicos Veterinarios",
    "sg:phone":"+34 922 75 00 27",
    "sg:postcode":"38660",
    "sg:province":"Santa Cruz De Tenerife",
    "wof:name":"Gonzalez Ortiz Sara",
    "wof:placetype":"venue"
},
  "geometry": {"coordinates":[-16.7317714691,28.0760765076],"type":"Point"}
}