{
  "type": "Feature",
  "properties": {
    "iso:country":"ES",
    "sg:address":"Calle de Lagunillas, 34",
    "sg:city":"Malaga",
    "sg:orig_category":"Confecci\u00d3n De Trajes Para Se\u00d1oras",
    "sg:phone":"+34 952 25 88 22",
    "sg:postcode":"29012",
    "sg:province":"M\u00e1laga",
    "wof:name":"Marfil Urdiales Rafael",
    "wof:placetype":"venue"
},
  "geometry": {"coordinates":[-4.4159522057,36.7255554199],"type":"Point"}
}