{
  "type": "Feature",
  "properties": {
    "addr:full":"Carr Closa D'en Llop, 18 Escala Girona 17130",
    "addr:housenumber":"18",
    "addr:postcode":"17130",
    "addr:street":"Carr Closa D'En Llop",
    "iso:country":"ES",
    "sg:address":"Carr Closa D'en Llop, 18",
    "sg:city":"Escala",
    "sg:orig_category":"Distribuci\u00d3n De Petr\u00d3leo Y Derivados",
    "sg:phone":"+34 972 77 08 20",
    "sg:postcode":"17130",
    "sg:province":"Girona",
    "wof:name":"Anxoves El Xillu S.l.",
    "wof:placetype":"venue"
},
  "geometry": {"coordinates":[3.1244575977,42.1241111755],"type":"Point"}
}