{
  "type": "Feature",
  "properties": {
    "addr:full":"Calle de Genil, 43 Bollullos Mitacion Sevilla 41110",
    "addr:housenumber":"43",
    "addr:postcode":"41110",
    "addr:street":"Calle De Genil",
    "iso:country":"ES",
    "sg:address":"Calle de Genil, 43",
    "sg:city":"Bollullos Mitacion",
    "sg:orig_category":"Escuelas De Maternidad P\u00dablicas",
    "sg:phone":"+34 955 76 62 98",
    "sg:postcode":"41110",
    "sg:province":"Sevilla",
    "wof:name":"Ponce Jara Maria Del Mar",
    "wof:placetype":"venue"
},
  "geometry": {"coordinates":[-6.1414699554,37.3451576233],"type":"Point"}
}