{
  "type": "Feature",
  "properties": {
    "iso:country":"ES",
    "sg:address":"Calle de Quintanal, 30",
    "sg:city":"Faramontanos Tabara",
    "sg:orig_category":"Carga Y Descarga",
    "sg:phone":"+34 980 59 50 91",
    "sg:postcode":"49141",
    "sg:province":"Zamora",
    "wof:name":"Carrocerias Y Basculantes Tanis S.l.",
    "wof:placetype":"venue"
},
  "geometry": {"coordinates":[-5.8913087845,41.8377532959],"type":"Point"}
}