{
  "type": "Feature",
  "properties": {
    "iso:country":"ES",
    "sg:address":"Carr Sant Roc, 16",
    "sg:city":"Vilavella",
    "sg:orig_category":"Art\u00cdculos De Regalo (al Por Menor)",
    "sg:phone":"+34 964 67 82 08",
    "sg:postcode":"12526",
    "sg:province":"Castell\u00f3n",
    "wof:name":"Roig Sanahuja Asuncion",
    "wof:placetype":"venue"
},
  "geometry": {"coordinates":[-0.0456800014,39.9851417542],"type":"Point"}
}