{
  "type": "Feature",
  "properties": {
    "iso:country":"ES",
    "sg:address":"Rond Panderola, 13",
    "sg:city":"Burriana",
    "sg:orig_category":"Iglesia Cat\u00d3lica",
    "sg:phone":"+34 964 51 14 00",
    "sg:postcode":"12530",
    "sg:province":"Castell\u00f3n",
    "wof:name":"Parroquia Nuestra Se\u00f1ora De Los Desamparados",
    "wof:placetype":"venue"
},
  "geometry": {"coordinates":[-0.0852660015,39.8894195557],"type":"Point"}
}