{
  "type": "Feature",
  "properties": {
    "addr:full":"Calle de Pardo Bazan, 5 Fuensalida Toledo 45510",
    "addr:housenumber":"5",
    "addr:postcode":"45510",
    "addr:street":"Calle De Pardo Bazan",
    "iso:country":"ES",
    "sg:address":"Calle de Pardo Bazan, 5",
    "sg:city":"Fuensalida",
    "sg:orig_category":"Art\u00cdculos De Madera (fabricaci\u00d3n Y Al Por Mayor)",
    "sg:phone":"+34 925 78 40 11",
    "sg:postcode":"45510",
    "sg:province":"Toledo",
    "wof:name":"Goybe Mobel S.l.",
    "wof:placetype":"venue"
},
  "geometry": {"coordinates":[-4.2068428993,40.0458145142],"type":"Point"}
}