{
  "type": "Feature",
  "properties": {
    "addr:full":"Calle de Oaxaca, 2 Caceres C\u00e1ceres 10005",
    "addr:housenumber":"2",
    "addr:postcode":"10005",
    "addr:street":"Calle De Oaxaca;Ca\u0301Ceres",
    "iso:country":"ES",
    "sg:address":"Calle de Oaxaca, 2",
    "sg:city":"Caceres",
    "sg:orig_category":"Papeler\u00cdas, Librer\u00cdas",
    "sg:phone":"+34 927 23 82 29",
    "sg:postcode":"10005",
    "sg:province":"C\u00e1ceres",
    "wof:name":"Papeleria El Tintero",
    "wof:placetype":"venue"
},
  "geometry": {"coordinates":[-6.379652977,39.4575271606],"type":"Point"}
}