{
  "type": "Feature",
  "properties": {
    "addr:full":"Calle de Juan Ramon Jimenez, 1 Puente Tocinos Murcia 30006",
    "addr:housenumber":"1",
    "addr:postcode":"30006",
    "addr:street":"Calle De Juan Ramon Jimenez",
    "iso:country":"ES",
    "sg:address":"Calle de Juan Ramon Jimenez, 1",
    "sg:city":"Puente Tocinos",
    "sg:orig_category":"Servicios De Telecomunicaciones",
    "sg:phone":"+34 968 30 45 08",
    "sg:postcode":"30006",
    "sg:province":"Murcia",
    "wof:name":"Touba Phone C.b.",
    "wof:placetype":"venue"
},
  "geometry": {"coordinates":[-1.1017260551,37.9946708679],"type":"Point"}
}