{
  "type": "Feature",
  "properties": {
    "addr:full":"Plaz Usategi, 7 Algorta Vizcaya 48993",
    "addr:housenumber":"7",
    "addr:postcode":"48993",
    "addr:street":"Plaz Usategi",
    "iso:country":"ES",
    "sg:address":"Plaz Usategi, 7",
    "sg:city":"Algorta",
    "sg:orig_category":"Alimentaci\u00d3n General (al Por Menor)",
    "sg:phone":"+34 944 60 88 36",
    "sg:postcode":"48993",
    "sg:province":"Vizcaya",
    "wof:name":"Cortazar Martinez De Zu\u00f1iga Jesus Maria",
    "wof:placetype":"venue"
},
  "geometry": {"coordinates":[-3.0164480209,43.3510551453],"type":"Point"}
}