{
  "type": "Feature",
  "properties": {
    "iso:country":"ES",
    "sg:address":"Calle de Jesus Hurtado Descalzo, S/n",
    "sg:city":"Alcantarilla",
    "sg:orig_category":"Caf\u00c9s, Bares, Cervecer\u00cdas",
    "sg:phone":"+34 968 89 48 17",
    "sg:postcode":"30820",
    "sg:province":"Murcia",
    "wof:name":"Andreu Lopez Juan Jose",
    "wof:placetype":"venue"
},
  "geometry": {"coordinates":[-1.2085444927,37.9703330994],"type":"Point"}
}