{
  "type": "Feature",
  "properties": {
    "iso:country":"ES",
    "sg:address":"Calle de Fuentesauco, 8",
    "sg:city":"Madrid",
    "sg:orig_category":"Institutos De Belleza",
    "sg:phone":"+34 917 11 30 20",
    "sg:postcode":"28024",
    "sg:province":"Madrid",
    "wof:name":"Saenz Lopez Maria",
    "wof:placetype":"venue"
},
  "geometry": {"coordinates":[-3.7706859112,40.3984909058],"type":"Point"}
}