{
  "type": "Feature",
  "properties": {
    "iso:country":"ES",
    "sg:address":"Ctra Estacion, 4",
    "sg:city":"Pe\u00f1iscola",
    "sg:orig_category":"Hoteles",
    "sg:phone":"+34 964 48 06 59",
    "sg:postcode":"12598",
    "sg:province":"Castell\u00f3n",
    "wof:name":"Escrig Garcia Jose Tomas",
    "wof:placetype":"venue"
},
  "geometry": {"coordinates":[-0.0456800014,39.9851417542],"type":"Point"}
}