{
  "type": "Feature",
  "properties": {
    "addr:full":"Calle de Leon Y Castillo, 87 Palmas De Gran Canaria Las Palmas 35004",
    "addr:postcode":"35004",
    "addr:street":"Calle De Leon Y Castillo 87",
    "iso:country":"ES",
    "sg:address":"Calle de Leon Y Castillo, 87",
    "sg:city":"Palmas De Gran Canaria",
    "sg:orig_category":"Inform\u00c1tica (estudios, Servicios, Asesor\u00cda, Formaci\u00d3n)",
    "sg:phone":"+34 928 23 43 00",
    "sg:postcode":"35004",
    "sg:province":"Las Palmas",
    "sg:website":"www.datisa.es",
    "wof:name":"Desarrollo De Aplicaciones Tecnicas Info",
    "wof:placetype":"venue"
},
  "geometry": {"coordinates":[-15.420466423,28.1144142151],"type":"Point"}
}