{
  "type": "Feature",
  "properties": {
    "addr:full":"Carr Torres Jonama, 17 Mont-ras Girona 17253",
    "addr:housenumber":"17",
    "addr:postcode":"17253",
    "addr:street":"Carr Torres Jonama",
    "iso:country":"ES",
    "sg:address":"Carr Torres Jonama, 17",
    "sg:city":"Mont-ras",
    "sg:orig_category":"Muebles, Minoristas",
    "sg:phone":"+34 972 61 15 21",
    "sg:postcode":"17253",
    "sg:province":"Girona",
    "sg:website":"www.labotigademoble.com",
    "wof:name":"Domenech Sala Albert",
    "wof:placetype":"venue"
},
  "geometry": {"coordinates":[3.1475400925,41.9082565308],"type":"Point"}
}