{
  "type": "Feature",
  "properties": {
    "iso:country":"ES",
    "sg:address":"Calle de Cervantes, 19",
    "sg:city":"Altura",
    "sg:orig_category":"Negocio De Materiales De Construcci\u00d3n",
    "sg:phone":"+34 964 14 68 57",
    "sg:postcode":"12410",
    "sg:province":"Castell\u00f3n",
    "wof:name":"Torrejon Martinez Antonio",
    "wof:placetype":"venue"
},
  "geometry": {"coordinates":[-0.5139999986,39.8505401611],"type":"Point"}
}