{
  "type": "Feature",
  "properties": {
    "addr:full":"Plaz Amazonas, S/n Zaragoza Zaragoza 50012",
    "addr:housenumber":"s / n",
    "addr:postcode":"50012",
    "addr:street":"Plaz Amazonas",
    "iso:country":"ES",
    "sg:address":"Plaz Amazonas, S/n",
    "sg:city":"Zaragoza",
    "sg:orig_category":"Transporte En General",
    "sg:phone":"+34 976 31 65 09",
    "sg:postcode":"50012",
    "sg:province":"Zaragoza",
    "wof:name":"Autoservicio Amazona S.l.",
    "wof:placetype":"venue"
},
  "geometry": {"coordinates":[-0.9177020192,41.646282196],"type":"Point"}
}