{
  "type": "Feature",
  "properties": {
    "iso:country":"ES",
    "sg:address":"Plaz Marques De Valdecilla, 17",
    "sg:city":"Miengo",
    "sg:orig_category":"Empresarios",
    "sg:phone":"+34 942 57 60 03",
    "sg:postcode":"39310",
    "sg:province":"Cantabria",
    "wof:name":"Eguia Balbontin Segundo",
    "wof:placetype":"venue"
},
  "geometry": {"coordinates":[-4.0002198219,43.4302825928],"type":"Point"}
}