{
  "type": "Feature",
  "properties": {
    "iso:country":"ES",
    "sg:address":"Pase Estacion (la), 50",
    "sg:city":"Jaen",
    "sg:orig_category":"Ense\u00d1anza: Idiomas",
    "sg:phone":"+34 953 27 59 83",
    "sg:postcode":"23007",
    "sg:province":"Ja\u00e9n",
    "wof:name":"Picardo Lozano Magdalena",
    "wof:placetype":"venue"
},
  "geometry": {"coordinates":[-3.7906870842,37.7650947571],"type":"Point"}
}