{
  "type": "Feature",
  "properties": {
    "addr:full":"Calle de San Miguel, 12 Zaragoza Zaragoza 50001",
    "addr:housenumber":"12",
    "addr:postcode":"50001",
    "addr:street":"Calle De San Miguel",
    "iso:country":"ES",
    "sg:address":"Calle de San Miguel, 12",
    "sg:city":"Zaragoza",
    "sg:orig_category":"Procuradores",
    "sg:phone":"+34 976 22 78 12",
    "sg:postcode":"50001",
    "sg:province":"Zaragoza",
    "wof:name":"Belloc Hierro Maria Luisa",
    "wof:placetype":"venue"
},
  "geometry": {"coordinates":[-0.8802909851,41.6507263184],"type":"Point"}
}