{
  "type": "Feature",
  "properties": {
    "addr:full":"Calle de Manuel Diz, 3 Ba\u00d1eza Le\u00f3n 24750",
    "addr:housenumber":"3",
    "addr:postcode":"24750",
    "addr:street":"Calle De Manuel Diz;Leo\u0301N",
    "iso:country":"ES",
    "sg:address":"Calle de Manuel Diz, 3",
    "sg:city":"Ba\u00d1eza",
    "sg:orig_category":"Zapatos (al Por Menor)",
    "sg:phone":"+34 987 64 14 33",
    "sg:postcode":"24750",
    "sg:province":"Le\u00f3n",
    "wof:name":"Fernandez Aparicio Maria Pilar",
    "wof:placetype":"venue"
},
  "geometry": {"coordinates":[-5.9242091179,42.3069114685],"type":"Point"}
}