{
  "type": "Feature",
  "properties": {
    "addr:full":"Avda Espa\u00d1a, 60 Estepona M\u00e1laga 29680",
    "addr:housenumber":"60",
    "addr:postcode":"29680",
    "addr:street":"Avda Espan\u0303A",
    "iso:country":"ES",
    "sg:address":"Avda Espa\u00d1a, 60",
    "sg:city":"Estepona",
    "sg:orig_category":"Asesor\u00cda Fiscal Y Jur\u00cddica",
    "sg:phone":"+34 952 79 20 52",
    "sg:postcode":"29680",
    "sg:province":"M\u00e1laga",
    "wof:name":"Barriento Segura Carlos",
    "wof:placetype":"venue"
},
  "geometry": {"coordinates":[-5.1419439316,36.4261245728],"type":"Point"}
}