{
  "type": "Feature",
  "properties": {
    "addr:full":"Calle de Doctor Grau Bassas, 42 Palmas De Gran Canaria Las Palmas 35007",
    "addr:housenumber":"42",
    "addr:postcode":"35007",
    "addr:street":"Calle De Doctor Grau Bassas",
    "iso:country":"ES",
    "sg:address":"Calle de Doctor Grau Bassas, 42",
    "sg:city":"Palmas De Gran Canaria",
    "sg:orig_category":"Supermercados Y Hipermercados",
    "sg:phone":"+34 928 26 66 47",
    "sg:postcode":"35007",
    "sg:province":"Las Palmas",
    "wof:name":"Proyectos Y Servicios Alimentarios S.l.",
    "wof:placetype":"venue"
},
  "geometry": {"coordinates":[-15.435675621,28.1393718719],"type":"Point"}
}