{
  "type": "Feature",
  "properties": {
    "addr:full":"Calle de Espartero, 26 Osuna Sevilla 41640",
    "addr:housenumber":"26",
    "addr:postcode":"41640",
    "addr:street":"Calle De Espartero",
    "iso:country":"ES",
    "sg:address":"Calle de Espartero, 26",
    "sg:city":"Osuna",
    "sg:orig_category":"Fotocopias, Reprograf\u00cda",
    "sg:phone":"+34 955 82 01 44",
    "sg:postcode":"41640",
    "sg:province":"Sevilla",
    "wof:name":"Copisterias Del Sur S.l.",
    "wof:placetype":"venue"
},
  "geometry": {"coordinates":[-5.1107487679,37.2385215759],"type":"Point"}
}