{
  "type": "Feature",
  "properties": {
    "iso:country":"ES",
    "sg:address":"Pase Adarves (los), 45",
    "sg:city":"Molina",
    "sg:orig_category":"Quincaller\u00cda (al Por Menor)",
    "sg:phone":"+34 949 83 19 10",
    "sg:postcode":"19300",
    "sg:province":"Guadalajara",
    "wof:name":"Ferreteria Guillen S.a.",
    "wof:placetype":"venue"
},
  "geometry": {"coordinates":[-1.8168599606,40.8542098999],"type":"Point"}
}