{
  "type": "Feature",
  "properties": {
    "iso:country":"ES",
    "sg:address":"Luga Fataga, Km. 0001,2",
    "sg:city":"Fataga",
    "sg:orig_category":"Productores Recolectores, Venta Directa De Vinos",
    "sg:phone":"+34 928 17 27 96",
    "sg:postcode":"35108",
    "sg:province":"Las Palmas",
    "wof:name":"Tavaibilla Agricola Y Ganadera S.l.",
    "wof:placetype":"venue"
},
  "geometry": {"coordinates":[-15.5638666153,27.8875045776],"type":"Point"}
}