{
  "type": "Feature",
  "properties": {
    "iso:country":"ES",
    "sg:address":"Calle de Doctor Fleming, 30",
    "sg:city":"Villares",
    "sg:orig_category":"Negocio De Materiales De Construcci\u00d3n",
    "sg:phone":"+34 953 32 02 11",
    "sg:postcode":"23160",
    "sg:province":"Ja\u00e9n",
    "wof:name":"Delgado Tirado Manuel",
    "wof:placetype":"venue"
},
  "geometry": {"coordinates":[-3.8200290203,37.6875610352],"type":"Point"}
}