{
  "type": "Feature",
  "properties": {
    "addr:full":"Calle de Don Lope De Sosa, 32 Cordoba C\u00f3rdoba 14004",
    "addr:housenumber":"32",
    "addr:postcode":"14004",
    "addr:street":"Calle De Don Lope De Sosa;Co\u0301Rdoba",
    "iso:country":"ES",
    "sg:address":"Calle de Don Lope De Sosa, 32",
    "sg:city":"Cordoba",
    "sg:orig_category":"Electricidad, Electr\u00d3nica: Suministros (al Por Menor)",
    "sg:phone":"+34 957 41 44 11",
    "sg:postcode":"14004",
    "sg:province":"C\u00f3rdoba",
    "wof:name":"Lopez Gomez Jose Manuel",
    "wof:placetype":"venue"
},
  "geometry": {"coordinates":[-4.7913131714,37.8799972534],"type":"Point"}
}