{
  "type": "Feature",
  "properties": {
    "iso:country":"ES",
    "sg:address":"Aptos. Torrecasim, S/n",
    "sg:city":"Benicassim",
    "sg:orig_category":"Asesor\u00cdas Y Estudios Financieros",
    "sg:phone":"+34 964 30 05 86",
    "sg:postcode":"12560",
    "sg:province":"Castell\u00f3n",
    "wof:name":"Azinovic  Zlatko",
    "wof:placetype":"venue"
},
  "geometry": {"coordinates":[0.0457400009,40.0510292053],"type":"Point"}
}