{
  "type": "Feature",
  "properties": {
    "iso:country":"ES",
    "sg:address":"Avda Estacion (de La), 175",
    "sg:city":"Puente-genil",
    "sg:orig_category":"Farmacias",
    "sg:phone":"+34 957 60 43 70",
    "sg:postcode":"14500",
    "sg:province":"C\u00f3rdoba",
    "wof:name":"Cabello Delgado Pablo",
    "wof:placetype":"venue"
},
  "geometry": {"coordinates":[-4.7557220459,37.395236969],"type":"Point"}
}