{
  "type": "Feature",
  "properties": {
    "iso:country":"ES",
    "sg:address":"Praz Quintana (da), 3",
    "sg:city":"Santiago De Compostela",
    "sg:orig_category":"Mutuas De Seguros",
    "sg:phone":"+34 981 57 34 57",
    "sg:postcode":"15704",
    "sg:province":"La Coru\u00f1a",
    "wof:name":"Hermandad Nacional De Arquitectos",
    "wof:placetype":"venue"
},
  "geometry": {"coordinates":[-8.4875040054,42.922454834],"type":"Point"}
}