{
  "type": "Feature",
  "properties": {
    "iso:country":"ES",
    "sg:address":"Calle de Portal De Legutiano, 52",
    "sg:city":"Vitoria-gasteiz",
    "sg:orig_category":"Iglesias Evang\u00c9licas",
    "sg:phone":"+34 945 01 04 75",
    "sg:postcode":"01002",
    "sg:province":"\u00c1lava",
    "wof:name":"Iglesia Evangelica Pentecostal De Vitoria",
    "wof:placetype":"venue"
},
  "geometry": {"coordinates":[-2.6618700027,42.8527183533],"type":"Point"}
}