{
  "type": "Feature",
  "properties": {
    "iso:country":"ES",
    "sg:address":"Calle de Narvaez, 24",
    "sg:city":"Madrid",
    "sg:orig_category":"Muebles, Minoristas",
    "sg:phone":"+34 915 76 97 32",
    "sg:postcode":"28009",
    "sg:province":"Madrid",
    "wof:name":"Frutos Domingo Hilaria",
    "wof:placetype":"venue"
},
  "geometry": {"coordinates":[-3.6761419773,40.4218635559],"type":"Point"}
}