{
  "type": "Feature",
  "properties": {
    "iso:country":"ES",
    "sg:address":"Calle de Buen Pastor, 70",
    "sg:city":"Barakaldo",
    "sg:orig_category":"Molduras, Junquillos, Listones Y Molduras Perforadas",
    "sg:phone":"+34 944 99 26 30",
    "sg:postcode":"48903",
    "sg:province":"Vizcaya",
    "wof:name":"I\u00f1ator, Sl",
    "wof:placetype":"venue"
},
  "geometry": {"coordinates":[-2.9769876003,43.2902755737],"type":"Point"}
}