{
  "type": "Feature",
  "properties": {
    "addr:full":"Calle de Rio Urdiales, 20 Ponferrada Le\u00f3n 24400",
    "addr:housenumber":"20",
    "addr:postcode":"24400",
    "addr:street":"Calle De Rio Urdiales",
    "iso:country":"ES",
    "sg:address":"Calle de Rio Urdiales, 20",
    "sg:city":"Ponferrada",
    "sg:orig_category":"Abogados",
    "sg:phone":"+34 987 41 25 52",
    "sg:postcode":"24400",
    "sg:province":"Le\u00f3n",
    "wof:name":"Fernandez Redondo Pedro",
    "wof:placetype":"venue"
},
  "geometry": {"coordinates":[-6.5939478874,42.5474472046],"type":"Point"}
}