{
  "type": "Feature",
  "properties": {
    "iso:country":"ES",
    "sg:address":"Rua Rocio, 57",
    "sg:city":"Vigo",
    "sg:orig_category":"Pescader\u00cdas (al Por Menor)",
    "sg:phone":"+34 986 23 97 39",
    "sg:postcode":"36208",
    "sg:province":"Pontevedra",
    "wof:name":"Comesa\u00f1a Fernandez Jose Angel",
    "wof:placetype":"venue"
},
  "geometry": {"coordinates":[-8.7517213821,42.2197723389],"type":"Point"}
}