{
  "type": "Feature",
  "properties": {
    "addr:full":"Calle de Poeta Mas Y Ros, 116 Valencia Valencia 46022",
    "addr:housenumber":"116",
    "addr:postcode":"46022",
    "addr:street":"Calle De Poeta Mas Y Ros",
    "iso:country":"ES",
    "sg:address":"Calle de Poeta Mas Y Ros, 116",
    "sg:city":"Valencia",
    "sg:orig_category":"Bisuter\u00cda, Joyer\u00cda, Relojer\u00cda (al Por Menor)",
    "sg:phone":"+34 963 72 05 16",
    "sg:postcode":"46022",
    "sg:province":"Valencia",
    "wof:name":"Albors Dionisio Salvador",
    "wof:placetype":"venue"
},
  "geometry": {"coordinates":[-0.3404760063,39.4681549072],"type":"Point"}
}