{
  "type": "Feature",
  "properties": {
    "iso:country":"ES",
    "sg:address":"Ctra Villanueva, 28",
    "sg:city":"Jerez De Los Caballeros",
    "sg:classifiers":[
        {
            "category":"Autos & Motor Vehicles",
            "subcategory":"Automobile Sales",
            "type":"Retail Goods"
        }
    ],
    "sg:phone":"+34 924 75 18 40",
    "sg:postcode":"06380",
    "sg:province":"Badajoz",
    "wof:name":"Auto Escuelas Jerez S.l.",
    "wof:placetype":"venue"
},
  "geometry": {"coordinates":[-6.7707271576,38.3264045715],"type":"Point"}
}