{
  "type": "Feature",
  "properties": {
    "iso:country":"ES",
    "sg:address":"Av Ribera, 25",
    "sg:city":"Montcada Centre",
    "sg:orig_category":"Molduras, Junquillos, Listones Y Molduras Perforadas",
    "sg:phone":"+34 935 75 31 22",
    "sg:postcode":"08110",
    "sg:province":"Barcelona",
    "wof:name":"Guillen Casero Santos",
    "wof:placetype":"venue"
},
  "geometry": {"coordinates":[2.1904280186,41.4834823608],"type":"Point"}
}