{
  "type": "Feature",
  "properties": {
    "iso:country":"ES",
    "sg:address":"Prje. Asensao, 1",
    "sg:city":"Cieza",
    "sg:orig_category":"Electromec\u00c1nica",
    "sg:phone":"+34 968 76 18 08",
    "sg:postcode":"30530",
    "sg:province":"Murcia",
    "wof:name":"Garcia Sanchez Juan",
    "wof:placetype":"venue"
},
  "geometry": {"coordinates":[-1.4821481705,38.2650794983],"type":"Point"}
}