{
  "type": "Feature",
  "properties": {
    "iso:country":"ES",
    "sg:address":"Calle de Murillo, S/n",
    "sg:city":"Cantimpalos",
    "sg:orig_category":"Cristaler\u00cdas",
    "sg:phone":"+34 921 49 63 29",
    "sg:postcode":"40360",
    "sg:province":"Segovia",
    "wof:name":"Aluminios Y Cristaleria Roma S.l.",
    "wof:placetype":"venue"
},
  "geometry": {"coordinates":[-4.1640849113,41.0739593506],"type":"Point"}
}