{
  "type": "Feature",
  "properties": {
    "iso:country":"ES",
    "sg:address":"Calle de Heroe De Sostoa, 136",
    "sg:city":"Malaga",
    "sg:orig_category":"Seguridad Social",
    "sg:phone":"+34 952 22 46 19",
    "sg:postcode":"29003",
    "sg:province":"M\u00e1laga",
    "wof:name":"Sat Mutua De Accidentes",
    "wof:placetype":"venue"
},
  "geometry": {"coordinates":[-4.4394721985,36.7047805786],"type":"Point"}
}