{
  "type": "Feature",
  "properties": {
    "iso:country":"ES",
    "sg:address":"Calle de Reina Victoria, 14",
    "sg:city":"Parla",
    "sg:orig_category":"Frutas, Legumbres Frescas Y Tempranas (al Por Menor)",
    "sg:phone":"+34 916 98 18 14",
    "sg:postcode":"28980",
    "sg:province":"Madrid",
    "wof:name":"Perez Lopez Santiago Javier",
    "wof:placetype":"venue"
},
  "geometry": {"coordinates":[-3.7693378925,40.2349586487],"type":"Point"}
}