{
  "type": "Feature",
  "properties": {
    "iso:country":"ES",
    "sg:address":"Calle de General Alvarez De Castro, 12",
    "sg:city":"Burgo Osma",
    "sg:orig_category":"Pescader\u00cdas (al Por Menor)",
    "sg:phone":"+34 975 36 02 99",
    "sg:postcode":"42300",
    "sg:province":"Soria",
    "wof:name":"Macarron Carro Jaime",
    "wof:placetype":"venue"
},
  "geometry": {"coordinates":[-3.068584919,41.5872268677],"type":"Point"}
}