{
  "type": "Feature",
  "properties": {
    "iso:country":"ES",
    "sg:address":"Avda Nuestra Se\u00d1ora Del Pilar, 33",
    "sg:city":"Binefar",
    "sg:orig_category":"Expertos Contables, Revisores De Cuentas",
    "sg:phone":"+34 974 42 98 78",
    "sg:postcode":"22500",
    "sg:province":"Huesca",
    "wof:name":"Jose Ortiz Pablo S.l.",
    "wof:placetype":"venue"
},
  "geometry": {"coordinates":[0.2904329896,41.852596283],"type":"Point"}
}