{
  "type": "Feature",
  "properties": {
    "addr:full":"Pl Porta Pintada, 3 Palma Islas Baleares 07002",
    "addr:housenumber":"3",
    "addr:postcode":"07002",
    "addr:street":"Pl Porta Pintada",
    "iso:country":"ES",
    "sg:address":"Pl Porta Pintada, 3",
    "sg:city":"Palma",
    "sg:orig_category":"Pr\u00c9stamos Personales E Hipotecarios",
    "sg:phone":"+34 971 42 52 48",
    "sg:postcode":"07002",
    "sg:province":"Islas Baleares",
    "wof:name":"Torrens Sanchez Antoni Miquel",
    "wof:placetype":"venue"
},
  "geometry": {"coordinates":[2.6528880596,39.5752487183],"type":"Point"}
}