{
  "type": "Feature",
  "properties": {
    "addr:full":"Calle de Marques De Aracena, 1 Repilado Huelva 21360",
    "addr:housenumber":"1",
    "addr:postcode":"21360",
    "addr:street":"Calle De Marques De Aracena",
    "iso:country":"ES",
    "sg:address":"Calle de Marques De Aracena, 1",
    "sg:city":"Repilado",
    "sg:orig_category":"Inmobiliaria (agencias)",
    "sg:phone":"+34 959 12 26 31",
    "sg:postcode":"21360",
    "sg:province":"Huelva",
    "wof:name":"Dehesas Del Murtiga S.l.",
    "wof:placetype":"venue"
},
  "geometry": {"coordinates":[-6.7729830742,37.9253921509],"type":"Point"}
}