{
  "type": "Feature",
  "properties": {
    "addr:full":"Ctra. General, 191 Sta.ursula Santa Cruz De Tenerife 38390",
    "addr:housenumber":"191",
    "addr:postcode":"38390",
    "addr:street":"Ctra. General",
    "iso:country":"ES",
    "sg:address":"Ctra. General, 191",
    "sg:city":"Sta.ursula",
    "sg:orig_category":"Comercio De Mobiliario De Oficina",
    "sg:phone":"+34 922 30 11 54",
    "sg:postcode":"38390",
    "sg:province":"Santa Cruz De Tenerife",
    "wof:name":"Indica 56 S.l.",
    "wof:placetype":"venue"
},
  "geometry": {"coordinates":[-16.4917697906,28.425359726],"type":"Point"}
}