{
  "type": "Feature",
  "properties": {
    "iso:country":"ES",
    "sg:address":"Psaj Santiago Mirat, S/n",
    "sg:city":"Santa Marta De Tormes",
    "sg:orig_category":"Alimentaci\u00d3n General (al Por Menor)",
    "sg:phone":"+34 923 13 02 83",
    "sg:postcode":"37900",
    "sg:province":"Salamanca",
    "wof:name":"Reyes Reyes Matilde",
    "wof:placetype":"venue"
},
  "geometry": {"coordinates":[-5.6283512115,40.951259613],"type":"Point"}
}