{
  "type": "Feature",
  "properties": {
    "iso:country":"ES",
    "sg:address":"Carrer de Sant Pere, 47",
    "sg:city":"Terrassa",
    "sg:orig_category":"Ropa De Hogar (al Por Menor)",
    "sg:phone":"+34 937 88 52 03",
    "sg:postcode":"08221",
    "sg:province":"Barcelona",
    "wof:name":"Julia Amat Maria Dolors",
    "wof:placetype":"venue"
},
  "geometry": {"coordinates":[2.0101029873,41.5662193298],"type":"Point"}
}