{
  "type": "Feature",
  "properties": {
    "iso:country":"ES",
    "sg:address":"Carrer de Bac De Roda, 83",
    "sg:city":"Barcelona",
    "sg:orig_category":"Electricidad: Instaladores",
    "sg:phone":"+34 933 08 10 16",
    "sg:postcode":"08005",
    "sg:province":"Barcelona",
    "wof:name":"Velme S. L.",
    "wof:placetype":"venue"
},
  "geometry": {"coordinates":[2.2057569027,41.406036377],"type":"Point"}
}