{
  "type": "Feature",
  "properties": {
    "iso:country":"ES",
    "sg:address":"Calle de Cruz, 23",
    "sg:city":"Mora",
    "sg:orig_category":"Aceites Y Grasas Alimentarias (fabricaci\u00d3n, Al Por Mayor)",
    "sg:phone":"+34 925 30 10 40",
    "sg:postcode":"45400",
    "sg:province":"Toledo",
    "sg:website":"www.aceitestolivir.com",
    "wof:name":"Explotaciones Agropecuarias Tolivir S. L.",
    "wof:placetype":"venue"
},
  "geometry": {"coordinates":[-3.7714107037,39.6862335205],"type":"Point"}
}