{
  "type": "Feature",
  "properties": {
    "addr:full":"Mayor-nagusia Kalea, 51 Iru\u00f1a Navarra 31001",
    "addr:housenumber":"51",
    "addr:postcode":"31001",
    "addr:street":"Mayor-Nagusia Kalea",
    "iso:country":"ES",
    "sg:address":"Mayor-nagusia Kalea, 51",
    "sg:city":"Iru\u00f1a",
    "sg:orig_category":"Farmacias",
    "sg:phone":"+34 948 22 17 65",
    "sg:postcode":"31001",
    "sg:province":"Navarra",
    "wof:name":"Diaz Huarte-mendicoa Angel Maria",
    "wof:placetype":"venue"
},
  "geometry": {"coordinates":[-1.6471509933,42.8175468445],"type":"Point"}
}