{
  "type": "Feature",
  "properties": {
    "addr:full":"Calle de Villanueva, 12 Medina Campo Valladolid 47400",
    "addr:housenumber":"12",
    "addr:postcode":"47400",
    "addr:street":"Calle De Villanueva",
    "iso:country":"ES",
    "sg:address":"Calle de Villanueva, 12",
    "sg:city":"Medina Campo",
    "sg:orig_category":"Librer\u00cdas",
    "sg:phone":"+34 983 80 24 39",
    "sg:postcode":"47400",
    "sg:province":"Valladolid",
    "wof:name":"Lopez Carabias Maria Flor",
    "wof:placetype":"venue"
},
  "geometry": {"coordinates":[-4.9126610756,41.3053131104],"type":"Point"}
}