{
  "type": "Feature",
  "properties": {
    "iso:country":"ES",
    "sg:address":"Calle de Estudios, 4",
    "sg:city":"Valladolid",
    "sg:orig_category":"Ingeniero",
    "sg:phone":"+34 983 29 69 29",
    "sg:postcode":"47005",
    "sg:province":"Valladolid",
    "wof:name":"Barba Rodriguez Augusto",
    "wof:placetype":"venue"
},
  "geometry": {"coordinates":[-4.7173380852,41.6532897949],"type":"Point"}
}