{
  "type": "Feature",
  "properties": {
    "addr:full":"Calle de Medico Duran, 25 Coru\u00d1a La Coru\u00f1a 15005",
    "addr:housenumber":"25",
    "addr:postcode":"15005",
    "addr:street":"Calle De;Corun\u0303A La Corun\u0303A",
    "iso:country":"ES",
    "sg:address":"Calle de Medico Duran, 25",
    "sg:city":"Coru\u00d1a",
    "sg:orig_category":"Impuestos, Tesoro P\u00dablico",
    "sg:phone":"+34 981 14 09 99",
    "sg:postcode":"15005",
    "sg:province":"La Coru\u00f1a",
    "wof:name":"Martinez Romero Rafael",
    "wof:placetype":"venue"
},
  "geometry": {"coordinates":[-8.4075679779,43.3605308533],"type":"Point"}
}