{
  "type": "Feature",
  "properties": {
    "addr:full":"Avda Granada, 57 Jaen Ja\u00e9n 23001",
    "addr:housenumber":"57;jae\u0301n",
    "addr:postcode":"23001",
    "addr:street":"Avda Granada",
    "iso:country":"ES",
    "sg:address":"Avda Granada, 57",
    "sg:city":"Jaen",
    "sg:orig_category":"Inform\u00c1tica (estudios, Servicios, Asesor\u00cda, Formaci\u00d3n)",
    "sg:phone":"+34 953 27 37 41",
    "sg:postcode":"23001",
    "sg:province":"Ja\u00e9n",
    "sg:website":"www.swin.net",
    "wof:name":"Centro De Informatica Softwin Jaen S.l.",
    "wof:placetype":"venue"
},
  "geometry": {"coordinates":[-3.7808120251,37.7696113586],"type":"Point"}
}