{
  "type": "Feature",
  "properties": {
    "iso:country":"ES",
    "sg:address":"Calle de Soto Galo, 17",
    "sg:city":"Logro\u00f1o",
    "sg:orig_category":"Mortero Y Material Para Jardines",
    "sg:phone":"+34 941 25 64 94",
    "sg:postcode":"26006",
    "sg:province":"La Rioja",
    "wof:name":"M.b.morteros S.l.",
    "wof:placetype":"venue"
},
  "geometry": {"coordinates":[-2.4036989212,42.46043396],"type":"Point"}
}