{
  "type": "Feature",
  "properties": {
    "iso:country":"ES",
    "sg:address":"Calle de La Cruz, 67",
    "sg:city":"Panticosa",
    "sg:orig_category":"Art\u00cdculos De Regalo (al Por Menor)",
    "sg:phone":"+34 974 48 72 47",
    "sg:postcode":"22661",
    "sg:province":"Huesca",
    "wof:name":"Vazquez Zaragoza Susana",
    "wof:placetype":"venue"
},
  "geometry": {"coordinates":[-0.2865389884,42.723739624],"type":"Point"}
}