{
  "type": "Feature",
  "properties": {
    "addr:full":"Calle de Miguel De Astigar, 9 Irun Guip\u00f9zcoa 20302",
    "addr:housenumber":"9",
    "addr:postcode":"20302",
    "addr:street":"Calle De Miguel De Astigar;Guipu\u0300Zcoa",
    "iso:country":"ES",
    "sg:address":"Calle de Miguel De Astigar, 9",
    "sg:city":"Irun",
    "sg:orig_category":"Inmobiliaria (agencias)",
    "sg:phone":"+34 943 66 61 05",
    "sg:postcode":"20302",
    "sg:province":"Guip\u00f9zcoa",
    "wof:name":"Blanco Viu S.l.",
    "wof:placetype":"venue"
},
  "geometry": {"coordinates":[-1.7943799496,43.3418655396],"type":"Point"}
}