{
  "type": "Feature",
  "properties": {
    "addr:full":"Calle de Pirineos, 3 Pedrola Zaragoza 50690",
    "addr:housenumber":"3",
    "addr:postcode":"50690",
    "addr:street":"Calle De Pirineos",
    "iso:country":"ES",
    "sg:address":"Calle de Pirineos, 3",
    "sg:city":"Pedrola",
    "sg:orig_category":"Comercio De Piezas De Recambio Y De Accesorios De Veh\u00cdculos, Veh\u00cdculos Industriales",
    "sg:phone":"+34 976 61 24 00",
    "sg:postcode":"50690",
    "sg:province":"Zaragoza",
    "wof:name":"Bosal Industrial Zaragoza S.a.",
    "wof:placetype":"venue"
},
  "geometry": {"coordinates":[-1.1834260225,41.7400779724],"type":"Point"}
}