{
  "type": "Feature",
  "properties": {
    "addr:full":"Calle de Gasco Oliag, 8 Valencia Valencia 46010",
    "addr:housenumber":"8",
    "addr:postcode":"46010",
    "addr:street":"Calle De;Oliag",
    "iso:country":"ES",
    "sg:address":"Calle de Gasco Oliag, 8",
    "sg:city":"Valencia",
    "sg:orig_category":"Molduras, Junquillos, Listones Y Molduras Perforadas",
    "sg:phone":"+34 963 61 00 23",
    "sg:postcode":"46010",
    "sg:province":"Valencia",
    "wof:name":"Feo Martinez Vicenta",
    "wof:placetype":"venue"
},
  "geometry": {"coordinates":[-0.3568710089,39.4791984558],"type":"Point"}
}