{
  "type": "Feature",
  "properties": {
    "iso:country":"ES",
    "sg:address":"Acera De La Yesera, 4",
    "sg:city":"Armilla",
    "sg:orig_category":"Deportes Diversos",
    "sg:phone":"+34 958 55 08 91",
    "sg:postcode":"18100",
    "sg:province":"Granada",
    "wof:name":"Federacion Granadina De Ciclismo",
    "wof:placetype":"venue"
},
  "geometry": {"coordinates":[-3.6233580112,37.1459732056],"type":"Point"}
}