{
  "type": "Feature",
  "properties": {
    "iso:country":"ES",
    "sg:address":"Calle de Alfonso De Castro, 21",
    "sg:city":"Salamanca",
    "sg:orig_category":"Farmacias",
    "sg:phone":"+34 923 22 44 87",
    "sg:postcode":"37005",
    "sg:province":"Salamanca",
    "wof:name":"Adela Gallego Y Ana Gonzalez C.b.",
    "wof:placetype":"venue"
},
  "geometry": {"coordinates":[-5.6597552299,40.973361969],"type":"Point"}
}