{
  "type": "Feature",
  "properties": {
    "iso:country":"ES",
    "sg:address":"Carr Valencia, 5",
    "sg:city":"Camprodon",
    "sg:orig_category":"Alimentaci\u00d3n General (al Por Menor)",
    "sg:phone":"+34 972 74 01 05",
    "sg:postcode":"17867",
    "sg:province":"Girona",
    "wof:name":"Moret Orriols Josep",
    "wof:placetype":"venue"
},
  "geometry": {"coordinates":[2.3655428886,42.3135070801],"type":"Point"}
}