{
  "type": "Feature",
  "properties": {
    "iso:country":"ES",
    "sg:address":"Ctra Logro\u00f1o-laguardia, Km. 0004,8",
    "sg:city":"Laguardia-biasteri",
    "sg:orig_category":"Productores Recolectores, Venta Directa De Vinos",
    "sg:phone":"+34 945 62 52 10",
    "sg:postcode":"01300",
    "sg:province":"\u00c1lava",
    "wof:name":"Compa\u00d1ia Vinicola Del Norte De Espa\u00d1a Cune",
    "wof:placetype":"venue"
},
  "geometry": {"coordinates":[-2.5706250668,42.5470809937],"type":"Point"}
}