{
  "type": "Feature",
  "properties": {
    "addr:full":"Calle de Zamacola, 61 Bilbao Vizcaya 48003",
    "addr:housenumber":"61",
    "addr:postcode":"48003",
    "addr:street":"Calle De Zamacola",
    "iso:country":"ES",
    "sg:address":"Calle de Zamacola, 61",
    "sg:city":"Bilbao",
    "sg:orig_category":"Pescader\u00cdas (al Por Menor)",
    "sg:phone":"+34 944 15 82 27",
    "sg:postcode":"48003",
    "sg:province":"Vizcaya",
    "wof:name":"Bustillo Merino Natividad",
    "wof:placetype":"venue"
},
  "geometry": {"coordinates":[-2.923101902,43.2413330078],"type":"Point"}
}