{
  "type": "Feature",
  "properties": {
    "iso:country":"ES",
    "sg:address":"Ctra Torrevieja, Km. 0007,0",
    "sg:city":"Bigastro",
    "sg:classifiers":[
        {
            "category":"Manufacturing",
            "subcategory":"Building Materials",
            "type":"Manufacturing & Wholesale Goods"
        }
    ],
    "sg:phone":"+34 965 35 00 76",
    "sg:postcode":"03380",
    "sg:province":"Alicante",
    "sg:tags":[
        "cemento",
        "y",
        "de",
        "fabricaci\u00d3n",
        "cal"
    ],
    "wof:name":"Prefabricados Bigastro S.a.",
    "wof:placetype":"venue"
},
  "geometry": {"coordinates":[-0.8838490248,38.0553817749],"type":"Point"}
}