{
  "type": "Feature",
  "properties": {
    "addr:full":"Carr Joanot Martorell, 13 Massamagrell Valencia 46130",
    "addr:housenumber":"13",
    "addr:postcode":"46130",
    "addr:street":"Carr Joanot Martorell",
    "iso:country":"ES",
    "sg:address":"Carr Joanot Martorell, 13",
    "sg:city":"Massamagrell",
    "sg:orig_category":"Aguas (distribuci\u00d3n, Servicios)",
    "sg:phone":"+34 961 45 10 94",
    "sg:postcode":"46130",
    "sg:province":"Valencia",
    "wof:name":"Aguas De Valencia S.a.",
    "wof:placetype":"venue"
},
  "geometry": {"coordinates":[-0.3322604001,39.5697097778],"type":"Point"}
}