{
  "type": "Feature",
  "properties": {
    "addr:full":"Calle de Rio Llano, 35 Toledo Toledo 45003",
    "addr:housenumber":"35",
    "addr:postcode":"45003",
    "addr:street":"Calle De Rio Llano",
    "iso:country":"ES",
    "sg:address":"Calle de Rio Llano, 35",
    "sg:city":"Toledo",
    "sg:orig_category":"Electrodom\u00c9sticos (al Por Menor)",
    "sg:phone":"+34 925 25 58 27",
    "sg:postcode":"45003",
    "sg:province":"Toledo",
    "wof:name":"Rusan Servicio Tecnico S.l.",
    "wof:placetype":"venue"
},
  "geometry": {"coordinates":[-4.0217418671,39.8643188477],"type":"Point"}
}