{
  "type": "Feature",
  "properties": {
    "iso:country":"ES",
    "sg:address":"Avda Betanzos, 42",
    "sg:city":"Madrid",
    "sg:orig_category":"Tintes (fabricaci\u00d3n, Al Por Mayor)",
    "sg:phone":"+34 917 30 97 48",
    "sg:postcode":"28029",
    "sg:province":"Madrid",
    "wof:name":"Blazquez Moreno Joaquin",
    "wof:placetype":"venue"
},
  "geometry": {"coordinates":[-3.7113380432,40.4759635925],"type":"Point"}
}