{
  "type": "Feature",
  "properties": {
    "addr:full":"Calle de Cura Francisco Lopez Hurtado, 10 Alcantarilla Murcia 30820",
    "addr:housenumber":"10",
    "addr:postcode":"30820",
    "addr:street":"Calle De Cura Francisco Lopez Hurtado",
    "iso:country":"ES",
    "sg:address":"Calle de Cura Francisco Lopez Hurtado, 10",
    "sg:city":"Alcantarilla",
    "sg:orig_category":"Agencias Y Agentes Comerciales, Representantes",
    "sg:phone":"+34 968 89 56 67",
    "sg:postcode":"30820",
    "sg:province":"Murcia",
    "wof:name":"Menchon Guillen David",
    "wof:placetype":"venue"
},
  "geometry": {"coordinates":[-1.2024116516,37.9718437195],"type":"Point"}
}