{
  "type": "Feature",
  "properties": {
    "addr:full":"Ctra. Cuenca, S/n Minglanilla Cuenca 16260",
    "addr:housenumber":"s / n",
    "addr:postcode":"16260",
    "addr:street":"Ctra. Cuenca",
    "iso:country":"ES",
    "sg:address":"Ctra. Cuenca, S/n",
    "sg:city":"Minglanilla",
    "sg:orig_category":"Centros De Educaci\u00d3n Especial",
    "sg:phone":"+34 962 18 72 18",
    "sg:postcode":"16260",
    "sg:province":"Cuenca",
    "wof:name":"Colegio Nacional Princesa Sofia",
    "wof:placetype":"venue"
},
  "geometry": {"coordinates":[-1.5995140076,39.5386962891],"type":"Point"}
}