{
  "type": "Feature",
  "properties": {
    "iso:country":"ES",
    "sg:address":"Carr Cavallers, 54",
    "sg:city":"Palafrugell",
    "sg:orig_category":"Zapatos (al Por Menor)",
    "sg:phone":"+34 972 61 05 90",
    "sg:postcode":"17200",
    "sg:province":"Girona",
    "wof:name":"Calzados Vives S.l.",
    "wof:placetype":"venue"
},
  "geometry": {"coordinates":[3.1640739441,41.9167175293],"type":"Point"}
}