{
  "type": "Feature",
  "properties": {
    "iso:country":"ES",
    "sg:address":"Carrer de Santa Rosa, 32",
    "sg:city":"Esplugues Llobregat",
    "sg:orig_category":"Asesor\u00cda Sobre Comunicaci\u00d3n De Empresas",
    "sg:phone":"+34 934 70 50 89",
    "sg:postcode":"08950",
    "sg:province":"Barcelona",
    "sg:website":"www.beachsoccer.com",
    "wof:name":"Pro Beach Soccer S.l.",
    "wof:placetype":"venue"
},
  "geometry": {"coordinates":[2.1016359329,41.3848495483],"type":"Point"}
}