{
  "type": "Feature",
  "properties": {
    "iso:country":"ES",
    "sg:address":"Calle de Bertolt Brecht, 44",
    "sg:city":"Alcala Henares",
    "sg:orig_category":"Trabajos De Soldaduras",
    "sg:phone":"+34 918 02 29 40",
    "sg:postcode":"28806",
    "sg:province":"Madrid",
    "wof:name":"Palacio Anelo Isabel",
    "wof:placetype":"venue"
},
  "geometry": {"coordinates":[-3.3698892593,40.4973640442],"type":"Point"}
}