{
  "type": "Feature",
  "properties": {
    "iso:country":"ES",
    "sg:address":"Calle de Do\u00d1a Iluminada, 1",
    "sg:city":"Oviedo",
    "sg:orig_category":"Desinfecci\u00d3n, Desinsectaci\u00d3n, Desratizaci\u00d3n",
    "sg:phone":"+34 985 28 76 42",
    "sg:postcode":"33011",
    "sg:province":"Asturias",
    "wof:name":"Fumigon S.l.",
    "wof:placetype":"venue"
},
  "geometry": {"coordinates":[-5.8168239594,43.3837509155],"type":"Point"}
}