{
  "type": "Feature",
  "properties": {
    "iso:country":"ES",
    "sg:address":"Pl. Cde Rodezno, 8",
    "sg:city":"Iru\u00f1a",
    "sg:orig_category":"M\u00c9dicos: Psiquiatr\u00cda",
    "sg:phone":"+34 948 23 62 14",
    "sg:postcode":"31003",
    "sg:province":"Navarra",
    "wof:name":"Del Amo Del Villar Francisco",
    "wof:placetype":"venue"
},
  "geometry": {"coordinates":[-1.6437540054,42.81275177],"type":"Point"}
}