{
  "type": "Feature",
  "properties": {
    "iso:country":"ES",
    "sg:address":"Carrer de Nou, 10",
    "sg:city":"Batea",
    "sg:orig_category":"Molduras, Junquillos, Listones Y Molduras Perforadas",
    "sg:phone":"+34 977 43 02 89",
    "sg:postcode":"43786",
    "sg:province":"Tarragona",
    "wof:name":"El Caliu C.b.",
    "wof:placetype":"venue"
},
  "geometry": {"coordinates":[0.3128409982,41.0938262939],"type":"Point"}
}