{
  "type": "Feature",
  "properties": {
    "iso:country":"ES",
    "sg:address":"Calle de Procion, 26",
    "sg:city":"Zaragoza",
    "sg:orig_category":"Contenedores (mercanc\u00cdas)",
    "sg:phone":"+34 976 75 38 93",
    "sg:postcode":"50012",
    "sg:province":"Zaragoza",
    "wof:name":"Cano Alzorriz Manuel",
    "wof:placetype":"venue"
},
  "geometry": {"coordinates":[-0.9276649952,41.6384658813],"type":"Point"}
}