{
  "type": "Feature",
  "properties": {
    "addr:full":"Carr Josep Monterde, 12 Puig Valencia 46540",
    "addr:housenumber":"12",
    "addr:postcode":"46540",
    "addr:street":"Carr Josep Monterde",
    "iso:country":"ES",
    "sg:address":"Carr Josep Monterde, 12",
    "sg:city":"Puig",
    "sg:orig_category":"Muebles, Minoristas",
    "sg:phone":"+34 961 47 11 80",
    "sg:postcode":"46540",
    "sg:province":"Valencia",
    "sg:website":"www.abetos.com",
    "wof:name":"Gasco Ma\u00f1es Carmen",
    "wof:placetype":"venue"
},
  "geometry": {"coordinates":[-0.3013620079,39.5888442993],"type":"Point"}
}