{
  "type": "Feature",
  "properties": {
    "addr:full":"Calle de Jesus Nazareno, 1 Albacete Albacete 02002",
    "addr:housenumber":"1",
    "addr:postcode":"02002",
    "addr:street":"Calle De Jesus Nazareno",
    "iso:country":"ES",
    "sg:address":"Calle de Jesus Nazareno, 1",
    "sg:city":"Albacete",
    "sg:orig_category":"Fabricaci\u00d3n De Fundas",
    "sg:phone":"+34 967 24 11 44",
    "sg:postcode":"02002",
    "sg:province":"Albacete",
    "wof:name":"Alarcon Conde Manuel",
    "wof:placetype":"venue"
},
  "geometry": {"coordinates":[-1.8538850546,38.9908752441],"type":"Point"}
}