{
  "type": "Feature",
  "properties": {
    "iso:country":"ES",
    "sg:address":"Carrer de Sant Pere, 1",
    "sg:city":"Terrassa",
    "sg:orig_category":"Lencer\u00cda Femenina, Corseter\u00cda, Trajes De Ba\u00d1o (al Por Menor)",
    "sg:phone":"+34 937 88 00 84",
    "sg:postcode":"08221",
    "sg:province":"Barcelona",
    "wof:name":"Altisen Serra Teresa",
    "wof:placetype":"venue"
},
  "geometry": {"coordinates":[2.0109143257,41.56300354],"type":"Point"}
}