{
  "type": "Feature",
  "properties": {
    "addr:full":"Arimazubi, 1 Arrasate Guip\u00f9zcoa 20500",
    "addr:housenumber":"1",
    "addr:postcode":"20500",
    "addr:street":"Arimazubi;Guipu\u0300Zcoa",
    "iso:country":"ES",
    "sg:address":"Arimazubi, 1",
    "sg:city":"Arrasate",
    "sg:orig_category":"Promotores Constructores",
    "sg:phone":"+34 943 71 26 71",
    "sg:postcode":"20500",
    "sg:province":"Guip\u00f9zcoa",
    "wof:name":"Construcciones Y Reformas Hiboi S.l.",
    "wof:placetype":"venue"
},
  "geometry": {"coordinates":[-2.4949359894,43.0619049072],"type":"Point"}
}