{
  "type": "Feature",
  "properties": {
    "addr:full":"Calle de San Juan, 2 Morro Jable Las Palmas 35625",
    "addr:housenumber":"2",
    "addr:postcode":"35625",
    "addr:street":"Calle De San Juan",
    "iso:country":"ES",
    "sg:address":"Calle de San Juan, 2",
    "sg:city":"Morro Jable",
    "sg:orig_category":"Ropa Para Ni\u00d1os (al Por Menor)",
    "sg:phone":"+34 928 54 20 16",
    "sg:postcode":"35625",
    "sg:province":"Las Palmas",
    "wof:name":"Que Pasa Fuerteventura S.l.",
    "wof:placetype":"venue"
},
  "geometry": {"coordinates":[-14.352388382,28.0502471924],"type":"Point"}
}