{
  "type": "Feature",
  "properties": {
    "iso:country":"ES",
    "sg:address":"Carrer de Lleida, 50",
    "sg:city":"Prat Llobregat",
    "sg:orig_category":"Papeler\u00cdas, Librer\u00cdas",
    "sg:phone":"+34 933 70 10 68",
    "sg:postcode":"08820",
    "sg:province":"Barcelona",
    "wof:name":"Saurat Borras Silvia",
    "wof:placetype":"venue"
},
  "geometry": {"coordinates":[2.0926969051,41.3212432861],"type":"Point"}
}