{
  "type": "Feature",
  "properties": {
    "iso:country":"ES",
    "sg:address":"Las Cendeas, 1",
    "sg:city":"Iru\u00f1a",
    "sg:orig_category":"Electricidad: Instalaciones Industriales",
    "sg:phone":"+34 948 12 77 44",
    "sg:postcode":"31014",
    "sg:province":"Navarra",
    "wof:name":"Electridad Azanza S.l.",
    "wof:placetype":"venue"
},
  "geometry": {"coordinates":[-1.6526839733,42.8285293579],"type":"Point"}
}