{
  "type": "Feature",
  "properties": {
    "iso:country":"ES",
    "sg:address":"Rua Manuel Rodriguez, 66",
    "sg:city":"Porri\u00f1o",
    "sg:orig_category":"T\u00c9cnicos Veterinarios",
    "sg:phone":"+34 986 33 49 42",
    "sg:postcode":"36400",
    "sg:province":"Pontevedra",
    "wof:name":"Albeitar Servicios Veterinarios C De B",
    "wof:placetype":"venue"
},
  "geometry": {"coordinates":[-8.6204023361,42.1578598022],"type":"Point"}
}