{
  "type": "Feature",
  "properties": {
    "iso:country":"ES",
    "sg:address":"Avda Marconi, S/n",
    "sg:city":"Madrid",
    "sg:orig_category":"Comercio De Piezas De Recambio Y De Accesorios De Veh\u00cdculos, Veh\u00cdculos Industriales",
    "sg:phone":"+34 917 10 99 30",
    "sg:postcode":"28021",
    "sg:province":"Madrid",
    "wof:name":"Comercial Del Motor S.a.",
    "wof:placetype":"venue"
},
  "geometry": {"coordinates":[-3.695168972,40.3340301514],"type":"Point"}
}