{
  "type": "Feature",
  "properties": {
    "iso:country":"ES",
    "sg:address":"Errekatxu Kalea, 4",
    "sg:city":"Eibar",
    "sg:orig_category":"Metales (labores, Pulido)",
    "sg:phone":"+34 943 70 21 90",
    "sg:postcode":"20600",
    "sg:province":"Guip\u00f9zcoa",
    "wof:name":"Simes Senco S.a.",
    "wof:placetype":"venue"
},
  "geometry": {"coordinates":[-2.4689850807,43.1841506958],"type":"Point"}
}