{
  "type": "Feature",
  "properties": {
    "iso:country":"ES",
    "sg:address":"Cno Motor De La Torre, 15",
    "sg:city":"Sangonera Seca",
    "sg:orig_category":"Mudanzas",
    "sg:phone":"+34 968 86 82 06",
    "sg:postcode":"30835",
    "sg:province":"Murcia",
    "wof:name":"Garcia Pellicer Francisco",
    "wof:placetype":"venue"
},
  "geometry": {"coordinates":[-1.1298867464,37.9834747314],"type":"Point"}
}