{
  "type": "Feature",
  "properties": {
    "addr:full":"Eskola Kalea, 3 Andoain Guip\u00f9zcoa 20140",
    "addr:housenumber":"3",
    "addr:postcode":"20140",
    "addr:street":"Eskola Kalea;Guipu\u0300Zcoa",
    "iso:country":"ES",
    "sg:address":"Eskola Kalea, 3",
    "sg:city":"Andoain",
    "sg:orig_category":"Asesor\u00cda Sobre Comunicaci\u00d3n De Empresas",
    "sg:phone":"+34 943 30 08 21",
    "sg:postcode":"20140",
    "sg:province":"Guip\u00f9zcoa",
    "wof:name":"Bartolome & Ajona Asesores S.l.",
    "wof:placetype":"venue"
},
  "geometry": {"coordinates":[-2.0216629505,43.2173042297],"type":"Point"}
}