{
  "type": "Feature",
  "properties": {
    "addr:full":"Calle de Cardenal Herrera Oria, 1 Estepona M\u00e1laga 29680",
    "addr:housenumber":"1",
    "addr:postcode":"29680",
    "addr:street":"Calle De Cardenal Herrera Oria",
    "iso:country":"ES",
    "sg:address":"Calle de Cardenal Herrera Oria, 1",
    "sg:city":"Estepona",
    "sg:orig_category":"Molduras, Junquillos, Listones Y Molduras Perforadas",
    "sg:phone":"+34 952 80 47 50",
    "sg:postcode":"29680",
    "sg:province":"M\u00e1laga",
    "wof:name":"Fernandez Garcia Manuel",
    "wof:placetype":"venue"
},
  "geometry": {"coordinates":[-5.1476006508,36.4293861389],"type":"Point"}
}