{
  "type": "Feature",
  "properties": {
    "iso:country":"ES",
    "sg:address":"Trva Carabanchel, 8",
    "sg:city":"Getafe",
    "sg:orig_category":"Aluminio Y Aleaciones (producci\u00d3n, Transformaci\u00d3n, Negocio)",
    "sg:phone":"+34 916 95 68 81",
    "sg:postcode":"28902",
    "sg:province":"Madrid",
    "wof:name":"Carpinteria De Aluminio Gama S.l.",
    "wof:placetype":"venue"
},
  "geometry": {"coordinates":[-3.7283010483,40.3135261536],"type":"Point"}
}