{
  "type": "Feature",
  "properties": {
    "addr:full":"Aginaga Auzoa, 22 Aginaga Guip\u00f9zcoa 20170",
    "addr:housenumber":"22",
    "addr:postcode":"20170",
    "addr:street":"Aginaga Auzoa;Guipu\u0300Zcoa",
    "iso:country":"ES",
    "sg:address":"Aginaga Auzoa, 22",
    "sg:city":"Aginaga",
    "sg:orig_category":"Semiller\u00cdas",
    "sg:phone":"+34 943 36 64 60",
    "sg:postcode":"20170",
    "sg:province":"Guip\u00f9zcoa",
    "wof:name":"Aramburu Alcorta Jose Manuel",
    "wof:placetype":"venue"
},
  "geometry": {"coordinates":[-2.0740373135,43.2733612061],"type":"Point"}
}