{
  "type": "Feature",
  "properties": {
    "addr:full":"Calle de Obispo Rey Redondo, 10 San Cristobal De La Laguna Santa Cruz De Tenerife 38201",
    "addr:housenumber":"10",
    "addr:postcode":"38201",
    "addr:street":"Calle De Obispo Rey Redondo",
    "iso:country":"ES",
    "sg:address":"Calle de Obispo Rey Redondo, 10",
    "sg:city":"San Cristobal De La Laguna",
    "sg:orig_category":"M\u00c9dicos: Estomatolog\u00cda",
    "sg:phone":"+34 922 26 44 04",
    "sg:postcode":"38201",
    "sg:province":"Santa Cruz De Tenerife",
    "wof:name":"Gonzalez Rodriguez Carlos",
    "wof:placetype":"venue"
},
  "geometry": {"coordinates":[-16.3153381348,28.4880867004],"type":"Point"}
}