{
  "type": "Feature",
  "properties": {
    "iso:country":"ES",
    "sg:address":"Plaz Espa\u00d1a, 12",
    "sg:city":"Herencia",
    "sg:orig_category":"Ropa Para Ni\u00d1os (al Por Menor)",
    "sg:phone":"+34 926 57 26 46",
    "sg:postcode":"13640",
    "sg:province":"Ciudad Real",
    "wof:name":"Mai Picias S.l.l",
    "wof:placetype":"venue"
},
  "geometry": {"coordinates":[-3.3544080257,39.3669624329],"type":"Point"}
}