{
  "type": "Feature",
  "properties": {
    "addr:full":"Rua Clerigos (dos), 23 Lugo Lugo 27001",
    "addr:housenumber":"23",
    "addr:postcode":"27001",
    "addr:street":"Rua Clerigos Dos",
    "iso:country":"ES",
    "sg:address":"Rua Clerigos (dos), 23",
    "sg:city":"Lugo",
    "sg:classifiers":[
        {
            "category":"Casinos & Gambling",
            "type":"Entertainment"
        }
    ],
    "sg:phone":"+34 982 22 88 85",
    "sg:postcode":"27001",
    "sg:province":"Lugo",
    "sg:tags":[
        "locale",
        "de",
        "juego"
    ],
    "wof:name":"Servicios De Juego S.a.",
    "wof:placetype":"venue"
},
  "geometry": {"coordinates":[-7.558052063,43.0085830688],"type":"Point"}
}