{
  "type": "Feature",
  "properties": {
    "iso:country":"ES",
    "sg:address":"Calle de Arrayanes, 31",
    "sg:city":"Ciudad Real",
    "sg:orig_category":"Transportes Por V\u00cdas Navegables",
    "sg:phone":"+34 926 21 63 84",
    "sg:postcode":"13005",
    "sg:province":"Ciudad Real",
    "wof:name":"Alcazar Perez Maria Francisca",
    "wof:placetype":"venue"
},
  "geometry": {"coordinates":[-3.9444065094,38.9733161926],"type":"Point"}
}