{
  "type": "Feature",
  "properties": {
    "addr:full":"Calle de Santiago, S/n Arzua La Coru\u00f1a 15810",
    "addr:housenumber":"s / n",
    "addr:postcode":"15810",
    "addr:street":"Calle De Santiago;La Corun\u0303A",
    "iso:country":"ES",
    "sg:address":"Calle de Santiago, S/n",
    "sg:city":"Arzua",
    "sg:orig_category":"Cerrajer\u00cda, Ferrallista",
    "sg:phone":"+34 981 50 04 83",
    "sg:postcode":"15810",
    "sg:province":"La Coru\u00f1a",
    "wof:name":"Mato Parrado Antonio",
    "wof:placetype":"venue"
},
  "geometry": {"coordinates":[-8.1644639969,42.9269065857],"type":"Point"}
}