{
  "type": "Feature",
  "properties": {
    "addr:full":"Avda Iparragirre, 68 Leioa Vizcaya 48940",
    "addr:housenumber":"68",
    "addr:postcode":"48940",
    "addr:street":"Avda Iparragirre",
    "iso:country":"ES",
    "sg:address":"Avda Iparragirre, 68",
    "sg:city":"Leioa",
    "sg:orig_category":"Herboristas (al Por Menor)",
    "sg:phone":"+34 944 80 06 18",
    "sg:postcode":"48940",
    "sg:province":"Vizcaya",
    "wof:name":"Celia Blanca Rivadulla Lorenzo - Dietetica",
    "wof:placetype":"venue"
},
  "geometry": {"coordinates":[-2.9872219563,43.325378418],"type":"Point"}
}