{
  "type": "Feature",
  "properties": {
    "iso:country":"ES",
    "sg:address":"Poligono Industrial De Bayas, S/n",
    "sg:city":"Miranda Ebro",
    "sg:orig_category":"Importaci\u00d3n",
    "sg:phone":"+34 947 31 12 06",
    "sg:postcode":"09200",
    "sg:province":"Burgos",
    "wof:name":"Garcia Molina Ramon",
    "wof:placetype":"venue"
},
  "geometry": {"coordinates":[-2.9675571918,42.6790657043],"type":"Point"}
}