{
  "type": "Feature",
  "properties": {
    "iso:country":"ES",
    "sg:address":"Calle de Carretera, 5",
    "sg:city":"S. Martin Valle",
    "sg:orig_category":"Empresas De Desmonte",
    "sg:phone":"+34 979 88 40 45",
    "sg:postcode":"34134",
    "sg:province":"Palencia",
    "wof:name":"Diez Manso Jesus",
    "wof:placetype":"venue"
},
  "geometry": {"coordinates":[-4.7547049522,42.4381332397],"type":"Point"}
}