{
  "type": "Feature",
  "properties": {
    "iso:country":"ES",
    "sg:address":"Rua Santo Domingo, 60",
    "sg:city":"Ourense",
    "sg:orig_category":"Peluqueros: De Se\u00d1oras",
    "sg:phone":"+34 988 23 25 57",
    "sg:postcode":"32003",
    "sg:province":"Ourense",
    "wof:name":"Conde Feijoo Adosinda",
    "wof:placetype":"venue"
},
  "geometry": {"coordinates":[-7.8628320694,42.3399772644],"type":"Point"}
}