{
  "type": "Feature",
  "properties": {
    "iso:country":"ES",
    "sg:address":"Calle de Trespaderne, 29",
    "sg:city":"Madrid",
    "sg:orig_category":"Contenedores (mercanc\u00cdas)",
    "sg:phone":"+34 917 47 28 06",
    "sg:postcode":"28042",
    "sg:province":"Madrid",
    "wof:name":"Newcargo S.l.",
    "wof:placetype":"venue"
},
  "geometry": {"coordinates":[-3.5840411186,40.4532623291],"type":"Point"}
}