{
  "type": "Feature",
  "properties": {
    "addr:full":"Carrer de Montserrat, 55 Martorell Barcelona 08760",
    "addr:housenumber":"55",
    "addr:postcode":"08760",
    "addr:street":"Carrer De Montserrat",
    "iso:country":"ES",
    "sg:address":"Carrer de Montserrat, 55",
    "sg:city":"Martorell",
    "sg:orig_category":"Dom\u00d3tica",
    "sg:phone":"+34 937 75 10 02",
    "sg:postcode":"08760",
    "sg:province":"Barcelona",
    "wof:name":"Artsdomotica S.c.p.",
    "wof:placetype":"venue"
},
  "geometry": {"coordinates":[1.9255950451,41.4779777527],"type":"Point"}
}