{
  "type": "Feature",
  "properties": {
    "addr:full":"Pla\u00c7 Del Mestre Ferrero, 1 Ontinyent Valencia 46870",
    "addr:postcode":"46870",
    "iso:country":"ES",
    "sg:address":"Pla\u00c7 Del Mestre Ferrero, 1",
    "sg:city":"Ontinyent",
    "sg:orig_category":"Panader\u00cdas, Panader\u00cdas",
    "sg:phone":"+34 962 91 06 37",
    "sg:postcode":"46870",
    "sg:province":"Valencia",
    "wof:name":"Hijo De Teodoro Mora S. A.",
    "wof:placetype":"venue"
},
  "geometry": {"coordinates":[-0.6583330035,38.7977752686],"type":"Point"}
}