{
  "type": "Feature",
  "properties": {
    "iso:country":"ES",
    "sg:address":"Avda Murcia, 18",
    "sg:city":"Albatera",
    "sg:orig_category":"Maquinaria Para Industrias Diversas",
    "sg:phone":"+34 965 48 60 74",
    "sg:postcode":"03340",
    "sg:province":"Alicante",
    "wof:name":"Garcia Canto Jose Fernando",
    "wof:placetype":"venue"
},
  "geometry": {"coordinates":[-0.8761669993,38.176776886],"type":"Point"}
}