{
  "type": "Feature",
  "properties": {
    "iso:country":"ES",
    "sg:address":"Afores, S/n",
    "sg:city":"Ra\u00efmat",
    "sg:classifiers":[
        {
            "category":"Sports & Exercise",
            "subcategory":"Golf",
            "type":"Entertainment"
        }
    ],
    "sg:phone":"+34 973 73 74 83",
    "sg:postcode":"25111",
    "sg:province":"Lleida",
    "sg:tags":[
        "y",
        "de",
        "campos",
        "clases"
    ],
    "wof:name":"Raimat Golf Club",
    "wof:placetype":"venue"
},
  "geometry": {"coordinates":[0.4778549969,41.6793136597],"type":"Point"}
}