{
  "type": "Feature",
  "properties": {
    "iso:country":"ES",
    "sg:address":"Calle de Princesa, 2",
    "sg:city":"Madrid",
    "sg:orig_category":"Librer\u00cdas",
    "sg:phone":"+34 915 47 30 78",
    "sg:postcode":"28008",
    "sg:province":"Madrid",
    "wof:name":"Alvarez Dominguez Alberto",
    "wof:placetype":"venue"
},
  "geometry": {"coordinates":[-3.7183656693,40.4335021973],"type":"Point"}
}