{
  "type": "Feature",
  "properties": {
    "addr:full":"Calle de San Sebastian, 9 Dos Hermanas Sevilla 41700",
    "addr:housenumber":"9",
    "addr:postcode":"41700",
    "addr:street":"Calle De San Sebastian;Sevilla",
    "iso:country":"ES",
    "sg:address":"Calle de San Sebastian, 9",
    "sg:city":"Dos Hermanas",
    "sg:orig_category":"Mercer\u00cda, Lencer\u00cda (al Por Menor)",
    "sg:phone":"+34 955 66 74 12",
    "sg:postcode":"41700",
    "sg:province":"Sevilla",
    "wof:name":"Olmedo Barbero Jose",
    "wof:placetype":"venue"
},
  "geometry": {"coordinates":[-5.9205942154,37.2809906006],"type":"Point"}
}