{
  "type": "Feature",
  "properties": {
    "addr:full":"Calle de Doctor Cajal, 2 Tomelloso Ciudad Real 13700",
    "addr:housenumber":"2",
    "addr:postcode":"13700",
    "addr:street":"Calle De Doctor Cajal",
    "iso:country":"ES",
    "sg:address":"Calle de Doctor Cajal, 2",
    "sg:city":"Tomelloso",
    "sg:orig_category":"Asociaciones Ecologistas",
    "sg:phone":"+34 926 51 49 12",
    "sg:postcode":"13700",
    "sg:province":"Ciudad Real",
    "wof:name":"Comunidad De Regantes Y Usuarios Del Acuifero 23 De Alcazar",
    "wof:placetype":"venue"
},
  "geometry": {"coordinates":[-3.0239663124,39.1513023376],"type":"Point"}
}