{
  "type": "Feature",
  "properties": {
    "iso:country":"ES",
    "sg:address":"Calle de Marques De Lozoya, 3",
    "sg:city":"Madrid",
    "sg:orig_category":"Peluquer\u00cdas, Peluquer\u00cda Mixta",
    "sg:phone":"+34 915 04 39 40",
    "sg:postcode":"28007",
    "sg:province":"Madrid",
    "sg:website":"www.rizos.es",
    "wof:name":"Pe\u00f1a Domingo Miriam",
    "wof:placetype":"venue"
},
  "geometry": {"coordinates":[-3.6651890278,40.4168357849],"type":"Point"}
}