{
  "type": "Feature",
  "properties": {
    "iso:country":"ES",
    "sg:address":"Carrer de Mas De La Mora, 20",
    "sg:city":"Vic",
    "sg:orig_category":"Fabricaci\u00d3n De Moldes Y Modelos",
    "sg:phone":"+34 938 86 27 55",
    "sg:postcode":"08500",
    "sg:province":"Barcelona",
    "wof:name":"Manufactures De Plastics Sola S.a.",
    "wof:placetype":"venue"
},
  "geometry": {"coordinates":[2.2713649273,41.9492607117],"type":"Point"}
}