{
  "type": "Feature",
  "properties": {
    "iso:country":"ES",
    "sg:address":"Pol Ind Plasencia, S/n",
    "sg:city":"Plasencia",
    "sg:orig_category":"Promotores Constructores",
    "sg:phone":"+34 927 41 41 81",
    "sg:postcode":"10600",
    "sg:province":"C\u00e1ceres",
    "wof:name":"Hidromantes, S.l.",
    "wof:placetype":"venue"
},
  "geometry": {"coordinates":[-6.0649971962,40.014591217],"type":"Point"}
}