{
  "type": "Feature",
  "properties": {
    "addr:full":"Av Pare Huguet, Del, 64 Alaior Islas Baleares 07730",
    "addr:housenumber":"64",
    "addr:postcode":"07730",
    "addr:street":"Av Pare Huguet Del",
    "iso:country":"ES",
    "sg:address":"Av Pare Huguet, Del, 64",
    "sg:city":"Alaior",
    "sg:orig_category":"Inmobiliaria (agencias)",
    "sg:phone":"+34 971 37 14 99",
    "sg:postcode":"07730",
    "sg:province":"Islas Baleares",
    "wof:name":"Gomila Pons Jose",
    "wof:placetype":"venue"
},
  "geometry": {"coordinates":[4.1383051872,39.9308853149],"type":"Point"}
}