{
  "type": "Feature",
  "properties": {
    "iso:country":"ES",
    "sg:address":"Calle de Cubo, 7",
    "sg:city":"Santander",
    "sg:orig_category":"Abogados",
    "sg:phone":"+34 942 21 09 69",
    "sg:postcode":"39001",
    "sg:province":"Cantabria",
    "wof:name":"Fernandez Garrido Vicente",
    "wof:placetype":"venue"
},
  "geometry": {"coordinates":[-3.8094007969,43.4631156921],"type":"Point"}
}