{
  "type": "Feature",
  "properties": {
    "addr:full":"Avda Osa Mayor, 56 Madrid Madrid 28023",
    "addr:housenumber":"56",
    "addr:postcode":"madrid;28023",
    "addr:street":"Avda Osa Mayor",
    "iso:country":"ES",
    "sg:address":"Avda Osa Mayor, 56",
    "sg:city":"Madrid",
    "sg:orig_category":"Molduras, Junquillos, Listones Y Molduras Perforadas",
    "sg:phone":"+34 913 07 07 10",
    "sg:postcode":"28023",
    "sg:province":"Madrid",
    "wof:name":"Cimarra Martin Juan",
    "wof:placetype":"venue"
},
  "geometry": {"coordinates":[-3.7821888924,40.4592208862],"type":"Point"}
}