{
  "type": "Feature",
  "properties": {
    "iso:country":"ES",
    "sg:address":"Carrer de Marcelino Menendez Pelayo, 7",
    "sg:city":"Cornella Llobregat",
    "sg:orig_category":"Molduras, Junquillos, Listones Y Molduras Perforadas",
    "sg:phone":"+34 933 77 12 81",
    "sg:postcode":"08940",
    "sg:province":"Barcelona",
    "wof:name":"Barea Blesa Jorge",
    "wof:placetype":"venue"
},
  "geometry": {"coordinates":[2.0706601143,41.352809906],"type":"Point"}
}