{
  "type": "Feature",
  "properties": {
    "addr:full":"Calle de Cadiz, 66 Puebla Vicar Almer\u00eda 04738",
    "addr:housenumber":"66",
    "addr:postcode":"04738",
    "addr:street":"Calle De Cadiz",
    "iso:country":"ES",
    "sg:address":"Calle de Cadiz, 66",
    "sg:city":"Puebla Vicar",
    "sg:orig_category":"Panader\u00cdas, Panader\u00cdas",
    "sg:phone":"+34 950 55 43 63",
    "sg:postcode":"04738",
    "sg:province":"Almer\u00eda",
    "wof:name":"Dulce Maravillas S.l.",
    "wof:placetype":"venue"
},
  "geometry": {"coordinates":[-2.6493330002,36.8015670776],"type":"Point"}
}