{
  "type": "Feature",
  "properties": {
    "addr:full":"Calle de San Sebastian, 14 Campillos M\u00e1laga 29320",
    "addr:housenumber":"14",
    "addr:postcode":"29320",
    "addr:street":"Calle De San Sebastian",
    "iso:country":"ES",
    "sg:address":"Calle de San Sebastian, 14",
    "sg:city":"Campillos",
    "sg:orig_category":"Pintura Y Barniz (al Por Menor)",
    "sg:phone":"+34 952 72 27 01",
    "sg:postcode":"29320",
    "sg:province":"M\u00e1laga",
    "sg:website":"www.miguelcaceres.com",
    "wof:name":"Miguel Caceres S. A.",
    "wof:placetype":"venue"
},
  "geometry": {"coordinates":[-4.8639121056,37.0477676392],"type":"Point"}
}