{
  "type": "Feature",
  "properties": {
    "addr:full":"Camilo Perez, 21 Pego Alicante 03780",
    "addr:housenumber":"21",
    "addr:postcode":"03780",
    "addr:street":"Camilo Perez",
    "iso:country":"ES",
    "sg:address":"Camilo Perez, 21",
    "sg:city":"Pego",
    "sg:orig_category":"Ortopedia General",
    "sg:phone":"+34 966 40 03 08",
    "sg:postcode":"03780",
    "sg:province":"Alicante",
    "wof:name":"Ortopedia Vimar S.l.",
    "wof:placetype":"venue"
},
  "geometry": {"coordinates":[-0.1168780029,38.8402709961],"type":"Point"}
}