{
  "type": "Feature",
  "properties": {
    "iso:country":"ES",
    "sg:address":"Calle de Hermanos Becquer, 5",
    "sg:city":"Madrid",
    "sg:orig_category":"Agencias Y Agentes Comerciales, Representantes",
    "sg:phone":"+34 915 63 96 82",
    "sg:postcode":"28006",
    "sg:province":"Madrid",
    "wof:name":"Iberavia Internacional S. A.",
    "wof:placetype":"venue"
},
  "geometry": {"coordinates":[-3.6878070831,40.4363975525],"type":"Point"}
}