{
  "type": "Feature",
  "properties": {
    "addr:full":"Pase Jose Fernandez Vega, 59 Brenes Sevilla 41310",
    "addr:housenumber":"59",
    "addr:postcode":"41310",
    "addr:street":"Vega",
    "iso:country":"ES",
    "sg:address":"Pase Jose Fernandez Vega, 59",
    "sg:city":"Brenes",
    "sg:orig_category":"Parques De Atracciones Y Centros De Esparcimiento",
    "sg:phone":"+34 955 65 35 72",
    "sg:postcode":"41310",
    "sg:province":"Sevilla",
    "wof:name":"Valisa Internacional S.a.",
    "wof:placetype":"venue"
},
  "geometry": {"coordinates":[-5.868019104,37.5461044312],"type":"Point"}
}