{
  "type": "Feature",
  "properties": {
    "addr:full":"Avda Reyes Catolicos, 95 Villarrobledo Albacete 02600",
    "addr:housenumber":"95",
    "addr:postcode":"02600",
    "addr:street":"Avda Reyes Catolicos",
    "iso:country":"ES",
    "sg:address":"Avda Reyes Catolicos, 95",
    "sg:city":"Villarrobledo",
    "sg:orig_category":"Suministros Para Carrocer\u00cdas",
    "sg:phone":"+34 967 14 14 34",
    "sg:postcode":"02600",
    "sg:province":"Albacete",
    "wof:name":"Carrocerias Y Cisternas Alite S.l.",
    "wof:placetype":"venue"
},
  "geometry": {"coordinates":[-2.5969569683,39.2675018311],"type":"Point"}
}