{
  "type": "Feature",
  "properties": {
    "iso:country":"ES",
    "sg:address":"Carr Pla De L'arc (del), 8",
    "sg:city":"Lliria",
    "sg:orig_category":"Tintes (fabricaci\u00d3n, Al Por Mayor)",
    "sg:phone":"+34 962 78 16 03",
    "sg:postcode":"46160",
    "sg:province":"Valencia",
    "wof:name":"Mico Navalon Francisco",
    "wof:placetype":"venue"
},
  "geometry": {"coordinates":[-0.5949550271,39.6303672791],"type":"Point"}
}