{
  "type": "Feature",
  "properties": {
    "iso:country":"ES",
    "sg:address":"Calle de Real, 28",
    "sg:city":"Torrelodones",
    "sg:orig_category":"Abogados",
    "sg:phone":"+34 918 59 66 10",
    "sg:postcode":"28250",
    "sg:province":"Madrid",
    "wof:name":"Galeano Y Gonzalez Consulting S.l.",
    "wof:placetype":"venue"
},
  "geometry": {"coordinates":[-3.9273219109,40.5752716064],"type":"Point"}
}