{
  "type": "Feature",
  "properties": {
    "iso:country":"ES",
    "sg:address":"Calle de Tormes, 18",
    "sg:city":"Madrid",
    "sg:orig_category":"Inmobiliaria (agencias)",
    "sg:phone":"+34 914 11 93 34",
    "sg:postcode":"28002",
    "sg:province":"Madrid",
    "wof:name":"Can Po-canals S.l.",
    "wof:placetype":"venue"
},
  "geometry": {"coordinates":[-3.6835830212,40.4499931335],"type":"Point"}
}