{
  "type": "Feature",
  "properties": {
    "iso:country":"ES",
    "sg:address":"Calle de Pirineos, 7",
    "sg:city":"Binefar",
    "sg:orig_category":"Restaurantes",
    "sg:phone":"+34 974 42 94 27",
    "sg:postcode":"22500",
    "sg:province":"Huesca",
    "wof:name":"Morgana Hostelera S.c.p.",
    "wof:placetype":"venue"
},
  "geometry": {"coordinates":[0.2884800136,41.8544235229],"type":"Point"}
}