{
  "type": "Feature",
  "properties": {
    "addr:full":"Calle de Maestro Guridi, 17 Castellon De La Plana Castell\u00f3n 12006",
    "addr:housenumber":"17",
    "addr:postcode":"12006",
    "addr:street":"Calle De Maestro Guridi",
    "iso:country":"ES",
    "sg:address":"Calle de Maestro Guridi, 17",
    "sg:city":"Castellon De La Plana",
    "sg:orig_category":"Molduras, Junquillos, Listones Y Molduras Perforadas",
    "sg:phone":"+34 964 20 35 82",
    "sg:postcode":"12006",
    "sg:province":"Castell\u00f3n",
    "wof:name":"Gonzalez Barba Paulina",
    "wof:placetype":"venue"
},
  "geometry": {"coordinates":[-0.1404139996,40.0213813782],"type":"Point"}
}