{
  "type": "Feature",
  "properties": {
    "addr:full":"C/ Antoni Rubi, 5 Inca Islas Baleares 07300",
    "addr:housenumber":"5",
    "addr:postcode":"07300",
    "addr:street":"C / Antoni Rubi",
    "iso:country":"ES",
    "sg:address":"C/ Antoni Rubi, 5",
    "sg:city":"Inca",
    "sg:orig_category":"Abogados",
    "sg:phone":"+34 971 88 12 11",
    "sg:postcode":"07300",
    "sg:province":"Islas Baleares",
    "wof:name":"Alberti Amengual Miguel",
    "wof:placetype":"venue"
},
  "geometry": {"coordinates":[2.9105079174,39.7213859558],"type":"Point"}
}