{
  "type": "Feature",
  "properties": {
    "iso:country":"ES",
    "sg:address":"Carr Casino, 14",
    "sg:city":"Castell D'aro",
    "sg:orig_category":"Servicios Diversos",
    "sg:phone":"+34 972 81 79 88",
    "sg:postcode":"17249",
    "sg:province":"Girona",
    "sg:website":"www.paginasamarillas.es",
    "wof:name":"Neteges Hurval S.l.",
    "wof:placetype":"venue"
},
  "geometry": {"coordinates":[3.0300045013,41.8136177063],"type":"Point"}
}