{
  "type": "Feature",
  "properties": {
    "addr:full":"Avda Pasaje, 2 Coru\u00d1a A Coru\u00f1a 15006",
    "addr:postcode":"15006",
    "addr:street":"Avda Pasaje 2 Corun\u0303A A Corun\u0303A",
    "iso:country":"ES",
    "sg:address":"Avda Pasaje, 2",
    "sg:city":"Coru\u00d1a",
    "sg:orig_category":"Carnicer\u00cdas, Carnicer\u00cdas",
    "sg:phone":"+34 981 13 43 95",
    "sg:postcode":"15006",
    "sg:province":"A Coru\u00f1a",
    "wof:name":"Suarez Alonso Concepcion",
    "wof:placetype":"venue"
},
  "geometry": {"coordinates":[-8.3863840103,43.3442001343],"type":"Point"}
}