{
  "type": "Feature",
  "properties": {
    "addr:full":"Calle de Bolsa, 62 Sanlucar De Barrameda C\u00e1diz 11540",
    "addr:housenumber":"62",
    "addr:postcode":"11540",
    "addr:street":"Calle De Bolsa;Ca\u0301Diz",
    "iso:country":"ES",
    "sg:address":"Calle de Bolsa, 62",
    "sg:city":"Sanlucar De Barrameda",
    "sg:orig_category":"Promotores Constructores",
    "sg:phone":"+34 956 36 98 73",
    "sg:postcode":"11540",
    "sg:province":"C\u00e1diz",
    "wof:name":"Caballero Tenorio David",
    "wof:placetype":"venue"
},
  "geometry": {"coordinates":[-6.3526568413,36.7806472778],"type":"Point"}
}