{
  "type": "Feature",
  "properties": {
    "iso:country":"ES",
    "sg:address":"Poli Cantabria, S/n",
    "sg:city":"Logro\u00f1o",
    "sg:orig_category":"Transportes Por V\u00cdas Navegables",
    "sg:phone":"+34 941 26 36 27",
    "sg:postcode":"26006",
    "sg:province":"La Rioja",
    "sg:website":"www.doman.es",
    "wof:name":"Doman S.a.",
    "wof:placetype":"venue"
},
  "geometry": {"coordinates":[-2.4036989212,42.46043396],"type":"Point"}
}