{
  "type": "Feature",
  "properties": {
    "iso:country":"ES",
    "sg:address":"Calle de San Sebastian, 4",
    "sg:city":"Reinosa",
    "sg:orig_category":"M\u00c9dicos: Endocrinolog\u00cda Y Metabolismo",
    "sg:phone":"+34 942 75 49 41",
    "sg:postcode":"39200",
    "sg:province":"Cantabria",
    "sg:website":"www.centrobcm.com",
    "wof:name":"Wellbeing Society S.l.l.",
    "wof:placetype":"venue"
},
  "geometry": {"coordinates":[-4.1384444237,43.0007972717],"type":"Point"}
}