{
  "type": "Feature",
  "properties": {
    "iso:country":"ES",
    "sg:address":"Carrer de Mossen Jacint Verdaguer, 62",
    "sg:city":"Premia Mar",
    "sg:orig_category":"Alimentaci\u00d3n General (al Por Menor)",
    "sg:phone":"+34 937 52 17 24",
    "sg:postcode":"08330",
    "sg:province":"Barcelona",
    "wof:name":"El Rebot Del Gourmet",
    "wof:placetype":"venue"
},
  "geometry": {"coordinates":[2.3564720154,41.4925193787],"type":"Point"}
}