{
  "type": "Feature",
  "properties": {
    "addr:full":"Poli Teknologi Elkartegia, 207 Arteaga Vizcaya 48170",
    "addr:housenumber":"207",
    "addr:postcode":"48170",
    "addr:street":"Arteaga Vizcaya",
    "iso:country":"ES",
    "sg:address":"Poli Teknologi Elkartegia, 207",
    "sg:city":"Arteaga",
    "sg:orig_category":"Ingeniero",
    "sg:phone":"+34 944 31 70 61",
    "sg:postcode":"48170",
    "sg:province":"Vizcaya",
    "wof:name":"Ingenieria Y Control Electronico S.a.",
    "wof:placetype":"venue"
},
  "geometry": {"coordinates":[-2.7841410637,43.1337165833],"type":"Point"}
}