{
  "type": "Feature",
  "properties": {
    "addr:full":"Calle de Federico Garcia Lorca, 17 Burgos Burgos 09007",
    "addr:housenumber":"17",
    "addr:postcode":"09007",
    "addr:street":"Calle De Federico Garcia Lorca",
    "iso:country":"ES",
    "sg:address":"Calle de Federico Garcia Lorca, 17",
    "sg:city":"Burgos",
    "sg:orig_category":"Comercio De Piezas De Recambio Y De Accesorios De Veh\u00cdculos, Veh\u00cdculos Industriales",
    "sg:phone":"+34 947 47 10 10",
    "sg:postcode":"09007",
    "sg:province":"Burgos",
    "wof:name":"Recambur S.l.",
    "wof:placetype":"venue"
},
  "geometry": {"coordinates":[-3.664331913,42.350227356],"type":"Point"}
}