{
  "type": "Feature",
  "properties": {
    "iso:country":"ES",
    "sg:address":"Carrer de Rossend Arus, S/n",
    "sg:city":"Hospitalet Llobregat",
    "sg:orig_category":"Cr\u00cda De Animales",
    "sg:phone":"+34 933 37 67 94",
    "sg:postcode":"08901",
    "sg:province":"Barcelona",
    "wof:name":"Font Martinez Juan",
    "wof:placetype":"venue"
},
  "geometry": {"coordinates":[2.0996201038,41.3590736389],"type":"Point"}
}