{
  "type": "Feature",
  "properties": {
    "addr:full":"Estd Castela, 834 Ponto La Coru\u00f1a 15570",
    "addr:housenumber":"834",
    "addr:postcode":"15570",
    "addr:street":"Castela;Corun\u0303A",
    "iso:country":"ES",
    "sg:address":"Estd Castela, 834",
    "sg:city":"Ponto",
    "sg:orig_category":"Ropa Para Se\u00d1oras Y Caballeros (al Por Menor)",
    "sg:phone":"+34 981 38 24 51",
    "sg:postcode":"15570",
    "sg:province":"La Coru\u00f1a",
    "wof:name":"Lopez Moda S.l.",
    "wof:placetype":"venue"
},
  "geometry": {"coordinates":[-8.1647539139,43.5165405273],"type":"Point"}
}