{
  "type": "Feature",
  "properties": {
    "addr:full":"Calle de Estanque De La Huerta, 21 San Lorenzo Las Palmas 35018",
    "addr:housenumber":"21",
    "addr:postcode":"35018",
    "addr:street":"Calle De Estanque De La Huerta",
    "iso:country":"ES",
    "sg:address":"Calle de Estanque De La Huerta, 21",
    "sg:city":"San Lorenzo",
    "sg:orig_category":"Instalaci\u00d3n, Mantenimiento De Porteros Electr\u00d3nicos Y Controles De Acceso",
    "sg:phone":"+34 928 67 06 61",
    "sg:postcode":"35018",
    "sg:province":"Las Palmas",
    "wof:name":"Garcia Padron Manuel",
    "wof:placetype":"venue"
},
  "geometry": {"coordinates":[-15.4746456146,28.0737495422],"type":"Point"}
}