{
  "type": "Feature",
  "properties": {
    "iso:country":"ES",
    "sg:address":"Calle de Sotera De La Mier, 14",
    "sg:city":"Sestao",
    "sg:orig_category":"Asociaciones, Organismos Culturales Y Socioeducativos",
    "sg:phone":"+34 944 95 38 96",
    "sg:postcode":"48910",
    "sg:province":"Vizcaya",
    "wof:name":"Sociedad Recreativa Gastronomica Olentzero",
    "wof:placetype":"venue"
},
  "geometry": {"coordinates":[-3.0072743893,43.3125610352],"type":"Point"}
}