{
  "type": "Feature",
  "properties": {
    "addr:full":"Ctra Nacional Ii, Km. 0578,2 Esparreguera Barcelona 08292",
    "addr:postcode":"08292",
    "addr:street":"Ctra Nacional Ii Km. 0578,2",
    "iso:country":"ES",
    "sg:address":"Ctra Nacional Ii, Km. 0578,2",
    "sg:city":"Esparreguera",
    "sg:orig_category":"Fabricaci\u00d3n, Importaci\u00d3n De L\u00c1mparas Y Bombillas",
    "sg:phone":"+34 937 77 33 55",
    "sg:postcode":"08292",
    "sg:province":"Barcelona",
    "wof:name":"Instal.lacions Ml Esparreguera S.l.",
    "wof:placetype":"venue"
},
  "geometry": {"coordinates":[1.8127340078,41.5431747437],"type":"Point"}
}