{
  "type": "Feature",
  "properties": {
    "addr:full":"Calle de Jaraiz De La Vera - Aldea Moret, S/n Caceres C\u00e1ceres 10195",
    "addr:housenumber":"s / n",
    "addr:postcode":"10195",
    "addr:street":"Calle De Jaraiz;Vera Aldea Moret;Ca\u0301Ceres",
    "iso:country":"ES",
    "sg:address":"Calle de Jaraiz De La Vera - Aldea Moret, S/n",
    "sg:city":"Caceres",
    "sg:orig_category":"Reposter\u00cdas",
    "sg:phone":"+34 927 23 52 55",
    "sg:postcode":"10195",
    "sg:province":"C\u00e1ceres",
    "wof:name":"Alonso Y Galan Panaderos Sl",
    "wof:placetype":"venue"
},
  "geometry": {"coordinates":[-6.3894290924,39.4484710693],"type":"Point"}
}