{
  "type": "Feature",
  "properties": {
    "iso:country":"ES",
    "sg:address":"Calle de Cinco De Febrero, 62",
    "sg:city":"Escatron",
    "sg:orig_category":"Empresas De Desmonte",
    "sg:phone":"+34 976 17 00 66",
    "sg:postcode":"50790",
    "sg:province":"Zaragoza",
    "wof:name":"Artal Tomas Francisco Javier",
    "wof:placetype":"venue"
},
  "geometry": {"coordinates":[-0.3245632052,41.2870559692],"type":"Point"}
}