{
  "type": "Feature",
  "properties": {
    "addr:full":"Calle de Ruise\u00d1or (del), 18 Puerto De Santa Maria C\u00e1diz 11500",
    "addr:postcode":"11500",
    "addr:street":"Calle De Ruisen\u0303Or Del 18 Puerto De Santa;Ca\u0301Diz",
    "iso:country":"ES",
    "sg:address":"Calle de Ruise\u00d1or (del), 18",
    "sg:city":"Puerto De Santa Maria",
    "sg:orig_category":"Asesores De Gesti\u00d3n Del Patrimonio",
    "sg:phone":"+34 956 87 30 84",
    "sg:postcode":"11500",
    "sg:province":"C\u00e1diz",
    "wof:name":"Alcasaba De Inversiones S.c.",
    "wof:placetype":"venue"
},
  "geometry": {"coordinates":[-6.2354488373,36.5925331116],"type":"Point"}
}