{
  "type": "Feature",
  "properties": {
    "iso:country":"ES",
    "sg:address":"Calle de Alicante, 15",
    "sg:city":"Castellon",
    "sg:orig_category":"Motocicletas (agentes, Concesionarios)",
    "sg:phone":"+34 964 22 25 98",
    "sg:postcode":"12004",
    "sg:province":"Castell\u00f3n",
    "wof:name":"Taller Y Venta Herrero Motos Castellon S.l.",
    "wof:placetype":"venue"
},
  "geometry": {"coordinates":[-0.0363450013,39.9948348999],"type":"Point"}
}