{
  "type": "Feature",
  "properties": {
    "addr:full":"Carr Mallorca, 6 Blanes Girona 17300",
    "addr:housenumber":"6",
    "addr:postcode":"17300",
    "addr:street":"Carr Mallorca",
    "iso:country":"ES",
    "sg:address":"Carr Mallorca, 6",
    "sg:city":"Blanes",
    "sg:orig_category":"Electricidad: Instaladores",
    "sg:phone":"+34 972 35 11 11",
    "sg:postcode":"17300",
    "sg:province":"Girona",
    "wof:name":"Garcia Garrido Luis",
    "wof:placetype":"venue"
},
  "geometry": {"coordinates":[2.7906849384,41.6724243164],"type":"Point"}
}