{
  "type": "Feature",
  "properties": {
    "iso:country":"ES",
    "sg:address":"Iglesias, 33",
    "sg:city":"La Coronada",
    "sg:orig_category":"Iglesia Cat\u00d3lica",
    "sg:phone":"+34 924 82 60 26",
    "sg:postcode":"06469",
    "sg:province":"Badajoz",
    "wof:name":"Parroquial De San Bartolome",
    "wof:placetype":"venue"
},
  "geometry": {"coordinates":[-5.6720261574,38.9206886292],"type":"Point"}
}