{
  "type": "Feature",
  "properties": {
    "addr:full":"Carrer de Vazquez De Mella, 63 Amposta Tarragona 43870",
    "addr:housenumber":"63",
    "addr:postcode":"43870",
    "addr:street":"Carrer De Vazquez De Mella",
    "iso:country":"ES",
    "sg:address":"Carrer de Vazquez De Mella, 63",
    "sg:city":"Amposta",
    "sg:orig_category":"Lavado, Limpieza De Veh\u00cdculos",
    "sg:phone":"+34 977 70 49 10",
    "sg:postcode":"43870",
    "sg:province":"Tarragona",
    "wof:name":"Ferre Tolda Agustin Jose",
    "wof:placetype":"venue"
},
  "geometry": {"coordinates":[0.572510004,40.7116889954],"type":"Point"}
}