{
  "type": "Feature",
  "properties": {
    "iso:country":"ES",
    "sg:address":"Plaz Escorial (del), 12",
    "sg:city":"Caserio De Perales",
    "sg:orig_category":"Infograf\u00cda",
    "sg:phone":"+34 916 84 76 49",
    "sg:postcode":"28909",
    "sg:province":"Madrid",
    "sg:website":"www.gsinfografia.com",
    "wof:name":"Gozzi  Silvia",
    "wof:placetype":"venue"
},
  "geometry": {"coordinates":[-3.6553490162,40.3250961304],"type":"Point"}
}