{
  "type": "Feature",
  "properties": {
    "iso:country":"ES",
    "sg:address":"Calle de Rey Alhamar, 7",
    "sg:city":"Jaen",
    "sg:orig_category":"Promotores Constructores",
    "sg:phone":"+34 953 29 47 00",
    "sg:postcode":"23007",
    "sg:province":"Ja\u00e9n",
    "wof:name":"Grupo De Gestion Y Dotacion Del Suelo S.l.",
    "wof:placetype":"venue"
},
  "geometry": {"coordinates":[-3.7907590866,37.7721786499],"type":"Point"}
}