{
  "type": "Feature",
  "properties": {
    "addr:full":"Calle de Almendralejo, S/n Merida Badajoz 06800",
    "addr:housenumber":"s",
    "addr:postcode":"06800",
    "addr:street":"Calle De Almendralejo;/ N",
    "iso:country":"ES",
    "sg:address":"Calle de Almendralejo, S/n",
    "sg:city":"Merida",
    "sg:orig_category":"Tribunales, Administraci\u00d3n De Justicia",
    "sg:phone":"+34 924 31 02 56",
    "sg:postcode":"06800",
    "sg:province":"Badajoz",
    "wof:name":"Administracion De Justicia",
    "wof:placetype":"venue"
},
  "geometry": {"coordinates":[-6.3462905884,38.9189491272],"type":"Point"}
}