{
  "type": "Feature",
  "properties": {
    "iso:country":"ES",
    "sg:address":"Calle de Campo Marin, 8",
    "sg:city":"Zafra",
    "sg:orig_category":"Agentes Generales De Seguros",
    "sg:phone":"+34 924 55 32 57",
    "sg:postcode":"06300",
    "sg:province":"Badajoz",
    "wof:name":"Calderon Bizarro Julian",
    "wof:placetype":"venue"
},
  "geometry": {"coordinates":[-6.4164791107,38.4230194092],"type":"Point"}
}