{
  "type": "Feature",
  "properties": {
    "iso:country":"ES",
    "sg:address":"Luga Lomo Del Fondillo, 5",
    "sg:city":"Fondillo",
    "sg:orig_category":"Iglesias Evang\u00c9licas",
    "sg:phone":"+34 928 35 50 77",
    "sg:postcode":"35017",
    "sg:province":"Las Palmas",
    "wof:name":"Iglesia Evangelica Bautista",
    "wof:placetype":"venue"
},
  "geometry": {"coordinates":[-15.4646606445,28.054693222],"type":"Point"}
}