{
  "type": "Feature",
  "properties": {
    "iso:country":"ES",
    "sg:address":"Carrer de Tucuman, 4",
    "sg:city":"Barcelona",
    "sg:orig_category":"Maquinaria Y Herramientas Para Madera, Pvc, Aluminio Y Aperos (fabricaci\u00d3n, Comercio)",
    "sg:phone":"+34 934 26 04 69",
    "sg:postcode":"08030",
    "sg:province":"Barcelona",
    "wof:name":"Giben De Espa\u00d1a S.a.",
    "wof:placetype":"venue"
},
  "geometry": {"coordinates":[2.1999208927,41.4451828003],"type":"Point"}
}