{
  "type": "Feature",
  "properties": {
    "addr:full":"Av Reus (de), 17 Vinyols I Els Arcs Tarragona 43391",
    "addr:housenumber":"17",
    "addr:postcode":"43391",
    "addr:street":"Av;De",
    "iso:country":"ES",
    "sg:address":"Av Reus (de), 17",
    "sg:city":"Vinyols I Els Arcs",
    "sg:orig_category":"Montaje (empresas De)",
    "sg:phone":"+34 977 85 11 96",
    "sg:postcode":"43391",
    "sg:province":"Tarragona",
    "wof:name":"Soler Guixe Montserrat",
    "wof:placetype":"venue"
},
  "geometry": {"coordinates":[1.0420850515,41.112701416],"type":"Point"}
}