{
  "type": "Feature",
  "properties": {
    "addr:full":"Guillermo Reina, 34 Huercal-overa Almer\u00eda 04600",
    "addr:housenumber":"34",
    "addr:postcode":"04600",
    "addr:street":"Guillermo Reina;Almeri\u0301A",
    "iso:country":"ES",
    "sg:address":"Guillermo Reina, 34",
    "sg:city":"Huercal-overa",
    "sg:orig_category":"Molduras, Junquillos, Listones Y Molduras Perforadas",
    "sg:phone":"+34 950 47 00 16",
    "sg:postcode":"04600",
    "sg:province":"Almer\u00eda",
    "wof:name":"Perez Camacho Maria",
    "wof:placetype":"venue"
},
  "geometry": {"coordinates":[-1.9450249672,37.3949241638],"type":"Point"}
}