{
  "type": "Feature",
  "properties": {
    "iso:country":"ES",
    "sg:address":"Calle de Cordeleria, 9",
    "sg:city":"Bilbao",
    "sg:orig_category":"Impermeabilizantes",
    "sg:phone":"+34 944 90 42 28",
    "sg:postcode":"48013",
    "sg:province":"Vizcaya",
    "sg:website":"www.texsa.com",
    "wof:name":"Texa S.a.",
    "wof:placetype":"venue"
},
  "geometry": {"coordinates":[-2.9714310169,43.2768249512],"type":"Point"}
}