{
  "type": "Feature",
  "properties": {
    "addr:full":"Av De Las Naciones, 11 Vera Almer\u00eda 04620",
    "addr:housenumber":"11;almeri\u0301a",
    "addr:postcode":"04620",
    "addr:street":"Av De Las Naciones",
    "iso:country":"ES",
    "sg:address":"Av De Las Naciones, 11",
    "sg:city":"Vera",
    "sg:orig_category":"Arquitectos",
    "sg:phone":"+34 950 39 20 94",
    "sg:postcode":"04620",
    "sg:province":"Almer\u00eda",
    "wof:name":"Arquitectura Alternativa S.l.",
    "wof:placetype":"venue"
},
  "geometry": {"coordinates":[-1.8748468161,37.2484474182],"type":"Point"}
}