{
  "type": "Feature",
  "properties": {
    "iso:country":"ES",
    "sg:address":"Calle de Cabrera Martin, S/n",
    "sg:city":"Tarajalejo",
    "sg:orig_category":"Centros De Educaci\u00d3n Especial",
    "sg:phone":"+34 928 16 13 71",
    "sg:postcode":"35627",
    "sg:province":"Las Palmas",
    "wof:name":"Colegio De E.g.b. Tarajalejo",
    "wof:placetype":"venue"
},
  "geometry": {"coordinates":[-14.1156578064,28.1929512024],"type":"Point"}
}