{
  "type": "Feature",
  "properties": {
    "iso:country":"ES",
    "sg:address":"Calle de Hoya (la), 73",
    "sg:city":"Puerto Cruz",
    "sg:orig_category":"Mec\u00c1nico Del Autom\u00d3vil",
    "sg:phone":"+34 922 38 40 35",
    "sg:postcode":"38400",
    "sg:province":"Santa Cruz De Tenerife",
    "wof:name":"Melian Escobar Manuel",
    "wof:placetype":"venue"
},
  "geometry": {"coordinates":[9.0760097504,52.7750091553],"type":"Point"}
}