{
  "type": "Feature",
  "properties": {
    "addr:full":"Calle de Mediavilla, 4 Calahorra La Rioja 26500",
    "addr:housenumber":"4",
    "addr:postcode":"26500",
    "addr:street":"Calle De Mediavilla",
    "iso:country":"ES",
    "sg:address":"Calle de Mediavilla, 4",
    "sg:city":"Calahorra",
    "sg:orig_category":"Ingeniero",
    "sg:phone":"+34 941 13 46 81",
    "sg:postcode":"26500",
    "sg:province":"La Rioja",
    "wof:name":"Asensio Abad Manuel",
    "wof:placetype":"venue"
},
  "geometry": {"coordinates":[-1.9641379118,42.3024215698],"type":"Point"}
}