{
  "type": "Feature",
  "properties": {
    "addr:full":"Luga Heros, 1 Heros Asturias 33410",
    "addr:housenumber":"1",
    "addr:postcode":"33410",
    "addr:street":"Heros",
    "iso:country":"ES",
    "sg:address":"Luga Heros, 1",
    "sg:city":"Heros",
    "sg:orig_category":"Procuradores",
    "sg:phone":"+34 985 12 90 32",
    "sg:postcode":"33410",
    "sg:province":"Asturias",
    "wof:name":"Davancla S.l.",
    "wof:placetype":"venue"
},
  "geometry": {"coordinates":[-5.9434437752,43.5360603333],"type":"Point"}
}