{
  "type": "Feature",
  "properties": {
    "iso:country":"ES",
    "sg:address":"Calle de Rvdo Eliseo Ramirez, 32",
    "sg:city":"Tomelloso",
    "sg:orig_category":"Tintes (fabricaci\u00d3n, Al Por Mayor)",
    "sg:phone":"+34 926 51 04 08",
    "sg:postcode":"13700",
    "sg:province":"Ciudad Real",
    "wof:name":"Ortiz Villalta Jose",
    "wof:placetype":"venue"
},
  "geometry": {"coordinates":[-3.0200099945,39.1575202942],"type":"Point"}
}