{
  "type": "Feature",
  "properties": {
    "addr:full":"Calle de Charcos (los), 6 Taco Santa Cruz De Tenerife 38108",
    "addr:housenumber":"6",
    "addr:postcode":"38108",
    "addr:street":"Calle De Charcos Los",
    "iso:country":"ES",
    "sg:address":"Calle de Charcos (los), 6",
    "sg:city":"Taco",
    "sg:orig_category":"Prot\u00c9sicos Dentales",
    "sg:phone":"+34 922 61 71 65",
    "sg:postcode":"38108",
    "sg:province":"Santa Cruz De Tenerife",
    "wof:name":"Fontenla Afonso Fernando",
    "wof:placetype":"venue"
},
  "geometry": {"coordinates":[-16.2976093292,28.4458198547],"type":"Point"}
}