{
  "type": "Feature",
  "properties": {
    "iso:country":"ES",
    "sg:address":"Rio Altzania, 19",
    "sg:city":"Iru\u00f1a",
    "sg:orig_category":"Peluquer\u00cdas, Peluquer\u00cda Mixta",
    "sg:phone":"+34 948 24 18 69",
    "sg:postcode":"31005",
    "sg:province":"Navarra",
    "wof:name":"Catalan Diaz Crespo Maria Del Rosario",
    "wof:placetype":"venue"
},
  "geometry": {"coordinates":[-1.6456090212,42.8039703369],"type":"Point"}
}