{
  "type": "Feature",
  "properties": {
    "addr:full":"Antonio Machado, 15 Santiponce Sevilla 41970",
    "addr:housenumber":"15",
    "addr:postcode":"41970",
    "addr:street":"Antonio Machado",
    "iso:country":"ES",
    "sg:address":"Antonio Machado, 15",
    "sg:city":"Santiponce",
    "sg:orig_category":"Agencias Y Agentes Comerciales, Representantes",
    "sg:phone":"+34 955 99 97 66",
    "sg:postcode":"41970",
    "sg:province":"Sevilla",
    "wof:name":"Herrera Casais Monica",
    "wof:placetype":"venue"
},
  "geometry": {"coordinates":[-6.0385842323,37.434841156],"type":"Point"}
}