{
  "type": "Feature",
  "properties": {
    "addr:full":"Ribela, 33 Ribela Ourense 32950",
    "addr:housenumber":"33",
    "addr:postcode":"32950",
    "addr:street":"Ribela",
    "iso:country":"ES",
    "sg:address":"Ribela, 33",
    "sg:city":"Ribela",
    "sg:orig_category":"Reposter\u00cdas",
    "sg:phone":"+34 988 20 42 67",
    "sg:postcode":"32950",
    "sg:province":"Ourense",
    "wof:name":"Souto Meiri\u00f1o Roberto",
    "wof:placetype":"venue"
},
  "geometry": {"coordinates":[-7.8384399414,42.3793144226],"type":"Point"}
}