{
  "type": "Feature",
  "properties": {
    "addr:full":"Calle de Okendo, 14 Donostia-san Sebastian Guip\u00f9zcoa 20004",
    "addr:housenumber":"14",
    "addr:postcode":"20004",
    "addr:street":"Calle De Okendo",
    "iso:country":"ES",
    "sg:address":"Calle de Okendo, 14",
    "sg:city":"Donostia-san Sebastian",
    "sg:orig_category":"Centros De Coordinaci\u00d3n",
    "sg:phone":"+34 943 42 31 43",
    "sg:postcode":"20004",
    "sg:province":"Guip\u00f9zcoa",
    "wof:name":"Munguia Urreisti Francisco",
    "wof:placetype":"venue"
},
  "geometry": {"coordinates":[-1.9812480211,43.3216247559],"type":"Point"}
}