{
  "type": "Feature",
  "properties": {
    "addr:full":"Crrd San Fernando, 23 Ubeda Ja\u00e9n 23400",
    "addr:housenumber":"23",
    "addr:postcode":"23400",
    "addr:street":"San Fernando;Jae\u0301N",
    "iso:country":"ES",
    "sg:address":"Crrd San Fernando, 23",
    "sg:city":"Ubeda",
    "sg:orig_category":"Cr\u00cda De Animales",
    "sg:phone":"+34 953 75 13 62",
    "sg:postcode":"23400",
    "sg:province":"Ja\u00e9n",
    "wof:name":"Martinez Rodriguez Jesus",
    "wof:placetype":"venue"
},
  "geometry": {"coordinates":[-3.3687260151,38.011806488],"type":"Point"}
}