{
  "type": "Feature",
  "properties": {
    "addr:full":"Ctra N-i (burgos), Km. 0019,0 San Sebastian De Los Reyes Madrid 28700",
    "addr:postcode":"28700",
    "addr:street":"Ctra N-I Burgos Km. 0019,0",
    "iso:country":"ES",
    "sg:address":"Ctra N-i (burgos), Km. 0019,0",
    "sg:city":"San Sebastian De Los Reyes",
    "sg:orig_category":"Ropa Para Se\u00d1oras Y Caballeros (al Por Menor)",
    "sg:phone":"+34 916 51 58 28",
    "sg:postcode":"28700",
    "sg:province":"Madrid",
    "sg:website":"www.zara.es",
    "wof:name":"Zara Espa\u00d1a S.a.",
    "wof:placetype":"venue"
},
  "geometry": {"coordinates":[-3.6200556755,40.5494880676],"type":"Point"}
}