{
  "type": "Feature",
  "properties": {
    "addr:full":"Calle de Concepcion, 11 Albacete Albacete 02002",
    "addr:housenumber":"11",
    "addr:postcode":"02002",
    "addr:street":"Calle De Concepcion",
    "iso:country":"ES",
    "sg:address":"Calle de Concepcion, 11",
    "sg:city":"Albacete",
    "sg:orig_category":"Mutuas De Seguros",
    "sg:phone":"+34 967 21 36 72",
    "sg:postcode":"02002",
    "sg:province":"Albacete",
    "wof:name":"Mutualidad General De Prevision Hogar Divina Pastora",
    "wof:placetype":"venue"
},
  "geometry": {"coordinates":[-1.8544490337,38.9938774109],"type":"Point"}
}