{
  "type": "Feature",
  "properties": {
    "iso:country":"ES",
    "sg:address":"Plaz Herradores, 10",
    "sg:city":"Madrid",
    "sg:orig_category":"Fabricaci\u00d3n De Peines Y De Accesorios De Peluquer\u00cda",
    "sg:phone":"+34 915 59 99 27",
    "sg:postcode":"28013",
    "sg:province":"Madrid",
    "wof:name":"Montane  Charles",
    "wof:placetype":"venue"
},
  "geometry": {"coordinates":[-3.7082850933,40.4165878296],"type":"Point"}
}