{
  "type": "Feature",
  "properties": {
    "iso:country":"ES",
    "sg:address":"C, 8",
    "sg:city":"Villanueva Gallego",
    "sg:orig_category":"Fabricaci\u00d3n De Moldes Y Modelos",
    "sg:phone":"+34 976 18 61 69",
    "sg:postcode":"50830",
    "sg:province":"Zaragoza",
    "wof:name":"Talleres Legaristi S.l.",
    "wof:placetype":"venue"
},
  "geometry": {"coordinates":[-0.8106639981,41.7982940674],"type":"Point"}
}