{
  "type": "Feature",
  "properties": {
    "addr:full":"Calle de Rio Jarama, 12 Azuqueca Henares Guadalajara 19200",
    "addr:housenumber":"12",
    "addr:postcode":"19200",
    "addr:street":"Calle De Rio Jarama",
    "iso:country":"ES",
    "sg:address":"Calle de Rio Jarama, 12",
    "sg:city":"Azuqueca Henares",
    "sg:orig_category":"Material Y Suministros Para Peluquer\u00cda",
    "sg:phone":"+34 949 26 77 82",
    "sg:postcode":"19200",
    "sg:province":"Guadalajara",
    "wof:name":"Logiestpel S.l.",
    "wof:placetype":"venue"
},
  "geometry": {"coordinates":[-3.2627539635,40.5722618103],"type":"Point"}
}