{
  "type": "Feature",
  "properties": {
    "iso:country":"ES",
    "sg:address":"Calle de Jesus Del Gran Poder, 57",
    "sg:city":"Sevilla",
    "sg:orig_category":"Arquitectos",
    "sg:phone":"+34 954 90 35 94",
    "sg:postcode":"41002",
    "sg:province":"Sevilla",
    "wof:name":"Lucas Ruiz Rafael",
    "wof:placetype":"venue"
},
  "geometry": {"coordinates":[-5.995429039,37.3965606689],"type":"Point"}
}