{
  "type": "Feature",
  "properties": {
    "iso:country":"ES",
    "sg:address":"Carretera, 1",
    "sg:city":"Benasau",
    "sg:orig_category":"Alimentaci\u00d3n General (al Por Mayor)",
    "sg:phone":"+34 965 51 31 24",
    "sg:postcode":"03814",
    "sg:province":"Alicante",
    "wof:name":"Diego Devesa S.l.",
    "wof:placetype":"venue"
},
  "geometry": {"coordinates":[-0.3345589936,38.6767311096],"type":"Point"}
}