{
  "type": "Feature",
  "properties": {
    "addr:full":"Calle de Tercia, 25 Santa Cruz De La Zarza Toledo 45370",
    "addr:housenumber":"25",
    "addr:postcode":"45370",
    "addr:street":"Calle De Tercia",
    "iso:country":"ES",
    "sg:address":"Calle de Tercia, 25",
    "sg:city":"Santa Cruz De La Zarza",
    "sg:classifiers":[
        {
            "category":"Taxi",
            "type":"Transportation"
        }
    ],
    "sg:phone":"+34 925 12 51 98",
    "sg:postcode":"45370",
    "sg:province":"Toledo",
    "wof:name":"Torres Belinchon Dionisio",
    "wof:placetype":"venue"
},
  "geometry": {"coordinates":[-3.1857290268,39.9847488403],"type":"Point"}
}