{
  "type": "Feature",
  "properties": {
    "iso:country":"ES",
    "sg:address":"Calle de Vega, 48",
    "sg:city":"Zaragoza",
    "sg:orig_category":"Chapister\u00cda",
    "sg:phone":"+34 976 75 32 12",
    "sg:postcode":"50012",
    "sg:province":"Zaragoza",
    "wof:name":"Tudo Parcerias Fernando",
    "wof:placetype":"venue"
},
  "geometry": {"coordinates":[-0.935536027,41.6385192871],"type":"Point"}
}