{
  "type": "Feature",
  "properties": {
    "iso:country":"ES",
    "sg:address":"Plaz General Fernandez Serrano, 2",
    "sg:city":"Moraleja",
    "sg:orig_category":"Abogados",
    "sg:phone":"+34 927 51 59 35",
    "sg:postcode":"10840",
    "sg:province":"C\u00e1ceres",
    "wof:name":"Aleman Hercilla Jesus",
    "wof:placetype":"venue"
},
  "geometry": {"coordinates":[-6.727991581,40.0115852356],"type":"Point"}
}