{
  "type": "Feature",
  "properties": {
    "iso:country":"ES",
    "sg:address":"Calle de Vasco Nu\u00d1ez De Balboa, 21",
    "sg:city":"Jerez De Los Caballeros",
    "sg:orig_category":"Abogados",
    "sg:phone":"+34 924 75 01 73",
    "sg:postcode":"06380",
    "sg:province":"Badajoz",
    "wof:name":"Lobo Delgado Jose Manuel",
    "wof:placetype":"venue"
},
  "geometry": {"coordinates":[-6.7698688507,38.3207168579],"type":"Point"}
}