{
  "type": "Feature",
  "properties": {
    "addr:full":"Calle de Malaga, 2 Viso Del Alcor Sevilla 41520",
    "addr:housenumber":"2",
    "addr:postcode":"41520",
    "addr:street":"Calle De Malaga",
    "iso:country":"ES",
    "sg:address":"Calle de Malaga, 2",
    "sg:city":"Viso Del Alcor",
    "sg:orig_category":"Arquitectos",
    "sg:phone":"+34 955 94 68 14",
    "sg:postcode":"41520",
    "sg:province":"Sevilla",
    "wof:name":"Calabuig Tschernko Arquitectos Asociados S.l",
    "wof:placetype":"venue"
},
  "geometry": {"coordinates":[-5.7278490067,37.3826026917],"type":"Point"}
}