{
  "type": "Feature",
  "properties": {
    "addr:full":"Carrer de Diputacio, 42 Barcelona Barcelona 08015",
    "addr:housenumber":"42",
    "addr:postcode":"08015",
    "addr:street":"Carrer De Diputacio",
    "iso:country":"ES",
    "sg:address":"Carrer de Diputacio, 42",
    "sg:city":"Barcelona",
    "sg:orig_category":"Inmobiliaria (agencias)",
    "sg:phone":"+34 934 23 00 31",
    "sg:postcode":"08015",
    "sg:province":"Barcelona",
    "wof:name":"Building Marina S.a.",
    "wof:placetype":"venue"
},
  "geometry": {"coordinates":[2.1519649029,41.3788719177],"type":"Point"}
}