{
  "type": "Feature",
  "properties": {
    "iso:country":"ES",
    "sg:address":"Calle de Lepe, 4",
    "sg:city":"Ayamonte",
    "sg:orig_category":"Alquiler De V\u00cddeo",
    "sg:phone":"+34 959 47 05 36",
    "sg:postcode":"21400",
    "sg:province":"Huelva",
    "wof:name":"Drago Barroso Jesus",
    "wof:placetype":"venue"
},
  "geometry": {"coordinates":[-7.40376091,37.2074584961],"type":"Point"}
}