{
  "type": "Feature",
  "properties": {
    "iso:country":"ES",
    "sg:address":"Luga Bai\u00d1a, S/n",
    "sg:city":"Bai\u00d1a",
    "sg:orig_category":"Mataderos De Poller\u00cda",
    "sg:phone":"+34 985 44 69 73",
    "sg:postcode":"33682",
    "sg:province":"Asturias",
    "wof:name":"Astur Lapin S.l.",
    "wof:placetype":"venue"
},
  "geometry": {"coordinates":[-5.8350610733,43.2745285034],"type":"Point"}
}