{
  "type": "Feature",
  "properties": {
    "addr:full":"Calle de Extremadura, S/n Jerez De La Frontera C\u00e1diz 11407",
    "addr:postcode":"11407",
    "addr:street":"Calle De Extremadura S / N",
    "iso:country":"ES",
    "sg:address":"Calle de Extremadura, S/n",
    "sg:city":"Jerez De La Frontera",
    "sg:orig_category":"Importaci\u00d3n",
    "sg:phone":"+34 956 30 91 03",
    "sg:postcode":"11407",
    "sg:province":"C\u00e1diz",
    "wof:name":"Arlin Y Asociados Ingenieros S.a.",
    "wof:placetype":"venue"
},
  "geometry": {"coordinates":[-6.1247344017,36.7054595947],"type":"Point"}
}