{
  "type": "Feature",
  "properties": {
    "iso:country":"ES",
    "sg:address":"Avda Perez Galdos, 53",
    "sg:city":"Valencia",
    "sg:orig_category":"Dise\u00d1o Industrial",
    "sg:phone":"+34 963 82 02 11",
    "sg:postcode":"46018",
    "sg:province":"Valencia",
    "wof:name":"Cuerda Garcia Arnelio",
    "wof:placetype":"venue"
},
  "geometry": {"coordinates":[-0.3901660144,39.4666862488],"type":"Point"}
}