{
  "type": "Feature",
  "properties": {
    "iso:country":"ES",
    "sg:address":"Carr Valencia, S/n",
    "sg:city":"Llombai",
    "sg:orig_category":"Poller\u00cda Y Caza (al Por Menor)",
    "sg:phone":"+34 962 55 04 66",
    "sg:postcode":"46195",
    "sg:province":"Valencia",
    "wof:name":"Agrupacion Pecuaria S. A.",
    "wof:placetype":"venue"
},
  "geometry": {"coordinates":[-0.5710896254,39.2816696167],"type":"Point"}
}