{
  "type": "Feature",
  "properties": {
    "addr:full":"Calle de Samalar, 16 Logro\u00f1o La Rioja 26005",
    "addr:housenumber":"16",
    "addr:postcode":"26005",
    "addr:street":"Calle De Samalar;Rioja",
    "iso:country":"ES",
    "sg:address":"Calle de Samalar, 16",
    "sg:city":"Logro\u00f1o",
    "sg:orig_category":"Material Y Herramientas Agr\u00cdcolas",
    "sg:phone":"+34 941 22 41 86",
    "sg:postcode":"26005",
    "sg:province":"La Rioja",
    "wof:name":"Romero Azofra Aquilino",
    "wof:placetype":"venue"
},
  "geometry": {"coordinates":[-2.4587199688,42.4689483643],"type":"Point"}
}