{
  "type": "Feature",
  "properties": {
    "addr:full":"Calle de Zaldoko, 3 Gorraitz-artzibar Navarra 31620",
    "addr:housenumber":"3",
    "addr:postcode":"31620",
    "addr:street":"Calle De Zaldoko",
    "iso:country":"ES",
    "sg:address":"Calle de Zaldoko, 3",
    "sg:city":"Gorraitz-artzibar",
    "sg:orig_category":"Negocio De Materiales De Construcci\u00d3n",
    "sg:phone":"+34 948 35 73 97",
    "sg:postcode":"31620",
    "sg:province":"Navarra",
    "wof:name":"Joanna Navarra S.l.",
    "wof:placetype":"venue"
},
  "geometry": {"coordinates":[-1.5902739763,42.83177948],"type":"Point"}
}