{
  "type": "Feature",
  "properties": {
    "iso:country":"ES",
    "sg:address":"Calle de Capitan Blanco Argibay, 141",
    "sg:city":"Madrid",
    "sg:orig_category":"Agencias Y Agentes Comerciales, Representantes",
    "sg:phone":"+34 913 14 41 54",
    "sg:postcode":"28029",
    "sg:province":"Madrid",
    "wof:name":"Roldan Cardenal Raul",
    "wof:placetype":"venue"
},
  "geometry": {"coordinates":[-3.7066681385,40.4678115845],"type":"Point"}
}