{
  "type": "Feature",
  "properties": {
    "iso:country":"ES",
    "sg:address":"Carrer de Canonge Almera, 18",
    "sg:city":"Barcelona",
    "sg:orig_category":"M\u00c9dicos: Psiquiatr\u00cda",
    "sg:phone":"+34 933 47 36 77",
    "sg:postcode":"08032",
    "sg:province":"Barcelona",
    "wof:name":"Bouzas Cacheda Francisco Javier",
    "wof:placetype":"venue"
},
  "geometry": {"coordinates":[2.162252903,41.425151825],"type":"Point"}
}