{
  "type": "Feature",
  "properties": {
    "addr:full":"Calle de Padilla, 2 Gijon Asturias 33205",
    "addr:housenumber":"2",
    "addr:postcode":"33205",
    "addr:street":"Calle De Padilla",
    "iso:country":"ES",
    "sg:address":"Calle de Padilla, 2",
    "sg:city":"Gijon",
    "sg:orig_category":"Maquinaria Para Industrias Diversas",
    "sg:phone":"+34 985 34 50 91",
    "sg:postcode":"33205",
    "sg:province":"Asturias",
    "wof:name":"Manrrique Menendez Juan",
    "wof:placetype":"venue"
},
  "geometry": {"coordinates":[-5.6623220444,43.5394477844],"type":"Point"}
}