{
  "type": "Feature",
  "properties": {
    "iso:country":"ES",
    "sg:address":"Landeta Hiribidea, 38",
    "sg:city":"Azpeitia",
    "sg:orig_category":"Barnizadores",
    "sg:phone":"+34 943 81 47 75",
    "sg:postcode":"20730",
    "sg:province":"Guip\u00f9zcoa",
    "wof:name":"Lixatu S.l.",
    "wof:placetype":"venue"
},
  "geometry": {"coordinates":[-2.2556200027,43.1764221191],"type":"Point"}
}