{
  "type": "Feature",
  "properties": {
    "iso:country":"ES",
    "sg:address":"Calle de General Gomez Nu\u00d1ez, 3",
    "sg:city":"Ponferrada",
    "sg:orig_category":"Ropa Para Se\u00d1oras (al Por Menor)",
    "sg:phone":"+34 987 42 92 16",
    "sg:postcode":"24400",
    "sg:province":"Le\u00f3n",
    "wof:name":"Modas Queen S.l.",
    "wof:placetype":"venue"
},
  "geometry": {"coordinates":[-6.5981612206,42.5482635498],"type":"Point"}
}