{
  "type": "Feature",
  "properties": {
    "addr:full":"Crri Penchos, 23 Carril De Los Penchos Murcia 30009",
    "addr:housenumber":"23",
    "addr:postcode":"30009",
    "addr:street":"Penchos;Carril De Los Penchos",
    "iso:country":"ES",
    "sg:address":"Crri Penchos, 23",
    "sg:city":"Carril De Los Penchos",
    "sg:orig_category":"Conservas De Legumbres (fabricaci\u00d3n, Al Por Mayor)",
    "sg:phone":"+34 968 29 19 02",
    "sg:postcode":"30009",
    "sg:province":"Murcia",
    "wof:name":"Esteban Zaragoza Francisco",
    "wof:placetype":"venue"
},
  "geometry": {"coordinates":[-1.1528439522,37.9883460999],"type":"Point"}
}