{
  "type": "Feature",
  "properties": {
    "addr:full":"Ptda Cotes Baixes, 8 Alcoi Alicante 03804",
    "addr:housenumber":"8",
    "addr:postcode":"03804",
    "addr:street":"Ptda Cotes Baixes",
    "iso:country":"ES",
    "sg:address":"Ptda Cotes Baixes, 8",
    "sg:city":"Alcoi",
    "sg:orig_category":"Ropa De Casa (fabricaci\u00d3n, Al Por Mayor)",
    "sg:phone":"+34 965 52 11 00",
    "sg:postcode":"03804",
    "sg:province":"Alicante",
    "sg:website":"www.coimasa.com",
    "wof:name":"Comercial Industrial De Manufacturas Textiles S.l.",
    "wof:placetype":"venue"
},
  "geometry": {"coordinates":[-0.4650489986,38.712688446],"type":"Point"}
}