{
  "type": "Feature",
  "properties": {
    "addr:full":"Calle de Galaroza, 49 Huelva Huelva 21006",
    "addr:housenumber":"49",
    "addr:postcode":"21006",
    "addr:street":"Calle De Galaroza",
    "iso:country":"ES",
    "sg:address":"Calle de Galaroza, 49",
    "sg:city":"Huelva",
    "sg:orig_category":"Discapacitados",
    "sg:phone":"+34 959 22 18 07",
    "sg:postcode":"21006",
    "sg:province":"Huelva",
    "wof:name":"Fundacion Andaluza Para La Integracion Social Del Enfermo Mental",
    "wof:placetype":"venue"
},
  "geometry": {"coordinates":[-6.9341425896,37.2634735107],"type":"Point"}
}