{
  "type": "Feature",
  "properties": {
    "iso:country":"ES",
    "sg:address":"Avda Campo De Gibraltar, S/n",
    "sg:city":"Algeciras",
    "sg:orig_category":"Desinfecci\u00d3n, Desinsectaci\u00d3n, Desratizaci\u00d3n",
    "sg:phone":"+34 956 66 12 25",
    "sg:postcode":"11206",
    "sg:province":"C\u00e1diz",
    "wof:name":"Coplaga Campo De Gibraltar S.l.",
    "wof:placetype":"venue"
},
  "geometry": {"coordinates":[-5.4690241814,36.1586112976],"type":"Point"}
}