{
  "type": "Feature",
  "properties": {
    "iso:country":"ES",
    "sg:address":"Pl Porta Pintada, 16",
    "sg:city":"Palma",
    "sg:orig_category":"Colchones (fabricaci\u00d3n, Al Por Mayor, Al Por Menor)",
    "sg:phone":"+34 971 72 20 98",
    "sg:postcode":"07002",
    "sg:province":"Islas Baleares",
    "wof:name":"Mocheto S.l.",
    "wof:placetype":"venue"
},
  "geometry": {"coordinates":[2.65335989,39.5754508972],"type":"Point"}
}