{
  "type": "Feature",
  "properties": {
    "addr:full":"Pase Mad. Jauregiberri, 4 Donostia-san Sebastian Guip\u00f9zcoa 20014",
    "addr:housenumber":"4",
    "addr:postcode":"20014",
    "addr:street":"Mad. Jauregiberri",
    "iso:country":"ES",
    "sg:address":"Pase Mad. Jauregiberri, 4",
    "sg:city":"Donostia-san Sebastian",
    "sg:orig_category":"Mec\u00c1nico Del Autom\u00d3vil",
    "sg:phone":"+34 943 47 53 95",
    "sg:postcode":"20014",
    "sg:province":"Guip\u00f9zcoa",
    "wof:name":"Talleres Carquizano C.b.",
    "wof:placetype":"venue"
},
  "geometry": {"coordinates":[-1.9009970427,43.2548027039],"type":"Point"}
}