{
  "type": "Feature",
  "properties": {
    "iso:country":"ES",
    "sg:address":"Calle de Odon Alonso, 6",
    "sg:city":"Ba\u00d1eza",
    "sg:orig_category":"Supermercados Y Hipermercados",
    "sg:phone":"+34 987 64 06 29",
    "sg:postcode":"24750",
    "sg:province":"Le\u00f3n",
    "wof:name":"Supermercado Sanchez Y Sanchez S.l.",
    "wof:placetype":"venue"
},
  "geometry": {"coordinates":[-5.9242091179,42.3069114685],"type":"Point"}
}