{
  "type": "Feature",
  "properties": {
    "iso:country":"ES",
    "sg:address":"Calle de Jose Antonio, 8",
    "sg:city":"Naquera",
    "sg:classifiers":[
        {
            "category":"Recreation",
            "type":"Entertainment"
        }
    ],
    "sg:phone":"+34 961 68 21 16",
    "sg:postcode":"46119",
    "sg:province":"Valencia",
    "sg:tags":[
        "caza",
        "pr\u00c1ctica",
        "la",
        "de",
        "pesca",
        "y"
    ],
    "wof:name":"Club De Cazadores El Gavilan",
    "wof:placetype":"venue"
},
  "geometry": {"coordinates":[-0.4259499907,39.6593017578],"type":"Point"}
}