{
  "type": "Feature",
  "properties": {
    "addr:full":"Calle de Oliva, 10 Daimus Valencia 46710",
    "addr:housenumber":"10",
    "addr:postcode":"46710",
    "addr:street":"Calle De Oliva",
    "iso:country":"ES",
    "sg:address":"Calle de Oliva, 10",
    "sg:city":"Daimus",
    "sg:orig_category":"Fabricaci\u00d3n De Art\u00cdculos Y Ornamentos Religiosos",
    "sg:phone":"+34 962 81 93 93",
    "sg:postcode":"46710",
    "sg:province":"Valencia",
    "sg:website":"www.bronces-jorda.com",
    "wof:name":"Bronacero Jorda S.a.",
    "wof:placetype":"venue"
},
  "geometry": {"coordinates":[-0.1547040045,38.9677886963],"type":"Point"}
}