{
  "type": "Feature",
  "properties": {
    "iso:country":"ES",
    "sg:address":"Avda Sistema Solar (del), 13",
    "sg:city":"Poligono De San Fernando De Henares",
    "sg:orig_category":"Quincaller\u00cda (al Por Menor)",
    "sg:phone":"+34 916 77 77 47",
    "sg:postcode":"28830",
    "sg:province":"Madrid",
    "wof:name":"Reca Hispania S.l.",
    "wof:placetype":"venue"
},
  "geometry": {"coordinates":[-3.4936339855,40.4505081177],"type":"Point"}
}