{
  "type": "Feature",
  "properties": {
    "iso:country":"ES",
    "sg:address":"Avda Valentin Masip, 23",
    "sg:city":"Oviedo",
    "sg:orig_category":"Talleres: Ropa A Medida",
    "sg:phone":"+34 985 23 28 18",
    "sg:postcode":"33013",
    "sg:province":"Asturias",
    "wof:name":"Carmen Canteli Diaz",
    "wof:placetype":"venue"
},
  "geometry": {"coordinates":[-5.8626351357,43.3621940613],"type":"Point"}
}