{
  "type": "Feature",
  "properties": {
    "iso:country":"ES",
    "sg:address":"Av Pau Casals, 10",
    "sg:city":"Barcelona",
    "sg:orig_category":"Inmobiliaria (agencias)",
    "sg:phone":"+34 934 53 08 04",
    "sg:postcode":"08021",
    "sg:province":"Barcelona",
    "wof:name":"Gestion De Inmuebles Personalizada",
    "wof:placetype":"venue"
},
  "geometry": {"coordinates":[2.1435201168,41.3936080933],"type":"Point"}
}