{
  "type": "Feature",
  "properties": {
    "addr:full":"Carr Jose Gascon, 46 Betera Valencia 46117",
    "addr:housenumber":"46",
    "addr:postcode":"46117",
    "addr:street":"Carr Jose Gascon",
    "iso:country":"ES",
    "sg:address":"Carr Jose Gascon, 46",
    "sg:city":"Betera",
    "sg:orig_category":"Droguer\u00cdas (al Por Menor)",
    "sg:phone":"+34 961 69 10 97",
    "sg:postcode":"46117",
    "sg:province":"Valencia",
    "wof:name":"Calatayud C.b.",
    "wof:placetype":"venue"
},
  "geometry": {"coordinates":[-0.4610350132,39.5913887024],"type":"Point"}
}