{
  "type": "Feature",
  "properties": {
    "iso:country":"ES",
    "sg:address":"Plaz Mayor, 5",
    "sg:city":"Escairon",
    "sg:orig_category":"Ense\u00d1anza, Formaci\u00d3n Profesional: Aprendizaje",
    "sg:phone":"+34 982 45 23 24",
    "sg:postcode":"27540",
    "sg:province":"Lugo",
    "wof:name":"Ayuntamiento De O Savi\u00f1ao-biblioteca",
    "wof:placetype":"venue"
},
  "geometry": {"coordinates":[-7.6389398575,42.5860443115],"type":"Point"}
}