{
  "type": "Feature",
  "properties": {
    "addr:full":"Calle de Diego De Ordax, 6 Zamora Zamora 49003",
    "addr:housenumber":"6",
    "addr:postcode":"49003",
    "addr:street":"Calle De Diego De Ordax",
    "iso:country":"ES",
    "sg:address":"Calle de Diego De Ordax, 6",
    "sg:city":"Zamora",
    "sg:orig_category":"Ense\u00d1anza Secundaria: Colegios Y Escuelas Privadas",
    "sg:phone":"+34 980 53 32 52",
    "sg:postcode":"49003",
    "sg:province":"Zamora",
    "wof:name":"Prieto Gonzalez Maria Angeles",
    "wof:placetype":"venue"
},
  "geometry": {"coordinates":[-5.7444486618,41.5041809082],"type":"Point"}
}