{
  "type": "Feature",
  "properties": {
    "iso:country":"ES",
    "sg:address":"Calle de Leopoldo Alas Clarin, 8",
    "sg:city":"Madrid",
    "sg:orig_category":"Laboratorios Y Trabajos De Fotograf\u00cda, V\u00cddeo Y Cine",
    "sg:phone":"+34 913 16 65 62",
    "sg:postcode":"28035",
    "sg:province":"Madrid",
    "wof:name":"Miralles Fernandez Elias Carlos",
    "wof:placetype":"venue"
},
  "geometry": {"coordinates":[-3.7359309196,40.4800872803],"type":"Point"}
}