{
  "type": "Feature",
  "properties": {
    "addr:full":"Bu\u00f1o, S/n Bu\u00f1o A Coru\u00f1a 15111",
    "addr:postcode":"15111",
    "addr:street":"Bun\u0303O S / N;Corun\u0303A",
    "iso:country":"ES",
    "sg:address":"Bu\u00f1o, S/n",
    "sg:city":"Bu\u00f1o",
    "sg:orig_category":"Asociaciones De Vecinos, Centros De Juventud",
    "sg:phone":"+34 981 70 73 01",
    "sg:postcode":"15111",
    "sg:province":"A Coru\u00f1a",
    "wof:name":"Sociedad Para O Desenvolvemento Comarcal De Galicia",
    "wof:placetype":"venue"
},
  "geometry": {"coordinates":[-8.7890987396,43.2669792175],"type":"Point"}
}