{
  "type": "Feature",
  "properties": {
    "iso:country":"ES",
    "sg:address":"Calle de Progreso, 25",
    "sg:city":"Aguilas",
    "sg:orig_category":"Supermercados Y Hipermercados",
    "sg:phone":"+34 968 41 03 88",
    "sg:postcode":"30880",
    "sg:province":"Murcia",
    "wof:name":"Lopez Soto Alejandro",
    "wof:placetype":"venue"
},
  "geometry": {"coordinates":[-1.5792909861,37.408115387],"type":"Point"}
}