{
  "type": "Feature",
  "properties": {
    "addr:full":"Sol, 35 Cala Millor Islas Baleares 07560",
    "addr:housenumber":"35",
    "addr:postcode":"07560",
    "addr:street":"Sol",
    "iso:country":"ES",
    "sg:address":"Sol, 35",
    "sg:city":"Cala Millor",
    "sg:orig_category":"Peleter\u00cdas",
    "sg:phone":"+34 971 58 50 19",
    "sg:postcode":"07560",
    "sg:province":"Islas Baleares",
    "wof:name":"Alcover Galmes Guillermo",
    "wof:placetype":"venue"
},
  "geometry": {"coordinates":[3.3840601444,39.6013298035],"type":"Point"}
}