{
  "type": "Feature",
  "properties": {
    "addr:full":"Av Barcelona, 137 Molins Rei Barcelona 08750",
    "addr:housenumber":"137",
    "addr:postcode":"08750",
    "addr:street":"Av Barcelona;Barcelona",
    "iso:country":"ES",
    "sg:address":"Av Barcelona, 137",
    "sg:city":"Molins Rei",
    "sg:orig_category":"Motocicletas (agentes, Concesionarios)",
    "sg:phone":"+34 936 68 58 53",
    "sg:postcode":"08750",
    "sg:province":"Barcelona",
    "sg:website":"www.catalamotos.com",
    "wof:name":"Catala Sabater Eduardo",
    "wof:placetype":"venue"
},
  "geometry": {"coordinates":[2.0227100849,41.4072113037],"type":"Point"}
}