{
  "type": "Feature",
  "properties": {
    "addr:full":"Calle de Hacienda De Pavones, 12 Madrid Madrid 28030",
    "addr:housenumber":"12",
    "addr:postcode":"madrid;28030",
    "addr:street":"Calle De Hacienda De Pavones",
    "iso:country":"ES",
    "sg:address":"Calle de Hacienda De Pavones, 12",
    "sg:city":"Madrid",
    "sg:orig_category":"Bazares, Art\u00cdculos De Limpieza Y De Cocina (al Por Menor)",
    "sg:phone":"+34 914 39 38 78",
    "sg:postcode":"28030",
    "sg:province":"Madrid",
    "wof:name":"Lopez Gonzalez Angel Luis",
    "wof:placetype":"venue"
},
  "geometry": {"coordinates":[-3.6477925777,40.4038619995],"type":"Point"}
}