{
  "type": "Feature",
  "properties": {
    "iso:country":"ES",
    "sg:address":"Avda Galicia De, 20",
    "sg:city":"Oviedo",
    "sg:orig_category":"Centros De Coordinaci\u00d3n",
    "sg:phone":"+34 985 96 64 45",
    "sg:postcode":"33005",
    "sg:province":"Asturias",
    "wof:name":"Gestion De Empresas Gesde S.l.",
    "wof:placetype":"venue"
},
  "geometry": {"coordinates":[-5.8563489914,43.3612594604],"type":"Point"}
}