{
  "type": "Feature",
  "properties": {
    "iso:country":"ES",
    "sg:address":"Calle de Padre Elias, S/n",
    "sg:city":"S. Vicente Sonsierra",
    "sg:orig_category":"Quincaller\u00cda (al Por Menor)",
    "sg:phone":"+34 941 33 44 30",
    "sg:postcode":"26338",
    "sg:province":"La Rioja",
    "wof:name":"Perez Fernandez Jose Maria",
    "wof:placetype":"venue"
},
  "geometry": {"coordinates":[-2.7588191032,42.5630836487],"type":"Point"}
}