{
  "type": "Feature",
  "properties": {
    "addr:full":"Trva Algemesi, 7 Madrid Madrid 28042",
    "addr:housenumber":"7",
    "addr:postcode":"madrid;28042",
    "addr:street":"Trva Algemesi",
    "iso:country":"ES",
    "sg:address":"Trva Algemesi, 7",
    "sg:city":"Madrid",
    "sg:orig_category":"Molduras, Junquillos, Listones Y Molduras Perforadas",
    "sg:phone":"+34 913 29 21 74",
    "sg:postcode":"28042",
    "sg:province":"Madrid",
    "wof:name":"Sevillano Gonzalez Rafael",
    "wof:placetype":"venue"
},
  "geometry": {"coordinates":[-3.5826690197,40.4727973938],"type":"Point"}
}