{
  "type": "Feature",
  "properties": {
    "addr:full":"Calle de Castelar, 12 Almeria Almer\u00eda 04001",
    "addr:housenumber":"12",
    "addr:postcode":"04001",
    "addr:street":"Calle De Castelar",
    "iso:country":"ES",
    "sg:address":"Calle de Castelar, 12",
    "sg:city":"Almeria",
    "sg:orig_category":"Bisuter\u00cda, Joyer\u00cda, Relojer\u00cda (al Por Menor)",
    "sg:phone":"+34 950 23 60 75",
    "sg:postcode":"04001",
    "sg:province":"Almer\u00eda",
    "wof:name":"Perez Cardila Jose",
    "wof:placetype":"venue"
},
  "geometry": {"coordinates":[-2.4644510746,36.8401679993],"type":"Point"}
}