{
  "type": "Feature",
  "properties": {
    "addr:full":"Calle de Merecillas, 4 Antequera M\u00e1laga 29200",
    "addr:housenumber":"4",
    "addr:postcode":"29200",
    "addr:street":"Calle De Merecillas",
    "iso:country":"ES",
    "sg:address":"Calle de Merecillas, 4",
    "sg:city":"Antequera",
    "sg:orig_category":"Moda",
    "sg:phone":"+34 952 84 66 82",
    "sg:postcode":"29200",
    "sg:province":"M\u00e1laga",
    "wof:name":"Sevilla Garcia Ana Rosa",
    "wof:placetype":"venue"
},
  "geometry": {"coordinates":[-4.5605940819,37.0208816528],"type":"Point"}
}