{
  "type": "Feature",
  "properties": {
    "iso:country":"ES",
    "sg:address":"Calle de Zurbaran, 12",
    "sg:city":"Almendralejo",
    "sg:orig_category":"Ingenier\u00cda, Centros De Estudios (diversos)",
    "sg:phone":"+34 924 66 27 89",
    "sg:postcode":"06200",
    "sg:province":"Badajoz",
    "wof:name":"Moreno Camacho Pedro Maria",
    "wof:placetype":"venue"
},
  "geometry": {"coordinates":[-6.4070038795,38.6861114502],"type":"Point"}
}