{
  "type": "Feature",
  "properties": {
    "iso:country":"ES",
    "sg:address":"Via Massague, 32",
    "sg:city":"Sabadell",
    "sg:orig_category":"Reposter\u00cdas",
    "sg:phone":"+34 937 25 13 13",
    "sg:postcode":"08202",
    "sg:province":"Barcelona",
    "wof:name":"Forn El Caliu S.l.",
    "wof:placetype":"venue"
},
  "geometry": {"coordinates":[2.1076529026,41.5502815247],"type":"Point"}
}