{
  "type": "Feature",
  "properties": {
    "addr:full":"Gipuzkoa Kalea, 28 Zarautz Guip\u00f9zcoa 20800",
    "addr:housenumber":"28",
    "addr:postcode":"20800",
    "addr:street":"Gipuzkoa Kalea;Guipu\u0300Zcoa",
    "iso:country":"ES",
    "sg:address":"Gipuzkoa Kalea, 28",
    "sg:city":"Zarautz",
    "sg:orig_category":"M\u00c9dicos: Estomatolog\u00cda",
    "sg:phone":"+34 943 83 04 24",
    "sg:postcode":"20800",
    "sg:province":"Guip\u00f9zcoa",
    "wof:name":"Aprell Lasagabaster Maria Del Carmen",
    "wof:placetype":"venue"
},
  "geometry": {"coordinates":[-2.1717669964,43.2853012085],"type":"Point"}
}