{
  "type": "Feature",
  "properties": {
    "iso:country":"ES",
    "sg:address":"Pg Barcelona, 3",
    "sg:city":"Olot",
    "sg:orig_category":"Doctores En Medicina",
    "sg:phone":"+34 972 26 80 28",
    "sg:postcode":"17800",
    "sg:province":"Girona",
    "wof:name":"Vayreda Casadevall Montserrat",
    "wof:placetype":"venue"
},
  "geometry": {"coordinates":[2.4854850769,42.1800537109],"type":"Point"}
}