{
  "type": "Feature",
  "properties": {
    "iso:country":"ES",
    "sg:address":"Avda. J. Galan El Zarandaor, 3",
    "sg:city":"Trebujena",
    "sg:orig_category":"Papeler\u00cdas, Librer\u00cdas",
    "sg:phone":"+34 956 39 56 91",
    "sg:postcode":"11560",
    "sg:province":"C\u00e1diz",
    "wof:name":"Gonzalez Real Manuel",
    "wof:placetype":"venue"
},
  "geometry": {"coordinates":[-6.2057447433,36.8675384521],"type":"Point"}
}