{
  "type": "Feature",
  "properties": {
    "addr:full":"Calle de Lagasca, 8 Madrid Madrid 28001",
    "addr:housenumber":"8",
    "addr:postcode":"madrid;28001",
    "addr:street":"Calle De Lagasca",
    "iso:country":"ES",
    "sg:address":"Calle de Lagasca, 8",
    "sg:city":"Madrid",
    "sg:orig_category":"Arte, Cultura, Edici\u00d3n",
    "sg:phone":"+34 914 31 25 46",
    "sg:postcode":"28001",
    "sg:province":"Madrid",
    "sg:website":"www.galon.com",
    "wof:name":"Galon S. A.",
    "wof:placetype":"venue"
},
  "geometry": {"coordinates":[-3.685642004,40.421295166],"type":"Point"}
}