{
  "type": "Feature",
  "properties": {
    "iso:country":"ES",
    "sg:address":"Pase Eduardo Dato, 15",
    "sg:city":"Madrid",
    "sg:orig_category":"Asesor\u00cda Fiscal Y Jur\u00cddica",
    "sg:phone":"+34 913 08 51 89",
    "sg:postcode":"28010",
    "sg:province":"Madrid",
    "wof:name":"Vplatas Asesores Fiscales, S.l.",
    "wof:placetype":"venue"
},
  "geometry": {"coordinates":[-3.6935446262,40.4328994751],"type":"Point"}
}