{
  "type": "Feature",
  "properties": {
    "addr:full":"Rua Conde (do), 2 Lugo Lugo 27003",
    "addr:housenumber":"2",
    "addr:postcode":"27003",
    "addr:street":"Rua Conde Do",
    "iso:country":"ES",
    "sg:address":"Rua Conde (do), 2",
    "sg:city":"Lugo",
    "sg:orig_category":"M\u00c9dicos: Ginecolog\u00cda Y Obstetricia",
    "sg:phone":"+34 982 22 45 03",
    "sg:postcode":"27003",
    "sg:province":"Lugo",
    "wof:name":"Paz Doel Gonzalo",
    "wof:placetype":"venue"
},
  "geometry": {"coordinates":[-7.5569348335,43.0148162842],"type":"Point"}
}