{
  "type": "Feature",
  "properties": {
    "iso:country":"ES",
    "sg:address":"Carrer de Valencia, 50",
    "sg:city":"Senia",
    "sg:orig_category":"Transportes Por Carretera: Lotes Completos, Mercanc\u00cdas Diversas",
    "sg:phone":"+34 977 71 38 47",
    "sg:postcode":"43560",
    "sg:province":"Tarragona",
    "wof:name":"Trans-muebles S.l.",
    "wof:placetype":"venue"
},
  "geometry": {"coordinates":[0.284525007,40.63306427],"type":"Point"}
}