{
  "type": "Feature",
  "properties": {
    "addr:full":"Carrer de Calabria, 119 Barcelona Barcelona 08015",
    "addr:housenumber":"119",
    "addr:postcode":"08015",
    "addr:street":"Carrer De Calabria",
    "iso:country":"ES",
    "sg:address":"Carrer de Calabria, 119",
    "sg:city":"Barcelona",
    "sg:orig_category":"Cajas De Ahorro",
    "sg:phone":"+34 932 28 93 55",
    "sg:postcode":"08015",
    "sg:province":"Barcelona",
    "wof:name":"Caixa D'estalvis De Catalunya",
    "wof:placetype":"venue"
},
  "geometry": {"coordinates":[2.1536331177,41.3805465698],"type":"Point"}
}