{
  "type": "Feature",
  "properties": {
    "iso:country":"ES",
    "sg:address":"Avgd Sant Josep Obrer (de), S/n",
    "sg:city":"Betxi",
    "sg:orig_category":"Venta, Montaje De Neum\u00c1ticos",
    "sg:phone":"+34 964 62 03 68",
    "sg:postcode":"12549",
    "sg:province":"Castell\u00f3n",
    "sg:website":"www.neumaticosandresservirueda.com",
    "wof:name":"Neumaticos Andres Catalan S.l.",
    "wof:placetype":"venue"
},
  "geometry": {"coordinates":[-0.1963589936,39.9285507202],"type":"Point"}
}