{
  "type": "Feature",
  "properties": {
    "iso:country":"ES",
    "sg:address":"Rua Rosalia De Castro, 4",
    "sg:city":"Betanzos",
    "sg:orig_category":"Servicio De Salud",
    "sg:phone":"+34 981 77 26 04",
    "sg:postcode":"15300",
    "sg:province":"La Coru\u00f1a",
    "wof:name":"Distribuciones Pedro Porca S.l.",
    "wof:placetype":"venue"
},
  "geometry": {"coordinates":[-8.2119092941,43.279914856],"type":"Point"}
}