{
  "type": "Feature",
  "properties": {
    "addr:full":"Avda Ordesa, 27 Broto Huesca 22370",
    "addr:housenumber":"27",
    "addr:postcode":"22370",
    "addr:street":"Avda Ordesa",
    "iso:country":"ES",
    "sg:address":"Avda Ordesa, 27",
    "sg:city":"Broto",
    "sg:orig_category":"Reparaciones Y Remolcado De Veh\u00cdculos",
    "sg:phone":"+34 974 48 61 16",
    "sg:postcode":"22370",
    "sg:province":"Huesca",
    "wof:name":"Cosculluela Noguero Manuel",
    "wof:placetype":"venue"
},
  "geometry": {"coordinates":[-0.1224109977,42.6043815613],"type":"Point"}
}