{
  "type": "Feature",
  "properties": {
    "addr:full":"Estd Xeral, 15 Pontenova Lugo 27720",
    "addr:housenumber":"15",
    "addr:postcode":"27720",
    "addr:street":"Xeral",
    "iso:country":"ES",
    "sg:address":"Estd Xeral, 15",
    "sg:city":"Pontenova",
    "sg:orig_category":"Peluqueros: De Se\u00d1oras",
    "sg:phone":"+34 982 34 22 38",
    "sg:postcode":"27720",
    "sg:province":"Lugo",
    "wof:name":"Gavin Gonzalez Maria Luz",
    "wof:placetype":"venue"
},
  "geometry": {"coordinates":[-7.1766328812,43.3744239807],"type":"Point"}
}