{
  "type": "Feature",
  "properties": {
    "iso:country":"ES",
    "sg:address":"Calle de San Bernabe, 5",
    "sg:city":"Oviedo",
    "sg:orig_category":"Sociedades, Compa\u00d1\u00cdas Aseguradoras",
    "sg:phone":"+34 985 20 43 39",
    "sg:postcode":"33002",
    "sg:province":"Asturias",
    "wof:name":"Valoraciones Mediterraneo S.a.",
    "wof:placetype":"venue"
},
  "geometry": {"coordinates":[-5.8494901657,43.3647994995],"type":"Point"}
}