{
  "type": "Feature",
  "properties": {
    "iso:country":"ES",
    "sg:address":"Calle de Dulcinea, 17",
    "sg:city":"Alcazar S. Juan",
    "sg:orig_category":"Peluquer\u00cdas, Peluquer\u00cda Mixta",
    "sg:phone":"+34 926 54 78 71",
    "sg:postcode":"13600",
    "sg:province":"Ciudad Real",
    "wof:name":"Garcia Herrero Amparo",
    "wof:placetype":"venue"
},
  "geometry": {"coordinates":[-3.2002990246,39.3913154602],"type":"Point"}
}