{
  "type": "Feature",
  "properties": {
    "addr:full":"Torrent Santa Anna, 33 Santa Anna-tio Barcelona 08338",
    "addr:housenumber":"33",
    "addr:postcode":"08338",
    "addr:street":"Anna",
    "iso:country":"ES",
    "sg:address":"Torrent Santa Anna, 33",
    "sg:city":"Santa Anna-tio",
    "sg:orig_category":"Molduras, Junquillos, Listones Y Molduras Perforadas",
    "sg:phone":"+34 937 51 35 10",
    "sg:postcode":"08338",
    "sg:province":"Barcelona",
    "wof:name":"Navarro Fernandez Francisco",
    "wof:placetype":"venue"
},
  "geometry": {"coordinates":[2.3502030373,41.5012817383],"type":"Point"}
}