{
  "type": "Feature",
  "properties": {
    "addr:full":"Calle de Pelayo, 1 Valencia Valencia 46007",
    "addr:housenumber":"1",
    "addr:postcode":"46007",
    "addr:street":"Calle De Pelayo",
    "iso:country":"ES",
    "sg:address":"Calle de Pelayo, 1",
    "sg:city":"Valencia",
    "sg:orig_category":"Estancos",
    "sg:phone":"+34 963 51 51 86",
    "sg:postcode":"46007",
    "sg:province":"Valencia",
    "wof:name":"Valero Gimenez Jose",
    "wof:placetype":"venue"
},
  "geometry": {"coordinates":[-0.3791354001,39.4656143188],"type":"Point"}
}