{
  "type": "Feature",
  "properties": {
    "addr:full":"C/ Font, 9 Llucmajor Islas Baleares 07620",
    "addr:housenumber":"9",
    "addr:postcode":"07620",
    "addr:street":"C / Font",
    "iso:country":"ES",
    "sg:address":"C/ Font, 9",
    "sg:city":"Llucmajor",
    "sg:orig_category":"Fabricaci\u00d3n, Venta, Instalaci\u00d3n De R\u00d3tulos, De R\u00d3tulos Luminosos",
    "sg:phone":"+34 971 66 44 00",
    "sg:postcode":"07620",
    "sg:province":"Islas Baleares",
    "wof:name":"Krausz  Claudia Maria",
    "wof:placetype":"venue"
},
  "geometry": {"coordinates":[2.891949892,39.4911193848],"type":"Point"}
}