{
  "type": "Feature",
  "properties": {
    "addr:full":"Carr Isabel La Catolica, 10 Olleria Valencia 46850",
    "addr:housenumber":"10",
    "addr:postcode":"46850",
    "addr:street":"Carr Isabel La Catolica",
    "iso:country":"ES",
    "sg:address":"Carr Isabel La Catolica, 10",
    "sg:city":"Olleria",
    "sg:orig_category":"Fabricaci\u00d3n, Distribuci\u00d3n De Discos, V\u00cddeodiscos Y Musicassettes",
    "sg:phone":"+34 962 20 14 02",
    "sg:postcode":"46850",
    "sg:province":"Valencia",
    "wof:name":"Studio Import-records S.l.",
    "wof:placetype":"venue"
},
  "geometry": {"coordinates":[-0.5499969721,38.9145088196],"type":"Point"}
}