{
  "type": "Feature",
  "properties": {
    "iso:country":"ES",
    "sg:address":"Av Generalitat, 20",
    "sg:city":"Pobla Mafumet",
    "sg:orig_category":"Ense\u00d1anza, Formaci\u00d3n Profesional: Aprendizaje",
    "sg:phone":"+34 977 84 05 55",
    "sg:postcode":"43140",
    "sg:province":"Tarragona",
    "wof:name":"Ajuntament De La Pobla De Mafumet",
    "wof:placetype":"venue"
},
  "geometry": {"coordinates":[1.2088593245,41.1868362427],"type":"Point"}
}