{
  "type": "Feature",
  "properties": {
    "iso:country":"ES",
    "sg:address":"Pg Dolores Piera, 4",
    "sg:city":"Benissa",
    "sg:orig_category":"Molduras, Junquillos, Listones Y Molduras Perforadas",
    "sg:phone":"+34 965 73 00 86",
    "sg:postcode":"03720",
    "sg:province":"Alicante",
    "wof:name":"Rio Font Pedro Del Rio",
    "wof:placetype":"venue"
},
  "geometry": {"coordinates":[0.0504180007,38.7151565552],"type":"Point"}
}