{
  "type": "Feature",
  "properties": {
    "addr:full":"Carrer de N Amargos, 17 Barcelona Barcelona 08002",
    "addr:housenumber":"17",
    "addr:postcode":"08002",
    "addr:street":"Carrer De N Amargos",
    "iso:country":"ES",
    "sg:address":"Carrer de N Amargos, 17",
    "sg:city":"Barcelona",
    "sg:orig_category":"M\u00c9dicos: Oftalmolog\u00cda",
    "sg:phone":"+34 933 01 67 19",
    "sg:postcode":"08002",
    "sg:province":"Barcelona",
    "sg:website":"www.oftalaser.es",
    "wof:name":"Oftalaser S.l.",
    "wof:placetype":"venue"
},
  "geometry": {"coordinates":[2.1738901138,41.386505127],"type":"Point"}
}