{
  "type": "Feature",
  "properties": {
    "iso:country":"ES",
    "sg:address":"Carr Orient, 39",
    "sg:city":"Girona",
    "sg:orig_category":"Persianas Interiores, Exteriores",
    "sg:phone":"+34 972 24 01 03",
    "sg:postcode":"17006",
    "sg:province":"Girona",
    "wof:name":"Cm Tapiz 2007 S.l.",
    "wof:placetype":"venue"
},
  "geometry": {"coordinates":[2.8081479073,41.9743843079],"type":"Point"}
}