{
  "type": "Feature",
  "properties": {
    "iso:country":"ES",
    "sg:address":"Avda Juan Carlos I, 6",
    "sg:city":"Talavera Reina",
    "sg:orig_category":"T\u00c9cnicos Veterinarios",
    "sg:phone":"+34 925 80 86 12",
    "sg:postcode":"45600",
    "sg:province":"Toledo",
    "wof:name":"Garcia Alia Luis Alberto",
    "wof:placetype":"venue"
},
  "geometry": {"coordinates":[-4.8231840134,39.9677391052],"type":"Point"}
}