{
  "type": "Feature",
  "properties": {
    "addr:full":"Carrer de Llevant, 19 Altafulla Tarragona 43893",
    "addr:housenumber":"19",
    "addr:postcode":"43893",
    "addr:street":"Carrer De Llevant",
    "iso:country":"ES",
    "sg:address":"Carrer de Llevant, 19",
    "sg:city":"Altafulla",
    "sg:orig_category":"Reposter\u00cdas",
    "sg:phone":"+34 977 65 08 08",
    "sg:postcode":"43893",
    "sg:province":"Tarragona",
    "wof:name":"Marti Marques Alfonso",
    "wof:placetype":"venue"
},
  "geometry": {"coordinates":[1.3789989948,41.1351623535],"type":"Point"}
}