{
  "type": "Feature",
  "properties": {
    "iso:country":"ES",
    "sg:address":"Calle de Fernan Gonzalez, 68",
    "sg:city":"Madrid",
    "sg:orig_category":"M\u00c9dicos: Ginecolog\u00cda Y Obstetricia",
    "sg:phone":"+34 914 00 80 20",
    "sg:postcode":"28009",
    "sg:province":"Madrid",
    "wof:name":"Benavides Garcia Pilar",
    "wof:placetype":"venue"
},
  "geometry": {"coordinates":[-3.6748669147,40.4171485901],"type":"Point"}
}