{
  "type": "Feature",
  "properties": {
    "addr:full":"Avda De Extremadura, S/n Aldeanueva Vera C\u00e1ceres 10440",
    "addr:postcode":"10440",
    "addr:street":"Avda De Extremadura S / N Aldeanueva Vera Ca\u0301Ceres",
    "iso:country":"ES",
    "sg:address":"Avda De Extremadura, S/n",
    "sg:city":"Aldeanueva Vera",
    "sg:orig_category":"Talleres: Ropa A Medida",
    "sg:phone":"+34 927 57 25 53",
    "sg:postcode":"10440",
    "sg:province":"C\u00e1ceres",
    "wof:name":"Sanchez Perino Josefa",
    "wof:placetype":"venue"
},
  "geometry": {"coordinates":[-5.6941342354,40.1334877014],"type":"Point"}
}