{
  "type": "Feature",
  "properties": {
    "addr:full":"Calle de Residencial Los Alamos, 13 Ciudad Del Campo Las Palmas 35018",
    "addr:housenumber":"13",
    "addr:postcode":"35018",
    "addr:street":"Calle De Residencial Los Alamos",
    "iso:country":"ES",
    "sg:address":"Calle de Residencial Los Alamos, 13",
    "sg:city":"Ciudad Del Campo",
    "sg:orig_category":"Asesor\u00cda Fiscal Y Jur\u00cddica",
    "sg:phone":"+34 928 66 70 31",
    "sg:postcode":"35018",
    "sg:province":"Las Palmas",
    "wof:name":"Falcon Toledo Carlos",
    "wof:placetype":"venue"
},
  "geometry": {"coordinates":[-15.4938993454,28.1144199371],"type":"Point"}
}