{
  "type": "Feature",
  "properties": {
    "iso:country":"ES",
    "sg:address":"Carr S Josep, 102",
    "sg:city":"Igualada",
    "sg:orig_category":"Energ\u00cda Solar Y Nuevas Energ\u00cdas (equipo, Estudios)",
    "sg:phone":"+34 938 04 41 53",
    "sg:postcode":"08700",
    "sg:province":"Barcelona",
    "wof:name":"Puiggros Carbonell Isidro",
    "wof:placetype":"venue"
},
  "geometry": {"coordinates":[1.6245830059,41.5838470459],"type":"Point"}
}