{
  "type": "Feature",
  "properties": {
    "addr:full":"Palacio, S/n Amandi Asturias 33311",
    "addr:housenumber":"s / n",
    "addr:postcode":"33311",
    "iso:country":"ES",
    "sg:address":"Palacio, S/n",
    "sg:city":"Amandi",
    "sg:orig_category":"Obras Y Organismos Sociales",
    "sg:phone":"+34 985 89 12 51",
    "sg:postcode":"33311",
    "sg:province":"Asturias",
    "wof:name":"Fundacion Benefica Miyar Somonte",
    "wof:placetype":"venue"
},
  "geometry": {"coordinates":[-5.3432879448,43.4807777405],"type":"Point"}
}