{
  "type": "Feature",
  "properties": {
    "addr:full":"Plaz Bizkaia, 5 Poligono El Casal Vizcaya 48500",
    "addr:housenumber":"5",
    "addr:postcode":"48500",
    "addr:street":"Bizkaia;El;Vizcaya",
    "iso:country":"ES",
    "sg:address":"Plaz Bizkaia, 5",
    "sg:city":"Poligono El Casal",
    "sg:orig_category":"Empresas De Pintura Y Revestimientos",
    "sg:phone":"+34 946 36 26 41",
    "sg:postcode":"48500",
    "sg:province":"Vizcaya",
    "wof:name":"Aplicaciones Marquez S.l.",
    "wof:placetype":"venue"
},
  "geometry": {"coordinates":[-2.6983869076,43.2204284668],"type":"Point"}
}