{
  "type": "Feature",
  "properties": {
    "iso:country":"ES",
    "sg:address":"Calle de Juan Agustin Palomar, 20",
    "sg:city":"Camas",
    "sg:orig_category":"Ense\u00d1anza, Formaci\u00d3n Profesional: Aprendizaje",
    "sg:phone":"+34 954 39 34 96",
    "sg:postcode":"41900",
    "sg:province":"Sevilla",
    "wof:name":"Tesoreria General De La Seguridad Social-direccion Provincial De Sevilla",
    "wof:placetype":"venue"
},
  "geometry": {"coordinates":[-6.0336999893,37.4024085999],"type":"Point"}
}