{
  "type": "Feature",
  "properties": {
    "iso:country":"ES",
    "sg:address":"Avda Madrid, S/n",
    "sg:city":"Brihuega",
    "sg:orig_category":"Cooperativas Agr\u00cdcolas",
    "sg:phone":"+34 949 28 02 68",
    "sg:postcode":"19400",
    "sg:province":"Guadalajara",
    "wof:name":"Cooperativa Real Fabrica Carlos Iii",
    "wof:placetype":"venue"
},
  "geometry": {"coordinates":[-2.8712348938,40.7622146606],"type":"Point"}
}