{
  "type": "Feature",
  "properties": {
    "iso:country":"ES",
    "sg:address":"Calle de Castillo, 65",
    "sg:city":"Santa Cruz De Tenerife",
    "sg:orig_category":"Bazares, Art\u00cdculos De Limpieza Y De Cocina (al Por Menor)",
    "sg:phone":"+34 922 24 35 95",
    "sg:postcode":"38003",
    "sg:province":"Santa Cruz De Tenerife",
    "wof:name":"Mahtani  Lachman",
    "wof:placetype":"venue"
},
  "geometry": {"coordinates":[-16.2540397644,28.4675006866],"type":"Point"}
}