{
  "type": "Feature",
  "properties": {
    "addr:full":"Calle de Rio Gallego, 2 Puebla Alfinden Zaragoza 50171",
    "addr:housenumber":"2",
    "addr:postcode":"50171",
    "addr:street":"Calle De Rio Gallego;Alfinden",
    "iso:country":"ES",
    "sg:address":"Calle de Rio Gallego, 2",
    "sg:city":"Puebla Alfinden",
    "sg:orig_category":"Comercio De Piezas De Recambio Y De Accesorios De Veh\u00cdculos, Veh\u00cdculos Industriales",
    "sg:phone":"+34 976 45 51 51",
    "sg:postcode":"50171",
    "sg:province":"Zaragoza",
    "wof:name":"Schulz Iberica S. A.",
    "wof:placetype":"venue"
},
  "geometry": {"coordinates":[-0.7461990118,41.6353988647],"type":"Point"}
}