{
  "type": "Feature",
  "properties": {
    "addr:full":"Pl Ayuntamiento, S/n Sant Joan Moro Castell\u00f3n 12130",
    "addr:postcode":"12130",
    "addr:street":"Pl Ayuntamiento S / N",
    "iso:country":"ES",
    "sg:address":"Pl Ayuntamiento, S/n",
    "sg:city":"Sant Joan Moro",
    "sg:orig_category":"Administraciones Regionales, Departamentales Y Locales",
    "sg:phone":"+34 964 70 11 00",
    "sg:postcode":"12130",
    "sg:province":"Castell\u00f3n",
    "wof:name":"Ayuntamiento De San Juan De Moro",
    "wof:placetype":"venue"
},
  "geometry": {"coordinates":[-0.1393920034,40.0601730347],"type":"Point"}
}