{
  "type": "Feature",
  "properties": {
    "addr:full":"Calle de Maria Espinosa, 11 Zaragoza Zaragoza 50015",
    "addr:housenumber":"11",
    "addr:postcode":"50015",
    "addr:street":"Calle De Maria Espinosa",
    "iso:country":"ES",
    "sg:address":"Calle de Maria Espinosa, 11",
    "sg:city":"Zaragoza",
    "sg:orig_category":"M\u00c9dicos: Estomatolog\u00cda",
    "sg:phone":"+34 976 52 52 54",
    "sg:postcode":"50015",
    "sg:province":"Zaragoza",
    "wof:name":"Gracia Piquero Julio Enrique",
    "wof:placetype":"venue"
},
  "geometry": {"coordinates":[-0.8917070031,41.6719818115],"type":"Point"}
}