{
  "type": "Feature",
  "properties": {
    "addr:full":"Calle de Cruz De Granada, 1 Granada Granada 18015",
    "addr:housenumber":"1",
    "addr:postcode":"18015",
    "addr:street":"Calle De Cruz De Granada",
    "iso:country":"ES",
    "sg:address":"Calle de Cruz De Granada, 1",
    "sg:city":"Granada",
    "sg:orig_category":"Caf\u00c9s, Bares, Cervecer\u00cdas",
    "sg:phone":"+34 958 28 84 36",
    "sg:postcode":"18015",
    "sg:province":"Granada",
    "wof:name":"Gonzalez Biondi Francisco Javier",
    "wof:placetype":"venue"
},
  "geometry": {"coordinates":[-3.6230986118,37.1889724731],"type":"Point"}
}