{
  "type": "Feature",
  "properties": {
    "iso:country":"ES",
    "sg:address":"Av Germanies, 23",
    "sg:city":"Inca",
    "sg:orig_category":"Iglesia Cat\u00d3lica",
    "sg:phone":"+34 971 50 05 65",
    "sg:postcode":"07300",
    "sg:province":"Islas Baleares",
    "wof:name":"Obispado De Mallorca",
    "wof:placetype":"venue"
},
  "geometry": {"coordinates":[2.9076089859,39.7208786011],"type":"Point"}
}