{
  "type": "Feature",
  "properties": {
    "addr:full":"Calle de Corullon, 20 Fuenlabrada Madrid 28947",
    "addr:housenumber":"20",
    "addr:postcode":"28947",
    "addr:street":"Calle De Corullon",
    "iso:country":"ES",
    "sg:address":"Calle de Corullon, 20",
    "sg:city":"Fuenlabrada",
    "sg:orig_category":"Contenedores (mercanc\u00cdas)",
    "sg:phone":"+34 916 42 22 94",
    "sg:postcode":"28947",
    "sg:province":"Madrid",
    "wof:name":"At 193 S.a.",
    "wof:placetype":"venue"
},
  "geometry": {"coordinates":[-3.7444899082,40.2590713501],"type":"Point"}
}