{
  "type": "Feature",
  "properties": {
    "addr:full":"Urb Concejero (el), 30 Cabez\u00f3n Sal Cantabria 39500",
    "addr:postcode":"39500",
    "addr:street":"Urb",
    "iso:country":"ES",
    "sg:address":"Urb Concejero (el), 30",
    "sg:city":"Cabez\u00f3n Sal",
    "sg:orig_category":"Molduras, Junquillos, Listones Y Molduras Perforadas",
    "sg:phone":"+34 942 70 25 09",
    "sg:postcode":"39500",
    "sg:province":"Cantabria",
    "wof:name":"Renedo Carrandi Francisco",
    "wof:placetype":"venue"
},
  "geometry": {"coordinates":[-4.2374691963,43.3085784912],"type":"Point"}
}