{
  "type": "Feature",
  "properties": {
    "iso:country":"ES",
    "sg:address":"Carrer de Pica\u00d1ol, 54",
    "sg:city":"Sabadell",
    "sg:orig_category":"Pod\u00d3logos: Pedicuros",
    "sg:phone":"+34 937 24 04 03",
    "sg:postcode":"08208",
    "sg:province":"Barcelona",
    "wof:name":"Moline Regla Carmen",
    "wof:placetype":"venue"
},
  "geometry": {"coordinates":[2.1015768051,41.5531539917],"type":"Point"}
}