{
  "type": "Feature",
  "properties": {
    "addr:full":"Calle de Monjas Franciscas, 14 Villanueva De Los Infantes Ciudad Real 13320",
    "addr:housenumber":"14",
    "addr:postcode":"13320",
    "addr:street":"Calle De Monjas Franciscas;Infantes",
    "iso:country":"ES",
    "sg:address":"Calle de Monjas Franciscas, 14",
    "sg:city":"Villanueva De Los Infantes",
    "sg:orig_category":"Cl\u00cdnicas M\u00c9dicas",
    "sg:phone":"+34 926 36 00 77",
    "sg:postcode":"13320",
    "sg:province":"Ciudad Real",
    "wof:name":"Renusa Residencia S.l.",
    "wof:placetype":"venue"
},
  "geometry": {"coordinates":[-3.0116689205,38.7382736206],"type":"Point"}
}