{
  "type": "Feature",
  "properties": {
    "iso:country":"ES",
    "sg:address":"Av Alfonso Puchades, 19",
    "sg:city":"Benidorm",
    "sg:orig_category":"Muebles Y Accesorios Para Cocinas Y Cuartos De Ba\u00d1o (al Por Menor)",
    "sg:phone":"+34 965 86 66 03",
    "sg:postcode":"03500",
    "sg:province":"Alicante",
    "wof:name":"Garcia Alonso Jose Luis",
    "wof:placetype":"venue"
},
  "geometry": {"coordinates":[-0.1273992956,38.5428657532],"type":"Point"}
}