{
  "type": "Feature",
  "properties": {
    "addr:full":"Ventas De Salda\u00f1a, S/n Salda\u00f1a Burgos Burgos 09620",
    "addr:housenumber":"s",
    "addr:postcode":"09620",
    "addr:street":"/ N Saldan\u0303A",
    "iso:country":"ES",
    "sg:address":"Ventas De Salda\u00f1a, S/n",
    "sg:city":"Salda\u00f1a Burgos",
    "sg:orig_category":"Muebles Y Accesorios Para Cocinas Y Cuartos De Ba\u00d1o (al Por Menor)",
    "sg:phone":"+34 947 40 40 60",
    "sg:postcode":"09620",
    "sg:province":"Burgos",
    "wof:name":"Estylco S. L.",
    "wof:placetype":"venue"
},
  "geometry": {"coordinates":[-3.6965339184,42.2641639709],"type":"Point"}
}