{
  "type": "Feature",
  "properties": {
    "iso:country":"ES",
    "sg:address":"Calle de Rabida, 2",
    "sg:city":"Huelva",
    "sg:orig_category":"Curtidos, Curtidos En Blanco",
    "sg:phone":"+34 959 24 52 12",
    "sg:postcode":"21001",
    "sg:province":"Huelva",
    "wof:name":"Juan Manuel Llanes Cerrejon Y Cinta Vazquez Garcia Cb",
    "wof:placetype":"venue"
},
  "geometry": {"coordinates":[-6.9508032799,37.256023407],"type":"Point"}
}