{
  "type": "Feature",
  "properties": {
    "iso:country":"ES",
    "sg:address":"Calle de Virgen De La Soledad, 19",
    "sg:city":"Guadalajara",
    "sg:orig_category":"Reposter\u00cdas",
    "sg:phone":"+34 949 23 07 64",
    "sg:postcode":"19003",
    "sg:province":"Guadalajara",
    "wof:name":"La Tahona C.b.",
    "wof:placetype":"venue"
},
  "geometry": {"coordinates":[-3.1654000282,40.6277999878],"type":"Point"}
}