{
  "type": "Feature",
  "properties": {
    "addr:full":"Calle de Riego, 24 Zamora Zamora 49004",
    "addr:housenumber":"24",
    "addr:postcode":"49004",
    "addr:street":"Calle De Riego",
    "iso:country":"ES",
    "sg:address":"Calle de Riego, 24",
    "sg:city":"Zamora",
    "sg:orig_category":"Asesor\u00cdas Y Estudios Financieros",
    "sg:phone":"+34 980 53 69 91",
    "sg:postcode":"49004",
    "sg:province":"Zamora",
    "sg:website":"www.solobancos.com",
    "wof:name":"Asesores Financieros Eurobeza Sl",
    "wof:placetype":"venue"
},
  "geometry": {"coordinates":[-5.7470064163,41.5049858093],"type":"Point"}
}