{
  "type": "Feature",
  "properties": {
    "addr:full":"Calle de Cardenal Cisneros, 55 Madrid Madrid 28010",
    "addr:housenumber":"55",
    "addr:postcode":"madrid;28010",
    "addr:street":"Calle De Cardenal Cisneros",
    "iso:country":"ES",
    "sg:address":"Calle de Cardenal Cisneros, 55",
    "sg:city":"Madrid",
    "sg:orig_category":"Organizaci\u00d3n De Seminarios, Congresos",
    "sg:phone":"+34 914 46 32 09",
    "sg:postcode":"28010",
    "sg:province":"Madrid",
    "wof:name":"Instituto Secular Alianza En Jesus Por Maria",
    "wof:placetype":"venue"
},
  "geometry": {"coordinates":[-3.702507019,40.4331359863],"type":"Point"}
}