{
  "type": "Feature",
  "properties": {
    "addr:full":"Av Paisos Catalans, 54 Reus Tarragona 43202",
    "addr:housenumber":"54",
    "addr:postcode":"43202",
    "addr:street":"Av Paisos Catalans",
    "iso:country":"ES",
    "sg:address":"Av Paisos Catalans, 54",
    "sg:city":"Reus",
    "sg:orig_category":"Molduras, Junquillos, Listones Y Molduras Perforadas",
    "sg:phone":"+34 977 33 01 90",
    "sg:postcode":"43202",
    "sg:province":"Tarragona",
    "wof:name":"Gonzalez Ortiz Jose",
    "wof:placetype":"venue"
},
  "geometry": {"coordinates":[1.0973440409,41.1544647217],"type":"Point"}
}