{
  "type": "Feature",
  "properties": {
    "iso:country":"ES",
    "sg:address":"Poli Poligon Industrial Colomer, S/n",
    "sg:city":"Codis",
    "sg:orig_category":"Contenedores (mercanc\u00cdas)",
    "sg:phone":"+34 973 71 27 89",
    "sg:postcode":"25241",
    "sg:province":"Lleida",
    "wof:name":"Carrera Lazaro Jose Maria",
    "wof:placetype":"venue"
},
  "geometry": {"coordinates":[0.9323819876,41.6301574707],"type":"Point"}
}