{
  "type": "Feature",
  "properties": {
    "iso:country":"ES",
    "sg:address":"Pl Picornell, 1",
    "sg:city":"Ondara",
    "sg:orig_category":"Art\u00cdculos Funerarios (al Por Menor)",
    "sg:phone":"+34 965 76 61 12",
    "sg:postcode":"03760",
    "sg:province":"Alicante",
    "wof:name":"Femenia Perez S.l.",
    "wof:placetype":"venue"
},
  "geometry": {"coordinates":[0.0168190002,38.8264122009],"type":"Point"}
}