{
  "type": "Feature",
  "properties": {
    "addr:full":"Avda Balneario (do), 90 Carballi\u00f1o Ourense 32500",
    "addr:housenumber":"90",
    "addr:postcode":"32500",
    "addr:street":"Avda Balneario Do",
    "iso:country":"ES",
    "sg:address":"Avda Balneario (do), 90",
    "sg:city":"Carballi\u00f1o",
    "sg:orig_category":"Molduras, Junquillos, Listones Y Molduras Perforadas",
    "sg:phone":"+34 988 27 06 03",
    "sg:postcode":"32500",
    "sg:province":"Ourense",
    "wof:name":"Rodriguez Fernandez Teresa",
    "wof:placetype":"venue"
},
  "geometry": {"coordinates":[-8.0793771744,42.434387207],"type":"Point"}
}