{
  "type": "Feature",
  "properties": {
    "iso:country":"ES",
    "sg:address":"C/ Illes Balears, 38",
    "sg:city":"Paterna",
    "sg:orig_category":"Sales (al Por Mayor)",
    "sg:phone":"+34 961 34 11 55",
    "sg:postcode":"46988",
    "sg:province":"Valencia",
    "wof:name":"Proyectos Valencia En El Caribe S.a.",
    "wof:placetype":"venue"
},
  "geometry": {"coordinates":[-0.4674440026,39.5153923035],"type":"Point"}
}