{
  "type": "Feature",
  "properties": {
    "addr:full":"Calle de Alonso De Quiros, 1 Plasencia C\u00e1ceres 10600",
    "addr:housenumber":"1",
    "addr:postcode":"10600",
    "addr:street":"Calle De Alonso De Quiros;Ca\u0301Ceres",
    "iso:country":"ES",
    "sg:address":"Calle de Alonso De Quiros, 1",
    "sg:city":"Plasencia",
    "sg:orig_category":"Asociaciones Humanitarias, De Cooperaci\u00d3n, De Acci\u00d3n Social",
    "sg:phone":"+34 927 42 40 94",
    "sg:postcode":"10600",
    "sg:province":"C\u00e1ceres",
    "wof:name":"Asociacion Para El Estudio De La Lesion Medular Espinal",
    "wof:placetype":"venue"
},
  "geometry": {"coordinates":[-6.0890731812,40.038444519],"type":"Point"}
}