{
  "type": "Feature",
  "properties": {
    "iso:country":"ES",
    "sg:address":"Calle de Juan Boscan, 18",
    "sg:city":"Madrid",
    "sg:orig_category":"Agencias Y Agentes Comerciales, Representantes",
    "sg:phone":"+34 914 07 79 28",
    "sg:postcode":"28017",
    "sg:province":"Madrid",
    "wof:name":"Martinez Lopez German",
    "wof:placetype":"venue"
},
  "geometry": {"coordinates":[-3.6407248974,40.426399231],"type":"Point"}
}