{
  "type": "Feature",
  "properties": {
    "addr:full":"As Quintans, S/n Quintans Pontevedra 36633",
    "addr:postcode":"36633",
    "addr:street":"Quintans S / N",
    "iso:country":"ES",
    "sg:address":"As Quintans, S/n",
    "sg:city":"Quintans",
    "sg:orig_category":"Material Y Suministros Para Horticultura, Arboricultura",
    "sg:phone":"+34 986 52 03 38",
    "sg:postcode":"36633",
    "sg:province":"Pontevedra",
    "wof:name":"Horticultores Del Umia S. A.",
    "wof:placetype":"venue"
},
  "geometry": {"coordinates":[-8.7952222824,42.2552261353],"type":"Point"}
}