{
  "type": "Feature",
  "properties": {
    "addr:full":"Carrer de Sant Pere, 21 Crevillent Alicante 03330",
    "addr:housenumber":"21",
    "addr:postcode":"03330",
    "addr:street":"Carrer De Sant Pere",
    "iso:country":"ES",
    "sg:address":"Carrer de Sant Pere, 21",
    "sg:city":"Crevillent",
    "sg:orig_category":"Librer\u00cdas",
    "sg:phone":"+34 966 68 12 53",
    "sg:postcode":"03330",
    "sg:province":"Alicante",
    "wof:name":"Lopez Penalva Maria Del Carmen",
    "wof:placetype":"venue"
},
  "geometry": {"coordinates":[-0.804840982,38.247177124],"type":"Point"}
}