{
  "type": "Feature",
  "properties": {
    "addr:full":"Calle de Calatrava, 13 S. Fernando C\u00e1diz 11100",
    "addr:housenumber":"13",
    "addr:postcode":"11100",
    "addr:street":"Calle De Calatrava;S. Fernando Ca\u0301Diz",
    "iso:country":"ES",
    "sg:address":"Calle de Calatrava, 13",
    "sg:city":"S. Fernando",
    "sg:orig_category":"Peluqueros: De Se\u00d1oras",
    "sg:phone":"+34 956 89 39 53",
    "sg:postcode":"11100",
    "sg:province":"C\u00e1diz",
    "wof:name":"Cabello Guerrero Maria Del Carmen",
    "wof:placetype":"venue"
},
  "geometry": {"coordinates":[-6.1967248917,36.4705886841],"type":"Point"}
}