{
  "type": "Feature",
  "properties": {
    "addr:full":"Calle de San Andres, 23 Torre Mar M\u00e1laga 29740",
    "addr:housenumber":"23",
    "addr:postcode":"29740",
    "addr:street":"Calle De San Andres;Ma\u0301Laga",
    "iso:country":"ES",
    "sg:address":"Calle de San Andres, 23",
    "sg:city":"Torre Mar",
    "sg:orig_category":"Cl\u00cdnicas Dentales",
    "sg:phone":"+34 952 54 40 51",
    "sg:postcode":"29740",
    "sg:province":"M\u00e1laga",
    "wof:name":"Clinica Rincon Bejar S.l.",
    "wof:placetype":"venue"
},
  "geometry": {"coordinates":[-4.4281549454,36.7120399475],"type":"Point"}
}