{
  "type": "Feature",
  "properties": {
    "addr:full":"C/ Major Del Pla, 19 Elche Alicante 03201",
    "addr:housenumber":"19",
    "addr:postcode":"03201",
    "addr:street":"C / Major Del Pla",
    "iso:country":"ES",
    "sg:address":"C/ Major Del Pla, 19",
    "sg:city":"Elche",
    "sg:orig_category":"Colocaci\u00d3n, Mantenimiento, Vitrificaci\u00d3n De Parquets",
    "sg:phone":"+34 965 43 25 09",
    "sg:postcode":"03201",
    "sg:province":"Alicante",
    "wof:name":"Latorre Mora Eva Maria",
    "wof:placetype":"venue"
},
  "geometry": {"coordinates":[-0.7019780278,38.2629089355],"type":"Point"}
}