{
  "type": "Feature",
  "properties": {
    "iso:country":"ES",
    "sg:address":"Rua Horreo, 2",
    "sg:city":"Carballo",
    "sg:orig_category":"Guarder\u00cdas",
    "sg:phone":"+34 981 75 59 60",
    "sg:postcode":"15100",
    "sg:province":"La Coru\u00f1a",
    "wof:name":"Guarderia Matogrande S.l.",
    "wof:placetype":"venue"
},
  "geometry": {"coordinates":[-8.690448761,43.2125167847],"type":"Point"}
}