{
  "type": "Feature",
  "properties": {
    "iso:country":"ES",
    "sg:address":"Avda Cordeda, S/n",
    "sg:city":"Cordeda",
    "sg:orig_category":"Molinos",
    "sg:phone":"+34 981 66 00 71",
    "sg:postcode":"15174",
    "sg:province":"La Coru\u00f1a",
    "wof:name":"Espi\u00f1eira Segade Manuel",
    "wof:placetype":"venue"
},
  "geometry": {"coordinates":[-8.3797693253,43.3209953308],"type":"Point"}
}