{
  "type": "Feature",
  "properties": {
    "iso:country":"ES",
    "sg:address":"Carrer de Gran Capita, S/n",
    "sg:city":"Barcelona",
    "sg:orig_category":"Ense\u00d1anza Variada",
    "sg:phone":"+34 932 05 42 89",
    "sg:postcode":"08034",
    "sg:province":"Barcelona",
    "wof:name":"Dortmund S.l.",
    "wof:placetype":"venue"
},
  "geometry": {"coordinates":[2.1092219353,41.3881950378],"type":"Point"}
}