{
  "type": "Feature",
  "properties": {
    "addr:full":"Calle de Toro, 84 Salamanca Salamanca 37002",
    "addr:housenumber":"84",
    "addr:postcode":"37002",
    "addr:street":"Calle De Toro",
    "iso:country":"ES",
    "sg:address":"Calle de Toro, 84",
    "sg:city":"Salamanca",
    "sg:orig_category":"T\u00c9cnicos Veterinarios",
    "sg:phone":"+34 923 21 93 63",
    "sg:postcode":"37002",
    "sg:province":"Salamanca",
    "wof:name":"Montero Vicente Mariano",
    "wof:placetype":"venue"
},
  "geometry": {"coordinates":[-5.6603951454,40.9683494568],"type":"Point"}
}