{
  "type": "Feature",
  "properties": {
    "addr:full":"Rbla Arago, 5 Lleida Lleida 25003",
    "addr:housenumber":"5",
    "addr:postcode":"25003",
    "addr:street":"Rbla Arago",
    "iso:country":"ES",
    "sg:address":"Rbla Arago, 5",
    "sg:city":"Lleida",
    "sg:orig_category":"Abogados",
    "sg:phone":"+34 973 26 81 95",
    "sg:postcode":"25003",
    "sg:province":"Lleida",
    "wof:name":"Duro Oriol Joan",
    "wof:placetype":"venue"
},
  "geometry": {"coordinates":[0.6196299791,41.612991333],"type":"Point"}
}