{
  "type": "Feature",
  "properties": {
    "iso:country":"ES",
    "sg:address":"Rua Couto San Honorato, 13",
    "sg:city":"Vigo",
    "sg:orig_category":"Arquitectos",
    "sg:phone":"+34 986 21 22 33",
    "sg:postcode":"36204",
    "sg:province":"Pontevedra",
    "wof:name":"Adro S.l.",
    "wof:placetype":"venue"
},
  "geometry": {"coordinates":[-8.7150211334,42.2284431458],"type":"Point"}
}