{
  "type": "Feature",
  "properties": {
    "iso:country":"ES",
    "sg:address":"Calle de Martinez Monta\u00d1es, 19",
    "sg:city":"Sevilla",
    "sg:orig_category":"Asociaciones, Organismos Culturales Y Socioeducativos",
    "sg:phone":"+34 954 38 11 54",
    "sg:postcode":"41002",
    "sg:province":"Sevilla",
    "wof:name":"Hermandad Sacramental De La Soledad",
    "wof:placetype":"venue"
},
  "geometry": {"coordinates":[-5.997235775,37.3959236145],"type":"Point"}
}