{
  "type": "Feature",
  "properties": {
    "addr:full":"Carrer de Pi I Margall, 40 Molins Rei Barcelona 08750",
    "addr:housenumber":"40",
    "addr:postcode":"08750",
    "addr:street":"Carrer De Pi I Margall;Barcelona",
    "iso:country":"ES",
    "sg:address":"Carrer de Pi I Margall, 40",
    "sg:city":"Molins Rei",
    "sg:orig_category":"Peluqueros: De Se\u00d1oras",
    "sg:phone":"+34 936 68 09 94",
    "sg:postcode":"08750",
    "sg:province":"Barcelona",
    "wof:name":"Balocas Moreno Piedad",
    "wof:placetype":"venue"
},
  "geometry": {"coordinates":[2.0186591148,41.4090270996],"type":"Point"}
}