{
  "type": "Feature",
  "properties": {
    "iso:country":"ES",
    "sg:address":"Calle de Lepanto, 3",
    "sg:city":"Granada",
    "sg:classifiers":[
        {
            "category":"Community Center",
            "subcategory":"Youth",
            "type":"Public Place"
        }
    ],
    "sg:phone":"+34 958 22 70 64",
    "sg:postcode":"18009",
    "sg:province":"Granada",
    "sg:tags":[
        "juventud",
        "administraci\u00d3n",
        "la",
        "en",
        "deporte",
        "el",
        "y"
    ],
    "wof:name":"Diverama S.l.",
    "wof:placetype":"venue"
},
  "geometry": {"coordinates":[-3.5983159542,37.1747245789],"type":"Point"}
}