{
  "type": "Feature",
  "properties": {
    "iso:country":"ES",
    "sg:address":"Calle de Gran Via, 36",
    "sg:city":"Salamanca",
    "sg:orig_category":"M\u00c9dicos: Otorrinolaringolog\u00cda",
    "sg:phone":"+34 923 21 62 66",
    "sg:postcode":"37001",
    "sg:province":"Salamanca",
    "wof:name":"Ca\u00f1izo Alvarez Agustin Del",
    "wof:placetype":"venue"
},
  "geometry": {"coordinates":[-5.6609520912,40.9648895264],"type":"Point"}
}