{
  "type": "Feature",
  "properties": {
    "iso:country":"ES",
    "sg:address":"Avda Principe De Asturias, 16",
    "sg:city":"Zamora",
    "sg:orig_category":"Peluqueros: De Se\u00d1oras",
    "sg:phone":"+34 980 52 05 10",
    "sg:postcode":"49012",
    "sg:province":"Zamora",
    "wof:name":"Nieves Gonzalez Josefa",
    "wof:placetype":"venue"
},
  "geometry": {"coordinates":[-5.7383089066,41.5101318359],"type":"Point"}
}