{
  "type": "Feature",
  "properties": {
    "addr:full":"Calle de Campo Grande, 4 Rua De Valdeorras Ourense 32350",
    "addr:housenumber":"4",
    "addr:postcode":"32350",
    "addr:street":"Calle De Campo;Rua De",
    "iso:country":"ES",
    "sg:address":"Calle de Campo Grande, 4",
    "sg:city":"Rua De Valdeorras",
    "sg:orig_category":"Supermercados Y Hipermercados",
    "sg:phone":"+34 988 31 05 66",
    "sg:postcode":"32350",
    "sg:province":"Ourense",
    "wof:name":"Juan Miguel Dieguez Rivas S.l.",
    "wof:placetype":"venue"
},
  "geometry": {"coordinates":[-7.1054272652,42.3958854675],"type":"Point"}
}