{
  "type": "Feature",
  "properties": {
    "iso:country":"ES",
    "sg:address":"Villares De Abajo, S/n",
    "sg:city":"Villares De Abajo",
    "sg:orig_category":"Explotaci\u00d3n De Minas",
    "sg:phone":"+34 985 91 81 32",
    "sg:postcode":"33812",
    "sg:province":"Asturias",
    "wof:name":"Minero Siderurgica De Ponferrada S.a.",
    "wof:placetype":"venue"
},
  "geometry": {"coordinates":[-6.5779118538,42.94165802],"type":"Point"}
}