{
  "type": "Feature",
  "properties": {
    "iso:country":"ES",
    "sg:address":"Calle de Llerena, 30",
    "sg:city":"Fuente Cantos",
    "sg:orig_category":"Asesor\u00cda Fiscal Y Jur\u00cddica",
    "sg:phone":"+34 924 50 01 50",
    "sg:postcode":"06240",
    "sg:province":"Badajoz",
    "wof:name":"Saban Asesores S.l.",
    "wof:placetype":"venue"
},
  "geometry": {"coordinates":[-6.3064408302,38.2469215393],"type":"Point"}
}