{
  "type": "Feature",
  "properties": {
    "addr:full":"Calle de Corrientes, 1 Palmas De Gran Canaria Las Palmas 35008",
    "addr:housenumber":"1",
    "addr:postcode":"35008",
    "addr:street":"Calle De Corrientes",
    "iso:country":"ES",
    "sg:address":"Calle de Corrientes, 1",
    "sg:city":"Palmas De Gran Canaria",
    "sg:orig_category":"Electricidad: Material Y Suministros De Instalaci\u00d3n (fabricaci\u00d3n)",
    "sg:phone":"+34 928 46 37 55",
    "sg:postcode":"35008",
    "sg:province":"Las Palmas",
    "wof:name":"Instaladora Quintana S. A. L.",
    "wof:placetype":"venue"
},
  "geometry": {"coordinates":[-15.4217681885,28.1573104858],"type":"Point"}
}