{
  "type": "Feature",
  "properties": {
    "addr:full":"Carr Cami Des Castell, 223 Mao Islas Baleares 07702",
    "addr:housenumber":"223",
    "addr:postcode":"07702",
    "addr:street":"Carr Cami Des Castell",
    "iso:country":"ES",
    "sg:address":"Carr Cami Des Castell, 223",
    "sg:city":"Mao",
    "sg:orig_category":"Supermercados Y Hipermercados",
    "sg:phone":"+34 971 35 36 83",
    "sg:postcode":"07702",
    "sg:province":"Islas Baleares",
    "wof:name":"Bellavista Supermercat S.a.",
    "wof:placetype":"venue"
},
  "geometry": {"coordinates":[4.270321846,39.8844566345],"type":"Point"}
}