{
  "type": "Feature",
  "properties": {
    "addr:full":"Carrer de Major, 76 Manresa Barcelona 08242",
    "addr:housenumber":"76",
    "addr:postcode":"08242",
    "addr:street":"Carrer De Major",
    "iso:country":"ES",
    "sg:address":"Carrer de Major, 76",
    "sg:city":"Manresa",
    "sg:orig_category":"Centros Empresariales",
    "sg:phone":"+34 938 77 18 18",
    "sg:postcode":"08242",
    "sg:province":"Barcelona",
    "wof:name":"Gestio Negocis I Serveis Bages S.l.",
    "wof:placetype":"venue"
},
  "geometry": {"coordinates":[1.8267960548,41.7343444824],"type":"Point"}
}