{
  "type": "Feature",
  "properties": {
    "addr:full":"Calle de San Roque, 4 Sevilla Sevilla 41001",
    "addr:housenumber":"4",
    "addr:postcode":"41001",
    "addr:street":"Calle De San Roque",
    "iso:country":"ES",
    "sg:address":"Calle de San Roque, 4",
    "sg:city":"Sevilla",
    "sg:orig_category":"Ropa Para Se\u00d1oras (al Por Menor)",
    "sg:phone":"+34 954 56 18 30",
    "sg:postcode":"41001",
    "sg:province":"Sevilla",
    "wof:name":"Gomez Vazquez Maria Del Sol",
    "wof:placetype":"venue"
},
  "geometry": {"coordinates":[-5.9983520508,37.3912162781],"type":"Point"}
}