{
  "type": "Feature",
  "properties": {
    "iso:country":"ES",
    "sg:address":"Albufera, 11",
    "sg:city":"Beniparrell",
    "sg:orig_category":"Plomeros",
    "sg:phone":"+34 961 20 08 07",
    "sg:postcode":"46469",
    "sg:province":"Valencia",
    "wof:name":"Coloma Rosel Francisco",
    "wof:placetype":"venue"
},
  "geometry": {"coordinates":[-0.4118140042,39.380241394],"type":"Point"}
}