{
  "type": "Feature",
  "properties": {
    "iso:country":"ES",
    "sg:address":"Calle de Valle Inclan, S/n",
    "sg:city":"Alacant",
    "sg:orig_category":"Iglesia Cat\u00d3lica",
    "sg:phone":"+34 965 18 26 45",
    "sg:postcode":"03011",
    "sg:province":"Alicante",
    "wof:name":"Parroquia Nuestra Se\u00f1ora Del Remedio",
    "wof:placetype":"venue"
},
  "geometry": {"coordinates":[-0.4912810922,38.374004364],"type":"Point"}
}