{
  "type": "Feature",
  "properties": {
    "iso:country":"ES",
    "sg:address":"Avda Virgen De Loreto, 14",
    "sg:city":"Torrejon Ardoz",
    "sg:orig_category":"Farmacias",
    "sg:phone":"+34 916 76 62 24",
    "sg:postcode":"28850",
    "sg:province":"Madrid",
    "wof:name":"Argudo Caballero Jose Carlos",
    "wof:placetype":"venue"
},
  "geometry": {"coordinates":[-3.47539711,40.4593963623],"type":"Point"}
}