{
  "type": "Feature",
  "properties": {
    "addr:full":"Rua Orense (de), 55 Carballi\u00f1o Ourense 32500",
    "addr:housenumber":"55",
    "addr:postcode":"32500",
    "addr:street":"Rua Orense De",
    "iso:country":"ES",
    "sg:address":"Rua Orense (de), 55",
    "sg:city":"Carballi\u00f1o",
    "sg:orig_category":"Empresas De Pintura Y Revestimientos",
    "sg:phone":"+34 988 27 40 15",
    "sg:postcode":"32500",
    "sg:province":"Ourense",
    "wof:name":"Garcia Mato Jose Manuel",
    "wof:placetype":"venue"
},
  "geometry": {"coordinates":[-8.0665817261,42.4291114807],"type":"Point"}
}