{
  "type": "Feature",
  "properties": {
    "addr:full":"Calle de Mies De San Juan, 7 Malia\u00d1o Cantabria 39600",
    "addr:housenumber":"7",
    "addr:postcode":"39600",
    "addr:street":"Calle De Mies De San Juan",
    "iso:country":"ES",
    "sg:address":"Calle de Mies De San Juan, 7",
    "sg:city":"Malia\u00d1o",
    "sg:orig_category":"Forjas Y Altos Hornos",
    "sg:phone":"+34 942 26 17 11",
    "sg:postcode":"39600",
    "sg:province":"Cantabria",
    "wof:name":"Martin Gutierrez Maria Angeles",
    "wof:placetype":"venue"
},
  "geometry": {"coordinates":[-3.8309459686,43.4223442078],"type":"Point"}
}