{
  "type": "Feature",
  "properties": {
    "iso:country":"ES",
    "sg:address":"Calle de Resina, 13",
    "sg:city":"Madrid",
    "sg:orig_category":"Venta, Instalaci\u00d3n, Reparaci\u00d3n De Antenas Para Televisi\u00d3n",
    "sg:phone":"+34 915 05 15 17",
    "sg:postcode":"28021",
    "sg:province":"Madrid",
    "wof:name":"Codinsa Deyre S.l.",
    "wof:placetype":"venue"
},
  "geometry": {"coordinates":[-3.6976959705,40.3359069824],"type":"Point"}
}