{
  "type": "Feature",
  "properties": {
    "addr:full":"Plaz Madrid, 2 Mora Toledo 45400",
    "addr:housenumber":"2",
    "addr:postcode":"45400",
    "addr:street":"Madrid",
    "iso:country":"ES",
    "sg:address":"Plaz Madrid, 2",
    "sg:city":"Mora",
    "sg:orig_category":"Producci\u00d3n, Comercio De Cereales",
    "sg:phone":"+34 925 34 19 47",
    "sg:postcode":"45400",
    "sg:province":"Toledo",
    "wof:name":"Cereales Del Carmen S.l.",
    "wof:placetype":"venue"
},
  "geometry": {"coordinates":[-3.7708759308,39.6840553284],"type":"Point"}
}