{
  "type": "Feature",
  "properties": {
    "iso:country":"ES",
    "sg:address":"Avda Granada, S/n",
    "sg:city":"Huescar",
    "sg:orig_category":"Mec\u00c1nico Del Autom\u00d3vil",
    "sg:phone":"+34 958 74 03 51",
    "sg:postcode":"18830",
    "sg:province":"Granada",
    "wof:name":"Gallego Ujaque Antonio",
    "wof:placetype":"venue"
},
  "geometry": {"coordinates":[-2.544203043,37.7994041443],"type":"Point"}
}