{
  "type": "Feature",
  "properties": {
    "iso:country":"ES",
    "sg:address":"Avda Bueu, 2",
    "sg:city":"Cangas",
    "sg:orig_category":"M\u00c9dicos: Estomatolog\u00cda",
    "sg:phone":"+34 986 30 49 65",
    "sg:postcode":"36940",
    "sg:province":"Pontevedra",
    "wof:name":"Centro Odontologico Cangas, Sl",
    "wof:placetype":"venue"
},
  "geometry": {"coordinates":[-8.8184690475,42.2742500305],"type":"Point"}
}