{
  "type": "Feature",
  "properties": {
    "addr:full":"Calle de Juan Sebastian Elcano, 3 Sant Joan D'alacant Alicante 03550",
    "addr:housenumber":"3",
    "addr:postcode":"03550",
    "addr:street":"Calle De Juan Sebastian Elcano",
    "iso:country":"ES",
    "sg:address":"Calle de Juan Sebastian Elcano, 3",
    "sg:city":"Sant Joan D'alacant",
    "sg:orig_category":"Molduras, Junquillos, Listones Y Molduras Perforadas",
    "sg:phone":"+34 965 65 74 96",
    "sg:postcode":"03550",
    "sg:province":"Alicante",
    "wof:name":"Oliva Arcas Laureano",
    "wof:placetype":"venue"
},
  "geometry": {"coordinates":[-0.4804700017,38.3440818787],"type":"Point"}
}