{
  "type": "Feature",
  "properties": {
    "iso:country":"ES",
    "sg:address":"Joan Peiro Belis(p I Vallmorena), S/n",
    "sg:city":"Vilassar Dalt",
    "sg:orig_category":"Marketing Directo",
    "sg:phone":"+34 937 53 24 22",
    "sg:postcode":"08339",
    "sg:province":"Barcelona",
    "sg:website":"www.presyntex.com",
    "wof:name":"Presyntex S.l.",
    "wof:placetype":"venue"
},
  "geometry": {"coordinates":[2.3616290092,41.5183601379],"type":"Point"}
}