{
  "type": "Feature",
  "properties": {
    "iso:country":"ES",
    "sg:address":"Calle de Hoya Del Molino, 14",
    "sg:city":"Lucena",
    "sg:orig_category":"Arreglo, Reparaci\u00d3n, Piezas Sueltas De Televisi\u00d3n, V\u00cddeo, Hi",
    "sg:phone":"+34 957 51 01 90",
    "sg:postcode":"14900",
    "sg:province":"C\u00f3rdoba",
    "wof:name":"Electronica Andalucia S.c.",
    "wof:placetype":"venue"
},
  "geometry": {"coordinates":[-4.4895219803,37.4062690735],"type":"Point"}
}