{
  "type": "Feature",
  "properties": {
    "addr:full":"Av Marina Alta (de La), 15 Gata Gorgos Alicante 03740",
    "addr:housenumber":"15",
    "addr:postcode":"03740",
    "addr:street":"Av",
    "iso:country":"ES",
    "sg:address":"Av Marina Alta (de La), 15",
    "sg:city":"Gata Gorgos",
    "sg:orig_category":"Moda",
    "sg:phone":"+34 965 75 61 56",
    "sg:postcode":"03740",
    "sg:province":"Alicante",
    "wof:name":"Matias Monfort S.l",
    "wof:placetype":"venue"
},
  "geometry": {"coordinates":[0.0845099986,38.7753562927],"type":"Point"}
}