{
  "type": "Feature",
  "properties": {
    "addr:full":"Calle de San Bernabe, 2 Marbella M\u00e1laga 29600",
    "addr:housenumber":"2",
    "addr:postcode":"29600",
    "addr:street":"Calle De San Bernabe;Ma\u0301Laga",
    "iso:country":"ES",
    "sg:address":"Calle de San Bernabe, 2",
    "sg:city":"Marbella",
    "sg:orig_category":"Albergues",
    "sg:phone":"+34 952 77 17 39",
    "sg:postcode":"29600",
    "sg:province":"M\u00e1laga",
    "wof:name":"Martin Caloto Eulalia",
    "wof:placetype":"venue"
},
  "geometry": {"coordinates":[-4.8792309761,36.5154571533],"type":"Point"}
}