{
  "type": "Feature",
  "properties": {
    "iso:country":"ES",
    "sg:address":"Calle de Barrionuevo, 4",
    "sg:city":"Cordoba",
    "sg:orig_category":"Librer\u00cdas",
    "sg:phone":"+34 957 26 92 12",
    "sg:postcode":"14002",
    "sg:province":"C\u00f3rdoba",
    "wof:name":"Perez De La Concha Camacho Manuel",
    "wof:placetype":"venue"
},
  "geometry": {"coordinates":[-4.7675848007,37.8839683533],"type":"Point"}
}