{
  "type": "Feature",
  "properties": {
    "addr:full":"Sector Carmanso, 132 Empuriabrava Girona 17487",
    "addr:housenumber":"132",
    "addr:postcode":"17487",
    "addr:street":"Sector Carmanso",
    "iso:country":"ES",
    "sg:address":"Sector Carmanso, 132",
    "sg:city":"Empuriabrava",
    "sg:orig_category":"Inmobiliaria (agencias)",
    "sg:phone":"+34 972 45 10 77",
    "sg:postcode":"17487",
    "sg:province":"Girona",
    "wof:name":"Agencia Cervera & Cervera S.l.",
    "wof:placetype":"venue"
},
  "geometry": {"coordinates":[3.1227703094,42.2480926514],"type":"Point"}
}