{
  "type": "Feature",
  "properties": {
    "iso:country":"ES",
    "sg:address":"Calle de Alegria, 14",
    "sg:city":"Gijon",
    "sg:orig_category":"Art\u00cdculos De Decoraci\u00d3n",
    "sg:phone":"+34 985 15 31 22",
    "sg:postcode":"33209",
    "sg:province":"Asturias",
    "wof:name":"E.crespo S.l.",
    "wof:placetype":"venue"
},
  "geometry": {"coordinates":[-5.659637928,43.5300559998],"type":"Point"}
}