{
  "type": "Feature",
  "properties": {
    "addr:full":"Calle de Perez Galdos, 80 Arrecife Las Palmas 35500",
    "addr:housenumber":"80",
    "addr:postcode":"35500",
    "addr:street":"Calle De Perez Galdos",
    "iso:country":"ES",
    "sg:address":"Calle de Perez Galdos, 80",
    "sg:city":"Arrecife",
    "sg:classifiers":[
        {
            "category":"Autos & Motor Vehicles",
            "subcategory":"Automobile Sales",
            "type":"Retail Goods"
        }
    ],
    "sg:phone":"+34 928 81 28 15",
    "sg:postcode":"35500",
    "sg:province":"Las Palmas",
    "sg:website":"www.aemcb.com",
    "wof:name":"Autoescuela Maria Del Carmen De Benitez S.l.",
    "wof:placetype":"venue"
},
  "geometry": {"coordinates":[-13.5449390411,28.9670295715],"type":"Point"}
}