{
  "type": "Feature",
  "properties": {
    "iso:country":"ES",
    "sg:address":"Avda Madariaga, 77",
    "sg:city":"Bilbao",
    "sg:orig_category":"Reciclaje Y Tratamiento De Desechos Varios",
    "sg:phone":"+34 944 76 13 34",
    "sg:postcode":"48014",
    "sg:province":"Vizcaya",
    "wof:name":"Floren Narro Arriortua",
    "wof:placetype":"venue"
},
  "geometry": {"coordinates":[-2.956964016,43.2698326111],"type":"Point"}
}