{
  "type": "Feature",
  "properties": {
    "iso:country":"ES",
    "sg:address":"Calle de Seis De Junio, 37",
    "sg:city":"Valdepe\u00f1as",
    "sg:orig_category":"Cl\u00cdnicas M\u00c9dicas",
    "sg:phone":"+34 926 32 25 03",
    "sg:postcode":"13300",
    "sg:province":"Ciudad Real",
    "wof:name":"Salem  Haidar",
    "wof:placetype":"venue"
},
  "geometry": {"coordinates":[-3.3883049488,38.7574462891],"type":"Point"}
}