{
  "type": "Feature",
  "properties": {
    "iso:country":"ES",
    "sg:address":"Calle de Sasikoa Kalea, 22",
    "sg:city":"Durango",
    "sg:orig_category":"Compraventa De Antig\u00dcedades",
    "sg:phone":"+34 944 66 85 94",
    "sg:postcode":"48200",
    "sg:province":"Vizcaya",
    "wof:name":"Silvia Corral Gilsanz",
    "wof:placetype":"venue"
},
  "geometry": {"coordinates":[-2.6392920017,43.1720924377],"type":"Point"}
}