{
  "type": "Feature",
  "properties": {
    "iso:country":"ES",
    "sg:address":"Calle de Padre Llanos, 30",
    "sg:city":"Valladolid",
    "sg:orig_category":"Promotores Constructores",
    "sg:phone":"+34 983 35 17 87",
    "sg:postcode":"47014",
    "sg:province":"Valladolid",
    "wof:name":"Sanz De Diego Elvira",
    "wof:placetype":"venue"
},
  "geometry": {"coordinates":[-4.758849144,41.6410102844],"type":"Point"}
}