{
  "type": "Feature",
  "properties": {
    "iso:country":"ES",
    "sg:address":"Rua Don Pepe Puga (de), 12",
    "sg:city":"Allariz",
    "sg:orig_category":"Notarios",
    "sg:phone":"+34 988 44 02 32",
    "sg:postcode":"32660",
    "sg:province":"Ourense",
    "wof:name":"Fernandez Gonzalez Francisco Javier",
    "wof:placetype":"venue"
},
  "geometry": {"coordinates":[-7.7995538712,42.1900787354],"type":"Point"}
}