{
  "type": "Feature",
  "properties": {
    "addr:full":"Calle de Claudiano (el), 4 Arrecife Las Palmas 35500",
    "addr:housenumber":"4",
    "addr:postcode":"35500",
    "addr:street":"Calle De Claudiano El",
    "iso:country":"ES",
    "sg:address":"Calle de Claudiano (el), 4",
    "sg:city":"Arrecife",
    "sg:orig_category":"Comercio De Piezas De Recambio Y De Accesorios De Veh\u00cdculos, Veh\u00cdculos Industriales",
    "sg:phone":"+34 928 81 30 17",
    "sg:postcode":"35500",
    "sg:province":"Las Palmas",
    "wof:name":"Autorepuestos Ramos S.l.",
    "wof:placetype":"venue"
},
  "geometry": {"coordinates":[-13.5440616608,28.964756012],"type":"Point"}
}