{
  "type": "Feature",
  "properties": {
    "addr:full":"Calle de Castrillo De Aza, 8 Madrid Madrid 28031",
    "addr:housenumber":"8",
    "addr:postcode":"madrid;28031",
    "addr:street":"Calle De Castrillo De Aza",
    "iso:country":"ES",
    "sg:address":"Calle de Castrillo De Aza, 8",
    "sg:city":"Madrid",
    "sg:orig_category":"Aluminio Y Aleaciones (producci\u00d3n, Transformaci\u00d3n, Negocio)",
    "sg:phone":"+34 913 32 62 22",
    "sg:postcode":"28031",
    "sg:province":"Madrid",
    "wof:name":"Aluminios Padron S.a.",
    "wof:placetype":"venue"
},
  "geometry": {"coordinates":[-3.6081371307,40.3852043152],"type":"Point"}
}