{
  "type": "Feature",
  "properties": {
    "iso:country":"ES",
    "sg:address":"Calle de Conde De Pe\u00d1alver, 18",
    "sg:city":"Madrid",
    "sg:orig_category":"Caf\u00c9s (al Por Menor)",
    "sg:phone":"+34 915 76 04 69",
    "sg:postcode":"28006",
    "sg:province":"Madrid",
    "wof:name":"Guilis Sociedad Anonima",
    "wof:placetype":"venue"
},
  "geometry": {"coordinates":[-3.675535202,40.4269599915],"type":"Point"}
}