{
  "type": "Feature",
  "properties": {
    "iso:country":"ES",
    "sg:address":"Calle de Arroyuelo Medio, 1",
    "sg:city":"Madridejos",
    "sg:orig_category":"Empresarios",
    "sg:phone":"+34 925 46 00 74",
    "sg:postcode":"45710",
    "sg:province":"Toledo",
    "wof:name":"Galan Garcia Migel Angel",
    "wof:placetype":"venue"
},
  "geometry": {"coordinates":[-3.5364646912,39.4689102173],"type":"Point"}
}