{
  "type": "Feature",
  "properties": {
    "addr:full":"Calle de Bilbao, 39 Arrecife Las Palmas 35500",
    "addr:housenumber":"39",
    "addr:postcode":"35500",
    "addr:street":"Calle De Bilbao",
    "iso:country":"ES",
    "sg:address":"Calle de Bilbao, 39",
    "sg:city":"Arrecife",
    "sg:orig_category":"Transportes Por Carretera: Lotes Completos, Mercanc\u00cdas Diversas",
    "sg:phone":"+34 928 82 42 35",
    "sg:postcode":"35500",
    "sg:province":"Las Palmas",
    "wof:name":"Cardom S.l.",
    "wof:placetype":"venue"
},
  "geometry": {"coordinates":[-13.545091629,28.9776554108],"type":"Point"}
}