{
  "type": "Feature",
  "properties": {
    "iso:country":"ES",
    "sg:address":"Calle de General Vives, 83",
    "sg:city":"Palmas De Gran Canaria",
    "sg:orig_category":"Herboristas (al Por Menor)",
    "sg:phone":"+34 928 22 30 39",
    "sg:postcode":"35007",
    "sg:province":"Las Palmas",
    "wof:name":"Diaz Fuentes Patricia",
    "wof:placetype":"venue"
},
  "geometry": {"coordinates":[-15.4313611984,28.1406173706],"type":"Point"}
}