{
  "type": "Feature",
  "properties": {
    "iso:country":"ES",
    "sg:address":"Avda General Sanjurjo, 16",
    "sg:city":"Coru\u00d1a",
    "sg:orig_category":"M\u00c9dicos: Dermatolog\u00cda Y Venereolog\u00cda",
    "sg:phone":"+34 981 13 09 15",
    "sg:postcode":"15006",
    "sg:province":"A Coru\u00f1a",
    "wof:name":"Seijo Garcia Juan Carlos",
    "wof:placetype":"venue"
},
  "geometry": {"coordinates":[-8.4032011032,43.3562583923],"type":"Point"}
}