{
  "type": "Feature",
  "properties": {
    "addr:full":"Calle de Vicente Aleixandre, 21 Infante Juan Manuel Murcia 30011",
    "addr:housenumber":"21",
    "addr:postcode":"30011",
    "addr:street":"Calle De Vicente Aleixandre;Juan",
    "iso:country":"ES",
    "sg:address":"Calle de Vicente Aleixandre, 21",
    "sg:city":"Infante Juan Manuel",
    "sg:classifiers":[
        {
            "category":"Professional",
            "subcategory":"Management & Consulting",
            "type":"Services"
        }
    ],
    "sg:phone":"+34 968 34 19 34",
    "sg:postcode":"30011",
    "sg:province":"Murcia",
    "sg:tags":[
        "asesor\u00cda",
        "en",
        "marketing"
    ],
    "wof:name":"Alarcon Lopez Antonio",
    "wof:placetype":"venue"
},
  "geometry": {"coordinates":[-1.1170941591,37.9771690369],"type":"Point"}
}