{
  "type": "Feature",
  "properties": {
    "iso:country":"ES",
    "sg:address":"Ptda Alberca (l'), S/n",
    "sg:city":"Nucia",
    "sg:orig_category":"Importaci\u00d3n",
    "sg:phone":"+34 965 88 70 80",
    "sg:postcode":"03530",
    "sg:province":"Alicante",
    "wof:name":"Artic Products S.l.",
    "wof:placetype":"venue"
},
  "geometry": {"coordinates":[-0.1259891987,38.6142196655],"type":"Point"}
}