{
  "type": "Feature",
  "properties": {
    "addr:full":"Calle de Aire, 1 Santa Marta De Tormes Salamanca 37900",
    "addr:housenumber":"1",
    "addr:postcode":"37900",
    "addr:street":"Calle De Aire",
    "iso:country":"ES",
    "sg:address":"Calle de Aire, 1",
    "sg:city":"Santa Marta De Tormes",
    "sg:orig_category":"Peluquer\u00cdas, Peluquer\u00cda Mixta",
    "sg:phone":"+34 923 20 08 74",
    "sg:postcode":"37900",
    "sg:province":"Salamanca",
    "wof:name":"Calvo Hernandez Ana",
    "wof:placetype":"venue"
},
  "geometry": {"coordinates":[-5.6321411133,40.9508590698],"type":"Point"}
}