{
  "type": "Feature",
  "properties": {
    "iso:country":"ES",
    "sg:address":"Avda Juan Carlos I, Km. 0433,0",
    "sg:city":"Fernan Nu\u00e7ez",
    "sg:orig_category":"Fabricaci\u00d3n De Muebles",
    "sg:phone":"+34 957 38 11 68",
    "sg:postcode":"14520",
    "sg:province":"C\u00f3rdoba",
    "wof:name":"Velasco Adana Juan",
    "wof:placetype":"venue"
},
  "geometry": {"coordinates":[-4.7239189148,37.6722068787],"type":"Point"}
}