{
  "type": "Feature",
  "properties": {
    "iso:country":"ES",
    "sg:address":"Carrer de Unio, 2",
    "sg:city":"Rubi",
    "sg:orig_category":"Empleado Administrativo",
    "sg:phone":"+34 935 88 35 18",
    "sg:postcode":"08191",
    "sg:province":"Barcelona",
    "wof:name":"Gestoria Capmany S. L.",
    "wof:placetype":"venue"
},
  "geometry": {"coordinates":[2.0300090313,41.4925270081],"type":"Point"}
}