{
  "type": "Feature",
  "properties": {
    "iso:country":"ES",
    "sg:address":"Av Mare De Deu De Bellvitge, 36",
    "sg:city":"Hospitalet Llobregat",
    "sg:orig_category":"Droguer\u00cdas (al Por Menor)",
    "sg:phone":"+34 933 36 17 51",
    "sg:postcode":"08907",
    "sg:province":"Barcelona",
    "wof:name":"Hidalgo Bonilla Miguel",
    "wof:placetype":"venue"
},
  "geometry": {"coordinates":[2.1075229645,41.3480224609],"type":"Point"}
}