{
  "type": "Feature",
  "properties": {
    "iso:country":"ES",
    "sg:address":"Calle de Higueras, 38",
    "sg:city":"Madrid",
    "sg:orig_category":"Comercio De Piezas De Recambio Y De Accesorios De Veh\u00cdculos, Veh\u00cdculos Industriales",
    "sg:phone":"+34 915 26 55 25",
    "sg:postcode":"28047",
    "sg:province":"Madrid",
    "wof:name":"Autorecambios Diana S.l.",
    "wof:placetype":"venue"
},
  "geometry": {"coordinates":[-3.7454555035,40.4028930664],"type":"Point"}
}