{
  "type": "Feature",
  "properties": {
    "iso:country":"ES",
    "sg:address":"Ctra Madrid, Km. 0303,7",
    "sg:city":"Ba\u00d1eza",
    "sg:orig_category":"Semiller\u00cdas",
    "sg:phone":"+34 987 64 35 61",
    "sg:postcode":"24750",
    "sg:province":"Le\u00f3n",
    "wof:name":"Lombo Delgado Jose Luis",
    "wof:placetype":"venue"
},
  "geometry": {"coordinates":[-5.8960561752,42.304019928],"type":"Point"}
}