{
  "type": "Feature",
  "properties": {
    "addr:full":"Carrer de Segre, 106 Barcelona Barcelona 08030",
    "addr:housenumber":"106",
    "addr:postcode":"08030",
    "addr:street":"Carrer De Segre",
    "iso:country":"ES",
    "sg:address":"Carrer de Segre, 106",
    "sg:city":"Barcelona",
    "sg:orig_category":"Estudios, Instalaci\u00d3n De Climatizaci\u00d3n",
    "sg:phone":"+34 934 15 76 04",
    "sg:postcode":"08030",
    "sg:province":"Barcelona",
    "wof:name":"Reigosa Ca\u00f1ellas Miguel",
    "wof:placetype":"venue"
},
  "geometry": {"coordinates":[2.1950230598,41.4303588867],"type":"Point"}
}