{
  "type": "Feature",
  "properties": {
    "addr:full":"Carrer de Sant Francesc, 20 Xixona Alicante 03100",
    "addr:housenumber":"20",
    "addr:postcode":"03100",
    "addr:street":"Carrer De Sant Francesc",
    "iso:country":"ES",
    "sg:address":"Carrer de Sant Francesc, 20",
    "sg:city":"Xixona",
    "sg:orig_category":"Cajas Y Embalajes De Madera",
    "sg:phone":"+34 965 61 05 66",
    "sg:postcode":"03100",
    "sg:province":"Alicante",
    "wof:name":"Industrias Jijonencas De La Madera S.l.",
    "wof:placetype":"venue"
},
  "geometry": {"coordinates":[-0.506286025,38.5458068848],"type":"Point"}
}