{
  "type": "Feature",
  "properties": {
    "iso:country":"ES",
    "sg:address":"Calle de General Vives, 23",
    "sg:city":"Palmas De Gran Canaria",
    "sg:orig_category":"Institutos De Belleza",
    "sg:phone":"+34 928 22 52 70",
    "sg:postcode":"35007",
    "sg:province":"Las Palmas",
    "wof:name":"Axon 2001 S.l.",
    "wof:placetype":"venue"
},
  "geometry": {"coordinates":[-15.4313058853,28.1363887787],"type":"Point"}
}