{
  "type": "Feature",
  "properties": {
    "iso:country":"ES",
    "sg:address":"Carrer de Oli, 3",
    "sg:city":"Palma",
    "sg:orig_category":"Granos Y Semillas (producci\u00d3n, Al Por Mayor)",
    "sg:phone":"+34 971 71 53 22",
    "sg:postcode":"07002",
    "sg:province":"Islas Baleares",
    "wof:name":"Llavors I Llegums Germanes Serra Cdad.",
    "wof:placetype":"venue"
},
  "geometry": {"coordinates":[2.6527600288,39.5711975098],"type":"Point"}
}