{
  "type": "Feature",
  "properties": {
    "iso:country":"ES",
    "sg:address":"Calle de Pedro De Asua, 49",
    "sg:city":"Vitoria-gasteiz",
    "sg:orig_category":"Electromec\u00c1nica",
    "sg:phone":"+34 945 24 76 40",
    "sg:postcode":"01008",
    "sg:province":"\u00c1lava",
    "wof:name":"Electromecanica Laguntza S.a.",
    "wof:placetype":"venue"
},
  "geometry": {"coordinates":[-2.6904249191,42.8466644287],"type":"Point"}
}