{
  "type": "Feature",
  "properties": {
    "addr:full":"Rda. Saliente, 8 Gevora Caudillo Badajoz 06180",
    "addr:housenumber":"8",
    "addr:postcode":"06180",
    "addr:street":"Saliente",
    "iso:country":"ES",
    "sg:address":"Rda. Saliente, 8",
    "sg:city":"Gevora Caudillo",
    "sg:orig_category":"Molduras, Junquillos, Listones Y Molduras Perforadas",
    "sg:phone":"+34 924 43 04 68",
    "sg:postcode":"06180",
    "sg:province":"Badajoz",
    "wof:name":"Mu\u00f1oz Talavera Juan Alberto",
    "wof:placetype":"venue"
},
  "geometry": {"coordinates":[-6.9436321259,38.9183158875],"type":"Point"}
}