{
  "type": "Feature",
  "properties": {
    "addr:full":"Calle de Federico Garcia Lorca, 5 Bargas Toledo 45593",
    "addr:housenumber":"5",
    "addr:postcode":"45593",
    "addr:street":"Calle De Federico Garcia Lorca",
    "iso:country":"ES",
    "sg:address":"Calle de Federico Garcia Lorca, 5",
    "sg:city":"Bargas",
    "sg:orig_category":"Promotores Constructores",
    "sg:phone":"+34 925 35 88 34",
    "sg:postcode":"45593",
    "sg:province":"Toledo",
    "wof:name":"Rodriguez Bargue\u00f1o Jose",
    "wof:placetype":"venue"
},
  "geometry": {"coordinates":[-4.015545845,39.9407730103],"type":"Point"}
}