{
  "type": "Feature",
  "properties": {
    "iso:country":"ES",
    "sg:address":"Vieja De Valencia, S/n",
    "sg:city":"Xeraco",
    "sg:orig_category":"Art\u00cdculos De Madera (fabricaci\u00d3n Y Al Por Mayor)",
    "sg:phone":"+34 962 89 12 19",
    "sg:postcode":"46770",
    "sg:province":"Valencia",
    "wof:name":"Wine Box S.l.",
    "wof:placetype":"venue"
},
  "geometry": {"coordinates":[-0.216049701,39.0328979492],"type":"Point"}
}