{
  "type": "Feature",
  "properties": {
    "addr:full":"Calle de Jose Andres Vazquez, S/n Aracena Huelva 21200",
    "addr:housenumber":"s / n",
    "addr:postcode":"21200",
    "addr:street":"Calle De Jose Andres Vazquez",
    "iso:country":"ES",
    "sg:address":"Calle de Jose Andres Vazquez, S/n",
    "sg:city":"Aracena",
    "sg:orig_category":"Agencias Y Agentes Comerciales, Representantes",
    "sg:phone":"+34 959 12 89 24",
    "sg:postcode":"21200",
    "sg:province":"Huelva",
    "wof:name":"Vazquez Colchero Maria Dolores",
    "wof:placetype":"venue"
},
  "geometry": {"coordinates":[-6.558368206,37.8906097412],"type":"Point"}
}