{
  "type": "Feature",
  "properties": {
    "iso:country":"ES",
    "sg:address":"Calle de San Vicente, 19",
    "sg:city":"Javea",
    "sg:orig_category":"Electricidad: Instaladores",
    "sg:phone":"+34 966 46 30 79",
    "sg:postcode":"03730",
    "sg:province":"Alicante",
    "wof:name":"Molina Ivars Juan",
    "wof:placetype":"venue"
},
  "geometry": {"coordinates":[0.1600089967,38.7864723206],"type":"Point"}
}