{
  "type": "Feature",
  "properties": {
    "iso:country":"ES",
    "sg:address":"Calle de Garcia Morato, 15",
    "sg:city":"Alacant",
    "sg:orig_category":"Compraventa De Antig\u00dcedades",
    "sg:phone":"+34 965 20 22 33",
    "sg:postcode":"03004",
    "sg:province":"Alicante",
    "wof:name":"Balboa Sempere Adolfo",
    "wof:placetype":"venue"
},
  "geometry": {"coordinates":[-0.4872451127,38.3483924866],"type":"Point"}
}