{
  "type": "Feature",
  "properties": {
    "addr:full":"Calle de Peru, 21 Coslada Madrid 28820",
    "addr:housenumber":"21",
    "addr:postcode":"28820",
    "addr:street":"Calle De Peru",
    "iso:country":"ES",
    "sg:address":"Calle de Peru, 21",
    "sg:city":"Coslada",
    "sg:orig_category":"Caf\u00c9s, Bares, Cervecer\u00cdas",
    "sg:phone":"+34 916 72 20 43",
    "sg:postcode":"28820",
    "sg:province":"Madrid",
    "wof:name":"Navarrete Martil Ventura",
    "wof:placetype":"venue"
},
  "geometry": {"coordinates":[-3.5409560204,40.430267334],"type":"Point"}
}