{
  "type": "Feature",
  "properties": {
    "addr:full":"Carrer de Casp, 23 Barcelona Barcelona 08010",
    "addr:housenumber":"23",
    "addr:postcode":"08010",
    "addr:street":"Carrer De Casp",
    "iso:country":"ES",
    "sg:address":"Carrer de Casp, 23",
    "sg:city":"Barcelona",
    "sg:orig_category":"Inform\u00c1tica (estudios, Servicios, Asesor\u00cda, Formaci\u00d3n)",
    "sg:phone":"+34 933 17 62 35",
    "sg:postcode":"08010",
    "sg:province":"Barcelona",
    "wof:name":"Software De Gestio S.l.",
    "wof:placetype":"venue"
},
  "geometry": {"coordinates":[2.1708109379,41.3896331787],"type":"Point"}
}