{
  "type": "Feature",
  "properties": {
    "addr:full":"Carrer de Arago, 99 Barcelona Barcelona 08015",
    "addr:housenumber":"99",
    "addr:postcode":"08015",
    "addr:street":"Carrer De Arago",
    "iso:country":"ES",
    "sg:address":"Carrer de Arago, 99",
    "sg:city":"Barcelona",
    "sg:orig_category":"Ropa Para Se\u00d1oras (al Por Menor)",
    "sg:phone":"+34 932 26 07 34",
    "sg:postcode":"08015",
    "sg:province":"Barcelona",
    "wof:name":"Estilo Grupo G S.c.p.",
    "wof:placetype":"venue"
},
  "geometry": {"coordinates":[2.151391983,41.3822059631],"type":"Point"}
}