{
  "type": "Feature",
  "properties": {
    "iso:country":"ES",
    "sg:address":"Calle de General Sabino Fernandez Campo, 8",
    "sg:city":"Oviedo",
    "sg:orig_category":"Controles De Edificaci\u00d3n (construcci\u00d3n, Seguridad)",
    "sg:phone":"+34 985 11 86 86",
    "sg:postcode":"33011",
    "sg:province":"Asturias",
    "wof:name":"Begar Construcciones Y Contratas S.a.",
    "wof:placetype":"venue"
},
  "geometry": {"coordinates":[-5.8340411186,43.3698158264],"type":"Point"}
}