{
  "type": "Feature",
  "properties": {
    "addr:full":"Plaz San Ildefonso, 2 Jaen Ja\u00e9n 23001",
    "addr:housenumber":"2;jae\u0301n",
    "addr:postcode":"23001",
    "addr:street":"Plaz San Ildefonso",
    "iso:country":"ES",
    "sg:address":"Plaz San Ildefonso, 2",
    "sg:city":"Jaen",
    "sg:orig_category":"Cajas De Ahorro",
    "sg:phone":"+34 953 24 06 15",
    "sg:postcode":"23001",
    "sg:province":"Ja\u00e9n",
    "sg:website":"www.lacaixa.es",
    "wof:name":"Caixa D'estalvis I Pensions De Barcelona",
    "wof:placetype":"venue"
},
  "geometry": {"coordinates":[-3.7906870842,37.7650947571],"type":"Point"}
}