{
  "type": "Feature",
  "properties": {
    "addr:full":"Calle de Beato Tomas De Zumarraga, 66 Vitoria-gasteiz \u00c1lava 01009",
    "addr:housenumber":"66",
    "addr:postcode":"01009",
    "addr:street":"Calle De Beato Tomas De Zumarraga",
    "iso:country":"ES",
    "sg:address":"Calle de Beato Tomas De Zumarraga, 66",
    "sg:city":"Vitoria-gasteiz",
    "sg:orig_category":"Automatizaci\u00d3n De Procesos Industriales Y De Edificaci\u00d3n (estudios, Instalaci\u00d3n)",
    "sg:phone":"+34 945 24 16 33",
    "sg:postcode":"01009",
    "sg:province":"\u00c1lava",
    "sg:website":"www.igoan.com",
    "wof:name":"Igoan S.l.",
    "wof:placetype":"venue"
},
  "geometry": {"coordinates":[-2.6851181984,42.8507232666],"type":"Point"}
}