{
  "type": "Feature",
  "properties": {
    "addr:full":"Calle de San Basilio, 19 Madrid Madrid 28026",
    "addr:housenumber":"19",
    "addr:postcode":"madrid;28026",
    "addr:street":"Calle De San",
    "iso:country":"ES",
    "sg:address":"Calle de San Basilio, 19",
    "sg:city":"Madrid",
    "sg:orig_category":"Internados & Ense\u00d1anza Privada",
    "sg:phone":"+34 914 75 23 92",
    "sg:postcode":"28026",
    "sg:province":"Madrid",
    "wof:name":"Religiosas Angeles Custodios",
    "wof:placetype":"venue"
},
  "geometry": {"coordinates":[-3.7078056335,40.3798828125],"type":"Point"}
}