{
  "type": "Feature",
  "properties": {
    "iso:country":"ES",
    "sg:address":"Carrer de Villarroel, 115",
    "sg:city":"Barcelona",
    "sg:orig_category":"Mayoristas E Intermediarios En Alcoholes",
    "sg:phone":"+34 934 51 62 92",
    "sg:postcode":"08011",
    "sg:province":"Barcelona",
    "wof:name":"Bodegas Gonzalez Byass S.a.",
    "wof:placetype":"venue"
},
  "geometry": {"coordinates":[2.1562271118,41.3854370117],"type":"Point"}
}