{
  "type": "Feature",
  "properties": {
    "iso:country":"ES",
    "sg:address":"Calle de Palmas (las), 13",
    "sg:city":"Palencia",
    "sg:orig_category":"Cervezas, Bebidas (al Por Mayor)",
    "sg:phone":"+34 979 17 05 22",
    "sg:postcode":"34003",
    "sg:province":"Palencia",
    "wof:name":"Villamarte S.l.",
    "wof:placetype":"venue"
},
  "geometry": {"coordinates":[-4.533302784,42.0245780945],"type":"Point"}
}