{
  "type": "Feature",
  "properties": {
    "iso:country":"ES",
    "sg:address":"Barr El Cerro, 7",
    "sg:city":"San Juan De Muskiz",
    "sg:orig_category":"Clubes Y Asociaciones Deportivas Y De Actividades Invernales Y De Monta\u00d1a",
    "sg:phone":"+34 946 70 64 60",
    "sg:postcode":"48550",
    "sg:province":"Vizcaya",
    "sg:website":"www.euskalnet.net/fuen",
    "wof:name":"Club Mendis Mendi",
    "wof:placetype":"venue"
},
  "geometry": {"coordinates":[-3.1228249073,43.3224563599],"type":"Point"}
}