{
  "type": "Feature",
  "properties": {
    "iso:country":"ES",
    "sg:address":"Calle de San Antonio, 6",
    "sg:city":"Vadillo De La Guare\u00e7a",
    "sg:orig_category":"Electricidad: Instaladores",
    "sg:phone":"+34 980 60 71 50",
    "sg:postcode":"49420",
    "sg:province":"Zamora",
    "wof:name":"Garcia Calderon Juan Jose",
    "wof:placetype":"venue"
},
  "geometry": {"coordinates":[-5.354683876,41.2795333862],"type":"Point"}
}