{
  "type": "Feature",
  "properties": {
    "iso:country":"ES",
    "sg:address":"Calle de Enmedio, 29",
    "sg:city":"Torrejon Ardoz",
    "sg:orig_category":"Ropa Para Beb\u00c9s Y Ni\u00d1os (confecci\u00d3n, Al Por Mayor)",
    "sg:phone":"+34 916 76 67 13",
    "sg:postcode":"28850",
    "sg:province":"Madrid",
    "wof:name":"Dong  Fanping",
    "wof:placetype":"venue"
},
  "geometry": {"coordinates":[-3.4787900448,40.4566764832],"type":"Point"}
}