{
  "type": "Feature",
  "properties": {
    "addr:full":"Calle de Almazan, 34 Madrid Madrid 28011",
    "addr:housenumber":"34",
    "addr:postcode":"madrid;28011",
    "addr:street":"Calle De Almazan",
    "iso:country":"ES",
    "sg:address":"Calle de Almazan, 34",
    "sg:city":"Madrid",
    "sg:orig_category":"Doctores En Medicina",
    "sg:phone":"+34 914 63 19 29",
    "sg:postcode":"28011",
    "sg:province":"Madrid",
    "wof:name":"Dominguez Moreno Bruno",
    "wof:placetype":"venue"
},
  "geometry": {"coordinates":[-3.7460186481,40.4056968689],"type":"Point"}
}