{
  "type": "Feature",
  "properties": {
    "iso:country":"ES",
    "sg:address":"Avda Cesar Augusto, 51",
    "sg:city":"Zaragoza",
    "sg:orig_category":"Confecci\u00d3n (fabricaci\u00d3n, Al Por Mayor)",
    "sg:phone":"+34 976 43 84 42",
    "sg:postcode":"50003",
    "sg:province":"Zaragoza",
    "wof:name":"Royo Merigo Manuel Fernando",
    "wof:placetype":"venue"
},
  "geometry": {"coordinates":[-0.8842290044,41.6551322937],"type":"Point"}
}