{
  "type": "Feature",
  "properties": {
    "addr:full":"Calle de Federico Garcia Lorca, 10 Balazote Albacete 02320",
    "addr:housenumber":"10",
    "addr:postcode":"02320",
    "addr:street":"Calle De Federico Garcia Lorca",
    "iso:country":"ES",
    "sg:address":"Calle de Federico Garcia Lorca, 10",
    "sg:city":"Balazote",
    "sg:orig_category":"Confecci\u00d3n (fabricaci\u00d3n, Al Por Mayor)",
    "sg:phone":"+34 967 36 01 20",
    "sg:postcode":"02320",
    "sg:province":"Albacete",
    "wof:name":"Confecciones Bicha S.l.",
    "wof:placetype":"venue"
},
  "geometry": {"coordinates":[-2.1537699699,38.8848724365],"type":"Point"}
}