{
  "type": "Feature",
  "properties": {
    "iso:country":"ES",
    "sg:address":"Calle de Rafael Chaparro, 34",
    "sg:city":"Arroyo Luz",
    "sg:orig_category":"Muebles, Minoristas",
    "sg:phone":"+34 927 27 00 64",
    "sg:postcode":"10900",
    "sg:province":"C\u00e1ceres",
    "wof:name":"Rodriguez Dominguez Francisco Javier",
    "wof:placetype":"venue"
},
  "geometry": {"coordinates":[-6.5832881927,39.4836502075],"type":"Point"}
}