{
  "type": "Feature",
  "properties": {
    "iso:country":"ES",
    "sg:address":"Calle de Flor, 1",
    "sg:city":"Mora",
    "sg:orig_category":"Plomeros",
    "sg:phone":"+34 925 30 05 06",
    "sg:postcode":"45400",
    "sg:province":"Toledo",
    "wof:name":"Villarrubia Navarro Roman",
    "wof:placetype":"venue"
},
  "geometry": {"coordinates":[-3.7752130032,39.6814880371],"type":"Point"}
}