{
  "type": "Feature",
  "properties": {
    "iso:country":"ES",
    "sg:address":"Carr Balmes, 2",
    "sg:city":"Palau D'anglesola",
    "sg:orig_category":"Mec\u00c1nico Del Autom\u00d3vil",
    "sg:phone":"+34 973 60 14 67",
    "sg:postcode":"25243",
    "sg:province":"Lleida",
    "wof:name":"Rames Gomez Ramon",
    "wof:placetype":"venue"
},
  "geometry": {"coordinates":[1.0831910372,41.6584892273],"type":"Point"}
}