{
  "type": "Feature",
  "properties": {
    "iso:country":"ES",
    "sg:address":"Pase Conferencia, 13",
    "sg:city":"Algeciras",
    "sg:orig_category":"Organizaciones Profesionales",
    "sg:phone":"+34 956 57 04 20",
    "sg:postcode":"11207",
    "sg:province":"C\u00e1diz",
    "wof:name":"Transbull Cadiz S.l.",
    "wof:placetype":"venue"
},
  "geometry": {"coordinates":[-5.4431581497,36.1253318787],"type":"Point"}
}