{
  "type": "Feature",
  "properties": {
    "iso:country":"ES",
    "sg:address":"Calle de San Luis, 40",
    "sg:city":"Castellon",
    "sg:orig_category":"Venta, Alquiler De Instrumentos Y Accesorios De M\u00dasica",
    "sg:phone":"+34 964 23 13 21",
    "sg:postcode":"12001",
    "sg:province":"Castell\u00f3n",
    "wof:name":"Portoles Canales Vicente",
    "wof:placetype":"venue"
},
  "geometry": {"coordinates":[-0.0358639993,39.9883766174],"type":"Point"}
}