{
  "type": "Feature",
  "properties": {
    "iso:country":"ES",
    "sg:address":"Polig. Ind. A Granxa, S/n",
    "sg:city":"Porri\u00f1o",
    "sg:orig_category":"Pr\u00c1ctica Del Submarinismo Y De Deportes Y Actividades Subacu\u00c1ticos",
    "sg:phone":"+34 986 34 25 59",
    "sg:postcode":"36475",
    "sg:province":"Pontevedra",
    "wof:name":"Emprogal S.l.",
    "wof:placetype":"venue"
},
  "geometry": {"coordinates":[-8.606926918,42.1053466797],"type":"Point"}
}