{
  "type": "Feature",
  "properties": {
    "addr:full":"Calle de Siete Picos (de Los), 9 Navalcarnero Madrid 28600",
    "addr:housenumber":"9",
    "addr:postcode":"28600",
    "addr:street":"Calle De Siete Picos De Los",
    "iso:country":"ES",
    "sg:address":"Calle de Siete Picos (de Los), 9",
    "sg:city":"Navalcarnero",
    "sg:orig_category":"Ense\u00d1anza: Comercio, Gesti\u00d3n, Inform\u00c1tica",
    "sg:phone":"+34 918 11 11 11",
    "sg:postcode":"28600",
    "sg:province":"Madrid",
    "wof:name":"Calvo Paredes Francisca",
    "wof:placetype":"venue"
},
  "geometry": {"coordinates":[-4.0282998085,40.2814292908],"type":"Point"}
}