{
  "type": "Feature",
  "properties": {
    "iso:country":"ES",
    "sg:address":"Calle de Huertas (de Las), 4",
    "sg:city":"Villanueva Pardillo",
    "sg:orig_category":"Ortopedia General",
    "sg:phone":"+34 918 15 28 33",
    "sg:postcode":"28229",
    "sg:province":"Madrid",
    "wof:name":"Accesos Generales S.l.",
    "wof:placetype":"venue"
},
  "geometry": {"coordinates":[-3.9634108543,40.4879760742],"type":"Point"}
}