{
  "type": "Feature",
  "properties": {
    "addr:full":"Avda Carlos V, 81 Carrizal Las Palmas 35240",
    "addr:housenumber":"81",
    "addr:postcode":"35240",
    "addr:street":"Avda Carlos V",
    "iso:country":"ES",
    "sg:address":"Avda Carlos V, 81",
    "sg:city":"Carrizal",
    "sg:orig_category":"Muebles, Minoristas",
    "sg:phone":"+34 928 12 49 37",
    "sg:postcode":"35240",
    "sg:province":"Las Palmas",
    "wof:name":"Muebles Corymac S.l.",
    "wof:placetype":"venue"
},
  "geometry": {"coordinates":[-15.4036588669,27.9124660492],"type":"Point"}
}