{
  "type": "Feature",
  "properties": {
    "iso:country":"ES",
    "sg:address":"Carrer de Noi Del Sucre, 61",
    "sg:city":"Viladecans",
    "sg:orig_category":"Trajes Y Adornos De Boda (confecci\u00d3n, Al Por Menor)",
    "sg:phone":"+34 936 58 33 97",
    "sg:postcode":"08840",
    "sg:province":"Barcelona",
    "sg:website":"www.jesuspeiro.com",
    "wof:name":"Intersposa S.a.",
    "wof:placetype":"venue"
},
  "geometry": {"coordinates":[2.0227000713,41.309261322],"type":"Point"}
}