{
  "type": "Feature",
  "properties": {
    "addr:full":"L'exportacio, 3 Alquerias Ni\u00f1o Perdido Castell\u00f3n 12539",
    "addr:housenumber":"3",
    "addr:postcode":"12539",
    "addr:street":"L'Exportacio;Castello\u0301N",
    "iso:country":"ES",
    "sg:address":"L'exportacio, 3",
    "sg:city":"Alquerias Ni\u00f1o Perdido",
    "sg:orig_category":"Arboricultura Y Producci\u00d3n De Frutas",
    "sg:phone":"+34 964 59 14 11",
    "sg:postcode":"12539",
    "sg:province":"Castell\u00f3n",
    "wof:name":"Vilodi S.l.",
    "wof:placetype":"venue"
},
  "geometry": {"coordinates":[-0.0456800014,39.9851417542],"type":"Point"}
}