{
  "type": "Feature",
  "properties": {
    "iso:country":"ES",
    "sg:address":"Malaga, 10",
    "sg:city":"Pilar Horadada",
    "sg:orig_category":"Limpieza Industrial",
    "sg:phone":"+34 966 76 63 08",
    "sg:postcode":"03190",
    "sg:province":"Alicante",
    "wof:name":"Alcaraz Valverde Laura",
    "wof:placetype":"venue"
},
  "geometry": {"coordinates":[-0.7923232913,37.8705596924],"type":"Point"}
}