{
  "type": "Feature",
  "properties": {
    "iso:country":"ES",
    "sg:address":"Pase Rollo, 96",
    "sg:city":"Salamanca",
    "sg:orig_category":"Alimentaci\u00d3n General (al Por Menor)",
    "sg:phone":"+34 923 18 63 68",
    "sg:postcode":"37003",
    "sg:province":"Salamanca",
    "wof:name":"Ni\u00d1o Alonso C.b.",
    "wof:placetype":"venue"
},
  "geometry": {"coordinates":[-5.6477241516,40.9681243896],"type":"Point"}
}