{
  "type": "Feature",
  "properties": {
    "addr:full":"Calle de Cristo De La Epidemia, 84 Malaga M\u00e1laga 29013",
    "addr:housenumber":"84",
    "addr:postcode":"29013",
    "addr:street":"Calle De Cristo De La Epidemia;Ma\u0301Laga",
    "iso:country":"ES",
    "sg:address":"Calle de Cristo De La Epidemia, 84",
    "sg:city":"Malaga",
    "sg:orig_category":"Peluqueros: De Se\u00d1oras",
    "sg:phone":"+34 952 65 01 00",
    "sg:postcode":"29013",
    "sg:province":"M\u00e1laga",
    "wof:name":"Isabel Herrera Gonzalez S.l.",
    "wof:placetype":"venue"
},
  "geometry": {"coordinates":[-4.4153108597,36.7318458557],"type":"Point"}
}