{
  "type": "Feature",
  "properties": {
    "iso:country":"ES",
    "sg:address":"Calle de Castelao, 44",
    "sg:city":"Malaga",
    "sg:orig_category":"Centros De Coordinaci\u00d3n",
    "sg:phone":"+34 952 23 65 62",
    "sg:postcode":"29004",
    "sg:province":"M\u00e1laga",
    "wof:name":"Harras Polonio Arturo",
    "wof:placetype":"venue"
},
  "geometry": {"coordinates":[-4.484210968,36.6949653625],"type":"Point"}
}