{
  "type": "Feature",
  "properties": {
    "iso:country":"ES",
    "sg:address":"Plaz Ayuntamiento, 1",
    "sg:city":"Alacant",
    "sg:orig_category":"Agencias De Aduana",
    "sg:phone":"+34 965 21 72 84",
    "sg:postcode":"03002",
    "sg:province":"Alicante",
    "wof:name":"Trujillo Merida Jose Manuel",
    "wof:placetype":"venue"
},
  "geometry": {"coordinates":[-0.4812180102,38.3453025818],"type":"Point"}
}