{
  "type": "Feature",
  "properties": {
    "iso:country":"ES",
    "sg:address":"Calle de Escorial (el), S/n",
    "sg:city":"Alcala Henares",
    "sg:orig_category":"Rectificaci\u00d3n, Mecanizado, Fresado",
    "sg:phone":"+34 918 83 26 28",
    "sg:postcode":"28805",
    "sg:province":"Madrid",
    "wof:name":"Imecal S.a.l.",
    "wof:placetype":"venue"
},
  "geometry": {"coordinates":[-3.3489470482,40.4934768677],"type":"Point"}
}