{
  "type": "Feature",
  "properties": {
    "iso:country":"ES",
    "sg:address":"Carr Enric Borras, 61",
    "sg:city":"Badalona",
    "sg:orig_category":"Azafatas De Vuelo",
    "sg:phone":"+34 933 84 58 74",
    "sg:postcode":"08912",
    "sg:province":"Barcelona",
    "wof:name":"Eadi Escola Empresarial D'idiomes I Gestio S.l.",
    "wof:placetype":"venue"
},
  "geometry": {"coordinates":[2.2453770638,41.4455757141],"type":"Point"}
}