{
  "type": "Feature",
  "properties": {
    "iso:country":"ES",
    "sg:address":"Av Puig I Cadafalch, 169",
    "sg:city":"Mataro",
    "sg:orig_category":"Marroquiner\u00cda Y Art\u00cdculos De Viaje (al Por Menor)",
    "sg:phone":"+34 937 98 36 46",
    "sg:postcode":"08303",
    "sg:province":"Barcelona",
    "wof:name":"Darbra S.l.",
    "wof:placetype":"venue"
},
  "geometry": {"coordinates":[2.4253480434,41.5402069092],"type":"Point"}
}