{
  "type": "Feature",
  "properties": {
    "addr:full":"Via Marconi (de), 27 Boisaca La Coru\u00f1a 15890",
    "addr:housenumber":"27",
    "addr:postcode":"15890",
    "addr:street":"Via Marconi De;La Corun\u0303A",
    "iso:country":"ES",
    "sg:address":"Via Marconi (de), 27",
    "sg:city":"Boisaca",
    "sg:orig_category":"Molduras, Junquillos, Listones Y Molduras Perforadas",
    "sg:phone":"+34 981 58 66 89",
    "sg:postcode":"15890",
    "sg:province":"La Coru\u00f1a",
    "wof:name":"Mosteiro Gomez Jose",
    "wof:placetype":"venue"
},
  "geometry": {"coordinates":[-8.4769210815,42.8835983276],"type":"Point"}
}