{
  "type": "Feature",
  "properties": {
    "addr:full":"Calle de Rufo, 15 Begijar Ja\u00e9n 23520",
    "addr:housenumber":"15",
    "addr:postcode":"23520",
    "addr:street":"Calle De Rufo;Jae\u0301N",
    "iso:country":"ES",
    "sg:address":"Calle de Rufo, 15",
    "sg:city":"Begijar",
    "sg:orig_category":"Perfumer\u00cda (al Por Menor)",
    "sg:phone":"+34 953 76 30 77",
    "sg:postcode":"23520",
    "sg:province":"Ja\u00e9n",
    "wof:name":"Soto Garcia Andres",
    "wof:placetype":"venue"
},
  "geometry": {"coordinates":[-3.5331680775,37.9849472046],"type":"Point"}
}