{
  "type": "Feature",
  "properties": {
    "addr:full":"Calle de Teniente Coronel Chapuli, 2 Alacant Alicante 03001",
    "addr:housenumber":"2",
    "addr:postcode":"03001",
    "addr:street":"Calle De Teniente Coronel Chapuli",
    "iso:country":"ES",
    "sg:address":"Calle de Teniente Coronel Chapuli, 2",
    "sg:city":"Alacant",
    "sg:orig_category":"Organismos De Turismo",
    "sg:phone":"+34 965 14 67 71",
    "sg:postcode":"03001",
    "sg:province":"Alicante",
    "sg:website":"www.alicanteturismo.com",
    "wof:name":"Ajuntament D'alacant",
    "wof:placetype":"venue"
},
  "geometry": {"coordinates":[-0.4839734137,38.3449172974],"type":"Point"}
}