{
  "type": "Feature",
  "properties": {
    "iso:country":"ES",
    "sg:address":"Calle de Martinez Campos, 5",
    "sg:city":"Malaga",
    "sg:orig_category":"Psic\u00d3logos",
    "sg:phone":"+34 952 22 90 20",
    "sg:postcode":"29001",
    "sg:province":"M\u00e1laga",
    "wof:name":"Lopez Ortega Ana Silvia",
    "wof:placetype":"venue"
},
  "geometry": {"coordinates":[-4.4225077629,36.715511322],"type":"Point"}
}