{
  "type": "Feature",
  "properties": {
    "addr:full":"Calle de Cuartel, S/n Barca De La Florida C\u00e1diz 11570",
    "addr:housenumber":"s / n",
    "addr:postcode":"11570",
    "addr:street":"Calle De Cuartel;Ca\u0301Diz",
    "iso:country":"ES",
    "sg:address":"Calle de Cuartel, S/n",
    "sg:city":"Barca De La Florida",
    "sg:orig_category":"Supermercados Y Hipermercados",
    "sg:phone":"+34 956 16 34 25",
    "sg:postcode":"11570",
    "sg:province":"C\u00e1diz",
    "wof:name":"United Services S.l.",
    "wof:placetype":"venue"
},
  "geometry": {"coordinates":[-5.9319238663,36.6499900818],"type":"Point"}
}