{
  "type": "Feature",
  "properties": {
    "iso:country":"ES",
    "sg:address":"Carr Alcudia, 16",
    "sg:city":"Pollen\u00e7a",
    "sg:orig_category":"Fabricaci\u00d3n, Venta De Productos Base Farmac\u00c9uticos",
    "sg:phone":"+34 971 53 00 63",
    "sg:postcode":"07460",
    "sg:province":"Islas Baleares",
    "wof:name":"Oliver Bisbal Miguel",
    "wof:placetype":"venue"
},
  "geometry": {"coordinates":[3.0059130192,39.8700141907],"type":"Point"}
}