{
  "type": "Feature",
  "properties": {
    "iso:country":"ES",
    "sg:address":"C/ Lleo Xiii, 7",
    "sg:city":"Manacor",
    "sg:orig_category":"Perfumer\u00cda (al Por Menor)",
    "sg:phone":"+34 971 55 10 97",
    "sg:postcode":"07500",
    "sg:province":"Islas Baleares",
    "wof:name":"Perfumeria Eden S.a.",
    "wof:placetype":"venue"
},
  "geometry": {"coordinates":[3.2054460049,39.571182251],"type":"Point"}
}