{
  "type": "Feature",
  "properties": {
    "iso:country":"ES",
    "sg:address":"Ctra Valencia-ademuz, Km. 0030,0",
    "sg:city":"Lliria",
    "sg:orig_category":"Ingenier\u00cda, Centros De Estudios (diversos)",
    "sg:phone":"+34 962 79 80 32",
    "sg:postcode":"46160",
    "sg:province":"Valencia",
    "wof:name":"3 Cip Plastic S.l.",
    "wof:placetype":"venue"
},
  "geometry": {"coordinates":[-0.586141,39.620533],"type":"Point"}
}