{
  "type": "Feature",
  "properties": {
    "iso:country":"ES",
    "sg:address":"Calle de Estrella (la), 1",
    "sg:city":"Lucena",
    "sg:orig_category":"Molduras, Junquillos, Listones Y Molduras Perforadas",
    "sg:phone":"+34 957 59 08 92",
    "sg:postcode":"14900",
    "sg:province":"C\u00f3rdoba",
    "wof:name":"Montes Vinuesa Antonio",
    "wof:placetype":"venue"
},
  "geometry": {"coordinates":[-4.4855690002,37.413898468],"type":"Point"}
}