{
  "type": "Feature",
  "properties": {
    "iso:country":"ES",
    "sg:address":"Plaz Cine (del), 1",
    "sg:city":"Villanueva Mesia",
    "sg:orig_category":"Farmacias",
    "sg:phone":"+34 958 44 42 86",
    "sg:postcode":"18369",
    "sg:province":"Granada",
    "wof:name":"Guzman Fortis Maria Soledad",
    "wof:placetype":"venue"
},
  "geometry": {"coordinates":[-4.011428833,37.2145957947],"type":"Point"}
}