{
  "type": "Feature",
  "properties": {
    "iso:country":"ES",
    "sg:address":"Calle de Santa Maria, 15",
    "sg:city":"Madrid",
    "sg:classifiers":[
        {
            "category":"Arts & Performance",
            "subcategory":"Art Gallery",
            "type":"Entertainment"
        }
    ],
    "sg:phone":"+34 913 69 35 80",
    "sg:postcode":"28014",
    "sg:province":"Madrid",
    "sg:tags":[
        "arte",
        "de",
        "galer\u00cdas"
    ],
    "wof:name":"Gonzalez-calero Gonzalez Luis Alfonso",
    "wof:placetype":"venue"
},
  "geometry": {"coordinates":[-3.6975259781,40.4130783081],"type":"Point"}
}