{
  "type": "Feature",
  "properties": {
    "iso:country":"ES",
    "sg:address":"Calle de Real De Burgos, 11",
    "sg:city":"Valladolid",
    "sg:orig_category":"Caf\u00c9s, Bares, Cervecer\u00cdas",
    "sg:phone":"+34 983 26 20 52",
    "sg:postcode":"47011",
    "sg:province":"Valladolid",
    "wof:name":"Perez Alonso Mari Cruz",
    "wof:placetype":"venue"
},
  "geometry": {"coordinates":[-4.7189207077,41.6585731506],"type":"Point"}
}