{
  "type": "Feature",
  "properties": {
    "addr:full":"Avda Libertad De La, 18 Donostia-san Sebastian Guip\u00f9zcoa 20004",
    "addr:housenumber":"18",
    "addr:postcode":"20004",
    "addr:street":"Avda Libertad De La",
    "iso:country":"ES",
    "sg:address":"Avda Libertad De La, 18",
    "sg:city":"Donostia-san Sebastian",
    "sg:orig_category":"M\u00c9dicos: Estomatolog\u00cda",
    "sg:phone":"+34 943 43 10 39",
    "sg:postcode":"20004",
    "sg:province":"Guip\u00f9zcoa",
    "wof:name":"Andonegui Unanue Agustin",
    "wof:placetype":"venue"
},
  "geometry": {"coordinates":[-1.981418252,43.3198852539],"type":"Point"}
}