{
  "type": "Feature",
  "properties": {
    "iso:country":"ES",
    "sg:address":"Calle de Victor Romanos, 2",
    "sg:city":"Fuenmayor",
    "sg:orig_category":"Escayola Y Productos De Escayola (fabricaci\u00d3n, Al Por Mayor)",
    "sg:phone":"+34 941 45 01 21",
    "sg:postcode":"26360",
    "sg:province":"La Rioja",
    "wof:name":"Barroso Pereira Jose",
    "wof:placetype":"venue"
},
  "geometry": {"coordinates":[-2.5612881184,42.4660301208],"type":"Point"}
}