{
  "type": "Feature",
  "properties": {
    "iso:country":"ES",
    "sg:address":"Merce, 45",
    "sg:city":"Almacelles",
    "sg:orig_category":"Promotores Constructores",
    "sg:phone":"+34 973 74 12 97",
    "sg:postcode":"25100",
    "sg:province":"Lleida",
    "wof:name":"Ambau Esteve Mateu",
    "wof:placetype":"venue"
},
  "geometry": {"coordinates":[0.4596720934,41.7298660278],"type":"Point"}
}