{
  "type": "Feature",
  "properties": {
    "addr:full":"Rua Laureano Pelaez, 39 Verin Ourense 32600",
    "addr:housenumber":"39",
    "addr:postcode":"32600",
    "addr:street":"Laureano Pelaez",
    "iso:country":"ES",
    "sg:address":"Rua Laureano Pelaez, 39",
    "sg:city":"Verin",
    "sg:orig_category":"Farmacias",
    "sg:phone":"+34 988 41 17 06",
    "sg:postcode":"32600",
    "sg:province":"Ourense",
    "wof:name":"Cid Fernandez Maria Concepcion",
    "wof:placetype":"venue"
},
  "geometry": {"coordinates":[-7.4366130829,41.9390792847],"type":"Point"}
}