{
  "type": "Feature",
  "properties": {
    "iso:country":"ES",
    "sg:address":"Ctra Berga, Km. 0004,0",
    "sg:city":"S. Fruitos Bages",
    "sg:orig_category":"Fabricaci\u00d3n De Motores El\u00c9ctricos",
    "sg:phone":"+34 938 78 60 12",
    "sg:postcode":"08272",
    "sg:province":"Barcelona",
    "wof:name":"Electromotores Pact S.l.",
    "wof:placetype":"venue"
},
  "geometry": {"coordinates":[1.8779350519,41.7520599365],"type":"Point"}
}