{
  "type": "Feature",
  "properties": {
    "iso:country":"ES",
    "sg:address":"Urb Planicia, 59",
    "sg:city":"El Altet",
    "sg:orig_category":"Panader\u00cdas, Panader\u00cdas",
    "sg:phone":"+34 965 68 77 56",
    "sg:postcode":"03195",
    "sg:province":"Alicante",
    "wof:name":"Tahona De Fernando S.l.",
    "wof:placetype":"venue"
},
  "geometry": {"coordinates":[-0.5206289887,38.2537002563],"type":"Point"}
}