{
  "type": "Feature",
  "properties": {
    "iso:country":"ES",
    "sg:address":"Calle de Obispo Ceballos, 4",
    "sg:city":"Alcala Real",
    "sg:orig_category":"Muebles, Minoristas",
    "sg:phone":"+34 953 58 29 16",
    "sg:postcode":"23680",
    "sg:province":"Ja\u00e9n",
    "wof:name":"Jose Antonio Perez Hinjojosa",
    "wof:placetype":"venue"
},
  "geometry": {"coordinates":[-3.9223210812,37.4616508484],"type":"Point"}
}