{
  "type": "Feature",
  "properties": {
    "iso:country":"ES",
    "sg:address":"Calle de Libertad (de La), 54",
    "sg:city":"Navalcarnero",
    "sg:orig_category":"Material Y Suministros Para Peluquer\u00cda",
    "sg:phone":"+34 918 11 31 21",
    "sg:postcode":"28600",
    "sg:province":"Madrid",
    "wof:name":"Rodriguez Ruiz Manuela",
    "wof:placetype":"venue"
},
  "geometry": {"coordinates":[-4.0129790306,40.2900657654],"type":"Point"}
}