{
  "type": "Feature",
  "properties": {
    "addr:full":"Av Caldes De Montbui, 52 Mollet Valles Barcelona 08100",
    "addr:housenumber":"52",
    "addr:postcode":"08100",
    "addr:street":"Av Caldes De Montbui",
    "iso:country":"ES",
    "sg:address":"Av Caldes De Montbui, 52",
    "sg:city":"Mollet Valles",
    "sg:orig_category":"Institutos De Belleza",
    "sg:phone":"+34 935 70 59 29",
    "sg:postcode":"08100",
    "sg:province":"Barcelona",
    "wof:name":"Calzado Contreras Maria Mercedes",
    "wof:placetype":"venue"
},
  "geometry": {"coordinates":[2.2060339451,41.5456581116],"type":"Point"}
}