{
  "type": "Feature",
  "properties": {
    "addr:full":"Calle de Pintor Palomino, 14 Cordoba C\u00f3rdoba 14006",
    "addr:housenumber":"14",
    "addr:postcode":"14006",
    "addr:street":"Calle De Pintor Palomino;Co\u0301Rdoba",
    "iso:country":"ES",
    "sg:address":"Calle de Pintor Palomino, 14",
    "sg:city":"Cordoba",
    "sg:orig_category":"Confecci\u00d3n De Trajes Para Se\u00d1oras",
    "sg:phone":"+34 957 27 82 01",
    "sg:postcode":"14006",
    "sg:province":"C\u00f3rdoba",
    "wof:name":"Morales Gonzalez Francisca",
    "wof:placetype":"venue"
},
  "geometry": {"coordinates":[-4.7851600647,37.8948326111],"type":"Point"}
}