{
  "type": "Feature",
  "properties": {
    "addr:full":"Calle de Independencia (de La), 7 Mostoles Madrid 28931",
    "addr:postcode":"28931",
    "addr:street":"Calle De Independencia De La 7 Mostoles",
    "iso:country":"ES",
    "sg:address":"Calle de Independencia (de La), 7",
    "sg:city":"Mostoles",
    "sg:orig_category":"Trajes Y Adornos De Boda (confecci\u00d3n, Al Por Menor)",
    "sg:phone":"+34 916 64 32 05",
    "sg:postcode":"28931",
    "sg:province":"Madrid",
    "wof:name":"Carmen Sanpe Novias Sll",
    "wof:placetype":"venue"
},
  "geometry": {"coordinates":[-3.8626000881,40.3229789734],"type":"Point"}
}