{
  "type": "Feature",
  "properties": {
    "iso:country":"ES",
    "sg:address":"Calle de Flecha Bermudez, 2",
    "sg:city":"Ceuta",
    "sg:orig_category":"Molduras, Junquillos, Listones Y Molduras Perforadas",
    "sg:phone":"+34 956 52 17 92",
    "sg:postcode":"51002",
    "sg:province":"Ceuta",
    "wof:name":"Moreno Lopez Matias",
    "wof:placetype":"venue"
},
  "geometry": {"coordinates":[-5.3272738457,35.8836402893],"type":"Point"}
}