{
  "type": "Feature",
  "properties": {
    "iso:country":"ES",
    "sg:address":"Avda Retamas (las), 6",
    "sg:city":"Alcorcon",
    "sg:orig_category":"Loter\u00cda Y T\u00d3mbola",
    "sg:phone":"+34 914 86 05 19",
    "sg:postcode":"28922",
    "sg:province":"Madrid",
    "wof:name":"Revilla Estebaranz Ana Maria",
    "wof:placetype":"venue"
},
  "geometry": {"coordinates":[-3.8369760513,40.3394088745],"type":"Point"}
}