{
  "type": "Feature",
  "properties": {
    "iso:country":"ES",
    "sg:address":"C/ Ciutat D'elda, 27",
    "sg:city":"Paterna",
    "sg:orig_category":"Bisuter\u00cda, Joyer\u00cda, Relojer\u00cda (al Por Menor)",
    "sg:phone":"+34 961 34 30 87",
    "sg:postcode":"46988",
    "sg:province":"Valencia",
    "sg:website":"www.siljova.es",
    "wof:name":"Jesus Higueras S.l.",
    "wof:placetype":"venue"
},
  "geometry": {"coordinates":[-0.4408999979,39.5301818848],"type":"Point"}
}