{
  "type": "Feature",
  "properties": {
    "addr:full":"Carrer de Puig Del Ravell, 14 Martorell Barcelona 08760",
    "addr:housenumber":"14",
    "addr:postcode":"08760",
    "addr:street":"Carrer De Puig Del Ravell",
    "iso:country":"ES",
    "sg:address":"Carrer de Puig Del Ravell, 14",
    "sg:city":"Martorell",
    "sg:orig_category":"Molduras, Junquillos, Listones Y Molduras Perforadas",
    "sg:phone":"+34 937 75 03 06",
    "sg:postcode":"08760",
    "sg:province":"Barcelona",
    "wof:name":"Baumatel S.l. L.",
    "wof:placetype":"venue"
},
  "geometry": {"coordinates":[1.9134720564,41.4781494141],"type":"Point"}
}