{
  "type": "Feature",
  "properties": {
    "iso:country":"ES",
    "sg:address":"Calle de Blas Otero, S/n",
    "sg:city":"Algeciras",
    "sg:orig_category":"Farmacias",
    "sg:phone":"+34 956 66 98 08",
    "sg:postcode":"11204",
    "sg:province":"C\u00e1diz",
    "wof:name":"Rodriguez-armijo Guerrero Diego Jose",
    "wof:placetype":"venue"
},
  "geometry": {"coordinates":[-5.4634723663,36.1395721436],"type":"Point"}
}