{
  "type": "Feature",
  "properties": {
    "iso:country":"ES",
    "sg:address":"Calle de Juan De La Encina, 8",
    "sg:city":"Almeria",
    "sg:orig_category":"Promotores Constructores",
    "sg:phone":"+34 950 24 00 55",
    "sg:postcode":"04006",
    "sg:province":"Almer\u00eda",
    "wof:name":"Gm Station S.l.",
    "wof:placetype":"venue"
},
  "geometry": {"coordinates":[-2.4482769966,36.8391838074],"type":"Point"}
}