{
  "type": "Feature",
  "properties": {
    "addr:full":"Calle de General Ricardos, 190 Madrid Madrid 28025",
    "addr:housenumber":"190",
    "addr:postcode":"28025",
    "addr:street":"Calle De General Ricardos",
    "iso:country":"ES",
    "sg:address":"Calle de General Ricardos, 190",
    "sg:city":"Madrid",
    "sg:orig_category":"Grabados",
    "sg:phone":"+34 914 61 91 56",
    "sg:postcode":"28025",
    "sg:province":"Madrid",
    "wof:name":"Galdon Gonzalez Manuel",
    "wof:placetype":"venue"
},
  "geometry": {"coordinates":[-3.7355811596,40.3859481812],"type":"Point"}
}