{
  "type": "Feature",
  "properties": {
    "addr:full":"Calle de Monta\u00d1es, 2 Salamanca Salamanca 37007",
    "addr:housenumber":"2",
    "addr:postcode":"37007",
    "addr:street":"Calle De Montan\u0303Es",
    "iso:country":"ES",
    "sg:address":"Calle de Monta\u00d1es, 2",
    "sg:city":"Salamanca",
    "sg:orig_category":"Platos Preparados Refrigerados (fabricaci\u00d3n, Al Por Mayor)",
    "sg:phone":"+34 923 27 18 07",
    "sg:postcode":"37007",
    "sg:province":"Salamanca",
    "wof:name":"Cocinados Rosbif C.b.",
    "wof:placetype":"venue"
},
  "geometry": {"coordinates":[-5.663848877,40.964225769],"type":"Point"}
}