{
  "type": "Feature",
  "properties": {
    "iso:country":"ES",
    "sg:address":"Carrer de Roselles, 12",
    "sg:city":"Santa Coloma De Gramenet",
    "sg:orig_category":"Molduras, Junquillos, Listones Y Molduras Perforadas",
    "sg:phone":"+34 934 66 06 39",
    "sg:postcode":"08923",
    "sg:province":"Barcelona",
    "wof:name":"Tomas Bonilla Manuel",
    "wof:placetype":"venue"
},
  "geometry": {"coordinates":[2.2125198841,41.4475708008],"type":"Point"}
}