{
  "type": "Feature",
  "properties": {
    "iso:country":"ES",
    "sg:address":"Carr Llevant, 1",
    "sg:city":"Casc Urba",
    "sg:orig_category":"Electricidad: Instaladores",
    "sg:phone":"+34 972 38 04 44",
    "sg:postcode":"17490",
    "sg:province":"Girona",
    "wof:name":"J.antich S.l.",
    "wof:placetype":"venue"
},
  "geometry": {"coordinates":[3.1481759548,42.3640785217],"type":"Point"}
}