{
  "type": "Feature",
  "properties": {
    "addr:full":"Ctra Valladolid, S/n Fuensalda\u00d1a Valladolid 47194",
    "addr:postcode":"47194",
    "addr:street":"Ctra Valladolid S / N",
    "iso:country":"ES",
    "sg:address":"Ctra Valladolid, S/n",
    "sg:city":"Fuensalda\u00d1a",
    "sg:orig_category":"Molduras, Junquillos, Listones Y Molduras Perforadas",
    "sg:phone":"+34 983 58 31 71",
    "sg:postcode":"47194",
    "sg:province":"Valladolid",
    "wof:name":"Xxii Alvaro Y Gonzalo Almaget S.l",
    "wof:placetype":"venue"
},
  "geometry": {"coordinates":[-4.7621107101,41.7061271667],"type":"Point"}
}