{
  "type": "Feature",
  "properties": {
    "addr:full":"Calle de Enfermeras Martires De Somiedo, 1 Astorga Le\u00f3n 24700",
    "addr:housenumber":"1",
    "addr:postcode":"24700",
    "addr:street":"Calle De Enfermeras Martires De Somiedo;Leo\u0301N",
    "iso:country":"ES",
    "sg:address":"Calle de Enfermeras Martires De Somiedo, 1",
    "sg:city":"Astorga",
    "sg:orig_category":"Asesor\u00cda Fiscal Y Jur\u00cddica",
    "sg:phone":"+34 987 61 76 34",
    "sg:postcode":"24700",
    "sg:province":"Le\u00f3n",
    "wof:name":"Mures Quintana Jose Luis",
    "wof:placetype":"venue"
},
  "geometry": {"coordinates":[-6.0530390739,42.4566268921],"type":"Point"}
}