{
  "type": "Feature",
  "properties": {
    "addr:full":"Carrer de Mallorca, 123 Barcelona Barcelona 08036",
    "addr:housenumber":"123",
    "addr:postcode":"08036",
    "addr:street":"Carrer De Mallorca",
    "iso:country":"ES",
    "sg:address":"Carrer de Mallorca, 123",
    "sg:city":"Barcelona",
    "sg:orig_category":"Aparatos Digitales",
    "sg:phone":"+34 934 54 74 03",
    "sg:postcode":"08036",
    "sg:province":"Barcelona",
    "sg:website":"www.colorlab.es",
    "wof:name":"Colorlab S. A.",
    "wof:placetype":"venue"
},
  "geometry": {"coordinates":[2.1532559395,41.3870124817],"type":"Point"}
}