{
  "type": "Feature",
  "properties": {
    "iso:country":"ES",
    "sg:address":"Calle de Corona, 36",
    "sg:city":"Valencia",
    "sg:orig_category":"Art\u00cdculos De Regalo (al Por Menor)",
    "sg:phone":"+34 963 92 47 46",
    "sg:postcode":"46003",
    "sg:province":"Valencia",
    "wof:name":"Vazquez Gimeno Dolores",
    "wof:placetype":"venue"
},
  "geometry": {"coordinates":[-0.3830659986,39.4783592224],"type":"Point"}
}