{
  "type": "Feature",
  "properties": {
    "addr:full":"Av Zaidin, Km. 0002,6 Fraga Huesca 22520",
    "addr:postcode":"22520",
    "addr:street":"Av Zaidin Km. 0002,6 Fraga",
    "iso:country":"ES",
    "sg:address":"Av Zaidin, Km. 0002,6",
    "sg:city":"Fraga",
    "sg:orig_category":"Hormig\u00d3n (m\u00c1quinas E Instalaci\u00d3n)",
    "sg:phone":"+34 974 45 41 91",
    "sg:postcode":"22520",
    "sg:province":"Huesca",
    "wof:name":"Hormigones Alcanadre S.l.",
    "wof:placetype":"venue"
},
  "geometry": {"coordinates":[0.3438299894,41.5223045349],"type":"Point"}
}