{
  "type": "Feature",
  "properties": {
    "iso:country":"ES",
    "sg:address":"Avda Santa Marina, 35",
    "sg:city":"Badajoz",
    "sg:orig_category":"Abogados",
    "sg:phone":"+34 924 22 02 71",
    "sg:postcode":"06005",
    "sg:province":"Badajoz",
    "wof:name":"Navarro De Prado Maria De Los Remedios",
    "wof:placetype":"venue"
},
  "geometry": {"coordinates":[-6.9798750877,38.876159668],"type":"Point"}
}