{
  "type": "Feature",
  "properties": {
    "addr:full":"La Manchica, S/n Merca Ourense 32830",
    "addr:housenumber":"s / n",
    "addr:postcode":"32830",
    "iso:country":"ES",
    "sg:address":"La Manchica, S/n",
    "sg:city":"Merca",
    "sg:orig_category":"Fabrica De Cer\u00c1micas",
    "sg:phone":"+34 988 26 00 08",
    "sg:postcode":"32830",
    "sg:province":"Ourense",
    "wof:name":"Ceramica La Manchica S.a.",
    "wof:placetype":"venue"
},
  "geometry": {"coordinates":[-7.9328742027,42.2269554138],"type":"Point"}
}