{
  "type": "Feature",
  "properties": {
    "addr:full":"Carrer de Lluis Sagnier, 31 Barcelona Barcelona 08032",
    "addr:housenumber":"31",
    "addr:postcode":"08032",
    "addr:street":"Carrer De Lluis Sagnier",
    "iso:country":"ES",
    "sg:address":"Carrer de Lluis Sagnier, 31",
    "sg:city":"Barcelona",
    "sg:orig_category":"Molduras, Junquillos, Listones Y Molduras Perforadas",
    "sg:phone":"+34 933 47 73 36",
    "sg:postcode":"08032",
    "sg:province":"Barcelona",
    "wof:name":"Boira Hernandez Milagros",
    "wof:placetype":"venue"
},
  "geometry": {"coordinates":[2.1749000549,41.4247055054],"type":"Point"}
}