{
  "type": "Feature",
  "properties": {
    "addr:full":"Calle de Calicasas, 125 Albolote Granada 18220",
    "addr:housenumber":"125",
    "addr:postcode":"18220",
    "addr:street":"Calle De Calicasas",
    "iso:country":"ES",
    "sg:address":"Calle de Calicasas, 125",
    "sg:city":"Albolote",
    "sg:orig_category":"Mayoristas E Intermediarios En Alcoholes",
    "sg:phone":"+34 958 46 54 38",
    "sg:postcode":"18220",
    "sg:province":"Granada",
    "wof:name":"Himar Licores",
    "wof:placetype":"venue"
},
  "geometry": {"coordinates":[-3.6446464062,37.2311096191],"type":"Point"}
}