{
  "type": "Feature",
  "properties": {
    "addr:full":"Avda Prado De Irache (el), S/n Irache Navarra 31240",
    "addr:postcode":"31240",
    "addr:street":"Avda Prado De Irache El S / N",
    "iso:country":"ES",
    "sg:address":"Avda Prado De Irache (el), S/n",
    "sg:city":"Irache",
    "sg:orig_category":"Zonas De Acampada, Aparcamiento Para Caravanas",
    "sg:phone":"+34 948 55 55 55",
    "sg:postcode":"31240",
    "sg:province":"Navarra",
    "wof:name":"Lokitz S.l.",
    "wof:placetype":"venue"
},
  "geometry": {"coordinates":[-2.041809082,42.6537399292],"type":"Point"}
}