{
  "type": "Feature",
  "properties": {
    "addr:full":"Calle de San Isidro, 2 Cullar-vega Granada 18195",
    "addr:housenumber":"2",
    "addr:postcode":"18195",
    "addr:street":"Calle De San Isidro",
    "iso:country":"ES",
    "sg:address":"Calle de San Isidro, 2",
    "sg:city":"Cullar-vega",
    "sg:orig_category":"Molduras, Junquillos, Listones Y Molduras Perforadas",
    "sg:phone":"+34 958 58 13 48",
    "sg:postcode":"18195",
    "sg:province":"Granada",
    "wof:name":"Alvarez Olgoso Gerardo",
    "wof:placetype":"venue"
},
  "geometry": {"coordinates":[-3.6727921963,37.1545448303],"type":"Point"}
}