{
  "type": "Feature",
  "properties": {
    "iso:country":"ES",
    "sg:address":"Pol Ind Tres Hermanas, S/n",
    "sg:city":"Aspe",
    "sg:orig_category":"Molduras, Junquillos, Listones Y Molduras Perforadas",
    "sg:phone":"+34 965 49 28 12",
    "sg:postcode":"03680",
    "sg:province":"Alicante",
    "wof:name":"Restaurante 3 Hermanas S.c.",
    "wof:placetype":"venue"
},
  "geometry": {"coordinates":[-0.7747089863,38.3399810791],"type":"Point"}
}