{
  "type": "Feature",
  "properties": {
    "addr:full":"Ctra. Madrid-toledo, Km. 0063,4 Urb.olias Toledo 45280",
    "addr:postcode":"45280",
    "addr:street":"Ctra. Madrid-Toledo Km. 0063,4",
    "iso:country":"ES",
    "sg:address":"Ctra. Madrid-toledo, Km. 0063,4",
    "sg:city":"Urb.olias",
    "sg:orig_category":"Rectificaci\u00d3n, Mecanizado, Fresado",
    "sg:phone":"+34 925 35 36 52",
    "sg:postcode":"45280",
    "sg:province":"Toledo",
    "wof:name":"Nueva Rectificadora S.c.l.",
    "wof:placetype":"venue"
},
  "geometry": {"coordinates":[-3.9885389805,39.9435043335],"type":"Point"}
}