{
  "type": "Feature",
  "properties": {
    "iso:country":"ES",
    "sg:address":"Plaz Inmaculada (la), 1",
    "sg:city":"Le\u00f3n",
    "sg:orig_category":"Agencias Y Agentes Comerciales, Representantes",
    "sg:phone":"+34 987 23 57 55",
    "sg:postcode":"24001",
    "sg:province":"Le\u00f3n",
    "wof:name":"Fernandez Gonzalez Jose Angel",
    "wof:placetype":"venue"
},
  "geometry": {"coordinates":[-5.5753369331,42.5991210938],"type":"Point"}
}