{
  "type": "Feature",
  "properties": {
    "addr:full":"Avda Pais Valencia, 52 Torrent Valencia 46900",
    "addr:housenumber":"52",
    "addr:postcode":"46900",
    "addr:street":"Avda Pais Valencia;Valencia",
    "iso:country":"ES",
    "sg:address":"Avda Pais Valencia, 52",
    "sg:city":"Torrent",
    "sg:orig_category":"Farmacias",
    "sg:phone":"+34 961 55 05 42",
    "sg:postcode":"46900",
    "sg:province":"Valencia",
    "wof:name":"Mateu Vidal Jose",
    "wof:placetype":"venue"
},
  "geometry": {"coordinates":[-0.469054997,39.4340934753],"type":"Point"}
}