{
  "type": "Feature",
  "properties": {
    "iso:country":"ES",
    "sg:address":"Calle de Gamonal, 5",
    "sg:city":"Madrid",
    "sg:orig_category":"Inform\u00c1tica (estudios, Servicios, Asesor\u00cda, Formaci\u00d3n)",
    "sg:phone":"+34 913 80 45 00",
    "sg:postcode":"28031",
    "sg:province":"Madrid",
    "sg:website":"www.cys.es",
    "wof:name":"Control Sys S.a.",
    "wof:placetype":"venue"
},
  "geometry": {"coordinates":[-3.6463000774,40.371925354],"type":"Point"}
}