{
  "type": "Feature",
  "properties": {
    "iso:country":"ES",
    "sg:address":"Calle de Galaroza, 15",
    "sg:city":"Huelva",
    "sg:orig_category":"Florister\u00cdas",
    "sg:phone":"+34 959 22 66 69",
    "sg:postcode":"21006",
    "sg:province":"Huelva",
    "wof:name":"Brioso Davalos Maria Isabel",
    "wof:placetype":"venue"
},
  "geometry": {"coordinates":[-6.9328670502,37.2618675232],"type":"Point"}
}