{
  "type": "Feature",
  "properties": {
    "addr:full":"Calle de San Lucas, 43 Aljorra Murcia 30390",
    "addr:housenumber":"43",
    "addr:postcode":"30390",
    "addr:street":"Calle De San Lucas",
    "iso:country":"ES",
    "sg:address":"Calle de San Lucas, 43",
    "sg:city":"Aljorra",
    "sg:orig_category":"Promotores Constructores",
    "sg:phone":"+34 968 55 83 72",
    "sg:postcode":"30390",
    "sg:province":"Murcia",
    "wof:name":"Construcciones Serafin Zaplana E Hijos S.l.",
    "wof:placetype":"venue"
},
  "geometry": {"coordinates":[-1.064043045,37.690574646],"type":"Point"}
}