{
  "type": "Feature",
  "properties": {
    "addr:full":"Tellerialde Plaza, 4 Errenteria Guip\u00f9zcoa 20100",
    "addr:housenumber":"4",
    "addr:postcode":"20100",
    "addr:street":"Guipu\u0300Zcoa",
    "iso:country":"ES",
    "sg:address":"Tellerialde Plaza, 4",
    "sg:city":"Errenteria",
    "sg:orig_category":"Plomeros",
    "sg:phone":"+34 943 34 04 45",
    "sg:postcode":"20100",
    "sg:province":"Guip\u00f9zcoa",
    "wof:name":"Irurieta Fabro Cesar",
    "wof:placetype":"venue"
},
  "geometry": {"coordinates":[-1.8996850252,43.314365387],"type":"Point"}
}