{
  "type": "Feature",
  "properties": {
    "iso:country":"ES",
    "sg:address":"Calle de Escuelas, S/n",
    "sg:city":"Torreaguera",
    "sg:orig_category":"Centros De Educaci\u00d3n Especial",
    "sg:phone":"+34 968 82 08 70",
    "sg:postcode":"30579",
    "sg:province":"Murcia",
    "wof:name":"Colegio Publico Cristo Del Valle",
    "wof:placetype":"venue"
},
  "geometry": {"coordinates":[-1.0546239614,37.9781036377],"type":"Point"}
}