{
  "type": "Feature",
  "properties": {
    "iso:country":"ES",
    "sg:address":"Mcdo C. Sainz, S/n",
    "sg:city":"Santander",
    "sg:orig_category":"Frutas, Legumbres Frescas Y Tempranas (al Por Menor)",
    "sg:phone":"+34 942 31 40 20",
    "sg:postcode":"39003",
    "sg:province":"Cantabria",
    "wof:name":"Garrido Escalada Maria Angeles",
    "wof:placetype":"venue"
},
  "geometry": {"coordinates":[-3.8013055325,43.4646339417],"type":"Point"}
}