{
  "type": "Feature",
  "properties": {
    "iso:country":"ES",
    "sg:address":"Av Puig (del), 1",
    "sg:city":"Vendrell",
    "sg:orig_category":"Arquitectos",
    "sg:phone":"+34 977 66 68 84",
    "sg:postcode":"43700",
    "sg:province":"Tarragona",
    "wof:name":"Sanchez Obaya Ricardo Saul",
    "wof:placetype":"venue"
},
  "geometry": {"coordinates":[1.5380690098,41.2174186707],"type":"Point"}
}