{
  "type": "Feature",
  "properties": {
    "iso:country":"ES",
    "sg:address":"Carr Industria, 36",
    "sg:city":"Angles",
    "sg:orig_category":"Empresas De Carpinter\u00cda De Madera",
    "sg:phone":"+34 972 42 10 14",
    "sg:postcode":"17160",
    "sg:province":"Girona",
    "wof:name":"Danes Serveis De Fusteria S.l.",
    "wof:placetype":"venue"
},
  "geometry": {"coordinates":[2.6372509003,41.9562454224],"type":"Point"}
}