{
  "type": "Feature",
  "properties": {
    "addr:full":"Calle de Juan De Garay, 29 Alacant Alicante 03015",
    "addr:housenumber":"29",
    "addr:postcode":"03015",
    "addr:street":"Calle De Juan De Garay",
    "iso:country":"ES",
    "sg:address":"Calle de Juan De Garay, 29",
    "sg:city":"Alacant",
    "sg:orig_category":"Muebles, Minoristas",
    "sg:phone":"+34 965 24 53 41",
    "sg:postcode":"03015",
    "sg:province":"Alicante",
    "wof:name":"Milano S. L.",
    "wof:placetype":"venue"
},
  "geometry": {"coordinates":[-0.4769200087,38.3642921448],"type":"Point"}
}