{
  "type": "Feature",
  "properties": {
    "addr:full":"Calle de Argimiro Torrecilla, S/n Jarandilla Vera C\u00e1ceres 10450",
    "addr:housenumber":"s / n",
    "addr:postcode":"10450",
    "addr:street":"Calle De Argimiro Torrecilla;Ca\u0301Ceres",
    "iso:country":"ES",
    "sg:address":"Calle de Argimiro Torrecilla, S/n",
    "sg:city":"Jarandilla Vera",
    "sg:orig_category":"Molduras, Junquillos, Listones Y Molduras Perforadas",
    "sg:phone":"+34 927 56 02 12",
    "sg:postcode":"10450",
    "sg:province":"C\u00e1ceres",
    "wof:name":"Serrano Lopez Jose Luis",
    "wof:placetype":"venue"
},
  "geometry": {"coordinates":[-5.6575140953,40.1289901733],"type":"Point"}
}