{
  "type": "Feature",
  "properties": {
    "iso:country":"ES",
    "sg:address":"Calle de Alburquerque, 5",
    "sg:city":"Madrid",
    "sg:orig_category":"Grabados",
    "sg:phone":"+34 914 48 73 83",
    "sg:postcode":"28010",
    "sg:province":"Madrid",
    "wof:name":"Rodriguez De Rivera Moron Rafael",
    "wof:placetype":"venue"
},
  "geometry": {"coordinates":[-3.7028081417,40.4311676025],"type":"Point"}
}