{
  "type": "Feature",
  "properties": {
    "addr:full":"Avda Ejercito (del), 42 Arganda Madrid 28500",
    "addr:housenumber":"42",
    "addr:postcode":"28500",
    "addr:street":"Avda Ejercito Del",
    "iso:country":"ES",
    "sg:address":"Avda Ejercito (del), 42",
    "sg:city":"Arganda",
    "sg:orig_category":"Comercio De Piezas De Recambio Y De Accesorios De Veh\u00cdculos, Veh\u00cdculos Industriales",
    "sg:phone":"+34 918 71 11 89",
    "sg:postcode":"28500",
    "sg:province":"Madrid",
    "wof:name":"Nilauto S. A.",
    "wof:placetype":"venue"
},
  "geometry": {"coordinates":[-3.447840929,40.3030052185],"type":"Point"}
}