{
  "type": "Feature",
  "properties": {
    "addr:full":"Carrer de Cial Cerro De La Comadre, S/n Bormujos Sevilla 41930",
    "addr:housenumber":"s / n",
    "addr:postcode":"41930",
    "addr:street":"Carrer De Cial Cerro De La Comadre",
    "iso:country":"ES",
    "sg:address":"Carrer de Cial Cerro De La Comadre, S/n",
    "sg:city":"Bormujos",
    "sg:orig_category":"Ropa Para Caballeros (al Por Menor)",
    "sg:phone":"+34 955 72 30 94",
    "sg:postcode":"41930",
    "sg:province":"Sevilla",
    "wof:name":"Out Factory S.l.",
    "wof:placetype":"venue"
},
  "geometry": {"coordinates":[-6.0711288452,37.3726081848],"type":"Point"}
}