{
  "type": "Feature",
  "properties": {
    "addr:full":"Calle de Carretera, 98 Pradejon La Rioja 26510",
    "addr:housenumber":"98",
    "addr:postcode":"26510",
    "addr:street":"Calle De Carretera;Rioja",
    "iso:country":"ES",
    "sg:address":"Calle de Carretera, 98",
    "sg:city":"Pradejon",
    "sg:orig_category":"Zapatos (al Por Menor)",
    "sg:phone":"+34 941 15 05 06",
    "sg:postcode":"26510",
    "sg:province":"La Rioja",
    "wof:name":"Cagigos Gomez Angel",
    "wof:placetype":"venue"
},
  "geometry": {"coordinates":[-2.0701010227,42.3337364197],"type":"Point"}
}