{
  "type": "Feature",
  "properties": {
    "addr:full":"Plaz San Vicente De Paul, 6 Madrid Madrid 28025",
    "addr:housenumber":"6",
    "addr:postcode":"28025",
    "addr:street":"Plaz",
    "iso:country":"ES",
    "sg:address":"Plaz San Vicente De Paul, 6",
    "sg:city":"Madrid",
    "sg:orig_category":"Estancos",
    "sg:phone":"+34 915 69 51 40",
    "sg:postcode":"28025",
    "sg:province":"Madrid",
    "wof:name":"Macias Ruiz Pilar",
    "wof:placetype":"venue"
},
  "geometry": {"coordinates":[-3.7261579037,40.3856391907],"type":"Point"}
}