{
  "type": "Feature",
  "properties": {
    "addr:full":"Carr Rubio, 14 Igualada Barcelona 08700",
    "addr:housenumber":"14",
    "addr:postcode":"08700",
    "addr:street":"Carr Rubio",
    "iso:country":"ES",
    "sg:address":"Carr Rubio, 14",
    "sg:city":"Igualada",
    "sg:orig_category":"Dietistas",
    "sg:phone":"+34 938 03 74 05",
    "sg:postcode":"08700",
    "sg:province":"Barcelona",
    "wof:name":"Balcells Bernaus Ana Maria",
    "wof:placetype":"venue"
},
  "geometry": {"coordinates":[1.6192324162,41.5849342346],"type":"Point"}
}