{
  "type": "Feature",
  "properties": {
    "addr:full":"Andalucia, 7 Mijas Costa M\u00e1laga 29649",
    "addr:housenumber":"7",
    "addr:postcode":"29649",
    "addr:street":"Andalucia",
    "iso:country":"ES",
    "sg:address":"Andalucia, 7",
    "sg:city":"Mijas Costa",
    "sg:orig_category":"Molduras, Junquillos, Listones Y Molduras Perforadas",
    "sg:phone":"+34 952 49 34 69",
    "sg:postcode":"29649",
    "sg:province":"M\u00e1laga",
    "wof:name":"Iba\u00f1ez Negrete Miguel",
    "wof:placetype":"venue"
},
  "geometry": {"coordinates":[-4.6369104385,36.5089149475],"type":"Point"}
}