{
  "type": "Feature",
  "properties": {
    "iso:country":"ES",
    "sg:address":"Calle de Puerto, 14",
    "sg:city":"Malaga",
    "sg:orig_category":"Centros Empresariales",
    "sg:phone":"+34 952 06 03 25",
    "sg:postcode":"29016",
    "sg:province":"M\u00e1laga",
    "wof:name":"Gesif S.a.",
    "wof:placetype":"venue"
},
  "geometry": {"coordinates":[-4.4082698822,36.7200317383],"type":"Point"}
}