{
  "type": "Feature",
  "properties": {
    "iso:country":"ES",
    "sg:address":"Carrer de Doctor Fleming, 85",
    "sg:city":"Castelldefels",
    "sg:orig_category":"Empresarios",
    "sg:phone":"+34 936 65 62 78",
    "sg:postcode":"08860",
    "sg:province":"Barcelona",
    "sg:website":"www.casatevareformes.com",
    "wof:name":"Casa Teva Reformes S.l.",
    "wof:placetype":"venue"
},
  "geometry": {"coordinates":[1.9730499983,41.2799110413],"type":"Point"}
}