{
  "type": "Feature",
  "properties": {
    "iso:country":"ES",
    "sg:address":"Calle de General Emilio Villaescusa, 16",
    "sg:city":"Tarancon",
    "sg:orig_category":"Cl\u00cdnicas Dentales",
    "sg:phone":"+34 969 32 50 08",
    "sg:postcode":"16400",
    "sg:province":"Cuenca",
    "wof:name":"Dentimatica S.l.",
    "wof:placetype":"venue"
},
  "geometry": {"coordinates":[-3.0078980923,40.0068435669],"type":"Point"}
}