{
  "type": "Feature",
  "properties": {
    "iso:country":"ES",
    "sg:address":"Calle de Participacion Ciudadana, 12",
    "sg:city":"Cordoba",
    "sg:orig_category":"Laboratorios",
    "sg:phone":"+34 957 40 08 42",
    "sg:postcode":"14011",
    "sg:province":"C\u00f3rdoba",
    "wof:name":"Qoras I D I S.l.",
    "wof:placetype":"venue"
},
  "geometry": {"coordinates":[-4.8106942177,37.8975601196],"type":"Point"}
}