{
  "type": "Feature",
  "properties": {
    "addr:full":"Calle de Amor De Dios, 17 Madrid Madrid 28014",
    "addr:housenumber":"17",
    "addr:postcode":"madrid;28014",
    "addr:street":"Calle De Amor De Dios",
    "iso:country":"ES",
    "sg:address":"Calle de Amor De Dios, 17",
    "sg:city":"Madrid",
    "sg:orig_category":"Librer\u00cdas",
    "sg:phone":"+34 914 20 40 07",
    "sg:postcode":"28014",
    "sg:province":"Madrid",
    "wof:name":"El Elefante Enamorado C.b.",
    "wof:placetype":"venue"
},
  "geometry": {"coordinates":[-3.6985087395,40.4124450684],"type":"Point"}
}