{
  "type": "Feature",
  "properties": {
    "iso:country":"ES",
    "sg:address":"Calle de Camino Viejo De Leganes, 174",
    "sg:city":"Madrid",
    "sg:orig_category":"Loter\u00cda Y T\u00d3mbola",
    "sg:phone":"+34 914 62 45 13",
    "sg:postcode":"28025",
    "sg:province":"Madrid",
    "wof:name":"Lazaro Tallon Jose",
    "wof:placetype":"venue"
},
  "geometry": {"coordinates":[-3.7328975201,40.3788375854],"type":"Point"}
}