{
  "type": "Feature",
  "properties": {
    "addr:full":"Plaz Luis Bu\u00d1uel, 1 Almansa Albacete 02640",
    "addr:housenumber":"1",
    "addr:postcode":"02640",
    "addr:street":"Plaz Luis Bun\u0303Uel",
    "iso:country":"ES",
    "sg:address":"Plaz Luis Bu\u00d1uel, 1",
    "sg:city":"Almansa",
    "sg:orig_category":"Obras Y Organismos Sociales",
    "sg:phone":"+34 967 31 05 62",
    "sg:postcode":"02640",
    "sg:province":"Albacete",
    "wof:name":"Ayuntamiento De Almansa",
    "wof:placetype":"venue"
},
  "geometry": {"coordinates":[-1.0969400406,38.8572387695],"type":"Point"}
}