{
  "type": "Feature",
  "properties": {
    "addr:full":"Carrer de Arquitecte Vives, 108 Valls Tarragona 43800",
    "addr:housenumber":"108",
    "addr:postcode":"43800",
    "addr:street":"Carrer De Arquitecte Vives",
    "iso:country":"ES",
    "sg:address":"Carrer de Arquitecte Vives, 108",
    "sg:city":"Valls",
    "sg:orig_category":"Centros De Coordinaci\u00d3n",
    "sg:phone":"+34 977 61 37 51",
    "sg:postcode":"43800",
    "sg:province":"Tarragona",
    "wof:name":"Ogea Lopez Francisco",
    "wof:placetype":"venue"
},
  "geometry": {"coordinates":[1.2605819702,41.2987442017],"type":"Point"}
}