{
  "type": "Feature",
  "properties": {
    "addr:full":"Cmno Landetabidea, 4 Bilbao Vizcaya 48007",
    "addr:housenumber":"4",
    "addr:postcode":"48007",
    "addr:street":"Cmno Landetabidea",
    "iso:country":"ES",
    "sg:address":"Cmno Landetabidea, 4",
    "sg:city":"Bilbao",
    "sg:orig_category":"Plomeros",
    "sg:phone":"+34 944 46 06 01",
    "sg:postcode":"48007",
    "sg:province":"Vizcaya",
    "wof:name":"Alcantara Fernando Rogelio",
    "wof:placetype":"venue"
},
  "geometry": {"coordinates":[-2.9250864983,43.270450592],"type":"Point"}
}