{
  "type": "Feature",
  "properties": {
    "iso:country":"ES",
    "sg:address":"Avda Ramon Y Cajal, S/n",
    "sg:city":"Dos Hermanas",
    "sg:orig_category":"Molduras, Junquillos, Listones Y Molduras Perforadas",
    "sg:phone":"+34 955 66 03 98",
    "sg:postcode":"41700",
    "sg:province":"Sevilla",
    "wof:name":"Mu\u00f1oz Valcarcel Jorge Gonzalo",
    "wof:placetype":"venue"
},
  "geometry": {"coordinates":[-5.9245371819,37.2899856567],"type":"Point"}
}