{
  "type": "Feature",
  "properties": {
    "addr:full":"Carrer de Jaume Balmes, 2 Premia Mar Barcelona 08330",
    "addr:housenumber":"2",
    "addr:postcode":"08330",
    "addr:street":"Carrer De Jaume Balmes",
    "iso:country":"ES",
    "sg:address":"Carrer de Jaume Balmes, 2",
    "sg:city":"Premia Mar",
    "sg:orig_category":"Construcci\u00d3n Mec\u00c1nica",
    "sg:phone":"+34 937 52 42 73",
    "sg:postcode":"08330",
    "sg:province":"Barcelona",
    "wof:name":"Roman Salinas Antonio",
    "wof:placetype":"venue"
},
  "geometry": {"coordinates":[2.3548870087,41.4903869629],"type":"Point"}
}