{
  "type": "Feature",
  "properties": {
    "iso:country":"ES",
    "sg:address":"Calle de Caballero Del Febo, 51",
    "sg:city":"Malaga",
    "sg:orig_category":"Muebles, Minoristas",
    "sg:phone":"+34 952 10 70 32",
    "sg:postcode":"29190",
    "sg:province":"M\u00e1laga",
    "wof:name":"Infantes Franco Sergio",
    "wof:placetype":"venue"
},
  "geometry": {"coordinates":[-4.4855475426,36.74559021],"type":"Point"}
}