{
  "type": "Feature",
  "properties": {
    "iso:country":"ES",
    "sg:address":"Calle de La Font, 7",
    "sg:city":"Tavernes Blanques",
    "sg:orig_category":"Maquinaria Para Industrias Diversas",
    "sg:phone":"+34 961 85 88 07",
    "sg:postcode":"46016",
    "sg:province":"Valencia",
    "wof:name":"Jimeno Obiol Antonio",
    "wof:placetype":"venue"
},
  "geometry": {"coordinates":[-0.3668639958,39.5048561096],"type":"Point"}
}