{
  "type": "Feature",
  "properties": {
    "iso:country":"ES",
    "sg:address":"Calle de San Vicente Martir, 11",
    "sg:city":"Zaragoza",
    "sg:orig_category":"M\u00c9dicos: Estomatolog\u00cda",
    "sg:phone":"+34 976 21 94 61",
    "sg:postcode":"50008",
    "sg:province":"Zaragoza",
    "wof:name":"Lecina Galve Ricardo",
    "wof:placetype":"venue"
},
  "geometry": {"coordinates":[-0.8813710213,41.6448745728],"type":"Point"}
}