{
  "type": "Feature",
  "properties": {
    "addr:full":"Ctra. S. Pablo, S/n Menasalbas Toledo 45128",
    "addr:housenumber":"s / n",
    "addr:postcode":"45128",
    "addr:street":"Ctra. S. Pablo",
    "iso:country":"ES",
    "sg:address":"Ctra. S. Pablo, S/n",
    "sg:city":"Menasalbas",
    "sg:orig_category":"Cooperativas Agr\u00cdcolas",
    "sg:phone":"+34 925 40 72 27",
    "sg:postcode":"45128",
    "sg:province":"Toledo",
    "wof:name":"Cooperativa Del Campo Valle De Mena",
    "wof:placetype":"venue"
},
  "geometry": {"coordinates":[-4.2866740227,39.6354866028],"type":"Point"}
}