{
  "type": "Feature",
  "properties": {
    "addr:full":"Calle de Gil De Fuentes, 18 Palencia Palencia 34001",
    "addr:housenumber":"18",
    "addr:postcode":"34001",
    "addr:street":"Calle De Gil De Fuentes",
    "iso:country":"ES",
    "sg:address":"Calle de Gil De Fuentes, 18",
    "sg:city":"Palencia",
    "sg:orig_category":"Obras Y Organismos Sociales",
    "sg:phone":"+34 979 74 90 42",
    "sg:postcode":"34001",
    "sg:province":"Palencia",
    "wof:name":"Fundacion Benefica Monedero",
    "wof:placetype":"venue"
},
  "geometry": {"coordinates":[-4.5351290703,42.0104103088],"type":"Point"}
}