{
  "type": "Feature",
  "properties": {
    "iso:country":"ES",
    "sg:address":"Avda Generalisimo, 8",
    "sg:city":"S. Vicente Barquera",
    "sg:orig_category":"Bisuter\u00cda, Joyer\u00cda, Relojer\u00cda (al Por Menor)",
    "sg:phone":"+34 942 71 21 29",
    "sg:postcode":"39540",
    "sg:province":"Cantabria",
    "wof:name":"Diaz Mantilla Jose Luis",
    "wof:placetype":"venue"
},
  "geometry": {"coordinates":[-4.3981928825,43.3852539062],"type":"Point"}
}