{
  "type": "Feature",
  "properties": {
    "iso:country":"ES",
    "sg:address":"Carrer de Jacinto Benavente, 42",
    "sg:city":"Mollet Valles",
    "sg:orig_category":"Empresas De Carpinter\u00cda",
    "sg:phone":"+34 935 93 67 12",
    "sg:postcode":"08100",
    "sg:province":"Barcelona",
    "wof:name":"Pedragosa Caralt Jose",
    "wof:placetype":"venue"
},
  "geometry": {"coordinates":[2.2107150555,41.5455627441],"type":"Point"}
}