{
  "type": "Feature",
  "properties": {
    "addr:full":"Galicia, 5 Ribeira-santa Uxia La Coru\u00f1a 15960",
    "addr:housenumber":"5",
    "addr:postcode":"15960",
    "addr:street":"Galicia;Uxia;Corun\u0303A",
    "iso:country":"ES",
    "sg:address":"Galicia, 5",
    "sg:city":"Ribeira-santa Uxia",
    "sg:orig_category":"Abogados",
    "sg:phone":"+34 981 87 23 09",
    "sg:postcode":"15960",
    "sg:province":"La Coru\u00f1a",
    "wof:name":"Mojica Gotti Andres Javier",
    "wof:placetype":"venue"
},
  "geometry": {"coordinates":[-8.9911775589,42.554473877],"type":"Point"}
}