{
  "type": "Feature",
  "properties": {
    "iso:country":"ES",
    "sg:address":"Calle de Virgen De La Soledad (de La), 6",
    "sg:city":"Mejorada Campo",
    "sg:orig_category":"Muebles, Minoristas",
    "sg:phone":"+34 916 79 42 55",
    "sg:postcode":"28840",
    "sg:province":"Madrid",
    "sg:website":"www.tumueble.com",
    "wof:name":"Gestion Y Compra S.a.",
    "wof:placetype":"venue"
},
  "geometry": {"coordinates":[-3.4894349575,40.3959884644],"type":"Point"}
}