{
  "type": "Feature",
  "properties": {
    "addr:full":"Ctra Sabadell, Km. 0004,0 Santa Perpetua De Mogoda Barcelona 08130",
    "addr:postcode":"08130",
    "addr:street":"Ctra Sabadell Km. 0004,0",
    "iso:country":"ES",
    "sg:address":"Ctra Sabadell, Km. 0004,0",
    "sg:city":"Santa Perpetua De Mogoda",
    "sg:orig_category":"Promotores Constructores",
    "sg:phone":"+34 935 60 75 48",
    "sg:postcode":"08130",
    "sg:province":"Barcelona",
    "wof:name":"Cooperativa La Perpetuenca S.c.c.l.",
    "wof:placetype":"venue"
},
  "geometry": {"coordinates":[2.1802799702,41.5371818542],"type":"Point"}
}