{
  "type": "Feature",
  "properties": {
    "iso:country":"ES",
    "sg:address":"As Corredoiras(os Anxeles), S/n",
    "sg:city":"Boimorto-gandara",
    "sg:orig_category":"Venta, Montaje De Neum\u00c1ticos",
    "sg:phone":"+34 981 51 64 96",
    "sg:postcode":"15807",
    "sg:province":"La Coru\u00f1a",
    "wof:name":"Gomez Arto Jose Antonio",
    "wof:placetype":"venue"
},
  "geometry": {"coordinates":[-8.1049156189,43.0180664062],"type":"Point"}
}