{
  "type": "Feature",
  "properties": {
    "iso:country":"ES",
    "sg:address":"Hortichuelas, S/n",
    "sg:city":"Parador Hortichuelas",
    "sg:orig_category":"Lavado, Limpieza De Veh\u00cdculos",
    "sg:phone":"+34 950 34 88 87",
    "sg:postcode":"04720",
    "sg:province":"Almer\u00eda",
    "wof:name":"Lopez Hernandez Miguel",
    "wof:placetype":"venue"
},
  "geometry": {"coordinates":[-2.596143961,36.8078041077],"type":"Point"}
}