{
  "type": "Feature",
  "properties": {
    "iso:country":"ES",
    "sg:address":"Rua Juan Bautista Andrade, 96",
    "sg:city":"Pontevedra",
    "sg:orig_category":"Florister\u00cdas",
    "sg:phone":"+34 986 87 03 87",
    "sg:postcode":"36005",
    "sg:province":"Pontevedra",
    "wof:name":"Ucha Lopez Maria Teresa",
    "wof:placetype":"venue"
},
  "geometry": {"coordinates":[-8.6386880875,42.4440536499],"type":"Point"}
}