{
  "type": "Feature",
  "properties": {
    "addr:full":"Po. Tilos, 6 Monteprincipe Madrid 28668",
    "addr:housenumber":"6",
    "addr:postcode":"28668",
    "addr:street":"Tilos",
    "iso:country":"ES",
    "sg:address":"Po. Tilos, 6",
    "sg:city":"Monteprincipe",
    "sg:orig_category":"Ingenier\u00cda, Centros De Estudios (diversos)",
    "sg:phone":"+34 913 51 32 52",
    "sg:postcode":"28668",
    "sg:province":"Madrid",
    "wof:name":"Trismegisto S.l.",
    "wof:placetype":"venue"
},
  "geometry": {"coordinates":[-3.8487160206,40.4117622375],"type":"Point"}
}