{
  "type": "Feature",
  "properties": {
    "addr:full":"Ctra Balneario, S/n Archena Murcia 30600",
    "addr:housenumber":"s / n",
    "addr:postcode":"30600",
    "addr:street":"Ctra Balneario",
    "iso:country":"ES",
    "sg:address":"Ctra Balneario, S/n",
    "sg:city":"Archena",
    "sg:orig_category":"Molduras, Junquillos, Listones Y Molduras Perforadas",
    "sg:phone":"+34 968 67 06 36",
    "sg:postcode":"30600",
    "sg:province":"Murcia",
    "wof:name":"Torres Alcolea Rafael",
    "wof:placetype":"venue"
},
  "geometry": {"coordinates":[-1.2981840372,38.1195793152],"type":"Point"}
}