{
  "type": "Feature",
  "properties": {
    "addr:full":"Calle de Alameda, 11 Coslada Madrid 28820",
    "addr:housenumber":"11",
    "addr:postcode":"28820",
    "addr:street":"Calle De Alameda",
    "iso:country":"ES",
    "sg:address":"Calle de Alameda, 11",
    "sg:city":"Coslada",
    "sg:orig_category":"Panader\u00cdas, Panader\u00cdas",
    "sg:phone":"+34 916 69 51 71",
    "sg:postcode":"28820",
    "sg:province":"Madrid",
    "wof:name":"Catalan Mu\u00f1oz Francisco",
    "wof:placetype":"venue"
},
  "geometry": {"coordinates":[-3.5611386299,40.4296684265],"type":"Point"}
}