{
  "type": "Feature",
  "properties": {
    "addr:full":"Cmno Molinos (de Los), S/n Estepona M\u00e1laga 29680",
    "addr:postcode":"29680",
    "addr:street":"Cmno Molinos De Los S / N;Ma\u0301Laga",
    "iso:country":"ES",
    "sg:address":"Cmno Molinos (de Los), S/n",
    "sg:city":"Estepona",
    "sg:orig_category":"Carnicer\u00cdas, Carnicer\u00cdas",
    "sg:phone":"+34 952 79 38 84",
    "sg:postcode":"29680",
    "sg:province":"M\u00e1laga",
    "wof:name":"Carniceria Los Molinos",
    "wof:placetype":"venue"
},
  "geometry": {"coordinates":[-5.1428442001,36.4302864075],"type":"Point"}
}