{
  "type": "Feature",
  "properties": {
    "addr:full":"Carr Bailen, 50 Vilanova I La Geltru Barcelona 08800",
    "addr:housenumber":"50",
    "addr:postcode":"08800",
    "addr:street":"Carr Bailen",
    "iso:country":"ES",
    "sg:address":"Carr Bailen, 50",
    "sg:city":"Vilanova I La Geltru",
    "sg:orig_category":"Empresas De Escayolas",
    "sg:phone":"+34 938 15 14 95",
    "sg:postcode":"08800",
    "sg:province":"Barcelona",
    "wof:name":"Bertran Bonastre Pedro",
    "wof:placetype":"venue"
},
  "geometry": {"coordinates":[1.7160270214,41.2226524353],"type":"Point"}
}