{
  "type": "Feature",
  "properties": {
    "iso:country":"ES",
    "sg:address":"Calle de Castalla, 21",
    "sg:city":"Petrer",
    "sg:orig_category":"Guarder\u00cdas",
    "sg:phone":"+34 965 37 68 71",
    "sg:postcode":"03610",
    "sg:province":"Alicante",
    "wof:name":"Bello Perez Antonio",
    "wof:placetype":"venue"
},
  "geometry": {"coordinates":[-0.7826610208,38.483669281],"type":"Point"}
}