{
  "type": "Feature",
  "properties": {
    "addr:full":"Calle de Cura Valera, 16 Huercal-overa Almer\u00eda 04600",
    "addr:housenumber":"16",
    "addr:postcode":"04600",
    "addr:street":"Calle De Cura Valera;Almeri\u0301A",
    "iso:country":"ES",
    "sg:address":"Calle de Cura Valera, 16",
    "sg:city":"Huercal-overa",
    "sg:orig_category":"Asistencia Y Consejos",
    "sg:phone":"+34 950 13 54 38",
    "sg:postcode":"04600",
    "sg:province":"Almer\u00eda",
    "wof:name":"Martinez Asensio Miguel Jesus",
    "wof:placetype":"venue"
},
  "geometry": {"coordinates":[-1.9447187185,37.3876609802],"type":"Point"}
}