{
  "type": "Feature",
  "properties": {
    "iso:country":"ES",
    "sg:address":"Ctra Alcudia (de L'), 9",
    "sg:city":"Alcudia",
    "sg:orig_category":"Fabricaci\u00d3n De Su\u00c9ters Y Chalecos De Punto",
    "sg:phone":"+34 966 50 08 96",
    "sg:postcode":"03820",
    "sg:province":"Alicante",
    "wof:name":"Atonio Giner S.l.",
    "wof:placetype":"venue"
},
  "geometry": {"coordinates":[-0.4330605865,38.7578086853],"type":"Point"}
}