{
  "type": "Feature",
  "properties": {
    "iso:country":"ES",
    "sg:address":"Catasol, 27",
    "sg:city":"Pedroso",
    "sg:orig_category":"Poller\u00cda Y Caza (al Por Menor)",
    "sg:phone":"+34 981 36 81 16",
    "sg:postcode":"15597",
    "sg:province":"La Coru\u00f1a",
    "wof:name":"Jose Montero Filgueiras Y Hermano Cdad.",
    "wof:placetype":"venue"
},
  "geometry": {"coordinates":[-8.163939476,43.5220413208],"type":"Point"}
}