{
  "type": "Feature",
  "properties": {
    "addr:full":"Carrer de Calassanc Marques, 6 Mataro Barcelona 08303",
    "addr:housenumber":"6",
    "addr:postcode":"08303",
    "addr:street":"Carrer De Calassanc Marques",
    "iso:country":"ES",
    "sg:address":"Carrer de Calassanc Marques, 6",
    "sg:city":"Mataro",
    "sg:orig_category":"Loter\u00cda Y T\u00d3mbola",
    "sg:phone":"+34 937 99 62 93",
    "sg:postcode":"08303",
    "sg:province":"Barcelona",
    "wof:name":"Medina Martin Encarnacion",
    "wof:placetype":"venue"
},
  "geometry": {"coordinates":[2.4256711006,41.5405044556],"type":"Point"}
}