{
  "type": "Feature",
  "properties": {
    "addr:full":"Calle de Coronacion De La Virgen Blanca, 10 Vitoria-gasteiz \u00c1lava 01012",
    "addr:housenumber":"10",
    "addr:postcode":"01012",
    "addr:street":"Calle De Coronacion De La Virgen Blanca",
    "iso:country":"ES",
    "sg:address":"Calle de Coronacion De La Virgen Blanca, 10",
    "sg:city":"Vitoria-gasteiz",
    "sg:orig_category":"Carnicer\u00cdas, Carnicer\u00cdas",
    "sg:phone":"+34 945 14 13 92",
    "sg:postcode":"01012",
    "sg:province":"\u00c1lava",
    "wof:name":"Miguel Antonio Gonzalez Garcia",
    "wof:placetype":"venue"
},
  "geometry": {"coordinates":[-2.6759266853,42.8524665833],"type":"Point"}
}