{
  "type": "Feature",
  "properties": {
    "iso:country":"ES",
    "sg:address":"Calle de Antonio Machado, 11",
    "sg:city":"Mairena Alcor",
    "sg:orig_category":"Muebles, Minoristas",
    "sg:phone":"+34 955 74 68 71",
    "sg:postcode":"41510",
    "sg:province":"Sevilla",
    "wof:name":"Muebles Antonio Kikito S.l",
    "wof:placetype":"venue"
},
  "geometry": {"coordinates":[-5.7587676048,37.3704795837],"type":"Point"}
}