{
  "type": "Feature",
  "properties": {
    "iso:country":"ES",
    "sg:address":"Paramo, 64",
    "sg:city":"Burgos",
    "sg:orig_category":"Bares, Piano",
    "sg:phone":"+34 947 48 14 24",
    "sg:postcode":"09007",
    "sg:province":"Burgos",
    "wof:name":"Hijos De Leonardo Carcedo S. L.",
    "wof:placetype":"venue"
},
  "geometry": {"coordinates":[-3.6527891159,42.3476219177],"type":"Point"}
}