{
  "type": "Feature",
  "properties": {
    "addr:full":"La Vega, S/n Porceyo Asturias 33392",
    "addr:housenumber":"s",
    "addr:postcode":"33392",
    "addr:street":"La Vega;/ N Porceyo Asturias",
    "iso:country":"ES",
    "sg:address":"La Vega, S/n",
    "sg:city":"Porceyo",
    "sg:orig_category":"Venta, Localizaci\u00d3n, Reparaci\u00d3n De Material E Instrumental M\u00c9dico",
    "sg:phone":"+34 985 16 70 92",
    "sg:postcode":"33392",
    "sg:province":"Asturias",
    "wof:name":"Linea Medica Hospitalaria S.l.",
    "wof:placetype":"venue"
},
  "geometry": {"coordinates":[-5.7052330971,43.5063514709],"type":"Point"}
}