{
  "type": "Feature",
  "properties": {
    "iso:country":"ES",
    "sg:address":"Carrer de Roger De Lluria, 53",
    "sg:city":"Barcelona",
    "sg:orig_category":"Florister\u00cdas",
    "sg:phone":"+34 932 15 53 59",
    "sg:postcode":"08009",
    "sg:province":"Barcelona",
    "wof:name":"Fortu\u00f1o Cornado Oriol",
    "wof:placetype":"venue"
},
  "geometry": {"coordinates":[2.168200016,41.3934516907],"type":"Point"}
}