{
  "type": "Feature",
  "properties": {
    "iso:country":"ES",
    "sg:address":"Calle de Real, S/n",
    "sg:city":"Burgos",
    "sg:orig_category":"Administraciones De Trabajo Y Empleo",
    "sg:phone":"+34 947 22 52 81",
    "sg:postcode":"09007",
    "sg:province":"Burgos",
    "wof:name":"Ecyl-servicio Publico De Empleo De Castilla Y Leon",
    "wof:placetype":"venue"
},
  "geometry": {"coordinates":[-3.6694540977,42.346950531],"type":"Point"}
}