{
  "type": "Feature",
  "properties": {
    "addr:full":"Calle de San Pedro, 14 Binefar Huesca 22500",
    "addr:housenumber":"14",
    "addr:postcode":"22500",
    "addr:street":"Calle De San Pedro",
    "iso:country":"ES",
    "sg:address":"Calle de San Pedro, 14",
    "sg:city":"Binefar",
    "sg:orig_category":"Panader\u00cdas, Panader\u00cdas",
    "sg:phone":"+34 974 42 95 81",
    "sg:postcode":"22500",
    "sg:province":"Huesca",
    "wof:name":"Piquer Frontons S.l.",
    "wof:placetype":"venue"
},
  "geometry": {"coordinates":[0.2925443053,41.8506584167],"type":"Point"}
}