{
  "type": "Feature",
  "properties": {
    "iso:country":"ES",
    "sg:address":"Calle de Illescas, 44",
    "sg:city":"Madrid",
    "sg:orig_category":"Publicidad (soportes Y Gesti\u00d3n)",
    "sg:phone":"+34 915 09 99 29",
    "sg:postcode":"28024",
    "sg:province":"Madrid",
    "wof:name":"Grupo Crisalia Regalos De Empresa, S.l.",
    "wof:placetype":"venue"
},
  "geometry": {"coordinates":[-3.7613260746,40.3929824829],"type":"Point"}
}