{
  "type": "Feature",
  "properties": {
    "iso:country":"ES",
    "sg:address":"Ctra Doctor Robert, 10",
    "sg:city":"Vendrell",
    "sg:orig_category":"Cajas De Ahorro",
    "sg:phone":"+34 977 66 03 80",
    "sg:postcode":"43700",
    "sg:province":"Tarragona",
    "sg:website":"www.caixatarragona.es",
    "wof:name":"Caixa D'estalvis De Tarragona",
    "wof:placetype":"venue"
},
  "geometry": {"coordinates":[1.5362329483,41.2210693359],"type":"Point"}
}