{
  "type": "Feature",
  "properties": {
    "iso:country":"ES",
    "sg:address":"Calle de Lopez De Hoyos, 393",
    "sg:city":"Madrid",
    "sg:orig_category":"Sociedades, Compa\u00d1\u00cdas Aseguradoras",
    "sg:phone":"+34 913 81 27 87",
    "sg:postcode":"28043",
    "sg:province":"Madrid",
    "wof:name":"Javier Checa Seguros S.l.",
    "wof:placetype":"venue"
},
  "geometry": {"coordinates":[-3.6499910355,40.4717178345],"type":"Point"}
}