{
  "type": "Feature",
  "properties": {
    "addr:full":"Calle de Mayor, 31 Pedro\u00d1eras Cuenca 16660",
    "addr:housenumber":"31",
    "addr:postcode":"16660",
    "addr:street":"Calle De Mayor",
    "iso:country":"ES",
    "sg:address":"Calle de Mayor, 31",
    "sg:city":"Pedro\u00d1eras",
    "sg:orig_category":"Confecci\u00d3n De Zapatos",
    "sg:phone":"+34 967 16 03 01",
    "sg:postcode":"16660",
    "sg:province":"Cuenca",
    "wof:name":"Gomez Sanchez Ramon",
    "wof:placetype":"venue"
},
  "geometry": {"coordinates":[-2.6749269962,39.4500846863],"type":"Point"}
}