{
  "type": "Feature",
  "properties": {
    "iso:country":"ES",
    "sg:address":"Calle de Obispo Rey Redondo, 23",
    "sg:city":"San Cristobal De La Laguna",
    "sg:orig_category":"Abogados",
    "sg:phone":"+34 922 25 29 01",
    "sg:postcode":"38201",
    "sg:province":"Santa Cruz De Tenerife",
    "wof:name":"Perera Alonso Rafael",
    "wof:placetype":"venue"
},
  "geometry": {"coordinates":[-16.3162689209,28.4884090424],"type":"Point"}
}