{
  "type": "Feature",
  "properties": {
    "addr:full":"Calle de Darsena, 5 Valladolid Valladolid 47009",
    "addr:housenumber":"5",
    "addr:postcode":"47009",
    "addr:street":"Calle De Darsena",
    "iso:country":"ES",
    "sg:address":"Calle de Darsena, 5",
    "sg:city":"Valladolid",
    "sg:orig_category":"Telas Y Sedas (al Por Menor)",
    "sg:phone":"+34 983 33 63 79",
    "sg:postcode":"47009",
    "sg:province":"Valladolid",
    "wof:name":"Blanco Guiles Maria Josefa",
    "wof:placetype":"venue"
},
  "geometry": {"coordinates":[-4.7337179184,41.6630134583],"type":"Point"}
}