{
  "type": "Feature",
  "properties": {
    "iso:country":"ES",
    "sg:address":"Logro\u00f1o, 37",
    "sg:city":"Castrillo Val",
    "sg:orig_category":"Abogados",
    "sg:phone":"+34 947 42 14 54",
    "sg:postcode":"09193",
    "sg:province":"Burgos",
    "wof:name":"Huidobro Diez Cesar",
    "wof:placetype":"venue"
},
  "geometry": {"coordinates":[-3.622344017,42.2870903015],"type":"Point"}
}