{
  "type": "Feature",
  "properties": {
    "addr:full":"Pje Cervantes, 2 Villargordo Ja\u00e9n 23630",
    "addr:housenumber":"2",
    "addr:postcode":"23630",
    "addr:street":"Pje Cervantes;Jae\u0301N",
    "iso:country":"ES",
    "sg:address":"Pje Cervantes, 2",
    "sg:city":"Villargordo",
    "sg:orig_category":"Parafarmacias",
    "sg:phone":"+34 953 37 77 51",
    "sg:postcode":"23630",
    "sg:province":"Ja\u00e9n",
    "wof:name":"Jimenez Moral Mari Carmen",
    "wof:placetype":"venue"
},
  "geometry": {"coordinates":[-3.7307140827,37.9388046265],"type":"Point"}
}