{
  "type": "Feature",
  "properties": {
    "addr:full":"Calle de Camarena, 93 Madrid Madrid 28047",
    "addr:housenumber":"93",
    "addr:postcode":"madrid;28047",
    "addr:street":"Calle De Camarena",
    "iso:country":"ES",
    "sg:address":"Calle de Camarena, 93",
    "sg:city":"Madrid",
    "sg:orig_category":"Perfumer\u00cda (al Por Menor)",
    "sg:phone":"+34 917 17 51 90",
    "sg:postcode":"28047",
    "sg:province":"Madrid",
    "wof:name":"Paljusa De Perfumeria S.a.",
    "wof:placetype":"venue"
},
  "geometry": {"coordinates":[-3.7555344105,40.3931503296],"type":"Point"}
}