{
  "type": "Feature",
  "properties": {
    "iso:country":"ES",
    "sg:address":"Calle de John Lennon, 38",
    "sg:city":"Merida",
    "sg:orig_category":"Bisuter\u00cda, Joyer\u00cda, Relojer\u00cda (al Por Menor)",
    "sg:phone":"+34 924 31 61 04",
    "sg:postcode":"06800",
    "sg:province":"Badajoz",
    "wof:name":"Guiberteau Correa Enrique",
    "wof:placetype":"venue"
},
  "geometry": {"coordinates":[-6.3449420929,38.914352417],"type":"Point"}
}