{
  "type": "Feature",
  "properties": {
    "iso:country":"ES",
    "sg:address":"Calle de Muguet, 6",
    "sg:city":"Madrid",
    "sg:orig_category":"Electricidad: Equipos Industriales, Componentes (fabricaci\u00d3n)",
    "sg:phone":"+34 915 08 01 95",
    "sg:postcode":"28044",
    "sg:province":"Madrid",
    "wof:name":"Medida Y Ensayos Electricos S.l.",
    "wof:placetype":"venue"
},
  "geometry": {"coordinates":[-3.7469100952,40.3699150085],"type":"Point"}
}