{
  "type": "Feature",
  "properties": {
    "addr:full":"Carrer de Clot, 80 Barcelona Barcelona 08018",
    "addr:housenumber":"80",
    "addr:postcode":"08018",
    "addr:street":"Carrer De Clot",
    "iso:country":"ES",
    "sg:address":"Carrer de Clot, 80",
    "sg:city":"Barcelona",
    "sg:orig_category":"Ense\u00d1anza: Profesiones Art\u00cdsticas",
    "sg:phone":"+34 932 45 51 87",
    "sg:postcode":"08018",
    "sg:province":"Barcelona",
    "wof:name":"Foto Nens S. L.",
    "wof:placetype":"venue"
},
  "geometry": {"coordinates":[2.1886219978,41.40832901],"type":"Point"}
}