{
  "type": "Feature",
  "properties": {
    "addr:full":"Carrer de Santa Teresa (de), 3 Tortosa Tarragona 43500",
    "addr:postcode":"43500",
    "addr:street":"Carrer De Santa Teresa De",
    "iso:country":"ES",
    "sg:address":"Carrer de Santa Teresa (de), 3",
    "sg:city":"Tortosa",
    "sg:orig_category":"Zapatos (al Por Menor)",
    "sg:phone":"+34 977 51 08 88",
    "sg:postcode":"43500",
    "sg:province":"Tarragona",
    "wof:name":"Serveis I Moda F.l.o. S.l.",
    "wof:placetype":"venue"
},
  "geometry": {"coordinates":[0.5132589936,40.7729911804],"type":"Point"}
}