{
  "type": "Feature",
  "properties": {
    "iso:country":"ES",
    "sg:address":"Pla\u00c7 Sardana (de La), 1",
    "sg:city":"Corbins",
    "sg:orig_category":"Fabricaci\u00d3n, Instalaci\u00d3n Y Reparaci\u00d3n De Bombas",
    "sg:phone":"+34 973 19 04 77",
    "sg:postcode":"25137",
    "sg:province":"Lleida",
    "sg:website":"www.tallerescorbins.com",
    "wof:name":"Talleres Corbins S.l.",
    "wof:placetype":"venue"
},
  "geometry": {"coordinates":[0.6952649951,41.6900482178],"type":"Point"}
}