{
  "type": "Feature",
  "properties": {
    "addr:full":"Calle de Verja, 63 Madrid Madrid 28026",
    "addr:housenumber":"63",
    "addr:postcode":"madrid;28026",
    "addr:street":"Calle De Verja",
    "iso:country":"ES",
    "sg:address":"Calle de Verja, 63",
    "sg:city":"Madrid",
    "sg:orig_category":"Fabricaci\u00d3n De Sobres, Bolsas Y Fundas",
    "sg:phone":"+34 902 20 05 67",
    "sg:postcode":"28026",
    "sg:province":"Madrid",
    "wof:name":"Sobre Plus S.a.",
    "wof:placetype":"venue"
},
  "geometry": {"coordinates":[-3.7117419243,40.382396698],"type":"Point"}
}