{
  "type": "Feature",
  "properties": {
    "addr:full":"Carrer de Figols, 23 Barcelona Barcelona 08028",
    "addr:housenumber":"23",
    "addr:postcode":"08028",
    "addr:street":"Carrer De Figols",
    "iso:country":"ES",
    "sg:address":"Carrer de Figols, 23",
    "sg:city":"Barcelona",
    "sg:orig_category":"Farmacias",
    "sg:phone":"+34 934 91 20 91",
    "sg:postcode":"08028",
    "sg:province":"Barcelona",
    "wof:name":"Massaneda Llinas Joaquim",
    "wof:placetype":"venue"
},
  "geometry": {"coordinates":[2.1301050186,41.3824424744],"type":"Point"}
}