{
  "type": "Feature",
  "properties": {
    "iso:country":"ES",
    "sg:address":"Calle de San Marcial, 40",
    "sg:city":"Donostia-san Sebastian",
    "sg:orig_category":"Centros De Coordinaci\u00d3n",
    "sg:phone":"+34 943 42 54 18",
    "sg:postcode":"20005",
    "sg:province":"Guip\u00f9zcoa",
    "wof:name":"Cospedal Apraiz Rafael",
    "wof:placetype":"venue"
},
  "geometry": {"coordinates":[-1.9833040237,43.3184204102],"type":"Point"}
}