{
  "type": "Feature",
  "properties": {
    "iso:country":"ES",
    "sg:address":"Calle de Pintor Murillo (del), 9",
    "sg:city":"Alcobendas",
    "sg:orig_category":"Estudios Y Construcci\u00d3n De Acuarios Y Viveros",
    "sg:phone":"+34 916 61 70 12",
    "sg:postcode":"28100",
    "sg:province":"Madrid",
    "wof:name":"Acuabierzo S.l.",
    "wof:placetype":"venue"
},
  "geometry": {"coordinates":[-3.6400179863,40.5389671326],"type":"Point"}
}