{
  "type": "Feature",
  "properties": {
    "iso:country":"ES",
    "sg:address":"Calle de Union (la), 20",
    "sg:city":"Alacant",
    "sg:orig_category":"Perfumer\u00cda (al Por Menor)",
    "sg:phone":"+34 965 92 34 78",
    "sg:postcode":"03005",
    "sg:province":"Alicante",
    "wof:name":"Euro-cosmetic-prof S.l.",
    "wof:placetype":"venue"
},
  "geometry": {"coordinates":[-0.4956550002,38.3476829529],"type":"Point"}
}