{
  "type": "Feature",
  "properties": {
    "iso:country":"ES",
    "sg:address":"Calle de Castello, 46",
    "sg:city":"Madrid",
    "sg:orig_category":"Costureras",
    "sg:phone":"+34 915 75 42 85",
    "sg:postcode":"28001",
    "sg:province":"Madrid",
    "wof:name":"Alvaro Martin Beatriz",
    "wof:placetype":"venue"
},
  "geometry": {"coordinates":[-3.6813666821,40.4267959595],"type":"Point"}
}