{
  "type": "Feature",
  "properties": {
    "iso:country":"ES",
    "sg:address":"Av Eramprunya (l'), 12",
    "sg:city":"Gava",
    "sg:orig_category":"Inform\u00c1tica (estudios, Servicios, Asesor\u00cda, Formaci\u00d3n)",
    "sg:phone":"+34 936 33 34 09",
    "sg:postcode":"08850",
    "sg:province":"Barcelona",
    "wof:name":"Ergose\u00d1a S L",
    "wof:placetype":"venue"
},
  "geometry": {"coordinates":[1.9987950325,41.3094062805],"type":"Point"}
}