{
  "type": "Feature",
  "properties": {
    "iso:country":"ES",
    "sg:address":"Carrer de Bisbe Urquinaona, 52",
    "sg:city":"Castelldefels",
    "sg:orig_category":"Empresarios",
    "sg:phone":"+34 936 36 46 55",
    "sg:postcode":"08860",
    "sg:province":"Barcelona",
    "wof:name":"Fundacio Privada Uszheimer",
    "wof:placetype":"venue"
},
  "geometry": {"coordinates":[1.9786800146,41.2827606201],"type":"Point"}
}