{
  "type": "Feature",
  "properties": {
    "iso:country":"ES",
    "sg:address":"Avda Blasco Iba\u00d1ez, 3",
    "sg:city":"Alcossebre",
    "sg:orig_category":"Inmobiliaria (agencias)",
    "sg:phone":"+34 964 41 44 04",
    "sg:postcode":"12579",
    "sg:province":"Castell\u00f3n",
    "wof:name":"Inmobiliaria D'asi",
    "wof:placetype":"venue"
},
  "geometry": {"coordinates":[0.2850950062,40.2547187805],"type":"Point"}
}