{
  "type": "Feature",
  "properties": {
    "addr:full":"Carrer de Sarria, 6 Gava Barcelona 08850",
    "addr:housenumber":"6",
    "addr:postcode":"08850",
    "addr:street":"Carrer De Sarria",
    "iso:country":"ES",
    "sg:address":"Carrer de Sarria, 6",
    "sg:city":"Gava",
    "sg:orig_category":"Empresas De Carpinter\u00cda De Madera",
    "sg:phone":"+34 936 38 29 02",
    "sg:postcode":"08850",
    "sg:province":"Barcelona",
    "wof:name":"Bienes Y Servicios Ansa S.l.",
    "wof:placetype":"venue"
},
  "geometry": {"coordinates":[2.0098049641,41.3058853149],"type":"Point"}
}