{
  "type": "Feature",
  "properties": {
    "iso:country":"ES",
    "sg:address":"Avda Ifach, De, 1",
    "sg:city":"Calpe",
    "sg:orig_category":"Inmobiliaria (agencias)",
    "sg:phone":"+34 965 83 69 30",
    "sg:postcode":"03710",
    "sg:province":"Alicante",
    "wof:name":"Calpe-sala",
    "wof:placetype":"venue"
},
  "geometry": {"coordinates":[0.0449060015,38.6455764771],"type":"Point"}
}