{
  "type": "Feature",
  "properties": {
    "addr:full":"Ctra Gral, Km. 0279,0 Pesues Cantabria 39594",
    "addr:postcode":"39594",
    "addr:street":"Ctra Gral Km. 0279,0",
    "iso:country":"ES",
    "sg:address":"Ctra Gral, Km. 0279,0",
    "sg:city":"Pesues",
    "sg:orig_category":"Comercio De Piezas De Recambio Y De Accesorios De Veh\u00cdculos, Veh\u00cdculos Industriales",
    "sg:phone":"+34 942 71 70 30",
    "sg:postcode":"39594",
    "sg:province":"Cantabria",
    "wof:name":"Arambarri Escobedo Antonio",
    "wof:placetype":"venue"
},
  "geometry": {"coordinates":[-4.4874253273,43.3749923706],"type":"Point"}
}