{
  "type": "Feature",
  "properties": {
    "iso:country":"ES",
    "sg:address":"Plaz Tarifa, 1",
    "sg:city":"Madrid",
    "sg:orig_category":"Peluquer\u00cdas, Peluquer\u00cda Mixta",
    "sg:phone":"+34 914 62 72 11",
    "sg:postcode":"28025",
    "sg:province":"Madrid",
    "wof:name":"Calle Principal S.l.",
    "wof:placetype":"venue"
},
  "geometry": {"coordinates":[-3.7314250469,40.3846893311],"type":"Point"}
}