{
  "type": "Feature",
  "properties": {
    "iso:country":"ES",
    "sg:address":"Carrer de Espirall, S/n",
    "sg:city":"Vilafranca Penedes",
    "sg:orig_category":"Televisi\u00d3n, V\u00cddeo: Aparatos Y Accesorios (venta)",
    "sg:phone":"+34 938 18 04 80",
    "sg:postcode":"08720",
    "sg:province":"Barcelona",
    "wof:name":"Tanaki Espa\u00f1a S.a.",
    "wof:placetype":"venue"
},
  "geometry": {"coordinates":[1.7055300474,41.3556137085],"type":"Point"}
}