{
  "type": "Feature",
  "properties": {
    "iso:country":"ES",
    "sg:address":"Carrer de Gran De Sant Andreu, 253",
    "sg:city":"Barcelona",
    "sg:orig_category":"Confecci\u00d3n De Trajes Para Se\u00d1oras",
    "sg:phone":"+34 933 46 15 22",
    "sg:postcode":"08030",
    "sg:province":"Barcelona",
    "wof:name":"Castells Navarro Laura",
    "wof:placetype":"venue"
},
  "geometry": {"coordinates":[2.1895470619,41.435256958],"type":"Point"}
}