{
  "type": "Feature",
  "properties": {
    "iso:country":"ES",
    "sg:address":"Calle de Modesto Lafuente, 42",
    "sg:city":"Aguilar Campoo",
    "sg:orig_category":"Carnicer\u00cdas, Carnicer\u00cdas",
    "sg:phone":"+34 979 12 31 78",
    "sg:postcode":"34800",
    "sg:province":"Palencia",
    "wof:name":"De La Fuente Diez Gonzalo",
    "wof:placetype":"venue"
},
  "geometry": {"coordinates":[-4.2625288963,42.7944412231],"type":"Point"}
}