{
  "type": "Feature",
  "properties": {
    "addr:full":"Calle de Barreros, 1 Gomecello Salamanca 37420",
    "addr:housenumber":"1",
    "addr:postcode":"37420",
    "addr:street":"Calle De Barreros",
    "iso:country":"ES",
    "sg:address":"Calle de Barreros, 1",
    "sg:city":"Gomecello",
    "sg:orig_category":"Fabricaci\u00d3n, Venta De Productos Base Farmac\u00c9uticos",
    "sg:phone":"+34 923 35 01 00",
    "sg:postcode":"37420",
    "sg:province":"Salamanca",
    "wof:name":"Vazquez Gomez Maria Angeles",
    "wof:placetype":"venue"
},
  "geometry": {"coordinates":[-5.5400629044,41.0433540344],"type":"Point"}
}