{
  "type": "Feature",
  "properties": {
    "addr:full":"Barr Salcedillo, S/n Galindo-salcedillo Vizcaya 48510",
    "addr:housenumber":"s",
    "addr:postcode":"48510",
    "addr:street":"/ N",
    "iso:country":"ES",
    "sg:address":"Barr Salcedillo, S/n",
    "sg:city":"Galindo-salcedillo",
    "sg:orig_category":"Empresas De Carpinter\u00cda De Madera",
    "sg:phone":"+34 944 92 20 91",
    "sg:postcode":"48510",
    "sg:province":"Vizcaya",
    "wof:name":"Carpinteria Gama C.b.",
    "wof:placetype":"venue"
},
  "geometry": {"coordinates":[-3.0369338989,43.3047294617],"type":"Point"}
}