{
  "type": "Feature",
  "properties": {
    "addr:full":"Calle de Herradores, 98 San Cristobal De La Laguna Santa Cruz De Tenerife 38201",
    "addr:housenumber":"98",
    "addr:postcode":"38201",
    "addr:street":"Calle De Herradores",
    "iso:country":"ES",
    "sg:address":"Calle de Herradores, 98",
    "sg:city":"San Cristobal De La Laguna",
    "sg:orig_category":"Bazares, Art\u00cdculos De Limpieza Y De Cocina (al Por Menor)",
    "sg:phone":"+34 922 25 08 20",
    "sg:postcode":"38201",
    "sg:province":"Santa Cruz De Tenerife",
    "wof:name":"Dopazo Marcos Avelino",
    "wof:placetype":"venue"
},
  "geometry": {"coordinates":[-16.3196201324,28.4899234772],"type":"Point"}
}