{
  "type": "Feature",
  "properties": {
    "iso:country":"ES",
    "sg:address":"Carr Verge De L'oreto, 4",
    "sg:city":"Alcudia",
    "sg:orig_category":"Cajas Para Embalar",
    "sg:phone":"+34 962 54 01 66",
    "sg:postcode":"46250",
    "sg:province":"Valencia",
    "wof:name":"Caixa Rural De L'alcudia",
    "wof:placetype":"venue"
},
  "geometry": {"coordinates":[-0.5060340166,39.1942558289],"type":"Point"}
}