{
  "type": "Feature",
  "properties": {
    "iso:country":"ES",
    "sg:address":"Calle de Virgen De La Fuensanta, 10",
    "sg:city":"Sevilla",
    "sg:orig_category":"Moda",
    "sg:phone":"+34 954 27 31 84",
    "sg:postcode":"41011",
    "sg:province":"Sevilla",
    "wof:name":"Gonzalez De La Puente Carmen",
    "wof:placetype":"venue"
},
  "geometry": {"coordinates":[-5.9970321655,37.3755073547],"type":"Point"}
}