{
  "type": "Feature",
  "properties": {
    "iso:country":"ES",
    "sg:address":"Grup San Diego, 7",
    "sg:city":"Sevilla",
    "sg:orig_category":"Producci\u00d3n, Distribuci\u00d3n De Electricidad",
    "sg:phone":"+34 954 94 56 40",
    "sg:postcode":"41008",
    "sg:province":"Sevilla",
    "wof:name":"Frias Vazquez Rafael",
    "wof:placetype":"venue"
},
  "geometry": {"coordinates":[-5.9673390388,37.4151115417],"type":"Point"}
}