{
  "type": "Feature",
  "properties": {
    "addr:full":"Calle de Kutxa, 3 Vitoria-gasteiz \u00c1lava 01012",
    "addr:housenumber":"3",
    "addr:postcode":"01012",
    "addr:street":"Calle De Kutxa",
    "iso:country":"ES",
    "sg:address":"Calle de Kutxa, 3",
    "sg:city":"Vitoria-gasteiz",
    "sg:orig_category":"Molduras, Junquillos, Listones Y Molduras Perforadas",
    "sg:phone":"+34 945 23 40 75",
    "sg:postcode":"01012",
    "sg:province":"\u00c1lava",
    "wof:name":"Juan Carlos Martin Mollor",
    "wof:placetype":"venue"
},
  "geometry": {"coordinates":[-2.6758260727,42.8514022827],"type":"Point"}
}