{
  "type": "Feature",
  "properties": {
    "iso:country":"ES",
    "sg:address":"Calle de San Juan De La Cruz, S/n",
    "sg:city":"Pastrana",
    "sg:orig_category":"Centros De Educaci\u00d3n Especial",
    "sg:phone":"+34 949 37 04 87",
    "sg:postcode":"19100",
    "sg:province":"Guadalajara",
    "wof:name":"Centro De Educacion De Adultos",
    "wof:placetype":"venue"
},
  "geometry": {"coordinates":[-2.9228289127,40.4174194336],"type":"Point"}
}