{
  "type": "Feature",
  "properties": {
    "addr:full":"Calle de Piqueras, 13 Logro\u00f1o La Rioja 26006",
    "addr:housenumber":"13",
    "addr:postcode":"26006",
    "addr:street":"Calle De Piqueras;Rioja",
    "iso:country":"ES",
    "sg:address":"Calle de Piqueras, 13",
    "sg:city":"Logro\u00f1o",
    "sg:orig_category":"Empresas De Pintura Y Revestimientos",
    "sg:phone":"+34 941 23 66 79",
    "sg:postcode":"26006",
    "sg:province":"La Rioja",
    "wof:name":"O\u00f1ate Fernandez Dario",
    "wof:placetype":"venue"
},
  "geometry": {"coordinates":[-2.4281690121,42.4548301697],"type":"Point"}
}