{
  "type": "Feature",
  "properties": {
    "addr:full":"Carrer de Palamos (de), 13 Tortosa Tarragona 43500",
    "addr:housenumber":"13",
    "addr:postcode":"43500",
    "addr:street":"Carrer De Palamos De",
    "iso:country":"ES",
    "sg:address":"Carrer de Palamos (de), 13",
    "sg:city":"Tortosa",
    "sg:orig_category":"Estudios, Instalaci\u00d3n De Climatizaci\u00d3n",
    "sg:phone":"+34 977 44 21 44",
    "sg:postcode":"43500",
    "sg:province":"Tarragona",
    "wof:name":"Tarazaga Teruel Jose Manuel",
    "wof:placetype":"venue"
},
  "geometry": {"coordinates":[0.525579989,40.7916908264],"type":"Point"}
}