{
  "type": "Feature",
  "properties": {
    "iso:country":"ES",
    "sg:address":"Feira, 25",
    "sg:city":"Ordes",
    "sg:orig_category":"Cr\u00cda De Animales",
    "sg:phone":"+34 981 68 06 09",
    "sg:postcode":"15680",
    "sg:province":"La Coru\u00f1a",
    "wof:name":"Gandogar S.l.",
    "wof:placetype":"venue"
},
  "geometry": {"coordinates":[-8.4109563828,43.0782928467],"type":"Point"}
}