{
  "type": "Feature",
  "properties": {
    "addr:full":"Calle de Lerida, 1 Logro\u00f1o La Rioja 26006",
    "addr:housenumber":"1",
    "addr:postcode":"26006",
    "addr:street":"Calle De Lerida;Rioja",
    "iso:country":"ES",
    "sg:address":"Calle de Lerida, 1",
    "sg:city":"Logro\u00f1o",
    "sg:orig_category":"Cables Y Hilos El\u00c9ctricos (fabricaci\u00d3n, Al Por Mayor)",
    "sg:phone":"+34 941 23 90 58",
    "sg:postcode":"26006",
    "sg:province":"La Rioja",
    "wof:name":"Sa Mercantil Europea 2089",
    "wof:placetype":"venue"
},
  "geometry": {"coordinates":[-2.4207389355,42.4621391296],"type":"Point"}
}