{
  "type": "Feature",
  "properties": {
    "addr:full":"Avda Barcelona, 25 Cuevas Almanzora Almer\u00eda 04610",
    "addr:housenumber":"25",
    "addr:postcode":"04610",
    "addr:street":"Avda Barcelona;Almeri\u0301A",
    "iso:country":"ES",
    "sg:address":"Avda Barcelona, 25",
    "sg:city":"Cuevas Almanzora",
    "sg:orig_category":"Ropa Para Se\u00d1oras Y Caballeros (al Por Menor)",
    "sg:phone":"+34 950 45 66 04",
    "sg:postcode":"04610",
    "sg:province":"Almer\u00eda",
    "wof:name":"Valero Torres Ana Manuela",
    "wof:placetype":"venue"
},
  "geometry": {"coordinates":[-1.8769919872,37.2949256897],"type":"Point"}
}