{
  "type": "Feature",
  "properties": {
    "iso:country":"ES",
    "sg:address":"Cra. Carrer de Disset, Km. 0100,0",
    "sg:city":"Ripoll",
    "sg:orig_category":"Electricidad: Instaladores",
    "sg:phone":"+34 972 70 30 98",
    "sg:postcode":"17500",
    "sg:province":"Girona",
    "wof:name":"Salt De La Escala",
    "wof:placetype":"venue"
},
  "geometry": {"coordinates":[2.1959049702,42.1965866089],"type":"Point"}
}