{
  "type": "Feature",
  "properties": {
    "addr:full":"Calvario, 32 Espinardo Murcia 30100",
    "addr:housenumber":"32",
    "addr:postcode":"30100",
    "addr:street":"Calvario",
    "iso:country":"ES",
    "sg:address":"Calvario, 32",
    "sg:city":"Espinardo",
    "sg:orig_category":"Cajas Para Embalar",
    "sg:phone":"+34 968 87 97 19",
    "sg:postcode":"30100",
    "sg:province":"Murcia",
    "sg:website":"www.cajamar.es",
    "wof:name":"Cajamar",
    "wof:placetype":"venue"
},
  "geometry": {"coordinates":[-1.1521010399,38.0111656189],"type":"Point"}
}