{
  "type": "Feature",
  "properties": {
    "iso:country":"ES",
    "sg:address":"Carrer de Mallorca, 27",
    "sg:city":"S. Boi Llobregat",
    "sg:orig_category":"Ropa Para Se\u00d1oras (al Por Menor)",
    "sg:phone":"+34 936 30 25 48",
    "sg:postcode":"08830",
    "sg:province":"Barcelona",
    "wof:name":"Lopez Montoya Natividad",
    "wof:placetype":"venue"
},
  "geometry": {"coordinates":[2.0436980724,41.3421516418],"type":"Point"}
}