{
  "type": "Feature",
  "properties": {
    "iso:country":"ES",
    "sg:address":"Calle de Vitoria, 58",
    "sg:city":"Burgos",
    "sg:orig_category":"Mutuas De Seguros",
    "sg:phone":"+34 947 20 71 61",
    "sg:postcode":"09004",
    "sg:province":"Burgos",
    "wof:name":"Fraternidad-muprexpa Mutua De Accidentes De Trabajo Y Enfermedades Profesionales",
    "wof:placetype":"venue"
},
  "geometry": {"coordinates":[-3.6875081062,42.3434791565],"type":"Point"}
}