{
  "type": "Feature",
  "properties": {
    "addr:full":"Plaz Moreno (del), 1 Cordoba C\u00f3rdoba 14001",
    "addr:postcode":"14001",
    "addr:street":"Del;Cordoba Co\u0301Rdoba",
    "iso:country":"ES",
    "sg:address":"Plaz Moreno (del), 1",
    "sg:city":"Cordoba",
    "sg:orig_category":"Abogados",
    "sg:phone":"+34 957 48 45 01",
    "sg:postcode":"14001",
    "sg:province":"C\u00f3rdoba",
    "wof:name":"Rios Vela Antonio",
    "wof:placetype":"venue"
},
  "geometry": {"coordinates":[-4.7779660225,37.8921394348],"type":"Point"}
}