{
  "type": "Feature",
  "properties": {
    "iso:country":"ES",
    "sg:address":"Calle de Casas De Campos, 33",
    "sg:city":"Malaga",
    "sg:orig_category":"Arquitectos",
    "sg:phone":"+34 952 60 96 17",
    "sg:postcode":"29001",
    "sg:province":"M\u00e1laga",
    "wof:name":"Bbarquitect Project Management Consulting S.l.",
    "wof:placetype":"venue"
},
  "geometry": {"coordinates":[-4.4243378639,36.7157096863],"type":"Point"}
}