{
  "type": "Feature",
  "properties": {
    "iso:country":"ES",
    "sg:address":"Calle de Vicente Camaron, 16",
    "sg:city":"Madrid",
    "sg:orig_category":"Ebanister\u00cda",
    "sg:phone":"+34 914 64 34 60",
    "sg:postcode":"28011",
    "sg:province":"Madrid",
    "wof:name":"Zazo Lopez Julian",
    "wof:placetype":"venue"
},
  "geometry": {"coordinates":[-3.7383329868,40.4061965942],"type":"Point"}
}