{
  "type": "Feature",
  "properties": {
    "addr:full":"Calle de Leon Xiii, 42 Elda Alicante 03600",
    "addr:housenumber":"42",
    "addr:postcode":"03600",
    "addr:street":"Calle De Leon Xiii",
    "iso:country":"ES",
    "sg:address":"Calle de Leon Xiii, 42",
    "sg:city":"Elda",
    "sg:orig_category":"Zapatos (al Por Menor)",
    "sg:phone":"+34 965 39 84 11",
    "sg:postcode":"03600",
    "sg:province":"Alicante",
    "wof:name":"Pilar Shoes S.l.",
    "wof:placetype":"venue"
},
  "geometry": {"coordinates":[-0.7884709835,38.4736671448],"type":"Point"}
}