{
  "type": "Feature",
  "properties": {
    "addr:full":"Calle de Metge Jose Bover, 5 Javea Alicante 03730",
    "addr:housenumber":"5",
    "addr:postcode":"03730",
    "addr:street":"Calle De Metge Jose Bover",
    "iso:country":"ES",
    "sg:address":"Calle de Metge Jose Bover, 5",
    "sg:city":"Javea",
    "sg:orig_category":"Molduras, Junquillos, Listones Y Molduras Perforadas",
    "sg:phone":"+34 966 46 04 86",
    "sg:postcode":"03730",
    "sg:province":"Alicante",
    "wof:name":"Martinez Sanchez C.b.",
    "wof:placetype":"venue"
},
  "geometry": {"coordinates":[0.1593299955,38.7889633179],"type":"Point"}
}