{
  "type": "Feature",
  "properties": {
    "iso:country":"ES",
    "sg:address":"Calle de Lele Del Pozo, 20",
    "sg:city":"Madrid",
    "sg:orig_category":"Empresarios",
    "sg:phone":"+34 917 85 70 97",
    "sg:postcode":"28053",
    "sg:province":"Madrid",
    "wof:name":"Lorenzo Nu\u00f1ez Francisco",
    "wof:placetype":"venue"
},
  "geometry": {"coordinates":[-3.6611030102,40.3727874756],"type":"Point"}
}