{
  "type": "Feature",
  "properties": {
    "addr:full":"Calle de La Esperanza, 13 Vitoria-gasteiz \u00c1lava 01002",
    "addr:housenumber":"13",
    "addr:postcode":"01002",
    "addr:street":"Calle De La Esperanza",
    "iso:country":"ES",
    "sg:address":"Calle de La Esperanza, 13",
    "sg:city":"Vitoria-gasteiz",
    "sg:orig_category":"Empresarios",
    "sg:phone":"+34 945 26 50 93",
    "sg:postcode":"01002",
    "sg:province":"\u00c1lava",
    "wof:name":"Fundacion Formacion Y Empleo",
    "wof:placetype":"venue"
},
  "geometry": {"coordinates":[-2.6674230099,42.849937439],"type":"Point"}
}