{
  "type": "Feature",
  "properties": {
    "iso:country":"ES",
    "sg:address":"Carrer de Mossen Jacint Verdaguer, 187",
    "sg:city":"Sant Vicen\u00c7 Dels Horts",
    "sg:orig_category":"Empresarios",
    "sg:phone":"+34 936 76 94 20",
    "sg:postcode":"08620",
    "sg:province":"Barcelona",
    "wof:name":"C.r.sant Vicens S.l.",
    "wof:placetype":"venue"
},
  "geometry": {"coordinates":[2.0070838928,41.3982048035],"type":"Point"}
}