{
  "type": "Feature",
  "properties": {
    "iso:country":"ES",
    "sg:address":"Plaz Mayor, 33",
    "sg:city":"Burgos",
    "sg:orig_category":"Juegos Y Juguetes (al Por Menor)",
    "sg:phone":"+34 947 25 67 27",
    "sg:postcode":"09003",
    "sg:province":"Burgos",
    "sg:website":"www.imaginarium.es",
    "wof:name":"Multisue\u00f1os S.l.",
    "wof:placetype":"venue"
},
  "geometry": {"coordinates":[-3.7020189762,42.3412208557],"type":"Point"}
}