{
  "type": "Feature",
  "properties": {
    "addr:full":"Ctra Cartama (de), 22 Alhaurin El Grande M\u00e1laga 29120",
    "addr:housenumber":"22",
    "addr:postcode":"29120",
    "addr:street":"Ctra Cartama De",
    "iso:country":"ES",
    "sg:address":"Ctra Cartama (de), 22",
    "sg:city":"Alhaurin El Grande",
    "sg:orig_category":"Art\u00cdculos De Decoraci\u00d3n",
    "sg:phone":"+34 952 49 12 84",
    "sg:postcode":"29120",
    "sg:province":"M\u00e1laga",
    "wof:name":"Bacarra S.a.",
    "wof:placetype":"venue"
},
  "geometry": {"coordinates":[-4.6809878349,36.6488418579],"type":"Point"}
}