{
  "type": "Feature",
  "properties": {
    "iso:country":"ES",
    "sg:address":"Calle de Amanecer, 2",
    "sg:city":"Ronda",
    "sg:orig_category":"Alimentaci\u00d3n General (al Por Menor)",
    "sg:phone":"+34 952 87 20 63",
    "sg:postcode":"29400",
    "sg:province":"M\u00e1laga",
    "wof:name":"Perez Corbacho Pedro",
    "wof:placetype":"venue"
},
  "geometry": {"coordinates":[-5.1650733948,36.7339897156],"type":"Point"}
}