{
  "type": "Feature",
  "properties": {
    "iso:country":"ES",
    "sg:address":"Carrer de Consellers, 21",
    "sg:city":"Llagostera",
    "sg:orig_category":"Inmobiliaria (agencias)",
    "sg:phone":"+34 972 83 18 30",
    "sg:postcode":"17240",
    "sg:province":"Girona",
    "wof:name":"Llagofinques. S.l.",
    "wof:placetype":"venue"
},
  "geometry": {"coordinates":[2.893748045,41.8264045715],"type":"Point"}
}