{
  "type": "Feature",
  "properties": {
    "addr:full":"Urb Pernasolas, 26 Villar Olalla Cuenca 16196",
    "addr:housenumber":"26",
    "addr:postcode":"16196",
    "addr:street":"Urb Pernasolas",
    "iso:country":"ES",
    "sg:address":"Urb Pernasolas, 26",
    "sg:city":"Villar Olalla",
    "sg:orig_category":"Venta, Instalaci\u00d3n De Calefacci\u00d3n",
    "sg:phone":"+34 969 26 72 00",
    "sg:postcode":"16196",
    "sg:province":"Cuenca",
    "wof:name":"Albanchez Culebras Juan Carlos",
    "wof:placetype":"venue"
},
  "geometry": {"coordinates":[-2.1340053082,40.0718345642],"type":"Point"}
}