{
  "type": "Feature",
  "properties": {
    "addr:full":"Calle de Navianos, S/n Aguilar Tera Zamora 49624",
    "addr:housenumber":"s",
    "addr:postcode":"49624",
    "addr:street":"Calle De Navianos;/ N",
    "iso:country":"ES",
    "sg:address":"Calle de Navianos, S/n",
    "sg:city":"Aguilar Tera",
    "sg:orig_category":"Empresas De Carpinter\u00cda Met\u00c1lica",
    "sg:phone":"+34 980 65 84 10",
    "sg:postcode":"49624",
    "sg:province":"Zamora",
    "wof:name":"Aluminios Aguilar De Tera S.l.",
    "wof:placetype":"venue"
},
  "geometry": {"coordinates":[-5.8431649208,41.983215332],"type":"Point"}
}