{
  "type": "Feature",
  "properties": {
    "iso:country":"ES",
    "sg:address":"C/ Calvari, 101",
    "sg:city":"Ripollet",
    "sg:orig_category":"Reposter\u00cdas",
    "sg:phone":"+34 935 80 86 48",
    "sg:postcode":"08291",
    "sg:province":"Barcelona",
    "wof:name":"Forn Call-2000 S.l.",
    "wof:placetype":"venue"
},
  "geometry": {"coordinates":[2.1594560146,41.4952583313],"type":"Point"}
}