{
  "type": "Feature",
  "properties": {
    "iso:country":"ES",
    "sg:address":"Calle de San Agustin, 10",
    "sg:city":"Miranda Ebro",
    "sg:orig_category":"Ropa Para Beb\u00c9s Y Ni\u00d1os (confecci\u00d3n, Al Por Mayor)",
    "sg:phone":"+34 947 31 37 02",
    "sg:postcode":"09200",
    "sg:province":"Burgos",
    "wof:name":"Perez Lopez Maria Felisa",
    "wof:placetype":"venue"
},
  "geometry": {"coordinates":[-2.9462471008,42.6848487854],"type":"Point"}
}