{
  "type": "Feature",
  "properties": {
    "addr:full":"Calle de Hemingway, 52 Malaga M\u00e1laga 29004",
    "addr:housenumber":"52",
    "addr:postcode":"29004",
    "addr:street":"Calle De Hemingway;Ma\u0301Laga",
    "iso:country":"ES",
    "sg:address":"Calle de Hemingway, 52",
    "sg:city":"Malaga",
    "sg:orig_category":"Bebidas",
    "sg:phone":"+34 952 24 40 12",
    "sg:postcode":"29004",
    "sg:province":"M\u00e1laga",
    "wof:name":"Logistica Y Distribucion Sayco S.l.",
    "wof:placetype":"venue"
},
  "geometry": {"coordinates":[-4.4801497459,36.6902122498],"type":"Point"}
}