{
  "type": "Feature",
  "properties": {
    "iso:country":"ES",
    "sg:address":"Pl L'esglesia, 1",
    "sg:city":"Colomers",
    "sg:orig_category":"Centros De Educaci\u00d3n Especial",
    "sg:phone":"+34 972 76 80 94",
    "sg:postcode":"17144",
    "sg:province":"Girona",
    "wof:name":"Ajuntament De Colomers. Escoles",
    "wof:placetype":"venue"
},
  "geometry": {"coordinates":[2.987226963,42.0841407776],"type":"Point"}
}