{
  "type": "Feature",
  "properties": {
    "addr:full":"Carrer de Duquessa D'orleans, 60 Barcelona Barcelona 08034",
    "addr:housenumber":"60",
    "addr:postcode":"08034",
    "addr:street":"Carrer De Duquessa D'Orleans",
    "iso:country":"ES",
    "sg:address":"Carrer de Duquessa D'orleans, 60",
    "sg:city":"Barcelona",
    "sg:orig_category":"Material Y Accesorios Para Soldaduras",
    "sg:phone":"+34 932 03 55 40",
    "sg:postcode":"08034",
    "sg:province":"Barcelona",
    "wof:name":"Bambu Technology. S.r.l.",
    "wof:placetype":"venue"
},
  "geometry": {"coordinates":[2.1183795929,41.3999862671],"type":"Point"}
}