{
  "type": "Feature",
  "properties": {
    "iso:country":"ES",
    "sg:address":"Carrer de Volta, 40",
    "sg:city":"Terrassa",
    "sg:orig_category":"Reposter\u00cdas",
    "sg:phone":"+34 937 80 90 49",
    "sg:postcode":"08224",
    "sg:province":"Barcelona",
    "wof:name":"Candelaria Castillo Rodrigo Y Cia C.b.",
    "wof:placetype":"venue"
},
  "geometry": {"coordinates":[2.0063679218,41.5632247925],"type":"Point"}
}