{
  "type": "Feature",
  "properties": {
    "iso:country":"ES",
    "sg:address":"Calle de Fuenclara, 72",
    "sg:city":"Villanueva Arzobispo",
    "sg:orig_category":"Muebles, Minoristas",
    "sg:phone":"+34 953 45 12 70",
    "sg:postcode":"23330",
    "sg:province":"Ja\u00e9n",
    "wof:name":"Muebles Carrascosa S.l.",
    "wof:placetype":"venue"
},
  "geometry": {"coordinates":[-3.0050089359,38.1647605896],"type":"Point"}
}