{
  "type": "Feature",
  "properties": {
    "iso:country":"ES",
    "sg:address":"Calle de Mansilla, 21",
    "sg:city":"Bejar",
    "sg:orig_category":"Caf\u00c9s, Bares, Cervecer\u00cdas",
    "sg:phone":"+34 923 40 22 98",
    "sg:postcode":"37700",
    "sg:province":"Salamanca",
    "wof:name":"Mateos Villafranca Bienvenido",
    "wof:placetype":"venue"
},
  "geometry": {"coordinates":[-5.7681560516,40.3873596191],"type":"Point"}
}