{
  "type": "Feature",
  "properties": {
    "addr:full":"Pl. Corazon De Maria, 3 Aranda Duero Burgos 09400",
    "addr:housenumber":"3",
    "addr:postcode":"09400",
    "addr:street":"Pl. Corazon;Maria",
    "iso:country":"ES",
    "sg:address":"Pl. Corazon De Maria, 3",
    "sg:city":"Aranda Duero",
    "sg:orig_category":"Ortopedia General",
    "sg:phone":"+34 947 50 88 05",
    "sg:postcode":"09400",
    "sg:province":"Burgos",
    "wof:name":"Alcalde Cobo Angel Miguel",
    "wof:placetype":"venue"
},
  "geometry": {"coordinates":[-3.6867694855,41.6694984436],"type":"Point"}
}