{
  "type": "Feature",
  "properties": {
    "iso:country":"ES",
    "sg:address":"Calle de Real Racing Club (del), 5",
    "sg:city":"Santander",
    "sg:orig_category":"Ingeniero",
    "sg:phone":"+34 942 27 18 01",
    "sg:postcode":"39005",
    "sg:province":"Cantabria",
    "wof:name":"Castagna  Giuseppe",
    "wof:placetype":"venue"
},
  "geometry": {"coordinates":[-3.7906749249,43.4751815796],"type":"Point"}
}