{
  "type": "Feature",
  "properties": {
    "addr:full":"Calle de Horizonte, 7 Mairena Aljarafe Sevilla 41927",
    "addr:housenumber":"7",
    "addr:postcode":"41927",
    "addr:street":"Calle De Horizonte",
    "iso:country":"ES",
    "sg:address":"Calle de Horizonte, 7",
    "sg:city":"Mairena Aljarafe",
    "sg:orig_category":"Albergues",
    "sg:phone":"+34 954 18 26 62",
    "sg:postcode":"41927",
    "sg:province":"Sevilla",
    "wof:name":"Lidelsur S.l.",
    "wof:placetype":"venue"
},
  "geometry": {"coordinates":[-6.0576820374,37.3548316956],"type":"Point"}
}