{
  "type": "Feature",
  "properties": {
    "addr:full":"Carrer de Potosi, 17 Lloret Mar Girona 17310",
    "addr:housenumber":"17",
    "addr:postcode":"17310",
    "addr:street":"Carrer De Potosi",
    "iso:country":"ES",
    "sg:address":"Carrer de Potosi, 17",
    "sg:city":"Lloret Mar",
    "sg:orig_category":"Molduras, Junquillos, Listones Y Molduras Perforadas",
    "sg:phone":"+34 972 36 24 28",
    "sg:postcode":"17310",
    "sg:province":"Girona",
    "wof:name":"Milroy  Andrew",
    "wof:placetype":"venue"
},
  "geometry": {"coordinates":[2.8402450085,41.698841095],"type":"Point"}
}