{
  "type": "Feature",
  "properties": {
    "addr:full":"Carrer de Napols, 45 Santa Coloma De Gramenet Barcelona 08921",
    "addr:housenumber":"45",
    "addr:postcode":"08921",
    "addr:street":"Carrer De Napols",
    "iso:country":"ES",
    "sg:address":"Carrer de Napols, 45",
    "sg:city":"Santa Coloma De Gramenet",
    "sg:orig_category":"Concepci\u00d3n Y Realizaci\u00d3n De Maquetas Profesionales Y Prototipos",
    "sg:phone":"+34 933 91 01 06",
    "sg:postcode":"08921",
    "sg:province":"Barcelona",
    "wof:name":"Garcia Garcia Rafael",
    "wof:placetype":"venue"
},
  "geometry": {"coordinates":[2.216342926,41.4532775879],"type":"Point"}
}