{
  "type": "Feature",
  "properties": {
    "iso:country":"ES",
    "sg:address":"Atv Madrid-toledo, Km. 0032,0",
    "sg:city":"Illescas",
    "sg:orig_category":"Muebles, Minoristas",
    "sg:phone":"+34 925 54 01 11",
    "sg:postcode":"45200",
    "sg:province":"Toledo",
    "sg:website":"www.banak.com",
    "wof:name":"House Mobel",
    "wof:placetype":"venue"
},
  "geometry": {"coordinates":[-3.8458640575,40.1230163574],"type":"Point"}
}