{
  "type": "Feature",
  "properties": {
    "addr:full":"Calle de Iglesia, 2 Pozuelo De Alarcon Madrid 28223",
    "addr:housenumber":"2",
    "addr:postcode":"28223",
    "addr:street":"Calle De Iglesia",
    "iso:country":"ES",
    "sg:address":"Calle de Iglesia, 2",
    "sg:city":"Pozuelo De Alarcon",
    "sg:orig_category":"Sociedades, Compa\u00d1\u00cdas Aseguradoras",
    "sg:phone":"+34 913 51 73 12",
    "sg:postcode":"28223",
    "sg:province":"Madrid",
    "wof:name":"Proyectos Y Seguros S.a.",
    "wof:placetype":"venue"
},
  "geometry": {"coordinates":[-3.8146278858,40.4355735779],"type":"Point"}
}