{
  "type": "Feature",
  "properties": {
    "addr:full":"Pol Ind Juncaril, 12 Peligros Granada 18210",
    "addr:housenumber":"12",
    "addr:postcode":"18210",
    "addr:street":"Juncaril",
    "iso:country":"ES",
    "sg:address":"Pol Ind Juncaril, 12",
    "sg:city":"Peligros",
    "sg:orig_category":"Industria Qu\u00cdmica",
    "sg:phone":"+34 958 43 09 78",
    "sg:postcode":"18210",
    "sg:province":"Granada",
    "wof:name":"Pinturas Carroceras G.c. S.l.",
    "wof:placetype":"venue"
},
  "geometry": {"coordinates":[-3.6276938915,37.2295036316],"type":"Point"}
}