{
  "type": "Feature",
  "properties": {
    "iso:country":"ES",
    "sg:address":"Calle de Joaquin Iglesias, 2",
    "sg:city":"Pola De Laviana",
    "sg:orig_category":"Confecci\u00d3n (fabricaci\u00d3n, Al Por Mayor)",
    "sg:phone":"+34 985 61 06 74",
    "sg:postcode":"33980",
    "sg:province":"Asturias",
    "wof:name":"Hevia Hevia Manuel",
    "wof:placetype":"venue"
},
  "geometry": {"coordinates":[-5.562125206,43.2456588745],"type":"Point"}
}