{
  "type": "Feature",
  "properties": {
    "addr:full":"Calle de Sotomayor, 1 Madrid Madrid 28003",
    "addr:housenumber":"1",
    "addr:postcode":"28003",
    "addr:street":"Calle De Sotomayor",
    "iso:country":"ES",
    "sg:address":"Calle de Sotomayor, 1",
    "sg:city":"Madrid",
    "sg:orig_category":"Cursos Particulares, Asistencia Escolar",
    "sg:phone":"+34 915 54 95 21",
    "sg:postcode":"28003",
    "sg:province":"Madrid",
    "wof:name":"Catalan Jimenez Pedro",
    "wof:placetype":"venue"
},
  "geometry": {"coordinates":[-3.7106978893,40.4458770752],"type":"Point"}
}