{
  "type": "Feature",
  "properties": {
    "iso:country":"ES",
    "sg:address":"Calle de Conde De Pe\u00d1alver, 12",
    "sg:city":"Madrid",
    "sg:orig_category":"Promotores Constructores",
    "sg:phone":"+34 915 75 56 59",
    "sg:postcode":"28006",
    "sg:province":"Madrid",
    "wof:name":"Consvector Madrid S.l.",
    "wof:placetype":"venue"
},
  "geometry": {"coordinates":[-3.67542696,40.4263153076],"type":"Point"}
}