{
  "type": "Feature",
  "properties": {
    "addr:full":"Avda General Franco, S/n Codo Zaragoza 50132",
    "addr:housenumber":"s / n",
    "addr:postcode":"50132",
    "addr:street":"Avda General Franco",
    "iso:country":"ES",
    "sg:address":"Avda General Franco, S/n",
    "sg:city":"Codo",
    "sg:orig_category":"Cajas Para Embalar",
    "sg:phone":"+34 976 83 07 85",
    "sg:postcode":"50132",
    "sg:province":"Zaragoza",
    "wof:name":"Caja Rural De Aragon S.coop Credito",
    "wof:placetype":"venue"
},
  "geometry": {"coordinates":[-0.6988099813,41.3328971863],"type":"Point"}
}