{
  "type": "Feature",
  "properties": {
    "addr:full":"Avda Alemania (de), 29 Playa Del Ingles Las Palmas 35100",
    "addr:housenumber":"29",
    "addr:postcode":"35100",
    "addr:street":"Avda Alemania De",
    "iso:country":"ES",
    "sg:address":"Avda Alemania (de), 29",
    "sg:city":"Playa Del Ingles",
    "sg:orig_category":"Importaci\u00d3n",
    "sg:phone":"+34 928 77 60 66",
    "sg:postcode":"35100",
    "sg:province":"Las Palmas",
    "wof:name":"Pegra-pharma Sl",
    "wof:placetype":"venue"
},
  "geometry": {"coordinates":[-15.5733470917,27.7500915527],"type":"Point"}
}