{
  "type": "Feature",
  "properties": {
    "iso:country":"ES",
    "sg:address":"Adelantado, 132",
    "sg:city":"Tacoronte",
    "sg:orig_category":"Mec\u00c1nico Del Autom\u00d3vil",
    "sg:phone":"+34 922 56 28 07",
    "sg:postcode":"38350",
    "sg:province":"Santa Cruz De Tenerife",
    "wof:name":"Reyes Figueroa Miguel Angel",
    "wof:placetype":"venue"
},
  "geometry": {"coordinates":[-16.4029331207,28.4825782776],"type":"Point"}
}