{
  "type": "Feature",
  "properties": {
    "addr:full":"Carrer de Lepant, 357 Barcelona Barcelona 08025",
    "addr:housenumber":"357",
    "addr:postcode":"08025",
    "addr:street":"Carrer De Lepant",
    "iso:country":"ES",
    "sg:address":"Carrer de Lepant, 357",
    "sg:city":"Barcelona",
    "sg:orig_category":"Electricidad: Resistencias",
    "sg:phone":"+34 934 36 10 95",
    "sg:postcode":"08025",
    "sg:province":"Barcelona",
    "wof:name":"Puigbo S. A.",
    "wof:placetype":"venue"
},
  "geometry": {"coordinates":[2.1708240509,41.4087524414],"type":"Point"}
}