{
  "type": "Feature",
  "properties": {
    "iso:country":"ES",
    "sg:address":"Rua Serafin Avenda\u00d1o, 12",
    "sg:city":"Vigo",
    "sg:orig_category":"Frutas, Legumbres Frescas Y Tempranas (al Por Menor)",
    "sg:phone":"+34 986 22 07 49",
    "sg:postcode":"36201",
    "sg:province":"Pontevedra",
    "wof:name":"Paz Garcia Maria Del Carmen",
    "wof:placetype":"venue"
},
  "geometry": {"coordinates":[-8.7126264572,42.2373847961],"type":"Point"}
}