{
  "type": "Feature",
  "properties": {
    "addr:full":"Calle de Bolivar, 22 Madrid Madrid 28045",
    "addr:housenumber":"22",
    "addr:postcode":"madrid;28045",
    "addr:street":"Calle De Bolivar",
    "iso:country":"ES",
    "sg:address":"Calle de Bolivar, 22",
    "sg:city":"Madrid",
    "sg:orig_category":"Administradores De Bienes Y Delegados De Comunidades De Propietarios",
    "sg:phone":"+34 915 28 60 22",
    "sg:postcode":"28045",
    "sg:province":"Madrid",
    "wof:name":"Gabinete De Peritaciones Carbel S.l.",
    "wof:placetype":"venue"
},
  "geometry": {"coordinates":[-3.6910440922,40.3923950195],"type":"Point"}
}