{
  "type": "Feature",
  "properties": {
    "addr:full":"Carrer de Torrent De Can Ninou, 1 Llevant Industrial Barcelona 08150",
    "addr:housenumber":"1",
    "addr:postcode":"08150",
    "addr:street":"Carrer De Torrent De Can Ninou",
    "iso:country":"ES",
    "sg:address":"Carrer de Torrent De Can Ninou, 1",
    "sg:city":"Llevant Industrial",
    "sg:orig_category":"Producci\u00d3n De Abonos Y De Fertilizantes",
    "sg:phone":"+34 935 62 03 95",
    "sg:postcode":"08150",
    "sg:province":"Barcelona",
    "wof:name":"Salvador Camps S.l.",
    "wof:placetype":"venue"
},
  "geometry": {"coordinates":[2.2293000221,41.5678787231],"type":"Point"}
}