{
  "type": "Feature",
  "properties": {
    "iso:country":"ES",
    "sg:address":"Calle de Luis Alvarez Cruz, 9",
    "sg:city":"Galletas",
    "sg:orig_category":"Agentes Generales De Seguros",
    "sg:phone":"+34 922 78 61 37",
    "sg:postcode":"38631",
    "sg:province":"Santa Cruz De Tenerife",
    "wof:name":"Crinse Gestiones S.l.",
    "wof:placetype":"venue"
},
  "geometry": {"coordinates":[-16.6544380188,28.0084762573],"type":"Point"}
}