{
  "type": "Feature",
  "properties": {
    "iso:country":"ES",
    "sg:address":"Ctra Castellar, 6",
    "sg:city":"Sentmenat",
    "sg:orig_category":"Agricultores, Agricultores",
    "sg:phone":"+34 937 15 02 81",
    "sg:postcode":"08181",
    "sg:province":"Barcelona",
    "wof:name":"Padro Robert Juan",
    "wof:placetype":"venue"
},
  "geometry": {"coordinates":[2.1373720169,41.6099853516],"type":"Point"}
}