{
  "type": "Feature",
  "properties": {
    "iso:country":"ES",
    "sg:address":"R Rubi (treumal D), S/n",
    "sg:city":"S. Antoni Calonge",
    "sg:orig_category":"Acondicionamiento, Mantenimiento De Jardines Y Parques",
    "sg:phone":"+34 972 65 12 22",
    "sg:postcode":"17252",
    "sg:province":"Girona",
    "wof:name":"Maso Caritx Luis",
    "wof:placetype":"venue"
},
  "geometry": {"coordinates":[3.1094601154,41.8569297791],"type":"Point"}
}