{
  "type": "Feature",
  "properties": {
    "addr:full":"Sector C, 120 Urb. Mas Camarena Valencia 46117",
    "addr:postcode":"46117",
    "addr:street":"C;Urb.",
    "iso:country":"ES",
    "sg:address":"Sector C, 120",
    "sg:city":"Urb. Mas Camarena",
    "sg:orig_category":"Agencias Y Agentes Comerciales, Representantes",
    "sg:phone":"+34 961 68 71 21",
    "sg:postcode":"46117",
    "sg:province":"Valencia",
    "wof:name":"Francisco Rubio Tatay Y Santiago Rubio Chulia C.b.",
    "wof:placetype":"venue"
},
  "geometry": {"coordinates":[-0.3768048882,39.4702377319],"type":"Point"}
}