{
  "type": "Feature",
  "properties": {
    "iso:country":"ES",
    "sg:address":"Calle de Plaza (de La), 104",
    "sg:city":"Pto Real",
    "sg:orig_category":"Bisuter\u00cda, Joyer\u00cda, Relojer\u00cda (al Por Menor)",
    "sg:phone":"+34 956 47 28 26",
    "sg:postcode":"11510",
    "sg:province":"C\u00e1diz",
    "wof:name":"Callealta Puga Maria Cristina",
    "wof:placetype":"venue"
},
  "geometry": {"coordinates":[-6.1898698807,36.5279350281],"type":"Point"}
}