{
  "type": "Feature",
  "properties": {
    "iso:country":"ES",
    "sg:address":"Desvio Distante, S/n",
    "sg:city":"Almeria",
    "sg:orig_category":"Desinfecci\u00d3n, Desinsectaci\u00d3n, Desratizaci\u00d3n",
    "sg:phone":"+34 950 24 03 33",
    "sg:postcode":"04007",
    "sg:province":"Almer\u00eda",
    "wof:name":"Garcia Romero Rafael Pablo",
    "wof:placetype":"venue"
},
  "geometry": {"coordinates":[-2.4356958866,36.8270874023],"type":"Point"}
}