{
  "type": "Feature",
  "properties": {
    "addr:full":"San Franzisko Kalea, 2 Elgoibar Guip\u00f9zcoa 20870",
    "addr:housenumber":"2",
    "addr:postcode":"20870",
    "addr:street":"San Franzisko Kalea;Guipu\u0300Zcoa",
    "iso:country":"ES",
    "sg:address":"San Franzisko Kalea, 2",
    "sg:city":"Elgoibar",
    "sg:orig_category":"Parafarmacias",
    "sg:phone":"+34 943 74 36 08",
    "sg:postcode":"20870",
    "sg:province":"Guip\u00f9zcoa",
    "wof:name":"Iriondo Zubiaurre Brigida",
    "wof:placetype":"venue"
},
  "geometry": {"coordinates":[-2.4150950909,43.2152786255],"type":"Point"}
}