{
  "type": "Feature",
  "properties": {
    "iso:country":"ES",
    "sg:address":"Rua Serra Dos Ancares, 18",
    "sg:city":"Lugo",
    "sg:orig_category":"Iglesias Evang\u00c9licas",
    "sg:phone":"+34 982 25 09 60",
    "sg:postcode":"27003",
    "sg:province":"Lugo",
    "wof:name":"Iglesia Cristiana Evangelica Buenas Noticias De Lugo",
    "wof:placetype":"venue"
},
  "geometry": {"coordinates":[-7.5577459335,43.0155982971],"type":"Point"}
}