{
  "type": "Feature",
  "properties": {
    "iso:country":"ES",
    "sg:address":"Kale Nagusia, 33",
    "sg:city":"Astigarraga",
    "sg:orig_category":"Caf\u00c9s, Bares, Cervecer\u00cdas",
    "sg:phone":"+34 943 33 26 68",
    "sg:postcode":"20115",
    "sg:province":"Guip\u00f9zcoa",
    "wof:name":"Marina San Nazario Del Rio Y Otro C.b.",
    "wof:placetype":"venue"
},
  "geometry": {"coordinates":[-1.9507540464,43.2802085876],"type":"Point"}
}