{
  "type": "Feature",
  "properties": {
    "iso:country":"ES",
    "sg:address":"Calle de Alcalde Jose Carlos Gonzalez, S/n",
    "sg:city":"Santa Maria De Guia",
    "sg:orig_category":"Contenedores (mercanc\u00cdas)",
    "sg:phone":"+34 928 55 33 39",
    "sg:postcode":"35450",
    "sg:province":"Las Palmas",
    "wof:name":"Gonzalez Hernandez Antonio",
    "wof:placetype":"venue"
},
  "geometry": {"coordinates":[-15.6343383789,28.141204834],"type":"Point"}
}