{
  "type": "Feature",
  "properties": {
    "addr:full":"Rcial Galera Playa, 1 Almu\u00f1ecar Granada 18690",
    "addr:housenumber":"1",
    "addr:postcode":"18690",
    "addr:street":"Playa",
    "iso:country":"ES",
    "sg:address":"Rcial Galera Playa, 1",
    "sg:city":"Almu\u00f1ecar",
    "sg:orig_category":"Ropa Para Se\u00d1oras (al Por Menor)",
    "sg:phone":"+34 958 88 08 27",
    "sg:postcode":"18690",
    "sg:province":"Granada",
    "wof:name":"Luba Modas Granada S.l.",
    "wof:placetype":"venue"
},
  "geometry": {"coordinates":[-3.6882688999,36.736743927],"type":"Point"}
}