{
  "type": "Feature",
  "properties": {
    "addr:full":"Calle de Victor De La Serna, 44 Madrid Madrid 28016",
    "addr:housenumber":"44",
    "addr:postcode":"madrid;28016",
    "addr:street":"Calle De Victor De La Serna",
    "iso:country":"ES",
    "sg:address":"Calle de Victor De La Serna, 44",
    "sg:city":"Madrid",
    "sg:orig_category":"Abogados",
    "sg:phone":"+34 913 50 61 07",
    "sg:postcode":"28016",
    "sg:province":"Madrid",
    "wof:name":"Diaz Marquina Abogados Cb",
    "wof:placetype":"venue"
},
  "geometry": {"coordinates":[-3.6709918976,40.4559707642],"type":"Point"}
}