{
  "type": "Feature",
  "properties": {
    "addr:full":"Carr Mossen Ferran, 16 Seros Lleida 25183",
    "addr:housenumber":"16",
    "addr:postcode":"25183",
    "addr:street":"Carr Mossen Ferran",
    "iso:country":"ES",
    "sg:address":"Carr Mossen Ferran, 16",
    "sg:city":"Seros",
    "sg:orig_category":"Guarder\u00cdas",
    "sg:phone":"+34 973 78 04 34",
    "sg:postcode":"25183",
    "sg:province":"Lleida",
    "wof:name":"Quitxalla S.c.p.",
    "wof:placetype":"venue"
},
  "geometry": {"coordinates":[0.4132210016,41.4649238586],"type":"Point"}
}