{
  "type": "Feature",
  "properties": {
    "iso:country":"ES",
    "sg:address":"Poli Vega De Arriba, S/n",
    "sg:city":"Mieres",
    "sg:orig_category":"Agentes, Concesionarios Y Sucursales De Veh\u00cdculos",
    "sg:phone":"+34 985 46 53 96",
    "sg:postcode":"33600",
    "sg:province":"Asturias",
    "wof:name":"Automocion Marcos S.l.",
    "wof:placetype":"venue"
},
  "geometry": {"coordinates":[-5.7194523811,43.235004425],"type":"Point"}
}