{
  "type": "Feature",
  "properties": {
    "iso:country":"ES",
    "sg:address":"Rua Cotaredo (do), 13",
    "sg:city":"Santiago De Compostela",
    "sg:orig_category":"Asociaciones Humanitarias, De Cooperaci\u00d3n, De Acci\u00d3n Social",
    "sg:phone":"+34 981 55 72 88",
    "sg:postcode":"15703",
    "sg:province":"La Coru\u00f1a",
    "wof:name":"De Oito A Oito S.c.",
    "wof:placetype":"venue"
},
  "geometry": {"coordinates":[-8.529088974,42.8851089478],"type":"Point"}
}