{
  "type": "Feature",
  "properties": {
    "addr:full":"Av Catalunya, 19 S. Cugat Valles Barcelona 08172",
    "addr:housenumber":"19",
    "addr:postcode":"08172",
    "addr:street":"Av Catalunya;S. Cugat Valles Barcelona",
    "iso:country":"ES",
    "sg:address":"Av Catalunya, 19",
    "sg:city":"S. Cugat Valles",
    "sg:orig_category":"Negocio De Materiales De Construcci\u00d3n",
    "sg:phone":"+34 936 75 69 65",
    "sg:postcode":"08172",
    "sg:province":"Barcelona",
    "wof:name":"Materiales Riomar S.l.",
    "wof:placetype":"venue"
},
  "geometry": {"coordinates":[2.0801439285,41.4725265503],"type":"Point"}
}