{
  "type": "Feature",
  "properties": {
    "iso:country":"ES",
    "sg:address":"Calle de Abades, 13",
    "sg:city":"Madrid",
    "sg:orig_category":"Confecci\u00d3n (fabricaci\u00d3n, Al Por Mayor)",
    "sg:phone":"+34 915 28 49 03",
    "sg:postcode":"28012",
    "sg:province":"Madrid",
    "wof:name":"Better Year Fashion S.l.",
    "wof:placetype":"venue"
},
  "geometry": {"coordinates":[-3.7059621811,40.4097518921],"type":"Point"}
}