{
  "type": "Feature",
  "properties": {
    "iso:country":"ES",
    "sg:address":"Plaz Jose Antonio, 5",
    "sg:city":"Villarta S. Juan",
    "sg:orig_category":"Iglesia Cat\u00d3lica",
    "sg:phone":"+34 926 64 00 60",
    "sg:postcode":"13210",
    "sg:province":"Ciudad Real",
    "wof:name":"Parroquia San Juan Bautista",
    "wof:placetype":"venue"
},
  "geometry": {"coordinates":[-3.4209120274,39.2350120544],"type":"Point"}
}