{
  "type": "Feature",
  "properties": {
    "iso:country":"ES",
    "sg:address":"Carr Llers, 5",
    "sg:city":"Figueres",
    "sg:orig_category":"Restaurantes",
    "sg:phone":"+34 972 51 03 77",
    "sg:postcode":"17600",
    "sg:province":"Girona",
    "wof:name":"Restaurant Antaviana S.c.",
    "wof:placetype":"venue"
},
  "geometry": {"coordinates":[2.9586679935,42.2674827576],"type":"Point"}
}