{
  "type": "Feature",
  "properties": {
    "iso:country":"ES",
    "sg:address":"Calle de Fuentidue\u00d1a (de), 22",
    "sg:city":"Alcobendas",
    "sg:orig_category":"Alimentaci\u00d3n General (al Por Menor)",
    "sg:phone":"+34 916 51 31 80",
    "sg:postcode":"28100",
    "sg:province":"Madrid",
    "wof:name":"Luli Me S.l.",
    "wof:placetype":"venue"
},
  "geometry": {"coordinates":[-3.6335771084,40.5380439758],"type":"Point"}
}