{
  "type": "Feature",
  "properties": {
    "addr:full":"Andra Mari Kalea (elkartegia), 37 Larrabetzu Vizcaya 48195",
    "addr:housenumber":"37",
    "addr:postcode":"48195",
    "addr:street":"Andra Mari Kalea Elkartegia",
    "iso:country":"ES",
    "sg:address":"Andra Mari Kalea (elkartegia), 37",
    "sg:city":"Larrabetzu",
    "sg:orig_category":"Metalizados",
    "sg:phone":"+34 944 55 84 67",
    "sg:postcode":"48195",
    "sg:province":"Vizcaya",
    "wof:name":"Predeco Xxi S.l",
    "wof:placetype":"venue"
},
  "geometry": {"coordinates":[-2.7971260548,43.256778717],"type":"Point"}
}