{
  "type": "Feature",
  "properties": {
    "addr:full":"Avda Zumalakarregi De, 5 Donostia-san Sebastian Guip\u00f9zcoa 20008",
    "addr:housenumber":"5",
    "addr:postcode":"20008",
    "addr:street":"Avda Zumalakarregi De",
    "iso:country":"ES",
    "sg:address":"Avda Zumalakarregi De, 5",
    "sg:city":"Donostia-san Sebastian",
    "sg:orig_category":"Inmobiliaria (agencias)",
    "sg:phone":"+34 943 31 77 57",
    "sg:postcode":"20008",
    "sg:province":"Guip\u00f9zcoa",
    "wof:name":"Alvarez Heredero Enrique",
    "wof:placetype":"venue"
},
  "geometry": {"coordinates":[-2.0017066002,43.3149032593],"type":"Point"}
}