{
  "type": "Feature",
  "properties": {
    "iso:country":"ES",
    "sg:address":"Pol Ind La Gangosa, S/n",
    "sg:city":"Parador Hortichuelas",
    "sg:orig_category":"Producci\u00d3n De Abonos Y De Fertilizantes",
    "sg:phone":"+34 950 34 90 35",
    "sg:postcode":"04720",
    "sg:province":"Almer\u00eda",
    "wof:name":"Consumomar S.c.a.",
    "wof:placetype":"venue"
},
  "geometry": {"coordinates":[-2.5741510391,36.8138160706],"type":"Point"}
}