{
  "type": "Feature",
  "properties": {
    "iso:country":"ES",
    "sg:address":"C/ Limon, 8",
    "sg:city":"Torrellano",
    "sg:orig_category":"Maquinaria Para Industrias Diversas",
    "sg:phone":"+34 965 68 39 55",
    "sg:postcode":"03320",
    "sg:province":"Alicante",
    "wof:name":"Maquinaria Y Servicios Rebolledo S.l.",
    "wof:placetype":"venue"
},
  "geometry": {"coordinates":[-0.5830870271,38.2905921936],"type":"Point"}
}