{
  "type": "Feature",
  "properties": {
    "iso:country":"ES",
    "sg:address":"Calle de Sor Valentina Miron, 19",
    "sg:city":"Plasencia",
    "sg:orig_category":"Carnicer\u00cdas, Carnicer\u00cdas",
    "sg:phone":"+34 927 41 82 91",
    "sg:postcode":"10600",
    "sg:province":"C\u00e1ceres",
    "wof:name":"Fernandez Garcia Julio",
    "wof:placetype":"venue"
},
  "geometry": {"coordinates":[-6.0905590057,40.0325965881],"type":"Point"}
}