{
  "type": "Feature",
  "properties": {
    "iso:country":"ES",
    "sg:address":"Carrer de Barcelona, 21",
    "sg:city":"Sant Vicen\u00c7 Dels Horts",
    "sg:orig_category":"Quincaller\u00cda (al Por Menor)",
    "sg:phone":"+34 936 56 14 59",
    "sg:postcode":"08620",
    "sg:province":"Barcelona",
    "wof:name":"Casanovas Pujadas Jaime",
    "wof:placetype":"venue"
},
  "geometry": {"coordinates":[2.0040550232,41.3991470337],"type":"Point"}
}