{
  "type": "Feature",
  "properties": {
    "iso:country":"ES",
    "sg:address":"Carrer de Verge (la), 13",
    "sg:city":"Muro Alcoy",
    "sg:orig_category":"Ense\u00d1anza: Idiomas",
    "sg:phone":"+34 965 53 04 62",
    "sg:postcode":"03830",
    "sg:province":"Alicante",
    "wof:name":"Cuenca Mateo Antonio",
    "wof:placetype":"venue"
},
  "geometry": {"coordinates":[-0.4414289892,38.7812538147],"type":"Point"}
}