{
  "type": "Feature",
  "properties": {
    "addr:full":"Carrer de Sol I Padris, 58 Sabadell Barcelona 08203",
    "addr:housenumber":"58",
    "addr:postcode":"08203",
    "addr:street":"Carrer De Sol I Padris",
    "iso:country":"ES",
    "sg:address":"Carrer de Sol I Padris, 58",
    "sg:city":"Sabadell",
    "sg:orig_category":"Inmobiliaria (agencias)",
    "sg:phone":"+34 937 12 00 47",
    "sg:postcode":"08203",
    "sg:province":"Barcelona",
    "wof:name":"Ajuntament De Sabadell",
    "wof:placetype":"venue"
},
  "geometry": {"coordinates":[2.1187384129,41.5373458862],"type":"Point"}
}