{
  "type": "Feature",
  "properties": {
    "iso:country":"ES",
    "sg:address":"Carr Vilar Petit, 18",
    "sg:city":"Blanes",
    "sg:orig_category":"Venta, Colocaci\u00d3n De Autoradios",
    "sg:phone":"+34 972 35 05 55",
    "sg:postcode":"17300",
    "sg:province":"Girona",
    "wof:name":"Massana Zaforas Josep Maria",
    "wof:placetype":"venue"
},
  "geometry": {"coordinates":[2.7823929787,41.6782150269],"type":"Point"}
}