{
  "type": "Feature",
  "properties": {
    "addr:full":"Calle de Miguel De Cervantes, 53 Vilamartin Valdeorras Ourense 32340",
    "addr:housenumber":"53",
    "addr:postcode":"32340",
    "addr:street":"Calle De Miguel De Cervantes",
    "iso:country":"ES",
    "sg:address":"Calle de Miguel De Cervantes, 53",
    "sg:city":"Vilamartin Valdeorras",
    "sg:orig_category":"Pizzer\u00cdas",
    "sg:phone":"+34 988 30 03 17",
    "sg:postcode":"32340",
    "sg:province":"Ourense",
    "wof:name":"Pizarras Gallegas S.a.",
    "wof:placetype":"venue"
},
  "geometry": {"coordinates":[-7.0608639717,42.414264679],"type":"Point"}
}