{
  "type": "Feature",
  "properties": {
    "addr:full":"Avda Baron De Warsage, 26 Calatayud Zaragoza 50300",
    "addr:housenumber":"26",
    "addr:postcode":"50300",
    "addr:street":"Avda Baron De Warsage",
    "iso:country":"ES",
    "sg:address":"Avda Baron De Warsage, 26",
    "sg:city":"Calatayud",
    "sg:orig_category":"Promotores Constructores",
    "sg:phone":"+34 976 88 33 04",
    "sg:postcode":"50300",
    "sg:province":"Zaragoza",
    "wof:name":"Promociones Warsage S.l.",
    "wof:placetype":"venue"
},
  "geometry": {"coordinates":[-1.6347409487,41.3542747498],"type":"Point"}
}