{
  "type": "Feature",
  "properties": {
    "iso:country":"ES",
    "sg:address":"Plaz Ayuntamiento, 2",
    "sg:city":"Castellnovo",
    "sg:orig_category":"Administraciones Regionales, Departamentales Y Locales",
    "sg:phone":"+34 964 13 73 05",
    "sg:postcode":"12413",
    "sg:province":"Castell\u00f3n",
    "wof:name":"Ayuntamiento De Castellnovo",
    "wof:placetype":"venue"
},
  "geometry": {"coordinates":[-0.4101420045,39.8707008362],"type":"Point"}
}