{
  "type": "Feature",
  "properties": {
    "addr:full":"Trss Creu, 37 Girona Girona 17002",
    "addr:housenumber":"37",
    "addr:postcode":"17002",
    "addr:street":"Creu",
    "iso:country":"ES",
    "sg:address":"Trss Creu, 37",
    "sg:city":"Girona",
    "sg:orig_category":"Ciencias Ocultas",
    "sg:phone":"+34 972 20 77 86",
    "sg:postcode":"17002",
    "sg:province":"Girona",
    "wof:name":"Bolsa Informacion S.l.",
    "wof:placetype":"venue"
},
  "geometry": {"coordinates":[2.8187448978,41.9808616638],"type":"Point"}
}