{
  "type": "Feature",
  "properties": {
    "iso:country":"ES",
    "sg:address":"Calle de Virgen De La Oliva, 2",
    "sg:city":"Madrid",
    "sg:orig_category":"Molduras, Junquillos, Listones Y Molduras Perforadas",
    "sg:phone":"+34 913 04 10 89",
    "sg:postcode":"28037",
    "sg:province":"Madrid",
    "wof:name":"Jimenez Candano Julian",
    "wof:placetype":"venue"
},
  "geometry": {"coordinates":[-3.6259748936,40.4305000305],"type":"Point"}
}