{
  "type": "Feature",
  "properties": {
    "iso:country":"ES",
    "sg:address":"Carrer de Sants, 266",
    "sg:city":"Barcelona",
    "sg:orig_category":"M\u00c9dicos: Medicina General Orientada A La Acupuntura",
    "sg:phone":"+34 934 90 66 66",
    "sg:postcode":"08028",
    "sg:province":"Barcelona",
    "wof:name":"Planes Oliveros Joaquin",
    "wof:placetype":"venue"
},
  "geometry": {"coordinates":[2.1277871132,41.375705719],"type":"Point"}
}