{
  "type": "Feature",
  "properties": {
    "iso:country":"ES",
    "sg:address":"Avda Ernesto Che Guevara, 11",
    "sg:city":"Perillo",
    "sg:orig_category":"Centros De Coordinaci\u00d3n",
    "sg:phone":"+34 981 63 54 81",
    "sg:postcode":"15172",
    "sg:province":"La Coru\u00f1a",
    "wof:name":"Barros Mosquera Josefa",
    "wof:placetype":"venue"
},
  "geometry": {"coordinates":[-8.3740053177,43.3324584961],"type":"Point"}
}