{
  "type": "Feature",
  "properties": {
    "iso:country":"ES",
    "sg:address":"Calle de Santo Domingo De Guzman, 13",
    "sg:city":"Villarrobledo",
    "sg:orig_category":"Ropa Para Se\u00d1oras Y Caballeros (al Por Menor)",
    "sg:phone":"+34 967 14 21 31",
    "sg:postcode":"02600",
    "sg:province":"Albacete",
    "wof:name":"Tiendas Serrano S.l.",
    "wof:placetype":"venue"
},
  "geometry": {"coordinates":[-2.5965309143,39.2736320496],"type":"Point"}
}