{
  "type": "Feature",
  "properties": {
    "addr:full":"Calle de Domingo Madan, S/n Santa Cruz De Tenerife Santa Cruz De Tenerife 38010",
    "addr:housenumber":"s / n",
    "addr:postcode":"38010",
    "addr:street":"Calle De Domingo Madan",
    "iso:country":"ES",
    "sg:address":"Calle de Domingo Madan, S/n",
    "sg:city":"Santa Cruz De Tenerife",
    "sg:orig_category":"Iglesia Cat\u00d3lica",
    "sg:phone":"+34 922 64 33 04",
    "sg:postcode":"38010",
    "sg:province":"Santa Cruz De Tenerife",
    "wof:name":"Parroquia De San Agustin",
    "wof:placetype":"venue"
},
  "geometry": {"coordinates":[-16.2814083099,28.4537181854],"type":"Point"}
}