{
  "type": "Feature",
  "properties": {
    "iso:country":"ES",
    "sg:address":"Pl Olimpia, 14",
    "sg:city":"Sabadell",
    "sg:orig_category":"Abogados",
    "sg:phone":"+34 937 23 41 81",
    "sg:postcode":"08206",
    "sg:province":"Barcelona",
    "wof:name":"Galisteo Lencastre Da Veiga Luis",
    "wof:placetype":"venue"
},
  "geometry": {"coordinates":[2.0908288956,41.5549430847],"type":"Point"}
}