{
  "type": "Feature",
  "properties": {
    "iso:country":"ES",
    "sg:address":"Carrer de Albeniz, 15",
    "sg:city":"Hospitalet Llobregat",
    "sg:orig_category":"Motocicletas (agentes, Concesionarios)",
    "sg:phone":"+34 934 40 63 94",
    "sg:postcode":"08906",
    "sg:province":"Barcelona",
    "wof:name":"Biker Power Custom Shop S.l.",
    "wof:placetype":"venue"
},
  "geometry": {"coordinates":[2.1060359478,41.3754997253],"type":"Point"}
}