{
  "type": "Feature",
  "properties": {
    "addr:full":"Plaz Pati De L'esglesia, 13 Cullera Valencia 46400",
    "addr:housenumber":"13",
    "addr:postcode":"46400",
    "addr:street":"Plaz;L'Esglesia",
    "iso:country":"ES",
    "sg:address":"Plaz Pati De L'esglesia, 13",
    "sg:city":"Cullera",
    "sg:orig_category":"Iglesia Cat\u00d3lica",
    "sg:phone":"+34 961 72 09 09",
    "sg:postcode":"46400",
    "sg:province":"Valencia",
    "wof:name":"Fornes Miralles Vicente",
    "wof:placetype":"venue"
},
  "geometry": {"coordinates":[-0.2545799911,39.1652297974],"type":"Point"}
}