{
  "type": "Feature",
  "properties": {
    "iso:country":"ES",
    "sg:address":"Calle de Derechos Humanos, 2",
    "sg:city":"Pizarra",
    "sg:orig_category":"Carnes De Carnicer\u00cda (al Por Mayor)",
    "sg:phone":"+34 952 48 42 51",
    "sg:postcode":"29560",
    "sg:province":"M\u00e1laga",
    "wof:name":"Incarfe S.l.",
    "wof:placetype":"venue"
},
  "geometry": {"coordinates":[-4.7103614807,36.7666549683],"type":"Point"}
}