{
  "type": "Feature",
  "properties": {
    "addr:full":"Arrufana, Km. 0004,6 Mos Pontevedra 36415",
    "addr:postcode":"36415",
    "addr:street":"Arrufana Km. 0004,6",
    "iso:country":"ES",
    "sg:address":"Arrufana, Km. 0004,6",
    "sg:city":"Mos",
    "sg:orig_category":"Suministros Para Carrocer\u00cdas",
    "sg:phone":"+34 986 33 42 00",
    "sg:postcode":"36415",
    "sg:province":"Pontevedra",
    "wof:name":"Incipresa S.a.",
    "wof:placetype":"venue"
},
  "geometry": {"coordinates":[-8.6081066132,42.201751709],"type":"Point"}
}