{
  "type": "Feature",
  "properties": {
    "addr:full":"Avda Maragatos, 11 Benavente Zamora 49600",
    "addr:housenumber":"11",
    "addr:postcode":"49600",
    "addr:street":"Avda Maragatos",
    "iso:country":"ES",
    "sg:address":"Avda Maragatos, 11",
    "sg:city":"Benavente",
    "sg:orig_category":"Molduras, Junquillos, Listones Y Molduras Perforadas",
    "sg:phone":"+34 980 63 46 22",
    "sg:postcode":"49600",
    "sg:province":"Zamora",
    "wof:name":"Llamazares Lopez Enrique",
    "wof:placetype":"venue"
},
  "geometry": {"coordinates":[-5.6770367622,42.0067558289],"type":"Point"}
}