{
  "type": "Feature",
  "properties": {
    "iso:country":"ES",
    "sg:address":"Calle de Aquiles Cuadra, 13",
    "sg:city":"Tudela",
    "sg:orig_category":"Ropa Para Se\u00d1oras (al Por Menor)",
    "sg:phone":"+34 948 41 17 18",
    "sg:postcode":"31500",
    "sg:province":"Navarra",
    "wof:name":"Charivari S.l.",
    "wof:placetype":"venue"
},
  "geometry": {"coordinates":[-1.4821481705,42.1872329712],"type":"Point"}
}