{
  "type": "Feature",
  "properties": {
    "addr:full":"Calle de Bierzo (del), 20 Fuenlabrada Madrid 28947",
    "addr:housenumber":"20",
    "addr:postcode":"28947",
    "addr:street":"Calle De Bierzo Del",
    "iso:country":"ES",
    "sg:address":"Calle de Bierzo (del), 20",
    "sg:city":"Fuenlabrada",
    "sg:orig_category":"Calderer\u00cda",
    "sg:phone":"+34 916 42 10 29",
    "sg:postcode":"28947",
    "sg:province":"Madrid",
    "sg:website":"www.suicalsa.com",
    "wof:name":"Suicalsa S.a.",
    "wof:placetype":"venue"
},
  "geometry": {"coordinates":[-3.7425630093,40.269657135],"type":"Point"}
}