{
  "type": "Feature",
  "properties": {
    "iso:country":"ES",
    "sg:address":"Cami Fanga, S/n",
    "sg:city":"Palafrugell",
    "sg:orig_category":"Madera Para Construcci\u00d3n E Industria",
    "sg:phone":"+34 972 30 66 30",
    "sg:postcode":"17200",
    "sg:province":"Girona",
    "wof:name":"Trefinos S.l.",
    "wof:placetype":"venue"
},
  "geometry": {"coordinates":[3.1533699036,41.9236946106],"type":"Point"}
}