{
  "type": "Feature",
  "properties": {
    "addr:full":"Calle de Plata, 5 Moraleja Enmedio Madrid 28950",
    "addr:housenumber":"5",
    "addr:postcode":"28950",
    "addr:street":"Calle De Plata",
    "iso:country":"ES",
    "sg:address":"Calle de Plata, 5",
    "sg:city":"Moraleja Enmedio",
    "sg:orig_category":"Producci\u00d3n, Comercio De Cereales",
    "sg:phone":"+34 916 09 44 73",
    "sg:postcode":"28950",
    "sg:province":"Madrid",
    "wof:name":"Castro Vara Pablo",
    "wof:placetype":"venue"
},
  "geometry": {"coordinates":[-3.8492081165,40.2625541687],"type":"Point"}
}