{
  "type": "Feature",
  "properties": {
    "addr:full":"Calle de Intendente Pablo De Olavide, 25 Baeza Ja\u00e9n 23440",
    "addr:housenumber":"25",
    "addr:postcode":"23440",
    "addr:street":"Calle De Intendente Pablo De Olavide",
    "iso:country":"ES",
    "sg:address":"Calle de Intendente Pablo De Olavide, 25",
    "sg:city":"Baeza",
    "sg:orig_category":"M\u00c9dicos: Estomatolog\u00cda",
    "sg:phone":"+34 953 74 82 23",
    "sg:postcode":"23440",
    "sg:province":"Ja\u00e9n",
    "wof:name":"Riola Gutierrez Maria Del Carmen",
    "wof:placetype":"venue"
},
  "geometry": {"coordinates":[-3.4661591053,37.9952583313],"type":"Point"}
}