{
  "type": "Feature",
  "properties": {
    "addr:full":"Avda Terra Cha, 87 Feira Do Monte Lugo 27377",
    "addr:housenumber":"87",
    "addr:postcode":"27377",
    "addr:street":"Avda Terra Cha",
    "iso:country":"ES",
    "sg:address":"Avda Terra Cha, 87",
    "sg:city":"Feira Do Monte",
    "sg:orig_category":"Alimentaci\u00d3n General (al Por Menor)",
    "sg:phone":"+34 982 52 00 95",
    "sg:postcode":"27377",
    "sg:province":"Lugo",
    "wof:name":"Aguiar Lago Jose Maria",
    "wof:placetype":"venue"
},
  "geometry": {"coordinates":[-7.562057972,43.2387084961],"type":"Point"}
}