{
  "type": "Feature",
  "properties": {
    "addr:full":"Av Roma, 67 Barcelona Barcelona 08029",
    "addr:housenumber":"67",
    "addr:postcode":"08029",
    "addr:street":"Av Roma",
    "iso:country":"ES",
    "sg:address":"Av Roma, 67",
    "sg:city":"Barcelona",
    "sg:orig_category":"Aluminio Y Aleaciones (producci\u00d3n, Transformaci\u00d3n, Negocio)",
    "sg:phone":"+34 934 30 70 21",
    "sg:postcode":"08029",
    "sg:province":"Barcelona",
    "wof:name":"Schuco International K.g.",
    "wof:placetype":"venue"
},
  "geometry": {"coordinates":[2.1493659019,41.3834686279],"type":"Point"}
}