{
  "type": "Feature",
  "properties": {
    "iso:country":"ES",
    "sg:address":"Calle de Cervantes, 24",
    "sg:city":"Oviedo",
    "sg:orig_category":"Equipo De Refrigeraci\u00d3n Industrial",
    "sg:phone":"+34 985 25 10 91",
    "sg:postcode":"33004",
    "sg:province":"Asturias",
    "wof:name":"Frimago S. L.",
    "wof:placetype":"venue"
},
  "geometry": {"coordinates":[-5.8567700386,43.3637924194],"type":"Point"}
}