{
  "type": "Feature",
  "properties": {
    "iso:country":"ES",
    "sg:address":"Avda Europa (de), 34",
    "sg:city":"San Cristobal",
    "sg:orig_category":"Sociedades, Compa\u00d1\u00cdas Aseguradoras",
    "sg:phone":"+34 968 47 19 26",
    "sg:postcode":"30800",
    "sg:province":"Murcia",
    "sg:website":"www.agroseguros.com",
    "wof:name":"Vera Sicilia Correduria De Seguros S. L.",
    "wof:placetype":"venue"
},
  "geometry": {"coordinates":[-1.6905640364,37.680557251],"type":"Point"}
}