{
  "type": "Feature",
  "properties": {
    "addr:full":"Avda Carril (del), 83 Archena Murcia 30600",
    "addr:housenumber":"83",
    "addr:postcode":"30600",
    "addr:street":"Avda Carril Del",
    "iso:country":"ES",
    "sg:address":"Avda Carril (del), 83",
    "sg:city":"Archena",
    "sg:orig_category":"Inmobiliaria (agencias)",
    "sg:phone":"+34 968 67 31 12",
    "sg:postcode":"30600",
    "sg:province":"Murcia",
    "wof:name":"Inmobiliaria Aia Vb S.l.",
    "wof:placetype":"venue"
},
  "geometry": {"coordinates":[-1.2968431711,38.1151580811],"type":"Point"}
}