{
  "type": "Feature",
  "properties": {
    "iso:country":"ES",
    "sg:address":"Calle de Fuensanta, 97",
    "sg:city":"Villanueva Arzobispo",
    "sg:orig_category":"Cl\u00cdnicas Dentales",
    "sg:phone":"+34 953 45 13 01",
    "sg:postcode":"23330",
    "sg:province":"Ja\u00e9n",
    "wof:name":"Centro De Protesis Y Salud Dental S.l.",
    "wof:placetype":"venue"
},
  "geometry": {"coordinates":[-3.0053329468,38.1641311646],"type":"Point"}
}