{
  "type": "Feature",
  "properties": {
    "iso:country":"ES",
    "sg:address":"Calle de Santiago De Compostela, 94",
    "sg:city":"Madrid",
    "sg:orig_category":"Molduras, Junquillos, Listones Y Molduras Perforadas",
    "sg:phone":"+34 913 86 70 54",
    "sg:postcode":"28035",
    "sg:province":"Madrid",
    "wof:name":"Delmer Hosteleria S.l.",
    "wof:placetype":"venue"
},
  "geometry": {"coordinates":[-3.720541954,40.4770355225],"type":"Point"}
}