{
  "type": "Feature",
  "properties": {
    "addr:full":"Calle de Perez Crespo, 2 Le\u00f3n Le\u00f3n 24002",
    "addr:housenumber":"2",
    "addr:postcode":"24002",
    "addr:street":"Calle De Perez Crespo;Leo\u0301N",
    "iso:country":"ES",
    "sg:address":"Calle de Perez Crespo, 2",
    "sg:city":"Le\u00f3n",
    "sg:orig_category":"Loter\u00cda Y T\u00d3mbola",
    "sg:phone":"+34 987 22 71 67",
    "sg:postcode":"24002",
    "sg:province":"Le\u00f3n",
    "wof:name":"Rodriguez Alonso Eugenio-francisco",
    "wof:placetype":"venue"
},
  "geometry": {"coordinates":[-5.5727801323,42.6034393311],"type":"Point"}
}