{
  "type": "Feature",
  "properties": {
    "iso:country":"ES",
    "sg:address":"Pl Catalunya, 6",
    "sg:city":"Ulldecona",
    "sg:orig_category":"Quincaller\u00cda (al Por Menor)",
    "sg:phone":"+34 977 57 33 76",
    "sg:postcode":"43550",
    "sg:province":"Tarragona",
    "wof:name":"Ferreteria Alfara S.l.",
    "wof:placetype":"venue"
},
  "geometry": {"coordinates":[0.4428859949,40.5969200134],"type":"Point"}
}