{
  "type": "Feature",
  "properties": {
    "iso:country":"ES",
    "sg:address":"Calle de Feria (la), 25",
    "sg:city":"Fernan Nu\u00e7ez",
    "sg:orig_category":"Ense\u00d1anza: Comercio, Gesti\u00d3n, Inform\u00c1tica",
    "sg:phone":"+34 957 38 20 87",
    "sg:postcode":"14520",
    "sg:province":"C\u00f3rdoba",
    "wof:name":"Ruiz Muoz Francisco",
    "wof:placetype":"venue"
},
  "geometry": {"coordinates":[-4.7239189148,37.6722068787],"type":"Point"}
}