{
  "type": "Feature",
  "properties": {
    "addr:full":"Avda Lerida (de), 15 Monzon Huesca 22400",
    "addr:housenumber":"15",
    "addr:postcode":"22400",
    "addr:street":"Avda Lerida De",
    "iso:country":"ES",
    "sg:address":"Avda Lerida (de), 15",
    "sg:city":"Monzon",
    "sg:orig_category":"Abogados",
    "sg:phone":"+34 974 40 41 12",
    "sg:postcode":"22400",
    "sg:province":"Huesca",
    "wof:name":"Campo Saura Angel Javier",
    "wof:placetype":"venue"
},
  "geometry": {"coordinates":[0.1934259981,41.9125328064],"type":"Point"}
}