{
  "type": "Feature",
  "properties": {
    "addr:full":"Ctra. Cadiz-malaga, S/n S. Roque C\u00e1diz 11360",
    "addr:housenumber":"s",
    "addr:postcode":"11360",
    "addr:street":"Ctra. Cadiz-Malaga;/ N S. Roque Ca\u0301Diz",
    "iso:country":"ES",
    "sg:address":"Ctra. Cadiz-malaga, S/n",
    "sg:city":"S. Roque",
    "sg:orig_category":"Venta De Caravanas, Casas M\u00d3viles, Camping",
    "sg:phone":"+34 956 69 40 41",
    "sg:postcode":"11360",
    "sg:province":"C\u00e1diz",
    "wof:name":"Leon Perez Manuel",
    "wof:placetype":"venue"
},
  "geometry": {"coordinates":[-5.3897438049,36.209690094],"type":"Point"}
}