{
  "type": "Feature",
  "properties": {
    "addr:full":"Calle de Camara La, S/n Aviles Asturias 33402",
    "addr:postcode":"33402",
    "addr:street":"Calle De Camara La S / N",
    "iso:country":"ES",
    "sg:address":"Calle de Camara La, S/n",
    "sg:city":"Aviles",
    "sg:orig_category":"Bisuter\u00cda, Joyer\u00cda, Relojer\u00cda (al Por Menor)",
    "sg:phone":"+34 985 52 51 40",
    "sg:postcode":"33402",
    "sg:province":"Asturias",
    "wof:name":"Asfee 2003 S.l.",
    "wof:placetype":"venue"
},
  "geometry": {"coordinates":[-5.9233317375,43.5563163757],"type":"Point"}
}