{
  "type": "Feature",
  "properties": {
    "addr:full":"Parque Girasoles, 12 Tarancon Cuenca 16400",
    "addr:housenumber":"12",
    "addr:postcode":"16400",
    "iso:country":"ES",
    "sg:address":"Parque Girasoles, 12",
    "sg:city":"Tarancon",
    "sg:orig_category":"Ense\u00d1anza Variada",
    "sg:phone":"+34 969 32 32 71",
    "sg:postcode":"16400",
    "sg:province":"Cuenca",
    "wof:name":"Academia Girasoles S.l.",
    "wof:placetype":"venue"
},
  "geometry": {"coordinates":[-3.0183458328,40.0081329346],"type":"Point"}
}