{
  "type": "Feature",
  "properties": {
    "iso:country":"ES",
    "sg:address":"Pol Ind El Portal, S/n",
    "sg:city":"Jerez",
    "sg:orig_category":"Producci\u00d3n, Distribuci\u00d3n De Electricidad",
    "sg:phone":"+34 956 14 32 56",
    "sg:postcode":"11408",
    "sg:province":"C\u00e1diz",
    "wof:name":"Alvarez Beltran S.a.",
    "wof:placetype":"venue"
},
  "geometry": {"coordinates":[-6.1633043289,36.6765556335],"type":"Point"}
}