{
  "type": "Feature",
  "properties": {
    "addr:full":"Calle de Parroco Antonio Gomez Villalobos, 85 Sevilla Sevilla 41006",
    "addr:housenumber":"85",
    "addr:postcode":"41006",
    "addr:street":"Calle De Parroco Antonio Gomez Villalobos",
    "iso:country":"ES",
    "sg:address":"Calle de Parroco Antonio Gomez Villalobos, 85",
    "sg:city":"Sevilla",
    "sg:orig_category":"Promotores Constructores",
    "sg:phone":"+34 954 66 06 31",
    "sg:postcode":"41006",
    "sg:province":"Sevilla",
    "wof:name":"Construcciones Borsegur S.l.",
    "wof:placetype":"venue"
},
  "geometry": {"coordinates":[-5.9519062042,37.3706550598],"type":"Point"}
}