{
  "type": "Feature",
  "properties": {
    "addr:full":"Carrer de Solsona, 124 Terrassa Barcelona 08227",
    "addr:housenumber":"124",
    "addr:postcode":"08227",
    "addr:street":"Carrer De Solsona",
    "iso:country":"ES",
    "sg:address":"Carrer de Solsona, 124",
    "sg:city":"Terrassa",
    "sg:orig_category":"Promotores Constructores",
    "sg:phone":"+34 937 83 71 17",
    "sg:postcode":"08227",
    "sg:province":"Barcelona",
    "wof:name":"Reformas Estrada S.l.",
    "wof:placetype":"venue"
},
  "geometry": {"coordinates":[2.0378329754,41.5744094849],"type":"Point"}
}