{
  "type": "Feature",
  "properties": {
    "iso:country":"ES",
    "sg:address":"Bijuters, S/n",
    "sg:city":"Ciutadella Menorca",
    "sg:orig_category":"Transportes Por Carretera: Lotes Completos, Mercanc\u00cdas Diversas",
    "sg:phone":"+34 971 38 04 86",
    "sg:postcode":"07760",
    "sg:province":"Islas Baleares",
    "wof:name":"Pons Pons Francisco",
    "wof:placetype":"venue"
},
  "geometry": {"coordinates":[3.8534450531,40.0113945007],"type":"Point"}
}