{
  "type": "Feature",
  "properties": {
    "iso:country":"ES",
    "sg:address":"Av Girona, 61",
    "sg:city":"S. Gregori",
    "sg:orig_category":"T\u00c9cnicos Veterinarios",
    "sg:phone":"+34 972 42 87 06",
    "sg:postcode":"17150",
    "sg:province":"Girona",
    "wof:name":"Fitlab S. C.",
    "wof:placetype":"venue"
},
  "geometry": {"coordinates":[2.7581830025,41.9904670715],"type":"Point"}
}