{
  "type": "Feature",
  "properties": {
    "addr:full":"Carrer de Nules, 12 Roquetes Tarragona 43520",
    "addr:housenumber":"12",
    "addr:postcode":"43520",
    "addr:street":"Carrer De Nules",
    "iso:country":"ES",
    "sg:address":"Carrer de Nules, 12",
    "sg:city":"Roquetes",
    "sg:orig_category":"Cajas De Ahorro",
    "sg:phone":"+34 977 50 33 46",
    "sg:postcode":"43520",
    "sg:province":"Tarragona",
    "sg:website":"www.caixasabadell.es",
    "wof:name":"Caixa D'estalvis Sabadell",
    "wof:placetype":"venue"
},
  "geometry": {"coordinates":[0.5042520165,40.8180198669],"type":"Point"}
}