{
  "type": "Feature",
  "properties": {
    "iso:country":"ES",
    "sg:address":"Ctra Torrequebradilla, S/n",
    "sg:city":"Jaen",
    "sg:orig_category":"Asilos De Ancianos. Centros Privados",
    "sg:phone":"+34 953 26 27 60",
    "sg:postcode":"23009",
    "sg:province":"Ja\u00e9n",
    "wof:name":"Diputacion Provincial De Jaen",
    "wof:placetype":"venue"
},
  "geometry": {"coordinates":[-3.7778189182,37.7850456238],"type":"Point"}
}