{
  "type": "Feature",
  "properties": {
    "addr:full":"Mcdo Sto Domingo, S/n Iru\u00f1a Navarra 31001",
    "addr:housenumber":"s / n",
    "addr:postcode":"31001",
    "addr:street":"Sto Domingo",
    "iso:country":"ES",
    "sg:address":"Mcdo Sto Domingo, S/n",
    "sg:city":"Iru\u00f1a",
    "sg:orig_category":"Carnicer\u00cdas, Carnicer\u00cdas",
    "sg:phone":"+34 948 22 35 12",
    "sg:postcode":"31001",
    "sg:province":"Navarra",
    "wof:name":"Yarnoz Casamayor Angel",
    "wof:placetype":"venue"
},
  "geometry": {"coordinates":[-1.6432837248,42.8191337585],"type":"Point"}
}