{
  "type": "Feature",
  "properties": {
    "iso:country":"ES",
    "sg:address":"Calle de Nave, 28",
    "sg:city":"Valencia",
    "sg:orig_category":"Ropa Para Se\u00d1oras (al Por Menor)",
    "sg:phone":"+34 963 51 34 34",
    "sg:postcode":"46003",
    "sg:province":"Valencia",
    "wof:name":"Palau Tur Antonio",
    "wof:placetype":"venue"
},
  "geometry": {"coordinates":[-0.3747780025,39.4774703979],"type":"Point"}
}