{
  "type": "Feature",
  "properties": {
    "iso:country":"ES",
    "sg:address":"Avda Pablo Neruda, 80",
    "sg:city":"Madrid",
    "sg:orig_category":"Cl\u00cdnicas Dentales",
    "sg:phone":"+34 917 77 60 78",
    "sg:postcode":"28018",
    "sg:province":"Madrid",
    "wof:name":"Fabian Jimenez Juana",
    "wof:placetype":"venue"
},
  "geometry": {"coordinates":[-3.653660059,40.3816452026],"type":"Point"}
}