{
  "type": "Feature",
  "properties": {
    "iso:country":"ES",
    "sg:address":"Calle de Reina Fabiola, 22",
    "sg:city":"Zaragoza",
    "sg:orig_category":"Papeler\u00cdas, Librer\u00cdas",
    "sg:phone":"+34 976 42 99 35",
    "sg:postcode":"50008",
    "sg:province":"Zaragoza",
    "wof:name":"Azuara Brualla Maria Teresa",
    "wof:placetype":"venue"
},
  "geometry": {"coordinates":[-0.8745747805,41.6452522278],"type":"Point"}
}