{
  "type": "Feature",
  "properties": {
    "iso:country":"ES",
    "sg:address":"Carr Major Sant Jaume, 10",
    "sg:city":"Villarreal",
    "sg:orig_category":"Panader\u00cdas, Panader\u00cdas",
    "sg:phone":"+34 964 52 07 05",
    "sg:postcode":"12540",
    "sg:province":"Castell\u00f3n",
    "wof:name":"Bonet Penalver Rosa",
    "wof:placetype":"venue"
},
  "geometry": {"coordinates":[-0.1004490033,39.9375762939],"type":"Point"}
}