{
  "type": "Feature",
  "properties": {
    "iso:country":"ES",
    "sg:address":"Calle de Xuquer, 5",
    "sg:city":"Alzira",
    "sg:orig_category":"Pe\u00d1as Y Asociaciones Varias",
    "sg:phone":"+34 962 41 08 42",
    "sg:postcode":"46600",
    "sg:province":"Valencia",
    "wof:name":"Asociacion Comarcal De Edificacion Y Alba\u00f1ileria",
    "wof:placetype":"venue"
},
  "geometry": {"coordinates":[-0.4371264875,39.1525230408],"type":"Point"}
}