{
  "type": "Feature",
  "properties": {
    "iso:country":"ES",
    "sg:address":"Calle de Federico Sanchez Bedoya, 20",
    "sg:city":"Sevilla",
    "sg:orig_category":"Centros De Coordinaci\u00d3n",
    "sg:phone":"+34 954 21 49 13",
    "sg:postcode":"41001",
    "sg:province":"Sevilla",
    "wof:name":"Mejias Pe\u00f1uelas Rafael",
    "wof:placetype":"venue"
},
  "geometry": {"coordinates":[-5.9955091476,37.3859405518],"type":"Point"}
}