{
  "type": "Feature",
  "properties": {
    "iso:country":"ES",
    "sg:address":"Prje El Chorrillo, S/n",
    "sg:city":"Sax",
    "sg:orig_category":"Ebanister\u00cda",
    "sg:phone":"+34 966 96 80 77",
    "sg:postcode":"03630",
    "sg:province":"Alicante",
    "sg:website":"www.cavasdepuros.com",
    "wof:name":"Zest Creaciones En Madera S.l.",
    "wof:placetype":"venue"
},
  "geometry": {"coordinates":[-0.8198775053,38.555683136],"type":"Point"}
}