{
  "type": "Feature",
  "properties": {
    "addr:full":"Calle de Fray Luis De Leon, 17 Valladolid Valladolid 47002",
    "addr:housenumber":"17",
    "addr:postcode":"47002",
    "addr:street":"Calle De Fray Luis De Leon",
    "iso:country":"ES",
    "sg:address":"Calle de Fray Luis De Leon, 17",
    "sg:city":"Valladolid",
    "sg:orig_category":"Papeler\u00cdas, Librer\u00cdas",
    "sg:phone":"+34 983 39 68 83",
    "sg:postcode":"47002",
    "sg:province":"Valladolid",
    "wof:name":"Mateos Garcia Catalina",
    "wof:placetype":"venue"
},
  "geometry": {"coordinates":[-4.7220292091,41.6506881714],"type":"Point"}
}