{
  "type": "Feature",
  "properties": {
    "iso:country":"ES",
    "sg:address":"Calle de Padre Angel, 7",
    "sg:city":"S. Vicente Barquera",
    "sg:orig_category":"Carnicer\u00cdas, Carnicer\u00cdas",
    "sg:phone":"+34 942 71 16 60",
    "sg:postcode":"39540",
    "sg:province":"Cantabria",
    "wof:name":"Ortiz Sa\u00d1udo Jose Tomas",
    "wof:placetype":"venue"
},
  "geometry": {"coordinates":[-4.3988361359,43.3829154968],"type":"Point"}
}