{
  "type": "Feature",
  "properties": {
    "addr:full":"Calle de Paseo, S/n Chirivel Almer\u00eda 04825",
    "addr:housenumber":"s",
    "addr:postcode":"04825",
    "addr:street":"Calle De Paseo;/ N;Almeri\u0301A",
    "iso:country":"ES",
    "sg:address":"Calle de Paseo, S/n",
    "sg:city":"Chirivel",
    "sg:orig_category":"Administraciones Regionales, Departamentales Y Locales",
    "sg:phone":"+34 950 41 30 01",
    "sg:postcode":"04825",
    "sg:province":"Almer\u00eda",
    "wof:name":"Ayuntamiento De Chirivel",
    "wof:placetype":"venue"
},
  "geometry": {"coordinates":[-2.2638673782,37.5957565308],"type":"Point"}
}