{
  "type": "Feature",
  "properties": {
    "iso:country":"ES",
    "sg:address":"Ctra Sanlucar-benacazon, Km. 0037,5",
    "sg:city":"Sanlucar Mayor",
    "sg:orig_category":"Ense\u00d1anza, Formaci\u00d3n Profesional: Aprendizaje",
    "sg:phone":"+34 955 70 03 86",
    "sg:postcode":"41800",
    "sg:province":"Sevilla",
    "wof:name":"Mancomunidad Guadalquivir",
    "wof:placetype":"venue"
},
  "geometry": {"coordinates":[-6.1956338882,37.3855361938],"type":"Point"}
}