{
  "type": "Feature",
  "properties": {
    "iso:country":"ES",
    "sg:address":"Calle de Henao, 7",
    "sg:city":"Bilbao",
    "sg:orig_category":"Asesor\u00cda Sobre Comunicaci\u00d3n De Empresas",
    "sg:phone":"+34 944 24 81 11",
    "sg:postcode":"48009",
    "sg:province":"Vizcaya",
    "wof:name":"Asesoria Integral Berupres S.l.",
    "wof:placetype":"venue"
},
  "geometry": {"coordinates":[-2.9302592278,43.264251709],"type":"Point"}
}