{
  "type": "Feature",
  "properties": {
    "iso:country":"ES",
    "sg:address":"Calle de Literato Azorin, 27",
    "sg:city":"Cheste",
    "sg:orig_category":"Fibras De Vidrio",
    "sg:phone":"+34 962 51 06 53",
    "sg:postcode":"46380",
    "sg:province":"Valencia",
    "wof:name":"Perez Mirisol Miguel Angel",
    "wof:placetype":"venue"
},
  "geometry": {"coordinates":[-0.6898108721,39.4959068298],"type":"Point"}
}