{
  "type": "Feature",
  "properties": {
    "addr:full":"Geranios, 33 Torrevieja Alicante 03180",
    "addr:housenumber":"33",
    "addr:postcode":"03180",
    "addr:street":"Geranios",
    "iso:country":"ES",
    "sg:address":"Geranios, 33",
    "sg:city":"Torrevieja",
    "sg:orig_category":"Productores Recolectores, Venta Directa De Vinos",
    "sg:phone":"+34 966 70 03 98",
    "sg:postcode":"03180",
    "sg:province":"Alicante",
    "wof:name":"Vanden Eeckhoudt George",
    "wof:placetype":"venue"
},
  "geometry": {"coordinates":[-0.6558700204,38.0096702576],"type":"Point"}
}