{
  "type": "Feature",
  "properties": {
    "iso:country":"ES",
    "sg:address":"Garmendipe Kalea, 7",
    "sg:city":"Azpeitia",
    "sg:orig_category":"Veh\u00cdculos De Ocasi\u00d3n",
    "sg:phone":"+34 943 81 19 15",
    "sg:postcode":"20730",
    "sg:province":"Guip\u00f9zcoa",
    "wof:name":"Aiertza Autoak S.l.",
    "wof:placetype":"venue"
},
  "geometry": {"coordinates":[-2.2610747814,43.1776351929],"type":"Point"}
}