{
  "type": "Feature",
  "properties": {
    "addr:full":"Carrer de Salvador Espriu, S/n Barcelona Barcelona 08...",
    "addr:housenumber":"s / n",
    "addr:street":"Carrer De Salvador Espriu",
    "iso:country":"ES",
    "sg:address":"Carrer de Salvador Espriu, S/n",
    "sg:city":"Barcelona",
    "sg:orig_category":"Suministros Y Materiales Industriales",
    "sg:phone":"+34 932 30 08 00",
    "sg:postcode":"08...",
    "sg:province":"Barcelona",
    "wof:name":"Grizzly Hispania S.l.",
    "wof:placetype":"venue"
},
  "geometry": {"coordinates":[2.1941030025,41.3868255615],"type":"Point"}
}