{
  "type": "Feature",
  "properties": {
    "iso:country":"ES",
    "sg:address":"Calle de San Marcos, 5",
    "sg:city":"Manzanares",
    "sg:orig_category":"Herboristas (al Por Menor)",
    "sg:phone":"+34 926 61 20 16",
    "sg:postcode":"13200",
    "sg:province":"Ciudad Real",
    "wof:name":"Ferrer Caballero Maria Gracia",
    "wof:placetype":"venue"
},
  "geometry": {"coordinates":[-3.3674819469,38.9991798401],"type":"Point"}
}