{
  "type": "Feature",
  "properties": {
    "addr:full":"Carr Pere Compte, 18 Girona Girona 17005",
    "addr:housenumber":"18",
    "addr:postcode":"17005",
    "addr:street":"Carr Pere Compte",
    "iso:country":"ES",
    "sg:address":"Carr Pere Compte, 18",
    "sg:city":"Girona",
    "sg:orig_category":"Dietistas",
    "sg:phone":"+34 972 24 59 71",
    "sg:postcode":"17005",
    "sg:province":"Girona",
    "wof:name":"Vendrell Rocha Maria Jesus",
    "wof:placetype":"venue"
},
  "geometry": {"coordinates":[2.8106980324,41.9776573181],"type":"Point"}
}