{
  "type": "Feature",
  "properties": {
    "iso:country":"ES",
    "sg:address":"Calle de Calderetas, 60",
    "sg:city":"S. Bartolome",
    "sg:orig_category":"Asesor\u00cda Sobre Comunicaci\u00d3n De Empresas",
    "sg:phone":"+34 928 52 08 46",
    "sg:postcode":"35550",
    "sg:province":"Las Palmas",
    "wof:name":"Gonzalez Martin Pablo Nicolas",
    "wof:placetype":"venue"
},
  "geometry": {"coordinates":[-13.6140909195,29.0028743744],"type":"Point"}
}