{
  "type": "Feature",
  "properties": {
    "iso:country":"ES",
    "sg:address":"Calle de Gines De Castro Y Alvarez, 12",
    "sg:city":"Arrecife",
    "sg:orig_category":"Abogados",
    "sg:phone":"+34 928 81 12 41",
    "sg:postcode":"35500",
    "sg:province":"Las Palmas",
    "wof:name":"Martinon Armas Antonio",
    "wof:placetype":"venue"
},
  "geometry": {"coordinates":[-13.5477247238,28.9590873718],"type":"Point"}
}