{
  "type": "Feature",
  "properties": {
    "addr:full":"Carr Arquebisbe Polou, 5 Gandia Valencia 46700",
    "addr:housenumber":"5",
    "addr:postcode":"46700",
    "addr:street":"Carr Arquebisbe Polou;Valencia",
    "iso:country":"ES",
    "sg:address":"Carr Arquebisbe Polou, 5",
    "sg:city":"Gandia",
    "sg:orig_category":"Confecci\u00d3n De Trajes Para Se\u00d1oras",
    "sg:phone":"+34 962 95 13 17",
    "sg:postcode":"46700",
    "sg:province":"Valencia",
    "wof:name":"Bejarano Insua Eva",
    "wof:placetype":"venue"
},
  "geometry": {"coordinates":[-0.1913339943,38.960735321],"type":"Point"}
}