{
  "type": "Feature",
  "properties": {
    "addr:full":"Carr Mar, De La, 11 Muro Islas Baleares 07440",
    "addr:housenumber":"11",
    "addr:postcode":"07440",
    "addr:street":"Carr Mar De La",
    "iso:country":"ES",
    "sg:address":"Carr Mar, De La, 11",
    "sg:city":"Muro",
    "sg:orig_category":"Empresas De Carpinter\u00cda Met\u00c1lica",
    "sg:phone":"+34 971 86 06 43",
    "sg:postcode":"07440",
    "sg:province":"Islas Baleares",
    "wof:name":"Serra Martorell Pau",
    "wof:placetype":"venue"
},
  "geometry": {"coordinates":[3.0891199112,39.7588310242],"type":"Point"}
}