{
  "type": "Feature",
  "properties": {
    "iso:country":"ES",
    "sg:address":"Carrer de Himalaia, 14",
    "sg:city":"Sabadell",
    "sg:orig_category":"Empresas De Limpieza",
    "sg:phone":"+34 937 24 36 54",
    "sg:postcode":"08207",
    "sg:province":"Barcelona",
    "wof:name":"Garcia Aranda Antonia",
    "wof:placetype":"venue"
},
  "geometry": {"coordinates":[2.0902860165,41.5713920593],"type":"Point"}
}