{
  "type": "Feature",
  "properties": {
    "iso:country":"ES",
    "sg:address":"Calle de Dolores, 16",
    "sg:city":"S. Fernando",
    "sg:orig_category":"Abogados",
    "sg:phone":"+34 956 59 12 42",
    "sg:postcode":"11100",
    "sg:province":"C\u00e1diz",
    "wof:name":"Rios Jimenez Miguel",
    "wof:placetype":"venue"
},
  "geometry": {"coordinates":[-6.1969437599,36.4635658264],"type":"Point"}
}