{
  "type": "Feature",
  "properties": {
    "addr:full":"Carrer de Anselm Clave, 96 Olesa Montserrat Barcelona 08640",
    "addr:housenumber":"96",
    "addr:postcode":"08640",
    "addr:street":"Carrer De Anselm Clave",
    "iso:country":"ES",
    "sg:address":"Carrer de Anselm Clave, 96",
    "sg:city":"Olesa Montserrat",
    "sg:orig_category":"\u00d3ptica: Instrumentos (fabricaci\u00d3n)",
    "sg:phone":"+34 937 78 12 39",
    "sg:postcode":"08640",
    "sg:province":"Barcelona",
    "wof:name":"Mateu Serrano Francesc Ramon",
    "wof:placetype":"venue"
},
  "geometry": {"coordinates":[1.8962999582,41.5422096252],"type":"Point"}
}