{
  "type": "Feature",
  "properties": {
    "addr:full":"Calle de Cronista Medardo Lainez, S/n Cazorla Ja\u00e9n 23470",
    "addr:housenumber":"s / n",
    "addr:postcode":"23470",
    "addr:street":"Calle De Cronista Medardo Lainez",
    "iso:country":"ES",
    "sg:address":"Calle de Cronista Medardo Lainez, S/n",
    "sg:city":"Cazorla",
    "sg:orig_category":"Ense\u00d1anza Variada",
    "sg:phone":"+34 953 71 00 56",
    "sg:postcode":"23470",
    "sg:province":"Ja\u00e9n",
    "wof:name":"Molina Mi\u00f1ana Carlos",
    "wof:placetype":"venue"
},
  "geometry": {"coordinates":[-3.0029060841,37.909702301],"type":"Point"}
}