{
  "type": "Feature",
  "properties": {
    "addr:full":"Carr Arnau Gatell, 5 Blanes Girona 17300",
    "addr:housenumber":"5",
    "addr:postcode":"17300",
    "addr:street":"Carr Arnau Gatell",
    "iso:country":"ES",
    "sg:address":"Carr Arnau Gatell, 5",
    "sg:city":"Blanes",
    "sg:orig_category":"Molduras, Junquillos, Listones Y Molduras Perforadas",
    "sg:phone":"+34 972 35 56 40",
    "sg:postcode":"17300",
    "sg:province":"Girona",
    "wof:name":"Plats De Cuina Blanes S.l.",
    "wof:placetype":"venue"
},
  "geometry": {"coordinates":[2.7821829319,41.676361084],"type":"Point"}
}