{
  "type": "Feature",
  "properties": {
    "addr:full":"Plaz Doctor Alvarez, 3 Almu\u00f1ecar Granada 18690",
    "addr:housenumber":"3",
    "addr:postcode":"18690",
    "addr:street":"Alvarez",
    "iso:country":"ES",
    "sg:address":"Plaz Doctor Alvarez, 3",
    "sg:city":"Almu\u00f1ecar",
    "sg:orig_category":"Inform\u00c1tica, Ofim\u00c1tica (estudios, Asesor\u00cda, Ingenier\u00cda, Formaci\u00d3n)",
    "sg:phone":"+34 958 63 32 03",
    "sg:postcode":"18690",
    "sg:province":"Granada",
    "wof:name":"Gonzalez Diaz Antonio",
    "wof:placetype":"venue"
},
  "geometry": {"coordinates":[-3.6918139458,36.7359886169],"type":"Point"}
}