{
  "type": "Feature",
  "properties": {
    "iso:country":"ES",
    "sg:address":"Ctra Calanda, 9",
    "sg:city":"Alca\u00f1iz",
    "sg:orig_category":"Piedra, Vidrio, Cer\u00c1mica Y Porcelana",
    "sg:phone":"+34 978 83 05 11",
    "sg:postcode":"44600",
    "sg:province":"Teruel",
    "wof:name":"Ca\u00f1ada S. A.",
    "wof:placetype":"venue"
},
  "geometry": {"coordinates":[-0.1319710016,41.0463256836],"type":"Point"}
}