{
  "type": "Feature",
  "properties": {
    "addr:full":"Carretera Mas Del Jutge, S/n Torrent Valencia 46900",
    "addr:housenumber":"s / n",
    "addr:postcode":"46900",
    "addr:street":"Carretera Mas Del Jutge;Valencia",
    "iso:country":"ES",
    "sg:address":"Carretera Mas Del Jutge, S/n",
    "sg:city":"Torrent",
    "sg:orig_category":"Piedra Natural",
    "sg:phone":"+34 961 58 03 42",
    "sg:postcode":"46900",
    "sg:province":"Valencia",
    "wof:name":"Medina Almerich Miguel Angel",
    "wof:placetype":"venue"
},
  "geometry": {"coordinates":[-0.522349,39.4335289001],"type":"Point"}
}