{
  "type": "Feature",
  "properties": {
    "addr:full":"Calle de Antonio Machado, 1 Lugones Asturias 33420",
    "addr:housenumber":"1",
    "addr:postcode":"33420",
    "addr:street":"Calle De Antonio Machado",
    "iso:country":"ES",
    "sg:address":"Calle de Antonio Machado, 1",
    "sg:city":"Lugones",
    "sg:orig_category":"Ense\u00d1anza, Formaci\u00d3n Profesional: Aprendizaje",
    "sg:phone":"+34 985 26 20 28",
    "sg:postcode":"33420",
    "sg:province":"Asturias",
    "wof:name":"Principado De Asturias",
    "wof:placetype":"venue"
},
  "geometry": {"coordinates":[-5.8076791763,43.4024848938],"type":"Point"}
}