{
  "type": "Feature",
  "properties": {
    "iso:country":"ES",
    "sg:address":"Carrer de Viriat, S/n",
    "sg:city":"Barcelona",
    "sg:orig_category":"Autob\u00das (explotaci\u00d3n Y Servicios De)",
    "sg:phone":"+34 934 90 40 00",
    "sg:postcode":"08014",
    "sg:province":"Barcelona",
    "sg:website":"www.eurolines.es",
    "wof:name":"Viajes Eurolines S.a.",
    "wof:placetype":"venue"
},
  "geometry": {"coordinates":[2.1414599419,41.3805007935],"type":"Point"}
}