{
  "type": "Feature",
  "properties": {
    "iso:country":"ES",
    "sg:address":"Carrer de Joan De Peguera, 42",
    "sg:city":"Barcelona",
    "sg:orig_category":"Internados & Ense\u00d1anza Privada",
    "sg:phone":"+34 934 56 93 02",
    "sg:postcode":"08026",
    "sg:province":"Barcelona",
    "wof:name":"Colegio Calasanz En Barcelona Hijas De Maria Religiosas De Las Escuelas Pias Escolapias. Prov. Catal",
    "wof:placetype":"venue"
},
  "geometry": {"coordinates":[2.1819410324,41.4130210876],"type":"Point"}
}