{
  "type": "Feature",
  "properties": {
    "addr:full":"Madeixes, 4 Ontinyent Valencia 46870",
    "addr:housenumber":"4",
    "addr:postcode":"46870",
    "addr:street":"Madeixes",
    "iso:country":"ES",
    "sg:address":"Madeixes, 4",
    "sg:city":"Ontinyent",
    "sg:orig_category":"Confecci\u00d3n (fabricaci\u00d3n, Al Por Mayor)",
    "sg:phone":"+34 962 38 40 88",
    "sg:postcode":"46870",
    "sg:province":"Valencia",
    "wof:name":"Acolchatex S.l.",
    "wof:placetype":"venue"
},
  "geometry": {"coordinates":[-0.587179482,38.8263473511],"type":"Point"}
}