{
  "type": "Feature",
  "properties": {
    "addr:full":"Plaz Cronista Chabret, 8 Sagunt Valencia 46500",
    "addr:housenumber":"8",
    "addr:postcode":"46500",
    "addr:street":"Plaz Cronista Chabret",
    "iso:country":"ES",
    "sg:address":"Plaz Cronista Chabret, 8",
    "sg:city":"Sagunt",
    "sg:orig_category":"Peluqueros: De Se\u00d1oras",
    "sg:phone":"+34 962 66 62 62",
    "sg:postcode":"46500",
    "sg:province":"Valencia",
    "wof:name":"Trujillo Moreno Isabel",
    "wof:placetype":"venue"
},
  "geometry": {"coordinates":[-0.2775610089,39.6811027527],"type":"Point"}
}