{
  "type": "Feature",
  "properties": {
    "addr:full":"Calle de Doctor Jesus Quesada Sanz, 7 San Andres Murcia 30005",
    "addr:housenumber":"7",
    "addr:postcode":"30005",
    "addr:street":"Calle De Doctor Jesus Quesada Sanz",
    "iso:country":"ES",
    "sg:address":"Calle de Doctor Jesus Quesada Sanz, 7",
    "sg:city":"San Andres",
    "sg:orig_category":"Carnicer\u00cdas, Carnicer\u00cdas",
    "sg:phone":"+34 968 29 35 25",
    "sg:postcode":"30005",
    "sg:province":"Murcia",
    "wof:name":"Martinez Esquiva Jose",
    "wof:placetype":"venue"
},
  "geometry": {"coordinates":[-1.1401462555,37.9858512878],"type":"Point"}
}