{
  "type": "Feature",
  "properties": {
    "addr:full":"Calle de Jose Manuel Pedregal, 14 000a Aviles Asturias 33401",
    "addr:housenumber":"14 000a",
    "addr:postcode":"33401",
    "addr:street":"Calle De Jose Manuel Pedregal",
    "iso:country":"ES",
    "sg:address":"Calle de Jose Manuel Pedregal, 14 000a",
    "sg:city":"Aviles",
    "sg:orig_category":"Agentes Generales De Seguros",
    "sg:phone":"+34 985 93 47 18",
    "sg:postcode":"33401",
    "sg:province":"Asturias",
    "wof:name":"Diaz Calvo Asesores S.l.",
    "wof:placetype":"venue"
},
  "geometry": {"coordinates":[-5.9263720512,43.5596389771],"type":"Point"}
}