{
  "type": "Feature",
  "properties": {
    "addr:full":"Carrer de Doctor Ferran, 13 Rubi Barcelona 08191",
    "addr:housenumber":"13",
    "addr:postcode":"08191",
    "addr:street":"Carrer De Doctor Ferran",
    "iso:country":"ES",
    "sg:address":"Carrer de Doctor Ferran, 13",
    "sg:city":"Rubi",
    "sg:orig_category":"Fabricaci\u00d3n De Distribuidores Autom\u00c1ticos",
    "sg:phone":"+34 936 97 87 62",
    "sg:postcode":"08191",
    "sg:province":"Barcelona",
    "wof:name":"J.a.v. Service 2002 S.l.",
    "wof:placetype":"venue"
},
  "geometry": {"coordinates":[2.0356791019,41.4810180664],"type":"Point"}
}