{
  "type": "Feature",
  "properties": {
    "addr:full":"Calle de Leon Y Castillo, 55 Pto. Rosario Las Palmas 35600",
    "addr:housenumber":"55",
    "addr:postcode":"35600",
    "addr:street":"Calle De Leon Y Castillo;Pto. Rosario Las",
    "iso:country":"ES",
    "sg:address":"Calle de Leon Y Castillo, 55",
    "sg:city":"Pto. Rosario",
    "sg:orig_category":"Ingenier\u00cda, Centros De Estudios (diversos)",
    "sg:phone":"+34 928 53 01 18",
    "sg:postcode":"35600",
    "sg:province":"Las Palmas",
    "wof:name":"Grupo Arquitectura Y Dise\u00f1o Y Urbanismo Y Planificacion S.l.",
    "wof:placetype":"venue"
},
  "geometry": {"coordinates":[-13.8664073944,28.5007095337],"type":"Point"}
}