{
  "type": "Feature",
  "properties": {
    "addr:full":"A(pol Ind Oeste), S/n S. Gines Murcia 30169",
    "addr:housenumber":"s",
    "addr:postcode":"30169",
    "addr:street":"Ind Oeste;/ N S.",
    "iso:country":"ES",
    "sg:address":"A(pol Ind Oeste), S/n",
    "sg:city":"S. Gines",
    "sg:orig_category":"Moquetas, Alfombras (al Por Menor)",
    "sg:phone":"+34 968 88 56 04",
    "sg:postcode":"30169",
    "sg:province":"Murcia",
    "wof:name":"Olimpic Import S.l.",
    "wof:placetype":"venue"
},
  "geometry": {"coordinates":[-1.177366972,37.9589958191],"type":"Point"}
}