{
  "type": "Feature",
  "properties": {
    "addr:full":"Carrer de Josep Maria De Sagarra, 34 Vendrell Tarragona 43700",
    "addr:housenumber":"34",
    "addr:postcode":"43700",
    "addr:street":"Carrer De Josep Maria De Sagarra",
    "iso:country":"ES",
    "sg:address":"Carrer de Josep Maria De Sagarra, 34",
    "sg:city":"Vendrell",
    "sg:orig_category":"Centros Y Asociaciones De Gesti\u00d3n Homologados",
    "sg:phone":"+34 977 66 24 08",
    "sg:postcode":"43700",
    "sg:province":"Tarragona",
    "wof:name":"Perez Diaz Juan Francisco",
    "wof:placetype":"venue"
},
  "geometry": {"coordinates":[1.5296750069,41.2185516357],"type":"Point"}
}