{
  "type": "Feature",
  "properties": {
    "iso:country":"ES",
    "sg:address":"Calle de Legion V, 21",
    "sg:city":"Merida",
    "sg:orig_category":"Arquitectos",
    "sg:phone":"+34 924 31 95 82",
    "sg:postcode":"06800",
    "sg:province":"Badajoz",
    "wof:name":"Ingenieria Emerita S.l.",
    "wof:placetype":"venue"
},
  "geometry": {"coordinates":[-6.3395690918,38.9130744934],"type":"Point"}
}