{
  "type": "Feature",
  "properties": {
    "addr:full":"Calle de Carretera De Murcia, 18 Angeles -apolonia Murcia 30815",
    "addr:housenumber":"18",
    "addr:postcode":"30815",
    "addr:street":"Calle De Carretera De Murcia",
    "iso:country":"ES",
    "sg:address":"Calle de Carretera De Murcia, 18",
    "sg:city":"Angeles -apolonia",
    "sg:orig_category":"Reposter\u00cdas",
    "sg:phone":"+34 968 46 81 48",
    "sg:postcode":"30815",
    "sg:province":"Murcia",
    "wof:name":"Lagonsto S.c.",
    "wof:placetype":"venue"
},
  "geometry": {"coordinates":[-1.1298867464,37.9834747314],"type":"Point"}
}