{
  "type": "Feature",
  "properties": {
    "iso:country":"ES",
    "sg:address":"Calle de Acacias, 16",
    "sg:city":"Cadiz",
    "sg:orig_category":"Electrodom\u00c9sticos (al Por Menor)",
    "sg:phone":"+34 956 20 09 38",
    "sg:postcode":"11007",
    "sg:province":"C\u00e1diz",
    "wof:name":"Pascual Sanchez Gijon Guillermo",
    "wof:placetype":"venue"
},
  "geometry": {"coordinates":[-6.2851915359,36.5233650208],"type":"Point"}
}