{
  "type": "Feature",
  "properties": {
    "iso:country":"ES",
    "sg:address":"Almirante, 6",
    "sg:city":"Almirante",
    "sg:classifiers":[
        {
            "category":"Taxi",
            "type":"Transportation"
        }
    ],
    "sg:phone":"+34 986 54 04 13",
    "sg:postcode":"36658",
    "sg:province":"Pontevedra",
    "wof:name":"Abalo Rivas Fernando",
    "wof:placetype":"venue"
},
  "geometry": {"coordinates":[-8.648053,42.43362],"type":"Point"}
}