{
  "type": "Feature",
  "properties": {
    "addr:full":"Calle de Yebenes, 94 Madrid Madrid 28047",
    "addr:housenumber":"94",
    "addr:postcode":"madrid;28047",
    "addr:street":"Calle De Yebenes",
    "iso:country":"ES",
    "sg:address":"Calle de Yebenes, 94",
    "sg:city":"Madrid",
    "sg:orig_category":"Agencias Y Asesores De Publicidad",
    "sg:phone":"+34 915 09 98 89",
    "sg:postcode":"28047",
    "sg:province":"Madrid",
    "sg:website":"www.canalbus.com",
    "wof:name":"Canal Bus Promociones Audiovisuales S.l.",
    "wof:placetype":"venue"
},
  "geometry": {"coordinates":[-3.7527189255,40.3927001953],"type":"Point"}
}