{
  "type": "Feature",
  "properties": {
    "iso:country":"ES",
    "sg:address":"Calle de Joaquin Arjona, 33",
    "sg:city":"Madrid",
    "sg:orig_category":"Abogados",
    "sg:phone":"+34 913 11 74 23",
    "sg:postcode":"28039",
    "sg:province":"Madrid",
    "wof:name":"Pinedo Santamaria Carlos",
    "wof:placetype":"venue"
},
  "geometry": {"coordinates":[-3.7085208893,40.4541778564],"type":"Point"}
}