{
  "type": "Feature",
  "properties": {
    "addr:full":"Carrer de Llovera, 36 Reus Tarragona 43201",
    "addr:housenumber":"36",
    "addr:postcode":"43201",
    "addr:street":"Carrer De Llovera",
    "iso:country":"ES",
    "sg:address":"Carrer de Llovera, 36",
    "sg:city":"Reus",
    "sg:orig_category":"Cajas De Ahorro",
    "sg:phone":"+34 977 32 68 83",
    "sg:postcode":"43201",
    "sg:province":"Tarragona",
    "sg:website":"www.caixacatalunya.es",
    "wof:name":"Caixa D'estalvis De Catalunya",
    "wof:placetype":"venue"
},
  "geometry": {"coordinates":[1.1062190533,41.1570014954],"type":"Point"}
}