{
  "type": "Feature",
  "properties": {
    "addr:full":"Calle de Alagon, 11 Madrid Madrid 28042",
    "addr:housenumber":"11",
    "addr:postcode":"madrid;28042",
    "addr:street":"Calle De Alagon",
    "iso:country":"ES",
    "sg:address":"Calle de Alagon, 11",
    "sg:city":"Madrid",
    "sg:orig_category":"Contenedores (mercanc\u00cdas)",
    "sg:phone":"+34 917 47 71 74",
    "sg:postcode":"28042",
    "sg:province":"Madrid",
    "wof:name":"Quintana Ruiz Miguel",
    "wof:placetype":"venue"
},
  "geometry": {"coordinates":[-3.587954998,40.4707603455],"type":"Point"}
}