{
  "type": "Feature",
  "properties": {
    "addr:full":"Gaintxurizketa Bidea, 7 Lezo Guip\u00f9zcoa 20100",
    "addr:housenumber":"7",
    "addr:postcode":"20100",
    "addr:street":"Gaintxurizketa Bidea;Guipu\u0300Zcoa",
    "iso:country":"ES",
    "sg:address":"Gaintxurizketa Bidea, 7",
    "sg:city":"Lezo",
    "sg:orig_category":"Organizaciones Profesionales",
    "sg:phone":"+34 943 35 16 32",
    "sg:postcode":"20100",
    "sg:province":"Guip\u00f9zcoa",
    "wof:name":"Itxasoa Abastecimientos Marinos S.l.",
    "wof:placetype":"venue"
},
  "geometry": {"coordinates":[-1.8582600355,43.3291015625],"type":"Point"}
}