{
  "type": "Feature",
  "properties": {
    "addr:full":"Carr Jumilla, 50 Badalona Barcelona 08918",
    "addr:housenumber":"50",
    "addr:postcode":"08918",
    "addr:street":"Carr Jumilla",
    "iso:country":"ES",
    "sg:address":"Carr Jumilla, 50",
    "sg:city":"Badalona",
    "sg:orig_category":"Promotores Constructores",
    "sg:phone":"+34 933 88 76 12",
    "sg:postcode":"08918",
    "sg:province":"Barcelona",
    "wof:name":"Agrupacion Guinovart Obras Y Servicios Hispania S.a.",
    "wof:placetype":"venue"
},
  "geometry": {"coordinates":[2.2245805264,41.4354171753],"type":"Point"}
}