{
  "type": "Feature",
  "properties": {
    "addr:full":"Calle de Velazquez, 3 Abanilla Murcia 30640",
    "addr:housenumber":"3",
    "addr:postcode":"30640",
    "addr:street":"Calle De Velazquez",
    "iso:country":"ES",
    "sg:address":"Calle de Velazquez, 3",
    "sg:city":"Abanilla",
    "sg:orig_category":"Equipo De Refrigeraci\u00d3n Industrial",
    "sg:phone":"+34 968 68 10 61",
    "sg:postcode":"30640",
    "sg:province":"Murcia",
    "wof:name":"Enercyr S.l.",
    "wof:placetype":"venue"
},
  "geometry": {"coordinates":[-1.043383956,38.2044906616],"type":"Point"}
}