{
  "type": "Feature",
  "properties": {
    "addr:full":"Av Doctor Joaquim Danes, 10 Olot Girona 17800",
    "addr:housenumber":"10",
    "addr:postcode":"17800",
    "addr:street":"Av Doctor Joaquim Danes",
    "iso:country":"ES",
    "sg:address":"Av Doctor Joaquim Danes, 10",
    "sg:city":"Olot",
    "sg:orig_category":"Caf\u00c9s, Bares, Cervecer\u00cdas",
    "sg:phone":"+34 972 27 23 94",
    "sg:postcode":"17800",
    "sg:province":"Girona",
    "wof:name":"Martin Gonzalez Antonia",
    "wof:placetype":"venue"
},
  "geometry": {"coordinates":[2.4808700085,42.1828689575],"type":"Point"}
}