{
  "type": "Feature",
  "properties": {
    "addr:full":"Calle de Estrella Polar (de La), 30 Pozuelo De Alarcon Madrid 28224",
    "addr:housenumber":"30",
    "addr:postcode":"28224",
    "addr:street":"Calle De Estrella Polar De La",
    "iso:country":"ES",
    "sg:address":"Calle de Estrella Polar (de La), 30",
    "sg:city":"Pozuelo De Alarcon",
    "sg:orig_category":"Promotores Constructores",
    "sg:phone":"+34 913 51 02 77",
    "sg:postcode":"28224",
    "sg:province":"Madrid",
    "wof:name":"Eurquiquet S.l.",
    "wof:placetype":"venue"
},
  "geometry": {"coordinates":[-3.7936611176,40.4413146973],"type":"Point"}
}