{
  "type": "Feature",
  "properties": {
    "iso:country":"ES",
    "sg:address":"Rua Vazquez Saco, S/n",
    "sg:city":"Sarria",
    "sg:orig_category":"Contenedores (mercanc\u00cdas)",
    "sg:phone":"+34 982 53 00 36",
    "sg:postcode":"27600",
    "sg:province":"Lugo",
    "wof:name":"Lopez Villanueva Isidro",
    "wof:placetype":"venue"
},
  "geometry": {"coordinates":[-7.415099144,42.7792167664],"type":"Point"}
}