{
  "type": "Feature",
  "properties": {
    "iso:country":"ES",
    "sg:address":"Calle de Mercedes (las), 31",
    "sg:city":"Arenas -areeta",
    "sg:orig_category":"Carnicer\u00cdas, Carnicer\u00cdas",
    "sg:phone":"+34 944 64 41 25",
    "sg:postcode":"48930",
    "sg:province":"Vizcaya",
    "wof:name":"Celaya Aguirre Juan Maria",
    "wof:placetype":"venue"
},
  "geometry": {"coordinates":[-3.0124020576,43.3276100159],"type":"Point"}
}