{
  "type": "Feature",
  "properties": {
    "iso:country":"ES",
    "sg:address":"Cno. Chiclana, S/n",
    "sg:city":"Conil",
    "sg:orig_category":"Empresas De Carpinter\u00cda De Madera",
    "sg:phone":"+34 956 44 10 67",
    "sg:postcode":"11140",
    "sg:province":"C\u00e1diz",
    "wof:name":"Carpinteria De Maderas Chano S.l.",
    "wof:placetype":"venue"
},
  "geometry": {"coordinates":[-6.0893549919,36.2775154114],"type":"Point"}
}