{
  "type": "Feature",
  "properties": {
    "iso:country":"ES",
    "sg:address":"Avda Laba\u00d1ou, S/n",
    "sg:city":"Coru\u00d1a",
    "sg:orig_category":"Pescader\u00cdas (al Por Mayor)",
    "sg:phone":"+34 981 27 13 09",
    "sg:postcode":"15011",
    "sg:province":"La Coru\u00f1a",
    "wof:name":"Balseiro Sabio Jesus",
    "wof:placetype":"venue"
},
  "geometry": {"coordinates":[-8.4238443375,43.3742332458],"type":"Point"}
}