{
  "type": "Feature",
  "properties": {
    "iso:country":"ES",
    "sg:address":"Avda Cervantes, 25",
    "sg:city":"Baena",
    "sg:orig_category":"Colchones (fabricaci\u00d3n, Al Por Mayor, Al Por Menor)",
    "sg:phone":"+34 957 69 09 56",
    "sg:postcode":"14850",
    "sg:province":"C\u00f3rdoba",
    "wof:name":"Muebles Ordo\u00d1ez C.b.",
    "wof:placetype":"venue"
},
  "geometry": {"coordinates":[-4.3224191666,37.6166610718],"type":"Point"}
}