{
  "type": "Feature",
  "properties": {
    "addr:full":"Diseminado Cortichelles, S/n Turis Valencia 46389",
    "addr:housenumber":"s / n",
    "addr:postcode":"46389",
    "addr:street":"Diseminado Cortichelles",
    "iso:country":"ES",
    "sg:address":"Diseminado Cortichelles, S/n",
    "sg:city":"Turis",
    "sg:orig_category":"Asociaciones Humanitarias, De Cooperaci\u00d3n, De Acci\u00d3n Social",
    "sg:phone":"+34 962 12 62 84",
    "sg:postcode":"46389",
    "sg:province":"Valencia",
    "wof:name":"Asprona Ong",
    "wof:placetype":"venue"
},
  "geometry": {"coordinates":[-0.6962853074,39.3807830811],"type":"Point"}
}