{
  "type": "Feature",
  "properties": {
    "iso:country":"ES",
    "sg:address":"Calle de Salamanca, 39",
    "sg:city":"Valencia",
    "sg:orig_category":"Imprenta",
    "sg:phone":"+34 963 74 29 17",
    "sg:postcode":"46005",
    "sg:province":"Valencia",
    "sg:website":"www.graficasgenives.com",
    "wof:name":"Graficas Genoves S. L.",
    "wof:placetype":"venue"
},
  "geometry": {"coordinates":[-0.3635169864,39.4654502869],"type":"Point"}
}