{
  "type": "Feature",
  "properties": {
    "iso:country":"ES",
    "sg:address":"Carrer de Francesc Macia, 85",
    "sg:city":"Granollers",
    "sg:orig_category":"Quincaller\u00cda (al Por Menor)",
    "sg:phone":"+34 938 70 27 45",
    "sg:postcode":"08402",
    "sg:province":"Barcelona",
    "wof:name":"Quintana Vila Jose",
    "wof:placetype":"venue"
},
  "geometry": {"coordinates":[2.2874999046,41.6006317139],"type":"Point"}
}