{
  "type": "Feature",
  "properties": {
    "addr:full":"Carrer de Casp, 37 Barcelona Barcelona 08010",
    "addr:housenumber":"37",
    "addr:postcode":"08010",
    "addr:street":"Carrer De Casp",
    "iso:country":"ES",
    "sg:address":"Carrer de Casp, 37",
    "sg:city":"Barcelona",
    "sg:orig_category":"Edici\u00d3n De Diarios, Revistas, Boletines",
    "sg:phone":"+34 933 01 49 60",
    "sg:postcode":"08010",
    "sg:province":"Barcelona",
    "wof:name":"Nova Catalunya Edicions S.l.",
    "wof:placetype":"venue"
},
  "geometry": {"coordinates":[2.1734819412,41.3916358948],"type":"Point"}
}