{
  "type": "Feature",
  "properties": {
    "iso:country":"ES",
    "sg:address":"Calle de Miracruz, 21",
    "sg:city":"Donostia-san Sebastian",
    "sg:orig_category":"Locales De Saunas, De Ba\u00d1os",
    "sg:phone":"+34 943 32 01 67",
    "sg:postcode":"20001",
    "sg:province":"Guip\u00f9zcoa",
    "wof:name":"I\u00f1igo Miranda S.l.",
    "wof:placetype":"venue"
},
  "geometry": {"coordinates":[-1.972612977,43.3224449158],"type":"Point"}
}