{
  "type": "Feature",
  "properties": {
    "iso:country":"ES",
    "sg:address":"Calle de Estrecho De Gibraltar, 13",
    "sg:city":"Madrid",
    "sg:orig_category":"Resinas Sint\u00c9ticas (fabricaci\u00d3n, Al Por Mayor)",
    "sg:phone":"+34 914 08 36 00",
    "sg:postcode":"28027",
    "sg:province":"Madrid",
    "wof:name":"Plasticos Y Transformados S. A.",
    "wof:placetype":"venue"
},
  "geometry": {"coordinates":[-3.6417779922,40.4367141724],"type":"Point"}
}