{
  "type": "Feature",
  "properties": {
    "addr:full":"Calle de Plaza De Toros Vieja, 10 Malaga M\u00e1laga 29002",
    "addr:housenumber":"10",
    "addr:postcode":"29002",
    "addr:street":"Calle De;Vieja;Ma\u0301Laga",
    "iso:country":"ES",
    "sg:address":"Calle de Plaza De Toros Vieja, 10",
    "sg:city":"Malaga",
    "sg:orig_category":"Venta, Colocaci\u00d3n, Reparaci\u00d3n De Parabrisas, Techos Descapotables",
    "sg:phone":"+34 952 32 10 20",
    "sg:postcode":"29002",
    "sg:province":"M\u00e1laga",
    "wof:name":"Autovidrios S.l.",
    "wof:placetype":"venue"
},
  "geometry": {"coordinates":[-4.4275860786,36.7125892639],"type":"Point"}
}