{
  "type": "Feature",
  "properties": {
    "addr:full":"Carrer de Maximi Fornes, 23 Rubi Barcelona 08191",
    "addr:housenumber":"23",
    "addr:postcode":"08191",
    "addr:street":"Carrer De Maximi Fornes",
    "iso:country":"ES",
    "sg:address":"Carrer de Maximi Fornes, 23",
    "sg:city":"Rubi",
    "sg:orig_category":"Caf\u00c9s, Bares, Cervecer\u00cdas",
    "sg:phone":"+34 935 88 52 05",
    "sg:postcode":"08191",
    "sg:province":"Barcelona",
    "wof:name":"Lopez Morales Antonia",
    "wof:placetype":"venue"
},
  "geometry": {"coordinates":[2.0308570862,41.4911270142],"type":"Point"}
}