{
  "type": "Feature",
  "properties": {
    "addr:full":"Carrer de Mestral, 3 Altafulla Tarragona 43893",
    "addr:housenumber":"3",
    "addr:postcode":"43893",
    "addr:street":"Carrer De Mestral",
    "iso:country":"ES",
    "sg:address":"Carrer de Mestral, 3",
    "sg:city":"Altafulla",
    "sg:orig_category":"Restaurantes",
    "sg:phone":"+34 977 65 07 81",
    "sg:postcode":"43893",
    "sg:province":"Tarragona",
    "wof:name":"Restaurante Costa Dorada Ii C.b.",
    "wof:placetype":"venue"
},
  "geometry": {"coordinates":[1.3769849539,41.1349334717],"type":"Point"}
}