{
  "type": "Feature",
  "properties": {
    "addr:full":"Ctra Basurtu-kastrexana, 21 Bilbao Vizcaya 48002",
    "addr:housenumber":"21",
    "addr:postcode":"48002",
    "addr:street":"Ctra Basurtu-Kastrexana",
    "iso:country":"ES",
    "sg:address":"Ctra Basurtu-kastrexana, 21",
    "sg:city":"Bilbao",
    "sg:orig_category":"Alquiler De V\u00cddeo",
    "sg:phone":"+34 944 00 49 39",
    "sg:postcode":"48002",
    "sg:province":"Vizcaya",
    "wof:name":"Sonia Rodriguez Montero E Igor Gonzalez Laseca",
    "wof:placetype":"venue"
},
  "geometry": {"coordinates":[-2.9523789883,43.2591705322],"type":"Point"}
}