{
  "type": "Feature",
  "properties": {
    "addr:full":"Carrer de Balmes, 440 Barcelona Barcelona 08022",
    "addr:housenumber":"440",
    "addr:postcode":"08022",
    "addr:street":"Carrer De Balmes",
    "iso:country":"ES",
    "sg:address":"Carrer de Balmes, 440",
    "sg:city":"Barcelona",
    "sg:orig_category":"Agentes Y Bufetes De Negocio",
    "sg:phone":"+34 934 17 08 36",
    "sg:postcode":"08022",
    "sg:province":"Barcelona",
    "wof:name":"Nuriolma S.l.",
    "wof:placetype":"venue"
},
  "geometry": {"coordinates":[2.1381120682,41.4081268311],"type":"Point"}
}