{
  "type": "Feature",
  "properties": {
    "iso:country":"ES",
    "sg:address":"Carrer de Querol, 29",
    "sg:city":"S. Climent Llobregat",
    "sg:orig_category":"Paletas",
    "sg:phone":"+34 936 37 41 99",
    "sg:postcode":"08849",
    "sg:province":"Barcelona",
    "wof:name":"Recuperaciones Jolica S.l.",
    "wof:placetype":"venue"
},
  "geometry": {"coordinates":[1.9954830408,41.3400878906],"type":"Point"}
}