{
  "type": "Feature",
  "properties": {
    "addr:full":"Lucenza, 41 Lucenza Ourense 32688",
    "addr:housenumber":"41",
    "addr:postcode":"32688",
    "addr:street":"Lucenza",
    "iso:country":"ES",
    "sg:address":"Lucenza, 41",
    "sg:city":"Lucenza",
    "sg:orig_category":"Empresas De Carpinter\u00cda De Madera",
    "sg:phone":"+34 988 42 03 11",
    "sg:postcode":"32688",
    "sg:province":"Ourense",
    "wof:name":"Carnero Bailon Gumersindo",
    "wof:placetype":"venue"
},
  "geometry": {"coordinates":[-7.6213388443,41.9537696838],"type":"Point"}
}