{
  "type": "Feature",
  "properties": {
    "addr:full":"Calle de Ercilla, 29 Bilbao Vizcaya 48011",
    "addr:housenumber":"29",
    "addr:postcode":"48011",
    "addr:street":"Calle De Ercilla",
    "iso:country":"ES",
    "sg:address":"Calle de Ercilla, 29",
    "sg:city":"Bilbao",
    "sg:orig_category":"Zapatos (al Por Menor)",
    "sg:phone":"+34 944 10 25 48",
    "sg:postcode":"48011",
    "sg:province":"Vizcaya",
    "wof:name":"Otazua Vitoria Consuelo",
    "wof:placetype":"venue"
},
  "geometry": {"coordinates":[-2.9373180866,43.2617530823],"type":"Point"}
}