{
  "type": "Feature",
  "properties": {
    "addr:full":"Calle de Reina Do\u00d1a Sofia, 81 Alpera Albacete 02690",
    "addr:housenumber":"81",
    "addr:postcode":"02690",
    "addr:street":"Calle De Reina Don\u0303A Sofia",
    "iso:country":"ES",
    "sg:address":"Calle de Reina Do\u00d1a Sofia, 81",
    "sg:city":"Alpera",
    "sg:orig_category":"Inform\u00c1tica (estudios, Servicios, Asesor\u00cda, Formaci\u00d3n)",
    "sg:phone":"+34 967 33 06 04",
    "sg:postcode":"02690",
    "sg:province":"Albacete",
    "wof:name":"New Media Profesional Services S.l.",
    "wof:placetype":"venue"
},
  "geometry": {"coordinates":[-1.2323989868,38.9560813904],"type":"Point"}
}