{
  "type": "Feature",
  "properties": {
    "addr:full":"Calle de Pozo Amargo, 6 Toledo Toledo 45002",
    "addr:housenumber":"6",
    "addr:postcode":"45002",
    "addr:street":"Calle De Pozo Amargo",
    "iso:country":"ES",
    "sg:address":"Calle de Pozo Amargo, 6",
    "sg:city":"Toledo",
    "sg:orig_category":"Alimentaci\u00d3n General (al Por Menor)",
    "sg:phone":"+34 925 22 32 48",
    "sg:postcode":"45002",
    "sg:province":"Toledo",
    "wof:name":"Paz Gonzalez Emilio De",
    "wof:placetype":"venue"
},
  "geometry": {"coordinates":[-4.0244607925,39.856010437],"type":"Point"}
}