{
  "type": "Feature",
  "properties": {
    "addr:full":"Poligono Industrial, 6 Castro Riberas Lugo 27260",
    "addr:postcode":"27260",
    "addr:street":"Industrial",
    "iso:country":"ES",
    "sg:address":"Poligono Industrial, 6",
    "sg:city":"Castro Riberas",
    "sg:orig_category":"Panader\u00cdas, Panader\u00cdas",
    "sg:phone":"+34 982 31 06 70",
    "sg:postcode":"27260",
    "sg:province":"Lugo",
    "wof:name":"Nu\u00f1ez Lopez Jose Manuel",
    "wof:placetype":"venue"
},
  "geometry": {"coordinates":[-7.5693798065,43.0095100403],"type":"Point"}
}