{
  "type": "Feature",
  "properties": {
    "iso:country":"ES",
    "sg:address":"Carr Colon, 22",
    "sg:city":"Betera",
    "sg:orig_category":"Multimedia: Servicios En L\u00cdnea, Acceso En L\u00cdnea, Cd",
    "sg:phone":"+34 961 69 19 76",
    "sg:postcode":"46117",
    "sg:province":"Valencia",
    "sg:website":"www.cursosbonilla.com",
    "wof:name":"Cursos Luis Bonilla, S.l.",
    "wof:placetype":"venue"
},
  "geometry": {"coordinates":[-0.4597679973,39.5903625488],"type":"Point"}
}