{
  "type": "Feature",
  "properties": {
    "iso:country":"ES",
    "sg:address":"Pase Direccion, 121",
    "sg:city":"Madrid",
    "sg:orig_category":"Mudanzas",
    "sg:phone":"+34 913 11 79 59",
    "sg:postcode":"28039",
    "sg:province":"Madrid",
    "wof:name":"Mudanzas Zarza S.a.",
    "wof:placetype":"venue"
},
  "geometry": {"coordinates":[-3.7069270611,40.4624214172],"type":"Point"}
}