{
  "type": "Feature",
  "properties": {
    "iso:country":"ES",
    "sg:address":"Paseo Los Fueros, 18",
    "sg:city":"Barakaldo",
    "sg:orig_category":"Panader\u00cdas, Panader\u00cdas",
    "sg:phone":"+34 944 38 61 00",
    "sg:postcode":"48901",
    "sg:province":"Vizcaya",
    "wof:name":"Pasteleria Zuberoa, S.l.",
    "wof:placetype":"venue"
},
  "geometry": {"coordinates":[-2.9883439541,43.2953224182],"type":"Point"}
}