{
  "type": "Feature",
  "properties": {
    "addr:full":"Carr Corregidor Escofet, 61 Lleida Lleida 25005",
    "addr:housenumber":"61",
    "addr:postcode":"25005",
    "addr:street":"Carr Corregidor Escofet",
    "iso:country":"ES",
    "sg:address":"Carr Corregidor Escofet, 61",
    "sg:city":"Lleida",
    "sg:orig_category":"Comercio, Reparaci\u00d3n De Motocicletas, Bicicletas Y Piezas Sueltas",
    "sg:phone":"+34 973 24 23 99",
    "sg:postcode":"25005",
    "sg:province":"Lleida",
    "wof:name":"Motos Parcerisas S.l.",
    "wof:placetype":"venue"
},
  "geometry": {"coordinates":[0.6307500005,41.6277999878],"type":"Point"}
}