{
  "type": "Feature",
  "properties": {
    "addr:full":"Calle de Camino Del Berrocal, 6 Estacion Madrid 28400",
    "addr:housenumber":"6 estacion",
    "addr:postcode":"28400",
    "addr:street":"Calle De Camino Del Berrocal",
    "iso:country":"ES",
    "sg:address":"Calle de Camino Del Berrocal, 6",
    "sg:city":"Estacion",
    "sg:orig_category":"Peluqueros: De Se\u00d1oras",
    "sg:phone":"+34 918 50 27 13",
    "sg:postcode":"28400",
    "sg:province":"Madrid",
    "wof:name":"Santamaria Higelmo Elena",
    "wof:placetype":"venue"
},
  "geometry": {"coordinates":[-3.9919650555,40.6455612183],"type":"Point"}
}