{
  "type": "Feature",
  "properties": {
    "addr:full":"Avda Andalucia, 33 Barbate C\u00e1diz 11160",
    "addr:housenumber":"33",
    "addr:postcode":"11160",
    "addr:street":"Avda Andalucia",
    "iso:country":"ES",
    "sg:address":"Avda Andalucia, 33",
    "sg:city":"Barbate",
    "sg:orig_category":"Venta Al Preg\u00d3n",
    "sg:phone":"+34 956 43 12 12",
    "sg:postcode":"11160",
    "sg:province":"C\u00e1diz",
    "wof:name":"Jimenez Mu\u00f1oz Manuel",
    "wof:placetype":"venue"
},
  "geometry": {"coordinates":[-5.9232039452,36.1918525696],"type":"Point"}
}