{
  "type": "Feature",
  "properties": {
    "iso:country":"ES",
    "sg:address":"Via Augusta, 37",
    "sg:city":"Hospitalet Infant",
    "sg:orig_category":"Cajas De Ahorro",
    "sg:phone":"+34 977 82 30 31",
    "sg:postcode":"43890",
    "sg:province":"Tarragona",
    "sg:website":"www.caixatarragona.es",
    "wof:name":"Caixa D'estalvis De Tarragona",
    "wof:placetype":"venue"
},
  "geometry": {"coordinates":[0.9224560261,40.9911117554],"type":"Point"}
}