{
  "type": "Feature",
  "properties": {
    "iso:country":"ES",
    "sg:address":"Ctra. Manacor, Km. 0009,0",
    "sg:city":"Portocristo",
    "sg:orig_category":"Molduras, Junquillos, Listones Y Molduras Perforadas",
    "sg:phone":"+34 971 82 12 88",
    "sg:postcode":"07680",
    "sg:province":"Islas Baleares",
    "wof:name":"Galmes Llull Guillermo",
    "wof:placetype":"venue"
},
  "geometry": {"coordinates":[3.3359000683,39.5415039062],"type":"Point"}
}