{
  "type": "Feature",
  "properties": {
    "addr:full":"Calle de Valenzuela, 7 Bola\u00e7os De Calatrava Ciudad Real 13260",
    "addr:housenumber":"7",
    "addr:postcode":"13260",
    "addr:street":"Calle De Valenzuela",
    "iso:country":"ES",
    "sg:address":"Calle de Valenzuela, 7",
    "sg:city":"Bola\u00e7os De Calatrava",
    "sg:orig_category":"Laboratorios Y Asesor\u00cda En Enolog\u00cda",
    "sg:phone":"+34 926 87 21 15",
    "sg:postcode":"13260",
    "sg:province":"Ciudad Real",
    "wof:name":"Carrasco Serrano Jose",
    "wof:placetype":"venue"
},
  "geometry": {"coordinates":[-3.6656041145,38.9035949707],"type":"Point"}
}