{
  "type": "Feature",
  "properties": {
    "addr:full":"Calle de Campo (del), 64 Almansa Albacete 02640",
    "addr:postcode":"02640",
    "addr:street":"Calle De Campo Del",
    "iso:country":"ES",
    "sg:address":"Calle de Campo (del), 64",
    "sg:city":"Almansa",
    "sg:orig_category":"Muebles, Minoristas",
    "sg:phone":"+34 967 34 03 47",
    "sg:postcode":"02640",
    "sg:province":"Albacete",
    "wof:name":"Tarraga Navalon Hilario",
    "wof:placetype":"venue"
},
  "geometry": {"coordinates":[-1.0974869728,38.8700180054],"type":"Point"}
}