{
  "type": "Feature",
  "properties": {
    "addr:full":"Av Alameda (l'), 53 Alcoi Alicante 03803",
    "addr:housenumber":"53",
    "addr:postcode":"03803",
    "addr:street":"Av Alameda L '",
    "iso:country":"ES",
    "sg:address":"Av Alameda (l'), 53",
    "sg:city":"Alcoi",
    "sg:orig_category":"Farmacias",
    "sg:phone":"+34 965 33 14 27",
    "sg:postcode":"03803",
    "sg:province":"Alicante",
    "wof:name":"Domenech Lloret Miguel",
    "wof:placetype":"venue"
},
  "geometry": {"coordinates":[-0.4766409993,38.7027931213],"type":"Point"}
}