{
  "type": "Feature",
  "properties": {
    "iso:country":"ES",
    "sg:address":"Calle de Aluminio, 8",
    "sg:city":"Humanes De Madrid",
    "sg:orig_category":"Empresas De Pintura Y Revestimientos",
    "sg:phone":"+34 916 06 31 22",
    "sg:postcode":"28970",
    "sg:province":"Madrid",
    "wof:name":"Pinturas El Pilar S.l.",
    "wof:placetype":"venue"
},
  "geometry": {"coordinates":[-3.8246533871,40.2680549622],"type":"Point"}
}