{
  "type": "Feature",
  "properties": {
    "addr:full":"Carr Galerias Albatros, 111 Platja D'aro Girona 17250",
    "addr:housenumber":"111",
    "addr:postcode":"17250",
    "addr:street":"Carr Galerias Albatros",
    "iso:country":"ES",
    "sg:address":"Carr Galerias Albatros, 111",
    "sg:city":"Platja D'aro",
    "sg:orig_category":"Zapatos (al Por Menor)",
    "sg:phone":"+34 972 81 68 92",
    "sg:postcode":"17250",
    "sg:province":"Girona",
    "wof:name":"Jimenez Lopez Justo",
    "wof:placetype":"venue"
},
  "geometry": {"coordinates":[2.8163490295,41.9701499939],"type":"Point"}
}