{
  "type": "Feature",
  "properties": {
    "addr:full":"Calle de Juan Jose Espejo, 45 Benameji C\u00f3rdoba 14910",
    "addr:housenumber":"45",
    "addr:postcode":"14910",
    "addr:street":"Calle De Juan Jose Espejo;Co\u0301Rdoba",
    "iso:country":"ES",
    "sg:address":"Calle de Juan Jose Espejo, 45",
    "sg:city":"Benameji",
    "sg:orig_category":"Peluqueros: De Se\u00d1oras",
    "sg:phone":"+34 957 53 02 98",
    "sg:postcode":"14910",
    "sg:province":"C\u00f3rdoba",
    "wof:name":"Linares Chacon Josefa",
    "wof:placetype":"venue"
},
  "geometry": {"coordinates":[-4.5398511887,37.2682991028],"type":"Point"}
}