{
  "type": "Feature",
  "properties": {
    "iso:country":"ES",
    "sg:address":"Calle de Caudal, 31",
    "sg:city":"Malaga",
    "sg:orig_category":"Muebles, Minoristas",
    "sg:phone":"+34 952 32 13 15",
    "sg:postcode":"29006",
    "sg:province":"M\u00e1laga",
    "wof:name":"Aguas Ordo\u00f1ez Jose",
    "wof:placetype":"venue"
},
  "geometry": {"coordinates":[-4.4836292267,36.7124252319],"type":"Point"}
}