{
  "type": "Feature",
  "properties": {
    "iso:country":"ES",
    "sg:address":"Joaquin Sorolla, 106",
    "sg:city":"Rivas Vaciamadrid",
    "sg:orig_category":"Inform\u00c1tica Equipo Y Programas (al Por Mayor)",
    "sg:phone":"+34 914 99 03 02",
    "sg:postcode":"28529",
    "sg:province":"Madrid",
    "sg:website":"www.gextcomputer.com",
    "wof:name":"Gextcomputer S. L.",
    "wof:placetype":"venue"
},
  "geometry": {"coordinates":[-3.5326149464,40.3466110229],"type":"Point"}
}