{
  "type": "Feature",
  "properties": {
    "iso:country":"ES",
    "sg:address":"Calle de Pontanilla, 5",
    "sg:city":"Salobre\u00f1a",
    "sg:orig_category":"Loter\u00cda Y T\u00d3mbola",
    "sg:phone":"+34 958 61 08 83",
    "sg:postcode":"18680",
    "sg:province":"Granada",
    "wof:name":"Gonzalez Hernandez Genaro",
    "wof:placetype":"venue"
},
  "geometry": {"coordinates":[-3.5844540596,36.7452201843],"type":"Point"}
}