{
  "type": "Feature",
  "properties": {
    "iso:country":"ES",
    "sg:address":"Avda Prado Boyal, 3",
    "sg:city":"Laguna Duero",
    "sg:orig_category":"Venta, Alquiler De V\u00cddeo",
    "sg:phone":"+34 983 54 34 09",
    "sg:postcode":"47140",
    "sg:province":"Valladolid",
    "wof:name":"Alonso De Pablo Fernando",
    "wof:placetype":"venue"
},
  "geometry": {"coordinates":[-4.7264518738,41.5897140503],"type":"Point"}
}