{
  "type": "Feature",
  "properties": {
    "addr:full":"Carrer de Progres, 68 Hospitalet Llobregat Barcelona 08904",
    "addr:housenumber":"68",
    "addr:postcode":"08904",
    "addr:street":"Carrer De Progres",
    "iso:country":"ES",
    "sg:address":"Carrer de Progres, 68",
    "sg:city":"Hospitalet Llobregat",
    "sg:orig_category":"Carnicer\u00cdas, Carnicer\u00cdas",
    "sg:phone":"+34 934 49 42 92",
    "sg:postcode":"08904",
    "sg:province":"Barcelona",
    "wof:name":"Juandri S.l.",
    "wof:placetype":"venue"
},
  "geometry": {"coordinates":[2.1201689243,41.3732414246],"type":"Point"}
}