{
  "type": "Feature",
  "properties": {
    "addr:full":"Carr Abat Sola, 40 Gandia Valencia 46700",
    "addr:housenumber":"40",
    "addr:postcode":"46700",
    "addr:street":"Carr Abat Sola;Valencia",
    "iso:country":"ES",
    "sg:address":"Carr Abat Sola, 40",
    "sg:city":"Gandia",
    "sg:orig_category":"Alimentaci\u00d3n General (al Por Menor)",
    "sg:phone":"+34 962 86 35 34",
    "sg:postcode":"46700",
    "sg:province":"Valencia",
    "wof:name":"Salazones Coll Sl",
    "wof:placetype":"venue"
},
  "geometry": {"coordinates":[-0.1913339943,38.960735321],"type":"Point"}
}