{
  "type": "Feature",
  "properties": {
    "iso:country":"ES",
    "sg:address":"Calle de Virgen Del Mar, 24",
    "sg:city":"Santurtzi",
    "sg:orig_category":"Molduras, Junquillos, Listones Y Molduras Perforadas",
    "sg:phone":"+34 944 83 54 24",
    "sg:postcode":"48980",
    "sg:province":"Vizcaya",
    "wof:name":"Vazquez Fernandez Maria Magdalena",
    "wof:placetype":"venue"
},
  "geometry": {"coordinates":[-3.0372509956,43.332118988],"type":"Point"}
}