{
  "type": "Feature",
  "properties": {
    "iso:country":"ES",
    "sg:address":"Felipe Ii, 20",
    "sg:city":"Minglanilla",
    "sg:orig_category":"Muebles, Minoristas",
    "sg:phone":"+34 962 18 81 12",
    "sg:postcode":"16260",
    "sg:province":"Cuenca",
    "wof:name":"Muebles Nieves Barberan S.l.",
    "wof:placetype":"venue"
},
  "geometry": {"coordinates":[-1.5970330238,39.5368270874],"type":"Point"}
}