{
  "type": "Feature",
  "properties": {
    "iso:country":"ES",
    "sg:address":"Carr Germanetes, 4",
    "sg:city":"Lleida",
    "sg:orig_category":"Ropa Para Se\u00d1oras (al Por Menor)",
    "sg:phone":"+34 973 27 56 00",
    "sg:postcode":"25002",
    "sg:province":"Lleida",
    "wof:name":"Barbera Guiterrez Francisca",
    "wof:placetype":"venue"
},
  "geometry": {"coordinates":[0.627129972,41.6145210266],"type":"Point"}
}