{
  "type": "Feature",
  "properties": {
    "iso:country":"ES",
    "sg:address":"Avda Somosierra (de), 20",
    "sg:city":"San Sebastian De Los Reyes",
    "sg:orig_category":"Equipos De Marcado, Etiquetado",
    "sg:phone":"+34 916 51 13 56",
    "sg:postcode":"28700",
    "sg:province":"Madrid",
    "wof:name":"Rotulacion Vinilos Y Ploteados S.l.",
    "wof:placetype":"venue"
},
  "geometry": {"coordinates":[-3.6159119606,40.5542793274],"type":"Point"}
}