{
  "type": "Feature",
  "properties": {
    "addr:full":"Vred Solis, 1 San Roque Murcia 30006",
    "addr:postcode":"30006",
    "iso:country":"ES",
    "sg:address":"Vred Solis, 1",
    "sg:city":"San Roque",
    "sg:orig_category":"Cervecer\u00cdas",
    "sg:phone":"+34 968 30 12 36",
    "sg:postcode":"30006",
    "sg:province":"Murcia",
    "wof:name":"Garcia Tovar Jose Vicente",
    "wof:placetype":"venue"
},
  "geometry": {"coordinates":[-1.1008939743,37.9940185547],"type":"Point"}
}