{
  "type": "Feature",
  "properties": {
    "addr:full":"Calle de Coso, 56 Zaragoza Zaragoza 50001",
    "addr:housenumber":"56",
    "addr:postcode":"50001",
    "addr:street":"Calle De Coso",
    "iso:country":"ES",
    "sg:address":"Calle de Coso, 56",
    "sg:city":"Zaragoza",
    "sg:orig_category":"Agentes Generales De Seguros",
    "sg:phone":"+34 976 23 31 01",
    "sg:postcode":"50001",
    "sg:province":"Zaragoza",
    "wof:name":"Fernandez-urrutia Perez Beatriz",
    "wof:placetype":"venue"
},
  "geometry": {"coordinates":[-0.8799551129,41.6518859863],"type":"Point"}
}