{
  "type": "Feature",
  "properties": {
    "addr:full":"Cno Orito, S/n Monforte Cid Alicante 03670",
    "addr:housenumber":"s",
    "addr:postcode":"03670",
    "addr:street":"Cno Orito;/ N",
    "iso:country":"ES",
    "sg:address":"Cno Orito, S/n",
    "sg:city":"Monforte Cid",
    "sg:orig_category":"Material Y Herramientas Agr\u00cdcolas",
    "sg:phone":"+34 965 62 04 47",
    "sg:postcode":"03670",
    "sg:province":"Alicante",
    "wof:name":"Saugar Compa\u00f1 Fernando",
    "wof:placetype":"venue"
},
  "geometry": {"coordinates":[-0.7296299934,38.3807296753],"type":"Point"}
}