{
  "type": "Feature",
  "properties": {
    "iso:country":"ES",
    "sg:address":"Sect Islas, 26",
    "sg:city":"Tres Cantos",
    "sg:orig_category":"Centros De Educaci\u00d3n Especial",
    "sg:phone":"+34 918 03 83 00",
    "sg:postcode":"28760",
    "sg:province":"Madrid",
    "wof:name":"C.e.i.p. Antonio Osuna",
    "wof:placetype":"venue"
},
  "geometry": {"coordinates":[-3.702272892,40.592590332],"type":"Point"}
}