{
  "type": "Feature",
  "properties": {
    "addr:full":"Carrer de Marti, 114 Barcelona Barcelona 08024",
    "addr:housenumber":"114",
    "addr:postcode":"08024",
    "addr:street":"Carrer De Marti",
    "iso:country":"ES",
    "sg:address":"Carrer de Marti, 114",
    "sg:city":"Barcelona",
    "sg:orig_category":"Ortopedia General",
    "sg:phone":"+34 932 10 34 48",
    "sg:postcode":"08024",
    "sg:province":"Barcelona",
    "wof:name":"Lopez Taravilla Pablo",
    "wof:placetype":"venue"
},
  "geometry": {"coordinates":[2.1602210999,41.4092979431],"type":"Point"}
}