{
  "type": "Feature",
  "properties": {
    "addr:full":"Calle de Alcaide, 4 Lucena C\u00f3rdoba 14900",
    "addr:housenumber":"4",
    "addr:postcode":"14900",
    "addr:street":"Calle De Alcaide",
    "iso:country":"ES",
    "sg:address":"Calle de Alcaide, 4",
    "sg:city":"Lucena",
    "sg:orig_category":"Peluquer\u00cdas, Peluquer\u00cda Mixta",
    "sg:phone":"+34 957 51 37 61",
    "sg:postcode":"14900",
    "sg:province":"C\u00f3rdoba",
    "wof:name":"Vanguardia C.b",
    "wof:placetype":"venue"
},
  "geometry": {"coordinates":[-4.4854311943,37.4098167419],"type":"Point"}
}