{
  "type": "Feature",
  "properties": {
    "addr:full":"Calle de Menendez Pelayo, 17 Abaran Murcia 30550",
    "addr:housenumber":"17",
    "addr:postcode":"30550",
    "addr:street":"Calle De Menendez Pelayo",
    "iso:country":"ES",
    "sg:address":"Calle de Menendez Pelayo, 17",
    "sg:city":"Abaran",
    "sg:orig_category":"Molduras, Junquillos, Listones Y Molduras Perforadas",
    "sg:phone":"+34 968 77 06 37",
    "sg:postcode":"30550",
    "sg:province":"Murcia",
    "wof:name":"Carrillo Pagan Maria Amparo",
    "wof:placetype":"venue"
},
  "geometry": {"coordinates":[-1.4018729925,38.2024688721],"type":"Point"}
}