{
  "type": "Feature",
  "properties": {
    "iso:country":"ES",
    "sg:address":"Calle de Corredera, 9",
    "sg:city":"San Mateo",
    "sg:orig_category":"Obras Y Organismos Sociales",
    "sg:phone":"+34 968 47 76 15",
    "sg:postcode":"30800",
    "sg:province":"Murcia",
    "wof:name":"Fundacion Poncemar",
    "wof:placetype":"venue"
},
  "geometry": {"coordinates":[-1.1298867464,37.9834747314],"type":"Point"}
}