{
  "type": "Feature",
  "properties": {
    "iso:country":"ES",
    "sg:address":"Elorriagazar Kalea, 14",
    "sg:city":"Tra\u00f1a-matiena",
    "sg:orig_category":"Muebles, Minoristas",
    "sg:phone":"+34 946 20 18 45",
    "sg:postcode":"48220",
    "sg:province":"Vizcaya",
    "wof:name":"Intermediacion Y Finanzas Maxwell S.l.",
    "wof:placetype":"venue"
},
  "geometry": {"coordinates":[-2.6079039574,43.1692581177],"type":"Point"}
}