{
  "type": "Feature",
  "properties": {
    "addr:full":"Av Universidad De Elx, 64 Elche Alicante 03202",
    "addr:housenumber":"64",
    "addr:postcode":"03202",
    "addr:street":"Av Universidad De Elx",
    "iso:country":"ES",
    "sg:address":"Av Universidad De Elx, 64",
    "sg:city":"Elche",
    "sg:orig_category":"Importaci\u00d3n",
    "sg:phone":"+34 965 42 10 73",
    "sg:postcode":"03202",
    "sg:province":"Alicante",
    "wof:name":"Francisco Oliva S. L.",
    "wof:placetype":"venue"
},
  "geometry": {"coordinates":[-0.6837239861,38.2738304138],"type":"Point"}
}