{
  "type": "Feature",
  "properties": {
    "addr:full":"A Mtnez De La Hoz, 11 Mancha Real Ja\u00e9n 23100",
    "addr:housenumber":"11",
    "addr:postcode":"23100",
    "addr:street":"Hoz",
    "iso:country":"ES",
    "sg:address":"A Mtnez De La Hoz, 11",
    "sg:city":"Mancha Real",
    "sg:orig_category":"Pescader\u00cdas (al Por Menor)",
    "sg:phone":"+34 953 35 15 71",
    "sg:postcode":"23100",
    "sg:province":"Ja\u00e9n",
    "wof:name":"Lopez Blanca Juan",
    "wof:placetype":"venue"
},
  "geometry": {"coordinates":[-3.609249115,37.7891464233],"type":"Point"}
}