{
  "type": "Feature",
  "properties": {
    "addr:full":"Avda Aeroporto, 151 Vigo Pontevedra 36215",
    "addr:housenumber":"151",
    "addr:postcode":"36215",
    "addr:street":"Avda Aeroporto",
    "iso:country":"ES",
    "sg:address":"Avda Aeroporto, 151",
    "sg:city":"Vigo",
    "sg:orig_category":"Contenedores (mercanc\u00cdas)",
    "sg:phone":"+34 986 27 37 81",
    "sg:postcode":"36215",
    "sg:province":"Pontevedra",
    "wof:name":"Herederos De Raul Alvarado S.l.",
    "wof:placetype":"venue"
},
  "geometry": {"coordinates":[-8.6881189346,42.2317619324],"type":"Point"}
}