{
  "type": "Feature",
  "properties": {
    "iso:country":"ES",
    "sg:address":"Avda Cardenal Costa, S/n",
    "sg:city":"Castellon",
    "sg:orig_category":"Cementerios",
    "sg:phone":"+34 964 21 00 75",
    "sg:postcode":"12004",
    "sg:province":"Castell\u00f3n",
    "wof:name":"Ajuntament D'castello",
    "wof:placetype":"venue"
},
  "geometry": {"coordinates":[-0.0482636988,39.9907493591],"type":"Point"}
}