{
  "type": "Feature",
  "properties": {
    "iso:country":"ES",
    "sg:address":"Calle de Simon Valverde, 28",
    "sg:city":"Villanueva Vera",
    "sg:orig_category":"Bebidas",
    "sg:phone":"+34 927 56 66 54",
    "sg:postcode":"10470",
    "sg:province":"C\u00e1ceres",
    "wof:name":"Ovidio Garcia Mayoral Distribuciones S.l",
    "wof:placetype":"venue"
},
  "geometry": {"coordinates":[-5.4608860016,40.1300888062],"type":"Point"}
}