{
  "type": "Feature",
  "properties": {
    "addr:full":"Calle de Extremadura, 5 Fuengirola M\u00e1laga 29640",
    "addr:housenumber":"5",
    "addr:postcode":"29640",
    "addr:street":"Calle De Extremadura;Ma\u0301Laga",
    "iso:country":"ES",
    "sg:address":"Calle de Extremadura, 5",
    "sg:city":"Fuengirola",
    "sg:orig_category":"Carnicer\u00cdas, Carnicer\u00cdas",
    "sg:phone":"+34 952 58 83 67",
    "sg:postcode":"29640",
    "sg:province":"M\u00e1laga",
    "wof:name":"Quesada Marquez Francisco",
    "wof:placetype":"venue"
},
  "geometry": {"coordinates":[-4.6283841133,36.5381965637],"type":"Point"}
}