{
  "type": "Feature",
  "properties": {
    "iso:country":"ES",
    "sg:address":"Calle de Jose Cruz Conde, 24",
    "sg:city":"Cordoba",
    "sg:orig_category":"Electrodom\u00c9sticos (al Por Menor)",
    "sg:phone":"+34 957 47 30 42",
    "sg:postcode":"14001",
    "sg:province":"C\u00f3rdoba",
    "wof:name":"Torres Vicent Angel",
    "wof:placetype":"venue"
},
  "geometry": {"coordinates":[-4.7806801796,37.8875923157],"type":"Point"}
}