{
  "type": "Feature",
  "properties": {
    "addr:full":"Expl Cervantes, 1 Denia Alicante 03700",
    "addr:housenumber":"1",
    "addr:postcode":"03700",
    "addr:street":"Cervantes",
    "iso:country":"ES",
    "sg:address":"Expl Cervantes, 1",
    "sg:city":"Denia",
    "sg:orig_category":"Estancos",
    "sg:phone":"+34 965 78 10 28",
    "sg:postcode":"03700",
    "sg:province":"Alicante",
    "wof:name":"Sancho Leyda Salvador",
    "wof:placetype":"venue"
},
  "geometry": {"coordinates":[0.1114400029,38.8428153992],"type":"Point"}
}