{
  "type": "Feature",
  "properties": {
    "iso:country":"ES",
    "sg:address":"Carr Dofi, 6",
    "sg:city":"Port D'alcudia",
    "sg:orig_category":"Fabricaci\u00d3n, Distribuci\u00d3n De Material Para La Climatizaci\u00d3n, Aireaci\u00d3n Y Ventilaci\u00d3n",
    "sg:phone":"+34 971 54 84 31",
    "sg:postcode":"07410",
    "sg:province":"Islas Baleares",
    "wof:name":"Ais Balear S.a.",
    "wof:placetype":"venue"
},
  "geometry": {"coordinates":[3.132512331,39.8432731628],"type":"Point"}
}