{
  "type": "Feature",
  "properties": {
    "addr:full":"Calle de Pe\u00d1alara, 15 Sevilla Sevilla 41005",
    "addr:housenumber":"15",
    "addr:postcode":"41005",
    "addr:street":"Calle De Pen\u0303Alara",
    "iso:country":"ES",
    "sg:address":"Calle de Pe\u00d1alara, 15",
    "sg:city":"Sevilla",
    "sg:orig_category":"Formaci\u00d3n Continuada (variada)",
    "sg:phone":"+34 954 93 38 07",
    "sg:postcode":"41005",
    "sg:province":"Sevilla",
    "wof:name":"Iese Intervencion Social S.l.",
    "wof:placetype":"venue"
},
  "geometry": {"coordinates":[-5.9734320641,37.3750801086],"type":"Point"}
}