{
  "type": "Feature",
  "properties": {
    "iso:country":"ES",
    "sg:address":"Pol Ind La Fabrica, 1",
    "sg:city":"Daya Nueva",
    "sg:orig_category":"Alumbrados",
    "sg:phone":"+34 966 78 38 89",
    "sg:postcode":"03159",
    "sg:province":"Alicante",
    "wof:name":"Beneluz Centro De Iluminacion S.l.",
    "wof:placetype":"venue"
},
  "geometry": {"coordinates":[-0.7626640201,38.1145858765],"type":"Point"}
}