{
  "type": "Feature",
  "properties": {
    "iso:country":"ES",
    "sg:address":"Merendero, 5",
    "sg:city":"Merendeiro",
    "sg:orig_category":"Reparaciones Y Remolcado De Veh\u00cdculos",
    "sg:phone":"+34 982 37 03 34",
    "sg:postcode":"27307",
    "sg:province":"Lugo",
    "wof:name":"Talleres Rivas Ansede S.l.",
    "wof:placetype":"venue"
},
  "geometry": {"coordinates":[-7.8914551735,43.3296852112],"type":"Point"}
}