{
  "type": "Feature",
  "properties": {
    "addr:full":"Carrer de Balmes, 206 Barcelona Barcelona 08006",
    "addr:housenumber":"206",
    "addr:postcode":"08006",
    "addr:street":"Carrer De Balmes",
    "iso:country":"ES",
    "sg:address":"Carrer de Balmes, 206",
    "sg:city":"Barcelona",
    "sg:orig_category":"Agencias Y Asesor\u00cda En Marketing Directo",
    "sg:phone":"+34 932 38 90 01",
    "sg:postcode":"08006",
    "sg:province":"Barcelona",
    "wof:name":"Baltack Iniciatives I Serveis S.l.",
    "wof:placetype":"venue"
},
  "geometry": {"coordinates":[2.1521360874,41.3975639343],"type":"Point"}
}