{
  "type": "Feature",
  "properties": {
    "addr:full":"Rbla Sant Jordi (de), 105 Ripollet Barcelona 08291",
    "addr:housenumber":"105",
    "addr:postcode":"08291",
    "addr:street":"Rbla Sant Jordi De",
    "iso:country":"ES",
    "sg:address":"Rbla Sant Jordi (de), 105",
    "sg:city":"Ripollet",
    "sg:orig_category":"Molduras, Junquillos, Listones Y Molduras Perforadas",
    "sg:phone":"+34 936 92 48 38",
    "sg:postcode":"08291",
    "sg:province":"Barcelona",
    "wof:name":"Rivera Rodriguez Encarnacion",
    "wof:placetype":"venue"
},
  "geometry": {"coordinates":[2.1659231186,41.4950485229],"type":"Point"}
}