{
  "type": "Feature",
  "properties": {
    "addr:full":"Calle de Tren De Arganda, 12 Madrid Madrid 28032",
    "addr:housenumber":"12",
    "addr:postcode":"madrid;28032",
    "addr:street":"Calle De Tren De Arganda",
    "iso:country":"ES",
    "sg:address":"Calle de Tren De Arganda, 12",
    "sg:city":"Madrid",
    "sg:orig_category":"Contenedores (mercanc\u00cdas)",
    "sg:phone":"+34 917 51 04 68",
    "sg:postcode":"28032",
    "sg:province":"Madrid",
    "wof:name":"Sanchez Martinez Miguel Angel",
    "wof:placetype":"venue"
},
  "geometry": {"coordinates":[-3.6192359924,40.4034996033],"type":"Point"}
}