{
  "type": "Feature",
  "properties": {
    "iso:country":"ES",
    "sg:address":"Urb Playa Cristal, S/n",
    "sg:city":"Miami Platja",
    "sg:orig_category":"Caf\u00c9s, Bares, Cervecer\u00cdas",
    "sg:phone":"+34 977 81 18 35",
    "sg:postcode":"43892",
    "sg:province":"Tarragona",
    "wof:name":"Santos Miranda Mercedes",
    "wof:placetype":"venue"
},
  "geometry": {"coordinates":[0.9573349953,41.0249786377],"type":"Point"}
}