{
  "type": "Feature",
  "properties": {
    "addr:full":"Rond Pintor Garate (del), 70 Albalate Arzobispo Teruel 44540",
    "addr:housenumber":"70",
    "addr:postcode":"44540",
    "addr:street":"Rond Pintor Garate Del",
    "iso:country":"ES",
    "sg:address":"Rond Pintor Garate (del), 70",
    "sg:city":"Albalate Arzobispo",
    "sg:orig_category":"Art\u00cdculos Funerarios (al Por Menor)",
    "sg:phone":"+34 978 81 25 50",
    "sg:postcode":"44540",
    "sg:province":"Teruel",
    "wof:name":"Funeraria Gasco S.l.",
    "wof:placetype":"venue"
},
  "geometry": {"coordinates":[-0.5094739795,41.1234474182],"type":"Point"}
}