{
  "type": "Feature",
  "properties": {
    "iso:country":"ES",
    "sg:address":"Carr Impressors Oliva, 12",
    "sg:city":"Girona",
    "sg:orig_category":"Muebles Y Accesorios Para Cocinas Y Cuartos De Ba\u00d1o (al Por Menor)",
    "sg:phone":"+34 972 21 87 19",
    "sg:postcode":"17001",
    "sg:province":"Girona",
    "wof:name":"Fabricuina Taules I Cadires S. L.",
    "wof:placetype":"venue"
},
  "geometry": {"coordinates":[2.8156440258,41.9830703735],"type":"Point"}
}