{
  "type": "Feature",
  "properties": {
    "addr:full":"Av Sarria, 40 Barcelona Barcelona 08029",
    "addr:housenumber":"40",
    "addr:postcode":"08029",
    "addr:street":"Av Sarria",
    "iso:country":"ES",
    "sg:address":"Av Sarria, 40",
    "sg:city":"Barcelona",
    "sg:orig_category":"Grafistas",
    "sg:phone":"+34 933 63 39 68",
    "sg:postcode":"08029",
    "sg:province":"Barcelona",
    "sg:website":"www.prontorotuloteam.com",
    "wof:name":"Prontorotulo Team S.l.",
    "wof:placetype":"venue"
},
  "geometry": {"coordinates":[2.1424939632,41.3907775879],"type":"Point"}
}