{
  "type": "Feature",
  "properties": {
    "iso:country":"ES",
    "sg:address":"Carrer de Maragall, 22",
    "sg:city":"S. Adria Besos",
    "sg:orig_category":"Guarder\u00cdas",
    "sg:phone":"+34 933 81 73 70",
    "sg:postcode":"08930",
    "sg:province":"Barcelona",
    "wof:name":"Carmona Gil Yolanda",
    "wof:placetype":"venue"
},
  "geometry": {"coordinates":[2.2183051109,41.4289970398],"type":"Point"}
}