{
  "type": "Feature",
  "properties": {
    "addr:full":"Trepuco, S/n Mao Islas Baleares 07703",
    "addr:postcode":"07703",
    "addr:street":"Trepuco S / N",
    "iso:country":"ES",
    "sg:address":"Trepuco, S/n",
    "sg:city":"Mao",
    "sg:orig_category":"Reciclaje, Desguace De Veh\u00cdculos",
    "sg:phone":"+34 971 36 54 18",
    "sg:postcode":"07703",
    "sg:province":"Islas Baleares",
    "wof:name":"Alarcon Cuadros S.l.",
    "wof:placetype":"venue"
},
  "geometry": {"coordinates":[4.2652339935,39.8772163391],"type":"Point"}
}