{
  "type": "Feature",
  "properties": {
    "addr:full":"Calle de Rio San Pedro, 11 Oviedo Asturias 33001",
    "addr:housenumber":"11",
    "addr:postcode":"33001",
    "addr:street":"Calle De Rio San Pedro",
    "iso:country":"ES",
    "sg:address":"Calle de Rio San Pedro, 11",
    "sg:city":"Oviedo",
    "sg:orig_category":"Cajas De Ahorro",
    "sg:phone":"+34 985 21 09 98",
    "sg:postcode":"33001",
    "sg:province":"Asturias",
    "sg:website":"www.cajastur.es",
    "wof:name":"Caja De Ahorros De Asturias",
    "wof:placetype":"venue"
},
  "geometry": {"coordinates":[-5.8518228531,43.3672790527],"type":"Point"}
}