{
  "type": "Feature",
  "properties": {
    "iso:country":"ES",
    "sg:address":"Donostia Ibilbidea, 86",
    "sg:city":"Astigarraga",
    "sg:orig_category":"Pintura, Barniz, Productos Asimilables (fabricaci\u00d3n, Al Por Mayor)",
    "sg:phone":"+34 943 33 37 70",
    "sg:postcode":"20115",
    "sg:province":"Guip\u00f9zcoa",
    "wof:name":"Casta\u00f1o Borreguero Pedro Marcial",
    "wof:placetype":"venue"
},
  "geometry": {"coordinates":[-1.9516700506,43.2813720703],"type":"Point"}
}