{
  "type": "Feature",
  "properties": {
    "iso:country":"ES",
    "sg:address":"Av Santiga, 26",
    "sg:city":"Santa Perpetua De Mogoda",
    "sg:orig_category":"Plomeros",
    "sg:phone":"+34 935 74 24 46",
    "sg:postcode":"08130",
    "sg:province":"Barcelona",
    "wof:name":"Ramirez Fernandez Antonio",
    "wof:placetype":"venue"
},
  "geometry": {"coordinates":[2.1802699566,41.5370826721],"type":"Point"}
}