{
  "type": "Feature",
  "properties": {
    "addr:full":"Calle de Husillo, 29 Estacion Madrid 28400",
    "addr:housenumber":"29",
    "addr:postcode":"28400",
    "addr:street":"Calle De Husillo",
    "iso:country":"ES",
    "sg:address":"Calle de Husillo, 29",
    "sg:city":"Estacion",
    "sg:orig_category":"Negocio De Madera",
    "sg:phone":"+34 918 49 97 70",
    "sg:postcode":"28400",
    "sg:province":"Madrid",
    "sg:website":"www.luhersa.com",
    "wof:name":"Puertas Luhersa S.l.",
    "wof:placetype":"venue"
},
  "geometry": {"coordinates":[-3.9919650555,40.6455612183],"type":"Point"}
}