{
  "type": "Feature",
  "properties": {
    "addr:full":"Calle de Monte Gorbea, 9 Miranda Ebro Burgos 09200",
    "addr:housenumber":"9",
    "addr:postcode":"09200",
    "addr:street":"Calle De Monte Gorbea",
    "iso:country":"ES",
    "sg:address":"Calle de Monte Gorbea, 9",
    "sg:city":"Miranda Ebro",
    "sg:orig_category":"Transportes Mar\u00cdtimos",
    "sg:phone":"+34 947 34 77 60",
    "sg:postcode":"09200",
    "sg:province":"Burgos",
    "sg:website":"www.jsvlogisti.com",
    "wof:name":"J.s.v. Logisti S.l.",
    "wof:placetype":"venue"
},
  "geometry": {"coordinates":[-2.9375610352,42.6868400574],"type":"Point"}
}