{
  "type": "Feature",
  "properties": {
    "addr:full":"Calle de Real, 2 Camarena Toledo 45180",
    "addr:housenumber":"2",
    "addr:postcode":"45180",
    "addr:street":"Calle De Real",
    "iso:country":"ES",
    "sg:address":"Calle de Real, 2",
    "sg:city":"Camarena",
    "sg:orig_category":"Molduras, Junquillos, Listones Y Molduras Perforadas",
    "sg:phone":"+34 918 17 40 66",
    "sg:postcode":"45180",
    "sg:province":"Toledo",
    "wof:name":"Mariscal Agudo Felix",
    "wof:placetype":"venue"
},
  "geometry": {"coordinates":[-4.1232638359,40.090965271],"type":"Point"}
}