{
  "type": "Feature",
  "properties": {
    "addr:full":"Rua Aguieira, S/n Grove Pontevedra 36980",
    "addr:housenumber":"s",
    "addr:postcode":"36980",
    "addr:street":"Rua Aguieira;/ N Grove",
    "iso:country":"ES",
    "sg:address":"Rua Aguieira, S/n",
    "sg:city":"Grove",
    "sg:classifiers":[
        {
            "category":"Autos & Motor Vehicles",
            "subcategory":"Automobile Sales",
            "type":"Retail Goods"
        }
    ],
    "sg:phone":"+34 986 73 25 49",
    "sg:postcode":"36980",
    "sg:province":"Pontevedra",
    "wof:name":"Auto Escuela O Grove S.l.",
    "wof:placetype":"venue"
},
  "geometry": {"coordinates":[-8.8684043884,42.4974098206],"type":"Point"}
}