{
  "type": "Feature",
  "properties": {
    "iso:country":"ES",
    "sg:address":"Calle de Teneria, S/n",
    "sg:city":"Torre Esteban Hambran",
    "sg:orig_category":"Charcuter\u00cdas (al Por Mayor)",
    "sg:phone":"+34 925 79 52 48",
    "sg:postcode":"45920",
    "sg:province":"Toledo",
    "wof:name":"Reguz S. L.",
    "wof:placetype":"venue"
},
  "geometry": {"coordinates":[-4.025138855,39.8618774414],"type":"Point"}
}