{
  "type": "Feature",
  "properties": {
    "addr:full":"Dels Rajolers, 18 P.i. Masia Del Juez Valencia 46900",
    "addr:housenumber":"18",
    "addr:postcode":"46900",
    "addr:street":"Rajolers;P.I. Masia Del Juez",
    "iso:country":"ES",
    "sg:address":"Dels Rajolers, 18",
    "sg:city":"P.i. Masia Del Juez",
    "sg:orig_category":"Empresas De Carpinter\u00cda Met\u00c1lica",
    "sg:phone":"+34 961 58 05 39",
    "sg:postcode":"46900",
    "sg:province":"Valencia",
    "wof:name":"Aluminios Ramjo S.l.",
    "wof:placetype":"venue"
},
  "geometry": {"coordinates":[-0.3768048882,39.4702377319],"type":"Point"}
}