{
  "type": "Feature",
  "properties": {
    "addr:full":"Laubide Auzoa, 25 Legazpi Guip\u00f9zcoa 20230",
    "addr:housenumber":"25",
    "addr:postcode":"20230",
    "addr:street":"Laubide Auzoa;Guipu\u0300Zcoa",
    "iso:country":"ES",
    "sg:address":"Laubide Auzoa, 25",
    "sg:city":"Legazpi",
    "sg:orig_category":"Confecci\u00d3n De Trajes Para Se\u00d1oras",
    "sg:phone":"+34 943 73 02 95",
    "sg:postcode":"20230",
    "sg:province":"Guip\u00f9zcoa",
    "wof:name":"Confecciones Sanchez",
    "wof:placetype":"venue"
},
  "geometry": {"coordinates":[-2.3363120556,43.0572776794],"type":"Point"}
}