{
  "type": "Feature",
  "properties": {
    "addr:full":"Carrer de Bruc, 39 Barcelona Barcelona 08010",
    "addr:housenumber":"39",
    "addr:postcode":"08010",
    "addr:street":"Carrer De Bruc",
    "iso:country":"ES",
    "sg:address":"Carrer de Bruc, 39",
    "sg:city":"Barcelona",
    "sg:orig_category":"Confecci\u00d3n (fabricaci\u00d3n, Al Por Mayor)",
    "sg:phone":"+34 933 02 13 24",
    "sg:postcode":"08010",
    "sg:province":"Barcelona",
    "wof:name":"Pepa Garcia S.l.",
    "wof:placetype":"venue"
},
  "geometry": {"coordinates":[2.1726229191,41.3918151855],"type":"Point"}
}