{
  "type": "Feature",
  "properties": {
    "addr:full":"Calle de Pablo Picasso, 21 Salamanca Salamanca 37005",
    "addr:housenumber":"21",
    "addr:postcode":"37005",
    "addr:street":"Calle De Pablo Picasso",
    "iso:country":"ES",
    "sg:address":"Calle de Pablo Picasso, 21",
    "sg:city":"Salamanca",
    "sg:orig_category":"Electricidad: Instaladores",
    "sg:phone":"+34 923 25 54 66",
    "sg:postcode":"37005",
    "sg:province":"Salamanca",
    "wof:name":"Mi.fase S.l.",
    "wof:placetype":"venue"
},
  "geometry": {"coordinates":[-5.6576690674,40.975982666],"type":"Point"}
}