{
  "type": "Feature",
  "properties": {
    "iso:country":"ES",
    "sg:address":"Carrer de Muntaner, 106",
    "sg:city":"Barcelona",
    "sg:orig_category":"Flores Y Plantas Naturales (al Por Mayor)",
    "sg:phone":"+34 934 51 88 82",
    "sg:postcode":"08036",
    "sg:province":"Barcelona",
    "wof:name":"Aparicio Bellver Laura",
    "wof:placetype":"venue"
},
  "geometry": {"coordinates":[2.1565227509,41.3888282776],"type":"Point"}
}