{
  "type": "Feature",
  "properties": {
    "iso:country":"ES",
    "sg:address":"Carrer de Baro De Malda, 21",
    "sg:city":"Hospitalet Llobregat",
    "sg:orig_category":"Institutos De Belleza",
    "sg:phone":"+34 933 37 90 43",
    "sg:postcode":"08901",
    "sg:province":"Barcelona",
    "wof:name":"Martin Perez Mirian",
    "wof:placetype":"venue"
},
  "geometry": {"coordinates":[2.0999209881,41.3607635498],"type":"Point"}
}