{
  "type": "Feature",
  "properties": {
    "iso:country":"ES",
    "sg:address":"Carrer de Margarida Xirgu, 12",
    "sg:city":"Rubi",
    "sg:orig_category":"Ortopedia General",
    "sg:phone":"+34 936 97 18 03",
    "sg:postcode":"08191",
    "sg:province":"Barcelona",
    "wof:name":"Alari Preixens Maria Cinta",
    "wof:placetype":"venue"
},
  "geometry": {"coordinates":[2.0311779976,41.4953155518],"type":"Point"}
}