{
  "type": "Feature",
  "properties": {
    "iso:country":"ES",
    "sg:address":"Pg Pare Manyanet, 47",
    "sg:city":"Tremp",
    "sg:orig_category":"Venta, Montaje De Neum\u00c1ticos",
    "sg:phone":"+34 973 65 02 80",
    "sg:postcode":"25620",
    "sg:province":"Lleida",
    "wof:name":"Pneumatics Pepin S.c.",
    "wof:placetype":"venue"
},
  "geometry": {"coordinates":[0.8940539956,42.1677589417],"type":"Point"}
}