{
  "type": "Feature",
  "properties": {
    "addr:full":"Calle de I\u00d1aki Deuna, 8 Ondarroa Vizcaya 48700",
    "addr:housenumber":"8",
    "addr:postcode":"48700",
    "addr:street":"Calle De In\u0303Aki Deuna",
    "iso:country":"ES",
    "sg:address":"Calle de I\u00d1aki Deuna, 8",
    "sg:city":"Ondarroa",
    "sg:orig_category":"Asociaciones Y Clubs Deportivos",
    "sg:phone":"+34 946 83 02 43",
    "sg:postcode":"48700",
    "sg:province":"Vizcaya",
    "wof:name":"Sociedad Deportiva De Pelota Vasca Ondar Gain",
    "wof:placetype":"venue"
},
  "geometry": {"coordinates":[-2.4242539406,43.3201255798],"type":"Point"}
}