{
  "type": "Feature",
  "properties": {
    "iso:country":"ES",
    "sg:address":"Avda Santa Maria, 5",
    "sg:city":"Meliana",
    "sg:orig_category":"Librer\u00cdas",
    "sg:phone":"+34 961 49 50 15",
    "sg:postcode":"46133",
    "sg:province":"Valencia",
    "wof:name":"Porras Garcia Vanesa",
    "wof:placetype":"venue"
},
  "geometry": {"coordinates":[-0.3492709994,39.5290870667],"type":"Point"}
}