{
  "type": "Feature",
  "properties": {
    "addr:full":"Carrer de Montseny, 2 Barcelona Barcelona 08012",
    "addr:housenumber":"2",
    "addr:postcode":"08012",
    "addr:street":"Carrer De Montseny",
    "iso:country":"ES",
    "sg:address":"Carrer de Montseny, 2",
    "sg:city":"Barcelona",
    "sg:orig_category":"Ense\u00d1anza: Profesiones Art\u00cdsticas",
    "sg:phone":"+34 932 37 05 08",
    "sg:postcode":"08012",
    "sg:province":"Barcelona",
    "wof:name":"Navarro Chuecos Antonio",
    "wof:placetype":"venue"
},
  "geometry": {"coordinates":[2.153801918,41.4013748169],"type":"Point"}
}