{
  "type": "Feature",
  "properties": {
    "addr:full":"Carrer de Sant Jaume, 10 Manresa Barcelona 08241",
    "addr:housenumber":"10",
    "addr:postcode":"08241",
    "addr:street":"Carrer De Sant Jaume",
    "iso:country":"ES",
    "sg:address":"Carrer de Sant Jaume, 10",
    "sg:city":"Manresa",
    "sg:orig_category":"Elementos Para Suelos Prefabricados",
    "sg:phone":"+34 938 74 37 63",
    "sg:postcode":"08241",
    "sg:province":"Barcelona",
    "wof:name":"Muxi Codina Jose Maria",
    "wof:placetype":"venue"
},
  "geometry": {"coordinates":[1.8360719681,41.721496582],"type":"Point"}
}