{
  "type": "Feature",
  "properties": {
    "addr:full":"Carrer de Riu De L'or, 13 Barcelona Barcelona 08034",
    "addr:housenumber":"13",
    "addr:postcode":"08034",
    "addr:street":"Carrer De Riu De L'Or",
    "iso:country":"ES",
    "sg:address":"Carrer de Riu De L'or, 13",
    "sg:city":"Barcelona",
    "sg:orig_category":"Reposter\u00cdas",
    "sg:phone":"+34 932 80 22 75",
    "sg:postcode":"08034",
    "sg:province":"Barcelona",
    "wof:name":"Web Terre-centro Habitat",
    "wof:placetype":"venue"
},
  "geometry": {"coordinates":[2.1239984035,41.3929481506],"type":"Point"}
}