{
  "type": "Feature",
  "properties": {
    "addr:full":"Calle de Doctor Piga, 4 Madrid Madrid 28012",
    "addr:housenumber":"4",
    "addr:postcode":"28012",
    "addr:street":"Calle De Doctor Piga",
    "iso:country":"ES",
    "sg:address":"Calle de Doctor Piga, 4",
    "sg:city":"Madrid",
    "sg:orig_category":"Iglesia Cat\u00d3lica",
    "sg:phone":"+34 915 27 49 01",
    "sg:postcode":"28012",
    "sg:province":"Madrid",
    "wof:name":"Parroquia De San Lorenzo",
    "wof:placetype":"venue"
},
  "geometry": {"coordinates":[-3.698769331,40.4086647034],"type":"Point"}
}