{
  "type": "Feature",
  "properties": {
    "addr:full":"Calle de Alberche, 19 Madrid Madrid 28045",
    "addr:housenumber":"19",
    "addr:postcode":"madrid;28045",
    "addr:street":"Calle De Alberche",
    "iso:country":"ES",
    "sg:address":"Calle de Alberche, 19",
    "sg:city":"Madrid",
    "sg:orig_category":"Fabricaci\u00d3n, Importaci\u00d3n, Venta De Material De Telefon\u00cda, Peritelefon\u00cda",
    "sg:phone":"+34 914 67 69 89",
    "sg:postcode":"28045",
    "sg:province":"Madrid",
    "wof:name":"Nextel Telecomunicaciones S.a.",
    "wof:placetype":"venue"
},
  "geometry": {"coordinates":[-3.6803152561,40.397857666],"type":"Point"}
}