{
  "type": "Feature",
  "properties": {
    "addr:full":"Calle de Virgen De Todos Los Santos, 9 Sevilla Sevilla 41011",
    "addr:housenumber":"9",
    "addr:postcode":"41011",
    "addr:street":"Calle De Virgen De Todos Los Santos",
    "iso:country":"ES",
    "sg:address":"Calle de Virgen De Todos Los Santos, 9",
    "sg:city":"Sevilla",
    "sg:orig_category":"Asociaciones, Organismos Culturales Y Socioeducativos",
    "sg:phone":"+34 954 45 91 12",
    "sg:postcode":"41011",
    "sg:province":"Sevilla",
    "wof:name":"Centro Cultural Y Recreativo Parque Los Principes",
    "wof:placetype":"venue"
},
  "geometry": {"coordinates":[-6.0035290718,37.375415802],"type":"Point"}
}