{
  "type": "Feature",
  "properties": {
    "iso:country":"ES",
    "sg:address":"Calle de Luisa Fernanda, 21",
    "sg:city":"Madrid",
    "sg:orig_category":"Procuradores",
    "sg:phone":"+34 915 47 00 56",
    "sg:postcode":"28008",
    "sg:province":"Madrid",
    "wof:name":"Tejedor Moyano Jose-buenaventura",
    "wof:placetype":"venue"
},
  "geometry": {"coordinates":[-3.7151648998,40.4254188538],"type":"Point"}
}