{
  "type": "Feature",
  "properties": {
    "iso:country":"ES",
    "sg:address":"Avda Canarias, 353",
    "sg:city":"Vecindario",
    "sg:orig_category":"Bazares, Art\u00cdculos De Limpieza Y De Cocina (al Por Menor)",
    "sg:phone":"+34 928 75 15 73",
    "sg:postcode":"35110",
    "sg:province":"Las Palmas",
    "wof:name":"Florido Ramirez Jose",
    "wof:placetype":"venue"
},
  "geometry": {"coordinates":[-15.4457368851,27.8434562683],"type":"Point"}
}