{
  "type": "Feature",
  "properties": {
    "iso:country":"ES",
    "sg:address":"Pase Alcobendas (de), 12",
    "sg:city":"Alcobendas",
    "sg:orig_category":"Inversiones",
    "sg:phone":"+34 916 50 70 30",
    "sg:postcode":"28109",
    "sg:province":"Madrid",
    "wof:name":"Alza Inversiones S.l.",
    "wof:placetype":"venue"
},
  "geometry": {"coordinates":[-3.6255605221,40.5269393921],"type":"Point"}
}