{
  "type": "Feature",
  "properties": {
    "addr:full":"Avda Burgos, 52 Valladolid Valladolid 47009",
    "addr:housenumber":"52",
    "addr:postcode":"47009",
    "addr:street":"Avda Burgos",
    "iso:country":"ES",
    "sg:address":"Avda Burgos, 52",
    "sg:city":"Valladolid",
    "sg:orig_category":"Molduras, Junquillos, Listones Y Molduras Perforadas",
    "sg:phone":"+34 983 34 10 05",
    "sg:postcode":"47009",
    "sg:province":"Valladolid",
    "wof:name":"Armesto Alvarez Jose Antonio",
    "wof:placetype":"venue"
},
  "geometry": {"coordinates":[-4.7287640572,41.6667137146],"type":"Point"}
}