{
  "type": "Feature",
  "properties": {
    "addr:full":"Calle de San Fernando, 16 Santander Cantabria 39010",
    "addr:housenumber":"16",
    "addr:postcode":"39010",
    "addr:street":"Calle De San Fernando",
    "iso:country":"ES",
    "sg:address":"Calle de San Fernando, 16",
    "sg:city":"Santander",
    "sg:classifiers":[
        {
            "category":"Shopping",
            "subcategory":"Crafts & Fabrics",
            "type":"Retail Goods"
        }
    ],
    "sg:phone":"+34 942 37 23 62",
    "sg:postcode":"39010",
    "sg:province":"Cantabria",
    "sg:tags":[
        "manta",
        "de",
        "fabricaci\u00d3n"
    ],
    "wof:name":"Fernandez Martinez Luis",
    "wof:placetype":"venue"
},
  "geometry": {"coordinates":[-3.8195800781,43.460521698],"type":"Point"}
}