{
  "type": "Feature",
  "properties": {
    "iso:country":"ES",
    "sg:address":"Calle de General Bergareche, 6",
    "sg:city":"Irun",
    "sg:orig_category":"Sellos De Goma Y Met\u00c1licos",
    "sg:phone":"+34 943 62 84 66",
    "sg:postcode":"20304",
    "sg:province":"Guip\u00f9zcoa",
    "wof:name":"Hernandez Asensio Alberto",
    "wof:placetype":"venue"
},
  "geometry": {"coordinates":[-1.7830890417,43.3405685425],"type":"Point"}
}