{
  "type": "Feature",
  "properties": {
    "iso:country":"ES",
    "sg:address":"Carr Alacant, 7",
    "sg:city":"Pu\u00e7ol",
    "sg:orig_category":"Centros Empresariales",
    "sg:phone":"+34 961 46 57 79",
    "sg:postcode":"46530",
    "sg:province":"Valencia",
    "wof:name":"Genopu S.l.",
    "wof:placetype":"venue"
},
  "geometry": {"coordinates":[-0.3070890009,39.6165390015],"type":"Point"}
}