{
  "type": "Feature",
  "properties": {
    "addr:full":"Lintzirin Poligonoa, 11 Arragua Guip\u00f9zcoa 20180",
    "addr:housenumber":"11",
    "addr:postcode":"20180",
    "addr:street":"Lintzirin Poligonoa;Guipu\u0300Zcoa",
    "iso:country":"ES",
    "sg:address":"Lintzirin Poligonoa, 11",
    "sg:city":"Arragua",
    "sg:orig_category":"Tiendas De Grano, Frutas Y Legumbres Secas (al Por Menor)",
    "sg:phone":"+34 943 49 36 22",
    "sg:postcode":"20180",
    "sg:province":"Guip\u00f9zcoa",
    "wof:name":"Iglesias Acosta Jose",
    "wof:placetype":"venue"
},
  "geometry": {"coordinates":[-1.8629590273,43.2992401123],"type":"Point"}
}