{
  "type": "Feature",
  "properties": {
    "iso:country":"ES",
    "sg:address":"Calle de Ganeta, 1",
    "sg:city":"Arenas -areeta",
    "sg:orig_category":"Inmobiliaria (agencias)",
    "sg:phone":"+34 944 64 62 44",
    "sg:postcode":"48930",
    "sg:province":"Vizcaya",
    "wof:name":"Gorro\u00f1o Ormaza Carmen",
    "wof:placetype":"venue"
},
  "geometry": {"coordinates":[-3.0088820457,43.3288574219],"type":"Point"}
}