{
  "type": "Feature",
  "properties": {
    "addr:full":"Calle de Obispo, 6 Antequera M\u00e1laga 29200",
    "addr:housenumber":"6",
    "addr:postcode":"29200",
    "addr:street":"Calle De Obispo",
    "iso:country":"ES",
    "sg:address":"Calle de Obispo, 6",
    "sg:city":"Antequera",
    "sg:orig_category":"Papeler\u00cdas, Librer\u00cdas",
    "sg:phone":"+34 952 84 09 86",
    "sg:postcode":"29200",
    "sg:province":"M\u00e1laga",
    "wof:name":"Maese Fidalgo Paz",
    "wof:placetype":"venue"
},
  "geometry": {"coordinates":[-4.5565190315,37.0190505981],"type":"Point"}
}