{
  "type": "Feature",
  "properties": {
    "addr:full":"Pl. Baja Navarra, S/n Agoitz Navarra 31430",
    "addr:housenumber":"/ n",
    "addr:postcode":"31430",
    "addr:street":"Pl.;Navarra S",
    "iso:country":"ES",
    "sg:address":"Pl. Baja Navarra, S/n",
    "sg:city":"Agoitz",
    "sg:orig_category":"Pr\u00c9stamos Personales E Hipotecarios",
    "sg:phone":"+34 948 33 60 06",
    "sg:postcode":"31430",
    "sg:province":"Navarra",
    "wof:name":"Lora Rodriguez Jose Maria",
    "wof:placetype":"venue"
},
  "geometry": {"coordinates":[-1.3681930304,42.7861404419],"type":"Point"}
}