{
  "type": "Feature",
  "properties": {
    "addr:full":"Las Vegas, 3 Potes Cantabria 39570",
    "addr:postcode":"39570",
    "iso:country":"ES",
    "sg:address":"Las Vegas, 3",
    "sg:city":"Potes",
    "sg:orig_category":"Plomeros",
    "sg:phone":"+34 942 73 04 38",
    "sg:postcode":"39570",
    "sg:province":"Cantabria",
    "wof:name":"Fernandez Alonso Angel",
    "wof:placetype":"venue"
},
  "geometry": {"coordinates":[-4.6223387718,43.1537704468],"type":"Point"}
}