{
  "type": "Feature",
  "properties": {
    "iso:country":"ES",
    "sg:address":"Carrer de Dentol, 31",
    "sg:city":"Can Pastilla",
    "sg:orig_category":"Deportes N\u00c1uticos, Acu\u00c1ticos Y Subacu\u00c1ticos: Art\u00cdculos Y Equipo (al Por Menor)",
    "sg:phone":"+34 971 26 78 74",
    "sg:postcode":"07610",
    "sg:province":"Islas Baleares",
    "wof:name":"Robuschi Mera Daniel",
    "wof:placetype":"venue"
},
  "geometry": {"coordinates":[2.7091779709,39.5383224487],"type":"Point"}
}