{
  "type": "Feature",
  "properties": {
    "addr:full":"Carr Lepanto, 20 Mercadal Islas Baleares 07740",
    "addr:housenumber":"20",
    "addr:postcode":"07740",
    "addr:street":"Carr Lepanto",
    "iso:country":"ES",
    "sg:address":"Carr Lepanto, 20",
    "sg:city":"Mercadal",
    "sg:orig_category":"Empresarios",
    "sg:phone":"+34 971 37 55 89",
    "sg:postcode":"07740",
    "sg:province":"Islas Baleares",
    "wof:name":"Mascaro Gomila Gabriel",
    "wof:placetype":"venue"
},
  "geometry": {"coordinates":[4.1529397964,40.00730896],"type":"Point"}
}