{
  "type": "Feature",
  "properties": {
    "iso:country":"ES",
    "sg:address":"C/ Vicent Andres Estelles, 32",
    "sg:city":"Elche",
    "sg:classifiers":[
        {
            "category":"Autos & Motor Vehicles",
            "subcategory":"Automobile Sales",
            "type":"Retail Goods"
        }
    ],
    "sg:phone":"+34 966 61 02 99",
    "sg:postcode":"03202",
    "sg:province":"Alicante",
    "wof:name":"Tramitacion Gestion E Inversiones Elx S.l.",
    "wof:placetype":"venue"
},
  "geometry": {"coordinates":[-0.6805220246,38.2727432251],"type":"Point"}
}