{
  "type": "Feature",
  "properties": {
    "addr:full":"Cjo Cuarto, S/n Sevilla Sevilla 41014",
    "addr:housenumber":"s / n",
    "addr:postcode":"41014",
    "addr:street":"Cuarto",
    "iso:country":"ES",
    "sg:address":"Cjo Cuarto, S/n",
    "sg:city":"Sevilla",
    "sg:orig_category":"Agricultores, Agricultores",
    "sg:phone":"+34 954 68 92 60",
    "sg:postcode":"41014",
    "sg:province":"Sevilla",
    "wof:name":"Asociacion Criadores De Caballos De Pura Raza Espa\u00d1ola",
    "wof:placetype":"venue"
},
  "geometry": {"coordinates":[-5.9647536278,37.3367156982],"type":"Point"}
}