{
  "type": "Feature",
  "properties": {
    "iso:country":"ES",
    "sg:address":"Carr Escoles, S/n",
    "sg:city":"Sort",
    "sg:orig_category":"Centros De Educaci\u00d3n Especial",
    "sg:phone":"+34 973 62 02 22",
    "sg:postcode":"25560",
    "sg:province":"Lleida",
    "wof:name":"Colegio Nacional Angel Serafin Casanovas",
    "wof:placetype":"venue"
},
  "geometry": {"coordinates":[1.1308150291,42.4134101868],"type":"Point"}
}