{
  "type": "Feature",
  "properties": {
    "iso:country":"ES",
    "sg:address":"Calle de Candeleda, 1",
    "sg:city":"Avila",
    "sg:orig_category":"Art\u00cdculos De Regalo (al Por Menor)",
    "sg:phone":"+34 920 25 31 37",
    "sg:postcode":"05001",
    "sg:province":"\u00c1vila",
    "wof:name":"Gonzalez Moreno Felix",
    "wof:placetype":"venue"
},
  "geometry": {"coordinates":[-4.6930952072,40.655670166],"type":"Point"}
}