{
  "type": "Feature",
  "properties": {
    "addr:full":"Afores, S/n Vinebre Tarragona 43792",
    "addr:housenumber":"s / n",
    "addr:postcode":"43792",
    "addr:street":"Afores",
    "iso:country":"ES",
    "sg:address":"Afores, S/n",
    "sg:city":"Vinebre",
    "sg:orig_category":"Vinos Y Licores (venta Al Por Menor)",
    "sg:phone":"+34 977 40 57 82",
    "sg:postcode":"43792",
    "sg:province":"Tarragona",
    "wof:name":"Poquet Pros Ramon",
    "wof:placetype":"venue"
},
  "geometry": {"coordinates":[0.589048028,41.1856117249],"type":"Point"}
}