{
  "type": "Feature",
  "properties": {
    "iso:country":"ES",
    "sg:address":"Av General Luque, 85",
    "sg:city":"Inca",
    "sg:orig_category":"Centros De Educaci\u00d3n Especial",
    "sg:phone":"+34 971 50 02 20",
    "sg:postcode":"07300",
    "sg:province":"Islas Baleares",
    "wof:name":"Centro De Educacion Infantil Sol Y Xend S.l.",
    "wof:placetype":"venue"
},
  "geometry": {"coordinates":[2.9083681107,39.7186737061],"type":"Point"}
}