{
  "type": "Feature",
  "properties": {
    "addr:full":"Calle de Rodrigo De Triana, S/n Aznalcazar Sevilla 41849",
    "addr:housenumber":"s / n",
    "addr:postcode":"41849",
    "addr:street":"Calle De Rodrigo De Triana",
    "iso:country":"ES",
    "sg:address":"Calle de Rodrigo De Triana, S/n",
    "sg:city":"Aznalcazar",
    "sg:orig_category":"Asilos De Ancianos. Centros Privados",
    "sg:phone":"+34 955 75 02 84",
    "sg:postcode":"41849",
    "sg:province":"Sevilla",
    "wof:name":"Fundacion Gracia Y Paz",
    "wof:placetype":"venue"
},
  "geometry": {"coordinates":[-6.2455439568,37.3050498962],"type":"Point"}
}