{
  "type": "Feature",
  "properties": {
    "addr:full":"Carr Major, 15 Puig Valencia 46540",
    "addr:housenumber":"15",
    "addr:postcode":"46540",
    "addr:street":"Carr Major",
    "iso:country":"ES",
    "sg:address":"Carr Major, 15",
    "sg:city":"Puig",
    "sg:orig_category":"Muebles, Minoristas",
    "sg:phone":"+34 961 47 29 37",
    "sg:postcode":"46540",
    "sg:province":"Valencia",
    "wof:name":"Gb Interiors S.l.",
    "wof:placetype":"venue"
},
  "geometry": {"coordinates":[-0.3034620881,39.5897216797],"type":"Point"}
}