{
  "type": "Feature",
  "properties": {
    "addr:full":"Carrer de Enric Prat De La Riba, 201 Hospitalet Llobregat Barcelona 08901",
    "addr:housenumber":"201",
    "addr:postcode":"08901",
    "addr:street":"Carrer De Enric Prat De La Riba",
    "iso:country":"ES",
    "sg:address":"Carrer de Enric Prat De La Riba, 201",
    "sg:city":"Hospitalet Llobregat",
    "sg:orig_category":"Trabajos De Fotocomposici\u00d3n",
    "sg:phone":"+34 933 38 97 28",
    "sg:postcode":"08901",
    "sg:province":"Barcelona",
    "wof:name":"Archs Garriga Montserrat",
    "wof:placetype":"venue"
},
  "geometry": {"coordinates":[2.1073207855,41.3616333008],"type":"Point"}
}