{
  "type": "Feature",
  "properties": {
    "iso:country":"ES",
    "sg:address":"Calle de Burgos, 5",
    "sg:city":"Vitoria-gasteiz",
    "sg:orig_category":"Contenedores (mercanc\u00cdas)",
    "sg:phone":"+34 945 28 63 91",
    "sg:postcode":"01002",
    "sg:province":"\u00c1lava",
    "wof:name":"Domingo Eduardo Gomez Urarte",
    "wof:placetype":"venue"
},
  "geometry": {"coordinates":[-2.6602060795,42.8550224304],"type":"Point"}
}