{
  "type": "Feature",
  "properties": {
    "addr:full":"Estda. De Vilardevos, S/n Rios Ourense 32611",
    "addr:housenumber":"s / n",
    "addr:postcode":"32611",
    "iso:country":"ES",
    "sg:address":"Estda. De Vilardevos, S/n",
    "sg:city":"Rios",
    "sg:orig_category":"Cajas De Ahorro",
    "sg:phone":"+34 988 42 50 46",
    "sg:postcode":"32611",
    "sg:province":"Ourense",
    "wof:name":"Caixa De Aforros De Vigo Ourense E Pontevedra",
    "wof:placetype":"venue"
},
  "geometry": {"coordinates":[-7.3494839668,41.9520835876],"type":"Point"}
}