{
  "type": "Feature",
  "properties": {
    "addr:full":"Avda Italia, 32 Huelva Huelva 21001",
    "addr:housenumber":"32",
    "addr:postcode":"21001",
    "addr:street":"Avda Italia",
    "iso:country":"ES",
    "sg:address":"Avda Italia, 32",
    "sg:city":"Huelva",
    "sg:orig_category":"Refiner\u00cdas De Petr\u00d3leo",
    "sg:phone":"+34 959 28 27 81",
    "sg:postcode":"21001",
    "sg:province":"Huelva",
    "wof:name":"Galpgest Petrogal Estaciones De Servicio S.l.u.",
    "wof:placetype":"venue"
},
  "geometry": {"coordinates":[-6.9518737793,37.2537651062],"type":"Point"}
}