{
  "type": "Feature",
  "properties": {
    "iso:country":"ES",
    "sg:address":"Pl Vila, 22",
    "sg:city":"Santa Coloma De Gramenet",
    "sg:orig_category":"Asesor\u00cda Fiscal Y Jur\u00cddica",
    "sg:phone":"+34 933 85 73 83",
    "sg:postcode":"08922",
    "sg:province":"Barcelona",
    "wof:name":"Asesoramiento Empresarial Dilma S. L.",
    "wof:placetype":"venue"
},
  "geometry": {"coordinates":[2.168610096,41.4337387085],"type":"Point"}
}