{
  "type": "Feature",
  "properties": {
    "addr:full":"Ctra Rubi, 288 Terrassa Barcelona 08228",
    "addr:housenumber":"288",
    "addr:postcode":"08228",
    "addr:street":"Ctra Rubi",
    "iso:country":"ES",
    "sg:address":"Ctra Rubi, 288",
    "sg:city":"Terrassa",
    "sg:orig_category":"Metales (labores, Pulido)",
    "sg:phone":"+34 937 83 53 98",
    "sg:postcode":"08228",
    "sg:province":"Barcelona",
    "sg:website":"www.coelbo.es",
    "wof:name":"Coelbo Control System S.l.",
    "wof:placetype":"venue"
},
  "geometry": {"coordinates":[2.0349860191,41.5328407288],"type":"Point"}
}