{
  "type": "Feature",
  "properties": {
    "iso:country":"ES",
    "sg:address":"Avda Carlos De Haya, 40",
    "sg:city":"Malaga",
    "sg:orig_category":"Asesor\u00cda Sobre Comunicaci\u00d3n De Empresas",
    "sg:phone":"+34 952 39 88 96",
    "sg:postcode":"29010",
    "sg:province":"M\u00e1laga",
    "wof:name":"Jimenez Cruz Jose Antonio",
    "wof:placetype":"venue"
},
  "geometry": {"coordinates":[-4.4446368217,36.7217597961],"type":"Point"}
}