{
  "type": "Feature",
  "properties": {
    "iso:country":"ES",
    "sg:address":"Calle de Velarde, 13",
    "sg:city":"Sevilla",
    "sg:orig_category":"Centros P\u00dablicos De Formaci\u00d3n Profesional Y T\u00c9cnica",
    "sg:phone":"+34 954 21 80 85",
    "sg:postcode":"41001",
    "sg:province":"Sevilla",
    "wof:name":"Colegio Oficial Ingenieria Tecnica Minera",
    "wof:placetype":"venue"
},
  "geometry": {"coordinates":[-5.9979290962,37.3849716187],"type":"Point"}
}