{
  "type": "Feature",
  "properties": {
    "addr:full":"Cra Mata (de), S/n Mataro Barcelona 08304",
    "addr:housenumber":"s",
    "addr:postcode":"08304",
    "addr:street":"/ N Mataro Barcelona",
    "iso:country":"ES",
    "sg:address":"Cra Mata (de), S/n",
    "sg:city":"Mataro",
    "sg:orig_category":"Fabricaci\u00d3n, Distribuci\u00d3n De Material Para La Climatizaci\u00d3n, Aireaci\u00d3n Y Ventilaci\u00d3n",
    "sg:phone":"+34 937 96 07 50",
    "sg:postcode":"08304",
    "sg:province":"Barcelona",
    "sg:website":"www.multi-wing.com",
    "wof:name":"Nielsen  Knud Finn",
    "wof:placetype":"venue"
},
  "geometry": {"coordinates":[2.4524469376,41.5485229492],"type":"Point"}
}