{
  "type": "Feature",
  "properties": {
    "iso:country":"ES",
    "sg:address":"Calle de Antonio 'el Sevillano', 2",
    "sg:city":"Sevilla",
    "sg:orig_category":"Inform\u00c1tica, Ofim\u00c1tica (estudios, Asesor\u00cda, Ingenier\u00cda, Formaci\u00d3n)",
    "sg:phone":"+34 954 93 43 66",
    "sg:postcode":"41009",
    "sg:province":"Sevilla",
    "wof:name":"Telecomputershop S.c.",
    "wof:placetype":"venue"
},
  "geometry": {"coordinates":[-5.9850974083,37.4107246399],"type":"Point"}
}