{
  "type": "Feature",
  "properties": {
    "addr:full":"Av Teular, S/n Sueca Valencia 46410",
    "addr:housenumber":"s",
    "addr:postcode":"46410",
    "addr:street":"Av Teular;/ N",
    "iso:country":"ES",
    "sg:address":"Av Teular, S/n",
    "sg:city":"Sueca",
    "sg:orig_category":"Cerrajer\u00cda, Ferrallista",
    "sg:phone":"+34 961 70 01 68",
    "sg:postcode":"46410",
    "sg:province":"Valencia",
    "wof:name":"Talleres Granell C.b.",
    "wof:placetype":"venue"
},
  "geometry": {"coordinates":[-0.2939789891,39.1984481812],"type":"Point"}
}