{
  "type": "Feature",
  "properties": {
    "addr:full":"Lug. Rinconcillo, S/n Poyales Del Hoyo \u00c1vila 05492",
    "addr:housenumber":"s",
    "addr:postcode":"05492",
    "addr:street":"Rinconcillo;/ N",
    "iso:country":"ES",
    "sg:address":"Lug. Rinconcillo, S/n",
    "sg:city":"Poyales Del Hoyo",
    "sg:orig_category":"Alquiler De Casas Y Habitaciones Amuebladas",
    "sg:phone":"+34 920 39 00 56",
    "sg:postcode":"05492",
    "sg:province":"\u00c1vila",
    "wof:name":"Enriquez Machota S.l.",
    "wof:placetype":"venue"
},
  "geometry": {"coordinates":[-5.1668691635,40.1736106873],"type":"Point"}
}