{
  "type": "Feature",
  "properties": {
    "iso:country":"ES",
    "sg:address":"Calle de San Francisco, 2",
    "sg:city":"Tarifa",
    "sg:orig_category":"Estancos",
    "sg:phone":"+34 956 68 40 31",
    "sg:postcode":"11380",
    "sg:province":"C\u00e1diz",
    "wof:name":"Manso Alvarez Patricio Miguel",
    "wof:placetype":"venue"
},
  "geometry": {"coordinates":[-5.602889061,36.0130500793],"type":"Point"}
}