{
  "type": "Feature",
  "properties": {
    "addr:full":"Calle de Doctor Braulio Busto, 23 Candas Asturias 33430",
    "addr:housenumber":"23",
    "addr:postcode":"33430",
    "addr:street":"Calle De Doctor Braulio Busto",
    "iso:country":"ES",
    "sg:address":"Calle de Doctor Braulio Busto, 23",
    "sg:city":"Candas",
    "sg:orig_category":"Ropa Para Se\u00d1oras (al Por Menor)",
    "sg:phone":"+34 985 87 16 00",
    "sg:postcode":"33430",
    "sg:province":"Asturias",
    "wof:name":"Junquera Vega Dolores",
    "wof:placetype":"venue"
},
  "geometry": {"coordinates":[-5.7656707764,43.5893745422],"type":"Point"}
}