{
  "type": "Feature",
  "properties": {
    "iso:country":"ES",
    "sg:address":"Calle de Capitan Bermejo, 42",
    "sg:city":"Mata",
    "sg:orig_category":"Bares, Piano",
    "sg:phone":"+34 925 74 71 86",
    "sg:postcode":"45534",
    "sg:province":"Toledo",
    "wof:name":"Ampuero Sede\u00f1o Luis",
    "wof:placetype":"venue"
},
  "geometry": {"coordinates":[-4.4383392334,39.9449234009],"type":"Point"}
}