{
  "type": "Feature",
  "properties": {
    "addr:full":"Calle de Eras, 1 Campillo De Deleitosa C\u00e1ceres 10329",
    "addr:housenumber":"1",
    "addr:postcode":"10329",
    "addr:street":"Calle De Eras;Ca\u0301Ceres",
    "iso:country":"ES",
    "sg:address":"Calle de Eras, 1",
    "sg:city":"Campillo De Deleitosa",
    "sg:orig_category":"Administraciones Regionales, Departamentales Y Locales",
    "sg:phone":"+34 927 57 50 22",
    "sg:postcode":"10329",
    "sg:province":"C\u00e1ceres",
    "wof:name":"Ayuntamiento De Campillo De Deleitosa",
    "wof:placetype":"venue"
},
  "geometry": {"coordinates":[-5.5725197792,39.703868866],"type":"Point"}
}