{
  "type": "Feature",
  "properties": {
    "iso:country":"ES",
    "sg:address":"Av Cubelles, 18",
    "sg:city":"Vilanova I La Geltru",
    "sg:orig_category":"Ense\u00d1anza Variada",
    "sg:phone":"+34 938 15 16 82",
    "sg:postcode":"08800",
    "sg:province":"Barcelona",
    "sg:website":"www.noronet.net",
    "wof:name":"Nironet S.l.",
    "wof:placetype":"venue"
},
  "geometry": {"coordinates":[1.7228519917,41.2211112976],"type":"Point"}
}