{
  "type": "Feature",
  "properties": {
    "iso:country":"ES",
    "sg:address":"Calle de Menacho, S/n",
    "sg:city":"Badajoz",
    "sg:orig_category":"Ropa Para Ni\u00d1os (al Por Menor)",
    "sg:phone":"+34 924 25 84 39",
    "sg:postcode":"06001",
    "sg:province":"Badajoz",
    "wof:name":"Ortigosa-carrasco S.c.",
    "wof:placetype":"venue"
},
  "geometry": {"coordinates":[-6.9732241631,38.8778991699],"type":"Point"}
}