{
  "type": "Feature",
  "properties": {
    "addr:full":"Calle de Toledo, 32 Petrer Alicante 03610",
    "addr:housenumber":"32",
    "addr:postcode":"03610",
    "addr:street":"Calle De Toledo",
    "iso:country":"ES",
    "sg:address":"Calle de Toledo, 32",
    "sg:city":"Petrer",
    "sg:orig_category":"Caf\u00c9s, Bares, Cervecer\u00cdas",
    "sg:phone":"+34 966 95 15 23",
    "sg:postcode":"03610",
    "sg:province":"Alicante",
    "wof:name":"Miralles Quiles Cesar",
    "wof:placetype":"venue"
},
  "geometry": {"coordinates":[-0.7834119797,38.4800682068],"type":"Point"}
}