{
  "type": "Feature",
  "properties": {
    "addr:full":"Av Pins, Dels (p.c.), 51 Porto Cristo Islas Baleares 07680",
    "addr:housenumber":"51",
    "addr:postcode":"07680",
    "addr:street":"Av Pins Dels P.C.;Baleares",
    "iso:country":"ES",
    "sg:address":"Av Pins, Dels (p.c.), 51",
    "sg:city":"Porto Cristo",
    "sg:orig_category":"Autob\u00das (explotaci\u00d3n Y Servicios De)",
    "sg:phone":"+34 971 82 10 42",
    "sg:postcode":"07680",
    "sg:province":"Islas Baleares",
    "wof:name":"Viajes San Francisco S.a.",
    "wof:placetype":"venue"
},
  "geometry": {"coordinates":[3.3309600353,39.5396690369],"type":"Point"}
}