{
  "type": "Feature",
  "properties": {
    "iso:country":"ES",
    "sg:address":"Calle de Arriba, 1",
    "sg:city":"Navafria",
    "sg:orig_category":"Transportes Por V\u00cdas Navegables",
    "sg:phone":"+34 921 50 60 17",
    "sg:postcode":"40161",
    "sg:province":"Segovia",
    "wof:name":"Martin Vicente Francisco",
    "wof:placetype":"venue"
},
  "geometry": {"coordinates":[-3.8216607571,41.0550308228],"type":"Point"}
}