{
  "type": "Feature",
  "properties": {
    "addr:full":"Avgd Castello, 54 Benicasim Castell\u00f3n 12560",
    "addr:housenumber":"54",
    "addr:postcode":"12560",
    "addr:street":"Castello",
    "iso:country":"ES",
    "sg:address":"Avgd Castello, 54",
    "sg:city":"Benicasim",
    "sg:orig_category":"Bares, Piano",
    "sg:phone":"+34 964 30 57 61",
    "sg:postcode":"12560",
    "sg:province":"Castell\u00f3n",
    "wof:name":"Lobato Santiago Andres",
    "wof:placetype":"venue"
},
  "geometry": {"coordinates":[0.0466559008,40.0530471802],"type":"Point"}
}