{
  "type": "Feature",
  "properties": {
    "addr:full":"Calle de Nicaragua, 26 Poligono Industrial Los Villares Salamanca 37184",
    "addr:housenumber":"26",
    "addr:postcode":"37184",
    "addr:street":"Calle De Nicaragua;Industrial",
    "iso:country":"ES",
    "sg:address":"Calle de Nicaragua, 26",
    "sg:city":"Poligono Industrial Los Villares",
    "sg:orig_category":"Colchones (fabricaci\u00d3n, Al Por Mayor, Al Por Menor)",
    "sg:phone":"+34 923 20 33 16",
    "sg:postcode":"37184",
    "sg:province":"Salamanca",
    "sg:website":"www.cibercolchon.com",
    "wof:name":"Hijos De Angel Sanchez S.l.",
    "wof:placetype":"venue"
},
  "geometry": {"coordinates":[-5.6439290047,40.9919433594],"type":"Point"}
}