{
  "type": "Feature",
  "properties": {
    "iso:country":"ES",
    "sg:address":"Calle de Virgen Del Socorro, 21",
    "sg:city":"Alacant",
    "sg:orig_category":"Inform\u00c1tica: Consultores",
    "sg:phone":"+34 965 26 16 58",
    "sg:postcode":"03002",
    "sg:province":"Alicante",
    "wof:name":"Vicedo Villanueva Carmen",
    "wof:placetype":"venue"
},
  "geometry": {"coordinates":[-0.4758926034,38.34765625],"type":"Point"}
}