{
  "type": "Feature",
  "properties": {
    "iso:country":"ES",
    "sg:address":"Carrer de Amadeu Vives, 3",
    "sg:city":"Arenys Munt",
    "sg:orig_category":"Lanas (al Por Mayor)",
    "sg:phone":"+34 937 95 00 09",
    "sg:postcode":"08358",
    "sg:province":"Barcelona",
    "wof:name":"Montes Duran Gina",
    "wof:placetype":"venue"
},
  "geometry": {"coordinates":[2.5384020805,41.6120643616],"type":"Point"}
}