{
  "type": "Feature",
  "properties": {
    "iso:country":"ES",
    "sg:address":"Pg Saladar, 58",
    "sg:city":"Denia",
    "sg:orig_category":"Centros De Coordinaci\u00d3n",
    "sg:phone":"+34 966 43 16 46",
    "sg:postcode":"03700",
    "sg:province":"Alicante",
    "wof:name":"March Salva S.l.",
    "wof:placetype":"venue"
},
  "geometry": {"coordinates":[0.1084199995,38.8376197815],"type":"Point"}
}