{
  "type": "Feature",
  "properties": {
    "iso:country":"ES",
    "sg:address":"Calle de Hernan Cortes, 15",
    "sg:city":"Pilas",
    "sg:orig_category":"Negocio De Materiales De Construcci\u00d3n",
    "sg:phone":"+34 954 75 05 32",
    "sg:postcode":"41840",
    "sg:province":"Sevilla",
    "wof:name":"Almacenes Mata S.l.",
    "wof:placetype":"venue"
},
  "geometry": {"coordinates":[-6.3071322441,37.3015289307],"type":"Point"}
}