{
  "type": "Feature",
  "properties": {
    "addr:full":"Calle de Pablo Vi, 7 Ciudad Rodrigo Salamanca 37500",
    "addr:housenumber":"7",
    "addr:postcode":"37500",
    "addr:street":"Calle De Pablo Vi",
    "iso:country":"ES",
    "sg:address":"Calle de Pablo Vi, 7",
    "sg:city":"Ciudad Rodrigo",
    "sg:orig_category":"Sociedades, Compa\u00d1\u00cdas Aseguradoras",
    "sg:phone":"+34 923 49 80 58",
    "sg:postcode":"37500",
    "sg:province":"Salamanca",
    "wof:name":"Union Mutuas Matepss",
    "wof:placetype":"venue"
},
  "geometry": {"coordinates":[-6.5300521851,40.604549408],"type":"Point"}
}