{
  "type": "Feature",
  "properties": {
    "iso:country":"ES",
    "sg:address":"Calle de Serranos, 33",
    "sg:city":"Salamanca",
    "sg:orig_category":"Caf\u00c9s, Bares, Cervecer\u00cdas",
    "sg:phone":"+34 923 21 82 39",
    "sg:postcode":"37008",
    "sg:province":"Salamanca",
    "wof:name":"Serranos 33 C.b.",
    "wof:placetype":"venue"
},
  "geometry": {"coordinates":[-5.6677961349,40.9622306824],"type":"Point"}
}