{
  "type": "Feature",
  "properties": {
    "addr:full":"Av Autopista Del Saler, 16 Valencia Valencia 46013",
    "addr:housenumber":"16",
    "addr:postcode":"46013",
    "addr:street":"Av Autopista Del Saler",
    "iso:country":"ES",
    "sg:address":"Av Autopista Del Saler, 16",
    "sg:city":"Valencia",
    "sg:orig_category":"Medias Y Calcetines (al Por Menor)",
    "sg:phone":"+34 963 73 20 29",
    "sg:postcode":"46013",
    "sg:province":"Valencia",
    "sg:website":"www.calzedonia.com",
    "wof:name":"Olmo Garcia Maria Dolores",
    "wof:placetype":"venue"
},
  "geometry": {"coordinates":[-0.3769130111,39.4687919617],"type":"Point"}
}