{
  "type": "Feature",
  "properties": {
    "addr:full":"Barr Santa Ma\u00d1a, 21 Santa Ma\u00e7a Vizcaya 48215",
    "addr:housenumber":"21",
    "addr:postcode":"48215",
    "addr:street":"Man\u0303A",
    "iso:country":"ES",
    "sg:address":"Barr Santa Ma\u00d1a, 21",
    "sg:city":"Santa Ma\u00e7a",
    "sg:orig_category":"Agentes, Concesionarios Y Sucursales De Veh\u00cdculos",
    "sg:phone":"+34 946 81 55 69",
    "sg:postcode":"48215",
    "sg:province":"Vizcaya",
    "wof:name":"Automoviles Kondia S. A.",
    "wof:placetype":"venue"
},
  "geometry": {"coordinates":[-2.6983869076,43.2204284668],"type":"Point"}
}