{
  "type": "Feature",
  "properties": {
    "addr:full":"Pase Medina (de), S/n Cabo Palos Murcia 30370",
    "addr:housenumber":"s",
    "addr:postcode":"30370",
    "addr:street":"/ N Cabo Palos",
    "iso:country":"ES",
    "sg:address":"Pase Medina (de), S/n",
    "sg:city":"Cabo Palos",
    "sg:orig_category":"Ense\u00d1anza Variada",
    "sg:phone":"+34 968 14 53 91",
    "sg:postcode":"30370",
    "sg:province":"Murcia",
    "wof:name":"Maravance S.l.",
    "wof:placetype":"venue"
},
  "geometry": {"coordinates":[-0.7274389863,37.6292953491],"type":"Point"}
}