{
  "type": "Feature",
  "properties": {
    "iso:country":"ES",
    "sg:address":"Pg Almogavers, 22",
    "sg:city":"Sabadell",
    "sg:orig_category":"Quincaller\u00cda (al Por Menor)",
    "sg:phone":"+34 937 10 03 88",
    "sg:postcode":"08204",
    "sg:province":"Barcelona",
    "wof:name":"Soler Torres Alonso",
    "wof:placetype":"venue"
},
  "geometry": {"coordinates":[2.1183741093,41.5293273926],"type":"Point"}
}