{
  "type": "Feature",
  "properties": {
    "iso:country":"ES",
    "sg:address":"Avda San Severiano, 41",
    "sg:city":"Cadiz",
    "sg:orig_category":"Supermercados Y Hipermercados",
    "sg:phone":"+34 956 27 93 16",
    "sg:postcode":"11007",
    "sg:province":"C\u00e1diz",
    "wof:name":"Sutega S.l.",
    "wof:placetype":"venue"
},
  "geometry": {"coordinates":[-6.2768979073,36.5172691345],"type":"Point"}
}