{
  "type": "Feature",
  "properties": {
    "addr:full":"Alexandre Rossello, 18 Montu\u00efri Islas Baleares 07230",
    "addr:housenumber":"18",
    "addr:postcode":"07230",
    "addr:street":"Alexandre Rossello;Islas",
    "iso:country":"ES",
    "sg:address":"Alexandre Rossello, 18",
    "sg:city":"Montu\u00efri",
    "sg:orig_category":"Ingenier\u00cda, Centros De Estudios (diversos)",
    "sg:phone":"+34 971 64 63 04",
    "sg:postcode":"07230",
    "sg:province":"Islas Baleares",
    "wof:name":"Frisamon Sxxi S.l.",
    "wof:placetype":"venue"
},
  "geometry": {"coordinates":[2.9825520515,39.5701408386],"type":"Point"}
}