{
  "type": "Feature",
  "properties": {
    "addr:full":"Av Gabriel Roca, 54 Sant Agusti Islas Baleares 07015",
    "addr:housenumber":"54",
    "addr:postcode":"07015",
    "addr:street":"Av Gabriel Roca",
    "iso:country":"ES",
    "sg:address":"Av Gabriel Roca, 54",
    "sg:city":"Sant Agusti",
    "sg:orig_category":"Librer\u00cdas",
    "sg:phone":"+34 971 40 20 83",
    "sg:postcode":"07015",
    "sg:province":"Islas Baleares",
    "wof:name":"Nova Area S.a.",
    "wof:placetype":"venue"
},
  "geometry": {"coordinates":[2.6182599068,39.5509223938],"type":"Point"}
}