{
  "type": "Feature",
  "properties": {
    "addr:full":"Crta Alca\u00f1iz-fraga, S/n Caspe Zaragoza 50700",
    "addr:housenumber":"s / n",
    "addr:postcode":"50700",
    "addr:street":"Crta Alcan\u0303Iz-Fraga",
    "iso:country":"ES",
    "sg:address":"Crta Alca\u00f1iz-fraga, S/n",
    "sg:city":"Caspe",
    "sg:orig_category":"Ropa Y Accesorios",
    "sg:phone":"+34 976 63 90 01",
    "sg:postcode":"50700",
    "sg:province":"Zaragoza",
    "wof:name":"Losan S. L.",
    "wof:placetype":"venue"
},
  "geometry": {"coordinates":[-0.0373200998,41.2406806946],"type":"Point"}
}