{
  "type": "Feature",
  "properties": {
    "addr:full":"Calle de Fernando Guanarteme, 22 Palmas De Gran Canaria Las Palmas 35007",
    "addr:housenumber":"22",
    "addr:postcode":"35007",
    "addr:street":"Calle De Fernando Guanarteme",
    "iso:country":"ES",
    "sg:address":"Calle de Fernando Guanarteme, 22",
    "sg:city":"Palmas De Gran Canaria",
    "sg:orig_category":"Muebles, Minoristas",
    "sg:phone":"+34 928 22 94 15",
    "sg:postcode":"35007",
    "sg:province":"Las Palmas",
    "wof:name":"Nuez Quesada Julio",
    "wof:placetype":"venue"
},
  "geometry": {"coordinates":[-15.4325780869,28.1392326355],"type":"Point"}
}