{
  "type": "Feature",
  "properties": {
    "addr:full":"Avda Marbella, 51 Coripe Sevilla 41780",
    "addr:housenumber":"51",
    "addr:postcode":"41780",
    "addr:street":"Avda Marbella",
    "iso:country":"ES",
    "sg:address":"Avda Marbella, 51",
    "sg:city":"Coripe",
    "sg:orig_category":"Asilos De Ancianos. Centros Privados",
    "sg:phone":"+34 955 85 85 03",
    "sg:postcode":"41780",
    "sg:province":"Sevilla",
    "wof:name":"Ayuntamiento De Coripe",
    "wof:placetype":"venue"
},
  "geometry": {"coordinates":[-5.4398798943,36.9744796753],"type":"Point"}
}