{
  "type": "Feature",
  "properties": {
    "iso:country":"ES",
    "sg:address":"Calle de Barbara, 14",
    "sg:city":"Sotogrande",
    "sg:orig_category":"Inmobiliaria (agencias)",
    "sg:phone":"+34 956 79 54 72",
    "sg:postcode":"11310",
    "sg:province":"C\u00e1diz",
    "wof:name":"Crismansalia S.l.",
    "wof:placetype":"venue"
},
  "geometry": {"coordinates":[-5.3065071106,36.282371521],"type":"Point"}
}