{
  "type": "Feature",
  "properties": {
    "addr:full":"Polig. Ind. Reboredo, 26 Monforte De Lemos Lugo 27420",
    "addr:housenumber":"26",
    "addr:postcode":"27420",
    "addr:street":"Polig. Ind. Reboredo",
    "iso:country":"ES",
    "sg:address":"Polig. Ind. Reboredo, 26",
    "sg:city":"Monforte De Lemos",
    "sg:orig_category":"Maquinaria Para Industrias Diversas",
    "sg:phone":"+34 982 40 46 23",
    "sg:postcode":"27420",
    "sg:province":"Lugo",
    "wof:name":"Ramiro Vila S.l.",
    "wof:placetype":"venue"
},
  "geometry": {"coordinates":[-7.5264849663,42.496887207],"type":"Point"}
}