{
  "type": "Feature",
  "properties": {
    "addr:full":"Sect Escultores, 5 Tres Cantos Madrid 28760",
    "addr:housenumber":"5",
    "addr:postcode":"28760",
    "addr:street":"Escultores",
    "iso:country":"ES",
    "sg:address":"Sect Escultores, 5",
    "sg:city":"Tres Cantos",
    "sg:orig_category":"Electromedicina: Equipo",
    "sg:phone":"+34 918 04 15 76",
    "sg:postcode":"28760",
    "sg:province":"Madrid",
    "wof:name":"Sibel S. A.",
    "wof:placetype":"venue"
},
  "geometry": {"coordinates":[-3.710695982,40.6140861511],"type":"Point"}
}