{
  "type": "Feature",
  "properties": {
    "addr:full":"Calle de Infanta Beatriz, 1 Granada Granada 18004",
    "addr:housenumber":"1",
    "addr:postcode":"18004",
    "addr:street":"Calle De Infanta Beatriz",
    "iso:country":"ES",
    "sg:address":"Calle de Infanta Beatriz, 1",
    "sg:city":"Granada",
    "sg:orig_category":"Pescader\u00cdas (al Por Menor)",
    "sg:phone":"+34 958 26 24 49",
    "sg:postcode":"18004",
    "sg:province":"Granada",
    "wof:name":"Membrilla Mesa Manuel",
    "wof:placetype":"venue"
},
  "geometry": {"coordinates":[-3.606877327,37.1733055115],"type":"Point"}
}