{
  "type": "Feature",
  "properties": {
    "addr:full":"Calle de Meteorologo Fco. Garcia, 42 Villafranqueza - Palamo Alicante 03112",
    "addr:housenumber":"42",
    "addr:postcode":"03112",
    "addr:street":"Calle De Meteorologo Fco. Garcia",
    "iso:country":"ES",
    "sg:address":"Calle de Meteorologo Fco. Garcia, 42",
    "sg:city":"Villafranqueza - Palamo",
    "sg:orig_category":"Mec\u00c1nico Del Autom\u00d3vil",
    "sg:phone":"+34 965 18 43 53",
    "sg:postcode":"03112",
    "sg:province":"Alicante",
    "wof:name":"Garcia Alhama Agustin",
    "wof:placetype":"venue"
},
  "geometry": {"coordinates":[-0.4690259993,38.4094772339],"type":"Point"}
}