{
  "type": "Feature",
  "properties": {
    "addr:full":"Eras, S/n Alcolea Del Pinar Guadalajara 19260",
    "addr:housenumber":"s / n",
    "addr:postcode":"19260",
    "addr:street":"Eras",
    "iso:country":"ES",
    "sg:address":"Eras, S/n",
    "sg:city":"Alcolea Del Pinar",
    "sg:orig_category":"Reposter\u00cdas",
    "sg:phone":"+34 949 30 00 58",
    "sg:postcode":"19260",
    "sg:province":"Guadalajara",
    "wof:name":"Palafox Albacete S.l.",
    "wof:placetype":"venue"
},
  "geometry": {"coordinates":[-2.4653708935,41.035949707],"type":"Point"}
}