{
  "type": "Feature",
  "properties": {
    "addr:full":"Carrer de Lleialtat, 48 Esplugues Llobregat Barcelona 08950",
    "addr:housenumber":"48",
    "addr:postcode":"08950",
    "addr:street":"Carrer De Lleialtat",
    "iso:country":"ES",
    "sg:address":"Carrer de Lleialtat, 48",
    "sg:city":"Esplugues Llobregat",
    "sg:orig_category":"Garajes De Veh\u00cdculos",
    "sg:phone":"+34 934 99 07 94",
    "sg:postcode":"08950",
    "sg:province":"Barcelona",
    "wof:name":"Circuit 96 S.l.",
    "wof:placetype":"venue"
},
  "geometry": {"coordinates":[2.0928180218,41.3737335205],"type":"Point"}
}