{
  "type": "Feature",
  "properties": {
    "iso:country":"ES",
    "sg:address":"Soutelo, S/n",
    "sg:city":"Soutelo",
    "sg:orig_category":"Empresas De Labores Complejas De Carga Y Descarga, Montaje Con Elevadores",
    "sg:phone":"+34 986 62 01 44",
    "sg:postcode":"36750",
    "sg:province":"Pontevedra",
    "wof:name":"Transportes \u00d1i S.l.",
    "wof:placetype":"venue"
},
  "geometry": {"coordinates":[-8.7706012726,41.9454116821],"type":"Point"}
}