{
  "type": "Feature",
  "properties": {
    "addr:full":"G.v. Hortaleza, 82 Madrid Madrid 28043",
    "addr:housenumber":"82",
    "addr:postcode":"madrid;28043",
    "iso:country":"ES",
    "sg:address":"G.v. Hortaleza, 82",
    "sg:city":"Madrid",
    "sg:orig_category":"Compraventa De Antig\u00dcedades",
    "sg:phone":"+34 917 21 97 21",
    "sg:postcode":"28043",
    "sg:province":"Madrid",
    "sg:website":"www.interiorismo.com",
    "wof:name":"Interiorismo Decoracion Y Eventos S.l.",
    "wof:placetype":"venue"
},
  "geometry": {"coordinates":[-3.6451978683,40.4687156677],"type":"Point"}
}