{
  "type": "Feature",
  "properties": {
    "iso:country":"ES",
    "sg:address":"Calle de Artilleria, 12",
    "sg:city":"Gijon",
    "sg:orig_category":"Tapicer\u00cdas",
    "sg:phone":"+34 985 35 28 71",
    "sg:postcode":"33201",
    "sg:province":"Asturias",
    "wof:name":"Roman Estevez Hermogenes",
    "wof:placetype":"venue"
},
  "geometry": {"coordinates":[-5.6654567719,43.5470237732],"type":"Point"}
}