{
  "type": "Feature",
  "properties": {
    "addr:full":"Calle de Presidente Adolfo Suarez, S/n Arganda Madrid 28500",
    "addr:housenumber":"s / n",
    "addr:postcode":"28500",
    "addr:street":"Calle De Presidente Adolfo Suarez",
    "iso:country":"ES",
    "sg:address":"Calle de Presidente Adolfo Suarez, S/n",
    "sg:city":"Arganda",
    "sg:orig_category":"Inmobiliaria (agencias)",
    "sg:phone":"+34 918 71 14 07",
    "sg:postcode":"28500",
    "sg:province":"Madrid",
    "wof:name":"Jones Lang Lasalle Espa\u00d1a S.a.",
    "wof:placetype":"venue"
},
  "geometry": {"coordinates":[-3.4458959103,40.2950706482],"type":"Point"}
}