{
  "type": "Feature",
  "properties": {
    "iso:country":"ES",
    "sg:address":"Calle de Nuestra Se\u00d1ora De La Asuncion, 3",
    "sg:city":"Valencia",
    "sg:orig_category":"Electrodom\u00c9sticos (al Por Menor)",
    "sg:phone":"+34 963 69 81 64",
    "sg:postcode":"46020",
    "sg:province":"Valencia",
    "wof:name":"Valiente Calvo Vicente",
    "wof:placetype":"venue"
},
  "geometry": {"coordinates":[-0.3595280051,39.4861679077],"type":"Point"}
}