{
  "type": "Feature",
  "properties": {
    "addr:full":"Carrer de Argentina, 2 S. Adria Besos Barcelona 08930",
    "addr:housenumber":"2",
    "addr:postcode":"08930",
    "addr:street":"Carrer De Argentina;Barcelona",
    "iso:country":"ES",
    "sg:address":"Carrer de Argentina, 2",
    "sg:city":"S. Adria Besos",
    "sg:orig_category":"Alquiler De V\u00cddeo",
    "sg:phone":"+34 934 62 09 66",
    "sg:postcode":"08930",
    "sg:province":"Barcelona",
    "wof:name":"Gutirrez Sanchez Antonio",
    "wof:placetype":"venue"
},
  "geometry": {"coordinates":[2.2126150131,41.4213066101],"type":"Point"}
}