{
  "type": "Feature",
  "properties": {
    "iso:country":"ES",
    "sg:address":"Avda Candina, 18",
    "sg:city":"Santander",
    "sg:orig_category":"Fabricaci\u00d3n De Jabones, Detergentes Y Lej\u00cdas",
    "sg:phone":"+34 942 33 35 00",
    "sg:postcode":"39011",
    "sg:province":"Cantabria",
    "wof:name":"Candina S.a.",
    "wof:placetype":"venue"
},
  "geometry": {"coordinates":[-3.8307189941,43.4524917603],"type":"Point"}
}