{
  "type": "Feature",
  "properties": {
    "addr:full":"Avgd Morera, 101 Badalona Barcelona 08915",
    "addr:housenumber":"101",
    "addr:postcode":"08915",
    "iso:country":"ES",
    "sg:address":"Avgd Morera, 101",
    "sg:city":"Badalona",
    "sg:orig_category":"Carnicer\u00cdas, Carnicer\u00cdas",
    "sg:phone":"+34 933 95 50 06",
    "sg:postcode":"08915",
    "sg:province":"Barcelona",
    "wof:name":"Soler Riu S.c.p",
    "wof:placetype":"venue"
},
  "geometry": {"coordinates":[2.2481179237,41.4622268677],"type":"Point"}
}