{
  "type": "Feature",
  "properties": {
    "addr:full":"Carrer de Lepant, 171 Barcelona Barcelona 08013",
    "addr:housenumber":"171",
    "addr:postcode":"08013",
    "addr:street":"Carrer De Lepant",
    "iso:country":"ES",
    "sg:address":"Carrer de Lepant, 171",
    "sg:city":"Barcelona",
    "sg:orig_category":"Adaptaciones, Acondicionamientos Especiales Para Veh\u00cdculos, Veh\u00cdculos Industriales",
    "sg:phone":"+34 932 32 34 65",
    "sg:postcode":"08013",
    "sg:province":"Barcelona",
    "wof:name":"Morales Aragones Juan S.l.",
    "wof:placetype":"venue"
},
  "geometry": {"coordinates":[2.1828401089,41.3995704651],"type":"Point"}
}