{
  "type": "Feature",
  "properties": {
    "addr:full":"Avda Nuestra Se\u00d1ora De La Fuensanta, 11 Cordoba C\u00f3rdoba 14010",
    "addr:housenumber":"11",
    "addr:postcode":"14010",
    "addr:street":"Avda Nuestra Sen\u0303Ora De La Fuensanta;Co\u0301Rdoba",
    "iso:country":"ES",
    "sg:address":"Avda Nuestra Se\u00d1ora De La Fuensanta, 11",
    "sg:city":"Cordoba",
    "sg:orig_category":"Electrodom\u00c9sticos (al Por Menor)",
    "sg:phone":"+34 957 25 12 85",
    "sg:postcode":"14010",
    "sg:province":"C\u00f3rdoba",
    "wof:name":"Urbano Fernandez Diego",
    "wof:placetype":"venue"
},
  "geometry": {"coordinates":[-4.7644639015,37.881652832],"type":"Point"}
}