{
  "type": "Feature",
  "properties": {
    "addr:full":"C/ Sant Cristofol, 37 Arenal Islas Baleares 07600",
    "addr:housenumber":"37",
    "addr:postcode":"07600",
    "addr:street":"C / Sant Cristofol",
    "iso:country":"ES",
    "sg:address":"C/ Sant Cristofol, 37",
    "sg:city":"Arenal",
    "sg:orig_category":"Muebles, Minoristas",
    "sg:phone":"+34 971 44 24 65",
    "sg:postcode":"07600",
    "sg:province":"Islas Baleares",
    "wof:name":"Mitjorn Mobles S.l.",
    "wof:placetype":"venue"
},
  "geometry": {"coordinates":[2.752327919,39.5086097717],"type":"Point"}
}