{
  "type": "Feature",
  "properties": {
    "addr:full":"Calle Javier Ferrero 13-15 Madrid 28002",
    "addr:housenumber":"13-15",
    "addr:postcode":"28002",
    "addr:street":"Calle Javier Ferrero",
    "iso:country":"ES",
    "sg:address":"Calle Javier Ferrero 13-15",
    "sg:city":"Madrid",
    "sg:classifiers":[
        {
            "category":"Professional",
            "subcategory":"Computer Services",
            "type":"Services"
        }
    ],
    "sg:postcode":"28002",
    "sg:tags":[
        "mobile",
        "vas",
        "community",
        "social-networking",
        "connected-devices",
        "android",
        "tablets",
        "smartphones"
    ],
    "sg:website":"http://www.buongiorno.com",
    "wof:name":"Buongiorno",
    "wof:placetype":"venue"
},
  "geometry": {"coordinates":[-3.6697641,40.4487974],"type":"Point"}
}