{
  "type": "Feature",
  "properties": {
    "addr:full":"C/ Joan Alcover, 44 Inca Islas Baleares 07300",
    "addr:housenumber":"44",
    "addr:postcode":"07300",
    "addr:street":"C / Joan Alcover",
    "iso:country":"ES",
    "sg:address":"C/ Joan Alcover, 44",
    "sg:city":"Inca",
    "sg:orig_category":"Estancos",
    "sg:phone":"+34 971 50 35 90",
    "sg:postcode":"07300",
    "sg:province":"Islas Baleares",
    "wof:name":"Gutierrez Avellaneda Maria Teresa",
    "wof:placetype":"venue"
},
  "geometry": {"coordinates":[2.9050900936,39.716884613],"type":"Point"}
}