{
  "type": "Feature",
  "properties": {
    "addr:full":"C. Maya, 44 Iru\u00f1a Navarra 31003",
    "addr:housenumber":"44",
    "addr:postcode":"31003",
    "addr:street":"Maya",
    "iso:country":"ES",
    "sg:address":"C. Maya, 44",
    "sg:city":"Iru\u00f1a",
    "sg:orig_category":"Ingeniero",
    "sg:phone":"+34 948 23 14 02",
    "sg:postcode":"31003",
    "sg:province":"Navarra",
    "wof:name":"Ciaurriz Ustarroz Manuel",
    "wof:placetype":"venue"
},
  "geometry": {"coordinates":[-1.6437540054,42.81275177],"type":"Point"}
}