{
  "type": "Feature",
  "properties": {
    "addr:full":"Carrer de Independencia, 32 Denia Alicante 03700",
    "addr:housenumber":"32",
    "addr:postcode":"03700",
    "addr:street":"Carrer De Independencia",
    "iso:country":"ES",
    "sg:address":"Carrer de Independencia, 32",
    "sg:city":"Denia",
    "sg:orig_category":"Extinci\u00d3n De Incendios: Material Y Suministros (fabricaci\u00d3n, Al Por Mayor)",
    "sg:phone":"+34 965 78 86 68",
    "sg:postcode":"03700",
    "sg:province":"Alicante",
    "wof:name":"Ivars Segui Vicente",
    "wof:placetype":"venue"
},
  "geometry": {"coordinates":[0.1008199975,38.8387107849],"type":"Point"}
}