{
  "type": "Feature",
  "properties": {
    "iso:country":"ES",
    "sg:address":"Reyes, 20",
    "sg:city":"Villamartin",
    "sg:classifiers":[
        {
            "category":"Taxi",
            "type":"Transportation"
        }
    ],
    "sg:phone":"+34 956 73 02 09",
    "sg:postcode":"11650",
    "sg:province":"C\u00e1diz",
    "wof:name":"Perez Gomez Obdulia",
    "wof:placetype":"venue"
},
  "geometry": {"coordinates":[-5.6441640854,36.8604202271],"type":"Point"}
}