{
  "type": "Feature",
  "properties": {
    "addr:full":"Ctra. Estacion, Km. 0003,0 Quintana Serena Badajoz 06450",
    "addr:postcode":"06450",
    "addr:street":"Ctra. Estacion;0003,0 Quintana Serena",
    "iso:country":"ES",
    "sg:address":"Ctra. Estacion, Km. 0003,0",
    "sg:city":"Quintana Serena",
    "sg:orig_category":"M\u00c1rmoles, Granitos Y Piedras Naturales",
    "sg:phone":"+34 924 77 71 60",
    "sg:postcode":"06450",
    "sg:province":"Badajoz",
    "wof:name":"Granitos Hermanos Orellana Tena C.b.",
    "wof:placetype":"venue"
},
  "geometry": {"coordinates":[-5.6712579727,38.743019104],"type":"Point"}
}