{
  "type": "Feature",
  "properties": {
    "addr:full":"Rbla Marquesa De Castellbell, 44 Sant Feliu Llobregat Barcelona 08980",
    "addr:housenumber":"44",
    "addr:postcode":"08980",
    "addr:street":"Rbla Marquesa De Castellbell",
    "iso:country":"ES",
    "sg:address":"Rbla Marquesa De Castellbell, 44",
    "sg:city":"Sant Feliu Llobregat",
    "sg:orig_category":"Cl\u00cdnicas Dentales",
    "sg:phone":"+34 936 85 30 51",
    "sg:postcode":"08980",
    "sg:province":"Barcelona",
    "wof:name":"Clinident",
    "wof:placetype":"venue"
},
  "geometry": {"coordinates":[2.0513470173,41.3819961548],"type":"Point"}
}