{
  "type": "Feature",
  "properties": {
    "addr:full":"Carr Blasco Iba\u00d1ez, 12 Burjassot Valencia 46100",
    "addr:housenumber":"12",
    "addr:postcode":"46100",
    "addr:street":"Carr Blasco Iban\u0303Ez",
    "iso:country":"ES",
    "sg:address":"Carr Blasco Iba\u00d1ez, 12",
    "sg:city":"Burjassot",
    "sg:orig_category":"Guarder\u00cdas",
    "sg:phone":"+34 963 63 80 75",
    "sg:postcode":"46100",
    "sg:province":"Valencia",
    "wof:name":"Marco Fabra Pilar",
    "wof:placetype":"venue"
},
  "geometry": {"coordinates":[-0.405934006,39.505821228],"type":"Point"}
}