{
  "type": "Feature",
  "properties": {
    "iso:country":"ES",
    "sg:address":"Calle de Calatayud, 3",
    "sg:city":"Zaragoza",
    "sg:orig_category":"Autob\u00das (explotaci\u00d3n Y Servicios De)",
    "sg:phone":"+34 976 22 98 86",
    "sg:postcode":"50005",
    "sg:province":"Zaragoza",
    "wof:name":"Automoviles Bajo Aragon S. A.",
    "wof:placetype":"venue"
},
  "geometry": {"coordinates":[-0.8923540711,41.6448745728],"type":"Point"}
}