{
  "type": "Feature",
  "properties": {
    "addr:full":"Rua Cesteiros, 8 Vigo Pontevedra 36202",
    "addr:housenumber":"8",
    "addr:postcode":"36202",
    "addr:street":"Rua Cesteiros",
    "iso:country":"ES",
    "sg:address":"Rua Cesteiros, 8",
    "sg:city":"Vigo",
    "sg:orig_category":"Cester\u00cda (fabricaci\u00d3n)",
    "sg:phone":"+34 986 43 34 70",
    "sg:postcode":"36202",
    "sg:province":"Pontevedra",
    "wof:name":"Suarez Davila Antonio",
    "wof:placetype":"venue"
},
  "geometry": {"coordinates":[-8.7260341644,42.2388725281],"type":"Point"}
}