{
  "type": "Feature",
  "properties": {
    "addr:full":"Carrer de Sant Antoni Abat, 46 Barcelona Barcelona 08001",
    "addr:housenumber":"46",
    "addr:postcode":"08001",
    "addr:street":"Carrer De Sant Antoni Abat",
    "iso:country":"ES",
    "sg:address":"Carrer de Sant Antoni Abat, 46",
    "sg:city":"Barcelona",
    "sg:orig_category":"Peluquer\u00cdas, Peluquer\u00cda Mixta",
    "sg:phone":"+34 934 42 27 44",
    "sg:postcode":"08001",
    "sg:province":"Barcelona",
    "wof:name":"Blanca 21 S.l.",
    "wof:placetype":"venue"
},
  "geometry": {"coordinates":[2.1639449596,41.379032135],"type":"Point"}
}