{
  "type": "Feature",
  "properties": {
    "addr:full":"Pol. Arenal, S/n Santovenia Pisuerga Valladolid 47155",
    "addr:housenumber":"s / n",
    "addr:postcode":"47155",
    "addr:street":"Pol. Arenal",
    "iso:country":"ES",
    "sg:address":"Pol. Arenal, S/n",
    "sg:city":"Santovenia Pisuerga",
    "sg:orig_category":"Fabricaci\u00d3n De Postres Y Desayunos Preparados",
    "sg:phone":"+34 983 40 08 50",
    "sg:postcode":"47155",
    "sg:province":"Valladolid",
    "wof:name":"Reposteria Panaderia El Arenal, Sl",
    "wof:placetype":"venue"
},
  "geometry": {"coordinates":[-4.6879892349,41.6882209778],"type":"Point"}
}