{
  "type": "Feature",
  "properties": {
    "addr:full":"Calle de Barbieri, 9 Madrid Madrid 28004",
    "addr:housenumber":"9",
    "addr:postcode":"madrid;28004",
    "addr:street":"Calle De Barbieri",
    "iso:country":"ES",
    "sg:address":"Calle de Barbieri, 9",
    "sg:city":"Madrid",
    "sg:orig_category":"Peluqueros: De Se\u00d1oras",
    "sg:phone":"+34 915 22 45 09",
    "sg:postcode":"28004",
    "sg:province":"Madrid",
    "wof:name":"Triguero Garcia Antonio",
    "wof:placetype":"venue"
},
  "geometry": {"coordinates":[-3.6983408928,40.4210319519],"type":"Point"}
}