{
  "type": "Feature",
  "properties": {
    "iso:country":"ES",
    "sg:address":"Barri Angles, S/n",
    "sg:city":"Montagut",
    "sg:orig_category":"Agricultores, Agricultores",
    "sg:phone":"+34 972 68 70 55",
    "sg:postcode":"17855",
    "sg:province":"Girona",
    "wof:name":"Societat Anonima Transformadora Suis",
    "wof:placetype":"venue"
},
  "geometry": {"coordinates":[2.5958900452,42.2317695618],"type":"Point"}
}