{
  "type": "Feature",
  "properties": {
    "addr:full":"Calle de Comercio, 37 Toledo Toledo 45001",
    "addr:housenumber":"37",
    "addr:postcode":"45001",
    "addr:street":"Calle De Comercio",
    "iso:country":"ES",
    "sg:address":"Calle de Comercio, 37",
    "sg:city":"Toledo",
    "sg:orig_category":"Abogados",
    "sg:phone":"+34 925 22 26 53",
    "sg:postcode":"45001",
    "sg:province":"Toledo",
    "wof:name":"Corrales Aragon Pablo Jose",
    "wof:placetype":"venue"
},
  "geometry": {"coordinates":[-4.0223178864,39.8592529297],"type":"Point"}
}