{
  "type": "Feature",
  "properties": {
    "iso:country":"ES",
    "sg:address":"Carr Joan D'austria, 19",
    "sg:city":"Eivissa",
    "sg:orig_category":"Asesor\u00cda Fiscal Y Jur\u00cddica",
    "sg:phone":"+34 971 31 54 62",
    "sg:postcode":"07800",
    "sg:province":"Islas Baleares",
    "wof:name":"Estudios Mercantiles Y Asesoria Contable S. A.",
    "wof:placetype":"venue"
},
  "geometry": {"coordinates":[1.4322949648,38.9097213745],"type":"Point"}
}