{
  "type": "Feature",
  "properties": {
    "iso:country":"ES",
    "sg:address":"Avda Constitucion, 18",
    "sg:city":"Santos De Maimona",
    "sg:orig_category":"Sociedades, Compa\u00d1\u00cdas Aseguradoras",
    "sg:phone":"+34 924 54 42 81",
    "sg:postcode":"06230",
    "sg:province":"Badajoz",
    "wof:name":"Seguros Ceron Ortiz S.c.",
    "wof:placetype":"venue"
},
  "geometry": {"coordinates":[-6.3794651031,38.4479751587],"type":"Point"}
}