{
  "type": "Feature",
  "properties": {
    "iso:country":"ES",
    "sg:address":"Calle de Cirilo Amoros, 9",
    "sg:city":"Valencia",
    "sg:orig_category":"Agencias Y Agentes Comerciales, Representantes",
    "sg:phone":"+34 963 53 00 51",
    "sg:postcode":"46004",
    "sg:province":"Valencia",
    "wof:name":"Espaiver Servicios Inmobiliarios S.l.u",
    "wof:placetype":"venue"
},
  "geometry": {"coordinates":[-0.3734599948,39.4666481018],"type":"Point"}
}