{
  "type": "Feature",
  "properties": {
    "addr:full":"Bo. Urberuaga, S/n Ubilla-urberuaga Vizcaya 48276",
    "addr:housenumber":"s",
    "addr:postcode":"48276",
    "addr:street":"Bo. Urberuaga;/ N",
    "iso:country":"ES",
    "sg:address":"Bo. Urberuaga, S/n",
    "sg:city":"Ubilla-urberuaga",
    "sg:classifiers":[
        {
            "category":"Manufacturing",
            "subcategory":"Metals",
            "type":"Manufacturing & Wholesale Goods"
        }
    ],
    "sg:phone":"+34 946 16 77 75",
    "sg:postcode":"48276",
    "sg:province":"Vizcaya",
    "sg:tags":[
        "en",
        "fundiciones"
    ],
    "wof:name":"Fundiciones Goicoechea S. L.",
    "wof:placetype":"venue"
},
  "geometry": {"coordinates":[-2.6833767891,43.3299293518],"type":"Point"}
}