{
  "type": "Feature",
  "properties": {
    "iso:country":"ES",
    "sg:address":"Prado Llano, 6",
    "sg:city":"Sierra Nevada",
    "sg:orig_category":"Bancos",
    "sg:phone":"+34 958 48 25 07",
    "sg:postcode":"18196",
    "sg:province":"Granada",
    "wof:name":"Caja Rural De Granada",
    "wof:placetype":"venue"
},
  "geometry": {"coordinates":[-3.0351140499,37.0072669983],"type":"Point"}
}