{
  "type": "Feature",
  "properties": {
    "iso:country":"ES",
    "sg:address":"Calle de Constitucion, 32",
    "sg:city":"Aldeacentenera",
    "sg:orig_category":"T\u00c9cnicos Veterinarios",
    "sg:phone":"+34 927 31 42 01",
    "sg:postcode":"10251",
    "sg:province":"C\u00e1ceres",
    "wof:name":"Murillo Mariscal Emilio",
    "wof:placetype":"venue"
},
  "geometry": {"coordinates":[-5.6322450638,39.5273971558],"type":"Point"}
}