{
  "type": "Feature",
  "properties": {
    "iso:country":"ES",
    "sg:address":"Pi i Margall, 7 baixos 2a",
    "sg:city":"Barcelona",
    "sg:classifiers":[
        {
            "category":"Professional",
            "subcategory":"Computer Services",
            "type":"Services"
        }
    ],
    "sg:postcode":"08024",
    "sg:tags":[
        "employment",
        "jobs",
        "job-seeking",
        "job-bank",
        "carreer-builder",
        "free-service"
    ],
    "sg:website":"http://www.ipsojobs.com/",
    "wof:name":"ipsojobs",
    "wof:placetype":"venue"
},
  "geometry": {"coordinates":[2.163194,41.406248],"type":"Point"}
}