{
  "type": "Feature",
  "properties": {
    "iso:country":"ES",
    "sg:address":"Calle de Sol (el), 1",
    "sg:city":"Icod De Los Vinos",
    "sg:orig_category":"Asesor\u00cda De Formaci\u00d3n Y Gesti\u00d3n De Personal",
    "sg:phone":"+34 922 81 54 13",
    "sg:postcode":"38430",
    "sg:province":"Santa Cruz De Tenerife",
    "wof:name":"Mendez Perez Maria Elena",
    "wof:placetype":"venue"
},
  "geometry": {"coordinates":[-16.7157497406,28.3690891266],"type":"Point"}
}