{
  "type": "Feature",
  "properties": {
    "iso:country":"ES",
    "sg:address":"Calle de Alfonso Vi, 51",
    "sg:city":"Miranda Ebro",
    "sg:orig_category":"Ense\u00d1anza Variada",
    "sg:phone":"+34 947 33 34 14",
    "sg:postcode":"09200",
    "sg:province":"Burgos",
    "wof:name":"Monsal Miranda S.l.",
    "wof:placetype":"venue"
},
  "geometry": {"coordinates":[-2.9420216084,42.6865081787],"type":"Point"}
}