{
  "type": "Feature",
  "properties": {
    "iso:country":"ES",
    "sg:address":"Calle de Gandia, 8",
    "sg:city":"Madrid",
    "sg:classifiers":[
        {
            "category":"Professional",
            "subcategory":"Business Services",
            "type":"Services"
        }
    ],
    "sg:phone":"+34 914 34 03 80",
    "sg:postcode":"28007",
    "sg:province":"Madrid",
    "sg:tags":[
        "control",
        "asesor\u00cda",
        "organizaci\u00d3n",
        "la",
        "de",
        "gesti\u00d3n",
        "y"
    ],
    "sg:website":"www.cobrador.com",
    "wof:name":"El Cobrador Eficaz S.l.",
    "wof:placetype":"venue"
},
  "geometry": {"coordinates":[-3.6710739136,40.3978729248],"type":"Point"}
}