{
  "type": "Feature",
  "properties": {
    "addr:full":"Calle de General Aguilera, 10 Ciudad Real Ciudad Real 13001",
    "addr:housenumber":"10",
    "addr:postcode":"13001",
    "addr:street":"Calle De General Aguilera",
    "iso:country":"ES",
    "sg:address":"Calle de General Aguilera, 10",
    "sg:city":"Ciudad Real",
    "sg:orig_category":"Asesor\u00cda Fiscal Y Jur\u00cddica",
    "sg:phone":"+34 926 21 69 37",
    "sg:postcode":"13001",
    "sg:province":"Ciudad Real",
    "wof:name":"Asesores Fiscales Integrales De Gestion S.l.",
    "wof:placetype":"venue"
},
  "geometry": {"coordinates":[-3.9284574986,38.9841423035],"type":"Point"}
}