{
  "type": "Feature",
  "properties": {
    "iso:country":"ES",
    "sg:address":"Avda Vena, 5",
    "sg:city":"Burgos",
    "sg:orig_category":"Comercio, Reparaci\u00d3n De Motocicletas, Bicicletas Y Piezas Sueltas",
    "sg:phone":"+34 947 21 33 11",
    "sg:postcode":"09005",
    "sg:province":"Burgos",
    "wof:name":"Gonzalez Orive S.l.l",
    "wof:placetype":"venue"
},
  "geometry": {"coordinates":[-3.6920289993,42.3472251892],"type":"Point"}
}