{
  "type": "Feature",
  "properties": {
    "addr:full":"Rua Lepanto, S/n Ferrol La Coru\u00f1a 15406",
    "addr:housenumber":"s / n",
    "addr:postcode":"15406",
    "addr:street":"Rua Lepanto;La Corun\u0303A",
    "iso:country":"ES",
    "sg:address":"Rua Lepanto, S/n",
    "sg:city":"Ferrol",
    "sg:orig_category":"Electricidad: Instaladores",
    "sg:phone":"+34 981 31 29 29",
    "sg:postcode":"15406",
    "sg:province":"La Coru\u00f1a",
    "wof:name":"Electro Montajes Cruz S.l.",
    "wof:placetype":"venue"
},
  "geometry": {"coordinates":[-8.2033481598,43.4856567383],"type":"Point"}
}