{
  "type": "Feature",
  "properties": {
    "addr:full":"Avd Ii (p Salvador), 81 Roda Albacete 02630",
    "addr:housenumber":"81",
    "addr:postcode":"02630",
    "addr:street":"Avd Ii P Salvador",
    "iso:country":"ES",
    "sg:address":"Avd Ii (p Salvador), 81",
    "sg:city":"Roda",
    "sg:orig_category":"Pintura, Barniz, Productos Asimilables (fabricaci\u00d3n, Al Por Mayor)",
    "sg:phone":"+34 967 44 36 57",
    "sg:postcode":"02630",
    "sg:province":"Albacete",
    "wof:name":"Serrano Escudero Paulino",
    "wof:placetype":"venue"
},
  "geometry": {"coordinates":[-2.1636590958,39.1957206726],"type":"Point"}
}