{
  "type": "Feature",
  "properties": {
    "addr:full":"Rua Carral, 21 Vigo Pontevedra 36202",
    "addr:housenumber":"21",
    "addr:postcode":"36202",
    "addr:street":"Rua Carral",
    "iso:country":"ES",
    "sg:address":"Rua Carral, 21",
    "sg:city":"Vigo",
    "sg:orig_category":"Moquetas, Alfombras (al Por Menor)",
    "sg:phone":"+34 986 43 00 09",
    "sg:postcode":"36202",
    "sg:province":"Pontevedra",
    "wof:name":"Garcia Cabezas Maria Elena",
    "wof:placetype":"venue"
},
  "geometry": {"coordinates":[-8.7248039246,42.2392463684],"type":"Point"}
}