{
  "type": "Feature",
  "properties": {
    "addr:full":"Pase Pinar, 2 Rozas De Madrid Madrid 28230",
    "addr:housenumber":"2",
    "addr:postcode":"28230",
    "addr:street":"Pinar",
    "iso:country":"ES",
    "sg:address":"Pase Pinar, 2",
    "sg:city":"Rozas De Madrid",
    "sg:orig_category":"Centros De Educaci\u00d3n Especial",
    "sg:phone":"+34 916 37 21 47",
    "sg:postcode":"28230",
    "sg:province":"Madrid",
    "wof:name":"Comunidad Autonoma De Madrid-centros De Educacion",
    "wof:placetype":"venue"
},
  "geometry": {"coordinates":[-3.8913800716,40.5247497559],"type":"Point"}
}