{
  "type": "Feature",
  "properties": {
    "iso:country":"ES",
    "sg:address":"Avda Castillo, 305",
    "sg:city":"Villaviciosa Odon",
    "sg:orig_category":"Doctores En Medicina",
    "sg:phone":"+34 916 16 06 90",
    "sg:postcode":"28670",
    "sg:province":"Madrid",
    "wof:name":"Sanchez Garcia Manuel",
    "wof:placetype":"venue"
},
  "geometry": {"coordinates":[-3.8717889786,40.3603096008],"type":"Point"}
}