{
  "type": "Feature",
  "properties": {
    "addr:full":"Ptge Celler, 1 S. Cugat Valles Barcelona 08172",
    "addr:housenumber":"1",
    "addr:postcode":"08172",
    "addr:street":"Ptge Celler;Barcelona",
    "iso:country":"ES",
    "sg:address":"Ptge Celler, 1",
    "sg:city":"S. Cugat Valles",
    "sg:orig_category":"Limpieza Industrial",
    "sg:phone":"+34 935 90 03 98",
    "sg:postcode":"08172",
    "sg:province":"Barcelona",
    "wof:name":"Beulen S.l.",
    "wof:placetype":"venue"
},
  "geometry": {"coordinates":[2.0842399597,41.4679336548],"type":"Point"}
}