{
  "type": "Feature",
  "properties": {
    "iso:country":"ES",
    "sg:address":"Carrer de Argullos, 82",
    "sg:city":"Barcelona",
    "sg:orig_category":"Zapatos (al Por Menor)",
    "sg:phone":"+34 933 53 28 83",
    "sg:postcode":"08016",
    "sg:province":"Barcelona",
    "wof:name":"Barmatic S.l.",
    "wof:placetype":"venue"
},
  "geometry": {"coordinates":[2.181456089,41.4419784546],"type":"Point"}
}