{
  "type": "Feature",
  "properties": {
    "addr:full":"Calle de Julian Rabanedo, 52 Madrid Madrid 28045",
    "addr:housenumber":"52",
    "addr:postcode":"madrid;28045",
    "addr:street":"Calle De Julian Rabanedo",
    "iso:country":"ES",
    "sg:address":"Calle de Julian Rabanedo, 52",
    "sg:city":"Madrid",
    "sg:orig_category":"Agencias Y Asesores De Publicidad",
    "sg:phone":"+34 915 30 96 17",
    "sg:postcode":"28045",
    "sg:province":"Madrid",
    "wof:name":"A.m. Publicidad General S.l.",
    "wof:placetype":"venue"
},
  "geometry": {"coordinates":[-3.6943697929,40.3877906799],"type":"Point"}
}