{
  "type": "Feature",
  "properties": {
    "iso:country":"ES",
    "sg:address":"Calle de Iberre Zeharbide, 3",
    "sg:city":"Elexalde Auzoa",
    "sg:orig_category":"Laboratorios Y Cl\u00cdnicas Veterinarias",
    "sg:phone":"+34 946 77 50 94",
    "sg:postcode":"48630",
    "sg:province":"Vizcaya",
    "wof:name":"Larrazabal Arrate Victor",
    "wof:placetype":"venue"
},
  "geometry": {"coordinates":[-2.93551898,43.4125518799],"type":"Point"}
}