{
  "type": "Feature",
  "properties": {
    "iso:country":"ES",
    "sg:address":"Carrer de Ramon Rocafull, 36",
    "sg:city":"Barcelona",
    "sg:orig_category":"Tratamiento De Metales",
    "sg:phone":"+34 934 20 66 71",
    "sg:postcode":"08032",
    "sg:province":"Barcelona",
    "wof:name":"Rodriguez Monterubio Jaime",
    "wof:placetype":"venue"
},
  "geometry": {"coordinates":[2.1527578831,41.4237442017],"type":"Point"}
}