{
  "type": "Feature",
  "properties": {
    "addr:full":"Calle de Villanueva, 16 Don Benito Badajoz 06400",
    "addr:housenumber":"16",
    "addr:postcode":"06400",
    "addr:street":"Calle De Villanueva",
    "iso:country":"ES",
    "sg:address":"Calle de Villanueva, 16",
    "sg:city":"Don Benito",
    "sg:orig_category":"Consultas M\u00c9dicas",
    "sg:phone":"+34 924 80 08 47",
    "sg:postcode":"06400",
    "sg:province":"Badajoz",
    "wof:name":"Centro Medico De Conductores Y Cazadores D.benito S.l.",
    "wof:placetype":"venue"
},
  "geometry": {"coordinates":[-5.8639888763,38.9548797607],"type":"Point"}
}