{
  "type": "Feature",
  "properties": {
    "addr:full":"Pl. Abastos, S/n Llangreu Asturias 33900",
    "addr:housenumber":"s / n",
    "addr:postcode":"33900",
    "addr:street":"Abastos",
    "iso:country":"ES",
    "sg:address":"Pl. Abastos, S/n",
    "sg:city":"Llangreu",
    "sg:orig_category":"Carnicer\u00cdas, Carnicer\u00cdas",
    "sg:phone":"+34 985 69 88 52",
    "sg:postcode":"33900",
    "sg:province":"Asturias",
    "wof:name":"Zapico Fernandez Maria Jose",
    "wof:placetype":"venue"
},
  "geometry": {"coordinates":[-5.684431076,43.2952537537],"type":"Point"}
}