{
  "type": "Feature",
  "properties": {
    "iso:country":"ES",
    "sg:address":"Calle de Hermanos De Pablo, 12",
    "sg:city":"Madrid",
    "sg:orig_category":"Estilistas Y Estudios De Estilo De Corte Y Confecci\u00d3n",
    "sg:phone":"+34 914 07 48 86",
    "sg:postcode":"28027",
    "sg:province":"Madrid",
    "wof:name":"Barrios Perez Antonio",
    "wof:placetype":"venue"
},
  "geometry": {"coordinates":[-3.6446390152,40.4358634949],"type":"Point"}
}