{
  "type": "Feature",
  "properties": {
    "iso:country":"ES",
    "sg:address":"Calle de Axular, 42",
    "sg:city":"Arizgoiti",
    "sg:orig_category":"Comerciantes Al Por Mayor De Vinos, Licores Y Alcoholes",
    "sg:phone":"+34 944 26 15 47",
    "sg:postcode":"48970",
    "sg:province":"Vizcaya",
    "wof:name":"Alvarez Feijoo Isabel",
    "wof:placetype":"venue"
},
  "geometry": {"coordinates":[-2.8960671425,43.2365226746],"type":"Point"}
}