{
  "type": "Feature",
  "properties": {
    "iso:country":"ES",
    "sg:address":"Ctra Chapatales, Km. 0003,6",
    "sg:city":"Chapatales",
    "sg:orig_category":"Producci\u00d3n De Abonos Y De Fertilizantes",
    "sg:phone":"+34 955 89 30 85",
    "sg:postcode":"41728",
    "sg:province":"Sevilla",
    "wof:name":"Agro Servicios Lopez Pastor S. L.",
    "wof:placetype":"venue"
},
  "geometry": {"coordinates":[-5.9962949753,37.3826408386],"type":"Point"}
}