{
  "type": "Feature",
  "properties": {
    "addr:full":"Calle de Navarra, 1 Bilbao Vizcaya 48001",
    "addr:housenumber":"1",
    "addr:postcode":"48001",
    "addr:street":"Calle De Navarra",
    "iso:country":"ES",
    "sg:address":"Calle de Navarra, 1",
    "sg:city":"Bilbao",
    "sg:orig_category":"Farmacias",
    "sg:phone":"+34 944 23 00 35",
    "sg:postcode":"48001",
    "sg:province":"Vizcaya",
    "wof:name":"Farmacia Susana Euba  Y Adriana Orueta, C.b.",
    "wof:placetype":"venue"
},
  "geometry": {"coordinates":[-2.9260060787,43.2605514526],"type":"Point"}
}