{
  "type": "Feature",
  "properties": {
    "iso:country":"ES",
    "sg:address":"Calle de Juan Bautista Uriarte, 30",
    "sg:city":"Kurtzea",
    "sg:orig_category":"Centros De Salud",
    "sg:phone":"+34 944 56 61 42",
    "sg:postcode":"48960",
    "sg:province":"Vizcaya",
    "wof:name":"Eguia Pe\u00f1a Miguel Angel",
    "wof:placetype":"venue"
},
  "geometry": {"coordinates":[-2.844506979,43.2300643921],"type":"Point"}
}