{
  "type": "Feature",
  "properties": {
    "addr:full":"Calle de Fornillos, 16 Madrid Madrid 28026",
    "addr:housenumber":"16",
    "addr:postcode":"madrid;28026",
    "addr:street":"Calle De Fornillos",
    "iso:country":"ES",
    "sg:address":"Calle de Fornillos, 16",
    "sg:city":"Madrid",
    "sg:orig_category":"Electromec\u00c1nica",
    "sg:phone":"+34 914 60 48 80",
    "sg:postcode":"28026",
    "sg:province":"Madrid",
    "wof:name":"Autos P. J. Martin S. L.",
    "wof:placetype":"venue"
},
  "geometry": {"coordinates":[-3.7140986919,40.3825492859],"type":"Point"}
}