{
  "type": "Feature",
  "properties": {
    "iso:country":"ES",
    "sg:address":"Rua Lepanto, 1",
    "sg:city":"Pontevedra",
    "sg:orig_category":"Ingenier\u00cda, Centros De Estudios (diversos)",
    "sg:phone":"+34 986 85 13 00",
    "sg:postcode":"36099",
    "sg:province":"Pontevedra",
    "wof:name":"Esproagro Ingenieria S.l.",
    "wof:placetype":"venue"
},
  "geometry": {"coordinates":[-8.6388692856,42.4304351807],"type":"Point"}
}