{
  "type": "Feature",
  "properties": {
    "addr:full":"Calle de Felix Chivite, 12 Cintruenigo Navarra 31592",
    "addr:housenumber":"12",
    "addr:postcode":"31592",
    "addr:street":"Calle De Felix Chivite",
    "iso:country":"ES",
    "sg:address":"Calle de Felix Chivite, 12",
    "sg:city":"Cintruenigo",
    "sg:orig_category":"Muebles, Minoristas",
    "sg:phone":"+34 948 81 13 20",
    "sg:postcode":"31592",
    "sg:province":"Navarra",
    "wof:name":"Ballester Ballester Jose",
    "wof:placetype":"venue"
},
  "geometry": {"coordinates":[-1.8059090376,42.0767478943],"type":"Point"}
}