{
  "type": "Feature",
  "properties": {
    "addr:full":"Carrer de Sant Josep, 20 Santa Coloma De Gramenet Barcelona 08922",
    "addr:housenumber":"20",
    "addr:postcode":"08922",
    "addr:street":"Carrer De Sant Josep",
    "iso:country":"ES",
    "sg:address":"Carrer de Sant Josep, 20",
    "sg:city":"Santa Coloma De Gramenet",
    "sg:orig_category":"Alimentaci\u00d3n General (al Por Menor)",
    "sg:phone":"+34 933 85 74 42",
    "sg:postcode":"08922",
    "sg:province":"Barcelona",
    "wof:name":"Antonio Ferreira Marco",
    "wof:placetype":"venue"
},
  "geometry": {"coordinates":[2.2106258869,41.4504699707],"type":"Point"}
}