{
  "type": "Feature",
  "properties": {
    "addr:full":"Ctra Pedrera-martin Jara, S/n Pedrera Sevilla 41566",
    "addr:housenumber":"s / n",
    "addr:postcode":"41566",
    "addr:street":"Ctra Pedrera-Martin Jara",
    "iso:country":"ES",
    "sg:address":"Ctra Pedrera-martin Jara, S/n",
    "sg:city":"Pedrera",
    "sg:orig_category":"Empresas De Carpinter\u00cda",
    "sg:phone":"+34 954 81 96 01",
    "sg:postcode":"41566",
    "sg:province":"Sevilla",
    "wof:name":"Alucisol S.l.l.",
    "wof:placetype":"venue"
},
  "geometry": {"coordinates":[-4.9014005661,37.2193527222],"type":"Point"}
}