{
  "type": "Feature",
  "properties": {
    "addr:full":"Avda Blas Infante (de), 50 Almeria Almer\u00eda 04006",
    "addr:housenumber":"50",
    "addr:postcode":"04006",
    "addr:street":"Avda Blas Infante De",
    "iso:country":"ES",
    "sg:address":"Avda Blas Infante (de), 50",
    "sg:city":"Almeria",
    "sg:orig_category":"Farmacias",
    "sg:phone":"+34 950 22 26 12",
    "sg:postcode":"04006",
    "sg:province":"Almer\u00eda",
    "wof:name":"Zoofarma S.l.",
    "wof:placetype":"venue"
},
  "geometry": {"coordinates":[-2.4518649578,36.8412132263],"type":"Point"}
}