{
  "type": "Feature",
  "properties": {
    "addr:full":"Calle de Pinos (los), 25 Lucena C\u00f3rdoba 14900",
    "addr:housenumber":"25",
    "addr:postcode":"14900",
    "addr:street":"Calle De Pinos Los",
    "iso:country":"ES",
    "sg:address":"Calle de Pinos (los), 25",
    "sg:city":"Lucena",
    "sg:orig_category":"Sales (al Por Mayor)",
    "sg:phone":"+34 957 50 30 18",
    "sg:postcode":"14900",
    "sg:province":"C\u00f3rdoba",
    "sg:website":"www.miraportusalud.com",
    "wof:name":"Ortiz Vilchez Antonio",
    "wof:placetype":"venue"
},
  "geometry": {"coordinates":[-4.4947361946,37.4036712646],"type":"Point"}
}