{
  "type": "Feature",
  "properties": {
    "addr:full":"Avda Blasco Iba\u00d1ez, 124 Valencia Valencia 46022",
    "addr:housenumber":"124",
    "addr:postcode":"46022",
    "addr:street":"Avda Blasco Iban\u0303Ez",
    "iso:country":"ES",
    "sg:address":"Avda Blasco Iba\u00d1ez, 124",
    "sg:city":"Valencia",
    "sg:orig_category":"Agencias Y Agentes Comerciales, Representantes",
    "sg:phone":"+34 963 71 36 29",
    "sg:postcode":"46022",
    "sg:province":"Valencia",
    "wof:name":"Bustos Iglesias Aurelio",
    "wof:placetype":"venue"
},
  "geometry": {"coordinates":[-0.3464260101,39.473110199],"type":"Point"}
}