{
  "type": "Feature",
  "properties": {
    "iso:country":"ES",
    "sg:address":"Huerta Los Bohorquez, 6",
    "sg:city":"Ubrique",
    "sg:orig_category":"Marroquiner\u00cda (confecci\u00d3n)",
    "sg:phone":"+34 956 46 41 40",
    "sg:postcode":"11600",
    "sg:province":"C\u00e1diz",
    "wof:name":"Toro Rincon Juan",
    "wof:placetype":"venue"
},
  "geometry": {"coordinates":[-5.4467940331,36.6768684387],"type":"Point"}
}