{
  "type": "Feature",
  "properties": {
    "iso:country":"ES",
    "sg:address":"Calle de Isla De La Palma (de La), 22",
    "sg:city":"San Sebastian De Los Reyes",
    "sg:orig_category":"Empresas De Pintura Y Revestimientos",
    "sg:phone":"+34 916 53 41 88",
    "sg:postcode":"28700",
    "sg:province":"Madrid",
    "wof:name":"Pinturas Marfil S.l.",
    "wof:placetype":"venue"
},
  "geometry": {"coordinates":[-3.6255059242,40.5569229126],"type":"Point"}
}