{
  "type": "Feature",
  "properties": {
    "addr:full":"Calle de Mendez Nu\u00d1ez, 17 Minas Riotinto Huelva 21660",
    "addr:housenumber":"17",
    "addr:postcode":"21660",
    "addr:street":"Calle De Mendez Nun\u0303Ez",
    "iso:country":"ES",
    "sg:address":"Calle de Mendez Nu\u00d1ez, 17",
    "sg:city":"Minas Riotinto",
    "sg:orig_category":"Farmacias",
    "sg:phone":"+34 959 59 02 87",
    "sg:postcode":"21660",
    "sg:province":"Huelva",
    "wof:name":"Gonzalez Hoyo Jose Luis",
    "wof:placetype":"venue"
},
  "geometry": {"coordinates":[-6.5932412148,37.6926612854],"type":"Point"}
}