{
  "type": "Feature",
  "properties": {
    "iso:country":"ES",
    "sg:address":"Calle de Almeria, 16",
    "sg:city":"Albanchez",
    "sg:orig_category":"Empresas De Carpinter\u00cda De Madera",
    "sg:phone":"+34 950 12 20 06",
    "sg:postcode":"04857",
    "sg:province":"Almer\u00eda",
    "wof:name":"Padilla Molina Pedro",
    "wof:placetype":"venue"
},
  "geometry": {"coordinates":[-2.1824848652,37.2843322754],"type":"Point"}
}