{
  "type": "Feature",
  "properties": {
    "iso:country":"ES",
    "sg:address":"Calle de Pasion (de La), 4",
    "sg:city":"Barco De Avila",
    "sg:orig_category":"Peluqueros: De Se\u00d1oras",
    "sg:phone":"+34 920 34 04 93",
    "sg:postcode":"05600",
    "sg:province":"\u00c1vila",
    "wof:name":"Garcia Talavan Maria Del Puerto",
    "wof:placetype":"venue"
},
  "geometry": {"coordinates":[-5.5254979134,40.3559074402],"type":"Point"}
}