{
  "type": "Feature",
  "properties": {
    "iso:country":"ES",
    "sg:address":"Calle de San Juan De La Pe\u00d1a, 188",
    "sg:city":"Zaragoza",
    "sg:orig_category":"Quincaller\u00cda (al Por Menor)",
    "sg:phone":"+34 976 52 30 69",
    "sg:postcode":"50015",
    "sg:province":"Zaragoza",
    "wof:name":"Artieda Plano Adela",
    "wof:placetype":"venue"
},
  "geometry": {"coordinates":[-0.8710743785,41.676322937],"type":"Point"}
}