{
  "type": "Feature",
  "properties": {
    "iso:country":"ES",
    "sg:address":"Carrer de Anselm Clave, 14",
    "sg:city":"Vilassar Dalt",
    "sg:orig_category":"Centros Comerciales Y Grandes Tiendas",
    "sg:phone":"+34 937 50 76 68",
    "sg:postcode":"08339",
    "sg:province":"Barcelona",
    "wof:name":"Pons Toral Maria Del Carmen",
    "wof:placetype":"venue"
},
  "geometry": {"coordinates":[2.3616290092,41.5183601379],"type":"Point"}
}