{
  "type": "Feature",
  "properties": {
    "addr:full":"Calle de Concepcion, 11 Burgos Burgos 09002",
    "addr:housenumber":"11",
    "addr:postcode":"09002",
    "addr:street":"Calle De Concepcion",
    "iso:country":"ES",
    "sg:address":"Calle de Concepcion, 11",
    "sg:city":"Burgos",
    "sg:orig_category":"Cajas De Ahorro",
    "sg:phone":"+34 947 26 42 70",
    "sg:postcode":"09002",
    "sg:province":"Burgos",
    "wof:name":"Caja De Ahorros Del Circulo Catolico Obrero De Burgos",
    "wof:placetype":"venue"
},
  "geometry": {"coordinates":[-3.7025930882,42.3369750977],"type":"Point"}
}