{
  "type": "Feature",
  "properties": {
    "iso:country":"ES",
    "sg:address":"Calle de Velazquez, 9",
    "sg:city":"Lebrija",
    "sg:orig_category":"Transportes Por V\u00cdas Navegables",
    "sg:phone":"+34 955 97 38 64",
    "sg:postcode":"41740",
    "sg:province":"Sevilla",
    "wof:name":"Bellido Cardenas Benito",
    "wof:placetype":"venue"
},
  "geometry": {"coordinates":[-6.0679211617,36.9192695618],"type":"Point"}
}