{
  "type": "Feature",
  "properties": {
    "addr:full":"Cmno Gaiztarro Nuevo, S/n Cuatrovientos Le\u00f3n 24400",
    "addr:housenumber":"s / n",
    "addr:postcode":"24400",
    "addr:street":"Cmno Gaiztarro Nuevo",
    "iso:country":"ES",
    "sg:address":"Cmno Gaiztarro Nuevo, S/n",
    "sg:city":"Cuatrovientos",
    "sg:orig_category":"Suministros Y Materiales Industriales",
    "sg:phone":"+34 987 42 73 32",
    "sg:postcode":"24400",
    "sg:province":"Le\u00f3n",
    "wof:name":"Herramientas Del Bierzo S.l.",
    "wof:placetype":"venue"
},
  "geometry": {"coordinates":[-6.6295471191,42.5611915588],"type":"Point"}
}