{
  "type": "Feature",
  "properties": {
    "addr:full":"Carrer de Napols, 33 Barcelona Barcelona 08018",
    "addr:housenumber":"33",
    "addr:postcode":"08018",
    "addr:street":"Carrer De Napols",
    "iso:country":"ES",
    "sg:address":"Carrer de Napols, 33",
    "sg:city":"Barcelona",
    "sg:orig_category":"Asesor\u00cda Sobre Comunicaci\u00d3n De Empresas",
    "sg:phone":"+34 933 00 16 14",
    "sg:postcode":"08018",
    "sg:province":"Barcelona",
    "wof:name":"Juanola Sistemas De Calidad S.l.",
    "wof:placetype":"venue"
},
  "geometry": {"coordinates":[2.1837799549,41.3918762207],"type":"Point"}
}