{
  "type": "Feature",
  "properties": {
    "addr:full":"Calle de Emperatriz Eugenia, 4 Granada Granada 18002",
    "addr:housenumber":"4",
    "addr:postcode":"18002",
    "addr:street":"Calle De Emperatriz Eugenia",
    "iso:country":"ES",
    "sg:address":"Calle de Emperatriz Eugenia, 4",
    "sg:city":"Granada",
    "sg:orig_category":"Panader\u00cdas, Panader\u00cdas",
    "sg:phone":"+34 958 27 20 52",
    "sg:postcode":"18002",
    "sg:province":"Granada",
    "wof:name":"Pedrosa Lara Jose",
    "wof:placetype":"venue"
},
  "geometry": {"coordinates":[-3.6064779758,37.1765670776],"type":"Point"}
}