{
  "type": "Feature",
  "properties": {
    "addr:full":"Calle de Sardoy, 5 San Lorenzo Murcia 30003",
    "addr:housenumber":"5",
    "addr:postcode":"30003",
    "addr:street":"Calle De Sardoy",
    "iso:country":"ES",
    "sg:address":"Calle de Sardoy, 5",
    "sg:city":"San Lorenzo",
    "sg:orig_category":"Fotocopias, Reprograf\u00cda",
    "sg:phone":"+34 968 24 75 97",
    "sg:postcode":"30003",
    "sg:province":"Murcia",
    "wof:name":"Galeria S.c.l",
    "wof:placetype":"venue"
},
  "geometry": {"coordinates":[-1.1257539988,37.9872055054],"type":"Point"}
}