{
  "type": "Feature",
  "properties": {
    "iso:country":"ES",
    "sg:address":"Plaz Eusebio Gurrutxaga, 2",
    "sg:city":"Zumaia",
    "sg:orig_category":"Cajas De Ahorro",
    "sg:phone":"+34 943 86 04 29",
    "sg:postcode":"20750",
    "sg:province":"Guip\u00f9zcoa",
    "wof:name":"Caja Laboral Popular",
    "wof:placetype":"venue"
},
  "geometry": {"coordinates":[-2.2593290806,43.2955284119],"type":"Point"}
}