{
  "type": "Feature",
  "properties": {
    "iso:country":"ES",
    "sg:address":"Rua Alonso Lopez, 6",
    "sg:city":"Ferrol",
    "sg:orig_category":"Quincaller\u00cda (al Por Menor)",
    "sg:phone":"+34 981 35 16 91",
    "sg:postcode":"15401",
    "sg:province":"La Coru\u00f1a",
    "wof:name":"Rodriguez Diaz Angel Antonio",
    "wof:placetype":"venue"
},
  "geometry": {"coordinates":[-8.2410764694,43.4842758179],"type":"Point"}
}