{
  "type": "Feature",
  "properties": {
    "addr:full":"Av Sarria, 44 Barcelona Barcelona 08029",
    "addr:housenumber":"44",
    "addr:postcode":"08029",
    "addr:street":"Av Sarria",
    "iso:country":"ES",
    "sg:address":"Av Sarria, 44",
    "sg:city":"Barcelona",
    "sg:orig_category":"Teatros Y Salas De Espect\u00c1culos",
    "sg:phone":"+34 934 30 91 56",
    "sg:postcode":"08029",
    "sg:province":"Barcelona",
    "wof:name":"Ferrer Sanvicente Bienvenido",
    "wof:placetype":"venue"
},
  "geometry": {"coordinates":[2.142072916,41.3908691406],"type":"Point"}
}