{
  "type": "Feature",
  "properties": {
    "iso:country":"ES",
    "sg:address":"Calle de Clara Del Rey, 54",
    "sg:city":"Madrid",
    "sg:orig_category":"Piedra, Vidrio, Cer\u00c1mica Y Porcelana",
    "sg:phone":"+34 914 15 78 47",
    "sg:postcode":"28002",
    "sg:province":"Madrid",
    "sg:website":"www.azulejosvalcarcel.com",
    "wof:name":"Valcarcel S.a.",
    "wof:placetype":"venue"
},
  "geometry": {"coordinates":[-3.6678860188,40.4461326599],"type":"Point"}
}