{
  "type": "Feature",
  "properties": {
    "addr:full":"Calle de Augusto Figueroa, 16 Madrid Madrid 28004",
    "addr:housenumber":"16",
    "addr:postcode":"madrid;28004",
    "addr:street":"Calle De Augusto Figueroa",
    "iso:country":"ES",
    "sg:address":"Calle de Augusto Figueroa, 16",
    "sg:city":"Madrid",
    "sg:orig_category":"Confecci\u00d3n De Trajes Para Se\u00d1oras",
    "sg:phone":"+34 915 21 66 03",
    "sg:postcode":"28004",
    "sg:province":"Madrid",
    "wof:name":"Casas Merino Vicenta",
    "wof:placetype":"venue"
},
  "geometry": {"coordinates":[-3.6988623142,40.4225273132],"type":"Point"}
}