{
  "type": "Feature",
  "properties": {
    "iso:country":"ES",
    "sg:address":"Calle de Orense, 18",
    "sg:city":"Madrid",
    "sg:orig_category":"Organismos De Turismo",
    "sg:phone":"+34 915 97 36 97",
    "sg:postcode":"28020",
    "sg:province":"Madrid",
    "wof:name":"Aste Holidays S. A.",
    "wof:placetype":"venue"
},
  "geometry": {"coordinates":[-3.695186615,40.4502372742],"type":"Point"}
}