{
  "type": "Feature",
  "properties": {
    "addr:full":"Carrer de Comtal, 5 Barcelona Barcelona 08002",
    "addr:housenumber":"5",
    "addr:postcode":"08002",
    "addr:street":"Carrer De Comtal",
    "iso:country":"ES",
    "sg:address":"Carrer de Comtal, 5",
    "sg:city":"Barcelona",
    "sg:orig_category":"Bisuteros (fabricaci\u00d3n, Al Por Mayor)",
    "sg:phone":"+34 933 18 22 80",
    "sg:postcode":"08002",
    "sg:province":"Barcelona",
    "wof:name":"Vidal Tost Maria",
    "wof:placetype":"venue"
},
  "geometry": {"coordinates":[2.1726830006,41.3864631653],"type":"Point"}
}