{
  "type": "Feature",
  "properties": {
    "addr:full":"Pase Colon, 2 Irun Guip\u00f9zcoa 20302",
    "addr:housenumber":"2",
    "addr:postcode":"20302",
    "addr:street":"Colon;Guipu\u0300Zcoa",
    "iso:country":"ES",
    "sg:address":"Pase Colon, 2",
    "sg:city":"Irun",
    "sg:orig_category":"Fotocopias, Reprograf\u00cda",
    "sg:phone":"+34 943 63 93 01",
    "sg:postcode":"20302",
    "sg:province":"Guip\u00f9zcoa",
    "wof:name":"Kopiart Inpresioak Et Paper Denda S.l.",
    "wof:placetype":"venue"
},
  "geometry": {"coordinates":[-1.7898960114,43.3395690918],"type":"Point"}
}