{
  "type": "Feature",
  "properties": {
    "addr:full":"Calle de Ca\u00d1os De Los, 12 Mijas M\u00e1laga 29650",
    "addr:housenumber":"12",
    "addr:postcode":"29650",
    "addr:street":"Calle De Can\u0303Os De Los",
    "iso:country":"ES",
    "sg:address":"Calle de Ca\u00d1os De Los, 12",
    "sg:city":"Mijas",
    "sg:orig_category":"Peleter\u00cdas",
    "sg:phone":"+34 952 59 01 75",
    "sg:postcode":"29650",
    "sg:province":"M\u00e1laga",
    "wof:name":"Hiper Bolsos S.l.",
    "wof:placetype":"venue"
},
  "geometry": {"coordinates":[-4.638109684,36.5951652527],"type":"Point"}
}