{
  "type": "Feature",
  "properties": {
    "iso:country":"ES",
    "sg:address":"Avda Valdelasfuentes (de), 16",
    "sg:city":"San Sebastian De Los Reyes",
    "sg:orig_category":"Asesor\u00cda Fiscal Y Jur\u00cddica",
    "sg:phone":"+34 916 54 11 59",
    "sg:postcode":"28700",
    "sg:province":"Madrid",
    "wof:name":"Redondo Martinez Luis",
    "wof:placetype":"venue"
},
  "geometry": {"coordinates":[-3.6325139999,40.551776886],"type":"Point"}
}