{
  "type": "Feature",
  "properties": {
    "iso:country":"ES",
    "sg:address":"Calle de Bocas Las, 1",
    "sg:city":"Huelva",
    "sg:orig_category":"Tintes (fabricaci\u00d3n, Al Por Mayor)",
    "sg:phone":"+34 959 25 75 94",
    "sg:postcode":"21001",
    "sg:province":"Huelva",
    "wof:name":"Tintopal S.l.",
    "wof:placetype":"venue"
},
  "geometry": {"coordinates":[-6.9533457756,37.2563896179],"type":"Point"}
}