{
  "type": "Feature",
  "properties": {
    "iso:country":"ES",
    "sg:address":"Calle de Santa Clara, 28",
    "sg:city":"Burgos",
    "sg:orig_category":"Hoteles",
    "sg:phone":"+34 947 25 60 77",
    "sg:postcode":"09002",
    "sg:province":"Burgos",
    "wof:name":"Pinillos Gonzalez Abel",
    "wof:placetype":"venue"
},
  "geometry": {"coordinates":[-3.6951196194,42.3376121521],"type":"Point"}
}