{
  "type": "Feature",
  "properties": {
    "iso:country":"ES",
    "sg:address":"Rua Flores (das), S/n",
    "sg:city":"Vilela",
    "sg:orig_category":"Delegados, Agentes De Tr\u00c1nsito, Auxiliares De Transporte Internacional",
    "sg:phone":"+34 988 41 19 94",
    "sg:postcode":"32600",
    "sg:province":"Ourense",
    "sg:website":"www.socitransa.com",
    "wof:name":"Sociedad De Transportes S.l",
    "wof:placetype":"venue"
},
  "geometry": {"coordinates":[-7.435254097,41.9402198792],"type":"Point"}
}