{
  "type": "Feature",
  "properties": {
    "iso:country":"ES",
    "sg:address":"Carr Font D'en Rafel, 11",
    "sg:city":"Llanars",
    "sg:orig_category":"Turismo: Lugares, Circuitos Y Curiosidades",
    "sg:phone":"+34 972 74 06 55",
    "sg:postcode":"17869",
    "sg:province":"Girona",
    "sg:website":"www.carrilet.com",
    "wof:name":"Carrilet Verd Vall De Camprodon S.l.",
    "wof:placetype":"venue"
},
  "geometry": {"coordinates":[2.3452429771,42.321685791],"type":"Point"}
}