{
  "type": "Feature",
  "properties": {
    "iso:country":"ES",
    "sg:address":"Rbla Catalunya, 15",
    "sg:city":"Barcelona",
    "sg:orig_category":"Abogados",
    "sg:phone":"+34 934 12 67 81",
    "sg:postcode":"08007",
    "sg:province":"Barcelona",
    "wof:name":"Galbany Vi\u00f1amata Antonio",
    "wof:placetype":"venue"
},
  "geometry": {"coordinates":[2.1673140526,41.3881568909],"type":"Point"}
}