{
  "type": "Feature",
  "properties": {
    "addr:full":"Pl. Fuensanta, 2 Cordoba C\u00f3rdoba 14010",
    "addr:postcode":"14010",
    "addr:street":"Fuensanta;Cordoba Co\u0301Rdoba",
    "iso:country":"ES",
    "sg:address":"Pl. Fuensanta, 2",
    "sg:city":"Cordoba",
    "sg:orig_category":"Asociaciones Humanitarias, De Cooperaci\u00d3n, De Acci\u00d3n Social",
    "sg:phone":"+34 957 43 43 85",
    "sg:postcode":"14010",
    "sg:province":"C\u00f3rdoba",
    "wof:name":"Alcer",
    "wof:placetype":"venue"
},
  "geometry": {"coordinates":[-4.762887001,37.880897522],"type":"Point"}
}