{
  "type": "Feature",
  "properties": {
    "iso:country":"ES",
    "sg:address":"Calle de Almirante Faustino Ruiz, 6",
    "sg:city":"S. Fernando",
    "sg:orig_category":"Asociaciones Y Clubs Deportivos",
    "sg:phone":"+34 956 88 48 85",
    "sg:postcode":"11100",
    "sg:province":"C\u00e1diz",
    "wof:name":"Morales Delgado Rafael",
    "wof:placetype":"venue"
},
  "geometry": {"coordinates":[-6.2009587288,36.4627494812],"type":"Point"}
}