{
  "type": "Feature",
  "properties": {
    "iso:country":"ES",
    "sg:address":"Avda Brasil, 4",
    "sg:city":"Madrid",
    "sg:orig_category":"Importaci\u00d3n",
    "sg:phone":"+34 915 56 13 13",
    "sg:postcode":"28020",
    "sg:province":"Madrid",
    "wof:name":"Euro Consulting De Maquinaria S.l.",
    "wof:placetype":"venue"
},
  "geometry": {"coordinates":[-3.6933660507,40.4537734985],"type":"Point"}
}