{
  "type": "Feature",
  "properties": {
    "addr:full":"Avda Arana Sabino, 30 Bilbao Vizcaya 48013",
    "addr:housenumber":"30",
    "addr:postcode":"48013",
    "addr:street":"Avda Arana Sabino",
    "iso:country":"ES",
    "sg:address":"Avda Arana Sabino, 30",
    "sg:city":"Bilbao",
    "sg:orig_category":"Arquitectos",
    "sg:phone":"+34 944 42 34 79",
    "sg:postcode":"48013",
    "sg:province":"Vizcaya",
    "wof:name":"Aceves Martin Jose Luis",
    "wof:placetype":"venue"
},
  "geometry": {"coordinates":[-2.9470829964,43.2612724304],"type":"Point"}
}