{
  "type": "Feature",
  "properties": {
    "addr:full":"Trencadors, 10 Ferreries Islas Baleares 07750",
    "addr:housenumber":"10",
    "addr:postcode":"07750",
    "addr:street":"Trencadors",
    "iso:country":"ES",
    "sg:address":"Trencadors, 10",
    "sg:city":"Ferreries",
    "sg:orig_category":"Forjas Y Altos Hornos",
    "sg:phone":"+34 971 37 36 16",
    "sg:postcode":"07750",
    "sg:province":"Islas Baleares",
    "wof:name":"Germans Marti Hidalgo S.l.",
    "wof:placetype":"venue"
},
  "geometry": {"coordinates":[4.0205187798,39.98670578],"type":"Point"}
}