{
  "type": "Feature",
  "properties": {
    "iso:country":"ES",
    "sg:address":"Avda Alfonso El Sabio, 47",
    "sg:city":"Alacant",
    "sg:orig_category":"Aud\u00cdfonos",
    "sg:phone":"+34 965 21 30 41",
    "sg:postcode":"03001",
    "sg:province":"Alicante",
    "wof:name":"Gasso Bosch Joan",
    "wof:placetype":"venue"
},
  "geometry": {"coordinates":[-0.489951998,38.3461647034],"type":"Point"}
}