{
  "type": "Feature",
  "properties": {
    "addr:full":"Calle de Reguera (la), 7 Adrada \u00c1vila 05430",
    "addr:housenumber":"7",
    "addr:postcode":"05430",
    "addr:street":"Calle De Reguera La",
    "iso:country":"ES",
    "sg:address":"Calle de Reguera (la), 7",
    "sg:city":"Adrada",
    "sg:orig_category":"Librer\u00cdas",
    "sg:phone":"+34 918 67 05 31",
    "sg:postcode":"05430",
    "sg:province":"\u00c1vila",
    "wof:name":"Pertegas Gabriel Emiliana",
    "wof:placetype":"venue"
},
  "geometry": {"coordinates":[-4.6336088181,40.300868988],"type":"Point"}
}