{
  "type": "Feature",
  "properties": {
    "addr:full":"Calle de Emilio Castelar, 80 Novelda Alicante 03660",
    "addr:housenumber":"80",
    "addr:postcode":"03660",
    "addr:street":"Calle De Emilio Castelar",
    "iso:country":"ES",
    "sg:address":"Calle de Emilio Castelar, 80",
    "sg:city":"Novelda",
    "sg:orig_category":"Estancos",
    "sg:phone":"+34 965 60 45 35",
    "sg:postcode":"03660",
    "sg:province":"Alicante",
    "wof:name":"Segura Verdu Magdalena",
    "wof:placetype":"venue"
},
  "geometry": {"coordinates":[-0.7680490017,38.3846817017],"type":"Point"}
}