{
  "type": "Feature",
  "properties": {
    "addr:full":"Carr Major, Carrer, 22 Casco Urbano Valencia 46760",
    "addr:housenumber":"22",
    "addr:postcode":"46760",
    "addr:street":"Carr;Carrer",
    "iso:country":"ES",
    "sg:address":"Carr Major, Carrer, 22",
    "sg:city":"Casco Urbano",
    "sg:orig_category":"Zapatos (al Por Menor)",
    "sg:phone":"+34 962 83 67 95",
    "sg:postcode":"46760",
    "sg:province":"Valencia",
    "wof:name":"Andres Aparici Noelia",
    "wof:placetype":"venue"
},
  "geometry": {"coordinates":[-0.3768048882,39.4702377319],"type":"Point"}
}