{
  "type": "Feature",
  "properties": {
    "addr:full":"Calle de Camino De Magacela, 4 Villanueva Serena Badajoz 06700",
    "addr:housenumber":"4",
    "addr:postcode":"06700",
    "addr:street":"Calle De Camino De Magacela",
    "iso:country":"ES",
    "sg:address":"Calle de Camino De Magacela, 4",
    "sg:city":"Villanueva Serena",
    "sg:orig_category":"Arreglo, Reparaci\u00d3n, Piezas Sueltas De Televisi\u00d3n, V\u00cddeo, Hi",
    "sg:phone":"+34 924 84 59 92",
    "sg:postcode":"06700",
    "sg:province":"Badajoz",
    "wof:name":"Centro De Electronica Villanovense C.b",
    "wof:placetype":"venue"
},
  "geometry": {"coordinates":[-5.6911454201,38.9140739441],"type":"Point"}
}