{
  "type": "Feature",
  "properties": {
    "addr:full":"Calle de Diego De Vergara, 65 Malaga M\u00e1laga 29009",
    "addr:housenumber":"65",
    "addr:postcode":"29009",
    "addr:street":"Calle De Diego De Vergara;Ma\u0301Laga",
    "iso:country":"ES",
    "sg:address":"Calle de Diego De Vergara, 65",
    "sg:city":"Malaga",
    "sg:orig_category":"M\u00c9dicos: Estomatolog\u00cda",
    "sg:phone":"+34 952 30 64 42",
    "sg:postcode":"29009",
    "sg:province":"M\u00e1laga",
    "wof:name":"Gamboa Fernandez Maria Dolores",
    "wof:placetype":"venue"
},
  "geometry": {"coordinates":[-4.4341249466,36.7245674133],"type":"Point"}
}