{
  "type": "Feature",
  "properties": {
    "iso:country":"ES",
    "sg:address":"Calle de General Lacy, 12",
    "sg:city":"Alacant",
    "sg:orig_category":"Restaurantes",
    "sg:phone":"+34 965 12 43 62",
    "sg:postcode":"03003",
    "sg:province":"Alicante",
    "wof:name":"Anca Navas Cesar",
    "wof:placetype":"venue"
},
  "geometry": {"coordinates":[-0.4921641946,38.3446006775],"type":"Point"}
}