{
  "type": "Feature",
  "properties": {
    "addr:full":"Calle de Camarena, 103 Madrid Madrid 28047",
    "addr:housenumber":"103",
    "addr:postcode":"28047",
    "addr:street":"Calle De Camarena",
    "iso:country":"ES",
    "sg:address":"Calle de Camarena, 103",
    "sg:city":"Madrid",
    "sg:orig_category":"Limpieza Industrial",
    "sg:phone":"+34 917 17 11 47",
    "sg:postcode":"28047",
    "sg:province":"Madrid",
    "wof:name":"Diaz Miralles Luis",
    "wof:placetype":"venue"
},
  "geometry": {"coordinates":[-3.7557010651,40.3925285339],"type":"Point"}
}