{
  "type": "Feature",
  "properties": {
    "iso:country":"ES",
    "sg:address":"Carr Mestre Lluis Millet, 5",
    "sg:city":"Badalona",
    "sg:orig_category":"Cl\u00cdnicas M\u00c9dicas",
    "sg:phone":"+34 933 89 35 42",
    "sg:postcode":"08911",
    "sg:province":"Barcelona",
    "wof:name":"Fabra Llopis Jose Maria",
    "wof:placetype":"venue"
},
  "geometry": {"coordinates":[2.247328043,41.4551582336],"type":"Point"}
}