{
  "type": "Feature",
  "properties": {
    "addr:full":"Avda Faro (el), S/n Castillo Bajo-conejito M\u00e1laga 29793",
    "addr:postcode":"29793",
    "addr:street":"Avda Faro El S / N Castillo Bajo-Conejito Ma\u0301Laga",
    "iso:country":"ES",
    "sg:address":"Avda Faro (el), S/n",
    "sg:city":"Castillo Bajo-conejito",
    "sg:orig_category":"Servicio De Salud",
    "sg:phone":"+34 952 53 10 59",
    "sg:postcode":"29793",
    "sg:province":"M\u00e1laga",
    "wof:name":"Saneamientos Visan S.l.",
    "wof:placetype":"venue"
},
  "geometry": {"coordinates":[-3.9633140564,36.7310066223],"type":"Point"}
}