{
  "type": "Feature",
  "properties": {
    "iso:country":"ES",
    "sg:address":"Calle de Conde De Pe\u00d1alver, 20",
    "sg:city":"Madrid",
    "sg:orig_category":"Zapatos (al Por Menor)",
    "sg:phone":"+34 914 35 07 80",
    "sg:postcode":"28006",
    "sg:province":"Madrid",
    "sg:website":"www.jotaefe.com",
    "wof:name":"Hermanos Dorado Bc",
    "wof:placetype":"venue"
},
  "geometry": {"coordinates":[-3.6755187511,40.4271888733],"type":"Point"}
}