{
  "type": "Feature",
  "properties": {
    "iso:country":"ES",
    "sg:address":"De La Radio, 3",
    "sg:city":"Talayuela",
    "sg:classifiers":[
        {
            "category":"Communications",
            "type":"Services"
        }
    ],
    "sg:phone":"+34 927 57 82 02",
    "sg:postcode":"10310",
    "sg:province":"C\u00e1ceres",
    "sg:tags":[
        "televisiones",
        "y",
        "radio"
    ],
    "wof:name":"Rincon Toledano Vicente Jesus",
    "wof:placetype":"venue"
},
  "geometry": {"coordinates":[-5.610019207,39.9897003174],"type":"Point"}
}