{
  "type": "Feature",
  "properties": {
    "addr:full":"Carrer de Adriatic, 4 Reus Tarragona 43205",
    "addr:housenumber":"4",
    "addr:postcode":"43205",
    "addr:street":"Carrer De Adriatic",
    "iso:country":"ES",
    "sg:address":"Carrer de Adriatic, 4",
    "sg:city":"Reus",
    "sg:orig_category":"Empresas De Carpinter\u00cda",
    "sg:phone":"+34 977 77 30 72",
    "sg:postcode":"43205",
    "sg:province":"Tarragona",
    "wof:name":"Cerrajeria Ricardo Torrente S.l.",
    "wof:placetype":"venue"
},
  "geometry": {"coordinates":[1.1124429703,41.1386756897],"type":"Point"}
}