{
  "type": "Feature",
  "properties": {
    "iso:country":"ES",
    "sg:address":"Calle de Gabiria, 128",
    "sg:city":"Irun",
    "sg:orig_category":"Diarios, Prensa, Revistas (al Por Menor)",
    "sg:phone":"+34 943 62 29 92",
    "sg:postcode":"20305",
    "sg:province":"Guip\u00f9zcoa",
    "wof:name":"Plastificados Alman S.l.",
    "wof:placetype":"venue"
},
  "geometry": {"coordinates":[-1.8281830549,43.3266601562],"type":"Point"}
}