{
  "type": "Feature",
  "properties": {
    "iso:country":"ES",
    "sg:address":"Calle de San Pedro Alcantara, 25",
    "sg:city":"Badajoz",
    "sg:orig_category":"Ense\u00d1anza: Idiomas",
    "sg:phone":"+34 924 25 31 07",
    "sg:postcode":"06001",
    "sg:province":"Badajoz",
    "sg:website":"www.ef.com",
    "wof:name":"E. F. Education S. A.",
    "wof:placetype":"venue"
},
  "geometry": {"coordinates":[-6.9695811272,38.8814430237],"type":"Point"}
}