{
  "type": "Feature",
  "properties": {
    "iso:country":"ES",
    "sg:address":"C/ Ramal, Des, 19",
    "sg:city":"Alaior",
    "sg:orig_category":"Zapatos (al Por Menor)",
    "sg:phone":"+34 971 37 28 34",
    "sg:postcode":"07730",
    "sg:province":"Islas Baleares",
    "wof:name":"Pons Moll Juana",
    "wof:placetype":"venue"
},
  "geometry": {"coordinates":[4.1376581192,39.9336166382],"type":"Point"}
}