{
  "type": "Feature",
  "properties": {
    "iso:country":"ES",
    "sg:address":"Calle de Jose Lazaro Galdiano, 2",
    "sg:city":"Madrid",
    "sg:orig_category":"Cristaler\u00cda: Suministros",
    "sg:phone":"+34 914 57 05 23",
    "sg:postcode":"28036",
    "sg:province":"Madrid",
    "wof:name":"Comercial Princo S.a.",
    "wof:placetype":"venue"
},
  "geometry": {"coordinates":[-3.6875560284,40.4573707581],"type":"Point"}
}