{
  "type": "Feature",
  "properties": {
    "addr:full":"Rua Doutor Iglesia Parga, 11 Ferrol La Coru\u00f1a 15403",
    "addr:housenumber":"11",
    "addr:postcode":"15403",
    "addr:street":"Rua Doutor Iglesia Parga;La Corun\u0303A",
    "iso:country":"ES",
    "sg:address":"Rua Doutor Iglesia Parga, 11",
    "sg:city":"Ferrol",
    "sg:orig_category":"Agentes Generales De Seguros",
    "sg:phone":"+34 981 33 01 00",
    "sg:postcode":"15403",
    "sg:province":"La Coru\u00f1a",
    "wof:name":"Mapareri S.l.",
    "wof:placetype":"venue"
},
  "geometry": {"coordinates":[-8.2273387909,43.4868507385],"type":"Point"}
}