{
  "type": "Feature",
  "properties": {
    "addr:full":"Las Lomas, Km. 0000,3 Valdelafuente Le\u00f3n 24227",
    "addr:postcode":"24227",
    "addr:street":"Las Lomas Km. 0000,3 Valdelafuente Leo\u0301N",
    "iso:country":"ES",
    "sg:address":"Las Lomas, Km. 0000,3",
    "sg:city":"Valdelafuente",
    "sg:orig_category":"Empresas De Carpinter\u00cda Met\u00c1lica",
    "sg:phone":"+34 987 21 49 20",
    "sg:postcode":"24227",
    "sg:province":"Le\u00f3n",
    "wof:name":"Aluminios Gon-per S. L.",
    "wof:placetype":"venue"
},
  "geometry": {"coordinates":[-5.5140676498,42.5694046021],"type":"Point"}
}