{
  "type": "Feature",
  "properties": {
    "addr:full":"Plaz Mariana Pineda, 4 Madrid Madrid 28038",
    "addr:housenumber":"4",
    "addr:postcode":"28038",
    "addr:street":"Pineda",
    "iso:country":"ES",
    "sg:address":"Plaz Mariana Pineda, 4",
    "sg:city":"Madrid",
    "sg:orig_category":"Ense\u00d1anza: Idiomas",
    "sg:phone":"+34 914 77 92 60",
    "sg:postcode":"28038",
    "sg:province":"Madrid",
    "wof:name":"Pacheco Fernandez Edwiges Elizabeth",
    "wof:placetype":"venue"
},
  "geometry": {"coordinates":[-3.6561911106,40.392868042],"type":"Point"}
}