{
  "type": "Feature",
  "properties": {
    "iso:country":"ES",
    "sg:address":"Ctra Via Interpolar, Km. 0004,0",
    "sg:city":"Granollers",
    "sg:orig_category":"Ferreter\u00cda (diversos)",
    "sg:phone":"+34 938 60 47 60",
    "sg:postcode":"08403",
    "sg:province":"Barcelona",
    "sg:website":"www.ferimet.com",
    "wof:name":"Ferimet S.l.",
    "wof:placetype":"venue"
},
  "geometry": {"coordinates":[2.279804945,41.6144218445],"type":"Point"}
}