{
  "type": "Feature",
  "properties": {
    "addr:full":"Pase Libertad (la), 15 Albacete Albacete 02001",
    "addr:housenumber":"15",
    "addr:postcode":"02001",
    "addr:street":"Libertad La",
    "iso:country":"ES",
    "sg:address":"Pase Libertad (la), 15",
    "sg:city":"Albacete",
    "sg:orig_category":"Juristas",
    "sg:phone":"+34 967 21 09 09",
    "sg:postcode":"02001",
    "sg:province":"Albacete",
    "wof:name":"Servicios De Inspeccion Y Certificacion S.l.u.",
    "wof:placetype":"venue"
},
  "geometry": {"coordinates":[-1.8527619839,38.9964447021],"type":"Point"}
}