{
  "type": "Feature",
  "properties": {
    "iso:country":"ES",
    "sg:address":"Calle de Barrero De Capuchinos, 9",
    "sg:city":"Velez-malaga",
    "sg:orig_category":"Mec\u00c1nico Del Autom\u00d3vil",
    "sg:phone":"+34 952 50 39 59",
    "sg:postcode":"29700",
    "sg:province":"M\u00e1laga",
    "wof:name":"Bellido Morales Antonio",
    "wof:placetype":"venue"
},
  "geometry": {"coordinates":[-4.0996551514,36.7775993347],"type":"Point"}
}