{
  "type": "Feature",
  "properties": {
    "iso:country":"ES",
    "sg:address":"Avda Ronda, 23",
    "sg:city":"Aguilar Campoo",
    "sg:orig_category":"Cajas De Ahorro",
    "sg:phone":"+34 979 12 29 61",
    "sg:postcode":"34800",
    "sg:province":"Palencia",
    "wof:name":"Caixa D'estalvis I Pensions De Barcelona",
    "wof:placetype":"venue"
},
  "geometry": {"coordinates":[-4.2649922371,42.7937965393],"type":"Point"}
}