{
  "type": "Feature",
  "properties": {
    "iso:country":"ES",
    "sg:address":"Pl Constitucio (la), 23",
    "sg:city":"Vilafranca Penedes",
    "sg:orig_category":"Art\u00cdculos De Regalo (al Por Menor)",
    "sg:phone":"+34 938 92 08 42",
    "sg:postcode":"08720",
    "sg:province":"Barcelona",
    "wof:name":"Barrachina Manero Ana Maria",
    "wof:placetype":"venue"
},
  "geometry": {"coordinates":[1.6992199421,41.3447799683],"type":"Point"}
}