{
  "type": "Feature",
  "properties": {
    "addr:full":"Calle de Ugarte, 10 \u00c1lava 01400",
    "addr:housenumber":"10",
    "addr:postcode":"01400",
    "addr:street":"Calle De Ugarte;A\u0301Lava",
    "iso:country":"ES",
    "sg:address":"Calle de Ugarte, 10",
    "sg:orig_category":"Alimentaci\u00d3n General (al Por Menor)",
    "sg:phone":"+34 946 72 05 63",
    "sg:postcode":"01400",
    "sg:province":"\u00c1lava",
    "wof:name":"Juan Ignacio Sallen Del Rio (alimentacion Sallen)",
    "wof:placetype":"venue"
},
  "geometry": {"coordinates":[-2.9647090435,43.1417808533],"type":"Point"}
}