{
  "type": "Feature",
  "properties": {
    "iso:country":"ES",
    "sg:address":"Calle de Greco, 2",
    "sg:city":"Talavera Reina",
    "sg:orig_category":"M\u00c9dicos: Estomatolog\u00cda",
    "sg:phone":"+34 925 81 39 14",
    "sg:postcode":"45600",
    "sg:province":"Toledo",
    "wof:name":"Asurmendi Zulueta Jose Felix",
    "wof:placetype":"venue"
},
  "geometry": {"coordinates":[-4.6279478073,39.9660606384],"type":"Point"}
}