{
  "type": "Feature",
  "properties": {
    "addr:full":"Carrer de Josep Bertrand, 9 Barcelona Barcelona 08021",
    "addr:housenumber":"9",
    "addr:postcode":"08021",
    "addr:street":"Carrer De Josep Bertrand",
    "iso:country":"ES",
    "sg:address":"Carrer de Josep Bertrand, 9",
    "sg:city":"Barcelona",
    "sg:orig_category":"M\u00c9dicos: Pediatr\u00cda. Enfermedades De Los Ni\u00d1os",
    "sg:phone":"+34 932 01 28 90",
    "sg:postcode":"08021",
    "sg:province":"Barcelona",
    "wof:name":"Trias Vidal De Llovatera Javier",
    "wof:placetype":"venue"
},
  "geometry": {"coordinates":[2.1396069527,41.3950691223],"type":"Point"}
}