{
  "type": "Feature",
  "properties": {
    "iso:country":"ES",
    "sg:address":"Trva Jose Alix Alix (de), 3",
    "sg:city":"San Fernando De Henares",
    "sg:orig_category":"Comercio De Piezas De Recambio Y De Accesorios De Veh\u00cdculos, Veh\u00cdculos Industriales",
    "sg:phone":"+34 916 69 64 39",
    "sg:postcode":"28830",
    "sg:province":"Madrid",
    "wof:name":"Lucauto S.l.",
    "wof:placetype":"venue"
},
  "geometry": {"coordinates":[-3.5332329273,40.4267501831],"type":"Point"}
}