{
  "type": "Feature",
  "properties": {
    "iso:country":"ES",
    "sg:address":"Calle de Conde Rodriguez San Pedro, 39",
    "sg:city":"Madrid",
    "sg:orig_category":"Carnicer\u00cdas, Carnicer\u00cdas",
    "sg:phone":"+34 914 78 49 64",
    "sg:postcode":"28053",
    "sg:province":"Madrid",
    "wof:name":"Garcia Villanueva Paulino",
    "wof:placetype":"venue"
},
  "geometry": {"coordinates":[-3.6720757484,40.3845596313],"type":"Point"}
}