{
  "type": "Feature",
  "properties": {
    "iso:country":"ES",
    "sg:address":"Carr Narcis Monturiol, 30",
    "sg:city":"Vidreres",
    "sg:classifiers":[
        {
            "category":"Autos & Motor Vehicles",
            "subcategory":"Automobile Sales",
            "type":"Retail Goods"
        }
    ],
    "sg:phone":"+34 972 85 05 46",
    "sg:postcode":"17411",
    "sg:province":"Girona",
    "wof:name":"Jaume Fugueras Llobet S.l.",
    "wof:placetype":"venue"
},
  "geometry": {"coordinates":[2.783039093,41.7910766602],"type":"Point"}
}