{
  "type": "Feature",
  "properties": {
    "addr:full":"Carr Bajoli, 47 Poima Islas Baleares 07714",
    "addr:housenumber":"47",
    "addr:postcode":"07714",
    "addr:street":"Carr Bajoli",
    "iso:country":"ES",
    "sg:address":"Carr Bajoli, 47",
    "sg:city":"Poima",
    "sg:orig_category":"Mudanzas",
    "sg:phone":"+34 971 36 45 79",
    "sg:postcode":"07714",
    "sg:province":"Islas Baleares",
    "wof:name":"Erchiga Logistica S.l.",
    "wof:placetype":"venue"
},
  "geometry": {"coordinates":[2.9117100239,39.6136398315],"type":"Point"}
}