{
  "type": "Feature",
  "properties": {
    "iso:country":"ES",
    "sg:address":"Calle de San Gregorio (de), 6",
    "sg:city":"Galapagar",
    "sg:orig_category":"Asilos De Ancianos. Centros Privados",
    "sg:phone":"+34 918 58 75 46",
    "sg:postcode":"28260",
    "sg:province":"Madrid",
    "wof:name":"Mial S.l.",
    "wof:placetype":"venue"
},
  "geometry": {"coordinates":[-4.0031781197,40.5783195496],"type":"Point"}
}