{
  "type": "Feature",
  "properties": {
    "addr:full":"Calle de Mayor, 10 Torrelaguna Madrid 28180",
    "addr:housenumber":"10",
    "addr:postcode":"28180",
    "addr:street":"Calle De Mayor",
    "iso:country":"ES",
    "sg:address":"Calle de Mayor, 10",
    "sg:city":"Torrelaguna",
    "sg:classifiers":[
        {
            "category":"Taxi",
            "type":"Transportation"
        }
    ],
    "sg:phone":"+34 918 43 03 38",
    "sg:postcode":"28180",
    "sg:province":"Madrid",
    "wof:name":"Oca\u00f1a Arias Emilio",
    "wof:placetype":"venue"
},
  "geometry": {"coordinates":[-3.5379559994,40.8260421753],"type":"Point"}
}