{
  "type": "Feature",
  "properties": {
    "addr:full":"Calle de San Jacinto Casta\u00d1eda, 6 Valencia Valencia 46006",
    "addr:housenumber":"6",
    "addr:postcode":"46006",
    "addr:street":"Calle De San;Castan\u0303Eda",
    "iso:country":"ES",
    "sg:address":"Calle de San Jacinto Casta\u00d1eda, 6",
    "sg:city":"Valencia",
    "sg:orig_category":"Fabrica De Charcuter\u00cda",
    "sg:phone":"+34 963 73 37 57",
    "sg:postcode":"46006",
    "sg:province":"Valencia",
    "wof:name":"Especialidades Artesanas El Mallorquin S.l.",
    "wof:placetype":"venue"
},
  "geometry": {"coordinates":[-0.3627539873,39.4598846436],"type":"Point"}
}