{
  "type": "Feature",
  "properties": {
    "iso:country":"ES",
    "sg:address":"Calle de Ochagavia, 18",
    "sg:city":"Madrid",
    "sg:orig_category":"\u00d3ptica: Instrumentos (fabricaci\u00d3n)",
    "sg:phone":"+34 914 59 37 51",
    "sg:postcode":"28039",
    "sg:province":"Madrid",
    "wof:name":"Reche Andres Maria",
    "wof:placetype":"venue"
},
  "geometry": {"coordinates":[-3.7172932625,40.4634475708],"type":"Point"}
}