{
  "type": "Feature",
  "properties": {
    "iso:country":"ES",
    "sg:address":"Avda Argentina, 60",
    "sg:city":"Maracena",
    "sg:orig_category":"Institutos De Belleza",
    "sg:phone":"+34 958 40 41 24",
    "sg:postcode":"18200",
    "sg:province":"Granada",
    "wof:name":"Fernandez Lopez Esperanza",
    "wof:placetype":"venue"
},
  "geometry": {"coordinates":[-3.6359689236,37.2108612061],"type":"Point"}
}