{
  "type": "Feature",
  "properties": {
    "addr:full":"Calle de Corredera, 272 Viso Del Alcor Sevilla 41520",
    "addr:housenumber":"272",
    "addr:postcode":"41520",
    "addr:street":"Calle De Corredera",
    "iso:country":"ES",
    "sg:address":"Calle de Corredera, 272",
    "sg:city":"Viso Del Alcor",
    "sg:orig_category":"Supermercados Y Hipermercados",
    "sg:phone":"+34 955 94 50 98",
    "sg:postcode":"41520",
    "sg:province":"Sevilla",
    "wof:name":"Borreguero Cadenas Antonio",
    "wof:placetype":"venue"
},
  "geometry": {"coordinates":[-5.7179613113,37.3920326233],"type":"Point"}
}