{
  "type": "Feature",
  "properties": {
    "iso:country":"ES",
    "sg:address":"Ezkaba, 1",
    "sg:city":"Iru\u00f1a",
    "sg:orig_category":"Inform\u00c1tica: Mantenimiento Y Reparaci\u00d3n De Ordenadores",
    "sg:phone":"+34 948 31 51 97",
    "sg:postcode":"31015",
    "sg:province":"Navarra",
    "wof:name":"Suministros Import.y Mantenimiento",
    "wof:placetype":"venue"
},
  "geometry": {"coordinates":[-1.6282609701,42.8265647888],"type":"Point"}
}