{
  "type": "Feature",
  "properties": {
    "iso:country":"ES",
    "sg:address":"Calle de Larga, 22",
    "sg:city":"Jerez De La Frontera",
    "sg:orig_category":"Lencer\u00cda Femenina, Corseter\u00cda, Trajes De Ba\u00d1o (al Por Menor)",
    "sg:phone":"+34 956 33 33 88",
    "sg:postcode":"11402",
    "sg:province":"C\u00e1diz",
    "sg:website":"www.oyshoespa\u00f1a.com",
    "wof:name":"Oysho Espa\u00d1a S.a.",
    "wof:placetype":"venue"
},
  "geometry": {"coordinates":[-6.1362338066,36.6852302551],"type":"Point"}
}