{
  "type": "Feature",
  "properties": {
    "addr:full":"Avda General Capalleja, 30 Navelgas Asturias 33873",
    "addr:housenumber":"30",
    "addr:postcode":"33873",
    "addr:street":"Avda General Capalleja;Asturias",
    "iso:country":"ES",
    "sg:address":"Avda General Capalleja, 30",
    "sg:city":"Navelgas",
    "sg:orig_category":"Contenedores (mercanc\u00cdas)",
    "sg:phone":"+34 985 80 60 24",
    "sg:postcode":"33873",
    "sg:province":"Asturias",
    "sg:website":"www.garrido.net",
    "wof:name":"Automoviles Garrido S.l",
    "wof:placetype":"venue"
},
  "geometry": {"coordinates":[-6.5406727791,43.4034004211],"type":"Point"}
}