{
  "type": "Feature",
  "properties": {
    "iso:country":"ES",
    "sg:address":"Calle de Madre Puy, 2",
    "sg:city":"Calatayud",
    "sg:orig_category":"Inmobiliaria (agencias)",
    "sg:phone":"+34 976 88 44 67",
    "sg:postcode":"50300",
    "sg:province":"Zaragoza",
    "wof:name":"Fincas Moscatel S.l",
    "wof:placetype":"venue"
},
  "geometry": {"coordinates":[-1.6383589506,41.3503494263],"type":"Point"}
}