{
  "type": "Feature",
  "properties": {
    "addr:full":"Rbla Rambla Vella, 63 Tarragona Tarragona 43003",
    "addr:housenumber":"63",
    "addr:postcode":"43003",
    "addr:street":"Rambla Vella",
    "iso:country":"ES",
    "sg:address":"Rbla Rambla Vella, 63",
    "sg:city":"Tarragona",
    "sg:orig_category":"Inmobiliaria (agencias)",
    "sg:phone":"+34 977 25 25 26",
    "sg:postcode":"43003",
    "sg:province":"Tarragona",
    "sg:website":"www.sinqueslaclua.com",
    "wof:name":"La Clau Costa Dorada S.l.",
    "wof:placetype":"venue"
},
  "geometry": {"coordinates":[1.2541049719,41.1169281006],"type":"Point"}
}