{
  "type": "Feature",
  "properties": {
    "iso:country":"ES",
    "sg:address":"Carrer de Lluis Guardiola (de), 10",
    "sg:city":"Vilassar De Mar",
    "sg:orig_category":"Fabricaci\u00d3n De Etiquetas",
    "sg:phone":"+34 937 59 15 76",
    "sg:postcode":"08340",
    "sg:province":"Barcelona",
    "wof:name":"Etiquetas Anver S.l.",
    "wof:placetype":"venue"
},
  "geometry": {"coordinates":[2.38727808,41.5078353882],"type":"Point"}
}