{
  "type": "Feature",
  "properties": {
    "addr:full":"Carr Santa Anna, 35 Benifaio Valencia 46450",
    "addr:housenumber":"35",
    "addr:postcode":"46450",
    "addr:street":"Carr Santa Anna",
    "iso:country":"ES",
    "sg:address":"Carr Santa Anna, 35",
    "sg:city":"Benifaio",
    "sg:orig_category":"Serigraf\u00cda (material Y Suministros)",
    "sg:phone":"+34 961 78 15 16",
    "sg:postcode":"46450",
    "sg:province":"Valencia",
    "wof:name":"Caballero Boluda Bernardo",
    "wof:placetype":"venue"
},
  "geometry": {"coordinates":[-0.4229789972,39.2867202759],"type":"Point"}
}