{
  "type": "Feature",
  "properties": {
    "iso:country":"ES",
    "sg:address":"Calle de Cruz Roja De Leon, 8",
    "sg:city":"Le\u00f3n",
    "sg:orig_category":"Papeler\u00cdas, Librer\u00cdas",
    "sg:phone":"+34 987 22 91 36",
    "sg:postcode":"24008",
    "sg:province":"Le\u00f3n",
    "wof:name":"Fernando Alonso Fernandez Y Pedro Angel Alonso Fernandez Cdad",
    "wof:placetype":"venue"
},
  "geometry": {"coordinates":[-5.5791015625,42.6047477722],"type":"Point"}
}