{
  "type": "Feature",
  "properties": {
    "addr:full":"Calle de Torres Quevedo, 4 Mostoles Madrid 28936",
    "addr:housenumber":"4",
    "addr:postcode":"28936",
    "addr:street":"Calle De Torres Quevedo",
    "iso:country":"ES",
    "sg:address":"Calle de Torres Quevedo, 4",
    "sg:city":"Mostoles",
    "sg:orig_category":"Supermercados Y Hipermercados",
    "sg:phone":"+34 916 45 36 65",
    "sg:postcode":"28936",
    "sg:province":"Madrid",
    "wof:name":"Hiper Usera S.a.",
    "wof:placetype":"venue"
},
  "geometry": {"coordinates":[-3.8472440243,40.3173027039],"type":"Point"}
}