{
  "type": "Feature",
  "properties": {
    "iso:country":"ES",
    "sg:address":"Calle de Valverde, 9",
    "sg:city":"Cadiz",
    "sg:orig_category":"Ropa Para Se\u00d1oras Y Caballeros (al Por Menor)",
    "sg:phone":"+34 956 22 80 30",
    "sg:postcode":"11004",
    "sg:province":"C\u00e1diz",
    "wof:name":"World Cotton Del Sur S.l.",
    "wof:placetype":"venue"
},
  "geometry": {"coordinates":[-6.2962880135,36.5331115723],"type":"Point"}
}