{
  "type": "Feature",
  "properties": {
    "addr:full":"Calle de Andres Pastor, 23 Alcazar S. Juan Ciudad Real 13600",
    "addr:housenumber":"23",
    "addr:postcode":"13600",
    "addr:street":"Calle De Andres Pastor;Alcazar S. Juan Ciudad Real",
    "iso:country":"ES",
    "sg:address":"Calle de Andres Pastor, 23",
    "sg:city":"Alcazar S. Juan",
    "sg:orig_category":"Mercer\u00cda, Lencer\u00cda (al Por Menor)",
    "sg:phone":"+34 926 55 22 13",
    "sg:postcode":"13600",
    "sg:province":"Ciudad Real",
    "wof:name":"Sanchez-mateos Campo Felisa",
    "wof:placetype":"venue"
},
  "geometry": {"coordinates":[-3.2138478756,39.3973579407],"type":"Point"}
}