{
  "type": "Feature",
  "properties": {
    "iso:country":"ES",
    "sg:address":"Carrer de Cartagena, 14",
    "sg:city":"Guardamar Segura",
    "sg:orig_category":"Promotores Constructores",
    "sg:phone":"+34 965 72 43 82",
    "sg:postcode":"03140",
    "sg:province":"Alicante",
    "wof:name":"Jose Antonio Martinez Aragones S.l.",
    "wof:placetype":"venue"
},
  "geometry": {"coordinates":[-0.6513929963,38.0854454041],"type":"Point"}
}