{
  "type": "Feature",
  "properties": {
    "addr:full":"Calle de Santiago, 36 Llerena Badajoz 06900",
    "addr:housenumber":"36",
    "addr:postcode":"06900",
    "addr:street":"Calle De Santiago",
    "iso:country":"ES",
    "sg:address":"Calle de Santiago, 36",
    "sg:city":"Llerena",
    "sg:orig_category":"Electricidad, Electr\u00d3nica: Suministros (al Por Menor)",
    "sg:phone":"+34 924 87 04 30",
    "sg:postcode":"06900",
    "sg:province":"Badajoz",
    "wof:name":"Alcalde Polo Andres",
    "wof:placetype":"venue"
},
  "geometry": {"coordinates":[-6.0149874687,38.2362060547],"type":"Point"}
}