{
  "type": "Feature",
  "properties": {
    "iso:country":"ES",
    "sg:address":"Plaz Virgen De La Vega, 1",
    "sg:city":"Benavente",
    "sg:orig_category":"Frutas, Legumbres Frescas Y Tempranas (al Por Menor)",
    "sg:phone":"+34 980 63 48 73",
    "sg:postcode":"49600",
    "sg:province":"Zamora",
    "wof:name":"Fernandez Gelado Juan Francisco",
    "wof:placetype":"venue"
},
  "geometry": {"coordinates":[-5.6768388748,42.0053787231],"type":"Point"}
}