{
  "type": "Feature",
  "properties": {
    "iso:country":"ES",
    "sg:address":"Carrer de Sant Jaume, 1",
    "sg:city":"Manlleu",
    "sg:orig_category":"Molduras, Junquillos, Listones Y Molduras Perforadas",
    "sg:phone":"+34 938 51 37 51",
    "sg:postcode":"08560",
    "sg:province":"Barcelona",
    "wof:name":"Vilarrasa Catala Joaquin",
    "wof:placetype":"venue"
},
  "geometry": {"coordinates":[2.2828381062,41.9995727539],"type":"Point"}
}