{
  "type": "Feature",
  "properties": {
    "iso:country":"ES",
    "sg:address":"Calle de Jacinta Garcia Hernandez, 15",
    "sg:city":"Badajoz",
    "sg:orig_category":"Alimentaci\u00d3n General (al Por Mayor)",
    "sg:phone":"+34 924 24 57 16",
    "sg:postcode":"06011",
    "sg:province":"Badajoz",
    "wof:name":"Cepa S.a.",
    "wof:placetype":"venue"
},
  "geometry": {"coordinates":[-6.9874258041,38.8717384338],"type":"Point"}
}