{
  "type": "Feature",
  "properties": {
    "iso:country":"ES",
    "sg:address":"Calle de Virgen De Los Desamparados, 2",
    "sg:city":"Madrid",
    "sg:orig_category":"Caf\u00c9s, Bares, Cervecer\u00cdas",
    "sg:phone":"+34 917 95 69 75",
    "sg:postcode":"28041",
    "sg:province":"Madrid",
    "wof:name":"Perez Grence Francisco",
    "wof:placetype":"venue"
},
  "geometry": {"coordinates":[-3.6988611221,40.3520622253],"type":"Point"}
}