{
  "type": "Feature",
  "properties": {
    "addr:full":"Carrer de Moli, 64 Hospitalet Llobregat Barcelona 08906",
    "addr:housenumber":"64",
    "addr:postcode":"08906",
    "addr:street":"Carrer De Moli",
    "iso:country":"ES",
    "sg:address":"Carrer de Moli, 64",
    "sg:city":"Hospitalet Llobregat",
    "sg:orig_category":"M\u00c9dicos: Estomatolog\u00cda",
    "sg:phone":"+34 934 37 83 11",
    "sg:postcode":"08906",
    "sg:province":"Barcelona",
    "wof:name":"Rodriguez De La Rubia Lopez Maria Del Rocio",
    "wof:placetype":"venue"
},
  "geometry": {"coordinates":[2.099684,41.3712844849],"type":"Point"}
}