{
  "type": "Feature",
  "properties": {
    "iso:country":"ES",
    "sg:address":"Pl Manuel Corachan, 4",
    "sg:city":"Barcelona",
    "sg:orig_category":"M\u00c9dicos: Ginecolog\u00cda Y Obstetricia",
    "sg:phone":"+34 932 80 00 44",
    "sg:postcode":"08017",
    "sg:province":"Barcelona",
    "wof:name":"Centre Ginecologic Dra.granollers Bohils S.l.",
    "wof:placetype":"venue"
},
  "geometry": {"coordinates":[2.1297869682,41.3940925598],"type":"Point"}
}