{
  "type": "Feature",
  "properties": {
    "addr:full":"Calle de Calvo Asensio, 5 Ronda M\u00e1laga 29400",
    "addr:housenumber":"5",
    "addr:postcode":"29400",
    "addr:street":"Calle De Calvo Asensio;Ronda Ma\u0301Laga",
    "iso:country":"ES",
    "sg:address":"Calle de Calvo Asensio, 5",
    "sg:city":"Ronda",
    "sg:orig_category":"Abogados",
    "sg:phone":"+34 952 87 12 02",
    "sg:postcode":"29400",
    "sg:province":"M\u00e1laga",
    "wof:name":"Morales Aguayo Jose Antonio",
    "wof:placetype":"venue"
},
  "geometry": {"coordinates":[-5.1637096405,36.7431945801],"type":"Point"}
}