{
  "type": "Feature",
  "properties": {
    "addr:full":"Avda Montgo, 17 Denia Alicante 03700",
    "addr:housenumber":"17",
    "addr:postcode":"03700",
    "addr:street":"Avda Montgo",
    "iso:country":"ES",
    "sg:address":"Avda Montgo, 17",
    "sg:city":"Denia",
    "sg:orig_category":"Herboristas (al Por Menor)",
    "sg:phone":"+34 966 43 52 05",
    "sg:postcode":"03700",
    "sg:province":"Alicante",
    "wof:name":"Carrio Rosello S.l",
    "wof:placetype":"venue"
},
  "geometry": {"coordinates":[0.1027119979,38.8349227905],"type":"Point"}
}