{
  "type": "Feature",
  "properties": {
    "iso:country":"ES",
    "sg:address":"Calle de Antonio Machado, 14",
    "sg:city":"Madrid",
    "sg:orig_category":"Laboratorios Y Trabajos De Fotograf\u00cda, V\u00cddeo Y Cine",
    "sg:phone":"+34 913 73 28 40",
    "sg:postcode":"28035",
    "sg:province":"Madrid",
    "wof:name":"Lozano Garcia Ana Andrea",
    "wof:placetype":"venue"
},
  "geometry": {"coordinates":[-3.7194161415,40.4661750793],"type":"Point"}
}