{
  "type": "Feature",
  "properties": {
    "addr:full":"Calle de Parejo Y Ca\u00d1ero, 9 Puente-genil C\u00f3rdoba 14500",
    "addr:housenumber":"9",
    "addr:postcode":"14500",
    "addr:street":"Calle De Parejo Y Can\u0303Ero;Co\u0301Rdoba",
    "iso:country":"ES",
    "sg:address":"Calle de Parejo Y Ca\u00d1ero, 9",
    "sg:city":"Puente-genil",
    "sg:orig_category":"M\u00c1rmoles, Granitos Y Piedras Naturales",
    "sg:phone":"+34 957 60 54 29",
    "sg:postcode":"14500",
    "sg:province":"C\u00f3rdoba",
    "wof:name":"Santaella Velazquez Rafael",
    "wof:placetype":"venue"
},
  "geometry": {"coordinates":[-4.7703819275,37.3909378052],"type":"Point"}
}