{
  "type": "Feature",
  "properties": {
    "addr:full":"Calle de Lopez De Hoyos, 117 Madrid Madrid 28002",
    "addr:housenumber":"117",
    "addr:postcode":"28002",
    "addr:street":"Calle De Lopez De Hoyos",
    "iso:country":"ES",
    "sg:address":"Calle de Lopez De Hoyos, 117",
    "sg:city":"Madrid",
    "sg:orig_category":"Abogados",
    "sg:phone":"+34 915 19 46 13",
    "sg:postcode":"28002",
    "sg:province":"Madrid",
    "wof:name":"Alonso Garcia Manuel Francisco",
    "wof:placetype":"venue"
},
  "geometry": {"coordinates":[-3.6715729237,40.4458732605],"type":"Point"}
}