{
  "type": "Feature",
  "properties": {
    "iso:country":"ES",
    "sg:address":"Calle de Santa Maria, 13",
    "sg:city":"Caba\u00d1uelas",
    "sg:orig_category":"Contenedores (mercanc\u00cdas)",
    "sg:phone":"+34 950 55 35 17",
    "sg:postcode":"04738",
    "sg:province":"Almer\u00eda",
    "wof:name":"Corral Ortiz Jose",
    "wof:placetype":"venue"
},
  "geometry": {"coordinates":[-2.6343340874,36.8009490967],"type":"Point"}
}