{
  "type": "Feature",
  "properties": {
    "iso:country":"ES",
    "sg:address":"Avda Madro\u00d1os, 83",
    "sg:city":"Madrid",
    "sg:orig_category":"Arquitectos",
    "sg:phone":"+34 913 88 76 32",
    "sg:postcode":"28043",
    "sg:province":"Madrid",
    "wof:name":"Arquitecnica Dise\u00f1o Tecnico Urbano S.l.",
    "wof:placetype":"venue"
},
  "geometry": {"coordinates":[-3.6402759552,40.4568481445],"type":"Point"}
}