{
  "type": "Feature",
  "properties": {
    "addr:full":"Calle de Floresta, 26 Valencia Valencia 46022",
    "addr:housenumber":"26",
    "addr:postcode":"46022",
    "addr:street":"Calle De Floresta",
    "iso:country":"ES",
    "sg:address":"Calle de Floresta, 26",
    "sg:city":"Valencia",
    "sg:orig_category":"Molduras, Junquillos, Listones Y Molduras Perforadas",
    "sg:phone":"+34 963 30 52 96",
    "sg:postcode":"46022",
    "sg:province":"Valencia",
    "wof:name":"Bayarri Marti Encarnacion",
    "wof:placetype":"venue"
},
  "geometry": {"coordinates":[-0.3487150073,39.4668121338],"type":"Point"}
}