{
  "type": "Feature",
  "properties": {
    "iso:country":"ES",
    "sg:address":"Ctra Ajalvir, 8",
    "sg:city":"Alcala Henares",
    "sg:orig_category":"Transportes Por Carretera: Lotes Completos, Mercanc\u00cdas Diversas",
    "sg:phone":"+34 918 80 37 74",
    "sg:postcode":"28806",
    "sg:province":"Madrid",
    "sg:website":"www.redel.es",
    "wof:name":"Grupalia Internet S.a.",
    "wof:placetype":"venue"
},
  "geometry": {"coordinates":[-3.3779473305,40.4895133972],"type":"Point"}
}