{
  "type": "Feature",
  "properties": {
    "addr:full":"Carrer de Guilleries, 1 Sabadell Barcelona 08207",
    "addr:housenumber":"1",
    "addr:postcode":"08207",
    "addr:street":"Carrer De Guilleries",
    "iso:country":"ES",
    "sg:address":"Carrer de Guilleries, 1",
    "sg:city":"Sabadell",
    "sg:orig_category":"Supermercados Y Hipermercados",
    "sg:phone":"+34 937 17 61 16",
    "sg:postcode":"08207",
    "sg:province":"Barcelona",
    "wof:name":"Salguero Montero Saturnino",
    "wof:placetype":"venue"
},
  "geometry": {"coordinates":[2.0942490101,41.5657081604],"type":"Point"}
}