{
  "type": "Feature",
  "properties": {
    "iso:country":"ES",
    "sg:address":"Rond Sant Ramon, 86",
    "sg:city":"S. Boi Llobregat",
    "sg:orig_category":"Cajas De Ahorro",
    "sg:phone":"+34 936 52 56 60",
    "sg:postcode":"08830",
    "sg:province":"Barcelona",
    "wof:name":"Caja De Ahorros Y Monte De Piedad De Zaragoza Aragon Y Rioja",
    "wof:placetype":"venue"
},
  "geometry": {"coordinates":[2.0449779034,41.3480606079],"type":"Point"}
}