{
  "type": "Feature",
  "properties": {
    "addr:full":"Calle de Miguel Indurain, 9 Oviedo Asturias 33010",
    "addr:housenumber":"9",
    "addr:postcode":"33010",
    "addr:street":"Calle De Miguel Indurain",
    "iso:country":"ES",
    "sg:address":"Calle de Miguel Indurain, 9",
    "sg:city":"Oviedo",
    "sg:orig_category":"Edici\u00d3n De Diarios, Revistas, Boletines",
    "sg:phone":"+34 985 20 75 13",
    "sg:postcode":"33010",
    "sg:province":"Asturias",
    "wof:name":"Ediciones Santillana S.l.",
    "wof:placetype":"venue"
},
  "geometry": {"coordinates":[-5.8333377838,43.3629684448],"type":"Point"}
}