{
  "type": "Feature",
  "properties": {
    "iso:country":"ES",
    "sg:address":"Calle de Guadiana, 8",
    "sg:city":"Ajalvir",
    "sg:orig_category":"Empresarios Y Productoras De Espect\u00c1culos",
    "sg:phone":"+34 918 84 36 35",
    "sg:postcode":"28864",
    "sg:province":"Madrid",
    "wof:name":"Morefec Cine Y Tv S.l",
    "wof:placetype":"venue"
},
  "geometry": {"coordinates":[-3.4813609123,40.5000915527],"type":"Point"}
}