{
  "type": "Feature",
  "properties": {
    "addr:full":"Calle de Bego\u00d1a, 6 Coslada Madrid 28820",
    "addr:housenumber":"6",
    "addr:postcode":"28820",
    "addr:street":"Calle De Begon\u0303A",
    "iso:country":"ES",
    "sg:address":"Calle de Bego\u00d1a, 6",
    "sg:city":"Coslada",
    "sg:orig_category":"Fabricaci\u00d3n De Peines Y De Accesorios De Peluquer\u00cda",
    "sg:phone":"+34 916 74 17 91",
    "sg:postcode":"28820",
    "sg:province":"Madrid",
    "wof:name":"Capibell Comercial L.m. S.l.",
    "wof:placetype":"venue"
},
  "geometry": {"coordinates":[-3.5663990974,40.4259872437],"type":"Point"}
}