{
  "type": "Feature",
  "properties": {
    "iso:country":"ES",
    "sg:address":"Calle de Do\u00d1a Antonia De Prado, 10",
    "sg:city":"Baena",
    "sg:orig_category":"Agencias Y Agentes Comerciales, Representantes",
    "sg:phone":"+34 957 67 10 56",
    "sg:postcode":"14850",
    "sg:province":"C\u00f3rdoba",
    "wof:name":"Perez Lara Francisco Antonio",
    "wof:placetype":"venue"
},
  "geometry": {"coordinates":[-4.3179068565,37.6189346313],"type":"Point"}
}