{
  "type": "Feature",
  "properties": {
    "addr:full":"Calle de Carretera, 89 Ayegui Navarra 31240",
    "addr:housenumber":"89",
    "addr:postcode":"31240",
    "addr:street":"Calle De Carretera",
    "iso:country":"ES",
    "sg:address":"Calle de Carretera, 89",
    "sg:city":"Ayegui",
    "sg:orig_category":"Empresas De Carpinter\u00cda",
    "sg:phone":"+34 948 55 45 10",
    "sg:postcode":"31240",
    "sg:province":"Navarra",
    "wof:name":"Carpinteria De Aluminio Valentin S.l.",
    "wof:placetype":"venue"
},
  "geometry": {"coordinates":[-2.0839898586,42.6447525024],"type":"Point"}
}