{
  "type": "Feature",
  "properties": {
    "addr:full":"Urkiola Kalea, 10 Legizamon Vizcaya 48450",
    "addr:housenumber":"10",
    "addr:postcode":"48450",
    "addr:street":"Urkiola Kalea",
    "iso:country":"ES",
    "sg:address":"Urkiola Kalea, 10",
    "sg:city":"Legizamon",
    "sg:orig_category":"Venta, Instalaci\u00d3n De Calefacci\u00d3n",
    "sg:phone":"+34 944 45 15 76",
    "sg:postcode":"48450",
    "sg:province":"Vizcaya",
    "wof:name":"Bical Control Termico S.l.",
    "wof:placetype":"venue"
},
  "geometry": {"coordinates":[-2.9009649754,43.2455635071],"type":"Point"}
}