{
  "type": "Feature",
  "properties": {
    "addr:full":"Rua Real, 165 Ferrol La Coru\u00f1a 15402",
    "addr:housenumber":"165",
    "addr:postcode":"15402",
    "addr:street":"Rua Real;La Corun\u0303A",
    "iso:country":"ES",
    "sg:address":"Rua Real, 165",
    "sg:city":"Ferrol",
    "sg:orig_category":"Farmacias",
    "sg:phone":"+34 981 35 20 34",
    "sg:postcode":"15402",
    "sg:province":"La Coru\u00f1a",
    "wof:name":"Martinez Villar Maria Del Carmen",
    "wof:placetype":"venue"
},
  "geometry": {"coordinates":[-8.2355899811,43.4827041626],"type":"Point"}
}