{
  "type": "Feature",
  "properties": {
    "addr:full":"Av Cadiz, 2 Miami Playa Tarragona 43892",
    "addr:housenumber":"2",
    "addr:postcode":"43892",
    "addr:street":"Av Cadiz",
    "iso:country":"ES",
    "sg:address":"Av Cadiz, 2",
    "sg:city":"Miami Playa",
    "sg:orig_category":"Molduras, Junquillos, Listones Y Molduras Perforadas",
    "sg:phone":"+34 977 17 02 82",
    "sg:postcode":"43892",
    "sg:province":"Tarragona",
    "wof:name":"Os De Corneas S.l.",
    "wof:placetype":"venue"
},
  "geometry": {"coordinates":[0.9573349953,41.0249786377],"type":"Point"}
}