{
  "type": "Feature",
  "properties": {
    "iso:country":"ES",
    "sg:address":"Cmno Hondonada, 5",
    "sg:city":"Pechina",
    "sg:orig_category":"Promotores Constructores",
    "sg:phone":"+34 950 31 76 15",
    "sg:postcode":"04250",
    "sg:province":"Almer\u00eda",
    "wof:name":"Navarrete Delgado Javier",
    "wof:placetype":"venue"
},
  "geometry": {"coordinates":[-2.4415290356,36.914730072],"type":"Point"}
}