{
  "type": "Feature",
  "properties": {
    "iso:country":"ES",
    "sg:address":"Plaz Marques, 1",
    "sg:city":"Gijon",
    "sg:orig_category":"Albergues",
    "sg:phone":"+34 985 35 23 78",
    "sg:postcode":"33201",
    "sg:province":"Asturias",
    "wof:name":"Hostal Manjon C.b.",
    "wof:placetype":"venue"
},
  "geometry": {"coordinates":[-5.6629490852,43.5453186035],"type":"Point"}
}