{
  "type": "Feature",
  "properties": {
    "addr:full":"Calle de San Francisco, 25 Valdepe\u00f1as Ciudad Real 13300",
    "addr:housenumber":"25",
    "addr:postcode":"13300",
    "addr:street":"Calle De San Francisco",
    "iso:country":"ES",
    "sg:address":"Calle de San Francisco, 25",
    "sg:city":"Valdepe\u00f1as",
    "sg:orig_category":"Chapister\u00cda",
    "sg:phone":"+34 926 32 40 51",
    "sg:postcode":"13300",
    "sg:province":"Ciudad Real",
    "wof:name":"Carrocerias Arias S.l.",
    "wof:placetype":"venue"
},
  "geometry": {"coordinates":[-3.3830189705,38.7694587708],"type":"Point"}
}