{
  "type": "Feature",
  "properties": {
    "addr:full":"Calle de Gran Avenida, 29 Madrid Madrid 28041",
    "addr:housenumber":"29",
    "addr:postcode":"madrid;28041",
    "addr:street":"Calle De Gran Avenida",
    "iso:country":"ES",
    "sg:address":"Calle de Gran Avenida, 29",
    "sg:city":"Madrid",
    "sg:orig_category":"Laboratorios Y Cl\u00cdnicas Veterinarias",
    "sg:phone":"+34 913 41 75 74",
    "sg:postcode":"28041",
    "sg:province":"Madrid",
    "wof:name":"Lomban Villanueva Manuel Jesus",
    "wof:placetype":"venue"
},
  "geometry": {"coordinates":[-3.7061519623,40.3697662354],"type":"Point"}
}