{
  "type": "Feature",
  "properties": {
    "iso:country":"ES",
    "sg:address":"Rua Escusa, 17",
    "sg:city":"Escusa",
    "sg:orig_category":"Promotores Constructores",
    "sg:phone":"+34 986 71 02 40",
    "sg:postcode":"36636",
    "sg:province":"Pontevedra",
    "wof:name":"Borrajeiros Falcon Mari Carmen",
    "wof:placetype":"venue"
},
  "geometry": {"coordinates":[-8.7683343887,42.5012207031],"type":"Point"}
}