{
  "type": "Feature",
  "properties": {
    "addr:full":"Avda Constitucion, 1 Villa Don Fadrique Toledo 45850",
    "addr:housenumber":"1 villa",
    "addr:postcode":"45850",
    "addr:street":"Avda Constitucion",
    "iso:country":"ES",
    "sg:address":"Avda Constitucion, 1",
    "sg:city":"Villa Don Fadrique",
    "sg:orig_category":"Asesor\u00cda Fiscal Y Jur\u00cddica",
    "sg:phone":"+34 925 19 52 13",
    "sg:postcode":"45850",
    "sg:province":"Toledo",
    "wof:name":"Mediagest S.c.",
    "wof:placetype":"venue"
},
  "geometry": {"coordinates":[-3.2279889584,39.6153907776],"type":"Point"}
}