{
  "type": "Feature",
  "properties": {
    "iso:country":"ES",
    "sg:address":"Av Diagonal, 24",
    "sg:city":"Gava",
    "sg:orig_category":"Inmobiliaria (agencias)",
    "sg:phone":"+34 936 62 70 72",
    "sg:postcode":"08850",
    "sg:province":"Barcelona",
    "wof:name":"Subiseu S.l.",
    "wof:placetype":"venue"
},
  "geometry": {"coordinates":[1.9969320297,41.3056716919],"type":"Point"}
}