{
  "type": "Feature",
  "properties": {
    "iso:country":"ES",
    "sg:address":"Avda Goya, 16",
    "sg:city":"Zaragoza",
    "sg:orig_category":"Arquitectos",
    "sg:phone":"+34 976 23 22 02",
    "sg:postcode":"50006",
    "sg:province":"Zaragoza",
    "wof:name":"Claveria Carreras Roberto",
    "wof:placetype":"venue"
},
  "geometry": {"coordinates":[-1.0290249586,41.7227897644],"type":"Point"}
}