{
  "type": "Feature",
  "properties": {
    "addr:full":"Av Barcelona, 132 Miami Playa Tarragona 43892",
    "addr:housenumber":"132",
    "addr:postcode":"43892",
    "addr:street":"Av Barcelona",
    "iso:country":"ES",
    "sg:address":"Av Barcelona, 132",
    "sg:city":"Miami Playa",
    "sg:orig_category":"Supermercados Y Hipermercados",
    "sg:phone":"+34 977 81 01 15",
    "sg:postcode":"43892",
    "sg:province":"Tarragona",
    "wof:name":"Pardo Mu\u00f1oz Adolfina",
    "wof:placetype":"venue"
},
  "geometry": {"coordinates":[0.9573349953,41.0249786377],"type":"Point"}
}