{
  "type": "Feature",
  "properties": {
    "iso:country":"ES",
    "sg:address":"Calle de Maestro Joaquin Rodrigo, 55",
    "sg:city":"Toboso",
    "sg:orig_category":"Negocio De Materiales De Construcci\u00d3n",
    "sg:phone":"+34 925 56 80 57",
    "sg:postcode":"45820",
    "sg:province":"Toledo",
    "wof:name":"Transportes Palvireva S.l.",
    "wof:placetype":"venue"
},
  "geometry": {"coordinates":[-2.9981219769,39.5132637024],"type":"Point"}
}