{
  "type": "Feature",
  "properties": {
    "addr:full":"Casti\u00f1eiras, S/n Casti\u00f1eiras La Coru\u00f1a 15966",
    "addr:postcode":"15966",
    "addr:street":"Castin\u0303Eiras S / N Castin\u0303Eiras La Corun\u0303A",
    "iso:country":"ES",
    "sg:address":"Casti\u00f1eiras, S/n",
    "sg:city":"Casti\u00f1eiras",
    "sg:orig_category":"Papeler\u00cdas, Librer\u00cdas",
    "sg:phone":"+34 981 84 18 56",
    "sg:postcode":"15966",
    "sg:province":"La Coru\u00f1a",
    "wof:name":"Rivas Fernandez Maria Dolores",
    "wof:placetype":"venue"
},
  "geometry": {"coordinates":[-8.9895505905,42.5456504822],"type":"Point"}
}