{
  "type": "Feature",
  "properties": {
    "addr:full":"Ptge Estudi, 8 Sabadell Barcelona 08208",
    "addr:housenumber":"8",
    "addr:postcode":"08208",
    "addr:street":"Ptge Estudi",
    "iso:country":"ES",
    "sg:address":"Ptge Estudi, 8",
    "sg:city":"Sabadell",
    "sg:orig_category":"Mec\u00c1nico Del Autom\u00d3vil",
    "sg:phone":"+34 937 16 53 95",
    "sg:postcode":"08208",
    "sg:province":"Barcelona",
    "wof:name":"Torvisco Martinez Manuel",
    "wof:placetype":"venue"
},
  "geometry": {"coordinates":[2.0981490612,41.5593414307],"type":"Point"}
}