{
  "type": "Feature",
  "properties": {
    "iso:country":"ES",
    "sg:address":"Calle de Primautzar, 39",
    "sg:city":"Irun",
    "sg:orig_category":"Muebles",
    "sg:phone":"+34 943 62 23 82",
    "sg:postcode":"20305",
    "sg:province":"Guip\u00f9zcoa",
    "sg:website":"www.tiradoresegoki.com",
    "wof:name":"Tiradores Egoki S.l.",
    "wof:placetype":"venue"
},
  "geometry": {"coordinates":[-1.8267079592,43.3263320923],"type":"Point"}
}