{
  "type": "Feature",
  "properties": {
    "iso:country":"ES",
    "sg:address":"C/ Ameller, 21",
    "sg:city":"Banyoles",
    "sg:orig_category":"Mec\u00c1nico Del Autom\u00d3vil",
    "sg:phone":"+34 972 57 59 58",
    "sg:postcode":"17820",
    "sg:province":"Girona",
    "wof:name":"Auto Reparacio Emporda S.c.",
    "wof:placetype":"venue"
},
  "geometry": {"coordinates":[2.76887393,42.1190757751],"type":"Point"}
}