{
  "type": "Feature",
  "properties": {
    "iso:country":"ES",
    "sg:address":"Calle de Constancia, 67",
    "sg:city":"Sevilla",
    "sg:orig_category":"Radiocomunicaciones, Telefon\u00cda M\u00d3vil, Radiomensajer\u00cda: Servicios, Comercializaci\u00d3n",
    "sg:phone":"+34 954 45 53 30",
    "sg:postcode":"41010",
    "sg:province":"Sevilla",
    "wof:name":"Pe\u00f1a Y Mora S.l.",
    "wof:placetype":"venue"
},
  "geometry": {"coordinates":[-6.0055990219,37.3770942688],"type":"Point"}
}