{
  "type": "Feature",
  "properties": {
    "iso:country":"ES",
    "sg:address":"Calle de Alcala, 106",
    "sg:city":"Madrid",
    "sg:orig_category":"Laboratorios Farmac\u00c9uticos",
    "sg:phone":"+34 914 31 79 97",
    "sg:postcode":"28009",
    "sg:province":"Madrid",
    "wof:name":"Facor",
    "wof:placetype":"venue"
},
  "geometry": {"coordinates":[-3.6739406586,40.4255981445],"type":"Point"}
}