{
  "type": "Feature",
  "properties": {
    "iso:country":"ES",
    "sg:address":"Avda Francisco Ayala (de), S/n",
    "sg:city":"Granada",
    "sg:orig_category":"Reposter\u00cdas",
    "sg:phone":"+34 958 17 01 58",
    "sg:postcode":"18014",
    "sg:province":"Granada",
    "wof:name":"Panaderia Lumar S.l.",
    "wof:placetype":"venue"
},
  "geometry": {"coordinates":[-3.6183419228,37.1947212219],"type":"Point"}
}