{
  "type": "Feature",
  "properties": {
    "iso:country":"ES",
    "sg:address":"Calle de Oro, 3",
    "sg:city":"Talavera Reina",
    "sg:orig_category":"Mec\u00c1nico Del Autom\u00d3vil",
    "sg:phone":"+34 925 80 24 38",
    "sg:postcode":"45600",
    "sg:province":"Toledo",
    "wof:name":"Navazo Taboada Miguel",
    "wof:placetype":"venue"
},
  "geometry": {"coordinates":[-4.8282260895,39.9602546692],"type":"Point"}
}