{
  "type": "Feature",
  "properties": {
    "addr:full":"Calle de Julio Hauzeur, 41 Torrelavega Cantabria 39300",
    "addr:housenumber":"41",
    "addr:postcode":"39300",
    "addr:street":"Calle De Julio Hauzeur",
    "iso:country":"ES",
    "sg:address":"Calle de Julio Hauzeur, 41",
    "sg:city":"Torrelavega",
    "sg:orig_category":"Peluquer\u00cdas, Peluquer\u00cda Mixta",
    "sg:phone":"+34 942 80 27 87",
    "sg:postcode":"39300",
    "sg:province":"Cantabria",
    "wof:name":"Fernandez Gutierrez Maria Jesus",
    "wof:placetype":"venue"
},
  "geometry": {"coordinates":[-4.0602240562,43.3519668579],"type":"Point"}
}