{
  "type": "Feature",
  "properties": {
    "addr:full":"Calle de Calvo Sotelo, 20 Llanos De Aridane Santa Cruz De Tenerife 38760",
    "addr:housenumber":"20",
    "addr:postcode":"38760",
    "addr:street":"Calle De Calvo Sotelo",
    "iso:country":"ES",
    "sg:address":"Calle de Calvo Sotelo, 20",
    "sg:city":"Llanos De Aridane",
    "sg:orig_category":"Turismo: Lugares, Circuitos Y Curiosidades",
    "sg:phone":"+34 922 40 19 27",
    "sg:postcode":"38760",
    "sg:province":"Santa Cruz De Tenerife",
    "wof:name":"Schuler  Siegmund",
    "wof:placetype":"venue"
},
  "geometry": {"coordinates":[-17.9107685089,28.6588497162],"type":"Point"}
}