{
  "type": "Feature",
  "properties": {
    "addr:full":"Plaz Teatro, 6 Molina Segura Murcia 30500",
    "addr:postcode":"30500",
    "iso:country":"ES",
    "sg:address":"Plaz Teatro, 6",
    "sg:city":"Molina Segura",
    "sg:orig_category":"Agencias De Trabajo Temporal",
    "sg:phone":"+34 968 64 22 92",
    "sg:postcode":"30500",
    "sg:province":"Murcia",
    "wof:name":"Adecco E.t.t. S.a.",
    "wof:placetype":"venue"
},
  "geometry": {"coordinates":[-1.1298867464,37.9834747314],"type":"Point"}
}