{
  "type": "Feature",
  "properties": {
    "addr:full":"Pol Ind El Oliveral, S/n P. I. El Oliveral Valencia 46190",
    "addr:housenumber":"s / n",
    "addr:postcode":"46190",
    "addr:street":"P. I. El Oliveral",
    "iso:country":"ES",
    "sg:address":"Pol Ind El Oliveral, S/n",
    "sg:city":"P. I. El Oliveral",
    "sg:orig_category":"Delegados, Agentes De Tr\u00c1nsito, Auxiliares De Transporte Internacional",
    "sg:phone":"+34 961 66 51 07",
    "sg:postcode":"46190",
    "sg:province":"Valencia",
    "wof:name":"Coherval Artesans C B",
    "wof:placetype":"venue"
},
  "geometry": {"coordinates":[-0.5698940158,39.5458450317],"type":"Point"}
}