{
  "type": "Feature",
  "properties": {
    "addr:full":"Carrer de Anselm Clave, 74 Granollers Barcelona 08401",
    "addr:housenumber":"74",
    "addr:postcode":"08401",
    "addr:street":"Carrer De Anselm Clave",
    "iso:country":"ES",
    "sg:address":"Carrer de Anselm Clave, 74",
    "sg:city":"Granollers",
    "sg:orig_category":"Sociedades, Compa\u00d1\u00cdas Aseguradoras",
    "sg:phone":"+34 938 70 09 30",
    "sg:postcode":"08401",
    "sg:province":"Barcelona",
    "wof:name":"Canal Margenat Natividad",
    "wof:placetype":"venue"
},
  "geometry": {"coordinates":[2.288367033,41.6060752869],"type":"Point"}
}