{
  "type": "Feature",
  "properties": {
    "iso:country":"ES",
    "sg:address":"Calle de Laguna Del Marquesado, 10",
    "sg:city":"Madrid",
    "sg:orig_category":"Servicios De Telecomunicaciones",
    "sg:phone":"+34 916 42 72 35",
    "sg:postcode":"28021",
    "sg:province":"Madrid",
    "wof:name":"Tefercon Servicios De Telecomunicaciones S.l.",
    "wof:placetype":"venue"
},
  "geometry": {"coordinates":[-3.704324007,40.3337593079],"type":"Point"}
}