{
  "type": "Feature",
  "properties": {
    "addr:full":"Calle de Pintor Lopez, 19 Castellon Castell\u00f3n 12004",
    "addr:housenumber":"19",
    "addr:postcode":"12004",
    "addr:street":"Calle De Pintor Lopez",
    "iso:country":"ES",
    "sg:address":"Calle de Pintor Lopez, 19",
    "sg:city":"Castellon",
    "sg:orig_category":"Empresas De Impermeabilizaci\u00d3n",
    "sg:phone":"+34 964 21 73 97",
    "sg:postcode":"12004",
    "sg:province":"Castell\u00f3n",
    "wof:name":"Tosca Celma Juan Alberto",
    "wof:placetype":"venue"
},
  "geometry": {"coordinates":[-0.0481470004,39.9910926819],"type":"Point"}
}