{
  "type": "Feature",
  "properties": {
    "iso:country":"ES",
    "sg:address":"Rua Nosa Sra. Da Sainza, 18",
    "sg:city":"Ourense",
    "sg:orig_category":"Peluquer\u00cdas, Peluquer\u00cda Mixta",
    "sg:phone":"+34 988 22 73 41",
    "sg:postcode":"32005",
    "sg:province":"Ourense",
    "wof:name":"Rodriguez Gonzalez Herminia",
    "wof:placetype":"venue"
},
  "geometry": {"coordinates":[-7.8621702194,42.329158783],"type":"Point"}
}