{
  "type": "Feature",
  "properties": {
    "iso:country":"ES",
    "sg:address":"Avda Constitucion, 72",
    "sg:city":"Talarrubias",
    "sg:orig_category":"Inform\u00c1tica, Ofim\u00c1tica (estudios, Asesor\u00cda, Ingenier\u00cda, Formaci\u00d3n)",
    "sg:phone":"+34 924 63 12 28",
    "sg:postcode":"06640",
    "sg:province":"Badajoz",
    "wof:name":"Cisel S.a.",
    "wof:placetype":"venue"
},
  "geometry": {"coordinates":[-5.2352728844,39.0370826721],"type":"Point"}
}