{
  "type": "Feature",
  "properties": {
    "addr:full":"Rua San Pedro (de), 71 Santiago De Compostela La Coru\u00f1a 15703",
    "addr:housenumber":"71",
    "addr:postcode":"15703",
    "addr:street":"Rua San Pedro De;Corun\u0303A",
    "iso:country":"ES",
    "sg:address":"Rua San Pedro (de), 71",
    "sg:city":"Santiago De Compostela",
    "sg:orig_category":"Peluquer\u00cdas, Peluquer\u00cda Mixta",
    "sg:phone":"+34 981 56 03 74",
    "sg:postcode":"15703",
    "sg:province":"La Coru\u00f1a",
    "wof:name":"Merche & Mara Peluquerias",
    "wof:placetype":"venue"
},
  "geometry": {"coordinates":[-8.5371990204,42.8815574646],"type":"Point"}
}