{
  "type": "Feature",
  "properties": {
    "addr:full":"Carrer de Batlle Dionis Mestre, 8 Montblanc Tarragona 43400",
    "addr:housenumber":"8",
    "addr:postcode":"43400",
    "addr:street":"Carrer De Batlle Dionis Mestre",
    "iso:country":"ES",
    "sg:address":"Carrer de Batlle Dionis Mestre, 8",
    "sg:city":"Montblanc",
    "sg:orig_category":"Equipo De Refrigeraci\u00d3n Industrial",
    "sg:phone":"+34 977 86 26 26",
    "sg:postcode":"43400",
    "sg:province":"Tarragona",
    "wof:name":"Civit Avila Jose",
    "wof:placetype":"venue"
},
  "geometry": {"coordinates":[1.1656800508,41.3746299744],"type":"Point"}
}