{
  "type": "Feature",
  "properties": {
    "addr:full":"Calle de Libertad La, 11 Piedras Blancas Asturias 33450",
    "addr:housenumber":"11",
    "addr:postcode":"33450",
    "addr:street":"Calle De Libertad La",
    "iso:country":"ES",
    "sg:address":"Calle de Libertad La, 11",
    "sg:city":"Piedras Blancas",
    "sg:orig_category":"Alimentaci\u00d3n General (al Por Menor)",
    "sg:phone":"+34 985 53 11 93",
    "sg:postcode":"33450",
    "sg:province":"Asturias",
    "wof:name":"Vallina Fernandez Isabel",
    "wof:placetype":"venue"
},
  "geometry": {"coordinates":[-5.9737539291,43.5611763],"type":"Point"}
}