{
  "type": "Feature",
  "properties": {
    "addr:full":"Major, 62 Almacelles Lleida 25100",
    "addr:housenumber":"62",
    "addr:postcode":"25100",
    "addr:street":"Major",
    "iso:country":"ES",
    "sg:address":"Major, 62",
    "sg:city":"Almacelles",
    "sg:orig_category":"Agricultura: Abastecimiento Y Cosechado (negocio)",
    "sg:phone":"+34 973 74 00 09",
    "sg:postcode":"25100",
    "sg:province":"Lleida",
    "wof:name":"Baltom S.c.p.",
    "wof:placetype":"venue"
},
  "geometry": {"coordinates":[0.4392989874,41.7295379639],"type":"Point"}
}