{
  "type": "Feature",
  "properties": {
    "iso:country":"ES",
    "sg:address":"Rua Castelao (de), 33",
    "sg:city":"Carballi\u00f1o",
    "sg:orig_category":"Mec\u00c1nico Del Autom\u00d3vil",
    "sg:phone":"+34 988 27 25 03",
    "sg:postcode":"32500",
    "sg:province":"Ourense",
    "wof:name":"Pinal Vazquez Ramon",
    "wof:placetype":"venue"
},
  "geometry": {"coordinates":[-8.0696849823,42.4391670227],"type":"Point"}
}