{
  "type": "Feature",
  "properties": {
    "iso:country":"ES",
    "sg:address":"Calle de Azafranal, 16",
    "sg:city":"Salamanca",
    "sg:orig_category":"Zapatos (al Por Menor)",
    "sg:phone":"+34 923 26 86 05",
    "sg:postcode":"37001",
    "sg:province":"Salamanca",
    "wof:name":"Hernandez Herrera Pedro",
    "wof:placetype":"venue"
},
  "geometry": {"coordinates":[-5.6611003876,40.9670944214],"type":"Point"}
}