{
  "type": "Feature",
  "properties": {
    "addr:full":"Plaz Espa\u00d1a, 13 Don Benito Badajoz 06400",
    "addr:housenumber":"13",
    "addr:postcode":"06400",
    "addr:street":"Plaz Espan\u0303A",
    "iso:country":"ES",
    "sg:address":"Plaz Espa\u00d1a, 13",
    "sg:city":"Don Benito",
    "sg:orig_category":"Molduras, Junquillos, Listones Y Molduras Perforadas",
    "sg:phone":"+34 924 80 15 43",
    "sg:postcode":"06400",
    "sg:province":"Badajoz",
    "wof:name":"Parejo Diaz Manuel",
    "wof:placetype":"venue"
},
  "geometry": {"coordinates":[-5.8639888763,38.9548797607],"type":"Point"}
}