{
  "type": "Feature",
  "properties": {
    "addr:full":"Calle de Andres Obispo, 37 Madrid Madrid 28043",
    "addr:housenumber":"37",
    "addr:postcode":"madrid;28043",
    "addr:street":"Calle De Andres Obispo",
    "iso:country":"ES",
    "sg:address":"Calle de Andres Obispo, 37",
    "sg:city":"Madrid",
    "sg:orig_category":"Ense\u00d1anza, Formaci\u00d3n Profesional: Aprendizaje",
    "sg:phone":"+34 913 88 30 25",
    "sg:postcode":"28043",
    "sg:province":"Madrid",
    "wof:name":"Escuela De Capacitacion Laboral Escala S.l.",
    "wof:placetype":"venue"
},
  "geometry": {"coordinates":[-3.6483073235,40.4654197693],"type":"Point"}
}