{
  "type": "Feature",
  "properties": {
    "addr:full":"Carrer de Fran\u00c7a, 66 Hospitalet Llobregat Barcelona 08907",
    "addr:housenumber":"66",
    "addr:postcode":"08907",
    "addr:street":"Carrer De Franc\u0327A",
    "iso:country":"ES",
    "sg:address":"Carrer de Fran\u00c7a, 66",
    "sg:city":"Hospitalet Llobregat",
    "sg:orig_category":"M\u00c9dicos: Endocrinolog\u00cda Y Metabolismo",
    "sg:phone":"+34 932 63 39 77",
    "sg:postcode":"08907",
    "sg:province":"Barcelona",
    "wof:name":"Coridalis S.c.p",
    "wof:placetype":"venue"
},
  "geometry": {"coordinates":[2.1118071079,41.3549957275],"type":"Point"}
}