{
  "type": "Feature",
  "properties": {
    "addr:full":"Calle de Rio Azuer, 13 Solana Ciudad Real 13240",
    "addr:housenumber":"13",
    "addr:postcode":"solana;13240",
    "addr:street":"Calle De Rio Azuer;Real",
    "iso:country":"ES",
    "sg:address":"Calle de Rio Azuer, 13",
    "sg:city":"Solana",
    "sg:orig_category":"Camiser\u00cda Y Ropa Interior Masculina (al Por Menor)",
    "sg:phone":"+34 926 63 39 57",
    "sg:postcode":"13240",
    "sg:province":"Ciudad Real",
    "wof:name":"Confecciones Larpi S.l.",
    "wof:placetype":"venue"
},
  "geometry": {"coordinates":[-3.2361390591,38.9365196228],"type":"Point"}
}