{
  "type": "Feature",
  "properties": {
    "iso:country":"ES",
    "sg:address":"Av J Ortega Y Gasset (mercamalaga), Km. 0007,0",
    "sg:city":"Malaga",
    "sg:orig_category":"Frutas Y Legumbres Frescas (al Por Mayor)",
    "sg:phone":"+34 952 17 90 26",
    "sg:postcode":"29196",
    "sg:province":"M\u00e1laga",
    "wof:name":"Frugaser S.l.",
    "wof:placetype":"venue"
},
  "geometry": {"coordinates":[-4.5153698921,36.7060813904],"type":"Point"}
}