{
  "type": "Feature",
  "properties": {
    "iso:country":"ES",
    "sg:address":"Ctra Aeropuerto, Km. 0005,0",
    "sg:city":"Garrapinillos",
    "sg:orig_category":"Fachadas",
    "sg:phone":"+34 976 53 01 79",
    "sg:postcode":"50190",
    "sg:province":"Zaragoza",
    "wof:name":"Hernandez Teson Josefina",
    "wof:placetype":"venue"
},
  "geometry": {"coordinates":[-1.0247139931,41.6755256653],"type":"Point"}
}