{
  "type": "Feature",
  "properties": {
    "iso:country":"ES",
    "sg:address":"Carr Cami De Corbins, S/n",
    "sg:city":"Lleida",
    "sg:orig_category":"Aceites Y Grasas Alimentarias (fabricaci\u00d3n, Al Por Mayor)",
    "sg:phone":"+34 973 23 71 14",
    "sg:postcode":"25005",
    "sg:province":"Lleida",
    "wof:name":"Ferran Baque Francisco",
    "wof:placetype":"venue"
},
  "geometry": {"coordinates":[0.636228025,41.625125885],"type":"Point"}
}