{
  "type": "Feature",
  "properties": {
    "iso:country":"ES",
    "sg:address":"Carr Barcelona, 2",
    "sg:city":"Mao",
    "sg:orig_category":"Alquiler De V\u00cddeo",
    "sg:phone":"+34 971 35 41 40",
    "sg:postcode":"07701",
    "sg:province":"Islas Baleares",
    "wof:name":"Mercadal Vinent Ana Maria",
    "wof:placetype":"venue"
},
  "geometry": {"coordinates":[4.2726988792,39.8891525269],"type":"Point"}
}