{
  "type": "Feature",
  "properties": {
    "addr:full":"Carrer de Muntaner, 177 Barcelona Barcelona 08036",
    "addr:housenumber":"177",
    "addr:postcode":"08036",
    "addr:street":"Carrer De Muntaner",
    "iso:country":"ES",
    "sg:address":"Carrer de Muntaner, 177",
    "sg:city":"Barcelona",
    "sg:orig_category":"Empresas De Pintura Y Revestimientos",
    "sg:phone":"+34 934 19 00 14",
    "sg:postcode":"08036",
    "sg:province":"Barcelona",
    "wof:name":"Color De Pipsa S.l.",
    "wof:placetype":"venue"
},
  "geometry": {"coordinates":[2.151927948,41.3920707703],"type":"Point"}
}