{
  "type": "Feature",
  "properties": {
    "addr:full":"Rua Alfonso Xiii, 44 Vigo Pontevedra 36201",
    "addr:housenumber":"44",
    "addr:postcode":"36201",
    "addr:street":"Rua Alfonso Xiii",
    "iso:country":"ES",
    "sg:address":"Rua Alfonso Xiii, 44",
    "sg:city":"Vigo",
    "sg:orig_category":"Farmacias",
    "sg:phone":"+34 986 43 07 15",
    "sg:postcode":"36201",
    "sg:province":"Pontevedra",
    "wof:name":"Dobarro Correa Maria Lourdes",
    "wof:placetype":"venue"
},
  "geometry": {"coordinates":[-8.7156095505,42.2355651855],"type":"Point"}
}