{
  "type": "Feature",
  "properties": {
    "iso:country":"ES",
    "sg:address":"Calle de Jesus Asuncion, 17",
    "sg:city":"Caceres",
    "sg:orig_category":"Transporte En General",
    "sg:phone":"+34 927 24 87 97",
    "sg:postcode":"10004",
    "sg:province":"C\u00e1ceres",
    "wof:name":"Sanchez Pico Andres Pedro",
    "wof:placetype":"venue"
},
  "geometry": {"coordinates":[-6.3583831787,39.5027656555],"type":"Point"}
}