{
  "type": "Feature",
  "properties": {
    "addr:full":"Calle de Castellana, 13 Madrid Madrid 28046",
    "addr:housenumber":"13",
    "addr:postcode":"madrid;28046",
    "addr:street":"Calle De Castellana",
    "iso:country":"ES",
    "sg:address":"Calle de Castellana, 13",
    "sg:city":"Madrid",
    "sg:orig_category":"Inform\u00c1tica (estudios, Servicios, Asesor\u00cda, Formaci\u00d3n)",
    "sg:phone":"+34 913 19 38 76",
    "sg:postcode":"28046",
    "sg:province":"Madrid",
    "wof:name":"Depositos De Materias Y Grasas Industriales",
    "wof:placetype":"venue"
},
  "geometry": {"coordinates":[-3.6903429031,40.4277648926],"type":"Point"}
}