{
  "type": "Feature",
  "properties": {
    "iso:country":"ES",
    "sg:address":"Avda Velazquez, S/n",
    "sg:city":"Malaga",
    "sg:orig_category":"Ropa De Hogar (al Por Menor)",
    "sg:phone":"+34 952 23 79 23",
    "sg:postcode":"29004",
    "sg:province":"M\u00e1laga",
    "wof:name":"Romero Mari Alejandro",
    "wof:placetype":"venue"
},
  "geometry": {"coordinates":[-4.4570689201,36.6909065247],"type":"Point"}
}