{
  "type": "Feature",
  "properties": {
    "addr:full":"Carr Major, 9 Seu D'urgell Lleida 25700",
    "addr:housenumber":"9",
    "addr:postcode":"25700",
    "addr:street":"Carr Major",
    "iso:country":"ES",
    "sg:address":"Carr Major, 9",
    "sg:city":"Seu D'urgell",
    "sg:orig_category":"Electricidad (montaje, Ensamblaje De Componentes)",
    "sg:phone":"+34 973 35 02 44",
    "sg:postcode":"25700",
    "sg:province":"Lleida",
    "wof:name":"Vilades Buixo Vicens",
    "wof:placetype":"venue"
},
  "geometry": {"coordinates":[0.6261399984,41.6142311096],"type":"Point"}
}