{
  "type": "Feature",
  "properties": {
    "iso:country":"ES",
    "sg:address":"Calle de San Jose, 3",
    "sg:city":"Plasencia",
    "sg:orig_category":"Laboratorios Y Trabajos De Fotograf\u00cda, V\u00cddeo Y Cine",
    "sg:phone":"+34 927 41 02 04",
    "sg:postcode":"10600",
    "sg:province":"C\u00e1ceres",
    "wof:name":"Placentina De Color S.l.",
    "wof:placetype":"venue"
},
  "geometry": {"coordinates":[-6.0825810432,40.0353622437],"type":"Point"}
}