{
  "type": "Feature",
  "properties": {
    "iso:country":"ES",
    "sg:address":"Disem. Las Presas, S/n",
    "sg:city":"Los Barrios",
    "sg:orig_category":"Asociaciones Y Clubs Deportivos",
    "sg:phone":"+34 956 62 24 44",
    "sg:postcode":"11370",
    "sg:province":"C\u00e1diz",
    "wof:name":"Espinosa Macias Juan",
    "wof:placetype":"venue"
},
  "geometry": {"coordinates":[-5.4749898911,36.179775238],"type":"Point"}
}