{
  "type": "Feature",
  "properties": {
    "iso:country":"ES",
    "sg:address":"Calle de Refugio, 10",
    "sg:city":"Zaragoza",
    "sg:orig_category":"Organismos De Turismo",
    "sg:phone":"+34 976 29 20 04",
    "sg:postcode":"50001",
    "sg:province":"Zaragoza",
    "wof:name":"Paris Roche Jose Alberto",
    "wof:placetype":"venue"
},
  "geometry": {"coordinates":[-0.8773360252,41.6534729004],"type":"Point"}
}