{
  "type": "Feature",
  "properties": {
    "iso:country":"ES",
    "sg:address":"Carrer de Ca L'alegre De Dalt, 28",
    "sg:city":"Barcelona",
    "sg:orig_category":"Electricidad: Instaladores",
    "sg:phone":"+34 932 10 83 76",
    "sg:postcode":"08024",
    "sg:province":"Barcelona",
    "wof:name":"Muntatges I Cablejats De Sistemes Inelec S.l.",
    "wof:placetype":"venue"
},
  "geometry": {"coordinates":[2.1621332169,41.4081535339],"type":"Point"}
}