{
  "type": "Feature",
  "properties": {
    "addr:full":"Ctra Rellinars, 293 Terrassa Barcelona 08225",
    "addr:housenumber":"293",
    "addr:postcode":"08225",
    "addr:street":"Ctra Rellinars",
    "iso:country":"ES",
    "sg:address":"Ctra Rellinars, 293",
    "sg:city":"Terrassa",
    "sg:orig_category":"Molduras, Junquillos, Listones Y Molduras Perforadas",
    "sg:phone":"+34 937 88 70 28",
    "sg:postcode":"08225",
    "sg:province":"Barcelona",
    "wof:name":"Brandulas Perez Francisco",
    "wof:placetype":"venue"
},
  "geometry": {"coordinates":[2.0045580864,41.5773849487],"type":"Point"}
}