{
  "type": "Feature",
  "properties": {
    "iso:country":"ES",
    "sg:address":"Ctra. Valmojado, Km. 0051,0",
    "sg:city":"Cedillo Condado",
    "sg:orig_category":"Muebles, Minoristas",
    "sg:phone":"+34 925 50 84 19",
    "sg:postcode":"45214",
    "sg:province":"Toledo",
    "wof:name":"Gaitan Torpedo Juan Antonio",
    "wof:placetype":"venue"
},
  "geometry": {"coordinates":[-3.9327785969,40.1182899475],"type":"Point"}
}