{
  "type": "Feature",
  "properties": {
    "iso:country":"ES",
    "sg:address":"Carretera Cordoba-valencia, Km. 0138,5",
    "sg:city":"Rus",
    "sg:orig_category":"Distribuci\u00d3n De Petr\u00d3leo Y Derivados",
    "sg:phone":"+34 953 79 95 37",
    "sg:postcode":"23430",
    "sg:province":"Ja\u00e9n",
    "wof:name":"Moreno Palomares Miguel",
    "wof:placetype":"venue"
},
  "geometry": {"coordinates":[-3.4641931057,38.0461196899],"type":"Point"}
}