{
  "type": "Feature",
  "properties": {
    "addr:full":"Avda Aceituneros, 43 Martos Ja\u00e9n 23600",
    "addr:housenumber":"43",
    "addr:postcode":"23600",
    "addr:street":"Avda Aceituneros;Jae\u0301N",
    "iso:country":"ES",
    "sg:address":"Avda Aceituneros, 43",
    "sg:city":"Martos",
    "sg:orig_category":"Transportes Por Carretera: Lotes Completos, Mercanc\u00cdas Diversas",
    "sg:phone":"+34 953 55 07 29",
    "sg:postcode":"23600",
    "sg:province":"Ja\u00e9n",
    "wof:name":"Fernandez Fernandez Diego",
    "wof:placetype":"venue"
},
  "geometry": {"coordinates":[-3.972132206,37.7183380127],"type":"Point"}
}