{
  "type": "Feature",
  "properties": {
    "addr:full":"Psj. Los Arcos, 7 S. Clemente Cuenca 16600",
    "addr:housenumber":"7",
    "addr:postcode":"16600",
    "addr:street":"Los Arcos;S. Clemente Cuenca",
    "iso:country":"ES",
    "sg:address":"Psj. Los Arcos, 7",
    "sg:city":"S. Clemente",
    "sg:orig_category":"Procuradores",
    "sg:phone":"+34 969 30 03 89",
    "sg:postcode":"16600",
    "sg:province":"Cuenca",
    "wof:name":"Molero Ortiz Ana Belen",
    "wof:placetype":"venue"
},
  "geometry": {"coordinates":[-2.4270188808,39.3993186951],"type":"Point"}
}