{
  "type": "Feature",
  "properties": {
    "iso:country":"ES",
    "sg:address":"Calle de Fundidores, 57",
    "sg:city":"Getafe",
    "sg:orig_category":"Animales (al Por Menor)",
    "sg:phone":"+34 916 83 33 12",
    "sg:postcode":"28906",
    "sg:province":"Madrid",
    "wof:name":"Distribuidora Madrile\u00f1a De Alimentacion S. A.",
    "wof:placetype":"venue"
},
  "geometry": {"coordinates":[-3.6945769787,40.3119812012],"type":"Point"}
}