{
  "type": "Feature",
  "properties": {
    "addr:full":"Pl Nova, 2 Santa Perpetua De Mogoda Barcelona 08130",
    "addr:housenumber":"2",
    "addr:postcode":"08130",
    "addr:street":"Pl Nova",
    "iso:country":"ES",
    "sg:address":"Pl Nova, 2",
    "sg:city":"Santa Perpetua De Mogoda",
    "sg:orig_category":"Florister\u00cdas",
    "sg:phone":"+34 935 60 18 17",
    "sg:postcode":"08130",
    "sg:province":"Barcelona",
    "wof:name":"Martos Burgos Teodoro",
    "wof:placetype":"venue"
},
  "geometry": {"coordinates":[2.1826400757,41.5343589783],"type":"Point"}
}