{
  "type": "Feature",
  "properties": {
    "addr:full":"Urbz Itaroa, S/n Huarte Navarra 31620",
    "addr:housenumber":"s / n",
    "addr:postcode":"31620",
    "addr:street":"Navarra",
    "iso:country":"ES",
    "sg:address":"Urbz Itaroa, S/n",
    "sg:city":"Huarte",
    "sg:orig_category":"Relojer\u00cda (al Por Menor, Reparaci\u00d3n)",
    "sg:phone":"+34 948 33 79 28",
    "sg:postcode":"31620",
    "sg:province":"Navarra",
    "wof:name":"Ballester Belcos Carolina",
    "wof:placetype":"venue"
},
  "geometry": {"coordinates":[-1.5902739763,42.83177948],"type":"Point"}
}