{
  "type": "Feature",
  "properties": {
    "iso:country":"ES",
    "sg:address":"Calle de Corredera, 8",
    "sg:city":"Herrera Pisuerga",
    "sg:orig_category":"Caf\u00c9s, Bares, Cervecer\u00cdas",
    "sg:phone":"+34 979 13 05 77",
    "sg:postcode":"34400",
    "sg:province":"Palencia",
    "wof:name":"Aranda Roldan Fatima",
    "wof:placetype":"venue"
},
  "geometry": {"coordinates":[-4.3302931786,42.5963020325],"type":"Point"}
}