{
  "type": "Feature",
  "properties": {
    "iso:country":"ES",
    "sg:address":"Calle de Pedro Antonio De Alarcon, 58",
    "sg:city":"Madrid",
    "sg:orig_category":"Lavado, Limpieza De Veh\u00cdculos",
    "sg:phone":"+34 914 08 19 15",
    "sg:postcode":"28017",
    "sg:province":"Madrid",
    "wof:name":"Engrase Garvi S.l.",
    "wof:placetype":"venue"
},
  "geometry": {"coordinates":[-3.6404540539,40.4275360107],"type":"Point"}
}