{
  "type": "Feature",
  "properties": {
    "addr:full":"Calle de Escuela De Capataces, 37 Mieres Asturias 33600",
    "addr:housenumber":"37",
    "addr:postcode":"33600",
    "addr:street":"Calle De;Capataces",
    "iso:country":"ES",
    "sg:address":"Calle de Escuela De Capataces, 37",
    "sg:city":"Mieres",
    "sg:orig_category":"Mercer\u00cda, Lencer\u00cda (al Por Menor)",
    "sg:phone":"+34 985 46 28 22",
    "sg:postcode":"33600",
    "sg:province":"Asturias",
    "wof:name":"Valdes Decoracion",
    "wof:placetype":"venue"
},
  "geometry": {"coordinates":[-5.7747220993,43.2525787354],"type":"Point"}
}