{
  "type": "Feature",
  "properties": {
    "addr:full":"Avgd Segre, 7 Lleida Lleida 25007",
    "addr:housenumber":"7",
    "addr:postcode":"25007",
    "addr:street":"Avgd Segre",
    "iso:country":"ES",
    "sg:address":"Avgd Segre, 7",
    "sg:city":"Lleida",
    "sg:orig_category":"Arquitectos",
    "sg:phone":"+34 973 24 93 81",
    "sg:postcode":"25007",
    "sg:province":"Lleida",
    "wof:name":"Macia Aymerich Roman",
    "wof:placetype":"venue"
},
  "geometry": {"coordinates":[0.6322609782,41.6168174744],"type":"Point"}
}