{
  "type": "Feature",
  "properties": {
    "addr:full":"Carr Joan Baptista Cabanillas, 29 Pollen\u00e7a Islas Baleares 07460",
    "addr:housenumber":"29",
    "addr:postcode":"07460",
    "addr:street":"Carr Joan Baptista Cabanillas",
    "iso:country":"ES",
    "sg:address":"Carr Joan Baptista Cabanillas, 29",
    "sg:city":"Pollen\u00e7a",
    "sg:orig_category":"Promotores Constructores",
    "sg:phone":"+34 971 53 01 72",
    "sg:postcode":"07460",
    "sg:province":"Islas Baleares",
    "wof:name":"Lopez Chacon S.l",
    "wof:placetype":"venue"
},
  "geometry": {"coordinates":[3.0141830444,39.8730316162],"type":"Point"}
}