{
  "type": "Feature",
  "properties": {
    "addr:full":"Carrer de Pompeu Fabra, S/n Castellvell Camp Tarragona 43392",
    "addr:housenumber":"s",
    "addr:postcode":"43392",
    "addr:street":"Carrer De Pompeu;/ N Castellvell",
    "iso:country":"ES",
    "sg:address":"Carrer de Pompeu Fabra, S/n",
    "sg:city":"Castellvell Camp",
    "sg:orig_category":"Centros De Educaci\u00d3n Especial",
    "sg:phone":"+34 977 85 54 31",
    "sg:postcode":"43392",
    "sg:province":"Tarragona",
    "wof:name":"Collegi Public Santa Anna",
    "wof:placetype":"venue"
},
  "geometry": {"coordinates":[1.0984250307,41.1802406311],"type":"Point"}
}