{
  "type": "Feature",
  "properties": {
    "addr:full":"Carr Sant Narcis, 2 Hostalric Girona 17450",
    "addr:housenumber":"2",
    "addr:postcode":"17450",
    "addr:street":"Carr Sant Narcis",
    "iso:country":"ES",
    "sg:address":"Carr Sant Narcis, 2",
    "sg:city":"Hostalric",
    "sg:classifiers":[
        {
            "category":"Taxi",
            "type":"Transportation"
        }
    ],
    "sg:phone":"+34 972 86 41 36",
    "sg:postcode":"17450",
    "sg:province":"Girona",
    "wof:name":"Rabassa Coma Juan",
    "wof:placetype":"venue"
},
  "geometry": {"coordinates":[2.6431410313,41.7457771301],"type":"Point"}
}