{
  "type": "Feature",
  "properties": {
    "addr:full":"Plaz Espa\u00d1a (de), S/n Torrecillas Tiesa C\u00e1ceres 10252",
    "addr:housenumber":"s / n",
    "addr:postcode":"10252",
    "addr:street":"Plaz;Ca\u0301Ceres",
    "iso:country":"ES",
    "sg:address":"Plaz Espa\u00d1a (de), S/n",
    "sg:city":"Torrecillas Tiesa",
    "sg:orig_category":"Cajas De Ahorro",
    "sg:phone":"+34 927 33 82 56",
    "sg:postcode":"10252",
    "sg:province":"C\u00e1ceres",
    "wof:name":"Caja De Ahorros Y Monte De Piedad De Extremadura",
    "wof:placetype":"venue"
},
  "geometry": {"coordinates":[-5.7408027649,39.5644073486],"type":"Point"}
}