{
  "type": "Feature",
  "properties": {
    "addr:full":"Rbla Fiveller, 3 Mollet Valles Barcelona 08100",
    "addr:housenumber":"3",
    "addr:postcode":"08100",
    "addr:street":"Rbla Fiveller",
    "iso:country":"ES",
    "sg:address":"Rbla Fiveller, 3",
    "sg:city":"Mollet Valles",
    "sg:orig_category":"M\u00c9dicos: Estomatolog\u00cda",
    "sg:phone":"+34 935 93 06 49",
    "sg:postcode":"08100",
    "sg:province":"Barcelona",
    "wof:name":"Fraga Rodriguez Severino",
    "wof:placetype":"venue"
},
  "geometry": {"coordinates":[2.2120790482,41.5381660461],"type":"Point"}
}