{
  "type": "Feature",
  "properties": {
    "addr:full":"Ctra Madrid-cadiz(bellavista), 45 Sevilla Sevilla 41014",
    "addr:housenumber":"45",
    "addr:postcode":"41014",
    "addr:street":"Ctra Madrid-Cadiz Bellavista",
    "iso:country":"ES",
    "sg:address":"Ctra Madrid-cadiz(bellavista), 45",
    "sg:city":"Sevilla",
    "sg:orig_category":"Asociaciones Y Clubs Deportivos",
    "sg:phone":"+34 954 69 05 69",
    "sg:postcode":"41014",
    "sg:province":"Sevilla",
    "wof:name":"Pe\u00f1a Sevillista Bellavista",
    "wof:placetype":"venue"
},
  "geometry": {"coordinates":[-5.9596791267,37.3278617859],"type":"Point"}
}