{
  "type": "Feature",
  "properties": {
    "addr:full":"Carrer de Benlliure, 9 Castalla Alicante 03420",
    "addr:housenumber":"9",
    "addr:postcode":"03420",
    "addr:street":"Carrer De Benlliure",
    "iso:country":"ES",
    "sg:address":"Carrer de Benlliure, 9",
    "sg:city":"Castalla",
    "sg:orig_category":"Art\u00cdculos De Pl\u00c1stico",
    "sg:phone":"+34 965 56 05 06",
    "sg:postcode":"03420",
    "sg:province":"Alicante",
    "wof:name":"Vidal Sempere Francisco Jose",
    "wof:placetype":"venue"
},
  "geometry": {"coordinates":[-0.6733350158,38.5904884338],"type":"Point"}
}