{
  "type": "Feature",
  "properties": {
    "addr:full":"Calle de San Antonio, 38 Donostia-san Sebastian Guip\u00f9zcoa 20017",
    "addr:housenumber":"38",
    "addr:postcode":"20017",
    "addr:street":"Calle De San Antonio",
    "iso:country":"ES",
    "sg:address":"Calle de San Antonio, 38",
    "sg:city":"Donostia-san Sebastian",
    "sg:orig_category":"Droguer\u00cdas (al Por Menor)",
    "sg:phone":"+34 943 39 66 84",
    "sg:postcode":"20017",
    "sg:province":"Guip\u00f9zcoa",
    "wof:name":"Azpillaga Zubillaga Carmen",
    "wof:placetype":"venue"
},
  "geometry": {"coordinates":[-1.9424868822,43.319683075],"type":"Point"}
}