{
  "type": "Feature",
  "properties": {
    "iso:country":"ES",
    "sg:address":"Calle de Real / Errege Kalea, 62",
    "sg:city":"Noain",
    "sg:orig_category":"Molduras, Junquillos, Listones Y Molduras Perforadas",
    "sg:phone":"+34 948 31 70 27",
    "sg:postcode":"31110",
    "sg:province":"Navarra",
    "wof:name":"Dominguez Garcia Nieves",
    "wof:placetype":"venue"
},
  "geometry": {"coordinates":[-1.6338239908,42.7598800659],"type":"Point"}
}