{
  "type": "Feature",
  "properties": {
    "addr:full":"Carr Valencia, 42 Camprodon Girona 17867",
    "addr:housenumber":"42",
    "addr:postcode":"17867",
    "addr:street":"Carr Valencia",
    "iso:country":"ES",
    "sg:address":"Carr Valencia, 42",
    "sg:city":"Camprodon",
    "sg:orig_category":"Inmobiliaria (agencias)",
    "sg:phone":"+34 972 13 01 21",
    "sg:postcode":"17867",
    "sg:province":"Girona",
    "wof:name":"Promocions Alta Garrotxa S.l.",
    "wof:placetype":"venue"
},
  "geometry": {"coordinates":[2.3671050072,42.3134994507],"type":"Point"}
}