{
  "type": "Feature",
  "properties": {
    "iso:country":"ES",
    "sg:address":"Poble Espanyol, S/n",
    "sg:city":"Barcelona",
    "sg:orig_category":"Ingenier\u00cda, Centros De Estudios (diversos)",
    "sg:phone":"+34 934 70 59 99",
    "sg:postcode":"08038",
    "sg:province":"Barcelona",
    "wof:name":"Pro A Solutions S.l.",
    "wof:placetype":"venue"
},
  "geometry": {"coordinates":[2.1687450409,41.3855895996],"type":"Point"}
}