{
  "type": "Feature",
  "properties": {
    "addr:full":"Calle de Real, 27 Valdepe\u00f1as Ciudad Real 13300",
    "addr:housenumber":"27",
    "addr:postcode":"13300",
    "addr:street":"Calle De Real",
    "iso:country":"ES",
    "sg:address":"Calle de Real, 27",
    "sg:city":"Valdepe\u00f1as",
    "sg:orig_category":"Ropa Para Se\u00d1oras (al Por Menor)",
    "sg:phone":"+34 926 31 24 60",
    "sg:postcode":"13300",
    "sg:province":"Ciudad Real",
    "wof:name":"Dewa De Punto S.l.",
    "wof:placetype":"venue"
},
  "geometry": {"coordinates":[-3.3830029964,38.7626152039],"type":"Point"}
}