{
  "type": "Feature",
  "properties": {
    "iso:country":"ES",
    "sg:address":"Calle de Francisco Cantera, 6",
    "sg:city":"Miranda Ebro",
    "sg:orig_category":"Ropa Para Caballeros (al Por Menor)",
    "sg:phone":"+34 947 33 26 76",
    "sg:postcode":"09200",
    "sg:province":"Burgos",
    "wof:name":"Enrique Y Javier Bravo S.l.",
    "wof:placetype":"venue"
},
  "geometry": {"coordinates":[-2.9455690384,42.6861114502],"type":"Point"}
}