{
  "type": "Feature",
  "properties": {
    "iso:country":"ES",
    "sg:address":"Plaz Espa\u00d1a, 17",
    "sg:city":"Osera De Ebro",
    "sg:orig_category":"Poller\u00cda Y Caza (al Por Menor)",
    "sg:phone":"+34 976 16 72 40",
    "sg:postcode":"50175",
    "sg:province":"Zaragoza",
    "wof:name":"Gimeno Gascon Vicente",
    "wof:placetype":"venue"
},
  "geometry": {"coordinates":[-0.5793420076,41.5365791321],"type":"Point"}
}