{
  "type": "Feature",
  "properties": {
    "addr:full":"Calle de Rodrigo Rebolledo, 14 Zaragoza Zaragoza 50002",
    "addr:housenumber":"14",
    "addr:postcode":"50002",
    "addr:street":"Calle De Rodrigo Rebolledo",
    "iso:country":"ES",
    "sg:address":"Calle de Rodrigo Rebolledo, 14",
    "sg:city":"Zaragoza",
    "sg:orig_category":"Cristaler\u00cdas",
    "sg:phone":"+34 976 42 62 26",
    "sg:postcode":"50002",
    "sg:province":"Zaragoza",
    "wof:name":"Ruiz Varas Francisco Javier",
    "wof:placetype":"venue"
},
  "geometry": {"coordinates":[-0.8645349741,41.6460571289],"type":"Point"}
}