{
  "type": "Feature",
  "properties": {
    "addr:full":"Calle de Monegros, 8 Zaragoza Zaragoza 50003",
    "addr:housenumber":"8",
    "addr:postcode":"50003",
    "addr:street":"Calle De Monegros",
    "iso:country":"ES",
    "sg:address":"Calle de Monegros, 8",
    "sg:city":"Zaragoza",
    "sg:orig_category":"Equipo De Refrigeraci\u00d3n Industrial",
    "sg:phone":"+34 976 44 38 69",
    "sg:postcode":"50003",
    "sg:province":"Zaragoza",
    "wof:name":"Manfri S.l.",
    "wof:placetype":"venue"
},
  "geometry": {"coordinates":[-0.8944326043,41.6611442566],"type":"Point"}
}