{
  "type": "Feature",
  "properties": {
    "iso:country":"ES",
    "sg:address":"Calle de Carmelo Baquero Jacoste, 4",
    "sg:city":"Tudela",
    "sg:orig_category":"Vinos Y Licores (venta Al Por Menor)",
    "sg:phone":"+34 948 82 12 63",
    "sg:postcode":"31500",
    "sg:province":"Navarra",
    "wof:name":"Perez Lahera Delfin",
    "wof:placetype":"venue"
},
  "geometry": {"coordinates":[-1.6002080441,42.0556182861],"type":"Point"}
}