{
  "type": "Feature",
  "properties": {
    "addr:full":"Ctra. Port D'alcudia, Km. 0001,0 Manacor Islas Baleares 07500",
    "addr:postcode":"07500",
    "addr:street":"Ctra. Port D'Alcudia Km. 0001,0",
    "iso:country":"ES",
    "sg:address":"Ctra. Port D'alcudia, Km. 0001,0",
    "sg:city":"Manacor",
    "sg:orig_category":"Hospitales",
    "sg:phone":"+34 971 84 70 00",
    "sg:postcode":"07500",
    "sg:province":"Islas Baleares",
    "wof:name":"Hospital De Manacor",
    "wof:placetype":"venue"
},
  "geometry": {"coordinates":[3.3331770897,39.5422592163],"type":"Point"}
}