{
  "type": "Feature",
  "properties": {
    "iso:country":"ES",
    "sg:address":"Calle de Rabida, 16",
    "sg:city":"Palos Frontera",
    "sg:orig_category":"Cajas De Ahorro",
    "sg:phone":"+34 959 65 61 56",
    "sg:postcode":"21810",
    "sg:province":"Huelva",
    "wof:name":"Unicaja",
    "wof:placetype":"venue"
},
  "geometry": {"coordinates":[-6.8939428329,37.2282295227],"type":"Point"}
}