{
  "type": "Feature",
  "properties": {
    "iso:country":"ES",
    "sg:address":"Carrer de Onze De Setembre, 2",
    "sg:city":"Alcanar",
    "sg:orig_category":"Administraci\u00d3n En Agricultura",
    "sg:phone":"+34 977 73 08 63",
    "sg:postcode":"43530",
    "sg:province":"Tarragona",
    "wof:name":"Agro-gestion Reverter S.l.",
    "wof:placetype":"venue"
},
  "geometry": {"coordinates":[0.4812492132,40.5410728455],"type":"Point"}
}