{
  "type": "Feature",
  "properties": {
    "iso:country":"ES",
    "sg:address":"Calle de Luna, 51",
    "sg:city":"Puerto De Santa Maria",
    "sg:orig_category":"Inmobiliaria (agencias)",
    "sg:phone":"+34 956 85 01 79",
    "sg:postcode":"11500",
    "sg:province":"C\u00e1diz",
    "wof:name":"Alba Regife Francisco Miguel",
    "wof:placetype":"venue"
},
  "geometry": {"coordinates":[-6.227273941,36.5993309021],"type":"Point"}
}