{
  "type": "Feature",
  "properties": {
    "addr:full":"Calle de Miguel De Cervantes, 2 Palmas De Gran Canaria Las Palmas 35002",
    "addr:housenumber":"2",
    "addr:postcode":"35002",
    "addr:street":"Calle De Miguel De Cervantes",
    "iso:country":"ES",
    "sg:address":"Calle de Miguel De Cervantes, 2",
    "sg:city":"Palmas De Gran Canaria",
    "sg:orig_category":"Ense\u00d1anza Variada",
    "sg:phone":"+34 928 36 92 11",
    "sg:postcode":"35002",
    "sg:province":"Las Palmas",
    "wof:name":"C.n.p. Espa\u00d1a S.l.",
    "wof:placetype":"venue"
},
  "geometry": {"coordinates":[-15.4138345718,28.1047153473],"type":"Point"}
}