{
  "type": "Feature",
  "properties": {
    "iso:country":"ES",
    "sg:address":"Calle de Montero Calvo, 8",
    "sg:city":"Valladolid",
    "sg:orig_category":"M\u00c9dicos: Estomatolog\u00cda",
    "sg:phone":"+34 983 35 12 02",
    "sg:postcode":"47001",
    "sg:province":"Valladolid",
    "wof:name":"Cantalapiedra Alvarez Jose Maria",
    "wof:placetype":"venue"
},
  "geometry": {"coordinates":[-4.72747612,41.6497802734],"type":"Point"}
}