{
  "type": "Feature",
  "properties": {
    "addr:full":"Calle de P, 91 Mutiloabeiti Navarra 31192",
    "addr:housenumber":"91",
    "addr:postcode":"31192",
    "addr:street":"Calle De P",
    "iso:country":"ES",
    "sg:address":"Calle de P, 91",
    "sg:city":"Mutiloabeiti",
    "sg:orig_category":"Naipes, Carteles, Artilugios",
    "sg:phone":"+34 948 23 48 85",
    "sg:postcode":"31192",
    "sg:province":"Navarra",
    "wof:name":"Dise\u00f1o Y Rotulos Lavin",
    "wof:placetype":"venue"
},
  "geometry": {"coordinates":[-1.627004981,42.7857246399],"type":"Point"}
}