{
  "type": "Feature",
  "properties": {
    "addr:full":"Calle de Juan Porcar, 15 Vall D'uixo Castell\u00f3n 12600",
    "addr:housenumber":"15",
    "addr:postcode":"12600",
    "addr:street":"Calle De Juan Porcar",
    "iso:country":"ES",
    "sg:address":"Calle de Juan Porcar, 15",
    "sg:city":"Vall D'uixo",
    "sg:classifiers":[
        {
            "category":"Taxi",
            "type":"Transportation"
        }
    ],
    "sg:phone":"+34 964 66 34 19",
    "sg:postcode":"12600",
    "sg:province":"Castell\u00f3n",
    "wof:name":"Colas Navarro Enrique",
    "wof:placetype":"venue"
},
  "geometry": {"coordinates":[-0.0482099988,39.992477417],"type":"Point"}
}