{
  "type": "Feature",
  "properties": {
    "iso:country":"ES",
    "sg:address":"Carrer de Llerona, 82",
    "sg:city":"Garriga",
    "sg:orig_category":"Autob\u00das (explotaci\u00d3n Y Servicios De)",
    "sg:phone":"+34 938 71 40 84",
    "sg:postcode":"08530",
    "sg:province":"Barcelona",
    "wof:name":"Samblas Sanchez Pedro Jose",
    "wof:placetype":"venue"
},
  "geometry": {"coordinates":[2.2854349613,41.68126297],"type":"Point"}
}