{
  "type": "Feature",
  "properties": {
    "iso:country":"ES",
    "sg:address":"Carrer de Viriat, 3",
    "sg:city":"Castelldefels",
    "sg:orig_category":"Molduras, Junquillos, Listones Y Molduras Perforadas",
    "sg:phone":"+34 936 64 51 50",
    "sg:postcode":"08860",
    "sg:province":"Barcelona",
    "wof:name":"Garcia Corcoles Alfonso",
    "wof:placetype":"venue"
},
  "geometry": {"coordinates":[1.9790869951,41.2856369019],"type":"Point"}
}