{
  "type": "Feature",
  "properties": {
    "iso:country":"ES",
    "sg:address":"Carrer de Florida (la), 38",
    "sg:city":"Cornella Llobregat",
    "sg:orig_category":"Asociaciones, Organismos Culturales Y Socioeducativos",
    "sg:phone":"+34 933 75 12 54",
    "sg:postcode":"08940",
    "sg:province":"Barcelona",
    "wof:name":"Asociacion Andaluza Hijos De Almachar",
    "wof:placetype":"venue"
},
  "geometry": {"coordinates":[2.0753722191,41.3570709229],"type":"Point"}
}