{
  "type": "Feature",
  "properties": {
    "addr:full":"Calle de Chinchon, 1 Ventorro Del Cano Madrid 28925",
    "addr:housenumber":"1",
    "addr:postcode":"28925",
    "addr:street":"Calle De Chinchon",
    "iso:country":"ES",
    "sg:address":"Calle de Chinchon, 1",
    "sg:city":"Ventorro Del Cano",
    "sg:orig_category":"Muebles, Minoristas",
    "sg:phone":"+34 916 32 10 10",
    "sg:postcode":"28925",
    "sg:province":"Madrid",
    "wof:name":"Rivel Mobihogar S.l.",
    "wof:placetype":"venue"
},
  "geometry": {"coordinates":[-3.835739851,40.393661499],"type":"Point"}
}