{
  "type": "Feature",
  "properties": {
    "addr:full":"Pl Adria, 8 Barcelona Barcelona 08021",
    "addr:housenumber":"8",
    "addr:postcode":"08021",
    "addr:street":"Pl Adria",
    "iso:country":"ES",
    "sg:address":"Pl Adria, 8",
    "sg:city":"Barcelona",
    "sg:orig_category":"Agencias Y Asesores De Publicidad",
    "sg:phone":"+34 932 01 91 03",
    "sg:postcode":"08021",
    "sg:province":"Barcelona",
    "sg:website":"www.digitalstudionet.com",
    "wof:name":"Digital Developments Studio.s.l",
    "wof:placetype":"venue"
},
  "geometry": {"coordinates":[2.1389300823,41.4012451172],"type":"Point"}
}