{
  "type": "Feature",
  "properties": {
    "iso:country":"ES",
    "sg:address":"Rua Nova, 37",
    "sg:city":"Lugo",
    "sg:orig_category":"Molduras, Junquillos, Listones Y Molduras Perforadas",
    "sg:phone":"+34 982 22 87 68",
    "sg:postcode":"27001",
    "sg:province":"Lugo",
    "wof:name":"Magdalena Carballo Jose",
    "wof:placetype":"venue"
},
  "geometry": {"coordinates":[-7.5592608452,43.0114212036],"type":"Point"}
}