{
  "type": "Feature",
  "properties": {
    "iso:country":"ES",
    "sg:address":"Calle de Arcipreste Esteban Diaz, 48",
    "sg:city":"Yecla",
    "sg:orig_category":"Electrodom\u00c9sticos (al Por Menor)",
    "sg:phone":"+34 968 75 28 32",
    "sg:postcode":"30510",
    "sg:province":"Murcia",
    "wof:name":"Vicente Diaz Pascual",
    "wof:placetype":"venue"
},
  "geometry": {"coordinates":[-1.108404994,38.6104202271],"type":"Point"}
}