{
  "type": "Feature",
  "properties": {
    "addr:full":"Avda Parque, 65 Torredonjimeno Ja\u00e9n 23650",
    "addr:housenumber":"65",
    "addr:postcode":"23650",
    "addr:street":"Avda Parque",
    "iso:country":"ES",
    "sg:address":"Avda Parque, 65",
    "sg:city":"Torredonjimeno",
    "sg:orig_category":"Transporte En General",
    "sg:phone":"+34 953 57 19 39",
    "sg:postcode":"23650",
    "sg:province":"Ja\u00e9n",
    "wof:name":"Sanchez Lopez Antonio",
    "wof:placetype":"venue"
},
  "geometry": {"coordinates":[-3.9502959251,37.7648277283],"type":"Point"}
}