{
  "type": "Feature",
  "properties": {
    "iso:country":"ES",
    "sg:address":"Ctra Manresa, 65",
    "sg:city":"Igualada",
    "sg:orig_category":"Guarder\u00cdas",
    "sg:phone":"+34 938 05 60 80",
    "sg:postcode":"08700",
    "sg:province":"Barcelona",
    "wof:name":"Grup Educatiu 0-3 S.c.p",
    "wof:placetype":"venue"
},
  "geometry": {"coordinates":[1.6169309616,41.584690094],"type":"Point"}
}