{
  "type": "Feature",
  "properties": {
    "iso:country":"ES",
    "sg:address":"Calle de Islas Britanicas, 8",
    "sg:city":"Madrid",
    "sg:orig_category":"Institutos De Belleza",
    "sg:phone":"+34 917 35 33 26",
    "sg:postcode":"28034",
    "sg:province":"Madrid",
    "wof:name":"Martinez Roa Aurora",
    "wof:placetype":"venue"
},
  "geometry": {"coordinates":[-3.6888029575,40.4937362671],"type":"Point"}
}