{
  "type": "Feature",
  "properties": {
    "iso:country":"ES",
    "sg:address":"Calle de Coronel Jimenez, 26",
    "sg:city":"Valle De Santa Ana",
    "sg:orig_category":"Charcuter\u00cdas (al Por Mayor)",
    "sg:phone":"+34 924 75 37 52",
    "sg:postcode":"06178",
    "sg:province":"Badajoz",
    "wof:name":"Embutidos Jose Guzman S.l.",
    "wof:placetype":"venue"
},
  "geometry": {"coordinates":[-6.7879757881,38.3652381897],"type":"Point"}
}