{
  "type": "Feature",
  "properties": {
    "addr:full":"Tomas Alba Kalea, 2 Astigarraga Guip\u00f9zcoa 20115",
    "addr:housenumber":"2",
    "addr:postcode":"20115",
    "addr:street":"Alba Kalea;Guipu\u0300Zcoa",
    "iso:country":"ES",
    "sg:address":"Tomas Alba Kalea, 2",
    "sg:city":"Astigarraga",
    "sg:orig_category":"Molduras, Junquillos, Listones Y Molduras Perforadas",
    "sg:phone":"+34 943 55 12 04",
    "sg:postcode":"20115",
    "sg:province":"Guip\u00f9zcoa",
    "wof:name":"Pastoriza Nieto Juan Ramon",
    "wof:placetype":"venue"
},
  "geometry": {"coordinates":[-1.9481979609,43.2814178467],"type":"Point"}
}