{
  "type": "Feature",
  "properties": {
    "iso:country":"ES",
    "sg:address":"Poli Pol.ind.belcaire, 519",
    "sg:city":"Vall D'uixo",
    "sg:orig_category":"Reparaciones Y Remolcado De Veh\u00cdculos",
    "sg:phone":"+34 964 69 68 94",
    "sg:postcode":"12600",
    "sg:province":"Castell\u00f3n",
    "wof:name":"Molina Gimenez Rafael",
    "wof:placetype":"venue"
},
  "geometry": {"coordinates":[-0.0360242017,39.9860687256],"type":"Point"}
}