{
  "type": "Feature",
  "properties": {
    "iso:country":"ES",
    "sg:address":"Calle de San Francisco, 18",
    "sg:city":"Tomelloso",
    "sg:orig_category":"Expertos Contables",
    "sg:phone":"+34 926 50 22 40",
    "sg:postcode":"13700",
    "sg:province":"Ciudad Real",
    "wof:name":"Mc Consultores Economistas S.l.",
    "wof:placetype":"venue"
},
  "geometry": {"coordinates":[-3.0255999565,39.1551361084],"type":"Point"}
}