{
  "type": "Feature",
  "properties": {
    "iso:country":"ES",
    "sg:address":"P Ind Risco Prieto, 20",
    "sg:city":"Pto. Rosario",
    "sg:orig_category":"Embalajes",
    "sg:phone":"+34 928 53 28 84",
    "sg:postcode":"35600",
    "sg:province":"Las Palmas",
    "sg:website":"www.plastpel95.com",
    "wof:name":"Plastpel 95 S.l.",
    "wof:placetype":"venue"
},
  "geometry": {"coordinates":[-13.8644685745,28.5023498535],"type":"Point"}
}