{
  "type": "Feature",
  "properties": {
    "addr:full":"Arbidea, 23 Bilbao Vizcaya 48004",
    "addr:housenumber":"23",
    "addr:postcode":"48004",
    "addr:street":"Arbidea",
    "iso:country":"ES",
    "sg:address":"Arbidea, 23",
    "sg:city":"Bilbao",
    "sg:orig_category":"Electrodom\u00c9sticos (al Por Menor)",
    "sg:phone":"+34 944 73 54 46",
    "sg:postcode":"48004",
    "sg:province":"Vizcaya",
    "wof:name":"Saez De Heredia Jayo, Beatriz",
    "wof:placetype":"venue"
},
  "geometry": {"coordinates":[-2.9097900391,43.2558097839],"type":"Point"}
}