{
  "type": "Feature",
  "properties": {
    "iso:country":"ES",
    "sg:address":"Calle de Arevalo, S/n",
    "sg:city":"Aldeanueva Del Codonal",
    "sg:orig_category":"Centros De Educaci\u00d3n Especial",
    "sg:phone":"+34 921 58 22 28",
    "sg:postcode":"40462",
    "sg:province":"Segovia",
    "wof:name":"Colegio Rural Agrupado Campos De Castilla",
    "wof:placetype":"venue"
},
  "geometry": {"coordinates":[-4.5452647209,41.0817184448],"type":"Point"}
}