{
  "type": "Feature",
  "properties": {
    "addr:full":"Carrer de Jaume Balmes, 46 Palma Islas Baleares 07004",
    "addr:housenumber":"46",
    "addr:postcode":"07004",
    "addr:street":"Carrer De Jaume Balmes",
    "iso:country":"ES",
    "sg:address":"Carrer de Jaume Balmes, 46",
    "sg:city":"Palma",
    "sg:orig_category":"Muebles Y Accesorios Para Cocinas Y Cuartos De Ba\u00d1o (al Por Menor)",
    "sg:phone":"+34 971 20 63 79",
    "sg:postcode":"07004",
    "sg:province":"Islas Baleares",
    "wof:name":"Pombo Lopez Maria Teresa",
    "wof:placetype":"venue"
},
  "geometry": {"coordinates":[2.6587309837,39.5802116394],"type":"Point"}
}