{
  "type": "Feature",
  "properties": {
    "iso:country":"ES",
    "sg:address":"Calle de Maria De Molina, 66",
    "sg:city":"Madrid",
    "sg:orig_category":"Asesor\u00cdas Y Estudios Financieros",
    "sg:phone":"+34 915 64 06 07",
    "sg:postcode":"28006",
    "sg:province":"Madrid",
    "wof:name":"Solfinan 90 S.l.",
    "wof:placetype":"venue"
},
  "geometry": {"coordinates":[-3.6781992912,40.4373435974],"type":"Point"}
}