{
  "type": "Feature",
  "properties": {
    "addr:full":"Calle de Pe\u00d1uelas, 19 Marbella M\u00e1laga 29600",
    "addr:housenumber":"19",
    "addr:postcode":"29600",
    "addr:street":"Calle De Pen\u0303Uelas;Ma\u0301Laga",
    "iso:country":"ES",
    "sg:address":"Calle de Pe\u00d1uelas, 19",
    "sg:city":"Marbella",
    "sg:classifiers":[
        {
            "category":"Autos & Motor Vehicles",
            "subcategory":"Automobile Sales",
            "type":"Retail Goods"
        }
    ],
    "sg:phone":"+34 952 90 30 40",
    "sg:postcode":"29600",
    "sg:province":"M\u00e1laga",
    "wof:name":"Merchan Rivas Jose",
    "wof:placetype":"venue"
},
  "geometry": {"coordinates":[-4.8800368309,36.5126533508],"type":"Point"}
}