{
  "type": "Feature",
  "properties": {
    "addr:full":"Calle de Zafiro, S/n Madrid Madrid 28021",
    "addr:housenumber":"/ n",
    "addr:postcode":"28021",
    "addr:street":"Calle De Zafiro S",
    "iso:country":"ES",
    "sg:address":"Calle de Zafiro, S/n",
    "sg:city":"Madrid",
    "sg:orig_category":"Transporte En General",
    "sg:phone":"+34 917 10 97 62",
    "sg:postcode":"28021",
    "sg:province":"Madrid",
    "wof:name":"Lopez Navalon Logic S.l.",
    "wof:placetype":"venue"
},
  "geometry": {"coordinates":[-3.6786255836,40.3473548889],"type":"Point"}
}