{
  "type": "Feature",
  "properties": {
    "iso:country":"ES",
    "sg:address":"Calle de Cruz, 4",
    "sg:city":"Motril",
    "sg:orig_category":"Inform\u00c1tica, Ofim\u00c1tica (estudios, Asesor\u00cda, Ingenier\u00cda, Formaci\u00d3n)",
    "sg:phone":"+34 958 60 02 89",
    "sg:postcode":"18600",
    "sg:province":"Granada",
    "wof:name":"Gonzalez Fernandez Jose Luis",
    "wof:placetype":"venue"
},
  "geometry": {"coordinates":[-3.5149691105,36.747379303],"type":"Point"}
}