{
  "type": "Feature",
  "properties": {
    "iso:country":"ES",
    "sg:address":"Ctra Montcada, 406",
    "sg:city":"Terrassa",
    "sg:orig_category":"Librer\u00cdas",
    "sg:phone":"+34 937 86 07 44",
    "sg:postcode":"08223",
    "sg:province":"Barcelona",
    "wof:name":"Prat Roca Gaspar",
    "wof:placetype":"venue"
},
  "geometry": {"coordinates":[2.0216600895,41.5576705933],"type":"Point"}
}