{
  "type": "Feature",
  "properties": {
    "iso:country":"ES",
    "sg:address":"Avda Jose Maria Fernandez, 62",
    "sg:city":"Le\u00f3n",
    "sg:orig_category":"Carnicer\u00cdas, Carnicer\u00cdas",
    "sg:phone":"+34 987 25 05 08",
    "sg:postcode":"24006",
    "sg:province":"Le\u00f3n",
    "sg:website":"www.paginasamarillas.es",
    "wof:name":"Ganados Tino S.l.",
    "wof:placetype":"venue"
},
  "geometry": {"coordinates":[-5.5598778725,42.5985298157],"type":"Point"}
}