{
  "type": "Feature",
  "properties": {
    "addr:full":"Avda Diputacion (de La), 17 Chipiona C\u00e1diz 11550",
    "addr:housenumber":"17",
    "addr:postcode":"11550",
    "addr:street":"Avda Diputacion De La",
    "iso:country":"ES",
    "sg:address":"Avda Diputacion (de La), 17",
    "sg:city":"Chipiona",
    "sg:orig_category":"Peluqueros: De Se\u00d1oras",
    "sg:phone":"+34 956 37 00 12",
    "sg:postcode":"11550",
    "sg:province":"C\u00e1diz",
    "wof:name":"Morales Giron Rosalia",
    "wof:placetype":"venue"
},
  "geometry": {"coordinates":[-6.4317889214,36.7390670776],"type":"Point"}
}