{
  "type": "Feature",
  "properties": {
    "iso:country":"ES",
    "sg:address":"Carr Major, 70",
    "sg:city":"Lleida",
    "sg:orig_category":"Lencer\u00cda Femenina, Corseter\u00cda, Trajes De Ba\u00d1o (al Por Menor)",
    "sg:phone":"+34 973 24 38 07",
    "sg:postcode":"25007",
    "sg:province":"Lleida",
    "wof:name":"Balaguero Llado Maria Rosa",
    "wof:placetype":"venue"
},
  "geometry": {"coordinates":[0.624812305,41.6134529114],"type":"Point"}
}