{
  "type": "Feature",
  "properties": {
    "iso:country":"ES",
    "sg:address":"De Malaga, 52",
    "sg:city":"Almeria",
    "sg:orig_category":"Ahumados Y Salazones",
    "sg:phone":"+34 950 23 58 96",
    "sg:postcode":"04002",
    "sg:province":"Almer\u00eda",
    "wof:name":"Restoy Campos Enrique",
    "wof:placetype":"venue"
},
  "geometry": {"coordinates":[-2.4813859463,36.8369750977],"type":"Point"}
}