{
  "type": "Feature",
  "properties": {
    "iso:country":"ES",
    "sg:address":"Calle de San Cristobal De La Laguna, 159",
    "sg:city":"Palmas De Gran Canaria",
    "sg:orig_category":"Electricidad Veh\u00cdculo",
    "sg:phone":"+34 928 31 13 73",
    "sg:postcode":"35016",
    "sg:province":"Las Palmas",
    "wof:name":"Tejera Medina Antonio Domingo",
    "wof:placetype":"venue"
},
  "geometry": {"coordinates":[-15.4299783707,28.0679779053],"type":"Point"}
}