{
  "type": "Feature",
  "properties": {
    "addr:full":"Avda Reyes Catolicos, 64 Cuenca Cuenca 16003",
    "addr:housenumber":"64",
    "addr:postcode":"16003",
    "addr:street":"Avda Reyes Catolicos",
    "iso:country":"ES",
    "sg:address":"Avda Reyes Catolicos, 64",
    "sg:city":"Cuenca",
    "sg:orig_category":"Ropa Para Ni\u00d1os (al Por Menor)",
    "sg:phone":"+34 969 22 10 78",
    "sg:postcode":"16003",
    "sg:province":"Cuenca",
    "wof:name":"Gomez Ramal Enrique",
    "wof:placetype":"venue"
},
  "geometry": {"coordinates":[-2.1383440495,40.0598716736],"type":"Point"}
}