{
  "type": "Feature",
  "properties": {
    "iso:country":"ES",
    "sg:address":"Carrer de Creu, 64",
    "sg:city":"S. Just Desvern",
    "sg:orig_category":"Empresas De Portes Y Mensajer\u00cda",
    "sg:phone":"+34 933 72 26 54",
    "sg:postcode":"08960",
    "sg:province":"Barcelona",
    "wof:name":"Alpec S.a.",
    "wof:placetype":"venue"
},
  "geometry": {"coordinates":[2.0757772923,41.3822631836],"type":"Point"}
}