{
  "type": "Feature",
  "properties": {
    "addr:full":"Carrer de Sant Pere, 23 S. Andreu Llavaneres Barcelona 08392",
    "addr:housenumber":"23",
    "addr:postcode":"08392",
    "addr:street":"Carrer De Sant Pere;S. Andreu Llavaneres Barcelona",
    "iso:country":"ES",
    "sg:address":"Carrer de Sant Pere, 23",
    "sg:city":"S. Andreu Llavaneres",
    "sg:orig_category":"Ense\u00d1anza: Profesiones Art\u00cdsticas",
    "sg:phone":"+34 937 93 02 93",
    "sg:postcode":"08392",
    "sg:province":"Barcelona",
    "wof:name":"Castro Gonzalez Jose Antonio",
    "wof:placetype":"venue"
},
  "geometry": {"coordinates":[2.4981720448,41.5575714111],"type":"Point"}
}