{
  "type": "Feature",
  "properties": {
    "addr:full":"Carrer de Llan\u00c7a, 31 Barcelona Barcelona 08015",
    "addr:housenumber":"31",
    "addr:postcode":"08015",
    "addr:street":"Carrer De Llanc\u0327A",
    "iso:country":"ES",
    "sg:address":"Carrer de Llan\u00c7a, 31",
    "sg:city":"Barcelona",
    "sg:orig_category":"Arquitectos",
    "sg:phone":"+34 932 26 48 93",
    "sg:postcode":"08015",
    "sg:province":"Barcelona",
    "wof:name":"Pastor Gonzalez Jose Ramon",
    "wof:placetype":"venue"
},
  "geometry": {"coordinates":[2.1463289261,41.3792572021],"type":"Point"}
}