{
  "type": "Feature",
  "properties": {
    "iso:country":"ES",
    "sg:address":"Av Prat De La Riba, 82",
    "sg:city":"Palleja",
    "sg:orig_category":"Guarder\u00cdas",
    "sg:phone":"+34 936 63 12 92",
    "sg:postcode":"08780",
    "sg:province":"Barcelona",
    "wof:name":"Salvado Sanchez Eva",
    "wof:placetype":"venue"
},
  "geometry": {"coordinates":[1.9977689981,41.4192848206],"type":"Point"}
}