{
  "type": "Feature",
  "properties": {
    "addr:full":"Calle de Sisones, 3 Pinto Madrid 28320",
    "addr:housenumber":"3",
    "addr:postcode":"28320",
    "addr:street":"Calle De Sisones;Pinto",
    "iso:country":"ES",
    "sg:address":"Calle de Sisones, 3",
    "sg:city":"Pinto",
    "sg:orig_category":"Fabricaci\u00d3n De Moldes Y Modelos",
    "sg:phone":"+34 916 91 19 11",
    "sg:postcode":"28320",
    "sg:province":"Madrid",
    "wof:name":"Martos Utillaje S.a.",
    "wof:placetype":"venue"
},
  "geometry": {"coordinates":[-3.7151401043,40.2482948303],"type":"Point"}
}