{
  "type": "Feature",
  "properties": {
    "iso:country":"ES",
    "sg:address":"Barr Sierrapando, 508",
    "sg:city":"Sierrapando",
    "sg:orig_category":"Asociaciones Humanitarias, De Cooperaci\u00d3n, De Acci\u00d3n Social",
    "sg:phone":"+34 942 89 52 09",
    "sg:postcode":"39317",
    "sg:province":"Cantabria",
    "wof:name":"Asociacion Amica",
    "wof:placetype":"venue"
},
  "geometry": {"coordinates":[-4.0345673561,43.3432006836],"type":"Point"}
}