{
  "type": "Feature",
  "properties": {
    "iso:country":"ES",
    "sg:address":"Creu, 10",
    "sg:city":"Tremp",
    "sg:orig_category":"Pensiones Familiares",
    "sg:phone":"+34 973 65 02 91",
    "sg:postcode":"25620",
    "sg:province":"Lleida",
    "wof:name":"Gay Santandreu Ramiro",
    "wof:placetype":"venue"
},
  "geometry": {"coordinates":[0.8969029784,42.167049408],"type":"Point"}
}