{
  "type": "Feature",
  "properties": {
    "addr:full":"Calle de Muro De Santiago, 73 Alca\u00f1iz Teruel 44600",
    "addr:housenumber":"73",
    "addr:postcode":"44600",
    "addr:street":"Calle De Muro De Santiago",
    "iso:country":"ES",
    "sg:address":"Calle de Muro De Santiago, 73",
    "sg:city":"Alca\u00f1iz",
    "sg:orig_category":"Aceites Y Grasas Alimentarias (fabricaci\u00d3n, Al Por Mayor)",
    "sg:phone":"+34 978 83 06 09",
    "sg:postcode":"44600",
    "sg:province":"Teruel",
    "wof:name":"Gaibar Hermanos S.l.",
    "wof:placetype":"venue"
},
  "geometry": {"coordinates":[-0.1349489987,41.0489807129],"type":"Point"}
}