{
  "type": "Feature",
  "properties": {
    "addr:full":"Ctra Aldealengua, Km. 0003,2 Cabrerizos Salamanca 37193",
    "addr:postcode":"37193",
    "addr:street":"Ctra Aldealengua Km. 0003,2",
    "iso:country":"ES",
    "sg:address":"Ctra Aldealengua, Km. 0003,2",
    "sg:city":"Cabrerizos",
    "sg:orig_category":"Transportes Por V\u00cdas Navegables",
    "sg:phone":"+34 923 18 46 16",
    "sg:postcode":"37193",
    "sg:province":"Salamanca",
    "wof:name":"L.m. Cabrerizos S.l.",
    "wof:placetype":"venue"
},
  "geometry": {"coordinates":[-5.6213741302,40.9721908569],"type":"Point"}
}