{
  "type": "Feature",
  "properties": {
    "iso:country":"ES",
    "sg:address":"Carr Pirroig, 8",
    "sg:city":"Calella",
    "sg:orig_category":"Supermercados Y Hipermercados",
    "sg:phone":"+34 972 61 58 60",
    "sg:postcode":"17210",
    "sg:province":"Girona",
    "wof:name":"Supermercats Els Forcats S.l.",
    "wof:placetype":"venue"
},
  "geometry": {"coordinates":[3.1854450703,41.8891067505],"type":"Point"}
}