{
  "type": "Feature",
  "properties": {
    "addr:full":"Calle de Padre Salvador Barri, 2 Onda Castell\u00f3n 12200",
    "addr:housenumber":"2",
    "addr:postcode":"12200",
    "addr:street":"Calle De Padre Salvador Barri;Castello\u0301N",
    "iso:country":"ES",
    "sg:address":"Calle de Padre Salvador Barri, 2",
    "sg:city":"Onda",
    "sg:orig_category":"Inmobiliaria (agencias)",
    "sg:phone":"+34 964 60 00 17",
    "sg:postcode":"12200",
    "sg:province":"Castell\u00f3n",
    "wof:name":"Asesoria Inmobiliaria Pepe Ramos",
    "wof:placetype":"venue"
},
  "geometry": {"coordinates":[-0.2640514076,39.9629135132],"type":"Point"}
}