{
  "type": "Feature",
  "properties": {
    "addr:full":"Avda Andalucia, 31 Barbate C\u00e1diz 11160",
    "addr:housenumber":"31",
    "addr:postcode":"11160",
    "addr:street":"Avda Andalucia",
    "iso:country":"ES",
    "sg:address":"Avda Andalucia, 31",
    "sg:city":"Barbate",
    "sg:orig_category":"Empresas De Portes Y Mensajer\u00cda",
    "sg:phone":"+34 956 43 39 37",
    "sg:postcode":"11160",
    "sg:province":"C\u00e1diz",
    "wof:name":"Garcia Lopez Juan",
    "wof:placetype":"venue"
},
  "geometry": {"coordinates":[-5.9230971336,36.1918563843],"type":"Point"}
}