{
  "type": "Feature",
  "properties": {
    "addr:full":"Rua Alcalde Maillata, 27 Olite Navarra 31390",
    "addr:housenumber":"27",
    "addr:postcode":"31390",
    "addr:street":"Rua Alcalde Maillata",
    "iso:country":"ES",
    "sg:address":"Rua Alcalde Maillata, 27",
    "sg:city":"Olite",
    "sg:orig_category":"Empresas De Carpinter\u00cda Met\u00c1lica",
    "sg:phone":"+34 948 74 01 34",
    "sg:postcode":"31390",
    "sg:province":"Navarra",
    "wof:name":"Talleres Olite S. C. L.",
    "wof:placetype":"venue"
},
  "geometry": {"coordinates":[-1.6522450447,42.4808883667],"type":"Point"}
}