{
  "type": "Feature",
  "properties": {
    "iso:country":"ES",
    "sg:address":"Calle de Marcos Trujillo, 11",
    "sg:city":"Antigua",
    "sg:orig_category":"Asociaciones, Organismos Culturales Y Socioeducativos",
    "sg:phone":"+34 928 87 81 06",
    "sg:postcode":"35630",
    "sg:province":"Las Palmas",
    "wof:name":"Fundacion Colectivo Mafasca",
    "wof:placetype":"venue"
},
  "geometry": {"coordinates":[-14.0143194199,28.4225292206],"type":"Point"}
}