{
  "type": "Feature",
  "properties": {
    "addr:full":"Polig El Carmen, S/n Revilla Cantabria 39600",
    "addr:housenumber":"s / n",
    "addr:postcode":"39600",
    "addr:street":"Polig El Carmen",
    "iso:country":"ES",
    "sg:address":"Polig El Carmen, S/n",
    "sg:city":"Revilla",
    "sg:orig_category":"Chapister\u00cda",
    "sg:phone":"+34 942 25 90 96",
    "sg:postcode":"39600",
    "sg:province":"Cantabria",
    "wof:name":"Carrocerias Hemanos Moja S.l.",
    "wof:placetype":"venue"
},
  "geometry": {"coordinates":[-3.8458189964,43.4184341431],"type":"Point"}
}