{
  "type": "Feature",
  "properties": {
    "iso:country":"ES",
    "sg:address":"Avda Aragon, 6",
    "sg:city":"Valencia",
    "sg:orig_category":"Distribuci\u00d3n De Petr\u00d3leo Y Derivados",
    "sg:phone":"+34 963 37 02 27",
    "sg:postcode":"46021",
    "sg:province":"Valencia",
    "wof:name":"Gebe S. L.",
    "wof:placetype":"venue"
},
  "geometry": {"coordinates":[-0.3596560061,39.4688034058],"type":"Point"}
}