{
  "type": "Feature",
  "properties": {
    "iso:country":"ES",
    "sg:address":"Calle de Romeria, 7",
    "sg:city":"Ajalvir",
    "sg:orig_category":"Maquinaria Para Industrias Diversas",
    "sg:phone":"+34 918 87 46 00",
    "sg:postcode":"28864",
    "sg:province":"Madrid",
    "sg:website":"www.deal-ll.com",
    "wof:name":"Deal Ii S.l.",
    "wof:placetype":"venue"
},
  "geometry": {"coordinates":[-3.4809999466,40.5031166077],"type":"Point"}
}