{
  "type": "Feature",
  "properties": {
    "addr:full":"Avda Ambrosio De Los Heros, 50 Carreras Vizcaya 48540",
    "addr:housenumber":"50",
    "addr:postcode":"48540",
    "addr:street":"Avda Ambrosio De Los Heros",
    "iso:country":"ES",
    "sg:address":"Avda Ambrosio De Los Heros, 50",
    "sg:city":"Carreras",
    "sg:orig_category":"Quincaller\u00cda (al Por Menor)",
    "sg:phone":"+34 946 36 85 28",
    "sg:postcode":"48540",
    "sg:province":"Vizcaya",
    "wof:name":"Angulo Azpiolea Lourdes",
    "wof:placetype":"venue"
},
  "geometry": {"coordinates":[-3.0960626602,43.3186416626],"type":"Point"}
}