{
  "type": "Feature",
  "properties": {
    "addr:full":"Calle de Botas, 5 Palmas De Gran Canaria Las Palmas 35001",
    "addr:housenumber":"5",
    "addr:postcode":"35001",
    "addr:street":"Calle De Botas",
    "iso:country":"ES",
    "sg:address":"Calle de Botas, 5",
    "sg:city":"Palmas De Gran Canaria",
    "sg:orig_category":"Asociaciones, Organismos Culturales Y Socioeducativos",
    "sg:phone":"+34 928 31 99 46",
    "sg:postcode":"35001",
    "sg:province":"Las Palmas",
    "wof:name":"Asociacion Cultural Guiniguada Comunicacion",
    "wof:placetype":"venue"
},
  "geometry": {"coordinates":[-15.4129972458,28.1022129059],"type":"Point"}
}