{
  "type": "Feature",
  "properties": {
    "addr:full":"Carrer de Sant Joan De Malta, 17 Barcelona Barcelona 08018",
    "addr:housenumber":"17",
    "addr:postcode":"08018",
    "addr:street":"Carrer De Sant Joan De Malta",
    "iso:country":"ES",
    "sg:address":"Carrer de Sant Joan De Malta, 17",
    "sg:city":"Barcelona",
    "sg:orig_category":"Empresas De Carpinter\u00cda De Madera",
    "sg:phone":"+34 933 07 55 46",
    "sg:postcode":"08018",
    "sg:province":"Barcelona",
    "wof:name":"Esplugas Calveras Jorge",
    "wof:placetype":"venue"
},
  "geometry": {"coordinates":[2.1914141178,41.4098701477],"type":"Point"}
}