{
  "type": "Feature",
  "properties": {
    "iso:country":"ES",
    "sg:address":"Avda Doctor Artero, 19",
    "sg:city":"Huesca",
    "sg:orig_category":"Escayola Y Productos De Escayola (fabricaci\u00d3n, Al Por Mayor)",
    "sg:phone":"+34 974 24 13 73",
    "sg:postcode":"22004",
    "sg:province":"Huesca",
    "wof:name":"Savicente Lailla Fidel",
    "wof:placetype":"venue"
},
  "geometry": {"coordinates":[-0.4152109921,42.1439437866],"type":"Point"}
}