{
  "type": "Feature",
  "properties": {
    "iso:country":"ES",
    "sg:address":"Avda Italia, 45",
    "sg:city":"Huelva",
    "sg:orig_category":"Peluqueros: De Se\u00d1oras",
    "sg:phone":"+34 959 26 02 90",
    "sg:postcode":"21001",
    "sg:province":"Huelva",
    "wof:name":"Capilla Perez Josefa",
    "wof:placetype":"venue"
},
  "geometry": {"coordinates":[-6.952562809,37.254196167],"type":"Point"}
}