{
  "type": "Feature",
  "properties": {
    "iso:country":"ES",
    "sg:address":"Calle de Castelar, 36",
    "sg:city":"Villafranqueza - Palamo",
    "sg:orig_category":"Piedra Natural",
    "sg:phone":"+34 965 18 20 52",
    "sg:postcode":"03112",
    "sg:province":"Alicante",
    "wof:name":"Raco Del Fardacho S.l.",
    "wof:placetype":"venue"
},
  "geometry": {"coordinates":[-0.4918991923,38.3855476379],"type":"Point"}
}