{
  "type": "Feature",
  "properties": {
    "iso:country":"ES",
    "sg:address":"Calle de Fruela, 2",
    "sg:city":"Aviles",
    "sg:orig_category":"Producci\u00d3n, Distribuci\u00d3n De Electricidad",
    "sg:phone":"+34 985 54 72 19",
    "sg:postcode":"33402",
    "sg:province":"Asturias",
    "wof:name":"Arjona Aguilera Manuel",
    "wof:placetype":"venue"
},
  "geometry": {"coordinates":[-5.9170942307,43.5487709045],"type":"Point"}
}