{
  "type": "Feature",
  "properties": {
    "iso:country":"ES",
    "sg:address":"Calle de Bobalar, 6",
    "sg:city":"Rafelbunyol",
    "sg:orig_category":"Alimentaci\u00d3n General (al Por Menor)",
    "sg:phone":"+34 961 41 03 67",
    "sg:postcode":"46138",
    "sg:province":"Valencia",
    "wof:name":"Calatayud Rodrigo Miguel",
    "wof:placetype":"venue"
},
  "geometry": {"coordinates":[-0.3382818997,39.5885887146],"type":"Point"}
}