{
  "type": "Feature",
  "properties": {
    "iso:country":"ES",
    "sg:address":"Carrer de Guitard, 71",
    "sg:city":"Barcelona",
    "sg:orig_category":"Financiaci\u00d3n Y Cr\u00c9ditos",
    "sg:phone":"+34 934 90 63 51",
    "sg:postcode":"08014",
    "sg:province":"Barcelona",
    "wof:name":"Mayoral Busto Ruth",
    "wof:placetype":"venue"
},
  "geometry": {"coordinates":[2.1362800598,41.3840637207],"type":"Point"}
}