{
  "type": "Feature",
  "properties": {
    "addr:full":"Avda Reina Mercedes, 13 Sevilla Sevilla 41012",
    "addr:housenumber":"13",
    "addr:postcode":"41012",
    "addr:street":"Avda Reina Mercedes",
    "iso:country":"ES",
    "sg:address":"Avda Reina Mercedes, 13",
    "sg:city":"Sevilla",
    "sg:orig_category":"Fotocopias, Reprograf\u00cda",
    "sg:phone":"+34 954 62 59 01",
    "sg:postcode":"41012",
    "sg:province":"Sevilla",
    "wof:name":"Dominguez Moreno Manuel",
    "wof:placetype":"venue"
},
  "geometry": {"coordinates":[-5.9858951569,37.3625221252],"type":"Point"}
}