{
  "type": "Feature",
  "properties": {
    "iso:country":"ES",
    "sg:address":"Calle de Teniente Hernandez Menor, 4",
    "sg:city":"Villena",
    "sg:orig_category":"Medias Y Calcetines (al Por Menor)",
    "sg:phone":"+34 965 80 12 88",
    "sg:postcode":"03400",
    "sg:province":"Alicante",
    "wof:name":"Garcia Ruiz Ramon",
    "wof:placetype":"venue"
},
  "geometry": {"coordinates":[-0.8697490096,38.6433677673],"type":"Point"}
}