{
  "type": "Feature",
  "properties": {
    "iso:country":"ES",
    "sg:address":"Avda Pinar (del), 86",
    "sg:city":"Collado Mediano",
    "sg:orig_category":"Asesor\u00cda, Estudio Y Control Medioambiental",
    "sg:phone":"+34 918 59 86 02",
    "sg:postcode":"28450",
    "sg:province":"Madrid",
    "wof:name":"Yefira Alfa S.l.",
    "wof:placetype":"venue"
},
  "geometry": {"coordinates":[-4.0334568024,40.6956367493],"type":"Point"}
}