{
  "type": "Feature",
  "properties": {
    "iso:country":"ES",
    "sg:address":"Carrer de Bergueda, 141",
    "sg:city":"Sabadell",
    "sg:orig_category":"Agencias Y Agentes Comerciales, Representantes",
    "sg:phone":"+34 937 17 06 43",
    "sg:postcode":"08207",
    "sg:province":"Barcelona",
    "wof:name":"Martinez Rodes Gloria",
    "wof:placetype":"venue"
},
  "geometry": {"coordinates":[2.0892701149,41.56772995],"type":"Point"}
}