{
  "type": "Feature",
  "properties": {
    "iso:country":"ES",
    "sg:address":"Avda Reyes Catolicos, 15",
    "sg:city":"Albolote",
    "sg:orig_category":"Producci\u00d3n De Abonos Y De Fertilizantes",
    "sg:phone":"+34 958 46 61 23",
    "sg:postcode":"18220",
    "sg:province":"Granada",
    "wof:name":"Titos Baena Marta",
    "wof:placetype":"venue"
},
  "geometry": {"coordinates":[-3.6582610607,37.227809906],"type":"Point"}
}