{
  "type": "Feature",
  "properties": {
    "iso:country":"ES",
    "sg:address":"Carrer de Anselm Clave, 6",
    "sg:city":"S. Boi Llobregat",
    "sg:orig_category":"Guarder\u00cdas",
    "sg:phone":"+34 936 54 27 89",
    "sg:postcode":"08830",
    "sg:province":"Barcelona",
    "wof:name":"El Reco Dels Menuts Huertas S.l.",
    "wof:placetype":"venue"
},
  "geometry": {"coordinates":[2.0384790897,41.345123291],"type":"Point"}
}