{
  "type": "Feature",
  "properties": {
    "iso:country":"ES",
    "sg:address":"Afores, S/n",
    "sg:city":"Cornudella Montsant",
    "sg:orig_category":"Productores Recolectores, Venta Directa De Vinos",
    "sg:phone":"+34 977 82 11 04",
    "sg:postcode":"43360",
    "sg:province":"Tarragona",
    "wof:name":"Ronadellas S.l.",
    "wof:placetype":"venue"
},
  "geometry": {"coordinates":[0.9047899842,41.2646980286],"type":"Point"}
}