{
  "type": "Feature",
  "properties": {
    "iso:country":"ES",
    "sg:address":"Pl Catalunya, 27",
    "sg:city":"Prat Llobregat",
    "sg:orig_category":"Partidos Pol\u00cdticos",
    "sg:phone":"+34 933 79 29 08",
    "sg:postcode":"08820",
    "sg:province":"Barcelona",
    "wof:name":"Partit Socialista Unificat De Catalunya",
    "wof:placetype":"venue"
},
  "geometry": {"coordinates":[2.0929160118,41.3235435486],"type":"Point"}
}