{
  "type": "Feature",
  "properties": {
    "addr:full":"Calle de Santa Clara, 16 Zamora Zamora 49014",
    "addr:housenumber":"16",
    "addr:postcode":"49014",
    "addr:street":"Calle De Santa Clara",
    "iso:country":"ES",
    "sg:address":"Calle de Santa Clara, 16",
    "sg:city":"Zamora",
    "sg:orig_category":"Abogados",
    "sg:phone":"+34 980 51 69 63",
    "sg:postcode":"49014",
    "sg:province":"Zamora",
    "wof:name":"Martin Anero Miguel Angel",
    "wof:placetype":"venue"
},
  "geometry": {"coordinates":[-5.7428541183,41.5057525635],"type":"Point"}
}