{
  "type": "Feature",
  "properties": {
    "addr:full":"Carrer de Sombrerers, 23 Barcelona Barcelona 08003",
    "addr:housenumber":"23",
    "addr:postcode":"08003",
    "addr:street":"Carrer De Sombrerers",
    "iso:country":"ES",
    "sg:address":"Carrer de Sombrerers, 23",
    "sg:city":"Barcelona",
    "sg:orig_category":"Frutas Y Legumbres Secas (al Por Mayor)",
    "sg:phone":"+34 933 19 71 71",
    "sg:postcode":"08003",
    "sg:province":"Barcelona",
    "sg:website":"www.casagispert.com",
    "wof:name":"E. Y A. Gispert S.l.",
    "wof:placetype":"venue"
},
  "geometry": {"coordinates":[2.1819119453,41.3840866089],"type":"Point"}
}