{
  "type": "Feature",
  "properties": {
    "iso:country":"ES",
    "sg:address":"Avda Andalucia (de), 203",
    "sg:city":"Padul",
    "sg:orig_category":"Reposter\u00cdas",
    "sg:phone":"+34 958 79 60 42",
    "sg:postcode":"18640",
    "sg:province":"Granada",
    "wof:name":"Fernandez Santiago Juan",
    "wof:placetype":"venue"
},
  "geometry": {"coordinates":[-3.6161088943,37.023021698],"type":"Point"}
}