{
  "type": "Feature",
  "properties": {
    "addr:full":"Carr Bassegoda, 22 Girona Girona 17006",
    "addr:housenumber":"22",
    "addr:postcode":"17006",
    "addr:street":"Carr Bassegoda",
    "iso:country":"ES",
    "sg:address":"Carr Bassegoda, 22",
    "sg:city":"Girona",
    "sg:orig_category":"Extinci\u00d3n De Incendios: Material Y Suministros (fabricaci\u00d3n, Al Por Mayor)",
    "sg:phone":"+34 972 40 18 98",
    "sg:postcode":"17006",
    "sg:province":"Girona",
    "wof:name":"Esta\u00f1ol Fabregas Emerio",
    "wof:placetype":"venue"
},
  "geometry": {"coordinates":[2.8048648834,41.9756965637],"type":"Point"}
}