{
  "type": "Feature",
  "properties": {
    "iso:country":"ES",
    "sg:address":"Calle de Doctor Gomez Ulla, 24",
    "sg:city":"Madrid",
    "sg:orig_category":"M\u00c9dicos: Radioterapia (radioterapia Como Opci\u00d3n Oncol\u00d3gica)",
    "sg:phone":"+34 913 55 64 73",
    "sg:postcode":"28028",
    "sg:province":"Madrid",
    "wof:name":"Casanova Morcillo Antonio",
    "wof:placetype":"venue"
},
  "geometry": {"coordinates":[-3.6671173573,40.4311180115],"type":"Point"}
}