{
  "type": "Feature",
  "properties": {
    "addr:full":"Carrer de Joan Mompeo, 30 Terrassa Barcelona 08...",
    "addr:housenumber":"30",
    "addr:street":"Carrer De Joan Mompeo",
    "iso:country":"ES",
    "sg:address":"Carrer de Joan Mompeo, 30",
    "sg:city":"Terrassa",
    "sg:orig_category":"Hilaturas, Hilos Y Actividades Relacionadas",
    "sg:phone":"+34 937 36 63 00",
    "sg:postcode":"08...",
    "sg:province":"Barcelona",
    "wof:name":"S.a. Hilados Egarfil",
    "wof:placetype":"venue"
},
  "geometry": {"coordinates":[2.0095911026,41.5549163818],"type":"Point"}
}