{
  "type": "Feature",
  "properties": {
    "addr:full":"Psaj Conde Alcala, 3 Granada Granada 18001",
    "addr:housenumber":"3",
    "addr:postcode":"18001",
    "addr:street":"Conde Alcala",
    "iso:country":"ES",
    "sg:address":"Psaj Conde Alcala, 3",
    "sg:city":"Granada",
    "sg:orig_category":"Bisuter\u00cda, Joyer\u00cda, Relojer\u00cda (al Por Menor)",
    "sg:phone":"+34 958 26 32 43",
    "sg:postcode":"18001",
    "sg:province":"Granada",
    "wof:name":"Torres Pereira Trinidad",
    "wof:placetype":"venue"
},
  "geometry": {"coordinates":[-3.6011009216,37.1749191284],"type":"Point"}
}