{
  "type": "Feature",
  "properties": {
    "iso:country":"ES",
    "sg:address":"Carles Riba, 4",
    "sg:city":"Tarragona",
    "sg:orig_category":"Marketing Telef\u00d3nico",
    "sg:phone":"+34 977 29 14 30",
    "sg:postcode":"43007",
    "sg:province":"Tarragona",
    "wof:name":"Mc Estrategia Sl",
    "wof:placetype":"venue"
},
  "geometry": {"coordinates":[1.272963047,41.1217918396],"type":"Point"}
}