{
  "type": "Feature",
  "properties": {
    "iso:country":"ES",
    "sg:address":"Av Advocat Fausto Caruana, 26",
    "sg:city":"Puerto Sagunto",
    "sg:orig_category":"Empresarios",
    "sg:phone":"+34 962 68 28 37",
    "sg:postcode":"46520",
    "sg:province":"Valencia",
    "wof:name":"Forem P.v.",
    "wof:placetype":"venue"
},
  "geometry": {"coordinates":[-0.242385,39.6702423096],"type":"Point"}
}