{
  "type": "Feature",
  "properties": {
    "iso:country":"ES",
    "sg:address":"Av Garona, S/n",
    "sg:city":"Vielha",
    "sg:orig_category":"Deportes Y Programas De Aventura",
    "sg:phone":"+34 973 64 12 99",
    "sg:postcode":"25530",
    "sg:province":"Lleida",
    "wof:name":"Monturiol Andinyach Gerard",
    "wof:placetype":"venue"
},
  "geometry": {"coordinates":[0.7996150255,42.7018203735],"type":"Point"}
}