{
  "type": "Feature",
  "properties": {
    "addr:full":"Carrer de Mestre Jesus Orti, 3 Prat Llobregat Barcelona 08820",
    "addr:housenumber":"3",
    "addr:postcode":"08820",
    "addr:street":"Carrer De Mestre Jesus Orti;Llobregat",
    "iso:country":"ES",
    "sg:address":"Carrer de Mestre Jesus Orti, 3",
    "sg:city":"Prat Llobregat",
    "sg:orig_category":"Alimentaci\u00d3n General (al Por Menor)",
    "sg:phone":"+34 933 70 73 54",
    "sg:postcode":"08820",
    "sg:province":"Barcelona",
    "wof:name":"Masclans Pascual Jose",
    "wof:placetype":"venue"
},
  "geometry": {"coordinates":[2.0944399834,41.3343048096],"type":"Point"}
}