{
  "type": "Feature",
  "properties": {
    "iso:country":"ES",
    "sg:address":"Av Isidor Macabich, 52",
    "sg:city":"Eivissa",
    "sg:orig_category":"Inmobiliaria (agencias)",
    "sg:phone":"+34 971 31 61 71",
    "sg:postcode":"07800",
    "sg:province":"Islas Baleares",
    "sg:website":"www.ctv.es/users/fincasarnau",
    "wof:name":"Fincas Arnau S.l.",
    "wof:placetype":"venue"
},
  "geometry": {"coordinates":[1.425377965,38.9099464417],"type":"Point"}
}