{
  "type": "Feature",
  "properties": {
    "addr:full":"Calle de Francisco Elipe, 7 Manzanares Ciudad Real 13200",
    "addr:housenumber":"7",
    "addr:postcode":"13200",
    "addr:street":"Calle De Francisco Elipe",
    "iso:country":"ES",
    "sg:address":"Calle de Francisco Elipe, 7",
    "sg:city":"Manzanares",
    "sg:orig_category":"Centros De Educaci\u00d3n Especial",
    "sg:phone":"+34 926 61 00 47",
    "sg:postcode":"13200",
    "sg:province":"Ciudad Real",
    "wof:name":"Colegio Nacional La Candelaria",
    "wof:placetype":"venue"
},
  "geometry": {"coordinates":[-3.3638689518,38.9953956604],"type":"Point"}
}