{
  "type": "Feature",
  "properties": {
    "iso:country":"ES",
    "sg:address":"Calle de Claudio Moyano, 24",
    "sg:city":"Valladolid",
    "sg:orig_category":"Cajas De Ahorro",
    "sg:phone":"+34 983 37 40 27",
    "sg:postcode":"47001",
    "sg:province":"Valladolid",
    "sg:website":"www.cajabadajoz.es",
    "wof:name":"Caja De Badajoz",
    "wof:placetype":"venue"
},
  "geometry": {"coordinates":[-4.7271718979,41.6489562988],"type":"Point"}
}