{
  "type": "Feature",
  "properties": {
    "addr:full":"Calle de Enmedio, 13 Artziniega \u00c1lava 01474",
    "addr:housenumber":"13",
    "addr:postcode":"01474",
    "addr:street":"Calle De Enmedio;A\u0301Lava",
    "iso:country":"ES",
    "sg:address":"Calle de Enmedio, 13",
    "sg:city":"Artziniega",
    "sg:orig_category":"Promotores Constructores",
    "sg:phone":"+34 945 39 60 26",
    "sg:postcode":"01474",
    "sg:province":"\u00c1lava",
    "wof:name":"Veulsa S.a.",
    "wof:placetype":"venue"
},
  "geometry": {"coordinates":[-3.1285500526,43.1209335327],"type":"Point"}
}