{
  "type": "Feature",
  "properties": {
    "addr:full":"Ctra Madrid, Km. 0303,0 Ba\u00d1eza Le\u00f3n 24750",
    "addr:postcode":"24750",
    "addr:street":"Ctra Madrid Km. 0303,0 Ban\u0303Eza Leo\u0301N",
    "iso:country":"ES",
    "sg:address":"Ctra Madrid, Km. 0303,0",
    "sg:city":"Ba\u00d1eza",
    "sg:orig_category":"Material Y Herramientas Agr\u00cdcolas",
    "sg:phone":"+34 987 64 01 79",
    "sg:postcode":"24750",
    "sg:province":"Le\u00f3n",
    "wof:name":"Talleres Pagra S.l.",
    "wof:placetype":"venue"
},
  "geometry": {"coordinates":[-5.9242091179,42.3069114685],"type":"Point"}
}