{
  "type": "Feature",
  "properties": {
    "iso:country":"ES",
    "sg:address":"Carrer de Pere Berruguete, 2",
    "sg:city":"Esplugues Llobregat",
    "sg:orig_category":"Peluqueros: De Se\u00d1oras",
    "sg:phone":"+34 933 72 01 60",
    "sg:postcode":"08950",
    "sg:province":"Barcelona",
    "wof:name":"Poveda Diaz Dolores",
    "wof:placetype":"venue"
},
  "geometry": {"coordinates":[2.0896139145,41.3872375488],"type":"Point"}
}