{
  "type": "Feature",
  "properties": {
    "addr:full":"Calle de Don Crescencio Somoza, 17 Barraco \u00c1vila 05110",
    "addr:housenumber":"17",
    "addr:postcode":"05110",
    "addr:street":"Calle De Don Crescencio Somoza",
    "iso:country":"ES",
    "sg:address":"Calle de Don Crescencio Somoza, 17",
    "sg:city":"Barraco",
    "sg:orig_category":"Electricidad: Instaladores",
    "sg:phone":"+34 920 28 10 33",
    "sg:postcode":"05110",
    "sg:province":"\u00c1vila",
    "wof:name":"Sanchez Jimenez Roman",
    "wof:placetype":"venue"
},
  "geometry": {"coordinates":[-4.6434679031,40.4789466858],"type":"Point"}
}