{
  "type": "Feature",
  "properties": {
    "addr:full":"Calle de Manuel Garcia Atance, 8 Sig\u00fcenza Guadalajara 19250",
    "addr:housenumber":"8",
    "addr:postcode":"19250",
    "addr:street":"Calle De Manuel Garcia Atance",
    "iso:country":"ES",
    "sg:address":"Calle de Manuel Garcia Atance, 8",
    "sg:city":"Sig\u00fcenza",
    "sg:orig_category":"Peluqueros: De Se\u00d1oras",
    "sg:phone":"+34 949 39 31 57",
    "sg:postcode":"19250",
    "sg:province":"Guadalajara",
    "wof:name":"Peluqueria Y Belleza Llorente S.l.",
    "wof:placetype":"venue"
},
  "geometry": {"coordinates":[-2.6425030231,41.0681800842],"type":"Point"}
}