{
  "type": "Feature",
  "properties": {
    "iso:country":"ES",
    "sg:address":"Avda Sevilla (de), 36",
    "sg:city":"Castilleja Cuesta",
    "sg:orig_category":"Art\u00cdculos De Madera (fabricaci\u00d3n Y Al Por Mayor)",
    "sg:phone":"+34 954 16 50 88",
    "sg:postcode":"41950",
    "sg:province":"Sevilla",
    "wof:name":"Ramirez Izquierdo Francisco",
    "wof:placetype":"venue"
},
  "geometry": {"coordinates":[-6.063313961,37.3849067688],"type":"Point"}
}