{
  "type": "Feature",
  "properties": {
    "iso:country":"ES",
    "sg:address":"Calle de Francisco Bethencourt, 16",
    "sg:city":"Palmas De Gran Canaria",
    "sg:orig_category":"Desinfecci\u00d3n, Desinsectaci\u00d3n, Desratizaci\u00d3n",
    "sg:phone":"+34 928 33 23 46",
    "sg:postcode":"35016",
    "sg:province":"Las Palmas",
    "sg:website":"www.floresalud.com",
    "wof:name":"Vega Santana Jose Manuel",
    "wof:placetype":"venue"
},
  "geometry": {"coordinates":[-15.4188814163,28.0808238983],"type":"Point"}
}