{
  "type": "Feature",
  "properties": {
    "iso:country":"ES",
    "sg:address":"Santo Sepulcro, 46",
    "sg:city":"Huercal-overa",
    "sg:orig_category":"Sociedades, Compa\u00d1\u00cdas Aseguradoras",
    "sg:phone":"+34 950 13 40 08",
    "sg:postcode":"04600",
    "sg:province":"Almer\u00eda",
    "wof:name":"Ocaso S.a.compa\u00f1ia De Seguros Y Reaseguros",
    "wof:placetype":"venue"
},
  "geometry": {"coordinates":[-1.9443229437,37.3903312683],"type":"Point"}
}