{
  "type": "Feature",
  "properties": {
    "iso:country":"ES",
    "sg:address":"Calle de Constitucion, 19",
    "sg:city":"Valdepe\u00f1as",
    "sg:classifiers":[
        {
            "category":"Banks & Credit Unions",
            "subcategory":"Bureau De Change",
            "type":"Services"
        }
    ],
    "sg:phone":"+34 926 32 27 88",
    "sg:postcode":"13300",
    "sg:province":"Ciudad Real",
    "sg:tags":[
        "organismos",
        "control"
    ],
    "wof:name":"Consejo Regulador De La Denominacion De Origen Valdepe\u00f1as",
    "wof:placetype":"venue"
},
  "geometry": {"coordinates":[-3.3905100822,38.7604370117],"type":"Point"}
}