{
  "type": "Feature",
  "properties": {
    "iso:country":"ES",
    "sg:address":"Pla\u00c7 Farners, 8",
    "sg:city":"Santa Coloma De Farners",
    "sg:orig_category":"Asesor\u00cda Sobre Comunicaci\u00d3n De Empresas",
    "sg:phone":"+34 972 84 35 60",
    "sg:postcode":"17430",
    "sg:province":"Girona",
    "wof:name":"Linea Dofill S.l.",
    "wof:placetype":"venue"
},
  "geometry": {"coordinates":[2.6626069546,41.8636894226],"type":"Point"}
}