{
  "type": "Feature",
  "properties": {
    "addr:full":"C/ Porta D'alacant, 10 Elche Alicante 03202",
    "addr:housenumber":"10",
    "addr:postcode":"03202",
    "addr:street":"C / Porta D'Alacant",
    "iso:country":"ES",
    "sg:address":"C/ Porta D'alacant, 10",
    "sg:city":"Elche",
    "sg:orig_category":"Reposter\u00cdas",
    "sg:phone":"+34 965 45 76 63",
    "sg:postcode":"03202",
    "sg:province":"Alicante",
    "wof:name":"Gonzalvez Belso Antonio",
    "wof:placetype":"venue"
},
  "geometry": {"coordinates":[-0.6948779821,38.2676506042],"type":"Point"}
}