{
  "type": "Feature",
  "properties": {
    "addr:full":"Carrer de Gran De Gracia, 101 Barcelona Barcelona 08012",
    "addr:housenumber":"101",
    "addr:postcode":"08012",
    "addr:street":"Carrer De Gran De Gracia",
    "iso:country":"ES",
    "sg:address":"Carrer de Gran De Gracia, 101",
    "sg:city":"Barcelona",
    "sg:orig_category":"Centros Comerciales Y Grandes Tiendas",
    "sg:phone":"+34 932 37 64 26",
    "sg:postcode":"08012",
    "sg:province":"Barcelona",
    "wof:name":"Etcetera Cien S.l.",
    "wof:placetype":"venue"
},
  "geometry": {"coordinates":[2.1538829803,41.4010047913],"type":"Point"}
}