{
  "type": "Feature",
  "properties": {
    "addr:full":"Calle de Ortega Y Gasset, 22 Elda Alicante 03600",
    "addr:housenumber":"22",
    "addr:postcode":"03600",
    "addr:street":"Calle De Ortega Y Gasset",
    "iso:country":"ES",
    "sg:address":"Calle de Ortega Y Gasset, 22",
    "sg:city":"Elda",
    "sg:orig_category":"Complementos De Vestir (al Por Menor)",
    "sg:phone":"+34 965 39 42 30",
    "sg:postcode":"03600",
    "sg:province":"Alicante",
    "wof:name":"Oliva Villaplana Lorena",
    "wof:placetype":"venue"
},
  "geometry": {"coordinates":[-0.7947430015,38.4785385132],"type":"Point"}
}