{
  "type": "Feature",
  "properties": {
    "addr:full":"Calle de Cervantes, 12 Malaga M\u00e1laga 29016",
    "addr:housenumber":"12",
    "addr:postcode":"29016",
    "addr:street":"Calle De Cervantes;Ma\u0301Laga",
    "iso:country":"ES",
    "sg:address":"Calle de Cervantes, 12",
    "sg:city":"Malaga",
    "sg:orig_category":"Peluqueros: De Se\u00d1oras",
    "sg:phone":"+34 952 21 64 97",
    "sg:postcode":"29016",
    "sg:province":"M\u00e1laga",
    "wof:name":"Orsi Rodriguez Juan Antonio",
    "wof:placetype":"venue"
},
  "geometry": {"coordinates":[-4.4100103378,36.7191963196],"type":"Point"}
}