{
  "type": "Feature",
  "properties": {
    "addr:full":"Plaz San Julian, 1 San Pedro Murcia 30004",
    "addr:housenumber":"1",
    "addr:postcode":"30004",
    "addr:street":"Plaz San Julian",
    "iso:country":"ES",
    "sg:address":"Plaz San Julian, 1",
    "sg:city":"San Pedro",
    "sg:orig_category":"Farmacias",
    "sg:phone":"+34 968 21 83 29",
    "sg:postcode":"30004",
    "sg:province":"Murcia",
    "wof:name":"Pe\u00f1alver Martinez Josefa",
    "wof:placetype":"venue"
},
  "geometry": {"coordinates":[-1.1302499771,37.9829597473],"type":"Point"}
}