{
  "type": "Feature",
  "properties": {
    "iso:country":"ES",
    "sg:address":"C/ Rentadors, 6",
    "sg:city":"Inca",
    "sg:orig_category":"Ense\u00d1anza Variada",
    "sg:phone":"+34 971 50 73 71",
    "sg:postcode":"07300",
    "sg:province":"Islas Baleares",
    "wof:name":"Centre Profesional De Formacio Publica S.l.",
    "wof:placetype":"venue"
},
  "geometry": {"coordinates":[2.9208989143,39.7179527283],"type":"Point"}
}