{
  "type": "Feature",
  "properties": {
    "iso:country":"ES",
    "sg:address":"Poli Industrial Alces, 55",
    "sg:city":"Alcazar S. Juan",
    "sg:orig_category":"Embalajes",
    "sg:phone":"+34 926 55 29 70",
    "sg:postcode":"13600",
    "sg:province":"Ciudad Real",
    "sg:website":"www.embalajestyd.com",
    "wof:name":"Embalajes T Y D S.l.",
    "wof:placetype":"venue"
},
  "geometry": {"coordinates":[-3.210203886,39.3900718689],"type":"Point"}
}