{
  "type": "Feature",
  "properties": {
    "iso:country":"ES",
    "sg:address":"Carrer de Miralta, 19",
    "sg:city":"Hospitalet Llobregat",
    "sg:orig_category":"Instalaci\u00d3n De Aspiraci\u00d3n De Gases Y Humos",
    "sg:phone":"+34 932 60 04 34",
    "sg:postcode":"08906",
    "sg:province":"Barcelona",
    "wof:name":"Gesco Serveis Bcn S.l.",
    "wof:placetype":"venue"
},
  "geometry": {"coordinates":[2.0887351036,41.3657455444],"type":"Point"}
}