{
  "type": "Feature",
  "properties": {
    "addr:full":"Calle de Retor, 40 Valencia Valencia 46006",
    "addr:housenumber":"40",
    "addr:postcode":"46006",
    "addr:street":"Calle De Retor",
    "iso:country":"ES",
    "sg:address":"Calle de Retor, 40",
    "sg:city":"Valencia",
    "sg:orig_category":"Artes Gr\u00c1ficas, Artes Pl\u00c1sticas (curso)",
    "sg:phone":"+34 963 74 01 59",
    "sg:postcode":"46006",
    "sg:province":"Valencia",
    "wof:name":"Graficas Rumar S.l.",
    "wof:placetype":"venue"
},
  "geometry": {"coordinates":[-0.366851002,39.4584732056],"type":"Point"}
}