{
  "type": "Feature",
  "properties": {
    "addr:full":"Pierre Lhande Kalea, 7 Akartegi Guip\u00f9zcoa 20280",
    "addr:housenumber":"7",
    "addr:postcode":"20280",
    "addr:street":"Pierre Lhande Kalea;Guipu\u0300Zcoa",
    "iso:country":"ES",
    "sg:address":"Pierre Lhande Kalea, 7",
    "sg:city":"Akartegi",
    "sg:orig_category":"Dom\u00d3tica",
    "sg:phone":"+34 943 64 34 55",
    "sg:postcode":"20280",
    "sg:province":"Guip\u00f9zcoa",
    "wof:name":"Sakai Yof S.l.",
    "wof:placetype":"venue"
},
  "geometry": {"coordinates":[-1.7936140299,43.3698997498],"type":"Point"}
}