{
  "type": "Feature",
  "properties": {
    "iso:country":"ES",
    "sg:address":"Av Sant Joan De Deu, 100",
    "sg:city":"Playa De Calafell",
    "sg:orig_category":"Inmobiliaria (agencias)",
    "sg:phone":"+34 977 69 24 94",
    "sg:postcode":"43820",
    "sg:province":"Tarragona",
    "wof:name":"Fincas M.suau S.l.",
    "wof:placetype":"venue"
},
  "geometry": {"coordinates":[1.5765160322,41.1873626709],"type":"Point"}
}