{
  "type": "Feature",
  "properties": {
    "iso:country":"ES",
    "sg:address":"Carr Costa I Llobera, De, 42",
    "sg:city":"Campos",
    "sg:orig_category":"Alquiler De V\u00cddeo",
    "sg:phone":"+34 971 65 27 58",
    "sg:postcode":"07630",
    "sg:province":"Islas Baleares",
    "wof:name":"Videos Sa Corredor",
    "wof:placetype":"venue"
},
  "geometry": {"coordinates":[3.0168209076,39.4346046448],"type":"Point"}
}