{
  "type": "Feature",
  "properties": {
    "addr:full":"Carrer de Alcala De Guadaira, 15 Barcelona Barcelona 08020",
    "addr:housenumber":"15",
    "addr:postcode":"08020",
    "addr:street":"Carrer De Alcala;Guadaira",
    "iso:country":"ES",
    "sg:address":"Carrer de Alcala De Guadaira, 15",
    "sg:city":"Barcelona",
    "sg:orig_category":"Guarder\u00cdas",
    "sg:phone":"+34 933 03 11 29",
    "sg:postcode":"08020",
    "sg:province":"Barcelona",
    "wof:name":"La Vila Del Pingui S.c.p.",
    "wof:placetype":"venue"
},
  "geometry": {"coordinates":[2.1963338852,41.4175338745],"type":"Point"}
}