{
  "type": "Feature",
  "properties": {
    "iso:country":"ES",
    "sg:address":"Calle de Iriarte, 21",
    "sg:city":"Madrid",
    "sg:orig_category":"Sindicatos De Trabajadores",
    "sg:phone":"+34 917 13 11 30",
    "sg:postcode":"28028",
    "sg:province":"Madrid",
    "wof:name":"Federacion Provincial De Comercio De Valladolid Ugt",
    "wof:placetype":"venue"
},
  "geometry": {"coordinates":[-3.6718120575,40.4370384216],"type":"Point"}
}