{
  "type": "Feature",
  "properties": {
    "addr:full":"Carretera Cuellar, S/n Cantalejo Segovia 40320",
    "addr:postcode":"40320",
    "addr:street":"Carretera Cuellar S / N Cantalejo Segovia",
    "iso:country":"ES",
    "sg:address":"Carretera Cuellar, S/n",
    "sg:city":"Cantalejo",
    "sg:orig_category":"Muebles, Minoristas",
    "sg:phone":"+34 921 52 20 70",
    "sg:postcode":"40320",
    "sg:province":"Segovia",
    "wof:name":"Alamo San German Antonio",
    "wof:placetype":"venue"
},
  "geometry": {"coordinates":[-3.9334578514,41.2621078491],"type":"Point"}
}