{
  "type": "Feature",
  "properties": {
    "addr:full":"Carrer de Biscaia, 358 Barcelona Barcelona 08027",
    "addr:housenumber":"358",
    "addr:postcode":"08027",
    "addr:street":"Carrer De Biscaia",
    "iso:country":"ES",
    "sg:address":"Carrer de Biscaia, 358",
    "sg:city":"Barcelona",
    "sg:orig_category":"Agentes, Concesionarios Y Sucursales De Veh\u00cdculos",
    "sg:phone":"+34 933 49 16 26",
    "sg:postcode":"08027",
    "sg:province":"Barcelona",
    "wof:name":"Barcinauto S.a.",
    "wof:placetype":"venue"
},
  "geometry": {"coordinates":[2.1887729168,41.4157943726],"type":"Point"}
}