{
  "type": "Feature",
  "properties": {
    "iso:country":"ES",
    "sg:address":"Carr Sant Miquel, 29",
    "sg:city":"Verdu",
    "sg:orig_category":"Transportes Por Carretera: Lotes Completos, Mercanc\u00cdas Diversas",
    "sg:phone":"+34 973 34 70 56",
    "sg:postcode":"25340",
    "sg:province":"Lleida",
    "wof:name":"Tapies Molins Victor",
    "wof:placetype":"venue"
},
  "geometry": {"coordinates":[1.1402699947,41.6114234924],"type":"Point"}
}