{
  "type": "Feature",
  "properties": {
    "addr:full":"Calle de Esperanza, 6 Gijon Asturias 33211",
    "addr:housenumber":"6",
    "addr:postcode":"33211",
    "addr:street":"Calle De Esperanza",
    "iso:country":"ES",
    "sg:address":"Calle de Esperanza, 6",
    "sg:city":"Gijon",
    "sg:orig_category":"Mensajer\u00cda Express, Portes Internacionales",
    "sg:phone":"+34 985 32 05 92",
    "sg:postcode":"33211",
    "sg:province":"Asturias",
    "wof:name":"Transportes Galastur S. L.",
    "wof:placetype":"venue"
},
  "geometry": {"coordinates":[-5.6966810226,43.5317077637],"type":"Point"}
}