{
  "type": "Feature",
  "properties": {
    "addr:full":"Calle de Abadia (de La), S/n Calaceite Teruel 44610",
    "addr:postcode":"44610",
    "addr:street":"Calle De Abadia De La S / N",
    "iso:country":"ES",
    "sg:address":"Calle de Abadia (de La), S/n",
    "sg:city":"Calaceite",
    "sg:orig_category":"Iglesia Cat\u00d3lica",
    "sg:phone":"+34 978 85 10 89",
    "sg:postcode":"44610",
    "sg:province":"Teruel",
    "wof:name":"Parroquia Nuestra Se\u00f1ora De La Asuncion",
    "wof:placetype":"venue"
},
  "geometry": {"coordinates":[0.1878219992,41.0171775818],"type":"Point"}
}