{
  "type": "Feature",
  "properties": {
    "addr:full":"C/ Gabriel De Tarrega, S/n Tarrega Lleida 25300",
    "addr:housenumber":"s / n",
    "addr:postcode":"25300",
    "addr:street":"C / Gabriel De Tarrega",
    "iso:country":"ES",
    "sg:address":"C/ Gabriel De Tarrega, S/n",
    "sg:city":"Tarrega",
    "sg:orig_category":"Centros De Educaci\u00d3n Especial",
    "sg:phone":"+34 973 31 07 00",
    "sg:postcode":"25300",
    "sg:province":"Lleida",
    "wof:name":"Ajuntament De Tarrega",
    "wof:placetype":"venue"
},
  "geometry": {"coordinates":[1.1401239634,41.6534156799],"type":"Point"}
}