{
  "type": "Feature",
  "properties": {
    "iso:country":"ES",
    "sg:address":"Avda. Constitucion, 35",
    "sg:city":"Caba\u00d1aquinta",
    "sg:classifiers":[
        {
            "category":"Recreation",
            "type":"Entertainment"
        }
    ],
    "sg:phone":"+34 985 49 51 00",
    "sg:postcode":"33686",
    "sg:province":"Asturias",
    "sg:tags":[
        "caza",
        "pr\u00c1ctica",
        "la",
        "de",
        "pesca",
        "y"
    ],
    "wof:name":"Asociacion De Cazadores El Rebeco",
    "wof:placetype":"venue"
},
  "geometry": {"coordinates":[-5.6252326965,43.1623306274],"type":"Point"}
}