{
  "type": "Feature",
  "properties": {
    "addr:full":"Parc Bit, S/n Son Sardina Islas Baleares 07120",
    "addr:housenumber":"s / n",
    "addr:postcode":"07120",
    "addr:street":"Bit",
    "iso:country":"ES",
    "sg:address":"Parc Bit, S/n",
    "sg:city":"Son Sardina",
    "sg:orig_category":"Asesor\u00cda De Comercio Exterior",
    "sg:phone":"+34 971 71 61 64",
    "sg:postcode":"07120",
    "sg:province":"Islas Baleares",
    "wof:name":"Io Consultores S.l.",
    "wof:placetype":"venue"
},
  "geometry": {"coordinates":[2.655944109,39.6189918518],"type":"Point"}
}