{
  "type": "Feature",
  "properties": {
    "addr:full":"Calle de Fernando El Santo, 24 Madrid Madrid 28010",
    "addr:housenumber":"24",
    "addr:postcode":"madrid;28010",
    "addr:street":"Calle De Fernando El Santo",
    "iso:country":"ES",
    "sg:address":"Calle de Fernando El Santo, 24",
    "sg:city":"Madrid",
    "sg:orig_category":"Inmobiliaria (agencias)",
    "sg:phone":"+34 913 10 01 61",
    "sg:postcode":"28010",
    "sg:province":"Madrid",
    "wof:name":"Ganima S.l.",
    "wof:placetype":"venue"
},
  "geometry": {"coordinates":[-3.6906549931,40.4280395508],"type":"Point"}
}