{
  "type": "Feature",
  "properties": {
    "iso:country":"ES",
    "sg:address":"Carrer de Baluard, 46",
    "sg:city":"Barcelona",
    "sg:orig_category":"Loter\u00cda Y T\u00d3mbola",
    "sg:phone":"+34 932 21 42 67",
    "sg:postcode":"08003",
    "sg:province":"Barcelona",
    "wof:name":"Jordi Ferran Maria Victoria",
    "wof:placetype":"venue"
},
  "geometry": {"coordinates":[2.1890540123,41.3796882629],"type":"Point"}
}