{
  "type": "Feature",
  "properties": {
    "iso:country":"ES",
    "sg:address":"Calle de Doctor Fleming, 14",
    "sg:city":"Bembibre",
    "sg:classifiers":[
        {
            "category":"Personal",
            "subcategory":"Barber",
            "type":"Services"
        }
    ],
    "sg:phone":"+34 987 51 00 95",
    "sg:postcode":"24300",
    "sg:province":"Le\u00f3n",
    "sg:tags":[
        "caballeros",
        "de",
        "peluqueros"
    ],
    "wof:name":"Balin Sanchez Jose Antonio",
    "wof:placetype":"venue"
},
  "geometry": {"coordinates":[-6.4170603752,42.6162605286],"type":"Point"}
}