{
  "type": "Feature",
  "properties": {
    "addr:full":"Calle de 28 De Febrero, 99 Berja Almer\u00eda 04760",
    "addr:housenumber":"28;99",
    "addr:postcode":"04760",
    "addr:street":"Calle De;De Febrero",
    "iso:country":"ES",
    "sg:address":"Calle de 28 De Febrero, 99",
    "sg:city":"Berja",
    "sg:orig_category":"Empresas De Pintura Y Revestimientos",
    "sg:phone":"+34 950 49 22 43",
    "sg:postcode":"04760",
    "sg:province":"Almer\u00eda",
    "wof:name":"Cruz Vicente Jose",
    "wof:placetype":"venue"
},
  "geometry": {"coordinates":[-2.9477388859,36.8420829773],"type":"Point"}
}