{
  "type": "Feature",
  "properties": {
    "addr:full":"Avda Zumalacarregui, 97 Bilbao Vizcaya 48007",
    "addr:housenumber":"97",
    "addr:postcode":"48007",
    "addr:street":"Avda Zumalacarregui",
    "iso:country":"ES",
    "sg:address":"Avda Zumalacarregui, 97",
    "sg:city":"Bilbao",
    "sg:orig_category":"Agentes, Concesionarios Y Sucursales De Veh\u00cdculos",
    "sg:phone":"+34 944 46 54 06",
    "sg:postcode":"48007",
    "sg:province":"Vizcaya",
    "wof:name":"Lorenzo Rubio Cesar",
    "wof:placetype":"venue"
},
  "geometry": {"coordinates":[-2.9148991108,43.2612380981],"type":"Point"}
}