{
  "type": "Feature",
  "properties": {
    "addr:full":"Calle de Entre Arroyos, 33 Madrid Madrid 28030",
    "addr:housenumber":"33",
    "addr:postcode":"madrid;28030",
    "addr:street":"Calle De Entre Arroyos",
    "iso:country":"ES",
    "sg:address":"Calle de Entre Arroyos, 33",
    "sg:city":"Madrid",
    "sg:orig_category":"Inform\u00c1tica, Ofim\u00c1tica (estudios, Asesor\u00cda, Ingenier\u00cda, Formaci\u00d3n)",
    "sg:phone":"+34 913 28 30 41",
    "sg:postcode":"28030",
    "sg:province":"Madrid",
    "wof:name":"Informatica Socket 7 S.l.",
    "wof:placetype":"venue"
},
  "geometry": {"coordinates":[-3.6537370682,40.4076499939],"type":"Point"}
}