{
  "type": "Feature",
  "properties": {
    "addr:full":"Calle de Alvaro De Bazan, 8 Valencia Valencia 46010",
    "addr:housenumber":"8",
    "addr:postcode":"46010",
    "addr:street":"Calle De Alvaro De Bazan",
    "iso:country":"ES",
    "sg:address":"Calle de Alvaro De Bazan, 8",
    "sg:city":"Valencia",
    "sg:orig_category":"Ense\u00d1anza: Idiomas",
    "sg:phone":"+34 963 60 20 07",
    "sg:postcode":"46010",
    "sg:province":"Valencia",
    "sg:website":"www.campuslenguaje.com",
    "wof:name":"Campus Lenguajes S.l.",
    "wof:placetype":"venue"
},
  "geometry": {"coordinates":[-0.3632392883,39.4812812805],"type":"Point"}
}