{
  "type": "Feature",
  "properties": {
    "addr:full":"Calle de Pablo Picasso, 1 Puente-genil C\u00f3rdoba 14500",
    "addr:housenumber":"1",
    "addr:postcode":"14500",
    "addr:street":"Calle De Pablo Picasso;Co\u0301Rdoba",
    "iso:country":"ES",
    "sg:address":"Calle de Pablo Picasso, 1",
    "sg:city":"Puente-genil",
    "sg:orig_category":"Supermercados Y Hipermercados",
    "sg:phone":"+34 957 60 42 07",
    "sg:postcode":"14500",
    "sg:province":"C\u00f3rdoba",
    "sg:website":"www.mercadona.es",
    "wof:name":"Mercadona S.a.",
    "wof:placetype":"venue"
},
  "geometry": {"coordinates":[-4.7641181946,37.3927116394],"type":"Point"}
}