{
  "type": "Feature",
  "properties": {
    "iso:country":"ES",
    "sg:address":"Pase Ni\u00d1o, 8",
    "sg:city":"Torrelavega",
    "sg:orig_category":"Comisarios",
    "sg:phone":"+34 942 80 48 48",
    "sg:postcode":"39300",
    "sg:province":"Cantabria",
    "wof:name":"Burgos Garcia Pablo Jose",
    "wof:placetype":"venue"
},
  "geometry": {"coordinates":[-4.0520391464,43.34897995],"type":"Point"}
}