{
  "type": "Feature",
  "properties": {
    "addr:full":"Calle de Marques De La Valdavia (del), 19 Alcobendas Madrid 28100",
    "addr:postcode":"28100",
    "addr:street":"Calle De Marques De La Valdavia Del;Alcobendas",
    "iso:country":"ES",
    "sg:address":"Calle de Marques De La Valdavia (del), 19",
    "sg:city":"Alcobendas",
    "sg:orig_category":"Tapicer\u00cdas",
    "sg:phone":"+34 916 61 53 17",
    "sg:postcode":"28100",
    "sg:province":"Madrid",
    "wof:name":"Tapicerias Lali",
    "wof:placetype":"venue"
},
  "geometry": {"coordinates":[-3.636916399,40.5408287048],"type":"Point"}
}