{
  "type": "Feature",
  "properties": {
    "iso:country":"ES",
    "sg:address":"Carrer de Angel Guimera, 23",
    "sg:city":"Sitges",
    "sg:orig_category":"Herboristas (al Por Menor)",
    "sg:phone":"+34 938 94 25 74",
    "sg:postcode":"08870",
    "sg:province":"Barcelona",
    "wof:name":"Dharani S.c.p.",
    "wof:placetype":"venue"
},
  "geometry": {"coordinates":[1.8149280548,41.2404136658],"type":"Point"}
}