{
  "type": "Feature",
  "properties": {
    "addr:full":"Calle de Carretera De Marchamalo, 1 Guadalajara Guadalajara 19004",
    "addr:housenumber":"1",
    "addr:postcode":"19004",
    "addr:street":"Calle De Carretera De Marchamalo",
    "iso:country":"ES",
    "sg:address":"Calle de Carretera De Marchamalo, 1",
    "sg:city":"Guadalajara",
    "sg:orig_category":"Empresas De Carpinter\u00cda",
    "sg:phone":"+34 949 21 16 39",
    "sg:postcode":"19004",
    "sg:province":"Guadalajara",
    "wof:name":"Metalcarria S.l.l.",
    "wof:placetype":"venue"
},
  "geometry": {"coordinates":[-3.181432724,40.6457748413],"type":"Point"}
}