{
  "type": "Feature",
  "properties": {
    "addr:full":"Calle de Juan Xxiii, 1 Fuente Alamo Murcia 30320",
    "addr:housenumber":"1",
    "addr:postcode":"30320",
    "addr:street":"Calle De Juan Xxiii",
    "iso:country":"ES",
    "sg:address":"Calle de Juan Xxiii, 1",
    "sg:city":"Fuente Alamo",
    "sg:orig_category":"Cr\u00cda De Animales",
    "sg:phone":"+34 968 59 79 29",
    "sg:postcode":"30320",
    "sg:province":"Murcia",
    "wof:name":"Serrano Montesinos Maria Dolores",
    "wof:placetype":"venue"
},
  "geometry": {"coordinates":[-1.1715250015,37.7228851318],"type":"Point"}
}