{
  "type": "Feature",
  "properties": {
    "iso:country":"ES",
    "sg:address":"Calle de Baleares (playa De Las Americas), S/n",
    "sg:city":"Torviscas Centro",
    "sg:orig_category":"Inmobiliaria (agencias)",
    "sg:phone":"+34 922 71 71 71",
    "sg:postcode":"38660",
    "sg:province":"Santa Cruz De Tenerife",
    "wof:name":"Tene-bau Construcciones S.l.",
    "wof:placetype":"venue"
},
  "geometry": {"coordinates":[-16.7213382721,28.0858097076],"type":"Point"}
}