{
  "type": "Feature",
  "properties": {
    "iso:country":"ES",
    "sg:address":"Calle de Luis Gomez, 3",
    "sg:city":"Madrid",
    "sg:orig_category":"Mec\u00c1nico Del Autom\u00d3vil",
    "sg:phone":"+34 914 72 12 50",
    "sg:postcode":"28025",
    "sg:province":"Madrid",
    "wof:name":"Ramirez Ortiz Emeterio",
    "wof:placetype":"venue"
},
  "geometry": {"coordinates":[-3.7298650742,40.3866691589],"type":"Point"}
}