{
  "type": "Feature",
  "properties": {
    "addr:full":"Av Libertad(b Progreso), 5 Murcia Murcia 30012",
    "addr:housenumber":"5",
    "addr:postcode":"30012",
    "addr:street":"Av Libertad B Progreso",
    "iso:country":"ES",
    "sg:address":"Av Libertad(b Progreso), 5",
    "sg:city":"Murcia",
    "sg:orig_category":"Comercio De Piezas De Recambio Y De Accesorios De Veh\u00cdculos, Veh\u00cdculos Industriales",
    "sg:phone":"+34 968 26 53 44",
    "sg:postcode":"30012",
    "sg:province":"Murcia",
    "wof:name":"Auto Recambios Anju S.l.",
    "wof:placetype":"venue"
},
  "geometry": {"coordinates":[-1.1212837696,37.9646835327],"type":"Point"}
}