{
  "type": "Feature",
  "properties": {
    "addr:full":"Emilio Arrieta, 4 Iru\u00f1a Navarra 31002",
    "addr:housenumber":"4",
    "addr:postcode":"31002",
    "addr:street":"Emilio Arrieta",
    "iso:country":"ES",
    "sg:address":"Emilio Arrieta, 4",
    "sg:city":"Iru\u00f1a",
    "sg:orig_category":"Organizaciones Internacionales",
    "sg:phone":"+34 948 22 59 66",
    "sg:postcode":"31002",
    "sg:province":"Navarra",
    "wof:name":"Hirugarren Mundua Ta Bakea-paz Y Tercer",
    "wof:placetype":"venue"
},
  "geometry": {"coordinates":[-1.6401439905,42.8146514893],"type":"Point"}
}