{
  "type": "Feature",
  "properties": {
    "addr:full":"Calle de Juan Ramon Jimenez, 3 Gines Sevilla 41960",
    "addr:housenumber":"3",
    "addr:postcode":"41960",
    "addr:street":"Calle De Juan Ramon Jimenez;Sevilla",
    "iso:country":"ES",
    "sg:address":"Calle de Juan Ramon Jimenez, 3",
    "sg:city":"Gines",
    "sg:orig_category":"Inmobiliaria (agencias)",
    "sg:phone":"+34 954 71 70 31",
    "sg:postcode":"41960",
    "sg:province":"Sevilla",
    "wof:name":"Juan Miguel Bejar Ramos S.l.",
    "wof:placetype":"venue"
},
  "geometry": {"coordinates":[-6.0655641556,37.3857498169],"type":"Point"}
}