{
  "type": "Feature",
  "properties": {
    "addr:full":"Calle de Cemento, 2 Arganda Madrid 28500",
    "addr:housenumber":"2",
    "addr:postcode":"28500",
    "addr:street":"Calle De Cemento",
    "iso:country":"ES",
    "sg:address":"Calle de Cemento, 2",
    "sg:city":"Arganda",
    "sg:orig_category":"Delegados, Agentes De Tr\u00c1nsito, Auxiliares De Transporte Internacional",
    "sg:phone":"+34 918 71 81 30",
    "sg:postcode":"28500",
    "sg:province":"Madrid",
    "wof:name":"Transportes Duarte S.a.",
    "wof:placetype":"venue"
},
  "geometry": {"coordinates":[-3.4576039314,40.3024368286],"type":"Point"}
}