{
  "type": "Feature",
  "properties": {
    "iso:country":"ES",
    "sg:address":"Carr Marques Del Turia, 107",
    "sg:city":"Benetusser",
    "sg:orig_category":"Peluqueros: De Se\u00d1oras",
    "sg:phone":"+34 963 96 02 41",
    "sg:postcode":"46910",
    "sg:province":"Valencia",
    "wof:name":"M.m. Y G. S.l.",
    "wof:placetype":"venue"
},
  "geometry": {"coordinates":[-0.3989410102,39.4183807373],"type":"Point"}
}