{
  "type": "Feature",
  "properties": {
    "iso:country":"ES",
    "sg:address":"Ctra. General, 30",
    "sg:city":"Lieres",
    "sg:orig_category":"Panader\u00cdas, Panader\u00cdas",
    "sg:phone":"+34 985 73 07 27",
    "sg:postcode":"33580",
    "sg:province":"Asturias",
    "wof:name":"Rodriguez Garcia Alfredo",
    "wof:placetype":"venue"
},
  "geometry": {"coordinates":[-5.5893321037,43.3640708923],"type":"Point"}
}