{
  "type": "Feature",
  "properties": {
    "iso:country":"ES",
    "sg:address":"C/ Blai Vila, 33",
    "sg:city":"Paterna",
    "sg:orig_category":"Freidur\u00cdas: Equipos Y Suministros",
    "sg:phone":"+34 961 38 79 04",
    "sg:postcode":"46980",
    "sg:province":"Valencia",
    "wof:name":"Fritos Montaner Sociedad Coop Valenciana",
    "wof:placetype":"venue"
},
  "geometry": {"coordinates":[-0.4466800094,39.5038948059],"type":"Point"}
}