{
  "type": "Feature",
  "properties": {
    "iso:country":"ES",
    "sg:address":"Rond Levante, 34",
    "sg:city":"Vista Alegre",
    "sg:orig_category":"Molduras, Junquillos, Listones Y Molduras Perforadas",
    "sg:phone":"+34 968 23 80 47",
    "sg:postcode":"30008",
    "sg:province":"Murcia",
    "wof:name":"Sistelcom-telemensaje S.a.",
    "wof:placetype":"venue"
},
  "geometry": {"coordinates":[-1.1267689466,37.9918785095],"type":"Point"}
}