{
  "type": "Feature",
  "properties": {
    "iso:country":"ES",
    "sg:address":"Calle de Erkuden, 5",
    "sg:city":"Alsasua",
    "sg:orig_category":"Empresas De Portes Y Mensajer\u00cda",
    "sg:phone":"+34 948 56 35 50",
    "sg:postcode":"31800",
    "sg:province":"Navarra",
    "wof:name":"Nuntius-celer S.l.",
    "wof:placetype":"venue"
},
  "geometry": {"coordinates":[-2.1735498905,42.89427948],"type":"Point"}
}