{
  "type": "Feature",
  "properties": {
    "addr:full":"Pg Francesc Macia, 4 Cambrils Tarragona 43850",
    "addr:housenumber":"4",
    "addr:postcode":"43850",
    "addr:street":"Pg Francesc Macia",
    "iso:country":"ES",
    "sg:address":"Pg Francesc Macia, 4",
    "sg:city":"Cambrils",
    "sg:orig_category":"Librer\u00cdas",
    "sg:phone":"+34 977 36 37 74",
    "sg:postcode":"43850",
    "sg:province":"Tarragona",
    "wof:name":"Salvado Monseny Victoria",
    "wof:placetype":"venue"
},
  "geometry": {"coordinates":[1.0611100197,41.0672683716],"type":"Point"}
}