{
  "type": "Feature",
  "properties": {
    "iso:country":"ES",
    "sg:address":"Carrer de Pare Llaurador, 145",
    "sg:city":"Terrassa",
    "sg:orig_category":"Extinci\u00d3n De Incendios: Material Y Suministros (fabricaci\u00d3n, Al Por Mayor)",
    "sg:phone":"+34 937 33 11 11",
    "sg:postcode":"08224",
    "sg:province":"Barcelona",
    "wof:name":"Joan Oller S.l.",
    "wof:placetype":"venue"
},
  "geometry": {"coordinates":[2.0030739307,41.564239502],"type":"Point"}
}