{
  "type": "Feature",
  "properties": {
    "addr:full":"Rua Calvo Sotelo, 46 Estrada Pontevedra 36680",
    "addr:housenumber":"46",
    "addr:postcode":"36680",
    "addr:street":"Rua Calvo Sotelo;Estrada Pontevedra",
    "iso:country":"ES",
    "sg:address":"Rua Calvo Sotelo, 46",
    "sg:city":"Estrada",
    "sg:orig_category":"Ropa Para Se\u00d1oras (al Por Menor)",
    "sg:phone":"+34 986 57 23 65",
    "sg:postcode":"36680",
    "sg:province":"Pontevedra",
    "wof:name":"Naty C.b.",
    "wof:placetype":"venue"
},
  "geometry": {"coordinates":[-8.4906387329,42.6898612976],"type":"Point"}
}