{
  "type": "Feature",
  "properties": {
    "addr:full":"Pase Maritimo De Mogor, S/n Baguin Pontevedra 36911",
    "addr:housenumber":"s",
    "addr:postcode":"36911",
    "addr:street":"/ N",
    "iso:country":"ES",
    "sg:address":"Pase Maritimo De Mogor, S/n",
    "sg:city":"Baguin",
    "sg:orig_category":"Venta, Instalaci\u00d3n De Cocinas",
    "sg:phone":"+34 986 88 23 33",
    "sg:postcode":"36911",
    "sg:province":"Pontevedra",
    "wof:name":"Garcia Montes Maria Victoria",
    "wof:placetype":"venue"
},
  "geometry": {"coordinates":[-8.7247037888,42.3783798218],"type":"Point"}
}