{
  "type": "Feature",
  "properties": {
    "iso:country":"ES",
    "sg:address":"Psaj San Isidro, S/n",
    "sg:city":"Ciudad Real",
    "sg:classifiers":[
        {
            "category":"Casinos & Gambling",
            "type":"Entertainment"
        }
    ],
    "sg:phone":"+34 926 21 20 27",
    "sg:postcode":"13001",
    "sg:province":"Ciudad Real",
    "sg:tags":[
        "locale",
        "de",
        "juego"
    ],
    "wof:name":"Wakimuki S.l.",
    "wof:placetype":"venue"
},
  "geometry": {"coordinates":[-3.9279243946,38.9830245972],"type":"Point"}
}