{
  "type": "Feature",
  "properties": {
    "addr:full":"Avda Peris Y Valero, 165 Valencia Valencia 46005",
    "addr:housenumber":"165",
    "addr:postcode":"46005",
    "addr:street":"Avda Peris Y Valero",
    "iso:country":"ES",
    "sg:address":"Avda Peris Y Valero, 165",
    "sg:city":"Valencia",
    "sg:orig_category":"Electrodom\u00c9sticos (al Por Menor)",
    "sg:phone":"+34 963 33 97 85",
    "sg:postcode":"46005",
    "sg:province":"Valencia",
    "wof:name":"Mier Bada Enrique Pelayo",
    "wof:placetype":"venue"
},
  "geometry": {"coordinates":[-0.3656359911,39.4613227844],"type":"Point"}
}