{
  "type": "Feature",
  "properties": {
    "addr:full":"Avda Constitucion, 211 San Isidro Nijar Almer\u00eda 04117",
    "addr:housenumber":"211",
    "addr:postcode":"04117",
    "addr:street":"Avda Constitucion",
    "iso:country":"ES",
    "sg:address":"Avda Constitucion, 211",
    "sg:city":"San Isidro Nijar",
    "sg:orig_category":"Empresas De Carpinter\u00cda Met\u00c1lica",
    "sg:phone":"+34 950 36 62 27",
    "sg:postcode":"04117",
    "sg:province":"Almer\u00eda",
    "wof:name":"Morales Roman Miguel",
    "wof:placetype":"venue"
},
  "geometry": {"coordinates":[-2.1090888977,36.7877845764],"type":"Point"}
}