{
  "type": "Feature",
  "properties": {
    "addr:full":"C/ Bartolome J. Gallardo, 4 Alcoi Alicante 03801",
    "addr:housenumber":"4",
    "addr:postcode":"03801",
    "addr:street":"C / Bartolome J. Gallardo",
    "iso:country":"ES",
    "sg:address":"C/ Bartolome J. Gallardo, 4",
    "sg:city":"Alcoi",
    "sg:orig_category":"Impuestos, Tesoro P\u00dablico",
    "sg:phone":"+34 965 54 53 58",
    "sg:postcode":"03801",
    "sg:province":"Alicante",
    "wof:name":"Santonja Palacio Jorge Luis",
    "wof:placetype":"venue"
},
  "geometry": {"coordinates":[-0.4751529992,38.6955070496],"type":"Point"}
}