{
  "type": "Feature",
  "properties": {
    "addr:full":"Carrer de Drago, 25 Masies Catalanes Tarragona 43479",
    "addr:housenumber":"25",
    "addr:postcode":"43479",
    "addr:street":"Carrer De Drago",
    "iso:country":"ES",
    "sg:address":"Carrer de Drago, 25",
    "sg:city":"Masies Catalanes",
    "sg:orig_category":"Inform\u00c1tica (estudios, Servicios, Asesor\u00cda, Formaci\u00d3n)",
    "sg:phone":"+34 977 84 69 73",
    "sg:postcode":"43479",
    "sg:province":"Tarragona",
    "wof:name":"Sosip Sl",
    "wof:placetype":"venue"
},
  "geometry": {"coordinates":[1.0893199444,41.25207901],"type":"Point"}
}