{
  "type": "Feature",
  "properties": {
    "iso:country":"ES",
    "sg:address":"Calle de Marcelo Usera, 123",
    "sg:city":"Madrid",
    "sg:orig_category":"Bisuter\u00cda, Joyer\u00cda, Relojer\u00cda (al Por Menor)",
    "sg:phone":"+34 914 75 40 88",
    "sg:postcode":"28026",
    "sg:province":"Madrid",
    "wof:name":"Hernandez Romon Luis",
    "wof:placetype":"venue"
},
  "geometry": {"coordinates":[-3.7095279694,40.3853187561],"type":"Point"}
}