{
  "type": "Feature",
  "properties": {
    "iso:country":"ES",
    "sg:address":"Campillo (el) Industrialdea Edif A, 12",
    "sg:city":"Abanto",
    "sg:orig_category":"Empresas De Carpinter\u00cda Met\u00c1lica",
    "sg:phone":"+34 944 72 06 66",
    "sg:postcode":"48500",
    "sg:province":"Vizcaya",
    "wof:name":"Carpinteria Kaiku 2003, S.l",
    "wof:placetype":"venue"
},
  "geometry": {"coordinates":[-2.9316000938,43.2383995056],"type":"Point"}
}