{
  "type": "Feature",
  "properties": {
    "addr:full":"San Vicente, 4 Puig D'en Valls Islas Baleares 07819",
    "addr:housenumber":"4",
    "addr:postcode":"07819",
    "addr:street":"San Vicente",
    "iso:country":"ES",
    "sg:address":"San Vicente, 4",
    "sg:city":"Puig D'en Valls",
    "sg:orig_category":"Fabrica De Charcuter\u00cda",
    "sg:phone":"+34 971 31 45 92",
    "sg:postcode":"07819",
    "sg:province":"Islas Baleares",
    "wof:name":"Esteban Espu\u00f1a S.a.",
    "wof:placetype":"venue"
},
  "geometry": {"coordinates":[2.9117100239,39.6136398315],"type":"Point"}
}