{
  "type": "Feature",
  "properties": {
    "addr:full":"Pase Toki Eder De, 21 Donostia-san Sebastian Guip\u00f9zcoa 20013",
    "addr:housenumber":"21",
    "addr:postcode":"20013",
    "iso:country":"ES",
    "sg:address":"Pase Toki Eder De, 21",
    "sg:city":"Donostia-san Sebastian",
    "sg:orig_category":"Ropa Para Se\u00d1oras Y Caballeros (al Por Menor)",
    "sg:phone":"+34 943 29 03 66",
    "sg:postcode":"20013",
    "sg:province":"Guip\u00f9zcoa",
    "wof:name":"Sissel S.a.",
    "wof:placetype":"venue"
},
  "geometry": {"coordinates":[-1.9588160515,43.3228149414],"type":"Point"}
}