{
  "type": "Feature",
  "properties": {
    "addr:full":"Rua Santiago Del Estero (de), 7 Santiago De Compostela La Coru\u00f1a 15706",
    "addr:housenumber":"7",
    "addr:postcode":"15706",
    "addr:street":"Rua Santiago Del Estero De;Corun\u0303A",
    "iso:country":"ES",
    "sg:address":"Rua Santiago Del Estero (de), 7",
    "sg:city":"Santiago De Compostela",
    "sg:orig_category":"Confecci\u00d3n (fabricaci\u00d3n, Al Por Mayor)",
    "sg:phone":"+34 981 59 54 05",
    "sg:postcode":"15706",
    "sg:province":"La Coru\u00f1a",
    "wof:name":"Rivera Alvarez Genoveva",
    "wof:placetype":"venue"
},
  "geometry": {"coordinates":[-8.5511131287,42.8731880188],"type":"Point"}
}