{
  "type": "Feature",
  "properties": {
    "addr:full":"Calle de Cuba, 50 Coru\u00d1a La Coru\u00f1a 15010",
    "addr:housenumber":"50",
    "addr:postcode":"15010",
    "addr:street":"Calle De Cuba;La Corun\u0303A",
    "iso:country":"ES",
    "sg:address":"Calle de Cuba, 50",
    "sg:city":"Coru\u00d1a",
    "sg:orig_category":"Peluqueros: De Se\u00d1oras",
    "sg:phone":"+34 981 27 40 52",
    "sg:postcode":"15010",
    "sg:province":"La Coru\u00f1a",
    "wof:name":"Fernandez Ma\u00f1anas Susana",
    "wof:placetype":"venue"
},
  "geometry": {"coordinates":[-8.4208040237,43.3629455566],"type":"Point"}
}