{
  "type": "Feature",
  "properties": {
    "iso:country":"ES",
    "sg:address":"Calle de Padilla, 6",
    "sg:city":"Salamanca",
    "sg:orig_category":"Art\u00cdculos De Decoraci\u00d3n",
    "sg:phone":"+34 923 26 93 11",
    "sg:postcode":"37003",
    "sg:province":"Salamanca",
    "wof:name":"Persianas Y Ventanas Hellin S. L.",
    "wof:placetype":"venue"
},
  "geometry": {"coordinates":[-5.6575927734,40.9659118652],"type":"Point"}
}