{
  "type": "Feature",
  "properties": {
    "addr:full":"Brul, S/n Tol Asturias 33794",
    "addr:postcode":"33794",
    "addr:street":"S / N Tol Asturias",
    "iso:country":"ES",
    "sg:address":"Brul, S/n",
    "sg:city":"Tol",
    "sg:orig_category":"Cr\u00cda De Animales",
    "sg:phone":"+34 985 62 80 14",
    "sg:postcode":"33794",
    "sg:province":"Asturias",
    "wof:name":"Ganaderia Adelina",
    "wof:placetype":"venue"
},
  "geometry": {"coordinates":[-7.0207791328,43.539642334],"type":"Point"}
}