{
  "type": "Feature",
  "properties": {
    "addr:full":"C/ Ramils, 51 Banyoles Girona 17820",
    "addr:housenumber":"51",
    "addr:postcode":"17820",
    "addr:street":"C / Ramils",
    "iso:country":"ES",
    "sg:address":"C/ Ramils, 51",
    "sg:city":"Banyoles",
    "sg:orig_category":"Psic\u00d3logos",
    "sg:phone":"+34 972 57 41 10",
    "sg:postcode":"17820",
    "sg:province":"Girona",
    "wof:name":"Blanco Rivera Roser",
    "wof:placetype":"venue"
},
  "geometry": {"coordinates":[2.7798841,42.1200218201],"type":"Point"}
}