{
  "type": "Feature",
  "properties": {
    "iso:country":"ES",
    "sg:address":"Avda Menesteo (de), 43",
    "sg:city":"Puerto De Santa Maria",
    "sg:orig_category":"Sonorizaci\u00d3n, Iluminaci\u00d3n Para Cine, Teatro Y Discotecas (al Por Mayor, Al Por Menor)",
    "sg:phone":"+34 956 85 07 82",
    "sg:postcode":"11500",
    "sg:province":"C\u00e1diz",
    "wof:name":"Otero Cressi Fernando",
    "wof:placetype":"venue"
},
  "geometry": {"coordinates":[-6.231897831,36.5908126831],"type":"Point"}
}