{
  "type": "Feature",
  "properties": {
    "iso:country":"ES",
    "sg:address":"Trva Basqui\u00d1os (dos), 6",
    "sg:city":"Santiago De Compostela",
    "sg:orig_category":"Promotores Constructores",
    "sg:phone":"+34 981 56 63 73",
    "sg:postcode":"15704",
    "sg:province":"La Coru\u00f1a",
    "wof:name":"Galicons Siglo Xx1 S.l.",
    "wof:placetype":"venue"
},
  "geometry": {"coordinates":[-8.5388374329,42.8870277405],"type":"Point"}
}