{
  "type": "Feature",
  "properties": {
    "addr:full":"Calle de General Queipo De Llano, 3 Cantalejo Segovia 40320",
    "addr:housenumber":"3",
    "addr:postcode":"40320",
    "addr:street":"Calle De General Queipo De Llano",
    "iso:country":"ES",
    "sg:address":"Calle de General Queipo De Llano, 3",
    "sg:city":"Cantalejo",
    "sg:orig_category":"Alquiler De V\u00cddeo",
    "sg:phone":"+34 921 52 06 49",
    "sg:postcode":"40320",
    "sg:province":"Segovia",
    "wof:name":"Sanz Sacristan Purificacion",
    "wof:placetype":"venue"
},
  "geometry": {"coordinates":[-3.9286050797,41.2584495544],"type":"Point"}
}