{
  "type": "Feature",
  "properties": {
    "addr:full":"Carrer de Cartagena (de), 8 Tarragona Tarragona 43004",
    "addr:postcode":"43004",
    "addr:street":"Carrer De Cartagena De 8",
    "iso:country":"ES",
    "sg:address":"Carrer de Cartagena (de), 8",
    "sg:city":"Tarragona",
    "sg:orig_category":"Artes Gr\u00c1ficas, Artes Pl\u00c1sticas (curso)",
    "sg:phone":"+34 977 23 00 02",
    "sg:postcode":"43004",
    "sg:province":"Tarragona",
    "wof:name":"Graficas Llovet S.l.",
    "wof:placetype":"venue"
},
  "geometry": {"coordinates":[1.250041008,41.1122932434],"type":"Point"}
}