{
  "type": "Feature",
  "properties": {
    "addr:full":"Pol Berenguer, 2 Cabrianes Barcelona 08650",
    "addr:housenumber":"2",
    "addr:postcode":"08650",
    "addr:street":"Berenguer;Barcelona",
    "iso:country":"ES",
    "sg:address":"Pol Berenguer, 2",
    "sg:city":"Cabrianes",
    "sg:orig_category":"Barnizadores",
    "sg:phone":"+34 938 37 23 69",
    "sg:postcode":"08650",
    "sg:province":"Barcelona",
    "wof:name":"Maya Envernissats S.l.",
    "wof:placetype":"venue"
},
  "geometry": {"coordinates":[1.8924599886,41.823589325],"type":"Point"}
}