{
  "type": "Feature",
  "properties": {
    "addr:full":"Carrer de Puigterra De Dalt, 24 Manresa Barcelona 08241",
    "addr:housenumber":"24",
    "addr:postcode":"08241",
    "addr:street":"Carrer De Puigterra De Dalt",
    "iso:country":"ES",
    "sg:address":"Carrer de Puigterra De Dalt, 24",
    "sg:city":"Manresa",
    "sg:orig_category":"Peluqueros: De Se\u00d1oras",
    "sg:phone":"+34 938 73 50 69",
    "sg:postcode":"08241",
    "sg:province":"Barcelona",
    "wof:name":"Torrijos Rios Raquel",
    "wof:placetype":"venue"
},
  "geometry": {"coordinates":[1.8273910284,41.7262496948],"type":"Point"}
}