{
  "type": "Feature",
  "properties": {
    "iso:country":"ES",
    "sg:address":"Calle de San Vicente Martir, 44",
    "sg:city":"Valencia",
    "sg:orig_category":"Teatros Y Salas De Espect\u00c1culos",
    "sg:phone":"+34 963 51 73 15",
    "sg:postcode":"46002",
    "sg:province":"Valencia",
    "wof:name":"Olympia Metropolitana S.a.",
    "wof:placetype":"venue"
},
  "geometry": {"coordinates":[-0.3780660033,39.4708251953],"type":"Point"}
}