{
  "type": "Feature",
  "properties": {
    "iso:country":"ES",
    "sg:address":"Calle de Esca\u00d1uela, S/n",
    "sg:city":"Arjona",
    "sg:orig_category":"Chapister\u00cda",
    "sg:phone":"+34 953 52 36 09",
    "sg:postcode":"23760",
    "sg:province":"Ja\u00e9n",
    "wof:name":"Criado Quero Francisco",
    "wof:placetype":"venue"
},
  "geometry": {"coordinates":[-4.0649690628,37.9371109009],"type":"Point"}
}