{
  "type": "Feature",
  "properties": {
    "addr:full":"Guiral, S/n Los Algarbes C\u00f3rdoba 14100",
    "addr:housenumber":"/ n",
    "addr:postcode":"14100",
    "addr:street":"Guiral S;Los Algarbes Co\u0301Rdoba",
    "iso:country":"ES",
    "sg:address":"Guiral, S/n",
    "sg:city":"Los Algarbes",
    "sg:orig_category":"Deportes Y Ocio: Art\u00cdculos Y Ropas (al Por Menor Y Accesorios)",
    "sg:phone":"+34 957 33 10 34",
    "sg:postcode":"14100",
    "sg:province":"C\u00f3rdoba",
    "sg:website":"www.kswsport.com",
    "wof:name":"Trasertran S.l.",
    "wof:placetype":"venue"
},
  "geometry": {"coordinates":[-4.9374890327,37.6685142517],"type":"Point"}
}