{
  "type": "Feature",
  "properties": {
    "addr:full":"Calle de Rio Ebro, 22 Escalona Toledo 45910",
    "addr:housenumber":"22",
    "addr:postcode":"45910",
    "addr:street":"Calle De Rio Ebro",
    "iso:country":"ES",
    "sg:address":"Calle de Rio Ebro, 22",
    "sg:city":"Escalona",
    "sg:classifiers":[
        {
            "category":"Autos & Motor Vehicles",
            "subcategory":"Automobile Sales",
            "type":"Retail Goods"
        }
    ],
    "sg:phone":"+34 925 78 04 10",
    "sg:postcode":"45910",
    "sg:province":"Toledo",
    "wof:name":"Fernandez Rojas Maria Victoria",
    "wof:placetype":"venue"
},
  "geometry": {"coordinates":[-4.4079890251,40.1652603149],"type":"Point"}
}