{
  "type": "Feature",
  "properties": {
    "iso:country":"ES",
    "sg:address":"Rua Dolores, 61",
    "sg:city":"Ferrol",
    "sg:orig_category":"Inform\u00c1tica: Material Y Suministros",
    "sg:phone":"+34 981 35 26 05",
    "sg:postcode":"15402",
    "sg:province":"La Coru\u00f1a",
    "wof:name":"Comunidad De Herederos De Maria Luisa Gonzalez Naya",
    "wof:placetype":"venue"
},
  "geometry": {"coordinates":[-8.2358903885,43.4830055237],"type":"Point"}
}