{
  "type": "Feature",
  "properties": {
    "iso:country":"ES",
    "sg:address":"Calle de Aitzbitarte, Pasaje De, 9",
    "sg:city":"Errenteria",
    "sg:orig_category":"Molduras, Junquillos, Listones Y Molduras Perforadas",
    "sg:phone":"+34 943 51 10 72",
    "sg:postcode":"20100",
    "sg:province":"Guip\u00f9zcoa",
    "wof:name":"Pe\u00f1a Novales Julio",
    "wof:placetype":"venue"
},
  "geometry": {"coordinates":[-1.891141057,43.3099746704],"type":"Point"}
}