{
  "type": "Feature",
  "properties": {
    "addr:full":"Rbla Rei En Jaume, S/n Manacor Islas Baleares 07500",
    "addr:housenumber":"s / n",
    "addr:postcode":"07500",
    "addr:street":"Rbla Rei En Jaume",
    "iso:country":"ES",
    "sg:address":"Rbla Rei En Jaume, S/n",
    "sg:city":"Manacor",
    "sg:orig_category":"Alimentaci\u00d3n General (al Por Mayor)",
    "sg:phone":"+34 971 84 34 44",
    "sg:postcode":"07500",
    "sg:province":"Islas Baleares",
    "sg:website":"www.cavalcan.com",
    "wof:name":"Adrover Llodra Nicolas",
    "wof:placetype":"venue"
},
  "geometry": {"coordinates":[3.2147188187,39.5648040771],"type":"Point"}
}