{
  "type": "Feature",
  "properties": {
    "addr:full":"Calle de Mayor, 16 Madrid Madrid 28013",
    "addr:housenumber":"16",
    "addr:postcode":"madrid;28013",
    "addr:street":"Calle De Mayor",
    "iso:country":"ES",
    "sg:address":"Calle de Mayor, 16",
    "sg:city":"Madrid",
    "sg:orig_category":"Perfumer\u00cda (al Por Menor)",
    "sg:phone":"+34 913 64 01 81",
    "sg:postcode":"28013",
    "sg:province":"Madrid",
    "sg:website":"www.marionnaud.es",
    "wof:name":"Marionnaud Perfumeries Iberica S.l.",
    "wof:placetype":"venue"
},
  "geometry": {"coordinates":[-3.7065601349,40.4163208008],"type":"Point"}
}