{
  "type": "Feature",
  "properties": {
    "addr:full":"Calle de Tucuman, 15 Tafira Baja Las Palmas 35017",
    "addr:housenumber":"15",
    "addr:postcode":"35017",
    "addr:street":"Calle De Tucuman",
    "iso:country":"ES",
    "sg:address":"Calle de Tucuman, 15",
    "sg:city":"Tafira Baja",
    "sg:orig_category":"Frutas, Legumbres Frescas Y Tempranas (al Por Menor)",
    "sg:phone":"+34 928 35 38 47",
    "sg:postcode":"35017",
    "sg:province":"Las Palmas",
    "wof:name":"Jupamag Las Palmas S.l.",
    "wof:placetype":"venue"
},
  "geometry": {"coordinates":[-15.4497919083,28.0705776215],"type":"Point"}
}