{
  "type": "Feature",
  "properties": {
    "iso:country":"ES",
    "sg:address":"Pase Condes De Barcelona, 7",
    "sg:city":"Badajoz",
    "sg:orig_category":"Centros M\u00c9dicos Y Sociales, Dispensarios",
    "sg:phone":"+34 924 24 89 91",
    "sg:postcode":"06010",
    "sg:province":"Badajoz",
    "wof:name":"Margarita Silvestre Garcia Y Alfonso Garcia-ordaz Alvarez",
    "wof:placetype":"venue"
},
  "geometry": {"coordinates":[-6.9803590775,38.8667831421],"type":"Point"}
}