{
  "type": "Feature",
  "properties": {
    "iso:country":"ES",
    "sg:address":"Calle de Ancha, 32",
    "sg:city":"Rincon Soto",
    "sg:orig_category":"Poller\u00cda Y Caza (al Por Menor)",
    "sg:phone":"+34 941 16 03 21",
    "sg:postcode":"26550",
    "sg:province":"La Rioja",
    "wof:name":"Perez Garcia Carlos",
    "wof:placetype":"venue"
},
  "geometry": {"coordinates":[-1.8526288271,42.2362327576],"type":"Point"}
}