{
  "type": "Feature",
  "properties": {
    "addr:full":"Calle de Valderrey, 26 Madrid Madrid 28035",
    "addr:housenumber":"26",
    "addr:postcode":"madrid;28035",
    "addr:street":"Calle De Valderrey",
    "iso:country":"ES",
    "sg:address":"Calle de Valderrey, 26",
    "sg:city":"Madrid",
    "sg:orig_category":"Ambulancias",
    "sg:phone":"+34 913 16 54 01",
    "sg:postcode":"28035",
    "sg:province":"Madrid",
    "wof:name":"Tratamientos Selvicolas S.l.",
    "wof:placetype":"venue"
},
  "geometry": {"coordinates":[-3.7205588818,40.4679794312],"type":"Point"}
}