{
  "type": "Feature",
  "properties": {
    "addr:full":"Ctra Ecija-herrera, Km. 0008,0 Ecija Sevilla 41400",
    "addr:postcode":"41400",
    "addr:street":"Ctra Ecija-Herrera Km. 0008,0",
    "iso:country":"ES",
    "sg:address":"Ctra Ecija-herrera, Km. 0008,0",
    "sg:city":"Ecija",
    "sg:orig_category":"Producci\u00d3n, Venta De Productos De Agricultura Biol\u00d3gica",
    "sg:phone":"+34 955 95 50 16",
    "sg:postcode":"41400",
    "sg:province":"Sevilla",
    "wof:name":"Agricola Cardenas Ecija S.l.",
    "wof:placetype":"venue"
},
  "geometry": {"coordinates":[-5.1037306786,37.7034301758],"type":"Point"}
}