{
  "type": "Feature",
  "properties": {
    "iso:country":"ES",
    "sg:address":"V. Dos Castillas, 33",
    "sg:city":"Madrid",
    "sg:orig_category":"Centros Empresariales",
    "sg:phone":"+34 913 51 92 69",
    "sg:postcode":"28023",
    "sg:province":"Madrid",
    "wof:name":"Asociacion Nacional De Franquiciados De B.k.",
    "wof:placetype":"venue"
},
  "geometry": {"coordinates":[-3.7675437927,40.4473152161],"type":"Point"}
}