{
  "type": "Feature",
  "properties": {
    "addr:full":"Calle de Rio Ebro, 53 Cuarte Huerva Zaragoza 50410",
    "addr:housenumber":"53",
    "addr:postcode":"50410",
    "addr:street":"Calle De Rio Ebro",
    "iso:country":"ES",
    "sg:address":"Calle de Rio Ebro, 53",
    "sg:city":"Cuarte Huerva",
    "sg:orig_category":"Metalurgia: Maquinaria Y Equipos",
    "sg:phone":"+34 976 50 48 07",
    "sg:postcode":"50410",
    "sg:province":"Zaragoza",
    "sg:website":"www.airfren.com",
    "wof:name":"Air Fren S.l.",
    "wof:placetype":"venue"
},
  "geometry": {"coordinates":[-0.9324563742,41.5984954834],"type":"Point"}
}