{
  "type": "Feature",
  "properties": {
    "addr:full":"Av Antoni Gaudi, 46 Mollet Valles Barcelona 08100",
    "addr:housenumber":"46",
    "addr:postcode":"08100",
    "addr:street":"Av Antoni Gaudi",
    "iso:country":"ES",
    "sg:address":"Av Antoni Gaudi, 46",
    "sg:city":"Mollet Valles",
    "sg:orig_category":"Reposter\u00cdas",
    "sg:phone":"+34 935 70 70 87",
    "sg:postcode":"08100",
    "sg:province":"Barcelona",
    "wof:name":"Corbalan Ruiz Manuel",
    "wof:placetype":"venue"
},
  "geometry": {"coordinates":[2.2203979492,41.5474052429],"type":"Point"}
}