{
  "type": "Feature",
  "properties": {
    "iso:country":"ES",
    "sg:address":"Pg Lloren\u00c7 Serra, 51",
    "sg:city":"Santa Coloma De Gramenet",
    "sg:orig_category":"Carnicer\u00cdas, Carnicer\u00cdas",
    "sg:phone":"+34 934 66 53 00",
    "sg:postcode":"08922",
    "sg:province":"Barcelona",
    "wof:name":"Enrique Tomas S.l.",
    "wof:placetype":"venue"
},
  "geometry": {"coordinates":[2.2044448853,41.449962616],"type":"Point"}
}