{
  "type": "Feature",
  "properties": {
    "iso:country":"ES",
    "sg:address":"Calle de Karmelo, 15",
    "sg:city":"Bilbao",
    "sg:orig_category":"Bisuter\u00cda, Joyer\u00cda, Relojer\u00cda (al Por Menor)",
    "sg:phone":"+34 944 73 25 81",
    "sg:postcode":"48004",
    "sg:province":"Vizcaya",
    "wof:name":"Urre Gazte S.l.",
    "wof:placetype":"venue"
},
  "geometry": {"coordinates":[-2.900121212,43.2565917969],"type":"Point"}
}