{
  "type": "Feature",
  "properties": {
    "iso:country":"ES",
    "sg:address":"Calle de San Antonio, 27",
    "sg:city":"Prado Del Rey",
    "sg:orig_category":"Delegados, Agentes De Tr\u00c1nsito, Auxiliares De Transporte Internacional",
    "sg:phone":"+34 956 72 37 12",
    "sg:postcode":"11660",
    "sg:province":"C\u00e1diz",
    "wof:name":"Lopez Fabero Pedro",
    "wof:placetype":"venue"
},
  "geometry": {"coordinates":[-5.5549931526,36.7869911194],"type":"Point"}
}