{
  "type": "Feature",
  "properties": {
    "iso:country":"ES",
    "sg:address":"Via Palma, 98",
    "sg:city":"Manacor",
    "sg:orig_category":"Asesor\u00cdas Y Estudios Financieros",
    "sg:phone":"+34 971 84 47 23",
    "sg:postcode":"07500",
    "sg:province":"Islas Baleares",
    "wof:name":"Rossello Nicolau Francesc Josep",
    "wof:placetype":"venue"
},
  "geometry": {"coordinates":[3.2034239769,39.5747680664],"type":"Point"}
}