{
  "type": "Feature",
  "properties": {
    "iso:country":"ES",
    "sg:address":"Carrer de Progres, 15",
    "sg:city":"Vendrell",
    "sg:orig_category":"Formaci\u00d3n Continuada (variada)",
    "sg:phone":"+34 977 66 01 17",
    "sg:postcode":"43700",
    "sg:province":"Tarragona",
    "wof:name":"Carne Nin Valenti",
    "wof:placetype":"venue"
},
  "geometry": {"coordinates":[1.5355060101,41.2232475281],"type":"Point"}
}