{
  "type": "Feature",
  "properties": {
    "addr:full":"Avda Villamayor, 40 Salamanca Salamanca 37007",
    "addr:housenumber":"40",
    "addr:postcode":"37007",
    "addr:street":"Avda Villamayor",
    "iso:country":"ES",
    "sg:address":"Avda Villamayor, 40",
    "sg:city":"Salamanca",
    "sg:orig_category":"Confecci\u00d3n (fabricaci\u00d3n, Al Por Mayor)",
    "sg:phone":"+34 923 25 24 93",
    "sg:postcode":"37007",
    "sg:province":"Salamanca",
    "wof:name":"Gonzalez Gonzalez Pedro",
    "wof:placetype":"venue"
},
  "geometry": {"coordinates":[-5.6696658134,40.9699401855],"type":"Point"}
}