{
  "type": "Feature",
  "properties": {
    "addr:full":"Carrer de Valencia, 479 Barcelona Barcelona 08013",
    "addr:housenumber":"479",
    "addr:postcode":"08013",
    "addr:street":"Carrer De Valencia",
    "iso:country":"ES",
    "sg:address":"Carrer de Valencia, 479",
    "sg:city":"Barcelona",
    "sg:orig_category":"Sociedades, Compa\u00d1\u00cdas Aseguradoras",
    "sg:phone":"+34 932 31 20 66",
    "sg:postcode":"08013",
    "sg:province":"Barcelona",
    "wof:name":"Alcaraz Martinez Rafael",
    "wof:placetype":"venue"
},
  "geometry": {"coordinates":[2.1785953045,41.4041938782],"type":"Point"}
}