{
  "type": "Feature",
  "properties": {
    "iso:country":"ES",
    "sg:address":"Calle de Dean Marti, 44",
    "sg:city":"Castellon",
    "sg:orig_category":"Cajas Y Embalajes De Cart\u00d3n Y Papel",
    "sg:phone":"+34 964 24 75 40",
    "sg:postcode":"12004",
    "sg:province":"Castell\u00f3n",
    "wof:name":"Jimenez Ca\u00f1ete Maria Concepcion",
    "wof:placetype":"venue"
},
  "geometry": {"coordinates":[-0.0279866997,40.0120239258],"type":"Point"}
}