{
  "type": "Feature",
  "properties": {
    "addr:full":"Carr Tenor Alonso, 101 Godella Valencia 46110",
    "addr:housenumber":"101",
    "addr:postcode":"46110",
    "addr:street":"Carr Tenor Alonso",
    "iso:country":"ES",
    "sg:address":"Carr Tenor Alonso, 101",
    "sg:city":"Godella",
    "sg:orig_category":"Droguer\u00cdas (al Por Menor)",
    "sg:phone":"+34 963 63 20 01",
    "sg:postcode":"46110",
    "sg:province":"Valencia",
    "wof:name":"Arnau Marco Maria Vicenta",
    "wof:placetype":"venue"
},
  "geometry": {"coordinates":[-0.4133473039,39.5187797546],"type":"Point"}
}