{
  "type": "Feature",
  "properties": {
    "iso:country":"ES",
    "sg:address":"Grup San Jose, 4",
    "sg:city":"Cancienes",
    "sg:orig_category":"Bibliotecas, Mediatecas",
    "sg:phone":"+34 985 51 82 08",
    "sg:postcode":"33470",
    "sg:province":"Asturias",
    "wof:name":"Ayuntamiento De Corvera (biblioteca Cancienes",
    "wof:placetype":"venue"
},
  "geometry": {"coordinates":[-5.8677392006,43.4768409729],"type":"Point"}
}