{
  "type": "Feature",
  "properties": {
    "iso:country":"ES",
    "sg:address":"Carrer de Murcia, 36",
    "sg:city":"Rubi",
    "sg:orig_category":"Asesor\u00cda Sobre Comunicaci\u00d3n De Empresas",
    "sg:phone":"+34 935 88 78 75",
    "sg:postcode":"08191",
    "sg:province":"Barcelona",
    "wof:name":"Rubilabor S.l.",
    "wof:placetype":"venue"
},
  "geometry": {"coordinates":[2.0365569592,41.49817276],"type":"Point"}
}