{
  "type": "Feature",
  "properties": {
    "iso:country":"ES",
    "sg:address":"Carrer de Joan Guell, 37",
    "sg:city":"Barcelona",
    "sg:orig_category":"Agencias Y Agentes Comerciales, Representantes",
    "sg:phone":"+34 934 91 24 53",
    "sg:postcode":"08028",
    "sg:province":"Barcelona",
    "wof:name":"San Segundo Blazquez Sergio",
    "wof:placetype":"venue"
},
  "geometry": {"coordinates":[2.1337258816,41.3775558472],"type":"Point"}
}