{
  "type": "Feature",
  "properties": {
    "addr:full":"Plaz Lauaxeta, 5 Bilbao Vizcaya 48004",
    "addr:housenumber":"5",
    "addr:postcode":"48004",
    "addr:street":"Lauaxeta",
    "iso:country":"ES",
    "sg:address":"Plaz Lauaxeta, 5",
    "sg:city":"Bilbao",
    "sg:orig_category":"Cajas Registradoras, Terminales De Puntos De Venta",
    "sg:phone":"+34 944 11 31 99",
    "sg:postcode":"48004",
    "sg:province":"Vizcaya",
    "wof:name":"Garcia Cerezo Felipe",
    "wof:placetype":"venue"
},
  "geometry": {"coordinates":[-2.9090030193,43.2516479492],"type":"Point"}
}