{
  "type": "Feature",
  "properties": {
    "addr:full":"Av Cornella, 74 Esplugues Llobregat Barcelona 08950",
    "addr:housenumber":"74",
    "addr:postcode":"08950",
    "addr:street":"Av Cornella",
    "iso:country":"ES",
    "sg:address":"Av Cornella, 74",
    "sg:city":"Esplugues Llobregat",
    "sg:orig_category":"Centros De Coordinaci\u00d3n",
    "sg:phone":"+34 933 71 00 00",
    "sg:postcode":"08950",
    "sg:province":"Barcelona",
    "wof:name":"Culebras Assessors S.l.",
    "wof:placetype":"venue"
},
  "geometry": {"coordinates":[2.0845549107,41.3737449646],"type":"Point"}
}