{
  "type": "Feature",
  "properties": {
    "iso:country":"ES",
    "sg:address":"Calle de Vazquez Coronado, 15",
    "sg:city":"Salamanca",
    "sg:orig_category":"Asociaciones Humanitarias, De Cooperaci\u00d3n, De Acci\u00d3n Social",
    "sg:phone":"+34 923 27 16 39",
    "sg:postcode":"37002",
    "sg:province":"Salamanca",
    "wof:name":"Asociacion De Hogares Para Ni\u00f1os Privados De Ambiente Familiar",
    "wof:placetype":"venue"
},
  "geometry": {"coordinates":[-5.6626982689,40.9679298401],"type":"Point"}
}