{
  "type": "Feature",
  "properties": {
    "iso:country":"ES",
    "sg:address":"Calle de Paseo Del Huerto, 18",
    "sg:city":"Antas",
    "sg:orig_category":"Bisuter\u00cda, Joyer\u00cda, Relojer\u00cda (al Por Menor)",
    "sg:phone":"+34 950 45 28 49",
    "sg:postcode":"04628",
    "sg:province":"Almer\u00eda",
    "wof:name":"Sanchez Garcia Alfonso",
    "wof:placetype":"venue"
},
  "geometry": {"coordinates":[-1.9187179804,37.2447776794],"type":"Point"}
}