{
  "type": "Feature",
  "properties": {
    "addr:full":"Carrer de Villarroel, 201 Barcelona Barcelona 08036",
    "addr:housenumber":"201",
    "addr:postcode":"08036",
    "addr:street":"Carrer De Villarroel",
    "iso:country":"ES",
    "sg:address":"Carrer de Villarroel, 201",
    "sg:city":"Barcelona",
    "sg:orig_category":"Loter\u00cda Y T\u00d3mbola",
    "sg:phone":"+34 934 10 59 88",
    "sg:postcode":"08036",
    "sg:province":"Barcelona",
    "wof:name":"Garcia Rojas Luisa",
    "wof:placetype":"venue"
},
  "geometry": {"coordinates":[2.1506860256,41.3896141052],"type":"Point"}
}