{
  "type": "Feature",
  "properties": {
    "addr:full":"Carrer de Bartomeu Amat, 26 Terrassa Barcelona 08225",
    "addr:housenumber":"26",
    "addr:postcode":"08225",
    "addr:street":"Carrer De Bartomeu Amat",
    "iso:country":"ES",
    "sg:address":"Carrer de Bartomeu Amat, 26",
    "sg:city":"Terrassa",
    "sg:orig_category":"Enfermeras: Consultas, Atenci\u00d3n A Domicilio",
    "sg:phone":"+34 937 35 78 61",
    "sg:postcode":"08225",
    "sg:province":"Barcelona",
    "wof:name":"Perez Herrero Jorge Rafael",
    "wof:placetype":"venue"
},
  "geometry": {"coordinates":[2.0124650002,41.5727500916],"type":"Point"}
}