{
  "type": "Feature",
  "properties": {
    "iso:country":"ES",
    "sg:address":"Calle de Campomanes, 20",
    "sg:city":"Oviedo",
    "sg:orig_category":"Procuradores",
    "sg:phone":"+34 985 21 96 84",
    "sg:postcode":"33008",
    "sg:province":"Asturias",
    "wof:name":"Garcia-bernardo Pendas Cristina",
    "wof:placetype":"venue"
},
  "geometry": {"coordinates":[-5.8464870453,43.3582458496],"type":"Point"}
}