{
  "type": "Feature",
  "properties": {
    "iso:country":"ES",
    "sg:address":"Calle de Prado Palomo, S/n",
    "sg:city":"San Ildefonso O La Granja",
    "sg:orig_category":"Centros De Educaci\u00d3n Especial",
    "sg:phone":"+34 921 47 18 53",
    "sg:postcode":"40100",
    "sg:province":"Segovia",
    "wof:name":"C.e.i.p. Agapito Marazuela",
    "wof:placetype":"venue"
},
  "geometry": {"coordinates":[-4.0091719627,40.9024200439],"type":"Point"}
}