{
  "type": "Feature",
  "properties": {
    "iso:country":"ES",
    "sg:address":"Pl D'europa, 7",
    "sg:city":"Castellar Valles",
    "sg:orig_category":"Sociedades, Compa\u00d1\u00cdas Aseguradoras",
    "sg:phone":"+34 937 14 83 12",
    "sg:postcode":"08211",
    "sg:province":"Barcelona",
    "wof:name":"Seguros Rovi 2001 S. L.",
    "wof:placetype":"venue"
},
  "geometry": {"coordinates":[2.0824997425,41.5572891235],"type":"Point"}
}