{
  "type": "Feature",
  "properties": {
    "addr:full":"Calle de General Santocildes, 5 Burgos Burgos 09003",
    "addr:housenumber":"5",
    "addr:postcode":"09003",
    "addr:street":"Calle De General Santocildes",
    "iso:country":"ES",
    "sg:address":"Calle de General Santocildes, 5",
    "sg:city":"Burgos",
    "sg:orig_category":"Art\u00cdculos De Decoraci\u00d3n",
    "sg:phone":"+34 947 26 09 43",
    "sg:postcode":"09003",
    "sg:province":"Burgos",
    "sg:website":"www.ka-international.com",
    "wof:name":"Kibur S.l.",
    "wof:placetype":"venue"
},
  "geometry": {"coordinates":[-3.6997199059,42.3433227539],"type":"Point"}
}