{
  "type": "Feature",
  "properties": {
    "iso:country":"ES",
    "sg:address":"Calle de Ibarra, 2",
    "sg:city":"Elorrio",
    "sg:orig_category":"Molduras, Junquillos, Listones Y Molduras Perforadas",
    "sg:phone":"+34 946 82 09 95",
    "sg:postcode":"48230",
    "sg:province":"Vizcaya",
    "wof:name":"Maria Teresa Asla Olarra",
    "wof:placetype":"venue"
},
  "geometry": {"coordinates":[-2.5471019745,43.1326522827],"type":"Point"}
}