{
  "type": "Feature",
  "properties": {
    "iso:country":"ES",
    "sg:address":"Calle de Vicente Blasco Iba\u00d1ez, 5",
    "sg:city":"Redovan",
    "sg:orig_category":"Marketing Telef\u00d3nico",
    "sg:phone":"+34 966 75 48 79",
    "sg:postcode":"03370",
    "sg:province":"Alicante",
    "wof:name":"Locutorio Yalile S.l",
    "wof:placetype":"venue"
},
  "geometry": {"coordinates":[-0.9038940072,38.1121368408],"type":"Point"}
}