{
  "type": "Feature",
  "properties": {
    "addr:full":"Calle de Mayor, 35 Pilar Horadada Alicante 03190",
    "addr:housenumber":"35",
    "addr:postcode":"03190",
    "addr:street":"Calle De Mayor",
    "iso:country":"ES",
    "sg:address":"Calle de Mayor, 35",
    "sg:city":"Pilar Horadada",
    "sg:orig_category":"Florister\u00cdas",
    "sg:phone":"+34 966 76 64 48",
    "sg:postcode":"03190",
    "sg:province":"Alicante",
    "wof:name":"Lopez Montesinos Cruz",
    "wof:placetype":"venue"
},
  "geometry": {"coordinates":[-0.7914490104,37.8649139404],"type":"Point"}
}