{
  "type": "Feature",
  "properties": {
    "addr:full":"Calle de Pedralba, 156 Benaguasil Valencia 46180",
    "addr:housenumber":"156",
    "addr:postcode":"46180",
    "addr:street":"Calle De Pedralba",
    "iso:country":"ES",
    "sg:address":"Calle de Pedralba, 156",
    "sg:city":"Benaguasil",
    "sg:orig_category":"Electricidad (montaje, Ensamblaje De Componentes)",
    "sg:phone":"+34 962 73 17 65",
    "sg:postcode":"46180",
    "sg:province":"Valencia",
    "wof:name":"Alaez Cabrera Manuel",
    "wof:placetype":"venue"
},
  "geometry": {"coordinates":[-0.5933392048,39.5951347351],"type":"Point"}
}