{
  "type": "Feature",
  "properties": {
    "addr:full":"Calle de Cardenal Cisneros, 13 Valladolid Valladolid 47010",
    "addr:housenumber":"13",
    "addr:postcode":"47010",
    "addr:street":"Calle De Cardenal Cisneros",
    "iso:country":"ES",
    "sg:address":"Calle de Cardenal Cisneros, 13",
    "sg:city":"Valladolid",
    "sg:orig_category":"Telas Y Sedas (al Por Menor)",
    "sg:phone":"+34 983 25 79 02",
    "sg:postcode":"47010",
    "sg:province":"Valladolid",
    "wof:name":"Hnos.cuadrado Garcia C.b.",
    "wof:placetype":"venue"
},
  "geometry": {"coordinates":[-4.7229781151,41.6618843079],"type":"Point"}
}