{
  "type": "Feature",
  "properties": {
    "addr:full":"Ctra Ribesalbes, Km. 0003,0 Castellon De La Plana Castell\u00f3n 12006",
    "addr:postcode":"12006",
    "addr:street":"Ctra Ribesalbes Km. 0003,0",
    "iso:country":"ES",
    "sg:address":"Ctra Ribesalbes, Km. 0003,0",
    "sg:city":"Castellon De La Plana",
    "sg:orig_category":"Mec\u00c1nico Del Autom\u00d3vil",
    "sg:phone":"+34 964 21 32 00",
    "sg:postcode":"12006",
    "sg:province":"Castell\u00f3n",
    "wof:name":"Badia Gomez Joaquin",
    "wof:placetype":"venue"
},
  "geometry": {"coordinates":[-0.1404139996,40.0213813782],"type":"Point"}
}