{
  "type": "Feature",
  "properties": {
    "addr:full":"Calle de Bailen, 42 Valencia Valencia 46007",
    "addr:housenumber":"42",
    "addr:postcode":"46007",
    "addr:street":"Calle De Bailen",
    "iso:country":"ES",
    "sg:address":"Calle de Bailen, 42",
    "sg:city":"Valencia",
    "sg:orig_category":"Restaurantes",
    "sg:phone":"+34 963 44 95 95",
    "sg:postcode":"46007",
    "sg:province":"Valencia",
    "wof:name":"Bueti Curcio Analia Soledad",
    "wof:placetype":"venue"
},
  "geometry": {"coordinates":[-0.3787471056,39.4650230408],"type":"Point"}
}