{
  "type": "Feature",
  "properties": {
    "addr:full":"Carrer de Moratin, 21 Barcelona Barcelona 08032",
    "addr:housenumber":"21",
    "addr:postcode":"08032",
    "addr:street":"Carrer De Moratin",
    "iso:country":"ES",
    "sg:address":"Carrer de Moratin, 21",
    "sg:city":"Barcelona",
    "sg:orig_category":"Fabricaci\u00d3n De Art\u00cdculos Para Papeler\u00cdas",
    "sg:phone":"+34 934 29 43 51",
    "sg:postcode":"08032",
    "sg:province":"Barcelona",
    "sg:website":"www.schwartz-recycled.com",
    "wof:name":"Sakk Und Sohne S.l",
    "wof:placetype":"venue"
},
  "geometry": {"coordinates":[2.1535320282,41.4249191284],"type":"Point"}
}