{
  "type": "Feature",
  "properties": {
    "addr:full":"Av Corts Catalanes, 545 S. Adria Besos Barcelona 08930",
    "addr:housenumber":"545",
    "addr:postcode":"08930",
    "addr:street":"Av Corts Catalanes;S. Adria Besos Barcelona",
    "iso:country":"ES",
    "sg:address":"Av Corts Catalanes, 545",
    "sg:city":"S. Adria Besos",
    "sg:orig_category":"Carnes De Carnicer\u00cda (al Por Mayor)",
    "sg:phone":"+34 933 81 09 44",
    "sg:postcode":"08930",
    "sg:province":"Barcelona",
    "wof:name":"Cartrad S.a.",
    "wof:placetype":"venue"
},
  "geometry": {"coordinates":[2.2211499214,41.4294815063],"type":"Point"}
}