{
  "type": "Feature",
  "properties": {
    "addr:full":"Zeus, S/n Rojales Alicante 03170",
    "addr:housenumber":"s / n",
    "addr:postcode":"03170",
    "addr:street":"Zeus",
    "iso:country":"ES",
    "sg:address":"Zeus, S/n",
    "sg:city":"Rojales",
    "sg:orig_category":"Asilos De Ancianos. Centros Privados",
    "sg:phone":"+34 966 71 50 71",
    "sg:postcode":"03170",
    "sg:province":"Alicante",
    "wof:name":"Residencia Rojales S.l.",
    "wof:placetype":"venue"
},
  "geometry": {"coordinates":[-0.7082290053,38.0876502991],"type":"Point"}
}