{
  "type": "Feature",
  "properties": {
    "addr:full":"Calle de Rey (del), 41 San Lorenzo De El Escorial Madrid 28200",
    "addr:housenumber":"41",
    "addr:postcode":"28200",
    "addr:street":"Calle De Rey Del",
    "iso:country":"ES",
    "sg:address":"Calle de Rey (del), 41",
    "sg:city":"San Lorenzo De El Escorial",
    "sg:orig_category":"Compraventa De Antig\u00dcedades",
    "sg:phone":"+34 918 90 70 93",
    "sg:postcode":"28200",
    "sg:province":"Madrid",
    "wof:name":"Azama S. A.",
    "wof:placetype":"venue"
},
  "geometry": {"coordinates":[-4.1452002525,40.5909614563],"type":"Point"}
}