{
  "type": "Feature",
  "properties": {
    "addr:full":"Plaz San Andres, 9 Cuellar Segovia 40200",
    "addr:housenumber":"9",
    "addr:postcode":"40200",
    "addr:street":"Plaz San Andres",
    "iso:country":"ES",
    "sg:address":"Plaz San Andres, 9",
    "sg:city":"Cuellar",
    "sg:orig_category":"Charcuter\u00cdas (al Por Mayor)",
    "sg:phone":"+34 921 14 31 62",
    "sg:postcode":"40200",
    "sg:province":"Segovia",
    "wof:name":"Embutidos Y Jamones De Cuellar S.l.",
    "wof:placetype":"venue"
},
  "geometry": {"coordinates":[-4.3167719841,41.4027099609],"type":"Point"}
}