{
  "type": "Feature",
  "properties": {
    "addr:full":"Calle de Santa Catalina, 11 Coru\u00d1a La Coru\u00f1a 15003",
    "addr:housenumber":"11",
    "addr:postcode":"15003",
    "addr:street":"Calle De Santa Catalina;La Corun\u0303A",
    "iso:country":"ES",
    "sg:address":"Calle de Santa Catalina, 11",
    "sg:city":"Coru\u00d1a",
    "sg:orig_category":"Psic\u00d3logos",
    "sg:phone":"+34 981 22 49 61",
    "sg:postcode":"15003",
    "sg:province":"La Coru\u00f1a",
    "wof:name":"Lago Ramos Maria De Los Angeles",
    "wof:placetype":"venue"
},
  "geometry": {"coordinates":[-8.4038801193,43.369720459],"type":"Point"}
}