{
  "type": "Feature",
  "properties": {
    "iso:country":"ES",
    "sg:address":"Parque De Los Enamorados, 15",
    "sg:city":"Iru\u00f1a",
    "sg:orig_category":"Transportes Por Carretera: Lotes Completos, Mercanc\u00cdas Diversas",
    "sg:phone":"+34 948 14 51 94",
    "sg:postcode":"31014",
    "sg:province":"Navarra",
    "wof:name":"Amezqueta Azcarate Pio",
    "wof:placetype":"venue"
},
  "geometry": {"coordinates":[-1.6493531466,42.8251419067],"type":"Point"}
}