{
  "type": "Feature",
  "properties": {
    "iso:country":"ES",
    "sg:address":"Calle de Castillo De Ponferrada, 24",
    "sg:city":"Villafranca Del Castillo-la Mocha Chica",
    "sg:orig_category":"Comit\u00c9s De Organizaci\u00d3n De Exposiciones, Ferias, Salones",
    "sg:phone":"+34 918 15 07 32",
    "sg:postcode":"28692",
    "sg:province":"Madrid",
    "wof:name":"Comunicacion Dinamica Y Marketing S.a.",
    "wof:placetype":"venue"
},
  "geometry": {"coordinates":[-3.9509994984,40.4667625427],"type":"Point"}
}