{
  "type": "Feature",
  "properties": {
    "addr:full":"Calle de Capitan Francisco Sanchez (del), 1 Alcobendas Madrid 28100",
    "addr:postcode":"28100",
    "addr:street":"Calle De Capitan Francisco Sanchez Del;Alcobendas",
    "iso:country":"ES",
    "sg:address":"Calle de Capitan Francisco Sanchez (del), 1",
    "sg:city":"Alcobendas",
    "sg:orig_category":"Parques De Atracciones Y Centros De Esparcimiento",
    "sg:phone":"+34 916 52 52 87",
    "sg:postcode":"28100",
    "sg:province":"Madrid",
    "wof:name":"Recreativos Gonzalez Garcia S.l.",
    "wof:placetype":"venue"
},
  "geometry": {"coordinates":[-3.6337594986,40.5409927368],"type":"Point"}
}