{
  "type": "Feature",
  "properties": {
    "iso:country":"ES",
    "sg:address":"Avda Alfonso Xiii, 9",
    "sg:city":"Elda",
    "sg:orig_category":"Maquinaria Para Industrias Diversas",
    "sg:phone":"+34 965 39 93 80",
    "sg:postcode":"03600",
    "sg:province":"Alicante",
    "wof:name":"Jumarcal S.l.",
    "wof:placetype":"venue"
},
  "geometry": {"coordinates":[-0.7984570265,38.4732017517],"type":"Point"}
}