{
  "type": "Feature",
  "properties": {
    "addr:full":"Calle de Benavente, 80 Puertollano Ciudad Real 13500",
    "addr:housenumber":"80",
    "addr:postcode":"13500",
    "addr:street":"Calle De Benavente",
    "iso:country":"ES",
    "sg:address":"Calle de Benavente, 80",
    "sg:city":"Puertollano",
    "sg:orig_category":"Muebles, Minoristas",
    "sg:phone":"+34 926 41 10 36",
    "sg:postcode":"13500",
    "sg:province":"Ciudad Real",
    "wof:name":"Pa\u00f1os Lopez-barrajon Bernardo",
    "wof:placetype":"venue"
},
  "geometry": {"coordinates":[-4.100165844,38.6826629639],"type":"Point"}
}