{
  "type": "Feature",
  "properties": {
    "iso:country":"ES",
    "sg:address":"Luga Pename, 15",
    "sg:city":"Pazos",
    "sg:orig_category":"Equitaci\u00d3n Y Centros De H\u00cdpica",
    "sg:phone":"+34 981 38 71 65",
    "sg:postcode":"15510",
    "sg:province":"La Coru\u00f1a",
    "wof:name":"Pename S.l.",
    "wof:placetype":"venue"
},
  "geometry": {"coordinates":[-8.1511478424,43.512386322],"type":"Point"}
}