{
  "type": "Feature",
  "properties": {
    "addr:full":"Av Puerta Del Mar, 42 Estepona M\u00e1laga 29680",
    "addr:housenumber":"42",
    "addr:postcode":"29680",
    "addr:street":"Av Puerta Del Mar",
    "iso:country":"ES",
    "sg:address":"Av Puerta Del Mar, 42",
    "sg:city":"Estepona",
    "sg:orig_category":"Centros Empresariales",
    "sg:phone":"+34 952 93 65 80",
    "sg:postcode":"29680",
    "sg:province":"M\u00e1laga",
    "wof:name":"Dubowska  Teresa Elisabeth",
    "wof:placetype":"venue"
},
  "geometry": {"coordinates":[-5.1452140808,36.4275817871],"type":"Point"}
}