{
  "type": "Feature",
  "properties": {
    "iso:country":"ES",
    "sg:address":"Avda 2 De Mayo, 30",
    "sg:city":"Mocejon",
    "sg:orig_category":"Abogados",
    "sg:phone":"+34 925 27 04 86",
    "sg:postcode":"45270",
    "sg:province":"Toledo",
    "wof:name":"Rodriguez Benitez Maria Cristina",
    "wof:placetype":"venue"
},
  "geometry": {"coordinates":[-3.9195990562,39.937046051],"type":"Point"}
}