{
  "type": "Feature",
  "properties": {
    "addr:full":"Calle de Uria, 24 Gijon Asturias 33202",
    "addr:housenumber":"24",
    "addr:postcode":"33202",
    "addr:street":"Calle De Uria",
    "iso:country":"ES",
    "sg:address":"Calle de Uria, 24",
    "sg:city":"Gijon",
    "sg:orig_category":"Perfumer\u00cda (al Por Menor)",
    "sg:phone":"+34 985 36 25 36",
    "sg:postcode":"33202",
    "sg:province":"Asturias",
    "wof:name":"Viejo Fernandez-asenjo Julio Juan",
    "wof:placetype":"venue"
},
  "geometry": {"coordinates":[-5.6558728218,43.5385971069],"type":"Point"}
}