{
  "type": "Feature",
  "properties": {
    "addr:full":"Monasterio Tulebras, 3 Iru\u00f1a Navarra 31011",
    "addr:housenumber":"3",
    "addr:postcode":"31011",
    "addr:street":"Tulebras",
    "iso:country":"ES",
    "sg:address":"Monasterio Tulebras, 3",
    "sg:city":"Iru\u00f1a",
    "sg:orig_category":"Ense\u00d1anza, Formaci\u00d3n Profesional: Aprendizaje",
    "sg:phone":"+34 948 25 10 12",
    "sg:postcode":"31011",
    "sg:province":"Navarra",
    "wof:name":"Ayuntamiento De Pamplona",
    "wof:placetype":"venue"
},
  "geometry": {"coordinates":[-1.6559944153,42.8140449524],"type":"Point"}
}