{
  "type": "Feature",
  "properties": {
    "iso:country":"ES",
    "sg:address":"Plaz Roma, 5",
    "sg:city":"Tordesillas",
    "sg:orig_category":"Alimentaci\u00d3n General (al Por Menor)",
    "sg:phone":"+34 983 77 06 09",
    "sg:postcode":"47100",
    "sg:province":"Valladolid",
    "wof:name":"Sanz Gonzalez Maria Del Carmen",
    "wof:placetype":"venue"
},
  "geometry": {"coordinates":[-4.9989957809,41.5035095215],"type":"Point"}
}