{
  "type": "Feature",
  "properties": {
    "iso:country":"ES",
    "sg:address":"Calle de Nogal (el), 9",
    "sg:city":"Callejones-san Silvestre",
    "sg:orig_category":"Fabricaci\u00d3n, Venta De Cuadros, Accesorios Para Enmarcar",
    "sg:phone":"+34 950 14 37 11",
    "sg:postcode":"04230",
    "sg:province":"Almer\u00eda",
    "wof:name":"Industrias Indamol Almeria S.l.",
    "wof:placetype":"venue"
},
  "geometry": {"coordinates":[-2.4478240013,36.8712463379],"type":"Point"}
}