{
  "type": "Feature",
  "properties": {
    "addr:full":"Calle de Soledad, 29 Campo Criptana Ciudad Real 13610",
    "addr:housenumber":"29",
    "addr:postcode":"13610",
    "addr:street":"Calle De Soledad;Criptana",
    "iso:country":"ES",
    "sg:address":"Calle de Soledad, 29",
    "sg:city":"Campo Criptana",
    "sg:orig_category":"Supermercados Y Hipermercados",
    "sg:phone":"+34 926 56 31 57",
    "sg:postcode":"13610",
    "sg:province":"Ciudad Real",
    "wof:name":"Supermercado Campoamor S.l.",
    "wof:placetype":"venue"
},
  "geometry": {"coordinates":[-3.1279566288,39.4057235718],"type":"Point"}
}