{
  "type": "Feature",
  "properties": {
    "iso:country":"ES",
    "sg:address":"Calle de Real, 6",
    "sg:city":"Robla",
    "sg:orig_category":"Explotaci\u00d3n De Canteras",
    "sg:phone":"+34 987 57 05 33",
    "sg:postcode":"24640",
    "sg:province":"Le\u00f3n",
    "wof:name":"Magil",
    "wof:placetype":"venue"
},
  "geometry": {"coordinates":[-5.6295390129,42.7999610901],"type":"Point"}
}