{
  "type": "Feature",
  "properties": {
    "iso:country":"ES",
    "sg:address":"Pl Espanya Pl De La Bascula, 10",
    "sg:city":"Molins Rei",
    "sg:orig_category":"\u00d3ptica: Instrumentos (fabricaci\u00d3n)",
    "sg:phone":"+34 936 80 32 42",
    "sg:postcode":"08750",
    "sg:province":"Barcelona",
    "wof:name":"Josa Optica Y Fotografia S. A.",
    "wof:placetype":"venue"
},
  "geometry": {"coordinates":[2.0164849758,41.414604187],"type":"Point"}
}