{
  "type": "Feature",
  "properties": {
    "addr:full":"Rua Emilia Pardo Bazan, 3 Celanova Ourense 32800",
    "addr:housenumber":"3",
    "addr:postcode":"32800",
    "addr:street":"Rua Emilia Pardo Bazan",
    "iso:country":"ES",
    "sg:address":"Rua Emilia Pardo Bazan, 3",
    "sg:city":"Celanova",
    "sg:orig_category":"Art\u00cdculos De Decoraci\u00d3n",
    "sg:phone":"+34 988 43 15 35",
    "sg:postcode":"32800",
    "sg:province":"Ourense",
    "wof:name":"Perez Martinez Castor",
    "wof:placetype":"venue"
},
  "geometry": {"coordinates":[-7.95789814,42.1526451111],"type":"Point"}
}