{
  "type": "Feature",
  "properties": {
    "addr:full":"Calle de Embajador Vich, 11 Valencia Valencia 46002",
    "addr:housenumber":"11",
    "addr:postcode":"46002",
    "addr:street":"Calle De Embajador Vich",
    "iso:country":"ES",
    "sg:address":"Calle de Embajador Vich, 11",
    "sg:city":"Valencia",
    "sg:orig_category":"Asistencia Domiciliaria",
    "sg:phone":"+34 963 94 05 40",
    "sg:postcode":"46002",
    "sg:province":"Valencia",
    "wof:name":"Giner Martinez Maria Estrella",
    "wof:placetype":"venue"
},
  "geometry": {"coordinates":[-0.3755199909,39.4720344543],"type":"Point"}
}