{
  "type": "Feature",
  "properties": {
    "iso:country":"ES",
    "sg:address":"Carr Valls D'andorra, 61",
    "sg:city":"Lleida",
    "sg:orig_category":"Desinfecci\u00d3n, Desinsectaci\u00d3n, Desratizaci\u00d3n",
    "sg:phone":"+34 973 22 44 88",
    "sg:postcode":"25005",
    "sg:province":"Lleida",
    "wof:name":"Cortes Mir Javier",
    "wof:placetype":"venue"
},
  "geometry": {"coordinates":[0.6206960082,41.6311912537],"type":"Point"}
}