{
  "type": "Feature",
  "properties": {
    "iso:country":"ES",
    "sg:address":"Calle de Hernan Perez Del Pulgar, 6",
    "sg:city":"Ciudad Real",
    "sg:orig_category":"Locales Y Clases De Danza",
    "sg:phone":"+34 926 22 35 18",
    "sg:postcode":"13001",
    "sg:province":"Ciudad Real",
    "wof:name":"Estudios Artisticos Y Culturales S.l.",
    "wof:placetype":"venue"
},
  "geometry": {"coordinates":[-3.9269580841,38.9833183289],"type":"Point"}
}