{
  "type": "Feature",
  "properties": {
    "addr:full":"Cost Brossa, 6 Palma Islas Baleares 07001",
    "addr:housenumber":"6",
    "addr:postcode":"07001",
    "addr:street":"Brossa",
    "iso:country":"ES",
    "sg:address":"Cost Brossa, 6",
    "sg:city":"Palma",
    "sg:orig_category":"Psic\u00d3logos",
    "sg:phone":"+34 971 71 25 67",
    "sg:postcode":"07001",
    "sg:province":"Islas Baleares",
    "wof:name":"Misinew S.l.",
    "wof:placetype":"venue"
},
  "geometry": {"coordinates":[2.6493639946,39.5702667236],"type":"Point"}
}