{
  "type": "Feature",
  "properties": {
    "addr:full":"Avda Rio Segura (del), S/n Abaran Murcia 30550",
    "addr:postcode":"30550",
    "addr:street":"Avda Rio Segura Del S / N",
    "iso:country":"ES",
    "sg:address":"Avda Rio Segura (del), S/n",
    "sg:city":"Abaran",
    "sg:orig_category":"Delegados, Agentes De Tr\u00c1nsito, Auxiliares De Transporte Internacional",
    "sg:phone":"+34 968 77 05 07",
    "sg:postcode":"30550",
    "sg:province":"Murcia",
    "wof:name":"Verdejo Moreno Ascension",
    "wof:placetype":"venue"
},
  "geometry": {"coordinates":[-1.3940889835,38.2038345337],"type":"Point"}
}