{
  "type": "Feature",
  "properties": {
    "addr:full":"Calle de Canarias, 27 Jerez De La Frontera C\u00e1diz 11408",
    "addr:housenumber":"27",
    "addr:postcode":"11408",
    "addr:street":"Calle De Canarias",
    "iso:country":"ES",
    "sg:address":"Calle de Canarias, 27",
    "sg:city":"Jerez De La Frontera",
    "sg:orig_category":"Mantenimiento Y Limpieza De Carreteras",
    "sg:phone":"+34 956 14 20 83",
    "sg:postcode":"11408",
    "sg:province":"C\u00e1diz",
    "wof:name":"Lopez Morales Maria Del Rocio",
    "wof:placetype":"venue"
},
  "geometry": {"coordinates":[-6.1356329918,36.6724319458],"type":"Point"}
}