{
  "type": "Feature",
  "properties": {
    "addr:full":"Herrerieta Kalea, 5 Getaria Guip\u00f9zcoa 20808",
    "addr:housenumber":"5",
    "addr:postcode":"20808",
    "addr:street":"Herrerieta Kalea;Guipu\u0300Zcoa",
    "iso:country":"ES",
    "sg:address":"Herrerieta Kalea, 5",
    "sg:city":"Getaria",
    "sg:orig_category":"Molduras, Junquillos, Listones Y Molduras Perforadas",
    "sg:phone":"+34 943 14 01 76",
    "sg:postcode":"20808",
    "sg:province":"Guip\u00f9zcoa",
    "wof:name":"Larra\u00f1aga Azcue Ana Jesus",
    "wof:placetype":"venue"
},
  "geometry": {"coordinates":[-2.2056200504,43.3029403687],"type":"Point"}
}