{
  "type": "Feature",
  "properties": {
    "iso:country":"ES",
    "sg:address":"Joaquin Larregla, 10",
    "sg:city":"Iru\u00f1a",
    "sg:orig_category":"Encuadernaci\u00d3n E Impresi\u00d3n De Folletos",
    "sg:phone":"+34 948 24 79 98",
    "sg:postcode":"31005",
    "sg:province":"Navarra",
    "wof:name":"Blasco Garcia Carlos",
    "wof:placetype":"venue"
},
  "geometry": {"coordinates":[-1.6408820152,42.8062820435],"type":"Point"}
}