{
  "type": "Feature",
  "properties": {
    "addr:full":"Calle de Casta\u00d1uelos, 5 Candeleda \u00c1vila 05480",
    "addr:housenumber":"5",
    "addr:postcode":"05480",
    "addr:street":"Calle De Castan\u0303Uelos",
    "iso:country":"ES",
    "sg:address":"Calle de Casta\u00d1uelos, 5",
    "sg:city":"Candeleda",
    "sg:orig_category":"Plomeros",
    "sg:phone":"+34 920 38 02 11",
    "sg:postcode":"05480",
    "sg:province":"\u00c1vila",
    "wof:name":"Garcia Blazquez Emilio",
    "wof:placetype":"venue"
},
  "geometry": {"coordinates":[-5.2397379875,40.1566886902],"type":"Point"}
}