{
  "type": "Feature",
  "properties": {
    "iso:country":"ES",
    "sg:address":"Rua Marques De Rodil, 14",
    "sg:city":"Fonsagrada",
    "sg:orig_category":"Doctores En Medicina",
    "sg:phone":"+34 982 34 00 97",
    "sg:postcode":"27100",
    "sg:province":"Lugo",
    "wof:name":"Barreira Fernandez Maria Del Pilar",
    "wof:placetype":"venue"
},
  "geometry": {"coordinates":[-7.0673189163,43.125995636],"type":"Point"}
}