{
  "type": "Feature",
  "properties": {
    "addr:full":"Calle de Calvario, 2 Zubia Granada 18140",
    "addr:housenumber":"2",
    "addr:postcode":"18140",
    "addr:street":"Calle De Calvario",
    "iso:country":"ES",
    "sg:address":"Calle de Calvario, 2",
    "sg:city":"Zubia",
    "sg:orig_category":"Molduras, Junquillos, Listones Y Molduras Perforadas",
    "sg:phone":"+34 958 59 09 97",
    "sg:postcode":"18140",
    "sg:province":"Granada",
    "wof:name":"Gamez Lopez Francisco",
    "wof:placetype":"venue"
},
  "geometry": {"coordinates":[-3.5818483829,37.1194839478],"type":"Point"}
}