{
  "type": "Feature",
  "properties": {
    "iso:country":"ES",
    "sg:address":"Pase Santa Maria De La Cabeza, 42",
    "sg:city":"Madrid",
    "sg:orig_category":"Administradores De Bienes Y Delegados De Comunidades De Propietarios",
    "sg:phone":"+34 915 30 22 23",
    "sg:postcode":"28045",
    "sg:province":"Madrid",
    "wof:name":"Moreno Malaga Francisco Javier",
    "wof:placetype":"venue"
},
  "geometry": {"coordinates":[-3.6967430115,40.4039421082],"type":"Point"}
}