{
  "type": "Feature",
  "properties": {
    "iso:country":"ES",
    "sg:address":"Carrer de Can Camps, 15",
    "sg:city":"Torre-romeu",
    "sg:orig_category":"Transporte En General",
    "sg:phone":"+34 937 45 70 07",
    "sg:postcode":"08203",
    "sg:province":"Barcelona",
    "wof:name":"Disnet Sistemas De Distribucion S.a.",
    "wof:placetype":"venue"
},
  "geometry": {"coordinates":[2.1460180283,41.4136962891],"type":"Point"}
}