{
  "type": "Feature",
  "properties": {
    "iso:country":"ES",
    "sg:address":"Rua Marques De Riestra, 32",
    "sg:city":"Pontevedra",
    "sg:orig_category":"Graf\u00d3logos",
    "sg:phone":"+34 986 86 31 22",
    "sg:postcode":"36002",
    "sg:province":"Pontevedra",
    "sg:website":"www.ryrabogados.com",
    "wof:name":"Rivas Teruelo Carlos",
    "wof:placetype":"venue"
},
  "geometry": {"coordinates":[-8.6466093063,42.4309806824],"type":"Point"}
}