{
  "type": "Feature",
  "properties": {
    "iso:country":"ES",
    "sg:address":"Avda Constitucion, 12",
    "sg:city":"Valencia",
    "sg:orig_category":"Estudios, Instalaci\u00d3n De Climatizaci\u00d3n",
    "sg:phone":"+34 963 48 29 75",
    "sg:postcode":"46009",
    "sg:province":"Valencia",
    "wof:name":"Fricli S.l.",
    "wof:placetype":"venue"
},
  "geometry": {"coordinates":[-0.3786250055,39.4841995239],"type":"Point"}
}