{
  "type": "Feature",
  "properties": {
    "addr:full":"Calle de Jose Jauregui, 7 Salamanca Salamanca 37002",
    "addr:housenumber":"7",
    "addr:postcode":"37002",
    "addr:street":"Calle De Jose Jauregui",
    "iso:country":"ES",
    "sg:address":"Calle de Jose Jauregui, 7",
    "sg:city":"Salamanca",
    "sg:orig_category":"Fabricaci\u00d3n De Sobres, Bolsas Y Fundas",
    "sg:phone":"+34 923 26 00 58",
    "sg:postcode":"37002",
    "sg:province":"Salamanca",
    "wof:name":"Gonzalez Maillo Olvido",
    "wof:placetype":"venue"
},
  "geometry": {"coordinates":[-5.6627950668,40.9694671631],"type":"Point"}
}