{
  "type": "Feature",
  "properties": {
    "iso:country":"ES",
    "sg:address":"J. Espada, 21",
    "sg:city":"Cartagena",
    "sg:orig_category":"Inform\u00c1tica: Soportes De Informaci\u00d3n, Suministros & Accesorios",
    "sg:phone":"+34 968 12 08 62",
    "sg:postcode":"30204",
    "sg:province":"Murcia",
    "wof:name":"Tecniprint Consumibles Impresora S.l.",
    "wof:placetype":"venue"
},
  "geometry": {"coordinates":[-0.9877589941,37.6067504883],"type":"Point"}
}