{
  "type": "Feature",
  "properties": {
    "addr:full":"Ctra. Granada, S/n Diezma Granada 18180",
    "addr:postcode":"18180",
    "addr:street":"Ctra. Granada S / N",
    "iso:country":"ES",
    "sg:address":"Ctra. Granada, S/n",
    "sg:city":"Diezma",
    "sg:orig_category":"Discotecas Y Salas De Baile",
    "sg:phone":"+34 958 68 01 20",
    "sg:postcode":"18180",
    "sg:province":"Granada",
    "wof:name":"Fercotel Explotacion De Telefonos Publicos S.l.",
    "wof:placetype":"venue"
},
  "geometry": {"coordinates":[-3.3351769447,37.3206710815],"type":"Point"}
}