{
  "type": "Feature",
  "properties": {
    "iso:country":"ES",
    "sg:address":"Calle de Doctor Fleming, 4",
    "sg:city":"Tavernes Blanques",
    "sg:orig_category":"Promotores Constructores",
    "sg:phone":"+34 961 85 94 26",
    "sg:postcode":"46016",
    "sg:province":"Valencia",
    "wof:name":"Aatt Manuel Sanchez S.l.",
    "wof:placetype":"venue"
},
  "geometry": {"coordinates":[-0.365518,39.510586],"type":"Point"}
}