{
  "type": "Feature",
  "properties": {
    "iso:country":"ES",
    "sg:address":"Carrer de Cast Oliver, S/n",
    "sg:city":"Garriga",
    "sg:orig_category":"Entrega Y Recogida (servicios)",
    "sg:phone":"+34 938 71 57 66",
    "sg:postcode":"08530",
    "sg:province":"Barcelona",
    "wof:name":"Cuenca Domingo Manuel",
    "wof:placetype":"venue"
},
  "geometry": {"coordinates":[2.2868950367,41.677230835],"type":"Point"}
}