{
  "type": "Feature",
  "properties": {
    "iso:country":"ES",
    "sg:address":"Rio De La Villa (p I Antequera), 3",
    "sg:city":"Antequera",
    "sg:orig_category":"Fabricaci\u00d3n De Enlosados, Soler\u00cdas",
    "sg:phone":"+34 952 84 37 51",
    "sg:postcode":"29200",
    "sg:province":"M\u00e1laga",
    "sg:website":"www.porcelanosa.com",
    "wof:name":"Mericer S.a.",
    "wof:placetype":"venue"
},
  "geometry": {"coordinates":[-4.5211935043,36.9971008301],"type":"Point"}
}