{
  "type": "Feature",
  "properties": {
    "iso:country":"ES",
    "sg:address":"Iglesia, 1",
    "sg:city":"Juviles",
    "sg:orig_category":"Administraciones Regionales, Departamentales Y Locales",
    "sg:phone":"+34 958 76 90 32",
    "sg:postcode":"18452",
    "sg:province":"Granada",
    "wof:name":"Ayuntamiento",
    "wof:placetype":"venue"
},
  "geometry": {"coordinates":[-3.2251417637,36.9483070374],"type":"Point"}
}