{
  "type": "Feature",
  "properties": {
    "iso:country":"ES",
    "sg:address":"Avda Arroyo De Los Angeles, 87",
    "sg:city":"Malaga",
    "sg:orig_category":"Agencias Y Agentes Comerciales, Representantes",
    "sg:phone":"+34 952 39 01 46",
    "sg:postcode":"29011",
    "sg:province":"M\u00e1laga",
    "wof:name":"Ramos Castro Miguel Angel",
    "wof:placetype":"venue"
},
  "geometry": {"coordinates":[-4.4359741211,36.7308311462],"type":"Point"}
}