{
  "type": "Feature",
  "properties": {
    "iso:country":"ES",
    "sg:address":"Avda Isabel De Moctezuma, 1",
    "sg:city":"Caceres",
    "sg:orig_category":"Centros Comerciales Y Grandes Tiendas",
    "sg:phone":"+34 927 22 09 59",
    "sg:postcode":"10005",
    "sg:province":"C\u00e1ceres",
    "wof:name":"Vivas Franco Julio",
    "wof:placetype":"venue"
},
  "geometry": {"coordinates":[-6.3790106773,39.4658813477],"type":"Point"}
}