{
  "type": "Feature",
  "properties": {
    "iso:country":"ES",
    "sg:address":"Ctra Pulgara, S/n",
    "sg:city":"Santa Quiteria",
    "sg:orig_category":"Centros Empresariales",
    "sg:phone":"+34 968 47 26 52",
    "sg:postcode":"30800",
    "sg:province":"Murcia",
    "wof:name":"Asesoramiento Y Gestion Servicios Union S.l.",
    "wof:placetype":"venue"
},
  "geometry": {"coordinates":[-1.1298867464,37.9834747314],"type":"Point"}
}