{
  "type": "Feature",
  "properties": {
    "addr:full":"Calle de Jupiter, 7 Madrid Madrid 28042",
    "addr:housenumber":"7",
    "addr:postcode":"madrid;28042",
    "addr:street":"Calle De Jupiter",
    "iso:country":"ES",
    "sg:address":"Calle de Jupiter, 7",
    "sg:city":"Madrid",
    "sg:orig_category":"Sindicatos De Trabajadores",
    "sg:phone":"+34 913 05 62 72",
    "sg:postcode":"28042",
    "sg:province":"Madrid",
    "wof:name":"Sindicato De Tripulantes Auxiliares De Vuelo De Lineas Aereas",
    "wof:placetype":"venue"
},
  "geometry": {"coordinates":[-3.5806798935,40.4758529663],"type":"Point"}
}