{
  "type": "Feature",
  "properties": {
    "iso:country":"ES",
    "sg:address":"Rua Rio Xubia, 153",
    "sg:city":"Ferrol",
    "sg:orig_category":"Electrodom\u00c9sticos (fabricaci\u00d3n, Al Por Mayor)",
    "sg:phone":"+34 981 31 99 93",
    "sg:postcode":"15403",
    "sg:province":"A Coru\u00f1a",
    "wof:name":"Teijeiro Carnero Aurelia",
    "wof:placetype":"venue"
},
  "geometry": {"coordinates":[-8.2221393585,43.492351532],"type":"Point"}
}