{
  "type": "Feature",
  "properties": {
    "iso:country":"ES",
    "sg:address":"Calle de San Vicente, 17",
    "sg:city":"Sevilla",
    "sg:orig_category":"Fotogrametr\u00cda",
    "sg:phone":"+34 954 90 21 81",
    "sg:postcode":"41002",
    "sg:province":"Sevilla",
    "wof:name":"Restisur S.l.",
    "wof:placetype":"venue"
},
  "geometry": {"coordinates":[-5.999475956,37.3936653137],"type":"Point"}
}