{
  "type": "Feature",
  "properties": {
    "iso:country":"ES",
    "sg:address":"Calle de Mayor, S/n",
    "sg:city":"Bascones De Ojeda",
    "sg:orig_category":"Promotores Constructores",
    "sg:phone":"+34 979 89 60 62",
    "sg:postcode":"34406",
    "sg:province":"Palencia",
    "wof:name":"Cosgaya Bravo Antonio",
    "wof:placetype":"venue"
},
  "geometry": {"coordinates":[-4.5260457993,42.6728553772],"type":"Point"}
}