{
  "type": "Feature",
  "properties": {
    "addr:full":"Calle de Atair, 29 Zaragoza Zaragoza 50012",
    "addr:housenumber":"29",
    "addr:postcode":"50012",
    "addr:street":"Calle De Atair",
    "iso:country":"ES",
    "sg:address":"Calle de Atair, 29",
    "sg:city":"Zaragoza",
    "sg:orig_category":"Electromedicina: Servicios",
    "sg:phone":"+34 976 75 17 68",
    "sg:postcode":"50012",
    "sg:province":"Zaragoza",
    "sg:website":"www.intechsl.com",
    "wof:name":"Ingenieria Tecnica Hospitalaria S.l.",
    "wof:placetype":"venue"
},
  "geometry": {"coordinates":[-0.9361407757,41.6392211914],"type":"Point"}
}