{
  "type": "Feature",
  "properties": {
    "addr:full":"Calle de San Jorge, 6 Zaragoza Zaragoza 50001",
    "addr:housenumber":"6",
    "addr:postcode":"50001",
    "addr:street":"Calle De San Jorge",
    "iso:country":"ES",
    "sg:address":"Calle de San Jorge, 6",
    "sg:city":"Zaragoza",
    "sg:orig_category":"Molduras, Junquillos, Listones Y Molduras Perforadas",
    "sg:phone":"+34 976 39 62 56",
    "sg:postcode":"50001",
    "sg:province":"Zaragoza",
    "wof:name":"Cafe Bar La Bodeguilla Del Arco S.l.",
    "wof:placetype":"venue"
},
  "geometry": {"coordinates":[-0.8779889941,41.6529388428],"type":"Point"}
}