{
  "type": "Feature",
  "properties": {
    "iso:country":"ES",
    "sg:address":"Carrer de Francesc Pi I Marg, 11",
    "sg:city":"Palma",
    "sg:orig_category":"Estancos",
    "sg:phone":"+34 971 27 66 35",
    "sg:postcode":"07007",
    "sg:province":"Islas Baleares",
    "wof:name":"Gomis Bauza Gabriel",
    "wof:placetype":"venue"
},
  "geometry": {"coordinates":[2.666023016,39.5723304749],"type":"Point"}
}