{
  "type": "Feature",
  "properties": {
    "iso:country":"ES",
    "sg:address":"Calle de San Jose, 75",
    "sg:city":"Gijon",
    "sg:orig_category":"Carb\u00d3n, Carb\u00d3n De Madera (al Por Mayor)",
    "sg:phone":"+34 985 38 68 56",
    "sg:postcode":"33208",
    "sg:province":"Asturias",
    "wof:name":"Fernandez Alvarez Ricardo",
    "wof:placetype":"venue"
},
  "geometry": {"coordinates":[-5.664659977,43.5339889526],"type":"Point"}
}