{
  "type": "Feature",
  "properties": {
    "iso:country":"ES",
    "sg:address":"Avda Paz (la), S/n",
    "sg:city":"Tamarite Litera",
    "sg:orig_category":"Insecticidas, Fumigaci\u00d3n",
    "sg:phone":"+34 974 42 19 42",
    "sg:postcode":"22550",
    "sg:province":"Huesca",
    "wof:name":"Agroquimicos Villacampa S.a",
    "wof:placetype":"venue"
},
  "geometry": {"coordinates":[0.4232487977,41.8623924255],"type":"Point"}
}