{
  "type": "Feature",
  "properties": {
    "addr:full":"Pla\u00c7 Llevant, 8 Roses Girona 17480",
    "addr:postcode":"17480",
    "iso:country":"ES",
    "sg:address":"Pla\u00c7 Llevant, 8",
    "sg:city":"Roses",
    "sg:orig_category":"Ropa Para Ni\u00d1os (al Por Menor)",
    "sg:phone":"+34 972 15 00 35",
    "sg:postcode":"17480",
    "sg:province":"Girona",
    "wof:name":"Pages Duran Montserrat",
    "wof:placetype":"venue"
},
  "geometry": {"coordinates":[3.1806840897,42.2613830566],"type":"Point"}
}