{
  "type": "Feature",
  "properties": {
    "iso:country":"ES",
    "sg:address":"Calle de Godofredo Ortega Y Mu\u00d1oz, 1",
    "sg:city":"Badajoz",
    "sg:orig_category":"Ense\u00d1anza, Formaci\u00d3n Profesional: Aprendizaje",
    "sg:phone":"+34 924 22 38 91",
    "sg:postcode":"06011",
    "sg:province":"Badajoz",
    "wof:name":"Apesex",
    "wof:placetype":"venue"
},
  "geometry": {"coordinates":[-6.9816040993,38.8698883057],"type":"Point"}
}