{
  "type": "Feature",
  "properties": {
    "addr:full":"Pol Ind Sete Pias, 55 Cereixeira Pontevedra 36635",
    "addr:housenumber":"55",
    "addr:postcode":"36635",
    "addr:street":"Pias",
    "iso:country":"ES",
    "sg:address":"Pol Ind Sete Pias, 55",
    "sg:city":"Cereixeira",
    "sg:orig_category":"Hilaturas, Hilos Y Actividades Relacionadas",
    "sg:phone":"+34 986 54 33 12",
    "sg:postcode":"36635",
    "sg:province":"Pontevedra",
    "wof:name":"Acha Cores Gonzalo",
    "wof:placetype":"venue"
},
  "geometry": {"coordinates":[-8.6480531693,42.4336204529],"type":"Point"}
}