{
  "type": "Feature",
  "properties": {
    "iso:country":"ES",
    "sg:address":"Calle de Esparteros, 16",
    "sg:city":"Madrid",
    "sg:orig_category":"Talleres: Ropa A Medida",
    "sg:phone":"+34 915 31 36 56",
    "sg:postcode":"28012",
    "sg:province":"Madrid",
    "wof:name":"Herguera Zurro Alejandro",
    "wof:placetype":"venue"
},
  "geometry": {"coordinates":[-3.7055559158,40.4155235291],"type":"Point"}
}