{
  "type": "Feature",
  "properties": {
    "addr:full":"Ctra. Parlava, S/n Serra Daro Girona 17133",
    "addr:housenumber":"s",
    "addr:postcode":"17133",
    "addr:street":"Ctra. Parlava;/ N",
    "iso:country":"ES",
    "sg:address":"Ctra. Parlava, S/n",
    "sg:city":"Serra Daro",
    "sg:orig_category":"Trabajos De Perforaciones, Sondeos, Construcci\u00d3n De Pozos",
    "sg:phone":"+34 972 75 87 57",
    "sg:postcode":"17133",
    "sg:province":"Girona",
    "wof:name":"Barris Bohigas Juan",
    "wof:placetype":"venue"
},
  "geometry": {"coordinates":[3.0319728851,42.0231246948],"type":"Point"}
}