{
  "type": "Feature",
  "properties": {
    "iso:country":"ES",
    "sg:address":"Calle de Miguel Servet, 11",
    "sg:city":"Monzon",
    "sg:orig_category":"Carnicer\u00cdas, Carnicer\u00cdas",
    "sg:phone":"+34 974 40 03 94",
    "sg:postcode":"22400",
    "sg:province":"Huesca",
    "wof:name":"Cazcarra Biel Jose Luis",
    "wof:placetype":"venue"
},
  "geometry": {"coordinates":[0.191662997,41.9108963013],"type":"Point"}
}