{
  "type": "Feature",
  "properties": {
    "iso:country":"ES",
    "sg:address":"Calle de Sagrada (la) (garrapinillos), 20",
    "sg:city":"Garrapinillos",
    "sg:orig_category":"Supermercados Y Hipermercados",
    "sg:phone":"+34 976 78 01 00",
    "sg:postcode":"50190",
    "sg:province":"Zaragoza",
    "wof:name":"Day Support S.l.",
    "wof:placetype":"venue"
},
  "geometry": {"coordinates":[-1.0262089968,41.6816711426],"type":"Point"}
}