{
  "type": "Feature",
  "properties": {
    "iso:country":"ES",
    "sg:address":"Urb. Edif. Tarifa Playa, 15",
    "sg:city":"Tarifa",
    "sg:orig_category":"Abogados",
    "sg:phone":"+34 956 68 22 32",
    "sg:postcode":"11380",
    "sg:province":"C\u00e1diz",
    "wof:name":"Guerrero Aznar Aurelia",
    "wof:placetype":"venue"
},
  "geometry": {"coordinates":[-5.6030340195,36.0151596069],"type":"Point"}
}