{
  "type": "Feature",
  "properties": {
    "addr:full":"Avda Rosa De Los Vientos, 19 San Gabriel Alicante 03710",
    "addr:housenumber":"19",
    "addr:postcode":"03710",
    "addr:street":"Avda Rosa De Los Vientos",
    "iso:country":"ES",
    "sg:address":"Avda Rosa De Los Vientos, 19",
    "sg:city":"San Gabriel",
    "sg:orig_category":"Caf\u00c9s, Bares, Cervecer\u00cdas",
    "sg:phone":"+34 965 83 98 96",
    "sg:postcode":"03710",
    "sg:province":"Alicante",
    "wof:name":"Blanco Garcia Antonio",
    "wof:placetype":"venue"
},
  "geometry": {"coordinates":[0.0535200015,38.6515808105],"type":"Point"}
}