{
  "type": "Feature",
  "properties": {
    "iso:country":"ES",
    "sg:address":"Calle de Grande, 24",
    "sg:city":"Calahorra",
    "sg:orig_category":"Librer\u00cdas",
    "sg:phone":"+34 941 13 12 86",
    "sg:postcode":"26500",
    "sg:province":"La Rioja",
    "wof:name":"Muro Ovejas Sara",
    "wof:placetype":"venue"
},
  "geometry": {"coordinates":[-1.9624240398,42.3018836975],"type":"Point"}
}