{
  "type": "Feature",
  "properties": {
    "iso:country":"ES",
    "sg:address":"Calle de Aguado, 3",
    "sg:city":"Gijon",
    "sg:orig_category":"M\u00c9dicos: Medicina General Orientada A La Acupuntura",
    "sg:phone":"+34 984 19 12 84",
    "sg:postcode":"33203",
    "sg:province":"Asturias",
    "wof:name":"Song Kang Sukmyung",
    "wof:placetype":"venue"
},
  "geometry": {"coordinates":[-5.6502494812,43.5375862122],"type":"Point"}
}