{
  "type": "Feature",
  "properties": {
    "addr:full":"Calle de Pe\u00d1a Trevinca, 27 Zamora Zamora 49023",
    "addr:housenumber":"27",
    "addr:postcode":"49023",
    "addr:street":"Calle De Pen\u0303A Trevinca",
    "iso:country":"ES",
    "sg:address":"Calle de Pe\u00d1a Trevinca, 27",
    "sg:city":"Zamora",
    "sg:orig_category":"Promotores Constructores",
    "sg:phone":"+34 980 51 66 26",
    "sg:postcode":"49023",
    "sg:province":"Zamora",
    "sg:website":"www.aldesaconstrucciones.es",
    "wof:name":"Aldesa Construcciones S.a.",
    "wof:placetype":"venue"
},
  "geometry": {"coordinates":[-5.74979496,41.5144882202],"type":"Point"}
}