{
  "type": "Feature",
  "properties": {
    "iso:country":"ES",
    "sg:address":"Rua Galicia, 34",
    "sg:city":"Noia",
    "sg:orig_category":"Inform\u00c1tica (estudios, Servicios, Asesor\u00cda, Formaci\u00d3n)",
    "sg:phone":"+34 981 82 01 62",
    "sg:postcode":"15200",
    "sg:province":"La Coru\u00f1a",
    "sg:website":"www.electronine.com",
    "wof:name":"Infonova Informatica E Comunicacions S.l.",
    "wof:placetype":"venue"
},
  "geometry": {"coordinates":[-8.8858566284,42.7848052979],"type":"Point"}
}