{
  "type": "Feature",
  "properties": {
    "iso:country":"ES",
    "sg:address":"Calle de Juan Bautista Pastor, 5",
    "sg:city":"Borboto",
    "sg:orig_category":"Reposter\u00cdas",
    "sg:phone":"+34 963 63 33 32",
    "sg:postcode":"46016",
    "sg:province":"Valencia",
    "wof:name":"Panificadora Estelles S.l.",
    "wof:placetype":"venue"
},
  "geometry": {"coordinates":[-0.3901300132,39.5143051147],"type":"Point"}
}