{
  "type": "Feature",
  "properties": {
    "addr:full":"Carrer de Pere Ii De Berga, 25 Berga-ciudad Barcelona 08600",
    "addr:housenumber":"25",
    "addr:postcode":"08600",
    "addr:street":"Carrer De Pere Ii De Berga;Barcelona",
    "iso:country":"ES",
    "sg:address":"Carrer de Pere Ii De Berga, 25",
    "sg:city":"Berga-ciudad",
    "sg:orig_category":"Librer\u00cdas",
    "sg:phone":"+34 938 22 00 19",
    "sg:postcode":"08600",
    "sg:province":"Barcelona",
    "wof:name":"Rodriguez Vilalta Maria Nuria",
    "wof:placetype":"venue"
},
  "geometry": {"coordinates":[1.8559099436,42.1032714844],"type":"Point"}
}