{
  "type": "Feature",
  "properties": {
    "iso:country":"ES",
    "sg:address":"Estd Ourense (de), 48",
    "sg:city":"Pazos",
    "sg:orig_category":"Muebles, Minoristas",
    "sg:phone":"+34 988 41 01 18",
    "sg:postcode":"32619",
    "sg:province":"Ourense",
    "wof:name":"Rodriguez Rodriguez German",
    "wof:placetype":"venue"
},
  "geometry": {"coordinates":[-7.4538340569,41.9393615723],"type":"Point"}
}