{
  "type": "Feature",
  "properties": {
    "addr:full":"Avda Primero De Mayo, 39 Valle Trapaga Vizcaya 48510",
    "addr:housenumber":"39",
    "addr:postcode":"48510",
    "addr:street":"Avda Primero De Mayo;Trapaga",
    "iso:country":"ES",
    "sg:address":"Avda Primero De Mayo, 39",
    "sg:city":"Valle Trapaga",
    "sg:orig_category":"Mercer\u00cda, Lencer\u00cda (al Por Menor)",
    "sg:phone":"+34 944 92 18 70",
    "sg:postcode":"48510",
    "sg:province":"Vizcaya",
    "wof:name":"Resurreccion Carrillo Lopez",
    "wof:placetype":"venue"
},
  "geometry": {"coordinates":[-3.0339291096,43.3019104004],"type":"Point"}
}