{
  "type": "Feature",
  "properties": {
    "addr:full":"Calle de La Platera, 2 Almonte Huelva 21730",
    "addr:housenumber":"2",
    "addr:postcode":"21730",
    "addr:street":"Calle De La Platera",
    "iso:country":"ES",
    "sg:address":"Calle de La Platera, 2",
    "sg:city":"Almonte",
    "sg:orig_category":"Albergues",
    "sg:phone":"+34 959 45 02 71",
    "sg:postcode":"21730",
    "sg:province":"Huelva",
    "wof:name":"Morano Martinez Jesus",
    "wof:placetype":"venue"
},
  "geometry": {"coordinates":[-6.5161290169,37.2684631348],"type":"Point"}
}