{
  "type": "Feature",
  "properties": {
    "addr:full":"A Cancela, 44 Cancela Pontevedra 36143",
    "addr:housenumber":"44",
    "addr:postcode":"36143",
    "addr:street":"Cancela",
    "iso:country":"ES",
    "sg:address":"A Cancela, 44",
    "sg:city":"Cancela",
    "sg:orig_category":"Art\u00cdculos De Decoraci\u00d3n",
    "sg:phone":"+34 986 84 60 09",
    "sg:postcode":"36143",
    "sg:province":"Pontevedra",
    "wof:name":"Hermida Vieitez Jose Luis",
    "wof:placetype":"venue"
},
  "geometry": {"coordinates":[-8.6421194077,42.4087219238],"type":"Point"}
}