{
  "type": "Feature",
  "properties": {
    "iso:country":"ES",
    "sg:address":"Calle de Sant Josep, 21",
    "sg:city":"Teulada",
    "sg:orig_category":"Promotores Constructores",
    "sg:phone":"+34 965 74 14 89",
    "sg:postcode":"03725",
    "sg:province":"Alicante",
    "wof:name":"Construccio Tossals Mar S.l.",
    "wof:placetype":"venue"
},
  "geometry": {"coordinates":[0.1014970019,38.7295074463],"type":"Point"}
}