{
  "type": "Feature",
  "properties": {
    "iso:country":"ES",
    "sg:address":"Hipodromo Etorbidea-avda Del Hipodromo, 8",
    "sg:city":"Lasarte-oria",
    "sg:orig_category":"\u00d3ptica: Instrumentos (fabricaci\u00d3n)",
    "sg:phone":"+34 943 36 64 82",
    "sg:postcode":"20160",
    "sg:province":"Guip\u00f9zcoa",
    "wof:name":"Optica Lizarri, S.l.",
    "wof:placetype":"venue"
},
  "geometry": {"coordinates":[-2.020414114,43.2698173523],"type":"Point"}
}