{
  "type": "Feature",
  "properties": {
    "addr:full":"Calle de San Esteban, S/n Almazcara Le\u00f3n 24398",
    "addr:housenumber":"s",
    "addr:postcode":"24398",
    "addr:street":"Calle De San;/ N Almazcara Leo\u0301N",
    "iso:country":"ES",
    "sg:address":"Calle de San Esteban, S/n",
    "sg:city":"Almazcara",
    "sg:orig_category":"Centros De Educaci\u00d3n Especial",
    "sg:phone":"+34 987 45 76 22",
    "sg:postcode":"24398",
    "sg:province":"Le\u00f3n",
    "wof:name":"Colegio Rural Agrupado Matachana",
    "wof:placetype":"venue"
},
  "geometry": {"coordinates":[-6.497563839,42.5967712402],"type":"Point"}
}