{
  "type": "Feature",
  "properties": {
    "addr:full":"Calle de Rufino Blanco, 7 Madrid Madrid 28028",
    "addr:housenumber":"7",
    "addr:postcode":"madrid;28028",
    "addr:street":"Calle De Rufino Blanco",
    "iso:country":"ES",
    "sg:address":"Calle de Rufino Blanco, 7",
    "sg:city":"Madrid",
    "sg:orig_category":"Renovaci\u00d3n Inmobiliaria",
    "sg:phone":"+34 913 56 60 05",
    "sg:postcode":"28028",
    "sg:province":"Madrid",
    "wof:name":"Rehabilitaciones Integrales S.l.",
    "wof:placetype":"venue"
},
  "geometry": {"coordinates":[-3.6666049957,40.4282913208],"type":"Point"}
}