{
  "type": "Feature",
  "properties": {
    "iso:country":"ES",
    "sg:address":"Calle de Hermanos Romero Ruiz, 2",
    "sg:city":"Caceres",
    "sg:orig_category":"Contenedores (mercanc\u00cdas)",
    "sg:phone":"+34 927 24 30 91",
    "sg:postcode":"10003",
    "sg:province":"C\u00e1ceres",
    "wof:name":"Gonzalez Garcia Manuel",
    "wof:placetype":"venue"
},
  "geometry": {"coordinates":[-6.3702940941,39.4682121277],"type":"Point"}
}