{
  "type": "Feature",
  "properties": {
    "iso:country":"ES",
    "sg:address":"Pg Saralegui, 114",
    "sg:city":"Puerto De Pollen\u00c7a",
    "sg:orig_category":"Molduras, Junquillos, Listones Y Molduras Perforadas",
    "sg:phone":"+34 971 86 48 81",
    "sg:postcode":"07470",
    "sg:province":"Islas Baleares",
    "wof:name":"Todavaro S.c.",
    "wof:placetype":"venue"
},
  "geometry": {"coordinates":[3.08050704,39.9034614563],"type":"Point"}
}