{
  "type": "Feature",
  "properties": {
    "iso:country":"ES",
    "sg:address":"Calle de Mayor, 98",
    "sg:city":"Canteras",
    "sg:orig_category":"Suministros Y Materiales Industriales",
    "sg:phone":"+34 968 16 20 41",
    "sg:postcode":"30394",
    "sg:province":"Murcia",
    "wof:name":"Control Llevant Instrumentacion Y Control S.l.",
    "wof:placetype":"venue"
},
  "geometry": {"coordinates":[-1.0452979803,37.6118812561],"type":"Point"}
}