{
  "type": "Feature",
  "properties": {
    "iso:country":"ES",
    "sg:address":"Av Onze De Setembre, 101",
    "sg:city":"Sabadell",
    "sg:orig_category":"Molduras, Junquillos, Listones Y Molduras Perforadas",
    "sg:phone":"+34 937 25 90 10",
    "sg:postcode":"08208",
    "sg:province":"Barcelona",
    "wof:name":"Noguera Romero Cesar",
    "wof:placetype":"venue"
},
  "geometry": {"coordinates":[2.1039509773,41.5535964966],"type":"Point"}
}