{
  "type": "Feature",
  "properties": {
    "addr:full":"Av Jacint Verdaguer, 1 Garriga Barcelona 08530",
    "addr:housenumber":"1",
    "addr:postcode":"08530",
    "addr:street":"Av Jacint Verdaguer",
    "iso:country":"ES",
    "sg:address":"Av Jacint Verdaguer, 1",
    "sg:city":"Garriga",
    "sg:orig_category":"Art\u00cdculos De Madera (fabricaci\u00d3n Y Al Por Mayor)",
    "sg:phone":"+34 938 71 91 08",
    "sg:postcode":"08530",
    "sg:province":"Barcelona",
    "wof:name":"Martin Mesa Inocencio",
    "wof:placetype":"venue"
},
  "geometry": {"coordinates":[2.2799201012,41.6734848022],"type":"Point"}
}