{
  "type": "Feature",
  "properties": {
    "addr:full":"Calle de Valderribas, 16 Madrid Madrid 28007",
    "addr:housenumber":"16",
    "addr:postcode":"madrid;28007",
    "addr:street":"Calle De Valderribas",
    "iso:country":"ES",
    "sg:address":"Calle de Valderribas, 16",
    "sg:city":"Madrid",
    "sg:orig_category":"Comercio De Piezas De Recambio Y De Accesorios De Veh\u00cdculos, Veh\u00cdculos Industriales",
    "sg:phone":"+34 915 51 33 96",
    "sg:postcode":"28007",
    "sg:province":"Madrid",
    "wof:name":"Grupo De Recambios Cema S.a.",
    "wof:placetype":"venue"
},
  "geometry": {"coordinates":[-3.6778640747,40.4053611755],"type":"Point"}
}