{
  "type": "Feature",
  "properties": {
    "addr:full":"Calle de Valeriano Leon, 17 Pola De Siero Asturias 33510",
    "addr:housenumber":"17",
    "addr:postcode":"33510",
    "addr:street":"Calle De Valeriano Leon",
    "iso:country":"ES",
    "sg:address":"Calle de Valeriano Leon, 17",
    "sg:city":"Pola De Siero",
    "sg:orig_category":"Muebles, Minoristas",
    "sg:phone":"+34 985 72 48 68",
    "sg:postcode":"33510",
    "sg:province":"Asturias",
    "wof:name":"Comercial Belmar De Siero 2000 S.l.",
    "wof:placetype":"venue"
},
  "geometry": {"coordinates":[-5.6598339081,43.3910522461],"type":"Point"}
}