{
  "type": "Feature",
  "properties": {
    "addr:full":"Cm\u00d1o Gandari\u00d1a, 38 Pi\u00f1eiro Pontevedra 36214",
    "addr:housenumber":"38",
    "addr:postcode":"36214",
    "addr:street":"Gandarin\u0303A",
    "iso:country":"ES",
    "sg:address":"Cm\u00d1o Gandari\u00d1a, 38",
    "sg:city":"Pi\u00f1eiro",
    "sg:orig_category":"Chapister\u00cda",
    "sg:phone":"+34 986 37 27 79",
    "sg:postcode":"36214",
    "sg:province":"Pontevedra",
    "wof:name":"Mendez Santos Jose Manuel",
    "wof:placetype":"venue"
},
  "geometry": {"coordinates":[-8.7059106827,42.2124443054],"type":"Point"}
}