{
  "type": "Feature",
  "properties": {
    "iso:country":"ES",
    "sg:address":"Urb Les Crestes, S/n",
    "sg:city":"Montserrat",
    "sg:orig_category":"Inform\u00c1tica: Consultores",
    "sg:phone":"+34 962 98 81 50",
    "sg:postcode":"46192",
    "sg:province":"Valencia",
    "wof:name":"Programacion Y Consultoria Informatica S.l.",
    "wof:placetype":"venue"
},
  "geometry": {"coordinates":[-0.6082429886,39.36668396],"type":"Point"}
}