{
  "type": "Feature",
  "properties": {
    "iso:country":"ES",
    "sg:address":"Avda Aragon, 47",
    "sg:city":"Puebla Vicar",
    "sg:orig_category":"Quincaller\u00cda (al Por Menor)",
    "sg:phone":"+34 950 55 32 36",
    "sg:postcode":"04738",
    "sg:province":"Almer\u00eda",
    "wof:name":"Perez Pe\u00f1a Miguel Angel",
    "wof:placetype":"venue"
},
  "geometry": {"coordinates":[-2.6517090797,36.8000984192],"type":"Point"}
}