{
  "type": "Feature",
  "properties": {
    "iso:country":"ES",
    "sg:address":"Calle de Mercedes, 4",
    "sg:city":"Valladolid",
    "sg:orig_category":"Peluquer\u00cdas, Peluquer\u00cda Mixta",
    "sg:phone":"+34 983 22 57 01",
    "sg:postcode":"47006",
    "sg:province":"Valladolid",
    "wof:name":"Mena Villa Maria Dolores De",
    "wof:placetype":"venue"
},
  "geometry": {"coordinates":[-4.7396378517,41.6403198242],"type":"Point"}
}