{
  "type": "Feature",
  "properties": {
    "iso:country":"ES",
    "sg:address":"Bard Espartera, S/n",
    "sg:city":"Estacion De Guadix",
    "sg:orig_category":"Empresas De Carpinter\u00cda Met\u00c1lica",
    "sg:phone":"+34 958 66 12 03",
    "sg:postcode":"18500",
    "sg:province":"Granada",
    "wof:name":"Aluminios Y Vidrios Del Sur S.l.",
    "wof:placetype":"venue"
},
  "geometry": {"coordinates":[-3.1345832348,37.3003959656],"type":"Point"}
}