{
  "type": "Feature",
  "properties": {
    "addr:full":"Av. Platja D'aro, 25 Castell D'aro Girona 17249",
    "addr:housenumber":"25",
    "addr:postcode":"17249",
    "addr:street":"Av. Platja D'Aro",
    "iso:country":"ES",
    "sg:address":"Av. Platja D'aro, 25",
    "sg:city":"Castell D'aro",
    "sg:orig_category":"Tapiceros Y Tapiceros",
    "sg:phone":"+34 972 82 81 49",
    "sg:postcode":"17249",
    "sg:province":"Girona",
    "wof:name":"C.d Inver Y Asociados S.l.",
    "wof:placetype":"venue"
},
  "geometry": {"coordinates":[2.8271551132,41.988822937],"type":"Point"}
}