{
  "type": "Feature",
  "properties": {
    "addr:full":"Pont Arseguell, S/n Arseguel Lleida 25722",
    "addr:housenumber":"s",
    "addr:postcode":"25722",
    "addr:street":"/ N Arseguel",
    "iso:country":"ES",
    "sg:address":"Pont Arseguell, S/n",
    "sg:city":"Arseguel",
    "sg:orig_category":"Lanas (al Por Mayor)",
    "sg:phone":"+34 973 38 40 09",
    "sg:postcode":"25722",
    "sg:province":"Lleida",
    "wof:name":"Fabrica Lanera Del Puente De Arseguell S. A.",
    "wof:placetype":"venue"
},
  "geometry": {"coordinates":[1.5907460451,42.3599510193],"type":"Point"}
}