{
  "type": "Feature",
  "properties": {
    "addr:full":"Carrer de Balmes, 295 Barcelona Barcelona 08006",
    "addr:housenumber":"295",
    "addr:postcode":"08006",
    "addr:street":"Carrer De Balmes",
    "iso:country":"ES",
    "sg:address":"Carrer de Balmes, 295",
    "sg:city":"Barcelona",
    "sg:orig_category":"Cl\u00cdnicas Dentales",
    "sg:phone":"+34 932 00 08 08",
    "sg:postcode":"08006",
    "sg:province":"Barcelona",
    "wof:name":"Alier Alcrudo Lorenzo Maria",
    "wof:placetype":"venue"
},
  "geometry": {"coordinates":[2.1464846134,41.4018173218],"type":"Point"}
}