{
  "type": "Feature",
  "properties": {
    "addr:full":"Calle de Hermano Pedro, 2 San Cristobal De La Laguna Santa Cruz De Tenerife 38205",
    "addr:housenumber":"2",
    "addr:postcode":"38205",
    "addr:street":"Calle De Hermano Pedro",
    "iso:country":"ES",
    "sg:address":"Calle de Hermano Pedro, 2",
    "sg:city":"San Cristobal De La Laguna",
    "sg:orig_category":"Farmacias",
    "sg:phone":"+34 922 25 89 70",
    "sg:postcode":"38205",
    "sg:province":"Santa Cruz De Tenerife",
    "wof:name":"Seco Pacio Felicitas",
    "wof:placetype":"venue"
},
  "geometry": {"coordinates":[-16.3124370575,28.4809970856],"type":"Point"}
}