{
  "type": "Feature",
  "properties": {
    "addr:full":"Ctra Villanueva, 44 Jerez De Los Caballeros Badajoz 06380",
    "addr:housenumber":"44",
    "addr:postcode":"06380",
    "addr:street":"Ctra Villanueva",
    "iso:country":"ES",
    "sg:address":"Ctra Villanueva, 44",
    "sg:city":"Jerez De Los Caballeros",
    "sg:orig_category":"Carnicer\u00cdas, Carnicer\u00cdas",
    "sg:phone":"+34 924 73 05 43",
    "sg:postcode":"06380",
    "sg:province":"Badajoz",
    "wof:name":"Jamones Y Embutidos De Jerez La Jamoneria S.a.",
    "wof:placetype":"venue"
},
  "geometry": {"coordinates":[-6.7712388039,38.3253707886],"type":"Point"}
}