{
  "type": "Feature",
  "properties": {
    "iso:country":"ES",
    "sg:address":"Carrer de Baro S M Sepulcre, 6",
    "sg:city":"Palma",
    "sg:orig_category":"Controles De Edificaci\u00d3n (construcci\u00d3n, Seguridad)",
    "sg:phone":"+34 971 71 07 84",
    "sg:postcode":"07012",
    "sg:province":"Islas Baleares",
    "wof:name":"Beach Baleares Construction Sl",
    "wof:placetype":"venue"
},
  "geometry": {"coordinates":[2.6441709995,39.5730133057],"type":"Point"}
}