{
  "type": "Feature",
  "properties": {
    "addr:full":"Via Circunvalacion, 3 Almansa Albacete 02640",
    "addr:housenumber":"3",
    "addr:postcode":"02640",
    "addr:street":"Via Circunvalacion",
    "iso:country":"ES",
    "sg:address":"Via Circunvalacion, 3",
    "sg:city":"Almansa",
    "sg:orig_category":"Instalaci\u00d3n, Reparaci\u00d3n De Calefacci\u00d3n Por Gas",
    "sg:phone":"+34 967 31 00 20",
    "sg:postcode":"02640",
    "sg:province":"Albacete",
    "wof:name":"Gestice S.l.u.",
    "wof:placetype":"venue"
},
  "geometry": {"coordinates":[-1.0889530182,38.8709564209],"type":"Point"}
}