{
  "type": "Feature",
  "properties": {
    "addr:full":"Carrer de Valenti Escalas, 2 Santa Coloma De Gramenet Barcelona 08923",
    "addr:housenumber":"2",
    "addr:postcode":"08923",
    "addr:street":"Carrer De Valenti Escalas",
    "iso:country":"ES",
    "sg:address":"Carrer de Valenti Escalas, 2",
    "sg:city":"Santa Coloma De Gramenet",
    "sg:orig_category":"Alimentaci\u00d3n General (al Por Menor)",
    "sg:phone":"+34 934 68 26 62",
    "sg:postcode":"08923",
    "sg:province":"Barcelona",
    "wof:name":"Alfonseda Ginesta Angela",
    "wof:placetype":"venue"
},
  "geometry": {"coordinates":[2.2161874771,41.4470443726],"type":"Point"}
}