{
  "type": "Feature",
  "properties": {
    "addr:full":"Cmno Malvas (somio), 199 Gijon Asturias 33203",
    "addr:housenumber":"199",
    "addr:postcode":"33203",
    "addr:street":"Cmno Malvas Somio",
    "iso:country":"ES",
    "sg:address":"Cmno Malvas (somio), 199",
    "sg:city":"Gijon",
    "sg:orig_category":"Inform\u00c1tica (estudios, Servicios, Asesor\u00cda, Formaci\u00d3n)",
    "sg:phone":"+34 985 13 22 66",
    "sg:postcode":"33203",
    "sg:province":"Asturias",
    "wof:name":"Bertrand Bertrand Clementina",
    "wof:placetype":"venue"
},
  "geometry": {"coordinates":[-5.5962839127,43.5261116028],"type":"Point"}
}