{
  "type": "Feature",
  "properties": {
    "addr:full":"Rua Numero 9, S/n Poligono Industrial Ourense 32901",
    "addr:housenumber":"s / n",
    "addr:postcode":"32901",
    "addr:street":"Rua Numero 9;Poligono Industrial Ourense",
    "iso:country":"ES",
    "sg:address":"Rua Numero 9, S/n",
    "sg:city":"Poligono Industrial",
    "sg:orig_category":"Limpieza Industrial",
    "sg:phone":"+34 988 38 45 55",
    "sg:postcode":"32901",
    "sg:province":"Ourense",
    "wof:name":"Servimgal S.l.",
    "wof:placetype":"venue"
},
  "geometry": {"coordinates":[-7.8334488869,42.2905006409],"type":"Point"}
}