{
  "type": "Feature",
  "properties": {
    "addr:full":"Carr Barcelona, 29 Balaguer Lleida 25600",
    "addr:housenumber":"29",
    "addr:postcode":"25600",
    "addr:street":"Carr Barcelona",
    "iso:country":"ES",
    "sg:address":"Carr Barcelona, 29",
    "sg:city":"Balaguer",
    "sg:orig_category":"Contenedores (mercanc\u00cdas)",
    "sg:phone":"+34 973 44 74 86",
    "sg:postcode":"25600",
    "sg:province":"Lleida",
    "wof:name":"Sanz Maria Angel",
    "wof:placetype":"venue"
},
  "geometry": {"coordinates":[0.8115900159,41.7902603149],"type":"Point"}
}