{
  "type": "Feature",
  "properties": {
    "addr:full":"Calle de General Moscardo, 1 Cuerva Toledo 45126",
    "addr:housenumber":"1",
    "addr:postcode":"45126",
    "addr:street":"Calle De General Moscardo",
    "iso:country":"ES",
    "sg:address":"Calle de General Moscardo, 1",
    "sg:city":"Cuerva",
    "sg:classifiers":[
        {
            "category":"Taxi",
            "type":"Transportation"
        }
    ],
    "sg:phone":"+34 925 42 41 31",
    "sg:postcode":"45126",
    "sg:province":"Toledo",
    "wof:name":"Serrano Balmaseda Angel",
    "wof:placetype":"venue"
},
  "geometry": {"coordinates":[-4.2114949226,39.6650466919],"type":"Point"}
}