{
  "type": "Feature",
  "properties": {
    "iso:country":"ES",
    "sg:address":"Av Pau Casals, 157",
    "sg:city":"Hospitalet Llobregat",
    "sg:orig_category":"Mec\u00c1nico Del Autom\u00d3vil",
    "sg:phone":"+34 933 36 45 51",
    "sg:postcode":"08907",
    "sg:province":"Barcelona",
    "wof:name":"Auto Record Hospitalet S.l.",
    "wof:placetype":"venue"
},
  "geometry": {"coordinates":[2.1048998833,41.3587303162],"type":"Point"}
}