{
  "type": "Feature",
  "properties": {
    "addr:full":"Ctra Cadiz (de), Km. 0043,8 Aranjuez Madrid 28300",
    "addr:postcode":"28300",
    "addr:street":"Ctra Cadiz De Km. 0043,8",
    "iso:country":"ES",
    "sg:address":"Ctra Cadiz (de), Km. 0043,8",
    "sg:city":"Aranjuez",
    "sg:orig_category":"Agentes, Concesionarios Y Sucursales De Veh\u00cdculos",
    "sg:phone":"+34 918 92 51 16",
    "sg:postcode":"28300",
    "sg:province":"Madrid",
    "wof:name":"Comercial Burgos S.l.",
    "wof:placetype":"venue"
},
  "geometry": {"coordinates":[-3.6042790413,40.0360946655],"type":"Point"}
}