{
  "type": "Feature",
  "properties": {
    "addr:full":"Av Magaluf, 10 Magaluf Islas Baleares 07181",
    "addr:housenumber":"10",
    "addr:postcode":"07181",
    "addr:street":"Av Magaluf",
    "iso:country":"ES",
    "sg:address":"Av Magaluf, 10",
    "sg:city":"Magaluf",
    "sg:orig_category":"Art\u00cdculos De Regalo (al Por Menor)",
    "sg:phone":"+34 971 13 13 49",
    "sg:postcode":"07181",
    "sg:province":"Islas Baleares",
    "wof:name":"Sanchez Castillo Dolores",
    "wof:placetype":"venue"
},
  "geometry": {"coordinates":[2.5331261158,39.5062103271],"type":"Point"}
}