{
  "type": "Feature",
  "properties": {
    "addr:full":"Calle de Palacio, 10 Almazan Soria 42200",
    "addr:housenumber":"10",
    "addr:postcode":"42200",
    "addr:street":"Calle De Palacio",
    "iso:country":"ES",
    "sg:address":"Calle de Palacio, 10",
    "sg:city":"Almazan",
    "sg:orig_category":"Laboratorios De An\u00c1lisis Agr\u00cdcolas Y De Biolog\u00cda Vegetal",
    "sg:phone":"+34 975 31 02 77",
    "sg:postcode":"42200",
    "sg:province":"Soria",
    "wof:name":"Labsor 96 S.l.",
    "wof:placetype":"venue"
},
  "geometry": {"coordinates":[-2.5340559483,41.4866828918],"type":"Point"}
}