{
  "type": "Feature",
  "properties": {
    "iso:country":"ES",
    "sg:address":"Calle de Luis Armi\u00d1an, 48",
    "sg:city":"Nava",
    "sg:orig_category":"Bancos",
    "sg:phone":"+34 985 71 71 54",
    "sg:postcode":"33529",
    "sg:province":"Asturias",
    "wof:name":"Banc Sabadell S.a.",
    "wof:placetype":"venue"
},
  "geometry": {"coordinates":[-5.4692487717,43.408908844],"type":"Point"}
}