{
  "type": "Feature",
  "properties": {
    "iso:country":"ES",
    "sg:address":"Carrer de Sant Antoni Maria Claret, 252",
    "sg:city":"Barcelona",
    "sg:orig_category":"Venta, Localizaci\u00d3n, Reparaci\u00d3n De Material E Instrumental M\u00c9dico",
    "sg:phone":"+34 934 36 10 03",
    "sg:postcode":"08041",
    "sg:province":"Barcelona",
    "wof:name":"Biosis Biologic System S.l.",
    "wof:placetype":"venue"
},
  "geometry": {"coordinates":[2.1759409904,41.4122314453],"type":"Point"}
}