{
  "type": "Feature",
  "properties": {
    "addr:full":"Calle de Feria, 64 Benameji C\u00f3rdoba 14910",
    "addr:housenumber":"64",
    "addr:postcode":"14910",
    "addr:street":"Calle De Feria;Co\u0301Rdoba",
    "iso:country":"ES",
    "sg:address":"Calle de Feria, 64",
    "sg:city":"Benameji",
    "sg:orig_category":"Molduras, Junquillos, Listones Y Molduras Perforadas",
    "sg:phone":"+34 957 53 13 22",
    "sg:postcode":"14910",
    "sg:province":"C\u00f3rdoba",
    "wof:name":"Martin Carmona Luis",
    "wof:placetype":"venue"
},
  "geometry": {"coordinates":[-4.5412559509,37.2692871094],"type":"Point"}
}