{
  "type": "Feature",
  "properties": {
    "addr:full":"Carrer de Cortada, 28 Barcelona Barcelona 08035",
    "addr:housenumber":"28",
    "addr:postcode":"08035",
    "addr:street":"Carrer De Cortada",
    "iso:country":"ES",
    "sg:address":"Carrer de Cortada, 28",
    "sg:city":"Barcelona",
    "sg:orig_category":"Empresas De Limpieza",
    "sg:phone":"+34 934 20 62 13",
    "sg:postcode":"08035",
    "sg:province":"Barcelona",
    "wof:name":"Moliter S.c.p.",
    "wof:placetype":"venue"
},
  "geometry": {"coordinates":[2.1469869614,41.4239425659],"type":"Point"}
}