{
  "type": "Feature",
  "properties": {
    "addr:full":"Calle de Linares Rivas, 10 Sada A Coru\u00f1a 15160",
    "addr:housenumber":"10",
    "addr:postcode":"15160",
    "addr:street":"Calle De Linares Rivas",
    "iso:country":"ES",
    "sg:address":"Calle de Linares Rivas, 10",
    "sg:city":"Sada",
    "sg:orig_category":"Molduras, Junquillos, Listones Y Molduras Perforadas",
    "sg:phone":"+34 981 62 28 82",
    "sg:postcode":"15160",
    "sg:province":"A Coru\u00f1a",
    "wof:name":"Viralta Godayol Maria Gloria",
    "wof:placetype":"venue"
},
  "geometry": {"coordinates":[-8.2548141479,43.3510665894],"type":"Point"}
}