{
  "type": "Feature",
  "properties": {
    "addr:full":"Avda Mari\u00d1a, 4 Sada La Coru\u00f1a 15160",
    "addr:housenumber":"4",
    "addr:postcode":"15160",
    "addr:street":"Avda Marin\u0303A;La",
    "iso:country":"ES",
    "sg:address":"Avda Mari\u00d1a, 4",
    "sg:city":"Sada",
    "sg:orig_category":"Cl\u00cdnicas Dentales",
    "sg:phone":"+34 981 62 41 56",
    "sg:postcode":"15160",
    "sg:province":"La Coru\u00f1a",
    "wof:name":"Odontogal S. L.",
    "wof:placetype":"venue"
},
  "geometry": {"coordinates":[-8.2524814606,43.3505516052],"type":"Point"}
}