{
  "type": "Feature",
  "properties": {
    "iso:country":"ES",
    "sg:address":"Calle de Carrero Juan Ramon, 1",
    "sg:city":"Madrid",
    "sg:orig_category":"Inform\u00c1tica: Mantenimiento Y Reparaci\u00d3n De Ordenadores",
    "sg:phone":"+34 915 60 78 44",
    "sg:postcode":"28025",
    "sg:province":"Madrid",
    "sg:website":"www.andlogic.net",
    "wof:name":"Campo Ortega Ruben",
    "wof:placetype":"venue"
},
  "geometry": {"coordinates":[-3.728508234,40.3787765503],"type":"Point"}
}