{
  "type": "Feature",
  "properties": {
    "addr:full":"Calle de Silva, 5 Madrid Madrid 28013",
    "addr:housenumber":"5",
    "addr:postcode":"28013",
    "addr:street":"Calle De Silva",
    "iso:country":"ES",
    "sg:address":"Calle de Silva, 5",
    "sg:city":"Madrid",
    "sg:orig_category":"Agencias Y Agentes Comerciales, Representantes",
    "sg:phone":"+34 915 47 29 11",
    "sg:postcode":"28013",
    "sg:province":"Madrid",
    "wof:name":"Ramirez Verdes-montenegro Rodrigo",
    "wof:placetype":"venue"
},
  "geometry": {"coordinates":[-3.7077870369,40.420791626],"type":"Point"}
}