{
  "type": "Feature",
  "properties": {
    "addr:full":"Calle de Gutierrez De Los Rios, 23 Cordoba C\u00f3rdoba 14002",
    "addr:housenumber":"23",
    "addr:postcode":"14002",
    "addr:street":"Calle De Gutierrez De Los Rios;Co\u0301Rdoba",
    "iso:country":"ES",
    "sg:address":"Calle de Gutierrez De Los Rios, 23",
    "sg:city":"Cordoba",
    "sg:orig_category":"Mercer\u00cda, Lencer\u00cda (al Por Menor)",
    "sg:phone":"+34 957 47 32 81",
    "sg:postcode":"14002",
    "sg:province":"C\u00f3rdoba",
    "wof:name":"Izquierdo Gonzalez Bernardo",
    "wof:placetype":"venue"
},
  "geometry": {"coordinates":[-4.772796154,37.8847618103],"type":"Point"}
}