{
  "type": "Feature",
  "properties": {
    "iso:country":"ES",
    "sg:address":"Calle de Salamanca, 25",
    "sg:city":"Valencia",
    "sg:orig_category":"Inform\u00c1tica (estudios, Servicios, Asesor\u00cda, Formaci\u00d3n)",
    "sg:phone":"+34 963 74 00 33",
    "sg:postcode":"46005",
    "sg:province":"Valencia",
    "wof:name":"Sistac Ils Sl",
    "wof:placetype":"venue"
},
  "geometry": {"coordinates":[-0.3642480075,39.4664878845],"type":"Point"}
}