{
  "type": "Feature",
  "properties": {
    "iso:country":"ES",
    "sg:address":"Pase Chopera, 71",
    "sg:city":"Madrid",
    "sg:orig_category":"Hoteles",
    "sg:phone":"+34 915 39 66 00",
    "sg:postcode":"28045",
    "sg:province":"Madrid",
    "wof:name":"Auto-hotel S.a.",
    "wof:placetype":"venue"
},
  "geometry": {"coordinates":[-3.6958909035,40.3919143677],"type":"Point"}
}