{
  "type": "Feature",
  "properties": {
    "addr:full":"Calle de Canalejas, 11 Arrecife Las Palmas 35500",
    "addr:housenumber":"11",
    "addr:postcode":"35500",
    "addr:street":"Calle De Canalejas",
    "iso:country":"ES",
    "sg:address":"Calle de Canalejas, 11",
    "sg:city":"Arrecife",
    "sg:orig_category":"Farmacias",
    "sg:phone":"+34 928 80 29 53",
    "sg:postcode":"35500",
    "sg:province":"Las Palmas",
    "wof:name":"Mendoza Rosales Maria Del Pino",
    "wof:placetype":"venue"
},
  "geometry": {"coordinates":[-13.55103302,28.9587192535],"type":"Point"}
}