{
  "type": "Feature",
  "properties": {
    "iso:country":"ES",
    "sg:address":"Calle de Sauces, S/n",
    "sg:city":"Sauces",
    "sg:orig_category":"Alimentaci\u00d3n General (al Por Menor)",
    "sg:phone":"+34 925 59 21 57",
    "sg:postcode":"45529",
    "sg:province":"Toledo",
    "wof:name":"Andrino Calvo Ana Jesus",
    "wof:placetype":"venue"
},
  "geometry": {"coordinates":[-3.8901262283,40.0669059753],"type":"Point"}
}