{
  "type": "Feature",
  "properties": {
    "addr:full":"Pl Nova, 20 Gata Gorgos Alicante 03740",
    "addr:housenumber":"20",
    "addr:postcode":"03740",
    "addr:street":"Pl Nova",
    "iso:country":"ES",
    "sg:address":"Pl Nova, 20",
    "sg:city":"Gata Gorgos",
    "sg:orig_category":"Alimentaci\u00d3n General (al Por Menor)",
    "sg:phone":"+34 965 75 65 23",
    "sg:postcode":"03740",
    "sg:province":"Alicante",
    "wof:name":"Diego Leyda Jose",
    "wof:placetype":"venue"
},
  "geometry": {"coordinates":[0.086139001,38.7741966248],"type":"Point"}
}