{
  "type": "Feature",
  "properties": {
    "iso:country":"ES",
    "sg:address":"Rambla (la), 42",
    "sg:city":"Mataro",
    "sg:orig_category":"Asesor\u00cdas Y Estudios Financieros",
    "sg:phone":"+34 937 96 24 02",
    "sg:postcode":"08302",
    "sg:province":"Barcelona",
    "wof:name":"Quintin Lopez Miguel Angel",
    "wof:placetype":"venue"
},
  "geometry": {"coordinates":[2.4439051151,41.5415153503],"type":"Point"}
}