{
  "type": "Feature",
  "properties": {
    "addr:full":"Afores, S/n Torroella Fluvia Girona 17474",
    "addr:housenumber":"s / n",
    "addr:postcode":"17474",
    "addr:street":"Afores",
    "iso:country":"ES",
    "sg:address":"Afores, S/n",
    "sg:city":"Torroella Fluvia",
    "sg:orig_category":"Cr\u00cda De Animales",
    "sg:phone":"+34 972 55 01 74",
    "sg:postcode":"17474",
    "sg:province":"Girona",
    "wof:name":"Rodau S.l.",
    "wof:placetype":"venue"
},
  "geometry": {"coordinates":[3.040982008,42.1750831604],"type":"Point"}
}