{
  "type": "Feature",
  "properties": {
    "addr:full":"Avda Mahia, 50 Bertamirans A Coru\u00f1a 15220",
    "addr:housenumber":"50",
    "addr:postcode":"15220",
    "addr:street":"Avda Mahia;Corun\u0303A",
    "iso:country":"ES",
    "sg:address":"Avda Mahia, 50",
    "sg:city":"Bertamirans",
    "sg:orig_category":"Abogados",
    "sg:phone":"+34 981 88 41 92",
    "sg:postcode":"15220",
    "sg:province":"A Coru\u00f1a",
    "wof:name":"Viqueira Abogados",
    "wof:placetype":"venue"
},
  "geometry": {"coordinates":[-8.6537876129,42.8589744568],"type":"Point"}
}