{
  "type": "Feature",
  "properties": {
    "iso:country":"ES",
    "sg:address":"Calle de Arias, 3",
    "sg:city":"Zaragoza",
    "sg:orig_category":"Servicios De Telecomunicaciones",
    "sg:phone":"+34 976 33 56 59",
    "sg:postcode":"50010",
    "sg:province":"Zaragoza",
    "wof:name":"De Sousa Araujo Antonio",
    "wof:placetype":"venue"
},
  "geometry": {"coordinates":[-0.9086297154,41.6527366638],"type":"Point"}
}