{
  "type": "Feature",
  "properties": {
    "iso:country":"ES",
    "sg:address":"Cra. Moja-vilafranca, S/n",
    "sg:city":"Moja",
    "sg:orig_category":"Reciclaje, Desguace De Veh\u00cdculos",
    "sg:phone":"+34 938 17 28 75",
    "sg:postcode":"08734",
    "sg:province":"Barcelona",
    "wof:name":"Recambios Moja S.l.",
    "wof:placetype":"venue"
},
  "geometry": {"coordinates":[1.7167370319,41.3229942322],"type":"Point"}
}