{
  "type": "Feature",
  "properties": {
    "addr:full":"Avda Fuente (de La), S/n Peligros Granada 18210",
    "addr:housenumber":"/ n",
    "addr:postcode":"18210",
    "addr:street":"Avda Fuente De La S",
    "iso:country":"ES",
    "sg:address":"Avda Fuente (de La), S/n",
    "sg:city":"Peligros",
    "sg:orig_category":"Asociaciones Y Clubs Deportivos",
    "sg:phone":"+34 958 40 59 83",
    "sg:postcode":"18210",
    "sg:province":"Granada",
    "wof:name":"Gallego Gomez Rosario",
    "wof:placetype":"venue"
},
  "geometry": {"coordinates":[-3.6318290234,37.2354736328],"type":"Point"}
}