{
  "type": "Feature",
  "properties": {
    "iso:country":"ES",
    "sg:address":"Calle de Obispo Miranda, 13",
    "sg:city":"Tamarite Litera",
    "sg:orig_category":"Telefon\u00cda: Instaladores Varios",
    "sg:phone":"+34 974 42 17 44",
    "sg:postcode":"22550",
    "sg:province":"Huesca",
    "wof:name":"Xtra Telecom S.a",
    "wof:placetype":"venue"
},
  "geometry": {"coordinates":[0.4215120077,41.8698234558],"type":"Point"}
}