{
  "type": "Feature",
  "properties": {
    "addr:full":"Calle de Jose Miguel Barandiaran, 37 Santurtzi Vizcaya 48980",
    "addr:housenumber":"37",
    "addr:postcode":"48980",
    "addr:street":"Calle De Jose Miguel Barandiaran",
    "iso:country":"ES",
    "sg:address":"Calle de Jose Miguel Barandiaran, 37",
    "sg:city":"Santurtzi",
    "sg:orig_category":"Cajas De Ahorro",
    "sg:phone":"+34 944 93 78 56",
    "sg:postcode":"48980",
    "sg:province":"Vizcaya",
    "wof:name":"Caixa D'estalvis I Pensions De Barcelona",
    "wof:placetype":"venue"
},
  "geometry": {"coordinates":[-3.0366339684,43.3228378296],"type":"Point"}
}