{
  "type": "Feature",
  "properties": {
    "iso:country":"ES",
    "sg:address":"Calle de Cami Reial, 112",
    "sg:city":"Torrent",
    "sg:orig_category":"Farmacias",
    "sg:phone":"+34 961 57 29 93",
    "sg:postcode":"46900",
    "sg:province":"Valencia",
    "wof:name":"Campos Carratala Martinez C.b.",
    "wof:placetype":"venue"
},
  "geometry": {"coordinates":[-0.5352355838,39.4127235413],"type":"Point"}
}