{
  "type": "Feature",
  "properties": {
    "iso:country":"ES",
    "sg:address":"Rua Da Esperanza, 23",
    "sg:city":"Ponteareas",
    "sg:orig_category":"Zapatos (al Por Menor)",
    "sg:phone":"+34 986 64 02 42",
    "sg:postcode":"36860",
    "sg:province":"Pontevedra",
    "wof:name":"Castro Fernandez Angeles",
    "wof:placetype":"venue"
},
  "geometry": {"coordinates":[-8.5163888931,42.1783599854],"type":"Point"}
}