{
  "type": "Feature",
  "properties": {
    "iso:country":"ES",
    "sg:address":"Carrer de Ramon I Cajal, 65",
    "sg:city":"Roses",
    "sg:orig_category":"Empresas De Carpinter\u00cda De Madera",
    "sg:phone":"+34 972 25 68 77",
    "sg:postcode":"17480",
    "sg:province":"Girona",
    "wof:name":"Marti Perez Francisco",
    "wof:placetype":"venue"
},
  "geometry": {"coordinates":[3.1821420193,42.2619400024],"type":"Point"}
}