{
  "type": "Feature",
  "properties": {
    "addr:full":"P. Hillo, 3 Sevilla Sevilla 41007",
    "addr:housenumber":"3",
    "addr:postcode":"41007",
    "addr:street":"P. Hillo",
    "iso:country":"ES",
    "sg:address":"P. Hillo, 3",
    "sg:city":"Sevilla",
    "sg:orig_category":"Agencias Y Agentes Comerciales, Representantes",
    "sg:phone":"+34 954 25 27 16",
    "sg:postcode":"41007",
    "sg:province":"Sevilla",
    "wof:name":"Romero Leon Natividad",
    "wof:placetype":"venue"
},
  "geometry": {"coordinates":[-5.9609680176,37.4001998901],"type":"Point"}
}