{
  "type": "Feature",
  "properties": {
    "addr:full":"Calle de Real, 75 Piedrabuena Ciudad Real 13100",
    "addr:housenumber":"75",
    "addr:postcode":"piedrabuena;13100",
    "addr:street":"Calle De Real",
    "iso:country":"ES",
    "sg:address":"Calle de Real, 75",
    "sg:city":"Piedrabuena",
    "sg:orig_category":"Venta, Montaje De Neum\u00c1ticos",
    "sg:phone":"+34 926 76 11 32",
    "sg:postcode":"13100",
    "sg:province":"Ciudad Real",
    "wof:name":"Neumaticos Y Accesorios Sanchez S.l.",
    "wof:placetype":"venue"
},
  "geometry": {"coordinates":[-4.1738390923,39.0354003906],"type":"Point"}
}