{
  "type": "Feature",
  "properties": {
    "iso:country":"ES",
    "sg:address":"Calle de Foglietti, 37",
    "sg:city":"Alacant",
    "sg:orig_category":"Iglesia Cat\u00d3lica",
    "sg:phone":"+34 965 10 79 14",
    "sg:postcode":"03007",
    "sg:province":"Alicante",
    "wof:name":"Parroquia San Juan Bautista",
    "wof:placetype":"venue"
},
  "geometry": {"coordinates":[-0.4993210137,38.3408546448],"type":"Point"}
}