{
  "type": "Feature",
  "properties": {
    "iso:country":"ES",
    "sg:address":"Calle de General San Martin, 4",
    "sg:city":"Valencia",
    "sg:orig_category":"Peluqueros: De Se\u00d1oras",
    "sg:phone":"+34 963 41 84 42",
    "sg:postcode":"46004",
    "sg:province":"Valencia",
    "wof:name":"Moret Gil Francisco",
    "wof:placetype":"venue"
},
  "geometry": {"coordinates":[-0.3756099939,39.4652824402],"type":"Point"}
}