{
  "type": "Feature",
  "properties": {
    "addr:full":"Calle de Vergara, 42 San Fernando De Henares Madrid 28830",
    "addr:housenumber":"42",
    "addr:postcode":"28830",
    "addr:street":"Calle De Vergara",
    "iso:country":"ES",
    "sg:address":"Calle de Vergara, 42",
    "sg:city":"San Fernando De Henares",
    "sg:orig_category":"Tiendas De Grano, Frutas Y Legumbres Secas (al Por Menor)",
    "sg:phone":"+34 916 74 18 05",
    "sg:postcode":"28830",
    "sg:province":"Madrid",
    "wof:name":"Martin Martin Maria Aurelia",
    "wof:placetype":"venue"
},
  "geometry": {"coordinates":[-3.5283479691,40.4210624695],"type":"Point"}
}