{
  "type": "Feature",
  "properties": {
    "addr:full":"Cami Ronda, 63 Alcudia Islas Baleares 07400",
    "addr:housenumber":"63",
    "addr:postcode":"07400",
    "addr:street":"Ronda",
    "iso:country":"ES",
    "sg:address":"Cami Ronda, 63",
    "sg:city":"Alcudia",
    "sg:orig_category":"Delegados, Agentes De Tr\u00c1nsito, Auxiliares De Transporte Internacional",
    "sg:phone":"+34 971 54 69 95",
    "sg:postcode":"07400",
    "sg:province":"Islas Baleares",
    "wof:name":"Reynes Valles Miguel",
    "wof:placetype":"venue"
},
  "geometry": {"coordinates":[3.1200098991,39.8544998169],"type":"Point"}
}