{
  "type": "Feature",
  "properties": {
    "addr:full":"Avda Pe\u00d1olite, 3 Puente Genave Ja\u00e9n 23350",
    "addr:housenumber":"3",
    "addr:postcode":"23350",
    "addr:street":"Avda Pen\u0303Olite;Genave Jae\u0301N",
    "iso:country":"ES",
    "sg:address":"Avda Pe\u00d1olite, 3",
    "sg:city":"Puente Genave",
    "sg:orig_category":"Iglesia Cat\u00d3lica",
    "sg:phone":"+34 953 43 52 05",
    "sg:postcode":"23350",
    "sg:province":"Ja\u00e9n",
    "wof:name":"Parroquia San Isidro Labrador",
    "wof:placetype":"venue"
},
  "geometry": {"coordinates":[-2.8030788898,38.3562431335],"type":"Point"}
}