{
  "type": "Feature",
  "properties": {
    "iso:country":"ES",
    "sg:address":"Liebana, 2",
    "sg:city":"Torrelavega",
    "sg:orig_category":"Estancos",
    "sg:phone":"+34 942 88 02 53",
    "sg:postcode":"39300",
    "sg:province":"Cantabria",
    "wof:name":"Vega Azcarate Oscar",
    "wof:placetype":"venue"
},
  "geometry": {"coordinates":[-4.0534920692,43.3416938782],"type":"Point"}
}