{
  "type": "Feature",
  "properties": {
    "addr:full":"Avda Castrelos, 164 Vigo Pontevedra 36210",
    "addr:housenumber":"164",
    "addr:postcode":"36210",
    "addr:street":"Avda Castrelos",
    "iso:country":"ES",
    "sg:address":"Avda Castrelos, 164",
    "sg:city":"Vigo",
    "sg:orig_category":"Peluquer\u00cdas, Peluquer\u00cda Mixta",
    "sg:phone":"+34 986 29 78 51",
    "sg:postcode":"36210",
    "sg:province":"Pontevedra",
    "wof:name":"Alonso Alonso Jose Ramon",
    "wof:placetype":"venue"
},
  "geometry": {"coordinates":[-8.7324743271,42.2176895142],"type":"Point"}
}