{
  "type": "Feature",
  "properties": {
    "addr:full":"Calle de Ni\u00d1o De Gloria, S/n Malaga M\u00e1laga 29003",
    "addr:housenumber":"s / n",
    "addr:postcode":"29003",
    "addr:street":"Calle De Nin\u0303O;Ma\u0301Laga",
    "iso:country":"ES",
    "sg:address":"Calle de Ni\u00d1o De Gloria, S/n",
    "sg:city":"Malaga",
    "sg:orig_category":"Polideportivos",
    "sg:phone":"+34 952 34 13 16",
    "sg:postcode":"29003",
    "sg:province":"M\u00e1laga",
    "wof:name":"Fundacion Publica Deportiva Municipal De Malaga",
    "wof:placetype":"venue"
},
  "geometry": {"coordinates":[-4.4489269257,36.7011985779],"type":"Point"}
}