{
  "type": "Feature",
  "properties": {
    "iso:country":"ES",
    "sg:address":"Calle de Monteperdido, 51",
    "sg:city":"Dos Hermanas",
    "sg:orig_category":"Caf\u00c9s, Bares, Cervecer\u00cdas",
    "sg:phone":"+34 955 66 26 95",
    "sg:postcode":"41700",
    "sg:province":"Sevilla",
    "wof:name":"Giraldez Romero Isabel Maria",
    "wof:placetype":"venue"
},
  "geometry": {"coordinates":[-5.9173569679,37.2914886475],"type":"Point"}
}