{
  "type": "Feature",
  "properties": {
    "iso:country":"ES",
    "sg:address":"Rua Pinar, 9",
    "sg:city":"Porri\u00f1o",
    "sg:orig_category":"Ingeniero",
    "sg:phone":"+34 986 33 81 66",
    "sg:postcode":"36400",
    "sg:province":"Pontevedra",
    "wof:name":"Sio Perez Angel",
    "wof:placetype":"venue"
},
  "geometry": {"coordinates":[-8.6181335449,42.1607208252],"type":"Point"}
}