{
  "type": "Feature",
  "properties": {
    "iso:country":"ES",
    "sg:address":"Calle de Division Azul, 1",
    "sg:city":"Corrales",
    "sg:orig_category":"Electrodom\u00c9sticos (fabricaci\u00d3n, Al Por Mayor)",
    "sg:phone":"+34 942 83 02 42",
    "sg:postcode":"39400",
    "sg:province":"Cantabria",
    "wof:name":"Electrodomesticos Valentin S.l.",
    "wof:placetype":"venue"
},
  "geometry": {"coordinates":[-4.0691900253,43.2594947815],"type":"Point"}
}