{
  "type": "Feature",
  "properties": {
    "addr:full":"Calle de Victoria Kent, S/n Cordoba C\u00f3rdoba 14011",
    "addr:housenumber":"s / n",
    "addr:postcode":"14011",
    "addr:street":"Calle De Victoria Kent;Co\u0301Rdoba",
    "iso:country":"ES",
    "sg:address":"Calle de Victoria Kent, S/n",
    "sg:city":"Cordoba",
    "sg:orig_category":"Discapacitados",
    "sg:phone":"+34 957 76 77 76",
    "sg:postcode":"14011",
    "sg:province":"C\u00f3rdoba",
    "wof:name":"Asociacion Cordobesa De Paralisis Cerebral Y Afecciones Similares",
    "wof:placetype":"venue"
},
  "geometry": {"coordinates":[-4.7943434715,37.8962440491],"type":"Point"}
}