{
  "type": "Feature",
  "properties": {
    "addr:full":"Isla Cristina, 2 Valdepastores Madrid 28660",
    "addr:postcode":"28660",
    "iso:country":"ES",
    "sg:address":"Isla Cristina, 2",
    "sg:city":"Valdepastores",
    "sg:orig_category":"Inmobiliaria (agencias)",
    "sg:phone":"+34 916 33 17 62",
    "sg:postcode":"28660",
    "sg:province":"Madrid",
    "wof:name":"Produccion Y Servicios S.a.",
    "wof:placetype":"venue"
},
  "geometry": {"coordinates":[-3.8825960159,40.4214553833],"type":"Point"}
}