{
  "type": "Feature",
  "properties": {
    "iso:country":"ES",
    "sg:address":"Calle de Puente De La Muleta, 52",
    "sg:city":"Barrio Del Puente De La Muleta",
    "sg:orig_category":"Empresas De Carpinter\u00cda Met\u00c1lica",
    "sg:phone":"+34 968 85 07 20",
    "sg:postcode":"30007",
    "sg:province":"Murcia",
    "wof:name":"Ortigosa Proyectos Y Construcciones S.l.",
    "wof:placetype":"venue"
},
  "geometry": {"coordinates":[-1.1062239408,38.018321991],"type":"Point"}
}