{
  "type": "Feature",
  "properties": {
    "iso:country":"ES",
    "sg:address":"Calle de Pascual Martinez, 123",
    "sg:city":"Redovan",
    "sg:orig_category":"Inmobiliaria (agencias)",
    "sg:phone":"+34 966 75 54 83",
    "sg:postcode":"03370",
    "sg:province":"Alicante",
    "wof:name":"Sunquest Spanish Properties S.l",
    "wof:placetype":"venue"
},
  "geometry": {"coordinates":[-0.9144939184,38.118309021],"type":"Point"}
}