{
  "type": "Feature",
  "properties": {
    "addr:full":"Calle de Rafael De Riego, 27 Madrid Madrid 28045",
    "addr:housenumber":"27",
    "addr:postcode":"madrid;28045",
    "addr:street":"Calle De Rafael De Riego",
    "iso:country":"ES",
    "sg:address":"Calle de Rafael De Riego, 27",
    "sg:city":"Madrid",
    "sg:orig_category":"Colchones (fabricaci\u00d3n, Al Por Mayor, Al Por Menor)",
    "sg:phone":"+34 915 30 26 07",
    "sg:postcode":"28045",
    "sg:province":"Madrid",
    "sg:website":"www.noctalia.es",
    "wof:name":"Noctalia",
    "wof:placetype":"venue"
},
  "geometry": {"coordinates":[-3.6921029091,40.4025688171],"type":"Point"}
}