{
  "type": "Feature",
  "properties": {
    "iso:country":"ES",
    "sg:address":"Calle de General O'donnell, 1",
    "sg:city":"Alacant",
    "sg:orig_category":"Ense\u00d1anza Variada",
    "sg:phone":"+34 965 13 14 38",
    "sg:postcode":"03003",
    "sg:province":"Alicante",
    "wof:name":"Roman Pastor Antonia",
    "wof:placetype":"venue"
},
  "geometry": {"coordinates":[-0.4902358949,38.3435211182],"type":"Point"}
}