{
  "type": "Feature",
  "properties": {
    "iso:country":"ES",
    "sg:address":"Calle de Juan Bautista Sacchetti, 4",
    "sg:city":"Madrid",
    "sg:orig_category":"Complementos De Vestir (al Por Menor)",
    "sg:phone":"+34 915 52 09 90",
    "sg:postcode":"28014",
    "sg:province":"Madrid",
    "wof:name":"Cruz Avalos Fernando",
    "wof:placetype":"venue"
},
  "geometry": {"coordinates":[-3.6876330376,40.4069290161],"type":"Point"}
}