{
  "type": "Feature",
  "properties": {
    "iso:country":"ES",
    "sg:address":"Ctra Base, Km. 0035,0",
    "sg:city":"Moron Frontera",
    "sg:orig_category":"Comit\u00c9s De Organizaci\u00d3n De Exposiciones, Ferias, Salones",
    "sg:phone":"+34 955 95 72 05",
    "sg:postcode":"41530",
    "sg:province":"Sevilla",
    "sg:website":"www.cortijodearenales.com",
    "wof:name":"Ruraltour De Arenales S.l.",
    "wof:placetype":"venue"
},
  "geometry": {"coordinates":[-5.4528231621,37.1294212341],"type":"Point"}
}