{
  "type": "Feature",
  "properties": {
    "addr:full":"Carretera De Maella, S/n Caspe Zaragoza 50700",
    "addr:housenumber":"s / n",
    "addr:postcode":"50700",
    "addr:street":"Carretera De Maella",
    "iso:country":"ES",
    "sg:address":"Carretera De Maella, S/n",
    "sg:city":"Caspe",
    "sg:orig_category":"Mec\u00c1nico Del Autom\u00d3vil",
    "sg:phone":"+34 976 63 17 06",
    "sg:postcode":"50700",
    "sg:province":"Zaragoza",
    "wof:name":"Piquer Franco Tomas",
    "wof:placetype":"venue"
},
  "geometry": {"coordinates":[-0.0385340005,41.2306289673],"type":"Point"}
}