{
  "type": "Feature",
  "properties": {
    "addr:full":"Calle de Escritor Atienza Huertos, 8 Malaga M\u00e1laga 29190",
    "addr:housenumber":"8",
    "addr:postcode":"29190",
    "addr:street":"Calle De Escritor Atienza Huertos;Ma\u0301Laga",
    "iso:country":"ES",
    "sg:address":"Calle de Escritor Atienza Huertos, 8",
    "sg:city":"Malaga",
    "sg:orig_category":"Peluquer\u00cdas, Peluquer\u00cda Mixta",
    "sg:phone":"+34 952 10 07 33",
    "sg:postcode":"29190",
    "sg:province":"M\u00e1laga",
    "wof:name":"Rubio Rueda Ruben",
    "wof:placetype":"venue"
},
  "geometry": {"coordinates":[-4.4798049927,36.7387504578],"type":"Point"}
}