{
  "type": "Feature",
  "properties": {
    "addr:full":"Carrer de Mujal, S/n Navas Barcelona 08670",
    "addr:housenumber":"s",
    "addr:postcode":"08670",
    "addr:street":"Carrer De Mujal;/ N",
    "iso:country":"ES",
    "sg:address":"Carrer de Mujal, S/n",
    "sg:city":"Navas",
    "sg:orig_category":"Maquinaria Para Industrias Diversas",
    "sg:phone":"+34 938 39 05 98",
    "sg:postcode":"08670",
    "sg:province":"Barcelona",
    "wof:name":"Excavacions Mujal S.l.",
    "wof:placetype":"venue"
},
  "geometry": {"coordinates":[1.8778250217,41.8981285095],"type":"Point"}
}