{
  "type": "Feature",
  "properties": {
    "addr:full":"Avda Erdotza, S/n Markina-xemein Vizcaya 48270",
    "addr:housenumber":"s / n",
    "addr:postcode":"48270",
    "addr:street":"Avda Erdotza",
    "iso:country":"ES",
    "sg:address":"Avda Erdotza, S/n",
    "sg:city":"Markina-xemein",
    "sg:orig_category":"Mec\u00c1nico Del Autom\u00d3vil",
    "sg:phone":"+34 946 16 62 76",
    "sg:postcode":"48270",
    "sg:province":"Vizcaya",
    "wof:name":"Markina Motor S.a.",
    "wof:placetype":"venue"
},
  "geometry": {"coordinates":[-2.5144650936,43.264503479],"type":"Point"}
}