{
  "type": "Feature",
  "properties": {
    "addr:full":"Av Jorda, 29 Barcelona Barcelona 08035",
    "addr:housenumber":"29",
    "addr:postcode":"08035",
    "addr:street":"Av Jorda",
    "iso:country":"ES",
    "sg:address":"Av Jorda, 29",
    "sg:city":"Barcelona",
    "sg:orig_category":"Supermercados Y Hipermercados",
    "sg:phone":"+34 932 12 54 80",
    "sg:postcode":"08035",
    "sg:province":"Barcelona",
    "wof:name":"Ziur Alimentacion S.l.l.",
    "wof:placetype":"venue"
},
  "geometry": {"coordinates":[2.136692524,41.4272232056],"type":"Point"}
}