{
  "type": "Feature",
  "properties": {
    "iso:country":"ES",
    "sg:address":"Carrer de Sant Isidor, 70",
    "sg:city":"Sabadell",
    "sg:orig_category":"M\u00c1rmoles, Granitos Y Piedras Naturales",
    "sg:phone":"+34 937 23 35 87",
    "sg:postcode":"08206",
    "sg:province":"Barcelona",
    "wof:name":"Marmoles J-p S.l.",
    "wof:placetype":"venue"
},
  "geometry": {"coordinates":[2.0831429958,41.5528945923],"type":"Point"}
}