{
  "type": "Feature",
  "properties": {
    "iso:country":"ES",
    "sg:address":"Calle de Estanco (del), 10",
    "sg:city":"Colmenar Viejo",
    "sg:orig_category":"Publicidad (soportes Y Gesti\u00d3n)",
    "sg:phone":"+34 918 46 43 75",
    "sg:postcode":"28770",
    "sg:province":"Madrid",
    "wof:name":"Gallego Colmenarejo Juan Manuel",
    "wof:placetype":"venue"
},
  "geometry": {"coordinates":[-3.7649366856,40.6594848633],"type":"Point"}
}