{
  "type": "Feature",
  "properties": {
    "iso:country":"ES",
    "sg:address":"Carrer de Pompeu Fabra, 53",
    "sg:city":"Santa Coloma De Gramenet",
    "sg:orig_category":"Radiocomunicaciones, Telefon\u00cda M\u00d3vil, Radiomensajer\u00cda: Servicios, Comercializaci\u00d3n",
    "sg:phone":"+34 934 66 13 03",
    "sg:postcode":"08922",
    "sg:province":"Barcelona",
    "wof:name":"Azad  Sattar",
    "wof:placetype":"venue"
},
  "geometry": {"coordinates":[2.2059209347,41.449508667],"type":"Point"}
}