{
  "type": "Feature",
  "properties": {
    "addr:full":"Plaz Mayor, 1 Solana Ciudad Real 13240",
    "addr:housenumber":"1",
    "addr:postcode":"solana;13240",
    "addr:street":"Plaz Mayor;Real",
    "iso:country":"ES",
    "sg:address":"Plaz Mayor, 1",
    "sg:city":"Solana",
    "sg:orig_category":"Ense\u00d1anza, Formaci\u00d3n Profesional: Aprendizaje",
    "sg:phone":"+34 926 63 11 82",
    "sg:postcode":"13240",
    "sg:province":"Ciudad Real",
    "wof:name":"Ayuntamiento De La Solana",
    "wof:placetype":"venue"
},
  "geometry": {"coordinates":[-3.2390003204,38.9420280457],"type":"Point"}
}