{
  "type": "Feature",
  "properties": {
    "iso:country":"ES",
    "sg:address":"Calle de Circunvalacion, 6",
    "sg:city":"Torrejon Ardoz",
    "sg:orig_category":"Bancos",
    "sg:phone":"+34 916 56 41 01",
    "sg:postcode":"28850",
    "sg:province":"Madrid",
    "wof:name":"Banco Espa\u00f1ol De Credito S.a.",
    "wof:placetype":"venue"
},
  "geometry": {"coordinates":[-3.4631280899,40.4499168396],"type":"Point"}
}