{
  "type": "Feature",
  "properties": {
    "addr:full":"Carr Gabriel Ciscar, 42 Oliva Valencia 46780",
    "addr:housenumber":"42",
    "addr:postcode":"46780",
    "addr:street":"Carr Gabriel Ciscar",
    "iso:country":"ES",
    "sg:address":"Carr Gabriel Ciscar, 42",
    "sg:city":"Oliva",
    "sg:orig_category":"Comercio, Reparaci\u00d3n De Motocicletas, Bicicletas Y Piezas Sueltas",
    "sg:phone":"+34 962 85 20 09",
    "sg:postcode":"46780",
    "sg:province":"Valencia",
    "wof:name":"Vidal Morell Juan Antonio",
    "wof:placetype":"venue"
},
  "geometry": {"coordinates":[-0.1171419993,38.9176330566],"type":"Point"}
}