{
  "type": "Feature",
  "properties": {
    "iso:country":"ES",
    "sg:address":"Ctra Puebla Farnals, S/n",
    "sg:city":"Puig",
    "sg:orig_category":"Deportes Y Ocio: Art\u00cdculos Y Ropas (al Por Menor Y Accesorios)",
    "sg:phone":"+34 961 47 26 57",
    "sg:postcode":"46540",
    "sg:province":"Valencia",
    "sg:website":"www.contactouno.net",
    "wof:name":"Bernet Cerezuela Enrique",
    "wof:placetype":"venue"
},
  "geometry": {"coordinates":[-0.3003390133,39.5875854492],"type":"Point"}
}