{
  "type": "Feature",
  "properties": {
    "addr:full":"Carrer de Miguel De Cervantes, 10 Cornella Llobregat Barcelona 08940",
    "addr:housenumber":"10",
    "addr:postcode":"08940",
    "addr:street":"Carrer De Miguel De Cervantes",
    "iso:country":"ES",
    "sg:address":"Carrer de Miguel De Cervantes, 10",
    "sg:city":"Cornella Llobregat",
    "sg:orig_category":"Mec\u00c1nico Del Autom\u00d3vil",
    "sg:phone":"+34 933 75 61 54",
    "sg:postcode":"08940",
    "sg:province":"Barcelona",
    "wof:name":"Lopez Jimenez Juan Antonio",
    "wof:placetype":"venue"
},
  "geometry": {"coordinates":[2.0715329647,41.3648452759],"type":"Point"}
}