{
  "type": "Feature",
  "properties": {
    "addr:full":"Calle de Galileo, 19 Madrid Madrid 28015",
    "addr:housenumber":"19",
    "addr:postcode":"madrid;28015",
    "addr:street":"Calle De Galileo",
    "iso:country":"ES",
    "sg:address":"Calle de Galileo, 19",
    "sg:city":"Madrid",
    "sg:orig_category":"Librer\u00cdas",
    "sg:phone":"+34 915 91 35 69",
    "sg:postcode":"28015",
    "sg:province":"Madrid",
    "wof:name":"Libropiel S.l.",
    "wof:placetype":"venue"
},
  "geometry": {"coordinates":[-3.7105879784,40.4320030212],"type":"Point"}
}