{
  "type": "Feature",
  "properties": {
    "iso:country":"ES",
    "sg:address":"Carrer de Industria, S/n",
    "sg:city":"Vimbodi",
    "sg:orig_category":"Arquitectos",
    "sg:phone":"+34 977 87 82 84",
    "sg:postcode":"43430",
    "sg:province":"Tarragona",
    "sg:website":"www.arinsa.com",
    "wof:name":"Miro Rufa Jose Maria",
    "wof:placetype":"venue"
},
  "geometry": {"coordinates":[1.0490460396,41.401348114],"type":"Point"}
}