{
  "type": "Feature",
  "properties": {
    "iso:country":"ES",
    "sg:address":"Calle de Lavadero, S/n",
    "sg:city":"Sanchonu\u00d1o",
    "sg:orig_category":"Material Y Suministros Para Horticultura, Arboricultura",
    "sg:phone":"+34 921 16 02 36",
    "sg:postcode":"40297",
    "sg:province":"Segovia",
    "wof:name":"Las Lagunas De Sanchonu\u00d1o S.a.",
    "wof:placetype":"venue"
},
  "geometry": {"coordinates":[-4.3067541122,41.3236808777],"type":"Point"}
}