{
  "type": "Feature",
  "properties": {
    "iso:country":"ES",
    "sg:address":"Carr Catalunya, 15",
    "sg:city":"Vidreres",
    "sg:orig_category":"Molduras, Junquillos, Listones Y Molduras Perforadas",
    "sg:phone":"+34 972 85 00 57",
    "sg:postcode":"17411",
    "sg:province":"Girona",
    "wof:name":"Casino La Union",
    "wof:placetype":"venue"
},
  "geometry": {"coordinates":[2.7798368931,41.7893943787],"type":"Point"}
}