{
  "type": "Feature",
  "properties": {
    "addr:full":"Calle de Zurita, 4 Zaragoza Zaragoza 50001",
    "addr:housenumber":"4",
    "addr:postcode":"50001",
    "addr:street":"Calle De Zurita",
    "iso:country":"ES",
    "sg:address":"Calle de Zurita, 4",
    "sg:city":"Zaragoza",
    "sg:orig_category":"Abogados",
    "sg:phone":"+34 976 23 83 52",
    "sg:postcode":"50001",
    "sg:province":"Zaragoza",
    "wof:name":"Arnedo Areitio Jose Alfonso De",
    "wof:placetype":"venue"
},
  "geometry": {"coordinates":[-0.8823856115,41.650390625],"type":"Point"}
}