{
  "type": "Feature",
  "properties": {
    "iso:country":"ES",
    "sg:address":"Calle de Fruela, 4",
    "sg:city":"Oviedo",
    "sg:orig_category":"Ense\u00d1anza: Idiomas",
    "sg:phone":"+34 985 22 97 96",
    "sg:postcode":"33007",
    "sg:province":"Asturias",
    "wof:name":"Dillon Lopez S.l.",
    "wof:placetype":"venue"
},
  "geometry": {"coordinates":[-5.8462147713,43.3609008789],"type":"Point"}
}