{
  "type": "Feature",
  "properties": {
    "addr:full":"Calle de Diputacion Provincial, 14 Nerja M\u00e1laga 29780",
    "addr:housenumber":"14",
    "addr:postcode":"29780",
    "addr:street":"Calle De Diputacion Provincial",
    "iso:country":"ES",
    "sg:address":"Calle de Diputacion Provincial, 14",
    "sg:city":"Nerja",
    "sg:orig_category":"Textil",
    "sg:phone":"+34 952 52 06 93",
    "sg:postcode":"29780",
    "sg:province":"M\u00e1laga",
    "wof:name":"Arrabal Ruiz Expedito",
    "wof:placetype":"venue"
},
  "geometry": {"coordinates":[-3.8789989948,36.7454566956],"type":"Point"}
}