{
  "type": "Feature",
  "properties": {
    "iso:country":"ES",
    "sg:address":"Carrer de Marian Aguilo, 1",
    "sg:city":"Palma",
    "sg:orig_category":"Doctores En Medicina",
    "sg:phone":"+34 971 24 84 58",
    "sg:postcode":"07005",
    "sg:province":"Islas Baleares",
    "wof:name":"Salom Santana Andres Arturo",
    "wof:placetype":"venue"
},
  "geometry": {"coordinates":[2.6608240604,39.5765266418],"type":"Point"}
}