{
  "type": "Feature",
  "properties": {
    "iso:country":"ES",
    "sg:address":"Calle de Bolivar, 3",
    "sg:city":"Madrid",
    "sg:orig_category":"Delegados, Agentes De Tr\u00c1nsito, Auxiliares De Transporte Internacional",
    "sg:phone":"+34 914 67 44 76",
    "sg:postcode":"28045",
    "sg:province":"Madrid",
    "wof:name":"Trujillo Reynaldo Alan Jose",
    "wof:placetype":"venue"
},
  "geometry": {"coordinates":[-3.6942310333,40.3915405273],"type":"Point"}
}