{
  "type": "Feature",
  "properties": {
    "iso:country":"ES",
    "sg:address":"Auto Salou A Reus (de), Km. 0013,0",
    "sg:city":"Salou",
    "sg:orig_category":"Mec\u00c1nico Del Autom\u00d3vil",
    "sg:phone":"+34 977 38 56 35",
    "sg:postcode":"43840",
    "sg:province":"Tarragona",
    "wof:name":"Trivi\u00f1o Perez Miguel",
    "wof:placetype":"venue"
},
  "geometry": {"coordinates":[1.136950016,41.0749702454],"type":"Point"}
}