{
  "type": "Feature",
  "properties": {
    "iso:country":"ES",
    "sg:address":"Carrer de Temple De Sant Telm, 16",
    "sg:city":"Denia",
    "sg:orig_category":"Comit\u00c9s De Organizaci\u00d3n De Exposiciones, Ferias, Salones",
    "sg:phone":"+34 965 78 72 98",
    "sg:postcode":"03700",
    "sg:province":"Alicante",
    "sg:website":"www.avima.com",
    "wof:name":"Costa Delgado Maria Del Carmen",
    "wof:placetype":"venue"
},
  "geometry": {"coordinates":[0.1108110026,38.8415908813],"type":"Point"}
}