{
  "type": "Feature",
  "properties": {
    "addr:full":"Av Princep D'asturies, 33 Barcelona Barcelona 08012",
    "addr:housenumber":"33",
    "addr:postcode":"08012",
    "addr:street":"Av Princep D'Asturies",
    "iso:country":"ES",
    "sg:address":"Av Princep D'asturies, 33",
    "sg:city":"Barcelona",
    "sg:orig_category":"Panader\u00cdas, Panader\u00cdas",
    "sg:phone":"+34 932 18 38 99",
    "sg:postcode":"08012",
    "sg:province":"Barcelona",
    "wof:name":"Jaran 33 S.l.",
    "wof:placetype":"venue"
},
  "geometry": {"coordinates":[2.1500155926,41.4038352966],"type":"Point"}
}