{
  "type": "Feature",
  "properties": {
    "iso:country":"ES",
    "sg:address":"Carrer de Fontanelles (de Les), 17",
    "sg:city":"Borges Del Camp",
    "sg:orig_category":"Empresas De Desmonte",
    "sg:phone":"+34 977 56 02 73",
    "sg:postcode":"43350",
    "sg:province":"Tarragona",
    "wof:name":"Chaparro Cuestas Eusebio",
    "wof:placetype":"venue"
},
  "geometry": {"coordinates":[1.0235249996,41.1695747375],"type":"Point"}
}