{
  "type": "Feature",
  "properties": {
    "addr:full":"Ptda La Canal, S/n Ontinyent Valencia 46870",
    "addr:housenumber":"s",
    "addr:postcode":"46870",
    "addr:street":"Ptda La Canal;/ N",
    "iso:country":"ES",
    "sg:address":"Ptda La Canal, S/n",
    "sg:city":"Ontinyent",
    "sg:orig_category":"Control T\u00c9cnico De Veh\u00cdculos",
    "sg:phone":"+34 962 91 07 20",
    "sg:postcode":"46870",
    "sg:province":"Valencia",
    "sg:website":"www.sircuitv.com",
    "wof:name":"Aseguramiento Tecnico De La Calidad S.a.",
    "wof:placetype":"venue"
},
  "geometry": {"coordinates":[-0.6583330035,38.7977752686],"type":"Point"}
}