{
  "type": "Feature",
  "properties": {
    "addr:full":"Calle de Alto Soria, 5 Alcazar S. Juan Ciudad Real 13600",
    "addr:housenumber":"5",
    "addr:postcode":"13600",
    "addr:street":"Calle De Alto Soria;Alcazar S. Juan Ciudad Real",
    "iso:country":"ES",
    "sg:address":"Calle de Alto Soria, 5",
    "sg:city":"Alcazar S. Juan",
    "sg:orig_category":"Reposter\u00cdas",
    "sg:phone":"+34 926 54 04 86",
    "sg:postcode":"13600",
    "sg:province":"Ciudad Real",
    "wof:name":"Santiago Campo Jose",
    "wof:placetype":"venue"
},
  "geometry": {"coordinates":[-3.2120680809,39.3943939209],"type":"Point"}
}