{
  "type": "Feature",
  "properties": {
    "addr:full":"Calle de Rufino Sanchez, 5 Matas-pinar-monte Rozas Madrid 28290",
    "addr:housenumber":"5",
    "addr:postcode":"28290",
    "addr:street":"Calle De Rufino Sanchez",
    "iso:country":"ES",
    "sg:address":"Calle de Rufino Sanchez, 5",
    "sg:city":"Matas-pinar-monte Rozas",
    "sg:orig_category":"Platos Preparados Refrigerados (fabricaci\u00d3n, Al Por Mayor)",
    "sg:phone":"+34 916 30 29 23",
    "sg:postcode":"28290",
    "sg:province":"Madrid",
    "wof:name":"Las Comidas Caseras De Maria Recio C.b.",
    "wof:placetype":"venue"
},
  "geometry": {"coordinates":[-3.8956000805,40.5530662537],"type":"Point"}
}