{
  "type": "Feature",
  "properties": {
    "iso:country":"ES",
    "sg:address":"Avda Aragon, 50",
    "sg:city":"Montalban",
    "sg:orig_category":"Farmacias",
    "sg:phone":"+34 978 75 05 54",
    "sg:postcode":"44700",
    "sg:province":"Teruel",
    "wof:name":"Martinez Garcia Fernando",
    "wof:placetype":"venue"
},
  "geometry": {"coordinates":[-0.804314971,40.831867218],"type":"Point"}
}