{
  "type": "Feature",
  "properties": {
    "iso:country":"ES",
    "sg:address":"Calle de Toneleros, 7",
    "sg:city":"Conil De La Frontera",
    "sg:orig_category":"Promotores Constructores",
    "sg:phone":"+34 956 44 44 01",
    "sg:postcode":"11140",
    "sg:province":"C\u00e1diz",
    "wof:name":"Construcciones Bernabe Gallardo S.l.",
    "wof:placetype":"venue"
},
  "geometry": {"coordinates":[-6.0883159637,36.2785606384],"type":"Point"}
}