{
  "type": "Feature",
  "properties": {
    "addr:full":"Avgd De Daniel Gil, 36 Ontinyent Valencia 46870",
    "addr:housenumber":"36",
    "addr:postcode":"46870",
    "addr:street":"Gil",
    "iso:country":"ES",
    "sg:address":"Avgd De Daniel Gil, 36",
    "sg:city":"Ontinyent",
    "sg:orig_category":"Fabricaci\u00d3n, Venta De Cuadros, Accesorios Para Enmarcar",
    "sg:phone":"+34 962 38 32 18",
    "sg:postcode":"46870",
    "sg:province":"Valencia",
    "wof:name":"Mico Molla Jorge",
    "wof:placetype":"venue"
},
  "geometry": {"coordinates":[-0.6014829874,38.8232917786],"type":"Point"}
}