{
  "type": "Feature",
  "properties": {
    "iso:country":"ES",
    "sg:address":"Calle de Fernando El Catolico, 82",
    "sg:city":"Madrid",
    "sg:orig_category":"Asociaciones Y Clubs Deportivos",
    "sg:phone":"+34 915 43 76 52",
    "sg:postcode":"28015",
    "sg:province":"Madrid",
    "wof:name":"Cocigas S.l.",
    "wof:placetype":"venue"
},
  "geometry": {"coordinates":[-3.7164471149,40.4346008301],"type":"Point"}
}