{
  "type": "Feature",
  "properties": {
    "addr:full":"Calle de Jata, 7 Andra Mari Vizcaya 48993",
    "addr:housenumber":"7",
    "addr:postcode":"48993",
    "addr:street":"Calle De Jata",
    "iso:country":"ES",
    "sg:address":"Calle de Jata, 7",
    "sg:city":"Andra Mari",
    "sg:orig_category":"Promotores Constructores",
    "sg:phone":"+34 944 60 52 07",
    "sg:postcode":"48993",
    "sg:province":"Vizcaya",
    "wof:name":"Iruane S.l.",
    "wof:placetype":"venue"
},
  "geometry": {"coordinates":[-2.7541499138,43.2982711792],"type":"Point"}
}