{
  "type": "Feature",
  "properties": {
    "addr:full":"Calle de Gomez Tejedor, 6 Pozuelo De Alarcon Madrid 28224",
    "addr:housenumber":"6",
    "addr:postcode":"28224",
    "addr:street":"Calle De Gomez Tejedor",
    "iso:country":"ES",
    "sg:address":"Calle de Gomez Tejedor, 6",
    "sg:city":"Pozuelo De Alarcon",
    "sg:orig_category":"Promotores Constructores",
    "sg:phone":"+34 913 51 55 21",
    "sg:postcode":"28224",
    "sg:province":"Madrid",
    "wof:name":"Holmes & Watson S.l.",
    "wof:placetype":"venue"
},
  "geometry": {"coordinates":[-3.8039870262,40.4514312744],"type":"Point"}
}