{
  "type": "Feature",
  "properties": {
    "addr:full":"Calle de Monasterio De Las Descalzas Reales, 16 Zaragoza Zaragoza 50014",
    "addr:housenumber":"16",
    "addr:postcode":"50014",
    "addr:street":"Calle De Monasterio De Las Descalzas Reales",
    "iso:country":"ES",
    "sg:address":"Calle de Monasterio De Las Descalzas Reales, 16",
    "sg:city":"Zaragoza",
    "sg:orig_category":"Mec\u00c1nico Del Autom\u00d3vil",
    "sg:phone":"+34 976 47 09 07",
    "sg:postcode":"50014",
    "sg:province":"Zaragoza",
    "wof:name":"La Jota Cogullada S.l.",
    "wof:placetype":"venue"
},
  "geometry": {"coordinates":[-0.8625040054,41.6744613647],"type":"Point"}
}