{
  "type": "Feature",
  "properties": {
    "addr:full":"Praz Rei (do), 5 Lugo Lugo 27002",
    "addr:housenumber":"5",
    "addr:postcode":"27002",
    "iso:country":"ES",
    "sg:address":"Praz Rei (do), 5",
    "sg:city":"Lugo",
    "sg:orig_category":"Sociedades, Compa\u00d1\u00cdas Aseguradoras",
    "sg:phone":"+34 982 25 18 97",
    "sg:postcode":"27002",
    "sg:province":"Lugo",
    "wof:name":"Santa Lucia S.a.",
    "wof:placetype":"venue"
},
  "geometry": {"coordinates":[-7.5502867699,43.0047264099],"type":"Point"}
}