{
  "type": "Feature",
  "properties": {
    "addr:full":"Carr Independencia, 227 Badalona Barcelona 08915",
    "addr:housenumber":"227",
    "addr:postcode":"08915",
    "addr:street":"Carr Independencia",
    "iso:country":"ES",
    "sg:address":"Carr Independencia, 227",
    "sg:city":"Badalona",
    "sg:orig_category":"Bazares, Art\u00cdculos De Limpieza Y De Cocina (al Por Menor)",
    "sg:phone":"+34 933 83 77 27",
    "sg:postcode":"08915",
    "sg:province":"Barcelona",
    "wof:name":"Botigues Nxp S.c.p.",
    "wof:placetype":"venue"
},
  "geometry": {"coordinates":[2.2412800789,41.4603233337],"type":"Point"}
}