{
  "type": "Feature",
  "properties": {
    "addr:full":"Carrer de Leonardo Da Vinci, 39 Sabadell Barcelona 08204",
    "addr:housenumber":"39",
    "addr:postcode":"08204",
    "addr:street":"Carrer De Leonardo Da Vinci",
    "iso:country":"ES",
    "sg:address":"Carrer de Leonardo Da Vinci, 39",
    "sg:city":"Sabadell",
    "sg:orig_category":"Asociaciones Y Clubs Deportivos",
    "sg:phone":"+34 937 11 54 41",
    "sg:postcode":"08204",
    "sg:province":"Barcelona",
    "wof:name":"Paez Barrero Manuel",
    "wof:placetype":"venue"
},
  "geometry": {"coordinates":[2.1119799614,41.5230789185],"type":"Point"}
}