{
  "type": "Feature",
  "properties": {
    "addr:full":"Ctra Jaen (p I Mirabueno), 126 Torredonjimeno Ja\u00e9n 23650",
    "addr:housenumber":"126",
    "addr:postcode":"23650",
    "addr:street":"Ctra Jaen P;Mirabueno",
    "iso:country":"ES",
    "sg:address":"Ctra Jaen (p I Mirabueno), 126",
    "sg:city":"Torredonjimeno",
    "sg:orig_category":"Tapicer\u00cdas",
    "sg:phone":"+34 953 34 40 60",
    "sg:postcode":"23650",
    "sg:province":"Ja\u00e9n",
    "wof:name":"Trigo Guardia Juan Manuel",
    "wof:placetype":"venue"
},
  "geometry": {"coordinates":[-3.9366519451,37.7623558044],"type":"Point"}
}