{
  "type": "Feature",
  "properties": {
    "addr:full":"Av Roma, 43 Barcelona Barcelona 08029",
    "addr:housenumber":"43",
    "addr:postcode":"08029",
    "addr:street":"Av Roma",
    "iso:country":"ES",
    "sg:address":"Av Roma, 43",
    "sg:city":"Barcelona",
    "sg:classifiers":[
        {
            "category":"Arts & Performance",
            "subcategory":"Art Gallery",
            "type":"Entertainment"
        }
    ],
    "sg:phone":"+34 934 30 91 79",
    "sg:postcode":"08029",
    "sg:province":"Barcelona",
    "sg:tags":[
        "arte",
        "de",
        "galer\u00cdas"
    ],
    "sg:website":"www.artetopaz.com",
    "wof:name":"Arte Topaz S.l.",
    "wof:placetype":"venue"
},
  "geometry": {"coordinates":[2.1466758251,41.3821716309],"type":"Point"}
}