{
  "type": "Feature",
  "properties": {
    "iso:country":"ES",
    "sg:address":"Calle de Luis Braille, 1",
    "sg:city":"Baza",
    "sg:orig_category":"Supermercados Y Hipermercados",
    "sg:phone":"+34 958 70 14 53",
    "sg:postcode":"18800",
    "sg:province":"Granada",
    "wof:name":"Herrera Brocal Antonio",
    "wof:placetype":"venue"
},
  "geometry": {"coordinates":[-2.7669289112,37.4913291931],"type":"Point"}
}