{
  "type": "Feature",
  "properties": {
    "iso:country":"ES",
    "sg:address":"Calle de Murillo, 17",
    "sg:city":"Hoya Del Campo",
    "sg:orig_category":"Construcci\u00d3n Mec\u00c1nica",
    "sg:phone":"+34 968 77 61 33",
    "sg:postcode":"30559",
    "sg:province":"Murcia",
    "wof:name":"Construcciones Tornero Y Pagan,s.l.",
    "wof:placetype":"venue"
},
  "geometry": {"coordinates":[-1.3382240534,38.2401199341],"type":"Point"}
}