{
  "type": "Feature",
  "properties": {
    "addr:full":"Calle de Julio Saez De La Hoya, 11 Burgos Burgos 09005",
    "addr:housenumber":"11",
    "addr:postcode":"09005",
    "addr:street":"Calle De Julio Saez De La Hoya",
    "iso:country":"ES",
    "sg:address":"Calle de Julio Saez De La Hoya, 11",
    "sg:city":"Burgos",
    "sg:orig_category":"Abogados",
    "sg:phone":"+34 947 21 19 43",
    "sg:postcode":"09005",
    "sg:province":"Burgos",
    "wof:name":"Llarena Conde I\u00f1igo",
    "wof:placetype":"venue"
},
  "geometry": {"coordinates":[-3.6973137856,42.345123291],"type":"Point"}
}