{
  "type": "Feature",
  "properties": {
    "addr:full":"Ctra. Pe\u00f1afiel, Km. 0004,2 Curiel De Duero Valladolid 47316",
    "addr:postcode":"47316",
    "addr:street":"Ctra. Pen\u0303Afiel Km. 0004,2",
    "iso:country":"ES",
    "sg:address":"Ctra. Pe\u00f1afiel, Km. 0004,2",
    "sg:city":"Curiel De Duero",
    "sg:orig_category":"Productores Recolectores, Venta Directa De Vinos",
    "sg:phone":"+34 983 87 80 88",
    "sg:postcode":"47316",
    "sg:province":"Valladolid",
    "wof:name":"Legaris S.l.",
    "wof:placetype":"venue"
},
  "geometry": {"coordinates":[-4.1452689171,41.6755561829],"type":"Point"}
}