{
  "type": "Feature",
  "properties": {
    "iso:country":"ES",
    "sg:address":"Calle de Epalza Viuda De, 6",
    "sg:city":"Bilbao",
    "sg:orig_category":"Artesan\u00cda Y Trabajos Manuales: Suministros (al Por Menor)",
    "sg:phone":"+34 944 79 28 62",
    "sg:postcode":"48005",
    "sg:province":"Vizcaya",
    "wof:name":"Asociacion Kidenda",
    "wof:placetype":"venue"
},
  "geometry": {"coordinates":[-2.9228870869,43.2611923218],"type":"Point"}
}