{
  "type": "Feature",
  "properties": {
    "iso:country":"ES",
    "sg:address":"Cno Mareny, S/n",
    "sg:city":"Sueca",
    "sg:orig_category":"Lavado, Limpieza De Veh\u00cdculos",
    "sg:phone":"+34 961 70 59 08",
    "sg:postcode":"46410",
    "sg:province":"Valencia",
    "wof:name":"Enrique Sapi\u00f1a Guerra Y Otros Cdad.",
    "wof:placetype":"venue"
},
  "geometry": {"coordinates":[-0.3072090149,39.207359314],"type":"Point"}
}