{
  "type": "Feature",
  "properties": {
    "iso:country":"ES",
    "sg:address":"Calle de Camarena, 163",
    "sg:city":"Madrid",
    "sg:orig_category":"Agentes Generales De Seguros",
    "sg:phone":"+34 917 19 24 69",
    "sg:postcode":"28047",
    "sg:province":"Madrid",
    "wof:name":"Ayuso Lopez Arturo",
    "wof:placetype":"venue"
},
  "geometry": {"coordinates":[-3.7555289268,40.3893241882],"type":"Point"}
}