{
  "type": "Feature",
  "properties": {
    "addr:full":"Avda. Torre, 24 Rincon Victoria M\u00e1laga 29730",
    "addr:housenumber":"24",
    "addr:postcode":"29730",
    "addr:street":"Avda. Torre;Ma\u0301Laga",
    "iso:country":"ES",
    "sg:address":"Avda. Torre, 24",
    "sg:city":"Rincon Victoria",
    "sg:orig_category":"Hospitales",
    "sg:phone":"+34 952 97 80 59",
    "sg:postcode":"29730",
    "sg:province":"M\u00e1laga",
    "wof:name":"Clinica Rincon Bejar S.l.",
    "wof:placetype":"venue"
},
  "geometry": {"coordinates":[-4.2807641029,36.714641571],"type":"Point"}
}