{
  "type": "Feature",
  "properties": {
    "addr:full":"Avda Constitucion (la), 14 Castro Urdiales Cantabria 39700",
    "addr:housenumber":"14",
    "addr:postcode":"39700",
    "addr:street":"Avda Constitucion La",
    "iso:country":"ES",
    "sg:address":"Avda Constitucion (la), 14",
    "sg:city":"Castro Urdiales",
    "sg:orig_category":"Inmobiliaria (agencias)",
    "sg:phone":"+34 942 86 18 86",
    "sg:postcode":"39700",
    "sg:province":"Cantabria",
    "wof:name":"Serrat Robledo Jose Antonio",
    "wof:placetype":"venue"
},
  "geometry": {"coordinates":[-3.2174100876,43.3808555603],"type":"Point"}
}