{
  "type": "Feature",
  "properties": {
    "iso:country":"ES",
    "sg:address":"Calle de Boldano, 18",
    "sg:city":"Madrid",
    "sg:orig_category":"Complementos De Vestir (al Por Menor)",
    "sg:phone":"+34 914 08 95 42",
    "sg:postcode":"28027",
    "sg:province":"Madrid",
    "sg:website":"www.iespana.es/floresparacostura",
    "wof:name":"Agru\u00f1a Aymerich Rosari Maria",
    "wof:placetype":"venue"
},
  "geometry": {"coordinates":[-3.6412630081,40.4382209778],"type":"Point"}
}