{
  "type": "Feature",
  "properties": {
    "addr:full":"Carrer de Aneto, 3101 Sabadell Barcelona 08207",
    "addr:postcode":"3101;08207",
    "addr:street":"Carrer De Aneto",
    "iso:country":"ES",
    "sg:address":"Carrer de Aneto, 3101",
    "sg:city":"Sabadell",
    "sg:orig_category":"Empresas De Carpinter\u00cda De Madera",
    "sg:phone":"+34 937 23 41 32",
    "sg:postcode":"08207",
    "sg:province":"Barcelona",
    "wof:name":"Ebanisteria Y Carpinteria Aneto Scp",
    "wof:placetype":"venue"
},
  "geometry": {"coordinates":[2.0870499611,41.5695381165],"type":"Point"}
}