{
  "type": "Feature",
  "properties": {
    "iso:country":"ES",
    "sg:address":"Avda. Adelfas, 22",
    "sg:city":"Matalasca\u00f1as",
    "sg:orig_category":"Molduras, Junquillos, Listones Y Molduras Perforadas",
    "sg:phone":"+34 959 44 80 13",
    "sg:postcode":"21760",
    "sg:province":"Huelva",
    "wof:name":"Hernandez Alvarez Concepcion",
    "wof:placetype":"venue"
},
  "geometry": {"coordinates":[-6.5643391609,37.0083312988],"type":"Point"}
}