{
  "type": "Feature",
  "properties": {
    "iso:country":"ES",
    "sg:address":"Av Curia, 5",
    "sg:city":"Andratx",
    "sg:orig_category":"Inform\u00c1tica: Mantenimiento Y Reparaci\u00d3n De Ordenadores",
    "sg:phone":"+34 971 23 54 82",
    "sg:postcode":"07150",
    "sg:province":"Islas Baleares",
    "wof:name":"Prieto Duval Joaquin",
    "wof:placetype":"venue"
},
  "geometry": {"coordinates":[2.424282074,39.5765838623],"type":"Point"}
}