{
  "type": "Feature",
  "properties": {
    "iso:country":"ES",
    "sg:address":"Calle de Santa Apolonia, 152",
    "sg:city":"Aviles",
    "sg:orig_category":"Comercio De Cuadros, L\u00c1minas Y Reproducciones De Obras De Arte",
    "sg:phone":"+34 985 57 64 54",
    "sg:postcode":"33403",
    "sg:province":"Asturias",
    "wof:name":"Alvarez Pintado Ceferino",
    "wof:placetype":"venue"
},
  "geometry": {"coordinates":[-5.9078798294,43.546585083],"type":"Point"}
}