{
  "type": "Feature",
  "properties": {
    "addr:full":"Calle de Vergel, 2 Denia Alicante 03700",
    "addr:housenumber":"2",
    "addr:postcode":"03700",
    "addr:street":"Calle De Vergel",
    "iso:country":"ES",
    "sg:address":"Calle de Vergel, 2",
    "sg:city":"Denia",
    "sg:orig_category":"Bares, Piano",
    "sg:phone":"+34 966 43 26 20",
    "sg:postcode":"03700",
    "sg:province":"Alicante",
    "sg:website":"www.ciberarenagames.com",
    "wof:name":"Santacreu Franco Raul",
    "wof:placetype":"venue"
},
  "geometry": {"coordinates":[0.10317,38.8373413086],"type":"Point"}
}