{
  "type": "Feature",
  "properties": {
    "iso:country":"ES",
    "sg:address":"Avda Ana De Viya, 17",
    "sg:city":"Cadiz",
    "sg:orig_category":"Ense\u00d1anza: Idiomas",
    "sg:phone":"+34 956 28 06 16",
    "sg:postcode":"11009",
    "sg:province":"C\u00e1diz",
    "wof:name":"Donovan  Alice",
    "wof:placetype":"venue"
},
  "geometry": {"coordinates":[-6.2789120674,36.5100860596],"type":"Point"}
}