{
  "type": "Feature",
  "properties": {
    "addr:full":"Rio Rubite, 3 Mijas Costa M\u00e1laga 29649",
    "addr:housenumber":"3",
    "addr:postcode":"29649",
    "addr:street":"Rubite",
    "iso:country":"ES",
    "sg:address":"Rio Rubite, 3",
    "sg:city":"Mijas Costa",
    "sg:orig_category":"Promotores Constructores",
    "sg:phone":"+34 952 46 70 77",
    "sg:postcode":"29649",
    "sg:province":"M\u00e1laga",
    "wof:name":"Blanco Postigo Carlos",
    "wof:placetype":"venue"
},
  "geometry": {"coordinates":[-4.6310629845,36.5238952637],"type":"Point"}
}