{
  "type": "Feature",
  "properties": {
    "addr:full":"Carrer de Santa Clara, 32 S. Pol Mar Barcelona 08395",
    "addr:housenumber":"32",
    "addr:postcode":"08395",
    "addr:street":"Carrer De Santa Clara;Pol;Barcelona",
    "iso:country":"ES",
    "sg:address":"Carrer de Santa Clara, 32",
    "sg:city":"S. Pol Mar",
    "sg:orig_category":"M\u00dasicos Int\u00c9rpretes",
    "sg:phone":"+34 937 60 13 83",
    "sg:postcode":"08395",
    "sg:province":"Barcelona",
    "wof:name":"C.c.p.tacet S.l.",
    "wof:placetype":"venue"
},
  "geometry": {"coordinates":[2.6230399609,41.6023635864],"type":"Point"}
}