{
  "type": "Feature",
  "properties": {
    "addr:full":"Calle de Santo Domingo, 11 Caceres C\u00e1ceres 10003",
    "addr:housenumber":"11",
    "addr:postcode":"10003",
    "addr:street":"Calle De Santo Domingo;Ca\u0301Ceres",
    "iso:country":"ES",
    "sg:address":"Calle de Santo Domingo, 11",
    "sg:city":"Caceres",
    "sg:orig_category":"Arquitectos",
    "sg:phone":"+34 927 22 15 06",
    "sg:postcode":"10003",
    "sg:province":"C\u00e1ceres",
    "wof:name":"Rubio Muriel Francisco Javier",
    "wof:placetype":"venue"
},
  "geometry": {"coordinates":[-6.3722639084,39.4764137268],"type":"Point"}
}