{
  "type": "Feature",
  "properties": {
    "iso:country":"ES",
    "sg:address":"Calle de Leganes (de), 6",
    "sg:city":"Fuenlabrada",
    "sg:orig_category":"Asesor\u00cda Fiscal Y Jur\u00cddica",
    "sg:phone":"+34 916 97 18 06",
    "sg:postcode":"28945",
    "sg:province":"Madrid",
    "wof:name":"Ferry Asesores S.l.",
    "wof:placetype":"venue"
},
  "geometry": {"coordinates":[-3.793749094,40.2845993042],"type":"Point"}
}