{
  "type": "Feature",
  "properties": {
    "addr:full":"Calle de Virgen De La Soledad, 28 Manzanares Ciudad Real 13200",
    "addr:housenumber":"28",
    "addr:postcode":"13200",
    "addr:street":"Calle De Virgen De La Soledad",
    "iso:country":"ES",
    "sg:address":"Calle de Virgen De La Soledad, 28",
    "sg:city":"Manzanares",
    "sg:orig_category":"Electricidad: Instaladores",
    "sg:phone":"+34 926 61 35 63",
    "sg:postcode":"13200",
    "sg:province":"Ciudad Real",
    "wof:name":"Gonzalez Alcaide Isabel",
    "wof:placetype":"venue"
},
  "geometry": {"coordinates":[-3.3765590191,38.9976615906],"type":"Point"}
}