{
  "type": "Feature",
  "properties": {
    "addr:full":"Calle de Le\u00d1eros, 25 Madrid Madrid 28039",
    "addr:housenumber":"25",
    "addr:postcode":"madrid;28039",
    "addr:street":"Calle De Len\u0303Eros",
    "iso:country":"ES",
    "sg:address":"Calle de Le\u00d1eros, 25",
    "sg:city":"Madrid",
    "sg:orig_category":"Guarder\u00cdas",
    "sg:phone":"+34 914 59 40 49",
    "sg:postcode":"28039",
    "sg:province":"Madrid",
    "wof:name":"La Flauta Dulde S.l.l.",
    "wof:placetype":"venue"
},
  "geometry": {"coordinates":[-3.7092599869,40.4540061951],"type":"Point"}
}