{
  "type": "Feature",
  "properties": {
    "iso:country":"ES",
    "sg:address":"E Poligono Industrial I, S/n",
    "sg:city":"Cintruenigo",
    "sg:orig_category":"Empresas De Carpinter\u00cda Met\u00c1lica",
    "sg:phone":"+34 948 81 50 52",
    "sg:postcode":"31592",
    "sg:province":"Navarra",
    "wof:name":"Carpinteria Metalica Hermanos Chibite S.l",
    "wof:placetype":"venue"
},
  "geometry": {"coordinates":[-1.7964639664,42.0835533142],"type":"Point"}
}