{
  "type": "Feature",
  "properties": {
    "iso:country":"ES",
    "sg:address":"Calle de Sevilla, 56",
    "sg:city":"Cabezas S. Juan",
    "sg:orig_category":"Alimentaci\u00d3n General (al Por Menor)",
    "sg:phone":"+34 955 87 03 85",
    "sg:postcode":"41730",
    "sg:province":"Sevilla",
    "wof:name":"Delgado Saborido Maria",
    "wof:placetype":"venue"
},
  "geometry": {"coordinates":[-5.9387688637,36.9864082336],"type":"Point"}
}