{
  "type": "Feature",
  "properties": {
    "iso:country":"ES",
    "sg:address":"Carrer de Bisbe Sivilla, 42",
    "sg:city":"Barcelona",
    "sg:orig_category":"Empresas De Carpinter\u00cda De Madera",
    "sg:phone":"+34 932 11 27 21",
    "sg:postcode":"08022",
    "sg:province":"Barcelona",
    "wof:name":"Esteban Santasusana Jose",
    "wof:placetype":"venue"
},
  "geometry": {"coordinates":[2.1342329979,41.404132843],"type":"Point"}
}