{
  "type": "Feature",
  "properties": {
    "addr:full":"Calle de Clavel (del), 5 Linea De La Concepcion C\u00e1diz 11300",
    "addr:housenumber":"5",
    "addr:postcode":"11300",
    "addr:street":"Calle De Clavel Del;Ca\u0301Diz",
    "iso:country":"ES",
    "sg:address":"Calle de Clavel (del), 5",
    "sg:city":"Linea De La Concepcion",
    "sg:orig_category":"Psic\u00d3logos",
    "sg:phone":"+34 956 76 93 35",
    "sg:postcode":"11300",
    "sg:province":"C\u00e1diz",
    "wof:name":"Vazquez Garcia Miguel",
    "wof:placetype":"venue"
},
  "geometry": {"coordinates":[-5.3483629227,36.1616706848],"type":"Point"}
}