{
  "type": "Feature",
  "properties": {
    "iso:country":"ES",
    "sg:address":"Avda Tinamar, 38",
    "sg:city":"Vega S. Mateo",
    "sg:orig_category":"Carnicer\u00cdas, Carnicer\u00cdas",
    "sg:phone":"+34 928 66 08 37",
    "sg:postcode":"35328",
    "sg:province":"Las Palmas",
    "wof:name":"Sanpequin S.l.",
    "wof:placetype":"venue"
},
  "geometry": {"coordinates":[-15.5824928284,28.0158691406],"type":"Point"}
}