{
  "type": "Feature",
  "properties": {
    "addr:full":"Calle de Chile, 24 Nerja M\u00e1laga 29780",
    "addr:housenumber":"24",
    "addr:postcode":"29780",
    "addr:street":"Calle De Chile",
    "iso:country":"ES",
    "sg:address":"Calle de Chile, 24",
    "sg:city":"Nerja",
    "sg:orig_category":"Supermercados Y Hipermercados",
    "sg:phone":"+34 952 52 04 20",
    "sg:postcode":"29780",
    "sg:province":"M\u00e1laga",
    "wof:name":"Mu\u00f1oz Cecilia Antonio",
    "wof:placetype":"venue"
},
  "geometry": {"coordinates":[-3.8751642704,36.7519035339],"type":"Point"}
}