{
  "type": "Feature",
  "properties": {
    "iso:country":"ES",
    "sg:address":"Calle de Horno De San Gil, 1",
    "sg:city":"Guadalajara",
    "sg:orig_category":"Arquitectos",
    "sg:phone":"+34 949 21 44 82",
    "sg:postcode":"19001",
    "sg:province":"Guadalajara",
    "wof:name":"Tecnicos Asesores Urbanos S.l.",
    "wof:placetype":"venue"
},
  "geometry": {"coordinates":[-3.1658489704,40.634021759],"type":"Point"}
}