{
  "type": "Feature",
  "properties": {
    "iso:country":"ES",
    "sg:address":"Calle de Ventas, 17",
    "sg:city":"San Pablo De Los Montes",
    "sg:orig_category":"Alimentaci\u00d3n General (al Por Menor)",
    "sg:phone":"+34 925 41 52 73",
    "sg:postcode":"45120",
    "sg:province":"Toledo",
    "wof:name":"Castro Galan Faustino",
    "wof:placetype":"venue"
},
  "geometry": {"coordinates":[-4.3296399117,39.5407104492],"type":"Point"}
}