{
  "type": "Feature",
  "properties": {
    "iso:country":"ES",
    "sg:address":"Calle de Libertad, 17",
    "sg:city":"Pola De Laviana",
    "sg:orig_category":"Caf\u00c9s, Bares, Cervecer\u00cdas",
    "sg:phone":"+34 985 60 00 19",
    "sg:postcode":"33980",
    "sg:province":"Asturias",
    "wof:name":"Rodriguez Fernandez Julio",
    "wof:placetype":"venue"
},
  "geometry": {"coordinates":[-5.562710762,43.2481765747],"type":"Point"}
}