{
  "type": "Feature",
  "properties": {
    "iso:country":"ES",
    "sg:address":"Calle de Portal, 9",
    "sg:city":"Torrente Cinca",
    "sg:orig_category":"Cajas Para Embalar",
    "sg:phone":"+34 974 46 72 60",
    "sg:postcode":"22590",
    "sg:province":"Huesca",
    "sg:website":"www.cajarural.com",
    "wof:name":"Caja Rural Aragonesa Y De Los Pirineos",
    "wof:placetype":"venue"
},
  "geometry": {"coordinates":[0.3358049989,41.4736442566],"type":"Point"}
}