{
  "type": "Feature",
  "properties": {
    "iso:country":"ES",
    "sg:address":"Calle de Nuestra Se\u00d1ora Del Aguila, 38",
    "sg:city":"Alcala Guadaira",
    "sg:orig_category":"M\u00c9dicos: Radiolog\u00cda (radiodiagn\u00d3stico E Im\u00c1genes En Medicina)",
    "sg:phone":"+34 955 68 47 20",
    "sg:postcode":"41500",
    "sg:province":"Sevilla",
    "wof:name":"Lamas Gutierrez Juan",
    "wof:placetype":"venue"
},
  "geometry": {"coordinates":[-5.8473820686,37.3356552124],"type":"Point"}
}