{
  "type": "Feature",
  "properties": {
    "addr:full":"Plaz San Jose, 2 Puerto Mazarron Murcia 30860",
    "addr:housenumber":"2",
    "addr:postcode":"30860",
    "addr:street":"Plaz San Jose",
    "iso:country":"ES",
    "sg:address":"Plaz San Jose, 2",
    "sg:city":"Puerto Mazarron",
    "sg:orig_category":"Inversiones",
    "sg:phone":"+34 968 15 36 92",
    "sg:postcode":"30860",
    "sg:province":"Murcia",
    "wof:name":"Viva House C.b",
    "wof:placetype":"venue"
},
  "geometry": {"coordinates":[-1.3136693239,37.5990715027],"type":"Point"}
}