{
  "type": "Feature",
  "properties": {
    "addr:full":"Av Generalitat (de La), 54 Tortosa Tarragona 43500",
    "addr:housenumber":"54",
    "addr:postcode":"43500",
    "addr:street":"Av Generalitat De La",
    "iso:country":"ES",
    "sg:address":"Av Generalitat (de La), 54",
    "sg:city":"Tortosa",
    "sg:orig_category":"Asociaciones Y Clubs Deportivos",
    "sg:phone":"+34 977 44 02 97",
    "sg:postcode":"43500",
    "sg:province":"Tarragona",
    "wof:name":"Pam I Toc S.l.",
    "wof:placetype":"venue"
},
  "geometry": {"coordinates":[0.5200049877,40.810710907],"type":"Point"}
}