{
  "type": "Feature",
  "properties": {
    "addr:full":"Plgno Urtia, S/n Ermua Vizcaya 48260",
    "addr:housenumber":"s",
    "addr:postcode":"48260",
    "addr:street":"/ N",
    "iso:country":"ES",
    "sg:address":"Plgno Urtia, S/n",
    "sg:city":"Ermua",
    "sg:orig_category":"Galvanizaci\u00d3n, Esta\u00d1ado, Emplomado",
    "sg:phone":"+34 943 17 02 46",
    "sg:postcode":"48260",
    "sg:province":"Vizcaya",
    "wof:name":"Zincados Aguirregomezcorta S.l.",
    "wof:placetype":"venue"
},
  "geometry": {"coordinates":[-2.4950428009,43.1911697388],"type":"Point"}
}