{
  "type": "Feature",
  "properties": {
    "iso:country":"ES",
    "sg:address":"Crta. Zafra-vva Fresno, S/n",
    "sg:city":"Oliva Frontera",
    "sg:orig_category":"Cooperativas Agr\u00cdcolas",
    "sg:phone":"+34 924 75 42 85",
    "sg:postcode":"06120",
    "sg:province":"Badajoz",
    "wof:name":"Cooperativa Jovenes Agricultores",
    "wof:placetype":"venue"
},
  "geometry": {"coordinates":[-6.9155139923,38.2829017639],"type":"Point"}
}