{
  "type": "Feature",
  "properties": {
    "addr:full":"Avda Alcalde Luis Uru\u00d1uela, 19 Sevilla Sevilla 41020",
    "addr:housenumber":"19",
    "addr:postcode":"41020",
    "addr:street":"Avda Alcalde Luis Urun\u0303Uela",
    "iso:country":"ES",
    "sg:address":"Avda Alcalde Luis Uru\u00d1uela, 19",
    "sg:city":"Sevilla",
    "sg:orig_category":"Pod\u00d3logos: Pedicuros",
    "sg:phone":"+34 954 25 07 29",
    "sg:postcode":"41020",
    "sg:province":"Sevilla",
    "wof:name":"Rodriguez Molina Virginia",
    "wof:placetype":"venue"
},
  "geometry": {"coordinates":[-5.9407792091,37.4026489258],"type":"Point"}
}