{
  "type": "Feature",
  "properties": {
    "iso:country":"ES",
    "sg:address":"Rua Blanco Amor, 5",
    "sg:city":"Santa Uxia De Ribeira",
    "sg:orig_category":"Cristaler\u00cdas",
    "sg:phone":"+34 981 87 13 32",
    "sg:postcode":"15960",
    "sg:province":"La Coru\u00f1a",
    "wof:name":"Cristaleria Filgueira S.l.",
    "wof:placetype":"venue"
},
  "geometry": {"coordinates":[-8.9955272675,42.5517921448],"type":"Point"}
}