{
  "type": "Feature",
  "properties": {
    "iso:country":"ES",
    "sg:address":"Plaz Salvador (del), S/n",
    "sg:city":"Granada",
    "sg:orig_category":"Comunidades Religiosas",
    "sg:phone":"+34 958 27 46 12",
    "sg:postcode":"18010",
    "sg:province":"Granada",
    "wof:name":"Colegio En Granada Misioneras Del Divino Maestro",
    "wof:placetype":"venue"
},
  "geometry": {"coordinates":[-3.5908839703,37.1822967529],"type":"Point"}
}