{
  "type": "Feature",
  "properties": {
    "iso:country":"ES",
    "sg:address":"Calle de Padre Arintero Del, 3",
    "sg:city":"Aviles",
    "sg:orig_category":"Ropa Para Se\u00d1oras Y Caballeros (al Por Menor)",
    "sg:phone":"+34 985 57 45 04",
    "sg:postcode":"33403",
    "sg:province":"Asturias",
    "wof:name":"Alonso Blanco Adelaida",
    "wof:placetype":"venue"
},
  "geometry": {"coordinates":[-5.907957077,43.5460128784],"type":"Point"}
}