{
  "type": "Feature",
  "properties": {
    "iso:country":"ES",
    "sg:address":"Avda Conde De Guadalhorce, 43",
    "sg:city":"Aviles",
    "sg:orig_category":"Laboratorios Farmac\u00c9uticos",
    "sg:phone":"+34 985 52 61 49",
    "sg:postcode":"33401",
    "sg:province":"Asturias",
    "wof:name":"Boticalia Red S.l.",
    "wof:placetype":"venue"
},
  "geometry": {"coordinates":[-5.9222688675,43.5647697449],"type":"Point"}
}