{
  "type": "Feature",
  "properties": {
    "addr:full":"Ctra Sta Creu Calafell-barcelona, S/n Segur Calafell Tarragona 43882",
    "addr:housenumber":"s / n",
    "addr:postcode":"43882",
    "addr:street":"Ctra Sta Creu Calafell-Barcelona",
    "iso:country":"ES",
    "sg:address":"Ctra Sta Creu Calafell-barcelona, S/n",
    "sg:city":"Segur Calafell",
    "sg:orig_category":"Cajas De Ahorro",
    "sg:phone":"+34 977 16 19 72",
    "sg:postcode":"43882",
    "sg:province":"Tarragona",
    "sg:website":"www.lacaixa.es",
    "wof:name":"Caixa D'estalvis I Pensions De Barcelona",
    "wof:placetype":"venue"
},
  "geometry": {"coordinates":[1.5907050371,41.1920433044],"type":"Point"}
}