{
  "type": "Feature",
  "properties": {
    "addr:full":"Calle de Jose Zorrilla, 54 Segovia Segovia 40002",
    "addr:housenumber":"54",
    "addr:postcode":"40002",
    "addr:street":"Calle De Jose Zorrilla",
    "iso:country":"ES",
    "sg:address":"Calle de Jose Zorrilla, 54",
    "sg:city":"Segovia",
    "sg:orig_category":"M\u00c9dicos: Estomatolog\u00cda",
    "sg:phone":"+34 921 43 33 26",
    "sg:postcode":"40002",
    "sg:province":"Segovia",
    "wof:name":"Asenjo Holgueras Santiago",
    "wof:placetype":"venue"
},
  "geometry": {"coordinates":[-4.1155071259,40.9407081604],"type":"Point"}
}