{
  "type": "Feature",
  "properties": {
    "iso:country":"ES",
    "sg:address":"Calle de Suiza (de), 20",
    "sg:city":"Fuenlabrada",
    "sg:orig_category":"Ropa De Hogar (al Por Menor)",
    "sg:phone":"+34 916 49 02 41",
    "sg:postcode":"28943",
    "sg:province":"Madrid",
    "sg:website":"www.nido.es",
    "wof:name":"Casa Tempo S.a.",
    "wof:placetype":"venue"
},
  "geometry": {"coordinates":[-3.8033130169,40.2845306396],"type":"Point"}
}