{
  "type": "Feature",
  "properties": {
    "iso:country":"ES",
    "sg:address":"Calle de Esperanza, 1",
    "sg:city":"Rozas De Madrid",
    "sg:orig_category":"M\u00c9dicos: Estomatolog\u00cda",
    "sg:phone":"+34 917 10 36 81",
    "sg:postcode":"28230",
    "sg:province":"Madrid",
    "wof:name":"Servicio Dental Especializado Ied S.l.",
    "wof:placetype":"venue"
},
  "geometry": {"coordinates":[-3.8724050522,40.4913291931],"type":"Point"}
}