{
  "type": "Feature",
  "properties": {
    "addr:full":"Ctra Valencia-barcelona, Km. 0012,5 Pobla Farnals Valencia 46139",
    "addr:postcode":"46139",
    "addr:street":"Ctra Valencia-Barcelona Km. 0012,5",
    "iso:country":"ES",
    "sg:address":"Ctra Valencia-barcelona, Km. 0012,5",
    "sg:city":"Pobla Farnals",
    "sg:orig_category":"Suministros Para Carrocer\u00cdas",
    "sg:phone":"+34 961 44 41 11",
    "sg:postcode":"46139",
    "sg:province":"Valencia",
    "wof:name":"Ramon Romero Rafael",
    "wof:placetype":"venue"
},
  "geometry": {"coordinates":[-0.3265590072,39.579334259],"type":"Point"}
}