{
  "type": "Feature",
  "properties": {
    "addr:full":"Calle de Azagra, 22 Albarracin Teruel 44100",
    "addr:housenumber":"22",
    "addr:postcode":"44100",
    "addr:street":"Calle De Azagra",
    "iso:country":"ES",
    "sg:address":"Calle de Azagra, 22",
    "sg:city":"Albarracin",
    "sg:orig_category":"Caf\u00c9s, Bares, Cervecer\u00cdas",
    "sg:phone":"+34 978 71 01 49",
    "sg:postcode":"44100",
    "sg:province":"Teruel",
    "wof:name":"Circulo Recreativo La Amistad",
    "wof:placetype":"venue"
},
  "geometry": {"coordinates":[-1.4424058199,40.4080963135],"type":"Point"}
}