{
  "type": "Feature",
  "properties": {
    "iso:country":"ES",
    "sg:address":"Pla\u00c7 Paeria, 14",
    "sg:city":"Lleida",
    "sg:orig_category":"Ense\u00d1anza: Profesiones Art\u00cdsticas",
    "sg:phone":"+34 973 24 22 19",
    "sg:postcode":"25007",
    "sg:province":"Lleida",
    "wof:name":"Garsaball Lagranja Jose Ramon",
    "wof:placetype":"venue"
},
  "geometry": {"coordinates":[0.627129972,41.6145210266],"type":"Point"}
}