{
  "type": "Feature",
  "properties": {
    "addr:full":"Calle de Principe Don Juan Carlos, 2 Alcorcon Madrid 28924",
    "addr:housenumber":"2",
    "addr:postcode":"28924",
    "addr:street":"Calle De Principe Don;Carlos",
    "iso:country":"ES",
    "sg:address":"Calle de Principe Don Juan Carlos, 2",
    "sg:city":"Alcorcon",
    "sg:orig_category":"Ense\u00d1anza: Peluquer\u00cda Est\u00c9tica",
    "sg:phone":"+34 916 11 50 41",
    "sg:postcode":"28924",
    "sg:province":"Madrid",
    "wof:name":"Serrano Corral Alfonso",
    "wof:placetype":"venue"
},
  "geometry": {"coordinates":[-3.8206539154,40.349811554],"type":"Point"}
}