{
  "type": "Feature",
  "properties": {
    "iso:country":"ES",
    "sg:address":"Calle de Pozo (el), 12",
    "sg:city":"Astorga",
    "sg:orig_category":"Lavado, Limpieza De Veh\u00cdculos",
    "sg:phone":"+34 987 61 94 42",
    "sg:postcode":"24700",
    "sg:province":"Le\u00f3n",
    "wof:name":"Gonzalez Gonzalez Jose Antonio",
    "wof:placetype":"venue"
},
  "geometry": {"coordinates":[-6.0523238182,42.4567565918],"type":"Point"}
}