{
  "type": "Feature",
  "properties": {
    "addr:full":"Calle de Eugenio Gross, 41 Malaga M\u00e1laga 29010",
    "addr:housenumber":"41",
    "addr:postcode":"29010",
    "addr:street":"Calle De Eugenio Gross;Ma\u0301Laga",
    "iso:country":"ES",
    "sg:address":"Calle de Eugenio Gross, 41",
    "sg:city":"Malaga",
    "sg:orig_category":"Farmacias",
    "sg:phone":"+34 952 07 06 54",
    "sg:postcode":"29010",
    "sg:province":"M\u00e1laga",
    "wof:name":"Garnica Navarro Eduardo",
    "wof:placetype":"venue"
},
  "geometry": {"coordinates":[-4.4351792336,36.7262458801],"type":"Point"}
}