{
  "type": "Feature",
  "properties": {
    "addr:full":"Pzta Iglesia, 2 Sada A Coru\u00f1a 15160",
    "addr:housenumber":"2",
    "addr:postcode":"15160",
    "iso:country":"ES",
    "sg:address":"Pzta Iglesia, 2",
    "sg:city":"Sada",
    "sg:orig_category":"Mercer\u00cda, Lencer\u00cda (al Por Menor)",
    "sg:phone":"+34 981 62 33 52",
    "sg:postcode":"15160",
    "sg:province":"A Coru\u00f1a",
    "wof:name":"Serantes Pernas Gerardo",
    "wof:placetype":"venue"
},
  "geometry": {"coordinates":[-8.2548141479,43.3510665894],"type":"Point"}
}