{
  "type": "Feature",
  "properties": {
    "addr:full":"Calle de Gonzalo De Cordoba, 22 Madrid Madrid 28010",
    "addr:housenumber":"22",
    "addr:postcode":"madrid;28010",
    "addr:street":"Calle De Gonzalo De Cordoba",
    "iso:country":"ES",
    "sg:address":"Calle de Gonzalo De Cordoba, 22",
    "sg:city":"Madrid",
    "sg:orig_category":"Importaci\u00d3n",
    "sg:phone":"+34 914 46 71 43",
    "sg:postcode":"28010",
    "sg:province":"Madrid",
    "wof:name":"Duncan  Robert Steven",
    "wof:placetype":"venue"
},
  "geometry": {"coordinates":[-3.7017540932,40.4324493408],"type":"Point"}
}