{
  "type": "Feature",
  "properties": {
    "addr:full":"M. Central, S/n Tarragona Tarragona 43001",
    "addr:housenumber":"s / n",
    "addr:postcode":"43001",
    "iso:country":"ES",
    "sg:address":"M. Central, S/n",
    "sg:city":"Tarragona",
    "sg:orig_category":"Carnicer\u00cdas, Carnicer\u00cdas",
    "sg:phone":"+34 977 23 89 23",
    "sg:postcode":"43001",
    "sg:province":"Tarragona",
    "wof:name":"Bardolet Penalba Vicenc",
    "wof:placetype":"venue"
},
  "geometry": {"coordinates":[1.2541049719,41.1169281006],"type":"Point"}
}