{
  "type": "Feature",
  "properties": {
    "iso:country":"ES",
    "sg:address":"Calle de Real, 2",
    "sg:city":"Castilleja Cuesta",
    "sg:orig_category":"Internados & Ense\u00d1anza Privada",
    "sg:phone":"+34 954 16 92 50",
    "sg:postcode":"41950",
    "sg:province":"Sevilla",
    "wof:name":"Hermanos Maristas Provincia Mediterranea",
    "wof:placetype":"venue"
},
  "geometry": {"coordinates":[-6.0462141037,37.3877258301],"type":"Point"}
}