{
  "type": "Feature",
  "properties": {
    "iso:country":"ES",
    "sg:address":"Av Teresa De Palleja, 3",
    "sg:city":"Fortia",
    "sg:orig_category":"Cerrajer\u00cda, Ferrallista",
    "sg:phone":"+34 972 53 40 88",
    "sg:postcode":"17469",
    "sg:province":"Girona",
    "wof:name":"Xatart De Fortia,s.c.",
    "wof:placetype":"venue"
},
  "geometry": {"coordinates":[3.039680481,42.2448005676],"type":"Point"}
}