{
  "type": "Feature",
  "properties": {
    "iso:country":"ES",
    "sg:address":"Calle de Pedrera Baja, 15",
    "sg:city":"Ciudad Real",
    "sg:orig_category":"Farmacias",
    "sg:phone":"+34 926 22 20 17",
    "sg:postcode":"13003",
    "sg:province":"Ciudad Real",
    "wof:name":"Gonzalez Martin-palomino Maria Lourdes",
    "wof:placetype":"venue"
},
  "geometry": {"coordinates":[-3.9297139645,38.9913139343],"type":"Point"}
}