{
  "type": "Feature",
  "properties": {
    "addr:full":"Carrer de Carles Buhigas, 17 Can Castells Barcelona 08420",
    "addr:housenumber":"17",
    "addr:postcode":"08420",
    "addr:street":"Carrer De Carles Buhigas",
    "iso:country":"ES",
    "sg:address":"Carrer de Carles Buhigas, 17",
    "sg:city":"Can Castells",
    "sg:orig_category":"Negocio De Materiales De Construcci\u00d3n",
    "sg:phone":"+34 938 70 04 91",
    "sg:postcode":"08420",
    "sg:province":"Barcelona",
    "wof:name":"Terres Granollers S.l.l.",
    "wof:placetype":"venue"
},
  "geometry": {"coordinates":[2.2783401012,41.6220207214],"type":"Point"}
}