{
  "type": "Feature",
  "properties": {
    "iso:country":"ES",
    "sg:address":"Avda Parque De Palomeras Bajas, S/n",
    "sg:city":"Madrid",
    "sg:orig_category":"Ense\u00d1anza Secundaria: Colegios Y Escuelas Privadas",
    "sg:phone":"+34 917 86 31 48",
    "sg:postcode":"28018",
    "sg:province":"Madrid",
    "wof:name":"I.e.s. Madrid Sur",
    "wof:placetype":"venue"
},
  "geometry": {"coordinates":[-3.6653139591,40.3814353943],"type":"Point"}
}