{
  "type": "Feature",
  "properties": {
    "iso:country":"ES",
    "sg:address":"Calle de Campo Sagrado, 59",
    "sg:city":"Gijon",
    "sg:orig_category":"Promotores Constructores",
    "sg:phone":"+34 985 13 03 74",
    "sg:postcode":"33205",
    "sg:province":"Asturias",
    "wof:name":"Lescoto Construccion S.l.",
    "wof:placetype":"venue"
},
  "geometry": {"coordinates":[-5.653696537,43.5346031189],"type":"Point"}
}