{
  "type": "Feature",
  "properties": {
    "iso:country":"ES",
    "sg:address":"Ptge Barca (de La), 18",
    "sg:city":"Seros",
    "sg:orig_category":"Empresas De Carpinter\u00cda De Madera",
    "sg:phone":"+34 973 78 03 26",
    "sg:postcode":"25183",
    "sg:province":"Lleida",
    "wof:name":"Baro Cortiella Raul",
    "wof:placetype":"venue"
},
  "geometry": {"coordinates":[0.4122770131,41.4636268616],"type":"Point"}
}