{
  "type": "Feature",
  "properties": {
    "iso:country":"ES",
    "sg:address":"Plaz Constitucion (la), 5",
    "sg:city":"Maracena",
    "sg:orig_category":"Electrodom\u00c9sticos (al Por Menor)",
    "sg:phone":"+34 958 42 12 01",
    "sg:postcode":"18200",
    "sg:province":"Granada",
    "wof:name":"Barrancos Arce Rosa",
    "wof:placetype":"venue"
},
  "geometry": {"coordinates":[-3.6350440979,37.2073287964],"type":"Point"}
}