{
  "type": "Feature",
  "properties": {
    "iso:country":"ES",
    "sg:address":"Pol Ind Las Cruces, S/n",
    "sg:city":"Fines",
    "sg:orig_category":"M\u00c1rmoles, Granitos Y Piedras Naturales",
    "sg:phone":"+34 950 44 42 05",
    "sg:postcode":"04869",
    "sg:province":"Almer\u00eda",
    "wof:name":"Construcciones Mecanicas Mam S.l.",
    "wof:placetype":"venue"
},
  "geometry": {"coordinates":[-2.2685689926,37.3611907959],"type":"Point"}
}