{
  "type": "Feature",
  "properties": {
    "iso:country":"ES",
    "sg:address":"Calle de Martires, 19",
    "sg:city":"Chilches",
    "sg:orig_category":"Peluqueros: De Se\u00d1oras",
    "sg:phone":"+34 964 59 00 68",
    "sg:postcode":"12592",
    "sg:province":"Castell\u00f3n",
    "wof:name":"Casinos Franch Manuel",
    "wof:placetype":"venue"
},
  "geometry": {"coordinates":[-0.1895029992,39.780632019],"type":"Point"}
}