{
  "type": "Feature",
  "properties": {
    "addr:full":"Av Valles, 34 Cardedeu Barcelona 08440",
    "addr:housenumber":"34",
    "addr:postcode":"08440",
    "addr:street":"Av Valles",
    "iso:country":"ES",
    "sg:address":"Av Valles, 34",
    "sg:city":"Cardedeu",
    "sg:orig_category":"Suministros Y Materiales Industriales",
    "sg:phone":"+34 938 45 49 71",
    "sg:postcode":"08440",
    "sg:province":"Barcelona",
    "sg:website":"www.prodecosl.com",
    "wof:name":"Suministros Industriales Prodeco S.l.",
    "wof:placetype":"venue"
},
  "geometry": {"coordinates":[2.359662056,41.6229286194],"type":"Point"}
}