{
  "type": "Feature",
  "properties": {
    "addr:full":"Av Magaluf, 13 Magaluf Islas Baleares 07181",
    "addr:housenumber":"13",
    "addr:postcode":"07181",
    "addr:street":"Av Magaluf",
    "iso:country":"ES",
    "sg:address":"Av Magaluf, 13",
    "sg:city":"Magaluf",
    "sg:orig_category":"Caf\u00c9s, Bares, Cervecer\u00cdas",
    "sg:phone":"+34 971 13 17 82",
    "sg:postcode":"07181",
    "sg:province":"Islas Baleares",
    "wof:name":"Iglesias Mir Antonio",
    "wof:placetype":"venue"
},
  "geometry": {"coordinates":[2.5347409248,39.509021759],"type":"Point"}
}