{
  "type": "Feature",
  "properties": {
    "iso:country":"ES",
    "sg:address":"Calle de Sants De La Pedra, 7",
    "sg:city":"Rafelbunyol",
    "sg:orig_category":"Tintes (fabricaci\u00d3n, Al Por Mayor)",
    "sg:phone":"+34 961 41 22 59",
    "sg:postcode":"46138",
    "sg:province":"Valencia",
    "wof:name":"Neteja En Sec Barrachina S.c.p.",
    "wof:placetype":"venue"
},
  "geometry": {"coordinates":[-0.3630670011,39.6022033691],"type":"Point"}
}