{
  "type": "Feature",
  "properties": {
    "addr:full":"Calle de Capitan Francisco Fuentes, 5 Santos Humosa Madrid 28817",
    "addr:housenumber":"5",
    "addr:postcode":"28817",
    "addr:street":"Calle De Capitan Francisco Fuentes",
    "iso:country":"ES",
    "sg:address":"Calle de Capitan Francisco Fuentes, 5",
    "sg:city":"Santos Humosa",
    "sg:orig_category":"Detectives, Agentes Investigadores Privados",
    "sg:phone":"+34 918 84 83 42",
    "sg:postcode":"28817",
    "sg:province":"Madrid",
    "wof:name":"Iba\u00f1ez Ayora Gonzalo",
    "wof:placetype":"venue"
},
  "geometry": {"coordinates":[-3.2495539188,40.5021514893],"type":"Point"}
}