{
  "type": "Feature",
  "properties": {
    "addr:full":"Avda Madrid, 46 Le\u00f3n Le\u00f3n 24005",
    "addr:housenumber":"46",
    "addr:postcode":"24005",
    "addr:street":"Avda Madrid;Leo\u0301N",
    "iso:country":"ES",
    "sg:address":"Avda Madrid, 46",
    "sg:city":"Le\u00f3n",
    "sg:orig_category":"Chapister\u00cda",
    "sg:phone":"+34 987 20 13 25",
    "sg:postcode":"24005",
    "sg:province":"Le\u00f3n",
    "wof:name":"Avelino Martinez Castro Y Otro Cdad",
    "wof:placetype":"venue"
},
  "geometry": {"coordinates":[-5.5515007973,42.5803985596],"type":"Point"}
}