{
  "type": "Feature",
  "properties": {
    "addr:full":"Calle de Cordel De Merinas, 145 Salamanca Salamanca 37008",
    "addr:housenumber":"145",
    "addr:postcode":"37008",
    "addr:street":"Calle De Cordel De Merinas",
    "iso:country":"ES",
    "sg:address":"Calle de Cordel De Merinas, 145",
    "sg:city":"Salamanca",
    "sg:orig_category":"Promotores Constructores",
    "sg:phone":"+34 923 26 31 76",
    "sg:postcode":"37008",
    "sg:province":"Salamanca",
    "wof:name":"Tejada Mi\u00f1ambres Miguel",
    "wof:placetype":"venue"
},
  "geometry": {"coordinates":[-5.6826601028,40.9508056641],"type":"Point"}
}