{
  "type": "Feature",
  "properties": {
    "iso:country":"ES",
    "sg:address":"Calle de Granada, 1",
    "sg:city":"Sevilla",
    "sg:orig_category":"C\u00c1maras De Comercio E Industria, Oficios, Agricultura",
    "sg:phone":"+34 954 46 13 55",
    "sg:postcode":"41001",
    "sg:province":"Sevilla",
    "sg:website":"www.camaradesevilla.com",
    "wof:name":"Camara Oficial De Comercio E Industria Y Navegacion De Sevilla",
    "wof:placetype":"venue"
},
  "geometry": {"coordinates":[-5.9943141937,37.3890228271],"type":"Point"}
}