{
  "type": "Feature",
  "properties": {
    "addr:full":"Poli Industrial Las Rozas, S/n Tauste Zaragoza 50660",
    "addr:housenumber":"s / n",
    "addr:postcode":"50660",
    "iso:country":"ES",
    "sg:address":"Poli Industrial Las Rozas, S/n",
    "sg:city":"Tauste",
    "sg:orig_category":"Mantenimiento Y Reparaci\u00d3n De Motores Industriales",
    "sg:phone":"+34 976 85 54 69",
    "sg:postcode":"50660",
    "sg:province":"Zaragoza",
    "wof:name":"Bobinado De Motores S. A.",
    "wof:placetype":"venue"
},
  "geometry": {"coordinates":[-1.2573059797,41.9222984314],"type":"Point"}
}