{
  "type": "Feature",
  "properties": {
    "iso:country":"ES",
    "sg:address":"Calle de Francia, 24",
    "sg:city":"Torremolinos",
    "sg:orig_category":"Complementos De Vestir (al Por Menor)",
    "sg:phone":"+34 952 05 13 76",
    "sg:postcode":"29620",
    "sg:province":"M\u00e1laga",
    "wof:name":"Lozano Perez Eduardo",
    "wof:placetype":"venue"
},
  "geometry": {"coordinates":[-4.5023412704,36.6136207581],"type":"Point"}
}