{
  "type": "Feature",
  "properties": {
    "iso:country":"ES",
    "sg:address":"Calle de Anaitasuna, 6",
    "sg:city":"Barakaldo",
    "sg:orig_category":"Electricidad: Equipos Industriales, Componentes (fabricaci\u00d3n)",
    "sg:phone":"+34 944 99 02 93",
    "sg:postcode":"48903",
    "sg:province":"Vizcaya",
    "sg:website":"www.marechal.com",
    "wof:name":"Tomas Y Descontactores Industriales Sa",
    "wof:placetype":"venue"
},
  "geometry": {"coordinates":[-2.990489006,43.2833099365],"type":"Point"}
}