{
  "type": "Feature",
  "properties": {
    "iso:country":"ES",
    "sg:address":"Calle de Zaragoza, 17",
    "sg:city":"Sevilla",
    "sg:orig_category":"Herboristas (al Por Menor)",
    "sg:phone":"+34 954 22 22 50",
    "sg:postcode":"41001",
    "sg:province":"Sevilla",
    "sg:website":"www.muysano.com",
    "wof:name":"Ferrer Campoy Inmaculada",
    "wof:placetype":"venue"
},
  "geometry": {"coordinates":[-5.9979681969,37.3886871338],"type":"Point"}
}