{
  "type": "Feature",
  "properties": {
    "iso:country":"ES",
    "sg:address":"Calle de Arahal, 2",
    "sg:city":"Alcala Guadaira",
    "sg:orig_category":"Mec\u00c1nico Del Autom\u00d3vil",
    "sg:phone":"+34 955 68 57 02",
    "sg:postcode":"41500",
    "sg:province":"Sevilla",
    "wof:name":"Garcia Ramirez Manuel",
    "wof:placetype":"venue"
},
  "geometry": {"coordinates":[-5.8405613899,37.336315155],"type":"Point"}
}