{
  "type": "Feature",
  "properties": {
    "addr:full":"Carrer de Dos De Maig, 4 Viladecans Barcelona 08840",
    "addr:housenumber":"4",
    "addr:postcode":"08840",
    "addr:street":"Carrer De Dos De Maig",
    "iso:country":"ES",
    "sg:address":"Carrer de Dos De Maig, 4",
    "sg:city":"Viladecans",
    "sg:orig_category":"Mercer\u00cda, Lencer\u00cda (al Por Menor)",
    "sg:phone":"+34 936 37 76 21",
    "sg:postcode":"08840",
    "sg:province":"Barcelona",
    "wof:name":"Romero Deja Maria Nieves",
    "wof:placetype":"venue"
},
  "geometry": {"coordinates":[2.0146119595,41.3159294128],"type":"Point"}
}