{
  "type": "Feature",
  "properties": {
    "iso:country":"ES",
    "sg:address":"Avda Do\u00f1a Juana, 2",
    "sg:city":"Huetor-vega",
    "sg:orig_category":"Promotores Constructores",
    "sg:phone":"+34 958 30 38 83",
    "sg:postcode":"18198",
    "sg:province":"Granada",
    "wof:name":"Construcciones Girela Ruiz S.l.",
    "wof:placetype":"venue"
},
  "geometry": {"coordinates":[-3.5746409893,37.1468925476],"type":"Point"}
}