{
  "type": "Feature",
  "properties": {
    "iso:country":"ES",
    "sg:address":"Calle de Larga, 23",
    "sg:city":"Oso",
    "sg:orig_category":"Transportes De Animales Vivos",
    "sg:phone":"+34 920 26 11 48",
    "sg:postcode":"05164",
    "sg:province":"\u00c1vila",
    "wof:name":"Rodriguez Moreno Gabriel",
    "wof:placetype":"venue"
},
  "geometry": {"coordinates":[-4.7698411942,40.8397521973],"type":"Point"}
}