{
  "type": "Feature",
  "properties": {
    "addr:full":"Calle de Buen Pastor, 12 Benidorm Alicante 03500",
    "addr:housenumber":"12",
    "addr:postcode":"03500",
    "addr:street":"Calle De Buen Pastor",
    "iso:country":"ES",
    "sg:address":"Calle de Buen Pastor, 12",
    "sg:city":"Benidorm",
    "sg:orig_category":"Peluquer\u00cdas, Peluquer\u00cda Mixta",
    "sg:phone":"+34 965 85 64 91",
    "sg:postcode":"03500",
    "sg:province":"Alicante",
    "wof:name":"Amores Aibar Maria Pilar",
    "wof:placetype":"venue"
},
  "geometry": {"coordinates":[-0.1324936002,38.5406455994],"type":"Point"}
}