{
  "type": "Feature",
  "properties": {
    "iso:country":"ES",
    "sg:address":"Calle de Nicolas Estevanez, 41",
    "sg:city":"Palmas De Gran Canaria",
    "sg:orig_category":"Fabricaci\u00d3n, Venta De Productos Base Farmac\u00c9uticos",
    "sg:phone":"+34 928 26 14 07",
    "sg:postcode":"35007",
    "sg:province":"Las Palmas",
    "wof:name":"Manrique De Lara Bosch Pedro",
    "wof:placetype":"venue"
},
  "geometry": {"coordinates":[-15.4364528656,28.139333725],"type":"Point"}
}