{
  "type": "Feature",
  "properties": {
    "addr:full":"Colonia Vidal, S/n Puig-reig Barcelona 08692",
    "addr:housenumber":"s / n",
    "addr:postcode":"08692",
    "addr:street":"Colonia Vidal",
    "iso:country":"ES",
    "sg:address":"Colonia Vidal, S/n",
    "sg:city":"Puig-reig",
    "sg:orig_category":"Museos",
    "sg:phone":"+34 938 29 04 58",
    "sg:postcode":"08692",
    "sg:province":"Barcelona",
    "wof:name":"Patronato Vidal",
    "wof:placetype":"venue"
},
  "geometry": {"coordinates":[1.8822699785,41.9447784424],"type":"Point"}
}