{
  "type": "Feature",
  "properties": {
    "addr:full":"Carrer de Sella, 5 Benidorm Alicante 03500",
    "addr:housenumber":"5",
    "addr:postcode":"03500",
    "addr:street":"Carrer De Sella",
    "iso:country":"ES",
    "sg:address":"Carrer de Sella, 5",
    "sg:city":"Benidorm",
    "sg:orig_category":"Promotores Constructores",
    "sg:phone":"+34 966 81 32 48",
    "sg:postcode":"03500",
    "sg:province":"Alicante",
    "sg:website":"www.mediterraneandolmens.com",
    "wof:name":"Mediterranea-ls Dolmen S.l.",
    "wof:placetype":"venue"
},
  "geometry": {"coordinates":[-0.1740590036,38.5364303589],"type":"Point"}
}