{
  "type": "Feature",
  "properties": {
    "addr:full":"Calle de San Pedro Del Mar, 34 Monte Cantabria 39012",
    "addr:housenumber":"34",
    "addr:postcode":"39012",
    "addr:street":"Calle De San Pedro Del Mar",
    "iso:country":"ES",
    "sg:address":"Calle de San Pedro Del Mar, 34",
    "sg:city":"Monte",
    "sg:orig_category":"Peluquer\u00cdas",
    "sg:phone":"+34 942 34 41 70",
    "sg:postcode":"39012",
    "sg:province":"Cantabria",
    "wof:name":"Bravo Camus Santiago",
    "wof:placetype":"venue"
},
  "geometry": {"coordinates":[-3.8301749229,43.4715461731],"type":"Point"}
}