{
  "type": "Feature",
  "properties": {
    "iso:country":"ES",
    "sg:address":"Calle de Martinez Campos, 23",
    "sg:city":"Granada",
    "sg:orig_category":"Inmobiliaria (agencias)",
    "sg:phone":"+34 958 25 99 44",
    "sg:postcode":"18002",
    "sg:province":"Granada",
    "wof:name":"P D P Inmobiliaria E Inversiones S.l.",
    "wof:placetype":"venue"
},
  "geometry": {"coordinates":[-3.6044585705,37.1723976135],"type":"Point"}
}