{
  "type": "Feature",
  "properties": {
    "iso:country":"ES",
    "sg:address":"Carrer de Biniali, 4",
    "sg:city":"Palma",
    "sg:orig_category":"Empresas De Carpinter\u00cda De Madera",
    "sg:phone":"+34 971 47 71 54",
    "sg:postcode":"07008",
    "sg:province":"Islas Baleares",
    "wof:name":"Soto Pravia Jose Ramon",
    "wof:placetype":"venue"
},
  "geometry": {"coordinates":[2.6812429428,39.5840263367],"type":"Point"}
}