{
  "type": "Feature",
  "properties": {
    "addr:full":"Calle de Villafranca, 4 Le\u00f3n Le\u00f3n 24001",
    "addr:housenumber":"4",
    "addr:postcode":"24001",
    "addr:street":"Calle De Villafranca;Leo\u0301N",
    "iso:country":"ES",
    "sg:address":"Calle de Villafranca, 4",
    "sg:city":"Le\u00f3n",
    "sg:orig_category":"M\u00c9dicos: Cirug\u00cda Maxilofacial",
    "sg:phone":"+34 987 20 68 65",
    "sg:postcode":"24001",
    "sg:province":"Le\u00f3n",
    "wof:name":"Santos Oller Juan",
    "wof:placetype":"venue"
},
  "geometry": {"coordinates":[-5.5758690834,42.5961456299],"type":"Point"}
}