{
  "type": "Feature",
  "properties": {
    "addr:full":"Calle de Duque De Alba, 6 Avila \u00c1vila 05001",
    "addr:housenumber":"6",
    "addr:postcode":"05001",
    "addr:street":"Calle De Duque De Alba;A\u0301Vila",
    "iso:country":"ES",
    "sg:address":"Calle de Duque De Alba, 6",
    "sg:city":"Avila",
    "sg:orig_category":"Bricolaje, Herramientas (al Por Menor)",
    "sg:phone":"+34 920 22 16 31",
    "sg:postcode":"05001",
    "sg:province":"\u00c1vila",
    "wof:name":"Prieto Tejedor Juan Carlos",
    "wof:placetype":"venue"
},
  "geometry": {"coordinates":[-4.6938667297,40.6549377441],"type":"Point"}
}