{
  "type": "Feature",
  "properties": {
    "addr:full":"Calle de Sierra De Urbasa, 8 Donostia-san Sebastian Guip\u00f9zcoa 20014",
    "addr:housenumber":"8",
    "addr:postcode":"20014",
    "addr:street":"Calle De Sierra De Urbasa",
    "iso:country":"ES",
    "sg:address":"Calle de Sierra De Urbasa, 8",
    "sg:city":"Donostia-san Sebastian",
    "sg:orig_category":"Molduras, Junquillos, Listones Y Molduras Perforadas",
    "sg:phone":"+34 943 46 82 61",
    "sg:postcode":"20014",
    "sg:province":"Guip\u00f9zcoa",
    "wof:name":"Macias Martinez Del Campo Juan Antonio",
    "wof:placetype":"venue"
},
  "geometry": {"coordinates":[-1.9668649435,43.3096847534],"type":"Point"}
}