{
  "type": "Feature",
  "properties": {
    "iso:country":"ES",
    "sg:address":"Carrer de Sant Antoni, 29",
    "sg:city":"S. Cugat Valles",
    "sg:orig_category":"Muebles, Minoristas",
    "sg:phone":"+34 935 89 62 46",
    "sg:postcode":"08172",
    "sg:province":"Barcelona",
    "wof:name":"3p Mobel 3 S. L.",
    "wof:placetype":"venue"
},
  "geometry": {"coordinates":[2.081237,41.469566],"type":"Point"}
}