{
  "type": "Feature",
  "properties": {
    "iso:country":"ES",
    "sg:address":"Pase Pio Baroja De, 5",
    "sg:city":"Donostia-san Sebastian",
    "sg:orig_category":"M\u00c9dicos: Cirug\u00cda Ortop\u00c9dica Y Traumatolog\u00cda",
    "sg:phone":"+34 943 21 62 85",
    "sg:postcode":"20008",
    "sg:province":"Guip\u00f9zcoa",
    "wof:name":"Querejeta Garate Juan Ignacio",
    "wof:placetype":"venue"
},
  "geometry": {"coordinates":[-1.9952449799,43.3108291626],"type":"Point"}
}