{
  "type": "Feature",
  "properties": {
    "addr:full":"Calle de Pontevedra, 1 Albacete Albacete 02005",
    "addr:housenumber":"1",
    "addr:postcode":"02005",
    "addr:street":"Calle De Pontevedra",
    "iso:country":"ES",
    "sg:address":"Calle de Pontevedra, 1",
    "sg:city":"Albacete",
    "sg:orig_category":"Carnicer\u00cdas, Carnicer\u00cdas",
    "sg:phone":"+34 967 23 33 95",
    "sg:postcode":"02005",
    "sg:province":"Albacete",
    "wof:name":"Martinez Ruiz Juan Ramon",
    "wof:placetype":"venue"
},
  "geometry": {"coordinates":[-1.8694310188,38.9985656738],"type":"Point"}
}