{
  "type": "Feature",
  "properties": {
    "iso:country":"ES",
    "sg:address":"Avda Padre Piquer, 16",
    "sg:city":"Madrid",
    "sg:orig_category":"Mec\u00c1nico Del Autom\u00d3vil",
    "sg:phone":"+34 917 11 06 03",
    "sg:postcode":"28024",
    "sg:province":"Madrid",
    "wof:name":"Servicios Gomez De La Gama S.l.",
    "wof:placetype":"venue"
},
  "geometry": {"coordinates":[-3.7684600353,40.3931274414],"type":"Point"}
}