{
  "type": "Feature",
  "properties": {
    "addr:full":"Calle de Tercia, 12 Antequera M\u00e1laga 29200",
    "addr:housenumber":"12",
    "addr:postcode":"29200",
    "addr:street":"Calle De Tercia",
    "iso:country":"ES",
    "sg:address":"Calle de Tercia, 12",
    "sg:city":"Antequera",
    "sg:orig_category":"Agencias Y Agentes Comerciales, Representantes",
    "sg:phone":"+34 952 84 22 82",
    "sg:postcode":"29200",
    "sg:province":"M\u00e1laga",
    "wof:name":"O\u00f1ate Teba Pedro",
    "wof:placetype":"venue"
},
  "geometry": {"coordinates":[-4.5618638992,37.0197486877],"type":"Point"}
}