{
  "type": "Feature",
  "properties": {
    "addr:full":"Pase Alameda, S/n Arevalo \u00c1vila 05200",
    "addr:housenumber":"s",
    "addr:postcode":"05200",
    "addr:street":"Alameda;/ N",
    "iso:country":"ES",
    "sg:address":"Pase Alameda, S/n",
    "sg:city":"Arevalo",
    "sg:orig_category":"Cer\u00c1mica Art\u00cdstica Y Decorativa",
    "sg:phone":"+34 920 30 15 80",
    "sg:postcode":"05200",
    "sg:province":"\u00c1vila",
    "wof:name":"Arroyo Hebrero Isidoro",
    "wof:placetype":"venue"
},
  "geometry": {"coordinates":[-4.7174062729,41.0337677002],"type":"Point"}
}