{
  "type": "Feature",
  "properties": {
    "addr:full":"Carrer de Teide, 17 Barcelona Barcelona 08031",
    "addr:housenumber":"17",
    "addr:postcode":"08031",
    "addr:street":"Carrer De Teide",
    "iso:country":"ES",
    "sg:address":"Carrer de Teide, 17",
    "sg:city":"Barcelona",
    "sg:orig_category":"Peluqueros: De Se\u00d1oras",
    "sg:phone":"+34 934 20 10 16",
    "sg:postcode":"08031",
    "sg:province":"Barcelona",
    "wof:name":"Martinez Barastegui Sebastian",
    "wof:placetype":"venue"
},
  "geometry": {"coordinates":[2.1684799194,41.4308738708],"type":"Point"}
}