{
  "type": "Feature",
  "properties": {
    "iso:country":"ES",
    "sg:address":"Avda Peirao Besada, 77",
    "sg:city":"Lourido",
    "sg:orig_category":"Bebidas",
    "sg:phone":"+34 986 87 28 49",
    "sg:postcode":"36163",
    "sg:province":"Pontevedra",
    "wof:name":"Gonzalez Martinez Luis Antonio",
    "wof:placetype":"venue"
},
  "geometry": {"coordinates":[-8.6428003311,42.4304618835],"type":"Point"}
}