{
  "type": "Feature",
  "properties": {
    "addr:full":"Calle de Santa Eulalia, 25 Santurtzi Vizcaya 48980",
    "addr:housenumber":"25",
    "addr:postcode":"48980",
    "addr:street":"Calle De Santa Eulalia",
    "iso:country":"ES",
    "sg:address":"Calle de Santa Eulalia, 25",
    "sg:city":"Santurtzi",
    "sg:orig_category":"M\u00c1rmoles, Granitos Y Piedras Naturales",
    "sg:phone":"+34 944 61 12 51",
    "sg:postcode":"48980",
    "sg:province":"Vizcaya",
    "wof:name":"Maria Rosa Silva Diez",
    "wof:placetype":"venue"
},
  "geometry": {"coordinates":[-3.0321109295,43.3254432678],"type":"Point"}
}