{
  "type": "Feature",
  "properties": {
    "addr:full":"Ctra Terrassa, 18 Sabadell Barcelona 08201",
    "addr:housenumber":"18",
    "addr:postcode":"08201",
    "addr:street":"Ctra Terrassa",
    "iso:country":"ES",
    "sg:address":"Ctra Terrassa, 18",
    "sg:city":"Sabadell",
    "sg:orig_category":"M\u00c9dicos: Neumolog\u00cda",
    "sg:phone":"+34 937 25 81 69",
    "sg:postcode":"08201",
    "sg:province":"Barcelona",
    "wof:name":"Marin Perez Alberto",
    "wof:placetype":"venue"
},
  "geometry": {"coordinates":[2.1025259495,41.543888092],"type":"Point"}
}