{
  "type": "Feature",
  "properties": {
    "iso:country":"ES",
    "sg:address":"Calle de Cobalto, 20",
    "sg:city":"Valladolid",
    "sg:orig_category":"Electricidad: Equipos Industriales, Componentes (fabricaci\u00d3n)",
    "sg:phone":"+34 983 30 24 81",
    "sg:postcode":"47012",
    "sg:province":"Valladolid",
    "wof:name":"Cegelec S.a.",
    "wof:placetype":"venue"
},
  "geometry": {"coordinates":[-4.7035636902,41.6215286255],"type":"Point"}
}