{
  "type": "Feature",
  "properties": {
    "addr:full":"Barriada Salmeron, 2 Antas Almer\u00eda 04628",
    "addr:housenumber":"2",
    "addr:postcode":"04628",
    "addr:street":"Barriada Salmeron",
    "iso:country":"ES",
    "sg:address":"Barriada Salmeron, 2",
    "sg:city":"Antas",
    "sg:orig_category":"Molduras, Junquillos, Listones Y Molduras Perforadas",
    "sg:phone":"+34 950 45 33 45",
    "sg:postcode":"04628",
    "sg:province":"Almer\u00eda",
    "wof:name":"Casquet Martinez Antonio",
    "wof:placetype":"venue"
},
  "geometry": {"coordinates":[-1.9187179804,37.2447776794],"type":"Point"}
}