{
  "type": "Feature",
  "properties": {
    "addr:full":"Calle de San Isidro, 34 Barrio Roca Valencia 46133",
    "addr:housenumber":"34",
    "addr:postcode":"46133",
    "addr:street":"Calle De San Isidro;Roca",
    "iso:country":"ES",
    "sg:address":"Calle de San Isidro, 34",
    "sg:city":"Barrio Roca",
    "sg:orig_category":"Carnicer\u00cdas, Carnicer\u00cdas",
    "sg:phone":"+34 961 49 18 11",
    "sg:postcode":"46133",
    "sg:province":"Valencia",
    "wof:name":"Roig Esteve Jaime",
    "wof:placetype":"venue"
},
  "geometry": {"coordinates":[-0.3229500055,39.5272941589],"type":"Point"}
}