{
  "type": "Feature",
  "properties": {
    "iso:country":"ES",
    "sg:address":"Plaz San Miguel Arcangel, 8",
    "sg:city":"Abaran",
    "sg:orig_category":"Bares, Piano",
    "sg:phone":"+34 968 77 13 25",
    "sg:postcode":"30550",
    "sg:province":"Murcia",
    "wof:name":"Belmonte Melgarejo Gregorio",
    "wof:placetype":"venue"
},
  "geometry": {"coordinates":[-1.3944859505,38.2074737549],"type":"Point"}
}