{
  "type": "Feature",
  "properties": {
    "iso:country":"ES",
    "sg:address":"Carrer de Menorca, 39",
    "sg:city":"Barcelona",
    "sg:orig_category":"Carnicer\u00cdas, Carnicer\u00cdas",
    "sg:phone":"+34 933 13 10 08",
    "sg:postcode":"08020",
    "sg:province":"Barcelona",
    "wof:name":"Iranzo Creus Jose",
    "wof:placetype":"venue"
},
  "geometry": {"coordinates":[2.1998689175,41.4220275879],"type":"Point"}
}