{
  "type": "Feature",
  "properties": {
    "iso:country":"ES",
    "sg:address":"Calle de Beratua, 14",
    "sg:city":"Logro\u00f1o",
    "sg:orig_category":"Mec\u00c1nico Del Autom\u00d3vil",
    "sg:phone":"+34 941 22 63 05",
    "sg:postcode":"26005",
    "sg:province":"La Rioja",
    "wof:name":"Valga\u00f1on Armas Juan Carlos",
    "wof:placetype":"venue"
},
  "geometry": {"coordinates":[-2.4582331181,42.4664726257],"type":"Point"}
}