{
  "type": "Feature",
  "properties": {
    "addr:full":"Calle de Doctor Patricio Castro, 11 Barbate C\u00e1diz 11160",
    "addr:housenumber":"11",
    "addr:postcode":"11160",
    "addr:street":"Calle De Doctor Patricio Castro",
    "iso:country":"ES",
    "sg:address":"Calle de Doctor Patricio Castro, 11",
    "sg:city":"Barbate",
    "sg:classifiers":[
        {
            "category":"Recreation",
            "type":"Entertainment"
        }
    ],
    "sg:phone":"+34 956 43 10 83",
    "sg:postcode":"11160",
    "sg:province":"C\u00e1diz",
    "sg:tags":[
        "caza",
        "pr\u00c1ctica",
        "la",
        "de",
        "pesca",
        "y"
    ],
    "wof:name":"Gilibert Alvarado C.b",
    "wof:placetype":"venue"
},
  "geometry": {"coordinates":[-5.9219789505,36.1915664673],"type":"Point"}
}