{
  "type": "Feature",
  "properties": {
    "iso:country":"ES",
    "sg:address":"Calle de Acantilado, 28",
    "sg:city":"Albacete",
    "sg:orig_category":"Cuchiller\u00cda (al Por Menor)",
    "sg:phone":"+34 967 23 56 40",
    "sg:postcode":"02006",
    "sg:province":"Albacete",
    "wof:name":"Frias Redondo Eladia",
    "wof:placetype":"venue"
},
  "geometry": {"coordinates":[-1.871689558,38.9835624695],"type":"Point"}
}