{
  "type": "Feature",
  "properties": {
    "addr:full":"Calle de Ferrocarril, 38 Madrid Madrid 28045",
    "addr:housenumber":"38",
    "addr:postcode":"madrid;28045",
    "addr:street":"Calle De Ferrocarril",
    "iso:country":"ES",
    "sg:address":"Calle de Ferrocarril, 38",
    "sg:city":"Madrid",
    "sg:classifiers":[
        {
            "category":"Casinos & Gambling",
            "type":"Entertainment"
        }
    ],
    "sg:phone":"+34 915 06 17 13",
    "sg:postcode":"28045",
    "sg:province":"Madrid",
    "sg:tags":[
        "locale",
        "de",
        "juego"
    ],
    "wof:name":"Ferrojuegos S.a.",
    "wof:placetype":"venue"
},
  "geometry": {"coordinates":[-3.6984980106,40.4011497498],"type":"Point"}
}