{
  "type": "Feature",
  "properties": {
    "iso:country":"ES",
    "sg:address":"Calle de Rumania, 5",
    "sg:city":"Alcala Henares",
    "sg:orig_category":"Alimentaci\u00d3n General (al Por Menor)",
    "sg:phone":"+34 918 77 00 91",
    "sg:postcode":"28802",
    "sg:province":"Madrid",
    "wof:name":"Batesa S.l.",
    "wof:placetype":"venue"
},
  "geometry": {"coordinates":[-3.4041180611,40.4754447937],"type":"Point"}
}