{
  "type": "Feature",
  "properties": {
    "iso:country":"ES",
    "sg:address":"Calle de Francisco Garcia De Sola, 45",
    "sg:city":"Cadiz",
    "sg:orig_category":"Molduras, Junquillos, Listones Y Molduras Perforadas",
    "sg:phone":"+34 956 20 05 34",
    "sg:postcode":"11008",
    "sg:province":"C\u00e1diz",
    "wof:name":"Maria Hosteleria S.l.",
    "wof:placetype":"venue"
},
  "geometry": {"coordinates":[-6.2788438797,36.5155487061],"type":"Point"}
}