{
  "type": "Feature",
  "properties": {
    "iso:country":"ES",
    "sg:address":"Plaz Maria Auxiliadora, 6",
    "sg:city":"Almargen",
    "sg:orig_category":"Cajas Para Embalar",
    "sg:phone":"+34 952 18 20 52",
    "sg:postcode":"29330",
    "sg:province":"M\u00e1laga",
    "wof:name":"Cajamar",
    "wof:placetype":"venue"
},
  "geometry": {"coordinates":[-5.0212688446,37.0026016235],"type":"Point"}
}