{
  "type": "Feature",
  "properties": {
    "iso:country":"ES",
    "sg:address":"Carr Sant Miquel, 3",
    "sg:city":"Solsona",
    "sg:orig_category":"Peluqueros: De Se\u00d1oras",
    "sg:phone":"+34 973 48 38 53",
    "sg:postcode":"25280",
    "sg:province":"Lleida",
    "wof:name":"Pelegrina I Pujol S.l.",
    "wof:placetype":"venue"
},
  "geometry": {"coordinates":[1.5175549984,41.9954185486],"type":"Point"}
}