{
  "type": "Feature",
  "properties": {
    "iso:country":"ES",
    "sg:address":"Poli Escopar, S/n",
    "sg:city":"Peralta",
    "sg:orig_category":"Fabricaci\u00d3n De Etiquetas",
    "sg:phone":"+34 948 75 30 06",
    "sg:postcode":"31350",
    "sg:province":"Navarra",
    "sg:website":"www.serviciosdica.com",
    "wof:name":"Servicios D.i.c.a. S.l.l.",
    "wof:placetype":"venue"
},
  "geometry": {"coordinates":[-1.8131040335,42.33385849],"type":"Point"}
}