{
  "type": "Feature",
  "properties": {
    "addr:full":"Julian Gayarre, 8 Iru\u00f1a Navarra 31005",
    "addr:housenumber":"8",
    "addr:postcode":"31005",
    "addr:street":"Julian Gayarre",
    "iso:country":"ES",
    "sg:address":"Julian Gayarre, 8",
    "sg:city":"Iru\u00f1a",
    "sg:orig_category":"Mercer\u00cda, Lencer\u00cda (al Por Menor)",
    "sg:phone":"+34 948 23 81 78",
    "sg:postcode":"31005",
    "sg:province":"Navarra",
    "wof:name":"Generos De Punto Leara S.l.",
    "wof:placetype":"venue"
},
  "geometry": {"coordinates":[-1.6430319548,42.8076248169],"type":"Point"}
}