{
  "type": "Feature",
  "properties": {
    "addr:full":"Calle de Jose M. Salaberria, 17 Donostia-san Sebastian Guip\u00f9zcoa 20010",
    "addr:housenumber":"17",
    "addr:postcode":"20010",
    "addr:street":"Calle De Jose M. Salaberria",
    "iso:country":"ES",
    "sg:address":"Calle de Jose M. Salaberria, 17",
    "sg:city":"Donostia-san Sebastian",
    "sg:orig_category":"Muebles, Minoristas",
    "sg:phone":"+34 943 47 17 43",
    "sg:postcode":"20010",
    "sg:province":"Guip\u00f9zcoa",
    "wof:name":"Irureta Gurruchaga Candido",
    "wof:placetype":"venue"
},
  "geometry": {"coordinates":[-1.9808549881,43.3073272705],"type":"Point"}
}