{
  "type": "Feature",
  "properties": {
    "iso:country":"ES",
    "sg:address":"Calle de Chavarria, 1",
    "sg:city":"Jerica",
    "sg:orig_category":"Negocio De Materiales De Construcci\u00d3n",
    "sg:phone":"+34 964 12 90 64",
    "sg:postcode":"12450",
    "sg:province":"Castell\u00f3n",
    "wof:name":"Chavarria Materiales De Construccion S.l.",
    "wof:placetype":"venue"
},
  "geometry": {"coordinates":[-0.5723479986,39.9132270813],"type":"Point"}
}