{
  "type": "Feature",
  "properties": {
    "iso:country":"ES",
    "sg:address":"Calle de Joaquin Ortu\u00d1o, 2",
    "sg:city":"S. Miguel Salinas",
    "sg:orig_category":"Librer\u00cdas",
    "sg:phone":"+34 966 72 34 25",
    "sg:postcode":"03193",
    "sg:province":"Alicante",
    "wof:name":"Bargain Books S.l.",
    "wof:placetype":"venue"
},
  "geometry": {"coordinates":[-0.7697899938,37.9393119812],"type":"Point"}
}