{
  "type": "Feature",
  "properties": {
    "addr:full":"Calle de Sor Juana De La Cruz, 10 Zaragoza Zaragoza 50015",
    "addr:housenumber":"10",
    "addr:postcode":"50015",
    "addr:street":"Calle De Sor Juana De La Cruz",
    "iso:country":"ES",
    "sg:address":"Calle de Sor Juana De La Cruz, 10",
    "sg:city":"Zaragoza",
    "sg:orig_category":"Caf\u00c9s, Bares, Cervecer\u00cdas",
    "sg:phone":"+34 976 52 60 02",
    "sg:postcode":"50015",
    "sg:province":"Zaragoza",
    "wof:name":"Suarez Riesco Ana Mary",
    "wof:placetype":"venue"
},
  "geometry": {"coordinates":[-0.8931198716,41.670375824],"type":"Point"}
}