{
  "type": "Feature",
  "properties": {
    "iso:country":"ES",
    "sg:address":"Pase Cervantes, 2",
    "sg:city":"Socuellamos",
    "sg:orig_category":"Bares, Piano",
    "sg:phone":"+34 926 50 01 26",
    "sg:postcode":"13630",
    "sg:province":"Ciudad Real",
    "wof:name":"Antequera Espadas Adrian",
    "wof:placetype":"venue"
},
  "geometry": {"coordinates":[-2.7934026718,39.2854156494],"type":"Point"}
}