{
  "type": "Feature",
  "properties": {
    "addr:full":"Carrer de Parellada (la), 2 Vilafranca Penedes Barcelona 08720",
    "addr:housenumber":"2",
    "addr:postcode":"08720",
    "addr:street":"Carrer De Parellada La;Penedes Barcelona",
    "iso:country":"ES",
    "sg:address":"Carrer de Parellada (la), 2",
    "sg:city":"Vilafranca Penedes",
    "sg:orig_category":"Farmacias",
    "sg:phone":"+34 938 92 01 23",
    "sg:postcode":"08720",
    "sg:province":"Barcelona",
    "wof:name":"Miralles Figueres Eloi",
    "wof:placetype":"venue"
},
  "geometry": {"coordinates":[1.6984440088,41.3469200134],"type":"Point"}
}