{
  "type": "Feature",
  "properties": {
    "iso:country":"ES",
    "sg:address":"Av. Gran Canaria, 18",
    "sg:city":"A Coru\u00f1a",
    "sg:orig_category":"Laboratorios",
    "sg:phone":"+34 981 25 07 99",
    "sg:postcode":"15011",
    "sg:province":"La Coru\u00f1a",
    "wof:name":"Pi\u00f1a Pu\u00f1al Maria De Los Angeles",
    "wof:placetype":"venue"
},
  "geometry": {"coordinates":[-8.4227848053,43.3720436096],"type":"Point"}
}