{
  "type": "Feature",
  "properties": {
    "addr:full":"Calle de Rector Lopez Gonzalez, S/n Santa Fe Granada 18320",
    "addr:postcode":"18320",
    "addr:street":"Calle De Rector Lopez Gonzalez S / N",
    "iso:country":"ES",
    "sg:address":"Calle de Rector Lopez Gonzalez, S/n",
    "sg:city":"Santa Fe",
    "sg:orig_category":"Ense\u00d1anza, Formaci\u00d3n Profesional: Aprendizaje",
    "sg:phone":"+34 958 44 27 44",
    "sg:postcode":"18320",
    "sg:province":"Granada",
    "wof:name":"Junta De Andalucia-consejeria De Cultura",
    "wof:placetype":"venue"
},
  "geometry": {"coordinates":[-3.7180440426,37.1854858398],"type":"Point"}
}