{
  "type": "Feature",
  "properties": {
    "iso:country":"ES",
    "sg:address":"Avda Tierra Llana, S/n",
    "sg:city":"Vilalba",
    "sg:orig_category":"M\u00c1rmoles, Granitos Y Piedras Naturales",
    "sg:phone":"+34 982 51 11 21",
    "sg:postcode":"27800",
    "sg:province":"Lugo",
    "wof:name":"Noche Perez Antonio",
    "wof:placetype":"venue"
},
  "geometry": {"coordinates":[-7.679942131,43.2966995239],"type":"Point"}
}