{
  "type": "Feature",
  "properties": {
    "addr:full":"Rambla De Chapi, 51 Agost Alicante 03698",
    "addr:housenumber":"51",
    "addr:postcode":"03698",
    "addr:street":"Rambla De Chapi",
    "iso:country":"ES",
    "sg:address":"Rambla De Chapi, 51",
    "sg:city":"Agost",
    "sg:orig_category":"Mec\u00c1nico Del Autom\u00d3vil",
    "sg:phone":"+34 965 69 17 78",
    "sg:postcode":"03698",
    "sg:province":"Alicante",
    "wof:name":"Hijos De Jose Berenguer S.l.",
    "wof:placetype":"venue"
},
  "geometry": {"coordinates":[-0.6407949924,38.4395523071],"type":"Point"}
}