{
  "type": "Feature",
  "properties": {
    "iso:country":"ES",
    "sg:address":"Calle de Cruceiro, 20",
    "sg:city":"Palas Rei",
    "sg:orig_category":"Alimentaci\u00d3n General (al Por Menor)",
    "sg:phone":"+34 982 38 03 04",
    "sg:postcode":"27200",
    "sg:province":"Lugo",
    "wof:name":"Garcia Rodriguez Jaime",
    "wof:placetype":"venue"
},
  "geometry": {"coordinates":[-7.8678216934,42.8730392456],"type":"Point"}
}