{
  "type": "Feature",
  "properties": {
    "addr:full":"Palma-inca, Km. 0007,1 Pol Indu Marratxi Islas Baleares 07141",
    "addr:postcode":"07141",
    "addr:street":"Palma-Inca Km. 0007,1 Pol Indu Marratxi",
    "iso:country":"ES",
    "sg:address":"Palma-inca, Km. 0007,1",
    "sg:city":"Pol Indu Marratxi",
    "sg:orig_category":"Bancos",
    "sg:phone":"+34 971 22 66 67",
    "sg:postcode":"07141",
    "sg:province":"Islas Baleares",
    "wof:name":"Banca March S.a.",
    "wof:placetype":"venue"
},
  "geometry": {"coordinates":[2.741590023,39.6156005859],"type":"Point"}
}