{
  "type": "Feature",
  "properties": {
    "addr:full":"Rua San Rosendo, 2 Ourense Ourense 32001",
    "addr:housenumber":"2",
    "addr:postcode":"32001",
    "addr:street":"Rua San Rosendo",
    "iso:country":"ES",
    "sg:address":"Rua San Rosendo, 2",
    "sg:city":"Ourense",
    "sg:orig_category":"Pintura Y Barniz (al Por Menor)",
    "sg:phone":"+34 988 21 83 41",
    "sg:postcode":"32001",
    "sg:province":"Ourense",
    "wof:name":"Quintairos Carrera Antonio",
    "wof:placetype":"venue"
},
  "geometry": {"coordinates":[-7.8725728989,42.3493537903],"type":"Point"}
}