{
  "type": "Feature",
  "properties": {
    "iso:country":"ES",
    "sg:address":"Carrer de Paris, 93",
    "sg:city":"Barcelona",
    "sg:orig_category":"Asesor\u00cda De Formaci\u00d3n Y Gesti\u00d3n De Personal",
    "sg:phone":"+34 933 31 01 83",
    "sg:postcode":"08029",
    "sg:province":"Barcelona",
    "wof:name":"Dominguez Rueda Juan Manuel",
    "wof:placetype":"venue"
},
  "geometry": {"coordinates":[2.1467180252,41.3889045715],"type":"Point"}
}