{
  "type": "Feature",
  "properties": {
    "iso:country":"ES",
    "sg:address":"Pg Sant Joan, 30",
    "sg:city":"Manlleu",
    "sg:orig_category":"Agencias Y Agentes Comerciales, Representantes",
    "sg:phone":"+34 938 51 39 42",
    "sg:postcode":"08560",
    "sg:province":"Barcelona",
    "wof:name":"Rafart Riu Elisabeth",
    "wof:placetype":"venue"
},
  "geometry": {"coordinates":[2.286303997,41.9991874695],"type":"Point"}
}