{
  "type": "Feature",
  "properties": {
    "iso:country":"ES",
    "sg:address":"Calle de George Pire, 16",
    "sg:city":"Palmas De Gran Canaria",
    "sg:orig_category":"Empresas De Limpieza",
    "sg:phone":"+34 928 33 70 63",
    "sg:postcode":"35015",
    "sg:province":"Las Palmas",
    "wof:name":"Limpiezas Miramar S.l.",
    "wof:placetype":"venue"
},
  "geometry": {"coordinates":[-15.4283103943,28.0939712524],"type":"Point"}
}