{
  "type": "Feature",
  "properties": {
    "addr:full":"Calle de Via Carpetana, 53 Madrid Madrid 28047",
    "addr:housenumber":"53",
    "addr:postcode":"madrid;28047",
    "addr:street":"Calle De Via Carpetana",
    "iso:country":"ES",
    "sg:address":"Calle de Via Carpetana, 53",
    "sg:city":"Madrid",
    "sg:orig_category":"Farmacias",
    "sg:phone":"+34 914 72 02 17",
    "sg:postcode":"28047",
    "sg:province":"Madrid",
    "wof:name":"Hernandez Garcia Paloma",
    "wof:placetype":"venue"
},
  "geometry": {"coordinates":[-3.7350149155,40.3981781006],"type":"Point"}
}