{
  "type": "Feature",
  "properties": {
    "addr:full":"Carrer de Sant Lluis, 49 Barcelona Barcelona 08024",
    "addr:housenumber":"49",
    "addr:postcode":"08024",
    "addr:street":"Carrer De Sant Lluis",
    "iso:country":"ES",
    "sg:address":"Carrer de Sant Lluis, 49",
    "sg:city":"Barcelona",
    "sg:orig_category":"Fabricaci\u00d3n, Venta De Cuadros, Accesorios Para Enmarcar",
    "sg:phone":"+34 932 10 28 54",
    "sg:postcode":"08024",
    "sg:province":"Barcelona",
    "wof:name":"Cristaleria Auge C.b.",
    "wof:placetype":"venue"
},
  "geometry": {"coordinates":[2.1602981091,41.4056167603],"type":"Point"}
}