{
  "type": "Feature",
  "properties": {
    "addr:full":"Calle de Pelicano, 13 Valladolid Valladolid 47012",
    "addr:housenumber":"13",
    "addr:postcode":"47012",
    "addr:street":"Calle De Pelicano",
    "iso:country":"ES",
    "sg:address":"Calle de Pelicano, 13",
    "sg:city":"Valladolid",
    "sg:orig_category":"Pescader\u00cdas (al Por Menor)",
    "sg:phone":"+34 983 21 01 26",
    "sg:postcode":"47012",
    "sg:province":"Valladolid",
    "wof:name":"Calvo Manso Pablo",
    "wof:placetype":"venue"
},
  "geometry": {"coordinates":[-4.7101631165,41.6472015381],"type":"Point"}
}