{
  "type": "Feature",
  "properties": {
    "iso:country":"ES",
    "sg:address":"Avgd Alameda Jaume I, 54",
    "sg:city":"Xativa",
    "sg:orig_category":"Parques De Atracciones Y Centros De Esparcimiento",
    "sg:phone":"+34 962 27 69 04",
    "sg:postcode":"46800",
    "sg:province":"Valencia",
    "wof:name":"Circulo Setabense",
    "wof:placetype":"venue"
},
  "geometry": {"coordinates":[-0.5206109881,38.9898643494],"type":"Point"}
}