{
  "type": "Feature",
  "properties": {
    "addr:full":"Pr. Alcalde Jose Crespo Lopez-mora, 2 A Coru\u00f1a La Coru\u00f1a 15008",
    "addr:housenumber":"2 a",
    "addr:postcode":"15008",
    "addr:street":"Jose;Lopez-Mora;Corun\u0303A La Corun\u0303A",
    "iso:country":"ES",
    "sg:address":"Pr. Alcalde Jose Crespo Lopez-mora, 2",
    "sg:city":"A Coru\u00f1a",
    "sg:orig_category":"Centros De Cr\u00c9dito Inmobiliario",
    "sg:phone":"+34 981 16 93 16",
    "sg:postcode":"15008",
    "sg:province":"La Coru\u00f1a",
    "wof:name":"Curto Promotores Inmobiliarios S.a.",
    "wof:placetype":"venue"
},
  "geometry": {"coordinates":[-8.4512443542,43.3434753418],"type":"Point"}
}