{
  "type": "Feature",
  "properties": {
    "iso:country":"ES",
    "sg:address":"Calle de Mendiko Kalea, 1",
    "sg:city":"Arteaga",
    "sg:orig_category":"Panader\u00cdas, Panader\u00cdas",
    "sg:phone":"+34 944 52 14 38",
    "sg:postcode":"48170",
    "sg:province":"Vizcaya",
    "wof:name":"Eva Maria Y Fe Maria Astorquiza Diego C.b.",
    "wof:placetype":"venue"
},
  "geometry": {"coordinates":[-2.8640561104,43.2834243774],"type":"Point"}
}