{
  "type": "Feature",
  "properties": {
    "addr:full":"Calle de Maestro Arrieta, 2 Sevilla Sevilla 41010",
    "addr:housenumber":"2",
    "addr:postcode":"41010",
    "addr:street":"Calle De Maestro Arrieta",
    "iso:country":"ES",
    "sg:address":"Calle de Maestro Arrieta, 2",
    "sg:city":"Sevilla",
    "sg:orig_category":"Confecci\u00d3n De Trajes Para Se\u00d1oras",
    "sg:phone":"+34 954 33 48 66",
    "sg:postcode":"41010",
    "sg:province":"Sevilla",
    "wof:name":"Rebollo Espejo Francisco De Asis",
    "wof:placetype":"venue"
},
  "geometry": {"coordinates":[-6.009428978,37.3822212219],"type":"Point"}
}