{
  "type": "Feature",
  "properties": {
    "addr:full":"Betanzos O Vello, 3 Betanzos-o-vello La Coru\u00f1a 15319",
    "addr:housenumber":"3",
    "addr:postcode":"15319",
    "addr:street":"Betanzos-O-Vello La Corun\u0303A",
    "iso:country":"ES",
    "sg:address":"Betanzos O Vello, 3",
    "sg:city":"Betanzos-o-vello",
    "sg:orig_category":"Forjas Y Altos Hornos",
    "sg:phone":"+34 981 77 00 35",
    "sg:postcode":"15319",
    "sg:province":"La Coru\u00f1a",
    "wof:name":"Picado Lagares Jose Manuel",
    "wof:placetype":"venue"
},
  "geometry": {"coordinates":[-8.2061786652,43.2923545837],"type":"Point"}
}