{
  "type": "Feature",
  "properties": {
    "addr:full":"Avda Brasilia, 11 Madrid Madrid 28028",
    "addr:housenumber":"11",
    "addr:postcode":"madrid;28028",
    "addr:street":"Avda Brasilia",
    "iso:country":"ES",
    "sg:address":"Avda Brasilia, 11",
    "sg:city":"Madrid",
    "sg:orig_category":"Internados & Ense\u00d1anza Privada",
    "sg:phone":"+34 913 56 79 62",
    "sg:postcode":"28028",
    "sg:province":"Madrid",
    "wof:name":"Colegio Menesiano",
    "wof:placetype":"venue"
},
  "geometry": {"coordinates":[-3.6610949039,40.4382743835],"type":"Point"}
}