{
  "type": "Feature",
  "properties": {
    "addr:full":"Avda Constitucion, 239 Valencia Valencia 46019",
    "addr:housenumber":"239",
    "addr:postcode":"46019",
    "addr:street":"Avda Constitucion",
    "iso:country":"ES",
    "sg:address":"Avda Constitucion, 239",
    "sg:city":"Valencia",
    "sg:orig_category":"Promotores Constructores",
    "sg:phone":"+34 963 65 06 21",
    "sg:postcode":"46019",
    "sg:province":"Valencia",
    "wof:name":"Aldesa Construcciones S.a Y Romymar S.a",
    "wof:placetype":"venue"
},
  "geometry": {"coordinates":[-0.3709774017,39.4968070984],"type":"Point"}
}