{
  "type": "Feature",
  "properties": {
    "iso:country":"ES",
    "sg:address":"Avda Rosalia De Castro (de), 158",
    "sg:city":"Santiago De Compostela",
    "sg:orig_category":"Mec\u00c1nico Del Autom\u00d3vil",
    "sg:phone":"+34 981 52 19 94",
    "sg:postcode":"15706",
    "sg:province":"La Coru\u00f1a",
    "wof:name":"M. Caeiro S.a.",
    "wof:placetype":"venue"
},
  "geometry": {"coordinates":[-8.5559473038,42.8719863892],"type":"Point"}
}