{
  "type": "Feature",
  "properties": {
    "iso:country":"ES",
    "sg:address":"Calle de Concepcion, 131",
    "sg:city":"Campo Criptana",
    "sg:orig_category":"M\u00c1rmoles, Granitos Y Piedras Naturales",
    "sg:phone":"+34 926 56 22 06",
    "sg:postcode":"13610",
    "sg:province":"Ciudad Real",
    "wof:name":"Marmoles Y Granitos Jj S.l.",
    "wof:placetype":"venue"
},
  "geometry": {"coordinates":[-3.1181325912,39.4022369385],"type":"Point"}
}