{
  "type": "Feature",
  "properties": {
    "addr:full":"Calle de Laguna, 74 Madrid Madrid 28025",
    "addr:housenumber":"74",
    "addr:postcode":"madrid;28025",
    "addr:street":"Calle De Laguna",
    "iso:country":"ES",
    "sg:address":"Calle de Laguna, 74",
    "sg:city":"Madrid",
    "sg:orig_category":"Reposter\u00cdas",
    "sg:phone":"+34 914 62 87 83",
    "sg:postcode":"28025",
    "sg:province":"Madrid",
    "wof:name":"Andueza Lopez Pedro",
    "wof:placetype":"venue"
},
  "geometry": {"coordinates":[-3.7420477867,40.3871231079],"type":"Point"}
}