{
  "type": "Feature",
  "properties": {
    "addr:full":"Carr Compositor Mundi, 12 Figueres Girona 17600",
    "addr:housenumber":"12",
    "addr:postcode":"17600",
    "addr:street":"Carr Compositor Mundi",
    "iso:country":"ES",
    "sg:address":"Carr Compositor Mundi, 12",
    "sg:city":"Figueres",
    "sg:orig_category":"Empresas De Carpinter\u00cda De Madera",
    "sg:phone":"+34 972 51 22 89",
    "sg:postcode":"17600",
    "sg:province":"Girona",
    "wof:name":"Brugat Ribera Santiago",
    "wof:placetype":"venue"
},
  "geometry": {"coordinates":[2.9668040276,42.2711868286],"type":"Point"}
}