{
  "type": "Feature",
  "properties": {
    "addr:full":"Calle de Sor Angela De La Cruz, 37 Madrid Madrid 28020",
    "addr:housenumber":"37",
    "addr:postcode":"madrid;28020",
    "addr:street":"Calle De Sor Angela De La Cruz",
    "iso:country":"ES",
    "sg:address":"Calle de Sor Angela De La Cruz, 37",
    "sg:city":"Madrid",
    "sg:orig_category":"Restaurantes",
    "sg:phone":"+34 915 71 87 93",
    "sg:postcode":"28020",
    "sg:province":"Madrid",
    "wof:name":"Alimentacion Preparada El Dorado S.l.",
    "wof:placetype":"venue"
},
  "geometry": {"coordinates":[-3.6973705292,40.4602127075],"type":"Point"}
}