{
  "type": "Feature",
  "properties": {
    "addr:full":"Ctra. Cala Gracio, S/n S. Antoni Portmany Islas Baleares 07820",
    "addr:housenumber":"s",
    "addr:postcode":"07820",
    "addr:street":"Ctra. Cala Gracio;/ N S. Antoni Portmany",
    "iso:country":"ES",
    "sg:address":"Ctra. Cala Gracio, S/n",
    "sg:city":"S. Antoni Portmany",
    "sg:orig_category":"Art\u00cdculos De Regalo (al Por Menor)",
    "sg:phone":"+34 971 34 18 22",
    "sg:postcode":"07820",
    "sg:province":"Islas Baleares",
    "wof:name":"Tiendas La Sirena S.l.",
    "wof:placetype":"venue"
},
  "geometry": {"coordinates":[1.2963110209,38.9871025085],"type":"Point"}
}