{
  "type": "Feature",
  "properties": {
    "iso:country":"ES",
    "sg:address":"Calle de Sanchez Toca, 1",
    "sg:city":"Donostia-san Sebastian",
    "sg:orig_category":"Molduras, Junquillos, Listones Y Molduras Perforadas",
    "sg:phone":"+34 943 45 50 23",
    "sg:postcode":"20006",
    "sg:province":"Guip\u00f9zcoa",
    "wof:name":"Alonso Ameztoy Elena",
    "wof:placetype":"venue"
},
  "geometry": {"coordinates":[-1.98036623,43.3161582947],"type":"Point"}
}