{
  "type": "Feature",
  "properties": {
    "addr:full":"Calle de Hort Torremocha, 13 Alzira Valencia 46600",
    "addr:housenumber":"13",
    "addr:postcode":"46600",
    "addr:street":"Calle De Hort Torremocha",
    "iso:country":"ES",
    "sg:address":"Calle de Hort Torremocha, 13",
    "sg:city":"Alzira",
    "sg:orig_category":"Puertas Y Portales",
    "sg:phone":"+34 962 40 36 67",
    "sg:postcode":"46600",
    "sg:province":"Valencia",
    "wof:name":"Puertas Xuquer Cdad.",
    "wof:placetype":"venue"
},
  "geometry": {"coordinates":[-0.4370709956,39.1474075317],"type":"Point"}
}