{
  "type": "Feature",
  "properties": {
    "iso:country":"ES",
    "sg:address":"Pg Catalunya, 21",
    "sg:city":"Torroella Montgri",
    "sg:orig_category":"Electricidad: Instaladores",
    "sg:phone":"+34 972 76 03 57",
    "sg:postcode":"17257",
    "sg:province":"Girona",
    "wof:name":"Insta%acions Baix Ter S.c.",
    "wof:placetype":"venue"
},
  "geometry": {"coordinates":[3.1276109219,42.039390564],"type":"Point"}
}