{
  "type": "Feature",
  "properties": {
    "addr:full":"Calle de Miguel Hernandez, 23 Majadas C\u00e1ceres 10529",
    "addr:housenumber":"23",
    "addr:postcode":"10529",
    "addr:street":"Calle De Miguel Hernandez;Ca\u0301Ceres",
    "iso:country":"ES",
    "sg:address":"Calle de Miguel Hernandez, 23",
    "sg:city":"Majadas",
    "sg:orig_category":"Bazares, Art\u00cdculos De Limpieza Y De Cocina (al Por Menor)",
    "sg:phone":"+34 927 57 71 34",
    "sg:postcode":"10529",
    "sg:province":"C\u00e1ceres",
    "wof:name":"Manzano Bernabe Eugenio",
    "wof:placetype":"venue"
},
  "geometry": {"coordinates":[-5.7461390495,39.9415206909],"type":"Point"}
}