{
  "type": "Feature",
  "properties": {
    "addr:full":"Calle de Granada, 2 Cullar-vega Granada 18195",
    "addr:housenumber":"2",
    "addr:postcode":"18195",
    "addr:street":"Calle De Granada",
    "iso:country":"ES",
    "sg:address":"Calle de Granada, 2",
    "sg:city":"Cullar-vega",
    "sg:orig_category":"Cooperativas Agr\u00cdcolas",
    "sg:phone":"+34 958 58 08 64",
    "sg:postcode":"18195",
    "sg:province":"Granada",
    "wof:name":"Couaga Vegas De Granada S.c.a.",
    "wof:placetype":"venue"
},
  "geometry": {"coordinates":[-3.669328928,37.1525840759],"type":"Point"}
}