{
  "type": "Feature",
  "properties": {
    "addr:full":"Carrer de Sant Eloi, 3 Barcelona Barcelona 08038",
    "addr:housenumber":"3",
    "addr:postcode":"08038",
    "addr:street":"Carrer De Sant Eloi",
    "iso:country":"ES",
    "sg:address":"Carrer de Sant Eloi, 3",
    "sg:city":"Barcelona",
    "sg:orig_category":"Mec\u00c1nico Del Autom\u00d3vil",
    "sg:phone":"+34 932 23 36 63",
    "sg:postcode":"08038",
    "sg:province":"Barcelona",
    "wof:name":"Moreno Lopez Antonio",
    "wof:placetype":"venue"
},
  "geometry": {"coordinates":[2.1425468922,41.3558921814],"type":"Point"}
}