{
  "type": "Feature",
  "properties": {
    "iso:country":"ES",
    "sg:address":"Calle de Garrigues, Les, 5",
    "sg:city":"Valencia",
    "sg:orig_category":"Grafistas",
    "sg:phone":"+34 963 51 44 72",
    "sg:postcode":"46001",
    "sg:province":"Valencia",
    "wof:name":"Eescenes C.b.",
    "wof:placetype":"venue"
},
  "geometry": {"coordinates":[-0.3784680068,39.4706306458],"type":"Point"}
}