{
  "type": "Feature",
  "properties": {
    "iso:country":"ES",
    "sg:address":"Calle de Higuera (la), S/n",
    "sg:city":"Cordoba",
    "sg:orig_category":"Material Y Suministros Para Peluquer\u00cda",
    "sg:phone":"+34 957 76 77 96",
    "sg:postcode":"14006",
    "sg:province":"C\u00f3rdoba",
    "wof:name":"Gonzalez Garcia Paloma",
    "wof:placetype":"venue"
},
  "geometry": {"coordinates":[-4.7801041603,37.8976783752],"type":"Point"}
}