{
  "type": "Feature",
  "properties": {
    "iso:country":"ES",
    "sg:address":"Calle de San Juan, 13",
    "sg:city":"Navas Del Marques",
    "sg:orig_category":"Molduras, Junquillos, Listones Y Molduras Perforadas",
    "sg:phone":"+34 918 97 24 62",
    "sg:postcode":"05230",
    "sg:province":"\u00c1vila",
    "wof:name":"Quiros Martin Felipe",
    "wof:placetype":"venue"
},
  "geometry": {"coordinates":[-4.3316340446,40.6026420593],"type":"Point"}
}