{
  "type": "Feature",
  "properties": {
    "addr:full":"Calle de Simon Hernandez (de), 53 Mostoles Madrid 28936",
    "addr:housenumber":"53",
    "addr:postcode":"28936",
    "addr:street":"Calle De Simon Hernandez De",
    "iso:country":"ES",
    "sg:address":"Calle de Simon Hernandez (de), 53",
    "sg:city":"Mostoles",
    "sg:orig_category":"Alimentaci\u00d3n General (al Por Menor)",
    "sg:phone":"+34 916 47 17 51",
    "sg:postcode":"28936",
    "sg:province":"Madrid",
    "wof:name":"Brizzolaro Mayoral Nelson Humberto",
    "wof:placetype":"venue"
},
  "geometry": {"coordinates":[-3.8527541161,40.3186073303],"type":"Point"}
}