{
  "type": "Feature",
  "properties": {
    "iso:country":"ES",
    "sg:address":"Calle de Balendin Berrio-otxoa, 24",
    "sg:city":"Elorrio",
    "sg:orig_category":"Agencias De Viajes",
    "sg:phone":"+34 946 58 46 51",
    "sg:postcode":"48230",
    "sg:province":"Vizcaya",
    "wof:name":"Txangoa Bidaiak S.l.",
    "wof:placetype":"venue"
},
  "geometry": {"coordinates":[-2.540612936,43.1289215088],"type":"Point"}
}