{
  "type": "Feature",
  "properties": {
    "iso:country":"ES",
    "sg:address":"Carrer de Bonestar, 9",
    "sg:city":"Cornella Llobregat",
    "sg:orig_category":"Mercer\u00cda, Lencer\u00cda (al Por Menor)",
    "sg:phone":"+34 934 71 04 19",
    "sg:postcode":"08940",
    "sg:province":"Barcelona",
    "wof:name":"Paquico Cumbre Eugenio",
    "wof:placetype":"venue"
},
  "geometry": {"coordinates":[2.0746641159,41.357635498],"type":"Point"}
}