{
  "type": "Feature",
  "properties": {
    "addr:full":"Masia Molino Sollavientos, S/n Allepuz Teruel 44145",
    "addr:housenumber":"s",
    "addr:postcode":"44145",
    "addr:street":"/ N",
    "iso:country":"ES",
    "sg:address":"Masia Molino Sollavientos, S/n",
    "sg:city":"Allepuz",
    "sg:orig_category":"Albergues",
    "sg:phone":"+34 978 72 41 42",
    "sg:postcode":"44145",
    "sg:province":"Teruel",
    "wof:name":"Hostal Masquemado S.l.",
    "wof:placetype":"venue"
},
  "geometry": {"coordinates":[-0.7304189801,40.4916610718],"type":"Point"}
}