{
  "type": "Feature",
  "properties": {
    "iso:country":"ES",
    "sg:address":"Praj San Babil, 1",
    "sg:city":"Salinas Pamplona",
    "sg:orig_category":"Contenedores (mercanc\u00cdas)",
    "sg:phone":"+34 948 34 69 80",
    "sg:postcode":"31191",
    "sg:province":"Navarra",
    "wof:name":"Viuda De Londaiz Y Sobrinos De L.mercade",
    "wof:placetype":"venue"
},
  "geometry": {"coordinates":[-1.6442149878,42.8179893494],"type":"Point"}
}