{
  "type": "Feature",
  "properties": {
    "addr:full":"Calle de Burgos, 2 Vitoria-gasteiz \u00c1lava 01002",
    "addr:housenumber":"2",
    "addr:postcode":"01002",
    "addr:street":"Calle De Burgos",
    "iso:country":"ES",
    "sg:address":"Calle de Burgos, 2",
    "sg:city":"Vitoria-gasteiz",
    "sg:orig_category":"Maquinaria Para Industrias Diversas",
    "sg:phone":"+34 945 27 99 88",
    "sg:postcode":"01002",
    "sg:province":"\u00c1lava",
    "wof:name":"Loizaga S.a.",
    "wof:placetype":"venue"
},
  "geometry": {"coordinates":[-2.6605141163,42.855178833],"type":"Point"}
}