{
  "type": "Feature",
  "properties": {
    "iso:country":"ES",
    "sg:address":"Calle de Felipe Iv, 10",
    "sg:city":"Madrid",
    "sg:orig_category":"Organismos De Reclutamiento",
    "sg:phone":"+34 913 69 23 23",
    "sg:postcode":"28014",
    "sg:province":"Madrid",
    "wof:name":"Human Resources Management International S.a.",
    "wof:placetype":"venue"
},
  "geometry": {"coordinates":[-3.6897749901,40.4150276184],"type":"Point"}
}