{
  "type": "Feature",
  "properties": {
    "iso:country":"ES",
    "sg:address":"Avda Mediterraneo, 43",
    "sg:city":"Benidorm",
    "sg:orig_category":"Bazares, Art\u00cdculos De Limpieza Y De Cocina (al Por Menor)",
    "sg:phone":"+34 965 85 84 85",
    "sg:postcode":"03500",
    "sg:province":"Alicante",
    "wof:name":"Yie  Shu Jing",
    "wof:placetype":"venue"
},
  "geometry": {"coordinates":[-0.1120525002,38.5359725952],"type":"Point"}
}