{
  "type": "Feature",
  "properties": {
    "addr:full":"Carrer de Francesc Catala-roca, 6 Terrassa Barcelona 08222",
    "addr:housenumber":"6",
    "addr:postcode":"08222",
    "addr:street":"Carrer De Francesc Catala-Roca",
    "iso:country":"ES",
    "sg:address":"Carrer de Francesc Catala-roca, 6",
    "sg:city":"Terrassa",
    "sg:orig_category":"Peluquer\u00cdas, Peluquer\u00cda Mixta",
    "sg:phone":"+34 937 83 97 16",
    "sg:postcode":"08222",
    "sg:province":"Barcelona",
    "wof:name":"Monfort Perez Marc",
    "wof:placetype":"venue"
},
  "geometry": {"coordinates":[2.0197920799,41.5618858337],"type":"Point"}
}