{
  "type": "Feature",
  "properties": {
    "iso:country":"ES",
    "sg:address":"Calle de Zodiaco, 2",
    "sg:city":"Arroyo De La Miel-benalmadena Costa",
    "sg:orig_category":"Librer\u00cdas",
    "sg:phone":"+34 952 44 65 59",
    "sg:postcode":"29630",
    "sg:province":"M\u00e1laga",
    "wof:name":"Garcia Ramirez Francisco",
    "wof:placetype":"venue"
},
  "geometry": {"coordinates":[-4.527739048,36.598613739],"type":"Point"}
}