{
  "type": "Feature",
  "properties": {
    "addr:full":"Plaz Molino, S/n Jerez Del Marquesado Granada 18518",
    "addr:housenumber":"s",
    "addr:postcode":"18518",
    "addr:street":"Plaz Molino;/ N",
    "iso:country":"ES",
    "sg:address":"Plaz Molino, S/n",
    "sg:city":"Jerez Del Marquesado",
    "sg:orig_category":"Administraciones Regionales, Departamentales Y Locales",
    "sg:phone":"+34 958 67 21 03",
    "sg:postcode":"18518",
    "sg:province":"Granada",
    "wof:name":"Ayuntamiento De Jerez Del Marquesado",
    "wof:placetype":"venue"
},
  "geometry": {"coordinates":[-3.1597568989,37.1837921143],"type":"Point"}
}