{
  "type": "Feature",
  "properties": {
    "iso:country":"ES",
    "sg:address":"Calle de Arrayanes, S/n",
    "sg:city":"Martos",
    "sg:orig_category":"M\u00c9dicos: Estomatolog\u00cda",
    "sg:phone":"+34 953 70 22 18",
    "sg:postcode":"23600",
    "sg:province":"Ja\u00e9n",
    "wof:name":"Pino Mitelbrum Manuel",
    "wof:placetype":"venue"
},
  "geometry": {"coordinates":[-3.9739730358,37.7199058533],"type":"Point"}
}