{
  "type": "Feature",
  "properties": {
    "addr:full":"Puga, S/n Pruvia Asturias 33192",
    "addr:postcode":"33192",
    "addr:street":"Puga S / N",
    "iso:country":"ES",
    "sg:address":"Puga, S/n",
    "sg:city":"Pruvia",
    "sg:orig_category":"Molduras, Junquillos, Listones Y Molduras Perforadas",
    "sg:phone":"+34 985 26 00 30",
    "sg:postcode":"33192",
    "sg:province":"Asturias",
    "wof:name":"Menendez Menendez Amadora",
    "wof:placetype":"venue"
},
  "geometry": {"coordinates":[-5.7745718956,43.4596939087],"type":"Point"}
}