{
  "type": "Feature",
  "properties": {
    "addr:full":"Calle de Mistral, 16 Majadahonda Madrid 28220",
    "addr:housenumber":"16",
    "addr:postcode":"28220",
    "addr:street":"Calle De Mistral",
    "iso:country":"ES",
    "sg:address":"Calle de Mistral, 16",
    "sg:city":"Majadahonda",
    "sg:orig_category":"Inform\u00c1tica: Consultores",
    "sg:phone":"+34 916 38 23 00",
    "sg:postcode":"28220",
    "sg:province":"Madrid",
    "wof:name":"Velarde Bleichner Mario",
    "wof:placetype":"venue"
},
  "geometry": {"coordinates":[-3.8588240147,40.4778289795],"type":"Point"}
}