{
  "type": "Feature",
  "properties": {
    "addr:full":"Rua Rosalia De Castro, 10 Cee La Coru\u00f1a 15270",
    "addr:housenumber":"10",
    "addr:postcode":"15270",
    "addr:street":"Rua Rosalia De Castro",
    "iso:country":"ES",
    "sg:address":"Rua Rosalia De Castro, 10",
    "sg:city":"Cee",
    "sg:orig_category":"Quincaller\u00cda (al Por Menor)",
    "sg:phone":"+34 981 74 61 10",
    "sg:postcode":"15270",
    "sg:province":"La Coru\u00f1a",
    "wof:name":"Costa Casais Jose Marcial",
    "wof:placetype":"venue"
},
  "geometry": {"coordinates":[-9.1875753403,42.9533348083],"type":"Point"}
}