{
  "type": "Feature",
  "properties": {
    "addr:full":"Calle de Uria, 26 Oviedo Asturias 33003",
    "addr:housenumber":"26",
    "addr:postcode":"33003",
    "addr:street":"Calle De Uria",
    "iso:country":"ES",
    "sg:address":"Calle de Uria, 26",
    "sg:city":"Oviedo",
    "sg:orig_category":"Asociaciones Humanitarias, De Cooperaci\u00d3n, De Acci\u00d3n Social",
    "sg:phone":"+34 985 20 32 45",
    "sg:postcode":"33003",
    "sg:province":"Asturias",
    "wof:name":"Asociacion Espa\u00f1ola Contra El Cancer",
    "wof:placetype":"venue"
},
  "geometry": {"coordinates":[-5.8507099152,43.3636283875],"type":"Point"}
}