{
  "type": "Feature",
  "properties": {
    "addr:full":"Calle de Lazaro, 33 Ciudad Rodrigo Salamanca 37500",
    "addr:housenumber":"33",
    "addr:postcode":"37500",
    "addr:street":"Calle De Lazaro",
    "iso:country":"ES",
    "sg:address":"Calle de Lazaro, 33",
    "sg:city":"Ciudad Rodrigo",
    "sg:classifiers":[
        {
            "category":"Home & Garden",
            "subcategory":"Household Appliances",
            "type":"Retail Goods"
        }
    ],
    "sg:phone":"+34 923 46 17 79",
    "sg:postcode":"37500",
    "sg:province":"Salamanca",
    "sg:tags":[
        "bodega",
        "de",
        "vino",
        "acondicionamiento"
    ],
    "wof:name":"Andres Perez Santiago",
    "wof:placetype":"venue"
},
  "geometry": {"coordinates":[-6.5260286331,40.5990753174],"type":"Point"}
}