{
  "type": "Feature",
  "properties": {
    "addr:full":"Via Augusta, 136 Barcelona Barcelona 08006",
    "addr:housenumber":"136",
    "addr:postcode":"08006",
    "addr:street":"Via Augusta",
    "iso:country":"ES",
    "sg:address":"Via Augusta, 136",
    "sg:city":"Barcelona",
    "sg:orig_category":"Comit\u00c9s De Organizaci\u00d3n De Exposiciones, Ferias, Salones",
    "sg:phone":"+34 934 57 31 00",
    "sg:postcode":"08006",
    "sg:province":"Barcelona",
    "sg:website":"www.dcompany.com",
    "wof:name":"D-company Incentivos S.l.",
    "wof:placetype":"venue"
},
  "geometry": {"coordinates":[2.1457819939,41.4006080627],"type":"Point"}
}