{
  "type": "Feature",
  "properties": {
    "iso:country":"ES",
    "sg:address":"Avda Pueyo, 34",
    "sg:city":"Monzon",
    "sg:orig_category":"Fabricaci\u00d3n De Juguetes Autom\u00c1ticos",
    "sg:phone":"+34 974 40 18 14",
    "sg:postcode":"22400",
    "sg:province":"Huesca",
    "wof:name":"Lancry S.a.",
    "wof:placetype":"venue"
},
  "geometry": {"coordinates":[0.1862799972,41.9063301086],"type":"Point"}
}