{
  "type": "Feature",
  "properties": {
    "iso:country":"ES",
    "sg:address":"Ctra Logro\u00d1o, S/n",
    "sg:city":"Navarrete",
    "sg:orig_category":"Alfarer\u00cda",
    "sg:phone":"+34 941 44 04 76",
    "sg:postcode":"26370",
    "sg:province":"La Rioja",
    "wof:name":"Alfareria Hnos.fajardo Lozano S.c",
    "wof:placetype":"venue"
},
  "geometry": {"coordinates":[-2.581387043,42.4241256714],"type":"Point"}
}