{
  "type": "Feature",
  "properties": {
    "iso:country":"ES",
    "sg:address":"Planta De Hormigon, S/n",
    "sg:city":"La Olmeda",
    "sg:orig_category":"Empresas De Hormig\u00d3n, Hormig\u00d3n Armado Y Pretensado",
    "sg:phone":"+34 975 34 07 88",
    "sg:postcode":"42313",
    "sg:province":"Soria",
    "wof:name":"Del Pino Y Mateo S. L.",
    "wof:placetype":"venue"
},
  "geometry": {"coordinates":[-2.9760789871,41.5080184937],"type":"Point"}
}