{
  "type": "Feature",
  "properties": {
    "addr:full":"Calle de General Primo De Rivera, 2 Tarifa C\u00e1diz 11380",
    "addr:housenumber":"2",
    "addr:postcode":"11380",
    "addr:street":"Calle De General Primo De Rivera;Ca\u0301Diz",
    "iso:country":"ES",
    "sg:address":"Calle de General Primo De Rivera, 2",
    "sg:city":"Tarifa",
    "sg:orig_category":"Deportes N\u00c1uticos, Acu\u00c1ticos Y Subacu\u00c1ticos: Art\u00cdculos Y Equipo (al Por Menor)",
    "sg:phone":"+34 956 68 22 57",
    "sg:postcode":"11380",
    "sg:province":"C\u00e1diz",
    "wof:name":"Trillo Huertas Daniel",
    "wof:placetype":"venue"
},
  "geometry": {"coordinates":[-5.6070342064,36.017250061],"type":"Point"}
}