{
  "type": "Feature",
  "properties": {
    "iso:country":"ES",
    "sg:address":"Pase Alfonso Xiii, 14",
    "sg:city":"Cartagena",
    "sg:orig_category":"M\u00c9dicos: Oftalmolog\u00cda",
    "sg:phone":"+34 968 50 43 13",
    "sg:postcode":"30201",
    "sg:province":"Murcia",
    "wof:name":"Jimenez Ca\u00f1avete Domingo",
    "wof:placetype":"venue"
},
  "geometry": {"coordinates":[-0.9862040281,37.6066856384],"type":"Point"}
}