{
  "type": "Feature",
  "properties": {
    "addr:full":"Villajoyosa(pol Ind Alberca), 67 La Nucia Alicante 03530",
    "addr:housenumber":"67",
    "addr:postcode":"03530",
    "addr:street":"Alberca",
    "iso:country":"ES",
    "sg:address":"Villajoyosa(pol Ind Alberca), 67",
    "sg:city":"La Nucia",
    "sg:orig_category":"Alimentaci\u00d3n General (al Por Menor)",
    "sg:phone":"+34 965 87 01 11",
    "sg:postcode":"03530",
    "sg:province":"Alicante",
    "wof:name":"Kuzh Alacant S.l.",
    "wof:placetype":"venue"
},
  "geometry": {"coordinates":[-0.1249789968,38.6157951355],"type":"Point"}
}