{
  "type": "Feature",
  "properties": {
    "addr:full":"Plaz Filabres, 7 Bacares Almer\u00eda 04889",
    "addr:housenumber":"7",
    "addr:postcode":"04889",
    "addr:street":"Filabres;Almeri\u0301A",
    "iso:country":"ES",
    "sg:address":"Plaz Filabres, 7",
    "sg:city":"Bacares",
    "sg:orig_category":"Administraciones Regionales, Departamentales Y Locales",
    "sg:phone":"+34 950 42 10 16",
    "sg:postcode":"04889",
    "sg:province":"Almer\u00eda",
    "wof:name":"Ayuntamiento",
    "wof:placetype":"venue"
},
  "geometry": {"coordinates":[-2.4534399509,37.2608718872],"type":"Point"}
}