{
  "type": "Feature",
  "properties": {
    "iso:country":"ES",
    "sg:address":"Plaz Alcolea, 18",
    "sg:city":"Cartagena",
    "sg:orig_category":"Abogados",
    "sg:phone":"+34 968 12 03 70",
    "sg:postcode":"30201",
    "sg:province":"Murcia",
    "wof:name":"Asem Servicio De Prevencion C.b.",
    "wof:placetype":"venue"
},
  "geometry": {"coordinates":[-0.9901285768,37.6052970886],"type":"Point"}
}