{
  "type": "Feature",
  "properties": {
    "addr:full":"Cal Batlle, S/n Breda Girona 17400",
    "addr:housenumber":"s / n",
    "addr:postcode":"17400",
    "addr:street":"Cal Batlle",
    "iso:country":"ES",
    "sg:address":"Cal Batlle, S/n",
    "sg:city":"Breda",
    "sg:orig_category":"Maquinaria Para Industrias Diversas",
    "sg:phone":"+34 972 87 15 22",
    "sg:postcode":"17400",
    "sg:province":"Girona",
    "wof:name":"Fernanadez Martin Francesc",
    "wof:placetype":"venue"
},
  "geometry": {"coordinates":[2.5594749451,41.7517814636],"type":"Point"}
}