{
  "type": "Feature",
  "properties": {
    "iso:country":"ES",
    "sg:address":"Carrer de Elisenda De Montcada, 15",
    "sg:city":"Premia Mar",
    "sg:orig_category":"Grabados",
    "sg:phone":"+34 937 51 73 24",
    "sg:postcode":"08330",
    "sg:province":"Barcelona",
    "wof:name":"Grabats Dos Mil S. L.",
    "wof:placetype":"venue"
},
  "geometry": {"coordinates":[2.3607289791,41.491607666],"type":"Point"}
}