{
  "type": "Feature",
  "properties": {
    "addr:full":"Pg Mediterrani, S/n Miami Platja Tarragona 43892",
    "addr:housenumber":"s / n",
    "addr:postcode":"43892",
    "addr:street":"Pg Mediterrani",
    "iso:country":"ES",
    "sg:address":"Pg Mediterrani, S/n",
    "sg:city":"Miami Platja",
    "sg:orig_category":"Administradores De Bienes Y Delegados De Comunidades De Propietarios",
    "sg:phone":"+34 977 17 00 95",
    "sg:postcode":"43892",
    "sg:province":"Tarragona",
    "wof:name":"Estiu Blau S.l.",
    "wof:placetype":"venue"
},
  "geometry": {"coordinates":[0.9380300045,41.0048484802],"type":"Point"}
}