{
  "type": "Feature",
  "properties": {
    "addr:full":"Comandante Franco, 22 Navas San Juan Ja\u00e9n 23240",
    "addr:housenumber":"22",
    "addr:postcode":"23240",
    "addr:street":"Comandante Franco",
    "iso:country":"ES",
    "sg:address":"Comandante Franco, 22",
    "sg:city":"Navas San Juan",
    "sg:orig_category":"Abogados",
    "sg:phone":"+34 953 68 70 13",
    "sg:postcode":"23240",
    "sg:province":"Ja\u00e9n",
    "wof:name":"Siles Heredia Francisca",
    "wof:placetype":"venue"
},
  "geometry": {"coordinates":[-3.3145930767,38.1859436035],"type":"Point"}
}