{
  "type": "Feature",
  "properties": {
    "iso:country":"ES",
    "sg:address":"Calle de Severo Ochoa, S/n",
    "sg:city":"Grela",
    "sg:orig_category":"Transporte En General",
    "sg:phone":"+34 981 14 31 10",
    "sg:postcode":"15008",
    "sg:province":"La Coru\u00f1a",
    "wof:name":"Rodriguez Rodriguez Jose",
    "wof:placetype":"venue"
},
  "geometry": {"coordinates":[-8.4512443542,43.3434753418],"type":"Point"}
}