{
  "type": "Feature",
  "properties": {
    "iso:country":"ES",
    "sg:address":"Carrer de Libra, 40",
    "sg:city":"Terrassa",
    "sg:orig_category":"Fabricaci\u00d3n De Revestimientos De Suelos Pl\u00c1sticos Y De Goma",
    "sg:phone":"+34 937 31 88 07",
    "sg:postcode":"08228",
    "sg:province":"Barcelona",
    "sg:website":"www.recubrimientosortega.com",
    "wof:name":"Acabats Sermar S.l.u",
    "wof:placetype":"venue"
},
  "geometry": {"coordinates":[2.037031,41.540581],"type":"Point"}
}