{
  "type": "Feature",
  "properties": {
    "addr:full":"Carrer de Turo De L'home, 42 Urbanitzacio El Mas Mora Barcelona 08490",
    "addr:housenumber":"42",
    "addr:postcode":"08490",
    "addr:street":"Carrer De Turo De L'Home;Urbanitzacio El Mas Mora Barcelona",
    "iso:country":"ES",
    "sg:address":"Carrer de Turo De L'home, 42",
    "sg:city":"Urbanitzacio El Mas Mora",
    "sg:orig_category":"Expertos Contables",
    "sg:phone":"+34 937 64 04 19",
    "sg:postcode":"08490",
    "sg:province":"Barcelona",
    "wof:name":"Am Peritajes Tecnicos S.l.",
    "wof:placetype":"venue"
},
  "geometry": {"coordinates":[2.7396330833,41.7067565918],"type":"Point"}
}