{
  "type": "Feature",
  "properties": {
    "iso:country":"ES",
    "sg:address":"Carrer de Turo De L'home, 42",
    "sg:city":"Urbanitzacio El Mas Mora",
    "sg:orig_category":"Expertos Contables",
    "sg:phone":"+34 937 64 04 19",
    "sg:postcode":"08490",
    "sg:province":"Barcelona",
    "wof:name":"Am Peritajes Tecnicos S.l.",
    "wof:placetype":"venue"
},
  "geometry": {"coordinates":[2.7396330833,41.7067565918],"type":"Point"}
}