{
  "type": "Feature",
  "properties": {
    "iso:country":"ES",
    "sg:address":"Calle de Santos Vivanco, 2",
    "sg:city":"Castellon",
    "sg:classifiers":[
        {
            "category":"Arts & Performance",
            "subcategory":"Art Gallery",
            "type":"Entertainment"
        }
    ],
    "sg:phone":"+34 964 20 20 27",
    "sg:postcode":"12001",
    "sg:province":"Castell\u00f3n",
    "sg:tags":[
        "arte",
        "de",
        "galer\u00cdas"
    ],
    "wof:name":"Galeria Zafiro S.l.",
    "wof:placetype":"venue"
},
  "geometry": {"coordinates":[-0.0390900001,39.9866714478],"type":"Point"}
}