{
  "type": "Feature",
  "properties": {
    "addr:full":"Avda Monte Igueldo, 26 Madrid Madrid 28053",
    "addr:housenumber":"26",
    "addr:postcode":"madrid;28053",
    "addr:street":"Avda Monte Igueldo",
    "iso:country":"ES",
    "sg:address":"Avda Monte Igueldo, 26",
    "sg:city":"Madrid",
    "sg:orig_category":"Ropa Para Se\u00d1oras Y Caballeros (al Por Menor)",
    "sg:phone":"+34 915 01 45 11",
    "sg:postcode":"28053",
    "sg:province":"Madrid",
    "wof:name":"Martinez Martinez Francisco",
    "wof:placetype":"venue"
},
  "geometry": {"coordinates":[-3.6687610149,40.3957290649],"type":"Point"}
}