{
  "type": "Feature",
  "properties": {
    "iso:country":"ES",
    "sg:address":"Carrer de Mare De Deu De L'orito, S/n",
    "sg:city":"Xixona",
    "sg:orig_category":"Pescader\u00cdas (al Por Menor)",
    "sg:phone":"+34 965 61 14 62",
    "sg:postcode":"03100",
    "sg:province":"Alicante",
    "wof:name":"Galva\u00f1 Alberola Hector Ramon",
    "wof:placetype":"venue"
},
  "geometry": {"coordinates":[-0.5068824291,38.5469474792],"type":"Point"}
}