{
  "type": "Feature",
  "properties": {
    "addr:full":"Cami Ral, 490 Mataro Barcelona 08302",
    "addr:housenumber":"490",
    "addr:postcode":"08302",
    "addr:street":"Ral",
    "iso:country":"ES",
    "sg:address":"Cami Ral, 490",
    "sg:city":"Mataro",
    "sg:orig_category":"Agencias De Viajes",
    "sg:phone":"+34 937 99 87 76",
    "sg:postcode":"08302",
    "sg:province":"Barcelona",
    "sg:website":"www.viajeselcorteingles.es",
    "wof:name":"Viajes El Corte Ingles S.a.",
    "wof:placetype":"venue"
},
  "geometry": {"coordinates":[2.4417819977,41.5354385376],"type":"Point"}
}