{
  "type": "Feature",
  "properties": {
    "addr:full":"Urb Cometa, S/n Calpe Alicante 03710",
    "addr:housenumber":"s / n",
    "addr:postcode":"03710",
    "iso:country":"ES",
    "sg:address":"Urb Cometa, S/n",
    "sg:city":"Calpe",
    "sg:orig_category":"Inmobiliaria (agencias)",
    "sg:phone":"+34 965 83 67 09",
    "sg:postcode":"03710",
    "sg:province":"Alicante",
    "wof:name":"Mccrae  Barry John",
    "wof:placetype":"venue"
},
  "geometry": {"coordinates":[0.0654349998,38.6643791199],"type":"Point"}
}