{
  "type": "Feature",
  "properties": {
    "iso:country":"ES",
    "sg:address":"Calle de Don Miro, 4",
    "sg:city":"Palencia",
    "sg:orig_category":"Peluqueros: De Se\u00d1oras",
    "sg:phone":"+34 979 74 13 29",
    "sg:postcode":"34005",
    "sg:province":"Palencia",
    "wof:name":"Fonseca Gonzalez Belinda",
    "wof:placetype":"venue"
},
  "geometry": {"coordinates":[-4.5349478722,42.0077400208],"type":"Point"}
}