{
  "type": "Feature",
  "properties": {
    "addr:full":"Avda Rafael Cabrera, 22 Palmas De Gran Canaria Las Palmas 35002",
    "addr:postcode":"35002",
    "addr:street":"Avda Rafael Cabrera 22",
    "iso:country":"ES",
    "sg:address":"Avda Rafael Cabrera, 22",
    "sg:city":"Palmas De Gran Canaria",
    "sg:orig_category":"Comercio De Mobiliario De Oficina",
    "sg:phone":"+34 928 36 93 45",
    "sg:postcode":"35002",
    "sg:province":"Las Palmas",
    "wof:name":"Servicio De Maquinas Electronicas S. A.",
    "wof:placetype":"venue"
},
  "geometry": {"coordinates":[-15.4150238037,28.1069698334],"type":"Point"}
}