{
  "type": "Feature",
  "properties": {
    "addr:full":"Calle de Puerto Del Pino, 9 Blimea Asturias 33960",
    "addr:housenumber":"9",
    "addr:postcode":"33960",
    "addr:street":"Calle De Puerto Del Pino;Asturias",
    "iso:country":"ES",
    "sg:address":"Calle de Puerto Del Pino, 9",
    "sg:city":"Blimea",
    "sg:orig_category":"Servidores Y Editores De Bases De Datos",
    "sg:phone":"+34 985 65 65 95",
    "sg:postcode":"33960",
    "sg:province":"Asturias",
    "sg:website":"www.asturiastelecentro.com",
    "wof:name":"Ayuntamiento De San Martin Del Rey Aurel",
    "wof:placetype":"venue"
},
  "geometry": {"coordinates":[-5.5887727737,43.2727432251],"type":"Point"}
}