{
  "type": "Feature",
  "properties": {
    "iso:country":"ES",
    "sg:address":"Avda Naos (de), S/n",
    "sg:city":"Arrecife",
    "sg:orig_category":"Contenedores (mercanc\u00cdas)",
    "sg:phone":"+34 928 80 67 21",
    "sg:postcode":"35500",
    "sg:province":"Las Palmas",
    "wof:name":"Dhl Exel Supply Chain S.l.u.",
    "wof:placetype":"venue"
},
  "geometry": {"coordinates":[-13.5420742035,28.9634456635],"type":"Point"}
}