{
  "type": "Feature",
  "properties": {
    "iso:country":"ES",
    "sg:address":"Pg Maragall, 309",
    "sg:city":"Barcelona",
    "sg:orig_category":"Ingeniero",
    "sg:phone":"+34 934 07 23 55",
    "sg:postcode":"08032",
    "sg:province":"Barcelona",
    "sg:website":"www.comsa98.com",
    "wof:name":"Comsa 98 S.l.",
    "wof:placetype":"venue"
},
  "geometry": {"coordinates":[2.1699140072,41.4271125793],"type":"Point"}
}