{
  "type": "Feature",
  "properties": {
    "iso:country":"ES",
    "sg:address":"Calle de Mota Del Cuervo, 8",
    "sg:city":"Madrid",
    "sg:orig_category":"Peluqueros: De Se\u00d1oras",
    "sg:phone":"+34 913 88 77 85",
    "sg:postcode":"28043",
    "sg:province":"Madrid",
    "wof:name":"Orosa Siller Susana",
    "wof:placetype":"venue"
},
  "geometry": {"coordinates":[-3.6328039169,40.4645729065],"type":"Point"}
}