{
  "type": "Feature",
  "properties": {
    "addr:full":"Tudela, 1 Iru\u00f1a Navarra 31002",
    "addr:housenumber":"1",
    "addr:postcode":"31002",
    "addr:street":"Tudela",
    "iso:country":"ES",
    "sg:address":"Tudela, 1",
    "sg:city":"Iru\u00f1a",
    "sg:orig_category":"Ingenier\u00cda, Centros De Estudios (diversos)",
    "sg:phone":"+34 948 22 43 86",
    "sg:postcode":"31002",
    "sg:province":"Navarra",
    "wof:name":"San Martin Hernaiz Luis",
    "wof:placetype":"venue"
},
  "geometry": {"coordinates":[-1.6446349621,42.8138542175],"type":"Point"}
}