{
  "type": "Feature",
  "properties": {
    "addr:full":"Calle de General Mola, 14 Coru\u00d1a La Coru\u00f1a 15003",
    "addr:housenumber":"14",
    "addr:postcode":"15003",
    "addr:street":"Calle De General Mola;La Corun\u0303A",
    "iso:country":"ES",
    "sg:address":"Calle de General Mola, 14",
    "sg:city":"Coru\u00d1a",
    "sg:orig_category":"Ropa Para Ni\u00d1os (al Por Menor)",
    "sg:phone":"+34 981 21 44 29",
    "sg:postcode":"15003",
    "sg:province":"La Coru\u00f1a",
    "sg:website":"www.neckandneck.com",
    "wof:name":"Neck Child S.a.",
    "wof:placetype":"venue"
},
  "geometry": {"coordinates":[-8.4015264511,43.3700141907],"type":"Point"}
}