{
  "type": "Feature",
  "properties": {
    "iso:country":"ES",
    "sg:address":"Calle de Chile, 56",
    "sg:city":"Logro\u00f1o",
    "sg:orig_category":"Carnicer\u00cdas, Carnicer\u00cdas",
    "sg:phone":"+34 941 21 30 24",
    "sg:postcode":"26005",
    "sg:province":"La Rioja",
    "wof:name":"Hermanos Espiga Garcia S.l.",
    "wof:placetype":"venue"
},
  "geometry": {"coordinates":[-2.4575388432,42.4565010071],"type":"Point"}
}