{
  "type": "Feature",
  "properties": {
    "iso:country":"ES",
    "sg:address":"Carrer de Brusi, 39",
    "sg:city":"Barcelona",
    "sg:orig_category":"Arquitectos",
    "sg:phone":"+34 932 02 01 67",
    "sg:postcode":"08006",
    "sg:province":"Barcelona",
    "wof:name":"Quintana Creus Marius",
    "wof:placetype":"venue"
},
  "geometry": {"coordinates":[2.1455929279,41.4008865356],"type":"Point"}
}