{
  "type": "Feature",
  "properties": {
    "iso:country":"ES",
    "sg:address":"Av Llibertat, 24",
    "sg:city":"Elche",
    "sg:orig_category":"Librer\u00cdas",
    "sg:phone":"+34 966 67 41 12",
    "sg:postcode":"03206",
    "sg:province":"Alicante",
    "wof:name":"Librerias Seneca C.b.",
    "wof:placetype":"venue"
},
  "geometry": {"coordinates":[-0.7031189799,38.2708129883],"type":"Point"}
}