{
  "type": "Feature",
  "properties": {
    "addr:full":"Poligono Industrial Boch, 48 Poligono Industrial Boch Alicante 03330",
    "addr:housenumber":"48 poligono",
    "addr:postcode":"03330",
    "addr:street":"Industrial Boch;Industrial Boch Alicante",
    "iso:country":"ES",
    "sg:address":"Poligono Industrial Boch, 48",
    "sg:city":"Poligono Industrial Boch",
    "sg:orig_category":"Fabricaci\u00d3n De Material Y Sistemas De Se\u00d1alizaci\u00d3n De Carreteras, Urbanos Y De Obras",
    "sg:phone":"+34 966 68 14 48",
    "sg:postcode":"03330",
    "sg:province":"Alicante",
    "sg:website":"www.pielpas.com",
    "wof:name":"Alepiel S.l.",
    "wof:placetype":"venue"
},
  "geometry": {"coordinates":[-0.4810059965,38.3452033997],"type":"Point"}
}