{
  "type": "Feature",
  "properties": {
    "iso:country":"ES",
    "sg:address":"Esquiroz-ezkirotz Kalea, 20",
    "sg:city":"Iru\u00f1a",
    "sg:orig_category":"Arquitectos",
    "sg:phone":"+34 948 27 04 55",
    "sg:postcode":"31007",
    "sg:province":"Navarra",
    "wof:name":"Gortari Solbes Joaquin",
    "wof:placetype":"venue"
},
  "geometry": {"coordinates":[-1.6513769627,42.8059844971],"type":"Point"}
}