{
  "type": "Feature",
  "properties": {
    "addr:full":"Calle de Ali De Gomara, 3 Alcala Guadaira Sevilla 41500",
    "addr:housenumber":"3",
    "addr:postcode":"41500",
    "addr:street":"Calle De Ali De Gomara",
    "iso:country":"ES",
    "sg:address":"Calle de Ali De Gomara, 3",
    "sg:city":"Alcala Guadaira",
    "sg:orig_category":"Peluqueros: De Se\u00d1oras",
    "sg:phone":"+34 955 68 47 80",
    "sg:postcode":"41500",
    "sg:province":"Sevilla",
    "wof:name":"Kpelos S.c",
    "wof:placetype":"venue"
},
  "geometry": {"coordinates":[-5.8496761322,37.3372421265],"type":"Point"}
}