{
  "type": "Feature",
  "properties": {
    "addr:full":"Calle de San Francisco, 39 Bilbao Vizcaya 48003",
    "addr:housenumber":"39",
    "addr:postcode":"48003",
    "addr:street":"Calle De San Francisco",
    "iso:country":"ES",
    "sg:address":"Calle de San Francisco, 39",
    "sg:city":"Bilbao",
    "sg:orig_category":"Costureras",
    "sg:phone":"+34 944 15 70 82",
    "sg:postcode":"48003",
    "sg:province":"Vizcaya",
    "wof:name":"Menendez Ruiz Carlos",
    "wof:placetype":"venue"
},
  "geometry": {"coordinates":[-2.9311869144,43.2570304871],"type":"Point"}
}