{
  "type": "Feature",
  "properties": {
    "addr:full":"Plaz Sancho Vii El Fuerte, 15 Tudela Navarra 31500",
    "addr:housenumber":"15",
    "addr:postcode":"31500",
    "addr:street":"Plaz;El Fuerte",
    "iso:country":"ES",
    "sg:address":"Plaz Sancho Vii El Fuerte, 15",
    "sg:city":"Tudela",
    "sg:orig_category":"Doctores En Medicina",
    "sg:phone":"+34 948 82 76 26",
    "sg:postcode":"31500",
    "sg:province":"Navarra",
    "wof:name":"Rodes Martinez Francisco Javier",
    "wof:placetype":"venue"
},
  "geometry": {"coordinates":[-1.603448987,42.0613708496],"type":"Point"}
}