{
  "type": "Feature",
  "properties": {
    "addr:full":"Plaz Santa Maria, 11 Vilalba Lugo 27800",
    "addr:housenumber":"11",
    "addr:postcode":"27800",
    "addr:street":"Santa Maria",
    "iso:country":"ES",
    "sg:address":"Plaz Santa Maria, 11",
    "sg:city":"Vilalba",
    "sg:orig_category":"Art\u00cdculos De Regalo (al Por Menor)",
    "sg:phone":"+34 982 51 20 25",
    "sg:postcode":"27800",
    "sg:province":"Lugo",
    "wof:name":"Lamela Onega Blas",
    "wof:placetype":"venue"
},
  "geometry": {"coordinates":[-7.6795740128,43.2989387512],"type":"Point"}
}