{
  "type": "Feature",
  "properties": {
    "iso:country":"ES",
    "sg:address":"Av. Valencia, 21",
    "sg:city":"Gandia",
    "sg:orig_category":"Centros De Coordinaci\u00d3n",
    "sg:phone":"+34 962 86 03 92",
    "sg:postcode":"46700",
    "sg:province":"Valencia",
    "wof:name":"Tramitaciones La Safor S.l.",
    "wof:placetype":"venue"
},
  "geometry": {"coordinates":[-0.1815519929,38.971370697],"type":"Point"}
}