{
  "type": "Feature",
  "properties": {
    "addr:full":"Calle de Placido Pedreira Alvarez, 9 Laracha La Coru\u00f1a 15145",
    "addr:housenumber":"9",
    "addr:postcode":"15145",
    "addr:street":"Calle De Placido Pedreira Alvarez;La Corun\u0303A",
    "iso:country":"ES",
    "sg:address":"Calle de Placido Pedreira Alvarez, 9",
    "sg:city":"Laracha",
    "sg:orig_category":"Guarder\u00cdas",
    "sg:phone":"+34 981 64 26 38",
    "sg:postcode":"15145",
    "sg:province":"La Coru\u00f1a",
    "wof:name":"Maria Lorena Frade Loureiro Y Cia S.c.",
    "wof:placetype":"venue"
},
  "geometry": {"coordinates":[-8.5850505829,43.2474594116],"type":"Point"}
}