{
  "type": "Feature",
  "properties": {
    "iso:country":"ES",
    "sg:address":"Plaz Luis Verde, 15",
    "sg:city":"Luis Verde",
    "sg:orig_category":"Guarder\u00cdas",
    "sg:phone":"+34 928 70 50 78",
    "sg:postcode":"35217",
    "sg:province":"Las Palmas",
    "wof:name":"Pototito S.l.l.",
    "wof:placetype":"venue"
},
  "geometry": {"coordinates":[-15.4973392487,27.9911899567],"type":"Point"}
}