{
  "type": "Feature",
  "properties": {
    "iso:country":"ES",
    "sg:address":"Calle de Oriente, 7",
    "sg:city":"Villamediana Iregua",
    "sg:orig_category":"Pescader\u00cdas (al Por Menor)",
    "sg:phone":"+34 941 43 50 43",
    "sg:postcode":"26142",
    "sg:province":"La Rioja",
    "wof:name":"Perez Marin Pascual",
    "wof:placetype":"venue"
},
  "geometry": {"coordinates":[-2.4184989929,42.4255409241],"type":"Point"}
}