{
  "type": "Feature",
  "properties": {
    "addr:full":"Ctra Trescasas (de), 39 S. Cristobal Segovia Segovia 40197",
    "addr:housenumber":"39",
    "addr:postcode":"40197",
    "addr:street":"Ctra Trescasas De;S. Cristobal Segovia Segovia",
    "iso:country":"ES",
    "sg:address":"Ctra Trescasas (de), 39",
    "sg:city":"S. Cristobal Segovia",
    "sg:orig_category":"Ense\u00d1anza, Formaci\u00d3n Profesional: Aprendizaje",
    "sg:phone":"+34 921 40 61 74",
    "sg:postcode":"40197",
    "sg:province":"Segovia",
    "wof:name":"Ayuntamiento De San Cristobal De Segovia",
    "wof:placetype":"venue"
},
  "geometry": {"coordinates":[-4.0762438774,40.9524841309],"type":"Point"}
}