{
  "type": "Feature",
  "properties": {
    "iso:country":"ES",
    "sg:address":"Avda Alfares (de Los), S/n",
    "sg:city":"Cuenca",
    "sg:orig_category":"Asociaciones Y Clubs Deportivos",
    "sg:phone":"+34 969 23 60 80",
    "sg:postcode":"16002",
    "sg:province":"Cuenca",
    "wof:name":"Shoes Gestion S.a.",
    "wof:placetype":"venue"
},
  "geometry": {"coordinates":[-2.1471540928,40.0769500732],"type":"Point"}
}