{
  "type": "Feature",
  "properties": {
    "addr:full":"Av Mas Mates, 27 Mas Mates Girona 17480",
    "addr:housenumber":"27",
    "addr:postcode":"17480",
    "addr:street":"Av Mas Mates;Mates",
    "iso:country":"ES",
    "sg:address":"Av Mas Mates, 27",
    "sg:city":"Mas Mates",
    "sg:orig_category":"Empresas De Carpinter\u00cda De Madera",
    "sg:phone":"+34 972 25 54 35",
    "sg:postcode":"17480",
    "sg:province":"Girona",
    "wof:name":"Monedero Martinez Juan",
    "wof:placetype":"venue"
},
  "geometry": {"coordinates":[3.1663351059,42.2661399841],"type":"Point"}
}