{
  "type": "Feature",
  "properties": {
    "iso:country":"ES",
    "sg:address":"Calle de Navarra, 2",
    "sg:city":"Madrid",
    "sg:orig_category":"Ense\u00d1anza: Costura",
    "sg:phone":"+34 914 50 23 88",
    "sg:postcode":"28039",
    "sg:province":"Madrid",
    "sg:website":"www.atenum.com",
    "wof:name":"Velez Perea Hilaria",
    "wof:placetype":"venue"
},
  "geometry": {"coordinates":[-3.7031130791,40.4535942078],"type":"Point"}
}