{
  "type": "Feature",
  "properties": {
    "iso:country":"ES",
    "sg:address":"Estacion De Aforos, S/n",
    "sg:city":"Presa Gallego",
    "sg:orig_category":"Asociaciones Ecologistas",
    "sg:phone":"+34 974 38 20 93",
    "sg:postcode":"22807",
    "sg:province":"Huesca",
    "wof:name":"Comunidad General De Riegos Del Alto Aragon",
    "wof:placetype":"venue"
},
  "geometry": {"coordinates":[-0.7504209876,42.2266120911],"type":"Point"}
}