{
  "type": "Feature",
  "properties": {
    "addr:full":"Carrer de Major, 614 Centre Barcelona 08759",
    "addr:housenumber":"614",
    "addr:postcode":"08759",
    "addr:street":"Carrer De Major;Centre Barcelona",
    "iso:country":"ES",
    "sg:address":"Carrer de Major, 614",
    "sg:city":"Centre",
    "sg:orig_category":"Frutas, Legumbres Frescas Y Tempranas (al Por Menor)",
    "sg:phone":"+34 936 83 01 07",
    "sg:postcode":"08759",
    "sg:province":"Barcelona",
    "wof:name":"Lopez Valiente Andres",
    "wof:placetype":"venue"
},
  "geometry": {"coordinates":[1.9328349829,41.3889045715],"type":"Point"}
}