{
  "type": "Feature",
  "properties": {
    "addr:full":"Calle de Ramon Patuel, 9 Madrid Madrid 28017",
    "addr:housenumber":"9",
    "addr:postcode":"madrid;28017",
    "addr:street":"Calle De Ramon Patuel",
    "iso:country":"ES",
    "sg:address":"Calle de Ramon Patuel, 9",
    "sg:city":"Madrid",
    "sg:orig_category":"Inform\u00c1tica (estudios, Servicios, Asesor\u00cda, Formaci\u00d3n)",
    "sg:phone":"+34 913 56 53 48",
    "sg:postcode":"28017",
    "sg:province":"Madrid",
    "wof:name":"Formacion 2020 S.a.",
    "wof:placetype":"venue"
},
  "geometry": {"coordinates":[-3.6556360722,40.4290466309],"type":"Point"}
}