{
  "type": "Feature",
  "properties": {
    "iso:country":"ES",
    "sg:address":"Plaz San Jose, 2",
    "sg:city":"Puertollano",
    "sg:classifiers":[
        {
            "category":"Taxi",
            "type":"Transportation"
        }
    ],
    "sg:phone":"+34 926 42 51 10",
    "sg:postcode":"13500",
    "sg:province":"Ciudad Real",
    "wof:name":"Andarias Mozos Jose Luis",
    "wof:placetype":"venue"
},
  "geometry": {"coordinates":[-4.1095309258,38.6860046387],"type":"Point"}
}