{
  "type": "Feature",
  "properties": {
    "addr:full":"Calle de Juan De Borgo\u00d1a, 8 Alcala Henares Madrid 28805",
    "addr:housenumber":"8",
    "addr:postcode":"28805",
    "addr:street":"Calle De Juan De Borgon\u0303A",
    "iso:country":"ES",
    "sg:address":"Calle de Juan De Borgo\u00d1a, 8",
    "sg:city":"Alcala Henares",
    "sg:orig_category":"Florister\u00cdas",
    "sg:phone":"+34 918 89 22 33",
    "sg:postcode":"28805",
    "sg:province":"Madrid",
    "wof:name":"Rodriguez Roldan Antonio",
    "wof:placetype":"venue"
},
  "geometry": {"coordinates":[-3.3572340012,40.4892807007],"type":"Point"}
}