{
  "type": "Feature",
  "properties": {
    "iso:country":"ES",
    "sg:address":"Calle de Jorge Juan, 84",
    "sg:city":"Madrid",
    "sg:orig_category":"M\u00c9dicos: Estomatolog\u00cda",
    "sg:phone":"+34 915 76 45 18",
    "sg:postcode":"28009",
    "sg:province":"Madrid",
    "wof:name":"Caballin Garcia Armando",
    "wof:placetype":"venue"
},
  "geometry": {"coordinates":[-3.6750609875,40.4231948853],"type":"Point"}
}