{
  "type": "Feature",
  "properties": {
    "iso:country":"ES",
    "sg:address":"Carretera, Km. 0080,0",
    "sg:city":"Villanueva Vera",
    "sg:orig_category":"Comercio De Carburantes",
    "sg:phone":"+34 927 56 71 11",
    "sg:postcode":"10470",
    "sg:province":"C\u00e1ceres",
    "wof:name":"Gasolinera Aguas Frias S.l.",
    "wof:placetype":"venue"
},
  "geometry": {"coordinates":[-5.4627428055,40.1311225891],"type":"Point"}
}