{
  "type": "Feature",
  "properties": {
    "addr:full":"Calle de Joaquin Benlloch, 63 Valencia Valencia 46026",
    "addr:housenumber":"63",
    "addr:postcode":"46026",
    "addr:street":"Calle De Joaquin Benlloch",
    "iso:country":"ES",
    "sg:address":"Calle de Joaquin Benlloch, 63",
    "sg:city":"Valencia",
    "sg:orig_category":"Agencias Y Agentes Comerciales, Representantes",
    "sg:phone":"+34 963 95 60 47",
    "sg:postcode":"46026",
    "sg:province":"Valencia",
    "wof:name":"Ferrer Paredes Ramon",
    "wof:placetype":"venue"
},
  "geometry": {"coordinates":[-0.3740470111,39.4502029419],"type":"Point"}
}