{
  "type": "Feature",
  "properties": {
    "iso:country":"ES",
    "sg:address":"Calle de Mascaraque, Km. 0004,5",
    "sg:city":"Villaminaya",
    "sg:orig_category":"Escotaduras, Torneados",
    "sg:phone":"+34 925 34 52 11",
    "sg:postcode":"45440",
    "sg:province":"Toledo",
    "wof:name":"Lopez Dorado Andres",
    "wof:placetype":"venue"
},
  "geometry": {"coordinates":[-3.8700339794,39.7122154236],"type":"Point"}
}