{
  "type": "Feature",
  "properties": {
    "iso:country":"ES",
    "sg:address":"Arragueta Kalea, 2 B",
    "sg:city":"Eibar",
    "sg:orig_category":"Empresas De Demolici\u00d3n",
    "sg:phone":"+34 943 70 19 54",
    "sg:postcode":"20600",
    "sg:province":"Guip\u00f9zcoa",
    "wof:name":"Excavaciones Bergaretxe, S. L.",
    "wof:placetype":"venue"
},
  "geometry": {"coordinates":[-2.4884390831,43.1800117493],"type":"Point"}
}