{
  "type": "Feature",
  "properties": {
    "iso:country":"ES",
    "sg:address":"Calle de Ginzo De Limia, 24",
    "sg:city":"Madrid",
    "sg:orig_category":"Droguer\u00cdas (al Por Menor)",
    "sg:phone":"+34 913 78 18 81",
    "sg:postcode":"28029",
    "sg:province":"Madrid",
    "wof:name":"Gil Vega Pedro",
    "wof:placetype":"venue"
},
  "geometry": {"coordinates":[-3.7037210464,40.478805542],"type":"Point"}
}