{
  "type": "Feature",
  "properties": {
    "iso:country":"ES",
    "sg:address":"Calle de Gaudi, 48",
    "sg:city":"Estepona",
    "sg:orig_category":"Cerrajer\u00cda, Ferrallista",
    "sg:phone":"+34 952 79 09 07",
    "sg:postcode":"29680",
    "sg:province":"M\u00e1laga",
    "wof:name":"Armenteros Martin Ildefonso",
    "wof:placetype":"venue"
},
  "geometry": {"coordinates":[-5.167473793,36.4285430908],"type":"Point"}
}