{
  "type": "Feature",
  "properties": {
    "iso:country":"ES",
    "sg:address":"Calle de Marquesa Viuda De Aldama (de La), 40",
    "sg:city":"Alcobendas",
    "sg:orig_category":"Ropa Para Se\u00d1oras (al Por Menor)",
    "sg:phone":"+34 916 54 36 45",
    "sg:postcode":"28100",
    "sg:province":"Madrid",
    "wof:name":"Calle 8 S.l.",
    "wof:placetype":"venue"
},
  "geometry": {"coordinates":[-3.6307160854,40.5422058105],"type":"Point"}
}