{
  "type": "Feature",
  "properties": {
    "iso:country":"ES",
    "sg:address":"Calle de Vicente Medina, 4",
    "sg:city":"Archena",
    "sg:orig_category":"Maquinaria Para Industrias Diversas",
    "sg:phone":"+34 968 67 00 94",
    "sg:postcode":"30600",
    "sg:province":"Murcia",
    "sg:website":"www.maquinariatomasguillen.com",
    "wof:name":"Maquinaria Conservera Tomas Guillen S.l.",
    "wof:placetype":"venue"
},
  "geometry": {"coordinates":[-1.2982970476,38.1160736084],"type":"Point"}
}