{
  "type": "Feature",
  "properties": {
    "addr:full":"Luga Santa Marina, S/n Santa Marina Asturias 33193",
    "addr:housenumber":"s / n",
    "addr:postcode":"33193",
    "addr:street":"Santa Marina",
    "iso:country":"ES",
    "sg:address":"Luga Santa Marina, S/n",
    "sg:city":"Santa Marina",
    "sg:orig_category":"Explotaci\u00d3n De Canteras",
    "sg:phone":"+34 985 78 10 66",
    "sg:postcode":"33193",
    "sg:province":"Asturias",
    "wof:name":"Canteras Mecanicas Carcaba S. A.",
    "wof:placetype":"venue"
},
  "geometry": {"coordinates":[-5.894742012,43.3435211182],"type":"Point"}
}