{
  "type": "Feature",
  "properties": {
    "addr:full":"Avda Constitucion, 7 Don Benito Badajoz 06400",
    "addr:housenumber":"7",
    "addr:postcode":"06400",
    "addr:street":"Avda Constitucion",
    "iso:country":"ES",
    "sg:address":"Avda Constitucion, 7",
    "sg:city":"Don Benito",
    "sg:orig_category":"Zapatos (al Por Menor)",
    "sg:phone":"+34 924 80 18 65",
    "sg:postcode":"06400",
    "sg:province":"Badajoz",
    "wof:name":"Calzados Angelo S.l.",
    "wof:placetype":"venue"
},
  "geometry": {"coordinates":[-5.8627138138,38.9662666321],"type":"Point"}
}