{
  "type": "Feature",
  "properties": {
    "addr:full":"Calle de Montecarlo, 1 Mostoles Madrid 28936",
    "addr:housenumber":"1",
    "addr:postcode":"28936",
    "addr:street":"Calle De Montecarlo",
    "iso:country":"ES",
    "sg:address":"Calle de Montecarlo, 1",
    "sg:city":"Mostoles",
    "sg:orig_category":"Agencias Y Agentes Comerciales, Representantes",
    "sg:phone":"+34 916 45 30 41",
    "sg:postcode":"28936",
    "sg:province":"Madrid",
    "wof:name":"Vesga Cortina Ana Maria",
    "wof:placetype":"venue"
},
  "geometry": {"coordinates":[-3.8517420292,40.3247756958],"type":"Point"}
}