{
  "type": "Feature",
  "properties": {
    "iso:country":"ES",
    "sg:address":"Calle de Constancia, 28",
    "sg:city":"Madrid",
    "sg:orig_category":"Renovaci\u00d3n Inmobiliaria",
    "sg:phone":"+34 914 15 11 62",
    "sg:postcode":"28002",
    "sg:province":"Madrid",
    "wof:name":"Coam Rehabilitacion S.l.",
    "wof:placetype":"venue"
},
  "geometry": {"coordinates":[-3.6723773479,40.4424247742],"type":"Point"}
}