{
  "type": "Feature",
  "properties": {
    "iso:country":"ES",
    "sg:address":"Balteiro, 54",
    "sg:city":"Vilaboa",
    "sg:orig_category":"Arqueolog\u00cda Y Patrimonio Cultural",
    "sg:phone":"+34 986 70 85 75",
    "sg:postcode":"36140",
    "sg:province":"Pontevedra",
    "wof:name":"Farto Mesias Maria Carmen",
    "wof:placetype":"venue"
},
  "geometry": {"coordinates":[-8.6367464066,42.381439209],"type":"Point"}
}