{
  "type": "Feature",
  "properties": {
    "iso:country":"ES",
    "sg:address":"Calle de Miguel Servet, 23",
    "sg:city":"Castellon",
    "sg:orig_category":"Mec\u00c1nico Del Autom\u00d3vil",
    "sg:phone":"+34 964 22 56 21",
    "sg:postcode":"12003",
    "sg:province":"Castell\u00f3n",
    "wof:name":"Talleres Pepe Guillen C.b.",
    "wof:placetype":"venue"
},
  "geometry": {"coordinates":[-0.0322940014,39.9887771606],"type":"Point"}
}