{
  "type": "Feature",
  "properties": {
    "addr:full":"Calle de Pasadilla, 4 Ubrique C\u00e1diz 11600",
    "addr:housenumber":"4",
    "addr:postcode":"11600",
    "addr:street":"Calle De Pasadilla;Ca\u0301Diz",
    "iso:country":"ES",
    "sg:address":"Calle de Pasadilla, 4",
    "sg:city":"Ubrique",
    "sg:orig_category":"Marroquiner\u00cda (confecci\u00d3n)",
    "sg:phone":"+34 956 46 43 13",
    "sg:postcode":"11600",
    "sg:province":"C\u00e1diz",
    "wof:name":"Lamela Ramirez Antonio Abad",
    "wof:placetype":"venue"
},
  "geometry": {"coordinates":[-5.4457988739,36.6738586426],"type":"Point"}
}