{
  "type": "Feature",
  "properties": {
    "iso:country":"ES",
    "sg:address":"Carr Lluis Companys, 12",
    "sg:city":"Lleida",
    "sg:orig_category":"Farmacias",
    "sg:phone":"+34 973 26 83 91",
    "sg:postcode":"25003",
    "sg:province":"Lleida",
    "wof:name":"Salafranca Surribas Ana Maria",
    "wof:placetype":"venue"
},
  "geometry": {"coordinates":[0.6160899997,41.611831665],"type":"Point"}
}