{
  "type": "Feature",
  "properties": {
    "addr:full":"Av Catalunya, 12 Lloret Mar Girona 17310",
    "addr:housenumber":"12",
    "addr:postcode":"17310",
    "addr:street":"Av Catalunya",
    "iso:country":"ES",
    "sg:address":"Av Catalunya, 12",
    "sg:city":"Lloret Mar",
    "sg:orig_category":"Tintes (fabricaci\u00d3n, Al Por Mayor)",
    "sg:phone":"+34 972 36 74 37",
    "sg:postcode":"17310",
    "sg:province":"Girona",
    "wof:name":"Morillas Jimenezlopez Dolores",
    "wof:placetype":"venue"
},
  "geometry": {"coordinates":[2.8439021111,41.7047233582],"type":"Point"}
}