{
  "type": "Feature",
  "properties": {
    "addr:full":"Calle de Aguilas, 18 Sevilla Sevilla 41003",
    "addr:housenumber":"18",
    "addr:postcode":"41003",
    "addr:street":"Calle De Aguilas",
    "iso:country":"ES",
    "sg:address":"Calle de Aguilas, 18",
    "sg:city":"Sevilla",
    "sg:orig_category":"Cr\u00cda De Animales",
    "sg:phone":"+34 954 22 76 88",
    "sg:postcode":"41003",
    "sg:province":"Sevilla",
    "wof:name":"Marin Vera Filomena",
    "wof:placetype":"venue"
},
  "geometry": {"coordinates":[-5.9883384705,37.3899116516],"type":"Point"}
}