{
  "type": "Feature",
  "properties": {
    "iso:country":"ES",
    "sg:address":"A Tolda, 26",
    "sg:city":"Bemantes",
    "sg:orig_category":"Supermercados Y Hipermercados",
    "sg:phone":"+34 981 78 43 33",
    "sg:postcode":"15635",
    "sg:province":"A Coru\u00f1a",
    "wof:name":"Tienda Salvador S.l.",
    "wof:placetype":"venue"
},
  "geometry": {"coordinates":[-8.1701183319,43.3359489441],"type":"Point"}
}