{
  "type": "Feature",
  "properties": {
    "iso:country":"ES",
    "sg:address":"Calle de Reyes Catolicos, 57",
    "sg:city":"Alacant",
    "sg:orig_category":"Cervecer\u00cdas",
    "sg:phone":"+34 965 92 44 68",
    "sg:postcode":"03003",
    "sg:province":"Alicante",
    "wof:name":"Abengozar Mesa Alejandro",
    "wof:placetype":"venue"
},
  "geometry": {"coordinates":[-0.493168,38.341148],"type":"Point"}
}