{
  "type": "Feature",
  "properties": {
    "addr:full":"Avda Rioja (la), 19 Entrena La Rioja 26375",
    "addr:housenumber":"19",
    "addr:postcode":"26375",
    "addr:street":"Avda Rioja La;Rioja",
    "iso:country":"ES",
    "sg:address":"Avda Rioja (la), 19",
    "sg:city":"Entrena",
    "sg:orig_category":"Reposter\u00cdas",
    "sg:phone":"+34 941 44 61 38",
    "sg:postcode":"26375",
    "sg:province":"La Rioja",
    "wof:name":"Rodriguez Lopez Jose Luis",
    "wof:placetype":"venue"
},
  "geometry": {"coordinates":[-2.5289540291,42.3865432739],"type":"Point"}
}