{
  "type": "Feature",
  "properties": {
    "addr:full":"Carrer de Ferran Casablancas, 98 Sabadell Barcelona 08201",
    "addr:housenumber":"98",
    "addr:postcode":"08201",
    "addr:street":"Carrer De Ferran Casablancas",
    "iso:country":"ES",
    "sg:address":"Carrer de Ferran Casablancas, 98",
    "sg:city":"Sabadell",
    "sg:orig_category":"Confiter\u00cda, Galletas Y Pastas, Chocolater\u00cda (al Por Mayor)",
    "sg:phone":"+34 937 25 09 95",
    "sg:postcode":"08201",
    "sg:province":"Barcelona",
    "wof:name":"Rodriguez Carpio Joan Josep",
    "wof:placetype":"venue"
},
  "geometry": {"coordinates":[2.1066429615,41.5420417786],"type":"Point"}
}