{
  "type": "Feature",
  "properties": {
    "addr:full":"Mercado Santa Barbara, S/n Vitoria-gasteiz \u00c1lava 01004",
    "addr:housenumber":"/ n",
    "addr:postcode":"01004",
    "addr:street":"Barbara S",
    "iso:country":"ES",
    "sg:address":"Mercado Santa Barbara, S/n",
    "sg:city":"Vitoria-gasteiz",
    "sg:orig_category":"Frutas Y Legumbres Frescas (al Por Mayor)",
    "sg:phone":"+34 945 27 49 86",
    "sg:postcode":"01004",
    "sg:province":"\u00c1lava",
    "wof:name":"Hernandez Hernandez Laurentino",
    "wof:placetype":"venue"
},
  "geometry": {"coordinates":[-2.6674389839,42.8450584412],"type":"Point"}
}