{
  "type": "Feature",
  "properties": {
    "iso:country":"ES",
    "sg:address":"Carrer de Calvet, 28",
    "sg:city":"Barcelona",
    "sg:orig_category":"Inmobiliaria (agencias)",
    "sg:phone":"+34 934 19 18 49",
    "sg:postcode":"08021",
    "sg:province":"Barcelona",
    "sg:website":"www.remax.es",
    "wof:name":"Villa Juliana S.l.",
    "wof:placetype":"venue"
},
  "geometry": {"coordinates":[2.1443939209,41.394203186],"type":"Point"}
}