{
  "type": "Feature",
  "properties": {
    "iso:country":"ES",
    "sg:address":"Trva Arena (de La), 6",
    "sg:city":"Fuenlabrada",
    "sg:orig_category":"Instalaci\u00d3n, Reparaci\u00d3n De Calefacci\u00d3n Por Gas",
    "sg:phone":"+34 912 97 46 30",
    "sg:postcode":"28944",
    "sg:province":"Madrid",
    "wof:name":"Joymacon Instalaciones S.l.",
    "wof:placetype":"venue"
},
  "geometry": {"coordinates":[-3.795484066,40.2804260254],"type":"Point"}
}