{
  "type": "Feature",
  "properties": {
    "iso:country":"ES",
    "sg:address":"Plaz Santisimo Cristo De La Humildad, S/n",
    "sg:city":"Sanlucar Mayor",
    "sg:orig_category":"Comunidades Religiosas",
    "sg:phone":"+34 955 70 24 47",
    "sg:postcode":"41800",
    "sg:province":"Sevilla",
    "wof:name":"Escuela Taller Vera Cruz",
    "wof:placetype":"venue"
},
  "geometry": {"coordinates":[-6.2015638351,37.3865509033],"type":"Point"}
}