{
  "type": "Feature",
  "properties": {
    "addr:full":"Pl Salvador, 3 Elche Alicante 03203",
    "addr:housenumber":"3",
    "addr:postcode":"03203",
    "addr:street":"Pl Salvador",
    "iso:country":"ES",
    "sg:address":"Pl Salvador, 3",
    "sg:city":"Elche",
    "sg:orig_category":"Florister\u00cdas",
    "sg:phone":"+34 965 45 96 17",
    "sg:postcode":"03203",
    "sg:province":"Alicante",
    "wof:name":"Tripiana Irles Rosa Maria",
    "wof:placetype":"venue"
},
  "geometry": {"coordinates":[-0.697495997,38.2652397156],"type":"Point"}
}