{
  "type": "Feature",
  "properties": {
    "iso:country":"ES",
    "sg:address":"Calle de Porteria, 2",
    "sg:city":"Huecija",
    "sg:orig_category":"Agricultores, Agricultores",
    "sg:phone":"+34 950 64 03 61",
    "sg:postcode":"04409",
    "sg:province":"Almer\u00eda",
    "wof:name":"Agricola Ganadera Andarax S.c.a.",
    "wof:placetype":"venue"
},
  "geometry": {"coordinates":[-2.6085493565,36.9683074951],"type":"Point"}
}