{
  "type": "Feature",
  "properties": {
    "addr:full":"Calle de San Leopoldo, 23 Madrid Madrid 28029",
    "addr:housenumber":"23",
    "addr:postcode":"madrid;28029",
    "addr:street":"Calle De San Leopoldo",
    "iso:country":"ES",
    "sg:address":"Calle de San Leopoldo, 23",
    "sg:city":"Madrid",
    "sg:orig_category":"Sociedades, Compa\u00d1\u00cdas Aseguradoras",
    "sg:phone":"+34 913 15 10 16",
    "sg:postcode":"28029",
    "sg:province":"Madrid",
    "wof:name":"Plaza Y Salazar Asociados S.l.",
    "wof:placetype":"venue"
},
  "geometry": {"coordinates":[-3.69165802,40.4697151184],"type":"Point"}
}