{
  "type": "Feature",
  "properties": {
    "addr:full":"Huerta Tejada, S/n Aznalcazar Sevilla 41849",
    "addr:postcode":"41849",
    "addr:street":"Tejada S / N Aznalcazar",
    "iso:country":"ES",
    "sg:address":"Huerta Tejada, S/n",
    "sg:city":"Aznalcazar",
    "sg:orig_category":"Empresarios",
    "sg:phone":"+34 955 95 90 25",
    "sg:postcode":"41849",
    "sg:province":"Sevilla",
    "wof:name":"Fundacion Do\u00f1ana 21",
    "wof:placetype":"venue"
},
  "geometry": {"coordinates":[-6.2510838509,37.303768158],"type":"Point"}
}