{
  "type": "Feature",
  "properties": {
    "iso:country":"ES",
    "sg:address":"Pase Zorrilla, 82",
    "sg:city":"Valladolid",
    "sg:orig_category":"Centros Comerciales Y Grandes Tiendas",
    "sg:phone":"+34 983 22 74 47",
    "sg:postcode":"47006",
    "sg:province":"Valladolid",
    "wof:name":"Rey Mu\u00f1oz Manuela",
    "wof:placetype":"venue"
},
  "geometry": {"coordinates":[-4.7377490997,41.6411323547],"type":"Point"}
}