{
  "type": "Feature",
  "properties": {
    "addr:full":"G.v. Corts Catalanes, 312 Barcelona Barcelona 08004",
    "addr:housenumber":"312",
    "addr:postcode":"08004",
    "addr:street":"Catalanes",
    "iso:country":"ES",
    "sg:address":"G.v. Corts Catalanes, 312",
    "sg:city":"Barcelona",
    "sg:orig_category":"Ingenier\u00cda, Centros De Estudios (diversos)",
    "sg:phone":"+34 934 24 00 39",
    "sg:postcode":"08004",
    "sg:province":"Barcelona",
    "wof:name":"Sisto Rovira Joaquin",
    "wof:placetype":"venue"
},
  "geometry": {"coordinates":[2.1467280388,41.3728408813],"type":"Point"}
}