{
  "type": "Feature",
  "properties": {
    "addr:full":"Carrer de Elisabets, 9 Barcelona Barcelona 08001",
    "addr:housenumber":"9",
    "addr:postcode":"08001",
    "addr:street":"Carrer De Elisabets",
    "iso:country":"ES",
    "sg:address":"Carrer de Elisabets, 9",
    "sg:city":"Barcelona",
    "sg:orig_category":"Inmobiliaria (agencias)",
    "sg:phone":"+34 933 42 91 64",
    "sg:postcode":"08001",
    "sg:province":"Barcelona",
    "wof:name":"Elisabets 2005 Gestion De Arrendamientos S.l.",
    "wof:placetype":"venue"
},
  "geometry": {"coordinates":[2.1686589718,41.3833045959],"type":"Point"}
}