{
  "type": "Feature",
  "properties": {
    "iso:country":"ES",
    "sg:address":"Ctra Estacion, 28",
    "sg:city":"Montijo",
    "sg:orig_category":"Fabricaci\u00d3n Y Comercio De M\u00c1quinas",
    "sg:phone":"+34 924 45 55 77",
    "sg:postcode":"06480",
    "sg:province":"Badajoz",
    "wof:name":"Talleres Mobeca S.l.",
    "wof:placetype":"venue"
},
  "geometry": {"coordinates":[-6.604019165,38.9118118286],"type":"Point"}
}