{
  "type": "Feature",
  "properties": {
    "addr:full":"Sondika Alde, 12 Zangroiz Vizcaya 48150",
    "addr:housenumber":"12",
    "addr:postcode":"48150",
    "addr:street":"Alde",
    "iso:country":"ES",
    "sg:address":"Sondika Alde, 12",
    "sg:city":"Zangroiz",
    "sg:orig_category":"Venta, Instalaci\u00d3n, Reparaci\u00d3n De Antenas Para Televisi\u00d3n",
    "sg:phone":"+34 944 67 69 38",
    "sg:postcode":"48150",
    "sg:province":"Vizcaya",
    "sg:website":"www.sondikatel.es",
    "wof:name":"Sondikatel S.l.",
    "wof:placetype":"venue"
},
  "geometry": {"coordinates":[-2.9244790077,43.2990455627],"type":"Point"}
}