{
  "type": "Feature",
  "properties": {
    "addr:full":"Avda Luxemburgo, S/n Torreciega Murcia 30392",
    "addr:housenumber":"s / n",
    "addr:postcode":"30392",
    "addr:street":"Avda Luxemburgo",
    "iso:country":"ES",
    "sg:address":"Avda Luxemburgo, S/n",
    "sg:city":"Torreciega",
    "sg:orig_category":"Negocio De Materiales De Construcci\u00d3n",
    "sg:phone":"+34 968 50 14 06",
    "sg:postcode":"30392",
    "sg:province":"Murcia",
    "sg:website":"www.e-palsa.com",
    "wof:name":"Palsa Materiales De Construcciones S.l.",
    "wof:placetype":"venue"
},
  "geometry": {"coordinates":[-0.9544889927,37.6084251404],"type":"Point"}
}