{
  "type": "Feature",
  "properties": {
    "addr:full":"Castillejos, 8 Palma Rio C\u00f3rdoba 14700",
    "addr:housenumber":"8",
    "addr:postcode":"14700",
    "addr:street":"Castillejos;Rio Co\u0301Rdoba",
    "iso:country":"ES",
    "sg:address":"Castillejos, 8",
    "sg:city":"Palma Rio",
    "sg:orig_category":"Cajas De Ahorro",
    "sg:phone":"+34 957 71 07 88",
    "sg:postcode":"14700",
    "sg:province":"C\u00f3rdoba",
    "sg:website":"www.cajasur.es",
    "wof:name":"Caja De Ahorros Y Monte De Piedad De Cordoba",
    "wof:placetype":"venue"
},
  "geometry": {"coordinates":[-5.2824811935,37.6975822449],"type":"Point"}
}