{
  "type": "Feature",
  "properties": {
    "iso:country":"ES",
    "sg:address":"Calle de Bolivia, S/n",
    "sg:city":"Madrid",
    "sg:orig_category":"Distribuci\u00d3n De Petr\u00d3leo Y Derivados",
    "sg:phone":"+34 914 57 06 81",
    "sg:postcode":"28016",
    "sg:province":"Madrid",
    "wof:name":"Remey S.a.",
    "wof:placetype":"venue"
},
  "geometry": {"coordinates":[-3.6777732372,40.4586486816],"type":"Point"}
}