{
  "type": "Feature",
  "properties": {
    "iso:country":"ES",
    "sg:address":"Avda Fisterra, S/n",
    "sg:city":"Arteixo",
    "sg:orig_category":"Serigraf\u00cda (material Y Suministros)",
    "sg:phone":"+34 981 64 04 38",
    "sg:postcode":"15142",
    "sg:province":"La Coru\u00f1a",
    "wof:name":"Alvari\u00f1o Primo Alvaro",
    "wof:placetype":"venue"
},
  "geometry": {"coordinates":[-8.5092773438,43.3054656982],"type":"Point"}
}