{
  "type": "Feature",
  "properties": {
    "iso:country":"ES",
    "sg:address":"Rua Cruxa, 4",
    "sg:city":"Milladoiro",
    "sg:orig_category":"Artes Gr\u00c1ficas, Artes Pl\u00c1sticas (curso)",
    "sg:phone":"+34 981 53 41 42",
    "sg:postcode":"15895",
    "sg:province":"La Coru\u00f1a",
    "wof:name":"Asociacion De Artes Graficas E Impresion De Galicia",
    "wof:placetype":"venue"
},
  "geometry": {"coordinates":[-8.5781955719,42.8454208374],"type":"Point"}
}