{
  "type": "Feature",
  "properties": {
    "addr:full":"Calle de Jesus, 10 Rambla C\u00f3rdoba 14540",
    "addr:housenumber":"10",
    "addr:postcode":"14540",
    "addr:street":"Calle De Jesus;Co\u0301Rdoba",
    "iso:country":"ES",
    "sg:address":"Calle de Jesus, 10",
    "sg:city":"Rambla",
    "sg:orig_category":"Hielo Artificial (fabricaci\u00d3n, Distribuci\u00d3n)",
    "sg:phone":"+34 957 68 41 31",
    "sg:postcode":"14540",
    "sg:province":"C\u00f3rdoba",
    "wof:name":"Colomina Candela Luis Enrique",
    "wof:placetype":"venue"
},
  "geometry": {"coordinates":[-4.7405738831,37.6078186035],"type":"Point"}
}