{
  "type": "Feature",
  "properties": {
    "addr:full":"Calle de Jose Del Hierro, 61 Madrid Madrid 28027",
    "addr:housenumber":"61",
    "addr:postcode":"madrid;28027",
    "addr:street":"Calle De Jose Del Hierro",
    "iso:country":"ES",
    "sg:address":"Calle de Jose Del Hierro, 61",
    "sg:city":"Madrid",
    "sg:orig_category":"Lencer\u00cda Femenina, Corseter\u00cda, Trajes De Ba\u00d1o (al Por Menor)",
    "sg:phone":"+34 913 67 47 47",
    "sg:postcode":"28027",
    "sg:province":"Madrid",
    "wof:name":"Vergara Ariza Dolores",
    "wof:placetype":"venue"
},
  "geometry": {"coordinates":[-3.6422851086,40.4410095215],"type":"Point"}
}