{
  "type": "Feature",
  "properties": {
    "addr:full":"Rond Corpus, 15 Salamanca Salamanca 37002",
    "addr:housenumber":"15",
    "addr:postcode":"37002",
    "addr:street":"Corpus",
    "iso:country":"ES",
    "sg:address":"Rond Corpus, 15",
    "sg:city":"Salamanca",
    "sg:orig_category":"Aparcamientos (infraestructuras, Accesorios)",
    "sg:phone":"+34 923 21 94 84",
    "sg:postcode":"37002",
    "sg:province":"Salamanca",
    "wof:name":"Martin Gomez Domingo",
    "wof:placetype":"venue"
},
  "geometry": {"coordinates":[-5.666601181,40.9684524536],"type":"Point"}
}