{
  "type": "Feature",
  "properties": {
    "addr:full":"Calle de Asturias, 6 Onda Castell\u00f3n 12200",
    "addr:housenumber":"6",
    "addr:postcode":"12200",
    "addr:street":"Calle De Asturias;Castello\u0301N",
    "iso:country":"ES",
    "sg:address":"Calle de Asturias, 6",
    "sg:city":"Onda",
    "sg:orig_category":"Servicio De Salud",
    "sg:phone":"+34 964 60 48 21",
    "sg:postcode":"12200",
    "sg:province":"Castell\u00f3n",
    "wof:name":"Mon De Gala S.a.",
    "wof:placetype":"venue"
},
  "geometry": {"coordinates":[-0.239428699,39.9645805359],"type":"Point"}
}