{
  "type": "Feature",
  "properties": {
    "addr:full":"Carrer de Rossello, 28 Barcelona Barcelona 08029",
    "addr:housenumber":"28",
    "addr:postcode":"08029",
    "addr:street":"Carrer De Rossello",
    "iso:country":"ES",
    "sg:address":"Carrer de Rossello, 28",
    "sg:city":"Barcelona",
    "sg:orig_category":"Cajas De Ahorro",
    "sg:phone":"+34 934 39 94 26",
    "sg:postcode":"08029",
    "sg:province":"Barcelona",
    "wof:name":"Bt Espa\u00d1a Compa\u00d1ia De Servicios Globales De Telecomunicaciones S.a.u.",
    "wof:placetype":"venue"
},
  "geometry": {"coordinates":[2.146130085,41.3847885132],"type":"Point"}
}