{
  "type": "Feature",
  "properties": {
    "iso:country":"ES",
    "sg:address":"Rua Marques De Valladares, 21",
    "sg:city":"Vigo",
    "sg:orig_category":"Agencias Y Agentes Comerciales, Representantes",
    "sg:phone":"+34 986 22 34 78",
    "sg:postcode":"36201",
    "sg:province":"Pontevedra",
    "wof:name":"Hernandez Costas Luis",
    "wof:placetype":"venue"
},
  "geometry": {"coordinates":[-8.7227735519,42.2383918762],"type":"Point"}
}