{
  "type": "Feature",
  "properties": {
    "iso:country":"ES",
    "sg:address":"Crta Viver-pto Burriana, 13",
    "sg:city":"Vila-real",
    "sg:orig_category":"Teatros Y Salas De Espect\u00c1culos",
    "sg:phone":"+34 964 53 57 37",
    "sg:postcode":"12540",
    "sg:province":"Castell\u00f3n",
    "sg:website":"www.visitans.com",
    "wof:name":"Els Visitants Compa\u00f1ia De Teatre S.l.",
    "wof:placetype":"venue"
},
  "geometry": {"coordinates":[-0.0952899978,39.9453010559],"type":"Point"}
}