{
  "type": "Feature",
  "properties": {
    "addr:full":"Nogueira, 10 Nogueira Ourense 32229",
    "addr:housenumber":"10",
    "addr:postcode":"32229",
    "addr:street":"Nogueira",
    "iso:country":"ES",
    "sg:address":"Nogueira, 10",
    "sg:city":"Nogueira",
    "sg:orig_category":"Ense\u00d1anza, Formaci\u00d3n Profesional: Aprendizaje",
    "sg:phone":"+34 988 49 45 11",
    "sg:postcode":"32229",
    "sg:province":"Ourense",
    "wof:name":"Ayuntamiento De Padrenda",
    "wof:placetype":"venue"
},
  "geometry": {"coordinates":[-7.7276921272,42.4118690491],"type":"Point"}
}