{
  "type": "Feature",
  "properties": {
    "addr:full":"Calle de Urbano Pineda, S/n Coin M\u00e1laga 29100",
    "addr:housenumber":"s / n",
    "addr:postcode":"29100",
    "addr:street":"Calle De Urbano Pineda;Ma\u0301Laga",
    "iso:country":"ES",
    "sg:address":"Calle de Urbano Pineda, S/n",
    "sg:city":"Coin",
    "sg:orig_category":"Supermercados Y Hipermercados",
    "sg:phone":"+34 952 45 51 94",
    "sg:postcode":"29100",
    "sg:province":"M\u00e1laga",
    "wof:name":"Dinosol Supermercados S.l.",
    "wof:placetype":"venue"
},
  "geometry": {"coordinates":[-4.7535839081,36.6610565186],"type":"Point"}
}