{
  "type": "Feature",
  "properties": {
    "addr:full":"Avda Escultora Miss Whitney, S/n Huelva Huelva 21003",
    "addr:housenumber":"s / n",
    "addr:postcode":"21003",
    "addr:street":"Avda Escultora Miss Whitney",
    "iso:country":"ES",
    "sg:address":"Avda Escultora Miss Whitney, S/n",
    "sg:city":"Huelva",
    "sg:orig_category":"Centros De Educaci\u00d3n Especial",
    "sg:phone":"+34 959 54 36 13",
    "sg:postcode":"21003",
    "sg:province":"Huelva",
    "wof:name":"Junta De Andalucia",
    "wof:placetype":"venue"
},
  "geometry": {"coordinates":[-6.9456238747,37.2540245056],"type":"Point"}
}