{
  "type": "Feature",
  "properties": {
    "addr:full":"Carr Bons Aires, 33 Sineu Islas Baleares 07510",
    "addr:housenumber":"33",
    "addr:postcode":"07510",
    "addr:street":"Carr Bons Aires",
    "iso:country":"ES",
    "sg:address":"Carr Bons Aires, 33",
    "sg:city":"Sineu",
    "sg:orig_category":"Empresas De Carpinter\u00cda De Madera",
    "sg:phone":"+34 971 52 01 23",
    "sg:postcode":"07510",
    "sg:province":"Islas Baleares",
    "wof:name":"Mas Florit Miguel",
    "wof:placetype":"venue"
},
  "geometry": {"coordinates":[3.0107710361,39.6455879211],"type":"Point"}
}