{
  "type": "Feature",
  "properties": {
    "addr:full":"Avda Vicente Aleixandre, 33 Segovia Segovia 40006",
    "addr:housenumber":"33",
    "addr:postcode":"40006",
    "addr:street":"Avda Vicente Aleixandre",
    "iso:country":"ES",
    "sg:address":"Avda Vicente Aleixandre, 33",
    "sg:city":"Segovia",
    "sg:orig_category":"Iglesia Cat\u00d3lica",
    "sg:phone":"+34 921 43 24 78",
    "sg:postcode":"40006",
    "sg:province":"Segovia",
    "wof:name":"Obispado Segovia",
    "wof:placetype":"venue"
},
  "geometry": {"coordinates":[-4.1017107964,40.9314041138],"type":"Point"}
}