{
  "type": "Feature",
  "properties": {
    "iso:country":"ES",
    "sg:address":"Calle de Ronda (la), 19",
    "sg:city":"Castro Urdiales",
    "sg:orig_category":"Negocio De Materiales De Construcci\u00d3n",
    "sg:phone":"+34 942 86 35 34",
    "sg:postcode":"39700",
    "sg:province":"Cantabria",
    "wof:name":"Arenal Agudo Miguel Vicente",
    "wof:placetype":"venue"
},
  "geometry": {"coordinates":[-3.2197394371,43.3807830811],"type":"Point"}
}