{
  "type": "Feature",
  "properties": {
    "iso:country":"ES",
    "sg:address":"Ctra Aguilar, S/n",
    "sg:city":"Puente-genil",
    "sg:orig_category":"Poller\u00cda Y Caza (al Por Menor)",
    "sg:phone":"+34 957 60 33 76",
    "sg:postcode":"14500",
    "sg:province":"C\u00f3rdoba",
    "wof:name":"Rosal Alferez Jose Del",
    "wof:placetype":"venue"
},
  "geometry": {"coordinates":[-4.7560892105,37.4059257507],"type":"Point"}
}