{
  "type": "Feature",
  "properties": {
    "iso:country":"ES",
    "sg:address":"Calle de General Pardi\u00d1as, 50",
    "sg:city":"Madrid",
    "sg:classifiers":[
        {
            "category":"Arts & Performance",
            "subcategory":"Art Gallery",
            "type":"Entertainment"
        }
    ],
    "sg:phone":"+34 914 02 80 90",
    "sg:postcode":"28001",
    "sg:province":"Madrid",
    "sg:tags":[
        "arte",
        "de",
        "galer\u00cdas"
    ],
    "sg:website":"www.galeriamaymore.com",
    "wof:name":"Arte E Ilusion S.l.",
    "wof:placetype":"venue"
},
  "geometry": {"coordinates":[-3.6783361435,40.4284248352],"type":"Point"}
}