{
  "type": "Feature",
  "properties": {
    "iso:country":"ES",
    "sg:address":"Mendeurren Etorbidea, 4",
    "sg:city":"Beasain",
    "sg:orig_category":"Comercio De Piezas De Recambio Y De Accesorios De Veh\u00cdculos, Veh\u00cdculos Industriales",
    "sg:phone":"+34 943 16 20 95",
    "sg:postcode":"20200",
    "sg:province":"Guip\u00f9zcoa",
    "wof:name":"Auto Recambios Goyerri S.l.",
    "wof:placetype":"venue"
},
  "geometry": {"coordinates":[-2.2056849003,43.0470619202],"type":"Point"}
}