{
  "type": "Feature",
  "properties": {
    "iso:country":"ES",
    "sg:address":"Carrer de Torrent De La Bomba, 36",
    "sg:city":"S. Cugat Valles",
    "sg:orig_category":"Institutos De Belleza",
    "sg:phone":"+34 936 74 53 50",
    "sg:postcode":"08172",
    "sg:province":"Barcelona",
    "sg:website":"www.solmania.com",
    "wof:name":"Vadesol Cugat 2000 S.l.",
    "wof:placetype":"venue"
},
  "geometry": {"coordinates":[2.0803821087,41.4712219238],"type":"Point"}
}