{
  "type": "Feature",
  "properties": {
    "addr:full":"Calle de Maria Auxiliadora, 1 Marbella M\u00e1laga 29600",
    "addr:housenumber":"1",
    "addr:postcode":"29600",
    "addr:street":"Calle De Maria Auxiliadora;Ma\u0301Laga",
    "iso:country":"ES",
    "sg:address":"Calle de Maria Auxiliadora, 1",
    "sg:city":"Marbella",
    "sg:orig_category":"Comercio De Mobiliario De Oficina",
    "sg:phone":"+34 952 92 46 74",
    "sg:postcode":"29600",
    "sg:province":"M\u00e1laga",
    "sg:website":"www.divatto.es",
    "wof:name":"Grupo Divatto Prestige S.l.",
    "wof:placetype":"venue"
},
  "geometry": {"coordinates":[-4.8874602318,36.5086631775],"type":"Point"}
}