{
  "type": "Feature",
  "properties": {
    "addr:full":"Carr Metge Miquel Rotger, Del, 2 Consell Islas Baleares 07330",
    "addr:housenumber":"2",
    "addr:postcode":"07330",
    "addr:street":"Carr Metge Miquel Rotger Del",
    "iso:country":"ES",
    "sg:address":"Carr Metge Miquel Rotger, Del, 2",
    "sg:city":"Consell",
    "sg:orig_category":"Negocio De Materiales De Construcci\u00d3n",
    "sg:phone":"+34 971 62 21 61",
    "sg:postcode":"07330",
    "sg:province":"Islas Baleares",
    "wof:name":"Pol Amengual S.l.",
    "wof:placetype":"venue"
},
  "geometry": {"coordinates":[2.8149449825,39.6679840088],"type":"Point"}
}