{
  "type": "Feature",
  "properties": {
    "addr:full":"Carr Pujades, 32 Figueres Girona 17600",
    "addr:housenumber":"32",
    "addr:postcode":"17600",
    "addr:street":"Carr Pujades",
    "iso:country":"ES",
    "sg:address":"Carr Pujades, 32",
    "sg:city":"Figueres",
    "sg:orig_category":"Fabricaci\u00d3n, Importaci\u00d3n De L\u00c1mparas Y Bombillas",
    "sg:phone":"+34 972 50 43 03",
    "sg:postcode":"17600",
    "sg:province":"Girona",
    "wof:name":"Caba\u00f1o Busquets Isidro",
    "wof:placetype":"venue"
},
  "geometry": {"coordinates":[2.963570118,42.2606010437],"type":"Point"}
}