{
  "type": "Feature",
  "properties": {
    "iso:country":"ES",
    "sg:address":"Calle de Riego, 12",
    "sg:city":"Arrecife",
    "sg:orig_category":"Traductores",
    "sg:phone":"+34 928 81 17 57",
    "sg:postcode":"35500",
    "sg:province":"Las Palmas",
    "wof:name":"Negrin Ramos Olga Maria",
    "wof:placetype":"venue"
},
  "geometry": {"coordinates":[-13.5509748459,28.9585895538],"type":"Point"}
}