{
  "type": "Feature",
  "properties": {
    "addr:full":"Ctra. Palma (p I Lirio), S/n Bollullos Par Condado Huelva 21710",
    "addr:housenumber":"/ n",
    "addr:postcode":"21710",
    "addr:street":"Ctra. Palma P;Lirio S",
    "iso:country":"ES",
    "sg:address":"Ctra. Palma (p I Lirio), S/n",
    "sg:city":"Bollullos Par Condado",
    "sg:orig_category":"Fabricaci\u00d3n De Muebles",
    "sg:phone":"+34 959 41 23 92",
    "sg:postcode":"21710",
    "sg:province":"Huelva",
    "wof:name":"Fabrica De Muebles Santos S.l.",
    "wof:placetype":"venue"
},
  "geometry": {"coordinates":[-6.5326490402,37.3390083313],"type":"Point"}
}