{
  "type": "Feature",
  "properties": {
    "iso:country":"ES",
    "sg:address":"Avda Santander, 45",
    "sg:city":"Valladolid",
    "sg:orig_category":"Restaurantes",
    "sg:phone":"+34 983 26 86 76",
    "sg:postcode":"47010",
    "sg:province":"Valladolid",
    "wof:name":"Restaurante Vegetariano El Huerto De Melibea Soc.coop.",
    "wof:placetype":"venue"
},
  "geometry": {"coordinates":[-4.710422039,41.6666641235],"type":"Point"}
}