{
  "type": "Feature",
  "properties": {
    "addr:full":"Calle de Subestacion, 10 Villarrubia Santiago Toledo 45360",
    "addr:housenumber":"10",
    "addr:postcode":"45360",
    "addr:street":"Calle De Subestacion",
    "iso:country":"ES",
    "sg:address":"Calle de Subestacion, 10",
    "sg:city":"Villarrubia Santiago",
    "sg:orig_category":"Rectificaci\u00d3n, Mecanizado, Fresado",
    "sg:phone":"+34 925 14 91 96",
    "sg:postcode":"45360",
    "sg:province":"Toledo",
    "wof:name":"Talleres Arana Luengo S.l.",
    "wof:placetype":"venue"
},
  "geometry": {"coordinates":[-3.3712830544,39.9833946228],"type":"Point"}
}