{
  "type": "Feature",
  "properties": {
    "iso:country":"ES",
    "sg:address":"Calle de Avenida De Navarra, 121",
    "sg:city":"Lodosa",
    "sg:orig_category":"Confecci\u00d3n (fabricaci\u00d3n, Al Por Mayor)",
    "sg:phone":"+34 948 69 37 35",
    "sg:postcode":"31580",
    "sg:province":"Navarra",
    "wof:name":"Maria Guadalupe Y Ramon Javier Martinez Leria S.c.",
    "wof:placetype":"venue"
},
  "geometry": {"coordinates":[-2.0849239826,42.4255332947],"type":"Point"}
}