{
  "type": "Feature",
  "properties": {
    "iso:country":"ES",
    "sg:address":"Carr Barranco, 4",
    "sg:city":"Oliva",
    "sg:orig_category":"Electrodom\u00c9sticos (fabricaci\u00d3n, Al Por Mayor)",
    "sg:phone":"+34 962 85 08 26",
    "sg:postcode":"46780",
    "sg:province":"Valencia",
    "wof:name":"Sanchis Calatayud Vicente",
    "wof:placetype":"venue"
},
  "geometry": {"coordinates":[-0.1230060011,38.9210968018],"type":"Point"}
}