{
  "type": "Feature",
  "properties": {
    "addr:full":"Plaz Cabildo (el), S/n Sevilla Sevilla 41001",
    "addr:housenumber":"/ n",
    "addr:postcode":"41001",
    "addr:street":"El S",
    "iso:country":"ES",
    "sg:address":"Plaz Cabildo (el), S/n",
    "sg:city":"Sevilla",
    "sg:orig_category":"Compraventa De Antig\u00dcedades",
    "sg:phone":"+34 954 21 87 71",
    "sg:postcode":"41001",
    "sg:province":"Sevilla",
    "wof:name":"Ortega Mellado Dolores",
    "wof:placetype":"venue"
},
  "geometry": {"coordinates":[-6.0018129349,37.3876953125],"type":"Point"}
}