{
  "type": "Feature",
  "properties": {
    "addr:full":"Carrer de Foixarda (de La), 12 Cala Tamarit Tarragona 43008",
    "addr:housenumber":"12",
    "addr:postcode":"43008",
    "addr:street":"Carrer De Foixarda De La",
    "iso:country":"ES",
    "sg:address":"Carrer de Foixarda (de La), 12",
    "sg:city":"Cala Tamarit",
    "sg:orig_category":"Centros Empresariales",
    "sg:phone":"+34 977 65 80 05",
    "sg:postcode":"43008",
    "sg:province":"Tarragona",
    "wof:name":"M.pilartorres Consulting Services",
    "wof:placetype":"venue"
},
  "geometry": {"coordinates":[1.3544900417,41.128780365],"type":"Point"}
}