{
  "type": "Feature",
  "properties": {
    "iso:country":"ES",
    "sg:address":"Calle de General Pardi\u00d1as, 103",
    "sg:city":"Madrid",
    "sg:orig_category":"Audiovisuales (producci\u00d3n, Edici\u00d3n, Realizaci\u00d3n)",
    "sg:phone":"+34 914 11 14 06",
    "sg:postcode":"28006",
    "sg:province":"Madrid",
    "sg:website":"www.lanave.tv",
    "wof:name":"La Nave Estudios S.l.",
    "wof:placetype":"venue"
},
  "geometry": {"coordinates":[-3.677693367,40.4369850159],"type":"Point"}
}