{
  "type": "Feature",
  "properties": {
    "iso:country":"ES",
    "sg:address":"Rond Outeiro, 130",
    "sg:city":"Coru\u00d1a",
    "sg:orig_category":"Peluquer\u00cdas, Peluquer\u00cda Mixta",
    "sg:phone":"+34 981 24 87 54",
    "sg:postcode":"15007",
    "sg:province":"La Coru\u00f1a",
    "wof:name":"Mourelle Castro Ines",
    "wof:placetype":"venue"
},
  "geometry": {"coordinates":[-8.7951183319,42.9959411621],"type":"Point"}
}