{
  "type": "Feature",
  "properties": {
    "addr:full":"Plaz Santa Maria, 3 Almazan Soria 42200",
    "addr:housenumber":"3",
    "addr:postcode":"42200",
    "addr:street":"Santa Maria",
    "iso:country":"ES",
    "sg:address":"Plaz Santa Maria, 3",
    "sg:city":"Almazan",
    "sg:orig_category":"Perfumer\u00cda (al Por Menor)",
    "sg:phone":"+34 975 30 20 61",
    "sg:postcode":"42200",
    "sg:province":"Soria",
    "wof:name":"Garcia Frias Consuelo",
    "wof:placetype":"venue"
},
  "geometry": {"coordinates":[-2.5325520039,41.4865989685],"type":"Point"}
}