{
  "type": "Feature",
  "properties": {
    "addr:full":"Ctra Rosario (del), 4 Santa Cruz De Tenerife Santa Cruz De Tenerife 38009",
    "addr:housenumber":"4",
    "addr:postcode":"38009",
    "addr:street":"Ctra Rosario Del",
    "iso:country":"ES",
    "sg:address":"Ctra Rosario (del), 4",
    "sg:city":"Santa Cruz De Tenerife",
    "sg:orig_category":"Ense\u00d1anza, Formaci\u00d3n Profesional: Aprendizaje",
    "sg:phone":"+34 922 64 42 11",
    "sg:postcode":"38009",
    "sg:province":"Santa Cruz De Tenerife",
    "wof:name":"Gobierno De Canarias",
    "wof:placetype":"venue"
},
  "geometry": {"coordinates":[-16.2734508514,28.4568061829],"type":"Point"}
}