{
  "type": "Feature",
  "properties": {
    "iso:country":"ES",
    "sg:address":"Avda Faro (del), 12",
    "sg:city":"Chipiona",
    "sg:orig_category":"Hoteles",
    "sg:phone":"+34 956 37 10 54",
    "sg:postcode":"11550",
    "sg:province":"C\u00e1diz",
    "wof:name":"Hotel Brasilia De Chipiona S.a.",
    "wof:placetype":"venue"
},
  "geometry": {"coordinates":[-6.4394497871,36.7384529114],"type":"Point"}
}