{
  "type": "Feature",
  "properties": {
    "addr:full":"Carrer de Palaudaries, 22 Barcelona Barcelona 08004",
    "addr:housenumber":"22",
    "addr:postcode":"08004",
    "addr:street":"Carrer De Palaudaries",
    "iso:country":"ES",
    "sg:address":"Carrer de Palaudaries, 22",
    "sg:city":"Barcelona",
    "sg:orig_category":"Reposter\u00cdas",
    "sg:phone":"+34 934 42 38 79",
    "sg:postcode":"08004",
    "sg:province":"Barcelona",
    "wof:name":"Miro Pauls Francisco",
    "wof:placetype":"venue"
},
  "geometry": {"coordinates":[2.1720991135,41.373046875],"type":"Point"}
}