{
  "type": "Feature",
  "properties": {
    "iso:country":"ES",
    "sg:address":"Calle de Enrique Romero Torres, 5",
    "sg:city":"Cordoba",
    "sg:orig_category":"Agencias Y Asesores De Publicidad",
    "sg:phone":"+34 957 48 17 00",
    "sg:postcode":"14002",
    "sg:province":"C\u00f3rdoba",
    "wof:name":"Vectorial S.l.",
    "wof:placetype":"venue"
},
  "geometry": {"coordinates":[-4.7742810249,37.8805770874],"type":"Point"}
}