{
  "type": "Feature",
  "properties": {
    "addr:full":"Calle de Logro\u00d1o, 9 Vitoria-gasteiz \u00c1lava 01003",
    "addr:housenumber":"9",
    "addr:postcode":"01003",
    "addr:street":"Calle De Logron\u0303O",
    "iso:country":"ES",
    "sg:address":"Calle de Logro\u00d1o, 9",
    "sg:city":"Vitoria-gasteiz",
    "sg:orig_category":"Electrodom\u00c9sticos (al Por Menor)",
    "sg:phone":"+34 945 28 49 42",
    "sg:postcode":"01003",
    "sg:province":"\u00c1lava",
    "wof:name":"Xu  Yongsong",
    "wof:placetype":"venue"
},
  "geometry": {"coordinates":[-2.6636679173,42.8491249084],"type":"Point"}
}