{
  "type": "Feature",
  "properties": {
    "addr:full":"Carrer de Mestre Nicolau, 5 Barcelona Barcelona 08021",
    "addr:housenumber":"5",
    "addr:postcode":"08021",
    "addr:street":"Carrer De Mestre Nicolau",
    "iso:country":"ES",
    "sg:address":"Carrer de Mestre Nicolau, 5",
    "sg:city":"Barcelona",
    "sg:orig_category":"Cajas De Ahorro",
    "sg:phone":"+34 932 01 26 44",
    "sg:postcode":"08021",
    "sg:province":"Barcelona",
    "sg:website":"www.cajalaboral.com",
    "wof:name":"Caja Laboral Popular",
    "wof:placetype":"venue"
},
  "geometry": {"coordinates":[2.1416740417,41.392791748],"type":"Point"}
}