{
  "type": "Feature",
  "properties": {
    "addr:full":"Carr Industria, 550 Badalona Barcelona 08918",
    "addr:housenumber":"550",
    "addr:postcode":"08918",
    "addr:street":"Carr Industria",
    "iso:country":"ES",
    "sg:address":"Carr Industria, 550",
    "sg:city":"Badalona",
    "sg:orig_category":"Aguas (distribuci\u00d3n, Servicios)",
    "sg:phone":"+34 933 83 59 67",
    "sg:postcode":"08918",
    "sg:province":"Barcelona",
    "wof:name":"Tecno Ambiente S. L.",
    "wof:placetype":"venue"
},
  "geometry": {"coordinates":[2.2344799042,41.4332809448],"type":"Point"}
}