{
  "type": "Feature",
  "properties": {
    "iso:country":"ES",
    "sg:address":"Calle de Pilar De Los Limones, 21",
    "sg:city":"Carmona",
    "sg:orig_category":"Asociaciones Y Clubs Deportivos",
    "sg:phone":"+34 954 14 37 49",
    "sg:postcode":"41410",
    "sg:province":"Sevilla",
    "sg:website":"www.taekwondocarmona.com",
    "wof:name":"Asociacion Deportiva Taekwondo Ciudad De Carmona",
    "wof:placetype":"venue"
},
  "geometry": {"coordinates":[-5.6037464142,37.4634742737],"type":"Point"}
}