{
  "type": "Feature",
  "properties": {
    "iso:country":"ES",
    "sg:address":"Carrer de Pablo Picasso, 60",
    "sg:city":"Manresa",
    "sg:orig_category":"Carnicer\u00cdas, Carnicer\u00cdas",
    "sg:phone":"+34 938 73 73 66",
    "sg:postcode":"08243",
    "sg:province":"Barcelona",
    "wof:name":"Sato Sabata Miguel",
    "wof:placetype":"venue"
},
  "geometry": {"coordinates":[1.8456350565,41.7197265625],"type":"Point"}
}