{
  "type": "Feature",
  "properties": {
    "iso:country":"ES",
    "sg:address":"Calle de San Cayetano, 1",
    "sg:city":"Torre-pacheco",
    "sg:orig_category":"Supermercados Y Hipermercados",
    "sg:phone":"+34 968 57 70 67",
    "sg:postcode":"30700",
    "sg:province":"Murcia",
    "wof:name":"Saura Rosique Maximo",
    "wof:placetype":"venue"
},
  "geometry": {"coordinates":[-0.9525030255,37.7450523376],"type":"Point"}
}