{
  "type": "Feature",
  "properties": {
    "addr:full":"Ipe\u00d1arrieta Kalea, 44 Urretxu Guip\u00f9zcoa 20700",
    "addr:housenumber":"44",
    "addr:postcode":"20700",
    "addr:street":"Ipen\u0303Arrieta Kalea;Guipu\u0300Zcoa",
    "iso:country":"ES",
    "sg:address":"Ipe\u00d1arrieta Kalea, 44",
    "sg:city":"Urretxu",
    "sg:orig_category":"Serrer\u00cdas De Madera",
    "sg:phone":"+34 943 72 09 57",
    "sg:postcode":"20700",
    "sg:province":"Guip\u00f9zcoa",
    "wof:name":"Bengolea S.l.",
    "wof:placetype":"venue"
},
  "geometry": {"coordinates":[-2.3228690624,43.085067749],"type":"Point"}
}