{
  "type": "Feature",
  "properties": {
    "addr:full":"Calle de Mayor, 26 Cartagena Murcia 30201",
    "addr:housenumber":"26",
    "addr:postcode":"30201",
    "addr:street":"Calle De Mayor",
    "iso:country":"ES",
    "sg:address":"Calle de Mayor, 26",
    "sg:city":"Cartagena",
    "sg:orig_category":"Arquitectos",
    "sg:phone":"+34 968 12 28 16",
    "sg:postcode":"30201",
    "sg:province":"Murcia",
    "wof:name":"Marin Esmenota Francisco",
    "wof:placetype":"venue"
},
  "geometry": {"coordinates":[-0.9156429768,37.600566864],"type":"Point"}
}