{
  "type": "Feature",
  "properties": {
    "addr:full":"Carrer de Doctor Trueta, 121 Barcelona Barcelona 08005",
    "addr:housenumber":"121",
    "addr:postcode":"08005",
    "addr:street":"Carrer De Doctor Trueta",
    "iso:country":"ES",
    "sg:address":"Carrer de Doctor Trueta, 121",
    "sg:city":"Barcelona",
    "sg:orig_category":"Venta, Instalaci\u00d3n De Sistemas De Alarmas Y Vigilancia",
    "sg:phone":"+34 932 25 76 90",
    "sg:postcode":"08005",
    "sg:province":"Barcelona",
    "sg:website":"www.boschsecurity.com",
    "wof:name":"Bosch Security Systems S.a.",
    "wof:placetype":"venue"
},
  "geometry": {"coordinates":[2.1983509064,41.3949775696],"type":"Point"}
}