{
  "type": "Feature",
  "properties": {
    "addr:full":"Carrer de Sant Pere Mes Alt, 20 Barcelona Barcelona 08003",
    "addr:housenumber":"20",
    "addr:postcode":"08003",
    "addr:street":"Carrer De Sant",
    "iso:country":"ES",
    "sg:address":"Carrer de Sant Pere Mes Alt, 20",
    "sg:city":"Barcelona",
    "sg:orig_category":"Ropa De Trabajo Y Profesionales (al Por Menor)",
    "sg:phone":"+34 933 19 08 48",
    "sg:postcode":"08003",
    "sg:province":"Barcelona",
    "wof:name":"Gine Duch Serafina",
    "wof:placetype":"venue"
},
  "geometry": {"coordinates":[2.17614007,41.3877639771],"type":"Point"}
}