{
  "type": "Feature",
  "properties": {
    "addr:full":"Calle de Julio Burell, 37 Linares Ja\u00e9n 23700",
    "addr:housenumber":"37",
    "addr:postcode":"23700",
    "addr:street":"Calle De Julio Burell;Jae\u0301N",
    "iso:country":"ES",
    "sg:address":"Calle de Julio Burell, 37",
    "sg:city":"Linares",
    "sg:orig_category":"Postigos, Persianas Y Celos\u00cdas",
    "sg:phone":"+34 953 65 61 77",
    "sg:postcode":"23700",
    "sg:province":"Ja\u00e9n",
    "wof:name":"Carmona Almodovar Francisco",
    "wof:placetype":"venue"
},
  "geometry": {"coordinates":[-3.6312789917,38.0967483521],"type":"Point"}
}