{
  "type": "Feature",
  "properties": {
    "addr:full":"Calle de Sevilla Moreno, 1 Fuente Alamo Murcia 30320",
    "addr:housenumber":"1",
    "addr:postcode":"30320",
    "addr:street":"Calle De Sevilla Moreno",
    "iso:country":"ES",
    "sg:address":"Calle de Sevilla Moreno, 1",
    "sg:city":"Fuente Alamo",
    "sg:orig_category":"Sociedades, Compa\u00d1\u00cdas Aseguradoras",
    "sg:phone":"+34 968 59 84 72",
    "sg:postcode":"30320",
    "sg:province":"Murcia",
    "wof:name":"Hernandez Garcia Eustaquia",
    "wof:placetype":"venue"
},
  "geometry": {"coordinates":[-1.1687190533,37.7235946655],"type":"Point"}
}