{
  "type": "Feature",
  "properties": {
    "iso:country":"ES",
    "sg:address":"Veinat Can Canyet, 9",
    "sg:city":"Campllong",
    "sg:orig_category":"Ebanister\u00cda",
    "sg:phone":"+34 972 46 13 66",
    "sg:postcode":"17457",
    "sg:province":"Girona",
    "wof:name":"Tauleria 1903 S.l.",
    "wof:placetype":"venue"
},
  "geometry": {"coordinates":[2.8040299416,41.8944282532],"type":"Point"}
}