{
  "type": "Feature",
  "properties": {
    "addr:full":"Plaz Escritor Pe\u00d1a Aguayo, 1 Cordoba C\u00f3rdoba 14007",
    "addr:housenumber":"1",
    "addr:postcode":"14007",
    "addr:street":"Plaz Escritor Pen\u0303A Aguayo;Co\u0301Rdoba",
    "iso:country":"ES",
    "sg:address":"Plaz Escritor Pe\u00d1a Aguayo, 1",
    "sg:city":"Cordoba",
    "sg:orig_category":"Papeler\u00cdas, Librer\u00cdas",
    "sg:phone":"+34 957 43 41 28",
    "sg:postcode":"14007",
    "sg:province":"C\u00f3rdoba",
    "wof:name":"Ramirez Llamas Rafael Juan",
    "wof:placetype":"venue"
},
  "geometry": {"coordinates":[-4.7673401833,37.8944740295],"type":"Point"}
}