{
  "type": "Feature",
  "properties": {
    "addr:full":"Av Fco Salzillo(pol Ind Oeste), S/n S. Gines Murcia 30169",
    "addr:housenumber":"s",
    "addr:postcode":"30169",
    "addr:street":"Av Fco Salzillo Pol Ind Oeste;/ N S.",
    "iso:country":"ES",
    "sg:address":"Av Fco Salzillo(pol Ind Oeste), S/n",
    "sg:city":"S. Gines",
    "sg:orig_category":"Importaci\u00d3n",
    "sg:phone":"+34 968 88 13 88",
    "sg:postcode":"30169",
    "sg:province":"Murcia",
    "wof:name":"Al-hama Spain S.l.",
    "wof:placetype":"venue"
},
  "geometry": {"coordinates":[-1.1298867464,37.9834747314],"type":"Point"}
}