{
  "type": "Feature",
  "properties": {
    "iso:country":"ES",
    "sg:address":"Calle de Caba, 35",
    "sg:city":"Albacete",
    "sg:orig_category":"Bancos",
    "sg:phone":"+34 967 50 97 10",
    "sg:postcode":"02001",
    "sg:province":"Albacete",
    "wof:name":"Banco Popular Espa\u00f1ol S.a.",
    "wof:placetype":"venue"
},
  "geometry": {"coordinates":[-1.8600269556,38.9940605164],"type":"Point"}
}