{
  "type": "Feature",
  "properties": {
    "iso:country":"ES",
    "sg:address":"Avda Santa Rosa De Lima, 22",
    "sg:city":"Malaga",
    "sg:orig_category":"Estudios De Grabaci\u00d3n Sonora",
    "sg:phone":"+34 952 34 96 55",
    "sg:postcode":"29007",
    "sg:province":"M\u00e1laga",
    "sg:website":"www.angelfire.com/biz/duendeproducciones",
    "wof:name":"Duende Producciones S.c.",
    "wof:placetype":"venue"
},
  "geometry": {"coordinates":[-4.4494900703,36.7198410034],"type":"Point"}
}