{
  "type": "Feature",
  "properties": {
    "iso:country":"ES",
    "sg:address":"Ptda Alameda, S/n",
    "sg:city":"Potries",
    "sg:orig_category":"Fabricaci\u00d3n De Jabones, Detergentes Y Lej\u00cdas",
    "sg:phone":"+34 962 80 04 75",
    "sg:postcode":"46721",
    "sg:province":"Valencia",
    "sg:website":"www.aimme.es/serpis",
    "wof:name":"Electroquimica Del Serpis S.a.",
    "wof:placetype":"venue"
},
  "geometry": {"coordinates":[-0.1931989938,38.916431427],"type":"Point"}
}