{
  "type": "Feature",
  "properties": {
    "addr:full":"Carrer de Progres, 9 Rubi Barcelona 08191",
    "addr:housenumber":"9",
    "addr:postcode":"08191",
    "addr:street":"Carrer De Progres",
    "iso:country":"ES",
    "sg:address":"Carrer de Progres, 9",
    "sg:city":"Rubi",
    "sg:orig_category":"Molduras, Junquillos, Listones Y Molduras Perforadas",
    "sg:phone":"+34 936 99 66 98",
    "sg:postcode":"08191",
    "sg:province":"Barcelona",
    "wof:name":"Llamas Gullon Gregorio",
    "wof:placetype":"venue"
},
  "geometry": {"coordinates":[2.0318300724,41.4795036316],"type":"Point"}
}