{
  "type": "Feature",
  "properties": {
    "addr:full":"Carrer de Azorin, 45 Castalla Alicante 03420",
    "addr:housenumber":"45",
    "addr:postcode":"03420",
    "addr:street":"Carrer De Azorin",
    "iso:country":"ES",
    "sg:address":"Carrer de Azorin, 45",
    "sg:city":"Castalla",
    "sg:orig_category":"Caf\u00c9s, Bares, Cervecer\u00cdas",
    "sg:phone":"+34 966 56 06 88",
    "sg:postcode":"03420",
    "sg:province":"Alicante",
    "wof:name":"La Basseta C.b.",
    "wof:placetype":"venue"
},
  "geometry": {"coordinates":[-0.6679700017,38.593547821],"type":"Point"}
}