{
  "type": "Feature",
  "properties": {
    "addr:full":"Calle de Sirera Y Dara, 19 Novelda Alicante 03660",
    "addr:housenumber":"19",
    "addr:postcode":"03660",
    "addr:street":"Calle De Sirera Y Dara",
    "iso:country":"ES",
    "sg:address":"Calle de Sirera Y Dara, 19",
    "sg:city":"Novelda",
    "sg:orig_category":"Internados & Ense\u00d1anza Privada",
    "sg:phone":"+34 965 60 09 95",
    "sg:postcode":"03660",
    "sg:province":"Alicante",
    "wof:name":"Colegio Sta Maria Magdalena Carmelitas Misioneras Teresianas Provincia San Alberto De Novelda",
    "wof:placetype":"venue"
},
  "geometry": {"coordinates":[-0.7643529773,38.3866500854],"type":"Point"}
}