{
  "type": "Feature",
  "properties": {
    "addr:full":"Calle de Mar, 6 Santa Pola Alicante 03130",
    "addr:housenumber":"6",
    "addr:postcode":"03130",
    "addr:street":"Calle De Mar",
    "iso:country":"ES",
    "sg:address":"Calle de Mar, 6",
    "sg:city":"Santa Pola",
    "sg:orig_category":"Supermercados Y Hipermercados",
    "sg:phone":"+34 965 41 12 95",
    "sg:postcode":"03130",
    "sg:province":"Alicante",
    "wof:name":"Provenza  Ester",
    "wof:placetype":"venue"
},
  "geometry": {"coordinates":[-0.5490880013,38.1907920837],"type":"Point"}
}