{
  "type": "Feature",
  "properties": {
    "addr:full":"Carrer de Girona, 27 Barcelona Barcelona 08010",
    "addr:housenumber":"27",
    "addr:postcode":"08010",
    "addr:street":"Carrer De Girona",
    "iso:country":"ES",
    "sg:address":"Carrer de Girona, 27",
    "sg:city":"Barcelona",
    "sg:orig_category":"Arquitectos",
    "sg:phone":"+34 933 17 44 71",
    "sg:postcode":"08010",
    "sg:province":"Barcelona",
    "wof:name":"Korpex Dietetica S.l.",
    "wof:placetype":"venue"
},
  "geometry": {"coordinates":[2.1746890545,41.3919448853],"type":"Point"}
}