{
  "type": "Feature",
  "properties": {
    "iso:country":"ES",
    "sg:address":"Calle de Cruz De Piedra, 20",
    "sg:city":"Yecla",
    "sg:orig_category":"Bares, Piano",
    "sg:phone":"+34 968 79 51 30",
    "sg:postcode":"30510",
    "sg:province":"Murcia",
    "wof:name":"Perez Perez Gines",
    "wof:placetype":"venue"
},
  "geometry": {"coordinates":[-1.1121828556,38.6109733582],"type":"Point"}
}