{
  "type": "Feature",
  "properties": {
    "iso:country":"ES",
    "sg:address":"Ctra Mig, 91",
    "sg:city":"Hospitalet Llobregat",
    "sg:orig_category":"Teatro, Ballet, Danza (agrupaciones, Compa\u00d1\u00cdas)",
    "sg:phone":"+34 933 36 26 13",
    "sg:postcode":"08907",
    "sg:province":"Barcelona",
    "wof:name":"Accions Teatrals La Cubana S.c.c.l.",
    "wof:placetype":"venue"
},
  "geometry": {"coordinates":[2.1086351871,41.3562393188],"type":"Point"}
}