{
  "type": "Feature",
  "properties": {
    "iso:country":"ES",
    "sg:address":"Pg Guayaquil, 47",
    "sg:city":"Barcelona",
    "sg:orig_category":"Fabricaci\u00d3n E Instalaci\u00d3n De Cocinas Profesionales",
    "sg:phone":"+34 933 46 17 94",
    "sg:postcode":"08030",
    "sg:province":"Barcelona",
    "wof:name":"Barna Norte Cocinas S.l.",
    "wof:placetype":"venue"
},
  "geometry": {"coordinates":[2.2030379772,41.4464912415],"type":"Point"}
}