{
  "type": "Feature",
  "properties": {
    "addr:full":"Calle de Duque De Sesto, 13 Madrid Madrid 28009",
    "addr:housenumber":"13",
    "addr:postcode":"madrid;28009",
    "addr:street":"Calle De Duque De Sesto",
    "iso:country":"ES",
    "sg:address":"Calle de Duque De Sesto, 13",
    "sg:city":"Madrid",
    "sg:orig_category":"M\u00c9dicos: Endocrinolog\u00cda Y Metabolismo",
    "sg:phone":"+34 914 31 75 38",
    "sg:postcode":"28009",
    "sg:province":"Madrid",
    "wof:name":"Sanchez Martin Jose Antonio",
    "wof:placetype":"venue"
},
  "geometry": {"coordinates":[-3.6770679951,40.4225654602],"type":"Point"}
}