{
  "type": "Feature",
  "properties": {
    "addr:full":"Calle de Bulevar Chajofe, 1 Cristianos Santa Cruz De Tenerife 38650",
    "addr:housenumber":"1",
    "addr:postcode":"38650",
    "addr:street":"Calle De Bulevar Chajofe",
    "iso:country":"ES",
    "sg:address":"Calle de Bulevar Chajofe, 1",
    "sg:city":"Cristianos",
    "sg:orig_category":"Asesor\u00cda Sobre Comunicaci\u00d3n De Empresas",
    "sg:phone":"+34 922 79 70 74",
    "sg:postcode":"38650",
    "sg:province":"Santa Cruz De Tenerife",
    "wof:name":"Asesoria Miguel Lopez S.l.",
    "wof:placetype":"venue"
},
  "geometry": {"coordinates":[-16.2548561096,28.4698104858],"type":"Point"}
}