{
  "type": "Feature",
  "properties": {
    "addr:full":"Avda Maria Auxiliadora (de), 14 Montilla C\u00f3rdoba 14550",
    "addr:housenumber":"14",
    "addr:postcode":"14550",
    "addr:street":"Avda Maria Auxiliadora De;Co\u0301Rdoba",
    "iso:country":"ES",
    "sg:address":"Avda Maria Auxiliadora (de), 14",
    "sg:city":"Montilla",
    "sg:orig_category":"Mercer\u00cda, Lencer\u00cda (al Por Menor)",
    "sg:phone":"+34 957 65 55 95",
    "sg:postcode":"14550",
    "sg:province":"C\u00f3rdoba",
    "wof:name":"Madrid Carmona Jose",
    "wof:placetype":"venue"
},
  "geometry": {"coordinates":[-4.6445422173,37.581111908],"type":"Point"}
}