{
  "type": "Feature",
  "properties": {
    "iso:country":"ES",
    "sg:address":"Rua Meni\u00d1os, 8",
    "sg:city":"Montrove",
    "sg:orig_category":"Arquitectos",
    "sg:phone":"+34 981 63 41 90",
    "sg:postcode":"15179",
    "sg:province":"La Coru\u00f1a",
    "wof:name":"Moreno Tonini Alejandro Manuel",
    "wof:placetype":"venue"
},
  "geometry": {"coordinates":[-8.352599144,43.3330764771],"type":"Point"}
}