{
  "type": "Feature",
  "properties": {
    "iso:country":"ES",
    "sg:address":"Calle de Salvador De Madariaga, 3",
    "sg:city":"Badajoz",
    "sg:orig_category":"Iglesia Cat\u00d3lica",
    "sg:phone":"+34 924 24 16 03",
    "sg:postcode":"06011",
    "sg:province":"Badajoz",
    "wof:name":"Parroquia Nuestra Se\u00f1ora Del Perpetuo Socorro",
    "wof:placetype":"venue"
},
  "geometry": {"coordinates":[-6.9864439964,38.8644218445],"type":"Point"}
}