{
  "type": "Feature",
  "properties": {
    "iso:country":"ES",
    "sg:address":"Carr Duc Alfons El Vell (del), 7",
    "sg:city":"Gandia",
    "sg:orig_category":"Centros P\u00dablicos De Formaci\u00d3n Profesional Y T\u00c9cnica",
    "sg:phone":"+34 962 87 30 82",
    "sg:postcode":"46700",
    "sg:province":"Valencia",
    "wof:name":"Colegio Oficial De Aparejadores Arquitectos Tecnicos De Valencia",
    "wof:placetype":"venue"
},
  "geometry": {"coordinates":[-0.1913339943,38.960735321],"type":"Point"}
}