{
  "type": "Feature",
  "properties": {
    "addr:full":"Carrer de Lluis Companys, 19 Santa Perpetua De Mogoda Barcelona 08130",
    "addr:housenumber":"19",
    "addr:postcode":"08130",
    "addr:street":"Carrer De Lluis Companys",
    "iso:country":"ES",
    "sg:address":"Carrer de Lluis Companys, 19",
    "sg:city":"Santa Perpetua De Mogoda",
    "sg:orig_category":"Ense\u00d1anza: Peluquer\u00cda Est\u00c9tica",
    "sg:phone":"+34 935 60 42 81",
    "sg:postcode":"08130",
    "sg:province":"Barcelona",
    "wof:name":"Academia Pachon S.l.",
    "wof:placetype":"venue"
},
  "geometry": {"coordinates":[2.1828050613,41.5320854187],"type":"Point"}
}