{
  "type": "Feature",
  "properties": {
    "iso:country":"ES",
    "sg:address":"Ctra Santa Creu De Calafell, Km. 0010,0",
    "sg:city":"S. Boi Llobregat",
    "sg:orig_category":"Fabricaci\u00d3n De Moldes Y Modelos",
    "sg:phone":"+34 936 52 53 05",
    "sg:postcode":"08830",
    "sg:province":"Barcelona",
    "wof:name":"Moldes Valma Scp",
    "wof:placetype":"venue"
},
  "geometry": {"coordinates":[2.0449779034,41.3480606079],"type":"Point"}
}