{
  "type": "Feature",
  "properties": {
    "addr:full":"Calle de Artilleros, 5 Alacant Alicante 03002",
    "addr:housenumber":"5",
    "addr:postcode":"03002",
    "addr:street":"Calle De Artilleros",
    "iso:country":"ES",
    "sg:address":"Calle de Artilleros, 5",
    "sg:city":"Alacant",
    "sg:orig_category":"\u00d3ptica: Instrumentos (fabricaci\u00d3n)",
    "sg:phone":"+34 965 21 65 08",
    "sg:postcode":"03002",
    "sg:province":"Alicante",
    "wof:name":"Molina Miquel Amelia",
    "wof:placetype":"venue"
},
  "geometry": {"coordinates":[-0.4850811064,38.3470153809],"type":"Point"}
}