{
  "type": "Feature",
  "properties": {
    "iso:country":"ES",
    "sg:address":"Calle de Justo Rodriguez, 2",
    "sg:city":"Nore\u00f1a",
    "sg:orig_category":"Asociaciones Y Clubs Deportivos",
    "sg:phone":"+34 985 74 45 91",
    "sg:postcode":"33180",
    "sg:province":"Asturias",
    "wof:name":"Gimnasio Pedregal S.l.",
    "wof:placetype":"venue"
},
  "geometry": {"coordinates":[-5.7053909302,43.3919715881],"type":"Point"}
}