{
  "type": "Feature",
  "properties": {
    "addr:full":"Calle de Guadarrama, 19 Belmonte Cuenca 16640",
    "addr:housenumber":"19",
    "addr:postcode":"16640",
    "addr:street":"Calle De Guadarrama",
    "iso:country":"ES",
    "sg:address":"Calle de Guadarrama, 19",
    "sg:city":"Belmonte",
    "sg:orig_category":"Cerrajer\u00cda, Ferrallista",
    "sg:phone":"+34 967 17 08 22",
    "sg:postcode":"16640",
    "sg:province":"Cuenca",
    "wof:name":"Metalicas Herrada Moreno S.l.",
    "wof:placetype":"venue"
},
  "geometry": {"coordinates":[-2.7075428963,39.5577278137],"type":"Point"}
}