{
  "type": "Feature",
  "properties": {
    "iso:country":"ES",
    "sg:address":"Serra Maurina, S/n",
    "sg:city":"Serra Maurina",
    "sg:orig_category":"Empresas De Carpinter\u00cda De Madera",
    "sg:phone":"+34 937 25 66 50",
    "sg:postcode":"08213",
    "sg:province":"Barcelona",
    "wof:name":"Carpinteria Yoni E Hijos S.c.p",
    "wof:placetype":"venue"
},
  "geometry": {"coordinates":[2.157804966,41.5574531555],"type":"Point"}
}