{
  "type": "Feature",
  "properties": {
    "addr:full":"Calle de Exacta (de La), 13 Pinto Madrid 28320",
    "addr:housenumber":"13",
    "addr:postcode":"28320",
    "addr:street":"Calle De Exacta De La",
    "iso:country":"ES",
    "sg:address":"Calle de Exacta (de La), 13",
    "sg:city":"Pinto",
    "sg:orig_category":"M\u00c9dicos: Radiolog\u00cda (radiodiagn\u00d3stico E Im\u00c1genes En Medicina)",
    "sg:phone":"+34 916 92 66 47",
    "sg:postcode":"28320",
    "sg:province":"Madrid",
    "wof:name":"Premium Dental S.l",
    "wof:placetype":"venue"
},
  "geometry": {"coordinates":[-3.6942028999,40.2456321716],"type":"Point"}
}