{
  "type": "Feature",
  "properties": {
    "addr:full":"Calle de Trinidad Grund, 7 Malaga M\u00e1laga 29001",
    "addr:housenumber":"7",
    "addr:postcode":"29001",
    "addr:street":"Calle De Trinidad Grund;Ma\u0301Laga",
    "iso:country":"ES",
    "sg:address":"Calle de Trinidad Grund, 7",
    "sg:city":"Malaga",
    "sg:orig_category":"Ense\u00d1anza: Comercio, Gesti\u00d3n, Inform\u00c1tica",
    "sg:phone":"+34 952 21 64 41",
    "sg:postcode":"29001",
    "sg:province":"M\u00e1laga",
    "wof:name":"Centro De Estudios Grund S.l.",
    "wof:placetype":"venue"
},
  "geometry": {"coordinates":[-4.4213910103,36.7172431946],"type":"Point"}
}