{
  "type": "Feature",
  "properties": {
    "iso:country":"ES",
    "sg:address":"Ctra Palmar, 182",
    "sg:city":"Barracas",
    "sg:orig_category":"Electromec\u00c1nica",
    "sg:phone":"+34 968 25 05 18",
    "sg:postcode":"30152",
    "sg:province":"Murcia",
    "wof:name":"Elevamac S.l.",
    "wof:placetype":"venue"
},
  "geometry": {"coordinates":[-1.1452490091,37.9643058777],"type":"Point"}
}