{
  "type": "Feature",
  "properties": {
    "addr:full":"Plaz Blas Infante (de), 21 Estepa Sevilla 41560",
    "addr:housenumber":"21",
    "addr:postcode":"41560",
    "addr:street":"Plaz Blas Infante De;Sevilla",
    "iso:country":"ES",
    "sg:address":"Plaz Blas Infante (de), 21",
    "sg:city":"Estepa",
    "sg:orig_category":"Ropa Para Ni\u00d1os (al Por Menor)",
    "sg:phone":"+34 955 91 45 88",
    "sg:postcode":"41560",
    "sg:province":"Sevilla",
    "wof:name":"Maireles Baez Carmen",
    "wof:placetype":"venue"
},
  "geometry": {"coordinates":[-4.8780741692,37.2938766479],"type":"Point"}
}