{
  "type": "Feature",
  "properties": {
    "addr:full":"Avda Carlos Vii, 8 Portugalete Vizcaya 48920",
    "addr:housenumber":"8",
    "addr:postcode":"48920",
    "addr:street":"Avda Carlos Vii",
    "iso:country":"ES",
    "sg:address":"Avda Carlos Vii, 8",
    "sg:city":"Portugalete",
    "sg:orig_category":"Diarios, Revistas Y Boletines (suscripciones)",
    "sg:phone":"+34 944 83 79 98",
    "sg:postcode":"48920",
    "sg:province":"Vizcaya",
    "wof:name":"Maria Paz Gomez Goitia",
    "wof:placetype":"venue"
},
  "geometry": {"coordinates":[-3.0211369991,43.3196525574],"type":"Point"}
}