{
  "type": "Feature",
  "properties": {
    "iso:country":"ES",
    "sg:address":"Calle de Principal, 77",
    "sg:city":"Boiro",
    "sg:orig_category":"Centros Empresariales",
    "sg:phone":"+34 981 84 82 16",
    "sg:postcode":"15930",
    "sg:province":"La Coru\u00f1a",
    "wof:name":"Federacion De Empresarios Do Barbanza",
    "wof:placetype":"venue"
},
  "geometry": {"coordinates":[-8.8847093582,42.6471214294],"type":"Point"}
}