{
  "type": "Feature",
  "properties": {
    "addr:full":"Calle de Martires, 24 Almendralejo Badajoz 06200",
    "addr:housenumber":"24",
    "addr:postcode":"06200",
    "addr:street":"Calle De Martires",
    "iso:country":"ES",
    "sg:address":"Calle de Martires, 24",
    "sg:city":"Almendralejo",
    "sg:orig_category":"Peleter\u00cdas",
    "sg:phone":"+34 924 66 40 06",
    "sg:postcode":"06200",
    "sg:province":"Badajoz",
    "wof:name":"Ventura Valiente Gallardo S.l.",
    "wof:placetype":"venue"
},
  "geometry": {"coordinates":[-6.4088959694,38.6810951233],"type":"Point"}
}