{
  "type": "Feature",
  "properties": {
    "iso:country":"ES",
    "sg:address":"Calle de Altamira, 1",
    "sg:city":"Azuqueca Henares",
    "sg:orig_category":"Arquitectos",
    "sg:phone":"+34 949 26 35 84",
    "sg:postcode":"19200",
    "sg:province":"Guadalajara",
    "wof:name":"Edages Promocion Inmobiliaria S.l.",
    "wof:placetype":"venue"
},
  "geometry": {"coordinates":[-3.2771468163,40.5640029907],"type":"Point"}
}