{
  "type": "Feature",
  "properties": {
    "iso:country":"ES",
    "sg:address":"Calle de Nuestra Se\u00d1ora De La Luz, 54",
    "sg:city":"Madrid",
    "sg:orig_category":"Perfumer\u00cda (al Por Menor)",
    "sg:phone":"+34 914 66 18 17",
    "sg:postcode":"28025",
    "sg:province":"Madrid",
    "sg:website":"www.bodybell.com",
    "wof:name":"Iberica De Drogueria Y Perfumeria S.a.",
    "wof:placetype":"venue"
},
  "geometry": {"coordinates":[-3.7466039658,40.3841896057],"type":"Point"}
}