{
  "type": "Feature",
  "properties": {
    "addr:full":"Carr Nou D'octubre, 13 Alboraya Valencia 46120",
    "addr:housenumber":"13",
    "addr:postcode":"46120",
    "addr:street":"Carr Nou D'Octubre",
    "iso:country":"ES",
    "sg:address":"Carr Nou D'octubre, 13",
    "sg:city":"Alboraya",
    "sg:orig_category":"Ingeniero",
    "sg:phone":"+34 961 85 67 36",
    "sg:postcode":"46120",
    "sg:province":"Valencia",
    "wof:name":"Alonso Giner Bernardo Antonio",
    "wof:placetype":"venue"
},
  "geometry": {"coordinates":[-0.3504492939,39.5014228821],"type":"Point"}
}