{
  "type": "Feature",
  "properties": {
    "addr:full":"Plaz Valle De Oro, 7 Madrid Madrid 28019",
    "addr:housenumber":"7",
    "addr:postcode":"madrid;28019",
    "addr:street":"Oro",
    "iso:country":"ES",
    "sg:address":"Plaz Valle De Oro, 7",
    "sg:city":"Madrid",
    "sg:orig_category":"Venta, Instalaci\u00d3n, Reparaci\u00d3n De Antenas Para Televisi\u00d3n",
    "sg:phone":"+34 914 71 53 55",
    "sg:postcode":"28019",
    "sg:province":"Madrid",
    "wof:name":"Inelco Telecomunicaciones S.l.n.e.",
    "wof:placetype":"venue"
},
  "geometry": {"coordinates":[-3.7292249203,40.3881950378],"type":"Point"}
}