{
  "type": "Feature",
  "properties": {
    "addr:full":"Tejeria, 31 Ziordia Navarra 31809",
    "addr:housenumber":"31",
    "addr:postcode":"31809",
    "addr:street":"Tejeria",
    "iso:country":"ES",
    "sg:address":"Tejeria, 31",
    "sg:city":"Ziordia",
    "sg:orig_category":"Aspiradoras Dom\u00c9sticas",
    "sg:phone":"+34 948 46 85 36",
    "sg:postcode":"31809",
    "sg:province":"Navarra",
    "wof:name":"Bengoetxea Morante Patxi",
    "wof:placetype":"venue"
},
  "geometry": {"coordinates":[-2.2252690792,42.8709716797],"type":"Point"}
}