{
  "type": "Feature",
  "properties": {
    "addr:full":"Plaz Ayuntamiento (el), 4 Alanis Sevilla 41380",
    "addr:postcode":"41380",
    "iso:country":"ES",
    "sg:address":"Plaz Ayuntamiento (el), 4",
    "sg:city":"Alanis",
    "sg:orig_category":"Tubos Y Tuber\u00cdas De Goma Y Pl\u00c1stico (fabricaci\u00d3n, Al Por Mayor)",
    "sg:phone":"+34 954 88 52 75",
    "sg:postcode":"41380",
    "sg:province":"Sevilla",
    "wof:name":"Industrias Ortega Morilla S.l.",
    "wof:placetype":"venue"
},
  "geometry": {"coordinates":[-5.7151060104,38.0377616882],"type":"Point"}
}