{
  "type": "Feature",
  "properties": {
    "iso:country":"ES",
    "sg:address":"Carrer de Laurea Figuerola, 9",
    "sg:city":"Calaf",
    "sg:orig_category":"Talleres: Ropa A Medida",
    "sg:phone":"+34 938 69 87 84",
    "sg:postcode":"08280",
    "sg:province":"Barcelona",
    "wof:name":"Escola Torra Ricard",
    "wof:placetype":"venue"
},
  "geometry": {"coordinates":[1.5121150017,41.7318572998],"type":"Point"}
}