{
  "type": "Feature",
  "properties": {
    "iso:country":"ES",
    "sg:address":"Calle de Madrid, 42",
    "sg:city":"Humanes De Madrid",
    "sg:orig_category":"Agencias Y Asesores De Publicidad",
    "sg:phone":"+34 916 04 23 40",
    "sg:postcode":"28970",
    "sg:province":"Madrid",
    "wof:name":"Huang  Shieng",
    "wof:placetype":"venue"
},
  "geometry": {"coordinates":[-3.82791996,40.2530021667],"type":"Point"}
}