{
  "type": "Feature",
  "properties": {
    "iso:country":"ES",
    "sg:address":"Calle de Circunde, 10",
    "sg:city":"Logro\u00f1o",
    "sg:orig_category":"Maquinaria Para Industrias Diversas",
    "sg:phone":"+34 941 26 07 02",
    "sg:postcode":"26006",
    "sg:province":"La Rioja",
    "wof:name":"Proyma",
    "wof:placetype":"venue"
},
  "geometry": {"coordinates":[-2.4005711079,42.4570541382],"type":"Point"}
}