{
  "type": "Feature",
  "properties": {
    "addr:full":"Calle de Puente Colgante, 44 Valladolid Valladolid 47006",
    "addr:housenumber":"44",
    "addr:postcode":"47006",
    "addr:street":"Calle De Puente Colgante",
    "iso:country":"ES",
    "sg:address":"Calle de Puente Colgante, 44",
    "sg:city":"Valladolid",
    "sg:orig_category":"Molduras, Junquillos, Listones Y Molduras Perforadas",
    "sg:phone":"+34 983 27 30 96",
    "sg:postcode":"47006",
    "sg:province":"Valladolid",
    "wof:name":"Hosteleria Chicote S.l.",
    "wof:placetype":"venue"
},
  "geometry": {"coordinates":[-4.7388429642,41.6408576965],"type":"Point"}
}