{
  "type": "Feature",
  "properties": {
    "iso:country":"ES",
    "sg:address":"Ctra Zamora, Km. 0516,0",
    "sg:city":"Alca\u00f1ices",
    "sg:orig_category":"Reparaciones Y Remolcado De Veh\u00cdculos",
    "sg:phone":"+34 980 68 01 45",
    "sg:postcode":"49500",
    "sg:province":"Zamora",
    "wof:name":"Taller Y Gruas Rivas Nieto S.l.",
    "wof:placetype":"venue"
},
  "geometry": {"coordinates":[-6.3475852013,41.6988945007],"type":"Point"}
}