{
  "type": "Feature",
  "properties": {
    "addr:full":"Calle de Burgo Nuevo, 15 Le\u00f3n Le\u00f3n 24001",
    "addr:housenumber":"15",
    "addr:postcode":"24001",
    "addr:street":"Calle De Burgo Nuevo;Leo\u0301N",
    "iso:country":"ES",
    "sg:address":"Calle de Burgo Nuevo, 15",
    "sg:city":"Le\u00f3n",
    "sg:orig_category":"Centros P\u00dablicos De Formaci\u00d3n Profesional Y T\u00c9cnica",
    "sg:phone":"+34 987 20 19 43",
    "sg:postcode":"24001",
    "sg:province":"Le\u00f3n",
    "wof:name":"Colegio Oficial De Ingenieros Tecnicos Agricolas",
    "wof:placetype":"venue"
},
  "geometry": {"coordinates":[-5.5733270645,42.5962791443],"type":"Point"}
}