{
  "type": "Feature",
  "properties": {
    "addr:full":"Coronel Alfonso Beorlegui, 41 Iru\u00f1a Navarra 31015",
    "addr:housenumber":"41",
    "addr:postcode":"31015",
    "addr:street":"Coronel Alfonso Beorlegui",
    "iso:country":"ES",
    "sg:address":"Coronel Alfonso Beorlegui, 41",
    "sg:city":"Iru\u00f1a",
    "sg:orig_category":"Librer\u00cdas",
    "sg:phone":"+34 948 12 75 53",
    "sg:postcode":"31015",
    "sg:province":"Navarra",
    "wof:name":"Garayoa Platero Fernando",
    "wof:placetype":"venue"
},
  "geometry": {"coordinates":[-1.6437540054,42.81275177],"type":"Point"}
}