{
  "type": "Feature",
  "properties": {
    "addr:full":"Carrer de Riera, 10 Vic Barcelona 08500",
    "addr:housenumber":"10",
    "addr:postcode":"08500",
    "addr:street":"Carrer De Riera",
    "iso:country":"ES",
    "sg:address":"Carrer de Riera, 10",
    "sg:city":"Vic",
    "sg:orig_category":"Laboratorios Y Trabajos De Fotograf\u00cda, V\u00cddeo Y Cine",
    "sg:phone":"+34 938 85 63 57",
    "sg:postcode":"08500",
    "sg:province":"Barcelona",
    "wof:name":"Gomis De Subira Jose",
    "wof:placetype":"venue"
},
  "geometry": {"coordinates":[2.2534580231,41.9295845032],"type":"Point"}
}