{
  "type": "Feature",
  "properties": {
    "addr:full":"Calle de Italia, 92 Palencia Palencia 34004",
    "addr:housenumber":"92",
    "addr:postcode":"34004",
    "addr:street":"Calle De Italia",
    "iso:country":"ES",
    "sg:address":"Calle de Italia, 92",
    "sg:city":"Palencia",
    "sg:orig_category":"Muebles Y Accesorios Para Cocinas Y Cuartos De Ba\u00d1o (al Por Menor)",
    "sg:phone":"+34 979 71 07 27",
    "sg:postcode":"34004",
    "sg:province":"Palencia",
    "wof:name":"Alcopal S.l.",
    "wof:placetype":"venue"
},
  "geometry": {"coordinates":[-4.51171875,42.0023803711],"type":"Point"}
}