{
  "type": "Feature",
  "properties": {
    "addr:full":"Rond Guinardo, 126 Barcelona Barcelona 08041",
    "addr:housenumber":"126",
    "addr:postcode":"08041",
    "iso:country":"ES",
    "sg:address":"Rond Guinardo, 126",
    "sg:city":"Barcelona",
    "sg:orig_category":"Empresas De Limpieza",
    "sg:phone":"+34 934 56 93 28",
    "sg:postcode":"08041",
    "sg:province":"Barcelona",
    "wof:name":"Chercoles Martinez Luciano",
    "wof:placetype":"venue"
},
  "geometry": {"coordinates":[2.1750950813,41.4169883728],"type":"Point"}
}