{
  "type": "Feature",
  "properties": {
    "iso:country":"ES",
    "sg:address":"Calle de San Manuel, 2",
    "sg:city":"Majadahonda",
    "sg:orig_category":"Importaci\u00d3n",
    "sg:phone":"+34 916 39 85 50",
    "sg:postcode":"28220",
    "sg:province":"Madrid",
    "wof:name":"Micromouse S.l.",
    "wof:placetype":"venue"
},
  "geometry": {"coordinates":[-3.8763329983,40.4738731384],"type":"Point"}
}