{
  "type": "Feature",
  "properties": {
    "iso:country":"ES",
    "sg:address":"Avda Julian Saez, 30",
    "sg:city":"Pedro Mu\u00e7oz",
    "sg:orig_category":"Venta, Montaje De Neum\u00c1ticos",
    "sg:phone":"+34 926 58 73 05",
    "sg:postcode":"13620",
    "sg:province":"Ciudad Real",
    "wof:name":"Serviautos Cuenca S.l.",
    "wof:placetype":"venue"
},
  "geometry": {"coordinates":[-2.944617033,39.3901367188],"type":"Point"}
}