{
  "type": "Feature",
  "properties": {
    "iso:country":"ES",
    "sg:address":"Calle de Alfonso Mejias, 8",
    "sg:city":"San Miguel",
    "sg:orig_category":"Alimentaci\u00d3n General (al Por Menor)",
    "sg:phone":"+34 922 70 00 77",
    "sg:postcode":"38620",
    "sg:province":"Santa Cruz De Tenerife",
    "wof:name":"Lemus Alonso Celestino",
    "wof:placetype":"venue"
},
  "geometry": {"coordinates":[-16.6155014038,28.0991039276],"type":"Point"}
}