{
  "type": "Feature",
  "properties": {
    "iso:country":"ES",
    "sg:address":"Pase Canalejas, 117",
    "sg:city":"Salamanca",
    "sg:orig_category":"Farmacias",
    "sg:phone":"+34 923 27 14 40",
    "sg:postcode":"37001",
    "sg:province":"Salamanca",
    "wof:name":"Alonso Buron Llamazares Maria Del Carmen",
    "wof:placetype":"venue"
},
  "geometry": {"coordinates":[-5.6590099335,40.961730957],"type":"Point"}
}