{
  "type": "Feature",
  "properties": {
    "addr:full":"Calle de Olas (las), 1 Costa Teguise Las Palmas 35509",
    "addr:housenumber":"1",
    "addr:postcode":"35509",
    "addr:street":"Calle De Olas Las",
    "iso:country":"ES",
    "sg:address":"Calle de Olas (las), 1",
    "sg:city":"Costa Teguise",
    "sg:orig_category":"Alquiler De Veh\u00cdculos: Turismos Y Utilitarios",
    "sg:phone":"+34 928 59 00 41",
    "sg:postcode":"35509",
    "sg:province":"Las Palmas",
    "wof:name":"Autos Borges S.l.",
    "wof:placetype":"venue"
},
  "geometry": {"coordinates":[-13.4913730621,28.9960174561],"type":"Point"}
}