{
  "type": "Feature",
  "properties": {
    "iso:country":"ES",
    "sg:address":"Csri Portada (la), 15",
    "sg:city":"Portada",
    "sg:orig_category":"Veh\u00cdculos De Ocasi\u00d3n",
    "sg:phone":"+34 922 41 70 15",
    "sg:postcode":"38700",
    "sg:province":"Santa Cruz De Tenerife",
    "wof:name":"Maritimo Automoviles S.l.",
    "wof:placetype":"venue"
},
  "geometry": {"coordinates":[-17.7677326202,28.6805782318],"type":"Point"}
}