{
  "type": "Feature",
  "properties": {
    "iso:country":"ES",
    "sg:address":"Calle de Luis Montoto, 88",
    "sg:city":"Sevilla",
    "sg:orig_category":"Arquitectos",
    "sg:phone":"+34 954 57 46 55",
    "sg:postcode":"41018",
    "sg:province":"Sevilla",
    "wof:name":"Becerra Corona Gallardo Arquitectos S.l.",
    "wof:placetype":"venue"
},
  "geometry": {"coordinates":[-5.9769940376,37.3870315552],"type":"Point"}
}