{
  "type": "Feature",
  "properties": {
    "iso:country":"ES",
    "sg:address":"Av Isidor Macabich, 52",
    "sg:city":"Eivissa",
    "sg:orig_category":"Confecci\u00d3n De Trajes Para Se\u00d1oras",
    "sg:phone":"+34 971 31 78 21",
    "sg:postcode":"07800",
    "sg:province":"Islas Baleares",
    "wof:name":"Maria Isabel",
    "wof:placetype":"venue"
},
  "geometry": {"coordinates":[1.425377965,38.9099464417],"type":"Point"}
}