{
  "type": "Feature",
  "properties": {
    "iso:country":"ES",
    "sg:address":"Villa Ant Urb, 15",
    "sg:city":"Pozo Camino",
    "sg:orig_category":"Frutas Y Legumbres Frescas (al Por Mayor)",
    "sg:phone":"+34 959 33 23 60",
    "sg:postcode":"21420",
    "sg:province":"Huelva",
    "wof:name":"S.a.t. Huerta Noble",
    "wof:placetype":"venue"
},
  "geometry": {"coordinates":[-7.3142957687,37.2253875732],"type":"Point"}
}