{
  "type": "Feature",
  "properties": {
    "addr:full":"Calle de Refugio, 18 Ciudad Real Ciudad Real 13004",
    "addr:housenumber":"18",
    "addr:postcode":"13004",
    "addr:street":"Calle De Refugio",
    "iso:country":"ES",
    "sg:address":"Calle de Refugio, 18",
    "sg:city":"Ciudad Real",
    "sg:orig_category":"Comercio, Reparaci\u00d3n De Motocicletas, Bicicletas Y Piezas Sueltas",
    "sg:phone":"+34 926 22 08 86",
    "sg:postcode":"13004",
    "sg:province":"Ciudad Real",
    "wof:name":"Barrera Perales Rafael",
    "wof:placetype":"venue"
},
  "geometry": {"coordinates":[-3.9246659279,38.9875450134],"type":"Point"}
}