{
  "type": "Feature",
  "properties": {
    "addr:full":"Carrer de Pallars, 189 Barcelona Barcelona 08005",
    "addr:housenumber":"189",
    "addr:postcode":"08005",
    "addr:street":"Carrer De Pallars",
    "iso:country":"ES",
    "sg:address":"Carrer de Pallars, 189",
    "sg:city":"Barcelona",
    "sg:orig_category":"Arreglo, Reparaci\u00d3n, Piezas Sueltas De Televisi\u00d3n, V\u00cddeo, Hi",
    "sg:phone":"+34 934 85 10 51",
    "sg:postcode":"08005",
    "sg:province":"Barcelona",
    "wof:name":"Afex Electronics S.a.",
    "wof:placetype":"venue"
},
  "geometry": {"coordinates":[2.1972644329,41.4007835388],"type":"Point"}
}