{
  "type": "Feature",
  "properties": {
    "iso:country":"ES",
    "sg:address":"Calle de Puerto De Somiedo, 10",
    "sg:city":"Gijon",
    "sg:orig_category":"Prot\u00c9sicos Dentales",
    "sg:phone":"+34 985 16 38 40",
    "sg:postcode":"33207",
    "sg:province":"Asturias",
    "wof:name":"Sanchez Echevarria Pedro",
    "wof:placetype":"venue"
},
  "geometry": {"coordinates":[-5.6738419533,43.533657074],"type":"Point"}
}