{
  "type": "Feature",
  "properties": {
    "addr:full":"Avda Alcalde De Lavadores, 88 Bagunda Pontevedra 36214",
    "addr:housenumber":"88",
    "addr:postcode":"36214",
    "addr:street":"Avda Alcalde De Lavadores",
    "iso:country":"ES",
    "sg:address":"Avda Alcalde De Lavadores, 88",
    "sg:city":"Bagunda",
    "sg:orig_category":"Contenedores (mercanc\u00cdas)",
    "sg:phone":"+34 986 27 96 84",
    "sg:postcode":"36214",
    "sg:province":"Pontevedra",
    "wof:name":"Gonzalez Rodriguez Manuel",
    "wof:placetype":"venue"
},
  "geometry": {"coordinates":[-8.6480531693,42.4336204529],"type":"Point"}
}