{
  "type": "Feature",
  "properties": {
    "addr:full":"Calle de Santa Teresa, 10 Carolina Ja\u00e9n 23200",
    "addr:housenumber":"10",
    "addr:postcode":"23200",
    "addr:street":"Calle De Santa Teresa;Jae\u0301N",
    "iso:country":"ES",
    "sg:address":"Calle de Santa Teresa, 10",
    "sg:city":"Carolina",
    "sg:orig_category":"Arquitectos",
    "sg:phone":"+34 953 66 10 09",
    "sg:postcode":"23200",
    "sg:province":"Ja\u00e9n",
    "wof:name":"Ferriz Quesada Francisco",
    "wof:placetype":"venue"
},
  "geometry": {"coordinates":[-3.61470294,38.2755050659],"type":"Point"}
}