{
  "type": "Feature",
  "properties": {
    "addr:full":"Pque Cial San Jeronimo, 20 Sevilla Sevilla 41015",
    "addr:housenumber":"20",
    "addr:postcode":"41015",
    "addr:street":"San Jeronimo",
    "iso:country":"ES",
    "sg:address":"Pque Cial San Jeronimo, 20",
    "sg:city":"Sevilla",
    "sg:orig_category":"Mec\u00c1nico Del Autom\u00d3vil",
    "sg:phone":"+34 954 37 17 33",
    "sg:postcode":"41015",
    "sg:province":"Sevilla",
    "wof:name":"Talleres Vicente Huerta S.l.",
    "wof:placetype":"venue"
},
  "geometry": {"coordinates":[-6.0018129349,37.3876953125],"type":"Point"}
}