{
  "type": "Feature",
  "properties": {
    "addr:full":"Calle de Fray Isidoro De Sevilla, 6 Sevilla Sevilla 41009",
    "addr:housenumber":"6",
    "addr:postcode":"41009",
    "addr:street":"Calle De Fray Isidoro De Sevilla",
    "iso:country":"ES",
    "sg:address":"Calle de Fray Isidoro De Sevilla, 6",
    "sg:city":"Sevilla",
    "sg:orig_category":"Caf\u00c9s, Bares, Cervecer\u00cdas",
    "sg:phone":"+34 954 37 66 57",
    "sg:postcode":"41009",
    "sg:province":"Sevilla",
    "wof:name":"Fray Isidoro Garden S.l.",
    "wof:placetype":"venue"
},
  "geometry": {"coordinates":[-5.986178875,37.4043045044],"type":"Point"}
}