{
  "type": "Feature",
  "properties": {
    "addr:full":"Av Canaliega, S/n El Rocio Huelva 21750",
    "addr:housenumber":"s / n",
    "addr:postcode":"21750",
    "addr:street":"Av Canaliega",
    "iso:country":"ES",
    "sg:address":"Av Canaliega, S/n",
    "sg:city":"El Rocio",
    "sg:orig_category":"Organismos De Turismo",
    "sg:phone":"+34 959 44 26 84",
    "sg:postcode":"21750",
    "sg:province":"Huelva",
    "wof:name":"Ayuntamiento De Almonte",
    "wof:placetype":"venue"
},
  "geometry": {"coordinates":[-6.4888510704,37.1334686279],"type":"Point"}
}