{
  "type": "Feature",
  "properties": {
    "iso:country":"ES",
    "sg:address":"Calle de Emiliano Bernabe, 20",
    "sg:city":"Avila",
    "sg:orig_category":"Peluqueros: De Se\u00d1oras",
    "sg:phone":"+34 920 22 47 52",
    "sg:postcode":"05002",
    "sg:province":"\u00c1vila",
    "wof:name":"Hernandez Martin Maria Angeles",
    "wof:placetype":"venue"
},
  "geometry": {"coordinates":[-4.6980757713,40.6497383118],"type":"Point"}
}