{
  "type": "Feature",
  "properties": {
    "iso:country":"ES",
    "sg:address":"Carr Castanyet, S/n",
    "sg:city":"Santa Coloma De Farners",
    "sg:orig_category":"Cerrajer\u00cda, Ferrallista",
    "sg:phone":"+34 972 84 08 74",
    "sg:postcode":"17430",
    "sg:province":"Girona",
    "wof:name":"Ma\u00f1ach Perajoan Salvador",
    "wof:placetype":"venue"
},
  "geometry": {"coordinates":[2.6601200104,41.8631057739],"type":"Point"}
}