{
  "type": "Feature",
  "properties": {
    "iso:country":"ES",
    "sg:address":"Avda Alange, S/n",
    "sg:city":"Zarza",
    "sg:orig_category":"Negocio De Materiales De Construcci\u00d3n",
    "sg:phone":"+34 924 36 62 02",
    "sg:postcode":"06830",
    "sg:province":"Badajoz",
    "wof:name":"Dominguez Tejada Antonio Javier",
    "wof:placetype":"venue"
},
  "geometry": {"coordinates":[-6.2206230164,38.8185386658],"type":"Point"}
}