{
  "type": "Feature",
  "properties": {
    "iso:country":"ES",
    "sg:address":"Calle de Rio De La Plata, 16",
    "sg:city":"Madrid",
    "sg:orig_category":"Empresas De Carpinter\u00cda Met\u00c1lica",
    "sg:phone":"+34 913 03 95 82",
    "sg:postcode":"28018",
    "sg:province":"Madrid",
    "wof:name":"Cerrajeria Jumar S.l.",
    "wof:placetype":"venue"
},
  "geometry": {"coordinates":[-3.6516699791,40.3871383667],"type":"Point"}
}