{
  "type": "Feature",
  "properties": {
    "addr:full":"Calle de Goikoibarra, 3 Gernika-lumo Vizcaya 48300",
    "addr:housenumber":"3",
    "addr:postcode":"48300",
    "addr:street":"Calle De Goikoibarra",
    "iso:country":"ES",
    "sg:address":"Calle de Goikoibarra, 3",
    "sg:city":"Gernika-lumo",
    "sg:orig_category":"Fabricaci\u00d3n Y Comercio De M\u00c1quinas",
    "sg:phone":"+34 946 25 05 00",
    "sg:postcode":"48300",
    "sg:province":"Vizcaya",
    "wof:name":"Talleres De Guernica S.a.",
    "wof:placetype":"venue"
},
  "geometry": {"coordinates":[-2.6784670353,43.3092536926],"type":"Point"}
}