{
  "type": "Feature",
  "properties": {
    "iso:country":"ES",
    "sg:address":"Calle de Antonio Toledano, 36",
    "sg:city":"Madrid",
    "sg:orig_category":"Bares, Piano",
    "sg:phone":"+34 915 73 73 46",
    "sg:postcode":"28028",
    "sg:province":"Madrid",
    "wof:name":"Multiservicio En Contacto S.l.",
    "wof:placetype":"venue"
},
  "geometry": {"coordinates":[-3.6670041084,40.4230575562],"type":"Point"}
}