{
  "type": "Feature",
  "properties": {
    "iso:country":"ES",
    "sg:address":"Cno. Vell Victoria, 30",
    "sg:city":"El Mal Pas",
    "sg:orig_category":"Inmobiliaria (agencias)",
    "sg:phone":"+34 971 54 51 89",
    "sg:postcode":"07409",
    "sg:province":"Islas Baleares",
    "wof:name":"Adirel S.l.",
    "wof:placetype":"venue"
},
  "geometry": {"coordinates":[3.1468868256,39.866230011],"type":"Point"}
}