{
  "type": "Feature",
  "properties": {
    "iso:country":"ES",
    "sg:address":"Carrer de Can Rabella, S/n",
    "sg:city":"Molins Rei",
    "sg:orig_category":"Quincaller\u00cda (al Por Menor)",
    "sg:phone":"+34 936 68 08 12",
    "sg:postcode":"08750",
    "sg:province":"Barcelona",
    "sg:website":"www.lasguias.com/industriasescobar",
    "wof:name":"Escobar Parra Andres",
    "wof:placetype":"venue"
},
  "geometry": {"coordinates":[2.0130450726,41.4200935364],"type":"Point"}
}