{
  "type": "Feature",
  "properties": {
    "iso:country":"ES",
    "sg:address":"Avda Alcalde Jose Victori Go\u00d1alons, 16",
    "sg:city":"Ceuta",
    "sg:orig_category":"Art\u00cdculos De Regalo (al Por Menor)",
    "sg:phone":"+34 956 51 17 92",
    "sg:postcode":"51001",
    "sg:province":"Ceuta",
    "wof:name":"Arjandas Shiudasani Hero",
    "wof:placetype":"venue"
},
  "geometry": {"coordinates":[-5.3193998337,35.8888816833],"type":"Point"}
}