{
  "type": "Feature",
  "properties": {
    "addr:full":"Calle de Ricardo Ibarreche, 2 Arrigorriaga Vizcaya 48480",
    "addr:housenumber":"2",
    "addr:postcode":"48480",
    "addr:street":"Calle De Ricardo Ibarreche",
    "iso:country":"ES",
    "sg:address":"Calle de Ricardo Ibarreche, 2",
    "sg:city":"Arrigorriaga",
    "sg:orig_category":"Alimentaci\u00d3n General (al Por Menor)",
    "sg:phone":"+34 946 71 39 06",
    "sg:postcode":"48480",
    "sg:province":"Vizcaya",
    "wof:name":"Jose Ignacio Carranza Dominguez",
    "wof:placetype":"venue"
},
  "geometry": {"coordinates":[-2.8875906467,43.2065124512],"type":"Point"}
}