{
  "type": "Feature",
  "properties": {
    "addr:full":"Carrer de Sant Antoni Maria Claret, S/n Molins Rei Barcelona 08750",
    "addr:housenumber":"s / n",
    "addr:postcode":"08750",
    "addr:street":"Carrer De Sant Antoni Maria Claret;Barcelona",
    "iso:country":"ES",
    "sg:address":"Carrer de Sant Antoni Maria Claret, S/n",
    "sg:city":"Molins Rei",
    "sg:orig_category":"Ba\u00d1os Y Duchas P\u00dablicos",
    "sg:phone":"+34 936 80 15 72",
    "sg:postcode":"08750",
    "sg:province":"Barcelona",
    "wof:name":"Ajuntament De Molins De Rei",
    "wof:placetype":"venue"
},
  "geometry": {"coordinates":[2.021099329,41.41015625],"type":"Point"}
}