{
  "type": "Feature",
  "properties": {
    "addr:full":"Avda Danzantes De Huesca (los), 6 Huesca Huesca 22005",
    "addr:housenumber":"6",
    "addr:postcode":"22005",
    "addr:street":"Avda Danzantes De Huesca Los",
    "iso:country":"ES",
    "sg:address":"Avda Danzantes De Huesca (los), 6",
    "sg:city":"Huesca",
    "sg:orig_category":"Comercio, Reparaci\u00d3n De Motocicletas, Bicicletas Y Piezas Sueltas",
    "sg:phone":"+34 974 22 39 47",
    "sg:postcode":"22005",
    "sg:province":"Huesca",
    "wof:name":"Aquilue Ena Jose Maria",
    "wof:placetype":"venue"
},
  "geometry": {"coordinates":[-0.4010390937,42.1388015747],"type":"Point"}
}