{
  "type": "Feature",
  "properties": {
    "addr:full":"Carr Agapit Llobet, 5 Eivissa Islas Baleares 07800",
    "addr:housenumber":"5",
    "addr:postcode":"07800",
    "addr:street":"Carr Agapit Llobet",
    "iso:country":"ES",
    "sg:address":"Carr Agapit Llobet, 5",
    "sg:city":"Eivissa",
    "sg:orig_category":"Comercio, Reparaci\u00d3n De Motocicletas, Bicicletas Y Piezas Sueltas",
    "sg:phone":"+34 971 30 05 16",
    "sg:postcode":"07800",
    "sg:province":"Islas Baleares",
    "wof:name":"Motomon S.l.",
    "wof:placetype":"venue"
},
  "geometry": {"coordinates":[1.4188899994,38.9061164856],"type":"Point"}
}