{
  "type": "Feature",
  "properties": {
    "iso:country":"ES",
    "sg:address":"Calle de Nueva, 51",
    "sg:city":"Vera",
    "sg:orig_category":"Transportes Frigor\u00cdficos",
    "sg:phone":"+34 950 39 09 86",
    "sg:postcode":"04620",
    "sg:province":"Almer\u00eda",
    "wof:name":"Frimugar S.l.",
    "wof:placetype":"venue"
},
  "geometry": {"coordinates":[-1.8702510595,37.2490653992],"type":"Point"}
}