{
  "type": "Feature",
  "properties": {
    "addr:full":"Praz Fonte Dos Ranchos, 46 Lugo Lugo 27004",
    "addr:housenumber":"46",
    "addr:postcode":"27004",
    "addr:street":"Praz Fonte Dos Ranchos",
    "iso:country":"ES",
    "sg:address":"Praz Fonte Dos Ranchos, 46",
    "sg:city":"Lugo",
    "sg:orig_category":"Agencias De Trabajo Temporal",
    "sg:phone":"+34 982 21 31 70",
    "sg:postcode":"27004",
    "sg:province":"Lugo",
    "sg:website":"www.adecco.es",
    "wof:name":"Adecco E.t.t. S.a.",
    "wof:placetype":"venue"
},
  "geometry": {"coordinates":[-7.5761876106,43.0135879517],"type":"Point"}
}