{
  "type": "Feature",
  "properties": {
    "iso:country":"ES",
    "sg:address":"Plaz Fernando Vi, 13",
    "sg:city":"Sevilla",
    "sg:orig_category":"Tintorer\u00cdas, Limpieza En Seco",
    "sg:phone":"+34 954 69 13 17",
    "sg:postcode":"41014",
    "sg:province":"Sevilla",
    "wof:name":"Huerta Perez Maria Teresa",
    "wof:placetype":"venue"
},
  "geometry": {"coordinates":[-5.9596791267,37.3278617859],"type":"Point"}
}