{
  "type": "Feature",
  "properties": {
    "addr:full":"Carrer de Antonio Ricardos, 10 Barcelona Barcelona 08027",
    "addr:housenumber":"10",
    "addr:postcode":"08027",
    "addr:street":"Carrer De Antonio Ricardos",
    "iso:country":"ES",
    "sg:address":"Carrer de Antonio Ricardos, 10",
    "sg:city":"Barcelona",
    "sg:orig_category":"Molduras, Junquillos, Listones Y Molduras Perforadas",
    "sg:phone":"+34 933 49 10 65",
    "sg:postcode":"08027",
    "sg:province":"Barcelona",
    "wof:name":"Camuna Acosta David",
    "wof:placetype":"venue"
},
  "geometry": {"coordinates":[2.1892740726,41.4257469177],"type":"Point"}
}