{
  "type": "Feature",
  "properties": {
    "iso:country":"ES",
    "sg:address":"Calle de Antonio Torrecillas, 11",
    "sg:city":"Vistabella",
    "sg:orig_category":"Panader\u00cdas, Panader\u00cdas",
    "sg:phone":"+34 968 25 14 90",
    "sg:postcode":"30003",
    "sg:province":"Murcia",
    "wof:name":"Perez Perez Paulino",
    "wof:placetype":"venue"
},
  "geometry": {"coordinates":[-1.1186852455,37.9842567444],"type":"Point"}
}