{
  "type": "Feature",
  "properties": {
    "iso:country":"ES",
    "sg:address":"Calle de Berdigon, 30",
    "sg:city":"Huelva",
    "sg:orig_category":"Ropa De Casa (fabricaci\u00d3n, Al Por Mayor)",
    "sg:phone":"+34 959 28 28 48",
    "sg:postcode":"21003",
    "sg:province":"Huelva",
    "wof:name":"Olgarre S.l.",
    "wof:placetype":"venue"
},
  "geometry": {"coordinates":[-6.9484815598,37.2550010681],"type":"Point"}
}