{
  "type": "Feature",
  "properties": {
    "addr:full":"Avda Andalucia, 13 S. Bartolome Torre Huelva 21510",
    "addr:housenumber":"13",
    "addr:postcode":"21510",
    "addr:street":"Avda Andalucia;S. Bartolome Torre",
    "iso:country":"ES",
    "sg:address":"Avda Andalucia, 13",
    "sg:city":"S. Bartolome Torre",
    "sg:orig_category":"Cajas Para Embalar",
    "sg:phone":"+34 959 38 60 52",
    "sg:postcode":"21510",
    "sg:province":"Huelva",
    "wof:name":"Caja Rural Del Sur Sociedad Cooperativa",
    "wof:placetype":"venue"
},
  "geometry": {"coordinates":[-7.1072249413,37.4469451904],"type":"Point"}
}