{
  "type": "Feature",
  "properties": {
    "addr:full":"Carrer de Proven\u00c7a, 26 Hospitalet Llobregat Barcelona 08901",
    "addr:housenumber":"26",
    "addr:postcode":"08901",
    "addr:street":"Carrer De Provenc\u0327A",
    "iso:country":"ES",
    "sg:address":"Carrer de Proven\u00c7a, 26",
    "sg:city":"Hospitalet Llobregat",
    "sg:orig_category":"Transporte En General",
    "sg:phone":"+34 933 37 19 38",
    "sg:postcode":"08901",
    "sg:province":"Barcelona",
    "wof:name":"Navarro Villanueva Ramon",
    "wof:placetype":"venue"
},
  "geometry": {"coordinates":[2.0978229046,41.357421875],"type":"Point"}
}