{
  "type": "Feature",
  "properties": {
    "addr:full":"Calle de San Luis, 83 Sevilla Sevilla 41003",
    "addr:housenumber":"83",
    "addr:postcode":"41003",
    "addr:street":"Calle De San Luis",
    "iso:country":"ES",
    "sg:address":"Calle de San Luis, 83",
    "sg:city":"Sevilla",
    "sg:orig_category":"Librer\u00cdas",
    "sg:phone":"+34 954 90 41 47",
    "sg:postcode":"41003",
    "sg:province":"Sevilla",
    "wof:name":"Nu\u00f1o Garcia Manuel",
    "wof:placetype":"venue"
},
  "geometry": {"coordinates":[-5.9887461662,37.4004402161],"type":"Point"}
}