{
  "type": "Feature",
  "properties": {
    "iso:country":"ES",
    "sg:address":"Calle de Joaquin Lorenzo, 56",
    "sg:city":"Madrid",
    "sg:orig_category":"Grafistas",
    "sg:phone":"+34 913 86 29 77",
    "sg:postcode":"28035",
    "sg:province":"Madrid",
    "wof:name":"Ebproject C.b.",
    "wof:placetype":"venue"
},
  "geometry": {"coordinates":[-3.7297079563,40.4747886658],"type":"Point"}
}