{
  "type": "Feature",
  "properties": {
    "addr:full":"Ctra Estacion (de La), 60 Carretera Estacion Murcia 30540",
    "addr:housenumber":"60",
    "addr:postcode":"30540",
    "addr:street":"Ctra Estacion De La;Carretera Estacion",
    "iso:country":"ES",
    "sg:address":"Ctra Estacion (de La), 60",
    "sg:city":"Carretera Estacion",
    "sg:orig_category":"Trajes Y Adornos De Boda (confecci\u00d3n, Al Por Menor)",
    "sg:phone":"+34 968 77 83 02",
    "sg:postcode":"30540",
    "sg:province":"Murcia",
    "wof:name":"Cano Carpena Jose",
    "wof:placetype":"venue"
},
  "geometry": {"coordinates":[-1.369478941,38.1796684265],"type":"Point"}
}