{
  "type": "Feature",
  "properties": {
    "addr:full":"Zugarreta Kalea, 2 Etxarri-aranatz Navarra 31820",
    "addr:housenumber":"2",
    "addr:postcode":"31820",
    "addr:street":"Zugarreta Kalea",
    "iso:country":"ES",
    "sg:address":"Zugarreta Kalea, 2",
    "sg:city":"Etxarri-aranatz",
    "sg:orig_category":"Vinos Y Licores (venta Al Por Menor)",
    "sg:phone":"+34 948 46 00 14",
    "sg:postcode":"31820",
    "sg:province":"Navarra",
    "wof:name":"Larraza Go\u00f1i Manuel",
    "wof:placetype":"venue"
},
  "geometry": {"coordinates":[-2.0613288879,42.9031600952],"type":"Point"}
}