{
  "type": "Feature",
  "properties": {
    "addr:full":"Rond Sant Pau, 35 Barcelona Barcelona 08015",
    "addr:housenumber":"35",
    "addr:postcode":"08015",
    "addr:street":"Pau",
    "iso:country":"ES",
    "sg:address":"Rond Sant Pau, 35",
    "sg:city":"Barcelona",
    "sg:orig_category":"Florister\u00cdas",
    "sg:phone":"+34 934 43 17 34",
    "sg:postcode":"08015",
    "sg:province":"Barcelona",
    "sg:website":"www.interflora.es/olimpia",
    "wof:name":"Olimpia Art Floral S.l.",
    "wof:placetype":"venue"
},
  "geometry": {"coordinates":[2.1687450409,41.3855895996],"type":"Point"}
}