{
  "type": "Feature",
  "properties": {
    "addr:full":"Pase Cantera (de La), S/n Jaca Huesca 22700",
    "addr:housenumber":"s / n",
    "addr:postcode":"22700",
    "iso:country":"ES",
    "sg:address":"Pase Cantera (de La), S/n",
    "sg:city":"Jaca",
    "sg:orig_category":"Guarder\u00cdas",
    "sg:phone":"+34 974 36 00 55",
    "sg:postcode":"22700",
    "sg:province":"Huesca",
    "wof:name":"Campo Beltran Maria Elena",
    "wof:placetype":"venue"
},
  "geometry": {"coordinates":[-0.5519520044,42.5658493042],"type":"Point"}
}