{
  "type": "Feature",
  "properties": {
    "iso:country":"ES",
    "sg:address":"Crta. Eivissa-portinatx, Km. 0002,3",
    "sg:city":"Eivissa",
    "sg:orig_category":"Negocio De Materiales De Construcci\u00d3n",
    "sg:phone":"+34 971 31 44 08",
    "sg:postcode":"07800",
    "sg:province":"Islas Baleares",
    "wof:name":"Bufi Riera Francisco",
    "wof:placetype":"venue"
},
  "geometry": {"coordinates":[1.4188899994,38.9061164856],"type":"Point"}
}