{
  "type": "Feature",
  "properties": {
    "iso:country":"ES",
    "sg:address":"Calle de Pino (el), 15",
    "sg:city":"Granadilla Abona",
    "sg:orig_category":"Florister\u00cdas",
    "sg:phone":"+34 922 77 30 92",
    "sg:postcode":"38600",
    "sg:province":"Santa Cruz De Tenerife",
    "wof:name":"Yvonne Floristeria Et Cetera S.l.",
    "wof:placetype":"venue"
},
  "geometry": {"coordinates":[-16.5760097504,28.1242027283],"type":"Point"}
}