{
  "type": "Feature",
  "properties": {
    "addr:full":"Rua Rosalia De Castro, 28 Vigo Pontevedra 36201",
    "addr:housenumber":"28",
    "addr:postcode":"36201",
    "addr:street":"Rua Rosalia De Castro",
    "iso:country":"ES",
    "sg:address":"Rua Rosalia De Castro, 28",
    "sg:city":"Vigo",
    "sg:classifiers":[
        {
            "category":"Arts & Performance",
            "subcategory":"Art Gallery",
            "type":"Entertainment"
        }
    ],
    "sg:phone":"+34 986 22 02 56",
    "sg:postcode":"36201",
    "sg:province":"Pontevedra",
    "sg:tags":[
        "arte",
        "de",
        "galer\u00cdas"
    ],
    "wof:name":"Kirlo Vigo S.l.",
    "wof:placetype":"venue"
},
  "geometry": {"coordinates":[-8.7160921097,42.2379112244],"type":"Point"}
}