{
  "type": "Feature",
  "properties": {
    "addr:full":"Trva Uribarri C, 31 Bilbao Vizcaya 48007",
    "addr:housenumber":"31",
    "addr:postcode":"48007",
    "addr:street":"Trva Uribarri C",
    "iso:country":"ES",
    "sg:address":"Trva Uribarri C, 31",
    "sg:city":"Bilbao",
    "sg:orig_category":"Sociedades, Compa\u00d1\u00cdas Aseguradoras",
    "sg:phone":"+34 944 46 61 23",
    "sg:postcode":"48007",
    "sg:province":"Vizcaya",
    "wof:name":"Bilbao Broker Global 5000, S.l.",
    "wof:placetype":"venue"
},
  "geometry": {"coordinates":[-2.9192450047,43.2676506042],"type":"Point"}
}