{
  "type": "Feature",
  "properties": {
    "addr:full":"Ptge Serra I Arola, 16 Barcelona Barcelona 08028",
    "addr:housenumber":"16",
    "addr:postcode":"08028",
    "addr:street":"Ptge Serra;Arola",
    "iso:country":"ES",
    "sg:address":"Ptge Serra I Arola, 16",
    "sg:city":"Barcelona",
    "sg:orig_category":"Laboratorios Y Trabajos De Fotograf\u00cda, V\u00cddeo Y Cine",
    "sg:phone":"+34 933 39 31 41",
    "sg:postcode":"08028",
    "sg:province":"Barcelona",
    "wof:name":"Cadena Fotografica S. A.",
    "wof:placetype":"venue"
},
  "geometry": {"coordinates":[2.1355900764,41.3763084412],"type":"Point"}
}