{
  "type": "Feature",
  "properties": {
    "addr:full":"Avda Mediterraneo, 63 Madrid Madrid 28007",
    "addr:housenumber":"63",
    "addr:postcode":"madrid;28007",
    "addr:street":"Avda Mediterraneo",
    "iso:country":"ES",
    "sg:address":"Avda Mediterraneo, 63",
    "sg:city":"Madrid",
    "sg:orig_category":"Asociaciones Humanitarias, De Cooperaci\u00d3n, De Acci\u00d3n Social",
    "sg:phone":"+34 915 04 45 66",
    "sg:postcode":"28007",
    "sg:province":"Madrid",
    "wof:name":"Asociacion De Recuperacion De Marginados De Madrid",
    "wof:placetype":"venue"
},
  "geometry": {"coordinates":[-3.6669239998,40.4068222046],"type":"Point"}
}