{
  "type": "Feature",
  "properties": {
    "addr:full":"Calle de Martin Laborda, S/n Almeria Almer\u00eda 04009",
    "addr:housenumber":"s / n",
    "addr:postcode":"04009",
    "addr:street":"Calle De Martin Laborda",
    "iso:country":"ES",
    "sg:address":"Calle de Martin Laborda, S/n",
    "sg:city":"Almeria",
    "sg:orig_category":"Naipes, Carteles, Artilugios",
    "sg:phone":"+34 950 14 17 23",
    "sg:postcode":"04009",
    "sg:province":"Almer\u00eda",
    "wof:name":"Serial Serigrafia S.l",
    "wof:placetype":"venue"
},
  "geometry": {"coordinates":[-2.4523789883,36.854888916],"type":"Point"}
}