{
  "type": "Feature",
  "properties": {
    "addr:full":"Poli P.i.barrionuevo, 12 Moraleja Enmedio Madrid 28950",
    "addr:housenumber":"12",
    "addr:postcode":"28950",
    "addr:street":"P.I.Barrionuevo",
    "iso:country":"ES",
    "sg:address":"Poli P.i.barrionuevo, 12",
    "sg:city":"Moraleja Enmedio",
    "sg:orig_category":"Panader\u00cdas, Pasteler\u00cdas, Boller\u00cda Industriale (fabricaci\u00d3n, Al Por Mayor)",
    "sg:phone":"+34 916 09 32 32",
    "sg:postcode":"28950",
    "sg:province":"Madrid",
    "wof:name":"Dispolen S.l.",
    "wof:placetype":"venue"
},
  "geometry": {"coordinates":[-3.8522839546,40.2605247498],"type":"Point"}
}