{
  "type": "Feature",
  "properties": {
    "iso:country":"ES",
    "sg:address":"Plaz Sarriegi De, 4",
    "sg:city":"Donostia-san Sebastian",
    "sg:orig_category":"Cester\u00cda (fabricaci\u00d3n)",
    "sg:phone":"+34 943 42 80 22",
    "sg:postcode":"20003",
    "sg:province":"Guip\u00f9zcoa",
    "wof:name":"Lapazaran Zuloaga Maria Iciar",
    "wof:placetype":"venue"
},
  "geometry": {"coordinates":[-1.9837969542,43.3229560852],"type":"Point"}
}