{
  "type": "Feature",
  "properties": {
    "addr:full":"Av Catalunya, 52 Mont-roig Camp Tarragona 43300",
    "addr:housenumber":"52",
    "addr:postcode":"43300",
    "addr:street":"Av Catalunya",
    "iso:country":"ES",
    "sg:address":"Av Catalunya, 52",
    "sg:city":"Mont-roig Camp",
    "sg:orig_category":"Empresas De Desmonte",
    "sg:phone":"+34 977 83 77 18",
    "sg:postcode":"43300",
    "sg:province":"Tarragona",
    "wof:name":"Excavaciones Hernandez Serrano,s.l",
    "wof:placetype":"venue"
},
  "geometry": {"coordinates":[0.9630820155,41.0885276794],"type":"Point"}
}