{
  "type": "Feature",
  "properties": {
    "iso:country":"ES",
    "sg:address":"Av Meridiana, 296",
    "sg:city":"Barcelona",
    "sg:orig_category":"Caf\u00c9s, Bares, Cervecer\u00cdas",
    "sg:phone":"+34 933 51 31 06",
    "sg:postcode":"08027",
    "sg:province":"Barcelona",
    "wof:name":"Lopez Diaz Miguel Angel",
    "wof:placetype":"venue"
},
  "geometry": {"coordinates":[2.1871829033,41.4223899841],"type":"Point"}
}