{
  "type": "Feature",
  "properties": {
    "iso:country":"ES",
    "sg:address":"Calle de Dehesa, S/n",
    "sg:city":"Pulgar",
    "sg:orig_category":"Mec\u00c1nico Del Autom\u00d3vil",
    "sg:phone":"+34 925 29 22 26",
    "sg:postcode":"45125",
    "sg:province":"Toledo",
    "wof:name":"Diaz Gamero Jesus",
    "wof:placetype":"venue"
},
  "geometry": {"coordinates":[-4.1557455063,39.6899261475],"type":"Point"}
}