{
  "type": "Feature",
  "properties": {
    "iso:country":"ES",
    "sg:address":"Ctra. Nal. 240, Km. 0017,0",
    "sg:city":"Valls",
    "sg:orig_category":"Restaurantes",
    "sg:phone":"+34 977 60 13 50",
    "sg:postcode":"43800",
    "sg:province":"Tarragona",
    "wof:name":"Felix Hotel Residencia S.l.",
    "wof:placetype":"venue"
},
  "geometry": {"coordinates":[1.2525299788,41.2871513367],"type":"Point"}
}