{
  "type": "Feature",
  "properties": {
    "addr:full":"Calle de Villafria, 7 Oviedo Asturias 33008",
    "addr:housenumber":"7",
    "addr:postcode":"33008",
    "addr:street":"Calle De Villafria",
    "iso:country":"ES",
    "sg:address":"Calle de Villafria, 7",
    "sg:city":"Oviedo",
    "sg:orig_category":"Inform\u00c1tica, Ofim\u00c1tica (estudios, Asesor\u00cda, Ingenier\u00cda, Formaci\u00d3n)",
    "sg:phone":"+34 985 21 94 21",
    "sg:postcode":"33008",
    "sg:province":"Asturias",
    "wof:name":"Electronic Data System Espa\u00f1a S.a.",
    "wof:placetype":"venue"
},
  "geometry": {"coordinates":[-5.8357081413,43.3549194336],"type":"Point"}
}