{
  "type": "Feature",
  "properties": {
    "iso:country":"ES",
    "sg:address":"Calle de Alvarez Abellan, 25",
    "sg:city":"Madrid",
    "sg:orig_category":"Plomeros",
    "sg:phone":"+34 915 25 83 15",
    "sg:postcode":"28025",
    "sg:province":"Madrid",
    "wof:name":"Lucas Rodriguez Jose Javier De",
    "wof:placetype":"venue"
},
  "geometry": {"coordinates":[-3.7315475941,40.3848381042],"type":"Point"}
}