{
  "type": "Feature",
  "properties": {
    "addr:full":"Carrer de Ripoll, 71 Vic Barcelona 08500",
    "addr:housenumber":"71",
    "addr:postcode":"08500",
    "addr:street":"Carrer De Ripoll",
    "iso:country":"ES",
    "sg:address":"Carrer de Ripoll, 71",
    "sg:city":"Vic",
    "sg:orig_category":"Frutas Y Legumbres Frescas (al Por Mayor)",
    "sg:phone":"+34 938 86 16 37",
    "sg:postcode":"08500",
    "sg:province":"Barcelona",
    "wof:name":"Eixfruits S.l.",
    "wof:placetype":"venue"
},
  "geometry": {"coordinates":[2.2578039169,41.9469223022],"type":"Point"}
}