{
  "type": "Feature",
  "properties": {
    "addr:full":"Calle de Viera Y Clavijo, 10 Palmas De Gran Canaria Las Palmas 35002",
    "addr:housenumber":"10",
    "addr:postcode":"35002",
    "addr:street":"Calle De Viera Y Clavijo",
    "iso:country":"ES",
    "sg:address":"Calle de Viera Y Clavijo, 10",
    "sg:city":"Palmas De Gran Canaria",
    "sg:orig_category":"Abogados",
    "sg:phone":"+34 928 38 39 52",
    "sg:postcode":"35002",
    "sg:province":"Las Palmas",
    "wof:name":"Santana Fuentes Carmen Delia",
    "wof:placetype":"venue"
},
  "geometry": {"coordinates":[-15.4174165726,28.1060829163],"type":"Point"}
}