{
  "type": "Feature",
  "properties": {
    "iso:country":"ES",
    "sg:address":"Pase Maria Agustin, 26",
    "sg:city":"Zaragoza",
    "sg:orig_category":"Organizaciones Internacionales",
    "sg:phone":"+34 976 28 22 42",
    "sg:postcode":"50004",
    "sg:province":"Zaragoza",
    "wof:name":"Fundacion Disminuidos Fisicos De Aragon",
    "wof:placetype":"venue"
},
  "geometry": {"coordinates":[-0.8916190267,41.6522483826],"type":"Point"}
}