{
  "type": "Feature",
  "properties": {
    "addr:full":"Calle de Capitan, 29 Osuna Sevilla 41640",
    "addr:housenumber":"29",
    "addr:postcode":"41640",
    "addr:street":"Calle De Capitan",
    "iso:country":"ES",
    "sg:address":"Calle de Capitan, 29",
    "sg:city":"Osuna",
    "sg:orig_category":"Laboratorios",
    "sg:phone":"+34 955 82 04 87",
    "sg:postcode":"41640",
    "sg:province":"Sevilla",
    "wof:name":"Agrocer S.l.",
    "wof:placetype":"venue"
},
  "geometry": {"coordinates":[-5.0997333527,37.2338371277],"type":"Point"}
}