{
  "type": "Feature",
  "properties": {
    "addr:full":"Carrer de Pau Casals, 74 Ametlla Mar Tarragona 43860",
    "addr:housenumber":"74",
    "addr:postcode":"43860",
    "addr:street":"Carrer De Pau Casals",
    "iso:country":"ES",
    "sg:address":"Carrer de Pau Casals, 74",
    "sg:city":"Ametlla Mar",
    "sg:classifiers":[
        {
            "category":"Recreation",
            "type":"Entertainment"
        }
    ],
    "sg:phone":"+34 977 45 63 04",
    "sg:postcode":"43860",
    "sg:province":"Tarragona",
    "sg:tags":[
        "caza",
        "pr\u00c1ctica",
        "la",
        "de",
        "pesca",
        "y"
    ],
    "wof:name":"Garcia Pasto C.b.",
    "wof:placetype":"venue"
},
  "geometry": {"coordinates":[0.804610014,40.8835716248],"type":"Point"}
}