{
  "type": "Feature",
  "properties": {
    "addr:full":"Luga Torre Nicolas Perez, S/n Perin Murcia 30396",
    "addr:postcode":"30396",
    "addr:street":"S / N Perin",
    "iso:country":"ES",
    "sg:address":"Luga Torre Nicolas Perez, S/n",
    "sg:city":"Perin",
    "sg:orig_category":"Organizaci\u00d3n De Actos, Seminarios Y Congresos",
    "sg:phone":"+34 968 16 32 21",
    "sg:postcode":"30396",
    "sg:province":"Murcia",
    "wof:name":"Gastroeventos S.l.",
    "wof:placetype":"venue"
},
  "geometry": {"coordinates":[-1.1008930206,37.6441917419],"type":"Point"}
}