{
  "type": "Feature",
  "properties": {
    "addr:full":"Pol Ind Plazaola Manzana E, 14 Aizoain Navarra 31195",
    "addr:housenumber":"14",
    "addr:postcode":"31195",
    "addr:street":"E",
    "iso:country":"ES",
    "sg:address":"Pol Ind Plazaola Manzana E, 14",
    "sg:city":"Aizoain",
    "sg:orig_category":"Art\u00cdculos De Aluminio",
    "sg:phone":"+34 948 30 23 11",
    "sg:postcode":"31195",
    "sg:province":"Navarra",
    "wof:name":"Carpinteria De Aluminio Aldaun S.l",
    "wof:placetype":"venue"
},
  "geometry": {"coordinates":[-1.6867979765,42.8470611572],"type":"Point"}
}