{
  "type": "Feature",
  "properties": {
    "addr:full":"Avd Poeta M. Reina, 52 Puente-genil C\u00f3rdoba 14500",
    "addr:housenumber":"52",
    "addr:postcode":"14500",
    "addr:street":"Avd Poeta M. Reina;Co\u0301Rdoba",
    "iso:country":"ES",
    "sg:address":"Avd Poeta M. Reina, 52",
    "sg:city":"Puente-genil",
    "sg:orig_category":"Arquitectos",
    "sg:phone":"+34 957 60 60 28",
    "sg:postcode":"14500",
    "sg:province":"C\u00f3rdoba",
    "wof:name":"Montero Morales Arquitectos S.l.",
    "wof:placetype":"venue"
},
  "geometry": {"coordinates":[-4.7659068108,37.3920478821],"type":"Point"}
}