{
  "type": "Feature",
  "properties": {
    "addr:full":"Avda Hispanidad (de La), 10 Fuenlabrada Madrid 28945",
    "addr:housenumber":"10",
    "addr:postcode":"28945",
    "addr:street":"Avda Hispanidad De La",
    "iso:country":"ES",
    "sg:address":"Avda Hispanidad (de La), 10",
    "sg:city":"Fuenlabrada",
    "sg:orig_category":"Electrodom\u00c9sticos (al Por Menor)",
    "sg:phone":"+34 916 06 22 60",
    "sg:postcode":"28945",
    "sg:province":"Madrid",
    "wof:name":"Madue\u00f1o Avila Juan Antonio",
    "wof:placetype":"venue"
},
  "geometry": {"coordinates":[-3.7871649265,40.2926902771],"type":"Point"}
}