{
  "type": "Feature",
  "properties": {
    "iso:country":"ES",
    "sg:address":"Avda Del Pais Valencia, 13",
    "sg:city":"Vinaros",
    "sg:orig_category":"Motores Diessel",
    "sg:phone":"+34 964 45 58 61",
    "sg:postcode":"12500",
    "sg:province":"Castell\u00f3n",
    "wof:name":"Buenaventura Del Mar S.l.",
    "wof:placetype":"venue"
},
  "geometry": {"coordinates":[0.4747200012,40.4679603577],"type":"Point"}
}