{
  "type": "Feature",
  "properties": {
    "addr:full":"Calle de Independencia, 22 Oviedo Asturias 33004",
    "addr:housenumber":"22",
    "addr:postcode":"33004",
    "addr:street":"Calle De Independencia",
    "iso:country":"ES",
    "sg:address":"Calle de Independencia, 22",
    "sg:city":"Oviedo",
    "sg:orig_category":"M\u00c9dicos: An\u00c1lisis Cl\u00cdnicos",
    "sg:phone":"+34 985 24 35 53",
    "sg:postcode":"33004",
    "sg:province":"Asturias",
    "wof:name":"Estrada Fernandez Ana",
    "wof:placetype":"venue"
},
  "geometry": {"coordinates":[-5.855465889,43.3648529053],"type":"Point"}
}