{
  "type": "Feature",
  "properties": {
    "addr:full":"Avda Mancha (de La), 1 Leganes Madrid 28911",
    "addr:housenumber":"1",
    "addr:postcode":"28911",
    "addr:street":"Avda Mancha De La",
    "iso:country":"ES",
    "sg:address":"Avda Mancha (de La), 1",
    "sg:city":"Leganes",
    "sg:orig_category":"Cerrajer\u00cda, Ferrallista",
    "sg:phone":"+34 916 87 78 68",
    "sg:postcode":"28911",
    "sg:province":"Madrid",
    "wof:name":"Pablos Altamirano Marcial",
    "wof:placetype":"venue"
},
  "geometry": {"coordinates":[-3.7586700916,40.3285331726],"type":"Point"}
}