{
  "type": "Feature",
  "properties": {
    "iso:country":"ES",
    "sg:address":"Calle de Mariano Benlliure, 99",
    "sg:city":"Sevilla",
    "sg:orig_category":"Animales (al Por Menor)",
    "sg:phone":"+34 954 57 28 56",
    "sg:postcode":"41005",
    "sg:province":"Sevilla",
    "wof:name":"Macias Ruiz Jose Luis",
    "wof:placetype":"venue"
},
  "geometry": {"coordinates":[-5.962790966,37.3818817139],"type":"Point"}
}