{
  "type": "Feature",
  "properties": {
    "addr:full":"Calle de Toledo, 57 Alacant Alicante 03002",
    "addr:housenumber":"57",
    "addr:postcode":"03002",
    "addr:street":"Calle De Toledo",
    "iso:country":"ES",
    "sg:address":"Calle de Toledo, 57",
    "sg:city":"Alacant",
    "sg:orig_category":"Comidas Por Encargo, Organizaci\u00d3n De Recepciones",
    "sg:phone":"+34 965 20 98 03",
    "sg:postcode":"03002",
    "sg:province":"Alicante",
    "wof:name":"Bernabeu Plaza Vicente",
    "wof:placetype":"venue"
},
  "geometry": {"coordinates":[-0.480347991,38.3465919495],"type":"Point"}
}