{
  "type": "Feature",
  "properties": {
    "addr:full":"Calle de Fray Ceferino, 52 Oviedo Asturias 33011",
    "addr:housenumber":"52",
    "addr:postcode":"33011",
    "addr:street":"Calle De Fray Ceferino",
    "iso:country":"ES",
    "sg:address":"Calle de Fray Ceferino, 52",
    "sg:city":"Oviedo",
    "sg:orig_category":"Cajas Para Embalar",
    "sg:phone":"+34 985 11 05 08",
    "sg:postcode":"33011",
    "sg:province":"Asturias",
    "wof:name":"Caja Rural De Asturias",
    "wof:placetype":"venue"
},
  "geometry": {"coordinates":[-5.8241991997,43.3843231201],"type":"Point"}
}