{
  "type": "Feature",
  "properties": {
    "iso:country":"ES",
    "sg:address":"Carr Tenor Salvador Alejos, 6",
    "sg:city":"Picanya",
    "sg:orig_category":"Electricidad: Instaladores",
    "sg:phone":"+34 961 59 30 51",
    "sg:postcode":"46210",
    "sg:province":"Valencia",
    "wof:name":"Martinez Garces Vicente",
    "wof:placetype":"venue"
},
  "geometry": {"coordinates":[-0.432814002,39.4351959229],"type":"Point"}
}