{
  "type": "Feature",
  "properties": {
    "iso:country":"ES",
    "sg:address":"Carrer de Beethoven, 39",
    "sg:city":"Santa Coloma De Gramenet",
    "sg:orig_category":"Mec\u00c1nico Del Autom\u00d3vil",
    "sg:phone":"+34 934 68 17 23",
    "sg:postcode":"08922",
    "sg:province":"Barcelona",
    "wof:name":"Llobet Yll Ana Luisa",
    "wof:placetype":"venue"
},
  "geometry": {"coordinates":[2.217799902,41.451965332],"type":"Point"}
}