{
  "type": "Feature",
  "properties": {
    "iso:country":"ES",
    "sg:address":"Carr Ausias March, 27",
    "sg:city":"Almussafes",
    "sg:orig_category":"Papeler\u00cdas, Librer\u00cdas",
    "sg:phone":"+34 961 78 26 20",
    "sg:postcode":"46440",
    "sg:province":"Valencia",
    "wof:name":"Carioca Almusafes S.l.",
    "wof:placetype":"venue"
},
  "geometry": {"coordinates":[-0.4143289924,39.292350769],"type":"Point"}
}