{
  "type": "Feature",
  "properties": {
    "addr:full":"Calle de Jesus Del Gran Poder, 4 Avila \u00c1vila 05003",
    "addr:housenumber":"4",
    "addr:postcode":"05003",
    "addr:street":"Calle De Jesus Del Gran Poder;A\u0301Vila",
    "iso:country":"ES",
    "sg:address":"Calle de Jesus Del Gran Poder, 4",
    "sg:city":"Avila",
    "sg:orig_category":"Ropa Para Se\u00d1oras Y Caballeros (al Por Menor)",
    "sg:phone":"+34 920 25 34 46",
    "sg:postcode":"05003",
    "sg:province":"\u00c1vila",
    "wof:name":"Padilla Caballero Julia",
    "wof:placetype":"venue"
},
  "geometry": {"coordinates":[-4.6964049339,40.6525382996],"type":"Point"}
}