{
  "type": "Feature",
  "properties": {
    "addr:full":"Calle de Profesor Blanco, 18 Valencia Valencia 46014",
    "addr:housenumber":"18",
    "addr:postcode":"46014",
    "addr:street":"Calle De Profesor Blanco",
    "iso:country":"ES",
    "sg:address":"Calle de Profesor Blanco, 18",
    "sg:city":"Valencia",
    "sg:orig_category":"Marroquiner\u00cda (confecci\u00d3n)",
    "sg:phone":"+34 963 57 90 45",
    "sg:postcode":"46014",
    "sg:province":"Valencia",
    "wof:name":"Marin Rueda Antonio",
    "wof:placetype":"venue"
},
  "geometry": {"coordinates":[-0.3997980058,39.457901001],"type":"Point"}
}