{
  "type": "Feature",
  "properties": {
    "iso:country":"ES",
    "sg:address":"Calle de Villafuerte, 12",
    "sg:city":"Malaga",
    "sg:orig_category":"Cristaler\u00cdas",
    "sg:phone":"+34 952 29 03 76",
    "sg:postcode":"29017",
    "sg:province":"M\u00e1laga",
    "wof:name":"Segado Altillo Juan",
    "wof:placetype":"venue"
},
  "geometry": {"coordinates":[-4.359662056,36.7218170166],"type":"Point"}
}