{
  "type": "Feature",
  "properties": {
    "addr:full":"Calle de Juan Carlos I, S/n Alhaurin Torre M\u00e1laga 29130",
    "addr:housenumber":"s",
    "addr:postcode":"29130",
    "addr:street":"Calle De Juan Carlos I;/ N Alhaurin Torre Ma\u0301Laga",
    "iso:country":"ES",
    "sg:address":"Calle de Juan Carlos I, S/n",
    "sg:city":"Alhaurin Torre",
    "sg:orig_category":"Centros De Educaci\u00d3n Especial",
    "sg:phone":"+34 952 41 04 94",
    "sg:postcode":"29130",
    "sg:province":"M\u00e1laga",
    "wof:name":"Junta De Andalucia",
    "wof:placetype":"venue"
},
  "geometry": {"coordinates":[-4.5684390068,36.6613006592],"type":"Point"}
}