{
  "type": "Feature",
  "properties": {
    "iso:country":"ES",
    "sg:address":"Calle de Najera (de), 1",
    "sg:city":"Boadilla Del Monte",
    "sg:orig_category":"Empresas De Vigilancia, Guardia Y Protecci\u00d3n",
    "sg:phone":"+34 916 32 10 47",
    "sg:postcode":"28660",
    "sg:province":"Madrid",
    "wof:name":"Prosecom S.l.",
    "wof:placetype":"venue"
},
  "geometry": {"coordinates":[-3.8811039925,40.4058609009],"type":"Point"}
}