{
  "type": "Feature",
  "properties": {
    "iso:country":"ES",
    "sg:address":"Calle de San Clemente, 1",
    "sg:city":"Valencia",
    "sg:orig_category":"Internados & Ense\u00d1anza Privada",
    "sg:phone":"+34 963 47 32 34",
    "sg:postcode":"46015",
    "sg:province":"Valencia",
    "wof:name":"Compa\u00d1ia Hijas De La Caridad De S Vicente De Paul Prov De Sevilla Cdad Casa S Vicente De Paul Sevill",
    "wof:placetype":"venue"
},
  "geometry": {"coordinates":[-0.4036999941,39.489238739],"type":"Point"}
}