{
  "type": "Feature",
  "properties": {
    "iso:country":"ES",
    "sg:address":"Plaz Ibiza, 12",
    "sg:city":"Almeria",
    "sg:orig_category":"Comadronas",
    "sg:phone":"+34 950 24 31 60",
    "sg:postcode":"04004",
    "sg:province":"Almer\u00eda",
    "wof:name":"Quesada Ortega Rosa Maria",
    "wof:placetype":"venue"
},
  "geometry": {"coordinates":[-2.4585959911,36.8344573975],"type":"Point"}
}