{
  "type": "Feature",
  "properties": {
    "addr:full":"Avda Fronteras, 3 Torrejon Ardoz Madrid 28850",
    "addr:housenumber":"3",
    "addr:postcode":"28850",
    "addr:street":"Avda Fronteras",
    "iso:country":"ES",
    "sg:address":"Avda Fronteras, 3",
    "sg:city":"Torrejon Ardoz",
    "sg:orig_category":"Cajas De Ahorro",
    "sg:phone":"+34 916 78 01 57",
    "sg:postcode":"28850",
    "sg:province":"Madrid",
    "wof:name":"Caja De Ahorros Y Monte De Piedad De Navarra",
    "wof:placetype":"venue"
},
  "geometry": {"coordinates":[-3.4834029675,40.4572715759],"type":"Point"}
}