{
  "type": "Feature",
  "properties": {
    "iso:country":"ES",
    "sg:address":"Calle de San Marcos, 26",
    "sg:city":"Valverde Jucar",
    "sg:orig_category":"Quincaller\u00cda (al Por Menor)",
    "sg:phone":"+34 969 20 10 05",
    "sg:postcode":"16100",
    "sg:province":"Cuenca",
    "wof:name":"Mucoci S.l.",
    "wof:placetype":"venue"
},
  "geometry": {"coordinates":[-2.2192876339,39.717754364],"type":"Point"}
}