{
  "type": "Feature",
  "properties": {
    "addr:full":"Calle de Henao, 16 Bilbao Vizcaya 48009",
    "addr:housenumber":"16",
    "addr:postcode":"48009",
    "addr:street":"Calle De Henao",
    "iso:country":"ES",
    "sg:address":"Calle de Henao, 16",
    "sg:city":"Bilbao",
    "sg:orig_category":"Retoques De Vestidos",
    "sg:phone":"+34 944 24 68 65",
    "sg:postcode":"48009",
    "sg:province":"Vizcaya",
    "wof:name":"La Aguja De Oro C.b",
    "wof:placetype":"venue"
},
  "geometry": {"coordinates":[-2.9312999249,43.264629364],"type":"Point"}
}