{
  "type": "Feature",
  "properties": {
    "iso:country":"ES",
    "sg:address":"Avda Martin Palomino, 58",
    "sg:city":"Plasencia",
    "sg:orig_category":"Electricidad: Equipos Industriales, Componentes (fabricaci\u00d3n)",
    "sg:phone":"+34 927 41 88 10",
    "sg:postcode":"10600",
    "sg:province":"C\u00e1ceres",
    "sg:website":"www.electrofilbadajoz.com",
    "wof:name":"Electrofil Oeste Distribucion S.i.",
    "wof:placetype":"venue"
},
  "geometry": {"coordinates":[-6.1094651222,40.0102577209],"type":"Point"}
}