{
  "type": "Feature",
  "properties": {
    "addr:full":"Calle de Alozaina, 23 Malaga M\u00e1laga 29006",
    "addr:housenumber":"23",
    "addr:postcode":"29006",
    "addr:street":"Calle De Alozaina;Ma\u0301Laga",
    "iso:country":"ES",
    "sg:address":"Calle de Alozaina, 23",
    "sg:city":"Malaga",
    "sg:orig_category":"Laboratorios Y Cl\u00cdnicas Veterinarias",
    "sg:phone":"+34 952 34 03 17",
    "sg:postcode":"29006",
    "sg:province":"M\u00e1laga",
    "sg:website":"www.animalandia/turincon.es",
    "wof:name":"Animal Guay S.l.",
    "wof:placetype":"venue"
},
  "geometry": {"coordinates":[-4.4493126869,36.7096366882],"type":"Point"}
}