{
  "type": "Feature",
  "properties": {
    "iso:country":"ES",
    "sg:address":"Calle de Perez Medina, 42",
    "sg:city":"Alacant",
    "sg:orig_category":"Producci\u00d3n, Venta De Productos De Agricultura Biol\u00d3gica",
    "sg:phone":"+34 965 92 78 65",
    "sg:postcode":"03007",
    "sg:province":"Alicante",
    "wof:name":"Produccion Agricola Del Mediterraneo S.l.",
    "wof:placetype":"venue"
},
  "geometry": {"coordinates":[-0.4978129864,38.3398742676],"type":"Point"}
}