{
  "type": "Feature",
  "properties": {
    "addr:full":"Calle de Cadiz, 64 Valencia Valencia 46006",
    "addr:housenumber":"64",
    "addr:postcode":"46006",
    "addr:street":"Calle De Cadiz",
    "iso:country":"ES",
    "sg:address":"Calle de Cadiz, 64",
    "sg:city":"Valencia",
    "sg:orig_category":"Mercer\u00cda, Lencer\u00cda (al Por Menor)",
    "sg:phone":"+34 963 74 40 28",
    "sg:postcode":"46006",
    "sg:province":"Valencia",
    "wof:name":"Carbonell Gil Concepcion",
    "wof:placetype":"venue"
},
  "geometry": {"coordinates":[-0.3729551136,39.4608726501],"type":"Point"}
}