{
  "type": "Feature",
  "properties": {
    "addr:full":"Carr Vallcalent, 61 Lleida Lleida 25006",
    "addr:housenumber":"61",
    "addr:postcode":"25006",
    "addr:street":"Carr Vallcalent",
    "iso:country":"ES",
    "sg:address":"Carr Vallcalent, 61",
    "sg:city":"Lleida",
    "sg:orig_category":"Molduras, Junquillos, Listones Y Molduras Perforadas",
    "sg:phone":"+34 973 28 01 07",
    "sg:postcode":"25006",
    "sg:province":"Lleida",
    "wof:name":"Vazquez Mu\u00f1oz Manuel",
    "wof:placetype":"venue"
},
  "geometry": {"coordinates":[0.6160920262,41.6179199219],"type":"Point"}
}