{
  "type": "Feature",
  "properties": {
    "addr:full":"Calle de Real, 2 Ballesteros De Calatrava Ciudad Real 13432",
    "addr:housenumber":"2",
    "addr:postcode":"13432",
    "addr:street":"Calle De Real",
    "iso:country":"ES",
    "sg:address":"Calle de Real, 2",
    "sg:city":"Ballesteros De Calatrava",
    "sg:orig_category":"Cajas Para Embalar",
    "sg:phone":"+34 926 84 20 06",
    "sg:postcode":"13432",
    "sg:province":"Ciudad Real",
    "wof:name":"Caja Rural De Ciudad Real",
    "wof:placetype":"venue"
},
  "geometry": {"coordinates":[-3.9453539848,38.8349571228],"type":"Point"}
}