{
  "type": "Feature",
  "properties": {
    "iso:country":"ES",
    "sg:address":"Carrer de Santiago Rusi\u00d1ol, 33",
    "sg:city":"S. Cugat Valles",
    "sg:orig_category":"Ropa Para Se\u00d1oras (al Por Menor)",
    "sg:phone":"+34 936 74 04 31",
    "sg:postcode":"08172",
    "sg:province":"Barcelona",
    "wof:name":"Alvarez Hurtado Carlos Enrique",
    "wof:placetype":"venue"
},
  "geometry": {"coordinates":[2.0833158493,41.4725494385],"type":"Point"}
}