{
  "type": "Feature",
  "properties": {
    "iso:country":"ES",
    "sg:address":"Calle de Mompo, 2",
    "sg:city":"Campo Criptana",
    "sg:orig_category":"Productores Recolectores, Venta Directa De Vinos",
    "sg:phone":"+34 926 58 96 50",
    "sg:postcode":"13610",
    "sg:province":"Ciudad Real",
    "wof:name":"Mostos Vinos Y Alcoholes S.a.",
    "wof:placetype":"venue"
},
  "geometry": {"coordinates":[-3.1196939945,39.3956031799],"type":"Point"}
}