{
  "type": "Feature",
  "properties": {
    "addr:full":"Ctra. Marcilla-villafranca, Km. 0002,8 Marcilla Navarra 31340",
    "addr:postcode":"31340",
    "addr:street":"Ctra. Marcilla-Villafranca Km. 0002,8;Navarra",
    "iso:country":"ES",
    "sg:address":"Ctra. Marcilla-villafranca, Km. 0002,8",
    "sg:city":"Marcilla",
    "sg:orig_category":"Agricultores, Agricultores",
    "sg:phone":"+34 948 75 70 75",
    "sg:postcode":"31340",
    "sg:province":"Navarra",
    "wof:name":"Agropecuaria Obanos S.a.",
    "wof:placetype":"venue"
},
  "geometry": {"coordinates":[-1.7365756035,42.3256416321],"type":"Point"}
}