{
  "type": "Feature",
  "properties": {
    "addr:full":"Calle de Ruda, 6 Madrid Madrid 28005",
    "addr:housenumber":"6",
    "addr:postcode":"28005",
    "addr:street":"Calle De Ruda",
    "iso:country":"ES",
    "sg:address":"Calle de Ruda, 6",
    "sg:city":"Madrid",
    "sg:orig_category":"Producci\u00d3n, Distribuci\u00d3n De Electricidad",
    "sg:phone":"+34 913 65 26 56",
    "sg:postcode":"28005",
    "sg:province":"Madrid",
    "wof:name":"Li  Xiao Kuan",
    "wof:placetype":"venue"
},
  "geometry": {"coordinates":[-3.7079150677,40.4105644226],"type":"Point"}
}