{
  "type": "Feature",
  "properties": {
    "iso:country":"ES",
    "sg:address":"Calle de Luis Carvajal, 23",
    "sg:city":"Jodar",
    "sg:orig_category":"Ropa Para Ni\u00d1os (al Por Menor)",
    "sg:phone":"+34 953 78 56 70",
    "sg:postcode":"23500",
    "sg:province":"Ja\u00e9n",
    "wof:name":"Ruiz Jimenez Mateo",
    "wof:placetype":"venue"
},
  "geometry": {"coordinates":[-3.3504340649,37.8394470215],"type":"Point"}
}