{
  "type": "Feature",
  "properties": {
    "iso:country":"ES",
    "sg:address":"C/ Escoles, 18",
    "sg:city":"Cerdanyola Valles",
    "sg:orig_category":"Centros Comerciales Y Grandes Tiendas",
    "sg:phone":"+34 936 92 73 49",
    "sg:postcode":"08290",
    "sg:province":"Barcelona",
    "wof:name":"Hierro Blanco Javier",
    "wof:placetype":"venue"
},
  "geometry": {"coordinates":[2.1470150948,41.4924812317],"type":"Point"}
}