{
  "type": "Feature",
  "properties": {
    "addr:full":"Ermitaga\u00f1a, 5 Iru\u00f1a Navarra 31008",
    "addr:housenumber":"5",
    "addr:postcode":"31008",
    "addr:street":"Ermitagan\u0303A",
    "iso:country":"ES",
    "sg:address":"Ermitaga\u00f1a, 5",
    "sg:city":"Iru\u00f1a",
    "sg:orig_category":"Sociedades, Compa\u00d1\u00cdas Aseguradoras",
    "sg:phone":"+34 948 27 60 62",
    "sg:postcode":"31008",
    "sg:province":"Navarra",
    "sg:website":"www.dkvseguros.com",
    "wof:name":"Dkv Seguros Y Reaseguros Sae",
    "wof:placetype":"venue"
},
  "geometry": {"coordinates":[-1.6700479984,42.8096237183],"type":"Point"}
}