{
  "type": "Feature",
  "properties": {
    "iso:country":"ES",
    "sg:address":"Pla\u00c7 Universitat, 47",
    "sg:city":"Cervera",
    "sg:orig_category":"Farmacias",
    "sg:phone":"+34 973 53 02 26",
    "sg:postcode":"25200",
    "sg:province":"Lleida",
    "wof:name":"Goma Balcells Mercedes",
    "wof:placetype":"venue"
},
  "geometry": {"coordinates":[1.2740499973,41.6712913513],"type":"Point"}
}