{
  "type": "Feature",
  "properties": {
    "addr:full":"Calle de Juan De Urbieta, 42 Madrid Madrid 28007",
    "addr:housenumber":"42",
    "addr:postcode":"madrid;28007",
    "addr:street":"Calle De Juan De Urbieta",
    "iso:country":"ES",
    "sg:address":"Calle de Juan De Urbieta, 42",
    "sg:city":"Madrid",
    "sg:orig_category":"Art\u00cdculos De Regalo (al Por Menor)",
    "sg:phone":"+34 915 13 00 23",
    "sg:postcode":"28007",
    "sg:province":"Madrid",
    "wof:name":"Daswani  Naresh Mohandas",
    "wof:placetype":"venue"
},
  "geometry": {"coordinates":[-3.6755750179,40.4066047668],"type":"Point"}
}