{
  "type": "Feature",
  "properties": {
    "iso:country":"ES",
    "sg:address":"Calle de Santa Clara, 8",
    "sg:city":"Oviedo",
    "sg:orig_category":"Administradores De Bienes Y Delegados De Comunidades De Propietarios",
    "sg:phone":"+34 985 20 39 06",
    "sg:postcode":"33001",
    "sg:province":"Asturias",
    "wof:name":"Maria Mercedes Garcia Lopez",
    "wof:placetype":"venue"
},
  "geometry": {"coordinates":[-5.8468251228,43.3642349243],"type":"Point"}
}