{
  "type": "Feature",
  "properties": {
    "iso:country":"ES",
    "sg:address":"Avda Andalucia, 35",
    "sg:city":"Santa Elena",
    "sg:orig_category":"Empresas De Carpinter\u00cda De Madera",
    "sg:phone":"+34 953 66 41 33",
    "sg:postcode":"23213",
    "sg:province":"Ja\u00e9n",
    "wof:name":"Gomez Alcaide Adolfo",
    "wof:placetype":"venue"
},
  "geometry": {"coordinates":[-3.5394430161,38.3422012329],"type":"Point"}
}