{
  "type": "Feature",
  "properties": {
    "addr:full":"Calle de Sagunto, 10 Pozuelo De Alarcon Madrid 28223",
    "addr:housenumber":"10",
    "addr:postcode":"28223",
    "addr:street":"Calle De Sagunto",
    "iso:country":"ES",
    "sg:address":"Calle de Sagunto, 10",
    "sg:city":"Pozuelo De Alarcon",
    "sg:orig_category":"M\u00c9dicos: An\u00c1lisis Cl\u00cdnicos",
    "sg:phone":"+34 913 52 86 86",
    "sg:postcode":"28223",
    "sg:province":"Madrid",
    "wof:name":"Clinamat S.a.",
    "wof:placetype":"venue"
},
  "geometry": {"coordinates":[-3.8125009537,40.4353637695],"type":"Point"}
}