{
  "type": "Feature",
  "properties": {
    "iso:country":"ES",
    "sg:address":"Carrer de Anselm Clave, 147",
    "sg:city":"Olesa Montserrat",
    "sg:orig_category":"Inmobiliaria (agencias)",
    "sg:phone":"+34 937 78 44 32",
    "sg:postcode":"08640",
    "sg:province":"Barcelona",
    "wof:name":"Inmobles Fac S.l.",
    "wof:placetype":"venue"
},
  "geometry": {"coordinates":[1.8936680555,41.5436058044],"type":"Point"}
}