{
  "type": "Feature",
  "properties": {
    "addr:full":"Calle de Bosque, 3 Goro Las Palmas 35215",
    "addr:housenumber":"3",
    "addr:postcode":"35215",
    "addr:street":"Calle De Bosque",
    "iso:country":"ES",
    "sg:address":"Calle de Bosque, 3",
    "sg:city":"Goro",
    "sg:orig_category":"Puros, Cigarrillos Y Tabaco (fabricaci\u00d3n, Al Por Mayor)",
    "sg:phone":"+34 928 70 01 73",
    "sg:postcode":"35215",
    "sg:province":"Las Palmas",
    "wof:name":"Empresa Canaria De Distribucion S.a.",
    "wof:placetype":"venue"
},
  "geometry": {"coordinates":[-15.3929481506,27.9670791626],"type":"Point"}
}