{
  "type": "Feature",
  "properties": {
    "addr:full":"Carrer de Balmes, 177 Barcelona Barcelona 08006",
    "addr:housenumber":"177",
    "addr:postcode":"08006",
    "addr:street":"Carrer De Balmes",
    "iso:country":"ES",
    "sg:address":"Carrer de Balmes, 177",
    "sg:city":"Barcelona",
    "sg:orig_category":"M\u00c9dicos: Cirug\u00cda Pl\u00c1stica, Reconstructiva Y Est\u00c9tica",
    "sg:phone":"+34 932 18 31 40",
    "sg:postcode":"08006",
    "sg:province":"Barcelona",
    "sg:website":"www.biosbcn.com",
    "wof:name":"Govantes Lopez Pilar",
    "wof:placetype":"venue"
},
  "geometry": {"coordinates":[2.1534090042,41.3961677551],"type":"Point"}
}