{
  "type": "Feature",
  "properties": {
    "iso:country":"ES",
    "sg:address":"Avda Musica (de La), 2",
    "sg:city":"Juncal",
    "sg:orig_category":"Carnicer\u00cdas, Carnicer\u00cdas",
    "sg:phone":"+34 956 87 79 48",
    "sg:postcode":"11500",
    "sg:province":"C\u00e1diz",
    "wof:name":"Borronda Y Rosso S.l",
    "wof:placetype":"venue"
},
  "geometry": {"coordinates":[-6.2197542191,36.6056632996],"type":"Point"}
}