{
  "type": "Feature",
  "properties": {
    "addr:full":"Calle de Venezuela, 2 Galletas Santa Cruz De Tenerife 38631",
    "addr:housenumber":"2",
    "addr:postcode":"38631",
    "addr:street":"Calle De Venezuela",
    "iso:country":"ES",
    "sg:address":"Calle de Venezuela, 2",
    "sg:city":"Galletas",
    "sg:orig_category":"Ortopedia General",
    "sg:phone":"+34 922 78 64 50",
    "sg:postcode":"38631",
    "sg:province":"Santa Cruz De Tenerife",
    "wof:name":"Ortopedia Ortosur S.l.",
    "wof:placetype":"venue"
},
  "geometry": {"coordinates":[-16.6541137695,28.007516861],"type":"Point"}
}