{
  "type": "Feature",
  "properties": {
    "iso:country":"ES",
    "sg:address":"Carrer de Fontanella, S/n",
    "sg:city":"Barcelona",
    "sg:orig_category":"Promotores Constructores",
    "sg:phone":"+34 934 12 37 27",
    "sg:postcode":"08010",
    "sg:province":"Barcelona",
    "wof:name":"Terratest Tecnicas Especiales S.a.",
    "wof:placetype":"venue"
},
  "geometry": {"coordinates":[2.1725299358,41.3882064819],"type":"Point"}
}