{
  "type": "Feature",
  "properties": {
    "iso:country":"ES",
    "sg:address":"Calle de Francisco Madariaga, 15",
    "sg:city":"Madrid",
    "sg:orig_category":"Radiocomunicaciones, Telefon\u00cda M\u00d3vil, Radiomensajer\u00cda: Servicios, Comercializaci\u00d3n",
    "sg:phone":"+34 914 07 71 99",
    "sg:postcode":"28017",
    "sg:province":"Madrid",
    "wof:name":"Henry Ramirez Santos Manuel",
    "wof:placetype":"venue"
},
  "geometry": {"coordinates":[-3.640887022,40.43542099],"type":"Point"}
}