{
  "type": "Feature",
  "properties": {
    "addr:full":"Carrer de Font D'en Canyelles, 80 Barcelona Barcelona 08042",
    "addr:housenumber":"80",
    "addr:postcode":"08042",
    "addr:street":"Carrer De Font D'En Canyelles",
    "iso:country":"ES",
    "sg:address":"Carrer de Font D'en Canyelles, 80",
    "sg:city":"Barcelona",
    "sg:orig_category":"Complementos De Vestir (al Por Menor)",
    "sg:phone":"+34 933 54 54 19",
    "sg:postcode":"08042",
    "sg:province":"Barcelona",
    "wof:name":"Gomez Diaz Emilia",
    "wof:placetype":"venue"
},
  "geometry": {"coordinates":[2.1751241684,41.4407310486],"type":"Point"}
}