{
  "type": "Feature",
  "properties": {
    "iso:country":"ES",
    "sg:address":"Carrer de Agudells, 85",
    "sg:city":"Barcelona",
    "sg:orig_category":"Formaci\u00d3n Continuada (variada)",
    "sg:phone":"+34 934 20 96 47",
    "sg:postcode":"08032",
    "sg:province":"Barcelona",
    "wof:name":"Centro Juvenil De Adolescentes Del Carmelo De Barcelona",
    "wof:placetype":"venue"
},
  "geometry": {"coordinates":[2.1559250355,41.4222145081],"type":"Point"}
}