{
  "type": "Feature",
  "properties": {
    "addr:full":"Calle de Escritora Gloria Fuertes, 4 Cordoba C\u00f3rdoba 14004",
    "addr:housenumber":"4",
    "addr:postcode":"14004",
    "addr:street":"Calle De Escritora Gloria Fuertes;Co\u0301Rdoba",
    "iso:country":"ES",
    "sg:address":"Calle de Escritora Gloria Fuertes, 4",
    "sg:city":"Cordoba",
    "sg:orig_category":"Peluqueros: De Se\u00d1oras",
    "sg:phone":"+34 957 41 34 35",
    "sg:postcode":"14004",
    "sg:province":"C\u00f3rdoba",
    "wof:name":"Lopez Garrido Rosario",
    "wof:placetype":"venue"
},
  "geometry": {"coordinates":[-4.792573452,37.8764572144],"type":"Point"}
}