{
  "type": "Feature",
  "properties": {
    "addr:full":"Travesia Del Rey, 28 Galisteo C\u00e1ceres 10691",
    "addr:housenumber":"28",
    "addr:postcode":"10691",
    "addr:street":"Travesia Del Rey;Ca\u0301Ceres",
    "iso:country":"ES",
    "sg:address":"Travesia Del Rey, 28",
    "sg:city":"Galisteo",
    "sg:orig_category":"Arquitectos",
    "sg:phone":"+34 927 45 22 25",
    "sg:postcode":"10691",
    "sg:province":"C\u00e1ceres",
    "wof:name":"Arriba Guillen Maria Jose",
    "wof:placetype":"venue"
},
  "geometry": {"coordinates":[-6.2679672241,39.9755859375],"type":"Point"}
}