{
  "type": "Feature",
  "properties": {
    "addr:full":"Rua Manuel Lemos, 6 Ramallosa Pontevedra 36379",
    "addr:housenumber":"6",
    "addr:postcode":"36379",
    "addr:street":"Rua Manuel Lemos",
    "iso:country":"ES",
    "sg:address":"Rua Manuel Lemos, 6",
    "sg:city":"Ramallosa",
    "sg:orig_category":"Agencias Y Agentes Comerciales, Representantes",
    "sg:phone":"+34 986 35 05 06",
    "sg:postcode":"36379",
    "sg:province":"Pontevedra",
    "wof:name":"Rodriguez Pombo Carlos",
    "wof:placetype":"venue"
},
  "geometry": {"coordinates":[-8.8124732971,42.116558075],"type":"Point"}
}