{
  "type": "Feature",
  "properties": {
    "addr:full":"Cala Finestrat, S/n Finestrat Alicante 03509",
    "addr:housenumber":"s / n",
    "addr:postcode":"03509",
    "iso:country":"ES",
    "sg:address":"Cala Finestrat, S/n",
    "sg:city":"Finestrat",
    "sg:orig_category":"Bisuter\u00cda, Joyer\u00cda, Relojer\u00cda (al Por Menor)",
    "sg:phone":"+34 966 80 08 00",
    "sg:postcode":"03509",
    "sg:province":"Alicante",
    "sg:website":"www.orovivo.es",
    "wof:name":"Oro Vivo S.a.",
    "wof:placetype":"venue"
},
  "geometry": {"coordinates":[-0.1988539994,38.5523109436],"type":"Point"}
}