{
  "type": "Feature",
  "properties": {
    "iso:country":"ES",
    "sg:address":"Grup Gandasegui Remigio Mons., 2",
    "sg:city":"Bilbao",
    "sg:orig_category":"Asociaciones, Organismos Culturales Y Socioeducativos",
    "sg:phone":"+34 944 33 11 30",
    "sg:postcode":"48006",
    "sg:province":"Vizcaya",
    "wof:name":"Sociedad Recreativa Y Gastronomica Zabal",
    "wof:placetype":"venue"
},
  "geometry": {"coordinates":[-2.915391922,43.2542037964],"type":"Point"}
}