{
  "type": "Feature",
  "properties": {
    "iso:country":"ES",
    "sg:address":"Calle de Oviedo, 4",
    "sg:city":"Mostoles",
    "sg:orig_category":"Peluquer\u00cdas, Peluquer\u00cda Mixta",
    "sg:phone":"+34 916 14 57 84",
    "sg:postcode":"28934",
    "sg:province":"Madrid",
    "wof:name":"Diaz Lara Patricia",
    "wof:placetype":"venue"
},
  "geometry": {"coordinates":[-3.8721959591,40.3210411072],"type":"Point"}
}