{
  "type": "Feature",
  "properties": {
    "iso:country":"ES",
    "sg:address":"Barrio Nuevo, 15",
    "sg:city":"Cullar",
    "sg:orig_category":"Negocio De Materiales De Construcci\u00d3n",
    "sg:phone":"+34 958 73 24 80",
    "sg:postcode":"18850",
    "sg:province":"Granada",
    "wof:name":"Los Robles Cullar S.l.",
    "wof:placetype":"venue"
},
  "geometry": {"coordinates":[-2.5812389851,37.5853652954],"type":"Point"}
}