{
  "type": "Feature",
  "properties": {
    "iso:country":"ES",
    "sg:address":"Calle de Delfines, Los, 10",
    "sg:city":"Perellonet",
    "sg:orig_category":"M\u00c9dicos: Cardiolog\u00cda Y Afecciones Cardiovasculares",
    "sg:phone":"+34 961 77 76 95",
    "sg:postcode":"46012",
    "sg:province":"Valencia",
    "wof:name":"Pomar Domingo Francisco",
    "wof:placetype":"venue"
},
  "geometry": {"coordinates":[-0.2858265042,39.2941322327],"type":"Point"}
}