{
  "type": "Feature",
  "properties": {
    "iso:country":"ES",
    "sg:address":"Rua Brasil, 50",
    "sg:city":"Vigo",
    "sg:orig_category":"Abogados",
    "sg:phone":"+34 986 42 04 07",
    "sg:postcode":"36204",
    "sg:province":"Pontevedra",
    "wof:name":"Arias Santos Manuel",
    "wof:placetype":"venue"
},
  "geometry": {"coordinates":[-8.7132816315,42.232334137],"type":"Point"}
}