{
  "type": "Feature",
  "properties": {
    "addr:full":"Paulino Caballero, 47 Iru\u00f1a Navarra 31003",
    "addr:housenumber":"47",
    "addr:postcode":"31003",
    "addr:street":"Caballero",
    "iso:country":"ES",
    "sg:address":"Paulino Caballero, 47",
    "sg:city":"Iru\u00f1a",
    "sg:orig_category":"Agencias Y Agentes Comerciales, Representantes",
    "sg:phone":"+34 948 23 72 56",
    "sg:postcode":"31003",
    "sg:province":"Navarra",
    "wof:name":"Unzu Lapeyra Francisco Javier",
    "wof:placetype":"venue"
},
  "geometry": {"coordinates":[-1.6373089552,42.8101882935],"type":"Point"}
}