{
  "type": "Feature",
  "properties": {
    "iso:country":"ES",
    "sg:address":"Calle de Mundir I, 8",
    "sg:city":"Zaragoza",
    "sg:orig_category":"Inmobiliaria (agencias)",
    "sg:phone":"+34 976 29 44 71",
    "sg:postcode":"50001",
    "sg:province":"Zaragoza",
    "wof:name":"Inmobiliaria Grupo Zaragoza S.a.",
    "wof:placetype":"venue"
},
  "geometry": {"coordinates":[-0.8739200234,41.6550979614],"type":"Point"}
}