{
  "type": "Feature",
  "properties": {
    "addr:full":"Cmno Zarzuela, 55 Madrid Madrid 28023",
    "addr:housenumber":"55",
    "addr:postcode":"madrid;28023",
    "addr:street":"Cmno Zarzuela",
    "iso:country":"ES",
    "sg:address":"Cmno Zarzuela, 55",
    "sg:city":"Madrid",
    "sg:orig_category":"Arquitectos",
    "sg:phone":"+34 917 40 28 13",
    "sg:postcode":"28023",
    "sg:province":"Madrid",
    "wof:name":"3dgp Infografia S.l.",
    "wof:placetype":"venue"
},
  "geometry": {"coordinates":[-3.790808,40.468525],"type":"Point"}
}