{
  "type": "Feature",
  "properties": {
    "addr:full":"Franca, 83 S'arraco Islas Baleares 07159",
    "addr:housenumber":"83",
    "addr:postcode":"07159",
    "addr:street":"Franca;Islas",
    "iso:country":"ES",
    "sg:address":"Franca, 83",
    "sg:city":"S'arraco",
    "sg:orig_category":"Agentes Generales De Seguros",
    "sg:phone":"+34 971 67 43 04",
    "sg:postcode":"07159",
    "sg:province":"Islas Baleares",
    "wof:name":"Flexas Juan Maria Catalina",
    "wof:placetype":"venue"
},
  "geometry": {"coordinates":[2.3928539753,39.5784072876],"type":"Point"}
}