{
  "type": "Feature",
  "properties": {
    "addr:full":"Calle de San Jose, 10 Santander Cantabria 39003",
    "addr:housenumber":"10",
    "addr:postcode":"39003",
    "addr:street":"Calle De San",
    "iso:country":"ES",
    "sg:address":"Calle de San Jose, 10",
    "sg:city":"Santander",
    "sg:orig_category":"Arquitectos",
    "sg:phone":"+34 942 31 34 65",
    "sg:postcode":"39003",
    "sg:province":"Cantabria",
    "wof:name":"Madariaga Galarza Jose Luis",
    "wof:placetype":"venue"
},
  "geometry": {"coordinates":[-3.8053319454,43.4624862671],"type":"Point"}
}