{
  "type": "Feature",
  "properties": {
    "addr:full":"Calle de Don Pedro Infinito, 24 Palmas De Gran Canaria Las Palmas 35012",
    "addr:postcode":"35012",
    "addr:street":"Calle De Don;Infinito 24",
    "iso:country":"ES",
    "sg:address":"Calle de Don Pedro Infinito, 24",
    "sg:city":"Palmas De Gran Canaria",
    "sg:orig_category":"Bisuter\u00cda, Joyer\u00cda, Relojer\u00cda (al Por Menor)",
    "sg:phone":"+34 928 28 61 10",
    "sg:postcode":"35012",
    "sg:province":"Las Palmas",
    "wof:name":"Cabrera Santana Concepcion",
    "wof:placetype":"venue"
},
  "geometry": {"coordinates":[-15.4310026169,28.110370636],"type":"Point"}
}