{
  "type": "Feature",
  "properties": {
    "iso:country":"ES",
    "sg:address":"C/ Pereres, 8",
    "sg:city":"Puigcerda",
    "sg:orig_category":"Inmobiliaria (agencias)",
    "sg:phone":"+34 972 14 09 37",
    "sg:postcode":"17520",
    "sg:province":"Girona",
    "wof:name":"Inmobiliaria Ismar S.a.",
    "wof:placetype":"venue"
},
  "geometry": {"coordinates":[1.9299550056,42.4291954041],"type":"Point"}
}