{
  "type": "Feature",
  "properties": {
    "addr:full":"Plce Charca (de La), 3 Granada Granada 18010",
    "addr:housenumber":"3",
    "addr:postcode":"18010",
    "iso:country":"ES",
    "sg:address":"Plce Charca (de La), 3",
    "sg:city":"Granada",
    "sg:orig_category":"Herboristas (al Por Menor)",
    "sg:phone":"+34 958 29 55 45",
    "sg:postcode":"18010",
    "sg:province":"Granada",
    "wof:name":"Los Tes De Al-andalus",
    "wof:placetype":"venue"
},
  "geometry": {"coordinates":[-3.5926840305,37.1819648743],"type":"Point"}
}