{
  "type": "Feature",
  "properties": {
    "iso:country":"ES",
    "sg:address":"Calle de San Blas, 1",
    "sg:city":"Santa Marta De Tormes",
    "sg:orig_category":"Promotores Constructores",
    "sg:phone":"+34 923 13 94 82",
    "sg:postcode":"37900",
    "sg:province":"Salamanca",
    "wof:name":"Comunidad Propietarios San Blas 1",
    "wof:placetype":"venue"
},
  "geometry": {"coordinates":[-5.6215910912,40.9517936707],"type":"Point"}
}