{
  "type": "Feature",
  "properties": {
    "addr:full":"Carrer de Canvis Vells, 1 Barcelona Barcelona 08003",
    "addr:housenumber":"1",
    "addr:postcode":"08003",
    "addr:street":"Carrer De Canvis Vells",
    "iso:country":"ES",
    "sg:address":"Carrer de Canvis Vells, 1",
    "sg:city":"Barcelona",
    "sg:orig_category":"Alimentaci\u00d3n General (al Por Menor)",
    "sg:phone":"+34 932 68 91 20",
    "sg:postcode":"08003",
    "sg:province":"Barcelona",
    "wof:name":"Morande Ruiz-tagle Maria Josefina",
    "wof:placetype":"venue"
},
  "geometry": {"coordinates":[2.1819279194,41.3831710815],"type":"Point"}
}