{
  "type": "Feature",
  "properties": {
    "iso:country":"ES",
    "sg:address":"Calle de Bidezabal, 32",
    "sg:city":"Getxo",
    "sg:orig_category":"Prot\u00c9sicos Dentales",
    "sg:phone":"+34 944 91 17 63",
    "sg:postcode":"48990",
    "sg:province":"Vizcaya",
    "wof:name":"Abel Gonzalez Herrero",
    "wof:placetype":"venue"
},
  "geometry": {"coordinates":[-3.011579,43.357113],"type":"Point"}
}