{
  "type": "Feature",
  "properties": {
    "addr:full":"Kontseju Zarra Kalea, 13 Usurbil Guip\u00f9zcoa 20170",
    "addr:housenumber":"13",
    "addr:postcode":"20170",
    "addr:street":"Kontseju Zarra Kalea;Guipu\u0300Zcoa",
    "iso:country":"ES",
    "sg:address":"Kontseju Zarra Kalea, 13",
    "sg:city":"Usurbil",
    "sg:orig_category":"Electrodom\u00c9sticos (fabricaci\u00d3n, Al Por Mayor)",
    "sg:phone":"+34 943 36 13 80",
    "sg:postcode":"20170",
    "sg:province":"Guip\u00f9zcoa",
    "wof:name":"Zugasti Lakidain, Conchi",
    "wof:placetype":"venue"
},
  "geometry": {"coordinates":[-2.0539140701,43.2733459473],"type":"Point"}
}