{
  "type": "Feature",
  "properties": {
    "iso:country":"ES",
    "sg:address":"Calle de Perez Galdos, 3",
    "sg:city":"Valsequillo",
    "sg:orig_category":"M\u00c9dicos: Naturistas",
    "sg:phone":"+34 928 57 13 71",
    "sg:postcode":"35217",
    "sg:province":"Las Palmas",
    "wof:name":"Martel Pe\u00f1ate Maria Del Pino",
    "wof:placetype":"venue"
},
  "geometry": {"coordinates":[-15.4993886948,27.9922599792],"type":"Point"}
}