{
  "type": "Feature",
  "properties": {
    "iso:country":"ES",
    "sg:address":"Pg Ramon Llull, 5",
    "sg:city":"Felanitx",
    "sg:orig_category":"Loter\u00cda Y T\u00d3mbola",
    "sg:phone":"+34 971 58 25 02",
    "sg:postcode":"07200",
    "sg:province":"Islas Baleares",
    "wof:name":"Ramon Roig Maria Antonia",
    "wof:placetype":"venue"
},
  "geometry": {"coordinates":[3.1446130276,39.4716339111],"type":"Point"}
}