{
  "type": "Feature",
  "properties": {
    "iso:country":"ES",
    "sg:address":"Calle de Luis Chamizo, 10",
    "sg:city":"Albuera",
    "sg:orig_category":"Trabajos De Perforaciones, Sondeos, Construcci\u00d3n De Pozos",
    "sg:phone":"+34 924 48 02 27",
    "sg:postcode":"06170",
    "sg:province":"Badajoz",
    "wof:name":"Sondeos Aforos Y Riegos La Albuera S.l.",
    "wof:placetype":"venue"
},
  "geometry": {"coordinates":[-6.8213310242,38.7193031311],"type":"Point"}
}