{
  "type": "Feature",
  "properties": {
    "addr:full":"Calle de Palacio Valdes, 3 Gijon Asturias 33206",
    "addr:housenumber":"3",
    "addr:postcode":"33206",
    "addr:street":"Calle De Palacio Valdes",
    "iso:country":"ES",
    "sg:address":"Calle de Palacio Valdes, 3",
    "sg:city":"Gijon",
    "sg:orig_category":"Parques De Atracciones Y Centros De Esparcimiento",
    "sg:phone":"+34 985 35 44 22",
    "sg:postcode":"33206",
    "sg:province":"Asturias",
    "wof:name":"Inverexpan",
    "wof:placetype":"venue"
},
  "geometry": {"coordinates":[-5.6659097672,43.5395927429],"type":"Point"}
}