{
  "type": "Feature",
  "properties": {
    "iso:country":"ES",
    "sg:address":"Calle de Menendez Pelayo, 10",
    "sg:city":"Laredo",
    "sg:orig_category":"Promotores Constructores",
    "sg:phone":"+34 942 60 30 58",
    "sg:postcode":"39770",
    "sg:province":"Cantabria",
    "wof:name":"Comunidad De Propietarios Menedez Pelayo N\u00ba10",
    "wof:placetype":"venue"
},
  "geometry": {"coordinates":[-3.4125909805,43.4122619629],"type":"Point"}
}