{
  "type": "Feature",
  "properties": {
    "addr:full":"Calle de Pintor Peiro, 4 Valencia Valencia 46010",
    "addr:housenumber":"4",
    "addr:postcode":"46010",
    "addr:street":"Calle De Pintor Peiro",
    "iso:country":"ES",
    "sg:address":"Calle de Pintor Peiro, 4",
    "sg:city":"Valencia",
    "sg:orig_category":"Arquitectos",
    "sg:phone":"+34 963 61 46 46",
    "sg:postcode":"46010",
    "sg:province":"Valencia",
    "wof:name":"Piposa Arquitectura Y Construcciones S.l.",
    "wof:placetype":"venue"
},
  "geometry": {"coordinates":[-0.3029510975,39.5897521973],"type":"Point"}
}