{
  "type": "Feature",
  "properties": {
    "iso:country":"ES",
    "sg:address":"Av Republica Argentina, 266",
    "sg:city":"Barcelona",
    "sg:orig_category":"Fabricaci\u00d3n, Importaci\u00d3n De L\u00c1mparas Y Bombillas",
    "sg:phone":"+34 934 18 06 38",
    "sg:postcode":"08023",
    "sg:province":"Barcelona",
    "wof:name":"Fer House S.l.",
    "wof:placetype":"venue"
},
  "geometry": {"coordinates":[2.1387710571,41.4135437012],"type":"Point"}
}