{
  "type": "Feature",
  "properties": {
    "iso:country":"ES",
    "sg:address":"Calle de Santa Cecilia, 20",
    "sg:city":"Illescas",
    "sg:orig_category":"Peluqueros: De Se\u00d1oras",
    "sg:phone":"+34 925 51 29 79",
    "sg:postcode":"45200",
    "sg:province":"Toledo",
    "wof:name":"Navas De Agueda Maria Del Pilar",
    "wof:placetype":"venue"
},
  "geometry": {"coordinates":[-3.8453910351,40.1216545105],"type":"Point"}
}