{
  "type": "Feature",
  "properties": {
    "iso:country":"ES",
    "sg:address":"Urb Los Porches, S/n",
    "sg:city":"Sevilla",
    "sg:orig_category":"Organizaciones Internacionales",
    "sg:phone":"+34 954 40 94 40",
    "sg:postcode":"41020",
    "sg:province":"Sevilla",
    "wof:name":"Caritas Diocesanas",
    "wof:placetype":"venue"
},
  "geometry": {"coordinates":[-5.9333291054,37.4165763855],"type":"Point"}
}