{
  "type": "Feature",
  "properties": {
    "iso:country":"ES",
    "sg:address":"Pol. Sta Isabel, 20",
    "sg:city":"El Viso Alcor",
    "sg:orig_category":"Empresas De Carpinter\u00cda De Madera",
    "sg:phone":"+34 955 94 53 48",
    "sg:postcode":"41520",
    "sg:province":"Sevilla",
    "wof:name":"Hijos De Jose Soto S.c.",
    "wof:placetype":"venue"
},
  "geometry": {"coordinates":[-5.7224740982,37.3872108459],"type":"Point"}
}