{
  "type": "Feature",
  "properties": {
    "iso:country":"ES",
    "sg:address":"Calle de Torno, 3",
    "sg:city":"San Vicente Del Raspeig-sant Vicent Del Raspeig",
    "sg:orig_category":"Delegados, Agentes De Tr\u00c1nsito, Auxiliares De Transporte Internacional",
    "sg:phone":"+34 965 67 41 71",
    "sg:postcode":"03690",
    "sg:province":"Alicante",
    "wof:name":"Hijos De Ramon Torregrosa S.l.",
    "wof:placetype":"venue"
},
  "geometry": {"coordinates":[-0.5411589742,38.4039802551],"type":"Point"}
}