{
  "type": "Feature",
  "properties": {
    "addr:full":"Calle de Jose Hierro (de), 5 Alcobendas Madrid 28100",
    "addr:postcode":"28100",
    "addr:street":"Calle De Jose Hierro De 5",
    "iso:country":"ES",
    "sg:address":"Calle de Jose Hierro (de), 5",
    "sg:city":"Alcobendas",
    "sg:orig_category":"Inmobiliaria (agencias)",
    "sg:phone":"+34 916 62 92 62",
    "sg:postcode":"28100",
    "sg:province":"Madrid",
    "wof:name":"Eurosun Medical Services S.a.",
    "wof:placetype":"venue"
},
  "geometry": {"coordinates":[-3.6558310986,40.5479660034],"type":"Point"}
}