{
  "type": "Feature",
  "properties": {
    "iso:country":"ES",
    "sg:address":"Grup Alonso Allende, 18",
    "sg:city":"Portugalete",
    "sg:orig_category":"Peluqueros: De Se\u00d1oras",
    "sg:phone":"+34 944 72 11 98",
    "sg:postcode":"48920",
    "sg:province":"Vizcaya",
    "wof:name":"Purificacion Garcia Gomez",
    "wof:placetype":"venue"
},
  "geometry": {"coordinates":[-3.0152130127,43.3130187988],"type":"Point"}
}