{
  "type": "Feature",
  "properties": {
    "iso:country":"ES",
    "sg:address":"Calle de Montijo, 1",
    "sg:city":"Catedral",
    "sg:orig_category":"Importaci\u00d3n",
    "sg:phone":"+34 968 22 50 56",
    "sg:postcode":"30001",
    "sg:province":"Murcia",
    "wof:name":"Carsae S.l.",
    "wof:placetype":"venue"
},
  "geometry": {"coordinates":[-1.1293640137,37.9857940674],"type":"Point"}
}