{
  "type": "Feature",
  "properties": {
    "iso:country":"ES",
    "sg:address":"Carrer de Pi I Margall, S/n",
    "sg:city":"Barcelona",
    "sg:orig_category":"Ense\u00d1anza, Formaci\u00d3n Profesional: Aprendizaje",
    "sg:phone":"+34 932 84 20 53",
    "sg:postcode":"08024",
    "sg:province":"Barcelona",
    "wof:name":"Institut Municipal De Mercats De Barcelona",
    "wof:placetype":"venue"
},
  "geometry": {"coordinates":[2.1629400253,41.4059944153],"type":"Point"}
}