{
  "type": "Feature",
  "properties": {
    "addr:full":"Calle de Serapio Mugica, 23 Irun Guip\u00f9zcoa 20302",
    "addr:housenumber":"23",
    "addr:postcode":"20302",
    "addr:street":"Calle De Serapio Mugica;Guipu\u0300Zcoa",
    "iso:country":"ES",
    "sg:address":"Calle de Serapio Mugica, 23",
    "sg:city":"Irun",
    "sg:orig_category":"Fabricaci\u00d3n De Ventanas",
    "sg:phone":"+34 943 61 19 21",
    "sg:postcode":"20302",
    "sg:province":"Guip\u00f9zcoa",
    "wof:name":"Salgado Rodriguez Julio",
    "wof:placetype":"venue"
},
  "geometry": {"coordinates":[-1.7961419821,43.3377075195],"type":"Point"}
}