{
  "type": "Feature",
  "properties": {
    "iso:country":"ES",
    "sg:address":"Calle de Poligono, 5",
    "sg:city":"Jerez De Los Caballeros",
    "sg:orig_category":"Tapicer\u00cdas",
    "sg:phone":"+34 924 73 03 73",
    "sg:postcode":"06380",
    "sg:province":"Badajoz",
    "wof:name":"Pitel Jimenez Emilio",
    "wof:placetype":"venue"
},
  "geometry": {"coordinates":[-6.7697892189,38.3272514343],"type":"Point"}
}