{
  "type": "Feature",
  "properties": {
    "addr:full":"Calle de Gaucin, 16 Malaga M\u00e1laga 29003",
    "addr:housenumber":"16",
    "addr:postcode":"29003",
    "addr:street":"Calle De Gaucin;Ma\u0301Laga",
    "iso:country":"ES",
    "sg:address":"Calle de Gaucin, 16",
    "sg:city":"Malaga",
    "sg:orig_category":"Droguer\u00cdas (al Por Menor)",
    "sg:phone":"+34 952 34 38 17",
    "sg:postcode":"29003",
    "sg:province":"M\u00e1laga",
    "wof:name":"Diaz Garcia Raimundo",
    "wof:placetype":"venue"
},
  "geometry": {"coordinates":[-4.4494509697,36.6985092163],"type":"Point"}
}