{
  "type": "Feature",
  "properties": {
    "addr:full":"Pol Ind Costa Del Sol, S/n Marbella M\u00e1laga 29600",
    "addr:housenumber":"/ n",
    "addr:postcode":"29600",
    "addr:street":"Costa Del Sol S;Ma\u0301Laga",
    "iso:country":"ES",
    "sg:address":"Pol Ind Costa Del Sol, S/n",
    "sg:city":"Marbella",
    "sg:orig_category":"Empresas De Carpinter\u00cda De Madera",
    "sg:phone":"+34 952 77 23 93",
    "sg:postcode":"29600",
    "sg:province":"M\u00e1laga",
    "wof:name":"Luque Zamarron Mario",
    "wof:placetype":"venue"
},
  "geometry": {"coordinates":[-4.7588043213,36.5039405823],"type":"Point"}
}