{
  "type": "Feature",
  "properties": {
    "iso:country":"ES",
    "sg:address":"Calle de Puerto De La Cruz Verde, 44",
    "sg:city":"Madrid",
    "sg:orig_category":"Peluquer\u00cdas, Peluquer\u00cda Mixta",
    "sg:phone":"+34 915 27 87 66",
    "sg:postcode":"28045",
    "sg:province":"Madrid",
    "wof:name":"Barrantes Royo Fernando",
    "wof:placetype":"venue"
},
  "geometry": {"coordinates":[-3.6870119572,40.3848876953],"type":"Point"}
}