{
  "type": "Feature",
  "properties": {
    "iso:country":"ES",
    "sg:address":"Carrer de Casp, 158",
    "sg:city":"Barcelona",
    "sg:orig_category":"Negocio De Metales No Ferrosos",
    "sg:phone":"+34 932 32 63 65",
    "sg:postcode":"08013",
    "sg:province":"Barcelona",
    "wof:name":"Obradors Drm S. L.",
    "wof:placetype":"venue"
},
  "geometry": {"coordinates":[2.1806759834,41.3966560364],"type":"Point"}
}