{
  "type": "Feature",
  "properties": {
    "iso:country":"ES",
    "sg:address":"Av Paral.lel, 48",
    "sg:city":"Barcelona",
    "sg:orig_category":"Molduras, Junquillos, Listones Y Molduras Perforadas",
    "sg:phone":"+34 933 29 88 58",
    "sg:postcode":"08001",
    "sg:province":"Barcelona",
    "wof:name":"Dorado Suarez Jose Luis",
    "wof:placetype":"venue"
},
  "geometry": {"coordinates":[2.1714930534,41.3749923706],"type":"Point"}
}