{
  "type": "Feature",
  "properties": {
    "addr:full":"Calle de San Pedro, 14 Sot De Ferrer Castell\u00f3n 12489",
    "addr:housenumber":"14",
    "addr:postcode":"12489",
    "addr:street":"Calle De San Pedro",
    "iso:country":"ES",
    "sg:address":"Calle de San Pedro, 14",
    "sg:city":"Sot De Ferrer",
    "sg:orig_category":"Empresarios",
    "sg:phone":"+34 964 13 51 34",
    "sg:postcode":"12489",
    "sg:province":"Castell\u00f3n",
    "wof:name":"Bada Bover Francisco",
    "wof:placetype":"venue"
},
  "geometry": {"coordinates":[-0.4118689895,39.8058204651],"type":"Point"}
}