{
  "type": "Feature",
  "properties": {
    "iso:country":"ES",
    "sg:address":"Avda Pirineos (de Los), 7",
    "sg:city":"San Sebastian De Los Reyes",
    "sg:orig_category":"Ropa Para Se\u00d1oras Y Caballeros (al Por Menor)",
    "sg:phone":"+34 916 52 70 37",
    "sg:postcode":"28700",
    "sg:province":"Madrid",
    "wof:name":"Linear International Entertiment S.l.",
    "wof:placetype":"venue"
},
  "geometry": {"coordinates":[-3.6103610992,40.5487136841],"type":"Point"}
}