{
  "type": "Feature",
  "properties": {
    "addr:full":"Calle de Humilladero (del), 8 Fuenlabrada Madrid 28945",
    "addr:housenumber":"8",
    "addr:postcode":"28945",
    "addr:street":"Calle De Humilladero Del",
    "iso:country":"ES",
    "sg:address":"Calle de Humilladero (del), 8",
    "sg:city":"Fuenlabrada",
    "sg:orig_category":"Mudanzas",
    "sg:phone":"+34 916 90 22 50",
    "sg:postcode":"28945",
    "sg:province":"Madrid",
    "sg:website":"www.transmobel.es",
    "wof:name":"Servi-nor",
    "wof:placetype":"venue"
},
  "geometry": {"coordinates":[-3.7952799797,40.2842559814],"type":"Point"}
}