{
  "type": "Feature",
  "properties": {
    "iso:country":"ES",
    "sg:address":"Pol. Ind. El Aguila, 63",
    "sg:city":"Utebo",
    "sg:orig_category":"Electricidad: Instaladores",
    "sg:phone":"+34 976 77 38 86",
    "sg:postcode":"50180",
    "sg:province":"Zaragoza",
    "wof:name":"Tecnielec S.l.",
    "wof:placetype":"venue"
},
  "geometry": {"coordinates":[-0.9998990297,41.7043800354],"type":"Point"}
}