{
  "type": "Feature",
  "properties": {
    "iso:country":"ES",
    "sg:address":"Calle de General Valcarcel, S/n",
    "sg:city":"Mula",
    "sg:orig_category":"Supermercados Y Hipermercados",
    "sg:phone":"+34 968 63 70 12",
    "sg:postcode":"30170",
    "sg:province":"Murcia",
    "wof:name":"Corbalan Matallana S.l.",
    "wof:placetype":"venue"
},
  "geometry": {"coordinates":[-1.4890489578,38.0401916504],"type":"Point"}
}