{
  "type": "Feature",
  "properties": {
    "iso:country":"ES",
    "sg:address":"Rua San Xoan, 59",
    "sg:city":"Vigo",
    "sg:orig_category":"Reposter\u00cdas",
    "sg:phone":"+34 986 26 25 46",
    "sg:postcode":"36206",
    "sg:province":"Pontevedra",
    "wof:name":"Pardellas Fernandez Hermelinda",
    "wof:placetype":"venue"
},
  "geometry": {"coordinates":[-8.6992225647,42.2389335632],"type":"Point"}
}