{
  "type": "Feature",
  "properties": {
    "addr:full":"Avda Constitucion, 3 Segorbe Castell\u00f3n 12400",
    "addr:housenumber":"3",
    "addr:postcode":"12400",
    "addr:street":"Avda Constitucion",
    "iso:country":"ES",
    "sg:address":"Avda Constitucion, 3",
    "sg:city":"Segorbe",
    "sg:orig_category":"Alquiler De V\u00cddeo",
    "sg:phone":"+34 964 71 34 61",
    "sg:postcode":"12400",
    "sg:province":"Castell\u00f3n",
    "wof:name":"Max-tec",
    "wof:placetype":"venue"
},
  "geometry": {"coordinates":[-0.489244014,39.8466491699],"type":"Point"}
}