{
  "type": "Feature",
  "properties": {
    "addr:full":"Calle de Pontevedra, 13 Cordoba C\u00f3rdoba 14013",
    "addr:housenumber":"13",
    "addr:postcode":"14013",
    "addr:street":"Calle De Pontevedra;Co\u0301Rdoba",
    "iso:country":"ES",
    "sg:address":"Calle de Pontevedra, 13",
    "sg:city":"Cordoba",
    "sg:orig_category":"Confecci\u00d3n De Trajes Para Se\u00d1oras",
    "sg:phone":"+34 957 20 15 11",
    "sg:postcode":"14013",
    "sg:province":"C\u00f3rdoba",
    "wof:name":"Requena Sanchez Olga",
    "wof:placetype":"venue"
},
  "geometry": {"coordinates":[-4.7778191566,37.8678817749],"type":"Point"}
}