{
  "type": "Feature",
  "properties": {
    "addr:full":"Los Llanos, 120 Estepona M\u00e1laga 29680",
    "addr:housenumber":"120",
    "addr:postcode":"29680",
    "addr:street":"Los Llanos",
    "iso:country":"ES",
    "sg:address":"Los Llanos, 120",
    "sg:city":"Estepona",
    "sg:orig_category":"Estudios De Grabaci\u00d3n Sonora",
    "sg:phone":"+34 952 80 80 88",
    "sg:postcode":"29680",
    "sg:province":"M\u00e1laga",
    "sg:website":"www.magicsound.com",
    "wof:name":"Piroska Salcedo Sigbrit",
    "wof:placetype":"venue"
},
  "geometry": {"coordinates":[-5.121284008,36.4365653992],"type":"Point"}
}