{
  "type": "Feature",
  "properties": {
    "iso:country":"ES",
    "sg:address":"Calle de Eduardo Vela, 12",
    "sg:city":"Madrid",
    "sg:orig_category":"Pintores",
    "sg:phone":"+34 913 07 12 54",
    "sg:postcode":"28023",
    "sg:province":"Madrid",
    "wof:name":"Westendorp Cabeza Isabel",
    "wof:placetype":"venue"
},
  "geometry": {"coordinates":[-3.7776260376,40.4615135193],"type":"Point"}
}