{
  "type": "Feature",
  "properties": {
    "iso:country":"ES",
    "sg:address":"Calle de Peru, 49",
    "sg:city":"Bormujos",
    "sg:orig_category":"Alquiler De V\u00cddeo",
    "sg:phone":"+34 955 72 43 74",
    "sg:postcode":"41930",
    "sg:province":"Sevilla",
    "wof:name":"Espelena S.l.l.",
    "wof:placetype":"venue"
},
  "geometry": {"coordinates":[-6.0798549652,37.3741226196],"type":"Point"}
}