{
  "type": "Feature",
  "properties": {
    "iso:country":"ES",
    "sg:address":"Calle de Domingo Gomez, 1",
    "sg:city":"Abaran",
    "sg:orig_category":"Iglesia Cat\u00d3lica",
    "sg:phone":"+34 968 77 45 06",
    "sg:postcode":"30550",
    "sg:province":"Murcia",
    "wof:name":"Obispado De Cartagena",
    "wof:placetype":"venue"
},
  "geometry": {"coordinates":[-1.400805831,38.2024497986],"type":"Point"}
}