{
  "type": "Feature",
  "properties": {
    "iso:country":"ES",
    "sg:address":"Pla\u00c7 Partidors (de), 5",
    "sg:city":"Lliria",
    "sg:orig_category":"Poller\u00cda Y Caza (al Por Menor)",
    "sg:phone":"+34 962 78 15 17",
    "sg:postcode":"46160",
    "sg:province":"Valencia",
    "wof:name":"Pe\u00f1arrubia Recio Maria Angeles",
    "wof:placetype":"venue"
},
  "geometry": {"coordinates":[-0.5952839851,39.6247406006],"type":"Point"}
}