{
  "type": "Feature",
  "properties": {
    "addr:full":"Carrer de Pallars, 286 Barcelona Barcelona 08005",
    "addr:housenumber":"286",
    "addr:postcode":"08005",
    "addr:street":"Carrer De Pallars",
    "iso:country":"ES",
    "sg:address":"Carrer de Pallars, 286",
    "sg:city":"Barcelona",
    "sg:orig_category":"Reparaci\u00d3n De Aparatos A Gas",
    "sg:phone":"+34 933 08 80 40",
    "sg:postcode":"08005",
    "sg:province":"Barcelona",
    "wof:name":"Ancargas S.l.",
    "wof:placetype":"venue"
},
  "geometry": {"coordinates":[2.2026093006,41.4047584534],"type":"Point"}
}