{
  "type": "Feature",
  "properties": {
    "addr:full":"Calle de Bernabe De Armendariz, 4 Sang\u00fcesa Navarra 31400",
    "addr:housenumber":"4",
    "addr:postcode":"31400",
    "addr:street":"Calle De Bernabe De Armendariz",
    "iso:country":"ES",
    "sg:address":"Calle de Bernabe De Armendariz, 4",
    "sg:city":"Sang\u00fcesa",
    "sg:orig_category":"Muebles, Minoristas",
    "sg:phone":"+34 948 87 03 12",
    "sg:postcode":"31400",
    "sg:province":"Navarra",
    "wof:name":"Rubio Remon Teresa",
    "wof:placetype":"venue"
},
  "geometry": {"coordinates":[-1.2840701342,42.5781593323],"type":"Point"}
}