{
  "type": "Feature",
  "properties": {
    "addr:full":"Calle de Joaquin Manzanares, 4 Oviedo Asturias 33013",
    "addr:housenumber":"4",
    "addr:postcode":"33013",
    "addr:street":"Calle De Joaquin Manzanares",
    "iso:country":"ES",
    "sg:address":"Calle de Joaquin Manzanares, 4",
    "sg:city":"Oviedo",
    "sg:orig_category":"Agencias Y Agentes Comerciales, Representantes",
    "sg:phone":"+34 985 24 23 13",
    "sg:postcode":"33013",
    "sg:province":"Asturias",
    "wof:name":"Alvarez Mu\u00f1iz Mariano",
    "wof:placetype":"venue"
},
  "geometry": {"coordinates":[-5.8618412018,43.3610687256],"type":"Point"}
}