{
  "type": "Feature",
  "properties": {
    "iso:country":"ES",
    "sg:address":"Calle de Cardenal Lorenzana, 2",
    "sg:city":"Le\u00f3n",
    "sg:orig_category":"Abogados",
    "sg:phone":"+34 987 22 81 28",
    "sg:postcode":"24001",
    "sg:province":"Le\u00f3n",
    "wof:name":"Sanchez Robles Juan Manuel",
    "wof:placetype":"venue"
},
  "geometry": {"coordinates":[-5.5772361755,42.5975151062],"type":"Point"}
}