{
  "type": "Feature",
  "properties": {
    "iso:country":"ES",
    "sg:address":"Rua Valencia, 14",
    "sg:city":"Vigo",
    "sg:orig_category":"Confecci\u00d3n (fabricaci\u00d3n, Al Por Mayor)",
    "sg:phone":"+34 986 42 19 78",
    "sg:postcode":"36203",
    "sg:province":"Pontevedra",
    "wof:name":"Herrero Ramos Andres",
    "wof:placetype":"venue"
},
  "geometry": {"coordinates":[-8.7240314484,42.2259178162],"type":"Point"}
}