{
  "type": "Feature",
  "properties": {
    "iso:country":"ES",
    "sg:address":"Plaz Alemania, 3",
    "sg:city":"Zamora",
    "sg:orig_category":"M\u00c9dicos: Dermatolog\u00cda Y Venereolog\u00cda",
    "sg:phone":"+34 980 52 42 34",
    "sg:postcode":"49014",
    "sg:province":"Zamora",
    "wof:name":"Sanchez Estella Juan De La Cruz",
    "wof:placetype":"venue"
},
  "geometry": {"coordinates":[-5.7431340218,41.5078735352],"type":"Point"}
}