{
  "type": "Feature",
  "properties": {
    "iso:country":"ES",
    "sg:address":"Muel San Diego, S/n",
    "sg:city":"Coru\u00d1a",
    "sg:orig_category":"Empresarios",
    "sg:phone":"+34 981 17 43 54",
    "sg:postcode":"15006",
    "sg:province":"A Coru\u00f1a",
    "wof:name":"Seguridad Alimentaria Del Noroeste S.l.",
    "wof:placetype":"venue"
},
  "geometry": {"coordinates":[-8.395524025,43.3576431274],"type":"Point"}
}