{
  "type": "Feature",
  "properties": {
    "addr:full":"Cami De Torrefarrera, Km. 0001,0 Benavent Segria Lleida 25132",
    "addr:postcode":"25132",
    "addr:street":"Cami De Torrefarrera Km. 0001,0",
    "iso:country":"ES",
    "sg:address":"Cami De Torrefarrera, Km. 0001,0",
    "sg:city":"Benavent Segria",
    "sg:orig_category":"Poller\u00cda Y Caza (al Por Menor)",
    "sg:phone":"+34 973 77 70 04",
    "sg:postcode":"25132",
    "sg:province":"Lleida",
    "wof:name":"Espinet Sole Jose Maria",
    "wof:placetype":"venue"
},
  "geometry": {"coordinates":[0.6339399815,41.6988792419],"type":"Point"}
}