{
  "type": "Feature",
  "properties": {
    "iso:country":"ES",
    "sg:address":"Corbeil Essones, S/n",
    "sg:city":"Alzira",
    "sg:orig_category":"Inform\u00c1tica (estudios, Servicios, Asesor\u00cda, Formaci\u00d3n)",
    "sg:phone":"+34 962 45 96 58",
    "sg:postcode":"46600",
    "sg:province":"Valencia",
    "wof:name":"Mapfre Servicios De Informatica S.a.",
    "wof:placetype":"venue"
},
  "geometry": {"coordinates":[-0.4378489852,39.1517295837],"type":"Point"}
}