{
  "type": "Feature",
  "properties": {
    "iso:country":"ES",
    "sg:address":"Pol Ind L'estadi, 60",
    "sg:city":"Castello Plana",
    "sg:orig_category":"Herramientas Y Suministros Para Plomeros",
    "sg:phone":"+34 964 25 51 77",
    "sg:postcode":"12004",
    "sg:province":"Castell\u00f3n",
    "wof:name":"Suministros A.e. S.c.v.l.",
    "wof:placetype":"venue"
},
  "geometry": {"coordinates":[0.4757849872,40.5413551331],"type":"Point"}
}