{
  "type": "Feature",
  "properties": {
    "addr:full":"Carrer de Hortal, 28 Barcelona Barcelona 08032",
    "addr:housenumber":"28",
    "addr:postcode":"08032",
    "addr:street":"Carrer De Hortal",
    "iso:country":"ES",
    "sg:address":"Carrer de Hortal, 28",
    "sg:city":"Barcelona",
    "sg:orig_category":"Promotores Constructores",
    "sg:phone":"+34 933 58 55 93",
    "sg:postcode":"08032",
    "sg:province":"Barcelona",
    "wof:name":"Collserola 2000 S.l.l.",
    "wof:placetype":"venue"
},
  "geometry": {"coordinates":[2.1517920494,41.4210281372],"type":"Point"}
}