{
  "type": "Feature",
  "properties": {
    "addr:full":"Calle de Arenal, 5 Bilbao Vizcaya 48005",
    "addr:housenumber":"5",
    "addr:postcode":"48005",
    "addr:street":"Calle De Arenal",
    "iso:country":"ES",
    "sg:address":"Calle de Arenal, 5",
    "sg:city":"Bilbao",
    "sg:orig_category":"Psic\u00d3logos",
    "sg:phone":"+34 944 15 08 90",
    "sg:postcode":"48005",
    "sg:province":"Vizcaya",
    "wof:name":"Isabel Espina Lesmes Y Otros Cdad",
    "wof:placetype":"venue"
},
  "geometry": {"coordinates":[-2.9239416122,43.2595214844],"type":"Point"}
}