{
  "type": "Feature",
  "properties": {
    "iso:country":"ES",
    "sg:address":"Fca. Rueda Tornijas, S/n",
    "sg:city":"Lumbrales",
    "sg:orig_category":"Mec\u00c1nico Del Autom\u00d3vil",
    "sg:phone":"+34 923 51 24 96",
    "sg:postcode":"37240",
    "sg:province":"Salamanca",
    "wof:name":"Agudo Lopez Genaro",
    "wof:placetype":"venue"
},
  "geometry": {"coordinates":[-6.685198307,40.9465484619],"type":"Point"}
}