{
  "type": "Feature",
  "properties": {
    "addr:full":"Av Rafael Casanova, 26 Sabadell Barcelona 08206",
    "addr:housenumber":"26",
    "addr:postcode":"08206",
    "addr:street":"Av Rafael Casanova",
    "iso:country":"ES",
    "sg:address":"Av Rafael Casanova, 26",
    "sg:city":"Sabadell",
    "sg:orig_category":"Deportes Y Programas De Aventura",
    "sg:phone":"+34 937 25 74 39",
    "sg:postcode":"08206",
    "sg:province":"Barcelona",
    "wof:name":"California Sports & Jeans S.a.",
    "wof:placetype":"venue"
},
  "geometry": {"coordinates":[2.0947389603,41.5469436646],"type":"Point"}
}