{
  "type": "Feature",
  "properties": {
    "iso:country":"ES",
    "sg:address":"Calle de Doreste Y Molina, S/n",
    "sg:city":"Puerto Rico",
    "sg:orig_category":"Bazares, Art\u00cdculos De Limpieza Y De Cocina (al Por Menor)",
    "sg:phone":"+34 928 56 00 34",
    "sg:postcode":"35130",
    "sg:province":"Las Palmas",
    "wof:name":"Sirwani Pessv S.l.",
    "wof:placetype":"venue"
},
  "geometry": {"coordinates":[-15.7137489319,27.7857456207],"type":"Point"}
}