{
  "type": "Feature",
  "properties": {
    "iso:country":"ES",
    "sg:address":"Calle de Fresno, 1",
    "sg:city":"Utrera",
    "sg:orig_category":"Armaduras De Hormig\u00d3n",
    "sg:phone":"+34 955 86 19 89",
    "sg:postcode":"41710",
    "sg:province":"Sevilla",
    "wof:name":"Constructora De Estructuras Avilo S.l.",
    "wof:placetype":"venue"
},
  "geometry": {"coordinates":[-5.781235218,37.1862487793],"type":"Point"}
}