{
  "type": "Feature",
  "properties": {
    "addr:full":"Calle de Marques De Santillana (del), 4 Colmenar Viejo Madrid 28770",
    "addr:postcode":"28770",
    "addr:street":"Calle De Marques De Santillana Del",
    "iso:country":"ES",
    "sg:address":"Calle de Marques De Santillana (del), 4",
    "sg:city":"Colmenar Viejo",
    "sg:orig_category":"Pr\u00c9stamos Personales E Hipotecarios",
    "sg:phone":"+34 918 45 10 14",
    "sg:postcode":"28770",
    "sg:province":"Madrid",
    "wof:name":"Registro De La Propiedad Numero 1",
    "wof:placetype":"venue"
},
  "geometry": {"coordinates":[-3.7674250603,40.6593132019],"type":"Point"}
}