{
  "type": "Feature",
  "properties": {
    "iso:country":"ES",
    "sg:address":"Carrer de Canigo, 73",
    "sg:city":"Barcelona",
    "sg:orig_category":"Laboratorios Y Cl\u00cdnicas Veterinarias",
    "sg:phone":"+34 934 27 97 29",
    "sg:postcode":"08031",
    "sg:province":"Barcelona",
    "wof:name":"Garceran Llorens Mario",
    "wof:placetype":"venue"
},
  "geometry": {"coordinates":[2.1591739655,41.4360427856],"type":"Point"}
}