{
  "type": "Feature",
  "properties": {
    "addr:full":"Barr Poligono De Ria\u00d1o, 16 Langreo Asturias 33900",
    "addr:housenumber":"16",
    "addr:postcode":"33900",
    "addr:street":"Poligono;Rian\u0303O",
    "iso:country":"ES",
    "sg:address":"Barr Poligono De Ria\u00d1o, 16",
    "sg:city":"Langreo",
    "sg:orig_category":"Loter\u00cda Y T\u00d3mbola",
    "sg:phone":"+34 985 69 39 96",
    "sg:postcode":"33900",
    "sg:province":"Asturias",
    "wof:name":"Mu\u00f1iz Zapico Aurora",
    "wof:placetype":"venue"
},
  "geometry": {"coordinates":[-5.6692090034,43.2883987427],"type":"Point"}
}