{
  "type": "Feature",
  "properties": {
    "addr:full":"Pase Pisones, 1 Burgos Burgos 09001",
    "addr:housenumber":"1",
    "addr:postcode":"09001",
    "addr:street":"Pase Pisones",
    "iso:country":"ES",
    "sg:address":"Pase Pisones, 1",
    "sg:city":"Burgos",
    "sg:orig_category":"Tiendas De Grano, Frutas Y Legumbres Secas (al Por Menor)",
    "sg:phone":"+34 947 26 67 04",
    "sg:postcode":"09001",
    "sg:province":"Burgos",
    "wof:name":"Distribuidora De Frutos Secos S.a.",
    "wof:placetype":"venue"
},
  "geometry": {"coordinates":[-3.7355909348,42.375667572],"type":"Point"}
}