{
  "type": "Feature",
  "properties": {
    "addr:full":"Calle de Ayr, S/n Vall De Almonacid Castell\u00f3n 12414",
    "addr:housenumber":"s / n",
    "addr:postcode":"12414",
    "addr:street":"Calle De Ayr",
    "iso:country":"ES",
    "sg:address":"Calle de Ayr, S/n",
    "sg:city":"Vall De Almonacid",
    "sg:orig_category":"Ense\u00d1anza Variada",
    "sg:phone":"+34 964 13 91 53",
    "sg:postcode":"12414",
    "sg:province":"Castell\u00f3n",
    "sg:website":"www.neitseminars.con",
    "wof:name":"Jodar Calpe Antonio",
    "wof:placetype":"venue"
},
  "geometry": {"coordinates":[-0.4586904943,39.9037322998],"type":"Point"}
}