{
  "type": "Feature",
  "properties": {
    "iso:country":"ES",
    "sg:address":"Carretera Banastas, S/n",
    "sg:city":"Chimillas",
    "sg:orig_category":"Poli\u00c9ster",
    "sg:phone":"+34 974 23 14 77",
    "sg:postcode":"22194",
    "sg:province":"Huesca",
    "wof:name":"Inospol S.l.",
    "wof:placetype":"venue"
},
  "geometry": {"coordinates":[-0.4513750076,42.1725120544],"type":"Point"}
}