{
  "type": "Feature",
  "properties": {
    "iso:country":"ES",
    "sg:address":"Carrer de Llacuna, 30",
    "sg:city":"Barcelona",
    "sg:orig_category":"Goma: Productos De Uso Industrial (fabricaci\u00d3n, Al Por Mayor)",
    "sg:phone":"+34 934 85 41 82",
    "sg:postcode":"08005",
    "sg:province":"Barcelona",
    "wof:name":"Abella Santamaria Antonio",
    "wof:placetype":"venue"
},
  "geometry": {"coordinates":[2.20104,41.399548],"type":"Point"}
}