{
  "type": "Feature",
  "properties": {
    "iso:country":"ES",
    "sg:address":"Calle de Barrenkalea, 4",
    "sg:city":"Gernika-lumo",
    "sg:orig_category":"Institutos De Belleza",
    "sg:phone":"+34 946 25 11 15",
    "sg:postcode":"48300",
    "sg:province":"Vizcaya",
    "sg:website":"www.euskalnet.net/manbilbao",
    "wof:name":"Bilbao Zarandona Maria Angeles",
    "wof:placetype":"venue"
},
  "geometry": {"coordinates":[-2.6776599884,43.3149185181],"type":"Point"}
}