{
  "type": "Feature",
  "properties": {
    "addr:full":"Rua Ramon Pi\u00d1eiro (de), 4 Santiago De Compostela La Coru\u00f1a 15702",
    "addr:housenumber":"4",
    "addr:postcode":"15702",
    "addr:street":"Rua Ramon Pin\u0303Eiro De;Corun\u0303A",
    "iso:country":"ES",
    "sg:address":"Rua Ramon Pi\u00d1eiro (de), 4",
    "sg:city":"Santiago De Compostela",
    "sg:orig_category":"Inform\u00c1tica: Material Y Suministros",
    "sg:phone":"+34 981 57 21 00",
    "sg:postcode":"15702",
    "sg:province":"La Coru\u00f1a",
    "sg:website":"www.es.fujitsu.com",
    "wof:name":"Fujitsu Espa\u00d1a Services S.a.",
    "wof:placetype":"venue"
},
  "geometry": {"coordinates":[-8.5443887711,42.8736915588],"type":"Point"}
}