{
  "type": "Feature",
  "properties": {
    "addr:full":"Calle de Cuesta Antigua, 8 Avila \u00c1vila 05003",
    "addr:housenumber":"8",
    "addr:postcode":"05003",
    "addr:street":"Calle De Cuesta Antigua;A\u0301Vila",
    "iso:country":"ES",
    "sg:address":"Calle de Cuesta Antigua, 8",
    "sg:city":"Avila",
    "sg:orig_category":"Peluqueros: De Se\u00d1oras",
    "sg:phone":"+34 920 25 51 69",
    "sg:postcode":"05003",
    "sg:province":"\u00c1vila",
    "wof:name":"Jimenez Martin Javier",
    "wof:placetype":"venue"
},
  "geometry": {"coordinates":[-4.6947317123,40.6535186768],"type":"Point"}
}