{
  "type": "Feature",
  "properties": {
    "iso:country":"ES",
    "sg:address":"Carr Rambla, De La, 35",
    "sg:city":"Campos",
    "sg:orig_category":"Centros Comerciales Y Grandes Tiendas",
    "sg:phone":"+34 971 65 15 06",
    "sg:postcode":"07630",
    "sg:province":"Islas Baleares",
    "wof:name":"Fumisteria Mitjorn S.l.",
    "wof:placetype":"venue"
},
  "geometry": {"coordinates":[3.0197050571,39.430480957],"type":"Point"}
}