{
  "type": "Feature",
  "properties": {
    "iso:country":"ES",
    "sg:address":"Unica, 1",
    "sg:city":"Lecina",
    "sg:orig_category":"Albergues",
    "sg:phone":"+34 974 34 30 70",
    "sg:postcode":"22148",
    "sg:province":"Huesca",
    "wof:name":"Blasco Franco Miguel Angel",
    "wof:placetype":"venue"
},
  "geometry": {"coordinates":[0.0706069991,42.241317749],"type":"Point"}
}