{
  "type": "Feature",
  "properties": {
    "addr:full":"Calle de Redonda De La Estacion, 56 Pedro Abad C\u00f3rdoba 14630",
    "addr:housenumber":"56",
    "addr:postcode":"14630",
    "addr:street":"Calle De Redonda De La Estacion",
    "iso:country":"ES",
    "sg:address":"Calle de Redonda De La Estacion, 56",
    "sg:city":"Pedro Abad",
    "sg:orig_category":"Puertas Y Portales",
    "sg:phone":"+34 957 18 62 35",
    "sg:postcode":"14630",
    "sg:province":"C\u00f3rdoba",
    "wof:name":"Meramadera S.l.",
    "wof:placetype":"venue"
},
  "geometry": {"coordinates":[-4.4539580345,37.9671363831],"type":"Point"}
}