{
  "type": "Feature",
  "properties": {
    "addr:full":"Carrer de Riera De La Creu, 42 Hospitalet Llobregat Barcelona 08901",
    "addr:housenumber":"42",
    "addr:postcode":"08901",
    "addr:street":"Carrer De Riera De La Creu",
    "iso:country":"ES",
    "sg:address":"Carrer de Riera De La Creu, 42",
    "sg:city":"Hospitalet Llobregat",
    "sg:orig_category":"Peluqueros: De Se\u00d1oras",
    "sg:phone":"+34 933 37 32 83",
    "sg:postcode":"08901",
    "sg:province":"Barcelona",
    "wof:name":"Velasco Lopez Jose Antonio",
    "wof:placetype":"venue"
},
  "geometry": {"coordinates":[2.105494976,41.3626899719],"type":"Point"}
}