{
  "type": "Feature",
  "properties": {
    "addr:full":"Rbla Joaquim Vayreda, 53 Gava Barcelona 08850",
    "addr:housenumber":"53",
    "addr:postcode":"08850",
    "addr:street":"Rbla Joaquim Vayreda",
    "iso:country":"ES",
    "sg:address":"Rbla Joaquim Vayreda, 53",
    "sg:city":"Gava",
    "sg:orig_category":"Cajas De Ahorro",
    "sg:phone":"+34 936 62 17 85",
    "sg:postcode":"08850",
    "sg:province":"Barcelona",
    "wof:name":"Caixa D'estalvis De Catalunya",
    "wof:placetype":"venue"
},
  "geometry": {"coordinates":[2.0075170994,41.3052062988],"type":"Point"}
}