{
  "type": "Feature",
  "properties": {
    "iso:country":"ES",
    "sg:address":"Carrer de Ramon Berenguer Iv, 5",
    "sg:city":"Cambrils",
    "sg:orig_category":"Reposter\u00cdas",
    "sg:phone":"+34 977 36 19 11",
    "sg:postcode":"43850",
    "sg:province":"Tarragona",
    "wof:name":"Pastisseria L'eixample S.l.",
    "wof:placetype":"venue"
},
  "geometry": {"coordinates":[1.0534739494,41.0712776184],"type":"Point"}
}