{
  "type": "Feature",
  "properties": {
    "addr:full":"Ctra Denia, 27 Pego Alicante 03780",
    "addr:housenumber":"27",
    "addr:postcode":"03780",
    "addr:street":"Ctra Denia",
    "iso:country":"ES",
    "sg:address":"Ctra Denia, 27",
    "sg:city":"Pego",
    "sg:orig_category":"Chapister\u00cda",
    "sg:phone":"+34 965 57 10 71",
    "sg:postcode":"03780",
    "sg:province":"Alicante",
    "wof:name":"Ramirez Femenia Antonio",
    "wof:placetype":"venue"
},
  "geometry": {"coordinates":[-0.1140760034,38.8430252075],"type":"Point"}
}