{
  "type": "Feature",
  "properties": {
    "iso:country":"ES",
    "sg:address":"Carr Isabel La Catolica, 25",
    "sg:city":"Olleria",
    "sg:orig_category":"Ropa Para Se\u00d1oras Y Caballeros (al Por Menor)",
    "sg:phone":"+34 962 20 04 83",
    "sg:postcode":"46850",
    "sg:province":"Valencia",
    "wof:name":"Juan Vidal Maria Isabel",
    "wof:placetype":"venue"
},
  "geometry": {"coordinates":[-0.5509819984,38.9149665833],"type":"Point"}
}