{
  "type": "Feature",
  "properties": {
    "iso:country":"ES",
    "sg:address":"Avda Burguillos, 35",
    "sg:city":"Guillena",
    "sg:orig_category":"Molduras, Junquillos, Listones Y Molduras Perforadas",
    "sg:phone":"+34 955 78 58 00",
    "sg:postcode":"41210",
    "sg:province":"Sevilla",
    "wof:name":"Diaz Rey Ana",
    "wof:placetype":"venue"
},
  "geometry": {"coordinates":[-6.0547299385,37.5486030579],"type":"Point"}
}