{
  "type": "Feature",
  "properties": {
    "iso:country":"ES",
    "sg:address":"Pje. Postas, 11",
    "sg:city":"Vitoria-gasteiz",
    "sg:orig_category":"Agencias De Viajes",
    "sg:phone":"+34 945 14 10 10",
    "sg:postcode":"01001",
    "sg:province":"\u00c1lava",
    "wof:name":"Viajes Alaska S. A.",
    "wof:placetype":"venue"
},
  "geometry": {"coordinates":[-2.6705870628,42.8459854126],"type":"Point"}
}