{
  "type": "Feature",
  "properties": {
    "iso:country":"ES",
    "sg:address":"Scho Mayor, 13",
    "sg:city":"Iru\u00f1a",
    "sg:orig_category":"Bisuter\u00cda, Joyer\u00cda, Relojer\u00cda (al Por Menor)",
    "sg:phone":"+34 948 22 37 65",
    "sg:postcode":"31002",
    "sg:province":"Navarra",
    "wof:name":"Optica Julio Ezpeleta S.l.",
    "wof:placetype":"venue"
},
  "geometry": {"coordinates":[-1.6437540054,42.81275177],"type":"Point"}
}