{
  "type": "Feature",
  "properties": {
    "iso:country":"ES",
    "sg:address":"Ctra Tangel, 5",
    "sg:city":"Villafranqueza",
    "sg:orig_category":"Empresas De Carpinter\u00cda De Madera",
    "sg:phone":"+34 965 17 54 55",
    "sg:postcode":"03112",
    "sg:province":"Alicante",
    "wof:name":"Lopez Egido Juan Carlos",
    "wof:placetype":"venue"
},
  "geometry": {"coordinates":[-0.4896889925,38.3873558044],"type":"Point"}
}