{
  "type": "Feature",
  "properties": {
    "iso:country":"ES",
    "sg:address":"Calle de Enrique Reig, 12",
    "sg:city":"Paiporta",
    "sg:orig_category":"Arquitectos",
    "sg:phone":"+34 963 97 15 84",
    "sg:postcode":"46200",
    "sg:province":"Valencia",
    "wof:name":"Montesa Peris Enrique",
    "wof:placetype":"venue"
},
  "geometry": {"coordinates":[-0.4176320136,39.4244422913],"type":"Point"}
}