{
  "type": "Feature",
  "properties": {
    "addr:full":"Avda America, 101 Zaragoza Zaragoza 50007",
    "addr:housenumber":"101",
    "addr:postcode":"50007",
    "addr:street":"Avda America",
    "iso:country":"ES",
    "sg:address":"Avda America, 101",
    "sg:city":"Zaragoza",
    "sg:orig_category":"Centros Comerciales Y Grandes Tiendas",
    "sg:phone":"+34 976 27 64 39",
    "sg:postcode":"50007",
    "sg:province":"Zaragoza",
    "wof:name":"Universal Del Regalo S.l.",
    "wof:placetype":"venue"
},
  "geometry": {"coordinates":[-0.8864889741,41.6275291443],"type":"Point"}
}