{
  "type": "Feature",
  "properties": {
    "iso:country":"ES",
    "sg:address":"Urb San Jeronimo, S/n",
    "sg:city":"San Jeronimo",
    "sg:orig_category":"Inmobiliaria (agencias)",
    "sg:phone":"+34 922 32 33 60",
    "sg:postcode":"38312",
    "sg:province":"Santa Cruz De Tenerife",
    "wof:name":"Gestion Inmobiliaria Orotava S.l.",
    "wof:placetype":"venue"
},
  "geometry": {"coordinates":[-16.5448322296,28.3948001862],"type":"Point"}
}