{
  "type": "Feature",
  "properties": {
    "addr:full":"Carrer de Valencia, 281 Barcelona Barcelona 08009",
    "addr:housenumber":"281",
    "addr:postcode":"08009",
    "addr:street":"Carrer De Valencia",
    "iso:country":"ES",
    "sg:address":"Carrer de Valencia, 281",
    "sg:city":"Barcelona",
    "sg:orig_category":"Psic\u00d3logos",
    "sg:phone":"+34 932 15 03 44",
    "sg:postcode":"08009",
    "sg:province":"Barcelona",
    "wof:name":"Centre Emili Mira S.c.p.",
    "wof:placetype":"venue"
},
  "geometry": {"coordinates":[2.1659460068,41.3948707581],"type":"Point"}
}