{
  "type": "Feature",
  "properties": {
    "addr:full":"Carretera De Albaladejo, Km. 0010,0 Villanueva Fuente Ciudad Real 13330",
    "addr:postcode":"13330",
    "addr:street":"Carretera De Albaladejo Km. 0010,0 Villanueva Fuente",
    "iso:country":"ES",
    "sg:address":"Carretera De Albaladejo, Km. 0010,0",
    "sg:city":"Villanueva Fuente",
    "sg:orig_category":"Comunidades Religiosas",
    "sg:phone":"+34 967 58 10 72",
    "sg:postcode":"13330",
    "sg:province":"Ciudad Real",
    "wof:name":"Hermandad Del Santisimo Cristo Del Consuelo Y Nuestra Se\u00f1ora De Los Desamparados",
    "wof:placetype":"venue"
},
  "geometry": {"coordinates":[-2.6923899651,38.6956100464],"type":"Point"}
}