{
  "type": "Feature",
  "properties": {
    "iso:country":"ES",
    "sg:address":"B, 8",
    "sg:city":"Irurtzun",
    "sg:orig_category":"Agentes, Concesionarios Y Sucursales De Veh\u00cdculos",
    "sg:phone":"+34 948 50 02 09",
    "sg:postcode":"31860",
    "sg:province":"Navarra",
    "wof:name":"Urriza Amorena Fermin",
    "wof:placetype":"venue"
},
  "geometry": {"coordinates":[-1.8282489777,42.9185066223],"type":"Point"}
}