{
  "type": "Feature",
  "properties": {
    "addr:full":"Calle de Iglesia, 11 Ejido Almer\u00eda 04700",
    "addr:housenumber":"11 ejido",
    "addr:postcode":"04700",
    "addr:street":"Calle De Iglesia;Almeri\u0301A",
    "iso:country":"ES",
    "sg:address":"Calle de Iglesia, 11",
    "sg:city":"Ejido",
    "sg:orig_category":"\u00d3ptica: Instrumentos (fabricaci\u00d3n)",
    "sg:phone":"+34 950 48 56 09",
    "sg:postcode":"04700",
    "sg:province":"Almer\u00eda",
    "wof:name":"Multiopticas Cuadrado S.a.",
    "wof:placetype":"venue"
},
  "geometry": {"coordinates":[-2.8145389557,36.7737197876],"type":"Point"}
}