{
  "type": "Feature",
  "properties": {
    "iso:country":"ES",
    "sg:address":"Calle de Esta\u00d1o, 6",
    "sg:city":"San Vicente Del Raspeig-sant Vicent Del Raspeig",
    "sg:orig_category":"Servicio De Salud",
    "sg:phone":"+34 965 67 22 29",
    "sg:postcode":"03690",
    "sg:province":"Alicante",
    "wof:name":"Material De Construccion Madrid Hermanos S.l.",
    "wof:placetype":"venue"
},
  "geometry": {"coordinates":[-0.510191977,38.3875656128],"type":"Point"}
}