{
  "type": "Feature",
  "properties": {
    "iso:country":"ES",
    "sg:address":"Calle de Barca, 47",
    "sg:city":"Arcos De La Polvorosa",
    "sg:orig_category":"Bosques (trabajos, Asesor\u00cda, Gesti\u00d3n)",
    "sg:phone":"+34 980 65 40 58",
    "sg:postcode":"49699",
    "sg:province":"Zamora",
    "wof:name":"H.e.a.g. S.a.t.",
    "wof:placetype":"venue"
},
  "geometry": {"coordinates":[-5.6972093582,41.9443588257],"type":"Point"}
}