{
  "type": "Feature",
  "properties": {
    "addr:full":"Calle de Miguel Solas, 19 Madrid Madrid 28021",
    "addr:housenumber":"19",
    "addr:postcode":"madrid;28021",
    "addr:street":"Calle De Miguel Solas",
    "iso:country":"ES",
    "sg:address":"Calle de Miguel Solas, 19",
    "sg:city":"Madrid",
    "sg:classifiers":[
        {
            "category":"Personal",
            "subcategory":"Barber",
            "type":"Services"
        }
    ],
    "sg:phone":"+34 917 97 32 64",
    "sg:postcode":"28021",
    "sg:province":"Madrid",
    "sg:tags":[
        "caballeros",
        "de",
        "peluqueros"
    ],
    "wof:name":"Diaz Gegundez Vicente",
    "wof:placetype":"venue"
},
  "geometry": {"coordinates":[-3.681180954,40.351650238],"type":"Point"}
}