{
  "type": "Feature",
  "properties": {
    "addr:full":"Rua Santo Domingo, 18 Ourense Ourense 32003",
    "addr:housenumber":"18",
    "addr:postcode":"32003",
    "addr:street":"Rua Santo Domingo",
    "iso:country":"ES",
    "sg:address":"Rua Santo Domingo, 18",
    "sg:city":"Ourense",
    "sg:orig_category":"Paisajistas Asesor\u00cda",
    "sg:phone":"+34 988 23 49 74",
    "sg:postcode":"32003",
    "sg:province":"Ourense",
    "wof:name":"Viveiros Centro Xardin S.l.",
    "wof:placetype":"venue"
},
  "geometry": {"coordinates":[-7.8631629944,42.3380203247],"type":"Point"}
}