{
  "type": "Feature",
  "properties": {
    "addr:full":"Calle de Real, 6 Herrera Duque Badajoz 06670",
    "addr:housenumber":"6",
    "addr:postcode":"06670",
    "addr:street":"Calle De Real",
    "iso:country":"ES",
    "sg:address":"Calle de Real, 6",
    "sg:city":"Herrera Duque",
    "sg:orig_category":"Electrodom\u00c9sticos (fabricaci\u00d3n, Al Por Mayor)",
    "sg:phone":"+34 924 64 20 13",
    "sg:postcode":"06670",
    "sg:province":"Badajoz",
    "wof:name":"Electrodomesticos Comercial Diaz Mateos",
    "wof:placetype":"venue"
},
  "geometry": {"coordinates":[-5.0465621948,39.167011261],"type":"Point"}
}