{
  "type": "Feature",
  "properties": {
    "iso:country":"ES",
    "sg:address":"Calle de Timanfaya (de), 8",
    "sg:city":"Humanes De Madrid",
    "sg:orig_category":"Muebles",
    "sg:phone":"+34 916 97 59 57",
    "sg:postcode":"28970",
    "sg:province":"Madrid",
    "wof:name":"Muebles Juma S.l.",
    "wof:placetype":"venue"
},
  "geometry": {"coordinates":[-3.8182609081,40.2720718384],"type":"Point"}
}