{
  "type": "Feature",
  "properties": {
    "iso:country":"ES",
    "sg:address":"Carrer de Pins, 1",
    "sg:city":"Sabadell",
    "sg:orig_category":"Centros De Educaci\u00d3n Especial",
    "sg:phone":"+34 937 16 83 51",
    "sg:postcode":"08207",
    "sg:province":"Barcelona",
    "wof:name":"Collegi Public Floresta",
    "wof:placetype":"venue"
},
  "geometry": {"coordinates":[2.0891029835,41.5756835938],"type":"Point"}
}