{
  "type": "Feature",
  "properties": {
    "iso:country":"ES",
    "sg:address":"Calle de Jorge Juan, 21",
    "sg:city":"Valencia",
    "sg:orig_category":"Lencer\u00cda Femenina, Corseter\u00cda, Trajes De Ba\u00d1o (al Por Menor)",
    "sg:phone":"+34 963 52 05 06",
    "sg:postcode":"46004",
    "sg:province":"Valencia",
    "wof:name":"La Luna De La Galeria Cb",
    "wof:placetype":"venue"
},
  "geometry": {"coordinates":[-0.3685370088,39.4683685303],"type":"Point"}
}