{
  "type": "Feature",
  "properties": {
    "iso:country":"ES",
    "sg:address":"Pg Saralegui, 124",
    "sg:city":"Puerto De Pollen\u00c7a",
    "sg:orig_category":"Oficinas De Cambio",
    "sg:phone":"+34 971 86 59 98",
    "sg:postcode":"07470",
    "sg:province":"Islas Baleares",
    "wof:name":"Locales Playa Blanca S.l.",
    "wof:placetype":"venue"
},
  "geometry": {"coordinates":[3.0803785324,39.9030761719],"type":"Point"}
}