{
  "type": "Feature",
  "properties": {
    "addr:full":"Carrer de Sant Llatzer, 4 Palma Islas Baleares 07005",
    "addr:housenumber":"4",
    "addr:postcode":"07005",
    "addr:street":"Carrer De Sant Llatzer",
    "iso:country":"ES",
    "sg:address":"Carrer de Sant Llatzer, 4",
    "sg:city":"Palma",
    "sg:orig_category":"Albergues",
    "sg:phone":"+34 971 42 04 36",
    "sg:postcode":"07005",
    "sg:province":"Islas Baleares",
    "wof:name":"Segui Riutort 2001 Distribuciones S.l.",
    "wof:placetype":"venue"
},
  "geometry": {"coordinates":[2.6618769169,39.5761413574],"type":"Point"}
}