{
  "type": "Feature",
  "properties": {
    "addr:full":"Carr Costa Brava, 272 Vidreres Girona 17411",
    "addr:housenumber":"272",
    "addr:postcode":"17411",
    "addr:street":"Carr Costa Brava",
    "iso:country":"ES",
    "sg:address":"Carr Costa Brava, 272",
    "sg:city":"Vidreres",
    "sg:orig_category":"Sanatorios M\u00c9dico",
    "sg:phone":"+34 972 85 01 56",
    "sg:postcode":"17411",
    "sg:province":"Girona",
    "wof:name":"Ajuntament De Vidreres",
    "wof:placetype":"venue"
},
  "geometry": {"coordinates":[2.7803854942,41.7901000977],"type":"Point"}
}