{
  "type": "Feature",
  "properties": {
    "iso:country":"ES",
    "sg:address":"Calle de Doctor Martin Gonzalez, 10",
    "sg:city":"Sauces",
    "sg:orig_category":"Ense\u00d1anza, Formaci\u00d3n Profesional: Aprendizaje",
    "sg:phone":"+34 922 45 06 16",
    "sg:postcode":"38720",
    "sg:province":"Santa Cruz De Tenerife",
    "wof:name":"Isonorte Empleo S.l.u.",
    "wof:placetype":"venue"
},
  "geometry": {"coordinates":[-17.7733020782,28.804977417],"type":"Point"}
}