{
  "type": "Feature",
  "properties": {
    "iso:country":"ES",
    "sg:address":"Z Parque Comercial Galaria, 1",
    "sg:city":"Cordovilla",
    "sg:orig_category":"Ropa Y Accesorios",
    "sg:phone":"+34 948 29 22 47",
    "sg:postcode":"31191",
    "sg:province":"Navarra",
    "sg:website":"www.pepejeans.com",
    "wof:name":"Pepe Jeans S.l.",
    "wof:placetype":"venue"
},
  "geometry": {"coordinates":[-1.6518089771,42.7533912659],"type":"Point"}
}