{
  "type": "Feature",
  "properties": {
    "iso:country":"ES",
    "sg:address":"Calle de Jose Martinez Ruiz-azorin, 1",
    "sg:city":"Merida",
    "sg:orig_category":"Peluquer\u00cdas, Peluquer\u00cda Mixta",
    "sg:phone":"+34 924 31 80 39",
    "sg:postcode":"06800",
    "sg:province":"Badajoz",
    "wof:name":"Martin Nevado Susana",
    "wof:placetype":"venue"
},
  "geometry": {"coordinates":[-6.341550827,38.9256744385],"type":"Point"}
}