{
  "type": "Feature",
  "properties": {
    "iso:country":"ES",
    "sg:address":"Calle de Madrid, 16",
    "sg:city":"Playa Del Ingles",
    "sg:orig_category":"Residencias De Turismo, Residencias Hoteleras",
    "sg:phone":"+34 928 76 99 86",
    "sg:postcode":"35100",
    "sg:province":"Las Palmas",
    "wof:name":"Homberg S.l.",
    "wof:placetype":"venue"
},
  "geometry": {"coordinates":[-15.5647001266,27.7607803345],"type":"Point"}
}