{
  "type": "Feature",
  "properties": {
    "iso:country":"ES",
    "sg:address":"Carrer de Cambrils, 10",
    "sg:city":"Reus",
    "sg:orig_category":"Piscinas, Accesorios, Suministros (fabricaci\u00d3n, Al Por Mayor)",
    "sg:phone":"+34 977 77 00 66",
    "sg:postcode":"43204",
    "sg:province":"Tarragona",
    "wof:name":"Garcia Calatayud Oscar",
    "wof:placetype":"venue"
},
  "geometry": {"coordinates":[1.1130260229,41.1516685486],"type":"Point"}
}