{
  "type": "Feature",
  "properties": {
    "iso:country":"ES",
    "sg:address":"Pase Colon De, 4",
    "sg:city":"Donostia-san Sebastian",
    "sg:orig_category":"Doctores En Medicina",
    "sg:phone":"+34 943 27 25 83",
    "sg:postcode":"20002",
    "sg:province":"Guip\u00f9zcoa",
    "wof:name":"Guerrero Pereda Rafael",
    "wof:placetype":"venue"
},
  "geometry": {"coordinates":[-1.9794000387,43.3173789978],"type":"Point"}
}