{
  "type": "Feature",
  "properties": {
    "addr:full":"Calle de Torrecilla, 53 Monesterio Badajoz 06260",
    "addr:housenumber":"53",
    "addr:postcode":"06260",
    "addr:street":"Calle De Torrecilla",
    "iso:country":"ES",
    "sg:address":"Calle de Torrecilla, 53",
    "sg:city":"Monesterio",
    "sg:orig_category":"Alimentaci\u00d3n General (al Por Menor)",
    "sg:phone":"+34 924 51 61 02",
    "sg:postcode":"06260",
    "sg:province":"Badajoz",
    "wof:name":"Quintero Vargas Antonio",
    "wof:placetype":"venue"
},
  "geometry": {"coordinates":[-6.2719488144,38.0891418457],"type":"Point"}
}