{
  "type": "Feature",
  "properties": {
    "iso:country":"ES",
    "sg:address":"Carrer de Galileu, 117",
    "sg:city":"Barcelona",
    "sg:orig_category":"Comercio De Cuadros, L\u00c1minas Y Reproducciones De Obras De Arte",
    "sg:phone":"+34 933 39 83 47",
    "sg:postcode":"08028",
    "sg:province":"Barcelona",
    "wof:name":"Teixeira Esteves Jorge Manuel",
    "wof:placetype":"venue"
},
  "geometry": {"coordinates":[2.1343588829,41.3790550232],"type":"Point"}
}