{
  "type": "Feature",
  "properties": {
    "addr:full":"Carrer de Lluis Sagnier, 5 Barcelona Barcelona 08041",
    "addr:housenumber":"5",
    "addr:postcode":"08041",
    "addr:street":"Carrer De Lluis Sagnier",
    "iso:country":"ES",
    "sg:address":"Carrer de Lluis Sagnier, 5",
    "sg:city":"Barcelona",
    "sg:orig_category":"Confecci\u00d3n De Trajes Para Se\u00d1oras",
    "sg:phone":"+34 934 08 22 47",
    "sg:postcode":"08041",
    "sg:province":"Barcelona",
    "wof:name":"Pontini Vittorio S. L.",
    "wof:placetype":"venue"
},
  "geometry": {"coordinates":[2.1769208908,41.423828125],"type":"Point"}
}