{
  "type": "Feature",
  "properties": {
    "addr:full":"Calle de Fueros, 1 Salvatierra O Agurain \u00c1lava 01200",
    "addr:housenumber":"1",
    "addr:postcode":"01200",
    "addr:street":"Calle De Fueros;A\u0301Lava",
    "iso:country":"ES",
    "sg:address":"Calle de Fueros, 1",
    "sg:city":"Salvatierra O Agurain",
    "sg:orig_category":"Freidur\u00cdas",
    "sg:phone":"+34 945 31 46 44",
    "sg:postcode":"01200",
    "sg:province":"\u00c1lava",
    "sg:website":"www.celig\u00dceta.com",
    "wof:name":"Celigueta S.a.",
    "wof:placetype":"venue"
},
  "geometry": {"coordinates":[-2.3874919415,42.8493881226],"type":"Point"}
}