{
  "type": "Feature",
  "properties": {
    "iso:country":"ES",
    "sg:address":"Calle de Torilejo, S/n",
    "sg:city":"Zurbaran",
    "sg:orig_category":"Inform\u00c1tica, Ofim\u00c1tica (estudios, Asesor\u00cda, Ingenier\u00cda, Formaci\u00d3n)",
    "sg:phone":"+34 971 47 83 93",
    "sg:postcode":"07008",
    "sg:province":"Islas Baleares",
    "sg:website":"www.caeb.es",
    "wof:name":"Confederacion De Asociaciones Empresariales De Baleares",
    "wof:placetype":"venue"
},
  "geometry": {"coordinates":[2.6823298931,39.5913238525],"type":"Point"}
}