{
  "type": "Feature",
  "properties": {
    "iso:country":"ES",
    "sg:address":"Calle de Juan De Bethencourt Dominguez, 20",
    "sg:city":"Arucas",
    "sg:classifiers":[
        {
            "category":"Autos & Motor Vehicles",
            "subcategory":"Automobile Sales",
            "type":"Retail Goods"
        }
    ],
    "sg:phone":"+34 928 60 02 21",
    "sg:postcode":"35400",
    "sg:province":"Las Palmas",
    "sg:website":"www.aemcb.com",
    "wof:name":"Autoescuela Maria Del Carmen De Benitez S.l.",
    "wof:placetype":"venue"
},
  "geometry": {"coordinates":[-15.5250406265,28.1178569794],"type":"Point"}
}