{
  "type": "Feature",
  "properties": {
    "addr:full":"Rua Ponte Sevilla, 18 Ourense Ourense 32005",
    "addr:housenumber":"18",
    "addr:postcode":"32005",
    "addr:street":"Rua Ponte Sevilla",
    "iso:country":"ES",
    "sg:address":"Rua Ponte Sevilla, 18",
    "sg:city":"Ourense",
    "sg:orig_category":"Venta, Montaje De Neum\u00c1ticos",
    "sg:phone":"+34 988 23 01 67",
    "sg:postcode":"32005",
    "sg:province":"Ourense",
    "wof:name":"O Pi\u00f1eiral S. L.",
    "wof:placetype":"venue"
},
  "geometry": {"coordinates":[-7.8641738892,42.3149528503],"type":"Point"}
}