{
  "type": "Feature",
  "properties": {
    "iso:country":"ES",
    "sg:address":"Calle de Guadarrama, 7",
    "sg:city":"Segovia",
    "sg:orig_category":"Cerrajer\u00cda, Ferrallista",
    "sg:phone":"+34 921 44 52 74",
    "sg:postcode":"40006",
    "sg:province":"Segovia",
    "wof:name":"Tapias Rincon Jose Antonio",
    "wof:placetype":"venue"
},
  "geometry": {"coordinates":[-4.1109437943,40.9333877563],"type":"Point"}
}