{
  "type": "Feature",
  "properties": {
    "iso:country":"ES",
    "sg:address":"Pda. Granadella, S/n",
    "sg:city":"Camarles",
    "sg:orig_category":"Fabricaci\u00d3n De Quesos",
    "sg:phone":"+34 977 47 10 05",
    "sg:postcode":"43894",
    "sg:province":"Tarragona",
    "wof:name":"Quesos Perfecto Del Delta S.l.",
    "wof:placetype":"venue"
},
  "geometry": {"coordinates":[0.6632630229,40.7668151855],"type":"Point"}
}