{
  "type": "Feature",
  "properties": {
    "addr:full":"Av Joan Xxiii, 13 Masnou Barcelona 08320",
    "addr:housenumber":"13",
    "addr:postcode":"08320",
    "addr:street":"Av Joan Xxiii",
    "iso:country":"ES",
    "sg:address":"Av Joan Xxiii, 13",
    "sg:city":"Masnou",
    "sg:orig_category":"Inform\u00c1tica (estudios, Servicios, Asesor\u00cda, Formaci\u00d3n)",
    "sg:phone":"+34 935 40 07 40",
    "sg:postcode":"08320",
    "sg:province":"Barcelona",
    "wof:name":"Oliva Vert Jose Maria",
    "wof:placetype":"venue"
},
  "geometry": {"coordinates":[2.3157000542,41.4831085205],"type":"Point"}
}