{
  "type": "Feature",
  "properties": {
    "addr:full":"Calle de Huesca, 15 Monzon Huesca 22400",
    "addr:housenumber":"15",
    "addr:postcode":"22400",
    "addr:street":"Calle De Huesca",
    "iso:country":"ES",
    "sg:address":"Calle de Huesca, 15",
    "sg:city":"Monzon",
    "sg:orig_category":"Alimentaci\u00d3n General (al Por Menor)",
    "sg:phone":"+34 974 40 06 18",
    "sg:postcode":"22400",
    "sg:province":"Huesca",
    "wof:name":"Olivan Felices Vicente",
    "wof:placetype":"venue"
},
  "geometry": {"coordinates":[0.1936949939,41.9165916443],"type":"Point"}
}