{
  "type": "Feature",
  "properties": {
    "iso:country":"ES",
    "sg:address":"Plaz Villa (la), 6",
    "sg:city":"Hondon Nieves",
    "sg:orig_category":"Administraciones Regionales, Departamentales Y Locales",
    "sg:phone":"+34 965 48 02 01",
    "sg:postcode":"03688",
    "sg:province":"Alicante",
    "wof:name":"Ayuntamiento De Hondon De Las Nieves",
    "wof:placetype":"venue"
},
  "geometry": {"coordinates":[-0.8527733088,38.3084602356],"type":"Point"}
}