{
  "type": "Feature",
  "properties": {
    "addr:full":"Calle de Depositos (de Los), 2 Getafe Madrid 28903",
    "addr:housenumber":"2",
    "addr:postcode":"28903",
    "addr:street":"Calle De Depositos De Los",
    "iso:country":"ES",
    "sg:address":"Calle de Depositos (de Los), 2",
    "sg:city":"Getafe",
    "sg:orig_category":"Peluquer\u00cdas, Peluquer\u00cda Mixta",
    "sg:phone":"+34 916 65 02 76",
    "sg:postcode":"28903",
    "sg:province":"Madrid",
    "wof:name":"Campo Arcas Maria Julia Del",
    "wof:placetype":"venue"
},
  "geometry": {"coordinates":[-3.7269330025,40.3132476807],"type":"Point"}
}