{
  "type": "Feature",
  "properties": {
    "iso:country":"ES",
    "sg:address":"Calle de Castilla, 60",
    "sg:city":"Madrid",
    "sg:orig_category":"Comercio De Piezas De Recambio Y De Accesorios De Veh\u00cdculos, Veh\u00cdculos Industriales",
    "sg:phone":"+34 913 11 55 51",
    "sg:postcode":"28039",
    "sg:province":"Madrid",
    "wof:name":"Devise Y Ready S.l.",
    "wof:placetype":"venue"
},
  "geometry": {"coordinates":[-3.7076830864,40.4532165527],"type":"Point"}
}