{
  "type": "Feature",
  "properties": {
    "iso:country":"ES",
    "sg:address":"Calle de San Francisco De Paula, 3",
    "sg:city":"Puerto De Santa Maria",
    "sg:orig_category":"Negocio De Enlosados, Soler\u00cdas",
    "sg:phone":"+34 956 87 43 95",
    "sg:postcode":"11500",
    "sg:province":"C\u00e1diz",
    "wof:name":"Alvarez Martin Pedro",
    "wof:placetype":"venue"
},
  "geometry": {"coordinates":[-6.2235794067,36.6034622192],"type":"Point"}
}