{
  "type": "Feature",
  "properties": {
    "addr:full":"Avda Francisco Aguirre, 209 Talavera Reina Toledo 45600",
    "addr:housenumber":"209",
    "addr:postcode":"45600",
    "addr:street":"Avda Francisco Aguirre",
    "iso:country":"ES",
    "sg:address":"Avda Francisco Aguirre, 209",
    "sg:city":"Talavera Reina",
    "sg:orig_category":"Agentes, Concesionarios Y Sucursales De Veh\u00cdculos",
    "sg:phone":"+34 925 82 25 62",
    "sg:postcode":"45600",
    "sg:province":"Toledo",
    "wof:name":"Vallejo Fernandez Jose Luis",
    "wof:placetype":"venue"
},
  "geometry": {"coordinates":[-4.8299059868,39.968170166],"type":"Point"}
}