{
  "type": "Feature",
  "properties": {
    "iso:country":"ES",
    "sg:address":"Calle de Juan De Herrera, 38",
    "sg:city":"Malaga",
    "sg:orig_category":"Centros P\u00dablicos De Formaci\u00d3n Profesional Y T\u00c9cnica",
    "sg:phone":"+34 952 39 53 20",
    "sg:postcode":"29009",
    "sg:province":"M\u00e1laga",
    "wof:name":"Colegio Oficial De Ayudantes Tecnicos Sanitarios",
    "wof:placetype":"venue"
},
  "geometry": {"coordinates":[-4.4277701378,36.7260055542],"type":"Point"}
}