{
  "type": "Feature",
  "properties": {
    "addr:full":"C/ Antonio Mora Ferrandez, 13 Elche Alicante 03202",
    "addr:housenumber":"13",
    "addr:postcode":"03202",
    "addr:street":"C / Antonio Mora Ferrandez",
    "iso:country":"ES",
    "sg:address":"C/ Antonio Mora Ferrandez, 13",
    "sg:city":"Elche",
    "sg:orig_category":"Fisioterapia",
    "sg:phone":"+34 965 42 74 49",
    "sg:postcode":"03202",
    "sg:province":"Alicante",
    "wof:name":"Santos Herrera Juan Jose",
    "wof:placetype":"venue"
},
  "geometry": {"coordinates":[-0.685863018,38.2716255188],"type":"Point"}
}