{
  "type": "Feature",
  "properties": {
    "iso:country":"ES",
    "sg:address":"Via Augusta, 109",
    "sg:city":"Barcelona",
    "sg:orig_category":"Peluqueros: De Se\u00d1oras",
    "sg:phone":"+34 932 00 07 23",
    "sg:postcode":"08006",
    "sg:province":"Barcelona",
    "wof:name":"Anmerbea S.l.",
    "wof:placetype":"venue"
},
  "geometry": {"coordinates":[2.1478533745,41.4011421204],"type":"Point"}
}