{
  "type": "Feature",
  "properties": {
    "iso:country":"ES",
    "sg:address":"M. Ing. S. Lloveras, S/n",
    "sg:city":"Castello Plana",
    "sg:orig_category":"Organizaciones Profesionales",
    "sg:phone":"+34 964 28 23 13",
    "sg:postcode":"12100",
    "sg:province":"Castell\u00f3n",
    "sg:website":"www.consulmar.es",
    "wof:name":"Consulmar S. L.",
    "wof:placetype":"venue"
},
  "geometry": {"coordinates":[0.0176999997,39.9888801575],"type":"Point"}
}