{
  "type": "Feature",
  "properties": {
    "iso:country":"ES",
    "sg:address":"Ctra Puebla Cazalla, Km. 0001,0",
    "sg:city":"Marchena",
    "sg:orig_category":"Aperitivos (fabricaci\u00d3n Y Al Por Mayor)",
    "sg:phone":"+34 955 96 08 05",
    "sg:postcode":"41620",
    "sg:province":"Sevilla",
    "wof:name":"Aperitivos Ligeros S.a.",
    "wof:placetype":"venue"
},
  "geometry": {"coordinates":[-5.4191846848,37.3234062195],"type":"Point"}
}