{
  "type": "Feature",
  "properties": {
    "iso:country":"ES",
    "sg:address":"Calle de Alanis De La Sierra, 30",
    "sg:city":"Huelva",
    "sg:orig_category":"Vulcanizado",
    "sg:phone":"+34 959 22 19 59",
    "sg:postcode":"21007",
    "sg:province":"Huelva",
    "wof:name":"Toronjo Rodriguez Fernando",
    "wof:placetype":"venue"
},
  "geometry": {"coordinates":[-6.9264836311,37.2638549805],"type":"Point"}
}