{
  "type": "Feature",
  "properties": {
    "addr:full":"Calle de Casimiro Escudero, 2 Madrid Madrid 28025",
    "addr:housenumber":"2",
    "addr:postcode":"28025",
    "addr:street":"Calle De Casimiro Escudero",
    "iso:country":"ES",
    "sg:address":"Calle de Casimiro Escudero, 2",
    "sg:city":"Madrid",
    "sg:orig_category":"Tapicer\u00cdas",
    "sg:phone":"+34 914 61 23 68",
    "sg:postcode":"28025",
    "sg:province":"Madrid",
    "wof:name":"Blazquez Lopez Emilio",
    "wof:placetype":"venue"
},
  "geometry": {"coordinates":[-3.7422978878,40.3900260925],"type":"Point"}
}