{
  "type": "Feature",
  "properties": {
    "iso:country":"ES",
    "sg:address":"Av. Rebullon, 8",
    "sg:city":"Mos",
    "sg:orig_category":"Encuadernaci\u00d3n E Impresi\u00d3n De Folletos",
    "sg:phone":"+34 986 28 81 50",
    "sg:postcode":"36416",
    "sg:province":"Pontevedra",
    "wof:name":"Grapha Vigo S.l.",
    "wof:placetype":"venue"
},
  "geometry": {"coordinates":[-8.6638851166,42.2042388916],"type":"Point"}
}