{
  "type": "Feature",
  "properties": {
    "addr:full":"Carrer de Marcelino Menendez Pelayo, S/n Cornella Llobregat Barcelona 08940",
    "addr:housenumber":"s / n",
    "addr:postcode":"08940",
    "addr:street":"Carrer De Marcelino Menendez Pelayo",
    "iso:country":"ES",
    "sg:address":"Carrer de Marcelino Menendez Pelayo, S/n",
    "sg:city":"Cornella Llobregat",
    "sg:classifiers":[
        {
            "category":"Arts & Performance",
            "subcategory":"Art Gallery",
            "type":"Entertainment"
        }
    ],
    "sg:phone":"+34 933 77 38 46",
    "sg:postcode":"08940",
    "sg:province":"Barcelona",
    "sg:tags":[
        "arte",
        "de",
        "galer\u00cdas"
    ],
    "wof:name":"Marne Medina Natividad",
    "wof:placetype":"venue"
},
  "geometry": {"coordinates":[2.0724248886,41.3540458679],"type":"Point"}
}