{
  "type": "Feature",
  "properties": {
    "addr:full":"Pol Ind Riu Clar, 38 Tarragona Tarragona 43006",
    "addr:housenumber":"38",
    "addr:postcode":"43006",
    "iso:country":"ES",
    "sg:address":"Pol Ind Riu Clar, 38",
    "sg:city":"Tarragona",
    "sg:orig_category":"Limpieza Industrial",
    "sg:phone":"+34 977 54 96 47",
    "sg:postcode":"43006",
    "sg:province":"Tarragona",
    "wof:name":"Copevac S.l.",
    "wof:placetype":"venue"
},
  "geometry": {"coordinates":[1.2209249735,41.1154441833],"type":"Point"}
}