{
  "type": "Feature",
  "properties": {
    "iso:country":"ES",
    "sg:address":"Calle de Granadera Canaria, 2",
    "sg:city":"Palmas De Gran Canaria",
    "sg:orig_category":"Registros",
    "sg:phone":"+34 928 31 06 00",
    "sg:postcode":"35001",
    "sg:province":"Las Palmas",
    "wof:name":"Gobierno De Canarias",
    "wof:placetype":"venue"
},
  "geometry": {"coordinates":[-15.4123392105,28.0963802338],"type":"Point"}
}