{
  "type": "Feature",
  "properties": {
    "iso:country":"ES",
    "sg:address":"Avda Vigo, 120",
    "sg:city":"Angoren",
    "sg:orig_category":"Imprenta",
    "sg:phone":"+34 986 45 33 26",
    "sg:postcode":"36320",
    "sg:province":"Pontevedra",
    "wof:name":"Rodriguez Prieto Maria Del Pilar",
    "wof:placetype":"venue"
},
  "geometry": {"coordinates":[-8.6428003311,42.4304618835],"type":"Point"}
}