{
  "type": "Feature",
  "properties": {
    "iso:country":"ES",
    "sg:address":"Calle de Enrique Cubero, 156",
    "sg:city":"Valladolid",
    "sg:orig_category":"Escuela De Arte Dram\u00c1tico",
    "sg:phone":"+34 983 33 06 03",
    "sg:postcode":"47014",
    "sg:province":"Valladolid",
    "wof:name":"Formacal S.l.",
    "wof:placetype":"venue"
},
  "geometry": {"coordinates":[-4.7680830956,41.6362876892],"type":"Point"}
}