{
  "type": "Feature",
  "properties": {
    "addr:full":"Ctra Alcoy, Km. 0021,0 Banyeres Mariola Alicante 03450",
    "addr:postcode":"03450",
    "addr:street":"Ctra Alcoy Km. 0021,0",
    "iso:country":"ES",
    "sg:address":"Ctra Alcoy, Km. 0021,0",
    "sg:city":"Banyeres Mariola",
    "sg:orig_category":"Fabricaci\u00d3n De Telas Y Sedas",
    "sg:phone":"+34 965 56 62 43",
    "sg:postcode":"03450",
    "sg:province":"Alicante",
    "sg:website":"www.rizonature.com",
    "wof:name":"Rizonature S.l.",
    "wof:placetype":"venue"
},
  "geometry": {"coordinates":[-0.6580740213,38.7120857239],"type":"Point"}
}