{
  "type": "Feature",
  "properties": {
    "addr:full":"Calle de Moncayo, 4 Santa Maria De Gracia Murcia 30009",
    "addr:housenumber":"4",
    "addr:postcode":"30009",
    "addr:street":"Calle De Moncayo",
    "iso:country":"ES",
    "sg:address":"Calle de Moncayo, 4",
    "sg:city":"Santa Maria De Gracia",
    "sg:orig_category":"Aparatos, Material Y Suministros Para Laboratorios",
    "sg:phone":"+34 968 29 35 02",
    "sg:postcode":"30009",
    "sg:province":"Murcia",
    "wof:name":"Radiometer Iberica S.a.",
    "wof:placetype":"venue"
},
  "geometry": {"coordinates":[-1.1393220425,37.9941101074],"type":"Point"}
}