{
  "type": "Feature",
  "properties": {
    "addr:full":"Pase Alameda (la), 23 Constantina Sevilla 41450",
    "addr:housenumber":"23",
    "addr:postcode":"41450",
    "addr:street":"Alameda La",
    "iso:country":"ES",
    "sg:address":"Pase Alameda (la), 23",
    "sg:city":"Constantina",
    "sg:orig_category":"Fabricaci\u00d3n Y Refinado De Az\u00dacares",
    "sg:phone":"+34 955 88 06 83",
    "sg:postcode":"41450",
    "sg:province":"Sevilla",
    "wof:name":"Alvarez Fuertes Carlos",
    "wof:placetype":"venue"
},
  "geometry": {"coordinates":[-5.6218881607,37.8773498535],"type":"Point"}
}