{
  "type": "Feature",
  "properties": {
    "addr:full":"Calle de Santa Teresa De Jesus, 11 Ronda M\u00e1laga 29400",
    "addr:housenumber":"11",
    "addr:postcode":"29400",
    "addr:street":"Calle De Santa Teresa De Jesus;Ronda Ma\u0301Laga",
    "iso:country":"ES",
    "sg:address":"Calle de Santa Teresa De Jesus, 11",
    "sg:city":"Ronda",
    "sg:orig_category":"Tapicer\u00cdas",
    "sg:phone":"+34 952 87 80 97",
    "sg:postcode":"29400",
    "sg:province":"M\u00e1laga",
    "wof:name":"Sanchez Ramirez Jose Maria",
    "wof:placetype":"venue"
},
  "geometry": {"coordinates":[-5.1543588638,36.7525024414],"type":"Point"}
}