{
  "type": "Feature",
  "properties": {
    "iso:country":"ES",
    "sg:address":"Calle de San Pedro (de), 39",
    "sg:city":"Coslada",
    "sg:orig_category":"Peluquer\u00cdas, Peluquer\u00cda Mixta",
    "sg:phone":"+34 916 71 28 98",
    "sg:postcode":"28820",
    "sg:province":"Madrid",
    "wof:name":"Lopez Sanchez Manuel",
    "wof:placetype":"venue"
},
  "geometry": {"coordinates":[-3.5394608974,40.4307365417],"type":"Point"}
}