{
  "type": "Feature",
  "properties": {
    "addr:full":"Carrer de Sant Joan, 6 Premia Mar Barcelona 08330",
    "addr:housenumber":"6",
    "addr:postcode":"08330",
    "addr:street":"Carrer De Sant Joan",
    "iso:country":"ES",
    "sg:address":"Carrer de Sant Joan, 6",
    "sg:city":"Premia Mar",
    "sg:orig_category":"Fabricaci\u00d3n De Su\u00c9ters Y Chalecos De Punto",
    "sg:phone":"+34 937 52 27 65",
    "sg:postcode":"08330",
    "sg:province":"Barcelona",
    "wof:name":"Textil Premia S.l.",
    "wof:placetype":"venue"
},
  "geometry": {"coordinates":[2.3596110344,41.49010849],"type":"Point"}
}