{
  "type": "Feature",
  "properties": {
    "iso:country":"ES",
    "sg:address":"Calle de Cayetano Tueros, 4",
    "sg:city":"Castro Urdiales",
    "sg:orig_category":"Laboratorios Y Cl\u00cdnicas Veterinarias",
    "sg:phone":"+34 942 86 36 73",
    "sg:postcode":"39700",
    "sg:province":"Cantabria",
    "wof:name":"Martinez Abaigar Teresa",
    "wof:placetype":"venue"
},
  "geometry": {"coordinates":[-3.2208664417,43.3843841553],"type":"Point"}
}