{
  "type": "Feature",
  "properties": {
    "addr:full":"B. Bajo, S/n Paulenca Granada 18519",
    "addr:housenumber":"s",
    "addr:postcode":"18519",
    "addr:street":"/ N Paulenca",
    "iso:country":"ES",
    "sg:address":"B. Bajo, S/n",
    "sg:city":"Paulenca",
    "sg:orig_category":"Serigraf\u00cda (material Y Suministros)",
    "sg:phone":"+34 958 66 13 11",
    "sg:postcode":"18519",
    "sg:province":"Granada",
    "wof:name":"Plaza Serrano Miguel",
    "wof:placetype":"venue"
},
  "geometry": {"coordinates":[-2.4648249149,37.9993972778],"type":"Point"}
}