{
  "type": "Feature",
  "properties": {
    "iso:country":"ES",
    "sg:address":"Calle de Sebastian Fernandez De Leceta, 11",
    "sg:city":"Vitoria-gasteiz",
    "sg:orig_category":"Agencias Y Agentes Comerciales, Representantes",
    "sg:phone":"+34 945 20 04 25",
    "sg:postcode":"01009",
    "sg:province":"\u00c1lava",
    "wof:name":"Metacom Representaciones S.l.",
    "wof:placetype":"venue"
},
  "geometry": {"coordinates":[-2.6825370789,42.8514060974],"type":"Point"}
}