{
  "type": "Feature",
  "properties": {
    "iso:country":"ES",
    "sg:address":"Calle de Zacarias Martinez, 30",
    "sg:city":"Huesca",
    "sg:orig_category":"Molduras, Junquillos, Listones Y Molduras Perforadas",
    "sg:phone":"+34 974 22 74 42",
    "sg:postcode":"22006",
    "sg:province":"Huesca",
    "wof:name":"Bar La Brasa Hermanos Saz S.l.",
    "wof:placetype":"venue"
},
  "geometry": {"coordinates":[-0.3936690092,42.1410903931],"type":"Point"}
}