{
  "type": "Feature",
  "properties": {
    "addr:full":"Calle de Floranes, 30 Santander Cantabria 39010",
    "addr:housenumber":"30",
    "addr:postcode":"39010",
    "addr:street":"Calle De Floranes",
    "iso:country":"ES",
    "sg:address":"Calle de Floranes, 30",
    "sg:city":"Santander",
    "sg:orig_category":"Aparatos, Sistemas De Tele",
    "sg:phone":"+34 942 23 55 34",
    "sg:postcode":"39010",
    "sg:province":"Cantabria",
    "wof:name":"Eurodos Seguridad S.l.",
    "wof:placetype":"venue"
},
  "geometry": {"coordinates":[-3.8220291138,43.4605903625],"type":"Point"}
}