{
  "type": "Feature",
  "properties": {
    "addr:full":"Carrer de Cal Bolet, 39 Vilafranca Penedes Barcelona 08720",
    "addr:housenumber":"39",
    "addr:postcode":"08720",
    "addr:street":"Carrer De Cal Bolet",
    "iso:country":"ES",
    "sg:address":"Carrer de Cal Bolet, 39",
    "sg:city":"Vilafranca Penedes",
    "sg:orig_category":"Maquinaria Para Industrias Diversas",
    "sg:phone":"+34 938 17 33 80",
    "sg:postcode":"08720",
    "sg:province":"Barcelona",
    "wof:name":"Sebastian Allue S.l.",
    "wof:placetype":"venue"
},
  "geometry": {"coordinates":[1.6999700069,41.3441810608],"type":"Point"}
}