{
  "type": "Feature",
  "properties": {
    "iso:country":"ES",
    "sg:address":"Calle de Sebastian Elcano, 9",
    "sg:city":"Ceuti",
    "sg:orig_category":"Promotores Constructores",
    "sg:phone":"+34 968 69 41 06",
    "sg:postcode":"30562",
    "sg:province":"Murcia",
    "wof:name":"Construcciones Y Reformas El Bolo",
    "wof:placetype":"venue"
},
  "geometry": {"coordinates":[-1.2717039585,38.0792503357],"type":"Point"}
}