{
  "type": "Feature",
  "properties": {
    "iso:country":"ES",
    "sg:address":"Calle de Palomar, 26",
    "sg:city":"Montilla",
    "sg:orig_category":"Agencias Y Asesores De Publicidad",
    "sg:phone":"+34 957 66 40 46",
    "sg:postcode":"14550",
    "sg:province":"C\u00f3rdoba",
    "wof:name":"Montillana De Comunicaciones S.l.",
    "wof:placetype":"venue"
},
  "geometry": {"coordinates":[-4.6407990456,37.5859375],"type":"Point"}
}