{
  "type": "Feature",
  "properties": {
    "iso:country":"ES",
    "sg:address":"Calle de Don Pio Coronado, 60",
    "sg:city":"Palmas De Gran Canaria",
    "sg:orig_category":"Tapicer\u00cdas",
    "sg:phone":"+34 928 25 51 05",
    "sg:postcode":"35012",
    "sg:province":"Las Palmas",
    "wof:name":"Perez Vega Ana",
    "wof:placetype":"venue"
},
  "geometry": {"coordinates":[-15.4334049225,28.1096553802],"type":"Point"}
}