{
  "type": "Feature",
  "properties": {
    "iso:country":"ES",
    "sg:address":"Calle de Turquesa, 7",
    "sg:city":"Madrid",
    "sg:orig_category":"Internados & Ense\u00d1anza Privada",
    "sg:phone":"+34 915 05 35 25",
    "sg:postcode":"28021",
    "sg:province":"Madrid",
    "wof:name":"Colegio San Pedro S.l.",
    "wof:placetype":"venue"
},
  "geometry": {"coordinates":[-3.6863939762,40.3503952026],"type":"Point"}
}