{
  "type": "Feature",
  "properties": {
    "iso:country":"ES",
    "sg:address":"Pase Peatonal San Andres, 1",
    "sg:city":"San Agustin",
    "sg:orig_category":"Asociaciones Y Clubs Deportivos",
    "sg:phone":"+34 922 34 32 72",
    "sg:postcode":"38410",
    "sg:province":"Santa Cruz De Tenerife",
    "wof:name":"Salviu  Alcides Antonio",
    "wof:placetype":"venue"
},
  "geometry": {"coordinates":[-16.5807914734,28.3678131104],"type":"Point"}
}