{
  "type": "Feature",
  "properties": {
    "iso:country":"ES",
    "sg:address":"Cmno Lateral, 32",
    "sg:city":"Guijuelo",
    "sg:orig_category":"Charcuter\u00cdas (al Por Mayor)",
    "sg:phone":"+34 923 58 10 12",
    "sg:postcode":"37770",
    "sg:province":"Salamanca",
    "wof:name":"Eduardo Hernandez S. A.",
    "wof:placetype":"venue"
},
  "geometry": {"coordinates":[-5.6728258133,40.5576896667],"type":"Point"}
}