{
  "type": "Feature",
  "properties": {
    "addr:full":"Calle de Andalucia, 11 Palencia Palencia 34004",
    "addr:housenumber":"11",
    "addr:postcode":"34004",
    "addr:street":"Calle De Andalucia",
    "iso:country":"ES",
    "sg:address":"Calle de Andalucia, 11",
    "sg:city":"Palencia",
    "sg:orig_category":"Suministros Y Materiales Industriales",
    "sg:phone":"+34 979 71 09 98",
    "sg:postcode":"34004",
    "sg:province":"Palencia",
    "sg:website":"www.procoinsuministros.com",
    "wof:name":"Procoin Suministros Profesionales S.l.l.",
    "wof:placetype":"venue"
},
  "geometry": {"coordinates":[-4.5160374641,42.0070304871],"type":"Point"}
}