{
  "type": "Feature",
  "properties": {
    "addr:full":"Avda Guadalix (del), Km. 0031,0 Santo Domingo Madrid 28120",
    "addr:postcode":"28120",
    "addr:street":"Avda Guadalix Del Km. 0031,0",
    "iso:country":"ES",
    "sg:address":"Avda Guadalix (del), Km. 0031,0",
    "sg:city":"Santo Domingo",
    "sg:orig_category":"Explotaci\u00d3n De Canteras",
    "sg:phone":"+34 916 22 15 05",
    "sg:postcode":"28120",
    "sg:province":"Madrid",
    "wof:name":"Tarmac Iberia S.a.u.",
    "wof:placetype":"venue"
},
  "geometry": {"coordinates":[-3.7057700157,40.42029953],"type":"Point"}
}