{
  "type": "Feature",
  "properties": {
    "addr:full":"Avda Alfonso Pe\u00d1a, 17 Zamora Zamora 49010",
    "addr:housenumber":"17",
    "addr:postcode":"49010",
    "addr:street":"Avda Alfonso Pen\u0303A",
    "iso:country":"ES",
    "sg:address":"Avda Alfonso Pe\u00d1a, 17",
    "sg:city":"Zamora",
    "sg:orig_category":"Tiendas De Grano, Frutas Y Legumbres Secas (al Por Menor)",
    "sg:phone":"+34 980 51 31 67",
    "sg:postcode":"49010",
    "sg:province":"Zamora",
    "wof:name":"Canas Andres Jose Manuel",
    "wof:placetype":"venue"
},
  "geometry": {"coordinates":[-5.7393770218,41.5145225525],"type":"Point"}
}