{
  "type": "Feature",
  "properties": {
    "iso:country":"ES",
    "sg:address":"Calle de Granada, 29",
    "sg:city":"Barrio De La Vega",
    "sg:orig_category":"Cer\u00c1mica Art\u00cdstica Y Decorativa",
    "sg:phone":"+34 958 50 01 25",
    "sg:postcode":"18193",
    "sg:province":"Granada",
    "wof:name":"Hermanos Casares S.l.",
    "wof:placetype":"venue"
},
  "geometry": {"coordinates":[-3.5594284534,37.1367149353],"type":"Point"}
}