{
  "type": "Feature",
  "properties": {
    "iso:country":"ES",
    "sg:address":"Ctra Sur, Km. 0044,0",
    "sg:city":"C. Romeral-juan Grande",
    "sg:orig_category":"Hormigonados",
    "sg:phone":"+34 928 72 82 01",
    "sg:postcode":"35107",
    "sg:province":"Las Palmas",
    "wof:name":"Hormigones Maspalomas S.l.",
    "wof:placetype":"venue"
},
  "geometry": {"coordinates":[-15.4633636475,27.7981491089],"type":"Point"}
}