{
  "type": "Feature",
  "properties": {
    "addr:full":"Carrer de Sant Maria, 99 Viladecans Barcelona 08840",
    "addr:housenumber":"99",
    "addr:postcode":"08840",
    "addr:street":"Carrer De Sant Maria",
    "iso:country":"ES",
    "sg:address":"Carrer de Sant Maria, 99",
    "sg:city":"Viladecans",
    "sg:orig_category":"Carnes De Carnicer\u00cda (al Por Mayor)",
    "sg:phone":"+34 936 37 75 24",
    "sg:postcode":"08840",
    "sg:province":"Barcelona",
    "wof:name":"Gamez Carmona Magdalena",
    "wof:placetype":"venue"
},
  "geometry": {"coordinates":[2.014756918,41.3216285706],"type":"Point"}
}