{
  "type": "Feature",
  "properties": {
    "addr:full":"Calle de Luis Correa Medina, 9 Palmas De Gran Canaria Las Palmas 35013",
    "addr:housenumber":"9",
    "addr:postcode":"35013",
    "addr:street":"Calle De Luis Correa Medina",
    "iso:country":"ES",
    "sg:address":"Calle de Luis Correa Medina, 9",
    "sg:city":"Palmas De Gran Canaria",
    "sg:orig_category":"Supermercados Y Hipermercados",
    "sg:phone":"+34 928 42 01 00",
    "sg:postcode":"35013",
    "sg:province":"Las Palmas",
    "sg:website":"www.ahold.es",
    "wof:name":"Dinosol Supermercados S.l.",
    "wof:placetype":"venue"
},
  "geometry": {"coordinates":[-15.4340047836,28.1033649445],"type":"Point"}
}