{
  "type": "Feature",
  "properties": {
    "addr:full":"Calle de Mejico, S/n Guadalajara Guadalajara 19004",
    "addr:housenumber":"s / n",
    "addr:postcode":"19004",
    "addr:street":"Calle De Mejico",
    "iso:country":"ES",
    "sg:address":"Calle de Mejico, S/n",
    "sg:city":"Guadalajara",
    "sg:orig_category":"Chapister\u00cda",
    "sg:phone":"+34 949 20 14 67",
    "sg:postcode":"19004",
    "sg:province":"Guadalajara",
    "wof:name":"Mu\u00f1oz Cifuentes Gonzalo",
    "wof:placetype":"venue"
},
  "geometry": {"coordinates":[-3.1880040169,40.6286964417],"type":"Point"}
}