{
  "type": "Feature",
  "properties": {
    "addr:full":"Rua Santo Domingo, 50 Ourense Ourense 32003",
    "addr:housenumber":"50",
    "addr:postcode":"32003",
    "addr:street":"Rua Santo Domingo",
    "iso:country":"ES",
    "sg:address":"Rua Santo Domingo, 50",
    "sg:city":"Ourense",
    "sg:orig_category":"Caf\u00c9s, Bares, Cervecer\u00cdas",
    "sg:phone":"+34 988 22 11 29",
    "sg:postcode":"32003",
    "sg:province":"Ourense",
    "wof:name":"Galtelcom",
    "wof:placetype":"venue"
},
  "geometry": {"coordinates":[-7.8628568649,42.3394584656],"type":"Point"}
}