{
  "type": "Feature",
  "properties": {
    "addr:full":"Calle de Gracurris, 9 Alfaro La Rioja 26540",
    "addr:housenumber":"9",
    "addr:postcode":"26540",
    "addr:street":"Calle De Gracurris;Rioja",
    "iso:country":"ES",
    "sg:address":"Calle de Gracurris, 9",
    "sg:city":"Alfaro",
    "sg:orig_category":"Librer\u00cdas",
    "sg:phone":"+34 941 18 23 91",
    "sg:postcode":"26540",
    "sg:province":"La Rioja",
    "wof:name":"Martinez Ausejo Jesus",
    "wof:placetype":"venue"
},
  "geometry": {"coordinates":[-1.7588419914,42.1783752441],"type":"Point"}
}