{
  "type": "Feature",
  "properties": {
    "iso:country":"ES",
    "sg:address":"Calle de Bernardina Garcia, 9",
    "sg:city":"Madrid",
    "sg:orig_category":"Negocio De Materiales De Construcci\u00d3n",
    "sg:phone":"+34 914 64 76 77",
    "sg:postcode":"28047",
    "sg:province":"Madrid",
    "wof:name":"Garcia Martinez Emilio",
    "wof:placetype":"venue"
},
  "geometry": {"coordinates":[-3.7472913265,40.4034614563],"type":"Point"}
}