{
  "type": "Feature",
  "properties": {
    "iso:country":"ES",
    "sg:address":"Rua Ramon Pi\u00d1eiro, 11",
    "sg:city":"Ourense",
    "sg:orig_category":"Molduras, Junquillos, Listones Y Molduras Perforadas",
    "sg:phone":"+34 988 37 13 26",
    "sg:postcode":"32001",
    "sg:province":"Ourense",
    "wof:name":"Galtelcom",
    "wof:placetype":"venue"
},
  "geometry": {"coordinates":[-7.8713769913,42.3521385193],"type":"Point"}
}