{
  "type": "Feature",
  "properties": {
    "addr:full":"Plaz Honduras, 9 Valencia Valencia 46022",
    "addr:housenumber":"9",
    "addr:postcode":"46022",
    "addr:street":"Plaz Honduras",
    "iso:country":"ES",
    "sg:address":"Plaz Honduras, 9",
    "sg:city":"Valencia",
    "sg:orig_category":"Instalaci\u00d3n, Reparaci\u00d3n De Calefacci\u00d3n Por Gas",
    "sg:phone":"+34 963 55 92 07",
    "sg:postcode":"46022",
    "sg:province":"Valencia",
    "wof:name":"Union Comercial De Gas Y Calefaccion De Valencia S.l.",
    "wof:placetype":"venue"
},
  "geometry": {"coordinates":[-0.3425270021,39.473865509],"type":"Point"}
}