{
  "type": "Feature",
  "properties": {
    "addr:full":"Carrer de Sant Joan B. De La Salle (de), 10 Tortosa Tarragona 43500",
    "addr:postcode":"43500",
    "addr:street":"Carrer De Sant;B.",
    "iso:country":"ES",
    "sg:address":"Carrer de Sant Joan B. De La Salle (de), 10",
    "sg:city":"Tortosa",
    "sg:orig_category":"Arreglo, Reparaci\u00d3n, Piezas Sueltas De Televisi\u00d3n, V\u00cddeo, Hi",
    "sg:phone":"+34 977 44 24 16",
    "sg:postcode":"43500",
    "sg:province":"Tarragona",
    "wof:name":"Pons Castells Juan",
    "wof:placetype":"venue"
},
  "geometry": {"coordinates":[0.5233309865,40.8091125488],"type":"Point"}
}