{
  "type": "Feature",
  "properties": {
    "addr:full":"Calle de Trueba, 7 Donostia-san Sebastian Guip\u00f9zcoa 20001",
    "addr:housenumber":"7",
    "addr:postcode":"20001",
    "addr:street":"Calle De Trueba",
    "iso:country":"ES",
    "sg:address":"Calle de Trueba, 7",
    "sg:city":"Donostia-san Sebastian",
    "sg:orig_category":"Negocio De Materiales De Construcci\u00d3n",
    "sg:phone":"+34 943 29 32 00",
    "sg:postcode":"20001",
    "sg:province":"Guip\u00f9zcoa",
    "wof:name":"Miguel Fuentes Ceramica S.l.",
    "wof:placetype":"venue"
},
  "geometry": {"coordinates":[-1.9750299454,43.3227500916],"type":"Point"}
}