{
  "type": "Feature",
  "properties": {
    "iso:country":"ES",
    "sg:address":"Poli Industrial La Gasolinera, S/n",
    "sg:city":"Salobre\u00f1a",
    "sg:orig_category":"Empresas De Carpinter\u00cda Met\u00c1lica",
    "sg:phone":"+34 958 61 24 54",
    "sg:postcode":"18680",
    "sg:province":"Granada",
    "wof:name":"Bosch Padilla Sl",
    "wof:placetype":"venue"
},
  "geometry": {"coordinates":[-3.5866270065,36.7461280823],"type":"Point"}
}