{
  "type": "Feature",
  "properties": {
    "addr:full":"Avda Constitucion, 11 Nules Castell\u00f3n 12520",
    "addr:housenumber":"11",
    "addr:postcode":"12520",
    "addr:street":"Avda Constitucion",
    "iso:country":"ES",
    "sg:address":"Avda Constitucion, 11",
    "sg:city":"Nules",
    "sg:orig_category":"Estancos",
    "sg:phone":"+34 964 67 27 29",
    "sg:postcode":"12520",
    "sg:province":"Castell\u00f3n",
    "wof:name":"Moreno Carratala Juana Elena",
    "wof:placetype":"venue"
},
  "geometry": {"coordinates":[-0.1567820013,39.8513793945],"type":"Point"}
}