{
  "type": "Feature",
  "properties": {
    "iso:country":"ES",
    "sg:address":"Cra Cirera (de), 65",
    "sg:city":"Mataro",
    "sg:orig_category":"Flores Y Plantas Naturales (al Por Mayor)",
    "sg:phone":"+34 937 57 93 21",
    "sg:postcode":"08304",
    "sg:province":"Barcelona",
    "wof:name":"Pardo Gonzalez Jose Antonio",
    "wof:placetype":"venue"
},
  "geometry": {"coordinates":[2.4344649315,41.550239563],"type":"Point"}
}