{
  "type": "Feature",
  "properties": {
    "addr:full":"Calle de Francisco Suarez, 20 Motril Granada 18600",
    "addr:housenumber":"20",
    "addr:postcode":"18600",
    "addr:street":"Calle De Francisco Suarez",
    "iso:country":"ES",
    "sg:address":"Calle de Francisco Suarez, 20",
    "sg:city":"Motril",
    "sg:orig_category":"Obras Y Organismos Sociales",
    "sg:phone":"+34 958 82 02 47",
    "sg:postcode":"18600",
    "sg:province":"Granada",
    "wof:name":"Asociacion Mensajeros De La Paz De Andalucia",
    "wof:placetype":"venue"
},
  "geometry": {"coordinates":[-3.5196061134,36.7510871887],"type":"Point"}
}