{
  "type": "Feature",
  "properties": {
    "addr:full":"Avda Virgen De Fatima (de), 13 Cordoba C\u00f3rdoba 14014",
    "addr:postcode":"14014",
    "addr:street":"Avda Virgen;Co\u0301Rdoba",
    "iso:country":"ES",
    "sg:address":"Avda Virgen De Fatima (de), 13",
    "sg:city":"Cordoba",
    "sg:orig_category":"Carnicer\u00cdas, Carnicer\u00cdas",
    "sg:phone":"+34 957 43 85 03",
    "sg:postcode":"14014",
    "sg:province":"C\u00f3rdoba",
    "wof:name":"Osuna Ortiz Francisco",
    "wof:placetype":"venue"
},
  "geometry": {"coordinates":[-4.758605957,37.898475647],"type":"Point"}
}