{
  "type": "Feature",
  "properties": {
    "iso:country":"ES",
    "sg:address":"Calle de Palma Del Rio, 24",
    "sg:city":"Sevilla",
    "sg:orig_category":"Asociaciones, Organismos Culturales Y Socioeducativos",
    "sg:phone":"+34 954 35 93 55",
    "sg:postcode":"41008",
    "sg:province":"Sevilla",
    "wof:name":"Pe\u00f1a Cultural Club Deportivo Pio Xii",
    "wof:placetype":"venue"
},
  "geometry": {"coordinates":[-5.9787077904,37.4034881592],"type":"Point"}
}