{
  "type": "Feature",
  "properties": {
    "addr:full":"Carr Alcalde Costa, 2 Lleida Lleida 25002",
    "addr:housenumber":"2",
    "addr:postcode":"25002",
    "addr:street":"Carr Alcalde Costa",
    "iso:country":"ES",
    "sg:address":"Carr Alcalde Costa, 2",
    "sg:city":"Lleida",
    "sg:orig_category":"Publicidad (soportes Y Gesti\u00d3n)",
    "sg:phone":"+34 973 28 29 06",
    "sg:postcode":"25002",
    "sg:province":"Lleida",
    "wof:name":"Gorras Tear S.l.",
    "wof:placetype":"venue"
},
  "geometry": {"coordinates":[0.6206765771,41.6113128662],"type":"Point"}
}