{
  "type": "Feature",
  "properties": {
    "addr:full":"Via Augusta, 318 Barcelona Barcelona 08017",
    "addr:housenumber":"318",
    "addr:postcode":"08017",
    "addr:street":"Via Augusta",
    "iso:country":"ES",
    "sg:address":"Via Augusta, 318",
    "sg:city":"Barcelona",
    "sg:orig_category":"Electricidad: Instaladores",
    "sg:phone":"+34 932 06 61 20",
    "sg:postcode":"08017",
    "sg:province":"Barcelona",
    "sg:website":"www.gestinel.com",
    "wof:name":"Gestinel S.l.",
    "wof:placetype":"venue"
},
  "geometry": {"coordinates":[2.1260139942,41.3983345032],"type":"Point"}
}