{
  "type": "Feature",
  "properties": {
    "addr:full":"Ctra. Tarragona-ss., Km. 0206,0 Huesca Huesca 22006",
    "addr:postcode":"22006",
    "addr:street":"Ctra. Tarragona-Ss. Km. 0206,0",
    "iso:country":"ES",
    "sg:address":"Ctra. Tarragona-ss., Km. 0206,0",
    "sg:city":"Huesca",
    "sg:orig_category":"Pintura, Barniz, Productos Asimilables (fabricaci\u00d3n, Al Por Mayor)",
    "sg:phone":"+34 974 24 39 09",
    "sg:postcode":"22006",
    "sg:province":"Huesca",
    "wof:name":"Pinturas Sorribas S.l.",
    "wof:placetype":"venue"
},
  "geometry": {"coordinates":[-0.4083139896,42.1365661621],"type":"Point"}
}