{
  "type": "Feature",
  "properties": {
    "iso:country":"ES",
    "sg:address":"Calle de Ribera, 1",
    "sg:city":"Bilbao",
    "sg:orig_category":"Cl\u00cdnicas Dentales",
    "sg:phone":"+34 944 16 80 25",
    "sg:postcode":"48005",
    "sg:province":"Vizcaya",
    "wof:name":"Abad Aldecoa Pedro",
    "wof:placetype":"venue"
},
  "geometry": {"coordinates":[-2.92464,43.259232],"type":"Point"}
}