{
  "type": "Feature",
  "properties": {
    "addr:full":"Calle de Siervo De Dios, 29 Icod De Los Vinos Santa Cruz De Tenerife 38430",
    "addr:housenumber":"29",
    "addr:postcode":"38430",
    "addr:street":"Calle De Siervo;Dios",
    "iso:country":"ES",
    "sg:address":"Calle de Siervo De Dios, 29",
    "sg:city":"Icod De Los Vinos",
    "sg:orig_category":"Molduras, Junquillos, Listones Y Molduras Perforadas",
    "sg:phone":"+34 922 81 17 70",
    "sg:postcode":"38430",
    "sg:province":"Santa Cruz De Tenerife",
    "wof:name":"Perez Luis Manuel",
    "wof:placetype":"venue"
},
  "geometry": {"coordinates":[-16.7170524597,28.3674163818],"type":"Point"}
}