{
  "type": "Feature",
  "properties": {
    "addr:full":"Avda Gipuzkoa, S/n Ermua Vizcaya 48260",
    "addr:housenumber":"s",
    "addr:postcode":"48260",
    "addr:street":"Avda Gipuzkoa;/ N",
    "iso:country":"ES",
    "sg:address":"Avda Gipuzkoa, S/n",
    "sg:city":"Ermua",
    "sg:orig_category":"Ense\u00d1anza, Formaci\u00d3n Profesional: Aprendizaje",
    "sg:phone":"+34 943 17 62 48",
    "sg:postcode":"48260",
    "sg:province":"Vizcaya",
    "wof:name":"Cruz Roja Espa\u00f1ola",
    "wof:placetype":"venue"
},
  "geometry": {"coordinates":[-2.4989349842,43.1816139221],"type":"Point"}
}