{
  "type": "Feature",
  "properties": {
    "iso:country":"ES",
    "sg:address":"Rua Norte, 64",
    "sg:city":"Palmeira",
    "sg:orig_category":"Empresas De Pintura Y Revestimientos",
    "sg:phone":"+34 981 83 86 22",
    "sg:postcode":"15950",
    "sg:province":"La Coru\u00f1a",
    "wof:name":"J.c. Pinturas Y Contratas S.l.",
    "wof:placetype":"venue"
},
  "geometry": {"coordinates":[-8.9576444626,42.5836868286],"type":"Point"}
}