{
  "type": "Feature",
  "properties": {
    "addr:full":"Calle de General San Martin, 3 Valencia Valencia 46004",
    "addr:housenumber":"3",
    "addr:postcode":"46004",
    "addr:street":"Calle De General San Martin",
    "iso:country":"ES",
    "sg:address":"Calle de General San Martin, 3",
    "sg:city":"Valencia",
    "sg:orig_category":"Abogados",
    "sg:phone":"+34 963 51 03 77",
    "sg:postcode":"46004",
    "sg:province":"Valencia",
    "wof:name":"Jordan Iba\u00f1ez Eva Maria",
    "wof:placetype":"venue"
},
  "geometry": {"coordinates":[-0.3759599924,39.4655570984],"type":"Point"}
}