{
  "type": "Feature",
  "properties": {
    "iso:country":"ES",
    "sg:address":"Carrer de Riu Llobregat, 92",
    "sg:city":"Prat Llobregat",
    "sg:orig_category":"Estancos",
    "sg:phone":"+34 934 78 67 37",
    "sg:postcode":"08820",
    "sg:province":"Barcelona",
    "wof:name":"Soro Urbea Emiliano",
    "wof:placetype":"venue"
},
  "geometry": {"coordinates":[2.0871899128,41.3167495728],"type":"Point"}
}