{
  "type": "Feature",
  "properties": {
    "iso:country":"ES",
    "sg:address":"Calle de Nicolas Sanchez, 24",
    "sg:city":"Madrid",
    "sg:orig_category":"Loter\u00cda Y T\u00d3mbola",
    "sg:phone":"+34 914 75 74 86",
    "sg:postcode":"28026",
    "sg:province":"Madrid",
    "wof:name":"De La Fuente Arevalo Maria Rosario",
    "wof:placetype":"venue"
},
  "geometry": {"coordinates":[-3.7064499855,40.385471344],"type":"Point"}
}