{
  "type": "Feature",
  "properties": {
    "addr:full":"Carrer de Bernat Metge, 47 Sabadell Barcelona 08205",
    "addr:housenumber":"47",
    "addr:postcode":"08205",
    "addr:street":"Carrer De Bernat Metge",
    "iso:country":"ES",
    "sg:address":"Carrer de Bernat Metge, 47",
    "sg:city":"Sabadell",
    "sg:orig_category":"Fabricaci\u00d3n De Art\u00cdculos Y Equipos Deportivos Y De Ocio",
    "sg:phone":"+34 937 10 06 95",
    "sg:postcode":"08205",
    "sg:province":"Barcelona",
    "sg:website":"www.mein.es",
    "wof:name":"Mecanizacion Industrial Sabadell S.a.",
    "wof:placetype":"venue"
},
  "geometry": {"coordinates":[2.1008899212,41.5313110352],"type":"Point"}
}