{
  "type": "Feature",
  "properties": {
    "addr:full":"Calle de Manolo Pilares, 1 Pola De Lena Asturias 33630",
    "addr:housenumber":"1",
    "addr:postcode":"33630",
    "addr:street":"Calle De;Pilares",
    "iso:country":"ES",
    "sg:address":"Calle de Manolo Pilares, 1",
    "sg:city":"Pola De Lena",
    "sg:orig_category":"Prot\u00c9sicos Dentales",
    "sg:phone":"+34 985 49 30 34",
    "sg:postcode":"33630",
    "sg:province":"Asturias",
    "wof:name":"Martinez Cortina Jose Luis",
    "wof:placetype":"venue"
},
  "geometry": {"coordinates":[-5.828209877,43.1568603516],"type":"Point"}
}