{
  "type": "Feature",
  "properties": {
    "addr:full":"Calle de Sotera De La Mier, 1 Portugalete Vizcaya 48920",
    "addr:housenumber":"1",
    "addr:postcode":"48920",
    "addr:street":"Calle De Sotera De La Mier",
    "iso:country":"ES",
    "sg:address":"Calle de Sotera De La Mier, 1",
    "sg:city":"Portugalete",
    "sg:orig_category":"Iglesia Cat\u00d3lica",
    "sg:phone":"+34 944 96 53 63",
    "sg:postcode":"48920",
    "sg:province":"Vizcaya",
    "wof:name":"Parroquia Santa Maria De Portugalete",
    "wof:placetype":"venue"
},
  "geometry": {"coordinates":[-3.0159790516,43.3191337585],"type":"Point"}
}