{
  "type": "Feature",
  "properties": {
    "addr:full":"Calle de Oasis, 3 Molina Segura Murcia 30500",
    "addr:housenumber":"3",
    "addr:postcode":"30500",
    "addr:street":"Calle De Oasis",
    "iso:country":"ES",
    "sg:address":"Calle de Oasis, 3",
    "sg:city":"Molina Segura",
    "sg:orig_category":"Suministros Para Hoteles",
    "sg:phone":"+34 968 64 41 61",
    "sg:postcode":"30500",
    "sg:province":"Murcia",
    "wof:name":"Moreno Orozco E Hijos S.l.",
    "wof:placetype":"venue"
},
  "geometry": {"coordinates":[-1.2164889574,38.0578384399],"type":"Point"}
}