{
  "type": "Feature",
  "properties": {
    "iso:country":"ES",
    "sg:address":"Ptge. J. Carbonell, 5",
    "sg:city":"Sitges",
    "sg:orig_category":"Lencer\u00cda Femenina, Corseter\u00cda, Trajes De Ba\u00d1o (al Por Menor)",
    "sg:phone":"+34 938 94 45 06",
    "sg:postcode":"08870",
    "sg:province":"Barcelona",
    "wof:name":"Molina Ros Montserrat",
    "wof:placetype":"venue"
},
  "geometry": {"coordinates":[1.8054499626,41.2342414856],"type":"Point"}
}