{
  "type": "Feature",
  "properties": {
    "iso:country":"ES",
    "sg:address":"Calle de Trigales, 22",
    "sg:city":"Almeria",
    "sg:orig_category":"Tapicer\u00cdas",
    "sg:phone":"+34 950 27 32 94",
    "sg:postcode":"04008",
    "sg:province":"Almer\u00eda",
    "wof:name":"Guillen Sorroche Jose Antonio",
    "wof:placetype":"venue"
},
  "geometry": {"coordinates":[-2.4600288868,36.8495101929],"type":"Point"}
}