{
  "type": "Feature",
  "properties": {
    "iso:country":"ES",
    "sg:address":"Calle de Aldeanueva De La Vera, 19",
    "sg:city":"Madrid",
    "sg:orig_category":"Farmacias",
    "sg:phone":"+34 917 05 50 50",
    "sg:postcode":"28044",
    "sg:province":"Madrid",
    "wof:name":"Criado Alcazar Angeles",
    "wof:placetype":"venue"
},
  "geometry": {"coordinates":[-3.7762413025,40.3775444031],"type":"Point"}
}