{
  "type": "Feature",
  "properties": {
    "iso:country":"ES",
    "sg:address":"Ctra Aldaia-xirivella, 52",
    "sg:city":"Aldaia",
    "sg:orig_category":"Servicio De Salud",
    "sg:phone":"+34 961 50 78 16",
    "sg:postcode":"46960",
    "sg:province":"Valencia",
    "wof:name":"Aldayense De Pavimentos S.l.",
    "wof:placetype":"venue"
},
  "geometry": {"coordinates":[-0.4453352094,39.4629745483],"type":"Point"}
}