{
  "type": "Feature",
  "properties": {
    "iso:country":"ES",
    "sg:address":"Plaz San Juan De La Cruz, 5",
    "sg:city":"Madrid",
    "sg:orig_category":"Cine (producci\u00d3n, Realizaci\u00d3n)",
    "sg:phone":"+34 915 35 81 65",
    "sg:postcode":"28003",
    "sg:province":"Madrid",
    "wof:name":"Trafico De Ideas S.l.",
    "wof:placetype":"venue"
},
  "geometry": {"coordinates":[-3.6946411133,40.4414710999],"type":"Point"}
}