{
  "type": "Feature",
  "properties": {
    "addr:full":"Areas, 53 Paderne-coristanco La Coru\u00f1a 15314",
    "addr:housenumber":"53",
    "addr:postcode":"15314",
    "addr:street":"Areas;La Corun\u0303A",
    "iso:country":"ES",
    "sg:address":"Areas, 53",
    "sg:city":"Paderne-coristanco",
    "sg:orig_category":"Pirotecnia (espect\u00c1culos)",
    "sg:phone":"+34 981 79 74 81",
    "sg:postcode":"15314",
    "sg:province":"La Coru\u00f1a",
    "wof:name":"Pirotecnia Areas S.l.",
    "wof:placetype":"venue"
},
  "geometry": {"coordinates":[-8.1407690048,43.295501709],"type":"Point"}
}