{
  "type": "Feature",
  "properties": {
    "addr:full":"Calle de Sales Y Ferre, 16 Sevilla Sevilla 41004",
    "addr:housenumber":"16",
    "addr:postcode":"41004",
    "addr:street":"Calle De Sales Y Ferre",
    "iso:country":"ES",
    "sg:address":"Calle de Sales Y Ferre, 16",
    "sg:city":"Sevilla",
    "sg:orig_category":"M\u00c9dicos: Cirug\u00cda Vascular",
    "sg:phone":"+34 954 22 35 36",
    "sg:postcode":"41004",
    "sg:province":"Sevilla",
    "wof:name":"Gutierrez Del Manzano Jose Antonio",
    "wof:placetype":"venue"
},
  "geometry": {"coordinates":[-5.99041605,37.3909645081],"type":"Point"}
}