{
  "type": "Feature",
  "properties": {
    "addr:full":"Avda Tomillar (del), 64 Pe\u00d1ascales Madrid 28250",
    "addr:housenumber":"64",
    "addr:postcode":"28250",
    "addr:street":"Avda Tomillar Del",
    "iso:country":"ES",
    "sg:address":"Avda Tomillar (del), 64",
    "sg:city":"Pe\u00d1ascales",
    "sg:orig_category":"Centros Empresariales",
    "sg:phone":"+34 918 59 95 06",
    "sg:postcode":"28250",
    "sg:province":"Madrid",
    "wof:name":"Suami S.a.",
    "wof:placetype":"venue"
},
  "geometry": {"coordinates":[-3.8935658932,40.5759315491],"type":"Point"}
}