{
  "type": "Feature",
  "properties": {
    "iso:country":"ES",
    "sg:address":"Ctra Villamartin, 13",
    "sg:city":"Gironda",
    "sg:orig_category":"Maquinaria Para Industrias Diversas",
    "sg:phone":"+34 955 84 20 83",
    "sg:postcode":"41600",
    "sg:province":"Sevilla",
    "wof:name":"Tepolac S.l.",
    "wof:placetype":"venue"
},
  "geometry": {"coordinates":[-5.5452737808,37.2582397461],"type":"Point"}
}