{
  "type": "Feature",
  "properties": {
    "addr:full":"Calle de Serapio Mugica, 18 Irun Guip\u00f9zcoa 20302",
    "addr:housenumber":"18",
    "addr:postcode":"20302",
    "addr:street":"Calle De Serapio Mugica;Guipu\u0300Zcoa",
    "iso:country":"ES",
    "sg:address":"Calle de Serapio Mugica, 18",
    "sg:city":"Irun",
    "sg:orig_category":"Pescader\u00cdas (al Por Menor)",
    "sg:phone":"+34 943 61 27 07",
    "sg:postcode":"20302",
    "sg:province":"Guip\u00f9zcoa",
    "wof:name":"Yarzabal Arizmendi Felix",
    "wof:placetype":"venue"
},
  "geometry": {"coordinates":[-1.7963490486,43.338142395],"type":"Point"}
}