{
  "type": "Feature",
  "properties": {
    "addr:full":"Calle de Ciudad Real, 1 Azuqueca Henares Guadalajara 19200",
    "addr:housenumber":"1",
    "addr:postcode":"19200",
    "addr:street":"Calle De Ciudad Real",
    "iso:country":"ES",
    "sg:address":"Calle de Ciudad Real, 1",
    "sg:city":"Azuqueca Henares",
    "sg:orig_category":"Ense\u00d1anza, Formaci\u00d3n Profesional: Aprendizaje",
    "sg:phone":"+34 949 26 63 58",
    "sg:postcode":"19200",
    "sg:province":"Guadalajara",
    "wof:name":"Ayuntamiento De Azuqueca De Henares",
    "wof:placetype":"venue"
},
  "geometry": {"coordinates":[-3.262039423,40.5655479431],"type":"Point"}
}