{
  "type": "Feature",
  "properties": {
    "iso:country":"ES",
    "sg:address":"Calle de Parroco Cobos, 39",
    "sg:city":"Benimamet-beniferri",
    "sg:orig_category":"Empresas De Carpinter\u00cda Met\u00c1lica",
    "sg:phone":"+34 963 48 69 04",
    "sg:postcode":"46035",
    "sg:province":"Valencia",
    "wof:name":"Ochandio Sotos Enrique",
    "wof:placetype":"venue"
},
  "geometry": {"coordinates":[-0.4216659963,39.4974212646],"type":"Point"}
}