{
  "type": "Feature",
  "properties": {
    "addr:full":"Euskal Herria Plaza, 5 Elizalde Guip\u00f9zcoa 20180",
    "addr:housenumber":"5",
    "addr:postcode":"20180",
    "addr:street":"Euskal Herria Plaza;Guipu\u0300Zcoa",
    "iso:country":"ES",
    "sg:address":"Euskal Herria Plaza, 5",
    "sg:city":"Elizalde",
    "sg:orig_category":"Partidos Pol\u00cdticos",
    "sg:phone":"+34 943 49 30 60",
    "sg:postcode":"20180",
    "sg:province":"Guip\u00f9zcoa",
    "wof:name":"Partido Nacionalista Vasco",
    "wof:placetype":"venue"
},
  "geometry": {"coordinates":[-1.8629590273,43.2992401123],"type":"Point"}
}