{
  "type": "Feature",
  "properties": {
    "addr:full":"Calle de Izbor, 2 Padul Granada 18640",
    "addr:housenumber":"2",
    "addr:postcode":"18640",
    "addr:street":"Calle De Izbor",
    "iso:country":"ES",
    "sg:address":"Calle de Izbor, 2",
    "sg:city":"Padul",
    "sg:orig_category":"Agencias Y Agentes Comerciales, Representantes",
    "sg:phone":"+34 958 77 40 96",
    "sg:postcode":"18640",
    "sg:province":"Granada",
    "wof:name":"Josalpla S.l.u",
    "wof:placetype":"venue"
},
  "geometry": {"coordinates":[-3.624655962,37.0213127136],"type":"Point"}
}