{
  "type": "Feature",
  "properties": {
    "addr:full":"Rincones, S/n Mazarron Murcia 30870",
    "addr:housenumber":"/ n",
    "addr:postcode":"30870",
    "addr:street":"S",
    "iso:country":"ES",
    "sg:address":"Rincones, S/n",
    "sg:city":"Mazarron",
    "sg:orig_category":"Cerrajer\u00cda, Ferrallista",
    "sg:phone":"+34 968 33 31 77",
    "sg:postcode":"30870",
    "sg:province":"Murcia",
    "wof:name":"Nancimerc S.l.",
    "wof:placetype":"venue"
},
  "geometry": {"coordinates":[-1.2970119715,37.6166343689],"type":"Point"}
}