{
  "type": "Feature",
  "properties": {
    "iso:country":"ES",
    "sg:address":"Calle de Santa Eulalia, 13",
    "sg:city":"Valladolid",
    "sg:orig_category":"Rectificaci\u00d3n, Mecanizado, Fresado",
    "sg:phone":"+34 983 39 52 14",
    "sg:postcode":"47012",
    "sg:province":"Valladolid",
    "wof:name":"Metafres",
    "wof:placetype":"venue"
},
  "geometry": {"coordinates":[-4.6976599693,41.6451225281],"type":"Point"}
}