{
  "type": "Feature",
  "properties": {
    "iso:country":"ES",
    "sg:address":"Carr Agulla, De L', S/n",
    "sg:city":"Cala Ratjada",
    "sg:orig_category":"Art\u00cdculos De Regalo (al Por Menor)",
    "sg:phone":"+34 971 56 57 55",
    "sg:postcode":"07590",
    "sg:province":"Islas Baleares",
    "wof:name":"Soler Torrens E Hijos S.l",
    "wof:placetype":"venue"
},
  "geometry": {"coordinates":[3.4626729488,39.7110137939],"type":"Point"}
}