{
  "type": "Feature",
  "properties": {
    "iso:country":"ES",
    "sg:address":"Calle de Barrero, 55",
    "sg:city":"Monfarracinos",
    "sg:orig_category":"Lavado, Limpieza De Veh\u00cdculos",
    "sg:phone":"+34 980 50 21 60",
    "sg:postcode":"49121",
    "sg:province":"Zamora",
    "wof:name":"Urue\u00f1a Teson Luis",
    "wof:placetype":"venue"
},
  "geometry": {"coordinates":[-5.7066750526,41.5522994995],"type":"Point"}
}