{
  "type": "Feature",
  "properties": {
    "iso:country":"ES",
    "sg:address":"Av Fonera, De Sa, 129",
    "sg:city":"Porto Cristo",
    "sg:orig_category":"Peluquer\u00cdas, Peluquer\u00cda Mixta",
    "sg:phone":"+34 971 82 01 19",
    "sg:postcode":"07680",
    "sg:province":"Islas Baleares",
    "wof:name":"Sanchez Villena Sonia",
    "wof:placetype":"venue"
},
  "geometry": {"coordinates":[3.339523077,39.546836853],"type":"Point"}
}