{
  "type": "Feature",
  "properties": {
    "addr:full":"Crt. Viso San Juan, S/n Ugena Toledo 45217",
    "addr:housenumber":"s / n",
    "addr:postcode":"45217",
    "addr:street":"San Juan",
    "iso:country":"ES",
    "sg:address":"Crt. Viso San Juan, S/n",
    "sg:city":"Ugena",
    "sg:orig_category":"Rectificaci\u00d3n, Mecanizado, Fresado",
    "sg:phone":"+34 925 54 41 23",
    "sg:postcode":"45217",
    "sg:province":"Toledo",
    "wof:name":"Mecanizacion Y Ensamblaje Toledo S.l.",
    "wof:placetype":"venue"
},
  "geometry": {"coordinates":[-3.8805239201,40.1541404724],"type":"Point"}
}