{
  "type": "Feature",
  "properties": {
    "addr:full":"Avda Constitucion (la), S/n Osuna Sevilla 41640",
    "addr:postcode":"41640",
    "addr:street":"Avda Constitucion La S / N",
    "iso:country":"ES",
    "sg:address":"Avda Constitucion (la), S/n",
    "sg:city":"Osuna",
    "sg:orig_category":"Mutuas De Seguros",
    "sg:phone":"+34 954 81 09 00",
    "sg:postcode":"41640",
    "sg:province":"Sevilla",
    "wof:name":"Fraternidad-muprespa Mutua De Accidentes De Trabajo Y Enfermedades Profesionales",
    "wof:placetype":"venue"
},
  "geometry": {"coordinates":[-5.0900940895,37.2338943481],"type":"Point"}
}