{
  "type": "Feature",
  "properties": {
    "addr:full":"Calle de Longuera (la), S/n Longuera Santa Cruz De Tenerife 38418",
    "addr:postcode":"38418",
    "addr:street":"Calle De Longuera La S / N Longuera",
    "iso:country":"ES",
    "sg:address":"Calle de Longuera (la), S/n",
    "sg:city":"Longuera",
    "sg:orig_category":"Pintores",
    "sg:phone":"+34 922 36 41 70",
    "sg:postcode":"38418",
    "sg:province":"Santa Cruz De Tenerife",
    "wof:name":"Loloi Feizy Mohsen",
    "wof:placetype":"venue"
},
  "geometry": {"coordinates":[-16.5777740479,28.397819519],"type":"Point"}
}