{
  "type": "Feature",
  "properties": {
    "iso:country":"ES",
    "sg:address":"Praj Pinillos, S/n",
    "sg:city":"Campo Abajo",
    "sg:orig_category":"Mec\u00c1nico Del Autom\u00d3vil",
    "sg:phone":"+34 968 75 38 62",
    "sg:postcode":"30510",
    "sg:province":"Murcia",
    "wof:name":"Hernandez Roldan Jose Francisco",
    "wof:placetype":"venue"
},
  "geometry": {"coordinates":[-1.1298867464,37.9834747314],"type":"Point"}
}