{
  "type": "Feature",
  "properties": {
    "addr:full":"Avda Rubians, 82 Barbeitos Pontevedra 36619",
    "addr:housenumber":"82",
    "addr:postcode":"36619",
    "addr:street":"Avda Rubians",
    "iso:country":"ES",
    "sg:address":"Avda Rubians, 82",
    "sg:city":"Barbeitos",
    "sg:orig_category":"Mec\u00c1nico Del Autom\u00d3vil",
    "sg:phone":"+34 986 50 32 54",
    "sg:postcode":"36619",
    "sg:province":"Pontevedra",
    "wof:name":"Iglesias Pedrido Santiago",
    "wof:placetype":"venue"
},
  "geometry": {"coordinates":[-8.7645044327,42.5797958374],"type":"Point"}
}