{
  "type": "Feature",
  "properties": {
    "iso:country":"ES",
    "sg:address":"Calle de Angel (del), 38",
    "sg:city":"Linea De La Concepcion",
    "sg:orig_category":"Centros Empresariales",
    "sg:phone":"+34 956 76 84 80",
    "sg:postcode":"11300",
    "sg:province":"C\u00e1diz",
    "wof:name":"Admin Soluciones Informaticas S.l.l.",
    "wof:placetype":"venue"
},
  "geometry": {"coordinates":[-5.3496303558,36.1660766602],"type":"Point"}
}