{
  "type": "Feature",
  "properties": {
    "iso:country":"ES",
    "sg:address":"Calle de Mayor, 339",
    "sg:city":"Raal",
    "sg:orig_category":"Reposter\u00cdas",
    "sg:phone":"+34 968 81 07 00",
    "sg:postcode":"30139",
    "sg:province":"Murcia",
    "wof:name":"Jose Imbernon Martinez C.b.",
    "wof:placetype":"venue"
},
  "geometry": {"coordinates":[-1.0279519558,38.0403022766],"type":"Point"}
}