{
  "type": "Feature",
  "properties": {
    "addr:full":"Urb Pero\u00d1o, 9 Pero\u00d1o Asturias 33440",
    "addr:housenumber":"9",
    "addr:postcode":"33440",
    "addr:street":"Urb Peron\u0303O;Asturias",
    "iso:country":"ES",
    "sg:address":"Urb Pero\u00d1o, 9",
    "sg:city":"Pero\u00d1o",
    "sg:orig_category":"T\u00c9cnicos Veterinarios",
    "sg:phone":"+34 985 88 28 57",
    "sg:postcode":"33440",
    "sg:province":"Asturias",
    "wof:name":"Garcia Suarez Emilio",
    "wof:placetype":"venue"
},
  "geometry": {"coordinates":[-5.9832577705,43.2504386902],"type":"Point"}
}