{
  "type": "Feature",
  "properties": {
    "iso:country":"ES",
    "sg:address":"Carrer de Muntaner, 521",
    "sg:city":"Barcelona",
    "sg:orig_category":"Confecci\u00d3n De Trajes Para Se\u00d1oras",
    "sg:phone":"+34 932 11 30 99",
    "sg:postcode":"08022",
    "sg:province":"Barcelona",
    "wof:name":"Luna Ponce Maria Isabel",
    "wof:placetype":"venue"
},
  "geometry": {"coordinates":[2.1366240978,41.4038391113],"type":"Point"}
}