{
  "type": "Feature",
  "properties": {
    "addr:full":"Cuesta Carcel, 7 Morella Castell\u00f3n 12300",
    "addr:housenumber":"7",
    "addr:postcode":"12300",
    "addr:street":"Carcel;Castello\u0301N",
    "iso:country":"ES",
    "sg:address":"Cuesta Carcel, 7",
    "sg:city":"Morella",
    "sg:orig_category":"Promotores Constructores",
    "sg:phone":"+34 964 16 07 06",
    "sg:postcode":"12300",
    "sg:province":"Castell\u00f3n",
    "wof:name":"Construcciones Angel Meseguer S.l.",
    "wof:placetype":"venue"
},
  "geometry": {"coordinates":[-0.0987680033,40.6192436218],"type":"Point"}
}