{
  "type": "Feature",
  "properties": {
    "iso:country":"ES",
    "sg:address":"Avda. Monte Luz, 6",
    "sg:city":"Peligros",
    "sg:classifiers":[
        {
            "category":"Food & Beverages",
            "subcategory":"Candy",
            "type":"Retail Goods"
        }
    ],
    "sg:phone":"+34 958 40 17 40",
    "sg:postcode":"18210",
    "sg:province":"Granada",
    "sg:tags":[
        "confiter\u00cdas",
        "y",
        "de",
        "fabricaci\u00d3n",
        "chocolate"
    ],
    "wof:name":"Sanchez Cano S.a.",
    "wof:placetype":"venue"
},
  "geometry": {"coordinates":[-3.643556118,37.2387504578],"type":"Point"}
}