{
  "type": "Feature",
  "properties": {
    "iso:country":"ES",
    "sg:address":"Calle de Castilla-la Mancha, 17",
    "sg:city":"Caudete",
    "sg:orig_category":"Empresas De Carpinter\u00cda",
    "sg:phone":"+34 965 82 68 15",
    "sg:postcode":"02660",
    "sg:province":"Albacete",
    "wof:name":"Aluminios Caudete S.l.",
    "wof:placetype":"venue"
},
  "geometry": {"coordinates":[-1.0011901855,38.7116012573],"type":"Point"}
}