{
  "type": "Feature",
  "properties": {
    "iso:country":"ES",
    "sg:address":"Carr Illes Canaries, 12",
    "sg:city":"Grau I Platja",
    "sg:orig_category":"Administradores De Bienes Y Delegados De Comunidades De Propietarios",
    "sg:phone":"+34 962 84 09 29",
    "sg:postcode":"46730",
    "sg:province":"Valencia",
    "wof:name":"Comunidad De Propietarios Edificio Residencial Miami",
    "wof:placetype":"venue"
},
  "geometry": {"coordinates":[-0.1631519943,39.0017776489],"type":"Point"}
}