{
  "type": "Feature",
  "properties": {
    "iso:country":"ES",
    "sg:address":"Rua Laxe, S/n",
    "sg:city":"Laxe",
    "sg:orig_category":"Electricidad: Equipos Industriales, Componentes (fabricaci\u00d3n)",
    "sg:phone":"+34 981 66 54 03",
    "sg:postcode":"15174",
    "sg:province":"La Coru\u00f1a",
    "wof:name":"Mui\u00f1os Grela Ricardo",
    "wof:placetype":"venue"
},
  "geometry": {"coordinates":[-8.3826389313,43.3110656738],"type":"Point"}
}