{
  "type": "Feature",
  "properties": {
    "iso:country":"ES",
    "sg:address":"Calle de Oscar Romero, 12",
    "sg:city":"Albacete",
    "sg:orig_category":"Venta, Instalaci\u00d3n De Calefacci\u00d3n",
    "sg:phone":"+34 967 50 67 85",
    "sg:postcode":"02006",
    "sg:province":"Albacete",
    "wof:name":"Collado Del Rey Andres",
    "wof:placetype":"venue"
},
  "geometry": {"coordinates":[-1.8761730194,38.9885215759],"type":"Point"}
}