{
  "type": "Feature",
  "properties": {
    "iso:country":"ES",
    "sg:address":"Carrer de Vallespir, 6",
    "sg:city":"S. Joan Despi",
    "sg:orig_category":"Sociedades, Compa\u00d1\u00cdas Aseguradoras",
    "sg:phone":"+34 933 73 81 57",
    "sg:postcode":"08970",
    "sg:province":"Barcelona",
    "wof:name":"Fiatc Mutua De Seguros Generales",
    "wof:placetype":"venue"
},
  "geometry": {"coordinates":[2.0589089394,41.3716659546],"type":"Point"}
}