{
  "type": "Feature",
  "properties": {
    "addr:full":"Ctra Castellar, 5 Terrassa Barcelona 08222",
    "addr:housenumber":"5",
    "addr:postcode":"08222",
    "addr:street":"Ctra Castellar",
    "iso:country":"ES",
    "sg:address":"Ctra Castellar, 5",
    "sg:city":"Terrassa",
    "sg:orig_category":"Cajas De Ahorro",
    "sg:phone":"+34 937 36 11 80",
    "sg:postcode":"08222",
    "sg:province":"Barcelona",
    "wof:name":"Caixa De Girona",
    "wof:placetype":"venue"
},
  "geometry": {"coordinates":[2.0225269794,41.5646133423],"type":"Point"}
}