{
  "type": "Feature",
  "properties": {
    "iso:country":"ES",
    "sg:address":"Carrer de Montsia, 95",
    "sg:city":"Poligono Industrial Can Carner",
    "sg:orig_category":"Maquinaria Para Industrias Diversas",
    "sg:phone":"+34 937 14 32 67",
    "sg:postcode":"08211",
    "sg:province":"Barcelona",
    "wof:name":"Alquycons Acu\u00f1a S.l.",
    "wof:placetype":"venue"
},
  "geometry": {"coordinates":[2.0775322914,41.5997695923],"type":"Point"}
}