{
  "type": "Feature",
  "properties": {
    "addr:full":"Calle de Betis, 41 Sevilla Sevilla 41010",
    "addr:housenumber":"41",
    "addr:postcode":"41010",
    "addr:street":"Calle De Betis",
    "iso:country":"ES",
    "sg:address":"Calle de Betis, 41",
    "sg:city":"Sevilla",
    "sg:orig_category":"Inmobiliaria (agencias)",
    "sg:phone":"+34 954 27 34 04",
    "sg:postcode":"41010",
    "sg:province":"Sevilla",
    "wof:name":"Artiguez Y Mejias S.l.",
    "wof:placetype":"venue"
},
  "geometry": {"coordinates":[-5.9995722771,37.3831214905],"type":"Point"}
}