{
  "type": "Feature",
  "properties": {
    "addr:full":"Calle de Roldan Y Marin, 7 Jaen Ja\u00e9n 23001",
    "addr:housenumber":"7;jae\u0301n",
    "addr:postcode":"23001",
    "addr:street":"Calle De Roldan Y Marin",
    "iso:country":"ES",
    "sg:address":"Calle de Roldan Y Marin, 7",
    "sg:city":"Jaen",
    "sg:orig_category":"Ropa Para Caballeros (al Por Menor)",
    "sg:phone":"+34 953 24 00 04",
    "sg:postcode":"23001",
    "sg:province":"Ja\u00e9n",
    "sg:website":"www.pullbear.com",
    "wof:name":"Pull & Bear Espa\u00f1a S.a.",
    "wof:placetype":"venue"
},
  "geometry": {"coordinates":[-3.7879989147,37.7687492371],"type":"Point"}
}