{
  "type": "Feature",
  "properties": {
    "addr:full":"Ptda Condomina, 480 Alacant Alicante 03016",
    "addr:housenumber":"480",
    "addr:postcode":"03016",
    "addr:street":"Ptda Condomina",
    "iso:country":"ES",
    "sg:address":"Ptda Condomina, 480",
    "sg:city":"Alacant",
    "sg:orig_category":"Arquitectos",
    "sg:phone":"+34 965 26 53 71",
    "sg:postcode":"03016",
    "sg:province":"Alicante",
    "wof:name":"Andres Silvestre Fernando",
    "wof:placetype":"venue"
},
  "geometry": {"coordinates":[-0.4643906057,38.3736000061],"type":"Point"}
}