{
  "type": "Feature",
  "properties": {
    "addr:full":"Avda Mancha (la), 11 Corral Almaguer Toledo 45880",
    "addr:housenumber":"11",
    "addr:postcode":"45880",
    "addr:street":"Avda Mancha La",
    "iso:country":"ES",
    "sg:address":"Avda Mancha (la), 11",
    "sg:city":"Corral Almaguer",
    "sg:orig_category":"M\u00c1rmoles, Granitos Y Piedras Naturales",
    "sg:phone":"+34 925 19 09 66",
    "sg:postcode":"45880",
    "sg:province":"Toledo",
    "wof:name":"Castellanos Molina Jose Antonio",
    "wof:placetype":"venue"
},
  "geometry": {"coordinates":[-3.1651539803,39.7596817017],"type":"Point"}
}