{
  "type": "Feature",
  "properties": {
    "addr:full":"Calle de Renedo, 10 Valladolid Valladolid 47005",
    "addr:housenumber":"10",
    "addr:postcode":"47005",
    "addr:street":"Calle De Renedo",
    "iso:country":"ES",
    "sg:address":"Calle de Renedo, 10",
    "sg:city":"Valladolid",
    "sg:orig_category":"Agentes Generales De Seguros",
    "sg:phone":"+34 983 29 24 26",
    "sg:postcode":"47005",
    "sg:province":"Valladolid",
    "wof:name":"Gonzalez Jimenez Maria Paz",
    "wof:placetype":"venue"
},
  "geometry": {"coordinates":[-4.7150101662,41.6521530151],"type":"Point"}
}