{
  "type": "Feature",
  "properties": {
    "iso:country":"ES",
    "sg:address":"Avda Camilo Alonso Vega, 14",
    "sg:city":"Santander",
    "sg:orig_category":"Bisuter\u00cda, Joyer\u00cda, Relojer\u00cda (al Por Menor)",
    "sg:phone":"+34 942 23 57 44",
    "sg:postcode":"39007",
    "sg:province":"Cantabria",
    "wof:name":"Alonso Hermosa Francisco Javier",
    "wof:placetype":"venue"
},
  "geometry": {"coordinates":[-3.8263390064,43.4597892761],"type":"Point"}
}