{
  "type": "Feature",
  "properties": {
    "addr:full":"Calle de Merida, 79 Santos De Maimona Badajoz 06230",
    "addr:housenumber":"79",
    "addr:postcode":"06230",
    "addr:street":"Calle De Merida",
    "iso:country":"ES",
    "sg:address":"Calle de Merida, 79",
    "sg:city":"Santos De Maimona",
    "sg:orig_category":"Delegados, Agentes De Tr\u00c1nsito, Auxiliares De Transporte Internacional",
    "sg:phone":"+34 924 57 14 40",
    "sg:postcode":"06230",
    "sg:province":"Badajoz",
    "wof:name":"Transportes Andres Gordillo S.l.",
    "wof:placetype":"venue"
},
  "geometry": {"coordinates":[-6.3741970062,38.4484481812],"type":"Point"}
}