{
  "type": "Feature",
  "properties": {
    "addr:full":"Pg Sort (de La), 27 Torredembarra Tarragona 43830",
    "addr:postcode":"43830",
    "iso:country":"ES",
    "sg:address":"Pg Sort (de La), 27",
    "sg:city":"Torredembarra",
    "sg:orig_category":"Inform\u00c1tica, Ofim\u00c1tica (estudios, Asesor\u00cda, Ingenier\u00cda, Formaci\u00d3n)",
    "sg:phone":"+34 977 64 53 05",
    "sg:postcode":"43830",
    "sg:province":"Tarragona",
    "wof:name":"Bitres Informatica I Comunicacions S.l.",
    "wof:placetype":"venue"
},
  "geometry": {"coordinates":[1.3995809555,41.1428642273],"type":"Point"}
}