{
  "type": "Feature",
  "properties": {
    "addr:full":"Carrer de Noi Del Sucre, 30 Viladecans Barcelona 08840",
    "addr:housenumber":"30",
    "addr:postcode":"08840",
    "addr:street":"Carrer De Noi Del Sucre",
    "iso:country":"ES",
    "sg:address":"Carrer de Noi Del Sucre, 30",
    "sg:city":"Viladecans",
    "sg:orig_category":"Restaurantes",
    "sg:phone":"+34 936 37 09 12",
    "sg:postcode":"08840",
    "sg:province":"Barcelona",
    "wof:name":"Peregrina Salvatierra Carmen",
    "wof:placetype":"venue"
},
  "geometry": {"coordinates":[2.0205490589,41.3112411499],"type":"Point"}
}