{
  "type": "Feature",
  "properties": {
    "iso:country":"ES",
    "sg:address":"Calle de Aurea Galindo, S/n",
    "sg:city":"Linares",
    "sg:orig_category":"Aceites Y Grasas Alimentarias (fabricaci\u00d3n, Al Por Mayor)",
    "sg:phone":"+34 953 69 82 36",
    "sg:postcode":"23700",
    "sg:province":"Ja\u00e9n",
    "wof:name":"Aceites Las Palomas S.l.",
    "wof:placetype":"venue"
},
  "geometry": {"coordinates":[-3.6437597275,38.0930557251],"type":"Point"}
}