{
  "type": "Feature",
  "properties": {
    "addr:full":"Ponte, S/n Carballo A Coru\u00f1a 15100",
    "addr:housenumber":"s / n",
    "addr:postcode":"15100",
    "addr:street":"Corun\u0303A",
    "iso:country":"ES",
    "sg:address":"Ponte, S/n",
    "sg:city":"Carballo",
    "sg:orig_category":"Vinos Y Licores (venta Al Por Menor)",
    "sg:phone":"+34 981 70 04 64",
    "sg:postcode":"15100",
    "sg:province":"A Coru\u00f1a",
    "wof:name":"Vinos Pichel S.l.",
    "wof:placetype":"venue"
},
  "geometry": {"coordinates":[-8.693903923,43.2135543823],"type":"Point"}
}