{
  "type": "Feature",
  "properties": {
    "addr:full":"Calle de Zu\u00d1iga, 4 Salamanca Salamanca 37004",
    "addr:housenumber":"4",
    "addr:postcode":"37004",
    "addr:street":"Calle De Zun\u0303Iga",
    "iso:country":"ES",
    "sg:address":"Calle de Zu\u00d1iga, 4",
    "sg:city":"Salamanca",
    "sg:orig_category":"Agencias Y Agentes Comerciales, Representantes",
    "sg:phone":"+34 923 23 46 01",
    "sg:postcode":"37004",
    "sg:province":"Salamanca",
    "wof:name":"Hernandez Madrid Pedro",
    "wof:placetype":"venue"
},
  "geometry": {"coordinates":[-5.6510648727,40.9716720581],"type":"Point"}
}