{
  "type": "Feature",
  "properties": {
    "addr:full":"Calle de Alta Del Mar, 86 Valencia Valencia 46024",
    "addr:housenumber":"86",
    "addr:postcode":"46024",
    "addr:street":"Calle De Alta Del Mar",
    "iso:country":"ES",
    "sg:address":"Calle de Alta Del Mar, 86",
    "sg:city":"Valencia",
    "sg:orig_category":"Peluquer\u00cdas, Peluquer\u00cda Mixta",
    "sg:phone":"+34 963 67 61 80",
    "sg:postcode":"46024",
    "sg:province":"Valencia",
    "wof:name":"Nacher Soler Miguel Angel",
    "wof:placetype":"venue"
},
  "geometry": {"coordinates":[-0.3340063095,39.4486503601],"type":"Point"}
}