{
  "type": "Feature",
  "properties": {
    "addr:full":"Limoneros, 32 Gelves Sevilla 41120",
    "addr:housenumber":"32",
    "addr:postcode":"41120",
    "addr:street":"Limoneros",
    "iso:country":"ES",
    "sg:address":"Limoneros, 32",
    "sg:city":"Gelves",
    "sg:orig_category":"Sociedades, Compa\u00d1\u00cdas Aseguradoras",
    "sg:phone":"+34 955 76 29 41",
    "sg:postcode":"41120",
    "sg:province":"Sevilla",
    "wof:name":"Cm Equipos De Seguridad Sl",
    "wof:placetype":"venue"
},
  "geometry": {"coordinates":[-6.023015976,37.3349304199],"type":"Point"}
}