{
  "type": "Feature",
  "properties": {
    "addr:full":"Carrer de Bisbe Morgades, 27 Vic Barcelona 08500",
    "addr:housenumber":"27",
    "addr:postcode":"08500",
    "addr:street":"Carrer De Bisbe Morgades",
    "iso:country":"ES",
    "sg:address":"Carrer de Bisbe Morgades, 27",
    "sg:city":"Vic",
    "sg:orig_category":"Ense\u00d1anza: Idiomas",
    "sg:phone":"+34 938 85 17 08",
    "sg:postcode":"08500",
    "sg:province":"Barcelona",
    "wof:name":"Intertravel Work S.l.",
    "wof:placetype":"venue"
},
  "geometry": {"coordinates":[2.2507069111,41.9305953979],"type":"Point"}
}