{
  "type": "Feature",
  "properties": {
    "iso:country":"ES",
    "sg:address":"Calle de Jose Maria Alonso, 8",
    "sg:city":"Malaga",
    "sg:orig_category":"Arquitectos",
    "sg:phone":"+34 952 29 69 49",
    "sg:postcode":"29018",
    "sg:province":"M\u00e1laga",
    "wof:name":"Navas Barcelo Agustin",
    "wof:placetype":"venue"
},
  "geometry": {"coordinates":[-4.3586220741,36.7311935425],"type":"Point"}
}