{
  "type": "Feature",
  "properties": {
    "iso:country":"ES",
    "sg:address":"Calle de Chile, 162",
    "sg:city":"Coslada",
    "sg:orig_category":"Farmacias",
    "sg:phone":"+34 916 69 87 79",
    "sg:postcode":"28820",
    "sg:province":"Madrid",
    "wof:name":"Gavilanes Borja Gema",
    "wof:placetype":"venue"
},
  "geometry": {"coordinates":[-3.5510401726,40.4242324829],"type":"Point"}
}