{
  "type": "Feature",
  "properties": {
    "addr:full":"Calle de Alamillo, 92 Saceruela Ciudad Real 13414",
    "addr:housenumber":"92",
    "addr:postcode":"13414",
    "addr:street":"Calle De Alamillo",
    "iso:country":"ES",
    "sg:address":"Calle de Alamillo, 92",
    "sg:city":"Saceruela",
    "sg:orig_category":"Delegados, Agentes De Tr\u00c1nsito, Auxiliares De Transporte Internacional",
    "sg:phone":"+34 926 77 90 45",
    "sg:postcode":"13414",
    "sg:province":"Ciudad Real",
    "wof:name":"Bermejo Rivera Luis",
    "wof:placetype":"venue"
},
  "geometry": {"coordinates":[-4.6062178612,38.9433631897],"type":"Point"}
}