{
  "type": "Feature",
  "properties": {
    "addr:full":"C/ Espronceda, 66 Elche Alicante 03204",
    "addr:housenumber":"66",
    "addr:postcode":"03204",
    "addr:street":"C / Espronceda",
    "iso:country":"ES",
    "sg:address":"C/ Espronceda, 66",
    "sg:city":"Elche",
    "sg:orig_category":"Ingeniero",
    "sg:phone":"+34 966 64 07 53",
    "sg:postcode":"03204",
    "sg:province":"Alicante",
    "wof:name":"Mora Martinez Jose",
    "wof:placetype":"venue"
},
  "geometry": {"coordinates":[-0.70638901,38.2605400085],"type":"Point"}
}