{
  "type": "Feature",
  "properties": {
    "iso:country":"ES",
    "sg:address":"Carr Sant Joan (de), 12",
    "sg:city":"Albaida",
    "sg:orig_category":"Estancos",
    "sg:phone":"+34 962 39 08 96",
    "sg:postcode":"46860",
    "sg:province":"Valencia",
    "wof:name":"Vilaplana Sanchis Jose Damian",
    "wof:placetype":"venue"
},
  "geometry": {"coordinates":[-0.5182440281,38.8401374817],"type":"Point"}
}