{
  "type": "Feature",
  "properties": {
    "addr:full":"Rua Garcia Olloqui, 9 Vigo Pontevedra 36201",
    "addr:housenumber":"9",
    "addr:postcode":"36201",
    "addr:street":"Rua Garcia Olloqui",
    "iso:country":"ES",
    "sg:address":"Rua Garcia Olloqui, 9",
    "sg:city":"Vigo",
    "sg:orig_category":"Almacenes Y Tiendas De Productos Variados",
    "sg:phone":"+34 986 22 92 17",
    "sg:postcode":"36201",
    "sg:province":"Pontevedra",
    "wof:name":"Baraci\u00f1a S.l.",
    "wof:placetype":"venue"
},
  "geometry": {"coordinates":[-8.724360466,42.2400741577],"type":"Point"}
}