{
  "type": "Feature",
  "properties": {
    "addr:full":"Avda Miguel Enriquez, 3 Real Pontevedra 36950",
    "addr:housenumber":"3",
    "addr:postcode":"36950",
    "addr:street":"Avda Miguel Enriquez",
    "iso:country":"ES",
    "sg:address":"Avda Miguel Enriquez, 3",
    "sg:city":"Real",
    "sg:orig_category":"Peluqueros: De Se\u00d1oras",
    "sg:phone":"+34 986 31 38 69",
    "sg:postcode":"36950",
    "sg:province":"Pontevedra",
    "wof:name":"Tenorio Gayo Ines",
    "wof:placetype":"venue"
},
  "geometry": {"coordinates":[-8.738442421,42.2772254944],"type":"Point"}
}