{
  "type": "Feature",
  "properties": {
    "addr:full":"Psaj Virgen Del Rocio, S/n Ecija Sevilla 41400",
    "addr:postcode":"41400",
    "addr:street":"S / N",
    "iso:country":"ES",
    "sg:address":"Psaj Virgen Del Rocio, S/n",
    "sg:city":"Ecija",
    "sg:orig_category":"Agencias Y Agentes Comerciales, Representantes",
    "sg:phone":"+34 954 83 18 66",
    "sg:postcode":"41400",
    "sg:province":"Sevilla",
    "wof:name":"Moya Espejo Aquilino",
    "wof:placetype":"venue"
},
  "geometry": {"coordinates":[-5.0780930519,37.5400657654],"type":"Point"}
}