{
  "type": "Feature",
  "properties": {
    "iso:country":"ES",
    "sg:address":"Avda Orense, 8",
    "sg:city":"Marin",
    "sg:orig_category":"Bibliotecas, Mediatecas",
    "sg:phone":"+34 986 88 01 97",
    "sg:postcode":"36900",
    "sg:province":"Pontevedra",
    "wof:name":"Biblioteca Publica Municipal",
    "wof:placetype":"venue"
},
  "geometry": {"coordinates":[-8.6985750198,42.3930587769],"type":"Point"}
}