{
  "type": "Feature",
  "properties": {
    "iso:country":"ES",
    "sg:address":"Carr Manuel De Falla, 1",
    "sg:city":"Pla Parcial Platja",
    "sg:orig_category":"Bares, Piano",
    "sg:phone":"+34 966 86 73 59",
    "sg:postcode":"03580",
    "sg:province":"Alicante",
    "wof:name":"Ejido Garcia Jose Alberto",
    "wof:placetype":"venue"
},
  "geometry": {"coordinates":[-0.1033039987,38.5793037415],"type":"Point"}
}