{
  "type": "Feature",
  "properties": {
    "iso:country":"ES",
    "sg:address":"Avda Repelega, 4",
    "sg:city":"Portugalete",
    "sg:orig_category":"Agencias Y Agentes Comerciales, Representantes",
    "sg:phone":"+34 944 72 19 65",
    "sg:postcode":"48920",
    "sg:province":"Vizcaya",
    "wof:name":"Gris Roman J. Manuel",
    "wof:placetype":"venue"
},
  "geometry": {"coordinates":[-3.0178596973,43.3148918152],"type":"Point"}
}