{
  "type": "Feature",
  "properties": {
    "iso:country":"ES",
    "sg:address":"Vint I Tres (urb Tres Cales), S/n",
    "sg:city":"Ametlla Mar",
    "sg:orig_category":"Deportes N\u00c1uticos, Acu\u00c1ticos Y Subacu\u00c1ticos: Art\u00cdculos Y Equipo (al Por Menor)",
    "sg:phone":"+34 977 45 70 71",
    "sg:postcode":"43860",
    "sg:province":"Tarragona",
    "wof:name":"Nautica Costa Dorada S.l.",
    "wof:placetype":"venue"
},
  "geometry": {"coordinates":[0.7992730141,40.8853607178],"type":"Point"}
}