{
  "type": "Feature",
  "properties": {
    "iso:country":"ES",
    "sg:address":"Av Montgo, 43",
    "sg:city":"Escala",
    "sg:orig_category":"Asociaciones Y Clubs Deportivos",
    "sg:phone":"+34 972 77 00 14",
    "sg:postcode":"17130",
    "sg:province":"Girona",
    "wof:name":"Sport Emporium S.l.",
    "wof:placetype":"venue"
},
  "geometry": {"coordinates":[3.1394970417,42.1139335632],"type":"Point"}
}