{
  "type": "Feature",
  "properties": {
    "iso:country":"ES",
    "sg:address":"C/ Padro, 42",
    "sg:city":"Ripollet",
    "sg:orig_category":"Pod\u00d3logos: Pedicuros",
    "sg:phone":"+34 936 91 46 79",
    "sg:postcode":"08291",
    "sg:province":"Barcelona",
    "wof:name":"Chaparro Nu\u00f1ez Lidia",
    "wof:placetype":"venue"
},
  "geometry": {"coordinates":[2.1570210457,41.497467041],"type":"Point"}
}