{
  "type": "Feature",
  "properties": {
    "addr:full":"Calle de Joaquin Arellano, 1 Arenas -areeta Vizcaya 48930",
    "addr:housenumber":"1;areeta",
    "addr:postcode":"48930",
    "addr:street":"Calle De Joaquin Arellano",
    "iso:country":"ES",
    "sg:address":"Calle de Joaquin Arellano, 1",
    "sg:city":"Arenas -areeta",
    "sg:orig_category":"Molduras, Junquillos, Listones Y Molduras Perforadas",
    "sg:phone":"+34 944 64 31 70",
    "sg:postcode":"48930",
    "sg:province":"Vizcaya",
    "wof:name":"Ferrero Chimeno Angel",
    "wof:placetype":"venue"
},
  "geometry": {"coordinates":[-3.0122210979,43.325958252],"type":"Point"}
}