{
  "type": "Feature",
  "properties": {
    "addr:full":"Pg Joan Carles I, 19 Eivissa Islas Baleares 07800",
    "addr:housenumber":"19",
    "addr:postcode":"07800",
    "addr:street":"Pg Joan Carles I",
    "iso:country":"ES",
    "sg:address":"Pg Joan Carles I, 19",
    "sg:city":"Eivissa",
    "sg:orig_category":"Arquitectos",
    "sg:phone":"+34 971 31 31 81",
    "sg:postcode":"07800",
    "sg:province":"Islas Baleares",
    "wof:name":"Millan Solsona Jose",
    "wof:placetype":"venue"
},
  "geometry": {"coordinates":[1.447726965,38.9138946533],"type":"Point"}
}