{
  "type": "Feature",
  "properties": {
    "addr:full":"Calvelo, 15 Sto.andre De Vea Pontevedra 36676",
    "addr:housenumber":"15",
    "addr:postcode":"36676",
    "addr:street":"Calvelo",
    "iso:country":"ES",
    "sg:address":"Calvelo, 15",
    "sg:city":"Sto.andre De Vea",
    "sg:orig_category":"Transportes Por V\u00cdas Navegables",
    "sg:phone":"+34 986 58 66 31",
    "sg:postcode":"36676",
    "sg:province":"Pontevedra",
    "wof:name":"Garcia Pernas Jesus",
    "wof:placetype":"venue"
},
  "geometry": {"coordinates":[-8.4650993347,42.645198822],"type":"Point"}
}