{
  "type": "Feature",
  "properties": {
    "iso:country":"ES",
    "sg:address":"Calle de Norte, S/n",
    "sg:city":"Valdepe\u00f1as",
    "sg:orig_category":"Inmobiliaria (agencias)",
    "sg:phone":"+34 926 32 01 56",
    "sg:postcode":"13300",
    "sg:province":"Ciudad Real",
    "wof:name":"Maresman S.l.",
    "wof:placetype":"venue"
},
  "geometry": {"coordinates":[-3.3907010555,38.7551193237],"type":"Point"}
}