{
  "type": "Feature",
  "properties": {
    "addr:full":"Av Paisos Catalans (dels), S/n Salou Tarragona 43840",
    "addr:postcode":"43840",
    "addr:street":"Av Paisos Catalans Dels S / N",
    "iso:country":"ES",
    "sg:address":"Av Paisos Catalans (dels), S/n",
    "sg:city":"Salou",
    "sg:orig_category":"Bancos",
    "sg:phone":"+34 977 38 10 82",
    "sg:postcode":"43840",
    "sg:province":"Tarragona",
    "wof:name":"Banc Sabadell S.a.",
    "wof:placetype":"venue"
},
  "geometry": {"coordinates":[1.1454210281,41.081237793],"type":"Point"}
}