{
  "type": "Feature",
  "properties": {
    "addr:full":"Plaz Jose Antonio, 2 Ardisa Zaragoza 50614",
    "addr:housenumber":"2",
    "addr:postcode":"50614",
    "addr:street":"Jose Antonio",
    "iso:country":"ES",
    "sg:address":"Plaz Jose Antonio, 2",
    "sg:city":"Ardisa",
    "sg:orig_category":"Producci\u00d3n, Venta De Productos De Agricultura Biol\u00d3gica",
    "sg:phone":"+34 976 68 78 03",
    "sg:postcode":"50614",
    "sg:province":"Zaragoza",
    "wof:name":"Botaya Bimbela Francisco",
    "wof:placetype":"venue"
},
  "geometry": {"coordinates":[-0.7578619719,42.201171875],"type":"Point"}
}