{
  "type": "Feature",
  "properties": {
    "addr:full":"Calle de Sol, 21 Puebla Cazalla Sevilla 41540",
    "addr:housenumber":"21",
    "addr:postcode":"41540",
    "addr:street":"Calle De Sol",
    "iso:country":"ES",
    "sg:address":"Calle de Sol, 21",
    "sg:city":"Puebla Cazalla",
    "sg:orig_category":"Inform\u00c1tica (estudios, Servicios, Asesor\u00cda, Formaci\u00d3n)",
    "sg:phone":"+34 954 84 63 21",
    "sg:postcode":"41540",
    "sg:province":"Sevilla",
    "sg:website":"www.lineapc.net",
    "wof:name":"Tejada Martinez Antonio Jesus",
    "wof:placetype":"venue"
},
  "geometry": {"coordinates":[-5.312169075,37.2214241028],"type":"Point"}
}