{
  "type": "Feature",
  "properties": {
    "addr:full":"Calle de Buenavista, 2 Sestao Vizcaya 48910",
    "addr:housenumber":"2",
    "addr:postcode":"48910",
    "addr:street":"Calle De Buenavista",
    "iso:country":"ES",
    "sg:address":"Calle de Buenavista, 2",
    "sg:city":"Sestao",
    "sg:orig_category":"Cristaler\u00cdas",
    "sg:phone":"+34 944 00 16 86",
    "sg:postcode":"48910",
    "sg:province":"Vizcaya",
    "wof:name":"Jose Luis Garcia Oribe",
    "wof:placetype":"venue"
},
  "geometry": {"coordinates":[-3.00812006,43.3075218201],"type":"Point"}
}