{
  "type": "Feature",
  "properties": {
    "iso:country":"ES",
    "sg:address":"Calle de Relator Gonzalez, 30",
    "sg:city":"Hervas",
    "sg:orig_category":"Ropa Para Se\u00d1oras Y Caballeros (al Por Menor)",
    "sg:phone":"+34 927 48 10 58",
    "sg:postcode":"10700",
    "sg:province":"C\u00e1ceres",
    "wof:name":"Martin Gonzalez Antonia",
    "wof:placetype":"venue"
},
  "geometry": {"coordinates":[-5.8584089279,40.2739601135],"type":"Point"}
}