{
  "type": "Feature",
  "properties": {
    "addr:full":"Calle de Grande, 3 Guare\u00f1a Badajoz 06470",
    "addr:housenumber":"3",
    "addr:postcode":"06470",
    "addr:street":"Calle De Grande",
    "iso:country":"ES",
    "sg:address":"Calle de Grande, 3",
    "sg:city":"Guare\u00f1a",
    "sg:orig_category":"Cajas De Ahorro",
    "sg:phone":"+34 924 35 12 65",
    "sg:postcode":"06470",
    "sg:province":"Badajoz",
    "sg:website":"www.cajaextremadura.es",
    "wof:name":"Caja De Ahorros Y Monte De Piedad De Extremadura",
    "wof:placetype":"venue"
},
  "geometry": {"coordinates":[-6.102312088,38.8593902588],"type":"Point"}
}