{
  "type": "Feature",
  "properties": {
    "addr:full":"Calle de Carpinteros, 1 Almansa Albacete 02640",
    "addr:housenumber":"1",
    "addr:postcode":"02640",
    "addr:street":"Calle De Carpinteros",
    "iso:country":"ES",
    "sg:address":"Calle de Carpinteros, 1",
    "sg:city":"Almansa",
    "sg:orig_category":"Agentes, Concesionarios Y Sucursales De Veh\u00cdculos",
    "sg:phone":"+34 967 34 02 03",
    "sg:postcode":"02640",
    "sg:province":"Albacete",
    "wof:name":"Autocomercial Almansa S.l.",
    "wof:placetype":"venue"
},
  "geometry": {"coordinates":[-1.113373518,38.8729858398],"type":"Point"}
}