{
  "type": "Feature",
  "properties": {
    "iso:country":"ES",
    "sg:address":"Calle de Daoiz, 5",
    "sg:city":"Ceuta",
    "sg:orig_category":"Televisi\u00d3n, V\u00cddeo: Aparatos Y Accesorios (venta)",
    "sg:phone":"+34 956 51 16 41",
    "sg:postcode":"51001",
    "sg:province":"Ceuta",
    "wof:name":"Mona Lisa Trading Corporation S.l.",
    "wof:placetype":"venue"
},
  "geometry": {"coordinates":[-5.3097295761,35.8878211975],"type":"Point"}
}