{
  "type": "Feature",
  "properties": {
    "iso:country":"ES",
    "sg:address":"Calle de Beira, 66",
    "sg:city":"Salamanca",
    "sg:orig_category":"Arquitectos",
    "sg:phone":"+34 923 21 68 89",
    "sg:postcode":"37008",
    "sg:province":"Salamanca",
    "wof:name":"Garcia Del Ca\u00f1izo Laura",
    "wof:placetype":"venue"
},
  "geometry": {"coordinates":[-5.6831541061,40.9482307434],"type":"Point"}
}