{
  "type": "Feature",
  "properties": {
    "addr:full":"Calle de Alonso Nu\u00d1ez De Reinoso, 2 Guadalajara Guadalajara 19002",
    "addr:housenumber":"2",
    "addr:postcode":"19002",
    "addr:street":"Calle De Alonso Nun\u0303Ez De Reinoso",
    "iso:country":"ES",
    "sg:address":"Calle de Alonso Nu\u00d1ez De Reinoso, 2",
    "sg:city":"Guadalajara",
    "sg:orig_category":"Comercio De Mobiliario De Oficina",
    "sg:phone":"+34 949 22 31 50",
    "sg:postcode":"19002",
    "sg:province":"Guadalajara",
    "wof:name":"Equimobel S.l.",
    "wof:placetype":"venue"
},
  "geometry": {"coordinates":[-3.1643242836,40.6265258789],"type":"Point"}
}