{
  "type": "Feature",
  "properties": {
    "addr:full":"Calle de Palacios, 21 Albarracin Teruel 44100",
    "addr:housenumber":"21",
    "addr:postcode":"44100",
    "addr:street":"Calle De Palacios",
    "iso:country":"ES",
    "sg:address":"Calle de Palacios, 21",
    "sg:city":"Albarracin",
    "sg:orig_category":"Albergues",
    "sg:phone":"+34 978 70 03 27",
    "sg:postcode":"44100",
    "sg:province":"Teruel",
    "wof:name":"Montepalacios Albarracin S.l.",
    "wof:placetype":"venue"
},
  "geometry": {"coordinates":[-1.4457730055,40.4087867737],"type":"Point"}
}