{
  "type": "Feature",
  "properties": {
    "iso:country":"ES",
    "sg:address":"Avda Cuenca (de), 2",
    "sg:city":"Tinajas",
    "sg:orig_category":"Aceites Y Grasas Alimentarias (fabricaci\u00d3n, Al Por Mayor)",
    "sg:phone":"+34 969 37 70 81",
    "sg:postcode":"16534",
    "sg:province":"Cuenca",
    "wof:name":"Aceites Tinajas S.l.",
    "wof:placetype":"venue"
},
  "geometry": {"coordinates":[-2.4928894043,40.3686523438],"type":"Point"}
}