{
  "type": "Feature",
  "properties": {
    "iso:country":"ES",
    "sg:address":"Arrabal Pedralba, 181",
    "sg:city":"Lliria",
    "sg:orig_category":"Puertas Y Portales",
    "sg:phone":"+34 962 78 18 74",
    "sg:postcode":"46160",
    "sg:province":"Valencia",
    "wof:name":"Puertas Metalicas Lliria S.l.",
    "wof:placetype":"venue"
},
  "geometry": {"coordinates":[-0.5952839851,39.6247406006],"type":"Point"}
}