{
  "type": "Feature",
  "properties": {
    "addr:full":"Av Santa Coloma, 114 Santa Coloma De Gramenet Barcelona 08922",
    "addr:housenumber":"114",
    "addr:postcode":"08922",
    "addr:street":"Av Santa Coloma",
    "iso:country":"ES",
    "sg:address":"Av Santa Coloma, 114",
    "sg:city":"Santa Coloma De Gramenet",
    "sg:orig_category":"Reposter\u00cdas",
    "sg:phone":"+34 934 66 15 96",
    "sg:postcode":"08922",
    "sg:province":"Barcelona",
    "wof:name":"Agrupacion De Industriales Panaderos De Santa Coloma S.a.",
    "wof:placetype":"venue"
},
  "geometry": {"coordinates":[2.2090406418,41.4458389282],"type":"Point"}
}