{
  "type": "Feature",
  "properties": {
    "addr:full":"Calle de Calderon, S/n Santa Fe Granada 18320",
    "addr:housenumber":"/ n",
    "addr:postcode":"18320",
    "addr:street":"Calle De Calderon S",
    "iso:country":"ES",
    "sg:address":"Calle de Calderon, S/n",
    "sg:city":"Santa Fe",
    "sg:orig_category":"M\u00c9dicos: Estomatolog\u00cda",
    "sg:phone":"+34 958 51 04 14",
    "sg:postcode":"18320",
    "sg:province":"Granada",
    "wof:name":"Salas Perez Eva Maria",
    "wof:placetype":"venue"
},
  "geometry": {"coordinates":[-3.7182695866,37.1907310486],"type":"Point"}
}