{
  "type": "Feature",
  "properties": {
    "iso:country":"ES",
    "sg:address":"Real, 49",
    "sg:city":"Betxi",
    "sg:orig_category":"Peluquer\u00cdas, Peluquer\u00cda Mixta",
    "sg:phone":"+34 964 62 23 21",
    "sg:postcode":"12549",
    "sg:province":"Castell\u00f3n",
    "wof:name":"Pina Vivas Juan Carlos",
    "wof:placetype":"venue"
},
  "geometry": {"coordinates":[-0.1983969957,39.9277191162],"type":"Point"}
}