{
  "type": "Feature",
  "properties": {
    "addr:full":"Calle de Figueroa, 20 Arrecife Las Palmas 35500",
    "addr:housenumber":"20",
    "addr:postcode":"35500",
    "addr:street":"Calle De Figueroa",
    "iso:country":"ES",
    "sg:address":"Calle de Figueroa, 20",
    "sg:city":"Arrecife",
    "sg:orig_category":"Clases De M\u00dasica Y Canto",
    "sg:phone":"+34 928 81 70 69",
    "sg:postcode":"35500",
    "sg:province":"Las Palmas",
    "wof:name":"Tocoyma Musical S.l.",
    "wof:placetype":"venue"
},
  "geometry": {"coordinates":[-13.5515823364,28.960187912],"type":"Point"}
}