{
  "type": "Feature",
  "properties": {
    "addr:full":"Calle de Andres Mellado, 45 Madrid Madrid 28015",
    "addr:housenumber":"45",
    "addr:postcode":"madrid;28015",
    "addr:street":"Calle De Andres Mellado",
    "iso:country":"ES",
    "sg:address":"Calle de Andres Mellado, 45",
    "sg:city":"Madrid",
    "sg:orig_category":"Abogados",
    "sg:phone":"+34 915 44 46 82",
    "sg:postcode":"28015",
    "sg:province":"Madrid",
    "sg:website":"www.gespaniagua.com",
    "wof:name":"Gestoria Paniagua S.l.",
    "wof:placetype":"venue"
},
  "geometry": {"coordinates":[-3.7143752575,40.4352340698],"type":"Point"}
}