{
  "type": "Feature",
  "properties": {
    "iso:country":"ES",
    "sg:address":"Calle de Zuatzu, 3",
    "sg:city":"Donostia-san Sebastian",
    "sg:orig_category":"Asesor\u00cda Sobre Comunicaci\u00d3n De Empresas",
    "sg:phone":"+34 943 01 42 24",
    "sg:postcode":"20018",
    "sg:province":"Guip\u00f9zcoa",
    "wof:name":"Consultores De Empresa -cde S.l.l.",
    "wof:placetype":"venue"
},
  "geometry": {"coordinates":[-2.0090401173,43.2967758179],"type":"Point"}
}