{
  "type": "Feature",
  "properties": {
    "iso:country":"ES",
    "sg:address":"Calle de Santa Teresa De Jesus, 7",
    "sg:city":"Talavera Reina",
    "sg:orig_category":"Imprenta",
    "sg:phone":"+34 925 82 08 88",
    "sg:postcode":"45600",
    "sg:province":"Toledo",
    "wof:name":"Recio Vadillo Ricardo",
    "wof:placetype":"venue"
},
  "geometry": {"coordinates":[-4.8289718628,39.963508606],"type":"Point"}
}