{
  "type": "Feature",
  "properties": {
    "addr:full":"Ptge Sant Bernat, 1 Barcelona Barcelona 08001",
    "addr:housenumber":"1",
    "addr:postcode":"08001",
    "addr:street":"Ptge Sant Bernat",
    "iso:country":"ES",
    "sg:address":"Ptge Sant Bernat, 1",
    "sg:city":"Barcelona",
    "sg:orig_category":"Molduras, Junquillos, Listones Y Molduras Perforadas",
    "sg:phone":"+34 933 18 43 45",
    "sg:postcode":"08001",
    "sg:province":"Barcelona",
    "wof:name":"Hidalgo Tejada Justiniano",
    "wof:placetype":"venue"
},
  "geometry": {"coordinates":[2.1646039486,41.3839187622],"type":"Point"}
}