{
  "type": "Feature",
  "properties": {
    "addr:full":"Ctra Monforte, Km. 0001,6 Aspe Alicante 03680",
    "addr:postcode":"03680",
    "addr:street":"Ctra Monforte Km. 0001,6",
    "iso:country":"ES",
    "sg:address":"Ctra Monforte, Km. 0001,6",
    "sg:city":"Aspe",
    "sg:orig_category":"Promotores Constructores",
    "sg:phone":"+34 965 49 50 02",
    "sg:postcode":"03680",
    "sg:province":"Alicante",
    "wof:name":"Castello Construcciones E Infraestructuras S.l.",
    "wof:placetype":"venue"
},
  "geometry": {"coordinates":[-0.7689840198,38.3471984863],"type":"Point"}
}