{
  "type": "Feature",
  "properties": {
    "iso:country":"ES",
    "sg:address":"Avda Carlos V (de), 28",
    "sg:city":"Mostoles",
    "sg:orig_category":"Centros De Educaci\u00d3n Especial",
    "sg:phone":"+34 916 45 85 55",
    "sg:postcode":"28937",
    "sg:province":"Madrid",
    "wof:name":"Colegio Leon Felipe",
    "wof:placetype":"venue"
},
  "geometry": {"coordinates":[-3.853399992,40.3165740967],"type":"Point"}
}