{
  "type": "Feature",
  "properties": {
    "iso:country":"ES",
    "sg:address":"Pla\u00c7 L'escorxador, 1",
    "sg:city":"Lleida",
    "sg:orig_category":"Fabricaci\u00d3n, Distribuci\u00d3n De Discos, V\u00cddeodiscos Y Musicassettes",
    "sg:phone":"+34 973 26 09 12",
    "sg:postcode":"25003",
    "sg:province":"Lleida",
    "wof:name":"Blind Valkyria Sl",
    "wof:placetype":"venue"
},
  "geometry": {"coordinates":[0.6176589727,41.6121826172],"type":"Point"}
}