{
  "type": "Feature",
  "properties": {
    "addr:full":"Av Pau Casals, 27 Lloret Mar Girona 17310",
    "addr:housenumber":"27",
    "addr:postcode":"17310",
    "addr:street":"Av Pau Casals",
    "iso:country":"ES",
    "sg:address":"Av Pau Casals, 27",
    "sg:city":"Lloret Mar",
    "sg:orig_category":"Zapatos (al Por Menor)",
    "sg:phone":"+34 972 36 08 54",
    "sg:postcode":"17310",
    "sg:province":"Girona",
    "wof:name":"Roura Cullall S.l.",
    "wof:placetype":"venue"
},
  "geometry": {"coordinates":[2.8550839424,41.7025413513],"type":"Point"}
}