{
  "type": "Feature",
  "properties": {
    "addr:full":"Calle de Potosi, 13 Malaga M\u00e1laga 29018",
    "addr:housenumber":"13",
    "addr:postcode":"29018",
    "addr:street":"Calle De Potosi;Ma\u0301Laga",
    "iso:country":"ES",
    "sg:address":"Calle de Potosi, 13",
    "sg:city":"Malaga",
    "sg:orig_category":"Empresas De Carpinter\u00cda",
    "sg:phone":"+34 952 20 20 72",
    "sg:postcode":"29018",
    "sg:province":"M\u00e1laga",
    "wof:name":"Industria De Aluminio El Palo S.l.",
    "wof:placetype":"venue"
},
  "geometry": {"coordinates":[-4.3513979912,36.7222480774],"type":"Point"}
}