{
  "type": "Feature",
  "properties": {
    "addr:full":"Urb Mas Gerembi, S/n El Catllar Tarragona 43764",
    "addr:housenumber":"s / n",
    "addr:postcode":"43764",
    "addr:street":"Urb",
    "iso:country":"ES",
    "sg:address":"Urb Mas Gerembi, S/n",
    "sg:city":"El Catllar",
    "sg:orig_category":"Productores Recolectores, Venta Directa De Vinos",
    "sg:phone":"+34 977 26 00 08",
    "sg:postcode":"43764",
    "sg:province":"Tarragona",
    "wof:name":"Bodegas Mas Del Cosme S.l.",
    "wof:placetype":"venue"
},
  "geometry": {"coordinates":[1.3273400068,41.17552948],"type":"Point"}
}