{
  "type": "Feature",
  "properties": {
    "addr:full":"Plaz Generalisimo, 12 Suances Cantabria 39340",
    "addr:housenumber":"12",
    "addr:postcode":"39340",
    "addr:street":"Plaz Generalisimo",
    "iso:country":"ES",
    "sg:address":"Plaz Generalisimo, 12",
    "sg:city":"Suances",
    "sg:orig_category":"Panader\u00cdas, Panader\u00cdas",
    "sg:phone":"+34 942 81 12 63",
    "sg:postcode":"39340",
    "sg:province":"Cantabria",
    "wof:name":"Ruiz Palacios Joaquin",
    "wof:placetype":"venue"
},
  "geometry": {"coordinates":[-4.0415692329,43.4246292114],"type":"Point"}
}