{
  "type": "Feature",
  "properties": {
    "addr:full":"Dehesilla Leon, S/n Alcolea C\u00f3rdoba 14610",
    "addr:postcode":"14610",
    "addr:street":"Leon S / N Alcolea Co\u0301Rdoba",
    "iso:country":"ES",
    "sg:address":"Dehesilla Leon, S/n",
    "sg:city":"Alcolea",
    "sg:orig_category":"Hormigonados",
    "sg:phone":"+34 957 33 31 51",
    "sg:postcode":"14610",
    "sg:province":"C\u00f3rdoba",
    "wof:name":"Hormigones Sumihor S.l.",
    "wof:placetype":"venue"
},
  "geometry": {"coordinates":[-4.6729812622,37.932182312],"type":"Point"}
}