{
  "type": "Feature",
  "properties": {
    "iso:country":"ES",
    "sg:address":"Calle de Madrid, 20",
    "sg:city":"Getafe",
    "sg:orig_category":"Ropa Para Caballeros (al Por Menor)",
    "sg:phone":"+34 916 82 36 60",
    "sg:postcode":"28901",
    "sg:province":"Madrid",
    "sg:website":"www.grupocortefiel.com",
    "wof:name":"Cortefiel S.a.",
    "wof:placetype":"venue"
},
  "geometry": {"coordinates":[-3.7309610844,40.306098938],"type":"Point"}
}