{
  "type": "Feature",
  "properties": {
    "iso:country":"ES",
    "sg:address":"Karrika Nagusia, 6",
    "sg:city":"Igantzi",
    "sg:orig_category":"Comunidades Religiosas",
    "sg:phone":"+34 948 63 77 30",
    "sg:postcode":"31790",
    "sg:province":"Navarra",
    "wof:name":"Parroquia San Miguel De Yanci",
    "wof:placetype":"venue"
},
  "geometry": {"coordinates":[-1.7011239529,43.2256507874],"type":"Point"}
}