{
  "type": "Feature",
  "properties": {
    "iso:country":"ES",
    "sg:address":"Calle de Iru\u00d1a, 2",
    "sg:city":"Bilbao",
    "sg:orig_category":"Centros Empresariales",
    "sg:phone":"+34 944 74 57 84",
    "sg:postcode":"48014",
    "sg:province":"Vizcaya",
    "wof:name":"Ikasge",
    "wof:placetype":"venue"
},
  "geometry": {"coordinates":[-2.9490470886,43.2688484192],"type":"Point"}
}