{
  "type": "Feature",
  "properties": {
    "iso:country":"ES",
    "sg:address":"Calle de Dos De Mayo, 20",
    "sg:city":"Cruce I",
    "sg:orig_category":"Peluquer\u00cdas, Peluquer\u00cda Mixta",
    "sg:phone":"+34 928 75 48 42",
    "sg:postcode":"35110",
    "sg:province":"Las Palmas",
    "wof:name":"Perez Nieve Antonia",
    "wof:placetype":"venue"
},
  "geometry": {"coordinates":[-15.4417943954,27.8526535034],"type":"Point"}
}