{
  "type": "Feature",
  "properties": {
    "iso:country":"ES",
    "sg:address":"Calle de Fernando El Catolico, 8",
    "sg:city":"Medina Campo",
    "sg:orig_category":"Venta, Instalaci\u00d3n De Calefacci\u00d3n",
    "sg:phone":"+34 983 83 76 78",
    "sg:postcode":"47400",
    "sg:province":"Valladolid",
    "wof:name":"Matilla Gago Jesus",
    "wof:placetype":"venue"
},
  "geometry": {"coordinates":[-4.9133691788,41.311088562],"type":"Point"}
}