{
  "type": "Feature",
  "properties": {
    "iso:country":"ES",
    "sg:address":"Urb El Prado, 1",
    "sg:city":"Merida",
    "sg:orig_category":"Ense\u00d1anza, Formaci\u00d3n Profesional: Aprendizaje",
    "sg:phone":"+34 924 37 28 61",
    "sg:postcode":"06800",
    "sg:province":"Badajoz",
    "wof:name":"Consorcio Provincial De Prevencion Y Extincion De Incendios",
    "wof:placetype":"venue"
},
  "geometry": {"coordinates":[-6.3500027657,38.9179878235],"type":"Point"}
}