{
  "type": "Feature",
  "properties": {
    "iso:country":"ES",
    "sg:address":"Amategi Aldea, 103",
    "sg:city":"Altzo",
    "sg:orig_category":"Piscinas, Accesorios, Suministros (fabricaci\u00d3n, Al Por Mayor)",
    "sg:phone":"+34 943 65 45 00",
    "sg:postcode":"20268",
    "sg:province":"Guip\u00f9zcoa",
    "wof:name":"Suministros Quimicos Gor S. A.",
    "wof:placetype":"venue"
},
  "geometry": {"coordinates":[-2.085203886,43.0452766418],"type":"Point"}
}