{
  "type": "Feature",
  "properties": {
    "addr:full":"Calle de Orellana, 1 Madrid Madrid 28004",
    "addr:housenumber":"1",
    "addr:postcode":"28004",
    "addr:street":"Calle De Orellana",
    "iso:country":"ES",
    "sg:address":"Calle de Orellana, 1",
    "sg:city":"Madrid",
    "sg:orig_category":"Ropa Para Se\u00d1oras Y Caballeros (al Por Menor)",
    "sg:phone":"+34 913 08 24 06",
    "sg:postcode":"28004",
    "sg:province":"Madrid",
    "sg:website":"www.bdba.es",
    "wof:name":"Orellana-1 S.l.",
    "wof:placetype":"venue"
},
  "geometry": {"coordinates":[-3.6958580017,40.4270401001],"type":"Point"}
}