{
  "type": "Feature",
  "properties": {
    "iso:country":"ES",
    "sg:address":"Padrenda De Abaixo, S/n",
    "sg:city":"Padrenda De Abaixo",
    "sg:orig_category":"Producci\u00d3n, Venta De Productos De Agricultura Biol\u00d3gica",
    "sg:phone":"+34 986 74 76 70",
    "sg:postcode":"36638",
    "sg:province":"Pontevedra",
    "wof:name":"Explotaciones Agrarias De Padrenda",
    "wof:placetype":"venue"
},
  "geometry": {"coordinates":[-8.7815494537,42.4442214966],"type":"Point"}
}