{
  "type": "Feature",
  "properties": {
    "addr:full":"Pase Plaza De Toros (de La), 4 Almagro Ciudad Real 13270",
    "addr:housenumber":"4",
    "addr:postcode":"13270",
    "iso:country":"ES",
    "sg:address":"Pase Plaza De Toros (de La), 4",
    "sg:city":"Almagro",
    "sg:orig_category":"Institutos De Belleza",
    "sg:phone":"+34 926 26 10 57",
    "sg:postcode":"13270",
    "sg:province":"Ciudad Real",
    "wof:name":"Vargas Ure\u00f1a Yolanda",
    "wof:placetype":"venue"
},
  "geometry": {"coordinates":[-3.7093889713,38.8842353821],"type":"Point"}
}