{
  "type": "Feature",
  "properties": {
    "iso:country":"ES",
    "sg:address":"Ctra Port, Del, 114",
    "sg:city":"Porto Cristo",
    "sg:orig_category":"Locales Y Clases De Danza",
    "sg:phone":"+34 971 82 05 93",
    "sg:postcode":"07680",
    "sg:province":"Islas Baleares",
    "wof:name":"Jimenez Mu\u00f1oz Saturnina",
    "wof:placetype":"venue"
},
  "geometry": {"coordinates":[3.3308730125,39.5457763672],"type":"Point"}
}