{
  "type": "Feature",
  "properties": {
    "addr:full":"San Anton, 1 Iru\u00f1a Navarra 31001",
    "addr:housenumber":"1",
    "addr:postcode":"31001",
    "addr:street":"San Anton",
    "iso:country":"ES",
    "sg:address":"San Anton, 1",
    "sg:city":"Iru\u00f1a",
    "sg:orig_category":"Arquitectos",
    "sg:phone":"+34 948 22 39 22",
    "sg:postcode":"31001",
    "sg:province":"Navarra",
    "wof:name":"Miranda Garcia Jose Enrique",
    "wof:placetype":"venue"
},
  "geometry": {"coordinates":[-1.6453479528,42.816570282],"type":"Point"}
}