{
  "type": "Feature",
  "properties": {
    "addr:full":"Calle de Marroquina, 36 Madrid Madrid 28030",
    "addr:housenumber":"36",
    "addr:postcode":"madrid;28030",
    "addr:street":"Calle De Marroquina",
    "iso:country":"ES",
    "sg:address":"Calle de Marroquina, 36",
    "sg:city":"Madrid",
    "sg:orig_category":"Molduras, Junquillos, Listones Y Molduras Perforadas",
    "sg:phone":"+34 914 30 51 00",
    "sg:postcode":"28030",
    "sg:province":"Madrid",
    "wof:name":"Acebes Gozalo Nicolas",
    "wof:placetype":"venue"
},
  "geometry": {"coordinates":[-3.6481978893,40.408164978],"type":"Point"}
}