{
  "type": "Feature",
  "properties": {
    "iso:country":"ES",
    "sg:address":"Rua Matias Lopez, 58",
    "sg:city":"Sarria",
    "sg:orig_category":"Peluquer\u00cdas, Peluquer\u00cda Mixta",
    "sg:phone":"+34 982 53 35 43",
    "sg:postcode":"27600",
    "sg:province":"Lugo",
    "wof:name":"Sobrado Carreira Montserrat",
    "wof:placetype":"venue"
},
  "geometry": {"coordinates":[-7.4130039215,42.7791442871],"type":"Point"}
}