{
  "type": "Feature",
  "properties": {
    "iso:country":"ES",
    "sg:address":"Calle de Fuencarral, 70",
    "sg:city":"Madrid",
    "sg:orig_category":"Edici\u00d3n De Diarios, Revistas, Boletines",
    "sg:phone":"+34 915 32 05 04",
    "sg:postcode":"28004",
    "sg:province":"Madrid",
    "sg:website":"www.incipeditores.com",
    "wof:name":"Proyectos Y Producciones Editoriales Cyan S.a.",
    "wof:placetype":"venue"
},
  "geometry": {"coordinates":[-3.7006988525,40.4246292114],"type":"Point"}
}