{
  "type": "Feature",
  "properties": {
    "addr:full":"Pol. Macua, 17 Aviles Asturias 33490",
    "addr:housenumber":"17",
    "addr:postcode":"33490",
    "iso:country":"ES",
    "sg:address":"Pol. Macua, 17",
    "sg:city":"Aviles",
    "sg:orig_category":"Calderer\u00cda",
    "sg:phone":"+34 985 51 13 56",
    "sg:postcode":"33490",
    "sg:province":"Asturias",
    "wof:name":"Talleres Julian Fernandez S.l.",
    "wof:placetype":"venue"
},
  "geometry": {"coordinates":[-5.894133091,43.5974273682],"type":"Point"}
}