{
  "type": "Feature",
  "properties": {
    "iso:country":"ES",
    "sg:address":"Avda Condes De San Isidro, 5",
    "sg:city":"Fuengirola",
    "sg:orig_category":"Zapatos (al Por Menor)",
    "sg:phone":"+34 952 46 54 58",
    "sg:postcode":"29640",
    "sg:province":"M\u00e1laga",
    "wof:name":"Morales Cortes Jose",
    "wof:placetype":"venue"
},
  "geometry": {"coordinates":[-4.6268019676,36.5328140259],"type":"Point"}
}