{
  "type": "Feature",
  "properties": {
    "addr:full":"Calle de Acacia, 29 Torrejon Ardoz Madrid 28850",
    "addr:housenumber":"29",
    "addr:postcode":"28850",
    "addr:street":"Calle De Acacia",
    "iso:country":"ES",
    "sg:address":"Calle de Acacia, 29",
    "sg:city":"Torrejon Ardoz",
    "sg:orig_category":"Empresas De Portes Y Mensajer\u00cda",
    "sg:phone":"+34 916 56 16 13",
    "sg:postcode":"28850",
    "sg:province":"Madrid",
    "wof:name":"General Service Business S.l.",
    "wof:placetype":"venue"
},
  "geometry": {"coordinates":[-3.4585008621,40.4467315674],"type":"Point"}
}