{
  "type": "Feature",
  "properties": {
    "iso:country":"ES",
    "sg:address":"Av Prat De La Riba, 19",
    "sg:city":"Tarragona",
    "sg:orig_category":"Consultor\u00cdas Diversas",
    "sg:phone":"+34 977 25 08 65",
    "sg:postcode":"43001",
    "sg:province":"Tarragona",
    "wof:name":"Abydos Enginyeria Consultoris I Ser",
    "wof:placetype":"venue"
},
  "geometry": {"coordinates":[1.246733,41.116177],"type":"Point"}
}