{
  "type": "Feature",
  "properties": {
    "addr:full":"Rua Paseo (do), 12 Ourense Ourense 32003",
    "addr:housenumber":"12",
    "addr:postcode":"32003",
    "addr:street":"Rua Paseo Do",
    "iso:country":"ES",
    "sg:address":"Rua Paseo (do), 12",
    "sg:city":"Ourense",
    "sg:orig_category":"Peluqueros: De Se\u00d1oras",
    "sg:phone":"+34 988 23 51 21",
    "sg:postcode":"32003",
    "sg:province":"Ourense",
    "wof:name":"Rodriguez Fernandez Avelino",
    "wof:placetype":"venue"
},
  "geometry": {"coordinates":[-7.8644618988,42.3388748169],"type":"Point"}
}