{
  "type": "Feature",
  "properties": {
    "addr:full":"Calle de Juan Ramon Jimenez, 651 Montecalderon Guadalajara 19170",
    "addr:postcode":"19170",
    "addr:street":"Calle De Juan Ramon Jimenez 651 Montecalderon",
    "iso:country":"ES",
    "sg:address":"Calle de Juan Ramon Jimenez, 651",
    "sg:city":"Montecalderon",
    "sg:orig_category":"Instalaci\u00d3n, Reparaci\u00d3n De Ascensores Y Montacargas",
    "sg:phone":"+34 949 33 47 19",
    "sg:postcode":"19170",
    "sg:province":"Guadalajara",
    "wof:name":"Salas Bocanegra Dolores",
    "wof:placetype":"venue"
},
  "geometry": {"coordinates":[-3.4147589207,40.6791305542],"type":"Point"}
}