{
  "type": "Feature",
  "properties": {
    "iso:country":"ES",
    "sg:address":"Carrer de Peix, 3",
    "sg:city":"Vendrell",
    "sg:orig_category":"Fotocopias, Reprograf\u00cda",
    "sg:phone":"+34 977 66 89 66",
    "sg:postcode":"43700",
    "sg:province":"Tarragona",
    "wof:name":"Papereria El Vendrell S.l.",
    "wof:placetype":"venue"
},
  "geometry": {"coordinates":[1.5352640152,41.2203712463],"type":"Point"}
}