{
  "type": "Feature",
  "properties": {
    "iso:country":"ES",
    "sg:address":"Carr Antoni Canovas, 5",
    "sg:city":"Muro",
    "sg:orig_category":"Electricidad: Instaladores",
    "sg:phone":"+34 971 86 05 50",
    "sg:postcode":"07440",
    "sg:province":"Islas Baleares",
    "wof:name":"Cloquell Riutort Juan",
    "wof:placetype":"venue"
},
  "geometry": {"coordinates":[3.055574894,39.7366905212],"type":"Point"}
}