{
  "type": "Feature",
  "properties": {
    "addr:full":"Calle de Acequia Grande, 16 Velez-rubio Almer\u00eda 04820",
    "addr:housenumber":"16",
    "addr:postcode":"04820",
    "addr:street":"Calle De Acequia Grande;Almeri\u0301A",
    "iso:country":"ES",
    "sg:address":"Calle de Acequia Grande, 16",
    "sg:city":"Velez-rubio",
    "sg:orig_category":"M\u00c1rmoles, Granitos Y Piedras Naturales",
    "sg:phone":"+34 950 41 25 08",
    "sg:postcode":"04820",
    "sg:province":"Almer\u00eda",
    "wof:name":"Marmoles Galera S.l.",
    "wof:placetype":"venue"
},
  "geometry": {"coordinates":[-2.0761520863,37.6467247009],"type":"Point"}
}