{
  "type": "Feature",
  "properties": {
    "addr:full":"Torre De Quevedo, 3 Torno Ciudad Real 13194",
    "addr:housenumber":"3",
    "addr:postcode":"13194",
    "iso:country":"ES",
    "sg:address":"Torre De Quevedo, 3",
    "sg:city":"Torno",
    "sg:orig_category":"Textil",
    "sg:phone":"+34 926 78 34 30",
    "sg:postcode":"13194",
    "sg:province":"Ciudad Real",
    "wof:name":"Garcia Colado Basilio",
    "wof:placetype":"venue"
},
  "geometry": {"coordinates":[-4.4072389603,39.4603309631],"type":"Point"}
}