{
  "type": "Feature",
  "properties": {
    "addr:full":"Calle de Fajardo, 12 Villanueva Serena Badajoz 06700",
    "addr:housenumber":"12",
    "addr:postcode":"06700",
    "addr:street":"Calle De Fajardo",
    "iso:country":"ES",
    "sg:address":"Calle de Fajardo, 12",
    "sg:city":"Villanueva Serena",
    "sg:orig_category":"Frutas Y Legumbres Secas (al Por Mayor)",
    "sg:phone":"+34 924 84 71 61",
    "sg:postcode":"06700",
    "sg:province":"Badajoz",
    "wof:name":"Diaz Calderon Antonio",
    "wof:placetype":"venue"
},
  "geometry": {"coordinates":[-5.8035588264,38.9732513428],"type":"Point"}
}