{
  "type": "Feature",
  "properties": {
    "iso:country":"ES",
    "sg:address":"Calle de Tahona, 10",
    "sg:city":"Brunete",
    "sg:orig_category":"Bricolaje, Herramientas (al Por Menor)",
    "sg:phone":"+34 918 15 80 57",
    "sg:postcode":"28690",
    "sg:province":"Madrid",
    "wof:name":"Alvarez Alonso Constante",
    "wof:placetype":"venue"
},
  "geometry": {"coordinates":[-4.0031309128,40.4036941528],"type":"Point"}
}