{
  "type": "Feature",
  "properties": {
    "addr:full":"Calle de Etxepare, 11 Valle Trapaga Vizcaya 48510",
    "addr:housenumber":"11",
    "addr:postcode":"48510",
    "addr:street":"Calle De Etxepare;Trapaga",
    "iso:country":"ES",
    "sg:address":"Calle de Etxepare, 11",
    "sg:city":"Valle Trapaga",
    "sg:orig_category":"Agentes, Concesionarios Y Sucursales De Camiones Y Veh\u00cdculos Industriales",
    "sg:phone":"+34 944 92 34 43",
    "sg:postcode":"48510",
    "sg:province":"Vizcaya",
    "wof:name":"Zaramategui S.l.",
    "wof:placetype":"venue"
},
  "geometry": {"coordinates":[-3.0372130871,43.3030891418],"type":"Point"}
}