{
  "type": "Feature",
  "properties": {
    "addr:full":"Calle de Genova, S/n Granada Granada 18004",
    "addr:housenumber":"s / n",
    "addr:postcode":"18004",
    "addr:street":"Calle De Genova",
    "iso:country":"ES",
    "sg:address":"Calle de Genova, S/n",
    "sg:city":"Granada",
    "sg:orig_category":"Empresas De Carpinter\u00cda Met\u00c1lica",
    "sg:phone":"+34 958 25 07 80",
    "sg:postcode":"18004",
    "sg:province":"Granada",
    "wof:name":"Hernandez Martin Victoriano",
    "wof:placetype":"venue"
},
  "geometry": {"coordinates":[-3.6044139862,37.1668891907],"type":"Point"}
}