{
  "type": "Feature",
  "properties": {
    "iso:country":"ES",
    "sg:address":"Berdules, S/n",
    "sg:city":"El Pozon",
    "sg:orig_category":"Semiller\u00cdas",
    "sg:phone":"+34 985 90 10 70",
    "sg:postcode":"33875",
    "sg:province":"Asturias",
    "wof:name":"Alvarez Garcia Jose Javier",
    "wof:placetype":"venue"
},
  "geometry": {"coordinates":[-6.4948635101,43.2939605713],"type":"Point"}
}