{
  "type": "Feature",
  "properties": {
    "addr:full":"Calle de Doyague, 12 Salamanca Salamanca 37008",
    "addr:housenumber":"12",
    "addr:postcode":"37008",
    "addr:street":"Calle De Doyague",
    "iso:country":"ES",
    "sg:address":"Calle de Doyague, 12",
    "sg:city":"Salamanca",
    "sg:orig_category":"Arquitectos",
    "sg:phone":"+34 923 26 05 18",
    "sg:postcode":"37008",
    "sg:province":"Salamanca",
    "wof:name":"Martin-cubas Fernandez Alfredo",
    "wof:placetype":"venue"
},
  "geometry": {"coordinates":[-5.6650128365,40.9599685669],"type":"Point"}
}