{
  "type": "Feature",
  "properties": {
    "iso:country":"ES",
    "sg:address":"Avda Nuestra Se\u00d1ora De Fatima, 92",
    "sg:city":"Madrid",
    "sg:orig_category":"Fisioterapia",
    "sg:phone":"+34 914 61 75 44",
    "sg:postcode":"28047",
    "sg:province":"Madrid",
    "wof:name":"Cruz Vazquez Jose Luis",
    "wof:placetype":"venue"
},
  "geometry": {"coordinates":[-3.7486009598,40.3805160522],"type":"Point"}
}