{
  "type": "Feature",
  "properties": {
    "iso:country":"ES",
    "sg:address":"Avgda Textil, 9",
    "sg:city":"Ontinyent",
    "sg:orig_category":"Chapister\u00cda",
    "sg:phone":"+34 962 91 50 76",
    "sg:postcode":"46870",
    "sg:province":"Valencia",
    "wof:name":"Vecauto Ontinyent S. Cop. V.",
    "wof:placetype":"venue"
},
  "geometry": {"coordinates":[-0.6013389826,38.8257293701],"type":"Point"}
}