{
  "type": "Feature",
  "properties": {
    "iso:country":"ES",
    "sg:address":"Calle de Estambrera, 5",
    "sg:city":"Logro\u00f1o",
    "sg:orig_category":"Autob\u00das (explotaci\u00d3n Y Servicios De)",
    "sg:phone":"+34 941 50 02 00",
    "sg:postcode":"26006",
    "sg:province":"La Rioja",
    "sg:website":"www.riojacar.com",
    "wof:name":"Riojana De Autocares S.l.",
    "wof:placetype":"venue"
},
  "geometry": {"coordinates":[-2.4386780262,42.4557991028],"type":"Point"}
}