{
  "type": "Feature",
  "properties": {
    "addr:full":"Calle de Coronel Lopez Pe\u00d1a, 6 Santiago Ribera Murcia 30720",
    "addr:housenumber":"6",
    "addr:postcode":"30720",
    "addr:street":"Calle De Coronel Lopez Pen\u0303A",
    "iso:country":"ES",
    "sg:address":"Calle de Coronel Lopez Pe\u00d1a, 6",
    "sg:city":"Santiago Ribera",
    "sg:orig_category":"Caf\u00c9s, Bares, Cervecer\u00cdas",
    "sg:phone":"+34 968 57 22 76",
    "sg:postcode":"30720",
    "sg:province":"Murcia",
    "wof:name":"Gomez Henarejos Jose Maria",
    "wof:placetype":"venue"
},
  "geometry": {"coordinates":[-0.8082981706,37.7956848145],"type":"Point"}
}