{
  "type": "Feature",
  "properties": {
    "addr:full":"Urb. Santa Lucia, 2 Alcoceber Castell\u00f3n 12579",
    "addr:housenumber":"2",
    "addr:postcode":"12579",
    "addr:street":"Santa Lucia;Castello\u0301N",
    "iso:country":"ES",
    "sg:address":"Urb. Santa Lucia, 2",
    "sg:city":"Alcoceber",
    "sg:orig_category":"Promotores Constructores",
    "sg:phone":"+34 964 41 32 38",
    "sg:postcode":"12579",
    "sg:province":"Castell\u00f3n",
    "wof:name":"Gestion Alcocebre S.l.",
    "wof:placetype":"venue"
},
  "geometry": {"coordinates":[0.2850950062,40.2547187805],"type":"Point"}
}