{
  "type": "Feature",
  "properties": {
    "addr:full":"Ctra. Aeropuerto, S/n Zaragoza Zaragoza 50011",
    "addr:housenumber":"s / n",
    "addr:postcode":"50011",
    "addr:street":"Ctra. Aeropuerto",
    "iso:country":"ES",
    "sg:address":"Ctra. Aeropuerto, S/n",
    "sg:city":"Zaragoza",
    "sg:orig_category":"Promotores Constructores",
    "sg:phone":"+34 976 13 10 08",
    "sg:postcode":"50011",
    "sg:province":"Zaragoza",
    "wof:name":"Goa Invest S.a.",
    "wof:placetype":"venue"
},
  "geometry": {"coordinates":[-0.9387440085,41.6622886658],"type":"Point"}
}