{
  "type": "Feature",
  "properties": {
    "iso:country":"ES",
    "sg:address":"Avgd Alcalde Recasens, 36",
    "sg:city":"Lleida",
    "sg:orig_category":"Asesor\u00cda Fiscal Y Jur\u00cddica",
    "sg:phone":"+34 973 22 26 25",
    "sg:postcode":"25005",
    "sg:province":"Lleida",
    "wof:name":"Puyol Capdevila Neus",
    "wof:placetype":"venue"
},
  "geometry": {"coordinates":[0.6317840219,41.6279830933],"type":"Point"}
}