{
  "type": "Feature",
  "properties": {
    "iso:country":"ES",
    "sg:address":"Calle de El Prado, 9",
    "sg:city":"Vitoria-gasteiz",
    "sg:orig_category":"Ense\u00d1anza, Formaci\u00d3n Profesional: Aprendizaje",
    "sg:phone":"+34 945 13 51 18",
    "sg:postcode":"01005",
    "sg:province":"\u00c1lava",
    "wof:name":"Ararteko",
    "wof:placetype":"venue"
},
  "geometry": {"coordinates":[-2.6750929356,42.8458480835],"type":"Point"}
}