{
  "type": "Feature",
  "properties": {
    "addr:full":"Calle de Emperatriz Eugenia, 18 Granada Granada 18002",
    "addr:housenumber":"18",
    "addr:postcode":"18002",
    "addr:street":"Calle De Emperatriz Eugenia",
    "iso:country":"ES",
    "sg:address":"Calle de Emperatriz Eugenia, 18",
    "sg:city":"Granada",
    "sg:orig_category":"Pescader\u00cdas (al Por Menor)",
    "sg:phone":"+34 958 20 60 70",
    "sg:postcode":"18002",
    "sg:province":"Granada",
    "wof:name":"Lopez Cantos Rafael",
    "wof:placetype":"venue"
},
  "geometry": {"coordinates":[-3.6077818871,37.1755180359],"type":"Point"}
}