{
  "type": "Feature",
  "properties": {
    "iso:country":"ES",
    "sg:address":"Calle de General Pardi\u00d1as, 48",
    "sg:city":"Madrid",
    "sg:orig_category":"Asesor\u00cdas Y Estudios Financieros",
    "sg:phone":"+34 913 09 14 65",
    "sg:postcode":"28001",
    "sg:province":"Madrid",
    "wof:name":"Toledano Nieto Juan Manuel",
    "wof:placetype":"venue"
},
  "geometry": {"coordinates":[-3.6782069206,40.4281997681],"type":"Point"}
}