{
  "type": "Feature",
  "properties": {
    "addr:full":"La Iglesia, 4 Mata Del Paramo Le\u00f3n 24887",
    "addr:housenumber":"4",
    "addr:postcode":"24887",
    "addr:street":"Iglesia;Leo\u0301N",
    "iso:country":"ES",
    "sg:address":"La Iglesia, 4",
    "sg:city":"Mata Del Paramo",
    "sg:orig_category":"Producci\u00d3n, Comercio De Cereales",
    "sg:phone":"+34 987 37 38 31",
    "sg:postcode":"24887",
    "sg:province":"Le\u00f3n",
    "wof:name":"Cereales Santiago S.l.",
    "wof:placetype":"venue"
},
  "geometry": {"coordinates":[-5.0011892319,42.8468589783],"type":"Point"}
}