{
  "type": "Feature",
  "properties": {
    "iso:country":"ES",
    "sg:address":"Pl Mercat, 1",
    "sg:city":"Ampolla",
    "sg:orig_category":"Restaurantes",
    "sg:phone":"+34 977 46 00 86",
    "sg:postcode":"43895",
    "sg:province":"Tarragona",
    "wof:name":"Estorach Caballe Pedro",
    "wof:placetype":"venue"
},
  "geometry": {"coordinates":[0.7096909881,40.8122291565],"type":"Point"}
}