{
  "type": "Feature",
  "properties": {
    "addr:full":"Calle de Virgen De Los Reyes, 32 Carmona Sevilla 41410",
    "addr:housenumber":"32",
    "addr:postcode":"41410",
    "addr:street":"Calle De Virgen De Los Reyes",
    "iso:country":"ES",
    "sg:address":"Calle de Virgen De Los Reyes, 32",
    "sg:city":"Carmona",
    "sg:orig_category":"Forjas Y Altos Hornos",
    "sg:phone":"+34 954 14 05 97",
    "sg:postcode":"41410",
    "sg:province":"Sevilla",
    "wof:name":"Garcia Saa Demetrio",
    "wof:placetype":"venue"
},
  "geometry": {"coordinates":[-5.6460490227,37.4664573669],"type":"Point"}
}