{
  "type": "Feature",
  "properties": {
    "addr:full":"Carr Fatima, S/n Garden Curt-la Paloma Alicante 03570",
    "addr:postcode":"03570",
    "addr:street":"Carr Fatima S / N Garden Curt-La",
    "iso:country":"ES",
    "sg:address":"Carr Fatima, S/n",
    "sg:city":"Garden Curt-la Paloma",
    "sg:orig_category":"Estancos",
    "sg:phone":"+34 965 89 39 93",
    "sg:postcode":"03570",
    "sg:province":"Alicante",
    "wof:name":"Jover Sanchez Antonio",
    "wof:placetype":"venue"
},
  "geometry": {"coordinates":[-0.2327190042,38.505821228],"type":"Point"}
}