{
  "type": "Feature",
  "properties": {
    "addr:full":"Carrer de Call, 10 Barcelona Barcelona 08002",
    "addr:housenumber":"10",
    "addr:postcode":"08002",
    "addr:street":"Carrer De Call",
    "iso:country":"ES",
    "sg:address":"Carrer de Call, 10",
    "sg:city":"Barcelona",
    "sg:orig_category":"Bisuter\u00cda, Joyer\u00cda, Relojer\u00cda (al Por Menor)",
    "sg:phone":"+34 933 01 08 76",
    "sg:postcode":"08002",
    "sg:province":"Barcelona",
    "wof:name":"Daryanani Arias Rochi",
    "wof:placetype":"venue"
},
  "geometry": {"coordinates":[2.1760659218,41.3820571899],"type":"Point"}
}