{
  "type": "Feature",
  "properties": {
    "iso:country":"ES",
    "sg:address":"Avda Oriental (sp), 3",
    "sg:city":"San Pedro Alcantara",
    "sg:orig_category":"Supermercados Y Hipermercados",
    "sg:phone":"+34 952 78 84 07",
    "sg:postcode":"29670",
    "sg:province":"M\u00e1laga",
    "wof:name":"Rodalgo Servicios Inmobiliarios S.l",
    "wof:placetype":"venue"
},
  "geometry": {"coordinates":[-4.9872617722,36.4867973328],"type":"Point"}
}