{
  "type": "Feature",
  "properties": {
    "addr:full":"Calle de Juan Fuentes Echevarria, 26 Caldas De Reis Pontevedra 36650",
    "addr:housenumber":"26",
    "addr:postcode":"36650",
    "addr:street":"Calle De Juan;Echevarria",
    "iso:country":"ES",
    "sg:address":"Calle de Juan Fuentes Echevarria, 26",
    "sg:city":"Caldas De Reis",
    "sg:orig_category":"Muebles, Minoristas",
    "sg:phone":"+34 986 54 03 33",
    "sg:postcode":"36650",
    "sg:province":"Pontevedra",
    "wof:name":"Muebles Caldas S. L.",
    "wof:placetype":"venue"
},
  "geometry": {"coordinates":[-8.6459236145,42.6039085388],"type":"Point"}
}