{
  "type": "Feature",
  "properties": {
    "iso:country":"ES",
    "sg:address":"Pg Fabra I Puig, 219",
    "sg:city":"Barcelona",
    "sg:orig_category":"Asesor\u00cda Fiscal Y Jur\u00cddica",
    "sg:phone":"+34 933 40 13 06",
    "sg:postcode":"08016",
    "sg:province":"Barcelona",
    "wof:name":"Lorenzo Trujillo Angeles",
    "wof:placetype":"venue"
},
  "geometry": {"coordinates":[2.1757209301,41.430229187],"type":"Point"}
}