{
  "type": "Feature",
  "properties": {
    "iso:country":"ES",
    "sg:address":"Calle de Alvaro De Lugo, 1",
    "sg:city":"Medina Campo",
    "sg:orig_category":"Promotores Constructores",
    "sg:phone":"+34 983 81 06 20",
    "sg:postcode":"47400",
    "sg:province":"Valladolid",
    "wof:name":"Araceli Rodriguez Lopez S.l.",
    "wof:placetype":"venue"
},
  "geometry": {"coordinates":[-4.9146022797,41.3029747009],"type":"Point"}
}