{
  "type": "Feature",
  "properties": {
    "iso:country":"ES",
    "sg:address":"Calle de P, 14",
    "sg:city":"Mutiloabeiti",
    "sg:orig_category":"Protecci\u00d3n Contra Incendios: Material, Instalaci\u00d3n, Mantenimiento",
    "sg:phone":"+34 948 23 64 85",
    "sg:postcode":"31192",
    "sg:province":"Navarra",
    "wof:name":"Extiniruna S.l.",
    "wof:placetype":"venue"
},
  "geometry": {"coordinates":[-1.6299179792,42.7884674072],"type":"Point"}
}