{
  "type": "Feature",
  "properties": {
    "iso:country":"ES",
    "sg:address":"Carrer de Can Brondo, 5",
    "sg:city":"Palma",
    "sg:orig_category":"Lencer\u00cda Femenina, Corseter\u00cda, Trajes De Ba\u00d1o (al Por Menor)",
    "sg:phone":"+34 971 71 11 03",
    "sg:postcode":"07001",
    "sg:province":"Islas Baleares",
    "sg:website":"www.undercolorsofbenetton.com",
    "wof:name":"Ltacataplis S.l.",
    "wof:placetype":"venue"
},
  "geometry": {"coordinates":[2.64782691,39.5712432861],"type":"Point"}
}