{
  "type": "Feature",
  "properties": {
    "addr:full":"Avda Castros (los), 65 Santander Cantabria 39005",
    "addr:housenumber":"65",
    "addr:postcode":"39005",
    "addr:street":"Avda Castros Los",
    "iso:country":"ES",
    "sg:address":"Avda Castros (los), 65",
    "sg:city":"Santander",
    "sg:orig_category":"Arquitectos",
    "sg:phone":"+34 942 21 91 90",
    "sg:postcode":"39005",
    "sg:province":"Cantabria",
    "wof:name":"Yurrita Paniagua Francisco Gerardo",
    "wof:placetype":"venue"
},
  "geometry": {"coordinates":[-3.8040802479,43.4703216553],"type":"Point"}
}