{
  "type": "Feature",
  "properties": {
    "iso:country":"ES",
    "sg:address":"Calle de Lucano, 2",
    "sg:city":"Almeria",
    "sg:orig_category":"Agentes De Seguros",
    "sg:phone":"+34 950 23 27 14",
    "sg:postcode":"04001",
    "sg:province":"Almer\u00eda",
    "wof:name":"Rodriguez Alonso Cesar Elias",
    "wof:placetype":"venue"
},
  "geometry": {"coordinates":[-2.4464359283,36.8485717773],"type":"Point"}
}