{
  "type": "Feature",
  "properties": {
    "addr:full":"Ctra Madrid, 14 Santa Marta De Tormes Salamanca 37900",
    "addr:housenumber":"14",
    "addr:postcode":"37900",
    "addr:street":"Ctra Madrid",
    "iso:country":"ES",
    "sg:address":"Ctra Madrid, 14",
    "sg:city":"Santa Marta De Tormes",
    "sg:orig_category":"Ense\u00d1anza, Formaci\u00d3n Profesional: Aprendizaje",
    "sg:phone":"+34 923 13 04 04",
    "sg:postcode":"37900",
    "sg:province":"Salamanca",
    "wof:name":"Padres Paules",
    "wof:placetype":"venue"
},
  "geometry": {"coordinates":[-5.6291890144,40.9501304626],"type":"Point"}
}