{
  "type": "Feature",
  "properties": {
    "addr:full":"Torres, 14 Lucena C\u00f3rdoba 14900",
    "addr:housenumber":"14",
    "addr:postcode":"14900",
    "addr:street":"Torres",
    "iso:country":"ES",
    "sg:address":"Torres, 14",
    "sg:city":"Lucena",
    "sg:orig_category":"Zapatos (al Por Menor)",
    "sg:phone":"+34 957 50 37 11",
    "sg:postcode":"14900",
    "sg:province":"C\u00f3rdoba",
    "wof:name":"Calzados Rogel S.l.",
    "wof:placetype":"venue"
},
  "geometry": {"coordinates":[-4.4869651794,37.4118537903],"type":"Point"}
}