{
  "type": "Feature",
  "properties": {
    "iso:country":"ES",
    "sg:address":"Carrer de Anselm Clave, 1",
    "sg:city":"Santa Perpetua De Mogoda",
    "sg:orig_category":"Ropa Para Se\u00d1oras Y Caballeros (al Por Menor)",
    "sg:phone":"+34 935 60 12 44",
    "sg:postcode":"08130",
    "sg:province":"Barcelona",
    "wof:name":"Casanovas Oriol Isidro",
    "wof:placetype":"venue"
},
  "geometry": {"coordinates":[2.1802799702,41.5371818542],"type":"Point"}
}