{
  "type": "Feature",
  "properties": {
    "addr:full":"Rua Conde Torrecedeira, 32 Vigo Pontevedra 36202",
    "addr:housenumber":"32",
    "addr:postcode":"36202",
    "addr:street":"Rua Conde Torrecedeira",
    "iso:country":"ES",
    "sg:address":"Rua Conde Torrecedeira, 32",
    "sg:city":"Vigo",
    "sg:orig_category":"M\u00c9dicos: Evaluaci\u00d3n Y Tratamiento Del Dolor",
    "sg:phone":"+34 986 20 50 39",
    "sg:postcode":"36202",
    "sg:province":"Pontevedra",
    "wof:name":"Marquina Tesouro Agustin",
    "wof:placetype":"venue"
},
  "geometry": {"coordinates":[-8.7319602966,42.2325363159],"type":"Point"}
}