{
  "type": "Feature",
  "properties": {
    "iso:country":"ES",
    "sg:address":"La Pozuela, 64",
    "sg:city":"Trebujena",
    "sg:orig_category":"Sales (al Por Mayor)",
    "sg:phone":"+34 956 39 57 43",
    "sg:postcode":"11560",
    "sg:province":"C\u00e1diz",
    "wof:name":"Comercial Angulas De Trebujena S.l.",
    "wof:placetype":"venue"
},
  "geometry": {"coordinates":[-6.1715888977,36.8716392517],"type":"Point"}
}