{
  "type": "Feature",
  "properties": {
    "addr:full":"J. Bonastre (pol Ind La Borda), S/n Caldes Montbui Barcelona 08140",
    "addr:postcode":"08140",
    "addr:street":"J.;Pol;La;S / N",
    "iso:country":"ES",
    "sg:address":"J. Bonastre (pol Ind La Borda), S/n",
    "sg:city":"Caldes Montbui",
    "sg:orig_category":"Fabricaci\u00d3n De Moldes Y Modelos",
    "sg:phone":"+34 938 65 33 45",
    "sg:postcode":"08140",
    "sg:province":"Barcelona",
    "wof:name":"Plastics Tecnics De Caldes S.a.",
    "wof:placetype":"venue"
},
  "geometry": {"coordinates":[2.1686599255,41.631111145],"type":"Point"}
}