{
  "type": "Feature",
  "properties": {
    "iso:country":"ES",
    "sg:address":"Calle de Cristobal Bordiu, 19",
    "sg:city":"Madrid",
    "sg:orig_category":"Centros Empresariales",
    "sg:phone":"+34 915 54 71 24",
    "sg:postcode":"28003",
    "sg:province":"Madrid",
    "wof:name":"Manpower Business Solutions S.l.u.",
    "wof:placetype":"venue"
},
  "geometry": {"coordinates":[-3.7002782822,40.4431228638],"type":"Point"}
}