{
  "type": "Feature",
  "properties": {
    "addr:full":"Avda Cruz Roja (la), 24 Jerez De La Frontera C\u00e1diz 11407",
    "addr:postcode":"11407",
    "addr:street":"Avda Cruz Roja La",
    "iso:country":"ES",
    "sg:address":"Avda Cruz Roja (la), 24",
    "sg:city":"Jerez De La Frontera",
    "sg:orig_category":"Asesor\u00cda Sobre Comunicaci\u00d3n De Empresas",
    "sg:phone":"+34 956 30 97 11",
    "sg:postcode":"11407",
    "sg:province":"C\u00e1diz",
    "wof:name":"Castro Cabrera Rafael",
    "wof:placetype":"venue"
},
  "geometry": {"coordinates":[-6.135445118,36.6978988647],"type":"Point"}
}