{
  "type": "Feature",
  "properties": {
    "iso:country":"ES",
    "sg:address":"Avda Constitucion, 5",
    "sg:city":"San Miguel",
    "sg:orig_category":"M\u00c9dicos: Otorrinolaringolog\u00cda",
    "sg:phone":"+34 968 23 68 31",
    "sg:postcode":"30008",
    "sg:province":"Murcia",
    "wof:name":"Caro Lopez Gerardo",
    "wof:placetype":"venue"
},
  "geometry": {"coordinates":[-1.1317830086,37.9894866943],"type":"Point"}
}