{
  "type": "Feature",
  "properties": {
    "iso:country":"ES",
    "sg:address":"Calle de Pais Valencia, 10",
    "sg:city":"Alcora",
    "sg:orig_category":"Peluquer\u00cdas, Peluquer\u00cda Mixta",
    "sg:phone":"+34 964 36 14 79",
    "sg:postcode":"12110",
    "sg:province":"Castell\u00f3n",
    "wof:name":"Abargues Juan Jose Antonio",
    "wof:placetype":"venue"
},
  "geometry": {"coordinates":[-0.211679,40.079216],"type":"Point"}
}