{
  "type": "Feature",
  "properties": {
    "iso:country":"ES",
    "sg:address":"Calle de Badajoz, S/n",
    "sg:city":"Coto",
    "sg:orig_category":"Paneles De Madera: Contrachapados, Fibras, Particulados, Estratificados (fabricaci\u00d3n, Venta)",
    "sg:phone":"+34 949 33 41 90",
    "sg:postcode":"19170",
    "sg:province":"Guadalajara",
    "wof:name":"Valentin Guerra Holgado",
    "wof:placetype":"venue"
},
  "geometry": {"coordinates":[-3.4445919991,40.7058448792],"type":"Point"}
}