{
  "type": "Feature",
  "properties": {
    "addr:full":"Calle de Pintor Lopez Mezquita, 6 Granada Granada 18002",
    "addr:housenumber":"6",
    "addr:postcode":"18002",
    "addr:street":"Calle De Pintor Lopez Mezquita",
    "iso:country":"ES",
    "sg:address":"Calle de Pintor Lopez Mezquita, 6",
    "sg:city":"Granada",
    "sg:orig_category":"Abogados",
    "sg:phone":"+34 958 20 29 99",
    "sg:postcode":"18002",
    "sg:province":"Granada",
    "wof:name":"Arenas Salvatierra Sigfredo",
    "wof:placetype":"venue"
},
  "geometry": {"coordinates":[-3.6076412201,37.1770744324],"type":"Point"}
}