{
  "type": "Feature",
  "properties": {
    "iso:country":"ES",
    "sg:address":"Calle de Mendez Nu\u00d1ez, 86",
    "sg:city":"Santa Cruz De Tenerife",
    "sg:orig_category":"Supermercados Y Hipermercados",
    "sg:phone":"+34 922 15 20 59",
    "sg:postcode":"38001",
    "sg:province":"Santa Cruz De Tenerife",
    "wof:name":"Herbendul S.l.",
    "wof:placetype":"venue"
},
  "geometry": {"coordinates":[-16.2511806488,28.4732017517],"type":"Point"}
}