{
  "type": "Feature",
  "properties": {
    "iso:country":"ES",
    "sg:address":"Calle de Alcalde Fernandez Mesa Porras, S/n",
    "sg:city":"Cordoba",
    "sg:orig_category":"Tapicer\u00cdas",
    "sg:phone":"+34 957 23 42 94",
    "sg:postcode":"14005",
    "sg:province":"C\u00f3rdoba",
    "sg:website":"www.venyveras.org/escabel.htm",
    "wof:name":"Miguez Y Castanedo S.l.",
    "wof:placetype":"venue"
},
  "geometry": {"coordinates":[-4.7926316261,37.8844833374],"type":"Point"}
}