{
  "type": "Feature",
  "properties": {
    "addr:full":"Avda Monegros, S/n Sari\u00f1ena Huesca 22200",
    "addr:housenumber":"s / n",
    "addr:postcode":"22200",
    "addr:street":"Avda Monegros",
    "iso:country":"ES",
    "sg:address":"Avda Monegros, S/n",
    "sg:city":"Sari\u00f1ena",
    "sg:classifiers":[
        {
            "category":"Taxi",
            "type":"Transportation"
        }
    ],
    "sg:phone":"+34 974 57 01 38",
    "sg:postcode":"22200",
    "sg:province":"Huesca",
    "wof:name":"Sales Altabas Angel",
    "wof:placetype":"venue"
},
  "geometry": {"coordinates":[-0.160879001,41.7910766602],"type":"Point"}
}