{
  "type": "Feature",
  "properties": {
    "iso:country":"ES",
    "sg:address":"Calle de Cadete Julio Llompart, 9",
    "sg:city":"Madrid",
    "sg:orig_category":"Trabajos De Soldaduras",
    "sg:phone":"+34 914 71 92 55",
    "sg:postcode":"28019",
    "sg:province":"Madrid",
    "wof:name":"Tecnicas Industriales De Mantenimiento Servicio Y Aplicacion S.l.",
    "wof:placetype":"venue"
},
  "geometry": {"coordinates":[-3.7336471081,40.3967437744],"type":"Point"}
}