{
  "type": "Feature",
  "properties": {
    "iso:country":"ES",
    "sg:address":"Calle de Vinacorba, 4",
    "sg:city":"Tamarite Litera",
    "sg:orig_category":"Equipo De Refrigeraci\u00d3n Industrial",
    "sg:phone":"+34 974 42 14 40",
    "sg:postcode":"22550",
    "sg:province":"Huesca",
    "wof:name":"Arfavima S.l.",
    "wof:placetype":"venue"
},
  "geometry": {"coordinates":[0.4185814857,41.8710250854],"type":"Point"}
}