{
  "type": "Feature",
  "properties": {
    "addr:full":"Bonatic Cavanilles, S/n Alcacer Valencia 46290",
    "addr:housenumber":"s / n",
    "addr:postcode":"46290",
    "addr:street":"Bonatic Cavanilles",
    "iso:country":"ES",
    "sg:address":"Bonatic Cavanilles, S/n",
    "sg:city":"Alcacer",
    "sg:orig_category":"Centros De Educaci\u00d3n Especial",
    "sg:phone":"+34 961 23 18 58",
    "sg:postcode":"46290",
    "sg:province":"Valencia",
    "wof:name":"Generalitat Valenciana",
    "wof:placetype":"venue"
},
  "geometry": {"coordinates":[-0.4453490078,39.3651695251],"type":"Point"}
}