{
  "type": "Feature",
  "properties": {
    "addr:full":"Calle de Virgen De La Capilla, 9 Jaen Ja\u00e9n 23001",
    "addr:housenumber":"9;jae\u0301n",
    "addr:postcode":"23001",
    "addr:street":"Calle De Virgen De La Capilla",
    "iso:country":"ES",
    "sg:address":"Calle de Virgen De La Capilla, 9",
    "sg:city":"Jaen",
    "sg:orig_category":"Asesor\u00cda Fiscal Y Jur\u00cddica",
    "sg:phone":"+34 953 23 93 41",
    "sg:postcode":"23001",
    "sg:province":"Ja\u00e9n",
    "wof:name":"Domingo Martinez Manuel",
    "wof:placetype":"venue"
},
  "geometry": {"coordinates":[-3.786935091,37.7685623169],"type":"Point"}
}