{
  "type": "Feature",
  "properties": {
    "addr:full":"Calle de Graveras, 8 Miranda Ebro Burgos 09200",
    "addr:housenumber":"8",
    "addr:postcode":"09200",
    "addr:street":"Calle De Graveras",
    "iso:country":"ES",
    "sg:address":"Calle de Graveras, 8",
    "sg:city":"Miranda Ebro",
    "sg:orig_category":"Molduras, Junquillos, Listones Y Molduras Perforadas",
    "sg:phone":"+34 947 31 43 66",
    "sg:postcode":"09200",
    "sg:province":"Burgos",
    "wof:name":"Ramirez Mari\u00f1as Antonio",
    "wof:placetype":"venue"
},
  "geometry": {"coordinates":[-2.9513139725,42.6911392212],"type":"Point"}
}