{
  "type": "Feature",
  "properties": {
    "addr:full":"Calle de Virgen De Gracia, 8 Rinconada Sevilla 41309",
    "addr:housenumber":"8",
    "addr:postcode":"41309",
    "addr:street":"Calle De Virgen De Gracia",
    "iso:country":"ES",
    "sg:address":"Calle de Virgen De Gracia, 8",
    "sg:city":"Rinconada",
    "sg:orig_category":"Parafarmacias",
    "sg:phone":"+34 955 79 82 21",
    "sg:postcode":"41309",
    "sg:province":"Sevilla",
    "wof:name":"Parafarmacia Herboristeria Aires De Salud S.c",
    "wof:placetype":"venue"
},
  "geometry": {"coordinates":[-5.9819111824,37.4880065918],"type":"Point"}
}