{
  "type": "Feature",
  "properties": {
    "addr:full":"Carrer de Nou De La Rambla, 32 Barcelona Barcelona 08001",
    "addr:housenumber":"32",
    "addr:postcode":"08001",
    "addr:street":"Carrer De Nou De La Rambla",
    "iso:country":"ES",
    "sg:address":"Carrer de Nou De La Rambla, 32",
    "sg:city":"Barcelona",
    "sg:orig_category":"Panader\u00cdas, Panader\u00cdas",
    "sg:phone":"+34 933 02 05 34",
    "sg:postcode":"08001",
    "sg:province":"Barcelona",
    "wof:name":"Pujol Sagrera Simeon",
    "wof:placetype":"venue"
},
  "geometry": {"coordinates":[2.1730470657,41.3781585693],"type":"Point"}
}