{
  "type": "Feature",
  "properties": {
    "iso:country":"ES",
    "sg:address":"Avda Virgen Del Encinar, 26",
    "sg:city":"Ceclavin",
    "sg:orig_category":"Asesor\u00cda Fiscal Y Jur\u00cddica",
    "sg:phone":"+34 927 37 45 76",
    "sg:postcode":"10870",
    "sg:province":"C\u00e1ceres",
    "wof:name":"Ceclavin Asesores S.l.",
    "wof:placetype":"venue"
},
  "geometry": {"coordinates":[-6.7751841545,39.8210411072],"type":"Point"}
}