{
  "type": "Feature",
  "properties": {
    "addr:full":"Calle de Manuel Gonzalez, 9 Almoradi Alicante 03160",
    "addr:housenumber":"9",
    "addr:postcode":"03160",
    "addr:street":"Calle De Manuel Gonzalez",
    "iso:country":"ES",
    "sg:address":"Calle de Manuel Gonzalez, 9",
    "sg:city":"Almoradi",
    "sg:orig_category":"Agencias Y Agentes Comerciales, Representantes",
    "sg:phone":"+34 966 78 20 38",
    "sg:postcode":"03160",
    "sg:province":"Alicante",
    "wof:name":"Kirkpatrick  Donald Arthur",
    "wof:placetype":"venue"
},
  "geometry": {"coordinates":[-0.7938150167,38.1107559204],"type":"Point"}
}