{
  "type": "Feature",
  "properties": {
    "addr:full":"Pg Muntanya, S/n S. Just Desvern Barcelona 08960",
    "addr:housenumber":"s",
    "addr:postcode":"08960",
    "addr:street":"Pg Muntanya;/ N",
    "iso:country":"ES",
    "sg:address":"Pg Muntanya, S/n",
    "sg:city":"S. Just Desvern",
    "sg:orig_category":"Locales Deportivos",
    "sg:phone":"+34 933 71 49 78",
    "sg:postcode":"08960",
    "sg:province":"Barcelona",
    "wof:name":"Ige-geafe S.l.",
    "wof:placetype":"venue"
},
  "geometry": {"coordinates":[2.0761640072,41.3891487122],"type":"Point"}
}