{
  "type": "Feature",
  "properties": {
    "addr:full":"Rond Sant Pere, 44 Barcelona Barcelona 08010",
    "addr:housenumber":"44",
    "addr:postcode":"08010",
    "addr:street":"Sant Pere",
    "iso:country":"ES",
    "sg:address":"Rond Sant Pere, 44",
    "sg:city":"Barcelona",
    "sg:orig_category":"Artes Gr\u00c1ficas, Artes Pl\u00c1sticas (curso)",
    "sg:phone":"+34 932 68 30 82",
    "sg:postcode":"08010",
    "sg:province":"Barcelona",
    "wof:name":"Urbez Gomez Jose",
    "wof:placetype":"venue"
},
  "geometry": {"coordinates":[2.1760249138,41.3900260925],"type":"Point"}
}