{
  "type": "Feature",
  "properties": {
    "iso:country":"ES",
    "sg:address":"Calle de Transportes (los), 27",
    "sg:city":"Alacant",
    "sg:orig_category":"Autob\u00das (explotaci\u00d3n Y Servicios De)",
    "sg:phone":"+34 965 10 70 48",
    "sg:postcode":"03008",
    "sg:province":"Alicante",
    "wof:name":"La Albaterense S A",
    "wof:placetype":"venue"
},
  "geometry": {"coordinates":[-0.5175868869,38.3365211487],"type":"Point"}
}