{
  "type": "Feature",
  "properties": {
    "iso:country":"ES",
    "sg:address":"Roser Dolcet, 39",
    "sg:city":"Vilanova Geltru",
    "sg:orig_category":"Electricidad: Equipos Industriales, Componentes (fabricaci\u00d3n)",
    "sg:phone":"+34 938 14 01 59",
    "sg:postcode":"08800",
    "sg:province":"Barcelona",
    "wof:name":"Serveis Industrials De Noia S. A.",
    "wof:placetype":"venue"
},
  "geometry": {"coordinates":[1.7401100397,41.2353668213],"type":"Point"}
}