{
  "type": "Feature",
  "properties": {
    "addr:full":"Ximeno, 9 S. Hilari Sacalm Girona 17403",
    "addr:housenumber":"9",
    "addr:postcode":"17403",
    "addr:street":"Ximeno",
    "iso:country":"ES",
    "sg:address":"Ximeno, 9",
    "sg:city":"S. Hilari Sacalm",
    "sg:orig_category":"Herboristas (al Por Menor)",
    "sg:phone":"+34 972 86 89 42",
    "sg:postcode":"17403",
    "sg:province":"Girona",
    "wof:name":"Torres Rodriguez Juan",
    "wof:placetype":"venue"
},
  "geometry": {"coordinates":[2.5091779232,41.8788261414],"type":"Point"}
}