{
  "type": "Feature",
  "properties": {
    "iso:country":"ES",
    "sg:address":"Avda Constitucion (la), 47",
    "sg:city":"Barruelo Santullan",
    "sg:orig_category":"Panader\u00cdas, Panader\u00cdas",
    "sg:phone":"+34 979 60 62 72",
    "sg:postcode":"34820",
    "sg:province":"Palencia",
    "wof:name":"Alvarez Marcano Juliana",
    "wof:placetype":"venue"
},
  "geometry": {"coordinates":[-4.2885518074,42.9088554382],"type":"Point"}
}