{
  "type": "Feature",
  "properties": {
    "addr:full":"Calle de Campo Madre De Dios, S/n Cordoba C\u00f3rdoba 14002",
    "addr:housenumber":"s / n",
    "addr:postcode":"14002",
    "addr:street":"Calle De Campo Madre;Dios;Co\u0301Rdoba",
    "iso:country":"ES",
    "sg:address":"Calle de Campo Madre De Dios, S/n",
    "sg:city":"Cordoba",
    "sg:orig_category":"Asociaciones, Organismos Culturales Y Socioeducativos",
    "sg:phone":"+34 957 43 86 19",
    "sg:postcode":"14002",
    "sg:province":"C\u00f3rdoba",
    "wof:name":"Consejo Local De La Juventud",
    "wof:placetype":"venue"
},
  "geometry": {"coordinates":[-4.7668209076,37.8843193054],"type":"Point"}
}