{
  "type": "Feature",
  "properties": {
    "iso:country":"ES",
    "sg:address":"Calle de Almirante Bonifaz, 16",
    "sg:city":"Burgos",
    "sg:orig_category":"Ropa Y Accesorios",
    "sg:phone":"+34 947 20 65 20",
    "sg:postcode":"09003",
    "sg:province":"Burgos",
    "wof:name":"Santamaria Pablo Rafael",
    "wof:placetype":"venue"
},
  "geometry": {"coordinates":[-3.7002780437,42.3423805237],"type":"Point"}
}