{
  "type": "Feature",
  "properties": {
    "iso:country":"ES",
    "sg:address":"Calle de Martinez Padin, 39",
    "sg:city":"Tui",
    "sg:orig_category":"Arreglo, Reparaci\u00d3n, Piezas Sueltas De Televisi\u00d3n, V\u00cddeo, Hi",
    "sg:phone":"+34 986 60 09 16",
    "sg:postcode":"36700",
    "sg:province":"Pontevedra",
    "wof:name":"Freiria Cabaleiro Jose Antonio",
    "wof:placetype":"venue"
},
  "geometry": {"coordinates":[-8.6464548111,42.0456733704],"type":"Point"}
}