{
  "type": "Feature",
  "properties": {
    "addr:full":"Plaz Valderas Y Pedraza, 19 Yebenes Toledo 45470",
    "addr:housenumber":"19",
    "addr:postcode":"45470",
    "addr:street":"Valderas Y Pedraza",
    "iso:country":"ES",
    "sg:address":"Plaz Valderas Y Pedraza, 19",
    "sg:city":"Yebenes",
    "sg:orig_category":"Molduras, Junquillos, Listones Y Molduras Perforadas",
    "sg:phone":"+34 925 34 80 05",
    "sg:postcode":"45470",
    "sg:province":"Toledo",
    "wof:name":"Bar Chincheta S.l.",
    "wof:placetype":"venue"
},
  "geometry": {"coordinates":[-3.8697290421,39.5791702271],"type":"Point"}
}