{
  "type": "Feature",
  "properties": {
    "addr:full":"Calle de Cruz De San Sebastian, 2 Alcala Henares Madrid 28803",
    "addr:housenumber":"2",
    "addr:postcode":"28803",
    "addr:street":"Calle De Cruz De San Sebastian",
    "iso:country":"ES",
    "sg:address":"Calle de Cruz De San Sebastian, 2",
    "sg:city":"Alcala Henares",
    "sg:orig_category":"Venta, Instalaci\u00d3n, Reparaci\u00d3n De Antenas Para Televisi\u00d3n",
    "sg:phone":"+34 918 88 01 36",
    "sg:postcode":"28803",
    "sg:province":"Madrid",
    "wof:name":"Guerrero Nieto Enrique",
    "wof:placetype":"venue"
},
  "geometry": {"coordinates":[-3.3698782921,40.4763450623],"type":"Point"}
}