{
  "type": "Feature",
  "properties": {
    "iso:country":"ES",
    "sg:address":"Avda Europa, 25",
    "sg:city":"Madrid",
    "sg:orig_category":"Tapicer\u00cdas",
    "sg:phone":"+34 913 52 73 74",
    "sg:postcode":"28224",
    "sg:province":"Madrid",
    "sg:website":"www.designersguild.com",
    "wof:name":"Garcia Gutierrez Teresa",
    "wof:placetype":"venue"
},
  "geometry": {"coordinates":[-3.7849509716,40.4444847107],"type":"Point"}
}