{
  "type": "Feature",
  "properties": {
    "addr:full":"Calle de Toledo, 4 Getafe Madrid 28901",
    "addr:housenumber":"4",
    "addr:postcode":"28901",
    "addr:street":"Calle De Toledo",
    "iso:country":"ES",
    "sg:address":"Calle de Toledo, 4",
    "sg:city":"Getafe",
    "sg:orig_category":"Bancos",
    "sg:phone":"+34 916 65 37 10",
    "sg:postcode":"28901",
    "sg:province":"Madrid",
    "wof:name":"Banco Guipuzcoano S.a.",
    "wof:placetype":"venue"
},
  "geometry": {"coordinates":[-3.7323870659,40.3048362732],"type":"Point"}
}