{
  "type": "Feature",
  "properties": {
    "iso:country":"ES",
    "sg:address":"Calle de Reyes Catolicos, 25",
    "sg:city":"S. Pedro Pinatar",
    "sg:orig_category":"Quincaller\u00cda (al Por Menor)",
    "sg:phone":"+34 968 18 22 58",
    "sg:postcode":"30740",
    "sg:province":"Murcia",
    "wof:name":"Martinez Lopez Adolfo Jose",
    "wof:placetype":"venue"
},
  "geometry": {"coordinates":[-0.7932540178,37.8340911865],"type":"Point"}
}