{
  "type": "Feature",
  "properties": {
    "iso:country":"ES",
    "sg:address":"Carrer de Bernat Oller, 14",
    "sg:city":"Manresa",
    "sg:orig_category":"Asilos De Ancianos. Centros Privados",
    "sg:phone":"+34 938 72 89 14",
    "sg:postcode":"08242",
    "sg:province":"Barcelona",
    "wof:name":"Fundacio Sociosanitaria De Manresa",
    "wof:placetype":"venue"
},
  "geometry": {"coordinates":[1.8191519976,41.7271652222],"type":"Point"}
}