{
  "type": "Feature",
  "properties": {
    "addr:full":"Carrer de Selva De Mar, 202 Barcelona Barcelona 08020",
    "addr:housenumber":"202",
    "addr:postcode":"08020",
    "addr:street":"Carrer De Selva De Mar",
    "iso:country":"ES",
    "sg:address":"Carrer de Selva De Mar, 202",
    "sg:city":"Barcelona",
    "sg:orig_category":"Inform\u00c1tica: Consultores",
    "sg:phone":"+34 933 13 72 05",
    "sg:postcode":"08020",
    "sg:province":"Barcelona",
    "wof:name":"Ideasoft S.l.",
    "wof:placetype":"venue"
},
  "geometry": {"coordinates":[2.1998200417,41.4163475037],"type":"Point"}
}