{
  "type": "Feature",
  "properties": {
    "addr:full":"Carrer de L'avio Plus Ultra, 6 Barcelona Barcelona 08017",
    "addr:housenumber":"6",
    "addr:postcode":"08017",
    "addr:street":"Carrer De;Ultra",
    "iso:country":"ES",
    "sg:address":"Carrer de L'avio Plus Ultra, 6",
    "sg:city":"Barcelona",
    "sg:orig_category":"Escultores, Estatuarios E Imagineros",
    "sg:phone":"+34 932 05 02 08",
    "sg:postcode":"08017",
    "sg:province":"Barcelona",
    "wof:name":"Blanc Bofill Luis",
    "wof:placetype":"venue"
},
  "geometry": {"coordinates":[2.121799469,41.4005203247],"type":"Point"}
}