{
  "type": "Feature",
  "properties": {
    "addr:full":"Calle de Progreso, S/n Atarfe Granada 18230",
    "addr:postcode":"18230",
    "addr:street":"Calle De Progreso S / N",
    "iso:country":"ES",
    "sg:address":"Calle de Progreso, S/n",
    "sg:city":"Atarfe",
    "sg:orig_category":"Mec\u00c1nico Del Autom\u00d3vil",
    "sg:phone":"+34 958 43 64 75",
    "sg:postcode":"18230",
    "sg:province":"Granada",
    "wof:name":"Torres Romero Juan De Dios",
    "wof:placetype":"venue"
},
  "geometry": {"coordinates":[-3.6833839417,37.2294654846],"type":"Point"}
}