{
  "type": "Feature",
  "properties": {
    "iso:country":"ES",
    "sg:address":"Calle de Juan Alvarez Mendizabal, 13",
    "sg:city":"Madrid",
    "sg:orig_category":"Motocicletas (agentes, Concesionarios)",
    "sg:phone":"+34 915 59 58 45",
    "sg:postcode":"28008",
    "sg:province":"Madrid",
    "sg:website":"www.motosvillar.com",
    "wof:name":"Motos Villar C.b.",
    "wof:placetype":"venue"
},
  "geometry": {"coordinates":[-3.7148149014,40.4245185852],"type":"Point"}
}