{
  "type": "Feature",
  "properties": {
    "iso:country":"ES",
    "sg:address":"Polig. Ind. A Granxa, 2",
    "sg:city":"Porri\u00f1o",
    "sg:orig_category":"Empresas De Carpinter\u00cda",
    "sg:phone":"+34 986 33 77 87",
    "sg:postcode":"36475",
    "sg:province":"Pontevedra",
    "sg:website":"www.aluporta.com",
    "wof:name":"Aluporta S.l.",
    "wof:placetype":"venue"
},
  "geometry": {"coordinates":[-8.6192989349,42.1603622437],"type":"Point"}
}