{
  "type": "Feature",
  "properties": {
    "addr:full":"Pago La Montosa, Km. 0002,5 Canillas De Albaida M\u00e1laga 29755",
    "addr:postcode":"29755",
    "addr:street":"Pago La Montosa Km. 0002,5;Ma\u0301Laga",
    "iso:country":"ES",
    "sg:address":"Pago La Montosa, Km. 0002,5",
    "sg:city":"Canillas De Albaida",
    "sg:orig_category":"Arenas, Guijarros Y Granulados",
    "sg:phone":"+34 952 11 51 42",
    "sg:postcode":"29755",
    "sg:province":"M\u00e1laga",
    "wof:name":"Aridos La Montasa S.l.",
    "wof:placetype":"venue"
},
  "geometry": {"coordinates":[-3.9776389599,36.8555183411],"type":"Point"}
}