{
  "type": "Feature",
  "properties": {
    "iso:country":"ES",
    "sg:address":"Calle de Juan Fuentes Echevarria, Km. 0002,0",
    "sg:city":"Caldas De Reis",
    "sg:orig_category":"Andamiajes Y Escaleras De Mano (fabricaci\u00d3n, Al Por Mayor)",
    "sg:phone":"+34 986 53 90 01",
    "sg:postcode":"36650",
    "sg:province":"Pontevedra",
    "sg:website":"www.layher.es",
    "wof:name":"Layher S.a.",
    "wof:placetype":"venue"
},
  "geometry": {"coordinates":[-8.788476944,42.5159721375],"type":"Point"}
}