{
  "type": "Feature",
  "properties": {
    "addr:full":"Via Laietana, 47 Barcelona Barcelona 08003",
    "addr:housenumber":"47",
    "addr:postcode":"08003",
    "addr:street":"Via Laietana",
    "iso:country":"ES",
    "sg:address":"Via Laietana, 47",
    "sg:city":"Barcelona",
    "sg:orig_category":"Bancos",
    "sg:phone":"+34 933 18 22 20",
    "sg:postcode":"08003",
    "sg:province":"Barcelona",
    "wof:name":"Banc Sabadell S.a.",
    "wof:placetype":"venue"
},
  "geometry": {"coordinates":[2.1747589111,41.3868179321],"type":"Point"}
}