{
  "type": "Feature",
  "properties": {
    "addr:full":"Notaries, 1 Palafrugell Girona 17200",
    "addr:housenumber":"1",
    "addr:postcode":"17200",
    "addr:street":"Notaries",
    "iso:country":"ES",
    "sg:address":"Notaries, 1",
    "sg:city":"Palafrugell",
    "sg:orig_category":"Ropa Para Caballeros (al Por Menor)",
    "sg:phone":"+34 972 30 27 46",
    "sg:postcode":"17200",
    "sg:province":"Girona",
    "wof:name":"Marti Bahi Nuria",
    "wof:placetype":"venue"
},
  "geometry": {"coordinates":[3.1638569832,41.9169158936],"type":"Point"}
}