{
  "type": "Feature",
  "properties": {
    "iso:country":"ES",
    "sg:address":"Villafranca, 1",
    "sg:city":"Iru\u00f1a",
    "sg:orig_category":"Farmacias",
    "sg:phone":"+34 948 12 57 86",
    "sg:postcode":"31015",
    "sg:province":"Navarra",
    "wof:name":"Ezquieta Zubicaray Francisca",
    "wof:placetype":"venue"
},
  "geometry": {"coordinates":[-1.6302759647,42.8323402405],"type":"Point"}
}