{
  "type": "Feature",
  "properties": {
    "iso:country":"ES",
    "sg:address":"C/ Antonio Brotons Pastor, 67",
    "sg:city":"Elche",
    "sg:orig_category":"Chapister\u00cda",
    "sg:phone":"+34 966 67 47 01",
    "sg:postcode":"03205",
    "sg:province":"Alicante",
    "wof:name":"Botella Alonso Andres",
    "wof:placetype":"venue"
},
  "geometry": {"coordinates":[-0.7146509886,38.2686500549],"type":"Point"}
}