{
  "type": "Feature",
  "properties": {
    "addr:full":"El Quesu, 1 Infiesto Asturias 33530",
    "addr:housenumber":"1",
    "addr:postcode":"33530",
    "addr:street":"Quesu",
    "iso:country":"ES",
    "sg:address":"El Quesu, 1",
    "sg:city":"Infiesto",
    "sg:orig_category":"Alimentaci\u00d3n General (al Por Menor)",
    "sg:phone":"+34 985 71 00 57",
    "sg:postcode":"33530",
    "sg:province":"Asturias",
    "wof:name":"Alonso Molina Carlos Omar",
    "wof:placetype":"venue"
},
  "geometry": {"coordinates":[-5.3636240959,43.3482475281],"type":"Point"}
}