{
  "type": "Feature",
  "properties": {
    "iso:country":"ES",
    "sg:address":"Camino De Los Lagares, 71",
    "sg:city":"Sotillo Ribera",
    "sg:orig_category":"Productores Recolectores, Venta Directa De Vinos",
    "sg:phone":"+34 947 53 23 09",
    "sg:postcode":"09441",
    "sg:province":"Burgos",
    "sg:website":"www.valsotillo.com",
    "wof:name":"Bodegas Ismael Arroyo S.l.",
    "wof:placetype":"venue"
},
  "geometry": {"coordinates":[-3.8244268894,41.777141571],"type":"Point"}
}