{
  "type": "Feature",
  "properties": {
    "iso:country":"ES",
    "sg:address":"Calle de Azorin, 32",
    "sg:city":"Aspe",
    "sg:orig_category":"Electricidad, Electr\u00d3nica: Material Y Suministros (al Por Mayor)",
    "sg:phone":"+34 965 49 14 74",
    "sg:postcode":"03680",
    "sg:province":"Alicante",
    "wof:name":"Alquiler De Maquinaria Marco S.l.",
    "wof:placetype":"venue"
},
  "geometry": {"coordinates":[-0.771725595,38.3493385315],"type":"Point"}
}