{
  "type": "Feature",
  "properties": {
    "iso:country":"ES",
    "sg:address":"Carrer de Can Parera (de), 26",
    "sg:city":"Montornes Centre",
    "sg:orig_category":"Delegados, Agentes De Tr\u00c1nsito, Auxiliares De Transporte Internacional",
    "sg:phone":"+34 935 68 38 22",
    "sg:postcode":"08170",
    "sg:province":"Barcelona",
    "wof:name":"Logtravi S.l.",
    "wof:placetype":"venue"
},
  "geometry": {"coordinates":[2.2678649426,41.5453796387],"type":"Point"}
}