{
  "type": "Feature",
  "properties": {
    "addr:full":"Calle de Pato Real, S/n Antilla Huelva 21449",
    "addr:housenumber":"s / n",
    "addr:postcode":"21449",
    "addr:street":"Calle De Pato Real",
    "iso:country":"ES",
    "sg:address":"Calle de Pato Real, S/n",
    "sg:city":"Antilla",
    "sg:orig_category":"Alquiler De Veh\u00cdculos: Turismos Y Utilitarios",
    "sg:phone":"+34 959 48 19 20",
    "sg:postcode":"21449",
    "sg:province":"Huelva",
    "wof:name":"Auto Jardin De Espa\u00d1a Alquiler De Coches S.l.",
    "wof:placetype":"venue"
},
  "geometry": {"coordinates":[-7.219083786,37.2103004456],"type":"Point"}
}