{
  "type": "Feature",
  "properties": {
    "addr:full":"Calle de Angeles (de Los), S/n Arganda Madrid 28500",
    "addr:postcode":"28500",
    "addr:street":"Calle De Angeles De Los S / N",
    "iso:country":"ES",
    "sg:address":"Calle de Angeles (de Los), S/n",
    "sg:city":"Arganda",
    "sg:orig_category":"Fabricaci\u00d3n De Juegos Y Juguetes",
    "sg:phone":"+34 918 71 09 44",
    "sg:postcode":"28500",
    "sg:province":"Madrid",
    "wof:name":"Hernandez Y Viso Maria De Las Nieves",
    "wof:placetype":"venue"
},
  "geometry": {"coordinates":[-3.4422698021,40.3019294739],"type":"Point"}
}