{
  "type": "Feature",
  "properties": {
    "iso:country":"ES",
    "sg:address":"Calle de Redolins, 98",
    "sg:city":"Palmar",
    "sg:orig_category":"Agricultores, Agricultores",
    "sg:phone":"+34 961 62 00 97",
    "sg:postcode":"46012",
    "sg:province":"Valencia",
    "wof:name":"Restaurante Raco De Les Eres S.l.",
    "wof:placetype":"venue"
},
  "geometry": {"coordinates":[-0.3184239864,39.3068618774],"type":"Point"}
}