{
  "type": "Feature",
  "properties": {
    "iso:country":"ES",
    "sg:address":"Calle de Jose Zorrilla, 48",
    "sg:city":"Segovia",
    "sg:orig_category":"Colchones (fabricaci\u00d3n, Al Por Mayor, Al Por Menor)",
    "sg:phone":"+34 921 42 57 13",
    "sg:postcode":"40002",
    "sg:province":"Segovia",
    "wof:name":"Barrio De La Esperanza Pablo Del",
    "wof:placetype":"venue"
},
  "geometry": {"coordinates":[-4.1155362129,40.940864563],"type":"Point"}
}