{
  "type": "Feature",
  "properties": {
    "addr:full":"El Pilar, 25 Calamonte Badajoz 06810",
    "addr:housenumber":"25",
    "addr:postcode":"06810",
    "addr:street":"El Pilar",
    "iso:country":"ES",
    "sg:address":"El Pilar, 25",
    "sg:city":"Calamonte",
    "sg:orig_category":"Empresas De Desmonte",
    "sg:phone":"+34 924 32 40 18",
    "sg:postcode":"06810",
    "sg:province":"Badajoz",
    "wof:name":"Excavaciones Hermanos Moregon S.l.",
    "wof:placetype":"venue"
},
  "geometry": {"coordinates":[-6.3850698471,38.8900108337],"type":"Point"}
}