{
  "type": "Feature",
  "properties": {
    "addr:full":"Ctra Pe\u00d1acerrada, 7 S. Vicente Sonsierra La Rioja 26338",
    "addr:housenumber":"7",
    "addr:postcode":"26338",
    "addr:street":"Ctra Pen\u0303Acerrada;S. Vicente Sonsierra;Rioja",
    "iso:country":"ES",
    "sg:address":"Ctra Pe\u00d1acerrada, 7",
    "sg:city":"S. Vicente Sonsierra",
    "sg:orig_category":"Comerciantes Al Por Mayor De Vinos, Licores Y Alcoholes",
    "sg:phone":"+34 941 30 80 10",
    "sg:postcode":"26338",
    "sg:province":"La Rioja",
    "wof:name":"Bodegas Abel Mendoza Monge S.l.",
    "wof:placetype":"venue"
},
  "geometry": {"coordinates":[-2.7588191032,42.5630836487],"type":"Point"}
}