{
  "type": "Feature",
  "properties": {
    "addr:full":"Calle de Vicente Blasco Iba\u00d1ez, 8 Sestao Vizcaya 48910",
    "addr:housenumber":"8",
    "addr:postcode":"48910",
    "addr:street":"Calle De Vicente Blasco Iban\u0303Ez",
    "iso:country":"ES",
    "sg:address":"Calle de Vicente Blasco Iba\u00d1ez, 8",
    "sg:city":"Sestao",
    "sg:orig_category":"Bricolaje, Herramientas (al Por Menor)",
    "sg:phone":"+34 944 96 20 63",
    "sg:postcode":"48910",
    "sg:province":"Vizcaya",
    "wof:name":"(jaio)  Almudena  Lorente",
    "wof:placetype":"venue"
},
  "geometry": {"coordinates":[-3.004349947,43.3076133728],"type":"Point"}
}