{
  "type": "Feature",
  "properties": {
    "addr:full":"Elizalde Kalea, 16 Iturmendi Navarra 31810",
    "addr:housenumber":"16",
    "addr:postcode":"31810",
    "addr:street":"Elizalde Kalea",
    "iso:country":"ES",
    "sg:address":"Elizalde Kalea, 16",
    "sg:city":"Iturmendi",
    "sg:orig_category":"Iglesia Cat\u00d3lica",
    "sg:phone":"+34 948 56 73 22",
    "sg:postcode":"31810",
    "sg:province":"Navarra",
    "wof:name":"Parroquia Iturmendi",
    "wof:placetype":"venue"
},
  "geometry": {"coordinates":[-2.117814064,42.8891372681],"type":"Point"}
}