{
  "type": "Feature",
  "properties": {
    "addr:full":"Cra Piera, 18 Martorell Barcelona 08760",
    "addr:housenumber":"18",
    "addr:postcode":"08760",
    "addr:street":"Piera",
    "iso:country":"ES",
    "sg:address":"Cra Piera, 18",
    "sg:city":"Martorell",
    "sg:orig_category":"Bancos",
    "sg:phone":"+34 937 75 44 70",
    "sg:postcode":"08760",
    "sg:province":"Barcelona",
    "sg:website":"www.bancopopular.es",
    "wof:name":"Banco Popular Espa\u00f1ol S.a.",
    "wof:placetype":"venue"
},
  "geometry": {"coordinates":[1.9207810163,41.4781188965],"type":"Point"}
}