{
  "type": "Feature",
  "properties": {
    "addr:full":"Pla\u00c7 Doctor Rovira Benet, 21 Breda Girona 17400",
    "addr:housenumber":"21",
    "addr:postcode":"17400",
    "addr:street":"Doctor;Benet",
    "iso:country":"ES",
    "sg:address":"Pla\u00c7 Doctor Rovira Benet, 21",
    "sg:city":"Breda",
    "sg:orig_category":"Electrodom\u00c9sticos (al Por Menor)",
    "sg:phone":"+34 972 16 03 02",
    "sg:postcode":"17400",
    "sg:province":"Girona",
    "wof:name":"Electro Breda S.l.",
    "wof:placetype":"venue"
},
  "geometry": {"coordinates":[2.5570750237,41.7470932007],"type":"Point"}
}