{
  "type": "Feature",
  "properties": {
    "addr:full":"Av Collada, 24 Vilanova I La Geltru Barcelona 08800",
    "addr:housenumber":"24",
    "addr:postcode":"08800",
    "addr:street":"Av Collada",
    "iso:country":"ES",
    "sg:address":"Av Collada, 24",
    "sg:city":"Vilanova I La Geltru",
    "sg:orig_category":"Empresas De Labores Complejas De Carga Y Descarga, Montaje Con Elevadores",
    "sg:phone":"+34 938 93 38 18",
    "sg:postcode":"08800",
    "sg:province":"Barcelona",
    "sg:website":"www.solena.net",
    "wof:name":"Martinez Elias Francisco",
    "wof:placetype":"venue"
},
  "geometry": {"coordinates":[1.7056180239,41.2234382629],"type":"Point"}
}