{
  "type": "Feature",
  "properties": {
    "iso:country":"ES",
    "sg:address":"Calle de Mimbre, 1",
    "sg:city":"Coria Rio",
    "sg:orig_category":"Chapister\u00cda",
    "sg:phone":"+34 954 77 54 73",
    "sg:postcode":"41100",
    "sg:province":"Sevilla",
    "wof:name":"Gutierrez Romero Jose Manuel",
    "wof:placetype":"venue"
},
  "geometry": {"coordinates":[-6.0556440353,37.2949905396],"type":"Point"}
}