{
  "type": "Feature",
  "properties": {
    "iso:country":"ES",
    "sg:address":"Carrer de Manso, 29",
    "sg:city":"Barcelona",
    "sg:orig_category":"Centros Empresariales",
    "sg:phone":"+34 934 23 36 74",
    "sg:postcode":"08015",
    "sg:province":"Barcelona",
    "wof:name":"Ciuro Bellver Javier",
    "wof:placetype":"venue"
},
  "geometry": {"coordinates":[2.1603438854,41.3766899109],"type":"Point"}
}