{
  "type": "Feature",
  "properties": {
    "iso:country":"ES",
    "sg:address":"Calle de Laguna, 111",
    "sg:city":"Madrid",
    "sg:orig_category":"Abogados",
    "sg:phone":"+34 915 25 15 76",
    "sg:postcode":"28025",
    "sg:province":"Madrid",
    "wof:name":"Alvarez Castro Isidoro",
    "wof:placetype":"venue"
},
  "geometry": {"coordinates":[-3.7420101166,40.3890914917],"type":"Point"}
}