{
  "type": "Feature",
  "properties": {
    "iso:country":"ES",
    "sg:address":"Carrer de Marina, 85",
    "sg:city":"Barcelona",
    "sg:orig_category":"Agencias Y Agentes Comerciales, Representantes",
    "sg:phone":"+34 934 85 28 15",
    "sg:postcode":"08018",
    "sg:province":"Barcelona",
    "wof:name":"Ferran I Ferran Associats S.l.",
    "wof:placetype":"venue"
},
  "geometry": {"coordinates":[2.1885080338,41.3933906555],"type":"Point"}
}