{
  "type": "Feature",
  "properties": {
    "iso:country":"ES",
    "sg:address":"Ctra Barcelona, 99",
    "sg:city":"Cerdanyola Valles",
    "sg:orig_category":"Sociedades, Compa\u00d1\u00cdas Aseguradoras",
    "sg:phone":"+34 936 91 88 07",
    "sg:postcode":"08290",
    "sg:province":"Barcelona",
    "wof:name":"Alerany Capdevila Jaume",
    "wof:placetype":"venue"
},
  "geometry": {"coordinates":[2.1479654312,41.493396759],"type":"Point"}
}