{
  "type": "Feature",
  "properties": {
    "iso:country":"ES",
    "sg:address":"Calle de Olimpico Francisco Fernandez Ochoa, S/n",
    "sg:city":"Alcorcon",
    "sg:orig_category":"Farmacias",
    "sg:phone":"+34 916 41 07 68",
    "sg:postcode":"28923",
    "sg:province":"Madrid",
    "wof:name":"Hernandez Rivas C.b.",
    "wof:placetype":"venue"
},
  "geometry": {"coordinates":[-3.8128941059,40.3445053101],"type":"Point"}
}