{
  "type": "Feature",
  "properties": {
    "addr:full":"Calle de Alvarez Pelayo, 19 Granada Granada 18014",
    "addr:housenumber":"19",
    "addr:postcode":"18014",
    "addr:street":"Calle De Alvarez Pelayo",
    "iso:country":"ES",
    "sg:address":"Calle de Alvarez Pelayo, 19",
    "sg:city":"Granada",
    "sg:orig_category":"Ambulancias",
    "sg:phone":"+34 958 15 00 04",
    "sg:postcode":"18014",
    "sg:province":"Granada",
    "wof:name":"Sociedad Cooperativa Andaluza De Trabajo Asociado De Ambulancias Sierra Nevada",
    "wof:placetype":"venue"
},
  "geometry": {"coordinates":[-3.6096389294,37.1937217712],"type":"Point"}
}