{
  "type": "Feature",
  "properties": {
    "addr:full":"Trva Navaluenga, 44 Majadahonda Madrid 28220",
    "addr:housenumber":"44",
    "addr:postcode":"28220",
    "addr:street":"Trva Navaluenga",
    "iso:country":"ES",
    "sg:address":"Trva Navaluenga, 44",
    "sg:city":"Majadahonda",
    "sg:orig_category":"Ropa De Hogar (al Por Menor)",
    "sg:phone":"+34 916 38 05 68",
    "sg:postcode":"28220",
    "sg:province":"Madrid",
    "sg:website":"www.entrealgodones.com",
    "wof:name":"Acer Saccarum S.l.",
    "wof:placetype":"venue"
},
  "geometry": {"coordinates":[-3.8526260853,40.4786720276],"type":"Point"}
}