{
  "type": "Feature",
  "properties": {
    "addr:full":"Calle de Camelia, 6 Palmas De Gran Canaria Las Palmas 35010",
    "addr:housenumber":"6",
    "addr:postcode":"35010",
    "addr:street":"Calle De Camelia",
    "iso:country":"ES",
    "sg:address":"Calle de Camelia, 6",
    "sg:city":"Palmas De Gran Canaria",
    "sg:orig_category":"Empresas De Carpinter\u00cda Met\u00c1lica",
    "sg:phone":"+34 928 22 38 26",
    "sg:postcode":"35010",
    "sg:province":"Las Palmas",
    "wof:name":"Rodriguez Rodriguez Jose Luis",
    "wof:placetype":"venue"
},
  "geometry": {"coordinates":[-15.3850221634,28.0117912292],"type":"Point"}
}