{
  "type": "Feature",
  "properties": {
    "addr:full":"Rua Bailen, 13 Vigo Pontevedra 36206",
    "addr:housenumber":"13",
    "addr:postcode":"36206",
    "addr:street":"Rua Bailen",
    "iso:country":"ES",
    "sg:address":"Rua Bailen, 13",
    "sg:city":"Vigo",
    "sg:orig_category":"Fabricaci\u00d3n De Productos L\u00c1cteos Y Derivados",
    "sg:phone":"+34 986 27 91 37",
    "sg:postcode":"36206",
    "sg:province":"Pontevedra",
    "wof:name":"Leite Rio S.l.",
    "wof:placetype":"venue"
},
  "geometry": {"coordinates":[-8.700135231,42.2420082092],"type":"Point"}
}