{
  "type": "Feature",
  "properties": {
    "iso:country":"ES",
    "sg:address":"Avda Juan Carlos I, S/n",
    "sg:city":"Ibi",
    "sg:classifiers":[
        {
            "category":"Taxi",
            "type":"Transportation"
        }
    ],
    "sg:phone":"+34 965 55 42 19",
    "sg:postcode":"03440",
    "sg:province":"Alicante",
    "wof:name":"Ayuntamiento De Ibi",
    "wof:placetype":"venue"
},
  "geometry": {"coordinates":[-0.5800690055,38.6207618713],"type":"Point"}
}