{
  "type": "Feature",
  "properties": {
    "addr:full":"Carrer de Albacete, 4 Barcelona Barcelona 08012",
    "addr:housenumber":"4",
    "addr:postcode":"08012",
    "addr:street":"Carrer De Albacete",
    "iso:country":"ES",
    "sg:address":"Carrer de Albacete, 4",
    "sg:city":"Barcelona",
    "sg:orig_category":"Escultores, Estatuarios E Imagineros",
    "sg:phone":"+34 932 37 65 82",
    "sg:postcode":"08012",
    "sg:province":"Barcelona",
    "wof:name":"Nogues Escoda Jose Maria",
    "wof:placetype":"venue"
},
  "geometry": {"coordinates":[2.1516098976,41.4077568054],"type":"Point"}
}