{
  "type": "Feature",
  "properties": {
    "addr:full":"Calle de Padre Santaella, 19 Almeria Almer\u00eda 04004",
    "addr:housenumber":"19",
    "addr:postcode":"04004",
    "addr:street":"Calle De Padre Santaella",
    "iso:country":"ES",
    "sg:address":"Calle de Padre Santaella, 19",
    "sg:city":"Almeria",
    "sg:orig_category":"M\u00c9dicos: An\u00c1lisis Cl\u00cdnicos",
    "sg:phone":"+34 950 23 04 96",
    "sg:postcode":"04004",
    "sg:province":"Almer\u00eda",
    "wof:name":"Rodriguez Ruiz Manuel",
    "wof:placetype":"venue"
},
  "geometry": {"coordinates":[-2.4615290165,36.8381614685],"type":"Point"}
}