{
  "type": "Feature",
  "properties": {
    "addr:full":"Calle de Luna, 11 Corral Almaguer Toledo 45880",
    "addr:housenumber":"11",
    "addr:postcode":"45880",
    "addr:street":"Calle De Luna",
    "iso:country":"ES",
    "sg:address":"Calle de Luna, 11",
    "sg:city":"Corral Almaguer",
    "sg:orig_category":"M\u00c1quinas De Coser Y De Hacer Punto (al Por Mayor)",
    "sg:phone":"+34 925 19 06 90",
    "sg:postcode":"45880",
    "sg:province":"Toledo",
    "wof:name":"Pernia Carre\u00f1o Fernando",
    "wof:placetype":"venue"
},
  "geometry": {"coordinates":[-3.1690282822,39.7614822388],"type":"Point"}
}