{
  "type": "Feature",
  "properties": {
    "addr:full":"Calle de Pedro De Cepeda, 4 Plasencia C\u00e1ceres 10600",
    "addr:housenumber":"4",
    "addr:postcode":"10600",
    "addr:street":"Calle De Pedro De Cepeda;Ca\u0301Ceres",
    "iso:country":"ES",
    "sg:address":"Calle de Pedro De Cepeda, 4",
    "sg:city":"Plasencia",
    "sg:orig_category":"Carnicer\u00cdas, Carnicer\u00cdas",
    "sg:phone":"+34 927 41 67 79",
    "sg:postcode":"10600",
    "sg:province":"C\u00e1ceres",
    "wof:name":"Galvez Izquierdo Jose Luis",
    "wof:placetype":"venue"
},
  "geometry": {"coordinates":[-6.0820689201,40.0358200073],"type":"Point"}
}