{
  "type": "Feature",
  "properties": {
    "iso:country":"ES",
    "sg:address":"Pase Santo Cristo, 8",
    "sg:city":"Villacarrillo",
    "sg:orig_category":"Sindicatos De Trabajadores",
    "sg:phone":"+34 953 44 06 76",
    "sg:postcode":"23300",
    "sg:province":"Ja\u00e9n",
    "wof:name":"Union General De Trabajadores",
    "wof:placetype":"venue"
},
  "geometry": {"coordinates":[-3.0809049606,38.1163444519],"type":"Point"}
}