{
  "type": "Feature",
  "properties": {
    "iso:country":"ES",
    "sg:address":"Calle de Juan Molina, 30",
    "sg:city":"Xirivella",
    "sg:orig_category":"Centros De Coordinaci\u00d3n",
    "sg:phone":"+34 963 79 21 71",
    "sg:postcode":"46950",
    "sg:province":"Valencia",
    "wof:name":"Terrasa Mu\u00f1oz Maria Dolores",
    "wof:placetype":"venue"
},
  "geometry": {"coordinates":[-0.4253109992,39.4668388367],"type":"Point"}
}