{
  "type": "Feature",
  "properties": {
    "iso:country":"ES",
    "sg:address":"Pg Gracia, 59",
    "sg:city":"Barcelona",
    "sg:orig_category":"Promotores Constructores",
    "sg:phone":"+34 934 87 61 60",
    "sg:postcode":"08007",
    "sg:province":"Barcelona",
    "wof:name":"Aldesa Construcciones S.a.",
    "wof:placetype":"venue"
},
  "geometry": {"coordinates":[2.1637425423,41.3928947449],"type":"Point"}
}