{
  "type": "Feature",
  "properties": {
    "iso:country":"ES",
    "sg:address":"Calle de Ronda (de La), 14",
    "sg:city":"Soria",
    "sg:orig_category":"Promotores Constructores",
    "sg:phone":"+34 975 23 04 96",
    "sg:postcode":"42005",
    "sg:province":"Soria",
    "wof:name":"Rebollar Rubio Rafael",
    "wof:placetype":"venue"
},
  "geometry": {"coordinates":[-2.4677920341,41.7572784424],"type":"Point"}
}