{
  "type": "Feature",
  "properties": {
    "addr:full":"Av Pau, 43 S. Celoni Barcelona 08470",
    "addr:housenumber":"43",
    "addr:postcode":"08470",
    "addr:street":"Av Pau;S. Celoni Barcelona",
    "iso:country":"ES",
    "sg:address":"Av Pau, 43",
    "sg:city":"S. Celoni",
    "sg:orig_category":"Cajas De Ahorro",
    "sg:phone":"+34 938 67 14 61",
    "sg:postcode":"08470",
    "sg:province":"Barcelona",
    "wof:name":"Caixa De Manlleu",
    "wof:placetype":"venue"
},
  "geometry": {"coordinates":[2.4842779636,41.6851539612],"type":"Point"}
}