{
  "type": "Feature",
  "properties": {
    "addr:full":"Ctra Alicante-valencia, Km. 0087,0 S. Juan Alicante Alicante 03550",
    "addr:postcode":"03550",
    "addr:street":"Ctra Alicante-Valencia Km. 0087,0 S. Juan",
    "iso:country":"ES",
    "sg:address":"Ctra Alicante-valencia, Km. 0087,0",
    "sg:city":"S. Juan Alicante",
    "sg:orig_category":"Deportes Y Ocio: Art\u00cdculos Y Ropas (al Por Menor Y Accesorios)",
    "sg:phone":"+34 965 65 61 61",
    "sg:postcode":"03550",
    "sg:province":"Alicante",
    "wof:name":"Nike Retail Sucursal En Espa\u00f1a",
    "wof:placetype":"venue"
},
  "geometry": {"coordinates":[-0.4289290011,38.400390625],"type":"Point"}
}