{
  "type": "Feature",
  "properties": {
    "iso:country":"ES",
    "sg:address":"Rua Maceiras, 2",
    "sg:city":"Franzomel",
    "sg:orig_category":"Zonas De Acampada, Aparcamiento Para Caravanas",
    "sg:phone":"+34 981 61 48 25",
    "sg:postcode":"15179",
    "sg:province":"La Coru\u00f1a",
    "wof:name":"Camping Los Manzanos Cb",
    "wof:placetype":"venue"
},
  "geometry": {"coordinates":[-8.3459596634,43.3464698792],"type":"Point"}
}