{
  "type": "Feature",
  "properties": {
    "iso:country":"ES",
    "sg:address":"Ctra General, 48",
    "sg:city":"Victoria Acentejo",
    "sg:orig_category":"Animales (al Por Menor)",
    "sg:phone":"+34 922 58 23 52",
    "sg:postcode":"38380",
    "sg:province":"Santa Cruz De Tenerife",
    "wof:name":"Alonso Perez Eugenio Luis",
    "wof:placetype":"venue"
},
  "geometry": {"coordinates":[-16.4665679932,28.4361133575],"type":"Point"}
}