{
  "type": "Feature",
  "properties": {
    "addr:full":"Hoyo Once, 10 Altorreal Murcia 30500",
    "addr:housenumber":"10",
    "addr:postcode":"30500",
    "addr:street":"Once",
    "iso:country":"ES",
    "sg:address":"Hoyo Once, 10",
    "sg:city":"Altorreal",
    "sg:orig_category":"Arquitectos",
    "sg:phone":"+34 968 64 87 51",
    "sg:postcode":"30500",
    "sg:province":"Murcia",
    "wof:name":"Leon Albert Jose Rafael",
    "wof:placetype":"venue"
},
  "geometry": {"coordinates":[-1.1636610031,38.0715675354],"type":"Point"}
}