{
  "type": "Feature",
  "properties": {
    "iso:country":"ES",
    "sg:address":"Calle de Arce (del), 6",
    "sg:city":"Alcobendas",
    "sg:orig_category":"Farmacias",
    "sg:phone":"+34 916 52 93 29",
    "sg:postcode":"28100",
    "sg:province":"Madrid",
    "wof:name":"Garcia Revilla Mariano",
    "wof:placetype":"venue"
},
  "geometry": {"coordinates":[-3.6414062977,40.545955658],"type":"Point"}
}