{
  "type": "Feature",
  "properties": {
    "addr:full":"Calle de Nicolas Usera, 101 Madrid Madrid 28026",
    "addr:housenumber":"101",
    "addr:postcode":"28026",
    "addr:street":"Calle De Nicolas Usera",
    "iso:country":"ES",
    "sg:address":"Calle de Nicolas Usera, 101",
    "sg:city":"Madrid",
    "sg:orig_category":"M\u00c9dicos: Estomatolog\u00cda",
    "sg:phone":"+34 915 00 36 99",
    "sg:postcode":"28026",
    "sg:province":"Madrid",
    "wof:name":"Manzanera Mu\u00f1oz Carlos",
    "wof:placetype":"venue"
},
  "geometry": {"coordinates":[-3.7049794197,40.3815994263],"type":"Point"}
}