{
  "type": "Feature",
  "properties": {
    "addr:full":"Carr Garraf, S/n Casc Urba Girona 17490",
    "addr:housenumber":"s / n",
    "addr:postcode":"17490",
    "addr:street":"Carr Garraf",
    "iso:country":"ES",
    "sg:address":"Carr Garraf, S/n",
    "sg:city":"Casc Urba",
    "sg:orig_category":"Inform\u00c1tica (estudios, Servicios, Asesor\u00cda, Formaci\u00d3n)",
    "sg:phone":"+34 972 12 05 13",
    "sg:postcode":"17490",
    "sg:province":"Girona",
    "wof:name":"A.p.a.catalunya S.l.",
    "wof:placetype":"venue"
},
  "geometry": {"coordinates":[2.8236999512,41.9817962646],"type":"Point"}
}