{
  "type": "Feature",
  "properties": {
    "addr:full":"Calle de Felix De La Torre, 6 Balmaseda Vizcaya 48800",
    "addr:housenumber":"6",
    "addr:postcode":"48800",
    "addr:street":"Calle De Felix De La Torre",
    "iso:country":"ES",
    "sg:address":"Calle de Felix De La Torre, 6",
    "sg:city":"Balmaseda",
    "sg:orig_category":"Zapatos (al Por Menor)",
    "sg:phone":"+34 946 10 30 28",
    "sg:postcode":"48800",
    "sg:province":"Vizcaya",
    "wof:name":"Cirion Pereda Maria Angeles",
    "wof:placetype":"venue"
},
  "geometry": {"coordinates":[-3.1967539787,43.1935348511],"type":"Point"}
}