{
  "type": "Feature",
  "properties": {
    "addr:full":"Carrer de Torrelles De Foix, 6 Vilafranca Penedes Barcelona 08720",
    "addr:housenumber":"6",
    "addr:postcode":"08720",
    "addr:street":"Carrer De Torrelles De Foix;Penedes Barcelona",
    "iso:country":"ES",
    "sg:address":"Carrer de Torrelles De Foix, 6",
    "sg:city":"Vilafranca Penedes",
    "sg:orig_category":"Empresarios",
    "sg:phone":"+34 938 17 02 50",
    "sg:postcode":"08720",
    "sg:province":"Barcelona",
    "wof:name":"Espai Penedes S.l.",
    "wof:placetype":"venue"
},
  "geometry": {"coordinates":[1.6967849731,41.350025177],"type":"Point"}
}