{
  "type": "Feature",
  "properties": {
    "addr:full":"Plaz Iglesia, 14 Ibarsos Castell\u00f3n 12193",
    "addr:housenumber":"14",
    "addr:postcode":"12193",
    "addr:street":"Iglesia;Castello\u0301N",
    "iso:country":"ES",
    "sg:address":"Plaz Iglesia, 14",
    "sg:city":"Ibarsos",
    "sg:orig_category":"Ropa Para Se\u00d1oras Y Caballeros (al Por Menor)",
    "sg:phone":"+34 964 70 85 15",
    "sg:postcode":"12193",
    "sg:province":"Castell\u00f3n",
    "wof:name":"Hermanos Chiva Celades Cdad.",
    "wof:placetype":"venue"
},
  "geometry": {"coordinates":[-0.0622310005,40.1653175354],"type":"Point"}
}