{
  "type": "Feature",
  "properties": {
    "addr:full":"Calle de Hernan Perez Del Pulgar, 4 Ciudad Real Ciudad Real 13001",
    "addr:housenumber":"4",
    "addr:postcode":"13001",
    "addr:street":"Calle De Hernan Perez Del Pulgar",
    "iso:country":"ES",
    "sg:address":"Calle de Hernan Perez Del Pulgar, 4",
    "sg:city":"Ciudad Real",
    "sg:orig_category":"Promotores Constructores",
    "sg:phone":"+34 926 22 87 85",
    "sg:postcode":"13001",
    "sg:province":"Ciudad Real",
    "sg:website":"www.trabit.com",
    "wof:name":"Trabajos Bituminosos S. A.",
    "wof:placetype":"venue"
},
  "geometry": {"coordinates":[-3.9272220135,38.9833602905],"type":"Point"}
}