{
  "type": "Feature",
  "properties": {
    "iso:country":"ES",
    "sg:address":"Barr Gatzamina, S/n",
    "sg:city":"Txipio",
    "sg:orig_category":"Ense\u00d1anza Secundaria: Colegios Y Escuelas Privadas",
    "sg:phone":"+34 946 77 00 82",
    "sg:postcode":"48620",
    "sg:province":"Vizcaya",
    "wof:name":"Instituto De Educacion Secundaria Uribe-kosta",
    "wof:placetype":"venue"
},
  "geometry": {"coordinates":[-2.9458739758,43.4066467285],"type":"Point"}
}