{
  "type": "Feature",
  "properties": {
    "iso:country":"ES",
    "sg:address":"C/ Riu Sec, S/n",
    "sg:city":"Cerdanyola Valles",
    "sg:orig_category":"Fabricaci\u00d3n De Moldes Y Modelos",
    "sg:phone":"+34 935 86 41 14",
    "sg:postcode":"08290",
    "sg:province":"Barcelona",
    "wof:name":"Plastisc Diaz S.l.",
    "wof:placetype":"venue"
},
  "geometry": {"coordinates":[2.1409909725,41.4970054626],"type":"Point"}
}