{
  "type": "Feature",
  "properties": {
    "addr:full":"Av Can Roqueta, 2 Torre-romeu Barcelona 08202",
    "addr:housenumber":"2",
    "addr:postcode":"08202",
    "addr:street":"Av Can Roqueta;Barcelona",
    "iso:country":"ES",
    "sg:address":"Av Can Roqueta, 2",
    "sg:city":"Torre-romeu",
    "sg:orig_category":"Tratamiento De Metales",
    "sg:phone":"+34 937 27 56 56",
    "sg:postcode":"08202",
    "sg:province":"Barcelona",
    "wof:name":"J. Clape S.a.",
    "wof:placetype":"venue"
},
  "geometry": {"coordinates":[2.1286709309,41.5617256165],"type":"Point"}
}