{
  "type": "Feature",
  "properties": {
    "addr:full":"Pol. Ind. El Brizo, 68 Aldeamayor S. Martin Valladolid 47162",
    "addr:housenumber":"68",
    "addr:postcode":"47162",
    "addr:street":"Brizo;Aldeamayor S. Martin",
    "iso:country":"ES",
    "sg:address":"Pol. Ind. El Brizo, 68",
    "sg:city":"Aldeamayor S. Martin",
    "sg:orig_category":"Promotores Constructores",
    "sg:phone":"+34 983 52 80 32",
    "sg:postcode":"47162",
    "sg:province":"Valladolid",
    "wof:name":"Beco Soluciones De Aire Comprimido S.l.",
    "wof:placetype":"venue"
},
  "geometry": {"coordinates":[-4.6361689568,41.515625],"type":"Point"}
}