{
  "type": "Feature",
  "properties": {
    "iso:country":"ES",
    "sg:address":"Carr Carles Iii, 10",
    "sg:city":"Eivissa",
    "sg:orig_category":"M\u00c9dicos: Psiquiatr\u00cda",
    "sg:phone":"+34 971 31 26 86",
    "sg:postcode":"07800",
    "sg:province":"Islas Baleares",
    "wof:name":"Santacruz Fernandez Sara",
    "wof:placetype":"venue"
},
  "geometry": {"coordinates":[1.4335019588,38.9117965698],"type":"Point"}
}