{
  "type": "Feature",
  "properties": {
    "addr:full":"Avda Espa\u00d1a, 114 Segorbe Castell\u00f3n 12400",
    "addr:housenumber":"114",
    "addr:postcode":"12400",
    "addr:street":"Avda Espan\u0303A",
    "iso:country":"ES",
    "sg:address":"Avda Espa\u00d1a, 114",
    "sg:city":"Segorbe",
    "sg:orig_category":"Muebles, Minoristas",
    "sg:phone":"+34 964 71 25 12",
    "sg:postcode":"12400",
    "sg:province":"Castell\u00f3n",
    "sg:website":"www.abetos.com",
    "wof:name":"Muebles Bolumar S.l.",
    "wof:placetype":"venue"
},
  "geometry": {"coordinates":[-0.4912689924,39.847530365],"type":"Point"}
}