{
  "type": "Feature",
  "properties": {
    "addr:full":"Avda Ebro (del), S/n Calahorra La Rioja 26500",
    "addr:housenumber":"/ n",
    "addr:postcode":"26500",
    "addr:street":"Avda Ebro Del S",
    "iso:country":"ES",
    "sg:address":"Avda Ebro (del), S/n",
    "sg:city":"Calahorra",
    "sg:orig_category":"Florister\u00cdas",
    "sg:phone":"+34 941 14 71 92",
    "sg:postcode":"26500",
    "sg:province":"La Rioja",
    "wof:name":"Ferrer Lopez Jesus",
    "wof:placetype":"venue"
},
  "geometry": {"coordinates":[-1.9558589458,42.3100662231],"type":"Point"}
}