{
  "type": "Feature",
  "properties": {
    "addr:full":"Calle de San Sebastian, S/n Sanlucar De Barrameda C\u00e1diz 11540",
    "addr:housenumber":"/ n",
    "addr:postcode":"11540",
    "addr:street":"Calle De San;S;Ca\u0301Diz",
    "iso:country":"ES",
    "sg:address":"Calle de San Sebastian, S/n",
    "sg:city":"Sanlucar De Barrameda",
    "sg:orig_category":"Molduras, Junquillos, Listones Y Molduras Perforadas",
    "sg:phone":"+34 956 36 11 19",
    "sg:postcode":"11540",
    "sg:province":"C\u00e1diz",
    "wof:name":"Mu\u00f1oz Ferrer Manuel",
    "wof:placetype":"venue"
},
  "geometry": {"coordinates":[-6.3474640846,36.7693595886],"type":"Point"}
}