{
  "type": "Feature",
  "properties": {
    "iso:country":"ES",
    "sg:address":"Ra\u00f1obre(oseiro), 60",
    "sg:city":"Ra\u00d1obre",
    "sg:orig_category":"Frutas Y Legumbres Frescas (al Por Mayor)",
    "sg:phone":"+34 981 60 05 85",
    "sg:postcode":"15141",
    "sg:province":"A Coru\u00f1a",
    "wof:name":"Verduras Chelin S.c.",
    "wof:placetype":"venue"
},
  "geometry": {"coordinates":[-8.4798288345,43.3172454834],"type":"Point"}
}