{
  "type": "Feature",
  "properties": {
    "iso:country":"ES",
    "sg:address":"Pago Los Kikos(venta Baja), S/n",
    "sg:city":"Puente Salia",
    "sg:classifiers":[
        {
            "category":"Professional",
            "subcategory":"Management & Consulting",
            "type":"Services"
        }
    ],
    "sg:phone":"+34 952 03 06 32",
    "sg:postcode":"29713",
    "sg:province":"M\u00e1laga",
    "sg:tags":[
        "asesor\u00cda",
        "en",
        "marketing"
    ],
    "wof:name":"Aliaga Cuesta Milagros",
    "wof:placetype":"venue"
},
  "geometry": {"coordinates":[-4.4200186729,36.7196464539],"type":"Point"}
}