{
  "type": "Feature",
  "properties": {
    "iso:country":"ES",
    "sg:address":"Calle de Almu\u00d1ecar, S/n",
    "sg:city":"Torrequebrada",
    "sg:orig_category":"Institutos De Belleza",
    "sg:phone":"+34 952 57 14 14",
    "sg:postcode":"29630",
    "sg:province":"M\u00e1laga",
    "wof:name":"Sanchez Cano Alfonso Jose",
    "wof:placetype":"venue"
},
  "geometry": {"coordinates":[-4.5517239571,36.5836143494],"type":"Point"}
}