{
  "type": "Feature",
  "properties": {
    "iso:country":"ES",
    "sg:address":"Igresia, 35",
    "sg:city":"Igrexa",
    "sg:orig_category":"Alimentaci\u00d3n General (al Por Menor)",
    "sg:phone":"+34 982 14 60 61",
    "sg:postcode":"27751",
    "sg:province":"Lugo",
    "wof:name":"Varela Fernandez Angeles",
    "wof:placetype":"venue"
},
  "geometry": {"coordinates":[-7.2695918083,43.4194831848],"type":"Point"}
}