{
  "type": "Feature",
  "properties": {
    "iso:country":"ES",
    "sg:address":"Calle de Argumosa, 7",
    "sg:city":"Madrid",
    "sg:orig_category":"Heladeros",
    "sg:phone":"+34 915 28 80 09",
    "sg:postcode":"28012",
    "sg:province":"Madrid",
    "wof:name":"Zevallos Conde Yolanda",
    "wof:placetype":"venue"
},
  "geometry": {"coordinates":[-3.6998291016,40.4084014893],"type":"Point"}
}