{
  "type": "Feature",
  "properties": {
    "addr:full":"Carrer de Balmes, 311 Barcelona Barcelona 08006",
    "addr:housenumber":"311",
    "addr:postcode":"08006",
    "addr:street":"Carrer De Balmes",
    "iso:country":"ES",
    "sg:address":"Carrer de Balmes, 311",
    "sg:city":"Barcelona",
    "sg:orig_category":"Contables",
    "sg:phone":"+34 932 09 48 42",
    "sg:postcode":"08006",
    "sg:province":"Barcelona",
    "wof:name":"Raventos Casanovas Montserrat",
    "wof:placetype":"venue"
},
  "geometry": {"coordinates":[2.144972086,41.4024848938],"type":"Point"}
}