{
  "type": "Feature",
  "properties": {
    "iso:country":"ES",
    "sg:address":"Calle de Tinajeros, S/n",
    "sg:city":"Bujalance",
    "sg:orig_category":"Empresas De Carpinter\u00cda De Madera",
    "sg:phone":"+34 957 17 15 74",
    "sg:postcode":"14650",
    "sg:province":"C\u00f3rdoba",
    "wof:name":"Caravaca Notario Pedro",
    "wof:placetype":"venue"
},
  "geometry": {"coordinates":[-4.3782191277,37.8914642334],"type":"Point"}
}