{
  "type": "Feature",
  "properties": {
    "addr:full":"Calle de Bremen, 2 Madrid Madrid 28028",
    "addr:housenumber":"2",
    "addr:postcode":"28028",
    "addr:street":"Calle De Bremen",
    "iso:country":"ES",
    "sg:address":"Calle de Bremen, 2",
    "sg:city":"Madrid",
    "sg:orig_category":"Iglesia Cat\u00d3lica",
    "sg:phone":"+34 913 56 65 25",
    "sg:postcode":"28028",
    "sg:province":"Madrid",
    "wof:name":"Parroquia De San Bonifacio",
    "wof:placetype":"venue"
},
  "geometry": {"coordinates":[-3.664760828,40.4374237061],"type":"Point"}
}