{
  "type": "Feature",
  "properties": {
    "iso:country":"ES",
    "sg:address":"Carr Dato, De, 29",
    "sg:city":"Campos",
    "sg:orig_category":"Tintes (fabricaci\u00d3n, Al Por Mayor)",
    "sg:phone":"+34 971 65 02 35",
    "sg:postcode":"07630",
    "sg:province":"Islas Baleares",
    "wof:name":"Ollers Garcias Gabriela Maria",
    "wof:placetype":"venue"
},
  "geometry": {"coordinates":[2.998032093,39.4063224792],"type":"Point"}
}