{
  "type": "Feature",
  "properties": {
    "iso:country":"ES",
    "sg:address":"Poligono 3, 334",
    "sg:city":"Porreres",
    "sg:orig_category":"Centros Empresariales",
    "sg:phone":"+34 971 16 85 53",
    "sg:postcode":"07260",
    "sg:province":"Islas Baleares",
    "wof:name":"Hans Hermann Noethel",
    "wof:placetype":"venue"
},
  "geometry": {"coordinates":[3.0226650238,39.5170059204],"type":"Point"}
}