{
  "type": "Feature",
  "properties": {
    "addr:full":"Calle de Fuente Nueva, 5 Toledo Toledo 45006",
    "addr:housenumber":"5",
    "addr:postcode":"45006",
    "addr:street":"Calle De Fuente Nueva",
    "iso:country":"ES",
    "sg:address":"Calle de Fuente Nueva, 5",
    "sg:city":"Toledo",
    "sg:orig_category":"Bazares, Art\u00cdculos De Limpieza Y De Cocina (al Por Menor)",
    "sg:phone":"+34 925 22 84 41",
    "sg:postcode":"45006",
    "sg:province":"Toledo",
    "wof:name":"Sanchez Moreno Mari Carmen",
    "wof:placetype":"venue"
},
  "geometry": {"coordinates":[-4.0015530586,39.8610992432],"type":"Point"}
}