{
  "type": "Feature",
  "properties": {
    "addr:full":"Ctra Rabassada, Km. 0006,0 S. Cugat Valles Barcelona 08173",
    "addr:postcode":"08173",
    "addr:street":"Ctra Rabassada Km. 0006,0 S. Cugat Valles Barcelona",
    "iso:country":"ES",
    "sg:address":"Ctra Rabassada, Km. 0006,0",
    "sg:city":"S. Cugat Valles",
    "sg:orig_category":"Discapacitados",
    "sg:phone":"+34 932 12 04 29",
    "sg:postcode":"08173",
    "sg:province":"Barcelona",
    "wof:name":"Patronat De Sant Medir",
    "wof:placetype":"venue"
},
  "geometry": {"coordinates":[2.1700499058,41.3857192993],"type":"Point"}
}