{
  "type": "Feature",
  "properties": {
    "iso:country":"ES",
    "sg:address":"Calle de Alberto Aguilera, 8",
    "sg:city":"Madrid",
    "sg:orig_category":"Psic\u00d3logos",
    "sg:phone":"+34 915 93 11 59",
    "sg:postcode":"28015",
    "sg:province":"Madrid",
    "wof:name":"Grupo Ellison",
    "wof:placetype":"venue"
},
  "geometry": {"coordinates":[-3.7071363926,40.4297828674],"type":"Point"}
}