{
  "type": "Feature",
  "properties": {
    "iso:country":"ES",
    "sg:address":"Carrer de Angel Guimera, 7",
    "sg:city":"Llagostera",
    "sg:orig_category":"Dietistas",
    "sg:phone":"+34 972 83 15 55",
    "sg:postcode":"17240",
    "sg:province":"Girona",
    "wof:name":"Vall-llovera Ramionet Enrique",
    "wof:placetype":"venue"
},
  "geometry": {"coordinates":[2.895004034,41.826587677],"type":"Point"}
}