{
  "type": "Feature",
  "properties": {
    "addr:full":"Calle de Pastor, S/n Playa De Salinetas Las Palmas 35214",
    "addr:housenumber":"s / n",
    "addr:postcode":"35214",
    "addr:street":"Calle De Pastor;Palmas",
    "iso:country":"ES",
    "sg:address":"Calle de Pastor, S/n",
    "sg:city":"Playa De Salinetas",
    "sg:orig_category":"Promotores Constructores",
    "sg:phone":"+34 928 70 75 87",
    "sg:postcode":"35214",
    "sg:province":"Las Palmas",
    "wof:name":"Contratos Y Promociones Monta\u00f1a Del Fuego S.l.",
    "wof:placetype":"venue"
},
  "geometry": {"coordinates":[-15.3882036209,27.9765491486],"type":"Point"}
}