{
  "type": "Feature",
  "properties": {
    "iso:country":"ES",
    "sg:address":"Calle de Batalla Del Salado, 10",
    "sg:city":"Tarifa",
    "sg:orig_category":"Artesan\u00cda Y Trabajos Manuales: Suministros (al Por Menor)",
    "sg:phone":"+34 956 62 72 55",
    "sg:postcode":"11380",
    "sg:province":"C\u00e1diz",
    "wof:name":"Sanchez Vi\u00f1uela Isabel",
    "wof:placetype":"venue"
},
  "geometry": {"coordinates":[-5.6050200462,36.0147743225],"type":"Point"}
}