{
  "type": "Feature",
  "properties": {
    "iso:country":"ES",
    "sg:address":"Zirkuitu Ibilbidea - Camino Del Circuito, 15",
    "sg:city":"Lasarte-oria",
    "sg:orig_category":"Reposter\u00cdas",
    "sg:phone":"+34 943 36 64 39",
    "sg:postcode":"20160",
    "sg:province":"Guip\u00f9zcoa",
    "wof:name":"Denda Berri Yk,s.l.",
    "wof:placetype":"venue"
},
  "geometry": {"coordinates":[-2.0192439556,43.2524108887],"type":"Point"}
}