{
  "type": "Feature",
  "properties": {
    "addr:full":"Calle de Empedrado, 112 Alginet Valencia 46230",
    "addr:housenumber":"112",
    "addr:postcode":"46230",
    "addr:street":"Calle De Empedrado",
    "iso:country":"ES",
    "sg:address":"Calle de Empedrado, 112",
    "sg:city":"Alginet",
    "sg:orig_category":"Asesor\u00cda Fiscal Y Jur\u00cddica",
    "sg:phone":"+34 961 75 32 20",
    "sg:postcode":"46230",
    "sg:province":"Valencia",
    "wof:name":"Maria Jose Iranzo S.l.",
    "wof:placetype":"venue"
},
  "geometry": {"coordinates":[-0.4729239941,39.2651977539],"type":"Point"}
}