{
  "type": "Feature",
  "properties": {
    "iso:country":"ES",
    "sg:address":"Calle de Santo Domingo De Guzman, 17",
    "sg:city":"Valladolid",
    "sg:orig_category":"Agencias Y Asesores De Publicidad",
    "sg:phone":"+34 983 35 85 34",
    "sg:postcode":"47003",
    "sg:province":"Valladolid",
    "wof:name":"Alonso Alonso Maria Teresa",
    "wof:placetype":"venue"
},
  "geometry": {"coordinates":[-4.7304568291,41.6557655334],"type":"Point"}
}