{
  "type": "Feature",
  "properties": {
    "addr:full":"Carrer de Sant Jaume, 10 Castellar Valles Barcelona 08211",
    "addr:housenumber":"10",
    "addr:postcode":"08211",
    "addr:street":"Carrer De Sant Jaume",
    "iso:country":"ES",
    "sg:address":"Carrer de Sant Jaume, 10",
    "sg:city":"Castellar Valles",
    "sg:orig_category":"Molduras, Junquillos, Listones Y Molduras Perforadas",
    "sg:phone":"+34 937 14 55 56",
    "sg:postcode":"08211",
    "sg:province":"Barcelona",
    "wof:name":"Cierco Castells Ramon",
    "wof:placetype":"venue"
},
  "geometry": {"coordinates":[2.0827050209,41.6137809753],"type":"Point"}
}