{
  "type": "Feature",
  "properties": {
    "addr:full":"Carrer de Pare Gallissa, 19 Vic Barcelona 08500",
    "addr:housenumber":"19",
    "addr:postcode":"08500",
    "addr:street":"Carrer De Pare Gallissa",
    "iso:country":"ES",
    "sg:address":"Carrer de Pare Gallissa, 19",
    "sg:city":"Vic",
    "sg:orig_category":"Muebles, Minoristas",
    "sg:phone":"+34 938 85 37 38",
    "sg:postcode":"08500",
    "sg:province":"Barcelona",
    "wof:name":"Mobles Vic S. A.",
    "wof:placetype":"venue"
},
  "geometry": {"coordinates":[2.2495799065,41.9322128296],"type":"Point"}
}