{
  "type": "Feature",
  "properties": {
    "iso:country":"ES",
    "sg:address":"Plaz Ecce Homo, 3",
    "sg:city":"Zaragoza",
    "sg:orig_category":"Ense\u00d1anza Variada",
    "sg:phone":"+34 976 20 31 20",
    "sg:postcode":"50003",
    "sg:province":"Zaragoza",
    "sg:website":"www.esturzar.com",
    "wof:name":"Fundacion Fernando Casamayor",
    "wof:placetype":"venue"
},
  "geometry": {"coordinates":[-0.8827859759,41.6546936035],"type":"Point"}
}