{
  "type": "Feature",
  "properties": {
    "iso:country":"ES",
    "sg:address":"Calle de Monte Naranco, 12",
    "sg:city":"Lugones",
    "sg:orig_category":"Centros Empresariales",
    "sg:phone":"+34 985 26 82 93",
    "sg:postcode":"33420",
    "sg:province":"Asturias",
    "wof:name":"Atra Asturias",
    "wof:placetype":"venue"
},
  "geometry": {"coordinates":[-5.8104739189,43.4038047791],"type":"Point"}
}