{
  "type": "Feature",
  "properties": {
    "iso:country":"ES",
    "sg:address":"Calle de Ca\u00d1os De Carmona, 9",
    "sg:city":"Sevilla",
    "sg:orig_category":"Arquitectos",
    "sg:phone":"+34 954 41 82 41",
    "sg:postcode":"41003",
    "sg:province":"Sevilla",
    "wof:name":"Aguilar Garcia Honorio",
    "wof:placetype":"venue"
},
  "geometry": {"coordinates":[-5.9835929871,37.3870544434],"type":"Point"}
}