{
  "type": "Feature",
  "properties": {
    "iso:country":"ES",
    "sg:address":"Avda Aldehuela, 44",
    "sg:city":"Salamanca",
    "sg:orig_category":"Aguas (distribuci\u00d3n, Servicios)",
    "sg:phone":"+34 923 18 56 57",
    "sg:postcode":"37008",
    "sg:province":"Salamanca",
    "wof:name":"Aqualia-fcc Salamanca Ute",
    "wof:placetype":"venue"
},
  "geometry": {"coordinates":[-5.6492657661,40.9591369629],"type":"Point"}
}