{
  "type": "Feature",
  "properties": {
    "addr:full":"Carrer de Ausias March, 29 Palma Islas Baleares 07003",
    "addr:housenumber":"29",
    "addr:postcode":"07003",
    "addr:street":"Carrer De Ausias March",
    "iso:country":"ES",
    "sg:address":"Carrer de Ausias March, 29",
    "sg:city":"Palma",
    "sg:orig_category":"Institutos De Belleza (productos Y Aparatos)",
    "sg:phone":"+34 971 75 52 62",
    "sg:postcode":"07003",
    "sg:province":"Islas Baleares",
    "wof:name":"Justo Carlos S.l.",
    "wof:placetype":"venue"
},
  "geometry": {"coordinates":[2.6478281021,39.5819282532],"type":"Point"}
}