{
  "type": "Feature",
  "properties": {
    "addr:full":"Carretera Zamora, Km. 0003,0 Moraleja Vino Zamora 49150",
    "addr:postcode":"49150",
    "addr:street":"Carretera Zamora Km. 0003,0",
    "iso:country":"ES",
    "sg:address":"Carretera Zamora, Km. 0003,0",
    "sg:city":"Moraleja Vino",
    "sg:orig_category":"Droguer\u00cdas (al Por Menor)",
    "sg:phone":"+34 980 57 12 64",
    "sg:postcode":"49150",
    "sg:province":"Zamora",
    "wof:name":"Drogas Vaquero S.a.",
    "wof:placetype":"venue"
},
  "geometry": {"coordinates":[-5.6560359001,41.4629325867],"type":"Point"}
}