{
  "type": "Feature",
  "properties": {
    "iso:country":"ES",
    "sg:address":"Calle de Fernan Gonzalez, 29",
    "sg:city":"Madrid",
    "sg:orig_category":"Perfumer\u00cda (al Por Menor)",
    "sg:phone":"+34 915 74 26 06",
    "sg:postcode":"28009",
    "sg:province":"Madrid",
    "sg:website":"www.bodybell.com",
    "wof:name":"Iberica De Drogueria Y Perfumeria S.a.",
    "wof:placetype":"venue"
},
  "geometry": {"coordinates":[-3.6741790771,40.4221801758],"type":"Point"}
}