{
  "type": "Feature",
  "properties": {
    "addr:full":"Carr Pais Valencia (del), 101 Betxi Castell\u00f3n 12549",
    "addr:housenumber":"101",
    "addr:postcode":"12549",
    "addr:street":"Carr Pais;Del;Castello\u0301N",
    "iso:country":"ES",
    "sg:address":"Carr Pais Valencia (del), 101",
    "sg:city":"Betxi",
    "sg:orig_category":"Plomeros",
    "sg:phone":"+34 964 62 05 09",
    "sg:postcode":"12549",
    "sg:province":"Castell\u00f3n",
    "wof:name":"Fongecor S.l.",
    "wof:placetype":"venue"
},
  "geometry": {"coordinates":[-0.1963589936,39.9285507202],"type":"Point"}
}