{
  "type": "Feature",
  "properties": {
    "iso:country":"ES",
    "sg:address":"Donostia Ibilbidea, 48",
    "sg:city":"Astigarraga",
    "sg:orig_category":"Electricidad, Electr\u00d3nica: Suministros (al Por Menor)",
    "sg:phone":"+34 943 33 02 40",
    "sg:postcode":"20115",
    "sg:province":"Guip\u00f9zcoa",
    "wof:name":"Doxon Electronica",
    "wof:placetype":"venue"
},
  "geometry": {"coordinates":[-1.9509220123,43.2834396362],"type":"Point"}
}