{
  "type": "Feature",
  "properties": {
    "iso:country":"ES",
    "sg:address":"Carr Ciutadans, 11",
    "sg:city":"Girona",
    "sg:orig_category":"Mutuas De Seguros",
    "sg:phone":"+34 972 21 83 87",
    "sg:postcode":"17004",
    "sg:province":"Girona",
    "wof:name":"Mutua Manresana Mutualitat De Previsio Social",
    "wof:placetype":"venue"
},
  "geometry": {"coordinates":[2.8252100945,41.9841041565],"type":"Point"}
}