{
  "type": "Feature",
  "properties": {
    "iso:country":"ES",
    "sg:address":"Av Tarragona, 52",
    "sg:city":"Vilafranca Penedes",
    "sg:orig_category":"Bares, Piano",
    "sg:phone":"+34 938 90 34 30",
    "sg:postcode":"08720",
    "sg:province":"Barcelona",
    "wof:name":"Soler Marrugat Santiago",
    "wof:placetype":"venue"
},
  "geometry": {"coordinates":[1.6963540316,41.3430519104],"type":"Point"}
}