{
  "type": "Feature",
  "properties": {
    "iso:country":"ES",
    "sg:address":"Calle de Autonomia, 68",
    "sg:city":"Bilbao",
    "sg:orig_category":"Ropa Para Se\u00d1oras (al Por Menor)",
    "sg:phone":"+34 944 43 35 58",
    "sg:postcode":"48012",
    "sg:province":"Vizcaya",
    "wof:name":"Boutique Feba S.l.",
    "wof:placetype":"venue"
},
  "geometry": {"coordinates":[-2.9457232952,43.2578926086],"type":"Point"}
}