{
  "type": "Feature",
  "properties": {
    "addr:full":"Calle de San Esteban, 65 Cuatrovientos Le\u00f3n 24400",
    "addr:housenumber":"65",
    "addr:postcode":"24400",
    "addr:street":"Calle De San Esteban",
    "iso:country":"ES",
    "sg:address":"Calle de San Esteban, 65",
    "sg:city":"Cuatrovientos",
    "sg:orig_category":"Droguer\u00cdas (al Por Menor)",
    "sg:phone":"+34 987 41 35 83",
    "sg:postcode":"24400",
    "sg:province":"Le\u00f3n",
    "wof:name":"Soto Lolo Manuel",
    "wof:placetype":"venue"
},
  "geometry": {"coordinates":[-6.6198649406,42.5608291626],"type":"Point"}
}