{
  "type": "Feature",
  "properties": {
    "addr:full":"Carrer de Aneto, 33 Barcelona Barcelona 08031",
    "addr:housenumber":"33",
    "addr:postcode":"08031",
    "addr:street":"Carrer De Aneto",
    "iso:country":"ES",
    "sg:address":"Carrer de Aneto, 33",
    "sg:city":"Barcelona",
    "sg:orig_category":"Asociaciones, Organismos Culturales Y Socioeducativos",
    "sg:phone":"+34 934 29 31 61",
    "sg:postcode":"08031",
    "sg:province":"Barcelona",
    "wof:name":"Pe\u00f1a Barcelonista Turo La Peira",
    "wof:placetype":"venue"
},
  "geometry": {"coordinates":[2.1702110767,41.4326591492],"type":"Point"}
}