{
  "type": "Feature",
  "properties": {
    "iso:country":"ES",
    "sg:address":"Calle de Magallanes, S/n",
    "sg:city":"Aspe",
    "sg:orig_category":"Ense\u00d1anza, Formaci\u00d3n Profesional: Aprendizaje",
    "sg:phone":"+34 965 49 27 34",
    "sg:postcode":"03680",
    "sg:province":"Alicante",
    "wof:name":"Ayuntamiento De Aspe-mercado De Abastos",
    "wof:placetype":"venue"
},
  "geometry": {"coordinates":[-0.7659059763,38.3461990356],"type":"Point"}
}