{
  "type": "Feature",
  "properties": {
    "iso:country":"ES",
    "sg:address":"Carrer de Generalitat, 3",
    "sg:city":"Montcada Centre",
    "sg:orig_category":"Platos Preparados Refrigerados (fabricaci\u00d3n, Al Por Mayor)",
    "sg:phone":"+34 935 64 85 52",
    "sg:postcode":"08110",
    "sg:province":"Barcelona",
    "wof:name":"Gonzalez Moral Gerarda",
    "wof:placetype":"venue"
},
  "geometry": {"coordinates":[2.1817800999,41.4892234802],"type":"Point"}
}