{
  "type": "Feature",
  "properties": {
    "iso:country":"ES",
    "sg:address":"Pase Duque De Mandas, 31",
    "sg:city":"Donostia-san Sebastian",
    "sg:orig_category":"Ense\u00d1anza Industrial Y T\u00c9cnica",
    "sg:phone":"+34 943 28 36 34",
    "sg:postcode":"20012",
    "sg:province":"Guip\u00f9zcoa",
    "wof:name":"Escuela Udaia Eskola, S.l.",
    "wof:placetype":"venue"
},
  "geometry": {"coordinates":[-1.9745500088,43.3181266785],"type":"Point"}
}