{
  "type": "Feature",
  "properties": {
    "addr:full":"Calle de Zurbaran, 8 Madrid Madrid 28010",
    "addr:housenumber":"8",
    "addr:postcode":"madrid;28010",
    "addr:street":"Calle De Zurbaran",
    "iso:country":"ES",
    "sg:address":"Calle de Zurbaran, 8",
    "sg:city":"Madrid",
    "sg:orig_category":"Ropa Para Beb\u00c9s Y Ni\u00d1os (confecci\u00d3n, Al Por Mayor)",
    "sg:phone":"+34 913 19 38 00",
    "sg:postcode":"28010",
    "sg:province":"Madrid",
    "wof:name":"Spirit Of Ballambamboo S.l.",
    "wof:placetype":"venue"
},
  "geometry": {"coordinates":[-3.6934638023,40.4295692444],"type":"Point"}
}