{
  "type": "Feature",
  "properties": {
    "addr:full":"Avda Pais Valencia, 73 Torrent Valencia 46900",
    "addr:housenumber":"73",
    "addr:postcode":"46900",
    "addr:street":"Avda Pais Valencia;Valencia",
    "iso:country":"ES",
    "sg:address":"Avda Pais Valencia, 73",
    "sg:city":"Torrent",
    "sg:orig_category":"Bisuter\u00cda, Joyer\u00cda, Relojer\u00cda (al Por Menor)",
    "sg:phone":"+34 961 55 34 72",
    "sg:postcode":"46900",
    "sg:province":"Valencia",
    "wof:name":"Jover Gonzalez Vicente",
    "wof:placetype":"venue"
},
  "geometry": {"coordinates":[-0.4697529972,39.4341392517],"type":"Point"}
}