{
  "type": "Feature",
  "properties": {
    "addr:full":"Calle de Santiago Apostol (de), 13 Alcobendas Madrid 28100",
    "addr:postcode":"28100",
    "addr:street":"Calle De Santiago",
    "iso:country":"ES",
    "sg:address":"Calle de Santiago Apostol (de), 13",
    "sg:city":"Alcobendas",
    "sg:orig_category":"Alquiler De V\u00cddeo",
    "sg:phone":"+34 916 51 45 79",
    "sg:postcode":"28100",
    "sg:province":"Madrid",
    "wof:name":"Perales Garcia Carmen",
    "wof:placetype":"venue"
},
  "geometry": {"coordinates":[-3.631841898,40.5431060791],"type":"Point"}
}