{
  "type": "Feature",
  "properties": {
    "iso:country":"ES",
    "sg:address":"Calle de Ciudad De La Habana, 4",
    "sg:city":"Valladolid",
    "sg:orig_category":"Fabricaci\u00d3n De Tapices Y Moquetas Para Suelos Y Paredes",
    "sg:phone":"+34 983 36 38 47",
    "sg:postcode":"47014",
    "sg:province":"Valladolid",
    "wof:name":"Tecnotrans Sabre S.a.",
    "wof:placetype":"venue"
},
  "geometry": {"coordinates":[-4.760078907,41.6385002136],"type":"Point"}
}