{
  "type": "Feature",
  "properties": {
    "iso:country":"ES",
    "sg:address":"Carrer de Narcis Giralt, 15",
    "sg:city":"Sabadell",
    "sg:orig_category":"Centros De Coordinaci\u00d3n",
    "sg:phone":"+34 937 25 41 88",
    "sg:postcode":"08202",
    "sg:province":"Barcelona",
    "wof:name":"Ferrer Gestio Professionals S.l.",
    "wof:placetype":"venue"
},
  "geometry": {"coordinates":[2.1106770039,41.5460586548],"type":"Point"}
}