{
  "type": "Feature",
  "properties": {
    "iso:country":"ES",
    "sg:address":"Avda Campones, S/n",
    "sg:city":"Gijon",
    "sg:orig_category":"Construcciones Met\u00c1licas",
    "sg:phone":"+34 902 19 65 20",
    "sg:postcode":"33211",
    "sg:province":"Asturias",
    "wof:name":"Esmena S.l.",
    "wof:placetype":"venue"
},
  "geometry": {"coordinates":[-5.6857228279,43.5342826843],"type":"Point"}
}