{
  "type": "Feature",
  "properties": {
    "iso:country":"ES",
    "sg:address":"Tolda, S/n",
    "sg:city":"Tolda",
    "sg:orig_category":"Material Y Herramientas Agr\u00cdcolas",
    "sg:phone":"+34 982 15 30 66",
    "sg:postcode":"27307",
    "sg:province":"Lugo",
    "wof:name":"Diaz Fraga Jose",
    "wof:placetype":"venue"
},
  "geometry": {"coordinates":[-7.8914551735,43.3296852112],"type":"Point"}
}