{
  "type": "Feature",
  "properties": {
    "iso:country":"ES",
    "sg:address":"Cust Llano (del), 4",
    "sg:city":"Balanegra",
    "sg:orig_category":"Centros De Educaci\u00d3n Especial",
    "sg:phone":"+34 950 40 61 16",
    "sg:postcode":"04713",
    "sg:province":"Almer\u00eda",
    "wof:name":"Junta De Andalucia Delegacion Provincial Ministerio Educacion Y Ciencia",
    "wof:placetype":"venue"
},
  "geometry": {"coordinates":[-2.9070239067,36.7499694824],"type":"Point"}
}