{
  "type": "Feature",
  "properties": {
    "iso:country":"ES",
    "sg:address":"Av Joan Miro, 336",
    "sg:city":"Sant Agusti",
    "sg:orig_category":"Ropa Para Se\u00d1oras (al Por Menor)",
    "sg:phone":"+34 971 70 36 42",
    "sg:postcode":"07015",
    "sg:province":"Islas Baleares",
    "wof:name":"Vidal-cuadras De La Rosa Barbara",
    "wof:placetype":"venue"
},
  "geometry": {"coordinates":[2.5995469093,39.5510520935],"type":"Point"}
}