{
  "type": "Feature",
  "properties": {
    "iso:country":"ES",
    "sg:address":"Carr Josep M Quadrado, 8",
    "sg:city":"Ciutadella Menorca",
    "sg:orig_category":"Panader\u00cdas, Panader\u00cdas",
    "sg:phone":"+34 971 38 06 40",
    "sg:postcode":"07760",
    "sg:province":"Islas Baleares",
    "wof:name":"Bagur Taltavull Pedro",
    "wof:placetype":"venue"
},
  "geometry": {"coordinates":[3.8390324116,40.0022659302],"type":"Point"}
}