{
  "type": "Feature",
  "properties": {
    "addr:full":"Calle de Parras, 1 Garrovillas De Alconetar C\u00e1ceres 10940",
    "addr:housenumber":"1",
    "addr:postcode":"10940",
    "addr:street":"Calle De Parras;Ca\u0301Ceres",
    "iso:country":"ES",
    "sg:address":"Calle de Parras, 1",
    "sg:city":"Garrovillas De Alconetar",
    "sg:orig_category":"Alimentaci\u00d3n General (al Por Menor)",
    "sg:phone":"+34 927 30 90 75",
    "sg:postcode":"10940",
    "sg:province":"C\u00e1ceres",
    "wof:name":"Solis Lazaro Juan",
    "wof:placetype":"venue"
},
  "geometry": {"coordinates":[-6.5516290665,39.7099952698],"type":"Point"}
}