{
  "type": "Feature",
  "properties": {
    "addr:full":"Avda Area, 21 Cedeira La Coru\u00f1a 15350",
    "addr:housenumber":"21",
    "addr:postcode":"15350",
    "addr:street":"Avda Area;La Corun\u0303A",
    "iso:country":"ES",
    "sg:address":"Avda Area, 21",
    "sg:city":"Cedeira",
    "sg:orig_category":"Lencer\u00cda Femenina, Corseter\u00cda, Trajes De Ba\u00d1o (al Por Menor)",
    "sg:phone":"+34 981 48 04 91",
    "sg:postcode":"15350",
    "sg:province":"La Coru\u00f1a",
    "wof:name":"Lopez Soto Mari Jose",
    "wof:placetype":"venue"
},
  "geometry": {"coordinates":[-8.0532627106,43.6611175537],"type":"Point"}
}