{
  "type": "Feature",
  "properties": {
    "iso:country":"ES",
    "sg:address":"Carrer de Narcis Monturiol, 2",
    "sg:city":"Manresa",
    "sg:orig_category":"Veh\u00cdculos De Ocasi\u00d3n",
    "sg:phone":"+34 938 74 46 27",
    "sg:postcode":"08243",
    "sg:province":"Barcelona",
    "sg:website":"www.autosmoure.com",
    "wof:name":"Autos Moure S.l.",
    "wof:placetype":"venue"
},
  "geometry": {"coordinates":[1.8470729589,41.7172737122],"type":"Point"}
}