{
  "type": "Feature",
  "properties": {
    "addr:full":"Rua Barcelona, 14 Carballo A Coru\u00f1a 15100",
    "addr:housenumber":"14",
    "addr:postcode":"15100",
    "addr:street":"Rua Barcelona;Corun\u0303A",
    "iso:country":"ES",
    "sg:address":"Rua Barcelona, 14",
    "sg:city":"Carballo",
    "sg:orig_category":"Radiocomunicaciones, Telefon\u00cda M\u00d3vil, Radiomensajer\u00cda: Servicios, Comercializaci\u00d3n",
    "sg:phone":"+34 981 70 14 83",
    "sg:postcode":"15100",
    "sg:province":"A Coru\u00f1a",
    "wof:name":"Telecomunicaciones Berganti\u00f1os S.l.",
    "wof:placetype":"venue"
},
  "geometry": {"coordinates":[-8.6932544708,43.212184906],"type":"Point"}
}