{
  "type": "Feature",
  "properties": {
    "iso:country":"ES",
    "sg:address":"Calle de San Jose De Calasanz, 8",
    "sg:city":"Binefar",
    "sg:orig_category":"Ense\u00d1ante, Direcci\u00d3n",
    "sg:phone":"+34 974 42 83 81",
    "sg:postcode":"22500",
    "sg:province":"Huesca",
    "wof:name":"Sanchez Catalan Jose Antonio",
    "wof:placetype":"venue"
},
  "geometry": {"coordinates":[0.2955630124,41.8505020142],"type":"Point"}
}