{
  "type": "Feature",
  "properties": {
    "addr:full":"Carrer de Caballero, 63 Barcelona Barcelona 08014",
    "addr:housenumber":"63",
    "addr:postcode":"08014",
    "addr:street":"Carrer De Caballero",
    "iso:country":"ES",
    "sg:address":"Carrer de Caballero, 63",
    "sg:city":"Barcelona",
    "sg:orig_category":"Mec\u00c1nico Del Autom\u00d3vil",
    "sg:phone":"+34 934 90 67 18",
    "sg:postcode":"08014",
    "sg:province":"Barcelona",
    "wof:name":"Serviauto Barcelona S.l.",
    "wof:placetype":"venue"
},
  "geometry": {"coordinates":[2.1364839077,41.383266449],"type":"Point"}
}