{
  "type": "Feature",
  "properties": {
    "iso:country":"ES",
    "sg:address":"Cmno Olmos, 55",
    "sg:city":"Zarandona",
    "sg:orig_category":"Reposter\u00cdas",
    "sg:phone":"+34 968 24 54 76",
    "sg:postcode":"30007",
    "sg:province":"Murcia",
    "wof:name":"Abellan Caravaca Abelardo",
    "wof:placetype":"venue"
},
  "geometry": {"coordinates":[-1.129887,37.983475],"type":"Point"}
}