{
  "type": "Feature",
  "properties": {
    "addr:full":"Enviande, S/n Enviande Lugo 27595",
    "addr:postcode":"27595",
    "addr:street":"Enviande S / N",
    "iso:country":"ES",
    "sg:address":"Enviande, S/n",
    "sg:city":"Enviande",
    "sg:orig_category":"Empresas De Electricidad En General",
    "sg:phone":"+34 982 18 20 38",
    "sg:postcode":"27595",
    "sg:province":"Lugo",
    "wof:name":"Hidroelectrica Cortizo S.a.",
    "wof:placetype":"venue"
},
  "geometry": {"coordinates":[-7.77079916,42.6171607971],"type":"Point"}
}