{
  "type": "Feature",
  "properties": {
    "iso:country":"ES",
    "sg:address":"Ctra. Arenal, 8",
    "sg:city":"Les Meravelles",
    "sg:orig_category":"Librer\u00cdas",
    "sg:phone":"+34 971 26 43 14",
    "sg:postcode":"07610",
    "sg:province":"Islas Baleares",
    "wof:name":"Nova Area S.a.",
    "wof:placetype":"venue"
},
  "geometry": {"coordinates":[2.7328209877,39.5273704529],"type":"Point"}
}