{
  "type": "Feature",
  "properties": {
    "iso:country":"ES",
    "sg:address":"Rua Quiroga Ballesteros, S/n",
    "sg:city":"Lugo",
    "sg:orig_category":"Carnicer\u00cdas, Carnicer\u00cdas",
    "sg:phone":"+34 982 23 12 67",
    "sg:postcode":"27001",
    "sg:province":"Lugo",
    "wof:name":"Diaz Vazquez Jesus",
    "wof:placetype":"venue"
},
  "geometry": {"coordinates":[-7.5588941574,43.0136413574],"type":"Point"}
}