{
  "type": "Feature",
  "properties": {
    "addr:full":"Avda Mejico, S/n Huelva Huelva 21001",
    "addr:housenumber":"s / n",
    "addr:postcode":"21001",
    "addr:street":"Avda Mejico",
    "iso:country":"ES",
    "sg:address":"Avda Mejico, S/n",
    "sg:city":"Huelva",
    "sg:orig_category":"Promotores Constructores",
    "sg:phone":"+34 959 25 30 33",
    "sg:postcode":"21001",
    "sg:province":"Huelva",
    "wof:name":"Conusa S. A.",
    "wof:placetype":"venue"
},
  "geometry": {"coordinates":[-6.9495940208,37.256313324],"type":"Point"}
}