{
  "type": "Feature",
  "properties": {
    "addr:full":"Carrer de Diputacio, 312 Barcelona Barcelona 08009",
    "addr:housenumber":"312",
    "addr:postcode":"08009",
    "addr:street":"Carrer De Diputacio",
    "iso:country":"ES",
    "sg:address":"Carrer de Diputacio, 312",
    "sg:city":"Barcelona",
    "sg:orig_category":"Bisuter\u00cda, Joyer\u00cda, Relojer\u00cda (al Por Menor)",
    "sg:phone":"+34 932 44 83 33",
    "sg:postcode":"08009",
    "sg:province":"Barcelona",
    "wof:name":"Joyeria Oriental Jade S.c.p.",
    "wof:placetype":"venue"
},
  "geometry": {"coordinates":[2.1723349094,41.3941879272],"type":"Point"}
}