{
  "type": "Feature",
  "properties": {
    "iso:country":"ES",
    "sg:address":"Calle de Donato Arguelles, 8",
    "sg:city":"Gijon",
    "sg:orig_category":"Procuradores",
    "sg:phone":"+34 984 19 78 28",
    "sg:postcode":"33206",
    "sg:province":"Asturias",
    "wof:name":"Pedro Manuel De Elias Cabal",
    "wof:placetype":"venue"
},
  "geometry": {"coordinates":[-5.66492033,43.5403404236],"type":"Point"}
}