{
  "type": "Feature",
  "properties": {
    "addr:full":"Carrer de Angel Guimera, 123 Esplugues Llobregat Barcelona 08950",
    "addr:housenumber":"123",
    "addr:postcode":"08950",
    "addr:street":"Carrer De Angel Guimera",
    "iso:country":"ES",
    "sg:address":"Carrer de Angel Guimera, 123",
    "sg:city":"Esplugues Llobregat",
    "sg:orig_category":"Alquiler De Climatizadores",
    "sg:phone":"+34 934 73 03 67",
    "sg:postcode":"08950",
    "sg:province":"Barcelona",
    "wof:name":"Climacat S.l.",
    "wof:placetype":"venue"
},
  "geometry": {"coordinates":[2.0804738998,41.3750267029],"type":"Point"}
}