{
  "type": "Feature",
  "properties": {
    "addr:full":"Carr Dr Fleming, 45 Balaguer Lleida 25600",
    "addr:housenumber":"45",
    "addr:postcode":"25600",
    "addr:street":"Carr Dr Fleming",
    "iso:country":"ES",
    "sg:address":"Carr Dr Fleming, 45",
    "sg:city":"Balaguer",
    "sg:orig_category":"Abogados",
    "sg:phone":"+34 973 44 31 52",
    "sg:postcode":"25600",
    "sg:province":"Lleida",
    "wof:name":"Viola Santallusia Manel",
    "wof:placetype":"venue"
},
  "geometry": {"coordinates":[0.8096100092,41.7884063721],"type":"Point"}
}