{
  "type": "Feature",
  "properties": {
    "iso:country":"ES",
    "sg:address":"Calle de Iparragirre, 1",
    "sg:city":"Ondarroa",
    "sg:orig_category":"Suministros Y Materiales Industriales",
    "sg:phone":"+34 946 83 22 50",
    "sg:postcode":"48700",
    "sg:province":"Vizcaya",
    "wof:name":"Leniz Larreategui Gotzon",
    "wof:placetype":"venue"
},
  "geometry": {"coordinates":[-2.4206979275,43.3210754395],"type":"Point"}
}