{
  "type": "Feature",
  "properties": {
    "addr:full":"Calle de Alamo, 17 Torrejon Ardoz Madrid 28850",
    "addr:housenumber":"17",
    "addr:postcode":"28850",
    "addr:street":"Calle De Alamo",
    "iso:country":"ES",
    "sg:address":"Calle de Alamo, 17",
    "sg:city":"Torrejon Ardoz",
    "sg:orig_category":"Quincaller\u00cda (al Por Menor)",
    "sg:phone":"+34 916 76 75 12",
    "sg:postcode":"28850",
    "sg:province":"Madrid",
    "wof:name":"Ferreteria Santa Engracia S. L.",
    "wof:placetype":"venue"
},
  "geometry": {"coordinates":[-3.4567828178,40.4461631775],"type":"Point"}
}