{
  "type": "Feature",
  "properties": {
    "addr:full":"Gabiria Gunea, 3 Gabiria Guip\u00f9zcoa 20217",
    "addr:housenumber":"3",
    "addr:postcode":"20217",
    "addr:street":"Gabiria Gunea;Guipu\u0300Zcoa",
    "iso:country":"ES",
    "sg:address":"Gabiria Gunea, 3",
    "sg:city":"Gabiria",
    "sg:orig_category":"Centros De Educaci\u00d3n Especial",
    "sg:phone":"+34 943 88 87 23",
    "sg:postcode":"20217",
    "sg:province":"Guip\u00f9zcoa",
    "sg:website":"www.euskadi.net",
    "wof:name":"Gobierno Vasco-eusko Jaurlaritza",
    "wof:placetype":"venue"
},
  "geometry": {"coordinates":[-2.2795989513,43.0502204895],"type":"Point"}
}