{
  "type": "Feature",
  "properties": {
    "addr:full":"Avda Zumalakarregi, 48 Llodio \u00c1lava 01400",
    "addr:housenumber":"48",
    "addr:postcode":"01400",
    "addr:street":"Avda Zumalakarregi",
    "iso:country":"ES",
    "sg:address":"Avda Zumalakarregi, 48",
    "sg:city":"Llodio",
    "sg:orig_category":"Agencias De Viajes",
    "sg:phone":"+34 946 72 28 42",
    "sg:postcode":"01400",
    "sg:province":"\u00c1lava",
    "wof:name":"Viajes Araba S.l.",
    "wof:placetype":"venue"
},
  "geometry": {"coordinates":[-2.9642589092,43.1418609619],"type":"Point"}
}