{
  "type": "Feature",
  "properties": {
    "iso:country":"ES",
    "sg:address":"Rbla Sant Sebastia, 52",
    "sg:city":"Santa Coloma De Gramenet",
    "sg:orig_category":"Fabricaci\u00d3n, Reparaci\u00d3n Y Mantenimiento De Construcciones Navales Y Fluviales",
    "sg:phone":"+34 934 66 52 51",
    "sg:postcode":"08922",
    "sg:province":"Barcelona",
    "wof:name":"Aramburu Llorente Angel",
    "wof:placetype":"venue"
},
  "geometry": {"coordinates":[2.1913874149,41.4287185669],"type":"Point"}
}