{
  "type": "Feature",
  "properties": {
    "iso:country":"ES",
    "sg:address":"Carrer de Marti Grive, 37",
    "sg:city":"Granollers",
    "sg:orig_category":"Mercer\u00cda (fabricaci\u00d3n, Al Por Mayor)",
    "sg:phone":"+34 938 70 15 33",
    "sg:postcode":"08402",
    "sg:province":"Barcelona",
    "wof:name":"Tuset Serradelarca Lluis",
    "wof:placetype":"venue"
},
  "geometry": {"coordinates":[2.2894320488,41.6037483215],"type":"Point"}
}