{
  "type": "Feature",
  "properties": {
    "addr:full":"Avda Castelao, 67 Vigo Pontevedra 36209",
    "addr:housenumber":"67",
    "addr:postcode":"36209",
    "addr:street":"Avda Castelao",
    "iso:country":"ES",
    "sg:address":"Avda Castelao, 67",
    "sg:city":"Vigo",
    "sg:orig_category":"Delegados, Agentes De Tr\u00c1nsito, Auxiliares De Transporte Internacional",
    "sg:phone":"+34 986 29 62 59",
    "sg:postcode":"36209",
    "sg:province":"Pontevedra",
    "wof:name":"Fernandez Garcia Alfonso",
    "wof:placetype":"venue"
},
  "geometry": {"coordinates":[-8.7456970215,42.217956543],"type":"Point"}
}