{
  "type": "Feature",
  "properties": {
    "iso:country":"ES",
    "sg:address":"Rua Infistela, 4",
    "sg:city":"Verin",
    "sg:orig_category":"Contenedores (mercanc\u00cdas)",
    "sg:phone":"+34 988 41 00 08",
    "sg:postcode":"32600",
    "sg:province":"Ourense",
    "wof:name":"Franco Alonso Francisco",
    "wof:placetype":"venue"
},
  "geometry": {"coordinates":[-7.4290761948,41.9345436096],"type":"Point"}
}