{
  "type": "Feature",
  "properties": {
    "addr:full":"Prol. Fray Serafin, 75 Moral Calatrava Ciudad Real 13350",
    "addr:housenumber":"75",
    "addr:postcode":"13350",
    "addr:street":"Prol. Fray Serafin;Calatrava",
    "iso:country":"ES",
    "sg:address":"Prol. Fray Serafin, 75",
    "sg:city":"Moral Calatrava",
    "sg:orig_category":"Persianas Interiores, Exteriores",
    "sg:phone":"+34 926 33 05 27",
    "sg:postcode":"13350",
    "sg:province":"Ciudad Real",
    "wof:name":"Naranjo Gonzalez Jose",
    "wof:placetype":"venue"
},
  "geometry": {"coordinates":[-3.5793139935,38.8292617798],"type":"Point"}
}