{
  "type": "Feature",
  "properties": {
    "addr:full":"Avda Cordoba (de), S/n Aguilar De La Frontera C\u00f3rdoba 14920",
    "addr:postcode":"14920",
    "addr:street":"Avda Cordoba De S / N",
    "iso:country":"ES",
    "sg:address":"Avda Cordoba (de), S/n",
    "sg:city":"Aguilar De La Frontera",
    "sg:orig_category":"Agentes, Concesionarios Y Sucursales De Veh\u00cdculos",
    "sg:phone":"+34 957 66 20 47",
    "sg:postcode":"14920",
    "sg:province":"C\u00f3rdoba",
    "wof:name":"Expoauto Aguilar S.l.",
    "wof:placetype":"venue"
},
  "geometry": {"coordinates":[-4.6528792381,37.5219841003],"type":"Point"}
}