{
  "type": "Feature",
  "properties": {
    "addr:full":"Avgd Marques De Sant Mori, 181 Badalona Barcelona 08914",
    "addr:housenumber":"181",
    "addr:postcode":"08914",
    "addr:street":"Mori",
    "iso:country":"ES",
    "sg:address":"Avgd Marques De Sant Mori, 181",
    "sg:city":"Badalona",
    "sg:orig_category":"Bancos",
    "sg:phone":"+34 934 60 05 48",
    "sg:postcode":"08914",
    "sg:province":"Barcelona",
    "wof:name":"Banco Espa\u00f1ol De Credito S.a.",
    "wof:placetype":"venue"
},
  "geometry": {"coordinates":[2.2239289284,41.4424819946],"type":"Point"}
}