{
  "type": "Feature",
  "properties": {
    "iso:country":"ES",
    "sg:address":"Pase Calanda, 11",
    "sg:city":"Zaragoza",
    "sg:orig_category":"Filatelia",
    "sg:phone":"+34 976 32 46 04",
    "sg:postcode":"50010",
    "sg:province":"Zaragoza",
    "wof:name":"Aguilar Caballero Miguel",
    "wof:placetype":"venue"
},
  "geometry": {"coordinates":[-0.9044589996,41.6536140442],"type":"Point"}
}