{
  "type": "Feature",
  "properties": {
    "addr:full":"Calle de Huelva, S/n Minas Riotinto Huelva 21660",
    "addr:housenumber":"s / n",
    "addr:postcode":"21660",
    "addr:street":"Calle De Huelva",
    "iso:country":"ES",
    "sg:address":"Calle de Huelva, S/n",
    "sg:city":"Minas Riotinto",
    "sg:orig_category":"Enfermeras: Consultas, Atenci\u00d3n A Domicilio",
    "sg:phone":"+34 959 59 01 60",
    "sg:postcode":"21660",
    "sg:province":"Huelva",
    "wof:name":"Hernandez Delgado Dolores",
    "wof:placetype":"venue"
},
  "geometry": {"coordinates":[-6.6005711555,37.6935005188],"type":"Point"}
}