{
  "type": "Feature",
  "properties": {
    "addr:full":"Calle de Trafalgar, 3 Tarifa C\u00e1diz 11380",
    "addr:housenumber":"3",
    "addr:postcode":"11380",
    "addr:street":"Calle De Trafalgar;Ca\u0301Diz",
    "iso:country":"ES",
    "sg:address":"Calle de Trafalgar, 3",
    "sg:city":"Tarifa",
    "sg:orig_category":"M\u00c1rmoles, Granitos Y Piedras Naturales",
    "sg:phone":"+34 956 68 02 18",
    "sg:postcode":"11380",
    "sg:province":"C\u00e1diz",
    "wof:name":"Marmoles Orsa S.l.",
    "wof:placetype":"venue"
},
  "geometry": {"coordinates":[-5.6070241928,36.014377594],"type":"Point"}
}