{
  "type": "Feature",
  "properties": {
    "addr:full":"Calle de Villa Benavente, 1 Le\u00f3n Le\u00f3n 24003",
    "addr:housenumber":"1",
    "addr:postcode":"24003",
    "addr:street":"Calle De Villa Benavente;Leo\u0301N",
    "iso:country":"ES",
    "sg:address":"Calle de Villa Benavente, 1",
    "sg:city":"Le\u00f3n",
    "sg:orig_category":"Zapatos (al Por Menor)",
    "sg:phone":"+34 987 21 13 20",
    "sg:postcode":"24003",
    "sg:province":"Le\u00f3n",
    "wof:name":"Zapaterias Zeranda S.l.",
    "wof:placetype":"venue"
},
  "geometry": {"coordinates":[-5.5729489326,42.5957183838],"type":"Point"}
}