{
  "type": "Feature",
  "properties": {
    "iso:country":"ES",
    "sg:address":"Barr Muntsaratz, 36",
    "sg:city":"Muntsaratz",
    "sg:orig_category":"Vulcanizado",
    "sg:phone":"+34 946 20 29 85",
    "sg:postcode":"48220",
    "sg:province":"Vizcaya",
    "wof:name":"Nazaret Etxeandia Y Lourdes Etxeandia C.",
    "wof:placetype":"venue"
},
  "geometry": {"coordinates":[-2.6079039574,43.1692581177],"type":"Point"}
}