{
  "type": "Feature",
  "properties": {
    "addr:full":"Calle de Antonio Lekuona Kalea, 7 Tolosa Guip\u00f9zcoa 20400",
    "addr:housenumber":"7",
    "addr:postcode":"20400",
    "addr:street":"Calle De Antonio Lekuona Kalea;Guipu\u0300Zcoa",
    "iso:country":"ES",
    "sg:address":"Calle de Antonio Lekuona Kalea, 7",
    "sg:city":"Tolosa",
    "sg:orig_category":"Abogados",
    "sg:phone":"+34 943 11 90 32",
    "sg:postcode":"20400",
    "sg:province":"Guip\u00f9zcoa",
    "wof:name":"Zubiria Guzman Aitor Abogado",
    "wof:placetype":"venue"
},
  "geometry": {"coordinates":[-2.0742430687,43.137386322],"type":"Point"}
}