{
  "type": "Feature",
  "properties": {
    "iso:country":"ES",
    "sg:address":"Calle de Abdon Rodilla, 11",
    "sg:city":"Guijuelo",
    "sg:orig_category":"Promotores Constructores",
    "sg:phone":"+34 923 58 21 65",
    "sg:postcode":"37770",
    "sg:province":"Salamanca",
    "wof:name":"Construcciones Manuel Cardoso S.l.",
    "wof:placetype":"venue"
},
  "geometry": {"coordinates":[-5.6722769737,40.5580978394],"type":"Point"}
}