{
  "type": "Feature",
  "properties": {
    "addr:full":"Avda Menendez Pelayo, 42 Sevilla Sevilla 41003",
    "addr:housenumber":"42",
    "addr:postcode":"41003",
    "addr:street":"Avda Menendez Pelayo",
    "iso:country":"ES",
    "sg:address":"Avda Menendez Pelayo, 42",
    "sg:city":"Sevilla",
    "sg:orig_category":"Agencias De Viajes",
    "sg:phone":"+34 954 53 64 94",
    "sg:postcode":"41003",
    "sg:province":"Sevilla",
    "wof:name":"Viajes Iberia S.a.",
    "wof:placetype":"venue"
},
  "geometry": {"coordinates":[-5.9855489731,37.3866195679],"type":"Point"}
}