{
  "type": "Feature",
  "properties": {
    "iso:country":"ES",
    "sg:address":"Plaz Puerta Del Mar, S/n",
    "sg:city":"Adra",
    "sg:orig_category":"Ense\u00d1anza, Formaci\u00d3n Profesional: Aprendizaje",
    "sg:phone":"+34 950 40 04 00",
    "sg:postcode":"04770",
    "sg:province":"Almer\u00eda",
    "wof:name":"Ayuntamiento",
    "wof:placetype":"venue"
},
  "geometry": {"coordinates":[-3.0476045609,36.7753677368],"type":"Point"}
}