{
  "type": "Feature",
  "properties": {
    "iso:country":"ES",
    "sg:address":"Avda Buenos Aires, 12",
    "sg:city":"Escairon",
    "sg:orig_category":"Comerciantes Al Por Mayor De Vinos, Licores Y Alcoholes",
    "sg:phone":"+34 982 45 27 00",
    "sg:postcode":"27540",
    "sg:province":"Lugo",
    "sg:website":"www.abadiadacova.com",
    "wof:name":"Adegas Moure S.a.",
    "wof:placetype":"venue"
},
  "geometry": {"coordinates":[-7.639854908,42.5837554932],"type":"Point"}
}