{
  "type": "Feature",
  "properties": {
    "addr:full":"Rua Alcalde Carlos V. Pimentel, 3 Lugo Lugo 27004",
    "addr:housenumber":"3",
    "addr:postcode":"27004",
    "addr:street":"Rua Alcalde Carlos V. Pimentel",
    "iso:country":"ES",
    "sg:address":"Rua Alcalde Carlos V. Pimentel, 3",
    "sg:city":"Lugo",
    "sg:orig_category":"Promotores Constructores",
    "sg:phone":"+34 982 26 52 39",
    "sg:postcode":"27004",
    "sg:province":"Lugo",
    "wof:name":"Promociones Abuin Y Escolante S.l.",
    "wof:placetype":"venue"
},
  "geometry": {"coordinates":[-7.569381237,43.0095176697],"type":"Point"}
}