{
  "type": "Feature",
  "properties": {
    "iso:country":"ES",
    "sg:address":"Carrer de Pallars, 505",
    "sg:city":"Barcelona",
    "sg:orig_category":"Electricidad: Instaladores",
    "sg:phone":"+34 932 66 15 37",
    "sg:postcode":"08019",
    "sg:province":"Barcelona",
    "wof:name":"J.f.malfer S.l.",
    "wof:placetype":"venue"
},
  "geometry": {"coordinates":[2.2145409584,41.4139137268],"type":"Point"}
}