{
  "type": "Feature",
  "properties": {
    "iso:country":"ES",
    "sg:address":"Calle de San Juan De Ba\u00d1os, 1",
    "sg:city":"Ba\u00e7os De Cerrato",
    "sg:orig_category":"Iglesia Cat\u00d3lica",
    "sg:phone":"+34 979 77 03 38",
    "sg:postcode":"34200",
    "sg:province":"Palencia",
    "wof:name":"Parroquia De San Martin De Ba\u00f1os",
    "wof:placetype":"venue"
},
  "geometry": {"coordinates":[-4.4738078117,41.9207763672],"type":"Point"}
}