{
  "type": "Feature",
  "properties": {
    "addr:full":"Carrer de Santuari, 17 Barcelona Barcelona 08032",
    "addr:housenumber":"17",
    "addr:postcode":"08032",
    "addr:street":"Carrer De Santuari",
    "iso:country":"ES",
    "sg:address":"Carrer de Santuari, 17",
    "sg:city":"Barcelona",
    "sg:orig_category":"Zapatos (al Por Menor)",
    "sg:phone":"+34 934 20 96 67",
    "sg:postcode":"08032",
    "sg:province":"Barcelona",
    "wof:name":"Zarosa S.c.p.",
    "wof:placetype":"venue"
},
  "geometry": {"coordinates":[2.1503920555,41.4203567505],"type":"Point"}
}