{
  "type": "Feature",
  "properties": {
    "addr:full":"San Juan, 85 San Juan De Mozarrifar Zaragoza 50820",
    "addr:housenumber":"85",
    "addr:postcode":"50820",
    "addr:street":"San Juan;Juan;Mozarrifar",
    "iso:country":"ES",
    "sg:address":"San Juan, 85",
    "sg:city":"San Juan De Mozarrifar",
    "sg:orig_category":"Promotores Constructores",
    "sg:phone":"+34 976 15 10 15",
    "sg:postcode":"50820",
    "sg:province":"Zaragoza",
    "wof:name":"Construcciones San Juan De Mozarrifar S.l.",
    "wof:placetype":"venue"
},
  "geometry": {"coordinates":[-0.8356789947,41.7148780823],"type":"Point"}
}