{
  "type": "Feature",
  "properties": {
    "iso:country":"ES",
    "sg:address":"Ctra. S. Juan Puerto, Km. 0004,7",
    "sg:city":"Moguer",
    "sg:orig_category":"Sales (al Por Mayor)",
    "sg:phone":"+34 959 37 25 34",
    "sg:postcode":"21800",
    "sg:province":"Huelva",
    "wof:name":"Frutas Moguer S.l.",
    "wof:placetype":"venue"
},
  "geometry": {"coordinates":[-6.8296589851,37.2830352783],"type":"Point"}
}