{
  "type": "Feature",
  "properties": {
    "iso:country":"ES",
    "sg:address":"Avda Sur (del), 17",
    "sg:city":"Granada",
    "sg:orig_category":"Abogados",
    "sg:phone":"+34 958 28 30 79",
    "sg:postcode":"18014",
    "sg:province":"Granada",
    "wof:name":"Camino Marinetto Antonio",
    "wof:placetype":"venue"
},
  "geometry": {"coordinates":[-3.6135420799,37.1878013611],"type":"Point"}
}