{
  "type": "Feature",
  "properties": {
    "iso:country":"ES",
    "sg:address":"Cno. Real, 44",
    "sg:city":"Agua Garcia",
    "sg:orig_category":"Ense\u00d1anza, Formaci\u00d3n Profesional: Aprendizaje",
    "sg:phone":"+34 922 58 41 06",
    "sg:postcode":"38355",
    "sg:province":"Santa Cruz De Tenerife",
    "wof:name":"Cabildo Insular De Tenerife",
    "wof:placetype":"venue"
},
  "geometry": {"coordinates":[-16.3852138519,28.4702281952],"type":"Point"}
}