{
  "type": "Feature",
  "properties": {
    "iso:country":"ES",
    "sg:address":"Calle de Adelfas, 16",
    "sg:city":"Madrid",
    "sg:orig_category":"Aguas Termales",
    "sg:phone":"+34 915 02 03 43",
    "sg:postcode":"28007",
    "sg:province":"Madrid",
    "wof:name":"Terma Actual S.l.",
    "wof:placetype":"venue"
},
  "geometry": {"coordinates":[-3.671667099,40.4033050537],"type":"Point"}
}