{
  "type": "Feature",
  "properties": {
    "iso:country":"ES",
    "sg:address":"Urb Las Lindes I, S/n",
    "sg:city":"Muriedas",
    "sg:orig_category":"Agencias Y Agentes Comerciales, Representantes",
    "sg:phone":"+34 942 26 13 77",
    "sg:postcode":"39600",
    "sg:province":"Cantabria",
    "wof:name":"Diaz Sanchez Manuel",
    "wof:placetype":"venue"
},
  "geometry": {"coordinates":[-3.8458189964,43.4184341431],"type":"Point"}
}