{
  "type": "Feature",
  "properties": {
    "iso:country":"ES",
    "sg:address":"Avgd Alameda Jaume I, 7",
    "sg:city":"Xativa",
    "sg:orig_category":"Arquitectos",
    "sg:phone":"+34 962 27 50 15",
    "sg:postcode":"46800",
    "sg:province":"Valencia",
    "sg:website":"www.gruphac.com",
    "wof:name":"Gruphac S.c.",
    "wof:placetype":"venue"
},
  "geometry": {"coordinates":[-0.5237929821,38.9893226624],"type":"Point"}
}