{
  "type": "Feature",
  "properties": {
    "iso:country":"ES",
    "sg:address":"Calle de Manzana, 8",
    "sg:city":"Getafe",
    "sg:orig_category":"Centros Empresariales",
    "sg:phone":"+34 916 95 12 48",
    "sg:postcode":"28901",
    "sg:province":"Madrid",
    "wof:name":"Conversa Ccs S.l.u",
    "wof:placetype":"venue"
},
  "geometry": {"coordinates":[-3.7277829647,40.3079528809],"type":"Point"}
}