{
  "type": "Feature",
  "properties": {
    "addr:full":"Av Joan Miro, 38 Palma Islas Baleares 07014",
    "addr:housenumber":"38",
    "addr:postcode":"07014",
    "addr:street":"Av Joan Miro",
    "iso:country":"ES",
    "sg:address":"Av Joan Miro, 38",
    "sg:city":"Palma",
    "sg:orig_category":"Molduras, Junquillos, Listones Y Molduras Perforadas",
    "sg:phone":"+34 971 45 40 30",
    "sg:postcode":"07014",
    "sg:province":"Islas Baleares",
    "wof:name":"Rullan Ripoll Bernardo",
    "wof:placetype":"venue"
},
  "geometry": {"coordinates":[2.6257410049,39.5637207031],"type":"Point"}
}