{
  "type": "Feature",
  "properties": {
    "addr:full":"Carrer de Sant Marc, 77 Terrassa Barcelona 08224",
    "addr:housenumber":"77",
    "addr:postcode":"08224",
    "addr:street":"Carrer De Sant Marc",
    "iso:country":"ES",
    "sg:address":"Carrer de Sant Marc, 77",
    "sg:city":"Terrassa",
    "sg:orig_category":"Peluquer\u00cdas, Peluquer\u00cda Mixta",
    "sg:phone":"+34 937 33 19 45",
    "sg:postcode":"08224",
    "sg:province":"Barcelona",
    "wof:name":"Gijon Pacheco Julian",
    "wof:placetype":"venue"
},
  "geometry": {"coordinates":[1.9999309778,41.5641174316],"type":"Point"}
}