{
  "type": "Feature",
  "properties": {
    "addr:full":"Calle de Deire, S/n Torrox M\u00e1laga 29770",
    "addr:housenumber":"s / n",
    "addr:postcode":"29770",
    "addr:street":"Calle De Deire",
    "iso:country":"ES",
    "sg:address":"Calle de Deire, S/n",
    "sg:city":"Torrox",
    "sg:classifiers":[
        {
            "category":"Taxi",
            "type":"Transportation"
        }
    ],
    "sg:phone":"+34 952 53 89 10",
    "sg:postcode":"29770",
    "sg:province":"M\u00e1laga",
    "wof:name":"Garcia Fernandez Ana Ester",
    "wof:placetype":"venue"
},
  "geometry": {"coordinates":[-3.9572374821,36.7701911926],"type":"Point"}
}