{
  "type": "Feature",
  "properties": {
    "addr:full":"Calle de Doctor Benitez, 25 A\u00d1ora C\u00f3rdoba 14450",
    "addr:housenumber":"25",
    "addr:postcode":"14450",
    "addr:street":"Calle De Doctor Benitez;Co\u0301Rdoba",
    "iso:country":"ES",
    "sg:address":"Calle de Doctor Benitez, 25",
    "sg:city":"A\u00d1ora",
    "sg:orig_category":"T\u00c9cnicos Veterinarios",
    "sg:phone":"+34 957 15 10 62",
    "sg:postcode":"14450",
    "sg:province":"C\u00f3rdoba",
    "wof:name":"Garcia Rodriguez Francico",
    "wof:placetype":"venue"
},
  "geometry": {"coordinates":[-4.8990364075,38.4115371704],"type":"Point"}
}