{
  "type": "Feature",
  "properties": {
    "iso:country":"ES",
    "sg:address":"Calle de Fundicion, S/n",
    "sg:city":"Rodalquilar",
    "sg:orig_category":"Formaci\u00d3n Continuada (variada)",
    "sg:phone":"+34 950 38 97 18",
    "sg:postcode":"04115",
    "sg:province":"Almer\u00eda",
    "wof:name":"Fundacion Andaluza Fondo De Formacion Y Empleo",
    "wof:placetype":"venue"
},
  "geometry": {"coordinates":[-2.0429375172,36.8472824097],"type":"Point"}
}