{
  "type": "Feature",
  "properties": {
    "iso:country":"ES",
    "sg:address":"Carrer de Rosari, 3",
    "sg:city":"Barcelona",
    "sg:orig_category":"Productos Qu\u00cdmicos (fabricaci\u00d3n, Al Por Mayor)",
    "sg:phone":"+34 932 03 18 19",
    "sg:postcode":"08017",
    "sg:province":"Barcelona",
    "wof:name":"Ortoquimica S. A.",
    "wof:placetype":"venue"
},
  "geometry": {"coordinates":[2.128344059,41.3956871033],"type":"Point"}
}