{
  "type": "Feature",
  "properties": {
    "iso:country":"ES",
    "sg:address":"Calle de Candeleria, 34",
    "sg:city":"Sevilla",
    "sg:classifiers":[
        {
            "category":"Autos & Motor Vehicles",
            "subcategory":"Automobile Sales",
            "type":"Retail Goods"
        }
    ],
    "sg:phone":"+34 954 65 94 10",
    "sg:postcode":"41006",
    "sg:province":"Sevilla",
    "wof:name":"Gutierrez Paez Francisco",
    "wof:placetype":"venue"
},
  "geometry": {"coordinates":[-5.9538087845,37.3826255798],"type":"Point"}
}