{
  "type": "Feature",
  "properties": {
    "addr:full":"Carrer de Alcalde Joan Bertran, 11 Reus Tarragona 43202",
    "addr:housenumber":"11",
    "addr:postcode":"43202",
    "addr:street":"Carrer De Alcalde Joan Bertran",
    "iso:country":"ES",
    "sg:address":"Carrer de Alcalde Joan Bertran, 11",
    "sg:city":"Reus",
    "sg:orig_category":"Artes Gr\u00c1ficas, Artes Pl\u00c1sticas (curso)",
    "sg:phone":"+34 977 31 12 16",
    "sg:postcode":"43202",
    "sg:province":"Tarragona",
    "wof:name":"Purroy Impressions S.l.",
    "wof:placetype":"venue"
},
  "geometry": {"coordinates":[1.1019010544,41.1507987976],"type":"Point"}
}