{
  "type": "Feature",
  "properties": {
    "iso:country":"ES",
    "sg:address":"C/ Angel, 16",
    "sg:city":"Elche",
    "sg:orig_category":"Carnes De Carnicer\u00cda (al Por Mayor)",
    "sg:phone":"+34 966 61 15 45",
    "sg:postcode":"03203",
    "sg:province":"Alicante",
    "wof:name":"Macia Vicente Maria Asuncion",
    "wof:placetype":"venue"
},
  "geometry": {"coordinates":[-0.6977289915,38.2624893188],"type":"Point"}
}