{
  "type": "Feature",
  "properties": {
    "iso:country":"ES",
    "sg:address":"Plaz Numancia, 3",
    "sg:city":"Santander",
    "sg:orig_category":"Parques De Atracciones Y Centros De Esparcimiento",
    "sg:phone":"+34 942 37 12 50",
    "sg:postcode":"39007",
    "sg:province":"Cantabria",
    "wof:name":"Gomarbol S.l.",
    "wof:placetype":"venue"
},
  "geometry": {"coordinates":[-3.8178400993,43.4613075256],"type":"Point"}
}