{
  "type": "Feature",
  "properties": {
    "iso:country":"ES",
    "sg:address":"Calle de Basaldua, 1",
    "sg:city":"Algorta",
    "sg:orig_category":"Peluqueros: De Se\u00d1oras",
    "sg:phone":"+34 944 60 22 71",
    "sg:postcode":"48993",
    "sg:province":"Vizcaya",
    "wof:name":"Juan Quintano Maria Del Carmen De",
    "wof:placetype":"venue"
},
  "geometry": {"coordinates":[-3.0158529282,43.3521957397],"type":"Point"}
}