{
  "type": "Feature",
  "properties": {
    "iso:country":"ES",
    "sg:address":"Calle de Santiago, 33",
    "sg:city":"Alburquerque",
    "sg:orig_category":"Bebidas",
    "sg:phone":"+34 924 40 01 10",
    "sg:postcode":"06510",
    "sg:province":"Badajoz",
    "wof:name":"Antonio Cabrera Mendez Y Otro C.b.",
    "wof:placetype":"venue"
},
  "geometry": {"coordinates":[-6.9948868752,39.2207183838],"type":"Point"}
}