{
  "type": "Feature",
  "properties": {
    "addr:full":"Ctra Palma Del Rio (villarrubia), Km. 0010,4 Villarrubia C\u00f3rdoba 14710",
    "addr:postcode":"14710",
    "addr:street":"Ctra Palma Del Rio Villarrubia Km. 0010,4 Villarrubia Co\u0301Rdoba",
    "iso:country":"ES",
    "sg:address":"Ctra Palma Del Rio (villarrubia), Km. 0010,4",
    "sg:city":"Villarrubia",
    "sg:orig_category":"Aceites Y Grasas Alimentarias (fabricaci\u00d3n, Al Por Mayor)",
    "sg:phone":"+34 957 45 84 33",
    "sg:postcode":"14710",
    "sg:province":"C\u00f3rdoba",
    "wof:name":"Apaprol Cordoliva",
    "wof:placetype":"venue"
},
  "geometry": {"coordinates":[-4.9000496864,37.8542518616],"type":"Point"}
}