{
  "type": "Feature",
  "properties": {
    "addr:full":"Calle de Guindos (de Los), 5 San Sebastian De Los Reyes Madrid 28700",
    "addr:housenumber":"5",
    "addr:postcode":"28700",
    "addr:street":"Calle De Guindos De Los",
    "iso:country":"ES",
    "sg:address":"Calle de Guindos (de Los), 5",
    "sg:city":"San Sebastian De Los Reyes",
    "sg:orig_category":"Laboratorios Y Trabajos De Fotograf\u00cda, V\u00cddeo Y Cine",
    "sg:phone":"+34 916 54 32 03",
    "sg:postcode":"28700",
    "sg:province":"Madrid",
    "wof:name":"Estudio Fotografico Futurlab S.l.",
    "wof:placetype":"venue"
},
  "geometry": {"coordinates":[-3.6197841167,40.5470123291],"type":"Point"}
}