{
  "type": "Feature",
  "properties": {
    "iso:country":"ES",
    "sg:address":"Calle de Aneto, 13",
    "sg:city":"Fuenlabrada",
    "sg:orig_category":"Cojinetes De Bolas, Agujas Y Rodillos (fabricaci\u00d3n, Al Por Mayor)",
    "sg:phone":"+34 916 06 50 10",
    "sg:postcode":"28944",
    "sg:province":"Madrid",
    "wof:name":"Rodaimport S. A.",
    "wof:placetype":"venue"
},
  "geometry": {"coordinates":[-3.8019714355,40.2792510986],"type":"Point"}
}