{
  "type": "Feature",
  "properties": {
    "iso:country":"ES",
    "sg:address":"Via Laietana, 20",
    "sg:city":"Barcelona",
    "sg:orig_category":"Relojer\u00cda (al Por Menor, Reparaci\u00d3n)",
    "sg:phone":"+34 934 86 75 00",
    "sg:postcode":"08...",
    "sg:province":"Barcelona",
    "wof:name":"Festina Lotus S.a.",
    "wof:placetype":"venue"
},
  "geometry": {"coordinates":[2.1788840294,41.3839569092],"type":"Point"}
}