{
  "type": "Feature",
  "properties": {
    "iso:country":"ES",
    "sg:address":"El Burrero, 1",
    "sg:city":"Galdar",
    "sg:orig_category":"Apicultura",
    "sg:phone":"+34 928 88 30 40",
    "sg:postcode":"35460",
    "sg:province":"Las Palmas",
    "wof:name":"Medina Rodriguez Carlos",
    "wof:placetype":"venue"
},
  "geometry": {"coordinates":[-15.6528720856,28.1450138092],"type":"Point"}
}