{
  "type": "Feature",
  "properties": {
    "iso:country":"ES",
    "sg:address":"Calle de Ines (la), 42",
    "sg:city":"Arrecife",
    "sg:orig_category":"Abogados",
    "sg:phone":"+34 928 81 75 25",
    "sg:postcode":"35500",
    "sg:province":"Las Palmas",
    "wof:name":"Gonzalez Gonzalez Carmen",
    "wof:placetype":"venue"
},
  "geometry": {"coordinates":[-13.5526638031,28.961057663],"type":"Point"}
}