{
  "type": "Feature",
  "properties": {
    "addr:full":"Calle de Padilla, 8 Ecija Sevilla 41400",
    "addr:housenumber":"8",
    "addr:postcode":"41400",
    "addr:street":"Calle De Padilla",
    "iso:country":"ES",
    "sg:address":"Calle de Padilla, 8",
    "sg:city":"Ecija",
    "sg:orig_category":"M\u00c9dicos: Estomatolog\u00cda",
    "sg:phone":"+34 955 90 05 18",
    "sg:postcode":"41400",
    "sg:province":"Sevilla",
    "wof:name":"Fernandez De Mesa Y Coca Manuel",
    "wof:placetype":"venue"
},
  "geometry": {"coordinates":[-5.0776982307,37.5382347107],"type":"Point"}
}