{
  "type": "Feature",
  "properties": {
    "iso:country":"ES",
    "sg:address":"C/ Ramon Llull, 64",
    "sg:city":"Llucmajor",
    "sg:orig_category":"Electricidad: Instaladores",
    "sg:phone":"+34 971 66 06 08",
    "sg:postcode":"07620",
    "sg:province":"Islas Baleares",
    "wof:name":"Calafat Juan Cristobal",
    "wof:placetype":"venue"
},
  "geometry": {"coordinates":[2.8689489365,39.4487228394],"type":"Point"}
}