{
  "type": "Feature",
  "properties": {
    "iso:country":"ES",
    "sg:address":"Calle de Calvo Sotelo, S/n",
    "sg:city":"Ampuero",
    "sg:orig_category":"Empresas De Carpinter\u00cda De Madera",
    "sg:phone":"+34 942 62 20 98",
    "sg:postcode":"39840",
    "sg:province":"Cantabria",
    "wof:name":"Secunza Claramunt Leandro",
    "wof:placetype":"venue"
},
  "geometry": {"coordinates":[-3.4161789417,43.3421478271],"type":"Point"}
}