{
  "type": "Feature",
  "properties": {
    "addr:full":"Av Principat D'andorra (del), 11 Salou Tarragona 43840",
    "addr:housenumber":"11",
    "addr:postcode":"43840",
    "addr:street":"Av Principat D'Andorra Del",
    "iso:country":"ES",
    "sg:address":"Av Principat D'andorra (del), 11",
    "sg:city":"Salou",
    "sg:orig_category":"Ropa De Hogar (al Por Menor)",
    "sg:phone":"+34 977 38 10 59",
    "sg:postcode":"43840",
    "sg:province":"Tarragona",
    "wof:name":"Caselli Gianni Giancarlo",
    "wof:placetype":"venue"
},
  "geometry": {"coordinates":[1.1443450451,41.0744247437],"type":"Point"}
}