{
  "type": "Feature",
  "properties": {
    "addr:full":"Calle de Reyes Catolicos, 47 Alacant Alicante 03003",
    "addr:housenumber":"47",
    "addr:postcode":"03003",
    "addr:street":"Calle De Reyes Catolicos",
    "iso:country":"ES",
    "sg:address":"Calle de Reyes Catolicos, 47",
    "sg:city":"Alacant",
    "sg:orig_category":"Supermercados Y Hipermercados",
    "sg:phone":"+34 965 12 27 76",
    "sg:postcode":"03003",
    "sg:province":"Alicante",
    "sg:website":"www.mercadona.es",
    "wof:name":"Mercadona S A",
    "wof:placetype":"venue"
},
  "geometry": {"coordinates":[-0.4920290112,38.3415374756],"type":"Point"}
}