{
  "type": "Feature",
  "properties": {
    "iso:country":"ES",
    "sg:address":"Avda Reyes Catolicos, 26",
    "sg:city":"Burgos",
    "sg:orig_category":"Abogados",
    "sg:phone":"+34 947 22 32 21",
    "sg:postcode":"09005",
    "sg:province":"Burgos",
    "wof:name":"Crespo Martinez Maria Elena",
    "wof:placetype":"venue"
},
  "geometry": {"coordinates":[-3.6928970814,42.3473930359],"type":"Point"}
}