{
  "type": "Feature",
  "properties": {
    "addr:full":"Carrer de Doctor Trueta, 1 Castelldefels Barcelona 08860",
    "addr:housenumber":"1",
    "addr:postcode":"08860",
    "addr:street":"Carrer De Doctor Trueta",
    "iso:country":"ES",
    "sg:address":"Carrer de Doctor Trueta, 1",
    "sg:city":"Castelldefels",
    "sg:orig_category":"Bisuter\u00cda, Joyer\u00cda, Relojer\u00cda (al Por Menor)",
    "sg:phone":"+34 936 64 01 50",
    "sg:postcode":"08860",
    "sg:province":"Barcelona",
    "wof:name":"Royo Garcia Manuel",
    "wof:placetype":"venue"
},
  "geometry": {"coordinates":[1.9776829481,41.2788124084],"type":"Point"}
}