{
  "type": "Feature",
  "properties": {
    "iso:country":"ES",
    "sg:address":"Padre Pedro De Benisa, 8",
    "sg:city":"Benissa",
    "sg:orig_category":"Farmacias",
    "sg:phone":"+34 965 73 40 04",
    "sg:postcode":"03720",
    "sg:province":"Alicante",
    "wof:name":"Mu\u00f1oz Iborra Mario Solon",
    "wof:placetype":"venue"
},
  "geometry": {"coordinates":[0.050774999,38.7144584656],"type":"Point"}
}