{
  "type": "Feature",
  "properties": {
    "addr:full":"Poli Las Capellanias, 30 Caceres C\u00e1ceres 10005",
    "addr:housenumber":"30",
    "addr:postcode":"10005",
    "addr:street":"Capellanias;Ca\u0301Ceres",
    "iso:country":"ES",
    "sg:address":"Poli Las Capellanias, 30",
    "sg:city":"Caceres",
    "sg:orig_category":"Veh\u00cdculos De Ocasi\u00d3n",
    "sg:phone":"+34 927 26 98 71",
    "sg:postcode":"10005",
    "sg:province":"C\u00e1ceres",
    "sg:website":"www.euromovilextremadura.com",
    "wof:name":"Euromovil Extremadura S.c.",
    "wof:placetype":"venue"
},
  "geometry": {"coordinates":[-6.5341739655,39.4675254822],"type":"Point"}
}