{
  "type": "Feature",
  "properties": {
    "addr:full":"Carr Jaume I, De, 6 Esporles Islas Baleares 07190",
    "addr:housenumber":"6",
    "addr:postcode":"07190",
    "addr:street":"Carr Jaume I De",
    "iso:country":"ES",
    "sg:address":"Carr Jaume I, De, 6",
    "sg:city":"Esporles",
    "sg:orig_category":"Ense\u00d1ante, Direcci\u00d3n",
    "sg:phone":"+34 971 61 92 02",
    "sg:postcode":"07190",
    "sg:province":"Islas Baleares",
    "wof:name":"Consultors Tributaris I Comptables S.l.",
    "wof:placetype":"venue"
},
  "geometry": {"coordinates":[2.5779759884,39.667350769],"type":"Point"}
}