{
  "type": "Feature",
  "properties": {
    "iso:country":"ES",
    "sg:address":"Trva Mayor, 1",
    "sg:city":"Cabezarrubias Del Puerto",
    "sg:orig_category":"Centros De Educaci\u00d3n Especial",
    "sg:phone":"+34 926 47 62 75",
    "sg:postcode":"13591",
    "sg:province":"Ciudad Real",
    "sg:website":"www.jccm.es/edu/cra/vallealcudia",
    "wof:name":"Colegio Rural Agrupado Valle Alcudia",
    "wof:placetype":"venue"
},
  "geometry": {"coordinates":[-4.184317112,38.6145133972],"type":"Point"}
}