{
  "type": "Feature",
  "properties": {
    "addr:full":"Calle de Juan Xxiii, 22 Librilla Murcia 30892",
    "addr:housenumber":"22",
    "addr:postcode":"30892",
    "addr:street":"Calle De Juan Xxiii",
    "iso:country":"ES",
    "sg:address":"Calle de Juan Xxiii, 22",
    "sg:city":"Librilla",
    "sg:orig_category":"Supermercados Y Hipermercados",
    "sg:phone":"+34 968 65 91 04",
    "sg:postcode":"30892",
    "sg:province":"Murcia",
    "wof:name":"Carnicas Antonio Ruiz S.l.",
    "wof:placetype":"venue"
},
  "geometry": {"coordinates":[-1.3533129692,37.8854866028],"type":"Point"}
}