{
  "type": "Feature",
  "properties": {
    "addr:full":"Calle de Mayor, 45 Alcantarilla Murcia 30820",
    "addr:housenumber":"45",
    "addr:postcode":"30820",
    "addr:street":"Calle De Mayor",
    "iso:country":"ES",
    "sg:address":"Calle de Mayor, 45",
    "sg:city":"Alcantarilla",
    "sg:orig_category":"Estancos",
    "sg:phone":"+34 968 80 21 87",
    "sg:postcode":"30820",
    "sg:province":"Murcia",
    "wof:name":"Martinez Martinez Rafael",
    "wof:placetype":"venue"
},
  "geometry": {"coordinates":[-1.2106399536,37.9715461731],"type":"Point"}
}