{
  "type": "Feature",
  "properties": {
    "iso:country":"ES",
    "sg:address":"C/ Maria Auxiliadora, 6",
    "sg:city":"Tossa",
    "sg:orig_category":"Electrodom\u00c9sticos (al Por Menor)",
    "sg:phone":"+34 972 34 03 42",
    "sg:postcode":"17320",
    "sg:province":"Girona",
    "wof:name":"Tort Ribas Pedro",
    "wof:placetype":"venue"
},
  "geometry": {"coordinates":[2.9300580025,41.7204551697],"type":"Point"}
}