{
  "type": "Feature",
  "properties": {
    "addr:full":"Psaj Doctor Serra, 12 Valencia Valencia 46004",
    "addr:housenumber":"12",
    "addr:postcode":"46004",
    "addr:street":"Doctor Serra",
    "iso:country":"ES",
    "sg:address":"Psaj Doctor Serra, 12",
    "sg:city":"Valencia",
    "sg:orig_category":"Abogados",
    "sg:phone":"+34 963 51 51 70",
    "sg:postcode":"46004",
    "sg:province":"Valencia",
    "wof:name":"Pardos Algarra Vicente",
    "wof:placetype":"venue"
},
  "geometry": {"coordinates":[-0.3758620024,39.4657669067],"type":"Point"}
}