{
  "type": "Feature",
  "properties": {
    "addr:full":"Calle de Alcalde Pedro Gonzalez Gonzalez, 17 Leganes Madrid 28914",
    "addr:housenumber":"17",
    "addr:postcode":"28914",
    "addr:street":"Calle De Alcalde Pedro Gonzalez Gonzalez",
    "iso:country":"ES",
    "sg:address":"Calle de Alcalde Pedro Gonzalez Gonzalez, 17",
    "sg:city":"Leganes",
    "sg:orig_category":"Cajas De Ahorro",
    "sg:phone":"+34 916 48 51 11",
    "sg:postcode":"28914",
    "sg:province":"Madrid",
    "wof:name":"Caja De Ahorros Y Monte De Piedad De Zaragoza Aragon Y Rioja",
    "wof:placetype":"venue"
},
  "geometry": {"coordinates":[-3.7861731052,40.3167304993],"type":"Point"}
}