{
  "type": "Feature",
  "properties": {
    "addr:full":"Avda Victoria, 126 Madrid Madrid 28...",
    "addr:housenumber":"126;28 ...",
    "addr:street":"Avda Victoria;Madrid",
    "iso:country":"ES",
    "sg:address":"Avda Victoria, 126",
    "sg:city":"Madrid",
    "sg:orig_category":"Agencias De Viajes",
    "sg:phone":"+34 916 02 43 00",
    "sg:postcode":"28...",
    "sg:province":"Madrid",
    "sg:website":"www.surland.com",
    "wof:name":"Click S.a.",
    "wof:placetype":"venue"
},
  "geometry": {"coordinates":[-3.8334600925,40.473903656],"type":"Point"}
}