{
  "type": "Feature",
  "properties": {
    "addr:full":"Rua Ramon Valle Inclan, 3 Vigo Pontevedra 36203",
    "addr:housenumber":"3",
    "addr:postcode":"36203",
    "addr:street":"Rua Ramon Valle Inclan",
    "iso:country":"ES",
    "sg:address":"Rua Ramon Valle Inclan, 3",
    "sg:city":"Vigo",
    "sg:orig_category":"Supermercados Y Hipermercados",
    "sg:phone":"+34 986 48 28 50",
    "sg:postcode":"36203",
    "sg:province":"Pontevedra",
    "wof:name":"Pereira Rodriguez Trinidad",
    "wof:placetype":"venue"
},
  "geometry": {"coordinates":[-8.7215795517,42.227645874],"type":"Point"}
}