{
  "type": "Feature",
  "properties": {
    "iso:country":"ES",
    "sg:address":"H. Tableada, 15",
    "sg:city":"Ca\u00f1ada San Urbano",
    "sg:orig_category":"Paisajistas Asesor\u00cda",
    "sg:phone":"+34 950 29 36 45",
    "sg:postcode":"04120",
    "sg:province":"Almer\u00eda",
    "wof:name":"Japrotec Andalucia S.l",
    "wof:placetype":"venue"
},
  "geometry": {"coordinates":[-2.389688015,36.8369255066],"type":"Point"}
}