{
  "type": "Feature",
  "properties": {
    "addr:full":"Avda Estacion, 5 Campo De San Pedro Segovia 40551",
    "addr:housenumber":"5",
    "addr:postcode":"40551",
    "addr:street":"Avda Estacion",
    "iso:country":"ES",
    "sg:address":"Avda Estacion, 5",
    "sg:city":"Campo De San Pedro",
    "sg:orig_category":"Producci\u00d3n, Comercio De Cereales",
    "sg:phone":"+34 921 55 62 26",
    "sg:postcode":"40551",
    "sg:province":"Segovia",
    "wof:name":"Comercial Gutierrez Martin S.a.",
    "wof:placetype":"venue"
},
  "geometry": {"coordinates":[-3.5433940887,41.4308547974],"type":"Point"}
}