{
  "type": "Feature",
  "properties": {
    "addr:full":"Carrer de Providencia, 1 Barcelona Barcelona 08024",
    "addr:housenumber":"1",
    "addr:postcode":"08024",
    "addr:street":"Carrer De Providencia",
    "iso:country":"ES",
    "sg:address":"Carrer de Providencia, 1",
    "sg:city":"Barcelona",
    "sg:orig_category":"Electrodom\u00c9sticos (al Por Menor)",
    "sg:phone":"+34 932 17 72 02",
    "sg:postcode":"08024",
    "sg:province":"Barcelona",
    "wof:name":"Sala Aguilo Jose Luis",
    "wof:placetype":"venue"
},
  "geometry": {"coordinates":[2.1551589966,41.405620575],"type":"Point"}
}