{
  "type": "Feature",
  "properties": {
    "iso:country":"ES",
    "sg:address":"Calle de Campos Crespo, 36",
    "sg:city":"Valencia",
    "sg:orig_category":"Molduras, Junquillos, Listones Y Molduras Perforadas",
    "sg:phone":"+34 963 77 48 28",
    "sg:postcode":"46014",
    "sg:province":"Valencia",
    "wof:name":"Castilla Cabrera Manuel",
    "wof:placetype":"venue"
},
  "geometry": {"coordinates":[-0.3963727057,39.4558830261],"type":"Point"}
}