{
  "type": "Feature",
  "properties": {
    "iso:country":"ES",
    "sg:address":"Calle de Senda De Abajo, S/n",
    "sg:city":"Ausejo",
    "sg:orig_category":"Poller\u00cda Y Caza (al Por Menor)",
    "sg:phone":"+34 941 74 01 21",
    "sg:postcode":"26513",
    "sg:province":"La Rioja",
    "wof:name":"Alfredo San Juan Espinosa Y Otra S.c.",
    "wof:placetype":"venue"
},
  "geometry": {"coordinates":[-2.1686069965,42.346206665],"type":"Point"}
}