{
  "type": "Feature",
  "properties": {
    "iso:country":"ES",
    "sg:address":"Calle de Langreo, 3",
    "sg:city":"Benidorm",
    "sg:orig_category":"Tintes (fabricaci\u00d3n, Al Por Mayor)",
    "sg:phone":"+34 965 86 86 60",
    "sg:postcode":"03500",
    "sg:province":"Alicante",
    "wof:name":"Ecoseco C.b.",
    "wof:placetype":"venue"
},
  "geometry": {"coordinates":[-0.164921999,38.5319213867],"type":"Point"}
}