{
  "type": "Feature",
  "properties": {
    "iso:country":"ES",
    "sg:address":"Avda Severo Ochoa, 16",
    "sg:city":"Marbella",
    "sg:orig_category":"Agencias Y Agentes Comerciales, Representantes",
    "sg:phone":"+34 952 92 40 02",
    "sg:postcode":"29600",
    "sg:province":"M\u00e1laga",
    "wof:name":"Frason Promotores S.l.",
    "wof:placetype":"venue"
},
  "geometry": {"coordinates":[-4.8789467812,36.508846283],"type":"Point"}
}