{
  "type": "Feature",
  "properties": {
    "iso:country":"ES",
    "sg:address":"Calle de Narciso Serra, 22",
    "sg:city":"Madrid",
    "sg:orig_category":"Ropa Para Se\u00d1oras (al Por Menor)",
    "sg:phone":"+34 915 52 49 30",
    "sg:postcode":"28007",
    "sg:province":"Madrid",
    "wof:name":"Perez Arrojo Adrian",
    "wof:placetype":"venue"
},
  "geometry": {"coordinates":[-3.6782739162,40.4054794312],"type":"Point"}
}