{
  "type": "Feature",
  "properties": {
    "iso:country":"ES",
    "sg:address":"Carrer de Puigmarti, 44",
    "sg:city":"Barcelona",
    "sg:orig_category":"Carnicer\u00cdas, Carnicer\u00cdas",
    "sg:phone":"+34 932 13 68 65",
    "sg:postcode":"08012",
    "sg:province":"Barcelona",
    "wof:name":"Els Artesans Del 1930 S.l.",
    "wof:placetype":"venue"
},
  "geometry": {"coordinates":[2.160574913,41.4022254944],"type":"Point"}
}