{
  "type": "Feature",
  "properties": {
    "addr:full":"Avda Guipuzcoa, S/n Berriozar Navarra 31013",
    "addr:housenumber":"s / n",
    "addr:postcode":"31013",
    "addr:street":"Avda Guipuzcoa",
    "iso:country":"ES",
    "sg:address":"Avda Guipuzcoa, S/n",
    "sg:city":"Berriozar",
    "sg:orig_category":"Contenedores (mercanc\u00cdas)",
    "sg:phone":"+34 948 30 25 89",
    "sg:postcode":"31013",
    "sg:province":"Navarra",
    "wof:name":"Agrunatra S.coop.",
    "wof:placetype":"venue"
},
  "geometry": {"coordinates":[-1.6711331606,42.8351287842],"type":"Point"}
}