{
  "type": "Feature",
  "properties": {
    "iso:country":"ES",
    "sg:address":"Ctra Guixa, 6",
    "sg:city":"Vic",
    "sg:orig_category":"Delegados, Agentes De Tr\u00c1nsito, Auxiliares De Transporte Internacional",
    "sg:phone":"+34 938 83 37 61",
    "sg:postcode":"08500",
    "sg:province":"Barcelona",
    "wof:name":"Almato Comermo Joan",
    "wof:placetype":"venue"
},
  "geometry": {"coordinates":[2.2530779839,41.9243927002],"type":"Point"}
}