{
  "type": "Feature",
  "properties": {
    "iso:country":"ES",
    "sg:address":"Barranco (p I Salinas San Jose), 11",
    "sg:city":"Pto Sta Maria",
    "sg:orig_category":"Empresas De Carpinter\u00cda Met\u00c1lica",
    "sg:phone":"+34 956 87 60 14",
    "sg:postcode":"11500",
    "sg:province":"C\u00e1diz",
    "wof:name":"Aluminios Victor Arias S.l.",
    "wof:placetype":"venue"
},
  "geometry": {"coordinates":[-6.2072963715,36.6076889038],"type":"Point"}
}