{
  "type": "Feature",
  "properties": {
    "addr:full":"Rua Saavedra Meneses, 103 Betanzos La Coru\u00f1a 15300",
    "addr:housenumber":"103",
    "addr:postcode":"15300",
    "addr:street":"Rua Saavedra Meneses;La",
    "iso:country":"ES",
    "sg:address":"Rua Saavedra Meneses, 103",
    "sg:city":"Betanzos",
    "sg:orig_category":"Empresas De Pintura Y Revestimientos",
    "sg:phone":"+34 981 77 23 99",
    "sg:postcode":"15300",
    "sg:province":"La Coru\u00f1a",
    "wof:name":"Garcia Prados Andres",
    "wof:placetype":"venue"
},
  "geometry": {"coordinates":[-8.2083129883,43.2855796814],"type":"Point"}
}