{
  "type": "Feature",
  "properties": {
    "addr:full":"Calle de Bri\u00d1as Luis, 11 Bilbao Vizcaya 48013",
    "addr:housenumber":"11",
    "addr:postcode":"48013",
    "addr:street":"Calle De Brin\u0303As Luis",
    "iso:country":"ES",
    "sg:address":"Calle de Bri\u00d1as Luis, 11",
    "sg:city":"Bilbao",
    "sg:orig_category":"Molduras, Junquillos, Listones Y Molduras Perforadas",
    "sg:phone":"+34 944 42 28 24",
    "sg:postcode":"48013",
    "sg:province":"Vizcaya",
    "wof:name":"Aparicio Turrado Jose Manuel",
    "wof:placetype":"venue"
},
  "geometry": {"coordinates":[-2.9478478432,43.2626876831],"type":"Point"}
}