{
  "type": "Feature",
  "properties": {
    "iso:country":"ES",
    "sg:address":"Pase Bertsol. Txirrita, 14",
    "sg:city":"Donostia-san Sebastian",
    "sg:orig_category":"Carnicer\u00cdas, Carnicer\u00cdas",
    "sg:phone":"+34 943 39 29 40",
    "sg:postcode":"20017",
    "sg:province":"Guip\u00f9zcoa",
    "wof:name":"Illarramendi Balerdi Imanol",
    "wof:placetype":"venue"
},
  "geometry": {"coordinates":[-1.9387940168,43.3144302368],"type":"Point"}
}