{
  "type": "Feature",
  "properties": {
    "addr:full":"Ctra Santander, Km. 0020,7 Monzon De Campos Palencia 34410",
    "addr:postcode":"34410",
    "addr:street":"Ctra Santander Km. 0020,7",
    "iso:country":"ES",
    "sg:address":"Ctra Santander, Km. 0020,7",
    "sg:city":"Monzon De Campos",
    "sg:orig_category":"Distribuci\u00d3n De Petr\u00d3leo Y Derivados",
    "sg:phone":"+34 979 80 80 26",
    "sg:postcode":"34410",
    "sg:province":"Palencia",
    "wof:name":"Vega Melendre Laura",
    "wof:placetype":"venue"
},
  "geometry": {"coordinates":[-4.4906082153,42.116268158],"type":"Point"}
}