{
  "type": "Feature",
  "properties": {
    "iso:country":"ES",
    "sg:address":"Avda Constitucion, 86",
    "sg:city":"Jaraiz Vera",
    "sg:orig_category":"Fabricaci\u00d3n De Productos L\u00c1cteos Y Derivados",
    "sg:phone":"+34 927 17 01 41",
    "sg:postcode":"10400",
    "sg:province":"C\u00e1ceres",
    "wof:name":"Alonso Carbajosa Gonzalo",
    "wof:placetype":"venue"
},
  "geometry": {"coordinates":[-5.753610611,40.0597381592],"type":"Point"}
}