{
  "type": "Feature",
  "properties": {
    "iso:country":"ES",
    "sg:address":"Rbla Anselm Clave, 37",
    "sg:city":"Cornella Llobregat",
    "sg:orig_category":"Poller\u00cda Y Caza (al Por Menor)",
    "sg:phone":"+34 933 77 19 99",
    "sg:postcode":"08940",
    "sg:province":"Barcelona",
    "wof:name":"Parra Caler Juan",
    "wof:placetype":"venue"
},
  "geometry": {"coordinates":[2.0733819008,41.3539161682],"type":"Point"}
}