{
  "type": "Feature",
  "properties": {
    "addr:full":"Calle de Matilde De La Torre, 7 Cabez\u00f3n Sal Cantabria 39500",
    "addr:housenumber":"7",
    "addr:postcode":"39500",
    "addr:street":"Calle De Matilde De La Torre",
    "iso:country":"ES",
    "sg:address":"Calle de Matilde De La Torre, 7",
    "sg:city":"Cabez\u00f3n Sal",
    "sg:orig_category":"Granos Y Semillas (producci\u00d3n, Al Por Mayor)",
    "sg:phone":"+34 942 70 02 07",
    "sg:postcode":"39500",
    "sg:province":"Cantabria",
    "wof:name":"Gutierrez Gomez Joaquina",
    "wof:placetype":"venue"
},
  "geometry": {"coordinates":[-4.2374691963,43.3085784912],"type":"Point"}
}