{
  "type": "Feature",
  "properties": {
    "iso:country":"ES",
    "sg:address":"Calle de Juan Relinque, 46",
    "sg:city":"Vejer De La Frontera",
    "sg:orig_category":"Librer\u00cdas",
    "sg:phone":"+34 956 44 70 44",
    "sg:postcode":"11150",
    "sg:province":"C\u00e1diz",
    "wof:name":"Mu\u00f1oz Rodriguez Manuel",
    "wof:placetype":"venue"
},
  "geometry": {"coordinates":[-5.96626091,36.2517127991],"type":"Point"}
}