{
  "type": "Feature",
  "properties": {
    "iso:country":"ES",
    "sg:address":"Calle de Santa Teresa, 3",
    "sg:city":"Alcala Henares",
    "sg:orig_category":"Frutas, Legumbres Frescas Y Tempranas (al Por Menor)",
    "sg:phone":"+34 918 82 64 30",
    "sg:postcode":"28803",
    "sg:province":"Madrid",
    "wof:name":"Cabrera Garcia Miguel",
    "wof:placetype":"venue"
},
  "geometry": {"coordinates":[-3.3771779537,40.4740791321],"type":"Point"}
}