{
  "type": "Feature",
  "properties": {
    "addr:full":"Ctra. Palma-arta, S/n Montu\u00efri Islas Baleares 07230",
    "addr:housenumber":"s",
    "addr:postcode":"07230",
    "addr:street":"Ctra. Palma-Arta;/ N",
    "iso:country":"ES",
    "sg:address":"Ctra. Palma-arta, S/n",
    "sg:city":"Montu\u00efri",
    "sg:orig_category":"Restaurantes",
    "sg:phone":"+34 971 64 63 14",
    "sg:postcode":"07230",
    "sg:province":"Islas Baleares",
    "wof:name":"Carbonell Niell Juan",
    "wof:placetype":"venue"
},
  "geometry": {"coordinates":[2.9810760021,39.5683860779],"type":"Point"}
}