{
  "type": "Feature",
  "properties": {
    "addr:full":"Calle de Uruguay, 9 Vitoria-gasteiz \u00c1lava 01012",
    "addr:housenumber":"9",
    "addr:postcode":"01012",
    "addr:street":"Calle De Uruguay",
    "iso:country":"ES",
    "sg:address":"Calle de Uruguay, 9",
    "sg:city":"Vitoria-gasteiz",
    "sg:orig_category":"Ense\u00d1anza: Idiomas",
    "sg:phone":"+34 945 20 00 45",
    "sg:postcode":"01012",
    "sg:province":"\u00c1lava",
    "wof:name":"Udaberria Elkartegia",
    "wof:placetype":"venue"
},
  "geometry": {"coordinates":[-2.6763350964,42.8580207825],"type":"Point"}
}