{
  "type": "Feature",
  "properties": {
    "iso:country":"ES",
    "sg:address":"Calle de Cenia, 5",
    "sg:city":"Valencia",
    "sg:orig_category":"Grabados",
    "sg:phone":"+34 963 91 68 18",
    "sg:postcode":"46001",
    "sg:province":"Valencia",
    "wof:name":"Roca Sanz Milagros",
    "wof:placetype":"venue"
},
  "geometry": {"coordinates":[-0.3778412044,39.4747123718],"type":"Point"}
}