{
  "type": "Feature",
  "properties": {
    "iso:country":"ES",
    "sg:address":"Avda Blas Infante (de), 2",
    "sg:city":"Lucena",
    "sg:orig_category":"Distribuci\u00d3n De Petr\u00d3leo Y Derivados",
    "sg:phone":"+34 957 50 93 85",
    "sg:postcode":"14900",
    "sg:province":"C\u00f3rdoba",
    "wof:name":"Mendoza Palomares Maria Teresa",
    "wof:placetype":"venue"
},
  "geometry": {"coordinates":[-4.4740638733,37.4099960327],"type":"Point"}
}