{
  "type": "Feature",
  "properties": {
    "addr:full":"Av Perpinya, 40 Figueres Girona 17600",
    "addr:housenumber":"40",
    "addr:postcode":"17600",
    "addr:street":"Av Perpinya",
    "iso:country":"ES",
    "sg:address":"Av Perpinya, 40",
    "sg:city":"Figueres",
    "sg:orig_category":"Fabricaci\u00d3n, Importaci\u00d3n De L\u00c1mparas Y Bombillas",
    "sg:phone":"+34 972 50 08 88",
    "sg:postcode":"17600",
    "sg:province":"Girona",
    "wof:name":"Batlle Duch Lluis",
    "wof:placetype":"venue"
},
  "geometry": {"coordinates":[2.956362009,42.273651123],"type":"Point"}
}