{
  "type": "Feature",
  "properties": {
    "iso:country":"ES",
    "sg:address":"Calle de Real De Santa Fe, 32",
    "sg:city":"Santa Fe",
    "sg:orig_category":"Promotores Constructores",
    "sg:phone":"+34 958 44 04 69",
    "sg:postcode":"18320",
    "sg:province":"Granada",
    "wof:name":"Handle Mandle S.a.",
    "wof:placetype":"venue"
},
  "geometry": {"coordinates":[-3.714564085,37.1907157898],"type":"Point"}
}