{
  "type": "Feature",
  "properties": {
    "addr:full":"Calle de Doctor Cazalla, 1 Valladolid Valladolid 47003",
    "addr:housenumber":"1",
    "addr:postcode":"47003",
    "addr:street":"Calle De Doctor Cazalla",
    "iso:country":"ES",
    "sg:address":"Calle de Doctor Cazalla, 1",
    "sg:city":"Valladolid",
    "sg:orig_category":"Barbacoas Y Accesorios",
    "sg:phone":"+34 983 33 31 55",
    "sg:postcode":"47003",
    "sg:province":"Valladolid",
    "wof:name":"Las Brasas S.l.",
    "wof:placetype":"venue"
},
  "geometry": {"coordinates":[-4.7277169228,41.6548843384],"type":"Point"}
}