{
  "type": "Feature",
  "properties": {
    "iso:country":"ES",
    "sg:address":"Av Comte De Sallent, 11",
    "sg:city":"Palma",
    "sg:orig_category":"Asesor\u00cda Sobre Comunicaci\u00d3n De Empresas",
    "sg:phone":"+34 971 42 55 50",
    "sg:postcode":"07003",
    "sg:province":"Islas Baleares",
    "sg:website":"www.pwc.com/es",
    "wof:name":"Price Water House Coopers S.l.",
    "wof:placetype":"venue"
},
  "geometry": {"coordinates":[2.6516010761,39.5776329041],"type":"Point"}
}