{
  "type": "Feature",
  "properties": {
    "iso:country":"ES",
    "sg:address":"Avda De Los Cabezudos, S/n",
    "sg:city":"Almonte",
    "sg:orig_category":"Cooperativas Agr\u00cdcolas",
    "sg:phone":"+34 959 40 73 03",
    "sg:postcode":"21730",
    "sg:province":"Huelva",
    "wof:name":"Cooperativa Apicola La Almonte\u00f1a",
    "wof:placetype":"venue"
},
  "geometry": {"coordinates":[-6.5231790543,37.2572212219],"type":"Point"}
}