{
  "type": "Feature",
  "properties": {
    "iso:country":"ES",
    "sg:address":"Calle de Trinidad Grund, 33",
    "sg:city":"Malaga",
    "sg:orig_category":"Notarios",
    "sg:phone":"+34 952 60 60 35",
    "sg:postcode":"29001",
    "sg:province":"M\u00e1laga",
    "wof:name":"Helmantica De Buffetes Y Despachos S.l.",
    "wof:placetype":"venue"
},
  "geometry": {"coordinates":[-4.4241700172,36.7164115906],"type":"Point"}
}