{
  "type": "Feature",
  "properties": {
    "iso:country":"ES",
    "sg:address":"Carrer de Santalo, 70",
    "sg:city":"Barcelona",
    "sg:orig_category":"Zapatos (al Por Menor)",
    "sg:phone":"+34 932 09 17 64",
    "sg:postcode":"08021",
    "sg:province":"Barcelona",
    "wof:name":"Ortells Alegre Pedro",
    "wof:placetype":"venue"
},
  "geometry": {"coordinates":[2.1440188885,41.3971939087],"type":"Point"}
}