{
  "type": "Feature",
  "properties": {
    "addr:full":"Rua Beniti\u00d1o, 1 Barbeito Pontevedra 36979",
    "addr:housenumber":"1",
    "addr:postcode":"36979",
    "addr:street":"Rua Benitin\u0303O",
    "iso:country":"ES",
    "sg:address":"Rua Beniti\u00d1o, 1",
    "sg:city":"Barbeito",
    "sg:orig_category":"Comercio De Piezas De Recambio Y De Accesorios De Veh\u00cdculos, Veh\u00cdculos Industriales",
    "sg:phone":"+34 986 69 05 72",
    "sg:postcode":"36979",
    "sg:province":"Pontevedra",
    "wof:name":"Recambios Romay S.l.",
    "wof:placetype":"venue"
},
  "geometry": {"coordinates":[-8.8151941299,42.4157600403],"type":"Point"}
}