{
  "type": "Feature",
  "properties": {
    "iso:country":"ES",
    "sg:address":"Ctra. General, S/n",
    "sg:city":"S. Antolin Ibias",
    "sg:orig_category":"Chapister\u00cda",
    "sg:phone":"+34 985 81 61 82",
    "sg:postcode":"33810",
    "sg:province":"Asturias",
    "wof:name":"Alvarez Perez Jose Luis",
    "wof:placetype":"venue"
},
  "geometry": {"coordinates":[-6.7922353745,43.0121154785],"type":"Point"}
}