{
  "type": "Feature",
  "properties": {
    "addr:full":"Calle de Corredera, 23 Viso Del Alcor Sevilla 41520",
    "addr:housenumber":"23",
    "addr:postcode":"41520",
    "addr:street":"Calle De Corredera",
    "iso:country":"ES",
    "sg:address":"Calle de Corredera, 23",
    "sg:city":"Viso Del Alcor",
    "sg:orig_category":"Asociaciones Y Clubs Deportivos",
    "sg:phone":"+34 955 74 19 78",
    "sg:postcode":"41520",
    "sg:province":"Sevilla",
    "wof:name":"Pe\u00f1a Betica El Viso Del Alcor",
    "wof:placetype":"venue"
},
  "geometry": {"coordinates":[-5.7235841751,37.3860054016],"type":"Point"}
}