{
  "type": "Feature",
  "properties": {
    "iso:country":"ES",
    "sg:address":"Plaz San Vicente, 3",
    "sg:city":"Onil",
    "sg:orig_category":"Complementos De Vestir (al Por Menor)",
    "sg:phone":"+34 966 55 73 29",
    "sg:postcode":"03430",
    "sg:province":"Alicante",
    "wof:name":"Olmos Estebez Yolanda",
    "wof:placetype":"venue"
},
  "geometry": {"coordinates":[-0.6756309867,38.623840332],"type":"Point"}
}