{
  "type": "Feature",
  "properties": {
    "addr:full":"Calle de Salamanca, 2 Cabezon.barrio Nuevo Valladolid 47260",
    "addr:housenumber":"2",
    "addr:postcode":"47260",
    "addr:street":"Calle De Salamanca",
    "iso:country":"ES",
    "sg:address":"Calle de Salamanca, 2",
    "sg:city":"Cabezon.barrio Nuevo",
    "sg:orig_category":"Inmobiliaria (agencias)",
    "sg:phone":"+34 983 50 01 85",
    "sg:postcode":"47260",
    "sg:province":"Valladolid",
    "wof:name":"Hisagar S.l.",
    "wof:placetype":"venue"
},
  "geometry": {"coordinates":[-4.6432561874,41.7405509949],"type":"Point"}
}