{
  "type": "Feature",
  "properties": {
    "iso:country":"ES",
    "sg:address":"Calle de Tembleque, 146",
    "sg:city":"Madrid",
    "sg:orig_category":"Art\u00cdculos De Decoraci\u00d3n",
    "sg:phone":"+34 917 11 12 81",
    "sg:postcode":"28024",
    "sg:province":"Madrid",
    "wof:name":"Villanueva Bascones Maria Rosario",
    "wof:placetype":"venue"
},
  "geometry": {"coordinates":[-3.7646980286,40.3914871216],"type":"Point"}
}