{
  "type": "Feature",
  "properties": {
    "addr:full":"Pase Zorrilla, 14 Valladolid Valladolid 47008",
    "addr:housenumber":"14",
    "addr:postcode":"47008",
    "addr:street":"Zorrilla",
    "iso:country":"ES",
    "sg:address":"Pase Zorrilla, 14",
    "sg:city":"Valladolid",
    "sg:orig_category":"Farmacias",
    "sg:phone":"+34 983 33 74 13",
    "sg:postcode":"47008",
    "sg:province":"Valladolid",
    "wof:name":"Santiago Sastre Genoveva",
    "wof:placetype":"venue"
},
  "geometry": {"coordinates":[-4.7927489281,41.6193618774],"type":"Point"}
}