{
  "type": "Feature",
  "properties": {
    "addr:full":"Calle de San Juan, 32 Vinaros Castell\u00f3n 12500",
    "addr:housenumber":"32",
    "addr:postcode":"12500",
    "addr:street":"Calle De San Juan",
    "iso:country":"ES",
    "sg:address":"Calle de San Juan, 32",
    "sg:city":"Vinaros",
    "sg:orig_category":"Inmobiliaria (agencias)",
    "sg:phone":"+34 964 45 92 84",
    "sg:postcode":"12500",
    "sg:province":"Castell\u00f3n",
    "wof:name":"Fincas Vinaros S.l.",
    "wof:placetype":"venue"
},
  "geometry": {"coordinates":[0.4749450088,40.4711990356],"type":"Point"}
}