{
  "type": "Feature",
  "properties": {
    "addr:full":"Calle de Ubeda, 18 Cordoba C\u00f3rdoba 14013",
    "addr:housenumber":"18",
    "addr:postcode":"14013",
    "addr:street":"Calle De Ubeda;Co\u0301Rdoba",
    "iso:country":"ES",
    "sg:address":"Calle de Ubeda, 18",
    "sg:city":"Cordoba",
    "sg:orig_category":"Zapatos (al Por Menor)",
    "sg:phone":"+34 957 42 19 00",
    "sg:postcode":"14013",
    "sg:province":"C\u00f3rdoba",
    "wof:name":"Almenara Serrano Pablo",
    "wof:placetype":"venue"
},
  "geometry": {"coordinates":[-4.7770991325,37.866104126],"type":"Point"}
}