{
  "type": "Feature",
  "properties": {
    "iso:country":"ES",
    "sg:address":"Residencia Los Tilos, S/n",
    "sg:city":"Ramales Victoria",
    "sg:orig_category":"Peluquer\u00cdas, Peluquer\u00cda Mixta",
    "sg:phone":"+34 942 67 83 72",
    "sg:postcode":"39800",
    "sg:province":"Cantabria",
    "wof:name":"Cano Tamayo Jose Cristobal",
    "wof:placetype":"venue"
},
  "geometry": {"coordinates":[-3.442991972,43.2613754272],"type":"Point"}
}