{
  "type": "Feature",
  "properties": {
    "iso:country":"ES",
    "sg:address":"Carrer de Napols, 265",
    "sg:city":"Barcelona",
    "sg:orig_category":"Carnicer\u00cdas, Carnicer\u00cdas",
    "sg:phone":"+34 934 57 91 79",
    "sg:postcode":"08025",
    "sg:province":"Barcelona",
    "wof:name":"Pastor Romero Antonio",
    "wof:placetype":"venue"
},
  "geometry": {"coordinates":[2.1699879169,41.4023361206],"type":"Point"}
}