{
  "type": "Feature",
  "properties": {
    "addr:full":"Avda Consejo De Europa, S/n Cadiz C\u00e1diz 11011",
    "addr:housenumber":"s / n",
    "addr:postcode":"11011",
    "addr:street":"Avda Consejo De Europa",
    "iso:country":"ES",
    "sg:address":"Avda Consejo De Europa, S/n",
    "sg:city":"Cadiz",
    "sg:orig_category":"Barcos",
    "sg:phone":"+34 956 26 35 13",
    "sg:postcode":"11011",
    "sg:province":"C\u00e1diz",
    "wof:name":"U.t.e. Port Cadiz",
    "wof:placetype":"venue"
},
  "geometry": {"coordinates":[-6.266849041,36.5016708374],"type":"Point"}
}