{
  "type": "Feature",
  "properties": {
    "iso:country":"ES",
    "sg:address":"C/ Ciutat De Barcelona, 56",
    "sg:city":"Paterna",
    "sg:orig_category":"Aluminio Y Aleaciones (producci\u00d3n, Transformaci\u00d3n, Negocio)",
    "sg:phone":"+34 961 32 45 85",
    "sg:postcode":"46988",
    "sg:province":"Valencia",
    "wof:name":"Alugom Valencia Sl",
    "wof:placetype":"venue"
},
  "geometry": {"coordinates":[-0.4748308063,39.5189247131],"type":"Point"}
}