{
  "type": "Feature",
  "properties": {
    "addr:full":"Plaz Torres Quevedo Ingeniero, 2 Bilbao Vizcaya 48013",
    "addr:housenumber":"2",
    "addr:postcode":"48013",
    "addr:street":"Plaz Torres Quevedo Ingeniero",
    "iso:country":"ES",
    "sg:address":"Plaz Torres Quevedo Ingeniero, 2",
    "sg:city":"Bilbao",
    "sg:orig_category":"Edici\u00d3n De Diarios, Revistas, Boletines",
    "sg:phone":"+34 944 39 63 82",
    "sg:postcode":"48013",
    "sg:province":"Vizcaya",
    "wof:name":"Unidad Editorial S.a.",
    "wof:placetype":"venue"
},
  "geometry": {"coordinates":[-2.9461190701,43.2686500549],"type":"Point"}
}