{
  "type": "Feature",
  "properties": {
    "iso:country":"ES",
    "sg:address":"Carr Quatre Cantons, 13",
    "sg:city":"Felanitx",
    "sg:orig_category":"Caf\u00c9s, Bares, Cervecer\u00cdas",
    "sg:phone":"+34 971 58 00 00",
    "sg:postcode":"07200",
    "sg:province":"Islas Baleares",
    "wof:name":"Bordoy Monserrat Magdalena",
    "wof:placetype":"venue"
},
  "geometry": {"coordinates":[3.1478059292,39.4699440002],"type":"Point"}
}