{
  "type": "Feature",
  "properties": {
    "addr:full":"Calle de Jose Gorostiza, 41 Malaga M\u00e1laga 29190",
    "addr:housenumber":"41",
    "addr:postcode":"29190",
    "addr:street":"Calle De Jose Gorostiza;Ma\u0301Laga",
    "iso:country":"ES",
    "sg:address":"Calle de Jose Gorostiza, 41",
    "sg:city":"Malaga",
    "sg:orig_category":"Dise\u00d1o Industrial",
    "sg:phone":"+34 952 43 83 52",
    "sg:postcode":"29190",
    "sg:province":"M\u00e1laga",
    "wof:name":"Fernandez Lorencio Jesus Maria",
    "wof:placetype":"venue"
},
  "geometry": {"coordinates":[-4.4774651527,36.7350616455],"type":"Point"}
}