{
  "type": "Feature",
  "properties": {
    "iso:country":"ES",
    "sg:address":"Calle de Joaquin Costa, 43",
    "sg:city":"Ejea De Los Caballeros",
    "sg:orig_category":"Material Y Herramientas Agr\u00cdcolas",
    "sg:phone":"+34 976 67 71 50",
    "sg:postcode":"50600",
    "sg:province":"Zaragoza",
    "wof:name":"Tenias S. A.",
    "wof:placetype":"venue"
},
  "geometry": {"coordinates":[-1.1425379515,42.1230773926],"type":"Point"}
}