{
  "type": "Feature",
  "properties": {
    "iso:country":"ES",
    "sg:address":"Calle de Mayor, 4",
    "sg:city":"Madrid",
    "sg:orig_category":"Fotocopias, Reprograf\u00cda",
    "sg:phone":"+34 915 21 98 12",
    "sg:postcode":"28013",
    "sg:province":"Madrid",
    "wof:name":"Vazquez Fraile Jaime",
    "wof:placetype":"venue"
},
  "geometry": {"coordinates":[-3.7046260834,40.4164848328],"type":"Point"}
}