{
  "type": "Feature",
  "properties": {
    "iso:country":"ES",
    "sg:address":"Av S'agaro, 19",
    "sg:city":"Platja D'aro",
    "sg:orig_category":"Zapatos (al Por Menor)",
    "sg:phone":"+34 972 81 97 05",
    "sg:postcode":"17250",
    "sg:province":"Girona",
    "wof:name":"Cornet Roca Josefa",
    "wof:placetype":"venue"
},
  "geometry": {"coordinates":[2.8163490295,41.9701499939],"type":"Point"}
}