{
  "type": "Feature",
  "properties": {
    "iso:country":"ES",
    "sg:address":"Calle de Catalina De Erauso, 11",
    "sg:city":"Donostia-san Sebastian",
    "sg:orig_category":"Mercer\u00cda, Lencer\u00cda (al Por Menor)",
    "sg:phone":"+34 943 47 23 28",
    "sg:postcode":"20010",
    "sg:province":"Guip\u00f9zcoa",
    "wof:name":"Arregui Aizpurua Olatz",
    "wof:placetype":"venue"
},
  "geometry": {"coordinates":[-1.981099844,43.3047409058],"type":"Point"}
}