{
  "type": "Feature",
  "properties": {
    "addr:full":"Hospital(barreros), 37 Cartagena Murcia 30310",
    "addr:housenumber":"37",
    "addr:postcode":"30310",
    "addr:street":"Barreros",
    "iso:country":"ES",
    "sg:address":"Hospital(barreros), 37",
    "sg:city":"Cartagena",
    "sg:classifiers":[
        {
            "category":"Professional",
            "subcategory":"Management & Consulting",
            "type":"Services"
        }
    ],
    "sg:phone":"+34 968 51 88 34",
    "sg:postcode":"30310",
    "sg:province":"Murcia",
    "sg:tags":[
        "asesor\u00cda",
        "en",
        "marketing"
    ],
    "wof:name":"Montoro Paradelo Candelaria",
    "wof:placetype":"venue"
},
  "geometry": {"coordinates":[-1.0082689524,37.6360816956],"type":"Point"}
}