{
  "type": "Feature",
  "properties": {
    "addr:full":"Avda Andalucia, 36 Benacazon Sevilla 41805",
    "addr:housenumber":"36",
    "addr:postcode":"41805",
    "addr:street":"Avda Andalucia",
    "iso:country":"ES",
    "sg:address":"Avda Andalucia, 36",
    "sg:city":"Benacazon",
    "sg:orig_category":"Quincaller\u00cda (al Por Menor)",
    "sg:phone":"+34 955 70 58 24",
    "sg:postcode":"41805",
    "sg:province":"Sevilla",
    "wof:name":"Rojas Y Valero S.l.",
    "wof:placetype":"venue"
},
  "geometry": {"coordinates":[-6.1903190613,37.3526725769],"type":"Point"}
}