{
  "type": "Feature",
  "properties": {
    "addr:full":"Calle de Balbastro, S/n Castillazuelo Huesca 22313",
    "addr:housenumber":"s",
    "addr:postcode":"22313",
    "addr:street":"Calle De Balbastro;/ N Castillazuelo",
    "iso:country":"ES",
    "sg:address":"Calle de Balbastro, S/n",
    "sg:city":"Castillazuelo",
    "sg:orig_category":"Cajas De Ahorro",
    "sg:phone":"+34 974 30 23 45",
    "sg:postcode":"22313",
    "sg:province":"Huesca",
    "wof:name":"Caja De Ahorros De La Inmaculada",
    "wof:placetype":"venue"
},
  "geometry": {"coordinates":[0.0657674968,42.0691070557],"type":"Point"}
}