{
  "type": "Feature",
  "properties": {
    "iso:country":"ES",
    "sg:address":"Carrer de Navarra, 3",
    "sg:city":"Torreta",
    "sg:orig_category":"Mec\u00c1nico Del Autom\u00d3vil",
    "sg:phone":"+34 938 70 95 17",
    "sg:postcode":"08430",
    "sg:province":"Barcelona",
    "wof:name":"Donadeu Tost Juan",
    "wof:placetype":"venue"
},
  "geometry": {"coordinates":[2.2972919941,41.6021575928],"type":"Point"}
}