{
  "type": "Feature",
  "properties": {
    "iso:country":"ES",
    "sg:address":"Carrer de Verge De La Soledat, 13",
    "sg:city":"Ondara",
    "sg:orig_category":"Centros De Coordinaci\u00d3n",
    "sg:phone":"+34 965 76 60 86",
    "sg:postcode":"03760",
    "sg:province":"Alicante",
    "wof:name":"Domenech Garcia Enriqueta",
    "wof:placetype":"venue"
},
  "geometry": {"coordinates":[0.0155999996,38.829460144],"type":"Point"}
}