{
  "type": "Feature",
  "properties": {
    "iso:country":"ES",
    "sg:address":"Calle de Manuel Velasco De Pando, 7",
    "sg:city":"Sevilla",
    "sg:orig_category":"Electricidad: Instaladores",
    "sg:phone":"+34 954 58 35 23",
    "sg:postcode":"41007",
    "sg:province":"Sevilla",
    "wof:name":"Telvent Outsourcing S.a.",
    "wof:placetype":"venue"
},
  "geometry": {"coordinates":[-5.9613938332,37.3890075684],"type":"Point"}
}