{
  "type": "Feature",
  "properties": {
    "addr:full":"Calle de Canarias, 1 San Vicente De Barakaldo Vizcaya 48902",
    "addr:housenumber":"1",
    "addr:postcode":"48902",
    "addr:street":"Calle De Canarias",
    "iso:country":"ES",
    "sg:address":"Calle de Canarias, 1",
    "sg:city":"San Vicente De Barakaldo",
    "sg:orig_category":"Fotocopias, Reprograf\u00cda",
    "sg:phone":"+34 944 90 39 81",
    "sg:postcode":"48902",
    "sg:province":"Vizcaya",
    "wof:name":"Merino Lopez Fernando",
    "wof:placetype":"venue"
},
  "geometry": {"coordinates":[-2.994487524,43.291721344],"type":"Point"}
}