{
  "type": "Feature",
  "properties": {
    "iso:country":"ES",
    "sg:address":"Carrer de Ramon Farguell, 206",
    "sg:city":"Manresa",
    "sg:orig_category":"M\u00c1quinas Textiles, Accesorios Y Suministros (fabricaci\u00d3n)",
    "sg:phone":"+34 938 73 98 98",
    "sg:postcode":"08243",
    "sg:province":"Barcelona",
    "wof:name":"Texma Maquinaria Textil S.l.",
    "wof:placetype":"venue"
},
  "geometry": {"coordinates":[1.85224998,41.7092590332],"type":"Point"}
}