{
  "type": "Feature",
  "properties": {
    "addr:full":"Carrer de Cristobal De Moura, 199 Barcelona Barcelona 08019",
    "addr:housenumber":"199",
    "addr:postcode":"08019",
    "addr:street":"Carrer De Cristobal De Moura",
    "iso:country":"ES",
    "sg:address":"Carrer de Cristobal De Moura, 199",
    "sg:city":"Barcelona",
    "sg:orig_category":"Alumbrados",
    "sg:phone":"+34 933 03 43 53",
    "sg:postcode":"08019",
    "sg:province":"Barcelona",
    "wof:name":"Servi Grup Generator S. L.",
    "wof:placetype":"venue"
},
  "geometry": {"coordinates":[2.2113060951,41.4148826599],"type":"Point"}
}