{
  "type": "Feature",
  "properties": {
    "addr:full":"Carr Sant Josep, 56 Palau D'anglesola Lleida 25243",
    "addr:housenumber":"56",
    "addr:postcode":"25243",
    "addr:street":"Carr Sant Josep",
    "iso:country":"ES",
    "sg:address":"Carr Sant Josep, 56",
    "sg:city":"Palau D'anglesola",
    "sg:orig_category":"Empresas De Carpinter\u00cda De Madera",
    "sg:phone":"+34 973 71 22 88",
    "sg:postcode":"25243",
    "sg:province":"Lleida",
    "wof:name":"Mo-espinet Cb",
    "wof:placetype":"venue"
},
  "geometry": {"coordinates":[0.6218330264,41.6141891479],"type":"Point"}
}