{
  "type": "Feature",
  "properties": {
    "iso:country":"ES",
    "sg:address":"Avda Juan Carlos I, 50",
    "sg:city":"Andratx",
    "sg:orig_category":"Zapatos (al Por Menor)",
    "sg:phone":"+34 971 23 58 43",
    "sg:postcode":"07150",
    "sg:province":"Islas Baleares",
    "wof:name":"Escudero Gomez Juan Carlos",
    "wof:placetype":"venue"
},
  "geometry": {"coordinates":[2.421118021,39.5741653442],"type":"Point"}
}