{
  "type": "Feature",
  "properties": {
    "iso:country":"ES",
    "sg:address":"Calle de Guarnicioneros, S/n",
    "sg:city":"Andujar",
    "sg:orig_category":"M\u00c1quinas De Coser Y De Hacer Punto (al Por Mayor)",
    "sg:phone":"+34 953 50 61 23",
    "sg:postcode":"23740",
    "sg:province":"Ja\u00e9n",
    "wof:name":"Camafort S.l.",
    "wof:placetype":"venue"
},
  "geometry": {"coordinates":[-4.0579991341,38.0317459106],"type":"Point"}
}