{
  "type": "Feature",
  "properties": {
    "iso:country":"ES",
    "sg:address":"Calle de Francisco Ruesta, 30",
    "sg:city":"Zaragoza",
    "sg:orig_category":"Electricidad, Electr\u00d3nica: Material Y Suministros (al Por Mayor)",
    "sg:phone":"+34 976 53 73 71",
    "sg:postcode":"50011",
    "sg:province":"Zaragoza",
    "wof:name":"Laura Material Electrico S.l.",
    "wof:placetype":"venue"
},
  "geometry": {"coordinates":[-0.9211210012,41.6530838013],"type":"Point"}
}