{
  "type": "Feature",
  "properties": {
    "addr:full":"Calle de Villanueva, 23 Madrid Madrid 28001",
    "addr:housenumber":"23",
    "addr:postcode":"madrid;28001",
    "addr:street":"Calle De Villanueva",
    "iso:country":"ES",
    "sg:address":"Calle de Villanueva, 23",
    "sg:city":"Madrid",
    "sg:orig_category":"Agencias Y Asesores De Publicidad",
    "sg:phone":"+34 915 76 67 58",
    "sg:postcode":"28001",
    "sg:province":"Madrid",
    "sg:website":"www.geiko-oler.com",
    "wof:name":"Servicios Marketing Koler S.l.",
    "wof:placetype":"venue"
},
  "geometry": {"coordinates":[-3.6845879555,40.4224967957],"type":"Point"}
}