{
  "type": "Feature",
  "properties": {
    "addr:full":"Pla\u00c7 Claustre Del Carme, 6 Mao Islas Baleares 07701",
    "addr:housenumber":"6",
    "addr:postcode":"07701",
    "addr:street":"Carme",
    "iso:country":"ES",
    "sg:address":"Pla\u00c7 Claustre Del Carme, 6",
    "sg:city":"Mao",
    "sg:orig_category":"Caf\u00c9s, Bares, Cervecer\u00cdas",
    "sg:phone":"+34 971 36 11 50",
    "sg:postcode":"07701",
    "sg:province":"Islas Baleares",
    "wof:name":"Mu\u00f1oz Pareja Raul",
    "wof:placetype":"venue"
},
  "geometry": {"coordinates":[4.2680602074,39.8879508972],"type":"Point"}
}