{
  "type": "Feature",
  "properties": {
    "iso:country":"ES",
    "sg:address":"Carrer de Pare Manyanet, 14",
    "sg:city":"Molins Rei",
    "sg:orig_category":"Tapicer\u00cdas",
    "sg:phone":"+34 936 68 96 01",
    "sg:postcode":"08750",
    "sg:province":"Barcelona",
    "wof:name":"Tapiceria Crisan S.l.",
    "wof:placetype":"venue"
},
  "geometry": {"coordinates":[2.0169401169,41.4136009216],"type":"Point"}
}