{
  "type": "Feature",
  "properties": {
    "iso:country":"ES",
    "sg:address":"Calle de Murga, 48",
    "sg:city":"Palmas De Gran Canaria",
    "sg:orig_category":"Cuidado Del Cabello",
    "sg:phone":"+34 928 37 24 44",
    "sg:postcode":"35003",
    "sg:province":"Las Palmas",
    "wof:name":"Doblas Carballo Enma Amalia",
    "wof:placetype":"venue"
},
  "geometry": {"coordinates":[-15.4215669632,28.110042572],"type":"Point"}
}