{
  "type": "Feature",
  "properties": {
    "iso:country":"ES",
    "sg:address":"Av Alameda (l'), 73",
    "sg:city":"Alcoi",
    "sg:orig_category":"Ropa Para Se\u00d1oras (al Por Menor)",
    "sg:phone":"+34 965 33 99 54",
    "sg:postcode":"03803",
    "sg:province":"Alicante",
    "sg:website":"www.torero.com",
    "wof:name":"Tonny Sango S.l.",
    "wof:placetype":"venue"
},
  "geometry": {"coordinates":[-0.4754990041,38.7037696838],"type":"Point"}
}