{
  "type": "Feature",
  "properties": {
    "iso:country":"ES",
    "sg:address":"Trva Bouzas Servicio Portuario, S/n",
    "sg:city":"Vigo",
    "sg:orig_category":"M\u00c1quinas Y Material Para La Industria De La Alimentaci\u00d3n",
    "sg:phone":"+34 986 37 20 11",
    "sg:postcode":"36208",
    "sg:province":"Pontevedra",
    "sg:website":"www.hrg.com",
    "wof:name":"Hermanos Rodriguez Gomez S. L.",
    "wof:placetype":"venue"
},
  "geometry": {"coordinates":[-8.7529735565,42.2268791199],"type":"Point"}
}