{
  "type": "Feature",
  "properties": {
    "addr:full":"Calle de Mendez Nu\u00d1ez, 36 Cangas Pontevedra 36940",
    "addr:housenumber":"36",
    "addr:postcode":"36940",
    "addr:street":"Calle De Mendez Nun\u0303Ez",
    "iso:country":"ES",
    "sg:address":"Calle de Mendez Nu\u00d1ez, 36",
    "sg:city":"Cangas",
    "sg:orig_category":"\u00d3ptica: Instrumentos (fabricaci\u00d3n)",
    "sg:phone":"+34 986 30 42 09",
    "sg:postcode":"36940",
    "sg:province":"Pontevedra",
    "wof:name":"Doval Herranz Beatriz",
    "wof:placetype":"venue"
},
  "geometry": {"coordinates":[-8.7796468735,42.2640914917],"type":"Point"}
}