{
  "type": "Feature",
  "properties": {
    "iso:country":"ES",
    "sg:address":"Avda Langraiz, 26",
    "sg:city":"Nanclares De La Oca",
    "sg:orig_category":"Cajas De Ahorro",
    "sg:phone":"+34 945 37 11 15",
    "sg:postcode":"01230",
    "sg:province":"\u00c1lava",
    "sg:website":"www.cajavital.es",
    "wof:name":"Caja De Ahorros De Vitoria Y Alava",
    "wof:placetype":"venue"
},
  "geometry": {"coordinates":[-2.8150889874,42.8163604736],"type":"Point"}
}