{
  "type": "Feature",
  "properties": {
    "iso:country":"ES",
    "sg:address":"Calle de Almirante Hernandez Pinzon, 1",
    "sg:city":"Moguer",
    "sg:classifiers":[
        {
            "category":"Personal",
            "subcategory":"Barber",
            "type":"Services"
        }
    ],
    "sg:phone":"+34 959 37 10 27",
    "sg:postcode":"21800",
    "sg:province":"Huelva",
    "sg:tags":[
        "caballeros",
        "de",
        "peluqueros"
    ],
    "wof:name":"Estevez Roque Francisco",
    "wof:placetype":"venue"
},
  "geometry": {"coordinates":[-6.8373174667,37.2751541138],"type":"Point"}
}