{
  "type": "Feature",
  "properties": {
    "iso:country":"ES",
    "sg:address":"Pla Palau, 12",
    "sg:city":"Barcelona",
    "sg:orig_category":"Fabricaci\u00d3n, Importaci\u00d3n, Venta De Material De Telefon\u00cda, Peritelefon\u00cda",
    "sg:phone":"+34 932 68 70 13",
    "sg:postcode":"08003",
    "sg:province":"Barcelona",
    "wof:name":"Pick Up Tel",
    "wof:placetype":"venue"
},
  "geometry": {"coordinates":[2.1832380295,41.3833427429],"type":"Point"}
}