{
  "type": "Feature",
  "properties": {
    "addr:full":"Calle de Leopoldo Cano, 3 Valladolid Valladolid 47003",
    "addr:housenumber":"3",
    "addr:postcode":"47003",
    "addr:street":"Calle De Leopoldo Cano",
    "iso:country":"ES",
    "sg:address":"Calle de Leopoldo Cano, 3",
    "sg:city":"Valladolid",
    "sg:orig_category":"Abogados",
    "sg:phone":"+34 983 35 74 41",
    "sg:postcode":"47003",
    "sg:province":"Valladolid",
    "wof:name":"Cordova Fernandez Antonio",
    "wof:placetype":"venue"
},
  "geometry": {"coordinates":[-4.7263698578,41.6542778015],"type":"Point"}
}