{
  "type": "Feature",
  "properties": {
    "iso:country":"ES",
    "sg:address":"Calle de Diego De Vargas, 20",
    "sg:city":"Madrid",
    "sg:orig_category":"Contenedores Para Transporte De Mercanc\u00cdas",
    "sg:phone":"+34 917 41 10 72",
    "sg:postcode":"28022",
    "sg:province":"Madrid",
    "wof:name":"Transportes Domasa S.l.",
    "wof:placetype":"venue"
},
  "geometry": {"coordinates":[-3.6127610207,40.4487457275],"type":"Point"}
}