{
  "type": "Feature",
  "properties": {
    "iso:country":"ES",
    "sg:address":"Carrer de General Rdo Ortega, 44",
    "sg:city":"Palma",
    "sg:orig_category":"Sociedades, Compa\u00d1\u00cdas Aseguradoras",
    "sg:phone":"+34 971 46 09 67",
    "sg:postcode":"07006",
    "sg:province":"Islas Baleares",
    "wof:name":"Segur-illes S.l.",
    "wof:placetype":"venue"
},
  "geometry": {"coordinates":[2.6629779339,39.5692367554],"type":"Point"}
}