{
  "type": "Feature",
  "properties": {
    "iso:country":"ES",
    "sg:address":"Lo Colorao, S/n",
    "sg:city":"Almu\u00f1ecar",
    "sg:orig_category":"Producci\u00d3n De Abonos Y De Fertilizantes",
    "sg:phone":"+34 958 63 57 45",
    "sg:postcode":"18690",
    "sg:province":"Granada",
    "wof:name":"Agrojardin Lara",
    "wof:placetype":"venue"
},
  "geometry": {"coordinates":[-3.6938381195,36.7327690125],"type":"Point"}
}