{
  "type": "Feature",
  "properties": {
    "addr:full":"Carr Jaume Arcelos, 20 Blanes Girona 17300",
    "addr:housenumber":"20",
    "addr:postcode":"17300",
    "addr:street":"Carr Jaume Arcelos",
    "iso:country":"ES",
    "sg:address":"Carr Jaume Arcelos, 20",
    "sg:city":"Blanes",
    "sg:orig_category":"Comercio, Reparaci\u00d3n De Motocicletas, Bicicletas Y Piezas Sueltas",
    "sg:phone":"+34 972 33 09 33",
    "sg:postcode":"17300",
    "sg:province":"Girona",
    "wof:name":"Llavina Fontanella Mario",
    "wof:placetype":"venue"
},
  "geometry": {"coordinates":[2.78678298,41.6754188538],"type":"Point"}
}