{
  "type": "Feature",
  "properties": {
    "iso:country":"ES",
    "sg:address":"Calle de Betsaida, 2",
    "sg:city":"Malaga",
    "sg:orig_category":"Electricidad: Instaladores",
    "sg:phone":"+34 952 33 62 96",
    "sg:postcode":"29006",
    "sg:province":"M\u00e1laga",
    "wof:name":"Montajes Electricos Seygo S.l.",
    "wof:placetype":"venue"
},
  "geometry": {"coordinates":[-4.4386281967,36.7131843567],"type":"Point"}
}