{
  "type": "Feature",
  "properties": {
    "addr:full":"Calle de San Miguel, 12 Manzanares Ciudad Real 13200",
    "addr:housenumber":"12",
    "addr:postcode":"13200",
    "addr:street":"Calle De San Miguel",
    "iso:country":"ES",
    "sg:address":"Calle de San Miguel, 12",
    "sg:city":"Manzanares",
    "sg:orig_category":"Mec\u00c1nico Del Autom\u00d3vil",
    "sg:phone":"+34 926 61 24 62",
    "sg:postcode":"13200",
    "sg:province":"Ciudad Real",
    "wof:name":"Talleres Y Gruas Arroyo S.l.",
    "wof:placetype":"venue"
},
  "geometry": {"coordinates":[-3.3767690659,39.0027351379],"type":"Point"}
}