{
  "type": "Feature",
  "properties": {
    "iso:country":"ES",
    "sg:address":"Calle de Mazo, 2",
    "sg:city":"Haro",
    "sg:orig_category":"Asesor\u00cda Fiscal Y Jur\u00cddica",
    "sg:phone":"+34 941 31 22 58",
    "sg:postcode":"26200",
    "sg:province":"La Rioja",
    "wof:name":"Ortun Saez Rebeca",
    "wof:placetype":"venue"
},
  "geometry": {"coordinates":[-2.8521199226,42.5727005005],"type":"Point"}
}