{
  "type": "Feature",
  "properties": {
    "iso:country":"ES",
    "sg:address":"Calle de Se\u00d1or Cura, 9",
    "sg:city":"Puebla Montalban",
    "sg:orig_category":"Pintores",
    "sg:phone":"+34 925 75 05 22",
    "sg:postcode":"45516",
    "sg:province":"Toledo",
    "wof:name":"Garcia Tenorio Garcia Sebastiana",
    "wof:placetype":"venue"
},
  "geometry": {"coordinates":[-4.3584671021,39.8651885986],"type":"Point"}
}