{
  "type": "Feature",
  "properties": {
    "addr:full":"Calle de Fausto Vigil, 5 Pola De Siero Asturias 33510",
    "addr:housenumber":"5",
    "addr:postcode":"33510",
    "addr:street":"Calle De Fausto Vigil",
    "iso:country":"ES",
    "sg:address":"Calle de Fausto Vigil, 5",
    "sg:city":"Pola De Siero",
    "sg:orig_category":"Telas Y Sedas (al Por Menor)",
    "sg:phone":"+34 985 72 18 95",
    "sg:postcode":"33510",
    "sg:province":"Asturias",
    "wof:name":"Noval Palacios Maria De Las Nieves",
    "wof:placetype":"venue"
},
  "geometry": {"coordinates":[-5.6587171555,43.3899383545],"type":"Point"}
}