{
  "type": "Feature",
  "properties": {
    "addr:full":"Carrer de Horta, 143 Barcelona Barcelona 08032",
    "addr:housenumber":"143",
    "addr:postcode":"08032",
    "addr:street":"Carrer De Horta",
    "iso:country":"ES",
    "sg:address":"Carrer de Horta, 143",
    "sg:city":"Barcelona",
    "sg:orig_category":"Material Y Suministros Para Fotocopiadoras, Reprograf\u00cda",
    "sg:phone":"+34 934 29 34 05",
    "sg:postcode":"08032",
    "sg:province":"Barcelona",
    "wof:name":"Intercrom Scp",
    "wof:placetype":"venue"
},
  "geometry": {"coordinates":[2.1573410034,41.432308197],"type":"Point"}
}