{
  "type": "Feature",
  "properties": {
    "addr:full":"Joan Maragall, 11 El Morell Tarragona 43760",
    "addr:housenumber":"11",
    "addr:postcode":"43760",
    "addr:street":"Joan Maragall;El Morell",
    "iso:country":"ES",
    "sg:address":"Joan Maragall, 11",
    "sg:city":"El Morell",
    "sg:orig_category":"Reposter\u00cdas",
    "sg:phone":"+34 977 84 21 57",
    "sg:postcode":"43760",
    "sg:province":"Tarragona",
    "wof:name":"Fleca De Les Comarques Meridionals De Catalunya S.l.",
    "wof:placetype":"venue"
},
  "geometry": {"coordinates":[1.2095279694,41.1909866333],"type":"Point"}
}