{
  "type": "Feature",
  "properties": {
    "addr:full":"Ctra Alicante, 38 Pe\u00d1icas Murcia 30163",
    "addr:housenumber":"38",
    "addr:postcode":"30163",
    "addr:street":"Ctra Alicante",
    "iso:country":"ES",
    "sg:address":"Ctra Alicante, 38",
    "sg:city":"Pe\u00d1icas",
    "sg:orig_category":"Molduras, Junquillos, Listones Y Molduras Perforadas",
    "sg:phone":"+34 968 86 58 67",
    "sg:postcode":"30163",
    "sg:province":"Murcia",
    "wof:name":"Martinez Espin Francisco",
    "wof:placetype":"venue"
},
  "geometry": {"coordinates":[-1.0834419727,38.0496711731],"type":"Point"}
}