{
  "type": "Feature",
  "properties": {
    "iso:country":"ES",
    "sg:address":"Carrer de Joan Samso, 6",
    "sg:city":"Caldes Montbui",
    "sg:orig_category":"Peluquer\u00cdas, Peluquer\u00cda Mixta",
    "sg:phone":"+34 938 65 28 00",
    "sg:postcode":"08140",
    "sg:province":"Barcelona",
    "wof:name":"M.i. Roca Perruquers S.l.",
    "wof:placetype":"venue"
},
  "geometry": {"coordinates":[2.1622340679,41.634437561],"type":"Point"}
}