{
  "type": "Feature",
  "properties": {
    "addr:full":"Barr Elexalde, S/n Elexalde Galdakao Vizcaya 48960",
    "addr:postcode":"48960",
    "addr:street":"Elexalde S / N Elexalde",
    "iso:country":"ES",
    "sg:address":"Barr Elexalde, S/n",
    "sg:city":"Elexalde Galdakao",
    "sg:orig_category":"Art\u00cdculos Funerarios (al Por Menor)",
    "sg:phone":"+34 944 56 72 66",
    "sg:postcode":"48960",
    "sg:province":"Vizcaya",
    "wof:name":"Funeraria Bilbaina S. A.",
    "wof:placetype":"venue"
},
  "geometry": {"coordinates":[-2.8470389843,43.2298049927],"type":"Point"}
}