{
  "type": "Feature",
  "properties": {
    "iso:country":"ES",
    "sg:address":"Carrer de Abdet, 5",
    "sg:city":"Callosa D'en Sarria",
    "sg:orig_category":"Doctores En Medicina",
    "sg:phone":"+34 965 88 19 08",
    "sg:postcode":"03510",
    "sg:province":"Alicante",
    "wof:name":"Llobel Bertomeu Vicente",
    "wof:placetype":"venue"
},
  "geometry": {"coordinates":[-0.1207797974,38.648399353],"type":"Point"}
}