{
  "type": "Feature",
  "properties": {
    "addr:full":"Av Mar (del), 21 Miami Playa Tarragona 43892",
    "addr:postcode":"43892",
    "addr:street":"Av;Del",
    "iso:country":"ES",
    "sg:address":"Av Mar (del), 21",
    "sg:city":"Miami Playa",
    "sg:orig_category":"Inmobiliaria (agencias)",
    "sg:phone":"+34 977 17 28 48",
    "sg:postcode":"43892",
    "sg:province":"Tarragona",
    "wof:name":"Finques Crisjoan Tarragona S.l.",
    "wof:placetype":"venue"
},
  "geometry": {"coordinates":[0.9392477274,41.0099830627],"type":"Point"}
}