{
  "type": "Feature",
  "properties": {
    "addr:full":"Calle de Real, 31 Almendralejo Badajoz 06200",
    "addr:housenumber":"31",
    "addr:postcode":"06200",
    "addr:street":"Calle De Real",
    "iso:country":"ES",
    "sg:address":"Calle de Real, 31",
    "sg:city":"Almendralejo",
    "sg:orig_category":"Abogados",
    "sg:phone":"+34 924 66 71 54",
    "sg:postcode":"06200",
    "sg:province":"Badajoz",
    "wof:name":"Castellano Alcantara Francisco Jose",
    "wof:placetype":"venue"
},
  "geometry": {"coordinates":[-6.4075131416,38.6839561462],"type":"Point"}
}