{
  "type": "Feature",
  "properties": {
    "addr:full":"Avda Aguirre Lehendakari, 143 Bilbao Vizcaya 48015",
    "addr:housenumber":"143",
    "addr:postcode":"48015",
    "addr:street":"Avda Aguirre Lehendakari",
    "iso:country":"ES",
    "sg:address":"Avda Aguirre Lehendakari, 143",
    "sg:city":"Bilbao",
    "sg:orig_category":"Papel Pintado (al Por Menor)",
    "sg:phone":"+34 944 75 81 93",
    "sg:postcode":"48015",
    "sg:province":"Vizcaya",
    "wof:name":"Ducar Martinez Antonio",
    "wof:placetype":"venue"
},
  "geometry": {"coordinates":[-2.9603490829,43.2770805359],"type":"Point"}
}