{
  "type": "Feature",
  "properties": {
    "addr:full":"Calle de Elio Antonio De Nebrija, 6 Rinconada Sevilla 41309",
    "addr:housenumber":"6",
    "addr:postcode":"41309",
    "addr:street":"Calle De Elio Antonio De Nebrija",
    "iso:country":"ES",
    "sg:address":"Calle de Elio Antonio De Nebrija, 6",
    "sg:city":"Rinconada",
    "sg:orig_category":"Publicidad (soportes Y Gesti\u00d3n)",
    "sg:phone":"+34 955 79 71 03",
    "sg:postcode":"41309",
    "sg:province":"Sevilla",
    "wof:name":"Parrado Varon S.l",
    "wof:placetype":"venue"
},
  "geometry": {"coordinates":[-5.9842133522,37.4854164124],"type":"Point"}
}