{
  "type": "Feature",
  "properties": {
    "iso:country":"ES",
    "sg:address":"Calle de Roma, 2",
    "sg:city":"Torrejon Ardoz",
    "sg:classifiers":[
        {
            "category":"Personal",
            "subcategory":"Barber",
            "type":"Services"
        }
    ],
    "sg:phone":"+34 916 77 39 88",
    "sg:postcode":"28850",
    "sg:province":"Madrid",
    "sg:tags":[
        "caballeros",
        "de",
        "peluqueros"
    ],
    "wof:name":"Guerrero Fernandez Francisco Manuel",
    "wof:placetype":"venue"
},
  "geometry": {"coordinates":[-3.4705369473,40.4582557678],"type":"Point"}
}