{
  "type": "Feature",
  "properties": {
    "addr:full":"Ebanista, 103 Aspe Alicante 03680",
    "addr:housenumber":"103",
    "addr:postcode":"03680",
    "addr:street":"Ebanista",
    "iso:country":"ES",
    "sg:address":"Ebanista, 103",
    "sg:city":"Aspe",
    "sg:orig_category":"Materias Pl\u00c1sticas: Art\u00cdculos Para La Industria",
    "sg:phone":"+34 965 49 52 92",
    "sg:postcode":"03680",
    "sg:province":"Alicante",
    "wof:name":"Gicagran S.l.",
    "wof:placetype":"venue"
},
  "geometry": {"coordinates":[-0.7560790181,38.3241500854],"type":"Point"}
}