{
  "type": "Feature",
  "properties": {
    "iso:country":"ES",
    "sg:address":"Carretera Leon, 21",
    "sg:city":"S. Cristobal Entrevi\u00f1as",
    "sg:orig_category":"Albergues",
    "sg:phone":"+34 980 64 39 19",
    "sg:postcode":"49690",
    "sg:province":"Zamora",
    "wof:name":"Benito Navarro Castro",
    "wof:placetype":"venue"
},
  "geometry": {"coordinates":[-5.6338539124,42.0473136902],"type":"Point"}
}