{
  "type": "Feature",
  "properties": {
    "iso:country":"ES",
    "sg:address":"Calle de Hilario Marco, 55",
    "sg:city":"Cazorla",
    "sg:orig_category":"Agencias De Viajes",
    "sg:phone":"+34 953 72 40 22",
    "sg:postcode":"23470",
    "sg:province":"Ja\u00e9n",
    "sg:website":"www.viajesbetula.com",
    "wof:name":"Viajes Betula S.l.",
    "wof:placetype":"venue"
},
  "geometry": {"coordinates":[-3.0047399998,37.9152297974],"type":"Point"}
}