{
  "type": "Feature",
  "properties": {
    "iso:country":"ES",
    "sg:address":"Calle de Ruiz Hernandez, 9",
    "sg:city":"Valladolid",
    "sg:orig_category":"Librer\u00cdas",
    "sg:phone":"+34 983 29 73 79",
    "sg:postcode":"47002",
    "sg:province":"Valladolid",
    "wof:name":"Redondo Cordero Jaime",
    "wof:placetype":"venue"
},
  "geometry": {"coordinates":[-4.7203330994,41.6529273987],"type":"Point"}
}