{
  "type": "Feature",
  "properties": {
    "addr:full":"Calle de Exposicion, 1 Guadalajara Guadalajara 19001",
    "addr:housenumber":"1",
    "addr:postcode":"19001",
    "addr:street":"Calle De Exposicion",
    "iso:country":"ES",
    "sg:address":"Calle de Exposicion, 1",
    "sg:city":"Guadalajara",
    "sg:orig_category":"Bisuter\u00cda, Joyer\u00cda, Relojer\u00cda (al Por Menor)",
    "sg:phone":"+34 949 25 50 70",
    "sg:postcode":"19001",
    "sg:province":"Guadalajara",
    "wof:name":"Hisamar De P.j. S.l.",
    "wof:placetype":"venue"
},
  "geometry": {"coordinates":[-3.1642894745,40.6319999695],"type":"Point"}
}