{
  "type": "Feature",
  "properties": {
    "addr:full":"Calle de Mercado (el), 6 Caudete Albacete 02660",
    "addr:postcode":"02660",
    "addr:street":"Calle De;El",
    "iso:country":"ES",
    "sg:address":"Calle de Mercado (el), 6",
    "sg:city":"Caudete",
    "sg:orig_category":"Centros De Coordinaci\u00d3n",
    "sg:phone":"+34 965 82 70 42",
    "sg:postcode":"02660",
    "sg:province":"Albacete",
    "wof:name":"Amoros Herrero Manuel",
    "wof:placetype":"venue"
},
  "geometry": {"coordinates":[-0.9890086055,38.7044334412],"type":"Point"}
}