{
  "type": "Feature",
  "properties": {
    "addr:full":"Calle de Feria, 8 Alhama Murcia Murcia 30840",
    "addr:housenumber":"8",
    "addr:postcode":"30840",
    "addr:street":"Calle De Feria",
    "iso:country":"ES",
    "sg:address":"Calle de Feria, 8",
    "sg:city":"Alhama Murcia",
    "sg:orig_category":"M\u00c9dicos: Naturistas",
    "sg:phone":"+34 968 63 06 98",
    "sg:postcode":"30840",
    "sg:province":"Murcia",
    "wof:name":"Martinez Martinez Juan Jose",
    "wof:placetype":"venue"
},
  "geometry": {"coordinates":[-1.4243210554,37.8515129089],"type":"Point"}
}