{
  "type": "Feature",
  "properties": {
    "iso:country":"ES",
    "sg:address":"Calle de Redonda, 7",
    "sg:city":"Pinos-puente",
    "sg:orig_category":"Fabricaci\u00d3n De Ventanas",
    "sg:phone":"+34 958 45 11 75",
    "sg:postcode":"18240",
    "sg:province":"Granada",
    "wof:name":"Recres S. L",
    "wof:placetype":"venue"
},
  "geometry": {"coordinates":[-3.7543690205,37.2501602173],"type":"Point"}
}