{
  "type": "Feature",
  "properties": {
    "addr:full":"Calle de Turia, 46 Valencia Valencia 46005",
    "addr:housenumber":"46",
    "addr:postcode":"46005",
    "addr:street":"Calle De Turia",
    "iso:country":"ES",
    "sg:address":"Calle de Turia, 46",
    "sg:city":"Valencia",
    "sg:orig_category":"Abogados",
    "sg:phone":"+34 963 11 17 92",
    "sg:postcode":"46005",
    "sg:province":"Valencia",
    "wof:name":"Sancho-tello Bertomeu Nuria",
    "wof:placetype":"venue"
},
  "geometry": {"coordinates":[-0.3852269948,39.4770965576],"type":"Point"}
}