{
  "type": "Feature",
  "properties": {
    "iso:country":"ES",
    "sg:address":"Avda Florida, 60",
    "sg:city":"Vigo",
    "sg:orig_category":"Supermercados Y Hipermercados",
    "sg:phone":"+34 986 24 25 60",
    "sg:postcode":"36210",
    "sg:province":"Pontevedra",
    "wof:name":"Distribuciones Froiz S.a.",
    "wof:placetype":"venue"
},
  "geometry": {"coordinates":[-8.7476491928,42.2103309631],"type":"Point"}
}