{
  "type": "Feature",
  "properties": {
    "iso:country":"ES",
    "sg:address":"Calle de Gerona, 66",
    "sg:city":"Camas",
    "sg:orig_category":"Farmacias",
    "sg:phone":"+34 954 39 57 04",
    "sg:postcode":"41900",
    "sg:province":"Sevilla",
    "wof:name":"Mena Alvarado Socorro",
    "wof:placetype":"venue"
},
  "geometry": {"coordinates":[-6.0374760628,37.3968696594],"type":"Point"}
}