{
  "type": "Feature",
  "properties": {
    "iso:country":"ES",
    "sg:address":"Calle de Maestro Mora, 7",
    "sg:city":"Yecla",
    "sg:orig_category":"Asesor\u00cda Fiscal Y Jur\u00cddica",
    "sg:phone":"+34 968 79 07 53",
    "sg:postcode":"30510",
    "sg:province":"Murcia",
    "wof:name":"Yago Boj Jose Manuel",
    "wof:placetype":"venue"
},
  "geometry": {"coordinates":[-1.110771656,38.6123275757],"type":"Point"}
}