{
  "type": "Feature",
  "properties": {
    "addr:full":"Calle de Misericordia, 9 Puerto De Santa Maria C\u00e1diz 11500",
    "addr:housenumber":"9",
    "addr:postcode":"11500",
    "addr:street":"Calle De Misericordia;Ca\u0301Diz",
    "iso:country":"ES",
    "sg:address":"Calle de Misericordia, 9",
    "sg:city":"Puerto De Santa Maria",
    "sg:orig_category":"Molduras, Junquillos, Listones Y Molduras Perforadas",
    "sg:phone":"+34 956 87 09 22",
    "sg:postcode":"11500",
    "sg:province":"C\u00e1diz",
    "wof:name":"Garcia Gomez Fernando",
    "wof:placetype":"venue"
},
  "geometry": {"coordinates":[-6.224656105,36.5984153748],"type":"Point"}
}