{
  "type": "Feature",
  "properties": {
    "iso:country":"ES",
    "sg:address":"Calle de Parque Eugenia De Montijo, 6",
    "sg:city":"Madrid",
    "sg:orig_category":"Asistencia Social",
    "sg:phone":"+34 914 62 93 75",
    "sg:postcode":"28047",
    "sg:province":"Madrid",
    "wof:name":"Asociacion Respuesta Social Siglo Xxi",
    "wof:placetype":"venue"
},
  "geometry": {"coordinates":[-3.753913641,40.378578186],"type":"Point"}
}