{
  "type": "Feature",
  "properties": {
    "addr:full":"Calle de Padre Damian, 3 Sevilla Sevilla 41011",
    "addr:housenumber":"3",
    "addr:postcode":"41011",
    "addr:street":"Calle De Padre Damian",
    "iso:country":"ES",
    "sg:address":"Calle de Padre Damian, 3",
    "sg:city":"Sevilla",
    "sg:orig_category":"Formaci\u00d3n Continuada (variada)",
    "sg:phone":"+34 954 27 65 56",
    "sg:postcode":"41011",
    "sg:province":"Sevilla",
    "wof:name":"Rodriguez Gonzalez Jose",
    "wof:placetype":"venue"
},
  "geometry": {"coordinates":[-5.9996762276,37.3753929138],"type":"Point"}
}