{
  "type": "Feature",
  "properties": {
    "addr:full":"Avda Miranda, 3 Barakaldo Vizcaya 48902",
    "addr:housenumber":"3",
    "addr:postcode":"48902",
    "addr:street":"Avda Miranda",
    "iso:country":"ES",
    "sg:address":"Avda Miranda, 3",
    "sg:city":"Barakaldo",
    "sg:orig_category":"Ropa Para Se\u00d1oras Y Caballeros (al Por Menor)",
    "sg:phone":"+34 944 37 85 05",
    "sg:postcode":"48902",
    "sg:province":"Vizcaya",
    "wof:name":"Jose Enrique Pazuelos Rodriguez",
    "wof:placetype":"venue"
},
  "geometry": {"coordinates":[-2.9934709072,43.2985916138],"type":"Point"}
}