{
  "type": "Feature",
  "properties": {
    "iso:country":"ES",
    "sg:address":"C/ Mossen Jacint Verdaguer, 53",
    "sg:city":"Banyoles",
    "sg:orig_category":"Internados & Ense\u00d1anza Privada",
    "sg:phone":"+34 972 57 01 62",
    "sg:postcode":"17820",
    "sg:province":"Girona",
    "wof:name":"Institucion Magdalena Aulina",
    "wof:placetype":"venue"
},
  "geometry": {"coordinates":[2.7609419823,42.1174240112],"type":"Point"}
}