{
  "type": "Feature",
  "properties": {
    "iso:country":"ES",
    "sg:address":"Calle de Secretario Padilla, 95",
    "sg:city":"Palmas De Gran Canaria",
    "sg:orig_category":"Ense\u00d1anza Variada",
    "sg:phone":"+34 928 26 50 78",
    "sg:postcode":"35010",
    "sg:province":"Las Palmas",
    "wof:name":"Instituto Formacion Canario S.l.",
    "wof:placetype":"venue"
},
  "geometry": {"coordinates":[-15.4425172806,28.1319313049],"type":"Point"}
}