{
  "type": "Feature",
  "properties": {
    "addr:full":"Avda Navarra, S/n Coru\u00d1a La Coru\u00f1a 15002",
    "addr:postcode":"15002",
    "addr:street":"Avda Navarra S / N Corun\u0303A La Corun\u0303A",
    "iso:country":"ES",
    "sg:address":"Avda Navarra, S/n",
    "sg:city":"Coru\u00d1a",
    "sg:orig_category":"Ferreter\u00cda (diversos)",
    "sg:phone":"+34 981 20 38 14",
    "sg:postcode":"15002",
    "sg:province":"La Coru\u00f1a",
    "wof:name":"Alvarez Porto Jose Antonio",
    "wof:placetype":"venue"
},
  "geometry": {"coordinates":[-8.4006414413,43.382232666],"type":"Point"}
}