{
  "type": "Feature",
  "properties": {
    "iso:country":"ES",
    "sg:address":"Rua Pai Crespo, 1",
    "sg:city":"Redondela",
    "sg:orig_category":"Psic\u00d3logos",
    "sg:phone":"+34 986 40 37 27",
    "sg:postcode":"36800",
    "sg:province":"Pontevedra",
    "wof:name":"Lareo Fernandez Margarita",
    "wof:placetype":"venue"
},
  "geometry": {"coordinates":[-8.6092290878,42.2811698914],"type":"Point"}
}