{
  "type": "Feature",
  "properties": {
    "iso:country":"ES",
    "sg:address":"Antime, 2",
    "sg:city":"Antime",
    "sg:orig_category":"Servicios Diversos",
    "sg:phone":"+34 986 36 03 30",
    "sg:postcode":"36380",
    "sg:province":"Pontevedra",
    "wof:name":"Gonzalez Giraldez Jose",
    "wof:placetype":"venue"
},
  "geometry": {"coordinates":[-8.7611093521,42.1116867065],"type":"Point"}
}