{
  "type": "Feature",
  "properties": {
    "addr:full":"Calle de Ontinyent, 1 Bocairent Valencia 46880",
    "addr:housenumber":"1",
    "addr:postcode":"46880",
    "addr:street":"Calle De Ontinyent",
    "iso:country":"ES",
    "sg:address":"Calle de Ontinyent, 1",
    "sg:city":"Bocairent",
    "sg:orig_category":"Bazares, Art\u00cdculos De Limpieza Y De Cocina (al Por Menor)",
    "sg:phone":"+34 962 35 07 48",
    "sg:postcode":"46880",
    "sg:province":"Valencia",
    "wof:name":"Trinidad Cabanes Belen",
    "wof:placetype":"venue"
},
  "geometry": {"coordinates":[-0.6156749725,38.7633895874],"type":"Point"}
}