{
  "type": "Feature",
  "properties": {
    "addr:full":"Calle de Sierra De Guadarrama, 27 Arganda Madrid 28500",
    "addr:housenumber":"27",
    "addr:postcode":"28500",
    "addr:street":"Calle De Sierra De Guadarrama",
    "iso:country":"ES",
    "sg:address":"Calle de Sierra De Guadarrama, 27",
    "sg:city":"Arganda",
    "sg:orig_category":"Maquinaria Para Industrias Diversas",
    "sg:phone":"+34 918 72 98 08",
    "sg:postcode":"28500",
    "sg:province":"Madrid",
    "sg:website":"www.imopsl.es",
    "wof:name":"Importacion Recambios Obras Publicas S.l.",
    "wof:placetype":"venue"
},
  "geometry": {"coordinates":[-3.4750521183,40.3066329956],"type":"Point"}
}