{
  "type": "Feature",
  "properties": {
    "addr:full":"Calle de Santo Domingo, 10 Marchena Sevilla 41620",
    "addr:housenumber":"10",
    "addr:postcode":"41620",
    "addr:street":"Calle De Santo Domingo",
    "iso:country":"ES",
    "sg:address":"Calle de Santo Domingo, 10",
    "sg:city":"Marchena",
    "sg:orig_category":"Transportes Por Carretera: Lotes Completos, Mercanc\u00cdas Diversas",
    "sg:phone":"+34 954 84 32 58",
    "sg:postcode":"41620",
    "sg:province":"Sevilla",
    "wof:name":"Quesada Berdugo Francisco Javier",
    "wof:placetype":"venue"
},
  "geometry": {"coordinates":[-5.4165530205,37.3290481567],"type":"Point"}
}