{
  "type": "Feature",
  "properties": {
    "iso:country":"ES",
    "sg:address":"Calle de Barahona, 16",
    "sg:city":"Le\u00f3n",
    "sg:orig_category":"Electricidad, Electr\u00d3nica: Material Y Suministros (al Por Mayor)",
    "sg:phone":"+34 987 21 55 16",
    "sg:postcode":"24003",
    "sg:province":"Le\u00f3n",
    "sg:website":"www.paginasamarillas.es",
    "wof:name":"Electronicos Leon S.l.",
    "wof:placetype":"venue"
},
  "geometry": {"coordinates":[-5.5670099258,42.5928649902],"type":"Point"}
}