{
  "type": "Feature",
  "properties": {
    "addr:full":"Rond Firal, 43 Figueres Girona 17600",
    "addr:housenumber":"43",
    "addr:postcode":"17600",
    "addr:street":"Firal",
    "iso:country":"ES",
    "sg:address":"Rond Firal, 43",
    "sg:city":"Figueres",
    "sg:orig_category":"Pod\u00d3logos: Pedicuros",
    "sg:phone":"+34 972 50 23 15",
    "sg:postcode":"17600",
    "sg:province":"Girona",
    "wof:name":"Rodriguez Limia Albino",
    "wof:placetype":"venue"
},
  "geometry": {"coordinates":[2.9581100941,42.2656898499],"type":"Point"}
}