{
  "type": "Feature",
  "properties": {
    "addr:full":"Calle de Montalban, 13 Malaga M\u00e1laga 29002",
    "addr:housenumber":"13",
    "addr:postcode":"29002",
    "addr:street":"Calle De Montalban;Ma\u0301Laga",
    "iso:country":"ES",
    "sg:address":"Calle de Montalban, 13",
    "sg:city":"Malaga",
    "sg:orig_category":"M\u00c1rmoles, Granitos Y Piedras Naturales",
    "sg:phone":"+34 952 32 88 29",
    "sg:postcode":"29002",
    "sg:province":"M\u00e1laga",
    "wof:name":"Marmolistas Amuedo S.l.",
    "wof:placetype":"venue"
},
  "geometry": {"coordinates":[-4.4294080734,36.7154388428],"type":"Point"}
}