{
  "type": "Feature",
  "properties": {
    "iso:country":"ES",
    "sg:address":"Calle de Santa Ana, 1",
    "sg:city":"Almendralejo",
    "sg:orig_category":"Lencer\u00cda Femenina, Corseter\u00cda, Trajes De Ba\u00d1o (al Por Menor)",
    "sg:phone":"+34 924 66 34 14",
    "sg:postcode":"06200",
    "sg:province":"Badajoz",
    "wof:name":"Delgado Aguilar Isabel",
    "wof:placetype":"venue"
},
  "geometry": {"coordinates":[-6.410405159,38.6856040955],"type":"Point"}
}