{
  "type": "Feature",
  "properties": {
    "addr:full":"Calle de Pastor, 10 Playa De Salinetas Las Palmas 35214",
    "addr:housenumber":"10",
    "addr:postcode":"35214",
    "addr:street":"Calle De Pastor;Palmas",
    "iso:country":"ES",
    "sg:address":"Calle de Pastor, 10",
    "sg:city":"Playa De Salinetas",
    "sg:orig_category":"Empresas De Carpinter\u00cda Met\u00c1lica",
    "sg:phone":"+34 928 13 19 40",
    "sg:postcode":"35214",
    "sg:province":"Las Palmas",
    "sg:website":"www.acinox.com",
    "wof:name":"Acinox S. L.",
    "wof:placetype":"venue"
},
  "geometry": {"coordinates":[-15.3887014389,27.9781303406],"type":"Point"}
}