{
  "type": "Feature",
  "properties": {
    "addr:full":"Carrer de Mossen Jaume Sole, S/n Cornella Llobregat Barcelona 08940",
    "addr:housenumber":"s / n",
    "addr:postcode":"08940",
    "addr:street":"Carrer De Mossen Jaume Sole",
    "iso:country":"ES",
    "sg:address":"Carrer de Mossen Jaume Sole, S/n",
    "sg:city":"Cornella Llobregat",
    "sg:orig_category":"Carnicer\u00cdas, Carnicer\u00cdas",
    "sg:phone":"+34 933 76 73 01",
    "sg:postcode":"08940",
    "sg:province":"Barcelona",
    "wof:name":"Montell Puigarnau Nuria",
    "wof:placetype":"venue"
},
  "geometry": {"coordinates":[2.075865984,41.3618812561],"type":"Point"}
}