{
  "type": "Feature",
  "properties": {
    "addr:full":"Av Mestre Josep Bonay, 28 Palafrugell Girona 17200",
    "addr:housenumber":"28",
    "addr:postcode":"17200",
    "addr:street":"Av Mestre Josep Bonay",
    "iso:country":"ES",
    "sg:address":"Av Mestre Josep Bonay, 28",
    "sg:city":"Palafrugell",
    "sg:orig_category":"Venta, Alquiler De V\u00cddeo",
    "sg:phone":"+34 972 61 06 30",
    "sg:postcode":"17200",
    "sg:province":"Girona",
    "wof:name":"Torrent Vila S.c.",
    "wof:placetype":"venue"
},
  "geometry": {"coordinates":[3.1689300537,41.9221191406],"type":"Point"}
}