{
  "type": "Feature",
  "properties": {
    "iso:country":"ES",
    "sg:address":"Calle de Mayor, 61",
    "sg:city":"Pilar Horadada",
    "sg:orig_category":"Perfumer\u00cda (al Por Menor)",
    "sg:phone":"+34 965 35 18 90",
    "sg:postcode":"03190",
    "sg:province":"Alicante",
    "wof:name":"Hernandez Lopez Pilar",
    "wof:placetype":"venue"
},
  "geometry": {"coordinates":[-0.7900379896,37.8642044067],"type":"Point"}
}