{
  "type": "Feature",
  "properties": {
    "addr:full":"Esca Santa Lucia, 1 Coru\u00d1a La Coru\u00f1a 15006",
    "addr:housenumber":"1",
    "addr:postcode":"15006",
    "addr:street":"Santa Lucia;La Corun\u0303A",
    "iso:country":"ES",
    "sg:address":"Esca Santa Lucia, 1",
    "sg:city":"Coru\u00d1a",
    "sg:orig_category":"Alimentaci\u00d3n General (al Por Menor)",
    "sg:phone":"+34 981 23 02 02",
    "sg:postcode":"15006",
    "sg:province":"La Coru\u00f1a",
    "wof:name":"Castro Varela Teresa",
    "wof:placetype":"venue"
},
  "geometry": {"coordinates":[-8.4048128128,43.3598175049],"type":"Point"}
}