{
  "type": "Feature",
  "properties": {
    "addr:full":"Carrer de Lisboa, 26 Barbera Valles Barcelona 08210",
    "addr:housenumber":"26",
    "addr:postcode":"08210",
    "addr:street":"Carrer De Lisboa",
    "iso:country":"ES",
    "sg:address":"Carrer de Lisboa, 26",
    "sg:city":"Barbera Valles",
    "sg:orig_category":"Artes Gr\u00c1ficas, Artes Pl\u00c1sticas (curso)",
    "sg:phone":"+34 937 29 10 67",
    "sg:postcode":"08210",
    "sg:province":"Barcelona",
    "wof:name":"Flores Guillem Cristina",
    "wof:placetype":"venue"
},
  "geometry": {"coordinates":[2.1300098896,41.5227851868],"type":"Point"}
}