{
  "type": "Feature",
  "properties": {
    "addr:full":"Pg Maragall, 40 Barcelona Barcelona 08041",
    "addr:housenumber":"40",
    "addr:postcode":"08041",
    "addr:street":"Pg Maragall",
    "iso:country":"ES",
    "sg:address":"Pg Maragall, 40",
    "sg:city":"Barcelona",
    "sg:orig_category":"Camiser\u00cda Y Ropa Interior Masculina (al Por Menor)",
    "sg:phone":"+34 934 55 02 16",
    "sg:postcode":"08041",
    "sg:province":"Barcelona",
    "wof:name":"Carbonell Roca Liberto",
    "wof:placetype":"venue"
},
  "geometry": {"coordinates":[2.1809620857,41.4147453308],"type":"Point"}
}