{
  "type": "Feature",
  "properties": {
    "iso:country":"ES",
    "sg:address":"Calle de Nosquera, 2",
    "sg:city":"Malaga",
    "sg:orig_category":"Peluqueros: De Se\u00d1oras",
    "sg:phone":"+34 952 22 30 33",
    "sg:postcode":"29008",
    "sg:province":"M\u00e1laga",
    "wof:name":"Alcaide Mesa Remedios",
    "wof:placetype":"venue"
},
  "geometry": {"coordinates":[-4.4218211174,36.7227516174],"type":"Point"}
}