{
  "type": "Feature",
  "properties": {
    "addr:full":"Carrer de Arago, 370 Barcelona Barcelona 08009",
    "addr:housenumber":"370",
    "addr:postcode":"08009",
    "addr:street":"Carrer De Arago",
    "iso:country":"ES",
    "sg:address":"Carrer de Arago, 370",
    "sg:city":"Barcelona",
    "sg:orig_category":"Agencias Y Agentes Comerciales, Representantes",
    "sg:phone":"+34 932 65 76 27",
    "sg:postcode":"08009",
    "sg:province":"Barcelona",
    "wof:name":"Reyes Vio Vicnete",
    "wof:placetype":"venue"
},
  "geometry": {"coordinates":[2.1720170975,41.3973503113],"type":"Point"}
}