{
  "type": "Feature",
  "properties": {
    "addr:full":"Carrer de Jacint Verdaguer, 24 Vic Barcelona 08500",
    "addr:housenumber":"24",
    "addr:postcode":"08500",
    "addr:street":"Carrer De Jacint Verdaguer",
    "iso:country":"ES",
    "sg:address":"Carrer de Jacint Verdaguer, 24",
    "sg:city":"Vic",
    "sg:orig_category":"Hilaturas, Hilos Y Actividades Relacionadas",
    "sg:phone":"+34 938 89 58 30",
    "sg:postcode":"08500",
    "sg:province":"Barcelona",
    "wof:name":"Vich Industrial S. A.",
    "wof:placetype":"venue"
},
  "geometry": {"coordinates":[2.2513120174,41.9308242798],"type":"Point"}
}