{
  "type": "Feature",
  "properties": {
    "addr:full":"Calle de San Cosme, S/n Iciz Navarra 31451",
    "addr:housenumber":"s",
    "addr:postcode":"31451",
    "addr:street":"Calle De San Cosme;/ N Iciz Navarra",
    "iso:country":"ES",
    "sg:address":"Calle de San Cosme, S/n",
    "sg:city":"Iciz",
    "sg:orig_category":"Montaje (empresas De)",
    "sg:phone":"+34 948 47 00 06",
    "sg:postcode":"31451",
    "sg:province":"Navarra",
    "wof:name":"Almisala S.l.",
    "wof:placetype":"venue"
},
  "geometry": {"coordinates":[-1.0890339613,42.7845497131],"type":"Point"}
}