{
  "type": "Feature",
  "properties": {
    "iso:country":"ES",
    "sg:address":"Calle de Lavadero, S/n",
    "sg:city":"Tardienta",
    "sg:orig_category":"Plomeros",
    "sg:phone":"+34 974 25 34 02",
    "sg:postcode":"22240",
    "sg:province":"Huesca",
    "wof:name":"Foncagas Osca S.l.",
    "wof:placetype":"venue"
},
  "geometry": {"coordinates":[-0.5367040038,41.9768104553],"type":"Point"}
}