{
  "type": "Feature",
  "properties": {
    "addr:full":"Ctra Malaga, 79 Alhaurin El Grande M\u00e1laga 29120",
    "addr:housenumber":"79",
    "addr:postcode":"29120",
    "addr:street":"Ctra Malaga",
    "iso:country":"ES",
    "sg:address":"Ctra Malaga, 79",
    "sg:city":"Alhaurin El Grande",
    "sg:orig_category":"Empresarios",
    "sg:phone":"+34 952 49 13 31",
    "sg:postcode":"29120",
    "sg:province":"M\u00e1laga",
    "wof:name":"Managa Construcciones Y Contratas",
    "wof:placetype":"venue"
},
  "geometry": {"coordinates":[-4.6911292076,36.6420783997],"type":"Point"}
}