{
  "type": "Feature",
  "properties": {
    "iso:country":"ES",
    "sg:address":"Rua Calvo Sotelo, 32",
    "sg:city":"Vilanova",
    "sg:orig_category":"Promotores Constructores",
    "sg:phone":"+34 982 12 14 01",
    "sg:postcode":"27760",
    "sg:province":"Lugo",
    "wof:name":"Construcciones Josbi C.b.",
    "wof:placetype":"venue"
},
  "geometry": {"coordinates":[-7.2977337837,43.4696350098],"type":"Point"}
}