{
  "type": "Feature",
  "properties": {
    "addr:full":"Carrer de Paris, 6 Rubi Barcelona 08191",
    "addr:housenumber":"6",
    "addr:postcode":"08191",
    "addr:street":"Carrer De Paris",
    "iso:country":"ES",
    "sg:address":"Carrer de Paris, 6",
    "sg:city":"Rubi",
    "sg:orig_category":"Aluminio Y Aleaciones (producci\u00d3n, Transformaci\u00d3n, Negocio)",
    "sg:phone":"+34 935 88 83 38",
    "sg:postcode":"08191",
    "sg:province":"Barcelona",
    "sg:website":"www.alucenter.es",
    "wof:name":"Aluminium Center S.a.",
    "wof:placetype":"venue"
},
  "geometry": {"coordinates":[2.0263843536,41.4806861877],"type":"Point"}
}