{
  "type": "Feature",
  "properties": {
    "iso:country":"ES",
    "sg:address":"Calle de Dos De Mayo, 54",
    "sg:city":"Zaragoza",
    "sg:orig_category":"Reposter\u00cdas",
    "sg:phone":"+34 976 37 18 41",
    "sg:postcode":"50007",
    "sg:province":"Zaragoza",
    "wof:name":"Dolce-pan Xxi",
    "wof:placetype":"venue"
},
  "geometry": {"coordinates":[-0.8749073744,41.6361083984],"type":"Point"}
}