{
  "type": "Feature",
  "properties": {
    "addr:full":"Calle de Fuente Del Prado, 11 Oviedo Asturias 33009",
    "addr:housenumber":"11",
    "addr:postcode":"33009",
    "addr:street":"Calle De Fuente Del Prado",
    "iso:country":"ES",
    "sg:address":"Calle de Fuente Del Prado, 11",
    "sg:city":"Oviedo",
    "sg:orig_category":"Frutas Y Legumbres Frescas (al Por Mayor)",
    "sg:phone":"+34 985 22 27 03",
    "sg:postcode":"33009",
    "sg:province":"Asturias",
    "wof:name":"Fernandez Orviz Maria Pilar Fe",
    "wof:placetype":"venue"
},
  "geometry": {"coordinates":[-5.8417978287,43.3561477661],"type":"Point"}
}