{
  "type": "Feature",
  "properties": {
    "addr:full":"Calle de Juan De La Cosa, 2 Marbella M\u00e1laga 29600",
    "addr:housenumber":"2",
    "addr:postcode":"29600",
    "addr:street":"Calle De Juan De La Cosa;Ma\u0301Laga",
    "iso:country":"ES",
    "sg:address":"Calle de Juan De La Cosa, 2",
    "sg:city":"Marbella",
    "sg:orig_category":"Almacenes Frigor\u00cdficos",
    "sg:phone":"+34 952 85 94 44",
    "sg:postcode":"29600",
    "sg:province":"M\u00e1laga",
    "wof:name":"Rodriguez Munoz Joaquin",
    "wof:placetype":"venue"
},
  "geometry": {"coordinates":[-4.8777499199,36.5104026794],"type":"Point"}
}