{
  "type": "Feature",
  "properties": {
    "addr:full":"Carrer de Gaia (del) - Torreforta, 13 Torreforta Tarragona 43006",
    "addr:housenumber":"13",
    "addr:postcode":"43006",
    "addr:street":"Carrer De Gaia Del Torreforta",
    "iso:country":"ES",
    "sg:address":"Carrer de Gaia (del) - Torreforta, 13",
    "sg:city":"Torreforta",
    "sg:orig_category":"Alimentaci\u00d3n General (al Por Menor)",
    "sg:phone":"+34 977 54 04 32",
    "sg:postcode":"43006",
    "sg:province":"Tarragona",
    "wof:name":"Vizcarro Burrut Maria Pilar",
    "wof:placetype":"venue"
},
  "geometry": {"coordinates":[1.2180299759,41.1190261841],"type":"Point"}
}