{
  "type": "Feature",
  "properties": {
    "addr:full":"Calle de San Ildefonso, 45 Sector Toledo 45111",
    "addr:housenumber":"45",
    "addr:postcode":"45111",
    "addr:street":"Calle De San Ildefonso",
    "iso:country":"ES",
    "sg:address":"Calle de San Ildefonso, 45",
    "sg:city":"Sector",
    "sg:orig_category":"Cr\u00cda De Animales",
    "sg:phone":"+34 925 37 84 01",
    "sg:postcode":"45111",
    "sg:province":"Toledo",
    "wof:name":"Gestion De Recursos Cinegeticos S.l.",
    "wof:placetype":"venue"
},
  "geometry": {"coordinates":[-4.0260148048,39.804901123],"type":"Point"}
}