{
  "type": "Feature",
  "properties": {
    "iso:country":"ES",
    "sg:address":"Calle de Santa Gertrudis, 94",
    "sg:city":"Cieza",
    "sg:orig_category":"Plomeros",
    "sg:phone":"+34 968 76 43 96",
    "sg:postcode":"30530",
    "sg:province":"Murcia",
    "wof:name":"Morcillo Yuste Manuel",
    "wof:placetype":"venue"
},
  "geometry": {"coordinates":[-1.423176527,38.2407646179],"type":"Point"}
}