{
  "type": "Feature",
  "properties": {
    "addr:full":"L. Bravo, 24 Villalonquejar Burgos 09001",
    "addr:housenumber":"24",
    "addr:postcode":"09001",
    "addr:street":"L. Bravo",
    "iso:country":"ES",
    "sg:address":"L. Bravo, 24",
    "sg:city":"Villalonquejar",
    "sg:orig_category":"Venta, Instalaci\u00d3n De Calefacci\u00d3n",
    "sg:phone":"+34 947 29 80 34",
    "sg:postcode":"09001",
    "sg:province":"Burgos",
    "wof:name":"Instalaciones Ferma Sl",
    "wof:placetype":"venue"
},
  "geometry": {"coordinates":[-3.7310340405,42.3711547852],"type":"Point"}
}