{
  "type": "Feature",
  "properties": {
    "iso:country":"ES",
    "sg:address":"Carr Paborde Marti, 3",
    "sg:city":"Ciutadella Menorca",
    "sg:orig_category":"Asociaciones Y Clubs Deportivos",
    "sg:phone":"+34 971 38 19 09",
    "sg:postcode":"07760",
    "sg:province":"Islas Baleares",
    "wof:name":"Club Gimastic Ciudadela C.b.",
    "wof:placetype":"venue"
},
  "geometry": {"coordinates":[3.8419039249,40.0010070801],"type":"Point"}
}