{
  "type": "Feature",
  "properties": {
    "iso:country":"ES",
    "sg:address":"Calle de Verano, 32",
    "sg:city":"Torrejon Ardoz",
    "sg:orig_category":"Maquinaria Neum\u00c1tica",
    "sg:phone":"+34 916 75 86 65",
    "sg:postcode":"28850",
    "sg:province":"Madrid",
    "wof:name":"Agrupacion Tecnica Comercial S.a.",
    "wof:placetype":"venue"
},
  "geometry": {"coordinates":[-3.4864323139,40.4460678101],"type":"Point"}
}