{
  "type": "Feature",
  "properties": {
    "iso:country":"ES",
    "sg:address":"Pase Rollo, 95",
    "sg:city":"Salamanca",
    "sg:orig_category":"Tintorer\u00cdas, Limpieza En Seco",
    "sg:phone":"+34 923 18 51 16",
    "sg:postcode":"37003",
    "sg:province":"Salamanca",
    "wof:name":"Martin Marcos Francisco Javier",
    "wof:placetype":"venue"
},
  "geometry": {"coordinates":[-5.6481180191,40.968132019],"type":"Point"}
}