{
  "type": "Feature",
  "properties": {
    "iso:country":"ES",
    "sg:address":"Carrer de Pescadors, 5",
    "sg:city":"Cambrils",
    "sg:orig_category":"Carnicer\u00cdas, Carnicer\u00cdas",
    "sg:phone":"+34 977 36 01 93",
    "sg:postcode":"43850",
    "sg:province":"Tarragona",
    "wof:name":"Salinas Salinas Daniel",
    "wof:placetype":"venue"
},
  "geometry": {"coordinates":[1.0613050461,41.0655555725],"type":"Point"}
}