{
  "type": "Feature",
  "properties": {
    "addr:full":"Cllo Villar (del), 2 Almagro Ciudad Real 13270",
    "addr:postcode":"13270",
    "iso:country":"ES",
    "sg:address":"Cllo Villar (del), 2",
    "sg:city":"Almagro",
    "sg:orig_category":"Art\u00cdculos De Regalo (al Por Menor)",
    "sg:phone":"+34 926 86 06 22",
    "sg:postcode":"13270",
    "sg:province":"Ciudad Real",
    "wof:name":"Cuadra Costoso Maria De Las Nieves",
    "wof:placetype":"venue"
},
  "geometry": {"coordinates":[-3.7093889713,38.8842353821],"type":"Point"}
}