{
  "type": "Feature",
  "properties": {
    "addr:full":"Rbla Prim, 226 Barcelona Barcelona 08020",
    "addr:housenumber":"226",
    "addr:postcode":"08020",
    "addr:street":"Rbla Prim",
    "iso:country":"ES",
    "sg:address":"Rbla Prim, 226",
    "sg:city":"Barcelona",
    "sg:orig_category":"Bancos",
    "sg:phone":"+34 934 98 79 10",
    "sg:postcode":"08020",
    "sg:province":"Barcelona",
    "sg:website":"www.bancogui.es",
    "wof:name":"Banco Guipuzcoano S.a.",
    "wof:placetype":"venue"
},
  "geometry": {"coordinates":[2.2034540176,41.4237709045],"type":"Point"}
}