{
  "type": "Feature",
  "properties": {
    "iso:country":"ES",
    "sg:address":"Urb Apartaclub La Barrosa I, 20",
    "sg:city":"Gallos -cerromolino",
    "sg:orig_category":"Piscinas, Accesorios, Suministros (fabricaci\u00d3n, Al Por Mayor)",
    "sg:phone":"+34 956 53 35 52",
    "sg:postcode":"11130",
    "sg:province":"C\u00e1diz",
    "wof:name":"Garcia Diaz Ramon",
    "wof:placetype":"venue"
},
  "geometry": {"coordinates":[-6.1447038651,36.4212188721],"type":"Point"}
}