{
  "type": "Feature",
  "properties": {
    "addr:full":"Pase Rosa, 44 Toledo Toledo 45006",
    "addr:housenumber":"44",
    "addr:postcode":"45006",
    "addr:street":"Rosa",
    "iso:country":"ES",
    "sg:address":"Pase Rosa, 44",
    "sg:city":"Toledo",
    "sg:orig_category":"Comercio, Reparaci\u00d3n De Bicicletas, De Motocicletas, De Accesorios",
    "sg:phone":"+34 925 21 66 05",
    "sg:postcode":"45006",
    "sg:province":"Toledo",
    "wof:name":"Diaz Mu\u00f1oz Lucia",
    "wof:placetype":"venue"
},
  "geometry": {"coordinates":[-4.0053992271,39.860748291],"type":"Point"}
}