{
  "type": "Feature",
  "properties": {
    "addr:full":"Carrer de Progres, 25 Gava Barcelona 08850",
    "addr:housenumber":"25",
    "addr:postcode":"08850",
    "addr:street":"Carrer De Progres",
    "iso:country":"ES",
    "sg:address":"Carrer de Progres, 25",
    "sg:city":"Gava",
    "sg:orig_category":"Organismos De Reclutamiento",
    "sg:phone":"+34 936 38 92 73",
    "sg:postcode":"08850",
    "sg:province":"Barcelona",
    "wof:name":"Qualitat I Formacio Consultoria I Gestio S.l.",
    "wof:placetype":"venue"
},
  "geometry": {"coordinates":[2.0111889839,41.2991027832],"type":"Point"}
}