{
  "type": "Feature",
  "properties": {
    "addr:full":"Carrer de Gonzalez Tablas, 7 Barcelona Barcelona 08034",
    "addr:housenumber":"7",
    "addr:postcode":"08034",
    "addr:street":"Carrer De Gonzalez Tablas",
    "iso:country":"ES",
    "sg:address":"Carrer de Gonzalez Tablas, 7",
    "sg:city":"Barcelona",
    "sg:orig_category":"Productos Qu\u00cdmicos (fabricaci\u00d3n, Al Por Mayor)",
    "sg:phone":"+34 932 80 20 50",
    "sg:postcode":"08034",
    "sg:province":"Barcelona",
    "wof:name":"Rohm And Haas Espa\u00f1a S.l.",
    "wof:placetype":"venue"
},
  "geometry": {"coordinates":[2.1095108986,41.3852310181],"type":"Point"}
}