{
  "type": "Feature",
  "properties": {
    "addr:full":"Cno Camps, S/n Fabara Zaragoza 50793",
    "addr:housenumber":"s / n",
    "addr:postcode":"50793",
    "addr:street":"Cno Camps",
    "iso:country":"ES",
    "sg:address":"Cno Camps, S/n",
    "sg:city":"Fabara",
    "sg:orig_category":"Cr\u00cda De Cerdos",
    "sg:phone":"+34 976 63 40 48",
    "sg:postcode":"50793",
    "sg:province":"Zaragoza",
    "wof:name":"Agropecuaria Badia Campanales S.l.",
    "wof:placetype":"venue"
},
  "geometry": {"coordinates":[0.170308,41.176311],"type":"Point"}
}