{
  "type": "Feature",
  "properties": {
    "iso:country":"ES",
    "sg:address":"C/ Major, 28",
    "sg:city":"Puigcerda",
    "sg:orig_category":"Ropa Para Caballeros (al Por Menor)",
    "sg:phone":"+34 972 14 01 52",
    "sg:postcode":"17520",
    "sg:province":"Girona",
    "wof:name":"Escribano Puigbertran Ramon",
    "wof:placetype":"venue"
},
  "geometry": {"coordinates":[1.9271379709,42.4320678711],"type":"Point"}
}