{
  "type": "Feature",
  "properties": {
    "addr:full":"C/ Escoles Pies, 16 Puigcerda Girona 17520",
    "addr:housenumber":"16",
    "addr:postcode":"17520",
    "addr:street":"C / Escoles Pies",
    "iso:country":"ES",
    "sg:address":"C/ Escoles Pies, 16",
    "sg:city":"Puigcerda",
    "sg:orig_category":"Ropa Para Ni\u00d1os (al Por Menor)",
    "sg:phone":"+34 972 88 04 89",
    "sg:postcode":"17520",
    "sg:province":"Girona",
    "wof:name":"Arteaga Valverde Concepcion",
    "wof:placetype":"venue"
},
  "geometry": {"coordinates":[1.9287420511,42.4314994812],"type":"Point"}
}