{
  "type": "Feature",
  "properties": {
    "addr:full":"Calle de Tomas Pelayo, 7 Zaragoza Zaragoza 50009",
    "addr:housenumber":"7",
    "addr:postcode":"50009",
    "addr:street":"Calle De Tomas Pelayo",
    "iso:country":"ES",
    "sg:address":"Calle de Tomas Pelayo, 7",
    "sg:city":"Zaragoza",
    "sg:classifiers":[
        {
            "category":"Personal",
            "subcategory":"Barber",
            "type":"Services"
        }
    ],
    "sg:phone":"+34 976 56 77 21",
    "sg:postcode":"50009",
    "sg:province":"Zaragoza",
    "sg:tags":[
        "caballeros",
        "de",
        "peluqueros"
    ],
    "wof:name":"Lozano Gomez Alfredo",
    "wof:placetype":"venue"
},
  "geometry": {"coordinates":[-0.9106749892,41.6317634583],"type":"Point"}
}