{
  "type": "Feature",
  "properties": {
    "addr:full":"Calle de Murias, 9 Fuenlabrada Madrid 28947",
    "addr:housenumber":"9",
    "addr:postcode":"28947",
    "addr:street":"Calle De Murias",
    "iso:country":"ES",
    "sg:address":"Calle de Murias, 9",
    "sg:city":"Fuenlabrada",
    "sg:orig_category":"Fabricaci\u00d3n De Sobres, Bolsas Y Fundas",
    "sg:phone":"+34 916 42 08 08",
    "sg:postcode":"28947",
    "sg:province":"Madrid",
    "wof:name":"Bolsos Alexander Sl",
    "wof:placetype":"venue"
},
  "geometry": {"coordinates":[-3.7513010502,40.2705116272],"type":"Point"}
}