{
  "type": "Feature",
  "properties": {
    "iso:country":"ES",
    "sg:address":"Carrer de Marathon, 108",
    "sg:city":"Mataro",
    "sg:orig_category":"Fabricaci\u00d3n De Su\u00c9ters Y Chalecos De Punto",
    "sg:phone":"+34 937 99 25 03",
    "sg:postcode":"08303",
    "sg:province":"Barcelona",
    "wof:name":"Mallo Blanco Antonio",
    "wof:placetype":"venue"
},
  "geometry": {"coordinates":[2.4236249924,41.5349121094],"type":"Point"}
}