{
  "type": "Feature",
  "properties": {
    "iso:country":"ES",
    "sg:address":"Estacion, S/n",
    "sg:city":"Cantillana",
    "sg:orig_category":"Art\u00cdculos De Limpieza Y De Cocina (fabricaci\u00d3n, Al Por Mayor)",
    "sg:phone":"+34 955 73 20 48",
    "sg:postcode":"41320",
    "sg:province":"Sevilla",
    "wof:name":"Bravo Garcia Rocio",
    "wof:placetype":"venue"
},
  "geometry": {"coordinates":[-5.822974205,37.6073455811],"type":"Point"}
}