{
  "type": "Feature",
  "properties": {
    "addr:full":"Almendro, 8 Galapagar Madrid 28250",
    "addr:housenumber":"8",
    "addr:postcode":"28250",
    "addr:street":"Almendro",
    "iso:country":"ES",
    "sg:address":"Almendro, 8",
    "sg:city":"Galapagar",
    "sg:orig_category":"Abogados",
    "sg:phone":"+34 918 59 05 07",
    "sg:postcode":"28250",
    "sg:province":"Madrid",
    "wof:name":"Camara Gonzalez Francisco",
    "wof:placetype":"venue"
},
  "geometry": {"coordinates":[-3.971214056,40.5839805603],"type":"Point"}
}