{
  "type": "Feature",
  "properties": {
    "iso:country":"ES",
    "sg:address":"Calle de Poeta Francisco Antonio Jimenez, 28",
    "sg:city":"Yecla",
    "sg:orig_category":"Barnizadores",
    "sg:phone":"+34 968 79 31 18",
    "sg:postcode":"30510",
    "sg:province":"Murcia",
    "wof:name":"Barnizados Rodrima S.l.",
    "wof:placetype":"venue"
},
  "geometry": {"coordinates":[-1.1368769407,38.6094207764],"type":"Point"}
}