{
  "type": "Feature",
  "properties": {
    "iso:country":"ES",
    "sg:address":"Carrer de Pais Basc, 17",
    "sg:city":"Cambrils",
    "sg:orig_category":"Asesor\u00cda Sobre Comunicaci\u00d3n De Empresas",
    "sg:phone":"+34 977 36 59 41",
    "sg:postcode":"43850",
    "sg:province":"Tarragona",
    "wof:name":"Gonzalo Perdrix I Associats S.l.",
    "wof:placetype":"venue"
},
  "geometry": {"coordinates":[1.0569499731,41.0691146851],"type":"Point"}
}