{
  "type": "Feature",
  "properties": {
    "addr:full":"Trva Rioja, 6 Madrid Madrid 28042",
    "addr:housenumber":"6",
    "addr:postcode":"28042",
    "addr:street":"Trva Rioja",
    "iso:country":"ES",
    "sg:address":"Trva Rioja, 6",
    "sg:city":"Madrid",
    "sg:orig_category":"Importaci\u00d3n",
    "sg:phone":"+34 914 47 09 08",
    "sg:postcode":"28042",
    "sg:province":"Madrid",
    "wof:name":"Mapas Consultores S. A.",
    "wof:placetype":"venue"
},
  "geometry": {"coordinates":[-3.5910680294,40.4556427002],"type":"Point"}
}