{
  "type": "Feature",
  "properties": {
    "addr:full":"G.v. Lopez De Haro D. Diego, 84 Bilbao Vizcaya 48011",
    "addr:housenumber":"84",
    "addr:postcode":"48011",
    "addr:street":"Lopez De Haro D. Diego",
    "iso:country":"ES",
    "sg:address":"G.v. Lopez De Haro D. Diego, 84",
    "sg:city":"Bilbao",
    "sg:orig_category":"M\u00c9dicos: Anatom\u00cda Patol\u00d3gica Y Citolog\u00cda",
    "sg:phone":"+34 944 42 47 11",
    "sg:postcode":"48011",
    "sg:province":"Vizcaya",
    "wof:name":"De Los Rios Sainz De La Maza Antonio",
    "wof:placetype":"venue"
},
  "geometry": {"coordinates":[-2.9440329075,43.2651367188],"type":"Point"}
}