{
  "type": "Feature",
  "properties": {
    "addr:full":"B (pol Talluntxe), 94 Noain Navarra 31110",
    "addr:housenumber":"94",
    "addr:postcode":"31110",
    "addr:street":"Talluntxe",
    "iso:country":"ES",
    "sg:address":"B (pol Talluntxe), 94",
    "sg:city":"Noain",
    "sg:orig_category":"Revisi\u00d3n, Reconstrucci\u00d3n De M\u00c1quinas Y Herramientas",
    "sg:phone":"+34 948 31 60 04",
    "sg:postcode":"31110",
    "sg:province":"Navarra",
    "sg:website":"www.wurth.es",
    "wof:name":"Wurth Espa\u00f1a S.a.",
    "wof:placetype":"venue"
},
  "geometry": {"coordinates":[-1.5935460329,42.7209968567],"type":"Point"}
}