{
  "type": "Feature",
  "properties": {
    "addr:full":"Carrer de Concepcion Arenal, 222 Barcelona Barcelona 08030",
    "addr:housenumber":"222",
    "addr:postcode":"08030",
    "addr:street":"Carrer De Concepcion Arenal",
    "iso:country":"ES",
    "sg:address":"Carrer de Concepcion Arenal, 222",
    "sg:city":"Barcelona",
    "sg:orig_category":"Quiropr\u00c1cticos",
    "sg:phone":"+34 932 74 24 00",
    "sg:postcode":"08030",
    "sg:province":"Barcelona",
    "wof:name":"Espejo Carrera Araceli",
    "wof:placetype":"venue"
},
  "geometry": {"coordinates":[2.1847279072,41.4307861328],"type":"Point"}
}