{
  "type": "Feature",
  "properties": {
    "iso:country":"ES",
    "sg:address":"Polig. Ind. Las Chafiras, 21",
    "sg:city":"Las Chafiras",
    "sg:orig_category":"Venta, Colocaci\u00d3n, Reparaci\u00d3n De Parabrisas, Techos Descapotables",
    "sg:phone":"+34 922 73 50 85",
    "sg:postcode":"38639",
    "sg:province":"Santa Cruz De Tenerife",
    "wof:name":"Tinerfe\u00f1a De Parabrisas S.l.",
    "wof:placetype":"venue"
},
  "geometry": {"coordinates":[-16.6115474701,28.0350246429],"type":"Point"}
}