{
  "type": "Feature",
  "properties": {
    "iso:country":"ES",
    "sg:address":"Avda Alt Rei En Jaume I (l'), 32",
    "sg:city":"Altea",
    "sg:orig_category":"Bisuter\u00cda, Joyer\u00cda, Relojer\u00cda (al Por Menor)",
    "sg:phone":"+34 965 84 24 91",
    "sg:postcode":"03590",
    "sg:province":"Alicante",
    "wof:name":"Amares Complementos S.l.",
    "wof:placetype":"venue"
},
  "geometry": {"coordinates":[-0.0279866997,38.6424942017],"type":"Point"}
}