{
  "type": "Feature",
  "properties": {
    "iso:country":"ES",
    "sg:address":"Calle de Gonzalo De Berceo, 29",
    "sg:city":"Logro\u00f1o",
    "sg:orig_category":"Patatas (al Por Mayor)",
    "sg:phone":"+34 941 22 15 22",
    "sg:postcode":"26005",
    "sg:province":"La Rioja",
    "wof:name":"Aransay Montoya Juan Antonio",
    "wof:placetype":"venue"
},
  "geometry": {"coordinates":[-2.458647728,42.46641922],"type":"Point"}
}