{
  "type": "Feature",
  "properties": {
    "addr:full":"Calle de General Pardi\u00d1as, 80 Madrid Madrid 28006",
    "addr:housenumber":"80",
    "addr:postcode":"madrid;28006",
    "addr:street":"Calle De General Pardin\u0303As",
    "iso:country":"ES",
    "sg:address":"Calle de General Pardi\u00d1as, 80",
    "sg:city":"Madrid",
    "sg:orig_category":"Molduras, Junquillos, Listones Y Molduras Perforadas",
    "sg:phone":"+34 914 02 24 58",
    "sg:postcode":"28006",
    "sg:province":"Madrid",
    "wof:name":"Serrano Amores Jose Alberto",
    "wof:placetype":"venue"
},
  "geometry": {"coordinates":[-3.6779060364,40.431640625],"type":"Point"}
}