{
  "type": "Feature",
  "properties": {
    "iso:country":"ES",
    "sg:address":"Calle de Juan Alzaga, 4",
    "sg:city":"Amorebieta",
    "sg:orig_category":"Asociaciones, Organismos Culturales Y Socioeducativos",
    "sg:phone":"+34 946 73 04 83",
    "sg:postcode":"48340",
    "sg:province":"Vizcaya",
    "wof:name":"Sociedad Artistico Cultural Zornoza",
    "wof:placetype":"venue"
},
  "geometry": {"coordinates":[-2.7321588993,43.2210960388],"type":"Point"}
}