{
  "type": "Feature",
  "properties": {
    "iso:country":"ES",
    "sg:address":"Avda Medina Del Campo, 13",
    "sg:city":"Valladolid",
    "sg:orig_category":"Caf\u00c9s, Bares, Cervecer\u00cdas",
    "sg:phone":"+34 983 47 95 62",
    "sg:postcode":"47014",
    "sg:province":"Valladolid",
    "wof:name":"Alvarez Moro Jose Antonio",
    "wof:placetype":"venue"
},
  "geometry": {"coordinates":[-4.7469987869,41.6335144043],"type":"Point"}
}