{
  "type": "Feature",
  "properties": {
    "iso:country":"ES",
    "sg:address":"Carrer de Lola Anglada, 1",
    "sg:city":"S. Cugat Valles",
    "sg:orig_category":"Asesor\u00cdas Y Estudios Financieros",
    "sg:phone":"+34 935 89 75 61",
    "sg:postcode":"08173",
    "sg:province":"Barcelona",
    "wof:name":"Antolin Bu\u00f1uel Javier",
    "wof:placetype":"venue"
},
  "geometry": {"coordinates":[2.0688455105,41.4737472534],"type":"Point"}
}