{
  "type": "Feature",
  "properties": {
    "addr:full":"Calle de Carmenes Los, 14 Arroyo De La Miel-benalmadena Costa M\u00e1laga 29631",
    "addr:housenumber":"14",
    "addr:postcode":"29631",
    "addr:street":"Calle De Carmenes Los;Ma\u0301Laga",
    "iso:country":"ES",
    "sg:address":"Calle de Carmenes Los, 14",
    "sg:city":"Arroyo De La Miel-benalmadena Costa",
    "sg:orig_category":"Agencias Y Agentes Comerciales, Representantes",
    "sg:phone":"+34 952 96 45 84",
    "sg:postcode":"29631",
    "sg:province":"M\u00e1laga",
    "wof:name":"Gonzalez Vargas Margarita",
    "wof:placetype":"venue"
},
  "geometry": {"coordinates":[-4.5301365852,36.6029853821],"type":"Point"}
}