{
  "type": "Feature",
  "properties": {
    "addr:full":"Calle de Cebreros, 26 Madrid Madrid 28011",
    "addr:housenumber":"26",
    "addr:postcode":"madrid;28011",
    "addr:street":"Calle De Cebreros",
    "iso:country":"ES",
    "sg:address":"Calle de Cebreros, 26",
    "sg:city":"Madrid",
    "sg:orig_category":"Ropa Para Ni\u00d1os (al Por Menor)",
    "sg:phone":"+34 914 64 90 88",
    "sg:postcode":"28011",
    "sg:province":"Madrid",
    "wof:name":"Trevi\u00f1o Perez Emilia",
    "wof:placetype":"venue"
},
  "geometry": {"coordinates":[-3.743942976,40.4051094055],"type":"Point"}
}