{
  "type": "Feature",
  "properties": {
    "iso:country":"ES",
    "sg:address":"Calle de Cervantes, 12",
    "sg:city":"Moral Calatrava",
    "sg:orig_category":"Supermercados Y Hipermercados",
    "sg:phone":"+34 926 34 95 11",
    "sg:postcode":"13350",
    "sg:province":"Ciudad Real",
    "wof:name":"Moralmarquet S.l.",
    "wof:placetype":"venue"
},
  "geometry": {"coordinates":[-3.5805859566,38.8294525146],"type":"Point"}
}