{
  "type": "Feature",
  "properties": {
    "iso:country":"ES",
    "sg:address":"Pase Salamanca De, 7",
    "sg:city":"Donostia-san Sebastian",
    "sg:orig_category":"M\u00c9dicos: Endocrinolog\u00cda Y Metabolismo",
    "sg:phone":"+34 943 42 04 78",
    "sg:postcode":"20003",
    "sg:province":"Guip\u00f9zcoa",
    "wof:name":"Blasco Olaechea Isabel",
    "wof:placetype":"venue"
},
  "geometry": {"coordinates":[-1.9818470478,43.3244171143],"type":"Point"}
}