{
  "type": "Feature",
  "properties": {
    "addr:full":"Carrer de Cant Dels Ocells, 12 Barri Maritim De Sant Salvador Tarragona 43880",
    "addr:housenumber":"12",
    "addr:postcode":"43880",
    "addr:street":"Carrer De Cant Dels Ocells",
    "iso:country":"ES",
    "sg:address":"Carrer de Cant Dels Ocells, 12",
    "sg:city":"Barri Maritim De Sant Salvador",
    "sg:orig_category":"Agencias Y Agentes Comerciales, Representantes",
    "sg:phone":"+34 977 68 43 75",
    "sg:postcode":"43880",
    "sg:province":"Tarragona",
    "wof:name":"Buil Seruendo Angel",
    "wof:placetype":"venue"
},
  "geometry": {"coordinates":[1.5370190144,41.1867027283],"type":"Point"}
}