{
  "type": "Feature",
  "properties": {
    "addr:full":"Avenida De Solvay, S/n Torrelavega Cantabria 39300",
    "addr:housenumber":"s / n",
    "addr:postcode":"39300",
    "addr:street":"Avenida De Solvay",
    "iso:country":"ES",
    "sg:address":"Avenida De Solvay, S/n",
    "sg:city":"Torrelavega",
    "sg:orig_category":"Ense\u00d1anza, Formaci\u00d3n Profesional: Aprendizaje",
    "sg:phone":"+34 942 83 51 49",
    "sg:postcode":"39300",
    "sg:province":"Cantabria",
    "wof:name":"Confederacion Hidrografica Del Norte",
    "wof:placetype":"venue"
},
  "geometry": {"coordinates":[-4.045156002,43.364692688],"type":"Point"}
}