{
  "type": "Feature",
  "properties": {
    "addr:full":"Calle de San Nicolas, 5 Santa Cruz De Tenerife Santa Cruz De Tenerife 38002",
    "addr:housenumber":"5",
    "addr:postcode":"38002",
    "addr:street":"Calle De San",
    "iso:country":"ES",
    "sg:address":"Calle de San Nicolas, 5",
    "sg:city":"Santa Cruz De Tenerife",
    "sg:orig_category":"Asilos De Ancianos. Centros Privados",
    "sg:phone":"+34 922 27 16 11",
    "sg:postcode":"38002",
    "sg:province":"Santa Cruz De Tenerife",
    "wof:name":"Asociacion Para El Ocio Y La Cultura De La Tercera Edad",
    "wof:placetype":"venue"
},
  "geometry": {"coordinates":[-16.2508010864,28.4715557098],"type":"Point"}
}