{
  "type": "Feature",
  "properties": {
    "addr:full":"C/ Lope De Vega, 55 Elche Alicante 03201",
    "addr:housenumber":"55",
    "addr:postcode":"03201",
    "addr:street":"C / Lope De Vega",
    "iso:country":"ES",
    "sg:address":"C/ Lope De Vega, 55",
    "sg:city":"Elche",
    "sg:orig_category":"Loter\u00cda Y T\u00d3mbola",
    "sg:phone":"+34 965 46 68 18",
    "sg:postcode":"03201",
    "sg:province":"Alicante",
    "wof:name":"Organizacion Impulsora De Discapacitados O.i.d.",
    "wof:placetype":"venue"
},
  "geometry": {"coordinates":[-0.7049739957,38.2678794861],"type":"Point"}
}