{
  "type": "Feature",
  "properties": {
    "addr:full":"Calle de Mayor, S/n Santervas De Campos Valladolid 47609",
    "addr:housenumber":"s",
    "addr:postcode":"47609",
    "addr:street":"Calle De Mayor;/ N",
    "iso:country":"ES",
    "sg:address":"Calle de Mayor, S/n",
    "sg:city":"Santervas De Campos",
    "sg:orig_category":"T\u00c9cnicos Veterinarios",
    "sg:phone":"+34 983 78 50 94",
    "sg:postcode":"47609",
    "sg:province":"Valladolid",
    "wof:name":"Benavides Flores Luis",
    "wof:placetype":"venue"
},
  "geometry": {"coordinates":[-5.0983338356,42.216796875],"type":"Point"}
}