{
  "type": "Feature",
  "properties": {
    "addr:full":"Calle de Poeta Mu\u00d1oz San Roman, S/n Camas Sevilla 41900",
    "addr:housenumber":"s / n",
    "addr:postcode":"41900",
    "addr:street":"Calle De Poeta Mun\u0303Oz San Roman",
    "iso:country":"ES",
    "sg:address":"Calle de Poeta Mu\u00d1oz San Roman, S/n",
    "sg:city":"Camas",
    "sg:orig_category":"Asociaciones Y Clubs Deportivos",
    "sg:phone":"+34 955 98 28 60",
    "sg:postcode":"41900",
    "sg:province":"Sevilla",
    "sg:website":"www.decathlon.es",
    "wof:name":"Decathlon Espa\u00d1a S.a.",
    "wof:placetype":"venue"
},
  "geometry": {"coordinates":[-6.0332450867,37.3931465149],"type":"Point"}
}