{
  "type": "Feature",
  "properties": {
    "iso:country":"ES",
    "sg:address":"Plaz Barcelona (de), 10",
    "sg:city":"Getafe",
    "sg:orig_category":"Energ\u00cda Solar Y Nuevas Energ\u00cdas (equipo, Estudios)",
    "sg:phone":"+34 916 81 51 35",
    "sg:postcode":"28903",
    "sg:province":"Madrid",
    "wof:name":"Instalaciones Solares Del Sur S.l.",
    "wof:placetype":"venue"
},
  "geometry": {"coordinates":[-3.7310590744,40.3048782349],"type":"Point"}
}