{
  "type": "Feature",
  "properties": {
    "addr:full":"Plaz Mayor, 10 Palencia Palencia 34001",
    "addr:housenumber":"10",
    "addr:postcode":"34001",
    "addr:street":"Plaz Mayor",
    "iso:country":"ES",
    "sg:address":"Plaz Mayor, 10",
    "sg:city":"Palencia",
    "sg:orig_category":"Fabricaci\u00d3n De Juguetes Autom\u00c1ticos",
    "sg:phone":"+34 979 75 09 78",
    "sg:postcode":"34001",
    "sg:province":"Palencia",
    "wof:name":"Inverexpan",
    "wof:placetype":"venue"
},
  "geometry": {"coordinates":[-4.5340671539,42.0126075745],"type":"Point"}
}