{
  "type": "Feature",
  "properties": {
    "addr:full":"Carrer de Paletes, S/n Vilanova Cami Barcelona 08788",
    "addr:housenumber":"s",
    "addr:postcode":"08788",
    "addr:street":"Carrer De Paletes;/ N;Cami Barcelona",
    "iso:country":"ES",
    "sg:address":"Carrer de Paletes, S/n",
    "sg:city":"Vilanova Cami",
    "sg:orig_category":"Bebidas",
    "sg:phone":"+34 938 06 31 00",
    "sg:postcode":"08788",
    "sg:province":"Barcelona",
    "sg:website":"www.bgrup.es",
    "wof:name":"Begudes Igualada S.a.",
    "wof:placetype":"venue"
},
  "geometry": {"coordinates":[1.6604750156,41.5647850037],"type":"Point"}
}