{
  "type": "Feature",
  "properties": {
    "iso:country":"ES",
    "sg:address":"Diseminados, S/n",
    "sg:city":"Fayon",
    "sg:orig_category":"Poller\u00cda Y Caza (al Por Menor)",
    "sg:phone":"+34 976 63 41 04",
    "sg:postcode":"50795",
    "sg:province":"Zaragoza",
    "wof:name":"Urbon Agropecuaria S.c.",
    "wof:placetype":"venue"
},
  "geometry": {"coordinates":[0.3319050074,41.2410240173],"type":"Point"}
}