{
  "type": "Feature",
  "properties": {
    "iso:country":"ES",
    "sg:address":"Av Salvador Allende, 39",
    "sg:city":"Cornella Llobregat",
    "sg:orig_category":"Persianas Interiores, Exteriores",
    "sg:phone":"+34 933 75 23 52",
    "sg:postcode":"08940",
    "sg:province":"Barcelona",
    "wof:name":"Doblas Granados Maria Jose",
    "wof:placetype":"venue"
},
  "geometry": {"coordinates":[2.0791759491,41.3580970764],"type":"Point"}
}