{
  "type": "Feature",
  "properties": {
    "iso:country":"ES",
    "sg:address":"Calle de San Ramon, 22",
    "sg:city":"Paiporta",
    "sg:orig_category":"Droguer\u00cdas (al Por Menor)",
    "sg:phone":"+34 963 97 46 52",
    "sg:postcode":"46200",
    "sg:province":"Valencia",
    "wof:name":"Catala Benavent Maria Encarnacion",
    "wof:placetype":"venue"
},
  "geometry": {"coordinates":[-0.4216170013,39.4261894226],"type":"Point"}
}