{
  "type": "Feature",
  "properties": {
    "addr:full":"Pamplona, S/n Imarcoain Navarra 31119",
    "addr:housenumber":"s / n",
    "addr:postcode":"31119",
    "addr:street":"Pamplona",
    "iso:country":"ES",
    "sg:address":"Pamplona, S/n",
    "sg:city":"Imarcoain",
    "sg:orig_category":"Contenedores (mercanc\u00cdas)",
    "sg:phone":"+34 948 31 43 00",
    "sg:postcode":"31119",
    "sg:province":"Navarra",
    "wof:name":"Disayt S.l.",
    "wof:placetype":"venue"
},
  "geometry": {"coordinates":[-1.5951639414,42.7345542908],"type":"Point"}
}