{
  "type": "Feature",
  "properties": {
    "iso:country":"ES",
    "sg:address":"Ctra Ossa De Montiel, 23",
    "sg:city":"Villarrobledo",
    "sg:orig_category":"Producci\u00d3n De Abonos Y De Fertilizantes",
    "sg:phone":"+34 967 14 72 64",
    "sg:postcode":"02600",
    "sg:province":"Albacete",
    "wof:name":"Abonos Y Derivados Los Poceros S.l.",
    "wof:placetype":"venue"
},
  "geometry": {"coordinates":[-2.613103,39.258278],"type":"Point"}
}