{
  "type": "Feature",
  "properties": {
    "iso:country":"ES",
    "sg:address":"Calle de Pacita Vigil La Guaxa, 5",
    "sg:city":"Pola De Siero",
    "sg:orig_category":"Abogados",
    "sg:phone":"+34 985 72 57 65",
    "sg:postcode":"33510",
    "sg:province":"Asturias",
    "wof:name":"Garcia Llano Guiomar",
    "wof:placetype":"venue"
},
  "geometry": {"coordinates":[-5.6608700752,43.3908615112],"type":"Point"}
}