{
  "type": "Feature",
  "properties": {
    "addr:full":"Ospela, 32 Berrobi Guip\u00f9zcoa 20493",
    "addr:housenumber":"32",
    "addr:postcode":"20493",
    "addr:street":"Ospela;Guipu\u0300Zcoa",
    "iso:country":"ES",
    "sg:address":"Ospela, 32",
    "sg:city":"Berrobi",
    "sg:orig_category":"Fabricaci\u00d3n De Cajas De Cart\u00d3n",
    "sg:phone":"+34 943 68 30 51",
    "sg:postcode":"20493",
    "sg:province":"Guip\u00f9zcoa",
    "wof:name":"Mayensa S.a.",
    "wof:placetype":"venue"
},
  "geometry": {"coordinates":[-2.023870945,43.1406402588],"type":"Point"}
}