{
  "type": "Feature",
  "properties": {
    "addr:full":"Avda Moya (de), 6 San Fernando Las Palmas 35100",
    "addr:postcode":"35100",
    "addr:street":"Avda Moya De 6",
    "iso:country":"ES",
    "sg:address":"Avda Moya (de), 6",
    "sg:city":"San Fernando",
    "sg:orig_category":"Abogados",
    "sg:phone":"+34 928 77 70 71",
    "sg:postcode":"35100",
    "sg:province":"Las Palmas",
    "wof:name":"Diaz Santana Fernando",
    "wof:placetype":"venue"
},
  "geometry": {"coordinates":[-15.5842504501,28.0904903412],"type":"Point"}
}