{
  "type": "Feature",
  "properties": {
    "addr:full":"Calle de Ametzaga\u00d1a, 14 Donostia-san Sebastian Guip\u00f9zcoa 20012",
    "addr:housenumber":"14",
    "addr:postcode":"20012",
    "addr:street":"Calle De Ametzagan\u0303A",
    "iso:country":"ES",
    "sg:address":"Calle de Ametzaga\u00d1a, 14",
    "sg:city":"Donostia-san Sebastian",
    "sg:orig_category":"Molduras, Junquillos, Listones Y Molduras Perforadas",
    "sg:phone":"+34 943 29 06 12",
    "sg:postcode":"20012",
    "sg:province":"Guip\u00f9zcoa",
    "wof:name":"Beti Boga S.l",
    "wof:placetype":"venue"
},
  "geometry": {"coordinates":[-1.9708939791,43.3161087036],"type":"Point"}
}