{
  "type": "Feature",
  "properties": {
    "iso:country":"ES",
    "sg:address":"Carr Valencia, 7",
    "sg:city":"Blanes",
    "sg:orig_category":"Venta, Montaje De Neum\u00c1ticos",
    "sg:phone":"+34 972 33 45 84",
    "sg:postcode":"17300",
    "sg:province":"Girona",
    "wof:name":"Mora Ramirez Rafael",
    "wof:placetype":"venue"
},
  "geometry": {"coordinates":[2.7869250774,41.6782455444],"type":"Point"}
}