{
  "type": "Feature",
  "properties": {
    "iso:country":"ES",
    "sg:address":"Calle de Cava, 3",
    "sg:city":"Priego Cordoba",
    "sg:classifiers":[
        {
            "category":"Autos & Motor Vehicles",
            "subcategory":"Automobile Sales",
            "type":"Retail Goods"
        }
    ],
    "sg:phone":"+34 957 54 17 78",
    "sg:postcode":"14800",
    "sg:province":"C\u00f3rdoba",
    "wof:name":"Autoescuela Adarve S.l.",
    "wof:placetype":"venue"
},
  "geometry": {"coordinates":[-4.1949486732,37.4393501282],"type":"Point"}
}