{
  "type": "Feature",
  "properties": {
    "iso:country":"ES",
    "sg:address":"Calle de Gonzalez Del Villar, 12",
    "sg:city":"Coru\u00d1a",
    "sg:orig_category":"Promotores Constructores",
    "sg:phone":"+34 981 15 38 97",
    "sg:postcode":"15005",
    "sg:province":"A Coru\u00f1a",
    "wof:name":"Soacsa Coru\u00f1a S.a.",
    "wof:placetype":"venue"
},
  "geometry": {"coordinates":[-8.4173345566,43.3596382141],"type":"Point"}
}