{
  "type": "Feature",
  "properties": {
    "iso:country":"ES",
    "sg:address":"San Lazaro, S/n",
    "sg:city":"Calahorra",
    "sg:orig_category":"Venta, Instalaci\u00d3n De Calefacci\u00d3n",
    "sg:phone":"+34 941 13 21 64",
    "sg:postcode":"26500",
    "sg:province":"La Rioja",
    "wof:name":"Instalaciones Martinez Soldevilla S.l.",
    "wof:placetype":"venue"
},
  "geometry": {"coordinates":[-1.942860961,42.2907104492],"type":"Point"}
}