{
  "type": "Feature",
  "properties": {
    "addr:full":"Calle de Libertad, 22 Bejar Salamanca 37700",
    "addr:housenumber":"22",
    "addr:postcode":"37700",
    "addr:street":"Calle De Libertad",
    "iso:country":"ES",
    "sg:address":"Calle de Libertad, 22",
    "sg:city":"Bejar",
    "sg:orig_category":"Venta, Instalaci\u00d3n De Cocinas",
    "sg:phone":"+34 923 41 03 83",
    "sg:postcode":"37700",
    "sg:province":"Salamanca",
    "wof:name":"Medina Mu\u00f1oz Jose",
    "wof:placetype":"venue"
},
  "geometry": {"coordinates":[-5.7637329102,40.3860397339],"type":"Point"}
}