{
  "type": "Feature",
  "properties": {
    "addr:full":"Plaz Inmaculada, S/n Zaragoza Zaragoza 50012",
    "addr:housenumber":"s / n",
    "addr:postcode":"50012",
    "iso:country":"ES",
    "sg:address":"Plaz Inmaculada, S/n",
    "sg:city":"Zaragoza",
    "sg:orig_category":"Asociaciones, Organismos Culturales Y Socioeducativos",
    "sg:phone":"+34 976 75 38 08",
    "sg:postcode":"50012",
    "sg:province":"Zaragoza",
    "wof:name":"Ayuntamiento De Zaragoza",
    "wof:placetype":"venue"
},
  "geometry": {"coordinates":[-0.9305490255,41.639755249],"type":"Point"}
}