{
  "type": "Feature",
  "properties": {
    "addr:full":"Calle de Amalloa, 4 Getxo Vizcaya 48930",
    "addr:housenumber":"4",
    "addr:postcode":"48930",
    "addr:street":"Calle De Amalloa",
    "iso:country":"ES",
    "sg:address":"Calle de Amalloa, 4",
    "sg:city":"Getxo",
    "sg:orig_category":"Empresas De Carpinter\u00cda De Madera",
    "sg:phone":"+34 944 63 85 03",
    "sg:postcode":"48930",
    "sg:province":"Vizcaya",
    "wof:name":"Jose Maria E I\u00f1igo Landaluze, C.b.",
    "wof:placetype":"venue"
},
  "geometry": {"coordinates":[-3.0090036392,43.3266525269],"type":"Point"}
}