{
  "type": "Feature",
  "properties": {
    "iso:country":"ES",
    "sg:address":"Calle de Ventura Rodriguez, 9",
    "sg:city":"Madrid",
    "sg:orig_category":"Panader\u00cdas, Panader\u00cdas",
    "sg:phone":"+34 915 47 69 48",
    "sg:postcode":"28008",
    "sg:province":"Madrid",
    "wof:name":"Garzon Garcia Isidra",
    "wof:placetype":"venue"
},
  "geometry": {"coordinates":[-3.713960886,40.4247970581],"type":"Point"}
}