{
  "type": "Feature",
  "properties": {
    "addr:full":"Calle de Faustekalea, 23 Durango Vizcaya 48200",
    "addr:housenumber":"23",
    "addr:postcode":"48200",
    "addr:street":"Calle De Faustekalea",
    "iso:country":"ES",
    "sg:address":"Calle de Faustekalea, 23",
    "sg:city":"Durango",
    "sg:orig_category":"Iglesia Cat\u00d3lica",
    "sg:phone":"+34 946 81 70 80",
    "sg:postcode":"48200",
    "sg:province":"Vizcaya",
    "wof:name":"Obispado De Bilbao",
    "wof:placetype":"venue"
},
  "geometry": {"coordinates":[-2.6223833561,43.1687011719],"type":"Point"}
}