{
  "type": "Feature",
  "properties": {
    "addr:full":"Calle de Quart, 74 Valencia Valencia 46008",
    "addr:housenumber":"74",
    "addr:postcode":"46008",
    "addr:street":"Calle De Quart",
    "iso:country":"ES",
    "sg:address":"Calle de Quart, 74",
    "sg:city":"Valencia",
    "sg:orig_category":"Florister\u00cdas",
    "sg:phone":"+34 963 91 19 83",
    "sg:postcode":"46008",
    "sg:province":"Valencia",
    "sg:website":"www.floresfelalliso.com",
    "wof:name":"Lliso Martin Gabriel",
    "wof:placetype":"venue"
},
  "geometry": {"coordinates":[-0.38557899,39.4756469727],"type":"Point"}
}