{
  "type": "Feature",
  "properties": {
    "iso:country":"ES",
    "sg:address":"Carr Pau Claris, 5",
    "sg:city":"Badalona",
    "sg:orig_category":"Fabricaci\u00d3n, Instalaci\u00d3n De Armarios",
    "sg:phone":"+34 933 83 09 06",
    "sg:postcode":"08914",
    "sg:province":"Barcelona",
    "wof:name":"Mora Lopez Ladislao",
    "wof:placetype":"venue"
},
  "geometry": {"coordinates":[2.231388092,41.4416503906],"type":"Point"}
}