{
  "type": "Feature",
  "properties": {
    "addr:full":"Calle de Molino, S/n Almendricos Murcia 30893",
    "addr:housenumber":"s",
    "addr:postcode":"30893",
    "addr:street":"Calle De Molino;/ N",
    "iso:country":"ES",
    "sg:address":"Calle de Molino, S/n",
    "sg:city":"Almendricos",
    "sg:orig_category":"Explotaci\u00d3n De Minas",
    "sg:phone":"+34 968 44 01 51",
    "sg:postcode":"30893",
    "sg:province":"Murcia",
    "wof:name":"Sonvoles S.l.",
    "wof:placetype":"venue"
},
  "geometry": {"coordinates":[-1.7780665159,37.4745407104],"type":"Point"}
}