{
  "type": "Feature",
  "properties": {
    "iso:country":"ES",
    "sg:address":"C/ Pedraforca, 7",
    "sg:city":"Ripollet",
    "sg:orig_category":"Alquiler De V\u00cddeo",
    "sg:phone":"+34 936 92 53 41",
    "sg:postcode":"08291",
    "sg:province":"Barcelona",
    "wof:name":"Nasolbert S.l.",
    "wof:placetype":"venue"
},
  "geometry": {"coordinates":[2.1526060104,41.5021858215],"type":"Point"}
}