{
  "type": "Feature",
  "properties": {
    "addr:full":"Calle de Periodista Francisco Guerrero Vilchez, 9 Granada Granada 18015",
    "addr:housenumber":"9",
    "addr:postcode":"18015",
    "addr:street":"Calle De Periodista Francisco Guerrero Vilchez",
    "iso:country":"ES",
    "sg:address":"Calle de Periodista Francisco Guerrero Vilchez, 9",
    "sg:city":"Granada",
    "sg:orig_category":"Empresarios",
    "sg:phone":"+34 958 17 19 97",
    "sg:postcode":"18015",
    "sg:province":"Granada",
    "wof:name":"Perez Molina Pedro",
    "wof:placetype":"venue"
},
  "geometry": {"coordinates":[-3.6283619404,37.1982498169],"type":"Point"}
}