{
  "type": "Feature",
  "properties": {
    "iso:country":"ES",
    "sg:address":"Urbanizacion Serramar, 4",
    "sg:city":"Cala Moral",
    "sg:orig_category":"Cr\u00cda De Animales",
    "sg:phone":"+34 952 40 43 64",
    "sg:postcode":"29720",
    "sg:province":"M\u00e1laga",
    "wof:name":"Garcia Del Rosal Inmaculada",
    "wof:placetype":"venue"
},
  "geometry": {"coordinates":[-4.325949192,36.7128982544],"type":"Point"}
}