{
  "type": "Feature",
  "properties": {
    "addr:full":"Calle de Avda. Diputacion, S/n Ribaforada Navarra 31550",
    "addr:housenumber":"s",
    "addr:postcode":"31550",
    "addr:street":"Calle De Avda. Diputacion;/ N",
    "iso:country":"ES",
    "sg:address":"Calle de Avda. Diputacion, S/n",
    "sg:city":"Ribaforada",
    "sg:orig_category":"Asociaciones Ecologistas",
    "sg:phone":"+34 948 86 41 34",
    "sg:postcode":"31550",
    "sg:province":"Navarra",
    "wof:name":"Comunidad De Regantes De La Dehesa",
    "wof:placetype":"venue"
},
  "geometry": {"coordinates":[-1.5155930519,41.9996643066],"type":"Point"}
}