{
  "type": "Feature",
  "properties": {
    "iso:country":"ES",
    "sg:address":"Vigovidin-almeiras, S/n",
    "sg:city":"Culleredo",
    "sg:orig_category":"Promotores Constructores",
    "sg:phone":"+34 981 66 67 45",
    "sg:postcode":"15174",
    "sg:province":"A Coru\u00f1a",
    "wof:name":"Seoana Varela Lucia Belen",
    "wof:placetype":"venue"
},
  "geometry": {"coordinates":[-8.3826389313,43.3110656738],"type":"Point"}
}