{
  "type": "Feature",
  "properties": {
    "addr:full":"Calle de Antonio Sanfiz, 12 Madrid Madrid 28023",
    "addr:housenumber":"12",
    "addr:postcode":"madrid;28023",
    "addr:street":"Calle De Antonio Sanfiz",
    "iso:country":"ES",
    "sg:address":"Calle de Antonio Sanfiz, 12",
    "sg:city":"Madrid",
    "sg:orig_category":"Arquitectos",
    "sg:phone":"+34 913 07 09 80",
    "sg:postcode":"28023",
    "sg:province":"Madrid",
    "wof:name":"Anduiza Arriola Rafael",
    "wof:placetype":"venue"
},
  "geometry": {"coordinates":[-3.7874705791,40.4604263306],"type":"Point"}
}