{
  "type": "Feature",
  "properties": {
    "addr:full":"Pg Gran Passeig Ronda, 139 Lleida Lleida 25008",
    "addr:housenumber":"139",
    "addr:postcode":"25008",
    "addr:street":"Pg Gran Passeig Ronda",
    "iso:country":"ES",
    "sg:address":"Pg Gran Passeig Ronda, 139",
    "sg:city":"Lleida",
    "sg:orig_category":"Farmacias",
    "sg:phone":"+34 973 23 35 79",
    "sg:postcode":"25008",
    "sg:province":"Lleida",
    "wof:name":"Farmacia Bendicho-isanta S.c.p.",
    "wof:placetype":"venue"
},
  "geometry": {"coordinates":[0.6198359728,41.622882843],"type":"Point"}
}