{
  "type": "Feature",
  "properties": {
    "addr:full":"Pl Alcalde Xifre, 14 Badalona Barcelona 08912",
    "addr:housenumber":"14",
    "addr:postcode":"08912",
    "addr:street":"Pl Alcalde Xifre",
    "iso:country":"ES",
    "sg:address":"Pl Alcalde Xifre, 14",
    "sg:city":"Badalona",
    "sg:orig_category":"M\u00c9dicos: Estomatolog\u00cda",
    "sg:phone":"+34 934 60 72 15",
    "sg:postcode":"08912",
    "sg:province":"Barcelona",
    "wof:name":"Steiger Gresely Griselda",
    "wof:placetype":"venue"
},
  "geometry": {"coordinates":[2.2411410809,41.4481163025],"type":"Point"}
}