{
  "type": "Feature",
  "properties": {
    "iso:country":"ES",
    "sg:address":"Sauquer, 2",
    "sg:city":"Casau",
    "sg:classifiers":[
        {
            "category":"Taxi",
            "type":"Transportation"
        }
    ],
    "sg:phone":"+34 973 64 21 43",
    "sg:postcode":"25538",
    "sg:province":"Lleida",
    "wof:name":"Ramos Ates Jorge",
    "wof:placetype":"venue"
},
  "geometry": {"coordinates":[0.7848029733,42.7056388855],"type":"Point"}
}