{
  "type": "Feature",
  "properties": {
    "iso:country":"ES",
    "sg:address":"Calle de Elda, 44",
    "sg:city":"Alacant",
    "sg:orig_category":"Delegados, Agentes De Tr\u00c1nsito, Auxiliares De Transporte Internacional",
    "sg:phone":"+34 965 20 30 73",
    "sg:postcode":"03013",
    "sg:province":"Alicante",
    "wof:name":"Rosendo & Ramon Garcia S.l.",
    "wof:placetype":"venue"
},
  "geometry": {"coordinates":[-0.4799819887,38.3548469543],"type":"Point"}
}