{
  "type": "Feature",
  "properties": {
    "addr:full":"Calle de Pobla De Farnals, 48 Valencia Valencia 46022",
    "addr:housenumber":"48",
    "addr:postcode":"46022",
    "addr:street":"Calle De Pobla;Farnals",
    "iso:country":"ES",
    "sg:address":"Calle de Pobla De Farnals, 48",
    "sg:city":"Valencia",
    "sg:orig_category":"Asociaciones, Organismos Culturales Y Socioeducativos",
    "sg:phone":"+34 963 31 26 29",
    "sg:postcode":"46022",
    "sg:province":"Valencia",
    "wof:name":"Falla Duque De Gaeta-puebla De Farnals",
    "wof:placetype":"venue"
},
  "geometry": {"coordinates":[-0.3492279947,39.4687271118],"type":"Point"}
}