{
  "type": "Feature",
  "properties": {
    "iso:country":"ES",
    "sg:address":"Calle de Bergantin, 5",
    "sg:city":"Madrid",
    "sg:orig_category":"Asesor\u00cda Fiscal Y Jur\u00cddica",
    "sg:phone":"+34 913 29 65 14",
    "sg:postcode":"28042",
    "sg:province":"Madrid",
    "wof:name":"Laboral Lawsuit S.l.",
    "wof:placetype":"venue"
},
  "geometry": {"coordinates":[-3.5861651897,40.4579544067],"type":"Point"}
}