{
  "type": "Feature",
  "properties": {
    "addr:full":"Poligono Industrial Congost, Km. 0591,0 Martorell Barcelona 08760",
    "addr:postcode":"08760",
    "addr:street":"Km. 0591,0",
    "iso:country":"ES",
    "sg:address":"Poligono Industrial Congost, Km. 0591,0",
    "sg:city":"Martorell",
    "sg:orig_category":"Electricidad, Electr\u00d3nica: Material Y Suministros (al Por Mayor)",
    "sg:phone":"+34 937 74 52 30",
    "sg:postcode":"08760",
    "sg:province":"Barcelona",
    "wof:name":"Mantgroup S. C. C. L.",
    "wof:placetype":"venue"
},
  "geometry": {"coordinates":[1.9265979528,41.474105835],"type":"Point"}
}