{
  "type": "Feature",
  "properties": {
    "iso:country":"ES",
    "sg:address":"Calle de San Agustin, 92",
    "sg:city":"Icod De Los Vinos",
    "sg:orig_category":"Farmacias",
    "sg:phone":"+34 922 12 13 64",
    "sg:postcode":"38430",
    "sg:province":"Santa Cruz De Tenerife",
    "wof:name":"Acosta Acevedo Maria Del Carmen",
    "wof:placetype":"venue"
},
  "geometry": {"coordinates":[-16.7148895264,28.3692512512],"type":"Point"}
}