{
  "type": "Feature",
  "properties": {
    "iso:country":"ES",
    "sg:address":"Calle de Hilario Agapito, 6",
    "sg:city":"Barakaldo",
    "sg:orig_category":"Caf\u00c9s, Bares, Cervecer\u00cdas",
    "sg:phone":"+34 944 99 86 41",
    "sg:postcode":"48903",
    "sg:province":"Vizcaya",
    "wof:name":"Ana Barroso ( Bar Itxaro)",
    "wof:placetype":"venue"
},
  "geometry": {"coordinates":[-2.9966332912,43.2841339111],"type":"Point"}
}