{
  "type": "Feature",
  "properties": {
    "addr:full":"Cmno San Roman, Km. 0002,0 Palencia Palencia 34006",
    "addr:postcode":"34006",
    "addr:street":"Cmno San Roman Km. 0002,0",
    "iso:country":"ES",
    "sg:address":"Cmno San Roman, Km. 0002,0",
    "sg:city":"Palencia",
    "sg:orig_category":"Frutas Y Legumbres Frescas (al Por Mayor)",
    "sg:phone":"+34 979 75 12 72",
    "sg:postcode":"34006",
    "sg:province":"Palencia",
    "wof:name":"Martin Martin Jose",
    "wof:placetype":"venue"
},
  "geometry": {"coordinates":[-4.5392618179,42.010433197],"type":"Point"}
}