{
  "type": "Feature",
  "properties": {
    "addr:full":"Avda Dionisio Cifuentes De, 102 Gijon Asturias 33203",
    "addr:housenumber":"102",
    "addr:postcode":"33203",
    "addr:street":"Avda Dionisio Cifuentes De",
    "iso:country":"ES",
    "sg:address":"Avda Dionisio Cifuentes De, 102",
    "sg:city":"Gijon",
    "sg:orig_category":"Reposter\u00cdas",
    "sg:phone":"+34 985 37 28 29",
    "sg:postcode":"33203",
    "sg:province":"Asturias",
    "wof:name":"Garcia Valdes Luis Manuel",
    "wof:placetype":"venue"
},
  "geometry": {"coordinates":[-5.6231455803,43.5355491638],"type":"Point"}
}