{
  "type": "Feature",
  "properties": {
    "iso:country":"ES",
    "sg:address":"Av Lluis Companys, 38",
    "sg:city":"Torroella Montgri",
    "sg:orig_category":"Fotocopias, Reprograf\u00cda",
    "sg:phone":"+34 972 76 15 15",
    "sg:postcode":"17257",
    "sg:province":"Girona",
    "wof:name":"Coll Colomer Susana",
    "wof:placetype":"venue"
},
  "geometry": {"coordinates":[3.1034500599,42.0303268433],"type":"Point"}
}