{
  "type": "Feature",
  "properties": {
    "addr:full":"Cmno Pajares Y Del Porcal (de), S/n Arganda Madrid 28500",
    "addr:postcode":"28500",
    "addr:street":"Cmno Pajares Y Del Porcal De S / N",
    "iso:country":"ES",
    "sg:address":"Cmno Pajares Y Del Porcal (de), S/n",
    "sg:city":"Arganda",
    "sg:orig_category":"Muebles Y Accesorios Para Cocinas Y Cuartos De Ba\u00d1o (al Por Menor)",
    "sg:phone":"+34 918 71 96 47",
    "sg:postcode":"28500",
    "sg:province":"Madrid",
    "wof:name":"Maderas Argan S.l.",
    "wof:placetype":"venue"
},
  "geometry": {"coordinates":[-3.4801940918,40.3003234863],"type":"Point"}
}