{
  "type": "Feature",
  "properties": {
    "iso:country":"ES",
    "sg:address":"Carrer de Turo De La Penya, S/n",
    "sg:city":"Cardedeu",
    "sg:orig_category":"Electricidad: Instaladores",
    "sg:phone":"+34 938 46 17 40",
    "sg:postcode":"08440",
    "sg:province":"Barcelona",
    "wof:name":"Trielectric S.c.c.l.",
    "wof:placetype":"venue"
},
  "geometry": {"coordinates":[2.3589351177,41.6370544434],"type":"Point"}
}