{
  "type": "Feature",
  "properties": {
    "iso:country":"ES",
    "sg:address":"Ctra Torrecardenas, 54",
    "sg:city":"Fuensanta -villa Ines",
    "sg:orig_category":"Caf\u00c9s, Bares, Cervecer\u00cdas",
    "sg:phone":"+34 950 14 20 91",
    "sg:postcode":"04230",
    "sg:province":"Almer\u00eda",
    "wof:name":"Martinez Martinez Juan",
    "wof:placetype":"venue"
},
  "geometry": {"coordinates":[-2.4411959648,36.8665809631],"type":"Point"}
}