{
  "type": "Feature",
  "properties": {
    "addr:full":"Plaz San Francisco, 1 Villanueva Jara Cuenca 16230",
    "addr:housenumber":"1",
    "addr:postcode":"16230",
    "addr:street":"Plaz San Francisco;Jara",
    "iso:country":"ES",
    "sg:address":"Plaz San Francisco, 1",
    "sg:city":"Villanueva Jara",
    "sg:orig_category":"Ense\u00d1anza, Formaci\u00d3n Profesional: Aprendizaje",
    "sg:phone":"+34 967 49 80 02",
    "sg:postcode":"16230",
    "sg:province":"Cuenca",
    "wof:name":"Ayuntamiento De Villanueva De La Jara",
    "wof:placetype":"venue"
},
  "geometry": {"coordinates":[-1.9547703266,39.4403953552],"type":"Point"}
}