{
  "type": "Feature",
  "properties": {
    "addr:full":"Calle de Milicias Nacionales, 5 Oviedo Asturias 33003",
    "addr:housenumber":"5",
    "addr:postcode":"33003",
    "addr:street":"Calle De Milicias Nacionales",
    "iso:country":"ES",
    "sg:address":"Calle de Milicias Nacionales, 5",
    "sg:city":"Oviedo",
    "sg:orig_category":"Agencias De Prensa E Informaci\u00d3n",
    "sg:phone":"+34 985 21 96 14",
    "sg:postcode":"33003",
    "sg:province":"Asturias",
    "wof:name":"Agencia Efe S. A.",
    "wof:placetype":"venue"
},
  "geometry": {"coordinates":[-5.8492369652,43.363319397],"type":"Point"}
}