{
  "type": "Feature",
  "properties": {
    "iso:country":"ES",
    "sg:address":"Rua Progreso, 75",
    "sg:city":"Ca\u00f1iza",
    "sg:orig_category":"Electricidad: Instaladores",
    "sg:phone":"+34 986 65 22 67",
    "sg:postcode":"36880",
    "sg:province":"Pontevedra",
    "wof:name":"Alvarez Carpintero Oscar",
    "wof:placetype":"venue"
},
  "geometry": {"coordinates":[-8.2744197845,42.2132072449],"type":"Point"}
}