{
  "type": "Feature",
  "properties": {
    "iso:country":"ES",
    "sg:address":"Avda Constitucion (de La), 48",
    "sg:city":"Iniesta",
    "sg:orig_category":"Artes Gr\u00c1ficas, Artes Pl\u00c1sticas (curso)",
    "sg:phone":"+34 967 49 09 05",
    "sg:postcode":"16235",
    "sg:province":"Cuenca",
    "sg:website":"www.graficasiniesta.com",
    "wof:name":"Graficas Iniesta S.l.",
    "wof:placetype":"venue"
},
  "geometry": {"coordinates":[-1.7394750118,39.4404182434],"type":"Point"}
}