{
  "type": "Feature",
  "properties": {
    "iso:country":"ES",
    "sg:address":"Carrer de Cementiri Nou, 13",
    "sg:city":"Sentmenat",
    "sg:orig_category":"Materias Pl\u00c1sticas: Art\u00cdculos Para La Industria",
    "sg:phone":"+34 937 15 32 32",
    "sg:postcode":"08181",
    "sg:province":"Barcelona",
    "wof:name":"Extrusion Y Manipulado S.l.",
    "wof:placetype":"venue"
},
  "geometry": {"coordinates":[2.1432650089,41.6143264771],"type":"Point"}
}