{
  "type": "Feature",
  "properties": {
    "addr:full":"Camino Tohuero, 76 Marchuquera Valencia 46728",
    "addr:housenumber":"76",
    "addr:postcode":"46728",
    "addr:street":"Camino Tohuero",
    "iso:country":"ES",
    "sg:address":"Camino Tohuero, 76",
    "sg:city":"Marchuquera",
    "sg:orig_category":"Agencias Y Agentes Comerciales, Representantes",
    "sg:phone":"+34 962 86 07 95",
    "sg:postcode":"46728",
    "sg:province":"Valencia",
    "wof:name":"Perez Belda Emilio",
    "wof:placetype":"venue"
},
  "geometry": {"coordinates":[-0.2635430098,38.9826202393],"type":"Point"}
}