{
  "type": "Feature",
  "properties": {
    "iso:country":"ES",
    "sg:address":"Calle de Luis Dorado, 18",
    "sg:city":"Puertollano",
    "sg:orig_category":"Transportes Por Carretera: Lotes Completos, Mercanc\u00cdas Diversas",
    "sg:phone":"+34 926 43 20 91",
    "sg:postcode":"13500",
    "sg:province":"Ciudad Real",
    "wof:name":"Romero Abenojar Pablo",
    "wof:placetype":"venue"
},
  "geometry": {"coordinates":[-4.0966858864,38.6840553284],"type":"Point"}
}