{
  "type": "Feature",
  "properties": {
    "addr:full":"Calle de San Basilio, 26 Madrid Madrid 28026",
    "addr:housenumber":"26",
    "addr:postcode":"madrid;28026",
    "addr:street":"Calle De San",
    "iso:country":"ES",
    "sg:address":"Calle de San Basilio, 26",
    "sg:city":"Madrid",
    "sg:orig_category":"Escayola Y Productos De Escayola (fabricaci\u00d3n, Al Por Mayor)",
    "sg:phone":"+34 914 75 55 27",
    "sg:postcode":"28026",
    "sg:province":"Madrid",
    "wof:name":"Escayolas Palacios Lafuente S.l.",
    "wof:placetype":"venue"
},
  "geometry": {"coordinates":[-3.7082529068,40.3798942566],"type":"Point"}
}