{
  "type": "Feature",
  "properties": {
    "addr:full":"Avda Bierzo (el), Km. 0006,0 Villalibre De La Jurisdiccion Le\u00f3n 24447",
    "addr:postcode":"24447",
    "addr:street":"Avda Bierzo El Km. 0006,0 Villalibre De La Jurisdiccion Leo\u0301N",
    "iso:country":"ES",
    "sg:address":"Avda Bierzo (el), Km. 0006,0",
    "sg:city":"Villalibre De La Jurisdiccion",
    "sg:orig_category":"Fabrica De Cer\u00c1micas",
    "sg:phone":"+34 987 41 44 44",
    "sg:postcode":"24447",
    "sg:province":"Le\u00f3n",
    "wof:name":"Canteras Industriales Del Bierzo S.a.",
    "wof:placetype":"venue"
},
  "geometry": {"coordinates":[-6.6582489014,42.5190086365],"type":"Point"}
}