{
  "type": "Feature",
  "properties": {
    "addr:full":"Avda Habana, 10 Motril Granada 18600",
    "addr:housenumber":"10",
    "addr:postcode":"18600",
    "addr:street":"Avda Habana",
    "iso:country":"ES",
    "sg:address":"Avda Habana, 10",
    "sg:city":"Motril",
    "sg:orig_category":"Agentes Generales De Seguros",
    "sg:phone":"+34 958 60 62 74",
    "sg:postcode":"18600",
    "sg:province":"Granada",
    "wof:name":"Vizcaino Y Megias C.b",
    "wof:placetype":"venue"
},
  "geometry": {"coordinates":[-3.5200564861,36.7426147461],"type":"Point"}
}