{
  "type": "Feature",
  "properties": {
    "iso:country":"ES",
    "sg:address":"Calle de Castilla, 25",
    "sg:city":"Madrid",
    "sg:orig_category":"Producci\u00d3n, Distribuci\u00d3n De Electricidad",
    "sg:phone":"+34 914 50 64 38",
    "sg:postcode":"28039",
    "sg:province":"Madrid",
    "wof:name":"Mu\u00f1iz Fernandez Jose",
    "wof:placetype":"venue"
},
  "geometry": {"coordinates":[-3.7061285973,40.4531173706],"type":"Point"}
}