{
  "type": "Feature",
  "properties": {
    "addr:full":"Arquimedes, S/n Gijon Asturias 33211",
    "addr:postcode":"33211",
    "addr:street":"Arquimedes S / N",
    "iso:country":"ES",
    "sg:address":"Arquimedes, S/n",
    "sg:city":"Gijon",
    "sg:orig_category":"Agencias Y Agentes Comerciales, Representantes",
    "sg:phone":"+34 985 16 73 36",
    "sg:postcode":"33211",
    "sg:province":"Asturias",
    "sg:website":"www.menciasl.com",
    "wof:name":"Representaciones Mencia S.l.",
    "wof:placetype":"venue"
},
  "geometry": {"coordinates":[-5.6916589737,43.505695343],"type":"Point"}
}