{
  "type": "Feature",
  "properties": {
    "addr:full":"Avda Jesus Santos Rein, 11 Fuengirola M\u00e1laga 29640",
    "addr:housenumber":"11",
    "addr:postcode":"29640",
    "addr:street":"Avda Jesus Santos Rein;Ma\u0301Laga",
    "iso:country":"ES",
    "sg:address":"Avda Jesus Santos Rein, 11",
    "sg:city":"Fuengirola",
    "sg:orig_category":"Ropa Para Se\u00d1oras (al Por Menor)",
    "sg:phone":"+34 952 46 78 80",
    "sg:postcode":"29640",
    "sg:province":"M\u00e1laga",
    "wof:name":"Wissenberg  Benedicte Elisabeth",
    "wof:placetype":"venue"
},
  "geometry": {"coordinates":[-4.6227278709,36.5435180664],"type":"Point"}
}