{
  "type": "Feature",
  "properties": {
    "addr:full":"Calle de Bolivia, 1 Toledo Toledo 45004",
    "addr:housenumber":"1",
    "addr:postcode":"45004",
    "addr:street":"Calle De Bolivia",
    "iso:country":"ES",
    "sg:address":"Calle de Bolivia, 1",
    "sg:city":"Toledo",
    "sg:orig_category":"Sales (al Por Mayor)",
    "sg:phone":"+34 925 25 08 60",
    "sg:postcode":"45004",
    "sg:province":"Toledo",
    "wof:name":"Cepas Alonso Antonio",
    "wof:placetype":"venue"
},
  "geometry": {"coordinates":[-4.0298228264,39.8662033081],"type":"Point"}
}