{
  "type": "Feature",
  "properties": {
    "iso:country":"ES",
    "sg:address":"Avda Industria (de La), 52",
    "sg:city":"Alcobendas",
    "sg:orig_category":"Goma: Productos De Uso Industrial (fabricaci\u00d3n, Al Por Mayor)",
    "sg:phone":"+34 916 61 00 57",
    "sg:postcode":"28108",
    "sg:province":"Madrid",
    "wof:name":"Crescenciano De Frutos S.a.",
    "wof:placetype":"venue"
},
  "geometry": {"coordinates":[-3.6563489437,40.5338172913],"type":"Point"}
}