{
  "type": "Feature",
  "properties": {
    "addr:full":"Calle de Alango, 30 Algorta Vizcaya 48992",
    "addr:housenumber":"30",
    "addr:postcode":"48992",
    "addr:street":"Calle De Alango",
    "iso:country":"ES",
    "sg:address":"Calle de Alango, 30",
    "sg:city":"Algorta",
    "sg:orig_category":"Ense\u00d1anza, Formaci\u00d3n Profesional: Aprendizaje",
    "sg:phone":"+34 944 60 26 92",
    "sg:postcode":"48992",
    "sg:province":"Vizcaya",
    "wof:name":"Ayuntamiento De Getxo-laboratorio Y Desinfeccion",
    "wof:placetype":"venue"
},
  "geometry": {"coordinates":[-3.0071780682,43.3466300964],"type":"Point"}
}