{
  "type": "Feature",
  "properties": {
    "addr:full":"Calle de Almirante Cadarso, 25 Valencia Valencia 46005",
    "addr:housenumber":"25",
    "addr:postcode":"46005",
    "addr:street":"Calle De Almirante Cadarso",
    "iso:country":"ES",
    "sg:address":"Calle de Almirante Cadarso, 25",
    "sg:city":"Valencia",
    "sg:orig_category":"Abogados",
    "sg:phone":"+34 963 95 25 32",
    "sg:postcode":"46005",
    "sg:province":"Valencia",
    "wof:name":"Valero Nadal Ana Maria",
    "wof:placetype":"venue"
},
  "geometry": {"coordinates":[-0.3673050106,39.4645462036],"type":"Point"}
}