{
  "type": "Feature",
  "properties": {
    "addr:full":"Avda Apostoles, 24 Madrid Madrid 28011",
    "addr:housenumber":"24",
    "addr:postcode":"madrid;28011",
    "addr:street":"Avda Apostoles",
    "iso:country":"ES",
    "sg:address":"Avda Apostoles, 24",
    "sg:city":"Madrid",
    "sg:orig_category":"Empresas De Carpinter\u00cda",
    "sg:phone":"+34 914 79 87 01",
    "sg:postcode":"28011",
    "sg:province":"Madrid",
    "wof:name":"Hermanos Garcia Y Sieu S.l.",
    "wof:placetype":"venue"
},
  "geometry": {"coordinates":[-3.7397990227,40.40574646],"type":"Point"}
}