{
  "type": "Feature",
  "properties": {
    "iso:country":"ES",
    "sg:address":"Calle de Camilo Jose Cela, 3",
    "sg:city":"Mula",
    "sg:orig_category":"Cobro De Pr\u00c9stamos",
    "sg:phone":"+34 968 66 10 10",
    "sg:postcode":"30170",
    "sg:province":"Murcia",
    "wof:name":"Agencia Regional De Recaudacion",
    "wof:placetype":"venue"
},
  "geometry": {"coordinates":[-1.5596116781,38.0951423645],"type":"Point"}
}