{
  "type": "Feature",
  "properties": {
    "iso:country":"ES",
    "sg:address":"Carr Luis Vives, 7",
    "sg:city":"Moncada",
    "sg:orig_category":"Agencias De Viajes",
    "sg:phone":"+34 961 30 90 53",
    "sg:postcode":"46113",
    "sg:province":"Valencia",
    "wof:name":"Viajes Amazona S.l.",
    "wof:placetype":"venue"
},
  "geometry": {"coordinates":[-0.3982529938,39.5452728271],"type":"Point"}
}