{
  "type": "Feature",
  "properties": {
    "addr:full":"Calle de Mora\u00d1a (la), 7 Avila \u00c1vila 05002",
    "addr:housenumber":"7",
    "addr:postcode":"05002",
    "addr:street":"Calle De Moran\u0303A La;A\u0301Vila",
    "iso:country":"ES",
    "sg:address":"Calle de Mora\u00d1a (la), 7",
    "sg:city":"Avila",
    "sg:orig_category":"Bares, Piano",
    "sg:phone":"+34 920 21 27 00",
    "sg:postcode":"05002",
    "sg:province":"\u00c1vila",
    "wof:name":"Jose Herranz E Hijos S.l.",
    "wof:placetype":"venue"
},
  "geometry": {"coordinates":[-4.6997661591,40.6498413086],"type":"Point"}
}