{
  "type": "Feature",
  "properties": {
    "addr:full":"Plaz Bibataubin (de), 1 Granada Granada 18009",
    "addr:postcode":"18009",
    "addr:street":"Plaz",
    "iso:country":"ES",
    "sg:address":"Plaz Bibataubin (de), 1",
    "sg:city":"Granada",
    "sg:orig_category":"Molduras, Junquillos, Listones Y Molduras Perforadas",
    "sg:phone":"+34 958 22 10 41",
    "sg:postcode":"18009",
    "sg:province":"Granada",
    "wof:name":"Martina Viola Johanffon",
    "wof:placetype":"venue"
},
  "geometry": {"coordinates":[-3.59760499,37.1718978882],"type":"Point"}
}