{
  "type": "Feature",
  "properties": {
    "iso:country":"ES",
    "sg:address":"Calle de Bruselas, 69",
    "sg:city":"Capellania",
    "sg:orig_category":"Electricidad, Electr\u00d3nica: Suministros (al Por Menor)",
    "sg:phone":"+34 952 44 93 96",
    "sg:postcode":"29639",
    "sg:province":"M\u00e1laga",
    "wof:name":"Telco Sensors S.l.",
    "wof:placetype":"venue"
},
  "geometry": {"coordinates":[-4.5734581947,36.5951728821],"type":"Point"}
}