{
  "type": "Feature",
  "properties": {
    "iso:country":"ES",
    "sg:address":"Calle de Alejandro Seiquer, 4",
    "sg:city":"San Lorenzo",
    "sg:orig_category":"M\u00c9dicos: Cirug\u00cda Maxilofacial",
    "sg:phone":"+34 968 21 53 34",
    "sg:postcode":"30001",
    "sg:province":"Murcia",
    "wof:name":"Ramirez Huete Juan Antonio",
    "wof:placetype":"venue"
},
  "geometry": {"coordinates":[-1.1298867464,37.9834747314],"type":"Point"}
}