{
  "type": "Feature",
  "properties": {
    "iso:country":"ES",
    "sg:address":"Calle de Ca\u00d1ada Real, 35",
    "sg:city":"Alovera",
    "sg:orig_category":"Cl\u00cdnicas Dentales",
    "sg:phone":"+34 949 27 52 18",
    "sg:postcode":"19208",
    "sg:province":"Guadalajara",
    "wof:name":"Dental Alovera Cb",
    "wof:placetype":"venue"
},
  "geometry": {"coordinates":[-3.2489299774,40.5955467224],"type":"Point"}
}