{
  "type": "Feature",
  "properties": {
    "addr:full":"Calle de Carpinteros, 6 Villaviciosa Odon Madrid 28670",
    "addr:housenumber":"6",
    "addr:postcode":"28670",
    "addr:street":"Calle De Carpinteros;Odon",
    "iso:country":"ES",
    "sg:address":"Calle de Carpinteros, 6",
    "sg:city":"Villaviciosa Odon",
    "sg:orig_category":"Grafistas",
    "sg:phone":"+34 917 10 04 26",
    "sg:postcode":"28670",
    "sg:province":"Madrid",
    "wof:name":"Noisy Studio S.l.",
    "wof:placetype":"venue"
},
  "geometry": {"coordinates":[-3.904910326,40.3502998352],"type":"Point"}
}