{
  "type": "Feature",
  "properties": {
    "iso:country":"ES",
    "sg:address":"Carr Sant Tomas, 94",
    "sg:city":"Benicasim",
    "sg:orig_category":"Farmacias",
    "sg:phone":"+34 964 30 48 30",
    "sg:postcode":"12560",
    "sg:province":"Castell\u00f3n",
    "wof:name":"Garcia Beltran Alfredo",
    "wof:placetype":"venue"
},
  "geometry": {"coordinates":[0.0466559008,40.0530471802],"type":"Point"}
}