{
  "type": "Feature",
  "properties": {
    "iso:country":"ES",
    "sg:address":"Calle de General Pardi\u00d1as, 102",
    "sg:city":"Madrid",
    "sg:classifiers":[
        {
            "category":"Professional",
            "subcategory":"Research",
            "type":"Services"
        }
    ],
    "sg:phone":"+34 915 61 05 23",
    "sg:postcode":"28006",
    "sg:province":"Madrid",
    "sg:tags":[
        "mercado",
        "de",
        "estudios"
    ],
    "wof:name":"Luis Martin De Dios S.a.",
    "wof:placetype":"venue"
},
  "geometry": {"coordinates":[-3.6776230335,40.43491745],"type":"Point"}
}