{
  "type": "Feature",
  "properties": {
    "addr:full":"Rond Maestranza, 15 Zafra Badajoz 06300",
    "addr:housenumber":"15",
    "addr:postcode":"06300",
    "addr:street":"Rond Maestranza",
    "iso:country":"ES",
    "sg:address":"Rond Maestranza, 15",
    "sg:city":"Zafra",
    "sg:orig_category":"Prot\u00c9sicos Dentales",
    "sg:phone":"+34 924 55 24 68",
    "sg:postcode":"06300",
    "sg:province":"Badajoz",
    "wof:name":"Hermanos Martinez C.b.",
    "wof:placetype":"venue"
},
  "geometry": {"coordinates":[-6.4171338081,38.4259185791],"type":"Point"}
}