{
  "type": "Feature",
  "properties": {
    "addr:full":"Pl Catalunya, 5 Porrera Tarragona 43739",
    "addr:housenumber":"5",
    "addr:postcode":"43739",
    "addr:street":"Pl Catalunya",
    "iso:country":"ES",
    "sg:address":"Pl Catalunya, 5",
    "sg:city":"Porrera",
    "sg:orig_category":"Productores Recolectores, Venta Directa De Vinos",
    "sg:phone":"+34 977 82 80 16",
    "sg:postcode":"43739",
    "sg:province":"Tarragona",
    "wof:name":"Tros Del Padri S.l.",
    "wof:placetype":"venue"
},
  "geometry": {"coordinates":[0.8565719724,41.1879577637],"type":"Point"}
}