{
  "type": "Feature",
  "properties": {
    "iso:country":"ES",
    "sg:address":"Carrer de Topete, 94",
    "sg:city":"Terrassa",
    "sg:orig_category":"Carnicer\u00cdas, Carnicer\u00cdas",
    "sg:phone":"+34 937 83 03 03",
    "sg:postcode":"08221",
    "sg:province":"Barcelona",
    "wof:name":"Gomez Santos Luis",
    "wof:placetype":"venue"
},
  "geometry": {"coordinates":[2.0170679092,41.5601501465],"type":"Point"}
}