{
  "type": "Feature",
  "properties": {
    "addr:full":"Menorca (pol. Ind. Can Oller), 21 Sta. Perpetua Mogoda Barcelona 08130",
    "addr:housenumber":"21",
    "addr:postcode":"08130",
    "addr:street":"Ind.",
    "iso:country":"ES",
    "sg:address":"Menorca (pol. Ind. Can Oller), 21",
    "sg:city":"Sta. Perpetua Mogoda",
    "sg:orig_category":"M\u00c1quinas Y Material Para La Industria De La Alimentaci\u00d3n",
    "sg:phone":"+34 935 44 38 00",
    "sg:postcode":"08130",
    "sg:province":"Barcelona",
    "wof:name":"Dordal S.a.",
    "wof:placetype":"venue"
},
  "geometry": {"coordinates":[2.1761109829,41.5448265076],"type":"Point"}
}