{
  "type": "Feature",
  "properties": {
    "addr:full":"Avda Elvas, S/n Badajoz Badajoz 06...",
    "addr:housenumber":"06 ...",
    "addr:street":"Avda Elvas S / N;Badajoz",
    "iso:country":"ES",
    "sg:address":"Avda Elvas, S/n",
    "sg:city":"Badajoz",
    "sg:orig_category":"Ense\u00d1anza, Formaci\u00d3n Profesional: Aprendizaje",
    "sg:phone":"+34 924 28 94 07",
    "sg:postcode":"06...",
    "sg:province":"Badajoz",
    "sg:website":"www.unex.es",
    "wof:name":"Universidad De Extremadura",
    "wof:placetype":"venue"
},
  "geometry": {"coordinates":[-7.0020041466,38.8824882507],"type":"Point"}
}