{
  "type": "Feature",
  "properties": {
    "addr:full":"Pase Aintzieta De, 32 Donostia-san Sebastian Guip\u00f9zcoa 20014",
    "addr:housenumber":"32",
    "addr:postcode":"20014",
    "iso:country":"ES",
    "sg:address":"Pase Aintzieta De, 32",
    "sg:city":"Donostia-san Sebastian",
    "sg:orig_category":"Pintura, Barniz, Productos Asimilables (fabricaci\u00d3n, Al Por Mayor)",
    "sg:phone":"+34 943 45 35 22",
    "sg:postcode":"20014",
    "sg:province":"Guip\u00f9zcoa",
    "sg:website":"www.pinturaspicon.com",
    "wof:name":"Picon S. L.",
    "wof:placetype":"venue"
},
  "geometry": {"coordinates":[-1.9009970427,43.2548027039],"type":"Point"}
}