{
  "type": "Feature",
  "properties": {
    "iso:country":"ES",
    "sg:address":"Plaz Espa\u00d1a, 11",
    "sg:city":"Salamanca",
    "sg:orig_category":"M\u00c9dicos: Medicina Del Trabajo",
    "sg:phone":"+34 923 26 07 55",
    "sg:postcode":"37004",
    "sg:province":"Salamanca",
    "wof:name":"Lopez Lopez Marcial",
    "wof:placetype":"venue"
},
  "geometry": {"coordinates":[-5.663848877,40.964225769],"type":"Point"}
}