{
  "type": "Feature",
  "properties": {
    "addr:full":"Cmno Coin, 2 Fuengirola M\u00e1laga 29640",
    "addr:housenumber":"2",
    "addr:postcode":"29640",
    "addr:street":"Cmno Coin;Ma\u0301Laga",
    "iso:country":"ES",
    "sg:address":"Cmno Coin, 2",
    "sg:city":"Fuengirola",
    "sg:orig_category":"Marketing Telef\u00d3nico",
    "sg:phone":"+34 951 31 15 08",
    "sg:postcode":"29640",
    "sg:province":"M\u00e1laga",
    "wof:name":"Morgan Marketing S.l.",
    "wof:placetype":"venue"
},
  "geometry": {"coordinates":[-4.6330537796,36.5426368713],"type":"Point"}
}