{
  "type": "Feature",
  "properties": {
    "iso:country":"ES",
    "sg:address":"Calle de Juan Ochoa, 17",
    "sg:city":"Aviles",
    "sg:orig_category":"Electricidad: Instaladores",
    "sg:phone":"+34 985 56 58 53",
    "sg:postcode":"33401",
    "sg:province":"Asturias",
    "wof:name":"Electricidad Taranis S.l.",
    "wof:placetype":"venue"
},
  "geometry": {"coordinates":[-5.9316577911,43.5566520691],"type":"Point"}
}