{
  "type": "Feature",
  "properties": {
    "addr:full":"Carrer de Pintor Tapiro, 2 Barcelona Barcelona 08028",
    "addr:housenumber":"2",
    "addr:postcode":"08028",
    "addr:street":"Carrer De Pintor Tapiro",
    "iso:country":"ES",
    "sg:address":"Carrer de Pintor Tapiro, 2",
    "sg:city":"Barcelona",
    "sg:orig_category":"Asociaciones Humanitarias, De Cooperaci\u00d3n, De Acci\u00d3n Social",
    "sg:phone":"+34 934 40 88 00",
    "sg:postcode":"08028",
    "sg:province":"Barcelona",
    "wof:name":"Asociacion De Enfermos Del Ri\u00f1on",
    "wof:placetype":"venue"
},
  "geometry": {"coordinates":[2.1196277142,41.3770256042],"type":"Point"}
}