{
  "type": "Feature",
  "properties": {
    "iso:country":"ES",
    "sg:address":"Calle de Valdivieso, 36",
    "sg:city":"Madrid",
    "sg:orig_category":"Frutas, Legumbres Frescas Y Tempranas (al Por Menor)",
    "sg:phone":"+34 913 57 30 58",
    "sg:postcode":"28023",
    "sg:province":"Madrid",
    "wof:name":"Delgado Tardon Jesus",
    "wof:placetype":"venue"
},
  "geometry": {"coordinates":[-3.7822449207,40.4586296082],"type":"Point"}
}