{
  "type": "Feature",
  "properties": {
    "iso:country":"ES",
    "sg:address":"Avda Sobrarbe, 4",
    "sg:city":"Ainsa",
    "sg:orig_category":"Asociaciones Y Clubs Deportivos",
    "sg:phone":"+34 974 50 09 83",
    "sg:postcode":"22330",
    "sg:province":"Huesca",
    "sg:website":"www.intersport.es",
    "wof:name":"Ajobin Arnaudas Lucia",
    "wof:placetype":"venue"
},
  "geometry": {"coordinates":[0.149872601,42.3956031799],"type":"Point"}
}