{
  "type": "Feature",
  "properties": {
    "iso:country":"ES",
    "sg:address":"Avda Claveles, S/n",
    "sg:city":"Majadahonda",
    "sg:orig_category":"Centros De Educaci\u00d3n Especial",
    "sg:phone":"+34 916 38 78 77",
    "sg:postcode":"28220",
    "sg:province":"Madrid",
    "wof:name":"Colegio Publico Rosalia De Castro",
    "wof:placetype":"venue"
},
  "geometry": {"coordinates":[-3.863451004,40.4712524414],"type":"Point"}
}