{
  "type": "Feature",
  "properties": {
    "iso:country":"ES",
    "sg:address":"Carr Horta D'en Geli, 10",
    "sg:city":"Jonquera",
    "sg:orig_category":"Empresas De Carpinter\u00cda De Madera",
    "sg:phone":"+34 972 55 48 21",
    "sg:postcode":"17700",
    "sg:province":"Girona",
    "wof:name":"Guixeras Punti Jose",
    "wof:placetype":"venue"
},
  "geometry": {"coordinates":[2.8747138977,42.4161338806],"type":"Point"}
}