{
  "type": "Feature",
  "properties": {
    "addr:full":"Avda Fernandez Balsera De, 37 Aviles Asturias 33402",
    "addr:postcode":"33402",
    "addr:street":"Avda Fernandez",
    "iso:country":"ES",
    "sg:address":"Avda Fernandez Balsera De, 37",
    "sg:city":"Aviles",
    "sg:orig_category":"Material Y Herramientas Agr\u00cdcolas",
    "sg:phone":"+34 985 56 33 00",
    "sg:postcode":"33402",
    "sg:province":"Asturias",
    "wof:name":"Laviada E Hijos S.l.",
    "wof:placetype":"venue"
},
  "geometry": {"coordinates":[-5.9256691933,43.5565490723],"type":"Point"}
}