{
  "type": "Feature",
  "properties": {
    "iso:country":"ES",
    "sg:address":"Calle de Marcelino Perdomo Reyes, 21",
    "sg:city":"San Cristobal De La Laguna",
    "sg:orig_category":"Diet\u00c9tica: Productos Biol\u00d3gicos, Naturales Y Diet\u00c9ticos (fabricaci\u00d3n, Al Por Mayor)",
    "sg:phone":"+34 922 63 17 94",
    "sg:postcode":"38206",
    "sg:province":"Santa Cruz De Tenerife",
    "wof:name":"Productos Naturales Bambu S.l.",
    "wof:placetype":"venue"
},
  "geometry": {"coordinates":[-16.3250389099,28.4848594666],"type":"Point"}
}