{
  "type": "Feature",
  "properties": {
    "addr:full":"Los Barreros, 4 Jimenez Jamuz Le\u00f3n 24767",
    "addr:housenumber":"4",
    "addr:postcode":"24767",
    "addr:street":"Los Barreros;Leo\u0301N",
    "iso:country":"ES",
    "sg:address":"Los Barreros, 4",
    "sg:city":"Jimenez Jamuz",
    "sg:orig_category":"Enfermeras: Consultas, Atenci\u00d3n A Domicilio",
    "sg:phone":"+34 987 66 43 93",
    "sg:postcode":"24767",
    "sg:province":"Le\u00f3n",
    "wof:name":"Mateos Miguelez Adelaida",
    "wof:placetype":"venue"
},
  "geometry": {"coordinates":[-5.9285740852,42.2646751404],"type":"Point"}
}