{
  "type": "Feature",
  "properties": {
    "iso:country":"ES",
    "sg:address":"Calle de Alfonso Vi, 31",
    "sg:city":"Segovia",
    "sg:orig_category":"Alumbrados",
    "sg:phone":"+34 921 43 54 10",
    "sg:postcode":"40004",
    "sg:province":"Segovia",
    "wof:name":"Pablo Martin Alvaro De",
    "wof:placetype":"venue"
},
  "geometry": {"coordinates":[-4.1068229675,40.9432868958],"type":"Point"}
}