{
  "type": "Feature",
  "properties": {
    "addr:full":"Avda Derechos Humanos, 9 Alhaurin El Grande M\u00e1laga 29120",
    "addr:housenumber":"9",
    "addr:postcode":"29120",
    "addr:street":"Avda Derechos Humanos",
    "iso:country":"ES",
    "sg:address":"Avda Derechos Humanos, 9",
    "sg:city":"Alhaurin El Grande",
    "sg:orig_category":"Muebles Y Accesorios Para Cocinas Y Cuartos De Ba\u00d1o (al Por Menor)",
    "sg:phone":"+34 952 59 71 23",
    "sg:postcode":"29120",
    "sg:province":"M\u00e1laga",
    "wof:name":"Magistral Cocinas S.l.l.",
    "wof:placetype":"venue"
},
  "geometry": {"coordinates":[-4.6795802116,36.6467323303],"type":"Point"}
}