{
  "type": "Feature",
  "properties": {
    "iso:country":"ES",
    "sg:address":"Avda Camino De Lo Cortao (de), 6",
    "sg:city":"San Sebastian De Los Reyes",
    "sg:orig_category":"Inform\u00c1tica, Ofim\u00c1tica (estudios, Asesor\u00cda, Ingenier\u00cda, Formaci\u00d3n)",
    "sg:phone":"+34 916 59 16 44",
    "sg:postcode":"28700",
    "sg:province":"Madrid",
    "wof:name":"Sistemas Informaticos De Alcobendas S.a.",
    "wof:placetype":"venue"
},
  "geometry": {"coordinates":[-3.6253190041,40.5473556519],"type":"Point"}
}