{
  "type": "Feature",
  "properties": {
    "iso:country":"ES",
    "sg:address":"Calle de Rosalia De Castro, 6",
    "sg:city":"Escairon",
    "sg:orig_category":"Empresas De Carpinter\u00cda De Madera",
    "sg:phone":"+34 982 45 23 46",
    "sg:postcode":"27540",
    "sg:province":"Lugo",
    "wof:name":"Vazquez Vazquez Ramon",
    "wof:placetype":"venue"
},
  "geometry": {"coordinates":[-7.6386108398,42.5862236023],"type":"Point"}
}