{
  "type": "Feature",
  "properties": {
    "addr:full":"Carr Mayor, 20 Oliva Valencia 46780",
    "addr:housenumber":"20",
    "addr:postcode":"46780",
    "addr:street":"Carr Mayor",
    "iso:country":"ES",
    "sg:address":"Carr Mayor, 20",
    "sg:city":"Oliva",
    "sg:orig_category":"Ropa Para Se\u00d1oras Y Caballeros (al Por Menor)",
    "sg:phone":"+34 962 85 22 39",
    "sg:postcode":"46780",
    "sg:province":"Valencia",
    "wof:name":"Simon Gilabert Maria Teresa",
    "wof:placetype":"venue"
},
  "geometry": {"coordinates":[-0.1179220006,38.9189491272],"type":"Point"}
}