{
  "type": "Feature",
  "properties": {
    "iso:country":"ES",
    "sg:address":"Calle de Brigadier Algarra, 28",
    "sg:city":"Petrer",
    "sg:orig_category":"Farmacias",
    "sg:phone":"+34 965 37 19 66",
    "sg:postcode":"03610",
    "sg:province":"Alicante",
    "wof:name":"Coves Lopez Carlos",
    "wof:placetype":"venue"
},
  "geometry": {"coordinates":[-0.7810459137,38.4825592041],"type":"Point"}
}