{
  "type": "Feature",
  "properties": {
    "addr:full":"Calle de Parroco Don Emilio Franco, 53 Madrid Madrid 28053",
    "addr:housenumber":"53",
    "addr:postcode":"madrid;28053",
    "addr:street":"Calle De Parroco;Franco",
    "iso:country":"ES",
    "sg:address":"Calle de Parroco Don Emilio Franco, 53",
    "sg:city":"Madrid",
    "sg:orig_category":"Electrodom\u00c9sticos (al Por Menor)",
    "sg:phone":"+34 914 77 76 71",
    "sg:postcode":"28053",
    "sg:province":"Madrid",
    "wof:name":"Lopez Viejo Pedro",
    "wof:placetype":"venue"
},
  "geometry": {"coordinates":[-3.6671760082,40.3900871277],"type":"Point"}
}