{
  "type": "Feature",
  "properties": {
    "addr:full":"Rua Rosalia De Castro, 17 Cee A Coru\u00f1a 15270",
    "addr:housenumber":"17",
    "addr:postcode":"15270",
    "addr:street":"Rua Rosalia De Castro",
    "iso:country":"ES",
    "sg:address":"Rua Rosalia De Castro, 17",
    "sg:city":"Cee",
    "sg:orig_category":"Ropa Para Se\u00d1oras (al Por Menor)",
    "sg:phone":"+34 981 70 65 26",
    "sg:postcode":"15270",
    "sg:province":"A Coru\u00f1a",
    "wof:name":"Valhalla Moda S.c.",
    "wof:placetype":"venue"
},
  "geometry": {"coordinates":[-9.1880369186,42.9536018372],"type":"Point"}
}