{
  "type": "Feature",
  "properties": {
    "addr:full":"Avda Provincias (de Las), 48 Fuenlabrada Madrid 28941",
    "addr:housenumber":"48",
    "addr:postcode":"28941",
    "addr:street":"Avda Provincias De Las",
    "iso:country":"ES",
    "sg:address":"Avda Provincias (de Las), 48",
    "sg:city":"Fuenlabrada",
    "sg:orig_category":"Agencias De Viajes",
    "sg:phone":"+34 916 90 66 63",
    "sg:postcode":"28941",
    "sg:province":"Madrid",
    "sg:website":"www.multiviajes.org",
    "wof:name":"Europa Multiviajes Sl",
    "wof:placetype":"venue"
},
  "geometry": {"coordinates":[-3.7949199677,40.2954406738],"type":"Point"}
}