{
  "type": "Feature",
  "properties": {
    "iso:country":"ES",
    "sg:address":"Calle de Escultor Marinas (del), 14",
    "sg:city":"Segovia",
    "sg:orig_category":"Poller\u00cda Y Caza (al Por Menor)",
    "sg:phone":"+34 921 42 58 07",
    "sg:postcode":"40002",
    "sg:province":"Segovia",
    "wof:name":"Martin Carrasco Jose Luis",
    "wof:placetype":"venue"
},
  "geometry": {"coordinates":[-4.1195950508,40.9444541931],"type":"Point"}
}