{
  "type": "Feature",
  "properties": {
    "iso:country":"ES",
    "sg:address":"Avda Petroliferas De Las, S/n",
    "sg:city":"Palmas De Gran Canaria",
    "sg:orig_category":"Fabricaci\u00d3n, Reparaci\u00d3n Y Mantenimiento De Construcciones Navales Y Fluviales",
    "sg:phone":"+34 928 46 78 51",
    "sg:postcode":"35008",
    "sg:province":"Las Palmas",
    "wof:name":"Scandinavian Marine Services S.l.",
    "wof:placetype":"venue"
},
  "geometry": {"coordinates":[-15.4141139984,28.153799057],"type":"Point"}
}