{
  "type": "Feature",
  "properties": {
    "addr:full":"Carrer de Moles (d'en), 2 Mataro Barcelona 08302",
    "addr:housenumber":"2",
    "addr:postcode":"08302",
    "addr:street":"Carrer De Moles D'En",
    "iso:country":"ES",
    "sg:address":"Carrer de Moles (d'en), 2",
    "sg:city":"Mataro",
    "sg:orig_category":"Arquitectos",
    "sg:phone":"+34 937 90 36 50",
    "sg:postcode":"08302",
    "sg:province":"Barcelona",
    "wof:name":"Carbonell Colominas Jose Maria",
    "wof:placetype":"venue"
},
  "geometry": {"coordinates":[2.4433350563,41.5397567749],"type":"Point"}
}