{
  "type": "Feature",
  "properties": {
    "addr:full":"Pla\u00c7 Esglesia, 2 Cellera Ter Girona 17165",
    "addr:housenumber":"2",
    "addr:postcode":"17165",
    "addr:street":"Plac\u0327 Esglesia;Cellera Ter",
    "iso:country":"ES",
    "sg:address":"Pla\u00c7 Esglesia, 2",
    "sg:city":"Cellera Ter",
    "sg:orig_category":"Pescader\u00cdas (al Por Menor)",
    "sg:phone":"+34 972 42 17 06",
    "sg:postcode":"17165",
    "sg:province":"Girona",
    "wof:name":"Selga Peix S.l.",
    "wof:placetype":"venue"
},
  "geometry": {"coordinates":[2.6211791039,41.9696998596],"type":"Point"}
}