{
  "type": "Feature",
  "properties": {
    "addr:full":"Pase Juan Xxiii, 6 Madrid Madrid 28040",
    "addr:housenumber":"6",
    "addr:postcode":"28040",
    "addr:street":"Juan Xxiii",
    "iso:country":"ES",
    "sg:address":"Pase Juan Xxiii, 6",
    "sg:city":"Madrid",
    "sg:orig_category":"Ense\u00d1anza: Idiomas",
    "sg:phone":"+34 915 33 62 52",
    "sg:postcode":"28040",
    "sg:province":"Madrid",
    "wof:name":"International House Madrid S. A.",
    "wof:placetype":"venue"
},
  "geometry": {"coordinates":[-3.7196729183,40.4446372986],"type":"Point"}
}