{
  "type": "Feature",
  "properties": {
    "iso:country":"ES",
    "sg:address":"Calle de Alcalde Francisco Arnau, 19",
    "sg:city":"Segorbe",
    "sg:orig_category":"T\u00c9cnicos Veterinarios",
    "sg:phone":"+34 964 71 28 11",
    "sg:postcode":"12400",
    "sg:province":"Castell\u00f3n",
    "wof:name":"Montolio Bartoll Juan Enrique",
    "wof:placetype":"venue"
},
  "geometry": {"coordinates":[-0.4929470122,39.8502693176],"type":"Point"}
}