{
  "type": "Feature",
  "properties": {
    "addr:full":"Calle de Alegria, 6 Madrid Madrid 28025",
    "addr:housenumber":"6",
    "addr:postcode":"28025",
    "addr:street":"Calle De Alegria",
    "iso:country":"ES",
    "sg:address":"Calle de Alegria, 6",
    "sg:city":"Madrid",
    "sg:orig_category":"Aparcamientos (infraestructuras, Accesorios)",
    "sg:phone":"+34 914 65 85 13",
    "sg:postcode":"28025",
    "sg:province":"Madrid",
    "wof:name":"Lopez Lopez Maria Del Carmen",
    "wof:placetype":"venue"
},
  "geometry": {"coordinates":[-3.7323789597,40.385383606],"type":"Point"}
}