{
  "type": "Feature",
  "properties": {
    "iso:country":"ES",
    "sg:address":"Calle de Duque De Liria, 9",
    "sg:city":"Madrid",
    "sg:orig_category":"Discotecas Y Salas De Baile",
    "sg:phone":"+34 915 48 12 44",
    "sg:postcode":"28015",
    "sg:province":"Madrid",
    "wof:name":"Coronado Suarez Alfonso Elias",
    "wof:placetype":"venue"
},
  "geometry": {"coordinates":[-3.7125511169,40.4261436462],"type":"Point"}
}