{
  "type": "Feature",
  "properties": {
    "iso:country":"ES",
    "sg:address":"Calle de Renova, 3",
    "sg:city":"Zamora",
    "sg:orig_category":"Fabricaci\u00d3n De Sobres, Bolsas Y Fundas",
    "sg:phone":"+34 980 53 38 81",
    "sg:postcode":"49002",
    "sg:province":"Zamora",
    "wof:name":"Mannu Leopoldo Manuel Melchor",
    "wof:placetype":"venue"
},
  "geometry": {"coordinates":[-5.7462449074,41.5035324097],"type":"Point"}
}