{
  "type": "Feature",
  "properties": {
    "addr:full":"Pase Doctor Torres Villarroel, 37 Salamanca Salamanca 37006",
    "addr:housenumber":"37",
    "addr:postcode":"37006",
    "addr:street":"Doctor Torres Villarroel",
    "iso:country":"ES",
    "sg:address":"Pase Doctor Torres Villarroel, 37",
    "sg:city":"Salamanca",
    "sg:orig_category":"Molduras, Junquillos, Listones Y Molduras Perforadas",
    "sg:phone":"+34 923 22 61 65",
    "sg:postcode":"37006",
    "sg:province":"Salamanca",
    "wof:name":"Sandietel S.l.",
    "wof:placetype":"venue"
},
  "geometry": {"coordinates":[-5.6632061005,40.973236084],"type":"Point"}
}