{
  "type": "Feature",
  "properties": {
    "iso:country":"ES",
    "sg:address":"Calle de Bailen, 9",
    "sg:city":"Madrid",
    "sg:orig_category":"Loter\u00cda Y T\u00d3mbola",
    "sg:phone":"+34 915 47 75 25",
    "sg:postcode":"28013",
    "sg:province":"Madrid",
    "wof:name":"Zamorano Garcia Isabel",
    "wof:placetype":"venue"
},
  "geometry": {"coordinates":[-3.7127888203,40.420249939],"type":"Point"}
}