{
  "type": "Feature",
  "properties": {
    "iso:country":"ES",
    "sg:address":"Calle de Mancoba, 2",
    "sg:city":"Baza",
    "sg:orig_category":"Maquinaria Para Industrias Diversas",
    "sg:phone":"+34 958 70 15 54",
    "sg:postcode":"18800",
    "sg:province":"Granada",
    "wof:name":"Garcia Ferrer Daniel",
    "wof:placetype":"venue"
},
  "geometry": {"coordinates":[-2.779227972,37.4825706482],"type":"Point"}
}