{
  "type": "Feature",
  "properties": {
    "iso:country":"ES",
    "sg:address":"Calle de Mayor, 44",
    "sg:city":"Corella",
    "sg:orig_category":"Confiter\u00cdas, Chocolater\u00cdas (al Por Menor)",
    "sg:phone":"+34 948 78 06 18",
    "sg:postcode":"31591",
    "sg:province":"Navarra",
    "wof:name":"Lazaro Gilcuartero Fermina",
    "wof:placetype":"venue"
},
  "geometry": {"coordinates":[-1.7858790159,42.1144714355],"type":"Point"}
}