{
  "type": "Feature",
  "properties": {
    "addr:full":"Plaz Espa\u00d1a, 16 Aguilar Campoo Palencia 34800",
    "addr:housenumber":"16",
    "addr:postcode":"34800",
    "addr:street":"Plaz Espan\u0303A",
    "iso:country":"ES",
    "sg:address":"Plaz Espa\u00d1a, 16",
    "sg:city":"Aguilar Campoo",
    "sg:orig_category":"Fabricaci\u00d3n, Importaci\u00d3n, Venta De Material De Telefon\u00cda, Peritelefon\u00cda",
    "sg:phone":"+34 979 12 80 98",
    "sg:postcode":"34800",
    "sg:province":"Palencia",
    "wof:name":"Telefonica Data Espa\u00f1a S.a.",
    "wof:placetype":"venue"
},
  "geometry": {"coordinates":[-4.2607240677,42.795501709],"type":"Point"}
}