{
  "type": "Feature",
  "properties": {
    "iso:country":"ES",
    "sg:address":"Santa Lucia, 1",
    "sg:city":"Albox",
    "sg:orig_category":"Ense\u00d1anza: Peluquer\u00cda Est\u00c9tica",
    "sg:phone":"+34 950 43 09 58",
    "sg:postcode":"04800",
    "sg:province":"Almer\u00eda",
    "wof:name":"Gomez Prados Juana Maria",
    "wof:placetype":"venue"
},
  "geometry": {"coordinates":[-2.1464169025,37.388710022],"type":"Point"}
}