{
  "type": "Feature",
  "properties": {
    "iso:country":"ES",
    "sg:address":"Calle de Vasco De Gama, 4",
    "sg:city":"Salamanca",
    "sg:orig_category":"Peluquer\u00cdas, Peluquer\u00cda Mixta",
    "sg:phone":"+34 923 24 76 24",
    "sg:postcode":"37004",
    "sg:province":"Salamanca",
    "wof:name":"Perez Celestino Eduardo",
    "wof:placetype":"venue"
},
  "geometry": {"coordinates":[-5.6572751999,40.9722137451],"type":"Point"}
}