{
  "type": "Feature",
  "properties": {
    "iso:country":"ES",
    "sg:address":"Calle de Toro, 1",
    "sg:city":"Salamanca",
    "sg:orig_category":"Ense\u00d1anza: Idiomas",
    "sg:phone":"+34 923 26 59 86",
    "sg:postcode":"37002",
    "sg:province":"Salamanca",
    "wof:name":"Murphy  Peter",
    "wof:placetype":"venue"
},
  "geometry": {"coordinates":[-5.6635251045,40.965221405],"type":"Point"}
}