{
  "type": "Feature",
  "properties": {
    "iso:country":"ES",
    "sg:address":"Pase Murallas (las), S/n",
    "sg:city":"Baeza",
    "sg:orig_category":"Enfermeras: Consultas, Atenci\u00d3n A Domicilio",
    "sg:phone":"+34 953 74 05 94",
    "sg:postcode":"23440",
    "sg:province":"Ja\u00e9n",
    "wof:name":"Contreras Berdonces Luis",
    "wof:placetype":"venue"
},
  "geometry": {"coordinates":[-3.455904007,37.9970626831],"type":"Point"}
}