{
  "type": "Feature",
  "properties": {
    "iso:country":"ES",
    "sg:address":"Calle de Alcalde De Zalamea, 22",
    "sg:city":"Algar",
    "sg:orig_category":"Bisuter\u00cda, Joyer\u00cda, Relojer\u00cda (al Por Menor)",
    "sg:phone":"+34 968 13 65 10",
    "sg:postcode":"30366",
    "sg:province":"Murcia",
    "wof:name":"Carre\u00d1o Garcia C.b.",
    "wof:placetype":"venue"
},
  "geometry": {"coordinates":[-0.8689574003,37.6454353333],"type":"Point"}
}