{
  "type": "Feature",
  "properties": {
    "addr:full":"Avda Capuchinos, 18 Castellon Castell\u00f3n 12004",
    "addr:housenumber":"18",
    "addr:postcode":"12004",
    "addr:street":"Avda Capuchinos",
    "iso:country":"ES",
    "sg:address":"Avda Capuchinos, 18",
    "sg:city":"Castellon",
    "sg:orig_category":"Inmobiliaria (agencias)",
    "sg:phone":"+34 964 22 49 49",
    "sg:postcode":"12004",
    "sg:province":"Castell\u00f3n",
    "wof:name":"Maife C.b.",
    "wof:placetype":"venue"
},
  "geometry": {"coordinates":[-0.0336900018,39.9903259277],"type":"Point"}
}