{
  "type": "Feature",
  "properties": {
    "iso:country":"ES",
    "sg:address":"Calle de Salud, 10",
    "sg:city":"Valladolid",
    "sg:orig_category":"Discapacitados",
    "sg:phone":"+34 983 20 10 93",
    "sg:postcode":"47012",
    "sg:province":"Valladolid",
    "wof:name":"Agrupacion De Sordos Vallisoletana",
    "wof:placetype":"venue"
},
  "geometry": {"coordinates":[-4.7137136459,41.6469078064],"type":"Point"}
}