{
  "type": "Feature",
  "properties": {
    "iso:country":"ES",
    "sg:address":"Carrer de Esglesia, 7",
    "sg:city":"Vallgorguina",
    "sg:orig_category":"Reposter\u00cdas",
    "sg:phone":"+34 938 67 92 43",
    "sg:postcode":"08470",
    "sg:province":"Barcelona",
    "wof:name":"Barri Teixido Maria Teresa",
    "wof:placetype":"venue"
},
  "geometry": {"coordinates":[2.5098910332,41.6478118896],"type":"Point"}
}