{
  "type": "Feature",
  "properties": {
    "iso:country":"ES",
    "sg:address":"C/ Sant Marti, 3",
    "sg:city":"Riudarenes",
    "sg:orig_category":"Estancos",
    "sg:phone":"+34 972 16 47 53",
    "sg:postcode":"17421",
    "sg:province":"Girona",
    "wof:name":"Negre Horta Josep",
    "wof:placetype":"venue"
},
  "geometry": {"coordinates":[2.71676898,41.8233261108],"type":"Point"}
}