{
  "type": "Feature",
  "properties": {
    "iso:country":"ES",
    "sg:address":"Rua Progreso (do), 20",
    "sg:city":"Ourense",
    "sg:orig_category":"M\u00c9dicos: Alergolog\u00cda",
    "sg:phone":"+34 988 25 47 98",
    "sg:postcode":"32005",
    "sg:province":"Ourense",
    "wof:name":"Justo Justo Julia",
    "wof:placetype":"venue"
},
  "geometry": {"coordinates":[-7.8656592369,42.3335838318],"type":"Point"}
}