{
  "type": "Feature",
  "properties": {
    "addr:full":"Carrer de Lusitania, 106 Sabadell Barcelona 08206",
    "addr:housenumber":"106",
    "addr:postcode":"08206",
    "addr:street":"Carrer De Lusitania",
    "iso:country":"ES",
    "sg:address":"Carrer de Lusitania, 106",
    "sg:city":"Sabadell",
    "sg:orig_category":"Tapiceros Y Tapiceros",
    "sg:phone":"+34 937 23 24 50",
    "sg:postcode":"08206",
    "sg:province":"Barcelona",
    "wof:name":"Calderon Sanchez Maria Del Carmen",
    "wof:placetype":"venue"
},
  "geometry": {"coordinates":[2.0912499428,41.5601615906],"type":"Point"}
}