{
  "type": "Feature",
  "properties": {
    "addr:full":"Honda, 11 Cullar Granada 18850",
    "addr:housenumber":"11",
    "addr:postcode":"18850",
    "iso:country":"ES",
    "sg:address":"Honda, 11",
    "sg:city":"Cullar",
    "sg:orig_category":"Asilos De Ancianos. Centros Privados",
    "sg:phone":"+34 958 73 27 21",
    "sg:postcode":"18850",
    "sg:province":"Granada",
    "wof:name":"Casa Caridad La Encarnacion",
    "wof:placetype":"venue"
},
  "geometry": {"coordinates":[-2.5776090622,37.5830955505],"type":"Point"}
}