{
  "type": "Feature",
  "properties": {
    "addr:full":"Avda Barrio Nuevo, 20 Cangas Narcea Asturias 33800",
    "addr:housenumber":"20",
    "addr:postcode":"33800",
    "addr:street":"Avda Barrio Nuevo",
    "iso:country":"ES",
    "sg:address":"Avda Barrio Nuevo, 20",
    "sg:city":"Cangas Narcea",
    "sg:orig_category":"Motocicletas (agentes, Concesionarios)",
    "sg:phone":"+34 985 81 02 69",
    "sg:postcode":"33800",
    "sg:province":"Asturias",
    "wof:name":"Arbas Garcia Ramon",
    "wof:placetype":"venue"
},
  "geometry": {"coordinates":[-6.5520114899,43.175037384],"type":"Point"}
}