{
  "type": "Feature",
  "properties": {
    "addr:full":"Carrer de Sant Jeroni, 28 Santa Coloma De Gramenet Barcelona 08921",
    "addr:housenumber":"28",
    "addr:postcode":"08921",
    "addr:street":"Carrer De Sant Jeroni",
    "iso:country":"ES",
    "sg:address":"Carrer de Sant Jeroni, 28",
    "sg:city":"Santa Coloma De Gramenet",
    "sg:orig_category":"Librer\u00cdas",
    "sg:phone":"+34 934 68 11 18",
    "sg:postcode":"08921",
    "sg:province":"Barcelona",
    "wof:name":"Perez Valera Carmen",
    "wof:placetype":"venue"
},
  "geometry": {"coordinates":[2.2080099583,41.454662323],"type":"Point"}
}