{
  "type": "Feature",
  "properties": {
    "addr:full":"Bard Juan Xxiii, 18 Burgos Burgos 09007",
    "addr:housenumber":"18",
    "addr:postcode":"09007",
    "addr:street":"Juan Xxiii",
    "iso:country":"ES",
    "sg:address":"Bard Juan Xxiii, 18",
    "sg:city":"Burgos",
    "sg:orig_category":"Confecci\u00d3n De Zapatos",
    "sg:phone":"+34 947 22 25 13",
    "sg:postcode":"09007",
    "sg:province":"Burgos",
    "wof:name":"Fernandez Escolar Arturo",
    "wof:placetype":"venue"
},
  "geometry": {"coordinates":[-3.674819231,42.3508491516],"type":"Point"}
}