{
  "type": "Feature",
  "properties": {
    "addr:full":"Avda Juan Carlos I, Rey, 32 Melilla Melilla 52001",
    "addr:housenumber":"32",
    "addr:postcode":"52001",
    "addr:street":"Avda Juan Carlos I Rey",
    "iso:country":"ES",
    "sg:address":"Avda Juan Carlos I, Rey, 32",
    "sg:city":"Melilla",
    "sg:orig_category":"Art\u00cdculos De Decoraci\u00d3n",
    "sg:phone":"+34 952 68 25 41",
    "sg:postcode":"52001",
    "sg:province":"Melilla",
    "wof:name":"Leon Asensio Pilar",
    "wof:placetype":"venue"
},
  "geometry": {"coordinates":[-2.9412930012,35.2942047119],"type":"Point"}
}