{
  "type": "Feature",
  "properties": {
    "addr:full":"Calle de Carolinas, 10 Madrid Madrid 28039",
    "addr:housenumber":"10",
    "addr:postcode":"madrid;28039",
    "addr:street":"Calle De Carolinas",
    "iso:country":"ES",
    "sg:address":"Calle de Carolinas, 10",
    "sg:city":"Madrid",
    "sg:orig_category":"Iglesias Evang\u00c9licas",
    "sg:phone":"+34 914 50 73 06",
    "sg:postcode":"28039",
    "sg:province":"Madrid",
    "wof:name":"Mision Evangelica China Espa\u00f1ola",
    "wof:placetype":"venue"
},
  "geometry": {"coordinates":[-3.7047386169,40.4512138367],"type":"Point"}
}