{
  "type": "Feature",
  "properties": {
    "iso:country":"ES",
    "sg:address":"Carr Carrilet, 6",
    "sg:city":"Mont-ras",
    "sg:orig_category":"Deportes Y Programas De Aventura",
    "sg:phone":"+34 972 30 41 29",
    "sg:postcode":"17253",
    "sg:province":"Girona",
    "wof:name":"Garcia Perez Maria Dolors",
    "wof:placetype":"venue"
},
  "geometry": {"coordinates":[3.1534330845,41.9085273743],"type":"Point"}
}