{
  "type": "Feature",
  "properties": {
    "iso:country":"ES",
    "sg:address":"Plaza De Mayo, 25",
    "sg:city":"Villarcayo",
    "sg:orig_category":"Urbanistas",
    "sg:phone":"+34 947 13 04 22",
    "sg:postcode":"09550",
    "sg:province":"Burgos",
    "wof:name":"Artec Arquitectura Y Urbanismo S.l",
    "wof:placetype":"venue"
},
  "geometry": {"coordinates":[-3.5729846954,42.9383049011],"type":"Point"}
}