{
  "type": "Feature",
  "properties": {
    "addr:full":"Virgen De La Paz, 17 Villar Arzobispo Valencia 46170",
    "addr:housenumber":"17",
    "addr:postcode":"46170",
    "addr:street":"Virgen;La Paz",
    "iso:country":"ES",
    "sg:address":"Virgen De La Paz, 17",
    "sg:city":"Villar Arzobispo",
    "sg:orig_category":"Laboratorios Y Trabajos De Fotograf\u00cda, V\u00cddeo Y Cine",
    "sg:phone":"+34 961 64 62 32",
    "sg:postcode":"46170",
    "sg:province":"Valencia",
    "wof:name":"Moreno Rodriguez Felix Reyes",
    "wof:placetype":"venue"
},
  "geometry": {"coordinates":[-0.8267620206,39.731502533],"type":"Point"}
}