{
  "type": "Feature",
  "properties": {
    "iso:country":"ES",
    "sg:address":"Telers, S/n",
    "sg:city":"Ontinyent",
    "sg:orig_category":"Estilistas, Estudios De Dise\u00d1o De Telas",
    "sg:phone":"+34 962 91 70 50",
    "sg:postcode":"46870",
    "sg:province":"Valencia",
    "wof:name":"Manuel Ramiro S. L.",
    "wof:placetype":"venue"
},
  "geometry": {"coordinates":[-0.5782790184,38.8317260742],"type":"Point"}
}