{
  "type": "Feature",
  "properties": {
    "addr:full":"Calle de San Pedro, 53 Madrid Madrid 28015",
    "addr:housenumber":"53",
    "addr:postcode":"madrid;28015",
    "addr:street":"Calle De San Pedro",
    "iso:country":"ES",
    "sg:address":"Calle de San Pedro, 53",
    "sg:city":"Madrid",
    "sg:orig_category":"Fisioterapia",
    "sg:phone":"+34 915 44 85 56",
    "sg:postcode":"28015",
    "sg:province":"Madrid",
    "wof:name":"Castillo Martinez Monica Adriana",
    "wof:placetype":"venue"
},
  "geometry": {"coordinates":[-3.7142028809,40.4316825867],"type":"Point"}
}