{
  "type": "Feature",
  "properties": {
    "addr:full":"Calle de Lope De Vega, 10 Zamora Zamora 49013",
    "addr:housenumber":"10",
    "addr:postcode":"49013",
    "addr:street":"Calle De Lope De Vega",
    "iso:country":"ES",
    "sg:address":"Calle de Lope De Vega, 10",
    "sg:city":"Zamora",
    "sg:orig_category":"Laboratorios Farmac\u00c9uticos",
    "sg:phone":"+34 980 51 16 86",
    "sg:postcode":"49013",
    "sg:province":"Zamora",
    "wof:name":"Conejero Dominguez Pedro Demetrio",
    "wof:placetype":"venue"
},
  "geometry": {"coordinates":[-5.7413787842,41.5083007812],"type":"Point"}
}