{
  "type": "Feature",
  "properties": {
    "addr:full":"Avda Lugo, 16 Melide La Coru\u00f1a 15800",
    "addr:housenumber":"16",
    "addr:postcode":"15800",
    "addr:street":"Avda Lugo;La Corun\u0303A",
    "iso:country":"ES",
    "sg:address":"Avda Lugo, 16",
    "sg:city":"Melide",
    "sg:orig_category":"Empresas De Carpinter\u00cda De Madera",
    "sg:phone":"+34 981 50 53 11",
    "sg:postcode":"15800",
    "sg:province":"La Coru\u00f1a",
    "wof:name":"Blanco Castro Horacio",
    "wof:placetype":"venue"
},
  "geometry": {"coordinates":[-8.0110464096,42.9134063721],"type":"Point"}
}