{
  "type": "Feature",
  "properties": {
    "iso:country":"ES",
    "sg:address":"Carrer de Industria, S/n",
    "sg:city":"Sant Feliu Llobregat",
    "sg:orig_category":"Adhesivos (fabricaci\u00d3n, Al Por Mayor)",
    "sg:phone":"+34 936 66 21 57",
    "sg:postcode":"08980",
    "sg:province":"Barcelona",
    "sg:website":"www.lohmannindustrias.com",
    "wof:name":"Lohmann Industrias S.a.",
    "wof:placetype":"venue"
},
  "geometry": {"coordinates":[2.0312700272,41.3963546753],"type":"Point"}
}