{
  "type": "Feature",
  "properties": {
    "iso:country":"ES",
    "sg:address":"Avda Miguel Hernandez, 8",
    "sg:city":"Alaquas",
    "sg:orig_category":"Electrodom\u00c9sticos (al Por Menor)",
    "sg:phone":"+34 961 50 39 29",
    "sg:postcode":"46970",
    "sg:province":"Valencia",
    "wof:name":"Elias Forment S.l.",
    "wof:placetype":"venue"
},
  "geometry": {"coordinates":[-0.4546310008,39.4580535889],"type":"Point"}
}