{
  "type": "Feature",
  "properties": {
    "addr:full":"Calle de Alcalde Henriquez Pitti, 9 Arucas Las Palmas 35400",
    "addr:housenumber":"9",
    "addr:postcode":"35400",
    "addr:street":"Calle De Alcalde Henriquez Pitti",
    "iso:country":"ES",
    "sg:address":"Calle de Alcalde Henriquez Pitti, 9",
    "sg:city":"Arucas",
    "sg:orig_category":"Inmobiliaria (agencias)",
    "sg:phone":"+34 928 62 45 64",
    "sg:postcode":"35400",
    "sg:province":"Las Palmas",
    "wof:name":"Medina Quintana Yasmina",
    "wof:placetype":"venue"
},
  "geometry": {"coordinates":[-15.526594162,28.1176757812],"type":"Point"}
}