{
  "type": "Feature",
  "properties": {
    "iso:country":"ES",
    "sg:address":"C/ Jocs, 94",
    "sg:city":"Inca",
    "sg:orig_category":"Alimentaci\u00d3n General (al Por Menor)",
    "sg:phone":"+34 971 50 11 99",
    "sg:postcode":"07300",
    "sg:province":"Islas Baleares",
    "wof:name":"Pujadas Pieras Miguel",
    "wof:placetype":"venue"
},
  "geometry": {"coordinates":[2.9167449474,39.7226066589],"type":"Point"}
}