{
  "type": "Feature",
  "properties": {
    "addr:full":"Poli Mocholi, S/n Noain Navarra 31110",
    "addr:housenumber":"s",
    "addr:postcode":"31110",
    "addr:street":"/ N",
    "iso:country":"ES",
    "sg:address":"Poli Mocholi, S/n",
    "sg:city":"Noain",
    "sg:orig_category":"Contenedores (mercanc\u00cdas)",
    "sg:phone":"+34 948 34 69 86",
    "sg:postcode":"31110",
    "sg:province":"Navarra",
    "wof:name":"Dslc Consultoria Y Sistemas De Logistica Integral S.l.l.",
    "wof:placetype":"venue"
},
  "geometry": {"coordinates":[-1.6356370449,42.7540054321],"type":"Point"}
}