{
  "type": "Feature",
  "properties": {
    "iso:country":"ES",
    "sg:address":"Rua Rosa (da), 17",
    "sg:city":"Santiago De Compostela",
    "sg:orig_category":"Asociaciones Y Clubs Deportivos",
    "sg:phone":"+34 981 53 15 50",
    "sg:postcode":"15701",
    "sg:province":"A Coru\u00f1a",
    "wof:name":"Varela Miguez Jose Luis",
    "wof:placetype":"venue"
},
  "geometry": {"coordinates":[-8.5476140976,42.871307373],"type":"Point"}
}