{
  "type": "Feature",
  "properties": {
    "addr:full":"Calle de Eduardo Iglesias, 30 Gondomar Pontevedra 36380",
    "addr:housenumber":"30",
    "addr:postcode":"36380",
    "addr:street":"Calle De Eduardo Iglesias",
    "iso:country":"ES",
    "sg:address":"Calle de Eduardo Iglesias, 30",
    "sg:city":"Gondomar",
    "sg:orig_category":"Arreglo, Reparaci\u00d3n, Piezas Sueltas De Televisi\u00d3n, V\u00cddeo, Hi",
    "sg:phone":"+34 986 36 07 62",
    "sg:postcode":"36380",
    "sg:province":"Pontevedra",
    "wof:name":"Portela Alonso Antonio",
    "wof:placetype":"venue"
},
  "geometry": {"coordinates":[-8.7611093521,42.1116867065],"type":"Point"}
}