{
  "type": "Feature",
  "properties": {
    "iso:country":"ES",
    "sg:address":"Calle de Landaburu, 8",
    "sg:city":"San Vicente De Barakaldo",
    "sg:orig_category":"Ense\u00d1anza: Idiomas",
    "sg:phone":"+34 944 78 20 24",
    "sg:postcode":"48902",
    "sg:province":"Vizcaya",
    "wof:name":"Cantalapiedra Gonzalez Maite",
    "wof:placetype":"venue"
},
  "geometry": {"coordinates":[-2.9857740402,43.2936630249],"type":"Point"}
}