{
  "type": "Feature",
  "properties": {
    "addr:full":"Rua Diaz De Rabago, 6 Pobra Do Carami\u00e7al La Coru\u00f1a 15940",
    "addr:housenumber":"6",
    "addr:postcode":"15940",
    "addr:street":"Rua Diaz De Rabago;Corun\u0303A",
    "iso:country":"ES",
    "sg:address":"Rua Diaz De Rabago, 6",
    "sg:city":"Pobra Do Carami\u00e7al",
    "sg:orig_category":"Arquitectos",
    "sg:phone":"+34 981 83 33 68",
    "sg:postcode":"15940",
    "sg:province":"La Coru\u00f1a",
    "wof:name":"Cota Cuatro Arquitectura E Xestion S.l.",
    "wof:placetype":"venue"
},
  "geometry": {"coordinates":[-8.9382047653,42.6066703796],"type":"Point"}
}