{
  "type": "Feature",
  "properties": {
    "addr:full":"Plaz Pescador (del), 3 Colindres Cantabria 39750",
    "addr:postcode":"39750",
    "iso:country":"ES",
    "sg:address":"Plaz Pescador (del), 3",
    "sg:city":"Colindres",
    "sg:orig_category":"Ropa Para Se\u00d1oras Y Caballeros (al Por Menor)",
    "sg:phone":"+34 942 67 45 70",
    "sg:postcode":"39750",
    "sg:province":"Cantabria",
    "wof:name":"Perez Borrajo Juan Antonio",
    "wof:placetype":"venue"
},
  "geometry": {"coordinates":[-3.4482440948,43.3958396912],"type":"Point"}
}