{
  "type": "Feature",
  "properties": {
    "iso:country":"ES",
    "sg:address":"Carrer de Torrijos, 96",
    "sg:city":"Mataro",
    "sg:orig_category":"Florister\u00cdas",
    "sg:phone":"+34 937 58 64 73",
    "sg:postcode":"08302",
    "sg:province":"Barcelona",
    "wof:name":"Vellvehi Altimira Josep Maria",
    "wof:placetype":"venue"
},
  "geometry": {"coordinates":[2.4355568886,41.5352630615],"type":"Point"}
}