{
  "type": "Feature",
  "properties": {
    "iso:country":"ES",
    "sg:address":"Calle de Ruiz De Alda, 8",
    "sg:city":"Navahermosa",
    "sg:orig_category":"Chapister\u00cda",
    "sg:phone":"+34 925 41 02 88",
    "sg:postcode":"45150",
    "sg:province":"Toledo",
    "wof:name":"Menor Lopez Vicente",
    "wof:placetype":"venue"
},
  "geometry": {"coordinates":[-4.4650621414,39.6318435669],"type":"Point"}
}