{
  "type": "Feature",
  "properties": {
    "iso:country":"ES",
    "sg:address":"Carrer de Murcia, 33",
    "sg:city":"Rubi",
    "sg:orig_category":"Empresas De Carpinter\u00cda Met\u00c1lica",
    "sg:phone":"+34 935 88 74 09",
    "sg:postcode":"08191",
    "sg:province":"Barcelona",
    "wof:name":"Alu-jecar S.l.",
    "wof:placetype":"venue"
},
  "geometry": {"coordinates":[2.0367972851,41.4982337952],"type":"Point"}
}