{
  "type": "Feature",
  "properties": {
    "iso:country":"ES",
    "sg:address":"Plaz Paris (de), 3",
    "sg:city":"Leganes",
    "sg:orig_category":"Centros De Coordinaci\u00d3n",
    "sg:phone":"+34 916 94 43 14",
    "sg:postcode":"28911",
    "sg:province":"Madrid",
    "wof:name":"Comunidad De Propietarios Plaza De Paris N? 3.",
    "wof:placetype":"venue"
},
  "geometry": {"coordinates":[-3.7654960155,40.3288803101],"type":"Point"}
}