{
  "type": "Feature",
  "properties": {
    "addr:full":"Cr. Palencia-ria\u00f1o, S/n Villalba De Guardo Palencia 34889",
    "addr:housenumber":"/ n",
    "addr:postcode":"34889",
    "addr:street":"Palencia-Rian\u0303O S",
    "iso:country":"ES",
    "sg:address":"Cr. Palencia-ria\u00f1o, S/n",
    "sg:city":"Villalba De Guardo",
    "sg:orig_category":"Semiller\u00cdas",
    "sg:phone":"+34 979 86 21 06",
    "sg:postcode":"34889",
    "sg:province":"Palencia",
    "wof:name":"Espadas Serrano Susana",
    "wof:placetype":"venue"
},
  "geometry": {"coordinates":[-4.823348999,42.7230110168],"type":"Point"}
}