{
  "type": "Feature",
  "properties": {
    "addr:full":"Ctra Granada (de), Km. 0315,0 Castro Rio C\u00f3rdoba 14840",
    "addr:postcode":"14840",
    "addr:street":"Ctra Granada De Km. 0315,0 Castro Rio Co\u0301Rdoba",
    "iso:country":"ES",
    "sg:address":"Ctra Granada (de), Km. 0315,0",
    "sg:city":"Castro Rio",
    "sg:orig_category":"Aceites Y Grasas Alimentarias (fabricaci\u00d3n, Al Por Mayor)",
    "sg:phone":"+34 957 37 08 93",
    "sg:postcode":"14840",
    "sg:province":"C\u00f3rdoba",
    "wof:name":"Aceites La Mata S.a.",
    "wof:placetype":"venue"
},
  "geometry": {"coordinates":[-4.6010651588,37.7613143921],"type":"Point"}
}