{
  "type": "Feature",
  "properties": {
    "addr:full":"La Glorieta (p I Pesquero Norte), S/n Huelva Huelva 21002",
    "addr:housenumber":"s / n",
    "addr:postcode":"21002",
    "addr:street":"P I Pesquero Norte",
    "iso:country":"ES",
    "sg:address":"La Glorieta (p I Pesquero Norte), S/n",
    "sg:city":"Huelva",
    "sg:classifiers":[
        {
            "category":"Recreation",
            "type":"Entertainment"
        }
    ],
    "sg:phone":"+34 959 28 07 50",
    "sg:postcode":"21002",
    "sg:province":"Huelva",
    "sg:tags":[
        "caza",
        "pr\u00c1ctica",
        "la",
        "de",
        "pesca",
        "y"
    ],
    "wof:name":"Gabrielitos S. A.",
    "wof:placetype":"venue"
},
  "geometry": {"coordinates":[-6.9603133202,37.2688446045],"type":"Point"}
}