{
  "type": "Feature",
  "properties": {
    "iso:country":"ES",
    "sg:address":"Calle de Sierra Del Brezo, 38",
    "sg:city":"Madrid",
    "sg:orig_category":"Empresas De Limpieza",
    "sg:phone":"+34 913 32 53 93",
    "sg:postcode":"28031",
    "sg:province":"Madrid",
    "wof:name":"Prestaciones Y Servicios Montesinos S.l.",
    "wof:placetype":"venue"
},
  "geometry": {"coordinates":[-3.6206851006,40.3720436096],"type":"Point"}
}