{
  "type": "Feature",
  "properties": {
    "iso:country":"ES",
    "sg:address":"Pl. Del Pilar, S/n",
    "sg:city":"Bujaraloz",
    "sg:orig_category":"Art\u00cdculos De Regalo (al Por Menor)",
    "sg:phone":"+34 976 17 32 08",
    "sg:postcode":"50177",
    "sg:province":"Zaragoza",
    "wof:name":"Uson Uson Rosa",
    "wof:placetype":"venue"
},
  "geometry": {"coordinates":[-0.1525900066,41.4985580444],"type":"Point"}
}