{
  "type": "Feature",
  "properties": {
    "addr:full":"Calle de Recondo, 9 Valladolid Valladolid 47007",
    "addr:housenumber":"9",
    "addr:postcode":"47007",
    "addr:street":"Calle De Recondo",
    "iso:country":"ES",
    "sg:address":"Calle de Recondo, 9",
    "sg:city":"Valladolid",
    "sg:orig_category":"Procuradores",
    "sg:phone":"+34 983 23 40 94",
    "sg:postcode":"47007",
    "sg:province":"Valladolid",
    "wof:name":"Mu\u00f1oz Santos Jose Luis",
    "wof:placetype":"venue"
},
  "geometry": {"coordinates":[-4.7295928001,41.6414031982],"type":"Point"}
}