{
  "type": "Feature",
  "properties": {
    "addr:full":"Ctra Alcoi (d'), 1 Albaida Valencia 46860",
    "addr:housenumber":"1",
    "addr:postcode":"46860",
    "addr:street":"Ctra Alcoi D '",
    "iso:country":"ES",
    "sg:address":"Ctra Alcoi (d'), 1",
    "sg:city":"Albaida",
    "sg:orig_category":"Fabricaci\u00d3n De Cortinas Y Visillos",
    "sg:phone":"+34 962 39 80 42",
    "sg:postcode":"46860",
    "sg:province":"Valencia",
    "wof:name":"Vicente Sempere S.a.",
    "wof:placetype":"venue"
},
  "geometry": {"coordinates":[-0.5185109973,38.8367805481],"type":"Point"}
}