{
  "type": "Feature",
  "properties": {
    "iso:country":"ES",
    "sg:address":"Avda Sabino Arana P E Ibarrabarri, 18",
    "sg:city":"Elexalde",
    "sg:orig_category":"Montaje (empresas De)",
    "sg:phone":"+34 944 53 20 66",
    "sg:postcode":"48940",
    "sg:province":"Vizcaya",
    "sg:website":"www.prainsa.es",
    "wof:name":"Montajes Plomada S.l.",
    "wof:placetype":"venue"
},
  "geometry": {"coordinates":[-2.9860789776,43.3275489807],"type":"Point"}
}