{
  "type": "Feature",
  "properties": {
    "addr:full":"Calle de Alarcon, S/n Barrio De Los Arocas Murcia 30006",
    "addr:housenumber":"s / n",
    "addr:postcode":"30006",
    "addr:street":"Calle De Alarcon",
    "iso:country":"ES",
    "sg:address":"Calle de Alarcon, S/n",
    "sg:city":"Barrio De Los Arocas",
    "sg:orig_category":"Pescader\u00cdas (al Por Menor)",
    "sg:phone":"+34 968 30 01 77",
    "sg:postcode":"30006",
    "sg:province":"Murcia",
    "wof:name":"Manzanares Madrid Jose",
    "wof:placetype":"venue"
},
  "geometry": {"coordinates":[-1.0940823555,37.9973640442],"type":"Point"}
}