{
  "type": "Feature",
  "properties": {
    "addr:full":"Ctra Ollarretxe, 9 Getxo Vizcaya 48990",
    "addr:housenumber":"9",
    "addr:postcode":"48990",
    "addr:street":"Ctra Ollarretxe",
    "iso:country":"ES",
    "sg:address":"Ctra Ollarretxe, 9",
    "sg:city":"Getxo",
    "sg:orig_category":"Ense\u00d1anza Variada",
    "sg:phone":"+34 944 30 77 08",
    "sg:postcode":"48990",
    "sg:province":"Vizcaya",
    "wof:name":"Centro De Estudios Ernesto",
    "wof:placetype":"venue"
},
  "geometry": {"coordinates":[-3.0057640076,43.354259491],"type":"Point"}
}