{
  "type": "Feature",
  "properties": {
    "addr:full":"Avda Madrid, 34 Benidorm Alicante 03500",
    "addr:housenumber":"34",
    "addr:postcode":"03500",
    "addr:street":"Avda Madrid",
    "iso:country":"ES",
    "sg:address":"Avda Madrid, 34",
    "sg:city":"Benidorm",
    "sg:orig_category":"Caf\u00c9s, Bares, Cervecer\u00cdas",
    "sg:phone":"+34 965 85 43 73",
    "sg:postcode":"03500",
    "sg:province":"Alicante",
    "wof:name":"Veracruz Beach S.l.",
    "wof:placetype":"venue"
},
  "geometry": {"coordinates":[-0.1076269969,38.5328407288],"type":"Point"}
}