{
  "type": "Feature",
  "properties": {
    "addr:full":"Calle de Los Frailes, 13 Frailes Madrid 28814",
    "addr:housenumber":"13",
    "addr:postcode":"28814",
    "addr:street":"Calle De Los Frailes",
    "iso:country":"ES",
    "sg:address":"Calle de Los Frailes, 13",
    "sg:city":"Frailes",
    "sg:orig_category":"M\u00c1quinas Para Recortar Y Pegar",
    "sg:phone":"+34 918 84 50 70",
    "sg:postcode":"28814",
    "sg:province":"Madrid",
    "wof:name":"Troquelados Graficos De La Fuente S.l.",
    "wof:placetype":"venue"
},
  "geometry": {"coordinates":[-3.4572339058,40.5436286926],"type":"Point"}
}