{
  "type": "Feature",
  "properties": {
    "addr:full":"Calle de Inglaterra, 5 Pozuelo De Alarcon Madrid 28224",
    "addr:housenumber":"5",
    "addr:postcode":"28224",
    "addr:street":"Calle De Inglaterra",
    "iso:country":"ES",
    "sg:address":"Calle de Inglaterra, 5",
    "sg:city":"Pozuelo De Alarcon",
    "sg:orig_category":"Plomeros",
    "sg:phone":"+34 913 51 11 22",
    "sg:postcode":"28224",
    "sg:province":"Madrid",
    "wof:name":"Castellana Building S.l.",
    "wof:placetype":"venue"
},
  "geometry": {"coordinates":[-3.7894999981,40.4424209595],"type":"Point"}
}