{
  "type": "Feature",
  "properties": {
    "iso:country":"ES",
    "sg:address":"Carrer de Consell De Cent, 410",
    "sg:city":"Barcelona",
    "sg:orig_category":"Construcci\u00d3n Mec\u00c1nica",
    "sg:phone":"+34 932 31 48 57",
    "sg:postcode":"08009",
    "sg:province":"Barcelona",
    "wof:name":"Sala Pares Juan",
    "wof:placetype":"venue"
},
  "geometry": {"coordinates":[2.1736040115,41.3968391418],"type":"Point"}
}