{
  "type": "Feature",
  "properties": {
    "addr:full":"Calle de Carboneros, 23 Tomelloso Ciudad Real 13700",
    "addr:housenumber":"23",
    "addr:postcode":"13700",
    "addr:street":"Calle De Carboneros",
    "iso:country":"ES",
    "sg:address":"Calle de Carboneros, 23",
    "sg:city":"Tomelloso",
    "sg:orig_category":"Mercer\u00cda, Lencer\u00cda (al Por Menor)",
    "sg:phone":"+34 926 51 46 91",
    "sg:postcode":"13700",
    "sg:province":"Ciudad Real",
    "wof:name":"Gonzalez Nieves Pilar",
    "wof:placetype":"venue"
},
  "geometry": {"coordinates":[-3.0159242153,39.1569442749],"type":"Point"}
}