{
  "type": "Feature",
  "properties": {
    "iso:country":"ES",
    "sg:address":"Carrer de Pau Casals, 54",
    "sg:city":"Ametlla Mar",
    "sg:orig_category":"Farmacias",
    "sg:phone":"+34 977 49 32 52",
    "sg:postcode":"43860",
    "sg:province":"Tarragona",
    "wof:name":"Borges Ayats Joan",
    "wof:placetype":"venue"
},
  "geometry": {"coordinates":[0.8039039969,40.8837890625],"type":"Point"}
}