{
  "type": "Feature",
  "properties": {
    "addr:full":"Pl Santa Pagesa, 4 Palma Islas Baleares 07003",
    "addr:housenumber":"4",
    "addr:postcode":"07003",
    "addr:street":"Pl Santa Pagesa",
    "iso:country":"ES",
    "sg:address":"Pl Santa Pagesa, 4",
    "sg:city":"Palma",
    "sg:orig_category":"Fabricaci\u00d3n De Juguetes Autom\u00c1ticos",
    "sg:phone":"+34 971 20 83 36",
    "sg:postcode":"07003",
    "sg:province":"Islas Baleares",
    "wof:name":"Opergrup S.l.",
    "wof:placetype":"venue"
},
  "geometry": {"coordinates":[2.6489849091,39.5822563171],"type":"Point"}
}