{
  "type": "Feature",
  "properties": {
    "iso:country":"ES",
    "sg:address":"Bard Pomar, 5",
    "sg:city":"Jerez De Los Caballeros",
    "sg:orig_category":"Farmacias",
    "sg:phone":"+34 924 73 14 74",
    "sg:postcode":"06380",
    "sg:province":"Badajoz",
    "wof:name":"Farmacia Mazuecos C.b.",
    "wof:placetype":"venue"
},
  "geometry": {"coordinates":[-6.7639608383,38.3214683533],"type":"Point"}
}