{
  "type": "Feature",
  "properties": {
    "iso:country":"ES",
    "sg:address":"Calle de Rigoletto, 12",
    "sg:city":"Malaga",
    "sg:orig_category":"Explosivos",
    "sg:phone":"+34 952 36 06 57",
    "sg:postcode":"29006",
    "sg:province":"M\u00e1laga",
    "wof:name":"Distribuidora Malague\u00f1a De Explosivos S.l.",
    "wof:placetype":"venue"
},
  "geometry": {"coordinates":[-4.4695429802,36.707611084],"type":"Point"}
}