{
  "type": "Feature",
  "properties": {
    "addr:full":"Colon, 5 Lora Rio Sevilla 41440",
    "addr:housenumber":"5",
    "addr:postcode":"41440",
    "addr:street":"Colon;Rio Sevilla",
    "iso:country":"ES",
    "sg:address":"Colon, 5",
    "sg:city":"Lora Rio",
    "sg:orig_category":"Agencias De Viajes",
    "sg:phone":"+34 955 80 21 00",
    "sg:postcode":"41440",
    "sg:province":"Sevilla",
    "wof:name":"Medrano Martinez Maria Jose",
    "wof:placetype":"venue"
},
  "geometry": {"coordinates":[-5.5313911438,37.656085968],"type":"Point"}
}