{
  "type": "Feature",
  "properties": {
    "iso:country":"ES",
    "sg:address":"Tajonar, 21",
    "sg:city":"Iru\u00f1a",
    "sg:orig_category":"Prot\u00c9sicos Dentales",
    "sg:phone":"+34 948 23 54 01",
    "sg:postcode":"31006",
    "sg:province":"Navarra",
    "wof:name":"Sequeros Sazatornil Jesus",
    "wof:placetype":"venue"
},
  "geometry": {"coordinates":[-1.6348639727,42.8054656982],"type":"Point"}
}