{
  "type": "Feature",
  "properties": {
    "iso:country":"ES",
    "sg:address":"Ctra. Figueres Roses, Km. 0029,0",
    "sg:city":"Vilatenim",
    "sg:orig_category":"Bisuter\u00cda, Joyer\u00cda, Relojer\u00cda (al Por Menor)",
    "sg:phone":"+34 972 67 23 38",
    "sg:postcode":"17484",
    "sg:province":"Girona",
    "wof:name":"Lagrifa Custey Teresa",
    "wof:placetype":"venue"
},
  "geometry": {"coordinates":[2.9948849678,42.2688064575],"type":"Point"}
}