{
  "type": "Feature",
  "properties": {
    "iso:country":"ES",
    "sg:address":"Trav De Gracia, 235",
    "sg:city":"Barcelona",
    "sg:orig_category":"Fabricaci\u00d3n, Venta De Productos Base Farmac\u00c9uticos",
    "sg:phone":"+34 932 13 78 33",
    "sg:postcode":"08012",
    "sg:province":"Barcelona",
    "wof:name":"Garcia-vela Grau Teresa",
    "wof:placetype":"venue"
},
  "geometry": {"coordinates":[2.1508028507,41.4053153992],"type":"Point"}
}