{
  "type": "Feature",
  "properties": {
    "addr:full":"Lancara, 5 Lancara Lugo 27367",
    "addr:housenumber":"5",
    "addr:postcode":"27367",
    "addr:street":"Lancara",
    "iso:country":"ES",
    "sg:address":"Lancara, 5",
    "sg:city":"Lancara",
    "sg:orig_category":"Ebanister\u00cda",
    "sg:phone":"+34 982 16 71 25",
    "sg:postcode":"27367",
    "sg:province":"Lugo",
    "wof:name":"Lopez Cela Jose",
    "wof:placetype":"venue"
},
  "geometry": {"coordinates":[-7.3430991173,42.9003257751],"type":"Point"}
}