{
  "type": "Feature",
  "properties": {
    "addr:full":"Ctra. D'inca, Km. 0008,0 Muro Islas Baleares 07440",
    "addr:postcode":"07440",
    "addr:street":"Ctra. D'Inca Km. 0008,0",
    "iso:country":"ES",
    "sg:address":"Ctra. D'inca, Km. 0008,0",
    "sg:city":"Muro",
    "sg:orig_category":"Empresarios",
    "sg:phone":"+34 971 53 73 88",
    "sg:postcode":"07440",
    "sg:province":"Islas Baleares",
    "wof:name":"Mir Pol Migel",
    "wof:placetype":"venue"
},
  "geometry": {"coordinates":[3.0191690922,39.7705116272],"type":"Point"}
}