{
  "type": "Feature",
  "properties": {
    "iso:country":"ES",
    "sg:address":"Calle de Maudes, 50",
    "sg:city":"Madrid",
    "sg:orig_category":"Empresarios",
    "sg:phone":"+34 915 36 16 58",
    "sg:postcode":"28003",
    "sg:province":"Madrid",
    "wof:name":"Portosilva S L",
    "wof:placetype":"venue"
},
  "geometry": {"coordinates":[-3.6976809502,40.4449882507],"type":"Point"}
}