{
  "type": "Feature",
  "properties": {
    "iso:country":"ES",
    "sg:address":"Primavera, 1",
    "sg:city":"Arucas",
    "sg:orig_category":"Barnizadores",
    "sg:phone":"+34 928 62 31 65",
    "sg:postcode":"35400",
    "sg:province":"Las Palmas",
    "wof:name":"Gonzalez Santana Maria Del Pino",
    "wof:placetype":"venue"
},
  "geometry": {"coordinates":[-15.5064249039,28.1357631683],"type":"Point"}
}