{
  "type": "Feature",
  "properties": {
    "addr:full":"Plaz Mayor, 9 Lalueza Huesca 22214",
    "addr:housenumber":"9",
    "addr:postcode":"22214",
    "addr:street":"Plaz Mayor",
    "iso:country":"ES",
    "sg:address":"Plaz Mayor, 9",
    "sg:city":"Lalueza",
    "sg:orig_category":"Asociaciones, Instituciones De Consumidores Y Usuarios",
    "sg:phone":"+34 974 57 52 73",
    "sg:postcode":"22214",
    "sg:province":"Huesca",
    "wof:name":"Asociacion Amas De Casa La Malena",
    "wof:placetype":"venue"
},
  "geometry": {"coordinates":[-0.2560000122,41.8408508301],"type":"Point"}
}