{
  "type": "Feature",
  "properties": {
    "iso:country":"ES",
    "sg:address":"Concejo De Egues, 10",
    "sg:city":"Iru\u00f1a",
    "sg:orig_category":"Farmacias",
    "sg:phone":"+34 948 16 36 00",
    "sg:postcode":"31016",
    "sg:province":"Navarra",
    "wof:name":"Recarte Perez De Ciriza Olimpia",
    "wof:placetype":"venue"
},
  "geometry": {"coordinates":[-1.6123969555,42.8118438721],"type":"Point"}
}