{
  "type": "Feature",
  "properties": {
    "iso:country":"ES",
    "sg:address":"Prado Llano, S/n",
    "sg:city":"Sierra Nevada",
    "sg:orig_category":"Reparaciones Y Remolcado De Veh\u00cdculos",
    "sg:phone":"+34 958 48 03 29",
    "sg:postcode":"18196",
    "sg:province":"Granada",
    "wof:name":"Quesada Lopez Manuel",
    "wof:placetype":"venue"
},
  "geometry": {"coordinates":[-3.0351140499,37.0072669983],"type":"Point"}
}