{
  "type": "Feature",
  "properties": {
    "addr:full":"Pase Castelar, 59 Villanueva Serena Badajoz 06700",
    "addr:housenumber":"59",
    "addr:postcode":"06700",
    "addr:street":"Castelar",
    "iso:country":"ES",
    "sg:address":"Pase Castelar, 59",
    "sg:city":"Villanueva Serena",
    "sg:orig_category":"Psic\u00d3logos",
    "sg:phone":"+34 924 84 31 66",
    "sg:postcode":"06700",
    "sg:province":"Badajoz",
    "wof:name":"Ruiz Izquierdo Maria Teresa",
    "wof:placetype":"venue"
},
  "geometry": {"coordinates":[-5.7927408218,38.9731750488],"type":"Point"}
}