{
  "type": "Feature",
  "properties": {
    "iso:country":"ES",
    "sg:address":"Pl. Prado, S/n",
    "sg:city":"Cortegana",
    "sg:orig_category":"Quincaller\u00cda (al Por Menor)",
    "sg:phone":"+34 959 13 13 12",
    "sg:postcode":"21230",
    "sg:province":"Huelva",
    "wof:name":"Almacenes San Blas S.a.",
    "wof:placetype":"venue"
},
  "geometry": {"coordinates":[-6.9418907166,37.7330055237],"type":"Point"}
}