{
  "type": "Feature",
  "properties": {
    "iso:country":"ES",
    "sg:address":"Ctra. P. Rio, Km. 0005,5",
    "sg:city":"El Higueron",
    "sg:orig_category":"Puertas Y Portales",
    "sg:phone":"+34 957 32 99 08",
    "sg:postcode":"14193",
    "sg:province":"C\u00f3rdoba",
    "sg:website":"almagroysiena.com",
    "wof:name":"Almagra Y Siena S.l.",
    "wof:placetype":"venue"
},
  "geometry": {"coordinates":[-4.7713050842,37.8700065613],"type":"Point"}
}