{
  "type": "Feature",
  "properties": {
    "iso:country":"ES",
    "sg:address":"Sagastialde Auzoa, 16",
    "sg:city":"Hernani",
    "sg:orig_category":"Asociaciones, Organismos Culturales Y Socioeducativos",
    "sg:phone":"+34 943 55 63 46",
    "sg:postcode":"20120",
    "sg:province":"Guip\u00f9zcoa",
    "wof:name":"Hernaniko Ahotsa Elkartea",
    "wof:placetype":"venue"
},
  "geometry": {"coordinates":[-1.9693520069,43.2718772888],"type":"Point"}
}