{
  "type": "Feature",
  "properties": {
    "addr:full":"Calle de Valle De La Fuenfria, 6 Madrid Madrid 28034",
    "addr:housenumber":"6",
    "addr:postcode":"28034",
    "addr:street":"Calle De Valle De La Fuenfria",
    "iso:country":"ES",
    "sg:address":"Calle de Valle De La Fuenfria, 6",
    "sg:city":"Madrid",
    "sg:orig_category":"Abogados",
    "sg:phone":"+34 913 72 16 99",
    "sg:postcode":"28034",
    "sg:province":"Madrid",
    "wof:name":"Fernandez-daza Alvear Jose Maria",
    "wof:placetype":"venue"
},
  "geometry": {"coordinates":[-3.7056419849,40.4991607666],"type":"Point"}
}