{
  "type": "Feature",
  "properties": {
    "addr:full":"Calle de Massamagrell, 30 Rafelbunyol Valencia 46138",
    "addr:housenumber":"30",
    "addr:postcode":"46138",
    "addr:street":"Calle De Massamagrell",
    "iso:country":"ES",
    "sg:address":"Calle de Massamagrell, 30",
    "sg:city":"Rafelbunyol",
    "sg:orig_category":"Ferreter\u00cda (diversos)",
    "sg:phone":"+34 961 41 09 36",
    "sg:postcode":"46138",
    "sg:province":"Valencia",
    "wof:name":"Recinclaje 99 S.l.",
    "wof:placetype":"venue"
},
  "geometry": {"coordinates":[-0.3252640069,39.58826828],"type":"Point"}
}