{
  "type": "Feature",
  "properties": {
    "addr:full":"Calle de Nomenclatura, 2 Fuentes De A\u00e7o \u00c1vila 05214",
    "addr:housenumber":"2",
    "addr:postcode":"05214",
    "addr:street":"Calle De Nomenclatura",
    "iso:country":"ES",
    "sg:address":"Calle de Nomenclatura, 2",
    "sg:city":"Fuentes De A\u00e7o",
    "sg:orig_category":"Sanatorios M\u00c9dico",
    "sg:phone":"+34 920 31 01 90",
    "sg:postcode":"05214",
    "sg:province":"\u00c1vila",
    "wof:name":"Ayuntamiento De Fuentes De A\u00f1o",
    "wof:placetype":"venue"
},
  "geometry": {"coordinates":[-4.700322628,40.6564216614],"type":"Point"}
}