{
  "type": "Feature",
  "properties": {
    "addr:full":"Calle de Fraga, 14 Zaragoza Zaragoza 50003",
    "addr:housenumber":"14",
    "addr:postcode":"50003",
    "addr:street":"Calle De Fraga",
    "iso:country":"ES",
    "sg:address":"Calle de Fraga, 14",
    "sg:city":"Zaragoza",
    "sg:orig_category":"Papeler\u00cdas, Librer\u00cdas",
    "sg:phone":"+34 976 28 50 50",
    "sg:postcode":"50003",
    "sg:province":"Zaragoza",
    "wof:name":"Cortes Martinez Miguel",
    "wof:placetype":"venue"
},
  "geometry": {"coordinates":[-0.9002910256,41.6594772339],"type":"Point"}
}