{
  "type": "Feature",
  "properties": {
    "addr:full":"Avda La Libertad, 19 San Vicente De Barakaldo Vizcaya 48901",
    "addr:housenumber":"19",
    "addr:postcode":"48901",
    "addr:street":"Avda La Libertad",
    "iso:country":"ES",
    "sg:address":"Avda La Libertad, 19",
    "sg:city":"San Vicente De Barakaldo",
    "sg:orig_category":"Abogados",
    "sg:phone":"+34 944 38 81 34",
    "sg:postcode":"48901",
    "sg:province":"Vizcaya",
    "wof:name":"Ramos Garcia Cristina",
    "wof:placetype":"venue"
},
  "geometry": {"coordinates":[-2.9908530712,43.296787262],"type":"Point"}
}