{
  "type": "Feature",
  "properties": {
    "addr:full":"Rua Porvenir, 7 Portonovo Pontevedra 36970",
    "addr:housenumber":"7",
    "addr:postcode":"36970",
    "addr:street":"Rua Porvenir",
    "iso:country":"ES",
    "sg:address":"Rua Porvenir, 7",
    "sg:city":"Portonovo",
    "sg:orig_category":"Promotores Constructores",
    "sg:phone":"+34 986 72 43 04",
    "sg:postcode":"36970",
    "sg:province":"Pontevedra",
    "wof:name":"Lima Outeda Humberto",
    "wof:placetype":"venue"
},
  "geometry": {"coordinates":[-8.8286962509,42.3900756836],"type":"Point"}
}