{
  "type": "Feature",
  "properties": {
    "iso:country":"ES",
    "sg:address":"Calle de Metal, 4",
    "sg:city":"Villaluenga Sagra",
    "sg:orig_category":"Montaje (empresas De)",
    "sg:phone":"+34 925 35 55 14",
    "sg:postcode":"45520",
    "sg:province":"Toledo",
    "wof:name":"Galto Montajes S.l.",
    "wof:placetype":"venue"
},
  "geometry": {"coordinates":[-3.9098680019,40.0303573608],"type":"Point"}
}