{
  "type": "Feature",
  "properties": {
    "addr:full":"Aingeru Kalea, 34 Bis Azkoitia Guip\u00f9zcoa 20720",
    "addr:housenumber":"34 bis",
    "addr:postcode":"20720",
    "addr:street":"Aingeru Kalea;Guipu\u0300Zcoa",
    "iso:country":"ES",
    "sg:address":"Aingeru Kalea, 34 Bis",
    "sg:city":"Azkoitia",
    "sg:orig_category":"Bricolaje, Herramientas (al Por Menor)",
    "sg:phone":"+34 943 02 69 05",
    "sg:postcode":"20720",
    "sg:province":"Guip\u00f9zcoa",
    "wof:name":"Landuz Eskulanak, C.b.",
    "wof:placetype":"venue"
},
  "geometry": {"coordinates":[-2.3134639263,43.1762886047],"type":"Point"}
}