{
  "type": "Feature",
  "properties": {
    "iso:country":"ES",
    "sg:address":"Calle de Plans Les Forques, S/n",
    "sg:city":"Vallada",
    "sg:orig_category":"Fabricaci\u00d3n, Comercio De Muebles En Ca\u00d1a, Mimbre",
    "sg:phone":"+34 962 25 71 69",
    "sg:postcode":"46691",
    "sg:province":"Valencia",
    "wof:name":"Castells C.b.",
    "wof:placetype":"venue"
},
  "geometry": {"coordinates":[-0.6874809861,38.9006080627],"type":"Point"}
}