{
  "type": "Feature",
  "properties": {
    "addr:full":"Calle de Molino De Viento, 8 Madrid Madrid 28004",
    "addr:housenumber":"8",
    "addr:postcode":"madrid;28004",
    "addr:street":"Calle De Molino De Viento",
    "iso:country":"ES",
    "sg:address":"Calle de Molino De Viento, 8",
    "sg:city":"Madrid",
    "sg:orig_category":"Comidas Por Encargo, Organizaci\u00d3n De Recepciones",
    "sg:phone":"+34 915 21 24 43",
    "sg:postcode":"28004",
    "sg:province":"Madrid",
    "wof:name":"Encinas Ayuso Alberto",
    "wof:placetype":"venue"
},
  "geometry": {"coordinates":[-3.7033491135,40.423412323],"type":"Point"}
}