{
  "type": "Feature",
  "properties": {
    "iso:country":"ES",
    "sg:address":"Rua Cura Pereiro, 49",
    "sg:city":"Carral",
    "sg:orig_category":"Agentes, Concesionarios Y Sucursales De Veh\u00cdculos",
    "sg:phone":"+34 981 67 04 99",
    "sg:postcode":"15175",
    "sg:province":"A Coru\u00f1a",
    "wof:name":"Trigo Miranda Luis",
    "wof:placetype":"venue"
},
  "geometry": {"coordinates":[-8.3558893204,43.2278442383],"type":"Point"}
}