{
  "type": "Feature",
  "properties": {
    "iso:country":"ES",
    "sg:address":"Calle de Reyes Leoneses, 13",
    "sg:city":"Le\u00f3n",
    "sg:orig_category":"Fabricaci\u00d3n De Muebles",
    "sg:phone":"+34 987 80 46 93",
    "sg:postcode":"24008",
    "sg:province":"Le\u00f3n",
    "wof:name":"Ca\u00f1on Bautista Antonio",
    "wof:placetype":"venue"
},
  "geometry": {"coordinates":[-5.5854611397,42.6090736389],"type":"Point"}
}