{
  "type": "Feature",
  "properties": {
    "addr:full":"Avda Doctor Fleming, 4 Yuncos Toledo 45210",
    "addr:housenumber":"4",
    "addr:postcode":"45210",
    "addr:street":"Avda Doctor Fleming",
    "iso:country":"ES",
    "sg:address":"Avda Doctor Fleming, 4",
    "sg:city":"Yuncos",
    "sg:orig_category":"Abogados",
    "sg:phone":"+34 925 55 38 16",
    "sg:postcode":"45210",
    "sg:province":"Toledo",
    "wof:name":"Servicios Juridicos Profesionales",
    "wof:placetype":"venue"
},
  "geometry": {"coordinates":[-3.8733589649,40.088180542],"type":"Point"}
}