{
  "type": "Feature",
  "properties": {
    "addr:full":"Plaz Mayor, 10 Madrid Madrid 28012",
    "addr:housenumber":"10",
    "addr:postcode":"madrid;28012",
    "addr:street":"Plaz Mayor",
    "iso:country":"ES",
    "sg:address":"Plaz Mayor, 10",
    "sg:city":"Madrid",
    "sg:orig_category":"Heladeros",
    "sg:phone":"+34 913 65 20 39",
    "sg:postcode":"28012",
    "sg:province":"Madrid",
    "wof:name":"Sonblaglas S.l.",
    "wof:placetype":"venue"
},
  "geometry": {"coordinates":[-3.7067389488,40.4157295227],"type":"Point"}
}