{
  "type": "Feature",
  "properties": {
    "addr:full":"Carrer de Francesc Macia, S/n Vilafranca Penedes Barcelona 08720",
    "addr:housenumber":"s / n",
    "addr:postcode":"08720",
    "addr:street":"Carrer De Francesc Macia;Penedes Barcelona",
    "iso:country":"ES",
    "sg:address":"Carrer de Francesc Macia, S/n",
    "sg:city":"Vilafranca Penedes",
    "sg:orig_category":"Pescader\u00cdas (al Por Menor)",
    "sg:phone":"+34 938 90 45 99",
    "sg:postcode":"08720",
    "sg:province":"Barcelona",
    "wof:name":"Gonzalez Macias Placida",
    "wof:placetype":"venue"
},
  "geometry": {"coordinates":[1.6925289631,41.3424186707],"type":"Point"}
}