{
  "type": "Feature",
  "properties": {
    "addr:full":"Carrer de Alfons Gubern, 5 Castellar Valles Barcelona 08211",
    "addr:housenumber":"5",
    "addr:postcode":"08211",
    "addr:street":"Carrer De Alfons Gubern",
    "iso:country":"ES",
    "sg:address":"Carrer de Alfons Gubern, 5",
    "sg:city":"Castellar Valles",
    "sg:orig_category":"Automatizaci\u00d3n De Procesos Industriales Y De Edificaci\u00d3n (estudios, Instalaci\u00d3n)",
    "sg:phone":"+34 937 14 33 34",
    "sg:postcode":"08211",
    "sg:province":"Barcelona",
    "wof:name":"Maquinaria Para El Polestireno S.l.",
    "wof:placetype":"venue"
},
  "geometry": {"coordinates":[2.0832099915,41.6093215942],"type":"Point"}
}