{
  "type": "Feature",
  "properties": {
    "addr:full":"Calle de General Bravo, 61 Carrizal Las Palmas 35240",
    "addr:housenumber":"61",
    "addr:postcode":"35240",
    "addr:street":"Calle De General Bravo",
    "iso:country":"ES",
    "sg:address":"Calle de General Bravo, 61",
    "sg:city":"Carrizal",
    "sg:orig_category":"Empresas De Carpinter\u00cda De Madera",
    "sg:phone":"+34 928 78 28 74",
    "sg:postcode":"35240",
    "sg:province":"Las Palmas",
    "wof:name":"Pe\u00f1a Lopez Jorge Luis",
    "wof:placetype":"venue"
},
  "geometry": {"coordinates":[-15.4098405838,27.9132289886],"type":"Point"}
}