{
  "type": "Feature",
  "properties": {
    "addr:full":"Plaz Primero De Mayo, 2 Melilla Melilla 52003",
    "addr:housenumber":"2",
    "addr:postcode":"52003",
    "addr:street":"Plaz Primero;Mayo",
    "iso:country":"ES",
    "sg:address":"Plaz Primero De Mayo, 2",
    "sg:city":"Melilla",
    "sg:orig_category":"Agentes, Concesionarios Y Sucursales De Veh\u00cdculos",
    "sg:phone":"+34 952 69 00 40",
    "sg:postcode":"52003",
    "sg:province":"Melilla",
    "wof:name":"Autofacil S.l.",
    "wof:placetype":"venue"
},
  "geometry": {"coordinates":[-2.955919981,35.3033714294],"type":"Point"}
}