{
  "type": "Feature",
  "properties": {
    "iso:country":"ES",
    "sg:address":"Carr Victoria, 2",
    "sg:city":"Cervera",
    "sg:orig_category":"Estancos",
    "sg:phone":"+34 973 53 21 90",
    "sg:postcode":"25200",
    "sg:province":"Lleida",
    "wof:name":"Gasol Trullols Jose",
    "wof:placetype":"venue"
},
  "geometry": {"coordinates":[1.2722489834,41.6716041565],"type":"Point"}
}