{
  "type": "Feature",
  "properties": {
    "iso:country":"ES",
    "sg:address":"Calle de Mayor, 9",
    "sg:city":"Mejorada Campo",
    "sg:orig_category":"Cl\u00cdnicas M\u00c9dicas",
    "sg:phone":"+34 916 79 29 94",
    "sg:postcode":"28840",
    "sg:province":"Madrid",
    "wof:name":"Carreira Leston Rosalia",
    "wof:placetype":"venue"
},
  "geometry": {"coordinates":[-3.4867289066,40.3972206116],"type":"Point"}
}