{
  "type": "Feature",
  "properties": {
    "addr:full":"Calle de Cueto Bajo, 15 Llanes Asturias 33500",
    "addr:postcode":"15;33500",
    "addr:street":"Calle De Cueto",
    "iso:country":"ES",
    "sg:address":"Calle de Cueto Bajo, 15",
    "sg:city":"Llanes",
    "sg:orig_category":"Supermercados Y Hipermercados",
    "sg:phone":"+34 985 40 36 10",
    "sg:postcode":"33500",
    "sg:province":"Asturias",
    "wof:name":"Alimerka S.a.",
    "wof:placetype":"venue"
},
  "geometry": {"coordinates":[-4.7540068626,43.4184684753],"type":"Point"}
}