{
  "type": "Feature",
  "properties": {
    "iso:country":"ES",
    "sg:address":"Calle de Francisco Pizarro, 47",
    "sg:city":"Albacete",
    "sg:orig_category":"Prendas Y Chalecos De Punto (al Por Menor)",
    "sg:phone":"+34 967 22 12 38",
    "sg:postcode":"02004",
    "sg:province":"Albacete",
    "wof:name":"Lopez Defez Ana",
    "wof:placetype":"venue"
},
  "geometry": {"coordinates":[-1.8648430109,38.9920387268],"type":"Point"}
}