{
  "type": "Feature",
  "properties": {
    "iso:country":"ES",
    "sg:address":"Carrer de Padua, 92",
    "sg:city":"Barcelona",
    "sg:orig_category":"Molduras, Junquillos, Listones Y Molduras Perforadas",
    "sg:phone":"+34 932 12 30 56",
    "sg:postcode":"08006",
    "sg:province":"Barcelona",
    "wof:name":"Have It With Cheese S.l.",
    "wof:placetype":"venue"
},
  "geometry": {"coordinates":[2.1438670158,41.4043617249],"type":"Point"}
}