{
  "type": "Feature",
  "properties": {
    "iso:country":"ES",
    "sg:address":"Calle de Santa Cruz, 19",
    "sg:city":"Broto",
    "sg:orig_category":"Iglesia Cat\u00d3lica",
    "sg:phone":"+34 974 48 60 33",
    "sg:postcode":"22370",
    "sg:province":"Huesca",
    "wof:name":"Parroquia De Broto",
    "wof:placetype":"venue"
},
  "geometry": {"coordinates":[-0.1213781014,42.6034164429],"type":"Point"}
}