{
  "type": "Feature",
  "properties": {
    "iso:country":"ES",
    "sg:address":"Calle de George Stephenson, 28",
    "sg:city":"Zaragoza",
    "sg:orig_category":"Delegados, Agentes De Tr\u00c1nsito, Auxiliares De Transporte Internacional",
    "sg:phone":"+34 976 74 10 00",
    "sg:postcode":"50015",
    "sg:province":"Zaragoza",
    "wof:name":"Nacional 10 Horas S.l.",
    "wof:placetype":"venue"
},
  "geometry": {"coordinates":[-0.8650869727,41.6790428162],"type":"Point"}
}