{
  "type": "Feature",
  "properties": {
    "iso:country":"ES",
    "sg:address":"Calle de San Antonio, 9",
    "sg:city":"Catedral",
    "sg:orig_category":"Agencias Y Agentes Comerciales, Representantes",
    "sg:phone":"+34 968 21 17 83",
    "sg:postcode":"30001",
    "sg:province":"Murcia",
    "wof:name":"Hellin Cespedes Francisco",
    "wof:placetype":"venue"
},
  "geometry": {"coordinates":[-1.1260739565,37.98462677],"type":"Point"}
}