{
  "type": "Feature",
  "properties": {
    "iso:country":"ES",
    "sg:address":"Calle de Mesena, 72",
    "sg:city":"Madrid",
    "sg:orig_category":"Fabricaci\u00d3n, Importaci\u00d3n, Venta De Material De Telefon\u00cda, Peritelefon\u00cda",
    "sg:phone":"+34 913 88 21 19",
    "sg:postcode":"28033",
    "sg:province":"Madrid",
    "wof:name":"Tower Consultores S.l.",
    "wof:placetype":"venue"
},
  "geometry": {"coordinates":[-3.6608290672,40.4627189636],"type":"Point"}
}