{
  "type": "Feature",
  "properties": {
    "addr:full":"Plaz Cura, 1 Vianos Albacete 02315",
    "addr:housenumber":"1",
    "addr:postcode":"02315",
    "addr:street":"Plaz Cura",
    "iso:country":"ES",
    "sg:address":"Plaz Cura, 1",
    "sg:city":"Vianos",
    "sg:orig_category":"Iglesia Cat\u00d3lica",
    "sg:phone":"+34 967 38 02 78",
    "sg:postcode":"02315",
    "sg:province":"Albacete",
    "wof:name":"Parroquia De San Sebastian",
    "wof:placetype":"venue"
},
  "geometry": {"coordinates":[-2.5165610313,38.6199035645],"type":"Point"}
}