{
  "type": "Feature",
  "properties": {
    "iso:country":"ES",
    "sg:address":"Ctra Granada, 13",
    "sg:city":"Baza",
    "sg:orig_category":"Electrodom\u00c9sticos (al Por Menor)",
    "sg:phone":"+34 958 70 30 70",
    "sg:postcode":"18800",
    "sg:province":"Granada",
    "wof:name":"Miron Martinez Blas",
    "wof:placetype":"venue"
},
  "geometry": {"coordinates":[-2.7665469646,37.4870185852],"type":"Point"}
}