{
  "type": "Feature",
  "properties": {
    "iso:country":"ES",
    "sg:address":"Rbla Sant Sebastia, 30",
    "sg:city":"Santa Coloma De Gramenet",
    "sg:orig_category":"Caf\u00c9s, Bares, Cervecer\u00cdas",
    "sg:phone":"+34 933 86 26 65",
    "sg:postcode":"08922",
    "sg:province":"Barcelona",
    "wof:name":"Jomarcamps S.l.",
    "wof:placetype":"venue"
},
  "geometry": {"coordinates":[2.2111439705,41.4506034851],"type":"Point"}
}