{
  "type": "Feature",
  "properties": {
    "addr:full":"Avda Doctor Meca, 51 Puerto Mazarron Murcia 30860",
    "addr:housenumber":"51",
    "addr:postcode":"30860",
    "addr:street":"Avda Doctor Meca",
    "iso:country":"ES",
    "sg:address":"Avda Doctor Meca, 51",
    "sg:city":"Puerto Mazarron",
    "sg:classifiers":[
        {
            "category":"Communications",
            "type":"Services"
        }
    ],
    "sg:phone":"+34 968 59 50 36",
    "sg:postcode":"30860",
    "sg:province":"Murcia",
    "sg:tags":[
        "televisiones",
        "y",
        "radio"
    ],
    "wof:name":"Radio Costa Calida S.l.",
    "wof:placetype":"venue"
},
  "geometry": {"coordinates":[-1.2611869574,37.5659828186],"type":"Point"}
}