{
  "type": "Feature",
  "properties": {
    "addr:full":"Ctra Media Sala, S/n Barreros Murcia 30310",
    "addr:housenumber":"s / n",
    "addr:postcode":"30310",
    "addr:street":"Ctra Media Sala",
    "iso:country":"ES",
    "sg:address":"Ctra Media Sala, S/n",
    "sg:city":"Barreros",
    "sg:orig_category":"Empresas De Limpieza",
    "sg:phone":"+34 968 31 42 60",
    "sg:postcode":"30310",
    "sg:province":"Murcia",
    "wof:name":"Camoin 1900 Servicios S.l",
    "wof:placetype":"venue"
},
  "geometry": {"coordinates":[-1.0082689524,37.6360816956],"type":"Point"}
}