{
  "type": "Feature",
  "properties": {
    "iso:country":"ES",
    "sg:address":"Poli La Pedrera, 7",
    "sg:city":"Benissa",
    "sg:orig_category":"Agentes, Concesionarios Y Sucursales De Veh\u00cdculos",
    "sg:phone":"+34 965 73 15 76",
    "sg:postcode":"03720",
    "sg:province":"Alicante",
    "wof:name":"La Marina Motor S. L.",
    "wof:placetype":"venue"
},
  "geometry": {"coordinates":[0.050774999,38.7144584656],"type":"Point"}
}