{
  "type": "Feature",
  "properties": {
    "iso:country":"ES",
    "sg:address":"Calle de Torrecilla, 8",
    "sg:city":"Valladolid",
    "sg:orig_category":"Abogados",
    "sg:phone":"+34 983 26 86 50",
    "sg:postcode":"47003",
    "sg:province":"Valladolid",
    "wof:name":"Alonso Narros Alfonso",
    "wof:placetype":"venue"
},
  "geometry": {"coordinates":[-4.7233548164,41.6559829712],"type":"Point"}
}