{
  "type": "Feature",
  "properties": {
    "addr:full":"Carrer de Nuno San\u00c7, 32 Palma Islas Baleares 07005",
    "addr:housenumber":"32",
    "addr:postcode":"07005",
    "addr:street":"Carrer De Nuno Sanc\u0327",
    "iso:country":"ES",
    "sg:address":"Carrer de Nuno San\u00c7, 32",
    "sg:city":"Palma",
    "sg:orig_category":"Asilos De Ancianos. Centros Privados",
    "sg:phone":"+34 971 24 87 09",
    "sg:postcode":"07005",
    "sg:province":"Islas Baleares",
    "wof:name":"Asociacion Tercera Edad Maria Plaza",
    "wof:placetype":"venue"
},
  "geometry": {"coordinates":[2.6620528698,39.5800094604],"type":"Point"}
}