{
  "type": "Feature",
  "properties": {
    "addr:full":"Carrer de Villar, 70 Barcelona Barcelona 08041",
    "addr:housenumber":"70",
    "addr:postcode":"08041",
    "addr:street":"Carrer De Villar",
    "iso:country":"ES",
    "sg:address":"Carrer de Villar, 70",
    "sg:city":"Barcelona",
    "sg:orig_category":"Fabricaci\u00d3n De Distribuidores Autom\u00c1ticos",
    "sg:phone":"+34 934 33 44 09",
    "sg:postcode":"08041",
    "sg:province":"Barcelona",
    "wof:name":"Monjo De Fontcuberta Gloria",
    "wof:placetype":"venue"
},
  "geometry": {"coordinates":[2.1766328812,41.4175720215],"type":"Point"}
}