{
  "type": "Feature",
  "properties": {
    "addr:full":"Calle de Zurbaran, 20 San Javier Murcia 30730",
    "addr:housenumber":"20",
    "addr:postcode":"30730",
    "addr:street":"Calle De Zurbaran",
    "iso:country":"ES",
    "sg:address":"Calle de Zurbaran, 20",
    "sg:city":"San Javier",
    "sg:orig_category":"Sales (al Por Mayor)",
    "sg:phone":"+34 968 19 08 80",
    "sg:postcode":"30730",
    "sg:province":"Murcia",
    "wof:name":"Sumnicar Mar Menor S.l.",
    "wof:placetype":"venue"
},
  "geometry": {"coordinates":[-0.8377289772,37.8054389954],"type":"Point"}
}