{
  "type": "Feature",
  "properties": {
    "addr:full":"Pg Hortsavinya, 5 Creus Barcelona 08397",
    "addr:housenumber":"5",
    "addr:postcode":"08397",
    "addr:street":"Pg Hortsavinya",
    "iso:country":"ES",
    "sg:address":"Pg Hortsavinya, 5",
    "sg:city":"Creus",
    "sg:orig_category":"Comercio De Piezas De Recambio Y De Accesorios De Veh\u00cdculos, Veh\u00cdculos Industriales",
    "sg:phone":"+34 937 62 64 57",
    "sg:postcode":"08397",
    "sg:province":"Barcelona",
    "wof:name":"Osuna Rodriguez Juan Jose",
    "wof:placetype":"venue"
},
  "geometry": {"coordinates":[2.6831099987,41.6262702942],"type":"Point"}
}