{
  "type": "Feature",
  "properties": {
    "addr:full":"Avda Albufereta, 50 Alacant Alicante 03016",
    "addr:housenumber":"50",
    "addr:postcode":"03016",
    "addr:street":"Avda Albufereta",
    "iso:country":"ES",
    "sg:address":"Avda Albufereta, 50",
    "sg:city":"Alacant",
    "sg:orig_category":"M\u00c9dicos: Cirug\u00cda General",
    "sg:phone":"+34 965 16 04 93",
    "sg:postcode":"03016",
    "sg:province":"Alicante",
    "wof:name":"Perez De La Romana Gonzalez Federico",
    "wof:placetype":"venue"
},
  "geometry": {"coordinates":[-0.4521790147,38.3649749756],"type":"Point"}
}