{
  "type": "Feature",
  "properties": {
    "addr:full":"Cami Ral, 480 Mataro Barcelona 08302",
    "addr:housenumber":"480",
    "addr:postcode":"08302",
    "addr:street":"Ral",
    "iso:country":"ES",
    "sg:address":"Cami Ral, 480",
    "sg:city":"Mataro",
    "sg:orig_category":"Centros Empresariales",
    "sg:phone":"+34 937 57 76 58",
    "sg:postcode":"08302",
    "sg:province":"Barcelona",
    "wof:name":"Telnor 2002 Sl",
    "wof:placetype":"venue"
},
  "geometry": {"coordinates":[2.4420681,41.5356750488],"type":"Point"}
}