{
  "type": "Feature",
  "properties": {
    "addr:full":"Calle de General Suarez Valdes, 34 Gijon Asturias 33204",
    "addr:housenumber":"34",
    "addr:postcode":"33204",
    "addr:street":"Calle De General Suarez Valdes",
    "iso:country":"ES",
    "sg:address":"Calle de General Suarez Valdes, 34",
    "sg:city":"Gijon",
    "sg:orig_category":"Pescader\u00cdas (al Por Menor)",
    "sg:phone":"+34 985 33 70 49",
    "sg:postcode":"33204",
    "sg:province":"Asturias",
    "wof:name":"Trancon Garcia Antonio",
    "wof:placetype":"venue"
},
  "geometry": {"coordinates":[-5.6484389305,43.5312652588],"type":"Point"}
}