{
  "type": "Feature",
  "properties": {
    "iso:country":"ES",
    "sg:address":"Carr Aiguanegra, 15",
    "sg:city":"Sant Joan Les Fonts",
    "sg:orig_category":"Electrodom\u00c9sticos (al Por Menor)",
    "sg:phone":"+34 972 29 07 81",
    "sg:postcode":"17857",
    "sg:province":"Girona",
    "wof:name":"Montoliu Juanola Carlos",
    "wof:placetype":"venue"
},
  "geometry": {"coordinates":[2.5107150078,42.2121162415],"type":"Point"}
}