{
  "type": "Feature",
  "properties": {
    "iso:country":"ES",
    "sg:address":"Calle de San Pablo, 2",
    "sg:city":"Priego Cordoba",
    "sg:orig_category":"Producci\u00d3n De Abonos Y De Fertilizantes",
    "sg:phone":"+34 957 70 01 58",
    "sg:postcode":"14800",
    "sg:province":"C\u00f3rdoba",
    "wof:name":"Padilla Lopez Lorenzo",
    "wof:placetype":"venue"
},
  "geometry": {"coordinates":[-4.201862812,37.4395103455],"type":"Point"}
}