{
  "type": "Feature",
  "properties": {
    "iso:country":"ES",
    "sg:address":"Avda Pueblos (de Los), S/n",
    "sg:city":"Playa Americas",
    "sg:orig_category":"Bazares, Art\u00cdculos De Limpieza Y De Cocina (al Por Menor)",
    "sg:phone":"+34 922 71 98 77",
    "sg:postcode":"38660",
    "sg:province":"Santa Cruz De Tenerife",
    "wof:name":"Atlanta Electronic S.l.",
    "wof:placetype":"venue"
},
  "geometry": {"coordinates":[-16.7267932892,28.0683612823],"type":"Point"}
}