{
  "type": "Feature",
  "properties": {
    "iso:country":"ES",
    "sg:address":"Calle de Tte Garau Fargas, 15",
    "sg:city":"Palma",
    "sg:orig_category":"Frutas, Legumbres Frescas Y Tempranas (al Por Menor)",
    "sg:phone":"+34 971 27 88 09",
    "sg:postcode":"07006",
    "sg:province":"Islas Baleares",
    "wof:name":"Munar Palou Elena",
    "wof:placetype":"venue"
},
  "geometry": {"coordinates":[2.6754970551,39.5605506897],"type":"Point"}
}