{
  "type": "Feature",
  "properties": {
    "iso:country":"ES",
    "sg:address":"Carrer de Emigrant, 2",
    "sg:city":"Hospitalet Llobregat",
    "sg:orig_category":"Peluquer\u00cdas, Peluquer\u00cda Mixta",
    "sg:phone":"+34 933 37 25 26",
    "sg:postcode":"08906",
    "sg:province":"Barcelona",
    "wof:name":"Perez Rayo Eva Esther",
    "wof:placetype":"venue"
},
  "geometry": {"coordinates":[2.0895910263,41.3657417297],"type":"Point"}
}