{
  "type": "Feature",
  "properties": {
    "addr:full":"Carr Sant Pere, 48 Gandia Valencia 46700",
    "addr:housenumber":"48",
    "addr:postcode":"46700",
    "addr:street":"Carr Sant Pere;Valencia",
    "iso:country":"ES",
    "sg:address":"Carr Sant Pere, 48",
    "sg:city":"Gandia",
    "sg:orig_category":"Peluquer\u00cdas, Peluquer\u00cda Mixta",
    "sg:phone":"+34 962 86 07 42",
    "sg:postcode":"46700",
    "sg:province":"Valencia",
    "wof:name":"Dominguez Lopez Esther",
    "wof:placetype":"venue"
},
  "geometry": {"coordinates":[-0.1913339943,38.960735321],"type":"Point"}
}