{
  "type": "Feature",
  "properties": {
    "addr:full":"Campi\u00d1o De Santa Maria, 3 Pontevedra Pontevedra 36099",
    "addr:housenumber":"3",
    "addr:postcode":"36099",
    "addr:street":"Maria",
    "iso:country":"ES",
    "sg:address":"Campi\u00d1o De Santa Maria, 3",
    "sg:city":"Pontevedra",
    "sg:orig_category":"Ebanister\u00cda",
    "sg:phone":"+34 986 85 28 26",
    "sg:postcode":"36099",
    "sg:province":"Pontevedra",
    "wof:name":"Omil Piay Ramiro",
    "wof:placetype":"venue"
},
  "geometry": {"coordinates":[-8.6471500397,42.4343643188],"type":"Point"}
}