{
  "type": "Feature",
  "properties": {
    "iso:country":"ES",
    "sg:address":"Ctra Alqueria, S/n",
    "sg:city":"Muro Alcoy",
    "sg:orig_category":"Abogados",
    "sg:phone":"+34 965 53 15 54",
    "sg:postcode":"03830",
    "sg:province":"Alicante",
    "wof:name":"Zaragoza Penoucos Hector Daniel",
    "wof:placetype":"venue"
},
  "geometry": {"coordinates":[-0.4325858951,38.7800102234],"type":"Point"}
}