{
  "type": "Feature",
  "properties": {
    "iso:country":"ES",
    "sg:address":"Carrer de Montseny, 16",
    "sg:city":"Canet Mar",
    "sg:orig_category":"Supermercados Y Hipermercados",
    "sg:phone":"+34 937 94 27 06",
    "sg:postcode":"08360",
    "sg:province":"Barcelona",
    "wof:name":"Cs Establiments De Proximitat S. L.",
    "wof:placetype":"venue"
},
  "geometry": {"coordinates":[2.5792460442,41.5919342041],"type":"Point"}
}