{
  "type": "Feature",
  "properties": {
    "addr:full":"Plaz Enrique Fernandez (de), 15 Belmonte Cuenca 16640",
    "addr:postcode":"16640",
    "iso:country":"ES",
    "sg:address":"Plaz Enrique Fernandez (de), 15",
    "sg:city":"Belmonte",
    "sg:orig_category":"Cl\u00cdnicas Dentales",
    "sg:phone":"+34 967 17 02 58",
    "sg:postcode":"16640",
    "sg:province":"Cuenca",
    "wof:name":"Cardenas Bazalar Octavio Alberto",
    "wof:placetype":"venue"
},
  "geometry": {"coordinates":[-2.7019920349,39.5578956604],"type":"Point"}
}