{
  "type": "Feature",
  "properties": {
    "iso:country":"ES",
    "sg:address":"Avda Orense, 62",
    "sg:city":"Espirito Santo",
    "sg:orig_category":"Pescader\u00cdas (al Por Mayor)",
    "sg:phone":"+34 986 30 38 72",
    "sg:postcode":"36940",
    "sg:province":"Pontevedra",
    "wof:name":"Surcafrio S.l.",
    "wof:placetype":"venue"
},
  "geometry": {"coordinates":[-8.8184690475,42.2742500305],"type":"Point"}
}