{
  "type": "Feature",
  "properties": {
    "iso:country":"ES",
    "sg:address":"Carr Baldomer Sola, 154",
    "sg:city":"Badalona",
    "sg:orig_category":"Loter\u00cda Y T\u00d3mbola",
    "sg:phone":"+34 933 83 88 08",
    "sg:postcode":"08912",
    "sg:province":"Barcelona",
    "wof:name":"Calvet Tarrida Rafael",
    "wof:placetype":"venue"
},
  "geometry": {"coordinates":[2.235129118,41.4436950684],"type":"Point"}
}