{
  "type": "Feature",
  "properties": {
    "iso:country":"ES",
    "sg:address":"Avda Reales (de Los), 73",
    "sg:city":"Estepona",
    "sg:orig_category":"Empresas De Carpinter\u00cda De Madera",
    "sg:phone":"+34 952 89 60 93",
    "sg:postcode":"29680",
    "sg:province":"M\u00e1laga",
    "wof:name":"Floguisol S.l.",
    "wof:placetype":"venue"
},
  "geometry": {"coordinates":[-5.1455287933,36.4317512512],"type":"Point"}
}