{
  "type": "Feature",
  "properties": {
    "iso:country":"ES",
    "sg:address":"Calle de Pablo Coronel, 8",
    "sg:city":"Alcala Henares",
    "sg:orig_category":"Farmacias",
    "sg:phone":"+34 918 80 50 32",
    "sg:postcode":"28802",
    "sg:province":"Madrid",
    "wof:name":"Sanz Pinilla Susana",
    "wof:placetype":"venue"
},
  "geometry": {"coordinates":[-3.3758831024,40.4783401489],"type":"Point"}
}