{
  "type": "Feature",
  "properties": {
    "addr:full":"Calle de Luis Montoto, 127 Sevilla Sevilla 41007",
    "addr:housenumber":"127",
    "addr:postcode":"41007",
    "addr:street":"Calle De Luis Montoto",
    "iso:country":"ES",
    "sg:address":"Calle de Luis Montoto, 127",
    "sg:city":"Sevilla",
    "sg:orig_category":"Estudios, Instalaci\u00d3n De Climatizaci\u00d3n",
    "sg:phone":"+34 954 57 83 65",
    "sg:postcode":"41007",
    "sg:province":"Sevilla",
    "sg:website":"www.isladeltesoro.com",
    "wof:name":"La Isla Del Tesoro Electrodomesticos S.a.",
    "wof:placetype":"venue"
},
  "geometry": {"coordinates":[-5.9687161446,37.387638092],"type":"Point"}
}