{
  "type": "Feature",
  "properties": {
    "addr:full":"Fca. Aldehuela, 21 Salamanca Salamanca 37003",
    "addr:housenumber":"21",
    "addr:postcode":"37003",
    "iso:country":"ES",
    "sg:address":"Fca. Aldehuela, 21",
    "sg:city":"Salamanca",
    "sg:orig_category":"Art\u00cdculos De Madera (fabricaci\u00d3n Y Al Por Mayor)",
    "sg:phone":"+34 923 18 08 10",
    "sg:postcode":"37003",
    "sg:province":"Salamanca",
    "wof:name":"Finca La Aldehuela S.l.",
    "wof:placetype":"venue"
},
  "geometry": {"coordinates":[-5.65498209,40.9584922791],"type":"Point"}
}