{
  "type": "Feature",
  "properties": {
    "addr:full":"Calle de Camino Viejo De Xirivella, 64 Mislata Valencia 46920",
    "addr:housenumber":"64",
    "addr:postcode":"46920",
    "addr:street":"Calle De Camino Viejo De Xirivella",
    "iso:country":"ES",
    "sg:address":"Calle de Camino Viejo De Xirivella, 64",
    "sg:city":"Mislata",
    "sg:orig_category":"Comercio, Reparaci\u00d3n De Motocicletas, Bicicletas Y Piezas Sueltas",
    "sg:phone":"+34 963 50 20 48",
    "sg:postcode":"46920",
    "sg:province":"Valencia",
    "wof:name":"Zame\u00f1o Perez Federico",
    "wof:placetype":"venue"
},
  "geometry": {"coordinates":[-0.4195876122,39.4779243469],"type":"Point"}
}