{
  "type": "Feature",
  "properties": {
    "iso:country":"ES",
    "sg:address":"Calle de Feijoo, 12",
    "sg:city":"Madrid",
    "sg:orig_category":"Farmacias",
    "sg:phone":"+34 914 47 19 77",
    "sg:postcode":"28010",
    "sg:province":"Madrid",
    "wof:name":"Munilla Saavedra Maria Elia",
    "wof:placetype":"venue"
},
  "geometry": {"coordinates":[-3.7031950951,40.4347076416],"type":"Point"}
}