{
  "type": "Feature",
  "properties": {
    "addr:full":"Calle de Gran Capitan, 11 Granada Granada 18002",
    "addr:housenumber":"11",
    "addr:postcode":"18002",
    "addr:street":"Calle De Gran Capitan",
    "iso:country":"ES",
    "sg:address":"Calle de Gran Capitan, 11",
    "sg:city":"Granada",
    "sg:orig_category":"Librer\u00cdas",
    "sg:phone":"+34 958 20 60 38",
    "sg:postcode":"18002",
    "sg:province":"Granada",
    "wof:name":"Ruiz Mancebo Manuel",
    "wof:placetype":"venue"
},
  "geometry": {"coordinates":[-3.6039791107,37.1783981323],"type":"Point"}
}