{
  "type": "Feature",
  "properties": {
    "iso:country":"ES",
    "sg:address":"Barr Txistulanda, 13",
    "sg:city":"Agirre-aperribai",
    "sg:orig_category":"Carnes De Carnicer\u00cda (al Por Mayor)",
    "sg:phone":"+34 944 40 36 65",
    "sg:postcode":"48960",
    "sg:province":"Vizcaya",
    "wof:name":"Edmundo Rebolleda Sanchez Y Maria Pilar Fernandez Marin S.c.",
    "wof:placetype":"venue"
},
  "geometry": {"coordinates":[-2.8646221161,43.2361068726],"type":"Point"}
}