{
  "type": "Feature",
  "properties": {
    "addr:full":"Calle de San Cristobal, S/n Tarancon Cuenca 16400",
    "addr:postcode":"16400",
    "addr:street":"Calle De San Cristobal S / N",
    "iso:country":"ES",
    "sg:address":"Calle de San Cristobal, S/n",
    "sg:city":"Tarancon",
    "sg:orig_category":"Escayola Y Productos De Escayola (fabricaci\u00d3n, Al Por Mayor)",
    "sg:phone":"+34 969 32 10 32",
    "sg:postcode":"16400",
    "sg:province":"Cuenca",
    "wof:name":"Escaplast S.l.",
    "wof:placetype":"venue"
},
  "geometry": {"coordinates":[-3.0039339066,40.0043334961],"type":"Point"}
}