{
  "type": "Feature",
  "properties": {
    "iso:country":"ES",
    "sg:address":"Calle de General Gomez Nu\u00d1ez, 5",
    "sg:city":"Ponferrada",
    "sg:orig_category":"Zapatos (al Por Menor)",
    "sg:phone":"+34 987 42 91 93",
    "sg:postcode":"24400",
    "sg:province":"Le\u00f3n",
    "wof:name":"Uria Garcia Antonio",
    "wof:placetype":"venue"
},
  "geometry": {"coordinates":[-6.5981431007,42.548324585],"type":"Point"}
}