{
  "type": "Feature",
  "properties": {
    "addr:full":"Calle de Alfonso Xiii, 26 Pto. Rosario Las Palmas 35600",
    "addr:housenumber":"26",
    "addr:postcode":"35600",
    "addr:street":"Calle De Alfonso Xiii;Pto. Rosario Las",
    "iso:country":"ES",
    "sg:address":"Calle de Alfonso Xiii, 26",
    "sg:city":"Pto. Rosario",
    "sg:orig_category":"Asociaciones Y Clubs Deportivos",
    "sg:phone":"+34 928 53 10 49",
    "sg:postcode":"35600",
    "sg:province":"Las Palmas",
    "wof:name":"Yague Suarez Jose Luis",
    "wof:placetype":"venue"
},
  "geometry": {"coordinates":[-13.8491182327,28.5035037994],"type":"Point"}
}