{
  "type": "Feature",
  "properties": {
    "addr:full":"Uceira, S/n Uceira Pontevedra 36885",
    "addr:postcode":"36885",
    "addr:street":"Uceira S / N",
    "iso:country":"ES",
    "sg:address":"Uceira, S/n",
    "sg:city":"Uceira",
    "sg:orig_category":"Aluminio Y Aleaciones (producci\u00d3n, Transformaci\u00d3n, Negocio)",
    "sg:phone":"+34 986 65 13 67",
    "sg:postcode":"36885",
    "sg:province":"Pontevedra",
    "wof:name":"Alugal S.l.",
    "wof:placetype":"venue"
},
  "geometry": {"coordinates":[-8.6480531693,42.4336204529],"type":"Point"}
}