{
  "type": "Feature",
  "properties": {
    "addr:full":"Calle de Mayor, 489 Raal Murcia 30139",
    "addr:housenumber":"489",
    "addr:postcode":"30139",
    "addr:street":"Calle De Mayor",
    "iso:country":"ES",
    "sg:address":"Calle de Mayor, 489",
    "sg:city":"Raal",
    "sg:orig_category":"Transportes Por V\u00cdas Navegables",
    "sg:phone":"+34 968 81 09 04",
    "sg:postcode":"30139",
    "sg:province":"Murcia",
    "wof:name":"Gonzalez Navarro Antonio",
    "wof:placetype":"venue"
},
  "geometry": {"coordinates":[-1.0201519728,38.0446243286],"type":"Point"}
}