{
  "type": "Feature",
  "properties": {
    "addr:full":"Calle de San Vicente Martir, 85 Valencia Valencia 46007",
    "addr:housenumber":"85",
    "addr:postcode":"46007",
    "addr:street":"Calle De San Vicente Martir",
    "iso:country":"ES",
    "sg:address":"Calle de San Vicente Martir, 85",
    "sg:city":"Valencia",
    "sg:orig_category":"Centros Empresariales",
    "sg:phone":"+34 963 51 53 37",
    "sg:postcode":"46007",
    "sg:province":"Valencia",
    "wof:name":"Asociacion De Empresarios De Oficinas Y Despachos",
    "wof:placetype":"venue"
},
  "geometry": {"coordinates":[-0.3806206882,39.4671173096],"type":"Point"}
}