{
  "type": "Feature",
  "properties": {
    "iso:country":"ES",
    "sg:address":"Calle de Casapalma, 9",
    "sg:city":"Malaga",
    "sg:orig_category":"Inmobiliaria (agencias)",
    "sg:phone":"+34 952 12 17 58",
    "sg:postcode":"29008",
    "sg:province":"M\u00e1laga",
    "wof:name":"Almelilu 2000 S.l.",
    "wof:placetype":"venue"
},
  "geometry": {"coordinates":[-4.420144558,36.7232437134],"type":"Point"}
}