{
  "type": "Feature",
  "properties": {
    "iso:country":"ES",
    "sg:address":"Carrer de Rossello, 203",
    "sg:city":"Barcelona",
    "sg:orig_category":"Frutas, Legumbres Frescas Y Tempranas (al Por Menor)",
    "sg:phone":"+34 932 17 07 16",
    "sg:postcode":"08008",
    "sg:province":"Barcelona",
    "wof:name":"Boguin S.c.c.p.",
    "wof:placetype":"venue"
},
  "geometry": {"coordinates":[2.1562330723,41.3926696777],"type":"Point"}
}