{
  "type": "Feature",
  "properties": {
    "addr:full":"Avda Nuestra Se\u00d1ora De Fatima, S/n San Vicente Alcantara Badajoz 06500",
    "addr:housenumber":"/ n",
    "addr:postcode":"06500",
    "addr:street":"Avda Nuestra Sen\u0303Ora De;S",
    "iso:country":"ES",
    "sg:address":"Avda Nuestra Se\u00d1ora De Fatima, S/n",
    "sg:city":"San Vicente Alcantara",
    "sg:orig_category":"Transportes Internacionales",
    "sg:phone":"+34 924 41 07 42",
    "sg:postcode":"06500",
    "sg:province":"Badajoz",
    "wof:name":"Ortes Duran Zoilo",
    "wof:placetype":"venue"
},
  "geometry": {"coordinates":[-7.1412239075,39.3616905212],"type":"Point"}
}