{
  "type": "Feature",
  "properties": {
    "iso:country":"ES",
    "sg:address":"C/ Vall, 49",
    "sg:city":"Llucmajor",
    "sg:orig_category":"Peluqueros: De Se\u00d1oras",
    "sg:phone":"+34 971 66 11 58",
    "sg:postcode":"07620",
    "sg:province":"Islas Baleares",
    "wof:name":"Garcia Mu\u00f1oz Josefina",
    "wof:placetype":"venue"
},
  "geometry": {"coordinates":[2.8896450996,39.4904174805],"type":"Point"}
}