{
  "type": "Feature",
  "properties": {
    "addr:full":"Calle de Murillo, 5 Bollullos Par Condado Huelva 21710",
    "addr:housenumber":"5",
    "addr:postcode":"21710",
    "addr:street":"Calle De Murillo",
    "iso:country":"ES",
    "sg:address":"Calle de Murillo, 5",
    "sg:city":"Bollullos Par Condado",
    "sg:orig_category":"Contenedores (mercanc\u00cdas)",
    "sg:phone":"+34 959 41 03 06",
    "sg:postcode":"21710",
    "sg:province":"Huelva",
    "wof:name":"Jimenez Fernandez Pascual",
    "wof:placetype":"venue"
},
  "geometry": {"coordinates":[-6.5370612144,37.3400344849],"type":"Point"}
}