{
  "type": "Feature",
  "properties": {
    "addr:full":"Carrer de Ample, 32 Reus Tarragona 43202",
    "addr:housenumber":"32",
    "addr:postcode":"43202",
    "addr:street":"Carrer De Ample",
    "iso:country":"ES",
    "sg:address":"Carrer de Ample, 32",
    "sg:city":"Reus",
    "sg:orig_category":"Empresas De Portes Y Mensajer\u00cda",
    "sg:phone":"+34 977 33 13 24",
    "sg:postcode":"43202",
    "sg:province":"Tarragona",
    "wof:name":"Teleenvios Reus S.l.",
    "wof:placetype":"venue"
},
  "geometry": {"coordinates":[1.1040090322,41.1589546204],"type":"Point"}
}