{
  "type": "Feature",
  "properties": {
    "addr:full":"Calle de Segre, 13 Madrid Madrid 28002",
    "addr:housenumber":"13",
    "addr:postcode":"madrid;28002",
    "addr:street":"Calle De Segre",
    "iso:country":"ES",
    "sg:address":"Calle de Segre, 13",
    "sg:city":"Madrid",
    "sg:orig_category":"Aspiradoras Dom\u00c9sticas",
    "sg:phone":"+34 902 30 55 30",
    "sg:postcode":"28002",
    "sg:province":"Madrid",
    "wof:name":"Dyson Spain S.l.",
    "wof:placetype":"venue"
},
  "geometry": {"coordinates":[-3.6837539673,40.4506988525],"type":"Point"}
}