{
  "type": "Feature",
  "properties": {
    "iso:country":"ES",
    "sg:address":"Ctra Base, 7",
    "sg:city":"Torrejon Ardoz",
    "sg:orig_category":"Clases De M\u00dasica Y Canto",
    "sg:phone":"+34 916 76 68 46",
    "sg:postcode":"28850",
    "sg:province":"Madrid",
    "wof:name":"Salvador Espasa Frederic",
    "wof:placetype":"venue"
},
  "geometry": {"coordinates":[-3.4572329521,40.4619789124],"type":"Point"}
}