{
  "type": "Feature",
  "properties": {
    "iso:country":"ES",
    "sg:address":"Pase Ramon Maria Lili, 7",
    "sg:city":"Donostia-san Sebastian",
    "sg:orig_category":"Centros Empresariales",
    "sg:phone":"+34 943 27 54 15",
    "sg:postcode":"20002",
    "sg:province":"Guip\u00f9zcoa",
    "wof:name":"Entidad De Gestion De Derechos Audiovisuales",
    "wof:placetype":"venue"
},
  "geometry": {"coordinates":[-1.9779280424,43.322052002],"type":"Point"}
}