{
  "type": "Feature",
  "properties": {
    "addr:full":"Calle de Maestro Puig Valera, S/n Santomera Murcia 30140",
    "addr:housenumber":"s / n",
    "addr:postcode":"30140",
    "addr:street":"Calle De Maestro Puig Valera",
    "iso:country":"ES",
    "sg:address":"Calle de Maestro Puig Valera, S/n",
    "sg:city":"Santomera",
    "sg:orig_category":"Veh\u00cdculos De Ocasi\u00d3n",
    "sg:phone":"+34 968 86 58 87",
    "sg:postcode":"30140",
    "sg:province":"Murcia",
    "wof:name":"Automoviles De Ocasion Santomera S.l.",
    "wof:placetype":"venue"
},
  "geometry": {"coordinates":[-1.0478343964,38.0598564148],"type":"Point"}
}