{
  "type": "Feature",
  "properties": {
    "addr:full":"Rua Industria (da), 91 Lugo Lugo 27003",
    "addr:housenumber":"91",
    "addr:postcode":"27003",
    "addr:street":"Rua Industria Da",
    "iso:country":"ES",
    "sg:address":"Rua Industria (da), 91",
    "sg:city":"Lugo",
    "sg:orig_category":"Cristaler\u00cdas",
    "sg:phone":"+34 982 22 16 19",
    "sg:postcode":"27003",
    "sg:province":"Lugo",
    "wof:name":"Vidrieria Lara S.l.",
    "wof:placetype":"venue"
},
  "geometry": {"coordinates":[-7.5691690445,43.0469284058],"type":"Point"}
}