{
  "type": "Feature",
  "properties": {
    "addr:full":"Carr Badia, 96 Moncada Valencia 46113",
    "addr:housenumber":"96",
    "addr:postcode":"46113",
    "addr:street":"Carr Badia",
    "iso:country":"ES",
    "sg:address":"Carr Badia, 96",
    "sg:city":"Moncada",
    "sg:orig_category":"T\u00c9cnicos Veterinarios",
    "sg:phone":"+34 961 39 44 28",
    "sg:postcode":"46113",
    "sg:province":"Valencia",
    "wof:name":"Juan Vicente Fernandez Villalba Y Otros Cdad",
    "wof:placetype":"venue"
},
  "geometry": {"coordinates":[-0.3988769948,39.5426254272],"type":"Point"}
}