{
  "type": "Feature",
  "properties": {
    "iso:country":"ES",
    "sg:address":"Avda Paseo De Almeria, 45",
    "sg:city":"Almeria",
    "sg:orig_category":"Arquitectos",
    "sg:phone":"+34 950 25 14 00",
    "sg:postcode":"04001",
    "sg:province":"Almer\u00eda",
    "wof:name":"Carmona Perez Manuel",
    "wof:placetype":"venue"
},
  "geometry": {"coordinates":[-2.4608390331,36.8422698975],"type":"Point"}
}