{
  "type": "Feature",
  "properties": {
    "iso:country":"ES",
    "sg:address":"Paseo De La Vega, 12",
    "sg:city":"Guma",
    "sg:orig_category":"Peleter\u00cdas",
    "sg:phone":"+34 947 53 81 02",
    "sg:postcode":"09491",
    "sg:province":"Burgos",
    "wof:name":"Jabonero Gonzalez Saturnino",
    "wof:placetype":"venue"
},
  "geometry": {"coordinates":[-3.6458818913,41.6477012634],"type":"Point"}
}