{
  "type": "Feature",
  "properties": {
    "addr:full":"Carrer de Numancia, 84 Barcelona Barcelona 08029",
    "addr:housenumber":"84",
    "addr:postcode":"08029",
    "addr:street":"Carrer De Numancia",
    "iso:country":"ES",
    "sg:address":"Carrer de Numancia, 84",
    "sg:city":"Barcelona",
    "sg:orig_category":"Farmacias",
    "sg:phone":"+34 933 21 94 42",
    "sg:postcode":"08029",
    "sg:province":"Barcelona",
    "wof:name":"Belart Tomas Josefa",
    "wof:placetype":"venue"
},
  "geometry": {"coordinates":[2.1371529102,41.3851661682],"type":"Point"}
}