{
  "type": "Feature",
  "properties": {
    "addr:full":"Calle de Duero, 8 Sevilla Sevilla 41012",
    "addr:housenumber":"8",
    "addr:postcode":"41012",
    "addr:street":"Calle De Duero",
    "iso:country":"ES",
    "sg:address":"Calle de Duero, 8",
    "sg:city":"Sevilla",
    "sg:orig_category":"Abogados",
    "sg:phone":"+34 954 62 15 28",
    "sg:postcode":"41012",
    "sg:province":"Sevilla",
    "wof:name":"Parra Andres Rosa Maria",
    "wof:placetype":"venue"
},
  "geometry": {"coordinates":[-5.9865880013,37.3526382446],"type":"Point"}
}