{
  "type": "Feature",
  "properties": {
    "addr:full":"Pla\u00c7 Escoles, 1 Escala Girona 17130",
    "addr:housenumber":"1",
    "addr:postcode":"17130",
    "addr:street":"Escoles",
    "iso:country":"ES",
    "sg:address":"Pla\u00c7 Escoles, 1",
    "sg:city":"Escala",
    "sg:orig_category":"Hoteles",
    "sg:phone":"+34 972 77 04 43",
    "sg:postcode":"17130",
    "sg:province":"Girona",
    "wof:name":"Hotel Can Catala C.b.",
    "wof:placetype":"venue"
},
  "geometry": {"coordinates":[3.1321649551,42.1229934692],"type":"Point"}
}