{
  "type": "Feature",
  "properties": {
    "iso:country":"ES",
    "sg:address":"Calle de Padre Felgueira, 13",
    "sg:city":"Jodar",
    "sg:orig_category":"Hielo Artificial (fabricaci\u00d3n, Distribuci\u00d3n)",
    "sg:phone":"+34 953 78 76 48",
    "sg:postcode":"23500",
    "sg:province":"Ja\u00e9n",
    "wof:name":"Helados Mayma S.l.",
    "wof:placetype":"venue"
},
  "geometry": {"coordinates":[-3.3542990685,37.8375930786],"type":"Point"}
}