{
  "type": "Feature",
  "properties": {
    "addr:full":"Carrer de Vilarrubias, 7 Sabadell Barcelona 08208",
    "addr:housenumber":"7",
    "addr:postcode":"08208",
    "addr:street":"Carrer De Vilarrubias",
    "iso:country":"ES",
    "sg:address":"Carrer de Vilarrubias, 7",
    "sg:city":"Sabadell",
    "sg:orig_category":"Abogados",
    "sg:phone":"+34 937 17 87 35",
    "sg:postcode":"08208",
    "sg:province":"Barcelona",
    "wof:name":"Riba Blanch Francina",
    "wof:placetype":"venue"
},
  "geometry": {"coordinates":[2.1071670055,41.5524864197],"type":"Point"}
}