{
  "type": "Feature",
  "properties": {
    "addr:full":"Calle de Calvo Sotelo, 14 Oviedo Asturias 33007",
    "addr:housenumber":"14",
    "addr:postcode":"33007",
    "addr:street":"Calle De Calvo Sotelo",
    "iso:country":"ES",
    "sg:address":"Calle de Calvo Sotelo, 14",
    "sg:city":"Oviedo",
    "sg:orig_category":"Abogados",
    "sg:phone":"+34 985 25 39 46",
    "sg:postcode":"33007",
    "sg:province":"Asturias",
    "wof:name":"Alvarez-buylla Ortega Alfonso",
    "wof:placetype":"venue"
},
  "geometry": {"coordinates":[-5.8520565033,43.3583679199],"type":"Point"}
}