{
  "type": "Feature",
  "properties": {
    "iso:country":"ES",
    "sg:address":"Calle de Musico Cabanilles, 29",
    "sg:city":"Valencia",
    "sg:orig_category":"Parques De Atracciones Y Centros De Esparcimiento",
    "sg:phone":"+34 963 58 16 05",
    "sg:postcode":"46017",
    "sg:province":"Valencia",
    "wof:name":"Comercial Igove 94 S.l.",
    "wof:placetype":"venue"
},
  "geometry": {"coordinates":[-0.3905229867,39.4447250366],"type":"Point"}
}