{
  "type": "Feature",
  "properties": {
    "addr:full":"Calle de Raimundo Moran, 11 Cistierna Le\u00f3n 24800",
    "addr:housenumber":"11",
    "addr:postcode":"24800",
    "addr:street":"Calle De Raimundo Moran;Leo\u0301N",
    "iso:country":"ES",
    "sg:address":"Calle de Raimundo Moran, 11",
    "sg:city":"Cistierna",
    "sg:orig_category":"Fisioterapia",
    "sg:phone":"+34 987 70 05 69",
    "sg:postcode":"24800",
    "sg:province":"Le\u00f3n",
    "wof:name":"Sis-salud,cb",
    "wof:placetype":"venue"
},
  "geometry": {"coordinates":[-5.1244292259,42.8032493591],"type":"Point"}
}