{
  "type": "Feature",
  "properties": {
    "addr:full":"Calle de Grande, 9 Calahorra La Rioja 26500",
    "addr:housenumber":"9",
    "addr:postcode":"26500",
    "addr:street":"Calle De Grande",
    "iso:country":"ES",
    "sg:address":"Calle de Grande, 9",
    "sg:city":"Calahorra",
    "sg:orig_category":"Perfumer\u00cda (al Por Menor)",
    "sg:phone":"+34 941 13 07 79",
    "sg:postcode":"26500",
    "sg:province":"La Rioja",
    "wof:name":"Gil Viguera Maria Del Carmen",
    "wof:placetype":"venue"
},
  "geometry": {"coordinates":[-1.961804986,42.3019104004],"type":"Point"}
}