{
  "type": "Feature",
  "properties": {
    "addr:full":"Calle de Conde De Pe\u00d1alver, 55 Madrid Madrid 28006",
    "addr:housenumber":"55",
    "addr:postcode":"madrid;28006",
    "addr:street":"Calle De Conde De Pen\u0303Alver",
    "iso:country":"ES",
    "sg:address":"Calle de Conde De Pe\u00d1alver, 55",
    "sg:city":"Madrid",
    "sg:orig_category":"Medias Y Calcetines (al Por Menor)",
    "sg:phone":"+34 914 01 04 51",
    "sg:postcode":"28006",
    "sg:province":"Madrid",
    "wof:name":"Asensio Fernandez Manuel",
    "wof:placetype":"venue"
},
  "geometry": {"coordinates":[-3.6751124859,40.4325828552],"type":"Point"}
}