{
  "type": "Feature",
  "properties": {
    "addr:full":"Carrer de Major, 67 Molins Rei Barcelona 08750",
    "addr:housenumber":"67",
    "addr:postcode":"08750",
    "addr:street":"Carrer De Major;Barcelona",
    "iso:country":"ES",
    "sg:address":"Carrer de Major, 67",
    "sg:city":"Molins Rei",
    "sg:orig_category":"Ropa De Hogar (al Por Menor)",
    "sg:phone":"+34 936 68 04 62",
    "sg:postcode":"08750",
    "sg:province":"Barcelona",
    "wof:name":"Paniagua Perez Amalia",
    "wof:placetype":"venue"
},
  "geometry": {"coordinates":[2.0175459385,41.4125404358],"type":"Point"}
}