{
  "type": "Feature",
  "properties": {
    "iso:country":"ES",
    "sg:address":"Calle de San Isidro, 5",
    "sg:city":"Alcorcon",
    "sg:orig_category":"Molduras, Junquillos, Listones Y Molduras Perforadas",
    "sg:phone":"+34 916 19 10 28",
    "sg:postcode":"28921",
    "sg:province":"Madrid",
    "wof:name":"Mu\u00f1oz Millan Guillermo",
    "wof:placetype":"venue"
},
  "geometry": {"coordinates":[-3.8256180286,40.3449821472],"type":"Point"}
}