{
  "type": "Feature",
  "properties": {
    "iso:country":"ES",
    "sg:address":"Calle de Puerto Rico, 29",
    "sg:city":"Madrid",
    "sg:orig_category":"Muebles, Minoristas",
    "sg:phone":"+34 913 59 74 02",
    "sg:postcode":"28016",
    "sg:province":"Madrid",
    "wof:name":"Garcia Sanchez Juan",
    "wof:placetype":"venue"
},
  "geometry": {"coordinates":[-3.6742999554,40.4555625916],"type":"Point"}
}