{
  "type": "Feature",
  "properties": {
    "addr:full":"Plaz Lex Flavia Malacitana, 5 Malaga M\u00e1laga 29013",
    "addr:housenumber":"5",
    "addr:postcode":"29013",
    "addr:street":"Malacitana;Ma\u0301Laga",
    "iso:country":"ES",
    "sg:address":"Plaz Lex Flavia Malacitana, 5",
    "sg:city":"Malaga",
    "sg:orig_category":"Prot\u00c9sicos Dentales",
    "sg:phone":"+34 952 60 21 74",
    "sg:postcode":"29013",
    "sg:province":"M\u00e1laga",
    "wof:name":"Porras Jimenez Juan Francisco",
    "wof:placetype":"venue"
},
  "geometry": {"coordinates":[-4.4179391861,36.7295341492],"type":"Point"}
}