{
  "type": "Feature",
  "properties": {
    "addr:full":"Calle de Pozo Hondo, 9 Miajadas C\u00e1ceres 10100",
    "addr:housenumber":"9",
    "addr:postcode":"10100",
    "addr:street":"Calle De Pozo Hondo;Ca\u0301Ceres",
    "iso:country":"ES",
    "sg:address":"Calle de Pozo Hondo, 9",
    "sg:city":"Miajadas",
    "sg:orig_category":"Mec\u00c1nico Del Autom\u00d3vil",
    "sg:phone":"+34 927 34 70 65",
    "sg:postcode":"10100",
    "sg:province":"C\u00e1ceres",
    "wof:name":"Mora\u00f1o Torres Fernando",
    "wof:placetype":"venue"
},
  "geometry": {"coordinates":[-5.9031319618,39.1550331116],"type":"Point"}
}