{
  "type": "Feature",
  "properties": {
    "addr:full":"Calle de Parral (del), 1 Segovia Segovia 40003",
    "addr:housenumber":"1",
    "addr:postcode":"40003",
    "addr:street":"Calle De Parral Del",
    "iso:country":"ES",
    "sg:address":"Calle de Parral (del), 1",
    "sg:city":"Segovia",
    "sg:orig_category":"Abogados",
    "sg:phone":"+34 921 43 74 29",
    "sg:postcode":"40003",
    "sg:province":"Segovia",
    "wof:name":"Moreno Hernandez Pedro",
    "wof:placetype":"venue"
},
  "geometry": {"coordinates":[-4.1279230118,40.9555435181],"type":"Point"}
}