{
  "type": "Feature",
  "properties": {
    "addr:full":"Calle de Collado (el), 8 Soria Soria 42002",
    "addr:housenumber":"8",
    "addr:postcode":"42002",
    "addr:street":"Calle De Collado El",
    "iso:country":"ES",
    "sg:address":"Calle de Collado (el), 8",
    "sg:city":"Soria",
    "sg:orig_category":"Electrodom\u00c9sticos (al Por Menor)",
    "sg:phone":"+34 975 21 15 96",
    "sg:postcode":"42002",
    "sg:province":"Soria",
    "wof:name":"Casa Zapata S.l",
    "wof:placetype":"venue"
},
  "geometry": {"coordinates":[-2.4647886753,41.7637557983],"type":"Point"}
}