{
  "type": "Feature",
  "properties": {
    "addr:full":"Carrer de Rossello, 228 Barcelona Barcelona 08008",
    "addr:housenumber":"228",
    "addr:postcode":"08008",
    "addr:street":"Carrer De Rossello",
    "iso:country":"ES",
    "sg:address":"Carrer de Rossello, 228",
    "sg:city":"Barcelona",
    "sg:orig_category":"M\u00c9dicos: Medicina Interna",
    "sg:phone":"+34 932 15 07 83",
    "sg:postcode":"08008",
    "sg:province":"Barcelona",
    "wof:name":"Campillo Pastells Francisco De Asis",
    "wof:placetype":"venue"
},
  "geometry": {"coordinates":[2.1599309444,41.3950881958],"type":"Point"}
}