{
  "type": "Feature",
  "properties": {
    "iso:country":"ES",
    "sg:address":"Calle de Iglesia, 16",
    "sg:city":"Casas De Fernando Alonso",
    "sg:orig_category":"Seguros",
    "sg:phone":"+34 969 38 33 37",
    "sg:postcode":"16610",
    "sg:province":"Cuenca",
    "wof:name":"Asegute S.l.",
    "wof:placetype":"venue"
},
  "geometry": {"coordinates":[-2.3223323822,39.3511772156],"type":"Point"}
}