{
  "type": "Feature",
  "properties": {
    "addr:full":"Rua Serra De Outes, S/n Lugo Lugo 27004",
    "addr:housenumber":"s / n",
    "addr:postcode":"27004",
    "addr:street":"Rua Serra De Outes",
    "iso:country":"ES",
    "sg:address":"Rua Serra De Outes, S/n",
    "sg:city":"Lugo",
    "sg:orig_category":"Centros De Educaci\u00d3n Especial",
    "sg:phone":"+34 982 21 81 74",
    "sg:postcode":"27004",
    "sg:province":"Lugo",
    "wof:name":"Colexio Publico De Educacion Xeral Basica Menendez Y Pelayo",
    "wof:placetype":"venue"
},
  "geometry": {"coordinates":[-7.5701441765,43.0156898499],"type":"Point"}
}