{
  "type": "Feature",
  "properties": {
    "addr:full":"Carrer de Badalona, 7 Terrassa Barcelona 08223",
    "addr:housenumber":"7",
    "addr:postcode":"08223",
    "addr:street":"Carrer De Badalona",
    "iso:country":"ES",
    "sg:address":"Carrer de Badalona, 7",
    "sg:city":"Terrassa",
    "sg:orig_category":"Agencias Y Agentes Comerciales, Representantes",
    "sg:phone":"+34 937 84 16 39",
    "sg:postcode":"08223",
    "sg:province":"Barcelona",
    "wof:name":"Garcia Perez Elisabeth",
    "wof:placetype":"venue"
},
  "geometry": {"coordinates":[2.0183749199,41.5497016907],"type":"Point"}
}