{
  "type": "Feature",
  "properties": {
    "addr:full":"Carr Tortosa, 84 Badalona Barcelona 08918",
    "addr:housenumber":"84",
    "addr:postcode":"08918",
    "addr:street":"Carr Tortosa",
    "iso:country":"ES",
    "sg:address":"Carr Tortosa, 84",
    "sg:city":"Badalona",
    "sg:orig_category":"Electricidad: Instaladores",
    "sg:phone":"+34 933 97 10 26",
    "sg:postcode":"08918",
    "sg:province":"Barcelona",
    "wof:name":"Instalacions O.l 96 S.l",
    "wof:placetype":"venue"
},
  "geometry": {"coordinates":[2.2334980965,41.4379043579],"type":"Point"}
}