{
  "type": "Feature",
  "properties": {
    "addr:full":"Calle de Nicolas Maria Urgoiti, 1 Aranguren Vizcaya 48850",
    "addr:housenumber":"1",
    "addr:postcode":"48850",
    "addr:street":"Calle De Nicolas Maria Urgoiti",
    "iso:country":"ES",
    "sg:address":"Calle de Nicolas Maria Urgoiti, 1",
    "sg:city":"Aranguren",
    "sg:orig_category":"Art\u00cdculos De Madera (fabricaci\u00d3n Y Al Por Mayor)",
    "sg:phone":"+34 946 39 13 37",
    "sg:postcode":"48850",
    "sg:province":"Vizcaya",
    "wof:name":"Muebles Bucorlevi Sll",
    "wof:placetype":"venue"
},
  "geometry": {"coordinates":[-3.1144390106,43.211025238],"type":"Point"}
}