{
  "type": "Feature",
  "properties": {
    "addr:full":"Rua Andres Muruais, 12 Pontevedra Pontevedra 36001",
    "addr:housenumber":"12",
    "addr:postcode":"36001",
    "addr:street":"Rua Andres Muruais",
    "iso:country":"ES",
    "sg:address":"Rua Andres Muruais, 12",
    "sg:city":"Pontevedra",
    "sg:orig_category":"Notarios",
    "sg:phone":"+34 986 85 18 78",
    "sg:postcode":"36001",
    "sg:province":"Pontevedra",
    "wof:name":"Mendez Apenela Eduardo Ramon",
    "wof:placetype":"venue"
},
  "geometry": {"coordinates":[-8.6438121796,42.4289321899],"type":"Point"}
}