{
  "type": "Feature",
  "properties": {
    "iso:country":"ES",
    "sg:address":"Ctra Llerena-utrera, Km. 0132,6",
    "sg:city":"Carmona",
    "sg:orig_category":"Distribuci\u00d3n De Petr\u00d3leo Y Derivados",
    "sg:phone":"+34 954 19 06 28",
    "sg:postcode":"41410",
    "sg:province":"Sevilla",
    "sg:website":"www.cepsa.es",
    "wof:name":"Gasovimar Andalucia S.l.",
    "wof:placetype":"venue"
},
  "geometry": {"coordinates":[-5.6433792114,37.4708709717],"type":"Point"}
}