{
  "type": "Feature",
  "properties": {
    "iso:country":"ES",
    "sg:address":"Orihuela, 15",
    "sg:city":"Mutxamel",
    "sg:orig_category":"Promotores Constructores",
    "sg:phone":"+34 965 95 12 12",
    "sg:postcode":"03110",
    "sg:province":"Alicante",
    "wof:name":"J.m.a Cooperativa Valenciana De Trabajo Asociado S.c.",
    "wof:placetype":"venue"
},
  "geometry": {"coordinates":[-0.4464640021,38.4123306274],"type":"Point"}
}