{
  "type": "Feature",
  "properties": {
    "iso:country":"ES",
    "sg:address":"Barr Poligono De Ria\u00d1o, S/n",
    "sg:city":"Langreo",
    "sg:orig_category":"Venta, Montaje De Neum\u00c1ticos",
    "sg:phone":"+34 985 69 12 61",
    "sg:postcode":"33900",
    "sg:province":"Asturias",
    "wof:name":"Transportes Consta S.a.",
    "wof:placetype":"venue"
},
  "geometry": {"coordinates":[-5.6692090034,43.2883987427],"type":"Point"}
}