{
  "type": "Feature",
  "properties": {
    "iso:country":"ES",
    "sg:address":"Avda. Langreo-el Berron, 2",
    "sg:city":"La Carrera",
    "sg:orig_category":"Fabrica De Charcuter\u00cda",
    "sg:phone":"+34 985 74 25 40",
    "sg:postcode":"33186",
    "sg:province":"Asturias",
    "wof:name":"Productos Carnicos Muttimax S.l.",
    "wof:placetype":"venue"
},
  "geometry": {"coordinates":[-5.7012858391,43.3833732605],"type":"Point"}
}