{
  "type": "Feature",
  "properties": {
    "addr:full":"Carrer de Conca, 5 Barcelona Barcelona 08026",
    "addr:housenumber":"5",
    "addr:postcode":"08026",
    "addr:street":"Carrer De Conca",
    "iso:country":"ES",
    "sg:address":"Carrer de Conca, 5",
    "sg:city":"Barcelona",
    "sg:orig_category":"Venta, Colocaci\u00d3n De Autoradios",
    "sg:phone":"+34 934 36 66 78",
    "sg:postcode":"08026",
    "sg:province":"Barcelona",
    "wof:name":"Julmax S.c.p.",
    "wof:placetype":"venue"
},
  "geometry": {"coordinates":[2.1806099415,41.4131011963],"type":"Point"}
}