{
  "type": "Feature",
  "properties": {
    "addr:full":"Calle de Tres De Mayo, 22 Pedernoso Cuenca 16638",
    "addr:housenumber":"22",
    "addr:postcode":"16638",
    "addr:street":"Calle De Tres De Mayo",
    "iso:country":"ES",
    "sg:address":"Calle de Tres De Mayo, 22",
    "sg:city":"Pedernoso",
    "sg:orig_category":"Tapicer\u00cdas",
    "sg:phone":"+34 967 16 42 88",
    "sg:postcode":"16638",
    "sg:province":"Cuenca",
    "wof:name":"Lozano Picazo Felix",
    "wof:placetype":"venue"
},
  "geometry": {"coordinates":[-2.7432868481,39.4827232361],"type":"Point"}
}