{
  "type": "Feature",
  "properties": {
    "iso:country":"ES",
    "sg:address":"Bo Elizalde, 10",
    "sg:city":"Izurtza",
    "sg:orig_category":"Pintura Industrial (trabajos De)",
    "sg:phone":"+34 946 21 81 34",
    "sg:postcode":"48213",
    "sg:province":"Vizcaya",
    "wof:name":"Pinturas Alvarez Y Rodriguez C. B.",
    "wof:placetype":"venue"
},
  "geometry": {"coordinates":[-2.6414520741,43.1543617249],"type":"Point"}
}