{
  "type": "Feature",
  "properties": {
    "addr:full":"Calle de Villanueva, 6 Iscar Valladolid 47420",
    "addr:housenumber":"6",
    "addr:postcode":"47420",
    "addr:street":"Calle De Villanueva",
    "iso:country":"ES",
    "sg:address":"Calle de Villanueva, 6",
    "sg:city":"Iscar",
    "sg:orig_category":"Peluquer\u00cdas, Peluquer\u00cda Mixta",
    "sg:phone":"+34 983 61 13 71",
    "sg:postcode":"47420",
    "sg:province":"Valladolid",
    "wof:name":"Acebes Gomez Nieves",
    "wof:placetype":"venue"
},
  "geometry": {"coordinates":[-4.5303425789,41.3608283997],"type":"Point"}
}