{
  "type": "Feature",
  "properties": {
    "iso:country":"ES",
    "sg:address":"Calle de Cruz (la), 82",
    "sg:city":"Molina Segura",
    "sg:orig_category":"Peluquer\u00cdas, Peluquer\u00cda Mixta",
    "sg:phone":"+34 968 61 22 61",
    "sg:postcode":"30500",
    "sg:province":"Murcia",
    "wof:name":"Ros Fenoll Jose Javier",
    "wof:placetype":"venue"
},
  "geometry": {"coordinates":[-1.1257617474,38.1818466187],"type":"Point"}
}