{
  "type": "Feature",
  "properties": {
    "addr:full":"Carrer de Cuba, 5 Mataro Barcelona 08302",
    "addr:housenumber":"5",
    "addr:postcode":"08302",
    "addr:street":"Carrer De Cuba",
    "iso:country":"ES",
    "sg:address":"Carrer de Cuba, 5",
    "sg:city":"Mataro",
    "sg:orig_category":"Inform\u00c1tica: Consultores",
    "sg:phone":"+34 937 41 50 22",
    "sg:postcode":"08302",
    "sg:province":"Barcelona",
    "sg:website":"www.maresmebusiness.com",
    "wof:name":"Maresme Business S.l.",
    "wof:placetype":"venue"
},
  "geometry": {"coordinates":[2.4399180412,41.5379562378],"type":"Point"}
}