{
  "type": "Feature",
  "properties": {
    "iso:country":"ES",
    "sg:address":"Rua Paris (de), S/n",
    "sg:city":"Santiago De Compostela",
    "sg:orig_category":"Supermercados Y Hipermercados",
    "sg:phone":"+34 981 57 50 15",
    "sg:postcode":"15703",
    "sg:province":"La Coru\u00f1a",
    "sg:website":"www.alcampo.es",
    "wof:name":"Alcampo S.a.",
    "wof:placetype":"venue"
},
  "geometry": {"coordinates":[-8.5255155563,42.8839149475],"type":"Point"}
}