{
  "type": "Feature",
  "properties": {
    "iso:country":"ES",
    "sg:address":"Calle de Madre Soledad Torres Acosta, 1",
    "sg:city":"Jaen",
    "sg:orig_category":"M\u00c9dicos: Psiquiatr\u00cda",
    "sg:phone":"+34 953 23 13 34",
    "sg:postcode":"23001",
    "sg:province":"Ja\u00e9n",
    "wof:name":"Castro Fernandez Francisco Jose",
    "wof:placetype":"venue"
},
  "geometry": {"coordinates":[-3.7883040905,37.768913269],"type":"Point"}
}