{
  "type": "Feature",
  "properties": {
    "iso:country":"ES",
    "sg:address":"Part. Planas, 460",
    "sg:city":"Riudoms",
    "sg:orig_category":"Fabricaci\u00d3n, Venta De Cuadros, Accesorios Para Enmarcar",
    "sg:phone":"+34 977 85 17 51",
    "sg:postcode":"43330",
    "sg:province":"Tarragona",
    "wof:name":"Jumper Guixos Y Escayolas Sl",
    "wof:placetype":"venue"
},
  "geometry": {"coordinates":[1.0541909933,41.1382713318],"type":"Point"}
}