{
  "type": "Feature",
  "properties": {
    "addr:full":"Mercapalma, 153 Coll Rabassa Islas Baleares 07007",
    "addr:housenumber":"153",
    "addr:postcode":"07007",
    "addr:street":"Mercapalma;Rabassa",
    "iso:country":"ES",
    "sg:address":"Mercapalma, 153",
    "sg:city":"Coll Rabassa",
    "sg:orig_category":"Frutas Y Legumbres Frescas (al Por Mayor)",
    "sg:phone":"+34 971 26 38 13",
    "sg:postcode":"07007",
    "sg:province":"Islas Baleares",
    "wof:name":"Ferra Ferra Salvador",
    "wof:placetype":"venue"
},
  "geometry": {"coordinates":[2.6974449158,39.5513114929],"type":"Point"}
}