{
  "type": "Feature",
  "properties": {
    "addr:full":"Carrer de Salmeron, 25 Terrassa Barcelona 08222",
    "addr:housenumber":"25",
    "addr:postcode":"08222",
    "addr:street":"Carrer De Salmeron",
    "iso:country":"ES",
    "sg:address":"Carrer de Salmeron, 25",
    "sg:city":"Terrassa",
    "sg:orig_category":"Ense\u00d1anza, Formaci\u00d3n Profesional: Aprendizaje",
    "sg:phone":"+34 937 31 52 02",
    "sg:postcode":"08222",
    "sg:province":"Barcelona",
    "wof:name":"Consorci Del Centre De Documentacio I Museu Textil De Terrassa",
    "wof:placetype":"venue"
},
  "geometry": {"coordinates":[2.0197179317,41.5650520325],"type":"Point"}
}