{
  "type": "Feature",
  "properties": {
    "addr:full":"Sevilla (p I Prado), 13 Merida Badajoz 06800",
    "addr:housenumber":"13",
    "addr:postcode":"06800",
    "addr:street":"P I Prado",
    "iso:country":"ES",
    "sg:address":"Sevilla (p I Prado), 13",
    "sg:city":"Merida",
    "sg:orig_category":"Panader\u00cdas, Panader\u00cdas",
    "sg:phone":"+34 924 37 33 16",
    "sg:postcode":"06800",
    "sg:province":"Badajoz",
    "wof:name":"Panrico S.l.u.",
    "wof:placetype":"venue"
},
  "geometry": {"coordinates":[-6.3668441772,38.9046936035],"type":"Point"}
}