{
  "type": "Feature",
  "properties": {
    "iso:country":"ES",
    "sg:address":"Carrer de L'escorial, 6",
    "sg:city":"Barcelona",
    "sg:orig_category":"Reposter\u00cdas",
    "sg:phone":"+34 932 84 95 71",
    "sg:postcode":"08024",
    "sg:province":"Barcelona",
    "wof:name":"Puig Perez Miguel",
    "wof:placetype":"venue"
},
  "geometry": {"coordinates":[2.1633200645,41.4051513672],"type":"Point"}
}