{
  "type": "Feature",
  "properties": {
    "addr:full":"Calle de General Franco, 8 Cristianos Santa Cruz De Tenerife 38650",
    "addr:housenumber":"8",
    "addr:postcode":"38650",
    "addr:street":"Calle De General Franco",
    "iso:country":"ES",
    "sg:address":"Calle de General Franco, 8",
    "sg:city":"Cristianos",
    "sg:orig_category":"Carnicer\u00cdas, Carnicer\u00cdas",
    "sg:phone":"+34 922 79 60 76",
    "sg:postcode":"38650",
    "sg:province":"Santa Cruz De Tenerife",
    "wof:name":"Simmelink  Archip",
    "wof:placetype":"venue"
},
  "geometry": {"coordinates":[-16.7155838013,28.0529975891],"type":"Point"}
}