{
  "type": "Feature",
  "properties": {
    "iso:country":"ES",
    "sg:address":"Calle de San Miguel, S/n",
    "sg:city":"Biota",
    "sg:orig_category":"Asociaciones, Organismos Culturales Y Socioeducativos",
    "sg:phone":"+34 976 67 01 37",
    "sg:postcode":"50695",
    "sg:province":"Zaragoza",
    "wof:name":"Ayuntamiento De Biota",
    "wof:placetype":"venue"
},
  "geometry": {"coordinates":[-1.1907989979,42.2605857849],"type":"Point"}
}