{
  "type": "Feature",
  "properties": {
    "addr:full":"Calle de Hermanos Machado, 1 Ayamonte Huelva 21400",
    "addr:housenumber":"1",
    "addr:postcode":"21400",
    "addr:street":"Calle De Hermanos Machado",
    "iso:country":"ES",
    "sg:address":"Calle de Hermanos Machado, 1",
    "sg:city":"Ayamonte",
    "sg:orig_category":"Ense\u00d1anza: Comercio, Gesti\u00d3n, Inform\u00c1tica",
    "sg:phone":"+34 959 47 19 47",
    "sg:postcode":"21400",
    "sg:province":"Huelva",
    "wof:name":"Martin Noriega Jose Manuel",
    "wof:placetype":"venue"
},
  "geometry": {"coordinates":[-7.4023637772,37.2106819153],"type":"Point"}
}