{
  "type": "Feature",
  "properties": {
    "iso:country":"ES",
    "sg:address":"Rua Principe, 49",
    "sg:city":"Vigo",
    "sg:orig_category":"Ingeniero",
    "sg:phone":"+34 986 22 64 36",
    "sg:postcode":"36202",
    "sg:province":"Pontevedra",
    "wof:name":"Fincas Fariza S.l.",
    "wof:placetype":"venue"
},
  "geometry": {"coordinates":[-8.7210683823,42.2363967896],"type":"Point"}
}