{
  "type": "Feature",
  "properties": {
    "iso:country":"ES",
    "sg:address":"Carr Arraval, 34",
    "sg:city":"Mao",
    "sg:classifiers":[
        {
            "category":"Autos & Motor Vehicles",
            "subcategory":"Automobile Sales",
            "type":"Retail Goods"
        }
    ],
    "sg:phone":"+34 971 36 33 27",
    "sg:postcode":"07701",
    "sg:province":"Islas Baleares",
    "wof:name":"Auto Escolas De Menorca S.l.",
    "wof:placetype":"venue"
},
  "geometry": {"coordinates":[4.2616176605,39.8896560669],"type":"Point"}
}