{
  "type": "Feature",
  "properties": {
    "iso:country":"ES",
    "sg:address":"Carrer de Anoia, 1",
    "sg:city":"Santa Perpetua De Mogoda",
    "sg:orig_category":"Trabajos De Perforaciones, Sondeos, Construcci\u00d3n De Pozos",
    "sg:phone":"+34 935 60 58 01",
    "sg:postcode":"08130",
    "sg:province":"Barcelona",
    "sg:website":"www.ceteigua.com",
    "wof:name":"Cata-igua S.l.",
    "wof:placetype":"venue"
},
  "geometry": {"coordinates":[2.1755599976,41.5544815063],"type":"Point"}
}