{
  "type": "Feature",
  "properties": {
    "iso:country":"ES",
    "sg:address":"La Gineta, 7",
    "sg:city":"Tarazona Mancha",
    "sg:orig_category":"Construcciones Met\u00c1licas",
    "sg:phone":"+34 967 48 06 61",
    "sg:postcode":"02100",
    "sg:province":"Albacete",
    "wof:name":"Bueno Cebrian S.a.",
    "wof:placetype":"venue"
},
  "geometry": {"coordinates":[-1.9154440165,39.2516098022],"type":"Point"}
}