{
  "type": "Feature",
  "properties": {
    "iso:country":"ES",
    "sg:address":"Avda Jorge Luis Borges, 2",
    "sg:city":"Malaga",
    "sg:orig_category":"Caf\u00c9s, Bares, Cervecer\u00cdas",
    "sg:phone":"+34 952 30 68 62",
    "sg:postcode":"29010",
    "sg:province":"M\u00e1laga",
    "wof:name":"Garcia Garcia Francisca",
    "wof:placetype":"venue"
},
  "geometry": {"coordinates":[-4.4557490349,36.7197380066],"type":"Point"}
}