{
  "type": "Feature",
  "properties": {
    "addr:full":"Carrer de Doctor Trueta, 128 Barcelona Barcelona 08005",
    "addr:housenumber":"128",
    "addr:postcode":"08005",
    "addr:street":"Carrer De Doctor Trueta",
    "iso:country":"ES",
    "sg:address":"Carrer de Doctor Trueta, 128",
    "sg:city":"Barcelona",
    "sg:orig_category":"Congelados: Productos Alimentarios (fabricaci\u00d3n, Al Por Mayor)",
    "sg:phone":"+34 932 25 02 74",
    "sg:postcode":"08005",
    "sg:province":"Barcelona",
    "wof:name":"Congelats M. Torras S.l.",
    "wof:placetype":"venue"
},
  "geometry": {"coordinates":[2.1989569664,41.3950576782],"type":"Point"}
}