{
  "type": "Feature",
  "properties": {
    "iso:country":"ES",
    "sg:address":"Calle de Petunia, 3",
    "sg:city":"San Borondon",
    "sg:orig_category":"Confecci\u00d3n De Trajes De Ba\u00d1o Y De Ropa De Playa",
    "sg:phone":"+34 928 13 32 14",
    "sg:postcode":"35212",
    "sg:province":"Las Palmas",
    "wof:name":"Brigitte Press S.l.",
    "wof:placetype":"venue"
},
  "geometry": {"coordinates":[-15.384888649,28.011505127],"type":"Point"}
}