{
  "type": "Feature",
  "properties": {
    "addr:full":"Pase Antigua (la), 1 Urdu\u00e7a-ordu\u00e7a Vizcaya 48460",
    "addr:housenumber":"1",
    "addr:postcode":"48460",
    "addr:street":"Antigua La",
    "iso:country":"ES",
    "sg:address":"Pase Antigua (la), 1",
    "sg:city":"Urdu\u00e7a-ordu\u00e7a",
    "sg:orig_category":"Doctores En Medicina",
    "sg:phone":"+34 945 38 34 00",
    "sg:postcode":"48460",
    "sg:province":"Vizcaya",
    "wof:name":"Gil Bengoa Francisco Javier",
    "wof:placetype":"venue"
},
  "geometry": {"coordinates":[-3.0069389343,42.9948730469],"type":"Point"}
}