{
  "type": "Feature",
  "properties": {
    "iso:country":"ES",
    "sg:address":"Calle de Guzman El Bueno, 67",
    "sg:city":"Madrid",
    "sg:orig_category":"Caf\u00c9s, Bares, Cervecer\u00cdas",
    "sg:phone":"+34 915 44 23 82",
    "sg:postcode":"28015",
    "sg:province":"Madrid",
    "wof:name":"Anton Carrillo Nicolas",
    "wof:placetype":"venue"
},
  "geometry": {"coordinates":[-3.7131314278,40.4361343384],"type":"Point"}
}