{
  "type": "Feature",
  "properties": {
    "iso:country":"ES",
    "sg:address":"Pol Ind Las Cruces, S/n",
    "sg:city":"Fines",
    "sg:orig_category":"Abrasivos Y Superabrasivos (fabricaci\u00d3n, Al Por Mayor)",
    "sg:phone":"+34 950 44 45 15",
    "sg:postcode":"04869",
    "sg:province":"Almer\u00eda",
    "wof:name":"Abradimar Sl",
    "wof:placetype":"venue"
},
  "geometry": {"coordinates":[-2.272888,37.371651],"type":"Point"}
}