{
  "type": "Feature",
  "properties": {
    "iso:country":"ES",
    "sg:address":"Pase Santa Maria De La Cabeza, 41",
    "sg:city":"Madrid",
    "sg:orig_category":"Alimentaci\u00d3n General (al Por Menor)",
    "sg:phone":"+34 914 68 29 15",
    "sg:postcode":"28045",
    "sg:province":"Madrid",
    "wof:name":"Von Berline Espinosa De Los Monteros Erika",
    "wof:placetype":"venue"
},
  "geometry": {"coordinates":[-3.6902165413,40.3954772949],"type":"Point"}
}