{
  "type": "Feature",
  "properties": {
    "addr:full":"Pg Saralegui, 110 Puerto De Pollen\u00c7a Islas Baleares 07470",
    "addr:housenumber":"110",
    "addr:postcode":"07470",
    "addr:street":"Pg Saralegui",
    "iso:country":"ES",
    "sg:address":"Pg Saralegui, 110",
    "sg:city":"Puerto De Pollen\u00c7a",
    "sg:orig_category":"Caf\u00c9s, Bares, Cervecer\u00cdas",
    "sg:phone":"+34 971 86 52 62",
    "sg:postcode":"07470",
    "sg:province":"Islas Baleares",
    "wof:name":"Martin Morillo Juan Jesus",
    "wof:placetype":"venue"
},
  "geometry": {"coordinates":[3.0806789398,39.9035148621],"type":"Point"}
}