{
  "type": "Feature",
  "properties": {
    "addr:full":"Carr Jacint Verdaguer, 8 Mollerussa Lleida 25230",
    "addr:housenumber":"8",
    "addr:postcode":"25230",
    "addr:street":"Carr Jacint Verdaguer",
    "iso:country":"ES",
    "sg:address":"Carr Jacint Verdaguer, 8",
    "sg:city":"Mollerussa",
    "sg:orig_category":"Art\u00cdculos De Regalo (al Por Menor)",
    "sg:phone":"+34 973 71 04 09",
    "sg:postcode":"25230",
    "sg:province":"Lleida",
    "wof:name":"Balcells Cos Maria Alba",
    "wof:placetype":"venue"
},
  "geometry": {"coordinates":[0.8946638703,41.629032135],"type":"Point"}
}