{
  "type": "Feature",
  "properties": {
    "iso:country":"ES",
    "sg:address":"Avda Ciudades (de Las), 102",
    "sg:city":"Getafe",
    "sg:orig_category":"Inmobiliaria (agencias)",
    "sg:phone":"+34 916 01 76 31",
    "sg:postcode":"28903",
    "sg:province":"Madrid",
    "wof:name":"Ali Aisa  Benaisa",
    "wof:placetype":"venue"
},
  "geometry": {"coordinates":[-3.7145192623,40.3130493164],"type":"Point"}
}