{
  "type": "Feature",
  "properties": {
    "iso:country":"ES",
    "sg:address":"C/ Cami (el), 29",
    "sg:city":"Alcoi",
    "sg:orig_category":"Protecci\u00d3n Contra Incendios: Material, Instalaci\u00d3n, Mantenimiento",
    "sg:phone":"+34 965 54 52 69",
    "sg:postcode":"03801",
    "sg:province":"Alicante",
    "wof:name":"Obiol Y Monllor S.l.",
    "wof:placetype":"venue"
},
  "geometry": {"coordinates":[-0.4746850133,38.693523407],"type":"Point"}
}