{
  "type": "Feature",
  "properties": {
    "addr:full":"Calle de Juan De Castilla, 1 Palencia Palencia 34001",
    "addr:housenumber":"1",
    "addr:postcode":"34001",
    "addr:street":"Calle De Juan De Castilla",
    "iso:country":"ES",
    "sg:address":"Calle de Juan De Castilla, 1",
    "sg:city":"Palencia",
    "sg:orig_category":"Alimentaci\u00d3n General (al Por Menor)",
    "sg:phone":"+34 979 74 21 39",
    "sg:postcode":"34001",
    "sg:province":"Palencia",
    "wof:name":"Curieses Sanz Fernando",
    "wof:placetype":"venue"
},
  "geometry": {"coordinates":[-4.5347819328,42.0114212036],"type":"Point"}
}