{
  "type": "Feature",
  "properties": {
    "addr:full":"Calle de Agustin Lara, 9 Granada Granada 18006",
    "addr:housenumber":"9",
    "addr:postcode":"18006",
    "addr:street":"Calle De Agustin Lara",
    "iso:country":"ES",
    "sg:address":"Calle de Agustin Lara, 9",
    "sg:city":"Granada",
    "sg:orig_category":"Caf\u00c9s, Bares, Cervecer\u00cdas",
    "sg:phone":"+34 958 81 22 52",
    "sg:postcode":"18006",
    "sg:province":"Granada",
    "wof:name":"Compa\u00f1ia Granadina De Telefonos A Monedas S.l.",
    "wof:placetype":"venue"
},
  "geometry": {"coordinates":[-3.59542799,37.1634902954],"type":"Point"}
}