{
  "type": "Feature",
  "properties": {
    "iso:country":"ES",
    "sg:address":"Calle de Puerto Del Rey, 8",
    "sg:city":"Madrid",
    "sg:orig_category":"Bibliotecas, Mediatecas",
    "sg:phone":"+34 915 51 07 83",
    "sg:postcode":"28038",
    "sg:province":"Madrid",
    "sg:website":"www.obrasocialcajamadrid.org",
    "wof:name":"Gecesa Gestion De Centros Culturales S.a",
    "wof:placetype":"venue"
},
  "geometry": {"coordinates":[-3.6629860401,40.4040145874],"type":"Point"}
}