{
  "type": "Feature",
  "properties": {
    "addr:full":"Calle de Chile, 41 Coslada Madrid 28820",
    "addr:housenumber":"41",
    "addr:postcode":"28820",
    "addr:street":"Calle De Chile",
    "iso:country":"ES",
    "sg:address":"Calle de Chile, 41",
    "sg:city":"Coslada",
    "sg:orig_category":"Muebles, Minoristas",
    "sg:phone":"+34 916 72 39 45",
    "sg:postcode":"28820",
    "sg:province":"Madrid",
    "wof:name":"Sanz Jimenez Felix",
    "wof:placetype":"venue"
},
  "geometry": {"coordinates":[-3.5462210178,40.4230194092],"type":"Point"}
}