{
  "type": "Feature",
  "properties": {
    "addr:full":"Carr Lepanto, 8 Badalona Barcelona 08914",
    "addr:housenumber":"8",
    "addr:postcode":"08914",
    "addr:street":"Carr Lepanto",
    "iso:country":"ES",
    "sg:address":"Carr Lepanto, 8",
    "sg:city":"Badalona",
    "sg:orig_category":"M\u00c9dicos: An\u00c1lisis Cl\u00cdnicos",
    "sg:phone":"+34 933 88 34 95",
    "sg:postcode":"08914",
    "sg:province":"Barcelona",
    "wof:name":"Pujol Tru\u00f1o Juan",
    "wof:placetype":"venue"
},
  "geometry": {"coordinates":[2.2450649738,41.4503440857],"type":"Point"}
}