{
  "type": "Feature",
  "properties": {
    "iso:country":"ES",
    "sg:address":"Carretera Madrid-coru\u00f1a, Km. 0336,0",
    "sg:city":"Combarros",
    "sg:orig_category":"Venta, Instalaci\u00d3n De Cocinas",
    "sg:phone":"+34 987 60 65 59",
    "sg:postcode":"24715",
    "sg:province":"Le\u00f3n",
    "wof:name":"Restaurante La Magdalena C.b.",
    "wof:placetype":"venue"
},
  "geometry": {"coordinates":[-6.126103878,42.5185203552],"type":"Point"}
}