{
  "type": "Feature",
  "properties": {
    "addr:full":"Avda Oporto, 17 Madrid Madrid 28019",
    "addr:housenumber":"17",
    "addr:postcode":"madrid;28019",
    "addr:street":"Avda Oporto",
    "iso:country":"ES",
    "sg:address":"Avda Oporto, 17",
    "sg:city":"Madrid",
    "sg:orig_category":"Inmobiliaria (agencias)",
    "sg:phone":"+34 914 69 71 73",
    "sg:postcode":"28019",
    "sg:province":"Madrid",
    "sg:website":"www.tecnocas.es/madrid/mdab4.htm",
    "wof:name":"Estudio Avenida Oporto S.l.",
    "wof:placetype":"venue"
},
  "geometry": {"coordinates":[-3.7225511074,40.3851318359],"type":"Point"}
}