{
  "type": "Feature",
  "properties": {
    "addr:full":"Carr Dr. Carles Pol I Aleu, 58 Sort Lleida 25560",
    "addr:housenumber":"58",
    "addr:postcode":"25560",
    "addr:street":"Carr Dr.;Pol;Aleu",
    "iso:country":"ES",
    "sg:address":"Carr Dr. Carles Pol I Aleu, 58",
    "sg:city":"Sort",
    "sg:orig_category":"Molduras, Junquillos, Listones Y Molduras Perforadas",
    "sg:phone":"+34 973 62 13 27",
    "sg:postcode":"25560",
    "sg:province":"Lleida",
    "wof:name":"Papapla S.l.",
    "wof:placetype":"venue"
},
  "geometry": {"coordinates":[1.1319500208,42.4144287109],"type":"Point"}
}