{
  "type": "Feature",
  "properties": {
    "addr:full":"Avda Rubios, 13 Matas-pinar-monte Rozas Madrid 28290",
    "addr:housenumber":"13",
    "addr:postcode":"28290",
    "addr:street":"Avda Rubios",
    "iso:country":"ES",
    "sg:address":"Avda Rubios, 13",
    "sg:city":"Matas-pinar-monte Rozas",
    "sg:orig_category":"Desinfecci\u00d3n, Desinsectaci\u00d3n, Desratizaci\u00d3n",
    "sg:phone":"+34 916 30 43 95",
    "sg:postcode":"28290",
    "sg:province":"Madrid",
    "wof:name":"S.i.g S.l",
    "wof:placetype":"venue"
},
  "geometry": {"coordinates":[-3.8965559006,40.5632324219],"type":"Point"}
}