{
  "type": "Feature",
  "properties": {
    "iso:country":"ES",
    "sg:address":"Pla\u00c7 Creu (de La), 25",
    "sg:city":"Tremp",
    "sg:orig_category":"Alimentaci\u00d3n General (al Por Menor)",
    "sg:phone":"+34 973 65 07 33",
    "sg:postcode":"25620",
    "sg:province":"Lleida",
    "wof:name":"Romero Claverol Luis",
    "wof:placetype":"venue"
},
  "geometry": {"coordinates":[0.8948950171,42.1686935425],"type":"Point"}
}