{
  "type": "Feature",
  "properties": {
    "addr:full":"Calle de Montearagon, 9 Madrid Madrid 28033",
    "addr:housenumber":"9",
    "addr:postcode":"madrid;28033",
    "addr:street":"Calle De Montearagon",
    "iso:country":"ES",
    "sg:address":"Calle de Montearagon, 9",
    "sg:city":"Madrid",
    "sg:classifiers":[
        {
            "category":"Manufacturing",
            "subcategory":"Building Materials",
            "type":"Manufacturing & Wholesale Goods"
        }
    ],
    "sg:phone":"+34 913 88 41 62",
    "sg:postcode":"28033",
    "sg:province":"Madrid",
    "sg:tags":[
        "cemento",
        "y",
        "de",
        "fabricaci\u00d3n",
        "cal"
    ],
    "wof:name":"Gestora De Cimentaciones Y Estructuras S.a.",
    "wof:placetype":"venue"
},
  "geometry": {"coordinates":[-3.6582450867,40.4634628296],"type":"Point"}
}