{
  "type": "Feature",
  "properties": {
    "addr:full":"Calle de Zubitxueta, 3 Barakaldo Vizcaya 48903",
    "addr:housenumber":"3",
    "addr:postcode":"48903",
    "addr:street":"Calle De Zubitxueta",
    "iso:country":"ES",
    "sg:address":"Calle de Zubitxueta, 3",
    "sg:city":"Barakaldo",
    "sg:orig_category":"Plomeros",
    "sg:phone":"+34 944 90 16 39",
    "sg:postcode":"48903",
    "sg:province":"Vizcaya",
    "wof:name":"Fontaneria Retuerto, S.l",
    "wof:placetype":"venue"
},
  "geometry": {"coordinates":[-2.9976119995,43.2860946655],"type":"Point"}
}