{
  "type": "Feature",
  "properties": {
    "iso:country":"ES",
    "sg:address":"Calle de Teobaldo Power, 26",
    "sg:city":"G\u00fcimar",
    "sg:orig_category":"Partidos Pol\u00cdticos",
    "sg:phone":"+34 922 51 24 56",
    "sg:postcode":"38500",
    "sg:province":"Santa Cruz De Tenerife",
    "wof:name":"Partido Popular",
    "wof:placetype":"venue"
},
  "geometry": {"coordinates":[-16.4120845795,28.3146476746],"type":"Point"}
}