{
  "type": "Feature",
  "properties": {
    "iso:country":"ES",
    "sg:address":"Cmno Ronda (de), 98",
    "sg:city":"Granada",
    "sg:orig_category":"Centros De Coordinaci\u00d3n",
    "sg:phone":"+34 958 26 65 63",
    "sg:postcode":"18004",
    "sg:province":"Granada",
    "wof:name":"Asesoria Olmedo Alguacil S.l.",
    "wof:placetype":"venue"
},
  "geometry": {"coordinates":[-3.6072573662,37.1725921631],"type":"Point"}
}