{
  "type": "Feature",
  "properties": {
    "addr:full":"Calle de Federico Garcia Lorca, 19 Jerez De La Frontera C\u00e1diz 11407",
    "addr:housenumber":"19",
    "addr:postcode":"11407",
    "addr:street":"Calle De Federico Garcia Lorca",
    "iso:country":"ES",
    "sg:address":"Calle de Federico Garcia Lorca, 19",
    "sg:city":"Jerez De La Frontera",
    "sg:orig_category":"Agencias Y Agentes Comerciales, Representantes",
    "sg:phone":"+34 956 18 20 77",
    "sg:postcode":"11407",
    "sg:province":"C\u00e1diz",
    "wof:name":"Gomez Verdugo Tomas",
    "wof:placetype":"venue"
},
  "geometry": {"coordinates":[-6.1358790398,36.699306488],"type":"Point"}
}