{
  "type": "Feature",
  "properties": {
    "iso:country":"ES",
    "sg:address":"Calle de Gran Via, 24",
    "sg:city":"Salamanca",
    "sg:orig_category":"Farmacias",
    "sg:phone":"+34 923 21 71 01",
    "sg:postcode":"37001",
    "sg:province":"Salamanca",
    "wof:name":"Avila Bardaji Pilar",
    "wof:placetype":"venue"
},
  "geometry": {"coordinates":[-5.6603097916,40.9656524658],"type":"Point"}
}