{
  "type": "Feature",
  "properties": {
    "addr:full":"Calle de Guillermo Pingarron, 36 Madrid Madrid 28018",
    "addr:housenumber":"36",
    "addr:postcode":"madrid;28018",
    "addr:street":"Calle De Guillermo Pingarron",
    "iso:country":"ES",
    "sg:address":"Calle de Guillermo Pingarron, 36",
    "sg:city":"Madrid",
    "sg:orig_category":"Cer\u00c1micas: Material Y Suministros",
    "sg:phone":"+34 917 78 46 14",
    "sg:postcode":"28018",
    "sg:province":"Madrid",
    "wof:name":"Plaza Heredia Victor",
    "wof:placetype":"venue"
},
  "geometry": {"coordinates":[-3.7057740688,40.42029953],"type":"Point"}
}