{
  "type": "Feature",
  "properties": {
    "addr:full":"Calle de Doctor Jose Manuel Pascual Y Pascual, 3 Cadiz C\u00e1diz 11008",
    "addr:housenumber":"3",
    "addr:postcode":"11008",
    "addr:street":"Calle De Doctor Jose Manuel Pascual Y Pascual",
    "iso:country":"ES",
    "sg:address":"Calle de Doctor Jose Manuel Pascual Y Pascual, 3",
    "sg:city":"Cadiz",
    "sg:orig_category":"Trabajos De Topograf\u00cda",
    "sg:phone":"+34 956 25 72 52",
    "sg:postcode":"11008",
    "sg:province":"C\u00e1diz",
    "wof:name":"Hydrocar S. A.",
    "wof:placetype":"venue"
},
  "geometry": {"coordinates":[-6.2828040123,36.5182991028],"type":"Point"}
}