{
  "type": "Feature",
  "properties": {
    "addr:full":"El Tercio, 10 Badajoz Badajoz 06002",
    "addr:housenumber":"10",
    "addr:postcode":"06002",
    "iso:country":"ES",
    "sg:address":"El Tercio, 10",
    "sg:city":"Badajoz",
    "sg:orig_category":"Alimentaci\u00d3n General (al Por Menor)",
    "sg:phone":"+34 924 22 10 53",
    "sg:postcode":"06002",
    "sg:province":"Badajoz",
    "wof:name":"Martin Prieto Clodomiro",
    "wof:placetype":"venue"
},
  "geometry": {"coordinates":[-6.9726238251,38.874835968],"type":"Point"}
}