{
  "type": "Feature",
  "properties": {
    "iso:country":"ES",
    "sg:address":"Pase Profesor Veremundo Nu\u00d1ez (del), 15",
    "sg:city":"Bembibre",
    "sg:orig_category":"Ense\u00d1anza, Formaci\u00d3n Profesional: Aprendizaje",
    "sg:phone":"+34 987 51 00 32",
    "sg:postcode":"24300",
    "sg:province":"Le\u00f3n",
    "wof:name":"Ayuntamiento De Bembibre",
    "wof:placetype":"venue"
},
  "geometry": {"coordinates":[-6.4167990685,42.614944458],"type":"Point"}
}