{
  "type": "Feature",
  "properties": {
    "addr:full":"Carr Anselm Claver, 8 Arbeca Lleida 25140",
    "addr:housenumber":"8",
    "addr:postcode":"25140",
    "addr:street":"Carr Anselm Claver",
    "iso:country":"ES",
    "sg:address":"Carr Anselm Claver, 8",
    "sg:city":"Arbeca",
    "sg:orig_category":"M\u00c9dicos: Estomatolog\u00cda",
    "sg:phone":"+34 973 14 91 21",
    "sg:postcode":"25140",
    "sg:province":"Lleida",
    "wof:name":"Mias Balaguero Oriol",
    "wof:placetype":"venue"
},
  "geometry": {"coordinates":[0.9258469939,41.540977478],"type":"Point"}
}