{
  "type": "Feature",
  "properties": {
    "iso:country":"ES",
    "sg:address":"Carr Maria Angels Vayreda, 3",
    "sg:city":"Figueres",
    "sg:orig_category":"Art\u00cdculos De Regalo (al Por Menor)",
    "sg:phone":"+34 972 50 93 82",
    "sg:postcode":"17600",
    "sg:province":"Girona",
    "wof:name":"Thomas Vila Maria Luisa",
    "wof:placetype":"venue"
},
  "geometry": {"coordinates":[2.95966506,42.2677459717],"type":"Point"}
}