{
  "type": "Feature",
  "properties": {
    "iso:country":"ES",
    "sg:address":"Calle de Real Baja, 10",
    "sg:city":"Majadahonda",
    "sg:orig_category":"Cristaler\u00cda: Suministros",
    "sg:phone":"+34 916 38 32 54",
    "sg:postcode":"28220",
    "sg:province":"Madrid",
    "wof:name":"Rivas Colmenarejo Teodoro",
    "wof:placetype":"venue"
},
  "geometry": {"coordinates":[-3.8727509975,40.4720306396],"type":"Point"}
}