{
  "type": "Feature",
  "properties": {
    "iso:country":"ES",
    "sg:address":"Calle de Mercedes De La Cardiniere, 36",
    "sg:city":"Pozuelo De Alarcon",
    "sg:orig_category":"Financiaci\u00d3n Y Cr\u00c9ditos",
    "sg:phone":"+34 913 51 01 38",
    "sg:postcode":"28223",
    "sg:province":"Madrid",
    "wof:name":"C.v.r.gestion Y Finanzas S.l.",
    "wof:placetype":"venue"
},
  "geometry": {"coordinates":[-3.8186349869,40.4305419922],"type":"Point"}
}