{
  "type": "Feature",
  "properties": {
    "iso:country":"ES",
    "sg:address":"Carrer de Maria Fortuny, 11",
    "sg:city":"Sabadell",
    "sg:orig_category":"Librer\u00cdas",
    "sg:phone":"+34 937 27 57 94",
    "sg:postcode":"08202",
    "sg:province":"Barcelona",
    "wof:name":"Tapide S.a.",
    "wof:placetype":"venue"
},
  "geometry": {"coordinates":[2.108839035,41.5486526489],"type":"Point"}
}