{
  "type": "Feature",
  "properties": {
    "addr:full":"Carrer de Anselm Turmeda, 23 Sabadell Barcelona 08205",
    "addr:housenumber":"23",
    "addr:postcode":"08205",
    "addr:street":"Carrer De Anselm Turmeda",
    "iso:country":"ES",
    "sg:address":"Carrer de Anselm Turmeda, 23",
    "sg:city":"Sabadell",
    "sg:orig_category":"Tapicer\u00cdas",
    "sg:phone":"+34 937 10 15 85",
    "sg:postcode":"08205",
    "sg:province":"Barcelona",
    "wof:name":"Tapicort S. A.",
    "wof:placetype":"venue"
},
  "geometry": {"coordinates":[2.0998799801,41.528377533],"type":"Point"}
}