{
  "type": "Feature",
  "properties": {
    "addr:full":"Calle de Salvador De Madariaga, 8 Santa Maria De Gracia Murcia 30009",
    "addr:housenumber":"8",
    "addr:postcode":"30009",
    "addr:street":"Calle De Salvador De Madariaga",
    "iso:country":"ES",
    "sg:address":"Calle de Salvador De Madariaga, 8",
    "sg:city":"Santa Maria De Gracia",
    "sg:orig_category":"Inform\u00c1tica (estudios, Servicios, Asesor\u00cda, Formaci\u00d3n)",
    "sg:phone":"+34 968 28 29 39",
    "sg:postcode":"30009",
    "sg:province":"Murcia",
    "wof:name":"Levan Cifmar Infor S.l.",
    "wof:placetype":"venue"
},
  "geometry": {"coordinates":[-1.1528439522,37.9883460999],"type":"Point"}
}