{
  "type": "Feature",
  "properties": {
    "addr:full":"Calle de Tizon (el), 6 San Cristobal De La Laguna Santa Cruz De Tenerife 38202",
    "addr:housenumber":"6",
    "addr:postcode":"38202",
    "addr:street":"Calle De Tizon El",
    "iso:country":"ES",
    "sg:address":"Calle de Tizon (el), 6",
    "sg:city":"San Cristobal De La Laguna",
    "sg:orig_category":"Peluquer\u00cdas, Peluquer\u00cda Mixta",
    "sg:phone":"+34 922 26 64 67",
    "sg:postcode":"38202",
    "sg:province":"Santa Cruz De Tenerife",
    "wof:name":"Due Peluqueros",
    "wof:placetype":"venue"
},
  "geometry": {"coordinates":[-16.3233699799,28.4907398224],"type":"Point"}
}