{
  "type": "Feature",
  "properties": {
    "iso:country":"ES",
    "sg:address":"Calle de Grande, 3",
    "sg:city":"Guare\u00f1a",
    "sg:orig_category":"Caf\u00c9s, Bares, Cervecer\u00cdas",
    "sg:phone":"+34 924 35 04 75",
    "sg:postcode":"06470",
    "sg:province":"Badajoz",
    "wof:name":"Vazrod S.l.",
    "wof:placetype":"venue"
},
  "geometry": {"coordinates":[-6.102312088,38.8593902588],"type":"Point"}
}