{
  "type": "Feature",
  "properties": {
    "addr:full":"Carrer de Josep Maria De Sagarra, 66 Granollers Barcelona 08402",
    "addr:housenumber":"66",
    "addr:postcode":"08402",
    "addr:street":"Carrer De Josep Maria De Sagarra",
    "iso:country":"ES",
    "sg:address":"Carrer de Josep Maria De Sagarra, 66",
    "sg:city":"Granollers",
    "sg:orig_category":"Grafistas",
    "sg:phone":"+34 938 60 01 53",
    "sg:postcode":"08402",
    "sg:province":"Barcelona",
    "sg:website":"www.magir-art.net",
    "wof:name":"Castillo Martinez Joan",
    "wof:placetype":"venue"
},
  "geometry": {"coordinates":[2.2952070236,41.6108779907],"type":"Point"}
}