{
  "type": "Feature",
  "properties": {
    "addr:full":"Nuestra Se\u00f1ora De Monserrat, S/n Zafra Badajoz 06300",
    "addr:housenumber":"s / n",
    "addr:postcode":"06300",
    "iso:country":"ES",
    "sg:address":"Nuestra Se\u00f1ora De Monserrat, S/n",
    "sg:city":"Zafra",
    "sg:orig_category":"Iglesia Cat\u00d3lica",
    "sg:phone":"+34 924 55 25 52",
    "sg:postcode":"06300",
    "sg:province":"Badajoz",
    "wof:name":"Parroquia De San Miguel",
    "wof:placetype":"venue"
},
  "geometry": {"coordinates":[-6.4134092331,38.4236793518],"type":"Point"}
}