{
  "type": "Feature",
  "properties": {
    "iso:country":"ES",
    "sg:address":"Calle de Jose Maria Manresa, 20",
    "sg:city":"S. Fulgencio",
    "sg:orig_category":"Cajas Para Embalar",
    "sg:phone":"+34 966 79 44 37",
    "sg:postcode":"03177",
    "sg:province":"Alicante",
    "wof:name":"Caja Rural Del Mediterraneo Ruralcaja S Coop De Credito",
    "wof:placetype":"venue"
},
  "geometry": {"coordinates":[-0.7186350226,38.112991333],"type":"Point"}
}