{
  "type": "Feature",
  "properties": {
    "iso:country":"ES",
    "sg:address":"Av Generalitat, 14",
    "sg:city":"Campello",
    "sg:orig_category":"Cajas De Ahorro",
    "sg:phone":"+34 965 63 41 12",
    "sg:postcode":"03560",
    "sg:province":"Alicante",
    "wof:name":"Caja De Ahorros De Valencia Castellon Y Alicante",
    "wof:placetype":"venue"
},
  "geometry": {"coordinates":[-0.3975949883,38.4270515442],"type":"Point"}
}