{
  "type": "Feature",
  "properties": {
    "addr:full":"Calle de San Andres, 72 Coru\u00d1a La Coru\u00f1a 15003",
    "addr:housenumber":"72",
    "addr:postcode":"15003",
    "addr:street":"Calle De San Andres;Corun\u0303A",
    "iso:country":"ES",
    "sg:address":"Calle de San Andres, 72",
    "sg:city":"Coru\u00d1a",
    "sg:orig_category":"Fabricaci\u00d3n De Productos Textiles Sin Tejer",
    "sg:phone":"+34 981 22 14 27",
    "sg:postcode":"15003",
    "sg:province":"La Coru\u00f1a",
    "wof:name":"Renda Carral Antonia",
    "wof:placetype":"venue"
},
  "geometry": {"coordinates":[-8.4032859802,43.369934082],"type":"Point"}
}