{
  "type": "Feature",
  "properties": {
    "iso:country":"ES",
    "sg:address":"Calle de Madrid, 54",
    "sg:city":"Burgos",
    "sg:orig_category":"Institutos De Belleza",
    "sg:phone":"+34 947 26 81 06",
    "sg:postcode":"09001",
    "sg:province":"Burgos",
    "sg:website":"www.paginasamarillas.es",
    "wof:name":"Val Trascasa Felix Del",
    "wof:placetype":"venue"
},
  "geometry": {"coordinates":[-3.7002670765,42.3309516907],"type":"Point"}
}