{
  "type": "Feature",
  "properties": {
    "addr:full":"Calle de Becquer, 7 Cehegin Murcia 30430",
    "addr:housenumber":"7",
    "addr:postcode":"30430",
    "addr:street":"Calle De Becquer",
    "iso:country":"ES",
    "sg:address":"Calle de Becquer, 7",
    "sg:city":"Cehegin",
    "sg:orig_category":"Electricidad: Instaladores",
    "sg:phone":"+34 968 74 04 16",
    "sg:postcode":"30430",
    "sg:province":"Murcia",
    "wof:name":"Irluz S.l.",
    "wof:placetype":"venue"
},
  "geometry": {"coordinates":[-1.7954870462,38.0968322754],"type":"Point"}
}