{
  "type": "Feature",
  "properties": {
    "iso:country":"ES",
    "sg:address":"Calle de Miguel Villanueva, 4",
    "sg:city":"Logro\u00f1o",
    "sg:orig_category":"Abogados",
    "sg:phone":"+34 941 25 22 66",
    "sg:postcode":"26001",
    "sg:province":"La Rioja",
    "wof:name":"Saez Morga Abogados C.b",
    "wof:placetype":"venue"
},
  "geometry": {"coordinates":[-2.4458758831,42.464012146],"type":"Point"}
}