{
  "type": "Feature",
  "properties": {
    "addr:full":"Carrer de Gabriel Cortes, 6 Indioteria Islas Baleares 07009",
    "addr:housenumber":"6",
    "addr:postcode":"07009",
    "addr:street":"Carrer De Gabriel Cortes;Islas",
    "iso:country":"ES",
    "sg:address":"Carrer de Gabriel Cortes, 6",
    "sg:city":"Indioteria",
    "sg:orig_category":"Alquiler De V\u00cddeo",
    "sg:phone":"+34 971 43 30 52",
    "sg:postcode":"07009",
    "sg:province":"Islas Baleares",
    "wof:name":"Ruzmar C.b.",
    "wof:placetype":"venue"
},
  "geometry": {"coordinates":[2.6778950691,39.6069946289],"type":"Point"}
}