{
  "type": "Feature",
  "properties": {
    "iso:country":"ES",
    "sg:address":"As Cabazas, 1",
    "sg:city":"Cabazas",
    "sg:orig_category":"Material Y Herramientas Agr\u00cdcolas",
    "sg:phone":"+34 981 74 11 28",
    "sg:postcode":"15127",
    "sg:province":"La Coru\u00f1a",
    "wof:name":"Cancela Amigo Juan",
    "wof:placetype":"venue"
},
  "geometry": {"coordinates":[-8.95773983,43.1091461182],"type":"Point"}
}