{
  "type": "Feature",
  "properties": {
    "iso:country":"ES",
    "sg:address":"Av Marina, 78",
    "sg:city":"S. Boi Llobregat",
    "sg:orig_category":"Arquitectos",
    "sg:phone":"+34 936 54 07 55",
    "sg:postcode":"08830",
    "sg:province":"Barcelona",
    "wof:name":"Arteco Coordinaciones S.l.",
    "wof:placetype":"venue"
},
  "geometry": {"coordinates":[2.036870718,41.3229217529],"type":"Point"}
}