{
  "type": "Feature",
  "properties": {
    "addr:full":"Carrer de Tavern, 64 Barcelona Barcelona 08006",
    "addr:housenumber":"64",
    "addr:postcode":"08006",
    "addr:street":"Carrer De Tavern",
    "iso:country":"ES",
    "sg:address":"Carrer de Tavern, 64",
    "sg:city":"Barcelona",
    "sg:orig_category":"Molduras, Junquillos, Listones Y Molduras Perforadas",
    "sg:phone":"+34 932 00 05 67",
    "sg:postcode":"08006",
    "sg:province":"Barcelona",
    "wof:name":"Martinez Mu\u00f1oz Maria Isabel",
    "wof:placetype":"venue"
},
  "geometry": {"coordinates":[2.1425299644,41.4006462097],"type":"Point"}
}