{
  "type": "Feature",
  "properties": {
    "iso:country":"ES",
    "sg:address":"Carrer de Corral De Sauner (del), 12",
    "sg:city":"Cap De Salou-nostra Senyora De Nuria",
    "sg:orig_category":"Empresarios Y Productoras De Espect\u00c1culos",
    "sg:phone":"+34 977 37 30 34",
    "sg:postcode":"43840",
    "sg:province":"Tarragona",
    "wof:name":"Morell  Daniel",
    "wof:placetype":"venue"
},
  "geometry": {"coordinates":[1.172639966,41.0635795593],"type":"Point"}
}