{
  "type": "Feature",
  "properties": {
    "addr:full":"Calle de Sargazos, S/n Huelva Huelva 21007",
    "addr:housenumber":"s / n",
    "addr:postcode":"21007",
    "addr:street":"Calle De Sargazos",
    "iso:country":"ES",
    "sg:address":"Calle de Sargazos, S/n",
    "sg:city":"Huelva",
    "sg:orig_category":"Promotores Constructores",
    "sg:phone":"+34 959 22 30 07",
    "sg:postcode":"21007",
    "sg:province":"Huelva",
    "wof:name":"Quinto S.a.",
    "wof:placetype":"venue"
},
  "geometry": {"coordinates":[-6.934109211,37.2547111511],"type":"Point"}
}