{
  "type": "Feature",
  "properties": {
    "iso:country":"ES",
    "sg:address":"Avda Juan Sebastian Elcano, 193",
    "sg:city":"Malaga",
    "sg:orig_category":"Bancos",
    "sg:phone":"+34 952 20 00 54",
    "sg:postcode":"29017",
    "sg:province":"M\u00e1laga",
    "sg:website":"www.bancoatlantico.es",
    "wof:name":"Banc Sabadell S.a.",
    "wof:placetype":"venue"
},
  "geometry": {"coordinates":[-4.3616352081,36.721282959],"type":"Point"}
}