{
  "type": "Feature",
  "properties": {
    "addr:full":"Trva Laurel-tajadas, S/n Corella Navarra 31591",
    "addr:housenumber":"s",
    "addr:postcode":"31591",
    "addr:street":"Trva Laurel-Tajadas;/ N",
    "iso:country":"ES",
    "sg:address":"Trva Laurel-tajadas, S/n",
    "sg:city":"Corella",
    "sg:orig_category":"Trajes Y Adornos De Boda (confecci\u00d3n, Al Por Menor)",
    "sg:phone":"+34 948 78 09 34",
    "sg:postcode":"31591",
    "sg:province":"Navarra",
    "wof:name":"Rodas Novias S.l.",
    "wof:placetype":"venue"
},
  "geometry": {"coordinates":[-1.7873059511,42.1155853271],"type":"Point"}
}