{
  "type": "Feature",
  "properties": {
    "iso:country":"ES",
    "sg:address":"Calle de Angel, 8",
    "sg:city":"Madrid",
    "sg:orig_category":"Electricidad (montaje, Ensamblaje De Componentes)",
    "sg:phone":"+34 913 65 60 53",
    "sg:postcode":"28005",
    "sg:province":"Madrid",
    "wof:name":"Gomez Gutierrez Felix",
    "wof:placetype":"venue"
},
  "geometry": {"coordinates":[-3.7123162746,40.4101257324],"type":"Point"}
}