{
  "type": "Feature",
  "properties": {
    "addr:full":"Carr Major, S/n Santa Pau Girona 17811",
    "addr:housenumber":"s / n",
    "addr:postcode":"17811",
    "addr:street":"Carr Major",
    "iso:country":"ES",
    "sg:address":"Carr Major, S/n",
    "sg:city":"Santa Pau",
    "sg:orig_category":"Cajas De Ahorro",
    "sg:phone":"+34 972 68 01 61",
    "sg:postcode":"17811",
    "sg:province":"Girona",
    "wof:name":"Caixa De Girona",
    "wof:placetype":"venue"
},
  "geometry": {"coordinates":[2.5696589947,42.1450805664],"type":"Point"}
}