{
  "type": "Feature",
  "properties": {
    "iso:country":"ES",
    "sg:address":"Calle de Monse\u00d1or Rouco Varela, 6",
    "sg:city":"Vilalba",
    "sg:classifiers":[
        {
            "category":"Taxi",
            "type":"Transportation"
        }
    ],
    "sg:phone":"+34 982 51 06 63",
    "sg:postcode":"27800",
    "sg:province":"Lugo",
    "wof:name":"Pardo Pardo Luis",
    "wof:placetype":"venue"
},
  "geometry": {"coordinates":[-7.6800031662,43.293838501],"type":"Point"}
}