{
  "type": "Feature",
  "properties": {
    "addr:full":"Calle de Bellavista, 3 Alcala Henares Madrid 28804",
    "addr:housenumber":"3",
    "addr:postcode":"28804",
    "addr:street":"Calle De Bellavista",
    "iso:country":"ES",
    "sg:address":"Calle de Bellavista, 3",
    "sg:city":"Alcala Henares",
    "sg:orig_category":"Molduras, Junquillos, Listones Y Molduras Perforadas",
    "sg:phone":"+34 918 81 67 59",
    "sg:postcode":"28804",
    "sg:province":"Madrid",
    "wof:name":"Mendez Rodriguez Guillermo",
    "wof:placetype":"venue"
},
  "geometry": {"coordinates":[-3.3551392555,40.4816246033],"type":"Point"}
}