{
  "type": "Feature",
  "properties": {
    "iso:country":"ES",
    "sg:address":"Calle de Constitucion (de La), 42",
    "sg:city":"Alcobendas",
    "sg:orig_category":"Confecci\u00d3n (fabricaci\u00d3n, Al Por Mayor)",
    "sg:phone":"+34 916 52 69 85",
    "sg:postcode":"28100",
    "sg:province":"Madrid",
    "wof:name":"Carbon Martin Crescenciano",
    "wof:placetype":"venue"
},
  "geometry": {"coordinates":[-3.6368479729,40.5426254272],"type":"Point"}
}