{
  "type": "Feature",
  "properties": {
    "iso:country":"ES",
    "sg:address":"Rua Urzaiz, 55",
    "sg:city":"Vigo",
    "sg:orig_category":"Frutas Y Legumbres Frescas (al Por Mayor)",
    "sg:phone":"+34 986 22 84 44",
    "sg:postcode":"36201",
    "sg:province":"Pontevedra",
    "wof:name":"Frutas Nieves S.l.",
    "wof:placetype":"venue"
},
  "geometry": {"coordinates":[-8.7159433365,42.2344360352],"type":"Point"}
}