{
  "type": "Feature",
  "properties": {
    "addr:full":"Carrer de Hercegovina, 19 Barcelona Barcelona 08006",
    "addr:housenumber":"19",
    "addr:postcode":"08006",
    "addr:street":"Carrer De Hercegovina",
    "iso:country":"ES",
    "sg:address":"Carrer de Hercegovina, 19",
    "sg:city":"Barcelona",
    "sg:orig_category":"Partidos Pol\u00cdticos",
    "sg:phone":"+34 934 14 67 41",
    "sg:postcode":"08006",
    "sg:province":"Barcelona",
    "wof:name":"Convergencia Democratica De Catalunya",
    "wof:placetype":"venue"
},
  "geometry": {"coordinates":[2.1392109394,41.402633667],"type":"Point"}
}