{
  "type": "Feature",
  "properties": {
    "addr:full":"Calle de Ribera Del Najerilla, 39 Najera La Rioja 26300",
    "addr:housenumber":"39",
    "addr:postcode":"26300",
    "addr:street":"Calle De Ribera Del Najerilla;Rioja",
    "iso:country":"ES",
    "sg:address":"Calle de Ribera Del Najerilla, 39",
    "sg:city":"Najera",
    "sg:orig_category":"Mec\u00c1nico Del Autom\u00d3vil",
    "sg:phone":"+34 941 36 27 69",
    "sg:postcode":"26300",
    "sg:province":"La Rioja",
    "wof:name":"Salinas Alvarez Elba",
    "wof:placetype":"venue"
},
  "geometry": {"coordinates":[-2.7335329056,42.4184188843],"type":"Point"}
}