{
  "type": "Feature",
  "properties": {
    "addr:full":"Avda Rubine, 8 Coru\u00d1a La Coru\u00f1a 15004",
    "addr:housenumber":"8",
    "addr:postcode":"15004",
    "addr:street":"Avda Rubine;La Corun\u0303A",
    "iso:country":"ES",
    "sg:address":"Avda Rubine, 8",
    "sg:city":"Coru\u00d1a",
    "sg:orig_category":"Inmobiliaria (agencias)",
    "sg:phone":"+34 981 27 27 35",
    "sg:postcode":"15004",
    "sg:province":"La Coru\u00f1a",
    "wof:name":"Construcuatro S.a.",
    "wof:placetype":"venue"
},
  "geometry": {"coordinates":[-8.409160614,43.3679428101],"type":"Point"}
}