{
  "type": "Feature",
  "properties": {
    "addr:full":"Urb. Risco, 16 Cebreros \u00c1vila 05260",
    "addr:housenumber":"16",
    "addr:postcode":"05260",
    "addr:street":"Risco",
    "iso:country":"ES",
    "sg:address":"Urb. Risco, 16",
    "sg:city":"Cebreros",
    "sg:orig_category":"Empresas De Impermeabilizaci\u00d3n",
    "sg:phone":"+34 918 63 09 75",
    "sg:postcode":"05260",
    "sg:province":"\u00c1vila",
    "wof:name":"Impermeabilizaciones Avila S.l.",
    "wof:placetype":"venue"
},
  "geometry": {"coordinates":[-4.4648017883,40.4579963684],"type":"Point"}
}