{
  "type": "Feature",
  "properties": {
    "iso:country":"ES",
    "sg:address":"Calle de Mayor, 2",
    "sg:city":"Alcorcon",
    "sg:orig_category":"Ropa Para Se\u00d1oras (al Por Menor)",
    "sg:phone":"+34 916 11 47 64",
    "sg:postcode":"28921",
    "sg:province":"Madrid",
    "wof:name":"Sanz Hernando Concepcion Blanca",
    "wof:placetype":"venue"
},
  "geometry": {"coordinates":[-3.828068018,40.3487548828],"type":"Point"}
}