{
  "type": "Feature",
  "properties": {
    "addr:full":"Pg Manuel Girona, 56 Barcelona Barcelona 08034",
    "addr:housenumber":"56",
    "addr:postcode":"08034",
    "addr:street":"Pg Manuel Girona",
    "iso:country":"ES",
    "sg:address":"Pg Manuel Girona, 56",
    "sg:city":"Barcelona",
    "sg:orig_category":"Bisuter\u00cda, Joyer\u00cda, Relojer\u00cda (al Por Menor)",
    "sg:phone":"+34 932 03 10 70",
    "sg:postcode":"08034",
    "sg:province":"Barcelona",
    "wof:name":"Diyarban S.l.",
    "wof:placetype":"venue"
},
  "geometry": {"coordinates":[2.1253249645,41.3912467957],"type":"Point"}
}