{
  "type": "Feature",
  "properties": {
    "iso:country":"ES",
    "sg:address":"Calle de Plaza (de La), 119",
    "sg:city":"Pto Real",
    "sg:orig_category":"\u00d3ptica: Instrumentos (fabricaci\u00d3n)",
    "sg:phone":"+34 956 83 08 51",
    "sg:postcode":"11510",
    "sg:province":"C\u00e1diz",
    "wof:name":"Barbado Jimenez Manuel Ramiro",
    "wof:placetype":"venue"
},
  "geometry": {"coordinates":[-6.1906681061,36.5279045105],"type":"Point"}
}