{
  "type": "Feature",
  "properties": {
    "addr:full":"Calle de Catalu\u00d1a, 6 Getafe Madrid 28903",
    "addr:housenumber":"6",
    "addr:postcode":"28903",
    "addr:street":"Calle De Catalun\u0303A",
    "iso:country":"ES",
    "sg:address":"Calle de Catalu\u00d1a, 6",
    "sg:city":"Getafe",
    "sg:orig_category":"Muebles, Minoristas",
    "sg:phone":"+34 916 82 39 29",
    "sg:postcode":"28903",
    "sg:province":"Madrid",
    "wof:name":"Sanchez Alonso Candido",
    "wof:placetype":"venue"
},
  "geometry": {"coordinates":[-3.7228899002,40.3125495911],"type":"Point"}
}