{
  "type": "Feature",
  "properties": {
    "iso:country":"ES",
    "sg:address":"Calle de Estartetxe, 7",
    "sg:city":"Leioa",
    "sg:orig_category":"Tintes (fabricaci\u00d3n, Al Por Mayor)",
    "sg:phone":"+34 944 31 63 57",
    "sg:postcode":"48940",
    "sg:province":"Vizcaya",
    "wof:name":"Tintoreria Linsay, S.l.",
    "wof:placetype":"venue"
},
  "geometry": {"coordinates":[-2.9884870052,43.3268814087],"type":"Point"}
}