{
  "type": "Feature",
  "properties": {
    "iso:country":"ES",
    "sg:address":"Carrer de Foners, 54",
    "sg:city":"Palma",
    "sg:orig_category":"Molduras, Junquillos, Listones Y Molduras Perforadas",
    "sg:phone":"+34 971 46 45 58",
    "sg:postcode":"07006",
    "sg:province":"Islas Baleares",
    "wof:name":"Ortiz Montejano Jose Antonio",
    "wof:placetype":"venue"
},
  "geometry": {"coordinates":[2.6624360085,39.5676040649],"type":"Point"}
}