{
  "type": "Feature",
  "properties": {
    "addr:full":"Calle de Erribera, 30 Ondarroa Vizcaya 48700",
    "addr:housenumber":"30",
    "addr:postcode":"48700",
    "addr:street":"Calle De Erribera",
    "iso:country":"ES",
    "sg:address":"Calle de Erribera, 30",
    "sg:city":"Ondarroa",
    "sg:orig_category":"Carnicer\u00cdas, Carnicer\u00cdas",
    "sg:phone":"+34 946 83 03 47",
    "sg:postcode":"48700",
    "sg:province":"Vizcaya",
    "wof:name":"Eguskizaga Gastelu Nerea",
    "wof:placetype":"venue"
},
  "geometry": {"coordinates":[-2.4224779606,43.3203048706],"type":"Point"}
}