{
  "type": "Feature",
  "properties": {
    "iso:country":"ES",
    "sg:address":"Carr Major, 25",
    "sg:city":"Colonia S. Jordi",
    "sg:orig_category":"Albergues",
    "sg:phone":"+34 971 65 52 56",
    "sg:postcode":"07638",
    "sg:province":"Islas Baleares",
    "wof:name":"Rodriguez Camacho Vicente",
    "wof:placetype":"venue"
},
  "geometry": {"coordinates":[2.9928250313,39.3186759949],"type":"Point"}
}