{
  "type": "Feature",
  "properties": {
    "addr:full":"Pase Fresquera (de La), 28 Villarejo Del Valle \u00c1vila 05413",
    "addr:postcode":"05413",
    "addr:street":"A\u0301Vila",
    "iso:country":"ES",
    "sg:address":"Pase Fresquera (de La), 28",
    "sg:city":"Villarejo Del Valle",
    "sg:orig_category":"Promotores Constructores",
    "sg:phone":"+34 920 38 32 93",
    "sg:postcode":"05413",
    "sg:province":"\u00c1vila",
    "wof:name":"Instalaciones Agustino S.l.",
    "wof:placetype":"venue"
},
  "geometry": {"coordinates":[-4.9964318275,40.285949707],"type":"Point"}
}