{
  "type": "Feature",
  "properties": {
    "addr:full":"Calle de Manuel Jontoya, 6 Jaen Ja\u00e9n 23001",
    "addr:housenumber":"6;jae\u0301n",
    "addr:postcode":"23001",
    "addr:street":"Calle De Manuel Jontoya",
    "iso:country":"ES",
    "sg:address":"Calle de Manuel Jontoya, 6",
    "sg:city":"Jaen",
    "sg:orig_category":"Fabricaci\u00d3n, Instalaci\u00d3n De Armarios",
    "sg:phone":"+34 953 23 82 97",
    "sg:postcode":"23001",
    "sg:province":"Ja\u00e9n",
    "wof:name":"Estudio Armario S.l.",
    "wof:placetype":"venue"
},
  "geometry": {"coordinates":[-3.7887589931,37.7646713257],"type":"Point"}
}