{
  "type": "Feature",
  "properties": {
    "iso:country":"ES",
    "sg:address":"Calle de Solana Baja, S/n",
    "sg:city":"Camporredondo",
    "sg:orig_category":"Patatas (al Por Mayor)",
    "sg:phone":"+34 983 69 41 52",
    "sg:postcode":"47165",
    "sg:province":"Valladolid",
    "wof:name":"Juan Carlos Bustos Criado Y Hermanos C.b",
    "wof:placetype":"venue"
},
  "geometry": {"coordinates":[-4.5039157867,41.4730758667],"type":"Point"}
}