{
  "type": "Feature",
  "properties": {
    "addr:full":"Calle de Orfeo, 12 Roquetas Mar Almer\u00eda 04740",
    "addr:housenumber":"12",
    "addr:postcode":"04740",
    "addr:street":"Calle De Orfeo",
    "iso:country":"ES",
    "sg:address":"Calle de Orfeo, 12",
    "sg:city":"Roquetas Mar",
    "sg:orig_category":"Electricidad, Electr\u00d3nica: Suministros (al Por Menor)",
    "sg:phone":"+34 950 32 18 76",
    "sg:postcode":"04740",
    "sg:province":"Almer\u00eda",
    "sg:website":"www.multitronica.com",
    "wof:name":"Multitronica Roquetas S.l.u.",
    "wof:placetype":"venue"
},
  "geometry": {"coordinates":[-2.6109609604,36.7641143799],"type":"Point"}
}