{
  "type": "Feature",
  "properties": {
    "iso:country":"ES",
    "sg:address":"Avda Paz, 33",
    "sg:city":"Ibi",
    "sg:orig_category":"Ropa Para Ni\u00d1os (al Por Menor)",
    "sg:phone":"+34 966 55 10 37",
    "sg:postcode":"03440",
    "sg:province":"Alicante",
    "wof:name":"Casarrubio Garcia Maria Jesus",
    "wof:placetype":"venue"
},
  "geometry": {"coordinates":[-0.5789960027,38.6223640442],"type":"Point"}
}