{
  "type": "Feature",
  "properties": {
    "addr:full":"Calle de San Francisco, 15 Valverde Santa Cruz De Tenerife 38910",
    "addr:housenumber":"15",
    "addr:postcode":"38910",
    "addr:street":"Calle De San Francisco",
    "iso:country":"ES",
    "sg:address":"Calle de San Francisco, 15",
    "sg:city":"Valverde",
    "sg:orig_category":"Sociedades, Compa\u00d1\u00cdas Aseguradoras",
    "sg:phone":"+34 922 55 44 64",
    "sg:postcode":"38910",
    "sg:province":"Santa Cruz De Tenerife",
    "wof:name":"Jose Miguel Leon S.l.",
    "wof:placetype":"venue"
},
  "geometry": {"coordinates":[-17.8970718384,27.8238143921],"type":"Point"}
}