{
  "type": "Feature",
  "properties": {
    "iso:country":"ES",
    "sg:address":"Carretera Tiedra, 2",
    "sg:city":"Pozoantiguo",
    "sg:orig_category":"Farmacias",
    "sg:phone":"+34 980 69 64 74",
    "sg:postcode":"49835",
    "sg:province":"Zamora",
    "wof:name":"Martin Martin  Clara Maria",
    "wof:placetype":"venue"
},
  "geometry": {"coordinates":[-5.4367041588,41.5965766907],"type":"Point"}
}