{
  "type": "Feature",
  "properties": {
    "addr:full":"Calle de Angel Lozano, 15 Alacant Alicante 03001",
    "addr:housenumber":"15",
    "addr:postcode":"03001",
    "addr:street":"Calle De Angel Lozano",
    "iso:country":"ES",
    "sg:address":"Calle de Angel Lozano, 15",
    "sg:city":"Alacant",
    "sg:orig_category":"Pod\u00d3logos: Pedicuros",
    "sg:phone":"+34 965 20 82 20",
    "sg:postcode":"03001",
    "sg:province":"Alicante",
    "wof:name":"Albeza Contreras Antonio Luis",
    "wof:placetype":"venue"
},
  "geometry": {"coordinates":[-0.4886493087,38.3466072083],"type":"Point"}
}