{
  "type": "Feature",
  "properties": {
    "iso:country":"ES",
    "sg:address":"Rua San Benito, 17",
    "sg:city":"Carballi\u00f1o",
    "sg:orig_category":"Construcciones Met\u00c1licas",
    "sg:phone":"+34 988 27 04 77",
    "sg:postcode":"32500",
    "sg:province":"Ourense",
    "wof:name":"Valeiras Rodriguez Miguel",
    "wof:placetype":"venue"
},
  "geometry": {"coordinates":[-8.0805177689,42.4258384705],"type":"Point"}
}