{
  "type": "Feature",
  "properties": {
    "addr:full":"Ctra. Cuerva, Km. 0000,7 Galvez Toledo 45164",
    "addr:postcode":"45164",
    "addr:street":"Ctra. Cuerva Km. 0000,7 Galvez",
    "iso:country":"ES",
    "sg:address":"Ctra. Cuerva, Km. 0000,7",
    "sg:city":"Galvez",
    "sg:orig_category":"Fabricaci\u00d3n De Muebles",
    "sg:phone":"+34 925 40 00 00",
    "sg:postcode":"45164",
    "sg:province":"Toledo",
    "wof:name":"Mueblarte 3000 S.l.",
    "wof:placetype":"venue"
},
  "geometry": {"coordinates":[-4.2757091522,39.7027244568],"type":"Point"}
}