{
  "type": "Feature",
  "properties": {
    "iso:country":"ES",
    "sg:address":"Calle de Ca\u00d1o, 9",
    "sg:city":"Rozas De Madrid",
    "sg:orig_category":"Art\u00cdculos De Decoraci\u00d3n",
    "sg:phone":"+34 916 37 28 31",
    "sg:postcode":"28230",
    "sg:province":"Madrid",
    "wof:name":"Seventh & Dot Dise\u00f1os Y Proyectos S.l.",
    "wof:placetype":"venue"
},
  "geometry": {"coordinates":[-3.873513937,40.4929962158],"type":"Point"}
}