{
  "type": "Feature",
  "properties": {
    "addr:full":"Calle de Ermita (de La), S/n Siscar Murcia 30149",
    "addr:postcode":"30149",
    "addr:street":"Calle De Ermita;La S / N",
    "iso:country":"ES",
    "sg:address":"Calle de Ermita (de La), S/n",
    "sg:city":"Siscar",
    "sg:orig_category":"Iglesia Cat\u00d3lica",
    "sg:phone":"+34 968 86 10 73",
    "sg:postcode":"30149",
    "sg:province":"Murcia",
    "wof:name":"Obispado De Cartagena",
    "wof:placetype":"venue"
},
  "geometry": {"coordinates":[-1.024279952,38.068157196],"type":"Point"}
}