{
  "type": "Feature",
  "properties": {
    "addr:full":"Cllj Lucios (de), 2 Brihuega Guadalajara 19400",
    "addr:postcode":"19400",
    "iso:country":"ES",
    "sg:address":"Cllj Lucios (de), 2",
    "sg:city":"Brihuega",
    "sg:orig_category":"Agencias Y Agentes Comerciales, Representantes",
    "sg:phone":"+34 949 28 05 13",
    "sg:postcode":"19400",
    "sg:province":"Guadalajara",
    "wof:name":"Equipamientos E Instalaciones Hospitalarias S.l",
    "wof:placetype":"venue"
},
  "geometry": {"coordinates":[-2.8703289032,40.7592315674],"type":"Point"}
}