{
  "type": "Feature",
  "properties": {
    "iso:country":"ES",
    "sg:address":"Pg Germanies (de Les), 80",
    "sg:city":"Gandia",
    "sg:orig_category":"Contenedores (mercanc\u00cdas)",
    "sg:phone":"+34 962 87 11 52",
    "sg:postcode":"46700",
    "sg:province":"Valencia",
    "wof:name":"Artes Martinez Juan",
    "wof:placetype":"venue"
},
  "geometry": {"coordinates":[-0.1937536001,38.9673576355],"type":"Point"}
}