{
  "type": "Feature",
  "properties": {
    "iso:country":"ES",
    "sg:address":"Ctra Barrero-santa Rosa (del), 321",
    "sg:city":"Huertas Y Extramuros",
    "sg:orig_category":"Empresas De Carpinter\u00cda De Madera",
    "sg:phone":"+34 953 50 75 34",
    "sg:postcode":"23740",
    "sg:province":"Ja\u00e9n",
    "wof:name":"Ruano Rios Miguel",
    "wof:placetype":"venue"
},
  "geometry": {"coordinates":[-4.057518959,38.0386962891],"type":"Point"}
}