{
  "type": "Feature",
  "properties": {
    "addr:full":"Calle de Treinta De Mayo, 17 San Pedro De Bre\u00e7a Alta Santa Cruz De Tenerife 38712",
    "addr:housenumber":"17",
    "addr:postcode":"38712",
    "addr:street":"Calle De Treinta De Mayo",
    "iso:country":"ES",
    "sg:address":"Calle de Treinta De Mayo, 17",
    "sg:city":"San Pedro De Bre\u00e7a Alta",
    "sg:orig_category":"Centros Empresariales",
    "sg:phone":"+34 922 43 80 35",
    "sg:postcode":"38712",
    "sg:province":"Santa Cruz De Tenerife",
    "wof:name":"Rodriguez Diaz Jose Francisco",
    "wof:placetype":"venue"
},
  "geometry": {"coordinates":[-17.7672138214,28.6476554871],"type":"Point"}
}