{
  "type": "Feature",
  "properties": {
    "addr:full":"Calle de Marceliano Santa Maria, 1 Madrid Madrid 28036",
    "addr:housenumber":"1",
    "addr:postcode":"28036",
    "addr:street":"Calle De Marceliano Santa Maria",
    "iso:country":"ES",
    "sg:address":"Calle de Marceliano Santa Maria, 1",
    "sg:city":"Madrid",
    "sg:orig_category":"Bisuter\u00cda, Joyer\u00cda, Relojer\u00cda (al Por Menor)",
    "sg:phone":"+34 915 62 62 17",
    "sg:postcode":"28036",
    "sg:province":"Madrid",
    "wof:name":"R.sanz De Madrid Joyeros S.l.",
    "wof:placetype":"venue"
},
  "geometry": {"coordinates":[-3.6888539791,40.4508934021],"type":"Point"}
}