{
  "type": "Feature",
  "properties": {
    "iso:country":"ES",
    "sg:address":"Mcdo. Abastos, S/n",
    "sg:city":"Portugalete",
    "sg:orig_category":"Pescader\u00cdas (al Por Menor)",
    "sg:phone":"+34 944 96 09 32",
    "sg:postcode":"48920",
    "sg:province":"Vizcaya",
    "wof:name":"Hermosilla Del Campo Domingo",
    "wof:placetype":"venue"
},
  "geometry": {"coordinates":[-3.0176839828,43.3219337463],"type":"Point"}
}