{
  "type": "Feature",
  "properties": {
    "addr:full":"Aios, 90 Aios Pontevedra 36990",
    "addr:housenumber":"90",
    "addr:postcode":"36990",
    "addr:street":"Aios",
    "iso:country":"ES",
    "sg:address":"Aios, 90",
    "sg:city":"Aios",
    "sg:orig_category":"Promotores Constructores",
    "sg:phone":"+34 986 69 09 53",
    "sg:postcode":"36990",
    "sg:province":"Pontevedra",
    "wof:name":"Constructora Aguin Magdalena S.l.",
    "wof:placetype":"venue"
},
  "geometry": {"coordinates":[-8.8508090973,42.4159317017],"type":"Point"}
}