{
  "type": "Feature",
  "properties": {
    "addr:full":"Calle de Rosalia De Castro, 95 Escairon Lugo 27540",
    "addr:housenumber":"95",
    "addr:postcode":"27540",
    "addr:street":"Calle De Rosalia De Castro",
    "iso:country":"ES",
    "sg:address":"Calle de Rosalia De Castro, 95",
    "sg:city":"Escairon",
    "sg:orig_category":"Peluquer\u00cdas, Peluquer\u00cda Mixta",
    "sg:phone":"+34 982 45 26 45",
    "sg:postcode":"27540",
    "sg:province":"Lugo",
    "wof:name":"Castro Moreiras Pilar",
    "wof:placetype":"venue"
},
  "geometry": {"coordinates":[-7.6355109215,42.5896263123],"type":"Point"}
}