{
  "type": "Feature",
  "properties": {
    "iso:country":"ES",
    "sg:address":"Ctra Fuensanta, 34",
    "sg:city":"Santiago El Mayor",
    "sg:orig_category":"Alimentaci\u00d3n General (al Por Menor)",
    "sg:phone":"+34 968 26 27 02",
    "sg:postcode":"30010",
    "sg:province":"Murcia",
    "wof:name":"Noguera Nicolas Fulgencio",
    "wof:placetype":"venue"
},
  "geometry": {"coordinates":[-1.1284470558,37.9726066589],"type":"Point"}
}