{
  "type": "Feature",
  "properties": {
    "addr:full":"Calle de Juan De Austria, S/n Guadalajara Guadalajara 19004",
    "addr:housenumber":"s / n",
    "addr:postcode":"19004",
    "addr:street":"Calle De Juan De Austria",
    "iso:country":"ES",
    "sg:address":"Calle de Juan De Austria, S/n",
    "sg:city":"Guadalajara",
    "sg:orig_category":"Artes Gr\u00c1ficas, Artes Pl\u00c1sticas (curso)",
    "sg:phone":"+34 949 24 74 33",
    "sg:postcode":"19004",
    "sg:province":"Guadalajara",
    "sg:website":"www.savasa.com",
    "wof:name":"Europrint S. A.",
    "wof:placetype":"venue"
},
  "geometry": {"coordinates":[-3.1758699417,40.6515197754],"type":"Point"}
}