{
  "type": "Feature",
  "properties": {
    "addr:full":"Carrer de Rosa, 20 Sabadell Barcelona 08201",
    "addr:housenumber":"20",
    "addr:postcode":"08201",
    "addr:street":"Carrer De Rosa",
    "iso:country":"ES",
    "sg:address":"Carrer de Rosa, 20",
    "sg:city":"Sabadell",
    "sg:orig_category":"Lencer\u00cda Femenina, Corseter\u00cda, Trajes De Ba\u00d1o (al Por Menor)",
    "sg:phone":"+34 937 25 65 75",
    "sg:postcode":"08201",
    "sg:province":"Barcelona",
    "wof:name":"Curiel Trillo Purificacion",
    "wof:placetype":"venue"
},
  "geometry": {"coordinates":[2.108109951,41.5472602844],"type":"Point"}
}