{
  "type": "Feature",
  "properties": {
    "addr:full":"Pla\u00c7 Porta Del Sol, 4 Ca\u00d1ada Valencia 46182",
    "addr:housenumber":"4",
    "addr:postcode":"46182",
    "addr:street":"Can\u0303Ada",
    "iso:country":"ES",
    "sg:address":"Pla\u00c7 Porta Del Sol, 4",
    "sg:city":"Ca\u00d1ada",
    "sg:orig_category":"Estancos",
    "sg:phone":"+34 961 32 13 84",
    "sg:postcode":"46182",
    "sg:province":"Valencia",
    "wof:name":"Guillem Ramos Maria Asuncion",
    "wof:placetype":"venue"
},
  "geometry": {"coordinates":[-0.8098580837,38.675239563],"type":"Point"}
}