{
  "type": "Feature",
  "properties": {
    "addr:full":"Calle de Mar, 43 Valencia Valencia 46003",
    "addr:housenumber":"43",
    "addr:postcode":"46003",
    "addr:street":"Calle De Mar",
    "iso:country":"ES",
    "sg:address":"Calle de Mar, 43",
    "sg:city":"Valencia",
    "sg:orig_category":"Abogados",
    "sg:phone":"+34 963 92 36 41",
    "sg:postcode":"46003",
    "sg:province":"Valencia",
    "wof:name":"Montagud Castello Enrique",
    "wof:placetype":"venue"
},
  "geometry": {"coordinates":[-0.371250689,39.4733581543],"type":"Point"}
}