{
  "type": "Feature",
  "properties": {
    "addr:full":"Calle de Nereo, 11 Malaga M\u00e1laga 29004",
    "addr:housenumber":"11",
    "addr:postcode":"29004",
    "addr:street":"Calle De Nereo;Ma\u0301Laga",
    "iso:country":"ES",
    "sg:address":"Calle de Nereo, 11",
    "sg:city":"Malaga",
    "sg:orig_category":"Fabricaci\u00d3n De Distribuidores Autom\u00c1ticos",
    "sg:phone":"+34 952 24 39 04",
    "sg:postcode":"29004",
    "sg:province":"M\u00e1laga",
    "wof:name":"Laiv S.l.",
    "wof:placetype":"venue"
},
  "geometry": {"coordinates":[-4.4455418587,36.6871643066],"type":"Point"}
}