{
  "type": "Feature",
  "properties": {
    "addr:full":"Avda Alfonso El Sabio, 36 Alacant Alicante 03004",
    "addr:housenumber":"36",
    "addr:postcode":"03004",
    "addr:street":"Avda Alfonso El Sabio",
    "iso:country":"ES",
    "sg:address":"Avda Alfonso El Sabio, 36",
    "sg:city":"Alacant",
    "sg:orig_category":"Cajas De Ahorro",
    "sg:phone":"+34 965 14 61 80",
    "sg:postcode":"03004",
    "sg:province":"Alicante",
    "wof:name":"Caja De Ahorros De Valencia Castellon Y Alicante",
    "wof:placetype":"venue"
},
  "geometry": {"coordinates":[-0.4888100028,38.3468589783],"type":"Point"}
}