{
  "type": "Feature",
  "properties": {
    "iso:country":"ES",
    "sg:address":"Av Creu Roja, 25",
    "sg:city":"Cerdanyola Valles",
    "sg:orig_category":"Asociaciones, Organismos Culturales Y Socioeducativos",
    "sg:phone":"+34 935 92 09 85",
    "sg:postcode":"08290",
    "sg:province":"Barcelona",
    "wof:name":"D.a.p.s.i. Cerdanyola S.c.c.l.",
    "wof:placetype":"venue"
},
  "geometry": {"coordinates":[2.1491000652,41.4938697815],"type":"Point"}
}