{
  "type": "Feature",
  "properties": {
    "iso:country":"ES",
    "sg:address":"Avda Galan Bergua, 5",
    "sg:city":"Alca\u00f1iz",
    "sg:orig_category":"Peluquer\u00cdas, Peluquer\u00cda Mixta",
    "sg:phone":"+34 978 83 07 08",
    "sg:postcode":"44600",
    "sg:province":"Teruel",
    "wof:name":"Gorriz Belles Diana",
    "wof:placetype":"venue"
},
  "geometry": {"coordinates":[-0.1311250031,41.0515708923],"type":"Point"}
}