{
  "type": "Feature",
  "properties": {
    "iso:country":"ES",
    "sg:address":"Garmendi Auzunea, 8",
    "sg:city":"Azpeitia",
    "sg:orig_category":"Promotores Constructores",
    "sg:phone":"+34 943 15 09 26",
    "sg:postcode":"20730",
    "sg:province":"Guip\u00f9zcoa",
    "wof:name":"Exkerra Etxegintza S.l.",
    "wof:placetype":"venue"
},
  "geometry": {"coordinates":[-2.2653059959,43.1791877747],"type":"Point"}
}