{
  "type": "Feature",
  "properties": {
    "iso:country":"ES",
    "sg:address":"Calle de Malaga, 3",
    "sg:city":"Valladolid",
    "sg:orig_category":"Reposter\u00cdas",
    "sg:phone":"+34 983 30 60 85",
    "sg:postcode":"47012",
    "sg:province":"Valladolid",
    "wof:name":"Oliveros Izquierdo Juan",
    "wof:placetype":"venue"
},
  "geometry": {"coordinates":[-4.7151961327,41.6440811157],"type":"Point"}
}