{
  "type": "Feature",
  "properties": {
    "iso:country":"ES",
    "sg:address":"Calle de Florez Estrada, S/n",
    "sg:city":"Pola Somiedo",
    "sg:orig_category":"Carnicer\u00cdas, Carnicer\u00cdas",
    "sg:phone":"+34 985 76 36 88",
    "sg:postcode":"33840",
    "sg:province":"Asturias",
    "wof:name":"Alvarez Riesgo Guillermo",
    "wof:placetype":"venue"
},
  "geometry": {"coordinates":[-6.2546806335,43.0931053162],"type":"Point"}
}