{
  "type": "Feature",
  "properties": {
    "iso:country":"ES",
    "sg:address":"Diego Romay(vilarrodis), 2",
    "sg:city":"Arteixo",
    "sg:orig_category":"Caf\u00c9s, Bares, Cervecer\u00cdas",
    "sg:phone":"+34 981 63 32 22",
    "sg:postcode":"15141",
    "sg:province":"La Coru\u00f1a",
    "wof:name":"Pimiamite S.l.",
    "wof:placetype":"venue"
},
  "geometry": {"coordinates":[-8.4743051529,43.3214683533],"type":"Point"}
}