{
  "type": "Feature",
  "properties": {
    "addr:full":"Calle de Minas, 25 Alcorcon Madrid 28925",
    "addr:housenumber":"25",
    "addr:postcode":"28925",
    "addr:street":"Calle De Minas",
    "iso:country":"ES",
    "sg:address":"Calle de Minas, 25",
    "sg:city":"Alcorcon",
    "sg:orig_category":"Moquetas, Alfombras (al Por Menor)",
    "sg:phone":"+34 916 43 99 25",
    "sg:postcode":"28925",
    "sg:province":"Madrid",
    "wof:name":"Comercial Mago Decoracciones S.l.",
    "wof:placetype":"venue"
},
  "geometry": {"coordinates":[-3.8151021004,40.3372650146],"type":"Point"}
}