{
  "type": "Feature",
  "properties": {
    "addr:full":"Avda General Lopez Dominguez, 28 Marbella M\u00e1laga 29600",
    "addr:postcode":"29600",
    "addr:street":"Avda General Lopez Dominguez 28;Ma\u0301Laga",
    "iso:country":"ES",
    "sg:address":"Avda General Lopez Dominguez, 28",
    "sg:city":"Marbella",
    "sg:orig_category":"Agentes Generales De Seguros",
    "sg:phone":"+34 952 86 52 89",
    "sg:postcode":"29600",
    "sg:province":"M\u00e1laga",
    "wof:name":"Lopez Sanchez Jose",
    "wof:placetype":"venue"
},
  "geometry": {"coordinates":[-4.8765358925,36.5137443542],"type":"Point"}
}