{
  "type": "Feature",
  "properties": {
    "iso:country":"ES",
    "sg:address":"Carrer de Major, 23",
    "sg:city":"Mataro",
    "sg:orig_category":"Tapicer\u00cdas",
    "sg:phone":"+34 937 57 25 32",
    "sg:postcode":"08303",
    "sg:province":"Barcelona",
    "wof:name":"Leiton Gilo Fernando",
    "wof:placetype":"venue"
},
  "geometry": {"coordinates":[2.4265189171,41.5411834717],"type":"Point"}
}