{
  "type": "Feature",
  "properties": {
    "iso:country":"ES",
    "sg:address":"Ipe\u00d1arrieta Kalea, 50",
    "sg:city":"Urretxu",
    "sg:orig_category":"Panader\u00cdas, Panader\u00cdas",
    "sg:phone":"+34 943 72 35 34",
    "sg:postcode":"20700",
    "sg:province":"Guip\u00f9zcoa",
    "wof:name":"Artukoluke S.l.",
    "wof:placetype":"venue"
},
  "geometry": {"coordinates":[-2.3238298893,43.0833625793],"type":"Point"}
}