{
  "type": "Feature",
  "properties": {
    "addr:full":"Calle de Gordoniz, 7 Bilbao Vizcaya 48010",
    "addr:housenumber":"7",
    "addr:postcode":"48010",
    "addr:street":"Calle De Gordoniz",
    "iso:country":"ES",
    "sg:address":"Calle de Gordoniz, 7",
    "sg:city":"Bilbao",
    "sg:orig_category":"Peluquer\u00cdas, Peluquer\u00cda Mixta",
    "sg:phone":"+34 944 22 16 79",
    "sg:postcode":"48010",
    "sg:province":"Vizcaya",
    "wof:name":"Mallea Boto Angel",
    "wof:placetype":"venue"
},
  "geometry": {"coordinates":[-2.9386329651,43.2594833374],"type":"Point"}
}