{
  "type": "Feature",
  "properties": {
    "iso:country":"ES",
    "sg:address":"Calle de Pintor Cabrera, 17",
    "sg:city":"Alacant",
    "sg:orig_category":"Ropa Para Ni\u00d1os (al Por Menor)",
    "sg:phone":"+34 965 13 16 81",
    "sg:postcode":"03003",
    "sg:province":"Alicante",
    "wof:name":"Ense\u00f1at Alvarez Almudena",
    "wof:placetype":"venue"
},
  "geometry": {"coordinates":[-0.4920319915,38.3442497253],"type":"Point"}
}