{
  "type": "Feature",
  "properties": {
    "iso:country":"ES",
    "sg:address":"Calle de Caramuel, 20",
    "sg:city":"Madrid",
    "sg:orig_category":"Centros De Coordinaci\u00d3n",
    "sg:phone":"+34 915 26 10 56",
    "sg:postcode":"28011",
    "sg:province":"Madrid",
    "wof:name":"Rolges S.l.",
    "wof:placetype":"venue"
},
  "geometry": {"coordinates":[-3.7268970013,40.4119300842],"type":"Point"}
}