{
  "type": "Feature",
  "properties": {
    "addr:full":"Calle de Plaza (de La), 37 Pto Real C\u00e1diz 11510",
    "addr:housenumber":"37",
    "addr:postcode":"11510",
    "addr:street":"Calle De Plaza De La;Ca\u0301Diz",
    "iso:country":"ES",
    "sg:address":"Calle de Plaza (de La), 37",
    "sg:city":"Pto Real",
    "sg:orig_category":"Perfumer\u00cda (al Por Menor)",
    "sg:phone":"+34 956 47 25 16",
    "sg:postcode":"11510",
    "sg:province":"C\u00e1diz",
    "wof:name":"Row Pice S.l.",
    "wof:placetype":"venue"
},
  "geometry": {"coordinates":[-6.1873540878,36.5270271301],"type":"Point"}
}