{
  "type": "Feature",
  "properties": {
    "addr:full":"Carrer de Joan Marti, 6 S. Boi Llobregat Barcelona 08830",
    "addr:housenumber":"6",
    "addr:postcode":"08830",
    "addr:street":"Carrer De Joan Marti",
    "iso:country":"ES",
    "sg:address":"Carrer de Joan Marti, 6",
    "sg:city":"S. Boi Llobregat",
    "sg:orig_category":"Molduras, Junquillos, Listones Y Molduras Perforadas",
    "sg:phone":"+34 936 30 00 44",
    "sg:postcode":"08830",
    "sg:province":"Barcelona",
    "wof:name":"Olle Fuste Ramon",
    "wof:placetype":"venue"
},
  "geometry": {"coordinates":[2.0349979401,41.3464279175],"type":"Point"}
}