{
  "type": "Feature",
  "properties": {
    "addr:full":"Carr Closa D'en Llop, 101 Escala Girona 17130",
    "addr:housenumber":"101",
    "addr:postcode":"17130",
    "addr:street":"Carr Closa D'En Llop",
    "iso:country":"ES",
    "sg:address":"Carr Closa D'en Llop, 101",
    "sg:city":"Escala",
    "sg:orig_category":"Electromec\u00c1nica",
    "sg:phone":"+34 972 77 31 62",
    "sg:postcode":"17130",
    "sg:province":"Girona",
    "wof:name":"Marti Vilavedra Jose",
    "wof:placetype":"venue"
},
  "geometry": {"coordinates":[3.1271460056,42.1177062988],"type":"Point"}
}