{
  "type": "Feature",
  "properties": {
    "addr:full":"Avda Castrelos, 1 Vigo Pontevedra 36210",
    "addr:housenumber":"1",
    "addr:postcode":"36210",
    "addr:street":"Avda Castrelos",
    "iso:country":"ES",
    "sg:address":"Avda Castrelos, 1",
    "sg:city":"Vigo",
    "sg:orig_category":"Asociaciones Y Clubs Deportivos",
    "sg:phone":"+34 986 24 27 31",
    "sg:postcode":"36210",
    "sg:province":"Pontevedra",
    "sg:website":"www.academiaoctavio.com",
    "wof:name":"Club Balonmano Academia Octavio",
    "wof:placetype":"venue"
},
  "geometry": {"coordinates":[-8.7322673798,42.2192726135],"type":"Point"}
}