{
  "type": "Feature",
  "properties": {
    "addr:full":"Avda Cantabrico, 12 Vitoria-gasteiz \u00c1lava 01013",
    "addr:housenumber":"12",
    "addr:postcode":"01013",
    "addr:street":"Avda Cantabrico",
    "iso:country":"ES",
    "sg:address":"Avda Cantabrico, 12",
    "sg:city":"Vitoria-gasteiz",
    "sg:orig_category":"Muebles, Minoristas",
    "sg:phone":"+34 945 26 34 85",
    "sg:postcode":"01013",
    "sg:province":"\u00c1lava",
    "wof:name":"Martinez De Mendijur Saez De Viteri Basilio",
    "wof:placetype":"venue"
},
  "geometry": {"coordinates":[-2.6595649719,42.8647041321],"type":"Point"}
}