{
  "type": "Feature",
  "properties": {
    "iso:country":"ES",
    "sg:address":"C/ Pou De La Vila, 16",
    "sg:city":"Tossa",
    "sg:orig_category":"Porcelanas, Azulejos (fabricaci\u00d3n, Al Por Mayor)",
    "sg:phone":"+34 972 34 19 52",
    "sg:postcode":"17320",
    "sg:province":"Girona",
    "wof:name":"Escayola Coris Maria Del Carmen",
    "wof:placetype":"venue"
},
  "geometry": {"coordinates":[2.9321930408,41.7201843262],"type":"Point"}
}