{
  "type": "Feature",
  "properties": {
    "addr:full":"Calle de Convento, 3 Petrer Alicante 03610",
    "addr:housenumber":"3",
    "addr:postcode":"03610",
    "addr:street":"Calle De Convento",
    "iso:country":"ES",
    "sg:address":"Calle de Convento, 3",
    "sg:city":"Petrer",
    "sg:orig_category":"Mec\u00c1nico Del Autom\u00d3vil",
    "sg:phone":"+34 966 95 59 89",
    "sg:postcode":"03610",
    "sg:province":"Alicante",
    "wof:name":"Gomez Garcia Rafael",
    "wof:placetype":"venue"
},
  "geometry": {"coordinates":[-0.7885370255,38.4846305847],"type":"Point"}
}