{
  "type": "Feature",
  "properties": {
    "iso:country":"ES",
    "sg:address":"Calle de San Juan Bautista De La Salle, 11",
    "sg:city":"Consuegra",
    "sg:orig_category":"Fisioterapia",
    "sg:phone":"+34 925 47 60 05",
    "sg:postcode":"45700",
    "sg:province":"Toledo",
    "wof:name":"Palomino Romeral Alfonso",
    "wof:placetype":"venue"
},
  "geometry": {"coordinates":[-3.6071090698,39.4602203369],"type":"Point"}
}