{
  "type": "Feature",
  "properties": {
    "iso:country":"ES",
    "sg:address":"Calle de Terrer, 4",
    "sg:city":"Zaragoza",
    "sg:orig_category":"Carnicer\u00cdas, Carnicer\u00cdas",
    "sg:phone":"+34 976 53 53 98",
    "sg:postcode":"50017",
    "sg:province":"Zaragoza",
    "wof:name":"Carnicerias Del Barrio S.l",
    "wof:placetype":"venue"
},
  "geometry": {"coordinates":[-0.9139140248,41.647644043],"type":"Point"}
}