{
  "type": "Feature",
  "properties": {
    "addr:full":"Ctra Alange, S/n Merida Badajoz 06800",
    "addr:housenumber":"s / n",
    "addr:postcode":"06800",
    "addr:street":"Ctra Alange",
    "iso:country":"ES",
    "sg:address":"Ctra Alange, S/n",
    "sg:city":"Merida",
    "sg:orig_category":"Escayola Y Productos De Escayola (fabricaci\u00d3n, Al Por Mayor)",
    "sg:phone":"+34 924 37 30 68",
    "sg:postcode":"06800",
    "sg:province":"Badajoz",
    "wof:name":"Polo Donaire Ramon",
    "wof:placetype":"venue"
},
  "geometry": {"coordinates":[-6.3543081284,38.9102210999],"type":"Point"}
}