{
  "type": "Feature",
  "properties": {
    "addr:full":"Carrer de Numancia, 51 Barcelona Barcelona 08029",
    "addr:housenumber":"51",
    "addr:postcode":"08029",
    "addr:street":"Carrer De Numancia",
    "iso:country":"ES",
    "sg:address":"Carrer de Numancia, 51",
    "sg:city":"Barcelona",
    "sg:orig_category":"Doctores En Medicina",
    "sg:phone":"+34 934 05 17 88",
    "sg:postcode":"08029",
    "sg:province":"Barcelona",
    "wof:name":"Area S.c.p.",
    "wof:placetype":"venue"
},
  "geometry": {"coordinates":[2.1387753487,41.3834686279],"type":"Point"}
}