{
  "type": "Feature",
  "properties": {
    "iso:country":"ES",
    "sg:address":"Calle de Antonio Machado, 8",
    "sg:city":"Almazan",
    "sg:orig_category":"Asesor\u00cda Sobre Comunicaci\u00d3n De Empresas",
    "sg:phone":"+34 975 30 00 23",
    "sg:postcode":"42200",
    "sg:province":"Soria",
    "wof:name":"Servicios Generales De Asesoramiento S.l.",
    "wof:placetype":"venue"
},
  "geometry": {"coordinates":[-2.5261940956,41.4815063477],"type":"Point"}
}