{
  "type": "Feature",
  "properties": {
    "addr:full":"Cmno Pe\u00d1itas, 42 Oropesa Toledo 45560",
    "addr:housenumber":"42",
    "addr:postcode":"45560",
    "addr:street":"Cmno Pen\u0303Itas",
    "iso:country":"ES",
    "sg:address":"Cmno Pe\u00d1itas, 42",
    "sg:city":"Oropesa",
    "sg:orig_category":"Arquitectos",
    "sg:phone":"+34 925 43 13 14",
    "sg:postcode":"45560",
    "sg:province":"Toledo",
    "wof:name":"Moreno Moreno Julio Cesar",
    "wof:placetype":"venue"
},
  "geometry": {"coordinates":[-5.1782941818,39.9192237854],"type":"Point"}
}