{
  "type": "Feature",
  "properties": {
    "iso:country":"ES",
    "sg:address":"Calle de Paseo Del Ebro, S/n",
    "sg:city":"Bu\u00f1uel",
    "sg:orig_category":"Distribuci\u00d3n De Petr\u00d3leo Y Derivados",
    "sg:phone":"+34 948 83 31 60",
    "sg:postcode":"31540",
    "sg:province":"Navarra",
    "wof:name":"Estacion De Servicio Bu\u00f1uel Sl",
    "wof:placetype":"venue"
},
  "geometry": {"coordinates":[-1.4451860189,41.9813766479],"type":"Point"}
}