{
  "type": "Feature",
  "properties": {
    "addr:full":"Calle de Roncal, 2 Lodosa Navarra 31580",
    "addr:housenumber":"2",
    "addr:postcode":"31580",
    "addr:street":"Calle De Roncal",
    "iso:country":"ES",
    "sg:address":"Calle de Roncal, 2",
    "sg:city":"Lodosa",
    "sg:orig_category":"Plomeros",
    "sg:phone":"+34 948 69 41 55",
    "sg:postcode":"31580",
    "sg:province":"Navarra",
    "wof:name":"Roldan Arnedillo Francisco",
    "wof:placetype":"venue"
},
  "geometry": {"coordinates":[-2.0805089474,42.4242477417],"type":"Point"}
}