{
  "type": "Feature",
  "properties": {
    "iso:country":"ES",
    "sg:address":"Carrer de Anselm Clave, 11",
    "sg:city":"Casco Urbano",
    "sg:orig_category":"Frutas, Legumbres Frescas Y Tempranas (al Por Menor)",
    "sg:phone":"+34 938 41 18 65",
    "sg:postcode":"08450",
    "sg:province":"Barcelona",
    "wof:name":"Giro Guriol Frances",
    "wof:placetype":"venue"
},
  "geometry": {"coordinates":[2.4019749165,41.6397705078],"type":"Point"}
}