{
  "type": "Feature",
  "properties": {
    "iso:country":"ES",
    "sg:address":"Calle de Fernando Tirado, 3",
    "sg:city":"Sevilla",
    "sg:orig_category":"Chapister\u00cda",
    "sg:phone":"+34 954 57 96 22",
    "sg:postcode":"41018",
    "sg:province":"Sevilla",
    "wof:name":"Adame Ortiz Miguel",
    "wof:placetype":"venue"
},
  "geometry": {"coordinates":[-5.9769010544,37.3867149353],"type":"Point"}
}