{
  "type": "Feature",
  "properties": {
    "iso:country":"ES",
    "sg:address":"Calle de Arrieta, 18",
    "sg:city":"Alegria-dulantzi",
    "sg:orig_category":"Centros Empresariales",
    "sg:phone":"+34 945 40 08 28",
    "sg:postcode":"01240",
    "sg:province":"\u00c1lava",
    "wof:name":"Darmma Tecnica S.l.",
    "wof:placetype":"venue"
},
  "geometry": {"coordinates":[-2.510705471,42.8429374695],"type":"Point"}
}