{
  "type": "Feature",
  "properties": {
    "addr:full":"Calle de San Juan, 1 Albalate Nogueras Cuenca 16841",
    "addr:housenumber":"1;nogueras",
    "addr:postcode":"16841",
    "addr:street":"Calle De San Juan",
    "iso:country":"ES",
    "sg:address":"Calle de San Juan, 1",
    "sg:city":"Albalate Nogueras",
    "sg:orig_category":"Centros De Educaci\u00d3n Especial",
    "sg:phone":"+34 969 31 36 07",
    "sg:postcode":"16841",
    "sg:province":"Cuenca",
    "wof:name":"Colegio Publico Rural Agrupado Los Sauces",
    "wof:placetype":"venue"
},
  "geometry": {"coordinates":[-2.277230978,40.3652801514],"type":"Point"}
}