{
  "type": "Feature",
  "properties": {
    "addr:full":"Calle de Prim, General, 5 Melilla Melilla 52004",
    "addr:housenumber":"5",
    "addr:postcode":"52004",
    "addr:street":"Calle De Prim General",
    "iso:country":"ES",
    "sg:address":"Calle de Prim, General, 5",
    "sg:city":"Melilla",
    "sg:orig_category":"Caf\u00c9s, Bares, Cervecer\u00cdas",
    "sg:phone":"+34 952 68 03 20",
    "sg:postcode":"52004",
    "sg:province":"Melilla",
    "wof:name":"Cafeteria  Rossy",
    "wof:placetype":"venue"
},
  "geometry": {"coordinates":[-2.9414598942,35.2887496948],"type":"Point"}
}