{
  "type": "Feature",
  "properties": {
    "addr:full":"Mercado De Mayoristas, S/n Vitoria-gasteiz \u00c1lava 01004",
    "addr:housenumber":"s / n",
    "addr:postcode":"01004",
    "iso:country":"ES",
    "sg:address":"Mercado De Mayoristas, S/n",
    "sg:city":"Vitoria-gasteiz",
    "sg:orig_category":"Mercados De Productos Alimenticios",
    "sg:phone":"+34 945 24 89 00",
    "sg:postcode":"01004",
    "sg:province":"\u00c1lava",
    "wof:name":"Union 84 S. A.",
    "wof:placetype":"venue"
},
  "geometry": {"coordinates":[-2.6666500568,42.8437004089],"type":"Point"}
}