{
  "type": "Feature",
  "properties": {
    "addr:full":"Calle de Don Pio Coronado, 114 Palmas De Gran Canaria Las Palmas 35012",
    "addr:housenumber":"114",
    "addr:postcode":"35012",
    "addr:street":"Calle De Don Pio Coronado",
    "iso:country":"ES",
    "sg:address":"Calle de Don Pio Coronado, 114",
    "sg:city":"Palmas De Gran Canaria",
    "sg:orig_category":"Alimentaci\u00d3n General (al Por Menor)",
    "sg:phone":"+34 928 20 84 01",
    "sg:postcode":"35012",
    "sg:province":"Las Palmas",
    "wof:name":"Almeida Betancor Eugenio Manuel",
    "wof:placetype":"venue"
},
  "geometry": {"coordinates":[-15.4354276657,28.1085853577],"type":"Point"}
}