{
  "type": "Feature",
  "properties": {
    "addr:full":"Carrer de Roser, 22 Gironella Barcelona 08680",
    "addr:housenumber":"22",
    "addr:postcode":"08680",
    "addr:street":"Carrer De Roser",
    "iso:country":"ES",
    "sg:address":"Carrer de Roser, 22",
    "sg:city":"Gironella",
    "sg:orig_category":"Marmolistas Funerarios",
    "sg:phone":"+34 938 25 01 19",
    "sg:postcode":"08680",
    "sg:province":"Barcelona",
    "wof:name":"Funeraria Pujols S.l.",
    "wof:placetype":"venue"
},
  "geometry": {"coordinates":[1.8833199739,42.0333518982],"type":"Point"}
}