{
  "type": "Feature",
  "properties": {
    "addr:full":"Rua San Antoni\u00d1o, 3 Pontevedra Pontevedra 36002",
    "addr:housenumber":"3",
    "addr:postcode":"36002",
    "addr:street":"Rua San Antonin\u0303O",
    "iso:country":"ES",
    "sg:address":"Rua San Antoni\u00d1o, 3",
    "sg:city":"Pontevedra",
    "sg:orig_category":"Mercer\u00cda, Lencer\u00cda (al Por Menor)",
    "sg:phone":"+34 986 85 83 36",
    "sg:postcode":"36002",
    "sg:province":"Pontevedra",
    "wof:name":"Guimerans Carballo Benito",
    "wof:placetype":"venue"
},
  "geometry": {"coordinates":[-8.6376981735,42.4305801392],"type":"Point"}
}