{
  "type": "Feature",
  "properties": {
    "iso:country":"ES",
    "sg:address":"Errota Poligonoa, 5",
    "sg:city":"Anoeta",
    "sg:orig_category":"Fabricaci\u00d3n, Instalaci\u00d3n Y Reparaci\u00d3n De Bombas",
    "sg:phone":"+34 943 65 36 54",
    "sg:postcode":"20270",
    "sg:province":"Guip\u00f9zcoa",
    "sg:website":"www.continental-industrie.com",
    "wof:name":"Continental Industrie Soplantes Y Bombas De Vacio S.l.",
    "wof:placetype":"venue"
},
  "geometry": {"coordinates":[-2.069963932,43.1619186401],"type":"Point"}
}