{
  "type": "Feature",
  "properties": {
    "addr:full":"Calle de Leizaola Lehendakari, 2 Bilbao Vizcaya 48011",
    "addr:housenumber":"2",
    "addr:postcode":"48011",
    "addr:street":"Calle De Leizaola Lehendakari",
    "iso:country":"ES",
    "sg:address":"Calle de Leizaola Lehendakari, 2",
    "sg:city":"Bilbao",
    "sg:orig_category":"Ropa Para Se\u00d1oras (al Por Menor)",
    "sg:phone":"+34 944 27 87 58",
    "sg:postcode":"48011",
    "sg:province":"Vizcaya",
    "sg:website":"www.bershka.com",
    "wof:name":"Bershka Bsr Espa\u00d1a S.a.",
    "wof:placetype":"venue"
},
  "geometry": {"coordinates":[-2.941026926,43.2676391602],"type":"Point"}
}