{
  "type": "Feature",
  "properties": {
    "addr:full":"Feros, S/n Feros La Coru\u00f1a 15883",
    "addr:postcode":"15883",
    "addr:street":"Feros S / N Feros La Corun\u0303A",
    "iso:country":"ES",
    "sg:address":"Feros, S/n",
    "sg:city":"Feros",
    "sg:orig_category":"Supermercados Y Hipermercados",
    "sg:phone":"+34 981 80 60 68",
    "sg:postcode":"15883",
    "sg:province":"La Coru\u00f1a",
    "wof:name":"La Plaza Pescados Y Frutas S.l.",
    "wof:placetype":"venue"
},
  "geometry": {"coordinates":[-8.5444011688,42.8382263184],"type":"Point"}
}