{
  "type": "Feature",
  "properties": {
    "iso:country":"ES",
    "sg:address":"Calle de Emilio Castelar, 29",
    "sg:city":"Alcazar S. Juan",
    "sg:orig_category":"Ense\u00d1anza Variada",
    "sg:phone":"+34 926 54 32 94",
    "sg:postcode":"13600",
    "sg:province":"Ciudad Real",
    "wof:name":"Salon",
    "wof:placetype":"venue"
},
  "geometry": {"coordinates":[-3.2084469795,39.3915290833],"type":"Point"}
}