{
  "type": "Feature",
  "properties": {
    "addr:full":"Cm\u00d1o Carreira Dos Ca\u00d1os, 17 Allariz Ourense 32660",
    "addr:housenumber":"17",
    "addr:postcode":"32660",
    "addr:street":"Dos Can\u0303Os",
    "iso:country":"ES",
    "sg:address":"Cm\u00d1o Carreira Dos Ca\u00d1os, 17",
    "sg:city":"Allariz",
    "sg:orig_category":"Empresas De Desmonte",
    "sg:phone":"+34 988 44 03 28",
    "sg:postcode":"32660",
    "sg:province":"Ourense",
    "wof:name":"Vidal Iglesias Manuel",
    "wof:placetype":"venue"
},
  "geometry": {"coordinates":[-7.796628952,42.1872901917],"type":"Point"}
}