{
  "type": "Feature",
  "properties": {
    "iso:country":"ES",
    "sg:address":"Cmno Viejo Rosell, S/n",
    "sg:city":"Vinaros",
    "sg:orig_category":"Fibras De Vidrio",
    "sg:phone":"+34 964 45 59 65",
    "sg:postcode":"12500",
    "sg:province":"Castell\u00f3n",
    "wof:name":"Silos Roca S.l.",
    "wof:placetype":"venue"
},
  "geometry": {"coordinates":[0.4720779955,40.4823303223],"type":"Point"}
}