{
  "type": "Feature",
  "properties": {
    "iso:country":"ES",
    "sg:address":"Plaz Mayor, 2",
    "sg:city":"Riaza",
    "sg:orig_category":"Molduras, Junquillos, Listones Y Molduras Perforadas",
    "sg:phone":"+34 921 55 06 28",
    "sg:postcode":"40500",
    "sg:province":"Segovia",
    "wof:name":"Allende Casado Pedro Miguel",
    "wof:placetype":"venue"
},
  "geometry": {"coordinates":[-3.4772500992,41.2795906067],"type":"Point"}
}