{
  "type": "Feature",
  "properties": {
    "addr:full":"Rbla Rambla Nova, 16 Tarragona Tarragona 43004",
    "addr:housenumber":"16",
    "addr:postcode":"43004",
    "addr:street":"Rambla Nova",
    "iso:country":"ES",
    "sg:address":"Rbla Rambla Nova, 16",
    "sg:city":"Tarragona",
    "sg:orig_category":"M\u00c9dicos: Medicina General Orientada A La Acupuntura",
    "sg:phone":"+34 977 23 32 32",
    "sg:postcode":"43004",
    "sg:province":"Tarragona",
    "wof:name":"Wong  Hon Wing",
    "wof:placetype":"venue"
},
  "geometry": {"coordinates":[1.2553603649,41.1140594482],"type":"Point"}
}