{
  "type": "Feature",
  "properties": {
    "iso:country":"ES",
    "sg:address":"Calle de Isaac Peral, 14",
    "sg:city":"Linares",
    "sg:orig_category":"Empleado Administrativo",
    "sg:phone":"+34 953 65 61 87",
    "sg:postcode":"23700",
    "sg:province":"Ja\u00e9n",
    "wof:name":"Gestoria Ortega S.l.",
    "wof:placetype":"venue"
},
  "geometry": {"coordinates":[-3.6332039833,38.0956916809],"type":"Point"}
}