{
  "type": "Feature",
  "properties": {
    "iso:country":"ES",
    "sg:address":"Afueras, S/n",
    "sg:city":"Estellencs",
    "sg:orig_category":"Edici\u00d3n De Diarios, Revistas, Boletines",
    "sg:phone":"+34 971 61 86 55",
    "sg:postcode":"07192",
    "sg:province":"Islas Baleares",
    "wof:name":"Editorial Gulaab C.b.",
    "wof:placetype":"venue"
},
  "geometry": {"coordinates":[2.482268095,39.6533966064],"type":"Point"}
}