{
  "type": "Feature",
  "properties": {
    "iso:country":"ES",
    "sg:address":"Calle de Rector Lopez Argueta, 23",
    "sg:city":"Granada",
    "sg:orig_category":"Inform\u00c1tica (estudios, Servicios, Asesor\u00cda, Formaci\u00d3n)",
    "sg:phone":"+34 958 80 45 21",
    "sg:postcode":"18001",
    "sg:province":"Granada",
    "sg:website":"www.agasystem.es",
    "wof:name":"Aga System",
    "wof:placetype":"venue"
},
  "geometry": {"coordinates":[-3.6056337357,37.181186676],"type":"Point"}
}