{
  "type": "Feature",
  "properties": {
    "iso:country":"ES",
    "sg:address":"Grup Landesa Etxe Taldea, 5",
    "sg:city":"Mungia",
    "sg:orig_category":"Electrodom\u00c9sticos (al Por Menor)",
    "sg:phone":"+34 946 15 58 48",
    "sg:postcode":"48100",
    "sg:province":"Vizcaya",
    "wof:name":"Asociacion Danontzat De Jubilados Y Pensionistas",
    "wof:placetype":"venue"
},
  "geometry": {"coordinates":[-2.8277962208,43.3621711731],"type":"Point"}
}