{
  "type": "Feature",
  "properties": {
    "addr:full":"Rua Conde, 3 Freixeiro Pontevedra 36210",
    "addr:housenumber":"3",
    "addr:postcode":"36210",
    "addr:street":"Rua Conde",
    "iso:country":"ES",
    "sg:address":"Rua Conde, 3",
    "sg:city":"Freixeiro",
    "sg:orig_category":"Ingeniero",
    "sg:phone":"+34 986 42 31 15",
    "sg:postcode":"36210",
    "sg:province":"Pontevedra",
    "wof:name":"Vidal Jabois Maria Luisa",
    "wof:placetype":"venue"
},
  "geometry": {"coordinates":[-8.6428003311,42.4304618835],"type":"Point"}
}