{
  "type": "Feature",
  "properties": {
    "addr:full":"Calle de Caleta De Velez, 53 Malaga M\u00e1laga 29196",
    "addr:housenumber":"53",
    "addr:postcode":"29196",
    "addr:street":"Calle De Caleta De Velez;Ma\u0301Laga",
    "iso:country":"ES",
    "sg:address":"Calle de Caleta De Velez, 53",
    "sg:city":"Malaga",
    "sg:orig_category":"Bebidas",
    "sg:phone":"+34 952 23 77 03",
    "sg:postcode":"29196",
    "sg:province":"M\u00e1laga",
    "wof:name":"Drinks Sol S.l.",
    "wof:placetype":"venue"
},
  "geometry": {"coordinates":[-4.4980940819,36.701374054],"type":"Point"}
}