{
  "type": "Feature",
  "properties": {
    "iso:country":"ES",
    "sg:address":"Pg Marina, 165",
    "sg:city":"Castelldefels",
    "sg:orig_category":"Molduras, Junquillos, Listones Y Molduras Perforadas",
    "sg:phone":"+34 936 64 13 46",
    "sg:postcode":"08860",
    "sg:province":"Barcelona",
    "wof:name":"Borrut Mundo Jaume",
    "wof:placetype":"venue"
},
  "geometry": {"coordinates":[1.9713959694,41.2674217224],"type":"Point"}
}