{
  "type": "Feature",
  "properties": {
    "iso:country":"ES",
    "sg:address":"Calle de Gomera, S/n",
    "sg:city":"Pto. Rosario",
    "sg:orig_category":"Centros De Coordinaci\u00d3n",
    "sg:phone":"+34 928 53 00 76",
    "sg:postcode":"35600",
    "sg:province":"Las Palmas",
    "wof:name":"Gestoria Espino Lopez S.l.",
    "wof:placetype":"venue"
},
  "geometry": {"coordinates":[-13.8657999039,28.5017299652],"type":"Point"}
}