{
  "type": "Feature",
  "properties": {
    "addr:full":"Calle de Lepanto, 12 Pinoso Alicante 03650",
    "addr:housenumber":"12",
    "addr:postcode":"03650",
    "addr:street":"Calle De Lepanto;Alicante",
    "iso:country":"ES",
    "sg:address":"Calle de Lepanto, 12",
    "sg:city":"Pinoso",
    "sg:orig_category":"Reposter\u00cdas",
    "sg:phone":"+34 966 97 01 74",
    "sg:postcode":"03650",
    "sg:province":"Alicante",
    "wof:name":"Albert Garcia Ana Maria",
    "wof:placetype":"venue"
},
  "geometry": {"coordinates":[-1.0402101278,38.4013710022],"type":"Point"}
}