{
  "type": "Feature",
  "properties": {
    "addr:full":"Avda Mar (del), 47 Torreblanca Castell\u00f3n 12596",
    "addr:housenumber":"47",
    "addr:postcode":"12596",
    "addr:street":"Avda Mar Del;Castello\u0301N",
    "iso:country":"ES",
    "sg:address":"Avda Mar (del), 47",
    "sg:city":"Torreblanca",
    "sg:orig_category":"Estancos",
    "sg:phone":"+34 964 42 06 89",
    "sg:postcode":"12596",
    "sg:province":"Castell\u00f3n",
    "wof:name":"Beltri Blas Marga",
    "wof:placetype":"venue"
},
  "geometry": {"coordinates":[0.1963250041,40.2192459106],"type":"Point"}
}