{
  "type": "Feature",
  "properties": {
    "iso:country":"ES",
    "sg:address":"Calle de Juan Ismael, 10",
    "sg:city":"Ejido",
    "sg:orig_category":"Transportes Por V\u00cdas Navegables",
    "sg:phone":"+34 928 69 12 32",
    "sg:postcode":"35200",
    "sg:province":"Las Palmas",
    "wof:name":"Jorge Suarez Juan German",
    "wof:placetype":"venue"
},
  "geometry": {"coordinates":[-15.4250087738,27.9897003174],"type":"Point"}
}