{
  "type": "Feature",
  "properties": {
    "iso:country":"ES",
    "sg:address":"Calle de Azorin, 3",
    "sg:city":"Santa Cruz De Tenerife",
    "sg:orig_category":"Estancos",
    "sg:phone":"+34 922 23 26 31",
    "sg:postcode":"38007",
    "sg:province":"Santa Cruz De Tenerife",
    "wof:name":"Trujillo Lima Maria Candelaria",
    "wof:placetype":"venue"
},
  "geometry": {"coordinates":[-16.265411377,28.4588527679],"type":"Point"}
}