{
  "type": "Feature",
  "properties": {
    "addr:full":"Calle de Francisco Encinas (de), 2 Humanes De Madrid Madrid 28970",
    "addr:postcode":"28970",
    "addr:street":"Calle De Francisco Encinas De 2",
    "iso:country":"ES",
    "sg:address":"Calle de Francisco Encinas (de), 2",
    "sg:city":"Humanes De Madrid",
    "sg:classifiers":[
        {
            "category":"Professional",
            "subcategory":"Business Services",
            "type":"Services"
        }
    ],
    "sg:phone":"+34 914 98 20 88",
    "sg:postcode":"28970",
    "sg:province":"Madrid",
    "sg:tags":[
        "control",
        "asesor\u00cda",
        "organizaci\u00d3n",
        "la",
        "de",
        "gesti\u00d3n",
        "y"
    ],
    "wof:name":"Humanes Gestion S.l.",
    "wof:placetype":"venue"
},
  "geometry": {"coordinates":[-3.8293828964,40.2508163452],"type":"Point"}
}