{
  "type": "Feature",
  "properties": {
    "addr:full":"Plaz Alfonso El Batallador, 1 Huesca Huesca 22002",
    "addr:housenumber":"1",
    "addr:postcode":"22002",
    "addr:street":"Plaz Alfonso El Batallador",
    "iso:country":"ES",
    "sg:address":"Plaz Alfonso El Batallador, 1",
    "sg:city":"Huesca",
    "sg:orig_category":"Molduras, Junquillos, Listones Y Molduras Perforadas",
    "sg:phone":"+34 974 22 90 85",
    "sg:postcode":"22002",
    "sg:province":"Huesca",
    "wof:name":"Jaen Cano Juan",
    "wof:placetype":"venue"
},
  "geometry": {"coordinates":[-0.4068650007,42.1363792419],"type":"Point"}
}