{
  "type": "Feature",
  "properties": {
    "iso:country":"ES",
    "sg:address":"Calle de Tomelloso, S/n",
    "sg:city":"Ciudad Real",
    "sg:orig_category":"Promotores Constructores",
    "sg:phone":"+34 926 21 55 05",
    "sg:postcode":"13005",
    "sg:province":"Ciudad Real",
    "wof:name":"Ciudad Real U.t.e.",
    "wof:placetype":"venue"
},
  "geometry": {"coordinates":[-3.9333031178,38.9733772278],"type":"Point"}
}