{
  "type": "Feature",
  "properties": {
    "iso:country":"ES",
    "sg:address":"Pozairon, 12",
    "sg:city":"Campanario",
    "sg:orig_category":"Agencias Y Agentes Comerciales, Representantes",
    "sg:phone":"+34 924 83 12 87",
    "sg:postcode":"06460",
    "sg:province":"Badajoz",
    "wof:name":"Coronado Ruiz Jose Antonio",
    "wof:placetype":"venue"
},
  "geometry": {"coordinates":[-5.6155891418,38.8644790649],"type":"Point"}
}