{
  "type": "Feature",
  "properties": {
    "iso:country":"ES",
    "sg:address":"Calle de Gaztelu, 24",
    "sg:city":"Donostia-san Sebastian",
    "sg:orig_category":"Empresas De Carpinter\u00cda De Madera",
    "sg:phone":"+34 943 27 43 33",
    "sg:postcode":"20013",
    "sg:province":"Guip\u00f9zcoa",
    "wof:name":"Perez Solano Juan",
    "wof:placetype":"venue"
},
  "geometry": {"coordinates":[-1.9551559687,43.3183937073],"type":"Point"}
}