{
  "type": "Feature",
  "properties": {
    "addr:full":"Ctra Collblanc, 241 Hospitalet Llobregat Barcelona 08906",
    "addr:housenumber":"241",
    "addr:postcode":"08906",
    "addr:street":"Ctra Collblanc",
    "iso:country":"ES",
    "sg:address":"Ctra Collblanc, 241",
    "sg:city":"Hospitalet Llobregat",
    "sg:orig_category":"Internados & Ense\u00d1anza Privada",
    "sg:phone":"+34 934 38 17 45",
    "sg:postcode":"08906",
    "sg:province":"Barcelona",
    "wof:name":"Colegio San Jose Obrero",
    "wof:placetype":"venue"
},
  "geometry": {"coordinates":[2.1010580063,41.3762702942],"type":"Point"}
}