{
  "type": "Feature",
  "properties": {
    "addr:full":"Calle de Farmaceutico Obdulio Fernandez, 9 Burgos Burgos 09006",
    "addr:housenumber":"9",
    "addr:postcode":"09006",
    "addr:street":"Calle De Farmaceutico Obdulio Fernandez",
    "iso:country":"ES",
    "sg:address":"Calle de Farmaceutico Obdulio Fernandez, 9",
    "sg:city":"Burgos",
    "sg:orig_category":"Asilos De Ancianos. Centros Privados",
    "sg:phone":"+34 947 21 10 86",
    "sg:postcode":"09006",
    "sg:province":"Burgos",
    "wof:name":"Residencia El Acebo S.a.l.",
    "wof:placetype":"venue"
},
  "geometry": {"coordinates":[-3.6847939491,42.3453445435],"type":"Point"}
}