{
  "type": "Feature",
  "properties": {
    "iso:country":"ES",
    "sg:address":"Rua San Pedro (de), 41",
    "sg:city":"Santiago De Compostela",
    "sg:orig_category":"Empresas De Portes Y Mensajer\u00cda",
    "sg:phone":"+34 981 57 00 02",
    "sg:postcode":"15703",
    "sg:province":"La Coru\u00f1a",
    "wof:name":"Donaire S.c.",
    "wof:placetype":"venue"
},
  "geometry": {"coordinates":[-8.5383377075,42.8814811707],"type":"Point"}
}