{
  "type": "Feature",
  "properties": {
    "iso:country":"ES",
    "sg:address":"Calle de Cipriano Larra\u00d1aga, 6",
    "sg:city":"Irun",
    "sg:orig_category":"Molduras, Junquillos, Listones Y Molduras Perforadas",
    "sg:phone":"+34 943 61 01 30",
    "sg:postcode":"20302",
    "sg:province":"Guip\u00f9zcoa",
    "wof:name":"Urrutia Aguerreche Juan Jose",
    "wof:placetype":"venue"
},
  "geometry": {"coordinates":[-1.7940380573,43.3410873413],"type":"Point"}
}