{
  "type": "Feature",
  "properties": {
    "addr:full":"Carrer de Ermita (l'), 80 Nucia Alicante 03530",
    "addr:housenumber":"80",
    "addr:postcode":"03530",
    "addr:street":"Carrer De Ermita L '",
    "iso:country":"ES",
    "sg:address":"Carrer de Ermita (l'), 80",
    "sg:city":"Nucia",
    "sg:orig_category":"Caf\u00c9s, Bares, Cervecer\u00cdas",
    "sg:phone":"+34 966 89 65 95",
    "sg:postcode":"03530",
    "sg:province":"Alicante",
    "wof:name":"Paperia Cafeteria Llorensac.b.",
    "wof:placetype":"venue"
},
  "geometry": {"coordinates":[-0.1276880056,38.612361908],"type":"Point"}
}