{
  "type": "Feature",
  "properties": {
    "iso:country":"ES",
    "sg:address":"Avgd Pla D'urgell, 1",
    "sg:city":"Lleida",
    "sg:orig_category":"Suministros Para Hoteles",
    "sg:phone":"+34 973 21 39 16",
    "sg:postcode":"25001",
    "sg:province":"Lleida",
    "wof:name":"Adm Ponent S.l.",
    "wof:placetype":"venue"
},
  "geometry": {"coordinates":[0.6441385746,41.6000404358],"type":"Point"}
}