{
  "type": "Feature",
  "properties": {
    "addr:full":"Calle de Jose Arcones Gil, 82 Madrid Madrid 28017",
    "addr:housenumber":"82",
    "addr:postcode":"madrid;28017",
    "addr:street":"Calle De Jose Arcones Gil",
    "iso:country":"ES",
    "sg:address":"Calle de Jose Arcones Gil, 82",
    "sg:city":"Madrid",
    "sg:orig_category":"Bazares, Art\u00cdculos De Limpieza Y De Cocina (al Por Menor)",
    "sg:phone":"+34 914 08 66 71",
    "sg:postcode":"28017",
    "sg:province":"Madrid",
    "wof:name":"Fuente Dorrego Roberto",
    "wof:placetype":"venue"
},
  "geometry": {"coordinates":[-3.6359379292,40.4308013916],"type":"Point"}
}