{
  "type": "Feature",
  "properties": {
    "addr:full":"Calle de Donoso Cortes, 2 Don Benito Badajoz 06400",
    "addr:housenumber":"2",
    "addr:postcode":"06400",
    "addr:street":"Calle De Donoso Cortes",
    "iso:country":"ES",
    "sg:address":"Calle de Donoso Cortes, 2",
    "sg:city":"Don Benito",
    "sg:orig_category":"Abogados",
    "sg:phone":"+34 924 81 00 45",
    "sg:postcode":"06400",
    "sg:province":"Badajoz",
    "wof:name":"Lobejon Gonzalez Carlos",
    "wof:placetype":"venue"
},
  "geometry": {"coordinates":[-5.8610777855,38.9557228088],"type":"Point"}
}