{
  "type": "Feature",
  "properties": {
    "addr:full":"C/ Mestre Llobet, 14 Tarrega Lleida 25300",
    "addr:housenumber":"14",
    "addr:postcode":"25300",
    "addr:street":"C / Mestre Llobet",
    "iso:country":"ES",
    "sg:address":"C/ Mestre Llobet, 14",
    "sg:city":"Tarrega",
    "sg:orig_category":"Granos Y Forrajes",
    "sg:phone":"+34 973 31 05 81",
    "sg:postcode":"25300",
    "sg:province":"Lleida",
    "wof:name":"Balaguero Muntada Luis",
    "wof:placetype":"venue"
},
  "geometry": {"coordinates":[1.1439534426,41.6493530273],"type":"Point"}
}