{
  "type": "Feature",
  "properties": {
    "iso:country":"ES",
    "sg:address":"Calle de Isla De Lobeira, 75",
    "sg:city":"Collado Villalba",
    "sg:orig_category":"Agencias De Prensa E Informaci\u00d3n",
    "sg:phone":"+34 918 49 70 42",
    "sg:postcode":"28400",
    "sg:province":"Madrid",
    "sg:website":"www.axar.com",
    "wof:name":"Fernandez Casta\u00d1o Pablo",
    "wof:placetype":"venue"
},
  "geometry": {"coordinates":[-4.0185980797,40.6199684143],"type":"Point"}
}