{
  "type": "Feature",
  "properties": {
    "addr:full":"Carr Francesc Layret, 119 Badalona Barcelona 08911",
    "addr:housenumber":"119",
    "addr:postcode":"08911",
    "addr:street":"Carr Francesc Layret",
    "iso:country":"ES",
    "sg:address":"Carr Francesc Layret, 119",
    "sg:city":"Badalona",
    "sg:orig_category":"Psic\u00d3logos",
    "sg:phone":"+34 933 84 46 23",
    "sg:postcode":"08911",
    "sg:province":"Barcelona",
    "wof:name":"Borras Vives Sergi",
    "wof:placetype":"venue"
},
  "geometry": {"coordinates":[2.2481920719,41.4508399963],"type":"Point"}
}