{
  "type": "Feature",
  "properties": {
    "iso:country":"ES",
    "sg:address":"Avda America, 2",
    "sg:city":"Rota",
    "sg:orig_category":"Congelados: Productos Alimentarios (al Por Menor)",
    "sg:phone":"+34 956 84 09 89",
    "sg:postcode":"11520",
    "sg:province":"C\u00e1diz",
    "sg:website":"www.procosur.com",
    "wof:name":"Procosur S.a.",
    "wof:placetype":"venue"
},
  "geometry": {"coordinates":[-6.3606638908,36.6264801025],"type":"Point"}
}