{
  "type": "Feature",
  "properties": {
    "iso:country":"ES",
    "sg:address":"Rua Castelao, 4",
    "sg:city":"Grove",
    "sg:orig_category":"Confecci\u00d3n (fabricaci\u00d3n, Al Por Mayor)",
    "sg:phone":"+34 986 73 05 60",
    "sg:postcode":"36980",
    "sg:province":"Pontevedra",
    "wof:name":"Rico Caneda Francisco",
    "wof:placetype":"venue"
},
  "geometry": {"coordinates":[-8.858622551,42.4910392761],"type":"Point"}
}