{
  "type": "Feature",
  "properties": {
    "iso:country":"ES",
    "sg:address":"Avda Ramon Y Cajal, 51",
    "sg:city":"Almaden",
    "sg:classifiers":[
        {
            "category":"Autos & Motor Vehicles",
            "subcategory":"Automobile Sales",
            "type":"Retail Goods"
        }
    ],
    "sg:phone":"+34 926 71 11 22",
    "sg:postcode":"13400",
    "sg:province":"Ciudad Real",
    "wof:name":"Berrogar S. L.",
    "wof:placetype":"venue"
},
  "geometry": {"coordinates":[-4.8295559883,38.7821083069],"type":"Point"}
}