{
  "type": "Feature",
  "properties": {
    "addr:full":"Avda Europa (de), S/n Jerez De La Frontera C\u00e1diz 11405",
    "addr:postcode":"11405",
    "addr:street":"Avda Europa De S / N",
    "iso:country":"ES",
    "sg:address":"Avda Europa (de), S/n",
    "sg:city":"Jerez De La Frontera",
    "sg:orig_category":"Servicios De Telecomunicaciones",
    "sg:phone":"+34 956 31 19 61",
    "sg:postcode":"11405",
    "sg:province":"C\u00e1diz",
    "wof:name":"Ericcson Espa\u00d1a S.a.",
    "wof:placetype":"venue"
},
  "geometry": {"coordinates":[-6.120223999,36.6962852478],"type":"Point"}
}