{
  "type": "Feature",
  "properties": {
    "addr:full":"Calle de General Aguilera, 3 Ciudad Real Ciudad Real 13001",
    "addr:housenumber":"3",
    "addr:postcode":"13001",
    "addr:street":"Calle De General Aguilera",
    "iso:country":"ES",
    "sg:address":"Calle de General Aguilera, 3",
    "sg:city":"Ciudad Real",
    "sg:orig_category":"Abogados",
    "sg:phone":"+34 926 22 35 56",
    "sg:postcode":"13001",
    "sg:province":"Ciudad Real",
    "wof:name":"Cuellar Sen Jesus",
    "wof:placetype":"venue"
},
  "geometry": {"coordinates":[-3.9279370308,38.9846878052],"type":"Point"}
}