{
  "type": "Feature",
  "properties": {
    "iso:country":"ES",
    "sg:address":"Rcial El Sol, 17",
    "sg:city":"Salobre\u00f1a",
    "sg:orig_category":"Discotecas Y Salas De Baile",
    "sg:phone":"+34 958 61 26 26",
    "sg:postcode":"18680",
    "sg:province":"Granada",
    "wof:name":"Toro Funes Francisco",
    "wof:placetype":"venue"
},
  "geometry": {"coordinates":[-3.5866270065,36.7461280823],"type":"Point"}
}