{
  "type": "Feature",
  "properties": {
    "addr:full":"Avda Fontanilla (de La), 6 Utrera Sevilla 41710",
    "addr:housenumber":"6",
    "addr:postcode":"41710",
    "addr:street":"Avda Fontanilla De La",
    "iso:country":"ES",
    "sg:address":"Avda Fontanilla (de La), 6",
    "sg:city":"Utrera",
    "sg:classifiers":[
        {
            "category":"Taxi",
            "type":"Transportation"
        }
    ],
    "sg:phone":"+34 954 86 18 20",
    "sg:postcode":"41710",
    "sg:province":"Sevilla",
    "wof:name":"Dorado Fernandez Felipe",
    "wof:placetype":"venue"
},
  "geometry": {"coordinates":[-5.7929692268,37.1812019348],"type":"Point"}
}