{
  "type": "Feature",
  "properties": {
    "addr:full":"Calle de Virgen De Iciar, 20 Alcorcon Madrid 28921",
    "addr:housenumber":"20",
    "addr:postcode":"28921",
    "addr:street":"Calle De Virgen De Iciar",
    "iso:country":"ES",
    "sg:address":"Calle de Virgen De Iciar, 20",
    "sg:city":"Alcorcon",
    "sg:orig_category":"Institutos De Belleza",
    "sg:phone":"+34 916 43 28 51",
    "sg:postcode":"28921",
    "sg:province":"Madrid",
    "wof:name":"Alvarez Cachinero Josefa",
    "wof:placetype":"venue"
},
  "geometry": {"coordinates":[-3.8290429115,40.3450737],"type":"Point"}
}