{
  "type": "Feature",
  "properties": {
    "addr:full":"Avda Florida, 179 Vigo Pontevedra 36210",
    "addr:housenumber":"179",
    "addr:postcode":"36210",
    "addr:street":"Avda Florida",
    "iso:country":"ES",
    "sg:address":"Avda Florida, 179",
    "sg:city":"Vigo",
    "sg:orig_category":"Molduras, Junquillos, Listones Y Molduras Perforadas",
    "sg:phone":"+34 986 23 20 66",
    "sg:postcode":"36210",
    "sg:province":"Pontevedra",
    "wof:name":"Diaz Prieto Manuel",
    "wof:placetype":"venue"
},
  "geometry": {"coordinates":[-8.7487869263,42.2091178894],"type":"Point"}
}