{
  "type": "Feature",
  "properties": {
    "iso:country":"ES",
    "sg:address":"Calle de Manuel Picar Morales, 4",
    "sg:city":"Barrio Del Pino",
    "sg:orig_category":"Panader\u00cdas, Panader\u00cdas",
    "sg:phone":"+34 928 63 21 87",
    "sg:postcode":"35330",
    "sg:province":"Las Palmas",
    "wof:name":"Dulcica S.l.",
    "wof:placetype":"venue"
},
  "geometry": {"coordinates":[-15.5451288223,28.0638542175],"type":"Point"}
}