{
  "type": "Feature",
  "properties": {
    "addr:full":"Av Catalunya, 46 S. Antoni Calonge Girona 17252",
    "addr:housenumber":"46",
    "addr:postcode":"17252",
    "addr:street":"Av Catalunya",
    "iso:country":"ES",
    "sg:address":"Av Catalunya, 46",
    "sg:city":"S. Antoni Calonge",
    "sg:orig_category":"Inmobiliaria (agencias)",
    "sg:phone":"+34 972 66 15 58",
    "sg:postcode":"17252",
    "sg:province":"Girona",
    "wof:name":"Monde Property Brokers S.l.",
    "wof:placetype":"venue"
},
  "geometry": {"coordinates":[3.099670887,41.8468894958],"type":"Point"}
}