{
  "type": "Feature",
  "properties": {
    "iso:country":"ES",
    "sg:address":"Carr Gutierrez Mas, 12",
    "sg:city":"Gandia",
    "sg:orig_category":"Edici\u00d3n De Diarios, Revistas, Boletines",
    "sg:phone":"+34 962 87 39 95",
    "sg:postcode":"46700",
    "sg:province":"Valencia",
    "wof:name":"Editorial Prensa Valenciana S.a.",
    "wof:placetype":"venue"
},
  "geometry": {"coordinates":[-0.1913339943,38.960735321],"type":"Point"}
}