{
  "type": "Feature",
  "properties": {
    "addr:full":"Calle de Lilas, 6 Monteclaro-la Caba\u00e7a Madrid 28223",
    "addr:housenumber":"6",
    "addr:postcode":"28223",
    "addr:street":"Calle De Lilas",
    "iso:country":"ES",
    "sg:address":"Calle de Lilas, 6",
    "sg:city":"Monteclaro-la Caba\u00e7a",
    "sg:orig_category":"Cursos Particulares, Asistencia Escolar",
    "sg:phone":"+34 913 51 85 52",
    "sg:postcode":"28223",
    "sg:province":"Madrid",
    "wof:name":"Loizard Informaticos S.l",
    "wof:placetype":"venue"
},
  "geometry": {"coordinates":[-3.8480839729,40.4387969971],"type":"Point"}
}