{
  "type": "Feature",
  "properties": {
    "addr:full":"Calle de Sicilia, 37 Madrid Madrid 28038",
    "addr:housenumber":"37",
    "addr:postcode":"madrid;28038",
    "addr:street":"Calle De Sicilia",
    "iso:country":"ES",
    "sg:address":"Calle de Sicilia, 37",
    "sg:city":"Madrid",
    "sg:orig_category":"Electrodom\u00c9sticos (al Por Menor)",
    "sg:phone":"+34 914 33 53 56",
    "sg:postcode":"28038",
    "sg:province":"Madrid",
    "wof:name":"Repmarc S.l.",
    "wof:placetype":"venue"
},
  "geometry": {"coordinates":[-3.665594101,40.4025764465],"type":"Point"}
}