{
  "type": "Feature",
  "properties": {
    "addr:full":"Calle de Ancha De Gracia, 9 Granada Granada 18004",
    "addr:housenumber":"9",
    "addr:postcode":"18004",
    "addr:street":"Calle De Ancha De Gracia",
    "iso:country":"ES",
    "sg:address":"Calle de Ancha De Gracia, 9",
    "sg:city":"Granada",
    "sg:orig_category":"Material Y Suministros Para Imprenta E Industrias Gr\u00c1ficas",
    "sg:phone":"+34 958 25 58 70",
    "sg:postcode":"18004",
    "sg:province":"Granada",
    "wof:name":"Bermudo Gomez Pablo",
    "wof:placetype":"venue"
},
  "geometry": {"coordinates":[-3.6056981087,37.1714553833],"type":"Point"}
}