{
  "type": "Feature",
  "properties": {
    "iso:country":"ES",
    "sg:address":"Calle de Hornos, 4",
    "sg:city":"Caldas De Reis",
    "sg:orig_category":"Centros De Coordinaci\u00d3n",
    "sg:phone":"+34 986 54 14 00",
    "sg:postcode":"36650",
    "sg:province":"Pontevedra",
    "wof:name":"Wuam S.l.",
    "wof:placetype":"venue"
},
  "geometry": {"coordinates":[-8.6710605621,42.623085022],"type":"Point"}
}