{
  "type": "Feature",
  "properties": {
    "addr:full":"Luga Ensenada Miraflores, 5 Taraguilla C\u00e1diz 11368",
    "addr:housenumber":"5",
    "addr:postcode":"11368",
    "addr:street":"Miraflores;Ca\u0301Diz",
    "iso:country":"ES",
    "sg:address":"Luga Ensenada Miraflores, 5",
    "sg:city":"Taraguilla",
    "sg:orig_category":"Asociaciones Y Clubs Deportivos",
    "sg:phone":"+34 956 61 23 66",
    "sg:postcode":"11368",
    "sg:province":"C\u00e1diz",
    "wof:name":"Club Deportivo Miraflores",
    "wof:placetype":"venue"
},
  "geometry": {"coordinates":[-5.4333500862,36.2157821655],"type":"Point"}
}