{
  "type": "Feature",
  "properties": {
    "addr:full":"Calle de Lugo, 15 Arzua La Coru\u00f1a 15810",
    "addr:housenumber":"15",
    "addr:postcode":"15810",
    "addr:street":"Calle De Lugo;La Corun\u0303A",
    "iso:country":"ES",
    "sg:address":"Calle de Lugo, 15",
    "sg:city":"Arzua",
    "sg:orig_category":"Ingeniero",
    "sg:phone":"+34 981 50 00 71",
    "sg:postcode":"15810",
    "sg:province":"La Coru\u00f1a",
    "wof:name":"Cambon Loureiro Eladio",
    "wof:placetype":"venue"
},
  "geometry": {"coordinates":[-8.1634550095,42.9267272949],"type":"Point"}
}