{
  "type": "Feature",
  "properties": {
    "iso:country":"ES",
    "sg:address":"C/ Manuel De Falla, 27",
    "sg:city":"Salt",
    "sg:orig_category":"Cr\u00cda De Animales",
    "sg:phone":"+34 972 24 56 29",
    "sg:postcode":"17190",
    "sg:province":"Girona",
    "wof:name":"Qui Bat Salt S.l",
    "wof:placetype":"venue"
},
  "geometry": {"coordinates":[2.7919089794,41.9761581421],"type":"Point"}
}