{
  "type": "Feature",
  "properties": {
    "iso:country":"ES",
    "sg:address":"Calle de Cantarranas, S/n",
    "sg:city":"Sotresgudo",
    "sg:orig_category":"Ense\u00d1anza, Formaci\u00d3n Profesional: Aprendizaje",
    "sg:phone":"+34 947 36 04 45",
    "sg:postcode":"09135",
    "sg:province":"Burgos",
    "wof:name":"Ayuntamiento De Sotresgudo",
    "wof:placetype":"venue"
},
  "geometry": {"coordinates":[-4.1762876511,42.5791740417],"type":"Point"}
}