{
  "type": "Feature",
  "properties": {
    "iso:country":"ES",
    "sg:address":"Urb Montecorona, 6",
    "sg:city":"Sabi\u00f1anigo",
    "sg:orig_category":"Empresas De Pintura Y Revestimientos",
    "sg:phone":"+34 974 48 26 60",
    "sg:postcode":"22600",
    "sg:province":"Huesca",
    "wof:name":"Grasa Rodriguez Jose Luis",
    "wof:placetype":"venue"
},
  "geometry": {"coordinates":[-0.3684540093,42.5186843872],"type":"Point"}
}