{
  "type": "Feature",
  "properties": {
    "addr:full":"Calle de Jacinto Verdaguer, 34 Madrid Madrid 28019",
    "addr:housenumber":"34",
    "addr:postcode":"madrid;28019",
    "addr:street":"Calle De Jacinto Verdaguer",
    "iso:country":"ES",
    "sg:address":"Calle de Jacinto Verdaguer, 34",
    "sg:city":"Madrid",
    "sg:orig_category":"Asociaciones, Organismos Culturales Y Socioeducativos",
    "sg:phone":"+34 914 72 96 99",
    "sg:postcode":"28019",
    "sg:province":"Madrid",
    "wof:name":"Acude San Miguel",
    "wof:placetype":"venue"
},
  "geometry": {"coordinates":[-3.7185211182,40.3952522278],"type":"Point"}
}