{
  "type": "Feature",
  "properties": {
    "iso:country":"ES",
    "sg:address":"Avgd Gregorio Molina, 11",
    "sg:city":"Xativa",
    "sg:orig_category":"Mec\u00c1nico Del Autom\u00d3vil",
    "sg:phone":"+34 962 27 21 18",
    "sg:postcode":"46800",
    "sg:province":"Valencia",
    "wof:name":"Coxauto S. C. L",
    "wof:placetype":"venue"
},
  "geometry": {"coordinates":[-0.5226439834,38.991519928],"type":"Point"}
}