{
  "type": "Feature",
  "properties": {
    "iso:country":"ES",
    "sg:address":"Rua Cami\u00d1o Novo, 7",
    "sg:city":"Carballo",
    "sg:orig_category":"Centros De Coordinaci\u00d3n",
    "sg:phone":"+34 981 75 67 09",
    "sg:postcode":"15100",
    "sg:province":"La Coru\u00f1a",
    "wof:name":"Jimeno Monteagudo Daniel",
    "wof:placetype":"venue"
},
  "geometry": {"coordinates":[-8.6909017563,43.2130508423],"type":"Point"}
}