{
  "type": "Feature",
  "properties": {
    "addr:full":"Av Eramprunya (l'), 4 Gava Barcelona 08850",
    "addr:housenumber":"4",
    "addr:postcode":"08850",
    "addr:street":"Av Eramprunya L '",
    "iso:country":"ES",
    "sg:address":"Av Eramprunya (l'), 4",
    "sg:city":"Gava",
    "sg:orig_category":"Centros Empresariales",
    "sg:phone":"+34 936 38 28 02",
    "sg:postcode":"08850",
    "sg:province":"Barcelona",
    "wof:name":"Construbrokers S.l",
    "wof:placetype":"venue"
},
  "geometry": {"coordinates":[1.9995499849,41.309211731],"type":"Point"}
}