{
  "type": "Feature",
  "properties": {
    "iso:country":"ES",
    "sg:address":"Calle de Madreselva, 5",
    "sg:city":"Navalmoral Mata",
    "sg:orig_category":"Agencias Y Asesores De Publicidad",
    "sg:phone":"+34 927 53 45 52",
    "sg:postcode":"10300",
    "sg:province":"C\u00e1ceres",
    "wof:name":"Punto De Encuentro Comunicacion S.l.u.",
    "wof:placetype":"venue"
},
  "geometry": {"coordinates":[-5.5419192314,39.8933410645],"type":"Point"}
}