{
  "type": "Feature",
  "properties": {
    "iso:country":"ES",
    "sg:address":"Calle de Gordoniz, 10",
    "sg:city":"Bilbao",
    "sg:orig_category":"Ense\u00d1anza Superior Privada",
    "sg:phone":"+34 944 70 12 76",
    "sg:postcode":"48010",
    "sg:province":"Vizcaya",
    "wof:name":"Colegio Mayor Bidealde",
    "wof:placetype":"venue"
},
  "geometry": {"coordinates":[-2.9394640923,43.2592582703],"type":"Point"}
}