{
  "type": "Feature",
  "properties": {
    "iso:country":"ES",
    "sg:address":"Calle de Arrabal, 35",
    "sg:city":"Binefar",
    "sg:orig_category":"Congelados: Productos Alimentarios (al Por Menor)",
    "sg:phone":"+34 974 43 00 60",
    "sg:postcode":"22500",
    "sg:province":"Huesca",
    "wof:name":"Arpa Ascaso Francisco Javier",
    "wof:placetype":"venue"
},
  "geometry": {"coordinates":[0.2948797047,41.8447952271],"type":"Point"}
}