{
  "type": "Feature",
  "properties": {
    "addr:full":"Carrer de Llibertat, 71 Ametlla Mar Tarragona 43860",
    "addr:housenumber":"71",
    "addr:postcode":"43860",
    "addr:street":"Carrer De Llibertat",
    "iso:country":"ES",
    "sg:address":"Carrer de Llibertat, 71",
    "sg:city":"Ametlla Mar",
    "sg:orig_category":"Muebles, Minoristas",
    "sg:phone":"+34 977 45 64 62",
    "sg:postcode":"43860",
    "sg:province":"Tarragona",
    "wof:name":"Samarra Estrada Maria Del Carmen",
    "wof:placetype":"venue"
},
  "geometry": {"coordinates":[0.8036230206,40.8867607117],"type":"Point"}
}