{
  "type": "Feature",
  "properties": {
    "iso:country":"ES",
    "sg:address":"Abejeras, 20",
    "sg:city":"Iru\u00f1a",
    "sg:orig_category":"Frutas, Legumbres Frescas Y Tempranas (al Por Menor)",
    "sg:phone":"+34 948 27 03 14",
    "sg:postcode":"31007",
    "sg:province":"Navarra",
    "wof:name":"Perez Ramos Aurelio",
    "wof:placetype":"venue"
},
  "geometry": {"coordinates":[-1.6461720467,42.8053855896],"type":"Point"}
}