{
  "type": "Feature",
  "properties": {
    "iso:country":"ES",
    "sg:address":"Avda Cosculluela, 8",
    "sg:city":"Ejea De Los Caballeros",
    "sg:orig_category":"Arquitectos",
    "sg:phone":"+34 976 66 07 01",
    "sg:postcode":"50600",
    "sg:province":"Zaragoza",
    "wof:name":"Sagaste Bericat Rafael",
    "wof:placetype":"venue"
},
  "geometry": {"coordinates":[-1.1383529902,42.123626709],"type":"Point"}
}