{
  "type": "Feature",
  "properties": {
    "iso:country":"ES",
    "sg:address":"Cromo (p I Calonge), 60",
    "sg:city":"Sevilla",
    "sg:orig_category":"Centros Empresariales",
    "sg:phone":"+34 902 42 12 12",
    "sg:postcode":"41007",
    "sg:province":"Sevilla",
    "sg:website":"www.seviser.com",
    "wof:name":"Seviser Mantenimiento Integral S.l.",
    "wof:placetype":"venue"
},
  "geometry": {"coordinates":[-5.9572339058,37.406463623],"type":"Point"}
}