{
  "type": "Feature",
  "properties": {
    "addr:full":"Calle de Paseo Del Majuelo, 21 Rinconada Sevilla 41309",
    "addr:housenumber":"21",
    "addr:postcode":"41309",
    "addr:street":"Calle De Paseo Del Majuelo",
    "iso:country":"ES",
    "sg:address":"Calle de Paseo Del Majuelo, 21",
    "sg:city":"Rinconada",
    "sg:orig_category":"Ense\u00d1anza Variada",
    "sg:phone":"+34 955 79 74 46",
    "sg:postcode":"41309",
    "sg:province":"Sevilla",
    "wof:name":"Vargas Serrano Maria Dolores",
    "wof:placetype":"venue"
},
  "geometry": {"coordinates":[-5.9782538414,37.492855072],"type":"Point"}
}