{
  "type": "Feature",
  "properties": {
    "addr:full":"Av. Can Amat (pol Barcelones), 10 Abrera Barcelona 08630",
    "addr:housenumber":"10",
    "addr:postcode":"08630",
    "addr:street":"Av. Can Amat;Barcelones",
    "iso:country":"ES",
    "sg:address":"Av. Can Amat (pol Barcelones), 10",
    "sg:city":"Abrera",
    "sg:classifiers":[
        {
            "category":"Banks & Credit Unions",
            "subcategory":"Bureau De Change",
            "type":"Services"
        }
    ],
    "sg:phone":"+34 937 70 15 37",
    "sg:postcode":"08630",
    "sg:province":"Barcelona",
    "sg:tags":[
        "organismos",
        "control"
    ],
    "wof:name":"Prototech System S.l.",
    "wof:placetype":"venue"
},
  "geometry": {"coordinates":[1.8970760107,41.5067977905],"type":"Point"}
}