{
  "type": "Feature",
  "properties": {
    "iso:country":"ES",
    "sg:address":"Calle de Mar Amarillo, 10",
    "sg:city":"Madrid",
    "sg:orig_category":"Tintorer\u00cdas, Limpieza En Seco",
    "sg:phone":"+34 917 64 27 04",
    "sg:postcode":"28033",
    "sg:province":"Madrid",
    "wof:name":"Barroso Calderon Juan Antonio",
    "wof:placetype":"venue"
},
  "geometry": {"coordinates":[-3.6412789822,40.4743003845],"type":"Point"}
}