{
  "type": "Feature",
  "properties": {
    "iso:country":"ES",
    "sg:address":"Joaquin Lopez, 2",
    "sg:city":"Playas Telde",
    "sg:orig_category":"Electricidad: Equipos Industriales, Componentes (fabricaci\u00d3n)",
    "sg:phone":"+34 928 70 40 72",
    "sg:postcode":"35214",
    "sg:province":"Las Palmas",
    "wof:name":"Instaladora Quintana S. A. L.",
    "wof:placetype":"venue"
},
  "geometry": {"coordinates":[-15.3901338577,27.9967041016],"type":"Point"}
}