{
  "type": "Feature",
  "properties": {
    "iso:country":"ES",
    "sg:address":"Pol Ind Costa Del Sol, 14",
    "sg:city":"Marbella",
    "sg:orig_category":"Panader\u00cdas, Panader\u00cdas",
    "sg:phone":"+34 952 82 90 01",
    "sg:postcode":"29600",
    "sg:province":"M\u00e1laga",
    "wof:name":"Saint Honore S.cv.",
    "wof:placetype":"venue"
},
  "geometry": {"coordinates":[-4.8833007812,36.5079956055],"type":"Point"}
}