{
  "type": "Feature",
  "properties": {
    "iso:country":"ES",
    "sg:address":"Calle de Zamacola, 2",
    "sg:city":"Bilbao",
    "sg:orig_category":"Tapicer\u00cdas",
    "sg:phone":"+34 944 15 03 86",
    "sg:postcode":"48003",
    "sg:province":"Vizcaya",
    "wof:name":"Angulo Ugarte Ignacio",
    "wof:placetype":"venue"
},
  "geometry": {"coordinates":[-2.9219841957,43.2498703003],"type":"Point"}
}