{
  "type": "Feature",
  "properties": {
    "addr:full":"Plaz Cristo De Burgos, 7 Sevilla Sevilla 41003",
    "addr:housenumber":"7",
    "addr:postcode":"41003",
    "addr:street":"Burgos",
    "iso:country":"ES",
    "sg:address":"Plaz Cristo De Burgos, 7",
    "sg:city":"Sevilla",
    "sg:orig_category":"Art\u00cdculos De Regalo (al Por Menor)",
    "sg:phone":"+34 954 21 18 77",
    "sg:postcode":"41003",
    "sg:province":"Sevilla",
    "sg:website":"www.kanaima.net",
    "wof:name":"Corada Gomez Roberto",
    "wof:placetype":"venue"
},
  "geometry": {"coordinates":[-5.989397049,37.3921203613],"type":"Point"}
}