{
  "type": "Feature",
  "properties": {
    "iso:country":"ES",
    "sg:address":"Calle de Benizalon, 6",
    "sg:city":"Almeria",
    "sg:orig_category":"Comercio De Piezas De Recambio Y De Accesorios De Veh\u00cdculos, Veh\u00cdculos Industriales",
    "sg:phone":"+34 950 14 36 11",
    "sg:postcode":"04007",
    "sg:province":"Almer\u00eda",
    "wof:name":"Frenos Sanchez S.a.",
    "wof:placetype":"venue"
},
  "geometry": {"coordinates":[-2.4448468685,36.8370552063],"type":"Point"}
}