{
  "type": "Feature",
  "properties": {
    "addr:full":"Calle de Parroco Don Emilio Franco, 51 Madrid Madrid 28053",
    "addr:housenumber":"51",
    "addr:postcode":"madrid;28053",
    "addr:street":"Calle De Parroco;Franco",
    "iso:country":"ES",
    "sg:address":"Calle de Parroco Don Emilio Franco, 51",
    "sg:city":"Madrid",
    "sg:orig_category":"Chapa Y Pintura Veh\u00cdculos",
    "sg:phone":"+34 914 78 12 12",
    "sg:postcode":"28053",
    "sg:province":"Madrid",
    "wof:name":"Motor Vallecas Madrid S.a.",
    "wof:placetype":"venue"
},
  "geometry": {"coordinates":[-3.6669449806,40.3902931213],"type":"Point"}
}