{
  "type": "Feature",
  "properties": {
    "iso:country":"ES",
    "sg:address":"C/ Ondategui, 48",
    "sg:city":"Cala Blava",
    "sg:orig_category":"Ense\u00d1anza: Idiomas",
    "sg:phone":"+34 971 78 65 26",
    "sg:postcode":"07609",
    "sg:province":"Islas Baleares",
    "sg:website":"www.ef.com",
    "wof:name":"E.f. Colegios Europeos De Verano",
    "wof:placetype":"venue"
},
  "geometry": {"coordinates":[2.7507419586,39.4544181824],"type":"Point"}
}