{
  "type": "Feature",
  "properties": {
    "iso:country":"ES",
    "sg:address":"Carrer de Santa Teresa, 8",
    "sg:city":"Barcelona",
    "sg:orig_category":"Expertos Contables, Revisores De Cuentas",
    "sg:phone":"+34 932 17 74 19",
    "sg:postcode":"08012",
    "sg:province":"Barcelona",
    "wof:name":"Laes Nexia Ac S.l.",
    "wof:placetype":"venue"
},
  "geometry": {"coordinates":[2.1597659588,41.3977012634],"type":"Point"}
}