{
  "type": "Feature",
  "properties": {
    "addr:full":"S. Mart\u00edn, 12 Soria Soria 42004",
    "addr:housenumber":"12",
    "addr:postcode":"42004",
    "addr:street":"Marti\u0301N",
    "iso:country":"ES",
    "sg:address":"S. Mart\u00edn, 12",
    "sg:city":"Soria",
    "sg:orig_category":"Electrodom\u00c9sticos (fabricaci\u00d3n, Al Por Mayor)",
    "sg:phone":"+34 975 23 24 00",
    "sg:postcode":"42004",
    "sg:province":"Soria",
    "wof:name":"Representaciones Latorre S.l.",
    "wof:placetype":"venue"
},
  "geometry": {"coordinates":[-2.4691669941,41.7646598816],"type":"Point"}
}