{
  "type": "Feature",
  "properties": {
    "iso:country":"ES",
    "sg:address":"Carrer de Pi I Margall, 2",
    "sg:city":"Barcelona",
    "sg:orig_category":"Ropa Para Se\u00d1oras (al Por Menor)",
    "sg:phone":"+34 932 85 00 91",
    "sg:postcode":"08025",
    "sg:province":"Barcelona",
    "wof:name":"Garcia Garcia-villaraco Maria Josefa",
    "wof:placetype":"venue"
},
  "geometry": {"coordinates":[2.1631519794,41.4055480957],"type":"Point"}
}