{
  "type": "Feature",
  "properties": {
    "addr:full":"Calle de Hermanos Garcia Noblejas, 18 Madrid Madrid 28037",
    "addr:housenumber":"18",
    "addr:postcode":"madrid;28037",
    "addr:street":"Calle De Hermanos Garcia Noblejas",
    "iso:country":"ES",
    "sg:address":"Calle de Hermanos Garcia Noblejas, 18",
    "sg:city":"Madrid",
    "sg:orig_category":"Delegados, Agentes De Tr\u00c1nsito, Auxiliares De Transporte Internacional",
    "sg:phone":"+34 914 06 15 63",
    "sg:postcode":"28037",
    "sg:province":"Madrid",
    "sg:website":"www.tammotor.com",
    "wof:name":"Tam Motor S.a.",
    "wof:placetype":"venue"
},
  "geometry": {"coordinates":[-3.6365630627,40.4355392456],"type":"Point"}
}