{
  "type": "Feature",
  "properties": {
    "addr:full":"Calle de Lasierra Purroy, 47 Zaragoza Zaragoza 50007",
    "addr:housenumber":"47",
    "addr:postcode":"50007",
    "addr:street":"Calle De Lasierra Purroy",
    "iso:country":"ES",
    "sg:address":"Calle de Lasierra Purroy, 47",
    "sg:city":"Zaragoza",
    "sg:orig_category":"Molduras, Junquillos, Listones Y Molduras Perforadas",
    "sg:phone":"+34 976 27 51 20",
    "sg:postcode":"50007",
    "sg:province":"Zaragoza",
    "wof:name":"Sasal Fuertes Sergio",
    "wof:placetype":"venue"
},
  "geometry": {"coordinates":[-0.8839250207,41.6287155151],"type":"Point"}
}