{
  "type": "Feature",
  "properties": {
    "iso:country":"ES",
    "sg:address":"Calle de Santa Ana, 65",
    "sg:city":"Le\u00f3n",
    "sg:orig_category":"Peluquer\u00cdas, Peluquer\u00cda Mixta",
    "sg:phone":"+34 987 20 73 20",
    "sg:postcode":"24006",
    "sg:province":"Le\u00f3n",
    "wof:name":"Blanco Gonzalez Rosa",
    "wof:placetype":"venue"
},
  "geometry": {"coordinates":[-5.5649700165,42.5923957825],"type":"Point"}
}