{
  "type": "Feature",
  "properties": {
    "iso:country":"ES",
    "sg:address":"Carrer de Valencia, 11",
    "sg:city":"Barcelona",
    "sg:orig_category":"Comercio Y Bancos",
    "sg:phone":"+34 932 26 53 56",
    "sg:postcode":"08015",
    "sg:province":"Barcelona",
    "wof:name":"Farmacia Militar Depositos De Medicamentos De Barcelona",
    "wof:placetype":"venue"
},
  "geometry": {"coordinates":[2.1463489532,41.380115509],"type":"Point"}
}