{
  "type": "Feature",
  "properties": {
    "addr:full":"Calle de Obispo Rocamora, 15 Orihuela Alicante 03300",
    "addr:housenumber":"15",
    "addr:postcode":"03300",
    "addr:street":"Calle De Obispo Rocamora",
    "iso:country":"ES",
    "sg:address":"Calle de Obispo Rocamora, 15",
    "sg:city":"Orihuela",
    "sg:orig_category":"Colchones (fabricaci\u00d3n, Al Por Mayor, Al Por Menor)",
    "sg:phone":"+34 966 73 92 68",
    "sg:postcode":"03300",
    "sg:province":"Alicante",
    "sg:website":"www.beeds.es",
    "wof:name":"Muebles Viuda S. L.",
    "wof:placetype":"venue"
},
  "geometry": {"coordinates":[-0.9438629746,38.0838737488],"type":"Point"}
}