{
  "type": "Feature",
  "properties": {
    "iso:country":"ES",
    "sg:address":"Calle de Ancha, 5",
    "sg:city":"Medina Rioseco",
    "sg:orig_category":"Inform\u00c1tica, Ofim\u00c1tica (estudios, Asesor\u00cda, Ingenier\u00cda, Formaci\u00d3n)",
    "sg:phone":"+34 983 70 05 63",
    "sg:postcode":"47800",
    "sg:province":"Valladolid",
    "wof:name":"Izquierdo Pascual Olga",
    "wof:placetype":"venue"
},
  "geometry": {"coordinates":[-5.0453515053,41.8839683533],"type":"Point"}
}