{
  "type": "Feature",
  "properties": {
    "addr:full":"Avda Vivar Tellez, S/n Velez-malaga M\u00e1laga 29700",
    "addr:housenumber":"s / n",
    "addr:postcode":"29700",
    "addr:street":"Avda Vivar Tellez",
    "iso:country":"ES",
    "sg:address":"Avda Vivar Tellez, S/n",
    "sg:city":"Velez-malaga",
    "sg:orig_category":"Heladeros",
    "sg:phone":"+34 952 50 21 96",
    "sg:postcode":"29700",
    "sg:province":"M\u00e1laga",
    "wof:name":"Garrigos Martinez Ana",
    "wof:placetype":"venue"
},
  "geometry": {"coordinates":[-4.1001439095,36.7758712769],"type":"Point"}
}