{
  "type": "Feature",
  "properties": {
    "addr:full":"Avda Agua Marina, 135 Algeciras C\u00e1diz 11203",
    "addr:housenumber":"135;ca\u0301diz",
    "addr:postcode":"11203",
    "addr:street":"Avda Agua Marina",
    "iso:country":"ES",
    "sg:address":"Avda Agua Marina, 135",
    "sg:city":"Algeciras",
    "sg:orig_category":"Chapister\u00cda",
    "sg:phone":"+34 956 66 13 04",
    "sg:postcode":"11203",
    "sg:province":"C\u00e1diz",
    "wof:name":"Garcia Ruiz Angel",
    "wof:placetype":"venue"
},
  "geometry": {"coordinates":[-5.4613690376,36.1293945312],"type":"Point"}
}