{
  "type": "Feature",
  "properties": {
    "iso:country":"ES",
    "sg:address":"Pl Cuba, 11",
    "sg:city":"Mataro",
    "sg:orig_category":"Zapatos (al Por Menor)",
    "sg:phone":"+34 937 98 68 03",
    "sg:postcode":"08302",
    "sg:province":"Barcelona",
    "wof:name":"Boixet Marti Francesc",
    "wof:placetype":"venue"
},
  "geometry": {"coordinates":[2.44074893,41.5378684998],"type":"Point"}
}