{
  "type": "Feature",
  "properties": {
    "iso:country":"ES",
    "sg:address":"Carrer de L'acer, S/n",
    "sg:city":"Barcelona",
    "sg:orig_category":"Fabricaci\u00d3n De Mobiliario De Oficina",
    "sg:phone":"+34 932 89 50 85",
    "sg:postcode":"08038",
    "sg:province":"Barcelona",
    "wof:name":"Haworth Espa\u00d1a S.l.",
    "wof:placetype":"venue"
},
  "geometry": {"coordinates":[2.1360003948,41.3528862],"type":"Point"}
}