{
  "type": "Feature",
  "properties": {
    "addr:full":"Carrer de Elisenda De Montcada, 17 Premia Mar Barcelona 08330",
    "addr:housenumber":"17",
    "addr:postcode":"08330",
    "addr:street":"Carrer De Elisenda De Montcada",
    "iso:country":"ES",
    "sg:address":"Carrer de Elisenda De Montcada, 17",
    "sg:city":"Premia Mar",
    "sg:orig_category":"Fabricaci\u00d3n De Moldes Y Modelos",
    "sg:phone":"+34 937 52 37 72",
    "sg:postcode":"08330",
    "sg:province":"Barcelona",
    "wof:name":"Bravo Lopez Francisco",
    "wof:placetype":"venue"
},
  "geometry": {"coordinates":[2.360683918,41.4916648865],"type":"Point"}
}