{
  "type": "Feature",
  "properties": {
    "iso:country":"ES",
    "sg:address":"O Castro, S/n",
    "sg:city":"Castro",
    "sg:orig_category":"Serrer\u00cdas De Madera",
    "sg:phone":"+34 982 37 91 09",
    "sg:postcode":"27576",
    "sg:province":"Lugo",
    "wof:name":"Varela Carnero Manuel",
    "wof:placetype":"venue"
},
  "geometry": {"coordinates":[-7.9309139252,42.7772750854],"type":"Point"}
}