{
  "type": "Feature",
  "properties": {
    "addr:full":"Iparragirre Kalea, 21 Urretxu Guip\u00f9zcoa 20700",
    "addr:housenumber":"21",
    "addr:postcode":"20700",
    "addr:street":"Iparragirre Kalea;Guipu\u0300Zcoa",
    "iso:country":"ES",
    "sg:address":"Iparragirre Kalea, 21",
    "sg:city":"Urretxu",
    "sg:orig_category":"Quincaller\u00cda (al Por Menor)",
    "sg:phone":"+34 943 72 21 04",
    "sg:postcode":"20700",
    "sg:province":"Guip\u00f9zcoa",
    "wof:name":"Elgarresta Arregui Eusebio",
    "wof:placetype":"venue"
},
  "geometry": {"coordinates":[-2.3135249615,43.0940170288],"type":"Point"}
}