{
  "type": "Feature",
  "properties": {
    "iso:country":"ES",
    "sg:address":"Plaz Segovia (de), 9",
    "sg:city":"Navalcarnero",
    "sg:orig_category":"\u00d3ptica: Instrumentos (fabricaci\u00d3n)",
    "sg:phone":"+34 918 11 12 11",
    "sg:postcode":"28600",
    "sg:province":"Madrid",
    "sg:website":"www.delgadoespinosa.com",
    "wof:name":"Delgado Espinosa Juan",
    "wof:placetype":"venue"
},
  "geometry": {"coordinates":[-4.014688015,40.2875404358],"type":"Point"}
}