{
  "type": "Feature",
  "properties": {
    "iso:country":"ES",
    "sg:address":"Cami Moli D'en Fontanet, S/n",
    "sg:city":"Sabadell",
    "sg:orig_category":"Animales: Material Y Suministros Para (fabricaci\u00d3n, Al Por Mayor)",
    "sg:phone":"+34 937 45 97 39",
    "sg:postcode":"08202",
    "sg:province":"Barcelona",
    "wof:name":"Industrias Y Accesorios Samot S.l.",
    "wof:placetype":"venue"
},
  "geometry": {"coordinates":[2.11687994,41.5518798828],"type":"Point"}
}