{
  "type": "Feature",
  "properties": {
    "addr:full":"Calle de Mastelero, 20 Madrid Madrid 28033",
    "addr:housenumber":"20",
    "addr:postcode":"madrid;28033",
    "addr:street":"Calle De Mastelero",
    "iso:country":"ES",
    "sg:address":"Calle de Mastelero, 20",
    "sg:city":"Madrid",
    "sg:orig_category":"Peluquer\u00cdas, Peluquer\u00cda Mixta",
    "sg:phone":"+34 913 02 96 37",
    "sg:postcode":"28033",
    "sg:province":"Madrid",
    "wof:name":"Hinojosa De Barbera Silvia Estela",
    "wof:placetype":"venue"
},
  "geometry": {"coordinates":[-3.6590230465,40.4731712341],"type":"Point"}
}