{
  "type": "Feature",
  "properties": {
    "addr:full":"Calle de Riego, 1 Zamora Zamora 49004",
    "addr:housenumber":"1",
    "addr:postcode":"49004",
    "addr:street":"Calle De Riego",
    "iso:country":"ES",
    "sg:address":"Calle de Riego, 1",
    "sg:city":"Zamora",
    "sg:orig_category":"Abogados",
    "sg:phone":"+34 980 53 24 62",
    "sg:postcode":"49004",
    "sg:province":"Zamora",
    "wof:name":"Brualla Santos-funcia Manuel",
    "wof:placetype":"venue"
},
  "geometry": {"coordinates":[-5.7450289726,41.5050697327],"type":"Point"}
}