{
  "type": "Feature",
  "properties": {
    "addr:full":"Carrer de Alfatares, 10 Ondara Alicante 03760",
    "addr:housenumber":"10",
    "addr:postcode":"03760",
    "addr:street":"Carrer De Alfatares",
    "iso:country":"ES",
    "sg:address":"Carrer de Alfatares, 10",
    "sg:city":"Ondara",
    "sg:orig_category":"Centros Empresariales",
    "sg:phone":"+34 966 47 69 00",
    "sg:postcode":"03760",
    "sg:province":"Alicante",
    "wof:name":"Aseyge Informatica S.l.",
    "wof:placetype":"venue"
},
  "geometry": {"coordinates":[0.0216528997,38.8273887634],"type":"Point"}
}