{
  "type": "Feature",
  "properties": {
    "addr:full":"Calle de Margarita Pardo De Cela, 19 Viveiro Lugo 27850",
    "addr:housenumber":"19",
    "addr:postcode":"27850",
    "addr:street":"Calle De Margarita Pardo De Cela",
    "iso:country":"ES",
    "sg:address":"Calle de Margarita Pardo De Cela, 19",
    "sg:city":"Viveiro",
    "sg:orig_category":"Zapatos (al Por Menor)",
    "sg:phone":"+34 982 56 03 07",
    "sg:postcode":"27850",
    "sg:province":"Lugo",
    "wof:name":"Perez Seijas Josefina",
    "wof:placetype":"venue"
},
  "geometry": {"coordinates":[-7.595179081,43.6631202698],"type":"Point"}
}