{
  "type": "Feature",
  "properties": {
    "addr:full":"Av Navarra, 9 Olot Girona 17800",
    "addr:housenumber":"9",
    "addr:postcode":"17800",
    "addr:street":"Av Navarra",
    "iso:country":"ES",
    "sg:address":"Av Navarra, 9",
    "sg:city":"Olot",
    "sg:orig_category":"Arquitectos",
    "sg:phone":"+34 972 26 57 74",
    "sg:postcode":"17800",
    "sg:province":"Girona",
    "wof:name":"Sacrest G\u00fcell Ramon",
    "wof:placetype":"venue"
},
  "geometry": {"coordinates":[2.487801075,42.1767349243],"type":"Point"}
}