{
  "type": "Feature",
  "properties": {
    "addr:full":"Pl. Riego, S/n Cangas Narcea Asturias 33800",
    "addr:housenumber":"s / n",
    "addr:postcode":"33800",
    "addr:street":"Riego",
    "iso:country":"ES",
    "sg:address":"Pl. Riego, S/n",
    "sg:city":"Cangas Narcea",
    "sg:orig_category":"Librer\u00cdas",
    "sg:phone":"+34 985 81 17 85",
    "sg:postcode":"33800",
    "sg:province":"Asturias",
    "wof:name":"Anton Blanco Argentina",
    "wof:placetype":"venue"
},
  "geometry": {"coordinates":[-5.9832577705,43.2504386902],"type":"Point"}
}