{
  "type": "Feature",
  "properties": {
    "iso:country":"ES",
    "sg:address":"Calle de Ciudad Real, 3",
    "sg:city":"Alcorcon",
    "sg:orig_category":"Empresas De Carpinter\u00cda De Madera",
    "sg:phone":"+34 916 43 18 51",
    "sg:postcode":"28922",
    "sg:province":"Madrid",
    "wof:name":"Sanchez Sanchez Joaquin",
    "wof:placetype":"venue"
},
  "geometry": {"coordinates":[-3.8292429447,40.3443565369],"type":"Point"}
}