{
  "type": "Feature",
  "properties": {
    "addr:full":"Capela, S/n Pontes Garcia Rodriguez La Coru\u00f1a 15320",
    "addr:housenumber":"s / n",
    "addr:postcode":"15320",
    "addr:street":"Pontes Garcia Rodriguez La Corun\u0303A",
    "iso:country":"ES",
    "sg:address":"Capela, S/n",
    "sg:city":"Pontes Garcia Rodriguez",
    "sg:orig_category":"Supermercados Y Hipermercados",
    "sg:phone":"+34 981 44 07 60",
    "sg:postcode":"15320",
    "sg:province":"La Coru\u00f1a",
    "wof:name":"Distribuidora Internacional De Alimentacion",
    "wof:placetype":"venue"
},
  "geometry": {"coordinates":[-7.8508791924,43.451789856],"type":"Point"}
}