{
  "type": "Feature",
  "properties": {
    "addr:full":"Avda Pablo Iglesias, 5 Errenteria Guip\u00f9zcoa 20100",
    "addr:housenumber":"5",
    "addr:postcode":"20100",
    "addr:street":"Avda Pablo Iglesias;Guipu\u0300Zcoa",
    "iso:country":"ES",
    "sg:address":"Avda Pablo Iglesias, 5",
    "sg:city":"Errenteria",
    "sg:orig_category":"Peluquer\u00cdas, Peluquer\u00cda Mixta",
    "sg:phone":"+34 943 51 35 66",
    "sg:postcode":"20100",
    "sg:province":"Guip\u00f9zcoa",
    "wof:name":"Iba\u00f1ez Alonso Maria Teresa",
    "wof:placetype":"venue"
},
  "geometry": {"coordinates":[-1.8993270397,43.3116950989],"type":"Point"}
}