{
  "type": "Feature",
  "properties": {
    "iso:country":"ES",
    "sg:address":"Calle de Angel Mu\u00d1oz, 4",
    "sg:city":"Madrid",
    "sg:orig_category":"Inform\u00c1tica (estudios, Servicios, Asesor\u00cda, Formaci\u00d3n)",
    "sg:phone":"+34 915 19 40 97",
    "sg:postcode":"28043",
    "sg:province":"Madrid",
    "wof:name":"Betan S.a.",
    "wof:placetype":"venue"
},
  "geometry": {"coordinates":[-3.6563200951,40.4547462463],"type":"Point"}
}