{
  "type": "Feature",
  "properties": {
    "addr:full":"Carr Doctor Vicente Navarro Soler, 23 Benetusser Valencia 46910",
    "addr:housenumber":"23",
    "addr:postcode":"46910",
    "addr:street":"Carr Doctor Vicente Navarro Soler",
    "iso:country":"ES",
    "sg:address":"Carr Doctor Vicente Navarro Soler, 23",
    "sg:city":"Benetusser",
    "sg:orig_category":"Asociaciones Y Clubs Deportivos",
    "sg:phone":"+34 963 75 83 35",
    "sg:postcode":"46910",
    "sg:province":"Valencia",
    "sg:website":"www.nuestrase\u00f1oradelsocorro.es",
    "wof:name":"Club Deportivo Nuestra Se\u00f1ora Del Socorro",
    "wof:placetype":"venue"
},
  "geometry": {"coordinates":[-0.4011330009,39.4204292297],"type":"Point"}
}