{
  "type": "Feature",
  "properties": {
    "addr:full":"Calle de Real, 83 Estepona M\u00e1laga 29680",
    "addr:housenumber":"83",
    "addr:postcode":"29680",
    "addr:street":"Calle De Real",
    "iso:country":"ES",
    "sg:address":"Calle de Real, 83",
    "sg:city":"Estepona",
    "sg:orig_category":"Bisuter\u00cda, Joyer\u00cda, Relojer\u00cda (al Por Menor)",
    "sg:phone":"+34 952 79 40 63",
    "sg:postcode":"29680",
    "sg:province":"M\u00e1laga",
    "wof:name":"Martinez Ruiz Tomas",
    "wof:placetype":"venue"
},
  "geometry": {"coordinates":[-5.1443719864,36.425617218],"type":"Point"}
}