{
  "type": "Feature",
  "properties": {
    "addr:full":"Av Rei Jaume I, 107 Santa Pon\u00c7a Islas Baleares 07180",
    "addr:housenumber":"107",
    "addr:postcode":"07180",
    "addr:street":"Av Rei Jaume I",
    "iso:country":"ES",
    "sg:address":"Av Rei Jaume I, 107",
    "sg:city":"Santa Pon\u00c7a",
    "sg:orig_category":"Peluquer\u00cdas, Peluquer\u00cda Mixta",
    "sg:phone":"+34 971 69 45 11",
    "sg:postcode":"07180",
    "sg:province":"Islas Baleares",
    "wof:name":"Sassu  Patrizia",
    "wof:placetype":"venue"
},
  "geometry": {"coordinates":[2.4842739105,39.5160675049],"type":"Point"}
}