{
  "type": "Feature",
  "properties": {
    "addr:full":"Calle de Braulio Lausin, 3 Zaragoza Zaragoza 50008",
    "addr:housenumber":"3",
    "addr:postcode":"50008",
    "addr:street":"Calle De Braulio Lausin",
    "iso:country":"ES",
    "sg:address":"Calle de Braulio Lausin, 3",
    "sg:city":"Zaragoza",
    "sg:orig_category":"Frutas, Legumbres Frescas Y Tempranas (al Por Menor)",
    "sg:phone":"+34 976 49 20 63",
    "sg:postcode":"50008",
    "sg:province":"Zaragoza",
    "wof:name":"Garcia Zapater Jose Vicente",
    "wof:placetype":"venue"
},
  "geometry": {"coordinates":[-0.8749668002,41.6446304321],"type":"Point"}
}