{
  "type": "Feature",
  "properties": {
    "iso:country":"ES",
    "sg:address":"Calle de Ribera, 1",
    "sg:city":"Bilbao",
    "sg:orig_category":"Abogados",
    "sg:phone":"+34 944 15 50 91",
    "sg:postcode":"48005",
    "sg:province":"Vizcaya",
    "wof:name":"Alfonso Amade Gabriel",
    "wof:placetype":"venue"
},
  "geometry": {"coordinates":[-2.9246404171,43.2592315674],"type":"Point"}
}