{
  "type": "Feature",
  "properties": {
    "iso:country":"ES",
    "sg:address":"Calle de Virgen De Gracia, 51",
    "sg:city":"Alquerias Del Ni\u00e7o Perdido",
    "sg:orig_category":"Molduras, Junquillos, Listones Y Molduras Perforadas",
    "sg:phone":"+34 964 51 14 18",
    "sg:postcode":"12539",
    "sg:province":"Castell\u00f3n",
    "wof:name":"Nebot Vilar Vicente Manuel",
    "wof:placetype":"venue"
},
  "geometry": {"coordinates":[-0.1214139983,39.8971862793],"type":"Point"}
}