{
  "type": "Feature",
  "properties": {
    "addr:full":"Calle de Pico Meras, 1 Pravia Asturias 33120",
    "addr:housenumber":"1",
    "addr:postcode":"33120",
    "addr:street":"Calle De Pico Meras",
    "iso:country":"ES",
    "sg:address":"Calle de Pico Meras, 1",
    "sg:city":"Pravia",
    "sg:orig_category":"M\u00c9dicos: Estomatolog\u00cda",
    "sg:phone":"+34 985 82 19 68",
    "sg:postcode":"33120",
    "sg:province":"Asturias",
    "wof:name":"Rodriguez Polo Gerardo Jesus",
    "wof:placetype":"venue"
},
  "geometry": {"coordinates":[-6.1132731438,43.4886665344],"type":"Point"}
}