{
  "type": "Feature",
  "properties": {
    "iso:country":"ES",
    "sg:address":"Calle de Tarifa, 3",
    "sg:city":"Alcala Rio",
    "sg:orig_category":"Transportes Por Carretera: Lotes Completos, Mercanc\u00cdas Diversas",
    "sg:phone":"+34 954 78 01 53",
    "sg:postcode":"41200",
    "sg:province":"Sevilla",
    "wof:name":"Alcazar Pliego Antonio",
    "wof:placetype":"venue"
},
  "geometry": {"coordinates":[-5.983938694,37.5170860291],"type":"Point"}
}