{
  "type": "Feature",
  "properties": {
    "iso:country":"ES",
    "sg:address":"Rond Outeiro, 274",
    "sg:city":"Coru\u00d1a",
    "sg:orig_category":"Asesor\u00cda Sobre Comunicaci\u00d3n De Empresas",
    "sg:phone":"+34 981 26 60 50",
    "sg:postcode":"15010",
    "sg:province":"La Coru\u00f1a",
    "wof:name":"Carro Fernandez Asesores S.l.",
    "wof:placetype":"venue"
},
  "geometry": {"coordinates":[-8.4383602142,43.3564109802],"type":"Point"}
}