{
  "type": "Feature",
  "properties": {
    "iso:country":"ES",
    "sg:address":"Mas Colls, S/n",
    "sg:city":"Fonteta",
    "sg:orig_category":"Ferreter\u00cda Artesanal",
    "sg:phone":"+34 972 64 17 22",
    "sg:postcode":"17110",
    "sg:province":"Girona",
    "wof:name":"Forjats Fonteta S.l.",
    "wof:placetype":"venue"
},
  "geometry": {"coordinates":[3.0577399731,41.9499855042],"type":"Point"}
}