{
  "type": "Feature",
  "properties": {
    "addr:full":"Calle de Carlos Marin Menu, 5 Aguilas Murcia 30880",
    "addr:housenumber":"5",
    "addr:postcode":"30880",
    "addr:street":"Calle De Carlos Marin Menu",
    "iso:country":"ES",
    "sg:address":"Calle de Carlos Marin Menu, 5",
    "sg:city":"Aguilas",
    "sg:orig_category":"Ense\u00d1anza: Comercio, Gesti\u00d3n, Inform\u00c1tica",
    "sg:phone":"+34 968 49 32 21",
    "sg:postcode":"30880",
    "sg:province":"Murcia",
    "wof:name":"Informatica Integrada Del Sureste Microneth S.l.",
    "wof:placetype":"venue"
},
  "geometry": {"coordinates":[-1.5848609209,37.4052238464],"type":"Point"}
}