{
  "type": "Feature",
  "properties": {
    "addr:full":"Calle de Canalejas, 85 Jumilla Murcia 30520",
    "addr:housenumber":"85",
    "addr:postcode":"30520",
    "addr:street":"Calle De Canalejas",
    "iso:country":"ES",
    "sg:address":"Calle de Canalejas, 85",
    "sg:city":"Jumilla",
    "sg:orig_category":"Iglesia Cat\u00d3lica",
    "sg:phone":"+34 968 78 00 42",
    "sg:postcode":"30520",
    "sg:province":"Murcia",
    "wof:name":"Obispado De Cartagena",
    "wof:placetype":"venue"
},
  "geometry": {"coordinates":[-1.3268015385,38.4760322571],"type":"Point"}
}