{
  "type": "Feature",
  "properties": {
    "addr:full":"Orient, 8 Viladasens Girona 17464",
    "addr:housenumber":"8",
    "addr:postcode":"17464",
    "addr:street":"Orient",
    "iso:country":"ES",
    "sg:address":"Orient, 8",
    "sg:city":"Viladasens",
    "sg:orig_category":"Producci\u00d3n, Venta De Productos De Agricultura Biol\u00d3gica",
    "sg:phone":"+34 972 49 61 53",
    "sg:postcode":"17464",
    "sg:province":"Girona",
    "wof:name":"Codimasa S.l.",
    "wof:placetype":"venue"
},
  "geometry": {"coordinates":[2.9092900753,42.067199707],"type":"Point"}
}