{
  "type": "Feature",
  "properties": {
    "iso:country":"ES",
    "sg:address":"Calle de Luchana, 40",
    "sg:city":"Madrid",
    "sg:orig_category":"Sociedades, Compa\u00d1\u00cdas Aseguradoras",
    "sg:phone":"+34 914 47 80 94",
    "sg:postcode":"28010",
    "sg:province":"Madrid",
    "wof:name":"Zabaleta Navarro Correduria De Seguros S.l.",
    "wof:placetype":"venue"
},
  "geometry": {"coordinates":[-3.6978745461,40.432346344],"type":"Point"}
}