{
  "type": "Feature",
  "properties": {
    "addr:full":"Calle de Portalegre, 3 Badajoz Badajoz 06007",
    "addr:housenumber":"3",
    "addr:postcode":"06007",
    "addr:street":"Calle De Portalegre",
    "iso:country":"ES",
    "sg:address":"Calle de Portalegre, 3",
    "sg:city":"Badajoz",
    "sg:orig_category":"Carnicer\u00cdas, Carnicer\u00cdas",
    "sg:phone":"+34 924 27 09 04",
    "sg:postcode":"06007",
    "sg:province":"Badajoz",
    "wof:name":"Marquez Cerrato Fernando",
    "wof:placetype":"venue"
},
  "geometry": {"coordinates":[-6.9818210602,38.8881759644],"type":"Point"}
}