{
  "type": "Feature",
  "properties": {
    "addr:full":"Calle de Pages Del Corro, 155 Sevilla Sevilla 41010",
    "addr:housenumber":"155",
    "addr:postcode":"41010",
    "addr:street":"Calle De Pages Del Corro",
    "iso:country":"ES",
    "sg:address":"Calle de Pages Del Corro, 155",
    "sg:city":"Sevilla",
    "sg:orig_category":"Vestidos Para Celebraciones (fabricaci\u00d3n, Al Por Mayor)",
    "sg:phone":"+34 954 27 13 13",
    "sg:postcode":"41010",
    "sg:province":"Sevilla",
    "wof:name":"Bermudez Mu\u00f1oz Maria Del Rosario",
    "wof:placetype":"venue"
},
  "geometry": {"coordinates":[-6.0003051758,37.3811759949],"type":"Point"}
}