{
  "type": "Feature",
  "properties": {
    "iso:country":"ES",
    "sg:address":"Carr Conquista, 70",
    "sg:city":"Badalona",
    "sg:orig_category":"Pescader\u00cdas (al Por Menor)",
    "sg:phone":"+34 933 83 49 07",
    "sg:postcode":"08912",
    "sg:province":"Barcelona",
    "wof:name":"Plana Pages Joaquin",
    "wof:placetype":"venue"
},
  "geometry": {"coordinates":[2.2430479527,41.4460067749],"type":"Point"}
}