{
  "type": "Feature",
  "properties": {
    "addr:full":"Ctra Palencia, Km. 0001,0 Castrogonzalo Zamora 49660",
    "addr:postcode":"49660",
    "addr:street":"Ctra Palencia Km. 0001,0",
    "iso:country":"ES",
    "sg:address":"Ctra Palencia, Km. 0001,0",
    "sg:city":"Castrogonzalo",
    "sg:orig_category":"Lecher\u00cdas",
    "sg:phone":"+34 980 66 40 50",
    "sg:postcode":"49660",
    "sg:province":"Zamora",
    "wof:name":"Lacteas Cobreros S.a.",
    "wof:placetype":"venue"
},
  "geometry": {"coordinates":[-5.598883152,41.9883079529],"type":"Point"}
}