{
  "type": "Feature",
  "properties": {
    "addr:full":"Calle de Juan Bautista Uriarte, 38 Kurtzea Vizcaya 48960",
    "addr:housenumber":"38",
    "addr:postcode":"48960",
    "addr:street":"Calle De Juan Bautista Uriarte",
    "iso:country":"ES",
    "sg:address":"Calle de Juan Bautista Uriarte, 38",
    "sg:city":"Kurtzea",
    "sg:orig_category":"Librer\u00cdas",
    "sg:phone":"+34 944 56 21 19",
    "sg:postcode":"48960",
    "sg:province":"Vizcaya",
    "wof:name":"Busquets Urruticoechea Claudio",
    "wof:placetype":"venue"
},
  "geometry": {"coordinates":[-2.8426458836,43.2303695679],"type":"Point"}
}