{
  "type": "Feature",
  "properties": {
    "iso:country":"ES",
    "sg:address":"Ctra. Colmenar-guadalix Sierra, Km. 0005,0",
    "sg:city":"Rancajales",
    "sg:orig_category":"Cr\u00cda De Bovinos",
    "sg:phone":"+34 918 44 12 09",
    "sg:postcode":"28791",
    "sg:province":"Madrid",
    "wof:name":"Granja Colmemar S.l.",
    "wof:placetype":"venue"
},
  "geometry": {"coordinates":[-3.7829489708,40.7544517517],"type":"Point"}
}