{
  "type": "Feature",
  "properties": {
    "iso:country":"ES",
    "sg:address":"Pase Autonomias (de Las), 8",
    "sg:city":"Huesca",
    "sg:orig_category":"Muebles, Minoristas",
    "sg:phone":"+34 974 23 05 44",
    "sg:postcode":"22004",
    "sg:province":"Huesca",
    "wof:name":"Leito Mobiliario S.l.",
    "wof:placetype":"venue"
},
  "geometry": {"coordinates":[-0.4181919992,42.1383285522],"type":"Point"}
}