{
  "type": "Feature",
  "properties": {
    "addr:full":"Calle de Doctor Fleming, 33 Espinos Las Palmas 35470",
    "addr:housenumber":"33",
    "addr:postcode":"35470",
    "addr:street":"Calle De Doctor Fleming",
    "iso:country":"ES",
    "sg:address":"Calle de Doctor Fleming, 33",
    "sg:city":"Espinos",
    "sg:orig_category":"Art\u00cdculos Funerarios (al Por Menor)",
    "sg:phone":"+34 928 89 13 61",
    "sg:postcode":"35470",
    "sg:province":"Las Palmas",
    "wof:name":"Melian Godoy Lorenzo Valeriano",
    "wof:placetype":"venue"
},
  "geometry": {"coordinates":[-15.7850942612,27.9865074158],"type":"Point"}
}