{
  "type": "Feature",
  "properties": {
    "addr:full":"Calle de Villafranca, 6 Le\u00f3n Le\u00f3n 24001",
    "addr:housenumber":"6",
    "addr:postcode":"24001",
    "addr:street":"Calle De Villafranca;Leo\u0301N",
    "iso:country":"ES",
    "sg:address":"Calle de Villafranca, 6",
    "sg:city":"Le\u00f3n",
    "sg:classifiers":[
        {
            "category":"Communications",
            "type":"Services"
        }
    ],
    "sg:phone":"+34 987 25 29 05",
    "sg:postcode":"24001",
    "sg:province":"Le\u00f3n",
    "sg:tags":[
        "televisiones",
        "y",
        "radio"
    ],
    "wof:name":"Radio Leon E. A. J. 63",
    "wof:placetype":"venue"
},
  "geometry": {"coordinates":[-5.5757222176,42.5958213806],"type":"Point"}
}