{
  "type": "Feature",
  "properties": {
    "iso:country":"ES",
    "sg:address":"Rua Pravia (da), 15",
    "sg:city":"Vilalba",
    "sg:orig_category":"Cajas De Ahorro",
    "sg:phone":"+34 982 52 30 06",
    "sg:postcode":"27800",
    "sg:province":"Lugo",
    "sg:website":"www.caixanova.es",
    "wof:name":"Caixa De Aforros De Vigo Ourense E Pontevedra",
    "wof:placetype":"venue"
},
  "geometry": {"coordinates":[-7.6811480522,43.2983589172],"type":"Point"}
}