{
  "type": "Feature",
  "properties": {
    "addr:full":"Mcdo Encarnacion, S/n Sevilla Sevilla 41003",
    "addr:housenumber":"/ n",
    "addr:postcode":"41003",
    "addr:street":"S",
    "iso:country":"ES",
    "sg:address":"Mcdo Encarnacion, S/n",
    "sg:city":"Sevilla",
    "sg:orig_category":"Alimentaci\u00d3n General (al Por Menor)",
    "sg:phone":"+34 954 21 72 21",
    "sg:postcode":"41003",
    "sg:province":"Sevilla",
    "wof:name":"El Bacalao S. A.",
    "wof:placetype":"venue"
},
  "geometry": {"coordinates":[-5.9919509888,37.3938064575],"type":"Point"}
}