{
  "type": "Feature",
  "properties": {
    "addr:full":"Psaj Caudal, 15 Malaga M\u00e1laga 29006",
    "addr:housenumber":"15",
    "addr:postcode":"29006",
    "addr:street":"Caudal;Ma\u0301Laga",
    "iso:country":"ES",
    "sg:address":"Psaj Caudal, 15",
    "sg:city":"Malaga",
    "sg:orig_category":"Chapister\u00cda",
    "sg:phone":"+34 952 31 18 80",
    "sg:postcode":"29006",
    "sg:province":"M\u00e1laga",
    "wof:name":"Taller Mifami S.c.",
    "wof:placetype":"venue"
},
  "geometry": {"coordinates":[-4.4823040962,36.7122306824],"type":"Point"}
}