{
  "type": "Feature",
  "properties": {
    "iso:country":"ES",
    "sg:address":"Ctra Massalfassar, 5",
    "sg:city":"Museros",
    "sg:orig_category":"Mec\u00c1nico Del Autom\u00d3vil",
    "sg:phone":"+34 961 44 15 33",
    "sg:postcode":"46136",
    "sg:province":"Valencia",
    "wof:name":"Cooperativa Auto-museros S. L.",
    "wof:placetype":"venue"
},
  "geometry": {"coordinates":[-0.3326840103,39.5605201721],"type":"Point"}
}