{
  "type": "Feature",
  "properties": {
    "iso:country":"ES",
    "sg:address":"Calle de Albacete, 10",
    "sg:city":"Alaquas",
    "sg:orig_category":"Farmacias",
    "sg:phone":"+34 961 50 19 08",
    "sg:postcode":"46970",
    "sg:province":"Valencia",
    "wof:name":"Chaques Alepuz Jose Luis",
    "wof:placetype":"venue"
},
  "geometry": {"coordinates":[-0.464288801,39.4555587769],"type":"Point"}
}