{
  "type": "Feature",
  "properties": {
    "addr:full":"Carrer de Jacint Verdaguer, 24 Vic Barcelona 08500",
    "addr:housenumber":"24",
    "addr:postcode":"08500",
    "addr:street":"Carrer De Jacint Verdaguer",
    "iso:country":"ES",
    "sg:address":"Carrer de Jacint Verdaguer, 24",
    "sg:city":"Vic",
    "sg:orig_category":"Arquitectos",
    "sg:phone":"+34 938 85 64 94",
    "sg:postcode":"08500",
    "sg:province":"Barcelona",
    "wof:name":"Vizcaino Canals Jacint",
    "wof:placetype":"venue"
},
  "geometry": {"coordinates":[2.251124382,41.9307174683],"type":"Point"}
}