{
  "type": "Feature",
  "properties": {
    "addr:full":"Calle de Maro, 8 Malaga M\u00e1laga 29006",
    "addr:housenumber":"8",
    "addr:postcode":"29006",
    "addr:street":"Calle De Maro;Ma\u0301Laga",
    "iso:country":"ES",
    "sg:address":"Calle de Maro, 8",
    "sg:city":"Malaga",
    "sg:orig_category":"Metalurgia",
    "sg:phone":"+34 952 32 52 00",
    "sg:postcode":"29006",
    "sg:province":"M\u00e1laga",
    "sg:website":"www.tobelem.net",
    "wof:name":"H.tobelem Morales S.l.",
    "wof:placetype":"venue"
},
  "geometry": {"coordinates":[-4.4641928673,36.7026100159],"type":"Point"}
}