{
  "type": "Feature",
  "properties": {
    "addr:full":"Avda Severino Fernandez, 5 Tafalla Navarra 31300",
    "addr:housenumber":"5",
    "addr:postcode":"31300",
    "addr:street":"Avda Severino Fernandez",
    "iso:country":"ES",
    "sg:address":"Avda Severino Fernandez, 5",
    "sg:city":"Tafalla",
    "sg:orig_category":"Agentes, Concesionarios Y Sucursales De Veh\u00cdculos",
    "sg:phone":"+34 948 70 33 17",
    "sg:postcode":"31300",
    "sg:province":"Navarra",
    "wof:name":"Arbona Asesores Correduria De Seguros S.l.",
    "wof:placetype":"venue"
},
  "geometry": {"coordinates":[-1.6747789383,42.5270881653],"type":"Point"}
}