{
  "type": "Feature",
  "properties": {
    "iso:country":"ES",
    "sg:address":"Calle de Milicias, 16",
    "sg:city":"Logro\u00f1o",
    "sg:orig_category":"Panader\u00cdas, Panader\u00cdas",
    "sg:phone":"+34 941 25 62 00",
    "sg:postcode":"26003",
    "sg:province":"La Rioja",
    "wof:name":"Inversiones Alimentarias Cruells Sl",
    "wof:placetype":"venue"
},
  "geometry": {"coordinates":[-2.4377129078,42.4624328613],"type":"Point"}
}