{
  "type": "Feature",
  "properties": {
    "addr:full":"Carrer de Currican, 14 Campello Alicante 03560",
    "addr:housenumber":"14",
    "addr:postcode":"03560",
    "addr:street":"Carrer De Currican",
    "iso:country":"ES",
    "sg:address":"Carrer de Currican, 14",
    "sg:city":"Campello",
    "sg:orig_category":"Inmobiliaria (agencias)",
    "sg:phone":"+34 965 63 01 06",
    "sg:postcode":"03560",
    "sg:province":"Alicante",
    "wof:name":"Promociones Bianmar S.l.",
    "wof:placetype":"venue"
},
  "geometry": {"coordinates":[-0.3888440132,38.4299163818],"type":"Point"}
}