{
  "type": "Feature",
  "properties": {
    "addr:full":"Calle de Pintor Murillo (del), 11 Alcobendas Madrid 28100",
    "addr:postcode":"28100",
    "addr:street":"Calle De Pintor Murillo Del;Alcobendas",
    "iso:country":"ES",
    "sg:address":"Calle de Pintor Murillo (del), 11",
    "sg:city":"Alcobendas",
    "sg:orig_category":"Molduras, Junquillos, Listones Y Molduras Perforadas",
    "sg:phone":"+34 916 61 96 57",
    "sg:postcode":"28100",
    "sg:province":"Madrid",
    "wof:name":"Fresno Garcia Cecilio",
    "wof:placetype":"venue"
},
  "geometry": {"coordinates":[-3.641479969,40.5383872986],"type":"Point"}
}