{
  "type": "Feature",
  "properties": {
    "iso:country":"ES",
    "sg:address":"Carr Nou, 9",
    "sg:city":"Mao",
    "sg:orig_category":"Peluquer\u00cdas, Peluquer\u00cda Mixta",
    "sg:phone":"+34 971 36 96 95",
    "sg:postcode":"07701",
    "sg:province":"Islas Baleares",
    "wof:name":"Peluqueria Juana Y Jose Luis S. Cv.",
    "wof:placetype":"venue"
},
  "geometry": {"coordinates":[4.265625,39.8903694153],"type":"Point"}
}