{
  "type": "Feature",
  "properties": {
    "iso:country":"ES",
    "sg:address":"Avda Naos (de), 64",
    "sg:city":"Arrecife",
    "sg:orig_category":"Empresas De Carpinter\u00cda De Madera",
    "sg:phone":"+34 928 81 37 68",
    "sg:postcode":"35500",
    "sg:province":"Las Palmas",
    "wof:name":"Ruiz Y Medina S.l.",
    "wof:placetype":"venue"
},
  "geometry": {"coordinates":[-13.5390968323,28.967502594],"type":"Point"}
}