{
  "type": "Feature",
  "properties": {
    "iso:country":"ES",
    "sg:address":"Calle de Santa Maria, S/n",
    "sg:city":"Valera Abajo",
    "sg:orig_category":"Alimentaci\u00d3n General (al Por Menor)",
    "sg:phone":"+34 969 20 82 50",
    "sg:postcode":"16120",
    "sg:province":"Cuenca",
    "wof:name":"Motos Beltran Mercedes",
    "wof:placetype":"venue"
},
  "geometry": {"coordinates":[-2.1584317684,39.769077301],"type":"Point"}
}