{
  "type": "Feature",
  "properties": {
    "iso:country":"ES",
    "sg:address":"Avda Eulogio Fernandez, 76",
    "sg:city":"Barco",
    "sg:orig_category":"Quincaller\u00cda (al Por Menor)",
    "sg:phone":"+34 988 32 28 52",
    "sg:postcode":"32300",
    "sg:province":"Ourense",
    "sg:website":"www.ferreteria-digital.com",
    "wof:name":"Delgado Fernandez Miguel Angel",
    "wof:placetype":"venue"
},
  "geometry": {"coordinates":[-6.9908161163,42.4184112549],"type":"Point"}
}