{
  "type": "Feature",
  "properties": {
    "iso:country":"ES",
    "sg:address":"Pg Til.lers, 49",
    "sg:city":"Corro D'avall",
    "sg:orig_category":"M\u00c1quinas Y Material Para La Industria De La Alimentaci\u00d3n",
    "sg:phone":"+34 938 49 29 21",
    "sg:postcode":"08520",
    "sg:province":"Barcelona",
    "wof:name":"Nordson Iberica S.a.",
    "wof:placetype":"venue"
},
  "geometry": {"coordinates":[2.1196091175,41.3895378113],"type":"Point"}
}