{
  "type": "Feature",
  "properties": {
    "addr:full":"Carrer de Bartomeu Amat, 105 Terrassa Barcelona 08225",
    "addr:housenumber":"105",
    "addr:postcode":"08225",
    "addr:street":"Carrer De Bartomeu Amat",
    "iso:country":"ES",
    "sg:address":"Carrer de Bartomeu Amat, 105",
    "sg:city":"Terrassa",
    "sg:orig_category":"Molduras, Junquillos, Listones Y Molduras Perforadas",
    "sg:phone":"+34 937 35 80 34",
    "sg:postcode":"08225",
    "sg:province":"Barcelona",
    "wof:name":"Salvador Sanchez Manuel",
    "wof:placetype":"venue"
},
  "geometry": {"coordinates":[2.0121309757,41.5732803345],"type":"Point"}
}