{
  "type": "Feature",
  "properties": {
    "iso:country":"ES",
    "sg:address":"Calle de Venezuela, S/n",
    "sg:city":"Alcantarilla",
    "sg:orig_category":"Material Y Equipo Para Conserver\u00cdas Y Confiter\u00cdas",
    "sg:phone":"+34 968 25 42 22",
    "sg:postcode":"30820",
    "sg:province":"Murcia",
    "wof:name":"Talleres Loira S.l.",
    "wof:placetype":"venue"
},
  "geometry": {"coordinates":[-1.2086009979,37.9554252625],"type":"Point"}
}