{
  "type": "Feature",
  "properties": {
    "iso:country":"ES",
    "sg:address":"Pase Principe Asturias, 79",
    "sg:city":"Tobarra",
    "sg:orig_category":"Bares, Piano",
    "sg:phone":"+34 967 32 53 25",
    "sg:postcode":"02500",
    "sg:province":"Albacete",
    "wof:name":"Distribuidora De Bebidas Fraunepa Sl",
    "wof:placetype":"venue"
},
  "geometry": {"coordinates":[-1.6869729757,38.5961761475],"type":"Point"}
}