{
  "type": "Feature",
  "properties": {
    "iso:country":"ES",
    "sg:address":"Sorriego, S/n",
    "sg:city":"Linares",
    "sg:orig_category":"Trabajos De Soldaduras",
    "sg:phone":"+34 985 66 07 09",
    "sg:postcode":"33947",
    "sg:province":"Asturias",
    "wof:name":"Soldaduras Del Nalon S.l.",
    "wof:placetype":"venue"
},
  "geometry": {"coordinates":[-5.6400060654,43.297706604],"type":"Point"}
}