{
  "type": "Feature",
  "properties": {
    "addr:full":"Calle de Escultor Jose Gutierrez, 1 Alacant Alicante 03540",
    "addr:housenumber":"1",
    "addr:postcode":"03540",
    "addr:street":"Calle De Escultor Jose Gutierrez",
    "iso:country":"ES",
    "sg:address":"Calle de Escultor Jose Gutierrez, 1",
    "sg:city":"Alacant",
    "sg:orig_category":"Asesor\u00cda Sobre Comunicaci\u00d3n De Empresas",
    "sg:phone":"+34 965 26 30 88",
    "sg:postcode":"03540",
    "sg:province":"Alicante",
    "wof:name":"Futura S.l.",
    "wof:placetype":"venue"
},
  "geometry": {"coordinates":[-0.4215739965,38.3693656921],"type":"Point"}
}