{
  "type": "Feature",
  "properties": {
    "iso:country":"ES",
    "sg:address":"Poli Teknologi Elkartegia, 105",
    "sg:city":"Arteaga",
    "sg:orig_category":"Automatizaci\u00d3n De Procesos Industriales Y De Edificaci\u00d3n (estudios, Instalaci\u00d3n)",
    "sg:phone":"+34 944 20 95 45",
    "sg:postcode":"48...",
    "sg:province":"Vizcaya",
    "wof:name":"Mikroa S.a.",
    "wof:placetype":"venue"
},
  "geometry": {"coordinates":[-2.9316000938,43.2383995056],"type":"Point"}
}