{
  "type": "Feature",
  "properties": {
    "addr:full":"Luga San Roque, S/n Castropol Asturias 33760",
    "addr:housenumber":"s / n",
    "addr:postcode":"33760",
    "addr:street":"Roque",
    "iso:country":"ES",
    "sg:address":"Luga San Roque, S/n",
    "sg:city":"Castropol",
    "sg:orig_category":"Agentes, Concesionarios Y Sucursales De Veh\u00cdculos",
    "sg:phone":"+34 985 63 54 57",
    "sg:postcode":"33760",
    "sg:province":"Asturias",
    "wof:name":"Gonzalez Garcia Gumersindo",
    "wof:placetype":"venue"
},
  "geometry": {"coordinates":[-7.0316839218,43.517364502],"type":"Point"}
}