{
  "type": "Feature",
  "properties": {
    "addr:full":"Rua Santa Comba (de), 2 Santiago De Compostela La Coru\u00f1a 15705",
    "addr:housenumber":"2",
    "addr:postcode":"15705",
    "addr:street":"Rua Santa Comba De;Corun\u0303A",
    "iso:country":"ES",
    "sg:address":"Rua Santa Comba (de), 2",
    "sg:city":"Santiago De Compostela",
    "sg:orig_category":"Frutas, Legumbres Frescas Y Tempranas (al Por Menor)",
    "sg:phone":"+34 981 56 28 78",
    "sg:postcode":"15705",
    "sg:province":"La Coru\u00f1a",
    "wof:name":"Merca-lozano S.l.",
    "wof:placetype":"venue"
},
  "geometry": {"coordinates":[-8.5472545624,42.892364502],"type":"Point"}
}