{
  "type": "Feature",
  "properties": {
    "addr:full":"Calle de Mulhacen, 8 Parador Hortichuelas Almer\u00eda 04720",
    "addr:housenumber":"8",
    "addr:postcode":"04720",
    "addr:street":"Calle De Mulhacen;Almeri\u0301A",
    "iso:country":"ES",
    "sg:address":"Calle de Mulhacen, 8",
    "sg:city":"Parador Hortichuelas",
    "sg:orig_category":"Agencias Y Asesores De Publicidad",
    "sg:phone":"+34 950 34 72 40",
    "sg:postcode":"04720",
    "sg:province":"Almer\u00eda",
    "sg:website":"www.plasmapublicidad.com",
    "wof:name":"Plasma Publicidad S.l.",
    "wof:placetype":"venue"
},
  "geometry": {"coordinates":[-2.6004099846,36.809387207],"type":"Point"}
}