{
  "type": "Feature",
  "properties": {
    "addr:full":"Calle de Marques De Vadillo, 5 Burgo Osma Soria 42300",
    "addr:housenumber":"5",
    "addr:postcode":"42300",
    "addr:street":"Calle De Marques De Vadillo",
    "iso:country":"ES",
    "sg:address":"Calle de Marques De Vadillo, 5",
    "sg:city":"Burgo Osma",
    "sg:orig_category":"Pescader\u00cdas (al Por Menor)",
    "sg:phone":"+34 975 34 13 44",
    "sg:postcode":"42300",
    "sg:province":"Soria",
    "wof:name":"Gil Bernal Eusebio",
    "wof:placetype":"venue"
},
  "geometry": {"coordinates":[-3.0671420097,41.5862045288],"type":"Point"}
}