{
  "type": "Feature",
  "properties": {
    "iso:country":"ES",
    "sg:address":"Tudela, 14",
    "sg:city":"Iru\u00f1a",
    "sg:orig_category":"M\u00c9dicos: Medicina Interna",
    "sg:phone":"+34 948 24 10 37",
    "sg:postcode":"31003",
    "sg:province":"Navarra",
    "wof:name":"Mendiri Ursua Ruperto Y Osacar Ocaiz Ana",
    "wof:placetype":"venue"
},
  "geometry": {"coordinates":[-1.6440399885,42.812122345],"type":"Point"}
}