{
  "type": "Feature",
  "properties": {
    "addr:full":"Calle de Jose Maria Lillo, 50 Mengibar Ja\u00e9n 23620",
    "addr:housenumber":"50",
    "addr:postcode":"23620",
    "addr:street":"Calle De Jose Maria Lillo;Jae\u0301N",
    "iso:country":"ES",
    "sg:address":"Calle de Jose Maria Lillo, 50",
    "sg:city":"Mengibar",
    "sg:orig_category":"Aguas (distribuci\u00d3n, Servicios)",
    "sg:phone":"+34 953 37 22 24",
    "sg:postcode":"23620",
    "sg:province":"Ja\u00e9n",
    "wof:name":"Aguas Jaen S.a.",
    "wof:placetype":"venue"
},
  "geometry": {"coordinates":[-3.8064427376,37.9685287476],"type":"Point"}
}