{
  "type": "Feature",
  "properties": {
    "addr:full":"Rua Doctor Cabaleiro, 4 Ourense Ourense 32005",
    "addr:housenumber":"4",
    "addr:postcode":"32005",
    "addr:street":"Rua Doctor Cabaleiro",
    "iso:country":"ES",
    "sg:address":"Rua Doctor Cabaleiro, 4",
    "sg:city":"Ourense",
    "sg:orig_category":"Caf\u00c9s, Bares, Cervecer\u00cdas",
    "sg:phone":"+34 988 24 25 20",
    "sg:postcode":"32005",
    "sg:province":"Ourense",
    "wof:name":"Rodriguez Mendez Berta",
    "wof:placetype":"venue"
},
  "geometry": {"coordinates":[-7.8613557816,42.3211326599],"type":"Point"}
}