{
  "type": "Feature",
  "properties": {
    "addr:full":"Calle de Gonzalez Sola, 16 Madrid Madrid 28029",
    "addr:housenumber":"16",
    "addr:postcode":"madrid;28029",
    "addr:street":"Calle De Gonzalez Sola",
    "iso:country":"ES",
    "sg:address":"Calle de Gonzalez Sola, 16",
    "sg:city":"Madrid",
    "sg:orig_category":"Radiocomunicaciones, Telefon\u00cda M\u00d3vil, Radiomensajer\u00cda: Servicios, Comercializaci\u00d3n",
    "sg:phone":"+34 913 14 79 49",
    "sg:postcode":"28029",
    "sg:province":"Madrid",
    "wof:name":"Silverio Milaya Luisa",
    "wof:placetype":"venue"
},
  "geometry": {"coordinates":[-3.6955809593,40.4670295715],"type":"Point"}
}