{
  "type": "Feature",
  "properties": {
    "iso:country":"ES",
    "sg:address":"Poli Zumarragako Industrialdea (industrial), 61",
    "sg:city":"Zumarraga",
    "sg:orig_category":"Tratamiento De Metales",
    "sg:phone":"+34 943 72 49 68",
    "sg:postcode":"20700",
    "sg:province":"Guip\u00f9zcoa",
    "wof:name":"Ttt Goiko S.a.",
    "wof:placetype":"venue"
},
  "geometry": {"coordinates":[-2.3182489872,43.0813789368],"type":"Point"}
}