{
  "type": "Feature",
  "properties": {
    "addr:full":"C/ Binissalem, 51 Inca Islas Baleares 07300",
    "addr:housenumber":"51",
    "addr:postcode":"07300",
    "addr:street":"C / Binissalem",
    "iso:country":"ES",
    "sg:address":"C/ Binissalem, 51",
    "sg:city":"Inca",
    "sg:orig_category":"Confecci\u00d3n De Zapatos",
    "sg:phone":"+34 971 50 46 55",
    "sg:postcode":"07300",
    "sg:province":"Islas Baleares",
    "sg:website":"www.yanko.com",
    "wof:name":"Yanko S.a.",
    "wof:placetype":"venue"
},
  "geometry": {"coordinates":[2.9022629261,39.7138824463],"type":"Point"}
}