{
  "type": "Feature",
  "properties": {
    "addr:full":"Carrer de Bailen, 190 Barcelona Barcelona 08037",
    "addr:housenumber":"190",
    "addr:postcode":"08037",
    "addr:street":"Carrer De Bailen",
    "iso:country":"ES",
    "sg:address":"Carrer de Bailen, 190",
    "sg:city":"Barcelona",
    "sg:orig_category":"Expertos Contables, Revisores De Cuentas",
    "sg:phone":"+34 934 59 00 52",
    "sg:postcode":"08037",
    "sg:province":"Barcelona",
    "wof:name":"Sw & Audit Group S.l",
    "wof:placetype":"venue"
},
  "geometry": {"coordinates":[2.1650710106,41.4013061523],"type":"Point"}
}