{
  "type": "Feature",
  "properties": {
    "addr:full":"Calle de Honda (la), S/n Illueca Zaragoza 50250",
    "addr:postcode":"50250",
    "addr:street":"Calle De Honda La S / N Illueca",
    "iso:country":"ES",
    "sg:address":"Calle de Honda (la), S/n",
    "sg:city":"Illueca",
    "sg:orig_category":"Mec\u00c1nico Del Autom\u00d3vil",
    "sg:phone":"+34 976 82 26 58",
    "sg:postcode":"50250",
    "sg:province":"Zaragoza",
    "wof:name":"Talleres Capape S.l.",
    "wof:placetype":"venue"
},
  "geometry": {"coordinates":[-1.6350140572,41.5382957458],"type":"Point"}
}