{
  "type": "Feature",
  "properties": {
    "addr:full":"Calle de Mesones, 47 Estepa Sevilla 41560",
    "addr:housenumber":"47",
    "addr:postcode":"41560",
    "addr:street":"Calle De Mesones;Sevilla",
    "iso:country":"ES",
    "sg:address":"Calle de Mesones, 47",
    "sg:city":"Estepa",
    "sg:orig_category":"Cajas Para Embalar",
    "sg:phone":"+34 955 91 33 68",
    "sg:postcode":"41560",
    "sg:province":"Sevilla",
    "sg:website":"www.cajarural.com",
    "wof:name":"Caja Rural Del Sur Sociedad Cooperativa",
    "wof:placetype":"venue"
},
  "geometry": {"coordinates":[-4.8798398972,37.2905044556],"type":"Point"}
}