{
  "type": "Feature",
  "properties": {
    "addr:full":"Plaz Espa\u00d1a, 5 Atienza Guadalajara 19270",
    "addr:housenumber":"5",
    "addr:postcode":"19270",
    "addr:street":"Plaz Espan\u0303A",
    "iso:country":"ES",
    "sg:address":"Plaz Espa\u00d1a, 5",
    "sg:city":"Atienza",
    "sg:orig_category":"Estancos",
    "sg:phone":"+34 949 39 91 22",
    "sg:postcode":"19270",
    "sg:province":"Guadalajara",
    "wof:name":"Lazaro Hernando Maximo",
    "wof:placetype":"venue"
},
  "geometry": {"coordinates":[-2.8690900803,41.1993293762],"type":"Point"}
}