{
  "type": "Feature",
  "properties": {
    "addr:full":"Avda Juan Carlos I, 9 Gijon Asturias 33212",
    "addr:housenumber":"9",
    "addr:postcode":"33212",
    "addr:street":"Avda Juan Carlos I",
    "iso:country":"ES",
    "sg:address":"Avda Juan Carlos I, 9",
    "sg:city":"Gijon",
    "sg:orig_category":"Bisuter\u00cda, Joyer\u00cda, Relojer\u00cda (al Por Menor)",
    "sg:phone":"+34 984 29 21 84",
    "sg:postcode":"33212",
    "sg:province":"Asturias",
    "wof:name":"Ceruma Sl",
    "wof:placetype":"venue"
},
  "geometry": {"coordinates":[-5.6822299957,43.5379905701],"type":"Point"}
}