{
  "type": "Feature",
  "properties": {
    "iso:country":"ES",
    "sg:address":"Avda Carolina Coronado, 7",
    "sg:city":"Badajoz",
    "sg:orig_category":"Cajas De Ahorro",
    "sg:phone":"+34 924 27 48 08",
    "sg:postcode":"06007",
    "sg:province":"Badajoz",
    "sg:website":"www.cajaextremadura.es",
    "wof:name":"Caja De Ahorros Y Monte De Piedad De Extremadura",
    "wof:placetype":"venue"
},
  "geometry": {"coordinates":[-6.9822878838,38.8903388977],"type":"Point"}
}