{
  "type": "Feature",
  "properties": {
    "iso:country":"ES",
    "sg:address":"Carrer de Princep Jordi, 20",
    "sg:city":"Barcelona",
    "sg:orig_category":"Centros De Coordinaci\u00d3n",
    "sg:phone":"+34 934 23 04 41",
    "sg:postcode":"08014",
    "sg:province":"Barcelona",
    "wof:name":"Bre\u00f1e Brulles Rosa Gemma",
    "wof:placetype":"venue"
},
  "geometry": {"coordinates":[2.1473369598,41.3759727478],"type":"Point"}
}