{
  "type": "Feature",
  "properties": {
    "iso:country":"ES",
    "sg:address":"Calle de Juan Mari Altuna Kalea, 18",
    "sg:city":"Durango",
    "sg:orig_category":"Caf\u00c9s, Bares, Cervecer\u00cdas",
    "sg:phone":"+34 946 20 13 94",
    "sg:postcode":"48200",
    "sg:province":"Vizcaya",
    "wof:name":"Albizuri Martinez Miren Maitane",
    "wof:placetype":"venue"
},
  "geometry": {"coordinates":[-2.6278665066,43.1699638367],"type":"Point"}
}