{
  "type": "Feature",
  "properties": {
    "addr:full":"Calle de Vi\u00d1a (la), 4 Torrelavega Cantabria 39300",
    "addr:housenumber":"4",
    "addr:postcode":"39300",
    "addr:street":"Calle De Vin\u0303A La",
    "iso:country":"ES",
    "sg:address":"Calle de Vi\u00d1a (la), 4",
    "sg:city":"Torrelavega",
    "sg:orig_category":"Estilistas Y Estudios De Estilo De Corte Y Confecci\u00d3n",
    "sg:phone":"+34 942 80 24 50",
    "sg:postcode":"39300",
    "sg:province":"Cantabria",
    "wof:name":"Gonzalez Toribio Jesus",
    "wof:placetype":"venue"
},
  "geometry": {"coordinates":[-4.0524749756,43.3478660583],"type":"Point"}
}