{
  "type": "Feature",
  "properties": {
    "addr:full":"Kale Nagusia, 98 Azkoitia Guip\u00f9zcoa 20720",
    "addr:housenumber":"98",
    "addr:postcode":"20720",
    "addr:street":"Kale Nagusia;Guipu\u0300Zcoa",
    "iso:country":"ES",
    "sg:address":"Kale Nagusia, 98",
    "sg:city":"Azkoitia",
    "sg:orig_category":"Asociaciones, Organismos Culturales Y Socioeducativos",
    "sg:phone":"+34 943 85 14 34",
    "sg:postcode":"20720",
    "sg:province":"Guip\u00f9zcoa",
    "wof:name":"Sociedad Plaza Berri",
    "wof:placetype":"venue"
},
  "geometry": {"coordinates":[-2.3134639263,43.1762886047],"type":"Point"}
}