{
  "type": "Feature",
  "properties": {
    "iso:country":"ES",
    "sg:address":"Calle de Granada, 190",
    "sg:city":"Almeria",
    "sg:orig_category":"Peluquer\u00cdas, Peluquer\u00cda Mixta",
    "sg:phone":"+34 950 27 17 08",
    "sg:postcode":"04008",
    "sg:province":"Almer\u00eda",
    "wof:name":"Guirado Berenguel Adela Belen",
    "wof:placetype":"venue"
},
  "geometry": {"coordinates":[-2.4571828842,36.847694397],"type":"Point"}
}