{
  "type": "Feature",
  "properties": {
    "iso:country":"ES",
    "sg:address":"Av Josep Tarradellas I Joan, 219",
    "sg:city":"Hospitalet Llobregat",
    "sg:orig_category":"Agencias De Trabajo Temporal",
    "sg:phone":"+34 933 38 31 25",
    "sg:postcode":"08901",
    "sg:province":"Barcelona",
    "wof:name":"Synergie T.t. E.t.t. S.a.",
    "wof:placetype":"venue"
},
  "geometry": {"coordinates":[2.0977530479,41.3629608154],"type":"Point"}
}