{
  "type": "Feature",
  "properties": {
    "addr:full":"Avgd Cristofol Colom, 21 Son Moro Islas Baleares 07560",
    "addr:housenumber":"21",
    "addr:postcode":"07560",
    "addr:street":"Colom",
    "iso:country":"ES",
    "sg:address":"Avgd Cristofol Colom, 21",
    "sg:city":"Son Moro",
    "sg:orig_category":"Oficinas De Cambio",
    "sg:phone":"+34 971 58 68 49",
    "sg:postcode":"07560",
    "sg:province":"Islas Baleares",
    "wof:name":"Massanet Mesquida Antonia",
    "wof:placetype":"venue"
},
  "geometry": {"coordinates":[3.3764801025,39.5764541626],"type":"Point"}
}