{
  "type": "Feature",
  "properties": {
    "iso:country":"ES",
    "sg:address":"C/ Espronceda, 58",
    "sg:city":"Elche",
    "sg:orig_category":"Reposter\u00cdas",
    "sg:phone":"+34 966 64 11 03",
    "sg:postcode":"03204",
    "sg:province":"Alicante",
    "wof:name":"La Canalosa S.l.",
    "wof:placetype":"venue"
},
  "geometry": {"coordinates":[-0.7063350081,38.2609786987],"type":"Point"}
}