{
  "type": "Feature",
  "properties": {
    "addr:full":"Calle de Santos Medicos, 66 Montesinos Alicante 03187",
    "addr:housenumber":"66",
    "addr:postcode":"03187",
    "addr:street":"Calle De Santos Medicos",
    "iso:country":"ES",
    "sg:address":"Calle de Santos Medicos, 66",
    "sg:city":"Montesinos",
    "sg:orig_category":"Contenedores (mercanc\u00cdas)",
    "sg:phone":"+34 966 72 11 62",
    "sg:postcode":"03187",
    "sg:province":"Alicante",
    "wof:name":"Andres Saez Martinez S.l.",
    "wof:placetype":"venue"
},
  "geometry": {"coordinates":[-0.741347909,38.0265579224],"type":"Point"}
}