{
  "type": "Feature",
  "properties": {
    "addr:full":"Calle de Brazato, 4 Zaragoza Zaragoza 50012",
    "addr:housenumber":"4",
    "addr:postcode":"50012",
    "addr:street":"Calle De Brazato",
    "iso:country":"ES",
    "sg:address":"Calle de Brazato, 4",
    "sg:city":"Zaragoza",
    "sg:orig_category":"Negocio De Materiales De Construcci\u00d3n",
    "sg:phone":"+34 976 35 40 90",
    "sg:postcode":"50012",
    "sg:province":"Zaragoza",
    "wof:name":"Uva-cib S.l.",
    "wof:placetype":"venue"
},
  "geometry": {"coordinates":[-0.9123439789,41.6263656616],"type":"Point"}
}