{
  "type": "Feature",
  "properties": {
    "addr:full":"Cmno Ciruelos, S/n Yepes Toledo 45313",
    "addr:housenumber":"s / n",
    "addr:postcode":"45313",
    "addr:street":"Cmno Ciruelos",
    "iso:country":"ES",
    "sg:address":"Cmno Ciruelos, S/n",
    "sg:city":"Yepes",
    "sg:orig_category":"Garajes De Veh\u00cdculos",
    "sg:phone":"+34 925 14 71 29",
    "sg:postcode":"45313",
    "sg:province":"Toledo",
    "wof:name":"Jacar S.c.",
    "wof:placetype":"venue"
},
  "geometry": {"coordinates":[-3.621669054,39.906955719],"type":"Point"}
}