{
  "type": "Feature",
  "properties": {
    "iso:country":"ES",
    "sg:address":"Carrer de Sang (de La), 3",
    "sg:city":"Tortosa",
    "sg:orig_category":"Ingeniero",
    "sg:phone":"+34 977 44 05 79",
    "sg:postcode":"43500",
    "sg:province":"Tarragona",
    "wof:name":"Princep Prades Luis",
    "wof:placetype":"venue"
},
  "geometry": {"coordinates":[0.5209299922,40.8120803833],"type":"Point"}
}