{
  "type": "Feature",
  "properties": {
    "iso:country":"ES",
    "sg:address":"Calle de Mayor, 7",
    "sg:city":"Uru\u00f1uela",
    "sg:orig_category":"Cajas De Ahorro",
    "sg:phone":"+34 941 37 10 20",
    "sg:postcode":"26313",
    "sg:province":"La Rioja",
    "wof:name":"Caja De Ahorros De La Rioja",
    "wof:placetype":"venue"
},
  "geometry": {"coordinates":[-2.7086091042,42.4415092468],"type":"Point"}
}