{
  "type": "Feature",
  "properties": {
    "addr:full":"Av Puig I Ferreter, 33 Selva Del Camp Tarragona 43470",
    "addr:housenumber":"33",
    "addr:postcode":"43470",
    "addr:street":"Av Puig I Ferreter",
    "iso:country":"ES",
    "sg:address":"Av Puig I Ferreter, 33",
    "sg:city":"Selva Del Camp",
    "sg:orig_category":"Cajas De Ahorro",
    "sg:phone":"+34 977 84 51 65",
    "sg:postcode":"43470",
    "sg:province":"Tarragona",
    "sg:website":"www.lacaixa.es",
    "wof:name":"Caixa D'estalvis I Pensions De Barcelona",
    "wof:placetype":"venue"
},
  "geometry": {"coordinates":[1.1409460306,41.212562561],"type":"Point"}
}