{
  "type": "Feature",
  "properties": {
    "iso:country":"ES",
    "sg:address":"Carr Major, 19",
    "sg:city":"Seu D'urgell",
    "sg:orig_category":"Bricolaje, Herramientas (al Por Menor)",
    "sg:phone":"+34 973 35 02 55",
    "sg:postcode":"25700",
    "sg:province":"Lleida",
    "wof:name":"Mestre Serra Manuel",
    "wof:placetype":"venue"
},
  "geometry": {"coordinates":[0.6258509755,41.6140022278],"type":"Point"}
}