{
  "type": "Feature",
  "properties": {
    "iso:country":"ES",
    "sg:address":"Veintiseis, S/n",
    "sg:city":"Boiro",
    "sg:orig_category":"Florister\u00cdas",
    "sg:phone":"+34 981 84 64 55",
    "sg:postcode":"15930",
    "sg:province":"La Coru\u00f1a",
    "wof:name":"Orquidea Floristas S.l.",
    "wof:placetype":"venue"
},
  "geometry": {"coordinates":[-8.8814992905,42.6458473206],"type":"Point"}
}