{
  "type": "Feature",
  "properties": {
    "addr:full":"Ctra Coru\u00d1a, Km. 0022,0 Carriles Madrid 28230",
    "addr:postcode":"28230",
    "addr:street":"Ctra Corun\u0303A Km. 0022,0",
    "iso:country":"ES",
    "sg:address":"Ctra Coru\u00d1a, Km. 0022,0",
    "sg:city":"Carriles",
    "sg:orig_category":"Peluquer\u00cdas, Peluquer\u00cda Mixta",
    "sg:phone":"+34 916 37 33 38",
    "sg:postcode":"28230",
    "sg:province":"Madrid",
    "wof:name":"Sanchez De Diego Francisco Javier",
    "wof:placetype":"venue"
},
  "geometry": {"coordinates":[-3.7057700157,40.42029953],"type":"Point"}
}