{
  "type": "Feature",
  "properties": {
    "addr:full":"Avda Manuel Llaneza, 2 Gijon Asturias 33205",
    "addr:housenumber":"2",
    "addr:postcode":"33205",
    "addr:street":"Avda Manuel Llaneza",
    "iso:country":"ES",
    "sg:address":"Avda Manuel Llaneza, 2",
    "sg:city":"Gijon",
    "sg:orig_category":"Ropa Para Se\u00d1oras (al Por Menor)",
    "sg:phone":"+34 985 39 64 24",
    "sg:postcode":"33205",
    "sg:province":"Asturias",
    "wof:name":"Montes Cueto Ana",
    "wof:placetype":"venue"
},
  "geometry": {"coordinates":[-5.6597480774,43.5364532471],"type":"Point"}
}