{
  "type": "Feature",
  "properties": {
    "addr:full":"Carrer de Margarit, 20 Barcelona Barcelona 08004",
    "addr:housenumber":"20",
    "addr:postcode":"08004",
    "addr:street":"Carrer De Margarit",
    "iso:country":"ES",
    "sg:address":"Carrer de Margarit, 20",
    "sg:city":"Barcelona",
    "sg:orig_category":"Prot\u00c9sicos Dentales",
    "sg:phone":"+34 934 41 92 00",
    "sg:postcode":"08004",
    "sg:province":"Barcelona",
    "wof:name":"Mu\u00f1oz Valero Cesar",
    "wof:placetype":"venue"
},
  "geometry": {"coordinates":[2.1634309292,41.3737754822],"type":"Point"}
}