{
  "type": "Feature",
  "properties": {
    "iso:country":"ES",
    "sg:address":"Calle de Espiritu Santo, 47",
    "sg:city":"Madrid",
    "sg:orig_category":"Caf\u00c9s, Bares, Cervecer\u00cdas",
    "sg:phone":"+34 915 21 85 76",
    "sg:postcode":"28004",
    "sg:province":"Madrid",
    "sg:website":"www.jandjbooksandcoffee.net",
    "wof:name":"J&j Book Shop And Coffee House S.l.",
    "wof:placetype":"venue"
},
  "geometry": {"coordinates":[-3.7070429325,40.425819397],"type":"Point"}
}