{
  "type": "Feature",
  "properties": {
    "iso:country":"ES",
    "sg:address":"Avda Fuerzas Armadas (de Las), 1",
    "sg:city":"Granada",
    "sg:orig_category":"Electrodom\u00c9sticos (al Por Menor)",
    "sg:phone":"+34 958 27 73 04",
    "sg:postcode":"18014",
    "sg:province":"Granada",
    "wof:name":"Garcia-lujan Nobel Dionisio",
    "wof:placetype":"venue"
},
  "geometry": {"coordinates":[-3.6117939949,37.1890907288],"type":"Point"}
}