{
  "type": "Feature",
  "properties": {
    "iso:country":"ES",
    "sg:address":"Calle de Alcalde Mu\u00d1oz, 41",
    "sg:city":"Almeria",
    "sg:orig_category":"Bisuter\u00cda, Joyer\u00cda, Relojer\u00cda (al Por Menor)",
    "sg:phone":"+34 950 26 05 98",
    "sg:postcode":"04004",
    "sg:province":"Almer\u00eda",
    "wof:name":"Villarrubia Pinzon Julio",
    "wof:placetype":"venue"
},
  "geometry": {"coordinates":[-2.459444046,36.8426475525],"type":"Point"}
}