{
  "type": "Feature",
  "properties": {
    "addr:full":"Avda Bucaramanga, 2 Madrid Madrid 28033",
    "addr:housenumber":"2",
    "addr:postcode":"28033",
    "addr:street":"Avda Bucaramanga",
    "iso:country":"ES",
    "sg:address":"Avda Bucaramanga, 2",
    "sg:city":"Madrid",
    "sg:orig_category":"Institutos De Belleza",
    "sg:phone":"+34 913 81 88 78",
    "sg:postcode":"28033",
    "sg:province":"Madrid",
    "wof:name":"Perez Giron Angel Carlos",
    "wof:placetype":"venue"
},
  "geometry": {"coordinates":[-3.6358850002,40.4720916748],"type":"Point"}
}