{
  "type": "Feature",
  "properties": {
    "addr:full":"Avda Rio Estenilla, 4 Poligono Sta M. De Benquerencia Toledo 45007",
    "addr:housenumber":"4 poligono",
    "addr:postcode":"45007",
    "addr:street":"Avda Rio Estenilla;Sta M. De Benquerencia",
    "iso:country":"ES",
    "sg:address":"Avda Rio Estenilla, 4",
    "sg:city":"Poligono Sta M. De Benquerencia",
    "sg:orig_category":"Mec\u00c1nico Del Autom\u00d3vil",
    "sg:phone":"+34 925 23 10 05",
    "sg:postcode":"45007",
    "sg:province":"Toledo",
    "wof:name":"Talleres Saez-toledo Motor S.l.l.",
    "wof:placetype":"venue"
},
  "geometry": {"coordinates":[-3.9474089146,39.8690643311],"type":"Point"}
}