{
  "type": "Feature",
  "properties": {
    "iso:country":"ES",
    "sg:address":"Calle de Jose Del Pino, 62",
    "sg:city":"Madrid",
    "sg:orig_category":"Molduras, Junquillos, Listones Y Molduras Perforadas",
    "sg:phone":"+34 917 98 16 68",
    "sg:postcode":"28021",
    "sg:province":"Madrid",
    "wof:name":"Bar Plaza Garrido",
    "wof:placetype":"venue"
},
  "geometry": {"coordinates":[-3.6889948845,40.3507766724],"type":"Point"}
}