{
  "type": "Feature",
  "properties": {
    "iso:country":"ES",
    "sg:address":"Carrer de Guarderia, 7",
    "sg:city":"Barcelona",
    "sg:orig_category":"Arquitectos",
    "sg:phone":"+34 932 06 00 13",
    "sg:postcode":"08017",
    "sg:province":"Barcelona",
    "wof:name":"Limit Cercos S.l.",
    "wof:placetype":"venue"
},
  "geometry": {"coordinates":[2.1094961166,41.402431488],"type":"Point"}
}