{
  "type": "Feature",
  "properties": {
    "addr:full":"Av Mar, 13 Orihuela Alicante 03300",
    "addr:housenumber":"13",
    "addr:postcode":"03300",
    "addr:street":"Av Mar",
    "iso:country":"ES",
    "sg:address":"Av Mar, 13",
    "sg:city":"Orihuela",
    "sg:orig_category":"Material Y Suministros Para Perforaciones, Sondeos",
    "sg:phone":"+34 965 30 16 30",
    "sg:postcode":"03300",
    "sg:province":"Alicante",
    "wof:name":"Ferrando Campillo Jose",
    "wof:placetype":"venue"
},
  "geometry": {"coordinates":[-0.947378993,38.0783004761],"type":"Point"}
}