{
  "type": "Feature",
  "properties": {
    "iso:country":"ES",
    "sg:address":"Calle de Rosa Seminario, 1",
    "sg:city":"Doneztebe",
    "sg:orig_category":"Promotores Constructores",
    "sg:phone":"+34 948 45 07 52",
    "sg:postcode":"31740",
    "sg:province":"Navarra",
    "wof:name":"Construcciones Inzakardi S.a.",
    "wof:placetype":"venue"
},
  "geometry": {"coordinates":[-1.6657040119,43.1346588135],"type":"Point"}
}