{
  "type": "Feature",
  "properties": {
    "iso:country":"ES",
    "sg:address":"Rua Antonio Palacios, S/n",
    "sg:city":"Porri\u00f1o",
    "sg:orig_category":"Tapicer\u00cdas",
    "sg:phone":"+34 986 33 07 19",
    "sg:postcode":"36400",
    "sg:province":"Pontevedra",
    "wof:name":"Losada Sequeiros Juan Francisco",
    "wof:placetype":"venue"
},
  "geometry": {"coordinates":[-8.6191692352,42.161315918],"type":"Point"}
}