{
  "type": "Feature",
  "properties": {
    "iso:country":"ES",
    "sg:address":"Calle de Albillera, S/n",
    "sg:city":"Zamora",
    "sg:orig_category":"Sales (al Por Mayor)",
    "sg:phone":"+34 980 51 92 43",
    "sg:postcode":"49025",
    "sg:province":"Zamora",
    "wof:name":"Bego\u00f1a Paramio S.l.",
    "wof:placetype":"venue"
},
  "geometry": {"coordinates":[-5.7527933121,41.5096740723],"type":"Point"}
}