{
  "type": "Feature",
  "properties": {
    "iso:country":"ES",
    "sg:address":"Calle de Picasso, 9",
    "sg:city":"Villanueva Reina",
    "sg:orig_category":"Reposter\u00cdas",
    "sg:phone":"+34 953 53 74 39",
    "sg:postcode":"23730",
    "sg:province":"Ja\u00e9n",
    "wof:name":"Cobo Lopez Diego",
    "wof:placetype":"venue"
},
  "geometry": {"coordinates":[-3.9134919643,38.0058631897],"type":"Point"}
}