{
  "type": "Feature",
  "properties": {
    "iso:country":"ES",
    "sg:address":"Calle de Navahermosa, 2",
    "sg:city":"San Pablo De Los Montes",
    "sg:orig_category":"Tiendas De Grano, Frutas Y Legumbres Secas (al Por Menor)",
    "sg:phone":"+34 925 41 61 02",
    "sg:postcode":"45120",
    "sg:province":"Toledo",
    "wof:name":"Ramos Ubeda Amelia",
    "wof:placetype":"venue"
},
  "geometry": {"coordinates":[-4.3332390785,39.5399284363],"type":"Point"}
}