{
  "type": "Feature",
  "properties": {
    "iso:country":"ES",
    "sg:address":"Calle de Garcia Luna, 24",
    "sg:city":"Madrid",
    "sg:orig_category":"Cerrajer\u00cda, Ferrallista",
    "sg:phone":"+34 914 15 23 36",
    "sg:postcode":"28002",
    "sg:province":"Madrid",
    "wof:name":"Merino Aparicio Emilio",
    "wof:placetype":"venue"
},
  "geometry": {"coordinates":[-3.6737830639,40.4462738037],"type":"Point"}
}