{
  "type": "Feature",
  "properties": {
    "iso:country":"ES",
    "sg:address":"Carrer de Caracas, 49",
    "sg:city":"Barcelona",
    "sg:orig_category":"Artes Gr\u00c1ficas, Artes Pl\u00c1sticas (curso)",
    "sg:phone":"+34 933 46 37 84",
    "sg:postcode":"08030",
    "sg:province":"Barcelona",
    "wof:name":"J.j. Art Grafic S.l.",
    "wof:placetype":"venue"
},
  "geometry": {"coordinates":[2.2019839287,41.4457397461],"type":"Point"}
}