{
  "type": "Feature",
  "properties": {
    "addr:full":"Calle de Alondra, 6 Humera-somosaguas-prado Del Rey Madrid 28223",
    "addr:housenumber":"6",
    "addr:postcode":"28223",
    "addr:street":"Calle De Alondra",
    "iso:country":"ES",
    "sg:address":"Calle de Alondra, 6",
    "sg:city":"Humera-somosaguas-prado Del Rey",
    "sg:orig_category":"Asesor\u00cda Sobre Comunicaci\u00d3n De Empresas",
    "sg:phone":"+34 913 51 72 74",
    "sg:postcode":"28223",
    "sg:province":"Madrid",
    "wof:name":"Finanzas 92 S.a.",
    "wof:placetype":"venue"
},
  "geometry": {"coordinates":[-3.7826886177,40.4150238037],"type":"Point"}
}