{
  "type": "Feature",
  "properties": {
    "addr:full":"Carrer de Pere Benavent, 22 Reus Tarragona 43205",
    "addr:housenumber":"22",
    "addr:postcode":"43205",
    "addr:street":"Carrer De Pere Benavent",
    "iso:country":"ES",
    "sg:address":"Carrer de Pere Benavent, 22",
    "sg:city":"Reus",
    "sg:orig_category":"Cerrajer\u00cda, Ferrallista",
    "sg:phone":"+34 977 75 55 53",
    "sg:postcode":"43205",
    "sg:province":"Tarragona",
    "wof:name":"Jaca Borao Alfredo",
    "wof:placetype":"venue"
},
  "geometry": {"coordinates":[1.107929945,41.1519889832],"type":"Point"}
}