{
  "type": "Feature",
  "properties": {
    "addr:full":"Calle de Tecen, 70 Palmas De Gran Canaria Las Palmas 35009",
    "addr:housenumber":"70",
    "addr:postcode":"35009",
    "addr:street":"Calle De Tecen",
    "iso:country":"ES",
    "sg:address":"Calle de Tecen, 70",
    "sg:city":"Palmas De Gran Canaria",
    "sg:orig_category":"Quincaller\u00cda (al Por Mayor)",
    "sg:phone":"+34 928 46 52 75",
    "sg:postcode":"35009",
    "sg:province":"Las Palmas",
    "wof:name":"Comercial Ferrecana S.l.",
    "wof:placetype":"venue"
},
  "geometry": {"coordinates":[-15.4243745804,28.1509361267],"type":"Point"}
}