{
  "type": "Feature",
  "properties": {
    "iso:country":"ES",
    "sg:address":"Rua Os Xuncos, S/n",
    "sg:city":"Nos",
    "sg:orig_category":"Montaje (empresas De)",
    "sg:phone":"+34 981 65 03 37",
    "sg:postcode":"15176",
    "sg:province":"La Coru\u00f1a",
    "wof:name":"Prefabricacion Y Montajes Del Noroeste S.a.",
    "wof:placetype":"venue"
},
  "geometry": {"coordinates":[-8.3265943527,43.3246536255],"type":"Point"}
}