{
  "type": "Feature",
  "properties": {
    "iso:country":"ES",
    "sg:address":"Avda Ordo\u00d1o Ii, 12",
    "sg:city":"Le\u00f3n",
    "sg:orig_category":"Ropa Para Se\u00d1oras (al Por Menor)",
    "sg:phone":"+34 987 22 99 72",
    "sg:postcode":"24001",
    "sg:province":"Le\u00f3n",
    "wof:name":"Carbajo Guerra Amable",
    "wof:placetype":"venue"
},
  "geometry": {"coordinates":[-5.5743870735,42.5973320007],"type":"Point"}
}