{
  "type": "Feature",
  "properties": {
    "addr:full":"Carr Ample, 14 Figueres Girona 17600",
    "addr:housenumber":"14",
    "addr:postcode":"17600",
    "addr:street":"Carr Ample",
    "iso:country":"ES",
    "sg:address":"Carr Ample, 14",
    "sg:city":"Figueres",
    "sg:orig_category":"Ropa Para Ni\u00d1os (al Por Menor)",
    "sg:phone":"+34 972 51 30 57",
    "sg:postcode":"17600",
    "sg:province":"Girona",
    "sg:website":"www.ikks.com",
    "wof:name":"Valso 07, S.l.",
    "wof:placetype":"venue"
},
  "geometry": {"coordinates":[2.9581100941,42.2656898499],"type":"Point"}
}