{
  "type": "Feature",
  "properties": {
    "iso:country":"ES",
    "sg:address":"Pj Maians, 1",
    "sg:city":"Toses",
    "sg:orig_category":"Promotores Constructores",
    "sg:phone":"+34 972 73 63 16",
    "sg:postcode":"17536",
    "sg:province":"Girona",
    "wof:name":"Cota 1400s.l.",
    "wof:placetype":"venue"
},
  "geometry": {"coordinates":[2.0153439045,42.3213729858],"type":"Point"}
}