{
  "type": "Feature",
  "properties": {
    "addr:full":"Pl Rector Rubi, 11 Manacor Islas Baleares 07500",
    "addr:housenumber":"11",
    "addr:postcode":"07500",
    "addr:street":"Pl Rector Rubi",
    "iso:country":"ES",
    "sg:address":"Pl Rector Rubi, 11",
    "sg:city":"Manacor",
    "sg:orig_category":"Financiaci\u00d3n Y Cr\u00c9ditos",
    "sg:phone":"+34 971 84 33 90",
    "sg:postcode":"07500",
    "sg:province":"Islas Baleares",
    "wof:name":"Isba S.g.r.",
    "wof:placetype":"venue"
},
  "geometry": {"coordinates":[3.2110528946,39.5686645508],"type":"Point"}
}