{
  "type": "Feature",
  "properties": {
    "iso:country":"ES",
    "sg:address":"Calle de Camino Viejo De Leganes, 177",
    "sg:city":"Madrid",
    "sg:orig_category":"Fabricaci\u00d3n De Sobres, Bolsas Y Fundas",
    "sg:phone":"+34 914 65 64 60",
    "sg:postcode":"28025",
    "sg:province":"Madrid",
    "wof:name":"Gomez Vicente Manuel",
    "wof:placetype":"venue"
},
  "geometry": {"coordinates":[-3.7311840057,40.3810997009],"type":"Point"}
}