{
  "type": "Feature",
  "properties": {
    "iso:country":"ES",
    "sg:address":"Carrer de Angel Guimera, 91",
    "sg:city":"Cardedeu",
    "sg:orig_category":"Arquitectos",
    "sg:phone":"+34 938 45 47 52",
    "sg:postcode":"08440",
    "sg:province":"Barcelona",
    "wof:name":"Angle Arquitectura S.l.",
    "wof:placetype":"venue"
},
  "geometry": {"coordinates":[2.3594360352,41.6426887512],"type":"Point"}
}