{
  "type": "Feature",
  "properties": {
    "addr:full":"C/ Manuel Vicente Pastor, 76 Elche Alicante 03206",
    "addr:housenumber":"76",
    "addr:postcode":"03206",
    "addr:street":"C / Manuel Vicente Pastor",
    "iso:country":"ES",
    "sg:address":"C/ Manuel Vicente Pastor, 76",
    "sg:city":"Elche",
    "sg:orig_category":"Droguer\u00cdas (al Por Menor)",
    "sg:phone":"+34 965 46 44 03",
    "sg:postcode":"03206",
    "sg:province":"Alicante",
    "wof:name":"Zapata Diaz Guadalupe",
    "wof:placetype":"venue"
},
  "geometry": {"coordinates":[-0.7067278028,38.2744216919],"type":"Point"}
}