{
  "type": "Feature",
  "properties": {
    "iso:country":"ES",
    "sg:address":"C/ Sor Josefa Alcorta, 38",
    "sg:city":"Elche",
    "sg:orig_category":"Alimentaci\u00d3n Animal (fabricaci\u00d3n, Al Por Mayor)",
    "sg:phone":"+34 966 63 17 49",
    "sg:postcode":"03204",
    "sg:province":"Alicante",
    "wof:name":"Vicente Orts Juan Jose",
    "wof:placetype":"venue"
},
  "geometry": {"coordinates":[-0.7024959922,38.2579612732],"type":"Point"}
}