{
  "type": "Feature",
  "properties": {
    "iso:country":"ES",
    "sg:address":"Cami Ral, 377",
    "sg:city":"Mataro",
    "sg:orig_category":"M\u00c9dicos: Estomatolog\u00cda",
    "sg:phone":"+34 937 55 30 95",
    "sg:postcode":"08301",
    "sg:province":"Barcelona",
    "wof:name":"Marmol Mastrangelo Pablo Jose",
    "wof:placetype":"venue"
},
  "geometry": {"coordinates":[2.4446258545,41.5372161865],"type":"Point"}
}