{
  "type": "Feature",
  "properties": {
    "addr:full":"Via Universitas, 2 Zaragoza Zaragoza 50009",
    "addr:housenumber":"2",
    "addr:postcode":"50009",
    "addr:street":"Via Universitas",
    "iso:country":"ES",
    "sg:address":"Via Universitas, 2",
    "sg:city":"Zaragoza",
    "sg:orig_category":"Caf\u00c9s, Bares, Cervecer\u00cdas",
    "sg:phone":"+34 976 35 00 04",
    "sg:postcode":"50009",
    "sg:province":"Zaragoza",
    "wof:name":"Valero Tomas Israel",
    "wof:placetype":"venue"
},
  "geometry": {"coordinates":[-0.905938983,41.6437797546],"type":"Point"}
}