{
  "type": "Feature",
  "properties": {
    "addr:full":"San Marcial Plaza - Plaza San Marcial, 3 Lasarte Guip\u00f9zcoa 20160",
    "addr:housenumber":"3",
    "addr:postcode":"20160",
    "addr:street":"San Marcial Plaza Plaza San Marcial;Lasarte Guipu\u0300Zcoa",
    "iso:country":"ES",
    "sg:address":"San Marcial Plaza - Plaza San Marcial, 3",
    "sg:city":"Lasarte",
    "sg:orig_category":"Dise\u00d1o Industrial",
    "sg:phone":"+34 943 37 24 96",
    "sg:postcode":"20160",
    "sg:province":"Guip\u00f9zcoa",
    "wof:name":"Aizpurua Arrizabalaga Miguel Angel",
    "wof:placetype":"venue"
},
  "geometry": {"coordinates":[-2.020414114,43.2698173523],"type":"Point"}
}