{
  "type": "Feature",
  "properties": {
    "addr:full":"Calle de Escofina, 51 Estacion Madrid 28400",
    "addr:housenumber":"51",
    "addr:postcode":"28400",
    "addr:street":"Calle De Escofina",
    "iso:country":"ES",
    "sg:address":"Calle de Escofina, 51",
    "sg:city":"Estacion",
    "sg:orig_category":"Muebles, Minoristas",
    "sg:phone":"+34 918 50 56 82",
    "sg:postcode":"28400",
    "sg:province":"Madrid",
    "wof:name":"Martin Anton Alfredo",
    "wof:placetype":"venue"
},
  "geometry": {"coordinates":[-4.0170531273,40.6260948181],"type":"Point"}
}