{
  "type": "Feature",
  "properties": {
    "addr:full":"Plaz Mariano Benlliure, 5 Valencia Valencia 46002",
    "addr:housenumber":"5",
    "addr:postcode":"46002",
    "addr:street":"Benlliure",
    "iso:country":"ES",
    "sg:address":"Plaz Mariano Benlliure, 5",
    "sg:city":"Valencia",
    "sg:orig_category":"Ense\u00d1anza Variada",
    "sg:phone":"+34 963 94 24 32",
    "sg:postcode":"46002",
    "sg:province":"Valencia",
    "sg:website":"www.adams.es",
    "wof:name":"Centro De Estudios Administrativos Y Profesionales S.a.",
    "wof:placetype":"venue"
},
  "geometry": {"coordinates":[-0.375981003,39.4723205566],"type":"Point"}
}