{
  "type": "Feature",
  "properties": {
    "addr:full":"Calle de Luna, 14 Campo Criptana Ciudad Real 13610",
    "addr:housenumber":"14",
    "addr:postcode":"13610",
    "addr:street":"Calle De Luna;Criptana",
    "iso:country":"ES",
    "sg:address":"Calle de Luna, 14",
    "sg:city":"Campo Criptana",
    "sg:orig_category":"Promotores Constructores",
    "sg:phone":"+34 926 56 32 24",
    "sg:postcode":"13610",
    "sg:province":"Ciudad Real",
    "wof:name":"Construcciones Y Reformas Manzaneque Lozano S.l.",
    "wof:placetype":"venue"
},
  "geometry": {"coordinates":[-3.1300730705,39.4066238403],"type":"Point"}
}