{
  "type": "Feature",
  "properties": {
    "iso:country":"ES",
    "sg:address":"Parque Corredor, S/n",
    "sg:city":"Torrejon Ardoz",
    "sg:orig_category":"Fabricaci\u00d3n De Sobres, Bolsas Y Fundas",
    "sg:phone":"+34 916 56 73 93",
    "sg:postcode":"28850",
    "sg:province":"Madrid",
    "wof:name":"Fernandez Veiga Lourdes",
    "wof:placetype":"venue"
},
  "geometry": {"coordinates":[-3.4763290882,40.4592514038],"type":"Point"}
}