{
  "type": "Feature",
  "properties": {
    "addr:full":"Ctra. Madrid-barcelona, S/n Medinaceli Soria 42240",
    "addr:housenumber":"s",
    "addr:postcode":"42240",
    "addr:street":"Ctra. Madrid-Barcelona;/ N",
    "iso:country":"ES",
    "sg:address":"Ctra. Madrid-barcelona, S/n",
    "sg:city":"Medinaceli",
    "sg:orig_category":"Administraciones Regionales, Departamentales Y Locales",
    "sg:phone":"+34 975 32 60 53",
    "sg:postcode":"42240",
    "sg:province":"Soria",
    "wof:name":"Ayuntamiento De Medinaceli",
    "wof:placetype":"venue"
},
  "geometry": {"coordinates":[-2.4210736752,41.1687316895],"type":"Point"}
}