{
  "type": "Feature",
  "properties": {
    "iso:country":"ES",
    "sg:address":"Calle de Secundino Esnaola, 2",
    "sg:city":"Zumarraga",
    "sg:orig_category":"Electricidad (montaje, Ensamblaje De Componentes)",
    "sg:phone":"+34 943 72 02 15",
    "sg:postcode":"20700",
    "sg:province":"Guip\u00f9zcoa",
    "wof:name":"Urcelay Maiztegui Jose Ramon",
    "wof:placetype":"venue"
},
  "geometry": {"coordinates":[-2.3170990944,43.0887718201],"type":"Point"}
}