{
  "type": "Feature",
  "properties": {
    "addr:full":"Calle de Huesca, 34 Logro\u00f1o La Rioja 26005",
    "addr:housenumber":"34",
    "addr:postcode":"26005",
    "addr:street":"Calle De Huesca;Rioja",
    "iso:country":"ES",
    "sg:address":"Calle de Huesca, 34",
    "sg:city":"Logro\u00f1o",
    "sg:orig_category":"Muebles, Minoristas",
    "sg:phone":"+34 941 20 74 75",
    "sg:postcode":"26005",
    "sg:province":"La Rioja",
    "sg:website":"www.banak.com",
    "wof:name":"Muebles J. Vicente S.a.",
    "wof:placetype":"venue"
},
  "geometry": {"coordinates":[-2.4551589489,42.4605407715],"type":"Point"}
}