{
  "type": "Feature",
  "properties": {
    "iso:country":"ES",
    "sg:address":"Carrer de Historiador Ramon D'abada, 10",
    "sg:city":"Vic",
    "sg:orig_category":"T\u00c9cnicos Veterinarios",
    "sg:phone":"+34 938 81 40 85",
    "sg:postcode":"08500",
    "sg:province":"Barcelona",
    "wof:name":"Gestio Porcina S.l.",
    "wof:placetype":"venue"
},
  "geometry": {"coordinates":[2.2531929016,41.9273757935],"type":"Point"}
}