{
  "type": "Feature",
  "properties": {
    "iso:country":"ES",
    "sg:address":"Rua Ramon Cabanillas, 116",
    "sg:city":"Praia",
    "sg:orig_category":"Tintes (fabricaci\u00d3n, Al Por Mayor)",
    "sg:phone":"+34 986 31 03 89",
    "sg:postcode":"36950",
    "sg:province":"Pontevedra",
    "wof:name":"Cruz Collazo Maria Jesus",
    "wof:placetype":"venue"
},
  "geometry": {"coordinates":[-8.738442421,42.2772254944],"type":"Point"}
}