{
  "type": "Feature",
  "properties": {
    "addr:full":"Calle de Cordoba, 10 Torres Alameda Madrid 28813",
    "addr:housenumber":"10",
    "addr:postcode":"28813",
    "addr:street":"Calle De Cordoba;Alameda",
    "iso:country":"ES",
    "sg:address":"Calle de Cordoba, 10",
    "sg:city":"Torres Alameda",
    "sg:orig_category":"Ropa Para Beb\u00c9s Y Ni\u00d1os (confecci\u00d3n, Al Por Mayor)",
    "sg:phone":"+34 918 85 80 90",
    "sg:postcode":"28813",
    "sg:province":"Madrid",
    "wof:name":"Pardo Adarve Ana Montserrat",
    "wof:placetype":"venue"
},
  "geometry": {"coordinates":[-3.3632357121,40.4045448303],"type":"Point"}
}