{
  "type": "Feature",
  "properties": {
    "addr:full":"Avda Mediterraneo, 19 Madrid Madrid 28007",
    "addr:housenumber":"19",
    "addr:postcode":"madrid;28007",
    "addr:street":"Avda Mediterraneo",
    "iso:country":"ES",
    "sg:address":"Avda Mediterraneo, 19",
    "sg:city":"Madrid",
    "sg:orig_category":"Bancos",
    "sg:phone":"+34 915 01 05 72",
    "sg:postcode":"28007",
    "sg:province":"Madrid",
    "wof:name":"Bankinter S.a.",
    "wof:placetype":"venue"
},
  "geometry": {"coordinates":[-3.6747610569,40.4072875977],"type":"Point"}
}