{
  "type": "Feature",
  "properties": {
    "iso:country":"ES",
    "sg:address":"Calle de Salobras, 22",
    "sg:city":"Monzon",
    "sg:orig_category":"Promotores Constructores",
    "sg:phone":"+34 974 40 15 56",
    "sg:postcode":"22400",
    "sg:province":"Huesca",
    "wof:name":"Ferrer Lordan Ismael",
    "wof:placetype":"venue"
},
  "geometry": {"coordinates":[0.1996289939,41.9150428772],"type":"Point"}
}