{
  "type": "Feature",
  "properties": {
    "addr:full":"Ctra Aguilar, Km. 0089,4 Puente-genil C\u00f3rdoba 14500",
    "addr:postcode":"14500",
    "addr:street":"Ctra Aguilar Km. 0089,4 Puente-Genil Co\u0301Rdoba",
    "iso:country":"ES",
    "sg:address":"Ctra Aguilar, Km. 0089,4",
    "sg:city":"Puente-genil",
    "sg:orig_category":"Pompas F\u00danebres, Inhumaciones Y Cremaciones",
    "sg:phone":"+34 957 60 62 65",
    "sg:postcode":"14500",
    "sg:province":"C\u00f3rdoba",
    "sg:website":"www.fedelsur.com",
    "wof:name":"Fedelsur S.l.",
    "wof:placetype":"venue"
},
  "geometry": {"coordinates":[-4.7779579163,37.3909187317],"type":"Point"}
}