{
  "type": "Feature",
  "properties": {
    "iso:country":"ES",
    "sg:address":"Calle de Nuestra Se\u00d1ora De Belvis, 6",
    "sg:city":"S. Lorenzo Parrilla",
    "sg:orig_category":"Farmacias",
    "sg:phone":"+34 969 29 60 32",
    "sg:postcode":"16770",
    "sg:province":"Cuenca",
    "wof:name":"Polo Ca\u00f1ada Sonia",
    "wof:placetype":"venue"
},
  "geometry": {"coordinates":[-2.3602690697,39.8505096436],"type":"Point"}
}