{
  "type": "Feature",
  "properties": {
    "addr:full":"Carrer de Apuntadors, 3 Palma Islas Baleares 07012",
    "addr:housenumber":"3",
    "addr:postcode":"07012",
    "addr:street":"Carrer De Apuntadors",
    "iso:country":"ES",
    "sg:address":"Carrer de Apuntadors, 3",
    "sg:city":"Palma",
    "sg:orig_category":"Abogados",
    "sg:phone":"+34 971 72 54 32",
    "sg:postcode":"07012",
    "sg:province":"Islas Baleares",
    "wof:name":"Dameto Cotoner Fernando",
    "wof:placetype":"venue"
},
  "geometry": {"coordinates":[2.6461250782,39.5688896179],"type":"Point"}
}