{
  "type": "Feature",
  "properties": {
    "addr:full":"Iturriotz Kalea, 43 Arrasate Guip\u00f9zcoa 20500",
    "addr:housenumber":"43",
    "addr:postcode":"20500",
    "addr:street":"Iturriotz Kalea;Guipu\u0300Zcoa",
    "iso:country":"ES",
    "sg:address":"Iturriotz Kalea, 43",
    "sg:city":"Arrasate",
    "sg:orig_category":"Ense\u00d1anza, Formaci\u00d3n Profesional: Aprendizaje",
    "sg:phone":"+34 943 79 13 20",
    "sg:postcode":"20500",
    "sg:province":"Guip\u00f9zcoa",
    "wof:name":"Lekuona Ruiz De Gauna Jenaro",
    "wof:placetype":"venue"
},
  "geometry": {"coordinates":[-2.4917221069,43.0649490356],"type":"Point"}
}