{
  "type": "Feature",
  "properties": {
    "addr:full":"Calle de Gaspar Calderas, 6 Sevilla Sevilla 41014",
    "addr:housenumber":"6",
    "addr:postcode":"41014",
    "addr:street":"Calle De Gaspar Calderas",
    "iso:country":"ES",
    "sg:address":"Calle de Gaspar Calderas, 6",
    "sg:city":"Sevilla",
    "sg:orig_category":"Art\u00cdculos De Decoraci\u00d3n",
    "sg:phone":"+34 954 69 23 34",
    "sg:postcode":"41014",
    "sg:province":"Sevilla",
    "wof:name":"Dominguez Salazar Jesus",
    "wof:placetype":"venue"
},
  "geometry": {"coordinates":[-5.969479084,37.3245887756],"type":"Point"}
}