{
  "type": "Feature",
  "properties": {
    "addr:full":"Carrer de Pescadors, 17 Barcelona Barcelona 08003",
    "addr:housenumber":"17",
    "addr:postcode":"08003",
    "addr:street":"Carrer De Pescadors",
    "iso:country":"ES",
    "sg:address":"Carrer de Pescadors, 17",
    "sg:city":"Barcelona",
    "sg:orig_category":"M\u00c9dicos: Estomatolog\u00cda",
    "sg:phone":"+34 932 21 46 84",
    "sg:postcode":"08003",
    "sg:province":"Barcelona",
    "wof:name":"Madrid Labarta Vicente",
    "wof:placetype":"venue"
},
  "geometry": {"coordinates":[2.1890621185,41.3788299561],"type":"Point"}
}