{
  "type": "Feature",
  "properties": {
    "addr:full":"Calle de Arzobispo Morcillo, S/n Madrid Madrid 28029",
    "addr:housenumber":"s / n",
    "addr:postcode":"28029",
    "addr:street":"Calle De Arzobispo Morcillo",
    "iso:country":"ES",
    "sg:address":"Calle de Arzobispo Morcillo, S/n",
    "sg:city":"Madrid",
    "sg:orig_category":"Ropa Para Se\u00d1oras (al Por Menor)",
    "sg:phone":"+34 913 58 00 40",
    "sg:postcode":"28029",
    "sg:province":"Madrid",
    "wof:name":"Cabo Romanutti Julia Cristina",
    "wof:placetype":"venue"
},
  "geometry": {"coordinates":[-3.6930296421,40.4813957214],"type":"Point"}
}