{
  "type": "Feature",
  "properties": {
    "addr:full":"Calle de Tras La Puerta, 2 Cordoba C\u00f3rdoba 14010",
    "addr:housenumber":"2",
    "addr:postcode":"14010",
    "addr:street":"Calle De Tras La Puerta;Co\u0301Rdoba",
    "iso:country":"ES",
    "sg:address":"Calle de Tras La Puerta, 2",
    "sg:city":"Cordoba",
    "sg:orig_category":"Ropa Para Ni\u00d1os (al Por Menor)",
    "sg:phone":"+34 957 26 54 42",
    "sg:postcode":"14010",
    "sg:province":"C\u00f3rdoba",
    "wof:name":"Baena Gomez Rafael",
    "wof:placetype":"venue"
},
  "geometry": {"coordinates":[-4.7634139061,37.8904647827],"type":"Point"}
}