{
  "type": "Feature",
  "properties": {
    "iso:country":"ES",
    "sg:address":"Calle de Mu\u00d1oz Crespo, 11",
    "sg:city":"Azuaga",
    "sg:orig_category":"Farmacias",
    "sg:phone":"+34 924 89 01 22",
    "sg:postcode":"06920",
    "sg:province":"Badajoz",
    "wof:name":"Cabeza Torres Maria Angeles",
    "wof:placetype":"venue"
},
  "geometry": {"coordinates":[-5.6754770279,38.2583312988],"type":"Point"}
}