{
  "type": "Feature",
  "properties": {
    "iso:country":"ES",
    "sg:address":"Carrer de Cortada, 13",
    "sg:city":"Hospitalet Llobregat",
    "sg:orig_category":"Animales (al Por Menor)",
    "sg:phone":"+34 934 40 51 76",
    "sg:postcode":"08905",
    "sg:province":"Barcelona",
    "wof:name":"Sirvent Valles Jesus",
    "wof:placetype":"venue"
},
  "geometry": {"coordinates":[2.115031004,41.369354248],"type":"Point"}
}