{
  "type": "Feature",
  "properties": {
    "iso:country":"ES",
    "sg:address":"Calle de Duque De Ahumada, 4",
    "sg:city":"Rota",
    "sg:orig_category":"Estancos",
    "sg:phone":"+34 956 81 57 03",
    "sg:postcode":"11520",
    "sg:province":"C\u00e1diz",
    "wof:name":"Torres Gallego Jose",
    "wof:placetype":"venue"
},
  "geometry": {"coordinates":[-6.3591361046,36.6273269653],"type":"Point"}
}