{
  "type": "Feature",
  "properties": {
    "iso:country":"ES",
    "sg:address":"Ctra Extremadura, Km. 0474,0",
    "sg:city":"Camas",
    "sg:orig_category":"Venta, Montaje De Neum\u00c1ticos",
    "sg:phone":"+34 954 39 23 07",
    "sg:postcode":"41900",
    "sg:province":"Sevilla",
    "wof:name":"Neumasur S.c.",
    "wof:placetype":"venue"
},
  "geometry": {"coordinates":[-6.0344491005,37.4007263184],"type":"Point"}
}