{
  "type": "Feature",
  "properties": {
    "addr:full":"Calle de Fuente Del Rey, 19 Madrid Madrid 28023",
    "addr:housenumber":"19",
    "addr:postcode":"madrid;28023",
    "addr:street":"Calle De Fuente Del Rey",
    "iso:country":"ES",
    "sg:address":"Calle de Fuente Del Rey, 19",
    "sg:city":"Madrid",
    "sg:orig_category":"Estancos",
    "sg:phone":"+34 913 07 15 10",
    "sg:postcode":"28023",
    "sg:province":"Madrid",
    "wof:name":"Regojo Otero Concepcion",
    "wof:placetype":"venue"
},
  "geometry": {"coordinates":[-3.7735130787,40.4567298889],"type":"Point"}
}