{
  "type": "Feature",
  "properties": {
    "addr:full":"Psaj Gutierrez Ortega, 3 Ciudad Real Ciudad Real 13001",
    "addr:postcode":"13001",
    "addr:street":"Ortega 3",
    "iso:country":"ES",
    "sg:address":"Psaj Gutierrez Ortega, 3",
    "sg:city":"Ciudad Real",
    "sg:orig_category":"Ropa Para Se\u00d1oras (al Por Menor)",
    "sg:phone":"+34 926 21 18 01",
    "sg:postcode":"13001",
    "sg:province":"Ciudad Real",
    "wof:name":"Espinosa Aparicio Eva",
    "wof:placetype":"venue"
},
  "geometry": {"coordinates":[-3.9291770458,38.9830741882],"type":"Point"}
}