{
  "type": "Feature",
  "properties": {
    "iso:country":"ES",
    "sg:address":"Calle de Gavilanes (blq), 19",
    "sg:city":"Madrid",
    "sg:orig_category":"Reposter\u00cdas",
    "sg:phone":"+34 913 88 34 72",
    "sg:postcode":"28043",
    "sg:province":"Madrid",
    "wof:name":"De La Fuente Fernandez Mercedes",
    "wof:placetype":"venue"
},
  "geometry": {"coordinates":[-3.7416288853,40.4796333313],"type":"Point"}
}