{
  "type": "Feature",
  "properties": {
    "iso:country":"ES",
    "sg:address":"Carrer de Peru, 234",
    "sg:city":"Barcelona",
    "sg:orig_category":"Contenedores (mercanc\u00cdas)",
    "sg:phone":"+34 933 08 80 62",
    "sg:postcode":"08020",
    "sg:province":"Barcelona",
    "wof:name":"Empresas Ramoneda S. A.",
    "wof:placetype":"venue"
},
  "geometry": {"coordinates":[2.2043728828,41.4145698547],"type":"Point"}
}