{
  "type": "Feature",
  "properties": {
    "iso:country":"ES",
    "sg:address":"Calle de Lapuyade, 6",
    "sg:city":"Zaragoza",
    "sg:orig_category":"Frutas, Legumbres Frescas Y Tempranas (al Por Menor)",
    "sg:phone":"+34 976 25 92 73",
    "sg:postcode":"50007",
    "sg:province":"Zaragoza",
    "wof:name":"Frecere S.l.l.",
    "wof:placetype":"venue"
},
  "geometry": {"coordinates":[-0.8842660189,41.6361122131],"type":"Point"}
}