{
  "type": "Feature",
  "properties": {
    "iso:country":"ES",
    "sg:address":"Calle de Poza Licenciado, 8",
    "sg:city":"Bilbao",
    "sg:orig_category":"Abogados",
    "sg:phone":"+34 944 43 21 49",
    "sg:postcode":"48008",
    "sg:province":"Vizcaya",
    "wof:name":"Ramon Varela Aldazabal",
    "wof:placetype":"venue"
},
  "geometry": {"coordinates":[-2.9346339703,43.2608718872],"type":"Point"}
}