{
  "type": "Feature",
  "properties": {
    "addr:full":"Calle de Arrecife, 5 Otura Granada 18630",
    "addr:housenumber":"5",
    "addr:postcode":"18630",
    "addr:street":"Calle De Arrecife",
    "iso:country":"ES",
    "sg:address":"Calle de Arrecife, 5",
    "sg:city":"Otura",
    "sg:orig_category":"Alumbrados",
    "sg:phone":"+34 958 55 60 48",
    "sg:postcode":"18630",
    "sg:province":"Granada",
    "wof:name":"Producciones Audiovisuales Granada S.l.",
    "wof:placetype":"venue"
},
  "geometry": {"coordinates":[-3.6365339756,37.0947494507],"type":"Point"}
}