{
  "type": "Feature",
  "properties": {
    "iso:country":"ES",
    "sg:address":"Calle de Arguelles, 40",
    "sg:city":"Jerez De La Frontera",
    "sg:orig_category":"Aparatos, Sistemas De Tele",
    "sg:phone":"+34 956 33 49 46",
    "sg:postcode":"11401",
    "sg:province":"C\u00e1diz",
    "wof:name":"Segury Control S.a.",
    "wof:placetype":"venue"
},
  "geometry": {"coordinates":[-6.125538826,36.6772613525],"type":"Point"}
}