{
  "type": "Feature",
  "properties": {
    "iso:country":"ES",
    "sg:address":"Calle de Zaida, 8",
    "sg:city":"Madrid",
    "sg:orig_category":"Servicios De Telecomunicaciones",
    "sg:phone":"+34 914 71 91 37",
    "sg:postcode":"28019",
    "sg:province":"Madrid",
    "wof:name":"Mel Comunicaciones S.l.",
    "wof:placetype":"venue"
},
  "geometry": {"coordinates":[-3.7340710163,40.3980751038],"type":"Point"}
}