{
  "type": "Feature",
  "properties": {
    "iso:country":"ES",
    "sg:address":"Carrer de Olzinelles, 70",
    "sg:city":"Barcelona",
    "sg:orig_category":"Carnicer\u00cdas, Carnicer\u00cdas",
    "sg:phone":"+34 933 32 05 92",
    "sg:postcode":"08014",
    "sg:province":"Barcelona",
    "wof:name":"Vila Pujolar Jose",
    "wof:placetype":"venue"
},
  "geometry": {"coordinates":[2.1368780136,41.3717765808],"type":"Point"}
}