{
  "type": "Feature",
  "properties": {
    "addr:full":"Carr Germa Arnald Ciril.li, 5 Mollerussa Lleida 25230",
    "addr:housenumber":"5",
    "addr:postcode":"25230",
    "addr:street":"Carr Germa;Ciril.Li",
    "iso:country":"ES",
    "sg:address":"Carr Germa Arnald Ciril.li, 5",
    "sg:city":"Mollerussa",
    "sg:orig_category":"Negocio De Materiales De Construcci\u00d3n",
    "sg:phone":"+34 973 60 12 14",
    "sg:postcode":"25230",
    "sg:province":"Lleida",
    "wof:name":"Jaume Raventos Jardi I Maria Consol Roura Carreras Cdad.",
    "wof:placetype":"venue"
},
  "geometry": {"coordinates":[0.8879119754,41.6303977966],"type":"Point"}
}