{
  "type": "Feature",
  "properties": {
    "addr:full":"Rond Fonti\u00d1as (das), 115 Lugo Lugo 27002",
    "addr:housenumber":"115",
    "addr:postcode":"27002",
    "iso:country":"ES",
    "sg:address":"Rond Fonti\u00d1as (das), 115",
    "sg:city":"Lugo",
    "sg:orig_category":"Empresarios",
    "sg:phone":"+34 982 28 03 61",
    "sg:postcode":"27002",
    "sg:province":"Lugo",
    "wof:name":"Reformas Lugo Sl",
    "wof:placetype":"venue"
},
  "geometry": {"coordinates":[-7.5480828285,43.0089645386],"type":"Point"}
}