{
  "type": "Feature",
  "properties": {
    "addr:full":"Av Diagonal, 367 Barcelona Barcelona 08037",
    "addr:housenumber":"367",
    "addr:postcode":"08037",
    "addr:street":"Av Diagonal",
    "iso:country":"ES",
    "sg:address":"Av Diagonal, 367",
    "sg:city":"Barcelona",
    "sg:orig_category":"Arquitectos",
    "sg:phone":"+34 932 15 82 49",
    "sg:postcode":"08037",
    "sg:province":"Barcelona",
    "wof:name":"Gomez Rahola Agustin",
    "wof:placetype":"venue"
},
  "geometry": {"coordinates":[2.1627130508,41.397026062],"type":"Point"}
}