{
  "type": "Feature",
  "properties": {
    "iso:country":"ES",
    "sg:address":"Grup Edificio Paraiso, 1",
    "sg:city":"Sevilla",
    "sg:orig_category":"Asesor\u00cdas En Comunicaci\u00d3n",
    "sg:phone":"+34 954 40 15 68",
    "sg:postcode":"41020",
    "sg:province":"Sevilla",
    "wof:name":"Asensio Nu\u00f1ez Pedro Miguel",
    "wof:placetype":"venue"
},
  "geometry": {"coordinates":[-5.9356870651,37.4206848145],"type":"Point"}
}