{
  "type": "Feature",
  "properties": {
    "addr:full":"Calle de Escorial, 1 Almoradi Alicante 03160",
    "addr:housenumber":"1",
    "addr:postcode":"03160",
    "addr:street":"Calle De Escorial",
    "iso:country":"ES",
    "sg:address":"Calle de Escorial, 1",
    "sg:city":"Almoradi",
    "sg:orig_category":"Art\u00cdculos Funerarios (al Por Menor)",
    "sg:phone":"+34 965 70 05 01",
    "sg:postcode":"03160",
    "sg:province":"Alicante",
    "wof:name":"Senerio Morales Jose",
    "wof:placetype":"venue"
},
  "geometry": {"coordinates":[-0.7897430062,38.1077690125],"type":"Point"}
}