{
  "type": "Feature",
  "properties": {
    "iso:country":"ES",
    "sg:address":"Calle de Generalisimo, S/n",
    "sg:city":"Vecilla De Curue\u00e7o",
    "sg:orig_category":"Centros De Educaci\u00d3n Especial",
    "sg:phone":"+34 987 74 11 38",
    "sg:postcode":"24840",
    "sg:province":"Le\u00f3n",
    "wof:name":"Colegio Publico Santo Tirso",
    "wof:placetype":"venue"
},
  "geometry": {"coordinates":[-5.4101839066,42.8550491333],"type":"Point"}
}