{
  "type": "Feature",
  "properties": {
    "addr:full":"Av Santa Coloma, 3 Casc Antic Barcelona 08690",
    "addr:housenumber":"3",
    "addr:postcode":"08690",
    "addr:street":"Av Santa Coloma",
    "iso:country":"ES",
    "sg:address":"Av Santa Coloma, 3",
    "sg:city":"Casc Antic",
    "sg:orig_category":"Reparaciones Y Remolcado De Veh\u00cdculos",
    "sg:phone":"+34 936 34 17 75",
    "sg:postcode":"08690",
    "sg:province":"Barcelona",
    "wof:name":"Ordo\u00f1ez Cradigales Carlos",
    "wof:placetype":"venue"
},
  "geometry": {"coordinates":[2.0196180344,41.3680763245],"type":"Point"}
}