{
  "type": "Feature",
  "properties": {
    "iso:country":"ES",
    "sg:address":"Calle de Miraflores (de), 2",
    "sg:city":"Alcobendas",
    "sg:orig_category":"Confecci\u00d3n (fabricaci\u00d3n, Al Por Mayor)",
    "sg:phone":"+34 916 52 52 85",
    "sg:postcode":"28100",
    "sg:province":"Madrid",
    "wof:name":"Esteban Gutierrez Enrique",
    "wof:placetype":"venue"
},
  "geometry": {"coordinates":[-3.6375238895,40.5433883667],"type":"Point"}
}