{
  "type": "Feature",
  "properties": {
    "addr:full":"Calle de Padre Damian, 42 Madrid Madrid 28036",
    "addr:housenumber":"42",
    "addr:postcode":"madrid;28036",
    "addr:street":"Calle De Padre Damian",
    "iso:country":"ES",
    "sg:address":"Calle de Padre Damian, 42",
    "sg:city":"Madrid",
    "sg:orig_category":"Bancos",
    "sg:phone":"+34 913 53 11 60",
    "sg:postcode":"28036",
    "sg:province":"Madrid",
    "sg:website":"www.ebankinter.com",
    "wof:name":"Bankinter S.a.",
    "wof:placetype":"venue"
},
  "geometry": {"coordinates":[-3.6853280067,40.4593582153],"type":"Point"}
}