{
  "type": "Feature",
  "properties": {
    "iso:country":"ES",
    "sg:address":"Calle de San Vicente, 27",
    "sg:city":"Talavera Reina",
    "sg:orig_category":"Mec\u00c1nico Del Autom\u00d3vil",
    "sg:phone":"+34 925 80 54 29",
    "sg:postcode":"45600",
    "sg:province":"Toledo",
    "wof:name":"Martinez Fernandez Julian",
    "wof:placetype":"venue"
},
  "geometry": {"coordinates":[-4.829767704,39.9656105042],"type":"Point"}
}