{
  "type": "Feature",
  "properties": {
    "iso:country":"ES",
    "sg:address":"Calle de Dulce Jesus, 75",
    "sg:city":"Andujar",
    "sg:orig_category":"Supermercados Y Hipermercados",
    "sg:phone":"+34 953 50 12 80",
    "sg:postcode":"23740",
    "sg:province":"Ja\u00e9n",
    "wof:name":"Porras Cazalilla Pedro",
    "wof:placetype":"venue"
},
  "geometry": {"coordinates":[-4.0483641624,38.0439872742],"type":"Point"}
}