{
  "type": "Feature",
  "properties": {
    "iso:country":"ES",
    "sg:address":"Carrer de Gran De Gracia, 162",
    "sg:city":"Barcelona",
    "sg:orig_category":"Alimentaci\u00d3n General (al Por Menor)",
    "sg:phone":"+34 932 18 38 56",
    "sg:postcode":"08012",
    "sg:province":"Barcelona",
    "wof:name":"Belda Corominas Raul",
    "wof:placetype":"venue"
},
  "geometry": {"coordinates":[2.1529259682,41.4023742676],"type":"Point"}
}