{
  "type": "Feature",
  "properties": {
    "iso:country":"ES",
    "sg:address":"Urb Punta Prima, S/n",
    "sg:city":"Punta Prima",
    "sg:orig_category":"M\u00c9dicos: Reumatolog\u00cda",
    "sg:phone":"+34 965 32 90 52",
    "sg:postcode":"03189",
    "sg:province":"Alicante",
    "wof:name":"Pe\u00f1a Gonzalez Alvaro",
    "wof:placetype":"venue"
},
  "geometry": {"coordinates":[-0.706938982,37.945526123],"type":"Point"}
}