{
  "type": "Feature",
  "properties": {
    "iso:country":"ES",
    "sg:address":"Calle de Nordica, S/n",
    "sg:city":"Cristianos",
    "sg:orig_category":"Inmobiliaria (agencias)",
    "sg:phone":"+34 922 75 71 62",
    "sg:postcode":"38650",
    "sg:province":"Santa Cruz De Tenerife",
    "sg:website":"www.tenerife-itc.com",
    "wof:name":"Tenerife Independent Property Consultants S.l.",
    "wof:placetype":"venue"
},
  "geometry": {"coordinates":[-16.7253189087,28.0541992188],"type":"Point"}
}