{
  "type": "Feature",
  "properties": {
    "addr:full":"Calle de Isla Cerde\u00d1a, 16 Puerto Valencia 46520",
    "addr:housenumber":"16",
    "addr:postcode":"46520",
    "addr:street":"Calle De Isla Cerden\u0303A",
    "iso:country":"ES",
    "sg:address":"Calle de Isla Cerde\u00d1a, 16",
    "sg:city":"Puerto",
    "sg:orig_category":"Agencias Y Agentes Comerciales, Representantes",
    "sg:phone":"+34 962 67 66 72",
    "sg:postcode":"46520",
    "sg:province":"Valencia",
    "wof:name":"Martinez Gutierrez Maria Luisa",
    "wof:placetype":"venue"
},
  "geometry": {"coordinates":[-0.2025949955,39.7040786743],"type":"Point"}
}