{
  "type": "Feature",
  "properties": {
    "addr:full":"Rua Pintor Laxeiro, 3 Vigo Pontevedra 36211",
    "addr:housenumber":"3",
    "addr:postcode":"36211",
    "addr:street":"Rua Pintor Laxeiro",
    "iso:country":"ES",
    "sg:address":"Rua Pintor Laxeiro, 3",
    "sg:city":"Vigo",
    "sg:orig_category":"Bisuter\u00cda, Joyer\u00cda, Relojer\u00cda (al Por Menor)",
    "sg:phone":"+34 986 29 86 66",
    "sg:postcode":"36211",
    "sg:province":"Pontevedra",
    "wof:name":"Prieto Tellado Guadalupe",
    "wof:placetype":"venue"
},
  "geometry": {"coordinates":[-8.7294626236,42.2223167419],"type":"Point"}
}