{
  "type": "Feature",
  "properties": {
    "addr:full":"Plaz Constitucion, 7 Pe\u00e7aranda De Bracamonte Salamanca 37300",
    "addr:housenumber":"7",
    "addr:postcode":"37300",
    "addr:street":"Constitucion",
    "iso:country":"ES",
    "sg:address":"Plaz Constitucion, 7",
    "sg:city":"Pe\u00e7aranda De Bracamonte",
    "sg:orig_category":"Bancos",
    "sg:phone":"+34 923 54 03 50",
    "sg:postcode":"37300",
    "sg:province":"Salamanca",
    "wof:name":"Banco De Castilla",
    "wof:placetype":"venue"
},
  "geometry": {"coordinates":[-5.2017068863,40.9006233215],"type":"Point"}
}