{
  "type": "Feature",
  "properties": {
    "addr:full":"Calle de Moncasi, 4 Zaragoza Zaragoza 50006",
    "addr:housenumber":"4",
    "addr:postcode":"50006",
    "addr:street":"Calle De Moncasi",
    "iso:country":"ES",
    "sg:address":"Calle de Moncasi, 4",
    "sg:city":"Zaragoza",
    "sg:orig_category":"Empresarios",
    "sg:phone":"+34 976 37 22 08",
    "sg:postcode":"50006",
    "sg:province":"Zaragoza",
    "wof:name":"Fundacion Gaspar Torrente",
    "wof:placetype":"venue"
},
  "geometry": {"coordinates":[-0.8865990043,41.6413993835],"type":"Point"}
}