{
  "type": "Feature",
  "properties": {
    "addr:full":"Calle de Romero De Torres, 14 Jerez De La Frontera C\u00e1diz 11405",
    "addr:housenumber":"14",
    "addr:postcode":"11405",
    "addr:street":"Calle De Romero De Torres",
    "iso:country":"ES",
    "sg:address":"Calle de Romero De Torres, 14",
    "sg:city":"Jerez De La Frontera",
    "sg:orig_category":"Estancos",
    "sg:phone":"+34 956 31 15 40",
    "sg:postcode":"11405",
    "sg:province":"C\u00e1diz",
    "wof:name":"Romero Berruti Francisco",
    "wof:placetype":"venue"
},
  "geometry": {"coordinates":[-6.0975518227,36.6978263855],"type":"Point"}
}