{
  "type": "Feature",
  "properties": {
    "iso:country":"ES",
    "sg:address":"Plaz Socorro (del), 3",
    "sg:city":"Cordoba",
    "sg:orig_category":"Ropa Para Se\u00d1oras Y Caballeros (al Por Menor)",
    "sg:phone":"+34 957 47 77 45",
    "sg:postcode":"14002",
    "sg:province":"C\u00f3rdoba",
    "wof:name":"Gutierrez Casares Jose Maria",
    "wof:placetype":"venue"
},
  "geometry": {"coordinates":[-4.7732658386,37.883266449],"type":"Point"}
}