{
  "type": "Feature",
  "properties": {
    "iso:country":"ES",
    "sg:address":"Calle de Ayuntamiento, S/n",
    "sg:city":"Mondariz",
    "sg:orig_category":"Abogados",
    "sg:phone":"+34 986 65 61 83",
    "sg:postcode":"36870",
    "sg:province":"Pontevedra",
    "wof:name":"Xunta De Galicia",
    "wof:placetype":"venue"
},
  "geometry": {"coordinates":[-8.4578638077,42.2318840027],"type":"Point"}
}