{
  "type": "Feature",
  "properties": {
    "addr:full":"Av Madrid, 72 Barcelona Barcelona 08028",
    "addr:housenumber":"72",
    "addr:postcode":"08028",
    "addr:street":"Av Madrid",
    "iso:country":"ES",
    "sg:address":"Av Madrid, 72",
    "sg:city":"Barcelona",
    "sg:orig_category":"Supermercados Y Hipermercados",
    "sg:phone":"+34 933 30 02 62",
    "sg:postcode":"08028",
    "sg:province":"Barcelona",
    "wof:name":"Cs Establiments De Proximitat S.l.",
    "wof:placetype":"venue"
},
  "geometry": {"coordinates":[2.126760006,41.377910614],"type":"Point"}
}