{
  "type": "Feature",
  "properties": {
    "addr:full":"Plaz Diego Velazquez, 2 Zaragoza Zaragoza 50006",
    "addr:housenumber":"2",
    "addr:postcode":"50006",
    "addr:street":"Plaz Diego Velazquez",
    "iso:country":"ES",
    "sg:address":"Plaz Diego Velazquez, 2",
    "sg:city":"Zaragoza",
    "sg:orig_category":"Psic\u00d3logos",
    "sg:phone":"+34 976 25 61 00",
    "sg:postcode":"50006",
    "sg:province":"Zaragoza",
    "wof:name":"Blazquez Ferrero Maria Reyes",
    "wof:placetype":"venue"
},
  "geometry": {"coordinates":[-0.8864349723,41.6383666992],"type":"Point"}
}