{
  "type": "Feature",
  "properties": {
    "addr:full":"Avda Cardenal Cisneros, 26 Zamora Zamora 49030",
    "addr:housenumber":"26",
    "addr:postcode":"49030",
    "addr:street":"Avda Cardenal Cisneros",
    "iso:country":"ES",
    "sg:address":"Avda Cardenal Cisneros, 26",
    "sg:city":"Zamora",
    "sg:orig_category":"Discapacitados",
    "sg:phone":"+34 980 67 12 04",
    "sg:postcode":"49030",
    "sg:province":"Zamora",
    "wof:name":"Asociacion Esclerosis Multiple De Zamora",
    "wof:placetype":"venue"
},
  "geometry": {"coordinates":[-5.7350082397,41.50989151],"type":"Point"}
}