{
  "type": "Feature",
  "properties": {
    "iso:country":"ES",
    "sg:address":"Calle de Nicolau Primitiu Gomez Serrano, 3",
    "sg:city":"Valencia",
    "sg:orig_category":"Adaptaciones, Acondicionamientos Especiales Para Veh\u00cdculos, Veh\u00cdculos Industriales",
    "sg:phone":"+34 963 78 36 74",
    "sg:postcode":"46014",
    "sg:province":"Valencia",
    "wof:name":"Zapater Lope Manuel",
    "wof:placetype":"venue"
},
  "geometry": {"coordinates":[-0.4031670094,39.4567184448],"type":"Point"}
}