{
  "type": "Feature",
  "properties": {
    "addr:full":"Calle de Domingo Martinez, 21 Valladolid Valladolid 47007",
    "addr:housenumber":"21",
    "addr:postcode":"47007",
    "addr:street":"Calle De Domingo Martinez",
    "iso:country":"ES",
    "sg:address":"Calle de Domingo Martinez, 21",
    "sg:city":"Valladolid",
    "sg:orig_category":"Reposter\u00cdas",
    "sg:phone":"+34 983 27 07 43",
    "sg:postcode":"47007",
    "sg:province":"Valladolid",
    "wof:name":"Fabricacion Y Distribucion De Pan S.l.",
    "wof:placetype":"venue"
},
  "geometry": {"coordinates":[-4.7355723381,41.6384658813],"type":"Point"}
}