{
  "type": "Feature",
  "properties": {
    "iso:country":"ES",
    "sg:address":"Calle de Antonio Ubieto, 8",
    "sg:city":"Zaragoza",
    "sg:orig_category":"Restaurantes",
    "sg:phone":"+34 976 52 96 05",
    "sg:postcode":"50015",
    "sg:province":"Zaragoza",
    "wof:name":"Restaurante El Refugio Sociedad Civil",
    "wof:placetype":"venue"
},
  "geometry": {"coordinates":[-0.8714429736,41.6782226562],"type":"Point"}
}