{
  "type": "Feature",
  "properties": {
    "iso:country":"ES",
    "sg:address":"Cami Lleida, S/n",
    "sg:city":"Alcoletge",
    "sg:orig_category":"Empresas De Carpinter\u00cda Met\u00c1lica",
    "sg:phone":"+34 973 19 71 58",
    "sg:postcode":"25660",
    "sg:province":"Lleida",
    "wof:name":"El Frisegre S.l.",
    "wof:placetype":"venue"
},
  "geometry": {"coordinates":[0.6822119951,41.645198822],"type":"Point"}
}