{
  "type": "Feature",
  "properties": {
    "addr:full":"Trva Jose Antonio Iii, 3 Laredo Cantabria 39770",
    "addr:housenumber":"3",
    "addr:postcode":"39770",
    "addr:street":"Trva Jose Antonio Iii",
    "iso:country":"ES",
    "sg:address":"Trva Jose Antonio Iii, 3",
    "sg:city":"Laredo",
    "sg:orig_category":"Peluquer\u00cdas, Peluquer\u00cda Mixta",
    "sg:phone":"+34 942 61 19 75",
    "sg:postcode":"39770",
    "sg:province":"Cantabria",
    "wof:name":"Tabernilla Fuente Maria",
    "wof:placetype":"venue"
},
  "geometry": {"coordinates":[-3.4155740738,43.4093132019],"type":"Point"}
}