{
  "type": "Feature",
  "properties": {
    "iso:country":"ES",
    "sg:address":"Calle de Santo Domingo, 61",
    "sg:city":"Badajoz",
    "sg:orig_category":"Panader\u00cdas, Panader\u00cdas",
    "sg:phone":"+34 924 22 33 18",
    "sg:postcode":"06001",
    "sg:province":"Badajoz",
    "wof:name":"Arg\u00fcelles Morgado Jose",
    "wof:placetype":"venue"
},
  "geometry": {"coordinates":[-6.974758625,38.8778419495],"type":"Point"}
}