{
  "type": "Feature",
  "properties": {
    "iso:country":"ES",
    "sg:address":"Rua Humboldt, 2",
    "sg:city":"Perillo",
    "sg:orig_category":"Discotecas Y Salas De Baile",
    "sg:phone":"+34 981 63 84 20",
    "sg:postcode":"15172",
    "sg:province":"La Coru\u00f1a",
    "wof:name":"Golden Fish S.l.",
    "wof:placetype":"venue"
},
  "geometry": {"coordinates":[-8.3761663437,43.3380622864],"type":"Point"}
}