{
  "type": "Feature",
  "properties": {
    "iso:country":"ES",
    "sg:address":"Rua Manuel Rodriguez, 110",
    "sg:city":"Porri\u00f1o",
    "sg:orig_category":"Alimentaci\u00d3n General (al Por Menor)",
    "sg:phone":"+34 986 33 57 24",
    "sg:postcode":"36400",
    "sg:province":"Pontevedra",
    "wof:name":"Rodriguez Martinez Oscar",
    "wof:placetype":"venue"
},
  "geometry": {"coordinates":[-8.6205568314,42.1558570862],"type":"Point"}
}