{
  "type": "Feature",
  "properties": {
    "addr:full":"Carr Jaume Ii, 9 Lleida Lleida 25001",
    "addr:housenumber":"9",
    "addr:postcode":"25001",
    "addr:street":"Carr Jaume Ii",
    "iso:country":"ES",
    "sg:address":"Carr Jaume Ii, 9",
    "sg:city":"Lleida",
    "sg:orig_category":"Arquitectos",
    "sg:phone":"+34 973 21 20 64",
    "sg:postcode":"25001",
    "sg:province":"Lleida",
    "wof:name":"Trifori Arquitectes S.l.",
    "wof:placetype":"venue"
},
  "geometry": {"coordinates":[0.6286219954,41.6130371094],"type":"Point"}
}