{
  "type": "Feature",
  "properties": {
    "iso:country":"ES",
    "sg:address":"Avda Andalucia (de), 77",
    "sg:city":"Estepa",
    "sg:orig_category":"Agencias De Viajes",
    "sg:phone":"+34 955 91 43 44",
    "sg:postcode":"41560",
    "sg:province":"Sevilla",
    "wof:name":"Viajes Ostippo S.l.",
    "wof:placetype":"venue"
},
  "geometry": {"coordinates":[-4.8813381195,37.2940101624],"type":"Point"}
}