{
  "type": "Feature",
  "properties": {
    "iso:country":"ES",
    "sg:address":"Carrer de Roger De Flor, S/n",
    "sg:city":"Granollers",
    "sg:orig_category":"Asociaciones Y Clubs Deportivos",
    "sg:phone":"+34 938 70 25 50",
    "sg:postcode":"08401",
    "sg:province":"Barcelona",
    "wof:name":"Club Natacion Granollers",
    "wof:placetype":"venue"
},
  "geometry": {"coordinates":[2.282875061,41.6029205322],"type":"Point"}
}