{
  "type": "Feature",
  "properties": {
    "addr:full":"Bo Echano, 18 Etxano Vizcaya 48340",
    "addr:housenumber":"18",
    "addr:postcode":"48340",
    "addr:street":"Echano",
    "iso:country":"ES",
    "sg:address":"Bo Echano, 18",
    "sg:city":"Etxano",
    "sg:orig_category":"Empresas De Pintura Y Revestimientos",
    "sg:phone":"+34 946 30 87 23",
    "sg:postcode":"48340",
    "sg:province":"Vizcaya",
    "wof:name":"Calles Trevi\u00f1o Felipe Ignacio",
    "wof:placetype":"venue"
},
  "geometry": {"coordinates":[-2.7321588993,43.2210960388],"type":"Point"}
}