{
  "type": "Feature",
  "properties": {
    "iso:country":"ES",
    "sg:address":"Calle de Santiago, 20",
    "sg:city":"San Vicente Del Raspeig-sant Vicent Del Raspeig",
    "sg:orig_category":"Equipo De Refrigeraci\u00d3n Industrial",
    "sg:phone":"+34 965 66 66 69",
    "sg:postcode":"03690",
    "sg:province":"Alicante",
    "wof:name":"Fagor Industrial S. Coop.",
    "wof:placetype":"venue"
},
  "geometry": {"coordinates":[-0.5186399817,38.397403717],"type":"Point"}
}