{
  "type": "Feature",
  "properties": {
    "iso:country":"ES",
    "sg:address":"Calle de Tierno Galvan, 9",
    "sg:city":"Cartagena",
    "sg:orig_category":"Pintura Industrial (trabajos De)",
    "sg:phone":"+34 968 52 05 62",
    "sg:postcode":"30201",
    "sg:province":"Murcia",
    "wof:name":"Apisureste S.l.",
    "wof:placetype":"venue"
},
  "geometry": {"coordinates":[-0.9830979705,37.6054954529],"type":"Point"}
}