{
  "type": "Feature",
  "properties": {
    "addr:full":"Avda Aragon, 5 Sang\u00fcesa Navarra 31400",
    "addr:housenumber":"5",
    "addr:postcode":"31400",
    "addr:street":"Avda Aragon",
    "iso:country":"ES",
    "sg:address":"Avda Aragon, 5",
    "sg:city":"Sang\u00fcesa",
    "sg:orig_category":"Mec\u00c1nico Del Autom\u00d3vil",
    "sg:phone":"+34 948 87 04 55",
    "sg:postcode":"31400",
    "sg:province":"Navarra",
    "wof:name":"Arbea Iba\u00f1ez Miguel Carlos",
    "wof:placetype":"venue"
},
  "geometry": {"coordinates":[-1.2807866335,42.5753936768],"type":"Point"}
}