{
  "type": "Feature",
  "properties": {
    "iso:country":"ES",
    "sg:address":"Carr Enric Granados, 9",
    "sg:city":"Albatarrec",
    "sg:orig_category":"Empresas De Impermeabilizaci\u00d3n",
    "sg:phone":"+34 973 72 07 63",
    "sg:postcode":"25171",
    "sg:province":"Lleida",
    "wof:name":"Hidrobalses S.l.",
    "wof:placetype":"venue"
},
  "geometry": {"coordinates":[0.6053900123,41.5725288391],"type":"Point"}
}