{
  "type": "Feature",
  "properties": {
    "addr:full":"Rond Mu\u00d1oces (de Los), 37 Pozoblanco C\u00f3rdoba 14400",
    "addr:postcode":"14400",
    "addr:street":"Co\u0301Rdoba",
    "iso:country":"ES",
    "sg:address":"Rond Mu\u00d1oces (de Los), 37",
    "sg:city":"Pozoblanco",
    "sg:orig_category":"Ense\u00d1anza, Formaci\u00d3n Profesional: Aprendizaje",
    "sg:phone":"+34 957 77 06 66",
    "sg:postcode":"14400",
    "sg:province":"C\u00f3rdoba",
    "wof:name":"Servicio Andaluz De Empleo",
    "wof:placetype":"venue"
},
  "geometry": {"coordinates":[-4.8492288589,38.3810462952],"type":"Point"}
}