{
  "type": "Feature",
  "properties": {
    "iso:country":"ES",
    "sg:address":"Carrer de Bisbe Torras I Bages, 5",
    "sg:city":"Vic",
    "sg:orig_category":"Venta, Instalaci\u00d3n, Mantenimiento De Chimeneas De Interior Y Accesorios",
    "sg:phone":"+34 938 89 07 90",
    "sg:postcode":"08500",
    "sg:province":"Barcelona",
    "wof:name":"Artdefoc Instal-ladors S.l.",
    "wof:placetype":"venue"
},
  "geometry": {"coordinates":[2.2531929016,41.9273757935],"type":"Point"}
}