{
  "type": "Feature",
  "properties": {
    "iso:country":"ES",
    "sg:address":"Calle de Calvo Sotelo, 49",
    "sg:city":"Santa Brigida",
    "sg:orig_category":"Comercio, Reparaci\u00d3n De Motocicletas, Bicicletas Y Piezas Sueltas",
    "sg:phone":"+34 928 64 22 07",
    "sg:postcode":"35300",
    "sg:province":"Las Palmas",
    "wof:name":"Benitez Rodriguez Juan Ignacio",
    "wof:placetype":"venue"
},
  "geometry": {"coordinates":[-15.4986619949,28.0326347351],"type":"Point"}
}