{
  "type": "Feature",
  "properties": {
    "addr:full":"Calle de Benito Perez Galdos, 84 Cadiz C\u00e1diz 11002",
    "addr:housenumber":"84",
    "addr:postcode":"11002",
    "addr:street":"Calle De Benito Perez Galdos",
    "iso:country":"ES",
    "sg:address":"Calle de Benito Perez Galdos, 84",
    "sg:city":"Cadiz",
    "sg:orig_category":"Alimentaci\u00d3n General (al Por Menor)",
    "sg:phone":"+34 956 22 93 62",
    "sg:postcode":"11002",
    "sg:province":"C\u00e1diz",
    "wof:name":"Olvera Bautista Maria",
    "wof:placetype":"venue"
},
  "geometry": {"coordinates":[-6.3034105301,36.533618927],"type":"Point"}
}