{
  "type": "Feature",
  "properties": {
    "addr:full":"Carr Riu Cervol (del), 12 Manises Valencia 46940",
    "addr:housenumber":"12",
    "addr:postcode":"46940",
    "addr:street":"Carr Riu Cervol Del",
    "iso:country":"ES",
    "sg:address":"Carr Riu Cervol (del), 12",
    "sg:city":"Manises",
    "sg:orig_category":"Escultores, Estatuarios E Imagineros",
    "sg:phone":"+34 961 52 07 37",
    "sg:postcode":"46940",
    "sg:province":"Valencia",
    "wof:name":"Herraiz Moreno Casimiro",
    "wof:placetype":"venue"
},
  "geometry": {"coordinates":[-0.4496214092,39.4879570007],"type":"Point"}
}