{
  "type": "Feature",
  "properties": {
    "addr:full":"Urb Almendros (los), 71 Almendros Las Palmas 35217",
    "addr:housenumber":"71",
    "addr:postcode":"35217",
    "addr:street":"Urb Almendros Los",
    "iso:country":"ES",
    "sg:address":"Urb Almendros (los), 71",
    "sg:city":"Almendros",
    "sg:orig_category":"Asesor\u00cda Sobre Comunicaci\u00d3n De Empresas",
    "sg:phone":"+34 928 70 58 03",
    "sg:postcode":"35217",
    "sg:province":"Las Palmas",
    "wof:name":"Pe\u00f1a Lasso Miguel Angel",
    "wof:placetype":"venue"
},
  "geometry": {"coordinates":[-15.4973392487,27.9911899567],"type":"Point"}
}