{
  "type": "Feature",
  "properties": {
    "iso:country":"ES",
    "sg:address":"Caldereria, 19",
    "sg:city":"Iru\u00f1a",
    "sg:orig_category":"Arquitectos",
    "sg:phone":"+34 948 22 40 41",
    "sg:postcode":"31001",
    "sg:province":"Navarra",
    "wof:name":"Irigaray Vidondo Jesus",
    "wof:placetype":"venue"
},
  "geometry": {"coordinates":[-1.6416416168,42.8179931641],"type":"Point"}
}