{
  "type": "Feature",
  "properties": {
    "addr:full":"Calle de Arrasate, 37 Donostia-san Sebastian Guip\u00f9zcoa 20005",
    "addr:housenumber":"37",
    "addr:postcode":"20005",
    "addr:street":"Calle De Arrasate",
    "iso:country":"ES",
    "sg:address":"Calle de Arrasate, 37",
    "sg:city":"Donostia-san Sebastian",
    "sg:orig_category":"Inversiones",
    "sg:phone":"+34 943 44 01 16",
    "sg:postcode":"20005",
    "sg:province":"Guip\u00f9zcoa",
    "sg:website":"www.renta4.es",
    "wof:name":"Renta 4 Guipuzcoa S.a.",
    "wof:placetype":"venue"
},
  "geometry": {"coordinates":[-1.9832502604,43.3176269531],"type":"Point"}
}