{
  "type": "Feature",
  "properties": {
    "iso:country":"ES",
    "sg:address":"Electricidad, 37",
    "sg:city":"Leganes",
    "sg:orig_category":"Protecci\u00d3n Contra Incendios: Material, Instalaci\u00d3n, Mantenimiento",
    "sg:phone":"+34 916 11 96 75",
    "sg:postcode":"28918",
    "sg:province":"Madrid",
    "wof:name":"Amsyspro S.l.",
    "wof:placetype":"venue"
},
  "geometry": {"coordinates":[-3.7984025478,40.3519363403],"type":"Point"}
}