{
  "type": "Feature",
  "properties": {
    "iso:country":"ES",
    "sg:address":"Calle de Maria Cristina, 31",
    "sg:city":"Novelda",
    "sg:orig_category":"Asesor\u00cda Fiscal Y Jur\u00cddica",
    "sg:phone":"+34 965 60 29 64",
    "sg:postcode":"03660",
    "sg:province":"Alicante",
    "wof:name":"Lopez Andres Y Compa\u00f1ia S. R. C.",
    "wof:placetype":"venue"
},
  "geometry": {"coordinates":[-0.7676702142,38.3805084229],"type":"Point"}
}