{
  "type": "Feature",
  "properties": {
    "addr:full":"Av Paisos Catalans, 163 Selva Negra Catalana Barcelona 08759",
    "addr:housenumber":"163",
    "addr:postcode":"08759",
    "addr:street":"Av Paisos Catalans",
    "iso:country":"ES",
    "sg:address":"Av Paisos Catalans, 163",
    "sg:city":"Selva Negra Catalana",
    "sg:orig_category":"Asilos De Ancianos. Centros Privados",
    "sg:phone":"+34 936 83 04 78",
    "sg:postcode":"08759",
    "sg:province":"Barcelona",
    "sg:website":"www.fundacionntrasrafatima.org",
    "wof:name":"Fundacion Nuestra Se\u00d1ora De Fatima",
    "wof:placetype":"venue"
},
  "geometry": {"coordinates":[1.9363410473,41.3764381409],"type":"Point"}
}