{
  "type": "Feature",
  "properties": {
    "addr:full":"Alejandro Rodriguez Valcarcel, 41 Pradoluengo Burgos 09260",
    "addr:housenumber":"41",
    "addr:postcode":"09260",
    "addr:street":"Alejandro;Valcarcel",
    "iso:country":"ES",
    "sg:address":"Alejandro Rodriguez Valcarcel, 41",
    "sg:city":"Pradoluengo",
    "sg:orig_category":"Medias Y Calcetines (fabricaci\u00d3n, Al Por Mayor)",
    "sg:phone":"+34 947 58 66 87",
    "sg:postcode":"09260",
    "sg:province":"Burgos",
    "wof:name":"Burmode S.a.",
    "wof:placetype":"venue"
},
  "geometry": {"coordinates":[-3.1974260807,42.323184967],"type":"Point"}
}