{
  "type": "Feature",
  "properties": {
    "iso:country":"ES",
    "sg:address":"Finca Moriscos, S/n",
    "sg:city":"Carrizal",
    "sg:orig_category":"Industria Qu\u00cdmica",
    "sg:phone":"+34 928 57 46 70",
    "sg:postcode":"35240",
    "sg:province":"Las Palmas",
    "sg:website":"www.weber-cemarksa.es",
    "wof:name":"Saint Gobain Weber Cemarksa S.a.",
    "wof:placetype":"venue"
},
  "geometry": {"coordinates":[-15.4088487625,27.9120388031],"type":"Point"}
}