{
  "type": "Feature",
  "properties": {
    "iso:country":"ES",
    "sg:address":"Carrer de Mar, 17",
    "sg:city":"Barcelona",
    "sg:orig_category":"Bares, Piano",
    "sg:phone":"+34 932 68 81 17",
    "sg:postcode":"08003",
    "sg:province":"Barcelona",
    "wof:name":"Saganhos S.l.",
    "wof:placetype":"venue"
},
  "geometry": {"coordinates":[2.1877191067,41.3807792664],"type":"Point"}
}