{
  "type": "Feature",
  "properties": {
    "addr:full":"Avda Blas Perez Gonzalez, 4 Puerto Cruz Santa Cruz De Tenerife 38400",
    "addr:housenumber":"4",
    "addr:postcode":"38400",
    "addr:street":"Avda Blas Perez Gonzalez;Cruz",
    "iso:country":"ES",
    "sg:address":"Avda Blas Perez Gonzalez, 4",
    "sg:city":"Puerto Cruz",
    "sg:orig_category":"Congelados: Productos Alimentarios (fabricaci\u00d3n, Al Por Mayor)",
    "sg:phone":"+34 922 38 40 02",
    "sg:postcode":"38400",
    "sg:province":"Santa Cruz De Tenerife",
    "wof:name":"Quintero Acosta Pablo",
    "wof:placetype":"venue"
},
  "geometry": {"coordinates":[-16.5536575317,28.4101276398],"type":"Point"}
}