{
  "type": "Feature",
  "properties": {
    "iso:country":"ES",
    "sg:address":"Calle de Pinzones, 6",
    "sg:city":"Salamanca",
    "sg:orig_category":"Copas, Insignias, Trofeos",
    "sg:phone":"+34 923 22 91 06",
    "sg:postcode":"37005",
    "sg:province":"Salamanca",
    "wof:name":"Angel Recio S.l.",
    "wof:placetype":"venue"
},
  "geometry": {"coordinates":[-5.6582942009,40.9717292786],"type":"Point"}
}