{
  "type": "Feature",
  "properties": {
    "addr:full":"Calle de Catalu\u00d1a, 17 Getafe Madrid 28903",
    "addr:housenumber":"17",
    "addr:postcode":"28903",
    "addr:street":"Calle De Catalun\u0303A",
    "iso:country":"ES",
    "sg:address":"Calle de Catalu\u00d1a, 17",
    "sg:city":"Getafe",
    "sg:orig_category":"Carnicer\u00cdas, Carnicer\u00cdas",
    "sg:phone":"+34 916 95 91 87",
    "sg:postcode":"28903",
    "sg:province":"Madrid",
    "wof:name":"Martin Barrios Jose Luis",
    "wof:placetype":"venue"
},
  "geometry": {"coordinates":[-3.7199912071,40.3155937195],"type":"Point"}
}