{
  "type": "Feature",
  "properties": {
    "addr:full":"Calle de San Antonio De Padua, 2 Mogan Las Palmas 35140",
    "addr:housenumber":"2",
    "addr:postcode":"35140",
    "addr:street":"Calle De San Antonio;Padua;Las",
    "iso:country":"ES",
    "sg:address":"Calle de San Antonio De Padua, 2",
    "sg:city":"Mogan",
    "sg:orig_category":"Asociaciones, Organismos Culturales Y Socioeducativos",
    "sg:phone":"+34 928 56 95 39",
    "sg:postcode":"35140",
    "sg:province":"Las Palmas",
    "wof:name":"Club De La Tercera Edad San Antonio",
    "wof:placetype":"venue"
},
  "geometry": {"coordinates":[-15.724612236,27.8838214874],"type":"Point"}
}