{
  "type": "Feature",
  "properties": {
    "addr:full":"Rua Coutadas, 56 Freixeiro Pontevedra 36207",
    "addr:housenumber":"56",
    "addr:postcode":"36207",
    "addr:street":"Rua Coutadas",
    "iso:country":"ES",
    "sg:address":"Rua Coutadas, 56",
    "sg:city":"Freixeiro",
    "sg:orig_category":"Ense\u00d1anza Secundaria: Colegios Y Escuelas Privadas",
    "sg:phone":"+34 986 37 81 81",
    "sg:postcode":"36207",
    "sg:province":"Pontevedra",
    "wof:name":"Instituto De Bacharelato Rosais 2",
    "wof:placetype":"venue"
},
  "geometry": {"coordinates":[-8.6428003311,42.4304618835],"type":"Point"}
}