{
  "type": "Feature",
  "properties": {
    "iso:country":"ES",
    "sg:address":"Calle de San Blas, 4",
    "sg:city":"Fonz",
    "sg:orig_category":"Centros Empresariales",
    "sg:phone":"+34 974 41 20 90",
    "sg:postcode":"22422",
    "sg:province":"Huesca",
    "wof:name":"Garces Bardaji Maria Dolores",
    "wof:placetype":"venue"
},
  "geometry": {"coordinates":[0.2563279867,42.0108947754],"type":"Point"}
}