{
  "type": "Feature",
  "properties": {
    "iso:country":"ES",
    "sg:address":"Calle de Martinez Maldonado, 40",
    "sg:city":"Malaga",
    "sg:orig_category":"Loter\u00cda Y T\u00d3mbola",
    "sg:phone":"+34 952 64 02 46",
    "sg:postcode":"29007",
    "sg:province":"M\u00e1laga",
    "wof:name":"Ponce Ramirez De Aguilera Simon",
    "wof:placetype":"venue"
},
  "geometry": {"coordinates":[-4.4353990555,36.721534729],"type":"Point"}
}