{
  "type": "Feature",
  "properties": {
    "addr:full":"Calle de Mayor, 45 Castronuevo Esgueva Valladolid 47171",
    "addr:housenumber":"45",
    "addr:postcode":"47171",
    "addr:street":"Calle De Mayor",
    "iso:country":"ES",
    "sg:address":"Calle de Mayor, 45",
    "sg:city":"Castronuevo Esgueva",
    "sg:orig_category":"Cr\u00cda De Animales",
    "sg:phone":"+34 983 50 61 70",
    "sg:postcode":"47171",
    "sg:province":"Valladolid",
    "wof:name":"San Jose Perez Carlos Juan",
    "wof:placetype":"venue"
},
  "geometry": {"coordinates":[-4.5891270638,41.6828918457],"type":"Point"}
}