{
  "type": "Feature",
  "properties": {
    "addr:full":"Z Pol Noain-esquiroz, 16 Noain Navarra 31110",
    "addr:housenumber":"16",
    "addr:postcode":"31110",
    "addr:street":"Z;Noain-Esquiroz",
    "iso:country":"ES",
    "sg:address":"Z Pol Noain-esquiroz, 16",
    "sg:city":"Noain",
    "sg:orig_category":"Trabajos De Soldaduras",
    "sg:phone":"+34 948 31 81 15",
    "sg:postcode":"31110",
    "sg:province":"Navarra",
    "wof:name":"Vifesa Soldaduras S.l.l",
    "wof:placetype":"venue"
},
  "geometry": {"coordinates":[-1.6338239908,42.7598800659],"type":"Point"}
}