{
  "type": "Feature",
  "properties": {
    "iso:country":"ES",
    "sg:address":"Calle de Nueva, 9",
    "sg:city":"Villaviciosa Odon",
    "sg:orig_category":"Farmacias",
    "sg:phone":"+34 916 65 73 79",
    "sg:postcode":"28670",
    "sg:province":"Madrid",
    "wof:name":"Maroto Maroto Manuel",
    "wof:placetype":"venue"
},
  "geometry": {"coordinates":[-3.9006910324,40.3578300476],"type":"Point"}
}