{
  "type": "Feature",
  "properties": {
    "iso:country":"ES",
    "sg:address":"Plaz Corredera, 23",
    "sg:city":"Cazorla",
    "sg:orig_category":"Cajas Para Embalar",
    "sg:phone":"+34 953 72 19 08",
    "sg:postcode":"23470",
    "sg:province":"Ja\u00e9n",
    "wof:name":"Caja Rural De Jaen",
    "wof:placetype":"venue"
},
  "geometry": {"coordinates":[-3.0027339458,37.9113121033],"type":"Point"}
}