{
  "type": "Feature",
  "properties": {
    "addr:full":"Cmno Zarza, 6 Almendralejo Badajoz 06200",
    "addr:housenumber":"6",
    "addr:postcode":"06200",
    "addr:street":"Cmno Zarza",
    "iso:country":"ES",
    "sg:address":"Cmno Zarza, 6",
    "sg:city":"Almendralejo",
    "sg:orig_category":"Afilado",
    "sg:phone":"+34 924 66 00 00",
    "sg:postcode":"06200",
    "sg:province":"Badajoz",
    "wof:name":"Hartmann Jimenez Roland",
    "wof:placetype":"venue"
},
  "geometry": {"coordinates":[-6.4068241119,38.6845092773],"type":"Point"}
}