{
  "type": "Feature",
  "properties": {
    "addr:full":"Calle de Colon, 44 Hoyocasero \u00c1vila 05124",
    "addr:housenumber":"44",
    "addr:postcode":"05124",
    "addr:street":"Calle De Colon",
    "iso:country":"ES",
    "sg:address":"Calle de Colon, 44",
    "sg:city":"Hoyocasero",
    "sg:orig_category":"Producci\u00d3n, Distribuci\u00d3n De Gas Butano Y Propano",
    "sg:phone":"+34 920 29 98 59",
    "sg:postcode":"05124",
    "sg:province":"\u00c1vila",
    "wof:name":"Gonzalez Sanchez Javier",
    "wof:placetype":"venue"
},
  "geometry": {"coordinates":[-4.9763503075,40.3999404907],"type":"Point"}
}