{
  "type": "Feature",
  "properties": {
    "iso:country":"ES",
    "sg:address":"Calle de Mateo Sanchez, 5",
    "sg:city":"Montilla",
    "sg:orig_category":"Artes Gr\u00c1ficas, Artes Pl\u00c1sticas (curso)",
    "sg:phone":"+34 957 65 24 02",
    "sg:postcode":"14550",
    "sg:province":"C\u00f3rdoba",
    "wof:name":"Artes Graficas La Montillana S.l.",
    "wof:placetype":"venue"
},
  "geometry": {"coordinates":[-4.6422905922,37.5890350342],"type":"Point"}
}