{
  "type": "Feature",
  "properties": {
    "iso:country":"ES",
    "sg:address":"Calle de Convento, 40",
    "sg:city":"Castilleja Cuesta",
    "sg:orig_category":"Dietistas",
    "sg:phone":"+34 954 16 08 61",
    "sg:postcode":"41950",
    "sg:province":"Sevilla",
    "sg:website":"www.biovidasalud.net",
    "wof:name":"Diez Perales Daniel",
    "wof:placetype":"venue"
},
  "geometry": {"coordinates":[-6.0500869751,37.3869552612],"type":"Point"}
}