{
  "type": "Feature",
  "properties": {
    "addr:full":"Ctra Teruel (de), S/n Molina Guadalajara 19300",
    "addr:postcode":"19300",
    "addr:street":"Ctra Teruel De S / N Molina",
    "iso:country":"ES",
    "sg:address":"Ctra Teruel (de), S/n",
    "sg:city":"Molina",
    "sg:orig_category":"Material Y Herramientas Agr\u00cdcolas",
    "sg:phone":"+34 949 83 07 42",
    "sg:postcode":"19300",
    "sg:province":"Guadalajara",
    "sg:website":"www.quiles-agro.com",
    "wof:name":"Quiles Servicios Empresariales",
    "wof:placetype":"venue"
},
  "geometry": {"coordinates":[-1.8790500164,40.8489608765],"type":"Point"}
}