{
  "type": "Feature",
  "properties": {
    "addr:full":"Calle de Eres, Les, 15 Burriana Castell\u00f3n 12530",
    "addr:housenumber":"15",
    "addr:postcode":"12530",
    "addr:street":"Calle De Eres Les",
    "iso:country":"ES",
    "sg:address":"Calle de Eres, Les, 15",
    "sg:city":"Burriana",
    "sg:orig_category":"Tiendas De Grano, Frutas Y Legumbres Secas (al Por Menor)",
    "sg:phone":"+34 964 51 04 77",
    "sg:postcode":"12530",
    "sg:province":"Castell\u00f3n",
    "wof:name":"Eurotel Sur S.l.",
    "wof:placetype":"venue"
},
  "geometry": {"coordinates":[-0.0860956013,39.8845825195],"type":"Point"}
}