{
  "type": "Feature",
  "properties": {
    "iso:country":"ES",
    "sg:address":"Ctra Plantio, 78",
    "sg:city":"Majadahonda",
    "sg:orig_category":"Abogados",
    "sg:phone":"+34 913 07 61 05",
    "sg:postcode":"28220",
    "sg:province":"Madrid",
    "wof:name":"Valdenebro Noguera Eladio",
    "wof:placetype":"venue"
},
  "geometry": {"coordinates":[-3.8417670727,40.4745368958],"type":"Point"}
}