{
  "type": "Feature",
  "properties": {
    "addr:full":"Av Salvador Espriu, 2 Sentmenat Barcelona 08181",
    "addr:housenumber":"2",
    "addr:postcode":"08181",
    "addr:street":"Av Salvador Espriu",
    "iso:country":"ES",
    "sg:address":"Av Salvador Espriu, 2",
    "sg:city":"Sentmenat",
    "sg:orig_category":"Zapatos (al Por Menor)",
    "sg:phone":"+34 937 15 14 05",
    "sg:postcode":"08181",
    "sg:province":"Barcelona",
    "wof:name":"Cal\u00e7ats Luque & Luque S.c.p.",
    "wof:placetype":"venue"
},
  "geometry": {"coordinates":[2.133795023,41.6082954407],"type":"Point"}
}