{
  "type": "Feature",
  "properties": {
    "iso:country":"ES",
    "sg:address":"Calle de Paez De Ribera, S/n",
    "sg:city":"Sevilla",
    "sg:orig_category":"Comercio De Piezas De Recambio Y De Accesorios De Veh\u00cdculos, Veh\u00cdculos Industriales",
    "sg:phone":"+34 954 62 40 13",
    "sg:postcode":"41012",
    "sg:province":"Sevilla",
    "wof:name":"Seviplaca S.l.",
    "wof:placetype":"venue"
},
  "geometry": {"coordinates":[-5.9885540009,37.3635940552],"type":"Point"}
}