{
  "type": "Feature",
  "properties": {
    "iso:country":"ES",
    "sg:address":"Carrer de Girona, 121",
    "sg:city":"Barcelona",
    "sg:orig_category":"Telas Y Sedas (al Por Menor)",
    "sg:phone":"+34 934 57 67 62",
    "sg:postcode":"08009",
    "sg:province":"Barcelona",
    "wof:name":"Madas Garreta S. L.",
    "wof:placetype":"venue"
},
  "geometry": {"coordinates":[2.1677350998,41.3971939087],"type":"Point"}
}