{
  "type": "Feature",
  "properties": {
    "iso:country":"ES",
    "sg:address":"Calle de Encomienda, 8",
    "sg:city":"Madrid",
    "sg:orig_category":"Importaci\u00d3n",
    "sg:phone":"+34 915 06 18 23",
    "sg:postcode":"28012",
    "sg:province":"Madrid",
    "wof:name":"Neik Tex Internacional S.l.",
    "wof:placetype":"venue"
},
  "geometry": {"coordinates":[-3.7052760124,40.4109344482],"type":"Point"}
}