{
  "type": "Feature",
  "properties": {
    "iso:country":"ES",
    "sg:address":"Calle de Musico Guerrero, 25",
    "sg:city":"Cordoba",
    "sg:orig_category":"Ingeniero",
    "sg:phone":"+34 957 40 33 47",
    "sg:postcode":"14012",
    "sg:province":"C\u00f3rdoba",
    "wof:name":"Ruiz Gimenez Rafael",
    "wof:placetype":"venue"
},
  "geometry": {"coordinates":[-4.7961111069,37.9167137146],"type":"Point"}
}