{
  "type": "Feature",
  "properties": {
    "addr:full":"San Roqui\u00f1o, S/n Noia La Coru\u00f1a 15200",
    "addr:housenumber":"s",
    "addr:postcode":"15200",
    "addr:street":"/ N;La Corun\u0303A",
    "iso:country":"ES",
    "sg:address":"San Roqui\u00f1o, S/n",
    "sg:city":"Noia",
    "sg:orig_category":"Serrer\u00cdas De Madera",
    "sg:phone":"+34 981 82 05 07",
    "sg:postcode":"15200",
    "sg:province":"La Coru\u00f1a",
    "wof:name":"Aquiles Nieto Filgueira S.l.",
    "wof:placetype":"venue"
},
  "geometry": {"coordinates":[-8.874876976,42.8063011169],"type":"Point"}
}