{
  "type": "Feature",
  "properties": {
    "iso:country":"ES",
    "sg:address":"Carrer de Sant Joan, 17",
    "sg:city":"Castellbisbal",
    "sg:orig_category":"Institutos De Belleza",
    "sg:phone":"+34 937 72 22 88",
    "sg:postcode":"08755",
    "sg:province":"Barcelona",
    "wof:name":"Hortet Martinez Juana",
    "wof:placetype":"venue"
},
  "geometry": {"coordinates":[1.9822820425,41.4750518799],"type":"Point"}
}