{
  "type": "Feature",
  "properties": {
    "addr:full":"Calle de Pablo Picasso (de), 5 Coslada Madrid 28820",
    "addr:housenumber":"5",
    "addr:postcode":"28820",
    "addr:street":"Calle De Pablo Picasso De",
    "iso:country":"ES",
    "sg:address":"Calle de Pablo Picasso (de), 5",
    "sg:city":"Coslada",
    "sg:orig_category":"Audiovisuales: Material Y Accesorios (al Por Menor)",
    "sg:phone":"+34 916 71 49 28",
    "sg:postcode":"28820",
    "sg:province":"Madrid",
    "wof:name":"Osuna Quiros Antonio",
    "wof:placetype":"venue"
},
  "geometry": {"coordinates":[-3.5645749569,40.4252319336],"type":"Point"}
}