{
  "type": "Feature",
  "properties": {
    "addr:full":"Praz Igrexa, 2 Temple La Coru\u00f1a 15679",
    "addr:housenumber":"2",
    "addr:postcode":"15679",
    "addr:street":"Praz Igrexa;La Corun\u0303A",
    "iso:country":"ES",
    "sg:address":"Praz Igrexa, 2",
    "sg:city":"Temple",
    "sg:orig_category":"Partidos Pol\u00cdticos",
    "sg:phone":"+34 981 65 12 87",
    "sg:postcode":"15679",
    "sg:province":"La Coru\u00f1a",
    "wof:name":"Partido Popular",
    "wof:placetype":"venue"
},
  "geometry": {"coordinates":[-8.3685693741,43.3172721863],"type":"Point"}
}