{
  "type": "Feature",
  "properties": {
    "iso:country":"ES",
    "sg:address":"Carr Tetuan, 16",
    "sg:city":"Vilanova I La Geltru",
    "sg:orig_category":"Peluquer\u00cdas, Peluquer\u00cda Mixta",
    "sg:phone":"+34 938 93 61 33",
    "sg:postcode":"08800",
    "sg:province":"Barcelona",
    "wof:name":"Noel Bou Xavier",
    "wof:placetype":"venue"
},
  "geometry": {"coordinates":[1.7271499634,41.2220954895],"type":"Point"}
}