{
  "type": "Feature",
  "properties": {
    "addr:full":"Carrer de Tramuntana, 32 Barcelona Barcelona 08030",
    "addr:housenumber":"32",
    "addr:postcode":"08030",
    "addr:street":"Carrer De Tramuntana",
    "iso:country":"ES",
    "sg:address":"Carrer de Tramuntana, 32",
    "sg:city":"Barcelona",
    "sg:orig_category":"Mec\u00c1nico Del Autom\u00d3vil",
    "sg:phone":"+34 933 45 41 98",
    "sg:postcode":"08030",
    "sg:province":"Barcelona",
    "wof:name":"Pera Serra Ignacio",
    "wof:placetype":"venue"
},
  "geometry": {"coordinates":[2.188024044,41.4387664795],"type":"Point"}
}