{
  "type": "Feature",
  "properties": {
    "addr:full":"Alicante-cartagena, Km. 0046,3 Torrevieja Alicante 03180",
    "addr:postcode":"03180",
    "addr:street":"Alicante-Cartagena Km. 0046,3",
    "iso:country":"ES",
    "sg:address":"Alicante-cartagena, Km. 0046,3",
    "sg:city":"Torrevieja",
    "sg:orig_category":"Supermercados Y Hipermercados",
    "sg:phone":"+34 965 71 16 25",
    "sg:postcode":"03180",
    "sg:province":"Alicante",
    "wof:name":"Bibiano Hnos.s.l.",
    "wof:placetype":"venue"
},
  "geometry": {"coordinates":[-0.6536790133,38.0173606873],"type":"Point"}
}