{
  "type": "Feature",
  "properties": {
    "addr:full":"Purisima, 19 Almassora Castell\u00f3n 12550",
    "addr:housenumber":"19",
    "addr:postcode":"12550",
    "addr:street":"Purisima;Castello\u0301N",
    "iso:country":"ES",
    "sg:address":"Purisima, 19",
    "sg:city":"Almassora",
    "sg:orig_category":"Carnicer\u00cdas, Carnicer\u00cdas",
    "sg:phone":"+34 964 56 24 05",
    "sg:postcode":"12550",
    "sg:province":"Castell\u00f3n",
    "wof:name":"Cabrera Marin Concepcion",
    "wof:placetype":"venue"
},
  "geometry": {"coordinates":[-0.0631700009,39.9439582825],"type":"Point"}
}