{
  "type": "Feature",
  "properties": {
    "iso:country":"ES",
    "sg:address":"Calle de Ca\u00d1a (de La), S/n",
    "sg:city":"Pto Real",
    "sg:orig_category":"Plomeros",
    "sg:phone":"+34 956 83 20 14",
    "sg:postcode":"11510",
    "sg:province":"C\u00e1diz",
    "wof:name":"Barragan Rodriguez Joaquin",
    "wof:placetype":"venue"
},
  "geometry": {"coordinates":[-6.1972241402,36.5322761536],"type":"Point"}
}