{
  "type": "Feature",
  "properties": {
    "addr:full":"Carrer de Mallorca, 435 Barcelona Barcelona 08013",
    "addr:housenumber":"435",
    "addr:postcode":"08013",
    "addr:street":"Carrer De Mallorca",
    "iso:country":"ES",
    "sg:address":"Carrer de Mallorca, 435",
    "sg:city":"Barcelona",
    "sg:orig_category":"Pescader\u00cdas (al Por Menor)",
    "sg:phone":"+34 934 33 47 90",
    "sg:postcode":"08013",
    "sg:province":"Barcelona",
    "wof:name":"Peixeteries Manero S.l.",
    "wof:placetype":"venue"
},
  "geometry": {"coordinates":[2.17750597,41.4052391052],"type":"Point"}
}