{
  "type": "Feature",
  "properties": {
    "iso:country":"ES",
    "sg:address":"Calle de Bego\u00d1a, 18",
    "sg:city":"Gijon",
    "sg:orig_category":"Centros Y Asociaciones De Gesti\u00d3n Homologados",
    "sg:phone":"+34 985 35 99 73",
    "sg:postcode":"33206",
    "sg:province":"Asturias",
    "wof:name":"Aladro Cabeza Jose Antonio",
    "wof:placetype":"venue"
},
  "geometry": {"coordinates":[-5.6630558968,43.5426864624],"type":"Point"}
}