{
  "type": "Feature",
  "properties": {
    "iso:country":"ES",
    "sg:address":"Carr Sant Pau, 22",
    "sg:city":"Figueres",
    "sg:orig_category":"Institutos De Belleza",
    "sg:phone":"+34 972 51 02 71",
    "sg:postcode":"17600",
    "sg:province":"Girona",
    "wof:name":"Costella Xampro Teresa",
    "wof:placetype":"venue"
},
  "geometry": {"coordinates":[2.9581100941,42.2656898499],"type":"Point"}
}