{
  "type": "Feature",
  "properties": {
    "iso:country":"ES",
    "sg:address":"Avda Cabo Noval, 9",
    "sg:city":"Sanlucar De Barrameda",
    "sg:orig_category":"Cajas Para Embalar",
    "sg:phone":"+34 956 38 53 58",
    "sg:postcode":"11540",
    "sg:province":"C\u00e1diz",
    "sg:website":"www.ruralvia.com",
    "wof:name":"Caja Rural Del Sur Sociedad Cooperativa",
    "wof:placetype":"venue"
},
  "geometry": {"coordinates":[-6.3523659706,36.7826309204],"type":"Point"}
}