{
  "type": "Feature",
  "properties": {
    "addr:full":"Calle de Santiago, 19 Valladolid Valladolid 47001",
    "addr:housenumber":"19",
    "addr:postcode":"47001",
    "addr:street":"Calle De Santiago",
    "iso:country":"ES",
    "sg:address":"Calle de Santiago, 19",
    "sg:city":"Valladolid",
    "sg:orig_category":"M\u00c9dicos: Medicina General",
    "sg:phone":"+34 983 37 29 24",
    "sg:postcode":"47001",
    "sg:province":"Valladolid",
    "wof:name":"Olmo Garcia Victor Faustino Del",
    "wof:placetype":"venue"
},
  "geometry": {"coordinates":[-4.7288417816,41.6495437622],"type":"Point"}
}