{
  "type": "Feature",
  "properties": {
    "addr:full":"Calle de Soledad, 46 Parla Madrid 28980",
    "addr:housenumber":"46",
    "addr:postcode":"28980",
    "addr:street":"Calle De Soledad",
    "iso:country":"ES",
    "sg:address":"Calle de Soledad, 46",
    "sg:city":"Parla",
    "sg:orig_category":"Panader\u00cdas, Panader\u00cdas",
    "sg:phone":"+34 916 98 24 28",
    "sg:postcode":"28980",
    "sg:province":"Madrid",
    "wof:name":"Fresno Franco Venancio",
    "wof:placetype":"venue"
},
  "geometry": {"coordinates":[-3.7718260288,40.2395973206],"type":"Point"}
}