{
  "type": "Feature",
  "properties": {
    "addr:full":"Arroyo Del Moro, 14 Cordoba C\u00f3rdoba 14011",
    "addr:housenumber":"14",
    "addr:postcode":"14011",
    "addr:street":"Arroyo Del Moro;Co\u0301Rdoba",
    "iso:country":"ES",
    "sg:address":"Arroyo Del Moro, 14",
    "sg:city":"Cordoba",
    "sg:orig_category":"Quincaller\u00cda (al Por Menor)",
    "sg:phone":"+34 957 46 39 83",
    "sg:postcode":"14011",
    "sg:province":"C\u00f3rdoba",
    "wof:name":"Alba Melero Juan",
    "wof:placetype":"venue"
},
  "geometry": {"coordinates":[-4.7968616486,37.8888015747],"type":"Point"}
}