{
  "type": "Feature",
  "properties": {
    "addr:full":"Calle de Ramiro El Monje (san Lorenzo), 7 San Lorenzo Del Flumen Huesca 22212",
    "addr:housenumber":"7",
    "addr:postcode":"22212",
    "addr:street":"Calle De Ramiro El;San Lorenzo",
    "iso:country":"ES",
    "sg:address":"Calle de Ramiro El Monje (san Lorenzo), 7",
    "sg:city":"San Lorenzo Del Flumen",
    "sg:orig_category":"Asociaciones, Instituciones De Consumidores Y Usuarios",
    "sg:phone":"+34 974 39 54 93",
    "sg:postcode":"22212",
    "sg:province":"Huesca",
    "wof:name":"Asociacion Amas De Casa Y Consumidores De Santa Agueda",
    "wof:placetype":"venue"
},
  "geometry": {"coordinates":[-0.4088979959,42.1401023865],"type":"Point"}
}