{
  "type": "Feature",
  "properties": {
    "addr:full":"Carrer de Casals I Cubero, 200 Barcelona Barcelona 08042",
    "addr:housenumber":"200",
    "addr:postcode":"08042",
    "addr:street":"Carrer De Casals I Cubero",
    "iso:country":"ES",
    "sg:address":"Carrer de Casals I Cubero, 200",
    "sg:city":"Barcelona",
    "sg:orig_category":"Cajas De Ahorro",
    "sg:phone":"+34 933 53 96 26",
    "sg:postcode":"08042",
    "sg:province":"Barcelona",
    "wof:name":"Caixa D'estalvis I Pensions De Barcelona",
    "wof:placetype":"venue"
},
  "geometry": {"coordinates":[2.1751821041,41.4410247803],"type":"Point"}
}