{
  "type": "Feature",
  "properties": {
    "iso:country":"ES",
    "sg:address":"Calle de Postas, 5",
    "sg:city":"Valdepe\u00f1as",
    "sg:orig_category":"Bares, Piano",
    "sg:phone":"+34 926 31 24 65",
    "sg:postcode":"13300",
    "sg:province":"Ciudad Real",
    "wof:name":"Cardona Prado Maria De Los Angeles",
    "wof:placetype":"venue"
},
  "geometry": {"coordinates":[-3.3888840675,38.7639808655],"type":"Point"}
}