{
  "type": "Feature",
  "properties": {
    "iso:country":"ES",
    "sg:address":"Behobia Au., 5",
    "sg:city":"Irun",
    "sg:orig_category":"Art\u00cdculos De Regalo (al Por Menor)",
    "sg:phone":"+34 943 62 14 44",
    "sg:postcode":"20305",
    "sg:province":"Guip\u00f9zcoa",
    "wof:name":"Bravo Sosa Alfonso",
    "wof:placetype":"venue"
},
  "geometry": {"coordinates":[-1.7587490082,43.3390426636],"type":"Point"}
}