{
  "type": "Feature",
  "properties": {
    "addr:full":"Ctra Benidorm, 58 La Nucia Alicante 03530",
    "addr:housenumber":"58",
    "addr:postcode":"03530",
    "addr:street":"Ctra Benidorm",
    "iso:country":"ES",
    "sg:address":"Ctra Benidorm, 58",
    "sg:city":"La Nucia",
    "sg:orig_category":"Ortopedia General",
    "sg:phone":"+34 966 89 58 06",
    "sg:postcode":"03530",
    "sg:province":"Alicante",
    "wof:name":"Ruiz Follana Juan",
    "wof:placetype":"venue"
},
  "geometry": {"coordinates":[-0.1321440041,38.6014900208],"type":"Point"}
}