{
  "type": "Feature",
  "properties": {
    "addr:full":"Avda Democracia, 7 Madrid Madrid 28031",
    "addr:housenumber":"7",
    "addr:postcode":"madrid;28031",
    "addr:street":"Avda Democracia",
    "iso:country":"ES",
    "sg:address":"Avda Democracia, 7",
    "sg:city":"Madrid",
    "sg:orig_category":"Empresas De Vigilancia, Guardia Y Protecci\u00d3n",
    "sg:phone":"+34 913 32 67 87",
    "sg:postcode":"28031",
    "sg:province":"Madrid",
    "wof:name":"Airo Tools S.l.",
    "wof:placetype":"venue"
},
  "geometry": {"coordinates":[-3.623904705,40.3859443665],"type":"Point"}
}