{
  "type": "Feature",
  "properties": {
    "addr:full":"Calle de Baleares, 12 Gijon Asturias 33208",
    "addr:housenumber":"12",
    "addr:postcode":"33208",
    "addr:street":"Calle De Baleares",
    "iso:country":"ES",
    "sg:address":"Calle de Baleares, 12",
    "sg:city":"Gijon",
    "sg:orig_category":"Servicio De Salud",
    "sg:phone":"+34 985 14 32 19",
    "sg:postcode":"33208",
    "sg:province":"Asturias",
    "wof:name":"Lindoso Prieto Rogelio",
    "wof:placetype":"venue"
},
  "geometry": {"coordinates":[-5.6699585915,43.52866745],"type":"Point"}
}