{
  "type": "Feature",
  "properties": {
    "addr:full":"Calle de Zurita, 13 Zaragoza Zaragoza 50001",
    "addr:housenumber":"13",
    "addr:postcode":"50001",
    "addr:street":"Calle De Zurita",
    "iso:country":"ES",
    "sg:address":"Calle de Zurita, 13",
    "sg:city":"Zaragoza",
    "sg:orig_category":"Ropa Para Se\u00d1oras (al Por Menor)",
    "sg:phone":"+34 976 22 82 48",
    "sg:postcode":"50001",
    "sg:province":"Zaragoza",
    "sg:website":"www.pedrobernal.com",
    "wof:name":"Pedro Bernal S.l.",
    "wof:placetype":"venue"
},
  "geometry": {"coordinates":[-0.8804230094,41.6501312256],"type":"Point"}
}