{
  "type": "Feature",
  "properties": {
    "iso:country":"ES",
    "sg:address":"A Gandara, 16",
    "sg:city":"Gandara",
    "sg:orig_category":"Bebidas",
    "sg:phone":"+34 986 55 50 36",
    "sg:postcode":"36628",
    "sg:province":"Pontevedra",
    "wof:name":"Oliveira Nogueira Agustin",
    "wof:placetype":"venue"
},
  "geometry": {"coordinates":[-8.7573289871,42.5457649231],"type":"Point"}
}