{
  "type": "Feature",
  "properties": {
    "addr:full":"Calle de Alonso Astulez, 10 Torrelavega Cantabria 39300",
    "addr:housenumber":"10",
    "addr:postcode":"39300",
    "addr:street":"Calle De Alonso Astulez",
    "iso:country":"ES",
    "sg:address":"Calle de Alonso Astulez, 10",
    "sg:city":"Torrelavega",
    "sg:orig_category":"Loter\u00cda Y T\u00d3mbola",
    "sg:phone":"+34 942 80 57 75",
    "sg:postcode":"39300",
    "sg:province":"Cantabria",
    "wof:name":"Fernandez Aguilera Rosa Maria",
    "wof:placetype":"venue"
},
  "geometry": {"coordinates":[-4.0469851494,43.348526001],"type":"Point"}
}