{
  "type": "Feature",
  "properties": {
    "iso:country":"ES",
    "sg:address":"Avda Compromiso De Caspe, 68",
    "sg:city":"Zaragoza",
    "sg:orig_category":"Cajas De Ahorro",
    "sg:phone":"+34 976 42 81 14",
    "sg:postcode":"50002",
    "sg:province":"Zaragoza",
    "sg:website":"www.ruralvia.es",
    "wof:name":"Caja Rural Aragonesa Y De Los Pirineos",
    "wof:placetype":"venue"
},
  "geometry": {"coordinates":[-0.8624979854,41.6451377869],"type":"Point"}
}