{
  "type": "Feature",
  "properties": {
    "iso:country":"ES",
    "sg:address":"Av Barcelona, 16",
    "sg:city":"S. Joan Despi",
    "sg:orig_category":"Sociedades, Compa\u00d1\u00cdas Aseguradoras",
    "sg:phone":"+34 933 73 61 06",
    "sg:postcode":"08970",
    "sg:province":"Barcelona",
    "wof:name":"Gil Gonzalez Scp",
    "wof:placetype":"venue"
},
  "geometry": {"coordinates":[2.0609240532,41.3667221069],"type":"Point"}
}