{
  "type": "Feature",
  "properties": {
    "iso:country":"ES",
    "sg:address":"Avda Casas De Compostela (das), 4",
    "sg:city":"Santiago De Compostela",
    "sg:orig_category":"Estilistas Y Estudios De Estilo De Corte Y Confecci\u00d3n",
    "sg:phone":"+34 981 58 07 82",
    "sg:postcode":"15706",
    "sg:province":"La Coru\u00f1a",
    "wof:name":"Hnos.cierto Gestal S.c.",
    "wof:placetype":"venue"
},
  "geometry": {"coordinates":[-8.5487089157,42.8762550354],"type":"Point"}
}