{
  "type": "Feature",
  "properties": {
    "addr:full":"Calle de Elisa Cendrero, 4 Ciudad Real Ciudad Real 13004",
    "addr:housenumber":"4",
    "addr:postcode":"13004",
    "addr:street":"Calle De Elisa Cendrero",
    "iso:country":"ES",
    "sg:address":"Calle de Elisa Cendrero, 4",
    "sg:city":"Ciudad Real",
    "sg:orig_category":"Laboratorios Y Trabajos De Fotograf\u00cda, V\u00cddeo Y Cine",
    "sg:phone":"+34 926 25 15 38",
    "sg:postcode":"13004",
    "sg:province":"Ciudad Real",
    "wof:name":"Mu\u00f1oz Palacio Carlos Jesus",
    "wof:placetype":"venue"
},
  "geometry": {"coordinates":[-3.9276530743,38.9878807068],"type":"Point"}
}