{
  "type": "Feature",
  "properties": {
    "iso:country":"ES",
    "sg:address":"Avda Principal, 105",
    "sg:city":"Navas Del Marques",
    "sg:orig_category":"Cajas De Ahorro",
    "sg:phone":"+34 918 97 00 94",
    "sg:postcode":"05230",
    "sg:province":"\u00c1vila",
    "sg:website":"www.lacaixa.es",
    "wof:name":"Caixa D'estalvis I Pensions De Barcelona",
    "wof:placetype":"venue"
},
  "geometry": {"coordinates":[-4.3335318565,40.6028747559],"type":"Point"}
}