{
  "type": "Feature",
  "properties": {
    "addr:full":"Calle de Salamanca-san Bartolome, 2 San Bartolome Alicante 03314",
    "addr:housenumber":"2",
    "addr:postcode":"03314",
    "addr:street":"Calle De Salamanca-San Bartolome",
    "iso:country":"ES",
    "sg:address":"Calle de Salamanca-san Bartolome, 2",
    "sg:city":"San Bartolome",
    "sg:orig_category":"Empresas De Pintura Y Revestimientos",
    "sg:phone":"+34 966 77 60 74",
    "sg:postcode":"03314",
    "sg:province":"Alicante",
    "wof:name":"Fernandez Garcia Marcial",
    "wof:placetype":"venue"
},
  "geometry": {"coordinates":[-0.8623440266,38.0960388184],"type":"Point"}
}