{
  "type": "Feature",
  "properties": {
    "addr:full":"Avda Aragon, 398 Madrid Madrid 28022",
    "addr:housenumber":"398",
    "addr:postcode":"28022",
    "addr:street":"Avda Aragon",
    "iso:country":"ES",
    "sg:address":"Avda Aragon, 398",
    "sg:city":"Madrid",
    "sg:orig_category":"Carnes De Carnicer\u00cda (al Por Mayor)",
    "sg:phone":"+34 913 29 01 59",
    "sg:postcode":"28022",
    "sg:province":"Madrid",
    "sg:website":"www.iberangus.com",
    "wof:name":"Iberangus Internacional S.l.",
    "wof:placetype":"venue"
},
  "geometry": {"coordinates":[-3.5590434074,40.4492759705],"type":"Point"}
}