{
  "type": "Feature",
  "properties": {
    "iso:country":"ES",
    "sg:address":"Calle de Obispo Jesus Dominguez, 5",
    "sg:city":"Caceres",
    "sg:orig_category":"Loter\u00cda Y T\u00d3mbola",
    "sg:phone":"+34 927 21 61 41",
    "sg:postcode":"10001",
    "sg:province":"C\u00e1ceres",
    "sg:website":"www.oid.es",
    "wof:name":"Organizacion Impulsora De Discapacitados O.i.d.",
    "wof:placetype":"venue"
},
  "geometry": {"coordinates":[-6.3816370964,39.469707489],"type":"Point"}
}