{
  "type": "Feature",
  "properties": {
    "addr:full":"Ctra Nacional Iii, Km. 0340,7 Quart Poblet Valencia 46930",
    "addr:postcode":"46930",
    "addr:street":"Ctra Nacional Iii Km. 0340,7;Poblet",
    "iso:country":"ES",
    "sg:address":"Ctra Nacional Iii, Km. 0340,7",
    "sg:city":"Quart Poblet",
    "sg:orig_category":"Carnes De Carnicer\u00cda (al Por Mayor)",
    "sg:phone":"+34 961 59 76 79",
    "sg:postcode":"46930",
    "sg:province":"Valencia",
    "sg:website":"www.skare.com",
    "wof:name":"Skare Spain S.l.",
    "wof:placetype":"venue"
},
  "geometry": {"coordinates":[-0.4419890046,39.482711792],"type":"Point"}
}