{
  "type": "Feature",
  "properties": {
    "addr:full":"Calle de Gloria, 83 Palmar  O Lugar De Don Juan Murcia 30120",
    "addr:housenumber":"83",
    "addr:postcode":"30120",
    "addr:street":"Calle De Gloria;Lugar",
    "iso:country":"ES",
    "sg:address":"Calle de Gloria, 83",
    "sg:city":"Palmar  O Lugar De Don Juan",
    "sg:orig_category":"Alimentaci\u00d3n General (al Por Menor)",
    "sg:phone":"+34 968 88 50 93",
    "sg:postcode":"30120",
    "sg:province":"Murcia",
    "wof:name":"Romero Alcaraz Fernando",
    "wof:placetype":"venue"
},
  "geometry": {"coordinates":[-1.1302490234,37.9829597473],"type":"Point"}
}