{
  "type": "Feature",
  "properties": {
    "iso:country":"ES",
    "sg:address":"Calle de Constitucion, 5",
    "sg:city":"Moral Calatrava",
    "sg:orig_category":"Molduras, Junquillos, Listones Y Molduras Perforadas",
    "sg:phone":"+34 926 33 01 91",
    "sg:postcode":"13350",
    "sg:province":"Ciudad Real",
    "wof:name":"Lopez Blanco Miguel",
    "wof:placetype":"venue"
},
  "geometry": {"coordinates":[-3.5816533566,38.8286552429],"type":"Point"}
}