{
  "type": "Feature",
  "properties": {
    "addr:full":"Calle de Juan De Herrera, 23 Entrepinos Valladolid 47130",
    "addr:housenumber":"23",
    "addr:postcode":"47130",
    "addr:street":"Calle De Juan De Herrera",
    "iso:country":"ES",
    "sg:address":"Calle de Juan De Herrera, 23",
    "sg:city":"Entrepinos",
    "sg:orig_category":"Ingeniero",
    "sg:phone":"+34 983 59 08 91",
    "sg:postcode":"47130",
    "sg:province":"Valladolid",
    "wof:name":"Alaguero Valerio Jesus",
    "wof:placetype":"venue"
},
  "geometry": {"coordinates":[-4.8386359215,41.569606781],"type":"Point"}
}