{
  "type": "Feature",
  "properties": {
    "iso:country":"ES",
    "sg:address":"Calle de Aranaz Y Vides, 10",
    "sg:city":"Tudela",
    "sg:orig_category":"Radiocomunicaciones, Telefon\u00cda M\u00d3vil, Radiomensajer\u00cda: Servicios, Comercializaci\u00d3n",
    "sg:phone":"+34 948 82 27 20",
    "sg:postcode":"31500",
    "sg:province":"Navarra",
    "wof:name":"Giros Monex S.l.",
    "wof:placetype":"venue"
},
  "geometry": {"coordinates":[-1.5994507074,42.0592651367],"type":"Point"}
}