{
  "type": "Feature",
  "properties": {
    "iso:country":"ES",
    "sg:address":"Las Dos V\u00edas, 26",
    "sg:city":"Grado",
    "sg:orig_category":"Distribuci\u00d3n De Petr\u00d3leo Y Derivados",
    "sg:phone":"+34 985 75 36 10",
    "sg:postcode":"33820",
    "sg:province":"Asturias",
    "wof:name":"Gutierrez Lopez Jesus Serafin",
    "wof:placetype":"venue"
},
  "geometry": {"coordinates":[-6.0672416687,43.392829895],"type":"Point"}
}