{
  "type": "Feature",
  "properties": {
    "addr:full":"Antonio Martinez De Haro, 3 Pozoblanco C\u00f3rdoba 14400",
    "addr:housenumber":"3",
    "addr:postcode":"14400",
    "addr:street":"Martinez De Haro",
    "iso:country":"ES",
    "sg:address":"Antonio Martinez De Haro, 3",
    "sg:city":"Pozoblanco",
    "sg:orig_category":"Carnicer\u00cdas, Carnicer\u00cdas",
    "sg:phone":"+34 957 77 06 18",
    "sg:postcode":"14400",
    "sg:province":"C\u00f3rdoba",
    "wof:name":"Moreno Diaz Jose Luis",
    "wof:placetype":"venue"
},
  "geometry": {"coordinates":[-4.8430118561,38.3784675598],"type":"Point"}
}