{
  "type": "Feature",
  "properties": {
    "iso:country":"ES",
    "sg:address":"Carr Pirotecnia Brunchu, 77",
    "sg:city":"Godella",
    "sg:orig_category":"Lubrificantes (fabricaci\u00d3n, Al Por Mayor)",
    "sg:phone":"+34 963 90 28 19",
    "sg:postcode":"46110",
    "sg:province":"Valencia",
    "wof:name":"Cronaval De Soldaduras Y Lubricantes S.l.",
    "wof:placetype":"venue"
},
  "geometry": {"coordinates":[-0.4224489927,39.5221405029],"type":"Point"}
}