{
  "type": "Feature",
  "properties": {
    "iso:country":"ES",
    "sg:address":"Carr Castell (del), 3",
    "sg:city":"Artesa Lleida",
    "sg:orig_category":"Administraciones Regionales, Departamentales Y Locales",
    "sg:phone":"+34 973 16 71 62",
    "sg:postcode":"25150",
    "sg:province":"Lleida",
    "wof:name":"Ajuntament D'artesa De Lleida",
    "wof:placetype":"venue"
},
  "geometry": {"coordinates":[0.7031033039,41.5517921448],"type":"Point"}
}