{
  "type": "Feature",
  "properties": {
    "addr:full":"Calle de Enrique Granados, 6 Pozuelo De Alarcon Madrid 28224",
    "addr:housenumber":"6",
    "addr:postcode":"28224",
    "addr:street":"Calle De Enrique Granados",
    "iso:country":"ES",
    "sg:address":"Calle de Enrique Granados, 6",
    "sg:city":"Pozuelo De Alarcon",
    "sg:orig_category":"Inform\u00c1tica Equipo Y Programas (al Por Mayor)",
    "sg:phone":"+34 913 51 71 60",
    "sg:postcode":"28224",
    "sg:province":"Madrid",
    "sg:website":"www.mathworks.com",
    "wof:name":"The Mathworks S.l.",
    "wof:placetype":"venue"
},
  "geometry": {"coordinates":[-3.8116030693,40.4582138062],"type":"Point"}
}