{
  "type": "Feature",
  "properties": {
    "iso:country":"ES",
    "sg:address":"Calle de Luis Montoto, 105",
    "sg:city":"Sevilla",
    "sg:orig_category":"Asesor\u00cda Fiscal Y Jur\u00cddica",
    "sg:phone":"+34 954 57 32 35",
    "sg:postcode":"41007",
    "sg:province":"Sevilla",
    "wof:name":"Asepyme Nervion Asesores S.l.",
    "wof:placetype":"venue"
},
  "geometry": {"coordinates":[-5.9707369804,37.3874664307],"type":"Point"}
}