{
  "type": "Feature",
  "properties": {
    "iso:country":"ES",
    "sg:address":"Calle de Pez Volador, 30",
    "sg:city":"Madrid",
    "sg:orig_category":"Piscinas (establecimientos)",
    "sg:phone":"+34 914 09 50 08",
    "sg:postcode":"28007",
    "sg:province":"Madrid",
    "wof:name":"Canoe Natacion Club",
    "wof:placetype":"venue"
},
  "geometry": {"coordinates":[-3.6647679806,40.4135475159],"type":"Point"}
}