{
  "type": "Feature",
  "properties": {
    "iso:country":"ES",
    "sg:address":"Calle de Jose Cueto, 15",
    "sg:city":"Aviles",
    "sg:orig_category":"Alumbrados",
    "sg:phone":"+34 985 56 92 55",
    "sg:postcode":"33401",
    "sg:province":"Asturias",
    "wof:name":"Alvarez Fernandez Senen",
    "wof:placetype":"venue"
},
  "geometry": {"coordinates":[-5.9274916649,43.5579299927],"type":"Point"}
}