{
  "type": "Feature",
  "properties": {
    "iso:country":"ES",
    "sg:address":"Calle de Cirilo Villena, S/n",
    "sg:city":"Tomelloso",
    "sg:orig_category":"Escayola Y Productos De Escayola (fabricaci\u00d3n, Al Por Mayor)",
    "sg:phone":"+34 926 50 27 28",
    "sg:postcode":"13700",
    "sg:province":"Ciudad Real",
    "wof:name":"Yesos Hilario S.l.u.",
    "wof:placetype":"venue"
},
  "geometry": {"coordinates":[-3.0195658207,39.165813446],"type":"Point"}
}