{
  "type": "Feature",
  "properties": {
    "iso:country":"ES",
    "sg:address":"Calle de Virgen De La Paz, 42",
    "sg:city":"Manzanares",
    "sg:orig_category":"Restaurantes",
    "sg:phone":"+34 926 61 06 42",
    "sg:postcode":"13200",
    "sg:province":"Ciudad Real",
    "wof:name":"Moraleda Eugena Vicenta",
    "wof:placetype":"venue"
},
  "geometry": {"coordinates":[-3.3715481758,39.0002365112],"type":"Point"}
}