{
  "type": "Feature",
  "properties": {
    "iso:country":"ES",
    "sg:address":"Calle de Menendez Pelayo, 17",
    "sg:city":"Laredo",
    "sg:orig_category":"Promotores Constructores",
    "sg:phone":"+34 942 60 61 88",
    "sg:postcode":"39770",
    "sg:province":"Cantabria",
    "wof:name":"Construcciones Peibasa, S. L.",
    "wof:placetype":"venue"
},
  "geometry": {"coordinates":[-3.4125781059,43.4128417969],"type":"Point"}
}