{
  "type": "Feature",
  "properties": {
    "iso:country":"ES",
    "sg:address":"Calle de Carreteria, 4",
    "sg:city":"Malaga",
    "sg:orig_category":"Asesor\u00cda Fiscal Y Jur\u00cddica",
    "sg:phone":"+34 952 22 71 70",
    "sg:postcode":"29008",
    "sg:province":"M\u00e1laga",
    "wof:name":"Tribuna Consulting S.l.",
    "wof:placetype":"venue"
},
  "geometry": {"coordinates":[-4.4248981476,36.7215423584],"type":"Point"}
}