{
  "type": "Feature",
  "properties": {
    "iso:country":"ES",
    "sg:address":"Urb. Breogan(feans), 23",
    "sg:city":"A Coru\u00f1a",
    "sg:orig_category":"Material Y Suministros Para Fotocopiadoras, Reprograf\u00cda",
    "sg:phone":"+34 981 28 14 55",
    "sg:postcode":"15192",
    "sg:province":"La Coru\u00f1a",
    "wof:name":"Ferreiro Seijas Antonio",
    "wof:placetype":"venue"
},
  "geometry": {"coordinates":[-8.4421863556,43.3124313354],"type":"Point"}
}