{
  "type": "Feature",
  "properties": {
    "iso:country":"ES",
    "sg:address":"Calle de Chinchorro, 10",
    "sg:city":"Puerto Del Carmen",
    "sg:orig_category":"Bazares, Art\u00cdculos De Limpieza Y De Cocina (al Por Menor)",
    "sg:phone":"+34 928 51 48 25",
    "sg:postcode":"35510",
    "sg:province":"Las Palmas",
    "wof:name":"Sughand  Lisha Rajehh",
    "wof:placetype":"venue"
},
  "geometry": {"coordinates":[-13.6477594376,28.9218482971],"type":"Point"}
}