{
  "type": "Feature",
  "properties": {
    "addr:full":"Plaz Constitucion, 10 Illar Almer\u00eda 04431",
    "addr:housenumber":"10",
    "addr:postcode":"04431",
    "addr:street":"Constitucion;Almeri\u0301A",
    "iso:country":"ES",
    "sg:address":"Plaz Constitucion, 10",
    "sg:city":"Illar",
    "sg:orig_category":"Fabricaci\u00d3n De Telas Y Sedas",
    "sg:phone":"+34 950 64 71 11",
    "sg:postcode":"04431",
    "sg:province":"Almer\u00eda",
    "wof:name":"Granados Fernandez Ramon",
    "wof:placetype":"venue"
},
  "geometry": {"coordinates":[-2.6437437534,36.9731292725],"type":"Point"}
}