{
  "type": "Feature",
  "properties": {
    "addr:full":"Isaac Peral, 9 Gijon Asturias 33211",
    "addr:housenumber":"9",
    "addr:postcode":"33211",
    "addr:street":"Isaac Peral",
    "iso:country":"ES",
    "sg:address":"Isaac Peral, 9",
    "sg:city":"Gijon",
    "sg:orig_category":"Publicidad (edici\u00d3n)",
    "sg:phone":"+34 985 31 16 30",
    "sg:postcode":"33211",
    "sg:province":"Asturias",
    "wof:name":"Prem Publicidad S.l.",
    "wof:placetype":"venue"
},
  "geometry": {"coordinates":[-5.6863942146,43.5233383179],"type":"Point"}
}