{
  "type": "Feature",
  "properties": {
    "iso:country":"ES",
    "sg:address":"Carrer de Valencia, 106",
    "sg:city":"Barcelona",
    "sg:orig_category":"Sociedades, Compa\u00d1\u00cdas Aseguradoras",
    "sg:phone":"+34 932 26 59 66",
    "sg:postcode":"08015",
    "sg:province":"Barcelona",
    "wof:name":"Ame Asistencia Medica Compa\u00d1ia De Seguros S.a.",
    "wof:placetype":"venue"
},
  "geometry": {"coordinates":[2.1507108212,41.3831748962],"type":"Point"}
}