{
  "type": "Feature",
  "properties": {
    "addr:full":"Rua San Roque, 39 Xinzo De Limia Ourense 32630",
    "addr:housenumber":"39",
    "addr:postcode":"32630",
    "addr:street":"Rua San Roque",
    "iso:country":"ES",
    "sg:address":"Rua San Roque, 39",
    "sg:city":"Xinzo De Limia",
    "sg:orig_category":"Ense\u00d1anza: Profesiones Art\u00cdsticas",
    "sg:phone":"+34 988 46 02 51",
    "sg:postcode":"32630",
    "sg:province":"Ourense",
    "wof:name":"Dacal De Castro Jose Luis",
    "wof:placetype":"venue"
},
  "geometry": {"coordinates":[-7.7260389328,42.0627403259],"type":"Point"}
}