{
  "type": "Feature",
  "properties": {
    "addr:full":"Rbla Principal, 59 Vilanova I La Geltru Barcelona 08800",
    "addr:housenumber":"59",
    "addr:postcode":"08800",
    "addr:street":"Rbla Principal",
    "iso:country":"ES",
    "sg:address":"Rbla Principal, 59",
    "sg:city":"Vilanova I La Geltru",
    "sg:orig_category":"M\u00c9dicos: Gastroenterolog\u00cda Y Hepatolog\u00cda (aparato Digestivo)",
    "sg:phone":"+34 938 93 72 30",
    "sg:postcode":"08800",
    "sg:province":"Barcelona",
    "wof:name":"Mundet Surroca Jorge",
    "wof:placetype":"venue"
},
  "geometry": {"coordinates":[1.7255129814,41.2229499817],"type":"Point"}
}