{
  "type": "Feature",
  "properties": {
    "iso:country":"ES",
    "sg:address":"Carr Juan Xxiii, 103",
    "sg:city":"Puerto De Pollen\u00c7a",
    "sg:orig_category":"M\u00c9dicos: Cardiolog\u00cda Y Afecciones Cardiovasculares",
    "sg:phone":"+34 971 53 33 40",
    "sg:postcode":"07470",
    "sg:province":"Islas Baleares",
    "wof:name":"Nadal Aguirre Alvaro",
    "wof:placetype":"venue"
},
  "geometry": {"coordinates":[3.0826599598,39.9063415527],"type":"Point"}
}