{
  "type": "Feature",
  "properties": {
    "addr:full":"Pg Lloren\u00c7 Serra, 37 Santa Coloma De Gramenet Barcelona 08922",
    "addr:housenumber":"37",
    "addr:postcode":"08922",
    "addr:street":"Pg Llorenc\u0327 Serra",
    "iso:country":"ES",
    "sg:address":"Pg Lloren\u00c7 Serra, 37",
    "sg:city":"Santa Coloma De Gramenet",
    "sg:orig_category":"M\u00c9dicos: Anestesiolog\u00cda Y Reanimaci\u00d3n Quir\u00dargica",
    "sg:phone":"+34 934 66 03 82",
    "sg:postcode":"08922",
    "sg:province":"Barcelona",
    "wof:name":"Blanco Vargas Domingo",
    "wof:placetype":"venue"
},
  "geometry": {"coordinates":[2.2054760456,41.4503288269],"type":"Point"}
}