{
  "type": "Feature",
  "properties": {
    "addr:full":"Calle de Papa Juan Xxiii, 74 Membrilla Ciudad Real 13230",
    "addr:housenumber":"74",
    "addr:postcode":"13230",
    "addr:street":"Calle De Papa Juan Xxiii",
    "iso:country":"ES",
    "sg:address":"Calle de Papa Juan Xxiii, 74",
    "sg:city":"Membrilla",
    "sg:classifiers":[
        {
            "category":"Taxi",
            "type":"Transportation"
        }
    ],
    "sg:phone":"+34 926 63 64 02",
    "sg:postcode":"13230",
    "sg:province":"Ciudad Real",
    "wof:name":"Villalta Jimenez Tomas",
    "wof:placetype":"venue"
},
  "geometry": {"coordinates":[-3.343626976,38.9723930359],"type":"Point"}
}