{
  "type": "Feature",
  "properties": {
    "iso:country":"ES",
    "sg:address":"Pol Ind La Victoria, 1",
    "sg:city":"Andujar",
    "sg:orig_category":"Lavander\u00cdas Para Particulares, Autoservicio De Lavander\u00cdas",
    "sg:phone":"+34 953 50 67 22",
    "sg:postcode":"23740",
    "sg:province":"Ja\u00e9n",
    "wof:name":"Lavanderia Industrial Lia S.l.",
    "wof:placetype":"venue"
},
  "geometry": {"coordinates":[-4.057518959,38.0386962891],"type":"Point"}
}