{
  "type": "Feature",
  "properties": {
    "addr:full":"Calle de Amsterdam, S/n Parla Madrid 28980",
    "addr:housenumber":"s / n",
    "addr:postcode":"28980",
    "addr:street":"Calle De Amsterdam",
    "iso:country":"ES",
    "sg:address":"Calle de Amsterdam, S/n",
    "sg:city":"Parla",
    "sg:orig_category":"Promotores Constructores",
    "sg:phone":"+34 917 65 05 99",
    "sg:postcode":"28980",
    "sg:province":"Madrid",
    "wof:name":"Imasatec S.a.",
    "wof:placetype":"venue"
},
  "geometry": {"coordinates":[-3.7444190979,40.2392921448],"type":"Point"}
}