{
  "type": "Feature",
  "properties": {
    "addr:full":"Calle de Vaqueras, 15 Alcala Henares Madrid 28801",
    "addr:housenumber":"15",
    "addr:postcode":"28801",
    "addr:street":"Calle De Vaqueras",
    "iso:country":"ES",
    "sg:address":"Calle de Vaqueras, 15",
    "sg:city":"Alcala Henares",
    "sg:orig_category":"Abogados",
    "sg:phone":"+34 918 81 64 60",
    "sg:postcode":"28801",
    "sg:province":"Madrid",
    "wof:name":"Fernandez-alcantud Dominguez Jose Antonio",
    "wof:placetype":"venue"
},
  "geometry": {"coordinates":[-3.369312048,40.4784164429],"type":"Point"}
}