{
  "type": "Feature",
  "properties": {
    "addr:full":"Calle de San Vicente De Paul, 3 Caceres C\u00e1ceres 10001",
    "addr:housenumber":"3",
    "addr:postcode":"10001",
    "addr:street":"Calle De San Vicente De Paul;Ca\u0301Ceres",
    "iso:country":"ES",
    "sg:address":"Calle de San Vicente De Paul, 3",
    "sg:city":"Caceres",
    "sg:orig_category":"Ingeniero",
    "sg:phone":"+34 927 22 73 28",
    "sg:postcode":"10001",
    "sg:province":"C\u00e1ceres",
    "wof:name":"Cobos Rodriguez Eugenio",
    "wof:placetype":"venue"
},
  "geometry": {"coordinates":[-6.3781070709,39.4669685364],"type":"Point"}
}