{
  "type": "Feature",
  "properties": {
    "iso:country":"ES",
    "sg:address":"Calle de San Pascual, 2",
    "sg:city":"Orihuela",
    "sg:orig_category":"Zapatos (al Por Menor)",
    "sg:phone":"+34 965 30 14 19",
    "sg:postcode":"03300",
    "sg:province":"Alicante",
    "wof:name":"Navarro Izquierdo Patrocinio",
    "wof:placetype":"venue"
},
  "geometry": {"coordinates":[-0.9465153813,38.0843162537],"type":"Point"}
}