{
  "type": "Feature",
  "properties": {
    "addr:full":"Calle de Real De Malaga, 7 Gabia Grande Granada 18110",
    "addr:housenumber":"7",
    "addr:postcode":"18110",
    "addr:street":"Calle De Real De Malaga",
    "iso:country":"ES",
    "sg:address":"Calle de Real De Malaga, 7",
    "sg:city":"Gabia Grande",
    "sg:orig_category":"Asesor\u00cda Fiscal Y Jur\u00cddica",
    "sg:phone":"+34 958 58 65 99",
    "sg:postcode":"18110",
    "sg:province":"Granada",
    "wof:name":"Vilchez Urbano Maria Nieves",
    "wof:placetype":"venue"
},
  "geometry": {"coordinates":[-3.6676669121,37.1360702515],"type":"Point"}
}