{
  "type": "Feature",
  "properties": {
    "iso:country":"ES",
    "sg:address":"El Faro, 2",
    "sg:city":"Torrox-costa",
    "sg:orig_category":"Arquitectos",
    "sg:phone":"+34 952 53 01 09",
    "sg:postcode":"29793",
    "sg:province":"M\u00e1laga",
    "wof:name":"Omero Espa\u00f1a S.c.",
    "wof:placetype":"venue"
},
  "geometry": {"coordinates":[-3.95946908,36.7297477722],"type":"Point"}
}