{
  "type": "Feature",
  "properties": {
    "addr:full":"Carr Prat De La Riba, 3 Hostal Nou Lleida 25617",
    "addr:housenumber":"3",
    "addr:postcode":"25617",
    "addr:street":"Carr Prat De La Riba",
    "iso:country":"ES",
    "sg:address":"Carr Prat De La Riba, 3",
    "sg:city":"Hostal Nou",
    "sg:orig_category":"Madera Para Construcci\u00d3n E Industria",
    "sg:phone":"+34 973 44 66 42",
    "sg:postcode":"25617",
    "sg:province":"Lleida",
    "wof:name":"Manuel Olives Sanchez Y Teresa Lloret Navarra C.b.",
    "wof:placetype":"venue"
},
  "geometry": {"coordinates":[0.8779199719,41.8057518005],"type":"Point"}
}