{
  "type": "Feature",
  "properties": {
    "addr:full":"Carr Princep De Viana, 68 Lleida Lleida 25008",
    "addr:housenumber":"68",
    "addr:postcode":"25008",
    "addr:street":"Carr Princep De Viana",
    "iso:country":"ES",
    "sg:address":"Carr Princep De Viana, 68",
    "sg:city":"Lleida",
    "sg:orig_category":"Confecci\u00d3n (fabricaci\u00d3n, Al Por Mayor)",
    "sg:phone":"+34 973 22 03 46",
    "sg:postcode":"25008",
    "sg:province":"Lleida",
    "wof:name":"Gestio De Produccio Controlada S.l.",
    "wof:placetype":"venue"
},
  "geometry": {"coordinates":[0.6264439821,41.6236686707],"type":"Point"}
}