{
  "type": "Feature",
  "properties": {
    "addr:full":"Pg Catalunya, 51 Torroella Montgri Girona 17257",
    "addr:housenumber":"51",
    "addr:postcode":"17257",
    "addr:street":"Pg Catalunya",
    "iso:country":"ES",
    "sg:address":"Pg Catalunya, 51",
    "sg:city":"Torroella Montgri",
    "sg:orig_category":"Ropa Para Ni\u00d1os (al Por Menor)",
    "sg:phone":"+34 972 76 09 15",
    "sg:postcode":"17257",
    "sg:province":"Girona",
    "wof:name":"Pidemunt Pol Rosa Maria",
    "wof:placetype":"venue"
},
  "geometry": {"coordinates":[3.1276900768,42.0407791138],"type":"Point"}
}