{
  "type": "Feature",
  "properties": {
    "addr:full":"Santiago Kalea, 6 Azpeitia Guip\u00f9zcoa 20730",
    "addr:housenumber":"6",
    "addr:postcode":"20730",
    "addr:street":"Santiago Kalea;Guipu\u0300Zcoa",
    "iso:country":"ES",
    "sg:address":"Santiago Kalea, 6",
    "sg:city":"Azpeitia",
    "sg:orig_category":"Peluquer\u00cdas, Peluquer\u00cda Mixta",
    "sg:phone":"+34 943 15 01 61",
    "sg:postcode":"20730",
    "sg:province":"Guip\u00f9zcoa",
    "wof:name":"Jauregi Beloki Jose Javier",
    "wof:placetype":"venue"
},
  "geometry": {"coordinates":[-2.2658040524,43.1840438843],"type":"Point"}
}