{
  "type": "Feature",
  "properties": {
    "addr:full":"Avda General Franco, 3 Ramales Victoria Cantabria 39800",
    "addr:housenumber":"3",
    "addr:postcode":"39800",
    "addr:street":"Avda General Franco",
    "iso:country":"ES",
    "sg:address":"Avda General Franco, 3",
    "sg:city":"Ramales Victoria",
    "sg:orig_category":"Gastronom\u00cda: Especialidades Regionales Y Extranjeras (producci\u00d3n, Al Por Mayor)",
    "sg:phone":"+34 942 64 63 69",
    "sg:postcode":"39800",
    "sg:province":"Cantabria",
    "wof:name":"Gutierrez Busto Teresa",
    "wof:placetype":"venue"
},
  "geometry": {"coordinates":[-3.442991972,43.2613754272],"type":"Point"}
}