{
  "type": "Feature",
  "properties": {
    "addr:full":"Calle de Pocaharina, S/n Burgo M\u00e1laga 29420",
    "addr:housenumber":"s / n",
    "addr:postcode":"29420",
    "addr:street":"Calle De Pocaharina;Burgo Ma\u0301Laga",
    "iso:country":"ES",
    "sg:address":"Calle de Pocaharina, S/n",
    "sg:city":"Burgo",
    "sg:orig_category":"Bosques (trabajos, Asesor\u00cda, Gesti\u00d3n)",
    "sg:phone":"+34 952 16 03 55",
    "sg:postcode":"29420",
    "sg:province":"M\u00e1laga",
    "wof:name":"Limaco S.c.",
    "wof:placetype":"venue"
},
  "geometry": {"coordinates":[-4.9449491501,36.7896385193],"type":"Point"}
}