{
  "type": "Feature",
  "properties": {
    "addr:full":"Calle de Mayor, 134 Alcantarilla Murcia 30820",
    "addr:housenumber":"134",
    "addr:postcode":"30820",
    "addr:street":"Calle De Mayor",
    "iso:country":"ES",
    "sg:address":"Calle de Mayor, 134",
    "sg:city":"Alcantarilla",
    "sg:orig_category":"Producci\u00d3n, Distribuci\u00d3n De Gas Butano Y Propano",
    "sg:phone":"+34 968 80 07 44",
    "sg:postcode":"30820",
    "sg:province":"Murcia",
    "wof:name":"Jover Perez Jose",
    "wof:placetype":"venue"
},
  "geometry": {"coordinates":[-1.215408206,37.9689712524],"type":"Point"}
}