{
  "type": "Feature",
  "properties": {
    "iso:country":"ES",
    "sg:address":"Calle de Nueva, 61",
    "sg:city":"Tomelloso",
    "sg:orig_category":"Muebles Y Accesorios Para Cocinas Y Cuartos De Ba\u00d1o (al Por Menor)",
    "sg:phone":"+34 926 51 16 13",
    "sg:postcode":"13700",
    "sg:province":"Ciudad Real",
    "wof:name":"Casarrubio Perales Angel",
    "wof:placetype":"venue"
},
  "geometry": {"coordinates":[-3.0271520615,39.157207489],"type":"Point"}
}