{
  "type": "Feature",
  "properties": {
    "iso:country":"ES",
    "sg:address":"Calle de Eucalipto, S/n",
    "sg:city":"Poligono Industrial De Arinaga",
    "sg:orig_category":"Productos Fitosanitarios (negocio, Aplicaci\u00d3n)",
    "sg:phone":"+34 928 75 48 29",
    "sg:postcode":"35118",
    "sg:province":"Las Palmas",
    "wof:name":"Agromave S. L.",
    "wof:placetype":"venue"
},
  "geometry": {"coordinates":[-15.39277,27.855799],"type":"Point"}
}