{
  "type": "Feature",
  "properties": {
    "addr:full":"Telleria, 1 Arrasate Edo Mondragon Guip\u00f9zcoa 20500",
    "addr:housenumber":"1",
    "addr:postcode":"20500",
    "addr:street":"Telleria;Edo;Guipu\u0300Zcoa",
    "iso:country":"ES",
    "sg:address":"Telleria, 1",
    "sg:city":"Arrasate Edo Mondragon",
    "sg:orig_category":"Transporte En General",
    "sg:phone":"+34 943 79 70 58",
    "sg:postcode":"20500",
    "sg:province":"Guip\u00f9zcoa",
    "wof:name":"Tkv Logistica S.l.",
    "wof:placetype":"venue"
},
  "geometry": {"coordinates":[-2.4945991039,43.060295105],"type":"Point"}
}