{
  "type": "Feature",
  "properties": {
    "addr:full":"Calle de Corpus Christi, 47 S. Andres Rabanedo Le\u00f3n 24010",
    "addr:housenumber":"47",
    "addr:postcode":"24010",
    "addr:street":"Calle De Corpus Christi;S. Andres Rabanedo Leo\u0301N",
    "iso:country":"ES",
    "sg:address":"Calle de Corpus Christi, 47",
    "sg:city":"S. Andres Rabanedo",
    "sg:orig_category":"Agentes Generales De Seguros",
    "sg:phone":"+34 987 84 61 90",
    "sg:postcode":"24010",
    "sg:province":"Le\u00f3n",
    "wof:name":"Gonzalez De Gruyeros S.l.",
    "wof:placetype":"venue"
},
  "geometry": {"coordinates":[-5.6085300446,42.6095924377],"type":"Point"}
}