{
  "type": "Feature",
  "properties": {
    "iso:country":"ES",
    "sg:address":"Pg Vilafranca, S/n",
    "sg:city":"Sitges",
    "sg:classifiers":[
        {
            "category":"Taxi",
            "type":"Transportation"
        }
    ],
    "sg:phone":"+34 938 94 35 94",
    "sg:postcode":"08870",
    "sg:province":"Barcelona",
    "wof:name":"Asociacion Empresarial Del Taxi De Sitges",
    "wof:placetype":"venue"
},
  "geometry": {"coordinates":[1.8060526848,41.2410621643],"type":"Point"}
}