{
  "type": "Feature",
  "properties": {
    "iso:country":"ES",
    "sg:address":"Rua Rio Arnoia, S/n",
    "sg:city":"Ourense",
    "sg:orig_category":"Fabricaci\u00d3n Y Refinado De Az\u00dacares",
    "sg:phone":"+34 988 37 37 37",
    "sg:postcode":"32001",
    "sg:province":"Ourense",
    "wof:name":"Comasucar S.a.",
    "wof:placetype":"venue"
},
  "geometry": {"coordinates":[-7.8678121567,42.3509597778],"type":"Point"}
}