{
  "type": "Feature",
  "properties": {
    "iso:country":"ES",
    "sg:address":"Avda Florez Estrada, 5",
    "sg:city":"Grado",
    "sg:orig_category":"Material Y Herramientas Agr\u00cdcolas",
    "sg:phone":"+34 985 75 26 32",
    "sg:postcode":"33820",
    "sg:province":"Asturias",
    "wof:name":"Agrojardin Tamargo S.l.",
    "wof:placetype":"venue"
},
  "geometry": {"coordinates":[-6.0733656883,43.3880882263],"type":"Point"}
}