{
  "type": "Feature",
  "properties": {
    "addr:full":"Calle de Frantzisko Kortabarria, 2 Arizgoiti Vizcaya 48970",
    "addr:housenumber":"2",
    "addr:postcode":"48970",
    "addr:street":"Calle De Frantzisko Kortabarria",
    "iso:country":"ES",
    "sg:address":"Calle de Frantzisko Kortabarria, 2",
    "sg:city":"Arizgoiti",
    "sg:orig_category":"Farmacias",
    "sg:phone":"+34 944 49 05 87",
    "sg:postcode":"48970",
    "sg:province":"Vizcaya",
    "wof:name":"Gometza Onaindia Ana",
    "wof:placetype":"venue"
},
  "geometry": {"coordinates":[-2.8802866936,43.2368888855],"type":"Point"}
}