{
  "type": "Feature",
  "properties": {
    "addr:full":"Via Parque, S/n Benidorm Alicante 03500",
    "addr:housenumber":"/ n",
    "addr:postcode":"03500",
    "addr:street":"Via Parque S",
    "iso:country":"ES",
    "sg:address":"Via Parque, S/n",
    "sg:city":"Benidorm",
    "sg:orig_category":"Promotores Constructores",
    "sg:phone":"+34 965 97 20 81",
    "sg:postcode":"03500",
    "sg:province":"Alicante",
    "sg:website":"www.grupoprasa.es",
    "wof:name":"Grupo Prasa",
    "wof:placetype":"venue"
},
  "geometry": {"coordinates":[-0.1500919014,38.5402336121],"type":"Point"}
}