{
  "type": "Feature",
  "properties": {
    "addr:full":"Calle de Alfonso Ix, 3 Caceres C\u00e1ceres 10004",
    "addr:housenumber":"3",
    "addr:postcode":"10004",
    "addr:street":"Calle De Alfonso Ix;Ca\u0301Ceres",
    "iso:country":"ES",
    "sg:address":"Calle de Alfonso Ix, 3",
    "sg:city":"Caceres",
    "sg:orig_category":"Asesor\u00cda Sobre Comunicaci\u00d3n De Empresas",
    "sg:phone":"+34 927 24 32 99",
    "sg:postcode":"10004",
    "sg:province":"C\u00e1ceres",
    "wof:name":"Caballero De La Osa Maria Nieves",
    "wof:placetype":"venue"
},
  "geometry": {"coordinates":[-6.3755311966,39.4746208191],"type":"Point"}
}