{
  "type": "Feature",
  "properties": {
    "addr:full":"Carrer de Retama, 76 Viladecans Barcelona 08840",
    "addr:housenumber":"76",
    "addr:postcode":"08840",
    "addr:street":"Carrer De Retama",
    "iso:country":"ES",
    "sg:address":"Carrer de Retama, 76",
    "sg:city":"Viladecans",
    "sg:orig_category":"Equipo De Refrigeraci\u00d3n Industrial",
    "sg:phone":"+34 936 59 40 95",
    "sg:postcode":"08840",
    "sg:province":"Barcelona",
    "wof:name":"Sociedad Cooperativa Industrial Kide",
    "wof:placetype":"venue"
},
  "geometry": {"coordinates":[2.0072479248,41.3205833435],"type":"Point"}
}