{
  "type": "Feature",
  "properties": {
    "addr:full":"Carrer de Cami De Castella, 80 Estacion Alicante 03660",
    "addr:housenumber":"80",
    "addr:postcode":"03660",
    "addr:street":"Carrer De Cami De Castella",
    "iso:country":"ES",
    "sg:address":"Carrer de Cami De Castella, 80",
    "sg:city":"Estacion",
    "sg:orig_category":"Ingenier\u00cda, Centros De Estudios (diversos)",
    "sg:phone":"+34 965 60 03 91",
    "sg:postcode":"03660",
    "sg:province":"Alicante",
    "wof:name":"Sener Ingenieria Y Sistemas S.a.",
    "wof:placetype":"venue"
},
  "geometry": {"coordinates":[-0.7638189793,38.3825035095],"type":"Point"}
}