{
  "type": "Feature",
  "properties": {
    "iso:country":"ES",
    "sg:address":"Avda Primero De Mayo, 10",
    "sg:city":"Valencia",
    "sg:orig_category":"Puertas De Acorde\u00d3n Y Flexibles",
    "sg:phone":"+34 963 57 58 11",
    "sg:postcode":"46017",
    "sg:province":"Valencia",
    "wof:name":"Levantina De Divisiones S.l.",
    "wof:placetype":"venue"
},
  "geometry": {"coordinates":[-0.3868330121,39.44896698],"type":"Point"}
}