{
  "type": "Feature",
  "properties": {
    "iso:country":"ES",
    "sg:address":"Carrer de Marques De Monistrol, 18",
    "sg:city":"S. Joan Despi",
    "sg:orig_category":"Electricidad, Electr\u00d3nica: Material Y Suministros (al Por Mayor)",
    "sg:phone":"+34 933 73 13 32",
    "sg:postcode":"08970",
    "sg:province":"Barcelona",
    "wof:name":"Qnv S.l.",
    "wof:placetype":"venue"
},
  "geometry": {"coordinates":[2.0700259209,41.3722915649],"type":"Point"}
}