{
  "type": "Feature",
  "properties": {
    "iso:country":"ES",
    "sg:address":"Granada, 44",
    "sg:city":"Caravaca Cruz",
    "sg:orig_category":"Contenedores (mercanc\u00cdas)",
    "sg:phone":"+34 968 70 21 62",
    "sg:postcode":"30400",
    "sg:province":"Murcia",
    "wof:name":"Transportes Por Carretera Mata Gomez Martinez Jimenez Y Marin Sociedad Cooperativa",
    "wof:placetype":"venue"
},
  "geometry": {"coordinates":[-1.8673290014,38.0959281921],"type":"Point"}
}