{
  "type": "Feature",
  "properties": {
    "iso:country":"ES",
    "sg:address":"Estd Coru\u00d1a (da), Km. 0515,0",
    "sg:city":"Lugo",
    "sg:orig_category":"Material Y Herramientas Agr\u00cdcolas",
    "sg:phone":"+34 982 21 30 01",
    "sg:postcode":"27003",
    "sg:province":"Lugo",
    "wof:name":"Comercial Cereijo S. A.",
    "wof:placetype":"venue"
},
  "geometry": {"coordinates":[-7.5763959885,43.0335426331],"type":"Point"}
}