{
  "type": "Feature",
  "properties": {
    "addr:full":"Calle de Principe, 3 Pravia Asturias 33120",
    "addr:housenumber":"3",
    "addr:postcode":"33120",
    "addr:street":"Calle De Principe",
    "iso:country":"ES",
    "sg:address":"Calle de Principe, 3",
    "sg:city":"Pravia",
    "sg:orig_category":"Librer\u00cdas",
    "sg:phone":"+34 985 82 04 27",
    "sg:postcode":"33120",
    "sg:province":"Asturias",
    "wof:name":"Granda Quiros Maria Luisa",
    "wof:placetype":"venue"
},
  "geometry": {"coordinates":[-6.112139225,43.4893951416],"type":"Point"}
}