{
  "type": "Feature",
  "properties": {
    "addr:full":"Ctra Madrid, Km. 0387,0 Molina Segura Murcia 30500",
    "addr:postcode":"30500",
    "addr:street":"Ctra Madrid Km. 0387,0 Molina",
    "iso:country":"ES",
    "sg:address":"Ctra Madrid, Km. 0387,0",
    "sg:city":"Molina Segura",
    "sg:orig_category":"Molduras, Junquillos, Listones Y Molduras Perforadas",
    "sg:phone":"+34 968 64 17 46",
    "sg:postcode":"30500",
    "sg:province":"Murcia",
    "wof:name":"Vera Pardo Antonio",
    "wof:placetype":"venue"
},
  "geometry": {"coordinates":[-1.2119740248,38.0535736084],"type":"Point"}
}