{
  "type": "Feature",
  "properties": {
    "iso:country":"ES",
    "sg:address":"Plaz Mayor, 1",
    "sg:city":"Villadiego",
    "sg:orig_category":"Museos",
    "sg:phone":"+34 947 36 16 39",
    "sg:postcode":"09120",
    "sg:province":"Burgos",
    "wof:name":"Ayuntamiento De Villadiego",
    "wof:placetype":"venue"
},
  "geometry": {"coordinates":[-3.9843444824,42.5307044983],"type":"Point"}
}