{
  "type": "Feature",
  "properties": {
    "iso:country":"ES",
    "sg:address":"Calle de Caceres, 3",
    "sg:city":"Arroyo Luz",
    "sg:orig_category":"Comercio De Piezas De Recambio Y De Accesorios De Veh\u00cdculos, Veh\u00cdculos Industriales",
    "sg:phone":"+34 927 27 19 66",
    "sg:postcode":"10900",
    "sg:province":"C\u00e1ceres",
    "wof:name":"Santano Bonilla Casto",
    "wof:placetype":"venue"
},
  "geometry": {"coordinates":[-6.5850868225,39.4806137085],"type":"Point"}
}