{
  "type": "Feature",
  "properties": {
    "addr:full":"Hortelanos (p I Antequera), 12 Antequera M\u00e1laga 29200",
    "addr:housenumber":"12",
    "addr:postcode":"29200",
    "addr:street":"Hortelanos;Antequera",
    "iso:country":"ES",
    "sg:address":"Hortelanos (p I Antequera), 12",
    "sg:city":"Antequera",
    "sg:orig_category":"Experto Qu\u00cdmico",
    "sg:phone":"+34 952 84 56 56",
    "sg:postcode":"29200",
    "sg:province":"M\u00e1laga",
    "wof:name":"Torcalidad S.l.",
    "wof:placetype":"venue"
},
  "geometry": {"coordinates":[-4.5342841148,37.0278816223],"type":"Point"}
}