{
  "type": "Feature",
  "properties": {
    "addr:full":"Calle de Moron, 9 Puebla Cazalla Sevilla 41540",
    "addr:housenumber":"9",
    "addr:postcode":"41540",
    "addr:street":"Calle De Moron",
    "iso:country":"ES",
    "sg:address":"Calle de Moron, 9",
    "sg:city":"Puebla Cazalla",
    "sg:orig_category":"Electrodom\u00c9sticos (al Por Menor)",
    "sg:phone":"+34 954 84 72 91",
    "sg:postcode":"41540",
    "sg:province":"Sevilla",
    "wof:name":"Valero Nu\u00f1ez Miguel",
    "wof:placetype":"venue"
},
  "geometry": {"coordinates":[-5.3115158081,37.2223510742],"type":"Point"}
}