{
  "type": "Feature",
  "properties": {
    "iso:country":"ES",
    "sg:address":"Plaz Zahara, S/n",
    "sg:city":"Jerez De La Frontera",
    "sg:orig_category":"Alimentaci\u00d3n General (al Por Menor)",
    "sg:phone":"+34 956 30 60 36",
    "sg:postcode":"11405",
    "sg:province":"C\u00e1diz",
    "wof:name":"Mu\u00f1oz Cala Jesus",
    "wof:placetype":"venue"
},
  "geometry": {"coordinates":[-6.101899147,36.6950798035],"type":"Point"}
}