{
  "type": "Feature",
  "properties": {
    "addr:full":"Av Santa Eulalia, 53 Terrassa Barcelona 08223",
    "addr:housenumber":"53",
    "addr:postcode":"08223",
    "addr:street":"Av Santa Eulalia",
    "iso:country":"ES",
    "sg:address":"Av Santa Eulalia, 53",
    "sg:city":"Terrassa",
    "sg:orig_category":"Agentes, Concesionarios Y Sucursales De Veh\u00cdculos",
    "sg:phone":"+34 937 31 88 28",
    "sg:postcode":"08223",
    "sg:province":"Barcelona",
    "wof:name":"Sarsa Valles S.a.",
    "wof:placetype":"venue"
},
  "geometry": {"coordinates":[2.0133159161,41.5499572754],"type":"Point"}
}