{
  "type": "Feature",
  "properties": {
    "iso:country":"ES",
    "sg:address":"Calle de Garcilaso De La Vega, 14",
    "sg:city":"Torrelavega",
    "sg:orig_category":"Comercio De Hierro",
    "sg:phone":"+34 942 88 22 55",
    "sg:postcode":"39300",
    "sg:province":"Cantabria",
    "wof:name":"Hierros Y Aceros De Santander S.a.",
    "wof:placetype":"venue"
},
  "geometry": {"coordinates":[-4.053290844,43.3468055725],"type":"Point"}
}