{
  "type": "Feature",
  "properties": {
    "addr:full":"Calle de Cura (del), 62 Casar Caceres C\u00e1ceres 10190",
    "addr:housenumber":"62",
    "addr:postcode":"10190",
    "addr:street":"Calle De Cura Del;Ca\u0301Ceres",
    "iso:country":"ES",
    "sg:address":"Calle de Cura (del), 62",
    "sg:city":"Casar Caceres",
    "sg:orig_category":"Fabricaci\u00d3n De Quesos",
    "sg:phone":"+34 927 29 06 99",
    "sg:postcode":"10190",
    "sg:province":"C\u00e1ceres",
    "wof:name":"Barrantes Moreno Eugenio",
    "wof:placetype":"venue"
},
  "geometry": {"coordinates":[-6.4166221619,39.5583076477],"type":"Point"}
}