{
  "type": "Feature",
  "properties": {
    "iso:country":"ES",
    "sg:address":"Calle de Martinez Monta\u00d1es, 22",
    "sg:city":"Santiponce",
    "sg:orig_category":"Revestimiento De Suelos Industriales",
    "sg:phone":"+34 955 99 98 83",
    "sg:postcode":"41970",
    "sg:province":"Sevilla",
    "wof:name":"Hormian Cadiz S.l.",
    "wof:placetype":"venue"
},
  "geometry": {"coordinates":[-6.0444660187,37.4324417114],"type":"Point"}
}