{
  "type": "Feature",
  "properties": {
    "iso:country":"ES",
    "sg:address":"Calle de Capitan Haya, 23",
    "sg:city":"Madrid",
    "sg:orig_category":"Cajas De Ahorro",
    "sg:phone":"+34 915 56 71 49",
    "sg:postcode":"28020",
    "sg:province":"Madrid",
    "sg:website":"www.caixacatalunya.es",
    "wof:name":"Caixa D'estalvis De Catalunya",
    "wof:placetype":"venue"
},
  "geometry": {"coordinates":[-3.6922020912,40.45885849],"type":"Point"}
}