{
  "type": "Feature",
  "properties": {
    "iso:country":"ES",
    "sg:address":"Carrer de Teixidors (dels), 20",
    "sg:city":"Vendrell",
    "sg:orig_category":"Plomeros",
    "sg:phone":"+34 977 18 12 30",
    "sg:postcode":"43700",
    "sg:province":"Tarragona",
    "wof:name":"Cano Matilla Luis Miguel",
    "wof:placetype":"venue"
},
  "geometry": {"coordinates":[1.5290600061,41.233379364],"type":"Point"}
}