{
  "type": "Feature",
  "properties": {
    "iso:country":"ES",
    "sg:address":"Ctra Tarragona, 28",
    "sg:city":"Lleida",
    "sg:orig_category":"Productos Qu\u00cdmicos (fabricaci\u00d3n, Al Por Mayor)",
    "sg:phone":"+34 973 24 43 47",
    "sg:postcode":"25005",
    "sg:province":"Lleida",
    "wof:name":"Ruiz Bernabeu Jose",
    "wof:placetype":"venue"
},
  "geometry": {"coordinates":[0.6379060149,41.6244316101],"type":"Point"}
}