{
  "type": "Feature",
  "properties": {
    "iso:country":"ES",
    "sg:address":"Calle de Vicente Aleixandre, 2",
    "sg:city":"Miranda Ebro",
    "sg:orig_category":"Masajistas Kinesiterapeutas",
    "sg:phone":"+34 947 31 28 40",
    "sg:postcode":"09200",
    "sg:province":"Burgos",
    "wof:name":"Revuelta Andino Carmen",
    "wof:placetype":"venue"
},
  "geometry": {"coordinates":[-2.9397950172,42.6881637573],"type":"Point"}
}