{
  "type": "Feature",
  "properties": {
    "addr:full":"Calle de Rosa Del Azafran, 2 Motilla Palancar Cuenca 16200",
    "addr:housenumber":"2",
    "addr:postcode":"16200",
    "addr:street":"Calle De Rosa Del Azafran",
    "iso:country":"ES",
    "sg:address":"Calle de Rosa Del Azafran, 2",
    "sg:city":"Motilla Palancar",
    "sg:orig_category":"Fabricaci\u00d3n De Muebles",
    "sg:phone":"+34 969 33 33 22",
    "sg:postcode":"16200",
    "sg:province":"Cuenca",
    "wof:name":"Mongar Motilla S.l.",
    "wof:placetype":"venue"
},
  "geometry": {"coordinates":[-1.9159309864,39.5618286133],"type":"Point"}
}