{
  "type": "Feature",
  "properties": {
    "addr:full":"Calle de Santa Amalia, 7 Madrid Madrid 28038",
    "addr:housenumber":"7",
    "addr:postcode":"madrid;28038",
    "addr:street":"Calle De Santa Amalia",
    "iso:country":"ES",
    "sg:address":"Calle de Santa Amalia, 7",
    "sg:city":"Madrid",
    "sg:orig_category":"Empresarios Y Productoras De Espect\u00c1culos",
    "sg:phone":"+34 915 51 07 54",
    "sg:postcode":"28038",
    "sg:province":"Madrid",
    "wof:name":"Gutierrez Centeno Martin",
    "wof:placetype":"venue"
},
  "geometry": {"coordinates":[-3.6636459827,40.4019775391],"type":"Point"}
}