{
  "type": "Feature",
  "properties": {
    "addr:full":"Rond Ponent, 144 Sabadell Barcelona 08201",
    "addr:housenumber":"144",
    "addr:postcode":"08201",
    "addr:street":"Rond Ponent",
    "iso:country":"ES",
    "sg:address":"Rond Ponent, 144",
    "sg:city":"Sabadell",
    "sg:orig_category":"Comercio De Muebles De Estilo Y Contempor\u00c1neos",
    "sg:phone":"+34 937 26 73 91",
    "sg:postcode":"08201",
    "sg:province":"Barcelona",
    "wof:name":"Sofastyl S.l.",
    "wof:placetype":"venue"
},
  "geometry": {"coordinates":[2.0990738869,41.5481491089],"type":"Point"}
}