{
  "type": "Feature",
  "properties": {
    "iso:country":"ES",
    "sg:address":"Avda Asturias, 8",
    "sg:city":"Bo\u00f1ar",
    "sg:orig_category":"Molduras, Junquillos, Listones Y Molduras Perforadas",
    "sg:phone":"+34 987 73 53 45",
    "sg:postcode":"24850",
    "sg:province":"Le\u00f3n",
    "wof:name":"Gutierrez Garcia Sara",
    "wof:placetype":"venue"
},
  "geometry": {"coordinates":[-5.3200588226,42.8762664795],"type":"Point"}
}