{
  "type": "Feature",
  "properties": {
    "addr:full":"Avda Zunzunegui Juan Antonio, 4 Bilbao Vizcaya 48013",
    "addr:housenumber":"4",
    "addr:postcode":"48013",
    "addr:street":"Avda Zunzunegui Juan Antonio",
    "iso:country":"ES",
    "sg:address":"Avda Zunzunegui Juan Antonio, 4",
    "sg:city":"Bilbao",
    "sg:orig_category":"M\u00c9dicos: Cirug\u00cda Ortop\u00c9dica Y Traumatolog\u00cda",
    "sg:phone":"+34 944 41 25 33",
    "sg:postcode":"48013",
    "sg:province":"Vizcaya",
    "wof:name":"Eskutraum S.l.",
    "wof:placetype":"venue"
},
  "geometry": {"coordinates":[-2.9472250938,43.2608222961],"type":"Point"}
}