{
  "type": "Feature",
  "properties": {
    "addr:full":"Carr Marques De Campo, 4 Algemesi Valencia 46680",
    "addr:housenumber":"4",
    "addr:postcode":"46680",
    "addr:street":"Carr Marques De Campo",
    "iso:country":"ES",
    "sg:address":"Carr Marques De Campo, 4",
    "sg:city":"Algemesi",
    "sg:orig_category":"Platos Preparados Refrigerados (fabricaci\u00d3n, Al Por Mayor)",
    "sg:phone":"+34 962 42 60 46",
    "sg:postcode":"46680",
    "sg:province":"Valencia",
    "wof:name":"Fuster Celda Jose Vicente",
    "wof:placetype":"venue"
},
  "geometry": {"coordinates":[-0.4323390126,39.1898994446],"type":"Point"}
}