{
  "type": "Feature",
  "properties": {
    "iso:country":"ES",
    "sg:address":"Rbla Prim, 238",
    "sg:city":"Barcelona",
    "sg:orig_category":"Ropa Para Se\u00d1oras (al Por Menor)",
    "sg:phone":"+34 932 78 30 66",
    "sg:postcode":"08020",
    "sg:province":"Barcelona",
    "wof:name":"Vallve Diaz Mercedes",
    "wof:placetype":"venue"
},
  "geometry": {"coordinates":[2.2026410103,41.4243965149],"type":"Point"}
}