{
  "type": "Feature",
  "properties": {
    "iso:country":"ES",
    "sg:address":"Calle de Paz, 8",
    "sg:city":"Alberca De Las Torres",
    "sg:orig_category":"Grafistas",
    "sg:phone":"+34 968 84 49 49",
    "sg:postcode":"30150",
    "sg:province":"Murcia",
    "wof:name":"Montoya Bonafos Maria Dolores",
    "wof:placetype":"venue"
},
  "geometry": {"coordinates":[-1.1389189959,37.9376945496],"type":"Point"}
}