{
  "type": "Feature",
  "properties": {
    "addr:full":"Calle de General Margallo, 3 Montanchez C\u00e1ceres 10170",
    "addr:housenumber":"3",
    "addr:postcode":"10170",
    "addr:street":"Calle De General Margallo;Ca\u0301Ceres",
    "iso:country":"ES",
    "sg:address":"Calle de General Margallo, 3",
    "sg:city":"Montanchez",
    "sg:orig_category":"Cajas De Ahorro",
    "sg:phone":"+34 927 38 00 78",
    "sg:postcode":"10170",
    "sg:province":"C\u00e1ceres",
    "sg:website":"www.cajaextremadura.es",
    "wof:name":"Caja De Ahorros Y Monte De Piedad De Extremadura",
    "wof:placetype":"venue"
},
  "geometry": {"coordinates":[-6.1525287628,39.2250938416],"type":"Point"}
}