{
  "type": "Feature",
  "properties": {
    "addr:full":"Azorin, 27 Trobajo Camino Le\u00f3n 24010",
    "addr:housenumber":"27",
    "addr:postcode":"24010",
    "addr:street":"Azorin;Camino Leo\u0301N",
    "iso:country":"ES",
    "sg:address":"Azorin, 27",
    "sg:city":"Trobajo Camino",
    "sg:orig_category":"Loter\u00cda Y T\u00d3mbola",
    "sg:phone":"+34 987 80 70 97",
    "sg:postcode":"24010",
    "sg:province":"Le\u00f3n",
    "wof:name":"Martinez Rubio Cayetano",
    "wof:placetype":"venue"
},
  "geometry": {"coordinates":[-5.5894989967,42.5993499756],"type":"Point"}
}