{
  "type": "Feature",
  "properties": {
    "addr:full":"Carrer de Ildefons Cerda, 22 S. Pere Ribes Barcelona 08810",
    "addr:housenumber":"22",
    "addr:postcode":"08810",
    "addr:street":"Carrer De Ildefons Cerda;S. Pere Ribes Barcelona",
    "iso:country":"ES",
    "sg:address":"Carrer de Ildefons Cerda, 22",
    "sg:city":"S. Pere Ribes",
    "sg:orig_category":"Sociedades, Compa\u00d1\u00cdas Aseguradoras",
    "sg:phone":"+34 938 96 23 70",
    "sg:postcode":"08810",
    "sg:province":"Barcelona",
    "sg:website":"www.mapfre.es",
    "wof:name":"Mapfre Servicios De Informatica",
    "wof:placetype":"venue"
},
  "geometry": {"coordinates":[1.7751380205,41.2614059448],"type":"Point"}
}