{
  "type": "Feature",
  "properties": {
    "addr:full":"Carrer de Cuba, 7 Sabadell Barcelona 08205",
    "addr:housenumber":"7",
    "addr:postcode":"08205",
    "addr:street":"Carrer De Cuba",
    "iso:country":"ES",
    "sg:address":"Carrer de Cuba, 7",
    "sg:city":"Sabadell",
    "sg:orig_category":"Cristaler\u00cdas",
    "sg:phone":"+34 937 25 74 40",
    "sg:postcode":"08205",
    "sg:province":"Barcelona",
    "wof:name":"Vidrios Algri S.l.",
    "wof:placetype":"venue"
},
  "geometry": {"coordinates":[2.093362093,41.5450592041],"type":"Point"}
}