{
  "type": "Feature",
  "properties": {
    "addr:full":"Calle de Salvador, 7 Ponferrada Le\u00f3n 24400",
    "addr:housenumber":"7",
    "addr:postcode":"24400",
    "addr:street":"Calle De Salvador",
    "iso:country":"ES",
    "sg:address":"Calle de Salvador, 7",
    "sg:city":"Ponferrada",
    "sg:orig_category":"Molduras, Junquillos, Listones Y Molduras Perforadas",
    "sg:phone":"+34 987 40 27 66",
    "sg:postcode":"24400",
    "sg:province":"Le\u00f3n",
    "wof:name":"Garcia Corral Sofia",
    "wof:placetype":"venue"
},
  "geometry": {"coordinates":[-6.5881547928,42.5508804321],"type":"Point"}
}