{
  "type": "Feature",
  "properties": {
    "iso:country":"ES",
    "sg:address":"Calle de Palma, 12",
    "sg:city":"Ciudad Real",
    "sg:orig_category":"Reposter\u00cdas",
    "sg:phone":"+34 926 25 25 10",
    "sg:postcode":"13001",
    "sg:province":"Ciudad Real",
    "wof:name":"Buitrago Jimenez Senen",
    "wof:placetype":"venue"
},
  "geometry": {"coordinates":[-3.9255099297,38.9833374023],"type":"Point"}
}