{
  "type": "Feature",
  "properties": {
    "addr:full":"Ctra San Javier, Km. 0011,5 Huerta Y Campo De Los Ramos Murcia 30589",
    "addr:postcode":"30589",
    "addr:street":"Ctra San Javier Km. 0011,5 Huerta Y Campo De",
    "iso:country":"ES",
    "sg:address":"Ctra San Javier, Km. 0011,5",
    "sg:city":"Huerta Y Campo De Los Ramos",
    "sg:orig_category":"Metalizados",
    "sg:phone":"+34 968 87 08 62",
    "sg:postcode":"30589",
    "sg:province":"Murcia",
    "wof:name":"Micro 6 S.a.l.",
    "wof:placetype":"venue"
},
  "geometry": {"coordinates":[-1.0358589888,37.992641449],"type":"Point"}
}