{
  "type": "Feature",
  "properties": {
    "addr:full":"Calle de Bilbao, 2 Villarcayo Burgos 09550",
    "addr:housenumber":"2",
    "addr:postcode":"09550",
    "addr:street":"Calle De Bilbao",
    "iso:country":"ES",
    "sg:address":"Calle de Bilbao, 2",
    "sg:city":"Villarcayo",
    "sg:orig_category":"Pescader\u00cdas (al Por Menor)",
    "sg:phone":"+34 947 13 20 51",
    "sg:postcode":"09550",
    "sg:province":"Burgos",
    "wof:name":"Serna Fernandez Miguel Angel",
    "wof:placetype":"venue"
},
  "geometry": {"coordinates":[-3.5727629662,42.9373550415],"type":"Point"}
}