{
  "type": "Feature",
  "properties": {
    "addr:full":"Pol Ind Mercagranada, S/n Granada Granada 18015",
    "addr:housenumber":"s / n",
    "addr:postcode":"18015",
    "iso:country":"ES",
    "sg:address":"Pol Ind Mercagranada, S/n",
    "sg:city":"Granada",
    "sg:orig_category":"Agentes, Concesionarios Y Sucursales De Veh\u00cdculos",
    "sg:phone":"+34 958 80 47 54",
    "sg:postcode":"18015",
    "sg:province":"Granada",
    "wof:name":"Jag Granada S.a.",
    "wof:placetype":"venue"
},
  "geometry": {"coordinates":[-3.6356139183,37.1961364746],"type":"Point"}
}