{
  "type": "Feature",
  "properties": {
    "addr:full":"Carrer de America, 2 Terrassa Barcelona 08228",
    "addr:housenumber":"2",
    "addr:postcode":"08228",
    "addr:street":"Carrer De America",
    "iso:country":"ES",
    "sg:address":"Carrer de America, 2",
    "sg:city":"Terrassa",
    "sg:orig_category":"Molduras, Junquillos, Listones Y Molduras Perforadas",
    "sg:phone":"+34 937 85 88 08",
    "sg:postcode":"08228",
    "sg:province":"Barcelona",
    "wof:name":"Tapias Martinez Francisco",
    "wof:placetype":"venue"
},
  "geometry": {"coordinates":[2.041656971,41.5394706726],"type":"Point"}
}