{
  "type": "Feature",
  "properties": {
    "iso:country":"ES",
    "sg:address":"Carrer de Sant Medir, 15",
    "sg:city":"Barcelona",
    "sg:orig_category":"Peluquer\u00cdas, Peluquer\u00cda Mixta",
    "sg:phone":"+34 933 39 65 75",
    "sg:postcode":"08028",
    "sg:province":"Barcelona",
    "wof:name":"Podio-morales S.l.l.",
    "wof:placetype":"venue"
},
  "geometry": {"coordinates":[2.1334059238,41.373916626],"type":"Point"}
}