{
  "type": "Feature",
  "properties": {
    "addr:full":"Avda Dos De Mayo (del), 67 Mostoles Madrid 28934",
    "addr:housenumber":"67",
    "addr:postcode":"28934",
    "addr:street":"Avda Dos De Mayo Del",
    "iso:country":"ES",
    "sg:address":"Avda Dos De Mayo (del), 67",
    "sg:city":"Mostoles",
    "sg:orig_category":"Confecci\u00d3n De Trajes Para Se\u00d1oras",
    "sg:phone":"+34 916 14 88 65",
    "sg:postcode":"28934",
    "sg:province":"Madrid",
    "wof:name":"Clemente Linarejo C.b.",
    "wof:placetype":"venue"
},
  "geometry": {"coordinates":[-3.8740739822,40.3194007874],"type":"Point"}
}