{
  "type": "Feature",
  "properties": {
    "iso:country":"ES",
    "sg:address":"Avda Aves, 4",
    "sg:city":"Pla De Xirau",
    "sg:orig_category":"Perreras, Pensiones Para Perros, Gatos Y Otros Animales",
    "sg:phone":"+34 965 66 46 01",
    "sg:postcode":"03699",
    "sg:province":"Alicante",
    "wof:name":"Pastor Martin Almudena",
    "wof:placetype":"venue"
},
  "geometry": {"coordinates":[-0.5900409818,38.4633216858],"type":"Point"}
}