{
  "type": "Feature",
  "properties": {
    "iso:country":"ES",
    "sg:address":"Calle de Aurora, 7",
    "sg:city":"Linea De La Concepcion",
    "sg:orig_category":"Librer\u00cdas",
    "sg:phone":"+34 956 76 08 97",
    "sg:postcode":"11300",
    "sg:province":"C\u00e1diz",
    "wof:name":"Gil Valle Juan Eugenio",
    "wof:placetype":"venue"
},
  "geometry": {"coordinates":[-5.3490438461,36.1632652283],"type":"Point"}
}