{
  "type": "Feature",
  "properties": {
    "iso:country":"ES",
    "sg:address":"Calle de Claudio Coello, 65",
    "sg:city":"Madrid",
    "sg:orig_category":"Bisuter\u00cda, Joyer\u00cda, Relojer\u00cda (al Por Menor)",
    "sg:phone":"+34 915 75 51 76",
    "sg:postcode":"28001",
    "sg:province":"Madrid",
    "sg:website":"www.tous.es",
    "wof:name":"Tous Joyeros Madrid S.a.",
    "wof:placetype":"venue"
},
  "geometry": {"coordinates":[-3.6862840652,40.4283828735],"type":"Point"}
}