{
  "type": "Feature",
  "properties": {
    "addr:full":"Calle de Jaen, 22 Ejido Almer\u00eda 04700",
    "addr:housenumber":"22 ejido",
    "addr:postcode":"04700",
    "addr:street":"Calle De Jaen;Almeri\u0301A",
    "iso:country":"ES",
    "sg:address":"Calle de Jaen, 22",
    "sg:city":"Ejido",
    "sg:orig_category":"Bancos",
    "sg:phone":"+34 950 57 03 54",
    "sg:postcode":"04700",
    "sg:province":"Almer\u00eda",
    "wof:name":"Master Locutorios S.a.",
    "wof:placetype":"venue"
},
  "geometry": {"coordinates":[-2.8197700977,36.7732696533],"type":"Point"}
}