{
  "type": "Feature",
  "properties": {
    "addr:full":"Calle de Quevedo, 58 Gijon Asturias 33204",
    "addr:housenumber":"58",
    "addr:postcode":"33204",
    "addr:street":"Calle De Quevedo",
    "iso:country":"ES",
    "sg:address":"Calle de Quevedo, 58",
    "sg:city":"Gijon",
    "sg:orig_category":"Piedra Natural",
    "sg:phone":"+34 985 13 31 90",
    "sg:postcode":"33204",
    "sg:province":"Asturias",
    "sg:website":"www.plasticosquevedo.com",
    "wof:name":"Plasticos Quevedo S.l.",
    "wof:placetype":"venue"
},
  "geometry": {"coordinates":[-5.6490969658,43.5315704346],"type":"Point"}
}