{
  "type": "Feature",
  "properties": {
    "addr:full":"Calle de Alangobarri, 7 Algorta Vizcaya 48992",
    "addr:housenumber":"7",
    "addr:postcode":"48992",
    "addr:street":"Calle De Alangobarri",
    "iso:country":"ES",
    "sg:address":"Calle de Alangobarri, 7",
    "sg:city":"Algorta",
    "sg:orig_category":"Ense\u00d1anza, Formaci\u00d3n Profesional: Aprendizaje",
    "sg:phone":"+34 944 91 03 22",
    "sg:postcode":"48992",
    "sg:province":"Vizcaya",
    "wof:name":"Euskaltel S.a.",
    "wof:placetype":"venue"
},
  "geometry": {"coordinates":[-3.0094738007,43.3481559753],"type":"Point"}
}