{
  "type": "Feature",
  "properties": {
    "addr:full":"Calle de Perez Comendador, 7 Almendralejo Badajoz 06200",
    "addr:housenumber":"7",
    "addr:postcode":"06200",
    "addr:street":"Calle De Perez Comendador",
    "iso:country":"ES",
    "sg:address":"Calle de Perez Comendador, 7",
    "sg:city":"Almendralejo",
    "sg:orig_category":"M\u00c1rmoles, Granitos Y Piedras Naturales",
    "sg:phone":"+34 924 67 02 25",
    "sg:postcode":"06200",
    "sg:province":"Badajoz",
    "wof:name":"Marmoles Y Granitos Almendralejo C.b.",
    "wof:placetype":"venue"
},
  "geometry": {"coordinates":[-6.424932003,38.6886444092],"type":"Point"}
}