{
  "type": "Feature",
  "properties": {
    "addr:full":"Calle de Calleja (la), 10 Aguilar Campoo Palencia 34800",
    "addr:housenumber":"10",
    "addr:postcode":"34800",
    "addr:street":"Calle De Calleja La",
    "iso:country":"ES",
    "sg:address":"Calle de Calleja (la), 10",
    "sg:city":"Aguilar Campoo",
    "sg:orig_category":"Discotecas Y Salas De Baile",
    "sg:phone":"+34 979 12 21 86",
    "sg:postcode":"34800",
    "sg:province":"Palencia",
    "wof:name":"Baile Laser 99 S.l.",
    "wof:placetype":"venue"
},
  "geometry": {"coordinates":[-4.5311746597,42.0124588013],"type":"Point"}
}