{
  "type": "Feature",
  "properties": {
    "addr:full":"Carrer de Carme, 40 Barcelona Barcelona 08001",
    "addr:housenumber":"40",
    "addr:postcode":"08001",
    "addr:street":"Carrer De Carme",
    "iso:country":"ES",
    "sg:address":"Carrer de Carme, 40",
    "sg:city":"Barcelona",
    "sg:orig_category":"Tapiceros Y Tapiceros",
    "sg:phone":"+34 933 01 67 38",
    "sg:postcode":"08001",
    "sg:province":"Barcelona",
    "wof:name":"Batllo Pinadell Ana",
    "wof:placetype":"venue"
},
  "geometry": {"coordinates":[2.1697878838,41.3820838928],"type":"Point"}
}