{
  "type": "Feature",
  "properties": {
    "iso:country":"ES",
    "sg:address":"Metge Gaspar Pujol, 75",
    "sg:city":"Andratx",
    "sg:orig_category":"Reposter\u00cdas",
    "sg:phone":"+34 971 23 58 57",
    "sg:postcode":"07150",
    "sg:province":"Islas Baleares",
    "wof:name":"Villa Moreno Dolores",
    "wof:placetype":"venue"
},
  "geometry": {"coordinates":[2.4200160503,39.57264328],"type":"Point"}
}