{
  "type": "Feature",
  "properties": {
    "iso:country":"ES",
    "sg:address":"Calle de Pedro Alonso, 2",
    "sg:city":"Jerez De La Frontera",
    "sg:orig_category":"Abogados",
    "sg:phone":"+34 956 33 29 26",
    "sg:postcode":"11402",
    "sg:province":"C\u00e1diz",
    "wof:name":"Fernandez Maqueira Manuel",
    "wof:placetype":"venue"
},
  "geometry": {"coordinates":[-6.1346569061,36.6807365417],"type":"Point"}
}