{
  "type": "Feature",
  "properties": {
    "addr:full":"Carrer de Tivissa, 6 Hospitalet De L'infant Tarragona 43890",
    "addr:housenumber":"6",
    "addr:postcode":"43890",
    "addr:street":"Carrer De Tivissa",
    "iso:country":"ES",
    "sg:address":"Carrer de Tivissa, 6",
    "sg:city":"Hospitalet De L'infant",
    "sg:orig_category":"Ingenier\u00cda, Centros De Estudios (diversos)",
    "sg:phone":"+34 977 82 20 75",
    "sg:postcode":"43890",
    "sg:province":"Tarragona",
    "wof:name":"Torne Terol Virginia",
    "wof:placetype":"venue"
},
  "geometry": {"coordinates":[1.2455840111,41.1117019653],"type":"Point"}
}