{
  "type": "Feature",
  "properties": {
    "addr:full":"Carrer de Mendez Nu\u00d1ez, 10 Barcelona Barcelona 08003",
    "addr:housenumber":"10",
    "addr:postcode":"08003",
    "addr:street":"Carrer De Mendez Nun\u0303Ez",
    "iso:country":"ES",
    "sg:address":"Carrer de Mendez Nu\u00d1ez, 10",
    "sg:city":"Barcelona",
    "sg:orig_category":"Telas Y Sedas (al Por Menor)",
    "sg:phone":"+34 932 68 39 24",
    "sg:postcode":"08003",
    "sg:province":"Barcelona",
    "wof:name":"Yabar Noain Juan Manuel",
    "wof:placetype":"venue"
},
  "geometry": {"coordinates":[2.1778073311,41.3897590637],"type":"Point"}
}