{
  "type": "Feature",
  "properties": {
    "iso:country":"ES",
    "sg:address":"Trva Cordero (del), 2",
    "sg:city":"Valdemoro",
    "sg:orig_category":"Bisuter\u00cda, Joyer\u00cda, Relojer\u00cda (al Por Menor)",
    "sg:phone":"+34 918 95 63 54",
    "sg:postcode":"28340",
    "sg:province":"Madrid",
    "wof:name":"Padilla Joven Jose Francisco",
    "wof:placetype":"venue"
},
  "geometry": {"coordinates":[-3.6738090515,40.1909751892],"type":"Point"}
}