{
  "type": "Feature",
  "properties": {
    "iso:country":"ES",
    "sg:address":"Calle de Chacel, General, 9",
    "sg:city":"Melilla",
    "sg:orig_category":"Telas Y Sedas (al Por Menor)",
    "sg:phone":"+34 952 68 25 58",
    "sg:postcode":"52001",
    "sg:province":"Melilla",
    "wof:name":"Baltasar Martin E Hijos S. A.",
    "wof:placetype":"venue"
},
  "geometry": {"coordinates":[-2.940196991,35.2935638428],"type":"Point"}
}