{
  "type": "Feature",
  "properties": {
    "addr:full":"Calle de Arturo Soria, 175 Madrid Madrid 28043",
    "addr:housenumber":"175",
    "addr:postcode":"28043",
    "addr:street":"Calle De Arturo Soria",
    "iso:country":"ES",
    "sg:address":"Calle de Arturo Soria, 175",
    "sg:city":"Madrid",
    "sg:orig_category":"Distribuci\u00d3n De Petr\u00d3leo Y Derivados",
    "sg:phone":"+34 914 15 40 23",
    "sg:postcode":"28043",
    "sg:province":"Madrid",
    "wof:name":"Repsol Ypf S.a.",
    "wof:placetype":"venue"
},
  "geometry": {"coordinates":[-3.6579902172,40.4573745728],"type":"Point"}
}