{
  "type": "Feature",
  "properties": {
    "addr:full":"Ctra. Cabra, Km. 0000,5 Montilla C\u00f3rdoba 14550",
    "addr:postcode":"14550",
    "addr:street":"Ctra. Cabra Km. 0000,5;Co\u0301Rdoba",
    "iso:country":"ES",
    "sg:address":"Ctra. Cabra, Km. 0000,5",
    "sg:city":"Montilla",
    "sg:orig_category":"Bebidas",
    "sg:phone":"+34 957 65 48 71",
    "sg:postcode":"14550",
    "sg:province":"C\u00f3rdoba",
    "wof:name":"Distribuciones Gomez Velazquez S.l.",
    "wof:placetype":"venue"
},
  "geometry": {"coordinates":[-4.6404590607,37.58177948],"type":"Point"}
}