{
  "type": "Feature",
  "properties": {
    "iso:country":"ES",
    "sg:address":"Ctr. Nacional 502, Km. 0074,7",
    "sg:city":"Sevilleja De La Jara",
    "sg:orig_category":"Distribuci\u00d3n De Petr\u00d3leo Y Derivados",
    "sg:phone":"+34 925 45 50 00",
    "sg:postcode":"45671",
    "sg:province":"Toledo",
    "wof:name":"E.s. El Ripion S.l.",
    "wof:placetype":"venue"
},
  "geometry": {"coordinates":[-4.9649891853,39.5739898682],"type":"Point"}
}