{
  "type": "Feature",
  "properties": {
    "iso:country":"ES",
    "sg:address":"Calle de Garcia De Paredes, 45",
    "sg:city":"Madrid",
    "sg:orig_category":"Iglesia Cat\u00d3lica",
    "sg:phone":"+34 914 47 32 49",
    "sg:postcode":"28010",
    "sg:province":"Madrid",
    "wof:name":"Padres Paules Provincia De Madrid Curia Provincial",
    "wof:placetype":"venue"
},
  "geometry": {"coordinates":[-3.6951990128,40.4367904663],"type":"Point"}
}