{
  "type": "Feature",
  "properties": {
    "addr:full":"Calle de Juan Anglada, S/n Vera Almer\u00eda 04620",
    "addr:housenumber":"s / n;almeri\u0301a",
    "addr:postcode":"04620",
    "addr:street":"Calle De Juan Anglada",
    "iso:country":"ES",
    "sg:address":"Calle de Juan Anglada, S/n",
    "sg:city":"Vera",
    "sg:orig_category":"Abogados",
    "sg:phone":"+34 950 39 07 00",
    "sg:postcode":"04620",
    "sg:province":"Almer\u00eda",
    "wof:name":"Diez Punto Diez Servicios Inmobiliarios S.l.",
    "wof:placetype":"venue"
},
  "geometry": {"coordinates":[-1.8679189682,37.2477531433],"type":"Point"}
}