{
  "type": "Feature",
  "properties": {
    "iso:country":"ES",
    "sg:address":"Carrer de Dos De Maig, 213",
    "sg:city":"Barcelona",
    "sg:orig_category":"Molduras, Junquillos, Listones Y Molduras Perforadas",
    "sg:phone":"+34 932 45 11 05",
    "sg:postcode":"08013",
    "sg:province":"Barcelona",
    "wof:name":"Valls Font Andreu",
    "wof:placetype":"venue"
},
  "geometry": {"coordinates":[2.1836578846,41.4056549072],"type":"Point"}
}