{
  "type": "Feature",
  "properties": {
    "iso:country":"ES",
    "sg:address":"Calle de Jose Gestoso, 6",
    "sg:city":"Sevilla",
    "sg:orig_category":"Condimentos, Especias, Vinagres, Salsas Preparadas (fabricaci\u00d3n, Al Por Mayor)",
    "sg:phone":"+34 954 22 43 41",
    "sg:postcode":"41003",
    "sg:province":"Sevilla",
    "wof:name":"Francisco Chisvert S. L.",
    "wof:placetype":"venue"
},
  "geometry": {"coordinates":[-5.9927740097,37.393497467],"type":"Point"}
}