{
  "type": "Feature",
  "properties": {
    "addr:full":"Avda Jose Fernandez Ruiz, 32 Lebrija Sevilla 41740",
    "addr:housenumber":"32",
    "addr:postcode":"41740",
    "addr:street":"Avda Jose Fernandez Ruiz",
    "iso:country":"ES",
    "sg:address":"Avda Jose Fernandez Ruiz, 32",
    "sg:city":"Lebrija",
    "sg:orig_category":"Carnicer\u00cdas, Carnicer\u00cdas",
    "sg:phone":"+34 955 97 27 26",
    "sg:postcode":"41740",
    "sg:province":"Sevilla",
    "wof:name":"Montes De Jabugo S.l.",
    "wof:placetype":"venue"
},
  "geometry": {"coordinates":[-6.0686888695,36.9202728271],"type":"Point"}
}