{
  "type": "Feature",
  "properties": {
    "addr:full":"Calle de Santo Reino, 2 Benatae Ja\u00e9n 23390",
    "addr:housenumber":"2",
    "addr:postcode":"23390",
    "addr:street":"Calle De Santo Reino",
    "iso:country":"ES",
    "sg:address":"Calle de Santo Reino, 2",
    "sg:city":"Benatae",
    "sg:orig_category":"Administraciones Regionales, Departamentales Y Locales",
    "sg:phone":"+34 953 48 03 78",
    "sg:postcode":"23390",
    "sg:province":"Ja\u00e9n",
    "wof:name":"Ayuntamiento De Benatae",
    "wof:placetype":"venue"
},
  "geometry": {"coordinates":[-2.6505830288,38.352645874],"type":"Point"}
}