{
  "type": "Feature",
  "properties": {
    "addr:full":"Avda Maisonnave, 3 Alacant Alicante 03003",
    "addr:housenumber":"3",
    "addr:postcode":"03003",
    "addr:street":"Avda Maisonnave",
    "iso:country":"ES",
    "sg:address":"Avda Maisonnave, 3",
    "sg:city":"Alacant",
    "sg:orig_category":"Inmobiliaria (agencias)",
    "sg:phone":"+34 965 98 40 47",
    "sg:postcode":"03003",
    "sg:province":"Alicante",
    "wof:name":"Forex Financ Group S.l.",
    "wof:placetype":"venue"
},
  "geometry": {"coordinates":[-0.4891560078,38.3434829712],"type":"Point"}
}