{
  "type": "Feature",
  "properties": {
    "addr:full":"Avda Garat Txomin, 6 Bilbao Vizcaya 48004",
    "addr:housenumber":"6",
    "addr:postcode":"48004",
    "addr:street":"Avda Garat Txomin",
    "iso:country":"ES",
    "sg:address":"Avda Garat Txomin, 6",
    "sg:city":"Bilbao",
    "sg:orig_category":"Agencias Y Agentes Comerciales, Representantes",
    "sg:phone":"+34 944 12 79 96",
    "sg:postcode":"48004",
    "sg:province":"Vizcaya",
    "wof:name":"Nu\u00f1ez Quijada Jose Maria",
    "wof:placetype":"venue"
},
  "geometry": {"coordinates":[-2.9090509415,43.2570343018],"type":"Point"}
}