{
  "type": "Feature",
  "properties": {
    "iso:country":"ES",
    "sg:address":"Calle de Juan Martino, 2",
    "sg:city":"Cuenca",
    "sg:orig_category":"Asociaciones Humanitarias, De Cooperaci\u00d3n, De Acci\u00d3n Social",
    "sg:phone":"+34 969 23 29 29",
    "sg:postcode":"16003",
    "sg:province":"Cuenca",
    "wof:name":"Federacion Provincial De Asociaciones De Minusvalidos Fisicos De Cuenca",
    "wof:placetype":"venue"
},
  "geometry": {"coordinates":[-2.1411879063,40.0674514771],"type":"Point"}
}