{
  "type": "Feature",
  "properties": {
    "addr:full":"Calle de Pedro Aleixandre, 36 Valencia Valencia 46006",
    "addr:housenumber":"36",
    "addr:postcode":"46006",
    "addr:street":"Calle De Pedro Aleixandre",
    "iso:country":"ES",
    "sg:address":"Calle de Pedro Aleixandre, 36",
    "sg:city":"Valencia",
    "sg:orig_category":"Internados & Ense\u00d1anza Privada",
    "sg:phone":"+34 963 74 71 26",
    "sg:postcode":"46006",
    "sg:province":"Valencia",
    "wof:name":"Liceo Corbi S.l.",
    "wof:placetype":"venue"
},
  "geometry": {"coordinates":[-0.3621095121,39.4600143433],"type":"Point"}
}