{
  "type": "Feature",
  "properties": {
    "addr:full":"Diliz Escaleras, 33 Andra Mari Vizcaya 48993",
    "addr:housenumber":"33",
    "addr:postcode":"48993",
    "addr:street":"Escaleras",
    "iso:country":"ES",
    "sg:address":"Diliz Escaleras, 33",
    "sg:city":"Andra Mari",
    "sg:orig_category":"Ingenier\u00cda, Centros De Estudios (diversos)",
    "sg:phone":"+34 944 91 10 81",
    "sg:postcode":"48993",
    "sg:province":"Vizcaya",
    "wof:name":"Oliver Design S.l.",
    "wof:placetype":"venue"
},
  "geometry": {"coordinates":[-2.7541499138,43.2982711792],"type":"Point"}
}