{
  "type": "Feature",
  "properties": {
    "addr:full":"Calle de Europa, 5 Torremolinos M\u00e1laga 29620",
    "addr:housenumber":"5",
    "addr:postcode":"29620",
    "addr:street":"Calle De Europa;Ma\u0301Laga",
    "iso:country":"ES",
    "sg:address":"Calle de Europa, 5",
    "sg:city":"Torremolinos",
    "sg:orig_category":"\u00d3ptica: Instrumentos (fabricaci\u00d3n)",
    "sg:phone":"+34 952 37 20 66",
    "sg:postcode":"29620",
    "sg:province":"M\u00e1laga",
    "wof:name":"Vision Optica Europa S.l.",
    "wof:placetype":"venue"
},
  "geometry": {"coordinates":[-4.5022549629,36.6236839294],"type":"Point"}
}