{
  "type": "Feature",
  "properties": {
    "iso:country":"ES",
    "sg:address":"Carrer de Francesc Fiol I Ju, 9",
    "sg:city":"Palma",
    "sg:orig_category":"Frutas, Legumbres Frescas Y Tempranas (al Por Menor)",
    "sg:phone":"+34 971 75 59 76",
    "sg:postcode":"07010",
    "sg:province":"Islas Baleares",
    "wof:name":"Pulpillo Casas Juana",
    "wof:placetype":"venue"
},
  "geometry": {"coordinates":[2.6505069733,39.5840187073],"type":"Point"}
}