{
  "type": "Feature",
  "properties": {
    "iso:country":"ES",
    "sg:address":"Ctra Vilassar De Dalt, 25",
    "sg:city":"Floresta",
    "sg:orig_category":"Peluqueros: De Se\u00d1oras",
    "sg:phone":"+34 937 51 58 84",
    "sg:postcode":"08338",
    "sg:province":"Barcelona",
    "wof:name":"Oller Montfort Florencio",
    "wof:placetype":"venue"
},
  "geometry": {"coordinates":[2.3460769653,41.505153656],"type":"Point"}
}