{
  "type": "Feature",
  "properties": {
    "addr:full":"Calle de Mairena, 41 Alcala Guadaira Sevilla 41500",
    "addr:housenumber":"41",
    "addr:postcode":"41500",
    "addr:street":"Calle De Mairena",
    "iso:country":"ES",
    "sg:address":"Calle de Mairena, 41",
    "sg:city":"Alcala Guadaira",
    "sg:orig_category":"Ense\u00d1ante, Direcci\u00d3n",
    "sg:phone":"+34 955 68 14 24",
    "sg:postcode":"41500",
    "sg:province":"Sevilla",
    "wof:name":"Trinidad Morillo Rodrigo",
    "wof:placetype":"venue"
},
  "geometry": {"coordinates":[-5.8415088654,37.33852005],"type":"Point"}
}