{
  "type": "Feature",
  "properties": {
    "iso:country":"ES",
    "sg:address":"Ctra Vella (sant Celoni), 66",
    "sg:city":"S. Celoni",
    "sg:orig_category":"Aparcamientos (infraestructuras, Accesorios)",
    "sg:phone":"+34 938 67 09 95",
    "sg:postcode":"08470",
    "sg:province":"Barcelona",
    "wof:name":"Parking Altimira S.l.",
    "wof:placetype":"venue"
},
  "geometry": {"coordinates":[2.4914200306,41.6880187988],"type":"Point"}
}