{
  "type": "Feature",
  "properties": {
    "addr:full":"Pl Mercadal, 37 Barcelona Barcelona 08030",
    "addr:housenumber":"37",
    "addr:postcode":"08030",
    "addr:street":"Pl Mercadal",
    "iso:country":"ES",
    "sg:address":"Pl Mercadal, 37",
    "sg:city":"Barcelona",
    "sg:orig_category":"Pescader\u00cdas (al Por Menor)",
    "sg:phone":"+34 933 46 94 06",
    "sg:postcode":"08030",
    "sg:province":"Barcelona",
    "wof:name":"Marisqueria Gerard S.l.",
    "wof:placetype":"venue"
},
  "geometry": {"coordinates":[2.1888198853,41.4348678589],"type":"Point"}
}