{
  "type": "Feature",
  "properties": {
    "iso:country":"ES",
    "sg:address":"Calle de Tampico, 47",
    "sg:city":"Gasco",
    "sg:orig_category":"Prendas Deportivas (fabricaci\u00d3n)",
    "sg:phone":"+34 918 59 20 48",
    "sg:postcode":"28250",
    "sg:province":"Madrid",
    "wof:name":"Maroto De Hoyos Maria Isabel",
    "wof:placetype":"venue"
},
  "geometry": {"coordinates":[-3.7003455162,40.4166908264],"type":"Point"}
}