{
  "type": "Feature",
  "properties": {
    "addr:full":"Carrer de Sant Josep, 15 Cambrils Tarragona 43850",
    "addr:housenumber":"15",
    "addr:postcode":"43850",
    "addr:street":"Carrer De Sant Josep",
    "iso:country":"ES",
    "sg:address":"Carrer de Sant Josep, 15",
    "sg:city":"Cambrils",
    "sg:orig_category":"Fisioterapia",
    "sg:phone":"+34 977 79 54 33",
    "sg:postcode":"43850",
    "sg:province":"Tarragona",
    "wof:name":"Axis, S.c.p.",
    "wof:placetype":"venue"
},
  "geometry": {"coordinates":[1.0530250072,41.0733108521],"type":"Point"}
}