{
  "type": "Feature",
  "properties": {
    "addr:full":"Pl Marinada, 5 Badalona Barcelona 08911",
    "addr:housenumber":"5",
    "addr:postcode":"08911",
    "addr:street":"Pl Marinada",
    "iso:country":"ES",
    "sg:address":"Pl Marinada, 5",
    "sg:city":"Badalona",
    "sg:orig_category":"Inmobiliaria (agencias)",
    "sg:phone":"+34 934 64 38 01",
    "sg:postcode":"08911",
    "sg:province":"Barcelona",
    "wof:name":"Dialtex S.l.",
    "wof:placetype":"venue"
},
  "geometry": {"coordinates":[2.2577600479,41.454410553],"type":"Point"}
}