{
  "type": "Feature",
  "properties": {
    "addr:full":"Plaz Luis De Zu\u00d1iga, S/n Plasencia C\u00e1ceres 10600",
    "addr:housenumber":"s",
    "addr:postcode":"10600",
    "addr:street":"Plaz Luis De Zun\u0303Iga;/ N;Ca\u0301Ceres",
    "iso:country":"ES",
    "sg:address":"Plaz Luis De Zu\u00d1iga, S/n",
    "sg:city":"Plasencia",
    "sg:orig_category":"Molduras, Junquillos, Listones Y Molduras Perforadas",
    "sg:phone":"+34 927 41 46 06",
    "sg:postcode":"10600",
    "sg:province":"C\u00e1ceres",
    "wof:name":"Carrion Zoniga Luis",
    "wof:placetype":"venue"
},
  "geometry": {"coordinates":[-6.0833740234,40.0323448181],"type":"Point"}
}