{
  "type": "Feature",
  "properties": {
    "iso:country":"ES",
    "sg:address":"Calle de Salamanca, 29",
    "sg:city":"Valencia",
    "sg:orig_category":"Peluqueros: De Se\u00d1oras",
    "sg:phone":"+34 963 73 90 68",
    "sg:postcode":"46005",
    "sg:province":"Valencia",
    "wof:name":"Sotos Sanchez Isabel Maria",
    "wof:placetype":"venue"
},
  "geometry": {"coordinates":[-0.3641566038,39.4660873413],"type":"Point"}
}