{
  "type": "Feature",
  "properties": {
    "addr:full":"Plaz Ayuntamiento, 26 Valencia Valencia 46002",
    "addr:housenumber":"26",
    "addr:postcode":"46002",
    "addr:street":"Valencia",
    "iso:country":"ES",
    "sg:address":"Plaz Ayuntamiento, 26",
    "sg:city":"Valencia",
    "sg:orig_category":"Promotores Constructores",
    "sg:phone":"+34 963 51 80 00",
    "sg:postcode":"46002",
    "sg:province":"Valencia",
    "wof:name":"Solher Almazara S.a.",
    "wof:placetype":"venue"
},
  "geometry": {"coordinates":[-0.3760420084,39.4694366455],"type":"Point"}
}