{
  "type": "Feature",
  "properties": {
    "iso:country":"ES",
    "sg:address":"Calle de Duque De La Victoria, 13",
    "sg:city":"Valladolid",
    "sg:orig_category":"Edici\u00d3n De Diarios, Revistas, Boletines",
    "sg:phone":"+34 983 21 92 00",
    "sg:postcode":"47001",
    "sg:province":"Valladolid",
    "wof:name":"Grupo Negocios De Ediciones Y Publicaciones S.l.",
    "wof:placetype":"venue"
},
  "geometry": {"coordinates":[-4.7265853882,41.6504249573],"type":"Point"}
}