{
  "type": "Feature",
  "properties": {
    "addr:full":"Rua San Bieito, S/n Gondomar Pontevedra 36380",
    "addr:housenumber":"s / n",
    "addr:postcode":"36380",
    "addr:street":"Rua San Bieito",
    "iso:country":"ES",
    "sg:address":"Rua San Bieito, S/n",
    "sg:city":"Gondomar",
    "sg:orig_category":"Lencer\u00cda Femenina, Corseter\u00cda, Trajes De Ba\u00d1o (al Por Menor)",
    "sg:phone":"+34 986 36 90 29",
    "sg:postcode":"36380",
    "sg:province":"Pontevedra",
    "wof:name":"Almacen Nos S.l.",
    "wof:placetype":"venue"
},
  "geometry": {"coordinates":[-8.7577219009,42.1102981567],"type":"Point"}
}