{
  "type": "Feature",
  "properties": {
    "addr:full":"Avda Jose Antonio, 8 San Javier Murcia 30730",
    "addr:housenumber":"8",
    "addr:postcode":"30730",
    "addr:street":"Avda Jose Antonio",
    "iso:country":"ES",
    "sg:address":"Avda Jose Antonio, 8",
    "sg:city":"San Javier",
    "sg:orig_category":"Sociedades, Compa\u00d1\u00cdas Aseguradoras",
    "sg:phone":"+34 968 19 03 87",
    "sg:postcode":"30730",
    "sg:province":"Murcia",
    "wof:name":"Banco Vitalicio De Espa\u00f1a-compa\u00f1ia Aseguradora De Seguros Y Reaseguros",
    "wof:placetype":"venue"
},
  "geometry": {"coordinates":[-0.8367030025,37.8053131104],"type":"Point"}
}