{
  "type": "Feature",
  "properties": {
    "addr:full":"Pl S Francesc Xavier, 1 Palma Islas Baleares 07007",
    "addr:housenumber":"1",
    "addr:postcode":"07007",
    "addr:street":"Pl S Francesc Xavier",
    "iso:country":"ES",
    "sg:address":"Pl S Francesc Xavier, 1",
    "sg:city":"Palma",
    "sg:orig_category":"Institutos De Belleza",
    "sg:phone":"+34 971 24 22 38",
    "sg:postcode":"07007",
    "sg:province":"Islas Baleares",
    "wof:name":"Juan Ferriol Francisca",
    "wof:placetype":"venue"
},
  "geometry": {"coordinates":[2.6732959747,39.5723342896],"type":"Point"}
}