{
  "type": "Feature",
  "properties": {
    "addr:full":"Avda Alcalde Jose Fernandin, 21 Piedras Blancas Asturias 33450",
    "addr:housenumber":"21",
    "addr:postcode":"33450",
    "addr:street":"Avda Alcalde Jose Fernandin",
    "iso:country":"ES",
    "sg:address":"Avda Alcalde Jose Fernandin, 21",
    "sg:city":"Piedras Blancas",
    "sg:orig_category":"Muebles Y Accesorios Para Cocinas Y Cuartos De Ba\u00d1o (al Por Menor)",
    "sg:phone":"+34 985 53 04 89",
    "sg:postcode":"33450",
    "sg:province":"Asturias",
    "wof:name":"Perez Gonzalez Manuel",
    "wof:placetype":"venue"
},
  "geometry": {"coordinates":[-5.9748167992,43.5612602234],"type":"Point"}
}