{
  "type": "Feature",
  "properties": {
    "iso:country":"ES",
    "sg:address":"Calle de Venezuela, 2",
    "sg:city":"Utebo",
    "sg:orig_category":"Ropa Para Se\u00d1oras Y Caballeros (al Por Menor)",
    "sg:phone":"+34 976 77 21 67",
    "sg:postcode":"50180",
    "sg:province":"Zaragoza",
    "wof:name":"Alonso Gomez Aurelio",
    "wof:placetype":"venue"
},
  "geometry": {"coordinates":[-0.9993292093,41.7050743103],"type":"Point"}
}