{
  "type": "Feature",
  "properties": {
    "addr:full":"Calle de Torre, 32 Coru\u00d1a A Coru\u00f1a 15002",
    "addr:housenumber":"32",
    "addr:postcode":"15002",
    "addr:street":"Calle De Torre;Corun\u0303A",
    "iso:country":"ES",
    "sg:address":"Calle de Torre, 32",
    "sg:city":"Coru\u00d1a",
    "sg:orig_category":"Reposter\u00cdas",
    "sg:phone":"+34 981 20 60 75",
    "sg:postcode":"15002",
    "sg:province":"A Coru\u00f1a",
    "wof:name":"Tahona Coru\u00f1a S.l.",
    "wof:placetype":"venue"
},
  "geometry": {"coordinates":[-8.5979213715,42.8414230347],"type":"Point"}
}