{
  "type": "Feature",
  "properties": {
    "addr:full":"Calle de Laton, S/n Arganda Madrid 28500",
    "addr:housenumber":"s / n",
    "addr:postcode":"28500",
    "addr:street":"Calle De Laton",
    "iso:country":"ES",
    "sg:address":"Calle de Laton, S/n",
    "sg:city":"Arganda",
    "sg:orig_category":"Protecci\u00d3n Contra Incendios: Material, Instalaci\u00d3n, Mantenimiento",
    "sg:phone":"+34 918 71 32 71",
    "sg:postcode":"28500",
    "sg:province":"Madrid",
    "wof:name":"Contrain S. A.",
    "wof:placetype":"venue"
},
  "geometry": {"coordinates":[-3.4649729729,40.3019599915],"type":"Point"}
}