{
  "type": "Feature",
  "properties": {
    "iso:country":"ES",
    "sg:address":"Calle de Julio Gonzalez Pola, 1",
    "sg:city":"San Antonio Abad",
    "sg:classifiers":[
        {
            "category":"Banks & Credit Unions",
            "subcategory":"Bureau De Change",
            "type":"Services"
        }
    ],
    "sg:phone":"+34 968 31 13 88",
    "sg:postcode":"30205",
    "sg:province":"Murcia",
    "sg:tags":[
        "organismos",
        "control"
    ],
    "wof:name":"Ingenieria Y Tecnicas De Calidad S.l.",
    "wof:placetype":"venue"
},
  "geometry": {"coordinates":[-1.1302499771,37.9829597473],"type":"Point"}
}