{
  "type": "Feature",
  "properties": {
    "iso:country":"ES",
    "sg:address":"Calle de Arroyo De La Luz, 8",
    "sg:city":"Aliseda",
    "sg:orig_category":"Molduras, Junquillos, Listones Y Molduras Perforadas",
    "sg:phone":"+34 927 27 72 15",
    "sg:postcode":"10550",
    "sg:province":"C\u00e1ceres",
    "wof:name":"Hidalgo Alva Maria Teresa",
    "wof:placetype":"venue"
},
  "geometry": {"coordinates":[-6.6902780533,39.4226837158],"type":"Point"}
}