{
  "type": "Feature",
  "properties": {
    "addr:full":"Pg Catalunya, 4 Torroella Montgri Girona 17257",
    "addr:housenumber":"4",
    "addr:postcode":"17257",
    "addr:street":"Pg Catalunya",
    "iso:country":"ES",
    "sg:address":"Pg Catalunya, 4",
    "sg:city":"Torroella Montgri",
    "sg:orig_category":"Electricidad: Instaladores",
    "sg:phone":"+34 972 75 84 01",
    "sg:postcode":"17257",
    "sg:province":"Girona",
    "wof:name":"Insta%acions Sola Serra S.l.",
    "wof:placetype":"venue"
},
  "geometry": {"coordinates":[3.1279315948,42.0386810303],"type":"Point"}
}