{
  "type": "Feature",
  "properties": {
    "addr:full":"Rua Madrid, 3 Sanxenxo Pontevedra 36960",
    "addr:housenumber":"3",
    "addr:postcode":"36960",
    "addr:street":"Rua Madrid",
    "iso:country":"ES",
    "sg:address":"Rua Madrid, 3",
    "sg:city":"Sanxenxo",
    "sg:orig_category":"Estancos",
    "sg:phone":"+34 986 72 03 83",
    "sg:postcode":"36960",
    "sg:province":"Pontevedra",
    "wof:name":"Qui\u00f1ones Novoa Manuel",
    "wof:placetype":"venue"
},
  "geometry": {"coordinates":[-8.8072242737,42.4002189636],"type":"Point"}
}