{
  "type": "Feature",
  "properties": {
    "iso:country":"ES",
    "sg:address":"Carrer de Francesc Macia, 28",
    "sg:city":"Suredes D'en Mairo-grecs-muntanyeta",
    "sg:orig_category":"Pescader\u00cdas (al Por Menor)",
    "sg:phone":"+34 972 25 62 95",
    "sg:postcode":"17480",
    "sg:province":"Girona",
    "wof:name":"Neptuno S.c.",
    "wof:placetype":"venue"
},
  "geometry": {"coordinates":[2.8309149742,41.9964065552],"type":"Point"}
}