{
  "type": "Feature",
  "properties": {
    "addr:full":"Calle de Mesina, 4 Quinto Sevilla 41089",
    "addr:housenumber":"4",
    "addr:postcode":"41089",
    "addr:street":"Calle De Mesina",
    "iso:country":"ES",
    "sg:address":"Calle de Mesina, 4",
    "sg:city":"Quinto",
    "sg:orig_category":"Molduras, Junquillos, Listones Y Molduras Perforadas",
    "sg:phone":"+34 954 12 55 00",
    "sg:postcode":"41089",
    "sg:province":"Sevilla",
    "wof:name":"Algecir S.l.",
    "wof:placetype":"venue"
},
  "geometry": {"coordinates":[-5.9962949753,37.3826408386],"type":"Point"}
}