{
  "type": "Feature",
  "properties": {
    "iso:country":"ES",
    "sg:address":"Avda Espa\u00d1a (de), 40",
    "sg:city":"San Sebastian De Los Reyes",
    "sg:orig_category":"Alumbrados",
    "sg:phone":"+34 916 53 59 06",
    "sg:postcode":"28700",
    "sg:province":"Madrid",
    "wof:name":"Iluminacion 2000 S. L.",
    "wof:placetype":"venue"
},
  "geometry": {"coordinates":[-3.6315460205,40.5448722839],"type":"Point"}
}