{
  "type": "Feature",
  "properties": {
    "iso:country":"ES",
    "sg:address":"Avda Olimpica, 6",
    "sg:city":"Mostoles",
    "sg:orig_category":"Peluqueros: De Se\u00d1oras",
    "sg:phone":"+34 916 13 45 51",
    "sg:postcode":"28935",
    "sg:province":"Madrid",
    "wof:name":"Lopez Pizarro Patricia",
    "wof:placetype":"venue"
},
  "geometry": {"coordinates":[-3.8838670254,40.3266525269],"type":"Point"}
}