{
  "type": "Feature",
  "properties": {
    "addr:full":"Calle de Malla, 4 Riba-roja Turia Valencia 46190",
    "addr:housenumber":"4",
    "addr:postcode":"46190",
    "addr:street":"Calle De Malla",
    "iso:country":"ES",
    "sg:address":"Calle de Malla, 4",
    "sg:city":"Riba-roja Turia",
    "sg:orig_category":"Mec\u00c1nico Del Autom\u00d3vil",
    "sg:phone":"+34 961 65 37 15",
    "sg:postcode":"46190",
    "sg:province":"Valencia",
    "wof:name":"Talleres Turia S.l.",
    "wof:placetype":"venue"
},
  "geometry": {"coordinates":[-0.58031708,39.5444488525],"type":"Point"}
}