{
  "type": "Feature",
  "properties": {
    "addr:full":"Calle de Jorge Luis Borges, 8 Guadalajara Guadalajara 19004",
    "addr:housenumber":"8",
    "addr:postcode":"19004",
    "addr:street":"Calle De Jorge Luis Borges",
    "iso:country":"ES",
    "sg:address":"Calle de Jorge Luis Borges, 8",
    "sg:city":"Guadalajara",
    "sg:orig_category":"Asociaciones Y Clubs Deportivos",
    "sg:phone":"+34 949 20 03 22",
    "sg:postcode":"19004",
    "sg:province":"Guadalajara",
    "sg:website":"www.cbguadalajara.tuportal.com",
    "wof:name":"Club Baloncesto De Guadalajara",
    "wof:placetype":"venue"
},
  "geometry": {"coordinates":[-3.1810050011,40.6303329468],"type":"Point"}
}