{
  "type": "Feature",
  "properties": {
    "addr:full":"Calle de Carretera De Burgos, Km. 0012,0 Navarrete La Rioja 26370",
    "addr:postcode":"26370",
    "addr:street":"Calle De Carretera De Burgos Km. 0012,0 Navarrete",
    "iso:country":"ES",
    "sg:address":"Calle de Carretera De Burgos, Km. 0012,0",
    "sg:city":"Navarrete",
    "sg:orig_category":"Alfarer\u00cda",
    "sg:phone":"+34 941 44 03 82",
    "sg:postcode":"26370",
    "sg:province":"La Rioja",
    "sg:website":"www.corzana.com",
    "wof:name":"Alfareria Corzana Martinez S.a.",
    "wof:placetype":"venue"
},
  "geometry": {"coordinates":[-2.5653500557,42.4315834045],"type":"Point"}
}