{
  "type": "Feature",
  "properties": {
    "addr:full":"Calle de Pablo Neruda, 5 Matarredonda Sevilla 41569",
    "addr:housenumber":"5",
    "addr:postcode":"41569",
    "addr:street":"Calle De Pablo Neruda",
    "iso:country":"ES",
    "sg:address":"Calle de Pablo Neruda, 5",
    "sg:city":"Matarredonda",
    "sg:orig_category":"Institutos M\u00c9dicos",
    "sg:phone":"+34 955 91 09 10",
    "sg:postcode":"41569",
    "sg:province":"Sevilla",
    "wof:name":"Servicio Andaluz De Salud",
    "wof:placetype":"venue"
},
  "geometry": {"coordinates":[-4.9448018074,37.3770713806],"type":"Point"}
}