{
  "type": "Feature",
  "properties": {
    "iso:country":"ES",
    "sg:address":"Rava Puigverd (de), 4",
    "sg:city":"Agramunt",
    "sg:orig_category":"Agencias Y Agentes Comerciales, Representantes",
    "sg:phone":"+34 973 39 17 31",
    "sg:postcode":"25310",
    "sg:province":"Lleida",
    "wof:name":"Santamaria Pascual Francisco Javier",
    "wof:placetype":"venue"
},
  "geometry": {"coordinates":[1.0996459723,41.7865028381],"type":"Point"}
}