{
  "type": "Feature",
  "properties": {
    "addr:full":"Po. Teruel Zaragoza Zaragoza 50004",
    "addr:postcode":"50004",
    "iso:country":"ES",
    "sg:address":"Po. Teruel",
    "sg:city":"Zaragoza",
    "sg:orig_category":"Inform\u00c1tica, Ofim\u00c1tica (estudios, Asesor\u00cda, Ingenier\u00cda, Formaci\u00d3n)",
    "sg:phone":"+34 976 46 80 02",
    "sg:postcode":"50004",
    "sg:province":"Zaragoza",
    "sg:website":"www.cldie.com",
    "wof:name":"C.l.d. S.l.",
    "wof:placetype":"venue"
},
  "geometry": {"coordinates":[-0.8916609883,41.6483688354],"type":"Point"}
}