{
  "type": "Feature",
  "properties": {
    "iso:country":"ES",
    "sg:address":"Calle de Boo, 5",
    "sg:city":"Boo",
    "sg:orig_category":"Carnicer\u00cdas, Carnicer\u00cdas",
    "sg:phone":"+34 942 54 04 75",
    "sg:postcode":"39673",
    "sg:province":"Cantabria",
    "wof:name":"Escallada Del Castillo Jose Antonio",
    "wof:placetype":"venue"
},
  "geometry": {"coordinates":[-3.8385002613,43.4057197571],"type":"Point"}
}