{
  "type": "Feature",
  "properties": {
    "iso:country":"ES",
    "sg:address":"Carrer de Dos De Maig, 186",
    "sg:city":"Barcelona",
    "sg:orig_category":"Venta Al Preg\u00d3n",
    "sg:phone":"+34 932 45 92 45",
    "sg:postcode":"08013",
    "sg:province":"Barcelona",
    "wof:name":"Contreras Lopez Antonio",
    "wof:placetype":"venue"
},
  "geometry": {"coordinates":[2.1853089333,41.404800415],"type":"Point"}
}