{
  "type": "Feature",
  "properties": {
    "iso:country":"ES",
    "sg:address":"Carrer de Caballero, 39",
    "sg:city":"Barcelona",
    "sg:orig_category":"Zapatos (al Por Menor)",
    "sg:phone":"+34 934 90 18 90",
    "sg:postcode":"08014",
    "sg:province":"Barcelona",
    "wof:name":"Erliso Nolla Montse",
    "wof:placetype":"venue"
},
  "geometry": {"coordinates":[2.134677887,41.3826217651],"type":"Point"}
}