{
  "type": "Feature",
  "properties": {
    "addr:full":"Pase Eduardo Dato, 17 Madrid Madrid 28010",
    "addr:housenumber":"17",
    "addr:postcode":"madrid;28010",
    "addr:street":"Eduardo Dato",
    "iso:country":"ES",
    "sg:address":"Pase Eduardo Dato, 17",
    "sg:city":"Madrid",
    "sg:classifiers":[
        {
            "category":"Arts & Performance",
            "subcategory":"Art Gallery",
            "type":"Entertainment"
        }
    ],
    "sg:phone":"+34 913 10 07 22",
    "sg:postcode":"28010",
    "sg:province":"Madrid",
    "sg:tags":[
        "obras",
        "de",
        "coleccionismo",
        "compraventa",
        "arte",
        "y"
    ],
    "sg:website":"www.galeriadelcisne.com",
    "wof:name":"Mararte S.l.",
    "wof:placetype":"venue"
},
  "geometry": {"coordinates":[-3.6930520535,40.4330253601],"type":"Point"}
}