{
  "type": "Feature",
  "properties": {
    "addr:full":"Pla\u00c7 Catalunya, 7 Girona Girona 17002",
    "addr:housenumber":"7",
    "addr:postcode":"17002",
    "iso:country":"ES",
    "sg:address":"Pla\u00c7 Catalunya, 7",
    "sg:city":"Girona",
    "sg:orig_category":"Bisuteros (fabricaci\u00d3n, Al Por Mayor)",
    "sg:phone":"+34 972 20 40 43",
    "sg:postcode":"17002",
    "sg:province":"Girona",
    "wof:name":"Ayuso Burcet Juan Antonio",
    "wof:placetype":"venue"
},
  "geometry": {"coordinates":[2.8190748692,41.9780960083],"type":"Point"}
}