{
  "type": "Feature",
  "properties": {
    "addr:full":"Calle de Pollo Martin, 34 Salamanca Salamanca 37005",
    "addr:housenumber":"34",
    "addr:postcode":"37005",
    "addr:street":"Calle De;Martin",
    "iso:country":"ES",
    "sg:address":"Calle de Pollo Martin, 34",
    "sg:city":"Salamanca",
    "sg:orig_category":"Arquitectos",
    "sg:phone":"+34 923 25 71 70",
    "sg:postcode":"37005",
    "sg:province":"Salamanca",
    "wof:name":"Poblacion Iscar Fernando",
    "wof:placetype":"venue"
},
  "geometry": {"coordinates":[-5.6588459015,40.9709968567],"type":"Point"}
}