{
  "type": "Feature",
  "properties": {
    "addr:full":"Calle de Antonio Acu\u00d1a, 13 Madrid Madrid 28009",
    "addr:housenumber":"13",
    "addr:postcode":"madrid;28009",
    "addr:street":"Calle De Antonio Acun\u0303A",
    "iso:country":"ES",
    "sg:address":"Calle de Antonio Acu\u00d1a, 13",
    "sg:city":"Madrid",
    "sg:orig_category":"Centros De Salud",
    "sg:phone":"+34 914 35 59 68",
    "sg:postcode":"28009",
    "sg:province":"Madrid",
    "wof:name":"Fernandez Arjona Virginia",
    "wof:placetype":"venue"
},
  "geometry": {"coordinates":[-3.6788709164,40.4220733643],"type":"Point"}
}