{
  "type": "Feature",
  "properties": {
    "addr:full":"Calle de Doctor Sanchis Sivera, 19 Valencia Valencia 46008",
    "addr:housenumber":"19",
    "addr:postcode":"46008",
    "addr:street":"Calle De Doctor Sanchis Sivera",
    "iso:country":"ES",
    "sg:address":"Calle de Doctor Sanchis Sivera, 19",
    "sg:city":"Valencia",
    "sg:orig_category":"Ense\u00d1ante, Direcci\u00d3n",
    "sg:phone":"+34 963 84 25 84",
    "sg:postcode":"46008",
    "sg:province":"Valencia",
    "wof:name":"Peinado Hernandez Antonio",
    "wof:placetype":"venue"
},
  "geometry": {"coordinates":[-0.3866527975,39.4687728882],"type":"Point"}
}