{
  "type": "Feature",
  "properties": {
    "iso:country":"ES",
    "sg:address":"Psaj Hazas, 2",
    "sg:city":"Toledo",
    "sg:orig_category":"Asociaciones Humanitarias, De Cooperaci\u00d3n, De Acci\u00d3n Social",
    "sg:phone":"+34 925 22 86 47",
    "sg:postcode":"45002",
    "sg:province":"Toledo",
    "wof:name":"Consejo De Asociaciones De Pensionistas De La Provincia De Toledo",
    "wof:placetype":"venue"
},
  "geometry": {"coordinates":[-4.0266981125,39.8560142517],"type":"Point"}
}