{
  "type": "Feature",
  "properties": {
    "addr:full":"Calle de Convento (del), 5 Boadilla Del Monte Madrid 28660",
    "addr:housenumber":"5",
    "addr:postcode":"28660",
    "addr:street":"Calle De Convento Del",
    "iso:country":"ES",
    "sg:address":"Calle de Convento (del), 5",
    "sg:city":"Boadilla Del Monte",
    "sg:orig_category":"Abogados",
    "sg:phone":"+34 916 32 06 71",
    "sg:postcode":"28660",
    "sg:province":"Madrid",
    "wof:name":"Mendiguchia Gonzalez Carlos",
    "wof:placetype":"venue"
},
  "geometry": {"coordinates":[-3.8772335052,40.4067306519],"type":"Point"}
}