{
  "type": "Feature",
  "properties": {
    "iso:country":"ES",
    "sg:address":"Calle de Alheli, 9",
    "sg:city":"Sevilla",
    "sg:orig_category":"Pescader\u00cdas (al Por Menor)",
    "sg:phone":"+34 954 35 07 16",
    "sg:postcode":"41008",
    "sg:province":"Sevilla",
    "wof:name":"Martin Pereira Luis",
    "wof:placetype":"venue"
},
  "geometry": {"coordinates":[-5.9790201187,37.4038467407],"type":"Point"}
}