{
  "type": "Feature",
  "properties": {
    "iso:country":"ES",
    "sg:address":"Calle de Gonzalo De Cordoba (de), 31",
    "sg:city":"San Fernando De Henares",
    "sg:orig_category":"Art\u00cdculos De Regalo (al Por Menor)",
    "sg:phone":"+34 916 71 27 53",
    "sg:postcode":"28830",
    "sg:province":"Madrid",
    "wof:name":"Ariza Garcia Jose",
    "wof:placetype":"venue"
},
  "geometry": {"coordinates":[-3.5351014137,40.4240913391],"type":"Point"}
}