{
  "type": "Feature",
  "properties": {
    "addr:full":"Avda Arquitecto Julio Carrilero, 29 Albacete Albacete 02005",
    "addr:housenumber":"29",
    "addr:postcode":"02005",
    "addr:street":"Avda Arquitecto Julio Carrilero",
    "iso:country":"ES",
    "sg:address":"Avda Arquitecto Julio Carrilero, 29",
    "sg:city":"Albacete",
    "sg:orig_category":"Material Y Herramientas Agr\u00cdcolas",
    "sg:phone":"+34 967 22 18 47",
    "sg:postcode":"02005",
    "sg:province":"Albacete",
    "wof:name":"Herreros Belmonte Antonio",
    "wof:placetype":"venue"
},
  "geometry": {"coordinates":[-1.8646310568,38.9985580444],"type":"Point"}
}