{
  "type": "Feature",
  "properties": {
    "iso:country":"ES",
    "sg:address":"Ibargarai Hiribidea, 18",
    "sg:city":"Bergara",
    "sg:orig_category":"Inmobiliaria (agencias)",
    "sg:phone":"+34 943 76 11 18",
    "sg:postcode":"20570",
    "sg:province":"Guip\u00f9zcoa",
    "wof:name":"Ortuibar S.l.",
    "wof:placetype":"venue"
},
  "geometry": {"coordinates":[-2.4145638943,43.1164894104],"type":"Point"}
}