{
  "type": "Feature",
  "properties": {
    "iso:country":"ES",
    "sg:address":"Carrer de Sunyer, 16",
    "sg:city":"Alcanar",
    "sg:orig_category":"Asesor\u00cda Fiscal Y Jur\u00cddica",
    "sg:phone":"+34 977 73 10 87",
    "sg:postcode":"43530",
    "sg:province":"Tarragona",
    "wof:name":"Fibla Jose Xavier",
    "wof:placetype":"venue"
},
  "geometry": {"coordinates":[0.4819630086,40.5423622131],"type":"Point"}
}