{
  "type": "Feature",
  "properties": {
    "iso:country":"ES",
    "sg:address":"Plaz Padre Fontova, 2",
    "sg:city":"Alacant",
    "sg:classifiers":[
        {
            "category":"Professional",
            "subcategory":"Research",
            "type":"Services"
        }
    ],
    "sg:phone":"+34 965 22 72 22",
    "sg:postcode":"03005",
    "sg:province":"Alicante",
    "sg:tags":[
        "mercado",
        "de",
        "estudios"
    ],
    "wof:name":"Cides Estudio De Mercado S.l.",
    "wof:placetype":"venue"
},
  "geometry": {"coordinates":[-0.4804739952,38.3440856934],"type":"Point"}
}