{
  "type": "Feature",
  "properties": {
    "iso:country":"ES",
    "sg:address":"Calle de Bravo Murillo, 2",
    "sg:city":"Palmas De Gran Canaria",
    "sg:orig_category":"Abogados",
    "sg:phone":"+34 928 36 66 97",
    "sg:postcode":"35003",
    "sg:province":"Las Palmas",
    "wof:name":"Ruano Aleman Pedro",
    "wof:placetype":"venue"
},
  "geometry": {"coordinates":[-15.4179496765,28.1089363098],"type":"Point"}
}