{
  "type": "Feature",
  "properties": {
    "addr:full":"Pg Gregorio Mayans Y Siscar, 5 Oliva Valencia 46780",
    "addr:housenumber":"5",
    "addr:postcode":"46780",
    "addr:street":"Pg Gregorio Mayans Y Siscar",
    "iso:country":"ES",
    "sg:address":"Pg Gregorio Mayans Y Siscar, 5",
    "sg:city":"Oliva",
    "sg:orig_category":"Molduras, Junquillos, Listones Y Molduras Perforadas",
    "sg:phone":"+34 962 85 02 36",
    "sg:postcode":"46780",
    "sg:province":"Valencia",
    "wof:name":"Eurotel Sur S.l.",
    "wof:placetype":"venue"
},
  "geometry": {"coordinates":[-0.1142669991,38.9196281433],"type":"Point"}
}