{
  "type": "Feature",
  "properties": {
    "addr:full":"Pl Major, 1 Flix Tarragona 43750",
    "addr:housenumber":"1",
    "addr:postcode":"43750",
    "addr:street":"Pl Major",
    "iso:country":"ES",
    "sg:address":"Pl Major, 1",
    "sg:city":"Flix",
    "sg:orig_category":"Arquitectos",
    "sg:phone":"+34 977 41 00 32",
    "sg:postcode":"43750",
    "sg:province":"Tarragona",
    "wof:name":"Forcades Margalef Montserrat",
    "wof:placetype":"venue"
},
  "geometry": {"coordinates":[0.5502200127,41.2317581177],"type":"Point"}
}