{
  "type": "Feature",
  "properties": {
    "iso:country":"ES",
    "sg:address":"Av Alacant, 6",
    "sg:city":"Playa Muchavista",
    "sg:orig_category":"Agricultores, Agricultores",
    "sg:phone":"+34 965 65 00 85",
    "sg:postcode":"03560",
    "sg:province":"Alicante",
    "wof:name":"Lopez Robles Antonio",
    "wof:placetype":"venue"
},
  "geometry": {"coordinates":[-0.4101764858,38.3887557983],"type":"Point"}
}