{
  "type": "Feature",
  "properties": {
    "iso:country":"ES",
    "sg:address":"Avda Huerta Abajo, 22",
    "sg:city":"S. Lorenzo Parrilla",
    "sg:orig_category":"M\u00c1rmoles, Granitos Y Piedras Naturales",
    "sg:phone":"+34 969 29 60 79",
    "sg:postcode":"16770",
    "sg:province":"Cuenca",
    "wof:name":"Lozano Garcia Eduardo",
    "wof:placetype":"venue"
},
  "geometry": {"coordinates":[-2.361825943,39.8524398804],"type":"Point"}
}