{
  "type": "Feature",
  "properties": {
    "iso:country":"ES",
    "sg:address":"Avda Paz De (la), 6",
    "sg:city":"Logro\u00f1o",
    "sg:orig_category":"Carnicer\u00cdas, Carnicer\u00cdas",
    "sg:phone":"+34 941 24 07 92",
    "sg:postcode":"26004",
    "sg:province":"La Rioja",
    "wof:name":"Valdemoros Zapata Amelia",
    "wof:placetype":"venue"
},
  "geometry": {"coordinates":[-2.4364690781,42.4647216797],"type":"Point"}
}