{
  "type": "Feature",
  "properties": {
    "iso:country":"ES",
    "sg:address":"Avda Alcalde Cantos Ropero, S/n",
    "sg:city":"Jerez De La Frontera",
    "sg:orig_category":"Reposter\u00cdas",
    "sg:phone":"+34 956 14 26 16",
    "sg:postcode":"11408",
    "sg:province":"C\u00e1diz",
    "wof:name":"Nuevos Distribuidores Panbol S.l.",
    "wof:placetype":"venue"
},
  "geometry": {"coordinates":[-6.1276321411,36.6497344971],"type":"Point"}
}