{
  "type": "Feature",
  "properties": {
    "iso:country":"ES",
    "sg:address":"Calle de Trabajo, 17",
    "sg:city":"Utrera",
    "sg:orig_category":"Chapister\u00cda",
    "sg:phone":"+34 954 86 43 04",
    "sg:postcode":"41710",
    "sg:province":"Sevilla",
    "wof:name":"Luque Mata Pedro",
    "wof:placetype":"venue"
},
  "geometry": {"coordinates":[-5.791738987,37.195148468],"type":"Point"}
}