{
  "type": "Feature",
  "properties": {
    "addr:full":"Calle de Eugenio Frutos, 49 Guare\u00f1a Badajoz 06470",
    "addr:housenumber":"49",
    "addr:postcode":"06470",
    "addr:street":"Calle De Eugenio Frutos",
    "iso:country":"ES",
    "sg:address":"Calle de Eugenio Frutos, 49",
    "sg:city":"Guare\u00f1a",
    "sg:orig_category":"Pod\u00d3logos: Pedicuros",
    "sg:phone":"+34 924 35 20 12",
    "sg:postcode":"06470",
    "sg:province":"Badajoz",
    "wof:name":"Paredes Ledesma Francisca",
    "wof:placetype":"venue"
},
  "geometry": {"coordinates":[-6.1030788422,38.858921051],"type":"Point"}
}