{
  "type": "Feature",
  "properties": {
    "iso:country":"ES",
    "sg:address":"Calle de San Isidro, 3",
    "sg:city":"S. Isidro",
    "sg:orig_category":"Periodistas Profesionales",
    "sg:phone":"+34 965 48 58 38",
    "sg:postcode":"03349",
    "sg:province":"Alicante",
    "wof:name":"Perez Garcia Mariano",
    "wof:placetype":"venue"
},
  "geometry": {"coordinates":[-0.8398900032,38.1710968018],"type":"Point"}
}