{
  "type": "Feature",
  "properties": {
    "iso:country":"ES",
    "sg:address":"Calle de Tenderina, 119",
    "sg:city":"Oviedo",
    "sg:orig_category":"Loter\u00cda Y T\u00d3mbola",
    "sg:phone":"+34 985 20 31 60",
    "sg:postcode":"33010",
    "sg:province":"Asturias",
    "wof:name":"Uria Varela Jose",
    "wof:placetype":"venue"
},
  "geometry": {"coordinates":[-5.8282499313,43.3668708801],"type":"Point"}
}