{
  "type": "Feature",
  "properties": {
    "addr:full":"Calle de San Juan De La Pe\u00d1a, 182 Zaragoza Zaragoza 50015",
    "addr:housenumber":"182",
    "addr:postcode":"50015",
    "addr:street":"Calle De San Juan;La Pen\u0303A",
    "iso:country":"ES",
    "sg:address":"Calle de San Juan De La Pe\u00d1a, 182",
    "sg:city":"Zaragoza",
    "sg:orig_category":"Mec\u00c1nico Del Autom\u00d3vil",
    "sg:phone":"+34 976 74 31 90",
    "sg:postcode":"50015",
    "sg:province":"Zaragoza",
    "wof:name":"Talleres Lape\u00f1a S.c.",
    "wof:placetype":"venue"
},
  "geometry": {"coordinates":[-0.8708869815,41.6758537292],"type":"Point"}
}