{
  "type": "Feature",
  "properties": {
    "addr:full":"Calle de Macias Belmonte, 44 Huelva Huelva 21002",
    "addr:housenumber":"44",
    "addr:postcode":"21002",
    "addr:street":"Calle De Macias Belmonte",
    "iso:country":"ES",
    "sg:address":"Calle de Macias Belmonte, 44",
    "sg:city":"Huelva",
    "sg:orig_category":"Chapister\u00cda",
    "sg:phone":"+34 959 24 48 20",
    "sg:postcode":"21002",
    "sg:province":"Huelva",
    "wof:name":"Talleres Blasfer S.l.u",
    "wof:placetype":"venue"
},
  "geometry": {"coordinates":[-6.9571828842,37.2637634277],"type":"Point"}
}