{
  "type": "Feature",
  "properties": {
    "iso:country":"ES",
    "sg:address":"Calle de Marques De La Hermida, 15",
    "sg:city":"Santander",
    "sg:orig_category":"Crust\u00c1ceos Y Almejas (al Por Mayor)",
    "sg:phone":"+34 942 21 30 63",
    "sg:postcode":"39009",
    "sg:province":"Cantabria",
    "wof:name":"Revuelta Alcala Maria Angeles",
    "wof:placetype":"venue"
},
  "geometry": {"coordinates":[-3.815433979,43.4547805786],"type":"Point"}
}