{
  "type": "Feature",
  "properties": {
    "addr:full":"Carr Sant Cristofol, 18 Eivissa Islas Baleares 07800",
    "addr:housenumber":"18",
    "addr:postcode":"07800",
    "addr:street":"Carr Sant Cristofol",
    "iso:country":"ES",
    "sg:address":"Carr Sant Cristofol, 18",
    "sg:city":"Eivissa",
    "sg:orig_category":"Empresarios",
    "sg:phone":"+34 971 31 61 42",
    "sg:postcode":"07800",
    "sg:province":"Islas Baleares",
    "wof:name":"Soria Garcia Eusebio",
    "wof:placetype":"venue"
},
  "geometry": {"coordinates":[1.4273999929,38.9121208191],"type":"Point"}
}