{
  "type": "Feature",
  "properties": {
    "addr:full":"Retuerto Carrer de Carrer de Max Center, 60 San Vicente De Barakaldo Vizcaya 48903",
    "addr:housenumber":"60",
    "addr:postcode":"48903",
    "addr:street":"Carrer De Carrer De Max Center",
    "iso:country":"ES",
    "sg:address":"Retuerto Carrer de Carrer de Max Center, 60",
    "sg:city":"San Vicente De Barakaldo",
    "sg:orig_category":"Ropa Para Se\u00d1oras (al Por Menor)",
    "sg:phone":"+34 944 90 26 43",
    "sg:postcode":"48903",
    "sg:province":"Vizcaya",
    "sg:website":"www.puntoroma.es",
    "wof:name":"Punto Roma S.l.",
    "wof:placetype":"venue"
},
  "geometry": {"coordinates":[-3.0188579559,43.2634010315],"type":"Point"}
}