{
  "type": "Feature",
  "properties": {
    "addr:full":"Carrer de Major, 78 Castellar Valles Barcelona 08211",
    "addr:housenumber":"78",
    "addr:postcode":"08211",
    "addr:street":"Carrer De Major",
    "iso:country":"ES",
    "sg:address":"Carrer de Major, 78",
    "sg:city":"Castellar Valles",
    "sg:orig_category":"Promotores Constructores",
    "sg:phone":"+34 937 14 56 66",
    "sg:postcode":"08211",
    "sg:province":"Barcelona",
    "wof:name":"Estructures Volum 2002 S.l.",
    "wof:placetype":"venue"
},
  "geometry": {"coordinates":[2.0861558914,41.6161956787],"type":"Point"}
}