{
  "type": "Feature",
  "properties": {
    "iso:country":"ES",
    "sg:address":"Avda Madrid (de), 10",
    "sg:city":"Xinzo De Limia",
    "sg:orig_category":"Enfermeras: Consultas, Atenci\u00d3n A Domicilio",
    "sg:phone":"+34 988 46 12 57",
    "sg:postcode":"32630",
    "sg:province":"Ourense",
    "wof:name":"Gonzalez Alvarellos Maria Consuelo",
    "wof:placetype":"venue"
},
  "geometry": {"coordinates":[-7.719399929,42.060256958],"type":"Point"}
}