{
  "type": "Feature",
  "properties": {
    "iso:country":"ES",
    "sg:address":"Calle de Industria (la), 1",
    "sg:city":"Navalcarnero",
    "sg:orig_category":"Empresas De Carpinter\u00cda De Madera",
    "sg:phone":"+34 918 11 30 07",
    "sg:postcode":"28600",
    "sg:province":"Madrid",
    "wof:name":"Fuente Gonzalez Vicente Y Otros Cdad",
    "wof:placetype":"venue"
},
  "geometry": {"coordinates":[-4.0136671066,40.28490448],"type":"Point"}
}