{
  "type": "Feature",
  "properties": {
    "iso:country":"ES",
    "sg:address":"Calle de General Romero Basart, S/n",
    "sg:city":"Madrid",
    "sg:orig_category":"Guarder\u00cdas",
    "sg:phone":"+34 917 06 40 33",
    "sg:postcode":"28044",
    "sg:province":"Madrid",
    "wof:name":"Hijas De La Caridad",
    "wof:placetype":"venue"
},
  "geometry": {"coordinates":[-3.76749897,40.377658844],"type":"Point"}
}