{
  "type": "Feature",
  "properties": {
    "addr:full":"Carrer de Can Magi, 20 Barbera Valles Barcelona 08210",
    "addr:housenumber":"20",
    "addr:postcode":"08210",
    "addr:street":"Carrer De Can Magi",
    "iso:country":"ES",
    "sg:address":"Carrer de Can Magi, 20",
    "sg:city":"Barbera Valles",
    "sg:orig_category":"Fabricaci\u00d3n De Pernos, Tornillos Y Clavos",
    "sg:phone":"+34 937 29 99 60",
    "sg:postcode":"08210",
    "sg:province":"Barcelona",
    "sg:website":"ww.hispanox.com",
    "wof:name":"Hispanox S. A.",
    "wof:placetype":"venue"
},
  "geometry": {"coordinates":[2.1271760464,41.5150566101],"type":"Point"}
}