{
  "type": "Feature",
  "properties": {
    "addr:full":"Avda Moratalaz, 185 Madrid Madrid 28030",
    "addr:housenumber":"185",
    "addr:postcode":"28030",
    "addr:street":"Avda Moratalaz",
    "iso:country":"ES",
    "sg:address":"Avda Moratalaz, 185",
    "sg:city":"Madrid",
    "sg:orig_category":"Molduras, Junquillos, Listones Y Molduras Perforadas",
    "sg:phone":"+34 914 37 84 02",
    "sg:postcode":"28030",
    "sg:province":"Madrid",
    "wof:name":"La Perla Bar S.l.",
    "wof:placetype":"venue"
},
  "geometry": {"coordinates":[-3.6445219517,40.4085960388],"type":"Point"}
}