{
  "type": "Feature",
  "properties": {
    "addr:full":"Rua Doutor Xerman Alonso Hortas, 39 Lugo Lugo 27004",
    "addr:housenumber":"39",
    "addr:postcode":"27004",
    "addr:street":"Rua Doutor Xerman Alonso Hortas",
    "iso:country":"ES",
    "sg:address":"Rua Doutor Xerman Alonso Hortas, 39",
    "sg:city":"Lugo",
    "sg:orig_category":"Motocicletas (agentes, Concesionarios)",
    "sg:phone":"+34 982 21 18 97",
    "sg:postcode":"27004",
    "sg:province":"Lugo",
    "wof:name":"Lopez Perez Martin",
    "wof:placetype":"venue"
},
  "geometry": {"coordinates":[-7.5649027824,43.0125694275],"type":"Point"}
}