{
  "type": "Feature",
  "properties": {
    "addr:full":"Calle de San Isidro, 14 Majadahonda Madrid 28220",
    "addr:housenumber":"14",
    "addr:postcode":"28220",
    "addr:street":"Calle De San Isidro",
    "iso:country":"ES",
    "sg:address":"Calle de San Isidro, 14",
    "sg:city":"Majadahonda",
    "sg:orig_category":"Molduras, Junquillos, Listones Y Molduras Perforadas",
    "sg:phone":"+34 916 39 16 91",
    "sg:postcode":"28220",
    "sg:province":"Madrid",
    "wof:name":"Sistelcom-telemensaje S.a.",
    "wof:placetype":"venue"
},
  "geometry": {"coordinates":[-3.8706419468,40.4729347229],"type":"Point"}
}