{
  "type": "Feature",
  "properties": {
    "iso:country":"ES",
    "sg:address":"Pase Rollo, 78",
    "sg:city":"Salamanca",
    "sg:orig_category":"M\u00c9dicos: Estomatolog\u00cda",
    "sg:phone":"+34 923 18 37 66",
    "sg:postcode":"37003",
    "sg:province":"Salamanca",
    "wof:name":"Jose Antonio Rubio Serraller Y Maria Jose Ramos Turrion Cb",
    "wof:placetype":"venue"
},
  "geometry": {"coordinates":[-5.6488142014,40.9675178528],"type":"Point"}
}