{
  "type": "Feature",
  "properties": {
    "addr:full":"Calle de Santiago Apostol, 5 Majadahonda Madrid 28220",
    "addr:housenumber":"5",
    "addr:postcode":"28220",
    "addr:street":"Calle De Santiago Apostol",
    "iso:country":"ES",
    "sg:address":"Calle de Santiago Apostol, 5",
    "sg:city":"Majadahonda",
    "sg:orig_category":"Art\u00cdculos De Regalo (al Por Menor)",
    "sg:phone":"+34 916 39 05 81",
    "sg:postcode":"28220",
    "sg:province":"Madrid",
    "wof:name":"De Marcos Y Bonugli S.l.",
    "wof:placetype":"venue"
},
  "geometry": {"coordinates":[-3.8716220856,40.473400116],"type":"Point"}
}