{
  "type": "Feature",
  "properties": {
    "addr:full":"Calle de Padre Xifre, 5 Madrid Madrid 28002",
    "addr:housenumber":"5",
    "addr:postcode":"28002",
    "addr:street":"Calle De Padre Xifre",
    "iso:country":"ES",
    "sg:address":"Calle de Padre Xifre, 5",
    "sg:city":"Madrid",
    "sg:orig_category":"Teatro, Ballet, Danza (agrupaciones, Compa\u00d1\u00cdas)",
    "sg:phone":"+34 914 16 33 82",
    "sg:postcode":"28002",
    "sg:province":"Madrid",
    "wof:name":"Ramos Chaparro Monica",
    "wof:placetype":"venue"
},
  "geometry": {"coordinates":[-3.673032999,40.4402046204],"type":"Point"}
}