{
  "type": "Feature",
  "properties": {
    "iso:country":"ES",
    "sg:address":"Carrer de Gran De Gracia, 23",
    "sg:city":"Barcelona",
    "sg:orig_category":"Fabricaci\u00d3n, Importaci\u00d3n De L\u00c1mparas Y Bombillas",
    "sg:phone":"+34 932 17 69 96",
    "sg:postcode":"08012",
    "sg:province":"Barcelona",
    "wof:name":"Iglesias Catalan Ramon",
    "wof:placetype":"venue"
},
  "geometry": {"coordinates":[2.1567769051,41.3986244202],"type":"Point"}
}