{
  "type": "Feature",
  "properties": {
    "addr:full":"Calle de Merced La, 22 Gijon Asturias 33201",
    "addr:housenumber":"22",
    "addr:postcode":"33201",
    "addr:street":"Calle De Merced La",
    "iso:country":"ES",
    "sg:address":"Calle de Merced La, 22",
    "sg:city":"Gijon",
    "sg:orig_category":"Ense\u00d1anza: Idiomas",
    "sg:phone":"+34 985 34 44 25",
    "sg:postcode":"33201",
    "sg:province":"Asturias",
    "wof:name":"Academia Windsor Scholl C.b.",
    "wof:placetype":"venue"
},
  "geometry": {"coordinates":[-5.6622977257,43.5425643921],"type":"Point"}
}