{
  "type": "Feature",
  "properties": {
    "iso:country":"ES",
    "sg:address":"Carr Magdalena, 20",
    "sg:city":"Lleida",
    "sg:orig_category":"Prendas Y Chalecos De Punto (al Por Menor)",
    "sg:phone":"+34 973 23 73 64",
    "sg:postcode":"25007",
    "sg:province":"Lleida",
    "wof:name":"Llangostera Solsona Milagros",
    "wof:placetype":"venue"
},
  "geometry": {"coordinates":[0.6294130087,41.6186981201],"type":"Point"}
}