{
  "type": "Feature",
  "properties": {
    "iso:country":"ES",
    "sg:address":"Calle de Jeronimo Martinez, S/n",
    "sg:city":"Canales Sierra",
    "sg:orig_category":"Iglesia Cat\u00d3lica",
    "sg:phone":"+34 941 37 60 69",
    "sg:postcode":"26326",
    "sg:province":"La Rioja",
    "wof:name":"Parroquia Nuestra Se Ora De La Asucio",
    "wof:placetype":"venue"
},
  "geometry": {"coordinates":[-2.8808579445,42.3107643127],"type":"Point"}
}