{
  "type": "Feature",
  "properties": {
    "iso:country":"ES",
    "sg:address":"Avda Daroca, 318",
    "sg:city":"Madrid",
    "sg:orig_category":"Institutos De Belleza",
    "sg:phone":"+34 917 76 95 61",
    "sg:postcode":"28032",
    "sg:province":"Madrid",
    "wof:name":"Rangel Bravo Eva",
    "wof:placetype":"venue"
},
  "geometry": {"coordinates":[-3.6134769917,40.4065093994],"type":"Point"}
}