{
  "type": "Feature",
  "properties": {
    "iso:country":"ES",
    "sg:address":"Pol Ind Area Dos Cuatro, S/n",
    "sg:city":"Huercal-overa",
    "sg:orig_category":"Chapister\u00cda",
    "sg:phone":"+34 950 13 57 31",
    "sg:postcode":"04600",
    "sg:province":"Almer\u00eda",
    "wof:name":"Talleres Riendas.l.",
    "wof:placetype":"venue"
},
  "geometry": {"coordinates":[-1.7358249426,37.4396438599],"type":"Point"}
}