{
  "type": "Feature",
  "properties": {
    "addr:full":"Calle de Zamora, 23 Villaviciosa Odon Madrid 28670",
    "addr:housenumber":"23",
    "addr:postcode":"28670",
    "addr:street":"Calle De Zamora;Odon",
    "iso:country":"ES",
    "sg:address":"Calle de Zamora, 23",
    "sg:city":"Villaviciosa Odon",
    "sg:orig_category":"Inform\u00c1tica (estudios, Servicios, Asesor\u00cda, Formaci\u00d3n)",
    "sg:phone":"+34 916 16 20 15",
    "sg:postcode":"28670",
    "sg:province":"Madrid",
    "wof:name":"3 B New Age S.a.",
    "wof:placetype":"venue"
},
  "geometry": {"coordinates":[-3.883228,40.357632],"type":"Point"}
}