{
  "type": "Feature",
  "properties": {
    "addr:full":"Avda Jose Antonio, 30 Plasencia C\u00e1ceres 10600",
    "addr:housenumber":"30",
    "addr:postcode":"10600",
    "addr:street":"Avda Jose Antonio;Ca\u0301Ceres",
    "iso:country":"ES",
    "sg:address":"Avda Jose Antonio, 30",
    "sg:city":"Plasencia",
    "sg:orig_category":"Inform\u00c1tica (estudios, Servicios, Asesor\u00cda, Formaci\u00d3n)",
    "sg:phone":"+34 927 42 65 70",
    "sg:postcode":"10600",
    "sg:province":"C\u00e1ceres",
    "wof:name":"Mapfre Servicios De Informatica S.a.",
    "wof:placetype":"venue"
},
  "geometry": {"coordinates":[-6.0850172043,40.0321426392],"type":"Point"}
}