{
  "type": "Feature",
  "properties": {
    "addr:full":"Pl Josep Maluquer I Salvador, 18 Granollers Barcelona 08401",
    "addr:housenumber":"18",
    "addr:postcode":"08401",
    "addr:street":"Pl Josep Maluquer I Salvador",
    "iso:country":"ES",
    "sg:address":"Pl Josep Maluquer I Salvador, 18",
    "sg:city":"Granollers",
    "sg:orig_category":"Producci\u00d3n, Comercio De Cereales",
    "sg:phone":"+34 938 79 25 66",
    "sg:postcode":"08401",
    "sg:province":"Barcelona",
    "wof:name":"Ganados Tres S.l.",
    "wof:placetype":"venue"
},
  "geometry": {"coordinates":[2.2802755833,41.5911216736],"type":"Point"}
}