{
  "type": "Feature",
  "properties": {
    "addr:full":"Calle de San Anton, 8 Granada Granada 18005",
    "addr:housenumber":"8",
    "addr:postcode":"18005",
    "addr:street":"Calle De San Anton",
    "iso:country":"ES",
    "sg:address":"Calle de San Anton, 8",
    "sg:city":"Granada",
    "sg:orig_category":"Agencias Y Agentes Comerciales, Representantes",
    "sg:phone":"+34 958 26 06 84",
    "sg:postcode":"18005",
    "sg:province":"Granada",
    "wof:name":"Promociones Maragoa S.l.",
    "wof:placetype":"venue"
},
  "geometry": {"coordinates":[-3.6001551151,37.1721878052],"type":"Point"}
}