{
  "type": "Feature",
  "properties": {
    "addr:full":"Ctra Hospitalet, 101 Almeda Mercader Barcelona 08940",
    "addr:housenumber":"101",
    "addr:postcode":"08940",
    "addr:street":"Ctra Hospitalet;Mercader Barcelona",
    "iso:country":"ES",
    "sg:address":"Ctra Hospitalet, 101",
    "sg:city":"Almeda Mercader",
    "sg:orig_category":"Museos",
    "sg:phone":"+34 933 77 00 25",
    "sg:postcode":"08940",
    "sg:province":"Barcelona",
    "wof:name":"Ajuntament De Cornella",
    "wof:placetype":"venue"
},
  "geometry": {"coordinates":[2.085726738,41.3562507629],"type":"Point"}
}