{
  "type": "Feature",
  "properties": {
    "addr:full":"Calle de Beire, 22 Tafalla Navarra 31300",
    "addr:housenumber":"22",
    "addr:postcode":"31300",
    "addr:street":"Calle De Beire",
    "iso:country":"ES",
    "sg:address":"Calle de Beire, 22",
    "sg:city":"Tafalla",
    "sg:orig_category":"Contenedores (mercanc\u00cdas)",
    "sg:phone":"+34 948 70 33 19",
    "sg:postcode":"31300",
    "sg:province":"Navarra",
    "wof:name":"Prieto Prieto Luis",
    "wof:placetype":"venue"
},
  "geometry": {"coordinates":[-1.6737704277,42.531917572],"type":"Point"}
}