{
  "type": "Feature",
  "properties": {
    "addr:full":"Calle de Santa Teresa, 14 Molina Segura Murcia 30500",
    "addr:housenumber":"14",
    "addr:postcode":"30500",
    "addr:street":"Calle De Santa Teresa",
    "iso:country":"ES",
    "sg:address":"Calle de Santa Teresa, 14",
    "sg:city":"Molina Segura",
    "sg:orig_category":"Frutas, Legumbres Frescas Y Tempranas (al Por Menor)",
    "sg:phone":"+34 968 64 36 71",
    "sg:postcode":"30500",
    "sg:province":"Murcia",
    "wof:name":"Perez Hernandez Bernardino",
    "wof:placetype":"venue"
},
  "geometry": {"coordinates":[-1.2127790451,38.0524597168],"type":"Point"}
}