{
  "type": "Feature",
  "properties": {
    "iso:country":"ES",
    "sg:address":"Calle de Colon, 34",
    "sg:city":"Le\u00f3n",
    "sg:orig_category":"Cr\u00cda De Animales",
    "sg:phone":"+34 987 22 43 54",
    "sg:postcode":"24001",
    "sg:province":"Le\u00f3n",
    "wof:name":"Mister Dog S.l.",
    "wof:placetype":"venue"
},
  "geometry": {"coordinates":[-5.5801734924,42.5997543335],"type":"Point"}
}