{
  "type": "Feature",
  "properties": {
    "addr:full":"Calle de Espiga, 7 Mairena Alcor Sevilla 41510",
    "addr:housenumber":"7",
    "addr:postcode":"41510",
    "addr:street":"Calle De Espiga",
    "iso:country":"ES",
    "sg:address":"Calle de Espiga, 7",
    "sg:city":"Mairena Alcor",
    "sg:orig_category":"Asesor\u00cda Sobre Comunicaci\u00d3n De Empresas",
    "sg:phone":"+34 955 74 44 05",
    "sg:postcode":"41510",
    "sg:province":"Sevilla",
    "wof:name":"M.j.asesoria Y Gestion S.l.",
    "wof:placetype":"venue"
},
  "geometry": {"coordinates":[-5.7478618622,37.3745155334],"type":"Point"}
}