{
  "type": "Feature",
  "properties": {
    "addr:full":"Pol Ind Isla Mayor, S/n Isla Mayor Sevilla 41140",
    "addr:housenumber":"s / n",
    "addr:postcode":"41140",
    "addr:street":"Isla",
    "iso:country":"ES",
    "sg:address":"Pol Ind Isla Mayor, S/n",
    "sg:city":"Isla Mayor",
    "sg:orig_category":"Estudios Y Construcci\u00d3n De Acuarios Y Viveros",
    "sg:phone":"+34 955 77 33 13",
    "sg:postcode":"41140",
    "sg:province":"Sevilla",
    "wof:name":"Arroyo Y Terriza S.l.",
    "wof:placetype":"venue"
},
  "geometry": {"coordinates":[-6.1739115715,37.0725708008],"type":"Point"}
}