{
  "type": "Feature",
  "properties": {
    "iso:country":"ES",
    "sg:address":"Calle de Pedro Coca, 24",
    "sg:city":"Albacete",
    "sg:orig_category":"Art\u00cdculos De Decoraci\u00d3n",
    "sg:phone":"+34 967 22 13 37",
    "sg:postcode":"02004",
    "sg:province":"Albacete",
    "wof:name":"Enrique Garcia Gil S.l.",
    "wof:placetype":"venue"
},
  "geometry": {"coordinates":[-1.8611700535,38.9926071167],"type":"Point"}
}