{
  "type": "Feature",
  "properties": {
    "addr:full":"Calle de Juntas Generales, 49 Vitoria-gasteiz \u00c1lava 01010",
    "addr:housenumber":"49",
    "addr:postcode":"01010",
    "addr:street":"Calle De Juntas Generales",
    "iso:country":"ES",
    "sg:address":"Calle de Juntas Generales, 49",
    "sg:city":"Vitoria-gasteiz",
    "sg:orig_category":"Mercer\u00cda, Lencer\u00cda (al Por Menor)",
    "sg:phone":"+34 945 27 76 29",
    "sg:postcode":"01010",
    "sg:province":"\u00c1lava",
    "wof:name":"Picado Garcia Francisca",
    "wof:placetype":"venue"
},
  "geometry": {"coordinates":[-2.6789190769,42.8655700684],"type":"Point"}
}