{
  "type": "Feature",
  "properties": {
    "addr:full":"Calle de Santiago, 3 Olula Rio Almer\u00eda 04860",
    "addr:housenumber":"3",
    "addr:postcode":"04860",
    "addr:street":"Calle De Santiago;Almeri\u0301A",
    "iso:country":"ES",
    "sg:address":"Calle de Santiago, 3",
    "sg:city":"Olula Rio",
    "sg:orig_category":"Centros Empresariales",
    "sg:phone":"+34 950 44 00 00",
    "sg:postcode":"04860",
    "sg:province":"Almer\u00eda",
    "wof:name":"Agente Financiero Almanzora S.l.",
    "wof:placetype":"venue"
},
  "geometry": {"coordinates":[-2.2955377102,37.3553733826],"type":"Point"}
}