{
  "type": "Feature",
  "properties": {
    "iso:country":"ES",
    "sg:address":"Avda Aspe, 30",
    "sg:city":"Monforte Cid",
    "sg:orig_category":"Delegados, Agentes De Tr\u00c1nsito, Auxiliares De Transporte Internacional",
    "sg:phone":"+34 965 62 16 47",
    "sg:postcode":"03670",
    "sg:province":"Alicante",
    "wof:name":"Translidon S.l.",
    "wof:placetype":"venue"
},
  "geometry": {"coordinates":[-0.732039988,38.3787651062],"type":"Point"}
}