{
  "type": "Feature",
  "properties": {
    "iso:country":"ES",
    "sg:address":"Av Tarragona, 23",
    "sg:city":"Vilafranca Penedes",
    "sg:orig_category":"Laboratorios Y Cl\u00cdnicas Veterinarias",
    "sg:phone":"+34 938 90 03 99",
    "sg:postcode":"08720",
    "sg:province":"Barcelona",
    "wof:name":"Nutrigan S. A.",
    "wof:placetype":"venue"
},
  "geometry": {"coordinates":[1.6978729963,41.3437576294],"type":"Point"}
}