{
  "type": "Feature",
  "properties": {
    "iso:country":"ES",
    "sg:address":"Calle de Capitan Vigueras, 12",
    "sg:city":"Sevilla",
    "sg:orig_category":"Abogados",
    "sg:phone":"+34 954 54 32 00",
    "sg:postcode":"41004",
    "sg:province":"Sevilla",
    "wof:name":"Metropol S.l.",
    "wof:placetype":"venue"
},
  "geometry": {"coordinates":[-5.9854516983,37.3835334778],"type":"Point"}
}