{
  "type": "Feature",
  "properties": {
    "iso:country":"ES",
    "sg:address":"Carrer de Sant Pere, S/n",
    "sg:city":"Hospitalet De L'infant",
    "sg:orig_category":"Promotores Constructores",
    "sg:phone":"+34 977 82 20 53",
    "sg:postcode":"43890",
    "sg:province":"Tarragona",
    "sg:website":"www.reverteconstruccion.com",
    "wof:name":"Promocions I Construccions Reverte S.l.",
    "wof:placetype":"venue"
},
  "geometry": {"coordinates":[1.2540999651,41.1169281006],"type":"Point"}
}