{
  "type": "Feature",
  "properties": {
    "addr:full":"Pase Ondarreta De, 3 Donostia-san Sebastian Guip\u00f9zcoa 20008",
    "addr:housenumber":"3",
    "addr:postcode":"20008",
    "addr:street":"Ondarreta",
    "iso:country":"ES",
    "sg:address":"Pase Ondarreta De, 3",
    "sg:city":"Donostia-san Sebastian",
    "sg:orig_category":"Organizaciones Internacionales",
    "sg:phone":"+34 943 29 00 00",
    "sg:postcode":"20008",
    "sg:province":"Guip\u00f9zcoa",
    "wof:name":"Coordinadora Gesto Por La Paz",
    "wof:placetype":"venue"
},
  "geometry": {"coordinates":[-2.0402700901,43.3095817566],"type":"Point"}
}