{
  "type": "Feature",
  "properties": {
    "iso:country":"ES",
    "sg:address":"Calle de Pintor Espinosa, 14",
    "sg:city":"Cordoba",
    "sg:classifiers":[
        {
            "category":"Personal",
            "subcategory":"Barber",
            "type":"Services"
        }
    ],
    "sg:phone":"+34 957 29 99 13",
    "sg:postcode":"14004",
    "sg:province":"C\u00f3rdoba",
    "sg:tags":[
        "caballeros",
        "de",
        "peluqueros"
    ],
    "wof:name":"Delgado Navarrete Felipe",
    "wof:placetype":"venue"
},
  "geometry": {"coordinates":[-4.7925639153,37.8728179932],"type":"Point"}
}