{
  "type": "Feature",
  "properties": {
    "iso:country":"ES",
    "sg:address":"Calle de General Solchaga, 71",
    "sg:city":"Valladolid",
    "sg:orig_category":"Venta, Montaje De Neum\u00c1ticos",
    "sg:phone":"+34 983 22 86 86",
    "sg:postcode":"47008",
    "sg:province":"Valladolid",
    "sg:website":"www.uneautomoviles.com",
    "wof:name":"1 Automoviles Innovacion Y Desarrollo S.l.",
    "wof:placetype":"venue"
},
  "geometry": {"coordinates":[-4.734424,41.624706],"type":"Point"}
}