{
  "type": "Feature",
  "properties": {
    "iso:country":"ES",
    "sg:address":"Calle de Conchita Piquer, 3",
    "sg:city":"Valencia",
    "sg:orig_category":"Farmacias",
    "sg:phone":"+34 963 49 48 19",
    "sg:postcode":"46015",
    "sg:province":"Valencia",
    "wof:name":"Ferrer Llusar Juan Bautista",
    "wof:placetype":"venue"
},
  "geometry": {"coordinates":[-0.3914014101,39.4864959717],"type":"Point"}
}