{
  "type": "Feature",
  "properties": {
    "addr:full":"C/ Murillo, 1 Cerdanyola Valles Barcelona 08290",
    "addr:housenumber":"1",
    "addr:postcode":"08290",
    "addr:street":"C / Murillo;Valles Barcelona",
    "iso:country":"ES",
    "sg:address":"C/ Murillo, 1",
    "sg:city":"Cerdanyola Valles",
    "sg:orig_category":"Automatizaci\u00d3n De Procesos Industriales Y De Edificaci\u00d3n (estudios, Instalaci\u00d3n)",
    "sg:phone":"+34 935 80 64 98",
    "sg:postcode":"08290",
    "sg:province":"Barcelona",
    "wof:name":"Benito Liebana Francisco",
    "wof:placetype":"venue"
},
  "geometry": {"coordinates":[2.1470150948,41.4924812317],"type":"Point"}
}