{
  "type": "Feature",
  "properties": {
    "addr:full":"Carrer de Ferran Casablancas, 100 Sabadell Barcelona 08201",
    "addr:housenumber":"100",
    "addr:postcode":"08201",
    "addr:street":"Carrer De Ferran Casablancas",
    "iso:country":"ES",
    "sg:address":"Carrer de Ferran Casablancas, 100",
    "sg:city":"Sabadell",
    "sg:orig_category":"Centros De Coordinaci\u00d3n",
    "sg:phone":"+34 937 27 83 65",
    "sg:postcode":"08201",
    "sg:province":"Barcelona",
    "wof:name":"Llevat Escoda Aaron",
    "wof:placetype":"venue"
},
  "geometry": {"coordinates":[2.1066739559,41.5419960022],"type":"Point"}
}