{
  "type": "Feature",
  "properties": {
    "addr:full":"Calle de Bide Zaharraren Etxartea, 7 Ugao-miraballes Vizcaya 48490",
    "addr:housenumber":"7",
    "addr:postcode":"48490",
    "addr:street":"Calle De Bide;Etxartea",
    "iso:country":"ES",
    "sg:address":"Calle de Bide Zaharraren Etxartea, 7",
    "sg:city":"Ugao-miraballes",
    "sg:orig_category":"Peluqueros: De Se\u00d1oras",
    "sg:phone":"+34 946 48 21 98",
    "sg:postcode":"48490",
    "sg:province":"Vizcaya",
    "wof:name":"Garcia Martin Estibaliz",
    "wof:placetype":"venue"
},
  "geometry": {"coordinates":[-2.900121212,43.1792259216],"type":"Point"}
}