{
  "type": "Feature",
  "properties": {
    "iso:country":"ES",
    "sg:address":"Calle de Blas Infante, 5",
    "sg:city":"Herrera",
    "sg:orig_category":"Molduras, Junquillos, Listones Y Molduras Perforadas",
    "sg:phone":"+34 954 01 31 81",
    "sg:postcode":"41567",
    "sg:province":"Sevilla",
    "wof:name":"Plasencia Benjumea Gregorio",
    "wof:placetype":"venue"
},
  "geometry": {"coordinates":[-4.8500833511,37.3649215698],"type":"Point"}
}