{
  "type": "Feature",
  "properties": {
    "iso:country":"ES",
    "sg:address":"Calle de Eras, 32",
    "sg:city":"Yuncos",
    "sg:orig_category":"Promotores Constructores",
    "sg:phone":"+34 925 55 38 90",
    "sg:postcode":"45210",
    "sg:province":"Toledo",
    "wof:name":"Jeanje Conejo S.c.l.",
    "wof:placetype":"venue"
},
  "geometry": {"coordinates":[-3.8776888847,40.0879936218],"type":"Point"}
}