{
  "type": "Feature",
  "properties": {
    "iso:country":"ES",
    "sg:address":"Pg Gracia, 78",
    "sg:city":"Barcelona",
    "sg:orig_category":"Peluquer\u00cdas, Peluquer\u00cda Mixta",
    "sg:phone":"+34 932 15 41 75",
    "sg:postcode":"08008",
    "sg:province":"Barcelona",
    "wof:name":"Llongueras Poveda Ester",
    "wof:placetype":"venue"
},
  "geometry": {"coordinates":[2.1632969379,41.3939170837],"type":"Point"}
}