{
  "type": "Feature",
  "properties": {
    "addr:full":"Calle de Peregrinos (los), 7 Barranco Grande Santa Cruz De Tenerife 38108",
    "addr:housenumber":"7",
    "addr:postcode":"38108",
    "addr:street":"Calle De Peregrinos Los",
    "iso:country":"ES",
    "sg:address":"Calle de Peregrinos (los), 7",
    "sg:city":"Barranco Grande",
    "sg:orig_category":"Chapister\u00cda",
    "sg:phone":"+34 922 61 20 03",
    "sg:postcode":"38108",
    "sg:province":"Santa Cruz De Tenerife",
    "wof:name":"Barroso Sacramento Pastor",
    "wof:placetype":"venue"
},
  "geometry": {"coordinates":[-16.3074550629,28.4355430603],"type":"Point"}
}