{
  "type": "Feature",
  "properties": {
    "iso:country":"ES",
    "sg:address":"Psaj Radio (de La), 3",
    "sg:city":"Alcobendas",
    "sg:orig_category":"Ropa Para Se\u00d1oras (al Por Menor)",
    "sg:phone":"+34 916 54 44 73",
    "sg:postcode":"28100",
    "sg:province":"Madrid",
    "wof:name":"Martin Berlana Domiciana",
    "wof:placetype":"venue"
},
  "geometry": {"coordinates":[-3.6311709881,40.5415534973],"type":"Point"}
}