{
  "type": "Feature",
  "properties": {
    "iso:country":"ES",
    "sg:address":"Calle de Alfareros, 51",
    "sg:city":"Burgos",
    "sg:orig_category":"Transportes Por V\u00cdas Navegables",
    "sg:phone":"+34 947 26 04 03",
    "sg:postcode":"09001",
    "sg:province":"Burgos",
    "wof:name":"Barriuso Sanchez Virgilio",
    "wof:placetype":"venue"
},
  "geometry": {"coordinates":[-3.7013568878,42.3299064636],"type":"Point"}
}