{
  "type": "Feature",
  "properties": {
    "addr:full":"Plaz Cuba, 5 Sevilla Sevilla 41011",
    "addr:housenumber":"5",
    "addr:postcode":"41011",
    "addr:street":"Plaz Cuba",
    "iso:country":"ES",
    "sg:address":"Plaz Cuba, 5",
    "sg:city":"Sevilla",
    "sg:orig_category":"Muebles, Minoristas",
    "sg:phone":"+34 954 27 39 23",
    "sg:postcode":"41011",
    "sg:province":"Sevilla",
    "wof:name":"Loscertales Aparicio Simon",
    "wof:placetype":"venue"
},
  "geometry": {"coordinates":[-6.0018129349,37.3876953125],"type":"Point"}
}