{
  "type": "Feature",
  "properties": {
    "iso:country":"ES",
    "sg:address":"Sector D, 31",
    "sg:city":"Urb. Mas Camarena",
    "sg:classifiers":[
        {
            "category":"Arts & Performance",
            "subcategory":"Art Gallery",
            "type":"Entertainment"
        }
    ],
    "sg:phone":"+34 961 68 75 88",
    "sg:postcode":"46117",
    "sg:province":"Valencia",
    "sg:tags":[
        "arte",
        "de",
        "galer\u00cdas"
    ],
    "wof:name":"Martinez Romero Manuel",
    "wof:placetype":"venue"
},
  "geometry": {"coordinates":[-0.45985201,39.5568771362],"type":"Point"}
}