{
  "type": "Feature",
  "properties": {
    "addr:full":"Avda Ruta De La Plata, 10 Caceres C\u00e1ceres 10001",
    "addr:housenumber":"10",
    "addr:postcode":"10001",
    "addr:street":"Avda Ruta De La Plata;Ca\u0301Ceres",
    "iso:country":"ES",
    "sg:address":"Avda Ruta De La Plata, 10",
    "sg:city":"Caceres",
    "sg:orig_category":"Pintura, Barniz, Productos Asimilables (fabricaci\u00d3n, Al Por Mayor)",
    "sg:phone":"+34 927 23 05 76",
    "sg:postcode":"10001",
    "sg:province":"C\u00e1ceres",
    "wof:name":"Santillana Cerro Andres",
    "wof:placetype":"venue"
},
  "geometry": {"coordinates":[-6.3858509064,39.4706726074],"type":"Point"}
}