{
  "type": "Feature",
  "properties": {
    "iso:country":"ES",
    "sg:address":"Calle de San Antonio, 14",
    "sg:city":"Catedral",
    "sg:orig_category":"Centros De Cr\u00c9dito Inmobiliario",
    "sg:phone":"+34 968 21 88 52",
    "sg:postcode":"30001",
    "sg:province":"Murcia",
    "wof:name":"Alfredo Sancho S.l.",
    "wof:placetype":"venue"
},
  "geometry": {"coordinates":[-1.1260961294,37.9847564697],"type":"Point"}
}