{
  "type": "Feature",
  "properties": {
    "addr:full":"Calle de Juan De Juanes, 12 Bocairent Valencia 46880",
    "addr:housenumber":"12",
    "addr:postcode":"46880",
    "addr:street":"Calle De Juan De Juanes",
    "iso:country":"ES",
    "sg:address":"Calle de Juan De Juanes, 12",
    "sg:city":"Bocairent",
    "sg:orig_category":"Ingeniero",
    "sg:phone":"+34 962 35 03 79",
    "sg:postcode":"46880",
    "sg:province":"Valencia",
    "wof:name":"Castello Mora Jose Maria",
    "wof:placetype":"venue"
},
  "geometry": {"coordinates":[-0.611420989,38.766708374],"type":"Point"}
}