{
  "type": "Feature",
  "properties": {
    "iso:country":"ES",
    "sg:address":"Avda Pirenaica, 4",
    "sg:city":"Ainsa",
    "sg:orig_category":"Partidos Pol\u00cdticos",
    "sg:phone":"+34 974 50 09 75",
    "sg:postcode":"22330",
    "sg:province":"Huesca",
    "wof:name":"Partido Popular",
    "wof:placetype":"venue"
},
  "geometry": {"coordinates":[0.1405899972,42.4154434204],"type":"Point"}
}