{
  "type": "Feature",
  "properties": {
    "iso:country":"ES",
    "sg:address":"Calle de Ansite, 57",
    "sg:city":"Cruce De Arinaga",
    "sg:classifiers":[
        {
            "category":"Autos & Motor Vehicles",
            "subcategory":"Automobile Sales",
            "type":"Retail Goods"
        }
    ],
    "sg:phone":"+34 928 18 33 09",
    "sg:postcode":"35118",
    "sg:province":"Las Palmas",
    "wof:name":"Autoescuela Aguairo S. L.",
    "wof:placetype":"venue"
},
  "geometry": {"coordinates":[-15.4286527634,27.8784694672],"type":"Point"}
}