{
  "type": "Feature",
  "properties": {
    "addr:full":"Calle de Juan Carlos I, 4 Redovan Alicante 03370",
    "addr:housenumber":"4",
    "addr:postcode":"03370",
    "addr:street":"Calle De Juan Carlos I;Alicante",
    "iso:country":"ES",
    "sg:address":"Calle de Juan Carlos I, 4",
    "sg:city":"Redovan",
    "sg:orig_category":"Asesor\u00cda Sobre Comunicaci\u00d3n De Empresas",
    "sg:phone":"+34 966 75 52 59",
    "sg:postcode":"03370",
    "sg:province":"Alicante",
    "wof:name":"Asesoria Viase Sl",
    "wof:placetype":"venue"
},
  "geometry": {"coordinates":[-0.9057611227,38.1131019592],"type":"Point"}
}