{
  "type": "Feature",
  "properties": {
    "addr:full":"Pg Mare De Deu Del Coll, 240 Barcelona Barcelona 08032",
    "addr:housenumber":"240",
    "addr:postcode":"08032",
    "addr:street":"Pg Mare De Deu Del Coll",
    "iso:country":"ES",
    "sg:address":"Pg Mare De Deu Del Coll, 240",
    "sg:city":"Barcelona",
    "sg:orig_category":"Quincaller\u00cda (al Por Menor)",
    "sg:phone":"+34 934 29 63 01",
    "sg:postcode":"08032",
    "sg:province":"Barcelona",
    "wof:name":"Gomez Monros Ramon",
    "wof:placetype":"venue"
},
  "geometry": {"coordinates":[2.1515600681,41.4242210388],"type":"Point"}
}