{
  "type": "Feature",
  "properties": {
    "addr:full":"Plaz Espa\u00d1a, S/n Novillas Zaragoza 50530",
    "addr:housenumber":"s",
    "addr:postcode":"50530",
    "addr:street":"Plaz Espan\u0303A;/ N Novillas",
    "iso:country":"ES",
    "sg:address":"Plaz Espa\u00d1a, S/n",
    "sg:city":"Novillas",
    "sg:orig_category":"Comunidades Religiosas",
    "sg:phone":"+34 976 86 10 43",
    "sg:postcode":"50530",
    "sg:province":"Zaragoza",
    "wof:name":"Parroquia",
    "wof:placetype":"venue"
},
  "geometry": {"coordinates":[-1.3940589428,41.9345359802],"type":"Point"}
}