{
  "type": "Feature",
  "properties": {
    "addr:full":"Carrer de Enric Granados, 121 Barcelona Barcelona 08008",
    "addr:housenumber":"121",
    "addr:postcode":"08008",
    "addr:street":"Carrer De Enric Granados",
    "iso:country":"ES",
    "sg:address":"Carrer de Enric Granados, 121",
    "sg:city":"Barcelona",
    "sg:classifiers":[
        {
            "category":"Arts & Performance",
            "subcategory":"Art Gallery",
            "type":"Entertainment"
        }
    ],
    "sg:phone":"+34 932 37 02 39",
    "sg:postcode":"08008",
    "sg:province":"Barcelona",
    "sg:tags":[
        "arte",
        "de",
        "galer\u00cdas"
    ],
    "wof:name":"Kamatashi Group S.l.",
    "wof:placetype":"venue"
},
  "geometry": {"coordinates":[2.1547079086,41.3933868408],"type":"Point"}
}