{
  "type": "Feature",
  "properties": {
    "iso:country":"ES",
    "sg:address":"Carrer de Torrent De L'alba, 3",
    "sg:city":"Rubi",
    "sg:orig_category":"Herboristas (al Por Menor)",
    "sg:phone":"+34 936 97 86 60",
    "sg:postcode":"08191",
    "sg:province":"Barcelona",
    "wof:name":"Rovira Del Ca\u00f1o Araceli",
    "wof:placetype":"venue"
},
  "geometry": {"coordinates":[2.0342679024,41.4900741577],"type":"Point"}
}