{
  "type": "Feature",
  "properties": {
    "iso:country":"ES",
    "sg:address":"Calle de Santa Maria, S/n",
    "sg:city":"Trigueros",
    "sg:orig_category":"Forjas Y Altos Hornos",
    "sg:phone":"+34 959 30 50 19",
    "sg:postcode":"21620",
    "sg:province":"Huelva",
    "wof:name":"Talleres Asuero S.l.",
    "wof:placetype":"venue"
},
  "geometry": {"coordinates":[-6.8320140839,37.3791007996],"type":"Point"}
}