{
  "type": "Feature",
  "properties": {
    "iso:country":"ES",
    "sg:address":"Bo. Rebullon, S/n",
    "sg:city":"Rebullon",
    "sg:orig_category":"Electrodom\u00c9sticos (fabricaci\u00d3n, Al Por Mayor)",
    "sg:phone":"+34 986 28 83 00",
    "sg:postcode":"36416",
    "sg:province":"Pontevedra",
    "sg:website":"www.fagorindustrial.com",
    "wof:name":"Fagor Industrial Sociedad Cooperativa Limitada",
    "wof:placetype":"venue"
},
  "geometry": {"coordinates":[-8.6403799057,42.1906967163],"type":"Point"}
}