{
  "type": "Feature",
  "properties": {
    "iso:country":"ES",
    "sg:address":"Ctra. Carabanchel, 11",
    "sg:city":"Pozuelo",
    "sg:orig_category":"Inmobiliaria (agencias)",
    "sg:phone":"+34 913 52 18 99",
    "sg:postcode":"28223",
    "sg:province":"Madrid",
    "wof:name":"Aurogar S.l./,",
    "wof:placetype":"venue"
},
  "geometry": {"coordinates":[-3.8135514259,40.4344940186],"type":"Point"}
}