{
  "type": "Feature",
  "properties": {
    "addr:full":"Calle de Alvar Lopez, 3 Jerez De La Frontera C\u00e1diz 11403",
    "addr:housenumber":"3",
    "addr:postcode":"11403",
    "addr:street":"Calle De Alvar Lopez",
    "iso:country":"ES",
    "sg:address":"Calle de Alvar Lopez, 3",
    "sg:city":"Jerez De La Frontera",
    "sg:orig_category":"Agentes Generales De Seguros",
    "sg:phone":"+34 956 33 34 28",
    "sg:postcode":"11403",
    "sg:province":"C\u00e1diz",
    "wof:name":"Francisco Perez Georgina De",
    "wof:placetype":"venue"
},
  "geometry": {"coordinates":[-6.1380486488,36.684211731],"type":"Point"}
}