{
  "type": "Feature",
  "properties": {
    "addr:full":"Calle de Independencia, 13 Piedrabuena Ciudad Real 13100",
    "addr:housenumber":"13",
    "addr:postcode":"13100",
    "addr:street":"Calle De Independencia",
    "iso:country":"ES",
    "sg:address":"Calle de Independencia, 13",
    "sg:city":"Piedrabuena",
    "sg:orig_category":"Alimentaci\u00d3n General (al Por Menor)",
    "sg:phone":"+34 926 76 22 96",
    "sg:postcode":"13100",
    "sg:province":"Ciudad Real",
    "wof:name":"Parra Mateo Jose",
    "wof:placetype":"venue"
},
  "geometry": {"coordinates":[-4.1783189774,39.0346374512],"type":"Point"}
}