{
  "type": "Feature",
  "properties": {
    "addr:full":"Rua Margarita Taboada, 8 Carballi\u00f1o Ourense 32500",
    "addr:housenumber":"8",
    "addr:postcode":"32500",
    "addr:street":"Rua Margarita Taboada",
    "iso:country":"ES",
    "sg:address":"Rua Margarita Taboada, 8",
    "sg:city":"Carballi\u00f1o",
    "sg:orig_category":"Inmobiliaria (agencias)",
    "sg:phone":"+34 988 27 43 08",
    "sg:postcode":"32500",
    "sg:province":"Ourense",
    "wof:name":"Proade S.l.",
    "wof:placetype":"venue"
},
  "geometry": {"coordinates":[-8.0795907974,42.4297866821],"type":"Point"}
}