{
  "type": "Feature",
  "properties": {
    "iso:country":"ES",
    "sg:address":"Calle de General Franco, 55",
    "sg:city":"Caparroso",
    "sg:orig_category":"Empresas De Carpinter\u00cda De Madera",
    "sg:phone":"+34 948 73 02 32",
    "sg:postcode":"31380",
    "sg:province":"Navarra",
    "wof:name":"Carpinteria Jimenez",
    "wof:placetype":"venue"
},
  "geometry": {"coordinates":[-1.6487209797,42.3442382812],"type":"Point"}
}