{
  "type": "Feature",
  "properties": {
    "iso:country":"ES",
    "sg:address":"Ausias March, 25",
    "sg:city":"Novelda",
    "sg:orig_category":"Especias Finas (al Por Menor)",
    "sg:phone":"+34 965 62 48 84",
    "sg:postcode":"03660",
    "sg:province":"Alicante",
    "wof:name":"Especies E Infusiones La Noveldense S.l.",
    "wof:placetype":"venue"
},
  "geometry": {"coordinates":[-0.7649880052,38.3809547424],"type":"Point"}
}