{
  "type": "Feature",
  "properties": {
    "iso:country":"ES",
    "sg:address":"Psaj Loarre, 5",
    "sg:city":"Monzon",
    "sg:orig_category":"Sociedades, Compa\u00d1\u00cdas Aseguradoras",
    "sg:phone":"+34 974 41 67 10",
    "sg:postcode":"22400",
    "sg:province":"Huesca",
    "wof:name":"Prepese Sl",
    "wof:placetype":"venue"
},
  "geometry": {"coordinates":[0.1915819943,41.9130134583],"type":"Point"}
}