{
  "type": "Feature",
  "properties": {
    "iso:country":"ES",
    "sg:address":"Rua Aldara, 10",
    "sg:city":"Carballi\u00f1o",
    "sg:orig_category":"Fotograf\u00cda Art\u00cdstica Y Retratos",
    "sg:phone":"+34 988 27 23 76",
    "sg:postcode":"32500",
    "sg:province":"Ourense",
    "wof:name":"Gonzalez Calvo Jose",
    "wof:placetype":"venue"
},
  "geometry": {"coordinates":[-8.0764131546,42.4304122925],"type":"Point"}
}