{
  "type": "Feature",
  "properties": {
    "addr:full":"Carrer de Puigmarti, 16 Barcelona Barcelona 08012",
    "addr:housenumber":"16",
    "addr:postcode":"08012",
    "addr:street":"Carrer De Puigmarti",
    "iso:country":"ES",
    "sg:address":"Carrer de Puigmarti, 16",
    "sg:city":"Barcelona",
    "sg:orig_category":"Ropa Para Se\u00d1oras (al Por Menor)",
    "sg:phone":"+34 932 19 46 16",
    "sg:postcode":"08012",
    "sg:province":"Barcelona",
    "wof:name":"Suarez Bravo Montserrat",
    "wof:placetype":"venue"
},
  "geometry": {"coordinates":[2.1591789722,41.4013824463],"type":"Point"}
}