{
  "type": "Feature",
  "properties": {
    "iso:country":"ES",
    "sg:address":"Calle de Fray Diego De Cadiz, 155",
    "sg:city":"Moron Frontera",
    "sg:orig_category":"Promotores Constructores",
    "sg:phone":"+34 954 85 13 35",
    "sg:postcode":"41530",
    "sg:province":"Sevilla",
    "wof:name":"Antonio Duran Ceballos S.l.l.",
    "wof:placetype":"venue"
},
  "geometry": {"coordinates":[-5.4583678246,37.1216850281],"type":"Point"}
}