{
  "type": "Feature",
  "properties": {
    "addr:full":"Plaz Hortal (del), 21 Ariza Zaragoza 50220",
    "addr:postcode":"50220",
    "addr:street":"Plaz;Del;Ariza",
    "iso:country":"ES",
    "sg:address":"Plaz Hortal (del), 21",
    "sg:city":"Ariza",
    "sg:orig_category":"Carnes De Carnicer\u00cda (al Por Mayor)",
    "sg:phone":"+34 976 84 50 82",
    "sg:postcode":"50220",
    "sg:province":"Zaragoza",
    "wof:name":"Gonzalez Y Romero Agrocarne S.l.",
    "wof:placetype":"venue"
},
  "geometry": {"coordinates":[-2.0560126305,41.3102073669],"type":"Point"}
}