{
  "type": "Feature",
  "properties": {
    "iso:country":"ES",
    "sg:address":"Carrer de Roger De Lluria, 47",
    "sg:city":"Barcelona",
    "sg:orig_category":"Arquitectos",
    "sg:phone":"+34 934 87 89 02",
    "sg:postcode":"08009",
    "sg:province":"Barcelona",
    "wof:name":"Ordeix Romo Agustin",
    "wof:placetype":"venue"
},
  "geometry": {"coordinates":[2.1687710285,41.3929901123],"type":"Point"}
}