{
  "type": "Feature",
  "properties": {
    "addr:full":"Calle de San Lorenzo, 11 Huesca Huesca 22002",
    "addr:housenumber":"11",
    "addr:postcode":"22002",
    "addr:street":"Calle De San Lorenzo",
    "iso:country":"ES",
    "sg:address":"Calle de San Lorenzo, 11",
    "sg:city":"Huesca",
    "sg:orig_category":"Zapater\u00cdas",
    "sg:phone":"+34 974 22 91 63",
    "sg:postcode":"22002",
    "sg:province":"Huesca",
    "wof:name":"Martinez Calvo Jose Antonio",
    "wof:placetype":"venue"
},
  "geometry": {"coordinates":[-0.406035006,42.136390686],"type":"Point"}
}