{
  "type": "Feature",
  "properties": {
    "addr:full":"Carr Sant Francesc, 17 Ciutadella Menorca Islas Baleares 07760",
    "addr:housenumber":"17",
    "addr:postcode":"07760",
    "addr:street":"Carr Sant Francesc",
    "iso:country":"ES",
    "sg:address":"Carr Sant Francesc, 17",
    "sg:city":"Ciutadella Menorca",
    "sg:orig_category":"Abogados",
    "sg:phone":"+34 971 48 45 92",
    "sg:postcode":"07760",
    "sg:province":"Islas Baleares",
    "wof:name":"Davies  Lewis",
    "wof:placetype":"venue"
},
  "geometry": {"coordinates":[3.8372600079,40.0003547668],"type":"Point"}
}