{
  "type": "Feature",
  "properties": {
    "addr:full":"Calle de Jaume I, 4 Paiporta Valencia 46200",
    "addr:housenumber":"4",
    "addr:postcode":"46200",
    "addr:street":"Calle De Jaume I",
    "iso:country":"ES",
    "sg:address":"Calle de Jaume I, 4",
    "sg:city":"Paiporta",
    "sg:orig_category":"Cajas De Ahorro",
    "sg:phone":"+34 963 97 03 61",
    "sg:postcode":"46200",
    "sg:province":"Valencia",
    "wof:name":"Caixa D'estalvis I Pensions De Barcelona",
    "wof:placetype":"venue"
},
  "geometry": {"coordinates":[-0.4172590077,39.4298248291],"type":"Point"}
}