{
  "type": "Feature",
  "properties": {
    "addr:full":"Calle de Maximo Garcia Garrido, 5 Santurtzi Vizcaya 48980",
    "addr:housenumber":"5",
    "addr:postcode":"48980",
    "addr:street":"Calle De Maximo Garcia Garrido",
    "iso:country":"ES",
    "sg:address":"Calle de Maximo Garcia Garrido, 5",
    "sg:city":"Santurtzi",
    "sg:classifiers":[
        {
            "category":"Personal",
            "subcategory":"Barber",
            "type":"Services"
        }
    ],
    "sg:phone":"+34 944 62 18 59",
    "sg:postcode":"48980",
    "sg:province":"Vizcaya",
    "sg:tags":[
        "caballeros",
        "de",
        "peluqueros"
    ],
    "wof:name":"Juan Manso Carvajal",
    "wof:placetype":"venue"
},
  "geometry": {"coordinates":[-3.0327899456,43.3271713257],"type":"Point"}
}