{
  "type": "Feature",
  "properties": {
    "iso:country":"ES",
    "sg:address":"Calle de Naranjo De Bulnes, 2",
    "sg:city":"Gijon",
    "sg:orig_category":"Inmobiliaria (agencias)",
    "sg:phone":"+34 985 38 69 43",
    "sg:postcode":"33211",
    "sg:province":"Asturias",
    "wof:name":"Inmobiliaria Nuevo Gijon S. A.",
    "wof:placetype":"venue"
},
  "geometry": {"coordinates":[-5.6796498299,43.5257606506],"type":"Point"}
}