{
  "type": "Feature",
  "properties": {
    "iso:country":"ES",
    "sg:address":"Plaz Espa\u00d1a, 4",
    "sg:city":"San Mames De Burgos",
    "sg:orig_category":"Farmacias",
    "sg:phone":"+34 947 41 21 51",
    "sg:postcode":"09230",
    "sg:province":"Burgos",
    "wof:name":"Romo Diez Sara",
    "wof:placetype":"venue"
},
  "geometry": {"coordinates":[-3.866697073,42.2947616577],"type":"Point"}
}