{
  "type": "Feature",
  "properties": {
    "iso:country":"ES",
    "sg:address":"Carr Ferreria (la), 11",
    "sg:city":"Alfas Pi",
    "sg:orig_category":"Centros De Coordinaci\u00d3n",
    "sg:phone":"+34 965 88 70 39",
    "sg:postcode":"03580",
    "sg:province":"Alicante",
    "wof:name":"Machado Romero Maria Ignacia",
    "wof:placetype":"venue"
},
  "geometry": {"coordinates":[-0.1106439978,38.5881652832],"type":"Point"}
}