{
  "type": "Feature",
  "properties": {
    "iso:country":"ES",
    "sg:address":"Calle de Ramon Y Cajal, 17",
    "sg:city":"Talavera Reina",
    "sg:orig_category":"Artes Gr\u00c1ficas, Artes Pl\u00c1sticas: Productos Y Suministros (al Por Mayor)",
    "sg:phone":"+34 925 81 25 37",
    "sg:postcode":"45600",
    "sg:province":"Toledo",
    "wof:name":"Geferca S.l.",
    "wof:placetype":"venue"
},
  "geometry": {"coordinates":[-4.8298869133,39.9618721008],"type":"Point"}
}