{
  "type": "Feature",
  "properties": {
    "addr:full":"Avgd D'albaida, 5 Ontinyent Valencia 46870",
    "addr:housenumber":"5",
    "addr:postcode":"46870",
    "addr:street":"D'Albaida",
    "iso:country":"ES",
    "sg:address":"Avgd D'albaida, 5",
    "sg:city":"Ontinyent",
    "sg:orig_category":"Centros Empresariales",
    "sg:phone":"+34 962 91 23 44",
    "sg:postcode":"46870",
    "sg:province":"Valencia",
    "sg:website":"www.creyfs.es",
    "wof:name":"Creyf's Trabajo Temporal Ett S.a.",
    "wof:placetype":"venue"
},
  "geometry": {"coordinates":[-0.6000689864,38.8250808716],"type":"Point"}
}