{
  "type": "Feature",
  "properties": {
    "iso:country":"ES",
    "sg:address":"Carrer de Amadeu Torner, 115",
    "sg:city":"Hospitalet Llobregat",
    "sg:orig_category":"Farmacias",
    "sg:phone":"+34 934 22 34 10",
    "sg:postcode":"08902",
    "sg:province":"Barcelona",
    "wof:name":"Bescos Mateu Grup S.c.p.",
    "wof:placetype":"venue"
},
  "geometry": {"coordinates":[2.1205320358,41.3647155762],"type":"Point"}
}