{
  "type": "Feature",
  "properties": {
    "iso:country":"ES",
    "sg:address":"Carrer de Guillem Tell, 51",
    "sg:city":"Barcelona",
    "sg:orig_category":"Cl\u00cdnicas M\u00c9dicas",
    "sg:phone":"+34 934 16 17 73",
    "sg:postcode":"08006",
    "sg:province":"Barcelona",
    "wof:name":"Institut Dermatologic Integral S.l.",
    "wof:placetype":"venue"
},
  "geometry": {"coordinates":[2.1475720406,41.4015808105],"type":"Point"}
}