{
  "type": "Feature",
  "properties": {
    "addr:full":"Americas, 22 Maspalomas Las Palmas 35100",
    "addr:housenumber":"22",
    "addr:postcode":"35100",
    "addr:street":"Americas",
    "iso:country":"ES",
    "sg:address":"Americas, 22",
    "sg:city":"Maspalomas",
    "sg:orig_category":"Importaci\u00d3n",
    "sg:phone":"+34 928 14 14 42",
    "sg:postcode":"35100",
    "sg:province":"Las Palmas",
    "wof:name":"Administrciones Vega Febles S.l.",
    "wof:placetype":"venue"
},
  "geometry": {"coordinates":[-15.6030473709,27.7710285187],"type":"Point"}
}