{
  "type": "Feature",
  "properties": {
    "iso:country":"ES",
    "sg:address":"Plaz Ochavo, 2",
    "sg:city":"Valladolid",
    "sg:orig_category":"Asistencia Y Consejos",
    "sg:phone":"+34 983 34 55 53",
    "sg:postcode":"47001",
    "sg:province":"Valladolid",
    "wof:name":"Ribero Hernandez Virginia",
    "wof:placetype":"venue"
},
  "geometry": {"coordinates":[-4.7269787788,41.6525306702],"type":"Point"}
}