{
  "type": "Feature",
  "properties": {
    "addr:full":"Avda Portugal, 3 Casillas De Flores Salamanca 37541",
    "addr:housenumber":"3",
    "addr:postcode":"37541",
    "addr:street":"Avda Portugal",
    "iso:country":"ES",
    "sg:address":"Avda Portugal, 3",
    "sg:city":"Casillas De Flores",
    "sg:orig_category":"Asilos De Ancianos. Centros Privados",
    "sg:phone":"+34 923 48 88 52",
    "sg:postcode":"37541",
    "sg:province":"Salamanca",
    "wof:name":"Residencia La Divina Pastora",
    "wof:placetype":"venue"
},
  "geometry": {"coordinates":[-6.7528409958,40.3818397522],"type":"Point"}
}