{
  "type": "Feature",
  "properties": {
    "iso:country":"ES",
    "sg:address":"Calle de San Anton, 16",
    "sg:city":"Alburquerque",
    "sg:orig_category":"Carnicer\u00cdas, Carnicer\u00cdas",
    "sg:phone":"+34 924 40 02 66",
    "sg:postcode":"06510",
    "sg:province":"Badajoz",
    "wof:name":"Exposito Aspane Francisco",
    "wof:placetype":"venue"
},
  "geometry": {"coordinates":[-6.9968791008,39.2189598083],"type":"Point"}
}