{
  "type": "Feature",
  "properties": {
    "iso:country":"ES",
    "sg:address":"Carr Aurora, 6",
    "sg:city":"Olleria",
    "sg:orig_category":"Estancos",
    "sg:phone":"+34 962 20 07 17",
    "sg:postcode":"46850",
    "sg:province":"Valencia",
    "wof:name":"Engo Valls Maria Carmen",
    "wof:placetype":"venue"
},
  "geometry": {"coordinates":[-0.5478360057,38.9096603394],"type":"Point"}
}