{
  "type": "Feature",
  "properties": {
    "iso:country":"ES",
    "sg:address":"Calle de Mentrida, 10",
    "sg:city":"Madrid",
    "sg:orig_category":"\u00d3ptica: Instrumentos (fabricaci\u00d3n)",
    "sg:phone":"+34 913 88 90 56",
    "sg:postcode":"28043",
    "sg:province":"Madrid",
    "wof:name":"Mecavision C.b.",
    "wof:placetype":"venue"
},
  "geometry": {"coordinates":[-3.6495909691,40.463508606],"type":"Point"}
}