{
  "type": "Feature",
  "properties": {
    "iso:country":"ES",
    "sg:address":"Avda Goya, 50",
    "sg:city":"Zaragoza",
    "sg:orig_category":"Inmobiliaria (agencias)",
    "sg:phone":"+34 976 21 13 33",
    "sg:postcode":"50006",
    "sg:province":"Zaragoza",
    "wof:name":"Aira S.l.",
    "wof:placetype":"venue"
},
  "geometry": {"coordinates":[-0.8913235068,41.6440582275],"type":"Point"}
}