{
  "type": "Feature",
  "properties": {
    "addr:full":"Calle de Lamana, 1 Bilbao Vizcaya 48003",
    "addr:housenumber":"1",
    "addr:postcode":"48003",
    "addr:street":"Calle De Lamana",
    "iso:country":"ES",
    "sg:address":"Calle de Lamana, 1",
    "sg:city":"Bilbao",
    "sg:orig_category":"Molduras, Junquillos, Listones Y Molduras Perforadas",
    "sg:phone":"+34 944 16 15 45",
    "sg:postcode":"48003",
    "sg:province":"Vizcaya",
    "wof:name":"Perez Saenz Felix Daniel",
    "wof:placetype":"venue"
},
  "geometry": {"coordinates":[-2.9282150269,43.2571296692],"type":"Point"}
}