{
  "type": "Feature",
  "properties": {
    "addr:full":"Av Ramon I Cajal, 39 Tarragona Tarragona 43001",
    "addr:housenumber":"39",
    "addr:postcode":"43001",
    "addr:street":"Av Ramon I Cajal",
    "iso:country":"ES",
    "sg:address":"Av Ramon I Cajal, 39",
    "sg:city":"Tarragona",
    "sg:orig_category":"Organismos De Reclutamiento",
    "sg:phone":"+34 977 21 60 86",
    "sg:postcode":"43001",
    "sg:province":"Tarragona",
    "wof:name":"Adecco Consultores En Recursos Humanos S.a.",
    "wof:placetype":"venue"
},
  "geometry": {"coordinates":[1.2447556257,41.1160049438],"type":"Point"}
}