{
  "type": "Feature",
  "properties": {
    "iso:country":"ES",
    "sg:address":"Calle de Cristo De La Yedra, 17",
    "sg:city":"Granada",
    "sg:orig_category":"Arte, Cultura, Edici\u00d3n",
    "sg:phone":"+34 958 28 37 89",
    "sg:postcode":"18012",
    "sg:province":"Granada",
    "wof:name":"Casa De Estudios Ce-70",
    "wof:placetype":"venue"
},
  "geometry": {"coordinates":[-3.6019291878,37.1869392395],"type":"Point"}
}