{
  "type": "Feature",
  "properties": {
    "addr:full":"Calle de Santa Luisa De Marillac, 13 Coru\u00d1a La Coru\u00f1a 15002",
    "addr:housenumber":"13",
    "addr:postcode":"15002",
    "addr:street":"Calle De Santa Luisa De Marillac;La Corun\u0303A",
    "iso:country":"ES",
    "sg:address":"Calle de Santa Luisa De Marillac, 13",
    "sg:city":"Coru\u00d1a",
    "sg:orig_category":"Agencias Y Agentes Comerciales, Representantes",
    "sg:phone":"+34 981 20 14 42",
    "sg:postcode":"15002",
    "sg:province":"La Coru\u00f1a",
    "wof:name":"Martell Balado Jose Maria",
    "wof:placetype":"venue"
},
  "geometry": {"coordinates":[-8.3977775574,43.3770675659],"type":"Point"}
}