{
  "type": "Feature",
  "properties": {
    "addr:full":"Av Elx, 38 Alcoi Alicante 03801",
    "addr:housenumber":"38",
    "addr:postcode":"03801",
    "addr:street":"Av Elx",
    "iso:country":"ES",
    "sg:address":"Av Elx, 38",
    "sg:city":"Alcoi",
    "sg:orig_category":"Agentes, Concesionarios Y Sucursales De Veh\u00cdculos",
    "sg:phone":"+34 965 54 40 44",
    "sg:postcode":"03801",
    "sg:province":"Alicante",
    "wof:name":"Automoviles Murcia S.l.",
    "wof:placetype":"venue"
},
  "geometry": {"coordinates":[-0.4739278853,38.6856384277],"type":"Point"}
}