{
  "type": "Feature",
  "properties": {
    "iso:country":"ES",
    "sg:address":"Almendros, 11",
    "sg:city":"Almendralejo",
    "sg:orig_category":"Empresas De Carpinter\u00cda Met\u00c1lica",
    "sg:phone":"+34 924 67 19 17",
    "sg:postcode":"06200",
    "sg:province":"Badajoz",
    "wof:name":"Extreme\u00f1a De Procesos Metalicos S.l.",
    "wof:placetype":"venue"
},
  "geometry": {"coordinates":[-6.4030251503,38.6906738281],"type":"Point"}
}