{
  "type": "Feature",
  "properties": {
    "addr:full":"Pico Roldan, 5 Canteras Murcia 30394",
    "addr:housenumber":"5",
    "addr:postcode":"30394",
    "addr:street":"Roldan",
    "iso:country":"ES",
    "sg:address":"Pico Roldan, 5",
    "sg:city":"Canteras",
    "sg:orig_category":"Institutos De Belleza",
    "sg:phone":"+34 968 16 25 16",
    "sg:postcode":"30394",
    "sg:province":"Murcia",
    "wof:name":"Diaz Saura Juani",
    "wof:placetype":"venue"
},
  "geometry": {"coordinates":[-1.0198190212,37.6126785278],"type":"Point"}
}