{
  "type": "Feature",
  "properties": {
    "iso:country":"ES",
    "sg:address":"Calle de Cristobal Colon, 3",
    "sg:city":"Cuevas San Marcos",
    "sg:orig_category":"Electrodom\u00c9sticos (al Por Menor)",
    "sg:phone":"+34 952 72 80 03",
    "sg:postcode":"29210",
    "sg:province":"M\u00e1laga",
    "wof:name":"Fonoelectric S.l.",
    "wof:placetype":"venue"
},
  "geometry": {"coordinates":[-4.4167671204,37.2678031921],"type":"Point"}
}