{
  "type": "Feature",
  "properties": {
    "addr:full":"Avda Alonso Martin, 43 Don Benito Badajoz 06400",
    "addr:housenumber":"43",
    "addr:postcode":"06400",
    "addr:street":"Avda Alonso Martin",
    "iso:country":"ES",
    "sg:address":"Avda Alonso Martin, 43",
    "sg:city":"Don Benito",
    "sg:orig_category":"Librer\u00cdas",
    "sg:phone":"+34 924 80 31 06",
    "sg:postcode":"06400",
    "sg:province":"Badajoz",
    "wof:name":"Lozano Martin-pero Francisco",
    "wof:placetype":"venue"
},
  "geometry": {"coordinates":[-5.8648891449,38.9614715576],"type":"Point"}
}