{
  "type": "Feature",
  "properties": {
    "addr:full":"Calle de Pablo Garnica, 4 Torrelavega Cantabria 39300",
    "addr:housenumber":"4",
    "addr:postcode":"39300",
    "addr:street":"Calle De Pablo Garnica",
    "iso:country":"ES",
    "sg:address":"Calle de Pablo Garnica, 4",
    "sg:city":"Torrelavega",
    "sg:orig_category":"Asociaciones Y Clubs Deportivos",
    "sg:phone":"+34 942 80 75 25",
    "sg:postcode":"39300",
    "sg:province":"Cantabria",
    "wof:name":"Anrro Bustamante S.l.",
    "wof:placetype":"venue"
},
  "geometry": {"coordinates":[-4.0481925011,43.3519744873],"type":"Point"}
}