{
  "type": "Feature",
  "properties": {
    "iso:country":"ES",
    "sg:address":"Calle de Viriato, 9",
    "sg:city":"Linares",
    "sg:orig_category":"Inform\u00c1tica, Ofim\u00c1tica (estudios, Asesor\u00cda, Ingenier\u00cda, Formaci\u00d3n)",
    "sg:phone":"+34 953 65 78 95",
    "sg:postcode":"23700",
    "sg:province":"Ja\u00e9n",
    "sg:website":"www.appinformatica.com",
    "wof:name":"Informatica Mobi-dick S.l.",
    "wof:placetype":"venue"
},
  "geometry": {"coordinates":[-3.6316039562,38.0949897766],"type":"Point"}
}