{
  "type": "Feature",
  "properties": {
    "addr:full":"San Miguel, S/n Tazones Asturias 33315",
    "addr:housenumber":"s",
    "addr:postcode":"33315",
    "addr:street":"San Miguel;/ N Tazones Asturias",
    "iso:country":"ES",
    "sg:address":"San Miguel, S/n",
    "sg:city":"Tazones",
    "sg:orig_category":"Crust\u00c1ceos Y Almejas (al Por Mayor)",
    "sg:phone":"+34 985 89 70 28",
    "sg:postcode":"33315",
    "sg:province":"Asturias",
    "wof:name":"Cetarea Tazones S.l.",
    "wof:placetype":"venue"
},
  "geometry": {"coordinates":[-5.4002161026,43.5276565552],"type":"Point"}
}