{
  "type": "Feature",
  "properties": {
    "addr:full":"Calle de Gallo, 2 Alcala Henares Madrid 28801",
    "addr:housenumber":"2",
    "addr:postcode":"28801",
    "addr:street":"Calle De Gallo",
    "iso:country":"ES",
    "sg:address":"Calle de Gallo, 2",
    "sg:city":"Alcala Henares",
    "sg:orig_category":"Ense\u00d1anza Variada",
    "sg:phone":"+34 918 89 90 75",
    "sg:postcode":"28801",
    "sg:province":"Madrid",
    "wof:name":"Cruz Rodriguez Luis",
    "wof:placetype":"venue"
},
  "geometry": {"coordinates":[-3.365942955,40.4808425903],"type":"Point"}
}