{
  "type": "Feature",
  "properties": {
    "addr:full":"Calle de Garcia De Paredes, 20 Madrid Madrid 28010",
    "addr:housenumber":"20",
    "addr:postcode":"madrid;28010",
    "addr:street":"Calle De Garcia De Paredes",
    "iso:country":"ES",
    "sg:address":"Calle de Garcia De Paredes, 20",
    "sg:city":"Madrid",
    "sg:classifiers":[
        {
            "category":"Taxi",
            "type":"Transportation"
        }
    ],
    "sg:phone":"+34 914 47 01 61",
    "sg:postcode":"28010",
    "sg:province":"Madrid",
    "wof:name":"Blanco Fernandez Marisa",
    "wof:placetype":"venue"
},
  "geometry": {"coordinates":[-3.7013659477,40.4367790222],"type":"Point"}
}