{
  "type": "Feature",
  "properties": {
    "addr:full":"Calle de Bilbao, 1 Alacant Alicante 03001",
    "addr:housenumber":"1",
    "addr:postcode":"03001",
    "addr:street":"Calle De Bilbao",
    "iso:country":"ES",
    "sg:address":"Calle de Bilbao, 1",
    "sg:city":"Alacant",
    "sg:orig_category":"Abogados",
    "sg:phone":"+34 965 14 41 05",
    "sg:postcode":"03001",
    "sg:province":"Alicante",
    "wof:name":"Lovells Boesebeck Droste Y Cia S.l.",
    "wof:placetype":"venue"
},
  "geometry": {"coordinates":[-0.4835444987,38.3439598083],"type":"Point"}
}