{
  "type": "Feature",
  "properties": {
    "addr:full":"Rbla Joan Miro, S/n Rubi Barcelona 08191",
    "addr:housenumber":"s / n",
    "addr:postcode":"08191",
    "addr:street":"Rbla Joan Miro",
    "iso:country":"ES",
    "sg:address":"Rbla Joan Miro, S/n",
    "sg:city":"Rubi",
    "sg:orig_category":"Molduras, Junquillos, Listones Y Molduras Perforadas",
    "sg:phone":"+34 936 97 02 55",
    "sg:postcode":"08191",
    "sg:province":"Barcelona",
    "wof:name":"Garcia Macia Maria",
    "wof:placetype":"venue"
},
  "geometry": {"coordinates":[2.030452013,41.4855995178],"type":"Point"}
}