{
  "type": "Feature",
  "properties": {
    "addr:full":"Extramuros, S/n Villanueva Alcardete Toledo 45810",
    "addr:postcode":"45810",
    "addr:street":"Extramuros S / N",
    "iso:country":"ES",
    "sg:address":"Extramuros, S/n",
    "sg:city":"Villanueva Alcardete",
    "sg:orig_category":"Cooperativas Agr\u00cdcolas",
    "sg:phone":"+34 925 16 63 50",
    "sg:postcode":"45810",
    "sg:province":"Toledo",
    "wof:name":"Cooperativa Vitivinicola San Isidro Labrador",
    "wof:placetype":"venue"
},
  "geometry": {"coordinates":[-3.0126190186,39.6733703613],"type":"Point"}
}