{
  "type": "Feature",
  "properties": {
    "iso:country":"ES",
    "sg:address":"Avda Ramon Valdes, 20",
    "sg:city":"Navia",
    "sg:orig_category":"Producci\u00d3n De Sidra",
    "sg:phone":"+34 985 63 18 80",
    "sg:postcode":"33710",
    "sg:province":"Asturias",
    "wof:name":"Mendez Alvarez Juan Manuel",
    "wof:placetype":"venue"
},
  "geometry": {"coordinates":[-6.7240591049,43.5387496948],"type":"Point"}
}