{
  "type": "Feature",
  "properties": {
    "iso:country":"ES",
    "sg:address":"Calle de Regimiento De Soria, 3",
    "sg:city":"Sevilla",
    "sg:orig_category":"Reposter\u00cdas",
    "sg:phone":"+34 954 35 12 25",
    "sg:postcode":"41008",
    "sg:province":"Sevilla",
    "wof:name":"Lobato Humanes Manuel",
    "wof:placetype":"venue"
},
  "geometry": {"coordinates":[-5.9709281921,37.4068946838],"type":"Point"}
}