{
  "type": "Feature",
  "properties": {
    "addr:full":"Calle de Olivo, 8 Puebla Alfinden Zaragoza 50171",
    "addr:housenumber":"8",
    "addr:postcode":"50171",
    "addr:street":"Calle De Olivo;Alfinden",
    "iso:country":"ES",
    "sg:address":"Calle de Olivo, 8",
    "sg:city":"Puebla Alfinden",
    "sg:orig_category":"Compresores",
    "sg:phone":"+34 976 10 80 33",
    "sg:postcode":"50171",
    "sg:province":"Zaragoza",
    "sg:website":"www.sogimair.com",
    "wof:name":"Sogimair S.a.",
    "wof:placetype":"venue"
},
  "geometry": {"coordinates":[-0.7614257932,41.6396141052],"type":"Point"}
}