{
  "type": "Feature",
  "properties": {
    "addr:full":"Calle de Anselmo Fernandez, 31 Requena Valencia 46340",
    "addr:housenumber":"31",
    "addr:postcode":"46340",
    "addr:street":"Calle De Anselmo Fernandez",
    "iso:country":"ES",
    "sg:address":"Calle de Anselmo Fernandez, 31",
    "sg:city":"Requena",
    "sg:orig_category":"Farmacias",
    "sg:phone":"+34 962 30 00 97",
    "sg:postcode":"46340",
    "sg:province":"Valencia",
    "wof:name":"Salvador Camps Inmaculada",
    "wof:placetype":"venue"
},
  "geometry": {"coordinates":[-1.0976200104,39.488079071],"type":"Point"}
}