{
  "type": "Feature",
  "properties": {
    "addr:full":"Calle de I\u00d1aki Deuna, 36 Ondarroa Vizcaya 48700",
    "addr:housenumber":"36",
    "addr:postcode":"48700",
    "addr:street":"Calle De In\u0303Aki Deuna",
    "iso:country":"ES",
    "sg:address":"Calle de I\u00d1aki Deuna, 36",
    "sg:city":"Ondarroa",
    "sg:orig_category":"Puertas Y Portales",
    "sg:phone":"+34 946 83 33 99",
    "sg:postcode":"48700",
    "sg:province":"Vizcaya",
    "wof:name":"Aristondo Iriondo Domingo Jesus",
    "wof:placetype":"venue"
},
  "geometry": {"coordinates":[-2.4274373055,43.3202629089],"type":"Point"}
}