{
  "type": "Feature",
  "properties": {
    "addr:full":"Calle de Paris, 4 Alacant Alicante 03003",
    "addr:housenumber":"4",
    "addr:postcode":"03003",
    "addr:street":"Calle De Paris",
    "iso:country":"ES",
    "sg:address":"Calle de Paris, 4",
    "sg:city":"Alacant",
    "sg:orig_category":"Centros P\u00dablicos De Formaci\u00d3n Profesional Y T\u00c9cnica",
    "sg:phone":"+34 965 92 78 62",
    "sg:postcode":"03003",
    "sg:province":"Alicante",
    "wof:name":"Colegio De Ingenieros Tecnicos De Obras Publicas",
    "wof:placetype":"venue"
},
  "geometry": {"coordinates":[-0.4902899861,38.343082428],"type":"Point"}
}