{
  "type": "Feature",
  "properties": {
    "addr:full":"Calle de Pino, 4 Torrejon Ardoz Madrid 28850",
    "addr:housenumber":"4",
    "addr:postcode":"28850",
    "addr:street":"Calle De Pino",
    "iso:country":"ES",
    "sg:address":"Calle de Pino, 4",
    "sg:city":"Torrejon Ardoz",
    "sg:orig_category":"Grifer\u00cda",
    "sg:phone":"+34 916 76 86 12",
    "sg:postcode":"28850",
    "sg:province":"Madrid",
    "wof:name":"Presto Iberica S. A.",
    "wof:placetype":"venue"
},
  "geometry": {"coordinates":[-3.4540998936,40.4536781311],"type":"Point"}
}