{
  "type": "Feature",
  "properties": {
    "iso:country":"ES",
    "sg:address":"Sant Oreste(p. I. Petita Industri), 21",
    "sg:city":"Begues",
    "sg:orig_category":"Material Y Suministros Para Perforaciones, Sondeos",
    "sg:phone":"+34 936 39 05 61",
    "sg:postcode":"08859",
    "sg:province":"Barcelona",
    "wof:name":"Excavacions Grau S.l.",
    "wof:placetype":"venue"
},
  "geometry": {"coordinates":[1.9208400249,41.3350906372],"type":"Point"}
}