{
  "type": "Feature",
  "properties": {
    "iso:country":"ES",
    "sg:address":"Carrer de Arquimedes, 17",
    "sg:city":"S. Adria Besos",
    "sg:orig_category":"Maquinaria Para Industrias Diversas",
    "sg:phone":"+34 934 62 66 36",
    "sg:postcode":"08930",
    "sg:province":"Barcelona",
    "wof:name":"Daosmaq S.l.",
    "wof:placetype":"venue"
},
  "geometry": {"coordinates":[2.2277851105,41.4300460815],"type":"Point"}
}