{
  "type": "Feature",
  "properties": {
    "addr:full":"Calle de Mocan (el), 6 Realejo Alto Santa Cruz De Tenerife 38410",
    "addr:housenumber":"6",
    "addr:postcode":"38410",
    "addr:street":"Calle De Mocan El",
    "iso:country":"ES",
    "sg:address":"Calle de Mocan (el), 6",
    "sg:city":"Realejo Alto",
    "sg:orig_category":"Centros Comerciales Y Grandes Tiendas",
    "sg:phone":"+34 922 34 60 08",
    "sg:postcode":"38410",
    "sg:province":"Santa Cruz De Tenerife",
    "wof:name":"Cristaleria El Cristal S.l.",
    "wof:placetype":"venue"
},
  "geometry": {"coordinates":[-16.5807914734,28.3678131104],"type":"Point"}
}