{
  "type": "Feature",
  "properties": {
    "iso:country":"ES",
    "sg:address":"Llarc, S/n",
    "sg:city":"Mao",
    "sg:orig_category":"Escayola Y Productos De Escayola (fabricaci\u00d3n, Al Por Mayor)",
    "sg:phone":"+34 971 35 02 86",
    "sg:postcode":"07700",
    "sg:province":"Islas Baleares",
    "wof:name":"Segui Villalonga Rafael",
    "wof:placetype":"venue"
},
  "geometry": {"coordinates":[4.2953400612,39.8923797607],"type":"Point"}
}