{
  "type": "Feature",
  "properties": {
    "iso:country":"ES",
    "sg:address":"Calle de San Pedro, 19",
    "sg:city":"Madrid",
    "sg:orig_category":"Arquitectos",
    "sg:phone":"+34 914 29 53 63",
    "sg:postcode":"28014",
    "sg:province":"Madrid",
    "wof:name":"Hermida Vazquez Fernando",
    "wof:placetype":"venue"
},
  "geometry": {"coordinates":[-3.6948130131,40.411026001],"type":"Point"}
}