{
  "type": "Feature",
  "properties": {
    "iso:country":"ES",
    "sg:address":"Calle de Corredera, 15",
    "sg:city":"Almansa",
    "sg:orig_category":"Fabricaci\u00d3n De Productos Textiles Sin Tejer",
    "sg:phone":"+34 967 34 10 71",
    "sg:postcode":"02640",
    "sg:province":"Albacete",
    "wof:name":"Almansa Moda S.l.",
    "wof:placetype":"venue"
},
  "geometry": {"coordinates":[-1.0961288214,38.8676376343],"type":"Point"}
}