{
  "type": "Feature",
  "properties": {
    "iso:country":"ES",
    "sg:address":"Carrer de Flor De Sant Joan, 3",
    "sg:city":"Montgo",
    "sg:orig_category":"Centros De Coordinaci\u00d3n",
    "sg:phone":"+34 966 42 32 46",
    "sg:postcode":"03700",
    "sg:province":"Alicante",
    "wof:name":"Fernandez Garcia Mercedes",
    "wof:placetype":"venue"
},
  "geometry": {"coordinates":[0.1039630026,38.8354949951],"type":"Point"}
}