{
  "type": "Feature",
  "properties": {
    "iso:country":"ES",
    "sg:address":"Rua Hermanos Alvarez Araujo, 42",
    "sg:city":"Ribadavia",
    "sg:orig_category":"Venta, Montaje De Neum\u00c1ticos",
    "sg:phone":"+34 988 47 09 87",
    "sg:postcode":"32400",
    "sg:province":"Ourense",
    "wof:name":"Regueiro Morgade Jaime",
    "wof:placetype":"venue"
},
  "geometry": {"coordinates":[-8.1376123428,42.2935600281],"type":"Point"}
}