{
  "type": "Feature",
  "properties": {
    "iso:country":"ES",
    "sg:address":"Calle de Benigafull, 1",
    "sg:city":"Vall D'uixo",
    "sg:orig_category":"Florister\u00cdas",
    "sg:phone":"+34 964 66 07 44",
    "sg:postcode":"12600",
    "sg:province":"Castell\u00f3n",
    "wof:name":"Pe\u00f1arroja Arnau Manuel",
    "wof:placetype":"venue"
},
  "geometry": {"coordinates":[-0.2328484952,39.8232727051],"type":"Point"}
}