{
  "type": "Feature",
  "properties": {
    "iso:country":"ES",
    "sg:address":"Cmno Sierra De Las Indias, S/n",
    "sg:city":"Rebolledo",
    "sg:orig_category":"Carros Elevadores, Carros De Operaciones Portuarias",
    "sg:phone":"+34 965 96 00 17",
    "sg:postcode":"03113",
    "sg:province":"Alicante",
    "wof:name":"Luque Cotino Juan Agustin",
    "wof:placetype":"venue"
},
  "geometry": {"coordinates":[-0.613263011,38.3420791626],"type":"Point"}
}