{
  "type": "Feature",
  "properties": {
    "addr:full":"Plaz Paz (de La), 13 Almunia De Do\u00e7a Godina Zaragoza 50100",
    "addr:postcode":"50100",
    "addr:street":"Plaz",
    "iso:country":"ES",
    "sg:address":"Plaz Paz (de La), 13",
    "sg:city":"Almunia De Do\u00e7a Godina",
    "sg:orig_category":"Procuradores",
    "sg:phone":"+34 976 60 10 24",
    "sg:postcode":"50100",
    "sg:province":"Zaragoza",
    "wof:name":"Sanz Romero Francisco Javier",
    "wof:placetype":"venue"
},
  "geometry": {"coordinates":[-1.3779189587,41.4772033691],"type":"Point"}
}