{
  "type": "Feature",
  "properties": {
    "addr:full":"Via Edison (de), 4 Boisaca La Coru\u00f1a 15890",
    "addr:postcode":"15890",
    "addr:street":"Via Edison De 4 Boisaca La Corun\u0303A",
    "iso:country":"ES",
    "sg:address":"Via Edison (de), 4",
    "sg:city":"Boisaca",
    "sg:orig_category":"Inform\u00c1tica (estudios, Servicios, Asesor\u00cda, Formaci\u00d3n)",
    "sg:phone":"+34 981 56 21 44",
    "sg:postcode":"15890",
    "sg:province":"La Coru\u00f1a",
    "wof:name":"Cyberlab Servicios Tecnicos S.l.",
    "wof:placetype":"venue"
},
  "geometry": {"coordinates":[-8.4769210815,42.8835983276],"type":"Point"}
}