{
  "type": "Feature",
  "properties": {
    "addr:full":"Calle de Senda Galiana (de La), S/n Coslada Madrid 28820",
    "addr:postcode":"28820",
    "addr:street":"Calle De Senda Galiana De La S / N",
    "iso:country":"ES",
    "sg:address":"Calle de Senda Galiana (de La), S/n",
    "sg:city":"Coslada",
    "sg:orig_category":"Marroquiner\u00cda (confecci\u00d3n)",
    "sg:phone":"+34 916 73 64 83",
    "sg:postcode":"28820",
    "sg:province":"Madrid",
    "wof:name":"Aparicio Morales Victor",
    "wof:placetype":"venue"
},
  "geometry": {"coordinates":[-3.5366523266,40.4430084229],"type":"Point"}
}