{
  "type": "Feature",
  "properties": {
    "addr:full":"Calle de General Benavent Garcia, 2 Alcazar S. Juan Ciudad Real 13600",
    "addr:housenumber":"2",
    "addr:postcode":"13600",
    "addr:street":"Calle De General Benavent Garcia;Alcazar S. Juan Ciudad Real",
    "iso:country":"ES",
    "sg:address":"Calle de General Benavent Garcia, 2",
    "sg:city":"Alcazar S. Juan",
    "sg:orig_category":"Ropa Para Se\u00d1oras Y Caballeros (al Por Menor)",
    "sg:phone":"+34 926 55 26 42",
    "sg:postcode":"13600",
    "sg:province":"Ciudad Real",
    "wof:name":"Cadena Chema S.l.",
    "wof:placetype":"venue"
},
  "geometry": {"coordinates":[-3.2147490978,39.3913040161],"type":"Point"}
}