{
  "type": "Feature",
  "properties": {
    "addr:full":"Calle de Reyes Catolicos, 13 Cordoba C\u00f3rdoba 14001",
    "addr:housenumber":"13",
    "addr:postcode":"14001",
    "addr:street":"Calle De Reyes Catolicos;Co\u0301Rdoba",
    "iso:country":"ES",
    "sg:address":"Calle de Reyes Catolicos, 13",
    "sg:city":"Cordoba",
    "sg:orig_category":"Centros M\u00c9dicos Y Sociales, Dispensarios",
    "sg:phone":"+34 957 49 06 27",
    "sg:postcode":"14001",
    "sg:province":"C\u00f3rdoba",
    "wof:name":"Saez Bravo Jose Maria",
    "wof:placetype":"venue"
},
  "geometry": {"coordinates":[-4.7811889648,37.8892402649],"type":"Point"}
}