{
  "type": "Feature",
  "properties": {
    "addr:full":"Calle de Carlos Iii, 4 Gijon Asturias 33204",
    "addr:housenumber":"4",
    "addr:postcode":"33204",
    "addr:street":"Calle De Carlos Iii",
    "iso:country":"ES",
    "sg:address":"Calle de Carlos Iii, 4",
    "sg:city":"Gijon",
    "sg:orig_category":"Molduras, Junquillos, Listones Y Molduras Perforadas",
    "sg:phone":"+34 985 13 19 24",
    "sg:postcode":"33204",
    "sg:province":"Asturias",
    "wof:name":"Martin Blazquez Amparo",
    "wof:placetype":"venue"
},
  "geometry": {"coordinates":[-5.6499004364,43.5365028381],"type":"Point"}
}