{
  "type": "Feature",
  "properties": {
    "addr:full":"Carr Pere Jacas, 7 Vilanova I La Geltru Barcelona 08800",
    "addr:housenumber":"7",
    "addr:postcode":"08800",
    "addr:street":"Carr Pere Jacas",
    "iso:country":"ES",
    "sg:address":"Carr Pere Jacas, 7",
    "sg:city":"Vilanova I La Geltru",
    "sg:orig_category":"Cerrajer\u00cda, Ferrallista",
    "sg:phone":"+34 938 15 80 89",
    "sg:postcode":"08800",
    "sg:province":"Barcelona",
    "wof:name":"Melgarejo Ruiz Pere",
    "wof:placetype":"venue"
},
  "geometry": {"coordinates":[1.7274149656,41.2169303894],"type":"Point"}
}