{
  "type": "Feature",
  "properties": {
    "addr:full":"Bo El Cruce, 109 Saron Cantabria 39620",
    "addr:housenumber":"109",
    "addr:postcode":"39620",
    "addr:street":"Cruce",
    "iso:country":"ES",
    "sg:address":"Bo El Cruce, 109",
    "sg:city":"Saron",
    "sg:orig_category":"Telas Y Sedas (al Por Menor)",
    "sg:phone":"+34 942 56 37 13",
    "sg:postcode":"39620",
    "sg:province":"Cantabria",
    "wof:name":"Rueda Trueba Fernando",
    "wof:placetype":"venue"
},
  "geometry": {"coordinates":[-3.8524339199,43.3249206543],"type":"Point"}
}