{
  "type": "Feature",
  "properties": {
    "iso:country":"ES",
    "sg:address":"Calle de Menendez Y Pelayo, 2",
    "sg:city":"Entrego",
    "sg:orig_category":"Asesor\u00cda Fiscal Y Jur\u00cddica",
    "sg:phone":"+34 985 66 21 22",
    "sg:postcode":"33940",
    "sg:province":"Asturias",
    "wof:name":"Olegario Gonzalez S.l.",
    "wof:placetype":"venue"
},
  "geometry": {"coordinates":[-5.6374349594,43.2872123718],"type":"Point"}
}