{
  "type": "Feature",
  "properties": {
    "iso:country":"ES",
    "sg:address":"C/ Alfons I, 5",
    "sg:city":"Puigcerda",
    "sg:orig_category":"Art\u00cdculos De Regalo (al Por Menor)",
    "sg:phone":"+34 972 14 13 34",
    "sg:postcode":"17520",
    "sg:province":"Girona",
    "wof:name":"Magdaleno Perez Aurelia",
    "wof:placetype":"venue"
},
  "geometry": {"coordinates":[1.9275510311,42.4316902161],"type":"Point"}
}