{
  "type": "Feature",
  "properties": {
    "addr:full":"Calle de Miguel Servet, 174 Zaragoza Zaragoza 50013",
    "addr:housenumber":"174",
    "addr:postcode":"50013",
    "addr:street":"Calle De Miguel Servet",
    "iso:country":"ES",
    "sg:address":"Calle de Miguel Servet, 174",
    "sg:city":"Zaragoza",
    "sg:orig_category":"Ense\u00d1anza, Formaci\u00d3n Profesional: Aprendizaje",
    "sg:phone":"+34 976 13 46 30",
    "sg:postcode":"50013",
    "sg:province":"Zaragoza",
    "wof:name":"Ayuntamiento De Zaragoza",
    "wof:placetype":"venue"
},
  "geometry": {"coordinates":[-0.8652338982,41.6385688782],"type":"Point"}
}