{
  "type": "Feature",
  "properties": {
    "iso:country":"ES",
    "sg:address":"Calle de Santa Isabel, 5",
    "sg:city":"Madrid",
    "sg:orig_category":"Poller\u00cda Y Caza (al Por Menor)",
    "sg:phone":"+34 913 69 25 07",
    "sg:postcode":"28012",
    "sg:province":"Madrid",
    "wof:name":"Casado Lopez Javier",
    "wof:placetype":"venue"
},
  "geometry": {"coordinates":[-3.6987159252,40.4114990234],"type":"Point"}
}