{
  "type": "Feature",
  "properties": {
    "iso:country":"ES",
    "sg:address":"Carrer de Quarter De Simancas, 52",
    "sg:city":"Barcelona",
    "sg:orig_category":"Perfumer\u00cda (al Por Menor)",
    "sg:phone":"+34 933 53 49 62",
    "sg:postcode":"08042",
    "sg:province":"Barcelona",
    "wof:name":"Castel Jarque Miguel",
    "wof:placetype":"venue"
},
  "geometry": {"coordinates":[2.1744990349,41.4454727173],"type":"Point"}
}