{
  "type": "Feature",
  "properties": {
    "iso:country":"ES",
    "sg:address":"Carrer de Rosa Sensat, 21",
    "sg:city":"Masnou",
    "sg:orig_category":"Administradores De Bienes Y Delegados De Comunidades De Propietarios",
    "sg:phone":"+34 935 55 25 70",
    "sg:postcode":"08320",
    "sg:province":"Barcelona",
    "sg:website":"www.fincasdomech.com",
    "wof:name":"Domoes S.c.p",
    "wof:placetype":"venue"
},
  "geometry": {"coordinates":[2.3043379784,41.4797782898],"type":"Point"}
}