{
  "type": "Feature",
  "properties": {
    "addr:full":"Avda Aurora, 12 Malaga M\u00e1laga 29002",
    "addr:housenumber":"12",
    "addr:postcode":"29002",
    "addr:street":"Avda Aurora;Ma\u0301Laga",
    "iso:country":"ES",
    "sg:address":"Avda Aurora, 12",
    "sg:city":"Malaga",
    "sg:orig_category":"Fabricaci\u00d3n De Ventanas",
    "sg:phone":"+34 952 31 46 36",
    "sg:postcode":"29002",
    "sg:province":"M\u00e1laga",
    "sg:website":"www.liebanaventana.com",
    "wof:name":"Liebana Ventanas Pvc S.l.",
    "wof:placetype":"venue"
},
  "geometry": {"coordinates":[-4.42897892,36.7160568237],"type":"Point"}
}