{
  "type": "Feature",
  "properties": {
    "addr:full":"Calle de Cartagena, 58 Rozas De Madrid Madrid 28230",
    "addr:housenumber":"58",
    "addr:postcode":"28230",
    "addr:street":"Calle De Cartagena",
    "iso:country":"ES",
    "sg:address":"Calle de Cartagena, 58",
    "sg:city":"Rozas De Madrid",
    "sg:orig_category":"Asesor\u00cda De Comercio Exterior",
    "sg:phone":"+34 916 34 12 27",
    "sg:postcode":"28230",
    "sg:province":"Madrid",
    "wof:name":"Robert Torres Jorge",
    "wof:placetype":"venue"
},
  "geometry": {"coordinates":[-3.8904857635,40.490940094],"type":"Point"}
}