{
  "type": "Feature",
  "properties": {
    "iso:country":"ES",
    "sg:address":"Avda Ricardo Carapeto Zambrano, 51",
    "sg:city":"Badajoz",
    "sg:orig_category":"Desinfecci\u00d3n, Desinsectaci\u00d3n, Desratizaci\u00d3n",
    "sg:phone":"+34 924 25 04 64",
    "sg:postcode":"06008",
    "sg:province":"Badajoz",
    "wof:name":"Tratamientos Tecnologicos S. A.",
    "wof:placetype":"venue"
},
  "geometry": {"coordinates":[-6.951777935,38.878490448],"type":"Point"}
}