{
  "type": "Feature",
  "properties": {
    "iso:country":"ES",
    "sg:address":"Ctra Bao, 74",
    "sg:city":"Combro",
    "sg:orig_category":"M\u00c1rmoles, Granitos Y Piedras Naturales",
    "sg:phone":"+34 986 49 01 07",
    "sg:postcode":"36330",
    "sg:province":"Pontevedra",
    "wof:name":"Maprehor S.l.",
    "wof:placetype":"venue"
},
  "geometry": {"coordinates":[-8.694773674,42.6678962708],"type":"Point"}
}