{
  "type": "Feature",
  "properties": {
    "iso:country":"ES",
    "sg:address":"Calle de Santiponce, S/n",
    "sg:city":"Camas",
    "sg:orig_category":"Fabricaci\u00d3n, Importaci\u00d3n, Venta De Material De Telefon\u00cda, Peritelefon\u00cda",
    "sg:phone":"+34 955 98 27 11",
    "sg:postcode":"41900",
    "sg:province":"Sevilla",
    "wof:name":"Jecomtel Comunicaciones S.l.",
    "wof:placetype":"venue"
},
  "geometry": {"coordinates":[-6.0321888924,37.3846168518],"type":"Point"}
}