{
  "type": "Feature",
  "properties": {
    "addr:full":"Calle de Hernan Cortes, 9 Malaga M\u00e1laga 29014",
    "addr:housenumber":"9",
    "addr:postcode":"29014",
    "addr:street":"Calle De Hernan Cortes;Ma\u0301Laga",
    "iso:country":"ES",
    "sg:address":"Calle de Hernan Cortes, 9",
    "sg:city":"Malaga",
    "sg:orig_category":"Mec\u00c1nico Del Autom\u00d3vil",
    "sg:phone":"+34 952 25 43 84",
    "sg:postcode":"29014",
    "sg:province":"M\u00e1laga",
    "wof:name":"Madrid Vera Jose",
    "wof:placetype":"venue"
},
  "geometry": {"coordinates":[-4.4225120544,36.7316627502],"type":"Point"}
}