{
  "type": "Feature",
  "properties": {
    "iso:country":"ES",
    "sg:address":"Calle de Jose Antonio Primo Rivera, 2",
    "sg:city":"Algeciras",
    "sg:orig_category":"Abogados",
    "sg:phone":"+34 956 63 30 80",
    "sg:postcode":"11201",
    "sg:province":"C\u00e1diz",
    "wof:name":"Vazquez Diaz Jose",
    "wof:placetype":"venue"
},
  "geometry": {"coordinates":[-5.4467148781,36.1308555603],"type":"Point"}
}