{
  "type": "Feature",
  "properties": {
    "iso:country":"ES",
    "sg:address":"Pol. Ind., S/n",
    "sg:city":"Azuaga",
    "sg:orig_category":"Agentes, Concesionarios Y Sucursales De Veh\u00cdculos",
    "sg:phone":"+34 924 89 25 31",
    "sg:postcode":"06920",
    "sg:province":"Badajoz",
    "wof:name":"Automoviles Morauto S.l.",
    "wof:placetype":"venue"
},
  "geometry": {"coordinates":[-5.7089242935,38.2832565308],"type":"Point"}
}