{
  "type": "Feature",
  "properties": {
    "addr:full":"Calle de Rodriguez Arias, 16 Bilbao Vizcaya 48011",
    "addr:housenumber":"16",
    "addr:postcode":"48011",
    "addr:street":"Calle De Rodriguez Arias",
    "iso:country":"ES",
    "sg:address":"Calle de Rodriguez Arias, 16",
    "sg:city":"Bilbao",
    "sg:orig_category":"Psic\u00d3logos",
    "sg:phone":"+34 944 16 02 06",
    "sg:postcode":"48011",
    "sg:province":"Vizcaya",
    "wof:name":"Ruiloba Carbonell Eva Estibaliz",
    "wof:placetype":"venue"
},
  "geometry": {"coordinates":[-2.9372289181,43.2624549866],"type":"Point"}
}