{
  "type": "Feature",
  "properties": {
    "addr:full":"Carrer de Agusti Vinyamata, 81 Granollers Barcelona 08402",
    "addr:housenumber":"81",
    "addr:postcode":"08402",
    "addr:street":"Carrer De Agusti Vinyamata",
    "iso:country":"ES",
    "sg:address":"Carrer de Agusti Vinyamata, 81",
    "sg:city":"Granollers",
    "sg:orig_category":"Tintes (fabricaci\u00d3n, Al Por Mayor)",
    "sg:phone":"+34 938 70 16 05",
    "sg:postcode":"08402",
    "sg:province":"Barcelona",
    "wof:name":"Cladellas Ros Pedro",
    "wof:placetype":"venue"
},
  "geometry": {"coordinates":[2.2925009727,41.6080932617],"type":"Point"}
}