{
  "type": "Feature",
  "properties": {
    "iso:country":"ES",
    "sg:address":"Av. Gran Canaria, 24",
    "sg:city":"A Coru\u00f1a",
    "sg:orig_category":"Inmobiliaria (agencias)",
    "sg:phone":"+34 981 27 63 57",
    "sg:postcode":"15011",
    "sg:province":"La Coru\u00f1a",
    "wof:name":"Inmogalicia 2003 S.l.",
    "wof:placetype":"venue"
},
  "geometry": {"coordinates":[-8.4247169495,43.3726768494],"type":"Point"}
}