{
  "type": "Feature",
  "properties": {
    "addr:full":"Carrer de Industria, 2 Vendrell Tarragona 43700",
    "addr:housenumber":"2",
    "addr:postcode":"43700",
    "addr:street":"Carrer De Industria",
    "iso:country":"ES",
    "sg:address":"Carrer de Industria, 2",
    "sg:city":"Vendrell",
    "sg:orig_category":"Veh\u00cdculos De Ocasi\u00d3n",
    "sg:phone":"+34 977 66 87 69",
    "sg:postcode":"43700",
    "sg:province":"Tarragona",
    "wof:name":"Automobils Alonso Penedes S.l.",
    "wof:placetype":"venue"
},
  "geometry": {"coordinates":[1.5322899818,41.2217712402],"type":"Point"}
}