{
  "type": "Feature",
  "properties": {
    "addr:full":"Antonio Tarazona, 26 Sedavi Valencia 46910",
    "addr:housenumber":"26",
    "addr:postcode":"46910",
    "addr:street":"Tarazona",
    "iso:country":"ES",
    "sg:address":"Antonio Tarazona, 26",
    "sg:city":"Sedavi",
    "sg:orig_category":"Alcoholes Y Aguardientes (fabricaci\u00d3n, Al Por Mayor)",
    "sg:phone":"+34 963 75 59 29",
    "sg:postcode":"46910",
    "sg:province":"Valencia",
    "wof:name":"Aurelio Crespo Sospedra C. B.",
    "wof:placetype":"venue"
},
  "geometry": {"coordinates":[-0.3847501874,39.4243011475],"type":"Point"}
}