{
  "type": "Feature",
  "properties": {
    "addr:full":"Calle de Valle De Tobalina, 40 Madrid Madrid 28021",
    "addr:housenumber":"40",
    "addr:postcode":"madrid;28021",
    "addr:street":"Calle De Valle De Tobalina",
    "iso:country":"ES",
    "sg:address":"Calle de Valle De Tobalina, 40",
    "sg:city":"Madrid",
    "sg:orig_category":"Cristaler\u00cdas",
    "sg:phone":"+34 915 05 09 14",
    "sg:postcode":"28021",
    "sg:province":"Madrid",
    "sg:website":"www.cristalexpress.com",
    "wof:name":"Abarce Cristal-express S.l.",
    "wof:placetype":"venue"
},
  "geometry": {"coordinates":[-3.715324,40.339298],"type":"Point"}
}