{
  "type": "Feature",
  "properties": {
    "addr:full":"Carrer de L'abat Samso, 20 Barcelona Barcelona 08017",
    "addr:housenumber":"20",
    "addr:postcode":"08017",
    "addr:street":"Carrer De L'Abat Samso",
    "iso:country":"ES",
    "sg:address":"Carrer de L'abat Samso, 20",
    "sg:city":"Barcelona",
    "sg:orig_category":"Peluquer\u00cdas, Peluquer\u00cda Mixta",
    "sg:phone":"+34 932 05 28 30",
    "sg:postcode":"08017",
    "sg:province":"Barcelona",
    "wof:name":"Lopez Muntane Nieves",
    "wof:placetype":"venue"
},
  "geometry": {"coordinates":[2.125742197,41.3962783813],"type":"Point"}
}