{
  "type": "Feature",
  "properties": {
    "iso:country":"ES",
    "sg:address":"Ctra Madrid, Km. 0168,0",
    "sg:city":"Mojados",
    "sg:orig_category":"Barbacoas Y Accesorios",
    "sg:phone":"+34 983 60 78 00",
    "sg:postcode":"47250",
    "sg:province":"Valladolid",
    "wof:name":"Pago El Borrego S.l.",
    "wof:placetype":"venue"
},
  "geometry": {"coordinates":[-4.6654090881,41.4321861267],"type":"Point"}
}