{
  "type": "Feature",
  "properties": {
    "addr:full":"Avenida Jose Antonio P. Rivera, S/n Salas Infantes Burgos 09600",
    "addr:housenumber":"s",
    "addr:postcode":"09600",
    "addr:street":"Avenida Jose Antonio P. Rivera;/ N Salas Infantes",
    "iso:country":"ES",
    "sg:address":"Avenida Jose Antonio P. Rivera, S/n",
    "sg:city":"Salas Infantes",
    "sg:orig_category":"Empresas De Carpinter\u00cda",
    "sg:phone":"+34 947 38 07 37",
    "sg:postcode":"09600",
    "sg:province":"Burgos",
    "wof:name":"Aluminio Crista Y Hierro S.l.",
    "wof:placetype":"venue"
},
  "geometry": {"coordinates":[-3.2822844982,42.0215339661],"type":"Point"}
}