{
  "type": "Feature",
  "properties": {
    "addr:full":"Cmno Santimia, S/n Lardero La Rioja 26140",
    "addr:housenumber":"s / n",
    "addr:postcode":"26140",
    "addr:street":"Cmno Santimia;Rioja",
    "iso:country":"ES",
    "sg:address":"Cmno Santimia, S/n",
    "sg:city":"Lardero",
    "sg:orig_category":"Animales (al Por Menor)",
    "sg:phone":"+34 941 44 85 45",
    "sg:postcode":"26140",
    "sg:province":"La Rioja",
    "wof:name":"Carretero Picazo Angel",
    "wof:placetype":"venue"
},
  "geometry": {"coordinates":[-2.4627640247,42.4269752502],"type":"Point"}
}