{
  "type": "Feature",
  "properties": {
    "addr:full":"Ctra Mas Del Jutge, Km. 0001,2 P.i. Masia Del Juez Valencia 46900",
    "addr:postcode":"46900",
    "addr:street":"Ctra Mas Del Jutge Km. 0001,2 P.I. Masia Del Juez",
    "iso:country":"ES",
    "sg:address":"Ctra Mas Del Jutge, Km. 0001,2",
    "sg:city":"P.i. Masia Del Juez",
    "sg:orig_category":"Pintura, Barniz, Productos Asimilables (fabricaci\u00d3n, Al Por Mayor)",
    "sg:phone":"+34 961 55 00 73",
    "sg:postcode":"46900",
    "sg:province":"Valencia",
    "sg:website":"www.blatem.com",
    "wof:name":"Pinturas Blatem S. L.",
    "wof:placetype":"venue"
},
  "geometry": {"coordinates":[-0.4623290002,39.441619873],"type":"Point"}
}