{
  "type": "Feature",
  "properties": {
    "iso:country":"ES",
    "sg:address":"Camino Balcon, S/n",
    "sg:city":"Morales Vino",
    "sg:orig_category":"M\u00c1rmoles, Granitos Y Piedras Naturales",
    "sg:phone":"+34 980 57 40 01",
    "sg:postcode":"49190",
    "sg:province":"Zamora",
    "wof:name":"Marmoleria San Damian Borrego S.l.",
    "wof:placetype":"venue"
},
  "geometry": {"coordinates":[-5.7349591255,41.445602417],"type":"Point"}
}