{
  "type": "Feature",
  "properties": {
    "iso:country":"ES",
    "sg:address":"Carrer de Flor De La Muntanya, 27",
    "sg:city":"Avia",
    "sg:orig_category":"Pintura Industrial (trabajos De)",
    "sg:phone":"+34 938 23 04 10",
    "sg:postcode":"08610",
    "sg:province":"Barcelona",
    "wof:name":"Pinturavi S.l.",
    "wof:placetype":"venue"
},
  "geometry": {"coordinates":[1.8168250322,42.0798950195],"type":"Point"}
}