{
  "type": "Feature",
  "properties": {
    "addr:full":"Calle de Fueros, 4 Irun Guip\u00f9zcoa 20302",
    "addr:housenumber":"4",
    "addr:postcode":"20302",
    "addr:street":"Calle De Fueros;Guipu\u0300Zcoa",
    "iso:country":"ES",
    "sg:address":"Calle de Fueros, 4",
    "sg:city":"Irun",
    "sg:orig_category":"Fotocopias, Reprograf\u00cda",
    "sg:phone":"+34 943 63 22 11",
    "sg:postcode":"20302",
    "sg:province":"Guip\u00f9zcoa",
    "wof:name":"Basalo Medrano Idoia",
    "wof:placetype":"venue"
},
  "geometry": {"coordinates":[-1.7898470163,43.3385391235],"type":"Point"}
}