{
  "type": "Feature",
  "properties": {
    "iso:country":"ES",
    "sg:address":"Calle de Exposicion, 2",
    "sg:city":"Mairena Aljarafe",
    "sg:orig_category":"Quincaller\u00cda (al Por Menor)",
    "sg:phone":"+34 954 18 49 86",
    "sg:postcode":"41927",
    "sg:province":"Sevilla",
    "wof:name":"Ferreteria El Tornillo S.l.",
    "wof:placetype":"venue"
},
  "geometry": {"coordinates":[-6.0594034195,37.3518371582],"type":"Point"}
}