{
  "type": "Feature",
  "properties": {
    "iso:country":"ES",
    "sg:address":"Carrer de Tucuman, 28",
    "sg:city":"Barcelona",
    "sg:orig_category":"Venta, Localizaci\u00d3n, Reparaci\u00d3n De Material E Instrumental M\u00c9dico",
    "sg:phone":"+34 933 12 03 61",
    "sg:postcode":"08030",
    "sg:province":"Barcelona",
    "wof:name":"Comercial Lluch S.a.",
    "wof:placetype":"venue"
},
  "geometry": {"coordinates":[2.2026751041,41.4466209412],"type":"Point"}
}