{
  "type": "Feature",
  "properties": {
    "addr:full":"Calle de Alonso Chirino, 4 Cuenca Cuenca 16002",
    "addr:housenumber":"4",
    "addr:postcode":"16002",
    "addr:street":"Calle De Alonso Chirino",
    "iso:country":"ES",
    "sg:address":"Calle de Alonso Chirino, 4",
    "sg:city":"Cuenca",
    "sg:orig_category":"Molduras, Junquillos, Listones Y Molduras Perforadas",
    "sg:phone":"+34 969 21 38 40",
    "sg:postcode":"16002",
    "sg:province":"Cuenca",
    "wof:name":"Antonio Martinez Y Eloy Diaz C.b.",
    "wof:placetype":"venue"
},
  "geometry": {"coordinates":[-2.1359539032,40.0725059509],"type":"Point"}
}