{
  "type": "Feature",
  "properties": {
    "iso:country":"ES",
    "sg:address":"Avda Irun (de), S/n",
    "sg:city":"San Fernando De Henares",
    "sg:orig_category":"Establecimientos De Cura, Prevenci\u00d3n Y Readaptaci\u00d3n",
    "sg:phone":"+34 916 74 00 14",
    "sg:postcode":"28830",
    "sg:province":"Madrid",
    "wof:name":"Ayuntamiento De San Fernando De Henares",
    "wof:placetype":"venue"
},
  "geometry": {"coordinates":[-3.5303707123,40.4233436584],"type":"Point"}
}