{
  "type": "Feature",
  "properties": {
    "addr:full":"Calle de Roa De La Vega, 12 Le\u00f3n Le\u00f3n 24002",
    "addr:housenumber":"12",
    "addr:postcode":"24002",
    "addr:street":"Calle De Roa De La Vega;Leo\u0301N",
    "iso:country":"ES",
    "sg:address":"Calle de Roa De La Vega, 12",
    "sg:city":"Le\u00f3n",
    "sg:orig_category":"Art\u00cdculos De Decoraci\u00d3n",
    "sg:phone":"+34 987 22 32 92",
    "sg:postcode":"24002",
    "sg:province":"Le\u00f3n",
    "wof:name":"Villastrigo Amez Francisco",
    "wof:placetype":"venue"
},
  "geometry": {"coordinates":[-5.5768389702,42.6006393433],"type":"Point"}
}