{
  "type": "Feature",
  "properties": {
    "addr:full":"Ctra Bolulla (de), 8 Callosa D'en Sarria Alicante 03510",
    "addr:housenumber":"8",
    "addr:postcode":"03510",
    "addr:street":"Ctra Bolulla De",
    "iso:country":"ES",
    "sg:address":"Ctra Bolulla (de), 8",
    "sg:city":"Callosa D'en Sarria",
    "sg:orig_category":"Panader\u00cdas, Panader\u00cdas",
    "sg:phone":"+34 965 88 24 81",
    "sg:postcode":"03510",
    "sg:province":"Alicante",
    "wof:name":"El Forn De Izla C.b.",
    "wof:placetype":"venue"
},
  "geometry": {"coordinates":[-0.1212422028,38.6500968933],"type":"Point"}
}