{
  "type": "Feature",
  "properties": {
    "addr:full":"Calle de Castillo De Aracena, 13 Alcala Guadaira Sevilla 41500",
    "addr:housenumber":"13",
    "addr:postcode":"41500",
    "addr:street":"Calle De Castillo;Aracena",
    "iso:country":"ES",
    "sg:address":"Calle de Castillo De Aracena, 13",
    "sg:city":"Alcala Guadaira",
    "sg:orig_category":"Contenedores (mercanc\u00cdas)",
    "sg:phone":"+34 955 68 21 44",
    "sg:postcode":"41500",
    "sg:province":"Sevilla",
    "wof:name":"Gocer Trans S.l.",
    "wof:placetype":"venue"
},
  "geometry": {"coordinates":[-5.8521213531,37.3400917053],"type":"Point"}
}