{
  "type": "Feature",
  "properties": {
    "iso:country":"ES",
    "sg:address":"Carrer de Santa Amelia, 45",
    "sg:city":"Barcelona",
    "sg:orig_category":"Peluquer\u00cdas, Peluquer\u00cda Mixta",
    "sg:phone":"+34 932 05 17 00",
    "sg:postcode":"08034",
    "sg:province":"Barcelona",
    "wof:name":"Garcia Vila Perruquers S.r.l.l.",
    "wof:placetype":"venue"
},
  "geometry": {"coordinates":[2.1245911121,41.3945922852],"type":"Point"}
}