{
  "type": "Feature",
  "properties": {
    "addr:full":"Pl Doncel, 1 San J. Aznalfarache Sevilla 41920",
    "addr:housenumber":"1",
    "addr:postcode":"41920",
    "addr:street":"Pl Doncel",
    "iso:country":"ES",
    "sg:address":"Pl Doncel, 1",
    "sg:city":"San J. Aznalfarache",
    "sg:orig_category":"Molduras, Junquillos, Listones Y Molduras Perforadas",
    "sg:phone":"+34 954 17 17 50",
    "sg:postcode":"41920",
    "sg:province":"Sevilla",
    "wof:name":"Ferrera Mu\u00f1oz Eduardo",
    "wof:placetype":"venue"
},
  "geometry": {"coordinates":[-6.0270290375,37.3696899414],"type":"Point"}
}