{
  "type": "Feature",
  "properties": {
    "addr:full":"Carrer de Mallorca, 349 Barcelona Barcelona 08013",
    "addr:housenumber":"349",
    "addr:postcode":"08013",
    "addr:street":"Carrer De Mallorca",
    "iso:country":"ES",
    "sg:address":"Carrer de Mallorca, 349",
    "sg:city":"Barcelona",
    "sg:orig_category":"Centros De Educaci\u00d3n Especial",
    "sg:phone":"+34 934 58 84 07",
    "sg:postcode":"08013",
    "sg:province":"Barcelona",
    "wof:name":"Fundacio Privada Educativa Dominiques De L'ensenyament",
    "wof:placetype":"venue"
},
  "geometry": {"coordinates":[2.1715750694,41.4007949829],"type":"Point"}
}