{
  "type": "Feature",
  "properties": {
    "addr:full":"Carrer de Via Augusta, S/n S. Vicen\u00e7 Castellet Barcelona 08295",
    "addr:housenumber":"s",
    "addr:postcode":"08295",
    "addr:street":"Carrer De Via Augusta;/ N S. Vicenc\u0327;Barcelona",
    "iso:country":"ES",
    "sg:address":"Carrer de Via Augusta, S/n",
    "sg:city":"S. Vicen\u00e7 Castellet",
    "sg:orig_category":"Aguas (distribuci\u00d3n, Servicios)",
    "sg:phone":"+34 938 33 43 70",
    "sg:postcode":"08295",
    "sg:province":"Barcelona",
    "wof:name":"Sociedad De Abastecimientos Urbanos Y Rurales S. A.",
    "wof:placetype":"venue"
},
  "geometry": {"coordinates":[1.8570100069,41.6684913635],"type":"Point"}
}