{
  "type": "Feature",
  "properties": {
    "iso:country":"ES",
    "sg:address":"Calle de Ferraz, 22",
    "sg:city":"Madrid",
    "sg:orig_category":"Asesor\u00cda Fiscal Y Jur\u00cddica",
    "sg:phone":"+34 917 58 12 00",
    "sg:postcode":"28008",
    "sg:province":"Madrid",
    "wof:name":"Grupo Asesores S.a.",
    "wof:placetype":"venue"
},
  "geometry": {"coordinates":[-3.7160301208,40.4248657227],"type":"Point"}
}