{
  "type": "Feature",
  "properties": {
    "iso:country":"ES",
    "sg:address":"Carrer de Pau Casals, 45",
    "sg:city":"Cambrils",
    "sg:orig_category":"Confecci\u00d3n De Trajes Para Se\u00d1oras",
    "sg:phone":"+34 977 36 50 45",
    "sg:postcode":"43850",
    "sg:province":"Tarragona",
    "wof:name":"Mu\u00f1oz Vilchez Agustina",
    "wof:placetype":"venue"
},
  "geometry": {"coordinates":[1.0624690056,41.0669021606],"type":"Point"}
}