{
  "type": "Feature",
  "properties": {
    "addr:full":"Av Josep Trias, 4 Ca'n Picafort Islas Baleares 07458",
    "addr:housenumber":"4",
    "addr:postcode":"07458",
    "addr:street":"Av Josep Trias",
    "iso:country":"ES",
    "sg:address":"Av Josep Trias, 4",
    "sg:city":"Ca'n Picafort",
    "sg:orig_category":"Molduras, Junquillos, Listones Y Molduras Perforadas",
    "sg:phone":"+34 971 85 06 95",
    "sg:postcode":"07458",
    "sg:province":"Islas Baleares",
    "wof:name":"Castello Vanrell Antonio",
    "wof:placetype":"venue"
},
  "geometry": {"coordinates":[2.9117100239,39.6136398315],"type":"Point"}
}