{
  "type": "Feature",
  "properties": {
    "addr:full":"Calle de Islas Canarias, 25 Valencia Valencia 46023",
    "addr:housenumber":"25",
    "addr:postcode":"46023",
    "addr:street":"Calle De Islas Canarias",
    "iso:country":"ES",
    "sg:address":"Calle de Islas Canarias, 25",
    "sg:city":"Valencia",
    "sg:orig_category":"Asesor\u00cda Sobre Comunicaci\u00d3n De Empresas",
    "sg:phone":"+34 963 37 95 20",
    "sg:postcode":"46023",
    "sg:province":"Valencia",
    "wof:name":"Nemesis Asesores S.l.",
    "wof:placetype":"venue"
},
  "geometry": {"coordinates":[-0.3563629985,39.4665031433],"type":"Point"}
}