{
  "type": "Feature",
  "properties": {
    "iso:country":"ES",
    "sg:address":"Calle de Javier Barkaiztegi, 3",
    "sg:city":"Donostia-san Sebastian",
    "sg:orig_category":"Arquitectos",
    "sg:phone":"+34 943 46 31 01",
    "sg:postcode":"20010",
    "sg:province":"Guip\u00f9zcoa",
    "wof:name":"Arruti Arquitectura S.l.",
    "wof:placetype":"venue"
},
  "geometry": {"coordinates":[-1.9802209139,43.3059196472],"type":"Point"}
}