{
  "type": "Feature",
  "properties": {
    "iso:country":"ES",
    "sg:address":"Av Diagonal, 30",
    "sg:city":"Castelldefels",
    "sg:orig_category":"Farmacias",
    "sg:phone":"+34 936 36 12 80",
    "sg:postcode":"08860",
    "sg:province":"Barcelona",
    "wof:name":"Puig Lluch Ana Maria",
    "wof:placetype":"venue"
},
  "geometry": {"coordinates":[1.9725190401,41.2787094116],"type":"Point"}
}