{
  "type": "Feature",
  "properties": {
    "addr:full":"Calle de Suarez De Salazar, 11 Cadiz C\u00e1diz 11006",
    "addr:housenumber":"11",
    "addr:postcode":"11006",
    "addr:street":"Calle De Suarez De Salazar",
    "iso:country":"ES",
    "sg:address":"Calle de Suarez De Salazar, 11",
    "sg:city":"Cadiz",
    "sg:orig_category":"Prensas Industriales",
    "sg:phone":"+34 956 27 00 51",
    "sg:postcode":"11006",
    "sg:province":"C\u00e1diz",
    "wof:name":"Gonzalez Arriola Francisco",
    "wof:placetype":"venue"
},
  "geometry": {"coordinates":[-6.2919211388,36.5283279419],"type":"Point"}
}