{
  "type": "Feature",
  "properties": {
    "addr:full":"Pg Ribera (de), 1 Tortosa Tarragona 43500",
    "addr:postcode":"43500",
    "addr:street":"Ribera",
    "iso:country":"ES",
    "sg:address":"Pg Ribera (de), 1",
    "sg:city":"Tortosa",
    "sg:orig_category":"Ense\u00d1anza: Comercio, Gesti\u00d3n, Inform\u00c1tica",
    "sg:phone":"+34 977 51 15 00",
    "sg:postcode":"43500",
    "sg:province":"Tarragona",
    "wof:name":"Oficomplet 75 S.l.",
    "wof:placetype":"venue"
},
  "geometry": {"coordinates":[0.5175899863,40.807308197],"type":"Point"}
}