{
  "type": "Feature",
  "properties": {
    "addr:full":"Carr Penyal, De Na, 24 Cala Millor Islas Baleares 07560",
    "addr:housenumber":"24",
    "addr:postcode":"07560",
    "addr:street":"Carr Penyal De Na;Millor",
    "iso:country":"ES",
    "sg:address":"Carr Penyal, De Na, 24",
    "sg:city":"Cala Millor",
    "sg:orig_category":"Servicios Gsm",
    "sg:phone":"+34 971 58 72 49",
    "sg:postcode":"07560",
    "sg:province":"Islas Baleares",
    "wof:name":"Asesoria Mediterranea Telecom S.l.",
    "wof:placetype":"venue"
},
  "geometry": {"coordinates":[3.382986784,39.6040153503],"type":"Point"}
}