{
  "type": "Feature",
  "properties": {
    "iso:country":"ES",
    "sg:address":"Avda Cid Campeador, S/n",
    "sg:city":"Soria",
    "sg:orig_category":"Centros De Educaci\u00d3n Especial",
    "sg:phone":"+34 975 22 58 38",
    "sg:postcode":"42004",
    "sg:province":"Soria",
    "wof:name":"Colegio Publico Los Doce Linajes",
    "wof:placetype":"venue"
},
  "geometry": {"coordinates":[-2.4829740524,41.7697486877],"type":"Point"}
}