{
  "type": "Feature",
  "properties": {
    "addr:full":"Carr Belgica, 31 Badalona Barcelona 08917",
    "addr:housenumber":"31",
    "addr:postcode":"08917",
    "addr:street":"Carr Belgica",
    "iso:country":"ES",
    "sg:address":"Carr Belgica, 31",
    "sg:city":"Badalona",
    "sg:orig_category":"Confecci\u00d3n De Trajes Para Se\u00d1oras",
    "sg:phone":"+34 933 95 64 36",
    "sg:postcode":"08917",
    "sg:province":"Barcelona",
    "wof:name":"Carolyjohn S.l.",
    "wof:placetype":"venue"
},
  "geometry": {"coordinates":[2.2236700058,41.4585609436],"type":"Point"}
}