{
  "type": "Feature",
  "properties": {
    "addr:full":"Calle de Martires, 109 Roda Albacete 02630",
    "addr:housenumber":"109",
    "addr:postcode":"02630",
    "addr:street":"Calle De Martires",
    "iso:country":"ES",
    "sg:address":"Calle de Martires, 109",
    "sg:city":"Roda",
    "sg:orig_category":"Propiedad Industrial: Patentes De Inventos, Marcas, Modelos, Dise\u00d1os",
    "sg:phone":"+34 967 44 50 17",
    "sg:postcode":"02630",
    "sg:province":"Albacete",
    "wof:name":"Ok Publicidad S.l.",
    "wof:placetype":"venue"
},
  "geometry": {"coordinates":[-2.1667189598,39.2107086182],"type":"Point"}
}