{
  "type": "Feature",
  "properties": {
    "addr:full":"Pol Ind Venta Colores, S/n Mancha Real Ja\u00e9n 23100",
    "addr:housenumber":"s / n",
    "addr:postcode":"23100",
    "iso:country":"ES",
    "sg:address":"Pol Ind Venta Colores, S/n",
    "sg:city":"Mancha Real",
    "sg:orig_category":"Fabricaci\u00d3n, Venta De Cuadros, Accesorios Para Enmarcar",
    "sg:phone":"+34 953 35 26 81",
    "sg:postcode":"23100",
    "sg:province":"Ja\u00e9n",
    "wof:name":"Molduline S.l.",
    "wof:placetype":"venue"
},
  "geometry": {"coordinates":[-3.6184639931,37.8074951172],"type":"Point"}
}