{
  "type": "Feature",
  "properties": {
    "iso:country":"ES",
    "sg:address":"Calle de Martires, 92",
    "sg:city":"Roda",
    "sg:orig_category":"Comercio De Piezas De Recambio Y De Accesorios De Veh\u00cdculos, Veh\u00cdculos Industriales",
    "sg:phone":"+34 967 44 10 03",
    "sg:postcode":"02630",
    "sg:province":"Albacete",
    "wof:name":"Hernandez Vazquez Angel",
    "wof:placetype":"venue"
},
  "geometry": {"coordinates":[-2.1667189598,39.2107086182],"type":"Point"}
}