{
  "type": "Feature",
  "properties": {
    "iso:country":"ES",
    "sg:address":"Pg Prim, 29",
    "sg:city":"Reus",
    "sg:orig_category":"Molduras, Junquillos, Listones Y Molduras Perforadas",
    "sg:phone":"+34 977 32 36 87",
    "sg:postcode":"43202",
    "sg:province":"Tarragona",
    "wof:name":"Lampurdanes Borrell Ramon",
    "wof:placetype":"venue"
},
  "geometry": {"coordinates":[1.1033569574,41.1509399414],"type":"Point"}
}