{
  "type": "Feature",
  "properties": {
    "addr:full":"Carrer de Rossello I Ca\u00c7ador, 20 Palma Islas Baleares 07004",
    "addr:housenumber":"20",
    "addr:postcode":"07004",
    "addr:street":"Carrer De Rossello;Cac\u0327Ador",
    "iso:country":"ES",
    "sg:address":"Carrer de Rossello I Ca\u00c7ador, 20",
    "sg:city":"Palma",
    "sg:orig_category":"Peluquer\u00cdas, Peluquer\u00cda Mixta",
    "sg:phone":"+34 971 29 05 58",
    "sg:postcode":"07004",
    "sg:province":"Islas Baleares",
    "wof:name":"Serantes Masia Adelina Vanessa",
    "wof:placetype":"venue"
},
  "geometry": {"coordinates":[2.6531960964,39.5818824768],"type":"Point"}
}