{
  "type": "Feature",
  "properties": {
    "iso:country":"ES",
    "sg:address":"Calle de Nicolas Mateos, 7",
    "sg:city":"Noblejas",
    "sg:orig_category":"Reposter\u00cdas",
    "sg:phone":"+34 925 14 03 00",
    "sg:postcode":"45350",
    "sg:province":"Toledo",
    "wof:name":"Crespo Crespo Isidro",
    "wof:placetype":"venue"
},
  "geometry": {"coordinates":[-3.4391400814,39.9785118103],"type":"Point"}
}