{
  "type": "Feature",
  "properties": {
    "addr:full":"Caseta Benataire, S/n Muro Alcoy Alicante 03830",
    "addr:housenumber":"s",
    "addr:postcode":"03830",
    "addr:street":"/ N Muro",
    "iso:country":"ES",
    "sg:address":"Caseta Benataire, S/n",
    "sg:city":"Muro Alcoy",
    "sg:orig_category":"Zapater\u00cds Y Cordeler\u00cda",
    "sg:phone":"+34 965 53 00 62",
    "sg:postcode":"03830",
    "sg:province":"Alicante",
    "wof:name":"Trenzalba S. A.",
    "wof:placetype":"venue"
},
  "geometry": {"coordinates":[-0.4414289892,38.7812538147],"type":"Point"}
}