{
  "type": "Feature",
  "properties": {
    "addr:full":"Calle de General Pintos, 25 Alacant Alicante 03010",
    "addr:housenumber":"25",
    "addr:postcode":"03010",
    "addr:street":"Calle De General Pintos",
    "iso:country":"ES",
    "sg:address":"Calle de General Pintos, 25",
    "sg:city":"Alacant",
    "sg:orig_category":"Molduras, Junquillos, Listones Y Molduras Perforadas",
    "sg:phone":"+34 965 25 19 41",
    "sg:postcode":"03010",
    "sg:province":"Alicante",
    "wof:name":"Diaz Gonzalez Jose",
    "wof:placetype":"venue"
},
  "geometry": {"coordinates":[-0.4878090024,38.3596572876],"type":"Point"}
}