{
  "type": "Feature",
  "properties": {
    "iso:country":"ES",
    "sg:address":"Carrer de Garcia Humet, 39",
    "sg:city":"Terrassa",
    "sg:orig_category":"Cl\u00cdnicas M\u00c9dicas",
    "sg:phone":"+34 937 83 72 99",
    "sg:postcode":"08221",
    "sg:province":"Barcelona",
    "wof:name":"Egarmatic S. A.",
    "wof:placetype":"venue"
},
  "geometry": {"coordinates":[2.0150079727,41.565700531],"type":"Point"}
}