{
  "type": "Feature",
  "properties": {
    "addr:full":"Avda Movera, 382 Movera Zaragoza 50194",
    "addr:housenumber":"382",
    "addr:postcode":"50194",
    "addr:street":"Avda Movera",
    "iso:country":"ES",
    "sg:address":"Avda Movera, 382",
    "sg:city":"Movera",
    "sg:orig_category":"Hormig\u00d3n Listo Para Usar",
    "sg:phone":"+34 976 58 63 71",
    "sg:postcode":"50194",
    "sg:province":"Zaragoza",
    "wof:name":"Tubos Besmo Sl",
    "wof:placetype":"venue"
},
  "geometry": {"coordinates":[-0.8233950138,41.6493644714],"type":"Point"}
}