{
  "type": "Feature",
  "properties": {
    "addr:full":"Ctra Almunia (de La), S/n Cari\u00f1ena Zaragoza 50400",
    "addr:postcode":"50400",
    "addr:street":"Ctra Almunia De La S / N Carin\u0303Ena",
    "iso:country":"ES",
    "sg:address":"Ctra Almunia (de La), S/n",
    "sg:city":"Cari\u00f1ena",
    "sg:orig_category":"Ingeniero",
    "sg:phone":"+34 976 62 01 29",
    "sg:postcode":"50400",
    "sg:province":"Zaragoza",
    "wof:name":"Tome Sebastian Miguel Angel",
    "wof:placetype":"venue"
},
  "geometry": {"coordinates":[-1.2234489918,41.340675354],"type":"Point"}
}