{
  "type": "Feature",
  "properties": {
    "addr:full":"C/ Manuel Lopez Quereda, 47 Elche Alicante 03204",
    "addr:housenumber":"47",
    "addr:postcode":"03204",
    "addr:street":"C / Manuel;Quereda",
    "iso:country":"ES",
    "sg:address":"C/ Manuel Lopez Quereda, 47",
    "sg:city":"Elche",
    "sg:orig_category":"Ense\u00d1anza: Idiomas",
    "sg:phone":"+34 966 63 45 53",
    "sg:postcode":"03204",
    "sg:province":"Alicante",
    "wof:name":"Marquez Ferrer Loreto",
    "wof:placetype":"venue"
},
  "geometry": {"coordinates":[-0.7052729726,38.2590179443],"type":"Point"}
}