{
  "type": "Feature",
  "properties": {
    "iso:country":"ES",
    "sg:address":"Avda Cervantes, 51",
    "sg:city":"Arizgoiti",
    "sg:orig_category":"Empresas De Vigilancia, Guardia Y Protecci\u00d3n",
    "sg:phone":"+34 944 26 29 80",
    "sg:postcode":"48970",
    "sg:province":"Vizcaya",
    "sg:website":"www.silicia.es",
    "wof:name":"Sabico Seguridad S.a.",
    "wof:placetype":"venue"
},
  "geometry": {"coordinates":[-2.8774580956,43.2388687134],"type":"Point"}
}