{
  "type": "Feature",
  "properties": {
    "iso:country":"ES",
    "sg:address":"Carrer de Llan\u00c7a, 47",
    "sg:city":"Barcelona",
    "sg:orig_category":"Abogados",
    "sg:phone":"+34 934 54 54 57",
    "sg:postcode":"08015",
    "sg:province":"Barcelona",
    "wof:name":"Cardenas Salamanca Manuel",
    "wof:placetype":"venue"
},
  "geometry": {"coordinates":[2.1449010372,41.3803405762],"type":"Point"}
}