{
  "type": "Feature",
  "properties": {
    "iso:country":"ES",
    "sg:address":"Calle de Rafael Beca, 53",
    "sg:city":"Alcala Guadaira",
    "sg:orig_category":"Molduras, Junquillos, Listones Y Molduras Perforadas",
    "sg:phone":"+34 955 61 25 00",
    "sg:postcode":"41500",
    "sg:province":"Sevilla",
    "wof:name":"Cortes Ramirez Antonio",
    "wof:placetype":"venue"
},
  "geometry": {"coordinates":[-5.8324837685,37.3365058899],"type":"Point"}
}