{
  "type": "Feature",
  "properties": {
    "iso:country":"ES",
    "sg:address":"Calle de Nuestra Se\u00d1ora De Valme, S/n",
    "sg:city":"Dos Hermanas",
    "sg:orig_category":"Cristaler\u00cda: Suministros",
    "sg:phone":"+34 955 66 57 97",
    "sg:postcode":"41700",
    "sg:province":"Sevilla",
    "wof:name":"Recuperadora De Vidrio S.a.",
    "wof:placetype":"venue"
},
  "geometry": {"coordinates":[-5.9225549698,37.2844543457],"type":"Point"}
}