{
  "type": "Feature",
  "properties": {
    "iso:country":"ES",
    "sg:address":"Calle de Guzman El Bueno, 133",
    "sg:city":"Madrid",
    "sg:orig_category":"Ingenier\u00cda, Centros De Estudios (diversos)",
    "sg:phone":"+34 915 54 70 78",
    "sg:postcode":"28003",
    "sg:province":"Madrid",
    "sg:website":"www.ariesnaval.com",
    "wof:name":"Aries Industrial Y Naval S. A.",
    "wof:placetype":"venue"
},
  "geometry": {"coordinates":[-3.7125484943,40.4431762695],"type":"Point"}
}