{
  "type": "Feature",
  "properties": {
    "iso:country":"ES",
    "sg:address":"Calle de Magdalena, 28",
    "sg:city":"Errenteria",
    "sg:orig_category":"Molduras, Junquillos, Listones Y Molduras Perforadas",
    "sg:phone":"+34 943 00 34 40",
    "sg:postcode":"20100",
    "sg:province":"Guip\u00f9zcoa",
    "wof:name":"Bar Manuel C.b.",
    "wof:placetype":"venue"
},
  "geometry": {"coordinates":[-1.9006530046,43.3118400574],"type":"Point"}
}