{
  "type": "Feature",
  "properties": {
    "addr:full":"Calle de Jose Maria Moreno, 20 Torrelodones Madrid 28250",
    "addr:housenumber":"20",
    "addr:postcode":"28250",
    "addr:street":"Calle De Jose Maria Moreno",
    "iso:country":"ES",
    "sg:address":"Calle de Jose Maria Moreno, 20",
    "sg:city":"Torrelodones",
    "sg:orig_category":"Asesor\u00cdas En Comunicaci\u00d3n",
    "sg:phone":"+34 918 59 64 20",
    "sg:postcode":"28250",
    "sg:province":"Madrid",
    "wof:name":"Sec Y Gomez Mar Asociados S.l.",
    "wof:placetype":"venue"
},
  "geometry": {"coordinates":[-3.9280900955,40.5785369873],"type":"Point"}
}