{
  "type": "Feature",
  "properties": {
    "iso:country":"ES",
    "sg:address":"Av Can Magarola, 22",
    "sg:city":"Mollet Valles",
    "sg:orig_category":"Empresas De Desmonte",
    "sg:phone":"+34 935 79 80 27",
    "sg:postcode":"08100",
    "sg:province":"Barcelona",
    "wof:name":"Transportes Jaime-84 S.a.",
    "wof:placetype":"venue"
},
  "geometry": {"coordinates":[2.2287650108,41.5498352051],"type":"Point"}
}