{
  "type": "Feature",
  "properties": {
    "iso:country":"ES",
    "sg:address":"Calle de Segovia, Km. 0048,8",
    "sg:city":"Cantalejo",
    "sg:orig_category":"Muebles, Minoristas",
    "sg:phone":"+34 921 52 03 78",
    "sg:postcode":"40320",
    "sg:province":"Segovia",
    "wof:name":"Lobo San German Gregorio",
    "wof:placetype":"venue"
},
  "geometry": {"coordinates":[-3.9288260937,41.2551383972],"type":"Point"}
}