{
  "type": "Feature",
  "properties": {
    "addr:full":"Avda Doctor Garcia Rogel, 37 Orihuela Alicante 03300",
    "addr:housenumber":"37",
    "addr:postcode":"03300",
    "addr:street":"Avda Doctor Garcia Rogel",
    "iso:country":"ES",
    "sg:address":"Avda Doctor Garcia Rogel, 37",
    "sg:city":"Orihuela",
    "sg:orig_category":"Ingeniero",
    "sg:phone":"+34 965 30 21 36",
    "sg:postcode":"03300",
    "sg:province":"Alicante",
    "wof:name":"Consultel Bacan S.l.",
    "wof:placetype":"venue"
},
  "geometry": {"coordinates":[-0.9355999827,38.0982055664],"type":"Point"}
}