{
  "type": "Feature",
  "properties": {
    "addr:full":"Pase Chopera, 63 Madrid Madrid 28045",
    "addr:housenumber":"63",
    "addr:postcode":"madrid;28045",
    "iso:country":"ES",
    "sg:address":"Pase Chopera, 63",
    "sg:city":"Madrid",
    "sg:orig_category":"Farmacias",
    "sg:phone":"+34 915 27 09 72",
    "sg:postcode":"28045",
    "sg:province":"Madrid",
    "wof:name":"Freire Escobar Jovita",
    "wof:placetype":"venue"
},
  "geometry": {"coordinates":[-3.6965088844,40.3923454285],"type":"Point"}
}