{
  "type": "Feature",
  "properties": {
    "addr:full":"Carrer de Francesc Macia, 4 Valls Tarragona 43800",
    "addr:housenumber":"4",
    "addr:postcode":"43800",
    "addr:street":"Carrer De Francesc Macia",
    "iso:country":"ES",
    "sg:address":"Carrer de Francesc Macia, 4",
    "sg:city":"Valls",
    "sg:orig_category":"Peluquer\u00cdas, Peluquer\u00cda Mixta",
    "sg:phone":"+34 977 60 40 09",
    "sg:postcode":"43800",
    "sg:province":"Tarragona",
    "wof:name":"Silva Iglesias Francisca",
    "wof:placetype":"venue"
},
  "geometry": {"coordinates":[1.2573440075,41.2878036499],"type":"Point"}
}