{
  "type": "Feature",
  "properties": {
    "iso:country":"ES",
    "sg:address":"Avda Constitucion, 27",
    "sg:city":"Don Benito",
    "sg:orig_category":"Ropa Para Ni\u00d1os (al Por Menor)",
    "sg:phone":"+34 924 80 04 42",
    "sg:postcode":"06400",
    "sg:province":"Badajoz",
    "wof:name":"Duran Arregui Manuela",
    "wof:placetype":"venue"
},
  "geometry": {"coordinates":[-5.8627138138,38.9662666321],"type":"Point"}
}