{
  "type": "Feature",
  "properties": {
    "addr:full":"Avda Galicia, S/n Cambados Pontevedra 36630",
    "addr:housenumber":"s / n",
    "addr:postcode":"36630",
    "addr:street":"Avda Galicia",
    "iso:country":"ES",
    "sg:address":"Avda Galicia, S/n",
    "sg:city":"Cambados",
    "sg:orig_category":"Conservas De Pescados Y Salazones Mar\u00cdtimos (fabricaci\u00d3n, Al Por Mayor)",
    "sg:phone":"+34 986 52 01 12",
    "sg:postcode":"36630",
    "sg:province":"Pontevedra",
    "wof:name":"Conservas Daporta S.l.",
    "wof:placetype":"venue"
},
  "geometry": {"coordinates":[-8.8156642914,42.5111503601],"type":"Point"}
}