{
  "type": "Feature",
  "properties": {
    "iso:country":"ES",
    "sg:address":"Calle de Bachiller Alonso Lopez (del), 13",
    "sg:city":"Alcobendas",
    "sg:orig_category":"Asociaciones, Organismos Culturales Y Socioeducativos",
    "sg:phone":"+34 916 63 61 20",
    "sg:postcode":"28100",
    "sg:province":"Madrid",
    "wof:name":"Patronato Socio-cultural De Alcobendas",
    "wof:placetype":"venue"
},
  "geometry": {"coordinates":[-3.6350252628,40.5456123352],"type":"Point"}
}