{
  "type": "Feature",
  "properties": {
    "iso:country":"ES",
    "sg:address":"Carrer de Arimon, 19",
    "sg:city":"Barcelona",
    "sg:orig_category":"Peluquer\u00cdas, Peluquer\u00cda Mixta",
    "sg:phone":"+34 934 17 10 19",
    "sg:postcode":"08022",
    "sg:province":"Barcelona",
    "wof:name":"Taborda Rodriguez Julia Adaliz",
    "wof:placetype":"venue"
},
  "geometry": {"coordinates":[2.1369719505,41.4041404724],"type":"Point"}
}