{
  "type": "Feature",
  "properties": {
    "iso:country":"ES",
    "sg:address":"Avda Rey Juan Carlos I, 53",
    "sg:city":"Tarancon",
    "sg:orig_category":"Supermercados Y Hipermercados",
    "sg:phone":"+34 969 32 28 68",
    "sg:postcode":"16400",
    "sg:province":"Cuenca",
    "wof:name":"Todymas S.a.",
    "wof:placetype":"venue"
},
  "geometry": {"coordinates":[-3.0034270287,40.0042533875],"type":"Point"}
}