{
  "type": "Feature",
  "properties": {
    "iso:country":"ES",
    "sg:address":"Calle de Cigue\u00d1a (la), 45",
    "sg:city":"Logro\u00f1o",
    "sg:orig_category":"Carnicer\u00cdas, Carnicer\u00cdas",
    "sg:phone":"+34 941 23 14 69",
    "sg:postcode":"26004",
    "sg:province":"La Rioja",
    "wof:name":"Ubis Espiga Felix",
    "wof:placetype":"venue"
},
  "geometry": {"coordinates":[-2.430382967,42.4648208618],"type":"Point"}
}