{
  "type": "Feature",
  "properties": {
    "addr:full":"Ctra Ametlla, 20 Garriga Barcelona 08530",
    "addr:housenumber":"20",
    "addr:postcode":"08530",
    "addr:street":"Ctra Ametlla",
    "iso:country":"ES",
    "sg:address":"Ctra Ametlla, 20",
    "sg:city":"Garriga",
    "sg:orig_category":"Delegados, Agentes De Tr\u00c1nsito, Auxiliares De Transporte Internacional",
    "sg:phone":"+34 938 71 74 78",
    "sg:postcode":"08530",
    "sg:province":"Barcelona",
    "wof:name":"Bedmar Borjas Miguel Angel",
    "wof:placetype":"venue"
},
  "geometry": {"coordinates":[2.2847700119,41.6811218262],"type":"Point"}
}