{
  "type": "Feature",
  "properties": {
    "iso:country":"ES",
    "sg:address":"Ctra. Villanueva, Km. 0099,1",
    "sg:city":"Don Benito",
    "sg:orig_category":"Electricidad: Equipos Industriales, Componentes (fabricaci\u00d3n)",
    "sg:phone":"+34 924 81 23 01",
    "sg:postcode":"06400",
    "sg:province":"Badajoz",
    "sg:website":"www.rsierra.es",
    "wof:name":"Ramos Sierra S.a.",
    "wof:placetype":"venue"
},
  "geometry": {"coordinates":[-5.8639888763,38.9548797607],"type":"Point"}
}