{
  "type": "Feature",
  "properties": {
    "addr:full":"Calle de Marques De Velasco, S/n Noja Cantabria 39180",
    "addr:postcode":"39180",
    "addr:street":"Calle De Marques De Velasco S / N",
    "iso:country":"ES",
    "sg:address":"Calle de Marques De Velasco, S/n",
    "sg:city":"Noja",
    "sg:orig_category":"Venta, Instalaci\u00d3n De Calefacci\u00d3n",
    "sg:phone":"+34 942 63 10 62",
    "sg:postcode":"39180",
    "sg:province":"Cantabria",
    "wof:name":"Nojagas S.l.",
    "wof:placetype":"venue"
},
  "geometry": {"coordinates":[-3.5218589306,43.4811248779],"type":"Point"}
}