{
  "type": "Feature",
  "properties": {
    "iso:country":"ES",
    "sg:address":"Calle de Doctor Iranzo, 86",
    "sg:city":"Zaragoza",
    "sg:orig_category":"Electricidad: Instaladores",
    "sg:phone":"+34 976 39 18 38",
    "sg:postcode":"50002",
    "sg:province":"Zaragoza",
    "wof:name":"Satrustegui Juanena Juan Jose",
    "wof:placetype":"venue"
},
  "geometry": {"coordinates":[-0.8633239865,41.6496276855],"type":"Point"}
}