{
  "type": "Feature",
  "properties": {
    "iso:country":"ES",
    "sg:address":"Avda Florida, 235",
    "sg:city":"Vigo",
    "sg:orig_category":"Mec\u00c1nico Del Autom\u00d3vil",
    "sg:phone":"+34 986 20 30 32",
    "sg:postcode":"36210",
    "sg:province":"Pontevedra",
    "wof:name":"Talleres Acu\u00f1a S.l.",
    "wof:placetype":"venue"
},
  "geometry": {"coordinates":[-8.7508792877,42.2073898315],"type":"Point"}
}