{
  "type": "Feature",
  "properties": {
    "iso:country":"ES",
    "sg:address":"Calle de Francisco Lopez Sanchez, 13",
    "sg:city":"Mengibar",
    "sg:orig_category":"Muebles Y Accesorios Para Cocinas Y Cuartos De Ba\u00d1o (al Por Menor)",
    "sg:phone":"+34 953 37 28 20",
    "sg:postcode":"23620",
    "sg:province":"Ja\u00e9n",
    "wof:name":"Gabifran Cocinas S.l.l.",
    "wof:placetype":"venue"
},
  "geometry": {"coordinates":[-3.8033540249,37.970615387],"type":"Point"}
}