{
  "type": "Feature",
  "properties": {
    "iso:country":"ES",
    "sg:address":"Rua Alta, 22",
    "sg:city":"Vigo",
    "sg:orig_category":"Plomeros",
    "sg:phone":"+34 986 43 50 97",
    "sg:postcode":"36202",
    "sg:province":"Pontevedra",
    "wof:name":"Barros Bascoy Jaime",
    "wof:placetype":"venue"
},
  "geometry": {"coordinates":[-8.7277870178,42.2383537292],"type":"Point"}
}