{
  "type": "Feature",
  "properties": {
    "addr:full":"Carrer de Ample, 39 Reus Tarragona 43202",
    "addr:housenumber":"39",
    "addr:postcode":"43202",
    "addr:street":"Carrer De Ample",
    "iso:country":"ES",
    "sg:address":"Carrer de Ample, 39",
    "sg:city":"Reus",
    "sg:orig_category":"Librer\u00cdas",
    "sg:phone":"+34 977 31 75 58",
    "sg:postcode":"43202",
    "sg:province":"Tarragona",
    "wof:name":"Bordes Miro Rosa Maria",
    "wof:placetype":"venue"
},
  "geometry": {"coordinates":[1.1041179895,41.1590194702],"type":"Point"}
}