{
  "type": "Feature",
  "properties": {
    "iso:country":"ES",
    "sg:address":"Carr Costa I Llobera, 12",
    "sg:city":"Felanitx",
    "sg:orig_category":"Empresas De Carpinter\u00cda De Madera",
    "sg:phone":"+34 971 58 09 86",
    "sg:postcode":"07200",
    "sg:province":"Islas Baleares",
    "wof:name":"Vicens Roig Antoni",
    "wof:placetype":"venue"
},
  "geometry": {"coordinates":[3.145720005,39.4688148499],"type":"Point"}
}