{
  "type": "Feature",
  "properties": {
    "addr:full":"Av Hispanitat, 21 Poblenou Barcelona 08397",
    "addr:housenumber":"21",
    "addr:postcode":"08397",
    "addr:street":"Av Hispanitat",
    "iso:country":"ES",
    "sg:address":"Av Hispanitat, 21",
    "sg:city":"Poblenou",
    "sg:orig_category":"Cajas De Ahorro",
    "sg:phone":"+34 937 69 05 42",
    "sg:postcode":"08397",
    "sg:province":"Barcelona",
    "sg:website":"www.lacaixa.es",
    "wof:name":"Caixa D'estalvis I Pensions De Barcelona",
    "wof:placetype":"venue"
},
  "geometry": {"coordinates":[2.6718709469,41.6183624268],"type":"Point"}
}