{
  "type": "Feature",
  "properties": {
    "addr:full":"Avda Espa\u00d1a, 190 Estepona M\u00e1laga 29680",
    "addr:housenumber":"190",
    "addr:postcode":"29680",
    "addr:street":"Avda Espan\u0303A",
    "iso:country":"ES",
    "sg:address":"Avda Espa\u00d1a, 190",
    "sg:city":"Estepona",
    "sg:orig_category":"Inmobiliaria (agencias)",
    "sg:phone":"+34 952 80 85 70",
    "sg:postcode":"29680",
    "sg:province":"M\u00e1laga",
    "sg:website":"www.gilmarinmobiliaria.com",
    "wof:name":"Consulting Inmobiliario Gilmar S.a.",
    "wof:placetype":"venue"
},
  "geometry": {"coordinates":[-5.1472787857,36.4229888916],"type":"Point"}
}