{
  "type": "Feature",
  "properties": {
    "addr:full":"Foruen Plaza, 5 Elgoibar Guip\u00f9zcoa 20870",
    "addr:housenumber":"5",
    "addr:postcode":"20870",
    "addr:street":"Foruen Plaza;Guipu\u0300Zcoa",
    "iso:country":"ES",
    "sg:address":"Foruen Plaza, 5",
    "sg:city":"Elgoibar",
    "sg:orig_category":"Molduras, Junquillos, Listones Y Molduras Perforadas",
    "sg:phone":"+34 943 53 17 84",
    "sg:postcode":"20870",
    "sg:province":"Guip\u00f9zcoa",
    "wof:name":"Gil Unamunzaga , M\u00aa Teresa",
    "wof:placetype":"venue"
},
  "geometry": {"coordinates":[-2.4171080589,43.2145652771],"type":"Point"}
}