{
  "type": "Feature",
  "properties": {
    "iso:country":"ES",
    "sg:address":"Calle de Fontaneros, 3",
    "sg:city":"Villaviciosa Odon",
    "sg:orig_category":"Chapister\u00cda",
    "sg:phone":"+34 916 16 23 61",
    "sg:postcode":"28670",
    "sg:province":"Madrid",
    "wof:name":"Autos Hermanos Navarrete S.l.",
    "wof:placetype":"venue"
},
  "geometry": {"coordinates":[-3.9098460674,40.3455276489],"type":"Point"}
}