{
  "type": "Feature",
  "properties": {
    "addr:full":"Plaz San Pedro, 12 Daimiel Ciudad Real 13250",
    "addr:housenumber":"12",
    "addr:postcode":"13250",
    "addr:street":"Plaz San Pedro",
    "iso:country":"ES",
    "sg:address":"Plaz San Pedro, 12",
    "sg:city":"Daimiel",
    "sg:orig_category":"Organizaci\u00d3n De Actos, Seminarios Y Congresos",
    "sg:phone":"+34 926 85 43 51",
    "sg:postcode":"13250",
    "sg:province":"Ciudad Real",
    "wof:name":"Daimiele\u00f1a De Restauracion Y Ocio S.l.",
    "wof:placetype":"venue"
},
  "geometry": {"coordinates":[-3.617358923,39.0695037842],"type":"Point"}
}