{
  "type": "Feature",
  "properties": {
    "iso:country":"ES",
    "sg:address":"Kale Barria, 31",
    "sg:city":"O\u00f1ati",
    "sg:orig_category":"Reposter\u00cdas",
    "sg:phone":"+34 943 78 14 67",
    "sg:postcode":"20560",
    "sg:province":"Guip\u00f9zcoa",
    "wof:name":"Ega\u00f1a Okindegia, S.l",
    "wof:placetype":"venue"
},
  "geometry": {"coordinates":[-2.4106230736,43.0316085815],"type":"Point"}
}