{
  "type": "Feature",
  "properties": {
    "iso:country":"ES",
    "sg:address":"Calle de Mundaiz, 16",
    "sg:city":"Donostia-san Sebastian",
    "sg:orig_category":"Compresores",
    "sg:phone":"+34 943 27 27 00",
    "sg:postcode":"20012",
    "sg:province":"Guip\u00f9zcoa",
    "wof:name":"Suministros Industriales Alarpe S.l.",
    "wof:placetype":"venue"
},
  "geometry": {"coordinates":[-1.977290988,43.31432724],"type":"Point"}
}