{
  "type": "Feature",
  "properties": {
    "addr:full":"Avda Obispo Perez Caceres, 22 G\u00fcimar Santa Cruz De Tenerife 38500",
    "addr:housenumber":"22",
    "addr:postcode":"38500",
    "addr:street":"Avda Obispo Perez Caceres",
    "iso:country":"ES",
    "sg:address":"Avda Obispo Perez Caceres, 22",
    "sg:city":"G\u00fcimar",
    "sg:orig_category":"Bisuteros (fabricaci\u00d3n, Al Por Mayor)",
    "sg:phone":"+34 922 51 21 78",
    "sg:postcode":"38500",
    "sg:province":"Santa Cruz De Tenerife",
    "wof:name":"Pemajona, S.l.",
    "wof:placetype":"venue"
},
  "geometry": {"coordinates":[-16.4103622437,28.3152656555],"type":"Point"}
}