{
  "type": "Feature",
  "properties": {
    "addr:full":"Molino, S/n Ordes La Coru\u00f1a 15680",
    "addr:postcode":"15680",
    "addr:street":"S / N;La Corun\u0303A",
    "iso:country":"ES",
    "sg:address":"Molino, S/n",
    "sg:city":"Ordes",
    "sg:orig_category":"Procuradores",
    "sg:phone":"+34 981 69 78 94",
    "sg:postcode":"15680",
    "sg:province":"La Coru\u00f1a",
    "wof:name":"Colegio De Procuradores De Santiago",
    "wof:placetype":"venue"
},
  "geometry": {"coordinates":[-8.4072790146,43.0771408081],"type":"Point"}
}