{
  "type": "Feature",
  "properties": {
    "iso:country":"ES",
    "sg:address":"Calle de Arroyo, 5",
    "sg:city":"Carbajosa Sagrada",
    "sg:orig_category":"Supermercados Y Hipermercados",
    "sg:phone":"+34 923 20 83 41",
    "sg:postcode":"37188",
    "sg:province":"Salamanca",
    "wof:name":"Gonzalez Pantaleon Miguel Angel",
    "wof:placetype":"venue"
},
  "geometry": {"coordinates":[-5.6598405838,40.9742927551],"type":"Point"}
}