{
  "type": "Feature",
  "properties": {
    "iso:country":"ES",
    "sg:address":"Calle de San Antonio, 12",
    "sg:city":"Villanueva Cordoba",
    "sg:orig_category":"Reposter\u00cdas",
    "sg:phone":"+34 957 12 12 97",
    "sg:postcode":"14440",
    "sg:province":"C\u00f3rdoba",
    "wof:name":"Ruiz Palomo Diego",
    "wof:placetype":"venue"
},
  "geometry": {"coordinates":[-4.6280422211,38.3176498413],"type":"Point"}
}