{
  "type": "Feature",
  "properties": {
    "addr:full":"Plaz Iglesia (de La), 16 Urda Toledo 45480",
    "addr:postcode":"45480",
    "iso:country":"ES",
    "sg:address":"Plaz Iglesia (de La), 16",
    "sg:city":"Urda",
    "sg:orig_category":"Farmacias",
    "sg:phone":"+34 925 47 20 19",
    "sg:postcode":"45480",
    "sg:province":"Toledo",
    "wof:name":"Garcia Condado Antonio",
    "wof:placetype":"venue"
},
  "geometry": {"coordinates":[-3.7219750881,39.4137535095],"type":"Point"}
}