{
  "type": "Feature",
  "properties": {
    "iso:country":"ES",
    "sg:address":"Carrer de Major, 12",
    "sg:city":"Rourell",
    "sg:orig_category":"Artes Gr\u00c1ficas, Artes Pl\u00c1sticas (curso)",
    "sg:phone":"+34 977 84 11 19",
    "sg:postcode":"43142",
    "sg:province":"Tarragona",
    "sg:website":"www.comtgn.com/madvi",
    "wof:name":"Serveis Integrals De Publicitat Madvi S.l.",
    "wof:placetype":"venue"
},
  "geometry": {"coordinates":[1.2180650234,41.2235603333],"type":"Point"}
}