{
  "type": "Feature",
  "properties": {
    "addr:full":"Calle de Echegaray, 6 Salamanca Salamanca 37005",
    "addr:housenumber":"6",
    "addr:postcode":"37005",
    "addr:street":"Calle De Echegaray",
    "iso:country":"ES",
    "sg:address":"Calle de Echegaray, 6",
    "sg:city":"Salamanca",
    "sg:orig_category":"Electrodom\u00c9sticos (al Por Menor)",
    "sg:phone":"+34 923 25 40 45",
    "sg:postcode":"37005",
    "sg:province":"Salamanca",
    "wof:name":"Graniere S.l.",
    "wof:placetype":"venue"
},
  "geometry": {"coordinates":[-5.6610980034,40.9707832336],"type":"Point"}
}