{
  "type": "Feature",
  "properties": {
    "iso:country":"ES",
    "sg:address":"Ctra San Javier, 22",
    "sg:city":"La Puebla",
    "sg:orig_category":"Farmacias",
    "sg:phone":"+34 968 55 91 28",
    "sg:postcode":"30395",
    "sg:province":"Murcia",
    "wof:name":"Obradors Rosique Juan Carlos",
    "wof:placetype":"venue"
},
  "geometry": {"coordinates":[-0.9203090072,37.717918396],"type":"Point"}
}