{
  "type": "Feature",
  "properties": {
    "iso:country":"ES",
    "sg:address":"Luga Bolonia, S/n",
    "sg:city":"Bolonia",
    "sg:orig_category":"Urbanistas",
    "sg:phone":"+34 956 68 85 79",
    "sg:postcode":"11391",
    "sg:province":"C\u00e1diz",
    "wof:name":"Del Rio Jorge Angel Maria",
    "wof:placetype":"venue"
},
  "geometry": {"coordinates":[-5.7029819489,36.1468696594],"type":"Point"}
}