{
  "type": "Feature",
  "properties": {
    "iso:country":"ES",
    "sg:address":"Avda Peris Y Valero, 186",
    "sg:city":"Valencia",
    "sg:classifiers":[
        {
            "category":"Casinos & Gambling",
            "type":"Entertainment"
        }
    ],
    "sg:phone":"+34 963 74 05 23",
    "sg:postcode":"46006",
    "sg:province":"Valencia",
    "sg:tags":[
        "locale",
        "de",
        "juego"
    ],
    "wof:name":"Juegos Kavi S. A.",
    "wof:placetype":"venue"
},
  "geometry": {"coordinates":[-0.3631660044,39.4620704651],"type":"Point"}
}