{
  "type": "Feature",
  "properties": {
    "iso:country":"ES",
    "sg:address":"Calle de Espronceda, 16",
    "sg:city":"Gijon",
    "sg:orig_category":"Equipo De Refrigeraci\u00d3n Industrial",
    "sg:phone":"+34 985 14 01 32",
    "sg:postcode":"33208",
    "sg:province":"Asturias",
    "wof:name":"Tamargo Rodriguez Dulce Irene",
    "wof:placetype":"venue"
},
  "geometry": {"coordinates":[-5.6677289009,43.5331306458],"type":"Point"}
}