{
  "type": "Feature",
  "properties": {
    "iso:country":"ES",
    "sg:address":"Cmno Huertas (de Las), S/n",
    "sg:city":"Casetas",
    "sg:orig_category":"Coches Y Camiones (caja De Cambios, Embrague Y Frenos)",
    "sg:phone":"+34 976 77 22 65",
    "sg:postcode":"50620",
    "sg:province":"Zaragoza",
    "wof:name":"Wabco Espa\u00d1a S.l.",
    "wof:placetype":"venue"
},
  "geometry": {"coordinates":[-1.0245081186,41.7198562622],"type":"Point"}
}