{
  "type": "Feature",
  "properties": {
    "addr:full":"Carrer de Estanc, 3 Palma Islas Baleares 07012",
    "addr:housenumber":"3",
    "addr:postcode":"07012",
    "addr:street":"Carrer De Estanc",
    "iso:country":"ES",
    "sg:address":"Carrer de Estanc, 3",
    "sg:city":"Palma",
    "sg:orig_category":"Inmobiliaria (agencias)",
    "sg:phone":"+34 971 72 30 41",
    "sg:postcode":"07012",
    "sg:province":"Islas Baleares",
    "sg:website":"www.morcasinternacional.com",
    "wof:name":"Inmocast S.l.",
    "wof:placetype":"venue"
},
  "geometry": {"coordinates":[2.6461479664,39.5695037842],"type":"Point"}
}