{
  "type": "Feature",
  "properties": {
    "iso:country":"ES",
    "sg:address":"Avda Ferrocarril, S/n",
    "sg:city":"Los Ramos",
    "sg:orig_category":"Arboricultura Y Producci\u00d3n De Frutas",
    "sg:phone":"+34 968 87 43 71",
    "sg:postcode":"30589",
    "sg:province":"Murcia",
    "wof:name":"Tana S.a.",
    "wof:placetype":"venue"
},
  "geometry": {"coordinates":[-1.028234005,37.9974632263],"type":"Point"}
}