{
  "type": "Feature",
  "properties": {
    "addr:full":"Calle de Gomez Acebo, 90 Villanueva Gallego Zaragoza 50830",
    "addr:housenumber":"90",
    "addr:postcode":"50830",
    "addr:street":"Calle De Gomez Acebo",
    "iso:country":"ES",
    "sg:address":"Calle de Gomez Acebo, 90",
    "sg:city":"Villanueva Gallego",
    "sg:orig_category":"Bancos",
    "sg:phone":"+34 976 45 10 50",
    "sg:postcode":"50830",
    "sg:province":"Zaragoza",
    "sg:website":"www.bancozaragozano.es",
    "wof:name":"Barclays Bank S.a.e.",
    "wof:placetype":"venue"
},
  "geometry": {"coordinates":[-0.8222020268,41.7705192566],"type":"Point"}
}