{
  "type": "Feature",
  "properties": {
    "addr:full":"Carrer de Antoni Gaudi, 57 S. Boi Llobregat Barcelona 08830",
    "addr:housenumber":"57",
    "addr:postcode":"08830",
    "addr:street":"Carrer De Antoni Gaudi",
    "iso:country":"ES",
    "sg:address":"Carrer de Antoni Gaudi, 57",
    "sg:city":"S. Boi Llobregat",
    "sg:orig_category":"Papel Pintado (al Por Menor)",
    "sg:phone":"+34 936 54 31 09",
    "sg:postcode":"08830",
    "sg:province":"Barcelona",
    "sg:website":"www.grupolober.com",
    "wof:name":"Ferrer Martin Antonio",
    "wof:placetype":"venue"
},
  "geometry": {"coordinates":[2.0302948952,41.3486061096],"type":"Point"}
}