{
  "type": "Feature",
  "properties": {
    "addr:full":"Ctr De La Solana, S/n Membrilla Ciudad Real 13230",
    "addr:housenumber":"s",
    "addr:postcode":"13230",
    "addr:street":"Solana;/ N",
    "iso:country":"ES",
    "sg:address":"Ctr De La Solana, S/n",
    "sg:city":"Membrilla",
    "sg:orig_category":"Molduras, Junquillos, Listones Y Molduras Perforadas",
    "sg:phone":"+34 926 63 74 09",
    "sg:postcode":"13230",
    "sg:province":"Ciudad Real",
    "wof:name":"Arroyo Cano Joaquina",
    "wof:placetype":"venue"
},
  "geometry": {"coordinates":[-3.3187470436,38.9197921753],"type":"Point"}
}