{
  "type": "Feature",
  "properties": {
    "iso:country":"ES",
    "sg:address":"Calle de Frigiliana, 41",
    "sg:city":"Malaga",
    "sg:orig_category":"Laboratorios Y Trabajos De Fotograf\u00cda, V\u00cddeo Y Cine",
    "sg:phone":"+34 952 33 62 93",
    "sg:postcode":"29003",
    "sg:province":"M\u00e1laga",
    "wof:name":"Avila Sanchez Constantino",
    "wof:placetype":"venue"
},
  "geometry": {"coordinates":[-4.443251133,36.695602417],"type":"Point"}
}