{
  "type": "Feature",
  "properties": {
    "iso:country":"ES",
    "sg:address":"Calle de General Garcia Escamez, 42",
    "sg:city":"Arrecife",
    "sg:orig_category":"Trabajos De Topograf\u00cda",
    "sg:phone":"+34 928 80 70 26",
    "sg:postcode":"35500",
    "sg:province":"Las Palmas",
    "wof:name":"Trancho Lemes Hildebrando",
    "wof:placetype":"venue"
},
  "geometry": {"coordinates":[-13.5539131165,28.9634208679],"type":"Point"}
}