{
  "type": "Feature",
  "properties": {
    "iso:country":"ES",
    "sg:address":"Irun Kalea, 4",
    "sg:city":"Hondarribia",
    "sg:orig_category":"Tiendas De Grano, Frutas Y Legumbres Secas (al Por Menor)",
    "sg:phone":"+34 943 11 19 22",
    "sg:postcode":"20280",
    "sg:province":"Guip\u00f9zcoa",
    "wof:name":"Olatz Arregui Garmendia (na-ya)",
    "wof:placetype":"venue"
},
  "geometry": {"coordinates":[-1.7969449759,43.3698730469],"type":"Point"}
}