{
  "type": "Feature",
  "properties": {
    "addr:full":"Regumiel, 9 Duruelo Sierra Soria 42158",
    "addr:housenumber":"9",
    "addr:postcode":"42158",
    "addr:street":"Regumiel",
    "iso:country":"ES",
    "sg:address":"Regumiel, 9",
    "sg:city":"Duruelo Sierra",
    "sg:orig_category":"Empresas De Carpinter\u00cda De Madera",
    "sg:phone":"+34 975 37 12 92",
    "sg:postcode":"42158",
    "sg:province":"Soria",
    "wof:name":"Vicente Abad Carlos",
    "wof:placetype":"venue"
},
  "geometry": {"coordinates":[-2.9291338921,41.9528656006],"type":"Point"}
}