{
  "type": "Feature",
  "properties": {
    "addr:full":"Avda Candina, 18 Santander Cantabria 39011",
    "addr:housenumber":"18",
    "addr:postcode":"39011",
    "addr:street":"Avda Candina",
    "iso:country":"ES",
    "sg:address":"Avda Candina, 18",
    "sg:city":"Santander",
    "sg:orig_category":"Centros Empresariales",
    "sg:phone":"+34 942 32 42 95",
    "sg:postcode":"39011",
    "sg:province":"Cantabria",
    "sg:website":"www.aecar.es",
    "wof:name":"Cuerno Estebanez Miguel Angel",
    "wof:placetype":"venue"
},
  "geometry": {"coordinates":[-3.8307189941,43.4524917603],"type":"Point"}
}