{
  "type": "Feature",
  "properties": {
    "iso:country":"ES",
    "sg:address":"Calle de Crevillente, 3",
    "sg:city":"Valencia",
    "sg:orig_category":"Servidores Y Editores De Bases De Datos",
    "sg:phone":"+34 963 26 96 10",
    "sg:postcode":"46022",
    "sg:province":"Valencia",
    "wof:name":"Host Studio S.l.",
    "wof:placetype":"venue"
},
  "geometry": {"coordinates":[-0.3402073979,39.468296051],"type":"Point"}
}