{
  "type": "Feature",
  "properties": {
    "addr:full":"Carrer de Enric Delaris, 24 Manlleu Barcelona 08560",
    "addr:housenumber":"24",
    "addr:postcode":"08560",
    "addr:street":"Carrer De Enric Delaris",
    "iso:country":"ES",
    "sg:address":"Carrer de Enric Delaris, 24",
    "sg:city":"Manlleu",
    "sg:orig_category":"Organismos Y Centros De Vacaciones Y Esparcimiento Para Ni\u00d1os Y Adolescentes",
    "sg:phone":"+34 938 51 07 04",
    "sg:postcode":"08560",
    "sg:province":"Barcelona",
    "sg:website":"www.al-lot.net",
    "wof:name":"Allot Educacio I Lleure S.l.",
    "wof:placetype":"venue"
},
  "geometry": {"coordinates":[2.2830617428,41.9998016357],"type":"Point"}
}