{
  "type": "Feature",
  "properties": {
    "iso:country":"ES",
    "sg:address":"Rua Republica Argentina, 22",
    "sg:city":"Vigo",
    "sg:orig_category":"Arquitectos",
    "sg:phone":"+34 986 22 66 52",
    "sg:postcode":"36201",
    "sg:province":"Pontevedra",
    "wof:name":"Viso Senra Marta",
    "wof:placetype":"venue"
},
  "geometry": {"coordinates":[-8.7188243866,42.2360038757],"type":"Point"}
}