{
  "type": "Feature",
  "properties": {
    "addr:full":"Av Republica Argentina, 179 Barcelona Barcelona 08023",
    "addr:housenumber":"179",
    "addr:postcode":"08023",
    "addr:street":"Av Republica Argentina",
    "iso:country":"ES",
    "sg:address":"Av Republica Argentina, 179",
    "sg:city":"Barcelona",
    "sg:orig_category":"Supermercados Y Hipermercados",
    "sg:phone":"+34 932 11 38 16",
    "sg:postcode":"08023",
    "sg:province":"Barcelona",
    "wof:name":"Jespac S. A.",
    "wof:placetype":"venue"
},
  "geometry": {"coordinates":[2.1421658993,41.4114608765],"type":"Point"}
}