{
  "type": "Feature",
  "properties": {
    "addr:full":"Barrio Los Valles, 4 Ramales Victoria Cantabria 39800",
    "addr:housenumber":"4",
    "addr:postcode":"39800",
    "addr:street":"Barrio Los Valles",
    "iso:country":"ES",
    "sg:address":"Barrio Los Valles, 4",
    "sg:city":"Ramales Victoria",
    "sg:orig_category":"Centros De Coordinaci\u00d3n",
    "sg:phone":"+34 942 64 69 08",
    "sg:postcode":"39800",
    "sg:province":"Cantabria",
    "wof:name":"Pe\u00f1a Conde Jose Antonio",
    "wof:placetype":"venue"
},
  "geometry": {"coordinates":[-3.442991972,43.2613754272],"type":"Point"}
}