{
  "type": "Feature",
  "properties": {
    "iso:country":"ES",
    "sg:address":"Calle de Batan De San Sebastian, 1",
    "sg:city":"Palencia",
    "sg:orig_category":"Ingenier\u00cda, Centros De Estudios (diversos)",
    "sg:phone":"+34 979 71 15 63",
    "sg:postcode":"34002",
    "sg:province":"Palencia",
    "wof:name":"Barcenilla Roman Lucio",
    "wof:placetype":"venue"
},
  "geometry": {"coordinates":[-4.5303487778,42.0038261414],"type":"Point"}
}