{
  "type": "Feature",
  "properties": {
    "iso:country":"ES",
    "sg:address":"Calle de Joaquin Blume, 28",
    "sg:city":"San Vicente Del Raspeig-sant Vicent Del Raspeig",
    "sg:orig_category":"Ferreter\u00cda (diversos)",
    "sg:phone":"+34 965 67 60 99",
    "sg:postcode":"03690",
    "sg:province":"Alicante",
    "wof:name":"Estructuras Y Forjados Delta S.l.",
    "wof:placetype":"venue"
},
  "geometry": {"coordinates":[-0.523014009,38.4012832642],"type":"Point"}
}