{
  "type": "Feature",
  "properties": {
    "addr:full":"Luga Horno (el), 33 Horno Las Palmas 35140",
    "addr:postcode":"35140",
    "iso:country":"ES",
    "sg:address":"Luga Horno (el), 33",
    "sg:city":"Horno",
    "sg:orig_category":"Alquiler De Gr\u00daas",
    "sg:phone":"+34 928 15 90 08",
    "sg:postcode":"35140",
    "sg:province":"Las Palmas",
    "wof:name":"Quintana Correa Dionisio",
    "wof:placetype":"venue"
},
  "geometry": {"coordinates":[-15.7237386703,27.8846378326],"type":"Point"}
}