{
  "type": "Feature",
  "properties": {
    "addr:full":"Calle de Marino Sirera, 12 Valencia Valencia 46011",
    "addr:housenumber":"12",
    "addr:postcode":"46011",
    "addr:street":"Calle De Marino Sirera",
    "iso:country":"ES",
    "sg:address":"Calle de Marino Sirera, 12",
    "sg:city":"Valencia",
    "sg:orig_category":"Cajas De Ahorro",
    "sg:phone":"+34 963 71 33 52",
    "sg:postcode":"46011",
    "sg:province":"Valencia",
    "sg:website":"www.bancaja.es",
    "wof:name":"Caja De Ahorros De Valencia Castellon Y Alicante",
    "wof:placetype":"venue"
},
  "geometry": {"coordinates":[-0.3325020075,39.4681968689],"type":"Point"}
}