{
  "type": "Feature",
  "properties": {
    "addr:full":"Ptda Madrigal, S/n Virgen De Gracia Castell\u00f3n 12540",
    "addr:housenumber":"s / n",
    "addr:postcode":"12540",
    "addr:street":"Ptda Madrigal;Castello\u0301N",
    "iso:country":"ES",
    "sg:address":"Ptda Madrigal, S/n",
    "sg:city":"Virgen De Gracia",
    "sg:orig_category":"Delegados, Agentes De Tr\u00c1nsito, Auxiliares De Transporte Internacional",
    "sg:phone":"+34 964 52 70 98",
    "sg:postcode":"12540",
    "sg:province":"Castell\u00f3n",
    "wof:name":"Francisco Pitarch S.l.",
    "wof:placetype":"venue"
},
  "geometry": {"coordinates":[-0.0952939987,39.9453048706],"type":"Point"}
}