{
  "type": "Feature",
  "properties": {
    "addr:full":"Calle de San Fructuoso, 24 Alcala Henares Madrid 28802",
    "addr:housenumber":"24",
    "addr:postcode":"28802",
    "addr:street":"Calle De San Fructuoso",
    "iso:country":"ES",
    "sg:address":"Calle de San Fructuoso, 24",
    "sg:city":"Alcala Henares",
    "sg:orig_category":"Relojer\u00cda (al Por Menor, Reparaci\u00d3n)",
    "sg:phone":"+34 918 82 45 92",
    "sg:postcode":"28802",
    "sg:province":"Madrid",
    "wof:name":"Luis Alvarez Cirilo",
    "wof:placetype":"venue"
},
  "geometry": {"coordinates":[-3.3765215874,40.4761657715],"type":"Point"}
}