{
  "type": "Feature",
  "properties": {
    "iso:country":"ES",
    "sg:address":"Calle de Echevarrieta Cosme, 11",
    "sg:city":"Bilbao",
    "sg:orig_category":"Cristaler\u00cda Art\u00cdstica, Vidrio Soplado (fabricaci\u00d3n, Al Por Mayor)",
    "sg:phone":"+34 944 23 08 19",
    "sg:postcode":"48009",
    "sg:province":"Vizcaya",
    "wof:name":"Fernando Ca\u00f1ada Vicinay",
    "wof:placetype":"venue"
},
  "geometry": {"coordinates":[-2.9316101074,43.2660484314],"type":"Point"}
}