{
  "type": "Feature",
  "properties": {
    "addr:full":"Calle de Caldereria Vieja, 22 Granada Granada 18010",
    "addr:housenumber":"22",
    "addr:postcode":"18010",
    "addr:street":"Calle De Caldereria Vieja",
    "iso:country":"ES",
    "sg:address":"Calle de Caldereria Vieja, 22",
    "sg:city":"Granada",
    "sg:orig_category":"Artesan\u00cda",
    "sg:phone":"+34 958 21 01 79",
    "sg:postcode":"18010",
    "sg:province":"Granada",
    "wof:name":"Loh  Omar",
    "wof:placetype":"venue"
},
  "geometry": {"coordinates":[-3.5966050625,37.1778182983],"type":"Point"}
}