{
  "type": "Feature",
  "properties": {
    "addr:full":"Avda Carmen (del), 33 Estepona M\u00e1laga 29680",
    "addr:housenumber":"33",
    "addr:postcode":"29680",
    "addr:street":"Avda Carmen Del",
    "iso:country":"ES",
    "sg:address":"Avda Carmen (del), 33",
    "sg:city":"Estepona",
    "sg:orig_category":"Deportes N\u00c1uticos, Acu\u00c1ticos Y Subacu\u00c1ticos: Art\u00cdculos Y Equipo (al Por Menor)",
    "sg:phone":"+34 952 79 59 13",
    "sg:postcode":"29680",
    "sg:province":"M\u00e1laga",
    "wof:name":"Yacht Help Group Mallorca S.l.",
    "wof:placetype":"venue"
},
  "geometry": {"coordinates":[-5.1452560425,36.4256248474],"type":"Point"}
}