{
  "type": "Feature",
  "properties": {
    "addr:full":"Av Diagonal, 586 Barcelona Barcelona 08021",
    "addr:housenumber":"586",
    "addr:postcode":"08021",
    "addr:street":"Av Diagonal",
    "iso:country":"ES",
    "sg:address":"Av Diagonal, 586",
    "sg:city":"Barcelona",
    "sg:orig_category":"Abogados",
    "sg:phone":"+34 932 00 97 07",
    "sg:postcode":"08021",
    "sg:province":"Barcelona",
    "wof:name":"Norwood Pe\u00f1a Esteban",
    "wof:placetype":"venue"
},
  "geometry": {"coordinates":[2.1469609737,41.3936882019],"type":"Point"}
}