{
  "type": "Feature",
  "properties": {
    "addr:full":"Parque Comercial Del Gorbeia, 1 Etxabarri Ibi\u00f1a \u00c1lava 01140",
    "addr:housenumber":"1",
    "addr:postcode":"01140",
    "addr:street":"Gorbeia;A\u0301Lava",
    "iso:country":"ES",
    "sg:address":"Parque Comercial Del Gorbeia, 1",
    "sg:city":"Etxabarri Ibi\u00f1a",
    "sg:orig_category":"Agencias De Viajes",
    "sg:phone":"+34 945 46 09 05",
    "sg:postcode":"01140",
    "sg:province":"\u00c1lava",
    "sg:website":"www.barceloviajes.com",
    "wof:name":"Viajes Barcelo S.l.",
    "wof:placetype":"venue"
},
  "geometry": {"coordinates":[-2.7102301121,42.917640686],"type":"Point"}
}