{
  "type": "Feature",
  "properties": {
    "addr:full":"Avgd Castello, 26 Villafranca Cid Castell\u00f3n 12150",
    "addr:housenumber":"26",
    "addr:postcode":"12150",
    "addr:street":"Castello",
    "iso:country":"ES",
    "sg:address":"Avgd Castello, 26",
    "sg:city":"Villafranca Cid",
    "sg:orig_category":"Supermercados Y Hipermercados",
    "sg:phone":"+34 964 44 08 18",
    "sg:postcode":"12150",
    "sg:province":"Castell\u00f3n",
    "wof:name":"Prats Garcia Ana Maria",
    "wof:placetype":"venue"
},
  "geometry": {"coordinates":[-0.2569360137,40.4276580811],"type":"Point"}
}