{
  "type": "Feature",
  "properties": {
    "addr:full":"Carrer de Can Ribera, 3 Palma Islas Baleares 07012",
    "addr:housenumber":"3",
    "addr:postcode":"07012",
    "addr:street":"Carrer De Can Ribera",
    "iso:country":"ES",
    "sg:address":"Carrer de Can Ribera, 3",
    "sg:city":"Palma",
    "sg:orig_category":"Arquitectos",
    "sg:phone":"+34 971 72 82 89",
    "sg:postcode":"07012",
    "sg:province":"Islas Baleares",
    "wof:name":"Matas Moya Guillermo Francisco",
    "wof:placetype":"venue"
},
  "geometry": {"coordinates":[2.645154953,39.5712738037],"type":"Point"}
}