{
  "type": "Feature",
  "properties": {
    "iso:country":"ES",
    "sg:address":"Calle de Huerta, 30",
    "sg:city":"Villanueva Campo",
    "sg:orig_category":"Electricidad: Instaladores",
    "sg:phone":"+34 980 66 60 76",
    "sg:postcode":"49100",
    "sg:province":"Zamora",
    "wof:name":"Fontanillas Torio Andres",
    "wof:placetype":"venue"
},
  "geometry": {"coordinates":[-5.4058232307,41.9830627441],"type":"Point"}
}