{
  "type": "Feature",
  "properties": {
    "iso:country":"ES",
    "sg:address":"Calle de Colon, 37",
    "sg:city":"Castellon",
    "sg:orig_category":"Farmacias",
    "sg:phone":"+34 964 22 40 64",
    "sg:postcode":"12001",
    "sg:province":"Castell\u00f3n",
    "wof:name":"Calderon Gomez Jesus",
    "wof:placetype":"venue"
},
  "geometry": {"coordinates":[-0.03816,39.9865379333],"type":"Point"}
}