{
  "type": "Feature",
  "properties": {
    "iso:country":"ES",
    "sg:address":"Calle de Mayor, 24",
    "sg:city":"Albacete",
    "sg:orig_category":"Ropa Para Se\u00d1oras (al Por Menor)",
    "sg:phone":"+34 967 52 05 18",
    "sg:postcode":"02002",
    "sg:province":"Albacete",
    "sg:website":"www.zara.com",
    "wof:name":"Zara Espa\u00f1a S.a.",
    "wof:placetype":"venue"
},
  "geometry": {"coordinates":[-2.0265111923,38.8528175354],"type":"Point"}
}