{
  "type": "Feature",
  "properties": {
    "addr:full":"Calle de Angel Barja, S/n Ponferrada Le\u00f3n 24400",
    "addr:housenumber":"s / n",
    "addr:postcode":"24400",
    "addr:street":"Calle De Angel Barja",
    "iso:country":"ES",
    "sg:address":"Calle de Angel Barja, S/n",
    "sg:city":"Ponferrada",
    "sg:orig_category":"Ense\u00d1anza: Peluquer\u00cda Est\u00c9tica",
    "sg:phone":"+34 987 41 75 75",
    "sg:postcode":"24400",
    "sg:province":"Le\u00f3n",
    "wof:name":"Escuela Tita Y Fely S.l.",
    "wof:placetype":"venue"
},
  "geometry": {"coordinates":[-6.5975894928,42.5494041443],"type":"Point"}
}