{
  "type": "Feature",
  "properties": {
    "addr:full":"Calle de Capitan Oroquieta, 2 Zaragoza Zaragoza 50007",
    "addr:housenumber":"2",
    "addr:postcode":"50007",
    "addr:street":"Calle De Capitan Oroquieta",
    "iso:country":"ES",
    "sg:address":"Calle de Capitan Oroquieta, 2",
    "sg:city":"Zaragoza",
    "sg:orig_category":"Panader\u00cdas, Panader\u00cdas",
    "sg:phone":"+34 976 37 59 01",
    "sg:postcode":"50007",
    "sg:province":"Zaragoza",
    "wof:name":"Escuin Carceller Isabel",
    "wof:placetype":"venue"
},
  "geometry": {"coordinates":[-0.8789502978,41.6328239441],"type":"Point"}
}