{
  "type": "Feature",
  "properties": {
    "addr:full":"Calle de Gran Via, 70 Salamanca Salamanca 37001",
    "addr:housenumber":"70",
    "addr:postcode":"37001",
    "addr:street":"Calle De Gran Via",
    "iso:country":"ES",
    "sg:address":"Calle de Gran Via, 70",
    "sg:city":"Salamanca",
    "sg:orig_category":"Informaci\u00d3n Financiera Y Comercial",
    "sg:phone":"+34 923 21 21 35",
    "sg:postcode":"37001",
    "sg:province":"Salamanca",
    "wof:name":"Gonzalez-orus Marcos Martin Jose",
    "wof:placetype":"venue"
},
  "geometry": {"coordinates":[-5.6623430252,40.9624786377],"type":"Point"}
}