{
  "type": "Feature",
  "properties": {
    "addr:full":"Pase Rosales, 7 Molina Segura Murcia 30500",
    "addr:housenumber":"7",
    "addr:postcode":"30500",
    "addr:street":"Rosales",
    "iso:country":"ES",
    "sg:address":"Pase Rosales, 7",
    "sg:city":"Molina Segura",
    "sg:orig_category":"Bancos",
    "sg:phone":"+34 968 61 37 84",
    "sg:postcode":"30500",
    "sg:province":"Murcia",
    "wof:name":"Banco Bilbao Vizcaya Argentaria S.a.",
    "wof:placetype":"venue"
},
  "geometry": {"coordinates":[-1.2119740248,38.0535736084],"type":"Point"}
}