{
  "type": "Feature",
  "properties": {
    "addr:full":"Carr Caritat, S/n Sant Lloren\u00c7 Des Cardassar Islas Baleares 07530",
    "addr:housenumber":"s / n",
    "addr:postcode":"07530",
    "addr:street":"Carr Caritat",
    "iso:country":"ES",
    "sg:address":"Carr Caritat, S/n",
    "sg:city":"Sant Lloren\u00c7 Des Cardassar",
    "sg:orig_category":"Guarder\u00cdas",
    "sg:phone":"+34 971 83 84 16",
    "sg:postcode":"07530",
    "sg:province":"Islas Baleares",
    "wof:name":"Ajuntament De Sant Llorenc Des Cardassar",
    "wof:placetype":"venue"
},
  "geometry": {"coordinates":[3.2852125168,39.6089248657],"type":"Point"}
}