{
  "type": "Feature",
  "properties": {
    "iso:country":"ES",
    "sg:address":"Calle de Pilarica, 65",
    "sg:city":"Madrid",
    "sg:orig_category":"Comercio De Piezas De Recambio Y De Accesorios De Veh\u00cdculos, Veh\u00cdculos Industriales",
    "sg:phone":"+34 915 00 35 98",
    "sg:postcode":"28026",
    "sg:province":"Madrid",
    "wof:name":"Pamauto S.a",
    "wof:placetype":"venue"
},
  "geometry": {"coordinates":[-3.7028129101,40.3840179443],"type":"Point"}
}