{
  "type": "Feature",
  "properties": {
    "addr:full":"Avda Europa, 1 Yebenes Toledo 45470",
    "addr:housenumber":"1",
    "addr:postcode":"45470",
    "addr:street":"Avda Europa",
    "iso:country":"ES",
    "sg:address":"Avda Europa, 1",
    "sg:city":"Yebenes",
    "sg:orig_category":"Asociaciones Y Clubs Deportivos",
    "sg:phone":"+34 925 34 81 57",
    "sg:postcode":"45470",
    "sg:province":"Toledo",
    "wof:name":"Club Deportivo Elemental Los Yebenes",
    "wof:placetype":"venue"
},
  "geometry": {"coordinates":[-3.8659288883,39.5764808655],"type":"Point"}
}