{
  "type": "Feature",
  "properties": {
    "iso:country":"ES",
    "sg:address":"Calle de Cadiz, 23",
    "sg:city":"Valencia",
    "sg:orig_category":"Art\u00cdculos De Regalo (al Por Menor)",
    "sg:phone":"+34 963 41 23 51",
    "sg:postcode":"46006",
    "sg:province":"Valencia",
    "wof:name":"Morell Carpi Vicente",
    "wof:placetype":"venue"
},
  "geometry": {"coordinates":[-0.3744382858,39.4630317688],"type":"Point"}
}