{
  "type": "Feature",
  "properties": {
    "iso:country":"ES",
    "sg:address":"Calle de Intxausti, 11",
    "sg:city":"Bermeo",
    "sg:orig_category":"Peluqueros: De Se\u00d1oras",
    "sg:phone":"+34 946 88 50 99",
    "sg:postcode":"48370",
    "sg:province":"Vizcaya",
    "wof:name":"Fradua Gaubeka Mari Feli",
    "wof:placetype":"venue"
},
  "geometry": {"coordinates":[-2.7242600918,43.4204788208],"type":"Point"}
}