{
  "type": "Feature",
  "properties": {
    "addr:full":"Avda Jose Antonio, 14 Lalin Pontevedra 36500",
    "addr:housenumber":"14",
    "addr:postcode":"36500",
    "addr:street":"Avda Jose Antonio",
    "iso:country":"ES",
    "sg:address":"Avda Jose Antonio, 14",
    "sg:city":"Lalin",
    "sg:orig_category":"Muebles, Minoristas",
    "sg:phone":"+34 986 78 01 23",
    "sg:postcode":"36500",
    "sg:province":"Pontevedra",
    "wof:name":"Taboada Arean Ramon",
    "wof:placetype":"venue"
},
  "geometry": {"coordinates":[-8.1081991196,42.6615600586],"type":"Point"}
}