{
  "type": "Feature",
  "properties": {
    "iso:country":"ES",
    "sg:address":"Av Paral.lel, 52",
    "sg:city":"Barcelona",
    "sg:orig_category":"Sexshops",
    "sg:phone":"+34 934 43 24 60",
    "sg:postcode":"08001",
    "sg:province":"Barcelona",
    "wof:name":"Bracol S.l.",
    "wof:placetype":"venue"
},
  "geometry": {"coordinates":[2.1711308956,41.3749885559],"type":"Point"}
}