{
  "type": "Feature",
  "properties": {
    "addr:full":"Calle de Francisco Javier De Landaburu, 78 Vitoria-gasteiz \u00c1lava 01011",
    "addr:housenumber":"78",
    "addr:postcode":"01011",
    "addr:street":"Calle De Francisco Javier De Landaburu",
    "iso:country":"ES",
    "sg:address":"Calle de Francisco Javier De Landaburu, 78",
    "sg:city":"Vitoria-gasteiz",
    "sg:orig_category":"M\u00c9dicos: Estomatolog\u00cda",
    "sg:phone":"+34 945 17 13 85",
    "sg:postcode":"01011",
    "sg:province":"\u00c1lava",
    "wof:name":"Hurtado Tejada Maria Victoria",
    "wof:placetype":"venue"
},
  "geometry": {"coordinates":[-2.6797299385,42.8475112915],"type":"Point"}
}