{
  "type": "Feature",
  "properties": {
    "addr:full":"Bda. Nieva, S/n Santa Maria Nieva Almer\u00eda 04693",
    "addr:housenumber":"s / n",
    "addr:postcode":"04693",
    "iso:country":"ES",
    "sg:address":"Bda. Nieva, S/n",
    "sg:city":"Santa Maria Nieva",
    "sg:orig_category":"Farmacias",
    "sg:phone":"+34 950 13 71 91",
    "sg:postcode":"04693",
    "sg:province":"Almer\u00eda",
    "wof:name":"Martinez Bravo Florentina",
    "wof:placetype":"venue"
},
  "geometry": {"coordinates":[-2.0006389618,37.471321106],"type":"Point"}
}