{
  "type": "Feature",
  "properties": {
    "addr:full":"Avgd De Daniel Gil, 20 Ontinyent Valencia 46870",
    "addr:housenumber":"20",
    "addr:postcode":"46870",
    "addr:street":"Gil",
    "iso:country":"ES",
    "sg:address":"Avgd De Daniel Gil, 20",
    "sg:city":"Ontinyent",
    "sg:orig_category":"Agencias Y Agentes Comerciales, Representantes",
    "sg:phone":"+34 962 91 33 73",
    "sg:postcode":"46870",
    "sg:province":"Valencia",
    "wof:name":"Frances Mora Jose Rafael",
    "wof:placetype":"venue"
},
  "geometry": {"coordinates":[-0.6022139788,38.8248023987],"type":"Point"}
}