{
  "type": "Feature",
  "properties": {
    "iso:country":"ES",
    "sg:address":"San Cristobal (p I Antequera), 12",
    "sg:city":"Antequera",
    "sg:orig_category":"Fabricaci\u00d3n De Su\u00c9ters Y Chalecos De Punto",
    "sg:phone":"+34 952 70 41 27",
    "sg:postcode":"29200",
    "sg:province":"M\u00e1laga",
    "wof:name":"Almacenes Al Andalus S.l.",
    "wof:placetype":"venue"
},
  "geometry": {"coordinates":[-4.5211935043,36.9971008301],"type":"Point"}
}