{
  "type": "Feature",
  "properties": {
    "addr:full":"Manolete Cordoba C\u00f3rdoba 14005",
    "addr:postcode":"14005",
    "addr:street":"Co\u0301Rdoba",
    "iso:country":"ES",
    "sg:address":"Manolete",
    "sg:city":"Cordoba",
    "sg:orig_category":"Panader\u00cdas, Panader\u00cdas",
    "sg:phone":"+34 957 23 84 75",
    "sg:postcode":"14005",
    "sg:province":"C\u00f3rdoba",
    "wof:name":"Panaderias Reunidas Cordobesas S.a.",
    "wof:placetype":"venue"
},
  "geometry": {"coordinates":[-4.7947092056,37.8804168701],"type":"Point"}
}