{
  "type": "Feature",
  "properties": {
    "addr:full":"Calle de Antonio Concha, 51 Navalmoral Mata C\u00e1ceres 10300",
    "addr:housenumber":"51",
    "addr:postcode":"10300",
    "addr:street":"Calle De Antonio Concha;Ca\u0301Ceres",
    "iso:country":"ES",
    "sg:address":"Calle de Antonio Concha, 51",
    "sg:city":"Navalmoral Mata",
    "sg:orig_category":"Controles De Edificaci\u00d3n (construcci\u00d3n, Seguridad)",
    "sg:phone":"+34 927 53 45 01",
    "sg:postcode":"10300",
    "sg:province":"C\u00e1ceres",
    "wof:name":"Construcciones Miguel Angel Macias S.l.",
    "wof:placetype":"venue"
},
  "geometry": {"coordinates":[-5.538128376,39.8905525208],"type":"Point"}
}