{
  "type": "Feature",
  "properties": {
    "addr:full":"Calle de San Francisco De Asis, S/n Ronda M\u00e1laga 29400",
    "addr:housenumber":"s",
    "addr:postcode":"29400",
    "addr:street":"Calle De San Francisco De Asis;/ N Ronda Ma\u0301Laga",
    "iso:country":"ES",
    "sg:address":"Calle de San Francisco De Asis, S/n",
    "sg:city":"Ronda",
    "sg:orig_category":"Internados & Ense\u00d1anza Privada",
    "sg:phone":"+34 952 87 15 95",
    "sg:postcode":"29400",
    "sg:province":"M\u00e1laga",
    "sg:website":"www.colegiofernandezlosrios.com",
    "wof:name":"Unicaja",
    "wof:placetype":"venue"
},
  "geometry": {"coordinates":[-5.16482687,36.728061676],"type":"Point"}
}