{
  "type": "Feature",
  "properties": {
    "iso:country":"ES",
    "sg:address":"Pase Habana, 22",
    "sg:city":"Madrid",
    "sg:orig_category":"Empresarios Y Productoras De Espect\u00c1culos",
    "sg:phone":"+34 915 61 73 34",
    "sg:postcode":"28036",
    "sg:province":"Madrid",
    "wof:name":"Tauro Carpeto S.l.",
    "wof:placetype":"venue"
},
  "geometry": {"coordinates":[-3.6893889904,40.4484176636],"type":"Point"}
}