{
  "type": "Feature",
  "properties": {
    "addr:full":"Carrer de Terrassa, 15 Reus Tarragona 43206",
    "addr:housenumber":"15",
    "addr:postcode":"43206",
    "addr:street":"Carrer De Terrassa",
    "iso:country":"ES",
    "sg:address":"Carrer de Terrassa, 15",
    "sg:city":"Reus",
    "sg:orig_category":"Automatizaci\u00d3n De Procesos Industriales Y De Edificaci\u00d3n (estudios, Instalaci\u00d3n)",
    "sg:phone":"+34 977 33 06 76",
    "sg:postcode":"43206",
    "sg:province":"Tarragona",
    "wof:name":"Mecamat Automatismes S.l.",
    "wof:placetype":"venue"
},
  "geometry": {"coordinates":[1.1216189861,41.1589851379],"type":"Point"}
}