{
  "type": "Feature",
  "properties": {
    "iso:country":"ES",
    "sg:address":"Calle de Martin Belda, 26",
    "sg:city":"Cabra",
    "sg:orig_category":"Agencias De Viajes",
    "sg:phone":"+34 957 52 96 23",
    "sg:postcode":"14940",
    "sg:province":"C\u00f3rdoba",
    "wof:name":"Viajes Simblia S.l",
    "wof:placetype":"venue"
},
  "geometry": {"coordinates":[-4.4424152374,37.4718894958],"type":"Point"}
}