{
  "type": "Feature",
  "properties": {
    "iso:country":"ES",
    "sg:address":"Calle de Volcan Elena, 26",
    "sg:city":"Chumberas",
    "sg:orig_category":"Inmobiliaria (agencias)",
    "sg:phone":"+34 922 24 37 12",
    "sg:postcode":"38108",
    "sg:province":"Santa Cruz De Tenerife",
    "wof:name":"Construcciones Daltre S.l.",
    "wof:placetype":"venue"
},
  "geometry": {"coordinates":[-16.2957706451,28.4491081238],"type":"Point"}
}