{
  "type": "Feature",
  "properties": {
    "iso:country":"ES",
    "sg:address":"Carr Lluis Vives, De, 14",
    "sg:city":"Carcaixent",
    "sg:orig_category":"Pintura Y Barniz (al Por Menor)",
    "sg:phone":"+34 962 43 11 31",
    "sg:postcode":"46740",
    "sg:province":"Valencia",
    "wof:name":"Pinturas M.lopez Ortega S.l.",
    "wof:placetype":"venue"
},
  "geometry": {"coordinates":[-0.4498789907,39.1257591248],"type":"Point"}
}