{
  "type": "Feature",
  "properties": {
    "iso:country":"ES",
    "sg:address":"Avda Orbigo (el), 64",
    "sg:city":"Benavides De Orbigo",
    "sg:orig_category":"Electrodom\u00c9sticos (al Por Menor)",
    "sg:phone":"+34 987 37 01 24",
    "sg:postcode":"24280",
    "sg:province":"Le\u00f3n",
    "wof:name":"Matilla Vega Isidro",
    "wof:placetype":"venue"
},
  "geometry": {"coordinates":[-5.8955731392,42.5015945435],"type":"Point"}
}