{
  "type": "Feature",
  "properties": {
    "iso:country":"ES",
    "sg:address":"C/ Ciutadella De Menorca, 10",
    "sg:city":"Elche",
    "sg:orig_category":"Fabricaci\u00d3n De Tapices Y Moquetas Para Suelos Y Paredes",
    "sg:phone":"+34 966 66 12 77",
    "sg:postcode":"03205",
    "sg:province":"Alicante",
    "wof:name":"Isle\u00d1a De Revestimiento S.l.",
    "wof:placetype":"venue"
},
  "geometry": {"coordinates":[-0.7156950235,38.2851371765],"type":"Point"}
}