{
  "type": "Feature",
  "properties": {
    "addr:full":"Calle de Francisco Gomez, 4 San Vicente De Barakaldo Vizcaya 48902",
    "addr:housenumber":"4",
    "addr:postcode":"48902",
    "addr:street":"Calle De Francisco Gomez",
    "iso:country":"ES",
    "sg:address":"Calle de Francisco Gomez, 4",
    "sg:city":"San Vicente De Barakaldo",
    "sg:orig_category":"Abogados",
    "sg:phone":"+34 944 78 20 51",
    "sg:postcode":"48902",
    "sg:province":"Vizcaya",
    "wof:name":"Salgado Nu\u00f1ez Josu",
    "wof:placetype":"venue"
},
  "geometry": {"coordinates":[-2.9908339977,43.2964401245],"type":"Point"}
}