{
  "type": "Feature",
  "properties": {
    "iso:country":"ES",
    "sg:address":"Calle de Zamora, 8",
    "sg:city":"Cerecinos De Campos",
    "sg:orig_category":"Bebidas",
    "sg:phone":"+34 980 66 90 22",
    "sg:postcode":"49640",
    "sg:province":"Zamora",
    "wof:name":"Vega Llamas Abelina",
    "wof:placetype":"venue"
},
  "geometry": {"coordinates":[-5.4850277901,41.8988265991],"type":"Point"}
}