{
  "type": "Feature",
  "properties": {
    "iso:country":"ES",
    "sg:address":"Barcia, S/n",
    "sg:city":"Barcia",
    "sg:orig_category":"Empresarios",
    "sg:phone":"+34 985 64 12 47",
    "sg:postcode":"33787",
    "sg:province":"Asturias",
    "wof:name":"Castro Morera Agustin",
    "wof:placetype":"venue"
},
  "geometry": {"coordinates":[-6.4964737892,43.5437965393],"type":"Point"}
}