{
  "type": "Feature",
  "properties": {
    "iso:country":"ES",
    "sg:address":"Pg Fabra I Puig, 179",
    "sg:city":"Barcelona",
    "sg:orig_category":"Lencer\u00cda Femenina, Corseter\u00cda, Trajes De Ba\u00d1o (al Por Menor)",
    "sg:phone":"+34 933 52 69 06",
    "sg:postcode":"08016",
    "sg:province":"Barcelona",
    "wof:name":"Pallas Xifre Cristina",
    "wof:placetype":"venue"
},
  "geometry": {"coordinates":[2.1776819229,41.4301605225],"type":"Point"}
}