{
  "type": "Feature",
  "properties": {
    "iso:country":"ES",
    "sg:address":"Ptda Molinet, S/n",
    "sg:city":"Pedreguer",
    "sg:orig_category":"Mec\u00c1nico Del Autom\u00d3vil",
    "sg:phone":"+34 965 76 19 47",
    "sg:postcode":"03750",
    "sg:province":"Alicante",
    "wof:name":"Signes Costa Miguel",
    "wof:placetype":"venue"
},
  "geometry": {"coordinates":[0.0545369983,38.7801246643],"type":"Point"}
}