{
  "type": "Feature",
  "properties": {
    "addr:full":"Carr Gomez Ferrer, 32 Picassent Valencia 46220",
    "addr:housenumber":"32",
    "addr:postcode":"46220",
    "addr:street":"Carr Gomez Ferrer",
    "iso:country":"ES",
    "sg:address":"Carr Gomez Ferrer, 32",
    "sg:city":"Picassent",
    "sg:orig_category":"Poller\u00cda Y Caza (al Por Menor)",
    "sg:phone":"+34 961 23 48 78",
    "sg:postcode":"46220",
    "sg:province":"Valencia",
    "wof:name":"Tarazona Aguado Maria Isabel",
    "wof:placetype":"venue"
},
  "geometry": {"coordinates":[-0.4625369906,39.3613853455],"type":"Point"}
}