{
  "type": "Feature",
  "properties": {
    "addr:full":"Pase Espolon (el), 18 Soria Soria 42001",
    "addr:postcode":"42001",
    "iso:country":"ES",
    "sg:address":"Pase Espolon (el), 18",
    "sg:city":"Soria",
    "sg:orig_category":"Arquitectos",
    "sg:phone":"+34 975 22 22 07",
    "sg:postcode":"42001",
    "sg:province":"Soria",
    "wof:name":"Iglesia Domingo Fernando De La",
    "wof:placetype":"venue"
},
  "geometry": {"coordinates":[-2.4691669941,41.7646598816],"type":"Point"}
}