{
  "type": "Feature",
  "properties": {
    "addr:full":"Carr Santa Margarida, 12 Palafrugell Girona 17200",
    "addr:housenumber":"12",
    "addr:postcode":"17200",
    "addr:street":"Carr Santa Margarida",
    "iso:country":"ES",
    "sg:address":"Carr Santa Margarida, 12",
    "sg:city":"Palafrugell",
    "sg:orig_category":"Peluquer\u00cdas",
    "sg:phone":"+34 972 30 40 55",
    "sg:postcode":"17200",
    "sg:province":"Girona",
    "sg:website":"www.cebado.es",
    "wof:name":"Mercadal Pujiula Mireia",
    "wof:placetype":"venue"
},
  "geometry": {"coordinates":[3.1648910046,41.9158248901],"type":"Point"}
}