{
  "type": "Feature",
  "properties": {
    "addr:full":"Avda Alcora, 28 Onda Castell\u00f3n 12200",
    "addr:housenumber":"28",
    "addr:postcode":"12200",
    "addr:street":"Avda Alcora;Castello\u0301N",
    "iso:country":"ES",
    "sg:address":"Avda Alcora, 28",
    "sg:city":"Onda",
    "sg:orig_category":"Piedra, Vidrio, Cer\u00c1mica Y Porcelana",
    "sg:phone":"+34 964 60 52 81",
    "sg:postcode":"12200",
    "sg:province":"Castell\u00f3n",
    "wof:name":"Crm Rectificados S.l.",
    "wof:placetype":"venue"
},
  "geometry": {"coordinates":[-0.2522430122,39.9668998718],"type":"Point"}
}