{
  "type": "Feature",
  "properties": {
    "addr:full":"Cmno Sese\u00d1a Nuevo, S/n Sese\u00f1a Toledo 45223",
    "addr:housenumber":"s",
    "addr:postcode":"45223",
    "addr:street":"Cmno Sesen\u0303A Nuevo;/ N Sesen\u0303A",
    "iso:country":"ES",
    "sg:address":"Cmno Sese\u00d1a Nuevo, S/n",
    "sg:city":"Sese\u00f1a",
    "sg:orig_category":"Empresas De Hormig\u00d3n, Hormig\u00d3n Armado Y Pretensado",
    "sg:phone":"+34 918 95 78 58",
    "sg:postcode":"45223",
    "sg:province":"Toledo",
    "wof:name":"Prefabricados Uniblok S.a.",
    "wof:placetype":"venue"
},
  "geometry": {"coordinates":[-3.6801590919,40.1138458252],"type":"Point"}
}