{
  "type": "Feature",
  "properties": {
    "addr:full":"Avda Cesareo Alierta, 8 Zaragoza Zaragoza 50008",
    "addr:housenumber":"8",
    "addr:postcode":"50008",
    "addr:street":"Avda Cesareo Alierta",
    "iso:country":"ES",
    "sg:address":"Avda Cesareo Alierta, 8",
    "sg:city":"Zaragoza",
    "sg:orig_category":"Peleter\u00cdas",
    "sg:phone":"+34 976 21 63 92",
    "sg:postcode":"50008",
    "sg:province":"Zaragoza",
    "wof:name":"Morales Ruiz Gabriel",
    "wof:placetype":"venue"
},
  "geometry": {"coordinates":[-0.8795819879,41.6465759277],"type":"Point"}
}