{
  "type": "Feature",
  "properties": {
    "addr:full":"Carr Cooperativa, 8 Silla Valencia 46460",
    "addr:housenumber":"8",
    "addr:postcode":"46460",
    "addr:street":"Carr Cooperativa",
    "iso:country":"ES",
    "sg:address":"Carr Cooperativa, 8",
    "sg:city":"Silla",
    "sg:orig_category":"Mec\u00c1nico Del Autom\u00d3vil",
    "sg:phone":"+34 961 20 26 28",
    "sg:postcode":"46460",
    "sg:province":"Valencia",
    "wof:name":"Martinez Martinez Jose Vicente",
    "wof:placetype":"venue"
},
  "geometry": {"coordinates":[-0.4091179967,39.3668556213],"type":"Point"}
}