{
  "type": "Feature",
  "properties": {
    "addr:full":"Avda Luis Gonzalez Taboada, 9 Lalin Pontevedra 36500",
    "addr:housenumber":"9",
    "addr:postcode":"36500",
    "addr:street":"Avda Luis Gonzalez Taboada",
    "iso:country":"ES",
    "sg:address":"Avda Luis Gonzalez Taboada, 9",
    "sg:city":"Lalin",
    "sg:orig_category":"Muebles, Minoristas",
    "sg:phone":"+34 986 78 34 79",
    "sg:postcode":"36500",
    "sg:province":"Pontevedra",
    "wof:name":"Gonzalez Dieguez Maria Del Carmen",
    "wof:placetype":"venue"
},
  "geometry": {"coordinates":[-8.1106271744,42.6613235474],"type":"Point"}
}