{
  "type": "Feature",
  "properties": {
    "iso:country":"ES",
    "sg:address":"Calle de Miguel De Unamuno, 2",
    "sg:city":"Alcazar S. Juan",
    "sg:orig_category":"Lencer\u00cda Femenina, Corseter\u00cda, Trajes De Ba\u00d1o (al Por Menor)",
    "sg:phone":"+34 926 54 27 13",
    "sg:postcode":"13600",
    "sg:province":"Ciudad Real",
    "wof:name":"Maria Torres Gonzalez S.l.",
    "wof:placetype":"venue"
},
  "geometry": {"coordinates":[-3.2069690228,39.3924865723],"type":"Point"}
}