{
  "type": "Feature",
  "properties": {
    "addr:full":"Calle de Villar Y Villate, 7 Sestao Vizcaya 48910",
    "addr:housenumber":"7",
    "addr:postcode":"48910",
    "addr:street":"Calle De Villar Y Villate",
    "iso:country":"ES",
    "sg:address":"Calle de Villar Y Villate, 7",
    "sg:city":"Sestao",
    "sg:orig_category":"Consultas M\u00c9dicas",
    "sg:phone":"+34 944 95 58 46",
    "sg:postcode":"48910",
    "sg:province":"Vizcaya",
    "wof:name":"Esteban Fernandez Abascal Y Otros Cdad",
    "wof:placetype":"venue"
},
  "geometry": {"coordinates":[-3.0073270798,43.3085250854],"type":"Point"}
}