{
  "type": "Feature",
  "properties": {
    "addr:full":"Calle de Mayor, 271 Raal Murcia 30139",
    "addr:housenumber":"271",
    "addr:postcode":"30139",
    "addr:street":"Calle De Mayor",
    "iso:country":"ES",
    "sg:address":"Calle de Mayor, 271",
    "sg:city":"Raal",
    "sg:orig_category":"Agencias Y Agentes Comerciales, Representantes",
    "sg:phone":"+34 968 81 29 62",
    "sg:postcode":"30139",
    "sg:province":"Murcia",
    "wof:name":"Gonzalez Sanchez Jose Antonio",
    "wof:placetype":"venue"
},
  "geometry": {"coordinates":[-1.0214036703,38.0437469482],"type":"Point"}
}