{
  "type": "Feature",
  "properties": {
    "addr:full":"Calle de Laboratorios, 12 Gijon Asturias 33212",
    "addr:housenumber":"12",
    "addr:postcode":"33212",
    "addr:street":"Calle De Laboratorios",
    "iso:country":"ES",
    "sg:address":"Calle de Laboratorios, 12",
    "sg:city":"Gijon",
    "sg:orig_category":"Tiendas De Grano, Frutas Y Legumbres Secas (al Por Menor)",
    "sg:phone":"+34 985 32 40 30",
    "sg:postcode":"33212",
    "sg:province":"Asturias",
    "wof:name":"Alvarez Sagredo Margarita",
    "wof:placetype":"venue"
},
  "geometry": {"coordinates":[-5.6913580894,43.5398445129],"type":"Point"}
}