{
  "type": "Feature",
  "properties": {
    "addr:full":"A Lagoa, S/n Dozon Pontevedra 36516",
    "addr:housenumber":"s",
    "addr:postcode":"36516",
    "addr:street":"A Lagoa;/ N",
    "iso:country":"ES",
    "sg:address":"A Lagoa, S/n",
    "sg:city":"Dozon",
    "sg:orig_category":"Alimentaci\u00d3n General (al Por Mayor)",
    "sg:phone":"+34 986 78 08 38",
    "sg:postcode":"36516",
    "sg:province":"Pontevedra",
    "sg:website":"www.nucamsa.es",
    "wof:name":"Nucamsa S.a.",
    "wof:placetype":"venue"
},
  "geometry": {"coordinates":[-8.0170211792,42.6201248169],"type":"Point"}
}