{
  "type": "Feature",
  "properties": {
    "iso:country":"ES",
    "sg:address":"Carrer de Antoni De Capmany, 52",
    "sg:city":"Mataro",
    "sg:orig_category":"Abogados",
    "sg:phone":"+34 937 55 02 17",
    "sg:postcode":"08301",
    "sg:province":"Barcelona",
    "wof:name":"Serra Toledo Inmaculada",
    "wof:placetype":"venue"
},
  "geometry": {"coordinates":[2.4527359009,41.5421676636],"type":"Point"}
}