{
  "type": "Feature",
  "properties": {
    "addr:full":"Avda Juan Luis Peralta, 16 Benalmadena M\u00e1laga 29639",
    "addr:housenumber":"16",
    "addr:postcode":"29639",
    "addr:street":"Avda Juan Luis Peralta",
    "iso:country":"ES",
    "sg:address":"Avda Juan Luis Peralta, 16",
    "sg:city":"Benalmadena",
    "sg:orig_category":"Farmacias",
    "sg:phone":"+34 952 56 92 71",
    "sg:postcode":"29639",
    "sg:province":"M\u00e1laga",
    "wof:name":"Romero Mu\u00f1oz Juan Manuel",
    "wof:placetype":"venue"
},
  "geometry": {"coordinates":[-4.5724902153,36.5963554382],"type":"Point"}
}