{
  "type": "Feature",
  "properties": {
    "iso:country":"ES",
    "sg:address":"Calle de Santa Teresa, 9",
    "sg:city":"Navalperal Pinares",
    "sg:orig_category":"Empresarios",
    "sg:phone":"+34 918 98 00 17",
    "sg:postcode":"05240",
    "sg:province":"\u00c1vila",
    "wof:name":"Aguila Herranz Juan",
    "wof:placetype":"venue"
},
  "geometry": {"coordinates":[-4.4106965065,40.5918769836],"type":"Point"}
}