{
  "type": "Feature",
  "properties": {
    "addr:full":"Avda Constitucion, 76 Cari\u00f1o La Coru\u00f1a 15360",
    "addr:housenumber":"76",
    "addr:postcode":"15360",
    "addr:street":"Avda Constitucion;Corun\u0303A",
    "iso:country":"ES",
    "sg:address":"Avda Constitucion, 76",
    "sg:city":"Cari\u00f1o",
    "sg:orig_category":"Quiropr\u00c1cticos",
    "sg:phone":"+34 981 42 00 89",
    "sg:postcode":"15360",
    "sg:province":"La Coru\u00f1a",
    "wof:name":"Garcia Cuevas Rosalinda",
    "wof:placetype":"venue"
},
  "geometry": {"coordinates":[-7.8734688759,43.7389183044],"type":"Point"}
}