{
  "type": "Feature",
  "properties": {
    "iso:country":"ES",
    "sg:address":"Calle de Torrejon, 28",
    "sg:city":"Ajalvir",
    "sg:orig_category":"Administradores De Bienes Y Delegados De Comunidades De Propietarios",
    "sg:phone":"+34 918 84 40 28",
    "sg:postcode":"28864",
    "sg:province":"Madrid",
    "wof:name":"Berdejo Garcia Feliciana",
    "wof:placetype":"venue"
},
  "geometry": {"coordinates":[-3.481511116,40.5311546326],"type":"Point"}
}