{
  "type": "Feature",
  "properties": {
    "addr:full":"Calle de Jose Echegaray, 34 Dolores Alicante 03150",
    "addr:housenumber":"34",
    "addr:postcode":"03150",
    "addr:street":"Calle De Jose Echegaray",
    "iso:country":"ES",
    "sg:address":"Calle de Jose Echegaray, 34",
    "sg:city":"Dolores",
    "sg:orig_category":"Ingenier\u00cda, Centros De Estudios (diversos)",
    "sg:phone":"+34 966 71 16 16",
    "sg:postcode":"03150",
    "sg:province":"Alicante",
    "wof:name":"Escribano Ruiz Jose Manuel",
    "wof:placetype":"venue"
},
  "geometry": {"coordinates":[-0.7708910108,38.1372566223],"type":"Point"}
}