{
  "type": "Feature",
  "properties": {
    "addr:full":"Pase Castellana, 40 Madrid Madrid 28046",
    "addr:housenumber":"40",
    "addr:postcode":"madrid;28046",
    "addr:street":"Castellana",
    "iso:country":"ES",
    "sg:address":"Pase Castellana, 40",
    "sg:city":"Madrid",
    "sg:orig_category":"Inversiones",
    "sg:phone":"+34 915 78 42 16",
    "sg:postcode":"28046",
    "sg:province":"Madrid",
    "wof:name":"Inaltia Grupo Empresarial S.l.",
    "wof:placetype":"venue"
},
  "geometry": {"coordinates":[-3.687967062,40.4335174561],"type":"Point"}
}