{
  "type": "Feature",
  "properties": {
    "iso:country":"ES",
    "sg:address":"Calle de Iglesia (de La), 5",
    "sg:city":"Fuenlabrada",
    "sg:orig_category":"Papel (al Por Mayor)",
    "sg:phone":"+34 916 85 62 47",
    "sg:postcode":"28944",
    "sg:province":"Madrid",
    "wof:name":"Manupapel Sociedad Cooperativa",
    "wof:placetype":"venue"
},
  "geometry": {"coordinates":[-3.7913389206,40.2824516296],"type":"Point"}
}