{
  "type": "Feature",
  "properties": {
    "iso:country":"ES",
    "sg:address":"Calle de Plata, 14",
    "sg:city":"Valladolid",
    "sg:orig_category":"Artes Gr\u00c1ficas, Artes Pl\u00c1sticas (curso)",
    "sg:phone":"+34 983 30 35 64",
    "sg:postcode":"47012",
    "sg:province":"Valladolid",
    "wof:name":"Encuadernaciones Quattro Sl",
    "wof:placetype":"venue"
},
  "geometry": {"coordinates":[-4.7002949715,41.6202659607],"type":"Point"}
}