{
  "type": "Feature",
  "properties": {
    "addr:full":"Calle de Leon Y Castillo, 100 Palmas De Gran Canaria Las Palmas 35004",
    "addr:housenumber":"100",
    "addr:postcode":"35004",
    "addr:street":"Calle De Leon Y Castillo",
    "iso:country":"ES",
    "sg:address":"Calle de Leon Y Castillo, 100",
    "sg:city":"Palmas De Gran Canaria",
    "sg:orig_category":"Muebles, Minoristas",
    "sg:phone":"+34 928 24 04 30",
    "sg:postcode":"35004",
    "sg:province":"Las Palmas",
    "wof:name":"Muebles Atlas S.l.",
    "wof:placetype":"venue"
},
  "geometry": {"coordinates":[-15.4227705002,28.116853714],"type":"Point"}
}