{
  "type": "Feature",
  "properties": {
    "addr:full":"Cmno Atajadero (del), S/n Huetor-vega Granada 18198",
    "addr:postcode":"18198",
    "addr:street":"Cmno Atajadero Del S / N Huetor-Vega",
    "iso:country":"ES",
    "sg:address":"Cmno Atajadero (del), S/n",
    "sg:city":"Huetor-vega",
    "sg:orig_category":"Chapister\u00cda",
    "sg:phone":"+34 958 30 07 98",
    "sg:postcode":"18198",
    "sg:province":"Granada",
    "wof:name":"Carrocerias Daytona S.l.l.",
    "wof:placetype":"venue"
},
  "geometry": {"coordinates":[-3.5697190762,37.1477661133],"type":"Point"}
}