{
  "type": "Feature",
  "properties": {
    "addr:full":"Pla\u00c7 Auditorium Moreno Gans, 5 Algemesi Valencia 46680",
    "addr:housenumber":"5",
    "addr:postcode":"46680",
    "addr:street":"Gans",
    "iso:country":"ES",
    "sg:address":"Pla\u00c7 Auditorium Moreno Gans, 5",
    "sg:city":"Algemesi",
    "sg:orig_category":"Fabricaci\u00d3n De Productos Textiles Sin Tejer",
    "sg:phone":"+34 962 42 63 67",
    "sg:postcode":"46680",
    "sg:province":"Valencia",
    "wof:name":"Chanomaravilla S.l.",
    "wof:placetype":"venue"
},
  "geometry": {"coordinates":[-0.4333930016,39.1900558472],"type":"Point"}
}