{
  "type": "Feature",
  "properties": {
    "addr:full":"Calle de Antonio Trueba, 1 Arizgoiti Vizcaya 48970",
    "addr:housenumber":"1",
    "addr:postcode":"48970",
    "addr:street":"Calle De Antonio Trueba",
    "iso:country":"ES",
    "sg:address":"Calle de Antonio Trueba, 1",
    "sg:city":"Arizgoiti",
    "sg:orig_category":"Peleter\u00cdas",
    "sg:phone":"+34 944 40 65 20",
    "sg:postcode":"48970",
    "sg:province":"Vizcaya",
    "wof:name":"Gomez Lopez Ana Maria",
    "wof:placetype":"venue"
},
  "geometry": {"coordinates":[-2.8836586475,43.2365646362],"type":"Point"}
}