{
  "type": "Feature",
  "properties": {
    "addr:full":"Avda Barranquilla, 24 Madrid Madrid 28033",
    "addr:housenumber":"24",
    "addr:postcode":"madrid;28033",
    "addr:street":"Avda Barranquilla",
    "iso:country":"ES",
    "sg:address":"Avda Barranquilla, 24",
    "sg:city":"Madrid",
    "sg:orig_category":"Alimentaci\u00d3n General (al Por Menor)",
    "sg:phone":"+34 913 81 43 85",
    "sg:postcode":"28033",
    "sg:province":"Madrid",
    "wof:name":"Benitez Prada Heriberto",
    "wof:placetype":"venue"
},
  "geometry": {"coordinates":[-3.6393389702,40.4757499695],"type":"Point"}
}