{
  "type": "Feature",
  "properties": {
    "addr:full":"Calle de Julio Gomez Relampaguito, 9 Almeria Almer\u00eda 04008",
    "addr:housenumber":"9",
    "addr:postcode":"04008",
    "addr:street":"Calle De Julio Gomez Relampaguito",
    "iso:country":"ES",
    "sg:address":"Calle de Julio Gomez Relampaguito, 9",
    "sg:city":"Almeria",
    "sg:orig_category":"Agentes Generales De Seguros",
    "sg:phone":"+34 950 25 01 66",
    "sg:postcode":"04008",
    "sg:province":"Almer\u00eda",
    "wof:name":"Garcia Crespo Ana Maria",
    "wof:placetype":"venue"
},
  "geometry": {"coordinates":[-2.4606499672,36.8487281799],"type":"Point"}
}