{
  "type": "Feature",
  "properties": {
    "addr:full":"Avda Jose Garcia Santos, 19 Villares Reina Salamanca 37184",
    "addr:housenumber":"19",
    "addr:postcode":"37184",
    "addr:street":"Avda Jose Garcia Santos",
    "iso:country":"ES",
    "sg:address":"Avda Jose Garcia Santos, 19",
    "sg:city":"Villares Reina",
    "sg:orig_category":"Bazares, Art\u00cdculos De Limpieza Y De Cocina (al Por Menor)",
    "sg:phone":"+34 923 28 86 34",
    "sg:postcode":"37184",
    "sg:province":"Salamanca",
    "wof:name":"Muriel Hernandez Victoria",
    "wof:placetype":"venue"
},
  "geometry": {"coordinates":[-5.6457839012,41.0042381287],"type":"Point"}
}