{
  "type": "Feature",
  "properties": {
    "addr:full":"Calle de Toledo, 14 Torrejon Ardoz Madrid 28850",
    "addr:housenumber":"14",
    "addr:postcode":"28850",
    "addr:street":"Calle De Toledo",
    "iso:country":"ES",
    "sg:address":"Calle de Toledo, 14",
    "sg:city":"Torrejon Ardoz",
    "sg:orig_category":"Fabricaci\u00d3n De Cortinas Y Visillos",
    "sg:phone":"+34 916 78 04 61",
    "sg:postcode":"28850",
    "sg:province":"Madrid",
    "wof:name":"Gofer Hogar S.l.",
    "wof:placetype":"venue"
},
  "geometry": {"coordinates":[-3.4850969315,40.4539718628],"type":"Point"}
}