{
  "type": "Feature",
  "properties": {
    "addr:full":"Calle de Floranes, 37 Santander Cantabria 39010",
    "addr:housenumber":"37",
    "addr:postcode":"39010",
    "addr:street":"Calle De Floranes",
    "iso:country":"ES",
    "sg:address":"Calle de Floranes, 37",
    "sg:city":"Santander",
    "sg:orig_category":"Frutas, Legumbres Frescas Y Tempranas (al Por Menor)",
    "sg:phone":"+34 942 37 50 45",
    "sg:postcode":"39010",
    "sg:province":"Cantabria",
    "wof:name":"Fuentevilla Perales Jose Alberto",
    "wof:placetype":"venue"
},
  "geometry": {"coordinates":[-3.82228899,43.4603843689],"type":"Point"}
}