{
  "type": "Feature",
  "properties": {
    "iso:country":"ES",
    "sg:address":"Calle de Linda Vista, 1",
    "sg:city":"San Pedro Alcantara",
    "sg:orig_category":"Centros De Adelgazamiento Y De Est\u00c9tica",
    "sg:phone":"+34 952 78 89 85",
    "sg:postcode":"29670",
    "sg:province":"M\u00e1laga",
    "wof:name":"Inversiones Torre Del Mar S.l.",
    "wof:placetype":"venue"
},
  "geometry": {"coordinates":[-4.9936599731,36.4844207764],"type":"Point"}
}