{
  "type": "Feature",
  "properties": {
    "addr:full":"Rua Rubalcava, 19 Ferrol La Coru\u00f1a 15402",
    "addr:housenumber":"19",
    "addr:postcode":"15402",
    "addr:street":"Rua Rubalcava;La Corun\u0303A",
    "iso:country":"ES",
    "sg:address":"Rua Rubalcava, 19",
    "sg:city":"Ferrol",
    "sg:orig_category":"Negocio De Materiales De Construcci\u00d3n",
    "sg:phone":"+34 981 35 26 41",
    "sg:postcode":"15402",
    "sg:province":"La Coru\u00f1a",
    "wof:name":"S.a. De Obras Y Servicios Copasa",
    "wof:placetype":"venue"
},
  "geometry": {"coordinates":[-8.2330989838,43.4854507446],"type":"Point"}
}