{
  "type": "Feature",
  "properties": {
    "iso:country":"ES",
    "sg:address":"Calle de Samaniego, 38",
    "sg:city":"Najera",
    "sg:orig_category":"T\u00c9cnicos Veterinarios",
    "sg:phone":"+34 941 36 30 72",
    "sg:postcode":"26300",
    "sg:province":"La Rioja",
    "wof:name":"Centro Veterinario De Najera S.l.",
    "wof:placetype":"venue"
},
  "geometry": {"coordinates":[-2.7296209335,42.4192276001],"type":"Point"}
}