{
  "type": "Feature",
  "properties": {
    "iso:country":"ES",
    "sg:address":"Bule Luciano Demetrio Herrero, 7",
    "sg:city":"Torrelavega",
    "sg:orig_category":"\u00d3ptica: Instrumentos (fabricaci\u00d3n)",
    "sg:phone":"+34 942 88 39 80",
    "sg:postcode":"39300",
    "sg:province":"Cantabria",
    "wof:name":"Centro Optico Bulevar S.l.",
    "wof:placetype":"venue"
},
  "geometry": {"coordinates":[-4.050134182,43.3491668701],"type":"Point"}
}