{
  "type": "Feature",
  "properties": {
    "addr:full":"Carrer de Virgili, 70 Barcelona Barcelona 08030",
    "addr:housenumber":"70",
    "addr:postcode":"08030",
    "addr:street":"Carrer De Virgili",
    "iso:country":"ES",
    "sg:address":"Carrer de Virgili, 70",
    "sg:city":"Barcelona",
    "sg:orig_category":"Molduras, Junquillos, Listones Y Molduras Perforadas",
    "sg:phone":"+34 933 11 10 06",
    "sg:postcode":"08030",
    "sg:province":"Barcelona",
    "wof:name":"Tutusans Olivella Jose",
    "wof:placetype":"venue"
},
  "geometry": {"coordinates":[2.1933660507,41.4318313599],"type":"Point"}
}