{
  "type": "Feature",
  "properties": {
    "addr:full":"Avda Almeria, 4 Pi\u00f1ar Granada 18568",
    "addr:housenumber":"4",
    "addr:postcode":"18568",
    "addr:street":"Avda Almeria",
    "iso:country":"ES",
    "sg:address":"Avda Almeria, 4",
    "sg:city":"Pi\u00f1ar",
    "sg:orig_category":"Agentes, Concesionarios Y Sucursales De Veh\u00cdculos",
    "sg:phone":"+34 958 39 46 01",
    "sg:postcode":"18568",
    "sg:province":"Granada",
    "wof:name":"Talleres Exta Montes S.l.",
    "wof:placetype":"venue"
},
  "geometry": {"coordinates":[-3.4385120869,37.4458808899],"type":"Point"}
}