{
  "type": "Feature",
  "properties": {
    "iso:country":"ES",
    "sg:address":"Avda Bilbao, S/n",
    "sg:city":"Medina Pomar",
    "sg:orig_category":"Frutas Y Legumbres Frescas (al Por Mayor)",
    "sg:phone":"+34 947 19 05 43",
    "sg:postcode":"09500",
    "sg:province":"Burgos",
    "wof:name":"Hortalizas Angel Santamaria Ortega S.l",
    "wof:placetype":"venue"
},
  "geometry": {"coordinates":[-3.4859941006,42.932598114],"type":"Point"}
}