{
  "type": "Feature",
  "properties": {
    "addr:full":"Calle de Wamba, 1 Valladolid Valladolid 47008",
    "addr:housenumber":"1",
    "addr:postcode":"47008",
    "addr:street":"Calle De Wamba",
    "iso:country":"ES",
    "sg:address":"Calle de Wamba, 1",
    "sg:city":"Valladolid",
    "sg:orig_category":"Artes Gr\u00c1ficas, Artes Pl\u00c1sticas (curso)",
    "sg:phone":"+34 983 22 70 07",
    "sg:postcode":"47008",
    "sg:province":"Valladolid",
    "wof:name":"De La Loma Preimpresion Digital S.l.",
    "wof:placetype":"venue"
},
  "geometry": {"coordinates":[-4.7413358688,41.6231842041],"type":"Point"}
}