{
  "type": "Feature",
  "properties": {
    "addr:full":"Guionista Iborra, 16 Alfas Pi Alicante 03580",
    "addr:housenumber":"16",
    "addr:postcode":"03580",
    "addr:street":"Iborra",
    "iso:country":"ES",
    "sg:address":"Guionista Iborra, 16",
    "sg:city":"Alfas Pi",
    "sg:orig_category":"Promotores Constructores",
    "sg:phone":"+34 965 88 70 44",
    "sg:postcode":"03580",
    "sg:province":"Alicante",
    "sg:website":"www.solerinmo.com",
    "wof:name":"Solalfas 1 S.l.",
    "wof:placetype":"venue"
},
  "geometry": {"coordinates":[-0.1106439978,38.5881652832],"type":"Point"}
}