{
  "type": "Feature",
  "properties": {
    "iso:country":"ES",
    "sg:address":"Calle de Antonio Eulate, 1",
    "sg:city":"Lucena",
    "sg:orig_category":"Promotores Constructores",
    "sg:phone":"+34 957 51 50 60",
    "sg:postcode":"14900",
    "sg:province":"C\u00f3rdoba",
    "sg:website":"www.probamo.com",
    "wof:name":"Probamo S.l.",
    "wof:placetype":"venue"
},
  "geometry": {"coordinates":[-4.4849729538,37.4071006775],"type":"Point"}
}