{
  "type": "Feature",
  "properties": {
    "iso:country":"ES",
    "sg:address":"Calle de Autonomia, 78",
    "sg:city":"Bilbao",
    "sg:orig_category":"Pintores",
    "sg:phone":"+34 944 42 54 61",
    "sg:postcode":"48012",
    "sg:province":"Vizcaya",
    "wof:name":"Garcia Campos Luis",
    "wof:placetype":"venue"
},
  "geometry": {"coordinates":[-2.9423234463,43.257610321],"type":"Point"}
}