{
  "type": "Feature",
  "properties": {
    "addr:full":"Calle de Puente, 2 Aguilar Campoo Palencia 34800",
    "addr:housenumber":"2",
    "addr:postcode":"34800",
    "addr:street":"Calle De Puente",
    "iso:country":"ES",
    "sg:address":"Calle de Puente, 2",
    "sg:city":"Aguilar Campoo",
    "sg:orig_category":"Bancos",
    "sg:phone":"+34 979 12 20 17",
    "sg:postcode":"34800",
    "sg:province":"Palencia",
    "sg:website":"www.bancocastilla.es",
    "wof:name":"Banco De Castilla",
    "wof:placetype":"venue"
},
  "geometry": {"coordinates":[-4.2620577812,42.7927627563],"type":"Point"}
}