{
  "type": "Feature",
  "properties": {
    "addr:full":"Calle de Concepcion, 17 Pto Real C\u00e1diz 11510",
    "addr:housenumber":"17",
    "addr:postcode":"11510",
    "addr:street":"Calle De Concepcion;Ca\u0301Diz",
    "iso:country":"ES",
    "sg:address":"Calle de Concepcion, 17",
    "sg:city":"Pto Real",
    "sg:classifiers":[
        {
            "category":"Autos & Motor Vehicles",
            "subcategory":"Automobile Sales",
            "type":"Retail Goods"
        }
    ],
    "sg:phone":"+34 956 83 54 01",
    "sg:postcode":"11510",
    "sg:province":"C\u00e1diz",
    "wof:name":"Venecia Sur S.l.",
    "wof:placetype":"venue"
},
  "geometry": {"coordinates":[-6.1860790253,36.5281295776],"type":"Point"}
}