{
  "type": "Feature",
  "properties": {
    "addr:full":"Luga Amarguillo-matamoros (el), S/n Ubrique C\u00e1diz 11600",
    "addr:housenumber":"/ n",
    "addr:postcode":"11600",
    "addr:street":"El S;Ca\u0301Diz",
    "iso:country":"ES",
    "sg:address":"Luga Amarguillo-matamoros (el), S/n",
    "sg:city":"Ubrique",
    "sg:orig_category":"Bebidas",
    "sg:phone":"+34 956 23 41 68",
    "sg:postcode":"11600",
    "sg:province":"C\u00e1diz",
    "wof:name":"Distribuciones O G O\u00f1ate Gomez S.l.",
    "wof:placetype":"venue"
},
  "geometry": {"coordinates":[-5.4475698471,36.6776618958],"type":"Point"}
}