{
  "type": "Feature",
  "properties": {
    "addr:full":"Calle de Santa Ana, 7 Logrosan C\u00e1ceres 10120",
    "addr:housenumber":"7",
    "addr:postcode":"10120",
    "addr:street":"Calle De Santa Ana;Ca\u0301Ceres",
    "iso:country":"ES",
    "sg:address":"Calle de Santa Ana, 7",
    "sg:city":"Logrosan",
    "sg:orig_category":"Carnicer\u00cdas, Carnicer\u00cdas",
    "sg:phone":"+34 927 36 00 11",
    "sg:postcode":"10120",
    "sg:province":"C\u00e1ceres",
    "wof:name":"Pedrero Fernandez Agustin",
    "wof:placetype":"venue"
},
  "geometry": {"coordinates":[-5.4972071648,39.3368034363],"type":"Point"}
}