{
  "type": "Feature",
  "properties": {
    "addr:full":"Calle de Poeta Miguel Hernandez, 11 San Antonio Abad Murcia 30204",
    "addr:housenumber":"11",
    "addr:postcode":"30204",
    "addr:street":"Calle De Poeta Miguel Hernandez",
    "iso:country":"ES",
    "sg:address":"Calle de Poeta Miguel Hernandez, 11",
    "sg:city":"San Antonio Abad",
    "sg:orig_category":"Inmobiliaria (agencias)",
    "sg:phone":"+34 968 51 74 68",
    "sg:postcode":"30204",
    "sg:province":"Murcia",
    "wof:name":"Yamaca Grupo Inmobiliario Sl",
    "wof:placetype":"venue"
},
  "geometry": {"coordinates":[-0.9877589941,37.6067504883],"type":"Point"}
}