{
  "type": "Feature",
  "properties": {
    "addr:full":"Pg Santa Coloma, 125 Barcelona Barcelona 08030",
    "addr:housenumber":"125",
    "addr:postcode":"08030",
    "addr:street":"Pg Santa Coloma",
    "iso:country":"ES",
    "sg:address":"Pg Santa Coloma, 125",
    "sg:city":"Barcelona",
    "sg:orig_category":"Art\u00cdculos Para Fumadores (al Por Menor)",
    "sg:phone":"+34 932 74 35 76",
    "sg:postcode":"08030",
    "sg:province":"Barcelona",
    "wof:name":"Miquel Y Costas Y Miquel S.a.",
    "wof:placetype":"venue"
},
  "geometry": {"coordinates":[2.2005469799,41.4489173889],"type":"Point"}
}