{
  "type": "Feature",
  "properties": {
    "iso:country":"ES",
    "sg:address":"Avda Castilla La Mancha, 1",
    "sg:city":"Illescas",
    "sg:orig_category":"Promotores Constructores",
    "sg:phone":"+34 925 53 20 27",
    "sg:postcode":"45200",
    "sg:province":"Toledo",
    "wof:name":"Grupo Inmobiliario Los Olivos 2004 S.l",
    "wof:placetype":"venue"
},
  "geometry": {"coordinates":[-3.8444209099,40.1288948059],"type":"Point"}
}