{
  "type": "Feature",
  "properties": {
    "addr:full":"Zaldibi Bidea, 2 Ordizia Guip\u00f9zcoa 20240",
    "addr:housenumber":"2",
    "addr:postcode":"20240",
    "addr:street":"Zaldibi Bidea;Guipu\u0300Zcoa",
    "iso:country":"ES",
    "sg:address":"Zaldibi Bidea, 2",
    "sg:city":"Ordizia",
    "sg:orig_category":"Comercio, Reparaci\u00d3n De Bicicletas, De Motocicletas, De Accesorios",
    "sg:phone":"+34 943 16 16 27",
    "sg:postcode":"20240",
    "sg:province":"Guip\u00f9zcoa",
    "wof:name":"Marotias Irazustabarrena Juan Carlos",
    "wof:placetype":"venue"
},
  "geometry": {"coordinates":[-2.1773040295,43.0538711548],"type":"Point"}
}