{
  "type": "Feature",
  "properties": {
    "addr:full":"Calle de Real, 7 Ayllon Segovia 40520",
    "addr:housenumber":"7",
    "addr:postcode":"40520",
    "addr:street":"Calle De Real",
    "iso:country":"ES",
    "sg:address":"Calle de Real, 7",
    "sg:city":"Ayllon",
    "sg:orig_category":"Contenedores (mercanc\u00cdas)",
    "sg:phone":"+34 921 55 32 06",
    "sg:postcode":"40520",
    "sg:province":"Segovia",
    "wof:name":"Transportes Sanz C.b.",
    "wof:placetype":"venue"
},
  "geometry": {"coordinates":[-3.3343780041,41.361541748],"type":"Point"}
}