{
  "type": "Feature",
  "properties": {
    "iso:country":"ES",
    "sg:address":"Av Europa (d'), 45",
    "sg:city":"Blanes",
    "sg:orig_category":"Carnes De Carnicer\u00cda (al Por Mayor)",
    "sg:phone":"+34 972 35 85 80",
    "sg:postcode":"17300",
    "sg:province":"Girona",
    "wof:name":"Carniques Illas Juli S.l.",
    "wof:placetype":"venue"
},
  "geometry": {"coordinates":[2.7747199535,41.6766014099],"type":"Point"}
}