{
  "type": "Feature",
  "properties": {
    "addr:full":"Calle de Isaac Peral, 15 Rota C\u00e1diz 11520",
    "addr:housenumber":"15",
    "addr:postcode":"11520",
    "addr:street":"Calle De Isaac Peral;Ca\u0301Diz",
    "iso:country":"ES",
    "sg:address":"Calle de Isaac Peral, 15",
    "sg:city":"Rota",
    "sg:orig_category":"Bazares, Art\u00cdculos De Limpieza Y De Cocina (al Por Menor)",
    "sg:phone":"+34 956 81 11 92",
    "sg:postcode":"11520",
    "sg:province":"C\u00e1diz",
    "wof:name":"Perez Alegre Antonio",
    "wof:placetype":"venue"
},
  "geometry": {"coordinates":[-6.3590149879,36.6200447083],"type":"Point"}
}