{
  "type": "Feature",
  "properties": {
    "addr:full":"Carrer de Cura Fenoll, 8 Mutxamel Alicante 03110",
    "addr:housenumber":"8",
    "addr:postcode":"03110",
    "addr:street":"Carrer De Cura Fenoll",
    "iso:country":"ES",
    "sg:address":"Carrer de Cura Fenoll, 8",
    "sg:city":"Mutxamel",
    "sg:orig_category":"Clubes Y Asociaciones Deportivas Y De Actividades Invernales Y De Monta\u00d1a",
    "sg:phone":"+34 965 95 06 83",
    "sg:postcode":"03110",
    "sg:province":"Alicante",
    "wof:name":"Centre Muntanyisme Mutxamel",
    "wof:placetype":"venue"
},
  "geometry": {"coordinates":[-0.4454540014,38.4149551392],"type":"Point"}
}