{
  "type": "Feature",
  "properties": {
    "iso:country":"ES",
    "sg:address":"Carrer de Pi I Margall, 17",
    "sg:city":"Barcelona",
    "sg:orig_category":"Psic\u00d3logos",
    "sg:phone":"+34 932 13 46 77",
    "sg:postcode":"08024",
    "sg:province":"Barcelona",
    "wof:name":"Gonzalez Fernandez Joan Emili",
    "wof:placetype":"venue"
},
  "geometry": {"coordinates":[2.1631350517,41.4066314697],"type":"Point"}
}