{
  "type": "Feature",
  "properties": {
    "addr:full":"Doctor Vega Fernandez, 11 Trobajo Camino Le\u00f3n 24010",
    "addr:housenumber":"11",
    "addr:postcode":"24010",
    "addr:street":"Doctor Vega Fernandez;Camino Leo\u0301N",
    "iso:country":"ES",
    "sg:address":"Doctor Vega Fernandez, 11",
    "sg:city":"Trobajo Camino",
    "sg:orig_category":"Asociaciones Y Clubs Deportivos",
    "sg:phone":"+34 987 80 75 69",
    "sg:postcode":"24010",
    "sg:province":"Le\u00f3n",
    "wof:name":"Club Deportivo Huracan Z",
    "wof:placetype":"venue"
},
  "geometry": {"coordinates":[-5.5716600418,42.5981292725],"type":"Point"}
}