{
  "type": "Feature",
  "properties": {
    "iso:country":"ES",
    "sg:address":"Calle de Lucena Del Puerto, S/n",
    "sg:city":"Huelva",
    "sg:orig_category":"Bancos",
    "sg:phone":"+34 959 24 65 99",
    "sg:postcode":"21002",
    "sg:province":"Huelva",
    "wof:name":"Banco De Andalucia",
    "wof:placetype":"venue"
},
  "geometry": {"coordinates":[-6.9561238289,37.2645950317],"type":"Point"}
}