{
  "type": "Feature",
  "properties": {
    "iso:country":"ES",
    "sg:address":"Calle de Santa Cruz De Marcenado, 14",
    "sg:city":"Madrid",
    "sg:orig_category":"Aparcamientos (infraestructuras, Accesorios)",
    "sg:phone":"+34 914 48 95 22",
    "sg:postcode":"28015",
    "sg:province":"Madrid",
    "wof:name":"Ecenarro Balparda Jose Maria",
    "wof:placetype":"venue"
},
  "geometry": {"coordinates":[-3.7085440159,40.428894043],"type":"Point"}
}