{
  "type": "Feature",
  "properties": {
    "addr:full":"Masterreka Kalea, 13 Bergara Guip\u00f9zcoa 20570",
    "addr:housenumber":"13",
    "addr:postcode":"20570",
    "addr:street":"Masterreka Kalea;Guipu\u0300Zcoa",
    "iso:country":"ES",
    "sg:address":"Masterreka Kalea, 13",
    "sg:city":"Bergara",
    "sg:orig_category":"Asociaciones, Organismos Culturales Y Socioeducativos",
    "sg:phone":"+34 943 76 16 99",
    "sg:postcode":"20570",
    "sg:province":"Guip\u00f9zcoa",
    "wof:name":"Sociedad Cultural Bordatxo",
    "wof:placetype":"venue"
},
  "geometry": {"coordinates":[-2.413631916,43.1203155518],"type":"Point"}
}