{
  "type": "Feature",
  "properties": {
    "addr:full":"Calle de Gutenberg, 13 Zaragoza Zaragoza 50015",
    "addr:housenumber":"13",
    "addr:postcode":"50015",
    "addr:street":"Calle De Gutenberg",
    "iso:country":"ES",
    "sg:address":"Calle de Gutenberg, 13",
    "sg:city":"Zaragoza",
    "sg:classifiers":[
        {
            "category":"Manufacturing",
            "subcategory":"Metals",
            "type":"Manufacturing & Wholesale Goods"
        }
    ],
    "sg:phone":"+34 976 74 13 97",
    "sg:postcode":"50015",
    "sg:province":"Zaragoza",
    "sg:tags":[
        "en",
        "fundiciones"
    ],
    "wof:name":"Zademo S.l.",
    "wof:placetype":"venue"
},
  "geometry": {"coordinates":[-0.8665620089,41.678062439],"type":"Point"}
}