{
  "type": "Feature",
  "properties": {
    "iso:country":"ES",
    "sg:address":"Polig. A Gandara, S/n",
    "sg:city":"Ferrol",
    "sg:orig_category":"Lavado, Limpieza De Veh\u00cdculos",
    "sg:phone":"+34 981 32 90 23",
    "sg:postcode":"15407",
    "sg:province":"A Coru\u00f1a",
    "wof:name":"Serafin Ra\u00f1al Gra\u00f1a Y Otro Cdad.",
    "wof:placetype":"venue"
},
  "geometry": {"coordinates":[-8.1969175339,43.5052642822],"type":"Point"}
}