{
  "type": "Feature",
  "properties": {
    "addr:full":"Calle de Guecho, 27 Madrid Madrid 28023",
    "addr:housenumber":"27",
    "addr:postcode":"madrid;28023",
    "addr:street":"Calle De Guecho",
    "iso:country":"ES",
    "sg:address":"Calle de Guecho, 27",
    "sg:city":"Madrid",
    "sg:orig_category":"Arquitectos",
    "sg:phone":"+34 913 07 77 89",
    "sg:postcode":"28023",
    "sg:province":"Madrid",
    "wof:name":"Estudio Cano Lasso S.l.",
    "wof:placetype":"venue"
},
  "geometry": {"coordinates":[-3.8186058998,40.4736747742],"type":"Point"}
}