{
  "type": "Feature",
  "properties": {
    "iso:country":"ES",
    "sg:address":"Pg Jaume I (de), 22",
    "sg:city":"Salou",
    "sg:orig_category":"Fabricaci\u00d3n De Su\u00c9ters Y Chalecos De Punto",
    "sg:phone":"+34 977 35 28 67",
    "sg:postcode":"43840",
    "sg:province":"Tarragona",
    "wof:name":"Cetusa 1020 S.l.",
    "wof:placetype":"venue"
},
  "geometry": {"coordinates":[1.136950016,41.0749702454],"type":"Point"}
}