{
  "type": "Feature",
  "properties": {
    "iso:country":"ES",
    "sg:address":"Jose Lasa Etorbidea, 15",
    "sg:city":"Lazkao",
    "sg:orig_category":"Peluquer\u00cdas, Peluquer\u00cda Mixta",
    "sg:phone":"+34 943 16 30 08",
    "sg:postcode":"20210",
    "sg:province":"Guip\u00f9zcoa",
    "wof:name":"Cirez Gutierrez Angel",
    "wof:placetype":"venue"
},
  "geometry": {"coordinates":[-2.1855099201,43.0323677063],"type":"Point"}
}