{
  "type": "Feature",
  "properties": {
    "addr:full":"Calle de Jose Cruz Conde, 19 Cordoba C\u00f3rdoba 14001",
    "addr:housenumber":"19",
    "addr:postcode":"14001",
    "addr:street":"Calle De Jose Cruz Conde;Co\u0301Rdoba",
    "iso:country":"ES",
    "sg:address":"Calle de Jose Cruz Conde, 19",
    "sg:city":"Cordoba",
    "sg:orig_category":"Sociedades, Compa\u00d1\u00cdas Aseguradoras",
    "sg:phone":"+34 957 49 06 98",
    "sg:postcode":"14001",
    "sg:province":"C\u00f3rdoba",
    "wof:name":"Velasco Ca\u00f1adas Correduria De Seguros S.l.",
    "wof:placetype":"venue"
},
  "geometry": {"coordinates":[-4.781170845,37.8880157471],"type":"Point"}
}