{
  "type": "Feature",
  "properties": {
    "iso:country":"ES",
    "sg:address":"Calle de San Juan De Dios, 2",
    "sg:city":"Churriana Vega",
    "sg:orig_category":"Postigos, Persianas Y Celos\u00cdas",
    "sg:phone":"+34 958 55 14 31",
    "sg:postcode":"18194",
    "sg:province":"Granada",
    "wof:name":"Linares Nieto Virtudes",
    "wof:placetype":"venue"
},
  "geometry": {"coordinates":[-3.6488509178,37.145652771],"type":"Point"}
}