{
  "type": "Feature",
  "properties": {
    "addr:full":"Pase Poeta Aviles De Taramancos, 4 Noia La Coru\u00f1a 15200",
    "addr:housenumber":"4",
    "addr:postcode":"15200",
    "addr:street":"Poeta Aviles De Taramancos;La Corun\u0303A",
    "iso:country":"ES",
    "sg:address":"Pase Poeta Aviles De Taramancos, 4",
    "sg:city":"Noia",
    "sg:orig_category":"Caf\u00c9s, Bares, Cervecer\u00cdas",
    "sg:phone":"+34 981 82 37 15",
    "sg:postcode":"15200",
    "sg:province":"La Coru\u00f1a",
    "wof:name":"Galtelcom",
    "wof:placetype":"venue"
},
  "geometry": {"coordinates":[-8.874876976,42.8063011169],"type":"Point"}
}