{
  "type": "Feature",
  "properties": {
    "addr:full":"Canal, 18 Ponferrada Le\u00f3n 24400",
    "addr:postcode":"24400",
    "addr:street":"Canal",
    "iso:country":"ES",
    "sg:address":"Canal, 18",
    "sg:city":"Ponferrada",
    "sg:orig_category":"Empresas De Carpinter\u00cda Met\u00c1lica",
    "sg:phone":"+34 987 40 91 33",
    "sg:postcode":"24400",
    "sg:province":"Le\u00f3n",
    "wof:name":"Arte Metal Bierzo S.l.",
    "wof:placetype":"venue"
},
  "geometry": {"coordinates":[-6.606543541,42.5620269775],"type":"Point"}
}