{
  "type": "Feature",
  "properties": {
    "iso:country":"ES",
    "sg:address":"Calle de Corregidor Costilla, 11",
    "sg:city":"Astorga",
    "sg:orig_category":"Autob\u00das (explotaci\u00d3n Y Servicios De)",
    "sg:phone":"+34 987 61 73 31",
    "sg:postcode":"24700",
    "sg:province":"Le\u00f3n",
    "wof:name":"Agencia De Viajes Turrado S.l.",
    "wof:placetype":"venue"
},
  "geometry": {"coordinates":[-6.0565028191,42.4561347961],"type":"Point"}
}