{
  "type": "Feature",
  "properties": {
    "iso:country":"ES",
    "sg:address":"Calle de Poeta Juan Ramon Jimenez, 4",
    "sg:city":"Cordoba",
    "sg:orig_category":"Asesor\u00cdas Y Estudios Financieros",
    "sg:phone":"+34 957 27 24 36",
    "sg:postcode":"14012",
    "sg:province":"C\u00f3rdoba",
    "wof:name":"Fernandez De Molina Latorre Jose Carlos",
    "wof:placetype":"venue"
},
  "geometry": {"coordinates":[-4.7903728485,37.9027709961],"type":"Point"}
}