{
  "type": "Feature",
  "properties": {
    "iso:country":"ES",
    "sg:address":"Bo. Magdalena, 5",
    "sg:city":"Ubide",
    "sg:orig_category":"Partidos Pol\u00cdticos",
    "sg:phone":"+34 945 46 14 21",
    "sg:postcode":"48145",
    "sg:province":"Vizcaya",
    "wof:name":"Partido Nacionalista Vasco",
    "wof:placetype":"venue"
},
  "geometry": {"coordinates":[-2.6884338856,43.0250968933],"type":"Point"}
}