{
  "type": "Feature",
  "properties": {
    "addr:full":"Ctra De Ayamonte, Km. 0021,0 Villanueva De Los Castillejos Huelva 21540",
    "addr:postcode":"21540",
    "addr:street":"Ctra De Ayamonte Km. 0021,0 Villanueva",
    "iso:country":"ES",
    "sg:address":"Ctra De Ayamonte, Km. 0021,0",
    "sg:city":"Villanueva De Los Castillejos",
    "sg:orig_category":"Arboricultura Y Producci\u00d3n De Frutas",
    "sg:phone":"+34 959 50 40 63",
    "sg:postcode":"21540",
    "sg:province":"Huelva",
    "wof:name":"Antonio Mu\u00d1oz Y Cia S.a.",
    "wof:placetype":"venue"
},
  "geometry": {"coordinates":[-7.2697691917,37.5053939819],"type":"Point"}
}