{
  "type": "Feature",
  "properties": {
    "iso:country":"ES",
    "sg:address":"Carrer de Narcis Oller, 8",
    "sg:city":"Reus",
    "sg:orig_category":"Peluqueros: De Se\u00d1oras",
    "sg:phone":"+34 977 77 34 54",
    "sg:postcode":"43205",
    "sg:province":"Tarragona",
    "wof:name":"Soler Gomez Josefa",
    "wof:placetype":"venue"
},
  "geometry": {"coordinates":[1.1126610041,41.1421051025],"type":"Point"}
}