{
  "type": "Feature",
  "properties": {
    "iso:country":"ES",
    "sg:address":"Cami Vileta (la), 120",
    "sg:city":"Vileta",
    "sg:orig_category":"Ortofonistas",
    "sg:phone":"+34 971 79 81 88",
    "sg:postcode":"07011",
    "sg:province":"Islas Baleares",
    "wof:name":"Fontan Endrino Mario",
    "wof:placetype":"venue"
},
  "geometry": {"coordinates":[2.6207311153,39.5931129456],"type":"Point"}
}