{
  "type": "Feature",
  "properties": {
    "addr:full":"Calle de Salobre\u00d1a, 94 Albolote Granada 18220",
    "addr:housenumber":"94",
    "addr:postcode":"18220",
    "addr:street":"Calle De Salobren\u0303A",
    "iso:country":"ES",
    "sg:address":"Calle de Salobre\u00d1a, 94",
    "sg:city":"Albolote",
    "sg:orig_category":"Ferreter\u00cda (diversos)",
    "sg:phone":"+34 958 49 12 82",
    "sg:postcode":"18220",
    "sg:province":"Granada",
    "wof:name":"Hierros Y Pilotes Granada S.l",
    "wof:placetype":"venue"
},
  "geometry": {"coordinates":[-3.6469590664,37.226940155],"type":"Point"}
}