{
  "type": "Feature",
  "properties": {
    "iso:country":"ES",
    "sg:address":"Calle de Pintor Joaquin, 7",
    "sg:city":"San Anton",
    "sg:orig_category":"Farmacias",
    "sg:phone":"+34 968 29 92 68",
    "sg:postcode":"30009",
    "sg:province":"Murcia",
    "wof:name":"Maurandi Guillen Maria Dolores",
    "wof:placetype":"venue"
},
  "geometry": {"coordinates":[-1.1418349743,37.991191864],"type":"Point"}
}