{
  "type": "Feature",
  "properties": {
    "addr:full":"Calle de Ritas, 44 Villena Alicante 03400",
    "addr:housenumber":"44",
    "addr:postcode":"03400",
    "addr:street":"Calle De Ritas",
    "iso:country":"ES",
    "sg:address":"Calle de Ritas, 44",
    "sg:city":"Villena",
    "sg:orig_category":"Conservas De Pescados Y Salazones Mar\u00cdtimos (fabricaci\u00d3n, Al Por Mayor)",
    "sg:phone":"+34 965 81 45 97",
    "sg:postcode":"03400",
    "sg:province":"Alicante",
    "wof:name":"Semiconservas Rubio S.l.",
    "wof:placetype":"venue"
},
  "geometry": {"coordinates":[-0.8629699945,38.6364059448],"type":"Point"}
}