{
  "type": "Feature",
  "properties": {
    "iso:country":"ES",
    "sg:address":"Calle de Antonio Cano, 5",
    "sg:city":"Almeria",
    "sg:orig_category":"Peluquer\u00cdas, Peluquer\u00cda Mixta",
    "sg:phone":"+34 950 14 11 15",
    "sg:postcode":"04009",
    "sg:province":"Almer\u00eda",
    "wof:name":"Miranda Garcia Dolores Del Consuelo",
    "wof:placetype":"venue"
},
  "geometry": {"coordinates":[-2.4473237991,36.8510971069],"type":"Point"}
}