{
  "type": "Feature",
  "properties": {
    "addr:full":"Iglesia, 5 Sergude La Coru\u00f1a 15881",
    "addr:housenumber":"5",
    "addr:postcode":"15881",
    "addr:street":"Iglesia;La Corun\u0303A",
    "iso:country":"ES",
    "sg:address":"Iglesia, 5",
    "sg:city":"Sergude",
    "sg:orig_category":"Molduras, Junquillos, Listones Y Molduras Perforadas",
    "sg:phone":"+34 981 51 18 44",
    "sg:postcode":"15881",
    "sg:province":"La Coru\u00f1a",
    "wof:name":"Munin Devesa Pedro",
    "wof:placetype":"venue"
},
  "geometry": {"coordinates":[-8.4128170013,42.8135566711],"type":"Point"}
}