{
  "type": "Feature",
  "properties": {
    "iso:country":"ES",
    "sg:address":"Ctr. Tresjuncos, S/n",
    "sg:city":"Osa Vega",
    "sg:orig_category":"Piedra Natural",
    "sg:phone":"+34 969 12 20 32",
    "sg:postcode":"16423",
    "sg:province":"Cuenca",
    "wof:name":"Marmoles Y Piedras Sanga S.l.",
    "wof:placetype":"venue"
},
  "geometry": {"coordinates":[-5.0554900169,42.0591087341],"type":"Point"}
}