{
  "type": "Feature",
  "properties": {
    "iso:country":"ES",
    "sg:address":"Calle de Santa Quiteria, S/n",
    "sg:city":"Santa Quiteria",
    "sg:orig_category":"Motocicletas (agentes, Concesionarios)",
    "sg:phone":"+34 968 46 78 79",
    "sg:postcode":"30800",
    "sg:province":"Murcia",
    "wof:name":"Alfonso Cuadrado Y Cia S.r.c.",
    "wof:placetype":"venue"
},
  "geometry": {"coordinates":[-1.1298867464,37.9834747314],"type":"Point"}
}