{
  "type": "Feature",
  "properties": {
    "addr:full":"Calle de Constitucion, 27 Alameda Sagra Toledo 45240",
    "addr:housenumber":"27",
    "addr:postcode":"45240",
    "addr:street":"Calle De Constitucion;Sagra",
    "iso:country":"ES",
    "sg:address":"Calle de Constitucion, 27",
    "sg:city":"Alameda Sagra",
    "sg:orig_category":"Negocio De Materiales De Construcci\u00d3n",
    "sg:phone":"+34 925 50 09 12",
    "sg:postcode":"45240",
    "sg:province":"Toledo",
    "wof:name":"F.a. Herrera S.l.",
    "wof:placetype":"venue"
},
  "geometry": {"coordinates":[-3.7962193489,40.012298584],"type":"Point"}
}