{
  "type": "Feature",
  "properties": {
    "iso:country":"ES",
    "sg:address":"Calle de Jaspe, 16",
    "sg:city":"Madrid",
    "sg:orig_category":"Chapister\u00cda",
    "sg:phone":"+34 914 75 32 30",
    "sg:postcode":"28026",
    "sg:province":"Madrid",
    "wof:name":"Gonzalez Blazquez Jose",
    "wof:placetype":"venue"
},
  "geometry": {"coordinates":[-3.7070949078,40.3821640015],"type":"Point"}
}