{
  "type": "Feature",
  "properties": {
    "addr:full":"Calle de San Lorenzo, 12 Donostia-san Sebastian Guip\u00f9zcoa 20003",
    "addr:housenumber":"12",
    "addr:postcode":"20003",
    "addr:street":"Calle De San Lorenzo",
    "iso:country":"ES",
    "sg:address":"Calle de San Lorenzo, 12",
    "sg:city":"Donostia-san Sebastian",
    "sg:orig_category":"Bisuter\u00cda, Joyer\u00cda, Relojer\u00cda (al Por Menor)",
    "sg:phone":"+34 943 42 76 29",
    "sg:postcode":"20003",
    "sg:province":"Guip\u00f9zcoa",
    "wof:name":"Beldarrain Larrea Jesus Maria",
    "wof:placetype":"venue"
},
  "geometry": {"coordinates":[-1.9839049578,43.3231506348],"type":"Point"}
}