{
  "type": "Feature",
  "properties": {
    "iso:country":"ES",
    "sg:address":"Calle de Don Ramon Areces, 2",
    "sg:city":"Valdemoro",
    "sg:orig_category":"Inmobiliaria (agencias)",
    "sg:phone":"+34 918 08 50 77",
    "sg:postcode":"28340",
    "sg:province":"Madrid",
    "wof:name":"Inmobiliaria Carrero Mu\u00d1oz S.l.",
    "wof:placetype":"venue"
},
  "geometry": {"coordinates":[-3.6802339554,40.1931686401],"type":"Point"}
}