{
  "type": "Feature",
  "properties": {
    "iso:country":"ES",
    "sg:address":"Carrer de Sant Segimon, 22",
    "sg:city":"Vic",
    "sg:orig_category":"Reposter\u00cdas",
    "sg:phone":"+34 938 86 22 29",
    "sg:postcode":"08500",
    "sg:province":"Barcelona",
    "wof:name":"Noguer Oms Albert",
    "wof:placetype":"venue"
},
  "geometry": {"coordinates":[2.261425972,41.9300537109],"type":"Point"}
}