{
  "type": "Feature",
  "properties": {
    "addr:full":"Plaz Moraleja (de La), 6 Alcobendas Madrid 28109",
    "addr:postcode":"28109",
    "iso:country":"ES",
    "sg:address":"Plaz Moraleja (de La), 6",
    "sg:city":"Alcobendas",
    "sg:orig_category":"Laboratorios Y Cl\u00cdnicas Veterinarias",
    "sg:phone":"+34 916 50 02 69",
    "sg:postcode":"28109",
    "sg:province":"Madrid",
    "wof:name":"Basagoiti Satrustegui Maria Bego\u00f1a",
    "wof:placetype":"venue"
},
  "geometry": {"coordinates":[-3.6214940548,40.5304832458],"type":"Point"}
}