{
  "type": "Feature",
  "properties": {
    "addr:full":"Rua Montero Rios, 18 Vigo Pontevedra 36201",
    "addr:housenumber":"18",
    "addr:postcode":"36201",
    "addr:street":"Rua Montero Rios",
    "iso:country":"ES",
    "sg:address":"Rua Montero Rios, 18",
    "sg:city":"Vigo",
    "sg:orig_category":"\u00d3ptica: Instrumentos (fabricaci\u00d3n)",
    "sg:phone":"+34 986 22 18 20",
    "sg:postcode":"36201",
    "sg:province":"Pontevedra",
    "wof:name":"Fonport S.l.",
    "wof:placetype":"venue"
},
  "geometry": {"coordinates":[-8.7225503922,42.2403259277],"type":"Point"}
}