{
  "type": "Feature",
  "properties": {
    "addr:full":"Bidebarrieta Kalea, 10 Eibar Guip\u00f9zcoa 20600",
    "addr:housenumber":"10",
    "addr:postcode":"20600",
    "addr:street":"Bidebarrieta Kalea;Guipu\u0300Zcoa",
    "iso:country":"ES",
    "sg:address":"Bidebarrieta Kalea, 10",
    "sg:city":"Eibar",
    "sg:orig_category":"Molduras, Junquillos, Listones Y Molduras Perforadas",
    "sg:phone":"+34 943 20 02 25",
    "sg:postcode":"20600",
    "sg:province":"Guip\u00f9zcoa",
    "wof:name":"Zabaleta C.b.",
    "wof:placetype":"venue"
},
  "geometry": {"coordinates":[-2.4696435928,43.1851959229],"type":"Point"}
}