{
  "type": "Feature",
  "properties": {
    "iso:country":"ES",
    "sg:address":"Calle de Sdo Isern Comas, 12",
    "sg:city":"Palma",
    "sg:orig_category":"Reposter\u00cdas",
    "sg:phone":"+34 971 75 62 16",
    "sg:postcode":"07010",
    "sg:province":"Islas Baleares",
    "wof:name":"Carbonell Ferriol Bartolome",
    "wof:placetype":"venue"
},
  "geometry": {"coordinates":[2.6215190887,39.6229019165],"type":"Point"}
}