{
  "type": "Feature",
  "properties": {
    "iso:country":"ES",
    "sg:address":"Avda Valdelaparra (de), 54",
    "sg:city":"Alcobendas",
    "sg:orig_category":"Importaci\u00d3n",
    "sg:phone":"+34 916 62 56 15",
    "sg:postcode":"28108",
    "sg:province":"Madrid",
    "wof:name":"Bausch & Lomb S.a.",
    "wof:placetype":"venue"
},
  "geometry": {"coordinates":[-3.6225941181,40.5358009338],"type":"Point"}
}