{
  "type": "Feature",
  "properties": {
    "addr:full":"Ctra. Nal. Iii, 13 Requena Valencia 46340",
    "addr:housenumber":"13",
    "addr:postcode":"46340",
    "addr:street":"Ctra. Nal. Iii",
    "iso:country":"ES",
    "sg:address":"Ctra. Nal. Iii, 13",
    "sg:city":"Requena",
    "sg:orig_category":"Empresas De Carpinter\u00cda Met\u00c1lica",
    "sg:phone":"+34 962 30 48 01",
    "sg:postcode":"46340",
    "sg:province":"Valencia",
    "wof:name":"Hermar Metal S.l.",
    "wof:placetype":"venue"
},
  "geometry": {"coordinates":[-1.0998990536,39.4906158447],"type":"Point"}
}