{
  "type": "Feature",
  "properties": {
    "iso:country":"ES",
    "sg:address":"Calle de Alcala De Henares, 4",
    "sg:city":"Granada",
    "sg:orig_category":"Cobro De Pr\u00c9stamos",
    "sg:phone":"+34 958 12 01 82",
    "sg:postcode":"18008",
    "sg:province":"Granada",
    "wof:name":"Central De Recaudacion C.b.",
    "wof:placetype":"venue"
},
  "geometry": {"coordinates":[-3.5891478062,37.1643257141],"type":"Point"}
}