{
  "type": "Feature",
  "properties": {
    "iso:country":"ES",
    "sg:address":"Av Madrid, 63",
    "sg:city":"Barcelona",
    "sg:orig_category":"Centros De Coordinaci\u00d3n",
    "sg:phone":"+34 933 30 88 36",
    "sg:postcode":"08028",
    "sg:province":"Barcelona",
    "wof:name":"Castillo Andres Isidra Victoria",
    "wof:placetype":"venue"
},
  "geometry": {"coordinates":[2.1263329983,41.3780021667],"type":"Point"}
}