{
  "type": "Feature",
  "properties": {
    "iso:country":"ES",
    "sg:address":"Calle de Vid (la), 5",
    "sg:city":"Chiclana De La Frontera",
    "sg:classifiers":[
        {
            "category":"Autos & Motor Vehicles",
            "subcategory":"Automobile Sales",
            "type":"Retail Goods"
        }
    ],
    "sg:phone":"+34 956 53 29 50",
    "sg:postcode":"11130",
    "sg:province":"C\u00e1diz",
    "wof:name":"Centro De Estudios Joint Beta S.l.",
    "wof:placetype":"venue"
},
  "geometry": {"coordinates":[-6.1584100723,36.4185447693],"type":"Point"}
}