{
  "type": "Feature",
  "properties": {
    "iso:country":"ES",
    "sg:address":"Calle de Luis Barahona De Soto, 15",
    "sg:city":"Malaga",
    "sg:orig_category":"Electricidad Veh\u00cdculo",
    "sg:phone":"+34 952 17 19 55",
    "sg:postcode":"29004",
    "sg:province":"M\u00e1laga",
    "wof:name":"Vidal Romero Enrique",
    "wof:placetype":"venue"
},
  "geometry": {"coordinates":[-4.4457211494,36.6919593811],"type":"Point"}
}