{
  "type": "Feature",
  "properties": {
    "addr:full":"Avda Campon El, 44 Salinas Asturias 33405",
    "addr:housenumber":"44",
    "addr:postcode":"33405",
    "addr:street":"Avda Campon El",
    "iso:country":"ES",
    "sg:address":"Avda Campon El, 44",
    "sg:city":"Salinas",
    "sg:orig_category":"Empresas De Hormig\u00d3n, Hormig\u00d3n Armado Y Pretensado",
    "sg:phone":"+34 985 50 01 42",
    "sg:postcode":"33405",
    "sg:province":"Asturias",
    "wof:name":"Luis Gonzalez Suarez Y Miguel Emilio Diaz Martinez Cdad",
    "wof:placetype":"venue"
},
  "geometry": {"coordinates":[-5.9546561241,43.572013855],"type":"Point"}
}