{
  "type": "Feature",
  "properties": {
    "iso:country":"ES",
    "sg:address":"Carrer de Comte Borrell, 34",
    "sg:city":"Terrassa",
    "sg:orig_category":"Asociaciones, Organismos Culturales Y Socioeducativos",
    "sg:phone":"+34 937 80 63 24",
    "sg:postcode":"08224",
    "sg:province":"Barcelona",
    "wof:name":"Irmandade Galega O Noso Lar",
    "wof:placetype":"venue"
},
  "geometry": {"coordinates":[2.0061409473,41.5584907532],"type":"Point"}
}