{
  "type": "Feature",
  "properties": {
    "iso:country":"ES",
    "sg:address":"Carrer de Pareto, 11",
    "sg:city":"Hospitalet Llobregat",
    "sg:orig_category":"Arreglo, Reparaci\u00d3n, Piezas Sueltas De Televisi\u00d3n, V\u00cddeo, Hi",
    "sg:phone":"+34 933 31 55 41",
    "sg:postcode":"08902",
    "sg:province":"Barcelona",
    "wof:name":"Luque Lopez Alfonso",
    "wof:placetype":"venue"
},
  "geometry": {"coordinates":[2.1272220612,41.3666496277],"type":"Point"}
}