{
  "type": "Feature",
  "properties": {
    "addr:full":"Ampla, 20 Rupia Girona 17131",
    "addr:housenumber":"20",
    "addr:postcode":"17131",
    "addr:street":"Ampla",
    "iso:country":"ES",
    "sg:address":"Ampla, 20",
    "sg:city":"Rupia",
    "sg:orig_category":"Empresas De Desmonte",
    "sg:phone":"+34 972 76 92 77",
    "sg:postcode":"17131",
    "sg:province":"Girona",
    "wof:name":"Vidal Ventura Jose",
    "wof:placetype":"venue"
},
  "geometry": {"coordinates":[3.01039505,42.0203590393],"type":"Point"}
}