{
  "type": "Feature",
  "properties": {
    "iso:country":"ES",
    "sg:address":"Junqueras, 36",
    "sg:city":"Xunqueiras",
    "sg:orig_category":"Estudios Y Construcci\u00d3n De Acuarios Y Viveros",
    "sg:phone":"+34 981 83 10 24",
    "sg:postcode":"15940",
    "sg:province":"La Coru\u00f1a",
    "wof:name":"Martinez Lojo Jose",
    "wof:placetype":"venue"
},
  "geometry": {"coordinates":[-8.9388437271,42.6042404175],"type":"Point"}
}