{
  "type": "Feature",
  "properties": {
    "iso:country":"ES",
    "sg:address":"Calle de Polvoranca (de), 8",
    "sg:city":"Fuenlabrada",
    "sg:orig_category":"Quincaller\u00cda (al Por Menor)",
    "sg:phone":"+34 916 06 94 40",
    "sg:postcode":"28945",
    "sg:province":"Madrid",
    "wof:name":"Reina Marin Jose Antronio",
    "wof:placetype":"venue"
},
  "geometry": {"coordinates":[-3.7938408852,40.2871742249],"type":"Point"}
}