{
  "type": "Feature",
  "properties": {
    "addr:full":"Avda Campo, 18 Humera-somosaguas-prado Del Rey Madrid 28223",
    "addr:postcode":"28223",
    "addr:street":"Avda Campo 18 Humera-Somosaguas-Prado Del",
    "iso:country":"ES",
    "sg:address":"Avda Campo, 18",
    "sg:city":"Humera-somosaguas-prado Del Rey",
    "sg:orig_category":"Cristaler\u00cdas",
    "sg:phone":"+34 913 51 71 65",
    "sg:postcode":"28223",
    "sg:province":"Madrid",
    "wof:name":"Carpentier Drique Benoit",
    "wof:placetype":"venue"
},
  "geometry": {"coordinates":[-3.7881131172,40.4220275879],"type":"Point"}
}