{
  "type": "Feature",
  "properties": {
    "addr:full":"Cmno Casicas, 4 Puerto Lumbreras Murcia 30890",
    "addr:housenumber":"4",
    "addr:postcode":"30890",
    "addr:street":"Cmno Casicas",
    "iso:country":"ES",
    "sg:address":"Cmno Casicas, 4",
    "sg:city":"Puerto Lumbreras",
    "sg:orig_category":"Contenedores (mercanc\u00cdas)",
    "sg:phone":"+34 968 49 66 04",
    "sg:postcode":"30890",
    "sg:province":"Murcia",
    "wof:name":"Cecilia Millan Gines",
    "wof:placetype":"venue"
},
  "geometry": {"coordinates":[-1.8125690222,37.5551490784],"type":"Point"}
}