{
  "type": "Feature",
  "properties": {
    "iso:country":"ES",
    "sg:address":"Avda Vilari\u00d1o, 4",
    "sg:city":"Cambados",
    "sg:classifiers":[
        {
            "category":"Autos & Motor Vehicles",
            "subcategory":"Automobile Sales",
            "type":"Retail Goods"
        }
    ],
    "sg:phone":"+34 986 54 22 87",
    "sg:postcode":"36630",
    "sg:province":"Pontevedra",
    "wof:name":"Autogrand Prixescuela S.l.",
    "wof:placetype":"venue"
},
  "geometry": {"coordinates":[-8.8141584396,42.5156059265],"type":"Point"}
}