{
  "type": "Feature",
  "properties": {
    "addr:full":"J.m. Ostolaza Kalea, 5 Deba Guip\u00f9zcoa 20820",
    "addr:housenumber":"5",
    "addr:postcode":"20820",
    "addr:street":"J.M. Ostolaza Kalea;Guipu\u0300Zcoa",
    "iso:country":"ES",
    "sg:address":"J.m. Ostolaza Kalea, 5",
    "sg:city":"Deba",
    "sg:orig_category":"Librer\u00cdas",
    "sg:phone":"+34 943 19 20 57",
    "sg:postcode":"20820",
    "sg:province":"Guip\u00f9zcoa",
    "wof:name":"Mugica Galarraga Maria Luisa",
    "wof:placetype":"venue"
},
  "geometry": {"coordinates":[-2.3545210361,43.2941589355],"type":"Point"}
}