{
  "type": "Feature",
  "properties": {
    "addr:full":"Cm\u00f1o. Toraldo, 39 Naron La Coru\u00f1a 15572",
    "addr:housenumber":"39",
    "addr:postcode":"15572",
    "addr:street":"Toraldo;La Corun\u0303A",
    "iso:country":"ES",
    "sg:address":"Cm\u00f1o. Toraldo, 39",
    "sg:city":"Naron",
    "sg:orig_category":"Laminadoras",
    "sg:phone":"+34 981 38 22 18",
    "sg:postcode":"15572",
    "sg:province":"La Coru\u00f1a",
    "wof:name":"M Pita Pena S.a.",
    "wof:placetype":"venue"
},
  "geometry": {"coordinates":[-8.1868391037,43.5232048035],"type":"Point"}
}