{
  "type": "Feature",
  "properties": {
    "addr:full":"Avda San Juan De Puerto Rico, S/n Rota C\u00e1diz 11520",
    "addr:housenumber":"s / n",
    "addr:postcode":"11520",
    "addr:street":"Avda San Juan De Puerto Rico;Ca\u0301Diz",
    "iso:country":"ES",
    "sg:address":"Avda San Juan De Puerto Rico, S/n",
    "sg:city":"Rota",
    "sg:orig_category":"Caf\u00c9s, Bares, Cervecer\u00cdas",
    "sg:phone":"+34 956 84 02 96",
    "sg:postcode":"11520",
    "sg:province":"C\u00e1diz",
    "wof:name":"Sur Copas S.c.",
    "wof:placetype":"venue"
},
  "geometry": {"coordinates":[-6.3569011688,36.6163825989],"type":"Point"}
}