{
  "type": "Feature",
  "properties": {
    "addr:full":"Calle de San Francisco, 33 Bilbao Vizcaya 48003",
    "addr:housenumber":"33",
    "addr:postcode":"48003",
    "addr:street":"Calle De San Francisco",
    "iso:country":"ES",
    "sg:address":"Calle de San Francisco, 33",
    "sg:city":"Bilbao",
    "sg:orig_category":"Molduras, Junquillos, Listones Y Molduras Perforadas",
    "sg:phone":"+34 944 15 69 71",
    "sg:postcode":"48003",
    "sg:province":"Vizcaya",
    "wof:name":"Arias Blanco Esther",
    "wof:placetype":"venue"
},
  "geometry": {"coordinates":[-2.928109169,43.2557525635],"type":"Point"}
}