{
  "type": "Feature",
  "properties": {
    "iso:country":"ES",
    "sg:address":"Calle de San Lucas, 11",
    "sg:city":"Madrid",
    "sg:orig_category":"Contables",
    "sg:phone":"+34 913 19 54 11",
    "sg:postcode":"28004",
    "sg:province":"Madrid",
    "wof:name":"Hernandez Ojeda Jose Manuel",
    "wof:placetype":"venue"
},
  "geometry": {"coordinates":[-3.6961669922,40.4238471985],"type":"Point"}
}