{
  "type": "Feature",
  "properties": {
    "iso:country":"ES",
    "sg:address":"Calle de San Pascual, 19",
    "sg:city":"Orihuela",
    "sg:orig_category":"M\u00c9dicos: Estomatolog\u00cda",
    "sg:phone":"+34 966 73 90 44",
    "sg:postcode":"03300",
    "sg:province":"Alicante",
    "wof:name":"Moreno Sanchez Juan Pedro",
    "wof:placetype":"venue"
},
  "geometry": {"coordinates":[-0.9462220073,38.0844154358],"type":"Point"}
}