{
  "type": "Feature",
  "properties": {
    "iso:country":"ES",
    "sg:address":"Calle de Simon Ruiz, 6",
    "sg:city":"Medina Campo",
    "sg:orig_category":"Ropa Para Se\u00d1oras (al Por Menor)",
    "sg:phone":"+34 983 80 34 72",
    "sg:postcode":"47400",
    "sg:province":"Valladolid",
    "wof:name":"Streno S.l.",
    "wof:placetype":"venue"
},
  "geometry": {"coordinates":[-4.9142913818,41.3076286316],"type":"Point"}
}