{
  "type": "Feature",
  "properties": {
    "iso:country":"ES",
    "sg:address":"Ctra Barcelona, 239",
    "sg:city":"Barbera Valles",
    "sg:orig_category":"Promotores Constructores",
    "sg:phone":"+34 937 47 94 90",
    "sg:postcode":"08210",
    "sg:province":"Barcelona",
    "wof:name":"Obrascon Huarte Lain S.a.",
    "wof:placetype":"venue"
},
  "geometry": {"coordinates":[2.1251831055,41.5186843872],"type":"Point"}
}