{
  "type": "Feature",
  "properties": {
    "iso:country":"ES",
    "sg:address":"Avda Gabriel Miro, 2",
    "sg:city":"Calpe",
    "sg:orig_category":"Institutos De Belleza",
    "sg:phone":"+34 965 83 11 43",
    "sg:postcode":"03710",
    "sg:province":"Alicante",
    "wof:name":"Perez Garcia Josefa",
    "wof:placetype":"venue"
},
  "geometry": {"coordinates":[0.0464439988,38.6440544128],"type":"Point"}
}