{
  "type": "Feature",
  "properties": {
    "iso:country":"ES",
    "sg:address":"Praz Maruja Mallo, 1",
    "sg:city":"Vigo",
    "sg:orig_category":"Urbanistas",
    "sg:phone":"+34 986 26 64 77",
    "sg:postcode":"36205",
    "sg:province":"Pontevedra",
    "wof:name":"Xestion Urbanistica De Pontevedra S.a.",
    "wof:placetype":"venue"
},
  "geometry": {"coordinates":[-8.7055854797,42.2321662903],"type":"Point"}
}