{
  "type": "Feature",
  "properties": {
    "iso:country":"ES",
    "sg:address":"Ctra Cala Fornells, 64",
    "sg:city":"Peguera",
    "sg:orig_category":"Importaci\u00d3n",
    "sg:phone":"+34 971 68 70 55",
    "sg:postcode":"07160",
    "sg:province":"Islas Baleares",
    "wof:name":"Drewes  Klaus",
    "wof:placetype":"venue"
},
  "geometry": {"coordinates":[2.4384939671,39.5358009338],"type":"Point"}
}