{
  "type": "Feature",
  "properties": {
    "iso:country":"ES",
    "sg:address":"Carrer de Joan Gamper, 33",
    "sg:city":"Barcelona",
    "sg:orig_category":"Fotograf\u00cda Art\u00cdstica Y Retratos",
    "sg:phone":"+34 934 10 84 44",
    "sg:postcode":"08014",
    "sg:province":"Barcelona",
    "wof:name":"Bosch Bea Neus",
    "wof:placetype":"venue"
},
  "geometry": {"coordinates":[2.1329131126,41.3880500793],"type":"Point"}
}