{
  "type": "Feature",
  "properties": {
    "addr:full":"Avda Miguel De Unamuno (de), 14 Cordoba C\u00f3rdoba 14010",
    "addr:housenumber":"14",
    "addr:postcode":"14010",
    "addr:street":"Avda Miguel De Unamuno De;Co\u0301Rdoba",
    "iso:country":"ES",
    "sg:address":"Avda Miguel De Unamuno (de), 14",
    "sg:city":"Cordoba",
    "sg:orig_category":"Alimentaci\u00d3n General (al Por Menor)",
    "sg:phone":"+34 957 43 59 18",
    "sg:postcode":"14010",
    "sg:province":"C\u00f3rdoba",
    "wof:name":"Francisco Morales E Hijos S.l.",
    "wof:placetype":"venue"
},
  "geometry": {"coordinates":[-4.7640089989,37.8850708008],"type":"Point"}
}