{
  "type": "Feature",
  "properties": {
    "iso:country":"ES",
    "sg:address":"Disseminat, S/n",
    "sg:city":"Saderra",
    "sg:orig_category":"Agricultores, Agricultores",
    "sg:phone":"+34 938 50 51 40",
    "sg:postcode":"08573",
    "sg:province":"Barcelona",
    "wof:name":"Vall Tartera S.l.",
    "wof:placetype":"venue"
},
  "geometry": {"coordinates":[2.2405800819,42.0612106323],"type":"Point"}
}