{
  "type": "Feature",
  "properties": {
    "iso:country":"ES",
    "sg:address":"A Chan, S/n",
    "sg:city":"Chan",
    "sg:orig_category":"Centros De Educaci\u00d3n Especial",
    "sg:phone":"+34 986 53 80 01",
    "sg:postcode":"36669",
    "sg:province":"Pontevedra",
    "wof:name":"Concello De Mora\u00d1a",
    "wof:placetype":"venue"
},
  "geometry": {"coordinates":[-8.4826135635,42.4715156555],"type":"Point"}
}