{
  "type": "Feature",
  "properties": {
    "addr:full":"Carrer de Travessera, 8 Cornella Llobregat Barcelona 08940",
    "addr:housenumber":"8",
    "addr:postcode":"08940",
    "addr:street":"Carrer De Travessera",
    "iso:country":"ES",
    "sg:address":"Carrer de Travessera, 8",
    "sg:city":"Cornella Llobregat",
    "sg:orig_category":"Tintorer\u00cdas, Limpieza En Seco",
    "sg:phone":"+34 934 71 07 38",
    "sg:postcode":"08940",
    "sg:province":"Barcelona",
    "wof:name":"Ribes Hernandez Jose",
    "wof:placetype":"venue"
},
  "geometry": {"coordinates":[2.0774140358,41.3646774292],"type":"Point"}
}