{
  "type": "Feature",
  "properties": {
    "addr:full":"Calle de Nueva, 32 Villarrobledo Albacete 02600",
    "addr:housenumber":"32",
    "addr:postcode":"02600",
    "addr:street":"Calle De Nueva",
    "iso:country":"ES",
    "sg:address":"Calle de Nueva, 32",
    "sg:city":"Villarrobledo",
    "sg:orig_category":"Empresas De Carpinter\u00cda Met\u00c1lica",
    "sg:phone":"+34 967 14 21 13",
    "sg:postcode":"02600",
    "sg:province":"Albacete",
    "wof:name":"Talleres Camacho Y Villarrobledo S.l.",
    "wof:placetype":"venue"
},
  "geometry": {"coordinates":[-2.6081790924,39.2609405518],"type":"Point"}
}