{
  "type": "Feature",
  "properties": {
    "iso:country":"ES",
    "sg:address":"Carr Del Violinista Matas, 5",
    "sg:city":"Ontinyent",
    "sg:orig_category":"Aguas (distribuci\u00d3n, Servicios)",
    "sg:phone":"+34 962 91 33 85",
    "sg:postcode":"46870",
    "sg:province":"Valencia",
    "wof:name":"Comunidad De Regantes Riego Mayor De Onteniente",
    "wof:placetype":"venue"
},
  "geometry": {"coordinates":[-0.6032490134,38.8189468384],"type":"Point"}
}