{
  "type": "Feature",
  "properties": {
    "iso:country":"ES",
    "sg:address":"Calle de Monico Sanchez, 2",
    "sg:city":"Piedrabuena",
    "sg:orig_category":"Producci\u00d3n, Distribuci\u00d3n De Gas Butano Y Propano",
    "sg:phone":"+34 926 76 02 76",
    "sg:postcode":"13100",
    "sg:province":"Ciudad Real",
    "wof:name":"Rodriguez Martin Purificacion",
    "wof:placetype":"venue"
},
  "geometry": {"coordinates":[-4.1757121086,39.0351638794],"type":"Point"}
}