{
  "type": "Feature",
  "properties": {
    "iso:country":"ES",
    "sg:address":"Rua Magdalena, 151",
    "sg:city":"Ferrol",
    "sg:orig_category":"Arquitectos",
    "sg:phone":"+34 981 35 99 17",
    "sg:postcode":"15402",
    "sg:province":"La Coru\u00f1a",
    "wof:name":"Habitat Arquitectura Y Rehabilitacion S.l.",
    "wof:placetype":"venue"
},
  "geometry": {"coordinates":[-8.2351961136,43.4824485779],"type":"Point"}
}