{
  "type": "Feature",
  "properties": {
    "addr:full":"Carr Doctor Ferran, 4 Figueres Girona 17600",
    "addr:housenumber":"4",
    "addr:postcode":"17600",
    "addr:street":"Carr Doctor Ferran",
    "iso:country":"ES",
    "sg:address":"Carr Doctor Ferran, 4",
    "sg:city":"Figueres",
    "sg:orig_category":"Librer\u00cdas",
    "sg:phone":"+34 972 51 08 14",
    "sg:postcode":"17600",
    "sg:province":"Girona",
    "wof:name":"Bach-esteve Gich Jaime",
    "wof:placetype":"venue"
},
  "geometry": {"coordinates":[2.9514639378,42.2654190063],"type":"Point"}
}