{
  "type": "Feature",
  "properties": {
    "iso:country":"ES",
    "sg:address":"Calle de Alemany, 2",
    "sg:city":"Valencia",
    "sg:orig_category":"Abrasivos Y Superabrasivos (fabricaci\u00d3n, Al Por Mayor)",
    "sg:phone":"+34 963 65 81 16",
    "sg:postcode":"46019",
    "sg:province":"Valencia",
    "wof:name":"Abrasivos Reunidos S. A.",
    "wof:placetype":"venue"
},
  "geometry": {"coordinates":[-0.375378,39.497883],"type":"Point"}
}