{
  "type": "Feature",
  "properties": {
    "addr:full":"Rond General Mitre, 5 Barcelona Barcelona 08017",
    "addr:housenumber":"5",
    "addr:postcode":"08017",
    "addr:street":"Mitre",
    "iso:country":"ES",
    "sg:address":"Rond General Mitre, 5",
    "sg:city":"Barcelona",
    "sg:orig_category":"Empresarios",
    "sg:phone":"+34 932 03 47 23",
    "sg:postcode":"08017",
    "sg:province":"Barcelona",
    "wof:name":"Tecnica I Humanisme Fundacio Privada",
    "wof:placetype":"venue"
},
  "geometry": {"coordinates":[2.1305189133,41.3929977417],"type":"Point"}
}