{
  "type": "Feature",
  "properties": {
    "addr:full":"La Ca\u00f1ada-ctro Comercial, S/n Marbella M\u00e1laga 29600",
    "addr:housenumber":"s / n",
    "addr:postcode":"29600",
    "addr:street":"Ma\u0301Laga",
    "iso:country":"ES",
    "sg:address":"La Ca\u00f1ada-ctro Comercial, S/n",
    "sg:city":"Marbella",
    "sg:orig_category":"Ropa Para Se\u00d1oras (al Por Menor)",
    "sg:phone":"+34 952 77 77 06",
    "sg:postcode":"29600",
    "sg:province":"M\u00e1laga",
    "sg:website":"www.mango.com",
    "wof:name":"Punto Fa S.l.",
    "wof:placetype":"venue"
},
  "geometry": {"coordinates":[-4.8833007812,36.5079956055],"type":"Point"}
}