{
  "type": "Feature",
  "properties": {
    "iso:country":"ES",
    "sg:address":"Calle de Hermano Julian, 3",
    "sg:city":"Terrero",
    "sg:orig_category":"Agencias Y Agentes Comerciales, Representantes",
    "sg:phone":"+34 928 60 59 34",
    "sg:postcode":"35400",
    "sg:province":"Las Palmas",
    "wof:name":"Cormercial Acosta Ribero S.l.",
    "wof:placetype":"venue"
},
  "geometry": {"coordinates":[-15.5152540207,28.1135654449],"type":"Point"}
}