{
  "type": "Feature",
  "properties": {
    "iso:country":"ES",
    "sg:address":"Avda Cardenal Benlloch, 16",
    "sg:city":"Valencia",
    "sg:orig_category":"Administradores De Bienes Y Delegados De Comunidades De Propietarios",
    "sg:phone":"+34 963 89 13 42",
    "sg:postcode":"46021",
    "sg:province":"Valencia",
    "wof:name":"Administracion De Fincas Vazquez Leva S.l.",
    "wof:placetype":"venue"
},
  "geometry": {"coordinates":[-0.3561108112,39.4677009583],"type":"Point"}
}