{
  "type": "Feature",
  "properties": {
    "iso:country":"ES",
    "sg:address":"Calle de Alonso De Oropesa, 23",
    "sg:city":"Oropesa",
    "sg:orig_category":"Estudios, Instalaci\u00d3n De Climatizaci\u00d3n",
    "sg:phone":"+34 925 43 13 37",
    "sg:postcode":"45560",
    "sg:province":"Toledo",
    "wof:name":"Instalaciones Hernandez C.b",
    "wof:placetype":"venue"
},
  "geometry": {"coordinates":[-5.1764779091,39.917804718],"type":"Point"}
}