{
  "type": "Feature",
  "properties": {
    "iso:country":"ES",
    "sg:address":"C/ 29, 23",
    "sg:city":"Ca\u00d1ada",
    "sg:orig_category":"Piscinas, Accesorios, Suministros (fabricaci\u00d3n, Al Por Mayor)",
    "sg:phone":"+34 961 32 03 32",
    "sg:postcode":"46182",
    "sg:province":"Valencia",
    "wof:name":"Piscilimp S.l.",
    "wof:placetype":"venue"
},
  "geometry": {"coordinates":[-0.4852339923,39.5221443176],"type":"Point"}
}