{
  "type": "Feature",
  "properties": {
    "addr:full":"Plaz Buen Pastor Del, 3 Donostia-san Sebastian Guip\u00f9zcoa 20005",
    "addr:housenumber":"3",
    "addr:postcode":"20005",
    "addr:street":"Plaz Buen Pastor Del",
    "iso:country":"ES",
    "sg:address":"Plaz Buen Pastor Del, 3",
    "sg:city":"Donostia-san Sebastian",
    "sg:orig_category":"Papeler\u00cdas, Librer\u00cdas",
    "sg:phone":"+34 943 42 72 03",
    "sg:postcode":"20005",
    "sg:province":"Guip\u00f9zcoa",
    "wof:name":"Martinez Martinez Miren Edurne",
    "wof:placetype":"venue"
},
  "geometry": {"coordinates":[-1.9813239574,43.3172645569],"type":"Point"}
}