{
  "type": "Feature",
  "properties": {
    "addr:full":"Carrer de Antoni Roig (d'), 42 Torredembarra Tarragona 43830",
    "addr:housenumber":"42",
    "addr:postcode":"43830",
    "addr:street":"Carrer De Antoni Roig D '",
    "iso:country":"ES",
    "sg:address":"Carrer de Antoni Roig (d'), 42",
    "sg:city":"Torredembarra",
    "sg:orig_category":"Librer\u00cdas",
    "sg:phone":"+34 977 64 01 33",
    "sg:postcode":"43830",
    "sg:province":"Tarragona",
    "wof:name":"Sonsona Vidal Maria Teresa",
    "wof:placetype":"venue"
},
  "geometry": {"coordinates":[1.3992040157,41.1444473267],"type":"Point"}
}