{
  "type": "Feature",
  "properties": {
    "iso:country":"ES",
    "sg:address":"Calle de Pilar De Las Almas, 17",
    "sg:city":"Teruel",
    "sg:orig_category":"Ferreter\u00cda (diversos)",
    "sg:phone":"+34 978 60 32 07",
    "sg:postcode":"44003",
    "sg:province":"Teruel",
    "wof:name":"Ballestero Juberias Jose",
    "wof:placetype":"venue"
},
  "geometry": {"coordinates":[-1.1027179956,40.3440666199],"type":"Point"}
}