{
  "type": "Feature",
  "properties": {
    "iso:country":"ES",
    "sg:address":"Avda Andalucia, Km. 0010,5",
    "sg:city":"Madrid",
    "sg:orig_category":"Fabricaci\u00d3n De Cervezas",
    "sg:phone":"+34 917 23 34 60",
    "sg:postcode":"28021",
    "sg:province":"Madrid",
    "sg:website":"www.sumcar.com",
    "wof:name":"Distribaria Cervezas S.a.",
    "wof:placetype":"venue"
},
  "geometry": {"coordinates":[-3.6932559013,40.3471412659],"type":"Point"}
}