{
  "type": "Feature",
  "properties": {
    "iso:country":"ES",
    "sg:address":"S Pol Noain-esquiroz, S/n",
    "sg:city":"Esquiroz",
    "sg:orig_category":"Empresas De Carpinter\u00cda De Madera",
    "sg:phone":"+34 948 31 15 20",
    "sg:postcode":"31191",
    "sg:province":"Navarra",
    "wof:name":"Alfaro Garcia Eloy",
    "wof:placetype":"venue"
},
  "geometry": {"coordinates":[-1.6557643414,42.7748374939],"type":"Point"}
}