{
  "type": "Feature",
  "properties": {
    "iso:country":"ES",
    "sg:address":"Carr Major, 5",
    "sg:city":"Santa Coloma De Farners",
    "sg:orig_category":"Carnicer\u00cdas, Carnicer\u00cdas",
    "sg:phone":"+34 972 84 06 92",
    "sg:postcode":"17430",
    "sg:province":"Girona",
    "wof:name":"Coll Sureda Juan",
    "wof:placetype":"venue"
},
  "geometry": {"coordinates":[2.6619400978,41.8633766174],"type":"Point"}
}