{
  "type": "Feature",
  "properties": {
    "addr:full":"Calle de Hipolito Frias, 12 Arrecife Las Palmas 35500",
    "addr:housenumber":"12",
    "addr:postcode":"35500",
    "addr:street":"Calle De Hipolito Frias",
    "iso:country":"ES",
    "sg:address":"Calle de Hipolito Frias, 12",
    "sg:city":"Arrecife",
    "sg:orig_category":"Agentes, Concesionarios Y Sucursales De Veh\u00cdculos",
    "sg:phone":"+34 928 80 00 69",
    "sg:postcode":"35500",
    "sg:province":"Las Palmas",
    "wof:name":"Centro Auto Canarias 2 S.l.",
    "wof:placetype":"venue"
},
  "geometry": {"coordinates":[-13.542596817,28.965877533],"type":"Point"}
}