{
  "type": "Feature",
  "properties": {
    "iso:country":"ES",
    "sg:address":"Avda Zaragoza, 13",
    "sg:city":"Utebo",
    "sg:classifiers":[
        {
            "category":"Personal",
            "subcategory":"Barber",
            "type":"Services"
        }
    ],
    "sg:phone":"+34 976 77 00 14",
    "sg:postcode":"50180",
    "sg:province":"Zaragoza",
    "sg:tags":[
        "caballeros",
        "de",
        "peluqueros"
    ],
    "wof:name":"Orcajo Soler Alfonso Jose",
    "wof:placetype":"venue"
},
  "geometry": {"coordinates":[-1.0001100302,41.7031059265],"type":"Point"}
}