{
  "type": "Feature",
  "properties": {
    "iso:country":"ES",
    "sg:address":"Calle de Fernando Guanarteme, 62",
    "sg:city":"Palmas De Gran Canaria",
    "sg:orig_category":"Comercio De Piezas De Recambio Y De Accesorios De Veh\u00cdculos, Veh\u00cdculos Industriales",
    "sg:phone":"+34 928 22 99 05",
    "sg:postcode":"35010",
    "sg:province":"Las Palmas",
    "wof:name":"Guerra Rodriguez Jose Miguel",
    "wof:placetype":"venue"
},
  "geometry": {"coordinates":[-15.4384298325,28.1344127655],"type":"Point"}
}