{
  "type": "Feature",
  "properties": {
    "addr:full":"Calle de Castilla, 5 Huesca Huesca 22002",
    "addr:housenumber":"5",
    "addr:postcode":"22002",
    "addr:street":"Calle De Castilla",
    "iso:country":"ES",
    "sg:address":"Calle de Castilla, 5",
    "sg:city":"Huesca",
    "sg:orig_category":"Administradores De Bienes Y Delegados De Comunidades De Propietarios",
    "sg:phone":"+34 974 22 30 04",
    "sg:postcode":"22002",
    "sg:province":"Huesca",
    "wof:name":"G & M Fincas S.cv.",
    "wof:placetype":"venue"
},
  "geometry": {"coordinates":[-0.4085854888,42.1390647888],"type":"Point"}
}