{
  "type": "Feature",
  "properties": {
    "addr:full":"Carr Sequia De Quart, S/n Picanya Valencia 46210",
    "addr:postcode":"46210",
    "addr:street":"Carr Sequia De Quart S / N",
    "iso:country":"ES",
    "sg:address":"Carr Sequia De Quart, S/n",
    "sg:city":"Picanya",
    "sg:orig_category":"Artes Gr\u00c1ficas, Artes Pl\u00c1sticas (curso)",
    "sg:phone":"+34 961 59 00 54",
    "sg:postcode":"46210",
    "sg:province":"Valencia",
    "wof:name":"Papel Para Impresoras S.a.",
    "wof:placetype":"venue"
},
  "geometry": {"coordinates":[-0.4231440127,39.4361686707],"type":"Point"}
}