{
  "type": "Feature",
  "properties": {
    "addr:full":"Ctr. Saelices, S/n Villamayor Santiago Cuenca 16415",
    "addr:housenumber":"s",
    "addr:postcode":"16415",
    "addr:street":"/ N Villamayor;Cuenca",
    "iso:country":"ES",
    "sg:address":"Ctr. Saelices, S/n",
    "sg:city":"Villamayor Santiago",
    "sg:orig_category":"Distribuci\u00d3n De Petr\u00d3leo Y Derivados",
    "sg:phone":"+34 969 13 91 12",
    "sg:postcode":"16415",
    "sg:province":"Cuenca",
    "wof:name":"Estacion De Servicio Valenciano Medina S.l.",
    "wof:placetype":"venue"
},
  "geometry": {"coordinates":[-2.9234220982,39.7301254272],"type":"Point"}
}