{
  "type": "Feature",
  "properties": {
    "addr:full":"Calle de Hermanas Carmelitas, 8 Trigueros Huelva 21620",
    "addr:housenumber":"8",
    "addr:postcode":"21620",
    "addr:street":"Calle De;Carmelitas",
    "iso:country":"ES",
    "sg:address":"Calle de Hermanas Carmelitas, 8",
    "sg:city":"Trigueros",
    "sg:orig_category":"Bisuter\u00cda, Joyer\u00cda, Relojer\u00cda (al Por Menor)",
    "sg:phone":"+34 959 30 66 61",
    "sg:postcode":"21620",
    "sg:province":"Huelva",
    "wof:name":"Garcia Novoa Consolacion",
    "wof:placetype":"venue"
},
  "geometry": {"coordinates":[-6.8324041367,37.3822631836],"type":"Point"}
}