{
  "type": "Feature",
  "properties": {
    "addr:full":"Calle de Vicente Puchol, 6 Castellar-oliveral Valencia 46026",
    "addr:housenumber":"6",
    "addr:postcode":"46026",
    "addr:street":"Calle De Vicente Puchol",
    "iso:country":"ES",
    "sg:address":"Calle de Vicente Puchol, 6",
    "sg:city":"Castellar-oliveral",
    "sg:orig_category":"\u00d3ptica: Instrumentos (fabricaci\u00d3n)",
    "sg:phone":"+34 963 96 11 84",
    "sg:postcode":"46026",
    "sg:province":"Valencia",
    "wof:name":"Marin Morales Elisa",
    "wof:placetype":"venue"
},
  "geometry": {"coordinates":[-0.3638260067,39.4289741516],"type":"Point"}
}