{
  "type": "Feature",
  "properties": {
    "addr:full":"Plaz Teatro, 4 Malaga M\u00e1laga 29008",
    "addr:postcode":"29008",
    "addr:street":"Ma\u0301Laga",
    "iso:country":"ES",
    "sg:address":"Plaz Teatro, 4",
    "sg:city":"Malaga",
    "sg:orig_category":"M\u00c9dicos: Cirug\u00cda General",
    "sg:phone":"+34 952 21 28 75",
    "sg:postcode":"29008",
    "sg:province":"M\u00e1laga",
    "wof:name":"Rivas Marin Jose Francisco",
    "wof:placetype":"venue"
},
  "geometry": {"coordinates":[-4.4208340645,36.7236480713],"type":"Point"}
}