{
  "type": "Feature",
  "properties": {
    "addr:full":"Avda Madrid, S/n Valladolid Valladolid 47008",
    "addr:housenumber":"s / n",
    "addr:postcode":"47008",
    "addr:street":"Avda Madrid",
    "iso:country":"ES",
    "sg:address":"Avda Madrid, S/n",
    "sg:city":"Valladolid",
    "sg:orig_category":"Centros Empresariales",
    "sg:phone":"+34 983 22 82 59",
    "sg:postcode":"47008",
    "sg:province":"Valladolid",
    "wof:name":"Castellana De Servicios Y Consulting S.l.",
    "wof:placetype":"venue"
},
  "geometry": {"coordinates":[-4.7260742188,41.6227035522],"type":"Point"}
}