{
  "type": "Feature",
  "properties": {
    "iso:country":"ES",
    "sg:address":"Carrer de Bernat Vidal I Tomas, 79",
    "sg:city":"Santanyi",
    "sg:orig_category":"Ense\u00d1anza Secundaria: Colegios Y Escuelas Privadas",
    "sg:phone":"+34 971 65 40 98",
    "sg:postcode":"07650",
    "sg:province":"Islas Baleares",
    "wof:name":"Instituto De Educacion Secundaria Santanyi",
    "wof:placetype":"venue"
},
  "geometry": {"coordinates":[3.1341340542,39.3506965637],"type":"Point"}
}