{
  "type": "Feature",
  "properties": {
    "iso:country":"ES",
    "sg:address":"Calle de Juan Llorens, 63",
    "sg:city":"Valencia",
    "sg:orig_category":"Papeler\u00cdas, Librer\u00cdas",
    "sg:phone":"+34 963 85 78 50",
    "sg:postcode":"46008",
    "sg:province":"Valencia",
    "wof:name":"Beneyto Rubio Jesus",
    "wof:placetype":"venue"
},
  "geometry": {"coordinates":[-0.3889099956,39.4703712463],"type":"Point"}
}