{
  "type": "Feature",
  "properties": {
    "iso:country":"ES",
    "sg:address":"Calle de Rubens Marichal Lopez, 34",
    "sg:city":"Santa Cruz De Tenerife",
    "sg:orig_category":"Arquitectos",
    "sg:phone":"+34 922 29 12 48",
    "sg:postcode":"38170",
    "sg:province":"Santa Cruz De Tenerife",
    "wof:name":"Planos De Arquitectura S.l.",
    "wof:placetype":"venue"
},
  "geometry": {"coordinates":[-16.2558689117,28.4795303345],"type":"Point"}
}