{
  "type": "Feature",
  "properties": {
    "addr:full":"Carr Girona, 51 Lleida Lleida 25005",
    "addr:housenumber":"51",
    "addr:postcode":"25005",
    "addr:street":"Carr Girona",
    "iso:country":"ES",
    "sg:address":"Carr Girona, 51",
    "sg:city":"Lleida",
    "sg:orig_category":"Carnicer\u00cdas, Carnicer\u00cdas",
    "sg:phone":"+34 973 22 04 42",
    "sg:postcode":"25005",
    "sg:province":"Lleida",
    "wof:name":"Cansaladeria Delfina Sl",
    "wof:placetype":"venue"
},
  "geometry": {"coordinates":[0.6339370012,41.6247596741],"type":"Point"}
}