{
  "type": "Feature",
  "properties": {
    "addr:full":"Calle de Solarillo De Gracia, 8 Granada Granada 18002",
    "addr:housenumber":"8",
    "addr:postcode":"18002",
    "addr:street":"Calle De Solarillo De Gracia",
    "iso:country":"ES",
    "sg:address":"Calle de Solarillo De Gracia, 8",
    "sg:city":"Granada",
    "sg:orig_category":"Molduras, Junquillos, Listones Y Molduras Perforadas",
    "sg:phone":"+34 958 25 53 04",
    "sg:postcode":"18002",
    "sg:province":"Granada",
    "wof:name":"Santiago Del Rio S.l.",
    "wof:placetype":"venue"
},
  "geometry": {"coordinates":[-3.603468895,37.1726722717],"type":"Point"}
}