{
  "type": "Feature",
  "properties": {
    "iso:country":"ES",
    "sg:address":"Carrer de Industria, 84",
    "sg:city":"Hospitalet Llobregat",
    "sg:orig_category":"Agencias Y Asesores De Publicidad",
    "sg:phone":"+34 932 23 19 89",
    "sg:postcode":"08908",
    "sg:province":"Barcelona",
    "wof:name":"Antalis Promotional Products S.l.",
    "wof:placetype":"venue"
},
  "geometry": {"coordinates":[2.127145052,41.3473320007],"type":"Point"}
}