{
  "type": "Feature",
  "properties": {
    "addr:full":"G.v. Corts Catalanes, 478 Barcelona Barcelona 08015",
    "addr:housenumber":"478",
    "addr:postcode":"08015",
    "addr:street":"Catalanes",
    "iso:country":"ES",
    "sg:address":"G.v. Corts Catalanes, 478",
    "sg:city":"Barcelona",
    "sg:orig_category":"Confecci\u00d3n De Zapatos",
    "sg:phone":"+34 934 23 64 58",
    "sg:postcode":"08015",
    "sg:province":"Barcelona",
    "wof:name":"Calzados Polo S.l.",
    "wof:placetype":"venue"
},
  "geometry": {"coordinates":[2.1560819149,41.3798332214],"type":"Point"}
}