{
  "type": "Feature",
  "properties": {
    "addr:full":"Calle de Torrecilla, 1 Sevilla Sevilla 41016",
    "addr:housenumber":"1",
    "addr:postcode":"41016",
    "addr:street":"Calle De Torrecilla",
    "iso:country":"ES",
    "sg:address":"Calle de Torrecilla, 1",
    "sg:city":"Sevilla",
    "sg:orig_category":"Quincaller\u00cda (al Por Menor)",
    "sg:phone":"+34 954 47 52 78",
    "sg:postcode":"41016",
    "sg:province":"Sevilla",
    "wof:name":"Juana Reche Pi\u00d1a Suministros Industriales S.l.",
    "wof:placetype":"venue"
},
  "geometry": {"coordinates":[-5.9171977043,37.3816986084],"type":"Point"}
}