{
  "type": "Feature",
  "properties": {
    "addr:full":"Calle de Santa Clara, 43 Burgos Burgos 09002",
    "addr:housenumber":"43",
    "addr:postcode":"09002",
    "addr:street":"Calle De Santa Clara",
    "iso:country":"ES",
    "sg:address":"Calle de Santa Clara, 43",
    "sg:city":"Burgos",
    "sg:orig_category":"Fotograf\u00cda Y Cine: Aparatos, Pel\u00cdculas Y Accesorios (al Por Menor)",
    "sg:phone":"+34 947 26 28 75",
    "sg:postcode":"09002",
    "sg:province":"Burgos",
    "wof:name":"Diez Rodrigo Pedro Antonio",
    "wof:placetype":"venue"
},
  "geometry": {"coordinates":[-3.6959700584,42.3378067017],"type":"Point"}
}