{
  "type": "Feature",
  "properties": {
    "iso:country":"ES",
    "sg:address":"Calle de Ibarrekolanda, 36",
    "sg:city":"Bilbao",
    "sg:orig_category":"Mec\u00c1nica Y Herramientas De Precisi\u00d3n",
    "sg:phone":"+34 944 47 31 04",
    "sg:postcode":"48015",
    "sg:province":"Vizcaya",
    "sg:website":"www.leica.com",
    "wof:name":"Leica Geosystems S.l.",
    "wof:placetype":"venue"
},
  "geometry": {"coordinates":[-2.9567470551,43.2748565674],"type":"Point"}
}