{
  "type": "Feature",
  "properties": {
    "iso:country":"ES",
    "sg:address":"Calle de Violeta Parra, 2",
    "sg:city":"Zaragoza",
    "sg:orig_category":"Electricidad: Instaladores",
    "sg:phone":"+34 976 51 40 09",
    "sg:postcode":"50015",
    "sg:province":"Zaragoza",
    "wof:name":"Utrilla Iba\u00f1ez Miguel Angel",
    "wof:placetype":"venue"
},
  "geometry": {"coordinates":[-0.8781690001,41.6692504883],"type":"Point"}
}