{
  "type": "Feature",
  "properties": {
    "addr:full":"Calle de Portillejo, 18 Logro\u00f1o La Rioja 26006",
    "addr:housenumber":"18",
    "addr:postcode":"26006",
    "addr:street":"Calle De Portillejo;Rioja",
    "iso:country":"ES",
    "sg:address":"Calle de Portillejo, 18",
    "sg:city":"Logro\u00f1o",
    "sg:orig_category":"Bancos",
    "sg:phone":"+34 941 51 90 31",
    "sg:postcode":"26006",
    "sg:province":"La Rioja",
    "wof:name":"Caja Rural De Aragon S.coop Credito",
    "wof:placetype":"venue"
},
  "geometry": {"coordinates":[-2.466989994,42.4626045227],"type":"Point"}
}