{
  "type": "Feature",
  "properties": {
    "iso:country":"ES",
    "sg:address":"Av Paral.lel, 103",
    "sg:city":"Barcelona",
    "sg:orig_category":"Empresarios",
    "sg:phone":"+34 934 43 01 61",
    "sg:postcode":"08004",
    "sg:province":"Barcelona",
    "wof:name":"Reformas Paralelo S.l",
    "wof:placetype":"venue"
},
  "geometry": {"coordinates":[2.1629118919,41.3748779297],"type":"Point"}
}