{
  "type": "Feature",
  "properties": {
    "iso:country":"ES",
    "sg:address":"San Cristovo, S/n",
    "sg:city":"Corgo",
    "sg:orig_category":"Supermercados Y Hipermercados",
    "sg:phone":"+34 982 30 20 86",
    "sg:postcode":"27169",
    "sg:province":"Lugo",
    "wof:name":"Hiper Do Corgo S.l.",
    "wof:placetype":"venue"
},
  "geometry": {"coordinates":[-7.4432148933,42.9501113892],"type":"Point"}
}