{
  "type": "Feature",
  "properties": {
    "iso:country":"ES",
    "sg:address":"Calle de Adolfo Diaz Ambrona, 38",
    "sg:city":"Villanueva Serena",
    "sg:orig_category":"Asesor\u00cda Sobre Comunicaci\u00d3n De Empresas",
    "sg:phone":"+34 924 84 62 70",
    "sg:postcode":"06700",
    "sg:province":"Badajoz",
    "wof:name":"Sanchez Rayego Y Molina C.b.",
    "wof:placetype":"venue"
},
  "geometry": {"coordinates":[-5.7976679802,38.9731178284],"type":"Point"}
}