{
  "type": "Feature",
  "properties": {
    "addr:full":"Calle de Genoveva Torres Morales, 1 Zaragoza Zaragoza 50006",
    "addr:housenumber":"1",
    "addr:postcode":"50006",
    "addr:street":"Calle De Genoveva Torres Morales",
    "iso:country":"ES",
    "sg:address":"Calle de Genoveva Torres Morales, 1",
    "sg:city":"Zaragoza",
    "sg:orig_category":"M\u00c9dicos: Dermatolog\u00cda Y Venereolog\u00cda",
    "sg:phone":"+34 976 37 03 73",
    "sg:postcode":"50006",
    "sg:province":"Zaragoza",
    "wof:name":"Iba\u00f1ez Vecino Miguel Angel",
    "wof:placetype":"venue"
},
  "geometry": {"coordinates":[-0.8897899985,41.6426315308],"type":"Point"}
}