{
  "type": "Feature",
  "properties": {
    "addr:full":"Calle de Marconi, S/n Don Benito Badajoz 06400",
    "addr:housenumber":"s / n",
    "addr:postcode":"06400",
    "addr:street":"Calle De Marconi",
    "iso:country":"ES",
    "sg:address":"Calle de Marconi, S/n",
    "sg:city":"Don Benito",
    "sg:orig_category":"Venta, Montaje De Neum\u00c1ticos",
    "sg:phone":"+34 924 80 41 59",
    "sg:postcode":"06400",
    "sg:province":"Badajoz",
    "wof:name":"Ruiz Garcia Luis",
    "wof:placetype":"venue"
},
  "geometry": {"coordinates":[-5.87976408,38.9597969055],"type":"Point"}
}