{
  "type": "Feature",
  "properties": {
    "iso:country":"ES",
    "sg:address":"Pol. Ind. Can Vardalet, 17",
    "sg:city":"Ve\u00efnat Sant Pere",
    "sg:orig_category":"Inform\u00c1tica, Ofim\u00c1tica (estudios, Asesor\u00cda, Ingenier\u00cda, Formaci\u00d3n)",
    "sg:phone":"+34 937 65 06 36",
    "sg:postcode":"08490",
    "sg:province":"Barcelona",
    "wof:name":"Carmen Iba\u00f1ez S.l.",
    "wof:placetype":"venue"
},
  "geometry": {"coordinates":[2.7179350853,41.6998901367],"type":"Point"}
}