{
  "type": "Feature",
  "properties": {
    "iso:country":"ES",
    "sg:address":"Carrer de Torrijos, 6",
    "sg:city":"Barcelona",
    "sg:orig_category":"Pescader\u00cdas (al Por Menor)",
    "sg:phone":"+34 932 13 59 18",
    "sg:postcode":"08012",
    "sg:province":"Barcelona",
    "wof:name":"Barrufet Ros Jose",
    "wof:placetype":"venue"
},
  "geometry": {"coordinates":[2.1600470543,41.402469635],"type":"Point"}
}