{
  "type": "Feature",
  "properties": {
    "addr:full":"Grup Bego\u00d1alde, 11 Bilbao Vizcaya 48007",
    "addr:housenumber":"11",
    "addr:postcode":"48007",
    "addr:street":"Begon\u0303Alde",
    "iso:country":"ES",
    "sg:address":"Grup Bego\u00d1alde, 11",
    "sg:city":"Bilbao",
    "sg:orig_category":"Abogados",
    "sg:phone":"+34 944 45 75 25",
    "sg:postcode":"48007",
    "sg:province":"Vizcaya",
    "wof:name":"Miravalles Saiz Juan Carlos",
    "wof:placetype":"venue"
},
  "geometry": {"coordinates":[-2.9138300419,43.2622795105],"type":"Point"}
}