{
  "type": "Feature",
  "properties": {
    "iso:country":"ES",
    "sg:address":"Carr Sant Vicen\u00c7, 26",
    "sg:city":"Figueres",
    "sg:orig_category":"Fabricaci\u00d3n, Importaci\u00d3n De L\u00c1mparas Y Bombillas",
    "sg:phone":"+34 972 67 43 16",
    "sg:postcode":"17600",
    "sg:province":"Girona",
    "wof:name":"Installacions Jordi Casademont, S.c",
    "wof:placetype":"venue"
},
  "geometry": {"coordinates":[2.9600479603,42.2651481628],"type":"Point"}
}