{
  "type": "Feature",
  "properties": {
    "addr:full":"Carr Historiador Josep Clapes, De L', 11 Eivissa Islas Baleares 07800",
    "addr:housenumber":"11",
    "addr:postcode":"07800",
    "addr:street":"Carr Historiador Josep Clapes De L '",
    "iso:country":"ES",
    "sg:address":"Carr Historiador Josep Clapes, De L', 11",
    "sg:city":"Eivissa",
    "sg:orig_category":"Abogados",
    "sg:phone":"+34 971 30 16 44",
    "sg:postcode":"07800",
    "sg:province":"Islas Baleares",
    "wof:name":"Ballester Arazo Amado",
    "wof:placetype":"venue"
},
  "geometry": {"coordinates":[1.4304840565,38.9087257385],"type":"Point"}
}