{
  "type": "Feature",
  "properties": {
    "addr:full":"Carr Escoles Pies, 37 Algemesi Valencia 46680",
    "addr:housenumber":"37",
    "addr:postcode":"46680",
    "addr:street":"Carr Escoles Pies",
    "iso:country":"ES",
    "sg:address":"Carr Escoles Pies, 37",
    "sg:city":"Algemesi",
    "sg:orig_category":"Doctores En Medicina",
    "sg:phone":"+34 962 42 13 28",
    "sg:postcode":"46680",
    "sg:province":"Valencia",
    "wof:name":"Bueno Barbera Jose",
    "wof:placetype":"venue"
},
  "geometry": {"coordinates":[-0.4319289923,39.1955108643],"type":"Point"}
}