{
  "type": "Feature",
  "properties": {
    "iso:country":"ES",
    "sg:address":"Av Girona, 35",
    "sg:city":"Olot",
    "sg:orig_category":"Textil",
    "sg:phone":"+34 972 26 11 98",
    "sg:postcode":"17800",
    "sg:province":"Girona",
    "wof:name":"Coll Maso Miguel",
    "wof:placetype":"venue"
},
  "geometry": {"coordinates":[2.4947009087,42.1856384277],"type":"Point"}
}