{
  "type": "Feature",
  "properties": {
    "addr:full":"Pase Fueros De Los, 1 Donostia-san Sebastian Guip\u00f9zcoa 20005",
    "addr:housenumber":"1",
    "addr:postcode":"20005",
    "iso:country":"ES",
    "sg:address":"Pase Fueros De Los, 1",
    "sg:city":"Donostia-san Sebastian",
    "sg:orig_category":"Inmobiliaria (agencias)",
    "sg:phone":"+34 943 42 65 65",
    "sg:postcode":"20005",
    "sg:province":"Guip\u00f9zcoa",
    "wof:name":"Comendador Azcarraga Luis",
    "wof:placetype":"venue"
},
  "geometry": {"coordinates":[-1.9794000387,43.3173789978],"type":"Point"}
}