{
  "type": "Feature",
  "properties": {
    "iso:country":"ES",
    "sg:address":"Carrer de Escola Pia, 121",
    "sg:city":"Sabadell",
    "sg:orig_category":"Marketing Directo",
    "sg:phone":"+34 937 25 62 90",
    "sg:postcode":"08201",
    "sg:province":"Barcelona",
    "wof:name":"Cartexpres S.l.",
    "wof:placetype":"venue"
},
  "geometry": {"coordinates":[2.1018788815,41.5483932495],"type":"Point"}
}