{
  "type": "Feature",
  "properties": {
    "iso:country":"ES",
    "sg:address":"Carrer de Ramon Jove, 12",
    "sg:city":"Sabadell",
    "sg:orig_category":"Carnicer\u00cdas, Carnicer\u00cdas",
    "sg:phone":"+34 937 16 60 25",
    "sg:postcode":"08208",
    "sg:province":"Barcelona",
    "wof:name":"Pelegrin Navarro Lorenzo",
    "wof:placetype":"venue"
},
  "geometry": {"coordinates":[2.1060340405,41.5653533936],"type":"Point"}
}