{
  "type": "Feature",
  "properties": {
    "addr:full":"Rond Segovia, 22 Madrid Madrid 28005",
    "addr:housenumber":"22",
    "addr:postcode":"madrid;28005",
    "addr:street":"Segovia",
    "iso:country":"ES",
    "sg:address":"Rond Segovia, 22",
    "sg:city":"Madrid",
    "sg:orig_category":"Frutas, Legumbres Frescas Y Tempranas (al Por Menor)",
    "sg:phone":"+34 913 65 86 46",
    "sg:postcode":"28005",
    "sg:province":"Madrid",
    "wof:name":"Betty Rocio  Jimenez Coello",
    "wof:placetype":"venue"
},
  "geometry": {"coordinates":[-3.7116479874,40.413848877],"type":"Point"}
}