{
  "type": "Feature",
  "properties": {
    "addr:full":"Carrer de Sant Jaume, 150 Calella Barcelona 08370",
    "addr:housenumber":"150",
    "addr:postcode":"08370",
    "addr:street":"Carrer De Sant Jaume",
    "iso:country":"ES",
    "sg:address":"Carrer de Sant Jaume, 150",
    "sg:city":"Calella",
    "sg:orig_category":"Molduras, Junquillos, Listones Y Molduras Perforadas",
    "sg:phone":"+34 937 66 19 29",
    "sg:postcode":"08370",
    "sg:province":"Barcelona",
    "wof:name":"Perez Rubio Juan",
    "wof:placetype":"venue"
},
  "geometry": {"coordinates":[2.6546990871,41.613986969],"type":"Point"}
}