{
  "type": "Feature",
  "properties": {
    "iso:country":"ES",
    "sg:address":"Calle de Torre Del Mar, 26",
    "sg:city":"Malaga",
    "sg:orig_category":"Transportes Por Carretera: Lotes Completos, Mercanc\u00cdas Diversas",
    "sg:phone":"+34 952 17 24 62",
    "sg:postcode":"29004",
    "sg:province":"M\u00e1laga",
    "wof:name":"Alpaso Grupo Logistico S.l.",
    "wof:placetype":"venue"
},
  "geometry": {"coordinates":[-4.4977169037,36.6955604553],"type":"Point"}
}