{
  "type": "Feature",
  "properties": {
    "addr:full":"Calle de Valle Inclan, 168 Granada Granada 18003",
    "addr:housenumber":"168",
    "addr:postcode":"18003",
    "addr:street":"Calle De Valle Inclan",
    "iso:country":"ES",
    "sg:address":"Calle de Valle Inclan, 168",
    "sg:city":"Granada",
    "sg:orig_category":"Herboristas (al Por Menor)",
    "sg:phone":"+34 958 27 94 38",
    "sg:postcode":"18003",
    "sg:province":"Granada",
    "wof:name":"Vilchez Fernandez Rafael",
    "wof:placetype":"venue"
},
  "geometry": {"coordinates":[-3.6115159988,37.1804733276],"type":"Point"}
}