{
  "type": "Feature",
  "properties": {
    "iso:country":"ES",
    "sg:address":"Rua Progreso, 59",
    "sg:city":"Sanxenxo",
    "sg:orig_category":"Sanatorios M\u00c9dico",
    "sg:phone":"+34 986 69 19 95",
    "sg:postcode":"36960",
    "sg:province":"Pontevedra",
    "wof:name":"Sergas-gerencia Atencion Primaria Pontevedra-area Norte",
    "wof:placetype":"venue"
},
  "geometry": {"coordinates":[-8.799908638,42.4011306763],"type":"Point"}
}