{
  "type": "Feature",
  "properties": {
    "iso:country":"ES",
    "sg:address":"Trva Luna (la), 28",
    "sg:city":"Espinar",
    "sg:orig_category":"Fisioterapia",
    "sg:phone":"+34 921 18 31 18",
    "sg:postcode":"40400",
    "sg:province":"Segovia",
    "wof:name":"Garcia De Andres Monica",
    "wof:placetype":"venue"
},
  "geometry": {"coordinates":[-4.2502188683,40.7170982361],"type":"Point"}
}