{
  "type": "Feature",
  "properties": {
    "addr:full":"Rosalia De Castro, 13 Padron La Coru\u00f1a 15900",
    "addr:housenumber":"13",
    "addr:postcode":"15900",
    "addr:street":"Rosalia De Castro;Padron La Corun\u0303A",
    "iso:country":"ES",
    "sg:address":"Rosalia De Castro, 13",
    "sg:city":"Padron",
    "sg:orig_category":"Laboratorios Y Trabajos De Fotograf\u00cda, V\u00cddeo Y Cine",
    "sg:phone":"+34 981 81 15 05",
    "sg:postcode":"15900",
    "sg:province":"La Coru\u00f1a",
    "wof:name":"Lafuente Llerena Salvador Antonio",
    "wof:placetype":"venue"
},
  "geometry": {"coordinates":[-8.6595220566,42.7391548157],"type":"Point"}
}