{
  "type": "Feature",
  "properties": {
    "iso:country":"ES",
    "sg:address":"Carrer de Sant Joan, 28",
    "sg:city":"Senia",
    "sg:orig_category":"Carnicer\u00cdas, Carnicer\u00cdas",
    "sg:phone":"+34 977 71 33 14",
    "sg:postcode":"43560",
    "sg:province":"Tarragona",
    "wof:name":"Mestre Farnos Martin",
    "wof:placetype":"venue"
},
  "geometry": {"coordinates":[0.2810870111,40.6342849731],"type":"Point"}
}