{
  "type": "Feature",
  "properties": {
    "iso:country":"ES",
    "sg:address":"Calle de General Lacy, 33",
    "sg:city":"S. Roque",
    "sg:orig_category":"Textil",
    "sg:phone":"+34 956 78 15 45",
    "sg:postcode":"11360",
    "sg:province":"C\u00e1diz",
    "wof:name":"Garcia Santos Maria Del Carmen",
    "wof:placetype":"venue"
},
  "geometry": {"coordinates":[-5.3856048584,36.2108192444],"type":"Point"}
}