{
  "type": "Feature",
  "properties": {
    "addr:full":"Ptda Cotes Baixes, 9 Alcoi Alicante 03804",
    "addr:housenumber":"9",
    "addr:postcode":"03804",
    "addr:street":"Ptda Cotes Baixes",
    "iso:country":"ES",
    "sg:address":"Ptda Cotes Baixes, 9",
    "sg:city":"Alcoi",
    "sg:orig_category":"Equipos De Marcado, Etiquetado",
    "sg:phone":"+34 965 52 02 55",
    "sg:postcode":"03804",
    "sg:province":"Alicante",
    "wof:name":"Artegraf Rotulacion Industrial S.l.",
    "wof:placetype":"venue"
},
  "geometry": {"coordinates":[-0.4714694023,38.7123031616],"type":"Point"}
}