{
  "type": "Feature",
  "properties": {
    "iso:country":"ES",
    "sg:address":"Pl Ajuntament (l'), 1",
    "sg:city":"Busot",
    "sg:orig_category":"Administraciones Regionales, Departamentales Y Locales",
    "sg:phone":"+34 965 69 90 92",
    "sg:postcode":"03111",
    "sg:province":"Alicante",
    "wof:name":"Ayuntamiento De Busot",
    "wof:placetype":"venue"
},
  "geometry": {"coordinates":[-0.3985723853,38.4265022278],"type":"Point"}
}