{
  "type": "Feature",
  "properties": {
    "addr:full":"Ibabe Pol Ind, 2 Lazkao Guip\u00f9zcoa 20210",
    "addr:housenumber":"2",
    "addr:postcode":"20210",
    "addr:street":"Ibabe Pol Ind;Guipu\u0300Zcoa",
    "iso:country":"ES",
    "sg:address":"Ibabe Pol Ind, 2",
    "sg:city":"Lazkao",
    "sg:orig_category":"Electricidad: Instaladores",
    "sg:phone":"+34 943 16 06 49",
    "sg:postcode":"20210",
    "sg:province":"Guip\u00f9zcoa",
    "wof:name":"Argilana, C.b.",
    "wof:placetype":"venue"
},
  "geometry": {"coordinates":[-2.1873590946,43.0314903259],"type":"Point"}
}