{
  "type": "Feature",
  "properties": {
    "addr:full":"Avda Majuelo (del), 19 Valdemoro Madrid 28340",
    "addr:housenumber":"19",
    "addr:postcode":"28340",
    "addr:street":"Avda Majuelo Del",
    "iso:country":"ES",
    "sg:address":"Avda Majuelo (del), 19",
    "sg:city":"Valdemoro",
    "sg:orig_category":"Transporte En General",
    "sg:phone":"+34 918 08 24 05",
    "sg:postcode":"28340",
    "sg:province":"Madrid",
    "wof:name":"Actea Logistica S.l.",
    "wof:placetype":"venue"
},
  "geometry": {"coordinates":[-3.6765348911,40.207824707],"type":"Point"}
}