{
  "type": "Feature",
  "properties": {
    "iso:country":"ES",
    "sg:address":"Calle de Sevilla, S/n",
    "sg:city":"Bailen",
    "sg:orig_category":"Promotores Constructores",
    "sg:phone":"+34 953 67 02 28",
    "sg:postcode":"23710",
    "sg:province":"Ja\u00e9n",
    "sg:website":"www.elgranaino.com",
    "wof:name":"Fearsa S.l.",
    "wof:placetype":"venue"
},
  "geometry": {"coordinates":[-3.7789280415,38.0936584473],"type":"Point"}
}