{
  "type": "Feature",
  "properties": {
    "addr:full":"Calle de Misael Ba\u00d1uelos, 2 Sedano Burgos 09142",
    "addr:housenumber":"2",
    "addr:postcode":"09142",
    "addr:street":"Calle De Misael Ban\u0303Uelos",
    "iso:country":"ES",
    "sg:address":"Calle de Misael Ba\u00d1uelos, 2",
    "sg:city":"Sedano",
    "sg:orig_category":"Iglesia Cat\u00d3lica",
    "sg:phone":"+34 947 15 00 11",
    "sg:postcode":"09142",
    "sg:province":"Burgos",
    "wof:name":"Parroquia Santa Maria",
    "wof:placetype":"venue"
},
  "geometry": {"coordinates":[-3.7526609898,42.716255188],"type":"Point"}
}