{
  "type": "Feature",
  "properties": {
    "addr:full":"Calle de San Diego De Alcala, 12 Palmas De Gran Canaria Las Palmas 35001",
    "addr:housenumber":"12",
    "addr:postcode":"35001",
    "addr:street":"Calle De San;De Alcala",
    "iso:country":"ES",
    "sg:address":"Calle de San Diego De Alcala, 12",
    "sg:city":"Palmas De Gran Canaria",
    "sg:orig_category":"Audiovisuales: Material Y Accesorios (al Por Menor)",
    "sg:phone":"+34 928 36 50 00",
    "sg:postcode":"35001",
    "sg:province":"Las Palmas",
    "sg:website":"www.digitron.es",
    "wof:name":"Digitron Estudios S.l.",
    "wof:placetype":"venue"
},
  "geometry": {"coordinates":[-15.418091774,28.100692749],"type":"Point"}
}