{
  "type": "Feature",
  "properties": {
    "addr:full":"Carrer de Venecia, 52 Lloret Mar Girona 17310",
    "addr:housenumber":"52",
    "addr:postcode":"17310",
    "addr:street":"Carrer De Venecia",
    "iso:country":"ES",
    "sg:address":"Carrer de Venecia, 52",
    "sg:city":"Lloret Mar",
    "sg:orig_category":"Bazares, Art\u00cdculos De Limpieza Y De Cocina (al Por Menor)",
    "sg:phone":"+34 972 37 28 90",
    "sg:postcode":"17310",
    "sg:province":"Girona",
    "wof:name":"Awad Caber  Mohamed Ali",
    "wof:placetype":"venue"
},
  "geometry": {"coordinates":[2.8516800404,41.7001838684],"type":"Point"}
}