{
  "type": "Feature",
  "properties": {
    "iso:country":"ES",
    "sg:address":"Calle de Calderon De La Barca, 1",
    "sg:city":"Socuellamos",
    "sg:orig_category":"Iglesia Cat\u00d3lica",
    "sg:phone":"+34 926 50 00 02",
    "sg:postcode":"13630",
    "sg:province":"Ciudad Real",
    "wof:name":"Parroquia Nrta. Sra. De La Asuncion",
    "wof:placetype":"venue"
},
  "geometry": {"coordinates":[-2.7928349972,39.2868499756],"type":"Point"}
}