{
  "type": "Feature",
  "properties": {
    "iso:country":"ES",
    "sg:address":"Avda Espa\u00d1a, 8",
    "sg:city":"Caceres",
    "sg:orig_category":"Centros De Coordinaci\u00d3n",
    "sg:phone":"+34 927 62 72 99",
    "sg:postcode":"10001",
    "sg:province":"C\u00e1ceres",
    "wof:name":"Gestoria Garcia Polo Marin S.l.",
    "wof:placetype":"venue"
},
  "geometry": {"coordinates":[-6.3776788712,39.471321106],"type":"Point"}
}