{
  "type": "Feature",
  "properties": {
    "iso:country":"ES",
    "sg:address":"Calle de Concejal Emilio Tarraga, S/n",
    "sg:city":"Pilar Horadada",
    "sg:orig_category":"Agencias Y Agentes Comerciales, Representantes",
    "sg:phone":"+34 965 35 29 42",
    "sg:postcode":"03190",
    "sg:province":"Alicante",
    "wof:name":"Key Mare Promotores S.l.",
    "wof:placetype":"venue"
},
  "geometry": {"coordinates":[-0.7860602736,37.8622245789],"type":"Point"}
}