{
  "type": "Feature",
  "properties": {
    "iso:country":"ES",
    "sg:address":"Pol. Monzu, S/n",
    "sg:city":"Huesca",
    "sg:orig_category":"Trabajos De Soldaduras",
    "sg:phone":"+34 974 22 15 55",
    "sg:postcode":"22006",
    "sg:province":"Huesca",
    "wof:name":"Soldadura Montaner S. L.",
    "wof:placetype":"venue"
},
  "geometry": {"coordinates":[-0.4083139896,42.1365661621],"type":"Point"}
}