{
  "type": "Feature",
  "properties": {
    "addr:full":"Av Saloria, 92 Seu D'urgell Lleida 25700",
    "addr:housenumber":"92",
    "addr:postcode":"25700",
    "addr:street":"Av Saloria",
    "iso:country":"ES",
    "sg:address":"Av Saloria, 92",
    "sg:city":"Seu D'urgell",
    "sg:orig_category":"Reparaciones Y Remolcado De Veh\u00cdculos",
    "sg:phone":"+34 973 35 12 34",
    "sg:postcode":"25700",
    "sg:province":"Lleida",
    "wof:name":"Sanvicens Giro Pere",
    "wof:placetype":"venue"
},
  "geometry": {"coordinates":[0.6457189918,41.6027946472],"type":"Point"}
}