{
  "type": "Feature",
  "properties": {
    "iso:country":"ES",
    "sg:address":"Calle de San Pedro, 27",
    "sg:city":"Espinardo",
    "sg:orig_category":"Inmobiliaria (agencias)",
    "sg:phone":"+34 968 22 32 09",
    "sg:postcode":"30004",
    "sg:province":"Murcia",
    "wof:name":"Hg Murcia 2002 S.l.",
    "wof:placetype":"venue"
},
  "geometry": {"coordinates":[-1.1341309547,37.9845848083],"type":"Point"}
}