{
  "type": "Feature",
  "properties": {
    "iso:country":"ES",
    "sg:address":"Pla\u00c7 Partidors (de), 6",
    "sg:city":"Lliria",
    "sg:orig_category":"Inmobiliaria (agencias)",
    "sg:phone":"+34 962 79 13 98",
    "sg:postcode":"46160",
    "sg:province":"Valencia",
    "sg:website":"www.lliriainvest.com",
    "wof:name":"Lliria Invest S.l.",
    "wof:placetype":"venue"
},
  "geometry": {"coordinates":[-0.5947580934,39.624584198],"type":"Point"}
}