{
  "type": "Feature",
  "properties": {
    "iso:country":"ES",
    "sg:address":"Calle de Circunvalacion, S/n",
    "sg:city":"Rua De Valdeorras",
    "sg:orig_category":"Asesor\u00cda Fiscal Y Jur\u00cddica",
    "sg:phone":"+34 988 31 04 87",
    "sg:postcode":"32350",
    "sg:province":"Ourense",
    "wof:name":"Repsol Ypf S.a.",
    "wof:placetype":"venue"
},
  "geometry": {"coordinates":[-7.1178226471,42.392616272],"type":"Point"}
}