{
  "type": "Feature",
  "properties": {
    "addr:full":"Calle de Pilar, S/n Arandiga Zaragoza 50266",
    "addr:housenumber":"s / n",
    "addr:postcode":"50266",
    "addr:street":"Calle De Pilar",
    "iso:country":"ES",
    "sg:address":"Calle de Pilar, S/n",
    "sg:city":"Arandiga",
    "sg:orig_category":"Asociaciones, Organismos Culturales Y Socioeducativos",
    "sg:phone":"+34 976 60 56 11",
    "sg:postcode":"50266",
    "sg:province":"Zaragoza",
    "wof:name":"Ayuntamiento De Arandiga",
    "wof:placetype":"venue"
},
  "geometry": {"coordinates":[-1.5007743835,41.5089492798],"type":"Point"}
}