{
  "type": "Feature",
  "properties": {
    "iso:country":"ES",
    "sg:address":"Praz Campo Castelo (do), 8",
    "sg:city":"Lugo",
    "sg:orig_category":"Art\u00cdculos De Decoraci\u00d3n",
    "sg:phone":"+34 982 22 54 50",
    "sg:postcode":"27001",
    "sg:province":"Lugo",
    "sg:website":"www.ajuardecoracion.com",
    "wof:name":"Ajuar Decoracion S.l.",
    "wof:placetype":"venue"
},
  "geometry": {"coordinates":[-7.5550122261,43.0094490051],"type":"Point"}
}