{
  "type": "Feature",
  "properties": {
    "iso:country":"ES",
    "sg:address":"Calle de Barriocepo, 3",
    "sg:city":"Logro\u00f1o",
    "sg:orig_category":"Asociaciones, Organismos Culturales Y Socioeducativos",
    "sg:phone":"+34 941 22 01 83",
    "sg:postcode":"26001",
    "sg:province":"La Rioja",
    "wof:name":"Sociedad Recreativa El Cole",
    "wof:placetype":"venue"
},
  "geometry": {"coordinates":[-2.4471790791,42.4676399231],"type":"Point"}
}