{
  "type": "Feature",
  "properties": {
    "addr:full":"Calle de Mota Del Cuervo, 74 Madrid Madrid 28043",
    "addr:housenumber":"74",
    "addr:postcode":"madrid;28043",
    "addr:street":"Calle De Mota Del Cuervo",
    "iso:country":"ES",
    "sg:address":"Calle de Mota Del Cuervo, 74",
    "sg:city":"Madrid",
    "sg:orig_category":"Cristaler\u00cdas",
    "sg:phone":"+34 913 88 00 46",
    "sg:postcode":"28043",
    "sg:province":"Madrid",
    "wof:name":"Delgado Manzano Juan",
    "wof:placetype":"venue"
},
  "geometry": {"coordinates":[-3.6316699982,40.4647102356],"type":"Point"}
}