{
  "type": "Feature",
  "properties": {
    "addr:full":"Calle de Calatrava, 25 Ciudad Real Ciudad Real 13003",
    "addr:housenumber":"25",
    "addr:postcode":"13003",
    "addr:street":"Calle De Calatrava",
    "iso:country":"ES",
    "sg:address":"Calle de Calatrava, 25",
    "sg:city":"Ciudad Real",
    "sg:orig_category":"Zapatos (al Por Menor)",
    "sg:phone":"+34 926 25 37 57",
    "sg:postcode":"13003",
    "sg:province":"Ciudad Real",
    "wof:name":"Liu  Xiao Chun",
    "wof:placetype":"venue"
},
  "geometry": {"coordinates":[-3.9256281853,38.9889030457],"type":"Point"}
}