{
  "type": "Feature",
  "properties": {
    "iso:country":"ES",
    "sg:address":"Carrer de Balmes, 6",
    "sg:city":"Barcelona",
    "sg:orig_category":"Supermercados Y Hipermercados",
    "sg:phone":"+34 933 18 34 60",
    "sg:postcode":"08007",
    "sg:province":"Barcelona",
    "wof:name":"Xin Hua Extremo Oriente S.l.",
    "wof:placetype":"venue"
},
  "geometry": {"coordinates":[2.1671130657,41.3859481812],"type":"Point"}
}