{
  "type": "Feature",
  "properties": {
    "addr:full":"Calle de Cuatro Esquinas, 57 Santomera Murcia 30140",
    "addr:housenumber":"57",
    "addr:postcode":"30140",
    "addr:street":"Calle De Cuatro Esquinas",
    "iso:country":"ES",
    "sg:address":"Calle de Cuatro Esquinas, 57",
    "sg:city":"Santomera",
    "sg:orig_category":"Producci\u00d3n, Venta De Productos De Agricultura Biol\u00d3gica",
    "sg:phone":"+34 968 86 51 06",
    "sg:postcode":"30140",
    "sg:province":"Murcia",
    "wof:name":"H H C.b.",
    "wof:placetype":"venue"
},
  "geometry": {"coordinates":[-1.0475500822,38.0609855652],"type":"Point"}
}