{
  "type": "Feature",
  "properties": {
    "addr:full":"Calle de Dr Romero (del), 6 S. Martin Valdeiglesias Madrid 28680",
    "addr:postcode":"28680",
    "addr:street":"Calle De Dr Romero Del 6 S. Martin Valdeiglesias",
    "iso:country":"ES",
    "sg:address":"Calle de Dr Romero (del), 6",
    "sg:city":"S. Martin Valdeiglesias",
    "sg:orig_category":"Panader\u00cdas, Panader\u00cdas",
    "sg:phone":"+34 918 61 02 77",
    "sg:postcode":"28680",
    "sg:province":"Madrid",
    "wof:name":"Panificadora Gloria C.b.",
    "wof:placetype":"venue"
},
  "geometry": {"coordinates":[-4.3987789154,40.3619842529],"type":"Point"}
}