{
  "type": "Feature",
  "properties": {
    "addr:full":"Avda Constitucion Espa\u00d1ola, 17 Burgos Burgos 09007",
    "addr:housenumber":"17",
    "addr:postcode":"09007",
    "addr:street":"Avda Constitucion Espan\u0303Ola",
    "iso:country":"ES",
    "sg:address":"Avda Constitucion Espa\u00d1ola, 17",
    "sg:city":"Burgos",
    "sg:orig_category":"Farmacias",
    "sg:phone":"+34 947 22 15 94",
    "sg:postcode":"09007",
    "sg:province":"Burgos",
    "wof:name":"Gozalo Nogales Maria Henar",
    "wof:placetype":"venue"
},
  "geometry": {"coordinates":[-3.6738569736,42.3483505249],"type":"Point"}
}