{
  "type": "Feature",
  "properties": {
    "addr:full":"Calle de Bolta\u00d1a, 69 Madrid Madrid 28022",
    "addr:housenumber":"69",
    "addr:postcode":"madrid;28022",
    "addr:street":"Calle De Boltan\u0303A",
    "iso:country":"ES",
    "sg:address":"Calle de Bolta\u00d1a, 69",
    "sg:city":"Madrid",
    "sg:orig_category":"Fabricaci\u00d3n De Acumuladores Y De Pilas El\u00c9ctricas",
    "sg:phone":"+34 913 20 34 08",
    "sg:postcode":"28022",
    "sg:province":"Madrid",
    "wof:name":"Aranaz Gestion S.a.",
    "wof:placetype":"venue"
},
  "geometry": {"coordinates":[-3.6085495949,40.4483718872],"type":"Point"}
}