{
  "type": "Feature",
  "properties": {
    "iso:country":"ES",
    "sg:address":"Calle de Real, 37",
    "sg:city":"Maracena",
    "sg:orig_category":"Confecci\u00d3n (fabricaci\u00d3n, Al Por Mayor)",
    "sg:phone":"+34 958 42 05 31",
    "sg:postcode":"18200",
    "sg:province":"Granada",
    "wof:name":"Bueno Bailon Juan Miguel",
    "wof:placetype":"venue"
},
  "geometry": {"coordinates":[-3.6331939697,37.2060241699],"type":"Point"}
}