{
  "type": "Feature",
  "properties": {
    "addr:full":"Avda Madrid, 13 Brihuega Guadalajara 19400",
    "addr:housenumber":"13",
    "addr:postcode":"19400",
    "addr:street":"Avda Madrid",
    "iso:country":"ES",
    "sg:address":"Avda Madrid, 13",
    "sg:city":"Brihuega",
    "sg:orig_category":"Mec\u00c1nico Del Autom\u00d3vil",
    "sg:phone":"+34 949 28 05 74",
    "sg:postcode":"19400",
    "sg:province":"Guadalajara",
    "wof:name":"Leganes Baro Daniel",
    "wof:placetype":"venue"
},
  "geometry": {"coordinates":[-2.8714449406,40.7622032166],"type":"Point"}
}