{
  "type": "Feature",
  "properties": {
    "addr:full":"Plaz Constitucion, 11 Calamonte Badajoz 06810",
    "addr:housenumber":"11",
    "addr:postcode":"06810",
    "addr:street":"Constitucion",
    "iso:country":"ES",
    "sg:address":"Plaz Constitucion, 11",
    "sg:city":"Calamonte",
    "sg:orig_category":"Empresas De Carpinter\u00cda De Madera",
    "sg:phone":"+34 924 32 35 87",
    "sg:postcode":"06810",
    "sg:province":"Badajoz",
    "wof:name":"Carpinteria Fernandez Trinidad S.l.",
    "wof:placetype":"venue"
},
  "geometry": {"coordinates":[-6.3869891167,38.8892211914],"type":"Point"}
}