{
  "type": "Feature",
  "properties": {
    "addr:full":"Calle de Villa De Negreira, 15 Coru\u00d1a La Coru\u00f1a 15011",
    "addr:housenumber":"15",
    "addr:postcode":"15011",
    "addr:street":"Calle De Villa De Negreira;La Corun\u0303A",
    "iso:country":"ES",
    "sg:address":"Calle de Villa De Negreira, 15",
    "sg:city":"Coru\u00d1a",
    "sg:orig_category":"Peluqueros: De Se\u00d1oras",
    "sg:phone":"+34 981 25 60 39",
    "sg:postcode":"15011",
    "sg:province":"La Coru\u00f1a",
    "wof:name":"Ma\u00f1as Barbeito Maria Luisa",
    "wof:placetype":"venue"
},
  "geometry": {"coordinates":[-8.419760704,43.3643913269],"type":"Point"}
}