{
  "type": "Feature",
  "properties": {
    "iso:country":"ES",
    "sg:address":"Calle de Corredera Alta De San Pablo, 32",
    "sg:city":"Madrid",
    "sg:orig_category":"Retoques De Vestidos",
    "sg:phone":"+34 914 46 31 95",
    "sg:postcode":"28004",
    "sg:province":"Madrid",
    "sg:website":"www.gildisimas.com",
    "wof:name":"Moda Y Customisajes Phas S.l.",
    "wof:placetype":"venue"
},
  "geometry": {"coordinates":[-3.701659441,40.4266166687],"type":"Point"}
}