{
  "type": "Feature",
  "properties": {
    "addr:full":"Carr Ntra. Sra. Del Carme (de), 5 Alcoletge Lleida 25660",
    "addr:housenumber":"5",
    "addr:postcode":"25660",
    "addr:street":"Carr Ntra. Sra. Del Carme De",
    "iso:country":"ES",
    "sg:address":"Carr Ntra. Sra. Del Carme (de), 5",
    "sg:city":"Alcoletge",
    "sg:orig_category":"Molduras, Junquillos, Listones Y Molduras Perforadas",
    "sg:phone":"+34 973 19 70 24",
    "sg:postcode":"25660",
    "sg:province":"Lleida",
    "wof:name":"Tiro Coti S.l.",
    "wof:placetype":"venue"
},
  "geometry": {"coordinates":[0.6949170232,41.6480026245],"type":"Point"}
}