{
  "type": "Feature",
  "properties": {
    "addr:full":"Avda Andalucia, 75 Jaen Ja\u00e9n 23005",
    "addr:housenumber":"75;jae\u0301n",
    "addr:postcode":"23005",
    "addr:street":"Avda Andalucia",
    "iso:country":"ES",
    "sg:address":"Avda Andalucia, 75",
    "sg:city":"Jaen",
    "sg:orig_category":"Peluqueros: De Se\u00d1oras",
    "sg:phone":"+34 953 26 33 31",
    "sg:postcode":"23005",
    "sg:province":"Ja\u00e9n",
    "wof:name":"Alpolo S.l.",
    "wof:placetype":"venue"
},
  "geometry": {"coordinates":[-3.7999744415,37.7778358459],"type":"Point"}
}