{
  "type": "Feature",
  "properties": {
    "iso:country":"ES",
    "sg:address":"Calle de Argentina, 32",
    "sg:city":"Zamora",
    "sg:orig_category":"Farmacias",
    "sg:phone":"+34 980 55 75 98",
    "sg:postcode":"49020",
    "sg:province":"Zamora",
    "wof:name":"Fernandez Delgado Maria Luisa",
    "wof:placetype":"venue"
},
  "geometry": {"coordinates":[-5.7317676544,41.5095176697],"type":"Point"}
}