{
  "type": "Feature",
  "properties": {
    "iso:country":"ES",
    "sg:address":"Calle de Tomas Breton, 31",
    "sg:city":"Zaragoza",
    "sg:orig_category":"Reposter\u00cdas",
    "sg:phone":"+34 976 56 87 48",
    "sg:postcode":"50005",
    "sg:province":"Zaragoza",
    "wof:name":"Iba\u00f1ez Roy Maria Esperanza",
    "wof:placetype":"venue"
},
  "geometry": {"coordinates":[-0.8976849914,41.6452903748],"type":"Point"}
}