{
  "type": "Feature",
  "properties": {
    "addr:full":"Calle de Cava Alta, 4 Madrid Madrid 28005",
    "addr:housenumber":"4",
    "addr:postcode":"28005",
    "addr:street":"Calle De Cava Alta",
    "iso:country":"ES",
    "sg:address":"Calle de Cava Alta, 4",
    "sg:city":"Madrid",
    "sg:orig_category":"Marroquiner\u00cda (confecci\u00d3n)",
    "sg:phone":"+34 913 65 86 43",
    "sg:postcode":"28005",
    "sg:province":"Madrid",
    "wof:name":"Garcia Diez Carlos",
    "wof:placetype":"venue"
},
  "geometry": {"coordinates":[-3.7083077431,40.4124488831],"type":"Point"}
}