{
  "type": "Feature",
  "properties": {
    "iso:country":"ES",
    "sg:address":"Calle de Pizarro, 4",
    "sg:city":"Aranda Duero",
    "sg:orig_category":"Molduras, Junquillos, Listones Y Molduras Perforadas",
    "sg:phone":"+34 947 51 22 91",
    "sg:postcode":"09400",
    "sg:province":"Burgos",
    "wof:name":"Antona Delgado Jose Manuel",
    "wof:placetype":"venue"
},
  "geometry": {"coordinates":[-3.681084156,41.6710243225],"type":"Point"}
}