{
  "type": "Feature",
  "properties": {
    "addr:full":"Calle de Azucenas, 49 Madrid Madrid 28039",
    "addr:housenumber":"49",
    "addr:postcode":"madrid;28039",
    "addr:street":"Calle De Azucenas",
    "iso:country":"ES",
    "sg:address":"Calle de Azucenas, 49",
    "sg:city":"Madrid",
    "sg:orig_category":"Mec\u00c1nico Del Autom\u00d3vil",
    "sg:phone":"+34 915 71 72 33",
    "sg:postcode":"28039",
    "sg:province":"Madrid",
    "wof:name":"Llave Felices Jose Luis De La",
    "wof:placetype":"venue"
},
  "geometry": {"coordinates":[-3.7012829781,40.4641265869],"type":"Point"}
}