{
  "type": "Feature",
  "properties": {
    "iso:country":"ES",
    "sg:address":"Calle de Plateria, 14",
    "sg:city":"San Bartolome",
    "sg:orig_category":"Cobro De Pr\u00c9stamos",
    "sg:phone":"+34 968 22 05 76",
    "sg:postcode":"30004",
    "sg:province":"Murcia",
    "wof:name":"Multigestion Iberica S.a.",
    "wof:placetype":"venue"
},
  "geometry": {"coordinates":[-1.1314200163,37.9855232239],"type":"Point"}
}