{
  "type": "Feature",
  "properties": {
    "iso:country":"ES",
    "sg:address":"C/ Sant Pelegri, 18",
    "sg:city":"Tarrega",
    "sg:classifiers":[
        {
            "category":"Home & Garden",
            "subcategory":"Household Appliances",
            "type":"Retail Goods"
        }
    ],
    "sg:phone":"+34 973 31 01 78",
    "sg:postcode":"25300",
    "sg:province":"Lleida",
    "sg:tags":[
        "bodega",
        "de",
        "vino",
        "acondicionamiento"
    ],
    "wof:name":"Bergada Tosquella Juan",
    "wof:placetype":"venue"
},
  "geometry": {"coordinates":[1.1400099993,41.6499481201],"type":"Point"}
}