{
  "type": "Feature",
  "properties": {
    "iso:country":"ES",
    "sg:address":"Calle de Juan Manuel Ramos Vallecillos, 116",
    "sg:city":"Alcaudique",
    "sg:orig_category":"Agentes, Concesionarios Y Sucursales De Veh\u00cdculos",
    "sg:phone":"+34 950 49 14 32",
    "sg:postcode":"04760",
    "sg:province":"Almer\u00eda",
    "wof:name":"Autorecambios Berja S.l.",
    "wof:placetype":"venue"
},
  "geometry": {"coordinates":[-2.9501290321,36.8471107483],"type":"Point"}
}