{
  "type": "Feature",
  "properties": {
    "addr:full":"Avda Jardines De Mendez Nu\u00d1ez, 5 Coru\u00d1a A Coru\u00f1a 15006",
    "addr:housenumber":"5",
    "addr:postcode":"15006",
    "addr:street":"Avda Jardines De Mendez Nun\u0303Ez;Corun\u0303A",
    "iso:country":"ES",
    "sg:address":"Avda Jardines De Mendez Nu\u00d1ez, 5",
    "sg:city":"Coru\u00d1a",
    "sg:classifiers":[
        {
            "category":"Communications",
            "type":"Services"
        }
    ],
    "sg:phone":"+34 981 22 09 46",
    "sg:postcode":"15006",
    "sg:province":"A Coru\u00f1a",
    "sg:tags":[
        "televisiones",
        "y",
        "radio"
    ],
    "wof:name":"Television Espa\u00f1ola S. A.",
    "wof:placetype":"venue"
},
  "geometry": {"coordinates":[-8.4014987946,43.3682441711],"type":"Point"}
}