{
  "type": "Feature",
  "properties": {
    "addr:full":"Avda Fred Olsen, 8 Arrecife Las Palmas 35500",
    "addr:housenumber":"8",
    "addr:postcode":"35500",
    "addr:street":"Avda Fred Olsen",
    "iso:country":"ES",
    "sg:address":"Avda Fred Olsen, 8",
    "sg:city":"Arrecife",
    "sg:orig_category":"Laboratorios Y Cl\u00cdnicas Veterinarias",
    "sg:phone":"+34 928 81 46 50",
    "sg:postcode":"35500",
    "sg:province":"Las Palmas",
    "wof:name":"Gustems Martinez Ramon",
    "wof:placetype":"venue"
},
  "geometry": {"coordinates":[-13.5576791763,28.9586296082],"type":"Point"}
}