{
  "type": "Feature",
  "properties": {
    "addr:full":"Calle de Estartetxe, 5 Estartetxe Vizcaya 48940",
    "addr:housenumber":"5",
    "addr:postcode":"48940",
    "addr:street":"Calle De Estartetxe",
    "iso:country":"ES",
    "sg:address":"Calle de Estartetxe, 5",
    "sg:city":"Estartetxe",
    "sg:orig_category":"Servicios Diversos",
    "sg:phone":"+34 944 64 95 93",
    "sg:postcode":"48940",
    "sg:province":"Vizcaya",
    "wof:name":"Timberland Espa\u00f1a S.l.u.",
    "wof:placetype":"venue"
},
  "geometry": {"coordinates":[-2.9860789776,43.3275489807],"type":"Point"}
}