{
  "type": "Feature",
  "properties": {
    "addr:full":"Pla\u00c7 Furs (dels), 1 Catarroja Valencia 46470",
    "addr:housenumber":"1",
    "addr:postcode":"46470",
    "addr:street":"Dels",
    "iso:country":"ES",
    "sg:address":"Pla\u00c7 Furs (dels), 1",
    "sg:city":"Catarroja",
    "sg:orig_category":"Caf\u00c9s, Bares, Cervecer\u00cdas",
    "sg:phone":"+34 961 26 21 02",
    "sg:postcode":"46470",
    "sg:province":"Valencia",
    "wof:name":"Serrano Moreno Javier",
    "wof:placetype":"venue"
},
  "geometry": {"coordinates":[-0.414440006,39.3972015381],"type":"Point"}
}