{
  "type": "Feature",
  "properties": {
    "addr:full":"Calle de Donato Fernandez, 8 Pola De Allande Asturias 33880",
    "addr:housenumber":"8",
    "addr:postcode":"33880",
    "addr:street":"Calle De Donato Fernandez",
    "iso:country":"ES",
    "sg:address":"Calle de Donato Fernandez, 8",
    "sg:city":"Pola De Allande",
    "sg:orig_category":"Iglesia Cat\u00d3lica",
    "sg:phone":"+34 985 80 70 38",
    "sg:postcode":"33880",
    "sg:province":"Asturias",
    "wof:name":"Diocesis De Oviedo",
    "wof:placetype":"venue"
},
  "geometry": {"coordinates":[-6.6102528572,43.2715530396],"type":"Point"}
}