{
  "type": "Feature",
  "properties": {
    "addr:full":"Avda Constitucion, 1 Roda Albacete 02630",
    "addr:housenumber":"1",
    "addr:postcode":"02630",
    "addr:street":"Avda Constitucion",
    "iso:country":"ES",
    "sg:address":"Avda Constitucion, 1",
    "sg:city":"Roda",
    "sg:orig_category":"Pintura, Barniz, Productos Asimilables (fabricaci\u00d3n, Al Por Mayor)",
    "sg:phone":"+34 967 44 13 51",
    "sg:postcode":"02630",
    "sg:province":"Albacete",
    "wof:name":"Serrano Escudero Paulino",
    "wof:placetype":"venue"
},
  "geometry": {"coordinates":[-2.1604189873,39.2095794678],"type":"Point"}
}