{
  "type": "Feature",
  "properties": {
    "iso:country":"ES",
    "sg:address":"Plaz Constitucion (la), S/n",
    "sg:city":"Lopera",
    "sg:orig_category":"Iglesia Cat\u00d3lica",
    "sg:phone":"+34 953 51 67 23",
    "sg:postcode":"23780",
    "sg:province":"Ja\u00e9n",
    "wof:name":"Parroquia De La Inmaculada Concepcion",
    "wof:placetype":"venue"
},
  "geometry": {"coordinates":[-4.2141809464,37.9437179565],"type":"Point"}
}