{
  "type": "Feature",
  "properties": {
    "addr:full":"Calle de Esteban Mora, 45 Madrid Madrid 28027",
    "addr:housenumber":"45",
    "addr:postcode":"madrid;28027",
    "addr:street":"Calle De Esteban Mora",
    "iso:country":"ES",
    "sg:address":"Calle de Esteban Mora, 45",
    "sg:city":"Madrid",
    "sg:orig_category":"Art\u00cdculos De Regalo (al Por Menor)",
    "sg:phone":"+34 914 05 30 72",
    "sg:postcode":"28027",
    "sg:province":"Madrid",
    "wof:name":"Just Falcucci Silvia Susana",
    "wof:placetype":"venue"
},
  "geometry": {"coordinates":[-3.6537630558,40.4391098022],"type":"Point"}
}