{
  "type": "Feature",
  "properties": {
    "iso:country":"ES",
    "sg:address":"Carrer de Mallorca, 121",
    "sg:city":"Barcelona",
    "sg:orig_category":"Prendas Y Chalecos De Punto (al Por Menor)",
    "sg:phone":"+34 934 54 40 22",
    "sg:postcode":"08036",
    "sg:province":"Barcelona",
    "wof:name":"Gonzalez Aguerri Joaquin",
    "wof:placetype":"venue"
},
  "geometry": {"coordinates":[2.1531550884,41.3869361877],"type":"Point"}
}