{
  "type": "Feature",
  "properties": {
    "iso:country":"ES",
    "sg:address":"Avda Fuentemar (de), 35",
    "sg:city":"Coslada",
    "sg:orig_category":"Sonorizaci\u00d3n, Iluminaci\u00d3n",
    "sg:phone":"+34 916 69 17 20",
    "sg:postcode":"28820",
    "sg:province":"Madrid",
    "wof:name":"Iberofon",
    "wof:placetype":"venue"
},
  "geometry": {"coordinates":[-3.5461580753,40.4338912964],"type":"Point"}
}