{
  "type": "Feature",
  "properties": {
    "addr:full":"Avda San Cristobal, S/n Linares Ja\u00e9n 23700",
    "addr:postcode":"23700",
    "addr:street":"Avda San Cristobal S / N;Jae\u0301N",
    "iso:country":"ES",
    "sg:address":"Avda San Cristobal, S/n",
    "sg:city":"Linares",
    "sg:orig_category":"Servicios Gsm",
    "sg:phone":"+34 953 60 26 50",
    "sg:postcode":"23700",
    "sg:province":"Ja\u00e9n",
    "wof:name":"Avenir Telecom S.a.",
    "wof:placetype":"venue"
},
  "geometry": {"coordinates":[-3.6443676949,38.0895729065],"type":"Point"}
}