{
  "type": "Feature",
  "properties": {
    "addr:full":"Carrer de Dos De Maig, 256 Barcelona Barcelona 08025",
    "addr:housenumber":"256",
    "addr:postcode":"08025",
    "addr:street":"Carrer De Dos De Maig",
    "iso:country":"ES",
    "sg:address":"Carrer de Dos De Maig, 256",
    "sg:city":"Barcelona",
    "sg:orig_category":"Fabricaci\u00d3n, Venta De Cuadros, Accesorios Para Enmarcar",
    "sg:phone":"+34 934 35 21 35",
    "sg:postcode":"08025",
    "sg:province":"Barcelona",
    "wof:name":"Vazquez Rojas Idalina",
    "wof:placetype":"venue"
},
  "geometry": {"coordinates":[2.1800100803,41.4086112976],"type":"Point"}
}