{
  "type": "Feature",
  "properties": {
    "iso:country":"ES",
    "sg:address":"Carrer de Providencia, 150",
    "sg:city":"Barcelona",
    "sg:orig_category":"Frutas, Legumbres Frescas Y Tempranas (al Por Menor)",
    "sg:phone":"+34 932 85 00 03",
    "sg:postcode":"08024",
    "sg:province":"Barcelona",
    "wof:name":"Fruit Sa2pe S.l.",
    "wof:placetype":"venue"
},
  "geometry": {"coordinates":[2.1622760296,41.4094543457],"type":"Point"}
}