{
  "type": "Feature",
  "properties": {
    "addr:full":"Avda Ramon Menendez Pidal, 43 Albacete Albacete 02005",
    "addr:housenumber":"43",
    "addr:postcode":"02005",
    "addr:street":"Avda Ramon Menendez Pidal",
    "iso:country":"ES",
    "sg:address":"Avda Ramon Menendez Pidal, 43",
    "sg:city":"Albacete",
    "sg:orig_category":"Fabricaci\u00d3n Y Comercio De M\u00c1quinas",
    "sg:phone":"+34 967 52 29 62",
    "sg:postcode":"02005",
    "sg:province":"Albacete",
    "wof:name":"Elevaciones Albacete S.l.l",
    "wof:placetype":"venue"
},
  "geometry": {"coordinates":[-1.864964962,39.0028457642],"type":"Point"}
}