{
  "type": "Feature",
  "properties": {
    "addr:full":"Calle de Goya, S/n Caravaca Cruz Murcia 30400",
    "addr:housenumber":"s",
    "addr:postcode":"30400",
    "addr:street":"Calle De Goya;/ N Caravaca Cruz",
    "iso:country":"ES",
    "sg:address":"Calle de Goya, S/n",
    "sg:city":"Caravaca Cruz",
    "sg:orig_category":"Iglesia Cat\u00d3lica",
    "sg:phone":"+34 968 70 20 10",
    "sg:postcode":"30400",
    "sg:province":"Murcia",
    "wof:name":"Parroquia San Francisco",
    "wof:placetype":"venue"
},
  "geometry": {"coordinates":[-1.8621490002,38.1118011475],"type":"Point"}
}