{
  "type": "Feature",
  "properties": {
    "iso:country":"ES",
    "sg:address":"Calle de Serrano, 211",
    "sg:city":"Madrid",
    "sg:orig_category":"Abogados",
    "sg:phone":"+34 913 44 06 72",
    "sg:postcode":"28016",
    "sg:province":"Madrid",
    "wof:name":"Jose Manuel Fernandez Castro S.l.",
    "wof:placetype":"venue"
},
  "geometry": {"coordinates":[-3.6795868874,40.4536781311],"type":"Point"}
}