{
  "type": "Feature",
  "properties": {
    "iso:country":"ES",
    "sg:address":"Calle de Sauce, 7",
    "sg:city":"Infante Juan Manuel",
    "sg:orig_category":"Caf\u00c9s, Bares, Cervecer\u00cdas",
    "sg:phone":"+34 968 34 29 70",
    "sg:postcode":"30011",
    "sg:province":"Murcia",
    "wof:name":"Andreu Sanchez Antonio",
    "wof:placetype":"venue"
},
  "geometry": {"coordinates":[-1.1298867464,37.9834747314],"type":"Point"}
}