{
  "type": "Feature",
  "properties": {
    "addr:full":"Carrer de Acapulco, 2 Maravillas Islas Baleares 07610",
    "addr:housenumber":"2",
    "addr:postcode":"07610",
    "addr:street":"Carrer De Acapulco",
    "iso:country":"ES",
    "sg:address":"Carrer de Acapulco, 2",
    "sg:city":"Maravillas",
    "sg:orig_category":"Zapatos (al Por Menor)",
    "sg:phone":"+34 971 26 60 77",
    "sg:postcode":"07610",
    "sg:province":"Islas Baleares",
    "wof:name":"Pons Santandreu Mateo",
    "wof:placetype":"venue"
},
  "geometry": {"coordinates":[2.7243249416,39.5336914062],"type":"Point"}
}