{
  "type": "Feature",
  "properties": {
    "iso:country":"ES",
    "sg:address":"Calle de Alhondiga, 5",
    "sg:city":"Gernika-lumo",
    "sg:orig_category":"Peluqueros: De Se\u00d1oras",
    "sg:phone":"+34 946 25 02 05",
    "sg:postcode":"48300",
    "sg:province":"Vizcaya",
    "wof:name":"Goicoechea Embeitia Juana",
    "wof:placetype":"venue"
},
  "geometry": {"coordinates":[-2.6778819561,43.31224823],"type":"Point"}
}