{
  "type": "Feature",
  "properties": {
    "iso:country":"ES",
    "sg:address":"Carr Marginera, 12",
    "sg:city":"Besalu",
    "sg:orig_category":"Rectificaci\u00d3n, Mecanizado, Fresado",
    "sg:phone":"+34 972 59 02 88",
    "sg:postcode":"17850",
    "sg:province":"Girona",
    "wof:name":"Mecanizacio I Reparacions Grau S.c.",
    "wof:placetype":"venue"
},
  "geometry": {"coordinates":[2.6911211014,42.2016181946],"type":"Point"}
}