{
  "type": "Feature",
  "properties": {
    "iso:country":"ES",
    "sg:address":"Plaz Manantiales (los), 1",
    "sg:city":"Guadalajara",
    "sg:classifiers":[
        {
            "category":"Casinos & Gambling",
            "type":"Entertainment"
        }
    ],
    "sg:phone":"+34 949 20 24 07",
    "sg:postcode":"19004",
    "sg:province":"Guadalajara",
    "sg:tags":[
        "locale",
        "de",
        "juego"
    ],
    "wof:name":"Recreativos Olbe S.l.",
    "wof:placetype":"venue"
},
  "geometry": {"coordinates":[-3.1904039383,40.6326675415],"type":"Point"}
}