{
  "type": "Feature",
  "properties": {
    "iso:country":"ES",
    "sg:address":"Carrer de Sant Sebastia, 10",
    "sg:city":"Rubi",
    "sg:orig_category":"Contenedores (mercanc\u00cdas)",
    "sg:phone":"+34 936 99 12 35",
    "sg:postcode":"08191",
    "sg:province":"Barcelona",
    "wof:name":"Farre Agusi Ramon",
    "wof:placetype":"venue"
},
  "geometry": {"coordinates":[2.0296239853,41.4912261963],"type":"Point"}
}