{
  "type": "Feature",
  "properties": {
    "addr:full":"Calle de Cercedilla, 24 Rozas De Madrid Madrid 28230",
    "addr:housenumber":"24",
    "addr:postcode":"28230",
    "addr:street":"Calle De Cercedilla",
    "iso:country":"ES",
    "sg:address":"Calle de Cercedilla, 24",
    "sg:city":"Rozas De Madrid",
    "sg:orig_category":"Inmobiliaria (agencias)",
    "sg:phone":"+34 916 37 78 35",
    "sg:postcode":"28230",
    "sg:province":"Madrid",
    "wof:name":"Inmofrom S.a.",
    "wof:placetype":"venue"
},
  "geometry": {"coordinates":[-3.8798632622,40.4908866882],"type":"Point"}
}