{
  "type": "Feature",
  "properties": {
    "addr:full":"Calle de Mayor, 15 Pinseque Zaragoza 50298",
    "addr:housenumber":"15",
    "addr:postcode":"50298",
    "addr:street":"Calle De Mayor",
    "iso:country":"ES",
    "sg:address":"Calle de Mayor, 15",
    "sg:city":"Pinseque",
    "sg:orig_category":"Iglesia Cat\u00d3lica",
    "sg:phone":"+34 976 61 70 32",
    "sg:postcode":"50298",
    "sg:province":"Zaragoza",
    "wof:name":"Parroquia San Pedro Martir",
    "wof:placetype":"venue"
},
  "geometry": {"coordinates":[-1.0263154507,41.6832275391],"type":"Point"}
}