{
  "type": "Feature",
  "properties": {
    "addr:full":"Calle de Iglesia, S/n Crespos \u00c1vila 05300",
    "addr:housenumber":"s / n",
    "addr:postcode":"05300",
    "addr:street":"Calle De Iglesia",
    "iso:country":"ES",
    "sg:address":"Calle de Iglesia, S/n",
    "sg:city":"Crespos",
    "sg:orig_category":"Peluquer\u00cdas, Peluquer\u00cda Mixta",
    "sg:phone":"+34 920 24 43 26",
    "sg:postcode":"05300",
    "sg:province":"\u00c1vila",
    "wof:name":"Nieto Perez Abencio Julian",
    "wof:placetype":"venue"
},
  "geometry": {"coordinates":[-4.970044136,40.8707084656],"type":"Point"}
}