{
  "type": "Feature",
  "properties": {
    "addr:full":"Calle de Hermanos Garcia De La Torre, 3 Palmas De Gran Canaria Las Palmas 35005",
    "addr:housenumber":"3",
    "addr:postcode":"35005",
    "addr:street":"Calle De Hermanos Garcia De La Torre",
    "iso:country":"ES",
    "sg:address":"Calle de Hermanos Garcia De La Torre, 3",
    "sg:city":"Palmas De Gran Canaria",
    "sg:orig_category":"Asilos De Ancianos. Centros Privados",
    "sg:phone":"+34 928 24 64 14",
    "sg:postcode":"35005",
    "sg:province":"Las Palmas",
    "wof:name":"Ramirez Melian Orlando P.",
    "wof:placetype":"venue"
},
  "geometry": {"coordinates":[-15.4311037064,28.1274852753],"type":"Point"}
}