{
  "type": "Feature",
  "properties": {
    "addr:full":"Plaz San Juan, 2 Sena Huesca 22230",
    "addr:housenumber":"2",
    "addr:postcode":"22230",
    "addr:street":"Plaz San Juan",
    "iso:country":"ES",
    "sg:address":"Plaz San Juan, 2",
    "sg:city":"Sena",
    "sg:orig_category":"Cajas Para Embalar",
    "sg:phone":"+34 974 57 80 56",
    "sg:postcode":"22230",
    "sg:province":"Huesca",
    "sg:website":"www.multicaja.es",
    "wof:name":"Caja Rural Aragonesa Y De Los Pirineos",
    "wof:placetype":"venue"
},
  "geometry": {"coordinates":[-0.0451389998,41.7145309448],"type":"Point"}
}