{
  "type": "Feature",
  "properties": {
    "addr:full":"Calle de Doctor Cazalla, 8 Valladolid Valladolid 47003",
    "addr:housenumber":"8",
    "addr:postcode":"47003",
    "addr:street":"Calle De Doctor Cazalla",
    "iso:country":"ES",
    "sg:address":"Calle de Doctor Cazalla, 8",
    "sg:city":"Valladolid",
    "sg:orig_category":"Cerrajer\u00cda, Ferrallista",
    "sg:phone":"+34 983 35 45 43",
    "sg:postcode":"47003",
    "sg:province":"Valladolid",
    "wof:name":"Guerra Azcona Fernando",
    "wof:placetype":"venue"
},
  "geometry": {"coordinates":[-4.7291183472,41.6549034119],"type":"Point"}
}