{
  "type": "Feature",
  "properties": {
    "iso:country":"ES",
    "sg:address":"Pase Facultades, 4",
    "sg:city":"Valencia",
    "sg:orig_category":"Alquiler De Casas Y Habitaciones Amuebladas",
    "sg:phone":"+34 963 62 88 61",
    "sg:postcode":"46021",
    "sg:province":"Valencia",
    "wof:name":"Clinica Cavadas S.l.",
    "wof:placetype":"venue"
},
  "geometry": {"coordinates":[-0.3474600017,39.4770927429],"type":"Point"}
}