{
  "type": "Feature",
  "properties": {
    "addr:full":"Av Menorca, 14 Mao Islas Baleares 07703",
    "addr:housenumber":"14",
    "addr:postcode":"07703",
    "addr:street":"Av Menorca",
    "iso:country":"ES",
    "sg:address":"Av Menorca, 14",
    "sg:city":"Mao",
    "sg:orig_category":"Parques De Atracciones Y Centros De Esparcimiento",
    "sg:phone":"+34 971 36 87 30",
    "sg:postcode":"07703",
    "sg:province":"Islas Baleares",
    "wof:name":"Panaderia Los Claveles S.l.",
    "wof:placetype":"venue"
},
  "geometry": {"coordinates":[4.258564949,39.8859710693],"type":"Point"}
}