{
  "type": "Feature",
  "properties": {
    "addr:full":"Monte De Las Mercedes, 165 Las Mercedes Santa Cruz De Tenerife 38293",
    "addr:housenumber":"165",
    "addr:postcode":"38293",
    "addr:street":"Las Mercedes",
    "iso:country":"ES",
    "sg:address":"Monte De Las Mercedes, 165",
    "sg:city":"Las Mercedes",
    "sg:orig_category":"Ingeniero",
    "sg:phone":"+34 922 26 87 27",
    "sg:postcode":"38293",
    "sg:province":"Santa Cruz De Tenerife",
    "wof:name":"Comunidad Herederos Hermanos Hernandez C",
    "wof:placetype":"venue"
},
  "geometry": {"coordinates":[-16.2907238007,28.5156917572],"type":"Point"}
}