{
  "type": "Feature",
  "properties": {
    "iso:country":"ES",
    "sg:address":"Carr Exercits Espanyols, 13",
    "sg:city":"Alfas Pi",
    "sg:orig_category":"Guarder\u00cdas",
    "sg:phone":"+34 966 86 01 26",
    "sg:postcode":"03580",
    "sg:province":"Alicante",
    "wof:name":"Guarderia Piotin C.b.",
    "wof:placetype":"venue"
},
  "geometry": {"coordinates":[-0.0995334983,38.5770874023],"type":"Point"}
}