{
  "type": "Feature",
  "properties": {
    "addr:full":"Calle de Pintor Benedito, 4 Valencia Valencia 46007",
    "addr:housenumber":"4",
    "addr:postcode":"46007",
    "addr:street":"Calle De Pintor Benedito",
    "iso:country":"ES",
    "sg:address":"Calle de Pintor Benedito, 4",
    "sg:city":"Valencia",
    "sg:orig_category":"Formaci\u00d3n Continuada (variada)",
    "sg:phone":"+34 963 80 63 36",
    "sg:postcode":"46007",
    "sg:province":"Valencia",
    "wof:name":"Espada Rodriguez Maria Luisa",
    "wof:placetype":"venue"
},
  "geometry": {"coordinates":[-0.3825820088,39.4657974243],"type":"Point"}
}