{
  "type": "Feature",
  "properties": {
    "iso:country":"ES",
    "sg:address":"Calle de Asistente Arjona, 21",
    "sg:city":"Osuna",
    "sg:orig_category":"Ropa Para Caballeros (al Por Menor)",
    "sg:phone":"+34 955 82 06 88",
    "sg:postcode":"41640",
    "sg:province":"Sevilla",
    "wof:name":"Martin Cornejo Francisco Manuel",
    "wof:placetype":"venue"
},
  "geometry": {"coordinates":[-5.1024365425,37.2364807129],"type":"Point"}
}