{
  "type": "Feature",
  "properties": {
    "addr:full":"Camping S Miquel, S/n Colera Girona 17469",
    "addr:housenumber":"s / n",
    "addr:postcode":"17469",
    "iso:country":"ES",
    "sg:address":"Camping S Miquel, S/n",
    "sg:city":"Colera",
    "sg:orig_category":"Zonas De Acampada, Aparcamiento Para Caravanas",
    "sg:phone":"+34 972 38 90 18",
    "sg:postcode":"17469",
    "sg:province":"Girona",
    "wof:name":"Bosch Vila Luis",
    "wof:placetype":"venue"
},
  "geometry": {"coordinates":[2.9704549313,42.2177505493],"type":"Point"}
}