{
  "type": "Feature",
  "properties": {
    "addr:full":"Carr Padre Damian, 11 Eliana Valencia 46183",
    "addr:housenumber":"11",
    "addr:postcode":"46183",
    "addr:street":"Carr Padre Damian",
    "iso:country":"ES",
    "sg:address":"Carr Padre Damian, 11",
    "sg:city":"Eliana",
    "sg:orig_category":"Abogados",
    "sg:phone":"+34 962 75 05 83",
    "sg:postcode":"46183",
    "sg:province":"Valencia",
    "wof:name":"Acarreta Bermejo Jesus",
    "wof:placetype":"venue"
},
  "geometry": {"coordinates":[-0.5348603129,39.5602684021],"type":"Point"}
}