{
  "type": "Feature",
  "properties": {
    "iso:country":"ES",
    "sg:address":"Carr Lleida, 4",
    "sg:city":"Alcoletge",
    "sg:orig_category":"Empresas De Carpinter\u00cda Met\u00c1lica",
    "sg:phone":"+34 973 19 64 40",
    "sg:postcode":"25660",
    "sg:province":"Lleida",
    "wof:name":"Capell Navarra Sergi",
    "wof:placetype":"venue"
},
  "geometry": {"coordinates":[0.6936349869,41.6474609375],"type":"Point"}
}