{
  "type": "Feature",
  "properties": {
    "addr:full":"Avda Victoria (la), 98 Laredo Cantabria 39770",
    "addr:housenumber":"98",
    "addr:postcode":"39770",
    "addr:street":"Avda Victoria La",
    "iso:country":"ES",
    "sg:address":"Avda Victoria (la), 98",
    "sg:city":"Laredo",
    "sg:orig_category":"Discotecas Y Salas De Baile",
    "sg:phone":"+34 942 60 81 02",
    "sg:postcode":"39770",
    "sg:province":"Cantabria",
    "wof:name":"El Aila 2004 S.l.",
    "wof:placetype":"venue"
},
  "geometry": {"coordinates":[-3.4483709335,43.4250335693],"type":"Point"}
}