{
  "type": "Feature",
  "properties": {
    "iso:country":"ES",
    "sg:address":"Calle de San Pedro Del Barco, 12",
    "sg:city":"Barco De Avila",
    "sg:orig_category":"M\u00c9dicos: Estomatolog\u00cda",
    "sg:phone":"+34 920 34 13 00",
    "sg:postcode":"05600",
    "sg:province":"\u00c1vila",
    "wof:name":"Plaza Santo Tomas Jose Luis",
    "wof:placetype":"venue"
},
  "geometry": {"coordinates":[-5.5256772041,40.3563041687],"type":"Point"}
}