{
  "type": "Feature",
  "properties": {
    "addr:full":"Trva Jesus (travessia), 5 Palma Islas Baleares 07010",
    "addr:housenumber":"5",
    "addr:postcode":"07010",
    "addr:street":"Trva Jesus Travessia",
    "iso:country":"ES",
    "sg:address":"Trva Jesus (travessia), 5",
    "sg:city":"Palma",
    "sg:orig_category":"Maquinaria Para Industrias Diversas",
    "sg:phone":"+34 971 20 02 57",
    "sg:postcode":"07010",
    "sg:province":"Islas Baleares",
    "wof:name":"Tost Despatx Equipaments S.l.",
    "wof:placetype":"venue"
},
  "geometry": {"coordinates":[2.6457500458,39.5827789307],"type":"Point"}
}