{
  "type": "Feature",
  "properties": {
    "addr:full":"Avda Menendez Pelayo, 27 Madrid Madrid 28009",
    "addr:housenumber":"27",
    "addr:postcode":"madrid;28009",
    "addr:street":"Avda Menendez Pelayo",
    "iso:country":"ES",
    "sg:address":"Avda Menendez Pelayo, 27",
    "sg:city":"Madrid",
    "sg:orig_category":"M\u00c9dicos: Cirug\u00cda Ortop\u00c9dica Y Traumatolog\u00cda",
    "sg:phone":"+34 915 74 10 07",
    "sg:postcode":"28009",
    "sg:province":"Madrid",
    "wof:name":"Ferrer Olmedo Jesus",
    "wof:placetype":"venue"
},
  "geometry": {"coordinates":[-3.6787950993,40.4188766479],"type":"Point"}
}