{
  "type": "Feature",
  "properties": {
    "addr:full":"Urb. Son Prunes, 8 Son Ferriol Islas Baleares 07198",
    "addr:housenumber":"8",
    "addr:postcode":"07198",
    "addr:street":"Prunes",
    "iso:country":"ES",
    "sg:address":"Urb. Son Prunes, 8",
    "sg:city":"Son Ferriol",
    "sg:orig_category":"Empresas De Carpinter\u00cda Met\u00c1lica",
    "sg:phone":"+34 971 42 98 93",
    "sg:postcode":"07198",
    "sg:province":"Islas Baleares",
    "wof:name":"Perez Garcia Juan Manuel",
    "wof:placetype":"venue"
},
  "geometry": {"coordinates":[2.7170300484,39.5755653381],"type":"Point"}
}