{
  "type": "Feature",
  "properties": {
    "iso:country":"ES",
    "sg:address":"Calle de Colegiata, 9",
    "sg:city":"Madrid",
    "sg:orig_category":"Molduras, Junquillos, Listones Y Molduras Perforadas",
    "sg:phone":"+34 913 69 06 62",
    "sg:postcode":"28012",
    "sg:province":"Madrid",
    "wof:name":"Paoletti Santochi Jose Ricardo",
    "wof:placetype":"venue"
},
  "geometry": {"coordinates":[-3.7059731483,40.4128417969],"type":"Point"}
}