{
  "type": "Feature",
  "properties": {
    "iso:country":"ES",
    "sg:address":"Calle de Telletxe, 10",
    "sg:city":"Algorta",
    "sg:orig_category":"Centros De Coordinaci\u00d3n",
    "sg:phone":"+34 944 60 70 16",
    "sg:postcode":"48993",
    "sg:province":"Vizcaya",
    "wof:name":"Lopez De Uralde Zuazo Miren Gorane",
    "wof:placetype":"venue"
},
  "geometry": {"coordinates":[-3.0106170177,43.3542098999],"type":"Point"}
}