{
  "type": "Feature",
  "properties": {
    "iso:country":"ES",
    "sg:address":"Calle de Virgen De Las Vi\u00d1as, 16",
    "sg:city":"Madrid",
    "sg:orig_category":"Sales (al Por Mayor)",
    "sg:phone":"+34 913 31 67 68",
    "sg:postcode":"28031",
    "sg:province":"Madrid",
    "wof:name":"Centro Comercial Santa Eugenia",
    "wof:placetype":"venue"
},
  "geometry": {"coordinates":[-3.6044399738,40.3817901611],"type":"Point"}
}