{
  "type": "Feature",
  "properties": {
    "addr:full":"Bernardo Ezenarro Kalea, 13 Elgoibar Guip\u00f9zcoa 20870",
    "addr:housenumber":"13",
    "addr:postcode":"20870",
    "addr:street":"Bernardo Ezenarro Kalea;Guipu\u0300Zcoa",
    "iso:country":"ES",
    "sg:address":"Bernardo Ezenarro Kalea, 13",
    "sg:city":"Elgoibar",
    "sg:orig_category":"Sanatorios M\u00c9dico",
    "sg:phone":"+34 943 03 26 10",
    "sg:postcode":"20870",
    "sg:province":"Guip\u00f9zcoa",
    "wof:name":"Osakidetza",
    "wof:placetype":"venue"
},
  "geometry": {"coordinates":[-2.4140110016,43.2147064209],"type":"Point"}
}