{
  "type": "Feature",
  "properties": {
    "addr:full":"Cami Can Bassa, 10 Granollers Barcelona 08401",
    "addr:housenumber":"10",
    "addr:postcode":"08401",
    "iso:country":"ES",
    "sg:address":"Cami Can Bassa, 10",
    "sg:city":"Granollers",
    "sg:orig_category":"Maquinaria Para Industrias Diversas",
    "sg:phone":"+34 938 70 89 89",
    "sg:postcode":"08401",
    "sg:province":"Barcelona",
    "wof:name":"Escobar Manchado Jose Antonio",
    "wof:placetype":"venue"
},
  "geometry": {"coordinates":[2.2825500965,41.5911712646],"type":"Point"}
}