{
  "type": "Feature",
  "properties": {
    "iso:country":"ES",
    "sg:address":"Calle de Don Pedro De Luna, 86",
    "sg:city":"Zaragoza",
    "sg:orig_category":"Electricidad: Instaladores",
    "sg:phone":"+34 976 34 66 57",
    "sg:postcode":"50010",
    "sg:province":"Zaragoza",
    "wof:name":"Fejusa S.cv.",
    "wof:placetype":"venue"
},
  "geometry": {"coordinates":[-0.9035829902,41.6490097046],"type":"Point"}
}