{
  "type": "Feature",
  "properties": {
    "addr:full":"Carrer de Barcelona, 171 Hospitalet Llobregat Barcelona 08901",
    "addr:housenumber":"171",
    "addr:postcode":"08901",
    "addr:street":"Carrer De Barcelona",
    "iso:country":"ES",
    "sg:address":"Carrer de Barcelona, 171",
    "sg:city":"Hospitalet Llobregat",
    "sg:orig_category":"Confecci\u00d3n De Trajes Para Se\u00d1oras",
    "sg:phone":"+34 933 38 69 41",
    "sg:postcode":"08901",
    "sg:province":"Barcelona",
    "wof:name":"Moresby S.l.",
    "wof:placetype":"venue"
},
  "geometry": {"coordinates":[2.0966949463,41.3596725464],"type":"Point"}
}