{
  "type": "Feature",
  "properties": {
    "addr:full":"Carrer de Amsterdam, 18 Amposta Tarragona 43870",
    "addr:housenumber":"18",
    "addr:postcode":"43870",
    "addr:street":"Carrer De Amsterdam",
    "iso:country":"ES",
    "sg:address":"Carrer de Amsterdam, 18",
    "sg:city":"Amposta",
    "sg:orig_category":"Industria Qu\u00cdmica",
    "sg:phone":"+34 977 70 80 59",
    "sg:postcode":"43870",
    "sg:province":"Tarragona",
    "wof:name":"Aceimon S.l.",
    "wof:placetype":"venue"
},
  "geometry": {"coordinates":[0.5618150234,40.7053794861],"type":"Point"}
}