{
  "type": "Feature",
  "properties": {
    "iso:country":"ES",
    "sg:address":"Carrer de Pompeu Fabra, 197",
    "sg:city":"Terrassa",
    "sg:orig_category":"Empresarios",
    "sg:phone":"+34 937 34 27 50",
    "sg:postcode":"08226",
    "sg:province":"Barcelona",
    "wof:name":"Construccions Anmasal S.l.",
    "wof:placetype":"venue"
},
  "geometry": {"coordinates":[2.0231070518,41.5790328979],"type":"Point"}
}