{
  "type": "Feature",
  "properties": {
    "iso:country":"ES",
    "sg:address":"Carrer de Sant Jordi, 38",
    "sg:city":"Roda De Bara",
    "sg:orig_category":"Molduras, Junquillos, Listones Y Molduras Perforadas",
    "sg:phone":"+34 977 80 95 39",
    "sg:postcode":"43883",
    "sg:province":"Tarragona",
    "wof:name":"Lario Perez Roman",
    "wof:placetype":"venue"
},
  "geometry": {"coordinates":[1.4565399885,41.1828346252],"type":"Point"}
}