{
  "type": "Feature",
  "properties": {
    "iso:country":"ES",
    "sg:address":"Sabaters, 5",
    "sg:city":"Inca",
    "sg:orig_category":"Gases Industriales",
    "sg:phone":"+34 971 50 71 11",
    "sg:postcode":"07300",
    "sg:province":"Islas Baleares",
    "wof:name":"Distribuidora Foranea De Gas S.l.",
    "wof:placetype":"venue"
},
  "geometry": {"coordinates":[2.9030749798,39.7123603821],"type":"Point"}
}