{
  "type": "Feature",
  "properties": {
    "iso:country":"ES",
    "sg:address":"Calle de Mayor, 15",
    "sg:city":"S. Cebrian Campos",
    "sg:orig_category":"Producci\u00d3n, Venta De Productos De Agricultura Biol\u00d3gica",
    "sg:phone":"+34 979 15 41 11",
    "sg:postcode":"34429",
    "sg:province":"Palencia",
    "wof:name":"Lopez Garcia Julian",
    "wof:placetype":"venue"
},
  "geometry": {"coordinates":[-4.5327086449,42.2000541687],"type":"Point"}
}