{
  "type": "Feature",
  "properties": {
    "addr:full":"Carrer de Enric Granados, 110 Premia Mar Barcelona 08330",
    "addr:housenumber":"110",
    "addr:postcode":"08330",
    "addr:street":"Carrer De Enric Granados",
    "iso:country":"ES",
    "sg:address":"Carrer de Enric Granados, 110",
    "sg:city":"Premia Mar",
    "sg:orig_category":"Peluquer\u00cdas, Peluquer\u00cda Mixta",
    "sg:phone":"+34 937 52 36 55",
    "sg:postcode":"08330",
    "sg:province":"Barcelona",
    "wof:name":"Murillo Espinosa Blanca",
    "wof:placetype":"venue"
},
  "geometry": {"coordinates":[2.3618929386,41.4955215454],"type":"Point"}
}