{
  "type": "Feature",
  "properties": {
    "addr:full":"Calle de Lope Gisbert, S/n Santiago Murcia 30800",
    "addr:housenumber":"/ n",
    "addr:postcode":"30800",
    "addr:street":"Calle De Lope Gisbert S",
    "iso:country":"ES",
    "sg:address":"Calle de Lope Gisbert, S/n",
    "sg:city":"Santiago",
    "sg:orig_category":"Peluqueros: De Se\u00d1oras",
    "sg:phone":"+34 968 46 13 57",
    "sg:postcode":"30800",
    "sg:province":"Murcia",
    "wof:name":"Gimenez Gonzalez Salvadora",
    "wof:placetype":"venue"
},
  "geometry": {"coordinates":[-1.6905640364,37.680557251],"type":"Point"}
}