{
  "type": "Feature",
  "properties": {
    "iso:country":"ES",
    "sg:address":"Calle de Regordo\u00d1o, 39",
    "sg:city":"Mostoles",
    "sg:orig_category":"Montaje (empresas De)",
    "sg:phone":"+34 916 48 04 22",
    "sg:postcode":"28936",
    "sg:province":"Madrid",
    "wof:name":"Emein S. A.",
    "wof:placetype":"venue"
},
  "geometry": {"coordinates":[-3.8449850082,40.3198394775],"type":"Point"}
}