{
  "type": "Feature",
  "properties": {
    "iso:country":"ES",
    "sg:address":"Calle de Moralejo, 6",
    "sg:city":"Aguilar De La Frontera",
    "sg:orig_category":"Imprenta",
    "sg:phone":"+34 957 66 00 94",
    "sg:postcode":"14920",
    "sg:province":"C\u00f3rdoba",
    "wof:name":"Juan Luis Lucena S.l.",
    "wof:placetype":"venue"
},
  "geometry": {"coordinates":[-4.6575517654,37.5147285461],"type":"Point"}
}