{
  "type": "Feature",
  "properties": {
    "iso:country":"ES",
    "sg:address":"Ctra Pastrana (de), S/n",
    "sg:city":"Anchuelo",
    "sg:orig_category":"Producci\u00d3n, Comercio De Cereales",
    "sg:phone":"+34 918 84 03 51",
    "sg:postcode":"28818",
    "sg:province":"Madrid",
    "wof:name":"Saz Anchuelo S.l.",
    "wof:placetype":"venue"
},
  "geometry": {"coordinates":[-3.2700080872,40.4659881592],"type":"Point"}
}