{
  "type": "Feature",
  "properties": {
    "iso:country":"ES",
    "sg:address":"C/ Hostals, 37",
    "sg:city":"Inca",
    "sg:orig_category":"Doctores En Medicina",
    "sg:phone":"+34 971 88 32 56",
    "sg:postcode":"07300",
    "sg:province":"Islas Baleares",
    "wof:name":"Institut Oftalmic De Mallorca S.l.",
    "wof:placetype":"venue"
},
  "geometry": {"coordinates":[2.9105300903,39.7215995789],"type":"Point"}
}