{
  "type": "Feature",
  "properties": {
    "iso:country":"ES",
    "sg:address":"Calle de Rafaela De Antonio, 9",
    "sg:city":"Avila",
    "sg:orig_category":"Venta, Instalaci\u00d3n De Calefacci\u00d3n",
    "sg:phone":"+34 920 22 95 47",
    "sg:postcode":"05002",
    "sg:province":"\u00c1vila",
    "wof:name":"Garcia Palomo Maria Sonsoles",
    "wof:placetype":"venue"
},
  "geometry": {"coordinates":[-4.6985530853,40.6483879089],"type":"Point"}
}