{
  "type": "Feature",
  "properties": {
    "iso:country":"ES",
    "sg:address":"Calle de Timanfaya (de), 6",
    "sg:city":"Partija-santa Monica",
    "sg:orig_category":"Frutas Y Legumbres Frescas (al Por Mayor)",
    "sg:phone":"+34 916 66 69 86",
    "sg:postcode":"28529",
    "sg:province":"Madrid",
    "wof:name":"Diaz-pavon Meson Julia",
    "wof:placetype":"venue"
},
  "geometry": {"coordinates":[-3.5102670193,40.314289093],"type":"Point"}
}