{
  "type": "Feature",
  "properties": {
    "iso:country":"ES",
    "sg:address":"S. Miguel Lillo, S/n",
    "sg:city":"San Claudio",
    "sg:orig_category":"Centros Empresariales",
    "sg:phone":"+34 985 78 13 27",
    "sg:postcode":"33191",
    "sg:province":"Asturias",
    "wof:name":"Sinergia Integration S.l.",
    "wof:placetype":"venue"
},
  "geometry": {"coordinates":[-5.9176192284,43.3596382141],"type":"Point"}
}