{
  "type": "Feature",
  "properties": {
    "addr:full":"Avda Real, 15 Le\u00f3n Le\u00f3n 24006",
    "addr:housenumber":"15",
    "addr:postcode":"24006",
    "addr:street":"Avda Real;Leo\u0301N",
    "iso:country":"ES",
    "sg:address":"Avda Real, 15",
    "sg:city":"Le\u00f3n",
    "sg:orig_category":"Alquiler De Casas Y Habitaciones Amuebladas",
    "sg:phone":"+34 987 26 39 60",
    "sg:postcode":"24006",
    "sg:province":"Le\u00f3n",
    "wof:name":"Congregacion Misioneras Siervas De San Jose",
    "wof:placetype":"venue"
},
  "geometry": {"coordinates":[-5.5580677986,42.5972442627],"type":"Point"}
}