{
  "type": "Feature",
  "properties": {
    "iso:country":"ES",
    "sg:address":"Carrer de Balmes, 66",
    "sg:city":"Reus",
    "sg:orig_category":"Imprenta",
    "sg:phone":"+34 977 75 74 49",
    "sg:postcode":"43205",
    "sg:province":"Tarragona",
    "wof:name":"Collblang S.l.",
    "wof:placetype":"venue"
},
  "geometry": {"coordinates":[1.1082750559,41.1511039734],"type":"Point"}
}