{
  "type": "Feature",
  "properties": {
    "iso:country":"ES",
    "sg:address":"Ctra Consuegra, Km. 0010,0",
    "sg:city":"Urda",
    "sg:orig_category":"Distribuci\u00d3n De Petr\u00d3leo Y Derivados",
    "sg:phone":"+34 925 47 43 78",
    "sg:postcode":"45480",
    "sg:province":"Toledo",
    "wof:name":"Garcia Agudo Maria",
    "wof:placetype":"venue"
},
  "geometry": {"coordinates":[-3.7077515125,39.4197425842],"type":"Point"}
}