{
  "type": "Feature",
  "properties": {
    "iso:country":"ES",
    "sg:address":"S. Fruitos",
    "sg:city":"Manresa",
    "sg:orig_category":"Loter\u00cda Y T\u00d3mbola",
    "sg:phone":"+34 938 73 66 67",
    "sg:postcode":"08242",
    "sg:province":"Barcelona",
    "wof:name":"Dorado Rosado Antonio",
    "wof:placetype":"venue"
},
  "geometry": {"coordinates":[1.8203140497,41.7291069031],"type":"Point"}
}