{
  "type": "Feature",
  "properties": {
    "iso:country":"ES",
    "sg:address":"Joaquin Sorolla, 58",
    "sg:city":"Rivas Vaciamadrid",
    "sg:orig_category":"Centros Empresariales",
    "sg:phone":"+34 916 66 90 53",
    "sg:postcode":"28529",
    "sg:province":"Madrid",
    "wof:name":"Chains & Sprockets S.l.",
    "wof:placetype":"venue"
},
  "geometry": {"coordinates":[-3.5346150398,40.3461990356],"type":"Point"}
}