{
  "type": "Feature",
  "properties": {
    "iso:country":"ES",
    "sg:address":"Calle de Besolla, 7",
    "sg:city":"Madrid",
    "sg:orig_category":"Asociaciones Humanitarias, De Cooperaci\u00d3n, De Acci\u00d3n Social",
    "sg:phone":"+34 914 66 28 45",
    "sg:postcode":"28025",
    "sg:province":"Madrid",
    "wof:name":"Asociacion De Madres Familiares Y Amigos De Drogodependientes",
    "wof:placetype":"venue"
},
  "geometry": {"coordinates":[-3.7356238365,40.3766746521],"type":"Point"}
}