{
  "type": "Feature",
  "properties": {
    "addr:full":"Calle de Huerta Del Marques, 7 Arevalo \u00c1vila 05200",
    "addr:housenumber":"7",
    "addr:postcode":"05200",
    "addr:street":"Calle De Huerta Del Marques",
    "iso:country":"ES",
    "sg:address":"Calle de Huerta Del Marques, 7",
    "sg:city":"Arevalo",
    "sg:orig_category":"Cristaler\u00cdas",
    "sg:phone":"+34 920 30 16 86",
    "sg:postcode":"05200",
    "sg:province":"\u00c1vila",
    "wof:name":"Cristaleria Hermanos Martin Alonso C.b.",
    "wof:placetype":"venue"
},
  "geometry": {"coordinates":[-4.7221188545,41.0559616089],"type":"Point"}
}