{
  "type": "Feature",
  "properties": {
    "addr:full":"Carrer de Bernat Vilar, 18 Olot Girona 17800",
    "addr:housenumber":"18",
    "addr:postcode":"17800",
    "addr:street":"Carrer De Bernat Vilar",
    "iso:country":"ES",
    "sg:address":"Carrer de Bernat Vilar, 18",
    "sg:city":"Olot",
    "sg:orig_category":"Cr\u00cda De Animales",
    "sg:phone":"+34 972 27 26 39",
    "sg:postcode":"17800",
    "sg:province":"Girona",
    "wof:name":"Juscafresa Estarriola Josefina",
    "wof:placetype":"venue"
},
  "geometry": {"coordinates":[2.4828059673,42.1833190918],"type":"Point"}
}