{
  "type": "Feature",
  "properties": {
    "addr:full":"Avda Francisco La Roche, 45 Santa Cruz De Tenerife Santa Cruz De Tenerife 38001",
    "addr:housenumber":"45",
    "addr:postcode":"38001",
    "addr:street":"Avda Francisco La Roche",
    "iso:country":"ES",
    "sg:address":"Avda Francisco La Roche, 45",
    "sg:city":"Santa Cruz De Tenerife",
    "sg:orig_category":"Ingenier\u00cda, Centros De Estudios (diversos)",
    "sg:phone":"+34 922 27 97 43",
    "sg:postcode":"38001",
    "sg:province":"Santa Cruz De Tenerife",
    "wof:name":"Perez Ortega Jose Maria",
    "wof:placetype":"venue"
},
  "geometry": {"coordinates":[-16.2449493408,28.4773406982],"type":"Point"}
}