{
  "type": "Feature",
  "properties": {
    "addr:full":"Calle de Doctor Gomez Ferrer, 4 Onda Castell\u00f3n 12200",
    "addr:housenumber":"4",
    "addr:postcode":"12200",
    "addr:street":"Calle De Doctor Gomez Ferrer;Castello\u0301N",
    "iso:country":"ES",
    "sg:address":"Calle de Doctor Gomez Ferrer, 4",
    "sg:city":"Onda",
    "sg:orig_category":"Mec\u00c1nico Del Autom\u00d3vil",
    "sg:phone":"+34 964 60 05 62",
    "sg:postcode":"12200",
    "sg:province":"Castell\u00f3n",
    "wof:name":"Herrera Garcia Pedro",
    "wof:placetype":"venue"
},
  "geometry": {"coordinates":[-0.2663519979,39.965221405],"type":"Point"}
}