{
  "type": "Feature",
  "properties": {
    "addr:full":"C/ Alvarez De Castro, 93 Banyoles Girona 17820",
    "addr:housenumber":"93",
    "addr:postcode":"17820",
    "addr:street":"C / Alvarez De Castro",
    "iso:country":"ES",
    "sg:address":"C/ Alvarez De Castro, 93",
    "sg:city":"Banyoles",
    "sg:orig_category":"Comercio, Reparaci\u00d3n De Motocicletas, Bicicletas Y Piezas Sueltas",
    "sg:phone":"+34 972 57 02 61",
    "sg:postcode":"17820",
    "sg:province":"Girona",
    "wof:name":"Taller J. J. Domenech S. L.",
    "wof:placetype":"venue"
},
  "geometry": {"coordinates":[2.7670350075,42.1157073975],"type":"Point"}
}