{
  "type": "Feature",
  "properties": {
    "addr:full":"Calle de Puerto Escondido, 4 Santa Cruz De Tenerife Santa Cruz De Tenerife 38002",
    "addr:housenumber":"4",
    "addr:postcode":"38002",
    "addr:street":"Calle De Puerto Escondido",
    "iso:country":"ES",
    "sg:address":"Calle de Puerto Escondido, 4",
    "sg:city":"Santa Cruz De Tenerife",
    "sg:orig_category":"Ropa Para Se\u00d1oras (al Por Menor)",
    "sg:phone":"+34 922 29 37 14",
    "sg:postcode":"38002",
    "sg:province":"Santa Cruz De Tenerife",
    "wof:name":"Mario Boutique S.l.",
    "wof:placetype":"venue"
},
  "geometry": {"coordinates":[-16.2522563934,28.4704971313],"type":"Point"}
}