{
  "type": "Feature",
  "properties": {
    "iso:country":"ES",
    "sg:address":"Carrer de Emporda, 7",
    "sg:city":"Granollers",
    "sg:orig_category":"Electricidad: Equipos Industriales, Componentes (fabricaci\u00d3n)",
    "sg:phone":"+34 938 40 45 68",
    "sg:postcode":"08403",
    "sg:province":"Barcelona",
    "wof:name":"Universal Productos Electricos S. A.",
    "wof:placetype":"venue"
},
  "geometry": {"coordinates":[2.273966074,41.5941314697],"type":"Point"}
}