{
  "type": "Feature",
  "properties": {
    "iso:country":"ES",
    "sg:address":"Calle de Sierra Elvira, 15",
    "sg:city":"Dos Hermanas",
    "sg:orig_category":"Molduras, Junquillos, Listones Y Molduras Perforadas",
    "sg:phone":"+34 954 72 21 80",
    "sg:postcode":"41700",
    "sg:province":"Sevilla",
    "wof:name":"Rivera Paez Francisco",
    "wof:placetype":"venue"
},
  "geometry": {"coordinates":[-5.910545826,37.2903633118],"type":"Point"}
}