{
  "type": "Feature",
  "properties": {
    "addr:full":"Calle de Sara Martin, 14 Tudela Duero Valladolid 47320",
    "addr:housenumber":"14;duero",
    "addr:postcode":"47320",
    "addr:street":"Calle De Sara Martin",
    "iso:country":"ES",
    "sg:address":"Calle de Sara Martin, 14",
    "sg:city":"Tudela Duero",
    "sg:orig_category":"Promotores Constructores",
    "sg:phone":"+34 983 52 24 26",
    "sg:postcode":"47320",
    "sg:province":"Valladolid",
    "wof:name":"Arias Barrientos Desiderio",
    "wof:placetype":"venue"
},
  "geometry": {"coordinates":[-4.5873208046,41.5887489319],"type":"Point"}
}