{
  "type": "Feature",
  "properties": {
    "iso:country":"ES",
    "sg:address":"Carr Mar, 4",
    "sg:city":"Portbou",
    "sg:orig_category":"Florister\u00cdas",
    "sg:phone":"+34 972 12 50 50",
    "sg:postcode":"17497",
    "sg:province":"Girona",
    "wof:name":"Gonzalez Bosch Alicia",
    "wof:placetype":"venue"
},
  "geometry": {"coordinates":[3.1483902931,42.4037666321],"type":"Point"}
}