{
  "type": "Feature",
  "properties": {
    "iso:country":"ES",
    "sg:address":"Carrer de Nemesi Valls, 58",
    "sg:city":"Barbera Valles",
    "sg:orig_category":"Peluquer\u00cdas, Peluquer\u00cda Mixta",
    "sg:phone":"+34 937 18 57 57",
    "sg:postcode":"08210",
    "sg:province":"Barcelona",
    "wof:name":"Torres-lopez Peluqueros S.l.",
    "wof:placetype":"venue"
},
  "geometry": {"coordinates":[2.1284589767,41.516658783],"type":"Point"}
}