{
  "type": "Feature",
  "properties": {
    "addr:full":"Calle de San Miguel, 19 Villamayor Salamanca 37185",
    "addr:housenumber":"19",
    "addr:postcode":"37185",
    "addr:street":"Calle De San Miguel",
    "iso:country":"ES",
    "sg:address":"Calle de San Miguel, 19",
    "sg:city":"Villamayor",
    "sg:orig_category":"Alimentaci\u00d3n General (al Por Menor)",
    "sg:phone":"+34 923 28 64 25",
    "sg:postcode":"37185",
    "sg:province":"Salamanca",
    "wof:name":"Zarzoso Sanchon Maria Luisa",
    "wof:placetype":"venue"
},
  "geometry": {"coordinates":[-5.6957130432,40.9985618591],"type":"Point"}
}