{
  "type": "Feature",
  "properties": {
    "iso:country":"ES",
    "sg:address":"Calle de Rios Rosas, 53",
    "sg:city":"Madrid",
    "sg:orig_category":"Cuidado Del Cabello",
    "sg:phone":"+34 915 53 72 08",
    "sg:postcode":"28003",
    "sg:province":"Madrid",
    "wof:name":"Centro Internacional De Diagnostico Y Tratamiento Capilar S.a.",
    "wof:placetype":"venue"
},
  "geometry": {"coordinates":[-3.6963999271,40.4418907166],"type":"Point"}
}