{
  "type": "Feature",
  "properties": {
    "iso:country":"ES",
    "sg:address":"Calle de Vazquez De Menchaca, 12",
    "sg:city":"Valladolid",
    "sg:orig_category":"Ropa Para Se\u00d1oras Y Caballeros (al Por Menor)",
    "sg:phone":"+34 983 23 45 01",
    "sg:postcode":"47008",
    "sg:province":"Valladolid",
    "wof:name":"Hnos.cuadrado Garcia C.b.",
    "wof:placetype":"venue"
},
  "geometry": {"coordinates":[-4.7356629372,41.6190643311],"type":"Point"}
}