{
  "type": "Feature",
  "properties": {
    "iso:country":"ES",
    "sg:address":"Calle de Carrasqueta, La, 9",
    "sg:city":"Valencia",
    "sg:orig_category":"Peluquer\u00cdas, Peluquer\u00cda Mixta",
    "sg:phone":"+34 963 48 97 01",
    "sg:postcode":"46015",
    "sg:province":"Valencia",
    "wof:name":"Sanchis Estevez Pilar",
    "wof:placetype":"venue"
},
  "geometry": {"coordinates":[-0.3958399892,39.4937515259],"type":"Point"}
}