{
  "type": "Feature",
  "properties": {
    "addr:full":"Calle de Alcantarilla, 16 Mota Cuervo Cuenca 16630",
    "addr:housenumber":"16",
    "addr:postcode":"16630",
    "addr:street":"Calle De Alcantarilla",
    "iso:country":"ES",
    "sg:address":"Calle de Alcantarilla, 16",
    "sg:city":"Mota Cuervo",
    "sg:orig_category":"Electricidad: Instaladores",
    "sg:phone":"+34 967 18 21 52",
    "sg:postcode":"16630",
    "sg:province":"Cuenca",
    "wof:name":"Chicotes Jimenez Juan",
    "wof:placetype":"venue"
},
  "geometry": {"coordinates":[-2.8624360561,39.4991874695],"type":"Point"}
}