{
  "type": "Feature",
  "properties": {
    "addr:full":"Carr Combat, 39 Cervera Lleida 25200",
    "addr:housenumber":"39",
    "addr:postcode":"25200",
    "addr:street":"Carr Combat",
    "iso:country":"ES",
    "sg:address":"Carr Combat, 39",
    "sg:city":"Cervera",
    "sg:orig_category":"Panader\u00cdas, Panader\u00cdas",
    "sg:phone":"+34 973 53 07 53",
    "sg:postcode":"25200",
    "sg:province":"Lleida",
    "wof:name":"Colom Rosich Elvira",
    "wof:placetype":"venue"
},
  "geometry": {"coordinates":[1.2714600563,41.6712989807],"type":"Point"}
}