{
  "type": "Feature",
  "properties": {
    "addr:full":"Avda Juan Xxiii, S/n Bosque C\u00e1diz 11670",
    "addr:housenumber":"s / n",
    "addr:postcode":"11670",
    "addr:street":"Avda Juan Xxiii;Ca\u0301Diz",
    "iso:country":"ES",
    "sg:address":"Avda Juan Xxiii, S/n",
    "sg:city":"Bosque",
    "sg:classifiers":[
        {
            "category":"Communications",
            "type":"Services"
        }
    ],
    "sg:phone":"+34 956 72 70 78",
    "sg:postcode":"11670",
    "sg:province":"C\u00e1diz",
    "sg:tags":[
        "televisiones",
        "y",
        "radio"
    ],
    "wof:name":"Ayuntamiento De El Bosque",
    "wof:placetype":"venue"
},
  "geometry": {"coordinates":[-5.5049767494,36.7575492859],"type":"Point"}
}