{
  "type": "Feature",
  "properties": {
    "iso:country":"ES",
    "sg:address":"Calle de Lenguas, 16",
    "sg:city":"Madrid",
    "sg:orig_category":"Agentes Y Bufetes De Negocio",
    "sg:phone":"+34 917 23 05 69",
    "sg:postcode":"28021",
    "sg:province":"Madrid",
    "wof:name":"Giroarte",
    "wof:placetype":"venue"
},
  "geometry": {"coordinates":[-3.7042651176,40.3428688049],"type":"Point"}
}