{
  "type": "Feature",
  "properties": {
    "iso:country":"ES",
    "sg:address":"Calle de Hilera, 1",
    "sg:city":"Malaga",
    "sg:orig_category":"Inform\u00c1tica, Ofim\u00c1tica (estudios, Asesor\u00cda, Ingenier\u00cda, Formaci\u00d3n)",
    "sg:phone":"+34 952 28 36 98",
    "sg:postcode":"29007",
    "sg:province":"M\u00e1laga",
    "sg:website":"www.chipsur.com",
    "wof:name":"Chipsur Sistemas Informaticos S.l.",
    "wof:placetype":"venue"
},
  "geometry": {"coordinates":[-4.4264988899,36.7176971436],"type":"Point"}
}