{
  "type": "Feature",
  "properties": {
    "addr:full":"Carrer de Mont Perdut, 129 Terrassa Barcelona 08227",
    "addr:housenumber":"129",
    "addr:postcode":"08227",
    "addr:street":"Carrer De Mont Perdut",
    "iso:country":"ES",
    "sg:address":"Carrer de Mont Perdut, 129",
    "sg:city":"Terrassa",
    "sg:orig_category":"Impresiones Sobre Tela",
    "sg:phone":"+34 937 31 10 80",
    "sg:postcode":"08227",
    "sg:province":"Barcelona",
    "wof:name":"Nakamoto Arakaki German",
    "wof:placetype":"venue"
},
  "geometry": {"coordinates":[2.0394060612,41.5710906982],"type":"Point"}
}