{
  "type": "Feature",
  "properties": {
    "addr:full":"Calle de Maria Zayas, 7 Madrid Madrid 28039",
    "addr:housenumber":"7",
    "addr:postcode":"madrid;28039",
    "addr:street":"Calle De Maria Zayas",
    "iso:country":"ES",
    "sg:address":"Calle de Maria Zayas, 7",
    "sg:city":"Madrid",
    "sg:orig_category":"Servicios De Telecomunicaciones",
    "sg:phone":"+34 914 25 05 40",
    "sg:postcode":"28039",
    "sg:province":"Madrid",
    "wof:name":"Telecom & Tecnology Investements S.l.",
    "wof:placetype":"venue"
},
  "geometry": {"coordinates":[-3.7009541988,40.4592781067],"type":"Point"}
}