{
  "type": "Feature",
  "properties": {
    "iso:country":"ES",
    "sg:address":"Calle de Arroyada, 72",
    "sg:city":"Sonseca",
    "sg:orig_category":"Abogados",
    "sg:phone":"+34 925 38 04 92",
    "sg:postcode":"45100",
    "sg:province":"Toledo",
    "wof:name":"Rodriguez Gomez-arevalillo Teodoro",
    "wof:placetype":"venue"
},
  "geometry": {"coordinates":[-3.9731535912,39.6777420044],"type":"Point"}
}