{
  "type": "Feature",
  "properties": {
    "addr:full":"Carr Nou, 33 Armentera Girona 17472",
    "addr:housenumber":"33",
    "addr:postcode":"17472",
    "addr:street":"Carr Nou",
    "iso:country":"ES",
    "sg:address":"Carr Nou, 33",
    "sg:city":"Armentera",
    "sg:orig_category":"Electricidad Veh\u00cdculo",
    "sg:phone":"+34 972 52 01 46",
    "sg:postcode":"17472",
    "sg:province":"Girona",
    "wof:name":"Costa Bague Josep",
    "wof:placetype":"venue"
},
  "geometry": {"coordinates":[3.0744850636,42.1720161438],"type":"Point"}
}