{
  "type": "Feature",
  "properties": {
    "iso:country":"ES",
    "sg:address":"Ciudad Transporte, 172",
    "sg:city":"Castello Plana",
    "sg:orig_category":"Autob\u00das (explotaci\u00d3n Y Servicios De)",
    "sg:phone":"+34 964 22 10 00",
    "sg:postcode":"12006",
    "sg:province":"Castell\u00f3n",
    "wof:name":"Autocares Meseguer S.a.",
    "wof:placetype":"venue"
},
  "geometry": {"coordinates":[-0.0360242017,39.9860687256],"type":"Point"}
}