{
  "type": "Feature",
  "properties": {
    "iso:country":"ES",
    "sg:address":"Calle de Navarra, 15",
    "sg:city":"Dos Hermanas",
    "sg:orig_category":"Asociaciones Y Clubs Deportivos",
    "sg:phone":"+34 955 67 60 99",
    "sg:postcode":"41700",
    "sg:province":"Sevilla",
    "wof:name":"Asociacion Pe\u00f1a Madridista Juan Gomez Juanito",
    "wof:placetype":"venue"
},
  "geometry": {"coordinates":[-5.9241881371,37.2769241333],"type":"Point"}
}