{
  "type": "Feature",
  "properties": {
    "iso:country":"ES",
    "sg:address":"Carrer de Platja, S/n",
    "sg:city":"Peguera",
    "sg:orig_category":"Supermercados Y Hipermercados",
    "sg:phone":"+34 971 68 60 46",
    "sg:postcode":"07160",
    "sg:province":"Islas Baleares",
    "wof:name":"Supermercados Superdeal, S.l.",
    "wof:placetype":"venue"
},
  "geometry": {"coordinates":[2.4549660683,39.5361824036],"type":"Point"}
}