{
  "type": "Feature",
  "properties": {
    "iso:country":"ES",
    "sg:address":"Calle de Tilos (los), S/n",
    "sg:city":"Teruel",
    "sg:orig_category":"Centros De Educaci\u00d3n Especial",
    "sg:phone":"+34 978 60 03 01",
    "sg:postcode":"44002",
    "sg:province":"Teruel",
    "wof:name":"Ceip La Fuenfresca",
    "wof:placetype":"venue"
},
  "geometry": {"coordinates":[-1.0956740379,40.3293113708],"type":"Point"}
}