{
  "type": "Feature",
  "properties": {
    "iso:country":"ES",
    "sg:address":"Calle de Terraza, S/n",
    "sg:city":"Estepona",
    "sg:orig_category":"Panader\u00cdas, Panader\u00cdas",
    "sg:phone":"+34 952 80 56 83",
    "sg:postcode":"29680",
    "sg:province":"M\u00e1laga",
    "wof:name":"Rualo Carre\u00f1o Alfonso",
    "wof:placetype":"venue"
},
  "geometry": {"coordinates":[-5.1449451447,36.4258232117],"type":"Point"}
}