{
  "type": "Feature",
  "properties": {
    "iso:country":"ES",
    "sg:address":"Plaz Espa\u00d1a, S/n",
    "sg:city":"Motril",
    "sg:orig_category":"Administraciones Regionales, Departamentales Y Locales",
    "sg:phone":"+34 958 83 83 01",
    "sg:postcode":"18600",
    "sg:province":"Granada",
    "sg:website":"www.motril.es",
    "wof:name":"Ayuntamiento De Motril",
    "wof:placetype":"venue"
},
  "geometry": {"coordinates":[-3.480134964,36.7527770996],"type":"Point"}
}