{
  "type": "Feature",
  "properties": {
    "iso:country":"ES",
    "sg:address":"Rua Paxari\u00d1os (dos), 28",
    "sg:city":"Lugo",
    "sg:orig_category":"Agencias Y Agentes Comerciales, Representantes",
    "sg:phone":"+34 982 22 06 93",
    "sg:postcode":"27002",
    "sg:province":"Lugo",
    "wof:name":"Perez Fari\u00f1as Delfin",
    "wof:placetype":"venue"
},
  "geometry": {"coordinates":[-7.5491957664,43.00963974],"type":"Point"}
}