{
  "type": "Feature",
  "properties": {
    "iso:country":"ES",
    "sg:address":"Carrer de Pujades, 181",
    "sg:city":"Barcelona",
    "sg:orig_category":"Peluqueros: De Se\u00d1oras",
    "sg:phone":"+34 934 85 49 01",
    "sg:postcode":"08005",
    "sg:province":"Barcelona",
    "wof:name":"Peluquerias Maria Garcia S.l.",
    "wof:placetype":"venue"
},
  "geometry": {"coordinates":[2.201157093,41.4022216797],"type":"Point"}
}