{
  "type": "Feature",
  "properties": {
    "iso:country":"ES",
    "sg:address":"Poli Pol.indust. Cami Dels Frares, 4",
    "sg:city":"Lleida",
    "sg:orig_category":"Material Y Herramientas Agr\u00cdcolas",
    "sg:phone":"+34 973 21 04 34",
    "sg:postcode":"25191",
    "sg:province":"Lleida",
    "sg:website":"www.eurorecambicconline.es",
    "wof:name":"Eurorecanvi S.c.c.l.",
    "wof:placetype":"venue"
},
  "geometry": {"coordinates":[0.6831650138,41.5832138062],"type":"Point"}
}