{
  "type": "Feature",
  "properties": {
    "iso:country":"ES",
    "sg:address":"Calle de Puerta De Abajo, 59",
    "sg:city":"Alpedrete",
    "sg:orig_category":"Fabricaci\u00d3n, Distribuci\u00d3n De Material Para La Climatizaci\u00d3n, Aireaci\u00d3n Y Ventilaci\u00d3n",
    "sg:phone":"+34 918 57 03 92",
    "sg:postcode":"28430",
    "sg:province":"Madrid",
    "sg:website":"www.serviconsierra.com",
    "wof:name":"Servicom Sierra S.l.",
    "wof:placetype":"venue"
},
  "geometry": {"coordinates":[-4.0123682022,40.6605491638],"type":"Point"}
}