{
  "type": "Feature",
  "properties": {
    "iso:country":"ES",
    "sg:address":"Ziku\u00d1aga Bailara, 57",
    "sg:city":"Zikuinaga",
    "sg:orig_category":"Alumbrados",
    "sg:phone":"+34 943 55 75 13",
    "sg:postcode":"20120",
    "sg:province":"Guip\u00f9zcoa",
    "wof:name":"A.b.s. Iluminacion S.l.",
    "wof:placetype":"venue"
},
  "geometry": {"coordinates":[-1.979829,43.264751],"type":"Point"}
}