{
  "type": "Feature",
  "properties": {
    "iso:country":"ES",
    "sg:address":"Calle de Fuego (del), 31",
    "sg:city":"Alcobendas",
    "sg:orig_category":"Guarder\u00cdas",
    "sg:phone":"+34 916 63 70 20",
    "sg:postcode":"28100",
    "sg:province":"Madrid",
    "wof:name":"Tortosa Segura Noe Jesus",
    "wof:placetype":"venue"
},
  "geometry": {"coordinates":[-3.6352310181,40.5430603027],"type":"Point"}
}