{
  "type": "Feature",
  "properties": {
    "addr:full":"Calle de Motxotekale, 5 Llodio \u00c1lava 01400",
    "addr:housenumber":"5",
    "addr:postcode":"01400",
    "addr:street":"Calle De Motxotekale",
    "iso:country":"ES",
    "sg:address":"Calle de Motxotekale, 5",
    "sg:city":"Llodio",
    "sg:orig_category":"Mercer\u00cda, Lencer\u00cda (al Por Menor)",
    "sg:phone":"+34 946 72 58 24",
    "sg:postcode":"01400",
    "sg:province":"\u00c1lava",
    "wof:name":"Mayo Gonzalez Maria De Los Angeles",
    "wof:placetype":"venue"
},
  "geometry": {"coordinates":[-2.9632759094,43.145488739],"type":"Point"}
}