{
  "type": "Feature",
  "properties": {
    "iso:country":"ES",
    "sg:address":"Calle de Iparragirre, 2",
    "sg:city":"Basauri",
    "sg:orig_category":"Cl\u00cdnicas Dentales",
    "sg:phone":"+34 944 05 96 23",
    "sg:postcode":"48970",
    "sg:province":"Vizcaya",
    "wof:name":"Clinica Dental Bidebieta, C.b.",
    "wof:placetype":"venue"
},
  "geometry": {"coordinates":[-2.8930900097,43.2371673584],"type":"Point"}
}