{
  "type": "Feature",
  "properties": {
    "addr:full":"Pol Ind San Gregorio, S/n Pozoblanco C\u00f3rdoba 14400",
    "addr:housenumber":"s / n",
    "addr:postcode":"14400",
    "addr:street":"San Gregorio",
    "iso:country":"ES",
    "sg:address":"Pol Ind San Gregorio, S/n",
    "sg:city":"Pozoblanco",
    "sg:orig_category":"Art\u00cdculos De Madera (fabricaci\u00d3n Y Al Por Mayor)",
    "sg:phone":"+34 957 77 20 71",
    "sg:postcode":"14400",
    "sg:province":"C\u00f3rdoba",
    "wof:name":"Francisco Jurado Olmo S.l.",
    "wof:placetype":"venue"
},
  "geometry": {"coordinates":[-4.8541440964,38.3830947876],"type":"Point"}
}