{
  "type": "Feature",
  "properties": {
    "addr:full":"Ctra Murcia, S/n Baza Granada 18800",
    "addr:housenumber":"s",
    "addr:postcode":"18800",
    "addr:street":"Ctra Murcia;/ N",
    "iso:country":"ES",
    "sg:address":"Ctra Murcia, S/n",
    "sg:city":"Baza",
    "sg:orig_category":"Ense\u00d1anza Variada",
    "sg:phone":"+34 958 70 36 22",
    "sg:postcode":"18800",
    "sg:province":"Granada",
    "sg:website":"www.fortecnomovil.com",
    "wof:name":"I D Fortecnomovil E. S.l.",
    "wof:placetype":"venue"
},
  "geometry": {"coordinates":[-2.7643990517,37.4935264587],"type":"Point"}
}