{
  "type": "Feature",
  "properties": {
    "iso:country":"ES",
    "sg:address":"Calle de Pe\u00d1a Primera, 24",
    "sg:city":"Salamanca",
    "sg:orig_category":"Edici\u00d3n De Diarios, Revistas, Boletines",
    "sg:phone":"+34 923 21 37 73",
    "sg:postcode":"37002",
    "sg:province":"Salamanca",
    "wof:name":"Tribuna Universitaria S.l.",
    "wof:placetype":"venue"
},
  "geometry": {"coordinates":[-5.6665110588,40.9670181274],"type":"Point"}
}