{
  "type": "Feature",
  "properties": {
    "iso:country":"ES",
    "sg:address":"Calle de Riera, S/n",
    "sg:city":"Cortijos Nuevos",
    "sg:orig_category":"Ense\u00d1anza: Profesiones Art\u00cdsticas",
    "sg:phone":"+34 953 49 61 15",
    "sg:postcode":"23293",
    "sg:province":"Ja\u00e9n",
    "wof:name":"Lumbreras Perez Pedro Jose",
    "wof:placetype":"venue"
},
  "geometry": {"coordinates":[-2.7253789902,38.2469863892],"type":"Point"}
}