{
  "type": "Feature",
  "properties": {
    "iso:country":"ES",
    "sg:address":"Calle de Concordia, 2",
    "sg:city":"Torrevieja",
    "sg:orig_category":"Administradores De Bienes Y Delegados De Comunidades De Propietarios",
    "sg:phone":"+34 965 71 04 04",
    "sg:postcode":"03180",
    "sg:province":"Alicante",
    "wof:name":"Harr Y Lange C.b",
    "wof:placetype":"venue"
},
  "geometry": {"coordinates":[-0.6805320978,37.9783782959],"type":"Point"}
}