{
  "type": "Feature",
  "properties": {
    "addr:full":"Send Valentin De Foronda, 5 Vitoria-gasteiz \u00c1lava 01010",
    "addr:housenumber":"5",
    "addr:postcode":"01010",
    "addr:street":"Send Valentin De Foronda",
    "iso:country":"ES",
    "sg:address":"Send Valentin De Foronda, 5",
    "sg:city":"Vitoria-gasteiz",
    "sg:orig_category":"Cajas De Ahorro",
    "sg:phone":"+34 945 21 71 20",
    "sg:postcode":"01010",
    "sg:province":"\u00c1lava",
    "wof:name":"Caja De Ahorros De Vitoria Y Alava",
    "wof:placetype":"venue"
},
  "geometry": {"coordinates":[-2.6998019218,42.8553733826],"type":"Point"}
}