{
  "type": "Feature",
  "properties": {
    "iso:country":"ES",
    "sg:address":"Carr Literato Azorin, 22",
    "sg:city":"Benetusser",
    "sg:orig_category":"Molduras, Junquillos, Listones Y Molduras Perforadas",
    "sg:phone":"+34 963 76 22 94",
    "sg:postcode":"46910",
    "sg:province":"Valencia",
    "wof:name":"Gomez Garcia Reyes",
    "wof:placetype":"venue"
},
  "geometry": {"coordinates":[-0.398198992,39.4188613892],"type":"Point"}
}