{
  "type": "Feature",
  "properties": {
    "iso:country":"ES",
    "sg:address":"Cami Ratera, S/n",
    "sg:city":"Alguaire",
    "sg:orig_category":"Cr\u00cda De Animales",
    "sg:phone":"+34 973 75 61 92",
    "sg:postcode":"25125",
    "sg:province":"Lleida",
    "wof:name":"Domingo Pu\u00f1et Alberto",
    "wof:placetype":"venue"
},
  "geometry": {"coordinates":[0.5873860121,41.7410583496],"type":"Point"}
}