{
  "type": "Feature",
  "properties": {
    "addr:full":"C/ Sant Quinti, 47 Ribes Freser Girona 17534",
    "addr:housenumber":"47",
    "addr:postcode":"17534",
    "addr:street":"C / Sant Quinti",
    "iso:country":"ES",
    "sg:address":"C/ Sant Quinti, 47",
    "sg:city":"Ribes Freser",
    "sg:orig_category":"Carnicer\u00cdas, Carnicer\u00cdas",
    "sg:phone":"+34 972 72 71 38",
    "sg:postcode":"17534",
    "sg:province":"Girona",
    "wof:name":"Anglada Marti Magdalena",
    "wof:placetype":"venue"
},
  "geometry": {"coordinates":[2.2073082924,42.265335083],"type":"Point"}
}