{
  "type": "Feature",
  "properties": {
    "addr:full":"Calle de Orotava La, 38 Malaga M\u00e1laga 29006",
    "addr:housenumber":"38",
    "addr:postcode":"29006",
    "addr:street":"Calle De Orotava La;Ma\u0301Laga",
    "iso:country":"ES",
    "sg:address":"Calle de Orotava La, 38",
    "sg:city":"Malaga",
    "sg:orig_category":"Importaci\u00d3n",
    "sg:phone":"+34 952 33 60 93",
    "sg:postcode":"29006",
    "sg:province":"M\u00e1laga",
    "wof:name":"Salfran Import S.l.",
    "wof:placetype":"venue"
},
  "geometry": {"coordinates":[-4.4767379761,36.7029304504],"type":"Point"}
}