{
  "type": "Feature",
  "properties": {
    "addr:full":"Calle de Joaquin Blume, 8 Torrejon Ardoz Madrid 28850",
    "addr:housenumber":"8",
    "addr:postcode":"28850",
    "addr:street":"Calle De Joaquin Blume",
    "iso:country":"ES",
    "sg:address":"Calle de Joaquin Blume, 8",
    "sg:city":"Torrejon Ardoz",
    "sg:orig_category":"Peluquer\u00cdas, Peluquer\u00cda Mixta",
    "sg:phone":"+34 916 56 33 99",
    "sg:postcode":"28850",
    "sg:province":"Madrid",
    "wof:name":"Gomez Saiz Judit",
    "wof:placetype":"venue"
},
  "geometry": {"coordinates":[-3.4703090191,40.4435119629],"type":"Point"}
}