{
  "type": "Feature",
  "properties": {
    "addr:full":"Avda Novelda, 28 Alacant Alicante 03...",
    "addr:housenumber":"28;03 ...",
    "addr:street":"Avda Novelda;Alicante",
    "iso:country":"ES",
    "sg:address":"Avda Novelda, 28",
    "sg:city":"Alacant",
    "sg:orig_category":"Organizaciones Internacionales",
    "sg:phone":"+34 965 25 41 41",
    "sg:postcode":"03...",
    "sg:province":"Alicante",
    "wof:name":"Cruz Roja Espa\u00d1ola",
    "wof:placetype":"venue"
},
  "geometry": {"coordinates":[-0.4921140075,38.3610649109],"type":"Point"}
}