{
  "type": "Feature",
  "properties": {
    "iso:country":"ES",
    "sg:address":"Calle de Campoamor, 93",
    "sg:city":"Torrevieja",
    "sg:orig_category":"Ense\u00d1anza Variada",
    "sg:phone":"+34 965 71 80 05",
    "sg:postcode":"03180",
    "sg:province":"Alicante",
    "wof:name":"Didactron Informatica S.l.u.",
    "wof:placetype":"venue"
},
  "geometry": {"coordinates":[-0.6852265,37.9786453247],"type":"Point"}
}