{
  "type": "Feature",
  "properties": {
    "addr:full":"Praj Ledua - A, S/n Novelda Alicante 03660",
    "addr:housenumber":"s / n",
    "addr:postcode":"03660",
    "iso:country":"ES",
    "sg:address":"Praj Ledua - A, S/n",
    "sg:city":"Novelda",
    "sg:orig_category":"Explotaci\u00d3n De Canteras",
    "sg:phone":"+34 965 60 48 60",
    "sg:postcode":"03660",
    "sg:province":"Alicante",
    "wof:name":"Levantina Y Asociados De Minerales S.a.",
    "wof:placetype":"venue"
},
  "geometry": {"coordinates":[-0.7638189793,38.3825035095],"type":"Point"}
}