{
  "type": "Feature",
  "properties": {
    "addr:full":"Ctra Terrassa, 389 Sabadell Barcelona 08205",
    "addr:housenumber":"389",
    "addr:postcode":"08205",
    "addr:street":"Ctra Terrassa",
    "iso:country":"ES",
    "sg:address":"Ctra Terrassa, 389",
    "sg:city":"Sabadell",
    "sg:orig_category":"\u00d3ptica: Instrumentos (fabricaci\u00d3n)",
    "sg:phone":"+34 937 27 67 71",
    "sg:postcode":"08205",
    "sg:province":"Barcelona",
    "wof:name":"Mu\u00f1oz Arca Dolors",
    "wof:placetype":"venue"
},
  "geometry": {"coordinates":[2.0842700005,41.5486488342],"type":"Point"}
}