{
  "type": "Feature",
  "properties": {
    "addr:full":"Calle de Juan Bautista Uriarte, 10 Kurtzea Vizcaya 48960",
    "addr:housenumber":"10",
    "addr:postcode":"48960",
    "addr:street":"Calle De Juan Bautista Uriarte",
    "iso:country":"ES",
    "sg:address":"Calle de Juan Bautista Uriarte, 10",
    "sg:city":"Kurtzea",
    "sg:orig_category":"Abogados",
    "sg:phone":"+34 944 56 38 12",
    "sg:postcode":"48960",
    "sg:province":"Vizcaya",
    "wof:name":"Iturriaga Sagarminaga Luis",
    "wof:placetype":"venue"
},
  "geometry": {"coordinates":[-2.8466889858,43.229850769],"type":"Point"}
}