{
  "type": "Feature",
  "properties": {
    "iso:country":"ES",
    "sg:address":"Calle de Ca\u00d1ada Real, 35",
    "sg:city":"Alovera",
    "sg:orig_category":"Molduras, Junquillos, Listones Y Molduras Perforadas",
    "sg:phone":"+34 949 29 72 46",
    "sg:postcode":"19208",
    "sg:province":"Guadalajara",
    "wof:name":"Rodriguez Luis Fernando",
    "wof:placetype":"venue"
},
  "geometry": {"coordinates":[-3.2432780266,40.5943756104],"type":"Point"}
}