{
  "type": "Feature",
  "properties": {
    "iso:country":"ES",
    "sg:address":"Avda Alejand. Del Castillo, 59",
    "sg:city":"San Fernando",
    "sg:orig_category":"Material Y Suministros Para Dentistas, Cirujanos",
    "sg:phone":"+34 928 73 04 79",
    "sg:postcode":"35100",
    "sg:province":"Las Palmas",
    "wof:name":"Clinica Pio Xii S.l.",
    "wof:placetype":"venue"
},
  "geometry": {"coordinates":[-15.5842504501,28.0904903412],"type":"Point"}
}