{
  "type": "Feature",
  "properties": {
    "iso:country":"ES",
    "sg:address":"Av Flors, 27",
    "sg:city":"Sitges",
    "sg:orig_category":"Agencias Y Agentes Comerciales, Representantes",
    "sg:phone":"+34 938 94 27 02",
    "sg:postcode":"08870",
    "sg:province":"Barcelona",
    "wof:name":"Nebleza Paco Jose Juan",
    "wof:placetype":"venue"
},
  "geometry": {"coordinates":[1.8073170185,41.23960495],"type":"Point"}
}