{
  "type": "Feature",
  "properties": {
    "iso:country":"ES",
    "sg:address":"Calle de Cuerva, 6",
    "sg:city":"Sonseca",
    "sg:orig_category":"Asesor\u00cda Sobre Comunicaci\u00d3n De Empresas",
    "sg:phone":"+34 925 38 21 34",
    "sg:postcode":"45100",
    "sg:province":"Toledo",
    "wof:name":"Martin Y Ortiz Abogados S.l.",
    "wof:placetype":"venue"
},
  "geometry": {"coordinates":[-3.9980485439,39.6348075867],"type":"Point"}
}