{
  "type": "Feature",
  "properties": {
    "iso:country":"ES",
    "sg:address":"Avda Venezuela (de), 6",
    "sg:city":"Santa Cruz De Tenerife",
    "sg:orig_category":"Peluqueros: De Se\u00d1oras",
    "sg:phone":"+34 922 22 06 05",
    "sg:postcode":"38007",
    "sg:province":"Santa Cruz De Tenerife",
    "wof:name":"Acosta Noda Isabel",
    "wof:placetype":"venue"
},
  "geometry": {"coordinates":[-16.2706451416,28.4669971466],"type":"Point"}
}