{
  "type": "Feature",
  "properties": {
    "addr:full":"Carrer de Miranda (la), 81 Cornella Llobregat Barcelona 08940",
    "addr:housenumber":"81",
    "addr:postcode":"08940",
    "addr:street":"Carrer De Miranda La",
    "iso:country":"ES",
    "sg:address":"Carrer de Miranda (la), 81",
    "sg:city":"Cornella Llobregat",
    "sg:orig_category":"M\u00c9dicos: Medicina General",
    "sg:phone":"+34 934 71 11 11",
    "sg:postcode":"08940",
    "sg:province":"Barcelona",
    "wof:name":"Llobregat Informedic S.l.",
    "wof:placetype":"venue"
},
  "geometry": {"coordinates":[2.0793309212,41.3601608276],"type":"Point"}
}