{
  "type": "Feature",
  "properties": {
    "iso:country":"ES",
    "sg:address":"Calle de San Francisco, 28",
    "sg:city":"Granadilla Abona",
    "sg:orig_category":"Art\u00cdculos Funerarios (al Por Menor)",
    "sg:phone":"+34 922 77 07 32",
    "sg:postcode":"38600",
    "sg:province":"Santa Cruz De Tenerife",
    "wof:name":"Baltasar Reyes Perez Florentino",
    "wof:placetype":"venue"
},
  "geometry": {"coordinates":[-16.5775032043,28.1246471405],"type":"Point"}
}