{
  "type": "Feature",
  "properties": {
    "addr:full":"Plaz Mayor, 1 Portezuelo C\u00e1ceres 10828",
    "addr:housenumber":"1",
    "addr:postcode":"10828",
    "addr:street":"Plaz Mayor;Ca\u0301Ceres",
    "iso:country":"ES",
    "sg:address":"Plaz Mayor, 1",
    "sg:city":"Portezuelo",
    "sg:orig_category":"Administraciones Regionales, Departamentales Y Locales",
    "sg:phone":"+34 927 30 20 37",
    "sg:postcode":"10828",
    "sg:province":"C\u00e1ceres",
    "wof:name":"Ayuntamiento De Portezuelo",
    "wof:placetype":"venue"
},
  "geometry": {"coordinates":[-6.4755291939,39.8120651245],"type":"Point"}
}