{
  "type": "Feature",
  "properties": {
    "addr:full":"Calle de Alonso Alcala, 3 Alcala Real Ja\u00e9n 23680",
    "addr:housenumber":"3",
    "addr:postcode":"23680",
    "addr:street":"Calle De Alonso Alcala;Jae\u0301N",
    "iso:country":"ES",
    "sg:address":"Calle de Alonso Alcala, 3",
    "sg:city":"Alcala Real",
    "sg:orig_category":"\u00d3ptica: Instrumentos (fabricaci\u00d3n)",
    "sg:phone":"+34 953 58 12 23",
    "sg:postcode":"23680",
    "sg:province":"Ja\u00e9n",
    "wof:name":"Bravo Lupia\u00f1ez Opticos S.l.",
    "wof:placetype":"venue"
},
  "geometry": {"coordinates":[-3.9242637157,37.4640197754],"type":"Point"}
}