{
  "type": "Feature",
  "properties": {
    "addr:full":"Carrer de Salva, 10 Barcelona Barcelona 08004",
    "addr:housenumber":"10",
    "addr:postcode":"08004",
    "addr:street":"Carrer De Salva",
    "iso:country":"ES",
    "sg:address":"Carrer de Salva, 10",
    "sg:city":"Barcelona",
    "sg:orig_category":"Centros Empresariales",
    "sg:phone":"+34 934 42 05 12",
    "sg:postcode":"08004",
    "sg:province":"Barcelona",
    "wof:name":"Adris  Mohammad",
    "wof:placetype":"venue"
},
  "geometry": {"coordinates":[2.1665604115,41.3743934631],"type":"Point"}
}