{
  "type": "Feature",
  "properties": {
    "iso:country":"ES",
    "sg:address":"Carrer de Compositor Pep Ventura, 56",
    "sg:city":"Olot",
    "sg:orig_category":"Fabricaci\u00d3n, Venta De Cuadros, Accesorios Para Enmarcar",
    "sg:phone":"+34 972 26 54 48",
    "sg:postcode":"17800",
    "sg:province":"Girona",
    "wof:name":"Decor Mark Santigosa S.l.",
    "wof:placetype":"venue"
},
  "geometry": {"coordinates":[2.5062360764,42.1924171448],"type":"Point"}
}