{
  "type": "Feature",
  "properties": {
    "iso:country":"ES",
    "sg:address":"Calle de Pimentero, 31",
    "sg:city":"Palmas De Gran Canaria",
    "sg:orig_category":"Mec\u00c1nico Del Autom\u00d3vil",
    "sg:phone":"+34 928 48 09 49",
    "sg:postcode":"35010",
    "sg:province":"Las Palmas",
    "wof:name":"Medina Hernandez Delfin",
    "wof:placetype":"venue"
},
  "geometry": {"coordinates":[-15.451333046,28.1153450012],"type":"Point"}
}