{
  "type": "Feature",
  "properties": {
    "iso:country":"ES",
    "sg:address":"Ctra Terrassa, 91",
    "sg:city":"Rubi",
    "sg:orig_category":"Instalaci\u00d3n, Reparaci\u00d3n De Ascensores Y Montacargas",
    "sg:phone":"+34 936 99 61 52",
    "sg:postcode":"08191",
    "sg:province":"Barcelona",
    "wof:name":"Asba Mantenimientos S.l.",
    "wof:placetype":"venue"
},
  "geometry": {"coordinates":[1.9875522852,41.5271072388],"type":"Point"}
}