{
  "type": "Feature",
  "properties": {
    "addr:full":"Calle de Maestro Falla, 59 Sevilla Sevilla 41006",
    "addr:housenumber":"59",
    "addr:postcode":"41006",
    "addr:street":"Calle De Maestro Falla",
    "iso:country":"ES",
    "sg:address":"Calle de Maestro Falla, 59",
    "sg:city":"Sevilla",
    "sg:orig_category":"Instalaci\u00d3n, Mantenimiento De Porteros Electr\u00d3nicos Y Controles De Acceso",
    "sg:phone":"+34 954 66 32 03",
    "sg:postcode":"41006",
    "sg:province":"Sevilla",
    "wof:name":"Tecnicas Andaluzas De Comunicacion S.l.",
    "wof:placetype":"venue"
},
  "geometry": {"coordinates":[-5.9589476585,37.3738975525],"type":"Point"}
}