{
  "type": "Feature",
  "properties": {
    "iso:country":"ES",
    "sg:address":"Avda Virgen De Los Imposibles, 108",
    "sg:city":"Villacedre",
    "sg:orig_category":"Venta, Instalaci\u00d3n De Calefacci\u00d3n",
    "sg:phone":"+34 987 26 00 03",
    "sg:postcode":"24194",
    "sg:province":"Le\u00f3n",
    "wof:name":"Suministros Otero Y Miranda S.l.",
    "wof:placetype":"venue"
},
  "geometry": {"coordinates":[-5.5894088745,42.559589386],"type":"Point"}
}