{
  "type": "Feature",
  "properties": {
    "addr:full":"Calle de Nardiz Tar Jon, 4 Bermeo Vizcaya 48370",
    "addr:housenumber":"4",
    "addr:postcode":"48370",
    "addr:street":"Calle De Nardiz Tar Jon",
    "iso:country":"ES",
    "sg:address":"Calle de Nardiz Tar Jon, 4",
    "sg:city":"Bermeo",
    "sg:orig_category":"Farmacias",
    "sg:phone":"+34 946 88 01 34",
    "sg:postcode":"48370",
    "sg:province":"Vizcaya",
    "wof:name":"Gabilondo Fernandez Maria Mercedes",
    "wof:placetype":"venue"
},
  "geometry": {"coordinates":[-2.7240440845,43.4199905396],"type":"Point"}
}