{
  "type": "Feature",
  "properties": {
    "iso:country":"ES",
    "sg:address":"Avda Errekalde De, 33",
    "sg:city":"A\u00d1orga",
    "sg:orig_category":"Venta, Instalaci\u00d3n De Calefacci\u00d3n",
    "sg:phone":"+34 943 36 49 09",
    "sg:postcode":"20018",
    "sg:province":"Guip\u00f9zcoa",
    "wof:name":"Landart Meslet Juan Luis",
    "wof:placetype":"venue"
},
  "geometry": {"coordinates":[-2.0061583519,43.2787818909],"type":"Point"}
}