{
  "type": "Feature",
  "properties": {
    "iso:country":"ES",
    "sg:address":"Carretera Vidreres, S/n",
    "sg:city":"Lloret Mar",
    "sg:orig_category":"Confecci\u00d3n De Trajes Para Se\u00d1oras",
    "sg:phone":"+34 972 36 78 00",
    "sg:postcode":"17310",
    "sg:province":"Girona",
    "wof:name":"Uncle Sam S.l.",
    "wof:placetype":"venue"
},
  "geometry": {"coordinates":[2.846834898,41.6981697083],"type":"Point"}
}