{
  "type": "Feature",
  "properties": {
    "addr:full":"Pase Juan Carlos I, 32 Valladolid Valladolid 47012",
    "addr:housenumber":"32",
    "addr:postcode":"47012",
    "addr:street":"Carlos I",
    "iso:country":"ES",
    "sg:address":"Pase Juan Carlos I, 32",
    "sg:city":"Valladolid",
    "sg:orig_category":"Peluqueros: De Se\u00d1oras",
    "sg:phone":"+34 983 39 16 36",
    "sg:postcode":"47012",
    "sg:province":"Valladolid",
    "wof:name":"Jimenez Brime Bego\u00f1a",
    "wof:placetype":"venue"
},
  "geometry": {"coordinates":[-4.7150058746,41.6403808594],"type":"Point"}
}