{
  "type": "Feature",
  "properties": {
    "addr:full":"Calle de Bermudez De Castro, 113 Oviedo Asturias 33011",
    "addr:housenumber":"113",
    "addr:postcode":"33011",
    "addr:street":"Calle De Bermudez De Castro",
    "iso:country":"ES",
    "sg:address":"Calle de Bermudez De Castro, 113",
    "sg:city":"Oviedo",
    "sg:orig_category":"Muebles Y Accesorios Para Cocinas Y Cuartos De Ba\u00d1o (al Por Menor)",
    "sg:phone":"+34 985 11 08 21",
    "sg:postcode":"33011",
    "sg:province":"Asturias",
    "wof:name":"Arias Fernandez Maria Del Rosario",
    "wof:placetype":"venue"
},
  "geometry": {"coordinates":[-5.8341856003,43.3759002686],"type":"Point"}
}