{
  "type": "Feature",
  "properties": {
    "addr:full":"G.v. Corts Catalanes, 451 Barcelona Barcelona 08015",
    "addr:housenumber":"451",
    "addr:postcode":"08015",
    "addr:street":"Catalanes",
    "iso:country":"ES",
    "sg:address":"G.v. Corts Catalanes, 451",
    "sg:city":"Barcelona",
    "sg:orig_category":"Ropa Para Se\u00d1oras (al Por Menor)",
    "sg:phone":"+34 934 23 88 02",
    "sg:postcode":"08015",
    "sg:province":"Barcelona",
    "wof:name":"Boutique Dama S.l.",
    "wof:placetype":"venue"
},
  "geometry": {"coordinates":[2.1540150642,41.3791503906],"type":"Point"}
}