{
  "type": "Feature",
  "properties": {
    "addr:full":"C/ Canal, 19 Banyoles Girona 17820",
    "addr:housenumber":"19",
    "addr:postcode":"17820",
    "addr:street":"C / Canal",
    "iso:country":"ES",
    "sg:address":"C/ Canal, 19",
    "sg:city":"Banyoles",
    "sg:orig_category":"Pensiones Familiares",
    "sg:phone":"+34 972 57 01 27",
    "sg:postcode":"17820",
    "sg:province":"Girona",
    "wof:name":"Pages Coromina Maria",
    "wof:placetype":"venue"
},
  "geometry": {"coordinates":[2.7644131184,42.1187477112],"type":"Point"}
}