{
  "type": "Feature",
  "properties": {
    "addr:full":"Cra. Granollers, S/n Montmelo Barcelona 08160",
    "addr:housenumber":"s",
    "addr:postcode":"08160",
    "addr:street":"/ N",
    "iso:country":"ES",
    "sg:address":"Cra. Granollers, S/n",
    "sg:city":"Montmelo",
    "sg:orig_category":"Deportes Diversos",
    "sg:phone":"+34 935 71 97 00",
    "sg:postcode":"08160",
    "sg:province":"Barcelona",
    "sg:website":"www.circuitcat.com",
    "wof:name":"Circuit De Catalunya S.l.",
    "wof:placetype":"venue"
},
  "geometry": {"coordinates":[2.2503800392,41.5538101196],"type":"Point"}
}