{
  "type": "Feature",
  "properties": {
    "iso:country":"ES",
    "sg:address":"Calle de Puerto Rico, 1",
    "sg:city":"Albolote",
    "sg:orig_category":"Empresarios",
    "sg:phone":"+34 958 46 72 97",
    "sg:postcode":"18220",
    "sg:province":"Granada",
    "wof:name":"Fundacion Francisco Carvajal",
    "wof:placetype":"venue"
},
  "geometry": {"coordinates":[-3.6570100784,37.2314071655],"type":"Point"}
}