{
  "type": "Feature",
  "properties": {
    "addr:full":"Calle de Konbenio, 11 Amorebieta Vizcaya 48340",
    "addr:housenumber":"11",
    "addr:postcode":"48340",
    "addr:street":"Calle De Konbenio",
    "iso:country":"ES",
    "sg:address":"Calle de Konbenio, 11",
    "sg:city":"Amorebieta",
    "sg:orig_category":"Asesor\u00cda, Estudio Y Control Medioambiental",
    "sg:phone":"+34 946 30 06 19",
    "sg:postcode":"48340",
    "sg:province":"Vizcaya",
    "wof:name":"Ekos European Ecological Consulting S.l.",
    "wof:placetype":"venue"
},
  "geometry": {"coordinates":[-2.7308270931,43.2201042175],"type":"Point"}
}