{
  "type": "Feature",
  "properties": {
    "addr:full":"Av Pau Casals, 3 Tarragona Tarragona 43003",
    "addr:housenumber":"3",
    "addr:postcode":"43003",
    "addr:street":"Av Pau Casals",
    "iso:country":"ES",
    "sg:address":"Av Pau Casals, 3",
    "sg:city":"Tarragona",
    "sg:orig_category":"M\u00c9dicos: Cirug\u00cda General",
    "sg:phone":"+34 977 24 09 87",
    "sg:postcode":"43003",
    "sg:province":"Tarragona",
    "wof:name":"Monegal Espinosa Francesc",
    "wof:placetype":"venue"
},
  "geometry": {"coordinates":[1.2506469488,41.1178092957],"type":"Point"}
}