{
  "type": "Feature",
  "properties": {
    "addr:full":"Calle de Casinos, 3 Vilamarxant Valencia 46191",
    "addr:housenumber":"3",
    "addr:postcode":"46191",
    "addr:street":"Calle De Casinos",
    "iso:country":"ES",
    "sg:address":"Calle de Casinos, 3",
    "sg:city":"Vilamarxant",
    "sg:orig_category":"Electricidad: Instaladores",
    "sg:phone":"+34 962 71 20 71",
    "sg:postcode":"46191",
    "sg:province":"Valencia",
    "wof:name":"Luna Faus Antonio",
    "wof:placetype":"venue"
},
  "geometry": {"coordinates":[-0.621861577,39.5702362061],"type":"Point"}
}