{
  "type": "Feature",
  "properties": {
    "addr:full":"Calle de Fotografo Pepe Gracia, S/n Le\u00f3n Le\u00f3n 24005",
    "addr:housenumber":"s",
    "addr:postcode":"24005",
    "addr:street":"Calle De;Pepe Gracia;/ N Leo\u0301N Leo\u0301N",
    "iso:country":"ES",
    "sg:address":"Calle de Fotografo Pepe Gracia, S/n",
    "sg:city":"Le\u00f3n",
    "sg:orig_category":"Centros P\u00dablicos De Formaci\u00d3n Profesional Y T\u00c9cnica",
    "sg:phone":"+34 987 25 23 22",
    "sg:postcode":"24005",
    "sg:province":"Le\u00f3n",
    "wof:name":"Colegio Oficial De Veterinarios",
    "wof:placetype":"venue"
},
  "geometry": {"coordinates":[-5.5643291473,42.5883560181],"type":"Point"}
}