{
  "type": "Feature",
  "properties": {
    "addr:full":"Calle de Arizpetxu, 12 Mungia Vizcaya 48100",
    "addr:housenumber":"12",
    "addr:postcode":"48100",
    "addr:street":"Calle De Arizpetxu",
    "iso:country":"ES",
    "sg:address":"Calle de Arizpetxu, 12",
    "sg:city":"Mungia",
    "sg:orig_category":"Reposter\u00cdas",
    "sg:phone":"+34 946 74 01 77",
    "sg:postcode":"48100",
    "sg:province":"Vizcaya",
    "wof:name":"Panaderia La Moderna Viuda E Hijos De J.beldarrain S.l.",
    "wof:placetype":"venue"
},
  "geometry": {"coordinates":[-2.8483097553,43.3551101685],"type":"Point"}
}