{
  "type": "Feature",
  "properties": {
    "addr:full":"Carr Major, 120 Bescano Girona 17162",
    "addr:housenumber":"120",
    "addr:postcode":"17162",
    "addr:street":"Carr Major",
    "iso:country":"ES",
    "sg:address":"Carr Major, 120",
    "sg:city":"Bescano",
    "sg:orig_category":"Ingenier\u00cda, Centros De Estudios (diversos)",
    "sg:phone":"+34 972 44 29 09",
    "sg:postcode":"17162",
    "sg:province":"Girona",
    "wof:name":"Sistemes De Gestio Tecnogest Girona S.l.",
    "wof:placetype":"venue"
},
  "geometry": {"coordinates":[2.7393751144,41.9661865234],"type":"Point"}
}