{
  "type": "Feature",
  "properties": {
    "addr:full":"Los Ciruelos, 33 Santander Cantabria 39011",
    "addr:housenumber":"33",
    "addr:postcode":"39011",
    "addr:street":"Los Ciruelos",
    "iso:country":"ES",
    "sg:address":"Los Ciruelos, 33",
    "sg:city":"Santander",
    "sg:orig_category":"Alquiler De V\u00cddeo",
    "sg:phone":"+34 942 32 47 93",
    "sg:postcode":"39011",
    "sg:province":"Cantabria",
    "wof:name":"Gestion De Espacio Y Tiempo Sl",
    "wof:placetype":"venue"
},
  "geometry": {"coordinates":[-3.8533990383,43.4580383301],"type":"Point"}
}