{
  "type": "Feature",
  "properties": {
    "addr:full":"Calle de San Pedro De Alcantara, 1 Merida Badajoz 06800",
    "addr:housenumber":"1",
    "addr:postcode":"06800",
    "addr:street":"Calle De;Alcantara",
    "iso:country":"ES",
    "sg:address":"Calle de San Pedro De Alcantara, 1",
    "sg:city":"Merida",
    "sg:orig_category":"Carnes De Carnicer\u00cda (al Por Mayor)",
    "sg:phone":"+34 924 31 93 02",
    "sg:postcode":"06800",
    "sg:province":"Badajoz",
    "wof:name":"Frimancha Industrias Carnicas S.a.",
    "wof:placetype":"venue"
},
  "geometry": {"coordinates":[-6.3377342224,38.909828186],"type":"Point"}
}