{
  "type": "Feature",
  "properties": {
    "addr:full":"Calle de Soto, S/n Esquiroz Navarra 31191",
    "addr:housenumber":"s",
    "addr:postcode":"31191",
    "addr:street":"Calle De Soto;/ N Esquiroz Navarra",
    "iso:country":"ES",
    "sg:address":"Calle de Soto, S/n",
    "sg:city":"Esquiroz",
    "sg:orig_category":"Polideportivos",
    "sg:phone":"+34 948 31 75 28",
    "sg:postcode":"31191",
    "sg:province":"Navarra",
    "wof:name":"Ayuntamiento De Cendea De Galar",
    "wof:placetype":"venue"
},
  "geometry": {"coordinates":[-1.6570199728,42.775188446],"type":"Point"}
}