{
  "type": "Feature",
  "properties": {
    "iso:country":"ES",
    "sg:address":"Plaz Foramontanos, 2",
    "sg:city":"Burgos",
    "sg:orig_category":"Plomeros",
    "sg:phone":"+34 947 23 88 39",
    "sg:postcode":"09007",
    "sg:province":"Burgos",
    "wof:name":"Carre\u00f1o Gracia Rafael",
    "wof:placetype":"venue"
},
  "geometry": {"coordinates":[-3.668227911,42.3476486206],"type":"Point"}
}