{
  "type": "Feature",
  "properties": {
    "iso:country":"ES",
    "sg:address":"Calle de Mendez Alvaro, 1",
    "sg:city":"Madrid",
    "sg:orig_category":"Farmacias",
    "sg:phone":"+34 915 39 34 44",
    "sg:postcode":"28045",
    "sg:province":"Madrid",
    "wof:name":"Garcia Alonso Maria Luisa",
    "wof:placetype":"venue"
},
  "geometry": {"coordinates":[-3.6879010201,40.4026603699],"type":"Point"}
}