{
  "type": "Feature",
  "properties": {
    "iso:country":"ES",
    "sg:address":"Calle de Alonso De Celada, 5",
    "sg:city":"Badajoz",
    "sg:orig_category":"Arreglo, Reparaci\u00d3n, Piezas Sueltas De Televisi\u00d3n, V\u00cddeo, Hi",
    "sg:phone":"+34 924 22 13 21",
    "sg:postcode":"06002",
    "sg:province":"Badajoz",
    "wof:name":"Marquez Arribas Jose Luis",
    "wof:placetype":"venue"
},
  "geometry": {"coordinates":[-6.9728245735,38.8754081726],"type":"Point"}
}