{
  "type": "Feature",
  "properties": {
    "addr:full":"Calle de Padre Damian, 48 Madrid Madrid 28036",
    "addr:housenumber":"48",
    "addr:postcode":"madrid;28036",
    "addr:street":"Calle De Padre Damian",
    "iso:country":"ES",
    "sg:address":"Calle de Padre Damian, 48",
    "sg:city":"Madrid",
    "sg:orig_category":"Arquitectos",
    "sg:phone":"+34 913 59 97 64",
    "sg:postcode":"28036",
    "sg:province":"Madrid",
    "wof:name":"Alas Rodriguez Genaro",
    "wof:placetype":"venue"
},
  "geometry": {"coordinates":[-3.6853847504,40.4604530334],"type":"Point"}
}