{
  "type": "Feature",
  "properties": {
    "iso:country":"ES",
    "sg:address":"Avda Carlos V, 1",
    "sg:city":"Carrizal",
    "sg:orig_category":"Material Y Accesorios Para Bisuter\u00cda Y Joyer\u00cda",
    "sg:phone":"+34 928 78 61 03",
    "sg:postcode":"35240",
    "sg:province":"Las Palmas",
    "wof:name":"Rodriguez Caballero Jorge",
    "wof:placetype":"venue"
},
  "geometry": {"coordinates":[-15.4080572128,27.9093875885],"type":"Point"}
}