{
  "type": "Feature",
  "properties": {
    "iso:country":"ES",
    "sg:address":"Carr Francesc Ciurana, 17",
    "sg:city":"Girona",
    "sg:orig_category":"Centros Empresariales",
    "sg:phone":"+34 972 21 50 80",
    "sg:postcode":"17002",
    "sg:province":"Girona",
    "wof:name":"Gotic Estudi S.l.",
    "wof:placetype":"venue"
},
  "geometry": {"coordinates":[2.8183629513,41.9768714905],"type":"Point"}
}