{
  "type": "Feature",
  "properties": {
    "addr:full":"Calle de Ermita (la), 2 Azuqueca Henares Guadalajara 19200",
    "addr:housenumber":"2",
    "addr:postcode":"19200",
    "addr:street":"Calle De Ermita La",
    "iso:country":"ES",
    "sg:address":"Calle de Ermita (la), 2",
    "sg:city":"Azuqueca Henares",
    "sg:orig_category":"Art\u00cdculos De Regalo (al Por Menor)",
    "sg:phone":"+34 949 26 02 25",
    "sg:postcode":"19200",
    "sg:province":"Guadalajara",
    "wof:name":"Provencio Provencio Maria Inmaculada",
    "wof:placetype":"venue"
},
  "geometry": {"coordinates":[-3.2628550529,40.5694503784],"type":"Point"}
}