{
  "type": "Feature",
  "properties": {
    "addr:full":"Calle de Dolores, 7 Baza Granada 18800",
    "addr:housenumber":"7",
    "addr:postcode":"18800",
    "addr:street":"Calle De Dolores",
    "iso:country":"ES",
    "sg:address":"Calle de Dolores, 7",
    "sg:city":"Baza",
    "sg:orig_category":"Quincaller\u00cda (al Por Menor)",
    "sg:phone":"+34 958 70 02 93",
    "sg:postcode":"18800",
    "sg:province":"Granada",
    "wof:name":"Pardo Diaz Manuel",
    "wof:placetype":"venue"
},
  "geometry": {"coordinates":[-2.7736682892,37.4907188416],"type":"Point"}
}