{
  "type": "Feature",
  "properties": {
    "iso:country":"ES",
    "sg:address":"Barranco, 1",
    "sg:city":"Pitres",
    "sg:orig_category":"Cooperativas Agr\u00cdcolas",
    "sg:phone":"+34 958 76 60 78",
    "sg:postcode":"18414",
    "sg:province":"Granada",
    "wof:name":"Sociedad Cooperativa Mulhacen",
    "wof:placetype":"venue"
},
  "geometry": {"coordinates":[-3.3246679306,36.9357337952],"type":"Point"}
}