{
  "type": "Feature",
  "properties": {
    "addr:full":"Veigamui\u00f1os, S/n Proba Ourense 32317",
    "addr:postcode":"32317",
    "addr:street":"Veigamuin\u0303Os S / N",
    "iso:country":"ES",
    "sg:address":"Veigamui\u00f1os, S/n",
    "sg:city":"Proba",
    "sg:orig_category":"Carnicer\u00cdas, Carnicer\u00cdas",
    "sg:phone":"+34 988 32 61 81",
    "sg:postcode":"32317",
    "sg:province":"Ourense",
    "wof:name":"Discarbi S.l.",
    "wof:placetype":"venue"
},
  "geometry": {"coordinates":[-7.0044908524,42.4339256287],"type":"Point"}
}