{
  "type": "Feature",
  "properties": {
    "addr:full":"Crt. Madrid-cadiz, Km. 0153,3 Villarta S. Juan Ciudad Real 13210",
    "addr:postcode":"13210",
    "addr:street":"Crt. Madrid-Cadiz Km. 0153,3 Villarta S. Juan Ciudad Real",
    "iso:country":"ES",
    "sg:address":"Crt. Madrid-cadiz, Km. 0153,3",
    "sg:city":"Villarta S. Juan",
    "sg:orig_category":"Distribuci\u00d3n De Petr\u00d3leo Y Derivados",
    "sg:phone":"+34 926 64 10 34",
    "sg:postcode":"13210",
    "sg:province":"Ciudad Real",
    "wof:name":"Menchero Y Rubio S.l.",
    "wof:placetype":"venue"
},
  "geometry": {"coordinates":[-3.4209120274,39.2350120544],"type":"Point"}
}