{
  "type": "Feature",
  "properties": {
    "addr:full":"Pg Pins, 30 Sant Feliu Llobregat Barcelona 08980",
    "addr:housenumber":"30",
    "addr:postcode":"08980",
    "addr:street":"Pg Pins",
    "iso:country":"ES",
    "sg:address":"Pg Pins, 30",
    "sg:city":"Sant Feliu Llobregat",
    "sg:orig_category":"Peluquer\u00cdas, Peluquer\u00cda Mixta",
    "sg:phone":"+34 936 85 14 11",
    "sg:postcode":"08980",
    "sg:province":"Barcelona",
    "wof:name":"Madro\u00f1o Sanchez Mario",
    "wof:placetype":"venue"
},
  "geometry": {"coordinates":[2.0430350304,41.3844718933],"type":"Point"}
}