{
  "type": "Feature",
  "properties": {
    "iso:country":"ES",
    "sg:address":"Avda Sor Teresa Prat, 59",
    "sg:city":"Malaga",
    "sg:orig_category":"Peluquer\u00cdas, Peluquer\u00cda Mixta",
    "sg:phone":"+34 952 35 29 13",
    "sg:postcode":"29003",
    "sg:province":"M\u00e1laga",
    "wof:name":"Gonzalez Sanchez Aurora",
    "wof:placetype":"venue"
},
  "geometry": {"coordinates":[-4.4423542023,36.6960830688],"type":"Point"}
}