{
  "type": "Feature",
  "properties": {
    "addr:full":"Angueira De Castro, 10 Sorribas La Coru\u00f1a 15986",
    "addr:housenumber":"10",
    "addr:postcode":"15986",
    "addr:street":"Angueira;Castro;La Corun\u0303A",
    "iso:country":"ES",
    "sg:address":"Angueira De Castro, 10",
    "sg:city":"Sorribas",
    "sg:orig_category":"Empresarios Y Productoras De Espect\u00c1culos",
    "sg:phone":"+34 981 80 36 31",
    "sg:postcode":"15986",
    "sg:province":"La Coru\u00f1a",
    "wof:name":"Lopez Rodriguez Maria Nazaret",
    "wof:placetype":"venue"
},
  "geometry": {"coordinates":[-8.6753158569,42.7911300659],"type":"Point"}
}