{
  "type": "Feature",
  "properties": {
    "iso:country":"ES",
    "sg:address":"Carrer de Pau Casals, 26",
    "sg:city":"Cambrils",
    "sg:orig_category":"Cl\u00cdnicas M\u00c9dicas",
    "sg:phone":"+34 977 79 13 54",
    "sg:postcode":"43850",
    "sg:province":"Tarragona",
    "wof:name":"Lopez Mulet Santiago",
    "wof:placetype":"venue"
},
  "geometry": {"coordinates":[1.0617599487,41.0666122437],"type":"Point"}
}