{
  "type": "Feature",
  "properties": {
    "addr:full":"Calle de Virtud, 6 Sevilla Sevilla 41010",
    "addr:housenumber":"6",
    "addr:postcode":"41010",
    "addr:street":"Calle De Virtud",
    "iso:country":"ES",
    "sg:address":"Calle de Virtud, 6",
    "sg:city":"Sevilla",
    "sg:orig_category":"Inmobiliaria (agencias)",
    "sg:phone":"+34 954 27 21 10",
    "sg:postcode":"41010",
    "sg:province":"Sevilla",
    "sg:website":"www.pisoinmobiliaria.com",
    "wof:name":"Perez Sarmiento Maria Auxiliadora",
    "wof:placetype":"venue"
},
  "geometry": {"coordinates":[-6.0060138702,37.3780021667],"type":"Point"}
}