{
  "type": "Feature",
  "properties": {
    "iso:country":"ES",
    "sg:address":"Calle de Cisneros, 37",
    "sg:city":"Alcorcon",
    "sg:orig_category":"Peluqueros: De Se\u00d1oras",
    "sg:phone":"+34 916 43 02 77",
    "sg:postcode":"28922",
    "sg:province":"Madrid",
    "wof:name":"Gamazo Gutierrez Maria Cruz",
    "wof:placetype":"venue"
},
  "geometry": {"coordinates":[-3.8321328163,40.3452415466],"type":"Point"}
}