{
  "type": "Feature",
  "properties": {
    "addr:full":"Calle de Rio Bidasoa, 43 Valencia Valencia 46019",
    "addr:housenumber":"43",
    "addr:postcode":"46019",
    "addr:street":"Calle De Rio Bidasoa",
    "iso:country":"ES",
    "sg:address":"Calle de Rio Bidasoa, 43",
    "sg:city":"Valencia",
    "sg:orig_category":"Alumbrados",
    "sg:phone":"+34 963 65 10 88",
    "sg:postcode":"46019",
    "sg:province":"Valencia",
    "sg:website":"www.iteval.net",
    "wof:name":"Iluminacion Tecnica Valencia S.l.",
    "wof:placetype":"venue"
},
  "geometry": {"coordinates":[-0.3785290122,39.4979286194],"type":"Point"}
}