{
  "type": "Feature",
  "properties": {
    "addr:full":"Carrer de Roger De Lluria, 57 Barcelona Barcelona 08009",
    "addr:housenumber":"57",
    "addr:postcode":"08009",
    "addr:street":"Carrer De Roger De Lluria",
    "iso:country":"ES",
    "sg:address":"Carrer de Roger De Lluria, 57",
    "sg:city":"Barcelona",
    "sg:orig_category":"Internados & Ense\u00d1anza Privada",
    "sg:phone":"+34 934 87 90 24",
    "sg:postcode":"08009",
    "sg:province":"Barcelona",
    "wof:name":"Casas Jolis Maria Del Carmen",
    "wof:placetype":"venue"
},
  "geometry": {"coordinates":[2.1679461002,41.3936462402],"type":"Point"}
}