{
  "type": "Feature",
  "properties": {
    "iso:country":"ES",
    "sg:address":"Calle de Enero, 16",
    "sg:city":"Madrid",
    "sg:orig_category":"Reciclaje Y Tratamiento De Desechos Varios",
    "sg:phone":"+34 913 29 59 06",
    "sg:postcode":"28022",
    "sg:province":"Madrid",
    "wof:name":"Fcc Medio Ambiente S.a.",
    "wof:placetype":"venue"
},
  "geometry": {"coordinates":[-3.5649075508,40.4476966858],"type":"Point"}
}