{
  "type": "Feature",
  "properties": {
    "iso:country":"ES",
    "sg:address":"Calle de Chancilleria, 2",
    "sg:city":"Valladolid",
    "sg:orig_category":"Formaci\u00d3n A Distancia, Por Correspondencia",
    "sg:phone":"+34 983 25 27 03",
    "sg:postcode":"47003",
    "sg:province":"Valladolid",
    "wof:name":"Real Academia De Medicina Y Cirugia De Valladolid",
    "wof:placetype":"venue"
},
  "geometry": {"coordinates":[-4.7201828957,41.6568984985],"type":"Point"}
}