{
  "type": "Feature",
  "properties": {
    "addr:full":"Carr Jose Gascon, 54 Betera Valencia 46117",
    "addr:housenumber":"54",
    "addr:postcode":"46117",
    "addr:street":"Carr Jose Gascon",
    "iso:country":"ES",
    "sg:address":"Carr Jose Gascon, 54",
    "sg:city":"Betera",
    "sg:orig_category":"Laboratorios Y Trabajos De Fotograf\u00cda, V\u00cddeo Y Cine",
    "sg:phone":"+34 961 60 19 82",
    "sg:postcode":"46117",
    "sg:province":"Valencia",
    "wof:name":"Producciones Profovi S.l.",
    "wof:placetype":"venue"
},
  "geometry": {"coordinates":[-0.4607590139,39.5912857056],"type":"Point"}
}