{
  "type": "Feature",
  "properties": {
    "addr:full":"Calle de San Jose Obrero, 101 Almeria Almer\u00eda 04009",
    "addr:housenumber":"101",
    "addr:postcode":"04009",
    "addr:street":"Calle De;Almeria Almeri\u0301A",
    "iso:country":"ES",
    "sg:address":"Calle de San Jose Obrero, 101",
    "sg:city":"Almeria",
    "sg:orig_category":"Producci\u00d3n De Huevos",
    "sg:phone":"+34 950 25 65 73",
    "sg:postcode":"04009",
    "sg:province":"Almer\u00eda",
    "wof:name":"Garcia Alfonso Victoriano",
    "wof:placetype":"venue"
},
  "geometry": {"coordinates":[-2.4536368847,36.8478088379],"type":"Point"}
}