{
  "type": "Feature",
  "properties": {
    "addr:full":"Calle de Fajardo, 7 Arrecife Las Palmas 35500",
    "addr:housenumber":"7",
    "addr:postcode":"35500",
    "addr:street":"Calle De Fajardo",
    "iso:country":"ES",
    "sg:address":"Calle de Fajardo, 7",
    "sg:city":"Arrecife",
    "sg:orig_category":"Farmacias",
    "sg:phone":"+34 928 81 10 68",
    "sg:postcode":"35500",
    "sg:province":"Las Palmas",
    "wof:name":"Martin Capote Maria Mercedes",
    "wof:placetype":"venue"
},
  "geometry": {"coordinates":[-13.5503425598,28.9603843689],"type":"Point"}
}