{
  "type": "Feature",
  "properties": {
    "addr:full":"Mercado Central, S/n Elche Alicante 03202",
    "addr:housenumber":"s / n",
    "addr:postcode":"03202",
    "addr:street":"Central",
    "iso:country":"ES",
    "sg:address":"Mercado Central, S/n",
    "sg:city":"Elche",
    "sg:orig_category":"Poller\u00cda Y Caza (al Por Menor)",
    "sg:phone":"+34 965 45 46 71",
    "sg:postcode":"03202",
    "sg:province":"Alicante",
    "wof:name":"Hijos De Tomas Pascual S.l.",
    "wof:placetype":"venue"
},
  "geometry": {"coordinates":[-0.5931239724,38.2568435669],"type":"Point"}
}