{
  "type": "Feature",
  "properties": {
    "addr:full":"Pl Pastoreta, 2 Reus Tarragona 43205",
    "addr:housenumber":"2",
    "addr:postcode":"43205",
    "addr:street":"Pl Pastoreta",
    "iso:country":"ES",
    "sg:address":"Pl Pastoreta, 2",
    "sg:city":"Reus",
    "sg:orig_category":"M\u00c9dicos: Cirug\u00cda General",
    "sg:phone":"+34 977 31 84 11",
    "sg:postcode":"43205",
    "sg:province":"Tarragona",
    "wof:name":"Serrano Lorente Felipe",
    "wof:placetype":"venue"
},
  "geometry": {"coordinates":[1.1052639484,41.1502037048],"type":"Point"}
}