{
  "type": "Feature",
  "properties": {
    "addr:full":"Leon-astorga, Km. 0009,0 Valverde Virgen Le\u00f3n 24391",
    "addr:postcode":"24391",
    "addr:street":"Leon-Astorga Km. 0009,0 Valverde Virgen Leo\u0301N",
    "iso:country":"ES",
    "sg:address":"Leon-astorga, Km. 0009,0",
    "sg:city":"Valverde Virgen",
    "sg:orig_category":"Veh\u00cdculos De Ocasi\u00d3n",
    "sg:phone":"+34 987 30 32 73",
    "sg:postcode":"24391",
    "sg:province":"Le\u00f3n",
    "wof:name":"Garciauto Hermanos 2001 S.l.",
    "wof:placetype":"venue"
},
  "geometry": {"coordinates":[-5.6244401932,42.5436477661],"type":"Point"}
}