{
  "type": "Feature",
  "properties": {
    "addr:full":"Calle de Coslada, 15 Madrid Madrid 28028",
    "addr:housenumber":"15",
    "addr:postcode":"madrid;28028",
    "addr:street":"Calle De Coslada",
    "iso:country":"ES",
    "sg:address":"Calle de Coslada, 15",
    "sg:city":"Madrid",
    "sg:orig_category":"Molduras, Junquillos, Listones Y Molduras Perforadas",
    "sg:phone":"+34 913 61 04 34",
    "sg:postcode":"28028",
    "sg:province":"Madrid",
    "wof:name":"San Jorge S.a.",
    "wof:placetype":"venue"
},
  "geometry": {"coordinates":[-3.6736559868,40.4382743835],"type":"Point"}
}