{
  "type": "Feature",
  "properties": {
    "iso:country":"ES",
    "sg:address":"Cmno Conf Hidr Guadalquivir, S/n",
    "sg:city":"Puente Obispo",
    "sg:orig_category":"Conservas De Platos Cocinados (fabricaci\u00d3n, Al Por Mayor)",
    "sg:phone":"+34 953 76 50 75",
    "sg:postcode":"23529",
    "sg:province":"Ja\u00e9n",
    "sg:website":"www.coosur.es",
    "wof:name":"Aceites Del Sur-coosur S.a.",
    "wof:placetype":"venue"
},
  "geometry": {"coordinates":[-3.7895176411,37.7657394409],"type":"Point"}
}