{
  "type": "Feature",
  "properties": {
    "addr:full":"Avda Goya, 57 Zaragoza Zaragoza 50005",
    "addr:housenumber":"57",
    "addr:postcode":"50005",
    "addr:street":"Avda Goya",
    "iso:country":"ES",
    "sg:address":"Avda Goya, 57",
    "sg:city":"Zaragoza",
    "sg:orig_category":"Bisuter\u00cda, Joyer\u00cda, Relojer\u00cda (al Por Menor)",
    "sg:phone":"+34 976 35 99 69",
    "sg:postcode":"50005",
    "sg:province":"Zaragoza",
    "wof:name":"Zamarvide Vallino Clara",
    "wof:placetype":"venue"
},
  "geometry": {"coordinates":[-0.8931192756,41.6451225281],"type":"Point"}
}