{
  "type": "Feature",
  "properties": {
    "addr:full":"Calle de Real, 37 Roquetas Mar Almer\u00eda 04740",
    "addr:housenumber":"37",
    "addr:postcode":"04740",
    "addr:street":"Calle De Real;Mar Almeri\u0301A",
    "iso:country":"ES",
    "sg:address":"Calle de Real, 37",
    "sg:city":"Roquetas Mar",
    "sg:orig_category":"Lencer\u00cda Femenina, Corseter\u00cda, Trajes De Ba\u00d1o (al Por Menor)",
    "sg:phone":"+34 950 32 43 51",
    "sg:postcode":"04740",
    "sg:province":"Almer\u00eda",
    "wof:name":"Jimenez Cano Leonor",
    "wof:placetype":"venue"
},
  "geometry": {"coordinates":[-2.6142790318,36.7631797791],"type":"Point"}
}