{
  "type": "Feature",
  "properties": {
    "addr:full":"Calle de Liberia, 3 Malaga M\u00e1laga 29014",
    "addr:housenumber":"3",
    "addr:postcode":"29014",
    "addr:street":"Calle De Liberia;Ma\u0301Laga",
    "iso:country":"ES",
    "sg:address":"Calle de Liberia, 3",
    "sg:city":"Malaga",
    "sg:orig_category":"Asociaciones Y Clubs Deportivos",
    "sg:phone":"+34 952 26 36 49",
    "sg:postcode":"29014",
    "sg:province":"M\u00e1laga",
    "wof:name":"Torralba Tenllado Julian",
    "wof:placetype":"venue"
},
  "geometry": {"coordinates":[-4.4229340553,36.7315292358],"type":"Point"}
}