{
  "type": "Feature",
  "properties": {
    "addr:full":"Calle de Zorita, 2 Salamanca Salamanca 37003",
    "addr:housenumber":"2",
    "addr:postcode":"37003",
    "addr:street":"Calle De Zorita",
    "iso:country":"ES",
    "sg:address":"Calle de Zorita, 2",
    "sg:city":"Salamanca",
    "sg:orig_category":"Asilos De Ancianos. Centros Privados",
    "sg:phone":"+34 923 18 39 14",
    "sg:postcode":"37003",
    "sg:province":"Salamanca",
    "wof:name":"Hermanas De La Caridad De Santa Ana",
    "wof:placetype":"venue"
},
  "geometry": {"coordinates":[-5.6520028114,40.96484375],"type":"Point"}
}