{
  "type": "Feature",
  "properties": {
    "addr:full":"Calle de Alboran, S/n Jerez De La Frontera C\u00e1diz 11406",
    "addr:housenumber":"s",
    "addr:postcode":"11406",
    "addr:street":"Calle De Alboran;/ N",
    "iso:country":"ES",
    "sg:address":"Calle de Alboran, S/n",
    "sg:city":"Jerez De La Frontera",
    "sg:orig_category":"Centros De Educaci\u00d3n Especial",
    "sg:phone":"+34 956 33 50 04",
    "sg:postcode":"11406",
    "sg:province":"C\u00e1diz",
    "wof:name":"Junta De Andalucia",
    "wof:placetype":"venue"
},
  "geometry": {"coordinates":[-6.1179795265,36.6798553467],"type":"Point"}
}