{
  "type": "Feature",
  "properties": {
    "iso:country":"ES",
    "sg:address":"Calle de Mayor, 37",
    "sg:city":"Burlada",
    "sg:orig_category":"Armas Y Municiones (fabricaci\u00d3n, Al Por Mayor)",
    "sg:phone":"+34 948 12 28 99",
    "sg:postcode":"31600",
    "sg:province":"Navarra",
    "wof:name":"Zubillaga Orderiz Angel Maria",
    "wof:placetype":"venue"
},
  "geometry": {"coordinates":[-1.6165608168,42.8256835938],"type":"Point"}
}