{
  "type": "Feature",
  "properties": {
    "iso:country":"ES",
    "sg:address":"Calle de Tutor, 43",
    "sg:city":"Madrid",
    "sg:orig_category":"M\u00c9dicos: Psiquiatr\u00cda",
    "sg:phone":"+34 915 41 49 82",
    "sg:postcode":"28008",
    "sg:province":"Madrid",
    "wof:name":"Alterman De Levit Maria",
    "wof:placetype":"venue"
},
  "geometry": {"coordinates":[-3.7172448635,40.4300384521],"type":"Point"}
}