{
  "type": "Feature",
  "properties": {
    "iso:country":"ES",
    "sg:address":"Avda Alemania (de), 21",
    "sg:city":"Caceres",
    "sg:orig_category":"Colchones (fabricaci\u00d3n, Al Por Mayor, Al Por Menor)",
    "sg:phone":"+34 927 23 34 41",
    "sg:postcode":"10001",
    "sg:province":"C\u00e1ceres",
    "wof:name":"Colchoneria Extreme\u00d1a S.l.",
    "wof:placetype":"venue"
},
  "geometry": {"coordinates":[-6.3801188469,39.4669303894],"type":"Point"}
}