{
  "type": "Feature",
  "properties": {
    "iso:country":"ES",
    "sg:address":"Calle de Salvador, 7",
    "sg:city":"Madridejos",
    "sg:orig_category":"Iglesia Cat\u00d3lica",
    "sg:phone":"+34 925 46 00 18",
    "sg:postcode":"45710",
    "sg:province":"Toledo",
    "wof:name":"Parroquia El Divino Salvador",
    "wof:placetype":"venue"
},
  "geometry": {"coordinates":[-3.5338869095,39.4688453674],"type":"Point"}
}