{
  "type": "Feature",
  "properties": {
    "addr:full":"Carrer de Arago, 241 Barcelona Barcelona 08007",
    "addr:housenumber":"241",
    "addr:postcode":"08007",
    "addr:street":"Carrer De Arago",
    "iso:country":"ES",
    "sg:address":"Carrer de Arago, 241",
    "sg:city":"Barcelona",
    "sg:orig_category":"Abogados",
    "sg:phone":"+34 932 15 26 36",
    "sg:postcode":"08007",
    "sg:province":"Barcelona",
    "wof:name":"Roda Alemany Tomas",
    "wof:placetype":"venue"
},
  "geometry": {"coordinates":[2.1627190113,41.3906974792],"type":"Point"}
}