{
  "type": "Feature",
  "properties": {
    "addr:full":"Carrer de Jacint Verdaguer, 99 Amposta Tarragona 43870",
    "addr:housenumber":"99",
    "addr:postcode":"43870",
    "addr:street":"Carrer De Jacint Verdaguer",
    "iso:country":"ES",
    "sg:address":"Carrer de Jacint Verdaguer, 99",
    "sg:city":"Amposta",
    "sg:orig_category":"Sociedades, Compa\u00d1\u00cdas Aseguradoras",
    "sg:phone":"+34 977 70 51 00",
    "sg:postcode":"43870",
    "sg:province":"Tarragona",
    "wof:name":"A.d.v. Corredoria D'assegurances S.l.",
    "wof:placetype":"venue"
},
  "geometry": {"coordinates":[0.5778180957,40.7056427002],"type":"Point"}
}