{
  "type": "Feature",
  "properties": {
    "addr:full":"Avda Constitucion, 10 Bollullos Par Condado Huelva 21710",
    "addr:housenumber":"10",
    "addr:postcode":"21710",
    "addr:street":"Avda Constitucion",
    "iso:country":"ES",
    "sg:address":"Avda Constitucion, 10",
    "sg:city":"Bollullos Par Condado",
    "sg:orig_category":"Desinfecci\u00d3n, Desinsectaci\u00d3n, Desratizaci\u00d3n",
    "sg:phone":"+34 959 41 11 51",
    "sg:postcode":"21710",
    "sg:province":"Huelva",
    "wof:name":"Gaipo S.l.",
    "wof:placetype":"venue"
},
  "geometry": {"coordinates":[-6.5371451378,37.3396339417],"type":"Point"}
}