{
  "type": "Feature",
  "properties": {
    "iso:country":"ES",
    "sg:address":"Urdaneta Bidea, 15",
    "sg:city":"Zarautz",
    "sg:orig_category":"Material Y Herramientas Agr\u00cdcolas",
    "sg:phone":"+34 943 83 23 22",
    "sg:postcode":"20800",
    "sg:province":"Guip\u00f9zcoa",
    "wof:name":"Ostadar Nekazaritza, S.l.l",
    "wof:placetype":"venue"
},
  "geometry": {"coordinates":[-2.1744129658,43.2777824402],"type":"Point"}
}