{
  "type": "Feature",
  "properties": {
    "iso:country":"ES",
    "sg:address":"Calle de Amantina Cobos, 85",
    "sg:city":"San Juan De Aznalfarache",
    "sg:orig_category":"Farmacias",
    "sg:phone":"+34 954 76 00 65",
    "sg:postcode":"41920",
    "sg:province":"Sevilla",
    "wof:name":"Alonso Plasencia Paloma",
    "wof:placetype":"venue"
},
  "geometry": {"coordinates":[-6.036134243,37.3605384827],"type":"Point"}
}