{
  "type": "Feature",
  "properties": {
    "addr:full":"Carrer de Pujades, 221 Barcelona Barcelona 08005",
    "addr:housenumber":"221",
    "addr:postcode":"08005",
    "addr:street":"Carrer De Pujades",
    "iso:country":"ES",
    "sg:address":"Carrer de Pujades, 221",
    "sg:city":"Barcelona",
    "sg:orig_category":"Molduras, Junquillos, Listones Y Molduras Perforadas",
    "sg:phone":"+34 932 66 00 41",
    "sg:postcode":"08005",
    "sg:province":"Barcelona",
    "wof:name":"Sierra Salgado Amador",
    "wof:placetype":"venue"
},
  "geometry": {"coordinates":[2.2031950951,41.403793335],"type":"Point"}
}