{
  "type": "Feature",
  "properties": {
    "iso:country":"ES",
    "sg:address":"Calle de Avefria, 29",
    "sg:city":"Madrid",
    "sg:orig_category":"Renovaci\u00d3n Inmobiliaria",
    "sg:phone":"+34 915 25 12 04",
    "sg:postcode":"28025",
    "sg:province":"Madrid",
    "wof:name":"Extraplomo S.l.",
    "wof:placetype":"venue"
},
  "geometry": {"coordinates":[-3.7324223518,40.3832855225],"type":"Point"}
}