{
  "type": "Feature",
  "properties": {
    "addr:full":"Calle de Cerrajon, 12 Alcorcon Madrid 28921",
    "addr:housenumber":"12",
    "addr:postcode":"28921",
    "addr:street":"Calle De Cerrajon",
    "iso:country":"ES",
    "sg:address":"Calle de Cerrajon, 12",
    "sg:city":"Alcorcon",
    "sg:classifiers":[
        {
            "category":"Arts & Performance",
            "subcategory":"Art Gallery",
            "type":"Entertainment"
        }
    ],
    "sg:phone":"+34 916 43 75 79",
    "sg:postcode":"28921",
    "sg:province":"Madrid",
    "sg:tags":[
        "arte",
        "de",
        "galer\u00cdas"
    ],
    "wof:name":"Redondo Benito Del Valle Miguel",
    "wof:placetype":"venue"
},
  "geometry": {"coordinates":[-3.8312089443,40.3437423706],"type":"Point"}
}