{
  "type": "Feature",
  "properties": {
    "iso:country":"ES",
    "sg:address":"Calle de Adelfa, 1",
    "sg:city":"Granada",
    "sg:orig_category":"Servicios De Telecomunicaciones",
    "sg:phone":"+34 958 12 34 36",
    "sg:postcode":"18006",
    "sg:province":"Granada",
    "wof:name":"Arias C.b.",
    "wof:placetype":"venue"
},
  "geometry": {"coordinates":[-3.6023075581,37.1638069153],"type":"Point"}
}