{
  "type": "Feature",
  "properties": {
    "addr:full":"Calle de Buenos Aires, 10 Ventas Zafarraya Granada 18128",
    "addr:housenumber":"10",
    "addr:postcode":"18128",
    "addr:street":"Calle De Buenos Aires",
    "iso:country":"ES",
    "sg:address":"Calle de Buenos Aires, 10",
    "sg:city":"Ventas Zafarraya",
    "sg:orig_category":"Comercio De Carburantes",
    "sg:phone":"+34 958 36 21 22",
    "sg:postcode":"18128",
    "sg:province":"Granada",
    "sg:website":"www.cepsa.es",
    "wof:name":"Gema Diez S.l.",
    "wof:placetype":"venue"
},
  "geometry": {"coordinates":[-4.1221718788,36.9556159973],"type":"Point"}
}