{
  "type": "Feature",
  "properties": {
    "addr:full":"Poli Jinamar Ii Fase, S/n Valle De Jinamar Las Palmas 35220",
    "addr:postcode":"35220",
    "addr:street":"S / N;Palmas",
    "iso:country":"ES",
    "sg:address":"Poli Jinamar Ii Fase, S/n",
    "sg:city":"Valle De Jinamar",
    "sg:orig_category":"Farmacias",
    "sg:phone":"+34 928 71 11 89",
    "sg:postcode":"35220",
    "sg:province":"Las Palmas",
    "wof:name":"Millares Ley Eduardo",
    "wof:placetype":"venue"
},
  "geometry": {"coordinates":[-15.4175510406,28.0331096649],"type":"Point"}
}