{
  "type": "Feature",
  "properties": {
    "iso:country":"ES",
    "sg:address":"Calle de Manuel De Falla, 19",
    "sg:city":"Salobre\u00f1a",
    "sg:classifiers":[
        {
            "category":"Personal",
            "subcategory":"Barber",
            "type":"Services"
        }
    ],
    "sg:phone":"+34 958 61 26 65",
    "sg:postcode":"18680",
    "sg:province":"Granada",
    "sg:tags":[
        "caballeros",
        "de",
        "peluqueros"
    ],
    "wof:name":"Medina Rodriguez Juan Antonio",
    "wof:placetype":"venue"
},
  "geometry": {"coordinates":[-3.5873119831,36.7459716797],"type":"Point"}
}