{
  "type": "Feature",
  "properties": {
    "iso:country":"ES",
    "sg:address":"Plaz Negrillon (el), 5",
    "sg:city":"Bo\u00f1ar",
    "sg:orig_category":"Farmacias",
    "sg:phone":"+34 987 73 53 50",
    "sg:postcode":"24850",
    "sg:province":"Le\u00f3n",
    "wof:name":"Tejerina Garcia Jesus Maria",
    "wof:placetype":"venue"
},
  "geometry": {"coordinates":[-5.3211669922,42.8659973145],"type":"Point"}
}