{
  "type": "Feature",
  "properties": {
    "iso:country":"ES",
    "sg:address":"Calle de Juan Ramon Jimenez, 12",
    "sg:city":"Sevilla",
    "sg:orig_category":"Retoques De Vestidos",
    "sg:phone":"+34 954 28 51 04",
    "sg:postcode":"41011",
    "sg:province":"Sevilla",
    "wof:name":"Hurtado Brito Maria Del Carmen",
    "wof:placetype":"venue"
},
  "geometry": {"coordinates":[-5.9988780022,37.3749160767],"type":"Point"}
}