{
  "type": "Feature",
  "properties": {
    "iso:country":"ES",
    "sg:address":"La Chopera, S/n",
    "sg:city":"S. Andres Rabanedo",
    "sg:orig_category":"Extinci\u00d3n De Incendios: Material Y Suministros (fabricaci\u00d3n, Al Por Mayor)",
    "sg:phone":"+34 987 84 74 99",
    "sg:postcode":"24010",
    "sg:province":"Le\u00f3n",
    "wof:name":"Extintores Y Recargas S.l.",
    "wof:placetype":"venue"
},
  "geometry": {"coordinates":[-5.5716600418,42.5981292725],"type":"Point"}
}