{
  "type": "Feature",
  "properties": {
    "addr:full":"Calle de Luis Morote, 21 Palmas De Gran Canaria Las Palmas 35007",
    "addr:housenumber":"21",
    "addr:postcode":"35007",
    "addr:street":"Calle De Luis Morote",
    "iso:country":"ES",
    "sg:address":"Calle de Luis Morote, 21",
    "sg:city":"Palmas De Gran Canaria",
    "sg:orig_category":"Zapatos (al Por Menor)",
    "sg:phone":"+34 928 26 70 14",
    "sg:postcode":"35007",
    "sg:province":"Las Palmas",
    "wof:name":"Varela Galvan Ignacio",
    "wof:placetype":"venue"
},
  "geometry": {"coordinates":[-15.4324588776,28.1413021088],"type":"Point"}
}