{
  "type": "Feature",
  "properties": {
    "addr:full":"Calle de Trabajo, 4 Aljorra Murcia 30390",
    "addr:housenumber":"4",
    "addr:postcode":"30390",
    "addr:street":"Calle De Trabajo",
    "iso:country":"ES",
    "sg:address":"Calle de Trabajo, 4",
    "sg:city":"Aljorra",
    "sg:orig_category":"Centros De Educaci\u00d3n Especial",
    "sg:phone":"+34 968 16 41 52",
    "sg:postcode":"30390",
    "sg:province":"Murcia",
    "wof:name":"Colegio Publico Miguel De Cervantes",
    "wof:placetype":"venue"
},
  "geometry": {"coordinates":[-1.0733289719,37.6905670166],"type":"Point"}
}