{
  "type": "Feature",
  "properties": {
    "addr:full":"Plaz Mariano Benlliure, 9 Valencia Valencia 46002",
    "addr:housenumber":"9",
    "addr:postcode":"46002",
    "addr:street":"Benlliure",
    "iso:country":"ES",
    "sg:address":"Plaz Mariano Benlliure, 9",
    "sg:city":"Valencia",
    "sg:orig_category":"Centros Empresariales",
    "sg:phone":"+34 963 51 04 09",
    "sg:postcode":"46002",
    "sg:province":"Valencia",
    "wof:name":"Asociacion Industriales Graficas De Valencia Y Su Provincia",
    "wof:placetype":"venue"
},
  "geometry": {"coordinates":[-0.376265198,39.4727783203],"type":"Point"}
}