{
  "type": "Feature",
  "properties": {
    "iso:country":"ES",
    "sg:address":"Calle de Mar (la), 47",
    "sg:city":"Colindres",
    "sg:orig_category":"Conservas De Pescados Y Salazones Mar\u00cdtimos (fabricaci\u00d3n, Al Por Mayor)",
    "sg:phone":"+34 942 65 21 21",
    "sg:postcode":"39750",
    "sg:province":"Cantabria",
    "sg:website":"www.conservasrevuelta.com",
    "wof:name":"Sucesores De Conservas Revuelta S.l.",
    "wof:placetype":"venue"
},
  "geometry": {"coordinates":[-3.462490797,43.3935470581],"type":"Point"}
}