{
  "type": "Feature",
  "properties": {
    "addr:full":"Carrer de Copernic, 8 Castelldefels Barcelona 08860",
    "addr:housenumber":"8",
    "addr:postcode":"08860",
    "addr:street":"Carrer De Copernic",
    "iso:country":"ES",
    "sg:address":"Carrer de Copernic, 8",
    "sg:city":"Castelldefels",
    "sg:orig_category":"M\u00c1quinas, Material Y Suministros Para Cajas Y Embalajes",
    "sg:phone":"+34 936 64 99 20",
    "sg:postcode":"08860",
    "sg:province":"Barcelona",
    "sg:website":"www.vaessen-schoemaker.com",
    "wof:name":"Vaessen-schoemaker Industrial S.a.",
    "wof:placetype":"venue"
},
  "geometry": {"coordinates":[1.9898699522,41.2850646973],"type":"Point"}
}