{
  "type": "Feature",
  "properties": {
    "iso:country":"ES",
    "sg:address":"Calle de Puerta Obispo, 1",
    "sg:city":"Astorga",
    "sg:orig_category":"Centros Comerciales Y Grandes Tiendas",
    "sg:phone":"+34 987 61 91 80",
    "sg:postcode":"24700",
    "sg:province":"Le\u00f3n",
    "wof:name":"Musical Zarabanda S.l.",
    "wof:placetype":"venue"
},
  "geometry": {"coordinates":[-6.0589289665,42.4567604065],"type":"Point"}
}