{
  "type": "Feature",
  "properties": {
    "addr:full":"Carrer de Comte D'urgell, 210 Barcelona Barcelona 08036",
    "addr:housenumber":"210",
    "addr:postcode":"08036",
    "addr:street":"Carrer De Comte D'Urgell",
    "iso:country":"ES",
    "sg:address":"Carrer de Comte D'urgell, 210",
    "sg:city":"Barcelona",
    "sg:classifiers":[
        {
            "category":"Personal",
            "subcategory":"Barber",
            "type":"Services"
        }
    ],
    "sg:phone":"+34 934 19 64 41",
    "sg:postcode":"08036",
    "sg:province":"Barcelona",
    "sg:tags":[
        "caballeros",
        "de",
        "peluqueros"
    ],
    "wof:name":"Buil Palomera Amado",
    "wof:placetype":"venue"
},
  "geometry": {"coordinates":[2.1501553059,41.3885040283],"type":"Point"}
}