{
  "type": "Feature",
  "properties": {
    "iso:country":"ES",
    "sg:address":"Calle de Pintores (los), 6",
    "sg:city":"Alcorcon",
    "sg:orig_category":"Hormigonados",
    "sg:phone":"+34 916 44 27 94",
    "sg:postcode":"28925",
    "sg:province":"Madrid",
    "wof:name":"Holcim Hormigones",
    "wof:placetype":"venue"
},
  "geometry": {"coordinates":[-3.8086390495,40.3402404785],"type":"Point"}
}