{
  "type": "Feature",
  "properties": {
    "iso:country":"ES",
    "sg:address":"Calle de Antonio Vargas Y Laguna, S/n",
    "sg:city":"Plasencia",
    "sg:orig_category":"Sanatorios M\u00c9dico",
    "sg:phone":"+34 927 42 31 00",
    "sg:postcode":"10600",
    "sg:province":"C\u00e1ceres",
    "wof:name":"Servicio Extreme\u00d1o De Salud",
    "wof:placetype":"venue"
},
  "geometry": {"coordinates":[-6.0956587791,40.0255661011],"type":"Point"}
}