{
  "type": "Feature",
  "properties": {
    "addr:full":"Calle de San Anton, 35 Granada Granada 18005",
    "addr:housenumber":"35",
    "addr:postcode":"18005",
    "addr:street":"Calle De San Anton",
    "iso:country":"ES",
    "sg:address":"Calle de San Anton, 35",
    "sg:city":"Granada",
    "sg:orig_category":"Bisuter\u00cda, Joyer\u00cda, Relojer\u00cda (al Por Menor)",
    "sg:phone":"+34 958 26 14 21",
    "sg:postcode":"18005",
    "sg:province":"Granada",
    "wof:name":"Rodriguez Gazquez Rafael",
    "wof:placetype":"venue"
},
  "geometry": {"coordinates":[-3.5996870995,37.1713752747],"type":"Point"}
}