{
  "type": "Feature",
  "properties": {
    "addr:full":"Avda Castilla, 64 Cheste Valencia 46380",
    "addr:housenumber":"64",
    "addr:postcode":"46380",
    "addr:street":"Avda Castilla",
    "iso:country":"ES",
    "sg:address":"Avda Castilla, 64",
    "sg:city":"Cheste",
    "sg:orig_category":"Arquitectos",
    "sg:phone":"+34 962 51 21 40",
    "sg:postcode":"46380",
    "sg:province":"Valencia",
    "wof:name":"Arqui Munsuri S.l.",
    "wof:placetype":"venue"
},
  "geometry": {"coordinates":[-0.6827728152,39.492389679],"type":"Point"}
}