{
  "type": "Feature",
  "properties": {
    "iso:country":"ES",
    "sg:address":"Carrer de Sant Pere, 56",
    "sg:city":"Mataro",
    "sg:orig_category":"Fabricaci\u00d3n De Su\u00c9ters Y Chalecos De Punto",
    "sg:phone":"+34 937 96 00 16",
    "sg:postcode":"08301",
    "sg:province":"Barcelona",
    "wof:name":"Prados-prados S. C. P.",
    "wof:placetype":"venue"
},
  "geometry": {"coordinates":[2.4499270916,41.5375938416],"type":"Point"}
}