{
  "type": "Feature",
  "properties": {
    "addr:full":"Vi\u00f1as, 14 Jimena Frontera C\u00e1diz 11330",
    "addr:housenumber":"14",
    "addr:postcode":"11330",
    "addr:street":"Vin\u0303As",
    "iso:country":"ES",
    "sg:address":"Vi\u00f1as, 14",
    "sg:city":"Jimena Frontera",
    "sg:orig_category":"Contenedores (mercanc\u00cdas)",
    "sg:phone":"+34 956 64 10 92",
    "sg:postcode":"11330",
    "sg:province":"C\u00e1diz",
    "wof:name":"Ortiz Cano Luis",
    "wof:placetype":"venue"
},
  "geometry": {"coordinates":[-5.4481987953,36.4326057434],"type":"Point"}
}