{
  "type": "Feature",
  "properties": {
    "iso:country":"ES",
    "sg:address":"Calle de Gran Via, S/n",
    "sg:city":"Hellin",
    "sg:orig_category":"Librer\u00cdas",
    "sg:phone":"+34 967 30 50 27",
    "sg:postcode":"02400",
    "sg:province":"Albacete",
    "wof:name":"Marin Sanchez Roberto",
    "wof:placetype":"venue"
},
  "geometry": {"coordinates":[-1.6970371008,38.5083122253],"type":"Point"}
}