{
  "type": "Feature",
  "properties": {
    "iso:country":"ES",
    "sg:address":"Calle de Solaron (el), S/n",
    "sg:city":"Castanedo",
    "sg:orig_category":"Distribuci\u00d3n De Petr\u00d3leo Y Derivados",
    "sg:phone":"+34 942 50 41 79",
    "sg:postcode":"39150",
    "sg:province":"Cantabria",
    "wof:name":"Caboteja S.l.",
    "wof:placetype":"venue"
},
  "geometry": {"coordinates":[-3.6713039875,43.457118988],"type":"Point"}
}