{
  "type": "Feature",
  "properties": {
    "addr:full":"Calle de Madrid, 54 Balazote Albacete 02320",
    "addr:housenumber":"54",
    "addr:postcode":"02320",
    "addr:street":"Calle De Madrid",
    "iso:country":"ES",
    "sg:address":"Calle de Madrid, 54",
    "sg:city":"Balazote",
    "sg:orig_category":"Mec\u00c1nico Del Autom\u00d3vil",
    "sg:phone":"+34 967 36 02 12",
    "sg:postcode":"02320",
    "sg:province":"Albacete",
    "wof:name":"Gomez Aroca Salvador",
    "wof:placetype":"venue"
},
  "geometry": {"coordinates":[-2.1460111141,38.887348175],"type":"Point"}
}