{
  "type": "Feature",
  "properties": {
    "addr:full":"Carretera De Tales, S/n Onda Castell\u00f3n 12200",
    "addr:housenumber":"s / n",
    "addr:postcode":"12200",
    "addr:street":"Carretera De Tales;Castello\u0301N",
    "iso:country":"ES",
    "sg:address":"Carretera De Tales, S/n",
    "sg:city":"Onda",
    "sg:orig_category":"Fabricaci\u00d3n De Enlosados, Soler\u00cdas",
    "sg:phone":"+34 964 60 28 78",
    "sg:postcode":"12200",
    "sg:province":"Castell\u00f3n",
    "wof:name":"Ceramicas Mezquita S.l.",
    "wof:placetype":"venue"
},
  "geometry": {"coordinates":[-0.2757329941,39.9628753662],"type":"Point"}
}