{
  "type": "Feature",
  "properties": {
    "addr:full":"Plaz Mayor, 11 Castrojeriz Burgos 09110",
    "addr:housenumber":"11",
    "addr:postcode":"09110",
    "addr:street":"Plaz Mayor",
    "iso:country":"ES",
    "sg:address":"Plaz Mayor, 11",
    "sg:city":"Castrojeriz",
    "sg:orig_category":"Estancos",
    "sg:phone":"+34 947 37 70 65",
    "sg:postcode":"09110",
    "sg:province":"Burgos",
    "wof:name":"Yag\u00fcez Rodriguez Amancio",
    "wof:placetype":"venue"
},
  "geometry": {"coordinates":[-4.1401233673,42.2884941101],"type":"Point"}
}