{
  "type": "Feature",
  "properties": {
    "addr:full":"Calle de Antonio Maura, 22 Alacant Alicante 03013",
    "addr:housenumber":"22",
    "addr:postcode":"03013",
    "addr:street":"Calle De Antonio Maura",
    "iso:country":"ES",
    "sg:address":"Calle de Antonio Maura, 22",
    "sg:city":"Alacant",
    "sg:orig_category":"Farmacias",
    "sg:phone":"+34 965 20 12 25",
    "sg:postcode":"03013",
    "sg:province":"Alicante",
    "wof:name":"Diaz Laliga Maria Concepcion",
    "wof:placetype":"venue"
},
  "geometry": {"coordinates":[-0.4775856137,38.3554992676],"type":"Point"}
}