{
  "type": "Feature",
  "properties": {
    "iso:country":"ES",
    "sg:address":"Calle de Hurtado, 2",
    "sg:city":"Jaen",
    "sg:orig_category":"Sellos De Goma Y Met\u00c1licos",
    "sg:phone":"+34 953 23 46 89",
    "sg:postcode":"23001",
    "sg:province":"Ja\u00e9n",
    "wof:name":"Marquez Vergara Maria",
    "wof:placetype":"venue"
},
  "geometry": {"coordinates":[-3.7887480259,37.7655601501],"type":"Point"}
}