{
  "type": "Feature",
  "properties": {
    "addr:full":"Avda Ramon Y Cajal, 35 Sevilla Sevilla 41005",
    "addr:housenumber":"35",
    "addr:postcode":"41005",
    "addr:street":"Avda Ramon Y Cajal",
    "iso:country":"ES",
    "sg:address":"Avda Ramon Y Cajal, 35",
    "sg:city":"Sevilla",
    "sg:orig_category":"Venta, Localizaci\u00d3n, Reparaci\u00d3n De Material E Instrumental M\u00c9dico",
    "sg:phone":"+34 954 64 45 97",
    "sg:postcode":"41005",
    "sg:province":"Sevilla",
    "wof:name":"Grupo Taper S.a.",
    "wof:placetype":"venue"
},
  "geometry": {"coordinates":[-5.9693517685,37.3756484985],"type":"Point"}
}