{
  "type": "Feature",
  "properties": {
    "addr:full":"Calle de Larramendi, 5 Donostia-san Sebastian Guip\u00f9zcoa 20006",
    "addr:housenumber":"5",
    "addr:postcode":"20006",
    "addr:street":"Calle De Larramendi",
    "iso:country":"ES",
    "sg:address":"Calle de Larramendi, 5",
    "sg:city":"Donostia-san Sebastian",
    "sg:orig_category":"Procuradores",
    "sg:phone":"+34 943 45 01 88",
    "sg:postcode":"20006",
    "sg:province":"Guip\u00f9zcoa",
    "wof:name":"Gurrea Frutos Jesus",
    "wof:placetype":"venue"
},
  "geometry": {"coordinates":[-1.9804389477,43.3154983521],"type":"Point"}
}