{
  "type": "Feature",
  "properties": {
    "iso:country":"ES",
    "sg:address":"Calle de Trovador, 67",
    "sg:city":"Puerto",
    "sg:orig_category":"Bisuter\u00cda, Joyer\u00cda, Relojer\u00cda (al Por Menor)",
    "sg:phone":"+34 962 67 87 34",
    "sg:postcode":"46520",
    "sg:province":"Valencia",
    "wof:name":"Bonanad Perez Graciano",
    "wof:placetype":"venue"
},
  "geometry": {"coordinates":[-0.2179590017,39.6590461731],"type":"Point"}
}