{
  "type": "Feature",
  "properties": {
    "addr:full":"Carrer de Isaac Peral, 58 Terrassa Barcelona 08224",
    "addr:housenumber":"58",
    "addr:postcode":"08224",
    "addr:street":"Carrer De Isaac Peral",
    "iso:country":"ES",
    "sg:address":"Carrer de Isaac Peral, 58",
    "sg:city":"Terrassa",
    "sg:orig_category":"Centros De Educaci\u00d3n Especial",
    "sg:phone":"+34 937 88 69 13",
    "sg:postcode":"08224",
    "sg:province":"Barcelona",
    "wof:name":"Patronat Municipal D'educacio De Terrassa",
    "wof:placetype":"venue"
},
  "geometry": {"coordinates":[1.9997060299,41.5632743835],"type":"Point"}
}