{
  "type": "Feature",
  "properties": {
    "iso:country":"ES",
    "sg:address":"Calle de Numancia, 53",
    "sg:city":"Soria",
    "sg:orig_category":"Fabricaci\u00d3n De Cortinas Y Visillos",
    "sg:phone":"+34 975 22 89 05",
    "sg:postcode":"42001",
    "sg:province":"Soria",
    "wof:name":"Alonso Jimenez Elvira",
    "wof:placetype":"venue"
},
  "geometry": {"coordinates":[-2.4681425095,41.7663116455],"type":"Point"}
}