{
  "type": "Feature",
  "properties": {
    "addr:full":"Carrer de Andreu Costa, 18 Manlleu Barcelona 08560",
    "addr:housenumber":"18",
    "addr:postcode":"08560",
    "addr:street":"Carrer De Andreu Costa",
    "iso:country":"ES",
    "sg:address":"Carrer de Andreu Costa, 18",
    "sg:city":"Manlleu",
    "sg:orig_category":"Torrefactado De Caf\u00c9",
    "sg:phone":"+34 938 50 62 70",
    "sg:postcode":"08560",
    "sg:province":"Barcelona",
    "wof:name":"Llado Subi\u00f1a Jose Maria",
    "wof:placetype":"venue"
},
  "geometry": {"coordinates":[2.2970769405,42.0046768188],"type":"Point"}
}