{
  "type": "Feature",
  "properties": {
    "addr:full":"Praj Sanchez (los), 261 Esparragal Murcia 30891",
    "addr:housenumber":"261",
    "addr:postcode":"30891",
    "addr:street":"Los",
    "iso:country":"ES",
    "sg:address":"Praj Sanchez (los), 261",
    "sg:city":"Esparragal",
    "sg:orig_category":"Flores Y Plantas Naturales (al Por Mayor)",
    "sg:phone":"+34 968 43 66 37",
    "sg:postcode":"30891",
    "sg:province":"Murcia",
    "wof:name":"Conchillo Oliver Diego",
    "wof:placetype":"venue"
},
  "geometry": {"coordinates":[-1.7536230087,37.5709495544],"type":"Point"}
}