{
  "type": "Feature",
  "properties": {
    "iso:country":"ES",
    "sg:address":"Avda Alfonso Vi, 15",
    "sg:city":"Salamanca",
    "sg:orig_category":"Reposter\u00cdas",
    "sg:phone":"+34 923 24 24 23",
    "sg:postcode":"37005",
    "sg:province":"Salamanca",
    "wof:name":"Gallardo Blacno Leonor",
    "wof:placetype":"venue"
},
  "geometry": {"coordinates":[-5.6607751846,40.9758148193],"type":"Point"}
}