{
  "type": "Feature",
  "properties": {
    "iso:country":"ES",
    "sg:address":"Calle de Sagrado Corazon, S/n",
    "sg:city":"San Mames De Campos",
    "sg:orig_category":"Administraci\u00d3n En Agricultura",
    "sg:phone":"+34 979 88 09 92",
    "sg:postcode":"34127",
    "sg:province":"Palencia",
    "wof:name":"Sociedad Agraria De Transformacion",
    "wof:placetype":"venue"
},
  "geometry": {"coordinates":[-4.5668292046,42.3549804688],"type":"Point"}
}