{
  "type": "Feature",
  "properties": {
    "iso:country":"ES",
    "sg:address":"Carr Alcudia, D', 15",
    "sg:city":"Consell",
    "sg:orig_category":"Inmobiliaria (agencias)",
    "sg:phone":"+34 971 62 27 27",
    "sg:postcode":"07330",
    "sg:province":"Islas Baleares",
    "wof:name":"Cascales Coll Juana Maria",
    "wof:placetype":"venue"
},
  "geometry": {"coordinates":[2.8147079945,39.6696205139],"type":"Point"}
}