{
  "type": "Feature",
  "properties": {
    "iso:country":"ES",
    "sg:address":"Rua Celso Emilio Ferreiro, 4",
    "sg:city":"Celanova",
    "sg:orig_category":"Vestidos Para Celebraciones (fabricaci\u00d3n, Al Por Mayor)",
    "sg:phone":"+34 988 43 20 20",
    "sg:postcode":"32800",
    "sg:province":"Ourense",
    "wof:name":"Nu\u00f1ez Enriquez S.l.",
    "wof:placetype":"venue"
},
  "geometry": {"coordinates":[-7.9567470551,42.153339386],"type":"Point"}
}