{
  "type": "Feature",
  "properties": {
    "iso:country":"ES",
    "sg:address":"Calle de Tras La Puerta, 2",
    "sg:city":"Cordoba",
    "sg:orig_category":"Zapatos (al Por Menor)",
    "sg:phone":"+34 957 25 10 51",
    "sg:postcode":"14010",
    "sg:province":"C\u00f3rdoba",
    "wof:name":"Nieto Montoro Antonio",
    "wof:placetype":"venue"
},
  "geometry": {"coordinates":[-4.7634139061,37.8904647827],"type":"Point"}
}