{
  "type": "Feature",
  "properties": {
    "addr:full":"I Poligono Industrial I, S/n Cintruenigo Navarra 31592",
    "addr:housenumber":"s",
    "addr:postcode":"31592",
    "addr:street":"I Poligono Industrial I;/ N",
    "iso:country":"ES",
    "sg:address":"I Poligono Industrial I, S/n",
    "sg:city":"Cintruenigo",
    "sg:orig_category":"Construcciones Met\u00c1licas",
    "sg:phone":"+34 948 81 12 57",
    "sg:postcode":"31592",
    "sg:province":"Navarra",
    "wof:name":"Macrife S.l.",
    "wof:placetype":"venue"
},
  "geometry": {"coordinates":[-1.7964639664,42.0835533142],"type":"Point"}
}