{
  "type": "Feature",
  "properties": {
    "addr:full":"Calle de Don Ramon De La Cruz, 36 Madrid Madrid 28001",
    "addr:housenumber":"36",
    "addr:postcode":"madrid;28001",
    "addr:street":"Calle De Don Ramon De La Cruz",
    "iso:country":"ES",
    "sg:address":"Calle de Don Ramon De La Cruz, 36",
    "sg:city":"Madrid",
    "sg:orig_category":"Inform\u00c1tica Equipo Y Programas (al Por Mayor)",
    "sg:phone":"+34 914 32 02 85",
    "sg:postcode":"28001",
    "sg:province":"Madrid",
    "sg:website":"www.multitrip.com",
    "wof:name":"Misterhouston",
    "wof:placetype":"venue"
},
  "geometry": {"coordinates":[-3.681987524,40.4290084839],"type":"Point"}
}