{
  "type": "Feature",
  "properties": {
    "addr:full":"Calle de Tesoro, 21 Madrid Madrid 28004",
    "addr:housenumber":"21",
    "addr:postcode":"madrid;28004",
    "addr:street":"Calle De Tesoro",
    "iso:country":"ES",
    "sg:address":"Calle de Tesoro, 21",
    "sg:city":"Madrid",
    "sg:orig_category":"Sexshops",
    "sg:phone":"+34 913 60 44 56",
    "sg:postcode":"28004",
    "sg:province":"Madrid",
    "wof:name":"Q & A Telecom S.l.",
    "wof:placetype":"venue"
},
  "geometry": {"coordinates":[-3.7051949501,40.4249420166],"type":"Point"}
}