{
  "type": "Feature",
  "properties": {
    "iso:country":"ES",
    "sg:address":"Crta Azucarera-intelhorce (pi Gudalhorc), 114",
    "sg:city":"Malaga",
    "sg:orig_category":"Equipo De Refrigeraci\u00d3n Industrial",
    "sg:phone":"+34 952 24 24 09",
    "sg:postcode":"29004",
    "sg:province":"M\u00e1laga",
    "wof:name":"Compa\u00d1ia Espa\u00d1ola De Mantenimiento E Instalaciones De Dispensing S.a.",
    "wof:placetype":"venue"
},
  "geometry": {"coordinates":[-4.493473053,36.6957550049],"type":"Point"}
}