{
  "type": "Feature",
  "properties": {
    "addr:full":"Ctra Montcada, 750 Terrassa Barcelona 08227",
    "addr:housenumber":"750",
    "addr:postcode":"08227",
    "addr:street":"Ctra Montcada",
    "iso:country":"ES",
    "sg:address":"Ctra Montcada, 750",
    "sg:city":"Terrassa",
    "sg:orig_category":"Grabados",
    "sg:phone":"+34 937 84 30 04",
    "sg:postcode":"08227",
    "sg:province":"Barcelona",
    "sg:website":"www.magnegraf.com",
    "wof:name":"Magnegraf S.l.",
    "wof:placetype":"venue"
},
  "geometry": {"coordinates":[2.0383529663,41.5572013855],"type":"Point"}
}