{
  "type": "Feature",
  "properties": {
    "iso:country":"ES",
    "sg:address":"Calle de Sierra De Gudar, 3",
    "sg:city":"Zaragoza",
    "sg:orig_category":"Cristaler\u00cdas",
    "sg:phone":"+34 976 29 98 40",
    "sg:postcode":"50015",
    "sg:province":"Zaragoza",
    "wof:name":"Anson Sanchez Jose",
    "wof:placetype":"venue"
},
  "geometry": {"coordinates":[-0.8719862103,41.6630973816],"type":"Point"}
}