{
  "type": "Feature",
  "properties": {
    "iso:country":"ES",
    "sg:address":"Plaz Villa (la), S/n",
    "sg:city":"Noja",
    "sg:orig_category":"Ropa Para Se\u00d1oras (al Por Menor)",
    "sg:phone":"+34 942 67 50 01",
    "sg:postcode":"39180",
    "sg:province":"Cantabria",
    "wof:name":"Pablo Seoane Emilio De",
    "wof:placetype":"venue"
},
  "geometry": {"coordinates":[-3.5296189785,43.4792633057],"type":"Point"}
}