{
  "type": "Feature",
  "properties": {
    "iso:country":"ES",
    "sg:address":"Ctra Estacion, S/n",
    "sg:city":"Caudete",
    "sg:orig_category":"Empresas De Carpinter\u00cda Met\u00c1lica",
    "sg:phone":"+34 965 82 67 49",
    "sg:postcode":"02660",
    "sg:province":"Albacete",
    "wof:name":"Piqueras Azorin Joaquin",
    "wof:placetype":"venue"
},
  "geometry": {"coordinates":[-0.9857239723,38.7085189819],"type":"Point"}
}