{
  "type": "Feature",
  "properties": {
    "iso:country":"ES",
    "sg:address":"Calle de Canalejas, 91",
    "sg:city":"Jumilla",
    "sg:orig_category":"Droguer\u00cdas (al Por Menor)",
    "sg:phone":"+34 968 78 00 72",
    "sg:postcode":"30520",
    "sg:province":"Murcia",
    "wof:name":"Juan Navarro Carmen",
    "wof:placetype":"venue"
},
  "geometry": {"coordinates":[-1.3261921406,38.4761238098],"type":"Point"}
}