{
  "type": "Feature",
  "properties": {
    "iso:country":"ES",
    "sg:address":"Plaz Flores, S/n",
    "sg:city":"Vera",
    "sg:classifiers":[
        {
            "category":"Communications",
            "type":"Services"
        }
    ],
    "sg:phone":"+34 950 39 06 51",
    "sg:postcode":"04620",
    "sg:province":"Almer\u00eda",
    "sg:tags":[
        "televisiones",
        "y",
        "radio"
    ],
    "wof:name":"Sol T.v S.l",
    "wof:placetype":"venue"
},
  "geometry": {"coordinates":[-1.864428997,37.2446937561],"type":"Point"}
}