{
  "type": "Feature",
  "properties": {
    "addr:full":"Ctra Nules (diseminado), S/n Alquerias Valencia Castell\u00f3n 12530",
    "addr:housenumber":"s / n",
    "addr:postcode":"12530",
    "addr:street":"Ctra Nules Diseminado",
    "iso:country":"ES",
    "sg:address":"Ctra Nules (diseminado), S/n",
    "sg:city":"Alquerias Valencia",
    "sg:orig_category":"Frutas Y Legumbres Frescas (al Por Mayor)",
    "sg:phone":"+34 964 51 49 54",
    "sg:postcode":"12530",
    "sg:province":"Castell\u00f3n",
    "wof:name":"Aparici Fruits S.l.",
    "wof:placetype":"venue"
},
  "geometry": {"coordinates":[-0.1134461015,39.8965263367],"type":"Point"}
}