{
  "type": "Feature",
  "properties": {
    "iso:country":"ES",
    "sg:address":"Cmno Huertas, 2",
    "sg:city":"Pozuelo De Alarcon",
    "sg:orig_category":"Cajas De Ahorro",
    "sg:phone":"+34 913 51 60 60",
    "sg:postcode":"28223",
    "sg:province":"Madrid",
    "wof:name":"Caja De Ahorros De Valencia Castellon Y Alicante",
    "wof:placetype":"venue"
},
  "geometry": {"coordinates":[-3.817841053,40.4373435974],"type":"Point"}
}