{
  "type": "Feature",
  "properties": {
    "iso:country":"ES",
    "sg:address":"Carrer de Muntaner, 514",
    "sg:city":"Barcelona",
    "sg:orig_category":"Fabricaci\u00d3n, Venta De Cuadros, Accesorios Para Enmarcar",
    "sg:phone":"+34 932 11 27 41",
    "sg:postcode":"08022",
    "sg:province":"Barcelona",
    "wof:name":"Buera Pueo Maria Luisa",
    "wof:placetype":"venue"
},
  "geometry": {"coordinates":[2.1364929676,41.404296875],"type":"Point"}
}