{
  "type": "Feature",
  "properties": {
    "addr:full":"Calle de Nueva, 47 Motril Granada 18600",
    "addr:housenumber":"47",
    "addr:postcode":"18600",
    "addr:street":"Calle De Nueva",
    "iso:country":"ES",
    "sg:address":"Calle de Nueva, 47",
    "sg:city":"Motril",
    "sg:orig_category":"Pod\u00d3logos: Pedicuros",
    "sg:phone":"+34 958 60 15 63",
    "sg:postcode":"18600",
    "sg:province":"Granada",
    "wof:name":"Haro Roldan Susana",
    "wof:placetype":"venue"
},
  "geometry": {"coordinates":[-3.5181660652,36.7475662231],"type":"Point"}
}