{
  "type": "Feature",
  "properties": {
    "addr:full":"Los Olivos, 8 Letur Albacete 02434",
    "addr:housenumber":"8",
    "addr:postcode":"02434",
    "addr:street":"Los Olivos",
    "iso:country":"ES",
    "sg:address":"Los Olivos, 8",
    "sg:city":"Letur",
    "sg:orig_category":"Transporte En General",
    "sg:phone":"+34 967 42 60 09",
    "sg:postcode":"02434",
    "sg:province":"Albacete",
    "wof:name":"Alarcon Jimenez Soledad",
    "wof:placetype":"venue"
},
  "geometry": {"coordinates":[-2.1025984287,38.361907959],"type":"Point"}
}