{
  "type": "Feature",
  "properties": {
    "addr:full":"Calle de Juan Bravo, 3 Madrid Madrid 28006",
    "addr:housenumber":"3",
    "addr:postcode":"28006",
    "addr:street":"Calle De Juan Bravo",
    "iso:country":"ES",
    "sg:address":"Calle de Juan Bravo, 3",
    "sg:city":"Madrid",
    "sg:orig_category":"Inform\u00c1tica (estudios, Servicios, Asesor\u00cda, Formaci\u00d3n)",
    "sg:phone":"+34 915 76 62 87",
    "sg:postcode":"28006",
    "sg:province":"Madrid",
    "wof:name":"Marketing Y Servicios En Tecnologia S.l.",
    "wof:placetype":"venue"
},
  "geometry": {"coordinates":[-3.6848099232,40.4331092834],"type":"Point"}
}