{
  "type": "Feature",
  "properties": {
    "addr:full":"Cuesta Del Mercado, 1 Huete Cuenca 16500",
    "addr:housenumber":"1",
    "addr:postcode":"16500",
    "addr:street":"Cuesta Del Mercado",
    "iso:country":"ES",
    "sg:address":"Cuesta Del Mercado, 1",
    "sg:city":"Huete",
    "sg:orig_category":"Promotores Constructores",
    "sg:phone":"+34 969 37 10 60",
    "sg:postcode":"16500",
    "sg:province":"Cuenca",
    "wof:name":"Pavimentos Y Hormigones Lopez Vaquero S.l.",
    "wof:placetype":"venue"
},
  "geometry": {"coordinates":[-2.6916589737,40.1434783936],"type":"Point"}
}