{
  "type": "Feature",
  "properties": {
    "addr:full":"Carr Emili Grahit, 62 Girona Girona 17002",
    "addr:housenumber":"62",
    "addr:postcode":"17002",
    "addr:street":"Carr Emili Grahit",
    "iso:country":"ES",
    "sg:address":"Carr Emili Grahit, 62",
    "sg:city":"Girona",
    "sg:orig_category":"Arquitectos",
    "sg:phone":"+34 872 08 16 99",
    "sg:postcode":"17002",
    "sg:province":"Girona",
    "wof:name":"Colomer Payet Jordi",
    "wof:placetype":"venue"
},
  "geometry": {"coordinates":[2.8187448978,41.9808616638],"type":"Point"}
}