{
  "type": "Feature",
  "properties": {
    "addr:full":"Calle de Pradilla, 34 Alacant Alicante 03012",
    "addr:housenumber":"34",
    "addr:postcode":"03012",
    "addr:street":"Calle De Pradilla",
    "iso:country":"ES",
    "sg:address":"Calle de Pradilla, 34",
    "sg:city":"Alacant",
    "sg:orig_category":"Peluquer\u00cdas, Peluquer\u00cda Mixta",
    "sg:phone":"+34 965 24 12 32",
    "sg:postcode":"03012",
    "sg:province":"Alicante",
    "wof:name":"Rosello Martinez Patricia",
    "wof:placetype":"venue"
},
  "geometry": {"coordinates":[-0.4789330065,38.3611717224],"type":"Point"}
}