{
  "type": "Feature",
  "properties": {
    "addr:full":"Calle de Santa Isabel, 1 Toledo Toledo 45002",
    "addr:postcode":"45002",
    "addr:street":"Calle De Santa Isabel",
    "iso:country":"ES",
    "sg:address":"Calle de Santa Isabel, 1",
    "sg:city":"Toledo",
    "sg:orig_category":"Alimentaci\u00d3n General (al Por Menor)",
    "sg:phone":"+34 925 22 32 59",
    "sg:postcode":"45002",
    "sg:province":"Toledo",
    "wof:name":"Utrilla Del Castillo Rufino",
    "wof:placetype":"venue"
},
  "geometry": {"coordinates":[-4.0244860649,39.856212616],"type":"Point"}
}