{
  "type": "Feature",
  "properties": {
    "iso:country":"ES",
    "sg:address":"Plaz Somorrostro, 13",
    "sg:city":"Segovia",
    "sg:orig_category":"Asesor\u00cdas Y Estudios Financieros",
    "sg:phone":"+34 921 43 24 23",
    "sg:postcode":"40005",
    "sg:province":"Segovia",
    "wof:name":"Arribas Alvaro Maria Pilar",
    "wof:placetype":"venue"
},
  "geometry": {"coordinates":[-4.1167445183,40.945186615],"type":"Point"}
}