{
  "type": "Feature",
  "properties": {
    "addr:full":"Carrer de Nanses, S/n Can Pastilla Islas Baleares 07610",
    "addr:housenumber":"s",
    "addr:postcode":"07610",
    "addr:street":"Carrer De Nanses;/ N",
    "iso:country":"ES",
    "sg:address":"Carrer de Nanses, S/n",
    "sg:city":"Can Pastilla",
    "sg:orig_category":"Turismo: Lugares, Circuitos Y Curiosidades",
    "sg:phone":"+34 971 26 41 81",
    "sg:postcode":"07610",
    "sg:province":"Islas Baleares",
    "wof:name":"Tramontana S.l.",
    "wof:placetype":"venue"
},
  "geometry": {"coordinates":[2.7140700817,39.5346298218],"type":"Point"}
}