{
  "type": "Feature",
  "properties": {
    "iso:country":"ES",
    "sg:address":"Calle de Menorca, 1",
    "sg:city":"Alcantarilla",
    "sg:orig_category":"Asesor\u00cda Fiscal Y Jur\u00cddica",
    "sg:phone":"+34 968 89 55 58",
    "sg:postcode":"30820",
    "sg:province":"Murcia",
    "wof:name":"Sanchez Garcia Francisco Jose",
    "wof:placetype":"venue"
},
  "geometry": {"coordinates":[-1.21854496,37.9675827026],"type":"Point"}
}