{
  "type": "Feature",
  "properties": {
    "iso:country":"ES",
    "sg:address":"Calle de Alejandria, 41",
    "sg:city":"Moravit",
    "sg:orig_category":"Agencias Y Agentes Comerciales, Representantes",
    "sg:phone":"+34 966 49 93 11",
    "sg:postcode":"03725",
    "sg:province":"Alicante",
    "wof:name":"Jan Jacob Peeters",
    "wof:placetype":"venue"
},
  "geometry": {"coordinates":[-0.4810059965,38.3452033997],"type":"Point"}
}