{
  "type": "Feature",
  "properties": {
    "iso:country":"ES",
    "sg:address":"Ctra Abanilla (de), 4",
    "sg:city":"Santomera",
    "sg:orig_category":"Frutas Y Legumbres Frescas (al Por Mayor)",
    "sg:phone":"+34 968 86 03 35",
    "sg:postcode":"30140",
    "sg:province":"Murcia",
    "wof:name":"O.marti,c.b.",
    "wof:placetype":"venue"
},
  "geometry": {"coordinates":[-1.0558949709,38.0695343018],"type":"Point"}
}