{
  "type": "Feature",
  "properties": {
    "iso:country":"ES",
    "sg:address":"Calle de Carcava, 5",
    "sg:city":"Mojados",
    "sg:orig_category":"Reposter\u00cdas",
    "sg:phone":"+34 983 60 75 64",
    "sg:postcode":"47250",
    "sg:province":"Valladolid",
    "wof:name":"Gomez Rodriguez Maria Yolanda",
    "wof:placetype":"venue"
},
  "geometry": {"coordinates":[-4.6633491516,41.4313545227],"type":"Point"}
}