{
  "type": "Feature",
  "properties": {
    "addr:full":"Rbla Catalunya (de), 11 Vila-seca Tarragona 43480",
    "addr:housenumber":"11",
    "addr:postcode":"43480",
    "addr:street":"Rbla Catalunya De",
    "iso:country":"ES",
    "sg:address":"Rbla Catalunya (de), 11",
    "sg:city":"Vila-seca",
    "sg:orig_category":"Dietistas",
    "sg:phone":"+34 977 39 33 29",
    "sg:postcode":"43480",
    "sg:province":"Tarragona",
    "wof:name":"El Taronger",
    "wof:placetype":"venue"
},
  "geometry": {"coordinates":[1.148187995,41.1096496582],"type":"Point"}
}