{
  "type": "Feature",
  "properties": {
    "iso:country":"ES",
    "sg:address":"Carrer de Santiago Rusi\u00d1ol, 29",
    "sg:city":"S. Cugat Valles",
    "sg:orig_category":"Partidos Pol\u00cdticos",
    "sg:phone":"+34 936 75 49 14",
    "sg:postcode":"08172",
    "sg:province":"Barcelona",
    "wof:name":"Iniciativa Per Catalunya",
    "wof:placetype":"venue"
},
  "geometry": {"coordinates":[2.0829548836,41.4724998474],"type":"Point"}
}