{
  "type": "Feature",
  "properties": {
    "addr:full":"Avda Cruz Roja (la), 45 Sevilla Sevilla 41009",
    "addr:housenumber":"45",
    "addr:postcode":"41009",
    "addr:street":"Avda Cruz Roja La",
    "iso:country":"ES",
    "sg:address":"Avda Cruz Roja (la), 45",
    "sg:city":"Sevilla",
    "sg:orig_category":"Herboristas (al Por Menor)",
    "sg:phone":"+34 954 43 18 00",
    "sg:postcode":"41009",
    "sg:province":"Sevilla",
    "wof:name":"Iriso Perez Gaspar",
    "wof:placetype":"venue"
},
  "geometry": {"coordinates":[-5.9811592102,37.403213501],"type":"Point"}
}