{
  "type": "Feature",
  "properties": {
    "iso:country":"ES",
    "sg:address":"R Pez Acevedo, 6",
    "sg:city":"Lepe",
    "sg:orig_category":"Ropa Para Se\u00d1oras (al Por Menor)",
    "sg:phone":"+34 959 38 08 04",
    "sg:postcode":"21440",
    "sg:province":"Huelva",
    "wof:name":"Rocion Trastallino, C.b",
    "wof:placetype":"venue"
},
  "geometry": {"coordinates":[-7.2031140327,37.2549629211],"type":"Point"}
}