{
  "type": "Feature",
  "properties": {
    "iso:country":"ES",
    "sg:address":"Carrer de Ample, 61",
    "sg:city":"Reus",
    "sg:orig_category":"Asociaciones Y Clubs Deportivos",
    "sg:phone":"+34 977 32 18 06",
    "sg:postcode":"43202",
    "sg:province":"Tarragona",
    "wof:name":"Puerto Garcia Juan Manuel",
    "wof:placetype":"venue"
},
  "geometry": {"coordinates":[1.1031470299,41.1599197388],"type":"Point"}
}