{
  "type": "Feature",
  "properties": {
    "addr:full":"Ctra Castellar, 462 Terrassa Barcelona 08227",
    "addr:housenumber":"462",
    "addr:postcode":"08227",
    "addr:street":"Ctra Castellar",
    "iso:country":"ES",
    "sg:address":"Ctra Castellar, 462",
    "sg:city":"Terrassa",
    "sg:orig_category":"Poller\u00cda Y Caza (al Por Menor)",
    "sg:phone":"+34 937 83 85 30",
    "sg:postcode":"08227",
    "sg:province":"Barcelona",
    "wof:name":"Mu\u00f1oz Macia Josefa",
    "wof:placetype":"venue"
},
  "geometry": {"coordinates":[2.0333409309,41.5769767761],"type":"Point"}
}