{
  "type": "Feature",
  "properties": {
    "addr:full":"Avgd Regne De Valencia, 40 Almassera Valencia 46132",
    "addr:housenumber":"40",
    "addr:postcode":"46132",
    "addr:street":"Almassera",
    "iso:country":"ES",
    "sg:address":"Avgd Regne De Valencia, 40",
    "sg:city":"Almassera",
    "sg:orig_category":"Porcelana Decorativa",
    "sg:phone":"+34 961 86 03 00",
    "sg:postcode":"46132",
    "sg:province":"Valencia",
    "wof:name":"Nalda S.a.",
    "wof:placetype":"venue"
},
  "geometry": {"coordinates":[-0.35304901,39.5146789551],"type":"Point"}
}