{
  "type": "Feature",
  "properties": {
    "addr:full":"Calle de Ba\u00d1eza (la), 1 Le\u00f3n Le\u00f3n 24007",
    "addr:housenumber":"1",
    "addr:postcode":"24007",
    "addr:street":"Calle De Ban\u0303Eza La;Leo\u0301N",
    "iso:country":"ES",
    "sg:address":"Calle de Ba\u00d1eza (la), 1",
    "sg:city":"Le\u00f3n",
    "sg:orig_category":"Molduras, Junquillos, Listones Y Molduras Perforadas",
    "sg:phone":"+34 987 23 69 58",
    "sg:postcode":"24007",
    "sg:province":"Le\u00f3n",
    "wof:name":"Marcos Del Rio Nemesio",
    "wof:placetype":"venue"
},
  "geometry": {"coordinates":[-5.570912838,42.6075325012],"type":"Point"}
}