{
  "type": "Feature",
  "properties": {
    "addr:full":"Rond Collsalarca, 89 Sabadell Barcelona 08207",
    "addr:housenumber":"89",
    "addr:postcode":"08207",
    "addr:street":"Collsalarca",
    "iso:country":"ES",
    "sg:address":"Rond Collsalarca, 89",
    "sg:city":"Sabadell",
    "sg:orig_category":"Empresarios",
    "sg:phone":"+34 937 24 30 59",
    "sg:postcode":"08207",
    "sg:province":"Barcelona",
    "wof:name":"Lozano S.c.p.",
    "wof:placetype":"venue"
},
  "geometry": {"coordinates":[2.0953760147,41.566783905],"type":"Point"}
}