{
  "type": "Feature",
  "properties": {
    "iso:country":"ES",
    "sg:address":"Calle de Calvario, 7",
    "sg:city":"Granadilla Abona",
    "sg:orig_category":"Peluquer\u00cdas, Peluquer\u00cda Mixta",
    "sg:phone":"+34 922 77 20 56",
    "sg:postcode":"38600",
    "sg:province":"Santa Cruz De Tenerife",
    "wof:name":"Casanova Perez Maria Mercedes",
    "wof:placetype":"venue"
},
  "geometry": {"coordinates":[-16.5769100189,28.1201820374],"type":"Point"}
}