{
  "type": "Feature",
  "properties": {
    "iso:country":"ES",
    "sg:address":"Cra Pobla, 22",
    "sg:city":"Vilanova Cami",
    "sg:orig_category":"Cer\u00c1mica Art\u00cdstica Y Decorativa",
    "sg:phone":"+34 938 04 70 52",
    "sg:postcode":"08788",
    "sg:province":"Barcelona",
    "sg:website":"www.solincer.com",
    "wof:name":"Solincer-soluciones Para La Industria Ceramica S.l.l.",
    "wof:placetype":"venue"
},
  "geometry": {"coordinates":[1.6405899525,41.5763664246],"type":"Point"}
}