{
  "type": "Feature",
  "properties": {
    "iso:country":"ES",
    "sg:address":"Calle de Batalla De Lepanto, 1",
    "sg:city":"Arenas San Pedro",
    "sg:orig_category":"M\u00c9dicos: Estomatolog\u00cda",
    "sg:phone":"+34 920 37 20 95",
    "sg:postcode":"05400",
    "sg:province":"\u00c1vila",
    "wof:name":"Yudicello Cortez Mario Cesar",
    "wof:placetype":"venue"
},
  "geometry": {"coordinates":[-5.0854434967,40.2109489441],"type":"Point"}
}