{
  "type": "Feature",
  "properties": {
    "addr:full":"Calle de Virgen De Loreto, 53 Castilleja Cuesta Sevilla 41950",
    "addr:housenumber":"53",
    "addr:postcode":"41950",
    "addr:street":"Calle De Virgen De Loreto;Cuesta Sevilla",
    "iso:country":"ES",
    "sg:address":"Calle de Virgen De Loreto, 53",
    "sg:city":"Castilleja Cuesta",
    "sg:orig_category":"Cerrajer\u00cda, Ferrallista",
    "sg:phone":"+34 954 16 18 02",
    "sg:postcode":"41950",
    "sg:province":"Sevilla",
    "wof:name":"Manufacturas Negron S.l.",
    "wof:placetype":"venue"
},
  "geometry": {"coordinates":[-6.048388958,37.3835906982],"type":"Point"}
}