{
  "type": "Feature",
  "properties": {
    "addr:full":"Carrer de Hospital (de L'), 48 Arbo\u00e7 Tarragona 43720",
    "addr:housenumber":"48",
    "addr:postcode":"43720",
    "addr:street":"Carrer De Hospital De L '",
    "iso:country":"ES",
    "sg:address":"Carrer de Hospital (de L'), 48",
    "sg:city":"Arbo\u00e7",
    "sg:orig_category":"Asilos De Ancianos. Centros Privados",
    "sg:phone":"+34 977 67 03 07",
    "sg:postcode":"43720",
    "sg:province":"Tarragona",
    "wof:name":"Congregacion Carmelitas Misioneras Teresianas",
    "wof:placetype":"venue"
},
  "geometry": {"coordinates":[1.5998339653,41.2674865723],"type":"Point"}
}