{
  "type": "Feature",
  "properties": {
    "addr:full":"Carrer de Valencia, 5 Barcelona Barcelona 08015",
    "addr:housenumber":"5",
    "addr:postcode":"08015",
    "addr:street":"Carrer De Valencia",
    "iso:country":"ES",
    "sg:address":"Carrer de Valencia, 5",
    "sg:city":"Barcelona",
    "sg:orig_category":"Cables Y Hilos El\u00c9ctricos (fabricaci\u00d3n, Al Por Mayor)",
    "sg:phone":"+34 932 28 22 89",
    "sg:postcode":"08015",
    "sg:province":"Barcelona",
    "sg:website":"www.fibercom.es",
    "wof:name":"Fibercom S.l.",
    "wof:placetype":"venue"
},
  "geometry": {"coordinates":[2.1451940536,41.3792419434],"type":"Point"}
}