{
  "type": "Feature",
  "properties": {
    "iso:country":"ES",
    "sg:address":"Calle de Travieso, 7",
    "sg:city":"Palmas De Gran Canaria",
    "sg:orig_category":"Zapatos (al Por Menor)",
    "sg:phone":"+34 928 37 28 68",
    "sg:postcode":"35002",
    "sg:province":"Las Palmas",
    "wof:name":"Rodriguez Valido Julio",
    "wof:placetype":"venue"
},
  "geometry": {"coordinates":[-15.4159946442,28.1050376892],"type":"Point"}
}