{
  "type": "Feature",
  "properties": {
    "addr:full":"Plaz Nueva De Gamonal, 3 Burgos Burgos 09007",
    "addr:housenumber":"3",
    "addr:postcode":"09007",
    "addr:street":"Plaz Nueva De Gamonal",
    "iso:country":"ES",
    "sg:address":"Plaz Nueva De Gamonal, 3",
    "sg:city":"Burgos",
    "sg:orig_category":"Asociaciones, Organismos Culturales Y Socioeducativos",
    "sg:phone":"+34 947 48 19 91",
    "sg:postcode":"09007",
    "sg:province":"Burgos",
    "wof:name":"Ce Circulo Catolico",
    "wof:placetype":"venue"
},
  "geometry": {"coordinates":[-3.668569088,42.3541755676],"type":"Point"}
}