{
  "type": "Feature",
  "properties": {
    "addr:full":"Calle de Bola\u00d1os, 15 Almagro Ciudad Real 13270",
    "addr:housenumber":"15",
    "addr:postcode":"13270",
    "addr:street":"Calle De Bolan\u0303Os",
    "iso:country":"ES",
    "sg:address":"Calle de Bola\u00d1os, 15",
    "sg:city":"Almagro",
    "sg:orig_category":"Ense\u00d1anza, Formaci\u00d3n Profesional: Aprendizaje",
    "sg:phone":"+34 926 88 29 30",
    "sg:postcode":"13270",
    "sg:province":"Ciudad Real",
    "wof:name":"Direccion General De La Guardia Civil",
    "wof:placetype":"venue"
},
  "geometry": {"coordinates":[-3.7073349953,38.8905487061],"type":"Point"}
}