{
  "type": "Feature",
  "properties": {
    "addr:full":"Calle de Doctor Juan De Padilla, 40 Palmas De Gran Canaria Las Palmas 35002",
    "addr:housenumber":"40",
    "addr:postcode":"35002",
    "addr:street":"Calle De Doctor Juan De Padilla",
    "iso:country":"ES",
    "sg:address":"Calle de Doctor Juan De Padilla, 40",
    "sg:city":"Palmas De Gran Canaria",
    "sg:orig_category":"Peluqueros: De Se\u00d1oras",
    "sg:phone":"+34 928 37 26 20",
    "sg:postcode":"35002",
    "sg:province":"Las Palmas",
    "wof:name":"Christian Peluqueria S.l.",
    "wof:placetype":"venue"
},
  "geometry": {"coordinates":[-15.4192428589,28.1058616638],"type":"Point"}
}