{
  "type": "Feature",
  "properties": {
    "addr:full":"Carrer de Bonaire, 38 Mora D'ebre Tarragona 43740",
    "addr:housenumber":"38",
    "addr:postcode":"43740",
    "addr:street":"Carrer De Bonaire",
    "iso:country":"ES",
    "sg:address":"Carrer de Bonaire, 38",
    "sg:city":"Mora D'ebre",
    "sg:orig_category":"Artes Gr\u00c1ficas, Artes Pl\u00c1sticas: Material Y Suministros (al Por Menor)",
    "sg:phone":"+34 977 40 26 12",
    "sg:postcode":"43740",
    "sg:province":"Tarragona",
    "wof:name":"Pi\u00f1ol Vilas Jose",
    "wof:placetype":"venue"
},
  "geometry": {"coordinates":[1.2540999651,41.1169281006],"type":"Point"}
}