{
  "type": "Feature",
  "properties": {
    "addr:full":"Calle de Guillem De Vinatea, 35 Burriana Castell\u00f3n 12530",
    "addr:housenumber":"35",
    "addr:postcode":"12530",
    "addr:street":"Calle De Guillem De Vinatea",
    "iso:country":"ES",
    "sg:address":"Calle de Guillem De Vinatea, 35",
    "sg:city":"Burriana",
    "sg:orig_category":"Plomeros",
    "sg:phone":"+34 964 57 03 93",
    "sg:postcode":"12530",
    "sg:province":"Castell\u00f3n",
    "wof:name":"Font-bur Cdad.",
    "wof:placetype":"venue"
},
  "geometry": {"coordinates":[-0.0790330023,39.888004303],"type":"Point"}
}