{
  "type": "Feature",
  "properties": {
    "addr:full":"Rbla Mendez Nu\u00d1ez, 9 Alacant Alicante 03002",
    "addr:housenumber":"9",
    "addr:postcode":"03002",
    "addr:street":"Rbla Mendez Nun\u0303Ez",
    "iso:country":"ES",
    "sg:address":"Rbla Mendez Nu\u00d1ez, 9",
    "sg:city":"Alacant",
    "sg:orig_category":"Parques De Atracciones Y Centros De Esparcimiento",
    "sg:phone":"+34 965 21 36 35",
    "sg:postcode":"03002",
    "sg:province":"Alicante",
    "wof:name":"Recreativos Del Este S. A.",
    "wof:placetype":"venue"
},
  "geometry": {"coordinates":[-0.4835120142,38.3448753357],"type":"Point"}
}