{
  "type": "Feature",
  "properties": {
    "addr:full":"Calle de Real, 8 Palazuelo De Orbigo Le\u00f3n 24285",
    "addr:housenumber":"8",
    "addr:postcode":"24285",
    "addr:street":"Calle De Real;Leo\u0301N",
    "iso:country":"ES",
    "sg:address":"Calle de Real, 8",
    "sg:city":"Palazuelo De Orbigo",
    "sg:orig_category":"Empresarios",
    "sg:phone":"+34 987 36 30 07",
    "sg:postcode":"24285",
    "sg:province":"Le\u00f3n",
    "wof:name":"Frangal S.l.",
    "wof:placetype":"venue"
},
  "geometry": {"coordinates":[-5.8814368248,42.5262794495],"type":"Point"}
}