{
  "type": "Feature",
  "properties": {
    "addr:full":"Alam Recalde, 37 Bilbao Vizcaya 48011",
    "addr:housenumber":"37",
    "addr:postcode":"48011",
    "addr:street":"Alam Recalde",
    "iso:country":"ES",
    "sg:address":"Alam Recalde, 37",
    "sg:city":"Bilbao",
    "sg:orig_category":"Bordado, Marcado A Medida",
    "sg:phone":"+34 944 10 21 80",
    "sg:postcode":"48011",
    "sg:province":"Vizcaya",
    "wof:name":"Lobera Aman Maria",
    "wof:placetype":"venue"
},
  "geometry": {"coordinates":[-2.9355049133,43.2612266541],"type":"Point"}
}