{
  "type": "Feature",
  "properties": {
    "iso:country":"ES",
    "sg:address":"Carrer de Garcilaso, 3",
    "sg:city":"Sabadell",
    "sg:orig_category":"Productos Qu\u00cdmicos (fabricaci\u00d3n, Al Por Mayor)",
    "sg:phone":"+34 937 27 55 50",
    "sg:postcode":"08201",
    "sg:province":"Barcelona",
    "wof:name":"Spm Quimica S.l.",
    "wof:placetype":"venue"
},
  "geometry": {"coordinates":[2.1068730354,41.5506248474],"type":"Point"}
}