{
  "type": "Feature",
  "properties": {
    "iso:country":"ES",
    "sg:address":"Av Gaudi, 66",
    "sg:city":"Barcelona",
    "sg:orig_category":"Imprenta",
    "sg:phone":"+34 933 47 65 45",
    "sg:postcode":"08025",
    "sg:province":"Barcelona",
    "wof:name":"Oltra Monforte Alejandro",
    "wof:placetype":"venue"
},
  "geometry": {"coordinates":[2.174612999,41.4100608826],"type":"Point"}
}