{
  "type": "Feature",
  "properties": {
    "iso:country":"ES",
    "sg:address":"Calle de Mendo Benavides, S/n",
    "sg:city":"Castellar",
    "sg:orig_category":"Librer\u00cdas",
    "sg:phone":"+34 953 46 03 24",
    "sg:postcode":"23260",
    "sg:province":"Ja\u00e9n",
    "wof:name":"Ojeda Ochoa Encarnacion",
    "wof:placetype":"venue"
},
  "geometry": {"coordinates":[-3.1285440922,38.2544631958],"type":"Point"}
}