{
  "type": "Feature",
  "properties": {
    "addr:full":"Calle de Caballeros, 16 Castellon Castell\u00f3n 12001",
    "addr:housenumber":"16",
    "addr:postcode":"12001",
    "addr:street":"Calle De Caballeros",
    "iso:country":"ES",
    "sg:address":"Calle de Caballeros, 16",
    "sg:city":"Castellon",
    "sg:orig_category":"Asociaciones, Organismos Culturales Y Socioeducativos",
    "sg:phone":"+34 964 23 66 28",
    "sg:postcode":"12001",
    "sg:province":"Castell\u00f3n",
    "wof:name":"Arsipe Gestion De Patrimonio Cultural S.l.l.",
    "wof:placetype":"venue"
},
  "geometry": {"coordinates":[-0.0362492986,39.9873199463],"type":"Point"}
}