{
  "type": "Feature",
  "properties": {
    "iso:country":"ES",
    "sg:address":"Calle de Higinio Mangas, 1",
    "sg:city":"Valladolid",
    "sg:orig_category":"Asociaciones Humanitarias, De Cooperaci\u00d3n, De Acci\u00d3n Social",
    "sg:phone":"+34 983 30 34 93",
    "sg:postcode":"47005",
    "sg:province":"Valladolid",
    "wof:name":"Asociacion Vallisoletana De Alcoholicos Rehabilitados",
    "wof:placetype":"venue"
},
  "geometry": {"coordinates":[-4.7129511833,41.6507072449],"type":"Point"}
}