{
  "type": "Feature",
  "properties": {
    "iso:country":"ES",
    "sg:address":"Avgd Vicente Ferri, 24",
    "sg:city":"Canals",
    "sg:orig_category":"Supermercados Y Hipermercados",
    "sg:phone":"+34 962 24 38 49",
    "sg:postcode":"46650",
    "sg:province":"Valencia",
    "wof:name":"Merkavalla S.l.",
    "wof:placetype":"venue"
},
  "geometry": {"coordinates":[-0.5857679844,38.9639892578],"type":"Point"}
}