{
  "type": "Feature",
  "properties": {
    "iso:country":"ES",
    "sg:address":"Calle de Poligono Industrial El Pabellon, S/n",
    "sg:city":"Jerez De Los Caballeros",
    "sg:orig_category":"Producci\u00d3n, Distribuci\u00d3n De Gas Butano Y Propano",
    "sg:phone":"+34 924 73 19 14",
    "sg:postcode":"06380",
    "sg:province":"Badajoz",
    "wof:name":"Dominguez Perez Miguel Antonio",
    "wof:placetype":"venue"
},
  "geometry": {"coordinates":[-6.7662930489,38.3218612671],"type":"Point"}
}