{
  "type": "Feature",
  "properties": {
    "iso:country":"ES",
    "sg:address":"Calle de Cea Bermudez, 43",
    "sg:city":"Madrid",
    "sg:orig_category":"Sindicatos De Trabajadores",
    "sg:phone":"+34 915 43 11 95",
    "sg:postcode":"28003",
    "sg:province":"Madrid",
    "wof:name":"Confederacion De Sindicatos Independientes Y Sindical De Funcionari",
    "wof:placetype":"venue"
},
  "geometry": {"coordinates":[-3.7130391598,40.4389457703],"type":"Point"}
}