{
  "type": "Feature",
  "properties": {
    "addr:full":"C/ Josep Tarradellas, 2 Banyoles Girona 17820",
    "addr:housenumber":"2",
    "addr:postcode":"17820",
    "addr:street":"C / Josep Tarradellas",
    "iso:country":"ES",
    "sg:address":"C/ Josep Tarradellas, 2",
    "sg:city":"Banyoles",
    "sg:orig_category":"Asesor\u00cda Fiscal Y Jur\u00cddica",
    "sg:phone":"+34 972 57 00 03",
    "sg:postcode":"17820",
    "sg:province":"Girona",
    "wof:name":"Assessoria Avui S.l.",
    "wof:placetype":"venue"
},
  "geometry": {"coordinates":[2.7627551556,42.1229782104],"type":"Point"}
}