{
  "type": "Feature",
  "properties": {
    "iso:country":"ES",
    "sg:address":"Somosierra, 6",
    "sg:city":"Galapagar",
    "sg:orig_category":"Promotores Constructores",
    "sg:phone":"+34 918 51 95 31",
    "sg:postcode":"28260",
    "sg:province":"Madrid",
    "wof:name":"La Calma Sanyago S.l.",
    "wof:placetype":"venue"
},
  "geometry": {"coordinates":[-4.0294408798,40.6205825806],"type":"Point"}
}