{
  "type": "Feature",
  "properties": {
    "addr:full":"Pase Zorrilla, 53 Valladolid Valladolid 47007",
    "addr:housenumber":"53",
    "addr:postcode":"47007",
    "addr:street":"Zorrilla",
    "iso:country":"ES",
    "sg:address":"Pase Zorrilla, 53",
    "sg:city":"Valladolid",
    "sg:orig_category":"Bancos",
    "sg:phone":"+34 983 27 88 56",
    "sg:postcode":"47007",
    "sg:province":"Valladolid",
    "wof:name":"Banc Sabadell S.a.",
    "wof:placetype":"venue"
},
  "geometry": {"coordinates":[-4.7382822037,41.6382446289],"type":"Point"}
}