{
  "type": "Feature",
  "properties": {
    "addr:full":"Avda Amsterdam (de), 14 Cristianos Santa Cruz De Tenerife 38650",
    "addr:postcode":"38650",
    "addr:street":"Avda",
    "iso:country":"ES",
    "sg:address":"Avda Amsterdam (de), 14",
    "sg:city":"Cristianos",
    "sg:orig_category":"Inmobiliaria (agencias)",
    "sg:phone":"+34 922 79 90 19",
    "sg:postcode":"38650",
    "sg:province":"Santa Cruz De Tenerife",
    "wof:name":"Obrian  Kevin",
    "wof:placetype":"venue"
},
  "geometry": {"coordinates":[-16.7100296021,28.0524272919],"type":"Point"}
}