{
  "type": "Feature",
  "properties": {
    "iso:country":"ES",
    "sg:address":"Avgd De L'alt Urgell, 17",
    "sg:city":"Oliana",
    "sg:orig_category":"Florister\u00cdas",
    "sg:phone":"+34 973 47 01 54",
    "sg:postcode":"25790",
    "sg:province":"Lleida",
    "wof:name":"More Viarut Maria Pilar",
    "wof:placetype":"venue"
},
  "geometry": {"coordinates":[1.3131630421,42.068271637],"type":"Point"}
}