{
  "type": "Feature",
  "properties": {
    "iso:country":"ES",
    "sg:address":"General Prim, 29",
    "sg:city":"Castellar",
    "sg:orig_category":"Reposter\u00cdas",
    "sg:phone":"+34 953 46 01 54",
    "sg:postcode":"23260",
    "sg:province":"Ja\u00e9n",
    "wof:name":"Panaderia Bolleria Sagrado Corazon S.l.",
    "wof:placetype":"venue"
},
  "geometry": {"coordinates":[-3.1293420792,38.2528266907],"type":"Point"}
}