{
  "type": "Feature",
  "properties": {
    "iso:country":"ES",
    "sg:address":"Carrer de Gaudi, 69",
    "sg:city":"Manresa",
    "sg:orig_category":"Telas Y Sedas (al Por Menor)",
    "sg:phone":"+34 938 73 88 46",
    "sg:postcode":"08243",
    "sg:province":"Barcelona",
    "wof:name":"Soler Comellas Jose",
    "wof:placetype":"venue"
},
  "geometry": {"coordinates":[1.8381279707,41.7268829346],"type":"Point"}
}