{
  "type": "Feature",
  "properties": {
    "addr:full":"Carrer de Sant Bartomeu, 49 Campello Alicante 03560",
    "addr:housenumber":"49",
    "addr:postcode":"03560",
    "addr:street":"Carrer De Sant Bartomeu",
    "iso:country":"ES",
    "sg:address":"Carrer de Sant Bartomeu, 49",
    "sg:city":"Campello",
    "sg:orig_category":"Inmobiliaria (agencias)",
    "sg:phone":"+34 965 63 63 28",
    "sg:postcode":"03560",
    "sg:province":"Alicante",
    "sg:website":"www.medsolproperty.com",
    "wof:name":"Medsol Consultancy S.l.",
    "wof:placetype":"venue"
},
  "geometry": {"coordinates":[-0.3911089897,38.4261322021],"type":"Point"}
}