{
  "type": "Feature",
  "properties": {
    "iso:country":"ES",
    "sg:address":"Av Passeig Del Comtat, 9",
    "sg:city":"Cocentaina",
    "sg:orig_category":"Telas Y Sedas (al Por Menor)",
    "sg:phone":"+34 965 59 10 63",
    "sg:postcode":"03820",
    "sg:province":"Alicante",
    "wof:name":"Manolo S. L.",
    "wof:placetype":"venue"
},
  "geometry": {"coordinates":[-0.4387629926,38.7515029907],"type":"Point"}
}