{
  "type": "Feature",
  "properties": {
    "addr:full":"Calle de Pedro De Valdivia, 13 Huelva Huelva 21004",
    "addr:housenumber":"13",
    "addr:postcode":"21004",
    "addr:street":"Calle De Pedro De Valdivia",
    "iso:country":"ES",
    "sg:address":"Calle de Pedro De Valdivia, 13",
    "sg:city":"Huelva",
    "sg:orig_category":"Electrodom\u00c9sticos (al Por Menor)",
    "sg:phone":"+34 959 22 12 50",
    "sg:postcode":"21004",
    "sg:province":"Huelva",
    "wof:name":"Rochamar S.l.",
    "wof:placetype":"venue"
},
  "geometry": {"coordinates":[-6.9423089027,37.2577209473],"type":"Point"}
}