{
  "type": "Feature",
  "properties": {
    "iso:country":"ES",
    "sg:address":"Los Silos, 3",
    "sg:city":"Cuevas Almanzora",
    "sg:orig_category":"Reparaciones Y Remolcado De Veh\u00cdculos",
    "sg:phone":"+34 950 45 64 51",
    "sg:postcode":"04610",
    "sg:province":"Almer\u00eda",
    "wof:name":"Castro Garcia Miguel",
    "wof:placetype":"venue"
},
  "geometry": {"coordinates":[-1.8781139851,37.2911911011],"type":"Point"}
}