{
  "type": "Feature",
  "properties": {
    "addr:full":"Afueras, S/n Collado C\u00e1ceres 10414",
    "addr:postcode":"10414",
    "addr:street":"Afueras S / N Collado Ca\u0301Ceres",
    "iso:country":"ES",
    "sg:address":"Afueras, S/n",
    "sg:city":"Collado",
    "sg:orig_category":"Material Y Herramientas Agr\u00cdcolas",
    "sg:phone":"+34 927 19 41 00",
    "sg:postcode":"10414",
    "sg:province":"C\u00e1ceres",
    "wof:name":"Talleres Agomecanicos S.l.",
    "wof:placetype":"venue"
},
  "geometry": {"coordinates":[-5.7204852104,40.0573692322],"type":"Point"}
}