{
  "type": "Feature",
  "properties": {
    "iso:country":"ES",
    "sg:address":"Calle de Chapineria, 4",
    "sg:city":"Madrid",
    "sg:orig_category":"Empresas De Carpinter\u00cda De Madera",
    "sg:phone":"+34 913 16 20 09",
    "sg:postcode":"28035",
    "sg:province":"Madrid",
    "wof:name":"Beniodon S.l.",
    "wof:placetype":"venue"
},
  "geometry": {"coordinates":[-3.7394530773,40.4761810303],"type":"Point"}
}