{
  "type": "Feature",
  "properties": {
    "addr:full":"Carrer de M. Mediterrania, S/n Galatzo Islas Baleares 07180",
    "addr:housenumber":"s / n",
    "addr:postcode":"07180",
    "addr:street":"Carrer De M. Mediterrania",
    "iso:country":"ES",
    "sg:address":"Carrer de M. Mediterrania, S/n",
    "sg:city":"Galatzo",
    "sg:orig_category":"Promotores Constructores",
    "sg:phone":"+34 971 69 95 59",
    "sg:postcode":"07180",
    "sg:province":"Islas Baleares",
    "wof:name":"Construcciones Llabres Feliu S.a.",
    "wof:placetype":"venue"
},
  "geometry": {"coordinates":[2.5037999153,39.5288658142],"type":"Point"}
}