{
  "type": "Feature",
  "properties": {
    "addr:full":"Canadenca, 6 Tremp Lleida 25620",
    "addr:housenumber":"6",
    "addr:postcode":"25620",
    "addr:street":"Canadenca",
    "iso:country":"ES",
    "sg:address":"Canadenca, 6",
    "sg:city":"Tremp",
    "sg:orig_category":"Acondicionamiento, Mantenimiento De Jardines Y Parques",
    "sg:phone":"+34 973 65 26 63",
    "sg:postcode":"25620",
    "sg:province":"Lleida",
    "wof:name":"Jardineria Servei Verd S.l.",
    "wof:placetype":"venue"
},
  "geometry": {"coordinates":[0.8881300092,42.1672935486],"type":"Point"}
}