{
  "type": "Feature",
  "properties": {
    "iso:country":"ES",
    "sg:address":"Carrer de Francesc Carbonell, 21",
    "sg:city":"Barcelona",
    "sg:orig_category":"Transportes Por Carretera: Lotes Completos, Mercanc\u00cdas Diversas",
    "sg:phone":"+34 932 80 13 65",
    "sg:postcode":"08034",
    "sg:province":"Barcelona",
    "wof:name":"Alimentaciones Escolares S.a.",
    "wof:placetype":"venue"
},
  "geometry": {"coordinates":[2.1256456375,41.3928985596],"type":"Point"}
}