{
  "type": "Feature",
  "properties": {
    "addr:full":"Calle de Francisco De Goya, 5 Barbastro Huesca 22300",
    "addr:housenumber":"5",
    "addr:postcode":"22300",
    "addr:street":"Calle De Francisco De Goya",
    "iso:country":"ES",
    "sg:address":"Calle de Francisco De Goya, 5",
    "sg:city":"Barbastro",
    "sg:orig_category":"Agencias Y Agentes Comerciales, Representantes",
    "sg:phone":"+34 974 31 40 39",
    "sg:postcode":"22300",
    "sg:province":"Huesca",
    "wof:name":"Mozas Muro Carlos",
    "wof:placetype":"venue"
},
  "geometry": {"coordinates":[0.1307796985,42.0187110901],"type":"Point"}
}