{
  "type": "Feature",
  "properties": {
    "addr:full":"Avda Coru\u00d1a, 70 Rozas De Madrid Madrid 28230",
    "addr:housenumber":"70",
    "addr:postcode":"28230",
    "addr:street":"Avda Corun\u0303A",
    "iso:country":"ES",
    "sg:address":"Avda Coru\u00d1a, 70",
    "sg:city":"Rozas De Madrid",
    "sg:orig_category":"Centros De Educaci\u00d3n Especial",
    "sg:phone":"+34 916 36 02 91",
    "sg:postcode":"28230",
    "sg:province":"Madrid",
    "wof:name":"Comunidad Autonoma De Madrid-centros De Educacion",
    "wof:placetype":"venue"
},
  "geometry": {"coordinates":[-3.8665399551,40.4900093079],"type":"Point"}
}