{
  "type": "Feature",
  "properties": {
    "iso:country":"ES",
    "sg:address":"Calle de Goya, 15",
    "sg:city":"Majadahonda",
    "sg:orig_category":"Distribuci\u00d3n De Petr\u00d3leo Y Derivados",
    "sg:phone":"+34 916 02 80 82",
    "sg:postcode":"28220",
    "sg:province":"Madrid",
    "wof:name":"Monteclaro Area De Servicio S.a.",
    "wof:placetype":"venue"
},
  "geometry": {"coordinates":[-3.8608129025,40.45104599],"type":"Point"}
}