{
  "type": "Feature",
  "properties": {
    "iso:country":"ES",
    "sg:address":"Carrer de Santander, 9",
    "sg:city":"Sant Vicen\u00c7 Dels Horts",
    "sg:orig_category":"Fabricaci\u00d3n De Moldes Y Modelos",
    "sg:phone":"+34 936 56 42 62",
    "sg:postcode":"08620",
    "sg:province":"Barcelona",
    "wof:name":"Plasticos Galma S.l.",
    "wof:placetype":"venue"
},
  "geometry": {"coordinates":[2.0065391064,41.3888626099],"type":"Point"}
}