{
  "type": "Feature",
  "properties": {
    "iso:country":"ES",
    "sg:address":"Avda Alfonso El Sabio, 23",
    "sg:city":"Novelda",
    "sg:orig_category":"Reposter\u00cdas",
    "sg:phone":"+34 965 60 72 99",
    "sg:postcode":"03660",
    "sg:province":"Alicante",
    "wof:name":"Marbel Cdad.",
    "wof:placetype":"venue"
},
  "geometry": {"coordinates":[-0.7734810114,38.3815002441],"type":"Point"}
}