{
  "type": "Feature",
  "properties": {
    "addr:full":"Calle de Ferrocarril, 69 Almeria Almer\u00eda 04007",
    "addr:housenumber":"69",
    "addr:postcode":"04007",
    "addr:street":"Calle De Ferrocarril",
    "iso:country":"ES",
    "sg:address":"Calle de Ferrocarril, 69",
    "sg:city":"Almeria",
    "sg:orig_category":"Quincaller\u00cda (al Por Menor)",
    "sg:phone":"+34 950 25 21 43",
    "sg:postcode":"04007",
    "sg:province":"Almer\u00eda",
    "wof:name":"Miranda Sanchez Josefa",
    "wof:placetype":"venue"
},
  "geometry": {"coordinates":[-2.4501636028,36.8343353271],"type":"Point"}
}