{
  "type": "Feature",
  "properties": {
    "addr:full":"Av Santa Coloma, 40 Santa Coloma De Gramenet Barcelona 08922",
    "addr:housenumber":"40",
    "addr:postcode":"08922",
    "addr:street":"Av Santa Coloma",
    "iso:country":"ES",
    "sg:address":"Av Santa Coloma, 40",
    "sg:city":"Santa Coloma De Gramenet",
    "sg:orig_category":"Caf\u00c9s, Bares, Cervecer\u00cdas",
    "sg:phone":"+34 933 86 77 91",
    "sg:postcode":"08922",
    "sg:province":"Barcelona",
    "wof:name":"Vicente Sanchez Raquel",
    "wof:placetype":"venue"
},
  "geometry": {"coordinates":[2.2074830532,41.4488677979],"type":"Point"}
}