{
  "type": "Feature",
  "properties": {
    "iso:country":"ES",
    "sg:address":"Calle de Dels Tapissers, 8",
    "sg:city":"Paiporta",
    "sg:orig_category":"Tapicer\u00cdas",
    "sg:phone":"+34 963 97 06 05",
    "sg:postcode":"46200",
    "sg:province":"Valencia",
    "wof:name":"Tapizados Luan S.l.",
    "wof:placetype":"venue"
},
  "geometry": {"coordinates":[-0.4108879864,39.4242019653],"type":"Point"}
}