{
  "type": "Feature",
  "properties": {
    "iso:country":"ES",
    "sg:address":"Rond Alzira, 12",
    "sg:city":"Algemesi",
    "sg:orig_category":"Bordado, Marcado A Medida",
    "sg:phone":"+34 962 48 04 88",
    "sg:postcode":"46680",
    "sg:province":"Valencia",
    "wof:name":"Gec.cb",
    "wof:placetype":"venue"
},
  "geometry": {"coordinates":[-0.4410069883,39.1916007996],"type":"Point"}
}