{
  "type": "Feature",
  "properties": {
    "iso:country":"ES",
    "sg:address":"Calle de Hoyo, 6",
    "sg:city":"Torremolinos",
    "sg:orig_category":"Abogados",
    "sg:phone":"+34 952 05 42 67",
    "sg:postcode":"29620",
    "sg:province":"M\u00e1laga",
    "wof:name":"Buendia Ordo\u00f1ez Salvador Enrique",
    "wof:placetype":"venue"
},
  "geometry": {"coordinates":[-4.4992818832,36.6257896423],"type":"Point"}
}