{
  "type": "Feature",
  "properties": {
    "addr:full":"Avda Lope De Vega, 23 Medina Campo Valladolid 47400",
    "addr:housenumber":"23",
    "addr:postcode":"47400",
    "addr:street":"Avda Lope De Vega",
    "iso:country":"ES",
    "sg:address":"Avda Lope De Vega, 23",
    "sg:city":"Medina Campo",
    "sg:orig_category":"Venta, Montaje De Neum\u00c1ticos",
    "sg:phone":"+34 983 81 08 17",
    "sg:postcode":"47400",
    "sg:province":"Valladolid",
    "wof:name":"Gonzalez Roman Patricio",
    "wof:placetype":"venue"
},
  "geometry": {"coordinates":[-4.912062645,41.3084831238],"type":"Point"}
}