{
  "type": "Feature",
  "properties": {
    "iso:country":"ES",
    "sg:address":"Calle de Xistral (do), 16",
    "sg:city":"Ferreira",
    "sg:orig_category":"Quincaller\u00cda (al Por Menor)",
    "sg:phone":"+34 982 57 43 84",
    "sg:postcode":"27770",
    "sg:province":"Lugo",
    "wof:name":"Pardeiro Geada Maria Teresa",
    "wof:placetype":"venue"
},
  "geometry": {"coordinates":[-7.4417719841,43.5520629883],"type":"Point"}
}