{
  "type": "Feature",
  "properties": {
    "addr:full":"Calle de Rio Extremera, S/n Quesada Ja\u00e9n 23480",
    "addr:housenumber":"s / n",
    "addr:postcode":"23480",
    "addr:street":"Calle De Rio Extremera",
    "iso:country":"ES",
    "sg:address":"Calle de Rio Extremera, S/n",
    "sg:city":"Quesada",
    "sg:orig_category":"Arquitectos",
    "sg:phone":"+34 953 73 32 41",
    "sg:postcode":"23480",
    "sg:province":"Ja\u00e9n",
    "wof:name":"Marin Zamora Apolinar",
    "wof:placetype":"venue"
},
  "geometry": {"coordinates":[-3.0672140121,37.845615387],"type":"Point"}
}