{
  "type": "Feature",
  "properties": {
    "addr:full":"Carrer de Mare De Deu Del Socors, 62 Terrassa Barcelona 08222",
    "addr:housenumber":"62",
    "addr:postcode":"08222",
    "addr:street":"Carrer De Mare De Deu Del Socors",
    "iso:country":"ES",
    "sg:address":"Carrer de Mare De Deu Del Socors, 62",
    "sg:city":"Terrassa",
    "sg:orig_category":"Pescader\u00cdas (al Por Menor)",
    "sg:phone":"+34 937 31 11 53",
    "sg:postcode":"08222",
    "sg:province":"Barcelona",
    "wof:name":"Sanchez Serrano Esperanza",
    "wof:placetype":"venue"
},
  "geometry": {"coordinates":[2.0309169292,41.5630683899],"type":"Point"}
}