{
  "type": "Feature",
  "properties": {
    "addr:full":"Carr Major, 66 Sort Lleida 25560",
    "addr:housenumber":"66",
    "addr:postcode":"25560",
    "addr:street":"Carr Major",
    "iso:country":"ES",
    "sg:address":"Carr Major, 66",
    "sg:city":"Sort",
    "sg:orig_category":"Pescader\u00cdas (al Por Menor)",
    "sg:phone":"+34 973 62 02 40",
    "sg:postcode":"25560",
    "sg:province":"Lleida",
    "wof:name":"Bordoll Llados Nuria",
    "wof:placetype":"venue"
},
  "geometry": {"coordinates":[1.1313459873,42.4128112793],"type":"Point"}
}