{
  "type": "Feature",
  "properties": {
    "addr:full":"Ctra. La \u00d1ora, 334 Rincon Beniscornia Murcia 30108",
    "addr:housenumber":"334",
    "addr:postcode":"30108",
    "addr:street":"Ctra. La N\u0303Ora",
    "iso:country":"ES",
    "sg:address":"Ctra. La \u00d1ora, 334",
    "sg:city":"Rincon Beniscornia",
    "sg:orig_category":"Flores Y Plantas Naturales (al Por Mayor)",
    "sg:phone":"+34 968 29 05 09",
    "sg:postcode":"30108",
    "sg:province":"Murcia",
    "wof:name":"Horticultura Aljufia S.l.",
    "wof:placetype":"venue"
},
  "geometry": {"coordinates":[-1.1802370548,37.987197876],"type":"Point"}
}