{
  "type": "Feature",
  "properties": {
    "addr:full":"Urb Sirenas, S/n Manga Mar Menor Murcia 30380",
    "addr:housenumber":"s / n",
    "addr:postcode":"30380",
    "addr:street":"Urb Sirenas",
    "iso:country":"ES",
    "sg:address":"Urb Sirenas, S/n",
    "sg:city":"Manga Mar Menor",
    "sg:orig_category":"Agencias De Viajes",
    "sg:phone":"+34 968 56 46 66",
    "sg:postcode":"30380",
    "sg:province":"Murcia",
    "wof:name":"Actividades Vidal S.l.",
    "wof:placetype":"venue"
},
  "geometry": {"coordinates":[-1.1298867464,37.9834747314],"type":"Point"}
}