{
  "type": "Feature",
  "properties": {
    "iso:country":"ES",
    "sg:address":"Avda Santa Maria, 35",
    "sg:city":"Meliana",
    "sg:orig_category":"Peluqueros: De Se\u00d1oras",
    "sg:phone":"+34 961 49 08 46",
    "sg:postcode":"46133",
    "sg:province":"Valencia",
    "wof:name":"Garcia Lopez Enrique",
    "wof:placetype":"venue"
},
  "geometry": {"coordinates":[-0.3512910008,39.5298919678],"type":"Point"}
}