{
  "type": "Feature",
  "properties": {
    "iso:country":"ES",
    "sg:address":"Calle de Francisco Gonzalez Sanche, 23",
    "sg:city":"Alacant",
    "sg:orig_category":"Arreglo, Reparaci\u00d3n, Piezas Sueltas De Televisi\u00d3n, V\u00cddeo, Hi",
    "sg:phone":"+34 965 26 56 55",
    "sg:postcode":"03013",
    "sg:province":"Alicante",
    "wof:name":"Rubio Ruiz Juan",
    "wof:placetype":"venue"
},
  "geometry": {"coordinates":[-0.4746609926,38.3600006104],"type":"Point"}
}