{
  "type": "Feature",
  "properties": {
    "iso:country":"ES",
    "sg:address":"Avda Condomina, 81",
    "sg:city":"Alacant",
    "sg:orig_category":"Molduras, Junquillos, Listones Y Molduras Perforadas",
    "sg:phone":"+34 965 26 11 44",
    "sg:postcode":"03540",
    "sg:province":"Alicante",
    "wof:name":"Borbolla Cuesta Feliciano",
    "wof:placetype":"venue"
},
  "geometry": {"coordinates":[-0.4337739944,38.3635635376],"type":"Point"}
}