{
  "type": "Feature",
  "properties": {
    "addr:full":"Luga Arboledas (las), S/n Arboledas Murcia 30600",
    "addr:postcode":"30600",
    "addr:street":"Las S / N",
    "iso:country":"ES",
    "sg:address":"Luga Arboledas (las), S/n",
    "sg:city":"Arboledas",
    "sg:orig_category":"Serigraf\u00cda (material Y Suministros)",
    "sg:phone":"+34 968 68 80 18",
    "sg:postcode":"30600",
    "sg:province":"Murcia",
    "wof:name":"Arboledas Artes Graficas S.l.",
    "wof:placetype":"venue"
},
  "geometry": {"coordinates":[-1.1298867464,37.9834747314],"type":"Point"}
}