{
  "type": "Feature",
  "properties": {
    "iso:country":"ES",
    "sg:address":"Mar Blanco, S/n",
    "sg:city":"Puerto Mazarron",
    "sg:orig_category":"Reposter\u00cdas",
    "sg:phone":"+34 968 15 45 46",
    "sg:postcode":"30860",
    "sg:province":"Murcia",
    "wof:name":"Perez Vivancos Jose",
    "wof:placetype":"venue"
},
  "geometry": {"coordinates":[-1.2746390104,37.5610466003],"type":"Point"}
}