{
  "type": "Feature",
  "properties": {
    "iso:country":"ES",
    "sg:address":"Avda Galicia, 86",
    "sg:city":"Ponferrada",
    "sg:orig_category":"Ense\u00d1anza, Formaci\u00d3n Profesional: Aprendizaje",
    "sg:phone":"+34 987 41 48 34",
    "sg:postcode":"24400",
    "sg:province":"Le\u00f3n",
    "wof:name":"Ayuntamiento De Ponferrada",
    "wof:placetype":"venue"
},
  "geometry": {"coordinates":[-6.614836216,42.5558738708],"type":"Point"}
}