{
  "type": "Feature",
  "properties": {
    "iso:country":"ES",
    "sg:address":"Calle de Maria Del Cristo Ossuna, 18",
    "sg:city":"San Cristobal De La Laguna",
    "sg:orig_category":"Institutos De Belleza",
    "sg:phone":"+34 922 26 52 98",
    "sg:postcode":"38204",
    "sg:province":"Santa Cruz De Tenerife",
    "wof:name":"Perez Perez Lucia Araceli",
    "wof:placetype":"venue"
},
  "geometry": {"coordinates":[-16.3141040802,28.4820346832],"type":"Point"}
}