{
  "type": "Feature",
  "properties": {
    "addr:full":"Poligono Seis, 199 Ontinyent Valencia 46870",
    "addr:housenumber":"199",
    "addr:postcode":"46870",
    "addr:street":"Poligono Seis",
    "iso:country":"ES",
    "sg:address":"Poligono Seis, 199",
    "sg:city":"Ontinyent",
    "sg:orig_category":"Alquiler De Gr\u00daas",
    "sg:phone":"+34 962 38 41 78",
    "sg:postcode":"46870",
    "sg:province":"Valencia",
    "wof:name":"Martinez Lopez Francisco",
    "wof:placetype":"venue"
},
  "geometry": {"coordinates":[-0.6030989885,38.8258895874],"type":"Point"}
}