{
  "type": "Feature",
  "properties": {
    "addr:full":"Carrer de L'escorial, 19 Barcelona Barcelona 08024",
    "addr:housenumber":"19",
    "addr:postcode":"08024",
    "addr:street":"Carrer De L'Escorial",
    "iso:country":"ES",
    "sg:address":"Carrer de L'escorial, 19",
    "sg:city":"Barcelona",
    "sg:orig_category":"Loter\u00cda Y T\u00d3mbola",
    "sg:phone":"+34 932 13 35 07",
    "sg:postcode":"08024",
    "sg:province":"Barcelona",
    "wof:name":"Maldonado Lupia\u00f1ez Jose-antonio",
    "wof:placetype":"venue"
},
  "geometry": {"coordinates":[2.1618535519,41.4067192078],"type":"Point"}
}