{
  "type": "Feature",
  "properties": {
    "addr:full":"Plaz Lasala De, 3 Donostia-san Sebastian Guip\u00f9zcoa 20003",
    "addr:housenumber":"3",
    "addr:postcode":"20003",
    "addr:street":"Plaz Lasala De",
    "iso:country":"ES",
    "sg:address":"Plaz Lasala De, 3",
    "sg:city":"Donostia-san Sebastian",
    "sg:orig_category":"Abogados",
    "sg:phone":"+34 943 43 16 97",
    "sg:postcode":"20003",
    "sg:province":"Guip\u00f9zcoa",
    "wof:name":"Lasala-3 Abokatuak C.b.",
    "wof:placetype":"venue"
},
  "geometry": {"coordinates":[-1.9794000387,43.3173789978],"type":"Point"}
}