{
  "type": "Feature",
  "properties": {
    "addr:full":"Plaz Santa Cecilia, 3 San Javier Murcia 30730",
    "addr:housenumber":"3",
    "addr:postcode":"30730",
    "addr:street":"Santa Cecilia",
    "iso:country":"ES",
    "sg:address":"Plaz Santa Cecilia, 3",
    "sg:city":"San Javier",
    "sg:orig_category":"Promotores Constructores",
    "sg:phone":"+34 968 57 01 58",
    "sg:postcode":"30730",
    "sg:province":"Murcia",
    "wof:name":"Conesa Martinez Jose",
    "wof:placetype":"venue"
},
  "geometry": {"coordinates":[-0.8334079981,37.8006134033],"type":"Point"}
}