{
  "type": "Feature",
  "properties": {
    "addr:full":"Fase Cuatro(p I La Luz), 7 Huelva Huelva 21007",
    "addr:housenumber":"7",
    "addr:postcode":"21007",
    "addr:street":"P I La Luz",
    "iso:country":"ES",
    "sg:address":"Fase Cuatro(p I La Luz), 7",
    "sg:city":"Huelva",
    "sg:orig_category":"Empresarios Y Productoras De Espect\u00c1culos",
    "sg:phone":"+34 959 22 07 77",
    "sg:postcode":"21007",
    "sg:province":"Huelva",
    "wof:name":"Jd Music Factory S.l.u.",
    "wof:placetype":"venue"
},
  "geometry": {"coordinates":[-6.9495940208,37.256313324],"type":"Point"}
}