{
  "type": "Feature",
  "properties": {
    "addr:full":"Avda Playas (las), 41 Puerto Del Carmen Las Palmas 35510",
    "addr:housenumber":"41",
    "addr:postcode":"35510",
    "addr:street":"Avda Playas Las",
    "iso:country":"ES",
    "sg:address":"Avda Playas (las), 41",
    "sg:city":"Puerto Del Carmen",
    "sg:orig_category":"Molduras, Junquillos, Listones Y Molduras Perforadas",
    "sg:phone":"+34 928 51 16 89",
    "sg:postcode":"35510",
    "sg:province":"Las Palmas",
    "wof:name":"Glendar Lanzarote Scp",
    "wof:placetype":"venue"
},
  "geometry": {"coordinates":[-13.6546278,28.9196548462],"type":"Point"}
}