{
  "type": "Feature",
  "properties": {
    "addr:full":"Avda Regne De Valencia, 43 Valencia Valencia 46005",
    "addr:housenumber":"43",
    "addr:postcode":"46005",
    "addr:street":"Avda Regne De Valencia",
    "iso:country":"ES",
    "sg:address":"Avda Regne De Valencia, 43",
    "sg:city":"Valencia",
    "sg:orig_category":"Arquitectos",
    "sg:phone":"+34 963 95 57 69",
    "sg:postcode":"46005",
    "sg:province":"Valencia",
    "wof:name":"Benlloch Marco Javier",
    "wof:placetype":"venue"
},
  "geometry": {"coordinates":[-0.3675439954,39.4638290405],"type":"Point"}
}