{
  "type": "Feature",
  "properties": {
    "iso:country":"ES",
    "sg:address":"Ctra Marquesado (del), Km. 0000,3",
    "sg:city":"Chiclana De La Frontera",
    "sg:orig_category":"Molduras, Junquillos, Listones Y Molduras Perforadas",
    "sg:phone":"+34 956 40 75 26",
    "sg:postcode":"11130",
    "sg:province":"C\u00e1diz",
    "wof:name":"Noel Garcia Roberto Carlos",
    "wof:placetype":"venue"
},
  "geometry": {"coordinates":[-6.1419582367,36.4297065735],"type":"Point"}
}