{
  "type": "Feature",
  "properties": {
    "iso:country":"ES",
    "sg:address":"Plg Indus. Valdeoli, 13",
    "sg:city":"Torrijos",
    "sg:orig_category":"Mec\u00c1nico Del Autom\u00d3vil",
    "sg:phone":"+34 925 76 03 95",
    "sg:postcode":"45500",
    "sg:province":"Toledo",
    "wof:name":"Celis Perez Luis Miguel De",
    "wof:placetype":"venue"
},
  "geometry": {"coordinates":[-4.2818388939,39.9835548401],"type":"Point"}
}