{
  "type": "Feature",
  "properties": {
    "addr:full":"Calle de San Francisco, 32 Alacant Alicante 03001",
    "addr:housenumber":"32",
    "addr:postcode":"03001",
    "addr:street":"Calle De San Francisco",
    "iso:country":"ES",
    "sg:address":"Calle de San Francisco, 32",
    "sg:city":"Alacant",
    "sg:orig_category":"\u00d3ptica: Instrumentos (fabricaci\u00d3n)",
    "sg:phone":"+34 965 21 43 73",
    "sg:postcode":"03001",
    "sg:province":"Alicante",
    "wof:name":"Torregrosa Gadea Jose",
    "wof:placetype":"venue"
},
  "geometry": {"coordinates":[-0.4855389893,38.3440284729],"type":"Point"}
}