{
  "type": "Feature",
  "properties": {
    "iso:country":"ES",
    "sg:address":"Ctra Moli De Pala, 2",
    "sg:city":"Horno De Alcedo",
    "sg:orig_category":"Artes Gr\u00c1ficas, Artes Pl\u00c1sticas (curso)",
    "sg:phone":"+34 963 75 60 59",
    "sg:postcode":"46026",
    "sg:province":"Valencia",
    "wof:name":"Campos Regen Dolores",
    "wof:placetype":"venue"
},
  "geometry": {"coordinates":[-0.3813689947,39.4338607788],"type":"Point"}
}