{
  "type": "Feature",
  "properties": {
    "iso:country":"ES",
    "sg:address":"Plaz Mayor, 15",
    "sg:city":"Villarino De Los Aires",
    "sg:orig_category":"Bancos",
    "sg:phone":"+34 923 57 30 81",
    "sg:postcode":"37160",
    "sg:province":"Salamanca",
    "wof:name":"Banco De Castilla",
    "wof:placetype":"venue"
},
  "geometry": {"coordinates":[-6.4644842148,41.2688102722],"type":"Point"}
}