{
  "type": "Feature",
  "properties": {
    "addr:full":"Avda Castilla (de), 2 Escorial Madrid 28280",
    "addr:housenumber":"2",
    "addr:postcode":"28280",
    "addr:street":"Avda Castilla De",
    "iso:country":"ES",
    "sg:address":"Avda Castilla (de), 2",
    "sg:city":"Escorial",
    "sg:orig_category":"Frutas, Legumbres Frescas Y Tempranas (al Por Menor)",
    "sg:phone":"+34 918 90 02 44",
    "sg:postcode":"28280",
    "sg:province":"Madrid",
    "wof:name":"Frutas Escorial S.l.",
    "wof:placetype":"venue"
},
  "geometry": {"coordinates":[-4.1308498383,40.5830345154],"type":"Point"}
}