{
  "type": "Feature",
  "properties": {
    "iso:country":"ES",
    "sg:address":"Ctra Jarandilla, S/n",
    "sg:city":"Navalmoral Mata",
    "sg:orig_category":"Frutas Y Legumbres Secas (al Por Mayor)",
    "sg:phone":"+34 927 53 29 17",
    "sg:postcode":"10300",
    "sg:province":"C\u00e1ceres",
    "wof:name":"Nu\u00f1ez Llorente Manuel",
    "wof:placetype":"venue"
},
  "geometry": {"coordinates":[-5.5438289642,39.896900177],"type":"Point"}
}