{
  "type": "Feature",
  "properties": {
    "iso:country":"ES",
    "sg:address":"Avda Union (de La), S/n",
    "sg:city":"San Javier",
    "sg:orig_category":"Cerrajer\u00cda, Ferrallista",
    "sg:phone":"+34 968 19 22 59",
    "sg:postcode":"30730",
    "sg:province":"Murcia",
    "wof:name":"Cerrajeria Montemar C.b.",
    "wof:placetype":"venue"
},
  "geometry": {"coordinates":[-0.8380789757,37.8047981262],"type":"Point"}
}