{
  "type": "Feature",
  "properties": {
    "iso:country":"ES",
    "sg:address":"Calle de Iglesia (la), 2",
    "sg:city":"Santa Engracia",
    "sg:orig_category":"Cr\u00cda De Animales",
    "sg:phone":"+34 941 48 21 58",
    "sg:postcode":"26131",
    "sg:province":"La Rioja",
    "wof:name":"Rio Saenz Jose Ramon Del",
    "wof:placetype":"venue"
},
  "geometry": {"coordinates":[-2.3061139584,42.3149795532],"type":"Point"}
}