{
  "type": "Feature",
  "properties": {
    "addr:full":"Carrer de Riudecols, 5 Reus Tarragona 43203",
    "addr:housenumber":"5",
    "addr:postcode":"43203",
    "addr:street":"Carrer De Riudecols",
    "iso:country":"ES",
    "sg:address":"Carrer de Riudecols, 5",
    "sg:city":"Reus",
    "sg:orig_category":"Agencias Y Agentes Comerciales, Representantes",
    "sg:phone":"+34 977 31 40 06",
    "sg:postcode":"43203",
    "sg:province":"Tarragona",
    "wof:name":"Antonio Sanchez Mu\u00d1oz",
    "wof:placetype":"venue"
},
  "geometry": {"coordinates":[1.1017270088,41.1636009216],"type":"Point"}
}