{
  "type": "Feature",
  "properties": {
    "addr:full":"Plaz Nogaledo (el), S/n Toral De Merayo Le\u00f3n 24448",
    "addr:postcode":"24448",
    "addr:street":"Plaz;El S / N Toral De Merayo Leo\u0301N",
    "iso:country":"ES",
    "sg:address":"Plaz Nogaledo (el), S/n",
    "sg:city":"Toral De Merayo",
    "sg:orig_category":"Centros De Educaci\u00d3n Especial",
    "sg:phone":"+34 987 42 12 90",
    "sg:postcode":"24448",
    "sg:province":"Le\u00f3n",
    "wof:name":"Colegio Publico El Salvador",
    "wof:placetype":"venue"
},
  "geometry": {"coordinates":[-6.6721191406,42.5083999634],"type":"Point"}
}