{
  "type": "Feature",
  "properties": {
    "iso:country":"ES",
    "sg:address":"Los Campones, S/n",
    "sg:city":"Riberas",
    "sg:orig_category":"Plomeros",
    "sg:phone":"+34 985 58 78 10",
    "sg:postcode":"33127",
    "sg:province":"Asturias",
    "wof:name":"Alonso Estrada Margarete",
    "wof:placetype":"venue"
},
  "geometry": {"coordinates":[-6.0665082932,43.5064926147],"type":"Point"}
}