{
  "type": "Feature",
  "properties": {
    "addr:full":"Barr Concha, 67 Concha Vizcaya 48891",
    "addr:housenumber":"67",
    "addr:postcode":"48891",
    "addr:street":"Concha",
    "iso:country":"ES",
    "sg:address":"Barr Concha, 67",
    "sg:city":"Concha",
    "sg:orig_category":"Agricultores, Agricultores",
    "sg:phone":"+34 946 10 69 47",
    "sg:postcode":"48891",
    "sg:province":"Vizcaya",
    "wof:name":"S.a.t. Valle De Carranza",
    "wof:placetype":"venue"
},
  "geometry": {"coordinates":[-3.3599720001,43.2248039246],"type":"Point"}
}