{
  "type": "Feature",
  "properties": {
    "addr:full":"Alam Urquijo, 102 Bilbao Vizcaya 48013",
    "addr:housenumber":"102",
    "addr:postcode":"48013",
    "addr:street":"Alam Urquijo",
    "iso:country":"ES",
    "sg:address":"Alam Urquijo, 102",
    "sg:city":"Bilbao",
    "sg:orig_category":"Arquitectos",
    "sg:phone":"+34 944 42 15 81",
    "sg:postcode":"48013",
    "sg:province":"Vizcaya",
    "wof:name":"Sebastian Esteras Juan Antonio",
    "wof:placetype":"venue"
},
  "geometry": {"coordinates":[-2.9477069378,43.2627105713],"type":"Point"}
}