{
  "type": "Feature",
  "properties": {
    "iso:country":"ES",
    "sg:address":"Alhama, Km. 0022,0",
    "sg:city":"Cuevas Reyllo",
    "sg:orig_category":"Suministros Para Carrocer\u00cdas",
    "sg:phone":"+34 968 15 14 16",
    "sg:postcode":"30333",
    "sg:province":"Murcia",
    "wof:name":"Carrocerias,gruasybasculantes",
    "wof:placetype":"venue"
},
  "geometry": {"coordinates":[-1.2445290089,37.7351493835],"type":"Point"}
}