{
  "type": "Feature",
  "properties": {
    "addr:full":"Calle de Fernandez Del Campo, 33 Bilbao Vizcaya 48010",
    "addr:housenumber":"33",
    "addr:postcode":"48010",
    "addr:street":"Calle De Fernandez Del Campo",
    "iso:country":"ES",
    "sg:address":"Calle de Fernandez Del Campo, 33",
    "sg:city":"Bilbao",
    "sg:orig_category":"Electrodom\u00c9sticos (al Por Menor)",
    "sg:phone":"+34 944 21 80 04",
    "sg:postcode":"48010",
    "sg:province":"Vizcaya",
    "wof:name":"Maria Eugenia Iturrioz Perez",
    "wof:placetype":"venue"
},
  "geometry": {"coordinates":[-2.9364230633,43.2590942383],"type":"Point"}
}