{
  "type": "Feature",
  "properties": {
    "iso:country":"ES",
    "sg:address":"Ctra Fortuna, S/n",
    "sg:city":"Archena",
    "sg:orig_category":"Ense\u00d1anza, Formaci\u00d3n Profesional: Aprendizaje",
    "sg:phone":"+34 968 43 23 60",
    "sg:postcode":"30600",
    "sg:province":"Murcia",
    "wof:name":"Mancomunidad De Los Canales Del Taibilla",
    "wof:placetype":"venue"
},
  "geometry": {"coordinates":[-1.2859790325,38.1163368225],"type":"Point"}
}