{
  "type": "Feature",
  "properties": {
    "addr:full":"Calle de Francisco Mendoza, 43 Paterna Campo Huelva 21880",
    "addr:housenumber":"43",
    "addr:postcode":"21880",
    "addr:street":"Calle De Francisco Mendoza",
    "iso:country":"ES",
    "sg:address":"Calle de Francisco Mendoza, 43",
    "sg:city":"Paterna Campo",
    "sg:orig_category":"Empresas De Desmonte",
    "sg:phone":"+34 959 42 88 54",
    "sg:postcode":"21880",
    "sg:province":"Huelva",
    "wof:name":"Reyes Orihuela Florentina",
    "wof:placetype":"venue"
},
  "geometry": {"coordinates":[-6.3989419937,37.4173545837],"type":"Point"}
}