{
  "type": "Feature",
  "properties": {
    "iso:country":"ES",
    "sg:address":"Plaz Espa\u00d1a (de), 1",
    "sg:city":"Moraleja",
    "sg:orig_category":"Administraciones Regionales, Departamentales Y Locales",
    "sg:phone":"+34 927 51 50 75",
    "sg:postcode":"10840",
    "sg:province":"C\u00e1ceres",
    "wof:name":"Ayuntamiento De Moraleja",
    "wof:placetype":"venue"
},
  "geometry": {"coordinates":[-6.6612792015,40.0684928894],"type":"Point"}
}