{
  "type": "Feature",
  "properties": {
    "iso:country":"ES",
    "sg:address":"Calle de Hondarribia, S/n",
    "sg:city":"Vitoria-gasteiz",
    "sg:orig_category":"Mec\u00c1nico Del Autom\u00d3vil",
    "sg:phone":"+34 945 17 98 61",
    "sg:postcode":"01010",
    "sg:province":"\u00c1lava",
    "wof:name":"Pedreno Elizazu Estanislao",
    "wof:placetype":"venue"
},
  "geometry": {"coordinates":[-2.69480896,42.8653335571],"type":"Point"}
}