{
  "type": "Feature",
  "properties": {
    "iso:country":"ES",
    "sg:address":"Avda Yurramendi, 2",
    "sg:city":"Ciudad Rodrigo",
    "sg:orig_category":"Supermercados Y Hipermercados",
    "sg:phone":"+34 923 48 00 56",
    "sg:postcode":"37500",
    "sg:province":"Salamanca",
    "wof:name":"Grupo El Arbol Distribucion Y Supermercados S.a. Unipersonal",
    "wof:placetype":"venue"
},
  "geometry": {"coordinates":[-6.5325980186,40.6001358032],"type":"Point"}
}