{
  "type": "Feature",
  "properties": {
    "addr:full":"Calle de Alloza, 94 Castellon Castell\u00f3n 12001",
    "addr:housenumber":"94",
    "addr:postcode":"12001",
    "addr:street":"Calle De Alloza",
    "iso:country":"ES",
    "sg:address":"Calle de Alloza, 94",
    "sg:city":"Castellon",
    "sg:orig_category":"Artesanado",
    "sg:phone":"+34 964 21 46 51",
    "sg:postcode":"12001",
    "sg:province":"Castell\u00f3n",
    "wof:name":"Prieto Alvarez Luis",
    "wof:placetype":"venue"
},
  "geometry": {"coordinates":[-0.0390903987,39.987121582],"type":"Point"}
}