{
  "type": "Feature",
  "properties": {
    "addr:full":"Avda Jose Mesa Y Lopez, 4 Palmas De Gran Canaria Las Palmas 35007",
    "addr:housenumber":"4",
    "addr:postcode":"35007",
    "addr:street":"Avda Jose Mesa Y Lopez",
    "iso:country":"ES",
    "sg:address":"Avda Jose Mesa Y Lopez, 4",
    "sg:city":"Palmas De Gran Canaria",
    "sg:orig_category":"Ingenier\u00cda, Centros De Estudios (industria)",
    "sg:phone":"+34 928 26 01 57",
    "sg:postcode":"35007",
    "sg:province":"Las Palmas",
    "wof:name":"Cantero Juarez Antonio",
    "wof:placetype":"venue"
},
  "geometry": {"coordinates":[-15.4296979904,28.1351127625],"type":"Point"}
}