{
  "type": "Feature",
  "properties": {
    "iso:country":"ES",
    "sg:address":"Calle de Ronda De Gracia, 6",
    "sg:city":"Medina Campo",
    "sg:orig_category":"Tapiceros Y Tapiceros",
    "sg:phone":"+34 983 80 48 97",
    "sg:postcode":"47400",
    "sg:province":"Valladolid",
    "wof:name":"Lobato Martinez Francisco",
    "wof:placetype":"venue"
},
  "geometry": {"coordinates":[-4.913184166,41.3120155334],"type":"Point"}
}