{
  "type": "Feature",
  "properties": {
    "addr:full":"Calle de Portuetxe, 45 Donostia-san Sebastian Guip\u00f9zcoa 20018",
    "addr:housenumber":"45",
    "addr:postcode":"20018",
    "addr:street":"Calle De Portuetxe",
    "iso:country":"ES",
    "sg:address":"Calle de Portuetxe, 45",
    "sg:city":"Donostia-san Sebastian",
    "sg:orig_category":"Promotores Constructores",
    "sg:phone":"+34 943 31 73 50",
    "sg:postcode":"20018",
    "sg:province":"Guip\u00f9zcoa",
    "wof:name":"Mallet Fuentes Rogelio",
    "wof:placetype":"venue"
},
  "geometry": {"coordinates":[-2.0134930611,43.3008346558],"type":"Point"}
}