{
  "type": "Feature",
  "properties": {
    "iso:country":"ES",
    "sg:address":"Avda San Miguel, 10",
    "sg:city":"San Miguel De Meruelo",
    "sg:orig_category":"Promotores Constructores",
    "sg:phone":"+34 942 63 79 29",
    "sg:postcode":"39192",
    "sg:province":"Cantabria",
    "wof:name":"Construcciones Sati Cantabria S.l.",
    "wof:placetype":"venue"
},
  "geometry": {"coordinates":[-3.5728600025,43.4554634094],"type":"Point"}
}