{
  "type": "Feature",
  "properties": {
    "addr:full":"Calle de Emilio Arce Vera, 4 Beniajan Murcia 30570",
    "addr:housenumber":"4",
    "addr:postcode":"30570",
    "addr:street":"Calle De Emilio Arce Vera",
    "iso:country":"ES",
    "sg:address":"Calle de Emilio Arce Vera, 4",
    "sg:city":"Beniajan",
    "sg:orig_category":"Material Y Herramientas Agr\u00cdcolas",
    "sg:phone":"+34 968 87 39 70",
    "sg:postcode":"30570",
    "sg:province":"Murcia",
    "wof:name":"Representaciones Abellan S.l.",
    "wof:placetype":"venue"
},
  "geometry": {"coordinates":[-1.0727909803,37.973361969],"type":"Point"}
}