{
  "type": "Feature",
  "properties": {
    "addr:full":"Carrer de Rauric, 8 Barcelona Barcelona 08002",
    "addr:housenumber":"8",
    "addr:postcode":"08002",
    "addr:street":"Carrer De Rauric",
    "iso:country":"ES",
    "sg:address":"Carrer de Rauric, 8",
    "sg:city":"Barcelona",
    "sg:orig_category":"Importaci\u00d3n, Exportaci\u00d3n Y Comercios De Productos Textiles",
    "sg:phone":"+34 933 02 30 41",
    "sg:postcode":"08002",
    "sg:province":"Barcelona",
    "wof:name":"Ruiz Gimenez Elisa",
    "wof:placetype":"venue"
},
  "geometry": {"coordinates":[2.1748409271,41.3811836243],"type":"Point"}
}