{
  "type": "Feature",
  "properties": {
    "addr:full":"Avda Mariano Andres, 104 Le\u00f3n Le\u00f3n 24008",
    "addr:housenumber":"104",
    "addr:postcode":"24008",
    "addr:street":"Avda Mariano Andres",
    "iso:country":"ES",
    "sg:address":"Avda Mariano Andres, 104",
    "sg:city":"Le\u00f3n",
    "sg:orig_category":"Muebles, Minoristas",
    "sg:phone":"+34 987 22 10 54",
    "sg:postcode":"24008",
    "sg:province":"Le\u00f3n",
    "sg:website":"www.paginasamarillas.es",
    "wof:name":"Rodriguez Rodriguez Maria Isabel",
    "wof:placetype":"venue"
},
  "geometry": {"coordinates":[-5.5707907677,42.6111602783],"type":"Point"}
}