{
  "type": "Feature",
  "properties": {
    "iso:country":"ES",
    "sg:address":"Calle de Gerona, 10",
    "sg:city":"Bejar",
    "sg:orig_category":"Molduras, Junquillos, Listones Y Molduras Perforadas",
    "sg:phone":"+34 923 41 17 77",
    "sg:postcode":"37700",
    "sg:province":"Salamanca",
    "wof:name":"Sanchez Paso Miguel Angel",
    "wof:placetype":"venue"
},
  "geometry": {"coordinates":[-5.7615890503,40.3858604431],"type":"Point"}
}