{
  "type": "Feature",
  "properties": {
    "iso:country":"ES",
    "sg:address":"Calle de Corredera (la), 12",
    "sg:city":"Villena",
    "sg:orig_category":"Agencias De Viajes",
    "sg:phone":"+34 965 80 73 90",
    "sg:postcode":"03400",
    "sg:province":"Alicante",
    "sg:website":"www.halconviajes.com",
    "wof:name":"Viajes Halcon S.a.",
    "wof:placetype":"venue"
},
  "geometry": {"coordinates":[-0.8634579778,38.6304855347],"type":"Point"}
}