{
  "type": "Feature",
  "properties": {
    "iso:country":"ES",
    "sg:address":"Calle de Natalio Rivas, S/n",
    "sg:city":"Adra",
    "sg:orig_category":"Peluqueros: De Se\u00d1oras",
    "sg:phone":"+34 950 40 32 82",
    "sg:postcode":"04770",
    "sg:province":"Almer\u00eda",
    "wof:name":"Garcia Liduea Julia",
    "wof:placetype":"venue"
},
  "geometry": {"coordinates":[-3.0144340992,36.7489814758],"type":"Point"}
}