{
  "type": "Feature",
  "properties": {
    "iso:country":"ES",
    "sg:address":"Calle de Andalucia, 2",
    "sg:city":"Vitoria-gasteiz",
    "sg:orig_category":"Agencias Y Asesores De Publicidad",
    "sg:phone":"+34 945 27 01 55",
    "sg:postcode":"01003",
    "sg:province":"\u00c1lava",
    "wof:name":"Sormen Creativos S.a.",
    "wof:placetype":"venue"
},
  "geometry": {"coordinates":[-2.658274889,42.8484954834],"type":"Point"}
}