{
  "type": "Feature",
  "properties": {
    "addr:full":"Calle de Sol (el), 8 Hellin Albacete 02400",
    "addr:housenumber":"8",
    "addr:postcode":"02400",
    "addr:street":"Calle De Sol El",
    "iso:country":"ES",
    "sg:address":"Calle de Sol (el), 8",
    "sg:city":"Hellin",
    "sg:orig_category":"Agencias Y Agentes Comerciales, Representantes",
    "sg:phone":"+34 967 30 60 47",
    "sg:postcode":"02400",
    "sg:province":"Albacete",
    "wof:name":"Checon S.a.",
    "wof:placetype":"venue"
},
  "geometry": {"coordinates":[-1.6464860439,38.4911270142],"type":"Point"}
}