{
  "type": "Feature",
  "properties": {
    "addr:full":"Calle de Huertos (los), 3 Andosilla Navarra 31261",
    "addr:housenumber":"3",
    "addr:postcode":"31261",
    "addr:street":"Calle De Huertos Los",
    "iso:country":"ES",
    "sg:address":"Calle de Huertos (los), 3",
    "sg:city":"Andosilla",
    "sg:orig_category":"Mec\u00c1nico Del Autom\u00d3vil",
    "sg:phone":"+34 948 67 46 95",
    "sg:postcode":"31261",
    "sg:province":"Navarra",
    "wof:name":"Gurrea Saenz Jose Ramon",
    "wof:placetype":"venue"
},
  "geometry": {"coordinates":[-1.9434939623,42.3765525818],"type":"Point"}
}