{
  "type": "Feature",
  "properties": {
    "iso:country":"ES",
    "sg:address":"Calle de Empecinado, 3",
    "sg:city":"Alcala Henares",
    "sg:orig_category":"Agencias De Viajes",
    "sg:phone":"+34 918 82 93 64",
    "sg:postcode":"28801",
    "sg:province":"Madrid",
    "wof:name":"Todoviaje S.l.",
    "wof:placetype":"venue"
},
  "geometry": {"coordinates":[-3.3684766293,40.4806785583],"type":"Point"}
}