{
  "type": "Feature",
  "properties": {
    "addr:full":"Concepcion, 11 Olvega Soria 42110",
    "addr:housenumber":"11",
    "addr:postcode":"42110",
    "addr:street":"Concepcion",
    "iso:country":"ES",
    "sg:address":"Concepcion, 11",
    "sg:city":"Olvega",
    "sg:orig_category":"Carnicer\u00cdas, Carnicer\u00cdas",
    "sg:phone":"+34 976 64 57 46",
    "sg:postcode":"42110",
    "sg:province":"Soria",
    "wof:name":"Carnicas Sierra De Torenzo S.l.",
    "wof:placetype":"venue"
},
  "geometry": {"coordinates":[-1.9842590094,41.7795372009],"type":"Point"}
}