{
  "type": "Feature",
  "properties": {
    "addr:full":"Calle de Rambla Pina, 17 Guadix Granada 18500",
    "addr:housenumber":"17",
    "addr:postcode":"18500",
    "addr:street":"Calle De Rambla Pina",
    "iso:country":"ES",
    "sg:address":"Calle de Rambla Pina, 17",
    "sg:city":"Guadix",
    "sg:orig_category":"Reposter\u00cdas",
    "sg:phone":"+34 958 66 04 71",
    "sg:postcode":"18500",
    "sg:province":"Granada",
    "wof:name":"Rodriguez Fernandez Juan Manuel",
    "wof:placetype":"venue"
},
  "geometry": {"coordinates":[-3.1343688965,37.303894043],"type":"Point"}
}