{
  "type": "Feature",
  "properties": {
    "addr:full":"Carr Santisimo, 15 Oliva Valencia 46780",
    "addr:housenumber":"15",
    "addr:postcode":"46780",
    "addr:street":"Carr Santisimo",
    "iso:country":"ES",
    "sg:address":"Carr Santisimo, 15",
    "sg:city":"Oliva",
    "sg:orig_category":"Inform\u00c1tica, Ofim\u00c1tica (estudios, Asesor\u00cda, Ingenier\u00cda, Formaci\u00d3n)",
    "sg:phone":"+34 962 85 55 18",
    "sg:postcode":"46780",
    "sg:province":"Valencia",
    "sg:website":"www.ciocanal.com",
    "wof:name":"Centre Informatic Oliva Sl",
    "wof:placetype":"venue"
},
  "geometry": {"coordinates":[-0.1219540015,38.9223251343],"type":"Point"}
}