{
  "type": "Feature",
  "properties": {
    "iso:country":"ES",
    "sg:address":"Barr San Cristobal, 7",
    "sg:city":"Burgos",
    "sg:orig_category":"Productos Qu\u00cdmicos (fabricaci\u00d3n, Al Por Mayor)",
    "sg:phone":"+34 947 47 10 34",
    "sg:postcode":"09007",
    "sg:province":"Burgos",
    "wof:name":"Asociacion Burgalesa Y Soriana Amigos De Sahara",
    "wof:placetype":"venue"
},
  "geometry": {"coordinates":[-3.6319131851,42.365978241],"type":"Point"}
}