{
  "type": "Feature",
  "properties": {
    "addr:full":"Pase Colon, 62 Irun Guip\u00f9zcoa 20301",
    "addr:housenumber":"62",
    "addr:postcode":"20301",
    "addr:street":"Colon;Guipu\u0300Zcoa",
    "iso:country":"ES",
    "sg:address":"Pase Colon, 62",
    "sg:city":"Irun",
    "sg:orig_category":"M\u00c9dicos: Cirug\u00cda Ortop\u00c9dica Y Traumatolog\u00cda",
    "sg:phone":"+34 943 61 31 35",
    "sg:postcode":"20301",
    "sg:province":"Guip\u00f9zcoa",
    "wof:name":"Armendariz Sanchez Roberto",
    "wof:placetype":"venue"
},
  "geometry": {"coordinates":[-1.7971489429,43.3411064148],"type":"Point"}
}