{
  "type": "Feature",
  "properties": {
    "addr:full":"Calle de Don Tello, 10 Gernika-lumo Vizcaya 48300",
    "addr:housenumber":"10",
    "addr:postcode":"48300",
    "addr:street":"Calle De Don Tello",
    "iso:country":"ES",
    "sg:address":"Calle de Don Tello, 10",
    "sg:city":"Gernika-lumo",
    "sg:orig_category":"Quincaller\u00cda (al Por Menor)",
    "sg:phone":"+34 946 25 09 42",
    "sg:postcode":"48300",
    "sg:province":"Vizcaya",
    "wof:name":"Bilbao Barrena Juan Miguel",
    "wof:placetype":"venue"
},
  "geometry": {"coordinates":[-2.6759839058,43.3162345886],"type":"Point"}
}