{
  "type": "Feature",
  "properties": {
    "addr:full":"Federico Soto, 8 Iru\u00f1a Navarra 31015",
    "addr:housenumber":"8",
    "addr:postcode":"31015",
    "addr:street":"Federico Soto",
    "iso:country":"ES",
    "sg:address":"Federico Soto, 8",
    "sg:city":"Iru\u00f1a",
    "sg:orig_category":"Perfumer\u00cda (al Por Menor)",
    "sg:phone":"+34 948 38 24 36",
    "sg:postcode":"31015",
    "sg:province":"Navarra",
    "wof:name":"Iribarren Blanco Jose Luis",
    "wof:placetype":"venue"
},
  "geometry": {"coordinates":[-1.6317269802,42.8267250061],"type":"Point"}
}