{
  "type": "Feature",
  "properties": {
    "addr:full":"Rua Santo Domingo, 60 Ourense Ourense 32003",
    "addr:housenumber":"60",
    "addr:postcode":"32003",
    "addr:street":"Rua Santo Domingo",
    "iso:country":"ES",
    "sg:address":"Rua Santo Domingo, 60",
    "sg:city":"Ourense",
    "sg:orig_category":"Inmobiliaria (agencias)",
    "sg:phone":"+34 988 25 40 11",
    "sg:postcode":"32003",
    "sg:province":"Ourense",
    "wof:name":"Colmenero Gonzalez Oscar",
    "wof:placetype":"venue"
},
  "geometry": {"coordinates":[-7.8628320694,42.3399772644],"type":"Point"}
}