{
  "type": "Feature",
  "properties": {
    "addr:full":"Calle de Serrano, 156 Madrid Madrid 28002",
    "addr:housenumber":"156",
    "addr:postcode":"28002",
    "addr:street":"Calle De Serrano",
    "iso:country":"ES",
    "sg:address":"Calle de Serrano, 156",
    "sg:city":"Madrid",
    "sg:orig_category":"Inform\u00c1tica (estudios, Servicios, Asesor\u00cda, Formaci\u00d3n)",
    "sg:phone":"+34 915 62 00 66",
    "sg:postcode":"28002",
    "sg:province":"Madrid",
    "wof:name":"Hierro Hermoso, S.l.",
    "wof:placetype":"venue"
},
  "geometry": {"coordinates":[-3.6851489544,40.4455680847],"type":"Point"}
}