{
  "type": "Feature",
  "properties": {
    "iso:country":"ES",
    "sg:address":"Amaya-amaia, 30",
    "sg:city":"Iru\u00f1a",
    "sg:classifiers":[
        {
            "category":"Food & Beverages",
            "subcategory":"Candy",
            "type":"Retail Goods"
        }
    ],
    "sg:phone":"+34 948 23 03 41",
    "sg:postcode":"31004",
    "sg:province":"Navarra",
    "sg:tags":[
        "confiter\u00cdas",
        "y",
        "de",
        "fabricaci\u00d3n",
        "chocolate"
    ],
    "wof:name":"Subiza Errea Jesus",
    "wof:placetype":"venue"
},
  "geometry": {"coordinates":[-1.6361420155,42.8113861084],"type":"Point"}
}