{
  "type": "Feature",
  "properties": {
    "addr:full":"Plaz Moyua Federico, 8 Bilbao Vizcaya 48009",
    "addr:housenumber":"8",
    "addr:postcode":"48009",
    "addr:street":"Plaz;Federico",
    "iso:country":"ES",
    "sg:address":"Plaz Moyua Federico, 8",
    "sg:city":"Bilbao",
    "sg:orig_category":"Sociedades, Compa\u00d1\u00cdas Aseguradoras",
    "sg:phone":"+34 944 35 43 00",
    "sg:postcode":"48009",
    "sg:province":"Vizcaya",
    "wof:name":"La Estrella S.a. De Seguros",
    "wof:placetype":"venue"
},
  "geometry": {"coordinates":[-2.9350240231,43.2635192871],"type":"Point"}
}