{
  "type": "Feature",
  "properties": {
    "iso:country":"ES",
    "sg:address":"Calle de Sanchez Pacheco, 62",
    "sg:city":"Madrid",
    "sg:orig_category":"Arquitectos",
    "sg:phone":"+34 915 10 06 73",
    "sg:postcode":"28002",
    "sg:province":"Madrid",
    "wof:name":"Alvarez Gomez Francisco",
    "wof:placetype":"venue"
},
  "geometry": {"coordinates":[-3.672798872,40.4474525452],"type":"Point"}
}