{
  "type": "Feature",
  "properties": {
    "addr:full":"Carrer de Cor De Jesus, 5 Crevillent Alicante 03330",
    "addr:housenumber":"5",
    "addr:postcode":"03330",
    "addr:street":"Carrer De Cor De Jesus",
    "iso:country":"ES",
    "sg:address":"Carrer de Cor De Jesus, 5",
    "sg:city":"Crevillent",
    "sg:orig_category":"Ense\u00d1anza Variada",
    "sg:phone":"+34 966 68 17 11",
    "sg:postcode":"03330",
    "sg:province":"Alicante",
    "wof:name":"Garcia Blanco Antonio Jesus",
    "wof:placetype":"venue"
},
  "geometry": {"coordinates":[-0.8081290126,38.2488555908],"type":"Point"}
}