{
  "type": "Feature",
  "properties": {
    "iso:country":"ES",
    "sg:address":"Calle de Puentezuelas, 16",
    "sg:city":"Granada",
    "sg:orig_category":"Asociaciones Y Clubs Deportivos",
    "sg:phone":"+34 958 26 43 07",
    "sg:postcode":"18002",
    "sg:province":"Granada",
    "wof:name":"Diez Del Moral Severino",
    "wof:placetype":"venue"
},
  "geometry": {"coordinates":[-3.6013360023,37.1734962463],"type":"Point"}
}