{
  "type": "Feature",
  "properties": {
    "iso:country":"ES",
    "sg:address":"Avda Sierra Nevada, 24",
    "sg:city":"Cenes Vega",
    "sg:orig_category":"Pescader\u00cdas (al Por Menor)",
    "sg:phone":"+34 958 48 68 00",
    "sg:postcode":"18190",
    "sg:province":"Granada",
    "wof:name":"Hernandez Lopez Mercedes",
    "wof:placetype":"venue"
},
  "geometry": {"coordinates":[-3.5417749882,37.1601867676],"type":"Point"}
}