{
  "type": "Feature",
  "properties": {
    "addr:full":"Calle de Pico Del Morron, 10 Santa Maria De Gracia Murcia 30009",
    "addr:housenumber":"10",
    "addr:postcode":"30009",
    "addr:street":"Calle De Pico Del Morron",
    "iso:country":"ES",
    "sg:address":"Calle de Pico Del Morron, 10",
    "sg:city":"Santa Maria De Gracia",
    "sg:orig_category":"Peluqueros: De Se\u00d1oras",
    "sg:phone":"+34 968 28 16 39",
    "sg:postcode":"30009",
    "sg:province":"Murcia",
    "wof:name":"Menchon Rios Manuel",
    "wof:placetype":"venue"
},
  "geometry": {"coordinates":[-1.1375180483,37.9939575195],"type":"Point"}
}