{
  "type": "Feature",
  "properties": {
    "iso:country":"ES",
    "sg:address":"Plaz San Juan, 15",
    "sg:city":"Porcuna",
    "sg:classifiers":[
        {
            "category":"Taxi",
            "type":"Transportation"
        }
    ],
    "sg:phone":"+34 953 54 49 30",
    "sg:postcode":"23790",
    "sg:province":"Ja\u00e9n",
    "wof:name":"Pulido Ramirez Pedro",
    "wof:placetype":"venue"
},
  "geometry": {"coordinates":[-4.183660984,37.871837616],"type":"Point"}
}