{
  "type": "Feature",
  "properties": {
    "addr:full":"Calle de Golfo De Salonica, 27 Madrid Madrid 28033",
    "addr:housenumber":"27",
    "addr:postcode":"madrid;28033",
    "addr:street":"Calle De Golfo De Salonica",
    "iso:country":"ES",
    "sg:address":"Calle de Golfo De Salonica, 27",
    "sg:city":"Madrid",
    "sg:orig_category":"Edici\u00d3n De Diarios, Revistas, Boletines",
    "sg:phone":"+34 917 66 48 63",
    "sg:postcode":"28033",
    "sg:province":"Madrid",
    "sg:website":"www.selecciones.com",
    "wof:name":"Readers Digest Selecciones",
    "wof:placetype":"venue"
},
  "geometry": {"coordinates":[-3.6657660007,40.4759407043],"type":"Point"}
}