{
  "type": "Feature",
  "properties": {
    "iso:country":"ES",
    "sg:address":"Calle de Nicasio Perez, 21",
    "sg:city":"Valladolid",
    "sg:orig_category":"Ebanister\u00cda",
    "sg:phone":"+34 983 39 97 89",
    "sg:postcode":"47005",
    "sg:province":"Valladolid",
    "wof:name":"Bartolome Gonzalez Julian",
    "wof:placetype":"venue"
},
  "geometry": {"coordinates":[-4.7155570984,41.6503677368],"type":"Point"}
}