{
  "type": "Feature",
  "properties": {
    "iso:country":"ES",
    "sg:address":"Calle de Banderas De Castilla, 10",
    "sg:city":"Toledo",
    "sg:orig_category":"Alimentaci\u00d3n General (al Por Menor)",
    "sg:phone":"+34 925 22 07 26",
    "sg:postcode":"45005",
    "sg:province":"Toledo",
    "wof:name":"Navarro Ortiz Julian",
    "wof:placetype":"venue"
},
  "geometry": {"coordinates":[-4.032351017,39.8714752197],"type":"Point"}
}