{
  "type": "Feature",
  "properties": {
    "addr:full":"Arejos, S/n Aguilas Murcia 30880",
    "addr:postcode":"30880",
    "addr:street":"Arejos S / N",
    "iso:country":"ES",
    "sg:address":"Arejos, S/n",
    "sg:city":"Aguilas",
    "sg:orig_category":"Producci\u00d3n, Venta De Productos De Agricultura Biol\u00d3gica",
    "sg:phone":"+34 968 43 92 87",
    "sg:postcode":"30880",
    "sg:province":"Murcia",
    "wof:name":"Looije Aguilas S.l.",
    "wof:placetype":"venue"
},
  "geometry": {"coordinates":[-1.6737940311,37.4608535767],"type":"Point"}
}