{
  "type": "Feature",
  "properties": {
    "addr:full":"Avda Cardenal Benlloch, 65 Valencia Valencia 46021",
    "addr:housenumber":"65",
    "addr:postcode":"46021",
    "addr:street":"Avda Cardenal Benlloch",
    "iso:country":"ES",
    "sg:address":"Avda Cardenal Benlloch, 65",
    "sg:city":"Valencia",
    "sg:orig_category":"M\u00c9dicos: Estomatolog\u00cda",
    "sg:phone":"+34 963 69 66 78",
    "sg:postcode":"46021",
    "sg:province":"Valencia",
    "wof:name":"Sarrion Martinez Francisco Javier",
    "wof:placetype":"venue"
},
  "geometry": {"coordinates":[-0.3546740115,39.4709854126],"type":"Point"}
}