{
  "type": "Feature",
  "properties": {
    "addr:full":"Calle de Edison, 18 Getafe Madrid 28906",
    "addr:housenumber":"18",
    "addr:postcode":"28906",
    "addr:street":"Calle De Edison",
    "iso:country":"ES",
    "sg:address":"Calle de Edison, 18",
    "sg:city":"Getafe",
    "sg:orig_category":"Calefacci\u00d3n Central: Material (fabricaci\u00d3n, Al Por Mayor)",
    "sg:phone":"+34 916 83 17 40",
    "sg:postcode":"28906",
    "sg:province":"Madrid",
    "sg:website":"www.tradesa",
    "wof:name":"Trade S. A.",
    "wof:placetype":"venue"
},
  "geometry": {"coordinates":[-3.694822073,40.3023262024],"type":"Point"}
}