{
  "type": "Feature",
  "properties": {
    "addr:full":"Calle de Doctor Ferran, 1 Santurtzi Vizcaya 48980",
    "addr:housenumber":"1",
    "addr:postcode":"48980",
    "addr:street":"Calle De Doctor Ferran",
    "iso:country":"ES",
    "sg:address":"Calle de Doctor Ferran, 1",
    "sg:city":"Santurtzi",
    "sg:orig_category":"Molduras, Junquillos, Listones Y Molduras Perforadas",
    "sg:phone":"+34 944 61 78 09",
    "sg:postcode":"48980",
    "sg:province":"Vizcaya",
    "wof:name":"Emilia Villalba Villalba",
    "wof:placetype":"venue"
},
  "geometry": {"coordinates":[-3.0401852131,43.3228874207],"type":"Point"}
}