{
  "type": "Feature",
  "properties": {
    "iso:country":"ES",
    "sg:address":"Poligon Ind. Pedrosa, S/n",
    "sg:city":"Masquefa",
    "sg:orig_category":"Contenedores Para Dep\u00d3sito De Sustancias Peligrosas (fabricaci\u00d3n, Al Por Mayor)",
    "sg:phone":"+34 937 72 76 70",
    "sg:postcode":"08783",
    "sg:province":"Barcelona",
    "sg:website":"www.ismcontenedores.com",
    "wof:name":"Ism Servicios Logisticos S.l.",
    "wof:placetype":"venue"
},
  "geometry": {"coordinates":[1.8109899759,41.5002937317],"type":"Point"}
}