{
  "type": "Feature",
  "properties": {
    "addr:full":"Calle de Sagasta, 1 Sevilla Sevilla 41004",
    "addr:housenumber":"1",
    "addr:postcode":"41004",
    "addr:street":"Calle De Sagasta",
    "iso:country":"ES",
    "sg:address":"Calle de Sagasta, 1",
    "sg:city":"Sevilla",
    "sg:orig_category":"Relojer\u00cda (al Por Menor, Reparaci\u00d3n)",
    "sg:phone":"+34 954 22 37 06",
    "sg:postcode":"41004",
    "sg:province":"Sevilla",
    "wof:name":"Torner Martinez De Azcoytia Rafael",
    "wof:placetype":"venue"
},
  "geometry": {"coordinates":[-5.9933381081,37.3900909424],"type":"Point"}
}