{
  "type": "Feature",
  "properties": {
    "addr:full":"Ctra Yecla, 1 Villena Alicante 03400",
    "addr:housenumber":"1",
    "addr:postcode":"03400",
    "addr:street":"Ctra Yecla",
    "iso:country":"ES",
    "sg:address":"Ctra Yecla, 1",
    "sg:city":"Villena",
    "sg:orig_category":"Comerciantes Al Por Mayor De Vinos, Licores Y Alcoholes",
    "sg:phone":"+34 965 80 01 79",
    "sg:postcode":"03400",
    "sg:province":"Alicante",
    "wof:name":"Ricardo Menor Cdad",
    "wof:placetype":"venue"
},
  "geometry": {"coordinates":[-0.8705040216,38.6358566284],"type":"Point"}
}