{
  "type": "Feature",
  "properties": {
    "addr:full":"Calle de Londres, 44 Madrid Madrid 28028",
    "addr:housenumber":"44",
    "addr:postcode":"madrid;28028",
    "addr:street":"Calle De Londres",
    "iso:country":"ES",
    "sg:address":"Calle de Londres, 44",
    "sg:city":"Madrid",
    "sg:orig_category":"Peluquer\u00cdas, Peluquer\u00cda Mixta",
    "sg:phone":"+34 913 56 85 30",
    "sg:postcode":"28028",
    "sg:province":"Madrid",
    "wof:name":"Smes Peluqueros S.l.",
    "wof:placetype":"venue"
},
  "geometry": {"coordinates":[-3.6676108837,40.4314613342],"type":"Point"}
}