{
  "type": "Feature",
  "properties": {
    "iso:country":"ES",
    "sg:address":"Sect Literatos, 33",
    "sg:city":"Tres Cantos",
    "sg:orig_category":"Inmobiliaria (agencias)",
    "sg:phone":"+34 918 04 91 71",
    "sg:postcode":"28760",
    "sg:province":"Madrid",
    "wof:name":"Intergestion Inmobiliaria Madrilena S.l.",
    "wof:placetype":"venue"
},
  "geometry": {"coordinates":[-3.7133891582,40.6084976196],"type":"Point"}
}