{
  "type": "Feature",
  "properties": {
    "addr:full":"Calle de Andalucia, 35 Santa Maria Aguila Almer\u00eda 04710",
    "addr:housenumber":"35",
    "addr:postcode":"04710",
    "addr:street":"Calle De Andalucia;Almeri\u0301A",
    "iso:country":"ES",
    "sg:address":"Calle de Andalucia, 35",
    "sg:city":"Santa Maria Aguila",
    "sg:orig_category":"Papeler\u00cdas, Librer\u00cdas",
    "sg:phone":"+34 950 58 10 42",
    "sg:postcode":"04710",
    "sg:province":"Almer\u00eda",
    "wof:name":"Rodriguez Martinez Manuel",
    "wof:placetype":"venue"
},
  "geometry": {"coordinates":[-2.7741787434,36.7809867859],"type":"Point"}
}