{
  "type": "Feature",
  "properties": {
    "iso:country":"ES",
    "sg:address":"Calle de Carmelitas, 1",
    "sg:city":"Veguellina Orbigo",
    "sg:orig_category":"Internados & Ense\u00d1anza Privada",
    "sg:phone":"+34 987 37 40 56",
    "sg:postcode":"24350",
    "sg:province":"Le\u00f3n",
    "wof:name":"Hermanas Carmelitas Teresas San Jose",
    "wof:placetype":"venue"
},
  "geometry": {"coordinates":[-5.8846845627,42.4336204529],"type":"Point"}
}