{
  "type": "Feature",
  "properties": {
    "addr:full":"Calle de Jose Perseguer, 8 Petrer Alicante 03610",
    "addr:housenumber":"8",
    "addr:postcode":"03610",
    "addr:street":"Calle De Jose Perseguer",
    "iso:country":"ES",
    "sg:address":"Calle de Jose Perseguer, 8",
    "sg:city":"Petrer",
    "sg:orig_category":"Arquitectos",
    "sg:phone":"+34 966 95 53 29",
    "sg:postcode":"03610",
    "sg:province":"Alicante",
    "wof:name":"Pina Y Poveda Arquitectos S.l.",
    "wof:placetype":"venue"
},
  "geometry": {"coordinates":[-0.7713800073,38.4836883545],"type":"Point"}
}