{
  "type": "Feature",
  "properties": {
    "addr:full":"Carretera De Leda\u00f1a, 4 Iniesta Cuenca 16235",
    "addr:housenumber":"4",
    "addr:postcode":"16235",
    "addr:street":"Carretera De Ledan\u0303A",
    "iso:country":"ES",
    "sg:address":"Carretera De Leda\u00f1a, 4",
    "sg:city":"Iniesta",
    "sg:orig_category":"Fisioterapia",
    "sg:phone":"+34 967 54 50 10",
    "sg:postcode":"16235",
    "sg:province":"Cuenca",
    "wof:name":"Ayuntamiento De Iniesta",
    "wof:placetype":"venue"
},
  "geometry": {"coordinates":[-1.7449692488,39.4393501282],"type":"Point"}
}