{
  "type": "Feature",
  "properties": {
    "addr:full":"Carrer de Sant Pere Mes Baix, 35 Barcelona Barcelona 08003",
    "addr:housenumber":"35",
    "addr:postcode":"08003",
    "addr:street":"Carrer De Sant",
    "iso:country":"ES",
    "sg:address":"Carrer de Sant Pere Mes Baix, 35",
    "sg:city":"Barcelona",
    "sg:orig_category":"Telas Y Sedas (al Por Menor)",
    "sg:phone":"+34 933 19 15 28",
    "sg:postcode":"08003",
    "sg:province":"Barcelona",
    "wof:name":"Bernaus Argemi Pedro",
    "wof:placetype":"venue"
},
  "geometry": {"coordinates":[2.177519083,41.3874931335],"type":"Point"}
}