{
  "type": "Feature",
  "properties": {
    "addr:full":"Carrer de Jesus, 11 Sitges Barcelona 08870",
    "addr:housenumber":"11",
    "addr:postcode":"08870",
    "addr:street":"Carrer De Jesus",
    "iso:country":"ES",
    "sg:address":"Carrer de Jesus, 11",
    "sg:city":"Sitges",
    "sg:orig_category":"Heladeros",
    "sg:phone":"+34 938 11 01 72",
    "sg:postcode":"08870",
    "sg:province":"Barcelona",
    "wof:name":"Olivier Olivier Joan Carles",
    "wof:placetype":"venue"
},
  "geometry": {"coordinates":[1.8099880219,41.2371177673],"type":"Point"}
}