{
  "type": "Feature",
  "properties": {
    "iso:country":"ES",
    "sg:address":"Calle de Soldados (los), 19",
    "sg:city":"Palencia",
    "sg:orig_category":"Venta, Instalaci\u00d3n De Calefacci\u00d3n",
    "sg:phone":"+34 979 74 40 48",
    "sg:postcode":"34001",
    "sg:province":"Palencia",
    "wof:name":"Serna Ramos Miguel Angel",
    "wof:placetype":"venue"
},
  "geometry": {"coordinates":[-4.5320940018,42.0135345459],"type":"Point"}
}