{
  "type": "Feature",
  "properties": {
    "addr:full":"Avda Rosales (de Los), 75 Parque Coimbra Madrid 28935",
    "addr:postcode":"28935",
    "addr:street":"Avda Rosales De Los;Parque",
    "iso:country":"ES",
    "sg:address":"Avda Rosales (de Los), 75",
    "sg:city":"Parque Coimbra",
    "sg:orig_category":"Marcado Industrial",
    "sg:phone":"+34 916 45 10 02",
    "sg:postcode":"28935",
    "sg:province":"Madrid",
    "wof:name":"Newprinter S.a.",
    "wof:placetype":"venue"
},
  "geometry": {"coordinates":[-3.9304029942,40.3058052063],"type":"Point"}
}