{
  "type": "Feature",
  "properties": {
    "addr:full":"C/ Amargura, 12 Manacor Islas Baleares 07500",
    "addr:housenumber":"12",
    "addr:postcode":"07500",
    "addr:street":"C / Amargura",
    "iso:country":"ES",
    "sg:address":"C/ Amargura, 12",
    "sg:city":"Manacor",
    "sg:orig_category":"Fabricaci\u00d3n, Importaci\u00d3n, Venta De Material De Telefon\u00cda, Peritelefon\u00cda",
    "sg:phone":"+34 971 84 36 03",
    "sg:postcode":"07500",
    "sg:province":"Islas Baleares",
    "wof:name":"Xtra Telecom S.a.",
    "wof:placetype":"venue"
},
  "geometry": {"coordinates":[3.2109119892,39.569732666],"type":"Point"}
}