{
  "type": "Feature",
  "properties": {
    "addr:full":"Calle de Santa Cruz De Marcenado, 1 Madrid Madrid 28015",
    "addr:housenumber":"1",
    "addr:postcode":"28015",
    "addr:street":"Calle De Santa Cruz De Marcenado",
    "iso:country":"ES",
    "sg:address":"Calle de Santa Cruz De Marcenado, 1",
    "sg:city":"Madrid",
    "sg:orig_category":"Cr\u00cda De Animales De Caza Menor",
    "sg:phone":"+34 914 48 31 41",
    "sg:postcode":"28015",
    "sg:province":"Madrid",
    "wof:name":"Los Lobos Valdeloboillos Sl",
    "wof:placetype":"venue"
},
  "geometry": {"coordinates":[-3.7069911957,40.4289207458],"type":"Point"}
}