{
  "type": "Feature",
  "properties": {
    "iso:country":"ES",
    "sg:address":"Calle de Virgen, 25",
    "sg:city":"Quintanar Rey",
    "sg:orig_category":"Asesor\u00cda Sobre Comunicaci\u00d3n De Empresas",
    "sg:phone":"+34 967 54 45 25",
    "sg:postcode":"16220",
    "sg:province":"Cuenca",
    "wof:name":"Asesoria Cantu De Quintanar Del Rey S.l.",
    "wof:placetype":"venue"
},
  "geometry": {"coordinates":[-1.911616087,39.263217926],"type":"Point"}
}