{
  "type": "Feature",
  "properties": {
    "addr:full":"Carr Lluis Tur I Palau, 12 Eivissa Islas Baleares 07800",
    "addr:housenumber":"12",
    "addr:postcode":"07800",
    "addr:street":"Carr Lluis Tur I Palau",
    "iso:country":"ES",
    "sg:address":"Carr Lluis Tur I Palau, 12",
    "sg:city":"Eivissa",
    "sg:orig_category":"Agencias De Viajes",
    "sg:phone":"+34 971 31 21 02",
    "sg:postcode":"07800",
    "sg:province":"Islas Baleares",
    "wof:name":"Karol Agencia De Viajes S. A.",
    "wof:placetype":"venue"
},
  "geometry": {"coordinates":[1.4361926317,38.9101982117],"type":"Point"}
}