{
  "type": "Feature",
  "properties": {
    "iso:country":"ES",
    "sg:address":"Av Marques De L'argentera, 21",
    "sg:city":"Barcelona",
    "sg:orig_category":"Inmobiliaria (agencias)",
    "sg:phone":"+34 932 68 18 27",
    "sg:postcode":"08003",
    "sg:province":"Barcelona",
    "wof:name":"Bon Piso Asesores Inmobiliarios S.l.",
    "wof:placetype":"venue"
},
  "geometry": {"coordinates":[2.1852593422,41.3850708008],"type":"Point"}
}