{
  "type": "Feature",
  "properties": {
    "addr:full":"Calle de San Francisco, 12 Aranda Duero Burgos 09400",
    "addr:housenumber":"12",
    "addr:postcode":"09400",
    "addr:street":"Calle De San Francisco",
    "iso:country":"ES",
    "sg:address":"Calle de San Francisco, 12",
    "sg:city":"Aranda Duero",
    "sg:orig_category":"Internados & Ense\u00d1anza Privada",
    "sg:phone":"+34 947 50 01 75",
    "sg:postcode":"09400",
    "sg:province":"Burgos",
    "wof:name":"Colegio De La Vera Cruz",
    "wof:placetype":"venue"
},
  "geometry": {"coordinates":[-3.6855089664,41.6727790833],"type":"Point"}
}