{
  "type": "Feature",
  "properties": {
    "addr:full":"Calle de Santa Ana, S/n Aguadulce Sevilla 41550",
    "addr:housenumber":"s / n",
    "addr:postcode":"41550",
    "addr:street":"Calle De Santa Ana",
    "iso:country":"ES",
    "sg:address":"Calle de Santa Ana, S/n",
    "sg:city":"Aguadulce",
    "sg:orig_category":"Frutas Y Legumbres Frescas (al Por Mayor)",
    "sg:phone":"+34 954 81 62 04",
    "sg:postcode":"41550",
    "sg:province":"Sevilla",
    "wof:name":"Suroliva Sociedad Cooperativa Andaluza",
    "wof:placetype":"venue"
},
  "geometry": {"coordinates":[-4.9899039268,37.2524604797],"type":"Point"}
}