{
  "type": "Feature",
  "properties": {
    "addr:full":"Calle de Jupiter, 29 Sevilla Sevilla 41003",
    "addr:housenumber":"29",
    "addr:postcode":"41003",
    "addr:street":"Calle De Jupiter",
    "iso:country":"ES",
    "sg:address":"Calle de Jupiter, 29",
    "sg:city":"Sevilla",
    "sg:orig_category":"Asociaciones Y Clubs Deportivos",
    "sg:phone":"+34 954 53 33 09",
    "sg:postcode":"41003",
    "sg:province":"Sevilla",
    "wof:name":"Asociacion Deportiva Jupiter Sevilla",
    "wof:placetype":"venue"
},
  "geometry": {"coordinates":[-5.9806900024,37.3908309937],"type":"Point"}
}