{
  "type": "Feature",
  "properties": {
    "iso:country":"ES",
    "sg:address":"Calle de Trinidad, 8",
    "sg:city":"Alcala Henares",
    "sg:orig_category":"Agencias Y Asesores De Publicidad",
    "sg:phone":"+34 918 80 22 63",
    "sg:postcode":"28801",
    "sg:province":"Madrid",
    "wof:name":"Fernandez Saez Roberto",
    "wof:placetype":"venue"
},
  "geometry": {"coordinates":[-3.3640999794,40.4808082581],"type":"Point"}
}