{
  "type": "Feature",
  "properties": {
    "iso:country":"ES",
    "sg:address":"Carrer de Sant Antoni, 17",
    "sg:city":"Sabadell",
    "sg:orig_category":"Ropa De Hogar (al Por Menor)",
    "sg:phone":"+34 937 27 92 72",
    "sg:postcode":"08201",
    "sg:province":"Barcelona",
    "sg:website":"www.textura-interiors.com",
    "wof:name":"Textil Textura S.l.",
    "wof:placetype":"venue"
},
  "geometry": {"coordinates":[2.107790947,41.5480613708],"type":"Point"}
}