{
  "type": "Feature",
  "properties": {
    "addr:full":"Cuesta-taco, Km. 0001,2 La Cuesta Santa Cruz De Tenerife 38320",
    "addr:postcode":"38320",
    "addr:street":"Cuesta-Taco Km. 0001,2",
    "iso:country":"ES",
    "sg:address":"Cuesta-taco, Km. 0001,2",
    "sg:city":"La Cuesta",
    "sg:orig_category":"Frutas Y Legumbres Frescas (al Por Mayor)",
    "sg:phone":"+34 922 64 24 11",
    "sg:postcode":"38320",
    "sg:province":"Santa Cruz De Tenerife",
    "wof:name":"Frutas Del Cono Sur S.l.",
    "wof:placetype":"venue"
},
  "geometry": {"coordinates":[-16.2880134583,28.468454361],"type":"Point"}
}