{
  "type": "Feature",
  "properties": {
    "iso:country":"ES",
    "sg:address":"Calle de Villa De Marin, 1",
    "sg:city":"Madrid",
    "sg:orig_category":"Guarder\u00cdas",
    "sg:phone":"+34 913 14 01 46",
    "sg:postcode":"28029",
    "sg:province":"Madrid",
    "wof:name":"Amelia Gutierrez Idosmas C.b.",
    "wof:placetype":"venue"
},
  "geometry": {"coordinates":[-3.7023389339,40.4747924805],"type":"Point"}
}