{
  "type": "Feature",
  "properties": {
    "iso:country":"ES",
    "sg:address":"Calle de Napoles, 15",
    "sg:city":"Pozuelo De Alarcon",
    "sg:orig_category":"Centros Empresariales",
    "sg:phone":"+34 913 51 78 46",
    "sg:postcode":"28224",
    "sg:province":"Madrid",
    "wof:name":"Regures Luzardo Javier",
    "wof:placetype":"venue"
},
  "geometry": {"coordinates":[-3.7930729389,40.4495010376],"type":"Point"}
}