{
  "type": "Feature",
  "properties": {
    "addr:full":"Hegokalea, 7 Zumaia Guip\u00f9zcoa 20750",
    "addr:housenumber":"7",
    "addr:postcode":"20750",
    "addr:street":"Hegokalea;Guipu\u0300Zcoa",
    "iso:country":"ES",
    "sg:address":"Hegokalea, 7",
    "sg:city":"Zumaia",
    "sg:orig_category":"Maquinaria Para Industrias Diversas",
    "sg:phone":"+34 943 86 56 77",
    "sg:postcode":"20750",
    "sg:province":"Guip\u00f9zcoa",
    "wof:name":"Harai Mekanizatuak S.l.",
    "wof:placetype":"venue"
},
  "geometry": {"coordinates":[-2.2583589554,43.2942314148],"type":"Point"}
}