{
  "type": "Feature",
  "properties": {
    "iso:country":"ES",
    "sg:address":"Calle de Santa Eulalia, 15",
    "sg:city":"Berriosuso",
    "sg:orig_category":"Fabricaci\u00d3n De Pernos, Tornillos Y Clavos",
    "sg:phone":"+34 948 30 27 39",
    "sg:postcode":"31195",
    "sg:province":"Navarra",
    "wof:name":"Industrias San Cristobal S.l.",
    "wof:placetype":"venue"
},
  "geometry": {"coordinates":[-1.6878319979,42.8602561951],"type":"Point"}
}