{
  "type": "Feature",
  "properties": {
    "addr:full":"Calle de Calzada, 19 Puertollano Ciudad Real 13500",
    "addr:housenumber":"19",
    "addr:postcode":"13500",
    "addr:street":"Calle De Calzada",
    "iso:country":"ES",
    "sg:address":"Calle de Calzada, 19",
    "sg:city":"Puertollano",
    "sg:orig_category":"Ropa Para Se\u00d1oras Y Caballeros (al Por Menor)",
    "sg:phone":"+34 926 42 16 83",
    "sg:postcode":"13500",
    "sg:province":"Ciudad Real",
    "wof:name":"Urbion Inversores S.a.",
    "wof:placetype":"venue"
},
  "geometry": {"coordinates":[-4.1099290848,38.6869659424],"type":"Point"}
}