{
  "type": "Feature",
  "properties": {
    "iso:country":"ES",
    "sg:address":"Pase Dolores Soria (de), 8",
    "sg:city":"Pinto",
    "sg:orig_category":"Cajas De Ahorro",
    "sg:phone":"+34 916 92 63 26",
    "sg:postcode":"28320",
    "sg:province":"Madrid",
    "sg:website":"www.bbk.es",
    "wof:name":"Bilbao Bizkaia Kutxa",
    "wof:placetype":"venue"
},
  "geometry": {"coordinates":[-3.697936058,40.2424278259],"type":"Point"}
}