{
  "type": "Feature",
  "properties": {
    "iso:country":"ES",
    "sg:address":"Calle de Ca\u00d1o, 5",
    "sg:city":"Cordoba",
    "sg:orig_category":"Promotores Constructores",
    "sg:phone":"+34 957 47 85 51",
    "sg:postcode":"14001",
    "sg:province":"C\u00f3rdoba",
    "wof:name":"Construcciones Leiva S.l.",
    "wof:placetype":"venue"
},
  "geometry": {"coordinates":[-4.7804341316,37.8879966736],"type":"Point"}
}