{
  "type": "Feature",
  "properties": {
    "addr:full":"Calle de Mayor, 18 Mejorada Campo Madrid 28840",
    "addr:housenumber":"18",
    "addr:postcode":"28840",
    "addr:street":"Calle De Mayor",
    "iso:country":"ES",
    "sg:address":"Calle de Mayor, 18",
    "sg:city":"Mejorada Campo",
    "sg:orig_category":"Zapatos (al Por Menor)",
    "sg:phone":"+34 916 68 08 96",
    "sg:postcode":"28840",
    "sg:province":"Madrid",
    "wof:name":"Rodriguez Chacon Joaquina",
    "wof:placetype":"venue"
},
  "geometry": {"coordinates":[-3.484828949,40.3973464966],"type":"Point"}
}