{
  "type": "Feature",
  "properties": {
    "addr:full":"Calle de Teodoro Calvache, 25 Jaen Ja\u00e9n 23001",
    "addr:housenumber":"25;jae\u0301n",
    "addr:postcode":"23001",
    "addr:street":"Calle De Teodoro Calvache",
    "iso:country":"ES",
    "sg:address":"Calle de Teodoro Calvache, 25",
    "sg:city":"Jaen",
    "sg:orig_category":"Molduras, Junquillos, Listones Y Molduras Perforadas",
    "sg:phone":"+34 953 24 29 40",
    "sg:postcode":"23001",
    "sg:province":"Ja\u00e9n",
    "wof:name":"Garrido Aguilera Antonio",
    "wof:placetype":"venue"
},
  "geometry": {"coordinates":[-3.7855060101,37.767906189],"type":"Point"}
}