{
  "type": "Feature",
  "properties": {
    "addr:full":"Calle de Calero, 3 Solana Ciudad Real 13240",
    "addr:housenumber":"3",
    "addr:postcode":"solana;13240",
    "addr:street":"Calle De Calero;Real",
    "iso:country":"ES",
    "sg:address":"Calle de Calero, 3",
    "sg:city":"Solana",
    "sg:orig_category":"Bancos",
    "sg:phone":"+34 926 63 51 93",
    "sg:postcode":"13240",
    "sg:province":"Ciudad Real",
    "wof:name":"Banco Espa\u00f1ol De Credito S.a.",
    "wof:placetype":"venue"
},
  "geometry": {"coordinates":[-3.2382259369,38.9433364868],"type":"Point"}
}