{
  "type": "Feature",
  "properties": {
    "addr:full":"Calle de Castrillo, 51 Palmas De Gran Canaria Las Palmas 35004",
    "addr:housenumber":"51",
    "addr:postcode":"35004",
    "addr:street":"Calle De Castrillo",
    "iso:country":"ES",
    "sg:address":"Calle de Castrillo, 51",
    "sg:city":"Palmas De Gran Canaria",
    "sg:orig_category":"Electromedicina: Equipo",
    "sg:phone":"+34 928 23 41 07",
    "sg:postcode":"35004",
    "sg:province":"Las Palmas",
    "wof:name":"Positronica S.a.",
    "wof:placetype":"venue"
},
  "geometry": {"coordinates":[-15.4253778458,28.1164417267],"type":"Point"}
}