{
  "type": "Feature",
  "properties": {
    "addr:full":"Avda San Amador, 98 Martos Ja\u00e9n 23600",
    "addr:housenumber":"98",
    "addr:postcode":"23600",
    "addr:street":"Avda San Amador;Jae\u0301N",
    "iso:country":"ES",
    "sg:address":"Avda San Amador, 98",
    "sg:city":"Martos",
    "sg:orig_category":"Agencias Y Asesores De Publicidad",
    "sg:phone":"+34 953 70 00 14",
    "sg:postcode":"23600",
    "sg:province":"Ja\u00e9n",
    "wof:name":"Publiuno S.l.",
    "wof:placetype":"venue"
},
  "geometry": {"coordinates":[-3.9778869152,37.7190437317],"type":"Point"}
}