{
  "type": "Feature",
  "properties": {
    "addr:full":"Carrer de Cardona, 366 Tres Cales Tarragona 43860",
    "addr:housenumber":"366",
    "addr:postcode":"43860",
    "addr:street":"Carrer De Cardona",
    "iso:country":"ES",
    "sg:address":"Carrer de Cardona, 366",
    "sg:city":"Tres Cales",
    "sg:orig_category":"Inmobiliaria (agencias)",
    "sg:phone":"+34 977 45 78 75",
    "sg:postcode":"43860",
    "sg:province":"Tarragona",
    "wof:name":"Agencia Ametlla Galaxy S.l.",
    "wof:placetype":"venue"
},
  "geometry": {"coordinates":[0.8079739213,40.9127998352],"type":"Point"}
}