{
  "type": "Feature",
  "properties": {
    "addr:full":"Calle de Rojas Zorrilla, 4 Alcala Henares Madrid 28805",
    "addr:housenumber":"4",
    "addr:postcode":"28805",
    "addr:street":"Calle De Rojas Zorrilla",
    "iso:country":"ES",
    "sg:address":"Calle de Rojas Zorrilla, 4",
    "sg:city":"Alcala Henares",
    "sg:orig_category":"Caf\u00c9s, Bares, Cervecer\u00cdas",
    "sg:phone":"+34 918 83 51 88",
    "sg:postcode":"28805",
    "sg:province":"Madrid",
    "wof:name":"Crespo Ricote Juan Jose",
    "wof:placetype":"venue"
},
  "geometry": {"coordinates":[-3.3595910072,40.4892349243],"type":"Point"}
}