{
  "type": "Feature",
  "properties": {
    "iso:country":"ES",
    "sg:address":"Calle de Sequia Real Del Xuquer, 4",
    "sg:city":"Alberic",
    "sg:orig_category":"Confecci\u00d3n (fabricaci\u00d3n, Al Por Mayor)",
    "sg:phone":"+34 962 44 15 89",
    "sg:postcode":"46260",
    "sg:province":"Valencia",
    "wof:name":"Zaragoza Sanfelix Maria Dolores",
    "wof:placetype":"venue"
},
  "geometry": {"coordinates":[-0.5199804902,39.115814209],"type":"Point"}
}