{
  "type": "Feature",
  "properties": {
    "addr:full":"Calle de Comandante Zorita, 4 Madrid Madrid 28020",
    "addr:housenumber":"4",
    "addr:postcode":"28020",
    "addr:street":"Calle De Comandante Zorita",
    "iso:country":"ES",
    "sg:address":"Calle de Comandante Zorita, 4",
    "sg:city":"Madrid",
    "sg:orig_category":"Ingeniero",
    "sg:phone":"+34 915 33 51 08",
    "sg:postcode":"28020",
    "sg:province":"Madrid",
    "wof:name":"Tecnologia Y Dise\u00f1os Electronicos S. A.",
    "wof:placetype":"venue"
},
  "geometry": {"coordinates":[-3.6984369755,40.4471092224],"type":"Point"}
}