{
  "type": "Feature",
  "properties": {
    "addr:full":"Calle de Cardenal Ilundain, 18 Sevilla Sevilla 41013",
    "addr:housenumber":"18",
    "addr:postcode":"41013",
    "addr:street":"Calle De Cardenal Ilundain",
    "iso:country":"ES",
    "sg:address":"Calle de Cardenal Ilundain, 18",
    "sg:city":"Sevilla",
    "sg:orig_category":"Embajadas, Consulados Y Otras Representaciones Diplom\u00c1ticas",
    "sg:phone":"+34 954 98 74 76",
    "sg:postcode":"41013",
    "sg:province":"Sevilla",
    "wof:name":"Consulado De Austria",
    "wof:placetype":"venue"
},
  "geometry": {"coordinates":[-5.9822630882,37.3642425537],"type":"Point"}
}