{
  "type": "Feature",
  "properties": {
    "addr:full":"L. Bravo, 11 Villalonquejar Burgos 09001",
    "addr:housenumber":"11",
    "addr:postcode":"09001",
    "addr:street":"L. Bravo",
    "iso:country":"ES",
    "sg:address":"L. Bravo, 11",
    "sg:city":"Villalonquejar",
    "sg:orig_category":"Comercio De Piezas De Recambio Y De Accesorios De Veh\u00cdculos, Veh\u00cdculos Industriales",
    "sg:phone":"+34 947 29 81 23",
    "sg:postcode":"09001",
    "sg:province":"Burgos",
    "wof:name":"Arda S.a.",
    "wof:placetype":"venue"
},
  "geometry": {"coordinates":[-3.7574877739,42.3648033142],"type":"Point"}
}