{
  "type": "Feature",
  "properties": {
    "addr:full":"Calle de Camus, 8 Cueto Cantabria 39012",
    "addr:housenumber":"8",
    "addr:postcode":"39012",
    "addr:street":"Calle De Camus",
    "iso:country":"ES",
    "sg:address":"Calle de Camus, 8",
    "sg:city":"Cueto",
    "sg:orig_category":"Farmacias",
    "sg:phone":"+34 942 39 30 36",
    "sg:postcode":"39012",
    "sg:province":"Cantabria",
    "wof:name":"Botas Prego Maria Victoria",
    "wof:placetype":"venue"
},
  "geometry": {"coordinates":[-3.8604888916,43.4665527344],"type":"Point"}
}