{
  "type": "Feature",
  "properties": {
    "addr:full":"Ctra. Burgos, Km. 0023,7 Najera La Rioja 26300",
    "addr:postcode":"26300",
    "addr:street":"Ctra. Burgos Km. 0023,7 Najera;Rioja",
    "iso:country":"ES",
    "sg:address":"Ctra. Burgos, Km. 0023,7",
    "sg:city":"Najera",
    "sg:orig_category":"Muebles Y Accesorios Para Cocinas Y Cuartos De Ba\u00d1o (al Por Menor)",
    "sg:phone":"+34 941 41 00 01",
    "sg:postcode":"26300",
    "sg:province":"La Rioja",
    "wof:name":"Fiora Bath Collections S.l.",
    "wof:placetype":"venue"
},
  "geometry": {"coordinates":[-2.7250440121,42.4189338684],"type":"Point"}
}