{
  "type": "Feature",
  "properties": {
    "iso:country":"ES",
    "sg:address":"Calle de Fragata Danmark, 1",
    "sg:city":"Santa Cruz De Tenerife",
    "sg:orig_category":"Aparcamientos (infraestructuras, Accesorios)",
    "sg:phone":"+34 922 20 20 59",
    "sg:postcode":"38005",
    "sg:province":"Santa Cruz De Tenerife",
    "wof:name":"Marcelo Vega Hermanos S.l.",
    "wof:placetype":"venue"
},
  "geometry": {"coordinates":[-16.2624149323,28.4590587616],"type":"Point"}
}