{
  "type": "Feature",
  "properties": {
    "addr:full":"Calle de Don Ramon De La Cruz, 90 Madrid Madrid 28006",
    "addr:housenumber":"90",
    "addr:postcode":"madrid;28006",
    "addr:street":"Calle De Don Ramon De La Cruz",
    "iso:country":"ES",
    "sg:address":"Calle de Don Ramon De La Cruz, 90",
    "sg:city":"Madrid",
    "sg:orig_category":"Organismos De Reclutamiento",
    "sg:phone":"+34 914 02 43 13",
    "sg:postcode":"28006",
    "sg:province":"Madrid",
    "wof:name":"De Luis Botin Jose Antonio",
    "wof:placetype":"venue"
},
  "geometry": {"coordinates":[-3.6720232964,40.4285240173],"type":"Point"}
}