{
  "type": "Feature",
  "properties": {
    "addr:full":"Calle de Real, 57 Guadahortuna Granada 18560",
    "addr:housenumber":"57",
    "addr:postcode":"18560",
    "addr:street":"Calle De Real",
    "iso:country":"ES",
    "sg:address":"Calle de Real, 57",
    "sg:city":"Guadahortuna",
    "sg:orig_category":"Iglesia Cat\u00d3lica",
    "sg:phone":"+34 958 38 30 40",
    "sg:postcode":"18560",
    "sg:province":"Granada",
    "wof:name":"Parroquia Santa Maria La Mayor",
    "wof:placetype":"venue"
},
  "geometry": {"coordinates":[-3.399214983,37.5584487915],"type":"Point"}
}