{
  "type": "Feature",
  "properties": {
    "iso:country":"ES",
    "sg:address":"Calle de Julio Palacios, 24",
    "sg:city":"Madrid",
    "sg:orig_category":"Abogados",
    "sg:phone":"+34 913 15 49 00",
    "sg:postcode":"28029",
    "sg:province":"Madrid",
    "wof:name":"Bachiller Ranera Javier Maria",
    "wof:placetype":"venue"
},
  "geometry": {"coordinates":[-3.6937468052,40.4840393066],"type":"Point"}
}