{
  "type": "Feature",
  "properties": {
    "addr:full":"Calle de Eloy Reigada, 41 Bembibre Le\u00f3n 24300",
    "addr:housenumber":"41",
    "addr:postcode":"24300",
    "addr:street":"Calle De Eloy Reigada;Leo\u0301N",
    "iso:country":"ES",
    "sg:address":"Calle de Eloy Reigada, 41",
    "sg:city":"Bembibre",
    "sg:orig_category":"Muebles Y Accesorios Para Cocinas Y Cuartos De Ba\u00d1o (al Por Menor)",
    "sg:phone":"+34 987 51 01 68",
    "sg:postcode":"24300",
    "sg:province":"Le\u00f3n",
    "wof:name":"Muebles De Cocina Rubial S.l.",
    "wof:placetype":"venue"
},
  "geometry": {"coordinates":[-6.4203810692,42.6163749695],"type":"Point"}
}