{
  "type": "Feature",
  "properties": {
    "addr:full":"Calle de Vicente Gaceo, 17 Madrid Madrid 28029",
    "addr:housenumber":"17",
    "addr:postcode":"madrid;28029",
    "addr:street":"Calle De Vicente Gaceo",
    "iso:country":"ES",
    "sg:address":"Calle de Vicente Gaceo, 17",
    "sg:city":"Madrid",
    "sg:orig_category":"Peluqueros: De Se\u00d1oras",
    "sg:phone":"+34 913 15 69 07",
    "sg:postcode":"28029",
    "sg:province":"Madrid",
    "wof:name":"Turon Gonzalez Victoriano",
    "wof:placetype":"venue"
},
  "geometry": {"coordinates":[-3.6879899502,40.473613739],"type":"Point"}
}