{
  "type": "Feature",
  "properties": {
    "iso:country":"ES",
    "sg:address":"B. Pedris, 4",
    "sg:city":"Bellcaire Urgell",
    "sg:orig_category":"Agricultura: Abastecimiento Y Cosechado (negocio)",
    "sg:phone":"+34 973 29 50 54",
    "sg:postcode":"25337",
    "sg:province":"Lleida",
    "wof:name":"Ramaderia Solsona S.c.p.",
    "wof:placetype":"venue"
},
  "geometry": {"coordinates":[0.9060400128,41.7576904297],"type":"Point"}
}