{
  "type": "Feature",
  "properties": {
    "addr:full":"C/ Sebastia Garriga, S/n Cerdanyola Valles Barcelona 08290",
    "addr:housenumber":"s / n",
    "addr:postcode":"08290",
    "addr:street":"C / Sebastia Garriga;Valles Barcelona",
    "iso:country":"ES",
    "sg:address":"C/ Sebastia Garriga, S/n",
    "sg:city":"Cerdanyola Valles",
    "sg:orig_category":"Empresarios",
    "sg:phone":"+34 935 94 70 97",
    "sg:postcode":"08290",
    "sg:province":"Barcelona",
    "wof:name":"Fundacio Privada Pro Persones Amb Disminucio Psiquica Catalonia",
    "wof:placetype":"venue"
},
  "geometry": {"coordinates":[2.1307499409,41.4910964966],"type":"Point"}
}