{
  "type": "Feature",
  "properties": {
    "iso:country":"ES",
    "sg:address":"Carr Leonor Servera, S/n",
    "sg:city":"Cala Ratjada",
    "sg:orig_category":"Peluquer\u00cdas, Peluquer\u00cda Mixta",
    "sg:phone":"+34 971 56 58 05",
    "sg:postcode":"07590",
    "sg:province":"Islas Baleares",
    "wof:name":"Ketstim  Detlefsen",
    "wof:placetype":"venue"
},
  "geometry": {"coordinates":[3.4593300819,39.7099304199],"type":"Point"}
}