{
  "type": "Feature",
  "properties": {
    "iso:country":"ES",
    "sg:address":"Calle de Granada, 89",
    "sg:city":"Nerja",
    "sg:orig_category":"Cajas Para Embalar",
    "sg:phone":"+34 952 52 14 42",
    "sg:postcode":"29780",
    "sg:province":"M\u00e1laga",
    "wof:name":"Cajamar",
    "wof:placetype":"venue"
},
  "geometry": {"coordinates":[-3.8790040016,36.747844696],"type":"Point"}
}