{
  "type": "Feature",
  "properties": {
    "iso:country":"ES",
    "sg:address":"Grup Edificio Paraiso, S/n",
    "sg:city":"Sevilla",
    "sg:orig_category":"Peluquer\u00cdas, Peluquer\u00cda Mixta",
    "sg:phone":"+34 954 40 39 70",
    "sg:postcode":"41020",
    "sg:province":"Sevilla",
    "wof:name":"Leon Perez Maria Del Rosario",
    "wof:placetype":"venue"
},
  "geometry": {"coordinates":[-5.9333291054,37.4165763855],"type":"Point"}
}