{
  "type": "Feature",
  "properties": {
    "addr:full":"Calle de Blas Infante, 12 Velez-malaga M\u00e1laga 29700",
    "addr:housenumber":"12",
    "addr:postcode":"29700",
    "addr:street":"Calle De Blas Infante",
    "iso:country":"ES",
    "sg:address":"Calle de Blas Infante, 12",
    "sg:city":"Velez-malaga",
    "sg:orig_category":"Centros Comerciales Y Grandes Tiendas",
    "sg:phone":"+34 952 55 81 06",
    "sg:postcode":"29700",
    "sg:province":"M\u00e1laga",
    "sg:website":"www.agrosarmiento.com",
    "wof:name":"Agrosarmiento S.l.",
    "wof:placetype":"venue"
},
  "geometry": {"coordinates":[-4.1090364456,36.7823486328],"type":"Point"}
}