{
  "type": "Feature",
  "properties": {
    "addr:full":"Calle de Larratundu, 5 Bilbao Vizcaya 48004",
    "addr:housenumber":"5",
    "addr:postcode":"48004",
    "addr:street":"Calle De Larratundu",
    "iso:country":"ES",
    "sg:address":"Calle de Larratundu, 5",
    "sg:city":"Bilbao",
    "sg:orig_category":"Ropa Para Se\u00d1oras Y Caballeros (al Por Menor)",
    "sg:phone":"+34 944 73 34 45",
    "sg:postcode":"48004",
    "sg:province":"Vizcaya",
    "wof:name":"Tara, C.b.",
    "wof:placetype":"venue"
},
  "geometry": {"coordinates":[-2.8994050026,43.2591934204],"type":"Point"}
}