{
  "type": "Feature",
  "properties": {
    "iso:country":"ES",
    "sg:address":"Pl Ajuntament, 6",
    "sg:city":"Casc Urba",
    "sg:orig_category":"Bancos",
    "sg:phone":"+34 935 40 82 40",
    "sg:postcode":"08328",
    "sg:province":"Barcelona",
    "wof:name":"Banc Sabadell S.a.",
    "wof:placetype":"venue"
},
  "geometry": {"coordinates":[2.2946848869,41.4925308228],"type":"Point"}
}