{
  "type": "Feature",
  "properties": {
    "addr:full":"Pl Ntra Sra Carmen, 14 Rada Moraira Alicante 03724",
    "addr:housenumber":"14",
    "addr:postcode":"03724",
    "addr:street":"Pl Ntra Sra Carmen",
    "iso:country":"ES",
    "sg:address":"Pl Ntra Sra Carmen, 14",
    "sg:city":"Rada Moraira",
    "sg:orig_category":"\u00d3ptica: Instrumentos (fabricaci\u00d3n)",
    "sg:phone":"+34 965 74 49 92",
    "sg:postcode":"03724",
    "sg:province":"Alicante",
    "wof:name":"Optica Kristal Alfaz S.l.",
    "wof:placetype":"venue"
},
  "geometry": {"coordinates":[0.1258890033,38.6994819641],"type":"Point"}
}