{
  "type": "Feature",
  "properties": {
    "addr:full":"Calle de Acacia, 14 Torrejon Ardoz Madrid 28850",
    "addr:housenumber":"14",
    "addr:postcode":"28850",
    "addr:street":"Calle De Acacia",
    "iso:country":"ES",
    "sg:address":"Calle de Acacia, 14",
    "sg:city":"Torrejon Ardoz",
    "sg:orig_category":"Tratamiento De Metales",
    "sg:phone":"+34 916 77 91 24",
    "sg:postcode":"28850",
    "sg:province":"Madrid",
    "wof:name":"Trayde S.l.",
    "wof:placetype":"venue"
},
  "geometry": {"coordinates":[-3.4598751068,40.4474716187],"type":"Point"}
}