{
  "type": "Feature",
  "properties": {
    "iso:country":"ES",
    "sg:address":"Pl Tereses (de Les), 27",
    "sg:city":"Mataro",
    "sg:orig_category":"Estudios, Instalaci\u00d3n De Climatizaci\u00d3n",
    "sg:phone":"+34 937 96 00 53",
    "sg:postcode":"08302",
    "sg:province":"Barcelona",
    "wof:name":"Climaresme S.c.c.l.",
    "wof:placetype":"venue"
},
  "geometry": {"coordinates":[2.4416489601,41.5381965637],"type":"Point"}
}