{
  "type": "Feature",
  "properties": {
    "addr:full":"Carr S Joan Baptista, 19 Igualada Barcelona 08700",
    "addr:housenumber":"19",
    "addr:postcode":"08700",
    "addr:street":"Carr S Joan Baptista",
    "iso:country":"ES",
    "sg:address":"Carr S Joan Baptista, 19",
    "sg:city":"Igualada",
    "sg:orig_category":"Fabricaci\u00d3n De Su\u00c9ters Y Chalecos De Punto",
    "sg:phone":"+34 938 03 62 02",
    "sg:postcode":"08700",
    "sg:province":"Barcelona",
    "wof:name":"Palmes Padro Salvador",
    "wof:placetype":"venue"
},
  "geometry": {"coordinates":[1.62530303,41.5832176208],"type":"Point"}
}