{
  "type": "Feature",
  "properties": {
    "addr:full":"Cm\u00d1o Folgueiras (de), 4 Vilaxuane Lugo 27780",
    "addr:postcode":"27780",
    "iso:country":"ES",
    "sg:address":"Cm\u00d1o Folgueiras (de), 4",
    "sg:city":"Vilaxuane",
    "sg:orig_category":"Arquitectos",
    "sg:phone":"+34 982 13 28 59",
    "sg:postcode":"27780",
    "sg:province":"Lugo",
    "wof:name":"Campos Gil Jesus",
    "wof:placetype":"venue"
},
  "geometry": {"coordinates":[-7.2613739967,43.5743751526],"type":"Point"}
}