{
  "type": "Feature",
  "properties": {
    "addr:full":"Carrer de Illa De Xipre, 35 Coll De'n Rabassa Islas Baleares 07007",
    "addr:housenumber":"35",
    "addr:postcode":"07007",
    "addr:street":"Carrer De Illa De Xipre;De'N;Islas",
    "iso:country":"ES",
    "sg:address":"Carrer de Illa De Xipre, 35",
    "sg:city":"Coll De'n Rabassa",
    "sg:orig_category":"Bares, Piano",
    "sg:phone":"+34 971 74 56 68",
    "sg:postcode":"07007",
    "sg:province":"Islas Baleares",
    "wof:name":"Royal Beach Pub S.l.",
    "wof:placetype":"venue"
},
  "geometry": {"coordinates":[2.9117100239,39.6136398315],"type":"Point"}
}