{
  "type": "Feature",
  "properties": {
    "addr:full":"Calle de Carnicerias, 12 Tudela Navarra 31500",
    "addr:housenumber":"12",
    "addr:postcode":"31500",
    "addr:street":"Calle De Carnicerias",
    "iso:country":"ES",
    "sg:address":"Calle de Carnicerias, 12",
    "sg:city":"Tudela",
    "sg:orig_category":"Molduras, Junquillos, Listones Y Molduras Perforadas",
    "sg:phone":"+34 948 82 57 00",
    "sg:postcode":"31500",
    "sg:province":"Navarra",
    "wof:name":"Berdonces Escudero Francisco Javier",
    "wof:placetype":"venue"
},
  "geometry": {"coordinates":[-1.606695056,42.0624275208],"type":"Point"}
}