{
  "type": "Feature",
  "properties": {
    "iso:country":"ES",
    "sg:address":"Calle de Obispo Manso, 4",
    "sg:city":"Zamora",
    "sg:orig_category":"M\u00c9dicos: Oftalmolog\u00cda",
    "sg:phone":"+34 980 53 41 74",
    "sg:postcode":"49001",
    "sg:province":"Zamora",
    "wof:name":"Palomero Pescador Maria Amalia",
    "wof:placetype":"venue"
},
  "geometry": {"coordinates":[-5.7529420853,41.4990386963],"type":"Point"}
}