{
  "type": "Feature",
  "properties": {
    "iso:country":"ES",
    "sg:address":"Calle de Henares (del), 23",
    "sg:city":"Velilla S.antonio",
    "sg:orig_category":"Comercio De Piezas De Recambio Y De Accesorios De Veh\u00cdculos, Veh\u00cdculos Industriales",
    "sg:phone":"+34 916 55 30 59",
    "sg:postcode":"28891",
    "sg:province":"Madrid",
    "sg:website":"www.radialin.es",
    "wof:name":"Radialin S.l.",
    "wof:placetype":"venue"
},
  "geometry": {"coordinates":[-3.493213892,40.3666572571],"type":"Point"}
}