{
  "type": "Feature",
  "properties": {
    "addr:full":"Calle de Boqueron, 2 Villarejo Del Valle \u00c1vila 05413",
    "addr:housenumber":"2",
    "addr:postcode":"05413",
    "addr:street":"Calle De Boqueron;A\u0301Vila",
    "iso:country":"ES",
    "sg:address":"Calle de Boqueron, 2",
    "sg:city":"Villarejo Del Valle",
    "sg:orig_category":"Molduras, Junquillos, Listones Y Molduras Perforadas",
    "sg:phone":"+34 920 38 40 74",
    "sg:postcode":"05413",
    "sg:province":"\u00c1vila",
    "wof:name":"Olayo Yestera Alberto",
    "wof:placetype":"venue"
},
  "geometry": {"coordinates":[-4.9976649284,40.2859382629],"type":"Point"}
}