{
  "type": "Feature",
  "properties": {
    "iso:country":"ES",
    "sg:address":"Avda Constitucion, 15",
    "sg:city":"Madridejos",
    "sg:orig_category":"Negocio De Materiales De Construcci\u00d3n",
    "sg:phone":"+34 925 46 39 43",
    "sg:postcode":"45710",
    "sg:province":"Toledo",
    "wof:name":"Garcia Due\u00f1as Josefa",
    "wof:placetype":"venue"
},
  "geometry": {"coordinates":[-3.5322339535,39.4691734314],"type":"Point"}
}