{
  "type": "Feature",
  "properties": {
    "addr:full":"Calle de Diego Lainez, 15 Burgos Burgos 09005",
    "addr:housenumber":"15",
    "addr:postcode":"09005",
    "addr:street":"Calle De Diego Lainez",
    "iso:country":"ES",
    "sg:address":"Calle de Diego Lainez, 15",
    "sg:city":"Burgos",
    "sg:orig_category":"Moquetas, Alfombras (al Por Menor)",
    "sg:phone":"+34 947 21 41 59",
    "sg:postcode":"09005",
    "sg:province":"Burgos",
    "wof:name":"Lopez Hervas Ildefonso",
    "wof:placetype":"venue"
},
  "geometry": {"coordinates":[-3.6993188858,42.3479804993],"type":"Point"}
}