{
  "type": "Feature",
  "properties": {
    "iso:country":"ES",
    "sg:address":"Carrer de Gremi De Sabaters, S/n",
    "sg:city":"Poligon Industrial De Son Castello",
    "sg:orig_category":"Quincaller\u00cda (al Por Menor)",
    "sg:phone":"+34 971 43 20 33",
    "sg:postcode":"07009",
    "sg:province":"Islas Baleares",
    "sg:website":"www.ferba.com",
    "wof:name":"Cofac;ferreeros Asociados Sccl",
    "wof:placetype":"venue"
},
  "geometry": {"coordinates":[2.6741399765,39.6011390686],"type":"Point"}
}