{
  "type": "Feature",
  "properties": {
    "addr:full":"Calle de Fernandez De Oviedo, 7 Oviedo Asturias 33012",
    "addr:housenumber":"7",
    "addr:postcode":"33012",
    "addr:street":"Calle De Fernandez De Oviedo",
    "iso:country":"ES",
    "sg:address":"Calle de Fernandez De Oviedo, 7",
    "sg:city":"Oviedo",
    "sg:orig_category":"Serigraf\u00cda (material Y Suministros)",
    "sg:phone":"+34 985 29 91 99",
    "sg:postcode":"33012",
    "sg:province":"Asturias",
    "wof:name":"Fierro Alonso Cesar Miguel",
    "wof:placetype":"venue"
},
  "geometry": {"coordinates":[-5.8567852974,43.3689346313],"type":"Point"}
}