{
  "type": "Feature",
  "properties": {
    "addr:full":"Rua Diego Pazos, 91 Sarria Lugo 27600",
    "addr:housenumber":"91",
    "addr:postcode":"27600",
    "addr:street":"Rua Diego Pazos",
    "iso:country":"ES",
    "sg:address":"Rua Diego Pazos, 91",
    "sg:city":"Sarria",
    "sg:orig_category":"Ense\u00d1anza Variada",
    "sg:phone":"+34 982 53 33 47",
    "sg:postcode":"27600",
    "sg:province":"Lugo",
    "wof:name":"Amado Basteiro Manuel",
    "wof:placetype":"venue"
},
  "geometry": {"coordinates":[-7.4088807106,42.782245636],"type":"Point"}
}