{
  "type": "Feature",
  "properties": {
    "iso:country":"ES",
    "sg:address":"Trva Eladia Baylina, 8",
    "sg:city":"Ponferrada",
    "sg:orig_category":"Fabricaci\u00d3n De Juguetes Autom\u00c1ticos",
    "sg:phone":"+34 987 42 87 37",
    "sg:postcode":"24400",
    "sg:province":"Le\u00f3n",
    "wof:name":"Bierzoplay S.l.",
    "wof:placetype":"venue"
},
  "geometry": {"coordinates":[-6.5970048904,42.5468292236],"type":"Point"}
}