{
  "type": "Feature",
  "properties": {
    "iso:country":"ES",
    "sg:address":"Ptge Sant Miquel, 4",
    "sg:city":"Mollet Valles",
    "sg:classifiers":[
        {
            "category":"Personal",
            "subcategory":"Barber",
            "type":"Services"
        }
    ],
    "sg:phone":"+34 935 93 51 50",
    "sg:postcode":"08100",
    "sg:province":"Barcelona",
    "sg:tags":[
        "caballeros",
        "de",
        "peluqueros"
    ],
    "wof:name":"Ferreiro Rodriguez Francisco",
    "wof:placetype":"venue"
},
  "geometry": {"coordinates":[2.2122709751,41.5373344421],"type":"Point"}
}