{
  "type": "Feature",
  "properties": {
    "addr:full":"Avda Carolina Coronado, 37 Badajoz Badajoz 06007",
    "addr:housenumber":"37",
    "addr:postcode":"06007",
    "addr:street":"Avda Carolina Coronado",
    "iso:country":"ES",
    "sg:address":"Avda Carolina Coronado, 37",
    "sg:city":"Badajoz",
    "sg:orig_category":"Promotores Constructores",
    "sg:phone":"+34 924 28 62 67",
    "sg:postcode":"06007",
    "sg:province":"Badajoz",
    "wof:name":"Coalfe Construcciones Extreme\u00f1as S.l.",
    "wof:placetype":"venue"
},
  "geometry": {"coordinates":[-6.9799809456,38.8858337402],"type":"Point"}
}