{
  "type": "Feature",
  "properties": {
    "addr:full":"Calle de Ingeniero Marquina, 2 Oviedo Asturias 33004",
    "addr:housenumber":"2",
    "addr:postcode":"33004",
    "addr:street":"Calle De Ingeniero Marquina",
    "iso:country":"ES",
    "sg:address":"Calle de Ingeniero Marquina, 2",
    "sg:city":"Oviedo",
    "sg:orig_category":"Alquiler De Veh\u00cdculos: Turismos Y Utilitarios",
    "sg:phone":"+34 985 27 44 83",
    "sg:postcode":"33004",
    "sg:province":"Asturias",
    "wof:name":"Alquiler De Vehiculos Y Maquinaria Asturias S.l.",
    "wof:placetype":"venue"
},
  "geometry": {"coordinates":[-5.855796814,43.3652801514],"type":"Point"}
}