{
  "type": "Feature",
  "properties": {
    "addr:full":"Av Josep Molins, 2 Hospitalet Llobregat Barcelona 08906",
    "addr:housenumber":"2",
    "addr:postcode":"08906",
    "addr:street":"Av Josep Molins",
    "iso:country":"ES",
    "sg:address":"Av Josep Molins, 2",
    "sg:city":"Hospitalet Llobregat",
    "sg:orig_category":"Inform\u00c1tica, Ofim\u00c1tica (estudios, Asesor\u00cda, Ingenier\u00cda, Formaci\u00d3n)",
    "sg:phone":"+34 934 40 36 67",
    "sg:postcode":"08906",
    "sg:province":"Barcelona",
    "wof:name":"Menendez Hernandez Lluis",
    "wof:placetype":"venue"
},
  "geometry": {"coordinates":[2.1067330837,41.3758621216],"type":"Point"}
}