{
  "type": "Feature",
  "properties": {
    "iso:country":"ES",
    "sg:address":"Calle de Alcalde Conangla, S/n",
    "sg:city":"Albacete",
    "sg:orig_category":"Loter\u00cda Y T\u00d3mbola",
    "sg:phone":"+34 967 24 38 89",
    "sg:postcode":"02002",
    "sg:province":"Albacete",
    "sg:website":"www.estrelladelasuerte/iespa\u00f1a.es",
    "wof:name":"Tebar Sanchez Juan Carlos",
    "wof:placetype":"venue"
},
  "geometry": {"coordinates":[-1.8480718136,38.9908752441],"type":"Point"}
}