{
  "type": "Feature",
  "properties": {
    "iso:country":"ES",
    "sg:address":"Calle de Aire, 8",
    "sg:city":"Quinzano",
    "sg:orig_category":"Producci\u00d3n, Comercio De Cereales",
    "sg:phone":"+34 974 27 04 86",
    "sg:postcode":"22810",
    "sg:province":"Huesca",
    "wof:name":"Forrajes H Nueno S.l.",
    "wof:placetype":"venue"
},
  "geometry": {"coordinates":[-0.6029068828,42.247631073],"type":"Point"}
}