{
  "type": "Feature",
  "properties": {
    "iso:country":"ES",
    "sg:address":"Plaz Marcos Fernandez, 9",
    "sg:city":"Valladolid",
    "sg:orig_category":"Lencer\u00cda Femenina, Corseter\u00cda, Trajes De Ba\u00d1o (al Por Menor)",
    "sg:phone":"+34 983 35 05 12",
    "sg:postcode":"47014",
    "sg:province":"Valladolid",
    "wof:name":"Monederolid S.l.",
    "wof:placetype":"venue"
},
  "geometry": {"coordinates":[-4.7321238518,41.6541938782],"type":"Point"}
}