{
  "type": "Feature",
  "properties": {
    "addr:full":"Avda Constitucion, 23 Navalmoral Mata C\u00e1ceres 10300",
    "addr:housenumber":"23",
    "addr:postcode":"10300",
    "addr:street":"Avda Constitucion;Ca\u0301Ceres",
    "iso:country":"ES",
    "sg:address":"Avda Constitucion, 23",
    "sg:city":"Navalmoral Mata",
    "sg:orig_category":"Laboratorios Y Trabajos De Fotograf\u00cda, V\u00cddeo Y Cine",
    "sg:phone":"+34 927 53 20 00",
    "sg:postcode":"10300",
    "sg:province":"C\u00e1ceres",
    "wof:name":"Melgares Rodriguez Ana Maria",
    "wof:placetype":"venue"
},
  "geometry": {"coordinates":[-5.5421338081,39.8942337036],"type":"Point"}
}