{
  "type": "Feature",
  "properties": {
    "iso:country":"ES",
    "sg:address":"Calle de Reina (de La), S/n",
    "sg:city":"Pinseque",
    "sg:orig_category":"Venta, Instalaci\u00d3n De Calefacci\u00d3n",
    "sg:phone":"+34 976 61 72 83",
    "sg:postcode":"50298",
    "sg:province":"Zaragoza",
    "wof:name":"Pimpinela Alvarez Simeon",
    "wof:placetype":"venue"
},
  "geometry": {"coordinates":[-1.0961960554,41.7380409241],"type":"Point"}
}