{
  "type": "Feature",
  "properties": {
    "addr:full":"Acequia Favara, 1 Massanassa Valencia 46470",
    "addr:housenumber":"1",
    "addr:postcode":"46470",
    "addr:street":"Favara",
    "iso:country":"ES",
    "sg:address":"Acequia Favara, 1",
    "sg:city":"Massanassa",
    "sg:orig_category":"Ebanister\u00cda",
    "sg:phone":"+34 961 25 23 62",
    "sg:postcode":"46470",
    "sg:province":"Valencia",
    "wof:name":"Pedrosa Moreno Julian",
    "wof:placetype":"venue"
},
  "geometry": {"coordinates":[-0.4032689929,39.4032859802],"type":"Point"}
}