{
  "type": "Feature",
  "properties": {
    "iso:country":"ES",
    "sg:address":"Av Sant Julia, S/n",
    "sg:city":"Granollers",
    "sg:orig_category":"Productos Qu\u00cdmicos (fabricaci\u00d3n, Al Por Mayor)",
    "sg:phone":"+34 938 64 21 00",
    "sg:postcode":"08...",
    "sg:province":"Barcelona",
    "wof:name":"Goldschmidt Espa\u00d1a S.a.",
    "wof:placetype":"venue"
},
  "geometry": {"coordinates":[2.2744998932,41.5907707214],"type":"Point"}
}