{
  "type": "Feature",
  "properties": {
    "addr:full":"Carrer de Pere Martell (de), S/n Tarragona Tarragona 43001",
    "addr:postcode":"43001",
    "addr:street":"Carrer De Pere Martell De S / N",
    "iso:country":"ES",
    "sg:address":"Carrer de Pere Martell (de), S/n",
    "sg:city":"Tarragona",
    "sg:orig_category":"Cajas De Ahorro",
    "sg:phone":"+34 977 23 18 32",
    "sg:postcode":"43001",
    "sg:province":"Tarragona",
    "sg:website":"www.caixatarragona.es",
    "wof:name":"Caixa D'estalvis De Tarragona",
    "wof:placetype":"venue"
},
  "geometry": {"coordinates":[1.2444939613,41.1168670654],"type":"Point"}
}