{
  "type": "Feature",
  "properties": {
    "iso:country":"ES",
    "sg:address":"El Pozo, 10",
    "sg:city":"Tapia Casariego",
    "sg:orig_category":"Pescader\u00cdas (al Por Menor)",
    "sg:phone":"+34 985 62 82 58",
    "sg:postcode":"33740",
    "sg:province":"Asturias",
    "wof:name":"Maseda Lopez Ernesto",
    "wof:placetype":"venue"
},
  "geometry": {"coordinates":[-6.9457688332,43.570602417],"type":"Point"}
}