{
  "type": "Feature",
  "properties": {
    "addr:full":"Carrer de Sardenya, 353 Barcelona Barcelona 08025",
    "addr:housenumber":"353",
    "addr:postcode":"08025",
    "addr:street":"Carrer De Sardenya",
    "iso:country":"ES",
    "sg:address":"Carrer de Sardenya, 353",
    "sg:city":"Barcelona",
    "sg:orig_category":"Venta, Localizaci\u00d3n, Reparaci\u00d3n De Material E Instrumental M\u00c9dico",
    "sg:phone":"+34 934 58 94 57",
    "sg:postcode":"08025",
    "sg:province":"Barcelona",
    "wof:name":"Ambi Medical S.l.",
    "wof:placetype":"venue"
},
  "geometry": {"coordinates":[2.1706192493,41.4054412842],"type":"Point"}
}