{
  "type": "Feature",
  "properties": {
    "addr:full":"Calle de Castello, 113 Madrid Madrid 28006",
    "addr:housenumber":"113",
    "addr:postcode":"28006",
    "addr:street":"Calle De Castello",
    "iso:country":"ES",
    "sg:address":"Calle de Castello, 113",
    "sg:city":"Madrid",
    "sg:orig_category":"Laboratorios Y Trabajos De Fotograf\u00cda, V\u00cddeo Y Cine",
    "sg:phone":"+34 915 64 02 39",
    "sg:postcode":"28006",
    "sg:province":"Madrid",
    "wof:name":"Boom S.l.",
    "wof:placetype":"venue"
},
  "geometry": {"coordinates":[-3.6808030605,40.4358139038],"type":"Point"}
}