{
  "type": "Feature",
  "properties": {
    "addr:full":"Calle de Canet De Berenguer, 1 Sagunt Valencia 46500",
    "addr:housenumber":"1",
    "addr:postcode":"46500",
    "addr:street":"Calle De Canet De Berenguer",
    "iso:country":"ES",
    "sg:address":"Calle de Canet De Berenguer, 1",
    "sg:city":"Sagunt",
    "sg:orig_category":"Arboricultura Y Producci\u00d3n De Frutas",
    "sg:phone":"+34 962 66 42 11",
    "sg:postcode":"46500",
    "sg:province":"Valencia",
    "wof:name":"Brulaf S. A.",
    "wof:placetype":"venue"
},
  "geometry": {"coordinates":[-0.2692072988,39.6782302856],"type":"Point"}
}