{
  "type": "Feature",
  "properties": {
    "addr:full":"Carrer de Victoria, 110 S. Boi Llobregat Barcelona 08830",
    "addr:housenumber":"110",
    "addr:postcode":"08830",
    "addr:street":"Carrer De Victoria;S.",
    "iso:country":"ES",
    "sg:address":"Carrer de Victoria, 110",
    "sg:city":"S. Boi Llobregat",
    "sg:orig_category":"Peluquer\u00cdas, Peluquer\u00cda Mixta",
    "sg:phone":"+34 936 54 21 42",
    "sg:postcode":"08830",
    "sg:province":"Barcelona",
    "sg:website":"www.tannara.es",
    "wof:name":"Tannara Perruquers S.l.",
    "wof:placetype":"venue"
},
  "geometry": {"coordinates":[2.0277199745,41.3493270874],"type":"Point"}
}