{
  "type": "Feature",
  "properties": {
    "iso:country":"ES",
    "sg:address":"Calle de Relojero Losada, 16",
    "sg:city":"Le\u00f3n",
    "sg:orig_category":"Farmacias",
    "sg:phone":"+34 987 23 56 66",
    "sg:postcode":"24009",
    "sg:province":"Le\u00f3n",
    "wof:name":"Arenal Martin Adelaida",
    "wof:placetype":"venue"
},
  "geometry": {"coordinates":[-5.5892262459,42.6004219055],"type":"Point"}
}