{
  "type": "Feature",
  "properties": {
    "addr:full":"Valdepe\u00f1-infantes, Km. 0081,0 Alcubillas Ciudad Real 13391",
    "addr:postcode":"13391",
    "addr:street":"Valdepen\u0303-Infantes Km. 0081,0",
    "iso:country":"ES",
    "sg:address":"Valdepe\u00f1-infantes, Km. 0081,0",
    "sg:city":"Alcubillas",
    "sg:orig_category":"Distribuci\u00d3n De Petr\u00d3leo Y Derivados",
    "sg:phone":"+34 926 35 60 63",
    "sg:postcode":"13391",
    "sg:province":"Ciudad Real",
    "sg:website":"www.cepsa.es",
    "wof:name":"Molina Mena Ramon",
    "wof:placetype":"venue"
},
  "geometry": {"coordinates":[-3.1344499588,38.7545280457],"type":"Point"}
}