{
  "type": "Feature",
  "properties": {
    "addr:full":"Calle de Garcilaso De La Vega, 3 Torrelavega Cantabria 39300",
    "addr:housenumber":"3",
    "addr:postcode":"39300",
    "addr:street":"Calle De Garcilaso De La Vega",
    "iso:country":"ES",
    "sg:address":"Calle de Garcilaso De La Vega, 3",
    "sg:city":"Torrelavega",
    "sg:orig_category":"Expertos Contables",
    "sg:phone":"+34 942 80 81 70",
    "sg:postcode":"39300",
    "sg:province":"Cantabria",
    "wof:name":"Jesus Esteban Rueda Correduria De Seguros S.l.",
    "wof:placetype":"venue"
},
  "geometry": {"coordinates":[-4.0518321991,43.347946167],"type":"Point"}
}