{
  "type": "Feature",
  "properties": {
    "addr:full":"Calle de Sepulveda, 97 Madrid Madrid 28011",
    "addr:housenumber":"97",
    "addr:postcode":"madrid;28011",
    "addr:street":"Calle De Sepulveda",
    "iso:country":"ES",
    "sg:address":"Calle de Sepulveda, 97",
    "sg:city":"Madrid",
    "sg:orig_category":"Tiendas De Grano, Frutas Y Legumbres Secas (al Por Menor)",
    "sg:phone":"+34 915 26 32 69",
    "sg:postcode":"28011",
    "sg:province":"Madrid",
    "wof:name":"Zhang  Lizhen",
    "wof:placetype":"venue"
},
  "geometry": {"coordinates":[-3.7445325851,40.4043121338],"type":"Point"}
}