{
  "type": "Feature",
  "properties": {
    "addr:full":"Carrer de Planet (del), 16 Duesaig\u00fces Tarragona 43773",
    "addr:housenumber":"16",
    "addr:postcode":"43773",
    "addr:street":"Carrer De Planet Del",
    "iso:country":"ES",
    "sg:address":"Carrer de Planet (del), 16",
    "sg:city":"Duesaig\u00fces",
    "sg:orig_category":"Alimentaci\u00d3n General (al Por Menor)",
    "sg:phone":"+34 977 83 43 84",
    "sg:postcode":"43773",
    "sg:province":"Tarragona",
    "wof:name":"Mestre Rabascall Natividad",
    "wof:placetype":"venue"
},
  "geometry": {"coordinates":[0.9303680062,41.1454582214],"type":"Point"}
}