{
  "type": "Feature",
  "properties": {
    "addr:full":"Menestrals, 15 Inca Islas Baleares 07300",
    "addr:housenumber":"15",
    "addr:postcode":"07300",
    "addr:street":"Menestrals",
    "iso:country":"ES",
    "sg:address":"Menestrals, 15",
    "sg:city":"Inca",
    "sg:orig_category":"Transporte En General",
    "sg:phone":"+34 971 50 40 25",
    "sg:postcode":"07300",
    "sg:province":"Islas Baleares",
    "wof:name":"Llinas Reus Bartolome",
    "wof:placetype":"venue"
},
  "geometry": {"coordinates":[2.9101700783,39.7144889832],"type":"Point"}
}