{
  "type": "Feature",
  "properties": {
    "iso:country":"ES",
    "sg:address":"Calle de Maestria, 2",
    "sg:city":"Almeria",
    "sg:orig_category":"Quincaller\u00cda (al Por Menor)",
    "sg:phone":"+34 950 23 48 94",
    "sg:postcode":"04008",
    "sg:province":"Almer\u00eda",
    "wof:name":"Comercial Maestria De Almeria S.l.",
    "wof:placetype":"venue"
},
  "geometry": {"coordinates":[-2.4559290409,36.8491516113],"type":"Point"}
}