{
  "type": "Feature",
  "properties": {
    "iso:country":"ES",
    "sg:address":"Poli Industrial Ibarria, 11",
    "sg:city":"Alsasua",
    "sg:orig_category":"Promotores Constructores",
    "sg:phone":"+34 948 56 47 56",
    "sg:postcode":"31800",
    "sg:province":"Navarra",
    "wof:name":"Enconfrados Y Construcciones Hesan S.l.",
    "wof:placetype":"venue"
},
  "geometry": {"coordinates":[-2.1696588993,42.8959083557],"type":"Point"}
}