{
  "type": "Feature",
  "properties": {
    "iso:country":"ES",
    "sg:address":"Calle de Presidente Alvear, 7",
    "sg:city":"Palmas De Gran Canaria",
    "sg:orig_category":"Asociaciones Y Clubs Deportivos",
    "sg:phone":"+34 928 29 02 74",
    "sg:postcode":"35006",
    "sg:province":"Las Palmas",
    "wof:name":"Cabrera Bonilla Maria Del Carmen",
    "wof:placetype":"venue"
},
  "geometry": {"coordinates":[-15.4303312302,28.1340179443],"type":"Point"}
}