{
  "type": "Feature",
  "properties": {
    "addr:full":"Rua Capitan Eloy, 27 Ourense Ourense 32003",
    "addr:housenumber":"27",
    "addr:postcode":"32003",
    "addr:street":"Rua Capitan Eloy",
    "iso:country":"ES",
    "sg:address":"Rua Capitan Eloy, 27",
    "sg:city":"Ourense",
    "sg:orig_category":"Bancos",
    "sg:phone":"+34 988 23 47 50",
    "sg:postcode":"32003",
    "sg:province":"Ourense",
    "wof:name":"Barclays Bank S.a.e.",
    "wof:placetype":"venue"
},
  "geometry": {"coordinates":[-7.863257885,42.3393173218],"type":"Point"}
}