{
  "type": "Feature",
  "properties": {
    "addr:full":"Calle de Colon, 20 Alcorcon Madrid 28921",
    "addr:housenumber":"20",
    "addr:postcode":"28921",
    "addr:street":"Calle De Colon",
    "iso:country":"ES",
    "sg:address":"Calle de Colon, 20",
    "sg:city":"Alcorcon",
    "sg:orig_category":"Carnicer\u00cdas, Carnicer\u00cdas",
    "sg:phone":"+34 916 43 48 40",
    "sg:postcode":"28921",
    "sg:province":"Madrid",
    "wof:name":"Berzal Castro Salvador",
    "wof:placetype":"venue"
},
  "geometry": {"coordinates":[-3.8284540176,40.3469276428],"type":"Point"}
}