{
  "type": "Feature",
  "properties": {
    "addr:full":"Avda Compromiso De Caspe, 93 Zaragoza Zaragoza 50002",
    "addr:housenumber":"93",
    "addr:postcode":"50002",
    "addr:street":"Avda Compromiso De Caspe",
    "iso:country":"ES",
    "sg:address":"Avda Compromiso De Caspe, 93",
    "sg:city":"Zaragoza",
    "sg:orig_category":"Zapatos (al Por Menor)",
    "sg:phone":"+34 976 59 01 72",
    "sg:postcode":"50002",
    "sg:province":"Zaragoza",
    "wof:name":"Dirocal S. L.",
    "wof:placetype":"venue"
},
  "geometry": {"coordinates":[-0.8622689843,41.6453857422],"type":"Point"}
}