{
  "type": "Feature",
  "properties": {
    "iso:country":"ES",
    "sg:address":"Calle de Artesanos (los), 15",
    "sg:city":"Alcorcon",
    "sg:orig_category":"Cristaler\u00cdas",
    "sg:phone":"+34 916 41 45 37",
    "sg:postcode":"28925",
    "sg:province":"Madrid",
    "wof:name":"Serviglass",
    "wof:placetype":"venue"
},
  "geometry": {"coordinates":[-3.8032801151,40.3409729004],"type":"Point"}
}