{
  "type": "Feature",
  "properties": {
    "iso:country":"ES",
    "sg:address":"Valtierra, 12",
    "sg:city":"Iru\u00f1a",
    "sg:orig_category":"Peluqueros: De Se\u00d1oras",
    "sg:phone":"+34 948 12 70 24",
    "sg:postcode":"31015",
    "sg:province":"Navarra",
    "wof:name":"Samanes Bezanilla Pilar",
    "wof:placetype":"venue"
},
  "geometry": {"coordinates":[-1.6272469759,42.8338546753],"type":"Point"}
}