{
  "type": "Feature",
  "properties": {
    "addr:full":"Calle de Oliva (la), 12 Almonacid Marquesado Cuenca 16431",
    "addr:housenumber":"12",
    "addr:postcode":"16431",
    "addr:street":"Calle De Oliva La",
    "iso:country":"ES",
    "sg:address":"Calle de Oliva (la), 12",
    "sg:city":"Almonacid Marquesado",
    "sg:orig_category":"Iglesia Cat\u00d3lica",
    "sg:phone":"+34 969 12 00 08",
    "sg:postcode":"16431",
    "sg:province":"Cuenca",
    "wof:name":"Parroquia Santiago Apostol",
    "wof:placetype":"venue"
},
  "geometry": {"coordinates":[-2.769012928,39.8230819702],"type":"Point"}
}