{
  "type": "Feature",
  "properties": {
    "addr:full":"Calle de Conde De Salvatierra, 13 Valencia Valencia 46004",
    "addr:housenumber":"13",
    "addr:postcode":"46004",
    "addr:street":"Calle De Conde De Salvatierra",
    "iso:country":"ES",
    "sg:address":"Calle de Conde De Salvatierra, 13",
    "sg:city":"Valencia",
    "sg:orig_category":"Electrodom\u00c9sticos (al Por Menor)",
    "sg:phone":"+34 963 51 28 72",
    "sg:postcode":"46004",
    "sg:province":"Valencia",
    "wof:name":"Futur Hogar S.a.",
    "wof:placetype":"venue"
},
  "geometry": {"coordinates":[-0.3686136007,39.4703369141],"type":"Point"}
}