{
  "type": "Feature",
  "properties": {
    "addr:full":"Calle de Palma Del Rio, 9 Malaga M\u00e1laga 29004",
    "addr:housenumber":"9",
    "addr:postcode":"29004",
    "addr:street":"Calle De Palma Del Rio;Ma\u0301Laga",
    "iso:country":"ES",
    "sg:address":"Calle de Palma Del Rio, 9",
    "sg:city":"Malaga",
    "sg:orig_category":"Empresas De Carpinter\u00cda De Madera",
    "sg:phone":"+34 952 17 42 86",
    "sg:postcode":"29004",
    "sg:province":"M\u00e1laga",
    "wof:name":"Nieto Sanchez Manuel",
    "wof:placetype":"venue"
},
  "geometry": {"coordinates":[-4.4540519714,36.6906738281],"type":"Point"}
}