{
  "type": "Feature",
  "properties": {
    "iso:country":"ES",
    "sg:address":"Urbieta Kalea, 7",
    "sg:city":"Hernani",
    "sg:orig_category":"Farmacias",
    "sg:phone":"+34 943 55 29 41",
    "sg:postcode":"20120",
    "sg:province":"Guip\u00f9zcoa",
    "wof:name":"Bilbao Sagastiberri Joseba Jokin",
    "wof:placetype":"venue"
},
  "geometry": {"coordinates":[-1.9758909941,43.2669067383],"type":"Point"}
}