{
  "type": "Feature",
  "properties": {
    "iso:country":"ES",
    "sg:address":"Cmno San Antonio (cartuja Baja), S/n",
    "sg:city":"Cartuja Baja",
    "sg:orig_category":"Negocio De Madera",
    "sg:phone":"+34 976 41 67 83",
    "sg:postcode":"50720",
    "sg:province":"Zaragoza",
    "wof:name":"Comercial Moldurera Lozano S. L.",
    "wof:placetype":"venue"
},
  "geometry": {"coordinates":[-0.8493639827,41.6246490479],"type":"Point"}
}