{
  "type": "Feature",
  "properties": {
    "iso:country":"ES",
    "sg:address":"Calle de Alcala, 182",
    "sg:city":"Madrid",
    "sg:orig_category":"Heladeros",
    "sg:phone":"+34 917 25 38 41",
    "sg:postcode":"28028",
    "sg:province":"Madrid",
    "wof:name":"Echegaray Deamato Maria Esther",
    "wof:placetype":"venue"
},
  "geometry": {"coordinates":[-3.6657004356,40.4296073914],"type":"Point"}
}