{
  "type": "Feature",
  "properties": {
    "iso:country":"ES",
    "sg:address":"Carrer de Ramon Llull, 58",
    "sg:city":"Sabadell",
    "sg:orig_category":"Fabricaci\u00d3n De Telas Y Sedas",
    "sg:phone":"+34 937 12 16 49",
    "sg:postcode":"08203",
    "sg:province":"Barcelona",
    "sg:website":"www.interasa.com",
    "wof:name":"Industrias Textiles De Raschel S.a.",
    "wof:placetype":"venue"
},
  "geometry": {"coordinates":[2.1094300747,41.53332901],"type":"Point"}
}