{
  "type": "Feature",
  "properties": {
    "iso:country":"ES",
    "sg:address":"Cno. El Ramo, S/n",
    "sg:city":"Olmedillo De Roa",
    "sg:orig_category":"Productores Recolectores, Venta Directa De Vinos",
    "sg:phone":"+34 947 55 10 70",
    "sg:postcode":"09311",
    "sg:province":"Burgos",
    "wof:name":"Bodegas Y Vi\u00f1edos Escudero S.l.",
    "wof:placetype":"venue"
},
  "geometry": {"coordinates":[-3.8752889633,41.7403335571],"type":"Point"}
}