{
  "type": "Feature",
  "properties": {
    "addr:full":"Avda Guadalquivir, 25 Cadiz C\u00e1diz 11012",
    "addr:housenumber":"25",
    "addr:postcode":"11012",
    "addr:street":"Avda Guadalquivir",
    "iso:country":"ES",
    "sg:address":"Avda Guadalquivir, 25",
    "sg:city":"Cadiz",
    "sg:orig_category":"Cajas De Ahorro",
    "sg:phone":"+34 956 25 73 49",
    "sg:postcode":"11012",
    "sg:province":"C\u00e1diz",
    "sg:website":"www.unicaja.es",
    "wof:name":"Unicaja",
    "wof:placetype":"venue"
},
  "geometry": {"coordinates":[-6.2774348259,36.5193862915],"type":"Point"}
}