{
  "type": "Feature",
  "properties": {
    "addr:full":"Carrer de Gran De Gracia, 140 Barcelona Barcelona 08012",
    "addr:housenumber":"140",
    "addr:postcode":"08012",
    "addr:street":"Carrer De Gran De Gracia",
    "iso:country":"ES",
    "sg:address":"Carrer de Gran De Gracia, 140",
    "sg:city":"Barcelona",
    "sg:orig_category":"Cajas De Ahorro",
    "sg:phone":"+34 932 18 59 58",
    "sg:postcode":"08012",
    "sg:province":"Barcelona",
    "wof:name":"Caixa D'estalvis I Pensions De Barcelona",
    "wof:placetype":"venue"
},
  "geometry": {"coordinates":[2.1534359455,41.4017677307],"type":"Point"}
}