{
  "type": "Feature",
  "properties": {
    "iso:country":"ES",
    "sg:address":"Avda Espa\u00d1a (de), 3",
    "sg:city":"Alcobendas",
    "sg:orig_category":"Peluquer\u00cdas, Peluquer\u00cda Mixta",
    "sg:phone":"+34 916 54 89 89",
    "sg:postcode":"28100",
    "sg:province":"Madrid",
    "wof:name":"Diaz Orgaz Maria Teresa",
    "wof:placetype":"venue"
},
  "geometry": {"coordinates":[-3.6432020664,40.5452690125],"type":"Point"}
}