{
  "type": "Feature",
  "properties": {
    "addr:full":"Carr San Juan De Ribera, 8 Canals Valencia 46650",
    "addr:housenumber":"8",
    "addr:postcode":"46650",
    "addr:street":"Carr San;De Ribera",
    "iso:country":"ES",
    "sg:address":"Carr San Juan De Ribera, 8",
    "sg:city":"Canals",
    "sg:orig_category":"Fabricaci\u00d3n De Sobres, Bolsas Y Fundas",
    "sg:phone":"+34 962 23 90 80",
    "sg:postcode":"46650",
    "sg:province":"Valencia",
    "wof:name":"Comercial Etilux S L",
    "wof:placetype":"venue"
},
  "geometry": {"coordinates":[-0.5798370242,38.9618110657],"type":"Point"}
}