{
  "type": "Feature",
  "properties": {
    "addr:full":"Calle de Daoiz Y Velarde, 14 Lora Rio Sevilla 41440",
    "addr:housenumber":"14",
    "addr:postcode":"41440",
    "addr:street":"Calle De Daoiz Y Velarde;Rio Sevilla",
    "iso:country":"ES",
    "sg:address":"Calle de Daoiz Y Velarde, 14",
    "sg:city":"Lora Rio",
    "sg:orig_category":"Promotores Constructores",
    "sg:phone":"+34 955 80 32 76",
    "sg:postcode":"41440",
    "sg:province":"Sevilla",
    "wof:name":"Santana Infantes S.l",
    "wof:placetype":"venue"
},
  "geometry": {"coordinates":[-5.532845974,37.6589851379],"type":"Point"}
}