{
  "type": "Feature",
  "properties": {
    "iso:country":"ES",
    "sg:address":"Rua B, 43",
    "sg:city":"Lalin",
    "sg:orig_category":"Asociaciones Y Clubs Deportivos",
    "sg:phone":"+34 986 78 12 20",
    "sg:postcode":"36500",
    "sg:province":"Pontevedra",
    "wof:name":"Lopez Conde Maria Luz",
    "wof:placetype":"venue"
},
  "geometry": {"coordinates":[-8.1109790802,42.657169342],"type":"Point"}
}