{
  "type": "Feature",
  "properties": {
    "addr:full":"Av Joan Maragall, 28 Sant Pere De Torello Barcelona 08572",
    "addr:housenumber":"28",
    "addr:postcode":"08572",
    "addr:street":"Av Joan Maragall",
    "iso:country":"ES",
    "sg:address":"Av Joan Maragall, 28",
    "sg:city":"Sant Pere De Torello",
    "sg:orig_category":"Art\u00cdculos De Madera (fabricaci\u00d3n Y Al Por Mayor)",
    "sg:phone":"+34 938 58 40 33",
    "sg:postcode":"08572",
    "sg:province":"Barcelona",
    "wof:name":"Sistemes Can Serra S.l.",
    "wof:placetype":"venue"
},
  "geometry": {"coordinates":[2.2932679653,42.0742301941],"type":"Point"}
}