{
  "type": "Feature",
  "properties": {
    "addr:full":"Calle de Sancho Davila, 9 Madrid Madrid 28028",
    "addr:housenumber":"9",
    "addr:postcode":"madrid;28028",
    "addr:street":"Calle De Sancho Davila",
    "iso:country":"ES",
    "sg:address":"Calle de Sancho Davila, 9",
    "sg:city":"Madrid",
    "sg:orig_category":"Asociaciones Humanitarias, De Cooperaci\u00d3n, De Acci\u00d3n Social",
    "sg:phone":"+34 917 25 39 88",
    "sg:postcode":"28028",
    "sg:province":"Madrid",
    "wof:name":"Mujeres Alerta Por Sus Derechos",
    "wof:placetype":"venue"
},
  "geometry": {"coordinates":[-3.6618928909,40.4281845093],"type":"Point"}
}