{
  "type": "Feature",
  "properties": {
    "iso:country":"ES",
    "sg:address":"Calle de Cruz De La, 58",
    "sg:city":"Torremolinos",
    "sg:orig_category":"Electromedicina: Equipo",
    "sg:phone":"+34 952 38 57 76",
    "sg:postcode":"29620",
    "sg:province":"M\u00e1laga",
    "wof:name":"Gambro S.a.",
    "wof:placetype":"venue"
},
  "geometry": {"coordinates":[-4.4992752075,36.6312713623],"type":"Point"}
}