{
  "type": "Feature",
  "properties": {
    "addr:full":"Av Torre D'en Mateu, 46 Barbera Valles Barcelona 08210",
    "addr:housenumber":"46",
    "addr:postcode":"08210",
    "addr:street":"Av Torre D'En Mateu",
    "iso:country":"ES",
    "sg:address":"Av Torre D'en Mateu, 46",
    "sg:city":"Barbera Valles",
    "sg:orig_category":"Fabricaci\u00d3n De Moldes Y Modelos",
    "sg:phone":"+34 937 29 95 95",
    "sg:postcode":"08210",
    "sg:province":"Barcelona",
    "wof:name":"Herolse S.a.",
    "wof:placetype":"venue"
},
  "geometry": {"coordinates":[2.14696908,41.51039505],"type":"Point"}
}