{
  "type": "Feature",
  "properties": {
    "iso:country":"ES",
    "sg:address":"Central, 1",
    "sg:city":"Torremolinos",
    "sg:orig_category":"Inmobiliaria (agencias)",
    "sg:phone":"+34 952 38 41 80",
    "sg:postcode":"29620",
    "sg:province":"M\u00e1laga",
    "wof:name":"Delgado Gutierrez Manuel",
    "wof:placetype":"venue"
},
  "geometry": {"coordinates":[-4.5030088425,36.6106033325],"type":"Point"}
}