{
  "type": "Feature",
  "properties": {
    "addr:full":"Cno. Polvorosa, S/n Bola\u00f1os Calatrava Ciudad Real 13260",
    "addr:housenumber":"s / n",
    "addr:postcode":"13260",
    "addr:street":"Cno. Polvorosa",
    "iso:country":"ES",
    "sg:address":"Cno. Polvorosa, S/n",
    "sg:city":"Bola\u00f1os Calatrava",
    "sg:orig_category":"Animales (al Por Menor)",
    "sg:phone":"+34 926 87 28 54",
    "sg:postcode":"13260",
    "sg:province":"Ciudad Real",
    "wof:name":"Avicola Santa Maria S.l.",
    "wof:placetype":"venue"
},
  "geometry": {"coordinates":[-3.9272627831,38.9860954285],"type":"Point"}
}