{
  "type": "Feature",
  "properties": {
    "addr:full":"Calle de Literato Azorin, 14 Valencia Valencia 46006",
    "addr:housenumber":"14",
    "addr:postcode":"46006",
    "addr:street":"Calle De Literato Azorin",
    "iso:country":"ES",
    "sg:address":"Calle de Literato Azorin, 14",
    "sg:city":"Valencia",
    "sg:orig_category":"Inmobiliaria (agencias)",
    "sg:phone":"+34 963 41 05 55",
    "sg:postcode":"46006",
    "sg:province":"Valencia",
    "wof:name":"Promociones Y Construcciones Churruca 2000 S.l.",
    "wof:placetype":"venue"
},
  "geometry": {"coordinates":[-0.3740620017,39.460609436],"type":"Point"}
}