{
  "type": "Feature",
  "properties": {
    "iso:country":"ES",
    "sg:address":"Calle de Anunciacion, 1",
    "sg:city":"Madrid",
    "sg:orig_category":"Empresarios",
    "sg:phone":"+34 915 73 23 37",
    "sg:postcode":"28009",
    "sg:province":"Madrid",
    "wof:name":"Fundacion Educacion Marianista Domingo Lazaro",
    "wof:placetype":"venue"
},
  "geometry": {"coordinates":[-3.6759901047,40.4115028381],"type":"Point"}
}