{
  "type": "Feature",
  "properties": {
    "iso:country":"ES",
    "sg:address":"Calle de Cruz Del Sur, 3",
    "sg:city":"Madrid",
    "sg:orig_category":"Frutas, Legumbres Frescas Y Tempranas (al Por Menor)",
    "sg:phone":"+34 915 73 73 38",
    "sg:postcode":"28007",
    "sg:province":"Madrid",
    "wof:name":"Yubero Martin Manuel",
    "wof:placetype":"venue"
},
  "geometry": {"coordinates":[-3.6686830521,40.4105262756],"type":"Point"}
}