{
  "type": "Feature",
  "properties": {
    "addr:full":"Urb Fuentebella (de La), 10 Parla Madrid 28980",
    "addr:housenumber":"10",
    "addr:postcode":"28980",
    "addr:street":"Urb Fuentebella De La",
    "iso:country":"ES",
    "sg:address":"Urb Fuentebella (de La), 10",
    "sg:city":"Parla",
    "sg:orig_category":"Farmacias",
    "sg:phone":"+34 916 99 28 09",
    "sg:postcode":"28980",
    "sg:province":"Madrid",
    "wof:name":"Gomez Juan Isidoro",
    "wof:placetype":"venue"
},
  "geometry": {"coordinates":[-3.7728250027,40.2323112488],"type":"Point"}
}