{
  "type": "Feature",
  "properties": {
    "iso:country":"ES",
    "sg:address":"Calle de Fernando El Catolico, 50",
    "sg:city":"Madrid",
    "sg:orig_category":"Electricidad, Electr\u00d3nica: Suministros (al Por Menor)",
    "sg:phone":"+34 915 49 44 34",
    "sg:postcode":"28015",
    "sg:province":"Madrid",
    "wof:name":"Jimenez Jimenez Maria Magdalena",
    "wof:placetype":"venue"
},
  "geometry": {"coordinates":[-3.7127931118,40.4343681335],"type":"Point"}
}