{
  "type": "Feature",
  "properties": {
    "iso:country":"ES",
    "sg:address":"Avda Balneario, S/n",
    "sg:city":"Arteixo",
    "sg:orig_category":"Molduras, Junquillos, Listones Y Molduras Perforadas",
    "sg:phone":"+34 981 60 08 80",
    "sg:postcode":"15142",
    "sg:province":"La Coru\u00f1a",
    "wof:name":"Castro Casti\u00f1eiras Maria Ofelia",
    "wof:placetype":"venue"
},
  "geometry": {"coordinates":[-8.5061349869,43.3034248352],"type":"Point"}
}