{
  "type": "Feature",
  "properties": {
    "addr:full":"Calle de Correal (el), 2 Molina Segura Murcia 30500",
    "addr:housenumber":"2",
    "addr:postcode":"30500",
    "addr:street":"Calle De Correal El",
    "iso:country":"ES",
    "sg:address":"Calle de Correal (el), 2",
    "sg:city":"Molina Segura",
    "sg:orig_category":"Promotores Constructores",
    "sg:phone":"+34 968 64 09 53",
    "sg:postcode":"30500",
    "sg:province":"Murcia",
    "wof:name":"Vista Real Proyectos S.l.",
    "wof:placetype":"venue"
},
  "geometry": {"coordinates":[-1.216850996,38.0585441589],"type":"Point"}
}