{
  "type": "Feature",
  "properties": {
    "iso:country":"ES",
    "sg:address":"Calle de Perez Galdos, 31",
    "sg:city":"Talavera Real",
    "sg:orig_category":"Farmacias",
    "sg:phone":"+34 924 44 14 14",
    "sg:postcode":"06140",
    "sg:province":"Badajoz",
    "wof:name":"Alia Ramos Maria Filomena",
    "wof:placetype":"venue"
},
  "geometry": {"coordinates":[-6.769115448,38.8748779297],"type":"Point"}
}