{
  "type": "Feature",
  "properties": {
    "iso:country":"ES",
    "sg:address":"Plaz Santa Ana, 1",
    "sg:city":"Bujalance",
    "sg:orig_category":"Internados & Ense\u00d1anza Privada",
    "sg:phone":"+34 957 17 18 97",
    "sg:postcode":"14650",
    "sg:province":"C\u00f3rdoba",
    "wof:name":"Colegio La Milagrosa",
    "wof:placetype":"venue"
},
  "geometry": {"coordinates":[-4.380753994,37.895160675],"type":"Point"}
}