{
  "type": "Feature",
  "properties": {
    "addr:full":"Calle de Paseo Chico, 20 Fontiveros \u00c1vila 05310",
    "addr:housenumber":"20",
    "addr:postcode":"05310",
    "addr:street":"Calle De Paseo Chico;A\u0301Vila",
    "iso:country":"ES",
    "sg:address":"Calle de Paseo Chico, 20",
    "sg:city":"Fontiveros",
    "sg:orig_category":"Empresarios",
    "sg:phone":"+34 920 24 52 38",
    "sg:postcode":"05310",
    "sg:province":"\u00c1vila",
    "wof:name":"Calleja Garcia Victor",
    "wof:placetype":"venue"
},
  "geometry": {"coordinates":[-4.9613490105,40.9290504456],"type":"Point"}
}