{
  "type": "Feature",
  "properties": {
    "iso:country":"ES",
    "sg:address":"Calle de Barrio Nuevo, 3",
    "sg:city":"Aranda Duero",
    "sg:orig_category":"Zapater\u00cdas",
    "sg:phone":"+34 947 50 46 52",
    "sg:postcode":"09400",
    "sg:province":"Burgos",
    "wof:name":"Rodriguez Rodriguez Juan Carlos",
    "wof:placetype":"venue"
},
  "geometry": {"coordinates":[-3.6883962154,41.6715965271],"type":"Point"}
}