{
  "type": "Feature",
  "properties": {
    "addr:full":"Avda Santiago (de), 90 Ourense Ourense 32001",
    "addr:housenumber":"90",
    "addr:postcode":"32001",
    "addr:street":"Avda Santiago De",
    "iso:country":"ES",
    "sg:address":"Avda Santiago (de), 90",
    "sg:city":"Ourense",
    "sg:orig_category":"Muebles",
    "sg:phone":"+34 988 37 15 54",
    "sg:postcode":"32001",
    "sg:province":"Ourense",
    "wof:name":"Campo Vazquez Muebles S.l.l.",
    "wof:placetype":"venue"
},
  "geometry": {"coordinates":[-7.8650050163,42.3548355103],"type":"Point"}
}