{
  "type": "Feature",
  "properties": {
    "addr:full":"Calle de Gutierrez Solana, 6 Madrid Madrid 28036",
    "addr:housenumber":"6",
    "addr:postcode":"28036",
    "addr:street":"Calle De Gutierrez Solana",
    "iso:country":"ES",
    "sg:address":"Calle de Gutierrez Solana, 6",
    "sg:city":"Madrid",
    "sg:orig_category":"Empresarios",
    "sg:phone":"+34 915 15 93 76",
    "sg:postcode":"28036",
    "sg:province":"Madrid",
    "sg:website":"www.tambien.org",
    "wof:name":"Fundacion Tambien",
    "wof:placetype":"venue"
},
  "geometry": {"coordinates":[-3.688090086,40.45079422],"type":"Point"}
}