{
  "type": "Feature",
  "properties": {
    "iso:country":"ES",
    "sg:address":"Calle de Atrio De Santiago, 5",
    "sg:city":"Valladolid",
    "sg:orig_category":"Ropa Para Se\u00d1oras (al Por Menor)",
    "sg:phone":"+34 983 37 36 06",
    "sg:postcode":"47001",
    "sg:province":"Valladolid",
    "wof:name":"Gutierrez Saiz Jose Carlos",
    "wof:placetype":"venue"
},
  "geometry": {"coordinates":[-4.7292613983,41.6505966187],"type":"Point"}
}