{
  "type": "Feature",
  "properties": {
    "addr:full":"Avda Venezuela (de), 39 G\u00fcimar Santa Cruz De Tenerife 38500",
    "addr:housenumber":"39",
    "addr:postcode":"38500",
    "addr:street":"Avda Venezuela De",
    "iso:country":"ES",
    "sg:address":"Avda Venezuela (de), 39",
    "sg:city":"G\u00fcimar",
    "sg:orig_category":"Trajes Y Adornos De Boda (confecci\u00d3n, Al Por Menor)",
    "sg:phone":"+34 922 51 29 15",
    "sg:postcode":"38500",
    "sg:province":"Santa Cruz De Tenerife",
    "wof:name":"Gomez Cabrera Isabel",
    "wof:placetype":"venue"
},
  "geometry": {"coordinates":[-16.4099159241,28.3160915375],"type":"Point"}
}