{
  "type": "Feature",
  "properties": {
    "addr:full":"Arry Santo Domingo, 17 Salamanca Salamanca 37008",
    "addr:housenumber":"17",
    "addr:postcode":"37008",
    "addr:street":"Santo Domingo",
    "iso:country":"ES",
    "sg:address":"Arry Santo Domingo, 17",
    "sg:city":"Salamanca",
    "sg:orig_category":"Charcuter\u00cdas (al Por Mayor)",
    "sg:phone":"+34 923 26 84 28",
    "sg:postcode":"37008",
    "sg:province":"Salamanca",
    "wof:name":"Jamones Embutidos Hermanos Hoyos S.l.",
    "wof:placetype":"venue"
},
  "geometry": {"coordinates":[-5.6637592316,40.959438324],"type":"Point"}
}