{
  "type": "Feature",
  "properties": {
    "addr:full":"Av Madrid, 191 Barcelona Barcelona 08014",
    "addr:housenumber":"191",
    "addr:postcode":"08014",
    "addr:street":"Av Madrid",
    "iso:country":"ES",
    "sg:address":"Av Madrid, 191",
    "sg:city":"Barcelona",
    "sg:orig_category":"Peluquer\u00cdas, Peluquer\u00cda Mixta",
    "sg:phone":"+34 934 90 87 88",
    "sg:postcode":"08014",
    "sg:province":"Barcelona",
    "wof:name":"Fernandez Garate Luisa",
    "wof:placetype":"venue"
},
  "geometry": {"coordinates":[2.1336989403,41.3813018799],"type":"Point"}
}