{
  "type": "Feature",
  "properties": {
    "addr:full":"Via Europa, 86 Mataro Barcelona 08303",
    "addr:housenumber":"86",
    "addr:postcode":"08303",
    "addr:street":"Via Europa",
    "iso:country":"ES",
    "sg:address":"Via Europa, 86",
    "sg:city":"Mataro",
    "sg:orig_category":"Sociedades, Compa\u00d1\u00cdas Aseguradoras",
    "sg:phone":"+34 937 57 46 08",
    "sg:postcode":"08303",
    "sg:province":"Barcelona",
    "wof:name":"Seguros Catalana Occidente Sa De Seguros Y Reaseguros",
    "wof:placetype":"venue"
},
  "geometry": {"coordinates":[2.4327349663,41.5437049866],"type":"Point"}
}