{
  "type": "Feature",
  "properties": {
    "iso:country":"ES",
    "sg:address":"Rbla Passeig, 8",
    "sg:city":"Vic",
    "sg:orig_category":"Laboratorios Y Trabajos De Fotograf\u00cda, V\u00cddeo Y Cine",
    "sg:phone":"+34 938 86 31 86",
    "sg:postcode":"08500",
    "sg:province":"Barcelona",
    "wof:name":"Jimenez Bach Francesc",
    "wof:placetype":"venue"
},
  "geometry": {"coordinates":[2.2556419373,41.9305458069],"type":"Point"}
}