{
  "type": "Feature",
  "properties": {
    "iso:country":"ES",
    "sg:address":"Carrer de Arquimedes, 122",
    "sg:city":"Terrassa",
    "sg:orig_category":"Fisioterapia",
    "sg:phone":"+34 937 33 04 42",
    "sg:postcode":"08224",
    "sg:province":"Barcelona",
    "wof:name":"Borras Cima Jordi",
    "wof:placetype":"venue"
},
  "geometry": {"coordinates":[2.0065209866,41.5597991943],"type":"Point"}
}