{
  "type": "Feature",
  "properties": {
    "addr:full":"Carr Ferrocarril D'alcoi, 110 Gandia Valencia 46700",
    "addr:housenumber":"110",
    "addr:postcode":"46700",
    "addr:street":"Carr Ferrocarril D'Alcoi;Valencia",
    "iso:country":"ES",
    "sg:address":"Carr Ferrocarril D'alcoi, 110",
    "sg:city":"Gandia",
    "sg:orig_category":"Sociedades, Compa\u00d1\u00cdas Aseguradoras",
    "sg:phone":"+34 962 87 13 53",
    "sg:postcode":"46700",
    "sg:province":"Valencia",
    "wof:name":"Domenech Loizaga Joan Ramon",
    "wof:placetype":"venue"
},
  "geometry": {"coordinates":[-0.1832838058,38.9725341797],"type":"Point"}
}