{
  "type": "Feature",
  "properties": {
    "addr:full":"Calle de Pedro Antonio De Alarcon, 71 Granada Granada 18003",
    "addr:housenumber":"71",
    "addr:postcode":"18003",
    "addr:street":"Calle De Pedro Antonio De Alarcon",
    "iso:country":"ES",
    "sg:address":"Calle de Pedro Antonio De Alarcon, 71",
    "sg:city":"Granada",
    "sg:orig_category":"Carnicer\u00cdas, Carnicer\u00cdas",
    "sg:phone":"+34 958 28 13 99",
    "sg:postcode":"18003",
    "sg:province":"Granada",
    "wof:name":"Lopez Puertas Antonio",
    "wof:placetype":"venue"
},
  "geometry": {"coordinates":[-3.6081690788,37.175579071],"type":"Point"}
}