{
  "type": "Feature",
  "properties": {
    "iso:country":"ES",
    "sg:address":"Calle de Agua, 17",
    "sg:city":"Alcubillas",
    "sg:orig_category":"Agencias Y Agentes Comerciales, Representantes",
    "sg:phone":"+34 926 35 62 20",
    "sg:postcode":"13391",
    "sg:province":"Ciudad Real",
    "wof:name":"Gonzalez Alvarez Tomas",
    "wof:placetype":"venue"
},
  "geometry": {"coordinates":[-3.1335222721,38.7524757385],"type":"Point"}
}