{
  "type": "Feature",
  "properties": {
    "iso:country":"ES",
    "sg:address":"Plaz Poeta Iglesias, 13",
    "sg:city":"Salamanca",
    "sg:orig_category":"Perfumer\u00cda (al Por Menor)",
    "sg:phone":"+34 923 21 62 68",
    "sg:postcode":"37001",
    "sg:province":"Salamanca",
    "wof:name":"Gomez Borrego Jeronimo",
    "wof:placetype":"venue"
},
  "geometry": {"coordinates":[-5.6639251709,40.9641265869],"type":"Point"}
}