{
  "type": "Feature",
  "properties": {
    "addr:full":"Avda Ribera La, 11 Puerto Valencia 46520",
    "addr:housenumber":"11",
    "addr:postcode":"46520",
    "addr:street":"Avda Ribera La",
    "iso:country":"ES",
    "sg:address":"Avda Ribera La, 11",
    "sg:city":"Puerto",
    "sg:orig_category":"Instalaci\u00d3n, Reparaci\u00d3n De Ascensores Y Montacargas",
    "sg:phone":"+34 962 67 10 80",
    "sg:postcode":"46520",
    "sg:province":"Valencia",
    "wof:name":"Zardoya Otis S.a.",
    "wof:placetype":"venue"
},
  "geometry": {"coordinates":[-0.2298990935,39.6666870117],"type":"Point"}
}