{
  "type": "Feature",
  "properties": {
    "iso:country":"ES",
    "sg:address":"Calle de Mejico, 1",
    "sg:city":"Coria Rio",
    "sg:orig_category":"Arquitectos",
    "sg:phone":"+34 954 77 31 45",
    "sg:postcode":"41100",
    "sg:province":"Sevilla",
    "wof:name":"Gonzalez Navarro Andres",
    "wof:placetype":"venue"
},
  "geometry": {"coordinates":[-6.0519790649,37.2871856689],"type":"Point"}
}