{
  "type": "Feature",
  "properties": {
    "iso:country":"ES",
    "sg:address":"Plaz Universidad (de La), 1",
    "sg:city":"Granada",
    "sg:orig_category":"Ropa Para Se\u00d1oras (al Por Menor)",
    "sg:phone":"+34 958 80 05 68",
    "sg:postcode":"18001",
    "sg:province":"Granada",
    "wof:name":"Reichenbach  Petra",
    "wof:placetype":"venue"
},
  "geometry": {"coordinates":[-3.6016340256,37.1783218384],"type":"Point"}
}