{
  "type": "Feature",
  "properties": {
    "addr:full":"Ctra Lerin, 8 Larraga Navarra 31251",
    "addr:housenumber":"8",
    "addr:postcode":"31251",
    "addr:street":"Ctra Lerin",
    "iso:country":"ES",
    "sg:address":"Ctra Lerin, 8",
    "sg:city":"Larraga",
    "sg:orig_category":"Construcciones E Instalaciones Agr\u00cdcolas",
    "sg:phone":"+34 948 71 10 38",
    "sg:postcode":"31251",
    "sg:province":"Navarra",
    "wof:name":"Macua Suescun Angel",
    "wof:placetype":"venue"
},
  "geometry": {"coordinates":[-1.8541070223,42.5530471802],"type":"Point"}
}