{
  "type": "Feature",
  "properties": {
    "iso:country":"ES",
    "sg:address":"Avda Hermanos Granda, 43",
    "sg:city":"Madrid",
    "sg:orig_category":"Papeler\u00cdas: Art\u00cdculos (al Por Mayor)",
    "sg:phone":"+34 917 48 29 30",
    "sg:postcode":"28022",
    "sg:province":"Madrid",
    "wof:name":"Novaline Plus Iberica S.a.",
    "wof:placetype":"venue"
},
  "geometry": {"coordinates":[-3.5608589649,40.4452781677],"type":"Point"}
}