{
  "type": "Feature",
  "properties": {
    "addr:full":"Calle de Geltoki Kalea, 1 Tolosa Guip\u00f9zcoa 20400",
    "addr:housenumber":"1",
    "addr:postcode":"20400",
    "addr:street":"Calle De Geltoki Kalea;Guipu\u0300Zcoa",
    "iso:country":"ES",
    "sg:address":"Calle de Geltoki Kalea, 1",
    "sg:city":"Tolosa",
    "sg:orig_category":"Centros M\u00c9dicos Y Sociales, Dispensarios",
    "sg:phone":"+34 943 11 85 47",
    "sg:postcode":"20400",
    "sg:province":"Guip\u00f9zcoa",
    "wof:name":"Ioana Arbillaga Plazaola (clinica Podologica)",
    "wof:placetype":"venue"
},
  "geometry": {"coordinates":[-2.0775949955,43.1350326538],"type":"Point"}
}