{
  "type": "Feature",
  "properties": {
    "iso:country":"ES",
    "sg:address":"Carrer de Major, 6",
    "sg:city":"Vendrell",
    "sg:orig_category":"Radiocomunicaciones, Telefon\u00cda M\u00d3vil, Radiomensajer\u00cda: Servicios, Comercializaci\u00d3n",
    "sg:phone":"+34 977 15 70 60",
    "sg:postcode":"43700",
    "sg:province":"Tarragona",
    "wof:name":"Parlofon S L",
    "wof:placetype":"venue"
},
  "geometry": {"coordinates":[1.5344280005,41.2203826904],"type":"Point"}
}