{
  "type": "Feature",
  "properties": {
    "iso:country":"ES",
    "sg:address":"Calle de San Roque, 26",
    "sg:city":"Ibi",
    "sg:orig_category":"Droguer\u00cdas (al Por Menor)",
    "sg:phone":"+34 965 55 33 01",
    "sg:postcode":"03440",
    "sg:province":"Alicante",
    "wof:name":"Dura Seva Trinitario",
    "wof:placetype":"venue"
},
  "geometry": {"coordinates":[-0.5763670206,38.6242103577],"type":"Point"}
}