{
  "type": "Feature",
  "properties": {
    "iso:country":"ES",
    "sg:address":"Pl Orson Welles, 5",
    "sg:city":"Palma",
    "sg:orig_category":"Cl\u00cdnicas Dentales",
    "sg:phone":"+34 971 24 51 00",
    "sg:postcode":"07008",
    "sg:province":"Islas Baleares",
    "wof:name":"Optident S.l.",
    "wof:placetype":"venue"
},
  "geometry": {"coordinates":[2.6706399918,39.5799026489],"type":"Point"}
}