{
  "type": "Feature",
  "properties": {
    "addr:full":"Ctra Madrid-cadiz, Km. 0176,7 Manzanares Ciudad Real 13200",
    "addr:postcode":"13200",
    "addr:street":"Ctra Madrid-Cadiz Km. 0176,7",
    "iso:country":"ES",
    "sg:address":"Ctra Madrid-cadiz, Km. 0176,7",
    "sg:city":"Manzanares",
    "sg:orig_category":"Reciclaje, Desguace De Veh\u00cdculos",
    "sg:phone":"+34 926 61 17 32",
    "sg:postcode":"13200",
    "sg:province":"Ciudad Real",
    "wof:name":"Desmansa S.l.",
    "wof:placetype":"venue"
},
  "geometry": {"coordinates":[-3.373128891,38.994140625],"type":"Point"}
}