{
  "type": "Feature",
  "properties": {
    "addr:full":"Grup Mugarra Auzunea, 1 Durango Vizcaya 48200",
    "addr:housenumber":"1",
    "addr:postcode":"48200",
    "addr:street":"Mugarra Auzunea",
    "iso:country":"ES",
    "sg:address":"Grup Mugarra Auzunea, 1",
    "sg:city":"Durango",
    "sg:orig_category":"Supermercados Y Hipermercados",
    "sg:phone":"+34 946 81 70 98",
    "sg:postcode":"48200",
    "sg:province":"Vizcaya",
    "wof:name":"Karim Iossaidene",
    "wof:placetype":"venue"
},
  "geometry": {"coordinates":[-2.6303210258,43.1630783081],"type":"Point"}
}