{
  "type": "Feature",
  "properties": {
    "iso:country":"ES",
    "sg:address":"Calle de Catalina Gibaja, 3",
    "sg:city":"Ortuella",
    "sg:orig_category":"Estancos",
    "sg:phone":"+34 946 64 02 55",
    "sg:postcode":"48530",
    "sg:province":"Vizcaya",
    "wof:name":"Bienvenida Garcia",
    "wof:placetype":"venue"
},
  "geometry": {"coordinates":[-3.0541379452,43.3094139099],"type":"Point"}
}