{
  "type": "Feature",
  "properties": {
    "iso:country":"ES",
    "sg:address":"Calle de Pardies, 2",
    "sg:city":"Candas",
    "sg:orig_category":"Reposter\u00cdas",
    "sg:phone":"+34 985 88 51 67",
    "sg:postcode":"33430",
    "sg:province":"Asturias",
    "wof:name":"Panaderia Mu\u00f1iz S.l.",
    "wof:placetype":"venue"
},
  "geometry": {"coordinates":[-5.767592907,43.5910758972],"type":"Point"}
}