{
  "type": "Feature",
  "properties": {
    "iso:country":"ES",
    "sg:address":"Calle de Teruel, 6",
    "sg:city":"Cordoba",
    "sg:orig_category":"Arquitectos",
    "sg:phone":"+34 957 27 54 66",
    "sg:postcode":"14012",
    "sg:province":"C\u00f3rdoba",
    "wof:name":"Meseguer Boldu Francisco",
    "wof:placetype":"venue"
},
  "geometry": {"coordinates":[-4.7838850021,37.9000968933],"type":"Point"}
}