{
  "type": "Feature",
  "properties": {
    "iso:country":"ES",
    "sg:address":"Kale Nagusia, 25",
    "sg:city":"Astigarraga",
    "sg:orig_category":"Mercer\u00cda, Lencer\u00cda (al Por Menor)",
    "sg:phone":"+34 943 55 13 66",
    "sg:postcode":"20115",
    "sg:province":"Guip\u00f9zcoa",
    "wof:name":"Isasti Zabalegui Maria Rosario",
    "wof:placetype":"venue"
},
  "geometry": {"coordinates":[-1.9456424713,43.2813034058],"type":"Point"}
}