{
  "type": "Feature",
  "properties": {
    "addr:full":"Avda Alf.provisionales, S/n Playa Del Ingles Las Palmas 35100",
    "addr:housenumber":"s / n",
    "addr:postcode":"35100",
    "addr:street":"Avda Alf.Provisionales",
    "iso:country":"ES",
    "sg:address":"Avda Alf.provisionales, S/n",
    "sg:city":"Playa Del Ingles",
    "sg:orig_category":"Deportes Diversos",
    "sg:phone":"+34 928 76 77 46",
    "sg:postcode":"35100",
    "sg:province":"Las Palmas",
    "wof:name":"Fresno Fresno Victor",
    "wof:placetype":"venue"
},
  "geometry": {"coordinates":[-15.5756196976,27.759519577],"type":"Point"}
}