{
  "type": "Feature",
  "properties": {
    "iso:country":"ES",
    "sg:address":"Calle de Surinam, S/n",
    "sg:city":"Torremolinos",
    "sg:orig_category":"Inform\u00c1tica: Material Y Suministros",
    "sg:phone":"+34 952 37 58 62",
    "sg:postcode":"29620",
    "sg:province":"M\u00e1laga",
    "wof:name":"Infordes S.l.",
    "wof:placetype":"venue"
},
  "geometry": {"coordinates":[-4.5127339363,36.6064987183],"type":"Point"}
}