{
  "type": "Feature",
  "properties": {
    "addr:full":"Calle de Evangelista, 44 Sevilla Sevilla 41010",
    "addr:housenumber":"44",
    "addr:postcode":"41010",
    "addr:street":"Calle De Evangelista",
    "iso:country":"ES",
    "sg:address":"Calle de Evangelista, 44",
    "sg:city":"Sevilla",
    "sg:orig_category":"Peluquer\u00cdas, Peluquer\u00cda Mixta",
    "sg:phone":"+34 954 33 30 77",
    "sg:postcode":"41010",
    "sg:province":"Sevilla",
    "wof:name":"Roylos S.l.",
    "wof:placetype":"venue"
},
  "geometry": {"coordinates":[-6.005461216,37.380897522],"type":"Point"}
}