{
  "type": "Feature",
  "properties": {
    "iso:country":"ES",
    "sg:address":"Calle de Pedro Arias, 26",
    "sg:city":"Socuellamos",
    "sg:orig_category":"Colocaci\u00d3n, Mantenimiento, Vitrificaci\u00d3n De Parquets",
    "sg:phone":"+34 926 53 27 58",
    "sg:postcode":"13630",
    "sg:province":"Ciudad Real",
    "wof:name":"Jmd Pintores Y Decoradores S.l.u.",
    "wof:placetype":"venue"
},
  "geometry": {"coordinates":[-2.7926390171,39.2893371582],"type":"Point"}
}