{
  "type": "Feature",
  "properties": {
    "addr:full":"Avda General, 29 Madrid Madrid 28042",
    "addr:housenumber":"29",
    "addr:postcode":"madrid;28042",
    "addr:street":"Avda General",
    "iso:country":"ES",
    "sg:address":"Avda General, 29",
    "sg:city":"Madrid",
    "sg:orig_category":"Artes Gr\u00c1ficas, Artes Pl\u00c1sticas (curso)",
    "sg:phone":"+34 917 47 37 69",
    "sg:postcode":"28042",
    "sg:province":"Madrid",
    "wof:name":"Ortiz Marcos Venancio",
    "wof:placetype":"venue"
},
  "geometry": {"coordinates":[-3.5795009136,40.4713973999],"type":"Point"}
}