{
  "type": "Feature",
  "properties": {
    "addr:full":"Calle de Honorio Lozano, 33 Estacion Madrid 28400",
    "addr:housenumber":"33",
    "addr:postcode":"28400",
    "addr:street":"Calle De Honorio Lozano",
    "iso:country":"ES",
    "sg:address":"Calle de Honorio Lozano, 33",
    "sg:city":"Estacion",
    "sg:orig_category":"Art\u00cdculos De Decoraci\u00d3n",
    "sg:phone":"+34 918 51 48 81",
    "sg:postcode":"28400",
    "sg:province":"Madrid",
    "sg:website":"www.ka-international.com",
    "wof:name":"Prieto Cruz Gloria",
    "wof:placetype":"venue"
},
  "geometry": {"coordinates":[-3.7003455162,40.4166908264],"type":"Point"}
}