{
  "type": "Feature",
  "properties": {
    "iso:country":"ES",
    "sg:address":"Calle de Antonia Diaz, 27",
    "sg:city":"Dos Hermanas",
    "sg:orig_category":"Servicios Gsm",
    "sg:phone":"+34 955 66 98 39",
    "sg:postcode":"41700",
    "sg:province":"Sevilla",
    "wof:name":"Psjm Screen Technics S.l.",
    "wof:placetype":"venue"
},
  "geometry": {"coordinates":[-5.9226155281,37.2824707031],"type":"Point"}
}