{
  "type": "Feature",
  "properties": {
    "iso:country":"ES",
    "sg:address":"Calle de San Pedro, 2",
    "sg:city":"Portugalete",
    "sg:orig_category":"Caf\u00c9s, Bares, Cervecer\u00cdas",
    "sg:phone":"+34 944 62 27 13",
    "sg:postcode":"48920",
    "sg:province":"Vizcaya",
    "wof:name":"Pulleiro Penas Andres",
    "wof:placetype":"venue"
},
  "geometry": {"coordinates":[-3.0226299763,43.317035675],"type":"Point"}
}