{
  "type": "Feature",
  "properties": {
    "iso:country":"ES",
    "sg:address":"Carrer de Advocat Cirera, 21",
    "sg:city":"Sabadell",
    "sg:orig_category":"Restaurantes",
    "sg:phone":"+34 937 27 03 07",
    "sg:postcode":"08201",
    "sg:province":"Barcelona",
    "wof:name":"Girbau I Torras Restauracio S.l.",
    "wof:placetype":"venue"
},
  "geometry": {"coordinates":[2.1071600914,41.5457344055],"type":"Point"}
}