{
  "type": "Feature",
  "properties": {
    "iso:country":"ES",
    "sg:address":"Avda Miguel Hernandez, 15",
    "sg:city":"Alaquas",
    "sg:orig_category":"Zapatos (al Por Menor)",
    "sg:phone":"+34 961 50 96 18",
    "sg:postcode":"46970",
    "sg:province":"Valencia",
    "wof:name":"Gonzalez Laosa Andres",
    "wof:placetype":"venue"
},
  "geometry": {"coordinates":[-0.4547770023,39.4581794739],"type":"Point"}
}