{
  "type": "Feature",
  "properties": {
    "addr:full":"Paraje De San Babil, S/n Esparza De Galar Navarra 31191",
    "addr:housenumber":"s / n",
    "addr:postcode":"31191",
    "addr:street":"Paraje De San Babil",
    "iso:country":"ES",
    "sg:address":"Paraje De San Babil, S/n",
    "sg:city":"Esparza De Galar",
    "sg:orig_category":"Refiner\u00cdas De Petr\u00d3leo",
    "sg:phone":"+34 948 31 70 63",
    "sg:postcode":"31191",
    "sg:province":"Navarra",
    "wof:name":"Compa\u00d1ia Logistica De Hidrocarburos Clh S.a.",
    "wof:placetype":"venue"
},
  "geometry": {"coordinates":[-1.6567909718,42.7743148804],"type":"Point"}
}