{
  "type": "Feature",
  "properties": {
    "iso:country":"ES",
    "sg:address":"Avda Valdelasfuentes (de), 30",
    "sg:city":"San Sebastian De Los Reyes",
    "sg:orig_category":"Carnicer\u00cdas, Carnicer\u00cdas",
    "sg:phone":"+34 916 52 81 93",
    "sg:postcode":"28700",
    "sg:province":"Madrid",
    "wof:name":"Jimenez Gutierrez Jesus",
    "wof:placetype":"venue"
},
  "geometry": {"coordinates":[-3.6328759193,40.5519142151],"type":"Point"}
}