{
  "type": "Feature",
  "properties": {
    "iso:country":"ES",
    "sg:address":"Calle de Fabero, 47",
    "sg:city":"Fuenlabrada",
    "sg:orig_category":"Serigraf\u00cda (material Y Suministros)",
    "sg:phone":"+34 916 42 29 04",
    "sg:postcode":"28947",
    "sg:province":"Madrid",
    "wof:name":"Fernandez Miranda S.a.",
    "wof:placetype":"venue"
},
  "geometry": {"coordinates":[-3.7518823147,40.2645683289],"type":"Point"}
}