{
  "type": "Feature",
  "properties": {
    "iso:country":"ES",
    "sg:address":"Carrer de Sant Joan D'en Coll, 22",
    "sg:city":"Manresa",
    "sg:orig_category":"Carnicer\u00cdas, Carnicer\u00cdas",
    "sg:phone":"+34 938 74 05 07",
    "sg:postcode":"08243",
    "sg:province":"Barcelona",
    "wof:name":"Vilaseca Catot Francisco",
    "wof:placetype":"venue"
},
  "geometry": {"coordinates":[1.8391100168,41.7207107544],"type":"Point"}
}