{
  "type": "Feature",
  "properties": {
    "addr:full":"Avda Ifach, De, S/n Calpe Alicante 03710",
    "addr:housenumber":"/ n",
    "addr:postcode":"03710",
    "addr:street":"Avda Ifach De S",
    "iso:country":"ES",
    "sg:address":"Avda Ifach, De, S/n",
    "sg:city":"Calpe",
    "sg:orig_category":"Restaurantes",
    "sg:phone":"+34 965 83 57 72",
    "sg:postcode":"03710",
    "sg:province":"Alicante",
    "wof:name":"Medina Sanchez Tomas",
    "wof:placetype":"venue"
},
  "geometry": {"coordinates":[0.0448749997,38.6455307007],"type":"Point"}
}