{
  "type": "Feature",
  "properties": {
    "addr:full":"Calle de Italia, 39 Palencia Palencia 34004",
    "addr:housenumber":"39",
    "addr:postcode":"34004",
    "addr:street":"Calle De Italia",
    "iso:country":"ES",
    "sg:address":"Calle de Italia, 39",
    "sg:city":"Palencia",
    "sg:orig_category":"Material Y Herramientas Agr\u00cdcolas",
    "sg:phone":"+34 979 16 01 81",
    "sg:postcode":"34004",
    "sg:province":"Palencia",
    "wof:name":"Kverneland Group Iberica S.a.",
    "wof:placetype":"venue"
},
  "geometry": {"coordinates":[-4.511838913,42.0029029846],"type":"Point"}
}