{
  "type": "Feature",
  "properties": {
    "iso:country":"ES",
    "sg:address":"Calle de Euskalerria, 8",
    "sg:city":"Zaldibar",
    "sg:orig_category":"Plomeros",
    "sg:phone":"+34 946 82 70 82",
    "sg:postcode":"48250",
    "sg:province":"Vizcaya",
    "wof:name":"Ortuzar Arriaga Valentin",
    "wof:placetype":"venue"
},
  "geometry": {"coordinates":[-2.546736002,43.1703109741],"type":"Point"}
}