{
  "type": "Feature",
  "properties": {
    "iso:country":"ES",
    "sg:address":"Poli Mugitegi-a, 27",
    "sg:city":"Urretxu",
    "sg:orig_category":"Comercio De Piezas De Recambio Y De Accesorios De Veh\u00cdculos, Veh\u00cdculos Industriales",
    "sg:phone":"+34 943 72 58 64",
    "sg:postcode":"20700",
    "sg:province":"Guip\u00f9zcoa",
    "wof:name":"Bertan Sociedad Cooperativa",
    "wof:placetype":"venue"
},
  "geometry": {"coordinates":[-2.3134770393,43.086730957],"type":"Point"}
}