{
  "type": "Feature",
  "properties": {
    "addr:full":"Av Tarragona, 7 Malgrat Mar Barcelona 08380",
    "addr:housenumber":"7",
    "addr:postcode":"08380",
    "addr:street":"Av Tarragona",
    "iso:country":"ES",
    "sg:address":"Av Tarragona, 7",
    "sg:city":"Malgrat Mar",
    "sg:orig_category":"Carnicer\u00cdas, Carnicer\u00cdas",
    "sg:phone":"+34 937 65 52 48",
    "sg:postcode":"08380",
    "sg:province":"Barcelona",
    "wof:name":"Persoja S.l.",
    "wof:placetype":"venue"
},
  "geometry": {"coordinates":[2.7355298996,41.6446113586],"type":"Point"}
}