{
  "type": "Feature",
  "properties": {
    "iso:country":"ES",
    "sg:address":"Rua Padron (de), S/n",
    "sg:city":"Santiago De Compostela",
    "sg:orig_category":"Alimentaci\u00d3n General (al Por Menor)",
    "sg:phone":"+34 981 59 14 48",
    "sg:postcode":"15702",
    "sg:province":"La Coru\u00f1a",
    "wof:name":"Aldea Velasco Jacinto",
    "wof:placetype":"venue"
},
  "geometry": {"coordinates":[-8.544254303,42.8671798706],"type":"Point"}
}