{
  "type": "Feature",
  "properties": {
    "addr:full":"Calle de Elexalde, 37 Elexalde Vizcaya 48140",
    "addr:housenumber":"37",
    "addr:postcode":"48140",
    "addr:street":"Calle De Elexalde",
    "iso:country":"ES",
    "sg:address":"Calle de Elexalde, 37",
    "sg:city":"Elexalde",
    "sg:orig_category":"Bancos",
    "sg:phone":"+34 946 31 50 18",
    "sg:postcode":"48140",
    "sg:province":"Vizcaya",
    "wof:name":"Banco Guipuzcoano S.a.",
    "wof:placetype":"venue"
},
  "geometry": {"coordinates":[-2.7812309265,43.1626434326],"type":"Point"}
}