{
  "type": "Feature",
  "properties": {
    "iso:country":"ES",
    "sg:address":"Calle de Llano De Palacio, 7",
    "sg:city":"Montilla",
    "sg:orig_category":"Fabricaci\u00d3n De Telas Y Sedas",
    "sg:phone":"+34 957 65 68 93",
    "sg:postcode":"14550",
    "sg:province":"C\u00f3rdoba",
    "wof:name":"Rioma S.a.",
    "wof:placetype":"venue"
},
  "geometry": {"coordinates":[-4.6404590607,37.58177948],"type":"Point"}
}