{
  "type": "Feature",
  "properties": {
    "addr:full":"Plaz Constitucion, 4 Torredonjimeno Ja\u00e9n 23650",
    "addr:housenumber":"4",
    "addr:postcode":"23650",
    "addr:street":"Constitucion",
    "iso:country":"ES",
    "sg:address":"Plaz Constitucion, 4",
    "sg:city":"Torredonjimeno",
    "sg:orig_category":"Cajas De Ahorro",
    "sg:phone":"+34 953 57 12 50",
    "sg:postcode":"23650",
    "sg:province":"Ja\u00e9n",
    "wof:name":"Caja De Ahorros Y Monte De Piedad De Cordoba",
    "wof:placetype":"venue"
},
  "geometry": {"coordinates":[-3.9586589336,37.766166687],"type":"Point"}
}