{
  "type": "Feature",
  "properties": {
    "iso:country":"ES",
    "sg:address":"Ctra Cartagena, 41",
    "sg:city":"Torre-pacheco",
    "sg:orig_category":"Asesor\u00cda De Formaci\u00d3n Y Gesti\u00d3n De Personal",
    "sg:phone":"+34 968 57 94 26",
    "sg:postcode":"30700",
    "sg:province":"Murcia",
    "wof:name":"Nu\u00f1ez Martin Antonio Javier",
    "wof:placetype":"venue"
},
  "geometry": {"coordinates":[-1.1318800449,37.9795188904],"type":"Point"}
}