{
  "type": "Feature",
  "properties": {
    "iso:country":"ES",
    "sg:address":"Carrer de Muntaner, 320",
    "sg:city":"Barcelona",
    "sg:orig_category":"Art\u00cdculos De Decoraci\u00d3n",
    "sg:phone":"+34 934 14 46 17",
    "sg:postcode":"08021",
    "sg:province":"Barcelona",
    "sg:website":"www.vtv.es",
    "wof:name":"Vtv Muebles Y Complementos S.l.",
    "wof:placetype":"venue"
},
  "geometry": {"coordinates":[2.1454529762,41.3972053528],"type":"Point"}
}