{
  "type": "Feature",
  "properties": {
    "iso:country":"ES",
    "sg:address":"Carrer de Abat Porta, 23",
    "sg:city":"Reus",
    "sg:orig_category":"Delegados, Agentes De Tr\u00c1nsito, Auxiliares De Transporte Internacional",
    "sg:phone":"+34 977 75 42 96",
    "sg:postcode":"43205",
    "sg:province":"Tarragona",
    "wof:name":"Gonzalez Guirado Jose Ramon",
    "wof:placetype":"venue"
},
  "geometry": {"coordinates":[1.1137959957,41.1384315491],"type":"Point"}
}