{
  "type": "Feature",
  "properties": {
    "addr:full":"Plaz Hauries, 2 Jerez De La Frontera C\u00e1diz 11405",
    "addr:housenumber":"2",
    "addr:postcode":"11405",
    "addr:street":"Plaz Hauries",
    "iso:country":"ES",
    "sg:address":"Plaz Hauries, 2",
    "sg:city":"Jerez De La Frontera",
    "sg:orig_category":"Peritos En Seguros",
    "sg:phone":"+34 956 30 56 13",
    "sg:postcode":"11405",
    "sg:province":"C\u00e1diz",
    "wof:name":"Bufete Cosano Y Asociados,sl",
    "wof:placetype":"venue"
},
  "geometry": {"coordinates":[-6.1288719177,36.6946563721],"type":"Point"}
}