{
  "type": "Feature",
  "properties": {
    "iso:country":"ES",
    "sg:address":"Avda Camilo Alonso Vega, 1",
    "sg:city":"Santander",
    "sg:orig_category":"Ropa De Hogar (al Por Menor)",
    "sg:phone":"+34 942 34 51 97",
    "sg:postcode":"39007",
    "sg:province":"Cantabria",
    "wof:name":"Rodriguez Vargas Faustino",
    "wof:placetype":"venue"
},
  "geometry": {"coordinates":[-3.8265318871,43.4587364197],"type":"Point"}
}