{
  "type": "Feature",
  "properties": {
    "addr:full":"Plaz Cartaya, 3 Madrid Madrid 28024",
    "addr:housenumber":"3",
    "addr:postcode":"madrid;28024",
    "iso:country":"ES",
    "sg:address":"Plaz Cartaya, 3",
    "sg:city":"Madrid",
    "sg:orig_category":"Estudios, Instalaci\u00d3n De Climatizaci\u00d3n",
    "sg:phone":"+34 917 11 66 41",
    "sg:postcode":"28024",
    "sg:province":"Madrid",
    "wof:name":"Calderas Autonomas S.coop Ltda",
    "wof:placetype":"venue"
},
  "geometry": {"coordinates":[-3.7709479332,40.3962478638],"type":"Point"}
}