{
  "type": "Feature",
  "properties": {
    "addr:full":"Carrer de Miquel Angel, 107 Barcelona Barcelona 08028",
    "addr:housenumber":"107",
    "addr:postcode":"08028",
    "addr:street":"Carrer De Miquel Angel",
    "iso:country":"ES",
    "sg:address":"Carrer de Miquel Angel, 107",
    "sg:city":"Barcelona",
    "sg:orig_category":"Prendas Y Chalecos De Punto (al Por Menor)",
    "sg:phone":"+34 934 90 79 62",
    "sg:postcode":"08028",
    "sg:province":"Barcelona",
    "wof:name":"Cortes Sanchez Fernando",
    "wof:placetype":"venue"
},
  "geometry": {"coordinates":[2.1292979717,41.3766708374],"type":"Point"}
}