{
  "type": "Feature",
  "properties": {
    "iso:country":"ES",
    "sg:address":"Ctra Vic, 277",
    "sg:city":"Manresa",
    "sg:orig_category":"Grabados",
    "sg:phone":"+34 938 77 31 01",
    "sg:postcode":"08243",
    "sg:province":"Barcelona",
    "wof:name":"Retols Visual S.l",
    "wof:placetype":"venue"
},
  "geometry": {"coordinates":[1.8445689678,41.7363090515],"type":"Point"}
}