{
  "type": "Feature",
  "properties": {
    "iso:country":"ES",
    "sg:address":"Calle de Caridad, 107",
    "sg:city":"Estepona",
    "sg:orig_category":"Inmobiliaria (agencias)",
    "sg:phone":"+34 952 80 68 47",
    "sg:postcode":"29680",
    "sg:province":"M\u00e1laga",
    "wof:name":"Bazan Pe\u00f1a S.l.",
    "wof:placetype":"venue"
},
  "geometry": {"coordinates":[-5.1435089111,36.4263496399],"type":"Point"}
}