{
  "type": "Feature",
  "properties": {
    "iso:country":"ES",
    "sg:address":"Ctra Catral, Km. 0003,5",
    "sg:city":"San Jose",
    "sg:orig_category":"Delegados, Agentes De Tr\u00c1nsito, Auxiliares De Transporte Internacional",
    "sg:phone":"+34 965 31 19 44",
    "sg:postcode":"03360",
    "sg:province":"Alicante",
    "wof:name":"Esteve Perez Jose Alfonso",
    "wof:placetype":"venue"
},
  "geometry": {"coordinates":[-0.8739690185,38.126083374],"type":"Point"}
}