{
  "type": "Feature",
  "properties": {
    "addr:full":"Calle de Alferez Oleza Gual, 10 Palma Islas Baleares 07010",
    "addr:housenumber":"10",
    "addr:postcode":"07010",
    "addr:street":"Calle De Alferez Oleza Gual",
    "iso:country":"ES",
    "sg:address":"Calle de Alferez Oleza Gual, 10",
    "sg:city":"Palma",
    "sg:orig_category":"Peluquer\u00cdas, Peluquer\u00cda Mixta",
    "sg:phone":"+34 971 20 18 23",
    "sg:postcode":"07010",
    "sg:province":"Islas Baleares",
    "wof:name":"Lares-franco Salom Vicente",
    "wof:placetype":"venue"
},
  "geometry": {"coordinates":[2.647465229,39.585067749],"type":"Point"}
}