{
  "type": "Feature",
  "properties": {
    "iso:country":"ES",
    "sg:address":"Calle de Pintor Oliet, 20",
    "sg:city":"Onda",
    "sg:orig_category":"Carnicer\u00cdas, Carnicer\u00cdas",
    "sg:phone":"+34 964 60 31 83",
    "sg:postcode":"12200",
    "sg:province":"Castell\u00f3n",
    "wof:name":"Azor Y Fernandez Scv.",
    "wof:placetype":"venue"
},
  "geometry": {"coordinates":[-0.2641929984,39.9602890015],"type":"Point"}
}