{
  "type": "Feature",
  "properties": {
    "addr:full":"Calle de Maldonado, 37 S. Pedro Martir Ii Las Palmas 35110",
    "addr:housenumber":"37",
    "addr:postcode":"35110",
    "addr:street":"Calle De Maldonado",
    "iso:country":"ES",
    "sg:address":"Calle de Maldonado, 37",
    "sg:city":"S. Pedro Martir Ii",
    "sg:orig_category":"Peluquer\u00cdas, Peluquer\u00cda Mixta",
    "sg:phone":"+34 928 75 63 56",
    "sg:postcode":"35110",
    "sg:province":"Las Palmas",
    "wof:name":"Martel Martel Mary",
    "wof:placetype":"venue"
},
  "geometry": {"coordinates":[-15.4485340118,27.8392906189],"type":"Point"}
}