{
  "type": "Feature",
  "properties": {
    "iso:country":"ES",
    "sg:address":"Avgd Antonio Almela, 53",
    "sg:city":"Alcudia",
    "sg:orig_category":"Asesor\u00cda Fiscal Y Jur\u00cddica",
    "sg:phone":"+34 962 54 14 59",
    "sg:postcode":"46250",
    "sg:province":"Valencia",
    "wof:name":"Atfilab Asesores S.l.",
    "wof:placetype":"venue"
},
  "geometry": {"coordinates":[-0.5027496219,39.1956672668],"type":"Point"}
}