{
  "type": "Feature",
  "properties": {
    "addr:full":"Carrer de Cami De Les Bruixes, 8 Altafulla Tarragona 43893",
    "addr:housenumber":"8",
    "addr:postcode":"43893",
    "addr:street":"Carrer De Cami De Les Bruixes",
    "iso:country":"ES",
    "sg:address":"Carrer de Cami De Les Bruixes, 8",
    "sg:city":"Altafulla",
    "sg:orig_category":"Centros Empresariales",
    "sg:phone":"+34 977 65 12 36",
    "sg:postcode":"43893",
    "sg:province":"Tarragona",
    "wof:name":"Santillan & Pedrosa Consulting S.l.",
    "wof:placetype":"venue"
},
  "geometry": {"coordinates":[1.3773850203,41.1404495239],"type":"Point"}
}