{
  "type": "Feature",
  "properties": {
    "iso:country":"ES",
    "sg:address":"Barr Alto (el), 7",
    "sg:city":"Escobedo",
    "sg:orig_category":"Agencias Y Agentes Comerciales, Representantes",
    "sg:phone":"+34 942 25 86 54",
    "sg:postcode":"39609",
    "sg:province":"Cantabria",
    "wof:name":"Cruz Castro Abel",
    "wof:placetype":"venue"
},
  "geometry": {"coordinates":[-3.8822391033,43.4023246765],"type":"Point"}
}