{
  "type": "Feature",
  "properties": {
    "iso:country":"ES",
    "sg:address":"Calle de Francisco Vitoria, 17",
    "sg:city":"Zaragoza",
    "sg:orig_category":"Abogados",
    "sg:phone":"+34 976 22 70 93",
    "sg:postcode":"50008",
    "sg:province":"Zaragoza",
    "wof:name":"Pinilla Alquezar Eduardo",
    "wof:placetype":"venue"
},
  "geometry": {"coordinates":[-0.8802329898,41.6463279724],"type":"Point"}
}