{
  "type": "Feature",
  "properties": {
    "iso:country":"ES",
    "sg:address":"Calle de Sagasta, 9",
    "sg:city":"Madrid",
    "sg:orig_category":"Retoques De Vestidos",
    "sg:phone":"+34 914 48 16 60",
    "sg:postcode":"28004",
    "sg:province":"Madrid",
    "wof:name":"Martin Arias Felipe",
    "wof:placetype":"venue"
},
  "geometry": {"coordinates":[-3.7013320923,40.4288139343],"type":"Point"}
}