{
  "type": "Feature",
  "properties": {
    "iso:country":"ES",
    "sg:address":"Calle de Iglesia, 27",
    "sg:city":"Bailen",
    "sg:orig_category":"Bebidas",
    "sg:phone":"+34 953 67 27 05",
    "sg:postcode":"23710",
    "sg:province":"Ja\u00e9n",
    "wof:name":"Puche Castillejo Alfonso",
    "wof:placetype":"venue"
},
  "geometry": {"coordinates":[-3.7758140564,38.0949363708],"type":"Point"}
}