{
  "type": "Feature",
  "properties": {
    "addr:full":"Ctra Circunvalacion, 155 Guarda Pontevedra 36780",
    "addr:housenumber":"155",
    "addr:postcode":"36780",
    "addr:street":"Ctra Circunvalacion",
    "iso:country":"ES",
    "sg:address":"Ctra Circunvalacion, 155",
    "sg:city":"Guarda",
    "sg:classifiers":[
        {
            "category":"Recreation",
            "type":"Entertainment"
        }
    ],
    "sg:phone":"+34 986 61 18 58",
    "sg:postcode":"36780",
    "sg:province":"Pontevedra",
    "sg:tags":[
        "caza",
        "pr\u00c1ctica",
        "la",
        "de",
        "pesca",
        "y"
    ],
    "wof:name":"Eluismar S.l.",
    "wof:placetype":"venue"
},
  "geometry": {"coordinates":[-8.8713140488,41.9025039673],"type":"Point"}
}