{
  "type": "Feature",
  "properties": {
    "iso:country":"ES",
    "sg:address":"Calle de Zamakoa, 5",
    "sg:city":"Kurtzea",
    "sg:orig_category":"Peluquer\u00cdas, Peluquer\u00cda Mixta",
    "sg:phone":"+34 944 56 26 48",
    "sg:postcode":"48960",
    "sg:province":"Vizcaya",
    "wof:name":"Uriarte Etxegarai Maria Belen",
    "wof:placetype":"venue"
},
  "geometry": {"coordinates":[-2.8428399563,43.2312240601],"type":"Point"}
}