{
  "type": "Feature",
  "properties": {
    "addr:full":"Calle de Rambla De Las Cruces, 93 Adra Almer\u00eda 04770",
    "addr:housenumber":"93",
    "addr:postcode":"04770",
    "addr:street":"Calle De Rambla De Las Cruces;Almeri\u0301A",
    "iso:country":"ES",
    "sg:address":"Calle de Rambla De Las Cruces, 93",
    "sg:city":"Adra",
    "sg:orig_category":"Centros De Educaci\u00d3n Especial",
    "sg:phone":"+34 950 56 09 72",
    "sg:postcode":"04770",
    "sg:province":"Almer\u00eda",
    "wof:name":"Centro Educacion Adultos Adra",
    "wof:placetype":"venue"
},
  "geometry": {"coordinates":[-3.014909029,36.7501296997],"type":"Point"}
}