{
  "type": "Feature",
  "properties": {
    "iso:country":"ES",
    "sg:address":"Jaraiz, S/n",
    "sg:city":"Jarandilla Vera",
    "sg:orig_category":"Arquitectos",
    "sg:phone":"+34 927 56 05 04",
    "sg:postcode":"10450",
    "sg:province":"C\u00e1ceres",
    "wof:name":"Miranda Garcia Marcelino",
    "wof:placetype":"venue"
},
  "geometry": {"coordinates":[-5.659965992,40.1283340454],"type":"Point"}
}