{
  "type": "Feature",
  "properties": {
    "iso:country":"ES",
    "sg:address":"Ctra Zaragoza, Km. 0073,0",
    "sg:city":"Alfaro",
    "sg:orig_category":"Negocio De Madera",
    "sg:phone":"+34 941 18 33 35",
    "sg:postcode":"26540",
    "sg:province":"La Rioja",
    "wof:name":"Puertas Venezia S.l.",
    "wof:placetype":"venue"
},
  "geometry": {"coordinates":[-1.7569589615,42.1787185669],"type":"Point"}
}