{
  "type": "Feature",
  "properties": {
    "iso:country":"ES",
    "sg:address":"J. Rei Pastor, S/n",
    "sg:city":"Granollers",
    "sg:orig_category":"Galvanizaci\u00d3n, Esta\u00d1ado, Emplomado",
    "sg:phone":"+34 938 46 39 17",
    "sg:postcode":"08403",
    "sg:province":"Barcelona",
    "wof:name":"Galvanizados Del Valles Oriental S.l.",
    "wof:placetype":"venue"
},
  "geometry": {"coordinates":[2.2640309334,41.582118988],"type":"Point"}
}