{
  "type": "Feature",
  "properties": {
    "addr:full":"C/ Tarragona, S/n Banyoles Girona 17820",
    "addr:postcode":"17820",
    "addr:street":"C / Tarragona S / N",
    "iso:country":"ES",
    "sg:address":"C/ Tarragona, S/n",
    "sg:city":"Banyoles",
    "sg:orig_category":"Tintorer\u00cdas, Limpieza En Seco",
    "sg:phone":"+34 972 58 07 70",
    "sg:postcode":"17820",
    "sg:province":"Girona",
    "wof:name":"Bugaderia Roura C.b.",
    "wof:placetype":"venue"
},
  "geometry": {"coordinates":[2.7746100426,42.1149253845],"type":"Point"}
}