{
  "type": "Feature",
  "properties": {
    "iso:country":"ES",
    "sg:address":"Calle de Monjas, 16",
    "sg:city":"Membrilla",
    "sg:orig_category":"Florister\u00cdas",
    "sg:phone":"+34 926 63 71 40",
    "sg:postcode":"13230",
    "sg:province":"Ciudad Real",
    "wof:name":"Diaz-pintado Jimenez Jose",
    "wof:placetype":"venue"
},
  "geometry": {"coordinates":[-3.3456990719,38.9703788757],"type":"Point"}
}