{
  "type": "Feature",
  "properties": {
    "addr:full":"Avda Compromiso De Caspe, 9 Zaragoza Zaragoza 50002",
    "addr:housenumber":"9",
    "addr:postcode":"50002",
    "addr:street":"Avda Compromiso De Caspe",
    "iso:country":"ES",
    "sg:address":"Avda Compromiso De Caspe, 9",
    "sg:city":"Zaragoza",
    "sg:orig_category":"Agentes De Seguros",
    "sg:phone":"+34 976 48 63 35",
    "sg:postcode":"50002",
    "sg:province":"Zaragoza",
    "wof:name":"Segura Forn Jesus",
    "wof:placetype":"venue"
},
  "geometry": {"coordinates":[-0.8709400296,41.6462783813],"type":"Point"}
}