{
  "type": "Feature",
  "properties": {
    "iso:country":"ES",
    "sg:address":"Avda Del Pais Valencia, 22",
    "sg:city":"Vinaros",
    "sg:orig_category":"Asesor\u00cda Fiscal Y Jur\u00cddica",
    "sg:phone":"+34 964 45 16 66",
    "sg:postcode":"12500",
    "sg:province":"Castell\u00f3n",
    "wof:name":"Romillo Garcia Asesores S.l.",
    "wof:placetype":"venue"
},
  "geometry": {"coordinates":[0.4741399884,40.4683799744],"type":"Point"}
}