{
  "type": "Feature",
  "properties": {
    "addr:full":"C/ Sant Lloren\u00c7, 10 Alcoi Alicante 03801",
    "addr:housenumber":"10",
    "addr:postcode":"03801",
    "addr:street":"C / Sant Llorenc\u0327",
    "iso:country":"ES",
    "sg:address":"C/ Sant Lloren\u00c7, 10",
    "sg:city":"Alcoi",
    "sg:orig_category":"Ropa Para Se\u00d1oras (al Por Menor)",
    "sg:phone":"+34 965 54 09 09",
    "sg:postcode":"03801",
    "sg:province":"Alicante",
    "sg:website":"www.guiluna@terra.es",
    "wof:name":"Guillermo Luna S.l.",
    "wof:placetype":"venue"
},
  "geometry": {"coordinates":[-0.4735589921,38.6976242065],"type":"Point"}
}