{
  "type": "Feature",
  "properties": {
    "iso:country":"ES",
    "sg:address":"Calle de Antonio Machado, 15",
    "sg:city":"Salinas",
    "sg:orig_category":"Aguas (distribuci\u00d3n, Servicios)",
    "sg:phone":"+34 965 47 91 38",
    "sg:postcode":"03658",
    "sg:province":"Alicante",
    "wof:name":"Aquagest Levante S.a.",
    "wof:placetype":"venue"
},
  "geometry": {"coordinates":[-0.9121413827,38.5200271606],"type":"Point"}
}