{
  "type": "Feature",
  "properties": {
    "addr:full":"Carrer de Hospital, 21 Cambrils Tarragona 43850",
    "addr:housenumber":"21",
    "addr:postcode":"43850",
    "addr:street":"Carrer De Hospital",
    "iso:country":"ES",
    "sg:address":"Carrer de Hospital, 21",
    "sg:city":"Cambrils",
    "sg:orig_category":"Abogados",
    "sg:phone":"+34 977 36 51 55",
    "sg:postcode":"43850",
    "sg:province":"Tarragona",
    "wof:name":"Fornes Nolla Ernest",
    "wof:placetype":"venue"
},
  "geometry": {"coordinates":[1.0528399944,41.0740203857],"type":"Point"}
}