{
  "type": "Feature",
  "properties": {
    "addr:full":"Calle de Alcala, 85 Madrid Madrid 28009",
    "addr:housenumber":"85",
    "addr:postcode":"madrid;28009",
    "addr:street":"Calle De Alcala",
    "iso:country":"ES",
    "sg:address":"Calle de Alcala, 85",
    "sg:city":"Madrid",
    "sg:orig_category":"Librer\u00cdas",
    "sg:phone":"+34 917 65 14 00",
    "sg:postcode":"28009",
    "sg:province":"Madrid",
    "wof:name":"Rodriguez Sanchez Maria Del Rosario",
    "wof:placetype":"venue"
},
  "geometry": {"coordinates":[-3.6857972145,40.4207267761],"type":"Point"}
}