{
  "type": "Feature",
  "properties": {
    "addr:full":"Plaz Escamilla, 9 Coin M\u00e1laga 29100",
    "addr:housenumber":"9",
    "addr:postcode":"29100",
    "addr:street":"Plaz Escamilla;Ma\u0301Laga",
    "iso:country":"ES",
    "sg:address":"Plaz Escamilla, 9",
    "sg:city":"Coin",
    "sg:orig_category":"Confecci\u00d3n (fabricaci\u00d3n, Al Por Mayor)",
    "sg:phone":"+34 952 45 25 71",
    "sg:postcode":"29100",
    "sg:province":"M\u00e1laga",
    "wof:name":"Martin Bermudez S.l.",
    "wof:placetype":"venue"
},
  "geometry": {"coordinates":[-4.7579641342,36.6597480774],"type":"Point"}
}