{
  "type": "Feature",
  "properties": {
    "iso:country":"ES",
    "sg:address":"Calle de Miguel Hernandez, 21",
    "sg:city":"Carmona",
    "sg:orig_category":"Molduras, Junquillos, Listones Y Molduras Perforadas",
    "sg:phone":"+34 954 14 90 61",
    "sg:postcode":"41410",
    "sg:province":"Sevilla",
    "wof:name":"Morales Rosales Ana",
    "wof:placetype":"venue"
},
  "geometry": {"coordinates":[-5.6430020332,37.4669265747],"type":"Point"}
}