{
  "type": "Feature",
  "properties": {
    "addr:full":"Carrer de Feliu I Codina, 27 Barcelona Barcelona 08031",
    "addr:housenumber":"27",
    "addr:postcode":"08031",
    "addr:street":"Carrer De Feliu;Codina",
    "iso:country":"ES",
    "sg:address":"Carrer de Feliu I Codina, 27",
    "sg:city":"Barcelona",
    "sg:orig_category":"Asociaciones Y Clubs Deportivos",
    "sg:phone":"+34 934 27 64 79",
    "sg:postcode":"08031",
    "sg:province":"Barcelona",
    "wof:name":"Unio Esportiva D'horta",
    "wof:placetype":"venue"
},
  "geometry": {"coordinates":[2.1609210968,41.4334487915],"type":"Point"}
}