{
  "type": "Feature",
  "properties": {
    "addr:full":"Carrer de Convent, 57 Cocentaina Alicante 03820",
    "addr:housenumber":"57",
    "addr:postcode":"03820",
    "addr:street":"Carrer De Convent",
    "iso:country":"ES",
    "sg:address":"Carrer de Convent, 57",
    "sg:city":"Cocentaina",
    "sg:orig_category":"Tubos Y Tuber\u00cdas De Goma Y Pl\u00c1stico (fabricaci\u00d3n, Al Por Mayor)",
    "sg:phone":"+34 965 59 15 71",
    "sg:postcode":"03820",
    "sg:province":"Alicante",
    "wof:name":"Segui Perez Manuel",
    "wof:placetype":"venue"
},
  "geometry": {"coordinates":[-0.441482991,38.7380981445],"type":"Point"}
}