{
  "type": "Feature",
  "properties": {
    "addr:full":"Calle de Miguel Iscar, 8 Valladolid Valladolid 47001",
    "addr:housenumber":"8",
    "addr:postcode":"47001",
    "addr:street":"Calle De Miguel Iscar",
    "iso:country":"ES",
    "sg:address":"Calle de Miguel Iscar, 8",
    "sg:city":"Valladolid",
    "sg:orig_category":"Confecci\u00d3n De Sombreros Y Tocados",
    "sg:phone":"+34 983 30 29 71",
    "sg:postcode":"47001",
    "sg:province":"Valladolid",
    "wof:name":"Santos Debran Maria Dolores",
    "wof:placetype":"venue"
},
  "geometry": {"coordinates":[-4.7274050713,41.6483154297],"type":"Point"}
}