{
  "type": "Feature",
  "properties": {
    "iso:country":"ES",
    "sg:address":"Carrer de Beat Oriol, 13",
    "sg:city":"Mas Rampinyo",
    "sg:orig_category":"Mec\u00c1nico Del Autom\u00d3vil",
    "sg:phone":"+34 935 75 07 11",
    "sg:postcode":"08110",
    "sg:province":"Barcelona",
    "wof:name":"Talleres La Jota S.l.",
    "wof:placetype":"venue"
},
  "geometry": {"coordinates":[2.1816411018,41.4911956787],"type":"Point"}
}