{
  "type": "Feature",
  "properties": {
    "iso:country":"ES",
    "sg:address":"Ctra Estacion De Contenedores, S/n",
    "sg:city":"Madrid",
    "sg:orig_category":"Contenedores (mercanc\u00cdas)",
    "sg:phone":"+34 917 23 09 47",
    "sg:postcode":"28021",
    "sg:province":"Madrid",
    "wof:name":"Algetren Logistica S.a.",
    "wof:placetype":"venue"
},
  "geometry": {"coordinates":[-3.6978263855,40.3366584778],"type":"Point"}
}