{
  "type": "Feature",
  "properties": {
    "addr:full":"Kaleberria, 18 Andoain Guip\u00f9zcoa 20140",
    "addr:housenumber":"18",
    "addr:postcode":"20140",
    "addr:street":"Kaleberria;Guipu\u0300Zcoa",
    "iso:country":"ES",
    "sg:address":"Kaleberria, 18",
    "sg:city":"Andoain",
    "sg:orig_category":"Electromec\u00c1nica",
    "sg:phone":"+34 943 59 13 01",
    "sg:postcode":"20140",
    "sg:province":"Guip\u00f9zcoa",
    "wof:name":"Talleres Ariceta C.b.-electromecanica",
    "wof:placetype":"venue"
},
  "geometry": {"coordinates":[-2.0212750435,43.2159729004],"type":"Point"}
}