{
  "type": "Feature",
  "properties": {
    "iso:country":"ES",
    "sg:address":"Calle de Fernando Fernandez Martinez, 7",
    "sg:city":"Cordoba",
    "sg:orig_category":"Agencias Y Agentes Comerciales, Representantes",
    "sg:phone":"+34 957 43 78 30",
    "sg:postcode":"14007",
    "sg:province":"C\u00f3rdoba",
    "wof:name":"Redondo Nistal Gregorio",
    "wof:placetype":"venue"
},
  "geometry": {"coordinates":[-4.7615060806,37.8901863098],"type":"Point"}
}