{
  "type": "Feature",
  "properties": {
    "addr:full":"Calle de Barcelona, 4 Palmas De Gran Canaria Las Palmas 35006",
    "addr:housenumber":"4",
    "addr:postcode":"35006",
    "addr:street":"Calle De Barcelona",
    "iso:country":"ES",
    "sg:address":"Calle de Barcelona, 4",
    "sg:city":"Palmas De Gran Canaria",
    "sg:orig_category":"Centros De Educaci\u00d3n Especial",
    "sg:phone":"+34 928 23 27 79",
    "sg:postcode":"35006",
    "sg:province":"Las Palmas",
    "wof:name":"Centro De Educacion Infantil Y Primaria Alcaravaneras",
    "wof:placetype":"venue"
},
  "geometry": {"coordinates":[-15.4178361893,28.0340175629],"type":"Point"}
}