{
  "type": "Feature",
  "properties": {
    "addr:full":"Carrer de Major, 100 Molins Rei Barcelona 08750",
    "addr:housenumber":"100",
    "addr:postcode":"08750",
    "addr:street":"Carrer De Major;Barcelona",
    "iso:country":"ES",
    "sg:address":"Carrer de Major, 100",
    "sg:city":"Molins Rei",
    "sg:orig_category":"Farmacias",
    "sg:phone":"+34 936 68 19 94",
    "sg:postcode":"08750",
    "sg:province":"Barcelona",
    "wof:name":"Xucla Bas Mariano",
    "wof:placetype":"venue"
},
  "geometry": {"coordinates":[2.0535550117,41.3682975769],"type":"Point"}
}