{
  "type": "Feature",
  "properties": {
    "iso:country":"ES",
    "sg:address":"Rua Peregrina (da), 9",
    "sg:city":"Pontevedra",
    "sg:orig_category":"Asesor\u00cda Sobre Comunicaci\u00d3n De Empresas",
    "sg:phone":"+34 986 85 82 82",
    "sg:postcode":"36001",
    "sg:province":"Pontevedra",
    "wof:name":"Fernandez Moreira Maria Dolores",
    "wof:placetype":"venue"
},
  "geometry": {"coordinates":[-8.6434278488,42.4302825928],"type":"Point"}
}