{
  "type": "Feature",
  "properties": {
    "addr:full":"Avda Andalucia, S/n Palmones C\u00e1diz 11379",
    "addr:postcode":"11379",
    "addr:street":"Avda Andalucia S / N;Ca\u0301Diz",
    "iso:country":"ES",
    "sg:address":"Avda Andalucia, S/n",
    "sg:city":"Palmones",
    "sg:orig_category":"Asesor\u00cda, Estudio Y Control Medioambiental",
    "sg:phone":"+34 956 67 60 55",
    "sg:postcode":"11379",
    "sg:province":"C\u00e1diz",
    "wof:name":"Empresa De Gestion Medio Ambiental S.a.",
    "wof:placetype":"venue"
},
  "geometry": {"coordinates":[-5.4401340485,36.1761665344],"type":"Point"}
}