{
  "type": "Feature",
  "properties": {
    "addr:full":"Calle de Venus, 10 Loja Granada 18300",
    "addr:housenumber":"10",
    "addr:postcode":"18300",
    "addr:street":"Calle De Venus",
    "iso:country":"ES",
    "sg:address":"Calle de Venus, 10",
    "sg:city":"Loja",
    "sg:orig_category":"Confecci\u00d3n (fabricaci\u00d3n, Al Por Mayor)",
    "sg:phone":"+34 958 32 38 59",
    "sg:postcode":"18300",
    "sg:province":"Granada",
    "wof:name":"Jimenez Quintana Manuel",
    "wof:placetype":"venue"
},
  "geometry": {"coordinates":[-4.1472048759,37.1765441895],"type":"Point"}
}