{
  "type": "Feature",
  "properties": {
    "addr:full":"Calle de San Francisco, 14 Lucena C\u00f3rdoba 14900",
    "addr:housenumber":"14",
    "addr:postcode":"14900",
    "addr:street":"Calle De San Francisco",
    "iso:country":"ES",
    "sg:address":"Calle de San Francisco, 14",
    "sg:city":"Lucena",
    "sg:orig_category":"M\u00c9dicos: Cardiolog\u00cda Y Afecciones Cardiovasculares",
    "sg:phone":"+34 957 59 04 17",
    "sg:postcode":"14900",
    "sg:province":"C\u00f3rdoba",
    "wof:name":"Herrera Gutierrez Norberto",
    "wof:placetype":"venue"
},
  "geometry": {"coordinates":[-4.4857640266,37.4147605896],"type":"Point"}
}