{
  "type": "Feature",
  "properties": {
    "addr:full":"Carrer de Mallorca, 479 Barcelona Barcelona 08013",
    "addr:housenumber":"479",
    "addr:postcode":"08013",
    "addr:street":"Carrer De Mallorca",
    "iso:country":"ES",
    "sg:address":"Carrer de Mallorca, 479",
    "sg:city":"Barcelona",
    "sg:orig_category":"Mec\u00c1nico Del Autom\u00d3vil",
    "sg:phone":"+34 933 47 64 18",
    "sg:postcode":"08013",
    "sg:province":"Barcelona",
    "wof:name":"Jose Cid Pozo Y Antonio Paez Trillo S. Cv.",
    "wof:placetype":"venue"
},
  "geometry": {"coordinates":[2.1800739765,41.4071731567],"type":"Point"}
}