{
  "type": "Feature",
  "properties": {
    "iso:country":"ES",
    "sg:address":"Lermandabidea, S/n",
    "sg:city":"Jundiz",
    "sg:orig_category":"Agencias De Aduana",
    "sg:phone":"+34 945 29 05 49",
    "sg:postcode":"01015",
    "sg:province":"\u00c1lava",
    "wof:name":"Abdon Frances Querejeta S.a.",
    "wof:placetype":"venue"
},
  "geometry": {"coordinates":[-2.73605,42.847771],"type":"Point"}
}