{
  "type": "Feature",
  "properties": {
    "iso:country":"ES",
    "sg:address":"Pantano, S/n",
    "sg:city":"Puebla Castro",
    "sg:orig_category":"Energ\u00cda Solar Y Nuevas Energ\u00cdas (equipo, Estudios)",
    "sg:phone":"+34 974 54 50 00",
    "sg:postcode":"22435",
    "sg:province":"Huesca",
    "wof:name":"Hidronitro Espa\u00f1ola S. A.",
    "wof:placetype":"venue"
},
  "geometry": {"coordinates":[0.2860850096,42.1436080933],"type":"Point"}
}