{
  "type": "Feature",
  "properties": {
    "iso:country":"ES",
    "sg:address":"Calle de Arriba, 2",
    "sg:city":"Dos-torres",
    "sg:orig_category":"Poller\u00cda Y Caza (al Por Menor)",
    "sg:phone":"+34 957 13 40 28",
    "sg:postcode":"14460",
    "sg:province":"C\u00f3rdoba",
    "wof:name":"Marquez Olmo Angel",
    "wof:placetype":"venue"
},
  "geometry": {"coordinates":[-4.8945550919,38.4469833374],"type":"Point"}
}