{
  "type": "Feature",
  "properties": {
    "addr:full":"Ctra. Jerez-arcos, Km. 0011,2 Torre Melgarejo C\u00e1diz 11592",
    "addr:postcode":"11592",
    "addr:street":"Ctra. Jerez-Arcos Km. 0011,2 Torre;Ca\u0301Diz",
    "iso:country":"ES",
    "sg:address":"Ctra. Jerez-arcos, Km. 0011,2",
    "sg:city":"Torre Melgarejo",
    "sg:orig_category":"Agricultores, Agricultores",
    "sg:phone":"+34 956 23 75 51",
    "sg:postcode":"11592",
    "sg:province":"C\u00e1diz",
    "wof:name":"Modernizacion De Cultivos S.a.",
    "wof:placetype":"venue"
},
  "geometry": {"coordinates":[-5.8789491653,36.7415237427],"type":"Point"}
}