{
  "type": "Feature",
  "properties": {
    "addr:full":"Calle de Vales, 3 Caparroso Navarra 31380",
    "addr:housenumber":"3",
    "addr:postcode":"31380",
    "addr:street":"Calle De Vales",
    "iso:country":"ES",
    "sg:address":"Calle de Vales, 3",
    "sg:city":"Caparroso",
    "sg:orig_category":"Internados & Ense\u00d1anza Privada",
    "sg:phone":"+34 948 73 00 63",
    "sg:postcode":"31380",
    "sg:province":"Navarra",
    "wof:name":"Misioneras De La Inmaculada Concepcion",
    "wof:placetype":"venue"
},
  "geometry": {"coordinates":[-1.655477047,42.3368186951],"type":"Point"}
}