{
  "type": "Feature",
  "properties": {
    "addr:full":"Real, 17 Pontedeume La Coru\u00f1a 15600",
    "addr:housenumber":"17",
    "addr:postcode":"15600",
    "addr:street":"Real;La Corun\u0303A",
    "iso:country":"ES",
    "sg:address":"Real, 17",
    "sg:city":"Pontedeume",
    "sg:orig_category":"Administraciones Regionales, Departamentales Y Locales",
    "sg:phone":"+34 981 43 30 54",
    "sg:postcode":"15600",
    "sg:province":"La Coru\u00f1a",
    "wof:name":"Concello De Pontedeume",
    "wof:placetype":"venue"
},
  "geometry": {"coordinates":[-8.1707906723,43.4062385559],"type":"Point"}
}