{
  "type": "Feature",
  "properties": {
    "addr:full":"Calle de Navarra, 4 Villanueva De La Ca\u00e7ada Madrid 28691",
    "addr:housenumber":"4",
    "addr:postcode":"28691",
    "addr:street":"Calle De Navarra",
    "iso:country":"ES",
    "sg:address":"Calle de Navarra, 4",
    "sg:city":"Villanueva De La Ca\u00e7ada",
    "sg:orig_category":"Bricolaje, Herramientas (al Por Menor)",
    "sg:phone":"+34 918 12 52 24",
    "sg:postcode":"28691",
    "sg:province":"Madrid",
    "wof:name":"Quality Woodf S.l.",
    "wof:placetype":"venue"
},
  "geometry": {"coordinates":[-4.0018692017,40.4398040771],"type":"Point"}
}