{
  "type": "Feature",
  "properties": {
    "addr:full":"Calle de Carreteria, 10 Cuenca Cuenca 16002",
    "addr:housenumber":"10",
    "addr:postcode":"16002",
    "addr:street":"Calle De Carreteria",
    "iso:country":"ES",
    "sg:address":"Calle de Carreteria, 10",
    "sg:city":"Cuenca",
    "sg:orig_category":"Centros Empresariales",
    "sg:phone":"+34 969 23 18 70",
    "sg:postcode":"16002",
    "sg:province":"Cuenca",
    "wof:name":"Dipacmar S.l.",
    "wof:placetype":"venue"
},
  "geometry": {"coordinates":[-2.1369600296,40.0738105774],"type":"Point"}
}