{
  "type": "Feature",
  "properties": {
    "addr:full":"Avda Conde De Vallellano, 1 Cordoba C\u00f3rdoba 14004",
    "addr:housenumber":"1",
    "addr:postcode":"14004",
    "addr:street":"Avda Conde De Vallellano;Co\u0301Rdoba",
    "iso:country":"ES",
    "sg:address":"Avda Conde De Vallellano, 1",
    "sg:city":"Cordoba",
    "sg:orig_category":"Ingenier\u00cda, Centros De Estudios (diversos)",
    "sg:phone":"+34 957 29 65 82",
    "sg:postcode":"14004",
    "sg:province":"C\u00f3rdoba",
    "wof:name":"Giraldez Cervera Juan Vicente",
    "wof:placetype":"venue"
},
  "geometry": {"coordinates":[-4.7849621773,37.878692627],"type":"Point"}
}