{
  "type": "Feature",
  "properties": {
    "iso:country":"ES",
    "sg:address":"Plaz Ayuntamiento, 15",
    "sg:city":"Valencia",
    "sg:orig_category":"Relojer\u00cda (al Por Menor, Reparaci\u00d3n)",
    "sg:phone":"+34 963 51 75 58",
    "sg:postcode":"46002",
    "sg:province":"Valencia",
    "wof:name":"Palom S. A.",
    "wof:placetype":"venue"
},
  "geometry": {"coordinates":[-0.376195997,39.4708709717],"type":"Point"}
}