{
  "type": "Feature",
  "properties": {
    "iso:country":"ES",
    "sg:address":"Carrer de Progres, 13",
    "sg:city":"Rubi",
    "sg:orig_category":"Chapister\u00cda",
    "sg:phone":"+34 936 97 59 73",
    "sg:postcode":"08191",
    "sg:province":"Barcelona",
    "wof:name":"Gracia Lopez Miguel",
    "wof:placetype":"venue"
},
  "geometry": {"coordinates":[2.032004118,41.4794692993],"type":"Point"}
}