{
  "type": "Feature",
  "properties": {
    "iso:country":"ES",
    "sg:address":"Calle de Castilla, 60",
    "sg:city":"Petrer",
    "sg:orig_category":"Dibujo",
    "sg:phone":"+34 966 95 01 52",
    "sg:postcode":"03610",
    "sg:province":"Alicante",
    "wof:name":"Valero Gil Jose Antonio",
    "wof:placetype":"venue"
},
  "geometry": {"coordinates":[-0.7817040086,38.4843826294],"type":"Point"}
}