{
  "type": "Feature",
  "properties": {
    "iso:country":"ES",
    "sg:address":"Carrer de Consell De Cent, 334",
    "sg:city":"Barcelona",
    "sg:orig_category":"Bancos",
    "sg:phone":"+34 934 87 82 29",
    "sg:postcode":"08009",
    "sg:province":"Barcelona",
    "wof:name":"Abn Amro Bank N.v.",
    "wof:placetype":"venue"
},
  "geometry": {"coordinates":[2.168035,41.392841],"type":"Point"}
}