{
  "type": "Feature",
  "properties": {
    "iso:country":"ES",
    "sg:address":"Estrada De Diliz, 8",
    "sg:city":"Andra Mari",
    "sg:orig_category":"M\u00c9dicos: Psiquiatr\u00cda",
    "sg:phone":"+34 944 91 05 75",
    "sg:postcode":"48993",
    "sg:province":"Vizcaya",
    "wof:name":"Franco Bilbao Javier",
    "wof:placetype":"venue"
},
  "geometry": {"coordinates":[-2.7541499138,43.2982711792],"type":"Point"}
}