{
  "type": "Feature",
  "properties": {
    "iso:country":"ES",
    "sg:address":"Plaz Cruz Verde, 6",
    "sg:city":"Valladolid",
    "sg:orig_category":"Abogados",
    "sg:phone":"+34 983 30 00 05",
    "sg:postcode":"47002",
    "sg:province":"Valladolid",
    "wof:name":"Marcos Flores Rosa Maria",
    "wof:placetype":"venue"
},
  "geometry": {"coordinates":[-4.7202801704,41.6480751038],"type":"Point"}
}