{
  "type": "Feature",
  "properties": {
    "iso:country":"ES",
    "sg:address":"Carr Sant Agusti, 22",
    "sg:city":"Girona",
    "sg:orig_category":"Mec\u00c1nico Del Autom\u00d3vil",
    "sg:phone":"+34 972 22 70 88",
    "sg:postcode":"17003",
    "sg:province":"Girona",
    "wof:name":"Cateura Y Capell S.l.",
    "wof:placetype":"venue"
},
  "geometry": {"coordinates":[2.8208661079,41.9696235657],"type":"Point"}
}