{
  "type": "Feature",
  "properties": {
    "addr:full":"Carr Palleter (el), 15 Picassent Valencia 46220",
    "addr:housenumber":"15",
    "addr:postcode":"46220",
    "addr:street":"Carr Palleter El",
    "iso:country":"ES",
    "sg:address":"Carr Palleter (el), 15",
    "sg:city":"Picassent",
    "sg:orig_category":"Fabricaci\u00d3n De Bolsos Y Bolsos De Tela",
    "sg:phone":"+34 961 23 01 47",
    "sg:postcode":"46220",
    "sg:province":"Valencia",
    "wof:name":"Escudero Lopez Salvador",
    "wof:placetype":"venue"
},
  "geometry": {"coordinates":[-0.4660860002,39.3639068604],"type":"Point"}
}