{
  "type": "Feature",
  "properties": {
    "addr:full":"Carrer de Verge De La Merce, 60 Esplugues Llobregat Barcelona 08950",
    "addr:housenumber":"60",
    "addr:postcode":"08950",
    "addr:street":"Carrer De Verge De La Merce",
    "iso:country":"ES",
    "sg:address":"Carrer de Verge De La Merce, 60",
    "sg:city":"Esplugues Llobregat",
    "sg:orig_category":"Cl\u00cdnicas Dentales",
    "sg:phone":"+34 934 73 43 16",
    "sg:postcode":"08950",
    "sg:province":"Barcelona",
    "wof:name":"Falco Aguilar Pilar",
    "wof:placetype":"venue"
},
  "geometry": {"coordinates":[2.0994939804,41.3732414246],"type":"Point"}
}