{
  "type": "Feature",
  "properties": {
    "addr:full":"Pol Ind B, 6 Olivares Sevilla 41804",
    "addr:postcode":"41804",
    "addr:street":"Olivares",
    "iso:country":"ES",
    "sg:address":"Pol Ind B, 6",
    "sg:city":"Olivares",
    "sg:orig_category":"Maquinaria Para Industrias Diversas",
    "sg:phone":"+34 954 11 09 00",
    "sg:postcode":"41804",
    "sg:province":"Sevilla",
    "wof:name":"Segura Y Abrines S.l.",
    "wof:placetype":"venue"
},
  "geometry": {"coordinates":[-6.153439045,37.4184074402],"type":"Point"}
}