{
  "type": "Feature",
  "properties": {
    "iso:country":"ES",
    "sg:address":"Calle de Salamanca, 45",
    "sg:city":"Santa Maria Aguila",
    "sg:orig_category":"Producci\u00d3n, Venta De Productos De Agricultura Biol\u00d3gica",
    "sg:phone":"+34 950 60 64 58",
    "sg:postcode":"04710",
    "sg:province":"Almer\u00eda",
    "wof:name":"Midofruit Sociedad Cooperativa Andaluza",
    "wof:placetype":"venue"
},
  "geometry": {"coordinates":[-2.7761170864,36.7821006775],"type":"Point"}
}