{
  "type": "Feature",
  "properties": {
    "iso:country":"ES",
    "sg:address":"Calle de Poeta Carlos Salvador, 11",
    "sg:city":"Valencia",
    "sg:orig_category":"Abogados",
    "sg:phone":"+34 963 60 66 00",
    "sg:postcode":"46020",
    "sg:province":"Valencia",
    "wof:name":"Moreno Greses Maria Isabel",
    "wof:placetype":"venue"
},
  "geometry": {"coordinates":[-0.3594000041,39.4859428406],"type":"Point"}
}