{
  "type": "Feature",
  "properties": {
    "iso:country":"ES",
    "sg:address":"Avda Doctor Artero Guirao, S/n",
    "sg:city":"S. Pedro Pinatar",
    "sg:orig_category":"Molduras, Junquillos, Listones Y Molduras Perforadas",
    "sg:phone":"+34 968 18 04 58",
    "sg:postcode":"30740",
    "sg:province":"Murcia",
    "wof:name":"Surtel Comunicaciones S L",
    "wof:placetype":"venue"
},
  "geometry": {"coordinates":[-0.7902640104,37.8375053406],"type":"Point"}
}