{
  "type": "Feature",
  "properties": {
    "iso:country":"ES",
    "sg:address":"Rua Tarascon (de), 15",
    "sg:city":"Ourense",
    "sg:orig_category":"Alimentaci\u00d3n General (al Por Menor)",
    "sg:phone":"+34 988 21 20 58",
    "sg:postcode":"32001",
    "sg:province":"Ourense",
    "wof:name":"Gomez Rubin Indalecio",
    "wof:placetype":"venue"
},
  "geometry": {"coordinates":[-7.8946437836,42.3564758301],"type":"Point"}
}