{
  "type": "Feature",
  "properties": {
    "addr:full":"Carrer de Sant Bartomeu, 109 Campello Alicante 03560",
    "addr:housenumber":"109",
    "addr:postcode":"03560",
    "addr:street":"Carrer De Sant Bartomeu",
    "iso:country":"ES",
    "sg:address":"Carrer de Sant Bartomeu, 109",
    "sg:city":"Campello",
    "sg:orig_category":"Administradores De Bienes Y Delegados De Comunidades De Propietarios",
    "sg:phone":"+34 965 63 40 12",
    "sg:postcode":"03560",
    "sg:province":"Alicante",
    "wof:name":"Administracion Control Inmobiliario S.a.",
    "wof:placetype":"venue"
},
  "geometry": {"coordinates":[-0.3891532123,38.4299507141],"type":"Point"}
}