{
  "type": "Feature",
  "properties": {
    "addr:full":"Poli Vega De Arriba, S/n Mieres Asturias 33600",
    "addr:housenumber":"s / n",
    "addr:postcode":"33600",
    "addr:street":"Vega;Arriba",
    "iso:country":"ES",
    "sg:address":"Poli Vega De Arriba, S/n",
    "sg:city":"Mieres",
    "sg:orig_category":"M\u00c1rmoles, Granitos Y Piedras Naturales",
    "sg:phone":"+34 985 46 24 03",
    "sg:postcode":"33600",
    "sg:province":"Asturias",
    "wof:name":"Marmoles J. Llaneza S.l.",
    "wof:placetype":"venue"
},
  "geometry": {"coordinates":[-5.7791390419,43.2342262268],"type":"Point"}
}