{
  "type": "Feature",
  "properties": {
    "iso:country":"ES",
    "sg:address":"C/ Calvari, 7",
    "sg:city":"Moncofa",
    "sg:orig_category":"Peluquer\u00cdas, Peluquer\u00cda Mixta",
    "sg:phone":"+34 964 58 06 69",
    "sg:postcode":"12593",
    "sg:province":"Castell\u00f3n",
    "wof:name":"Carbonell Tena Maria Magdalena",
    "wof:placetype":"venue"
},
  "geometry": {"coordinates":[-0.1463640034,39.8070678711],"type":"Point"}
}