{
  "type": "Feature",
  "properties": {
    "iso:country":"ES",
    "sg:address":"Calle de Antonio Machado, 6",
    "sg:city":"Toboso",
    "sg:orig_category":"Velas Y Cirios (fabricaci\u00d3n, Al Por Menor)",
    "sg:phone":"+34 925 19 70 60",
    "sg:postcode":"45820",
    "sg:province":"Toledo",
    "wof:name":"Velas Martinez Morales S.l.",
    "wof:placetype":"venue"
},
  "geometry": {"coordinates":[-2.9938950539,39.5132522583],"type":"Point"}
}