{
  "type": "Feature",
  "properties": {
    "addr:full":"Calle de Carpinteros, 22 Talavera Reina Toledo 45600",
    "addr:housenumber":"22",
    "addr:postcode":"45600",
    "addr:street":"Calle De Carpinteros",
    "iso:country":"ES",
    "sg:address":"Calle de Carpinteros, 22",
    "sg:city":"Talavera Reina",
    "sg:orig_category":"Quincaller\u00cda (al Por Menor)",
    "sg:phone":"+34 925 80 19 79",
    "sg:postcode":"45600",
    "sg:province":"Toledo",
    "wof:name":"Ferrygas S. A.",
    "wof:placetype":"venue"
},
  "geometry": {"coordinates":[-4.846736908,39.9562911987],"type":"Point"}
}