{
  "type": "Feature",
  "properties": {
    "iso:country":"ES",
    "sg:address":"Calle de Salamero, 1",
    "sg:city":"Graus",
    "sg:orig_category":"Florister\u00cdas",
    "sg:phone":"+34 974 54 00 75",
    "sg:postcode":"22430",
    "sg:province":"Huesca",
    "wof:name":"Borgo\u00f1o Larruy Jose Antonio",
    "wof:placetype":"venue"
},
  "geometry": {"coordinates":[0.3382329941,42.1914825439],"type":"Point"}
}