{
  "type": "Feature",
  "properties": {
    "addr:full":"Carr Manel Bonmati I Romaguera, 2 Girona Girona 17003",
    "addr:housenumber":"2",
    "addr:postcode":"17003",
    "addr:street":"Carr Manel Bonmati;Romaguera",
    "iso:country":"ES",
    "sg:address":"Carr Manel Bonmati I Romaguera, 2",
    "sg:city":"Girona",
    "sg:orig_category":"Ense\u00d1anza: Comercio, Gesti\u00d3n, Inform\u00c1tica",
    "sg:phone":"+34 972 41 13 11",
    "sg:postcode":"17003",
    "sg:province":"Girona",
    "wof:name":"Institut Tecnic J. Balmes S.l.",
    "wof:placetype":"venue"
},
  "geometry": {"coordinates":[2.8156709671,41.9748764038],"type":"Point"}
}