{
  "type": "Feature",
  "properties": {
    "iso:country":"ES",
    "sg:address":"Carr Major, 39",
    "sg:city":"Palamos",
    "sg:orig_category":"Farmacias",
    "sg:phone":"+34 972 31 41 23",
    "sg:postcode":"17230",
    "sg:province":"Girona",
    "wof:name":"Matamala Joan Maria Jose",
    "wof:placetype":"venue"
},
  "geometry": {"coordinates":[3.1293900013,41.8470611572],"type":"Point"}
}