{
  "type": "Feature",
  "properties": {
    "iso:country":"ES",
    "sg:address":"Calle de Aguilon, 5",
    "sg:city":"Madrid",
    "sg:orig_category":"Bisuter\u00cda, Joyer\u00cda, Relojer\u00cda (al Por Menor)",
    "sg:phone":"+34 914 73 58 87",
    "sg:postcode":"28045",
    "sg:province":"Madrid",
    "wof:name":"Gil Gomez Francisco Salvador",
    "wof:placetype":"venue"
},
  "geometry": {"coordinates":[-3.7017405033,40.3975257874],"type":"Point"}
}