{
  "type": "Feature",
  "properties": {
    "addr:full":"Avda Castilla-la Mancha (de), 164 San Sebastian De Los Reyes Madrid 28700",
    "addr:housenumber":"164",
    "addr:postcode":"28700",
    "addr:street":"Avda Castilla-La Mancha De",
    "iso:country":"ES",
    "sg:address":"Avda Castilla-la Mancha (de), 164",
    "sg:city":"San Sebastian De Los Reyes",
    "sg:orig_category":"Ense\u00d1anza Variada",
    "sg:phone":"+34 916 23 70 53",
    "sg:postcode":"28700",
    "sg:province":"Madrid",
    "wof:name":"Colyseum Academy S.l.",
    "wof:placetype":"venue"
},
  "geometry": {"coordinates":[-3.6396260262,40.5580825806],"type":"Point"}
}