{
  "type": "Feature",
  "properties": {
    "addr:full":"Calle de Quevedo, 22 Albacete Albacete 02005",
    "addr:housenumber":"22",
    "addr:postcode":"02005",
    "addr:street":"Calle De Quevedo",
    "iso:country":"ES",
    "sg:address":"Calle de Quevedo, 22",
    "sg:city":"Albacete",
    "sg:orig_category":"Muebles",
    "sg:phone":"+34 967 22 52 64",
    "sg:postcode":"02005",
    "sg:province":"Albacete",
    "wof:name":"Diaz Abia Martin",
    "wof:placetype":"venue"
},
  "geometry": {"coordinates":[-1.8652869463,38.9996185303],"type":"Point"}
}