{
  "type": "Feature",
  "properties": {
    "addr:full":"Calle de Erremedio, 19 Bermeo Vizcaya 48370",
    "addr:housenumber":"19",
    "addr:postcode":"48370",
    "addr:street":"Calle De Erremedio",
    "iso:country":"ES",
    "sg:address":"Calle de Erremedio, 19",
    "sg:city":"Bermeo",
    "sg:orig_category":"Perfumer\u00cda (al Por Menor)",
    "sg:phone":"+34 946 88 03 40",
    "sg:postcode":"48370",
    "sg:province":"Vizcaya",
    "wof:name":"Guadalupe Benguria (perfumeria Benguria)",
    "wof:placetype":"venue"
},
  "geometry": {"coordinates":[-2.7243528366,43.4197654724],"type":"Point"}
}