{
  "type": "Feature",
  "properties": {
    "addr:full":"Avda Independencia, 28 Zaragoza Zaragoza 50004",
    "addr:housenumber":"28",
    "addr:postcode":"50004",
    "addr:street":"Avda Independencia",
    "iso:country":"ES",
    "sg:address":"Avda Independencia, 28",
    "sg:city":"Zaragoza",
    "sg:orig_category":"Abogados",
    "sg:phone":"+34 976 22 11 77",
    "sg:postcode":"50004",
    "sg:province":"Zaragoza",
    "wof:name":"Ortiz Iba\u00f1ez Marina",
    "wof:placetype":"venue"
},
  "geometry": {"coordinates":[-0.8835729957,41.649772644],"type":"Point"}
}