{
  "type": "Feature",
  "properties": {
    "iso:country":"ES",
    "sg:address":"Calle de San Andres, 8",
    "sg:city":"Huelva",
    "sg:orig_category":"M\u00c9dicos: Dermatolog\u00cda Y Venereolog\u00cda",
    "sg:phone":"+34 959 24 48 40",
    "sg:postcode":"21004",
    "sg:province":"Huelva",
    "wof:name":"Saavedra Martin Victoria",
    "wof:placetype":"venue"
},
  "geometry": {"coordinates":[-6.9492278099,37.26039505],"type":"Point"}
}