{
  "type": "Feature",
  "properties": {
    "iso:country":"ES",
    "sg:address":"Carrer de Call, 7",
    "sg:city":"S. Feliu Guixols",
    "sg:orig_category":"Empresarios Y Productoras De Espect\u00c1culos",
    "sg:phone":"+34 972 32 22 75",
    "sg:postcode":"17220",
    "sg:province":"Girona",
    "wof:name":"Disco Mobil Va De So S.l",
    "wof:placetype":"venue"
},
  "geometry": {"coordinates":[3.0280179977,41.7806243896],"type":"Point"}
}