{
  "type": "Feature",
  "properties": {
    "addr:full":"C/ Santa Catalina Tomas, 9 Manacor Islas Baleares 07500",
    "addr:housenumber":"9",
    "addr:postcode":"07500",
    "addr:street":"C / Santa Catalina Tomas",
    "iso:country":"ES",
    "sg:address":"C/ Santa Catalina Tomas, 9",
    "sg:city":"Manacor",
    "sg:orig_category":"Empresas De Carpinter\u00cda",
    "sg:phone":"+34 971 55 00 70",
    "sg:postcode":"07500",
    "sg:province":"Islas Baleares",
    "wof:name":"Castor Pascual S.a.",
    "wof:placetype":"venue"
},
  "geometry": {"coordinates":[3.2031309605,39.5732192993],"type":"Point"}
}