{
  "type": "Feature",
  "properties": {
    "addr:full":"Calle de Castro De Oro, 5 Madrid Madrid 28019",
    "addr:housenumber":"5",
    "addr:postcode":"28019",
    "addr:street":"Calle De Castro De Oro",
    "iso:country":"ES",
    "sg:address":"Calle de Castro De Oro, 5",
    "sg:city":"Madrid",
    "sg:orig_category":"Peluquer\u00cdas, Peluquer\u00cda Mixta",
    "sg:phone":"+34 914 71 36 74",
    "sg:postcode":"28019",
    "sg:province":"Madrid",
    "wof:name":"Chen  Bin",
    "wof:placetype":"venue"
},
  "geometry": {"coordinates":[-3.7297415733,40.3892669678],"type":"Point"}
}