{
  "type": "Feature",
  "properties": {
    "addr:full":"Calle de Zurbaran, 8 Santa Maria Del Paramo Le\u00f3n 24240",
    "addr:housenumber":"8",
    "addr:postcode":"24240",
    "addr:street":"Calle De Zurbaran",
    "iso:country":"ES",
    "sg:address":"Calle de Zurbaran, 8",
    "sg:city":"Santa Maria Del Paramo",
    "sg:orig_category":"M\u00c1rmoles, Granitos Y Piedras Naturales",
    "sg:phone":"+34 987 35 06 47",
    "sg:postcode":"24240",
    "sg:province":"Le\u00f3n",
    "wof:name":"Garcia Garmon Abilio",
    "wof:placetype":"venue"
},
  "geometry": {"coordinates":[-5.7487740517,42.3562965393],"type":"Point"}
}