{
  "type": "Feature",
  "properties": {
    "addr:full":"Pase Victoria (de La), 35 Victoria C\u00f3rdoba 14140",
    "addr:housenumber":"35",
    "addr:postcode":"14140",
    "addr:street":"Victoria Co\u0301Rdoba",
    "iso:country":"ES",
    "sg:address":"Pase Victoria (de La), 35",
    "sg:city":"Victoria",
    "sg:orig_category":"Formaci\u00d3n Continuada (variada)",
    "sg:phone":"+34 957 30 82 24",
    "sg:postcode":"14140",
    "sg:province":"C\u00f3rdoba",
    "wof:name":"Maestre Maestre Antonio",
    "wof:placetype":"venue"
},
  "geometry": {"coordinates":[-4.8528242111,37.6821556091],"type":"Point"}
}