{
  "type": "Feature",
  "properties": {
    "iso:country":"ES",
    "sg:address":"Carr Pere Cavasequia, 21",
    "sg:city":"Lleida",
    "sg:orig_category":"Peluquer\u00cdas, Peluquer\u00cda Mixta",
    "sg:phone":"+34 973 22 16 47",
    "sg:postcode":"25005",
    "sg:province":"Lleida",
    "wof:name":"Lega Mur Anna",
    "wof:placetype":"venue"
},
  "geometry": {"coordinates":[0.6369540095,41.6218032837],"type":"Point"}
}