{
  "type": "Feature",
  "properties": {
    "iso:country":"ES",
    "sg:address":"Calle de Juan Ramon Jimenez, 43",
    "sg:city":"Algeciras",
    "sg:orig_category":"Empresarios",
    "sg:phone":"+34 956 60 47 76",
    "sg:postcode":"11207",
    "sg:province":"C\u00e1diz",
    "wof:name":"Sanchez Romero Jose Luis",
    "wof:placetype":"venue"
},
  "geometry": {"coordinates":[-5.4491882324,36.116268158],"type":"Point"}
}