{
  "type": "Feature",
  "properties": {
    "addr:full":"Calle de Juan De Mariana, 29 Sevilla Sevilla 41005",
    "addr:housenumber":"29",
    "addr:postcode":"41005",
    "addr:street":"Calle De Juan De Mariana",
    "iso:country":"ES",
    "sg:address":"Calle de Juan De Mariana, 29",
    "sg:city":"Sevilla",
    "sg:orig_category":"Droguer\u00cdas (al Por Menor)",
    "sg:phone":"+34 954 58 08 87",
    "sg:postcode":"41005",
    "sg:province":"Sevilla",
    "wof:name":"Pallares Alcaraz Eduardo",
    "wof:placetype":"venue"
},
  "geometry": {"coordinates":[-5.9616909027,37.3817405701],"type":"Point"}
}