{
  "type": "Feature",
  "properties": {
    "addr:full":"Calle de Molino De Viento (del), 33 Colmenar Viejo Madrid 28770",
    "addr:postcode":"28770",
    "addr:street":"Calle De Molino De Viento Del",
    "iso:country":"ES",
    "sg:address":"Calle de Molino De Viento (del), 33",
    "sg:city":"Colmenar Viejo",
    "sg:orig_category":"Electrodom\u00c9sticos (al Por Menor)",
    "sg:phone":"+34 918 46 25 64",
    "sg:postcode":"28770",
    "sg:province":"Madrid",
    "wof:name":"Pedro Luis Sanz Alvarez Y Otro C.b.",
    "wof:placetype":"venue"
},
  "geometry": {"coordinates":[-3.774561882,40.6632232666],"type":"Point"}
}