{
  "type": "Feature",
  "properties": {
    "iso:country":"ES",
    "sg:address":"Rua San Roque, 7",
    "sg:city":"Vilagarcia",
    "sg:orig_category":"Zapatos (al Por Menor)",
    "sg:phone":"+34 986 50 16 12",
    "sg:postcode":"36600",
    "sg:province":"Pontevedra",
    "wof:name":"Alegret Bouzon Maria Josefa",
    "wof:placetype":"venue"
},
  "geometry": {"coordinates":[-8.763261795,42.5946083069],"type":"Point"}
}