{
  "type": "Feature",
  "properties": {
    "iso:country":"ES",
    "sg:address":"Cami Cuixa (de La), 34",
    "sg:city":"Tarragona",
    "sg:orig_category":"Doctores En Medicina",
    "sg:phone":"+34 977 29 02 14",
    "sg:postcode":"43007",
    "sg:province":"Tarragona",
    "wof:name":"Sa\u00f1udo Santos Antonio",
    "wof:placetype":"venue"
},
  "geometry": {"coordinates":[1.2692400217,41.1192398071],"type":"Point"}
}