{
  "type": "Feature",
  "properties": {
    "addr:full":"Pdo Molina, 19 Alora M\u00e1laga 29500",
    "addr:housenumber":"19",
    "addr:postcode":"29500",
    "addr:street":"Molina;Ma\u0301Laga",
    "iso:country":"ES",
    "sg:address":"Pdo Molina, 19",
    "sg:city":"Alora",
    "sg:orig_category":"Fabricaci\u00d3n De Productos L\u00c1cteos Y Derivados",
    "sg:phone":"+34 952 49 55 12",
    "sg:postcode":"29500",
    "sg:province":"M\u00e1laga",
    "wof:name":"Hermanos Vargas Jimenez S.l.",
    "wof:placetype":"venue"
},
  "geometry": {"coordinates":[-4.6967186928,36.872303009],"type":"Point"}
}