{
  "type": "Feature",
  "properties": {
    "iso:country":"ES",
    "sg:address":"Calle de Santa Brigida, 9",
    "sg:city":"Teruel",
    "sg:orig_category":"Promotores Constructores",
    "sg:phone":"+34 978 61 76 46",
    "sg:postcode":"44003",
    "sg:province":"Teruel",
    "wof:name":"Valero Y Ramo S. L",
    "wof:placetype":"venue"
},
  "geometry": {"coordinates":[-1.102627039,40.3392562866],"type":"Point"}
}