{
  "type": "Feature",
  "properties": {
    "iso:country":"ES",
    "sg:address":"Avda Concordia, 65",
    "sg:city":"Tui",
    "sg:orig_category":"Alimentaci\u00d3n General (al Por Menor)",
    "sg:phone":"+34 986 60 39 73",
    "sg:postcode":"36700",
    "sg:province":"Pontevedra",
    "wof:name":"Martinez Cortegosa Manuel",
    "wof:placetype":"venue"
},
  "geometry": {"coordinates":[-8.6448440552,42.0485496521],"type":"Point"}
}