{
  "type": "Feature",
  "properties": {
    "addr:full":"Calle de Granada, 297 Almeria Almer\u00eda 04008",
    "addr:housenumber":"297",
    "addr:postcode":"04008",
    "addr:street":"Calle De Granada",
    "iso:country":"ES",
    "sg:address":"Calle de Granada, 297",
    "sg:city":"Almeria",
    "sg:orig_category":"Cajas De Ahorro",
    "sg:phone":"+34 950 23 98 22",
    "sg:postcode":"04008",
    "sg:province":"Almer\u00eda",
    "wof:name":"Unicaja",
    "wof:placetype":"venue"
},
  "geometry": {"coordinates":[-2.4544439316,36.8500938416],"type":"Point"}
}