{
  "type": "Feature",
  "properties": {
    "iso:country":"ES",
    "sg:address":"S. Vilarrasa, 19",
    "sg:city":"Besalu",
    "sg:orig_category":"Panader\u00cdas, Panader\u00cdas",
    "sg:phone":"+34 972 59 00 84",
    "sg:postcode":"17850",
    "sg:province":"Girona",
    "wof:name":"Surroca Costa Pedro",
    "wof:placetype":"venue"
},
  "geometry": {"coordinates":[2.7091920376,42.2370147705],"type":"Point"}
}