{
  "type": "Feature",
  "properties": {
    "addr:full":"Calle de Almacellas, 35 Binefar Huesca 22500",
    "addr:housenumber":"35",
    "addr:postcode":"22500",
    "addr:street":"Calle De Almacellas",
    "iso:country":"ES",
    "sg:address":"Calle de Almacellas, 35",
    "sg:city":"Binefar",
    "sg:orig_category":"Agricultores, Agricultores",
    "sg:phone":"+34 974 43 12 33",
    "sg:postcode":"22500",
    "sg:province":"Huesca",
    "wof:name":"Lazagon 2000 S.l.",
    "wof:placetype":"venue"
},
  "geometry": {"coordinates":[0.2958756983,41.8461456299],"type":"Point"}
}