{
  "type": "Feature",
  "properties": {
    "addr:full":"Cra. Riudoms, S/n Reus Tarragona 43205",
    "addr:housenumber":"s / n",
    "addr:postcode":"43205",
    "iso:country":"ES",
    "sg:address":"Cra. Riudoms, S/n",
    "sg:city":"Reus",
    "sg:orig_category":"Poller\u00cda Y Caza (al Por Menor)",
    "sg:phone":"+34 977 32 60 30",
    "sg:postcode":"43205",
    "sg:province":"Tarragona",
    "wof:name":"Maxim Borras S.a.",
    "wof:placetype":"venue"
},
  "geometry": {"coordinates":[1.0970150232,41.1530303955],"type":"Point"}
}