{
  "type": "Feature",
  "properties": {
    "iso:country":"ES",
    "sg:address":"Plaza Irailaren 23a, 2",
    "sg:city":"Erandio",
    "sg:orig_category":"Alimentaci\u00d3n General (al Por Menor)",
    "sg:phone":"+34 944 67 15 44",
    "sg:postcode":"48950",
    "sg:province":"Vizcaya",
    "wof:name":"Ana Maria Marquijano Urrecho",
    "wof:placetype":"venue"
},
  "geometry": {"coordinates":[-2.9758749008,43.3025283813],"type":"Point"}
}