{
  "type": "Feature",
  "properties": {
    "addr:full":"Carr Major Sant Jaume, 45 Villarreal Castell\u00f3n 12540",
    "addr:housenumber":"45",
    "addr:postcode":"12540",
    "addr:street":"Carr Major Sant Jaume",
    "iso:country":"ES",
    "sg:address":"Carr Major Sant Jaume, 45",
    "sg:city":"Villarreal",
    "sg:orig_category":"Bisuter\u00cda, Joyer\u00cda, Relojer\u00cda (al Por Menor)",
    "sg:phone":"+34 964 53 47 82",
    "sg:postcode":"12540",
    "sg:province":"Castell\u00f3n",
    "wof:name":"Vilosma S.l.",
    "wof:placetype":"venue"
},
  "geometry": {"coordinates":[-0.0994609967,39.9384498596],"type":"Point"}
}