{
  "type": "Feature",
  "properties": {
    "iso:country":"ES",
    "sg:address":"Osinaga Bailara, 49",
    "sg:city":"Osinaga",
    "sg:orig_category":"Cr\u00cda De Animales",
    "sg:phone":"+34 943 33 10 61",
    "sg:postcode":"20120",
    "sg:province":"Guip\u00f9zcoa",
    "wof:name":"Ceberio Zubiarrai Jose Ramon",
    "wof:placetype":"venue"
},
  "geometry": {"coordinates":[-1.9798289537,43.2647514343],"type":"Point"}
}