{
  "type": "Feature",
  "properties": {
    "addr:full":"Calle de San Faustino, 8 Madrid Madrid 28022",
    "addr:housenumber":"8",
    "addr:postcode":"madrid;28022",
    "addr:street":"Calle De San Faustino",
    "iso:country":"ES",
    "sg:address":"Calle de San Faustino, 8",
    "sg:city":"Madrid",
    "sg:orig_category":"Confecci\u00d3n (fabricaci\u00d3n, Al Por Mayor)",
    "sg:phone":"+34 917 41 12 28",
    "sg:postcode":"28022",
    "sg:province":"Madrid",
    "wof:name":"Gomez Sanchez Emilio Benito",
    "wof:placetype":"venue"
},
  "geometry": {"coordinates":[-3.6091508865,40.4469718933],"type":"Point"}
}