{
  "type": "Feature",
  "properties": {
    "iso:country":"ES",
    "sg:address":"Pase Doctor Gregorio Mara\u00d1on, 22",
    "sg:city":"Poligono Sta M. De Benquerencia",
    "sg:classifiers":[
        {
            "category":"Taxi",
            "type":"Transportation"
        }
    ],
    "sg:phone":"+34 925 23 06 84",
    "sg:postcode":"45007",
    "sg:province":"Toledo",
    "wof:name":"Perez Garcia Valentin",
    "wof:placetype":"venue"
},
  "geometry": {"coordinates":[-3.9474089146,39.8690643311],"type":"Point"}
}