{
  "type": "Feature",
  "properties": {
    "addr:full":"Barr Azurleku, 9 Bilbao Vizcaya 48004",
    "addr:housenumber":"9",
    "addr:postcode":"48004",
    "addr:street":"Azurleku",
    "iso:country":"ES",
    "sg:address":"Barr Azurleku, 9",
    "sg:city":"Bilbao",
    "sg:orig_category":"Alimentaci\u00d3n General (al Por Menor)",
    "sg:phone":"+34 944 11 74 30",
    "sg:postcode":"48004",
    "sg:province":"Vizcaya",
    "wof:name":"Pe\u00f1a Perez Dionisio",
    "wof:placetype":"venue"
},
  "geometry": {"coordinates":[-2.9096360207,43.2503585815],"type":"Point"}
}