{
  "type": "Feature",
  "properties": {
    "addr:full":"Calle de Berlin, 7 Torreciega Murcia 30392",
    "addr:housenumber":"7",
    "addr:postcode":"30392",
    "addr:street":"Calle De Berlin",
    "iso:country":"ES",
    "sg:address":"Calle de Berlin, 7",
    "sg:city":"Torreciega",
    "sg:orig_category":"Electricidad: Instaladores",
    "sg:phone":"+34 968 12 01 84",
    "sg:postcode":"30392",
    "sg:province":"Murcia",
    "wof:name":"Duly Electric S.a.",
    "wof:placetype":"venue"
},
  "geometry": {"coordinates":[-0.9641757011,37.6235923767],"type":"Point"}
}