{
  "type": "Feature",
  "properties": {
    "iso:country":"ES",
    "sg:address":"Calle de San Pedro, 19",
    "sg:city":"Cuenca",
    "sg:orig_category":"Artes Gr\u00c1ficas, Artes Pl\u00c1sticas (curso)",
    "sg:phone":"+34 969 23 72 50",
    "sg:postcode":"16001",
    "sg:province":"Cuenca",
    "wof:name":"Escuela De Arte",
    "wof:placetype":"venue"
},
  "geometry": {"coordinates":[-2.1295309067,40.0796661377],"type":"Point"}
}