{
  "type": "Feature",
  "properties": {
    "iso:country":"ES",
    "sg:address":"Carrer de Calderon De La Barca, 3",
    "sg:city":"Terrassa",
    "sg:orig_category":"Molduras, Junquillos, Listones Y Molduras Perforadas",
    "sg:phone":"+34 937 80 45 78",
    "sg:postcode":"08224",
    "sg:province":"Barcelona",
    "wof:name":"Perez Garcia Fermin",
    "wof:placetype":"venue"
},
  "geometry": {"coordinates":[1.9962110519,41.5560073853],"type":"Point"}
}