{
  "type": "Feature",
  "properties": {
    "addr:full":"Calle de Fray Luis Fuensalida, 14 Fuensalida Toledo 45510",
    "addr:housenumber":"14",
    "addr:postcode":"45510",
    "addr:street":"Calle De Fray Luis Fuensalida",
    "iso:country":"ES",
    "sg:address":"Calle de Fray Luis Fuensalida, 14",
    "sg:city":"Fuensalida",
    "sg:orig_category":"Bordado, Marcado A Medida",
    "sg:phone":"+34 925 73 00 41",
    "sg:postcode":"45510",
    "sg:province":"Toledo",
    "wof:name":"Bordados Fuensalida S.l.",
    "wof:placetype":"venue"
},
  "geometry": {"coordinates":[-4.2031011581,40.0510902405],"type":"Point"}
}