{
  "type": "Feature",
  "properties": {
    "addr:full":"Calle de Leon Y Castillo, 16 Arrecife Las Palmas 35500",
    "addr:housenumber":"16",
    "addr:postcode":"35500",
    "addr:street":"Calle De Leon Y Castillo",
    "iso:country":"ES",
    "sg:address":"Calle de Leon Y Castillo, 16",
    "sg:city":"Arrecife",
    "sg:orig_category":"Equitaci\u00d3n: Guarnicioner\u00cda, Equipo (al Por Menor)",
    "sg:phone":"+34 928 81 45 06",
    "sg:postcode":"35500",
    "sg:province":"Las Palmas",
    "wof:name":"Sarmiento Deniz Jose Antonio",
    "wof:placetype":"venue"
},
  "geometry": {"coordinates":[-13.5487318039,28.9595737457],"type":"Point"}
}