{
  "type": "Feature",
  "properties": {
    "iso:country":"ES",
    "sg:address":"Calle de Ramiro Ledesma, 1",
    "sg:city":"Socuellamos",
    "sg:orig_category":"Pescader\u00cdas (al Por Menor)",
    "sg:phone":"+34 926 53 20 09",
    "sg:postcode":"13630",
    "sg:province":"Ciudad Real",
    "wof:name":"Pescados Quico S.l.",
    "wof:placetype":"venue"
},
  "geometry": {"coordinates":[-2.7956092358,39.2843894958],"type":"Point"}
}