{
  "type": "Feature",
  "properties": {
    "iso:country":"ES",
    "sg:address":"Carr Sant Cristofol, 20",
    "sg:city":"Sueca",
    "sg:orig_category":"Agencias De Viajes",
    "sg:phone":"+34 961 71 05 75",
    "sg:postcode":"46410",
    "sg:province":"Valencia",
    "wof:name":"Viajes Barcelo S.l.",
    "wof:placetype":"venue"
},
  "geometry": {"coordinates":[-0.3118039966,39.2023162842],"type":"Point"}
}