{
  "type": "Feature",
  "properties": {
    "addr:full":"Calle de Gorrion, 20 Fuenlabrada Madrid 28946",
    "addr:housenumber":"20",
    "addr:postcode":"28946",
    "addr:street":"Calle De Gorrion",
    "iso:country":"ES",
    "sg:address":"Calle de Gorrion, 20",
    "sg:city":"Fuenlabrada",
    "sg:orig_category":"Muebles, Minoristas",
    "sg:phone":"+34 916 42 33 76",
    "sg:postcode":"28946",
    "sg:province":"Madrid",
    "wof:name":"Martin Gil Gregorio",
    "wof:placetype":"venue"
},
  "geometry": {"coordinates":[-3.7633390427,40.2566413879],"type":"Point"}
}