{
  "type": "Feature",
  "properties": {
    "iso:country":"ES",
    "sg:address":"Carrer de Sardenya, 437",
    "sg:city":"Barcelona",
    "sg:orig_category":"T\u00c9cnicos Veterinarios",
    "sg:phone":"+34 932 19 60 12",
    "sg:postcode":"08025",
    "sg:province":"Barcelona",
    "wof:name":"Castelar Castelar Jose Maria",
    "wof:placetype":"venue"
},
  "geometry": {"coordinates":[2.1665530205,41.4083480835],"type":"Point"}
}