{
  "type": "Feature",
  "properties": {
    "iso:country":"ES",
    "sg:address":"Ctra Marques De La Calzada, S/n",
    "sg:city":"Felipa",
    "sg:orig_category":"Promotores Constructores",
    "sg:phone":"+34 967 26 20 39",
    "sg:postcode":"02156",
    "sg:province":"Albacete",
    "wof:name":"Bernabe Briones S.l",
    "wof:placetype":"venue"
},
  "geometry": {"coordinates":[-1.7055939436,39.0387954712],"type":"Point"}
}