{
  "type": "Feature",
  "properties": {
    "iso:country":"ES",
    "sg:address":"Carrer de Ronda Boada Vell, 6",
    "sg:city":"Poligon Industrial Riera De Caldes",
    "sg:orig_category":"Ropa Y Art\u00cdculos Pre",
    "sg:phone":"+34 938 64 80 27",
    "sg:postcode":"08184",
    "sg:province":"Barcelona",
    "sg:website":"www.play.es",
    "wof:name":"Play S. A.",
    "wof:placetype":"venue"
},
  "geometry": {"coordinates":[2.1748530865,41.5814743042],"type":"Point"}
}