{
  "type": "Feature",
  "properties": {
    "iso:country":"ES",
    "sg:address":"Calle de Soria, 2",
    "sg:city":"Moron Frontera",
    "sg:orig_category":"Molduras, Junquillos, Listones Y Molduras Perforadas",
    "sg:phone":"+34 954 85 06 83",
    "sg:postcode":"41530",
    "sg:province":"Sevilla",
    "wof:name":"Galvan Berengeno Antonio",
    "wof:placetype":"venue"
},
  "geometry": {"coordinates":[-5.4615240097,37.1198616028],"type":"Point"}
}