{
  "type": "Feature",
  "properties": {
    "addr:full":"Calle de Escritor Ramirez Gongora, S/n Cordoba C\u00f3rdoba 14014",
    "addr:housenumber":"s / n",
    "addr:postcode":"14014",
    "addr:street":"Calle De Escritor Ramirez Gongora;Co\u0301Rdoba",
    "iso:country":"ES",
    "sg:address":"Calle de Escritor Ramirez Gongora, S/n",
    "sg:city":"Cordoba",
    "sg:orig_category":"Supermercados Y Hipermercados",
    "sg:phone":"+34 957 25 77 03",
    "sg:postcode":"14014",
    "sg:province":"C\u00f3rdoba",
    "wof:name":"Promotora De Detallistas De Alimentacion S.a.",
    "wof:placetype":"venue"
},
  "geometry": {"coordinates":[-4.7534041405,37.8939094543],"type":"Point"}
}