{
  "type": "Feature",
  "properties": {
    "iso:country":"ES",
    "sg:address":"Ptge Santa Catalina Sen, S/n",
    "sg:city":"Palma",
    "sg:orig_category":"Centros Empresariales",
    "sg:phone":"+34 971 71 52 15",
    "sg:postcode":"07002",
    "sg:province":"Islas Baleares",
    "wof:name":"Comunitel Global S.a.",
    "wof:placetype":"venue"
},
  "geometry": {"coordinates":[2.65239501,39.5749702454],"type":"Point"}
}