{
  "type": "Feature",
  "properties": {
    "iso:country":"ES",
    "sg:address":"Calle de Virgen De Lujan, 41",
    "sg:city":"Sevilla",
    "sg:orig_category":"Transportes Por Carretera: Lotes Completos, Mercanc\u00cdas Diversas",
    "sg:phone":"+34 954 27 56 15",
    "sg:postcode":"41011",
    "sg:province":"Sevilla",
    "wof:name":"Azusur S.l.",
    "wof:placetype":"venue"
},
  "geometry": {"coordinates":[-6.0018568039,37.3745651245],"type":"Point"}
}