{
  "type": "Feature",
  "properties": {
    "addr:full":"Av Montserrat, 4 Torello Barcelona 08570",
    "addr:housenumber":"4",
    "addr:postcode":"08570",
    "addr:street":"Av Montserrat",
    "iso:country":"ES",
    "sg:address":"Av Montserrat, 4",
    "sg:city":"Torello",
    "sg:orig_category":"Controles De Edificaci\u00d3n (construcci\u00d3n, Seguridad)",
    "sg:phone":"+34 938 59 51 96",
    "sg:postcode":"08570",
    "sg:province":"Barcelona",
    "wof:name":"Kauai Fusta S.l.",
    "wof:placetype":"venue"
},
  "geometry": {"coordinates":[2.2547769547,42.0520515442],"type":"Point"}
}