{
  "type": "Feature",
  "properties": {
    "addr:full":"Rua Gaivota, 12 Vigo Pontevedra 36205",
    "addr:housenumber":"12",
    "addr:postcode":"36205",
    "addr:street":"Rua Gaivota",
    "iso:country":"ES",
    "sg:address":"Rua Gaivota, 12",
    "sg:city":"Vigo",
    "sg:orig_category":"M\u00c1quinas De Escribir, M\u00c1quinas De Oficina (al Por Menor, Reparaci\u00d3n)",
    "sg:phone":"+34 986 25 07 05",
    "sg:postcode":"36205",
    "sg:province":"Pontevedra",
    "wof:name":"Fernandez Fernandez Antonio Enrique",
    "wof:placetype":"venue"
},
  "geometry": {"coordinates":[-8.7077941895,42.2253456116],"type":"Point"}
}