{
  "type": "Feature",
  "properties": {
    "addr:full":"Calle de Pinos, 43 Nieves Toledo 45190",
    "addr:housenumber":"43",
    "addr:postcode":"45190",
    "addr:street":"Calle De Pinos",
    "iso:country":"ES",
    "sg:address":"Calle de Pinos, 43",
    "sg:city":"Nieves",
    "sg:orig_category":"T\u00c9cnicos Veterinarios",
    "sg:phone":"+34 925 27 85 51",
    "sg:postcode":"45190",
    "sg:province":"Toledo",
    "wof:name":"Figuls Janer Jorge",
    "wof:placetype":"venue"
},
  "geometry": {"coordinates":[-3.9429790974,39.7946815491],"type":"Point"}
}