{
  "type": "Feature",
  "properties": {
    "iso:country":"ES",
    "sg:address":"Carr Aneto, 7",
    "sg:city":"Vielha",
    "sg:orig_category":"Empresas De Limpieza",
    "sg:phone":"+34 973 64 15 22",
    "sg:postcode":"25530",
    "sg:province":"Lleida",
    "wof:name":"House Aran S.c.p.",
    "wof:placetype":"venue"
},
  "geometry": {"coordinates":[0.793775022,42.70287323],"type":"Point"}
}