{
  "type": "Feature",
  "properties": {
    "addr:full":"Carrer de Roger De Flor, 18 Gava Barcelona 08850",
    "addr:housenumber":"18",
    "addr:postcode":"08850",
    "addr:street":"Carrer De Roger De Flor",
    "iso:country":"ES",
    "sg:address":"Carrer de Roger De Flor, 18",
    "sg:city":"Gava",
    "sg:orig_category":"Promotores Constructores",
    "sg:phone":"+34 936 38 15 99",
    "sg:postcode":"08850",
    "sg:province":"Barcelona",
    "wof:name":"Estructuras Jomar Baix Llobregat S.l.",
    "wof:placetype":"venue"
},
  "geometry": {"coordinates":[1.9972430468,41.3102226257],"type":"Point"}
}