{
  "type": "Feature",
  "properties": {
    "iso:country":"ES",
    "sg:address":"Barr Fuente Camacho, S/n",
    "sg:city":"Fuente Camacho",
    "sg:orig_category":"Explotaci\u00d3n De Canteras",
    "sg:phone":"+34 958 34 88 09",
    "sg:postcode":"18314",
    "sg:province":"Granada",
    "wof:name":"Ofitas El Paramo S.a.",
    "wof:placetype":"venue"
},
  "geometry": {"coordinates":[-4.2559690475,37.1000366211],"type":"Point"}
}