{
  "type": "Feature",
  "properties": {
    "addr:full":"Cra. Manresa-bassella, Km. 0005,7 S. Joan Vilatorrada Barcelona 08250",
    "addr:postcode":"08250",
    "addr:street":"Km. 0005,7 S. Joan Vilatorrada Barcelona",
    "iso:country":"ES",
    "sg:address":"Cra. Manresa-bassella, Km. 0005,7",
    "sg:city":"S. Joan Vilatorrada",
    "sg:orig_category":"Mataderos Y Talleres De Despiezado",
    "sg:phone":"+34 938 76 41 41",
    "sg:postcode":"08250",
    "sg:province":"Barcelona",
    "wof:name":"Matadero Comarcal Del Bages-sat",
    "wof:placetype":"venue"
},
  "geometry": {"coordinates":[1.8038949966,41.7427635193],"type":"Point"}
}