{
  "type": "Feature",
  "properties": {
    "addr:full":"Calle de Pedro Aragones, 10 Callosa Segura Alicante 03360",
    "addr:housenumber":"10",
    "addr:postcode":"03360",
    "addr:street":"Calle De Pedro Aragones",
    "iso:country":"ES",
    "sg:address":"Calle de Pedro Aragones, 10",
    "sg:city":"Callosa Segura",
    "sg:orig_category":"Carnicer\u00cdas, Carnicer\u00cdas",
    "sg:phone":"+34 965 31 01 69",
    "sg:postcode":"03360",
    "sg:province":"Alicante",
    "wof:name":"Martinez Cartagena Antonio",
    "wof:placetype":"venue"
},
  "geometry": {"coordinates":[-0.8781719804,38.1257781982],"type":"Point"}
}