{
  "type": "Feature",
  "properties": {
    "addr:full":"Calle de Jaizkibel, 19 Errenteria Guip\u00f9zcoa 20100",
    "addr:housenumber":"19",
    "addr:postcode":"20100",
    "addr:street":"Calle De Jaizkibel;Guipu\u0300Zcoa",
    "iso:country":"ES",
    "sg:address":"Calle de Jaizkibel, 19",
    "sg:city":"Errenteria",
    "sg:orig_category":"Peluqueros: De Se\u00d1oras",
    "sg:phone":"+34 943 52 94 52",
    "sg:postcode":"20100",
    "sg:province":"Guip\u00f9zcoa",
    "wof:name":"Maria Mar Blazquez Martin (peluqueria)",
    "wof:placetype":"venue"
},
  "geometry": {"coordinates":[-1.9123870134,43.3127479553],"type":"Point"}
}