{
  "type": "Feature",
  "properties": {
    "iso:country":"ES",
    "sg:address":"Madrid, Km. 0384,0",
    "sg:city":"Espinardo",
    "sg:orig_category":"Fabricaci\u00d3n De Motores El\u00c9ctricos",
    "sg:phone":"+34 968 30 64 11",
    "sg:postcode":"30100",
    "sg:province":"Murcia",
    "wof:name":"Segura Hernandez Pedro",
    "wof:placetype":"venue"
},
  "geometry": {"coordinates":[-1.153594017,38.0103034973],"type":"Point"}
}