{
  "type": "Feature",
  "properties": {
    "addr:full":"Carrer de L'espiga, 1 Barcelona Barcelona 08027",
    "addr:housenumber":"1",
    "addr:postcode":"08027",
    "addr:street":"Carrer De L'Espiga",
    "iso:country":"ES",
    "sg:address":"Carrer de L'espiga, 1",
    "sg:city":"Barcelona",
    "sg:orig_category":"Librer\u00cdas",
    "sg:phone":"+34 933 52 40 08",
    "sg:postcode":"08027",
    "sg:province":"Barcelona",
    "wof:name":"Biblaria S. Coop. C. Ltda.",
    "wof:placetype":"venue"
},
  "geometry": {"coordinates":[2.1796219349,41.4260253906],"type":"Point"}
}