{
  "type": "Feature",
  "properties": {
    "iso:country":"ES",
    "sg:address":"Av Torrent, D'es, 2",
    "sg:city":"Manacor",
    "sg:orig_category":"Art\u00cdculos De Decoraci\u00d3n",
    "sg:phone":"+34 971 55 98 59",
    "sg:postcode":"07500",
    "sg:province":"Islas Baleares",
    "wof:name":"Riera Barcelo,s.l",
    "wof:placetype":"venue"
},
  "geometry": {"coordinates":[3.2087171078,39.5662155151],"type":"Point"}
}