{
  "type": "Feature",
  "properties": {
    "addr:full":"Rbla Sant Jordi (de), 78 Ripollet Barcelona 08291",
    "addr:housenumber":"78",
    "addr:postcode":"08291",
    "addr:street":"Rbla Sant Jordi De",
    "iso:country":"ES",
    "sg:address":"Rbla Sant Jordi (de), 78",
    "sg:city":"Ripollet",
    "sg:orig_category":"Fabricaci\u00d3n De Productos Textiles Sin Tejer",
    "sg:phone":"+34 936 92 55 51",
    "sg:postcode":"08291",
    "sg:province":"Barcelona",
    "wof:name":"Pastor Chorda Maria Del Carmen",
    "wof:placetype":"venue"
},
  "geometry": {"coordinates":[2.162651062,41.4961547852],"type":"Point"}
}