{
  "type": "Feature",
  "properties": {
    "addr:full":"Calle de Lago Enol, 2 Lugo De Llanera Asturias 33690",
    "addr:housenumber":"2",
    "addr:postcode":"33690",
    "addr:street":"Calle De Lago Enol",
    "iso:country":"ES",
    "sg:address":"Calle de Lago Enol, 2",
    "sg:city":"Lugo De Llanera",
    "sg:orig_category":"Molduras, Junquillos, Listones Y Molduras Perforadas",
    "sg:phone":"+34 985 77 11 01",
    "sg:postcode":"33690",
    "sg:province":"Asturias",
    "wof:name":"Bar Sidreria Maite C.b.",
    "wof:placetype":"venue"
},
  "geometry": {"coordinates":[-5.8194169998,43.4427032471],"type":"Point"}
}