{
  "type": "Feature",
  "properties": {
    "addr:full":"Calle de Las Cuevas, S/n Moreda De Alava \u00c1lava 01314",
    "addr:housenumber":"s",
    "addr:postcode":"01314",
    "addr:street":"Calle De Las Cuevas;/ N;A\u0301Lava",
    "iso:country":"ES",
    "sg:address":"Calle de Las Cuevas, S/n",
    "sg:city":"Moreda De Alava",
    "sg:orig_category":"Ense\u00d1anza, Formaci\u00d3n Profesional: Aprendizaje",
    "sg:phone":"+34 945 60 18 93",
    "sg:postcode":"01314",
    "sg:province":"\u00c1lava",
    "wof:name":"Ayuntamiento De Moreda De Alava",
    "wof:placetype":"venue"
},
  "geometry": {"coordinates":[-2.407777071,42.5224685669],"type":"Point"}
}