{
  "type": "Feature",
  "properties": {
    "iso:country":"ES",
    "sg:address":"Avda Nueve De Octubre, 17",
    "sg:city":"Puerto",
    "sg:orig_category":"Mantenimiento Industrial",
    "sg:phone":"+34 962 67 28 11",
    "sg:postcode":"46520",
    "sg:province":"Valencia",
    "wof:name":"Emresa S.a.l.",
    "wof:placetype":"venue"
},
  "geometry": {"coordinates":[-0.2251600027,39.6608695984],"type":"Point"}
}