{
  "type": "Feature",
  "properties": {
    "iso:country":"ES",
    "sg:address":"Carr Maria Benlliure, De, 50",
    "sg:city":"Carcaixent",
    "sg:orig_category":"Aparatos E Instalaci\u00d3n De Regad\u00cdos",
    "sg:phone":"+34 962 43 12 35",
    "sg:postcode":"46740",
    "sg:province":"Valencia",
    "wof:name":"Enrique Vercher C.b.",
    "wof:placetype":"venue"
},
  "geometry": {"coordinates":[-0.4507440031,39.119430542],"type":"Point"}
}