{
  "type": "Feature",
  "properties": {
    "addr:full":"F. Malamonedilla, S/n Hontanar Toledo 45159",
    "addr:housenumber":"s / n",
    "addr:postcode":"45159",
    "addr:street":"F. Malamonedilla",
    "iso:country":"ES",
    "sg:address":"F. Malamonedilla, S/n",
    "sg:city":"Hontanar",
    "sg:orig_category":"Agricultura: Abastecimiento Y Cosechado (negocio)",
    "sg:phone":"+34 925 59 10 74",
    "sg:postcode":"45159",
    "sg:province":"Toledo",
    "wof:name":"Corporacion Villanueva S.a.",
    "wof:placetype":"venue"
},
  "geometry": {"coordinates":[-4.5001168251,39.6151733398],"type":"Point"}
}