{
  "type": "Feature",
  "properties": {
    "iso:country":"ES",
    "sg:address":"Luga Palmita (la), 3",
    "sg:city":"Lugarejo",
    "sg:orig_category":"Peluquer\u00cdas, Peluquer\u00cda Mixta",
    "sg:phone":"+34 928 35 42 35",
    "sg:postcode":"35300",
    "sg:province":"Las Palmas",
    "wof:name":"Canbepel S.l.",
    "wof:placetype":"venue"
},
  "geometry": {"coordinates":[-15.4988956451,28.0369472504],"type":"Point"}
}