{
  "type": "Feature",
  "properties": {
    "iso:country":"ES",
    "sg:address":"Carrer de Creu Coberta, 94",
    "sg:city":"Barcelona",
    "sg:orig_category":"Ropa Para Se\u00d1oras (al Por Menor)",
    "sg:phone":"+34 934 21 93 38",
    "sg:postcode":"08014",
    "sg:province":"Barcelona",
    "wof:name":"Martinez Laita Jordi",
    "wof:placetype":"venue"
},
  "geometry": {"coordinates":[2.1428859234,41.3754005432],"type":"Point"}
}