{
  "type": "Feature",
  "properties": {
    "addr:full":"El Calvario, 11 Los Llanos Aridane Santa Cruz De Tenerife 38760",
    "addr:housenumber":"11",
    "addr:postcode":"38760",
    "addr:street":"El Calvario",
    "iso:country":"ES",
    "sg:address":"El Calvario, 11",
    "sg:city":"Los Llanos Aridane",
    "sg:orig_category":"Centros Empresariales",
    "sg:phone":"+34 922 46 43 05",
    "sg:postcode":"38760",
    "sg:province":"Santa Cruz De Tenerife",
    "wof:name":"Confederacion De La Peque\u00d1a Y Mediana Empresa",
    "wof:placetype":"venue"
},
  "geometry": {"coordinates":[-17.9086284637,28.6585788727],"type":"Point"}
}