{
  "type": "Feature",
  "properties": {
    "addr:full":"Carrer de Doctor Dou, 4 Barcelona Barcelona 08001",
    "addr:housenumber":"4",
    "addr:postcode":"08001",
    "addr:street":"Carrer De Doctor Dou",
    "iso:country":"ES",
    "sg:address":"Carrer de Doctor Dou, 4",
    "sg:city":"Barcelona",
    "sg:orig_category":"Asociaciones, Organismos Culturales Y Socioeducativos",
    "sg:phone":"+34 933 01 67 03",
    "sg:postcode":"08001",
    "sg:province":"Barcelona",
    "wof:name":"La Xina Associacio Per L'art De Recerca Total",
    "wof:placetype":"venue"
},
  "geometry": {"coordinates":[2.1692800522,41.3823471069],"type":"Point"}
}