{
  "type": "Feature",
  "properties": {
    "iso:country":"ES",
    "sg:address":"Carr Francesc Camprodon, 24",
    "sg:city":"Santa Coloma De Farners",
    "sg:orig_category":"Agencias De Trabajo Temporal",
    "sg:phone":"+34 972 84 35 16",
    "sg:postcode":"17430",
    "sg:province":"Girona",
    "sg:website":"www.marlex.es",
    "wof:name":"Marlex Gestio Ett S. L.",
    "wof:placetype":"venue"
},
  "geometry": {"coordinates":[2.6689898968,41.8601913452],"type":"Point"}
}