{
  "type": "Feature",
  "properties": {
    "addr:full":"Avda Alfares (de Los), 12 Cuenca Cuenca 16002",
    "addr:housenumber":"12",
    "addr:postcode":"16002",
    "addr:street":"Avda Alfares De Los",
    "iso:country":"ES",
    "sg:address":"Avda Alfares (de Los), 12",
    "sg:city":"Cuenca",
    "sg:orig_category":"Abogados",
    "sg:phone":"+34 969 22 72 19",
    "sg:postcode":"16002",
    "sg:province":"Cuenca",
    "wof:name":"Gallen Matas Javier",
    "wof:placetype":"venue"
},
  "geometry": {"coordinates":[-2.138117075,40.0790863037],"type":"Point"}
}