{
  "type": "Feature",
  "properties": {
    "iso:country":"ES",
    "sg:address":"Donostia Ibilbidea, 106",
    "sg:city":"Astigarraga",
    "sg:orig_category":"Congelados: Productos Alimentarios (al Por Menor)",
    "sg:phone":"+34 943 33 08 28",
    "sg:postcode":"20115",
    "sg:province":"Guip\u00f9zcoa",
    "wof:name":"Susperregi S.l.",
    "wof:placetype":"venue"
},
  "geometry": {"coordinates":[-1.9528510571,43.2826347351],"type":"Point"}
}