{
  "type": "Feature",
  "properties": {
    "iso:country":"ES",
    "sg:address":"Calle de Miralcampo, 12",
    "sg:city":"Sese\u00e7a Nuevo",
    "sg:orig_category":"Molduras, Junquillos, Listones Y Molduras Perforadas",
    "sg:phone":"+34 918 93 67 47",
    "sg:postcode":"45224",
    "sg:province":"Toledo",
    "wof:name":"Vara Trompeta Jose Antonio De La",
    "wof:placetype":"venue"
},
  "geometry": {"coordinates":[-3.649739027,40.1083908081],"type":"Point"}
}