{
  "type": "Feature",
  "properties": {
    "addr:full":"Av Maria Fortuny, 70 Reus Tarragona 43203",
    "addr:housenumber":"70",
    "addr:postcode":"43203",
    "addr:street":"Av Maria Fortuny",
    "iso:country":"ES",
    "sg:address":"Av Maria Fortuny, 70",
    "sg:city":"Reus",
    "sg:orig_category":"Inmobiliaria (agencias)",
    "sg:phone":"+34 977 34 60 11",
    "sg:postcode":"43203",
    "sg:province":"Tarragona",
    "wof:name":"Inbamar S.l.",
    "wof:placetype":"venue"
},
  "geometry": {"coordinates":[1.1151930094,41.1604957581],"type":"Point"}
}