{
  "type": "Feature",
  "properties": {
    "addr:full":"Carrer de Gosol, 15 Barcelona Barcelona 08017",
    "addr:housenumber":"15",
    "addr:postcode":"08017",
    "addr:street":"Carrer De Gosol",
    "iso:country":"ES",
    "sg:address":"Carrer de Gosol, 15",
    "sg:city":"Barcelona",
    "sg:orig_category":"Alumbrados",
    "sg:phone":"+34 934 58 19 48",
    "sg:postcode":"08017",
    "sg:province":"Barcelona",
    "wof:name":"Compta Il.luminacio S.l.",
    "wof:placetype":"venue"
},
  "geometry": {"coordinates":[2.1282000542,41.396068573],"type":"Point"}
}