{
  "type": "Feature",
  "properties": {
    "addr:full":"Calle de Miguel Martin, 5 Algeciras C\u00e1diz 11201",
    "addr:housenumber":"5;ca\u0301diz",
    "addr:postcode":"11201",
    "addr:street":"Calle De Miguel Martin",
    "iso:country":"ES",
    "sg:address":"Calle de Miguel Martin, 5",
    "sg:city":"Algeciras",
    "sg:orig_category":"M\u00c9dicos: Estomatolog\u00cda",
    "sg:phone":"+34 956 63 37 70",
    "sg:postcode":"11201",
    "sg:province":"C\u00e1diz",
    "wof:name":"Rubio Diaz Rafael",
    "wof:placetype":"venue"
},
  "geometry": {"coordinates":[-5.4466238022,36.1279907227],"type":"Point"}
}