{
  "type": "Feature",
  "properties": {
    "iso:country":"ES",
    "sg:address":"Calle de Jorge Juan, 114",
    "sg:city":"Madrid",
    "sg:orig_category":"Confiter\u00cdas, Chocolater\u00cdas (al Por Menor)",
    "sg:phone":"+34 914 09 78 49",
    "sg:postcode":"28028",
    "sg:province":"Madrid",
    "wof:name":"Garcia Anton Agustin Benito",
    "wof:placetype":"venue"
},
  "geometry": {"coordinates":[-3.666590929,40.4226989746],"type":"Point"}
}