{
  "type": "Feature",
  "properties": {
    "iso:country":"ES",
    "sg:address":"Valtierra, 20",
    "sg:city":"Iru\u00f1a",
    "sg:orig_category":"Farmacias",
    "sg:phone":"+34 948 12 90 26",
    "sg:postcode":"31015",
    "sg:province":"Navarra",
    "wof:name":"Irizar Giral Maria Josefa De",
    "wof:placetype":"venue"
},
  "geometry": {"coordinates":[-1.6275219917,42.8341064453],"type":"Point"}
}