{
  "type": "Feature",
  "properties": {
    "iso:country":"ES",
    "sg:address":"Avda Galicia (de), 5",
    "sg:city":"Viveiro",
    "sg:orig_category":"Empresas De Electricidad En General",
    "sg:phone":"+34 982 56 31 21",
    "sg:postcode":"27850",
    "sg:province":"Lugo",
    "wof:name":"Diaz Perez Maria Del Carmen",
    "wof:placetype":"venue"
},
  "geometry": {"coordinates":[-7.5956959724,43.663066864],"type":"Point"}
}