{
  "type": "Feature",
  "properties": {
    "iso:country":"ES",
    "sg:address":"Calle de Joaquin Costa, 2",
    "sg:city":"San Lorenzo De El Escorial",
    "sg:orig_category":"Abogados",
    "sg:phone":"+34 918 90 48 14",
    "sg:postcode":"28200",
    "sg:province":"Madrid",
    "wof:name":"Torres Sanchez Isabel",
    "wof:placetype":"venue"
},
  "geometry": {"coordinates":[-4.1475849152,40.5916786194],"type":"Point"}
}