{
  "type": "Feature",
  "properties": {
    "iso:country":"ES",
    "sg:address":"Plaz Constitucion, 14",
    "sg:city":"Riba-roja Turia",
    "sg:orig_category":"Inform\u00c1tica (estudios, Servicios, Asesor\u00cda, Formaci\u00d3n)",
    "sg:phone":"+34 961 65 30 05",
    "sg:postcode":"46190",
    "sg:province":"Valencia",
    "sg:website":"www.redestebe.es/cemac",
    "wof:name":"Cemac Ordenadores S.l.",
    "wof:placetype":"venue"
},
  "geometry": {"coordinates":[-0.5698940158,39.5458450317],"type":"Point"}
}