{
  "type": "Feature",
  "properties": {
    "addr:full":"Calle de Lope De Vega, 14 Palencia Palencia 34001",
    "addr:housenumber":"14",
    "addr:postcode":"34001",
    "addr:street":"Calle De Lope De Vega",
    "iso:country":"ES",
    "sg:address":"Calle de Lope De Vega, 14",
    "sg:city":"Palencia",
    "sg:orig_category":"Asistencia Y Consejos",
    "sg:phone":"+34 979 74 58 26",
    "sg:postcode":"34001",
    "sg:province":"Palencia",
    "wof:name":"Antolin De La Hoz Salvador",
    "wof:placetype":"venue"
},
  "geometry": {"coordinates":[-4.5313539505,42.0127067566],"type":"Point"}
}