{
  "type": "Feature",
  "properties": {
    "addr:full":"Calle de Santa Clara, 12 Zamora Zamora 49003",
    "addr:housenumber":"12",
    "addr:postcode":"49003",
    "addr:street":"Calle De Santa Clara",
    "iso:country":"ES",
    "sg:address":"Calle de Santa Clara, 12",
    "sg:city":"Zamora",
    "sg:orig_category":"Ropa Para Se\u00d1oras Y Caballeros (al Por Menor)",
    "sg:phone":"+34 980 53 18 28",
    "sg:postcode":"49003",
    "sg:province":"Zamora",
    "wof:name":"Gonzalez Y Lavin S. A.",
    "wof:placetype":"venue"
},
  "geometry": {"coordinates":[-5.743543148,41.5051765442],"type":"Point"}
}