{
  "type": "Feature",
  "properties": {
    "addr:full":"Mcdo Abastos, S/n Castello Plana Castell\u00f3n 12006",
    "addr:housenumber":"s / n",
    "addr:postcode":"12006",
    "addr:street":"Castello\u0301N",
    "iso:country":"ES",
    "sg:address":"Mcdo Abastos, S/n",
    "sg:city":"Castello Plana",
    "sg:orig_category":"Frutas Y Legumbres Frescas (al Por Mayor)",
    "sg:phone":"+34 964 73 05 29",
    "sg:postcode":"12006",
    "sg:province":"Castell\u00f3n",
    "wof:name":"Ribelles Tel Jose",
    "wof:placetype":"venue"
},
  "geometry": {"coordinates":[-0.1292939931,40.0168533325],"type":"Point"}
}