{
  "type": "Feature",
  "properties": {
    "iso:country":"ES",
    "sg:address":"Calle de Santa Ana, 13",
    "sg:city":"Puebla Almoradiel",
    "sg:orig_category":"Electricidad: Instaladores",
    "sg:phone":"+34 925 17 82 67",
    "sg:postcode":"45840",
    "sg:province":"Toledo",
    "wof:name":"Instanive S.l.",
    "wof:placetype":"venue"
},
  "geometry": {"coordinates":[-3.1163380146,39.6001625061],"type":"Point"}
}