{
  "type": "Feature",
  "properties": {
    "addr:full":"Rond Pilar, 8 Badajoz Badajoz 06002",
    "addr:housenumber":"8",
    "addr:postcode":"06002",
    "addr:street":"Pilar",
    "iso:country":"ES",
    "sg:address":"Rond Pilar, 8",
    "sg:city":"Badajoz",
    "sg:orig_category":"Asociaciones, Organismos Culturales Y Socioeducativos",
    "sg:phone":"+34 924 23 59 02",
    "sg:postcode":"06002",
    "sg:province":"Badajoz",
    "wof:name":"Asociacion De Coros Y Danzas De Badajoz",
    "wof:placetype":"venue"
},
  "geometry": {"coordinates":[-6.9678902626,38.877696991],"type":"Point"}
}