{
  "type": "Feature",
  "properties": {
    "addr:full":"Plaz Santo Domingo (de), 4 Granada Granada 18009",
    "addr:postcode":"18009",
    "iso:country":"ES",
    "sg:address":"Plaz Santo Domingo (de), 4",
    "sg:city":"Granada",
    "sg:orig_category":"Ense\u00d1anza Superior Privada",
    "sg:phone":"+34 958 22 97 52",
    "sg:postcode":"18009",
    "sg:province":"Granada",
    "wof:name":"Colegio Mayor Femenino Santo Domingo",
    "wof:placetype":"venue"
},
  "geometry": {"coordinates":[-3.5955269337,37.1735267639],"type":"Point"}
}