{
  "type": "Feature",
  "properties": {
    "addr:full":"C/ Manuel De Falla, 44 Salt Girona 17190",
    "addr:housenumber":"44",
    "addr:postcode":"17190",
    "addr:street":"C / Manuel De Falla",
    "iso:country":"ES",
    "sg:address":"C/ Manuel De Falla, 44",
    "sg:city":"Salt",
    "sg:orig_category":"Librer\u00cdas",
    "sg:phone":"+34 972 23 11 88",
    "sg:postcode":"17190",
    "sg:province":"Girona",
    "wof:name":"Palahi Figueras Montserrat",
    "wof:placetype":"venue"
},
  "geometry": {"coordinates":[2.7922170162,41.9762840271],"type":"Point"}
}