{
  "type": "Feature",
  "properties": {
    "addr:full":"Av Francesc Macia, 60 Vilanova I La Geltru Barcelona 08800",
    "addr:housenumber":"60",
    "addr:postcode":"08800",
    "addr:street":"Av Francesc Macia",
    "iso:country":"ES",
    "sg:address":"Av Francesc Macia, 60",
    "sg:city":"Vilanova I La Geltru",
    "sg:orig_category":"M\u00c9dicos: Estomatolog\u00cda",
    "sg:phone":"+34 938 93 70 70",
    "sg:postcode":"08800",
    "sg:province":"Barcelona",
    "wof:name":"Luna Bertran Raul",
    "wof:placetype":"venue"
},
  "geometry": {"coordinates":[1.7211259604,41.2228507996],"type":"Point"}
}