{
  "type": "Feature",
  "properties": {
    "addr:full":"Calle de Alonso De Ojeda, 16 Algeciras C\u00e1diz 11207",
    "addr:housenumber":"16;ca\u0301diz",
    "addr:postcode":"11207",
    "addr:street":"Calle De Alonso De Ojeda",
    "iso:country":"ES",
    "sg:address":"Calle de Alonso De Ojeda, 16",
    "sg:city":"Algeciras",
    "sg:orig_category":"Reposter\u00cdas",
    "sg:phone":"+34 956 60 44 50",
    "sg:postcode":"11207",
    "sg:province":"C\u00e1diz",
    "wof:name":"Horno La Milagrosa S.l.",
    "wof:placetype":"venue"
},
  "geometry": {"coordinates":[-5.4465870857,36.1178894043],"type":"Point"}
}