{
  "type": "Feature",
  "properties": {
    "iso:country":"ES",
    "sg:address":"Calle de Prim, 53",
    "sg:city":"Torreperogil",
    "sg:orig_category":"Mec\u00c1nico Del Autom\u00d3vil",
    "sg:phone":"+34 953 77 69 40",
    "sg:postcode":"23320",
    "sg:province":"Ja\u00e9n",
    "wof:name":"Automantenimiento Guerrero S. L.",
    "wof:placetype":"venue"
},
  "geometry": {"coordinates":[-3.2846496105,38.0373535156],"type":"Point"}
}