{
  "type": "Feature",
  "properties": {
    "iso:country":"ES",
    "sg:address":"Calle de Fray Junipero Serra, 13",
    "sg:city":"Alhama Murcia",
    "sg:orig_category":"Promotores Constructores",
    "sg:phone":"+34 968 63 02 73",
    "sg:postcode":"30840",
    "sg:province":"Murcia",
    "wof:name":"Copadul S.l.",
    "wof:placetype":"venue"
},
  "geometry": {"coordinates":[-1.4225850105,37.8483772278],"type":"Point"}
}