{
  "type": "Feature",
  "properties": {
    "addr:full":"Av Catalunya, 37 Anglesola Lleida 25320",
    "addr:housenumber":"37",
    "addr:postcode":"25320",
    "addr:street":"Av Catalunya",
    "iso:country":"ES",
    "sg:address":"Av Catalunya, 37",
    "sg:city":"Anglesola",
    "sg:orig_category":"Sanatorios M\u00c9dico",
    "sg:phone":"+34 973 30 82 54",
    "sg:postcode":"25320",
    "sg:province":"Lleida",
    "wof:name":"Ajuntament D'anglesola",
    "wof:placetype":"venue"
},
  "geometry": {"coordinates":[1.0831139088,41.6571540833],"type":"Point"}
}