{
  "type": "Feature",
  "properties": {
    "addr:full":"Carrer de Jaume Huguet, 13 Valls Tarragona 43800",
    "addr:housenumber":"13",
    "addr:postcode":"43800",
    "addr:street":"Carrer De Jaume Huguet",
    "iso:country":"ES",
    "sg:address":"Carrer de Jaume Huguet, 13",
    "sg:city":"Valls",
    "sg:orig_category":"Ropa Para Se\u00d1oras Y Caballeros (al Por Menor)",
    "sg:phone":"+34 977 60 54 97",
    "sg:postcode":"43800",
    "sg:province":"Tarragona",
    "wof:name":"Bardina Saperas Jose",
    "wof:placetype":"venue"
},
  "geometry": {"coordinates":[1.2508009672,41.2864303589],"type":"Point"}
}