{
  "type": "Feature",
  "properties": {
    "addr:full":"Pol. Ind. Erletxes, 115 Gumuzio Vizcaya 48960",
    "addr:housenumber":"115",
    "addr:postcode":"48960",
    "addr:street":"Erletxes;Vizcaya",
    "iso:country":"ES",
    "sg:address":"Pol. Ind. Erletxes, 115",
    "sg:city":"Gumuzio",
    "sg:orig_category":"Centros Empresariales",
    "sg:phone":"+34 944 56 70 53",
    "sg:postcode":"48960",
    "sg:province":"Vizcaya",
    "wof:name":"Vitrame S.l.",
    "wof:placetype":"venue"
},
  "geometry": {"coordinates":[-2.8133413792,43.2343292236],"type":"Point"}
}