{
  "type": "Feature",
  "properties": {
    "iso:country":"ES",
    "sg:address":"Gipuzkoa Kalea, 64",
    "sg:city":"Zarautz",
    "sg:orig_category":"Alimentaci\u00d3n General (al Por Menor)",
    "sg:phone":"+34 943 83 07 93",
    "sg:postcode":"20800",
    "sg:province":"Guip\u00f9zcoa",
    "wof:name":"Maria Garrastazu Aranguren Y Otros C.b.",
    "wof:placetype":"venue"
},
  "geometry": {"coordinates":[-2.1612610817,43.284576416],"type":"Point"}
}