{
  "type": "Feature",
  "properties": {
    "iso:country":"ES",
    "sg:address":"Calle de Sevilla, 86",
    "sg:city":"Ronda",
    "sg:orig_category":"Agencias Y Agentes Comerciales, Representantes",
    "sg:phone":"+34 952 87 40 28",
    "sg:postcode":"29400",
    "sg:province":"M\u00e1laga",
    "wof:name":"Calvo Ruiz Matilde",
    "wof:placetype":"venue"
},
  "geometry": {"coordinates":[-5.1668009758,36.7462310791],"type":"Point"}
}