{
  "type": "Feature",
  "properties": {
    "iso:country":"ES",
    "sg:address":"Via Augusta, 13",
    "sg:city":"Barcelona",
    "sg:orig_category":"Artes Gr\u00c1ficas, Artes Pl\u00c1sticas (curso)",
    "sg:phone":"+34 934 15 07 99",
    "sg:postcode":"08006",
    "sg:province":"Barcelona",
    "wof:name":"Giesa Export S.l.",
    "wof:placetype":"venue"
},
  "geometry": {"coordinates":[2.1547160149,41.3967475891],"type":"Point"}
}