{
  "type": "Feature",
  "properties": {
    "iso:country":"ES",
    "sg:address":"Carrer de Breton, 21",
    "sg:city":"Terrassa",
    "sg:orig_category":"Estancos",
    "sg:phone":"+34 937 88 37 71",
    "sg:postcode":"08224",
    "sg:province":"Barcelona",
    "wof:name":"Ferrer Carol Montserrat",
    "wof:placetype":"venue"
},
  "geometry": {"coordinates":[2.0008230209,41.5672912598],"type":"Point"}
}