{
  "type": "Feature",
  "properties": {
    "iso:country":"ES",
    "sg:address":"Calle de Padilla, 39",
    "sg:city":"Madrid",
    "sg:orig_category":"Inmobiliaria (agencias)",
    "sg:phone":"+34 913 09 66 88",
    "sg:postcode":"28006",
    "sg:province":"Madrid",
    "wof:name":"Poscam Gestion Inmobiliaria S.l.",
    "wof:placetype":"venue"
},
  "geometry": {"coordinates":[-3.6771600246,40.4313774109],"type":"Point"}
}