{
  "type": "Feature",
  "properties": {
    "addr:full":"Calle de Santa Maria Magdalena, 24 Madrid Madrid 28016",
    "addr:housenumber":"24",
    "addr:postcode":"madrid;28016",
    "addr:street":"Calle De Santa;Magdalena",
    "iso:country":"ES",
    "sg:address":"Calle de Santa Maria Magdalena, 24",
    "sg:city":"Madrid",
    "sg:orig_category":"Abogados",
    "sg:phone":"+34 913 59 86 85",
    "sg:postcode":"28016",
    "sg:province":"Madrid",
    "wof:name":"Valero De La Parra Ramon",
    "wof:placetype":"venue"
},
  "geometry": {"coordinates":[-3.6708199978,40.4644737244],"type":"Point"}
}