{
  "type": "Feature",
  "properties": {
    "iso:country":"ES",
    "sg:address":"Calle de Mariano Gonzalez Bartolome, 11",
    "sg:city":"Riaza",
    "sg:orig_category":"Pescader\u00cdas (al Por Menor)",
    "sg:phone":"+34 921 55 03 83",
    "sg:postcode":"40500",
    "sg:province":"Segovia",
    "wof:name":"Lloret Sierra Margaret",
    "wof:placetype":"venue"
},
  "geometry": {"coordinates":[-3.4786567688,41.27866745],"type":"Point"}
}