{
  "type": "Feature",
  "properties": {
    "addr:full":"Calle de San Francisco, 39 Aranda Duero Burgos 09400",
    "addr:housenumber":"39",
    "addr:postcode":"09400",
    "addr:street":"Calle De San Francisco",
    "iso:country":"ES",
    "sg:address":"Calle de San Francisco, 39",
    "sg:city":"Aranda Duero",
    "sg:orig_category":"Distribuci\u00d3n De Petr\u00d3leo Y Derivados",
    "sg:phone":"+34 947 50 10 36",
    "sg:postcode":"09400",
    "sg:province":"Burgos",
    "wof:name":"El Fronton De Alcher S.l.",
    "wof:placetype":"venue"
},
  "geometry": {"coordinates":[-3.6860671043,41.6750450134],"type":"Point"}
}