{
  "type": "Feature",
  "properties": {
    "addr:full":"Avda Madrid (de), S/n Jaen Ja\u00e9n 23008",
    "addr:postcode":"23008",
    "addr:street":"Avda Madrid De S / N Jaen Jae\u0301N",
    "iso:country":"ES",
    "sg:address":"Avda Madrid (de), S/n",
    "sg:city":"Jaen",
    "sg:orig_category":"Universidades",
    "sg:phone":"+34 953 28 14 25",
    "sg:postcode":"23008",
    "sg:province":"Ja\u00e9n",
    "wof:name":"Universidad De Jaen",
    "wof:placetype":"venue"
},
  "geometry": {"coordinates":[-3.785474062,37.7762336731],"type":"Point"}
}