{
  "type": "Feature",
  "properties": {
    "iso:country":"ES",
    "sg:address":"Pase Maritimo Ciudad De Melilla, 17",
    "sg:city":"Malaga",
    "sg:orig_category":"Geolog\u00cda Y Geof\u00cdsica",
    "sg:phone":"+34 952 21 09 41",
    "sg:postcode":"29016",
    "sg:province":"M\u00e1laga",
    "wof:name":"Cabanas Cordoba Rafael",
    "wof:placetype":"venue"
},
  "geometry": {"coordinates":[-4.4113669395,36.7169952393],"type":"Point"}
}