{
  "type": "Feature",
  "properties": {
    "addr:full":"Calle de Estrella, 24 Coru\u00d1a La Coru\u00f1a 15003",
    "addr:housenumber":"24",
    "addr:postcode":"15003",
    "addr:street":"Calle De Estrella;La Corun\u0303A",
    "iso:country":"ES",
    "sg:address":"Calle de Estrella, 24",
    "sg:city":"Coru\u00d1a",
    "sg:orig_category":"Peluqueros: De Se\u00d1oras",
    "sg:phone":"+34 981 22 95 69",
    "sg:postcode":"15003",
    "sg:province":"La Coru\u00f1a",
    "wof:name":"Mendez Lopez Olga",
    "wof:placetype":"venue"
},
  "geometry": {"coordinates":[-8.4037151337,43.3687019348],"type":"Point"}
}