{
  "type": "Feature",
  "properties": {
    "addr:full":"Calle de Maestro Guridi, 3 Torrejon Ardoz Madrid 28850",
    "addr:housenumber":"3",
    "addr:postcode":"28850",
    "addr:street":"Calle De Maestro Guridi",
    "iso:country":"ES",
    "sg:address":"Calle de Maestro Guridi, 3",
    "sg:city":"Torrejon Ardoz",
    "sg:orig_category":"Molduras, Junquillos, Listones Y Molduras Perforadas",
    "sg:phone":"+34 916 76 44 69",
    "sg:postcode":"28850",
    "sg:province":"Madrid",
    "wof:name":"Moreno Rodriguez Juana Manuela",
    "wof:placetype":"venue"
},
  "geometry": {"coordinates":[-3.4883959293,40.4588737488],"type":"Point"}
}