{
  "type": "Feature",
  "properties": {
    "iso:country":"ES",
    "sg:address":"B(pol Ind Oeste), S/n",
    "sg:city":"S. Gines",
    "sg:orig_category":"Quincaller\u00cda (fabricaci\u00d3n)",
    "sg:phone":"+34 968 88 22 34",
    "sg:postcode":"30169",
    "sg:province":"Murcia",
    "wof:name":"Hurtado Suministros S.l.",
    "wof:placetype":"venue"
},
  "geometry": {"coordinates":[-1.1817729473,37.9517326355],"type":"Point"}
}