{
  "type": "Feature",
  "properties": {
    "iso:country":"ES",
    "sg:address":"Avda Luxemburgo, S/n",
    "sg:city":"Eurovillas-las Villas",
    "sg:orig_category":"Peluqueros: De Se\u00d1oras",
    "sg:phone":"+34 918 72 55 94",
    "sg:postcode":"28514",
    "sg:province":"Madrid",
    "wof:name":"Roncero Carrondo Monica",
    "wof:placetype":"venue"
},
  "geometry": {"coordinates":[-3.2648088932,40.3544883728],"type":"Point"}
}