{
  "type": "Feature",
  "properties": {
    "iso:country":"ES",
    "sg:address":"Calle de Andres Mellado, 61",
    "sg:city":"Madrid",
    "sg:orig_category":"Art\u00cdculos De Regalo (al Por Menor)",
    "sg:phone":"+34 915 43 93 63",
    "sg:postcode":"28015",
    "sg:province":"Madrid",
    "wof:name":"Bazar India Asociados C.b.",
    "wof:placetype":"venue"
},
  "geometry": {"coordinates":[-3.7143518925,40.4379272461],"type":"Point"}
}