{
  "type": "Feature",
  "properties": {
    "addr:full":"Calle de Matahacas, 37 Montellano Sevilla 41770",
    "addr:housenumber":"37",
    "addr:postcode":"41770",
    "addr:street":"Calle De Matahacas",
    "iso:country":"ES",
    "sg:address":"Calle de Matahacas, 37",
    "sg:city":"Montellano",
    "sg:orig_category":"Cervezas (negociantes Y Depositarios)",
    "sg:phone":"+34 954 87 51 49",
    "sg:postcode":"41770",
    "sg:province":"Sevilla",
    "wof:name":"Francisco Jose Alvarez Gonzalezs.l.",
    "wof:placetype":"venue"
},
  "geometry": {"coordinates":[-5.574048996,36.9939117432],"type":"Point"}
}