{
  "type": "Feature",
  "properties": {
    "iso:country":"ES",
    "sg:address":"Calle de Padre Lucas, 13",
    "sg:city":"Calahorra",
    "sg:orig_category":"Centros Empresariales",
    "sg:phone":"+34 941 13 06 81",
    "sg:postcode":"26500",
    "sg:province":"La Rioja",
    "wof:name":"Royo Ochoa Alicia",
    "wof:placetype":"venue"
},
  "geometry": {"coordinates":[-1.9648770094,42.3054161072],"type":"Point"}
}