{
  "type": "Feature",
  "properties": {
    "iso:country":"ES",
    "sg:address":"Calle de Ricardo San Juan, 26",
    "sg:city":"Madrid",
    "sg:orig_category":"Centros Empresariales",
    "sg:phone":"+34 913 88 06 66",
    "sg:postcode":"28043",
    "sg:province":"Madrid",
    "wof:name":"Hemag S.a",
    "wof:placetype":"venue"
},
  "geometry": {"coordinates":[-3.6536250114,40.4655342102],"type":"Point"}
}