{
  "type": "Feature",
  "properties": {
    "iso:country":"ES",
    "sg:address":"Plaz Hispanidad (de La), 8",
    "sg:city":"Villar Olalla",
    "sg:orig_category":"Ense\u00d1anza, Formaci\u00d3n Profesional: Aprendizaje",
    "sg:phone":"+34 969 26 15 09",
    "sg:postcode":"16196",
    "sg:province":"Cuenca",
    "wof:name":"Ayuntamiento De Villar De Olalla-secretaria",
    "wof:placetype":"venue"
},
  "geometry": {"coordinates":[-2.1362042427,40.0716171265],"type":"Point"}
}