{
  "type": "Feature",
  "properties": {
    "iso:country":"ES",
    "sg:address":"Calle de Ricardo Ortiz, 62",
    "sg:city":"Madrid",
    "sg:orig_category":"Carnicer\u00cdas, Carnicer\u00cdas",
    "sg:phone":"+34 913 55 33 08",
    "sg:postcode":"28017",
    "sg:province":"Madrid",
    "wof:name":"Carrera Prieto Alejandro",
    "wof:placetype":"venue"
},
  "geometry": {"coordinates":[-3.6587181091,40.4253425598],"type":"Point"}
}