{
  "type": "Feature",
  "properties": {
    "iso:country":"ES",
    "sg:address":"Carrer de Eusebi Guell, 8",
    "sg:city":"S. Boi Llobregat",
    "sg:orig_category":"Zapatos (al Por Menor)",
    "sg:phone":"+34 936 30 73 52",
    "sg:postcode":"08830",
    "sg:province":"Barcelona",
    "wof:name":"Martin Bou Jaume",
    "wof:placetype":"venue"
},
  "geometry": {"coordinates":[2.0354409218,41.3480072021],"type":"Point"}
}