{
  "type": "Feature",
  "properties": {
    "iso:country":"ES",
    "sg:address":"Calle de Leganes (de), 52",
    "sg:city":"Fuenlabrada",
    "sg:orig_category":"Droguer\u00cdas (al Por Menor)",
    "sg:phone":"+34 916 06 45 22",
    "sg:postcode":"28945",
    "sg:province":"Madrid",
    "wof:name":"Nicolas Jimenez Blazquez S.l.",
    "wof:placetype":"venue"
},
  "geometry": {"coordinates":[-3.7907390594,40.2913780212],"type":"Point"}
}