{
  "type": "Feature",
  "properties": {
    "addr:full":"Carrer de Pablo Picasso, 21 S. Boi Llobregat Barcelona 08830",
    "addr:housenumber":"21",
    "addr:postcode":"08830",
    "addr:street":"Carrer De Pablo Picasso",
    "iso:country":"ES",
    "sg:address":"Carrer de Pablo Picasso, 21",
    "sg:city":"S. Boi Llobregat",
    "sg:orig_category":"Alimentaci\u00d3n General (al Por Menor)",
    "sg:phone":"+34 936 40 13 69",
    "sg:postcode":"08830",
    "sg:province":"Barcelona",
    "wof:name":"Adler Instrumentos S.l.",
    "wof:placetype":"venue"
},
  "geometry": {"coordinates":[2.0349011421,41.3507881165],"type":"Point"}
}