{
  "type": "Feature",
  "properties": {
    "addr:full":"Calle de Cuenca, 11 Ibi Alicante 03440",
    "addr:housenumber":"11",
    "addr:postcode":"03440",
    "addr:street":"Calle De Cuenca",
    "iso:country":"ES",
    "sg:address":"Calle de Cuenca, 11",
    "sg:city":"Ibi",
    "sg:orig_category":"Contenedores (mercanc\u00cdas)",
    "sg:phone":"+34 965 55 13 01",
    "sg:postcode":"03440",
    "sg:province":"Alicante",
    "wof:name":"Ibi Transportes S.l.",
    "wof:placetype":"venue"
},
  "geometry": {"coordinates":[-0.5935025215,38.612071991],"type":"Point"}
}