{
  "type": "Feature",
  "properties": {
    "iso:country":"ES",
    "sg:address":"Avda Mediterraneo (del), 66",
    "sg:city":"Rincon Victoria",
    "sg:orig_category":"Doctores En Medicina",
    "sg:phone":"+34 952 40 83 77",
    "sg:postcode":"29730",
    "sg:province":"M\u00e1laga",
    "wof:name":"Torrecillas Cabrera Francisco Javier",
    "wof:placetype":"venue"
},
  "geometry": {"coordinates":[-4.2876338959,36.7155647278],"type":"Point"}
}