{
  "type": "Feature",
  "properties": {
    "addr:full":"Calle de Sagitario, S/n Callejones-san Silvestre Almer\u00eda 04230",
    "addr:housenumber":"s",
    "addr:postcode":"04230",
    "addr:street":"Calle De Sagitario;/ N Callejones-San Silvestre Almeri\u0301A",
    "iso:country":"ES",
    "sg:address":"Calle de Sagitario, S/n",
    "sg:city":"Callejones-san Silvestre",
    "sg:orig_category":"Fabricaci\u00d3n Y Comercio De M\u00c1quinas",
    "sg:phone":"+34 950 62 46 35",
    "sg:postcode":"04230",
    "sg:province":"Almer\u00eda",
    "wof:name":"Suministros Industriales Rasan S.l.",
    "wof:placetype":"venue"
},
  "geometry": {"coordinates":[-2.447314024,36.8765907288],"type":"Point"}
}