{
  "type": "Feature",
  "properties": {
    "addr:full":"Plno. Industrial, 38 Villamuriel Palencia 34190",
    "addr:housenumber":"38",
    "addr:postcode":"34190",
    "addr:street":"Villamuriel Palencia",
    "iso:country":"ES",
    "sg:address":"Plno. Industrial, 38",
    "sg:city":"Villamuriel",
    "sg:orig_category":"Puertas Y Portales",
    "sg:phone":"+34 979 77 11 28",
    "sg:postcode":"34190",
    "sg:province":"Palencia",
    "wof:name":"Ceresa Blanco Angel Luis",
    "wof:placetype":"venue"
},
  "geometry": {"coordinates":[-4.5164442062,41.9515914917],"type":"Point"}
}