{
  "type": "Feature",
  "properties": {
    "addr:full":"Carrer de Rios Rosas, 51 Barcelona Barcelona 08006",
    "addr:housenumber":"51",
    "addr:postcode":"08006",
    "addr:street":"Carrer De Rios Rosas",
    "iso:country":"ES",
    "sg:address":"Carrer de Rios Rosas, 51",
    "sg:city":"Barcelona",
    "sg:orig_category":"M\u00c9dicos: Foniatr\u00cda Y Logopedia",
    "sg:phone":"+34 932 11 86 00",
    "sg:postcode":"08006",
    "sg:province":"Barcelona",
    "wof:name":"Centre D'estudi I Tractament De Dislexia Montserrat Estil-les S. L.",
    "wof:placetype":"venue"
},
  "geometry": {"coordinates":[2.14249897,41.404460907],"type":"Point"}
}