{
  "type": "Feature",
  "properties": {
    "addr:full":"Calle de Corregidor Juan De Bobadilla, 41 Madrid Madrid 28030",
    "addr:housenumber":"41",
    "addr:postcode":"madrid;28030",
    "addr:street":"Calle De Corregidor Juan De Bobadilla",
    "iso:country":"ES",
    "sg:address":"Calle de Corregidor Juan De Bobadilla, 41",
    "sg:city":"Madrid",
    "sg:orig_category":"Servidores Y Editores De Bases De Datos",
    "sg:phone":"+34 913 01 62 80",
    "sg:postcode":"28030",
    "sg:province":"Madrid",
    "sg:website":"www.okyservice.com",
    "wof:name":"Jimenez Palmilha Victor",
    "wof:placetype":"venue"
},
  "geometry": {"coordinates":[-3.6427519321,40.408203125],"type":"Point"}
}