{
  "type": "Feature",
  "properties": {
    "addr:full":"Carr Emili Grahit, S/n Girona Girona 17002",
    "addr:housenumber":"s / n",
    "addr:postcode":"17002",
    "addr:street":"Carr Emili Grahit",
    "iso:country":"ES",
    "sg:address":"Carr Emili Grahit, S/n",
    "sg:city":"Girona",
    "sg:orig_category":"Promotores Constructores",
    "sg:phone":"+34 972 20 40 30",
    "sg:postcode":"17002",
    "sg:province":"Girona",
    "wof:name":"Construcciones Rubau S.a.",
    "wof:placetype":"venue"
},
  "geometry": {"coordinates":[2.8170800209,41.9755706787],"type":"Point"}
}