{
  "type": "Feature",
  "properties": {
    "addr:full":"Calle de San Diego De Alcala, 14 Palmas De Gran Canaria Las Palmas 35001",
    "addr:housenumber":"14",
    "addr:postcode":"35001",
    "addr:street":"Calle De San;De Alcala",
    "iso:country":"ES",
    "sg:address":"Calle de San Diego De Alcala, 14",
    "sg:city":"Palmas De Gran Canaria",
    "sg:orig_category":"Empresas De Portes Y Mensajer\u00cda",
    "sg:phone":"+34 928 38 46 22",
    "sg:postcode":"35001",
    "sg:province":"Las Palmas",
    "wof:name":"Trans Aerea Canarias S.l.",
    "wof:placetype":"venue"
},
  "geometry": {"coordinates":[-15.4183244705,28.1005687714],"type":"Point"}
}