{
  "type": "Feature",
  "properties": {
    "addr:full":"Avda Andalucia, 27 Puerta De Segura Ja\u00e9n 23360",
    "addr:housenumber":"27",
    "addr:postcode":"23360",
    "addr:street":"Avda Andalucia;Jae\u0301N",
    "iso:country":"ES",
    "sg:address":"Avda Andalucia, 27",
    "sg:city":"Puerta De Segura",
    "sg:orig_category":"Armas Y Municiones (fabricaci\u00d3n, Al Por Mayor)",
    "sg:phone":"+34 953 48 61 58",
    "sg:postcode":"23360",
    "sg:province":"Ja\u00e9n",
    "wof:name":"Lopez Navarro Justiniano",
    "wof:placetype":"venue"
},
  "geometry": {"coordinates":[-2.7381548882,38.350692749],"type":"Point"}
}