{
  "type": "Feature",
  "properties": {
    "addr:full":"Ctra Nacional Ii, 710 Fornells-park Girona 17458",
    "addr:housenumber":"710",
    "addr:postcode":"17458",
    "addr:street":"Ctra Nacional Ii",
    "iso:country":"ES",
    "sg:address":"Ctra Nacional Ii, 710",
    "sg:city":"Fornells-park",
    "sg:orig_category":"Negocio De Materiales De Construcci\u00d3n",
    "sg:phone":"+34 972 47 54 00",
    "sg:postcode":"17458",
    "sg:province":"Girona",
    "sg:website":"www.bricoceramic.com",
    "wof:name":"Bricoceramic S.a.",
    "wof:placetype":"venue"
},
  "geometry": {"coordinates":[2.8099250793,41.9300727844],"type":"Point"}
}