{
  "type": "Feature",
  "properties": {
    "addr:full":"Avda Gines Campos, 30 Alhama Murcia Murcia 30840",
    "addr:housenumber":"30",
    "addr:postcode":"30840",
    "addr:street":"Avda Gines Campos",
    "iso:country":"ES",
    "sg:address":"Avda Gines Campos, 30",
    "sg:city":"Alhama Murcia",
    "sg:orig_category":"Electricidad (montaje, Ensamblaje De Componentes)",
    "sg:phone":"+34 968 63 01 53",
    "sg:postcode":"30840",
    "sg:province":"Murcia",
    "wof:name":"Higinio Garcia Costa S.l.",
    "wof:placetype":"venue"
},
  "geometry": {"coordinates":[-1.4133319855,37.8529891968],"type":"Point"}
}