{
  "type": "Feature",
  "properties": {
    "iso:country":"ES",
    "sg:address":"Calle de Gasolinera, 12",
    "sg:city":"Estacion",
    "sg:orig_category":"Hormigonados",
    "sg:phone":"+34 950 46 40 08",
    "sg:postcode":"04640",
    "sg:province":"Almer\u00eda",
    "wof:name":"Hormigones Pulpi S.l.",
    "wof:placetype":"venue"
},
  "geometry": {"coordinates":[-1.725260973,37.3879928589],"type":"Point"}
}