{
  "type": "Feature",
  "properties": {
    "iso:country":"ES",
    "sg:address":"Calle de Marquesa De Silvela, 4",
    "sg:city":"Madrid",
    "sg:orig_category":"\u00d3ptica: Instrumentos (fabricaci\u00d3n)",
    "sg:phone":"+34 915 69 88 67",
    "sg:postcode":"28026",
    "sg:province":"Madrid",
    "wof:name":"Galiano Lopez-mingo Cristina",
    "wof:placetype":"venue"
},
  "geometry": {"coordinates":[-3.7154150009,40.3859443665],"type":"Point"}
}