{
  "type": "Feature",
  "properties": {
    "addr:full":"Calle de Rio Mi\u00d1o, 6 Parla Madrid 28980",
    "addr:housenumber":"6",
    "addr:postcode":"28980",
    "addr:street":"Calle De Rio Min\u0303O",
    "iso:country":"ES",
    "sg:address":"Calle de Rio Mi\u00d1o, 6",
    "sg:city":"Parla",
    "sg:orig_category":"M\u00c9dicos: Pediatr\u00cda. Enfermedades De Los Ni\u00d1os",
    "sg:phone":"+34 916 99 09 15",
    "sg:postcode":"28980",
    "sg:province":"Madrid",
    "wof:name":"Clavel Ponce Emilio",
    "wof:placetype":"venue"
},
  "geometry": {"coordinates":[-3.7707669735,40.2407417297],"type":"Point"}
}