{
  "type": "Feature",
  "properties": {
    "addr:full":"Calle de Artistas, 2 Madrid Madrid 28020",
    "addr:housenumber":"2",
    "addr:postcode":"28020",
    "addr:street":"Calle De Artistas",
    "iso:country":"ES",
    "sg:address":"Calle de Artistas, 2",
    "sg:city":"Madrid",
    "sg:orig_category":"Asociaciones, Organismos Culturales Y Socioeducativos",
    "sg:phone":"+34 915 53 39 75",
    "sg:postcode":"28020",
    "sg:province":"Madrid",
    "wof:name":"Asociacion Miralta",
    "wof:placetype":"venue"
},
  "geometry": {"coordinates":[-3.7037537098,40.4470863342],"type":"Point"}
}