{
  "type": "Feature",
  "properties": {
    "addr:full":"Astola Auzunea, 6 Abadi\u00f1o Vizcaya 48220",
    "addr:housenumber":"6",
    "addr:postcode":"48220",
    "addr:street":"Astola Auzunea",
    "iso:country":"ES",
    "sg:address":"Astola Auzunea, 6",
    "sg:city":"Abadi\u00f1o",
    "sg:orig_category":"Mec\u00c1nico Del Autom\u00d3vil",
    "sg:phone":"+34 946 20 37 74",
    "sg:postcode":"48220",
    "sg:province":"Vizcaya",
    "wof:name":"Mecanizados Fibe S.l.",
    "wof:placetype":"venue"
},
  "geometry": {"coordinates":[-2.6119830608,43.1629371643],"type":"Point"}
}