{
  "type": "Feature",
  "properties": {
    "iso:country":"ES",
    "sg:address":"Av Europa (d'), 47",
    "sg:city":"Blanes",
    "sg:orig_category":"Distribuci\u00d3n De Petr\u00d3leo Y Derivados",
    "sg:phone":"+34 972 35 46 50",
    "sg:postcode":"17300",
    "sg:province":"Girona",
    "wof:name":"Blanes Oil S.l.",
    "wof:placetype":"venue"
},
  "geometry": {"coordinates":[2.7747199535,41.6766014099],"type":"Point"}
}