{
  "type": "Feature",
  "properties": {
    "addr:full":"Carretera De Madrid, S/n Aranda Duero Burgos 09400",
    "addr:housenumber":"s / n",
    "addr:postcode":"09400",
    "addr:street":"Carretera De Madrid",
    "iso:country":"ES",
    "sg:address":"Carretera De Madrid, S/n",
    "sg:city":"Aranda Duero",
    "sg:orig_category":"Material Y Herramientas Agr\u00cdcolas",
    "sg:phone":"+34 947 50 13 72",
    "sg:postcode":"09400",
    "sg:province":"Burgos",
    "wof:name":"Comercial Parra Aranda S.a.",
    "wof:placetype":"venue"
},
  "geometry": {"coordinates":[-3.6922938824,41.6564483643],"type":"Point"}
}