{
  "type": "Feature",
  "properties": {
    "addr:full":"Calle de Garay Juan De, 15 Bilbao Vizcaya 48003",
    "addr:housenumber":"15",
    "addr:postcode":"48003",
    "addr:street":"Calle De Garay Juan De",
    "iso:country":"ES",
    "sg:address":"Calle de Garay Juan De, 15",
    "sg:city":"Bilbao",
    "sg:orig_category":"Empresas De Pintura Y Revestimientos",
    "sg:phone":"+34 944 22 29 34",
    "sg:postcode":"48003",
    "sg:province":"Vizcaya",
    "wof:name":"Valcarcel Bilbao Ignacio",
    "wof:placetype":"venue"
},
  "geometry": {"coordinates":[-2.9333410263,43.2548332214],"type":"Point"}
}