{
  "type": "Feature",
  "properties": {
    "iso:country":"ES",
    "sg:address":"Av Llibertat, 108",
    "sg:city":"Sant Joan De Palamos",
    "sg:orig_category":"Agricultores, Agricultores",
    "sg:phone":"+34 972 31 43 94",
    "sg:postcode":"17230",
    "sg:province":"Girona",
    "wof:name":"Agro Entorn Palamos Sccl",
    "wof:placetype":"venue"
},
  "geometry": {"coordinates":[3.1294519901,41.8542251587],"type":"Point"}
}