{
  "type": "Feature",
  "properties": {
    "addr:full":"Av Can Bordoll, 131 Torre-romeu Barcelona 08202",
    "addr:housenumber":"131",
    "addr:postcode":"08202",
    "addr:street":"Av Can Bordoll;Barcelona",
    "iso:country":"ES",
    "sg:address":"Av Can Bordoll, 131",
    "sg:city":"Torre-romeu",
    "sg:orig_category":"Transportes Por V\u00cdas Navegables",
    "sg:phone":"+34 937 26 11 86",
    "sg:postcode":"08202",
    "sg:province":"Barcelona",
    "sg:website":"www.empresas.sumi.es/sabatransport",
    "wof:name":"Sabatransport S.l.",
    "wof:placetype":"venue"
},
  "geometry": {"coordinates":[2.1286709309,41.5617256165],"type":"Point"}
}