{
  "type": "Feature",
  "properties": {
    "iso:country":"ES",
    "sg:address":"Calle de Vi\u00d1a, 7",
    "sg:city":"Majadahonda",
    "sg:orig_category":"Inform\u00c1tica (estudios, Servicios, Asesor\u00cda, Formaci\u00d3n)",
    "sg:phone":"+34 916 34 40 95",
    "sg:postcode":"28220",
    "sg:province":"Madrid",
    "wof:name":"Zirtan On Line S.l.",
    "wof:placetype":"venue"
},
  "geometry": {"coordinates":[-3.8761959076,40.4705696106],"type":"Point"}
}