{
  "type": "Feature",
  "properties": {
    "addr:full":"Carr Sant Gregori, S/n Girona Girona 17007",
    "addr:housenumber":"s / n",
    "addr:postcode":"17007",
    "addr:street":"Carr Sant Gregori",
    "iso:country":"ES",
    "sg:address":"Carr Sant Gregori, S/n",
    "sg:city":"Girona",
    "sg:orig_category":"Mec\u00c1nico Del Autom\u00d3vil",
    "sg:phone":"+34 972 21 37 10",
    "sg:postcode":"17007",
    "sg:province":"Girona",
    "wof:name":"Fabregas Grabulosa Jorge",
    "wof:placetype":"venue"
},
  "geometry": {"coordinates":[2.8072800636,41.9923210144],"type":"Point"}
}