{
  "type": "Feature",
  "properties": {
    "addr:full":"Avda Extremadura, 6 Coria C\u00e1ceres 10800",
    "addr:housenumber":"6",
    "addr:postcode":"10800",
    "addr:street":"Avda Extremadura;Ca\u0301Ceres",
    "iso:country":"ES",
    "sg:address":"Avda Extremadura, 6",
    "sg:city":"Coria",
    "sg:orig_category":"Insecticidas, Fumigaci\u00d3n",
    "sg:phone":"+34 927 50 14 88",
    "sg:postcode":"10800",
    "sg:province":"C\u00e1ceres",
    "wof:name":"Herrero Peral Joaquin",
    "wof:placetype":"venue"
},
  "geometry": {"coordinates":[-6.5341992378,39.9841117859],"type":"Point"}
}