{
  "type": "Feature",
  "properties": {
    "addr:full":"Calle de Castillo, 58 Santa Cruz De Tenerife Santa Cruz De Tenerife 38003",
    "addr:housenumber":"58",
    "addr:postcode":"38003",
    "addr:street":"Calle De Castillo",
    "iso:country":"ES",
    "sg:address":"Calle de Castillo, 58",
    "sg:city":"Santa Cruz De Tenerife",
    "sg:orig_category":"Zapatos (al Por Menor)",
    "sg:phone":"+34 922 28 84 62",
    "sg:postcode":"38003",
    "sg:province":"Santa Cruz De Tenerife",
    "wof:name":"Gonzalez De Chavez Diaz Santiago",
    "wof:placetype":"venue"
},
  "geometry": {"coordinates":[-16.2527732849,28.4673347473],"type":"Point"}
}