{
  "type": "Feature",
  "properties": {
    "iso:country":"ES",
    "sg:address":"Calle de Real, 30",
    "sg:city":"Paracuellos De Jarama",
    "sg:orig_category":"Bancos",
    "sg:phone":"+34 916 58 23 53",
    "sg:postcode":"28860",
    "sg:province":"Madrid",
    "sg:website":"www.bancopopular.es",
    "wof:name":"Banco Popular Espa\u00f1ol S.a.",
    "wof:placetype":"venue"
},
  "geometry": {"coordinates":[-3.5307168961,40.5041618347],"type":"Point"}
}