{
  "type": "Feature",
  "properties": {
    "iso:country":"ES",
    "sg:address":"Calle de Ancha, 13",
    "sg:city":"Leganes",
    "sg:orig_category":"Transportes Por Carretera: Lotes Completos, Mercanc\u00cdas Diversas",
    "sg:phone":"+34 916 94 22 11",
    "sg:postcode":"28914",
    "sg:province":"Madrid",
    "wof:name":"Lomas Castillo Filomena",
    "wof:placetype":"venue"
},
  "geometry": {"coordinates":[-3.7706921101,40.3182640076],"type":"Point"}
}