{
  "type": "Feature",
  "properties": {
    "addr:full":"Ctra. Madrid-cadiz, Km. 0346,6 Lopera Ja\u00e9n 23780",
    "addr:postcode":"23780",
    "addr:street":"Ctra. Madrid-Cadiz Km. 0346,6;Jae\u0301N",
    "iso:country":"ES",
    "sg:address":"Ctra. Madrid-cadiz, Km. 0346,6",
    "sg:city":"Lopera",
    "sg:orig_category":"Distribuci\u00d3n De Petr\u00d3leo Y Derivados",
    "sg:phone":"+34 953 51 67 72",
    "sg:postcode":"23780",
    "sg:province":"Ja\u00e9n",
    "wof:name":"Romero Mu\u00f1oz Manuel",
    "wof:placetype":"venue"
},
  "geometry": {"coordinates":[-4.210878849,37.9476242065],"type":"Point"}
}