{
  "type": "Feature",
  "properties": {
    "addr:full":"Mayor, 8 Atarrabia Navarra 31610",
    "addr:housenumber":"8",
    "addr:postcode":"31610",
    "addr:street":"Mayor",
    "iso:country":"ES",
    "sg:address":"Mayor, 8",
    "sg:city":"Atarrabia",
    "sg:orig_category":"Lencer\u00cda Femenina, Corseter\u00cda, Trajes De Ba\u00d1o (al Por Menor)",
    "sg:phone":"+34 948 14 79 98",
    "sg:postcode":"31610",
    "sg:province":"Navarra",
    "wof:name":"Ab S.l.",
    "wof:placetype":"venue"
},
  "geometry": {"coordinates":[-1.618489,42.823925],"type":"Point"}
}