{
  "type": "Feature",
  "properties": {
    "iso:country":"ES",
    "sg:address":"Pase San Francisco De Sales, 23",
    "sg:city":"Madrid",
    "sg:orig_category":"Ingeniero",
    "sg:phone":"+34 915 49 32 59",
    "sg:postcode":"28003",
    "sg:province":"Madrid",
    "wof:name":"Ayora Baena Francisco",
    "wof:placetype":"venue"
},
  "geometry": {"coordinates":[-3.7146580219,40.4413833618],"type":"Point"}
}