{
  "type": "Feature",
  "properties": {
    "iso:country":"ES",
    "sg:address":"Calle de Prim, 55",
    "sg:city":"Bilbao",
    "sg:orig_category":"Peluquer\u00cdas, Peluquer\u00cda Mixta",
    "sg:phone":"+34 944 05 88 92",
    "sg:postcode":"48006",
    "sg:province":"Vizcaya",
    "wof:name":"Fernando Martin Fernandez",
    "wof:placetype":"venue"
},
  "geometry": {"coordinates":[-2.9153580666,43.2570838928],"type":"Point"}
}