{
  "type": "Feature",
  "properties": {
    "iso:country":"ES",
    "sg:address":"Avda Reina Victoria, 45",
    "sg:city":"Santander",
    "sg:orig_category":"Inmobiliaria (agencias)",
    "sg:phone":"+34 942 27 08 10",
    "sg:postcode":"39004",
    "sg:province":"Cantabria",
    "wof:name":"Gonzalez Rumoroso Felix Damaso",
    "wof:placetype":"venue"
},
  "geometry": {"coordinates":[-3.7881560326,43.4638442993],"type":"Point"}
}