{
  "type": "Feature",
  "properties": {
    "addr:full":"Avda Amaia, 20 Pinos Vizcaya 48940",
    "addr:housenumber":"20",
    "addr:postcode":"48940",
    "addr:street":"Avda Amaia",
    "iso:country":"ES",
    "sg:address":"Avda Amaia, 20",
    "sg:city":"Pinos",
    "sg:orig_category":"Reposter\u00cdas",
    "sg:phone":"+34 944 64 36 73",
    "sg:postcode":"48940",
    "sg:province":"Vizcaya",
    "wof:name":"Gonzalez Vallinas Maria Asuncion",
    "wof:placetype":"venue"
},
  "geometry": {"coordinates":[-2.9860789776,43.3275489807],"type":"Point"}
}