{
  "type": "Feature",
  "properties": {
    "addr:full":"Carrer de Sant Antoni Maria Claret, 450 Barcelona Barcelona 08027",
    "addr:housenumber":"450",
    "addr:postcode":"08027",
    "addr:street":"Carrer De Sant Antoni Maria Claret",
    "iso:country":"ES",
    "sg:address":"Carrer de Sant Antoni Maria Claret, 450",
    "sg:city":"Barcelona",
    "sg:orig_category":"Peluquer\u00cdas, Peluquer\u00cda Mixta",
    "sg:phone":"+34 933 40 69 69",
    "sg:postcode":"08027",
    "sg:province":"Barcelona",
    "wof:name":"Rije Perruquers S.l.",
    "wof:placetype":"venue"
},
  "geometry": {"coordinates":[2.185336113,41.4192123413],"type":"Point"}
}