{
  "type": "Feature",
  "properties": {
    "addr:full":"Rua Zaragoza, 32 Vigo Pontevedra 36203",
    "addr:housenumber":"32",
    "addr:postcode":"36203",
    "addr:street":"Rua Zaragoza",
    "iso:country":"ES",
    "sg:address":"Rua Zaragoza, 32",
    "sg:city":"Vigo",
    "sg:orig_category":"Promotores Constructores",
    "sg:phone":"+34 986 48 53 73",
    "sg:postcode":"36203",
    "sg:province":"Pontevedra",
    "wof:name":"Pazu Ba\u00d1os S.l.",
    "wof:placetype":"venue"
},
  "geometry": {"coordinates":[-8.7251443863,42.2253990173],"type":"Point"}
}