{
  "type": "Feature",
  "properties": {
    "addr:full":"Avda America (de), 15 Cordoba C\u00f3rdoba 14008",
    "addr:housenumber":"15",
    "addr:postcode":"14008",
    "addr:street":"Avda America De;Co\u0301Rdoba",
    "iso:country":"ES",
    "sg:address":"Avda America (de), 15",
    "sg:city":"Cordoba",
    "sg:orig_category":"Farmacias",
    "sg:phone":"+34 957 47 34 24",
    "sg:postcode":"14008",
    "sg:province":"C\u00f3rdoba",
    "wof:name":"Toledano Serrano Dolores",
    "wof:placetype":"venue"
},
  "geometry": {"coordinates":[-4.7837381363,37.890083313],"type":"Point"}
}