{
  "type": "Feature",
  "properties": {
    "addr:full":"Calle de Padre Melchor Prieto, 5 Burgos Burgos 09005",
    "addr:housenumber":"5",
    "addr:postcode":"09005",
    "addr:street":"Calle De Padre Melchor Prieto",
    "iso:country":"ES",
    "sg:address":"Calle de Padre Melchor Prieto, 5",
    "sg:city":"Burgos",
    "sg:orig_category":"Fisioterapia",
    "sg:phone":"+34 947 22 78 16",
    "sg:postcode":"09005",
    "sg:province":"Burgos",
    "wof:name":"Fisioterapia Vicray S.l",
    "wof:placetype":"venue"
},
  "geometry": {"coordinates":[-3.699682951,42.3469200134],"type":"Point"}
}