{
  "type": "Feature",
  "properties": {
    "iso:country":"ES",
    "sg:address":"Calle de Esparteros, 10",
    "sg:city":"A\u00e7over De Tajo",
    "sg:orig_category":"Sociedades, Compa\u00d1\u00cdas Aseguradoras",
    "sg:phone":"+34 925 55 55 31",
    "sg:postcode":"45250",
    "sg:province":"Toledo",
    "wof:name":"Segurcel Sociedad De Agencia De Seguros S.l.",
    "wof:placetype":"venue"
},
  "geometry": {"coordinates":[-3.7629699707,39.9871559143],"type":"Point"}
}