{
  "type": "Feature",
  "properties": {
    "iso:country":"ES",
    "sg:address":"Calle de Pintor Picasso, 20",
    "sg:city":"San Vicente Del Raspeig-sant Vicent Del Raspeig",
    "sg:orig_category":"Mercer\u00cda, Lencer\u00cda (al Por Menor)",
    "sg:phone":"+34 965 66 04 29",
    "sg:postcode":"03690",
    "sg:province":"Alicante",
    "wof:name":"Mira Carbonell Francisco",
    "wof:placetype":"venue"
},
  "geometry": {"coordinates":[-0.5233131051,38.3955535889],"type":"Point"}
}