{
  "type": "Feature",
  "properties": {
    "addr:full":"Sancho Ramirez, 31 Iru\u00f1a Navarra 31008",
    "addr:housenumber":"31",
    "addr:postcode":"31008",
    "addr:street":"Ramirez",
    "iso:country":"ES",
    "sg:address":"Sancho Ramirez, 31",
    "sg:city":"Iru\u00f1a",
    "sg:orig_category":"Electromec\u00c1nica",
    "sg:phone":"+34 948 26 43 53",
    "sg:postcode":"31008",
    "sg:province":"Navarra",
    "wof:name":"Astrain Bescos Raul",
    "wof:placetype":"venue"
},
  "geometry": {"coordinates":[-1.6661082506,42.808265686],"type":"Point"}
}