{
  "type": "Feature",
  "properties": {
    "addr:full":"Carrer de Flors, 58 Vendrell Tarragona 43700",
    "addr:housenumber":"58",
    "addr:postcode":"43700",
    "addr:street":"Carrer De Flors",
    "iso:country":"ES",
    "sg:address":"Carrer de Flors, 58",
    "sg:city":"Vendrell",
    "sg:orig_category":"Molduras, Junquillos, Listones Y Molduras Perforadas",
    "sg:phone":"+34 977 66 63 83",
    "sg:postcode":"43700",
    "sg:province":"Tarragona",
    "wof:name":"Bar Restaurante Mas D'en Gual S.l.",
    "wof:placetype":"venue"
},
  "geometry": {"coordinates":[1.5266890526,41.2182655334],"type":"Point"}
}