{
  "type": "Feature",
  "properties": {
    "addr:full":"Calle de Francisco Grandmontagne, 23 Burgos Burgos 09007",
    "addr:housenumber":"23",
    "addr:postcode":"09007",
    "addr:street":"Calle De Francisco Grandmontagne",
    "iso:country":"ES",
    "sg:address":"Calle de Francisco Grandmontagne, 23",
    "sg:city":"Burgos",
    "sg:orig_category":"Confecci\u00d3n De Botones",
    "sg:phone":"+34 947 22 62 73",
    "sg:postcode":"09007",
    "sg:province":"Burgos",
    "wof:name":"Fuente Lara Jose Luis De La",
    "wof:placetype":"venue"
},
  "geometry": {"coordinates":[-3.6701447964,42.3497810364],"type":"Point"}
}