{
  "type": "Feature",
  "properties": {
    "addr:full":"Avda Alberto Alcocer, 49 Madrid Madrid 28016",
    "addr:housenumber":"49",
    "addr:postcode":"madrid;28016",
    "addr:street":"Alberto Alcocer",
    "iso:country":"ES",
    "sg:address":"Avda Alberto Alcocer, 49",
    "sg:city":"Madrid",
    "sg:orig_category":"Institutos De Belleza",
    "sg:phone":"+34 913 43 10 98",
    "sg:postcode":"28016",
    "sg:province":"Madrid",
    "wof:name":"Sunmusic S.l.",
    "wof:placetype":"venue"
},
  "geometry": {"coordinates":[-3.6771891117,40.4588432312],"type":"Point"}
}