{
  "type": "Feature",
  "properties": {
    "iso:country":"ES",
    "sg:address":"Avda Cid, 58",
    "sg:city":"Valencia",
    "sg:orig_category":"Sociedades, Compa\u00d1\u00cdas Aseguradoras",
    "sg:phone":"+34 963 70 44 22",
    "sg:postcode":"46018",
    "sg:province":"Valencia",
    "wof:name":"Estanislao Rubio Desde 1946 Correduria De Seguros",
    "wof:placetype":"venue"
},
  "geometry": {"coordinates":[-0.4035919905,39.4691467285],"type":"Point"}
}