{
  "type": "Feature",
  "properties": {
    "iso:country":"ES",
    "sg:address":"Amutalde Auzoa, 22",
    "sg:city":"Amute-kosta",
    "sg:orig_category":"Fabricaci\u00d3n, Distribuci\u00d3n De Discos, V\u00cddeodiscos Y Musicassettes",
    "sg:phone":"+34 943 64 56 52",
    "sg:postcode":"20280",
    "sg:province":"Guip\u00f9zcoa",
    "wof:name":"Aterki Records S.l.",
    "wof:placetype":"venue"
},
  "geometry": {"coordinates":[-1.8032524586,43.3495368958],"type":"Point"}
}