{
  "type": "Feature",
  "properties": {
    "addr:full":"Calle de Pozos, 1 Puebla Montalban Toledo 45516",
    "addr:housenumber":"1",
    "addr:postcode":"45516",
    "addr:street":"Calle De Pozos",
    "iso:country":"ES",
    "sg:address":"Calle de Pozos, 1",
    "sg:city":"Puebla Montalban",
    "sg:classifiers":[
        {
            "category":"Taxi",
            "type":"Transportation"
        }
    ],
    "sg:phone":"+34 925 75 02 81",
    "sg:postcode":"45516",
    "sg:province":"Toledo",
    "wof:name":"Fernandez De La Hoz Medina Guillermo",
    "wof:placetype":"venue"
},
  "geometry": {"coordinates":[-4.3634738922,39.8630447388],"type":"Point"}
}