{
  "type": "Feature",
  "properties": {
    "iso:country":"ES",
    "sg:address":"Calle de Cabezas, 11",
    "sg:city":"Huelma",
    "sg:orig_category":"Zapatos (al Por Menor)",
    "sg:phone":"+34 953 39 07 70",
    "sg:postcode":"23560",
    "sg:province":"Ja\u00e9n",
    "wof:name":"Baltasar Martinez Fernandez C.b.",
    "wof:placetype":"venue"
},
  "geometry": {"coordinates":[-3.4582970142,37.6498641968],"type":"Point"}
}