{
  "type": "Feature",
  "properties": {
    "addr:full":"Calle de Pilar, 9 San Nicolas Murcia 30004",
    "addr:housenumber":"9",
    "addr:postcode":"30004",
    "addr:street":"Calle De Pilar",
    "iso:country":"ES",
    "sg:address":"Calle de Pilar, 9",
    "sg:city":"San Nicolas",
    "sg:orig_category":"Perreras, Pensiones Para Perros, Gatos Y Otros Animales",
    "sg:phone":"+34 968 21 36 28",
    "sg:postcode":"30004",
    "sg:province":"Murcia",
    "wof:name":"Sociedad Canina De Murcia S.l.",
    "wof:placetype":"venue"
},
  "geometry": {"coordinates":[-1.1357339621,37.9846343994],"type":"Point"}
}