{
  "type": "Feature",
  "properties": {
    "iso:country":"ES",
    "sg:address":"Plaz Trianilla (de La), 16",
    "sg:city":"Utrera",
    "sg:orig_category":"M\u00c9dicos: Estomatolog\u00cda",
    "sg:phone":"+34 955 86 08 13",
    "sg:postcode":"41710",
    "sg:province":"Sevilla",
    "wof:name":"Plate Vega Maria Azucena",
    "wof:placetype":"venue"
},
  "geometry": {"coordinates":[-5.7877287865,37.1873664856],"type":"Point"}
}