{
  "type": "Feature",
  "properties": {
    "iso:country":"ES",
    "sg:address":"Avda Maria Auxiliadora, 65",
    "sg:city":"Rota",
    "sg:orig_category":"Muebles, Minoristas",
    "sg:phone":"+34 956 81 37 70",
    "sg:postcode":"11520",
    "sg:province":"C\u00e1diz",
    "wof:name":"Ramirez Verdugo Jesus",
    "wof:placetype":"venue"
},
  "geometry": {"coordinates":[-6.3638491631,36.6251983643],"type":"Point"}
}