{
  "type": "Feature",
  "properties": {
    "addr:full":"Calle de Fraternidad, 5 Tias Las Palmas 35572",
    "addr:housenumber":"5",
    "addr:postcode":"35572",
    "addr:street":"Calle De Fraternidad",
    "iso:country":"ES",
    "sg:address":"Calle de Fraternidad, 5",
    "sg:city":"Tias",
    "sg:orig_category":"Loter\u00cda Y T\u00d3mbola",
    "sg:phone":"+34 928 83 40 35",
    "sg:postcode":"35572",
    "sg:province":"Las Palmas",
    "wof:name":"Perez Perez Manuel",
    "wof:placetype":"venue"
},
  "geometry": {"coordinates":[-13.6531944275,28.9532661438],"type":"Point"}
}