{
  "type": "Feature",
  "properties": {
    "addr:full":"Azara Kalea, 7 Zarautz Guip\u00f9zcoa 20800",
    "addr:housenumber":"7",
    "addr:postcode":"20800",
    "addr:street":"Azara Kalea;Guipu\u0300Zcoa",
    "iso:country":"ES",
    "sg:address":"Azara Kalea, 7",
    "sg:city":"Zarautz",
    "sg:orig_category":"Doctores En Medicina",
    "sg:phone":"+34 943 13 02 15",
    "sg:postcode":"20800",
    "sg:province":"Guip\u00f9zcoa",
    "wof:name":"Gurutze Ormazabal Arruti",
    "wof:placetype":"venue"
},
  "geometry": {"coordinates":[-2.1755619049,43.2862586975],"type":"Point"}
}