{
  "type": "Feature",
  "properties": {
    "addr:full":"Ctra Bilbao-plencia, S/n Erandio-goikoa Vizcaya 48950",
    "addr:housenumber":"s / n",
    "addr:postcode":"48950",
    "addr:street":"Ctra Bilbao-Plencia",
    "iso:country":"ES",
    "sg:address":"Ctra Bilbao-plencia, S/n",
    "sg:city":"Erandio-goikoa",
    "sg:orig_category":"Art\u00cdculos Funerarios (al Por Menor)",
    "sg:phone":"+34 944 71 01 61",
    "sg:postcode":"48950",
    "sg:province":"Vizcaya",
    "wof:name":"Servicios Especiales S. A.",
    "wof:placetype":"venue"
},
  "geometry": {"coordinates":[-2.9546589851,43.2939758301],"type":"Point"}
}