{
  "type": "Feature",
  "properties": {
    "addr:full":"Avda Cid Campeador, 79 Burgos Burgos 09005",
    "addr:housenumber":"79",
    "addr:postcode":"09005",
    "addr:street":"Avda Cid Campeador",
    "iso:country":"ES",
    "sg:address":"Avda Cid Campeador, 79",
    "sg:city":"Burgos",
    "sg:orig_category":"Empresarios",
    "sg:phone":"+34 947 22 78 96",
    "sg:postcode":"09005",
    "sg:province":"Burgos",
    "wof:name":"Burgos Machon Dionisio",
    "wof:placetype":"venue"
},
  "geometry": {"coordinates":[-3.6956510544,42.3509407043],"type":"Point"}
}