{
  "type": "Feature",
  "properties": {
    "iso:country":"ES",
    "sg:address":"Calle de Teniente Jose Olmo, 4",
    "sg:city":"Ceuta",
    "sg:orig_category":"Frutas, Legumbres Frescas Y Tempranas (al Por Menor)",
    "sg:phone":"+34 956 51 88 72",
    "sg:postcode":"51001",
    "sg:province":"Ceuta",
    "wof:name":"Hassan Mohamed Hamido",
    "wof:placetype":"venue"
},
  "geometry": {"coordinates":[-5.3302302361,35.8947601318],"type":"Point"}
}