{
  "type": "Feature",
  "properties": {
    "iso:country":"ES",
    "sg:address":"Calle de Maestro Gozalbo, 12",
    "sg:city":"Valencia",
    "sg:orig_category":"Fisioterapia",
    "sg:phone":"+34 963 33 00 39",
    "sg:postcode":"46005",
    "sg:province":"Valencia",
    "wof:name":"Gares Garcia Ana",
    "wof:placetype":"venue"
},
  "geometry": {"coordinates":[-0.3696810007,39.4654922485],"type":"Point"}
}