{
  "type": "Feature",
  "properties": {
    "iso:country":"ES",
    "sg:address":"Calle de San Gregorio (de), 36",
    "sg:city":"Galapagar",
    "sg:orig_category":"Reposter\u00cdas",
    "sg:phone":"+34 918 58 68 95",
    "sg:postcode":"28260",
    "sg:province":"Madrid",
    "wof:name":"Hernan Rollol Maria Isabel",
    "wof:placetype":"venue"
},
  "geometry": {"coordinates":[-4.0021591187,40.579875946],"type":"Point"}
}