{
  "type": "Feature",
  "properties": {
    "iso:country":"ES",
    "sg:address":"Calle de Montejano, 26",
    "sg:city":"Pedro\u00d1eras",
    "sg:orig_category":"Estancos",
    "sg:phone":"+34 967 16 12 96",
    "sg:postcode":"16660",
    "sg:province":"Cuenca",
    "wof:name":"Jare\u00f1o Ojero Anselmo",
    "wof:placetype":"venue"
},
  "geometry": {"coordinates":[-2.673648119,39.4496612549],"type":"Point"}
}