{
  "type": "Feature",
  "properties": {
    "addr:full":"Calle de Caldereros, 33 Alca\u00f1iz Teruel 44600",
    "addr:housenumber":"33",
    "addr:postcode":"44600",
    "addr:street":"Calle De Caldereros",
    "iso:country":"ES",
    "sg:address":"Calle de Caldereros, 33",
    "sg:city":"Alca\u00f1iz",
    "sg:orig_category":"Promotores Constructores",
    "sg:phone":"+34 978 83 39 65",
    "sg:postcode":"44600",
    "sg:province":"Teruel",
    "wof:name":"Lopez Sancho Antonio",
    "wof:placetype":"venue"
},
  "geometry": {"coordinates":[-0.1313710958,41.0479469299],"type":"Point"}
}