{
  "type": "Feature",
  "properties": {
    "iso:country":"ES",
    "sg:address":"Calle de Frieira, 14",
    "sg:city":"Frieira",
    "sg:orig_category":"Mayoristas E Intermediarios En Alcoholes",
    "sg:phone":"+34 988 49 41 92",
    "sg:postcode":"32236",
    "sg:province":"Ourense",
    "wof:name":"Montero Ferreira Fernando",
    "wof:placetype":"venue"
},
  "geometry": {"coordinates":[-8.1739740372,42.1518173218],"type":"Point"}
}