{
  "type": "Feature",
  "properties": {
    "iso:country":"ES",
    "sg:address":"Calle de Vicente Y Tutor, 15",
    "sg:city":"Agreda",
    "sg:orig_category":"Asilos De Ancianos. Centros Privados",
    "sg:phone":"+34 976 64 73 02",
    "sg:postcode":"42100",
    "sg:province":"Soria",
    "wof:name":"Diputacion De Soria",
    "wof:placetype":"venue"
},
  "geometry": {"coordinates":[-1.9183189869,41.8537597656],"type":"Point"}
}