{
  "type": "Feature",
  "properties": {
    "iso:country":"ES",
    "sg:address":"Calle de Duquesa De La Victoria, 75",
    "sg:city":"Logro\u00f1o",
    "sg:orig_category":"Plomeros",
    "sg:phone":"+34 941 25 13 17",
    "sg:postcode":"26004",
    "sg:province":"La Rioja",
    "wof:name":"Fontaneria La Moderna S.l.",
    "wof:placetype":"venue"
},
  "geometry": {"coordinates":[-2.4326944351,42.4632492065],"type":"Point"}
}