{
  "type": "Feature",
  "properties": {
    "addr:full":"Pase Aixin Zolua Ibilbidea, 3 Irun Guip\u00f9zcoa 20304",
    "addr:housenumber":"3",
    "addr:postcode":"20304",
    "addr:street":"Zolua Ibilbidea;Guipu\u0300Zcoa",
    "iso:country":"ES",
    "sg:address":"Pase Aixin Zolua Ibilbidea, 3",
    "sg:city":"Irun",
    "sg:orig_category":"M\u00c9dicos: Salud P\u00dablica",
    "sg:phone":"+34 943 63 05 88",
    "sg:postcode":"20304",
    "sg:province":"Guip\u00f9zcoa",
    "wof:name":"Ugarte Etxepare Juncal",
    "wof:placetype":"venue"
},
  "geometry": {"coordinates":[-1.7847739458,43.3386039734],"type":"Point"}
}