{
  "type": "Feature",
  "properties": {
    "addr:full":"Calle de Carril Del Conde, 61 Madrid Madrid 28043",
    "addr:housenumber":"61",
    "addr:postcode":"madrid;28043",
    "addr:street":"Calle De Carril Del Conde",
    "iso:country":"ES",
    "sg:address":"Calle de Carril Del Conde, 61",
    "sg:city":"Madrid",
    "sg:orig_category":"M\u00c9dicos: Dermatolog\u00cda Y Venereolog\u00cda",
    "sg:phone":"+34 913 88 50 25",
    "sg:postcode":"28043",
    "sg:province":"Madrid",
    "wof:name":"Dermatologia Formulada Especifica S.l.",
    "wof:placetype":"venue"
},
  "geometry": {"coordinates":[-3.6541900635,40.4611473083],"type":"Point"}
}