{
  "type": "Feature",
  "properties": {
    "addr:full":"Calle de General Varela, 37 Madrid Madrid 28020",
    "addr:housenumber":"37",
    "addr:postcode":"madrid;28020",
    "addr:street":"Calle De General Varela",
    "iso:country":"ES",
    "sg:address":"Calle de General Varela, 37",
    "sg:city":"Madrid",
    "sg:orig_category":"Asociaciones Y Clubs Deportivos",
    "sg:phone":"+34 915 67 03 75",
    "sg:postcode":"28020",
    "sg:province":"Madrid",
    "wof:name":"Fitness First S.a.",
    "wof:placetype":"venue"
},
  "geometry": {"coordinates":[-3.6950159073,40.4586906433],"type":"Point"}
}