{
  "type": "Feature",
  "properties": {
    "iso:country":"ES",
    "sg:address":"Tarabelo, S/n",
    "sg:city":"Tarabelo",
    "sg:orig_category":"Chapister\u00cda",
    "sg:phone":"+34 981 62 08 42",
    "sg:postcode":"15160",
    "sg:province":"A Coru\u00f1a",
    "wof:name":"Ya\u00f1ez Vidal Agustin",
    "wof:placetype":"venue"
},
  "geometry": {"coordinates":[-8.2673053741,43.3484077454],"type":"Point"}
}