{
  "type": "Feature",
  "properties": {
    "iso:country":"ES",
    "sg:address":"Calle de Nicolas Estevanez, 14",
    "sg:city":"Palmas De Gran Canaria",
    "sg:orig_category":"Bazares, Art\u00cdculos De Limpieza Y De Cocina (al Por Menor)",
    "sg:phone":"+34 928 26 35 27",
    "sg:postcode":"35007",
    "sg:province":"Las Palmas",
    "wof:name":"Baxani Shmsunder Lachmandas",
    "wof:placetype":"venue"
},
  "geometry": {"coordinates":[-15.4320173264,28.1395740509],"type":"Point"}
}