{
  "type": "Feature",
  "properties": {
    "iso:country":"ES",
    "sg:address":"Calle de Conde Torreanaz, 4",
    "sg:city":"Torrelavega",
    "sg:orig_category":"Caf\u00c9s, Bares, Cervecer\u00cdas",
    "sg:phone":"+34 942 88 31 36",
    "sg:postcode":"39300",
    "sg:province":"Cantabria",
    "wof:name":"Barba Salda\u00f1a Guillermo",
    "wof:placetype":"venue"
},
  "geometry": {"coordinates":[-4.0486040115,43.3515357971],"type":"Point"}
}