{
  "type": "Feature",
  "properties": {
    "addr:full":"Calle de Velazquez, 4 S. Fernando C\u00e1diz 11100",
    "addr:housenumber":"4",
    "addr:postcode":"11100",
    "addr:street":"Calle De Velazquez;S. Fernando Ca\u0301Diz",
    "iso:country":"ES",
    "sg:address":"Calle de Velazquez, 4",
    "sg:city":"S. Fernando",
    "sg:orig_category":"Enfermeras: Consultas, Atenci\u00d3n A Domicilio",
    "sg:phone":"+34 956 89 57 60",
    "sg:postcode":"11100",
    "sg:province":"C\u00e1diz",
    "wof:name":"Gil Soriano Bonifacio Jeronimo",
    "wof:placetype":"venue"
},
  "geometry": {"coordinates":[-6.1969408989,36.4648246765],"type":"Point"}
}