{
  "type": "Feature",
  "properties": {
    "iso:country":"ES",
    "sg:address":"Cmno Aguas, 53",
    "sg:city":"Salamanca",
    "sg:orig_category":"Cajas Para Embalar",
    "sg:phone":"+34 923 18 08 64",
    "sg:postcode":"37003",
    "sg:province":"Salamanca",
    "wof:name":"Caja Rural Provincial De Salamanca",
    "wof:placetype":"venue"
},
  "geometry": {"coordinates":[-5.6504731178,40.9632492065],"type":"Point"}
}