{
  "type": "Feature",
  "properties": {
    "iso:country":"ES",
    "sg:address":"Carrer de Mossen Coy, 1",
    "sg:city":"Vilafranca Penedes",
    "sg:orig_category":"Empresarios",
    "sg:phone":"+34 938 92 04 95",
    "sg:postcode":"08720",
    "sg:province":"Barcelona",
    "wof:name":"Contratista De Obras Pere Agudo Royo S.l.",
    "wof:placetype":"venue"
},
  "geometry": {"coordinates":[1.7026900053,41.3513908386],"type":"Point"}
}