{
  "type": "Feature",
  "properties": {
    "addr:full":"Avda Peris Y Valero, 164 Valencia Valencia 46006",
    "addr:housenumber":"164",
    "addr:postcode":"46006",
    "addr:street":"Avda Peris Y Valero",
    "iso:country":"ES",
    "sg:address":"Avda Peris Y Valero, 164",
    "sg:city":"Valencia",
    "sg:orig_category":"Electricidad: Instaladores",
    "sg:phone":"+34 963 33 48 49",
    "sg:postcode":"46006",
    "sg:province":"Valencia",
    "wof:name":"Vidal Bataller Salvador",
    "wof:placetype":"venue"
},
  "geometry": {"coordinates":[-0.3647989929,39.4613723755],"type":"Point"}
}