{
  "type": "Feature",
  "properties": {
    "addr:full":"Barr Andramaria De Bego\u00d1a, 26 Bilbao Vizcaya 48007",
    "addr:housenumber":"26",
    "addr:postcode":"48007",
    "iso:country":"ES",
    "sg:address":"Barr Andramaria De Bego\u00d1a, 26",
    "sg:city":"Bilbao",
    "sg:orig_category":"Imprenta",
    "sg:phone":"+34 944 46 19 20",
    "sg:postcode":"48007",
    "sg:province":"Vizcaya",
    "wof:name":"Maria Yolanda Seco Saez",
    "wof:placetype":"venue"
},
  "geometry": {"coordinates":[-2.9120941162,43.2633247375],"type":"Point"}
}