{
  "type": "Feature",
  "properties": {
    "addr:full":"Plaz Rey Don Jaime I, 3 Almansa Albacete 02640",
    "addr:postcode":"02640",
    "addr:street":"Plaz Rey Don;I",
    "iso:country":"ES",
    "sg:address":"Plaz Rey Don Jaime I, 3",
    "sg:city":"Almansa",
    "sg:orig_category":"Pod\u00d3logos: Pedicuros",
    "sg:phone":"+34 967 31 08 86",
    "sg:postcode":"02640",
    "sg:province":"Albacete",
    "wof:name":"Candel Ferrero Fernando",
    "wof:placetype":"venue"
},
  "geometry": {"coordinates":[-1.0960650444,38.8701591492],"type":"Point"}
}