{
  "type": "Feature",
  "properties": {
    "addr:full":"Calle de Maria Dolores Madaria, 3 Urdu\u00e7a-ordu\u00e7a Vizcaya 48460",
    "addr:housenumber":"3",
    "addr:postcode":"48460",
    "addr:street":"Calle De Maria Dolores Madaria",
    "iso:country":"ES",
    "sg:address":"Calle de Maria Dolores Madaria, 3",
    "sg:city":"Urdu\u00e7a-ordu\u00e7a",
    "sg:classifiers":[
        {
            "category":"Taxi",
            "type":"Transportation"
        }
    ],
    "sg:phone":"+34 945 38 38 67",
    "sg:postcode":"48460",
    "sg:province":"Vizcaya",
    "wof:name":"Sarachaga Sobera Jose Maria",
    "wof:placetype":"venue"
},
  "geometry": {"coordinates":[-3.0069389343,42.9948730469],"type":"Point"}
}