{
  "type": "Feature",
  "properties": {
    "addr:full":"Calle de Tharsis, 8 Sevilla Sevilla 41008",
    "addr:housenumber":"8",
    "addr:postcode":"41008",
    "addr:street":"Calle De Tharsis",
    "iso:country":"ES",
    "sg:address":"Calle de Tharsis, 8",
    "sg:city":"Sevilla",
    "sg:classifiers":[
        {
            "category":"Autos & Motor Vehicles",
            "subcategory":"Automobile Sales",
            "type":"Retail Goods"
        }
    ],
    "sg:phone":"+34 954 53 80 48",
    "sg:postcode":"41008",
    "sg:province":"Sevilla",
    "wof:name":"Cooperativa Sevillana De Autoescuela",
    "wof:placetype":"venue"
},
  "geometry": {"coordinates":[-5.973192215,37.3985443115],"type":"Point"}
}