{
  "type": "Feature",
  "properties": {
    "iso:country":"ES",
    "sg:address":"Calle de Reyes Catolicos, 60",
    "sg:city":"Palmas De Gran Canaria",
    "sg:orig_category":"Abogados",
    "sg:phone":"+34 928 33 23 06",
    "sg:postcode":"35001",
    "sg:province":"Las Palmas",
    "wof:name":"Berna Marquez Jose Luis",
    "wof:placetype":"venue"
},
  "geometry": {"coordinates":[-15.4146776199,28.0971813202],"type":"Point"}
}