{
  "type": "Feature",
  "properties": {
    "iso:country":"ES",
    "sg:address":"Rua Nova, 44",
    "sg:city":"Santiago De Compostela",
    "sg:orig_category":"Artesan\u00cda",
    "sg:phone":"+34 981 58 33 59",
    "sg:postcode":"15705",
    "sg:province":"La Coru\u00f1a",
    "wof:name":"Alejandro Sande Y Otro S.c.",
    "wof:placetype":"venue"
},
  "geometry": {"coordinates":[-8.5439472198,42.878036499],"type":"Point"}
}