{
  "type": "Feature",
  "properties": {
    "iso:country":"ES",
    "sg:address":"Luga Mezquez, S/n",
    "sg:city":"Pajara",
    "sg:classifiers":[
        {
            "category":"Taxi",
            "type":"Transportation"
        }
    ],
    "sg:phone":"+34 928 16 14 28",
    "sg:postcode":"35628",
    "sg:province":"Las Palmas",
    "wof:name":"Brito Hernandez Jose Miguel",
    "wof:placetype":"venue"
},
  "geometry": {"coordinates":[-14.1208333969,28.3775596619],"type":"Point"}
}