{
  "type": "Feature",
  "properties": {
    "iso:country":"ES",
    "sg:address":"Calle de Jose Nogales, 5",
    "sg:city":"Huelva",
    "sg:orig_category":"Arquitectos",
    "sg:phone":"+34 959 25 89 00",
    "sg:postcode":"21001",
    "sg:province":"Huelva",
    "wof:name":"Orozco Mu\u00f1oz Guillermo",
    "wof:placetype":"venue"
},
  "geometry": {"coordinates":[-6.9547591209,37.2577590942],"type":"Point"}
}