{
  "type": "Feature",
  "properties": {
    "addr:full":"Calle de Viticultor, 2 Jerez De La Frontera C\u00e1diz 11404",
    "addr:housenumber":"2",
    "addr:postcode":"11404",
    "addr:street":"Calle De Viticultor",
    "iso:country":"ES",
    "sg:address":"Calle de Viticultor, 2",
    "sg:city":"Jerez De La Frontera",
    "sg:orig_category":"Par\u00cds",
    "sg:phone":"+34 956 30 13 91",
    "sg:postcode":"11404",
    "sg:province":"C\u00e1diz",
    "wof:name":"Navarro Guillen Manuela",
    "wof:placetype":"venue"
},
  "geometry": {"coordinates":[-6.1492490768,36.6946105957],"type":"Point"}
}