{
  "type": "Feature",
  "properties": {
    "addr:full":"Avgd Constitucion, 10 Betera Valencia 46117",
    "addr:housenumber":"10",
    "addr:postcode":"46117",
    "addr:street":"Constitucion",
    "iso:country":"ES",
    "sg:address":"Avgd Constitucion, 10",
    "sg:city":"Betera",
    "sg:orig_category":"Delegados, Agentes De Tr\u00c1nsito, Auxiliares De Transporte Internacional",
    "sg:phone":"+34 961 60 12 47",
    "sg:postcode":"46117",
    "sg:province":"Valencia",
    "wof:name":"Trans Alba S.l.",
    "wof:placetype":"venue"
},
  "geometry": {"coordinates":[-0.4550780058,39.5889968872],"type":"Point"}
}