{
  "type": "Feature",
  "properties": {
    "iso:country":"ES",
    "sg:address":"Pol Ind Plasencia, 5",
    "sg:city":"Plasencia",
    "sg:orig_category":"Material Y Herramientas Agr\u00cdcolas",
    "sg:phone":"+34 927 42 52 65",
    "sg:postcode":"10600",
    "sg:province":"C\u00e1ceres",
    "wof:name":"Conrado Gomez S.l.",
    "wof:placetype":"venue"
},
  "geometry": {"coordinates":[-6.094684124,40.016658783],"type":"Point"}
}