{
  "type": "Feature",
  "properties": {
    "iso:country":"ES",
    "sg:address":"Avda Marques De Figueroa, 47",
    "sg:city":"Ameneiral",
    "sg:orig_category":"Loter\u00cda Y T\u00d3mbola",
    "sg:phone":"+34 981 34 40 73",
    "sg:postcode":"15500",
    "sg:province":"La Coru\u00f1a",
    "wof:name":"Blanco Otero Lucia",
    "wof:placetype":"venue"
},
  "geometry": {"coordinates":[-8.1644191742,43.4750747681],"type":"Point"}
}