{
  "type": "Feature",
  "properties": {
    "iso:country":"ES",
    "sg:address":"Alam Colon, 16",
    "sg:city":"Malaga",
    "sg:orig_category":"M\u00c9dicos: Ginecolog\u00cda Y Obstetricia",
    "sg:phone":"+34 952 22 24 66",
    "sg:postcode":"29001",
    "sg:province":"M\u00e1laga",
    "wof:name":"Garcia Garcia Jesus",
    "wof:placetype":"venue"
},
  "geometry": {"coordinates":[-4.4246897697,36.714931488],"type":"Point"}
}