{
  "type": "Feature",
  "properties": {
    "addr:full":"Carrer de Pau Claris, S/n S. Boi Llobregat Barcelona 08830",
    "addr:housenumber":"s",
    "addr:postcode":"08830",
    "addr:street":"Carrer De Pau Claris;/ N",
    "iso:country":"ES",
    "sg:address":"Carrer de Pau Claris, S/n",
    "sg:city":"S. Boi Llobregat",
    "sg:orig_category":"Electrodom\u00c9sticos (al Por Menor)",
    "sg:phone":"+34 936 40 67 04",
    "sg:postcode":"08830",
    "sg:province":"Barcelona",
    "wof:name":"Escudaga S.l.",
    "wof:placetype":"venue"
},
  "geometry": {"coordinates":[2.0370900631,41.3427238464],"type":"Point"}
}