{
  "type": "Feature",
  "properties": {
    "addr:full":"Calle de Curtidero, S/n Santa Croya De Tera Zamora 49626",
    "addr:housenumber":"s / n",
    "addr:postcode":"49626",
    "addr:street":"Calle De Curtidero",
    "iso:country":"ES",
    "sg:address":"Calle de Curtidero, S/n",
    "sg:city":"Santa Croya De Tera",
    "sg:orig_category":"Peluqueros: De Se\u00d1oras",
    "sg:phone":"+34 980 64 52 73",
    "sg:postcode":"49626",
    "sg:province":"Zamora",
    "wof:name":"Santiago Alvarez Emperatriz",
    "wof:placetype":"venue"
},
  "geometry": {"coordinates":[-5.9748888016,41.9869384766],"type":"Point"}
}