{
  "type": "Feature",
  "properties": {
    "iso:country":"ES",
    "sg:address":"Calle de Mayor, 93",
    "sg:city":"Guardo",
    "sg:orig_category":"Alimentaci\u00d3n General (al Por Menor)",
    "sg:phone":"+34 979 85 01 46",
    "sg:postcode":"34880",
    "sg:province":"Palencia",
    "wof:name":"Ruiz Mantecon Miguel",
    "wof:placetype":"venue"
},
  "geometry": {"coordinates":[-4.8401460648,42.7896194458],"type":"Point"}
}