{
  "type": "Feature",
  "properties": {
    "addr:full":"Calle de Fernando De Herrera, 8 Linares Ja\u00e9n 23700",
    "addr:housenumber":"8",
    "addr:postcode":"23700",
    "addr:street":"Calle De Fernando De Herrera;Jae\u0301N",
    "iso:country":"ES",
    "sg:address":"Calle de Fernando De Herrera, 8",
    "sg:city":"Linares",
    "sg:orig_category":"Ense\u00d1anza Secundaria: Colegios Y Escuelas Privadas",
    "sg:phone":"+34 953 65 35 86",
    "sg:postcode":"23700",
    "sg:province":"Ja\u00e9n",
    "wof:name":"Junta De Andalucia",
    "wof:placetype":"venue"
},
  "geometry": {"coordinates":[-3.6369390488,38.1101913452],"type":"Point"}
}