{
  "type": "Feature",
  "properties": {
    "addr:full":"Carrer de Selva De Mar, 239 Barcelona Barcelona 08020",
    "addr:housenumber":"239",
    "addr:postcode":"08020",
    "addr:street":"Carrer De Selva De Mar",
    "iso:country":"ES",
    "sg:address":"Carrer de Selva De Mar, 239",
    "sg:city":"Barcelona",
    "sg:orig_category":"Peluquer\u00cdas, Peluquer\u00cda Mixta",
    "sg:phone":"+34 932 66 03 86",
    "sg:postcode":"08020",
    "sg:province":"Barcelona",
    "wof:name":"Domenech Murcia Maria Isabel",
    "wof:placetype":"venue"
},
  "geometry": {"coordinates":[2.1975529194,41.4173316956],"type":"Point"}
}