{
  "type": "Feature",
  "properties": {
    "addr:full":"Calle de San Cristobal, 14 Segovia Segovia 40003",
    "addr:housenumber":"14",
    "addr:postcode":"40003",
    "addr:street":"Calle De San Cristobal",
    "iso:country":"ES",
    "sg:address":"Calle de San Cristobal, 14",
    "sg:city":"Segovia",
    "sg:orig_category":"Reposter\u00cdas",
    "sg:phone":"+34 921 43 43 45",
    "sg:postcode":"40003",
    "sg:province":"Segovia",
    "wof:name":"Martin Gomez Ricardo",
    "wof:placetype":"venue"
},
  "geometry": {"coordinates":[-4.1118888855,40.9549484253],"type":"Point"}
}