{
  "type": "Feature",
  "properties": {
    "addr:full":"Calle de Roble (del), 9 Segovia Segovia 40002",
    "addr:housenumber":"9",
    "addr:postcode":"40002",
    "addr:street":"Calle De Roble Del",
    "iso:country":"ES",
    "sg:address":"Calle de Roble (del), 9",
    "sg:city":"Segovia",
    "sg:orig_category":"Materias Pl\u00c1sticas: Productos De Consumo Masivo (fabricaci\u00d3n, Al Por Mayor)",
    "sg:phone":"+34 921 42 51 07",
    "sg:postcode":"40002",
    "sg:province":"Segovia",
    "sg:website":"www.papelalvarez.com",
    "wof:name":"Francisca Andres Ledo Y Otros C.b.",
    "wof:placetype":"venue"
},
  "geometry": {"coordinates":[-4.1175079346,40.9444885254],"type":"Point"}
}