{
  "type": "Feature",
  "properties": {
    "iso:country":"ES",
    "sg:address":"Pla\u00c7 Porta Sant Francesc, 10",
    "sg:city":"Xativa",
    "sg:orig_category":"Bancos",
    "sg:phone":"+34 962 27 71 33",
    "sg:postcode":"46800",
    "sg:province":"Valencia",
    "wof:name":"Banco Vitalicio De Espa\u00f1a C.a.",
    "wof:placetype":"venue"
},
  "geometry": {"coordinates":[-0.5219669938,38.989730835],"type":"Point"}
}