{
  "type": "Feature",
  "properties": {
    "addr:full":"Avda Murcia (de), 10 Jumilla Murcia 30520",
    "addr:housenumber":"10",
    "addr:postcode":"30520",
    "addr:street":"Avda Murcia De",
    "iso:country":"ES",
    "sg:address":"Avda Murcia (de), 10",
    "sg:city":"Jumilla",
    "sg:orig_category":"Inmobiliaria (agencias)",
    "sg:phone":"+34 968 78 03 68",
    "sg:postcode":"30520",
    "sg:province":"Murcia",
    "wof:name":"Prosejema S.l.",
    "wof:placetype":"venue"
},
  "geometry": {"coordinates":[-1.321491003,38.4757499695],"type":"Point"}
}