{
  "type": "Feature",
  "properties": {
    "addr:full":"Ctra Herrera, 11 Estepa Sevilla 41560",
    "addr:housenumber":"11",
    "addr:postcode":"41560",
    "addr:street":"Ctra Herrera;Sevilla",
    "iso:country":"ES",
    "sg:address":"Ctra Herrera, 11",
    "sg:city":"Estepa",
    "sg:orig_category":"Confiter\u00cdas, Chocolater\u00cdas (al Por Menor)",
    "sg:phone":"+34 955 91 26 81",
    "sg:postcode":"41560",
    "sg:province":"Sevilla",
    "sg:website":"www.dulces-gamito.com",
    "wof:name":"Mantecados Gamito Hermanos S.l.",
    "wof:placetype":"venue"
},
  "geometry": {"coordinates":[-4.8733940125,37.2936820984],"type":"Point"}
}