{
  "type": "Feature",
  "properties": {
    "iso:country":"ES",
    "sg:address":"Carrer de Pubilla Casas, 45",
    "sg:city":"Esplugues Llobregat",
    "sg:orig_category":"Empresas De Carpinter\u00cda",
    "sg:phone":"+34 933 71 30 28",
    "sg:postcode":"08950",
    "sg:province":"Barcelona",
    "wof:name":"Barreire Nu\u00f1ez Jose Luis",
    "wof:placetype":"venue"
},
  "geometry": {"coordinates":[2.0992159843,41.372467041],"type":"Point"}
}