{
  "type": "Feature",
  "properties": {
    "iso:country":"ES",
    "sg:address":"Calle de Balbin Busto, 12",
    "sg:city":"Villaviciosa",
    "sg:orig_category":"Ense\u00d1anza: Idiomas",
    "sg:phone":"+34 985 89 26 49",
    "sg:postcode":"33300",
    "sg:province":"Asturias",
    "wof:name":"Gonzalez Brevers Francisco",
    "wof:placetype":"venue"
},
  "geometry": {"coordinates":[-5.4341616631,43.4805145264],"type":"Point"}
}