{
  "type": "Feature",
  "properties": {
    "addr:full":"Calle de Plaza De Los Capuchinos, 7 Cintruenigo Navarra 31592",
    "addr:housenumber":"7",
    "addr:postcode":"31592",
    "addr:street":"Calle De Plaza De Los Capuchinos",
    "iso:country":"ES",
    "sg:address":"Calle de Plaza De Los Capuchinos, 7",
    "sg:city":"Cintruenigo",
    "sg:orig_category":"Transportes Por Carretera: Lotes Completos, Mercanc\u00cdas Diversas",
    "sg:phone":"+34 948 81 19 28",
    "sg:postcode":"31592",
    "sg:province":"Navarra",
    "wof:name":"Sucesores De Fernando Calavia S.a.",
    "wof:placetype":"venue"
},
  "geometry": {"coordinates":[-1.8060102463,42.083984375],"type":"Point"}
}