{
  "type": "Feature",
  "properties": {
    "iso:country":"ES",
    "sg:address":"Avda Constitucion (la), 8",
    "sg:city":"Bollullos Mitacion",
    "sg:orig_category":"Frutas Y Legumbres Frescas (al Por Mayor)",
    "sg:phone":"+34 955 76 59 73",
    "sg:postcode":"41110",
    "sg:province":"Sevilla",
    "wof:name":"Exportaciones Naranjas Bego\u00f1a S.l.",
    "wof:placetype":"venue"
},
  "geometry": {"coordinates":[-6.1363959312,37.3361129761],"type":"Point"}
}