{
  "type": "Feature",
  "properties": {
    "addr:full":"Calle de Gran Via, 15 Sax Alicante 03630",
    "addr:housenumber":"15",
    "addr:postcode":"03630",
    "addr:street":"Calle De Gran Via",
    "iso:country":"ES",
    "sg:address":"Calle de Gran Via, 15",
    "sg:city":"Sax",
    "sg:orig_category":"Asesor\u00cda Sobre Comunicaci\u00d3n De Empresas",
    "sg:phone":"+34 966 96 77 48",
    "sg:postcode":"03630",
    "sg:province":"Alicante",
    "wof:name":"Maestre Maestre S.l.",
    "wof:placetype":"venue"
},
  "geometry": {"coordinates":[-0.8192690015,38.5358352661],"type":"Point"}
}