{
  "type": "Feature",
  "properties": {
    "addr:full":"Calle de Primavera, 20 Torrejon Ardoz Madrid 28850",
    "addr:housenumber":"20",
    "addr:postcode":"28850",
    "addr:street":"Calle De Primavera",
    "iso:country":"ES",
    "sg:address":"Calle de Primavera, 20",
    "sg:city":"Torrejon Ardoz",
    "sg:orig_category":"Compresores",
    "sg:phone":"+34 916 77 04 96",
    "sg:postcode":"28850",
    "sg:province":"Madrid",
    "wof:name":"Gardner Denver Iberica S.l.",
    "wof:placetype":"venue"
},
  "geometry": {"coordinates":[-3.4846029282,40.4473457336],"type":"Point"}
}