{
  "type": "Feature",
  "properties": {
    "iso:country":"ES",
    "sg:address":"Carrer de Comer\u00c7, 84",
    "sg:city":"Hospitalet Llobregat",
    "sg:orig_category":"Cl\u00cdnicas Dentales",
    "sg:phone":"+34 934 31 15 65",
    "sg:postcode":"08902",
    "sg:province":"Barcelona",
    "wof:name":"Estrugo Devesa Albert",
    "wof:placetype":"venue"
},
  "geometry": {"coordinates":[2.1268029213,41.3636550903],"type":"Point"}
}