{
  "type": "Feature",
  "properties": {
    "iso:country":"ES",
    "sg:address":"Calle de San Jose, 23",
    "sg:city":"Rotova",
    "sg:orig_category":"Bazares, Art\u00cdculos De Limpieza Y De Cocina (al Por Menor)",
    "sg:phone":"+34 962 83 51 62",
    "sg:postcode":"46725",
    "sg:province":"Valencia",
    "wof:name":"Polop Polop Pascual",
    "wof:placetype":"venue"
},
  "geometry": {"coordinates":[-0.2580940127,38.9322662354],"type":"Point"}
}