{
  "type": "Feature",
  "properties": {
    "iso:country":"ES",
    "sg:address":"Calle de Saltona, 41",
    "sg:city":"Argana Alta",
    "sg:orig_category":"Desinfecci\u00d3n, Desinsectaci\u00d3n, Desratizaci\u00d3n",
    "sg:phone":"+34 928 80 45 14",
    "sg:postcode":"35500",
    "sg:province":"Las Palmas",
    "wof:name":"Fumigaciones Vema S.l.",
    "wof:placetype":"venue"
},
  "geometry": {"coordinates":[-13.5683736801,28.9777698517],"type":"Point"}
}