{
  "type": "Feature",
  "properties": {
    "iso:country":"ES",
    "sg:address":"Avda Andalucia, 51",
    "sg:city":"Barbate",
    "sg:orig_category":"Supermercados Y Hipermercados",
    "sg:phone":"+34 956 43 06 64",
    "sg:postcode":"11160",
    "sg:province":"C\u00e1diz",
    "wof:name":"Hermanos Calderon Y Cia Cdad",
    "wof:placetype":"venue"
},
  "geometry": {"coordinates":[-5.9242219925,36.1925086975],"type":"Point"}
}