{
  "type": "Feature",
  "properties": {
    "iso:country":"ES",
    "sg:address":"Alto De San Roque, 11",
    "sg:city":"Alto De San Roque",
    "sg:orig_category":"Maquinaria Para Industrias Diversas",
    "sg:phone":"+34 982 46 54 82",
    "sg:postcode":"27596",
    "sg:province":"Lugo",
    "wof:name":"Talleres Martin-san Roque S.l.",
    "wof:placetype":"venue"
},
  "geometry": {"coordinates":[-7.7525677681,42.6650772095],"type":"Point"}
}