{
  "type": "Feature",
  "properties": {
    "iso:country":"ES",
    "sg:address":"Calle de Principe De Asturias, 9",
    "sg:city":"Javea",
    "sg:orig_category":"Traductores",
    "sg:phone":"+34 966 46 09 24",
    "sg:postcode":"03730",
    "sg:province":"Alicante",
    "wof:name":"Bultitude  Susana",
    "wof:placetype":"venue"
},
  "geometry": {"coordinates":[0.1618050039,38.7892341614],"type":"Point"}
}