{
  "type": "Feature",
  "properties": {
    "addr:full":"Avda Camino Viejo De Torrent, 52 Alaquas Valencia 46970",
    "addr:housenumber":"52",
    "addr:postcode":"46970",
    "addr:street":"Avda Camino Viejo De Torrent",
    "iso:country":"ES",
    "sg:address":"Avda Camino Viejo De Torrent, 52",
    "sg:city":"Alaquas",
    "sg:orig_category":"Chapister\u00cda",
    "sg:phone":"+34 961 50 78 90",
    "sg:postcode":"46970",
    "sg:province":"Valencia",
    "wof:name":"1978 Carma S.l.",
    "wof:placetype":"venue"
},
  "geometry": {"coordinates":[-0.471469,39.451843],"type":"Point"}
}