{
  "type": "Feature",
  "properties": {
    "addr:full":"Calle de Labakua, 7 Elorrio Vizcaya 48230",
    "addr:housenumber":"7",
    "addr:postcode":"48230",
    "addr:street":"Calle De Labakua",
    "iso:country":"ES",
    "sg:address":"Calle de Labakua, 7",
    "sg:city":"Elorrio",
    "sg:orig_category":"Agentes Generales De Seguros",
    "sg:phone":"+34 946 58 29 27",
    "sg:postcode":"48230",
    "sg:province":"Vizcaya",
    "wof:name":"Juan Carlos Arrazola Ania",
    "wof:placetype":"venue"
},
  "geometry": {"coordinates":[-2.5461874008,43.1319122314],"type":"Point"}
}