{
  "type": "Feature",
  "properties": {
    "addr:full":"Calle de Navarra, 5 San Pedro Alcantara M\u00e1laga 29670",
    "addr:housenumber":"5",
    "addr:postcode":"29670",
    "addr:street":"Calle De Navarra",
    "iso:country":"ES",
    "sg:address":"Calle de Navarra, 5",
    "sg:city":"San Pedro Alcantara",
    "sg:orig_category":"Bebidas",
    "sg:phone":"+34 952 78 18 13",
    "sg:postcode":"29670",
    "sg:province":"M\u00e1laga",
    "wof:name":"Almacenes Paco Alvarez S.l.",
    "wof:placetype":"venue"
},
  "geometry": {"coordinates":[-4.9903764725,36.4897613525],"type":"Point"}
}