{
  "type": "Feature",
  "properties": {
    "iso:country":"ES",
    "sg:address":"Av Valencia, 14",
    "sg:city":"Molins Rei",
    "sg:orig_category":"Centros De Coordinaci\u00d3n",
    "sg:phone":"+34 936 68 23 81",
    "sg:postcode":"08750",
    "sg:province":"Barcelona",
    "wof:name":"Gestoria Fabrega Consultors S.l.",
    "wof:placetype":"venue"
},
  "geometry": {"coordinates":[2.0186240673,41.4100036621],"type":"Point"}
}