{
  "type": "Feature",
  "properties": {
    "addr:full":"Calle de Gipuzkoa, 27 Legizamon Vizcaya 48450",
    "addr:housenumber":"27",
    "addr:postcode":"48450",
    "addr:street":"Calle De Gipuzkoa",
    "iso:country":"ES",
    "sg:address":"Calle de Gipuzkoa, 27",
    "sg:city":"Legizamon",
    "sg:orig_category":"Construcciones Met\u00c1licas",
    "sg:phone":"+34 944 40 67 15",
    "sg:postcode":"48450",
    "sg:province":"Vizcaya",
    "wof:name":"Trespaderne Alvarez Francisco Javier",
    "wof:placetype":"venue"
},
  "geometry": {"coordinates":[-2.8946321011,43.2525482178],"type":"Point"}
}