{
  "type": "Feature",
  "properties": {
    "addr:full":"Calle de Campo Rey, 23 Mascaraque Toledo 45430",
    "addr:housenumber":"23",
    "addr:postcode":"45430",
    "addr:street":"Calle De Campo Rey",
    "iso:country":"ES",
    "sg:address":"Calle de Campo Rey, 23",
    "sg:city":"Mascaraque",
    "sg:orig_category":"Neum\u00c1ticos (fabricaci\u00d3n, Al Por Mayor)",
    "sg:phone":"+34 925 31 62 06",
    "sg:postcode":"45430",
    "sg:province":"Toledo",
    "wof:name":"J. Manzano Neumaticos Y Accesorios S.l.",
    "wof:placetype":"venue"
},
  "geometry": {"coordinates":[-3.8120691776,39.719039917],"type":"Point"}
}