{
  "type": "Feature",
  "properties": {
    "iso:country":"ES",
    "sg:address":"Parque Cementerio, S/n",
    "sg:city":"Campanillas",
    "sg:orig_category":"Florister\u00cdas",
    "sg:phone":"+34 952 43 42 20",
    "sg:postcode":"29590",
    "sg:province":"M\u00e1laga",
    "wof:name":"Carvajal Lara Miguel",
    "wof:placetype":"venue"
},
  "geometry": {"coordinates":[-4.5224900246,36.7190055847],"type":"Point"}
}