{
  "type": "Feature",
  "properties": {
    "iso:country":"ES",
    "sg:address":"Calle de Sevilla, 33",
    "sg:city":"Ronda",
    "sg:orig_category":"Ropa Para Se\u00d1oras Y Caballeros (al Por Menor)",
    "sg:phone":"+34 952 87 06 97",
    "sg:postcode":"29400",
    "sg:province":"M\u00e1laga",
    "wof:name":"Ramirez Conejo Andres",
    "wof:placetype":"venue"
},
  "geometry": {"coordinates":[-5.1657328606,36.7443504333],"type":"Point"}
}