{
  "type": "Feature",
  "properties": {
    "addr:full":"Rond Muralla (da), 58 Lugo Lugo 27003",
    "addr:postcode":"27003",
    "addr:street":"Rond;Da",
    "iso:country":"ES",
    "sg:address":"Rond Muralla (da), 58",
    "sg:city":"Lugo",
    "sg:orig_category":"Inform\u00c1tica, Ofim\u00c1tica (estudios, Asesor\u00cda, Ingenier\u00cda, Formaci\u00d3n)",
    "sg:phone":"+34 982 25 41 60",
    "sg:postcode":"27003",
    "sg:province":"Lugo",
    "wof:name":"Instituto De Formacion Y Asuntos Sociales",
    "wof:placetype":"venue"
},
  "geometry": {"coordinates":[-7.5763959885,43.0335426331],"type":"Point"}
}