{
  "type": "Feature",
  "properties": {
    "addr:full":"Calle de Juan De Castilla, 3 Palencia Palencia 34001",
    "addr:housenumber":"3",
    "addr:postcode":"34001",
    "addr:street":"Calle De Juan De Castilla",
    "iso:country":"ES",
    "sg:address":"Calle de Juan De Castilla, 3",
    "sg:city":"Palencia",
    "sg:orig_category":"Producci\u00d3n, Comercio De Cereales",
    "sg:phone":"+34 979 70 04 72",
    "sg:postcode":"34001",
    "sg:province":"Palencia",
    "wof:name":"Cereales Y Abonos Mu\u00d1oz",
    "wof:placetype":"venue"
},
  "geometry": {"coordinates":[-4.5350298882,42.0113525391],"type":"Point"}
}