{
  "type": "Feature",
  "properties": {
    "addr:full":"Calle de Andalucia, 7 Arroyo De La Miel-benalmadena Costa M\u00e1laga 29631",
    "addr:housenumber":"7",
    "addr:postcode":"29631",
    "addr:street":"Calle De Andalucia;Arroyo De La Miel-Benalmadena Costa Ma\u0301Laga",
    "iso:country":"ES",
    "sg:address":"Calle de Andalucia, 7",
    "sg:city":"Arroyo De La Miel-benalmadena Costa",
    "sg:orig_category":"Colchones (fabricaci\u00d3n, Al Por Mayor, Al Por Menor)",
    "sg:phone":"+34 952 44 64 49",
    "sg:postcode":"29631",
    "sg:province":"M\u00e1laga",
    "wof:name":"Moreno Rose Esteban",
    "wof:placetype":"venue"
},
  "geometry": {"coordinates":[-4.5344848633,36.5976448059],"type":"Point"}
}