{
  "type": "Feature",
  "properties": {
    "iso:country":"ES",
    "sg:address":"Rua Benigno Quiroga, 1",
    "sg:city":"Sarria",
    "sg:orig_category":"Reposter\u00cdas",
    "sg:phone":"+34 982 53 33 34",
    "sg:postcode":"27600",
    "sg:province":"Lugo",
    "wof:name":"Garcia Martinez Tarcisio",
    "wof:placetype":"venue"
},
  "geometry": {"coordinates":[-7.4150738716,42.7694473267],"type":"Point"}
}