{
  "type": "Feature",
  "properties": {
    "iso:country":"ES",
    "sg:address":"Calle de Mesnaderos, 7",
    "sg:city":"Huesca",
    "sg:orig_category":"Fotocopias, Reprograf\u00cda",
    "sg:phone":"+34 974 22 75 46",
    "sg:postcode":"22003",
    "sg:province":"Huesca",
    "wof:name":"Copisteria Delycom S.l.u",
    "wof:placetype":"venue"
},
  "geometry": {"coordinates":[-0.4121100008,42.1394805908],"type":"Point"}
}