{
  "type": "Feature",
  "properties": {
    "iso:country":"ES",
    "sg:address":"Luga Rematacaudales, Km. 0001,0",
    "sg:city":"Miraflores",
    "sg:orig_category":"Maquinaria Para Industrias Diversas",
    "sg:phone":"+34 956 38 50 43",
    "sg:postcode":"11540",
    "sg:province":"C\u00e1diz",
    "sg:website":"www.arozama.com",
    "wof:name":"Aromaza S.l.",
    "wof:placetype":"venue"
},
  "geometry": {"coordinates":[-6.29240942,36.5299415588],"type":"Point"}
}