{
  "type": "Feature",
  "properties": {
    "addr:full":"Calle de Sequia Real Del Xuquer, 19 Alberic Valencia 46260",
    "addr:housenumber":"19",
    "addr:postcode":"46260",
    "addr:street":"Calle De Sequia Real Del Xuquer",
    "iso:country":"ES",
    "sg:address":"Calle de Sequia Real Del Xuquer, 19",
    "sg:city":"Alberic",
    "sg:orig_category":"Supermercados Y Hipermercados",
    "sg:phone":"+34 962 44 23 46",
    "sg:postcode":"46260",
    "sg:province":"Valencia",
    "sg:website":"www.mercadona.es",
    "wof:name":"Mercadona S.a.",
    "wof:placetype":"venue"
},
  "geometry": {"coordinates":[-0.5206760168,39.115234375],"type":"Point"}
}