{
  "type": "Feature",
  "properties": {
    "iso:country":"ES",
    "sg:address":"Carrer de Doctor Mallafre Guasch, 4",
    "sg:city":"Tarragona",
    "sg:orig_category":"Bibliotecas, Mediatecas",
    "sg:phone":"+34 977 22 77 53",
    "sg:postcode":"43007",
    "sg:province":"Tarragona",
    "wof:name":"Iron Mountain Espa\u00f1a S.a.",
    "wof:placetype":"venue"
},
  "geometry": {"coordinates":[1.238888979,41.1237716675],"type":"Point"}
}