{
  "type": "Feature",
  "properties": {
    "addr:full":"Calle de Donantes De Sangre, 1 Coru\u00d1a La Coru\u00f1a 15004",
    "addr:housenumber":"1",
    "addr:postcode":"15004",
    "addr:street":"Calle De Donantes De Sangre;La Corun\u0303A",
    "iso:country":"ES",
    "sg:address":"Calle de Donantes De Sangre, 1",
    "sg:city":"Coru\u00d1a",
    "sg:orig_category":"M\u00c9dicos: Estomatolog\u00cda",
    "sg:phone":"+34 981 26 53 32",
    "sg:postcode":"15004",
    "sg:province":"La Coru\u00f1a",
    "wof:name":"Pardo Porta Ignacio",
    "wof:placetype":"venue"
},
  "geometry": {"coordinates":[-8.4096317291,43.3659515381],"type":"Point"}
}