{
  "type": "Feature",
  "properties": {
    "iso:country":"ES",
    "sg:address":"Carrer de Puigterra De Dalt, 8",
    "sg:city":"Manresa",
    "sg:orig_category":"Fabricaci\u00d3n De Muebles",
    "sg:phone":"+34 938 72 19 25",
    "sg:postcode":"08241",
    "sg:province":"Barcelona",
    "wof:name":"Mobles Pujol S.c.p.",
    "wof:placetype":"venue"
},
  "geometry": {"coordinates":[1.8273370266,41.7253913879],"type":"Point"}
}