{
  "type": "Feature",
  "properties": {
    "addr:full":"Calle de Pintor Rosales, S/n Linares Ja\u00e9n 23700",
    "addr:housenumber":"/ n",
    "addr:postcode":"23700",
    "addr:street":"Calle De Pintor Rosales S;Jae\u0301N",
    "iso:country":"ES",
    "sg:address":"Calle de Pintor Rosales, S/n",
    "sg:city":"Linares",
    "sg:orig_category":"Mensajer\u00cda Express, Portes Internacionales",
    "sg:phone":"+34 953 69 96 17",
    "sg:postcode":"23700",
    "sg:province":"Ja\u00e9n",
    "sg:website":"www.seur.es",
    "wof:name":"Red Transjaen S.l.",
    "wof:placetype":"venue"
},
  "geometry": {"coordinates":[-3.6408340931,38.0929107666],"type":"Point"}
}