{
  "type": "Feature",
  "properties": {
    "addr:full":"Calle de Diaz Del Moral, 2 Salobre\u00f1a Granada 18680",
    "addr:housenumber":"2",
    "addr:postcode":"18680",
    "addr:street":"Calle De Diaz Del Moral",
    "iso:country":"ES",
    "sg:address":"Calle de Diaz Del Moral, 2",
    "sg:city":"Salobre\u00f1a",
    "sg:orig_category":"Ropa Para Se\u00d1oras (al Por Menor)",
    "sg:phone":"+34 958 61 28 69",
    "sg:postcode":"18680",
    "sg:province":"Granada",
    "wof:name":"Tendencias Mavisa S.l.",
    "wof:placetype":"venue"
},
  "geometry": {"coordinates":[-3.5829689503,36.7435760498],"type":"Point"}
}