{
  "type": "Feature",
  "properties": {
    "addr:full":"Calle de Gran Via, 60 Madrid Madrid 28013",
    "addr:housenumber":"60",
    "addr:postcode":"madrid;28013",
    "addr:street":"Calle De Gran Via",
    "iso:country":"ES",
    "sg:address":"Calle de Gran Via, 60",
    "sg:city":"Madrid",
    "sg:orig_category":"Ense\u00d1anza Variada",
    "sg:phone":"+34 915 40 02 36",
    "sg:postcode":"28013",
    "sg:province":"Madrid",
    "sg:website":"www.arrobaestudios.iespana.es",
    "wof:name":"Torron Sl",
    "wof:placetype":"venue"
},
  "geometry": {"coordinates":[-3.7082650661,40.4219017029],"type":"Point"}
}