{
  "type": "Feature",
  "properties": {
    "addr:full":"Calle de Oro, 34 Valladolid Valladolid 47012",
    "addr:housenumber":"34",
    "addr:postcode":"47012",
    "addr:street":"Calle De Oro",
    "iso:country":"ES",
    "sg:address":"Calle de Oro, 34",
    "sg:city":"Valladolid",
    "sg:orig_category":"Electricidad: Instaladores",
    "sg:phone":"+34 983 39 12 14",
    "sg:postcode":"47012",
    "sg:province":"Valladolid",
    "wof:name":"Cobra Instalaciones Y Servicios, S.a.",
    "wof:placetype":"venue"
},
  "geometry": {"coordinates":[-4.7037158012,41.6171302795],"type":"Point"}
}