{
  "type": "Feature",
  "properties": {
    "iso:country":"ES",
    "sg:address":"Calle de Huerta (la), 64",
    "sg:city":"San Vicente Del Raspeig-sant Vicent Del Raspeig",
    "sg:orig_category":"Cr\u00cda De Animales",
    "sg:phone":"+34 965 66 75 44",
    "sg:postcode":"03690",
    "sg:province":"Alicante",
    "sg:website":"www.eusgar.com",
    "wof:name":"Centro Veterinario Eusgar S.l.",
    "wof:placetype":"venue"
},
  "geometry": {"coordinates":[-0.5190629959,38.3991966248],"type":"Point"}
}