{
  "type": "Feature",
  "properties": {
    "iso:country":"ES",
    "sg:address":"Calle de Hospital Militar, 16",
    "sg:city":"Burgos",
    "sg:orig_category":"Transportes Por V\u00cdas Navegables",
    "sg:phone":"+34 947 20 77 23",
    "sg:postcode":"09002",
    "sg:province":"Burgos",
    "wof:name":"Arroyo Garcia Elisa",
    "wof:placetype":"venue"
},
  "geometry": {"coordinates":[-3.7035119534,42.3375968933],"type":"Point"}
}