{
  "type": "Feature",
  "properties": {
    "addr:full":"Calle de Real, 198 Fuensanta Martos Ja\u00e9n 23610",
    "addr:housenumber":"198",
    "addr:postcode":"23610",
    "addr:street":"Calle De Real",
    "iso:country":"ES",
    "sg:address":"Calle de Real, 198",
    "sg:city":"Fuensanta Martos",
    "sg:orig_category":"Empresas De Carpinter\u00cda Met\u00c1lica",
    "sg:phone":"+34 953 56 50 58",
    "sg:postcode":"23610",
    "sg:province":"Ja\u00e9n",
    "wof:name":"Pe\u00f1a Planelles Jose Antonio",
    "wof:placetype":"venue"
},
  "geometry": {"coordinates":[-3.9129068851,37.6459579468],"type":"Point"}
}