{
  "type": "Feature",
  "properties": {
    "addr:full":"Calle de Orense, 10 Madrid Madrid 28020",
    "addr:housenumber":"10",
    "addr:postcode":"madrid;28020",
    "addr:street":"Calle De Orense",
    "iso:country":"ES",
    "sg:address":"Calle de Orense, 10",
    "sg:city":"Madrid",
    "sg:orig_category":"Agricultura: Abastecimiento Y Cosechado (negocio)",
    "sg:phone":"+34 915 56 61 21",
    "sg:postcode":"28020",
    "sg:province":"Madrid",
    "wof:name":"El Quintillo S.a.t.",
    "wof:placetype":"venue"
},
  "geometry": {"coordinates":[-3.6951830387,40.4485702515],"type":"Point"}
}