{
  "type": "Feature",
  "properties": {
    "iso:country":"ES",
    "sg:address":"Zona Aeroport, S/n",
    "sg:city":"Prat Llobregat",
    "sg:orig_category":"Delegados, Agentes De Tr\u00c1nsito, Auxiliares De Transporte Internacional",
    "sg:phone":"+34 933 79 29 47",
    "sg:postcode":"08820",
    "sg:province":"Barcelona",
    "wof:name":"Trans Junior S.l.",
    "wof:placetype":"venue"
},
  "geometry": {"coordinates":[2.0864720345,41.3289909363],"type":"Point"}
}