{
  "type": "Feature",
  "properties": {
    "iso:country":"ES",
    "sg:address":"Calle de Gara Y Jonay, 1",
    "sg:city":"Santa Cruz De Tenerife",
    "sg:orig_category":"Asociaciones Humanitarias, De Cooperaci\u00d3n, De Acci\u00d3n Social",
    "sg:phone":"+34 922 64 40 51",
    "sg:postcode":"38010",
    "sg:province":"Santa Cruz De Tenerife",
    "wof:name":"Fundacion Sagrada Familia",
    "wof:placetype":"venue"
},
  "geometry": {"coordinates":[-16.3302192688,28.4371891022],"type":"Point"}
}