{
  "type": "Feature",
  "properties": {
    "iso:country":"ES",
    "sg:address":"Avda Manuel Martin, 21",
    "sg:city":"Torno",
    "sg:classifiers":[
        {
            "category":"Taxi",
            "type":"Transportation"
        }
    ],
    "sg:phone":"+34 927 17 51 48",
    "sg:postcode":"10617",
    "sg:province":"C\u00e1ceres",
    "wof:name":"Riolobos Garcia Maximo",
    "wof:placetype":"venue"
},
  "geometry": {"coordinates":[-5.9428920746,40.1353683472],"type":"Point"}
}