{
  "type": "Feature",
  "properties": {
    "addr:full":"Calle de Isabel Cabral, 4 Ceuta Ceuta 51001",
    "addr:housenumber":"4",
    "addr:postcode":"51001",
    "addr:street":"Calle De Isabel Cabral",
    "iso:country":"ES",
    "sg:address":"Calle de Isabel Cabral, 4",
    "sg:city":"Ceuta",
    "sg:orig_category":"Empresas De Vigilancia, Guardia Y Protecci\u00d3n",
    "sg:phone":"+34 956 51 43 94",
    "sg:postcode":"51001",
    "sg:province":"Ceuta",
    "sg:website":"www.serramar.com",
    "wof:name":"Serramar Vigilancia Y Seguridad S.l.",
    "wof:placetype":"venue"
},
  "geometry": {"coordinates":[-5.3067069054,35.888004303],"type":"Point"}
}