{
  "type": "Feature",
  "properties": {
    "iso:country":"ES",
    "sg:address":"Calle de Valmojado, 121",
    "sg:city":"Madrid",
    "sg:orig_category":"Carnicer\u00cdas, Carnicer\u00cdas",
    "sg:phone":"+34 917 18 22 40",
    "sg:postcode":"28047",
    "sg:province":"Madrid",
    "wof:name":"Pajares Anta Rogelio",
    "wof:placetype":"venue"
},
  "geometry": {"coordinates":[-3.7582490444,40.3924293518],"type":"Point"}
}