{
  "type": "Feature",
  "properties": {
    "iso:country":"ES",
    "sg:address":"San Agustin, 3",
    "sg:city":"Iru\u00f1a",
    "sg:orig_category":"Comunidades Religiosas",
    "sg:phone":"+34 948 22 04 24",
    "sg:postcode":"31001",
    "sg:province":"Navarra",
    "wof:name":"Cursillos De Cristiandad",
    "wof:placetype":"venue"
},
  "geometry": {"coordinates":[-1.6410900354,42.8177337646],"type":"Point"}
}