{
  "type": "Feature",
  "properties": {
    "addr:full":"Calle de Vides, S/n Tomares Sevilla 41940",
    "addr:housenumber":"s / n",
    "addr:postcode":"41940",
    "addr:street":"Calle De Vides",
    "iso:country":"ES",
    "sg:address":"Calle de Vides, S/n",
    "sg:city":"Tomares",
    "sg:orig_category":"Agencias Y Agentes Comerciales, Representantes",
    "sg:phone":"+34 954 15 10 76",
    "sg:postcode":"41940",
    "sg:province":"Sevilla",
    "wof:name":"Avivar Contreras Manuel",
    "wof:placetype":"venue"
},
  "geometry": {"coordinates":[-6.0463480949,37.377784729],"type":"Point"}
}