{
  "type": "Feature",
  "properties": {
    "addr:full":"Calle de Daniel Del Olmo Gonzalez, 43 Valladolid Valladolid 47008",
    "addr:housenumber":"43",
    "addr:postcode":"47008",
    "addr:street":"Calle De Daniel Del Olmo Gonzalez",
    "iso:country":"ES",
    "sg:address":"Calle de Daniel Del Olmo Gonzalez, 43",
    "sg:city":"Valladolid",
    "sg:classifiers":[
        {
            "category":"Communications",
            "type":"Services"
        }
    ],
    "sg:phone":"+34 983 22 19 80",
    "sg:postcode":"47008",
    "sg:province":"Valladolid",
    "sg:tags":[
        "televisiones",
        "y",
        "radio"
    ],
    "wof:name":"Remar Espa\u00f1a",
    "wof:placetype":"venue"
},
  "geometry": {"coordinates":[-4.734685421,41.6283149719],"type":"Point"}
}