{
  "type": "Feature",
  "properties": {
    "addr:full":"Carrer de Cristofor Colom, 14 Manresa Barcelona 08242",
    "addr:housenumber":"14",
    "addr:postcode":"08242",
    "addr:street":"Carrer De Cristofor Colom",
    "iso:country":"ES",
    "sg:address":"Carrer de Cristofor Colom, 14",
    "sg:city":"Manresa",
    "sg:orig_category":"Productos Qu\u00cdmicos (fabricaci\u00d3n, Al Por Mayor)",
    "sg:phone":"+34 938 73 28 07",
    "sg:postcode":"08242",
    "sg:province":"Barcelona",
    "sg:website":"www.stempelteqt.com",
    "wof:name":"Stempel Tqt S.l.",
    "wof:placetype":"venue"
},
  "geometry": {"coordinates":[1.8186099529,41.7394714355],"type":"Point"}
}