{
  "type": "Feature",
  "properties": {
    "addr:full":"Avgd Paiporta, 72 Benetusser Valencia 46910",
    "addr:housenumber":"72",
    "addr:postcode":"46910",
    "addr:street":"Paiporta",
    "iso:country":"ES",
    "sg:address":"Avgd Paiporta, 72",
    "sg:city":"Benetusser",
    "sg:orig_category":"Carnicer\u00cdas, Carnicer\u00cdas",
    "sg:phone":"+34 963 18 50 47",
    "sg:postcode":"46910",
    "sg:province":"Valencia",
    "wof:name":"Torres Torres Tomas",
    "wof:placetype":"venue"
},
  "geometry": {"coordinates":[-0.3992800117,39.42527771],"type":"Point"}
}