{
  "type": "Feature",
  "properties": {
    "iso:country":"ES",
    "sg:address":"Calle de Joaquin Jose Landazuri, 7",
    "sg:city":"Vitoria-gasteiz",
    "sg:orig_category":"M\u00c9dicos: Estomatolog\u00cda",
    "sg:phone":"+34 945 13 12 66",
    "sg:postcode":"01008",
    "sg:province":"\u00c1lava",
    "wof:name":"Bilbao Anitua Jesus",
    "wof:placetype":"venue"
},
  "geometry": {"coordinates":[-2.6770789623,42.8475341797],"type":"Point"}
}