{
  "type": "Feature",
  "properties": {
    "addr:full":"Calle de Castilla, 44 Matas-pinar-monte Rozas Madrid 28290",
    "addr:housenumber":"44",
    "addr:postcode":"28290",
    "addr:street":"Calle De Castilla",
    "iso:country":"ES",
    "sg:address":"Calle de Castilla, 44",
    "sg:city":"Matas-pinar-monte Rozas",
    "sg:orig_category":"Organizaciones Internacionales",
    "sg:phone":"+34 916 30 34 15",
    "sg:postcode":"28290",
    "sg:province":"Madrid",
    "wof:name":"Asociacion Manos Mundi",
    "wof:placetype":"venue"
},
  "geometry": {"coordinates":[-3.9152576923,40.5226135254],"type":"Point"}
}