{
  "type": "Feature",
  "properties": {
    "iso:country":"ES",
    "sg:address":"Calle de Villafranca Del Bierzo, 21",
    "sg:city":"Fuenlabrada",
    "sg:orig_category":"Bazares, Art\u00cdculos De Limpieza Y De Cocina (al Por Menor)",
    "sg:phone":"+34 916 42 17 57",
    "sg:postcode":"28947",
    "sg:province":"Madrid",
    "wof:name":"Pin Pin Regalos S.l.",
    "wof:placetype":"venue"
},
  "geometry": {"coordinates":[-3.7465589046,40.2651405334],"type":"Point"}
}