{
  "type": "Feature",
  "properties": {
    "addr:full":"Avda Pirineos (de Los), 7 San Sebastian De Los Reyes Madrid 28700",
    "addr:housenumber":"7",
    "addr:postcode":"28700",
    "addr:street":"Avda Pirineos De Los",
    "iso:country":"ES",
    "sg:address":"Avda Pirineos (de Los), 7",
    "sg:city":"San Sebastian De Los Reyes",
    "sg:orig_category":"Promotores Constructores",
    "sg:phone":"+34 916 58 67 53",
    "sg:postcode":"28700",
    "sg:province":"Madrid",
    "wof:name":"Proimfa Promociones S.a.",
    "wof:placetype":"venue"
},
  "geometry": {"coordinates":[-3.6103610992,40.5487136841],"type":"Point"}
}