{
  "type": "Feature",
  "properties": {
    "iso:country":"ES",
    "sg:address":"Poli Industrial, 29",
    "sg:city":"S. Adrian",
    "sg:orig_category":"Suministros Y Materiales Industriales",
    "sg:phone":"+34 948 67 04 80",
    "sg:postcode":"31570",
    "sg:province":"Navarra",
    "sg:website":"www.repuestosebro.com",
    "wof:name":"Repuestos Industriales Ebro S.a.",
    "wof:placetype":"venue"
},
  "geometry": {"coordinates":[-1.9321240187,42.33335495],"type":"Point"}
}