{
  "type": "Feature",
  "properties": {
    "addr:full":"Carrer de Rafael De Casanova, 8 Molins Rei Barcelona 08750",
    "addr:housenumber":"8",
    "addr:postcode":"08750",
    "addr:street":"Carrer De Rafael De Casanova;Barcelona",
    "iso:country":"ES",
    "sg:address":"Carrer de Rafael De Casanova, 8",
    "sg:city":"Molins Rei",
    "sg:orig_category":"Herboristas (al Por Menor)",
    "sg:phone":"+34 936 68 74 07",
    "sg:postcode":"08750",
    "sg:province":"Barcelona",
    "wof:name":"Puyana Guerrero Manuela",
    "wof:placetype":"venue"
},
  "geometry": {"coordinates":[2.018693924,41.4110717773],"type":"Point"}
}