{
  "type": "Feature",
  "properties": {
    "iso:country":"ES",
    "sg:address":"Avda Miguel De Cervantes, 38",
    "sg:city":"Tarancon",
    "sg:orig_category":"Abogados",
    "sg:phone":"+34 969 32 51 19",
    "sg:postcode":"16400",
    "sg:province":"Cuenca",
    "wof:name":"Zarzuela Garcia Pedro Angel",
    "wof:placetype":"venue"
},
  "geometry": {"coordinates":[-3.0108091831,40.0101127625],"type":"Point"}
}