{
  "type": "Feature",
  "properties": {
    "addr:full":"Rua San Sebastian, S/n Xinzo De Limia Ourense 32630",
    "addr:housenumber":"s",
    "addr:postcode":"32630",
    "addr:street":"Rua San Sebastian;/ N",
    "iso:country":"ES",
    "sg:address":"Rua San Sebastian, S/n",
    "sg:city":"Xinzo De Limia",
    "sg:orig_category":"Mec\u00c1nico Del Autom\u00d3vil",
    "sg:phone":"+34 988 46 05 41",
    "sg:postcode":"32630",
    "sg:province":"Ourense",
    "wof:name":"Lopez Taboada Camilo",
    "wof:placetype":"venue"
},
  "geometry": {"coordinates":[-7.722094059,42.0643386841],"type":"Point"}
}