{
  "type": "Feature",
  "properties": {
    "addr:full":"Calle de Pintor Cabrera, 12 Alacant Alicante 03003",
    "addr:housenumber":"12",
    "addr:postcode":"03003",
    "addr:street":"Calle De Pintor Cabrera",
    "iso:country":"ES",
    "sg:address":"Calle de Pintor Cabrera, 12",
    "sg:city":"Alacant",
    "sg:orig_category":"Ropa Para Se\u00d1oras (al Por Menor)",
    "sg:phone":"+34 965 13 22 05",
    "sg:postcode":"03003",
    "sg:province":"Alicante",
    "wof:name":"Gandolfo Hernandez Josefa",
    "wof:placetype":"venue"
},
  "geometry": {"coordinates":[-0.4914050102,38.3448410034],"type":"Point"}
}