{
  "type": "Feature",
  "properties": {
    "iso:country":"ES",
    "sg:address":"Plaz San Francisco, 2",
    "sg:city":"Monzon",
    "sg:orig_category":"Reposter\u00cdas",
    "sg:phone":"+34 974 41 62 66",
    "sg:postcode":"22400",
    "sg:province":"Huesca",
    "wof:name":"Ordobas Heras Javier Antonio",
    "wof:placetype":"venue"
},
  "geometry": {"coordinates":[0.1915819943,41.9130134583],"type":"Point"}
}