{
  "type": "Feature",
  "properties": {
    "iso:country":"ES",
    "sg:address":"Avda Constitucion (la), 43",
    "sg:city":"Algodonales",
    "sg:orig_category":"Iglesia Cat\u00d3lica",
    "sg:phone":"+34 956 13 70 83",
    "sg:postcode":"11680",
    "sg:province":"C\u00e1diz",
    "wof:name":"Parroquia De Santa Ana",
    "wof:placetype":"venue"
},
  "geometry": {"coordinates":[-5.4065451622,36.880569458],"type":"Point"}
}