{
  "type": "Feature",
  "properties": {
    "iso:country":"ES",
    "sg:address":"Avda Cayetano Feu, 1",
    "sg:city":"Ayamonte",
    "sg:orig_category":"Molduras, Junquillos, Listones Y Molduras Perforadas",
    "sg:phone":"+34 959 32 00 95",
    "sg:postcode":"21400",
    "sg:province":"Huelva",
    "wof:name":"Garcia Landero Antonio",
    "wof:placetype":"venue"
},
  "geometry": {"coordinates":[-7.3995881081,37.2153358459],"type":"Point"}
}