{
  "type": "Feature",
  "properties": {
    "iso:country":"ES",
    "sg:address":"Ctra Arevalo-erillas, Km. 0005,5",
    "sg:city":"Serillas",
    "sg:orig_category":"Producci\u00d3n De Abonos Y De Fertilizantes",
    "sg:phone":"+34 921 43 00 83",
    "sg:postcode":"40003",
    "sg:province":"Segovia",
    "wof:name":"Campo Segoviano Ii S. Coop. Ltda.",
    "wof:placetype":"venue"
},
  "geometry": {"coordinates":[-4.1387348175,40.9539337158],"type":"Point"}
}