{
  "type": "Feature",
  "properties": {
    "addr:full":"Calle de Virgen Del Rosario, 1 Alhaurin El Grande M\u00e1laga 29120",
    "addr:housenumber":"1",
    "addr:postcode":"29120",
    "addr:street":"Calle De Virgen Del Rosario",
    "iso:country":"ES",
    "sg:address":"Calle de Virgen Del Rosario, 1",
    "sg:city":"Alhaurin El Grande",
    "sg:orig_category":"Asociaciones Y Clubs Deportivos",
    "sg:phone":"+34 952 59 47 76",
    "sg:postcode":"29120",
    "sg:province":"M\u00e1laga",
    "wof:name":"Castillo Ortu\u00f1o Antonio",
    "wof:placetype":"venue"
},
  "geometry": {"coordinates":[-4.6854400635,36.643913269],"type":"Point"}
}