{
  "type": "Feature",
  "properties": {
    "addr:full":"Calle de Monasterio Santa Catalina, S/n Zaragoza Zaragoza 50002",
    "addr:housenumber":"s / n",
    "addr:postcode":"50002",
    "addr:street":"Calle De Monasterio Santa Catalina",
    "iso:country":"ES",
    "sg:address":"Calle de Monasterio Santa Catalina, S/n",
    "sg:city":"Zaragoza",
    "sg:orig_category":"Molduras, Junquillos, Listones Y Molduras Perforadas",
    "sg:phone":"+34 976 49 85 61",
    "sg:postcode":"50002",
    "sg:province":"Zaragoza",
    "wof:name":"Oca\u00f1a Roldan Fernando",
    "wof:placetype":"venue"
},
  "geometry": {"coordinates":[-0.8605648875,41.6446800232],"type":"Point"}
}