{
  "type": "Feature",
  "properties": {
    "addr:full":"Calle de Mayor, 137 Llano De Brujas Murcia 30161",
    "addr:housenumber":"137",
    "addr:postcode":"30161",
    "addr:street":"Calle De Mayor",
    "iso:country":"ES",
    "sg:address":"Calle de Mayor, 137",
    "sg:city":"Llano De Brujas",
    "sg:orig_category":"Transportes Por V\u00cdas Navegables",
    "sg:phone":"+34 968 81 14 19",
    "sg:postcode":"30161",
    "sg:province":"Murcia",
    "wof:name":"Bravo Zapata Antonio Manuel",
    "wof:placetype":"venue"
},
  "geometry": {"coordinates":[-1.0689790249,38.0063896179],"type":"Point"}
}