{
  "type": "Feature",
  "properties": {
    "addr:full":"Rua Candido Acu\u00d1a Blanco, 4 Grove Pontevedra 36980",
    "addr:housenumber":"4",
    "addr:postcode":"36980",
    "addr:street":"Rua Candido Acun\u0303A Blanco",
    "iso:country":"ES",
    "sg:address":"Rua Candido Acu\u00d1a Blanco, 4",
    "sg:city":"Grove",
    "sg:orig_category":"Cl\u00cdnicas Dentales",
    "sg:phone":"+34 986 73 04 00",
    "sg:postcode":"36980",
    "sg:province":"Pontevedra",
    "wof:name":"Muruais Gonzalez Luis",
    "wof:placetype":"venue"
},
  "geometry": {"coordinates":[-8.8635253906,42.4955024719],"type":"Point"}
}