{
  "type": "Feature",
  "properties": {
    "iso:country":"ES",
    "sg:address":"Carrer de Mallorca, 152",
    "sg:city":"Barcelona",
    "sg:orig_category":"Asesores De Gesti\u00d3n Del Patrimonio",
    "sg:phone":"+34 933 23 26 17",
    "sg:postcode":"08036",
    "sg:province":"Barcelona",
    "wof:name":"Feirelmo S.l.",
    "wof:placetype":"venue"
},
  "geometry": {"coordinates":[2.1547820568,41.3877868652],"type":"Point"}
}