{
  "type": "Feature",
  "properties": {
    "addr:full":"Calle de Puja Del Fielato, 20 Villalonga Valencia 46720",
    "addr:housenumber":"20",
    "addr:postcode":"46720",
    "addr:street":"Calle De Puja Del Fielato",
    "iso:country":"ES",
    "sg:address":"Calle de Puja Del Fielato, 20",
    "sg:city":"Villalonga",
    "sg:orig_category":"Estancos",
    "sg:phone":"+34 962 81 73 93",
    "sg:postcode":"46720",
    "sg:province":"Valencia",
    "wof:name":"Ferrando Bataller Isidro",
    "wof:placetype":"venue"
},
  "geometry": {"coordinates":[-0.2102890015,38.8871841431],"type":"Point"}
}