{
  "type": "Feature",
  "properties": {
    "addr:full":"Carr Terri, 16 Platja D'aro Girona 17250",
    "addr:housenumber":"16",
    "addr:postcode":"17250",
    "addr:street":"Carr Terri",
    "iso:country":"ES",
    "sg:address":"Carr Terri, 16",
    "sg:city":"Platja D'aro",
    "sg:classifiers":[
        {
            "category":"Taxi",
            "type":"Transportation"
        }
    ],
    "sg:phone":"+34 972 81 86 39",
    "sg:postcode":"17250",
    "sg:province":"Girona",
    "wof:name":"Magide Varela Antonio",
    "wof:placetype":"venue"
},
  "geometry": {"coordinates":[2.8160719872,41.968082428],"type":"Point"}
}