{
  "type": "Feature",
  "properties": {
    "addr:full":"Calle de Baron De La Torre, 50 Cintruenigo Navarra 31592",
    "addr:housenumber":"50",
    "addr:postcode":"31592",
    "addr:street":"Calle De Baron De La Torre",
    "iso:country":"ES",
    "sg:address":"Calle de Baron De La Torre, 50",
    "sg:city":"Cintruenigo",
    "sg:orig_category":"Bancos",
    "sg:phone":"+34 948 81 13 25",
    "sg:postcode":"31592",
    "sg:province":"Navarra",
    "wof:name":"Banco De Vasconia",
    "wof:placetype":"venue"
},
  "geometry": {"coordinates":[-1.8085589409,42.0796546936],"type":"Point"}
}