{
  "type": "Feature",
  "properties": {
    "iso:country":"ES",
    "sg:address":"Pase Arroyomolinos (de), 4",
    "sg:city":"Mostoles",
    "sg:orig_category":"Asociaciones Y Clubs Deportivos",
    "sg:phone":"+34 916 18 31 79",
    "sg:postcode":"28934",
    "sg:province":"Madrid",
    "wof:name":"Lacri's Y Molina S.l.",
    "wof:placetype":"venue"
},
  "geometry": {"coordinates":[-3.866902113,40.3202438354],"type":"Point"}
}