{
  "type": "Feature",
  "properties": {
    "iso:country":"ES",
    "sg:address":"Calle de Galeon, 27",
    "sg:city":"Madrid",
    "sg:orig_category":"Peluquer\u00cdas, Peluquer\u00cda Mixta",
    "sg:phone":"+34 917 47 57 58",
    "sg:postcode":"28042",
    "sg:province":"Madrid",
    "wof:name":"Fernandez Pardo Maria Del Pilar",
    "wof:placetype":"venue"
},
  "geometry": {"coordinates":[-3.582041502,40.4588279724],"type":"Point"}
}