{
  "type": "Feature",
  "properties": {
    "iso:country":"ES",
    "sg:address":"Calle de Virgen De Guadalupe, 3",
    "sg:city":"Badajoz",
    "sg:orig_category":"Muebles Y Accesorios Para Cocinas Y Cuartos De Ba\u00d1o (al Por Menor)",
    "sg:phone":"+34 924 23 23 17",
    "sg:postcode":"06004",
    "sg:province":"Badajoz",
    "wof:name":"Escobar Becerra Eugenio",
    "wof:placetype":"venue"
},
  "geometry": {"coordinates":[-6.9723510742,38.8709335327],"type":"Point"}
}