{
  "type": "Feature",
  "properties": {
    "addr:full":"Carrer de Enten\u00c7a, 332 Barcelona Barcelona 08029",
    "addr:housenumber":"332",
    "addr:postcode":"08029",
    "addr:street":"Carrer De Entenc\u0327A",
    "iso:country":"ES",
    "sg:address":"Carrer de Enten\u00c7a, 332",
    "sg:city":"Barcelona",
    "sg:orig_category":"Financiaci\u00d3n Y Cr\u00c9ditos",
    "sg:phone":"+34 934 10 67 61",
    "sg:postcode":"08029",
    "sg:province":"Barcelona",
    "sg:website":"www.financa.es",
    "wof:name":"Financa S.a.",
    "wof:placetype":"venue"
},
  "geometry": {"coordinates":[2.1378250122,41.3903427124],"type":"Point"}
}