{
  "type": "Feature",
  "properties": {
    "addr:full":"Poligono Ind. El Pla, S/n Alcasser Valencia 46290",
    "addr:housenumber":"/ n",
    "addr:postcode":"46290",
    "addr:street":"Poligono Ind.;S",
    "iso:country":"ES",
    "sg:address":"Poligono Ind. El Pla, S/n",
    "sg:city":"Alcasser",
    "sg:orig_category":"Reciclaje, Tratamiento De Pl\u00c1sticos",
    "sg:phone":"+34 961 23 45 54",
    "sg:postcode":"46290",
    "sg:province":"Valencia",
    "wof:name":"Plasticos El Pla S.l.",
    "wof:placetype":"venue"
},
  "geometry": {"coordinates":[-0.4453490078,39.3651695251],"type":"Point"}
}