{
  "type": "Feature",
  "properties": {
    "addr:full":"C/ Josep Pla, 1 S. Antoni Calonge Girona 17252",
    "addr:housenumber":"1",
    "addr:postcode":"17252",
    "addr:street":"C / Josep Pla",
    "iso:country":"ES",
    "sg:address":"C/ Josep Pla, 1",
    "sg:city":"S. Antoni Calonge",
    "sg:orig_category":"Art\u00cdculos De Regalo (al Por Menor)",
    "sg:phone":"+34 972 65 29 21",
    "sg:postcode":"17252",
    "sg:province":"Girona",
    "wof:name":"Pujol Llovet Pere",
    "wof:placetype":"venue"
},
  "geometry": {"coordinates":[3.1094601154,41.8569297791],"type":"Point"}
}