{
  "type": "Feature",
  "properties": {
    "addr:full":"Rua Curro, 61 Noia La Coru\u00f1a 15200",
    "addr:housenumber":"61",
    "addr:postcode":"15200",
    "addr:street":"Rua Curro;La Corun\u0303A",
    "iso:country":"ES",
    "sg:address":"Rua Curro, 61",
    "sg:city":"Noia",
    "sg:orig_category":"Ropa Para Ni\u00d1os (al Por Menor)",
    "sg:phone":"+34 981 82 12 45",
    "sg:postcode":"15200",
    "sg:province":"La Coru\u00f1a",
    "wof:name":"Calvo Calo Maria Dolores",
    "wof:placetype":"venue"
},
  "geometry": {"coordinates":[-8.8864994049,42.7829284668],"type":"Point"}
}