{
  "type": "Feature",
  "properties": {
    "iso:country":"ES",
    "sg:address":"Calle de Nuestra Se\u00d1ora De Las Mercedes, 22",
    "sg:city":"Almeria",
    "sg:orig_category":"Fabricaci\u00d3n, Distribuci\u00d3n De Material Para La Climatizaci\u00d3n, Aireaci\u00d3n Y Ventilaci\u00d3n",
    "sg:phone":"+34 950 24 60 90",
    "sg:postcode":"04008",
    "sg:province":"Almer\u00eda",
    "wof:name":"Alcozar Vitalair Sl",
    "wof:placetype":"venue"
},
  "geometry": {"coordinates":[-2.4610536098,36.8465003967],"type":"Point"}
}