{
  "type": "Feature",
  "properties": {
    "addr:full":"Calle de Valencia, 7 Yuncos Toledo 45210",
    "addr:housenumber":"7",
    "addr:postcode":"45210",
    "addr:street":"Calle De Valencia",
    "iso:country":"ES",
    "sg:address":"Calle de Valencia, 7",
    "sg:city":"Yuncos",
    "sg:orig_category":"Agencias Y Agentes Comerciales, Representantes",
    "sg:phone":"+34 925 52 51 20",
    "sg:postcode":"45210",
    "sg:province":"Toledo",
    "wof:name":"Suministros Yunkos S.l.u",
    "wof:placetype":"venue"
},
  "geometry": {"coordinates":[-3.8789556026,40.0872612],"type":"Point"}
}