{
  "type": "Feature",
  "properties": {
    "iso:country":"ES",
    "sg:address":"Calle de Primavera, 34",
    "sg:city":"Torrejon Ardoz",
    "sg:orig_category":"Mec\u00c1nico Del Autom\u00d3vil",
    "sg:phone":"+34 916 75 21 02",
    "sg:postcode":"28850",
    "sg:province":"Madrid",
    "wof:name":"Talleres Diesel Serrano C.b.",
    "wof:placetype":"venue"
},
  "geometry": {"coordinates":[-3.4840245247,40.4460411072],"type":"Point"}
}