{
  "type": "Feature",
  "properties": {
    "iso:country":"ES",
    "sg:address":"Calle de Poeta Gerardo Diego, 34",
    "sg:city":"Santander",
    "sg:orig_category":"Tapiceros Y Tapiceros",
    "sg:phone":"+34 942 33 21 30",
    "sg:postcode":"39011",
    "sg:province":"Cantabria",
    "wof:name":"Dominguez Crespo Luis",
    "wof:placetype":"venue"
},
  "geometry": {"coordinates":[-3.8460080624,43.45570755],"type":"Point"}
}