{
  "type": "Feature",
  "properties": {
    "iso:country":"ES",
    "sg:address":"Avda Alfonso Pe\u00d1a, 11",
    "sg:city":"Zamora",
    "sg:orig_category":"Peleter\u00cdas",
    "sg:phone":"+34 980 51 36 49",
    "sg:postcode":"49010",
    "sg:province":"Zamora",
    "wof:name":"Rodriguez Silva Argimiro",
    "wof:placetype":"venue"
},
  "geometry": {"coordinates":[-5.7396831512,41.5141105652],"type":"Point"}
}