{
  "type": "Feature",
  "properties": {
    "addr:full":"Calle de Elexondo Kalea, 2 Amurrio \u00c1lava 01470",
    "addr:housenumber":"2",
    "addr:postcode":"01470",
    "addr:street":"Calle De Elexondo Kalea",
    "iso:country":"ES",
    "sg:address":"Calle de Elexondo Kalea, 2",
    "sg:city":"Amurrio",
    "sg:orig_category":"Abogados",
    "sg:phone":"+34 945 02 63 69",
    "sg:postcode":"01470",
    "sg:province":"\u00c1lava",
    "wof:name":"Alberto Zulueta Martinez",
    "wof:placetype":"venue"
},
  "geometry": {"coordinates":[-2.9998335838,43.0531806946],"type":"Point"}
}