{
  "type": "Feature",
  "properties": {
    "addr:full":"Calle de General Moscardo, 3 Madro\u00f1era C\u00e1ceres 10210",
    "addr:housenumber":"3",
    "addr:postcode":"10210",
    "addr:street":"Calle De General Moscardo;Ca\u0301Ceres",
    "iso:country":"ES",
    "sg:address":"Calle de General Moscardo, 3",
    "sg:city":"Madro\u00f1era",
    "sg:orig_category":"Telas Y Sedas (al Por Menor)",
    "sg:phone":"+34 927 33 40 82",
    "sg:postcode":"10210",
    "sg:province":"C\u00e1ceres",
    "wof:name":"Hoyas Barrado Saturnino",
    "wof:placetype":"venue"
},
  "geometry": {"coordinates":[-5.7585301399,39.428314209],"type":"Point"}
}