{
  "type": "Feature",
  "properties": {
    "iso:country":"ES",
    "sg:address":"Calle de Pintor Sorolla, 3",
    "sg:city":"Logro\u00f1o",
    "sg:orig_category":"Estudios De Grabaci\u00d3n Sonora",
    "sg:phone":"+34 941 20 40 14",
    "sg:postcode":"26007",
    "sg:province":"La Rioja",
    "wof:name":"Casas Esquete Emilio",
    "wof:placetype":"venue"
},
  "geometry": {"coordinates":[-2.4581758976,42.4581642151],"type":"Point"}
}