{
  "type": "Feature",
  "properties": {
    "iso:country":"ES",
    "sg:address":"Calle de Lucena, 59",
    "sg:city":"Antequera",
    "sg:orig_category":"Quincaller\u00cda (al Por Menor)",
    "sg:phone":"+34 952 84 23 38",
    "sg:postcode":"29200",
    "sg:province":"M\u00e1laga",
    "wof:name":"Suministros Industriales S.l.",
    "wof:placetype":"venue"
},
  "geometry": {"coordinates":[-4.559858799,37.0210456848],"type":"Point"}
}