{
  "type": "Feature",
  "properties": {
    "addr:full":"Calle de Veintidos De Julio, 15 Andujar Ja\u00e9n 23740",
    "addr:housenumber":"15",
    "addr:postcode":"23740",
    "addr:street":"Calle De Veintidos De Julio",
    "iso:country":"ES",
    "sg:address":"Calle de Veintidos De Julio, 15",
    "sg:city":"Andujar",
    "sg:orig_category":"Inmobiliaria (agencias)",
    "sg:phone":"+34 953 50 56 31",
    "sg:postcode":"23740",
    "sg:province":"Ja\u00e9n",
    "wof:name":"Figueras Resino Francisco Javier",
    "wof:placetype":"venue"
},
  "geometry": {"coordinates":[-4.0521879196,38.0370864868],"type":"Point"}
}