{
  "type": "Feature",
  "properties": {
    "iso:country":"ES",
    "sg:address":"C/ Joanot Colom, 29",
    "sg:city":"Inca",
    "sg:orig_category":"Confecci\u00d3n De Zapatos",
    "sg:phone":"+34 971 50 17 89",
    "sg:postcode":"07300",
    "sg:province":"Islas Baleares",
    "wof:name":"Creaciones Plaju S.l.",
    "wof:placetype":"venue"
},
  "geometry": {"coordinates":[2.9055120945,39.7210998535],"type":"Point"}
}