{
  "type": "Feature",
  "properties": {
    "iso:country":"ES",
    "sg:address":"Calle de General Romero Basart, 71",
    "sg:city":"Madrid",
    "sg:orig_category":"Farmacias",
    "sg:phone":"+34 917 06 54 60",
    "sg:postcode":"28044",
    "sg:province":"Madrid",
    "wof:name":"Lozano Monago Daniel",
    "wof:placetype":"venue"
},
  "geometry": {"coordinates":[-3.7737250328,40.3787307739],"type":"Point"}
}