{
  "type": "Feature",
  "properties": {
    "iso:country":"ES",
    "sg:address":"Calle de Diego De Vergara, 45",
    "sg:city":"Malaga",
    "sg:orig_category":"Prot\u00c9sicos Dentales",
    "sg:phone":"+34 952 39 20 98",
    "sg:postcode":"29009",
    "sg:province":"M\u00e1laga",
    "wof:name":"Lozano Alarcon Rafael",
    "wof:placetype":"venue"
},
  "geometry": {"coordinates":[-4.4344325066,36.7235488892],"type":"Point"}
}