{
  "type": "Feature",
  "properties": {
    "addr:full":"Calle de Zarza, 4 Ciudad Real Ciudad Real 13003",
    "addr:housenumber":"4",
    "addr:postcode":"13003",
    "addr:street":"Calle De Zarza",
    "iso:country":"ES",
    "sg:address":"Calle de Zarza, 4",
    "sg:city":"Ciudad Real",
    "sg:orig_category":"Peluquer\u00cdas, Peluquer\u00cda Mixta",
    "sg:phone":"+34 926 23 07 14",
    "sg:postcode":"13003",
    "sg:province":"Ciudad Real",
    "wof:name":"Estilistas Javier Miron S.l.",
    "wof:placetype":"venue"
},
  "geometry": {"coordinates":[-3.9310500622,38.9879188538],"type":"Point"}
}