{
  "type": "Feature",
  "properties": {
    "iso:country":"ES",
    "sg:address":"Rua Mendez Nu\u00d1ez, S/n",
    "sg:city":"Santa Uxia De Ribeira",
    "sg:classifiers":[
        {
            "category":"Personal",
            "subcategory":"Barber",
            "type":"Services"
        }
    ],
    "sg:phone":"+34 981 87 43 22",
    "sg:postcode":"15960",
    "sg:province":"La Coru\u00f1a",
    "sg:tags":[
        "caballeros",
        "de",
        "peluqueros"
    ],
    "wof:name":"Cadorniga Sampedro Antonio Manuel",
    "wof:placetype":"venue"
},
  "geometry": {"coordinates":[-8.9910440445,42.554233551],"type":"Point"}
}