{
  "type": "Feature",
  "properties": {
    "addr:full":"Avda Italia (de), 21 Playa Del Ingles Las Palmas 35100",
    "addr:housenumber":"21",
    "addr:postcode":"35100",
    "addr:street":"Avda Italia De",
    "iso:country":"ES",
    "sg:address":"Avda Italia (de), 21",
    "sg:city":"Playa Del Ingles",
    "sg:orig_category":"Heladeros",
    "sg:phone":"+34 928 76 54 46",
    "sg:postcode":"35100",
    "sg:province":"Las Palmas",
    "wof:name":"Aliprando S.l.",
    "wof:placetype":"venue"
},
  "geometry": {"coordinates":[-15.5650863647,27.7615299225],"type":"Point"}
}