{
  "type": "Feature",
  "properties": {
    "addr:full":"Calle de Manuel Torres, 1 Mairena Alcor Sevilla 41510",
    "addr:housenumber":"1",
    "addr:postcode":"41510",
    "addr:street":"Calle De Manuel Torres",
    "iso:country":"ES",
    "sg:address":"Calle de Manuel Torres, 1",
    "sg:city":"Mairena Alcor",
    "sg:orig_category":"M\u00c9dicos: Ginecolog\u00cda Y Obstetricia",
    "sg:phone":"+34 955 74 56 84",
    "sg:postcode":"41510",
    "sg:province":"Sevilla",
    "wof:name":"Jimenez Ruiz Jose Luis",
    "wof:placetype":"venue"
},
  "geometry": {"coordinates":[-5.7555689812,37.3727073669],"type":"Point"}
}