{
  "type": "Feature",
  "properties": {
    "addr:full":"Calle de Gran Via De San Marcos, 4 Le\u00f3n Le\u00f3n 24002",
    "addr:housenumber":"4",
    "addr:postcode":"24002",
    "addr:street":"Calle De Gran Via De San Marcos;Leo\u0301N",
    "iso:country":"ES",
    "sg:address":"Calle de Gran Via De San Marcos, 4",
    "sg:city":"Le\u00f3n",
    "sg:orig_category":"Abogados",
    "sg:phone":"+34 987 24 52 82",
    "sg:postcode":"24002",
    "sg:province":"Le\u00f3n",
    "wof:name":"Alvarez Due\u00f1a Angelica Maria",
    "wof:placetype":"venue"
},
  "geometry": {"coordinates":[-5.5727849007,42.598400116],"type":"Point"}
}