{
  "type": "Feature",
  "properties": {
    "iso:country":"ES",
    "sg:address":"Calle de Marruecos, 13",
    "sg:city":"Sevilla",
    "sg:orig_category":"Carnicer\u00cdas, Carnicer\u00cdas",
    "sg:phone":"+34 954 90 00 94",
    "sg:postcode":"41015",
    "sg:province":"Sevilla",
    "wof:name":"Teran Mena Maria Inmaculada",
    "wof:placetype":"venue"
},
  "geometry": {"coordinates":[-5.9857230186,37.423286438],"type":"Point"}
}