{
  "type": "Feature",
  "properties": {
    "iso:country":"ES",
    "sg:address":"Calle de Real, 43",
    "sg:city":"Navas San Juan",
    "sg:orig_category":"Artes Gr\u00c1ficas, Artes Pl\u00c1sticas (curso)",
    "sg:phone":"+34 953 68 70 90",
    "sg:postcode":"23240",
    "sg:province":"Ja\u00e9n",
    "wof:name":"Rubio Artero Jose Luis",
    "wof:placetype":"venue"
},
  "geometry": {"coordinates":[-3.3145930767,38.1859436035],"type":"Point"}
}