{
  "type": "Feature",
  "properties": {
    "iso:country":"ES",
    "sg:address":"Calle de Chile, 36",
    "sg:city":"Logro\u00f1o",
    "sg:orig_category":"Muebles Y Accesorios Para Cocinas Y Cuartos De Ba\u00d1o (al Por Menor)",
    "sg:phone":"+34 941 20 19 77",
    "sg:postcode":"26005",
    "sg:province":"La Rioja",
    "wof:name":"Hernandez Zabalo Alberto",
    "wof:placetype":"venue"
},
  "geometry": {"coordinates":[-2.4545586109,42.4614982605],"type":"Point"}
}