{
  "type": "Feature",
  "properties": {
    "addr:full":"Pla\u00c7 Del Mercat Vell, 3 Benicarlo Castell\u00f3n 12580",
    "addr:housenumber":"3",
    "addr:postcode":"12580",
    "iso:country":"ES",
    "sg:address":"Pla\u00c7 Del Mercat Vell, 3",
    "sg:city":"Benicarlo",
    "sg:orig_category":"Cajas De Ahorro",
    "sg:phone":"+34 964 47 46 11",
    "sg:postcode":"12580",
    "sg:province":"Castell\u00f3n",
    "sg:website":"www.lacaixa.es",
    "wof:name":"Caixa D'estalvis I Pensions De Barcelona",
    "wof:placetype":"venue"
},
  "geometry": {"coordinates":[0.4042100012,40.4457893372],"type":"Point"}
}