{
  "type": "Feature",
  "properties": {
    "addr:full":"Calle de California, 13 Almeria Almer\u00eda 04007",
    "addr:housenumber":"13",
    "addr:postcode":"04007",
    "addr:street":"Calle De California",
    "iso:country":"ES",
    "sg:address":"Calle de California, 13",
    "sg:city":"Almeria",
    "sg:orig_category":"Supermercados Y Hipermercados",
    "sg:phone":"+34 950 27 48 99",
    "sg:postcode":"04007",
    "sg:province":"Almer\u00eda",
    "wof:name":"Silva Canton Juan",
    "wof:placetype":"venue"
},
  "geometry": {"coordinates":[-2.4520070553,36.8282432556],"type":"Point"}
}