{
  "type": "Feature",
  "properties": {
    "iso:country":"ES",
    "sg:address":"Calle de Reyes De Navarra, 28",
    "sg:city":"Vitoria-gasteiz",
    "sg:orig_category":"Molduras, Junquillos, Listones Y Molduras Perforadas",
    "sg:phone":"+34 945 25 08 81",
    "sg:postcode":"01013",
    "sg:province":"\u00c1lava",
    "wof:name":"Jesus Largo Gibaja (bar La Paloma)",
    "wof:placetype":"venue"
},
  "geometry": {"coordinates":[-2.6680550575,42.8567276001],"type":"Point"}
}