{
  "type": "Feature",
  "properties": {
    "iso:country":"ES",
    "sg:address":"C/ Leopoldo Vicente Serrano, 8",
    "sg:city":"Elche",
    "sg:orig_category":"Abogados",
    "sg:phone":"+34 965 43 43 47",
    "sg:postcode":"03205",
    "sg:province":"Alicante",
    "wof:name":"Soro Cordoba Maria Jose",
    "wof:placetype":"venue"
},
  "geometry": {"coordinates":[-0.6995239854,38.2634811401],"type":"Point"}
}