{
  "type": "Feature",
  "properties": {
    "iso:country":"ES",
    "sg:address":"Calle de Menendez Pelayo, 30",
    "sg:city":"Villena",
    "sg:orig_category":"Zapatos: Material, Suministros, Accesorios (fabricaci\u00d3n, Al Por Mayor)",
    "sg:phone":"+34 965 34 33 55",
    "sg:postcode":"03400",
    "sg:province":"Alicante",
    "wof:name":"Arraez Paya Francisco",
    "wof:placetype":"venue"
},
  "geometry": {"coordinates":[-0.866134584,38.63331604],"type":"Point"}
}