{
  "type": "Feature",
  "properties": {
    "addr:full":"Calle de Amasorrain, 2 Donostia-san Sebastian Guip\u00f9zcoa 20018",
    "addr:housenumber":"2",
    "addr:postcode":"20018",
    "addr:street":"Calle De Amasorrain",
    "iso:country":"ES",
    "sg:address":"Calle de Amasorrain, 2",
    "sg:city":"Donostia-san Sebastian",
    "sg:orig_category":"Fabricaci\u00d3n De Transformadores, De M\u00c1quinas Giratorias De Peque\u00d1a Y Media Potencia",
    "sg:phone":"+34 943 36 21 40",
    "sg:postcode":"20018",
    "sg:province":"Guip\u00f9zcoa",
    "wof:name":"Oasa Transformadores Xxi S.a.l.",
    "wof:placetype":"venue"
},
  "geometry": {"coordinates":[-2.0098280907,43.2787780762],"type":"Point"}
}