{
  "type": "Feature",
  "properties": {
    "addr:full":"Ctra Villacastin Vigo, Km. 0057,0 Mombuey Zamora 49310",
    "addr:postcode":"49310",
    "addr:street":"Ctra Villacastin Vigo Km. 0057,0",
    "iso:country":"ES",
    "sg:address":"Ctra Villacastin Vigo, Km. 0057,0",
    "sg:city":"Mombuey",
    "sg:orig_category":"Empresas De Carpinter\u00cda Met\u00c1lica",
    "sg:phone":"+34 980 64 27 78",
    "sg:postcode":"49310",
    "sg:province":"Zamora",
    "wof:name":"Pedrero Madrigal Antonio",
    "wof:placetype":"venue"
},
  "geometry": {"coordinates":[-6.3319950104,42.0238761902],"type":"Point"}
}