{
  "type": "Feature",
  "properties": {
    "iso:country":"ES",
    "sg:address":"Calle de Pedro\u00d1eras, 10",
    "sg:city":"Madrid",
    "sg:orig_category":"Inform\u00c1tica: Consultores",
    "sg:phone":"+34 913 88 53 17",
    "sg:postcode":"28043",
    "sg:province":"Madrid",
    "wof:name":"Lucas Franco Carlos",
    "wof:placetype":"venue"
},
  "geometry": {"coordinates":[-3.6294550896,40.4646110535],"type":"Point"}
}