{
  "type": "Feature",
  "properties": {
    "iso:country":"ES",
    "sg:address":"Carrer de Joan Guell, 108",
    "sg:city":"Barcelona",
    "sg:orig_category":"Financiaci\u00d3n Y Cr\u00c9ditos",
    "sg:phone":"+34 933 30 29 53",
    "sg:postcode":"08028",
    "sg:province":"Barcelona",
    "wof:name":"Llar Finantial Services,s.l.",
    "wof:placetype":"venue"
},
  "geometry": {"coordinates":[2.1323490143,41.3813438416],"type":"Point"}
}