{
  "type": "Feature",
  "properties": {
    "iso:country":"ES",
    "sg:address":"Pase Urgoiti, 5",
    "sg:city":"Arrigorriaga",
    "sg:orig_category":"Fisioterapia",
    "sg:phone":"+34 946 71 39 28",
    "sg:postcode":"48480",
    "sg:province":"Vizcaya",
    "wof:name":"Parro Zulueta I\u00f1igo",
    "wof:placetype":"venue"
},
  "geometry": {"coordinates":[-2.8882789612,43.2112236023],"type":"Point"}
}