{
  "type": "Feature",
  "properties": {
    "iso:country":"ES",
    "sg:address":"Calle de Sancho Ordo\u00d1ez, 13",
    "sg:city":"Le\u00f3n",
    "sg:orig_category":"Escayola Y Productos De Escayola (fabricaci\u00d3n, Al Por Mayor)",
    "sg:phone":"+34 987 23 49 57",
    "sg:postcode":"24007",
    "sg:province":"Le\u00f3n",
    "wof:name":"Alvarez Gutierrez Juan Manuel",
    "wof:placetype":"venue"
},
  "geometry": {"coordinates":[-5.5693855286,42.6085395813],"type":"Point"}
}