{
  "type": "Feature",
  "properties": {
    "addr:full":"Calle de Duque De Gor, 15 Guadix Granada 18500",
    "addr:housenumber":"15",
    "addr:postcode":"18500",
    "addr:street":"Calle De Duque De Gor",
    "iso:country":"ES",
    "sg:address":"Calle de Duque De Gor, 15",
    "sg:city":"Guadix",
    "sg:orig_category":"Asesor\u00cda Fiscal Y Jur\u00cddica",
    "sg:phone":"+34 958 66 47 14",
    "sg:postcode":"18500",
    "sg:province":"Granada",
    "wof:name":"Asesora Anros S.l.",
    "wof:placetype":"venue"
},
  "geometry": {"coordinates":[-3.1334974766,37.301486969],"type":"Point"}
}