{
  "type": "Feature",
  "properties": {
    "iso:country":"ES",
    "sg:address":"Calle de Salamanca, 53",
    "sg:city":"Valencia",
    "sg:orig_category":"Tintorer\u00cdas, Limpieza En Seco",
    "sg:phone":"+34 963 34 00 45",
    "sg:postcode":"46005",
    "sg:province":"Valencia",
    "wof:name":"Nogales Macia Antonio",
    "wof:placetype":"venue"
},
  "geometry": {"coordinates":[-0.3625718951,39.4638366699],"type":"Point"}
}