{
  "type": "Feature",
  "properties": {
    "addr:full":"Calle de Loza, 8 Borox Toledo 45222",
    "addr:housenumber":"8",
    "addr:postcode":"45222",
    "addr:street":"Calle De Loza",
    "iso:country":"ES",
    "sg:address":"Calle de Loza, 8",
    "sg:city":"Borox",
    "sg:orig_category":"Art\u00cdculos De Regalo (al Por Menor)",
    "sg:phone":"+34 925 52 80 04",
    "sg:postcode":"45222",
    "sg:province":"Toledo",
    "wof:name":"Lozano Revidiego Jose Damian",
    "wof:placetype":"venue"
},
  "geometry": {"coordinates":[-3.7405939102,40.0739746094],"type":"Point"}
}