{
  "type": "Feature",
  "properties": {
    "iso:country":"ES",
    "sg:address":"Carr Migdia, 67",
    "sg:city":"Girona",
    "sg:orig_category":"Ense\u00d1anza, Formaci\u00d3n Profesional: Aprendizaje",
    "sg:phone":"+34 972 20 22 09",
    "sg:postcode":"17003",
    "sg:province":"Girona",
    "sg:website":"www.cteep.com",
    "wof:name":"Centro Tecnico Europeo De Ense\u00f1anzas Profesionales S.l.",
    "wof:placetype":"venue"
},
  "geometry": {"coordinates":[2.8204789162,41.9731369019],"type":"Point"}
}