{
  "type": "Feature",
  "properties": {
    "iso:country":"ES",
    "sg:address":"Estaci\u00f3n, S/n",
    "sg:city":"Caudiel",
    "sg:orig_category":"Fabricaci\u00d3n De Pernos, Tornillos Y Clavos",
    "sg:phone":"+34 964 14 41 21",
    "sg:postcode":"12440",
    "sg:province":"Castell\u00f3n",
    "wof:name":"Vicente Moliner S.a.",
    "wof:placetype":"venue"
},
  "geometry": {"coordinates":[-0.5716469884,39.9471321106],"type":"Point"}
}