{
  "type": "Feature",
  "properties": {
    "addr:full":"Calle de Isla De Oza, 35 Madrid Madrid 28035",
    "addr:housenumber":"35",
    "addr:postcode":"madrid;28035",
    "addr:street":"Calle De Isla De Oza",
    "iso:country":"ES",
    "sg:address":"Calle de Isla De Oza, 35",
    "sg:city":"Madrid",
    "sg:orig_category":"Alimentaci\u00d3n General (al Por Menor)",
    "sg:phone":"+34 913 16 13 14",
    "sg:postcode":"28035",
    "sg:province":"Madrid",
    "wof:name":"Garcia Garcia Aurelio",
    "wof:placetype":"venue"
},
  "geometry": {"coordinates":[-3.7244269848,40.4647750854],"type":"Point"}
}