{
  "type": "Feature",
  "properties": {
    "addr:full":"De Asturias, 7 Roquetas Mar Almer\u00eda 04740",
    "addr:housenumber":"7",
    "addr:postcode":"04740",
    "addr:street":"Asturias",
    "iso:country":"ES",
    "sg:address":"De Asturias, 7",
    "sg:city":"Roquetas Mar",
    "sg:orig_category":"Frutas Y Legumbres Frescas (al Por Mayor)",
    "sg:phone":"+34 950 32 86 96",
    "sg:postcode":"04740",
    "sg:province":"Almer\u00eda",
    "wof:name":"Martinez Morales Maria Estrella",
    "wof:placetype":"venue"
},
  "geometry": {"coordinates":[-2.602408886,36.7856254578],"type":"Point"}
}