{
  "type": "Feature",
  "properties": {
    "iso:country":"ES",
    "sg:address":"Calle de Fueros, 11",
    "sg:city":"Vitoria-gasteiz",
    "sg:orig_category":"Arquitectos",
    "sg:phone":"+34 945 28 30 06",
    "sg:postcode":"01004",
    "sg:province":"\u00c1lava",
    "wof:name":"Fernandez De Landa Altuna Juan I Ignacio",
    "wof:placetype":"venue"
},
  "geometry": {"coordinates":[-2.6666500568,42.8437004089],"type":"Point"}
}