{
  "type": "Feature",
  "properties": {
    "iso:country":"ES",
    "sg:address":"Av Catalunya, S/n",
    "sg:city":"Deltebre",
    "sg:orig_category":"Asilos De Ancianos. Centros Privados",
    "sg:phone":"+34 977 48 94 70",
    "sg:postcode":"43580",
    "sg:province":"Tarragona",
    "wof:name":"Ajuntament De Deltebre",
    "wof:placetype":"venue"
},
  "geometry": {"coordinates":[0.724219203,40.7210388184],"type":"Point"}
}