{
  "type": "Feature",
  "properties": {
    "addr:full":"Carrer de Castellvi De Rosanes, 2 Martorell Barcelona 08760",
    "addr:housenumber":"2",
    "addr:postcode":"08760",
    "addr:street":"Carrer De Castellvi;Rosanes",
    "iso:country":"ES",
    "sg:address":"Carrer de Castellvi De Rosanes, 2",
    "sg:city":"Martorell",
    "sg:orig_category":"Bricolaje, Herramientas (al Por Menor)",
    "sg:phone":"+34 937 76 91 10",
    "sg:postcode":"08760",
    "sg:province":"Barcelona",
    "wof:name":"Porta Alucuina S.l.",
    "wof:placetype":"venue"
},
  "geometry": {"coordinates":[1.9144810438,41.4737319946],"type":"Point"}
}