{
  "type": "Feature",
  "properties": {
    "iso:country":"ES",
    "sg:address":"Calle de Principe De Vergara, 9",
    "sg:city":"Madrid",
    "sg:orig_category":"Asesor\u00cda Sobre Comunicaci\u00d3n De Empresas",
    "sg:phone":"+34 914 11 95 28",
    "sg:postcode":"28001",
    "sg:province":"Madrid",
    "wof:name":"Madrid Inversiones S.a.",
    "wof:placetype":"venue"
},
  "geometry": {"coordinates":[-3.6804609299,40.4237670898],"type":"Point"}
}