{
  "type": "Feature",
  "properties": {
    "addr:full":"Urkizu Pasealekua, 11 Eibar Guip\u00f9zcoa 20600",
    "addr:housenumber":"11",
    "addr:postcode":"20600",
    "addr:street":"Urkizu Pasealekua;Guipu\u0300Zcoa",
    "iso:country":"ES",
    "sg:address":"Urkizu Pasealekua, 11",
    "sg:city":"Eibar",
    "sg:orig_category":"Asociaciones, Organismos Culturales Y Socioeducativos",
    "sg:phone":"+34 943 12 16 84",
    "sg:postcode":"20600",
    "sg:province":"Guip\u00f9zcoa",
    "wof:name":"Sociedad Cultural Recreativa Dorrepe",
    "wof:placetype":"venue"
},
  "geometry": {"coordinates":[-2.463187933,43.1869850159],"type":"Point"}
}