{
  "type": "Feature",
  "properties": {
    "addr:full":"Calle de Antonio Garrochena, 9 Almonte Huelva 21730",
    "addr:housenumber":"9",
    "addr:postcode":"21730",
    "addr:street":"Calle De Antonio Garrochena",
    "iso:country":"ES",
    "sg:address":"Calle de Antonio Garrochena, 9",
    "sg:city":"Almonte",
    "sg:orig_category":"Instalaci\u00d3n De Aspiraci\u00d3n De Gases Y Humos",
    "sg:phone":"+34 959 40 65 80",
    "sg:postcode":"21730",
    "sg:province":"Huelva",
    "wof:name":"Faraco Soltero Manuel",
    "wof:placetype":"venue"
},
  "geometry": {"coordinates":[-6.5243139267,37.263381958],"type":"Point"}
}