{
  "type": "Feature",
  "properties": {
    "addr:full":"Zaldibar Kalea, 4 Arrasate Guip\u00f9zcoa 20500",
    "addr:housenumber":"4",
    "addr:postcode":"20500",
    "addr:street":"Zaldibar Kalea;Guipu\u0300Zcoa",
    "iso:country":"ES",
    "sg:address":"Zaldibar Kalea, 4",
    "sg:city":"Arrasate",
    "sg:orig_category":"M\u00c9dicos: Fisioterapia Y Rehabilitaci\u00d3n",
    "sg:phone":"+34 943 77 14 72",
    "sg:postcode":"20500",
    "sg:province":"Guip\u00f9zcoa",
    "wof:name":"Tamorde 2004 S.l.",
    "wof:placetype":"venue"
},
  "geometry": {"coordinates":[-2.4868209362,43.0644073486],"type":"Point"}
}