{
  "type": "Feature",
  "properties": {
    "iso:country":"ES",
    "sg:address":"Av Sant Miquel, S/n",
    "sg:city":"Masos Vespella",
    "sg:orig_category":"Trabajos De Perforaciones, Sondeos, Construcci\u00d3n De Pozos",
    "sg:phone":"+34 977 65 55 25",
    "sg:postcode":"43763",
    "sg:province":"Tarragona",
    "wof:name":"Sanroma Fortuny Pedro Maria",
    "wof:placetype":"venue"
},
  "geometry": {"coordinates":[1.3597609997,41.2055664062],"type":"Point"}
}