{
  "type": "Feature",
  "properties": {
    "iso:country":"ES",
    "sg:address":"Av Barcelona, 24",
    "sg:city":"Cunit",
    "sg:orig_category":"Inmobiliaria (agencias)",
    "sg:phone":"+34 977 16 10 20",
    "sg:postcode":"43881",
    "sg:province":"Tarragona",
    "sg:website":"www.fincasannadal.com",
    "wof:name":"An-nadal S.l.",
    "wof:placetype":"venue"
},
  "geometry": {"coordinates":[1.6174720526,41.1950263977],"type":"Point"}
}