{
  "type": "Feature",
  "properties": {
    "iso:country":"ES",
    "sg:address":"Rua Ca\u00d1iza, 9",
    "sg:city":"Vigo",
    "sg:orig_category":"Promotores Constructores",
    "sg:phone":"+34 986 29 85 10",
    "sg:postcode":"36213",
    "sg:province":"Pontevedra",
    "wof:name":"Prosampaio S.l.",
    "wof:placetype":"venue"
},
  "geometry": {"coordinates":[-8.7522125244,42.2098770142],"type":"Point"}
}