{
  "type": "Feature",
  "properties": {
    "iso:country":"ES",
    "sg:address":"Plaz Miguel Del Pino, 5",
    "sg:city":"Puerto De Santa Maria",
    "sg:orig_category":"Servicio De Salud",
    "sg:phone":"+34 956 54 01 19",
    "sg:postcode":"11500",
    "sg:province":"C\u00e1diz",
    "wof:name":"Saneamientos Y Ferreteria Gocasa S.l.",
    "wof:placetype":"venue"
},
  "geometry": {"coordinates":[-6.2339038849,36.5961494446],"type":"Point"}
}