{
  "type": "Feature",
  "properties": {
    "addr:full":"Calle de San Jose, 30 Durcal Granada 18650",
    "addr:housenumber":"30",
    "addr:postcode":"18650",
    "addr:street":"Calle De San;Durcal Granada",
    "iso:country":"ES",
    "sg:address":"Calle de San Jose, 30",
    "sg:city":"Durcal",
    "sg:orig_category":"Contenedores Para Transporte De Mercanc\u00cdas",
    "sg:phone":"+34 958 78 02 43",
    "sg:postcode":"18650",
    "sg:province":"Granada",
    "wof:name":"Recestur S.l.",
    "wof:placetype":"venue"
},
  "geometry": {"coordinates":[-3.569329977,36.9910697937],"type":"Point"}
}