{
  "type": "Feature",
  "properties": {
    "iso:country":"ES",
    "sg:address":"Avda General Antero Rubin, 6",
    "sg:city":"Pontevedra",
    "sg:orig_category":"Cr\u00cda De Animales",
    "sg:phone":"+34 986 84 67 50",
    "sg:postcode":"36001",
    "sg:province":"Pontevedra",
    "wof:name":"San Segundo Espinosa Maria Pilar",
    "wof:placetype":"venue"
},
  "geometry": {"coordinates":[-8.6467227936,42.4271736145],"type":"Point"}
}