{
  "type": "Feature",
  "properties": {
    "addr:full":"Calle de Huerta Del Cura, 11 Guadamur Toledo 45160",
    "addr:housenumber":"11",
    "addr:postcode":"45160",
    "addr:street":"Calle De Huerta Del Cura",
    "iso:country":"ES",
    "sg:address":"Calle de Huerta Del Cura, 11",
    "sg:city":"Guadamur",
    "sg:orig_category":"Asilos De Ancianos. Centros Privados",
    "sg:phone":"+34 925 29 15 62",
    "sg:postcode":"45160",
    "sg:province":"Toledo",
    "wof:name":"Carmavila S.l.",
    "wof:placetype":"venue"
},
  "geometry": {"coordinates":[-4.1457920074,39.8075828552],"type":"Point"}
}