{
  "type": "Feature",
  "properties": {
    "iso:country":"ES",
    "sg:address":"Calle de Manuel Arranz, 21",
    "sg:city":"Madrid",
    "sg:orig_category":"Montaje (empresas De)",
    "sg:phone":"+34 914 33 93 29",
    "sg:postcode":"28038",
    "sg:province":"Madrid",
    "wof:name":"Montajes Spainbul, S.l.",
    "wof:placetype":"venue"
},
  "geometry": {"coordinates":[-3.6612811089,40.4046592712],"type":"Point"}
}