{
  "type": "Feature",
  "properties": {
    "iso:country":"ES",
    "sg:address":"Carrer de Jacint Verdaguer, 145",
    "sg:city":"Molins Rei",
    "sg:orig_category":"Confecci\u00d3n De Ropa Interior",
    "sg:phone":"+34 936 80 02 25",
    "sg:postcode":"08750",
    "sg:province":"Barcelona",
    "wof:name":"Naturana Iberica S. A.",
    "wof:placetype":"venue"
},
  "geometry": {"coordinates":[2.0134589672,41.4142990112],"type":"Point"}
}