{
  "type": "Feature",
  "properties": {
    "iso:country":"ES",
    "sg:address":"Calle de Cabrahigos, 14",
    "sg:city":"Toledo",
    "sg:orig_category":"Asilos De Ancianos. Centros Privados",
    "sg:phone":"+34 925 25 20 11",
    "sg:postcode":"45006",
    "sg:province":"Toledo",
    "sg:website":"wwwpaginasamarillas.es",
    "wof:name":"Castellana Geriatrica De Servicios Cdad.",
    "wof:placetype":"venue"
},
  "geometry": {"coordinates":[-4.0108361244,39.8602752686],"type":"Point"}
}