{
  "type": "Feature",
  "properties": {
    "addr:full":"Calle de San Lesmes, 18 Burgos Burgos 09004",
    "addr:housenumber":"18",
    "addr:postcode":"09004",
    "addr:street":"Calle De San Lesmes",
    "iso:country":"ES",
    "sg:address":"Calle de San Lesmes, 18",
    "sg:city":"Burgos",
    "sg:orig_category":"Arquitectos",
    "sg:phone":"+34 947 27 64 08",
    "sg:postcode":"09004",
    "sg:province":"Burgos",
    "wof:name":"Sendin Martin Juan Ignacio",
    "wof:placetype":"venue"
},
  "geometry": {"coordinates":[-3.6966719627,42.3433990479],"type":"Point"}
}