{
  "type": "Feature",
  "properties": {
    "addr:full":"Calle de Goya, 3 Puertollano Ciudad Real 13500",
    "addr:housenumber":"3",
    "addr:postcode":"13500",
    "addr:street":"Calle De Goya",
    "iso:country":"ES",
    "sg:address":"Calle de Goya, 3",
    "sg:city":"Puertollano",
    "sg:orig_category":"Peluquer\u00cdas, Peluquer\u00cda Mixta",
    "sg:phone":"+34 926 44 13 64",
    "sg:postcode":"13500",
    "sg:province":"Ciudad Real",
    "wof:name":"Sanchez Mu\u00f1oz Dionisio",
    "wof:placetype":"venue"
},
  "geometry": {"coordinates":[-4.1035490036,38.685218811],"type":"Point"}
}