{
  "type": "Feature",
  "properties": {
    "addr:full":"Av Lluis Companys, 23 S. Joan Despi Barcelona 08970",
    "addr:housenumber":"23",
    "addr:postcode":"08970",
    "addr:street":"Av Lluis Companys;S. Joan Despi",
    "iso:country":"ES",
    "sg:address":"Av Lluis Companys, 23",
    "sg:city":"S. Joan Despi",
    "sg:orig_category":"Lencer\u00cda Femenina, Corseter\u00cda, Trajes De Ba\u00d1o (al Por Menor)",
    "sg:phone":"+34 933 73 80 53",
    "sg:postcode":"08970",
    "sg:province":"Barcelona",
    "wof:name":"Lga Fashion S.l.",
    "wof:placetype":"venue"
},
  "geometry": {"coordinates":[2.0605280399,41.3778648376],"type":"Point"}
}