{
  "type": "Feature",
  "properties": {
    "iso:country":"ES",
    "sg:address":"Ptge Sta. Maria De L'estany, 12",
    "sg:city":"Sabadell",
    "sg:orig_category":"Fabricaci\u00d3n De Telas Y Sedas",
    "sg:phone":"+34 937 10 42 33",
    "sg:postcode":"08205",
    "sg:province":"Barcelona",
    "wof:name":"Giralt Textil S.a.",
    "wof:placetype":"venue"
},
  "geometry": {"coordinates":[2.1001689434,41.5378494263],"type":"Point"}
}