{
  "type": "Feature",
  "properties": {
    "iso:country":"ES",
    "sg:address":"Carr Vicente Boix, 9",
    "sg:city":"Xativa",
    "sg:orig_category":"Ropa Para Se\u00d1oras (al Por Menor)",
    "sg:phone":"+34 962 28 17 65",
    "sg:postcode":"46800",
    "sg:province":"Valencia",
    "wof:name":"Creaciones Avenida Alzira S.l.",
    "wof:placetype":"venue"
},
  "geometry": {"coordinates":[-0.5245770216,38.9909477234],"type":"Point"}
}