{
  "type": "Feature",
  "properties": {
    "iso:country":"ES",
    "sg:address":"Pase Repolo, 6",
    "sg:city":"Tarazona",
    "sg:orig_category":"Empresas De Carpinter\u00cda De Madera",
    "sg:phone":"+34 976 64 00 83",
    "sg:postcode":"50500",
    "sg:province":"Zaragoza",
    "wof:name":"Carpinteria Izmar S.l.",
    "wof:placetype":"venue"
},
  "geometry": {"coordinates":[-1.7308889627,41.898853302],"type":"Point"}
}