{
  "type": "Feature",
  "properties": {
    "iso:country":"ES",
    "sg:address":"Chopo, S/n",
    "sg:city":"Aracena",
    "sg:orig_category":"Promotores Constructores",
    "sg:phone":"+34 959 12 77 26",
    "sg:postcode":"21200",
    "sg:province":"Huelva",
    "wof:name":"Construcciones Jabuguillo S.l.",
    "wof:placetype":"venue"
},
  "geometry": {"coordinates":[-6.5674538612,37.8917350769],"type":"Point"}
}