{
  "type": "Feature",
  "properties": {
    "iso:country":"ES",
    "sg:address":"Calle de Jesus Del Perdon, 6",
    "sg:city":"Manzanares",
    "sg:orig_category":"Artes Gr\u00c1ficas, Artes Pl\u00c1sticas (curso)",
    "sg:phone":"+34 926 61 10 10",
    "sg:postcode":"13200",
    "sg:province":"Ciudad Real",
    "wof:name":"Copigraphic Martin Lara S.l.",
    "wof:placetype":"venue"
},
  "geometry": {"coordinates":[-3.3729729652,38.9966888428],"type":"Point"}
}