{
  "type": "Feature",
  "properties": {
    "iso:country":"ES",
    "sg:address":"Calle de Mu\u00d1oz Torrero, 2",
    "sg:city":"Malaga",
    "sg:orig_category":"Abogados",
    "sg:phone":"+34 952 07 04 48",
    "sg:postcode":"29007",
    "sg:province":"M\u00e1laga",
    "wof:name":"Alcantara Jimenez Luis Manuel",
    "wof:placetype":"venue"
},
  "geometry": {"coordinates":[-4.4283242226,36.7194900513],"type":"Point"}
}