{
  "type": "Feature",
  "properties": {
    "iso:country":"ES",
    "sg:address":"Calle de Pico Cejo, 57",
    "sg:city":"Madrid",
    "sg:orig_category":"Panader\u00cdas, Panader\u00cdas",
    "sg:phone":"+34 914 37 54 14",
    "sg:postcode":"28038",
    "sg:province":"Madrid",
    "wof:name":"Rojo Fernandez Juan",
    "wof:placetype":"venue"
},
  "geometry": {"coordinates":[-3.6631178856,40.3988685608],"type":"Point"}
}