{
  "type": "Feature",
  "properties": {
    "iso:country":"ES",
    "sg:address":"Av. Paz, 32",
    "sg:city":"Bollullos Par Condado",
    "sg:orig_category":"Venta, Colocaci\u00d3n De Frenos",
    "sg:phone":"+34 959 41 27 89",
    "sg:postcode":"21710",
    "sg:province":"Huelva",
    "wof:name":"Suministros Orihuela S.l.",
    "wof:placetype":"venue"
},
  "geometry": {"coordinates":[-6.5412459373,37.332649231],"type":"Point"}
}