{
  "type": "Feature",
  "properties": {
    "addr:full":"Calle de San Roque, 25 Estepona M\u00e1laga 29680",
    "addr:housenumber":"25",
    "addr:postcode":"29680",
    "addr:street":"Calle De San Roque",
    "iso:country":"ES",
    "sg:address":"Calle de San Roque, 25",
    "sg:city":"Estepona",
    "sg:orig_category":"Instalaci\u00d3n, Reparaci\u00d3n De Ascensores Y Montacargas",
    "sg:phone":"+34 952 80 27 98",
    "sg:postcode":"29680",
    "sg:province":"M\u00e1laga",
    "wof:name":"A. Embarba S. A.",
    "wof:placetype":"venue"
},
  "geometry": {"coordinates":[-5.1497979164,36.4218139648],"type":"Point"}
}