{
  "type": "Feature",
  "properties": {
    "addr:full":"Ceuta, S/n Rincon Victoria M\u00e1laga 29730",
    "addr:housenumber":"s / n",
    "addr:postcode":"29730",
    "addr:street":"Ceuta;Ma\u0301Laga",
    "iso:country":"ES",
    "sg:address":"Ceuta, S/n",
    "sg:city":"Rincon Victoria",
    "sg:orig_category":"Promotores Constructores",
    "sg:phone":"+34 952 97 02 76",
    "sg:postcode":"29730",
    "sg:province":"M\u00e1laga",
    "wof:name":"Infrusa S.l.",
    "wof:placetype":"venue"
},
  "geometry": {"coordinates":[-4.4200186729,36.7196464539],"type":"Point"}
}