{
  "type": "Feature",
  "properties": {
    "iso:country":"ES",
    "sg:address":"Calle de Polancos (los), 9",
    "sg:city":"Sevilla",
    "sg:orig_category":"Mec\u00c1nico Del Autom\u00d3vil",
    "sg:phone":"+34 954 35 84 03",
    "sg:postcode":"41008",
    "sg:province":"Sevilla",
    "wof:name":"Talleres Gracelisl S.l.",
    "wof:placetype":"venue"
},
  "geometry": {"coordinates":[-5.9817790985,37.4001998901],"type":"Point"}
}