{
  "type": "Feature",
  "properties": {
    "iso:country":"ES",
    "sg:address":"Avda P. Iglesias Caballero, S/n",
    "sg:city":"Cabra",
    "sg:orig_category":"Pescader\u00cdas (al Por Menor)",
    "sg:phone":"+34 957 52 59 34",
    "sg:postcode":"14940",
    "sg:province":"C\u00f3rdoba",
    "wof:name":"Hnos Granados C.b.",
    "wof:placetype":"venue"
},
  "geometry": {"coordinates":[-4.4374289513,37.4714813232],"type":"Point"}
}