{
  "type": "Feature",
  "properties": {
    "addr:full":"Barr Barreda, S/n Barreda Cantabria 39300",
    "addr:postcode":"39300",
    "addr:street":"S / N",
    "iso:country":"ES",
    "sg:address":"Barr Barreda, S/n",
    "sg:city":"Barreda",
    "sg:orig_category":"Polideportivos",
    "sg:phone":"+34 942 80 80 80",
    "sg:postcode":"39300",
    "sg:province":"Cantabria",
    "wof:name":"Instituto Municipal De Deportes",
    "wof:placetype":"venue"
},
  "geometry": {"coordinates":[-4.0448408127,43.3681602478],"type":"Point"}
}