{
  "type": "Feature",
  "properties": {
    "iso:country":"ES",
    "sg:address":"Avda Milagros, S/n",
    "sg:city":"Merida",
    "sg:orig_category":"Cl\u00cdnicas Dentales",
    "sg:phone":"+34 924 30 23 57",
    "sg:postcode":"06800",
    "sg:province":"Badajoz",
    "wof:name":"Zavala  Roberto Daniel",
    "wof:placetype":"venue"
},
  "geometry": {"coordinates":[-6.3437328339,38.9250907898],"type":"Point"}
}