{
  "type": "Feature",
  "properties": {
    "iso:country":"ES",
    "sg:address":"Calle de San Simon, 13",
    "sg:city":"Sonseca",
    "sg:orig_category":"Confecciones De Art\u00cdculos De Punto",
    "sg:phone":"+34 925 38 33 46",
    "sg:postcode":"45100",
    "sg:province":"Toledo",
    "wof:name":"Catha C.b.",
    "wof:placetype":"venue"
},
  "geometry": {"coordinates":[-3.9751930237,39.6805686951],"type":"Point"}
}