{
  "type": "Feature",
  "properties": {
    "addr:full":"Abenda\u00d1o Kalea, 35 Lezo Guip\u00f9zcoa 20100",
    "addr:housenumber":"35",
    "addr:postcode":"20100",
    "addr:street":"Abendan\u0303O Kalea;Guipu\u0300Zcoa",
    "iso:country":"ES",
    "sg:address":"Abenda\u00d1o Kalea, 35",
    "sg:city":"Lezo",
    "sg:orig_category":"Centros Empresariales",
    "sg:phone":"+34 943 49 12 40",
    "sg:postcode":"20100",
    "sg:province":"Guip\u00f9zcoa",
    "sg:website":"www.eskulancoop.com",
    "wof:name":"Eskulan S. Coop.",
    "wof:placetype":"venue"
},
  "geometry": {"coordinates":[-1.8691079617,43.3218994141],"type":"Point"}
}