{
  "type": "Feature",
  "properties": {
    "iso:country":"ES",
    "sg:address":"Rua Alfonso Daniel Rodriguez Castelao, 14",
    "sg:city":"Carballo",
    "sg:orig_category":"Centros Empresariales",
    "sg:phone":"+34 981 75 63 60",
    "sg:postcode":"15100",
    "sg:province":"La Coru\u00f1a",
    "wof:name":"Centro Especial De Empleo Aspaber S.l. Ute",
    "wof:placetype":"venue"
},
  "geometry": {"coordinates":[-8.6951494217,43.2093544006],"type":"Point"}
}