{
  "type": "Feature",
  "properties": {
    "addr:full":"Calle de Moncayo, 19 Zaragoza Zaragoza 50010",
    "addr:housenumber":"19",
    "addr:postcode":"50010",
    "addr:street":"Calle De Moncayo",
    "iso:country":"ES",
    "sg:address":"Calle de Moncayo, 19",
    "sg:city":"Zaragoza",
    "sg:orig_category":"Asesor\u00cda Sobre Comunicaci\u00d3n De Empresas",
    "sg:phone":"+34 976 32 77 61",
    "sg:postcode":"50010",
    "sg:province":"Zaragoza",
    "wof:name":"Auditoasesores D.p.g.s. P.f.m.b. S.cv.",
    "wof:placetype":"venue"
},
  "geometry": {"coordinates":[-0.8959559798,41.6498603821],"type":"Point"}
}