{
  "type": "Feature",
  "properties": {
    "addr:full":"Calle de Genova, 17 Zaragoza Zaragoza 50007",
    "addr:housenumber":"17",
    "addr:postcode":"50007",
    "addr:street":"Calle De Genova",
    "iso:country":"ES",
    "sg:address":"Calle de Genova, 17",
    "sg:city":"Zaragoza",
    "sg:orig_category":"Ropa Para Beb\u00c9s Y Ni\u00d1os (confecci\u00d3n, Al Por Mayor)",
    "sg:phone":"+34 976 38 21 80",
    "sg:postcode":"50007",
    "sg:province":"Zaragoza",
    "wof:name":"Bellmon S. L.",
    "wof:placetype":"venue"
},
  "geometry": {"coordinates":[-0.8822410107,41.6363983154],"type":"Point"}
}