{
  "type": "Feature",
  "properties": {
    "addr:full":"Avda La Loma, S/n Ibros Ja\u00e9n 23450",
    "addr:housenumber":"/ n",
    "addr:postcode":"23450",
    "addr:street":"Avda La Loma S;Jae\u0301N",
    "iso:country":"ES",
    "sg:address":"Avda La Loma, S/n",
    "sg:city":"Ibros",
    "sg:orig_category":"Aguas (distribuci\u00d3n, Servicios)",
    "sg:phone":"+34 953 76 60 24",
    "sg:postcode":"23450",
    "sg:province":"Ja\u00e9n",
    "wof:name":"Aguas Jaen S.a.",
    "wof:placetype":"venue"
},
  "geometry": {"coordinates":[-3.531740427,37.9859046936],"type":"Point"}
}