{
  "type": "Feature",
  "properties": {
    "addr:full":"Calle de Fermin Salvochea, 3 Cadiz C\u00e1diz 11004",
    "addr:housenumber":"3",
    "addr:postcode":"11004",
    "addr:street":"Calle De Fermin Salvochea",
    "iso:country":"ES",
    "sg:address":"Calle de Fermin Salvochea, 3",
    "sg:city":"Cadiz",
    "sg:orig_category":"Prot\u00c9sicos Dentales",
    "sg:phone":"+34 956 22 56 89",
    "sg:postcode":"11004",
    "sg:province":"C\u00e1diz",
    "wof:name":"Rivas Puerta Andres",
    "wof:placetype":"venue"
},
  "geometry": {"coordinates":[-6.2944860458,36.5358352661],"type":"Point"}
}