{
  "type": "Feature",
  "properties": {
    "iso:country":"ES",
    "sg:address":"La Solana, 2",
    "sg:city":"Argamasilla Alba",
    "sg:orig_category":"Farmacias",
    "sg:phone":"+34 926 52 11 46",
    "sg:postcode":"13710",
    "sg:province":"Ciudad Real",
    "wof:name":"Zurita Aranda Antonio",
    "wof:placetype":"venue"
},
  "geometry": {"coordinates":[-3.0912435055,39.1282615662],"type":"Point"}
}