{
  "type": "Feature",
  "properties": {
    "addr:full":"Calle de Robledo, S/n Menasalbas Toledo 45128",
    "addr:housenumber":"s / n",
    "addr:postcode":"45128",
    "addr:street":"Calle De Robledo",
    "iso:country":"ES",
    "sg:address":"Calle de Robledo, S/n",
    "sg:city":"Menasalbas",
    "sg:orig_category":"Charcuter\u00cdas (al Por Mayor)",
    "sg:phone":"+34 925 41 30 03",
    "sg:postcode":"45128",
    "sg:province":"Toledo",
    "wof:name":"Cerezo Rodriguez Pedro",
    "wof:placetype":"venue"
},
  "geometry": {"coordinates":[-4.2917170525,39.6361808777],"type":"Point"}
}