{
  "type": "Feature",
  "properties": {
    "addr:full":"Calle de Juan Antonio Fernandez, 53 Tudela Navarra 31500",
    "addr:housenumber":"53",
    "addr:postcode":"31500",
    "addr:street":"Calle De Juan Antonio Fernandez",
    "iso:country":"ES",
    "sg:address":"Calle de Juan Antonio Fernandez, 53",
    "sg:city":"Tudela",
    "sg:orig_category":"Ortopedia General",
    "sg:phone":"+34 948 82 50 05",
    "sg:postcode":"31500",
    "sg:province":"Navarra",
    "wof:name":"Moracho Perez Maria Josefa",
    "wof:placetype":"venue"
},
  "geometry": {"coordinates":[-1.6054799557,42.059627533],"type":"Point"}
}