{
  "type": "Feature",
  "properties": {
    "addr:full":"Carrer de Bonavista, 112 S. Just Desvern Barcelona 08960",
    "addr:housenumber":"112",
    "addr:postcode":"08960",
    "addr:street":"Carrer De Bonavista;S. Just Desvern Barcelona",
    "iso:country":"ES",
    "sg:address":"Carrer de Bonavista, 112",
    "sg:city":"S. Just Desvern",
    "sg:orig_category":"Ingenier\u00cda, Centros De Estudios (diversos)",
    "sg:phone":"+34 933 71 91 56",
    "sg:postcode":"08960",
    "sg:province":"Barcelona",
    "wof:name":"Orti Guardia Alfonso",
    "wof:placetype":"venue"
},
  "geometry": {"coordinates":[2.0764169693,41.3858299255],"type":"Point"}
}