{
  "type": "Feature",
  "properties": {
    "iso:country":"ES",
    "sg:address":"Calle de San Miguel, S/n",
    "sg:city":"Cuevas Almanzora",
    "sg:orig_category":"Cementerios",
    "sg:phone":"+34 950 45 63 35",
    "sg:postcode":"04610",
    "sg:province":"Almer\u00eda",
    "wof:name":"Ayuntamiento De Cuevas Del Almanzora",
    "wof:placetype":"venue"
},
  "geometry": {"coordinates":[-1.8803988695,37.2959327698],"type":"Point"}
}