{
  "type": "Feature",
  "properties": {
    "iso:country":"ES",
    "sg:address":"Cra Navarcles, Km. 0004,0",
    "sg:city":"Santpedor",
    "sg:orig_category":"Conservas De Legumbres (fabricaci\u00d3n, Al Por Mayor)",
    "sg:phone":"+34 938 27 25 12",
    "sg:postcode":"08251",
    "sg:province":"Barcelona",
    "wof:name":"Conserves Ferrer S.a.",
    "wof:placetype":"venue"
},
  "geometry": {"coordinates":[1.8371499777,41.8343658447],"type":"Point"}
}