{
  "type": "Feature",
  "properties": {
    "iso:country":"ES",
    "sg:address":"Carrer de Vidal I Quadras, 3",
    "sg:city":"Barcelona",
    "sg:orig_category":"Peluquer\u00cdas, Peluquer\u00cda Mixta",
    "sg:phone":"+34 932 80 13 77",
    "sg:postcode":"08017",
    "sg:province":"Barcelona",
    "wof:name":"Sogicoif S.a.",
    "wof:placetype":"venue"
},
  "geometry": {"coordinates":[2.1143989563,41.4051055908],"type":"Point"}
}