{
  "type": "Feature",
  "properties": {
    "iso:country":"ES",
    "sg:address":"Calle de San Nicolas, 8",
    "sg:city":"Gijon",
    "sg:orig_category":"Librer\u00cdas",
    "sg:phone":"+34 985 38 02 21",
    "sg:postcode":"33210",
    "sg:province":"Asturias",
    "wof:name":"Ordo\u00f1ez Comesa\u00f1a Rosa Maria",
    "wof:placetype":"venue"
},
  "geometry": {"coordinates":[-5.6688418388,43.5241279602],"type":"Point"}
}