{
  "type": "Feature",
  "properties": {
    "addr:full":"Calle de Virgen De Loreto, 18 Majadahonda Madrid 28220",
    "addr:housenumber":"18",
    "addr:postcode":"28220",
    "addr:street":"Calle De Virgen De Loreto",
    "iso:country":"ES",
    "sg:address":"Calle de Virgen De Loreto, 18",
    "sg:city":"Majadahonda",
    "sg:orig_category":"Perfumer\u00cda Y Cosm\u00c9tica (fabricaci\u00d3n, Al Por Mayor)",
    "sg:phone":"+34 916 38 74 62",
    "sg:postcode":"28220",
    "sg:province":"Madrid",
    "wof:name":"Fragancias Y Aromas Consulting S.l.",
    "wof:placetype":"venue"
},
  "geometry": {"coordinates":[-3.8787400723,40.4751396179],"type":"Point"}
}