{
  "type": "Feature",
  "properties": {
    "iso:country":"ES",
    "sg:address":"Avda Guijar (del), 1",
    "sg:city":"Arganda",
    "sg:orig_category":"Molduras, Junquillos, Listones Y Molduras Perforadas",
    "sg:phone":"+34 918 71 17 76",
    "sg:postcode":"28500",
    "sg:province":"Madrid",
    "wof:name":"Rodriguez Noguerales Carmelo",
    "wof:placetype":"venue"
},
  "geometry": {"coordinates":[-3.4630019665,40.3189353943],"type":"Point"}
}