{
  "type": "Feature",
  "properties": {
    "iso:country":"ES",
    "sg:address":"Plaz Purisima Concepcion, 1",
    "sg:city":"Arquillos",
    "sg:orig_category":"Aguas (distribuci\u00d3n, Servicios)",
    "sg:phone":"+34 953 63 30 40",
    "sg:postcode":"23230",
    "sg:province":"Ja\u00e9n",
    "wof:name":"Hidrogestion",
    "wof:placetype":"venue"
},
  "geometry": {"coordinates":[-3.4296445847,38.213924408],"type":"Point"}
}