{
  "type": "Feature",
  "properties": {
    "addr:full":"Ctra. B-motril, Km. 0312,0 Mengibar Ja\u00e9n 23620",
    "addr:postcode":"23620",
    "addr:street":"Ctra. B-Motril Km. 0312,0 Mengibar Jae\u0301N",
    "iso:country":"ES",
    "sg:address":"Ctra. B-motril, Km. 0312,0",
    "sg:city":"Mengibar",
    "sg:orig_category":"Muebles",
    "sg:phone":"+34 953 37 12 00",
    "sg:postcode":"23620",
    "sg:province":"Ja\u00e9n",
    "wof:name":"Creaciones Del Descanso S.l.",
    "wof:placetype":"venue"
},
  "geometry": {"coordinates":[-3.8033540249,37.970615387],"type":"Point"}
}