{
  "type": "Feature",
  "properties": {
    "addr:full":"Carrer de Major, 12 Prat Llobregat Barcelona 08820",
    "addr:housenumber":"12",
    "addr:postcode":"08820",
    "addr:street":"Carrer De Major;Llobregat",
    "iso:country":"ES",
    "sg:address":"Carrer de Major, 12",
    "sg:city":"Prat Llobregat",
    "sg:orig_category":"Farmacias",
    "sg:phone":"+34 933 79 06 01",
    "sg:postcode":"08820",
    "sg:province":"Barcelona",
    "wof:name":"Farmacia Alvarez Quintana Bcn, S.c.p.",
    "wof:placetype":"venue"
},
  "geometry": {"coordinates":[2.0935239792,41.3311538696],"type":"Point"}
}