{
  "type": "Feature",
  "properties": {
    "iso:country":"ES",
    "sg:address":"Av Matadepera, 138",
    "sg:city":"Sabadell",
    "sg:orig_category":"Peluquer\u00cdas, Peluquer\u00cda Mixta",
    "sg:phone":"+34 937 16 46 40",
    "sg:postcode":"08207",
    "sg:province":"Barcelona",
    "wof:name":"Gerona Martinez Pedro",
    "wof:placetype":"venue"
},
  "geometry": {"coordinates":[2.0882260799,41.5676002502],"type":"Point"}
}