{
  "type": "Feature",
  "properties": {
    "iso:country":"ES",
    "sg:address":"Praj San Vicente, 6",
    "sg:city":"Alcora",
    "sg:orig_category":"Promotores Constructores",
    "sg:phone":"+34 964 36 04 41",
    "sg:postcode":"12110",
    "sg:province":"Castell\u00f3n",
    "wof:name":"Lopez Garcia Jose",
    "wof:placetype":"venue"
},
  "geometry": {"coordinates":[-0.2178789973,40.0734786987],"type":"Point"}
}