{
  "type": "Feature",
  "properties": {
    "addr:full":"Calle de Carretera De Villena, S/n Yecla Murcia 30510",
    "addr:housenumber":"s / n",
    "addr:postcode":"30510",
    "addr:street":"Calle De Carretera De Villena",
    "iso:country":"ES",
    "sg:address":"Calle de Carretera De Villena, S/n",
    "sg:city":"Yecla",
    "sg:orig_category":"Agencias Y Agentes Comerciales, Representantes",
    "sg:phone":"+34 968 75 12 23",
    "sg:postcode":"30510",
    "sg:province":"Murcia",
    "wof:name":"Lombrimur C.b.",
    "wof:placetype":"venue"
},
  "geometry": {"coordinates":[-1.173699379,38.6051635742],"type":"Point"}
}