{
  "type": "Feature",
  "properties": {
    "iso:country":"ES",
    "sg:address":"Calle de Robinson Crusoe, 7",
    "sg:city":"Malaga",
    "sg:orig_category":"Empresas De Vigilancia, Guardia Y Protecci\u00d3n",
    "sg:phone":"+34 952 32 11 81",
    "sg:postcode":"29006",
    "sg:province":"M\u00e1laga",
    "sg:website":"www.gruposermacon.com",
    "wof:name":"Alben Vega Bao E Hijos S.l",
    "wof:placetype":"venue"
},
  "geometry": {"coordinates":[-4.4635691643,36.7094612122],"type":"Point"}
}