{
  "type": "Feature",
  "properties": {
    "iso:country":"ES",
    "sg:address":"Calle de Fueros, 18",
    "sg:city":"Salvatierra O Agurain",
    "sg:orig_category":"Caf\u00c9s, Bares, Cervecer\u00cdas",
    "sg:phone":"+34 945 31 22 23",
    "sg:postcode":"01200",
    "sg:province":"\u00c1lava",
    "wof:name":"C.t.a. Comunicaciones Telefonicas Alavesas",
    "wof:placetype":"venue"
},
  "geometry": {"coordinates":[-2.3866341114,42.8496437073],"type":"Point"}
}