{
  "type": "Feature",
  "properties": {
    "iso:country":"ES",
    "sg:address":"Calle de Antonio Acu\u00d1a, 6",
    "sg:city":"Madrid",
    "sg:orig_category":"Trajes Y Adornos De Boda (confecci\u00d3n, Al Por Menor)",
    "sg:phone":"+34 914 31 23 70",
    "sg:postcode":"28009",
    "sg:province":"Madrid",
    "wof:name":"Arroyo Del Rio Jose Antonio",
    "wof:placetype":"venue"
},
  "geometry": {"coordinates":[-3.6788396835,40.4227638245],"type":"Point"}
}