{
  "type": "Feature",
  "properties": {
    "addr:full":"Avda Ourense (de), 195 Xinzo De Limia Ourense 32630",
    "addr:housenumber":"195",
    "addr:postcode":"32630",
    "addr:street":"Avda Ourense De",
    "iso:country":"ES",
    "sg:address":"Avda Ourense (de), 195",
    "sg:city":"Xinzo De Limia",
    "sg:orig_category":"Mec\u00c1nico Del Autom\u00d3vil",
    "sg:phone":"+34 988 46 09 76",
    "sg:postcode":"32630",
    "sg:province":"Ourense",
    "wof:name":"Pousa Lage Antonio",
    "wof:placetype":"venue"
},
  "geometry": {"coordinates":[-7.7259440422,42.0631408691],"type":"Point"}
}