{
  "type": "Feature",
  "properties": {
    "iso:country":"ES",
    "sg:address":"Calle de Diaz De Haro Maria, 10",
    "sg:city":"Bilbao",
    "sg:orig_category":"Centros De Coordinaci\u00d3n",
    "sg:phone":"+34 944 41 29 39",
    "sg:postcode":"48013",
    "sg:province":"Vizcaya",
    "wof:name":"Tramites Generales Para Empresas, Sl",
    "wof:placetype":"venue"
},
  "geometry": {"coordinates":[-2.9458360672,43.2619171143],"type":"Point"}
}