{
  "type": "Feature",
  "properties": {
    "addr:full":"Bda Rev. Joaquim Bosch, 2 Cassa Selva Girona 17244",
    "addr:housenumber":"2",
    "addr:postcode":"17244",
    "addr:street":"Bosch",
    "iso:country":"ES",
    "sg:address":"Bda Rev. Joaquim Bosch, 2",
    "sg:city":"Cassa Selva",
    "sg:orig_category":"Iglesia Cat\u00d3lica",
    "sg:phone":"+34 972 46 01 63",
    "sg:postcode":"17244",
    "sg:province":"Girona",
    "wof:name":"Bisbat De Girona",
    "wof:placetype":"venue"
},
  "geometry": {"coordinates":[2.8780760765,41.8896598816],"type":"Point"}
}