{
  "type": "Feature",
  "properties": {
    "addr:full":"Carr Maria Benlliure, De, 56 Carcaixent Valencia 46740",
    "addr:housenumber":"56",
    "addr:postcode":"46740",
    "addr:street":"Carr Maria Benlliure De",
    "iso:country":"ES",
    "sg:address":"Carr Maria Benlliure, De, 56",
    "sg:city":"Carcaixent",
    "sg:orig_category":"Promotores Constructores",
    "sg:phone":"+34 962 43 46 91",
    "sg:postcode":"46740",
    "sg:province":"Valencia",
    "wof:name":"Crispau S.l.",
    "wof:placetype":"venue"
},
  "geometry": {"coordinates":[-0.4510819912,39.1191329956],"type":"Point"}
}