{
  "type": "Feature",
  "properties": {
    "iso:country":"ES",
    "sg:address":"Avda Viveiro (de), 12",
    "sg:city":"Ferreira",
    "sg:orig_category":"Chapister\u00cda",
    "sg:phone":"+34 982 57 42 22",
    "sg:postcode":"27770",
    "sg:province":"Lugo",
    "wof:name":"Fernandez Guerreiro Jose Luis",
    "wof:placetype":"venue"
},
  "geometry": {"coordinates":[-7.4423680305,43.5538711548],"type":"Point"}
}