{
  "type": "Feature",
  "properties": {
    "iso:country":"ES",
    "sg:address":"Calle de Obispo Cobos, 24",
    "sg:city":"Ubeda",
    "sg:orig_category":"Art\u00cdculos De Regalo (al Por Menor)",
    "sg:phone":"+34 953 75 14 03",
    "sg:postcode":"23400",
    "sg:province":"Ja\u00e9n",
    "wof:name":"Martin Villar Vizcaino S.l.",
    "wof:placetype":"venue"
},
  "geometry": {"coordinates":[-3.3760390282,38.011390686],"type":"Point"}
}