{
  "type": "Feature",
  "properties": {
    "iso:country":"ES",
    "sg:address":"Avda Constitucion, 7",
    "sg:city":"San Miguel",
    "sg:orig_category":"Doctores En Medicina",
    "sg:phone":"+34 968 23 77 82",
    "sg:postcode":"30008",
    "sg:province":"Murcia",
    "wof:name":"Martinez Lozano Joaquina Margarita",
    "wof:placetype":"venue"
},
  "geometry": {"coordinates":[-1.1315510273,37.9904098511],"type":"Point"}
}