{
  "type": "Feature",
  "properties": {
    "addr:full":"Rua Rosalia De Castro, 1 Noia La Coru\u00f1a 15200",
    "addr:housenumber":"1",
    "addr:postcode":"15200",
    "addr:street":"Rua Rosalia De Castro;La Corun\u0303A",
    "iso:country":"ES",
    "sg:address":"Rua Rosalia De Castro, 1",
    "sg:city":"Noia",
    "sg:orig_category":"Ense\u00d1anza Secundaria: Colegios Y Escuelas Privadas",
    "sg:phone":"+34 981 82 01 19",
    "sg:postcode":"15200",
    "sg:province":"La Coru\u00f1a",
    "wof:name":"Instituto De Ense\u00f1anza Secundaria Virxe Do Mar",
    "wof:placetype":"venue"
},
  "geometry": {"coordinates":[-8.8884820938,42.7858085632],"type":"Point"}
}