{
  "type": "Feature",
  "properties": {
    "iso:country":"ES",
    "sg:address":"Rua Conde De Vallellano, 27",
    "sg:city":"Carballi\u00f1o",
    "sg:orig_category":"Panader\u00cdas, Panader\u00cdas",
    "sg:phone":"+34 988 27 51 62",
    "sg:postcode":"32500",
    "sg:province":"Ourense",
    "wof:name":"Manuel Gallardo Penedo S.l.",
    "wof:placetype":"venue"
},
  "geometry": {"coordinates":[-8.0758600235,42.4306373596],"type":"Point"}
}