{
  "type": "Feature",
  "properties": {
    "iso:country":"ES",
    "sg:address":"Calle de Nueva, 12",
    "sg:city":"Malaga",
    "sg:orig_category":"Trajes Y Adornos De Boda (confecci\u00d3n, Al Por Menor)",
    "sg:phone":"+34 952 22 78 95",
    "sg:postcode":"29005",
    "sg:province":"M\u00e1laga",
    "wof:name":"Navarro Rivera Juan",
    "wof:placetype":"venue"
},
  "geometry": {"coordinates":[-4.422855854,36.7204170227],"type":"Point"}
}