{
  "type": "Feature",
  "properties": {
    "iso:country":"ES",
    "sg:address":"Calle de Toneleros, 22",
    "sg:city":"Puerto Mazarron",
    "sg:orig_category":"Inmobiliaria (agencias)",
    "sg:phone":"+34 968 59 43 24",
    "sg:postcode":"30860",
    "sg:province":"Murcia",
    "wof:name":"Gestion Inmobiliaria Brisamar S.l.",
    "wof:placetype":"venue"
},
  "geometry": {"coordinates":[-1.2596509457,37.5647315979],"type":"Point"}
}