{
  "type": "Feature",
  "properties": {
    "iso:country":"ES",
    "sg:address":"Trva Huerta De Los Cristales, 11",
    "sg:city":"Marbella",
    "sg:orig_category":"Muebles Y Accesorios Para Cocinas Y Cuartos De Ba\u00d1o (al Por Menor)",
    "sg:phone":"+34 952 82 09 60",
    "sg:postcode":"29600",
    "sg:province":"M\u00e1laga",
    "sg:website":"www.anabelen_gonz.es",
    "wof:name":"Gonzalez Sanchez Ana Belen",
    "wof:placetype":"venue"
},
  "geometry": {"coordinates":[-4.8797497749,36.5110855103],"type":"Point"}
}