{
  "type": "Feature",
  "properties": {
    "addr:full":"Avda Espa\u00d1a (de), 44 Dos Hermanas Sevilla 41700",
    "addr:housenumber":"44",
    "addr:postcode":"41700",
    "addr:street":"Avda Espan\u0303A De",
    "iso:country":"ES",
    "sg:address":"Avda Espa\u00d1a (de), 44",
    "sg:city":"Dos Hermanas",
    "sg:orig_category":"Quincaller\u00cda (al Por Menor)",
    "sg:phone":"+34 955 67 87 74",
    "sg:postcode":"41700",
    "sg:province":"Sevilla",
    "wof:name":"Delgado Lopez Manuel",
    "wof:placetype":"venue"
},
  "geometry": {"coordinates":[-5.9256310463,37.292137146],"type":"Point"}
}