{
  "type": "Feature",
  "properties": {
    "addr:full":"Calle de Dario De Regoyos, 42 Irun Guip\u00f9zcoa 20305",
    "addr:housenumber":"42",
    "addr:postcode":"20305",
    "addr:street":"Calle De Dario De Regoyos;Guipu\u0300Zcoa",
    "iso:country":"ES",
    "sg:address":"Calle de Dario De Regoyos, 42",
    "sg:city":"Irun",
    "sg:orig_category":"Asociaciones, Organismos Culturales Y Socioeducativos",
    "sg:phone":"+34 943 63 37 90",
    "sg:postcode":"20305",
    "sg:province":"Guip\u00f9zcoa",
    "wof:name":"Pe\u00f1a Irundarra De Amigos Del Real Madrid",
    "wof:placetype":"venue"
},
  "geometry": {"coordinates":[-1.7704739571,43.3415412903],"type":"Point"}
}