{
  "type": "Feature",
  "properties": {
    "addr:full":"Carrer de Valencia, 574 Barcelona Barcelona 08026",
    "addr:housenumber":"574",
    "addr:postcode":"08026",
    "addr:street":"Carrer De Valencia",
    "iso:country":"ES",
    "sg:address":"Carrer de Valencia, 574",
    "sg:city":"Barcelona",
    "sg:orig_category":"Comercio, Reparaci\u00d3n De Bicicletas, De Motocicletas, De Accesorios",
    "sg:phone":"+34 932 65 65 53",
    "sg:postcode":"08026",
    "sg:province":"Barcelona",
    "wof:name":"Barna-cicloturisme S.l.",
    "wof:placetype":"venue"
},
  "geometry": {"coordinates":[2.1837038994,41.4078330994],"type":"Point"}
}