{
  "type": "Feature",
  "properties": {
    "addr:full":"Calle de Floridablanca, 3 Almeria Almer\u00eda 04001",
    "addr:housenumber":"3",
    "addr:postcode":"04001",
    "addr:street":"Calle De Floridablanca",
    "iso:country":"ES",
    "sg:address":"Calle de Floridablanca, 3",
    "sg:city":"Almeria",
    "sg:orig_category":"Abogados",
    "sg:phone":"+34 950 23 88 84",
    "sg:postcode":"04001",
    "sg:province":"Almer\u00eda",
    "wof:name":"Checa Garcia Juan",
    "wof:placetype":"venue"
},
  "geometry": {"coordinates":[-2.4655280113,36.8396377563],"type":"Point"}
}