{
  "type": "Feature",
  "properties": {
    "addr:full":"Ctra Cortes (de), Km. 0004,0 Jerez De La Frontera C\u00e1diz 11406",
    "addr:postcode":"11406",
    "addr:street":"Ctra Cortes De Km. 0004,0",
    "iso:country":"ES",
    "sg:address":"Ctra Cortes (de), Km. 0004,0",
    "sg:city":"Jerez De La Frontera",
    "sg:orig_category":"Molduras, Junquillos, Listones Y Molduras Perforadas",
    "sg:phone":"+34 956 33 86 84",
    "sg:postcode":"11406",
    "sg:province":"C\u00e1diz",
    "wof:name":"Garrido Nu\u00f1ez Manuel",
    "wof:placetype":"venue"
},
  "geometry": {"coordinates":[-6.0907607079,36.6850891113],"type":"Point"}
}