{
  "type": "Feature",
  "properties": {
    "iso:country":"ES",
    "sg:address":"Carr Juan Izquierdo (de), 57",
    "sg:city":"Lliria",
    "sg:orig_category":"Sindicatos De Trabajadores",
    "sg:phone":"+34 962 78 34 68",
    "sg:postcode":"46160",
    "sg:province":"Valencia",
    "wof:name":"Comissions Obreres Del Pais Valencia",
    "wof:placetype":"venue"
},
  "geometry": {"coordinates":[-0.5927489996,39.6237411499],"type":"Point"}
}