{
  "type": "Feature",
  "properties": {
    "iso:country":"ES",
    "sg:address":"Calle de Inmobiliaria Setsa, S/n",
    "sg:city":"Langreo",
    "sg:orig_category":"Servicios De Telecomunicaciones",
    "sg:phone":"+34 985 69 63 56",
    "sg:postcode":"33930",
    "sg:province":"Asturias",
    "sg:website":"www.movired.as",
    "wof:name":"Moviastur Networks S.a.",
    "wof:placetype":"venue"
},
  "geometry": {"coordinates":[-5.6926388741,43.3080215454],"type":"Point"}
}