{
  "type": "Feature",
  "properties": {
    "iso:country":"ES",
    "sg:address":"Ctra Villanueva (de), S/n",
    "sg:city":"Archena",
    "sg:orig_category":"M\u00c1quinas, Material Y Suministros Para Cajas Y Embalajes",
    "sg:phone":"+34 968 67 12 92",
    "sg:postcode":"30600",
    "sg:province":"Murcia",
    "wof:name":"Guillen Guillen Pedro Jose",
    "wof:placetype":"venue"
},
  "geometry": {"coordinates":[-1.3030389547,38.1182861328],"type":"Point"}
}