{
  "type": "Feature",
  "properties": {
    "iso:country":"ES",
    "sg:address":"Avda Federico Soto, 4",
    "sg:city":"Alacant",
    "sg:orig_category":"M\u00c9dicos: Estomatolog\u00cda",
    "sg:phone":"+34 965 21 53 00",
    "sg:postcode":"03001",
    "sg:province":"Alicante",
    "wof:name":"Novasmile S.l.",
    "wof:placetype":"venue"
},
  "geometry": {"coordinates":[-0.4889090061,38.3441581726],"type":"Point"}
}