{
  "type": "Feature",
  "properties": {
    "iso:country":"ES",
    "sg:address":"Pol Ind Tres Hermanas, 8",
    "sg:city":"Aspe",
    "sg:orig_category":"Fabricaci\u00d3n De Muebles",
    "sg:phone":"+34 965 49 36 79",
    "sg:postcode":"03680",
    "sg:province":"Alicante",
    "wof:name":"Muebles Joinma S.l.",
    "wof:placetype":"venue"
},
  "geometry": {"coordinates":[-0.7746989727,38.3399620056],"type":"Point"}
}