{
  "type": "Feature",
  "properties": {
    "addr:full":"Pg Francesc Cambo, S/n Besalu Girona 17850",
    "addr:housenumber":"s / n",
    "addr:postcode":"17850",
    "addr:street":"Pg Francesc Cambo",
    "iso:country":"ES",
    "sg:address":"Pg Francesc Cambo, S/n",
    "sg:city":"Besalu",
    "sg:orig_category":"Polideportivos",
    "sg:phone":"+34 972 59 04 77",
    "sg:postcode":"17850",
    "sg:province":"Girona",
    "wof:name":"Ajuntament De Besalu - Pavello Municipal",
    "wof:placetype":"venue"
},
  "geometry": {"coordinates":[2.695966959,42.1990852356],"type":"Point"}
}