{
  "type": "Feature",
  "properties": {
    "addr:full":"C/ Sant Ramon, 120 Cerdanyola Valles Barcelona 08290",
    "addr:housenumber":"120",
    "addr:postcode":"08290",
    "addr:street":"C / Sant Ramon;Valles Barcelona",
    "iso:country":"ES",
    "sg:address":"C/ Sant Ramon, 120",
    "sg:city":"Cerdanyola Valles",
    "sg:orig_category":"Trabajos De Topograf\u00cda",
    "sg:phone":"+34 935 80 59 47",
    "sg:postcode":"08290",
    "sg:province":"Barcelona",
    "wof:name":"Carttop Proyectos S.agrafics S.l.",
    "wof:placetype":"venue"
},
  "geometry": {"coordinates":[2.1373128891,41.4907646179],"type":"Point"}
}