{
  "type": "Feature",
  "properties": {
    "addr:full":"Carrer de Coral Infantil Rossinyols, 3 Lloren\u00e7 Penedes Tarragona 43712",
    "addr:housenumber":"3",
    "addr:postcode":"43712",
    "addr:street":"Carrer De;Llorenc\u0327 Penedes",
    "iso:country":"ES",
    "sg:address":"Carrer de Coral Infantil Rossinyols, 3",
    "sg:city":"Lloren\u00e7 Penedes",
    "sg:orig_category":"Empresas De Limpieza",
    "sg:phone":"+34 977 69 80 89",
    "sg:postcode":"43712",
    "sg:province":"Tarragona",
    "wof:name":"Grado-net Scp",
    "wof:placetype":"venue"
},
  "geometry": {"coordinates":[1.550254941,41.2816009521],"type":"Point"}
}