{
  "type": "Feature",
  "properties": {
    "iso:country":"ES",
    "sg:address":"Calle de Agata, 13",
    "sg:city":"Almeria",
    "sg:orig_category":"Escotaduras, Torneados",
    "sg:phone":"+34 950 14 10 57",
    "sg:postcode":"04009",
    "sg:province":"Almer\u00eda",
    "wof:name":"Alvarez Nieto Manuel",
    "wof:placetype":"venue"
},
  "geometry": {"coordinates":[-2.4423263073,36.8464546204],"type":"Point"}
}