{
  "type": "Feature",
  "properties": {
    "iso:country":"ES",
    "sg:address":"Calle de Arra\u00d1ales, 1",
    "sg:city":"Torreperogil",
    "sg:orig_category":"Farmacias",
    "sg:phone":"+34 953 77 60 62",
    "sg:postcode":"23320",
    "sg:province":"Ja\u00e9n",
    "wof:name":"Poyatos Lorite Mercedes",
    "wof:placetype":"venue"
},
  "geometry": {"coordinates":[-3.2890634537,38.0328369141],"type":"Point"}
}