{
  "type": "Feature",
  "properties": {
    "iso:country":"ES",
    "sg:address":"Carrer de Teulada (de), 20",
    "sg:city":"Gata Gorgos",
    "sg:orig_category":"Confecci\u00d3n De Sombreros Y Tocados",
    "sg:phone":"+34 965 75 61 54",
    "sg:postcode":"03740",
    "sg:province":"Alicante",
    "wof:name":"Torres Feliu S.l.",
    "wof:placetype":"venue"
},
  "geometry": {"coordinates":[0.0852200016,38.7730064392],"type":"Point"}
}