{
  "type": "Feature",
  "properties": {
    "iso:country":"ES",
    "sg:address":"Calle de Lecera, 33",
    "sg:city":"Zaragoza",
    "sg:orig_category":"Empresas De Portes Y Mensajer\u00cda",
    "sg:phone":"+34 976 47 22 49",
    "sg:postcode":"50014",
    "sg:province":"Zaragoza",
    "wof:name":"Unipost S.a.",
    "wof:placetype":"venue"
},
  "geometry": {"coordinates":[-0.8556770086,41.6706199646],"type":"Point"}
}