{
  "type": "Feature",
  "properties": {
    "iso:country":"ES",
    "sg:address":"Calle de Sintes Obrador, 4",
    "sg:city":"Arcos Jalon",
    "sg:orig_category":"Internados & Ense\u00d1anza Privada",
    "sg:phone":"+34 975 32 04 26",
    "sg:postcode":"42250",
    "sg:province":"Soria",
    "wof:name":"Escuela Hogar Julian Sanz Del Rio",
    "wof:placetype":"venue"
},
  "geometry": {"coordinates":[-2.2755200863,41.2157592773],"type":"Point"}
}