{
  "type": "Feature",
  "properties": {
    "addr:full":"Pg Olot, 99 Girona Girona 17006",
    "addr:housenumber":"99",
    "addr:postcode":"17006",
    "addr:street":"Pg Olot",
    "iso:country":"ES",
    "sg:address":"Pg Olot, 99",
    "sg:city":"Girona",
    "sg:orig_category":"Veh\u00cdculos De Ocasi\u00d3n",
    "sg:phone":"+34 972 24 54 28",
    "sg:postcode":"17006",
    "sg:province":"Girona",
    "wof:name":"Expo Automobil Girona S.l.",
    "wof:placetype":"venue"
},
  "geometry": {"coordinates":[2.8033111095,41.9745254517],"type":"Point"}
}