{
  "type": "Feature",
  "properties": {
    "iso:country":"ES",
    "sg:address":"Avda Alfonso El Sabio, 9",
    "sg:city":"Alacant",
    "sg:orig_category":"Arquitectos",
    "sg:phone":"+34 965 14 25 67",
    "sg:postcode":"03002",
    "sg:province":"Alicante",
    "wof:name":"Gomez De Cadiz Delgado De Molina Jorge",
    "wof:placetype":"venue"
},
  "geometry": {"coordinates":[-0.4857789874,38.347694397],"type":"Point"}
}