{
  "type": "Feature",
  "properties": {
    "addr:full":"Calle de Sagarminaga, 42 Bilbao Vizcaya 48004",
    "addr:housenumber":"42",
    "addr:postcode":"48004",
    "addr:street":"Calle De Sagarminaga",
    "iso:country":"ES",
    "sg:address":"Calle de Sagarminaga, 42",
    "sg:city":"Bilbao",
    "sg:orig_category":"Tapiceros Y Tapiceros",
    "sg:phone":"+34 944 11 68 40",
    "sg:postcode":"48004",
    "sg:province":"Vizcaya",
    "wof:name":"Lozano Astorquiza Maria Elisa",
    "wof:placetype":"venue"
},
  "geometry": {"coordinates":[-2.9120659828,43.2483139038],"type":"Point"}
}