{
  "type": "Feature",
  "properties": {
    "iso:country":"ES",
    "sg:address":"Avda Menendez Y Pelayo, 3",
    "sg:city":"Valencia",
    "sg:orig_category":"Inform\u00c1tica (estudios, Servicios, Asesor\u00cda, Formaci\u00d3n)",
    "sg:phone":"+34 963 39 14 28",
    "sg:postcode":"46010",
    "sg:province":"Valencia",
    "wof:name":"Agrupacion Empresas Automatismos Montajes Y Servicios S.l.",
    "wof:placetype":"venue"
},
  "geometry": {"coordinates":[-0.3638040125,39.4802322388],"type":"Point"}
}