{
  "type": "Feature",
  "properties": {
    "addr:full":"Carrer de Jacint Verdaguer, S/n S. Fruitos Bages Barcelona 08272",
    "addr:housenumber":"s",
    "addr:postcode":"08272",
    "addr:street":"Carrer De Jacint Verdaguer;/ N S. Fruitos Bages Barcelona",
    "iso:country":"ES",
    "sg:address":"Carrer de Jacint Verdaguer, S/n",
    "sg:city":"S. Fruitos Bages",
    "sg:orig_category":"Peluquer\u00cdas, Peluquer\u00cda Mixta",
    "sg:phone":"+34 938 76 02 15",
    "sg:postcode":"08272",
    "sg:province":"Barcelona",
    "wof:name":"Serra Segarra Asuncion",
    "wof:placetype":"venue"
},
  "geometry": {"coordinates":[1.87520504,41.7521934509],"type":"Point"}
}