{
  "type": "Feature",
  "properties": {
    "addr:full":"Calle de Terral, 1 Humera-somosaguas-prado Del Rey Madrid 28223",
    "addr:housenumber":"1",
    "addr:postcode":"28223",
    "addr:street":"Calle De Terral",
    "iso:country":"ES",
    "sg:address":"Calle de Terral, 1",
    "sg:city":"Humera-somosaguas-prado Del Rey",
    "sg:orig_category":"Inversiones",
    "sg:phone":"+34 915 18 62 72",
    "sg:postcode":"28223",
    "sg:province":"Madrid",
    "wof:name":"Roberna Inversiones S.l",
    "wof:placetype":"venue"
},
  "geometry": {"coordinates":[-3.7978088856,40.4075965881],"type":"Point"}
}