{
  "type": "Feature",
  "properties": {
    "iso:country":"ES",
    "sg:address":"Ctra. Tordesillas, S/n",
    "sg:city":"Coreses",
    "sg:orig_category":"Fabricaci\u00d3n De Productos L\u00c1cteos Y Derivados",
    "sg:phone":"+34 980 50 01 14",
    "sg:postcode":"49530",
    "sg:province":"Zamora",
    "wof:name":"Qualia Lacteos S.l.u.",
    "wof:placetype":"venue"
},
  "geometry": {"coordinates":[-5.6516489983,41.5275611877],"type":"Point"}
}