{
  "type": "Feature",
  "properties": {
    "iso:country":"ES",
    "sg:address":"Av Doctor Severo Ochoa, 59",
    "sg:city":"Benidorm",
    "sg:orig_category":"Agencias Y Agentes Comerciales, Representantes",
    "sg:phone":"+34 965 86 55 88",
    "sg:postcode":"03500",
    "sg:province":"Alicante",
    "wof:name":"Barderas Reviejo Antonio",
    "wof:placetype":"venue"
},
  "geometry": {"coordinates":[-0.1743289977,38.5408058167],"type":"Point"}
}