{
  "type": "Feature",
  "properties": {
    "addr:full":"Calle de Se\u00d1era, 64 Alaquas Valencia 46970",
    "addr:housenumber":"64",
    "addr:postcode":"46970",
    "addr:street":"Calle De Sen\u0303Era",
    "iso:country":"ES",
    "sg:address":"Calle de Se\u00d1era, 64",
    "sg:city":"Alaquas",
    "sg:orig_category":"Art\u00cdculos De Decoraci\u00d3n",
    "sg:phone":"+34 961 50 09 66",
    "sg:postcode":"46970",
    "sg:province":"Valencia",
    "wof:name":"Interdecora Sp. S.l.",
    "wof:placetype":"venue"
},
  "geometry": {"coordinates":[-0.4710809886,39.4540214539],"type":"Point"}
}