{
  "type": "Feature",
  "properties": {
    "addr:full":"Calle de Federico Coullaut Valera, 6 Hellin Albacete 02400",
    "addr:housenumber":"6",
    "addr:postcode":"02400",
    "addr:street":"Calle De Federico Coullaut Valera",
    "iso:country":"ES",
    "sg:address":"Calle de Federico Coullaut Valera, 6",
    "sg:city":"Hellin",
    "sg:classifiers":[
        {
            "category":"Autos & Motor Vehicles",
            "subcategory":"Automobile Sales",
            "type":"Retail Goods"
        }
    ],
    "sg:phone":"+34 967 30 59 85",
    "sg:postcode":"02400",
    "sg:province":"Albacete",
    "wof:name":"Autoescuela Paco S.l.",
    "wof:placetype":"venue"
},
  "geometry": {"coordinates":[-1.7000410557,38.5090827942],"type":"Point"}
}