{
  "type": "Feature",
  "properties": {
    "addr:full":"Calle de Otero Blas De, 26 Bilbao Vizcaya 48014",
    "addr:housenumber":"26",
    "addr:postcode":"48014",
    "addr:street":"Calle De Otero Blas De",
    "iso:country":"ES",
    "sg:address":"Calle de Otero Blas De, 26",
    "sg:city":"Bilbao",
    "sg:orig_category":"Bazares, Art\u00cdculos De Limpieza Y De Cocina (al Por Menor)",
    "sg:phone":"+34 944 76 18 23",
    "sg:postcode":"48014",
    "sg:province":"Vizcaya",
    "wof:name":"Manjon Perez Maria",
    "wof:placetype":"venue"
},
  "geometry": {"coordinates":[-2.9452960491,43.2702407837],"type":"Point"}
}