{
  "type": "Feature",
  "properties": {
    "addr:full":"Plaz Casilla, 2 Bilbao Vizcaya 48012",
    "addr:housenumber":"2",
    "addr:postcode":"48012",
    "addr:street":"Casilla",
    "iso:country":"ES",
    "sg:address":"Plaz Casilla, 2",
    "sg:city":"Bilbao",
    "sg:orig_category":"Trabajos De Topograf\u00cda",
    "sg:phone":"+34 944 22 08 20",
    "sg:postcode":"48012",
    "sg:province":"Vizcaya",
    "wof:name":"Karmelo Nicolas Garcia",
    "wof:placetype":"venue"
},
  "geometry": {"coordinates":[-2.9445700645,43.257396698],"type":"Point"}
}