{
  "type": "Feature",
  "properties": {
    "addr:full":"Calle de Corona De Aragon, 21 Barbastro Huesca 22300",
    "addr:housenumber":"21",
    "addr:postcode":"22300",
    "addr:street":"Calle De Corona De Aragon",
    "iso:country":"ES",
    "sg:address":"Calle de Corona De Aragon, 21",
    "sg:city":"Barbastro",
    "sg:orig_category":"Albergues",
    "sg:phone":"+34 974 31 10 64",
    "sg:postcode":"22300",
    "sg:province":"Huesca",
    "wof:name":"Lopez Puyuelo Fermin",
    "wof:placetype":"venue"
},
  "geometry": {"coordinates":[0.1285538971,42.0356788635],"type":"Point"}
}