{
  "type": "Feature",
  "properties": {
    "addr:full":"Calle de Santa Ana, 61 Madridejos Toledo 45710",
    "addr:housenumber":"61",
    "addr:postcode":"45710",
    "addr:street":"Calle De Santa Ana",
    "iso:country":"ES",
    "sg:address":"Calle de Santa Ana, 61",
    "sg:city":"Madridejos",
    "sg:orig_category":"Telas Y Sedas (al Por Menor)",
    "sg:phone":"+34 925 46 15 31",
    "sg:postcode":"45710",
    "sg:province":"Toledo",
    "wof:name":"Aguado Laguna Maria Del Milagro",
    "wof:placetype":"venue"
},
  "geometry": {"coordinates":[-3.5294208527,39.467880249],"type":"Point"}
}