{
  "type": "Feature",
  "properties": {
    "addr:full":"Pol Ind Ituci, S/n Escacena Campo Huelva 21870",
    "addr:housenumber":"s",
    "addr:postcode":"21870",
    "addr:street":"/ N Escacena Campo",
    "iso:country":"ES",
    "sg:address":"Pol Ind Ituci, S/n",
    "sg:city":"Escacena Campo",
    "sg:orig_category":"Fabricaci\u00d3n, Alquiler, Venta De Encofrados",
    "sg:phone":"+34 959 42 35 18",
    "sg:postcode":"21870",
    "sg:province":"Huelva",
    "wof:name":"Tableros Y Encofrados Del Sur S.a.",
    "wof:placetype":"venue"
},
  "geometry": {"coordinates":[-6.388449192,37.4082336426],"type":"Point"}
}