{
  "type": "Feature",
  "properties": {
    "iso:country":"ES",
    "sg:address":"Calle de Agustina De Aragon, 5",
    "sg:city":"Ceuta",
    "sg:orig_category":"Alimentaci\u00d3n General (al Por Menor)",
    "sg:phone":"+34 956 51 75 01",
    "sg:postcode":"51001",
    "sg:province":"Ceuta",
    "wof:name":"Rosa Flores Antonio",
    "wof:placetype":"venue"
},
  "geometry": {"coordinates":[-5.3068771362,35.8883018494],"type":"Point"}
}