{
  "type": "Feature",
  "properties": {
    "iso:country":"ES",
    "sg:address":"Carr Mariscal Cabanes, 11",
    "sg:city":"Badalona",
    "sg:orig_category":"Discapacitados",
    "sg:phone":"+34 933 87 29 40",
    "sg:postcode":"08918",
    "sg:province":"Barcelona",
    "wof:name":"Asociacion De Minusvalidos De Barcelona",
    "wof:placetype":"venue"
},
  "geometry": {"coordinates":[2.2186844349,41.4331588745],"type":"Point"}
}