{
  "type": "Feature",
  "properties": {
    "iso:country":"ES",
    "sg:address":"Calle de Dragonera, 8",
    "sg:city":"Palma",
    "sg:orig_category":"Supermercados Y Hipermercados",
    "sg:phone":"+34 971 28 45 85",
    "sg:postcode":"07014",
    "sg:province":"Islas Baleares",
    "wof:name":"Taribo Pujal Carlos",
    "wof:placetype":"venue"
},
  "geometry": {"coordinates":[2.6290199757,39.5787391663],"type":"Point"}
}