{
  "type": "Feature",
  "properties": {
    "addr:full":"Calle de Soledad, 12 Torrejon Ardoz Madrid 28850",
    "addr:housenumber":"12",
    "addr:postcode":"28850",
    "addr:street":"Calle De Soledad",
    "iso:country":"ES",
    "sg:address":"Calle de Soledad, 12",
    "sg:city":"Torrejon Ardoz",
    "sg:orig_category":"Pensiones Familiares",
    "sg:phone":"+34 916 76 61 32",
    "sg:postcode":"28850",
    "sg:province":"Madrid",
    "wof:name":"Servicios Hosteleria El Astigi S.l.",
    "wof:placetype":"venue"
},
  "geometry": {"coordinates":[-3.4768519402,40.4583091736],"type":"Point"}
}