{
  "type": "Feature",
  "properties": {
    "addr:full":"Dtor. Norberto Pizjuan, S/n Boiro La Coru\u00f1a 15930",
    "addr:housenumber":"s / n",
    "addr:postcode":"15930",
    "addr:street":"La Corun\u0303A",
    "iso:country":"ES",
    "sg:address":"Dtor. Norberto Pizjuan, S/n",
    "sg:city":"Boiro",
    "sg:orig_category":"Panader\u00cdas, Panader\u00cdas",
    "sg:phone":"+34 981 84 68 50",
    "sg:postcode":"15930",
    "sg:province":"La Coru\u00f1a",
    "wof:name":"Pi\u00f1eiro Alcalde Maria Fatima",
    "wof:placetype":"venue"
},
  "geometry": {"coordinates":[-8.882019043,42.647354126],"type":"Point"}
}