{
  "type": "Feature",
  "properties": {
    "addr:full":"Calle de Vicente Regueral, 40 Pola De Lena Asturias 33630",
    "addr:housenumber":"40",
    "addr:postcode":"33630",
    "addr:street":"Calle De Vicente Regueral",
    "iso:country":"ES",
    "sg:address":"Calle de Vicente Regueral, 40",
    "sg:city":"Pola De Lena",
    "sg:orig_category":"Confecci\u00d3n (fabricaci\u00d3n, Al Por Mayor)",
    "sg:phone":"+34 985 49 21 12",
    "sg:postcode":"33630",
    "sg:province":"Asturias",
    "wof:name":"Decoraciones Anre S.l.",
    "wof:placetype":"venue"
},
  "geometry": {"coordinates":[-5.8278651237,43.1634254456],"type":"Point"}
}