{
  "type": "Feature",
  "properties": {
    "iso:country":"ES",
    "sg:address":"Calle de General Franco, 13",
    "sg:city":"Cristianos",
    "sg:orig_category":"Abogados",
    "sg:phone":"+34 922 75 14 91",
    "sg:postcode":"38650",
    "sg:province":"Santa Cruz De Tenerife",
    "wof:name":"Mesa Perez Ormaeche S.l.",
    "wof:placetype":"venue"
},
  "geometry": {"coordinates":[-16.7158031464,28.0525684357],"type":"Point"}
}