{
  "type": "Feature",
  "properties": {
    "iso:country":"ES",
    "sg:address":"Calle de Serenata, 1",
    "sg:city":"Marbella",
    "sg:orig_category":"Cajas Para Embalar",
    "sg:phone":"+34 952 82 00 62",
    "sg:postcode":"29600",
    "sg:province":"M\u00e1laga",
    "sg:website":"www.cajamar.es",
    "wof:name":"Cajamar",
    "wof:placetype":"venue"
},
  "geometry": {"coordinates":[-4.8797588348,36.5133361816],"type":"Point"}
}