{
  "type": "Feature",
  "properties": {
    "addr:full":"Calle de Alfredo Atienza, 36 Roda Albacete 02630",
    "addr:housenumber":"36",
    "addr:postcode":"02630",
    "addr:street":"Calle De Alfredo Atienza",
    "iso:country":"ES",
    "sg:address":"Calle de Alfredo Atienza, 36",
    "sg:city":"Roda",
    "sg:orig_category":"Ortopedia General",
    "sg:phone":"+34 967 44 28 06",
    "sg:postcode":"02630",
    "sg:province":"Albacete",
    "wof:name":"Grupo Maser 2005 S.l.",
    "wof:placetype":"venue"
},
  "geometry": {"coordinates":[-2.1548247337,39.2052764893],"type":"Point"}
}