{
  "type": "Feature",
  "properties": {
    "iso:country":"ES",
    "sg:address":"Avda Provincia, S/n",
    "sg:city":"Ibi",
    "sg:orig_category":"Supermercados Y Hipermercados",
    "sg:phone":"+34 966 55 34 57",
    "sg:postcode":"03440",
    "sg:province":"Alicante",
    "wof:name":"Aldi Supermercados S.l.",
    "wof:placetype":"venue"
},
  "geometry": {"coordinates":[-0.5869911909,38.6149635315],"type":"Point"}
}