{
  "type": "Feature",
  "properties": {
    "addr:full":"Calle de Comandante Azcarraga, 4 Madrid Madrid 28016",
    "addr:housenumber":"4",
    "addr:postcode":"28016",
    "addr:street":"Calle De Comandante Azcarraga",
    "iso:country":"ES",
    "sg:address":"Calle de Comandante Azcarraga, 4",
    "sg:city":"Madrid",
    "sg:orig_category":"Promotores Constructores",
    "sg:phone":"+34 913 45 39 00",
    "sg:postcode":"28016",
    "sg:province":"Madrid",
    "wof:name":"Indagsa",
    "wof:placetype":"venue"
},
  "geometry": {"coordinates":[-3.66918993,40.4613723755],"type":"Point"}
}