{
  "type": "Feature",
  "properties": {
    "addr:full":"Calle de Gabriel Miro, 1 Pilar Horadada Alicante 03190",
    "addr:housenumber":"1",
    "addr:postcode":"03190",
    "addr:street":"Calle De Gabriel Miro",
    "iso:country":"ES",
    "sg:address":"Calle de Gabriel Miro, 1",
    "sg:city":"Pilar Horadada",
    "sg:orig_category":"Inmobiliaria (agencias)",
    "sg:phone":"+34 965 35 25 52",
    "sg:postcode":"03190",
    "sg:province":"Alicante",
    "wof:name":"Wretman Janiccee Maria",
    "wof:placetype":"venue"
},
  "geometry": {"coordinates":[-0.792827487,37.8655166626],"type":"Point"}
}