{
  "type": "Feature",
  "properties": {
    "addr:full":"Ctra Madridejos, S/n Villaca\u00f1as Toledo 45860",
    "addr:housenumber":"s / n",
    "addr:postcode":"45860",
    "addr:street":"Ctra Madridejos",
    "iso:country":"ES",
    "sg:address":"Ctra Madridejos, S/n",
    "sg:city":"Villaca\u00f1as",
    "sg:orig_category":"Fisioterapia",
    "sg:phone":"+34 925 20 18 18",
    "sg:postcode":"45860",
    "sg:province":"Toledo",
    "wof:name":"Servicios Medicos Villaca\u00f1as S.l.",
    "wof:placetype":"venue"
},
  "geometry": {"coordinates":[-3.3477540016,39.6101455688],"type":"Point"}
}