{
  "type": "Feature",
  "properties": {
    "addr:full":"Calle de Maiatzaren Bata Kalea, 2 Leioa Vizcaya 48940",
    "addr:housenumber":"2",
    "addr:postcode":"48940",
    "addr:street":"Calle De Maiatzaren Bata Kalea",
    "iso:country":"ES",
    "sg:address":"Calle de Maiatzaren Bata Kalea, 2",
    "sg:city":"Leioa",
    "sg:orig_category":"Ludotecas",
    "sg:phone":"+34 946 55 95 45",
    "sg:postcode":"48940",
    "sg:province":"Vizcaya",
    "wof:name":"Ignacio Lopez- Marcos Novo, C.b.",
    "wof:placetype":"venue"
},
  "geometry": {"coordinates":[-3.0063159466,43.326499939],"type":"Point"}
}