{
  "type": "Feature",
  "properties": {
    "iso:country":"ES",
    "sg:address":"Av Doctor Vilaseca, 10",
    "sg:city":"Reus",
    "sg:orig_category":"Reposter\u00cdas",
    "sg:phone":"+34 977 31 54 52",
    "sg:postcode":"43202",
    "sg:province":"Tarragona",
    "wof:name":"Llaurado Forns Ricardo",
    "wof:placetype":"venue"
},
  "geometry": {"coordinates":[1.0996164083,41.1562919617],"type":"Point"}
}