{
  "type": "Feature",
  "properties": {
    "iso:country":"ES",
    "sg:address":"Calle de Pintor Zabaleta, 38",
    "sg:city":"Mancha Real",
    "sg:orig_category":"Animales (al Por Menor)",
    "sg:phone":"+34 953 35 09 26",
    "sg:postcode":"23100",
    "sg:province":"Ja\u00e9n",
    "wof:name":"J.sanchez Salido S.l.",
    "wof:placetype":"venue"
},
  "geometry": {"coordinates":[-3.6044709682,37.7867279053],"type":"Point"}
}