{
  "type": "Feature",
  "properties": {
    "iso:country":"ES",
    "sg:address":"Avda Trapiche, S/n",
    "sg:city":"Marbella",
    "sg:orig_category":"Promotores Constructores",
    "sg:phone":"+34 952 82 68 88",
    "sg:postcode":"29600",
    "sg:province":"M\u00e1laga",
    "sg:website":"www.promopinar.es",
    "wof:name":"Promopinar-vemusa U.t.e.",
    "wof:placetype":"venue"
},
  "geometry": {"coordinates":[-4.8885779381,36.5168647766],"type":"Point"}
}