{
  "type": "Feature",
  "properties": {
    "addr:full":"Alam Urquijo, 100 Bilbao Vizcaya 48013",
    "addr:housenumber":"100",
    "addr:postcode":"48013",
    "addr:street":"Alam Urquijo",
    "iso:country":"ES",
    "sg:address":"Alam Urquijo, 100",
    "sg:city":"Bilbao",
    "sg:orig_category":"Agentes, Concesionarios Y Sucursales De Veh\u00cdculos",
    "sg:phone":"+34 944 41 73 72",
    "sg:postcode":"48013",
    "sg:province":"Vizcaya",
    "wof:name":"Laum S.l.",
    "wof:placetype":"venue"
},
  "geometry": {"coordinates":[-2.9474151134,43.2626495361],"type":"Point"}
}