{
  "type": "Feature",
  "properties": {
    "iso:country":"ES",
    "sg:address":"Calle de San Andres, S/n",
    "sg:city":"Coru\u00d1a",
    "sg:orig_category":"Iglesia Cat\u00d3lica",
    "sg:phone":"+34 981 21 37 29",
    "sg:postcode":"15003",
    "sg:province":"La Coru\u00f1a",
    "wof:name":"Parroquia Castrense De San Andres",
    "wof:placetype":"venue"
},
  "geometry": {"coordinates":[-8.4061288834,43.3680267334],"type":"Point"}
}