{
  "type": "Feature",
  "properties": {
    "iso:country":"ES",
    "sg:address":"Carr Pi I Margall, 28",
    "sg:city":"Lleida",
    "sg:orig_category":"Inmobiliaria (agencias)",
    "sg:phone":"+34 973 72 80 60",
    "sg:postcode":"25004",
    "sg:province":"Lleida",
    "wof:name":"La Clau Lleida S.l.",
    "wof:placetype":"venue"
},
  "geometry": {"coordinates":[0.6279969811,41.621055603],"type":"Point"}
}