{
  "type": "Feature",
  "properties": {
    "iso:country":"ES",
    "sg:address":"Carrer de Mi\u00d1o, 11",
    "sg:city":"Barcelona",
    "sg:orig_category":"Fabricaci\u00d3n, Importaci\u00d3n De Material Y Sistemas De Telecomunicaciones",
    "sg:phone":"+34 932 11 70 15",
    "sg:postcode":"08022",
    "sg:province":"Barcelona",
    "sg:website":"soloparani\u00f1os.com",
    "wof:name":"Solo Para Ni\u00d1os S.l.",
    "wof:placetype":"venue"
},
  "geometry": {"coordinates":[2.1396849155,41.404384613],"type":"Point"}
}