{
  "type": "Feature",
  "properties": {
    "addr:full":"Calle de Venencia (la), S/n Chiclana De La Frontera C\u00e1diz 11130",
    "addr:postcode":"11130",
    "addr:street":"Calle De Venencia La S / N",
    "iso:country":"ES",
    "sg:address":"Calle de Venencia (la), S/n",
    "sg:city":"Chiclana De La Frontera",
    "sg:orig_category":"Arreglo, Reparaci\u00d3n, Piezas Sueltas De Televisi\u00d3n, V\u00cddeo, Hi",
    "sg:phone":"+34 956 40 27 07",
    "sg:postcode":"11130",
    "sg:province":"C\u00e1diz",
    "wof:name":"Virues Fornell Raul",
    "wof:placetype":"venue"
},
  "geometry": {"coordinates":[-6.146654129,36.423538208],"type":"Point"}
}