{
  "type": "Feature",
  "properties": {
    "addr:full":"Calle de Jaen, S/n Villanueva Cordoba C\u00f3rdoba 14440",
    "addr:housenumber":"s / n;cordoba co\u0301rdoba",
    "addr:postcode":"14440",
    "addr:street":"Calle De Jaen",
    "iso:country":"ES",
    "sg:address":"Calle de Jaen, S/n",
    "sg:city":"Villanueva Cordoba",
    "sg:orig_category":"Relojer\u00cda (al Por Menor, Reparaci\u00d3n)",
    "sg:phone":"+34 957 12 10 12",
    "sg:postcode":"14440",
    "sg:province":"C\u00f3rdoba",
    "wof:name":"Toril Cobos Daniel",
    "wof:placetype":"venue"
},
  "geometry": {"coordinates":[-4.6195039749,38.3229255676],"type":"Point"}
}