{
  "type": "Feature",
  "properties": {
    "addr:full":"Ctra General Del Norte, 318 Cantillo Santa Cruz De Tenerife 38350",
    "addr:housenumber":"318",
    "addr:postcode":"38350",
    "addr:street":"Ctra General Del Norte",
    "iso:country":"ES",
    "sg:address":"Ctra General Del Norte, 318",
    "sg:city":"Cantillo",
    "sg:orig_category":"Agentes, Concesionarios Y Sucursales De Veh\u00cdculos",
    "sg:phone":"+34 922 57 29 28",
    "sg:postcode":"38350",
    "sg:province":"Santa Cruz De Tenerife",
    "wof:name":"Autos Ramos 24 S.l.",
    "wof:placetype":"venue"
},
  "geometry": {"coordinates":[-16.394990921,28.4831752777],"type":"Point"}
}