{
  "type": "Feature",
  "properties": {
    "addr:full":"Plaz Cruz De Humilladero, 9 Malaga M\u00e1laga 29006",
    "addr:housenumber":"9",
    "addr:postcode":"29006",
    "addr:street":"Plaz Cruz De Humilladero;Ma\u0301Laga",
    "iso:country":"ES",
    "sg:address":"Plaz Cruz De Humilladero, 9",
    "sg:city":"Malaga",
    "sg:orig_category":"Cl\u00cdnicas M\u00c9dicas",
    "sg:phone":"+34 952 33 62 25",
    "sg:postcode":"29006",
    "sg:province":"M\u00e1laga",
    "wof:name":"Dura Cazorla David",
    "wof:placetype":"venue"
},
  "geometry": {"coordinates":[-4.4406571388,36.712223053],"type":"Point"}
}