{
  "type": "Feature",
  "properties": {
    "iso:country":"ES",
    "sg:address":"Diseminado, Km. 0021,0",
    "sg:city":"Saigots",
    "sg:orig_category":"Distribuci\u00d3n De Petr\u00d3leo Y Derivados",
    "sg:phone":"+34 948 30 40 40",
    "sg:postcode":"31639",
    "sg:province":"Navarra",
    "wof:name":"Hermanos Caballero S. L.",
    "wof:placetype":"venue"
},
  "geometry": {"coordinates":[-1.5467300415,42.9683952332],"type":"Point"}
}