{
  "type": "Feature",
  "properties": {
    "iso:country":"ES",
    "sg:address":"Calle de Alfonso Ix, 5",
    "sg:city":"Zamora",
    "sg:orig_category":"Ropa Para Se\u00d1oras Y Caballeros (al Por Menor)",
    "sg:phone":"+34 980 53 65 01",
    "sg:postcode":"49014",
    "sg:province":"Zamora",
    "wof:name":"Gavilanes Marcos Maria",
    "wof:placetype":"venue"
},
  "geometry": {"coordinates":[-5.7424120903,41.5075416565],"type":"Point"}
}