{
  "type": "Feature",
  "properties": {
    "addr:full":"Avda Reyes Catolicos, 46 Alcantarilla Murcia 30820",
    "addr:housenumber":"46",
    "addr:postcode":"30820",
    "addr:street":"Avda Reyes Catolicos",
    "iso:country":"ES",
    "sg:address":"Avda Reyes Catolicos, 46",
    "sg:city":"Alcantarilla",
    "sg:orig_category":"Cl\u00cdnicas Dentales",
    "sg:phone":"+34 968 89 40 89",
    "sg:postcode":"30820",
    "sg:province":"Murcia",
    "wof:name":"Diaz Arboleda Maria Beatriz",
    "wof:placetype":"venue"
},
  "geometry": {"coordinates":[-1.2202279568,37.9696044922],"type":"Point"}
}