{
  "type": "Feature",
  "properties": {
    "iso:country":"ES",
    "sg:address":"Calle de Projecte 31 - Poligono Industrial, 7",
    "sg:city":"Catarroja",
    "sg:orig_category":"Agencias Y Agentes Comerciales, Representantes",
    "sg:phone":"+34 961 22 01 10",
    "sg:postcode":"46470",
    "sg:province":"Valencia",
    "wof:name":"Tarazona Alonso Ramon",
    "wof:placetype":"venue"
},
  "geometry": {"coordinates":[-0.414440006,39.3972015381],"type":"Point"}
}