{
  "type": "Feature",
  "properties": {
    "iso:country":"ES",
    "sg:address":"Gonzalez Tablas, 2",
    "sg:city":"Iru\u00f1a",
    "sg:orig_category":"Zapater\u00cdas",
    "sg:phone":"+34 948 23 97 90",
    "sg:postcode":"31003",
    "sg:province":"Navarra",
    "wof:name":"Perez Pastor Milagros",
    "wof:placetype":"venue"
},
  "geometry": {"coordinates":[-1.6369459629,42.8095626831],"type":"Point"}
}