{
  "type": "Feature",
  "properties": {
    "addr:full":"Bda San Jose, 31 La Montiela C\u00f3rdoba 14549",
    "addr:postcode":"14549",
    "addr:street":"31 La Montiela Co\u0301Rdoba",
    "iso:country":"ES",
    "sg:address":"Bda San Jose, 31",
    "sg:city":"La Montiela",
    "sg:orig_category":"Frutas Y Legumbres Frescas (al Por Mayor)",
    "sg:phone":"+34 957 31 57 90",
    "sg:postcode":"14549",
    "sg:province":"C\u00f3rdoba",
    "wof:name":"Hortofruticola Ruri S.l.",
    "wof:placetype":"venue"
},
  "geometry": {"coordinates":[-4.9205827713,37.5231704712],"type":"Point"}
}