{
  "type": "Feature",
  "properties": {
    "addr:full":"Carrer de Arquitectura, 12 Hospitalet Llobregat Barcelona 08908",
    "addr:housenumber":"12",
    "addr:postcode":"08908",
    "addr:street":"Carrer De Arquitectura",
    "iso:country":"ES",
    "sg:address":"Carrer de Arquitectura, 12",
    "sg:city":"Hospitalet Llobregat",
    "sg:orig_category":"Oficinas: Suministros Para (fabricaci\u00d3n, Al Por Mayor)",
    "sg:phone":"+34 934 31 12 95",
    "sg:postcode":"08908",
    "sg:province":"Barcelona",
    "sg:website":"www.gispertonline.com",
    "wof:name":"Gestion Informatica Catalana S. A.",
    "wof:placetype":"venue"
},
  "geometry": {"coordinates":[2.13418293,41.3609886169],"type":"Point"}
}