{
  "type": "Feature",
  "properties": {
    "addr:full":"Calle de Mapuche, 2 Santa Cruz De Tenerife Santa Cruz De Tenerife 38010",
    "addr:housenumber":"2",
    "addr:postcode":"38010",
    "addr:street":"Calle De Mapuche",
    "iso:country":"ES",
    "sg:address":"Calle de Mapuche, 2",
    "sg:city":"Santa Cruz De Tenerife",
    "sg:orig_category":"Mec\u00c1nico Del Autom\u00d3vil",
    "sg:phone":"+34 922 64 47 55",
    "sg:postcode":"38010",
    "sg:province":"Santa Cruz De Tenerife",
    "wof:name":"Fernandez Alberto Jose Luis",
    "wof:placetype":"venue"
},
  "geometry": {"coordinates":[-16.2806186676,28.4530200958],"type":"Point"}
}