{
  "type": "Feature",
  "properties": {
    "addr:full":"Calle de San Pedro, 7 Espinardo Murcia 30004",
    "addr:housenumber":"7",
    "addr:postcode":"30004",
    "addr:street":"Calle De San Pedro",
    "iso:country":"ES",
    "sg:address":"Calle de San Pedro, 7",
    "sg:city":"Espinardo",
    "sg:orig_category":"Fabricaci\u00d3n, Venta De Cuadros, Accesorios Para Enmarcar",
    "sg:phone":"+34 968 21 21 84",
    "sg:postcode":"30004",
    "sg:province":"Murcia",
    "wof:name":"Cristaleria Lopez S.l.",
    "wof:placetype":"venue"
},
  "geometry": {"coordinates":[-1.1335639954,37.9843559265],"type":"Point"}
}