{
  "type": "Feature",
  "properties": {
    "iso:country":"ES",
    "sg:address":"Urb. San Miguel, S/n",
    "sg:city":"A Carida",
    "sg:orig_category":"Laboratorios Y Trabajos De Fotograf\u00cda, V\u00cddeo Y Cine",
    "sg:phone":"+34 985 63 70 71",
    "sg:postcode":"33750",
    "sg:province":"Asturias",
    "wof:name":"Fernandez Mendez Elia",
    "wof:placetype":"venue"
},
  "geometry": {"coordinates":[-6.8270339966,43.5506744385],"type":"Point"}
}