{
  "type": "Feature",
  "properties": {
    "addr:full":"Oialume Bidea, 14 Astigarraga Guip\u00f9zcoa 20115",
    "addr:housenumber":"14",
    "addr:postcode":"20115",
    "addr:street":"Oialume Bidea;Guipu\u0300Zcoa",
    "iso:country":"ES",
    "sg:address":"Oialume Bidea, 14",
    "sg:city":"Astigarraga",
    "sg:orig_category":"Mec\u00c1nico Del Autom\u00d3vil",
    "sg:phone":"+34 943 55 74 69",
    "sg:postcode":"20115",
    "sg:province":"Guip\u00f9zcoa",
    "wof:name":"Gutierrez Gutierrez Unai",
    "wof:placetype":"venue"
},
  "geometry": {"coordinates":[-1.9537400007,43.2747879028],"type":"Point"}
}