{
  "type": "Feature",
  "properties": {
    "addr:full":"Carrer de Flors, 29 Vandellos Tarragona 43891",
    "addr:housenumber":"29",
    "addr:postcode":"43891",
    "addr:street":"Carrer De Flors",
    "iso:country":"ES",
    "sg:address":"Carrer de Flors, 29",
    "sg:city":"Vandellos",
    "sg:orig_category":"Frutas Y Legumbres Secas (al Por Mayor)",
    "sg:phone":"+34 977 82 40 22",
    "sg:postcode":"43891",
    "sg:province":"Tarragona",
    "wof:name":"Nomen Domenech Luis",
    "wof:placetype":"venue"
},
  "geometry": {"coordinates":[0.8324329853,41.0193901062],"type":"Point"}
}