{
  "type": "Feature",
  "properties": {
    "iso:country":"ES",
    "sg:address":"A Castellana, 16",
    "sg:city":"Castellana",
    "sg:orig_category":"Caf\u00c9s, Bares, Cervecer\u00cdas",
    "sg:phone":"+34 988 23 72 81",
    "sg:postcode":"32901",
    "sg:province":"Ourense",
    "wof:name":"Ferreira Iglesias Antonio",
    "wof:placetype":"venue"
},
  "geometry": {"coordinates":[-7.8159580231,42.2799491882],"type":"Point"}
}