{
  "type": "Feature",
  "properties": {
    "addr:full":"Carr Plateria, 7 Lleida Lleida 25002",
    "addr:housenumber":"7",
    "addr:postcode":"25002",
    "addr:street":"Carr Plateria",
    "iso:country":"ES",
    "sg:address":"Carr Plateria, 7",
    "sg:city":"Lleida",
    "sg:orig_category":"Discapacitados",
    "sg:phone":"+34 973 23 87 71",
    "sg:postcode":"25002",
    "sg:province":"Lleida",
    "wof:name":"Fundacio Catalana Tutelar De Disminuits Psiquics",
    "wof:placetype":"venue"
},
  "geometry": {"coordinates":[0.6219750047,41.6121864319],"type":"Point"}
}