{
  "type": "Feature",
  "properties": {
    "iso:country":"ES",
    "sg:address":"Calle de Fernando Alvarez, S/n",
    "sg:city":"Medina Pomar",
    "sg:orig_category":"Asociaciones, Organismos Culturales Y Socioeducativos",
    "sg:phone":"+34 947 14 70 42",
    "sg:postcode":"09500",
    "sg:province":"Burgos",
    "wof:name":"Patronato Del Museo De Las Merindades",
    "wof:placetype":"venue"
},
  "geometry": {"coordinates":[-3.4866139889,42.9322853088],"type":"Point"}
}