{
  "type": "Feature",
  "properties": {
    "addr:full":"Calle de Pelayo, 3 Vila Joiosa Alicante 03570",
    "addr:housenumber":"3",
    "addr:postcode":"03570",
    "addr:street":"Calle De Pelayo",
    "iso:country":"ES",
    "sg:address":"Calle de Pelayo, 3",
    "sg:city":"Vila Joiosa",
    "sg:orig_category":"Orquestas De Variedades",
    "sg:phone":"+34 966 85 35 62",
    "sg:postcode":"03570",
    "sg:province":"Alicante",
    "wof:name":"Ateneo Musical S.cv.",
    "wof:placetype":"venue"
},
  "geometry": {"coordinates":[-0.2342334986,38.5038566589],"type":"Point"}
}