{
  "type": "Feature",
  "properties": {
    "addr:full":"Carrer de Besalu, 55 Barcelona Barcelona 08026",
    "addr:housenumber":"55",
    "addr:postcode":"08026",
    "addr:street":"Carrer De Besalu",
    "iso:country":"ES",
    "sg:address":"Carrer de Besalu, 55",
    "sg:city":"Barcelona",
    "sg:orig_category":"Reposter\u00cdas",
    "sg:phone":"+34 934 55 64 72",
    "sg:postcode":"08026",
    "sg:province":"Barcelona",
    "wof:name":"Plana Roca Jaime",
    "wof:placetype":"venue"
},
  "geometry": {"coordinates":[2.1840000153,41.4142723083],"type":"Point"}
}