{
  "type": "Feature",
  "properties": {
    "iso:country":"ES",
    "sg:address":"Calle de Zurbaran, 14",
    "sg:city":"Badajoz",
    "sg:orig_category":"Agentes, Concesionarios Y Sucursales De Veh\u00cdculos",
    "sg:phone":"+34 924 24 94 71",
    "sg:postcode":"06002",
    "sg:province":"Badajoz",
    "wof:name":"Motor Zurbaran S.a.",
    "wof:placetype":"venue"
},
  "geometry": {"coordinates":[-6.9704518318,38.877204895],"type":"Point"}
}