{
  "type": "Feature",
  "properties": {
    "addr:full":"Avda Mediterraneo, 83 Teulada Alicante 03725",
    "addr:housenumber":"83",
    "addr:postcode":"03725",
    "addr:street":"Avda Mediterraneo",
    "iso:country":"ES",
    "sg:address":"Avda Mediterraneo, 83",
    "sg:city":"Teulada",
    "sg:orig_category":"Empresas De Carpinter\u00cda Met\u00c1lica",
    "sg:phone":"+34 965 74 09 24",
    "sg:postcode":"03725",
    "sg:province":"Alicante",
    "wof:name":"Jesus Camacho S.l.",
    "wof:placetype":"venue"
},
  "geometry": {"coordinates":[0.1018790007,38.7275276184],"type":"Point"}
}