{
  "type": "Feature",
  "properties": {
    "addr:full":"Cja Toros, 8 Estella Navarra 31200",
    "addr:housenumber":"8",
    "addr:postcode":"31200",
    "addr:street":"Toros",
    "iso:country":"ES",
    "sg:address":"Cja Toros, 8",
    "sg:city":"Estella",
    "sg:orig_category":"Mec\u00c1nico Del Autom\u00d3vil",
    "sg:phone":"+34 948 55 04 56",
    "sg:postcode":"31200",
    "sg:province":"Navarra",
    "wof:name":"Ott Eigl Fernando",
    "wof:placetype":"venue"
},
  "geometry": {"coordinates":[-2.0353488922,42.6726417542],"type":"Point"}
}