{
  "type": "Feature",
  "properties": {
    "iso:country":"ES",
    "sg:address":"Calle de Mariana Pineda, 6",
    "sg:city":"Oca\u00f1a",
    "sg:orig_category":"Promotores Constructores",
    "sg:phone":"+34 925 13 15 76",
    "sg:postcode":"45300",
    "sg:province":"Toledo",
    "wof:name":"Servicios Forestales Agroca\u00f1a Sl",
    "wof:placetype":"venue"
},
  "geometry": {"coordinates":[-3.4973599911,39.9558448792],"type":"Point"}
}