{
  "type": "Feature",
  "properties": {
    "addr:full":"Calle de Quijote, 11 Alcazar S. Juan Ciudad Real 13600",
    "addr:housenumber":"11",
    "addr:postcode":"13600",
    "addr:street":"Calle De Quijote;Alcazar S. Juan Ciudad Real",
    "iso:country":"ES",
    "sg:address":"Calle de Quijote, 11",
    "sg:city":"Alcazar S. Juan",
    "sg:orig_category":"Peluqueros: De Se\u00d1oras",
    "sg:phone":"+34 926 54 05 92",
    "sg:postcode":"13600",
    "sg:province":"Ciudad Real",
    "wof:name":"Vela Abengozar Rosa Maria",
    "wof:placetype":"venue"
},
  "geometry": {"coordinates":[-3.213496685,39.3878135681],"type":"Point"}
}