{
  "type": "Feature",
  "properties": {
    "iso:country":"ES",
    "sg:address":"Calle de Oca, 85",
    "sg:city":"Madrid",
    "sg:orig_category":"Tintes (fabricaci\u00d3n, Al Por Mayor)",
    "sg:phone":"+34 914 62 00 84",
    "sg:postcode":"28025",
    "sg:province":"Madrid",
    "wof:name":"Heranz Gil Julian",
    "wof:placetype":"venue"
},
  "geometry": {"coordinates":[-3.7422969341,40.3882522583],"type":"Point"}
}