{
  "type": "Feature",
  "properties": {
    "addr:full":"Calle de Puente, 23 Pe\u00e7arroya-pueblonuevo C\u00f3rdoba 14200",
    "addr:housenumber":"23",
    "addr:postcode":"14200",
    "addr:street":"Calle De Puente;Co\u0301Rdoba",
    "iso:country":"ES",
    "sg:address":"Calle de Puente, 23",
    "sg:city":"Pe\u00e7arroya-pueblonuevo",
    "sg:orig_category":"Mec\u00c1nico Del Autom\u00d3vil",
    "sg:phone":"+34 957 57 11 12",
    "sg:postcode":"14200",
    "sg:province":"C\u00f3rdoba",
    "wof:name":"Sanchez Mediavilla Antonio",
    "wof:placetype":"venue"
},
  "geometry": {"coordinates":[-5.2619948387,38.2979774475],"type":"Point"}
}