{
  "type": "Feature",
  "properties": {
    "iso:country":"ES",
    "sg:address":"Calle de Francisco Carter, 4",
    "sg:city":"Malaga",
    "sg:orig_category":"Internados & Ense\u00d1anza Privada",
    "sg:phone":"+34 952 10 25 86",
    "sg:postcode":"29011",
    "sg:province":"M\u00e1laga",
    "wof:name":"Instituto De Misioneras Cruzadas De La Iglesia",
    "wof:placetype":"venue"
},
  "geometry": {"coordinates":[-4.4270272255,36.7419242859],"type":"Point"}
}