{
  "type": "Feature",
  "properties": {
    "iso:country":"ES",
    "sg:address":"Calle de Eduardo Dominguez Avila, 12",
    "sg:city":"Malaga",
    "sg:orig_category":"Ludotecas",
    "sg:phone":"+34 952 25 55 08",
    "sg:postcode":"29014",
    "sg:province":"M\u00e1laga",
    "wof:name":"Infoarce S.l.",
    "wof:placetype":"venue"
},
  "geometry": {"coordinates":[-4.4212789536,36.7301635742],"type":"Point"}
}