{
  "type": "Feature",
  "properties": {
    "addr:full":"Carrer de Rossello, 85 Barcelona Barcelona 08029",
    "addr:housenumber":"85",
    "addr:postcode":"08029",
    "addr:street":"Carrer De Rossello",
    "iso:country":"ES",
    "sg:address":"Carrer de Rossello, 85",
    "sg:city":"Barcelona",
    "sg:orig_category":"Empresas De Limpieza",
    "sg:phone":"+34 933 22 49 59",
    "sg:postcode":"08029",
    "sg:province":"Barcelona",
    "wof:name":"Euval S.l.",
    "wof:placetype":"venue"
},
  "geometry": {"coordinates":[2.1473710537,41.3859901428],"type":"Point"}
}