{
  "type": "Feature",
  "properties": {
    "addr:full":"Avda Eysines De, 14 Piedras Blancas Asturias 33450",
    "addr:housenumber":"14",
    "addr:postcode":"33450",
    "addr:street":"Avda Eysines De",
    "iso:country":"ES",
    "sg:address":"Avda Eysines De, 14",
    "sg:city":"Piedras Blancas",
    "sg:orig_category":"Peluquer\u00cdas, Peluquer\u00cda Mixta",
    "sg:phone":"+34 985 50 73 82",
    "sg:postcode":"33450",
    "sg:province":"Asturias",
    "wof:name":"Macavi Teylu S.l.",
    "wof:placetype":"venue"
},
  "geometry": {"coordinates":[-5.9752020836,43.5594367981],"type":"Point"}
}