{
  "type": "Feature",
  "properties": {
    "addr:full":"Calle de Cerro Del Casta\u00d1ar, 104 Madrid Madrid 28034",
    "addr:housenumber":"104",
    "addr:postcode":"28034",
    "addr:street":"Calle De Cerro Del Castan\u0303Ar",
    "iso:country":"ES",
    "sg:address":"Calle de Cerro Del Casta\u00d1ar, 104",
    "sg:city":"Madrid",
    "sg:orig_category":"Inmobiliaria (agencias)",
    "sg:phone":"+34 917 34 79 41",
    "sg:postcode":"28034",
    "sg:province":"Madrid",
    "wof:name":"Brabyn Hombravella Felipe",
    "wof:placetype":"venue"
},
  "geometry": {"coordinates":[-3.711824894,40.4899024963],"type":"Point"}
}