{
  "type": "Feature",
  "properties": {
    "iso:country":"ES",
    "sg:address":"Carrer de Gaspar Fabregas, 30",
    "sg:city":"Esplugues Llobregat",
    "sg:orig_category":"Molduras, Junquillos, Listones Y Molduras Perforadas",
    "sg:phone":"+34 933 71 56 74",
    "sg:postcode":"08950",
    "sg:province":"Barcelona",
    "wof:name":"Rodriguez Fernandez Secundino",
    "wof:placetype":"venue"
},
  "geometry": {"coordinates":[2.0811929703,41.3751487732],"type":"Point"}
}