{
  "type": "Feature",
  "properties": {
    "addr:full":"Carrer de Sevilla, 15 Masnou Barcelona 08320",
    "addr:housenumber":"15",
    "addr:postcode":"08320",
    "addr:street":"Carrer De Sevilla",
    "iso:country":"ES",
    "sg:address":"Carrer de Sevilla, 15",
    "sg:city":"Masnou",
    "sg:orig_category":"Mec\u00c1nico Del Autom\u00d3vil",
    "sg:phone":"+34 935 55 97 84",
    "sg:postcode":"08320",
    "sg:province":"Barcelona",
    "wof:name":"Garcia Alonso Francisco",
    "wof:placetype":"venue"
},
  "geometry": {"coordinates":[2.3095240593,41.4865455627],"type":"Point"}
}