{
  "type": "Feature",
  "properties": {
    "iso:country":"ES",
    "sg:address":"Carrer de Bori I Fontesta, 7",
    "sg:city":"Barcelona",
    "sg:orig_category":"Zapatos (al Por Menor)",
    "sg:phone":"+34 934 14 58 18",
    "sg:postcode":"08021",
    "sg:province":"Barcelona",
    "wof:name":"Ermisch Soria Carlos",
    "wof:placetype":"venue"
},
  "geometry": {"coordinates":[2.1410050392,41.3935394287],"type":"Point"}
}