{
  "type": "Feature",
  "properties": {
    "addr:full":"Carrer de Navarra, 176 Masnou Barcelona 08320",
    "addr:housenumber":"176",
    "addr:postcode":"08320",
    "addr:street":"Carrer De Navarra",
    "iso:country":"ES",
    "sg:address":"Carrer de Navarra, 176",
    "sg:city":"Masnou",
    "sg:orig_category":"Asilos De Ancianos. Centros Privados",
    "sg:phone":"+34 935 40 09 71",
    "sg:postcode":"08320",
    "sg:province":"Barcelona",
    "wof:name":"Residencia Els Ametllers",
    "wof:placetype":"venue"
},
  "geometry": {"coordinates":[2.3098669052,41.4793052673],"type":"Point"}
}