{
  "type": "Feature",
  "properties": {
    "iso:country":"ES",
    "sg:address":"Calle de Ochavo, 5",
    "sg:city":"Frumales",
    "sg:orig_category":"Carnicer\u00cdas, Carnicer\u00cdas",
    "sg:phone":"+34 921 16 42 15",
    "sg:postcode":"40298",
    "sg:province":"Segovia",
    "wof:name":"Pozo Mu\u00f1oz Luis Del",
    "wof:placetype":"venue"
},
  "geometry": {"coordinates":[-4.1859221458,41.3840522766],"type":"Point"}
}