{
  "type": "Feature",
  "properties": {
    "iso:country":"ES",
    "sg:address":"Calle de Nueva, 12",
    "sg:city":"Puerto",
    "sg:orig_category":"Negocio De Materiales De Construcci\u00d3n",
    "sg:phone":"+34 962 67 14 36",
    "sg:postcode":"46520",
    "sg:province":"Valencia",
    "wof:name":"Anisavi Sl",
    "wof:placetype":"venue"
},
  "geometry": {"coordinates":[-0.2188923061,39.6630821228],"type":"Point"}
}