{
  "type": "Feature",
  "properties": {
    "iso:country":"ES",
    "sg:address":"Trasar De Carballo, 6",
    "sg:city":"Cartelos",
    "sg:orig_category":"Producci\u00d3n, Venta De Productos De Agricultura Biol\u00d3gica",
    "sg:phone":"+34 982 46 62 35",
    "sg:postcode":"27527",
    "sg:province":"Lugo",
    "wof:name":"Gonzalez Fernandez Luis",
    "wof:placetype":"venue"
},
  "geometry": {"coordinates":[-7.8438329697,42.5592575073],"type":"Point"}
}