{
  "type": "Feature",
  "properties": {
    "iso:country":"ES",
    "sg:address":"C/ Ciutat De Gibraltar, 8",
    "sg:city":"Paterna",
    "sg:orig_category":"Construcciones Met\u00c1licas",
    "sg:phone":"+34 961 34 15 88",
    "sg:postcode":"46988",
    "sg:province":"Valencia",
    "wof:name":"Metalicas Zetra S.a.l.",
    "wof:placetype":"venue"
},
  "geometry": {"coordinates":[-0.4724059999,39.5111808777],"type":"Point"}
}