{
  "type": "Feature",
  "properties": {
    "addr:full":"Plaz Constitucion, 3 Cantoria Almer\u00eda 04850",
    "addr:housenumber":"3",
    "addr:postcode":"04850",
    "addr:street":"Constitucion;Almeri\u0301A",
    "iso:country":"ES",
    "sg:address":"Plaz Constitucion, 3",
    "sg:city":"Cantoria",
    "sg:orig_category":"Administraciones Regionales, Departamentales Y Locales",
    "sg:phone":"+34 950 43 60 00",
    "sg:postcode":"04850",
    "sg:province":"Almer\u00eda",
    "wof:name":"Ayuntamiento De Cantoria",
    "wof:placetype":"venue"
},
  "geometry": {"coordinates":[-2.2039933205,37.3409042358],"type":"Point"}
}