{
  "type": "Feature",
  "properties": {
    "addr:full":"Ctra Madrid (de), S/n Molina Guadalajara 19300",
    "addr:postcode":"19300",
    "addr:street":"Ctra Madrid De S / N Molina",
    "iso:country":"ES",
    "sg:address":"Ctra Madrid (de), S/n",
    "sg:city":"Molina",
    "sg:orig_category":"Sierras (fabricaci\u00d3n, Al Por Mayor)",
    "sg:phone":"+34 949 83 20 75",
    "sg:postcode":"19300",
    "sg:province":"Guadalajara",
    "wof:name":"Blasco Hurtado Juan Francisco",
    "wof:placetype":"venue"
},
  "geometry": {"coordinates":[-1.8790500164,40.8489608765],"type":"Point"}
}