{
  "type": "Feature",
  "properties": {
    "addr:full":"Rua Uruguay, 2 Vigo Pontevedra 36201",
    "addr:housenumber":"2",
    "addr:postcode":"36201",
    "addr:street":"Rua Uruguay",
    "iso:country":"ES",
    "sg:address":"Rua Uruguay, 2",
    "sg:city":"Vigo",
    "sg:orig_category":"Inmobiliaria (agencias)",
    "sg:phone":"+34 986 22 62 17",
    "sg:postcode":"36201",
    "sg:province":"Pontevedra",
    "wof:name":"Picovi 2003 S.l.",
    "wof:placetype":"venue"
},
  "geometry": {"coordinates":[-8.7196521759,42.2364730835],"type":"Point"}
}