{
  "type": "Feature",
  "properties": {
    "iso:country":"ES",
    "sg:address":"Atvia De Logro\u00f1o, Km. 0001,0",
    "sg:city":"Zaragoza",
    "sg:orig_category":"Agentes, Concesionarios Y Sucursales De Camiones Y Veh\u00cdculos Industriales",
    "sg:phone":"+34 976 53 25 46",
    "sg:postcode":"50011",
    "sg:province":"Zaragoza",
    "wof:name":"Matilla Val Jose Daniel",
    "wof:placetype":"venue"
},
  "geometry": {"coordinates":[-0.9913589954,41.662853241],"type":"Point"}
}