{
  "type": "Feature",
  "properties": {
    "iso:country":"ES",
    "sg:address":"Calle de Guardia Civil (de La), 11",
    "sg:city":"Cervera Pisuerga",
    "sg:orig_category":"Ingenier\u00cda, Centros De Estudios (diversos)",
    "sg:phone":"+34 979 87 06 65",
    "sg:postcode":"34840",
    "sg:province":"Palencia",
    "wof:name":"Niebla Battistella Oiane",
    "wof:placetype":"venue"
},
  "geometry": {"coordinates":[-4.5311746597,42.0124588013],"type":"Point"}
}