{
  "type": "Feature",
  "properties": {
    "addr:full":"Av Generalitat, 70 Santa Coloma De Gramenet Barcelona 08922",
    "addr:housenumber":"70",
    "addr:postcode":"08922",
    "addr:street":"Av Generalitat",
    "iso:country":"ES",
    "sg:address":"Av Generalitat, 70",
    "sg:city":"Santa Coloma De Gramenet",
    "sg:orig_category":"M\u00c9dicos: Ginecolog\u00cda Y Obstetricia",
    "sg:phone":"+34 933 85 25 54",
    "sg:postcode":"08922",
    "sg:province":"Barcelona",
    "wof:name":"Carreras Collado Ramon",
    "wof:placetype":"venue"
},
  "geometry": {"coordinates":[2.21043396,41.4475975037],"type":"Point"}
}