{
  "type": "Feature",
  "properties": {
    "addr:full":"Calle de Vilamarxant, 74 Benaguasil Valencia 46180",
    "addr:housenumber":"74",
    "addr:postcode":"46180",
    "addr:street":"Calle De Vilamarxant",
    "iso:country":"ES",
    "sg:address":"Calle de Vilamarxant, 74",
    "sg:city":"Benaguasil",
    "sg:orig_category":"Arboricultura Y Producci\u00d3n De Frutas",
    "sg:phone":"+34 962 73 71 55",
    "sg:postcode":"46180",
    "sg:province":"Valencia",
    "wof:name":"Stefan Fruit S.l.",
    "wof:placetype":"venue"
},
  "geometry": {"coordinates":[-0.587731719,39.5907249451],"type":"Point"}
}