{
  "type": "Feature",
  "properties": {
    "iso:country":"ES",
    "sg:address":"Calle de Cabo Negrete, 2",
    "sg:city":"Santiago Ribera",
    "sg:orig_category":"Armaduras De Hormig\u00d3n",
    "sg:phone":"+34 968 57 20 91",
    "sg:postcode":"30720",
    "sg:province":"Murcia",
    "wof:name":"Estructuras Copa S.l.",
    "wof:placetype":"venue"
},
  "geometry": {"coordinates":[-0.81417799,37.7976951599],"type":"Point"}
}