{
  "type": "Feature",
  "properties": {
    "addr:full":"Calle de Monasterio De Poblet, 1 Zaragoza Zaragoza 50013",
    "addr:housenumber":"1",
    "addr:postcode":"50013",
    "addr:street":"Calle De Monasterio De Poblet",
    "iso:country":"ES",
    "sg:address":"Calle de Monasterio De Poblet, 1",
    "sg:city":"Zaragoza",
    "sg:orig_category":"Montaje (empresas De)",
    "sg:phone":"+34 976 59 11 59",
    "sg:postcode":"50013",
    "sg:province":"Zaragoza",
    "wof:name":"Montajes Electricos Arranz S.l",
    "wof:placetype":"venue"
},
  "geometry": {"coordinates":[-0.8710479736,41.6441116333],"type":"Point"}
}