{
  "type": "Feature",
  "properties": {
    "addr:full":"Avda Minero, 2 Ortuella Vizcaya 48530",
    "addr:housenumber":"2",
    "addr:postcode":"48530",
    "addr:street":"Avda Minero",
    "iso:country":"ES",
    "sg:address":"Avda Minero, 2",
    "sg:city":"Ortuella",
    "sg:orig_category":"Farmacias",
    "sg:phone":"+34 946 64 03 27",
    "sg:postcode":"48530",
    "sg:province":"Vizcaya",
    "wof:name":"Lopez-linares Ramo Jesus",
    "wof:placetype":"venue"
},
  "geometry": {"coordinates":[-3.0522739887,43.3086585999],"type":"Point"}
}