{
  "type": "Feature",
  "properties": {
    "iso:country":"ES",
    "sg:address":"Calle de General Ricardos, 250",
    "sg:city":"Madrid",
    "sg:orig_category":"Deportes Y Programas De Aventura",
    "sg:phone":"+34 913 60 20 78",
    "sg:postcode":"28025",
    "sg:province":"Madrid",
    "wof:name":"Rainbow Express S.l.",
    "wof:placetype":"venue"
},
  "geometry": {"coordinates":[-3.7413640022,40.3832550049],"type":"Point"}
}