{
  "type": "Feature",
  "properties": {
    "addr:full":"Calle de Bizkai, 5 Galdakao Vizcaya 48960",
    "addr:housenumber":"5",
    "addr:postcode":"48960",
    "addr:street":"Calle De Bizkai",
    "iso:country":"ES",
    "sg:address":"Calle de Bizkai, 5",
    "sg:city":"Galdakao",
    "sg:orig_category":"M\u00c9dicos: Fisioterapia Y Rehabilitaci\u00d3n",
    "sg:phone":"+34 944 57 32 68",
    "sg:postcode":"48960",
    "sg:province":"Vizcaya",
    "wof:name":"Clinica Bizkai, S.l",
    "wof:placetype":"venue"
},
  "geometry": {"coordinates":[-2.842744112,43.2340812683],"type":"Point"}
}