{
  "type": "Feature",
  "properties": {
    "addr:full":"Carrer de Professor Castello, S/n Arenys Mar Barcelona 08350",
    "addr:housenumber":"s / n",
    "addr:postcode":"08350",
    "addr:street":"Carrer De Professor Castello",
    "iso:country":"ES",
    "sg:address":"Carrer de Professor Castello, S/n",
    "sg:city":"Arenys Mar",
    "sg:orig_category":"Formaci\u00d3n Continuada (variada)",
    "sg:phone":"+34 937 95 83 20",
    "sg:postcode":"08350",
    "sg:province":"Barcelona",
    "wof:name":"Laboritas S.l.",
    "wof:placetype":"venue"
},
  "geometry": {"coordinates":[2.549284935,41.5831947327],"type":"Point"}
}