{
  "type": "Feature",
  "properties": {
    "addr:full":"Calle de Padre Ferris, 34 Valencia Valencia 46009",
    "addr:housenumber":"34",
    "addr:postcode":"46009",
    "addr:street":"Calle De Padre Ferris",
    "iso:country":"ES",
    "sg:address":"Calle de Padre Ferris, 34",
    "sg:city":"Valencia",
    "sg:orig_category":"M\u00c1quinas De Coser Y De Hacer Punto (al Por Mayor)",
    "sg:phone":"+34 963 49 68 22",
    "sg:postcode":"46009",
    "sg:province":"Valencia",
    "wof:name":"Enrique Andreu S.l.",
    "wof:placetype":"venue"
},
  "geometry": {"coordinates":[-0.3863129914,39.4853973389],"type":"Point"}
}