{
  "type": "Feature",
  "properties": {
    "addr:full":"Calle de Hospital, 6 Aguilas Murcia 30880",
    "addr:housenumber":"6",
    "addr:postcode":"30880",
    "addr:street":"Calle De Hospital",
    "iso:country":"ES",
    "sg:address":"Calle de Hospital, 6",
    "sg:city":"Aguilas",
    "sg:orig_category":"Negocio De Materiales De Construcci\u00d3n",
    "sg:phone":"+34 968 41 31 07",
    "sg:postcode":"30880",
    "sg:province":"Murcia",
    "wof:name":"Visanfer S. A.",
    "wof:placetype":"venue"
},
  "geometry": {"coordinates":[-1.5833193064,37.4113616943],"type":"Point"}
}