{
  "type": "Feature",
  "properties": {
    "addr:full":"Calle de Valle De La Ballestera, 42 Valencia Valencia 46015",
    "addr:housenumber":"42",
    "addr:postcode":"46015",
    "addr:street":"Calle De Valle De La Ballestera",
    "iso:country":"ES",
    "sg:address":"Calle de Valle De La Ballestera, 42",
    "sg:city":"Valencia",
    "sg:orig_category":"Agencias Y Agentes Comerciales, Representantes",
    "sg:phone":"+34 963 40 11 59",
    "sg:postcode":"46015",
    "sg:province":"Valencia",
    "wof:name":"Cozzo Schillizzi Giuseppe",
    "wof:placetype":"venue"
},
  "geometry": {"coordinates":[-0.3998549879,39.4785995483],"type":"Point"}
}