{
  "type": "Feature",
  "properties": {
    "iso:country":"ES",
    "sg:address":"Carrer de Vilapicina, 75",
    "sg:city":"Barcelona",
    "sg:orig_category":"Extinci\u00d3n De Incendios: Material Y Suministros (fabricaci\u00d3n, Al Por Mayor)",
    "sg:phone":"+34 933 57 19 79",
    "sg:postcode":"08031",
    "sg:province":"Barcelona",
    "wof:name":"Pou Rivero Juan Maria",
    "wof:placetype":"venue"
},
  "geometry": {"coordinates":[2.1690781116,41.4294013977],"type":"Point"}
}