{
  "type": "Feature",
  "properties": {
    "iso:country":"ES",
    "sg:address":"Av Josep Tarradellas, 15",
    "sg:city":"Terrassa",
    "sg:orig_category":"Promotores Constructores",
    "sg:phone":"+34 937 88 31 58",
    "sg:postcode":"08225",
    "sg:province":"Barcelona",
    "wof:name":"Cazorla Artigas Jose",
    "wof:placetype":"venue"
},
  "geometry": {"coordinates":[2.0036180019,41.5702705383],"type":"Point"}
}