{
  "type": "Feature",
  "properties": {
    "iso:country":"ES",
    "sg:address":"Calle de Dr Fleming (del), 31",
    "sg:city":"Coslada",
    "sg:orig_category":"Pod\u00d3logos: Pedicuros",
    "sg:phone":"+34 916 69 18 80",
    "sg:postcode":"28820",
    "sg:province":"Madrid",
    "wof:name":"Mendez Prieto Isaac",
    "wof:placetype":"venue"
},
  "geometry": {"coordinates":[-3.5654902458,40.423828125],"type":"Point"}
}