{
  "type": "Feature",
  "properties": {
    "addr:full":"Avda Cid, 104 Valencia Valencia 46018",
    "addr:housenumber":"104",
    "addr:postcode":"46018",
    "addr:street":"Avda Cid",
    "iso:country":"ES",
    "sg:address":"Avda Cid, 104",
    "sg:city":"Valencia",
    "sg:orig_category":"Marketing Directo",
    "sg:phone":"+34 963 70 75 50",
    "sg:postcode":"46018",
    "sg:province":"Valencia",
    "wof:name":"Optimizacion",
    "wof:placetype":"venue"
},
  "geometry": {"coordinates":[-0.4008400142,39.4691886902],"type":"Point"}
}