{
  "type": "Feature",
  "properties": {
    "addr:full":"Carr Doctor Callis, 3 Cadaques Girona 17488",
    "addr:housenumber":"3",
    "addr:postcode":"17488",
    "addr:street":"Carr Doctor Callis",
    "iso:country":"ES",
    "sg:address":"Carr Doctor Callis, 3",
    "sg:city":"Cadaques",
    "sg:orig_category":"Restaurantes",
    "sg:phone":"+34 972 15 94 80",
    "sg:postcode":"17488",
    "sg:province":"Girona",
    "wof:name":"Hachani  Nordine",
    "wof:placetype":"venue"
},
  "geometry": {"coordinates":[3.276829958,42.288394928],"type":"Point"}
}