{
  "type": "Feature",
  "properties": {
    "iso:country":"ES",
    "sg:address":"Finca Verdelpino, S/n",
    "sg:city":"Cuenca",
    "sg:orig_category":"Agricultura: Abastecimiento Y Cosechado (negocio)",
    "sg:phone":"+34 969 22 76 75",
    "sg:postcode":"16004",
    "sg:province":"Cuenca",
    "wof:name":"Luz Lamarca Maria Del Coral De",
    "wof:placetype":"venue"
},
  "geometry": {"coordinates":[-2.1362390518,40.0720710754],"type":"Point"}
}