{
  "type": "Feature",
  "properties": {
    "addr:full":"Av Constitucio, 138 Castelldefels Barcelona 08860",
    "addr:housenumber":"138",
    "addr:postcode":"08860",
    "addr:street":"Av Constitucio",
    "iso:country":"ES",
    "sg:address":"Av Constitucio, 138",
    "sg:city":"Castelldefels",
    "sg:orig_category":"Farmacias",
    "sg:phone":"+34 936 65 12 44",
    "sg:postcode":"08860",
    "sg:province":"Barcelona",
    "wof:name":"Sentelles Monill Anna",
    "wof:placetype":"venue"
},
  "geometry": {"coordinates":[1.9783070087,41.2793502808],"type":"Point"}
}