{
  "type": "Feature",
  "properties": {
    "addr:full":"Garbi(urb Montecasino), 19 La Nucia Alicante 03530",
    "addr:housenumber":"19",
    "addr:postcode":"03530",
    "addr:street":"Urb Montecasino",
    "iso:country":"ES",
    "sg:address":"Garbi(urb Montecasino), 19",
    "sg:city":"La Nucia",
    "sg:orig_category":"Sales (al Por Mayor)",
    "sg:phone":"+34 966 87 58 93",
    "sg:postcode":"03530",
    "sg:province":"Alicante",
    "wof:name":"Ruiz Mu\u00f1oz Antonio",
    "wof:placetype":"venue"
},
  "geometry": {"coordinates":[-0.1249789968,38.6157951355],"type":"Point"}
}