{
  "type": "Feature",
  "properties": {
    "addr:full":"C/ Mestre Laporta, 6 Alcoi Alicante 03804",
    "addr:housenumber":"6",
    "addr:postcode":"03804",
    "addr:street":"C / Mestre Laporta",
    "iso:country":"ES",
    "sg:address":"C/ Mestre Laporta, 6",
    "sg:city":"Alcoi",
    "sg:orig_category":"Promotores Constructores",
    "sg:phone":"+34 965 33 12 93",
    "sg:postcode":"03804",
    "sg:province":"Alicante",
    "wof:name":"Construcciones Alcoy 2001 S.l.",
    "wof:placetype":"venue"
},
  "geometry": {"coordinates":[-0.4717079997,38.7075386047],"type":"Point"}
}