{
  "type": "Feature",
  "properties": {
    "iso:country":"ES",
    "sg:address":"Calle de Sierra Pambley, 22",
    "sg:city":"Ponferrada",
    "sg:orig_category":"Maquinaria Para Industrias Diversas",
    "sg:phone":"+34 987 42 34 06",
    "sg:postcode":"24400",
    "sg:province":"Le\u00f3n",
    "wof:name":"Red Ofisat S.l.",
    "wof:placetype":"venue"
},
  "geometry": {"coordinates":[-6.5985760689,42.5465393066],"type":"Point"}
}