{
  "type": "Feature",
  "properties": {
    "addr:full":"Av Estanislau Figueres (d'), 51 Tarragona Tarragona 43002",
    "addr:housenumber":"51",
    "addr:postcode":"43002",
    "addr:street":"Av Estanislau Figueres D '",
    "iso:country":"ES",
    "sg:address":"Av Estanislau Figueres (d'), 51",
    "sg:city":"Tarragona",
    "sg:orig_category":"Albergues",
    "sg:phone":"+34 977 24 05 65",
    "sg:postcode":"43002",
    "sg:province":"Tarragona",
    "wof:name":"Clausell Redondo Encarnacion",
    "wof:placetype":"venue"
},
  "geometry": {"coordinates":[1.2466700077,41.1190261841],"type":"Point"}
}