{
  "type": "Feature",
  "properties": {
    "iso:country":"ES",
    "sg:address":"Calle de Playa Samil, 16",
    "sg:city":"Estacion",
    "sg:orig_category":"Electrodom\u00c9sticos (al Por Menor)",
    "sg:phone":"+34 918 51 35 76",
    "sg:postcode":"28400",
    "sg:province":"Madrid",
    "wof:name":"Reparaciones San Bruno S.l",
    "wof:placetype":"venue"
},
  "geometry": {"coordinates":[-4.0117778778,40.6177787781],"type":"Point"}
}