{
  "type": "Feature",
  "properties": {
    "iso:country":"ES",
    "sg:address":"Calle de Ayora, Km. 0050,3",
    "sg:city":"Enguera",
    "sg:orig_category":"Autob\u00das (explotaci\u00d3n Y Servicios De)",
    "sg:phone":"+34 962 22 42 50",
    "sg:postcode":"46810",
    "sg:province":"Valencia",
    "wof:name":"Tomas Granero S.a.",
    "wof:placetype":"venue"
},
  "geometry": {"coordinates":[-0.6903539896,38.9775886536],"type":"Point"}
}