{
  "type": "Feature",
  "properties": {
    "iso:country":"ES",
    "sg:address":"Pl Espa\u00d1a, 3",
    "sg:city":"Elche",
    "sg:orig_category":"M\u00c9dicos: Pediatr\u00cda. Enfermedades De Los Ni\u00d1os",
    "sg:phone":"+34 965 44 23 89",
    "sg:postcode":"03201",
    "sg:province":"Alicante",
    "wof:name":"Vargas Torcal Fernando",
    "wof:placetype":"venue"
},
  "geometry": {"coordinates":[-0.7023360133,38.2667541504],"type":"Point"}
}