{
  "type": "Feature",
  "properties": {
    "iso:country":"ES",
    "sg:address":"Calle de Nicolas De Las Pe\u00d1as, 36",
    "sg:city":"Beniel",
    "sg:orig_category":"Fisioterapia",
    "sg:phone":"+34 968 60 27 10",
    "sg:postcode":"30130",
    "sg:province":"Murcia",
    "wof:name":"Ortin Aviles Maria Angeles",
    "wof:placetype":"venue"
},
  "geometry": {"coordinates":[-1.0035680532,38.0478782654],"type":"Point"}
}