{
  "type": "Feature",
  "properties": {
    "iso:country":"ES",
    "sg:address":"Calle de Hoyos, 10",
    "sg:city":"Parla",
    "sg:orig_category":"Ense\u00d1anza Variada",
    "sg:phone":"+34 916 05 83 90",
    "sg:postcode":"28980",
    "sg:province":"Madrid",
    "wof:name":"Garcia De Rivera Fernandez Francisco Jose",
    "wof:placetype":"venue"
},
  "geometry": {"coordinates":[-3.7714600563,40.2394714355],"type":"Point"}
}