{
  "type": "Feature",
  "properties": {
    "iso:country":"ES",
    "sg:address":"Avda America (de), 55",
    "sg:city":"Cordoba",
    "sg:orig_category":"Transportes Por V\u00cdas Navegables",
    "sg:phone":"+34 957 45 43 12",
    "sg:postcode":"14005",
    "sg:province":"C\u00f3rdoba",
    "wof:name":"Villareal Lucena Rafael",
    "wof:placetype":"venue"
},
  "geometry": {"coordinates":[-4.7911992073,37.8869438171],"type":"Point"}
}