{
  "type": "Feature",
  "properties": {
    "iso:country":"ES",
    "sg:address":"Cra. Vall D'aran, Km. 0014,6",
    "sg:city":"Alguaire",
    "sg:orig_category":"Mec\u00c1nico Del Autom\u00d3vil",
    "sg:phone":"+34 973 75 63 44",
    "sg:postcode":"25125",
    "sg:province":"Lleida",
    "wof:name":"Abaigar Amoros Jesus",
    "wof:placetype":"venue"
},
  "geometry": {"coordinates":[0.554149,41.72945],"type":"Point"}
}