{
  "type": "Feature",
  "properties": {
    "iso:country":"ES",
    "sg:address":"Carr Hostalric, 27",
    "sg:city":"Urbanitzacio Mas Altaba",
    "sg:orig_category":"Promotores Constructores",
    "sg:phone":"+34 972 85 88 33",
    "sg:postcode":"17412",
    "sg:province":"Girona",
    "wof:name":"Construcciones Todel S.cv.",
    "wof:placetype":"venue"
},
  "geometry": {"coordinates":[2.7342700958,41.7778396606],"type":"Point"}
}