{
  "type": "Feature",
  "properties": {
    "iso:country":"ES",
    "sg:address":"Calle de Toledo, 1",
    "sg:city":"Burgos",
    "sg:orig_category":"Cajas De Ahorro",
    "sg:phone":"+34 947 27 76 71",
    "sg:postcode":"09004",
    "sg:province":"Burgos",
    "sg:website":"www.iberjaca.es",
    "wof:name":"Caja De Ahorros Y Monte De Piedad De Zaragoza Aragon Y Rioja",
    "wof:placetype":"venue"
},
  "geometry": {"coordinates":[-3.6976459026,42.341255188],"type":"Point"}
}