{
  "type": "Feature",
  "properties": {
    "iso:country":"ES",
    "sg:address":"Calle de Silvestre Bello, 4",
    "sg:city":"Canario",
    "sg:orig_category":"Colchones (fabricaci\u00d3n, Al Por Mayor, Al Por Menor)",
    "sg:phone":"+34 928 79 13 61",
    "sg:postcode":"35110",
    "sg:province":"Las Palmas",
    "wof:name":"Ronandez S.a.",
    "wof:placetype":"venue"
},
  "geometry": {"coordinates":[-15.4373636246,27.8569469452],"type":"Point"}
}