{
  "type": "Feature",
  "properties": {
    "addr:full":"Carrer de Laurea Miro, 353 Esplugues Llobregat Barcelona 08950",
    "addr:housenumber":"353",
    "addr:postcode":"08950",
    "addr:street":"Carrer De Laurea Miro",
    "iso:country":"ES",
    "sg:address":"Carrer de Laurea Miro, 353",
    "sg:city":"Esplugues Llobregat",
    "sg:orig_category":"Agencias De Viajes",
    "sg:phone":"+34 933 71 41 61",
    "sg:postcode":"08950",
    "sg:province":"Barcelona",
    "wof:name":"Jortor",
    "wof:placetype":"venue"
},
  "geometry": {"coordinates":[2.08096385,41.3781661987],"type":"Point"}
}