{
  "type": "Feature",
  "properties": {
    "iso:country":"ES",
    "sg:address":"Avgd Blondel, S/n",
    "sg:city":"Lleida",
    "sg:orig_category":"Aparcamientos (infraestructuras, Accesorios)",
    "sg:phone":"+34 973 26 41 43",
    "sg:postcode":"25002",
    "sg:province":"Lleida",
    "wof:name":"Leridana De Aparcamientos S. A.",
    "wof:placetype":"venue"
},
  "geometry": {"coordinates":[0.6232450008,41.6121253967],"type":"Point"}
}