{
  "type": "Feature",
  "properties": {
    "iso:country":"ES",
    "sg:address":"Calle de Gonzalo Torrente Ballester, 46",
    "sg:city":"Alcala Henares",
    "sg:orig_category":"Promotores Constructores",
    "sg:phone":"+34 918 30 31 36",
    "sg:postcode":"28806",
    "sg:province":"Madrid",
    "wof:name":"Anfase Del Henares,s.l.",
    "wof:placetype":"venue"
},
  "geometry": {"coordinates":[-3.364685297,40.5004806519],"type":"Point"}
}