{
  "type": "Feature",
  "properties": {
    "iso:country":"ES",
    "sg:address":"Av Diagonal, 456",
    "sg:city":"Barcelona",
    "sg:orig_category":"Edici\u00d3n De Diarios, Revistas, Boletines",
    "sg:phone":"+34 934 15 41 05",
    "sg:postcode":"08006",
    "sg:province":"Barcelona",
    "wof:name":"Editorial De Serveis De Obres Literaries 90 S.l.",
    "wof:placetype":"venue"
},
  "geometry": {"coordinates":[2.1577289104,41.3964004517],"type":"Point"}
}