{
  "type": "Feature",
  "properties": {
    "iso:country":"ES",
    "sg:address":"Calle de San Nicasio, 31",
    "sg:city":"Leganes",
    "sg:orig_category":"Abogados",
    "sg:phone":"+34 916 94 77 47",
    "sg:postcode":"28911",
    "sg:province":"Madrid",
    "wof:name":"Sanchez Vidanes Maria Del Carmen",
    "wof:placetype":"venue"
},
  "geometry": {"coordinates":[-3.7673680782,40.3310966492],"type":"Point"}
}