{
  "type": "Feature",
  "properties": {
    "iso:country":"ES",
    "sg:address":"Pase Julio Beobide, 3",
    "sg:city":"Zumaia",
    "sg:orig_category":"Material Y Suministros Para Fotocopiadoras, Reprograf\u00cda",
    "sg:phone":"+34 943 86 23 01",
    "sg:postcode":"20750",
    "sg:province":"Guip\u00f9zcoa",
    "wof:name":"Mugica Larrarte Jose Maria",
    "wof:placetype":"venue"
},
  "geometry": {"coordinates":[-2.2552950382,43.2982215881],"type":"Point"}
}