{
  "type": "Feature",
  "properties": {
    "iso:country":"ES",
    "sg:address":"Avda Padre Usera, 14",
    "sg:city":"Roa",
    "sg:orig_category":"Sales (al Por Mayor)",
    "sg:phone":"+34 947 54 06 11",
    "sg:postcode":"09300",
    "sg:province":"Burgos",
    "wof:name":"Colinas Y Velasco S.l.",
    "wof:placetype":"venue"
},
  "geometry": {"coordinates":[-3.929929018,41.6976394653],"type":"Point"}
}