{
  "type": "Feature",
  "properties": {
    "iso:country":"ES",
    "sg:address":"Plaz Conde Del Valle De Suchil, 20",
    "sg:city":"Madrid",
    "sg:orig_category":"M\u00c9dicos: Anestesiolog\u00cda Y Reanimaci\u00d3n Quir\u00dargica",
    "sg:phone":"+34 914 47 50 81",
    "sg:postcode":"28015",
    "sg:province":"Madrid",
    "wof:name":"Colon Bombin Tomas",
    "wof:placetype":"venue"
},
  "geometry": {"coordinates":[-3.7068109512,40.4311904907],"type":"Point"}
}