{
  "type": "Feature",
  "properties": {
    "addr:full":"Carr Coscollar, 7 Manises Valencia 46940",
    "addr:housenumber":"7",
    "addr:postcode":"46940",
    "addr:street":"Carr Coscollar",
    "iso:country":"ES",
    "sg:address":"Carr Coscollar, 7",
    "sg:city":"Manises",
    "sg:orig_category":"Maquinaria Para Industrias Diversas",
    "sg:phone":"+34 961 52 62 50",
    "sg:postcode":"46940",
    "sg:province":"Valencia",
    "wof:name":"Cordes Espa\u00f1a Logistica S.l.",
    "wof:placetype":"venue"
},
  "geometry": {"coordinates":[-0.465568006,39.4893836975],"type":"Point"}
}