{
  "type": "Feature",
  "properties": {
    "iso:country":"ES",
    "sg:address":"Carr Arago, S/n",
    "sg:city":"Alfas Pi",
    "sg:orig_category":"Inform\u00c1tica (estudios, Servicios, Asesor\u00cda, Formaci\u00d3n)",
    "sg:phone":"+34 966 86 00 72",
    "sg:postcode":"03580",
    "sg:province":"Alicante",
    "sg:website":"www.dragonet.es",
    "wof:name":"Dragonet Comunicaciones S.l. Unipersonal",
    "wof:placetype":"venue"
},
  "geometry": {"coordinates":[-0.1106439978,38.5881652832],"type":"Point"}
}