{
  "type": "Feature",
  "properties": {
    "iso:country":"ES",
    "sg:address":"Calle de Puerta De Rota, 4",
    "sg:city":"Sanlucar De Barrameda",
    "sg:orig_category":"Empresas De Desmonte",
    "sg:phone":"+34 956 38 01 61",
    "sg:postcode":"11540",
    "sg:province":"C\u00e1diz",
    "wof:name":"Sumariva Hernandez Jose Antonio",
    "wof:placetype":"venue"
},
  "geometry": {"coordinates":[-6.3542590141,36.7743682861],"type":"Point"}
}