{
  "type": "Feature",
  "properties": {
    "addr:full":"Calle de Concepcion, 6 Torrevieja Alicante 03180",
    "addr:housenumber":"6",
    "addr:postcode":"03180",
    "addr:street":"Calle De Concepcion",
    "iso:country":"ES",
    "sg:address":"Calle de Concepcion, 6",
    "sg:city":"Torrevieja",
    "sg:orig_category":"Herradores, Herreros, Carreteros",
    "sg:phone":"+34 965 71 09 82",
    "sg:postcode":"03180",
    "sg:province":"Alicante",
    "wof:name":"Garcia Traba Maria",
    "wof:placetype":"venue"
},
  "geometry": {"coordinates":[-0.6827428937,37.9763259888],"type":"Point"}
}