{
  "type": "Feature",
  "properties": {
    "iso:country":"ES",
    "sg:address":"Calle de Heros, 24",
    "sg:city":"Bilbao",
    "sg:orig_category":"M\u00c9dicos: Endocrinolog\u00cda Y Metabolismo",
    "sg:phone":"+34 944 24 71 41",
    "sg:postcode":"48009",
    "sg:province":"Vizcaya",
    "wof:name":"Suarez De Puga Diez Jorge",
    "wof:placetype":"venue"
},
  "geometry": {"coordinates":[-2.9327194691,43.2646484375],"type":"Point"}
}