{
  "type": "Feature",
  "properties": {
    "iso:country":"ES",
    "sg:address":"Av America, 44",
    "sg:city":"Mataro",
    "sg:orig_category":"Centros Empresariales",
    "sg:phone":"+34 937 90 23 78",
    "sg:postcode":"08304",
    "sg:province":"Barcelona",
    "wof:name":"Union Comarcal De Empresarios Carpinteros Ebanistas Y Afines",
    "wof:placetype":"venue"
},
  "geometry": {"coordinates":[2.4473369122,41.5472717285],"type":"Point"}
}