{
  "type": "Feature",
  "properties": {
    "addr:full":"Calle de Doctor Severo Ochoa, 1 Valle Trapaga Vizcaya 48510",
    "addr:housenumber":"1",
    "addr:postcode":"48510",
    "addr:street":"Calle De Doctor Severo Ochoa;Trapaga",
    "iso:country":"ES",
    "sg:address":"Calle de Doctor Severo Ochoa, 1",
    "sg:city":"Valle Trapaga",
    "sg:orig_category":"Mec\u00c1nico Del Autom\u00d3vil",
    "sg:phone":"+34 944 92 07 54",
    "sg:postcode":"48510",
    "sg:province":"Vizcaya",
    "wof:name":"Jaime Barrenetxea Gil",
    "wof:placetype":"venue"
},
  "geometry": {"coordinates":[-3.0361230373,43.3021621704],"type":"Point"}
}