{
  "type": "Feature",
  "properties": {
    "addr:full":"Carr Carles V, 12 Eivissa Islas Baleares 07800",
    "addr:housenumber":"12",
    "addr:postcode":"07800",
    "addr:street":"Carr Carles V",
    "iso:country":"ES",
    "sg:address":"Carr Carles V, 12",
    "sg:city":"Eivissa",
    "sg:orig_category":"M\u00c9dicos: Ginecolog\u00cda Y Obstetricia",
    "sg:phone":"+34 971 31 30 53",
    "sg:postcode":"07800",
    "sg:province":"Islas Baleares",
    "wof:name":"Lia Garcia Maria Jesus",
    "wof:placetype":"venue"
},
  "geometry": {"coordinates":[1.4337149858,38.9111824036],"type":"Point"}
}