{
  "type": "Feature",
  "properties": {
    "iso:country":"ES",
    "sg:address":"Ctra Fuenlabrada (c-707), Km. 0007,2",
    "sg:city":"Mostoles",
    "sg:orig_category":"Cerrajer\u00cda, Ferrallista",
    "sg:phone":"+34 916 45 45 01",
    "sg:postcode":"28936",
    "sg:province":"Madrid",
    "wof:name":"Construcciones Metalicas Jose Luis Mu\u00f1oz S.l.",
    "wof:placetype":"venue"
},
  "geometry": {"coordinates":[-3.8453359604,40.3152503967],"type":"Point"}
}