{
  "type": "Feature",
  "properties": {
    "addr:full":"Calle de Tercia, 5 Castro Rio C\u00f3rdoba 14840",
    "addr:housenumber":"5",
    "addr:postcode":"14840",
    "addr:street":"Calle De Tercia;Rio Co\u0301Rdoba",
    "iso:country":"ES",
    "sg:address":"Calle de Tercia, 5",
    "sg:city":"Castro Rio",
    "sg:orig_category":"Supermercados Y Hipermercados",
    "sg:phone":"+34 957 37 23 34",
    "sg:postcode":"14840",
    "sg:province":"C\u00f3rdoba",
    "wof:name":"Galvez Y Quintero S.l.",
    "wof:placetype":"venue"
},
  "geometry": {"coordinates":[-4.4827690125,37.688949585],"type":"Point"}
}