{
  "type": "Feature",
  "properties": {
    "iso:country":"ES",
    "sg:address":"Plaz Hermanos Martin Escudero, 2",
    "sg:city":"Aguadulce",
    "sg:orig_category":"Transportes Por V\u00cdas Navegables",
    "sg:phone":"+34 950 34 54 36",
    "sg:postcode":"04720",
    "sg:province":"Almer\u00eda",
    "wof:name":"Martin Martinez Jose Manuel",
    "wof:placetype":"venue"
},
  "geometry": {"coordinates":[-2.5712640285,36.8165206909],"type":"Point"}
}