{
  "type": "Feature",
  "properties": {
    "addr:full":"Calle de Gaitan De Ayala, S/n Algeciras C\u00e1diz 11207",
    "addr:housenumber":"s / n;ca\u0301diz",
    "addr:postcode":"11207",
    "addr:street":"Calle De Gaitan De Ayala",
    "iso:country":"ES",
    "sg:address":"Calle de Gaitan De Ayala, S/n",
    "sg:city":"Algeciras",
    "sg:orig_category":"Empresas Portuarias",
    "sg:phone":"+34 956 66 47 91",
    "sg:postcode":"11207",
    "sg:province":"C\u00e1diz",
    "sg:website":"www.seritel.com/seritel.com",
    "wof:name":"Servimar Sur S.l.",
    "wof:placetype":"venue"
},
  "geometry": {"coordinates":[-5.4420690536,36.1238365173],"type":"Point"}
}