{
  "type": "Feature",
  "properties": {
    "addr:full":"Av Voltes, 14 Bisbal D'emporda Girona 17100",
    "addr:housenumber":"14",
    "addr:postcode":"17100",
    "addr:street":"Av Voltes",
    "iso:country":"ES",
    "sg:address":"Av Voltes, 14",
    "sg:city":"Bisbal D'emporda",
    "sg:orig_category":"Enfermeras: Consultas, Atenci\u00d3n A Domicilio",
    "sg:phone":"+34 972 64 06 58",
    "sg:postcode":"17100",
    "sg:province":"Girona",
    "wof:name":"Martell Cals Josefa",
    "wof:placetype":"venue"
},
  "geometry": {"coordinates":[2.813131094,41.9749221802],"type":"Point"}
}