{
  "type": "Feature",
  "properties": {
    "iso:country":"ES",
    "sg:address":"Pase Redondillo (del), S/n",
    "sg:city":"Colmenar Viejo",
    "sg:orig_category":"Alquiler De V\u00cddeo",
    "sg:phone":"+34 918 45 92 78",
    "sg:postcode":"28770",
    "sg:province":"Madrid",
    "wof:name":"Canal Star S.l.",
    "wof:placetype":"venue"
},
  "geometry": {"coordinates":[-3.7756450176,40.656036377],"type":"Point"}
}