{
  "type": "Feature",
  "properties": {
    "addr:full":"Calle de Carlos I, 19 Torrijos Toledo 45500",
    "addr:housenumber":"19",
    "addr:postcode":"45500",
    "addr:street":"Calle De Carlos I",
    "iso:country":"ES",
    "sg:address":"Calle de Carlos I, 19",
    "sg:city":"Torrijos",
    "sg:orig_category":"Asilos De Ancianos. Centros Privados",
    "sg:phone":"+34 925 76 26 58",
    "sg:postcode":"45500",
    "sg:province":"Toledo",
    "wof:name":"Residencia Sociales Edad De Oro",
    "wof:placetype":"venue"
},
  "geometry": {"coordinates":[-4.2889418602,39.9849586487],"type":"Point"}
}