{
  "type": "Feature",
  "properties": {
    "addr:full":"Cra San Agustin, 2 Loja Granada 18300",
    "addr:housenumber":"2 loja",
    "addr:postcode":"18300",
    "addr:street":"Agustin",
    "iso:country":"ES",
    "sg:address":"Cra San Agustin, 2",
    "sg:city":"Loja",
    "sg:orig_category":"Quincaller\u00cda (al Por Mayor)",
    "sg:phone":"+34 958 32 01 00",
    "sg:postcode":"18300",
    "sg:province":"Granada",
    "wof:name":"El Candado Antonio Jimenez Garcia S.l.",
    "wof:placetype":"venue"
},
  "geometry": {"coordinates":[-4.1492190361,37.1664733887],"type":"Point"}
}