{
  "type": "Feature",
  "properties": {
    "iso:country":"ES",
    "sg:address":"Pl Major, 34",
    "sg:city":"Vic",
    "sg:orig_category":"Carnicer\u00cdas, Carnicer\u00cdas",
    "sg:phone":"+34 938 86 32 59",
    "sg:postcode":"08500",
    "sg:province":"Barcelona",
    "wof:name":"Can Vilada S.l.",
    "wof:placetype":"venue"
},
  "geometry": {"coordinates":[2.2551569939,41.9305801392],"type":"Point"}
}