{
  "type": "Feature",
  "properties": {
    "addr:full":"Carrer de Mistral, 5 Hospitalet Llobregat Barcelona 08904",
    "addr:housenumber":"5",
    "addr:postcode":"08904",
    "addr:street":"Carrer De Mistral",
    "iso:country":"ES",
    "sg:address":"Carrer de Mistral, 5",
    "sg:city":"Hospitalet Llobregat",
    "sg:classifiers":[
        {
            "category":"Food & Beverages",
            "subcategory":"Candy",
            "type":"Retail Goods"
        }
    ],
    "sg:phone":"+34 934 48 23 46",
    "sg:postcode":"08904",
    "sg:province":"Barcelona",
    "sg:tags":[
        "confiter\u00cdas",
        "y",
        "de",
        "fabricaci\u00d3n",
        "chocolate"
    ],
    "wof:name":"Productos Aguera Sociedad Limitada",
    "wof:placetype":"venue"
},
  "geometry": {"coordinates":[2.1160259247,41.3719444275],"type":"Point"}
}