{
  "type": "Feature",
  "properties": {
    "iso:country":"ES",
    "sg:address":"Carr Mig, 24",
    "sg:city":"Vilanova I La Geltru",
    "sg:orig_category":"Cursos Particulares, Asistencia Escolar",
    "sg:phone":"+34 938 14 58 97",
    "sg:postcode":"08800",
    "sg:province":"Barcelona",
    "wof:name":"Vera Gonzalez Jose",
    "wof:placetype":"venue"
},
  "geometry": {"coordinates":[1.7268999815,41.2211303711],"type":"Point"}
}