{
  "type": "Feature",
  "properties": {
    "addr:full":"Avda Principes De Espa\u00d1a, 15 Ejido Almer\u00eda 04700",
    "addr:housenumber":"15 ejido",
    "addr:postcode":"04700",
    "addr:street":"Avda Principes De Espan\u0303A;Almeri\u0301A",
    "iso:country":"ES",
    "sg:address":"Avda Principes De Espa\u00d1a, 15",
    "sg:city":"Ejido",
    "sg:orig_category":"Centros De Educaci\u00d3n Especial",
    "sg:phone":"+34 950 57 31 29",
    "sg:postcode":"04700",
    "sg:province":"Almer\u00eda",
    "wof:name":"Junta De Andalucia.",
    "wof:placetype":"venue"
},
  "geometry": {"coordinates":[-2.8174378872,36.7815933228],"type":"Point"}
}