{
  "type": "Feature",
  "properties": {
    "iso:country":"ES",
    "sg:address":"Calle de Uriondo, 1",
    "sg:city":"Done Bikendi Harana",
    "sg:orig_category":"Producci\u00d3n, Comercio De Cereales",
    "sg:phone":"+34 945 40 61 16",
    "sg:postcode":"01117",
    "sg:province":"\u00c1lava",
    "wof:name":"Garlan S.coop.",
    "wof:placetype":"venue"
},
  "geometry": {"coordinates":[-2.3616440296,42.7425270081],"type":"Point"}
}