{
  "type": "Feature",
  "properties": {
    "addr:full":"Carr Del Dos De Maig, 52 Ontinyent Valencia 46870",
    "addr:housenumber":"52",
    "addr:postcode":"46870",
    "addr:street":"Carr Del Dos De Maig",
    "iso:country":"ES",
    "sg:address":"Carr Del Dos De Maig, 52",
    "sg:city":"Ontinyent",
    "sg:orig_category":"Asociaciones, Organismos Culturales Y Socioeducativos",
    "sg:phone":"+34 962 38 34 98",
    "sg:postcode":"46870",
    "sg:province":"Valencia",
    "wof:name":"Comparsas Moros Berberiscos",
    "wof:placetype":"venue"
},
  "geometry": {"coordinates":[-0.6030989885,38.8258895874],"type":"Point"}
}