{
  "type": "Feature",
  "properties": {
    "addr:full":"Ptda Casa\u00f1a, S/n Vall Uixo Castell\u00f3n 12600",
    "addr:housenumber":"s / n",
    "addr:postcode":"12600",
    "addr:street":"Ptda Casan\u0303A",
    "iso:country":"ES",
    "sg:address":"Ptda Casa\u00f1a, S/n",
    "sg:city":"Vall Uixo",
    "sg:orig_category":"Pirotecnia (espect\u00c1culos)",
    "sg:phone":"+34 964 76 65 29",
    "sg:postcode":"12600",
    "sg:province":"Castell\u00f3n",
    "sg:website":"www.codsc.com/penarroja",
    "wof:name":"Pirotecnia Pe\u00d1arroja S.l.",
    "wof:placetype":"venue"
},
  "geometry": {"coordinates":[-0.2315589935,39.8232955933],"type":"Point"}
}