{
  "type": "Feature",
  "properties": {
    "addr:full":"Pque Erreniega Parkea, 24 Zizur Mayor Navarra 31180",
    "addr:housenumber":"24",
    "addr:postcode":"31180",
    "addr:street":"Parkea",
    "iso:country":"ES",
    "sg:address":"Pque Erreniega Parkea, 24",
    "sg:city":"Zizur Mayor",
    "sg:orig_category":"Carnicer\u00cdas, Carnicer\u00cdas",
    "sg:phone":"+34 948 18 35 28",
    "sg:postcode":"31180",
    "sg:province":"Navarra",
    "wof:name":"Sanguesa Arizaleta Mercedes Y Yoldi Bustingorri Felipe S.i.c.",
    "wof:placetype":"venue"
},
  "geometry": {"coordinates":[-1.6922559738,42.7863388062],"type":"Point"}
}