{
  "type": "Feature",
  "properties": {
    "iso:country":"ES",
    "sg:address":"Av Abat Marcet, 357",
    "sg:city":"Terrassa",
    "sg:orig_category":"Electricidad: Instaladores",
    "sg:phone":"+34 937 33 65 56",
    "sg:postcode":"08225",
    "sg:province":"Barcelona",
    "sg:website":"www.sivnetwork.com",
    "wof:name":"Grup S.i.v.s.c.p.",
    "wof:placetype":"venue"
},
  "geometry": {"coordinates":[2.0036029816,41.5742797852],"type":"Point"}
}