{
  "type": "Feature",
  "properties": {
    "iso:country":"ES",
    "sg:address":"Calle de Plata, 68",
    "sg:city":"Torrejon Ardoz",
    "sg:orig_category":"Molduras, Junquillos, Listones Y Molduras Perforadas",
    "sg:phone":"+34 916 56 33 39",
    "sg:postcode":"28850",
    "sg:province":"Madrid",
    "wof:name":"Cadierno Ambite Maximo",
    "wof:placetype":"venue"
},
  "geometry": {"coordinates":[-3.4554579258,40.4551200867],"type":"Point"}
}