{
  "type": "Feature",
  "properties": {
    "iso:country":"ES",
    "sg:address":"Calle de Maria Diaz De Haro, 11",
    "sg:city":"Portugalete",
    "sg:orig_category":"Arquitectos",
    "sg:phone":"+34 944 96 26 72",
    "sg:postcode":"48920",
    "sg:province":"Vizcaya",
    "wof:name":"Torres Carranza Armando",
    "wof:placetype":"venue"
},
  "geometry": {"coordinates":[-3.0191419125,43.3232307434],"type":"Point"}
}