{
  "type": "Feature",
  "properties": {
    "addr:full":"Calle de Antonio Lopez, 99 Madrid Madrid 28026",
    "addr:housenumber":"99",
    "addr:postcode":"madrid;28026",
    "addr:street":"Calle De Antonio Lopez",
    "iso:country":"ES",
    "sg:address":"Calle de Antonio Lopez, 99",
    "sg:city":"Madrid",
    "sg:orig_category":"Equipo De Refrigeraci\u00d3n Industrial",
    "sg:phone":"+34 915 00 35 81",
    "sg:postcode":"28026",
    "sg:province":"Madrid",
    "wof:name":"Sofrisa S.a.",
    "wof:placetype":"venue"
},
  "geometry": {"coordinates":[-3.6995229721,40.3880805969],"type":"Point"}
}