{
  "type": "Feature",
  "properties": {
    "addr:full":"Urbitarte Auzunea, 3 Azpeitia Guip\u00f9zcoa 20730",
    "addr:housenumber":"3",
    "addr:postcode":"20730",
    "addr:street":"Urbitarte Auzunea;Guipu\u0300Zcoa",
    "iso:country":"ES",
    "sg:address":"Urbitarte Auzunea, 3",
    "sg:city":"Azpeitia",
    "sg:orig_category":"Farmacias",
    "sg:phone":"+34 943 81 19 49",
    "sg:postcode":"20730",
    "sg:province":"Guip\u00f9zcoa",
    "wof:name":"Beristain Muguruza Maria Belen",
    "wof:placetype":"venue"
},
  "geometry": {"coordinates":[-2.2702929974,43.1788444519],"type":"Point"}
}