{
  "type": "Feature",
  "properties": {
    "addr:full":"Calle de Paco Leon, 2 Cordoba C\u00f3rdoba 14014",
    "addr:housenumber":"2",
    "addr:postcode":"14014",
    "addr:street":"Calle De Paco Leon;Co\u0301Rdoba",
    "iso:country":"ES",
    "sg:address":"Calle de Paco Leon, 2",
    "sg:city":"Cordoba",
    "sg:orig_category":"Bisuteros (fabricaci\u00d3n, Al Por Mayor)",
    "sg:phone":"+34 957 25 17 75",
    "sg:postcode":"14014",
    "sg:province":"C\u00f3rdoba",
    "wof:name":"Martinez Rosa Juan Manuel",
    "wof:placetype":"venue"
},
  "geometry": {"coordinates":[-4.7565689087,37.8909988403],"type":"Point"}
}