{
  "type": "Feature",
  "properties": {
    "iso:country":"ES",
    "sg:address":"Calle de Suspiros, 72",
    "sg:city":"Alora",
    "sg:orig_category":"Escayola Y Productos De Escayola (fabricaci\u00d3n, Al Por Mayor)",
    "sg:phone":"+34 952 49 80 36",
    "sg:postcode":"29500",
    "sg:province":"M\u00e1laga",
    "wof:name":"Diaz Morilla Jose Fernando",
    "wof:placetype":"venue"
},
  "geometry": {"coordinates":[-4.707529068,36.8279838562],"type":"Point"}
}