{
  "type": "Feature",
  "properties": {
    "addr:full":"Calle de Martin Machio, 17 Madrid Madrid 28002",
    "addr:housenumber":"17",
    "addr:postcode":"madrid;28002",
    "addr:street":"Calle De Martin Machio",
    "iso:country":"ES",
    "sg:address":"Calle de Martin Machio, 17",
    "sg:city":"Madrid",
    "sg:orig_category":"Chapister\u00cda",
    "sg:phone":"+34 914 15 95 75",
    "sg:postcode":"28002",
    "sg:province":"Madrid",
    "wof:name":"Carrocerias Cuarta Entrada S.l.",
    "wof:placetype":"venue"
},
  "geometry": {"coordinates":[-3.6630260944,40.4476127625],"type":"Point"}
}