{
  "type": "Feature",
  "properties": {
    "iso:country":"ES",
    "sg:address":"Calle de Teresa Cajal, 5",
    "sg:city":"Tarazona",
    "sg:orig_category":"Papeler\u00cdas, Librer\u00cdas",
    "sg:phone":"+34 976 64 37 99",
    "sg:postcode":"50500",
    "sg:province":"Zaragoza",
    "wof:name":"Andia Laborda Elena",
    "wof:placetype":"venue"
},
  "geometry": {"coordinates":[-1.724381566,41.8998298645],"type":"Point"}
}