{
  "type": "Feature",
  "properties": {
    "iso:country":"ES",
    "sg:address":"Calle de Minerva, 105",
    "sg:city":"Madrid",
    "sg:orig_category":"Carnicer\u00cdas, Carnicer\u00cdas",
    "sg:phone":"+34 917 60 17 12",
    "sg:postcode":"28032",
    "sg:province":"Madrid",
    "wof:name":"Loranca Gomez David",
    "wof:placetype":"venue"
},
  "geometry": {"coordinates":[-3.6065919399,40.3958435059],"type":"Point"}
}