{
  "type": "Feature",
  "properties": {
    "addr:full":"Calle de San Bernardo, 12 Madrid Madrid 28015",
    "addr:housenumber":"12",
    "addr:postcode":"madrid;28015",
    "addr:street":"Calle De San Bernardo",
    "iso:country":"ES",
    "sg:address":"Calle de San Bernardo, 12",
    "sg:city":"Madrid",
    "sg:orig_category":"Molduras, Junquillos, Listones Y Molduras Perforadas",
    "sg:phone":"+34 915 23 03 61",
    "sg:postcode":"28015",
    "sg:province":"Madrid",
    "wof:name":"Gonzalez Lopez Francisco",
    "wof:placetype":"venue"
},
  "geometry": {"coordinates":[-3.707638979,40.4222717285],"type":"Point"}
}