{
  "type": "Feature",
  "properties": {
    "addr:full":"Calle de Panaderos, 34 Valladolid Valladolid 47004",
    "addr:housenumber":"34",
    "addr:postcode":"47004",
    "addr:street":"Calle De Panaderos",
    "iso:country":"ES",
    "sg:address":"Calle de Panaderos, 34",
    "sg:city":"Valladolid",
    "sg:orig_category":"Droguer\u00cdas (al Por Menor)",
    "sg:phone":"+34 983 20 28 24",
    "sg:postcode":"47004",
    "sg:province":"Valladolid",
    "wof:name":"Ares Izquierdo Juvencio",
    "wof:placetype":"venue"
},
  "geometry": {"coordinates":[-4.7226958275,41.6464653015],"type":"Point"}
}