{
  "type": "Feature",
  "properties": {
    "iso:country":"ES",
    "sg:address":"Galindo, 12",
    "sg:city":"Galindo-salcedillo",
    "sg:orig_category":"Construcciones Prefabricadas Y Desmontables",
    "sg:phone":"+34 944 71 15 09",
    "sg:postcode":"48510",
    "sg:province":"Vizcaya",
    "wof:name":"Algeco Construcciones Modulares S.a.",
    "wof:placetype":"venue"
},
  "geometry": {"coordinates":[-3.0168557167,43.3053665161],"type":"Point"}
}