{
  "type": "Feature",
  "properties": {
    "iso:country":"ES",
    "sg:address":"Calle de Pedro Iv El Ceremonioso, 10",
    "sg:city":"Zaragoza",
    "sg:orig_category":"M\u00c9dicos: Estomatolog\u00cda",
    "sg:phone":"+34 976 56 49 50",
    "sg:postcode":"50009",
    "sg:province":"Zaragoza",
    "wof:name":"Mur Sanchez Antonio",
    "wof:placetype":"venue"
},
  "geometry": {"coordinates":[-0.9049659967,41.6342353821],"type":"Point"}
}