{
  "type": "Feature",
  "properties": {
    "iso:country":"ES",
    "sg:address":"Calle de Real, 67",
    "sg:city":"Pulgar",
    "sg:orig_category":"Caf\u00c9s, Bares, Cervecer\u00cdas",
    "sg:phone":"+34 925 29 22 46",
    "sg:postcode":"45125",
    "sg:province":"Toledo",
    "wof:name":"Balmaseda Villarrubia Juan",
    "wof:placetype":"venue"
},
  "geometry": {"coordinates":[-4.1510691643,39.6959609985],"type":"Point"}
}