{
  "type": "Feature",
  "properties": {
    "addr:full":"Ctra Ba\u00d1os De Arteijo, 7 Coru\u00d1a A Coru\u00f1a 15008",
    "addr:housenumber":"7",
    "addr:postcode":"15008",
    "addr:street":"Ctra Ban\u0303Os De Arteijo;Corun\u0303A",
    "iso:country":"ES",
    "sg:address":"Ctra Ba\u00d1os De Arteijo, 7",
    "sg:city":"Coru\u00d1a",
    "sg:orig_category":"Molduras, Junquillos, Listones Y Molduras Perforadas",
    "sg:phone":"+34 981 13 91 97",
    "sg:postcode":"15008",
    "sg:province":"A Coru\u00f1a",
    "wof:name":"Suarez Prego Dorotea",
    "wof:placetype":"venue"
},
  "geometry": {"coordinates":[-8.4512443542,43.3434753418],"type":"Point"}
}