{
  "type": "Feature",
  "properties": {
    "addr:full":"Carro Barrera, 2 Velilla Reina Le\u00f3n 24392",
    "addr:postcode":"24392",
    "addr:street":"Leo\u0301N",
    "iso:country":"ES",
    "sg:address":"Carro Barrera, 2",
    "sg:city":"Velilla Reina",
    "sg:orig_category":"Animales (al Por Menor)",
    "sg:phone":"+34 987 35 85 52",
    "sg:postcode":"24392",
    "sg:province":"Le\u00f3n",
    "wof:name":"De La Flor De Granda Sl",
    "wof:placetype":"venue"
},
  "geometry": {"coordinates":[-5.7662639618,42.5171508789],"type":"Point"}
}