{
  "type": "Feature",
  "properties": {
    "addr:full":"Ctra Madrid, Km. 0061,0 Olias Rey Toledo 45280",
    "addr:postcode":"45280",
    "addr:street":"Ctra Madrid Km. 0061,0 Olias Rey",
    "iso:country":"ES",
    "sg:address":"Ctra Madrid, Km. 0061,0",
    "sg:city":"Olias Rey",
    "sg:orig_category":"Art\u00cdculos De Madera (fabricaci\u00d3n Y Al Por Mayor)",
    "sg:phone":"+34 925 49 01 90",
    "sg:postcode":"45280",
    "sg:province":"Toledo",
    "wof:name":"Artesanos Reunidos S. A.",
    "wof:placetype":"venue"
},
  "geometry": {"coordinates":[-4.010412693,39.9090270996],"type":"Point"}
}