{
  "type": "Feature",
  "properties": {
    "iso:country":"ES",
    "sg:address":"Trva Ballesteros, 4",
    "sg:city":"Huesca",
    "sg:orig_category":"Locales Y Clases De Danza",
    "sg:phone":"+34 974 22 33 76",
    "sg:postcode":"22001",
    "sg:province":"Huesca",
    "wof:name":"Elenco Aragones",
    "wof:placetype":"venue"
},
  "geometry": {"coordinates":[-0.402707994,42.1364898682],"type":"Point"}
}