{
  "type": "Feature",
  "properties": {
    "iso:country":"ES",
    "sg:address":"Calle de Damas, 1",
    "sg:city":"Riaza",
    "sg:orig_category":"Carnicer\u00cdas, Carnicer\u00cdas",
    "sg:phone":"+34 921 55 05 97",
    "sg:postcode":"40500",
    "sg:province":"Segovia",
    "wof:name":"Encinas Vicente Jesus",
    "wof:placetype":"venue"
},
  "geometry": {"coordinates":[-3.4785454273,41.2770233154],"type":"Point"}
}