{
  "type": "Feature",
  "properties": {
    "iso:country":"ES",
    "sg:address":"Ctra Viladamat Figueres, Km. 0023,7",
    "sg:city":"Saldet",
    "sg:orig_category":"Alquiler De Veh\u00cdculos: Turismos Y Utilitarios",
    "sg:phone":"+34 972 55 00 13",
    "sg:postcode":"17473",
    "sg:province":"Girona",
    "sg:website":"www.caravaninn.net",
    "wof:name":"Caravan Inn S.l.",
    "wof:placetype":"venue"
},
  "geometry": {"coordinates":[3.0266749859,42.1492004395],"type":"Point"}
}