{
  "type": "Feature",
  "properties": {
    "iso:country":"ES",
    "sg:address":"Carrer de Cadi, 48",
    "sg:city":"Barcelona",
    "sg:orig_category":"Inmobiliaria (agencias)",
    "sg:phone":"+34 934 20 67 91",
    "sg:postcode":"08031",
    "sg:province":"Barcelona",
    "wof:name":"Alba Gestion S.l.",
    "wof:placetype":"venue"
},
  "geometry": {"coordinates":[2.1697020531,41.4324760437],"type":"Point"}
}