{
  "type": "Feature",
  "properties": {
    "iso:country":"ES",
    "sg:address":"Calle de Santa Engracia, 65",
    "sg:city":"Madrid",
    "sg:orig_category":"Cl\u00cdnicas Dentales",
    "sg:phone":"+34 915 93 92 59",
    "sg:postcode":"28010",
    "sg:province":"Madrid",
    "sg:website":"www.vitaldent.com",
    "wof:name":"Iglesias Dental S.l.",
    "wof:placetype":"venue"
},
  "geometry": {"coordinates":[-3.6985909939,40.4341773987],"type":"Point"}
}