{
  "type": "Feature",
  "properties": {
    "addr:full":"Calle de Olimpia (de), S/n Jaca Huesca 22700",
    "addr:housenumber":"/ n",
    "addr:postcode":"22700",
    "addr:street":"Calle De Olimpia De S",
    "iso:country":"ES",
    "sg:address":"Calle de Olimpia (de), S/n",
    "sg:city":"Jaca",
    "sg:classifiers":[
        {
            "category":"Taxi",
            "type":"Transportation"
        }
    ],
    "sg:phone":"+34 974 36 07 90",
    "sg:postcode":"22700",
    "sg:province":"Huesca",
    "wof:name":"Bescos Betran Felix",
    "wof:placetype":"venue"
},
  "geometry": {"coordinates":[-0.5487509966,42.5653343201],"type":"Point"}
}