{
  "type": "Feature",
  "properties": {
    "iso:country":"ES",
    "sg:address":"Calle de Tenderina, 22",
    "sg:city":"Oviedo",
    "sg:orig_category":"Negocio De Materiales De Construcci\u00d3n",
    "sg:phone":"+34 985 21 02 88",
    "sg:postcode":"33010",
    "sg:province":"Asturias",
    "wof:name":"Servicios Integrales Del Hogar S. L.",
    "wof:placetype":"venue"
},
  "geometry": {"coordinates":[-5.8370089531,43.3641777039],"type":"Point"}
}