{
  "type": "Feature",
  "properties": {
    "iso:country":"ES",
    "sg:address":"Calle de San Romualdo, 26",
    "sg:city":"Madrid",
    "sg:orig_category":"Ingenier\u00cda, Centros De Estudios (diversos)",
    "sg:phone":"+34 913 27 46 15",
    "sg:postcode":"28037",
    "sg:province":"Madrid",
    "wof:name":"Rollan Rodriguez S.c.",
    "wof:placetype":"venue"
},
  "geometry": {"coordinates":[-3.6216089725,40.4380226135],"type":"Point"}
}