{
  "type": "Feature",
  "properties": {
    "iso:country":"ES",
    "sg:address":"Avda Juan De Austria, S/n",
    "sg:city":"Salamanca",
    "sg:orig_category":"Ense\u00d1anza, Formaci\u00d3n Profesional: Aprendizaje",
    "sg:phone":"+34 923 26 36 99",
    "sg:postcode":"37008",
    "sg:province":"Salamanca",
    "wof:name":"Ayuntamiento De Salamanca-escuela De Musica Municipal",
    "wof:placetype":"venue"
},
  "geometry": {"coordinates":[-5.6660265923,40.9515380859],"type":"Point"}
}