{
  "type": "Feature",
  "properties": {
    "addr:full":"Trva Lopez Corton, 11 Cedeira La Coru\u00f1a 15350",
    "addr:housenumber":"11",
    "addr:postcode":"15350",
    "addr:street":"Trva Lopez Corton;La Corun\u0303A",
    "iso:country":"ES",
    "sg:address":"Trva Lopez Corton, 11",
    "sg:city":"Cedeira",
    "sg:orig_category":"Molduras, Junquillos, Listones Y Molduras Perforadas",
    "sg:phone":"+34 981 48 00 05",
    "sg:postcode":"15350",
    "sg:province":"La Coru\u00f1a",
    "wof:name":"Fernandez Pazos Jose Manuel",
    "wof:placetype":"venue"
},
  "geometry": {"coordinates":[-8.0542783737,43.6598968506],"type":"Point"}
}