{
  "type": "Feature",
  "properties": {
    "addr:full":"Plz De Oviedo, 5 Pedro Mu\u00f1oz Ciudad Real 13620",
    "addr:housenumber":"5",
    "addr:postcode":"13620",
    "addr:street":"Plz De Oviedo;Pedro Mun\u0303Oz",
    "iso:country":"ES",
    "sg:address":"Plz De Oviedo, 5",
    "sg:city":"Pedro Mu\u00f1oz",
    "sg:orig_category":"Droguer\u00cdas (al Por Menor)",
    "sg:phone":"+34 926 58 64 79",
    "sg:postcode":"13620",
    "sg:province":"Ciudad Real",
    "wof:name":"Martinez Fernandez Santiago",
    "wof:placetype":"venue"
},
  "geometry": {"coordinates":[-2.9435579777,39.4077987671],"type":"Point"}
}