{
  "type": "Feature",
  "properties": {
    "addr:full":"Calle de Tala La, S/n Llanes Asturias 33500",
    "addr:housenumber":"/ n",
    "addr:postcode":"33500",
    "addr:street":"Calle De Tala La S",
    "iso:country":"ES",
    "sg:address":"Calle de Tala La, S/n",
    "sg:city":"Llanes",
    "sg:orig_category":"Inmobiliaria (agencias)",
    "sg:phone":"+34 985 40 19 59",
    "sg:postcode":"33500",
    "sg:province":"Asturias",
    "wof:name":"Pulido Cabrera Ildefonso",
    "wof:placetype":"venue"
},
  "geometry": {"coordinates":[-4.7549939156,43.4207191467],"type":"Point"}
}