{
  "type": "Feature",
  "properties": {
    "iso:country":"ES",
    "sg:address":"Calle de Portalegre, 102",
    "sg:city":"Madrid",
    "sg:orig_category":"Cueros Y Pieles (al Por Mayor)",
    "sg:phone":"+34 914 69 62 30",
    "sg:postcode":"28019",
    "sg:province":"Madrid",
    "wof:name":"Jose Luis Zumel S.l.",
    "wof:placetype":"venue"
},
  "geometry": {"coordinates":[-3.7236990929,40.3856658936],"type":"Point"}
}