{
  "type": "Feature",
  "properties": {
    "iso:country":"ES",
    "sg:address":"Calle de Mayor, 20",
    "sg:city":"Arenas -areeta",
    "sg:orig_category":"Centros Comerciales Y Grandes Tiendas",
    "sg:phone":"+34 944 80 32 87",
    "sg:postcode":"48930",
    "sg:province":"Vizcaya",
    "wof:name":"Txirtxilu Mundua S.l.",
    "wof:placetype":"venue"
},
  "geometry": {"coordinates":[-2.6983869076,43.2204284668],"type":"Point"}
}