{
  "type": "Feature",
  "properties": {
    "iso:country":"ES",
    "sg:address":"Rua Rio Salas, 8",
    "sg:city":"Ourense",
    "sg:orig_category":"Empresas De Carpinter\u00cda De Madera",
    "sg:phone":"+34 988 21 77 20",
    "sg:postcode":"32001",
    "sg:province":"Ourense",
    "wof:name":"Carpinteria Parga S.l.",
    "wof:placetype":"venue"
},
  "geometry": {"coordinates":[-7.8688988686,42.3539237976],"type":"Point"}
}