{
  "type": "Feature",
  "properties": {
    "iso:country":"ES",
    "sg:address":"Carrer de Industria, 16",
    "sg:city":"Santa Barbara",
    "sg:orig_category":"Farmacias",
    "sg:phone":"+34 977 71 88 14",
    "sg:postcode":"43570",
    "sg:province":"Tarragona",
    "wof:name":"Bertomeu Arasa Angels",
    "wof:placetype":"venue"
},
  "geometry": {"coordinates":[0.4927839935,40.7134208679],"type":"Point"}
}