{
  "type": "Feature",
  "properties": {
    "addr:full":"Calle de Mies De La Revilla, 1 Ramales Victoria Cantabria 39800",
    "addr:housenumber":"1",
    "addr:postcode":"39800",
    "addr:street":"Calle De Mies De La Revilla",
    "iso:country":"ES",
    "sg:address":"Calle de Mies De La Revilla, 1",
    "sg:city":"Ramales Victoria",
    "sg:orig_category":"Cristaler\u00cdas",
    "sg:phone":"+34 942 64 62 47",
    "sg:postcode":"39800",
    "sg:province":"Cantabria",
    "wof:name":"Fernandez Gato Jose Antonio",
    "wof:placetype":"venue"
},
  "geometry": {"coordinates":[-3.442991972,43.2613754272],"type":"Point"}
}