{
  "type": "Feature",
  "properties": {
    "addr:full":"Carr Escola De Ses Nines, 22 Maria De La Salut Islas Baleares 07519",
    "addr:housenumber":"22",
    "addr:postcode":"07519",
    "addr:street":"Carr Escola De Ses Nines",
    "iso:country":"ES",
    "sg:address":"Carr Escola De Ses Nines, 22",
    "sg:city":"Maria De La Salut",
    "sg:orig_category":"Chapister\u00cda",
    "sg:phone":"+34 971 52 52 39",
    "sg:postcode":"07519",
    "sg:province":"Islas Baleares",
    "wof:name":"Colombram Font Martin",
    "wof:placetype":"venue"
},
  "geometry": {"coordinates":[3.0768389702,39.6683883667],"type":"Point"}
}