{
  "type": "Feature",
  "properties": {
    "iso:country":"ES",
    "sg:address":"Avda Frontera De Haro, 3",
    "sg:city":"Venta De Ba\u00e7os",
    "sg:orig_category":"Carnicer\u00cdas, Carnicer\u00cdas",
    "sg:phone":"+34 979 77 06 54",
    "sg:postcode":"34200",
    "sg:province":"Palencia",
    "wof:name":"Paredes De La Fuente Camelia Margarita",
    "wof:placetype":"venue"
},
  "geometry": {"coordinates":[-4.4889569283,41.9214324951],"type":"Point"}
}