{
  "type": "Feature",
  "properties": {
    "addr:full":"Carr Mossen Blanch, 15 Algemesi Valencia 46680",
    "addr:housenumber":"15",
    "addr:postcode":"46680",
    "addr:street":"Carr Mossen Blanch",
    "iso:country":"ES",
    "sg:address":"Carr Mossen Blanch, 15",
    "sg:city":"Algemesi",
    "sg:orig_category":"Asesor\u00cda Fiscal Y Jur\u00cddica",
    "sg:phone":"+34 962 42 57 11",
    "sg:postcode":"46680",
    "sg:province":"Valencia",
    "wof:name":"Diaz Morcillo Julio",
    "wof:placetype":"venue"
},
  "geometry": {"coordinates":[-0.4361110032,39.190410614],"type":"Point"}
}