{
  "type": "Feature",
  "properties": {
    "addr:full":"Pl Catalunya, 39 Mataro Barcelona 08303",
    "addr:housenumber":"39",
    "addr:postcode":"08303",
    "addr:street":"Pl Catalunya",
    "iso:country":"ES",
    "sg:address":"Pl Catalunya, 39",
    "sg:city":"Mataro",
    "sg:orig_category":"Molduras, Junquillos, Listones Y Molduras Perforadas",
    "sg:phone":"+34 937 57 04 42",
    "sg:postcode":"08303",
    "sg:province":"Barcelona",
    "wof:name":"Hamburger Scp",
    "wof:placetype":"venue"
},
  "geometry": {"coordinates":[2.4320869446,41.5390357971],"type":"Point"}
}