{
  "type": "Feature",
  "properties": {
    "addr:full":"Calle de Guadalajara, 9 Marchamalo Guadalajara 19180",
    "addr:housenumber":"9",
    "addr:postcode":"19180",
    "addr:street":"Calle De Guadalajara",
    "iso:country":"ES",
    "sg:address":"Calle de Guadalajara, 9",
    "sg:city":"Marchamalo",
    "sg:orig_category":"Alimentaci\u00d3n General (al Por Menor)",
    "sg:phone":"+34 949 25 06 83",
    "sg:postcode":"19180",
    "sg:province":"Guadalajara",
    "wof:name":"Andres San Juan Garcia Y Jose San Juan Garcia Cdad",
    "wof:placetype":"venue"
},
  "geometry": {"coordinates":[-3.1995835304,40.6665000916],"type":"Point"}
}