{
  "type": "Feature",
  "properties": {
    "addr:full":"Calle de Lido, 8 Madrid Madrid 28043",
    "addr:housenumber":"8",
    "addr:postcode":"madrid;28043",
    "addr:street":"Calle De Lido",
    "iso:country":"ES",
    "sg:address":"Calle de Lido, 8",
    "sg:city":"Madrid",
    "sg:orig_category":"Arquitectos",
    "sg:phone":"+34 913 88 71 79",
    "sg:postcode":"28043",
    "sg:province":"Madrid",
    "wof:name":"Pastor Navarro Jesus",
    "wof:placetype":"venue"
},
  "geometry": {"coordinates":[-3.6527140141,40.4562568665],"type":"Point"}
}