{
  "type": "Feature",
  "properties": {
    "addr:full":"Carr Calvario, 26 Betera Valencia 46117",
    "addr:housenumber":"26",
    "addr:postcode":"46117",
    "addr:street":"Carr Calvario",
    "iso:country":"ES",
    "sg:address":"Carr Calvario, 26",
    "sg:city":"Betera",
    "sg:orig_category":"Guarder\u00cdas",
    "sg:phone":"+34 961 69 20 96",
    "sg:postcode":"46117",
    "sg:province":"Valencia",
    "wof:name":"Canos Garcia Laura",
    "wof:placetype":"venue"
},
  "geometry": {"coordinates":[-0.4615089893,39.5908508301],"type":"Point"}
}