{
  "type": "Feature",
  "properties": {
    "addr:full":"Plaz Pilar, 2 Almodovar Campo Ciudad Real 13580",
    "addr:housenumber":"2",
    "addr:postcode":"13580",
    "addr:street":"Plaz Pilar;Campo",
    "iso:country":"ES",
    "sg:address":"Plaz Pilar, 2",
    "sg:city":"Almodovar Campo",
    "sg:orig_category":"Reposter\u00cdas",
    "sg:phone":"+34 926 48 33 80",
    "sg:postcode":"13580",
    "sg:province":"Ciudad Real",
    "wof:name":"Morena Fernandez Miguel",
    "wof:placetype":"venue"
},
  "geometry": {"coordinates":[-4.1820688248,38.7115097046],"type":"Point"}
}