{
  "type": "Feature",
  "properties": {
    "addr:full":"Calle de Alcala, 45 Madrid Madrid 28...",
    "addr:housenumber":"45;28 ...",
    "addr:postcode":"madrid",
    "addr:street":"Calle De Alcala;Madrid",
    "iso:country":"ES",
    "sg:address":"Calle de Alcala, 45",
    "sg:city":"Madrid",
    "sg:orig_category":"Abogados",
    "sg:phone":"+34 913 64 98 00",
    "sg:postcode":"28...",
    "sg:province":"Madrid",
    "sg:website":"www.ashurst.com",
    "wof:name":"Ashurst Morris Crisp",
    "wof:placetype":"venue"
},
  "geometry": {"coordinates":[-3.6958351135,40.4189987183],"type":"Point"}
}