{
  "type": "Feature",
  "properties": {
    "addr:full":"Carrer de Barcelona, 121 Amposta Tarragona 43870",
    "addr:housenumber":"121",
    "addr:postcode":"43870",
    "addr:street":"Carrer De Barcelona",
    "iso:country":"ES",
    "sg:address":"Carrer de Barcelona, 121",
    "sg:city":"Amposta",
    "sg:orig_category":"Materiales De Aislamiento T\u00c9rmico Y Ac\u00dastico",
    "sg:phone":"+34 977 70 11 42",
    "sg:postcode":"43870",
    "sg:province":"Tarragona",
    "wof:name":"Aislamientos Tarraco S.l.",
    "wof:placetype":"venue"
},
  "geometry": {"coordinates":[0.5804061294,40.7029304504],"type":"Point"}
}