{
  "type": "Feature",
  "properties": {
    "iso:country":"ES",
    "sg:address":"Calle de Padre Polanco, 2",
    "sg:city":"Zaragoza",
    "sg:orig_category":"Bisuter\u00cda, Joyer\u00cda, Relojer\u00cda (al Por Menor)",
    "sg:phone":"+34 976 59 52 88",
    "sg:postcode":"50008",
    "sg:province":"Zaragoza",
    "wof:name":"Barasoain Ochoa Miguel Angel",
    "wof:placetype":"venue"
},
  "geometry": {"coordinates":[-0.8757330179,41.6387672424],"type":"Point"}
}