{
  "type": "Feature",
  "properties": {
    "addr:full":"Placerilla, S/n La Antigua Le\u00f3n 24796",
    "addr:housenumber":"/ n",
    "addr:postcode":"24796",
    "addr:street":"Placerilla S;Leo\u0301N",
    "iso:country":"ES",
    "sg:address":"Placerilla, S/n",
    "sg:city":"La Antigua",
    "sg:orig_category":"Distribuci\u00d3n De Petr\u00d3leo Y Derivados",
    "sg:phone":"+34 987 65 16 24",
    "sg:postcode":"24796",
    "sg:province":"Le\u00f3n",
    "wof:name":"La Balinesa S.l.",
    "wof:placetype":"venue"
},
  "geometry": {"coordinates":[-5.7715787888,42.1699867249],"type":"Point"}
}