{
  "type": "Feature",
  "properties": {
    "addr:full":"Avda Aragon De, 79 Fraga Huesca 22520",
    "addr:housenumber":"79",
    "addr:postcode":"22520",
    "addr:street":"Avda Aragon De",
    "iso:country":"ES",
    "sg:address":"Avda Aragon De, 79",
    "sg:city":"Fraga",
    "sg:orig_category":"Fabricaci\u00d3n Y Comercio De M\u00c1quinas",
    "sg:phone":"+34 974 47 02 94",
    "sg:postcode":"22520",
    "sg:province":"Huesca",
    "wof:name":"Vera Trems S.l.",
    "wof:placetype":"venue"
},
  "geometry": {"coordinates":[0.334277004,41.5203742981],"type":"Point"}
}