{
  "type": "Feature",
  "properties": {
    "iso:country":"ES",
    "sg:address":"C/ Conrado Del Campo, 9",
    "sg:city":"Elche",
    "sg:orig_category":"Empresas De Carpinter\u00cda De Madera",
    "sg:phone":"+34 965 44 22 69",
    "sg:postcode":"03204",
    "sg:province":"Alicante",
    "wof:name":"Carpinteria Molto S.l.",
    "wof:placetype":"venue"
},
  "geometry": {"coordinates":[-0.7038570046,38.2622718811],"type":"Point"}
}