{
  "type": "Feature",
  "properties": {
    "addr:full":"Calle de Santo Domingo, 24 Pto Real C\u00e1diz 11510",
    "addr:housenumber":"24",
    "addr:postcode":"11510",
    "addr:street":"Calle De Santo Domingo;Ca\u0301Diz",
    "iso:country":"ES",
    "sg:address":"Calle de Santo Domingo, 24",
    "sg:city":"Pto Real",
    "sg:orig_category":"Internados & Ense\u00d1anza Privada",
    "sg:phone":"+34 956 83 02 90",
    "sg:postcode":"11510",
    "sg:province":"C\u00e1diz",
    "wof:name":"Colegio Del Santo Angel",
    "wof:placetype":"venue"
},
  "geometry": {"coordinates":[-6.1936969757,36.528427124],"type":"Point"}
}