{
  "type": "Feature",
  "properties": {
    "addr:full":"Calle de Agua, 30 Alfacar Granada 18170",
    "addr:housenumber":"30",
    "addr:postcode":"18170",
    "addr:street":"Calle De Agua",
    "iso:country":"ES",
    "sg:address":"Calle de Agua, 30",
    "sg:city":"Alfacar",
    "sg:orig_category":"Promotores Constructores",
    "sg:phone":"+34 958 54 07 65",
    "sg:postcode":"18170",
    "sg:province":"Granada",
    "wof:name":"Construcciones Guinaroz",
    "wof:placetype":"venue"
},
  "geometry": {"coordinates":[-3.5671930313,37.2373657227],"type":"Point"}
}