{
  "type": "Feature",
  "properties": {
    "iso:country":"ES",
    "sg:address":"Crrd Capuchinos, 53",
    "sg:city":"Andujar",
    "sg:orig_category":"Aceites Y Grasas Alimentarias (fabricaci\u00d3n, Al Por Mayor)",
    "sg:phone":"+34 953 50 38 91",
    "sg:postcode":"23740",
    "sg:province":"Ja\u00e9n",
    "wof:name":"Comunidad De Propietarios Corredera Capuchinos 53",
    "wof:placetype":"venue"
},
  "geometry": {"coordinates":[-4.0484380722,38.0364341736],"type":"Point"}
}