{
  "type": "Feature",
  "properties": {
    "addr:full":"Calle de Valdihuertos, 12 Cuellar Segovia 40200",
    "addr:housenumber":"12",
    "addr:postcode":"40200",
    "addr:street":"Calle De Valdihuertos",
    "iso:country":"ES",
    "sg:address":"Calle de Valdihuertos, 12",
    "sg:city":"Cuellar",
    "sg:orig_category":"Fabricaci\u00d3n, Venta, Instalaci\u00d3n De R\u00d3tulos, De R\u00d3tulos Luminosos",
    "sg:phone":"+34 921 14 07 13",
    "sg:postcode":"40200",
    "sg:province":"Segovia",
    "wof:name":"Decoraciones Fradejas S.l.",
    "wof:placetype":"venue"
},
  "geometry": {"coordinates":[-4.311316967,41.4053497314],"type":"Point"}
}