{
  "type": "Feature",
  "properties": {
    "iso:country":"ES",
    "sg:address":"Calle de Cancela De Afuera, 12",
    "sg:city":"Coru\u00d1a",
    "sg:orig_category":"Mec\u00c1nico Del Autom\u00d3vil",
    "sg:phone":"+34 981 26 07 30",
    "sg:postcode":"15005",
    "sg:province":"La Coru\u00f1a",
    "wof:name":"Antonio Y Jose Rodriguez Insua S.cv.",
    "wof:placetype":"venue"
},
  "geometry": {"coordinates":[-8.4149036407,43.3608207703],"type":"Point"}
}