{
  "type": "Feature",
  "properties": {
    "addr:full":"Rbla San Julian (de), 38 Teruel Teruel 44003",
    "addr:housenumber":"38",
    "addr:postcode":"44003",
    "addr:street":"Rbla San Julian De",
    "iso:country":"ES",
    "sg:address":"Rbla San Julian (de), 38",
    "sg:city":"Teruel",
    "sg:orig_category":"Cr\u00cda De Animales",
    "sg:phone":"+34 978 60 77 63",
    "sg:postcode":"44003",
    "sg:province":"Teruel",
    "wof:name":"Menelendez Goriz Trinidad",
    "wof:placetype":"venue"
},
  "geometry": {"coordinates":[-1.1028319597,40.3411979675],"type":"Point"}
}