{
  "type": "Feature",
  "properties": {
    "addr:full":"Cmno Procesional, 5 Santa Ursula Santa Cruz De Tenerife 38390",
    "addr:housenumber":"5",
    "addr:postcode":"38390",
    "addr:street":"Cmno Procesional",
    "iso:country":"ES",
    "sg:address":"Cmno Procesional, 5",
    "sg:city":"Santa Ursula",
    "sg:orig_category":"Centros Empresariales",
    "sg:phone":"+34 922 33 77 03",
    "sg:postcode":"38390",
    "sg:province":"Santa Cruz De Tenerife",
    "wof:name":"Garcia Correa Manuel",
    "wof:placetype":"venue"
},
  "geometry": {"coordinates":[-16.4917697906,28.425359726],"type":"Point"}
}