{
  "type": "Feature",
  "properties": {
    "addr:full":"Calle de Zamacola, 39 Bilbao Vizcaya 48003",
    "addr:housenumber":"39",
    "addr:postcode":"48003",
    "addr:street":"Calle De Zamacola",
    "iso:country":"ES",
    "sg:address":"Calle de Zamacola, 39",
    "sg:city":"Bilbao",
    "sg:orig_category":"Carnicer\u00cdas, Carnicer\u00cdas",
    "sg:phone":"+34 944 15 22 94",
    "sg:postcode":"48003",
    "sg:province":"Vizcaya",
    "wof:name":"Marcos Capellan Jose Miguel",
    "wof:placetype":"venue"
},
  "geometry": {"coordinates":[-2.9212288857,43.2467346191],"type":"Point"}
}