{
  "type": "Feature",
  "properties": {
    "addr:full":"Plaz Juan Donapetry, 3 Viveiro Lugo 27850",
    "addr:housenumber":"3",
    "addr:postcode":"27850",
    "addr:street":"Plaz Juan Donapetry",
    "iso:country":"ES",
    "sg:address":"Plaz Juan Donapetry, 3",
    "sg:city":"Viveiro",
    "sg:orig_category":"Peluquer\u00cdas, Peluquer\u00cda Mixta",
    "sg:phone":"+34 982 55 04 26",
    "sg:postcode":"27850",
    "sg:province":"Lugo",
    "wof:name":"Martinez Paleo Esperanza",
    "wof:placetype":"venue"
},
  "geometry": {"coordinates":[-7.5926671028,43.6626319885],"type":"Point"}
}