{
  "type": "Feature",
  "properties": {
    "iso:country":"ES",
    "sg:address":"C/ Sant Joan, 7",
    "sg:city":"Tarrega",
    "sg:orig_category":"Ropa Para Ni\u00d1os (al Por Menor)",
    "sg:phone":"+34 973 50 06 61",
    "sg:postcode":"25300",
    "sg:province":"Lleida",
    "wof:name":"Maria & Fina C.c.p.",
    "wof:placetype":"venue"
},
  "geometry": {"coordinates":[1.1386350393,41.6472702026],"type":"Point"}
}