{
  "type": "Feature",
  "properties": {
    "addr:full":"Calle de Hospital, 1 Guadalajara Guadalajara 19001",
    "addr:housenumber":"1",
    "addr:postcode":"19001",
    "addr:street":"Calle De Hospital",
    "iso:country":"ES",
    "sg:address":"Calle de Hospital, 1",
    "sg:city":"Guadalajara",
    "sg:orig_category":"Promotores Constructores",
    "sg:phone":"+34 949 22 82 12",
    "sg:postcode":"19001",
    "sg:province":"Guadalajara",
    "wof:name":"Dragados S.a.",
    "wof:placetype":"venue"
},
  "geometry": {"coordinates":[-3.1713778973,40.6394424438],"type":"Point"}
}