{
  "type": "Feature",
  "properties": {
    "addr:full":"Avda Valladolid, 5 Valencia Valencia 46020",
    "addr:housenumber":"5",
    "addr:postcode":"46020",
    "addr:street":"Avda Valladolid",
    "iso:country":"ES",
    "sg:address":"Avda Valladolid, 5",
    "sg:city":"Valencia",
    "sg:orig_category":"Farmacias",
    "sg:phone":"+34 963 69 26 25",
    "sg:postcode":"46020",
    "sg:province":"Valencia",
    "wof:name":"Abella Aparisi Teresa",
    "wof:placetype":"venue"
},
  "geometry": {"coordinates":[-0.360842,39.489239],"type":"Point"}
}