{
  "type": "Feature",
  "properties": {
    "iso:country":"ES",
    "sg:address":"Calle de Pelayo, 1",
    "sg:city":"Santander",
    "sg:orig_category":"Ense\u00d1ante, Direcci\u00d3n",
    "sg:phone":"+34 942 23 59 82",
    "sg:postcode":"39008",
    "sg:province":"Cantabria",
    "wof:name":"Mazorra Palazuelos Angel",
    "wof:placetype":"venue"
},
  "geometry": {"coordinates":[-3.8135409355,43.4613304138],"type":"Point"}
}