{
  "type": "Feature",
  "properties": {
    "iso:country":"ES",
    "sg:address":"Calle de Santa Ana, 14",
    "sg:city":"Soraluze-placencia Armas",
    "sg:orig_category":"Zapatos (al Por Menor)",
    "sg:phone":"+34 943 75 23 72",
    "sg:postcode":"20590",
    "sg:province":"Guip\u00f9zcoa",
    "wof:name":"Miguelez Alonso Mercedes",
    "wof:placetype":"venue"
},
  "geometry": {"coordinates":[-2.412872076,43.1734580994],"type":"Point"}
}