{
  "type": "Feature",
  "properties": {
    "addr:full":"Carrer de Margarida Xirgu, 38 Sant Feliu Llobregat Barcelona 08980",
    "addr:housenumber":"38",
    "addr:postcode":"08980",
    "addr:street":"Carrer De Margarida Xirgu",
    "iso:country":"ES",
    "sg:address":"Carrer de Margarida Xirgu, 38",
    "sg:city":"Sant Feliu Llobregat",
    "sg:orig_category":"Centros Empresariales",
    "sg:phone":"+34 934 21 55 94",
    "sg:postcode":"08980",
    "sg:province":"Barcelona",
    "wof:name":"Eurosigma Consultores S.l.",
    "wof:placetype":"venue"
},
  "geometry": {"coordinates":[2.0544879436,41.3873977661],"type":"Point"}
}