{
  "type": "Feature",
  "properties": {
    "iso:country":"ES",
    "sg:address":"Plaz Castilla (de), 3",
    "sg:city":"Alcobendas",
    "sg:orig_category":"Arreglo, Reparaci\u00d3n, Piezas Sueltas De Televisi\u00d3n, V\u00cddeo, Hi",
    "sg:phone":"+34 916 54 24 77",
    "sg:postcode":"28100",
    "sg:province":"Madrid",
    "wof:name":"Uzquiano Alonso Angel",
    "wof:placetype":"venue"
},
  "geometry": {"coordinates":[-3.63261199,40.5437088013],"type":"Point"}
}