{
  "type": "Feature",
  "properties": {
    "addr:full":"Plaz Santa Barbara, S/n Pe\u00e7arroya-pueblonuevo C\u00f3rdoba 14200",
    "addr:postcode":"14200",
    "addr:street":"Barbara S / N Pec\u0327Arroya-Pueblonuevo Co\u0301Rdoba",
    "iso:country":"ES",
    "sg:address":"Plaz Santa Barbara, S/n",
    "sg:city":"Pe\u00e7arroya-pueblonuevo",
    "sg:orig_category":"Iglesia Cat\u00d3lica",
    "sg:phone":"+34 957 56 08 49",
    "sg:postcode":"14200",
    "sg:province":"C\u00f3rdoba",
    "wof:name":"Parroquia De Santa Barbara",
    "wof:placetype":"venue"
},
  "geometry": {"coordinates":[-5.2669591904,38.2983703613],"type":"Point"}
}