{
  "type": "Feature",
  "properties": {
    "addr:full":"Calle de Melchor De Macanaz, 17 Albacete Albacete 02005",
    "addr:housenumber":"17",
    "addr:postcode":"02005",
    "addr:street":"Calle De Melchor De Macanaz",
    "iso:country":"ES",
    "sg:address":"Calle de Melchor De Macanaz, 17",
    "sg:city":"Albacete",
    "sg:orig_category":"Guarder\u00cdas",
    "sg:phone":"+34 967 22 64 57",
    "sg:postcode":"02005",
    "sg:province":"Albacete",
    "wof:name":"Jupasper S.l.",
    "wof:placetype":"venue"
},
  "geometry": {"coordinates":[-1.8632750511,38.9990692139],"type":"Point"}
}