{
  "type": "Feature",
  "properties": {
    "iso:country":"ES",
    "sg:address":"Av Roma (de), 16",
    "sg:city":"Tarragona",
    "sg:orig_category":"Ingenier\u00cda, Centros De Estudios (diversos)",
    "sg:phone":"+34 977 22 28 07",
    "sg:postcode":"43005",
    "sg:province":"Tarragona",
    "wof:name":"Apoyo Tecnico De La Construccion S.a.",
    "wof:placetype":"venue"
},
  "geometry": {"coordinates":[1.2415399551,41.1182670593],"type":"Point"}
}