{
  "type": "Feature",
  "properties": {
    "addr:full":"Calle de General Chavarre (la Villa), 11 Lucena C\u00f3rdoba 14900",
    "addr:housenumber":"11",
    "addr:postcode":"14900",
    "addr:street":"Calle De General Chavarre La",
    "iso:country":"ES",
    "sg:address":"Calle de General Chavarre (la Villa), 11",
    "sg:city":"Lucena",
    "sg:orig_category":"Arquitectos",
    "sg:phone":"+34 957 51 66 33",
    "sg:postcode":"14900",
    "sg:province":"C\u00f3rdoba",
    "wof:name":"Gamez Lara Juan",
    "wof:placetype":"venue"
},
  "geometry": {"coordinates":[-4.4839692116,37.4093208313],"type":"Point"}
}