{
  "type": "Feature",
  "properties": {
    "iso:country":"ES",
    "sg:address":"Calle de Cristo De La Salud (del), 6",
    "sg:city":"Valdemoro",
    "sg:orig_category":"Molduras, Junquillos, Listones Y Molduras Perforadas",
    "sg:phone":"+34 918 95 28 96",
    "sg:postcode":"28340",
    "sg:province":"Madrid",
    "wof:name":"Vetas Labrado Luis Vicente",
    "wof:placetype":"venue"
},
  "geometry": {"coordinates":[-3.679602623,40.1915550232],"type":"Point"}
}