{
  "type": "Feature",
  "properties": {
    "iso:country":"ES",
    "sg:address":"Calle de Torrecilla, 10",
    "sg:city":"Valdepe\u00f1as",
    "sg:orig_category":"Ropa Para Se\u00d1oras Y Caballeros (al Por Menor)",
    "sg:phone":"+34 926 31 69 49",
    "sg:postcode":"13300",
    "sg:province":"Ciudad Real",
    "wof:name":"Cortefiel S.a.",
    "wof:placetype":"venue"
},
  "geometry": {"coordinates":[-3.3863809109,38.7622375488],"type":"Point"}
}