{
  "type": "Feature",
  "properties": {
    "iso:country":"ES",
    "sg:address":"Calle de Joaquin Lopez Huici, 6",
    "sg:city":"Cordoba",
    "sg:orig_category":"Electricidad: Equipos Industriales, Componentes (fabricaci\u00d3n)",
    "sg:phone":"+34 957 23 54 26",
    "sg:postcode":"14005",
    "sg:province":"C\u00f3rdoba",
    "wof:name":"Sudielec S.l.",
    "wof:placetype":"venue"
},
  "geometry": {"coordinates":[-4.7902097702,37.8834686279],"type":"Point"}
}