{
  "type": "Feature",
  "properties": {
    "iso:country":"ES",
    "sg:address":"Carr Pont Major, 86",
    "sg:city":"Girona",
    "sg:orig_category":"Desinfecci\u00d3n, Desinsectaci\u00d3n, Desratizaci\u00d3n",
    "sg:phone":"+34 972 20 24 00",
    "sg:postcode":"17007",
    "sg:province":"Girona",
    "wof:name":"Xarles Terminator Europ S.a.",
    "wof:placetype":"venue"
},
  "geometry": {"coordinates":[2.8260509968,42.0131568909],"type":"Point"}
}