{
  "type": "Feature",
  "properties": {
    "addr:full":"Carrer de Esglesia, 86 Calella Barcelona 08370",
    "addr:housenumber":"86",
    "addr:postcode":"08370",
    "addr:street":"Carrer De Esglesia",
    "iso:country":"ES",
    "sg:address":"Carrer de Esglesia, 86",
    "sg:city":"Calella",
    "sg:orig_category":"Cajas De Ahorro",
    "sg:phone":"+34 937 66 44 10",
    "sg:postcode":"08370",
    "sg:province":"Barcelona",
    "wof:name":"Caja De Ahorros Del Mediterraneo",
    "wof:placetype":"venue"
},
  "geometry": {"coordinates":[2.6604170799,41.614025116],"type":"Point"}
}