{
  "type": "Feature",
  "properties": {
    "addr:full":"Stor. S. Antoni, S/n S. Vicen\u00e7 Horts Barcelona 08620",
    "addr:housenumber":"s",
    "addr:postcode":"08620",
    "addr:street":"Stor. S. Antoni;/ N S. Vicenc\u0327 Horts Barcelona",
    "iso:country":"ES",
    "sg:address":"Stor. S. Antoni, S/n",
    "sg:city":"S. Vicen\u00e7 Horts",
    "sg:orig_category":"Artes Gr\u00c1ficas, Artes Pl\u00c1sticas (curso)",
    "sg:phone":"+34 936 76 82 83",
    "sg:postcode":"08620",
    "sg:province":"Barcelona",
    "wof:name":"Serimak S.a.",
    "wof:placetype":"venue"
},
  "geometry": {"coordinates":[2.0100400448,41.3932189941],"type":"Point"}
}