{
  "type": "Feature",
  "properties": {
    "addr:full":"Calle de Reina Fabiola, 23 Zaragoza Zaragoza 50008",
    "addr:housenumber":"23",
    "addr:postcode":"50008",
    "addr:street":"Calle De Reina Fabiola",
    "iso:country":"ES",
    "sg:address":"Calle de Reina Fabiola, 23",
    "sg:city":"Zaragoza",
    "sg:orig_category":"Procuradores",
    "sg:phone":"+34 976 59 62 62",
    "sg:postcode":"50008",
    "sg:province":"Zaragoza",
    "wof:name":"Del Rio Artal Lucia",
    "wof:placetype":"venue"
},
  "geometry": {"coordinates":[-0.874499023,41.6451034546],"type":"Point"}
}