{
  "type": "Feature",
  "properties": {
    "iso:country":"ES",
    "sg:address":"Carrer de Neopatria, 42",
    "sg:city":"Barcelona",
    "sg:orig_category":"Servicios De Telecomunicaciones",
    "sg:phone":"+34 933 46 66 11",
    "sg:postcode":"08030",
    "sg:province":"Barcelona",
    "wof:name":"Ingenieria De Aplicaciones S. A.",
    "wof:placetype":"venue"
},
  "geometry": {"coordinates":[2.188710928,41.4310112],"type":"Point"}
}