{
  "type": "Feature",
  "properties": {
    "addr:full":"Carr Pintor Sorolla, 56 Cullera Valencia 46400",
    "addr:housenumber":"56",
    "addr:postcode":"46400",
    "addr:street":"Carr Pintor Sorolla",
    "iso:country":"ES",
    "sg:address":"Carr Pintor Sorolla, 56",
    "sg:city":"Cullera",
    "sg:orig_category":"Cristaler\u00cdas",
    "sg:phone":"+34 961 72 09 02",
    "sg:postcode":"46400",
    "sg:province":"Valencia",
    "wof:name":"Lucrisal S.l:",
    "wof:placetype":"venue"
},
  "geometry": {"coordinates":[-0.2522949874,39.1629371643],"type":"Point"}
}