{
  "type": "Feature",
  "properties": {
    "addr:full":"Carrer de Madrid, 42 S. Feliu Guixols Girona 17220",
    "addr:housenumber":"42",
    "addr:postcode":"17220",
    "addr:street":"Carrer De Madrid;S. Feliu Guixols",
    "iso:country":"ES",
    "sg:address":"Carrer de Madrid, 42",
    "sg:city":"S. Feliu Guixols",
    "sg:orig_category":"Promotores Constructores",
    "sg:phone":"+34 972 82 30 64",
    "sg:postcode":"17220",
    "sg:province":"Girona",
    "wof:name":"Comunidad De Propietarios Joan Bordas 45-47",
    "wof:placetype":"venue"
},
  "geometry": {"coordinates":[3.0237300396,41.789150238],"type":"Point"}
}