{
  "type": "Feature",
  "properties": {
    "addr:full":"Medano, S/n El Medano Santa Cruz De Tenerife 38612",
    "addr:housenumber":"s / n",
    "addr:postcode":"38612",
    "addr:street":"Medano",
    "iso:country":"ES",
    "sg:address":"Medano, S/n",
    "sg:city":"El Medano",
    "sg:orig_category":"Importaci\u00d3n",
    "sg:phone":"+34 922 17 64 71",
    "sg:postcode":"38612",
    "sg:province":"Santa Cruz De Tenerife",
    "wof:name":"Luis Cortes E Hijos S.a.",
    "wof:placetype":"venue"
},
  "geometry": {"coordinates":[-16.5262241364,28.0532035828],"type":"Point"}
}