{
  "type": "Feature",
  "properties": {
    "iso:country":"ES",
    "sg:address":"Carrer de Moreres (les), 3",
    "sg:city":"Gava",
    "sg:orig_category":"Agentes, Concesionarios Y Sucursales De Veh\u00cdculos",
    "sg:phone":"+34 936 62 30 54",
    "sg:postcode":"08850",
    "sg:province":"Barcelona",
    "wof:name":"Morenas Herrera Antonio",
    "wof:placetype":"venue"
},
  "geometry": {"coordinates":[2.0084180832,41.3029785156],"type":"Point"}
}