{
  "type": "Feature",
  "properties": {
    "addr:full":"Avda Leon Iruretagoyena, 1 Irun Guip\u00f9zcoa 20304",
    "addr:housenumber":"1",
    "addr:postcode":"20304",
    "addr:street":"Avda Leon Iruretagoyena;Guipu\u0300Zcoa",
    "iso:country":"ES",
    "sg:address":"Avda Leon Iruretagoyena, 1",
    "sg:city":"Irun",
    "sg:orig_category":"Edici\u00d3n De Diarios, Revistas, Boletines",
    "sg:phone":"+34 943 62 41 78",
    "sg:postcode":"20304",
    "sg:province":"Guip\u00f9zcoa",
    "wof:name":"Sociedad Vascongada De Publicaciones S.a.",
    "wof:placetype":"venue"
},
  "geometry": {"coordinates":[-1.7902339697,43.3395233154],"type":"Point"}
}