{
  "type": "Feature",
  "properties": {
    "addr:full":"Calle de Don Ramon De La Cruz, 38 Madrid Madrid 28001",
    "addr:housenumber":"38",
    "addr:postcode":"madrid;28001",
    "addr:street":"Calle De Don Ramon De La Cruz",
    "iso:country":"ES",
    "sg:address":"Calle de Don Ramon De La Cruz, 38",
    "sg:city":"Madrid",
    "sg:orig_category":"Discapacitados",
    "sg:phone":"+34 914 35 24 41",
    "sg:postcode":"28001",
    "sg:province":"Madrid",
    "wof:name":"Fundosa Accesibilidad S.a.",
    "wof:placetype":"venue"
},
  "geometry": {"coordinates":[-3.6816773415,40.4289894104],"type":"Point"}
}