{
  "type": "Feature",
  "properties": {
    "iso:country":"ES",
    "sg:address":"Ctra Vila, Km. 0002,0",
    "sg:city":"Viladecans",
    "sg:orig_category":"Ferreter\u00cda (diversos)",
    "sg:phone":"+34 936 58 29 58",
    "sg:postcode":"08840",
    "sg:province":"Barcelona",
    "wof:name":"Hierros Saiz S.l.",
    "wof:placetype":"venue"
},
  "geometry": {"coordinates":[2.021805048,41.3167800903],"type":"Point"}
}