{
  "type": "Feature",
  "properties": {
    "iso:country":"ES",
    "sg:address":"Calle de Navas De Tolosa, 18",
    "sg:city":"Soria",
    "sg:orig_category":"Pescader\u00cdas (al Por Menor)",
    "sg:phone":"+34 975 22 98 91",
    "sg:postcode":"42001",
    "sg:province":"Soria",
    "wof:name":"Llorente Lorenzo Calixto",
    "wof:placetype":"venue"
},
  "geometry": {"coordinates":[-2.4734590054,41.7663803101],"type":"Point"}
}