{
  "type": "Feature",
  "properties": {
    "addr:full":"Carrer de Floridablanca, 135 Barcelona Barcelona 08011",
    "addr:housenumber":"135",
    "addr:postcode":"08011",
    "addr:street":"Carrer De Floridablanca",
    "iso:country":"ES",
    "sg:address":"Carrer de Floridablanca, 135",
    "sg:city":"Barcelona",
    "sg:orig_category":"Empresarios Y Productoras De Espect\u00c1culos",
    "sg:phone":"+34 934 23 24 55",
    "sg:postcode":"08011",
    "sg:province":"Barcelona",
    "sg:website":"www.cinesa.es",
    "wof:name":"Cinesa",
    "wof:placetype":"venue"
},
  "geometry": {"coordinates":[2.1623630524,41.3815917969],"type":"Point"}
}