{
  "type": "Feature",
  "properties": {
    "addr:full":"Molinaseca, Km. 0001,5 Ponferrada Le\u00f3n 24400",
    "addr:postcode":"24400",
    "addr:street":"Molinaseca Km. 0001,5;Leo\u0301N",
    "iso:country":"ES",
    "sg:address":"Molinaseca, Km. 0001,5",
    "sg:city":"Ponferrada",
    "sg:orig_category":"Panader\u00cdas, Panader\u00cdas",
    "sg:phone":"+34 987 41 64 83",
    "sg:postcode":"24400",
    "sg:province":"Le\u00f3n",
    "wof:name":"Confiteria Pili S.a.",
    "wof:placetype":"venue"
},
  "geometry": {"coordinates":[-6.5886659622,42.5438537598],"type":"Point"}
}