{
  "type": "Feature",
  "properties": {
    "iso:country":"ES",
    "sg:address":"Calle de Salvador Minguijon, 1",
    "sg:city":"Zaragoza",
    "sg:orig_category":"Molduras, Junquillos, Listones Y Molduras Perforadas",
    "sg:phone":"+34 976 49 05 80",
    "sg:postcode":"50002",
    "sg:province":"Zaragoza",
    "wof:name":"Telefonos Publicos De Aragon S.l.",
    "wof:placetype":"venue"
},
  "geometry": {"coordinates":[-0.8623149991,41.6446647644],"type":"Point"}
}