{
  "type": "Feature",
  "properties": {
    "iso:country":"ES",
    "sg:address":"Rua Manuel Cominges, 7",
    "sg:city":"Lagarella",
    "sg:orig_category":"Florister\u00cdas",
    "sg:phone":"+34 986 20 50 79",
    "sg:postcode":"36213",
    "sg:province":"Pontevedra",
    "wof:name":"Bascapi S.l.",
    "wof:placetype":"venue"
},
  "geometry": {"coordinates":[-8.7210121155,42.1948318481],"type":"Point"}
}