{
  "type": "Feature",
  "properties": {
    "addr:full":"C/ Lepanto, 32 Elche Alicante 03201",
    "addr:housenumber":"32",
    "addr:postcode":"03201",
    "addr:street":"C / Lepanto",
    "iso:country":"ES",
    "sg:address":"C/ Lepanto, 32",
    "sg:city":"Elche",
    "sg:orig_category":"Comercio De Mobiliario De Oficina",
    "sg:phone":"+34 965 46 57 40",
    "sg:postcode":"03201",
    "sg:province":"Alicante",
    "wof:name":"Lepanto Todo Para Su Oficina S.l.",
    "wof:placetype":"venue"
},
  "geometry": {"coordinates":[-0.7028020024,38.2658538818],"type":"Point"}
}