{
  "type": "Feature",
  "properties": {
    "iso:country":"ES",
    "sg:address":"Calle de Mariana Pineda, 2",
    "sg:city":"Zaragoza",
    "sg:orig_category":"Peluquer\u00cdas, Peluquer\u00cda Mixta",
    "sg:phone":"+34 976 74 15 70",
    "sg:postcode":"50015",
    "sg:province":"Zaragoza",
    "wof:name":"Sales Garcia Eva",
    "wof:placetype":"venue"
},
  "geometry": {"coordinates":[-0.8871690035,41.6660423279],"type":"Point"}
}