{
  "type": "Feature",
  "properties": {
    "iso:country":"ES",
    "sg:address":"Carrer de Binefar, 38",
    "sg:city":"Barcelona",
    "sg:orig_category":"Transporte En General",
    "sg:phone":"+34 933 13 40 41",
    "sg:postcode":"08020",
    "sg:province":"Barcelona",
    "wof:name":"Villalba Bernal Antonio",
    "wof:placetype":"venue"
},
  "geometry": {"coordinates":[2.2058620453,41.4266548157],"type":"Point"}
}