{
  "type": "Feature",
  "properties": {
    "iso:country":"ES",
    "sg:address":"Poli Pol.indust. Cami Dels Frares, S/n",
    "sg:city":"Lleida",
    "sg:orig_category":"Contenedores (mercanc\u00cdas)",
    "sg:phone":"+34 973 25 70 51",
    "sg:postcode":"25191",
    "sg:province":"Lleida",
    "wof:name":"Trans-barcons S.l.",
    "wof:placetype":"venue"
},
  "geometry": {"coordinates":[0.6831650138,41.5832138062],"type":"Point"}
}