{
  "type": "Feature",
  "properties": {
    "addr:full":"Carr Casetes, 72 Massamagrell Valencia 46130",
    "addr:housenumber":"72",
    "addr:postcode":"46130",
    "addr:street":"Carr Casetes",
    "iso:country":"ES",
    "sg:address":"Carr Casetes, 72",
    "sg:city":"Massamagrell",
    "sg:orig_category":"Goma: Productos De Uso Industrial (fabricaci\u00d3n, Al Por Mayor)",
    "sg:phone":"+34 961 44 12 14",
    "sg:postcode":"46130",
    "sg:province":"Valencia",
    "wof:name":"Segarra Martinez Vicente",
    "wof:placetype":"venue"
},
  "geometry": {"coordinates":[-0.3338769972,39.5720100403],"type":"Point"}
}