{
  "type": "Feature",
  "properties": {
    "addr:full":"Calle de Fernando Amor Y Mayor, 8 Cordoba C\u00f3rdoba 14011",
    "addr:housenumber":"8",
    "addr:postcode":"14011",
    "addr:street":"Calle De Fernando Amor Y Mayor;Co\u0301Rdoba",
    "iso:country":"ES",
    "sg:address":"Calle de Fernando Amor Y Mayor, 8",
    "sg:city":"Cordoba",
    "sg:orig_category":"Cl\u00cdnicas Dentales",
    "sg:phone":"+34 957 46 46 88",
    "sg:postcode":"14011",
    "sg:province":"C\u00f3rdoba",
    "wof:name":"Sanidont S.l.",
    "wof:placetype":"venue"
},
  "geometry": {"coordinates":[-4.7954268456,37.887512207],"type":"Point"}
}