{
  "type": "Feature",
  "properties": {
    "addr:full":"Ctra Cartagena, Km. 0018,0 Fuente Alamo Murcia 30320",
    "addr:postcode":"30320",
    "addr:street":"Ctra Cartagena Km. 0018,0",
    "iso:country":"ES",
    "sg:address":"Ctra Cartagena, Km. 0018,0",
    "sg:city":"Fuente Alamo",
    "sg:orig_category":"Agentes, Concesionarios Y Sucursales De Veh\u00cdculos",
    "sg:phone":"+34 968 59 80 08",
    "sg:postcode":"30320",
    "sg:province":"Murcia",
    "wof:name":"Torres Rojo S.l.",
    "wof:placetype":"venue"
},
  "geometry": {"coordinates":[-1.1687190533,37.7235946655],"type":"Point"}
}