{
  "type": "Feature",
  "properties": {
    "iso:country":"ES",
    "sg:address":"La Mesada, S/n",
    "sg:city":"Amandi",
    "sg:orig_category":"Agentes, Concesionarios Y Sucursales De Veh\u00cdculos",
    "sg:phone":"+34 985 89 02 70",
    "sg:postcode":"33311",
    "sg:province":"Asturias",
    "wof:name":"Inverpor S.l.",
    "wof:placetype":"venue"
},
  "geometry": {"coordinates":[-5.3432879448,43.4807777405],"type":"Point"}
}