{
  "type": "Feature",
  "properties": {
    "iso:country":"ES",
    "sg:address":"Calle de Ribera De Curtidores, 47",
    "sg:city":"Madrid",
    "sg:orig_category":"Zapatos (al Por Menor)",
    "sg:phone":"+34 915 28 20 61",
    "sg:postcode":"28005",
    "sg:province":"Madrid",
    "wof:name":"Torres Campi\u00f1a Francisco",
    "wof:placetype":"venue"
},
  "geometry": {"coordinates":[-3.7065529823,40.4041442871],"type":"Point"}
}