{
  "type": "Feature",
  "properties": {
    "iso:country":"ES",
    "sg:address":"Calle de Gutenberg, 131",
    "sg:city":"Poligono Industrial Los Villares",
    "sg:orig_category":"Lavado, Limpieza De Veh\u00cdculos",
    "sg:phone":"+34 923 20 43 51",
    "sg:postcode":"37184",
    "sg:province":"Salamanca",
    "wof:name":"Engrases Anselmo S.l.l",
    "wof:placetype":"venue"
},
  "geometry": {"coordinates":[-5.6355609894,40.9907150269],"type":"Point"}
}