{
  "type": "Feature",
  "properties": {
    "addr:full":"Carrer de Dega Bahi, 16 Barcelona Barcelona 08026",
    "addr:housenumber":"16",
    "addr:postcode":"08026",
    "addr:street":"Carrer De Dega Bahi",
    "iso:country":"ES",
    "sg:address":"Carrer de Dega Bahi, 16",
    "sg:city":"Barcelona",
    "sg:orig_category":"Peluqueros: De Se\u00d1oras",
    "sg:phone":"+34 933 47 38 15",
    "sg:postcode":"08026",
    "sg:province":"Barcelona",
    "wof:name":"Rangel Fraile Julia",
    "wof:placetype":"venue"
},
  "geometry": {"coordinates":[2.1837399006,41.4109954834],"type":"Point"}
}