{
  "type": "Feature",
  "properties": {
    "addr:full":"Calle de Martinez De Medina, 2 Sevilla Sevilla 41018",
    "addr:housenumber":"2",
    "addr:postcode":"41018",
    "addr:street":"Calle De Martinez De Medina",
    "iso:country":"ES",
    "sg:address":"Calle de Martinez De Medina, 2",
    "sg:city":"Sevilla",
    "sg:orig_category":"Internados & Ense\u00d1anza Privada",
    "sg:phone":"+34 954 53 02 64",
    "sg:postcode":"41018",
    "sg:province":"Sevilla",
    "wof:name":"Colegio Buen Pastor S.l.",
    "wof:placetype":"venue"
},
  "geometry": {"coordinates":[-5.97371912,37.3849411011],"type":"Point"}
}