{
  "type": "Feature",
  "properties": {
    "iso:country":"ES",
    "sg:address":"Plgo. I. Merindades, S/n",
    "sg:city":"Villarcayo",
    "sg:orig_category":"Empresas De Carpinter\u00cda De Madera",
    "sg:phone":"+34 947 13 12 53",
    "sg:postcode":"09550",
    "sg:province":"Burgos",
    "wof:name":"Carpinteria Praygar S.l.",
    "wof:placetype":"venue"
},
  "geometry": {"coordinates":[-3.5794770718,42.926776886],"type":"Point"}
}