{
  "type": "Feature",
  "properties": {
    "addr:full":"Ctra Bigastro, Km. 0001,0 Correntias Medias Alicante 03300",
    "addr:postcode":"03300",
    "addr:street":"Ctra Bigastro Km. 0001,0 Correntias",
    "iso:country":"ES",
    "sg:address":"Ctra Bigastro, Km. 0001,0",
    "sg:city":"Correntias Medias",
    "sg:orig_category":"Reciclaje, Tratamiento De Pl\u00c1sticos",
    "sg:phone":"+34 966 74 33 64",
    "sg:postcode":"03300",
    "sg:province":"Alicante",
    "wof:name":"Genesis Persianas Y Plasticos S.l.",
    "wof:placetype":"venue"
},
  "geometry": {"coordinates":[-0.9460989833,38.0866203308],"type":"Point"}
}