{
  "type": "Feature",
  "properties": {
    "iso:country":"ES",
    "sg:address":"Carrer de Sant Gil, 16",
    "sg:city":"Barcelona",
    "sg:orig_category":"Grafistas",
    "sg:phone":"+34 934 42 17 86",
    "sg:postcode":"08001",
    "sg:province":"Barcelona",
    "sg:website":"www.ques-tions.net",
    "wof:name":"Valles Lopez Cristina",
    "wof:placetype":"venue"
},
  "geometry": {"coordinates":[2.1637840271,41.3808898926],"type":"Point"}
}