{
  "type": "Feature",
  "properties": {
    "addr:full":"Calle de Manuel Aleixandre, 164 Pinos De Alhaurin M\u00e1laga 29130",
    "addr:housenumber":"164",
    "addr:postcode":"29130",
    "addr:street":"Calle De Manuel Aleixandre",
    "iso:country":"ES",
    "sg:address":"Calle de Manuel Aleixandre, 164",
    "sg:city":"Pinos De Alhaurin",
    "sg:orig_category":"Calcoman\u00cda, Impresi\u00d3n, Transferencia (transfert)",
    "sg:phone":"+34 952 41 51 05",
    "sg:postcode":"29130",
    "sg:province":"M\u00e1laga",
    "wof:name":"Codice Transfer Factory S.l.l.",
    "wof:placetype":"venue"
},
  "geometry": {"coordinates":[-4.5941410065,36.6464424133],"type":"Point"}
}