{
  "type": "Feature",
  "properties": {
    "addr:full":"Salbador Kalea, 2 Elgeta Guip\u00f9zcoa 20690",
    "addr:housenumber":"2",
    "addr:postcode":"20690",
    "addr:street":"Salbador Kalea;Guipu\u0300Zcoa",
    "iso:country":"ES",
    "sg:address":"Salbador Kalea, 2",
    "sg:city":"Elgeta",
    "sg:orig_category":"Medicamentos",
    "sg:phone":"+34 943 76 81 50",
    "sg:postcode":"20690",
    "sg:province":"Guip\u00f9zcoa",
    "wof:name":"Elcoro Galdos Elena",
    "wof:placetype":"venue"
},
  "geometry": {"coordinates":[-2.4879999161,43.1366844177],"type":"Point"}
}