{
  "type": "Feature",
  "properties": {
    "addr:full":"Calle de Zaragoza, 8 Binefar Huesca 22500",
    "addr:housenumber":"8",
    "addr:postcode":"22500",
    "addr:street":"Calle De Zaragoza",
    "iso:country":"ES",
    "sg:address":"Calle de Zaragoza, 8",
    "sg:city":"Binefar",
    "sg:orig_category":"Juegos Y Juguetes (al Por Menor)",
    "sg:phone":"+34 974 42 96 44",
    "sg:postcode":"22500",
    "sg:province":"Huesca",
    "wof:name":"Maench Olle Montserat",
    "wof:placetype":"venue"
},
  "geometry": {"coordinates":[0.2926307917,41.8501396179],"type":"Point"}
}