{
  "type": "Feature",
  "properties": {
    "iso:country":"ES",
    "sg:address":"Calle de Monte, 1",
    "sg:city":"Yepes",
    "sg:orig_category":"Venta, Montaje De Neum\u00c1ticos",
    "sg:phone":"+34 925 15 48 31",
    "sg:postcode":"45313",
    "sg:province":"Toledo",
    "wof:name":"Lopez-palomino Diaz-mayordomo Anastasio",
    "wof:placetype":"venue"
},
  "geometry": {"coordinates":[-3.6292641163,39.9054718018],"type":"Point"}
}