{
  "type": "Feature",
  "properties": {
    "iso:country":"ES",
    "sg:address":"Bisbe Sever, 26",
    "sg:city":"Ferreries",
    "sg:orig_category":"Inform\u00c1tica, Ofim\u00c1tica (estudios, Asesor\u00cda, Ingenier\u00cda, Formaci\u00d3n)",
    "sg:phone":"+34 971 37 35 37",
    "sg:postcode":"07750",
    "sg:province":"Islas Baleares",
    "wof:name":"Reset Informatica Ferreries S.c.",
    "wof:placetype":"venue"
},
  "geometry": {"coordinates":[4.0123181343,39.9834938049],"type":"Point"}
}