{
  "type": "Feature",
  "properties": {
    "addr:full":"Calle de Zuloaga, 2 Jerez De La Frontera C\u00e1diz 11405",
    "addr:housenumber":"2",
    "addr:postcode":"11405",
    "addr:street":"Calle De Zuloaga",
    "iso:country":"ES",
    "sg:address":"Calle de Zuloaga, 2",
    "sg:city":"Jerez De La Frontera",
    "sg:orig_category":"Contenedores (mercanc\u00cdas)",
    "sg:phone":"+34 956 30 42 08",
    "sg:postcode":"11405",
    "sg:province":"C\u00e1diz",
    "wof:name":"Soto Ramirez Jose Maria",
    "wof:placetype":"venue"
},
  "geometry": {"coordinates":[-6.0982108116,36.6971931458],"type":"Point"}
}