{
  "type": "Feature",
  "properties": {
    "addr:full":"Calle de Lonja, 1 Rozas De Madrid Madrid 28230",
    "addr:housenumber":"1",
    "addr:postcode":"28230",
    "addr:street":"Calle De Lonja",
    "iso:country":"ES",
    "sg:address":"Calle de Lonja, 1",
    "sg:city":"Rozas De Madrid",
    "sg:orig_category":"Administradores De Bienes Y Delegados De Comunidades De Propietarios",
    "sg:phone":"+34 916 37 37 42",
    "sg:postcode":"28230",
    "sg:province":"Madrid",
    "wof:name":"Bellido Perez Jose",
    "wof:placetype":"venue"
},
  "geometry": {"coordinates":[-3.8744590282,40.4924926758],"type":"Point"}
}