{
  "type": "Feature",
  "properties": {
    "iso:country":"ES",
    "sg:address":"Rua Formosende, 15",
    "sg:city":"Formosende",
    "sg:orig_category":"Reposter\u00cdas",
    "sg:phone":"+34 981 34 03 40",
    "sg:postcode":"15500",
    "sg:province":"A Coru\u00f1a",
    "wof:name":"Vilar Fernandez Jose Manuel",
    "wof:placetype":"venue"
},
  "geometry": {"coordinates":[-8.1644191742,43.4750747681],"type":"Point"}
}