{
  "type": "Feature",
  "properties": {
    "addr:full":"Rond Sancti Spiritus, 24 Salamanca Salamanca 37001",
    "addr:housenumber":"24",
    "addr:postcode":"37001",
    "addr:street":"Rond Sancti Spiritus",
    "iso:country":"ES",
    "sg:address":"Rond Sancti Spiritus, 24",
    "sg:city":"Salamanca",
    "sg:orig_category":"Iglesia Cat\u00d3lica",
    "sg:phone":"+34 923 26 91 15",
    "sg:postcode":"37001",
    "sg:province":"Salamanca",
    "wof:name":"Parroquia De Sancti-spiritus",
    "wof:placetype":"venue"
},
  "geometry": {"coordinates":[-5.6589508057,40.9648323059],"type":"Point"}
}