{
  "type": "Feature",
  "properties": {
    "iso:country":"ES",
    "sg:address":"Calle de Castan Tobe\u00d1as, 65",
    "sg:city":"Valencia",
    "sg:orig_category":"Molduras, Junquillos, Listones Y Molduras Perforadas",
    "sg:phone":"+34 963 83 83 36",
    "sg:postcode":"46018",
    "sg:province":"Valencia",
    "wof:name":"Rodriguez Vieira Manuel",
    "wof:placetype":"venue"
},
  "geometry": {"coordinates":[-0.4018892944,39.4728126526],"type":"Point"}
}