{
  "type": "Feature",
  "properties": {
    "iso:country":"ES",
    "sg:address":"Ctra Madrid-cadiz, Km. 0171,0",
    "sg:city":"Manzanares",
    "sg:orig_category":"Material Y Herramientas Agr\u00cdcolas",
    "sg:phone":"+34 926 61 07 31",
    "sg:postcode":"13200",
    "sg:province":"Ciudad Real",
    "sg:website":"www.riegoslozano.com",
    "wof:name":"Riegos Lozano S.a.",
    "wof:placetype":"venue"
},
  "geometry": {"coordinates":[-3.373128891,38.994140625],"type":"Point"}
}