{
  "type": "Feature",
  "properties": {
    "iso:country":"ES",
    "sg:address":"Calle de Beatas, 17",
    "sg:city":"Malaga",
    "sg:orig_category":"Abogados",
    "sg:phone":"+34 952 21 97 25",
    "sg:postcode":"29008",
    "sg:province":"M\u00e1laga",
    "wof:name":"Souviron Garcia Federico Javier",
    "wof:placetype":"venue"
},
  "geometry": {"coordinates":[-4.419672966,36.723274231],"type":"Point"}
}