{
  "type": "Feature",
  "properties": {
    "iso:country":"ES",
    "sg:address":"Calle de Libertad (de La), 5",
    "sg:city":"Mostoles",
    "sg:orig_category":"Guarder\u00cdas",
    "sg:phone":"+34 916 46 69 99",
    "sg:postcode":"28936",
    "sg:province":"Madrid",
    "wof:name":"Centro Infantil Tobogan S.l.",
    "wof:placetype":"venue"
},
  "geometry": {"coordinates":[-3.8552370071,40.3291168213],"type":"Point"}
}