{
  "type": "Feature",
  "properties": {
    "iso:country":"ES",
    "sg:address":"Calle de Freniche, S/n",
    "sg:city":"Almeria",
    "sg:orig_category":"Autob\u00das (explotaci\u00d3n Y Servicios De)",
    "sg:phone":"+34 950 62 47 35",
    "sg:postcode":"04009",
    "sg:province":"Almer\u00eda",
    "wof:name":"Transportes Alsina Graell Sur S.a.",
    "wof:placetype":"venue"
},
  "geometry": {"coordinates":[-2.4485709667,36.8561401367],"type":"Point"}
}