{
  "type": "Feature",
  "properties": {
    "addr:full":"Ctra S Pedro S Javier, S/n S. Pedro Pinatar Murcia 30740",
    "addr:postcode":"30740",
    "addr:street":"Ctra S Pedro S Javier S / N S. Pedro",
    "iso:country":"ES",
    "sg:address":"Ctra S Pedro S Javier, S/n",
    "sg:city":"S. Pedro Pinatar",
    "sg:orig_category":"Ahumados Y Salazones",
    "sg:phone":"+34 968 18 53 40",
    "sg:postcode":"30740",
    "sg:province":"Murcia",
    "wof:name":"Salazones Garre S.l.",
    "wof:placetype":"venue"
},
  "geometry": {"coordinates":[-0.7932540178,37.8340911865],"type":"Point"}
}