{
  "type": "Feature",
  "properties": {
    "iso:country":"ES",
    "sg:address":"Carr Academia, 2",
    "sg:city":"Lleida",
    "sg:orig_category":"Ingenier\u00cda, Centros De Estudios (diversos)",
    "sg:phone":"+34 973 28 09 80",
    "sg:postcode":"25002",
    "sg:province":"Lleida",
    "wof:name":"Einesa Ingenieria S.l.",
    "wof:placetype":"venue"
},
  "geometry": {"coordinates":[0.6200399995,41.6116600037],"type":"Point"}
}