{
  "type": "Feature",
  "properties": {
    "iso:country":"ES",
    "sg:address":"Calle de Aluminio, 65",
    "sg:city":"Moraleja Enmedio",
    "sg:orig_category":"Suministros Para Hoteles",
    "sg:phone":"+34 916 09 46 71",
    "sg:postcode":"28950",
    "sg:province":"Madrid",
    "wof:name":"Numensat S.l.",
    "wof:placetype":"venue"
},
  "geometry": {"coordinates":[-3.8495328426,40.2654762268],"type":"Point"}
}