{
  "type": "Feature",
  "properties": {
    "addr:full":"Bard Miraflores, S/n Antequera M\u00e1laga 29200",
    "addr:housenumber":"s",
    "addr:postcode":"29200",
    "addr:street":"Miraflores;/ N;Ma\u0301Laga",
    "iso:country":"ES",
    "sg:address":"Bard Miraflores, S/n",
    "sg:city":"Antequera",
    "sg:orig_category":"Mec\u00c1nico Del Autom\u00d3vil",
    "sg:phone":"+34 952 84 46 09",
    "sg:postcode":"29200",
    "sg:province":"M\u00e1laga",
    "wof:name":"Garcia Nu\u00f1ez Manuel",
    "wof:placetype":"venue"
},
  "geometry": {"coordinates":[-4.5211935043,36.9971008301],"type":"Point"}
}