{
  "type": "Feature",
  "properties": {
    "iso:country":"ES",
    "sg:address":"Calle de Virgen De La Vega, 44",
    "sg:city":"Haro",
    "sg:orig_category":"Fisioterapia",
    "sg:phone":"+34 941 30 40 89",
    "sg:postcode":"26200",
    "sg:province":"La Rioja",
    "wof:name":"Fisioterapia Y Osteopatia Atlas S.l.",
    "wof:placetype":"venue"
},
  "geometry": {"coordinates":[-2.8507230282,42.5762023926],"type":"Point"}
}