{
  "type": "Feature",
  "properties": {
    "iso:country":"ES",
    "sg:address":"Calle de Nicolas Gomez Gonzalez, 15",
    "sg:city":"Palma Condado",
    "sg:orig_category":"Imprenta",
    "sg:phone":"+34 959 40 01 87",
    "sg:postcode":"21700",
    "sg:province":"Huelva",
    "wof:name":"Imprenta Y Papeleria Union S.l.",
    "wof:placetype":"venue"
},
  "geometry": {"coordinates":[-6.5555171967,37.389831543],"type":"Point"}
}