{
  "type": "Feature",
  "properties": {
    "addr:full":"Luga Chalets Rodeo Tres, S/n Rodeo Tercero O De Los Tenderos Murcia 30191",
    "addr:housenumber":"s / n",
    "addr:postcode":"30191",
    "iso:country":"ES",
    "sg:address":"Luga Chalets Rodeo Tres, S/n",
    "sg:city":"Rodeo Tercero O De Los Tenderos",
    "sg:orig_category":"Cr\u00cda De Cerdos",
    "sg:phone":"+34 968 43 14 99",
    "sg:postcode":"30191",
    "sg:province":"Murcia",
    "wof:name":"Aryversa S.a.",
    "wof:placetype":"venue"
},
  "geometry": {"coordinates":[-1.1298867464,37.9834747314],"type":"Point"}
}