{
  "type": "Feature",
  "properties": {
    "iso:country":"ES",
    "sg:address":"Calle de Tirso De Molina, 9",
    "sg:city":"Malaga",
    "sg:orig_category":"Agencias Y Agentes Comerciales, Representantes",
    "sg:phone":"+34 952 26 05 23",
    "sg:postcode":"29013",
    "sg:province":"M\u00e1laga",
    "wof:name":"Martin Nu\u00f1ez Jose Carlos",
    "wof:placetype":"venue"
},
  "geometry": {"coordinates":[-4.4243597984,36.7277183533],"type":"Point"}
}