{
  "type": "Feature",
  "properties": {
    "addr:full":"Rua Emilia Pardo Bazan, 11 Melide La Coru\u00f1a 15800",
    "addr:housenumber":"11",
    "addr:postcode":"15800",
    "addr:street":"Rua Emilia Pardo Bazan;La Corun\u0303A",
    "iso:country":"ES",
    "sg:address":"Rua Emilia Pardo Bazan, 11",
    "sg:city":"Melide",
    "sg:orig_category":"Tintes (fabricaci\u00d3n, Al Por Mayor)",
    "sg:phone":"+34 981 50 78 06",
    "sg:postcode":"15800",
    "sg:province":"La Coru\u00f1a",
    "wof:name":"Iris Melide S.l.",
    "wof:placetype":"venue"
},
  "geometry": {"coordinates":[-8.0127067566,42.9148025513],"type":"Point"}
}