{
  "type": "Feature",
  "properties": {
    "addr:full":"Carr Carme, 241 Girona Girona 17004",
    "addr:housenumber":"241",
    "addr:postcode":"17004",
    "addr:street":"Carr Carme",
    "iso:country":"ES",
    "sg:address":"Carr Carme, 241",
    "sg:city":"Girona",
    "sg:orig_category":"M\u00c1rmoles, Granitos Y Piedras Naturales",
    "sg:phone":"+34 972 22 42 53",
    "sg:postcode":"17004",
    "sg:province":"Girona",
    "wof:name":"Lapides I Marbres Rustey S.l.",
    "wof:placetype":"venue"
},
  "geometry": {"coordinates":[2.828469038,41.9742736816],"type":"Point"}
}