{
  "type": "Feature",
  "properties": {
    "iso:country":"ES",
    "sg:address":"Calle de San Jacinto, 90",
    "sg:city":"Sevilla",
    "sg:orig_category":"Estancos",
    "sg:phone":"+34 954 33 37 35",
    "sg:postcode":"41010",
    "sg:province":"Sevilla",
    "sg:website":"www.cavapuros.com",
    "wof:name":"Duarte Luque Jorge",
    "wof:placetype":"venue"
},
  "geometry": {"coordinates":[-6.0074338913,37.382194519],"type":"Point"}
}