{
  "type": "Feature",
  "properties": {
    "iso:country":"ES",
    "sg:address":"Avda Judimendi, 12",
    "sg:city":"Vitoria-gasteiz",
    "sg:orig_category":"Herboristas (al Por Menor)",
    "sg:phone":"+34 945 26 81 18",
    "sg:postcode":"01003",
    "sg:province":"\u00c1lava",
    "wof:name":"Rimak Dietetica S.l.",
    "wof:placetype":"venue"
},
  "geometry": {"coordinates":[-2.6615378857,42.8468551636],"type":"Point"}
}