{
  "type": "Feature",
  "properties": {
    "addr:full":"Ctra Extremadura (zona Ind Camas), Km. 0535,0 Camas Sevilla 41900",
    "addr:housenumber":"km.",
    "addr:postcode":"41900",
    "addr:street":"Ctra Extremadura Zona Ind Camas;0535,0 Camas",
    "iso:country":"ES",
    "sg:address":"Ctra Extremadura (zona Ind Camas), Km. 0535,0",
    "sg:city":"Camas",
    "sg:orig_category":"Mec\u00c1nico Del Autom\u00d3vil",
    "sg:phone":"+34 954 39 04 33",
    "sg:postcode":"41900",
    "sg:province":"Sevilla",
    "wof:name":"Honorio Romero E Hijos S.l.",
    "wof:placetype":"venue"
},
  "geometry": {"coordinates":[-6.0344491005,37.4007263184],"type":"Point"}
}