{
  "type": "Feature",
  "properties": {
    "iso:country":"ES",
    "sg:address":"Ctra Vic, S/n",
    "sg:city":"S. Fruitos Bages",
    "sg:orig_category":"Tratamiento De Metales",
    "sg:phone":"+34 938 73 09 08",
    "sg:postcode":"08272",
    "sg:province":"Barcelona",
    "wof:name":"Comercial De Tratamientos Termicos S.a.",
    "wof:placetype":"venue"
},
  "geometry": {"coordinates":[1.8738100529,41.7506446838],"type":"Point"}
}