{
  "type": "Feature",
  "properties": {
    "addr:full":"Ctra Alicante-cartagena, Km. 0063,3 Torrelamata Alicante 03188",
    "addr:postcode":"03188",
    "addr:street":"Ctra Alicante-Cartagena Km. 0063,3",
    "iso:country":"ES",
    "sg:address":"Ctra Alicante-cartagena, Km. 0063,3",
    "sg:city":"Torrelamata",
    "sg:orig_category":"Distribuci\u00d3n De Petr\u00d3leo Y Derivados",
    "sg:phone":"+34 966 92 01 52",
    "sg:postcode":"03188",
    "sg:province":"Alicante",
    "sg:website":"www.cepsa.es",
    "wof:name":"Cedipsa Compa\u00d1ia Espa\u00d1ola Distribuidora De Petroleos S.a.",
    "wof:placetype":"venue"
},
  "geometry": {"coordinates":[-0.6580709815,38.0311698914],"type":"Point"}
}