{
  "type": "Feature",
  "properties": {
    "addr:full":"Calle de Mayor, 20 Berantevilla \u00c1lava 01218",
    "addr:housenumber":"20",
    "addr:postcode":"01218",
    "addr:street":"Calle De Mayor;A\u0301Lava",
    "iso:country":"ES",
    "sg:address":"Calle de Mayor, 20",
    "sg:city":"Berantevilla",
    "sg:orig_category":"Cajas De Ahorro",
    "sg:phone":"+34 945 33 71 27",
    "sg:postcode":"01218",
    "sg:province":"\u00c1lava",
    "wof:name":"Caja De Ahorros De Vitoria Y Alava",
    "wof:placetype":"venue"
},
  "geometry": {"coordinates":[-2.859539032,42.6825485229],"type":"Point"}
}