{
  "type": "Feature",
  "properties": {
    "addr:full":"Carrer de Goya, 6 Barcelona Barcelona 08012",
    "addr:housenumber":"6",
    "addr:postcode":"08012",
    "addr:street":"Carrer De Goya",
    "iso:country":"ES",
    "sg:address":"Carrer de Goya, 6",
    "sg:city":"Barcelona",
    "sg:orig_category":"Tintes (fabricaci\u00d3n, Al Por Mayor)",
    "sg:phone":"+34 932 18 28 21",
    "sg:postcode":"08012",
    "sg:province":"Barcelona",
    "wof:name":"Casanyas Vila Francina",
    "wof:placetype":"venue"
},
  "geometry": {"coordinates":[2.1568489075,41.3992004395],"type":"Point"}
}