{
  "type": "Feature",
  "properties": {
    "iso:country":"ES",
    "sg:address":"Calle de Mariano Baselga, 5",
    "sg:city":"Zaragoza",
    "sg:orig_category":"Contenedores (mercanc\u00cdas)",
    "sg:phone":"+34 976 51 93 20",
    "sg:postcode":"50015",
    "sg:province":"Zaragoza",
    "wof:name":"Subias Perna Bienvenido",
    "wof:placetype":"venue"
},
  "geometry": {"coordinates":[-0.876835227,41.6608772278],"type":"Point"}
}