{
  "type": "Feature",
  "properties": {
    "addr:full":"Ptge Pompeu, 4 Lleida Lleida 25006",
    "addr:housenumber":"4",
    "addr:postcode":"25006",
    "addr:street":"Ptge Pompeu",
    "iso:country":"ES",
    "sg:address":"Ptge Pompeu, 4",
    "sg:city":"Lleida",
    "sg:orig_category":"Asociaciones, Organismos Culturales Y Socioeducativos",
    "sg:phone":"+34 973 22 47 84",
    "sg:postcode":"25006",
    "sg:province":"Lleida",
    "wof:name":"Club Estel",
    "wof:placetype":"venue"
},
  "geometry": {"coordinates":[0.6197850108,41.6199226379],"type":"Point"}
}