{
  "type": "Feature",
  "properties": {
    "addr:full":"Avda Barca, 24 Barca Pontevedra 36005",
    "addr:housenumber":"24",
    "addr:postcode":"36005",
    "addr:street":"Avda Barca",
    "iso:country":"ES",
    "sg:address":"Avda Barca, 24",
    "sg:city":"Barca",
    "sg:orig_category":"Reposter\u00cdas",
    "sg:phone":"+34 986 87 28 46",
    "sg:postcode":"36005",
    "sg:province":"Pontevedra",
    "wof:name":"Del Rio Panificacion S.l.",
    "wof:placetype":"venue"
},
  "geometry": {"coordinates":[-8.6331739426,42.4493751526],"type":"Point"}
}