{
  "type": "Feature",
  "properties": {
    "addr:full":"Calle de General Villacampa, 8 Sabi\u00f1anigo Huesca 22600",
    "addr:housenumber":"8",
    "addr:postcode":"22600",
    "addr:street":"Calle De General Villacampa",
    "iso:country":"ES",
    "sg:address":"Calle de General Villacampa, 8",
    "sg:city":"Sabi\u00f1anigo",
    "sg:orig_category":"Mec\u00c1nico Del Autom\u00d3vil",
    "sg:phone":"+34 974 48 23 36",
    "sg:postcode":"22600",
    "sg:province":"Huesca",
    "wof:name":"Hernandez Sanchez Andres",
    "wof:placetype":"venue"
},
  "geometry": {"coordinates":[-0.3629882932,42.5201263428],"type":"Point"}
}