{
  "type": "Feature",
  "properties": {
    "iso:country":"ES",
    "sg:address":"Calle de Bujaraloz, 8",
    "sg:city":"Caspe",
    "sg:orig_category":"Agentes, Concesionarios Y Sucursales De Veh\u00cdculos",
    "sg:phone":"+34 976 63 16 44",
    "sg:postcode":"50700",
    "sg:province":"Zaragoza",
    "wof:name":"Talleres Poblador S. L.",
    "wof:placetype":"venue"
},
  "geometry": {"coordinates":[-0.0353940018,41.2268028259],"type":"Point"}
}