{
  "type": "Feature",
  "properties": {
    "iso:country":"ES",
    "sg:address":"Avda Guerrita, 18",
    "sg:city":"Cordoba",
    "sg:orig_category":"Restaurantes",
    "sg:phone":"+34 957 45 44 70",
    "sg:postcode":"14005",
    "sg:province":"C\u00f3rdoba",
    "wof:name":"Guerrita S.l.",
    "wof:placetype":"venue"
},
  "geometry": {"coordinates":[-4.7951102257,37.8785133362],"type":"Point"}
}