{
  "type": "Feature",
  "properties": {
    "addr:full":"Calle de Federico Ozanan, 31 Zaragoza Zaragoza 50012",
    "addr:housenumber":"31",
    "addr:postcode":"50012",
    "addr:street":"Calle De Federico Ozanan",
    "iso:country":"ES",
    "sg:address":"Calle de Federico Ozanan, 31",
    "sg:city":"Zaragoza",
    "sg:orig_category":"Centros De Coordinaci\u00d3n",
    "sg:phone":"+34 976 45 87 80",
    "sg:postcode":"50012",
    "sg:province":"Zaragoza",
    "wof:name":"Gestoria Esteban S.l.",
    "wof:placetype":"venue"
},
  "geometry": {"coordinates":[-0.9321736097,41.640171051],"type":"Point"}
}