{
  "type": "Feature",
  "properties": {
    "addr:full":"Avda Union Europea De La, S/n Huelva Huelva 21002",
    "addr:postcode":"21002",
    "addr:street":"Avda Union Europea De La S / N",
    "iso:country":"ES",
    "sg:address":"Avda Union Europea De La, S/n",
    "sg:city":"Huelva",
    "sg:orig_category":"Electricidad, Electr\u00d3nica: Material Y Suministros (al Por Mayor)",
    "sg:phone":"+34 959 24 00 94",
    "sg:postcode":"21002",
    "sg:province":"Huelva",
    "wof:name":"Onulec S.l.",
    "wof:placetype":"venue"
},
  "geometry": {"coordinates":[-6.9506139755,37.2717285156],"type":"Point"}
}