{
  "type": "Feature",
  "properties": {
    "addr:full":"Avda Cerro De Los Angeles, 18 Madrid Madrid 28026",
    "addr:housenumber":"18",
    "addr:postcode":"madrid;28026",
    "addr:street":"Avda Cerro De Los Angeles",
    "iso:country":"ES",
    "sg:address":"Avda Cerro De Los Angeles, 18",
    "sg:city":"Madrid",
    "sg:orig_category":"Electricidad Veh\u00cdculo",
    "sg:phone":"+34 915 65 27 01",
    "sg:postcode":"28026",
    "sg:province":"Madrid",
    "wof:name":"Garcia Garcia Jose Manuel",
    "wof:placetype":"venue"
},
  "geometry": {"coordinates":[-3.7127270699,40.3790168762],"type":"Point"}
}