{
  "type": "Feature",
  "properties": {
    "iso:country":"ES",
    "sg:address":"Calle de Constitucion, 21",
    "sg:city":"Requena",
    "sg:orig_category":"Ropa Y Art\u00cdculos Pre",
    "sg:phone":"+34 962 30 13 17",
    "sg:postcode":"46340",
    "sg:province":"Valencia",
    "wof:name":"Ochando Martinez Luis",
    "wof:placetype":"venue"
},
  "geometry": {"coordinates":[-1.0984330177,39.4884719849],"type":"Point"}
}