{
  "type": "Feature",
  "properties": {
    "addr:full":"Calle de Andres Lopez Palmeiro, 2 Ferreira Lugo 27770",
    "addr:housenumber":"2",
    "addr:postcode":"27770",
    "addr:street":"Calle De Andres Lopez Palmeiro",
    "iso:country":"ES",
    "sg:address":"Calle de Andres Lopez Palmeiro, 2",
    "sg:city":"Ferreira",
    "sg:orig_category":"Plomeros",
    "sg:phone":"+34 982 57 41 59",
    "sg:postcode":"27770",
    "sg:province":"Lugo",
    "wof:name":"Perez Eijo Antonio",
    "wof:placetype":"venue"
},
  "geometry": {"coordinates":[-7.4817819595,43.5736885071],"type":"Point"}
}