{
  "type": "Feature",
  "properties": {
    "iso:country":"ES",
    "sg:address":"Calle de Recoletas, 4",
    "sg:city":"Miranda Ebro",
    "sg:orig_category":"Asesor\u00cda Fiscal Y Jur\u00cddica",
    "sg:phone":"+34 947 33 23 06",
    "sg:postcode":"09200",
    "sg:province":"Burgos",
    "wof:name":"Balbuena Grupo Asesor Auditor S.c.",
    "wof:placetype":"venue"
},
  "geometry": {"coordinates":[-2.9675571918,42.6790657043],"type":"Point"}
}