{
  "type": "Feature",
  "properties": {
    "addr:full":"Calle de La Rasa, 90 Terrassa Barcelona 08221",
    "addr:housenumber":"90",
    "addr:postcode":"08221",
    "addr:street":"Calle De La Rasa",
    "iso:country":"ES",
    "sg:address":"Calle de La Rasa, 90",
    "sg:city":"Terrassa",
    "sg:orig_category":"Pantallas, Mamparas Y Accesorios (fabricaci\u00d3n)",
    "sg:phone":"+34 937 88 19 49",
    "sg:postcode":"08221",
    "sg:province":"Barcelona",
    "wof:name":"Mallofre Graells Rosa",
    "wof:placetype":"venue"
},
  "geometry": {"coordinates":[2.0092310905,41.5641098022],"type":"Point"}
}