{
  "type": "Feature",
  "properties": {
    "addr:full":"Calle de Eduardo Marquina, 8 Avila \u00c1vila 05001",
    "addr:housenumber":"8",
    "addr:postcode":"05001",
    "addr:street":"Calle De Eduardo Marquina;A\u0301Vila",
    "iso:country":"ES",
    "sg:address":"Calle de Eduardo Marquina, 8",
    "sg:city":"Avila",
    "sg:orig_category":"Agentes Generales De Seguros",
    "sg:phone":"+34 920 25 07 64",
    "sg:postcode":"05001",
    "sg:province":"\u00c1vila",
    "wof:name":"Guimar Asesores S.l.",
    "wof:placetype":"venue"
},
  "geometry": {"coordinates":[-4.6939845085,40.6566619873],"type":"Point"}
}