{
  "type": "Feature",
  "properties": {
    "addr:full":"La Cachurra, 9 Negreira La Coru\u00f1a 15830",
    "addr:housenumber":"9",
    "addr:postcode":"15830",
    "addr:street":"Cachurra;La Corun\u0303A",
    "iso:country":"ES",
    "sg:address":"La Cachurra, 9",
    "sg:city":"Negreira",
    "sg:orig_category":"Bancos",
    "sg:phone":"+34 981 88 53 59",
    "sg:postcode":"15830",
    "sg:province":"La Coru\u00f1a",
    "wof:name":"Banco De Galicia",
    "wof:placetype":"venue"
},
  "geometry": {"coordinates":[-8.7369537354,42.9097671509],"type":"Point"}
}