{
  "type": "Feature",
  "properties": {
    "iso:country":"ES",
    "sg:address":"Rbla Arago, 17",
    "sg:city":"Lleida",
    "sg:orig_category":"Guarder\u00cdas",
    "sg:phone":"+34 973 26 91 12",
    "sg:postcode":"25003",
    "sg:province":"Lleida",
    "wof:name":"Alba Perez Maria Jose",
    "wof:placetype":"venue"
},
  "geometry": {"coordinates":[0.6196671724,41.6131134033],"type":"Point"}
}