{
  "type": "Feature",
  "properties": {
    "addr:full":"Calle de Mayor, 36 Murillo De Rio Leza La Rioja 26143",
    "addr:housenumber":"36",
    "addr:postcode":"26143",
    "addr:street":"Calle De Mayor;Rioja",
    "iso:country":"ES",
    "sg:address":"Calle de Mayor, 36",
    "sg:city":"Murillo De Rio Leza",
    "sg:orig_category":"Alimentaci\u00d3n General (al Por Menor)",
    "sg:phone":"+34 941 43 20 13",
    "sg:postcode":"26143",
    "sg:province":"La Rioja",
    "wof:name":"Fernandez Galilea Francisco",
    "wof:placetype":"venue"
},
  "geometry": {"coordinates":[-2.3255090714,42.401058197],"type":"Point"}
}