{
  "type": "Feature",
  "properties": {
    "addr:full":"Ctra. Nacional, S/n Larouco Ourense 32358",
    "addr:housenumber":"s / n",
    "addr:postcode":"32358",
    "addr:street":"Ctra. Nacional",
    "iso:country":"ES",
    "sg:address":"Ctra. Nacional, S/n",
    "sg:city":"Larouco",
    "sg:orig_category":"Quincaller\u00cda (al Por Menor)",
    "sg:phone":"+34 988 34 80 07",
    "sg:postcode":"32358",
    "sg:province":"Ourense",
    "wof:name":"Ramos Campos Odilo",
    "wof:placetype":"venue"
},
  "geometry": {"coordinates":[-7.1602640152,42.3461837769],"type":"Point"}
}