{
  "type": "Feature",
  "properties": {
    "iso:country":"ES",
    "sg:address":"Plaz Gabriel Y Galan, 3",
    "sg:city":"Salamanca",
    "sg:orig_category":"M\u00c9dicos: Medicina Interna",
    "sg:phone":"+34 923 22 08 77",
    "sg:postcode":"37005",
    "sg:province":"Salamanca",
    "wof:name":"Benavente Herrero Julian",
    "wof:placetype":"venue"
},
  "geometry": {"coordinates":[-5.662127018,40.9702606201],"type":"Point"}
}