{
  "type": "Feature",
  "properties": {
    "addr:full":"Agra De Ba\u00f1o, S/n Muros La Coru\u00f1a 15250",
    "addr:housenumber":"/ n",
    "addr:postcode":"15250",
    "addr:street":"Agra;Ban\u0303O S;La Corun\u0303A",
    "iso:country":"ES",
    "sg:address":"Agra De Ba\u00f1o, S/n",
    "sg:city":"Muros",
    "sg:orig_category":"Procuradores",
    "sg:phone":"+34 981 82 74 30",
    "sg:postcode":"15250",
    "sg:province":"La Coru\u00f1a",
    "wof:name":"Otero Ramos Ignacio",
    "wof:placetype":"venue"
},
  "geometry": {"coordinates":[-9.0576505661,42.7748222351],"type":"Point"}
}