{
  "type": "Feature",
  "properties": {
    "addr:full":"Calle de Iribar, 2 Donostia-san Sebastian Guip\u00f9zcoa 20018",
    "addr:housenumber":"2",
    "addr:postcode":"20018",
    "addr:street":"Calle De Iribar",
    "iso:country":"ES",
    "sg:address":"Calle de Iribar, 2",
    "sg:city":"Donostia-san Sebastian",
    "sg:orig_category":"Agencias Y Asesores De Publicidad",
    "sg:phone":"+34 943 22 38 22",
    "sg:postcode":"20018",
    "sg:province":"Guip\u00f9zcoa",
    "wof:name":"Medio 10 S.l.",
    "wof:placetype":"venue"
},
  "geometry": {"coordinates":[-2.0226299763,43.3030433655],"type":"Point"}
}