{
  "type": "Feature",
  "properties": {
    "addr:full":"Carr Era Carrera, 10 Les Lleida 25540",
    "addr:housenumber":"10",
    "addr:postcode":"25540",
    "addr:street":"Carr Era Carrera",
    "iso:country":"ES",
    "sg:address":"Carr Era Carrera, 10",
    "sg:city":"Les",
    "sg:orig_category":"Panader\u00cdas, Panader\u00cdas",
    "sg:phone":"+34 973 64 80 49",
    "sg:postcode":"25540",
    "sg:province":"Lleida",
    "wof:name":"Moreno Estevez Sccl",
    "wof:placetype":"venue"
},
  "geometry": {"coordinates":[0.7095199823,42.8099403381],"type":"Point"}
}