{
  "type": "Feature",
  "properties": {
    "iso:country":"ES",
    "sg:address":"Calle de Sierra Carbonera, 9",
    "sg:city":"Teruel",
    "sg:orig_category":"Doctores En Medicina",
    "sg:phone":"+34 978 60 88 38",
    "sg:postcode":"44002",
    "sg:province":"Teruel",
    "wof:name":"Gutierrez Corduente Angel",
    "wof:placetype":"venue"
},
  "geometry": {"coordinates":[-1.093675971,40.3265991211],"type":"Point"}
}