{
  "type": "Feature",
  "properties": {
    "addr:full":"Carr Portal, 8 Alfara De Algimia Valencia 46148",
    "addr:housenumber":"8",
    "addr:postcode":"46148",
    "addr:street":"Carr Portal",
    "iso:country":"ES",
    "sg:address":"Carr Portal, 8",
    "sg:city":"Alfara De Algimia",
    "sg:orig_category":"Producci\u00d3n De Abonos Y De Fertilizantes",
    "sg:phone":"+34 962 62 60 14",
    "sg:postcode":"46148",
    "sg:province":"Valencia",
    "wof:name":"Fito Garriga Armando",
    "wof:placetype":"venue"
},
  "geometry": {"coordinates":[-0.3624440134,39.7540664673],"type":"Point"}
}