{
  "type": "Feature",
  "properties": {
    "addr:full":"Calle de Doctor Faustino Blasco, 35 Alzira Valencia 46600",
    "addr:housenumber":"35",
    "addr:postcode":"46600",
    "addr:street":"Calle De Doctor Faustino Blasco",
    "iso:country":"ES",
    "sg:address":"Calle de Doctor Faustino Blasco, 35",
    "sg:city":"Alzira",
    "sg:orig_category":"Alimentaci\u00d3n General (al Por Menor)",
    "sg:phone":"+34 962 41 26 71",
    "sg:postcode":"46600",
    "sg:province":"Valencia",
    "wof:name":"Esteve Monerri Rafael",
    "wof:placetype":"venue"
},
  "geometry": {"coordinates":[-0.4394226968,39.1499938965],"type":"Point"}
}