{
  "type": "Feature",
  "properties": {
    "addr:full":"Calle de Santo Tomas De Aquino, 8 Alcantarilla Murcia 30820",
    "addr:housenumber":"8",
    "addr:postcode":"30820",
    "addr:street":"Calle De Santo",
    "iso:country":"ES",
    "sg:address":"Calle de Santo Tomas De Aquino, 8",
    "sg:city":"Alcantarilla",
    "sg:orig_category":"Transportes Por V\u00cdas Navegables",
    "sg:phone":"+34 968 80 05 42",
    "sg:postcode":"30820",
    "sg:province":"Murcia",
    "wof:name":"Garcia Picon Juan Alfonso",
    "wof:placetype":"venue"
},
  "geometry": {"coordinates":[-1.2194550037,37.9698677063],"type":"Point"}
}