{
  "type": "Feature",
  "properties": {
    "addr:full":"Carrer de Pompeu Fabra, 194 Terrassa Barcelona 08226",
    "addr:housenumber":"194",
    "addr:postcode":"08226",
    "addr:street":"Carrer De Pompeu Fabra",
    "iso:country":"ES",
    "sg:address":"Carrer de Pompeu Fabra, 194",
    "sg:city":"Terrassa",
    "sg:orig_category":"Mec\u00c1nico Del Autom\u00d3vil",
    "sg:phone":"+34 937 35 57 24",
    "sg:postcode":"08226",
    "sg:province":"Barcelona",
    "wof:name":"Autojam S. L.",
    "wof:placetype":"venue"
},
  "geometry": {"coordinates":[2.0235629082,41.5783195496],"type":"Point"}
}