{
  "type": "Feature",
  "properties": {
    "iso:country":"ES",
    "sg:address":"Avda Obispo Perez Caceres, 34",
    "sg:city":"G\u00fcimar",
    "sg:orig_category":"Telas Y Sedas (al Por Menor)",
    "sg:phone":"+34 922 51 03 13",
    "sg:postcode":"38500",
    "sg:province":"Santa Cruz De Tenerife",
    "wof:name":"Sucesores De Emilio Mosfi C.b",
    "wof:placetype":"venue"
},
  "geometry": {"coordinates":[-16.4106960297,28.3142261505],"type":"Point"}
}