{
  "type": "Feature",
  "properties": {
    "addr:full":"C/ Asuncion Parre\u00d1o Garcia, 65 Elche Alicante 03205",
    "addr:housenumber":"65",
    "addr:postcode":"03205",
    "addr:street":"C / Asuncion Parren\u0303O Garcia",
    "iso:country":"ES",
    "sg:address":"C/ Asuncion Parre\u00d1o Garcia, 65",
    "sg:city":"Elche",
    "sg:orig_category":"Empresas De Carpinter\u00cda",
    "sg:phone":"+34 966 66 50 66",
    "sg:postcode":"03205",
    "sg:province":"Alicante",
    "wof:name":"Casado Puertas Antonio Javier",
    "wof:placetype":"venue"
},
  "geometry": {"coordinates":[-0.7131479979,38.269153595],"type":"Point"}
}