{
  "type": "Feature",
  "properties": {
    "addr:full":"Carrer de Sindicat, 40 Palma Islas Baleares 07002",
    "addr:housenumber":"40",
    "addr:postcode":"07002",
    "addr:street":"Carrer De Sindicat",
    "iso:country":"ES",
    "sg:address":"Carrer de Sindicat, 40",
    "sg:city":"Palma",
    "sg:orig_category":"Panader\u00cdas, Panader\u00cdas",
    "sg:phone":"+34 971 71 11 34",
    "sg:postcode":"07002",
    "sg:province":"Islas Baleares",
    "wof:name":"Agueda Catalina Mas Vera Cdad.",
    "wof:placetype":"venue"
},
  "geometry": {"coordinates":[2.6543881893,39.5716362],"type":"Point"}
}