{
  "type": "Feature",
  "properties": {
    "iso:country":"ES",
    "sg:address":"Ctra. La Rambla, Km. 0003,2",
    "sg:city":"Montalban",
    "sg:orig_category":"Comercio De Carburantes",
    "sg:phone":"+34 957 31 04 91",
    "sg:postcode":"14548",
    "sg:province":"C\u00f3rdoba",
    "wof:name":"E.s. La Fuente S.l.",
    "wof:placetype":"venue"
},
  "geometry": {"coordinates":[-4.7487092018,37.5843391418],"type":"Point"}
}