{
  "type": "Feature",
  "properties": {
    "iso:country":"ES",
    "sg:address":"Rua Antonio Roson, 2",
    "sg:city":"Lugo",
    "sg:orig_category":"Molduras, Junquillos, Listones Y Molduras Perforadas",
    "sg:phone":"+34 982 25 45 79",
    "sg:postcode":"27002",
    "sg:province":"Lugo",
    "wof:name":"Recreativos Dandy S.l.",
    "wof:placetype":"venue"
},
  "geometry": {"coordinates":[-7.5468411446,42.9979133606],"type":"Point"}
}