{
  "type": "Feature",
  "properties": {
    "addr:full":"Pase Morella, 41 Castellon Castell\u00f3n 12006",
    "addr:housenumber":"41",
    "addr:postcode":"12006",
    "addr:street":"Morella",
    "iso:country":"ES",
    "sg:address":"Pase Morella, 41",
    "sg:city":"Castellon",
    "sg:orig_category":"Agentes, Concesionarios Y Sucursales De Camiones Y Veh\u00cdculos Industriales",
    "sg:phone":"+34 964 34 02 03",
    "sg:postcode":"12006",
    "sg:province":"Castell\u00f3n",
    "wof:name":"Josep Pallas Calpe S.l.",
    "wof:placetype":"venue"
},
  "geometry": {"coordinates":[-0.1292939931,40.0168533325],"type":"Point"}
}