{
  "type": "Feature",
  "properties": {
    "addr:full":"Carrer de Jesus, 2 Reus Tarragona 43201",
    "addr:housenumber":"2",
    "addr:postcode":"43201",
    "addr:street":"Carrer De Jesus",
    "iso:country":"ES",
    "sg:address":"Carrer de Jesus, 2",
    "sg:city":"Reus",
    "sg:orig_category":"Higiene, Belleza: Art\u00cdculos (al Por Menor)",
    "sg:phone":"+34 977 12 79 15",
    "sg:postcode":"43201",
    "sg:province":"Tarragona",
    "sg:website":"www.thebodyshop.es",
    "wof:name":"Mentrida Pisano Angel Santiago",
    "wof:placetype":"venue"
},
  "geometry": {"coordinates":[1.108643055,41.1546707153],"type":"Point"}
}