{
  "type": "Feature",
  "properties": {
    "iso:country":"ES",
    "sg:address":"Avgd Arquitecte Antoni Gilabert, 11",
    "sg:city":"Pedreguer",
    "sg:orig_category":"Arquitectos",
    "sg:phone":"+34 966 45 64 58",
    "sg:postcode":"03750",
    "sg:province":"Alicante",
    "wof:name":"Arquimizara Sl",
    "wof:placetype":"venue"
},
  "geometry": {"coordinates":[0.0372169018,38.7943992615],"type":"Point"}
}