{
  "type": "Feature",
  "properties": {
    "addr:full":"Cra Malaga-cadiz, Km. 0198,0 Mijas Costa M\u00e1laga 29649",
    "addr:postcode":"29649",
    "addr:street":"Km. 0198,0",
    "iso:country":"ES",
    "sg:address":"Cra Malaga-cadiz, Km. 0198,0",
    "sg:city":"Mijas Costa",
    "sg:orig_category":"Distribuci\u00d3n De Petr\u00d3leo Y Derivados",
    "sg:phone":"+34 952 93 14 44",
    "sg:postcode":"29649",
    "sg:province":"M\u00e1laga",
    "wof:name":"Cedipsa Compa\u00d1ia Espa\u00d1ola Distribuidora De Petroleos S.a.",
    "wof:placetype":"venue"
},
  "geometry": {"coordinates":[-4.7157039642,36.4931945801],"type":"Point"}
}