{
  "type": "Feature",
  "properties": {
    "addr:full":"Pl. Generalisimo, 18 Sevilleja De La Jara Toledo 45671",
    "addr:housenumber":"18",
    "addr:postcode":"45671",
    "addr:street":"Pl. Generalisimo",
    "iso:country":"ES",
    "sg:address":"Pl. Generalisimo, 18",
    "sg:city":"Sevilleja De La Jara",
    "sg:orig_category":"Cajas De Ahorro",
    "sg:phone":"+34 925 45 50 17",
    "sg:postcode":"45671",
    "sg:province":"Toledo",
    "sg:website":"www.ccm.es",
    "wof:name":"Caja De Ahorros De Castilla La Mancha",
    "wof:placetype":"venue"
},
  "geometry": {"coordinates":[-4.9645848274,39.5752487183],"type":"Point"}
}