{
  "type": "Feature",
  "properties": {
    "addr:full":"Carrer de Esglesia, 323 Calella Barcelona 08370",
    "addr:housenumber":"323",
    "addr:postcode":"08370",
    "addr:street":"Carrer De Esglesia",
    "iso:country":"ES",
    "sg:address":"Carrer de Esglesia, 323",
    "sg:city":"Calella",
    "sg:orig_category":"Marroquiner\u00cda (confecci\u00d3n)",
    "sg:phone":"+34 937 66 07 23",
    "sg:postcode":"08370",
    "sg:province":"Barcelona",
    "wof:name":"Carol Pell S.c.p.",
    "wof:placetype":"venue"
},
  "geometry": {"coordinates":[2.6677401066,41.6166801453],"type":"Point"}
}