{
  "type": "Feature",
  "properties": {
    "iso:country":"ES",
    "sg:address":"Carrer de Saclosa, 25",
    "sg:city":"Manresa",
    "sg:orig_category":"Oficinas: Suministros Para (fabricaci\u00d3n, Al Por Mayor)",
    "sg:phone":"+34 938 72 80 09",
    "sg:postcode":"08241",
    "sg:province":"Barcelona",
    "wof:name":"Ofimatica Del Bages S.l.",
    "wof:placetype":"venue"
},
  "geometry": {"coordinates":[1.8200700283,41.7284355164],"type":"Point"}
}