{
  "type": "Feature",
  "properties": {
    "addr:full":"Pase Estacion, 5 Pe\u00e7aranda De Bracamonte Salamanca 37300",
    "addr:housenumber":"5",
    "addr:postcode":"37300",
    "addr:street":"Estacion",
    "iso:country":"ES",
    "sg:address":"Pase Estacion, 5",
    "sg:city":"Pe\u00e7aranda De Bracamonte",
    "sg:orig_category":"Alquiler De Veh\u00cdculos: Turismos Y Utilitarios",
    "sg:phone":"+34 923 54 12 29",
    "sg:postcode":"37300",
    "sg:province":"Salamanca",
    "wof:name":"Autocares Galan Gomez S.l.",
    "wof:placetype":"venue"
},
  "geometry": {"coordinates":[-5.6630473137,40.9649734497],"type":"Point"}
}