{
  "type": "Feature",
  "properties": {
    "iso:country":"ES",
    "sg:address":"Jose Artetxe Kalea, S/n",
    "sg:city":"Azpeitia",
    "sg:orig_category":"Asociaciones, Organismos Culturales Y Socioeducativos",
    "sg:phone":"+34 943 81 28 89",
    "sg:postcode":"20730",
    "sg:province":"Guip\u00f9zcoa",
    "wof:name":"Sociedad Recreativa Izarraitzpe",
    "wof:placetype":"venue"
},
  "geometry": {"coordinates":[-2.2667789459,43.182144165],"type":"Point"}
}