{
  "type": "Feature",
  "properties": {
    "addr:full":"Calle de Pradillo, 34 Madrid Madrid 28002",
    "addr:housenumber":"34",
    "addr:postcode":"madrid;28002",
    "addr:street":"Calle De Pradillo",
    "iso:country":"ES",
    "sg:address":"Calle de Pradillo, 34",
    "sg:city":"Madrid",
    "sg:orig_category":"Librer\u00cdas",
    "sg:phone":"+34 914 15 38 98",
    "sg:postcode":"28002",
    "sg:province":"Madrid",
    "wof:name":"Andujar Lopez Jesus Casimiro",
    "wof:placetype":"venue"
},
  "geometry": {"coordinates":[-3.6722457409,40.4489173889],"type":"Point"}
}