{
  "type": "Feature",
  "properties": {
    "addr:full":"El Bamio De San Eusebio De Coles, 6 Barra Mi\u00f1o Ourense 32950",
    "addr:housenumber":"6",
    "addr:postcode":"32950",
    "addr:street":"Barra Min\u0303O",
    "iso:country":"ES",
    "sg:address":"El Bamio De San Eusebio De Coles, 6",
    "sg:city":"Barra Mi\u00f1o",
    "sg:orig_category":"Fabricaci\u00d3n De Muebles",
    "sg:phone":"+34 988 20 51 28",
    "sg:postcode":"32950",
    "sg:province":"Ourense",
    "wof:name":"Lois Novoa Alfredo",
    "wof:placetype":"venue"
},
  "geometry": {"coordinates":[-7.8384737968,42.3799209595],"type":"Point"}
}