{
  "type": "Feature",
  "properties": {
    "iso:country":"ES",
    "sg:address":"Carrer de Marina, 53",
    "sg:city":"Premia Mar",
    "sg:orig_category":"Peluquer\u00cdas, Peluquer\u00cda Mixta",
    "sg:phone":"+34 937 51 07 34",
    "sg:postcode":"08330",
    "sg:province":"Barcelona",
    "wof:name":"Peluqueria Arregui S.l.",
    "wof:placetype":"venue"
},
  "geometry": {"coordinates":[2.3542881012,41.4914512634],"type":"Point"}
}