{
  "type": "Feature",
  "properties": {
    "addr:full":"Calle de Fragua, 1 Mostoles Madrid 28933",
    "addr:housenumber":"1",
    "addr:postcode":"28933",
    "addr:street":"Calle De Fragua",
    "iso:country":"ES",
    "sg:address":"Calle de Fragua, 1",
    "sg:city":"Mostoles",
    "sg:orig_category":"Pr\u00c9stamos Personales E Hipotecarios",
    "sg:phone":"+34 916 18 37 14",
    "sg:postcode":"28933",
    "sg:province":"Madrid",
    "wof:name":"Pizarro Lopez Eduardo",
    "wof:placetype":"venue"
},
  "geometry": {"coordinates":[-3.8636069298,40.3413887024],"type":"Point"}
}