{
  "type": "Feature",
  "properties": {
    "iso:country":"ES",
    "sg:address":"Ur Golf Iii, S/n",
    "sg:city":"Aljaraque",
    "sg:orig_category":"Productos Qu\u00cdmicos (fabricaci\u00d3n, Al Por Mayor)",
    "sg:phone":"+34 959 31 96 13",
    "sg:postcode":"21110",
    "sg:province":"Huelva",
    "wof:name":"Nalco Espa\u00f1ola S.a.",
    "wof:placetype":"venue"
},
  "geometry": {"coordinates":[-7.0241990089,37.2709159851],"type":"Point"}
}