{
  "type": "Feature",
  "properties": {
    "addr:full":"Ramon Y Cajal, 3 Corbera Valencia 46612",
    "addr:housenumber":"3",
    "addr:postcode":"46612",
    "addr:street":"Ramon Y Cajal",
    "iso:country":"ES",
    "sg:address":"Ramon Y Cajal, 3",
    "sg:city":"Corbera",
    "sg:orig_category":"Fabricaci\u00d3n De Bebidas No Alcoh\u00d3licas",
    "sg:phone":"+34 962 97 87 53",
    "sg:postcode":"46612",
    "sg:province":"Valencia",
    "wof:name":"Orxata I Gelats Rover S.l.",
    "wof:placetype":"venue"
},
  "geometry": {"coordinates":[-0.3539539874,39.1592330933],"type":"Point"}
}