{
  "type": "Feature",
  "properties": {
    "addr:full":"Cra. Fran\u00e7a, Km. 0110,0 Sort Lleida 25560",
    "addr:postcode":"25560",
    "addr:street":"Franc\u0327A Km. 0110,0",
    "iso:country":"ES",
    "sg:address":"Cra. Fran\u00e7a, Km. 0110,0",
    "sg:city":"Sort",
    "sg:orig_category":"Zonas De Acampada, Aparcamiento Para Caravanas",
    "sg:phone":"+34 973 62 08 20",
    "sg:postcode":"25560",
    "sg:province":"Lleida",
    "wof:name":"Camping Noguera Pallaresa S.a.",
    "wof:placetype":"venue"
},
  "geometry": {"coordinates":[1.1303800344,42.4112358093],"type":"Point"}
}