{
  "type": "Feature",
  "properties": {
    "addr:full":"Carr Arago, 38 Eivissa Islas Baleares 07800",
    "addr:housenumber":"38",
    "addr:postcode":"07800",
    "addr:street":"Carr Arago",
    "iso:country":"ES",
    "sg:address":"Carr Arago, 38",
    "sg:city":"Eivissa",
    "sg:orig_category":"Electrodom\u00c9sticos (al Por Menor)",
    "sg:phone":"+34 971 30 34 22",
    "sg:postcode":"07800",
    "sg:province":"Islas Baleares",
    "wof:name":"Mari Tur Santiago",
    "wof:placetype":"venue"
},
  "geometry": {"coordinates":[1.427752018,38.9085159302],"type":"Point"}
}