{
  "type": "Feature",
  "properties": {
    "iso:country":"ES",
    "sg:address":"Avda Barra\u00d1a, 15",
    "sg:city":"Boiro",
    "sg:orig_category":"Centros Comerciales Y Grandes Tiendas",
    "sg:phone":"+34 981 84 65 62",
    "sg:postcode":"15930",
    "sg:province":"La Coru\u00f1a",
    "wof:name":"Hermo Lopez Maria Purificacion",
    "wof:placetype":"venue"
},
  "geometry": {"coordinates":[-8.8832931519,42.6449394226],"type":"Point"}
}