{
  "type": "Feature",
  "properties": {
    "addr:full":"Calle de Cordoba, 1 Malaga M\u00e1laga 29001",
    "addr:housenumber":"1",
    "addr:postcode":"29001",
    "addr:street":"Calle De Cordoba;Ma\u0301Laga",
    "iso:country":"ES",
    "sg:address":"Calle de Cordoba, 1",
    "sg:city":"Malaga",
    "sg:orig_category":"Agencias Y Agentes Comerciales, Representantes",
    "sg:phone":"+34 952 06 08 41",
    "sg:postcode":"29001",
    "sg:province":"M\u00e1laga",
    "wof:name":"Espejo Zurita Juan Jose",
    "wof:placetype":"venue"
},
  "geometry": {"coordinates":[-4.4223041534,36.7173728943],"type":"Point"}
}