{
  "type": "Feature",
  "properties": {
    "iso:country":"ES",
    "sg:address":"La Loma, 13",
    "sg:city":"Pueblonuevo Guadiana",
    "sg:orig_category":"Pescader\u00cdas (al Por Menor)",
    "sg:phone":"+34 924 47 41 14",
    "sg:postcode":"06184",
    "sg:province":"Badajoz",
    "wof:name":"Morillo Abasolo Fernando",
    "wof:placetype":"venue"
},
  "geometry": {"coordinates":[-6.7551579475,38.924987793],"type":"Point"}
}