{
  "type": "Feature",
  "properties": {
    "addr:full":"Avda Lorca, 75 Sangonera Seca Murcia 30835",
    "addr:housenumber":"75",
    "addr:postcode":"30835",
    "addr:street":"Avda Lorca",
    "iso:country":"ES",
    "sg:address":"Avda Lorca, 75",
    "sg:city":"Sangonera Seca",
    "sg:orig_category":"Antig\u00dcedades (coches Y Motos)",
    "sg:phone":"+34 968 80 56 28",
    "sg:postcode":"30835",
    "sg:province":"Murcia",
    "wof:name":"Belando Baeza Juan Jose",
    "wof:placetype":"venue"
},
  "geometry": {"coordinates":[-1.2283860445,37.9600410461],"type":"Point"}
}