{
  "type": "Feature",
  "properties": {
    "iso:country":"ES",
    "sg:address":"Avda Valencia, 31",
    "sg:city":"Ibi",
    "sg:orig_category":"Fabricaci\u00d3n De Bolsos Y Bolsos De Tela",
    "sg:phone":"+34 965 55 06 79",
    "sg:postcode":"03440",
    "sg:province":"Alicante",
    "wof:name":"Plasticos Miras S.l.",
    "wof:placetype":"venue"
},
  "geometry": {"coordinates":[-0.5976629853,38.6172943115],"type":"Point"}
}