{
  "type": "Feature",
  "properties": {
    "iso:country":"ES",
    "sg:address":"Avda Mateo Bosch, 26",
    "sg:city":"Port D'andratx",
    "sg:orig_category":"Inmobiliaria (agencias)",
    "sg:phone":"+34 971 67 46 95",
    "sg:postcode":"07157",
    "sg:province":"Islas Baleares",
    "wof:name":"Crown Properties Balearecs Sl",
    "wof:placetype":"venue"
},
  "geometry": {"coordinates":[2.3882329464,39.544467926],"type":"Point"}
}