{
  "type": "Feature",
  "properties": {
    "addr:full":"Calle de Ciprea, 4 Melilla Melilla 52006",
    "addr:housenumber":"4",
    "addr:postcode":"52006",
    "addr:street":"Calle De Ciprea",
    "iso:country":"ES",
    "sg:address":"Calle de Ciprea, 4",
    "sg:city":"Melilla",
    "sg:orig_category":"Peluqueros: De Se\u00d1oras",
    "sg:phone":"+34 952 67 36 39",
    "sg:postcode":"52006",
    "sg:province":"Melilla",
    "wof:name":"Rico Bernabe Consuelo",
    "wof:placetype":"venue"
},
  "geometry": {"coordinates":[-2.9425001144,35.2733345032],"type":"Point"}
}