{
  "type": "Feature",
  "properties": {
    "iso:country":"ES",
    "sg:address":"Carretera De Don Benito-miajadas, Km. 0004,0",
    "sg:city":"Don Benito",
    "sg:orig_category":"Aguas (distribuci\u00d3n, Servicios)",
    "sg:phone":"+34 924 14 70 02",
    "sg:postcode":"06400",
    "sg:province":"Badajoz",
    "wof:name":"Aqualia Gestion Integral Del Agua S.a.",
    "wof:placetype":"venue"
},
  "geometry": {"coordinates":[-5.9062600136,39.1474914551],"type":"Point"}
}