{
  "type": "Feature",
  "properties": {
    "iso:country":"ES",
    "sg:address":"Calle de Juan Pages, 6",
    "sg:city":"Andratx",
    "sg:orig_category":"Plomeros",
    "sg:phone":"+34 971 13 68 66",
    "sg:postcode":"07150",
    "sg:province":"Islas Baleares",
    "wof:name":"Vazquez Sanchez Manuel",
    "wof:placetype":"venue"
},
  "geometry": {"coordinates":[2.4199171066,39.573261261],"type":"Point"}
}