{
  "type": "Feature",
  "properties": {
    "iso:country":"ES",
    "sg:address":"Rua Rosalia De Castro, 3",
    "sg:city":"Vilamean",
    "sg:orig_category":"Centros Empresariales",
    "sg:phone":"+34 986 36 67 30",
    "sg:postcode":"36350",
    "sg:province":"Pontevedra",
    "wof:name":"Asociacion De Empresarios De La Comarca Val Mi\u00f1or",
    "wof:placetype":"venue"
},
  "geometry": {"coordinates":[-8.8062162399,42.1411209106],"type":"Point"}
}