{
  "type": "Feature",
  "properties": {
    "addr:full":"La Fuente, 9 S. Lorenzo Parrilla Cuenca 16770",
    "addr:housenumber":"9",
    "addr:postcode":"16770",
    "addr:street":"La Fuente;S. Lorenzo",
    "iso:country":"ES",
    "sg:address":"La Fuente, 9",
    "sg:city":"S. Lorenzo Parrilla",
    "sg:orig_category":"Reposter\u00cdas",
    "sg:phone":"+34 969 29 62 54",
    "sg:postcode":"16770",
    "sg:province":"Cuenca",
    "wof:name":"Vieco Villanueva Ismael",
    "wof:placetype":"venue"
},
  "geometry": {"coordinates":[-2.3596169949,39.8523674011],"type":"Point"}
}