{
  "type": "Feature",
  "properties": {
    "iso:country":"ES",
    "sg:address":"Avda Bierzo (el), 40",
    "sg:city":"Dehesas",
    "sg:orig_category":"Empresas De Hormig\u00d3n, Hormig\u00d3n Armado Y Pretensado",
    "sg:phone":"+34 987 41 30 02",
    "sg:postcode":"24390",
    "sg:province":"Le\u00f3n",
    "wof:name":"Prefabricados Moran S.l.",
    "wof:placetype":"venue"
},
  "geometry": {"coordinates":[-6.66933918,42.5314903259],"type":"Point"}
}