{
  "type": "Feature",
  "properties": {
    "iso:country":"ES",
    "sg:address":"Avda Parque (del), 6",
    "sg:city":"Oca\u00f1a",
    "sg:orig_category":"Loter\u00cda Y T\u00d3mbola",
    "sg:phone":"+34 925 13 01 45",
    "sg:postcode":"45300",
    "sg:province":"Toledo",
    "wof:name":"Garcia-bueno Garcia Vicente",
    "wof:placetype":"venue"
},
  "geometry": {"coordinates":[-3.4982938766,39.9577217102],"type":"Point"}
}