{
  "type": "Feature",
  "properties": {
    "iso:country":"ES",
    "sg:address":"Calle de Doctor Garcia Del Pino, 7",
    "sg:city":"Noblejas",
    "sg:orig_category":"Lavado, Limpieza De Veh\u00cdculos",
    "sg:phone":"+34 925 14 06 62",
    "sg:postcode":"45350",
    "sg:province":"Toledo",
    "wof:name":"Contreras Rodriguez Maria Sagrario",
    "wof:placetype":"venue"
},
  "geometry": {"coordinates":[-3.4393284321,39.9807815552],"type":"Point"}
}