{
  "type": "Feature",
  "properties": {
    "addr:full":"C/ Eres, 24 Ribes Freser Girona 17534",
    "addr:housenumber":"24",
    "addr:postcode":"17534",
    "addr:street":"C / Eres",
    "iso:country":"ES",
    "sg:address":"C/ Eres, 24",
    "sg:city":"Ribes Freser",
    "sg:orig_category":"Electricidad: Instaladores",
    "sg:phone":"+34 972 72 71 24",
    "sg:postcode":"17534",
    "sg:province":"Girona",
    "wof:name":"Electricitat Franch S.l.",
    "wof:placetype":"venue"
},
  "geometry": {"coordinates":[2.1643021107,42.3507347107],"type":"Point"}
}