{
  "type": "Feature",
  "properties": {
    "iso:country":"ES",
    "sg:address":"Calle de Rio Mesa, 28",
    "sg:city":"Torremolinos",
    "sg:orig_category":"Servicios De Higiene Y Peluquer\u00cda Para Perros Y Gatos",
    "sg:phone":"+34 952 37 81 44",
    "sg:postcode":"29620",
    "sg:province":"M\u00e1laga",
    "wof:name":"Gonzalez Carrascosa Noble Alejandra",
    "wof:placetype":"venue"
},
  "geometry": {"coordinates":[-4.4998278618,36.6285934448],"type":"Point"}
}