{
  "type": "Feature",
  "properties": {
    "iso:country":"ES",
    "sg:address":"Ctra Cordoba-malaga, Km. 0444,0",
    "sg:city":"Montilla",
    "sg:orig_category":"Materias Pl\u00c1sticas: Art\u00cdculos Para La Industria",
    "sg:phone":"+34 957 65 18 13",
    "sg:postcode":"14550",
    "sg:province":"C\u00f3rdoba",
    "wof:name":"Fibopal S.l.",
    "wof:placetype":"venue"
},
  "geometry": {"coordinates":[-4.6605410576,37.5884437561],"type":"Point"}
}