{
  "type": "Feature",
  "properties": {
    "addr:full":"Avda Alcalde Cantos Ropero, 7 Jerez De La Frontera C\u00e1diz 11408",
    "addr:housenumber":"7",
    "addr:postcode":"11408",
    "addr:street":"Avda Alcalde Cantos Ropero",
    "iso:country":"ES",
    "sg:address":"Avda Alcalde Cantos Ropero, 7",
    "sg:city":"Jerez De La Frontera",
    "sg:orig_category":"Adaptaciones, Acondicionamientos Especiales Para Veh\u00cdculos, Veh\u00cdculos Industriales",
    "sg:phone":"+34 956 14 70 39",
    "sg:postcode":"11408",
    "sg:province":"C\u00e1diz",
    "wof:name":"Talleres Andaluci S.c.a.",
    "wof:placetype":"venue"
},
  "geometry": {"coordinates":[-6.1592831612,36.6686592102],"type":"Point"}
}