{
  "type": "Feature",
  "properties": {
    "iso:country":"ES",
    "sg:address":"Calle de Lirio, 10",
    "sg:city":"Ciudad Real",
    "sg:orig_category":"Tapicer\u00cdas",
    "sg:phone":"+34 926 22 64 46",
    "sg:postcode":"13004",
    "sg:province":"Ciudad Real",
    "wof:name":"Ruiz Madrid Rafael",
    "wof:placetype":"venue"
},
  "geometry": {"coordinates":[-3.9239048958,38.98828125],"type":"Point"}
}