{
  "type": "Feature",
  "properties": {
    "iso:country":"ES",
    "sg:address":"Calle de Teniente Merchante, 89",
    "sg:city":"Bollullos Par Condado",
    "sg:orig_category":"Mec\u00c1nico Del Autom\u00d3vil",
    "sg:phone":"+34 959 41 09 38",
    "sg:postcode":"21710",
    "sg:province":"Huelva",
    "wof:name":"Morales Fernandez Antonio",
    "wof:placetype":"venue"
},
  "geometry": {"coordinates":[-6.5416088104,37.3350906372],"type":"Point"}
}