{
  "type": "Feature",
  "properties": {
    "iso:country":"ES",
    "sg:address":"Calle de Melchor Cano, 1",
    "sg:city":"Madrid",
    "sg:orig_category":"Carnicer\u00cdas, Carnicer\u00cdas",
    "sg:phone":"+34 915 48 21 23",
    "sg:postcode":"28008",
    "sg:province":"Madrid",
    "wof:name":"Mu\u00f1oz Rincon Adoracion",
    "wof:placetype":"venue"
},
  "geometry": {"coordinates":[-3.7333040237,40.4271812439],"type":"Point"}
}