{
  "type": "Feature",
  "properties": {
    "iso:country":"ES",
    "sg:address":"Calle de San Buenaventura, 21",
    "sg:city":"Morro Jable",
    "sg:orig_category":"Servicios De Telecomunicaciones",
    "sg:phone":"+34 928 16 64 45",
    "sg:postcode":"35625",
    "sg:province":"Las Palmas",
    "wof:name":"Raji  Ali",
    "wof:placetype":"venue"
},
  "geometry": {"coordinates":[-14.3532619476,28.0538921356],"type":"Point"}
}