{
  "type": "Feature",
  "properties": {
    "iso:country":"ES",
    "sg:address":"Calle de Mauricio Legendre, 6",
    "sg:city":"Madrid",
    "sg:orig_category":"Cl\u00cdnicas M\u00c9dicas",
    "sg:phone":"+34 913 23 08 23",
    "sg:postcode":"28046",
    "sg:province":"Madrid",
    "wof:name":"Rodriga\u00f1ez Armero Juan Jose",
    "wof:placetype":"venue"
},
  "geometry": {"coordinates":[-3.6862170696,40.4699211121],"type":"Point"}
}