{
  "type": "Feature",
  "properties": {
    "addr:full":"Rua Sanjurjo Badia, 87 Vigo Pontevedra 36207",
    "addr:housenumber":"87",
    "addr:postcode":"36207",
    "addr:street":"Rua Sanjurjo Badia",
    "iso:country":"ES",
    "sg:address":"Rua Sanjurjo Badia, 87",
    "sg:city":"Vigo",
    "sg:orig_category":"Ropa Para Se\u00d1oras (al Por Menor)",
    "sg:phone":"+34 986 37 96 11",
    "sg:postcode":"36207",
    "sg:province":"Pontevedra",
    "wof:name":"Martinez Taboas Alfonso",
    "wof:placetype":"venue"
},
  "geometry": {"coordinates":[-8.702996254,42.2453918457],"type":"Point"}
}