{
  "type": "Feature",
  "properties": {
    "addr:full":"Poligono De El Raposal, 63 Arnedo La Rioja 26580",
    "addr:housenumber":"63",
    "addr:postcode":"26580",
    "addr:street":"Raposal;Rioja",
    "iso:country":"ES",
    "sg:address":"Poligono De El Raposal, 63",
    "sg:city":"Arnedo",
    "sg:orig_category":"Confecci\u00d3n De Zapatos",
    "sg:phone":"+34 941 38 42 66",
    "sg:postcode":"26580",
    "sg:province":"La Rioja",
    "wof:name":"Calzados De Blas S.l.",
    "wof:placetype":"venue"
},
  "geometry": {"coordinates":[-2.0899488926,42.2300453186],"type":"Point"}
}