{
  "type": "Feature",
  "properties": {
    "iso:country":"ES",
    "sg:address":"Calle de Escultor Palao, 20",
    "sg:city":"Zaragoza",
    "sg:orig_category":"Farmacias",
    "sg:phone":"+34 976 31 37 34",
    "sg:postcode":"50017",
    "sg:province":"Zaragoza",
    "wof:name":"Mainar Rodrigo Ana Mercedes",
    "wof:placetype":"venue"
},
  "geometry": {"coordinates":[-0.9131947756,41.6491470337],"type":"Point"}
}