{
  "type": "Feature",
  "properties": {
    "iso:country":"ES",
    "sg:address":"Calle de Alfares (los), 18",
    "sg:city":"Alcorcon",
    "sg:orig_category":"Molduras, Junquillos, Listones Y Molduras Perforadas",
    "sg:phone":"+34 916 43 46 55",
    "sg:postcode":"28921",
    "sg:province":"Madrid",
    "wof:name":"Lopez Arroyo Jose Antonio",
    "wof:placetype":"venue"
},
  "geometry": {"coordinates":[-3.8294510841,40.3467979431],"type":"Point"}
}