{
  "type": "Feature",
  "properties": {
    "addr:full":"Calle de Espoz Y Mina, 16 Salamanca Salamanca 37002",
    "addr:housenumber":"16",
    "addr:postcode":"37002",
    "addr:street":"Calle De Espoz Y Mina",
    "iso:country":"ES",
    "sg:address":"Calle de Espoz Y Mina, 16",
    "sg:city":"Salamanca",
    "sg:orig_category":"Relojer\u00cda (al Por Menor, Reparaci\u00d3n)",
    "sg:phone":"+34 923 21 92 72",
    "sg:postcode":"37002",
    "sg:province":"Salamanca",
    "wof:name":"Martin Santana Julian",
    "wof:placetype":"venue"
},
  "geometry": {"coordinates":[-5.6653060913,40.966091156],"type":"Point"}
}