{
  "type": "Feature",
  "properties": {
    "iso:country":"ES",
    "sg:address":"Calle de Marques De Urquijo, 33",
    "sg:city":"Madrid",
    "sg:orig_category":"Institutos De Belleza",
    "sg:phone":"+34 915 47 24 38",
    "sg:postcode":"28008",
    "sg:province":"Madrid",
    "wof:name":"Alonso Estebaranz Montserrat",
    "wof:placetype":"venue"
},
  "geometry": {"coordinates":[-3.7195620537,40.4295387268],"type":"Point"}
}