{
  "type": "Feature",
  "properties": {
    "addr:full":"Poligon F, S/n Xativa Valencia 46800",
    "addr:housenumber":"s / n",
    "addr:postcode":"46800",
    "iso:country":"ES",
    "sg:address":"Poligon F, S/n",
    "sg:city":"Xativa",
    "sg:orig_category":"Cojinetes De Bolas, Agujas Y Rodillos (fabricaci\u00d3n, Al Por Mayor)",
    "sg:phone":"+34 962 28 72 02",
    "sg:postcode":"46800",
    "sg:province":"Valencia",
    "wof:name":"Rodamientos Moscardo S.l.",
    "wof:placetype":"venue"
},
  "geometry": {"coordinates":[-0.5239239931,38.9976882935],"type":"Point"}
}