{
  "type": "Feature",
  "properties": {
    "iso:country":"ES",
    "sg:address":"Carrer de Vila, 61",
    "sg:city":"Lloret Mar",
    "sg:orig_category":"Alimentaci\u00d3n General (al Por Menor)",
    "sg:phone":"+34 972 36 48 11",
    "sg:postcode":"17310",
    "sg:province":"Girona",
    "wof:name":"Fabregas Bruguera Antonio",
    "wof:placetype":"venue"
},
  "geometry": {"coordinates":[2.8486130238,41.6998672485],"type":"Point"}
}