{
  "type": "Feature",
  "properties": {
    "iso:country":"ES",
    "sg:address":"Avda Lerida (de), 5",
    "sg:city":"Monzon",
    "sg:orig_category":"Abogados",
    "sg:phone":"+34 974 40 14 75",
    "sg:postcode":"22400",
    "sg:province":"Huesca",
    "wof:name":"Flores Molina Ana",
    "wof:placetype":"venue"
},
  "geometry": {"coordinates":[0.1942970008,41.9124107361],"type":"Point"}
}