{
  "type": "Feature",
  "properties": {
    "iso:country":"ES",
    "sg:address":"Fca. V. Amatos, S/n",
    "sg:city":"Pedrosillo Aires",
    "sg:orig_category":"Agricultores, Agricultores",
    "sg:phone":"+34 923 39 06 46",
    "sg:postcode":"37788",
    "sg:province":"Salamanca",
    "wof:name":"Julian Martin S.a.",
    "wof:placetype":"venue"
},
  "geometry": {"coordinates":[-5.6927871704,40.7566108704],"type":"Point"}
}