{
  "type": "Feature",
  "properties": {
    "iso:country":"ES",
    "sg:address":"Calle de Comunidad Valenciana, 15",
    "sg:city":"Almoradi",
    "sg:orig_category":"Supermercados Y Hipermercados",
    "sg:phone":"+34 966 78 16 84",
    "sg:postcode":"03160",
    "sg:province":"Alicante",
    "sg:website":"www.mercadona.es",
    "wof:name":"Mercadona S.a.",
    "wof:placetype":"venue"
},
  "geometry": {"coordinates":[-0.7891141176,38.110206604],"type":"Point"}
}