{
  "type": "Feature",
  "properties": {
    "iso:country":"ES",
    "sg:address":"Calle de Teresa De Calcuta, 6",
    "sg:city":"Cordoba",
    "sg:orig_category":"Institutos De Belleza",
    "sg:phone":"+34 957 40 30 07",
    "sg:postcode":"14011",
    "sg:province":"C\u00f3rdoba",
    "wof:name":"Pacha Portillo Maria Isabel",
    "wof:placetype":"venue"
},
  "geometry": {"coordinates":[-4.7964677811,37.8954353333],"type":"Point"}
}