{
  "type": "Feature",
  "properties": {
    "iso:country":"ES",
    "sg:address":"Avda Doctor Mara\u00d1on, 11",
    "sg:city":"Almoradi",
    "sg:orig_category":"Albergues",
    "sg:phone":"+34 965 70 03 25",
    "sg:postcode":"03160",
    "sg:province":"Alicante",
    "wof:name":"Gomez Monge Maria Teresa",
    "wof:placetype":"venue"
},
  "geometry": {"coordinates":[-0.7884020209,38.1073036194],"type":"Point"}
}