{
  "type": "Feature",
  "properties": {
    "iso:country":"ES",
    "sg:address":"Pase Direccion, 65",
    "sg:city":"Madrid",
    "sg:orig_category":"Comercio De Piezas De Recambio Y De Accesorios De Veh\u00cdculos, Veh\u00cdculos Industriales",
    "sg:phone":"+34 914 50 35 53",
    "sg:postcode":"28039",
    "sg:province":"Madrid",
    "wof:name":"Recambios Cabellos S.a.",
    "wof:placetype":"venue"
},
  "geometry": {"coordinates":[-3.7085669041,40.4603652954],"type":"Point"}
}