{
  "type": "Feature",
  "properties": {
    "iso:country":"ES",
    "sg:address":"Avda Gran Via, 34",
    "sg:city":"Vigo",
    "sg:orig_category":"Audiovisuales (producci\u00d3n, Edici\u00d3n, Realizaci\u00d3n)",
    "sg:phone":"+34 986 48 05 78",
    "sg:postcode":"36203",
    "sg:province":"Pontevedra",
    "wof:name":"Producciones Sanmartin Padron S.l.",
    "wof:placetype":"venue"
},
  "geometry": {"coordinates":[-8.7181005478,42.2318725586],"type":"Point"}
}