{
  "type": "Feature",
  "properties": {
    "iso:country":"ES",
    "sg:address":"Calle de San Antonio, 7",
    "sg:city":"Rojales",
    "sg:orig_category":"Farmacias",
    "sg:phone":"+34 966 71 52 40",
    "sg:postcode":"03170",
    "sg:province":"Alicante",
    "wof:name":"Hermanos Varela Alonso C.b.",
    "wof:placetype":"venue"
},
  "geometry": {"coordinates":[-0.723788023,38.0880622864],"type":"Point"}
}