{
  "type": "Feature",
  "properties": {
    "addr:full":"Plaz Gonzalez Conde, 7 Carmen Murcia 30002",
    "addr:housenumber":"7",
    "addr:postcode":"30002",
    "addr:street":"Plaz;Conde",
    "iso:country":"ES",
    "sg:address":"Plaz Gonzalez Conde, 7",
    "sg:city":"Carmen",
    "sg:orig_category":"Supermercados Y Hipermercados",
    "sg:phone":"+34 968 22 71 66",
    "sg:postcode":"30002",
    "sg:province":"Murcia",
    "sg:website":"www.mercadona.es",
    "wof:name":"Mercadona S.a.",
    "wof:placetype":"venue"
},
  "geometry": {"coordinates":[-1.1302499771,37.9829597473],"type":"Point"}
}