{
  "type": "Feature",
  "properties": {
    "addr:full":"Avda Andalucia, 73 Lebrija Sevilla 41740",
    "addr:housenumber":"73",
    "addr:postcode":"41740",
    "addr:street":"Avda Andalucia",
    "iso:country":"ES",
    "sg:address":"Avda Andalucia, 73",
    "sg:city":"Lebrija",
    "sg:orig_category":"Mec\u00c1nico Del Autom\u00d3vil",
    "sg:phone":"+34 955 97 24 54",
    "sg:postcode":"41740",
    "sg:province":"Sevilla",
    "wof:name":"Talleres Lebrija S.l.",
    "wof:placetype":"venue"
},
  "geometry": {"coordinates":[-6.0832591057,36.9267311096],"type":"Point"}
}