{
  "type": "Feature",
  "properties": {
    "addr:full":"Pl Angel, S/n Sabadell Barcelona 08202",
    "addr:housenumber":"s",
    "addr:postcode":"08202",
    "addr:street":"Pl Angel;/ N",
    "iso:country":"ES",
    "sg:address":"Pl Angel, S/n",
    "sg:city":"Sabadell",
    "sg:orig_category":"Autob\u00das (explotaci\u00d3n Y Servicios De)",
    "sg:phone":"+34 937 27 00 90",
    "sg:postcode":"08202",
    "sg:province":"Barcelona",
    "wof:name":"Tus S Coop. Ltda.",
    "wof:placetype":"venue"
},
  "geometry": {"coordinates":[2.1085650921,41.549243927],"type":"Point"}
}