{
  "type": "Feature",
  "properties": {
    "iso:country":"ES",
    "sg:address":"Calle de Vazquez De Mella, 1",
    "sg:city":"Alberic",
    "sg:orig_category":"Electricidad: Instaladores",
    "sg:phone":"+34 962 44 50 15",
    "sg:postcode":"46260",
    "sg:province":"Valencia",
    "wof:name":"Pla Monar Vicente",
    "wof:placetype":"venue"
},
  "geometry": {"coordinates":[-0.5205760002,39.1192893982],"type":"Point"}
}