{
  "type": "Feature",
  "properties": {
    "iso:country":"ES",
    "sg:address":"Calle de Calvario, 2",
    "sg:city":"Oria",
    "sg:orig_category":"Centros De Educaci\u00d3n Especial",
    "sg:phone":"+34 950 12 27 35",
    "sg:postcode":"04810",
    "sg:province":"Almer\u00eda",
    "wof:name":"Agrupacion Escolar Mixta",
    "wof:placetype":"venue"
},
  "geometry": {"coordinates":[-2.2950181961,37.4850311279],"type":"Point"}
}