{
  "type": "Feature",
  "properties": {
    "addr:full":"Calle de Ibaiondo, 7 Ondarroa Vizcaya 48700",
    "addr:housenumber":"7",
    "addr:postcode":"48700",
    "addr:street":"Calle De Ibaiondo",
    "iso:country":"ES",
    "sg:address":"Calle de Ibaiondo, 7",
    "sg:city":"Ondarroa",
    "sg:orig_category":"Supermercados Y Hipermercados",
    "sg:phone":"+34 946 83 17 83",
    "sg:postcode":"48700",
    "sg:province":"Vizcaya",
    "wof:name":"Janariak Zaton, S.l.",
    "wof:placetype":"venue"
},
  "geometry": {"coordinates":[-2.4317040443,43.3209648132],"type":"Point"}
}