{
  "type": "Feature",
  "properties": {
    "addr:full":"Calle de Zapateria, 44 Vitoria-gasteiz \u00c1lava 01001",
    "addr:housenumber":"44",
    "addr:postcode":"01001",
    "addr:street":"Calle De Zapateria",
    "iso:country":"ES",
    "sg:address":"Calle de Zapateria, 44",
    "sg:city":"Vitoria-gasteiz",
    "sg:orig_category":"Muebles Y Accesorios Para Cocinas Y Cuartos De Ba\u00d1o (al Por Menor)",
    "sg:phone":"+34 945 27 24 97",
    "sg:postcode":"01001",
    "sg:province":"\u00c1lava",
    "wof:name":"Echeguren Ruiz Roberto",
    "wof:placetype":"venue"
},
  "geometry": {"coordinates":[-2.6738569736,42.8481178284],"type":"Point"}
}