{
  "type": "Feature",
  "properties": {
    "iso:country":"ES",
    "sg:address":"Calle de Madre Elisea Oliver, 2",
    "sg:city":"Alacant",
    "sg:orig_category":"Internados & Ense\u00d1anza Privada",
    "sg:phone":"+34 965 17 45 34",
    "sg:postcode":"03005",
    "sg:province":"Alicante",
    "wof:name":"Colegio Santa Maria Del Carmen",
    "wof:placetype":"venue"
},
  "geometry": {"coordinates":[-0.5015540123,38.3623352051],"type":"Point"}
}