{
  "type": "Feature",
  "properties": {
    "iso:country":"ES",
    "sg:address":"Calle de Prado, 25",
    "sg:city":"Madrid",
    "sg:orig_category":"Audiovisuales (producci\u00d3n, Edici\u00d3n, Realizaci\u00d3n)",
    "sg:phone":"+34 914 29 40 00",
    "sg:postcode":"28014",
    "sg:province":"Madrid",
    "wof:name":"Lazona Films S.l.",
    "wof:placetype":"venue"
},
  "geometry": {"coordinates":[-3.6982069016,40.4151649475],"type":"Point"}
}