{
  "type": "Feature",
  "properties": {
    "addr:full":"Calle de Logro\u00d1o, 46 Miranda Ebro Burgos 09200",
    "addr:housenumber":"46",
    "addr:postcode":"09200",
    "addr:street":"Calle De Logron\u0303O",
    "iso:country":"ES",
    "sg:address":"Calle de Logro\u00d1o, 46",
    "sg:city":"Miranda Ebro",
    "sg:orig_category":"Maquinaria Para Industrias Diversas",
    "sg:phone":"+34 947 32 00 05",
    "sg:postcode":"09200",
    "sg:province":"Burgos",
    "wof:name":"Lopez Pi\u00f1eiro Eduardo",
    "wof:placetype":"venue"
},
  "geometry": {"coordinates":[-2.9365921021,42.6872520447],"type":"Point"}
}