{
  "type": "Feature",
  "properties": {
    "addr:full":"Aldea Carnoedo, 14 Sada La Coru\u00f1a 15160",
    "addr:housenumber":"14",
    "addr:postcode":"15160",
    "addr:street":"Carnoedo;La",
    "iso:country":"ES",
    "sg:address":"Aldea Carnoedo, 14",
    "sg:city":"Sada",
    "sg:orig_category":"Reposter\u00cdas",
    "sg:phone":"+34 981 62 31 55",
    "sg:postcode":"15160",
    "sg:province":"La Coru\u00f1a",
    "wof:name":"Rodriguez Cubeiro Manuel",
    "wof:placetype":"venue"
},
  "geometry": {"coordinates":[-8.2548141479,43.3510665894],"type":"Point"}
}