{
  "type": "Feature",
  "properties": {
    "addr:full":"Carr El Penedes, 75 Lleida Lleida 25005",
    "addr:housenumber":"75",
    "addr:postcode":"25005",
    "addr:street":"Carr El Penedes",
    "iso:country":"ES",
    "sg:address":"Carr El Penedes, 75",
    "sg:city":"Lleida",
    "sg:orig_category":"Juegos Y Juguetes (al Por Menor)",
    "sg:phone":"+34 973 22 29 48",
    "sg:postcode":"25005",
    "sg:province":"Lleida",
    "wof:name":"Societat Escolar De Complements S.l.",
    "wof:placetype":"venue"
},
  "geometry": {"coordinates":[0.6246309876,41.6283988953],"type":"Point"}
}