{
  "type": "Feature",
  "properties": {
    "addr:full":"Riera Del Pare Fita, 94 Arenys Mar Barcelona 08350",
    "addr:housenumber":"94",
    "addr:postcode":"08350",
    "addr:street":"Riera Del Pare Fita",
    "iso:country":"ES",
    "sg:address":"Riera Del Pare Fita, 94",
    "sg:city":"Arenys Mar",
    "sg:orig_category":"Sociedades, Compa\u00d1\u00cdas Aseguradoras",
    "sg:phone":"+34 937 95 78 88",
    "sg:postcode":"08350",
    "sg:province":"Barcelona",
    "wof:name":"Seguros Catalana Occidente S.a. De Seguros Y Reaseguros",
    "wof:placetype":"venue"
},
  "geometry": {"coordinates":[2.5463600159,41.5853691101],"type":"Point"}
}