{
  "type": "Feature",
  "properties": {
    "addr:full":"Calle de Puerta De La Macarena, 23 Bormujos Sevilla 41930",
    "addr:housenumber":"23",
    "addr:postcode":"41930",
    "addr:street":"Calle De Puerta De La Macarena",
    "iso:country":"ES",
    "sg:address":"Calle de Puerta De La Macarena, 23",
    "sg:city":"Bormujos",
    "sg:orig_category":"Ingeniero",
    "sg:phone":"+34 955 72 33 73",
    "sg:postcode":"41930",
    "sg:province":"Sevilla",
    "wof:name":"Romero Gomez Javier",
    "wof:placetype":"venue"
},
  "geometry": {"coordinates":[-6.0790348053,37.3704452515],"type":"Point"}
}