{
  "type": "Feature",
  "properties": {
    "addr:full":"Avda. Palamos, Km. 0035,0 Mont-ras Girona 17253",
    "addr:postcode":"17253",
    "addr:street":"Avda. Palamos Km. 0035,0",
    "iso:country":"ES",
    "sg:address":"Avda. Palamos, Km. 0035,0",
    "sg:city":"Mont-ras",
    "sg:orig_category":"Compraventa De Antig\u00dcedades",
    "sg:phone":"+34 972 30 31 68",
    "sg:postcode":"17253",
    "sg:province":"Girona",
    "wof:name":"Coll Juanola Luis",
    "wof:placetype":"venue"
},
  "geometry": {"coordinates":[3.1424300671,41.8871994019],"type":"Point"}
}