{
  "type": "Feature",
  "properties": {
    "iso:country":"ES",
    "sg:address":"Calle de Santa Lucia, 11",
    "sg:city":"Merida",
    "sg:classifiers":[
        {
            "category":"Autos & Motor Vehicles",
            "subcategory":"Automobile Sales",
            "type":"Retail Goods"
        }
    ],
    "sg:phone":"+34 924 33 09 12",
    "sg:postcode":"06800",
    "sg:province":"Badajoz",
    "wof:name":"Auto Escuela Anca S.c.",
    "wof:placetype":"venue"
},
  "geometry": {"coordinates":[-6.3407111168,38.9196205139],"type":"Point"}
}