{
  "type": "Feature",
  "properties": {
    "iso:country":"ES",
    "sg:address":"Carr Roquetes, 13",
    "sg:city":"Vilanova I La Geltru",
    "sg:orig_category":"Electricidad: Instaladores",
    "sg:phone":"+34 938 14 22 54",
    "sg:postcode":"08800",
    "sg:province":"Barcelona",
    "wof:name":"Asociacion Profesional De Empresarios De",
    "wof:placetype":"venue"
},
  "geometry": {"coordinates":[1.7375968695,41.2274475098],"type":"Point"}
}