{
  "type": "Feature",
  "properties": {
    "addr:full":"Avda Cabezo De La Joya, 1 Huelva Huelva 21004",
    "addr:housenumber":"1",
    "addr:postcode":"21004",
    "addr:street":"Avda Cabezo De La Joya",
    "iso:country":"ES",
    "sg:address":"Avda Cabezo De La Joya, 1",
    "sg:city":"Huelva",
    "sg:orig_category":"Alimentaci\u00d3n General (al Por Menor)",
    "sg:phone":"+34 959 24 36 50",
    "sg:postcode":"21004",
    "sg:province":"Huelva",
    "wof:name":"Gomez Bria Javiera",
    "wof:placetype":"venue"
},
  "geometry": {"coordinates":[-6.9495940208,37.256313324],"type":"Point"}
}