{
  "type": "Feature",
  "properties": {
    "iso:country":"ES",
    "sg:address":"Av Catalunya, 87",
    "sg:city":"Pallaresos",
    "sg:orig_category":"Inmobiliaria (agencias)",
    "sg:phone":"+34 977 61 09 74",
    "sg:postcode":"43151",
    "sg:province":"Tarragona",
    "wof:name":"Bonell Tampesta",
    "wof:placetype":"venue"
},
  "geometry": {"coordinates":[1.2767390013,41.1739044189],"type":"Point"}
}