{
  "type": "Feature",
  "properties": {
    "addr:full":"Pase Torremata (de La), S/n Alagon Zaragoza 50630",
    "addr:housenumber":"s",
    "addr:postcode":"50630",
    "addr:street":"/ N Alagon",
    "iso:country":"ES",
    "sg:address":"Pase Torremata (de La), S/n",
    "sg:city":"Alagon",
    "sg:orig_category":"Cooperativas Agr\u00cdcolas",
    "sg:phone":"+34 976 61 08 45",
    "sg:postcode":"50630",
    "sg:province":"Zaragoza",
    "wof:name":"Cooperativa Del Campo San Antonio",
    "wof:placetype":"venue"
},
  "geometry": {"coordinates":[-1.1281570196,41.7637176514],"type":"Point"}
}