{
  "type": "Feature",
  "properties": {
    "iso:country":"ES",
    "sg:address":"Carrer de Piquer, 55",
    "sg:city":"Barcelona",
    "sg:orig_category":"Promotores Constructores",
    "sg:phone":"+34 934 41 46 57",
    "sg:postcode":"08004",
    "sg:province":"Barcelona",
    "wof:name":"Construcciones H.pascual S.l.",
    "wof:placetype":"venue"
},
  "geometry": {"coordinates":[2.1677069664,41.3735122681],"type":"Point"}
}