{
  "type": "Feature",
  "properties": {
    "addr:full":"Carrer de Bisbe Perello, S/n Manresa Barcelona 08240",
    "addr:housenumber":"s / n",
    "addr:postcode":"08240",
    "addr:street":"Carrer De Bisbe Perello",
    "iso:country":"ES",
    "sg:address":"Carrer de Bisbe Perello, S/n",
    "sg:city":"Manresa",
    "sg:orig_category":"Comercio De Piezas De Recambio Y De Accesorios De Veh\u00cdculos, Veh\u00cdculos Industriales",
    "sg:phone":"+34 938 74 86 36",
    "sg:postcode":"08240",
    "sg:province":"Barcelona",
    "sg:website":"www.norauto.es",
    "wof:name":"Norauto S.a.",
    "wof:placetype":"venue"
},
  "geometry": {"coordinates":[1.8378000259,41.7214050293],"type":"Point"}
}