{
  "type": "Feature",
  "properties": {
    "addr:full":"Avda San Juan De Sahagun, 18 Le\u00f3n Le\u00f3n 24007",
    "addr:housenumber":"18",
    "addr:postcode":"24007",
    "addr:street":"Avda San Juan De Sahagun;Leo\u0301N",
    "iso:country":"ES",
    "sg:address":"Avda San Juan De Sahagun, 18",
    "sg:city":"Le\u00f3n",
    "sg:orig_category":"Confecci\u00d3n (fabricaci\u00d3n, Al Por Mayor)",
    "sg:phone":"+34 987 22 39 36",
    "sg:postcode":"24007",
    "sg:province":"Le\u00f3n",
    "wof:name":"Platea S.c.p",
    "wof:placetype":"venue"
},
  "geometry": {"coordinates":[-5.5668091774,42.6091384888],"type":"Point"}
}