{
  "type": "Feature",
  "properties": {
    "iso:country":"ES",
    "sg:address":"Calle de Marva, 9",
    "sg:city":"Valencia",
    "sg:orig_category":"Asesor\u00cda Fiscal Y Jur\u00cddica",
    "sg:phone":"+34 963 80 78 19",
    "sg:postcode":"46007",
    "sg:province":"Valencia",
    "wof:name":"Juan Espi Alonso S.l.",
    "wof:placetype":"venue"
},
  "geometry": {"coordinates":[-0.3829024136,39.4634170532],"type":"Point"}
}