{
  "type": "Feature",
  "properties": {
    "iso:country":"ES",
    "sg:address":"Carr Blasco Iba\u00d1ez, 25",
    "sg:city":"Pu\u00e7ol",
    "sg:orig_category":"Empresas De Carpinter\u00cda Met\u00c1lica",
    "sg:phone":"+34 961 46 41 75",
    "sg:postcode":"46530",
    "sg:province":"Valencia",
    "wof:name":"Blasco Mu\u00f1oz Estrella",
    "wof:placetype":"venue"
},
  "geometry": {"coordinates":[-0.3094420135,39.6213951111],"type":"Point"}
}