{
  "type": "Feature",
  "properties": {
    "addr:full":"Pg Ferrocarril, 337 Castelldefels Barcelona 08860",
    "addr:housenumber":"337",
    "addr:postcode":"08860",
    "addr:street":"Pg Ferrocarril",
    "iso:country":"ES",
    "sg:address":"Pg Ferrocarril, 337",
    "sg:city":"Castelldefels",
    "sg:orig_category":"Panader\u00cdas, Panader\u00cdas",
    "sg:phone":"+34 936 34 27 72",
    "sg:postcode":"08860",
    "sg:province":"Barcelona",
    "wof:name":"Central De Negocis Flequers I Pastissers S.l.",
    "wof:placetype":"venue"
},
  "geometry": {"coordinates":[1.988607049,41.2833099365],"type":"Point"}
}