{
  "type": "Feature",
  "properties": {
    "iso:country":"ES",
    "sg:address":"Calle de Aniceto Marinas, 92",
    "sg:city":"Madrid",
    "sg:orig_category":"Edici\u00d3n De Diarios, Revistas, Boletines",
    "sg:phone":"+34 915 48 96 51",
    "sg:postcode":"28...",
    "sg:province":"Madrid",
    "wof:name":"Progourmet S.a.",
    "wof:placetype":"venue"
},
  "geometry": {"coordinates":[-3.7296733856,40.4275665283],"type":"Point"}
}