{
  "type": "Feature",
  "properties": {
    "iso:country":"ES",
    "sg:address":"Avda Maritima (corralejo), 14",
    "sg:city":"Corralejo",
    "sg:orig_category":"Caf\u00c9s, Bares, Cervecer\u00cdas",
    "sg:phone":"+34 928 86 73 87",
    "sg:postcode":"35660",
    "sg:province":"Las Palmas",
    "wof:name":"Fitzgerald  John Anthony",
    "wof:placetype":"venue"
},
  "geometry": {"coordinates":[-13.8674459457,28.7365913391],"type":"Point"}
}