{
  "type": "Feature",
  "properties": {
    "addr:full":"Calle de Padre Claret, 3 Madrid Madrid 28002",
    "addr:housenumber":"3",
    "addr:postcode":"28002",
    "addr:street":"Calle De Padre Claret",
    "iso:country":"ES",
    "sg:address":"Calle de Padre Claret, 3",
    "sg:city":"Madrid",
    "sg:orig_category":"Maquinaria Para Industrias Diversas",
    "sg:phone":"+34 914 13 98 99",
    "sg:postcode":"28002",
    "sg:province":"Madrid",
    "wof:name":"Casals Cardona Industrial S. A.",
    "wof:placetype":"venue"
},
  "geometry": {"coordinates":[-3.6652328968,40.4448356628],"type":"Point"}
}