{
  "type": "Feature",
  "properties": {
    "addr:full":"Calle de Lopez Oca\u00d1a, 5 Carpio Tajo Toledo 45533",
    "addr:housenumber":"5",
    "addr:postcode":"45533",
    "addr:street":"Calle De;Ocan\u0303A",
    "iso:country":"ES",
    "sg:address":"Calle de Lopez Oca\u00d1a, 5",
    "sg:city":"Carpio Tajo",
    "sg:orig_category":"Reposter\u00cdas",
    "sg:phone":"+34 925 75 72 94",
    "sg:postcode":"45533",
    "sg:province":"Toledo",
    "wof:name":"Ahijado Pizarro Antonio",
    "wof:placetype":"venue"
},
  "geometry": {"coordinates":[-4.4534568787,39.8871688843],"type":"Point"}
}