{
  "type": "Feature",
  "properties": {
    "addr:full":"Av Josep Tarradellas, 8 Barcelona Barcelona 08029",
    "addr:housenumber":"8",
    "addr:postcode":"08029",
    "addr:street":"Av Josep Tarradellas",
    "iso:country":"ES",
    "sg:address":"Av Josep Tarradellas, 8",
    "sg:city":"Barcelona",
    "sg:orig_category":"Servidores Y Editores De Bases De Datos",
    "sg:phone":"+34 933 63 33 47",
    "sg:postcode":"08029",
    "sg:province":"Barcelona",
    "sg:website":"www.acens.com",
    "wof:name":"Acens Technologies S.a.",
    "wof:placetype":"venue"
},
  "geometry": {"coordinates":[2.1430306435,41.387046814],"type":"Point"}
}