{
  "type": "Feature",
  "properties": {
    "iso:country":"ES",
    "sg:address":"Calle de San Gines, 75",
    "sg:city":"Guare\u00f1a",
    "sg:orig_category":"Cajas Y Embalajes De Madera",
    "sg:phone":"+34 924 35 03 85",
    "sg:postcode":"06470",
    "sg:province":"Badajoz",
    "wof:name":"Gomez Rodriguez Ramon",
    "wof:placetype":"venue"
},
  "geometry": {"coordinates":[-6.1045389175,38.864151001],"type":"Point"}
}