{
  "type": "Feature",
  "properties": {
    "iso:country":"ES",
    "sg:address":"Avda Pablo Neruda, 38",
    "sg:city":"Madrid",
    "sg:orig_category":"Farmacias",
    "sg:phone":"+34 917 77 16 27",
    "sg:postcode":"28038",
    "sg:province":"Madrid",
    "wof:name":"Martinez Melero Julia",
    "wof:placetype":"venue"
},
  "geometry": {"coordinates":[-3.6438319683,40.3896903992],"type":"Point"}
}