{
  "type": "Feature",
  "properties": {
    "iso:country":"ES",
    "sg:address":"Avda Republica Argentina, 32",
    "sg:city":"Sevilla",
    "sg:orig_category":"Asesor\u00cda Sobre Comunicaci\u00d3n De Empresas",
    "sg:phone":"+34 954 45 46 39",
    "sg:postcode":"41011",
    "sg:province":"Sevilla",
    "wof:name":"Defensa Y Tecnica Empresarial S. A.",
    "wof:placetype":"venue"
},
  "geometry": {"coordinates":[-6.0035290718,37.3769683838],"type":"Point"}
}