{
  "type": "Feature",
  "properties": {
    "iso:country":"ES",
    "sg:address":"Calle de San Francisco, 47",
    "sg:city":"Aranda Duero",
    "sg:orig_category":"Agencias Y Agentes Comerciales, Representantes",
    "sg:phone":"+34 947 51 14 73",
    "sg:postcode":"09400",
    "sg:province":"Burgos",
    "wof:name":"Fernandez Arranz Maria Angeles",
    "wof:placetype":"venue"
},
  "geometry": {"coordinates":[-3.6858079433,41.6761016846],"type":"Point"}
}