{
  "type": "Feature",
  "properties": {
    "addr:full":"Calle de Cardenal Paya, 117 Beneixama Alicante 03460",
    "addr:housenumber":"117",
    "addr:postcode":"03460",
    "addr:street":"Calle De Cardenal Paya",
    "iso:country":"ES",
    "sg:address":"Calle de Cardenal Paya, 117",
    "sg:city":"Beneixama",
    "sg:orig_category":"Fabricaci\u00d3n De Su\u00c9ters Y Chalecos De Punto",
    "sg:phone":"+34 965 82 21 14",
    "sg:postcode":"03460",
    "sg:province":"Alicante",
    "wof:name":"Hijos De Celestino Berenguer S. A.",
    "wof:placetype":"venue"
},
  "geometry": {"coordinates":[-0.7637891769,38.6998977661],"type":"Point"}
}