{
  "type": "Feature",
  "properties": {
    "iso:country":"ES",
    "sg:address":"Calle de Juan Arnela, 7",
    "sg:city":"Garrovilla",
    "sg:orig_category":"Maquinaria Para Industrias Diversas",
    "sg:phone":"+34 924 33 53 61",
    "sg:postcode":"06870",
    "sg:province":"Badajoz",
    "wof:name":"Gomez Casado Manuel",
    "wof:placetype":"venue"
},
  "geometry": {"coordinates":[-6.4767727852,38.9211769104],"type":"Point"}
}