{
  "type": "Feature",
  "properties": {
    "addr:full":"Calle de Angel Mugica, 4 Madrid Madrid 28034",
    "addr:housenumber":"4",
    "addr:postcode":"28034",
    "addr:street":"Calle De Angel Mugica",
    "iso:country":"ES",
    "sg:address":"Calle de Angel Mugica, 4",
    "sg:city":"Madrid",
    "sg:orig_category":"Librer\u00cdas",
    "sg:phone":"+34 917 29 13 53",
    "sg:postcode":"28034",
    "sg:province":"Madrid",
    "wof:name":"Palma Garcia Francisco",
    "wof:placetype":"venue"
},
  "geometry": {"coordinates":[-3.6852824688,40.4850006104],"type":"Point"}
}