{
  "type": "Feature",
  "properties": {
    "addr:full":"Carrer de Joan Maragall, 38 Sant Sadurni D'anoia Barcelona 08770",
    "addr:housenumber":"38",
    "addr:postcode":"08770",
    "addr:street":"Carrer De Joan Maragall",
    "iso:country":"ES",
    "sg:address":"Carrer de Joan Maragall, 38",
    "sg:city":"Sant Sadurni D'anoia",
    "sg:orig_category":"Material Y Herramientas Agr\u00cdcolas",
    "sg:phone":"+34 938 91 05 62",
    "sg:postcode":"08770",
    "sg:province":"Barcelona",
    "wof:name":"Maquinaria Agricola Parroth S.l.",
    "wof:placetype":"venue"
},
  "geometry": {"coordinates":[1.611948967,41.5836410522],"type":"Point"}
}