{
  "type": "Feature",
  "properties": {
    "iso:country":"ES",
    "sg:address":"Calle de Presidente Rivadavia, 2",
    "sg:city":"Cadiz",
    "sg:orig_category":"Asesor\u00cda, Estudio Y Control Medioambiental",
    "sg:phone":"+34 956 22 50 31",
    "sg:postcode":"11001",
    "sg:province":"C\u00e1diz",
    "wof:name":"Gabinete Estudios Del Territorio Reshef S.l.",
    "wof:placetype":"venue"
},
  "geometry": {"coordinates":[-6.2902388573,36.5298614502],"type":"Point"}
}