{
  "type": "Feature",
  "properties": {
    "iso:country":"ES",
    "sg:address":"C/ Olesa, 9",
    "sg:city":"Manacor",
    "sg:orig_category":"Internados & Ense\u00d1anza Privada",
    "sg:phone":"+34 971 55 17 37",
    "sg:postcode":"07500",
    "sg:province":"Islas Baleares",
    "wof:name":"Convento De Las Hermanas De La Caridad",
    "wof:placetype":"venue"
},
  "geometry": {"coordinates":[3.210050106,39.5671806335],"type":"Point"}
}