{
  "type": "Feature",
  "properties": {
    "iso:country":"ES",
    "sg:address":"Calle de Gante, 9",
    "sg:city":"Toledo",
    "sg:orig_category":"Electrodom\u00c9sticos (al Por Menor)",
    "sg:phone":"+34 925 22 85 29",
    "sg:postcode":"45005",
    "sg:province":"Toledo",
    "wof:name":"Santorio Gomez Vicente",
    "wof:placetype":"venue"
},
  "geometry": {"coordinates":[-4.0300788879,39.8700714111],"type":"Point"}
}