{
  "type": "Feature",
  "properties": {
    "addr:full":"Carrer de Mallorca, 590 Barcelona Barcelona 08026",
    "addr:housenumber":"590",
    "addr:postcode":"08026",
    "addr:street":"Carrer De Mallorca",
    "iso:country":"ES",
    "sg:address":"Carrer de Mallorca, 590",
    "sg:city":"Barcelona",
    "sg:orig_category":"Supermercados Y Hipermercados",
    "sg:phone":"+34 932 32 02 21",
    "sg:postcode":"08026",
    "sg:province":"Barcelona",
    "wof:name":"Superficies De Alimentacion S. A.",
    "wof:placetype":"venue"
},
  "geometry": {"coordinates":[2.1848459244,41.4103775024],"type":"Point"}
}