{
  "type": "Feature",
  "properties": {
    "iso:country":"ES",
    "sg:address":"Avda Constitucion, 7",
    "sg:city":"Alacant",
    "sg:orig_category":"Heladeros",
    "sg:phone":"+34 965 20 06 15",
    "sg:postcode":"03002",
    "sg:province":"Alicante",
    "wof:name":"Gisbert Valls Jose Luis",
    "wof:placetype":"venue"
},
  "geometry": {"coordinates":[-0.4858720005,38.3472824097],"type":"Point"}
}