{
  "type": "Feature",
  "properties": {
    "addr:full":"Carrer de Rossello, 33 Mataro Barcelona 08303",
    "addr:housenumber":"33",
    "addr:postcode":"08303",
    "addr:street":"Carrer De Rossello",
    "iso:country":"ES",
    "sg:address":"Carrer de Rossello, 33",
    "sg:city":"Mataro",
    "sg:orig_category":"Telas Y Sedas (al Por Menor)",
    "sg:phone":"+34 937 99 37 55",
    "sg:postcode":"08303",
    "sg:province":"Barcelona",
    "wof:name":"Magester Granollers Elisa",
    "wof:placetype":"venue"
},
  "geometry": {"coordinates":[2.4250249863,41.539150238],"type":"Point"}
}