{
  "type": "Feature",
  "properties": {
    "addr:full":"Calle de Tejuela, 44 Alcala Real Ja\u00e9n 23680",
    "addr:housenumber":"44",
    "addr:postcode":"23680",
    "addr:street":"Calle De Tejuela;Jae\u0301N",
    "iso:country":"ES",
    "sg:address":"Calle de Tejuela, 44",
    "sg:city":"Alcala Real",
    "sg:orig_category":"Chapister\u00cda",
    "sg:phone":"+34 953 58 25 10",
    "sg:postcode":"23680",
    "sg:province":"Ja\u00e9n",
    "wof:name":"Lopez Perez Vicente",
    "wof:placetype":"venue"
},
  "geometry": {"coordinates":[-3.9251089096,37.4667205811],"type":"Point"}
}