{
  "type": "Feature",
  "properties": {
    "addr:full":"Calle de Yebenes, 150 Madrid Madrid 28047",
    "addr:housenumber":"150",
    "addr:postcode":"28047",
    "addr:street":"Calle De Yebenes",
    "iso:country":"ES",
    "sg:address":"Calle de Yebenes, 150",
    "sg:city":"Madrid",
    "sg:orig_category":"Electricidad Veh\u00cdculo",
    "sg:phone":"+34 917 19 40 26",
    "sg:postcode":"28047",
    "sg:province":"Madrid",
    "wof:name":"Moreno Rojo Marcelino",
    "wof:placetype":"venue"
},
  "geometry": {"coordinates":[-3.7517690659,40.3903617859],"type":"Point"}
}