{
  "type": "Feature",
  "properties": {
    "addr:full":"Calle de Canalejas, 28 Almoradi Alicante 03160",
    "addr:housenumber":"28",
    "addr:postcode":"03160",
    "addr:street":"Calle De Canalejas",
    "iso:country":"ES",
    "sg:address":"Calle de Canalejas, 28",
    "sg:city":"Almoradi",
    "sg:orig_category":"Molduras, Junquillos, Listones Y Molduras Perforadas",
    "sg:phone":"+34 965 70 01 36",
    "sg:postcode":"03160",
    "sg:province":"Alicante",
    "wof:name":"Benitez Gomez Pablo Anibal",
    "wof:placetype":"venue"
},
  "geometry": {"coordinates":[-0.7911390066,38.1122817993],"type":"Point"}
}