{
  "type": "Feature",
  "properties": {
    "iso:country":"ES",
    "sg:address":"Carrer de Mare De Deu Dels Angels, 2",
    "sg:city":"Barcelona",
    "sg:orig_category":"Empresas De Pintura Y Revestimientos",
    "sg:phone":"+34 933 58 66 50",
    "sg:postcode":"08035",
    "sg:province":"Barcelona",
    "wof:name":"Azorin Sanchez Joaquin",
    "wof:placetype":"venue"
},
  "geometry": {"coordinates":[2.1467700005,41.4212417603],"type":"Point"}
}