{
  "type": "Feature",
  "properties": {
    "iso:country":"ES",
    "sg:address":"Carrer de Doctor Joaquim Masmitja, 12",
    "sg:city":"Olot",
    "sg:orig_category":"Agencias Y Asesores De Publicidad",
    "sg:phone":"+34 972 26 42 78",
    "sg:postcode":"17800",
    "sg:province":"Girona",
    "wof:name":"Genesis Sociedad Anonima De Publicidad General",
    "wof:placetype":"venue"
},
  "geometry": {"coordinates":[2.4879970551,42.1843528748],"type":"Point"}
}