{
  "type": "Feature",
  "properties": {
    "iso:country":"ES",
    "sg:address":"Avda Cortijos Los, S/n",
    "sg:city":"Sotogrande",
    "sg:orig_category":"Arquitectos",
    "sg:phone":"+34 956 69 54 54",
    "sg:postcode":"11310",
    "sg:province":"C\u00e1diz",
    "wof:name":"Gayarre Lopez De Tejada Salvador Enrique",
    "wof:placetype":"venue"
},
  "geometry": {"coordinates":[-5.3471941948,36.2757606506],"type":"Point"}
}