{
  "type": "Feature",
  "properties": {
    "iso:country":"ES",
    "sg:address":"Carrer de Sant Pasqual Bailon, 6",
    "sg:city":"Barcelona",
    "sg:orig_category":"Artes Gr\u00c1ficas, Artes Pl\u00c1sticas (curso)",
    "sg:phone":"+34 933 49 96 51",
    "sg:postcode":"08027",
    "sg:province":"Barcelona",
    "wof:name":"Ortega Marco Nuria",
    "wof:placetype":"venue"
},
  "geometry": {"coordinates":[2.1785149574,41.4272003174],"type":"Point"}
}