{
  "type": "Feature",
  "properties": {
    "iso:country":"ES",
    "sg:address":"Calle de Doctor Horno Alcorta, 5",
    "sg:city":"Zaragoza",
    "sg:classifiers":[
        {
            "category":"Professional",
            "subcategory":"Management & Consulting",
            "type":"Services"
        }
    ],
    "sg:phone":"+34 976 55 17 32",
    "sg:postcode":"50004",
    "sg:province":"Zaragoza",
    "sg:tags":[
        "asesor\u00cda",
        "en",
        "marketing"
    ],
    "wof:name":"Madrid Redes De Campo S.a.",
    "wof:placetype":"venue"
},
  "geometry": {"coordinates":[-0.8897505999,41.6506118774],"type":"Point"}
}