{
  "type": "Feature",
  "properties": {
    "iso:country":"ES",
    "sg:address":"Calle de Prado Del, 22",
    "sg:city":"Aviles",
    "sg:orig_category":"Caf\u00c9s, Bares, Cervecer\u00cdas",
    "sg:phone":"+34 985 56 59 11",
    "sg:postcode":"33401",
    "sg:province":"Asturias",
    "wof:name":"Sociedad Regional De Informatica, S.a.",
    "wof:placetype":"venue"
},
  "geometry": {"coordinates":[-5.9311900139,43.5588226318],"type":"Point"}
}