{
  "type": "Feature",
  "properties": {
    "addr:full":"Pl Agusti Querol (d'), 4 Tortosa Tarragona 43500",
    "addr:housenumber":"4",
    "addr:postcode":"43500",
    "addr:street":"Pl Agusti Querol D '",
    "iso:country":"ES",
    "sg:address":"Pl Agusti Querol (d'), 4",
    "sg:city":"Tortosa",
    "sg:orig_category":"Agencias Y Agentes Comerciales, Representantes",
    "sg:phone":"+34 977 44 24 34",
    "sg:postcode":"43500",
    "sg:province":"Tarragona",
    "wof:name":"Andreu Curto Lut",
    "wof:placetype":"venue"
},
  "geometry": {"coordinates":[0.5216466188,40.812625885],"type":"Point"}
}