{
  "type": "Feature",
  "properties": {
    "addr:full":"Avda Ponte, 80 Gorxal Pontevedra 36318",
    "addr:housenumber":"80",
    "addr:postcode":"36318",
    "addr:street":"Avda Ponte",
    "iso:country":"ES",
    "sg:address":"Avda Ponte, 80",
    "sg:city":"Gorxal",
    "sg:orig_category":"Internados & Ense\u00d1anza Privada",
    "sg:phone":"+34 986 37 25 27",
    "sg:postcode":"36318",
    "sg:province":"Pontevedra",
    "wof:name":"Centro De Estudios Marcote Sl",
    "wof:placetype":"venue"
},
  "geometry": {"coordinates":[-8.6428003311,42.4304618835],"type":"Point"}
}