{
  "type": "Feature",
  "properties": {
    "iso:country":"ES",
    "sg:address":"Calle de Secorun, S/n",
    "sg:city":"Sabi\u00f1anigo",
    "sg:orig_category":"Maquinaria Para Industrias Diversas",
    "sg:phone":"+34 974 48 13 98",
    "sg:postcode":"22600",
    "sg:province":"Huesca",
    "wof:name":"Alquileres Y Servicios Pirenaicos S.l.",
    "wof:placetype":"venue"
},
  "geometry": {"coordinates":[-0.3602100015,42.52709198],"type":"Point"}
}