{
  "type": "Feature",
  "properties": {
    "iso:country":"ES",
    "sg:address":"Calle de Eduardo Dato, 9",
    "sg:city":"Sari\u00f1ena",
    "sg:orig_category":"Peluquer\u00cdas, Peluquer\u00cda Mixta",
    "sg:phone":"+34 974 57 07 60",
    "sg:postcode":"22200",
    "sg:province":"Huesca",
    "wof:name":"Carbajo Casas Ana Maria",
    "wof:placetype":"venue"
},
  "geometry": {"coordinates":[-0.1572269946,41.7925605774],"type":"Point"}
}