{
  "type": "Feature",
  "properties": {
    "iso:country":"ES",
    "sg:address":"Plaz Mayor, 29",
    "sg:city":"Burgos",
    "sg:orig_category":"Juegos Y Juguetes (al Por Menor)",
    "sg:phone":"+34 947 20 38 47",
    "sg:postcode":"09003",
    "sg:province":"Burgos",
    "wof:name":"Chapero S. L.",
    "wof:placetype":"venue"
},
  "geometry": {"coordinates":[-3.7014570236,42.3411331177],"type":"Point"}
}