{
  "type": "Feature",
  "properties": {
    "iso:country":"ES",
    "sg:address":"Cmno Portu, 8",
    "sg:city":"Zangroiz",
    "sg:orig_category":"Publicidad (soportes Y Gesti\u00d3n)",
    "sg:phone":"+34 944 35 22 72",
    "sg:postcode":"48150",
    "sg:province":"Vizcaya",
    "wof:name":"Vehiculos Publicitarios S.l.",
    "wof:placetype":"venue"
},
  "geometry": {"coordinates":[-2.9244790077,43.2990455627],"type":"Point"}
}