{
  "type": "Feature",
  "properties": {
    "addr:full":"Calle de San Francisco, 8 Torrejon Ardoz Madrid 28850",
    "addr:housenumber":"8",
    "addr:postcode":"28850",
    "addr:street":"Calle De San Francisco",
    "iso:country":"ES",
    "sg:address":"Calle de San Francisco, 8",
    "sg:city":"Torrejon Ardoz",
    "sg:orig_category":"Ebanistas Y Talladores De Muebles Y Objetos De Arte",
    "sg:phone":"+34 916 75 09 54",
    "sg:postcode":"28850",
    "sg:province":"Madrid",
    "wof:name":"Calero Toril Bartolome",
    "wof:placetype":"venue"
},
  "geometry": {"coordinates":[-3.4637920856,40.4404678345],"type":"Point"}
}