{
  "type": "Feature",
  "properties": {
    "iso:country":"ES",
    "sg:address":"Calle de Alfredo Calderon, 18",
    "sg:city":"Palmas De Gran Canaria",
    "sg:orig_category":"Inform\u00c1tica: Mantenimiento Y Reparaci\u00d3n De Ordenadores",
    "sg:phone":"+34 928 23 23 32",
    "sg:postcode":"35006",
    "sg:province":"Las Palmas",
    "sg:website":"www.getronics.com",
    "wof:name":"Getronics Espa\u00f1a Solutions S.r.l.",
    "wof:placetype":"venue"
},
  "geometry": {"coordinates":[-15.431101799,28.1305580139],"type":"Point"}
}