{
  "type": "Feature",
  "properties": {
    "addr:full":"Trav De Gracia, 396 Barcelona Barcelona 08025",
    "addr:housenumber":"396",
    "addr:postcode":"08025",
    "addr:street":"Trav De Gracia",
    "iso:country":"ES",
    "sg:address":"Trav De Gracia, 396",
    "sg:city":"Barcelona",
    "sg:orig_category":"Embalajes",
    "sg:phone":"+34 934 50 38 76",
    "sg:postcode":"08025",
    "sg:province":"Barcelona",
    "wof:name":"Pack Service S.a.",
    "wof:placetype":"venue"
},
  "geometry": {"coordinates":[2.1737380028,41.4113235474],"type":"Point"}
}