{
  "type": "Feature",
  "properties": {
    "addr:full":"Calle de Garran, 3 Najera La Rioja 26300",
    "addr:housenumber":"3",
    "addr:postcode":"26300",
    "addr:street":"Calle De Garran;Rioja",
    "iso:country":"ES",
    "sg:address":"Calle de Garran, 3",
    "sg:city":"Najera",
    "sg:orig_category":"Art\u00cdculos De Regalo (al Por Menor)",
    "sg:phone":"+34 941 36 17 39",
    "sg:postcode":"26300",
    "sg:province":"La Rioja",
    "wof:name":"Narval 99 S.l.",
    "wof:placetype":"venue"
},
  "geometry": {"coordinates":[-2.7343189716,42.4165992737],"type":"Point"}
}