{
  "type": "Feature",
  "properties": {
    "addr:full":"Calle de Paraje De Paterna, S/n Bormujos Sevilla 41930",
    "addr:housenumber":"s / n",
    "addr:postcode":"41930",
    "addr:street":"Calle De Paraje De Paterna",
    "iso:country":"ES",
    "sg:address":"Calle de Paraje De Paterna, S/n",
    "sg:city":"Bormujos",
    "sg:orig_category":"Alquiler De Casas Y Habitaciones Amuebladas",
    "sg:phone":"+34 955 72 39 00",
    "sg:postcode":"41930",
    "sg:province":"Sevilla",
    "wof:name":"Campus Patrimonial S.a",
    "wof:placetype":"venue"
},
  "geometry": {"coordinates":[-6.0771598816,37.3668136597],"type":"Point"}
}