{
  "type": "Feature",
  "properties": {
    "iso:country":"ES",
    "sg:address":"Calle de Jose Echegaray (de), 4",
    "sg:city":"Alcobendas",
    "sg:orig_category":"Asesor\u00cda Sobre Comunicaci\u00d3n De Empresas",
    "sg:phone":"+34 916 61 80 35",
    "sg:postcode":"28100",
    "sg:province":"Madrid",
    "wof:name":"Acf Consultores S.l.",
    "wof:placetype":"venue"
},
  "geometry": {"coordinates":[-3.6549253464,40.5418891907],"type":"Point"}
}