{
  "type": "Feature",
  "properties": {
    "addr:full":"Rbla. J. Maria Jujol, 51 S. Joan Despi Barcelona 08970",
    "addr:housenumber":"51",
    "addr:postcode":"08970",
    "addr:street":"J. Maria Jujol;S. Joan Despi",
    "iso:country":"ES",
    "sg:address":"Rbla. J. Maria Jujol, 51",
    "sg:city":"S. Joan Despi",
    "sg:orig_category":"Cajas De Ahorro",
    "sg:phone":"+34 934 77 04 81",
    "sg:postcode":"08970",
    "sg:province":"Barcelona",
    "sg:website":"www.caixacatalunya.es",
    "wof:name":"Caixa D'estalvis De Catalunya",
    "wof:placetype":"venue"
},
  "geometry": {"coordinates":[2.0706489086,41.3694610596],"type":"Point"}
}