{
  "type": "Feature",
  "properties": {
    "iso:country":"ES",
    "sg:address":"Calle de Nobles, 18",
    "sg:city":"Huetor-tajar",
    "sg:orig_category":"Promotores Constructores",
    "sg:phone":"+34 958 33 38 96",
    "sg:postcode":"18360",
    "sg:province":"Granada",
    "wof:name":"Construcciones Hermanos Pe\u00f1a Roldan S.l.",
    "wof:placetype":"venue"
},
  "geometry": {"coordinates":[-4.0451889038,37.1962127686],"type":"Point"}
}