{
  "type": "Feature",
  "properties": {
    "addr:full":"Calle de Monago Torre Kalea, 2 Durango Vizcaya 48200",
    "addr:housenumber":"2",
    "addr:postcode":"48200",
    "addr:street":"Calle De Monago Torre Kalea",
    "iso:country":"ES",
    "sg:address":"Calle de Monago Torre Kalea, 2",
    "sg:city":"Durango",
    "sg:orig_category":"Frutas, Legumbres Frescas Y Tempranas (al Por Menor)",
    "sg:phone":"+34 946 20 43 33",
    "sg:postcode":"48200",
    "sg:province":"Vizcaya",
    "wof:name":"Fruteria Marrubi",
    "wof:placetype":"venue"
},
  "geometry": {"coordinates":[-2.6327190399,43.1716842651],"type":"Point"}
}