{
  "type": "Feature",
  "properties": {
    "addr:full":"Calle de Musico Jose Torregrosa, S/n Villafranqueza - Palamo Alicante 03112",
    "addr:housenumber":"s / n",
    "addr:postcode":"03112",
    "addr:street":"Calle De Musico Jose Torregrosa;Villafranqueza Palamo",
    "iso:country":"ES",
    "sg:address":"Calle de Musico Jose Torregrosa, S/n",
    "sg:city":"Villafranqueza - Palamo",
    "sg:orig_category":"Cajas De Ahorro",
    "sg:phone":"+34 965 17 86 11",
    "sg:postcode":"03112",
    "sg:province":"Alicante",
    "wof:name":"Caja De Ahorros Del Mediterraneo",
    "wof:placetype":"venue"
},
  "geometry": {"coordinates":[-0.4690259993,38.4094772339],"type":"Point"}
}