{
  "type": "Feature",
  "properties": {
    "addr:full":"Calle de Cervantes, 13 Horcajo De Los Montes Ciudad Real 13110",
    "addr:housenumber":"13",
    "addr:postcode":"13110",
    "addr:street":"Calle De Cervantes",
    "iso:country":"ES",
    "sg:address":"Calle de Cervantes, 13",
    "sg:city":"Horcajo De Los Montes",
    "sg:orig_category":"Cajas Para Embalar",
    "sg:phone":"+34 926 77 52 18",
    "sg:postcode":"13110",
    "sg:province":"Ciudad Real",
    "wof:name":"Caja Rural De Ciudad Real",
    "wof:placetype":"venue"
},
  "geometry": {"coordinates":[-4.6499361992,39.3263664246],"type":"Point"}
}