{
  "type": "Feature",
  "properties": {
    "iso:country":"ES",
    "sg:address":"Avda Marques De Los Velez, S/n",
    "sg:city":"Vista Alegre",
    "sg:orig_category":"Restaurantes",
    "sg:phone":"+34 968 24 77 40",
    "sg:postcode":"30008",
    "sg:province":"Murcia",
    "wof:name":"Eurest Colectividades",
    "wof:placetype":"venue"
},
  "geometry": {"coordinates":[-1.1309310198,37.9965934753],"type":"Point"}
}