{
  "type": "Feature",
  "properties": {
    "addr:full":"Calle de Garbileku, 5 Elexalde Vizcaya 48970",
    "addr:housenumber":"5",
    "addr:postcode":"48970",
    "addr:street":"Calle De Garbileku",
    "iso:country":"ES",
    "sg:address":"Calle de Garbileku, 5",
    "sg:city":"Elexalde",
    "sg:orig_category":"Institutos De Belleza",
    "sg:phone":"+34 944 49 40 76",
    "sg:postcode":"48970",
    "sg:province":"Vizcaya",
    "wof:name":"Garcia Coria Manuela",
    "wof:placetype":"venue"
},
  "geometry": {"coordinates":[-2.8872718811,43.2221412659],"type":"Point"}
}