{
  "type": "Feature",
  "properties": {
    "addr:full":"Rond General Mitre, 152 Barcelona Barcelona 08006",
    "addr:housenumber":"152",
    "addr:postcode":"08006",
    "addr:street":"Mitre",
    "iso:country":"ES",
    "sg:address":"Rond General Mitre, 152",
    "sg:city":"Barcelona",
    "sg:orig_category":"Molduras, Junquillos, Listones Y Molduras Perforadas",
    "sg:phone":"+34 932 09 24 80",
    "sg:postcode":"08006",
    "sg:province":"Barcelona",
    "wof:name":"Canelas Escudero Luciano",
    "wof:placetype":"venue"
},
  "geometry": {"coordinates":[2.139359951,41.4037208557],"type":"Point"}
}