{
  "type": "Feature",
  "properties": {
    "iso:country":"ES",
    "sg:address":"Calle de Canal De Isabel Ii, 18",
    "sg:city":"San Sebastian De Los Reyes",
    "sg:orig_category":"El Hogar: Amueblado, Acondicionamiento, Decoraci\u00d3n Y Mantenimiento",
    "sg:phone":"+34 916 63 88 43",
    "sg:postcode":"28700",
    "sg:province":"Madrid",
    "wof:name":"Ghazali  Said",
    "wof:placetype":"venue"
},
  "geometry": {"coordinates":[-3.6370360851,40.5491065979],"type":"Point"}
}