{
  "type": "Feature",
  "properties": {
    "addr:full":"Calle de Velazquez, 15 Ubrique C\u00e1diz 11600",
    "addr:housenumber":"15",
    "addr:postcode":"11600",
    "addr:street":"Calle De Velazquez;Ca\u0301Diz",
    "iso:country":"ES",
    "sg:address":"Calle de Velazquez, 15",
    "sg:city":"Ubrique",
    "sg:orig_category":"Marroquiner\u00cda (confecci\u00d3n)",
    "sg:phone":"+34 956 46 35 13",
    "sg:postcode":"11600",
    "sg:province":"C\u00e1diz",
    "wof:name":"Lopez Rubiales Jose",
    "wof:placetype":"venue"
},
  "geometry": {"coordinates":[-5.4466438293,36.6796531677],"type":"Point"}
}