{
  "type": "Feature",
  "properties": {
    "iso:country":"ES",
    "sg:address":"C/ Ciutadella, 12",
    "sg:city":"Vilafant",
    "sg:orig_category":"Abogados",
    "sg:phone":"+34 972 54 60 24",
    "sg:postcode":"17740",
    "sg:province":"Girona",
    "wof:name":"Pineda Ginjaume Josep",
    "wof:placetype":"venue"
},
  "geometry": {"coordinates":[2.9383299351,42.2458381653],"type":"Point"}
}