{
  "type": "Feature",
  "properties": {
    "addr:full":"Calle de Pilar Monteverde, 9 Orotava Santa Cruz De Tenerife 38300",
    "addr:housenumber":"9",
    "addr:postcode":"38300",
    "addr:street":"Calle De Pilar Monteverde",
    "iso:country":"ES",
    "sg:address":"Calle de Pilar Monteverde, 9",
    "sg:city":"Orotava",
    "sg:orig_category":"Bazares, Art\u00cdculos De Limpieza Y De Cocina (al Por Menor)",
    "sg:phone":"+34 922 32 04 76",
    "sg:postcode":"38300",
    "sg:province":"Santa Cruz De Tenerife",
    "wof:name":"Porto Mata Roberto",
    "wof:placetype":"venue"
},
  "geometry": {"coordinates":[-16.5265407562,28.3931083679],"type":"Point"}
}