{
  "type": "Feature",
  "properties": {
    "addr:full":"Carrer de Tetuan, 8 Reus Tarragona 43205",
    "addr:housenumber":"8",
    "addr:postcode":"43205",
    "addr:street":"Carrer De Tetuan",
    "iso:country":"ES",
    "sg:address":"Carrer de Tetuan, 8",
    "sg:city":"Reus",
    "sg:orig_category":"Alimentaci\u00d3n General (al Por Menor)",
    "sg:phone":"+34 977 75 68 42",
    "sg:postcode":"43205",
    "sg:province":"Tarragona",
    "wof:name":"Ferrero Cerda Manuel",
    "wof:placetype":"venue"
},
  "geometry": {"coordinates":[1.1094609499,41.1508216858],"type":"Point"}
}