{
  "type": "Feature",
  "properties": {
    "addr:full":"Pla\u00c7 Espanya, 6 Camprodon Girona 17867",
    "addr:postcode":"6;17867",
    "iso:country":"ES",
    "sg:address":"Pla\u00c7 Espanya, 6",
    "sg:city":"Camprodon",
    "sg:orig_category":"Carnicer\u00cdas, Carnicer\u00cdas",
    "sg:phone":"+34 972 74 09 79",
    "sg:postcode":"17867",
    "sg:province":"Girona",
    "wof:name":"Carnisseria Tony S.c",
    "wof:placetype":"venue"
},
  "geometry": {"coordinates":[2.3646419048,42.3104515076],"type":"Point"}
}