{
  "type": "Feature",
  "properties": {
    "addr:full":"Calle de Alcala, 195 Madrid Madrid 28009",
    "addr:housenumber":"195",
    "addr:postcode":"28009",
    "addr:street":"Calle De Alcala",
    "iso:country":"ES",
    "sg:address":"Calle de Alcala, 195",
    "sg:city":"Madrid",
    "sg:orig_category":"Bisuter\u00cda, Joyer\u00cda, Relojer\u00cda (al Por Menor)",
    "sg:phone":"+34 914 01 16 43",
    "sg:postcode":"28009",
    "sg:province":"Madrid",
    "wof:name":"Fresno Arce Manuel",
    "wof:placetype":"venue"
},
  "geometry": {"coordinates":[-3.6691873074,40.4279174805],"type":"Point"}
}