{
  "type": "Feature",
  "properties": {
    "addr:full":"Calle de Patricio Ferrandiz, 16 Denia Alicante 03700",
    "addr:housenumber":"16",
    "addr:postcode":"03700",
    "addr:street":"Calle De Patricio Ferrandiz",
    "iso:country":"ES",
    "sg:address":"Calle de Patricio Ferrandiz, 16",
    "sg:city":"Denia",
    "sg:orig_category":"Librer\u00cdas",
    "sg:phone":"+34 965 78 05 43",
    "sg:postcode":"03700",
    "sg:province":"Alicante",
    "wof:name":"Prensa Dianense S. C.",
    "wof:placetype":"venue"
},
  "geometry": {"coordinates":[0.1056300029,38.8369369507],"type":"Point"}
}