{
  "type": "Feature",
  "properties": {
    "iso:country":"ES",
    "sg:address":"Calle de Chiva, 6",
    "sg:city":"Barrio Orba",
    "sg:orig_category":"Transportes Por Carretera: Lotes Completos, Mercanc\u00cdas Diversas",
    "sg:phone":"+34 963 75 47 17",
    "sg:postcode":"46910",
    "sg:province":"Valencia",
    "wof:name":"Oliver Narro Juan Manuel",
    "wof:placetype":"venue"
},
  "geometry": {"coordinates":[-0.063861303,38.7803611755],"type":"Point"}
}