{
  "type": "Feature",
  "properties": {
    "addr:full":"Rua Caeiro, S/n Caeiro Pontevedra 36215",
    "addr:housenumber":"s / n",
    "addr:postcode":"36215",
    "addr:street":"Rua Caeiro",
    "iso:country":"ES",
    "sg:address":"Rua Caeiro, S/n",
    "sg:city":"Caeiro",
    "sg:orig_category":"Vinos Y Licores (venta Al Por Menor)",
    "sg:phone":"+34 986 48 77 73",
    "sg:postcode":"36215",
    "sg:province":"Pontevedra",
    "wof:name":"Soto Estevez Francisco",
    "wof:placetype":"venue"
},
  "geometry": {"coordinates":[-8.663274765,42.2263412476],"type":"Point"}
}