{
  "type": "Feature",
  "properties": {
    "addr:full":"Via De Ronda, 13 El Paso Santa Cruz De Tenerife 38750",
    "addr:housenumber":"13",
    "addr:postcode":"38750",
    "addr:street":"Via De Ronda",
    "iso:country":"ES",
    "sg:address":"Via De Ronda, 13",
    "sg:city":"El Paso",
    "sg:orig_category":"Negocio De Materiales De Construcci\u00d3n",
    "sg:phone":"+34 922 49 71 35",
    "sg:postcode":"38750",
    "sg:province":"Santa Cruz De Tenerife",
    "wof:name":"Host Adoquines El Paso S.l.",
    "wof:placetype":"venue"
},
  "geometry": {"coordinates":[-17.8813228607,28.6505889893],"type":"Point"}
}