{
  "type": "Feature",
  "properties": {
    "addr:full":"Avda Zaragoza, 33 Tudela Navarra 31500",
    "addr:housenumber":"33",
    "addr:postcode":"31500",
    "addr:street":"Avda Zaragoza",
    "iso:country":"ES",
    "sg:address":"Avda Zaragoza, 33",
    "sg:city":"Tudela",
    "sg:orig_category":"Construcciones Prefabricadas Y Desmontables",
    "sg:phone":"+34 948 82 80 12",
    "sg:postcode":"31500",
    "sg:province":"Navarra",
    "wof:name":"Eneriz Y Reguant Gestiones S.l.",
    "wof:placetype":"venue"
},
  "geometry": {"coordinates":[-1.6009360552,42.059879303],"type":"Point"}
}