{
  "type": "Feature",
  "properties": {
    "addr:full":"Rua Dalias, 16 Carballo La Coru\u00f1a 15100",
    "addr:housenumber":"16",
    "addr:postcode":"15100",
    "addr:street":"Rua Dalias;La Corun\u0303A",
    "iso:country":"ES",
    "sg:address":"Rua Dalias, 16",
    "sg:city":"Carballo",
    "sg:orig_category":"Electricidad: Instaladores",
    "sg:phone":"+34 981 70 34 17",
    "sg:postcode":"15100",
    "sg:province":"La Coru\u00f1a",
    "wof:name":"Casas Rey Jesus",
    "wof:placetype":"venue"
},
  "geometry": {"coordinates":[-8.6989936829,43.2161750793],"type":"Point"}
}