{
  "type": "Feature",
  "properties": {
    "addr:full":"Rua Velle (de), 5 Velle Ourense 32960",
    "addr:housenumber":"5",
    "addr:postcode":"32960",
    "addr:street":"Rua Velle De",
    "iso:country":"ES",
    "sg:address":"Rua Velle (de), 5",
    "sg:city":"Velle",
    "sg:orig_category":"Confecci\u00d3n De Cinturones Y De Tirantes",
    "sg:phone":"+34 988 22 47 28",
    "sg:postcode":"32960",
    "sg:province":"Ourense",
    "wof:name":"Pousa A\u00f1el Antonio",
    "wof:placetype":"venue"
},
  "geometry": {"coordinates":[-7.8337731361,42.3690948486],"type":"Point"}
}