{
  "type": "Feature",
  "properties": {
    "addr:full":"Carrer de Escoles Pies, 109 Barcelona Barcelona 08017",
    "addr:housenumber":"109",
    "addr:postcode":"08017",
    "addr:street":"Carrer De Escoles Pies",
    "iso:country":"ES",
    "sg:address":"Carrer de Escoles Pies, 109",
    "sg:city":"Barcelona",
    "sg:orig_category":"Cl\u00cdnicas Dentales",
    "sg:phone":"+34 934 17 19 17",
    "sg:postcode":"08017",
    "sg:province":"Barcelona",
    "wof:name":"Metrometric S.a.",
    "wof:placetype":"venue"
},
  "geometry": {"coordinates":[2.1259100437,41.4054260254],"type":"Point"}
}