{
  "type": "Feature",
  "properties": {
    "addr:full":"Calle de Carreteria, 48 Cuenca Cuenca 16004",
    "addr:housenumber":"48",
    "addr:postcode":"16004",
    "addr:street":"Calle De Carreteria",
    "iso:country":"ES",
    "sg:address":"Calle de Carreteria, 48",
    "sg:city":"Cuenca",
    "sg:orig_category":"Lencer\u00cda Femenina, Corseter\u00cda, Trajes De Ba\u00d1o (al Por Menor)",
    "sg:phone":"+34 969 21 13 72",
    "sg:postcode":"16004",
    "sg:province":"Cuenca",
    "wof:name":"Luis Saez C.b.",
    "wof:placetype":"venue"
},
  "geometry": {"coordinates":[-2.1366837025,40.0732002258],"type":"Point"}
}