{
  "type": "Feature",
  "properties": {
    "iso:country":"ES",
    "sg:address":"Calle de Porcell, 7",
    "sg:city":"Zaragoza",
    "sg:orig_category":"Asilos De Ancianos. Centros Privados",
    "sg:phone":"+34 976 21 87 36",
    "sg:postcode":"50001",
    "sg:province":"Zaragoza",
    "wof:name":"Caridad De Santa Ana Hermanas De La Provincia Nuestra Senora Del Pilar Curia Provincial",
    "wof:placetype":"venue"
},
  "geometry": {"coordinates":[-0.8792849779,41.6507606506],"type":"Point"}
}