{
  "type": "Feature",
  "properties": {
    "addr:full":"Calle de Constancia, 30 Sevilla Sevilla 41010",
    "addr:housenumber":"30",
    "addr:postcode":"41010",
    "addr:street":"Calle De Constancia",
    "iso:country":"ES",
    "sg:address":"Calle de Constancia, 30",
    "sg:city":"Sevilla",
    "sg:orig_category":"Farmacias",
    "sg:phone":"+34 954 45 05 59",
    "sg:postcode":"41010",
    "sg:province":"Sevilla",
    "wof:name":"Leon Vizmanos Maria Jose",
    "wof:placetype":"venue"
},
  "geometry": {"coordinates":[-6.0057182312,37.377166748],"type":"Point"}
}