{
  "type": "Feature",
  "properties": {
    "addr:full":"Rua Cando, 1 Porri\u00f1o Pontevedra 36400",
    "addr:housenumber":"1",
    "addr:postcode":"36400",
    "addr:street":"Rua Cando",
    "iso:country":"ES",
    "sg:address":"Rua Cando, 1",
    "sg:city":"Porri\u00f1o",
    "sg:orig_category":"Peluquer\u00cdas, Peluquer\u00cda Mixta",
    "sg:phone":"+34 986 33 96 02",
    "sg:postcode":"36400",
    "sg:province":"Pontevedra",
    "wof:name":"Alvarez Gonzalez Maria Teresa",
    "wof:placetype":"venue"
},
  "geometry": {"coordinates":[-8.6213922501,42.1594810486],"type":"Point"}
}