{
  "type": "Feature",
  "properties": {
    "iso:country":"ES",
    "sg:address":"Calle de Miguel Redondo, 45",
    "sg:city":"Huelva",
    "sg:orig_category":"Filatelia",
    "sg:phone":"+34 959 25 42 76",
    "sg:postcode":"21003",
    "sg:province":"Huelva",
    "wof:name":"Garcia Garcia Jose",
    "wof:placetype":"venue"
},
  "geometry": {"coordinates":[-6.951002121,37.2539596558],"type":"Point"}
}