{
  "type": "Feature",
  "properties": {
    "addr:full":"Avda Constitucion (de La), 8 Mostoles Madrid 28931",
    "addr:postcode":"28931",
    "addr:street":"Avda Constitucion De La 8 Mostoles",
    "iso:country":"ES",
    "sg:address":"Avda Constitucion (de La), 8",
    "sg:city":"Mostoles",
    "sg:orig_category":"Comercios E Industrias (cesi\u00d3n Y Reactivaci\u00d3n)",
    "sg:phone":"+34 916 64 37 00",
    "sg:postcode":"28931",
    "sg:province":"Madrid",
    "wof:name":"Fedatarios Publicos De Mostoles S.c.",
    "wof:placetype":"venue"
},
  "geometry": {"coordinates":[-3.8635149002,40.3235931396],"type":"Point"}
}