{
  "type": "Feature",
  "properties": {
    "addr:full":"Carrer de Alguer, 34 Terrassa Barcelona 08226",
    "addr:housenumber":"34",
    "addr:postcode":"08226",
    "addr:street":"Carrer De Alguer",
    "iso:country":"ES",
    "sg:address":"Carrer de Alguer, 34",
    "sg:city":"Terrassa",
    "sg:orig_category":"Mec\u00c1nica Y Herramientas De Precisi\u00d3n",
    "sg:phone":"+34 937 35 42 84",
    "sg:postcode":"08226",
    "sg:province":"Barcelona",
    "wof:name":"Talleres Gibraltar S. A.",
    "wof:placetype":"venue"
},
  "geometry": {"coordinates":[2.0207579136,41.5833969116],"type":"Point"}
}