{
  "type": "Feature",
  "properties": {
    "addr:full":"Calle de Rectoria, 8 Fuentepelayo Segovia 40260",
    "addr:housenumber":"8",
    "addr:postcode":"40260",
    "addr:street":"Calle De Rectoria",
    "iso:country":"ES",
    "sg:address":"Calle de Rectoria, 8",
    "sg:city":"Fuentepelayo",
    "sg:orig_category":"Iglesia Cat\u00d3lica",
    "sg:phone":"+34 921 57 40 75",
    "sg:postcode":"40260",
    "sg:province":"Segovia",
    "wof:name":"Obispado Segovia",
    "wof:placetype":"venue"
},
  "geometry": {"coordinates":[-4.1774892807,41.221862793],"type":"Point"}
}