{
  "type": "Feature",
  "properties": {
    "addr:full":"Plaz Santo (del), S/n Caravaca Cruz Murcia 30400",
    "addr:housenumber":"/ n",
    "addr:postcode":"30400",
    "addr:street":"S;Caravaca Cruz",
    "iso:country":"ES",
    "sg:address":"Plaz Santo (del), S/n",
    "sg:city":"Caravaca Cruz",
    "sg:orig_category":"Orquestas Cl\u00c1sicas, Asociaciones De M\u00dasica, Coros Y Corales",
    "sg:phone":"+34 968 70 27 72",
    "sg:postcode":"30400",
    "sg:province":"Murcia",
    "wof:name":"Agrupacion Musical San Sebastian De Caravaca De La Cruz",
    "wof:placetype":"venue"
},
  "geometry": {"coordinates":[-1.8615913391,38.1066398621],"type":"Point"}
}