{
  "type": "Feature",
  "properties": {
    "addr:full":"Calle de Nuestra Se\u00d1ora De Los Dolores, 10 Jerez De La Frontera C\u00e1diz 11406",
    "addr:housenumber":"10",
    "addr:postcode":"11406",
    "addr:street":"Calle De Nuestra Sen\u0303Ora De Los Dolores",
    "iso:country":"ES",
    "sg:address":"Calle de Nuestra Se\u00d1ora De Los Dolores, 10",
    "sg:city":"Jerez De La Frontera",
    "sg:orig_category":"Farmacias",
    "sg:phone":"+34 956 34 47 75",
    "sg:postcode":"11406",
    "sg:province":"C\u00e1diz",
    "wof:name":"Ameneiro Bustos Enrique",
    "wof:placetype":"venue"
},
  "geometry": {"coordinates":[-6.1139435768,36.6848220825],"type":"Point"}
}