{
  "type": "Feature",
  "properties": {
    "iso:country":"ES",
    "sg:address":"Barr Veiga, S/n",
    "sg:city":"Veiga",
    "sg:orig_category":"Asociaciones Y Clubs Deportivos",
    "sg:phone":"+34 982 39 30 25",
    "sg:postcode":"27153",
    "sg:province":"Lugo",
    "wof:name":"Sociedad Deportiva Club De Campo Y Tiro De Lugo",
    "wof:placetype":"venue"
},
  "geometry": {"coordinates":[-7.537378788,43.0830574036],"type":"Point"}
}