{
  "type": "Feature",
  "properties": {
    "iso:country":"ES",
    "sg:address":"Calle de Bocinegro, 35",
    "sg:city":"Corralejo",
    "sg:orig_category":"Tapicer\u00cdas",
    "sg:phone":"+34 928 86 76 47",
    "sg:postcode":"35660",
    "sg:province":"Las Palmas",
    "wof:name":"Fe Gonzalez Ricardo De La",
    "wof:placetype":"venue"
},
  "geometry": {"coordinates":[-13.870382309,28.7412166595],"type":"Point"}
}