{
  "type": "Feature",
  "properties": {
    "addr:full":"Calle de Parreta, 28 Xirivella Valencia 46950",
    "addr:housenumber":"28",
    "addr:postcode":"46950",
    "addr:street":"Calle De Parreta",
    "iso:country":"ES",
    "sg:address":"Calle de Parreta, 28",
    "sg:city":"Xirivella",
    "sg:orig_category":"Ambulancias",
    "sg:phone":"+34 963 83 82 89",
    "sg:postcode":"46950",
    "sg:province":"Valencia",
    "wof:name":"Coordinacion Lopez S.l.",
    "wof:placetype":"venue"
},
  "geometry": {"coordinates":[-0.430456996,39.4654655457],"type":"Point"}
}