{
  "type": "Feature",
  "properties": {
    "iso:country":"ES",
    "sg:address":"Avda Alcalde Federico Molina, 50",
    "sg:city":"Huelva",
    "sg:orig_category":"Quincaller\u00cda (al Por Menor)",
    "sg:phone":"+34 959 22 16 47",
    "sg:postcode":"21006",
    "sg:province":"Huelva",
    "wof:name":"Perez Ortiz Aranzazu Inmaculada",
    "wof:placetype":"venue"
},
  "geometry": {"coordinates":[-6.933098793,37.2590103149],"type":"Point"}
}