{
  "type": "Feature",
  "properties": {
    "addr:full":"Rua Ramon Y Cajal, 4 Ourense Ourense 32001",
    "addr:housenumber":"4",
    "addr:postcode":"32001",
    "addr:street":"Rua Ramon Y Cajal",
    "iso:country":"ES",
    "sg:address":"Rua Ramon Y Cajal, 4",
    "sg:city":"Ourense",
    "sg:orig_category":"Tintorer\u00cdas, Limpieza En Seco",
    "sg:phone":"+34 988 21 86 21",
    "sg:postcode":"32001",
    "sg:province":"Ourense",
    "wof:name":"Rodriguez Fernandez Maria Josefa",
    "wof:placetype":"venue"
},
  "geometry": {"coordinates":[-7.8680438995,42.3476409912],"type":"Point"}
}