{
  "type": "Feature",
  "properties": {
    "iso:country":"ES",
    "sg:address":"Calle de Fernando Vela, 10",
    "sg:city":"Oviedo",
    "sg:orig_category":"Institutos De Belleza (productos Y Aparatos)",
    "sg:phone":"+34 985 11 68 93",
    "sg:postcode":"33001",
    "sg:province":"Asturias",
    "wof:name":"Aguilar Sanz Bego\u00d1a",
    "wof:placetype":"venue"
},
  "geometry": {"coordinates":[-5.8429532051,43.3668022156],"type":"Point"}
}