{
  "type": "Feature",
  "properties": {
    "addr:full":"Almacenes, 10 Villares Reina Salamanca 37184",
    "addr:postcode":"37184",
    "iso:country":"ES",
    "sg:address":"Almacenes, 10",
    "sg:city":"Villares Reina",
    "sg:orig_category":"Imprenta",
    "sg:phone":"+34 923 20 43 53",
    "sg:postcode":"37184",
    "sg:province":"Salamanca",
    "wof:name":"Gutierrez Quirce Jose Luis",
    "wof:placetype":"venue"
},
  "geometry": {"coordinates":[-5.6435341835,40.987411499],"type":"Point"}
}