{
  "type": "Feature",
  "properties": {
    "iso:country":"ES",
    "sg:address":"Carrer de Corro, 195",
    "sg:city":"Granollers",
    "sg:orig_category":"Asesor\u00cda Sobre Comunicaci\u00d3n De Empresas",
    "sg:phone":"+34 938 49 88 17",
    "sg:postcode":"08401",
    "sg:province":"Barcelona",
    "wof:name":"Met Valles Inversiones S.l.",
    "wof:placetype":"venue"
},
  "geometry": {"coordinates":[2.2900090218,41.6145706177],"type":"Point"}
}