{
  "type": "Feature",
  "properties": {
    "iso:country":"ES",
    "sg:address":"Avda Zunzunegui Juan Antonio, 5",
    "sg:city":"Bilbao",
    "sg:orig_category":"Centros Empresariales",
    "sg:phone":"+34 944 39 61 11",
    "sg:postcode":"48013",
    "sg:province":"Vizcaya",
    "wof:name":"Agrupacion Provincial De Auto-escuelas",
    "wof:placetype":"venue"
},
  "geometry": {"coordinates":[-2.9486384392,43.2616157532],"type":"Point"}
}