{
  "type": "Feature",
  "properties": {
    "addr:full":"Calle de Carretera Artajona, 7 Tafalla Navarra 31300",
    "addr:housenumber":"7",
    "addr:postcode":"31300",
    "addr:street":"Calle De Carretera Artajona",
    "iso:country":"ES",
    "sg:address":"Calle de Carretera Artajona, 7",
    "sg:city":"Tafalla",
    "sg:orig_category":"Bebidas",
    "sg:phone":"+34 948 70 02 84",
    "sg:postcode":"31300",
    "sg:province":"Navarra",
    "wof:name":"Espumosos Iru S.l.",
    "wof:placetype":"venue"
},
  "geometry": {"coordinates":[-1.674399972,42.5275344849],"type":"Point"}
}