{
  "type": "Feature",
  "properties": {
    "addr:full":"Calle de Pinzon, 31 Madrid Madrid 28025",
    "addr:housenumber":"31",
    "addr:postcode":"madrid;28025",
    "addr:street":"Calle De Pinzon",
    "iso:country":"ES",
    "sg:address":"Calle de Pinzon, 31",
    "sg:city":"Madrid",
    "sg:orig_category":"Caf\u00c9s, Bares, Cervecer\u00cdas",
    "sg:phone":"+34 914 62 04 66",
    "sg:postcode":"28025",
    "sg:province":"Madrid",
    "wof:name":"San Martin Leal Fernando",
    "wof:placetype":"venue"
},
  "geometry": {"coordinates":[-3.7399759293,40.3889656067],"type":"Point"}
}