{
  "type": "Feature",
  "properties": {
    "addr:full":"Luga Veta De La Serrana, S/n Bonanza C\u00e1diz 11540",
    "addr:housenumber":"s / n",
    "addr:postcode":"11540",
    "addr:street":"Serrana;Ca\u0301Diz",
    "iso:country":"ES",
    "sg:address":"Luga Veta De La Serrana, S/n",
    "sg:city":"Bonanza",
    "sg:orig_category":"Aguas (distribuci\u00d3n, Servicios)",
    "sg:phone":"+34 956 23 52 10",
    "sg:postcode":"11540",
    "sg:province":"C\u00e1diz",
    "wof:name":"Comunidad De Regantes Colonia Agricola Monte Algaida",
    "wof:placetype":"venue"
},
  "geometry": {"coordinates":[-6.3575987816,36.777721405],"type":"Point"}
}