{
  "type": "Feature",
  "properties": {
    "iso:country":"ES",
    "sg:address":"Calle de Podabines, 3",
    "sg:city":"Donostia-san Sebastian",
    "sg:orig_category":"Seguridad Social",
    "sg:phone":"+34 943 44 73 50",
    "sg:postcode":"20...",
    "sg:province":"Guip\u00f9zcoa",
    "wof:name":"Tesoreria General De La Seguridad Social-servicios Centrales",
    "wof:placetype":"venue"
},
  "geometry": {"coordinates":[-1.9796609879,43.3025054932],"type":"Point"}
}