{
  "type": "Feature",
  "properties": {
    "iso:country":"ES",
    "sg:address":"Cant Grande, 5",
    "sg:city":"Coru\u00d1a",
    "sg:orig_category":"M\u00c9dicos: Ginecolog\u00cda Y Obstetricia",
    "sg:phone":"+34 981 21 23 23",
    "sg:postcode":"15003",
    "sg:province":"La Coru\u00f1a",
    "wof:name":"Fernandez-villarrenaga Boedo Ana Maria",
    "wof:placetype":"venue"
},
  "geometry": {"coordinates":[-8.4023170471,43.3684387207],"type":"Point"}
}