{
  "type": "Feature",
  "properties": {
    "iso:country":"ES",
    "sg:address":"Calle de Zurbano, 34",
    "sg:city":"Madrid",
    "sg:orig_category":"Ropa Para Caballeros Y Se\u00d1oras (al Por Mayor)",
    "sg:phone":"+34 913 19 07 70",
    "sg:postcode":"28010",
    "sg:province":"Madrid",
    "wof:name":"In Fashion D'real S.l.",
    "wof:placetype":"venue"
},
  "geometry": {"coordinates":[-3.693377018,40.4302368164],"type":"Point"}
}