{
  "type": "Feature",
  "properties": {
    "iso:country":"ES",
    "sg:address":"Calle de Concordia, 5",
    "sg:city":"Cabeza Buey",
    "sg:orig_category":"Cooperativas Agr\u00cdcolas",
    "sg:phone":"+34 924 60 01 01",
    "sg:postcode":"06600",
    "sg:province":"Badajoz",
    "wof:name":"Cooperativa De Consumo Nuestra Se\u00f1ora De Belen",
    "wof:placetype":"venue"
},
  "geometry": {"coordinates":[-5.2199110985,38.7222709656],"type":"Point"}
}