{
  "type": "Feature",
  "properties": {
    "addr:full":"Carrer de Caputxes, 6 Barcelona Barcelona 08003",
    "addr:housenumber":"6",
    "addr:postcode":"08003",
    "addr:street":"Carrer De Caputxes",
    "iso:country":"ES",
    "sg:address":"Carrer de Caputxes, 6",
    "sg:city":"Barcelona",
    "sg:orig_category":"Restaurantes",
    "sg:phone":"+34 933 10 57 73",
    "sg:postcode":"08003",
    "sg:province":"Barcelona",
    "wof:name":"El Bon Sucre S.l.",
    "wof:placetype":"venue"
},
  "geometry": {"coordinates":[2.1817259789,41.3832054138],"type":"Point"}
}