{
  "type": "Feature",
  "properties": {
    "iso:country":"ES",
    "sg:address":"Avda Salobre\u00d1a, 41",
    "sg:city":"Motril",
    "sg:orig_category":"Colchones (fabricaci\u00d3n, Al Por Mayor, Al Por Menor)",
    "sg:phone":"+34 958 60 03 64",
    "sg:postcode":"18600",
    "sg:province":"Granada",
    "wof:name":"Colchoneria Moderna S.l.",
    "wof:placetype":"venue"
},
  "geometry": {"coordinates":[-3.5188140869,36.7434768677],"type":"Point"}
}