{
  "type": "Feature",
  "properties": {
    "iso:country":"ES",
    "sg:address":"Calle de Pilar Garcia Alonso, 12",
    "sg:city":"Sevilla",
    "sg:orig_category":"Agentes, Concesionarios Y Sucursales De Camiones Y Veh\u00cdculos Industriales",
    "sg:phone":"+34 954 51 17 94",
    "sg:postcode":"41007",
    "sg:province":"Sevilla",
    "wof:name":"Cualitys Rodes S.a.l.",
    "wof:placetype":"venue"
},
  "geometry": {"coordinates":[-5.9508390427,37.3911361694],"type":"Point"}
}