{
  "type": "Feature",
  "properties": {
    "iso:country":"ES",
    "sg:address":"Avda Andalucia (de), 201",
    "sg:city":"Estepa",
    "sg:orig_category":"Inform\u00c1tica, Ofim\u00c1tica (estudios, Asesor\u00cda, Ingenier\u00cda, Formaci\u00d3n)",
    "sg:phone":"+34 955 91 58 45",
    "sg:postcode":"41560",
    "sg:province":"Sevilla",
    "sg:website":"www.pcerainformatica.com",
    "wof:name":"Pc Era Informatica 1999 S.l.",
    "wof:placetype":"venue"
},
  "geometry": {"coordinates":[-4.8743171692,37.2935714722],"type":"Point"}
}