{
  "type": "Feature",
  "properties": {
    "addr:full":"Ctra Cadiz De, Km. 0202,0 Cala M\u00e1laga 29649",
    "addr:postcode":"29649",
    "addr:street":"Ctra Cadiz De Km. 0202,0 Cala Ma\u0301Laga",
    "iso:country":"ES",
    "sg:address":"Ctra Cadiz De, Km. 0202,0",
    "sg:city":"Cala",
    "sg:orig_category":"Art\u00cdculos De Decoraci\u00d3n",
    "sg:phone":"+34 952 49 42 31",
    "sg:postcode":"29649",
    "sg:province":"M\u00e1laga",
    "wof:name":"Constructuralia Andaluci S.l",
    "wof:placetype":"venue"
},
  "geometry": {"coordinates":[-4.7157039642,36.4931945801],"type":"Point"}
}