{
  "type": "Feature",
  "properties": {
    "iso:country":"ES",
    "sg:address":"Font, S/n",
    "sg:city":"Serra Daro",
    "sg:orig_category":"Electricidad Veh\u00cdculo",
    "sg:phone":"+34 972 75 76 03",
    "sg:postcode":"17133",
    "sg:province":"Girona",
    "wof:name":"Turon Costabella Juan",
    "wof:placetype":"venue"
},
  "geometry": {"coordinates":[3.0719320774,42.0287742615],"type":"Point"}
}