{
  "type": "Feature",
  "properties": {
    "addr:full":"Calle de Vazquez De Mella, 26 Alacant Alicante 03013",
    "addr:housenumber":"26",
    "addr:postcode":"03013",
    "addr:street":"Calle De Vazquez De Mella",
    "iso:country":"ES",
    "sg:address":"Calle de Vazquez De Mella, 26",
    "sg:city":"Alacant",
    "sg:orig_category":"Cl\u00cdnicas M\u00c9dicas",
    "sg:phone":"+34 965 20 78 25",
    "sg:postcode":"03013",
    "sg:province":"Alicante",
    "wof:name":"Radiocirugia San Francisco De Asis S. A.",
    "wof:placetype":"venue"
},
  "geometry": {"coordinates":[-0.479719013,38.3523902893],"type":"Point"}
}