{
  "type": "Feature",
  "properties": {
    "addr:full":"Carr Doctora Castells, 7 Lleida Lleida 25001",
    "addr:housenumber":"7",
    "addr:postcode":"25001",
    "addr:street":"Carr Doctora Castells",
    "iso:country":"ES",
    "sg:address":"Carr Doctora Castells, 7",
    "sg:city":"Lleida",
    "sg:orig_category":"Librer\u00cdas",
    "sg:phone":"+34 973 20 59 40",
    "sg:postcode":"25001",
    "sg:province":"Lleida",
    "wof:name":"Amoros Martinez Rafael",
    "wof:placetype":"venue"
},
  "geometry": {"coordinates":[0.6310222149,41.6114196777],"type":"Point"}
}