{
  "type": "Feature",
  "properties": {
    "addr:full":"Avda Doctor Villanueva, 41 Pontedeume La Coru\u00f1a 15600",
    "addr:housenumber":"41",
    "addr:postcode":"15600",
    "addr:street":"Avda Doctor Villanueva;La Corun\u0303A",
    "iso:country":"ES",
    "sg:address":"Avda Doctor Villanueva, 41",
    "sg:city":"Pontedeume",
    "sg:orig_category":"Peluqueros: De Se\u00d1oras",
    "sg:phone":"+34 981 43 20 94",
    "sg:postcode":"15600",
    "sg:province":"La Coru\u00f1a",
    "wof:name":"Gonzalez Rios Maria Dolores",
    "wof:placetype":"venue"
},
  "geometry": {"coordinates":[-8.1806650162,43.4109916687],"type":"Point"}
}