{
  "type": "Feature",
  "properties": {
    "addr:full":"Pl Cuba, 7 Mataro Barcelona 08302",
    "addr:housenumber":"7",
    "addr:postcode":"08302",
    "addr:street":"Pl Cuba",
    "iso:country":"ES",
    "sg:address":"Pl Cuba, 7",
    "sg:city":"Mataro",
    "sg:orig_category":"Papeler\u00cdas, Librer\u00cdas",
    "sg:phone":"+34 937 98 86 64",
    "sg:postcode":"08302",
    "sg:province":"Barcelona",
    "wof:name":"Mas Mas Jose",
    "wof:placetype":"venue"
},
  "geometry": {"coordinates":[2.4405939579,41.5377578735],"type":"Point"}
}