{
  "type": "Feature",
  "properties": {
    "iso:country":"ES",
    "sg:address":"Calle de Pedroso, S/n",
    "sg:city":"Noja",
    "sg:orig_category":"Hoteles",
    "sg:phone":"+34 942 63 00 74",
    "sg:postcode":"39180",
    "sg:province":"Cantabria",
    "wof:name":"Promociones Turisticas Zenit-mar S.a.",
    "wof:placetype":"venue"
},
  "geometry": {"coordinates":[-3.5206930637,43.483417511],"type":"Point"}
}