{
  "type": "Feature",
  "properties": {
    "iso:country":"ES",
    "sg:address":"Carr Creu, 10",
    "sg:city":"Girona",
    "sg:orig_category":"Restaurantes",
    "sg:phone":"+34 972 22 23 47",
    "sg:postcode":"17002",
    "sg:province":"Girona",
    "wof:name":"Santiago Cuadrado Antonio Jesus",
    "wof:placetype":"venue"
},
  "geometry": {"coordinates":[2.8187448978,41.9808616638],"type":"Point"}
}