{
  "type": "Feature",
  "properties": {
    "iso:country":"ES",
    "sg:address":"Calle de Lepanto, 43",
    "sg:city":"Corralejo",
    "sg:orig_category":"Fabricaci\u00d3n De Art\u00cdculos Y Equipos Deportivos Y De Ocio",
    "sg:phone":"+34 928 53 56 77",
    "sg:postcode":"35660",
    "sg:province":"Las Palmas",
    "wof:name":"Quinteiro Mi\u00f1ones Andres",
    "wof:placetype":"venue"
},
  "geometry": {"coordinates":[-13.8711690903,28.7388191223],"type":"Point"}
}