{
  "type": "Feature",
  "properties": {
    "addr:full":"Calle de Luis Suarez Ximielga, 14 Colloto Asturias 33010",
    "addr:housenumber":"14",
    "addr:postcode":"33010",
    "addr:street":"Calle De Luis Suarez Ximielga;Asturias",
    "iso:country":"ES",
    "sg:address":"Calle de Luis Suarez Ximielga, 14",
    "sg:city":"Colloto",
    "sg:orig_category":"Perfumer\u00cda Y Cosm\u00c9tica (fabricaci\u00d3n, Al Por Mayor)",
    "sg:phone":"+34 985 79 44 18",
    "sg:postcode":"33010",
    "sg:province":"Asturias",
    "wof:name":"Gonzalez Miguel Alejandro Desiderio",
    "wof:placetype":"venue"
},
  "geometry": {"coordinates":[-5.7993540764,43.3772239685],"type":"Point"}
}