{
  "type": "Feature",
  "properties": {
    "iso:country":"ES",
    "sg:address":"Calle de Maestro Salvador Ortiz, 17",
    "sg:city":"San Antolin",
    "sg:orig_category":"Inform\u00c1tica (estudios, Servicios, Asesor\u00cda, Formaci\u00d3n)",
    "sg:phone":"+34 968 28 64 00",
    "sg:postcode":"30004",
    "sg:province":"Murcia",
    "sg:website":"www.pc-dau.com",
    "wof:name":"Pc-dau Systemas S.l.",
    "wof:placetype":"venue"
},
  "geometry": {"coordinates":[-1.1361310482,37.9837379456],"type":"Point"}
}