{
  "type": "Feature",
  "properties": {
    "addr:full":"Calle de Vega, 30 Chiclana De La Frontera C\u00e1diz 11130",
    "addr:housenumber":"30",
    "addr:postcode":"11130",
    "addr:street":"Calle De Vega",
    "iso:country":"ES",
    "sg:address":"Calle de Vega, 30",
    "sg:city":"Chiclana De La Frontera",
    "sg:orig_category":"Ropa Para Se\u00d1oras Y Caballeros (al Por Menor)",
    "sg:phone":"+34 956 40 22 54",
    "sg:postcode":"11130",
    "sg:province":"C\u00e1diz",
    "wof:name":"Morales Vela Rafael",
    "wof:placetype":"venue"
},
  "geometry": {"coordinates":[-6.1491799355,36.42004776],"type":"Point"}
}