{
  "type": "Feature",
  "properties": {
    "addr:full":"Major, 39 S. Jaume Enveja Tarragona 43877",
    "addr:housenumber":"39",
    "addr:postcode":"43877",
    "addr:street":"Major;S. Jaume Enveja",
    "iso:country":"ES",
    "sg:address":"Major, 39",
    "sg:city":"S. Jaume Enveja",
    "sg:orig_category":"Librer\u00cdas",
    "sg:phone":"+34 977 47 81 65",
    "sg:postcode":"43877",
    "sg:province":"Tarragona",
    "wof:name":"Gonell Arques Ana Cristina",
    "wof:placetype":"venue"
},
  "geometry": {"coordinates":[0.7350059748,40.7188796997],"type":"Point"}
}