{
  "type": "Feature",
  "properties": {
    "iso:country":"ES",
    "sg:address":"Calle de Silvestre Perez, 6",
    "sg:city":"Zaragoza",
    "sg:orig_category":"Torrefactado De Caf\u00c9",
    "sg:phone":"+34 976 42 62 60",
    "sg:postcode":"50002",
    "sg:province":"Zaragoza",
    "wof:name":"Union Tostadora S.a.",
    "wof:placetype":"venue"
},
  "geometry": {"coordinates":[-0.8620139956,41.6481132507],"type":"Point"}
}