{
  "type": "Feature",
  "properties": {
    "addr:full":"Rbla Nostra Senyora, 39 Vilafranca Penedes Barcelona 08720",
    "addr:housenumber":"39",
    "addr:postcode":"08720",
    "addr:street":"Rbla Nostra Senyora",
    "iso:country":"ES",
    "sg:address":"Rbla Nostra Senyora, 39",
    "sg:city":"Vilafranca Penedes",
    "sg:orig_category":"Partidos Pol\u00cdticos",
    "sg:phone":"+34 938 90 31 82",
    "sg:postcode":"08720",
    "sg:province":"Barcelona",
    "wof:name":"Convergencia Democratica De Catalunya",
    "wof:placetype":"venue"
},
  "geometry": {"coordinates":[1.7004189491,41.3451805115],"type":"Point"}
}