{
  "type": "Feature",
  "properties": {
    "addr:full":"Carrer de Roses (sants), 58 Barcelona Barcelona 08028",
    "addr:housenumber":"58",
    "addr:postcode":"08028",
    "addr:street":"Carrer De Roses Sants",
    "iso:country":"ES",
    "sg:address":"Carrer de Roses (sants), 58",
    "sg:city":"Barcelona",
    "sg:orig_category":"Lencer\u00cda Femenina, Corseter\u00cda, Trajes De Ba\u00d1o (al Por Menor)",
    "sg:phone":"+34 934 91 04 28",
    "sg:postcode":"08028",
    "sg:province":"Barcelona",
    "wof:name":"Weni S.c.p.",
    "wof:placetype":"venue"
},
  "geometry": {"coordinates":[2.1278398037,41.3790893555],"type":"Point"}
}