{
  "type": "Feature",
  "properties": {
    "addr:full":"Carr Oreneta, 4 Colomina Girona 17213",
    "addr:housenumber":"4",
    "addr:postcode":"17213",
    "addr:street":"Carr Oreneta",
    "iso:country":"ES",
    "sg:address":"Carr Oreneta, 4",
    "sg:city":"Colomina",
    "sg:orig_category":"Ingeniero",
    "sg:phone":"+34 972 30 04 88",
    "sg:postcode":"17213",
    "sg:province":"Girona",
    "wof:name":"Oliveras Madi Jaime",
    "wof:placetype":"venue"
},
  "geometry": {"coordinates":[3.2090060711,41.93775177],"type":"Point"}
}