{
  "type": "Feature",
  "properties": {
    "iso:country":"ES",
    "sg:address":"Ctra. Son Vitamina, S/n",
    "sg:city":"Alaior",
    "sg:orig_category":"Promotores Constructores",
    "sg:phone":"+34 971 37 75 20",
    "sg:postcode":"07730",
    "sg:province":"Islas Baleares",
    "wof:name":"Proexme S.l.",
    "wof:placetype":"venue"
},
  "geometry": {"coordinates":[4.1611318588,39.871257782],"type":"Point"}
}