{
  "type": "Feature",
  "properties": {
    "addr:full":"Poli Casa Grande, 5 Torrevieja Alicante 03180",
    "addr:postcode":"03180",
    "iso:country":"ES",
    "sg:address":"Poli Casa Grande, 5",
    "sg:city":"Torrevieja",
    "sg:orig_category":"Veh\u00cdculos De Ocasi\u00d3n",
    "sg:phone":"+34 965 71 64 45",
    "sg:postcode":"03180",
    "sg:province":"Alicante",
    "wof:name":"Talleres Garpi S.l.",
    "wof:placetype":"venue"
},
  "geometry": {"coordinates":[-0.6536790133,38.0173606873],"type":"Point"}
}