{
  "type": "Feature",
  "properties": {
    "addr:full":"Calle de Fuencarral, 7 Madrid Madrid 28004",
    "addr:housenumber":"7",
    "addr:postcode":"madrid;28004",
    "addr:street":"Calle De Fuencarral",
    "iso:country":"ES",
    "sg:address":"Calle de Fuencarral, 7",
    "sg:city":"Madrid",
    "sg:orig_category":"M\u00c9dicos: Oftalmolog\u00cda",
    "sg:phone":"+34 915 23 75 75",
    "sg:postcode":"28004",
    "sg:province":"Madrid",
    "wof:name":"Iogs Instituto Oftalmologico S.a.",
    "wof:placetype":"venue"
},
  "geometry": {"coordinates":[-3.7016270161,40.4205207825],"type":"Point"}
}