{
  "type": "Feature",
  "properties": {
    "iso:country":"ES",
    "sg:address":"Calle de Hernan Cortes, 21",
    "sg:city":"Almansa",
    "sg:orig_category":"Tapicer\u00cdas",
    "sg:phone":"+34 967 34 56 23",
    "sg:postcode":"02640",
    "sg:province":"Albacete",
    "wof:name":"Garcia Cobo Francisco",
    "wof:placetype":"venue"
},
  "geometry": {"coordinates":[-1.0917439461,38.8625907898],"type":"Point"}
}