{
  "type": "Feature",
  "properties": {
    "addr:full":"Calle de Conde De Barcelona, 114 San Juan De Aznalfarache Sevilla 41920",
    "addr:housenumber":"114",
    "addr:postcode":"41920",
    "addr:street":"Calle De Conde De Barcelona",
    "iso:country":"ES",
    "sg:address":"Calle de Conde De Barcelona, 114",
    "sg:city":"San Juan De Aznalfarache",
    "sg:orig_category":"Panader\u00cdas, Panader\u00cdas",
    "sg:phone":"+34 954 17 33 55",
    "sg:postcode":"41920",
    "sg:province":"Sevilla",
    "wof:name":"Villa Mateo Jesus",
    "wof:placetype":"venue"
},
  "geometry": {"coordinates":[-6.0362420082,37.3597564697],"type":"Point"}
}