{
  "type": "Feature",
  "properties": {
    "addr:full":"Carrer de Roger, 29 Barcelona Barcelona 08028",
    "addr:housenumber":"29",
    "addr:postcode":"08028",
    "addr:street":"Carrer De Roger",
    "iso:country":"ES",
    "sg:address":"Carrer de Roger, 29",
    "sg:city":"Barcelona",
    "sg:orig_category":"Mec\u00c1nico Del Autom\u00d3vil",
    "sg:phone":"+34 933 39 44 35",
    "sg:postcode":"08028",
    "sg:province":"Barcelona",
    "wof:name":"Talleres Clemente Villamayor S.l",
    "wof:placetype":"venue"
},
  "geometry": {"coordinates":[2.1273870468,41.3771476746],"type":"Point"}
}