{
  "type": "Feature",
  "properties": {
    "addr:full":"Avda Estacion De La, 8 Arroyo De La Miel-benalmadena Costa M\u00e1laga 29631",
    "addr:housenumber":"8",
    "addr:postcode":"29631",
    "addr:street":"Avda Estacion De La;Arroyo De La Miel-Benalmadena Costa Ma\u0301Laga",
    "iso:country":"ES",
    "sg:address":"Avda Estacion De La, 8",
    "sg:city":"Arroyo De La Miel-benalmadena Costa",
    "sg:orig_category":"Inversiones",
    "sg:phone":"+34 952 44 19 25",
    "sg:postcode":"29631",
    "sg:province":"M\u00e1laga",
    "wof:name":"International Investments Costa Del Sol",
    "wof:placetype":"venue"
},
  "geometry": {"coordinates":[-4.5482521057,36.6017608643],"type":"Point"}
}