{
  "type": "Feature",
  "properties": {
    "iso:country":"ES",
    "sg:address":"Carrer de Pujol, 43",
    "sg:city":"Mataro",
    "sg:orig_category":"Camiser\u00cda Y Ropa Interior Masculina (al Por Menor)",
    "sg:phone":"+34 937 55 35 72",
    "sg:postcode":"08301",
    "sg:province":"Barcelona",
    "wof:name":"Addo Camiseria S.l.",
    "wof:placetype":"venue"
},
  "geometry": {"coordinates":[2.4465110302,41.5394287109],"type":"Point"}
}