{
  "type": "Feature",
  "properties": {
    "iso:country":"ES",
    "sg:address":"Carrer de Mateu Enric Llado, 34",
    "sg:city":"Palma",
    "sg:orig_category":"Pe\u00d1as Y Asociaciones Varias",
    "sg:phone":"+34 971 71 94 23",
    "sg:postcode":"07002",
    "sg:province":"Islas Baleares",
    "wof:name":"Asociacion Balear De Adopcion Internacional Creixer Junts",
    "wof:placetype":"venue"
},
  "geometry": {"coordinates":[2.6562526226,39.5686721802],"type":"Point"}
}