{
  "type": "Feature",
  "properties": {
    "addr:full":"Calle de San Andres, 1 Zaragoza Zaragoza 50001",
    "addr:housenumber":"1",
    "addr:postcode":"50001",
    "addr:street":"Calle De San Andres",
    "iso:country":"ES",
    "sg:address":"Calle de San Andres, 1",
    "sg:city":"Zaragoza",
    "sg:orig_category":"Audiovisuales (producci\u00d3n, Edici\u00d3n, Realizaci\u00d3n)",
    "sg:phone":"+34 976 39 16 78",
    "sg:postcode":"50001",
    "sg:province":"Zaragoza",
    "wof:name":"Toi Movie Sl",
    "wof:placetype":"venue"
},
  "geometry": {"coordinates":[-0.8789454103,41.652256012],"type":"Point"}
}