{
  "type": "Feature",
  "properties": {
    "addr:full":"Calle de Honorio Garcia Condoy, 3 Zaragoza Zaragoza 50007",
    "addr:housenumber":"3",
    "addr:postcode":"50007",
    "addr:street":"Calle De Honorio Garcia Condoy",
    "iso:country":"ES",
    "sg:address":"Calle de Honorio Garcia Condoy, 3",
    "sg:city":"Zaragoza",
    "sg:orig_category":"Institutos De Belleza",
    "sg:phone":"+34 976 25 31 01",
    "sg:postcode":"50007",
    "sg:province":"Zaragoza",
    "wof:name":"Salones Espiral S.l.l.",
    "wof:placetype":"venue"
},
  "geometry": {"coordinates":[-0.882479012,41.6320915222],"type":"Point"}
}