{
  "type": "Feature",
  "properties": {
    "iso:country":"ES",
    "sg:address":"Calle de O'donnell, 46",
    "sg:city":"Madrid",
    "sg:orig_category":"M\u00c9dicos: Cirug\u00cda Urol\u00d3gica",
    "sg:phone":"+34 915 04 57 53",
    "sg:postcode":"28009",
    "sg:province":"Madrid",
    "wof:name":"Mayayo Dehesa Teodoro",
    "wof:placetype":"venue"
},
  "geometry": {"coordinates":[-3.6768717766,40.4215507507],"type":"Point"}
}