{
  "type": "Feature",
  "properties": {
    "iso:country":"ES",
    "sg:address":"Calle de Colon, 31",
    "sg:city":"Bejar",
    "sg:classifiers":[
        {
            "category":"Autos & Motor Vehicles",
            "subcategory":"Automobile Sales",
            "type":"Retail Goods"
        }
    ],
    "sg:phone":"+34 923 40 06 32",
    "sg:postcode":"37700",
    "sg:province":"Salamanca",
    "wof:name":"Mazo Granados Pedro Luis",
    "wof:placetype":"venue"
},
  "geometry": {"coordinates":[-5.7656769753,40.3854217529],"type":"Point"}
}