{
  "type": "Feature",
  "properties": {
    "addr:full":"Carrer de Salvador Espriu, 10 Canet Mar Barcelona 08360",
    "addr:housenumber":"10",
    "addr:postcode":"08360",
    "addr:street":"Carrer De Salvador Espriu",
    "iso:country":"ES",
    "sg:address":"Carrer de Salvador Espriu, 10",
    "sg:city":"Canet Mar",
    "sg:orig_category":"Empresas De Escayolas",
    "sg:phone":"+34 937 94 29 64",
    "sg:postcode":"08360",
    "sg:province":"Barcelona",
    "wof:name":"Vidal Masso Jordi",
    "wof:placetype":"venue"
},
  "geometry": {"coordinates":[2.578414917,41.5975265503],"type":"Point"}
}