{
  "type": "Feature",
  "properties": {
    "addr:full":"Ctra Camu\u00d1as, 1 Villafranca De Los Caballeros Toledo 45730",
    "addr:housenumber":"1",
    "addr:postcode":"45730",
    "addr:street":"Ctra Camun\u0303As",
    "iso:country":"ES",
    "sg:address":"Ctra Camu\u00d1as, 1",
    "sg:city":"Villafranca De Los Caballeros",
    "sg:orig_category":"Negocio De Materiales De Construcci\u00d3n",
    "sg:phone":"+34 926 57 81 08",
    "sg:postcode":"45730",
    "sg:province":"Toledo",
    "wof:name":"Hijos De Natalio Loarces S.l.",
    "wof:placetype":"venue"
},
  "geometry": {"coordinates":[-3.3676819801,39.4262733459],"type":"Point"}
}