{
  "type": "Feature",
  "properties": {
    "iso:country":"ES",
    "sg:address":"Ctr Arenas S Pedro, 16",
    "sg:city":"Velada",
    "sg:orig_category":"Extinci\u00d3n De Incendios: Material Y Suministros (fabricaci\u00d3n, Al Por Mayor)",
    "sg:phone":"+34 925 70 81 40",
    "sg:postcode":"45612",
    "sg:province":"Toledo",
    "wof:name":"Eborex Sll",
    "wof:placetype":"venue"
},
  "geometry": {"coordinates":[-4.9730501175,39.9781951904],"type":"Point"}
}