{
  "type": "Feature",
  "properties": {
    "iso:country":"ES",
    "sg:address":"Rond Pilar, 2",
    "sg:city":"Badajoz",
    "sg:orig_category":"M\u00c9dicos: Estomatolog\u00cda",
    "sg:phone":"+34 924 24 69 35",
    "sg:postcode":"06002",
    "sg:province":"Badajoz",
    "wof:name":"Llinas Parra Jose Maria",
    "wof:placetype":"venue"
},
  "geometry": {"coordinates":[-6.9718379974,38.8750267029],"type":"Point"}
}