{
  "type": "Feature",
  "properties": {
    "addr:full":"Ctra Torrenueva, S/n Valdepe\u00f1as Ciudad Real 13300",
    "addr:housenumber":"s / n",
    "addr:postcode":"13300",
    "addr:street":"Ctra Torrenueva",
    "iso:country":"ES",
    "sg:address":"Ctra Torrenueva, S/n",
    "sg:city":"Valdepe\u00f1as",
    "sg:orig_category":"Estaciones Y Oficinas De Meteorolog\u00cda",
    "sg:phone":"+34 926 32 30 70",
    "sg:postcode":"13300",
    "sg:province":"Ciudad Real",
    "wof:name":"Direccion General Del Instituto Nacional De Meteorologia",
    "wof:placetype":"venue"
},
  "geometry": {"coordinates":[-3.3911190033,38.7507019043],"type":"Point"}
}