{
  "type": "Feature",
  "properties": {
    "addr:full":"Avda Suecia (de), 23 Cristianos Santa Cruz De Tenerife 38650",
    "addr:housenumber":"23",
    "addr:postcode":"38650",
    "addr:street":"Avda Suecia De",
    "iso:country":"ES",
    "sg:address":"Avda Suecia (de), 23",
    "sg:city":"Cristianos",
    "sg:orig_category":"Peluquer\u00cdas, Peluquer\u00cda Mixta",
    "sg:phone":"+34 922 75 14 12",
    "sg:postcode":"38650",
    "sg:province":"Santa Cruz De Tenerife",
    "wof:name":"Salon Cocos S.l.",
    "wof:placetype":"venue"
},
  "geometry": {"coordinates":[-16.7190227509,28.0517444611],"type":"Point"}
}