{
  "type": "Feature",
  "properties": {
    "iso:country":"ES",
    "sg:address":"Calle de Lepe, 32",
    "sg:city":"Villanueva De Los Castillejos",
    "sg:orig_category":"Supermercados Y Hipermercados",
    "sg:phone":"+34 959 38 72 17",
    "sg:postcode":"21540",
    "sg:province":"Huelva",
    "wof:name":"Macias Martin Maria Luz",
    "wof:placetype":"venue"
},
  "geometry": {"coordinates":[-7.2721419334,37.4990158081],"type":"Point"}
}