{
  "type": "Feature",
  "properties": {
    "iso:country":"ES",
    "sg:address":"Calle de Juntas Generales, 61",
    "sg:city":"Vitoria-gasteiz",
    "sg:orig_category":"Asociaciones Humanitarias, De Cooperaci\u00d3n, De Acci\u00d3n Social",
    "sg:phone":"+34 945 25 21 93",
    "sg:postcode":"01010",
    "sg:province":"\u00c1lava",
    "wof:name":"Comision Ciudadana Anti-sida De Alava",
    "wof:placetype":"venue"
},
  "geometry": {"coordinates":[-2.6776919365,42.8660049438],"type":"Point"}
}