{
  "type": "Feature",
  "properties": {
    "addr:full":"Carr Mestre Miquel Galan, 17 Puig Valencia 46540",
    "addr:housenumber":"17",
    "addr:postcode":"46540",
    "addr:street":"Carr Mestre Miquel Galan",
    "iso:country":"ES",
    "sg:address":"Carr Mestre Miquel Galan, 17",
    "sg:city":"Puig",
    "sg:orig_category":"Imprenta",
    "sg:phone":"+34 961 47 01 86",
    "sg:postcode":"46540",
    "sg:province":"Valencia",
    "wof:name":"Sancho Almi\u00f1ana Vicente Blas",
    "wof:placetype":"venue"
},
  "geometry": {"coordinates":[-0.306742996,39.5879859924],"type":"Point"}
}