{
  "type": "Feature",
  "properties": {
    "iso:country":"ES",
    "sg:address":"Calle de Real De Arriba, 69",
    "sg:city":"Valverde Camino",
    "sg:orig_category":"Librer\u00cdas",
    "sg:phone":"+34 959 55 04 54",
    "sg:postcode":"21600",
    "sg:province":"Huelva",
    "wof:name":"Fernandez Batanero Diego",
    "wof:placetype":"venue"
},
  "geometry": {"coordinates":[-6.7535200119,37.5749740601],"type":"Point"}
}