{
  "type": "Feature",
  "properties": {
    "addr:full":"Pase Direccion, 95 Madrid Madrid 28039",
    "addr:housenumber":"95",
    "addr:postcode":"madrid;28039",
    "iso:country":"ES",
    "sg:address":"Pase Direccion, 95",
    "sg:city":"Madrid",
    "sg:orig_category":"Farmacias",
    "sg:phone":"+34 913 11 53 15",
    "sg:postcode":"28039",
    "sg:province":"Madrid",
    "wof:name":"Fernandez Guerras Inmaculada",
    "wof:placetype":"venue"
},
  "geometry": {"coordinates":[-3.7061729431,40.4603729248],"type":"Point"}
}