{
  "type": "Feature",
  "properties": {
    "iso:country":"ES",
    "sg:address":"Av Santiga, 27",
    "sg:city":"Santa Perpetua De Mogoda",
    "sg:orig_category":"Molduras, Junquillos, Listones Y Molduras Perforadas",
    "sg:phone":"+34 935 60 58 04",
    "sg:postcode":"08130",
    "sg:province":"Barcelona",
    "wof:name":"Garrido Casado Juan Francisco",
    "wof:placetype":"venue"
},
  "geometry": {"coordinates":[2.179142952,41.5366134644],"type":"Point"}
}