{
  "type": "Feature",
  "properties": {
    "iso:country":"ES",
    "sg:address":"Avda Levante (de), 124",
    "sg:city":"Rivas Vaciamadrid",
    "sg:orig_category":"Farmacias",
    "sg:phone":"+34 916 70 10 69",
    "sg:postcode":"28529",
    "sg:province":"Madrid",
    "wof:name":"Bonilla Delgado Encarnacion",
    "wof:placetype":"venue"
},
  "geometry": {"coordinates":[-3.5125761032,40.3285217285],"type":"Point"}
}