{
  "type": "Feature",
  "properties": {
    "iso:country":"ES",
    "sg:address":"Ctra Fuente Del Maestre, S/n",
    "sg:city":"Almendralejo",
    "sg:orig_category":"Organizaciones Internacionales",
    "sg:phone":"+34 924 66 54 31",
    "sg:postcode":"06200",
    "sg:province":"Badajoz",
    "sg:website":"www.cruzroja.es",
    "wof:name":"Cruz Roja Espa\u00f1ola-asamblea Local",
    "wof:placetype":"venue"
},
  "geometry": {"coordinates":[-6.4111638069,38.673160553],"type":"Point"}
}