{
  "type": "Feature",
  "properties": {
    "addr:full":"Ctra Castellon-san Mateo, Km. 0008,2 Borriol Castell\u00f3n 12190",
    "addr:postcode":"12190",
    "addr:street":"Ctra Castellon-San Mateo Km. 0008,2;Castello\u0301N",
    "iso:country":"ES",
    "sg:address":"Ctra Castellon-san Mateo, Km. 0008,2",
    "sg:city":"Borriol",
    "sg:orig_category":"Cer\u00c1mica Art\u00cdstica Y Decorativa",
    "sg:phone":"+34 964 32 15 49",
    "sg:postcode":"12190",
    "sg:province":"Castell\u00f3n",
    "wof:name":"La Vila S.l.",
    "wof:placetype":"venue"
},
  "geometry": {"coordinates":[-0.070262,40.0408325195],"type":"Point"}
}