{
  "type": "Feature",
  "properties": {
    "addr:full":"Doctor Gallego, S/n Cabezas S. Juan Sevilla 41730",
    "addr:housenumber":"s / n",
    "addr:postcode":"41730",
    "addr:street":"Doctor Gallego;Cabezas S. Juan Sevilla",
    "iso:country":"ES",
    "sg:address":"Doctor Gallego, S/n",
    "sg:city":"Cabezas S. Juan",
    "sg:orig_category":"Ense\u00d1anza, Formaci\u00d3n Profesional: Aprendizaje",
    "sg:phone":"+34 955 87 14 54",
    "sg:postcode":"41730",
    "sg:province":"Sevilla",
    "wof:name":"Servicio Andaluz De Empleo",
    "wof:placetype":"venue"
},
  "geometry": {"coordinates":[-5.9365491867,36.9817962646],"type":"Point"}
}