{
  "type": "Feature",
  "properties": {
    "iso:country":"ES",
    "sg:address":"Carrer de Barcelona, 47",
    "sg:city":"Roda Ter",
    "sg:orig_category":"Alquiler De Camiones Y Veh\u00cdculos Industriales",
    "sg:phone":"+34 938 54 04 54",
    "sg:postcode":"08510",
    "sg:province":"Barcelona",
    "sg:website":"www.alrent.net",
    "wof:name":"Auto Lloguers Roda S.l.",
    "wof:placetype":"venue"
},
  "geometry": {"coordinates":[2.3061950207,41.9785995483],"type":"Point"}
}