{
  "type": "Feature",
  "properties": {
    "iso:country":"ES",
    "sg:address":"Calle de Okendo, 11",
    "sg:city":"Donostia-san Sebastian",
    "sg:orig_category":"Asesor\u00cda Sobre Comunicaci\u00d3n De Empresas",
    "sg:phone":"+34 943 42 61 40",
    "sg:postcode":"20004",
    "sg:province":"Guip\u00f9zcoa",
    "wof:name":"Asesoria Loyola C.b.",
    "wof:placetype":"venue"
},
  "geometry": {"coordinates":[-1.9802513123,43.3204078674],"type":"Point"}
}