{
  "type": "Feature",
  "properties": {
    "iso:country":"ES",
    "sg:address":"Avda Zaragoza, 12",
    "sg:city":"Tudela",
    "sg:orig_category":"Complementos De Vestir (al Por Menor)",
    "sg:phone":"+34 948 82 02 79",
    "sg:postcode":"31500",
    "sg:province":"Navarra",
    "wof:name":"Mia",
    "wof:placetype":"venue"
},
  "geometry": {"coordinates":[-1.602609992,42.0613861084],"type":"Point"}
}