{
  "type": "Feature",
  "properties": {
    "addr:full":"Calle de San Vicente, 5 Soria Soria 42004",
    "addr:housenumber":"5",
    "addr:postcode":"42004",
    "addr:street":"Calle De San Vicente",
    "iso:country":"ES",
    "sg:address":"Calle de San Vicente, 5",
    "sg:city":"Soria",
    "sg:orig_category":"Apicultura",
    "sg:phone":"+34 975 21 10 53",
    "sg:postcode":"42004",
    "sg:province":"Soria",
    "wof:name":"Cacho Solaesa Simon",
    "wof:placetype":"venue"
},
  "geometry": {"coordinates":[-2.458106041,41.7669067383],"type":"Point"}
}