{
  "type": "Feature",
  "properties": {
    "iso:country":"ES",
    "sg:address":"Rua Garcia Lorca (de), 27",
    "sg:city":"Santiago De Compostela",
    "sg:orig_category":"Molduras, Junquillos, Listones Y Molduras Perforadas",
    "sg:phone":"+34 981 58 91 49",
    "sg:postcode":"15704",
    "sg:province":"A Coru\u00f1a",
    "wof:name":"Suarez Fraga Jesus",
    "wof:placetype":"venue"
},
  "geometry": {"coordinates":[-8.5358810425,42.8916397095],"type":"Point"}
}