{
  "type": "Feature",
  "properties": {
    "iso:country":"ES",
    "sg:address":"Avda Antonio Machado, 90",
    "sg:city":"Arroyo De La Miel-benalmadena Costa",
    "sg:orig_category":"Molduras, Junquillos, Listones Y Molduras Perforadas",
    "sg:phone":"+34 952 44 05 07",
    "sg:postcode":"29630",
    "sg:province":"M\u00e1laga",
    "wof:name":"Harrison  Keith",
    "wof:placetype":"venue"
},
  "geometry": {"coordinates":[-4.5322303772,36.5866928101],"type":"Point"}
}