{
  "type": "Feature",
  "properties": {
    "addr:full":"Ptge Stravinsky, 6 Rubi Barcelona 08191",
    "addr:housenumber":"6",
    "addr:postcode":"08191",
    "addr:street":"Ptge Stravinsky",
    "iso:country":"ES",
    "sg:address":"Ptge Stravinsky, 6",
    "sg:city":"Rubi",
    "sg:orig_category":"Papel, Reciclaje",
    "sg:phone":"+34 936 99 35 98",
    "sg:postcode":"08191",
    "sg:province":"Barcelona",
    "wof:name":"Cadlineal S.l",
    "wof:placetype":"venue"
},
  "geometry": {"coordinates":[2.0202379227,41.4700813293],"type":"Point"}
}