{
  "type": "Feature",
  "properties": {
    "addr:full":"Carrer de Arago, 476 Barcelona Barcelona 08013",
    "addr:housenumber":"476",
    "addr:postcode":"08013",
    "addr:street":"Carrer De Arago",
    "iso:country":"ES",
    "sg:address":"Carrer de Arago, 476",
    "sg:city":"Barcelona",
    "sg:orig_category":"Farmacias",
    "sg:phone":"+34 932 31 60 57",
    "sg:postcode":"08013",
    "sg:province":"Barcelona",
    "wof:name":"Olivella Comas Mercedes",
    "wof:placetype":"venue"
},
  "geometry": {"coordinates":[2.1803030968,41.4035644531],"type":"Point"}
}