{
  "type": "Feature",
  "properties": {
    "iso:country":"ES",
    "sg:address":"Rua Calvo Sotelo, 151",
    "sg:city":"Sarria",
    "sg:orig_category":"Molduras, Junquillos, Listones Y Molduras Perforadas",
    "sg:phone":"+34 982 53 35 73",
    "sg:postcode":"27600",
    "sg:province":"Lugo",
    "wof:name":"Baamonde Viador Jose Benito",
    "wof:placetype":"venue"
},
  "geometry": {"coordinates":[-7.4098157883,42.7780838013],"type":"Point"}
}