{
  "type": "Feature",
  "properties": {
    "addr:full":"Trva Uribarri C, 16 Bilbao Vizcaya 48007",
    "addr:housenumber":"16",
    "addr:postcode":"48007",
    "addr:street":"Trva Uribarri C",
    "iso:country":"ES",
    "sg:address":"Trva Uribarri C, 16",
    "sg:city":"Bilbao",
    "sg:orig_category":"Mercer\u00cda, Lencer\u00cda (al Por Menor)",
    "sg:phone":"+34 944 13 06 83",
    "sg:postcode":"48007",
    "sg:province":"Vizcaya",
    "wof:name":"Isabel Yeste Curiel",
    "wof:placetype":"venue"
},
  "geometry": {"coordinates":[-2.9195330143,43.2674789429],"type":"Point"}
}