{
  "type": "Feature",
  "properties": {
    "iso:country":"ES",
    "sg:address":"Calle de Marino Sirera, 16",
    "sg:city":"Valencia",
    "sg:orig_category":"Parques De Atracciones Y Centros De Esparcimiento",
    "sg:phone":"+34 963 71 34 18",
    "sg:postcode":"46011",
    "sg:province":"Valencia",
    "wof:name":"Caba\u00f1al 16 S.l.",
    "wof:placetype":"venue"
},
  "geometry": {"coordinates":[-0.3323880136,39.4683647156],"type":"Point"}
}