{
  "type": "Feature",
  "properties": {
    "iso:country":"ES",
    "sg:address":"Calle de Duquesa Villahermosa, 32",
    "sg:city":"Zaragoza",
    "sg:orig_category":"Lencer\u00cda Femenina, Corseter\u00cda, Trajes De Ba\u00d1o (al Por Menor)",
    "sg:phone":"+34 976 53 14 35",
    "sg:postcode":"50010",
    "sg:province":"Zaragoza",
    "wof:name":"Gallego Se\u00f1alada Carmen",
    "wof:placetype":"venue"
},
  "geometry": {"coordinates":[-0.9020097256,41.6483955383],"type":"Point"}
}