{
  "type": "Feature",
  "properties": {
    "addr:full":"Calle de Pedro Alfaro, 12 Burgos Burgos 09007",
    "addr:housenumber":"12",
    "addr:postcode":"09007",
    "addr:street":"Calle De Pedro Alfaro",
    "iso:country":"ES",
    "sg:address":"Calle de Pedro Alfaro, 12",
    "sg:city":"Burgos",
    "sg:orig_category":"Asociaciones Y Clubs Deportivos",
    "sg:phone":"+34 947 47 08 09",
    "sg:postcode":"09007",
    "sg:province":"Burgos",
    "wof:name":"Calleja Bayona Julio",
    "wof:placetype":"venue"
},
  "geometry": {"coordinates":[-3.6638629436,42.3505859375],"type":"Point"}
}