{
  "type": "Feature",
  "properties": {
    "iso:country":"ES",
    "sg:address":"Carr Santa Teresa, 2",
    "sg:city":"Pu\u00e7ol",
    "sg:orig_category":"Cajas De Ahorro",
    "sg:phone":"+34 961 42 06 08",
    "sg:postcode":"46530",
    "sg:province":"Valencia",
    "wof:name":"Caja De Ahorros De Valencia Castellon Y Alicante",
    "wof:placetype":"venue"
},
  "geometry": {"coordinates":[-0.307938993,39.6172103882],"type":"Point"}
}