{
  "type": "Feature",
  "properties": {
    "addr:full":"Calle de Manuel Gra\u00d1a, 11 Cangas Pontevedra 36940",
    "addr:housenumber":"11",
    "addr:postcode":"36940",
    "addr:street":"Calle De Manuel Gran\u0303A",
    "iso:country":"ES",
    "sg:address":"Calle de Manuel Gra\u00d1a, 11",
    "sg:city":"Cangas",
    "sg:orig_category":"Art\u00cdculos Reciclados",
    "sg:phone":"+34 900 10 11 57",
    "sg:postcode":"36940",
    "sg:province":"Pontevedra",
    "wof:name":"Ecoloxica Galega De Consumibles Reciclados S.l.",
    "wof:placetype":"venue"
},
  "geometry": {"coordinates":[-8.7862272263,42.2627334595],"type":"Point"}
}