{
  "type": "Feature",
  "properties": {
    "iso:country":"ES",
    "sg:address":"Rua Manuel Rodriguez, 9",
    "sg:city":"Porri\u00f1o",
    "sg:orig_category":"Trabajos De Soldaduras",
    "sg:phone":"+34 986 33 12 20",
    "sg:postcode":"36400",
    "sg:province":"Pontevedra",
    "wof:name":"Re Asesoria Inmobiliaria E Proxectos De Enerxias Limpas S.l",
    "wof:placetype":"venue"
},
  "geometry": {"coordinates":[-8.6211147308,42.1597938538],"type":"Point"}
}