{
  "type": "Feature",
  "properties": {
    "addr:full":"Calle de Jaime El Conquistador, 33 Madrid Madrid 28045",
    "addr:housenumber":"33",
    "addr:postcode":"madrid;28045",
    "addr:street":"Calle De Jaime El Conquistador",
    "iso:country":"ES",
    "sg:address":"Calle de Jaime El Conquistador, 33",
    "sg:city":"Madrid",
    "sg:orig_category":"Electricidad, Electr\u00d3nica: Material Y Suministros (al Por Mayor)",
    "sg:phone":"+34 914 73 72 66",
    "sg:postcode":"28045",
    "sg:province":"Madrid",
    "wof:name":"Dimel-madrid S.a.",
    "wof:placetype":"venue"
},
  "geometry": {"coordinates":[-3.6982309818,40.3945770264],"type":"Point"}
}