{
  "type": "Feature",
  "properties": {
    "iso:country":"ES",
    "sg:address":"Rond Guinardo, 76",
    "sg:city":"Barcelona",
    "sg:orig_category":"Confecci\u00d3n De Botones",
    "sg:phone":"+34 934 35 61 00",
    "sg:postcode":"08025",
    "sg:province":"Barcelona",
    "wof:name":"Botones Disgosa S.l.",
    "wof:placetype":"venue"
},
  "geometry": {"coordinates":[2.1700708866,41.4132652283],"type":"Point"}
}