{
  "type": "Feature",
  "properties": {
    "iso:country":"ES",
    "sg:address":"Calle de Cervantes, 7",
    "sg:city":"Catarroja",
    "sg:orig_category":"Quincaller\u00cda (al Por Menor)",
    "sg:phone":"+34 961 27 45 23",
    "sg:postcode":"46470",
    "sg:province":"Valencia",
    "wof:name":"Villanueva Peris Juan",
    "wof:placetype":"venue"
},
  "geometry": {"coordinates":[-0.4033510089,39.4008026123],"type":"Point"}
}