{
  "type": "Feature",
  "properties": {
    "iso:country":"ES",
    "sg:address":"Calle de Rodriguez Paterna, 14",
    "sg:city":"Logro\u00f1o",
    "sg:orig_category":"Empresas De Carpinter\u00cda",
    "sg:phone":"+34 941 24 93 19",
    "sg:postcode":"26001",
    "sg:province":"La Rioja",
    "wof:name":"Martinez Moradillo Pedro",
    "wof:placetype":"venue"
},
  "geometry": {"coordinates":[-2.4429609776,42.4674186707],"type":"Point"}
}