{
  "type": "Feature",
  "properties": {
    "addr:full":"Carrer de Monterols, 16 Reus Tarragona 43201",
    "addr:housenumber":"16",
    "addr:postcode":"43201",
    "addr:street":"Carrer De Monterols",
    "iso:country":"ES",
    "sg:address":"Carrer de Monterols, 16",
    "sg:city":"Reus",
    "sg:orig_category":"M\u00c9dicos: Cirug\u00cda General",
    "sg:phone":"+34 977 34 16 00",
    "sg:postcode":"43201",
    "sg:province":"Tarragona",
    "wof:name":"Perez Burillo Maria Del Pilar",
    "wof:placetype":"venue"
},
  "geometry": {"coordinates":[1.1077849865,41.1554069519],"type":"Point"}
}