{
  "type": "Feature",
  "properties": {
    "addr:full":"Carrer de Can Veri, 1 Palma Islas Baleares 07001",
    "addr:housenumber":"1",
    "addr:postcode":"07001",
    "addr:street":"Carrer De Can Veri",
    "iso:country":"ES",
    "sg:address":"Carrer de Can Veri, 1",
    "sg:city":"Palma",
    "sg:orig_category":"Muebles, Minoristas",
    "sg:phone":"+34 971 72 76 74",
    "sg:postcode":"07001",
    "sg:province":"Islas Baleares",
    "wof:name":"Janer Grau Jose Maria",
    "wof:placetype":"venue"
},
  "geometry": {"coordinates":[2.6484630108,39.5703010559],"type":"Point"}
}