{
  "type": "Feature",
  "properties": {
    "iso:country":"ES",
    "sg:address":"Calle de Padre Rafael, 2",
    "sg:city":"Badajoz",
    "sg:orig_category":"Ingenier\u00cda, Centros De Estudios (diversos)",
    "sg:phone":"+34 924 22 92 06",
    "sg:postcode":"06001",
    "sg:province":"Badajoz",
    "wof:name":"Exaco Y Dopex S.a.",
    "wof:placetype":"venue"
},
  "geometry": {"coordinates":[-6.9721941948,38.8773422241],"type":"Point"}
}