{
  "type": "Feature",
  "properties": {
    "addr:full":"Calle de San Miguel, 6 Tarbena Alicante 03518",
    "addr:housenumber":"6",
    "addr:postcode":"03518",
    "addr:street":"Calle De San Miguel;Alicante",
    "iso:country":"ES",
    "sg:address":"Calle de San Miguel, 6",
    "sg:city":"Tarbena",
    "sg:orig_category":"Pe\u00d1as Y Asociaciones Varias",
    "sg:phone":"+34 965 88 40 33",
    "sg:postcode":"03518",
    "sg:province":"Alicante",
    "wof:name":"Cooperativa De Labradores Y Ganaderos",
    "wof:placetype":"venue"
},
  "geometry": {"coordinates":[-0.1019629985,38.6939239502],"type":"Point"}
}