{
  "type": "Feature",
  "properties": {
    "iso:country":"ES",
    "sg:address":"Calle de Picasso, 25",
    "sg:city":"Bola\u00e7os De Calatrava",
    "sg:orig_category":"M\u00c1rmoles, Granitos Y Piedras Naturales",
    "sg:phone":"+34 926 87 25 69",
    "sg:postcode":"13260",
    "sg:province":"Ciudad Real",
    "wof:name":"Gregorio Velazquez S.l.",
    "wof:placetype":"venue"
},
  "geometry": {"coordinates":[-3.6548190117,38.9102287292],"type":"Point"}
}