{
  "type": "Feature",
  "properties": {
    "addr:full":"Carrer de Santuari, 95 Barcelona Barcelona 08032",
    "addr:housenumber":"95",
    "addr:postcode":"08032",
    "addr:street":"Carrer De Santuari",
    "iso:country":"ES",
    "sg:address":"Carrer de Santuari, 95",
    "sg:city":"Barcelona",
    "sg:orig_category":"Maquinaria Y Herramientas Para Madera, Pvc, Aluminio Y Aperos (fabricaci\u00d3n, Comercio)",
    "sg:phone":"+34 934 20 02 43",
    "sg:postcode":"08032",
    "sg:province":"Barcelona",
    "wof:name":"Gil Rosa Dolores",
    "wof:placetype":"venue"
},
  "geometry": {"coordinates":[2.1544389725,41.4206733704],"type":"Point"}
}