{
  "type": "Feature",
  "properties": {
    "addr:full":"Avda Neguri, 9 Algorta Vizcaya 48992",
    "addr:housenumber":"9",
    "addr:postcode":"48992",
    "addr:street":"Avda Neguri",
    "iso:country":"ES",
    "sg:address":"Avda Neguri, 9",
    "sg:city":"Algorta",
    "sg:orig_category":"Inmobiliaria (agencias)",
    "sg:phone":"+34 944 91 46 89",
    "sg:postcode":"48992",
    "sg:province":"Vizcaya",
    "sg:website":"www.infoempresas.com",
    "wof:name":"Inmneg S.l.",
    "wof:placetype":"venue"
},
  "geometry": {"coordinates":[-3.0073699951,43.3402404785],"type":"Point"}
}