{
  "type": "Feature",
  "properties": {
    "iso:country":"ES",
    "sg:address":"Carrer de Santa Anna, 21",
    "sg:city":"Barcelona",
    "sg:orig_category":"Marroquiner\u00cda (confecci\u00d3n)",
    "sg:phone":"+34 933 17 43 92",
    "sg:postcode":"08002",
    "sg:province":"Barcelona",
    "wof:name":"Belmonte Piquer Adoracion",
    "wof:placetype":"venue"
},
  "geometry": {"coordinates":[2.1713790894,41.3853721619],"type":"Point"}
}