{
  "type": "Feature",
  "properties": {
    "addr:full":"Pl Bonanova, 4 Barcelona Barcelona 08022",
    "addr:housenumber":"4",
    "addr:postcode":"08022",
    "addr:street":"Pl Bonanova",
    "iso:country":"ES",
    "sg:address":"Pl Bonanova, 4",
    "sg:city":"Barcelona",
    "sg:orig_category":"Abogados",
    "sg:phone":"+34 932 53 04 48",
    "sg:postcode":"08022",
    "sg:province":"Barcelona",
    "sg:website":"www.rosinyol-alavedra.com",
    "wof:name":"Rossinyol Alavedra Advocats S.l",
    "wof:placetype":"venue"
},
  "geometry": {"coordinates":[2.1340739727,41.4067726135],"type":"Point"}
}