{
  "type": "Feature",
  "properties": {
    "addr:full":"Calle de Jardines, 2 Castro Urdiales Cantabria 39700",
    "addr:housenumber":"2",
    "addr:postcode":"39700",
    "addr:street":"Calle De Jardines",
    "iso:country":"ES",
    "sg:address":"Calle de Jardines, 2",
    "sg:city":"Castro Urdiales",
    "sg:orig_category":"M\u00c9dicos: Oftalmolog\u00cda",
    "sg:phone":"+34 942 87 15 82",
    "sg:postcode":"39700",
    "sg:province":"Cantabria",
    "wof:name":"Hernaez Ortega Maria Conceccion",
    "wof:placetype":"venue"
},
  "geometry": {"coordinates":[-3.2176239491,43.3807678223],"type":"Point"}
}