{
  "type": "Feature",
  "properties": {
    "addr:full":"Calle de Cardenal Segura, 25 Burgos Burgos 09003",
    "addr:housenumber":"25",
    "addr:postcode":"09003",
    "addr:street":"Calle De Cardenal Segura",
    "iso:country":"ES",
    "sg:address":"Calle de Cardenal Segura, 25",
    "sg:city":"Burgos",
    "sg:orig_category":"Ense\u00d1anza: Idiomas",
    "sg:phone":"+34 947 27 75 63",
    "sg:postcode":"09003",
    "sg:province":"Burgos",
    "wof:name":"Centro Ingles Burgos S.l.",
    "wof:placetype":"venue"
},
  "geometry": {"coordinates":[-3.7029929161,42.3417434692],"type":"Point"}
}