{
  "type": "Feature",
  "properties": {
    "iso:country":"ES",
    "sg:address":"Calle de Maestro Vicente Rodriguez, 19",
    "sg:city":"Fuensalida",
    "sg:orig_category":"Ense\u00d1anza: Profesiones Art\u00cdsticas",
    "sg:phone":"+34 925 73 02 93",
    "sg:postcode":"45510",
    "sg:province":"Toledo",
    "wof:name":"Ramos Blanco Roberto",
    "wof:placetype":"venue"
},
  "geometry": {"coordinates":[-4.2103190422,40.0522384644],"type":"Point"}
}