{
  "type": "Feature",
  "properties": {
    "addr:full":"Polig Industrial, 17 Lorqui Murcia 30564",
    "addr:housenumber":"17",
    "addr:postcode":"30564",
    "addr:street":"Polig Industrial",
    "iso:country":"ES",
    "sg:address":"Polig Industrial, 17",
    "sg:city":"Lorqui",
    "sg:orig_category":"Mec\u00c1nico Del Autom\u00d3vil",
    "sg:phone":"+34 968 69 08 48",
    "sg:postcode":"30564",
    "sg:province":"Murcia",
    "wof:name":"Perez Ruiz Joaquin",
    "wof:placetype":"venue"
},
  "geometry": {"coordinates":[-1.2517440319,38.0802001953],"type":"Point"}
}