{
  "type": "Feature",
  "properties": {
    "iso:country":"ES",
    "sg:address":"Ctra Bajada De Las Guayarminas, 9",
    "sg:city":"Galdar",
    "sg:orig_category":"Asesor\u00cda Sobre Comunicaci\u00d3n De Empresas",
    "sg:phone":"+34 928 55 29 85",
    "sg:postcode":"35460",
    "sg:province":"Las Palmas",
    "wof:name":"Diaz Moreno Miguel Angel",
    "wof:placetype":"venue"
},
  "geometry": {"coordinates":[-15.6528720856,28.1450138092],"type":"Point"}
}