{
  "type": "Feature",
  "properties": {
    "iso:country":"ES",
    "sg:address":"Avda Primero De Mayo, 36",
    "sg:city":"Valle Trapaga",
    "sg:orig_category":"Comercio, Reparaci\u00d3n De Bicicletas, De Motocicletas, De Accesorios",
    "sg:phone":"+34 944 92 17 02",
    "sg:postcode":"48510",
    "sg:province":"Vizcaya",
    "wof:name":"Gonzalez Sarasola Jesus",
    "wof:placetype":"venue"
},
  "geometry": {"coordinates":[-3.0331020355,43.3008613586],"type":"Point"}
}