{
  "type": "Feature",
  "properties": {
    "addr:full":"Calle de Ciscar, 1 Castellon Castell\u00f3n 12003",
    "addr:housenumber":"1",
    "addr:postcode":"12003",
    "addr:street":"Calle De Ciscar;Castello\u0301N",
    "iso:country":"ES",
    "sg:address":"Calle de Ciscar, 1",
    "sg:city":"Castellon",
    "sg:orig_category":"Electrodom\u00c9sticos (al Por Menor)",
    "sg:phone":"+34 964 26 05 47",
    "sg:postcode":"12003",
    "sg:province":"Castell\u00f3n",
    "sg:website":"www.redelite.es",
    "wof:name":"Redon Sebastia Joaquin Salvador",
    "wof:placetype":"venue"
},
  "geometry": {"coordinates":[-0.0312456992,39.9849853516],"type":"Point"}
}