{
  "type": "Feature",
  "properties": {
    "iso:country":"ES",
    "sg:address":"Plaz Sol (del), 6",
    "sg:city":"Alcorcon",
    "sg:orig_category":"Restaurantes",
    "sg:phone":"+34 916 41 12 88",
    "sg:postcode":"28922",
    "sg:province":"Madrid",
    "wof:name":"Sanchez Lopez Peninsular S.l.",
    "wof:placetype":"venue"
},
  "geometry": {"coordinates":[-3.8242239952,40.3513946533],"type":"Point"}
}