{
  "type": "Feature",
  "properties": {
    "iso:country":"ES",
    "sg:address":"Calle de Antonio Machado, 8",
    "sg:city":"Arnedo",
    "sg:orig_category":"Inform\u00c1tica (estudios, Servicios, Asesor\u00cda, Formaci\u00d3n)",
    "sg:phone":"+34 941 38 50 20",
    "sg:postcode":"26580",
    "sg:province":"La Rioja",
    "sg:website":"www.infomax-es.com",
    "wof:name":"Informax Bibelot S.l.\u00e7",
    "wof:placetype":"venue"
},
  "geometry": {"coordinates":[-2.0994665623,42.2266387939],"type":"Point"}
}