{
  "type": "Feature",
  "properties": {
    "iso:country":"ES",
    "sg:address":"Avgd Reis Catolics, 24",
    "sg:city":"Benifaio",
    "sg:orig_category":"Empresas De Carpinter\u00cda De Madera",
    "sg:phone":"+34 961 78 13 87",
    "sg:postcode":"46450",
    "sg:province":"Valencia",
    "wof:name":"Modesto Aguado Mas Y Jose Maria Aguado Mas Cdad",
    "wof:placetype":"venue"
},
  "geometry": {"coordinates":[-0.4230839908,39.2885322571],"type":"Point"}
}