{
  "type": "Feature",
  "properties": {
    "addr:full":"Avda Primero De Mayo, 17 Palmas De Gran Canaria Las Palmas 35002",
    "addr:postcode":"35002",
    "addr:street":"Avda Primero De Mayo 17",
    "iso:country":"ES",
    "sg:address":"Avda Primero De Mayo, 17",
    "sg:city":"Palmas De Gran Canaria",
    "sg:orig_category":"M\u00c9dicos: An\u00c1lisis Cl\u00cdnicos",
    "sg:phone":"+34 928 36 46 99",
    "sg:postcode":"35002",
    "sg:province":"Las Palmas",
    "wof:name":"Bosch Millares Carlos",
    "wof:placetype":"venue"
},
  "geometry": {"coordinates":[-15.4188814163,28.1039810181],"type":"Point"}
}