{
  "type": "Feature",
  "properties": {
    "addr:full":"Calle de Infantes, 22 Malaga M\u00e1laga 29002",
    "addr:housenumber":"22",
    "addr:postcode":"29002",
    "addr:street":"Calle De Infantes;Ma\u0301Laga",
    "iso:country":"ES",
    "sg:address":"Calle de Infantes, 22",
    "sg:city":"Malaga",
    "sg:orig_category":"T\u00c9cnicos Veterinarios",
    "sg:phone":"+34 952 36 04 13",
    "sg:postcode":"29002",
    "sg:province":"M\u00e1laga",
    "wof:name":"Ortega Diaz Nieves",
    "wof:placetype":"venue"
},
  "geometry": {"coordinates":[-4.4375429153,36.7019119263],"type":"Point"}
}