{
  "type": "Feature",
  "properties": {
    "addr:full":"Carr Monserrat, 7 Picassent Valencia 46220",
    "addr:housenumber":"7",
    "addr:postcode":"46220",
    "addr:street":"Carr Monserrat",
    "iso:country":"ES",
    "sg:address":"Carr Monserrat, 7",
    "sg:city":"Picassent",
    "sg:orig_category":"Fabricaci\u00d3n De Material Y Sistemas De Se\u00d1alizaci\u00d3n De Carreteras, Urbanos Y De Obras",
    "sg:phone":"+34 961 23 44 72",
    "sg:postcode":"46220",
    "sg:province":"Valencia",
    "wof:name":"Instalaciones Viales S.l.",
    "wof:placetype":"venue"
},
  "geometry": {"coordinates":[-0.4595290124,39.3631401062],"type":"Point"}
}