{
  "type": "Feature",
  "properties": {
    "iso:country":"ES",
    "sg:address":"Calle de Honorio Lozano, 1",
    "sg:city":"Estacion",
    "sg:orig_category":"M\u00c9dicos: Radioterapia (radioterapia Como Opci\u00d3n Oncol\u00d3gica)",
    "sg:phone":"+34 918 51 00 82",
    "sg:postcode":"28400",
    "sg:province":"Madrid",
    "wof:name":"Babe Romero Juan Carlos",
    "wof:placetype":"venue"
},
  "geometry": {"coordinates":[-3.9919650555,40.6455612183],"type":"Point"}
}