{
  "type": "Feature",
  "properties": {
    "iso:country":"ES",
    "sg:address":"Carrer de Artesans, S/n",
    "sg:city":"Valls",
    "sg:orig_category":"Materias Pl\u00c1sticas: Productos De Consumo Masivo (fabricaci\u00d3n, Al Por Mayor)",
    "sg:phone":"+34 977 60 44 00",
    "sg:postcode":"43800",
    "sg:province":"Tarragona",
    "wof:name":"Fabricacio I Recuperacio De Plastics Valls Faset S.l.",
    "wof:placetype":"venue"
},
  "geometry": {"coordinates":[1.2628949881,41.3012657166],"type":"Point"}
}