{
  "type": "Feature",
  "properties": {
    "addr:full":"Calle de Cervantes, 1 Santo\u00f1a Cantabria 39740",
    "addr:housenumber":"1",
    "addr:postcode":"39740",
    "addr:street":"Calle De Cervantes",
    "iso:country":"ES",
    "sg:address":"Calle de Cervantes, 1",
    "sg:city":"Santo\u00f1a",
    "sg:orig_category":"\u00d3ptica: Instrumentos (fabricaci\u00d3n)",
    "sg:phone":"+34 942 67 15 16",
    "sg:postcode":"39740",
    "sg:province":"Cantabria",
    "wof:name":"Marchese Palacio Angel Manuel",
    "wof:placetype":"venue"
},
  "geometry": {"coordinates":[-3.4557359219,43.4426879883],"type":"Point"}
}