{
  "type": "Feature",
  "properties": {
    "iso:country":"ES",
    "sg:address":"Carrer de L'aurora, 9",
    "sg:city":"Barcelona",
    "sg:orig_category":"Zapater\u00cds Y Cordeler\u00cda",
    "sg:phone":"+34 934 41 81 27",
    "sg:postcode":"08001",
    "sg:province":"Barcelona",
    "wof:name":"Simon Mora Maria",
    "wof:placetype":"venue"
},
  "geometry": {"coordinates":[2.1682024002,41.3787574768],"type":"Point"}
}