{
  "type": "Feature",
  "properties": {
    "addr:full":"Calle de Rigoberta Menchu, 4 Ca\u00e7ada De San Urbano Almer\u00eda 04120",
    "addr:housenumber":"4",
    "addr:postcode":"04120",
    "addr:street":"Calle De Rigoberta Menchu;Almeri\u0301A",
    "iso:country":"ES",
    "sg:address":"Calle de Rigoberta Menchu, 4",
    "sg:city":"Ca\u00e7ada De San Urbano",
    "sg:orig_category":"Asesor\u00cda Sobre Comunicaci\u00d3n De Empresas",
    "sg:phone":"+34 950 29 21 31",
    "sg:postcode":"04120",
    "sg:province":"Almer\u00eda",
    "wof:name":"Asesoria A & B Martos C.b.",
    "wof:placetype":"venue"
},
  "geometry": {"coordinates":[-2.4035944939,36.8389434814],"type":"Point"}
}