{
  "type": "Feature",
  "properties": {
    "addr:full":"Avda Valencia, 6 Villanueva Arzobispo Ja\u00e9n 23330",
    "addr:housenumber":"6",
    "addr:postcode":"23330",
    "addr:street":"Avda Valencia",
    "iso:country":"ES",
    "sg:address":"Avda Valencia, 6",
    "sg:city":"Villanueva Arzobispo",
    "sg:orig_category":"Importaci\u00d3n",
    "sg:phone":"+34 953 45 06 63",
    "sg:postcode":"23330",
    "sg:province":"Ja\u00e9n",
    "wof:name":"Sociedad Espa\u00f1ola De Mercado De Origen S.l.",
    "wof:placetype":"venue"
},
  "geometry": {"coordinates":[-3.007365942,38.1686210632],"type":"Point"}
}