{
  "type": "Feature",
  "properties": {
    "addr:full":"Calle de Conde, 3 Jaen Ja\u00e9n 23002",
    "addr:housenumber":"3;jae\u0301n",
    "addr:postcode":"23002",
    "addr:street":"Calle De Conde",
    "iso:country":"ES",
    "sg:address":"Calle de Conde, 3",
    "sg:city":"Jaen",
    "sg:orig_category":"Veh\u00cdculos De Ocasi\u00d3n",
    "sg:phone":"+34 953 24 56 15",
    "sg:postcode":"23002",
    "sg:province":"Ja\u00e9n",
    "wof:name":"Fernandez Molina Silvia",
    "wof:placetype":"venue"
},
  "geometry": {"coordinates":[-3.7927680016,37.7633781433],"type":"Point"}
}