{
  "type": "Feature",
  "properties": {
    "iso:country":"ES",
    "sg:address":"Cronista L Polaino, 10",
    "sg:city":"Cazorla",
    "sg:orig_category":"Sindicatos De Trabajadores",
    "sg:phone":"+34 953 72 20 20",
    "sg:postcode":"23470",
    "sg:province":"Ja\u00e9n",
    "wof:name":"Union General De Trabajadores",
    "wof:placetype":"venue"
},
  "geometry": {"coordinates":[-3.0030300617,37.9129638672],"type":"Point"}
}