{
  "type": "Feature",
  "properties": {
    "iso:country":"ES",
    "sg:address":"Carrer de Wagner, 54",
    "sg:city":"Terrassa",
    "sg:orig_category":"Material Y Suministros Para Fotocopiadoras, Reprograf\u00cda",
    "sg:phone":"+34 937 83 63 23",
    "sg:postcode":"08222",
    "sg:province":"Barcelona",
    "wof:name":"Filmaccio S.c.p.",
    "wof:placetype":"venue"
},
  "geometry": {"coordinates":[2.0219299793,41.5614585876],"type":"Point"}
}