{
  "type": "Feature",
  "properties": {
    "addr:full":"Bernard Vicent (p I Dos Octubre), 6 Santa Fe Granada 18320",
    "addr:housenumber":"6",
    "addr:postcode":"18320",
    "addr:street":"Bernard Vicent P;Dos Octubre;Fe",
    "iso:country":"ES",
    "sg:address":"Bernard Vicent (p I Dos Octubre), 6",
    "sg:city":"Santa Fe",
    "sg:orig_category":"Centros Empresariales",
    "sg:phone":"+34 958 44 15 53",
    "sg:postcode":"18320",
    "sg:province":"Granada",
    "wof:name":"Stc",
    "wof:placetype":"venue"
},
  "geometry": {"coordinates":[-3.7343680859,37.1921691895],"type":"Point"}
}