{
  "type": "Feature",
  "properties": {
    "iso:country":"ES",
    "sg:address":"Calle de Espronceda, 31",
    "sg:city":"Madrid",
    "sg:orig_category":"Fotocopias, Reprograf\u00cda",
    "sg:phone":"+34 915 34 53 17",
    "sg:postcode":"28003",
    "sg:province":"Madrid",
    "sg:website":"www.croquis-online.com",
    "wof:name":"Croquis Fotocopias S.l.",
    "wof:placetype":"venue"
},
  "geometry": {"coordinates":[-3.6951069832,40.4406471252],"type":"Point"}
}