{
  "type": "Feature",
  "properties": {
    "iso:country":"ES",
    "sg:address":"Calle de Victor Hevia, 12",
    "sg:city":"Oviedo",
    "sg:orig_category":"Guarder\u00cdas",
    "sg:phone":"+34 985 25 91 90",
    "sg:postcode":"33012",
    "sg:province":"Asturias",
    "wof:name":"Fraga Seoane Maria Del Carmen",
    "wof:placetype":"venue"
},
  "geometry": {"coordinates":[-5.8633117676,43.3664970398],"type":"Point"}
}