{
  "type": "Feature",
  "properties": {
    "addr:full":"Carr Ctra De Calaf, S/n S. Guim Freixenet Lleida 25270",
    "addr:housenumber":"s",
    "addr:postcode":"25270",
    "addr:street":"Carr Ctra De Calaf;/ N S.",
    "iso:country":"ES",
    "sg:address":"Carr Ctra De Calaf, S/n",
    "sg:city":"S. Guim Freixenet",
    "sg:orig_category":"Material Y Herramientas Agr\u00cdcolas",
    "sg:phone":"+34 973 55 60 84",
    "sg:postcode":"25270",
    "sg:province":"Lleida",
    "wof:name":"Co-trac Agricola S.l.",
    "wof:placetype":"venue"
},
  "geometry": {"coordinates":[1.3964250088,41.6603088379],"type":"Point"}
}