{
  "type": "Feature",
  "properties": {
    "addr:full":"Afueras, S/n S. Antoni Portmany Islas Baleares 07820",
    "addr:postcode":"07820",
    "addr:street":"Afueras S / N S. Antoni Portmany",
    "iso:country":"ES",
    "sg:address":"Afueras, S/n",
    "sg:city":"S. Antoni Portmany",
    "sg:orig_category":"Empresarios",
    "sg:phone":"+34 971 34 60 34",
    "sg:postcode":"07820",
    "sg:province":"Islas Baleares",
    "wof:name":"Arabi Serra Juan",
    "wof:placetype":"venue"
},
  "geometry": {"coordinates":[2.8577105999,39.5341796875],"type":"Point"}
}