{
  "type": "Feature",
  "properties": {
    "addr:full":"Calle de Carderos, 20 Merida Badajoz 06800",
    "addr:housenumber":"20",
    "addr:postcode":"06800",
    "addr:street":"Calle De Carderos",
    "iso:country":"ES",
    "sg:address":"Calle de Carderos, 20",
    "sg:city":"Merida",
    "sg:orig_category":"Sindicatos De Trabajadores",
    "sg:phone":"+34 924 33 04 53",
    "sg:postcode":"06800",
    "sg:province":"Badajoz",
    "wof:name":"Union General De Trabajadores Federacion De Transportes Comunicaciones Y Mar",
    "wof:placetype":"venue"
},
  "geometry": {"coordinates":[-6.3434591293,38.9212112427],"type":"Point"}
}