{
  "type": "Feature",
  "properties": {
    "iso:country":"ES",
    "sg:address":"Carrer de Anglesola, 33",
    "sg:city":"Barcelona",
    "sg:orig_category":"Autob\u00das (explotaci\u00d3n Y Servicios De)",
    "sg:phone":"+34 933 22 78 14",
    "sg:postcode":"08014",
    "sg:province":"Barcelona",
    "wof:name":"La Hispano De Fuente Ensegures S. A.",
    "wof:placetype":"venue"
},
  "geometry": {"coordinates":[2.1330530643,41.388584137],"type":"Point"}
}