{
  "type": "Feature",
  "properties": {
    "addr:full":"Plaz Autonomia (de La), 8 Andujar Ja\u00e9n 23740",
    "addr:postcode":"23740",
    "addr:street":"Jae\u0301N",
    "iso:country":"ES",
    "sg:address":"Plaz Autonomia (de La), 8",
    "sg:city":"Andujar",
    "sg:orig_category":"Electrodom\u00c9sticos (fabricaci\u00d3n, Al Por Mayor)",
    "sg:phone":"+34 953 50 14 70",
    "sg:postcode":"23740",
    "sg:province":"Ja\u00e9n",
    "wof:name":"Singer Distribucion S.a.",
    "wof:placetype":"venue"
},
  "geometry": {"coordinates":[-4.057518959,38.0386962891],"type":"Point"}
}