{
  "type": "Feature",
  "properties": {
    "iso:country":"ES",
    "sg:address":"Carr Marques De Dos Aguas, 7",
    "sg:city":"Betera",
    "sg:orig_category":"Asesor\u00cda Sobre Comunicaci\u00d3n De Empresas",
    "sg:phone":"+34 961 69 12 16",
    "sg:postcode":"46117",
    "sg:province":"Valencia",
    "wof:name":"Adc Asesores Mislata S.l.",
    "wof:placetype":"venue"
},
  "geometry": {"coordinates":[-0.4582732916,39.5875205994],"type":"Point"}
}