{
  "type": "Feature",
  "properties": {
    "iso:country":"ES",
    "sg:address":"Calle de Islas Cies, 15",
    "sg:city":"Madrid",
    "sg:orig_category":"Farmacias",
    "sg:phone":"+34 917 39 64 58",
    "sg:postcode":"28035",
    "sg:province":"Madrid",
    "wof:name":"Mantecon Silva Cesar",
    "wof:placetype":"venue"
},
  "geometry": {"coordinates":[-3.719285965,40.4802932739],"type":"Point"}
}