{
  "type": "Feature",
  "properties": {
    "addr:full":"Calle de San Gerardo, 7 Madrid Madrid 28035",
    "addr:housenumber":"7",
    "addr:postcode":"madrid;28035",
    "addr:street":"Calle De San Gerardo",
    "iso:country":"ES",
    "sg:address":"Calle de San Gerardo, 7",
    "sg:city":"Madrid",
    "sg:orig_category":"Cl\u00cdnicas Dentales",
    "sg:phone":"+34 913 76 86 12",
    "sg:postcode":"28035",
    "sg:province":"Madrid",
    "wof:name":"Dental Aza\u00f1on S.l.",
    "wof:placetype":"venue"
},
  "geometry": {"coordinates":[-3.721558094,40.4666175842],"type":"Point"}
}