{
  "type": "Feature",
  "properties": {
    "iso:country":"ES",
    "sg:address":"Pagoeta Kalea, 2",
    "sg:city":"Zarautz",
    "sg:orig_category":"Escayola Y Productos De Escayola (fabricaci\u00d3n, Al Por Mayor)",
    "sg:phone":"+34 943 83 47 15",
    "sg:postcode":"20800",
    "sg:province":"Guip\u00f9zcoa",
    "wof:name":"Vicente Ramos Juan Alfonso",
    "wof:placetype":"venue"
},
  "geometry": {"coordinates":[-2.164495945,43.2801780701],"type":"Point"}
}