{
  "type": "Feature",
  "properties": {
    "iso:country":"ES",
    "sg:address":"Carrer de Angel Guimera, 16",
    "sg:city":"Manresa",
    "sg:orig_category":"Cajas Para Embalar",
    "sg:phone":"+34 938 72 33 33",
    "sg:postcode":"08241",
    "sg:province":"Barcelona",
    "sg:website":"www.cajamar.es",
    "wof:name":"Cajamar",
    "wof:placetype":"venue"
},
  "geometry": {"coordinates":[1.8245199919,41.7261199951],"type":"Point"}
}