{
  "type": "Feature",
  "properties": {
    "addr:full":"Pg Sant Joan, 111 Barcelona Barcelona 08037",
    "addr:housenumber":"111",
    "addr:postcode":"08037",
    "addr:street":"Pg Sant Joan",
    "iso:country":"ES",
    "sg:address":"Pg Sant Joan, 111",
    "sg:city":"Barcelona",
    "sg:orig_category":"Platos Preparados Refrigerados (fabricaci\u00d3n, Al Por Mayor)",
    "sg:phone":"+34 934 57 54 27",
    "sg:postcode":"08037",
    "sg:province":"Barcelona",
    "wof:name":"Ferrer Vila Pedro",
    "wof:placetype":"venue"
},
  "geometry": {"coordinates":[2.1684930325,41.3999671936],"type":"Point"}
}