{
  "type": "Feature",
  "properties": {
    "addr:full":"Calle de Doctor Manuel Candela, 8 Valencia Valencia 46021",
    "addr:housenumber":"8",
    "addr:postcode":"46021",
    "addr:street":"Calle De Doctor Manuel Candela",
    "iso:country":"ES",
    "sg:address":"Calle de Doctor Manuel Candela, 8",
    "sg:city":"Valencia",
    "sg:orig_category":"Asesor\u00cda Sobre Comunicaci\u00d3n De Empresas",
    "sg:phone":"+34 963 30 58 48",
    "sg:postcode":"46021",
    "sg:province":"Valencia",
    "wof:name":"Sifre Asesoria S.l.",
    "wof:placetype":"venue"
},
  "geometry": {"coordinates":[-0.3507229984,39.4661712646],"type":"Point"}
}