{
  "type": "Feature",
  "properties": {
    "iso:country":"ES",
    "sg:address":"Calle de Marques De La Ensenada, 12",
    "sg:city":"Flota",
    "sg:orig_category":"Psic\u00d3logos",
    "sg:phone":"+34 968 20 30 36",
    "sg:postcode":"30007",
    "sg:province":"Murcia",
    "wof:name":"Martinez Martinez Isabel",
    "wof:placetype":"venue"
},
  "geometry": {"coordinates":[-1.1142389774,37.9970092773],"type":"Point"}
}