{
  "type": "Feature",
  "properties": {
    "addr:full":"Carrer de Pare Llaurador, 181 Terrassa Barcelona 08224",
    "addr:housenumber":"181",
    "addr:postcode":"08224",
    "addr:street":"Carrer De Pare Llaurador",
    "iso:country":"ES",
    "sg:address":"Carrer de Pare Llaurador, 181",
    "sg:city":"Terrassa",
    "sg:orig_category":"Fabricaci\u00d3n De Etiquetas",
    "sg:phone":"+34 937 80 95 81",
    "sg:postcode":"08224",
    "sg:province":"Barcelona",
    "wof:name":"Rodriguez Artero Juan Manuel",
    "wof:placetype":"venue"
},
  "geometry": {"coordinates":[2.0015149117,41.5640029907],"type":"Point"}
}