{
  "type": "Feature",
  "properties": {
    "addr:full":"Avda Ramon Y Cajal, 87 Almaden Ciudad Real 13400",
    "addr:housenumber":"87",
    "addr:postcode":"13400",
    "addr:street":"Avda Ramon Y Cajal;Real",
    "iso:country":"ES",
    "sg:address":"Avda Ramon Y Cajal, 87",
    "sg:city":"Almaden",
    "sg:orig_category":"Mec\u00c1nico Del Autom\u00d3vil",
    "sg:phone":"+34 926 71 33 01",
    "sg:postcode":"13400",
    "sg:province":"Ciudad Real",
    "wof:name":"Talleres El Cristo C.b.",
    "wof:placetype":"venue"
},
  "geometry": {"coordinates":[-4.8295559883,38.7821083069],"type":"Point"}
}