{
  "type": "Feature",
  "properties": {
    "iso:country":"ES",
    "sg:address":"Plaz Constitucion, 19",
    "sg:city":"Hinojosa Del Valle",
    "sg:orig_category":"Iglesia Cat\u00d3lica",
    "sg:phone":"+34 924 53 76 53",
    "sg:postcode":"06226",
    "sg:province":"Badajoz",
    "wof:name":"Parroquia Nuestra Se\u00f1ora De Los Angeles",
    "wof:placetype":"venue"
},
  "geometry": {"coordinates":[-6.1845979691,38.4829139709],"type":"Point"}
}