{
  "type": "Feature",
  "properties": {
    "iso:country":"ES",
    "sg:address":"Calle de Lopez De Hoyos, 371",
    "sg:city":"Madrid",
    "sg:orig_category":"Molduras, Junquillos, Listones Y Molduras Perforadas",
    "sg:phone":"+34 917 63 80 69",
    "sg:postcode":"28043",
    "sg:province":"Madrid",
    "wof:name":"Alonso Somolinos Victor",
    "wof:placetype":"venue"
},
  "geometry": {"coordinates":[-3.6564846039,40.4646072388],"type":"Point"}
}