{
  "type": "Feature",
  "properties": {
    "iso:country":"ES",
    "sg:address":"Paradivas, S/n",
    "sg:city":"Cesar",
    "sg:orig_category":"Vidrio, Fabricaci\u00d3n Y Comercio",
    "sg:phone":"+34 986 55 21 53",
    "sg:postcode":"36654",
    "sg:province":"Pontevedra",
    "wof:name":"Cristaleria Senin S. L.",
    "wof:placetype":"venue"
},
  "geometry": {"coordinates":[-8.8061437607,42.5139198303],"type":"Point"}
}