{
  "type": "Feature",
  "properties": {
    "iso:country":"ES",
    "sg:address":"Carrer de Mas Casanovas, 30",
    "sg:city":"Barcelona",
    "sg:orig_category":"Peluqueros: De Se\u00d1oras",
    "sg:phone":"+34 934 36 46 19",
    "sg:postcode":"08025",
    "sg:province":"Barcelona",
    "wof:name":"Alvaro Perez Vicenta",
    "wof:placetype":"venue"
},
  "geometry": {"coordinates":[2.1695575714,41.41223526],"type":"Point"}
}