{
  "type": "Feature",
  "properties": {
    "iso:country":"ES",
    "sg:address":"Las Tosquillas, 27",
    "sg:city":"Telde",
    "sg:orig_category":"Garajes De Veh\u00cdculos",
    "sg:phone":"+34 928 69 40 03",
    "sg:postcode":"35200",
    "sg:province":"Las Palmas",
    "wof:name":"Talleres El Contrapeso S.l.",
    "wof:placetype":"venue"
},
  "geometry": {"coordinates":[-15.4153785706,27.9927692413],"type":"Point"}
}