{
  "type": "Feature",
  "properties": {
    "addr:full":"Avda Andalucia (de), 229 Estepa Sevilla 41560",
    "addr:housenumber":"229",
    "addr:postcode":"41560",
    "addr:street":"Avda Andalucia De;Sevilla",
    "iso:country":"ES",
    "sg:address":"Avda Andalucia (de), 229",
    "sg:city":"Estepa",
    "sg:orig_category":"Molduras, Junquillos, Listones Y Molduras Perforadas",
    "sg:phone":"+34 955 91 35 11",
    "sg:postcode":"41560",
    "sg:province":"Sevilla",
    "wof:name":"Dulces La Ponderosa S. L.",
    "wof:placetype":"venue"
},
  "geometry": {"coordinates":[-4.8734321594,37.2929878235],"type":"Point"}
}