{
  "type": "Feature",
  "properties": {
    "iso:country":"ES",
    "sg:address":"Pase Amanecer, S/n",
    "sg:city":"Javea",
    "sg:orig_category":"Molduras, Junquillos, Listones Y Molduras Perforadas",
    "sg:phone":"+34 966 46 84 67",
    "sg:postcode":"03730",
    "sg:province":"Alicante",
    "wof:name":"Gilabert Fornes Pablo",
    "wof:placetype":"venue"
},
  "geometry": {"coordinates":[0.1684439927,38.7892303467],"type":"Point"}
}