{
  "type": "Feature",
  "properties": {
    "iso:country":"ES",
    "sg:address":"Carrer de Argullos, 76",
    "sg:city":"Barcelona",
    "sg:orig_category":"Perfumer\u00cda Y Cosm\u00c9tica (fabricaci\u00d3n, Al Por Mayor)",
    "sg:phone":"+34 933 54 64 85",
    "sg:postcode":"08016",
    "sg:province":"Barcelona",
    "wof:name":"Combe Europa S.l.",
    "wof:placetype":"venue"
},
  "geometry": {"coordinates":[2.1818709373,41.4416732788],"type":"Point"}
}