{
  "type": "Feature",
  "properties": {
    "iso:country":"ES",
    "sg:address":"Calle de Fuenterrabia, 3",
    "sg:city":"Donostia-san Sebastian",
    "sg:orig_category":"Abogados",
    "sg:phone":"+34 943 43 04 29",
    "sg:postcode":"20005",
    "sg:province":"Guip\u00f9zcoa",
    "wof:name":"Santos Redondo Rafael",
    "wof:placetype":"venue"
},
  "geometry": {"coordinates":[-1.9818949699,43.318649292],"type":"Point"}
}