{
  "type": "Feature",
  "properties": {
    "addr:full":"Calle de Union La, 40 Langreo Asturias 33900",
    "addr:housenumber":"40",
    "addr:postcode":"33900",
    "addr:street":"Calle De Union La",
    "iso:country":"ES",
    "sg:address":"Calle de Union La, 40",
    "sg:city":"Langreo",
    "sg:orig_category":"Serigraf\u00cda (material Y Suministros)",
    "sg:phone":"+34 985 67 42 32",
    "sg:postcode":"33900",
    "sg:province":"Asturias",
    "wof:name":"Manuel Corral Fernandez",
    "wof:placetype":"venue"
},
  "geometry": {"coordinates":[-5.6875095367,43.3013191223],"type":"Point"}
}