{
  "type": "Feature",
  "properties": {
    "iso:country":"ES",
    "sg:address":"C/ Josep Maria De Sagarra, 1",
    "sg:city":"Salt",
    "sg:orig_category":"Centros Empresariales",
    "sg:phone":"+34 972 24 25 36",
    "sg:postcode":"17190",
    "sg:province":"Girona",
    "wof:name":"Ros Abuli Cristina",
    "wof:placetype":"venue"
},
  "geometry": {"coordinates":[2.7987589836,41.9758338928],"type":"Point"}
}