{
  "type": "Feature",
  "properties": {
    "iso:country":"ES",
    "sg:address":"Calle de Carrequemada, 88",
    "sg:city":"Aranda Duero",
    "sg:orig_category":"Agencias De Viajes",
    "sg:phone":"+34 947 50 96 43",
    "sg:postcode":"09400",
    "sg:province":"Burgos",
    "wof:name":"Viajes Clemente S.a.",
    "wof:placetype":"venue"
},
  "geometry": {"coordinates":[-3.6818189621,41.6720695496],"type":"Point"}
}