{
  "type": "Feature",
  "properties": {
    "iso:country":"ES",
    "sg:address":"Calle de Cuna, 47",
    "sg:city":"Sevilla",
    "sg:orig_category":"Ropa Para Se\u00d1oras (al Por Menor)",
    "sg:phone":"+34 954 22 04 40",
    "sg:postcode":"41004",
    "sg:province":"Sevilla",
    "wof:name":"Nobasic S.l.",
    "wof:placetype":"venue"
},
  "geometry": {"coordinates":[-5.9933495522,37.3907165527],"type":"Point"}
}