{
  "type": "Feature",
  "properties": {
    "iso:country":"ES",
    "sg:address":"C/ Marques D'asprella, 45",
    "sg:city":"Elche",
    "sg:orig_category":"Asesor\u00cda Fiscal Y Jur\u00cddica",
    "sg:phone":"+34 965 46 50 92",
    "sg:postcode":"03201",
    "sg:province":"Alicante",
    "wof:name":"Unidessa Asesores S.l.",
    "wof:placetype":"venue"
},
  "geometry": {"coordinates":[-0.7026540041,38.2682991028],"type":"Point"}
}