{
  "type": "Feature",
  "properties": {
    "addr:full":"Calle de Federico Garcia Lorca, 19 Almansa Albacete 02640",
    "addr:housenumber":"19",
    "addr:postcode":"02640",
    "addr:street":"Calle De Federico Garcia Lorca",
    "iso:country":"ES",
    "sg:address":"Calle de Federico Garcia Lorca, 19",
    "sg:city":"Almansa",
    "sg:orig_category":"Asociaciones Humanitarias, De Cooperaci\u00d3n, De Acci\u00d3n Social",
    "sg:phone":"+34 967 34 31 07",
    "sg:postcode":"02640",
    "sg:province":"Albacete",
    "wof:name":"Apat Asociacion Para La Prevencion Y Ayuda De Toxicomanos",
    "wof:placetype":"venue"
},
  "geometry": {"coordinates":[-1.0966507196,38.8699760437],"type":"Point"}
}