{
  "type": "Feature",
  "properties": {
    "iso:country":"ES",
    "sg:address":"Avda Castro Girona, S/n",
    "sg:city":"Fuentes Nava",
    "sg:orig_category":"Producci\u00d3n De Abonos Y De Fertilizantes",
    "sg:phone":"+34 979 84 21 43",
    "sg:postcode":"34337",
    "sg:province":"Palencia",
    "wof:name":"Cereales Y Abonos Tazo S.l.",
    "wof:placetype":"venue"
},
  "geometry": {"coordinates":[-4.7915902138,42.0841026306],"type":"Point"}
}