{
  "type": "Feature",
  "properties": {
    "iso:country":"ES",
    "sg:address":"Calle de Tres Forques, 6",
    "sg:city":"Valencia",
    "sg:orig_category":"Alimentaci\u00d3n General (al Por Menor)",
    "sg:phone":"+34 963 84 23 84",
    "sg:postcode":"46018",
    "sg:province":"Valencia",
    "wof:name":"March Bas Carlos",
    "wof:placetype":"venue"
},
  "geometry": {"coordinates":[-0.38894099,39.4644012451],"type":"Point"}
}