{
  "type": "Feature",
  "properties": {
    "addr:full":"Calle de Blasco De Garay, 7 Malaga M\u00e1laga 29001",
    "addr:housenumber":"7",
    "addr:postcode":"29001",
    "addr:street":"Calle De Blasco De Garay;Ma\u0301Laga",
    "iso:country":"ES",
    "sg:address":"Calle de Blasco De Garay, 7",
    "sg:city":"Malaga",
    "sg:orig_category":"Asesor\u00cdas Y Estudios Financieros",
    "sg:phone":"+34 952 21 63 92",
    "sg:postcode":"29001",
    "sg:province":"M\u00e1laga",
    "wof:name":"Perez Romero Jose Manuel",
    "wof:placetype":"venue"
},
  "geometry": {"coordinates":[-4.4223403931,36.7158279419],"type":"Point"}
}