{
  "type": "Feature",
  "properties": {
    "iso:country":"ES",
    "sg:address":"Calle de Puerto De Cardoso, 11",
    "sg:city":"Madrid",
    "sg:orig_category":"Cl\u00cdnicas M\u00c9dicas",
    "sg:phone":"+34 913 03 81 15",
    "sg:postcode":"28018",
    "sg:province":"Madrid",
    "wof:name":"Canovas Garcia Miguel",
    "wof:placetype":"venue"
},
  "geometry": {"coordinates":[-3.6536710262,40.3882522583],"type":"Point"}
}