{
  "type": "Feature",
  "properties": {
    "iso:country":"ES",
    "sg:address":"Calle de Doctor Barraquer, 8",
    "sg:city":"Getafe",
    "sg:orig_category":"Comercio, Reparaci\u00d3n De Bicicletas, De Motocicletas, De Accesorios",
    "sg:phone":"+34 916 96 72 33",
    "sg:postcode":"28903",
    "sg:province":"Madrid",
    "wof:name":"Paris Sanchez Remedios",
    "wof:placetype":"venue"
},
  "geometry": {"coordinates":[-3.7215111256,40.3159713745],"type":"Point"}
}