{
  "type": "Feature",
  "properties": {
    "addr:full":"Avgd Valencia, 47 Lleida Lleida 25001",
    "addr:housenumber":"47",
    "addr:postcode":"25001",
    "addr:street":"Valencia",
    "iso:country":"ES",
    "sg:address":"Avgd Valencia, 47",
    "sg:city":"Lleida",
    "sg:orig_category":"Sonorizaci\u00d3n, Iluminaci\u00d3n",
    "sg:phone":"+34 973 21 36 05",
    "sg:postcode":"25001",
    "sg:province":"Lleida",
    "wof:name":"Muntatges Electro So, Sl",
    "wof:placetype":"venue"
},
  "geometry": {"coordinates":[0.6268299818,41.6096305847],"type":"Point"}
}