{
  "type": "Feature",
  "properties": {
    "iso:country":"ES",
    "sg:address":"Calle de Embajadores, 161",
    "sg:city":"Madrid",
    "sg:orig_category":"Bancos",
    "sg:phone":"+34 915 17 87 10",
    "sg:postcode":"28045",
    "sg:province":"Madrid",
    "wof:name":"Otero Conde Maria Elena",
    "wof:placetype":"venue"
},
  "geometry": {"coordinates":[-3.6953849792,40.3954658508],"type":"Point"}
}