{
  "type": "Feature",
  "properties": {
    "addr:full":"Calle de Mirador, 6 Benidorm Alicante 03500",
    "addr:housenumber":"6",
    "addr:postcode":"03500",
    "addr:street":"Calle De Mirador",
    "iso:country":"ES",
    "sg:address":"Calle de Mirador, 6",
    "sg:city":"Benidorm",
    "sg:orig_category":"Agencias De Viajes",
    "sg:phone":"+34 965 86 92 52",
    "sg:postcode":"03500",
    "sg:province":"Alicante",
    "wof:name":"Rosaltour S.l.",
    "wof:placetype":"venue"
},
  "geometry": {"coordinates":[-0.1264639944,38.5410232544],"type":"Point"}
}