{
  "type": "Feature",
  "properties": {
    "addr:full":"Ctra Villar Del Humo, 6 Cardenete Cuenca 16373",
    "addr:housenumber":"6",
    "addr:postcode":"16373",
    "addr:street":"Ctra Villar Del Humo",
    "iso:country":"ES",
    "sg:address":"Ctra Villar Del Humo, 6",
    "sg:city":"Cardenete",
    "sg:orig_category":"Cr\u00cda De Animales",
    "sg:phone":"+34 969 34 83 12",
    "sg:postcode":"16373",
    "sg:province":"Cuenca",
    "wof:name":"Herraiz Perez Amador",
    "wof:placetype":"venue"
},
  "geometry": {"coordinates":[-1.6894241571,39.768825531],"type":"Point"}
}