{
  "type": "Feature",
  "properties": {
    "iso:country":"ES",
    "sg:address":"Plaz Claret, 5",
    "sg:city":"Aranda Duero",
    "sg:orig_category":"Compraventa De Antig\u00dcedades",
    "sg:phone":"+34 947 51 02 96",
    "sg:postcode":"09400",
    "sg:province":"Burgos",
    "wof:name":"Holgueras Gonzalez Francisco",
    "wof:placetype":"venue"
},
  "geometry": {"coordinates":[-3.6889948845,41.6699256897],"type":"Point"}
}