{
  "type": "Feature",
  "properties": {
    "iso:country":"ES",
    "sg:address":"Avda Luis Cuevas, S/n",
    "sg:city":"Tama",
    "sg:orig_category":"Serrer\u00cdas De Madera",
    "sg:phone":"+34 942 73 03 13",
    "sg:postcode":"39584",
    "sg:province":"Cantabria",
    "wof:name":"Diaz Bada Ramona",
    "wof:placetype":"venue"
},
  "geometry": {"coordinates":[-4.6000890732,43.1761398315],"type":"Point"}
}