{
  "type": "Feature",
  "properties": {
    "iso:country":"ES",
    "sg:address":"Carrer de L'artesania, 38",
    "sg:city":"Barcelona",
    "sg:orig_category":"Muebles, Minoristas",
    "sg:phone":"+34 933 50 70 46",
    "sg:postcode":"08042",
    "sg:province":"Barcelona",
    "wof:name":"Muebles Carruesco S.c.p.",
    "wof:placetype":"venue"
},
  "geometry": {"coordinates":[2.1745398045,41.4396438599],"type":"Point"}
}