{
  "type": "Feature",
  "properties": {
    "iso:country":"ES",
    "sg:address":"Calle de Cardenal Goma, 13",
    "sg:city":"Zaragoza",
    "sg:orig_category":"Asociaciones, Organismos Culturales Y Socioeducativos",
    "sg:phone":"+34 976 35 02 16",
    "sg:postcode":"50009",
    "sg:province":"Zaragoza",
    "wof:name":"Asociacion De Antiguos Alumnos Del Colegio Del Salvador",
    "wof:placetype":"venue"
},
  "geometry": {"coordinates":[-0.9024754167,41.6327323914],"type":"Point"}
}