{
  "type": "Feature",
  "properties": {
    "iso:country":"ES",
    "sg:address":"Calle de Doctor Fleming, 6",
    "sg:city":"Orgiva",
    "sg:orig_category":"Carnicer\u00cdas, Carnicer\u00cdas",
    "sg:phone":"+34 958 78 42 74",
    "sg:postcode":"18400",
    "sg:province":"Granada",
    "wof:name":"Fernandez Marquez Agustin Segundo",
    "wof:placetype":"venue"
},
  "geometry": {"coordinates":[-3.4239623547,36.9014854431],"type":"Point"}
}