{
  "type": "Feature",
  "properties": {
    "addr:full":"Carrer de Ermengarda, 39 Barcelona Barcelona 08014",
    "addr:housenumber":"39",
    "addr:postcode":"08014",
    "addr:street":"Carrer De Ermengarda",
    "iso:country":"ES",
    "sg:address":"Carrer de Ermengarda, 39",
    "sg:city":"Barcelona",
    "sg:orig_category":"Ingeniero",
    "sg:phone":"+34 933 25 21 46",
    "sg:postcode":"08014",
    "sg:province":"Barcelona",
    "wof:name":"Carroi Pic, Sl",
    "wof:placetype":"venue"
},
  "geometry": {"coordinates":[2.1436769962,41.3773155212],"type":"Point"}
}