{
  "type": "Feature",
  "properties": {
    "iso:country":"ES",
    "sg:address":"Arruriaga Kalea, 13",
    "sg:city":"Bergara",
    "sg:orig_category":"Sindicatos De Trabajadores",
    "sg:phone":"+34 943 76 46 51",
    "sg:postcode":"20570",
    "sg:province":"Guip\u00f9zcoa",
    "wof:name":"Comisiones Obreras De Euskadi",
    "wof:placetype":"venue"
},
  "geometry": {"coordinates":[-2.4120531082,43.118522644],"type":"Point"}
}