{
  "type": "Feature",
  "properties": {
    "addr:full":"Carrer de L'artesania, 39 Barcelona Barcelona 08042",
    "addr:housenumber":"39",
    "addr:postcode":"08042",
    "addr:street":"Carrer De L'Artesania",
    "iso:country":"ES",
    "sg:address":"Carrer de L'artesania, 39",
    "sg:city":"Barcelona",
    "sg:orig_category":"Centros De Educaci\u00d3n Especial",
    "sg:phone":"+34 933 50 57 48",
    "sg:postcode":"08042",
    "sg:province":"Barcelona",
    "wof:name":"Ajuntament De Barcelona",
    "wof:placetype":"venue"
},
  "geometry": {"coordinates":[2.1728389263,41.4413795471],"type":"Point"}
}