{
  "type": "Feature",
  "properties": {
    "addr:full":"Calle de Cuestablanca (de), 153 Alcobendas Madrid 28108",
    "addr:housenumber":"153",
    "addr:postcode":"28108",
    "addr:street":"Calle De Cuestablanca De",
    "iso:country":"ES",
    "sg:address":"Calle de Cuestablanca (de), 153",
    "sg:city":"Alcobendas",
    "sg:orig_category":"Industria Qu\u00cdmica",
    "sg:phone":"+34 916 25 21 01",
    "sg:postcode":"28108",
    "sg:province":"Madrid",
    "wof:name":"Dozaro Medio Ambiente S.l.",
    "wof:placetype":"venue"
},
  "geometry": {"coordinates":[-3.6535570621,40.5214691162],"type":"Point"}
}