{
  "type": "Feature",
  "properties": {
    "addr:full":"Calle de Principe De Vergara, 62 Madrid Madrid 28006",
    "addr:housenumber":"62",
    "addr:postcode":"madrid;28006",
    "addr:street":"Calle De Principe De Vergara",
    "iso:country":"ES",
    "sg:address":"Calle de Principe De Vergara, 62",
    "sg:city":"Madrid",
    "sg:orig_category":"Ense\u00d1anza: Idiomas",
    "sg:phone":"+34 915 78 17 15",
    "sg:postcode":"28006",
    "sg:province":"Madrid",
    "wof:name":"Pesquera Del Pozo Jorge Luis",
    "wof:placetype":"venue"
},
  "geometry": {"coordinates":[-3.6793711185,40.4323348999],"type":"Point"}
}