{
  "type": "Feature",
  "properties": {
    "iso:country":"ES",
    "sg:address":"Cno. Zarcilla, S/n",
    "sg:city":"Las Navas Marques",
    "sg:orig_category":"Empresas De Carpinter\u00cda De Madera",
    "sg:phone":"+34 918 97 24 76",
    "sg:postcode":"05230",
    "sg:province":"\u00c1vila",
    "wof:name":"Quiros Pascual Julian",
    "wof:placetype":"venue"
},
  "geometry": {"coordinates":[-4.3334889412,40.6027450562],"type":"Point"}
}