{
  "type": "Feature",
  "properties": {
    "addr:full":"Avda Espa\u00d1a (de), S/n San Eugenio Bajo Santa Cruz De Tenerife 38660",
    "addr:housenumber":"/ n",
    "addr:postcode":"38660",
    "addr:street":"Avda Espan\u0303A De S",
    "iso:country":"ES",
    "sg:address":"Avda Espa\u00d1a (de), S/n",
    "sg:city":"San Eugenio Bajo",
    "sg:orig_category":"Supermercados Y Hipermercados",
    "sg:phone":"+34 922 71 43 21",
    "sg:postcode":"38660",
    "sg:province":"Santa Cruz De Tenerife",
    "wof:name":"Mcdowell  Carol Rosly",
    "wof:placetype":"venue"
},
  "geometry": {"coordinates":[-16.7335681915,28.0807247162],"type":"Point"}
}