{
  "type": "Feature",
  "properties": {
    "iso:country":"ES",
    "sg:address":"Avda Mariano Andres, 21",
    "sg:city":"Le\u00f3n",
    "sg:orig_category":"Farmacias",
    "sg:phone":"+34 987 22 57 86",
    "sg:postcode":"24008",
    "sg:province":"Le\u00f3n",
    "wof:name":"Rodriguez Torre Rosa Maria",
    "wof:placetype":"venue"
},
  "geometry": {"coordinates":[-5.5732607841,42.6062355042],"type":"Point"}
}