{
  "type": "Feature",
  "properties": {
    "iso:country":"ES",
    "sg:address":"Ctra Jimena, Km. 0006,6",
    "sg:city":"Baeza",
    "sg:orig_category":"Aceites Y Grasas Alimentarias (fabricaci\u00d3n, Al Por Mayor)",
    "sg:phone":"+34 953 74 02 85",
    "sg:postcode":"23440",
    "sg:province":"Ja\u00e9n",
    "wof:name":"Olea Andaluza S.a.t.",
    "wof:placetype":"venue"
},
  "geometry": {"coordinates":[-3.4683389664,37.9931411743],"type":"Point"}
}