{
  "type": "Feature",
  "properties": {
    "iso:country":"ES",
    "sg:address":"Calle de Barcelo, 6",
    "sg:city":"Madrid",
    "sg:orig_category":"Comerciantes Al Por Mayor De Vinos, Licores Y Alcoholes",
    "sg:phone":"+34 914 45 08 90",
    "sg:postcode":"28004",
    "sg:province":"Madrid",
    "wof:name":"Velez Tinitana Wilmer Francisco",
    "wof:placetype":"venue"
},
  "geometry": {"coordinates":[-3.6990070343,40.4268722534],"type":"Point"}
}