{
  "type": "Feature",
  "properties": {
    "addr:full":"Calle de Manuel Luna, 12 Madrid Madrid 28020",
    "addr:housenumber":"12",
    "addr:postcode":"madrid;28020",
    "addr:street":"Calle De Manuel Luna",
    "iso:country":"ES",
    "sg:address":"Calle de Manuel Luna, 12",
    "sg:city":"Madrid",
    "sg:orig_category":"Centros Empresariales",
    "sg:phone":"+34 914 25 24 10",
    "sg:postcode":"28020",
    "sg:province":"Madrid",
    "wof:name":"Prysma Calidad Y Medioambiente S.a.",
    "wof:placetype":"venue"
},
  "geometry": {"coordinates":[-3.7000110149,40.4544868469],"type":"Point"}
}