{
  "type": "Feature",
  "properties": {
    "addr:full":"Av Creu Roja, 1 Cerdanyola Valles Barcelona 08290",
    "addr:housenumber":"1",
    "addr:postcode":"08290",
    "addr:street":"Av Creu Roja;Valles Barcelona",
    "iso:country":"ES",
    "sg:address":"Av Creu Roja, 1",
    "sg:city":"Cerdanyola Valles",
    "sg:orig_category":"Inform\u00c1tica (estudios, Servicios, Asesor\u00cda, Formaci\u00d3n)",
    "sg:phone":"+34 935 92 15 56",
    "sg:postcode":"08290",
    "sg:province":"Barcelona",
    "wof:name":"Proyecto De Informatica Portatil S.l.",
    "wof:placetype":"venue"
},
  "geometry": {"coordinates":[2.1486101151,41.4935913086],"type":"Point"}
}