{
  "type": "Feature",
  "properties": {
    "addr:full":"Avda Constitucion, 59 Talarrubias Badajoz 06640",
    "addr:housenumber":"59",
    "addr:postcode":"06640",
    "addr:street":"Avda Constitucion",
    "iso:country":"ES",
    "sg:address":"Avda Constitucion, 59",
    "sg:city":"Talarrubias",
    "sg:orig_category":"Inform\u00c1tica, Ofim\u00c1tica (estudios, Asesor\u00cda, Ingenier\u00cda, Formaci\u00d3n)",
    "sg:phone":"+34 924 63 12 34",
    "sg:postcode":"06640",
    "sg:province":"Badajoz",
    "wof:name":"Gonzalez Camacho Victor Manuel",
    "wof:placetype":"venue"
},
  "geometry": {"coordinates":[-5.2351150513,39.0364875793],"type":"Point"}
}