{
  "type": "Feature",
  "properties": {
    "iso:country":"ES",
    "sg:address":"Calle de San Roque, 48",
    "sg:city":"Valencia",
    "sg:orig_category":"Maquinaria Para Industrias Diversas",
    "sg:phone":"+34 963 40 72 35",
    "sg:postcode":"46015",
    "sg:province":"Valencia",
    "wof:name":"Microclima,72,s.l.",
    "wof:placetype":"venue"
},
  "geometry": {"coordinates":[-0.3949609995,39.4914703369],"type":"Point"}
}