{
  "type": "Feature",
  "properties": {
    "addr:full":"Plaz Espa\u00d1a, 7 Aguilas Murcia 30880",
    "addr:housenumber":"7",
    "addr:postcode":"30880",
    "addr:street":"Plaz Espan\u0303A",
    "iso:country":"ES",
    "sg:address":"Plaz Espa\u00d1a, 7",
    "sg:city":"Aguilas",
    "sg:orig_category":"Inmobiliaria (agencias)",
    "sg:phone":"+34 968 41 21 70",
    "sg:postcode":"30880",
    "sg:province":"Murcia",
    "wof:name":"Dursa Properties S.l.",
    "wof:placetype":"venue"
},
  "geometry": {"coordinates":[-1.5839740038,37.4077987671],"type":"Point"}
}