{
  "type": "Feature",
  "properties": {
    "iso:country":"ES",
    "sg:address":"Ctra Villacastin, S/n",
    "sg:city":"Valcabado",
    "sg:orig_category":"Contenedores (mercanc\u00cdas)",
    "sg:phone":"+34 980 53 86 02",
    "sg:postcode":"49192",
    "sg:province":"Zamora",
    "wof:name":"Esteban Iberdion Transporte S.l.",
    "wof:placetype":"venue"
},
  "geometry": {"coordinates":[-5.8029990196,41.550819397],"type":"Point"}
}