{
  "type": "Feature",
  "properties": {
    "addr:full":"Calle de Flor De Azalea, 2 Sevilla Sevilla 41020",
    "addr:housenumber":"2",
    "addr:postcode":"41020",
    "addr:street":"Calle De Flor De Azalea",
    "iso:country":"ES",
    "sg:address":"Calle de Flor De Azalea, 2",
    "sg:city":"Sevilla",
    "sg:orig_category":"Agentes Generales De Seguros",
    "sg:phone":"+34 954 40 17 46",
    "sg:postcode":"41020",
    "sg:province":"Sevilla",
    "wof:name":"Cortes Ruiz Diego",
    "wof:placetype":"venue"
},
  "geometry": {"coordinates":[-5.9194560051,37.391960144],"type":"Point"}
}