{
  "type": "Feature",
  "properties": {
    "addr:full":"Ctra Valverde Del Camino De, 4 Palma Condado Huelva 21700",
    "addr:housenumber":"4",
    "addr:postcode":"21700",
    "addr:street":"Ctra Valverde;Camino De",
    "iso:country":"ES",
    "sg:address":"Ctra Valverde Del Camino De, 4",
    "sg:city":"Palma Condado",
    "sg:orig_category":"Velas Y Cirios (fabricaci\u00d3n, Al Por Menor)",
    "sg:phone":"+34 959 40 19 55",
    "sg:postcode":"21700",
    "sg:province":"Huelva",
    "sg:website":"www.cereriaelnazareno.com",
    "wof:name":"Ortega Gamero Maria Del Rosario",
    "wof:placetype":"venue"
},
  "geometry": {"coordinates":[-6.556842804,37.3890342712],"type":"Point"}
}