{
  "type": "Feature",
  "properties": {
    "addr:full":"Avda Avila, 27 Mu\u00f1ico \u00c1vila 05144",
    "addr:housenumber":"27",
    "addr:postcode":"05144",
    "addr:street":"Avda Avila;A\u0301Vila",
    "iso:country":"ES",
    "sg:address":"Avda Avila, 27",
    "sg:city":"Mu\u00f1ico",
    "sg:orig_category":"Cajas De Ahorro",
    "sg:phone":"+34 920 23 23 06",
    "sg:postcode":"05144",
    "sg:province":"\u00c1vila",
    "wof:name":"Caja De Avila",
    "wof:placetype":"venue"
},
  "geometry": {"coordinates":[-5.0269908905,40.7054824829],"type":"Point"}
}