{
  "type": "Feature",
  "properties": {
    "addr:full":"Calle de Hermanos Maristas, 1 Huelva Huelva 21006",
    "addr:housenumber":"1",
    "addr:postcode":"21006",
    "addr:street":"Calle De Hermanos Maristas",
    "iso:country":"ES",
    "sg:address":"Calle de Hermanos Maristas, 1",
    "sg:city":"Huelva",
    "sg:orig_category":"Mercer\u00cda, Lencer\u00cda (al Por Menor)",
    "sg:phone":"+34 959 23 09 99",
    "sg:postcode":"21006",
    "sg:province":"Huelva",
    "wof:name":"Garcia Caro Josefa",
    "wof:placetype":"venue"
},
  "geometry": {"coordinates":[-6.9495940208,37.256313324],"type":"Point"}
}