{
  "type": "Feature",
  "properties": {
    "addr:full":"Carr De Maians, 3 Ontinyent Valencia 46870",
    "addr:housenumber":"3",
    "addr:postcode":"46870",
    "addr:street":"Carr De Maians",
    "iso:country":"ES",
    "sg:address":"Carr De Maians, 3",
    "sg:city":"Ontinyent",
    "sg:orig_category":"M\u00c9dicos: Estomatolog\u00cda",
    "sg:phone":"+34 962 91 02 79",
    "sg:postcode":"46870",
    "sg:province":"Valencia",
    "wof:name":"Sempere Galbis Jose Alberto",
    "wof:placetype":"venue"
},
  "geometry": {"coordinates":[-0.6030989885,38.8258895874],"type":"Point"}
}