{
  "type": "Feature",
  "properties": {
    "iso:country":"ES",
    "sg:address":"Calle de Padre Suarez, 22",
    "sg:city":"Oviedo",
    "sg:orig_category":"Diarios, Revistas Y Boletines (distribuidores)",
    "sg:phone":"+34 985 21 35 36",
    "sg:postcode":"33009",
    "sg:province":"Asturias",
    "wof:name":"Diaz Vallina Amalia",
    "wof:placetype":"venue"
},
  "geometry": {"coordinates":[-5.8424038887,43.3573989868],"type":"Point"}
}