{
  "type": "Feature",
  "properties": {
    "iso:country":"ES",
    "sg:address":"Plaz Barcelona, 26",
    "sg:city":"Salamanca",
    "sg:orig_category":"Maquinaria Para Industrias Diversas",
    "sg:phone":"+34 923 23 05 97",
    "sg:postcode":"37004",
    "sg:province":"Salamanca",
    "wof:name":"Hernandez Gonzalez Desiderio",
    "wof:placetype":"venue"
},
  "geometry": {"coordinates":[-5.6506609917,40.9734649658],"type":"Point"}
}