{
  "type": "Feature",
  "properties": {
    "addr:full":"Ctra Norte Del, 158 Palmas De Gran Canaria Las Palmas 35013",
    "addr:housenumber":"158",
    "addr:postcode":"35013",
    "addr:street":"Ctra Norte Del",
    "iso:country":"ES",
    "sg:address":"Ctra Norte Del, 158",
    "sg:city":"Palmas De Gran Canaria",
    "sg:orig_category":"Veh\u00cdculos De Ocasi\u00d3n",
    "sg:phone":"+34 928 42 25 60",
    "sg:postcode":"35013",
    "sg:province":"Las Palmas",
    "wof:name":"Velasco Paquez Ruben Oscar",
    "wof:placetype":"venue"
},
  "geometry": {"coordinates":[-15.5745563507,28.1141796112],"type":"Point"}
}