{
  "type": "Feature",
  "properties": {
    "addr:full":"Avgd Horchata, 45 Alboraya Valencia 46120",
    "addr:housenumber":"45",
    "addr:postcode":"46120",
    "addr:street":"Horchata",
    "iso:country":"ES",
    "sg:address":"Avgd Horchata, 45",
    "sg:city":"Alboraya",
    "sg:orig_category":"Alquiler De Veh\u00cdculos: Turismos Y Utilitarios",
    "sg:phone":"+34 961 85 22 04",
    "sg:postcode":"46120",
    "sg:province":"Valencia",
    "sg:website":"www.atesa.es",
    "wof:name":"Autotransporte Turistico Espa\u00f1ol S.a.",
    "wof:placetype":"venue"
},
  "geometry": {"coordinates":[-0.3535161018,39.4964790344],"type":"Point"}
}