{
  "type": "Feature",
  "properties": {
    "iso:country":"ES",
    "sg:address":"Calle de C(san Rafael), 47",
    "sg:city":"Hellin",
    "sg:orig_category":"Suministros Para Carrocer\u00cdas",
    "sg:phone":"+34 967 30 76 93",
    "sg:postcode":"02400",
    "sg:province":"Albacete",
    "wof:name":"Carrocerias Juan Y Julio S.l.l.",
    "wof:placetype":"venue"
},
  "geometry": {"coordinates":[-1.7024521828,38.5132217407],"type":"Point"}
}