{
  "type": "Feature",
  "properties": {
    "addr:full":"Calle de Poniente, 39 Armilla Granada 18100",
    "addr:housenumber":"39",
    "addr:postcode":"18100",
    "addr:street":"Calle De Poniente",
    "iso:country":"ES",
    "sg:address":"Calle de Poniente, 39",
    "sg:city":"Armilla",
    "sg:orig_category":"Agencias Y Agentes Comerciales, Representantes",
    "sg:phone":"+34 958 57 86 13",
    "sg:postcode":"18100",
    "sg:province":"Granada",
    "wof:name":"Comunidad De Propieatarios Avenida Poniente 43",
    "wof:placetype":"venue"
},
  "geometry": {"coordinates":[-3.6318669319,37.1427230835],"type":"Point"}
}