{
  "type": "Feature",
  "properties": {
    "iso:country":"ES",
    "sg:address":"Calle de Doctor Moliner, 5",
    "sg:city":"Valencia",
    "sg:orig_category":"Doctores En Medicina",
    "sg:phone":"+34 963 62 13 50",
    "sg:postcode":"46010",
    "sg:province":"Valencia",
    "wof:name":"Fernandez Rodriguez Angel",
    "wof:placetype":"venue"
},
  "geometry": {"coordinates":[-0.3629972041,39.4759635925],"type":"Point"}
}