{
  "type": "Feature",
  "properties": {
    "iso:country":"ES",
    "sg:address":"Carrer de Valencia, 5",
    "sg:city":"Ampolla",
    "sg:orig_category":"Inmobiliaria (agencias)",
    "sg:phone":"+34 977 46 06 55",
    "sg:postcode":"43895",
    "sg:province":"Tarragona",
    "wof:name":"Comunitat De Propietaris Edifici Llevant",
    "wof:placetype":"venue"
},
  "geometry": {"coordinates":[0.7041680217,40.8076210022],"type":"Point"}
}