{
  "type": "Feature",
  "properties": {
    "addr:full":"Calle de Enric Valor, 1 Mislata Valencia 46920",
    "addr:housenumber":"1",
    "addr:postcode":"46920",
    "addr:street":"Calle De Enric Valor",
    "iso:country":"ES",
    "sg:address":"Calle de Enric Valor, 1",
    "sg:city":"Mislata",
    "sg:orig_category":"Ropa De Trabajo Y Profesionales (fabricaci\u00d3n, Al Por Mayor)",
    "sg:phone":"+34 963 59 95 55",
    "sg:postcode":"46920",
    "sg:province":"Valencia",
    "wof:name":"Lujan Mateo Maria Teresa",
    "wof:placetype":"venue"
},
  "geometry": {"coordinates":[-0.4255439937,39.4771118164],"type":"Point"}
}