{
  "type": "Feature",
  "properties": {
    "addr:full":"Ctra Villamarchante, 119 Riba-roja Turia Valencia 46190",
    "addr:housenumber":"119",
    "addr:postcode":"46190",
    "addr:street":"Ctra Villamarchante",
    "iso:country":"ES",
    "sg:address":"Ctra Villamarchante, 119",
    "sg:city":"Riba-roja Turia",
    "sg:orig_category":"Mec\u00c1nico Del Autom\u00d3vil",
    "sg:phone":"+34 961 65 22 28",
    "sg:postcode":"46190",
    "sg:province":"Valencia",
    "wof:name":"Sebriauto-2000 S.l.l.",
    "wof:placetype":"venue"
},
  "geometry": {"coordinates":[-0.5716459751,39.5446052551],"type":"Point"}
}