{
  "type": "Feature",
  "properties": {
    "iso:country":"ES",
    "sg:address":"Partida El Pontet, 1",
    "sg:city":"Altea",
    "sg:orig_category":"Comercio, Reparaci\u00d3n De Motocicletas, Bicicletas Y Piezas Sueltas",
    "sg:phone":"+34 965 84 25 56",
    "sg:postcode":"03590",
    "sg:province":"Alicante",
    "wof:name":"Guardiola Calafat Nicolas",
    "wof:placetype":"venue"
},
  "geometry": {"coordinates":[-0.0522690006,38.601108551],"type":"Point"}
}