{
  "type": "Feature",
  "properties": {
    "addr:full":"Carrer de Arnau D'oms, 33 Barcelona Barcelona 08016",
    "addr:housenumber":"33",
    "addr:postcode":"08016",
    "addr:street":"Carrer De;D'Oms",
    "iso:country":"ES",
    "sg:address":"Carrer de Arnau D'oms, 33",
    "sg:city":"Barcelona",
    "sg:orig_category":"Negocio De Materiales De Construcci\u00d3n",
    "sg:phone":"+34 934 08 36 89",
    "sg:postcode":"08016",
    "sg:province":"Barcelona",
    "wof:name":"Sucesores M Altes S.l.",
    "wof:placetype":"venue"
},
  "geometry": {"coordinates":[2.1773121357,41.4299964905],"type":"Point"}
}