{
  "type": "Feature",
  "properties": {
    "iso:country":"ES",
    "sg:address":"Carrer de Espronceda, 180",
    "sg:city":"Barcelona",
    "sg:orig_category":"Suministros Y Materiales Industriales",
    "sg:phone":"+34 933 08 29 90",
    "sg:postcode":"08018",
    "sg:province":"Barcelona",
    "wof:name":"Utiltall S.a.",
    "wof:placetype":"venue"
},
  "geometry": {"coordinates":[2.1991360188,41.4097175598],"type":"Point"}
}