{
  "type": "Feature",
  "properties": {
    "addr:full":"Carrer de Sardenya, 342 Barcelona Barcelona 08025",
    "addr:housenumber":"342",
    "addr:postcode":"08025",
    "addr:street":"Carrer De Sardenya",
    "iso:country":"ES",
    "sg:address":"Carrer de Sardenya, 342",
    "sg:city":"Barcelona",
    "sg:orig_category":"\u00d3ptica: Instrumentos (fabricaci\u00d3n)",
    "sg:phone":"+34 934 36 25 77",
    "sg:postcode":"08025",
    "sg:province":"Barcelona",
    "wof:name":"Caballero Brualla Antonia",
    "wof:placetype":"venue"
},
  "geometry": {"coordinates":[2.1719939709,41.4045791626],"type":"Point"}
}