{
  "type": "Feature",
  "properties": {
    "iso:country":"ES",
    "sg:address":"Pase Zumalakarregi Ibiltokia, 3",
    "sg:city":"Tolosa",
    "sg:orig_category":"Arquitectos",
    "sg:phone":"+34 943 65 46 56",
    "sg:postcode":"20400",
    "sg:province":"Guip\u00f9zcoa",
    "wof:name":"Labayen Celaya Jaime",
    "wof:placetype":"venue"
},
  "geometry": {"coordinates":[-2.0736289024,43.1361122131],"type":"Point"}
}