{
  "type": "Feature",
  "properties": {
    "iso:country":"ES",
    "sg:address":"Ctra Boadilla Del Monte, 46",
    "sg:city":"Madrid",
    "sg:orig_category":"Electromec\u00c1nica",
    "sg:phone":"+34 917 11 34 37",
    "sg:postcode":"28024",
    "sg:province":"Madrid",
    "wof:name":"Fluasa S. A.",
    "wof:placetype":"venue"
},
  "geometry": {"coordinates":[-3.7765541077,40.3993530273],"type":"Point"}
}