{
  "type": "Feature",
  "properties": {
    "iso:country":"ES",
    "sg:address":"Carr Rejolar, 4",
    "sg:city":"Lleida",
    "sg:orig_category":"Asociaciones Y Clubs Deportivos",
    "sg:phone":"+34 973 23 36 28",
    "sg:postcode":"25008",
    "sg:province":"Lleida",
    "wof:name":"Peralta Nicolas Jose",
    "wof:placetype":"venue"
},
  "geometry": {"coordinates":[0.6200590134,41.6217193604],"type":"Point"}
}