{
  "type": "Feature",
  "properties": {
    "addr:full":"Calle de San Juan De Dios, 4 Casas-iba\u00e7ez Albacete 02200",
    "addr:housenumber":"4",
    "addr:postcode":"02200",
    "addr:street":"Calle De San Juan;Dios",
    "iso:country":"ES",
    "sg:address":"Calle de San Juan De Dios, 4",
    "sg:city":"Casas-iba\u00e7ez",
    "sg:orig_category":"Alimentaci\u00d3n General (al Por Menor)",
    "sg:phone":"+34 967 46 09 35",
    "sg:postcode":"02200",
    "sg:province":"Albacete",
    "wof:name":"Martinez Perez Vicente",
    "wof:placetype":"venue"
},
  "geometry": {"coordinates":[-1.469966054,39.2841491699],"type":"Point"}
}