{
  "type": "Feature",
  "properties": {
    "addr:full":"Partida Cap-blanch, 81 Cap-blanch Alicante 03590",
    "addr:housenumber":"81",
    "addr:postcode":"03590",
    "addr:street":"Partida Cap-Blanch;Alicante",
    "iso:country":"ES",
    "sg:address":"Partida Cap-blanch, 81",
    "sg:city":"Cap-blanch",
    "sg:orig_category":"Urbanistas",
    "sg:phone":"+34 965 84 35 37",
    "sg:postcode":"03590",
    "sg:province":"Alicante",
    "wof:name":"Agrupacion De Interes Urbanistico Cap Blanc",
    "wof:placetype":"venue"
},
  "geometry": {"coordinates":[-0.4810059965,38.3452033997],"type":"Point"}
}