{
  "type": "Feature",
  "properties": {
    "iso:country":"ES",
    "sg:address":"Rua Ireira, 30",
    "sg:city":"Guarda",
    "sg:orig_category":"Venta, Instalaci\u00d3n De Calefacci\u00d3n",
    "sg:phone":"+34 986 61 43 88",
    "sg:postcode":"36780",
    "sg:province":"Pontevedra",
    "wof:name":"Castro Lomba Ramon",
    "wof:placetype":"venue"
},
  "geometry": {"coordinates":[-8.8730792999,41.901260376],"type":"Point"}
}