{
  "type": "Feature",
  "properties": {
    "addr:full":"Calle de Norte, 25 Valencia Valencia 46008",
    "addr:housenumber":"25",
    "addr:postcode":"46008",
    "addr:street":"Calle De Norte",
    "iso:country":"ES",
    "sg:address":"Calle de Norte, 25",
    "sg:city":"Valencia",
    "sg:orig_category":"Droguer\u00cdas (al Por Menor)",
    "sg:phone":"+34 963 82 03 29",
    "sg:postcode":"46008",
    "sg:province":"Valencia",
    "wof:name":"Aguilar Marti Vicente",
    "wof:placetype":"venue"
},
  "geometry": {"coordinates":[-0.391307801,39.4761161804],"type":"Point"}
}