{
  "type": "Feature",
  "properties": {
    "addr:full":"Calle de Santiago Bernabeu, 7 Madrid Madrid 28036",
    "addr:housenumber":"7",
    "addr:postcode":"madrid;28036",
    "addr:street":"Calle De Santiago Bernabeu",
    "iso:country":"ES",
    "sg:address":"Calle de Santiago Bernabeu, 7",
    "sg:city":"Madrid",
    "sg:orig_category":"Cajas De Ahorro",
    "sg:phone":"+34 914 11 08 51",
    "sg:postcode":"28036",
    "sg:province":"Madrid",
    "sg:website":"www.caixalaietana.es",
    "wof:name":"Caixa D'estalvis Laietana",
    "wof:placetype":"venue"
},
  "geometry": {"coordinates":[-3.6888968945,40.4503669739],"type":"Point"}
}