{
  "type": "Feature",
  "properties": {
    "addr:full":"Ctra Ronda, 27 Baza Granada 18800",
    "addr:housenumber":"27",
    "addr:postcode":"18800",
    "addr:street":"Ctra Ronda",
    "iso:country":"ES",
    "sg:address":"Ctra Ronda, 27",
    "sg:city":"Baza",
    "sg:orig_category":"Molduras, Junquillos, Listones Y Molduras Perforadas",
    "sg:phone":"+34 958 86 05 44",
    "sg:postcode":"18800",
    "sg:province":"Granada",
    "wof:name":"Fernandez Granero Clara",
    "wof:placetype":"venue"
},
  "geometry": {"coordinates":[-2.7787330151,37.4896774292],"type":"Point"}
}