{
  "type": "Feature",
  "properties": {
    "addr:full":"Calle de Real, 41 Lepe Huelva 21440",
    "addr:housenumber":"41",
    "addr:postcode":"21440",
    "addr:street":"Calle De Real",
    "iso:country":"ES",
    "sg:address":"Calle de Real, 41",
    "sg:city":"Lepe",
    "sg:orig_category":"Cl\u00cdnicas M\u00c9dicas",
    "sg:phone":"+34 959 38 33 71",
    "sg:postcode":"21440",
    "sg:province":"Huelva",
    "wof:name":"Contreras Rodriguez Manuel",
    "wof:placetype":"venue"
},
  "geometry": {"coordinates":[-7.2018442154,37.2560501099],"type":"Point"}
}