{
  "type": "Feature",
  "properties": {
    "addr:full":"Calle de Lealtad, 3 Santander Cantabria 39002",
    "addr:housenumber":"3",
    "addr:postcode":"39002",
    "addr:street":"Calle De Lealtad",
    "iso:country":"ES",
    "sg:address":"Calle de Lealtad, 3",
    "sg:city":"Santander",
    "sg:orig_category":"Bisuter\u00cda, Joyer\u00cda, Relojer\u00cda (al Por Menor)",
    "sg:phone":"+34 942 22 12 27",
    "sg:postcode":"39002",
    "sg:province":"Cantabria",
    "wof:name":"Hermosa Pariol Luis",
    "wof:placetype":"venue"
},
  "geometry": {"coordinates":[-3.8082180023,43.46251297],"type":"Point"}
}