{
  "type": "Feature",
  "properties": {
    "iso:country":"ES",
    "sg:address":"Calle de Baleares, 16",
    "sg:city":"Mostoles",
    "sg:orig_category":"Librer\u00cdas",
    "sg:phone":"+34 916 45 65 62",
    "sg:postcode":"28937",
    "sg:province":"Madrid",
    "wof:name":"Asesores Ense\u00f1anza A Distancia S.l.",
    "wof:placetype":"venue"
},
  "geometry": {"coordinates":[-3.8569300175,40.3254852295],"type":"Point"}
}