{
  "type": "Feature",
  "properties": {
    "addr:full":"Calle de Salvador Escandon, 14 Luanco Asturias 33440",
    "addr:housenumber":"14",
    "addr:postcode":"33440",
    "addr:street":"Calle De Salvador Escandon;Luanco Asturias",
    "iso:country":"ES",
    "sg:address":"Calle de Salvador Escandon, 14",
    "sg:city":"Luanco",
    "sg:orig_category":"Bisuter\u00cda, Joyer\u00cda, Relojer\u00cda (al Por Menor)",
    "sg:phone":"+34 985 88 14 95",
    "sg:postcode":"33440",
    "sg:province":"Asturias",
    "wof:name":"Pantiga Fernandez Faustino",
    "wof:placetype":"venue"
},
  "geometry": {"coordinates":[-5.7915887833,43.6161613464],"type":"Point"}
}