{
  "type": "Feature",
  "properties": {
    "addr:full":"Carrer de Madrazo, 97 Barcelona Barcelona 08006",
    "addr:housenumber":"97",
    "addr:postcode":"08006",
    "addr:street":"Carrer De Madrazo",
    "iso:country":"ES",
    "sg:address":"Carrer de Madrazo, 97",
    "sg:city":"Barcelona",
    "sg:orig_category":"Carnicer\u00cdas, Carnicer\u00cdas",
    "sg:phone":"+34 932 09 45 62",
    "sg:postcode":"08006",
    "sg:province":"Barcelona",
    "wof:name":"Rabasseda Pardo Avelina",
    "wof:placetype":"venue"
},
  "geometry": {"coordinates":[2.1471869946,41.398639679],"type":"Point"}
}