{
  "type": "Feature",
  "properties": {
    "addr:full":"Calle de Arroyada, 44 Sonseca Toledo 45100",
    "addr:housenumber":"44",
    "addr:postcode":"45100",
    "addr:street":"Calle De Arroyada",
    "iso:country":"ES",
    "sg:address":"Calle de Arroyada, 44",
    "sg:city":"Sonseca",
    "sg:orig_category":"Abogados",
    "sg:phone":"+34 925 38 34 10",
    "sg:postcode":"45100",
    "sg:province":"Toledo",
    "wof:name":"Martin Martin-maestro Sagrario",
    "wof:placetype":"venue"
},
  "geometry": {"coordinates":[-3.9731535912,39.6777420044],"type":"Point"}
}