{
  "type": "Feature",
  "properties": {
    "addr:full":"Av Caldero, 5 Mollet Valles Barcelona 08100",
    "addr:housenumber":"5",
    "addr:postcode":"08100",
    "addr:street":"Av Caldero",
    "iso:country":"ES",
    "sg:address":"Av Caldero, 5",
    "sg:city":"Mollet Valles",
    "sg:orig_category":"Caf\u00c9s, Bares, Cervecer\u00cdas",
    "sg:phone":"+34 935 79 29 61",
    "sg:postcode":"08100",
    "sg:province":"Barcelona",
    "wof:name":"Mollet Business S.l",
    "wof:placetype":"venue"
},
  "geometry": {"coordinates":[2.2137761116,41.5366821289],"type":"Point"}
}