{
  "type": "Feature",
  "properties": {
    "addr:full":"Mercaderes, 6 Iru\u00f1a Navarra 31001",
    "addr:housenumber":"6",
    "addr:postcode":"31001",
    "addr:street":"Mercaderes",
    "iso:country":"ES",
    "sg:address":"Mercaderes, 6",
    "sg:city":"Iru\u00f1a",
    "sg:orig_category":"Cajas Para Embalar",
    "sg:phone":"+34 948 20 40 80",
    "sg:postcode":"31001",
    "sg:province":"Navarra",
    "wof:name":"Caja Rural Provincial De Navarra",
    "wof:placetype":"venue"
},
  "geometry": {"coordinates":[-1.6432050467,42.8182487488],"type":"Point"}
}