{
  "type": "Feature",
  "properties": {
    "iso:country":"ES",
    "sg:address":"Calle de Torrelaguna, 70",
    "sg:city":"Madrid",
    "sg:orig_category":"Frutas, Legumbres Frescas Y Tempranas (al Por Menor)",
    "sg:phone":"+34 914 15 81 03",
    "sg:postcode":"28043",
    "sg:province":"Madrid",
    "wof:name":"Gonzalez Maquedano Juan Antonio",
    "wof:placetype":"venue"
},
  "geometry": {"coordinates":[-3.6575920582,40.4494361877],"type":"Point"}
}