{
  "type": "Feature",
  "properties": {
    "iso:country":"ES",
    "sg:address":"Carrer de Santa Teresa, 19",
    "sg:city":"Mataro",
    "sg:orig_category":"Pr\u00c9stamos Personales E Hipotecarios",
    "sg:phone":"+34 937 96 24 00",
    "sg:postcode":"08302",
    "sg:province":"Barcelona",
    "wof:name":"Va Aguaviva Mariano",
    "wof:placetype":"venue"
},
  "geometry": {"coordinates":[2.4435279369,41.5384254456],"type":"Point"}
}