{
  "type": "Feature",
  "properties": {
    "addr:full":"Calle de Seixo, 16 Cangas Pontevedra 36940",
    "addr:housenumber":"16",
    "addr:postcode":"36940",
    "addr:street":"Calle De Seixo",
    "iso:country":"ES",
    "sg:address":"Calle de Seixo, 16",
    "sg:city":"Cangas",
    "sg:orig_category":"Transportes Por Carretera: Lotes Completos, Mercanc\u00cdas Diversas",
    "sg:phone":"+34 986 30 29 45",
    "sg:postcode":"36940",
    "sg:province":"Pontevedra",
    "wof:name":"Mercash-sar S.l.",
    "wof:placetype":"venue"
},
  "geometry": {"coordinates":[-8.8040046692,42.2660064697],"type":"Point"}
}