{
  "type": "Feature",
  "properties": {
    "iso:country":"ES",
    "sg:address":"Carrer de Ibi, 2",
    "sg:city":"Algars",
    "sg:orig_category":"Engranajes Y Elementos De Transmisi\u00d3n",
    "sg:phone":"+34 966 50 02 23",
    "sg:postcode":"03820",
    "sg:province":"Alicante",
    "wof:name":"Engranajes Masia S.l.",
    "wof:placetype":"venue"
},
  "geometry": {"coordinates":[-0.4387629926,38.7515029907],"type":"Point"}
}