{
  "type": "Feature",
  "properties": {
    "iso:country":"ES",
    "sg:address":"Carretera, 83",
    "sg:city":"S. Andreu Barca",
    "sg:orig_category":"Centros Empresariales",
    "sg:phone":"+34 936 82 10 43",
    "sg:postcode":"08740",
    "sg:province":"Barcelona",
    "sg:website":"www.7itria.com",
    "wof:name":"7 I Tria S.a.l.",
    "wof:placetype":"venue"
},
  "geometry": {"coordinates":[2.186116,41.434624],"type":"Point"}
}