{
  "type": "Feature",
  "properties": {
    "iso:country":"ES",
    "sg:address":"Av. Valdepastores, 7",
    "sg:city":"Valdepastores",
    "sg:orig_category":"El Hogar: Amueblado, Acondicionamiento, Decoraci\u00d3n Y Mantenimiento",
    "sg:phone":"+34 916 33 48 34",
    "sg:postcode":"28660",
    "sg:province":"Madrid",
    "wof:name":"Martin Martin Olga",
    "wof:placetype":"venue"
},
  "geometry": {"coordinates":[-3.8836228848,40.4217224121],"type":"Point"}
}