{
  "type": "Feature",
  "properties": {
    "addr:full":"Muel Santa Catalina, S/n Palmas De Gran Canaria Las Palmas 35008",
    "addr:housenumber":"s",
    "addr:postcode":"35008",
    "addr:street":"Santa Catalina;/ N",
    "iso:country":"ES",
    "sg:address":"Muel Santa Catalina, S/n",
    "sg:city":"Palmas De Gran Canaria",
    "sg:orig_category":"Ropa Para Se\u00d1oras Y Caballeros (al Por Menor)",
    "sg:phone":"+34 928 22 07 07",
    "sg:postcode":"35008",
    "sg:province":"Las Palmas",
    "sg:website":"www.womensecret.com",
    "wof:name":"Cortefiel S.a.",
    "wof:placetype":"venue"
},
  "geometry": {"coordinates":[-15.4279222488,28.1409034729],"type":"Point"}
}