{
  "type": "Feature",
  "properties": {
    "addr:full":"Carrer de Pintor Sorolla, 1 Terrassa Barcelona 08224",
    "addr:housenumber":"1",
    "addr:postcode":"08224",
    "addr:street":"Carrer De Pintor Sorolla",
    "iso:country":"ES",
    "sg:address":"Carrer de Pintor Sorolla, 1",
    "sg:city":"Terrassa",
    "sg:orig_category":"Molduras, Junquillos, Listones Y Molduras Perforadas",
    "sg:phone":"+34 937 88 12 04",
    "sg:postcode":"08224",
    "sg:province":"Barcelona",
    "wof:name":"Alba Padilla Juan",
    "wof:placetype":"venue"
},
  "geometry": {"coordinates":[2.0027258396,41.5529022217],"type":"Point"}
}