{
  "type": "Feature",
  "properties": {
    "iso:country":"ES",
    "sg:address":"Tejeras, 11",
    "sg:city":"Argamasilla Alba",
    "sg:orig_category":"Asociaciones Ecologistas",
    "sg:phone":"+34 926 52 11 01",
    "sg:postcode":"13710",
    "sg:province":"Ciudad Real",
    "wof:name":"Comunidad De Regantes Del Pantano Del Estrecho De Pe\u00f1arroya",
    "wof:placetype":"venue"
},
  "geometry": {"coordinates":[-3.0932850838,39.129283905],"type":"Point"}
}