{
  "type": "Feature",
  "properties": {
    "iso:country":"ES",
    "sg:address":"Calle de Bego\u00d1a, 16",
    "sg:city":"Coslada",
    "sg:orig_category":"Administradores De Bienes Y Delegados De Comunidades De Propietarios",
    "sg:phone":"+34 916 72 76 93",
    "sg:postcode":"28820",
    "sg:province":"Madrid",
    "wof:name":"Perez Mu\u00f1oz Jose Roman",
    "wof:placetype":"venue"
},
  "geometry": {"coordinates":[-3.5679726601,40.4256286621],"type":"Point"}
}