{
  "type": "Feature",
  "properties": {
    "iso:country":"ES",
    "sg:address":"Avda Monforte De Lemos, 135",
    "sg:city":"Madrid",
    "sg:orig_category":"Fabricaci\u00d3n De Sobres, Bolsas Y Fundas",
    "sg:phone":"+34 917 30 03 64",
    "sg:postcode":"28029",
    "sg:province":"Madrid",
    "wof:name":"Gil Gomez Francisco",
    "wof:placetype":"venue"
},
  "geometry": {"coordinates":[-3.7121450901,40.4775848389],"type":"Point"}
}