{
  "type": "Feature",
  "properties": {
    "addr:full":"Calle de Circunvalacion, 6 Torrejon Ardoz Madrid 28850",
    "addr:housenumber":"6",
    "addr:postcode":"28850",
    "addr:street":"Calle De Circunvalacion",
    "iso:country":"ES",
    "sg:address":"Calle de Circunvalacion, 6",
    "sg:city":"Torrejon Ardoz",
    "sg:orig_category":"Electricidad, Electr\u00d3nica: Suministros (al Por Menor)",
    "sg:phone":"+34 916 76 22 20",
    "sg:postcode":"28850",
    "sg:province":"Madrid",
    "wof:name":"Mdr Mantenimiento De Redes S.l.",
    "wof:placetype":"venue"
},
  "geometry": {"coordinates":[-3.4591083527,40.4517784119],"type":"Point"}
}