{
  "type": "Feature",
  "properties": {
    "iso:country":"ES",
    "sg:address":"Llevant, S/n",
    "sg:city":"Vilablareix",
    "sg:orig_category":"Mec\u00c1nico Del Autom\u00d3vil",
    "sg:phone":"+34 972 23 46 98",
    "sg:postcode":"17180",
    "sg:province":"Girona",
    "wof:name":"Collsaplana Motor S.l.",
    "wof:placetype":"venue"
},
  "geometry": {"coordinates":[2.8018500805,41.9523658752],"type":"Point"}
}