{
  "type": "Feature",
  "properties": {
    "iso:country":"ES",
    "sg:address":"Riera (la), 4",
    "sg:city":"Mataro",
    "sg:orig_category":"Organismos De Reclutamiento",
    "sg:phone":"+34 937 90 66 33",
    "sg:postcode":"08301",
    "sg:province":"Barcelona",
    "sg:website":"www.6tma.com",
    "wof:name":"Marti Mora Jaume",
    "wof:placetype":"venue"
},
  "geometry": {"coordinates":[2.4439051151,41.5415153503],"type":"Point"}
}