{
  "type": "Feature",
  "properties": {
    "addr:full":"Plaz Santa Ana, 3 Avila \u00c1vila 05001",
    "addr:housenumber":"3",
    "addr:postcode":"05001",
    "addr:street":"Santa Ana;A\u0301Vila",
    "iso:country":"ES",
    "sg:address":"Plaz Santa Ana, 3",
    "sg:city":"Avila",
    "sg:orig_category":"Agencias De Viajes",
    "sg:phone":"+34 920 25 59 13",
    "sg:postcode":"05001",
    "sg:province":"\u00c1vila",
    "sg:website":"www.marsans.es",
    "wof:name":"Viajes Marsans S.a.",
    "wof:placetype":"venue"
},
  "geometry": {"coordinates":[-4.7072339058,40.6581344604],"type":"Point"}
}