{
  "type": "Feature",
  "properties": {
    "addr:full":"Calle de Obispo Romo, 16 Palmas De Gran Canaria Las Palmas 35011",
    "addr:postcode":"35011",
    "addr:street":"Calle De Obispo Romo 16",
    "iso:country":"ES",
    "sg:address":"Calle de Obispo Romo, 16",
    "sg:city":"Palmas De Gran Canaria",
    "sg:orig_category":"Fisioterapia",
    "sg:phone":"+34 928 25 40 82",
    "sg:postcode":"35011",
    "sg:province":"Las Palmas",
    "wof:name":"Lopez Viera Bartolome",
    "wof:placetype":"venue"
},
  "geometry": {"coordinates":[-15.4353981018,28.1150627136],"type":"Point"}
}