{
  "type": "Feature",
  "properties": {
    "iso:country":"ES",
    "sg:address":"Calle de Blas Infante, 2",
    "sg:city":"Ubeda",
    "sg:orig_category":"Mec\u00c1nico Del Autom\u00d3vil",
    "sg:phone":"+34 953 75 26 41",
    "sg:postcode":"23400",
    "sg:province":"Ja\u00e9n",
    "wof:name":"Rodriguez Olmedo Jose",
    "wof:placetype":"venue"
},
  "geometry": {"coordinates":[-3.3784732819,38.0158729553],"type":"Point"}
}