{
  "type": "Feature",
  "properties": {
    "iso:country":"ES",
    "sg:address":"Avda Espa\u00d1a (de), S/n",
    "sg:city":"Dos Hermanas",
    "sg:orig_category":"Seguridad Social",
    "sg:phone":"+34 955 67 61 72",
    "sg:postcode":"41700",
    "sg:province":"Sevilla",
    "sg:website":"www.fremap.es",
    "wof:name":"Fremap - Mutua De Accidentes De Trabajo Y Enfermedades",
    "wof:placetype":"venue"
},
  "geometry": {"coordinates":[-5.9342660904,37.2805404663],"type":"Point"}
}