{
  "type": "Feature",
  "properties": {
    "iso:country":"ES",
    "sg:address":"Carr Amadeu Vives, 12",
    "sg:city":"Palau D'anglesola",
    "sg:orig_category":"Chapister\u00cda",
    "sg:phone":"+34 973 71 28 47",
    "sg:postcode":"25243",
    "sg:province":"Lleida",
    "wof:name":"Longo Lo Salvatore",
    "wof:placetype":"venue"
},
  "geometry": {"coordinates":[1.0851399899,41.6593704224],"type":"Point"}
}