{
  "type": "Feature",
  "properties": {
    "addr:full":"Mas Rodonella, S/n S. Joan Abadesses Girona 17860",
    "addr:housenumber":"s",
    "addr:postcode":"17860",
    "addr:street":"/ N S. Joan Abadesses",
    "iso:country":"ES",
    "sg:address":"Mas Rodonella, S/n",
    "sg:city":"S. Joan Abadesses",
    "sg:orig_category":"Cr\u00cda De Cerdos",
    "sg:phone":"+34 972 72 03 23",
    "sg:postcode":"17860",
    "sg:province":"Girona",
    "wof:name":"La Rodonella S.l.",
    "wof:placetype":"venue"
},
  "geometry": {"coordinates":[2.2854809761,42.2338752747],"type":"Point"}
}