{
  "type": "Feature",
  "properties": {
    "iso:country":"ES",
    "sg:address":"Calle de Papa Juan Xxiii, 1",
    "sg:city":"Pobla Farnals",
    "sg:orig_category":"Mataderos Y Talleres De Despiezado",
    "sg:phone":"+34 961 44 08 86",
    "sg:postcode":"46139",
    "sg:province":"Valencia",
    "wof:name":"Carnicas Teva S.l.",
    "wof:placetype":"venue"
},
  "geometry": {"coordinates":[-0.3301270008,39.5791473389],"type":"Point"}
}