{
  "type": "Feature",
  "properties": {
    "iso:country":"ES",
    "sg:address":"Plaz Torres Quevedo, 149",
    "sg:city":"Puerto",
    "sg:orig_category":"Autob\u00das (explotaci\u00d3n Y Servicios De)",
    "sg:phone":"+34 962 65 14 49",
    "sg:postcode":"46520",
    "sg:province":"Valencia",
    "sg:website":"www.vmarques.servit.com",
    "wof:name":"Viajes Marques S.l.",
    "wof:placetype":"venue"
},
  "geometry": {"coordinates":[-0.2025949955,39.7040786743],"type":"Point"}
}