{
  "type": "Feature",
  "properties": {
    "iso:country":"ES",
    "sg:address":"Avda Pedro Lain Entralgo, 5",
    "sg:city":"Urrea Gaen",
    "sg:orig_category":"Cervezas, Bebidas (al Por Mayor)",
    "sg:phone":"+34 978 82 17 13",
    "sg:postcode":"44593",
    "sg:province":"Teruel",
    "wof:name":"Sobradiel Meseguer Miguel Angel",
    "wof:placetype":"venue"
},
  "geometry": {"coordinates":[-0.4697889984,41.1614151001],"type":"Point"}
}