{
  "type": "Feature",
  "properties": {
    "addr:full":"Calle de Aguirre Maximo, 24 Bilbao Vizcaya 48011",
    "addr:housenumber":"24",
    "addr:postcode":"48011",
    "addr:street":"Calle De Aguirre Maximo",
    "iso:country":"ES",
    "sg:address":"Calle de Aguirre Maximo, 24",
    "sg:city":"Bilbao",
    "sg:orig_category":"Muebles, Minoristas",
    "sg:phone":"+34 944 42 19 62",
    "sg:postcode":"48011",
    "sg:province":"Vizcaya",
    "wof:name":"Villate Aguirre Ana Maria",
    "wof:placetype":"venue"
},
  "geometry": {"coordinates":[-2.9384160042,43.2623977661],"type":"Point"}
}