{
  "type": "Feature",
  "properties": {
    "addr:full":"Av Isabel Cat\u00f3lica, 18 Vilavella Castell\u00f3n 12526",
    "addr:housenumber":"18",
    "addr:postcode":"12526",
    "addr:street":"Av Isabel Cato\u0301Lica;Castello\u0301N",
    "iso:country":"ES",
    "sg:address":"Av Isabel Cat\u00f3lica, 18",
    "sg:city":"Vilavella",
    "sg:orig_category":"Panader\u00cdas, Panader\u00cdas",
    "sg:phone":"+34 964 67 79 44",
    "sg:postcode":"12526",
    "sg:province":"Castell\u00f3n",
    "wof:name":"Vicent Flors Maestros Artesanos S.l.",
    "wof:placetype":"venue"
},
  "geometry": {"coordinates":[-0.1819770038,39.8587112427],"type":"Point"}
}