{
  "type": "Feature",
  "properties": {
    "iso:country":"ES",
    "sg:address":"Calle de Magdalena, 15",
    "sg:city":"Rafelbunyol",
    "sg:orig_category":"Promotores Constructores",
    "sg:phone":"+34 961 41 01 05",
    "sg:postcode":"46138",
    "sg:province":"Valencia",
    "wof:name":"Hijos De Rafael Garrido Construcciones S.l.",
    "wof:placetype":"venue"
},
  "geometry": {"coordinates":[-0.3352200091,39.5886535645],"type":"Point"}
}