{
  "type": "Feature",
  "properties": {
    "iso:country":"ES",
    "sg:address":"Calle de Mesonero Mayor, 16",
    "sg:city":"Coca",
    "sg:orig_category":"Supermercados Y Hipermercados",
    "sg:phone":"+34 921 58 61 79",
    "sg:postcode":"40480",
    "sg:province":"Segovia",
    "wof:name":"Supermercados La Salve S.l.",
    "wof:placetype":"venue"
},
  "geometry": {"coordinates":[-4.5202651024,41.218170166],"type":"Point"}
}