{
  "type": "Feature",
  "properties": {
    "iso:country":"ES",
    "sg:address":"Calle de Ancha De Gracia, 3",
    "sg:city":"Granada",
    "sg:orig_category":"Abogados",
    "sg:phone":"+34 958 25 09 92",
    "sg:postcode":"18002",
    "sg:province":"Granada",
    "wof:name":"Sanchez Angulo Emilio",
    "wof:placetype":"venue"
},
  "geometry": {"coordinates":[-3.6048402786,37.1722640991],"type":"Point"}
}