{
  "type": "Feature",
  "properties": {
    "addr:full":"Ilekueta Karrika, 11 Bera Navarra 31780",
    "addr:housenumber":"11",
    "addr:postcode":"31780",
    "addr:street":"Ilekueta Karrika",
    "iso:country":"ES",
    "sg:address":"Ilekueta Karrika, 11",
    "sg:city":"Bera",
    "sg:orig_category":"Restaurantes",
    "sg:phone":"+34 948 63 15 84",
    "sg:postcode":"31780",
    "sg:province":"Navarra",
    "wof:name":"Restaurante Auzoa S.i.",
    "wof:placetype":"venue"
},
  "geometry": {"coordinates":[-1.6759799719,43.2814788818],"type":"Point"}
}