{
  "type": "Feature",
  "properties": {
    "addr:full":"Rua Dous De Maio, 24 Xinzo De Limia Ourense 32630",
    "addr:housenumber":"24",
    "addr:postcode":"32630",
    "addr:street":"Rua Dous;Maio",
    "iso:country":"ES",
    "sg:address":"Rua Dous De Maio, 24",
    "sg:city":"Xinzo De Limia",
    "sg:orig_category":"Fabricaci\u00d3n De Telas Y Sedas",
    "sg:phone":"+34 988 46 15 34",
    "sg:postcode":"32630",
    "sg:province":"Ourense",
    "wof:name":"Fernandez Rodriguez Augusto",
    "wof:placetype":"venue"
},
  "geometry": {"coordinates":[-7.7253708839,42.0626983643],"type":"Point"}
}