{
  "type": "Feature",
  "properties": {
    "iso:country":"ES",
    "sg:address":"Mur, 58",
    "sg:city":"Almenara",
    "sg:orig_category":"Agencias Y Agentes Comerciales, Representantes",
    "sg:phone":"+34 962 62 30 71",
    "sg:postcode":"12590",
    "sg:province":"Castell\u00f3n",
    "wof:name":"Valero Orero Angel",
    "wof:placetype":"venue"
},
  "geometry": {"coordinates":[-0.2262379974,39.7544250488],"type":"Point"}
}