{
  "type": "Feature",
  "properties": {
    "addr:full":"Avda Prudencio Gonzalez, 40 Posada Asturias 33424",
    "addr:housenumber":"40",
    "addr:postcode":"33424",
    "addr:street":"Avda Prudencio Gonzalez",
    "iso:country":"ES",
    "sg:address":"Avda Prudencio Gonzalez, 40",
    "sg:city":"Posada",
    "sg:orig_category":"Mercer\u00cda, Lencer\u00cda (al Por Menor)",
    "sg:phone":"+34 985 77 03 35",
    "sg:postcode":"33424",
    "sg:province":"Asturias",
    "wof:name":"Fernandez Garcia Maria Gloria",
    "wof:placetype":"venue"
},
  "geometry": {"coordinates":[-5.8532037735,43.4415092468],"type":"Point"}
}