{
  "type": "Feature",
  "properties": {
    "addr:full":"Ctra Valderas, 15 Valencia De Don Juan Le\u00f3n 24200",
    "addr:housenumber":"15",
    "addr:postcode":"24200",
    "addr:street":"Ctra Valderas",
    "iso:country":"ES",
    "sg:address":"Ctra Valderas, 15",
    "sg:city":"Valencia De Don Juan",
    "sg:orig_category":"Centros De Educaci\u00d3n Especial",
    "sg:phone":"+34 987 75 03 67",
    "sg:postcode":"24200",
    "sg:province":"Le\u00f3n",
    "wof:name":"Colegio Publico Comarcal Bernardino Perez",
    "wof:placetype":"venue"
},
  "geometry": {"coordinates":[-5.5147738457,42.293170929],"type":"Point"}
}