{
  "type": "Feature",
  "properties": {
    "iso:country":"ES",
    "sg:address":"Trebol, 1",
    "sg:city":"Rivas Vaciamadrid",
    "sg:orig_category":"Inform\u00c1tica Equipo Y Programas (al Por Mayor)",
    "sg:phone":"+34 916 66 83 58",
    "sg:postcode":"28529",
    "sg:province":"Madrid",
    "sg:website":"www.jcrinfoimagen.com",
    "wof:name":"Perez Sanchez Ana Maria",
    "wof:placetype":"venue"
},
  "geometry": {"coordinates":[-3.5240080357,40.3563766479],"type":"Point"}
}