{
  "type": "Feature",
  "properties": {
    "iso:country":"ES",
    "sg:address":"Calle de Independencia, 52",
    "sg:city":"Benalup",
    "sg:orig_category":"Estudios, Instalaci\u00d3n De Climatizaci\u00d3n",
    "sg:phone":"+34 956 41 78 46",
    "sg:postcode":"11190",
    "sg:province":"C\u00e1diz",
    "wof:name":"Climatizaciones Y Electricidad Guerrero S.l.",
    "wof:placetype":"venue"
},
  "geometry": {"coordinates":[-5.8128499985,36.3423538208],"type":"Point"}
}