{
  "type": "Feature",
  "properties": {
    "iso:country":"ES",
    "sg:address":"Avda Pureza Canelo, 45",
    "sg:city":"Moraleja",
    "sg:classifiers":[
        {
            "category":"Communications",
            "type":"Services"
        }
    ],
    "sg:phone":"+34 927 51 60 60",
    "sg:postcode":"10840",
    "sg:province":"C\u00e1ceres",
    "sg:tags":[
        "televisiones",
        "y",
        "radio"
    ],
    "wof:name":"Radio Interior S.l",
    "wof:placetype":"venue"
},
  "geometry": {"coordinates":[-6.6566281319,40.0693740845],"type":"Point"}
}