{
  "type": "Feature",
  "properties": {
    "addr:full":"Avda Coru\u00d1a, 2 Meicende La Coru\u00f1a 15140",
    "addr:housenumber":"2",
    "addr:postcode":"15140",
    "addr:street":"Avda Corun\u0303A;La Corun\u0303A",
    "iso:country":"ES",
    "sg:address":"Avda Coru\u00d1a, 2",
    "sg:city":"Meicende",
    "sg:orig_category":"Molduras, Junquillos, Listones Y Molduras Perforadas",
    "sg:phone":"+34 981 28 00 84",
    "sg:postcode":"15140",
    "sg:province":"La Coru\u00f1a",
    "wof:name":"Rivero Souto Maria Del Carmen",
    "wof:placetype":"venue"
},
  "geometry": {"coordinates":[-8.46671772,43.3288497925],"type":"Point"}
}