{
  "type": "Feature",
  "properties": {
    "addr:full":"Calle de Portillo De Balboa, 40 Valladolid Valladolid 47010",
    "addr:housenumber":"40",
    "addr:postcode":"47010",
    "addr:street":"Calle De Portillo De Balboa",
    "iso:country":"ES",
    "sg:address":"Calle de Portillo De Balboa, 40",
    "sg:city":"Valladolid",
    "sg:orig_category":"Cl\u00cdnicas Dentales",
    "sg:phone":"+34 983 26 20 03",
    "sg:postcode":"47010",
    "sg:province":"Valladolid",
    "wof:name":"Ordo\u00f1ez Sanchez Antonio",
    "wof:placetype":"venue"
},
  "geometry": {"coordinates":[-4.7193179131,41.661945343],"type":"Point"}
}