{
  "type": "Feature",
  "properties": {
    "iso:country":"ES",
    "sg:address":"Carr Torres I Jonama, 83",
    "sg:city":"Palafrugell",
    "sg:orig_category":"Ingenier\u00cda, Centros De Estudios (diversos)",
    "sg:phone":"+34 972 30 15 33",
    "sg:postcode":"17200",
    "sg:province":"Girona",
    "wof:name":"Medis Enginyeria Ambiental I Agroindustrial S.l.",
    "wof:placetype":"venue"
},
  "geometry": {"coordinates":[3.1588039398,41.9182357788],"type":"Point"}
}