{
  "type": "Feature",
  "properties": {
    "iso:country":"ES",
    "sg:address":"Calle de Puerto, 14",
    "sg:city":"Malaga",
    "sg:orig_category":"Promotores Constructores",
    "sg:phone":"+34 952 22 60 00",
    "sg:postcode":"29016",
    "sg:province":"M\u00e1laga",
    "wof:name":"Obras Caminos Y Redes S.a.",
    "wof:placetype":"venue"
},
  "geometry": {"coordinates":[-4.4082698822,36.7200317383],"type":"Point"}
}