{
  "type": "Feature",
  "properties": {
    "addr:full":"Plaz San Pedro, 4 San Pedro Murcia 30004",
    "addr:housenumber":"4",
    "addr:postcode":"30004",
    "addr:street":"Plaz San Pedro",
    "iso:country":"ES",
    "sg:address":"Plaz San Pedro, 4",
    "sg:city":"San Pedro",
    "sg:orig_category":"Art\u00cdculos De Regalo (al Por Menor)",
    "sg:phone":"+34 968 22 16 10",
    "sg:postcode":"30004",
    "sg:province":"Murcia",
    "wof:name":"Sanchez Lopez Juan Ramon",
    "wof:placetype":"venue"
},
  "geometry": {"coordinates":[-1.1302499771,37.9829597473],"type":"Point"}
}