{
  "type": "Feature",
  "properties": {
    "iso:country":"ES",
    "sg:address":"Avda Valladolid, 6",
    "sg:city":"Cigales",
    "sg:orig_category":"Molduras, Junquillos, Listones Y Molduras Perforadas",
    "sg:phone":"+34 983 58 68 67",
    "sg:postcode":"47270",
    "sg:province":"Valladolid",
    "wof:name":"Dominguez Vallejo Jose Carlos",
    "wof:placetype":"venue"
},
  "geometry": {"coordinates":[-4.6987919807,41.7558784485],"type":"Point"}
}