{
  "type": "Feature",
  "properties": {
    "addr:full":"Ctra Cadiz (de), Km. 0042,8 Aranjuez Madrid 28300",
    "addr:postcode":"28300",
    "addr:street":"Ctra Cadiz De Km. 0042,8",
    "iso:country":"ES",
    "sg:address":"Ctra Cadiz (de), Km. 0042,8",
    "sg:city":"Aranjuez",
    "sg:orig_category":"Promotores Constructores",
    "sg:phone":"+34 918 92 04 33",
    "sg:postcode":"28300",
    "sg:province":"Madrid",
    "sg:website":"www.fadesa.es",
    "wof:name":"Fadesa Inmobiliaria S.a.",
    "wof:placetype":"venue"
},
  "geometry": {"coordinates":[-3.6042790413,40.0360946655],"type":"Point"}
}