{
  "type": "Feature",
  "properties": {
    "addr:full":"Plaz Espa\u00d1a, 2 Miranda Ebro Burgos 09200",
    "addr:housenumber":"2",
    "addr:postcode":"09200",
    "addr:street":"Plaz Espan\u0303A",
    "iso:country":"ES",
    "sg:address":"Plaz Espa\u00d1a, 2",
    "sg:city":"Miranda Ebro",
    "sg:orig_category":"Cajas De Ahorro",
    "sg:phone":"+34 947 32 12 01",
    "sg:postcode":"09200",
    "sg:province":"Burgos",
    "sg:website":"www.cajacirculo.es",
    "wof:name":"Caja De Ahorros Del Circulo Catolico Obrero De Burgos",
    "wof:placetype":"venue"
},
  "geometry": {"coordinates":[-2.9524741173,42.6833839417],"type":"Point"}
}