{
  "type": "Feature",
  "properties": {
    "iso:country":"ES",
    "sg:address":"Calle de Beaterio Del Santisimo, S/n",
    "sg:city":"Granada",
    "sg:orig_category":"Agencias De Trabajo Temporal",
    "sg:phone":"+34 958 28 65 19",
    "sg:postcode":"18001",
    "sg:province":"Granada",
    "wof:name":"Arca-emplered Ara\u00f1a Tejido Entidades Sociales Por El Empleo",
    "wof:placetype":"venue"
},
  "geometry": {"coordinates":[-3.6011230946,37.1820335388],"type":"Point"}
}