{
  "type": "Feature",
  "properties": {
    "addr:full":"Calle de Canalejas, 7 Villacarrillo Ja\u00e9n 23300",
    "addr:housenumber":"7",
    "addr:postcode":"23300",
    "addr:street":"Calle De Canalejas;Jae\u0301N",
    "iso:country":"ES",
    "sg:address":"Calle de Canalejas, 7",
    "sg:city":"Villacarrillo",
    "sg:orig_category":"Florister\u00cdas",
    "sg:phone":"+34 953 44 23 31",
    "sg:postcode":"23300",
    "sg:province":"Ja\u00e9n",
    "wof:name":"Fernandez Secadoras Hermanos C.b.",
    "wof:placetype":"venue"
},
  "geometry": {"coordinates":[-3.0818927288,38.1164894104],"type":"Point"}
}