{
  "type": "Feature",
  "properties": {
    "iso:country":"ES",
    "sg:address":"Rua Republica Argentina, 18",
    "sg:city":"Silleda",
    "sg:orig_category":"Muebles Y Accesorios Para Cocinas Y Cuartos De Ba\u00d1o (al Por Menor)",
    "sg:phone":"+34 986 58 14 59",
    "sg:postcode":"36540",
    "sg:province":"Pontevedra",
    "wof:name":"Muebles F-ii Silleda S.l.",
    "wof:placetype":"venue"
},
  "geometry": {"coordinates":[-8.246679306,42.6987495422],"type":"Point"}
}