{
  "type": "Feature",
  "properties": {
    "iso:country":"ES",
    "sg:address":"Calle de Piscis, 62",
    "sg:city":"Zaragoza",
    "sg:orig_category":"Asociaciones Y Clubs Deportivos",
    "sg:phone":"+34 976 75 20 43",
    "sg:postcode":"50012",
    "sg:province":"Zaragoza",
    "wof:name":"Algaba Murillo Nemesio",
    "wof:placetype":"venue"
},
  "geometry": {"coordinates":[-0.9336915016,41.6373710632],"type":"Point"}
}