{
  "type": "Feature",
  "properties": {
    "addr:full":"Av Paisos Catalans, 82 Vic Barcelona 08500",
    "addr:housenumber":"82",
    "addr:postcode":"08500",
    "addr:street":"Av Paisos Catalans",
    "iso:country":"ES",
    "sg:address":"Av Paisos Catalans, 82",
    "sg:city":"Vic",
    "sg:orig_category":"Molduras, Junquillos, Listones Y Molduras Perforadas",
    "sg:phone":"+34 938 85 47 66",
    "sg:postcode":"08500",
    "sg:province":"Barcelona",
    "wof:name":"Germans Riera Vallverdu S.c.p.",
    "wof:placetype":"venue"
},
  "geometry": {"coordinates":[2.25831604,41.9198684692],"type":"Point"}
}