{
  "type": "Feature",
  "properties": {
    "addr:full":"Ptge Irlanda, 16 Santa Coloma De Gramenet Barcelona 08922",
    "addr:housenumber":"16",
    "addr:postcode":"08922",
    "addr:street":"Ptge Irlanda",
    "iso:country":"ES",
    "sg:address":"Ptge Irlanda, 16",
    "sg:city":"Santa Coloma De Gramenet",
    "sg:orig_category":"Zapatos (al Por Menor)",
    "sg:phone":"+34 933 92 44 03",
    "sg:postcode":"08922",
    "sg:province":"Barcelona",
    "wof:name":"Borrell Bosque Agustin",
    "wof:placetype":"venue"
},
  "geometry": {"coordinates":[2.2137401104,41.4504394531],"type":"Point"}
}