{
  "type": "Feature",
  "properties": {
    "addr:full":"Carr Miquel De Veri, 51 Mao Islas Baleares 07703",
    "addr:housenumber":"51",
    "addr:postcode":"07703",
    "addr:street":"Carr Miquel De Veri",
    "iso:country":"ES",
    "sg:address":"Carr Miquel De Veri, 51",
    "sg:city":"Mao",
    "sg:orig_category":"Instalaci\u00d3n, Reparaci\u00d3n De Ascensores Y Montacargas",
    "sg:phone":"+34 971 36 03 03",
    "sg:postcode":"07703",
    "sg:province":"Islas Baleares",
    "sg:website":"www.otis.com",
    "wof:name":"Zardoya Otis S.a.",
    "wof:placetype":"venue"
},
  "geometry": {"coordinates":[4.2559638023,39.8891601562],"type":"Point"}
}