{
  "type": "Feature",
  "properties": {
    "addr:full":"Calle de Virtud, 3 Puerto Cruz Santa Cruz De Tenerife 38400",
    "addr:housenumber":"3",
    "addr:postcode":"38400",
    "addr:street":"Calle De Virtud;Cruz",
    "iso:country":"ES",
    "sg:address":"Calle de Virtud, 3",
    "sg:city":"Puerto Cruz",
    "sg:orig_category":"Agencias De Viajes",
    "sg:phone":"+34 922 37 45 37",
    "sg:postcode":"38400",
    "sg:province":"Santa Cruz De Tenerife",
    "wof:name":"Iberojet S A",
    "wof:placetype":"venue"
},
  "geometry": {"coordinates":[-16.5480670929,28.4155197144],"type":"Point"}
}