{
  "type": "Feature",
  "properties": {
    "iso:country":"ES",
    "sg:address":"Calle de Escultor Rivera, 25",
    "sg:city":"Ba\u00d1eza",
    "sg:orig_category":"Abogados",
    "sg:phone":"+34 987 64 27 84",
    "sg:postcode":"24750",
    "sg:province":"Le\u00f3n",
    "wof:name":"Sanchez Prieto Rodolfo",
    "wof:placetype":"venue"
},
  "geometry": {"coordinates":[-5.9242091179,42.3069114685],"type":"Point"}
}