{
  "type": "Feature",
  "properties": {
    "addr:full":"Calle de Pablo Iglesias, 18 Alacant Alicante 03004",
    "addr:housenumber":"18",
    "addr:postcode":"03004",
    "addr:street":"Calle De Pablo Iglesias",
    "iso:country":"ES",
    "sg:address":"Calle de Pablo Iglesias, 18",
    "sg:city":"Alacant",
    "sg:orig_category":"M\u00c9dicos: Estomatolog\u00cda",
    "sg:phone":"+34 965 14 35 24",
    "sg:postcode":"03004",
    "sg:province":"Alicante",
    "wof:name":"Garcia Lacal Jose Miguel",
    "wof:placetype":"venue"
},
  "geometry": {"coordinates":[-0.4881600142,38.347984314],"type":"Point"}
}