{
  "type": "Feature",
  "properties": {
    "addr:full":"Calle de Empedrada (de La), 5 Pinto Madrid 28320",
    "addr:housenumber":"5",
    "addr:postcode":"28320",
    "addr:street":"Calle De Empedrada De La;Pinto",
    "iso:country":"ES",
    "sg:address":"Calle de Empedrada (de La), 5",
    "sg:city":"Pinto",
    "sg:orig_category":"Peluquer\u00cdas, Peluquer\u00cda Mixta",
    "sg:phone":"+34 916 92 15 76",
    "sg:postcode":"28320",
    "sg:province":"Madrid",
    "wof:name":"Zamaga Peluqueros S.l.",
    "wof:placetype":"venue"
},
  "geometry": {"coordinates":[-3.7003765106,40.2432899475],"type":"Point"}
}