{
  "type": "Feature",
  "properties": {
    "iso:country":"ES",
    "sg:address":"Av. Valencia, 56",
    "sg:city":"Gandia",
    "sg:orig_category":"Puertas Y Portales",
    "sg:phone":"+34 962 87 60 06",
    "sg:postcode":"46700",
    "sg:province":"Valencia",
    "wof:name":"Obrim Espai S.l.",
    "wof:placetype":"venue"
},
  "geometry": {"coordinates":[-0.182209,38.9741592407],"type":"Point"}
}