{
  "type": "Feature",
  "properties": {
    "iso:country":"ES",
    "sg:address":"Avda Sevilla, 3",
    "sg:city":"Palacios Y Villafranca",
    "sg:orig_category":"Agentes Generales De Seguros",
    "sg:phone":"+34 955 81 14 18",
    "sg:postcode":"41720",
    "sg:province":"Sevilla",
    "wof:name":"Pazo Y Gomez Agencia De Seguros S.l.",
    "wof:placetype":"venue"
},
  "geometry": {"coordinates":[-5.9239330292,37.160194397],"type":"Point"}
}