{
  "type": "Feature",
  "properties": {
    "iso:country":"ES",
    "sg:address":"Calle de Ejercito, 30",
    "sg:city":"Albacete",
    "sg:orig_category":"Carnicer\u00cdas, Carnicer\u00cdas",
    "sg:phone":"+34 967 22 35 88",
    "sg:postcode":"02002",
    "sg:province":"Albacete",
    "wof:name":"Gonzalez Mellina Antonio",
    "wof:placetype":"venue"
},
  "geometry": {"coordinates":[-1.8544909954,38.9835128784],"type":"Point"}
}