{
  "type": "Feature",
  "properties": {
    "iso:country":"ES",
    "sg:address":"Calle de Santiago, 38",
    "sg:city":"Albacete",
    "sg:orig_category":"Peluqueros: De Se\u00d1oras",
    "sg:phone":"+34 967 24 64 97",
    "sg:postcode":"02005",
    "sg:province":"Albacete",
    "wof:name":"Molina Martinez Pedro",
    "wof:placetype":"venue"
},
  "geometry": {"coordinates":[-1.865706563,39.0010223389],"type":"Point"}
}