{
  "type": "Feature",
  "properties": {
    "addr:full":"Calle de Temeroso, 9 Carbonero El Mayor Segovia 40270",
    "addr:housenumber":"9",
    "addr:postcode":"40270",
    "addr:street":"Calle De Temeroso",
    "iso:country":"ES",
    "sg:address":"Calle de Temeroso, 9",
    "sg:city":"Carbonero El Mayor",
    "sg:orig_category":"Contenedores (mercanc\u00cdas)",
    "sg:phone":"+34 921 56 08 21",
    "sg:postcode":"40270",
    "sg:province":"Segovia",
    "wof:name":"Senin Maestro Juan Antonio",
    "wof:placetype":"venue"
},
  "geometry": {"coordinates":[-4.2684340477,41.1229743958],"type":"Point"}
}