{
  "type": "Feature",
  "properties": {
    "addr:full":"Calle de Martinez Monta\u00d1es, 27 Utrera Sevilla 41710",
    "addr:housenumber":"27",
    "addr:postcode":"41710",
    "addr:street":"Calle De Martinez Montan\u0303Es",
    "iso:country":"ES",
    "sg:address":"Calle de Martinez Monta\u00d1es, 27",
    "sg:city":"Utrera",
    "sg:classifiers":[
        {
            "category":"Tea Room",
            "subcategory":"None",
            "type":"Food & Drink"
        }
    ],
    "sg:phone":"+34 955 86 17 25",
    "sg:postcode":"41710",
    "sg:province":"Sevilla",
    "sg:tags":[
        "snack"
    ],
    "wof:name":"Millan Nieto Dolores",
    "wof:placetype":"venue"
},
  "geometry": {"coordinates":[-5.7823591232,37.1924171448],"type":"Point"}
}