{
  "type": "Feature",
  "properties": {
    "addr:full":"Pg Ribera, 56 Sitges Barcelona 08870",
    "addr:housenumber":"56",
    "addr:postcode":"08870",
    "addr:street":"Ribera",
    "iso:country":"ES",
    "sg:address":"Pg Ribera, 56",
    "sg:city":"Sitges",
    "sg:orig_category":"Grafistas",
    "sg:phone":"+34 938 11 44 71",
    "sg:postcode":"08870",
    "sg:province":"Barcelona",
    "wof:name":"Co Dos S.l.",
    "wof:placetype":"venue"
},
  "geometry": {"coordinates":[1.8057370186,41.2344741821],"type":"Point"}
}