{
  "type": "Feature",
  "properties": {
    "addr:full":"Calle de Chapi, 6 Santa Maria Aguila Almer\u00eda 04710",
    "addr:housenumber":"6",
    "addr:postcode":"04710",
    "addr:street":"Calle De Chapi;Almeri\u0301A",
    "iso:country":"ES",
    "sg:address":"Calle de Chapi, 6",
    "sg:city":"Santa Maria Aguila",
    "sg:orig_category":"Fabricaci\u00d3n De Ventanas",
    "sg:phone":"+34 950 58 16 37",
    "sg:postcode":"04710",
    "sg:province":"Almer\u00eda",
    "wof:name":"Garcia Nieto Dolores",
    "wof:placetype":"venue"
},
  "geometry": {"coordinates":[-2.7699143887,36.7796363831],"type":"Point"}
}