{
  "type": "Feature",
  "properties": {
    "iso:country":"ES",
    "sg:address":"Calle de San Vicente Martir, 19",
    "sg:city":"Valencia",
    "sg:orig_category":"Farmacias",
    "sg:phone":"+34 963 51 39 65",
    "sg:postcode":"46002",
    "sg:province":"Valencia",
    "wof:name":"Salmeron Miron Juan Antonio",
    "wof:placetype":"venue"
},
  "geometry": {"coordinates":[-0.3763070107,39.4727249146],"type":"Point"}
}