{
  "type": "Feature",
  "properties": {
    "iso:country":"ES",
    "sg:address":"Calle de Navellos, 8",
    "sg:city":"Valencia",
    "sg:orig_category":"Librer\u00cdas",
    "sg:phone":"+34 963 91 81 33",
    "sg:postcode":"46003",
    "sg:province":"Valencia",
    "sg:website":"www.parisvalencia.com",
    "wof:name":"Olivert Crespo Cipriano",
    "wof:placetype":"venue"
},
  "geometry": {"coordinates":[-0.375056088,39.477142334],"type":"Point"}
}