{
  "type": "Feature",
  "properties": {
    "addr:full":"Plz. Eva Duarte, 1 Palmaces Jadraque Guadalajara 19245",
    "addr:housenumber":"1",
    "addr:postcode":"19245",
    "addr:street":"Eva Duarte;Jadraque",
    "iso:country":"ES",
    "sg:address":"Plz. Eva Duarte, 1",
    "sg:city":"Palmaces Jadraque",
    "sg:orig_category":"Iglesia Cat\u00d3lica",
    "sg:phone":"+34 949 89 21 30",
    "sg:postcode":"19245",
    "sg:province":"Guadalajara",
    "wof:name":"Obispado De Siguenza-guadalajara",
    "wof:placetype":"venue"
},
  "geometry": {"coordinates":[-2.8743751049,40.9827690125],"type":"Point"}
}