{
  "type": "Feature",
  "properties": {
    "iso:country":"ES",
    "sg:address":"Calle de Francisco Sainz Roldan, 27",
    "sg:city":"Alburquerque",
    "sg:orig_category":"Muebles, Minoristas",
    "sg:phone":"+34 924 40 01 20",
    "sg:postcode":"06510",
    "sg:province":"Badajoz",
    "wof:name":"Casatejada Chamizo Angel",
    "wof:placetype":"venue"
},
  "geometry": {"coordinates":[-7.0059947968,39.2234420776],"type":"Point"}
}