{
  "type": "Feature",
  "properties": {
    "iso:country":"ES",
    "sg:address":"Calle de Platero, 8",
    "sg:city":"San Juan De Aznalfarache",
    "sg:orig_category":"Fabricaci\u00d3n De Distribuidores Autom\u00c1ticos",
    "sg:phone":"+34 954 76 55 66",
    "sg:postcode":"41920",
    "sg:province":"Sevilla",
    "wof:name":"Eurest Colectividades S.a.",
    "wof:placetype":"venue"
},
  "geometry": {"coordinates":[-6.0394229889,37.3582191467],"type":"Point"}
}