{
  "type": "Feature",
  "properties": {
    "addr:full":"Calle de Lain Calvo, 2 Haro La Rioja 26200",
    "addr:housenumber":"2",
    "addr:postcode":"26200",
    "addr:street":"Calle De Lain Calvo",
    "iso:country":"ES",
    "sg:address":"Calle de Lain Calvo, 2",
    "sg:city":"Haro",
    "sg:orig_category":"Productores Recolectores, Venta Directa De Vinos",
    "sg:phone":"+34 941 30 55 83",
    "sg:postcode":"26200",
    "sg:province":"La Rioja",
    "wof:name":"Pe\u00f1agaricano Akutain Juan Jose",
    "wof:placetype":"venue"
},
  "geometry": {"coordinates":[-2.8458657265,42.5764961243],"type":"Point"}
}