{
  "type": "Feature",
  "properties": {
    "addr:full":"Calle de General Pintos, 15 Alacant Alicante 03010",
    "addr:housenumber":"15",
    "addr:postcode":"03010",
    "addr:street":"Calle De General Pintos",
    "iso:country":"ES",
    "sg:address":"Calle de General Pintos, 15",
    "sg:city":"Alacant",
    "sg:orig_category":"Muebles, Minoristas",
    "sg:phone":"+34 965 25 28 96",
    "sg:postcode":"03010",
    "sg:province":"Alicante",
    "wof:name":"Rico Yago Maria Teresa",
    "wof:placetype":"venue"
},
  "geometry": {"coordinates":[-0.4875670075,38.3572883606],"type":"Point"}
}