{
  "type": "Feature",
  "properties": {
    "addr:full":"Calle de Ramon Y Cajal, 12 Oropesa Castell\u00f3n 12594",
    "addr:housenumber":"12",
    "addr:postcode":"12594",
    "addr:street":"Calle De Ramon Y Cajal",
    "iso:country":"ES",
    "sg:address":"Calle de Ramon Y Cajal, 12",
    "sg:city":"Oropesa",
    "sg:orig_category":"Comisarios",
    "sg:phone":"+34 964 31 07 51",
    "sg:postcode":"12594",
    "sg:province":"Castell\u00f3n",
    "wof:name":"Luis Elvira S.a.",
    "wof:placetype":"venue"
},
  "geometry": {"coordinates":[0.1353400052,40.0945281982],"type":"Point"}
}