{
  "type": "Feature",
  "properties": {
    "iso:country":"ES",
    "sg:address":"Calle de Fernando Villalon, 55",
    "sg:city":"Puerto De Santa Maria",
    "sg:orig_category":"Molduras, Junquillos, Listones Y Molduras Perforadas",
    "sg:phone":"+34 956 87 57 02",
    "sg:postcode":"11500",
    "sg:province":"C\u00e1diz",
    "wof:name":"Ariza Oliva Francisco Jose",
    "wof:placetype":"venue"
},
  "geometry": {"coordinates":[-6.2368836403,36.5989227295],"type":"Point"}
}