{
  "type": "Feature",
  "properties": {
    "iso:country":"ES",
    "sg:address":"Calle de Andalucia, 42",
    "sg:city":"Malaga",
    "sg:orig_category":"Asesor\u00cda De Formaci\u00d3n Y Gesti\u00d3n De Personal",
    "sg:phone":"+34 952 07 02 99",
    "sg:postcode":"29009",
    "sg:province":"M\u00e1laga",
    "wof:name":"Gestoria Gesimo S.l.",
    "wof:placetype":"venue"
},
  "geometry": {"coordinates":[-4.4401345253,36.7166442871],"type":"Point"}
}