{
  "type": "Feature",
  "properties": {
    "iso:country":"ES",
    "sg:address":"Rier Sant Andreu, 24",
    "sg:city":"Barcelona",
    "sg:orig_category":"Fabricaci\u00d3n, Importaci\u00d3n De L\u00c1mparas Y Bombillas",
    "sg:phone":"+34 933 46 88 54",
    "sg:postcode":"08030",
    "sg:province":"Barcelona",
    "wof:name":"Instaquatre S.l.",
    "wof:placetype":"venue"
},
  "geometry": {"coordinates":[2.188338995,41.434009552],"type":"Point"}
}