{
  "type": "Feature",
  "properties": {
    "addr:full":"Calle de Joan Miro, 1 Valencia De Don Juan Le\u00f3n 24200",
    "addr:housenumber":"1",
    "addr:postcode":"24200",
    "addr:street":"Calle De Joan Miro",
    "iso:country":"ES",
    "sg:address":"Calle de Joan Miro, 1",
    "sg:city":"Valencia De Don Juan",
    "sg:orig_category":"Promotores Constructores",
    "sg:phone":"+34 987 75 08 57",
    "sg:postcode":"24200",
    "sg:province":"Le\u00f3n",
    "wof:name":"Villoria Del Valle Cesareo",
    "wof:placetype":"venue"
},
  "geometry": {"coordinates":[-5.5177340508,42.2922782898],"type":"Point"}
}