{
  "type": "Feature",
  "properties": {
    "addr:full":"C/ Ramon Llull, 3 Ripollet Barcelona 08291",
    "addr:housenumber":"3",
    "addr:postcode":"08291",
    "addr:street":"C / Ramon Llull",
    "iso:country":"ES",
    "sg:address":"C/ Ramon Llull, 3",
    "sg:city":"Ripollet",
    "sg:orig_category":"Reposter\u00cdas",
    "sg:phone":"+34 936 91 62 03",
    "sg:postcode":"08291",
    "sg:province":"Barcelona",
    "wof:name":"Forn Call-2000 S.l.",
    "wof:placetype":"venue"
},
  "geometry": {"coordinates":[2.1633551121,41.4955863953],"type":"Point"}
}