{
  "type": "Feature",
  "properties": {
    "iso:country":"ES",
    "sg:address":"Calle de Albalate, S/n",
    "sg:city":"Binaced",
    "sg:orig_category":"Asesor\u00cda Sobre Comunicaci\u00d3n De Empresas",
    "sg:phone":"+34 974 42 72 56",
    "sg:postcode":"22510",
    "sg:province":"Huesca",
    "wof:name":"Planificacion Organizacion Y Sistemas S.c.t.a.",
    "wof:placetype":"venue"
},
  "geometry": {"coordinates":[0.2001857013,41.8243713379],"type":"Point"}
}