{
  "type": "Feature",
  "properties": {
    "iso:country":"ES",
    "sg:address":"Calle de Pico Mampodre, 19",
    "sg:city":"Madrid",
    "sg:orig_category":"Pintura Y Barniz (al Por Menor)",
    "sg:phone":"+34 913 32 51 55",
    "sg:postcode":"28031",
    "sg:province":"Madrid",
    "wof:name":"Crespo Fernandez Jose",
    "wof:placetype":"venue"
},
  "geometry": {"coordinates":[-3.6201450825,40.3778572083],"type":"Point"}
}