{
  "type": "Feature",
  "properties": {
    "addr:full":"Carrer de General Josep Moragues, 2 Gava Barcelona 08850",
    "addr:housenumber":"2",
    "addr:postcode":"08850",
    "addr:street":"Carrer De General Josep Moragues",
    "iso:country":"ES",
    "sg:address":"Carrer de General Josep Moragues, 2",
    "sg:city":"Gava",
    "sg:orig_category":"Supermercados Y Hipermercados",
    "sg:phone":"+34 936 62 49 70",
    "sg:postcode":"08850",
    "sg:province":"Barcelona",
    "wof:name":"Tiendas De Conveniencia S.a.",
    "wof:placetype":"venue"
},
  "geometry": {"coordinates":[1.99474895,41.306186676],"type":"Point"}
}