{
  "type": "Feature",
  "properties": {
    "addr:full":"Calle de Martires, 6 Torrelavega Cantabria 39300",
    "addr:housenumber":"6",
    "addr:postcode":"39300",
    "addr:street":"Calle De Martires",
    "iso:country":"ES",
    "sg:address":"Calle de Martires, 6",
    "sg:city":"Torrelavega",
    "sg:orig_category":"Agencias De Viajes",
    "sg:phone":"+34 942 89 16 26",
    "sg:postcode":"39300",
    "sg:province":"Cantabria",
    "wof:name":"Canyon Tames Maria Mercedes",
    "wof:placetype":"venue"
},
  "geometry": {"coordinates":[-4.048309803,43.3512840271],"type":"Point"}
}