{
  "type": "Feature",
  "properties": {
    "iso:country":"ES",
    "sg:address":"Ctra. Villacastin-vigo, Km. 0279,0",
    "sg:city":"Roales",
    "sg:orig_category":"Materiales De Construcci\u00d3n (en General)",
    "sg:phone":"+34 980 53 87 51",
    "sg:postcode":"49192",
    "sg:province":"Zamora",
    "wof:name":"Tuberias Y Prefabricados De Hormigon Hermanos Martin Rodriguez S.l.",
    "wof:placetype":"venue"
},
  "geometry": {"coordinates":[-5.8029990196,41.550819397],"type":"Point"}
}