{
  "type": "Feature",
  "properties": {
    "iso:country":"ES",
    "sg:address":"Plaz Candelaria (la), 11",
    "sg:city":"Santa Cruz De Tenerife",
    "sg:orig_category":"Bazares, Art\u00cdculos De Limpieza Y De Cocina (al Por Menor)",
    "sg:phone":"+34 922 24 34 19",
    "sg:postcode":"38002",
    "sg:province":"Santa Cruz De Tenerife",
    "wof:name":"C. B. Hijos De Parsram Dadlani",
    "wof:placetype":"venue"
},
  "geometry": {"coordinates":[-17.2191944122,28.1820106506],"type":"Point"}
}