{
  "type": "Feature",
  "properties": {
    "addr:full":"Calle de Chile, 23 Madrid Madrid 28016",
    "addr:housenumber":"23",
    "addr:postcode":"madrid;28016",
    "addr:street":"Calle De Chile",
    "iso:country":"ES",
    "sg:address":"Calle de Chile, 23",
    "sg:city":"Madrid",
    "sg:orig_category":"Carnicer\u00cdas, Carnicer\u00cdas",
    "sg:phone":"+34 913 59 35 65",
    "sg:postcode":"28016",
    "sg:province":"Madrid",
    "wof:name":"Velasco Gordo Jose Luis",
    "wof:placetype":"venue"
},
  "geometry": {"coordinates":[-3.6758079529,40.459274292],"type":"Point"}
}