{
  "type": "Feature",
  "properties": {
    "addr:full":"Barr Estacion, S/n Humanes Guadalajara 19220",
    "addr:postcode":"19220",
    "addr:street":"S / N",
    "iso:country":"ES",
    "sg:address":"Barr Estacion, S/n",
    "sg:city":"Humanes",
    "sg:orig_category":"Fabricaci\u00d3n Y Comercio De M\u00c1quinas",
    "sg:phone":"+34 949 85 12 42",
    "sg:postcode":"19220",
    "sg:province":"Guadalajara",
    "wof:name":"Tecnologias Orotava S.l.",
    "wof:placetype":"venue"
},
  "geometry": {"coordinates":[-3.1475710869,40.8301887512],"type":"Point"}
}