{
  "type": "Feature",
  "properties": {
    "iso:country":"ES",
    "sg:address":"Calle de Carreteria, 55",
    "sg:city":"Malaga",
    "sg:orig_category":"M\u00c9dicos: Estomatolog\u00cda",
    "sg:phone":"+34 952 22 15 43",
    "sg:postcode":"29008",
    "sg:province":"M\u00e1laga",
    "wof:name":"Santamaria Gaethe Francisco",
    "wof:placetype":"venue"
},
  "geometry": {"coordinates":[-4.4234409332,36.7235679626],"type":"Point"}
}