{
  "type": "Feature",
  "properties": {
    "addr:full":"Carrer de Melcior De Palau, 143 Barcelona Barcelona 08014",
    "addr:housenumber":"143",
    "addr:postcode":"08014",
    "addr:street":"Carrer De Melcior De Palau",
    "iso:country":"ES",
    "sg:address":"Carrer de Melcior De Palau, 143",
    "sg:city":"Barcelona",
    "sg:orig_category":"Venta, Alquiler De V\u00cddeo",
    "sg:phone":"+34 933 30 41 85",
    "sg:postcode":"08014",
    "sg:province":"Barcelona",
    "wof:name":"Hgamer Bcn Scp",
    "wof:placetype":"venue"
},
  "geometry": {"coordinates":[2.1385860443,41.3813972473],"type":"Point"}
}