{
  "type": "Feature",
  "properties": {
    "iso:country":"ES",
    "sg:address":"Calle de Granada, 7",
    "sg:city":"Alcantarilla",
    "sg:orig_category":"Material Y Suministros Para Perforaciones, Sondeos",
    "sg:phone":"+34 968 80 20 64",
    "sg:postcode":"30820",
    "sg:province":"Murcia",
    "wof:name":"Vivo Bastida Domingo",
    "wof:placetype":"venue"
},
  "geometry": {"coordinates":[-1.2224994898,37.9637489319],"type":"Point"}
}