{
  "type": "Feature",
  "properties": {
    "iso:country":"ES",
    "sg:address":"Av Antoni Maura, 14",
    "sg:city":"Palma",
    "sg:orig_category":"Material Y Accesorios Para Bisuter\u00cda Y Joyer\u00cda",
    "sg:phone":"+34 971 72 28 89",
    "sg:postcode":"07012",
    "sg:province":"Islas Baleares",
    "wof:name":"Nicolas Joyero S.a.",
    "wof:placetype":"venue"
},
  "geometry": {"coordinates":[2.6460530758,39.5683517456],"type":"Point"}
}