{
  "type": "Feature",
  "properties": {
    "addr:full":"Calle de Penaguila, S/n Alacant Alicante 03009",
    "addr:housenumber":"s / n",
    "addr:postcode":"03009",
    "addr:street":"Calle De Penaguila",
    "iso:country":"ES",
    "sg:address":"Calle de Penaguila, S/n",
    "sg:city":"Alacant",
    "sg:orig_category":"Bancos",
    "sg:phone":"+34 965 17 75 86",
    "sg:postcode":"03009",
    "sg:province":"Alicante",
    "wof:name":"Banco Guipuzcoano S.a.",
    "wof:placetype":"venue"
},
  "geometry": {"coordinates":[-0.4984439909,38.3715209961],"type":"Point"}
}