{
  "type": "Feature",
  "properties": {
    "addr:full":"Avda Conde De Gondomar, 19 Gondomar Pontevedra 36380",
    "addr:housenumber":"19",
    "addr:postcode":"36380",
    "addr:street":"Avda Conde De Gondomar",
    "iso:country":"ES",
    "sg:address":"Avda Conde De Gondomar, 19",
    "sg:city":"Gondomar",
    "sg:orig_category":"Ense\u00d1ante, Direcci\u00d3n",
    "sg:phone":"+34 986 38 93 53",
    "sg:postcode":"36380",
    "sg:province":"Pontevedra",
    "wof:name":"Perez Lopez Ana Isabel",
    "wof:placetype":"venue"
},
  "geometry": {"coordinates":[-8.7597951889,42.1080551147],"type":"Point"}
}