{
  "type": "Feature",
  "properties": {
    "iso:country":"ES",
    "sg:address":"Avda Aragon, 89",
    "sg:city":"Alca\u00f1iz",
    "sg:orig_category":"Asociaciones Humanitarias, De Cooperaci\u00d3n, De Acci\u00d3n Social",
    "sg:phone":"+34 978 83 12 24",
    "sg:postcode":"44600",
    "sg:province":"Teruel",
    "wof:name":"Asociacion Espa\u00f1ola Contra El Cancer",
    "wof:placetype":"venue"
},
  "geometry": {"coordinates":[-0.1290924996,41.0449562073],"type":"Point"}
}