{
  "type": "Feature",
  "properties": {
    "addr:full":"Calle de Panama, 7 Costa Teguise Las Palmas 35509",
    "addr:housenumber":"7",
    "addr:postcode":"35509",
    "addr:street":"Calle De Panama",
    "iso:country":"ES",
    "sg:address":"Calle de Panama, 7",
    "sg:city":"Costa Teguise",
    "sg:orig_category":"M\u00c9dicos: Pediatr\u00cda. Enfermedades De Los Ni\u00d1os",
    "sg:phone":"+34 928 59 06 84",
    "sg:postcode":"35509",
    "sg:province":"Las Palmas",
    "wof:name":"Khalaf Khalaf Adnan Yousef",
    "wof:placetype":"venue"
},
  "geometry": {"coordinates":[-13.5916891098,28.955160141],"type":"Point"}
}