{
  "type": "Feature",
  "properties": {
    "iso:country":"ES",
    "sg:address":"Calle de Cristo Del, 1",
    "sg:city":"Bilbao",
    "sg:orig_category":"Administradores De Bienes Y Delegados De Comunidades De Propietarios",
    "sg:phone":"+34 944 46 45 46",
    "sg:postcode":"48007",
    "sg:province":"Vizcaya",
    "wof:name":"Asesoria Adeya S.l.",
    "wof:placetype":"venue"
},
  "geometry": {"coordinates":[-2.9223937988,43.2651977539],"type":"Point"}
}