{
  "type": "Feature",
  "properties": {
    "addr:full":"Calle de Mayor, 30 Guardo Palencia 34880",
    "addr:housenumber":"30",
    "addr:postcode":"34880",
    "addr:street":"Calle De Mayor",
    "iso:country":"ES",
    "sg:address":"Calle de Mayor, 30",
    "sg:city":"Guardo",
    "sg:orig_category":"Promotores Constructores",
    "sg:phone":"+34 979 85 33 52",
    "sg:postcode":"34880",
    "sg:province":"Palencia",
    "wof:name":"Construcciones Tarilonte S.l.",
    "wof:placetype":"venue"
},
  "geometry": {"coordinates":[-4.8436188698,42.7889213562],"type":"Point"}
}