{
  "type": "Feature",
  "properties": {
    "iso:country":"ES",
    "sg:address":"Calle de Nazaret, 5",
    "sg:city":"Mostoles",
    "sg:orig_category":"Maquinaria Para Industrias Diversas",
    "sg:phone":"+34 916 45 58 99",
    "sg:postcode":"28936",
    "sg:province":"Madrid",
    "wof:name":"Alquifacil S.l.",
    "wof:placetype":"venue"
},
  "geometry": {"coordinates":[-3.8538229465,40.3292160034],"type":"Point"}
}