{
  "type": "Feature",
  "properties": {
    "iso:country":"ES",
    "sg:address":"Calle de Pellejo (del), 51",
    "sg:city":"Valdepe\u00f1as",
    "sg:orig_category":"Pintura Y Barniz (al Por Menor)",
    "sg:phone":"+34 926 32 49 85",
    "sg:postcode":"13300",
    "sg:province":"Ciudad Real",
    "wof:name":"Comercial De Pinturas Jabalon S. L.",
    "wof:placetype":"venue"
},
  "geometry": {"coordinates":[-3.3911440372,38.7782402039],"type":"Point"}
}