{
  "type": "Feature",
  "properties": {
    "iso:country":"ES",
    "sg:address":"Carrer de Beltran I Rozpide, 4",
    "sg:city":"Barcelona",
    "sg:classifiers":[
        {
            "category":"Professional",
            "subcategory":"Business Services",
            "type":"Services"
        }
    ],
    "sg:phone":"+34 932 05 18 00",
    "sg:postcode":"08034",
    "sg:province":"Barcelona",
    "sg:tags":[
        "control",
        "asesor\u00cda",
        "organizaci\u00d3n",
        "la",
        "de",
        "gesti\u00d3n",
        "y"
    ],
    "wof:name":"Berozpi S.l.",
    "wof:placetype":"venue"
},
  "geometry": {"coordinates":[2.1210930347,41.3889007568],"type":"Point"}
}