{
  "type": "Feature",
  "properties": {
    "iso:country":"ES",
    "sg:address":"Carrer de Comtessa De Sobradiel, 8",
    "sg:city":"Barcelona",
    "sg:orig_category":"Ense\u00d1anza: Profesiones Art\u00cdsticas",
    "sg:phone":"+34 933 15 11 62",
    "sg:postcode":"08002",
    "sg:province":"Barcelona",
    "wof:name":"Condesa 8 S.l.",
    "wof:placetype":"venue"
},
  "geometry": {"coordinates":[2.1784820557,41.3810997009],"type":"Point"}
}