{
  "type": "Feature",
  "properties": {
    "iso:country":"ES",
    "sg:address":"Calle de San Agustin, 17",
    "sg:city":"Palmas De Gran Canaria",
    "sg:orig_category":"Procuradores",
    "sg:phone":"+34 928 33 24 66",
    "sg:postcode":"35001",
    "sg:province":"Las Palmas",
    "wof:name":"Apolinario Hidalgo Maria Dolores",
    "wof:placetype":"venue"
},
  "geometry": {"coordinates":[-15.4128074646,28.0999698639],"type":"Point"}
}