{
  "type": "Feature",
  "properties": {
    "iso:country":"ES",
    "sg:address":"Avda Castilla-la Mancha (de), 111",
    "sg:city":"San Sebastian De Los Reyes",
    "sg:orig_category":"Empresarios",
    "sg:phone":"+34 916 63 88 08",
    "sg:postcode":"28700",
    "sg:province":"Madrid",
    "wof:name":"Construcciones Masoed Y Linares S.l.",
    "wof:placetype":"venue"
},
  "geometry": {"coordinates":[-3.64092803,40.5571098328],"type":"Point"}
}