{
  "type": "Feature",
  "properties": {
    "addr:full":"Calle de Ciudad Real, 33 Parla Madrid 28980",
    "addr:housenumber":"33",
    "addr:postcode":"28980",
    "addr:street":"Calle De Ciudad Real",
    "iso:country":"ES",
    "sg:address":"Calle de Ciudad Real, 33",
    "sg:city":"Parla",
    "sg:orig_category":"Fotocopias, Reprograf\u00cda",
    "sg:phone":"+34 916 99 17 69",
    "sg:postcode":"28980",
    "sg:province":"Madrid",
    "wof:name":"Duckman World S.l.",
    "wof:placetype":"venue"
},
  "geometry": {"coordinates":[-3.7657244205,40.2436599731],"type":"Point"}
}