{
  "type": "Feature",
  "properties": {
    "addr:full":"Calle de Duquesa De La Victoria, 68 Logro\u00f1o La Rioja 26004",
    "addr:housenumber":"68",
    "addr:postcode":"26004",
    "addr:street":"Calle De Duquesa De La Victoria;Rioja",
    "iso:country":"ES",
    "sg:address":"Calle de Duquesa De La Victoria, 68",
    "sg:city":"Logro\u00f1o",
    "sg:orig_category":"Carnicer\u00cdas, Carnicer\u00cdas",
    "sg:phone":"+34 941 24 80 50",
    "sg:postcode":"26004",
    "sg:province":"La Rioja",
    "wof:name":"Millan Garcia Olalla Luis",
    "wof:placetype":"venue"
},
  "geometry": {"coordinates":[-2.4350531101,42.4637794495],"type":"Point"}
}