{
  "type": "Feature",
  "properties": {
    "addr:full":"Carrer de Rocafort, 191 Barcelona Barcelona 08029",
    "addr:housenumber":"191",
    "addr:postcode":"08029",
    "addr:street":"Carrer De Rocafort",
    "iso:country":"ES",
    "sg:address":"Carrer de Rocafort, 191",
    "sg:city":"Barcelona",
    "sg:orig_category":"Mec\u00c1nico Del Autom\u00d3vil",
    "sg:phone":"+34 933 21 37 43",
    "sg:postcode":"08029",
    "sg:province":"Barcelona",
    "wof:name":"Herrero Vera Miguel",
    "wof:placetype":"venue"
},
  "geometry": {"coordinates":[2.1477239132,41.3833198547],"type":"Point"}
}