{
  "type": "Feature",
  "properties": {
    "addr:full":"Calle de Alcorcon, 8 Parla Madrid 28980",
    "addr:housenumber":"8",
    "addr:postcode":"28980",
    "addr:street":"Calle De Alcorcon",
    "iso:country":"ES",
    "sg:address":"Calle de Alcorcon, 8",
    "sg:city":"Parla",
    "sg:orig_category":"Flores Y Plantas Naturales (al Por Mayor)",
    "sg:phone":"+34 916 98 37 39",
    "sg:postcode":"28980",
    "sg:province":"Madrid",
    "wof:name":"Sanchez Go\u00f1e Jose Maria",
    "wof:placetype":"venue"
},
  "geometry": {"coordinates":[-3.7721693516,40.2411766052],"type":"Point"}
}