{
  "type": "Feature",
  "properties": {
    "iso:country":"ES",
    "sg:address":"Calle de Marquesa Paterna Del Campo, 28",
    "sg:city":"Valencia",
    "sg:orig_category":"Folclore",
    "sg:phone":"+34 963 49 74 17",
    "sg:postcode":"46025",
    "sg:province":"Valencia",
    "wof:name":"Martinez Molla Jose",
    "wof:placetype":"venue"
},
  "geometry": {"coordinates":[-0.3918769956,39.5007247925],"type":"Point"}
}