{
  "type": "Feature",
  "properties": {
    "addr:full":"Avda Andalucia, 42 Albu\u00f1ol Granada 18700",
    "addr:housenumber":"42 albun\u0303ol",
    "addr:postcode":"18700",
    "addr:street":"Avda Andalucia",
    "iso:country":"ES",
    "sg:address":"Avda Andalucia, 42",
    "sg:city":"Albu\u00f1ol",
    "sg:orig_category":"Distribuci\u00d3n De Petr\u00d3leo Y Derivados",
    "sg:phone":"+34 958 82 67 98",
    "sg:postcode":"18700",
    "sg:province":"Granada",
    "wof:name":"Rivas Domingo Juan Ramon",
    "wof:placetype":"venue"
},
  "geometry": {"coordinates":[-3.1974129677,36.7914085388],"type":"Point"}
}