{
  "type": "Feature",
  "properties": {
    "addr:full":"Plaz San Jose, S/n S. Fernando C\u00e1diz 11100",
    "addr:housenumber":"s",
    "addr:postcode":"11100",
    "addr:street":"Plaz San Jose;/ N S. Fernando Ca\u0301Diz",
    "iso:country":"ES",
    "sg:address":"Plaz San Jose, S/n",
    "sg:city":"S. Fernando",
    "sg:orig_category":"Ense\u00d1anza, Formaci\u00d3n Profesional: Aprendizaje",
    "sg:phone":"+34 956 59 00 24",
    "sg:postcode":"11100",
    "sg:province":"C\u00e1diz",
    "wof:name":"Escuela San Jose",
    "wof:placetype":"venue"
},
  "geometry": {"coordinates":[-6.1967391968,36.4654541016],"type":"Point"}
}