{
  "type": "Feature",
  "properties": {
    "addr:full":"La Lloma, 2 Pobla Vallbona Valencia 46185",
    "addr:housenumber":"2",
    "addr:postcode":"46185",
    "iso:country":"ES",
    "sg:address":"La Lloma, 2",
    "sg:city":"Pobla Vallbona",
    "sg:orig_category":"Molduras, Junquillos, Listones Y Molduras Perforadas",
    "sg:phone":"+34 961 66 22 24",
    "sg:postcode":"46185",
    "sg:province":"Valencia",
    "wof:name":"Gramuntell Serra Vicente",
    "wof:placetype":"venue"
},
  "geometry": {"coordinates":[-0.5248320103,39.5816268921],"type":"Point"}
}