{
  "type": "Feature",
  "properties": {
    "addr:full":"Ctra Torrequebradilla, S/n Jaen Ja\u00e9n 23009",
    "addr:housenumber":"s / n;jae\u0301n",
    "addr:postcode":"23009",
    "addr:street":"Ctra Torrequebradilla",
    "iso:country":"ES",
    "sg:address":"Ctra Torrequebradilla, S/n",
    "sg:city":"Jaen",
    "sg:orig_category":"Supermercados Y Hipermercados",
    "sg:phone":"+34 953 27 11 15",
    "sg:postcode":"23009",
    "sg:province":"Ja\u00e9n",
    "sg:website":"www.mercadona.es",
    "wof:name":"Mercadona S.a.",
    "wof:placetype":"venue"
},
  "geometry": {"coordinates":[-3.7778189182,37.7850456238],"type":"Point"}
}