{
  "type": "Feature",
  "properties": {
    "iso:country":"ES",
    "sg:address":"Calle de Parras, 19",
    "sg:city":"Cuellar",
    "sg:orig_category":"Bancos",
    "sg:phone":"+34 921 14 13 61",
    "sg:postcode":"40200",
    "sg:province":"Segovia",
    "wof:name":"Banco De Castilla",
    "wof:placetype":"venue"
},
  "geometry": {"coordinates":[-4.311809063,41.4002799988],"type":"Point"}
}