{
  "type": "Feature",
  "properties": {
    "addr:full":"Av Pais Valencia, 54 Alcoi Alicante 03801",
    "addr:housenumber":"54",
    "addr:postcode":"03801",
    "addr:street":"Av Pais Valencia",
    "iso:country":"ES",
    "sg:address":"Av Pais Valencia, 54",
    "sg:city":"Alcoi",
    "sg:orig_category":"Financiaci\u00d3n Y Cr\u00c9ditos",
    "sg:phone":"+34 965 54 21 88",
    "sg:postcode":"03801",
    "sg:province":"Alicante",
    "wof:name":"Bt Espa\u00d1a Compa\u00d1ia De Servicios Globales De Telecomunicaciones S.a.u.",
    "wof:placetype":"venue"
},
  "geometry": {"coordinates":[-0.4774259925,38.6960601807],"type":"Point"}
}