{
  "type": "Feature",
  "properties": {
    "iso:country":"ES",
    "sg:address":"C/ Calvari, 51",
    "sg:city":"Ripollet",
    "sg:orig_category":"Peluqueros: De Se\u00d1oras",
    "sg:phone":"+34 935 80 00 95",
    "sg:postcode":"08291",
    "sg:province":"Barcelona",
    "wof:name":"Velasco Fernandez Carmen",
    "wof:placetype":"venue"
},
  "geometry": {"coordinates":[2.1577041149,41.4962882996],"type":"Point"}
}