{
  "type": "Feature",
  "properties": {
    "addr:full":"Avda Algeciras, 63 Neda La Coru\u00f1a 15510",
    "addr:housenumber":"63",
    "addr:postcode":"15510",
    "addr:street":"Avda Algeciras;La Corun\u0303A",
    "iso:country":"ES",
    "sg:address":"Avda Algeciras, 63",
    "sg:city":"Neda",
    "sg:orig_category":"Aguas (distribuci\u00d3n, Servicios)",
    "sg:phone":"+34 981 38 00 26",
    "sg:postcode":"15510",
    "sg:province":"La Coru\u00f1a",
    "wof:name":"Ayuntamiento De Neda",
    "wof:placetype":"venue"
},
  "geometry": {"coordinates":[-8.1511478424,43.512386322],"type":"Point"}
}