{
  "type": "Feature",
  "properties": {
    "addr:full":"Calle de San Andres, 2 Valencia Valencia 46002",
    "addr:housenumber":"2",
    "addr:postcode":"46002",
    "addr:street":"Calle De San Andres",
    "iso:country":"ES",
    "sg:address":"Calle de San Andres, 2",
    "sg:city":"Valencia",
    "sg:orig_category":"Museos",
    "sg:phone":"+34 963 51 63 92",
    "sg:postcode":"46002",
    "sg:province":"Valencia",
    "wof:name":"Museo Nacional De Ceramica",
    "wof:placetype":"venue"
},
  "geometry": {"coordinates":[-0.3754110038,39.4721794128],"type":"Point"}
}