{
  "type": "Feature",
  "properties": {
    "iso:country":"ES",
    "sg:address":"Calle de Santiago, 14",
    "sg:city":"Valladolid",
    "sg:orig_category":"Reciclaje Y Tratamiento De Desechos Varios",
    "sg:phone":"+34 983 34 59 61",
    "sg:postcode":"47001",
    "sg:province":"Valladolid",
    "wof:name":"Tratamientos Especificos Curativos De La",
    "wof:placetype":"venue"
},
  "geometry": {"coordinates":[-4.7288980484,41.6501083374],"type":"Point"}
}