{
  "type": "Feature",
  "properties": {
    "addr:full":"Calle de Sierra De Las Estancias, 6 Viator Almer\u00eda 04240",
    "addr:housenumber":"6",
    "addr:postcode":"04240",
    "addr:street":"Calle De Sierra De Las Estancias;Almeri\u0301A",
    "iso:country":"ES",
    "sg:address":"Calle de Sierra De Las Estancias, 6",
    "sg:city":"Viator",
    "sg:orig_category":"Mec\u00c1nico Del Autom\u00d3vil",
    "sg:phone":"+34 950 30 41 70",
    "sg:postcode":"04240",
    "sg:province":"Almer\u00eda",
    "wof:name":"Talleres Gallardo La Juaira S.l.",
    "wof:placetype":"venue"
},
  "geometry": {"coordinates":[-2.4201040268,36.8810653687],"type":"Point"}
}