{
  "type": "Feature",
  "properties": {
    "addr:full":"Calle de General Elorza, 45 Oviedo Asturias 33001",
    "addr:housenumber":"45",
    "addr:postcode":"33001",
    "addr:street":"Calle De General Elorza",
    "iso:country":"ES",
    "sg:address":"Calle de General Elorza, 45",
    "sg:city":"Oviedo",
    "sg:orig_category":"Institutos De Belleza",
    "sg:phone":"+34 985 20 93 33",
    "sg:postcode":"33001",
    "sg:province":"Asturias",
    "wof:name":"Patricia Aronatur S.l.",
    "wof:placetype":"venue"
},
  "geometry": {"coordinates":[-5.8458547592,43.3665237427],"type":"Point"}
}