{
  "type": "Feature",
  "properties": {
    "addr:full":"Calle de Pintor Segrelles, 2 Xara Alicante 03700",
    "addr:housenumber":"2",
    "addr:postcode":"03700",
    "addr:street":"Calle De Pintor Segrelles;Alicante",
    "iso:country":"ES",
    "sg:address":"Calle de Pintor Segrelles, 2",
    "sg:city":"Xara",
    "sg:orig_category":"Ense\u00d1anza: Profesiones Art\u00cdsticas",
    "sg:phone":"+34 965 78 67 24",
    "sg:postcode":"03700",
    "sg:province":"Alicante",
    "wof:name":"Pedro Agulles Fotograf Srll",
    "wof:placetype":"venue"
},
  "geometry": {"coordinates":[0.1039630026,38.8354949951],"type":"Point"}
}