{
  "type": "Feature",
  "properties": {
    "iso:country":"ES",
    "sg:address":"Carrer de Sant Roc (de), 2",
    "sg:city":"Vilassar De Mar",
    "sg:orig_category":"Abogados",
    "sg:phone":"+34 937 59 05 04",
    "sg:postcode":"08340",
    "sg:province":"Barcelona",
    "wof:name":"Gonzalez Ferrero Jose Luis",
    "wof:placetype":"venue"
},
  "geometry": {"coordinates":[2.3909409046,41.5021133423],"type":"Point"}
}