{
  "type": "Feature",
  "properties": {
    "addr:full":"Calle de Martires, 5 Carolina Ja\u00e9n 23200",
    "addr:housenumber":"5",
    "addr:postcode":"23200",
    "addr:street":"Calle De Martires;Carolina Jae\u0301N",
    "iso:country":"ES",
    "sg:address":"Calle de Martires, 5",
    "sg:city":"Carolina",
    "sg:orig_category":"Cajas De Ahorro",
    "sg:phone":"+34 953 66 13 19",
    "sg:postcode":"23200",
    "sg:province":"Ja\u00e9n",
    "wof:name":"Unicaja",
    "wof:placetype":"venue"
},
  "geometry": {"coordinates":[-3.614964962,38.2739601135],"type":"Point"}
}