{
  "type": "Feature",
  "properties": {
    "addr:full":"Calle de Pintor Barjola, 13 Almendralejo Badajoz 06200",
    "addr:housenumber":"13",
    "addr:postcode":"06200",
    "addr:street":"Calle De Pintor Barjola",
    "iso:country":"ES",
    "sg:address":"Calle de Pintor Barjola, 13",
    "sg:city":"Almendralejo",
    "sg:orig_category":"Hielo Artificial (fabricaci\u00d3n, Distribuci\u00d3n)",
    "sg:phone":"+34 924 67 19 07",
    "sg:postcode":"06200",
    "sg:province":"Badajoz",
    "wof:name":"Congelados A Domicilio La Goleta S.l.",
    "wof:placetype":"venue"
},
  "geometry": {"coordinates":[-6.4068241119,38.6845092773],"type":"Point"}
}