{
  "type": "Feature",
  "properties": {
    "iso:country":"ES",
    "sg:address":"Ptda El Moco, 137",
    "sg:city":"Albatera",
    "sg:orig_category":"Contenedores (mercanc\u00cdas)",
    "sg:phone":"+34 965 48 83 41",
    "sg:postcode":"03340",
    "sg:province":"Alicante",
    "wof:name":"Quesada Bernabeu Jesus",
    "wof:placetype":"venue"
},
  "geometry": {"coordinates":[-0.8711339831,38.1797294617],"type":"Point"}
}