{
  "type": "Feature",
  "properties": {
    "addr:full":"Calle de Sevilla, S/n Jimena Frontera C\u00e1diz 11330",
    "addr:housenumber":"s",
    "addr:postcode":"11330",
    "addr:street":"Calle De Sevilla;/ N Jimena;Ca\u0301Diz",
    "iso:country":"ES",
    "sg:address":"Calle de Sevilla, S/n",
    "sg:city":"Jimena Frontera",
    "sg:orig_category":"Ense\u00d1anza, Formaci\u00d3n Profesional: Aprendizaje",
    "sg:phone":"+34 956 64 02 64",
    "sg:postcode":"11330",
    "sg:province":"C\u00e1diz",
    "wof:name":"Junta De Andalucia-consejeria De Cultura",
    "wof:placetype":"venue"
},
  "geometry": {"coordinates":[-5.4515137672,36.432346344],"type":"Point"}
}