{
  "type": "Feature",
  "properties": {
    "addr:full":"Carrer de Mossen Cinto Verdaguer (de), 12 Santa Oliva Tarragona 43710",
    "addr:housenumber":"12",
    "addr:postcode":"43710",
    "addr:street":"Carrer De Mossen Cinto Verdaguer De",
    "iso:country":"ES",
    "sg:address":"Carrer de Mossen Cinto Verdaguer (de), 12",
    "sg:city":"Santa Oliva",
    "sg:orig_category":"Reposter\u00cdas",
    "sg:phone":"+34 977 67 96 35",
    "sg:postcode":"43710",
    "sg:province":"Tarragona",
    "wof:name":"Aguilar Via Santiago",
    "wof:placetype":"venue"
},
  "geometry": {"coordinates":[1.5979640484,41.2726631165],"type":"Point"}
}