{
  "type": "Feature",
  "properties": {
    "addr:full":"Pase San Antonio, 3 Ponferrada Le\u00f3n 24400",
    "addr:housenumber":"3",
    "addr:postcode":"24400",
    "addr:street":"San Antonio",
    "iso:country":"ES",
    "sg:address":"Pase San Antonio, 3",
    "sg:city":"Ponferrada",
    "sg:orig_category":"Centros Empresariales",
    "sg:phone":"+34 987 40 59 99",
    "sg:postcode":"24400",
    "sg:province":"Le\u00f3n",
    "wof:name":"Federacion Leonesa Empresarios",
    "wof:placetype":"venue"
},
  "geometry": {"coordinates":[-6.5881700516,42.5477218628],"type":"Point"}
}