{
  "type": "Feature",
  "properties": {
    "addr:full":"Ctra Palmar, 147 Beniajan Murcia 30570",
    "addr:housenumber":"147",
    "addr:postcode":"30570",
    "addr:street":"Ctra Palmar",
    "iso:country":"ES",
    "sg:address":"Ctra Palmar, 147",
    "sg:city":"Beniajan",
    "sg:orig_category":"Arboricultura Y Producci\u00d3n De Frutas",
    "sg:phone":"+34 968 82 04 71",
    "sg:postcode":"30570",
    "sg:province":"Murcia",
    "wof:name":"Frutas Loar S.l.",
    "wof:placetype":"venue"
},
  "geometry": {"coordinates":[-1.0764789581,37.9721717834],"type":"Point"}
}