{
  "type": "Feature",
  "properties": {
    "addr:full":"Calle de Francisco Silvela, 75 Madrid Madrid 28028",
    "addr:housenumber":"75",
    "addr:postcode":"madrid;28028",
    "addr:street":"Calle De Francisco Silvela",
    "iso:country":"ES",
    "sg:address":"Calle de Francisco Silvela, 75",
    "sg:city":"Madrid",
    "sg:orig_category":"Asesor\u00cda Fiscal Y Jur\u00cddica",
    "sg:phone":"+34 915 64 87 39",
    "sg:postcode":"28028",
    "sg:province":"Madrid",
    "wof:name":"Ferlin Y Dinar S.l.",
    "wof:placetype":"venue"
},
  "geometry": {"coordinates":[-3.6762509346,40.4361000061],"type":"Point"}
}