{
  "type": "Feature",
  "properties": {
    "addr:full":"Pla\u00c7 Nova, 6 Centre Urba Girona 17500",
    "addr:postcode":"17500",
    "iso:country":"ES",
    "sg:address":"Pla\u00c7 Nova, 6",
    "sg:city":"Centre Urba",
    "sg:orig_category":"Ense\u00d1anza Variada",
    "sg:phone":"+34 972 70 07 44",
    "sg:postcode":"17500",
    "sg:province":"Girona",
    "wof:name":"Amils Espinet Maria Rosa",
    "wof:placetype":"venue"
},
  "geometry": {"coordinates":[2.8236999512,41.9817962646],"type":"Point"}
}