{
  "type": "Feature",
  "properties": {
    "addr:full":"Calle de Milana (la), 3 San Isidro Santa Cruz De Tenerife 38611",
    "addr:postcode":"38611",
    "addr:street":"Calle De Milana La 3",
    "iso:country":"ES",
    "sg:address":"Calle de Milana (la), 3",
    "sg:city":"San Isidro",
    "sg:classifiers":[
        {
            "category":"Community Center",
            "subcategory":"Youth",
            "type":"Public Place"
        }
    ],
    "sg:phone":"+34 922 39 22 75",
    "sg:postcode":"38611",
    "sg:province":"Santa Cruz De Tenerife",
    "sg:tags":[
        "juventud",
        "administraci\u00d3n",
        "la",
        "en",
        "deporte",
        "el",
        "y"
    ],
    "wof:name":"Pi\u00f1ero Gaspar Pedro",
    "wof:placetype":"venue"
},
  "geometry": {"coordinates":[-16.5576667786,28.0790710449],"type":"Point"}
}