{
  "type": "Feature",
  "properties": {
    "addr:full":"Calle de Redonda, 1 Pinos-puente Granada 18240",
    "addr:housenumber":"1",
    "addr:postcode":"18240",
    "addr:street":"Calle De Redonda",
    "iso:country":"ES",
    "sg:address":"Calle de Redonda, 1",
    "sg:city":"Pinos-puente",
    "sg:orig_category":"Distribuci\u00d3n De Petr\u00d3leo Y Derivados",
    "sg:phone":"+34 958 45 21 05",
    "sg:postcode":"18240",
    "sg:province":"Granada",
    "wof:name":"Moreno Vaquero Antonio",
    "wof:placetype":"venue"
},
  "geometry": {"coordinates":[-3.7543690205,37.2501602173],"type":"Point"}
}