{
  "type": "Feature",
  "properties": {
    "iso:country":"ES",
    "sg:address":"Carrer de Cornella Modern, 64",
    "sg:city":"Cornella Llobregat",
    "sg:orig_category":"Artes Gr\u00c1ficas, Artes Pl\u00c1sticas (curso)",
    "sg:phone":"+34 933 75 21 14",
    "sg:postcode":"08940",
    "sg:province":"Barcelona",
    "wof:name":"Graficas Dueto S.c.p.",
    "wof:placetype":"venue"
},
  "geometry": {"coordinates":[2.0766348839,41.3641738892],"type":"Point"}
}