{
  "type": "Feature",
  "properties": {
    "addr:full":"Plza. De Abastos, S/n Velez-malaga M\u00e1laga 29700",
    "addr:housenumber":"s / n",
    "addr:postcode":"29700",
    "addr:street":"Plza.",
    "iso:country":"ES",
    "sg:address":"Plza. De Abastos, S/n",
    "sg:city":"Velez-malaga",
    "sg:orig_category":"Supermercados Y Hipermercados",
    "sg:phone":"+34 952 50 08 88",
    "sg:postcode":"29700",
    "sg:province":"M\u00e1laga",
    "wof:name":"Alimentacion Perez Nu\u00f1ez S.l.",
    "wof:placetype":"venue"
},
  "geometry": {"coordinates":[-4.141140461,36.7639465332],"type":"Point"}
}