{
  "type": "Feature",
  "properties": {
    "iso:country":"ES",
    "sg:address":"Pl Mercat, 4",
    "sg:city":"Palma",
    "sg:orig_category":"Asociaciones Humanitarias, De Cooperaci\u00d3n, De Acci\u00d3n Social",
    "sg:phone":"+34 971 72 28 56",
    "sg:postcode":"07001",
    "sg:province":"Islas Baleares",
    "wof:name":"Instituto De Reinsercion Social",
    "wof:placetype":"venue"
},
  "geometry": {"coordinates":[2.6486070156,39.5713195801],"type":"Point"}
}