{
  "type": "Feature",
  "properties": {
    "addr:full":"Rua Fonte De Santo Antonio (da), 6 Santiago De Compostela La Coru\u00f1a 15702",
    "addr:postcode":"15702",
    "addr:street":"Rua Fonte De Santo;Da;Corun\u0303A",
    "iso:country":"ES",
    "sg:address":"Rua Fonte De Santo Antonio (da), 6",
    "sg:city":"Santiago De Compostela",
    "sg:orig_category":"Estilistas Y Estudios De Estilo De Corte Y Confecci\u00d3n",
    "sg:phone":"+34 981 56 13 23",
    "sg:postcode":"15702",
    "sg:province":"La Coru\u00f1a",
    "wof:name":"Hnos Cierto Gestal S.l.",
    "wof:placetype":"venue"
},
  "geometry": {"coordinates":[-8.536397934,42.8636016846],"type":"Point"}
}