{
  "type": "Feature",
  "properties": {
    "iso:country":"ES",
    "sg:address":"Calle de Rosales, 15",
    "sg:city":"Aranda Duero",
    "sg:orig_category":"Plomeros",
    "sg:phone":"+34 947 50 84 46",
    "sg:postcode":"09400",
    "sg:province":"Burgos",
    "wof:name":"Comercial De La Ribera S.l.",
    "wof:placetype":"venue"
},
  "geometry": {"coordinates":[-3.6931269169,41.6659240723],"type":"Point"}
}