{
  "type": "Feature",
  "properties": {
    "addr:full":"Calle de Deporte (del), 2 Cordoba C\u00f3rdoba 14005",
    "addr:housenumber":"2",
    "addr:postcode":"14005",
    "addr:street":"Calle De Deporte Del;Co\u0301Rdoba",
    "iso:country":"ES",
    "sg:address":"Calle de Deporte (del), 2",
    "sg:city":"Cordoba",
    "sg:orig_category":"Agencias Y Agentes Comerciales, Representantes",
    "sg:phone":"+34 957 46 31 63",
    "sg:postcode":"14005",
    "sg:province":"C\u00f3rdoba",
    "wof:name":"Alvarez De Dios Jose",
    "wof:placetype":"venue"
},
  "geometry": {"coordinates":[-4.8137683868,37.8808631897],"type":"Point"}
}