{
  "type": "Feature",
  "properties": {
    "addr:full":"Carrer de Valencia, 182 Barcelona Barcelona 08011",
    "addr:housenumber":"182",
    "addr:postcode":"08011",
    "addr:street":"Carrer De Valencia",
    "iso:country":"ES",
    "sg:address":"Carrer de Valencia, 182",
    "sg:city":"Barcelona",
    "sg:orig_category":"Fabricaci\u00d3n De Juegos Y Juguetes",
    "sg:phone":"+34 934 53 08 58",
    "sg:postcode":"08011",
    "sg:province":"Barcelona",
    "wof:name":"Perez Felip Maria Azucena",
    "wof:placetype":"venue"
},
  "geometry": {"coordinates":[2.1567571163,41.3875770569],"type":"Point"}
}