{
  "type": "Feature",
  "properties": {
    "iso:country":"ES",
    "sg:address":"Cami Via, 28",
    "sg:city":"Viladecans",
    "sg:classifiers":[
        {
            "category":"Wholesale",
            "subcategory":"Construction Materials",
            "type":"Manufacturing & Wholesale Goods"
        }
    ],
    "sg:phone":"+34 936 38 12 55",
    "sg:postcode":"08840",
    "sg:province":"Barcelona",
    "sg:tags":[
        "de",
        "embotellado"
    ],
    "wof:name":"Suministraments Gamar S.l.",
    "wof:placetype":"venue"
},
  "geometry": {"coordinates":[2.0139598846,41.3045043945],"type":"Point"}
}