{
  "type": "Feature",
  "properties": {
    "addr:full":"Carrer de Sant Jordi, 1 Vic Barcelona 08500",
    "addr:housenumber":"1",
    "addr:postcode":"08500",
    "addr:street":"Carrer De Sant Jordi",
    "iso:country":"ES",
    "sg:address":"Carrer de Sant Jordi, 1",
    "sg:city":"Vic",
    "sg:orig_category":"Molduras, Junquillos, Listones Y Molduras Perforadas",
    "sg:phone":"+34 938 89 16 20",
    "sg:postcode":"08500",
    "sg:province":"Barcelona",
    "wof:name":"Mini Brindis S.c.p.",
    "wof:placetype":"venue"
},
  "geometry": {"coordinates":[2.2614650726,41.9309959412],"type":"Point"}
}