{
  "type": "Feature",
  "properties": {
    "iso:country":"ES",
    "sg:address":"Calle de Profesor Beltran Baguena, 4",
    "sg:city":"Valencia",
    "sg:orig_category":"Papeler\u00cdas, Librer\u00cdas",
    "sg:phone":"+34 963 46 31 01",
    "sg:postcode":"46009",
    "sg:province":"Valencia",
    "sg:website":"www.saimar.net",
    "wof:name":"Suministros Saimar S.l.",
    "wof:placetype":"venue"
},
  "geometry": {"coordinates":[-0.3890551925,39.4804420471],"type":"Point"}
}