{
  "type": "Feature",
  "properties": {
    "addr:full":"Rua Venezuela, 19 Celanova Ourense 32800",
    "addr:housenumber":"19",
    "addr:postcode":"32800",
    "addr:street":"Rua Venezuela",
    "iso:country":"ES",
    "sg:address":"Rua Venezuela, 19",
    "sg:city":"Celanova",
    "sg:orig_category":"Supermercados Y Hipermercados",
    "sg:phone":"+34 988 43 21 29",
    "sg:postcode":"32800",
    "sg:province":"Ourense",
    "wof:name":"Adela Maria Alimentacion S.l",
    "wof:placetype":"venue"
},
  "geometry": {"coordinates":[-7.9538669586,42.1564331055],"type":"Point"}
}