{
  "type": "Feature",
  "properties": {
    "iso:country":"ES",
    "sg:address":"Carr Metge Josep Mateu, 4",
    "sg:city":"Mancor Vall",
    "sg:orig_category":"Iglesia Cat\u00d3lica",
    "sg:phone":"+34 971 50 18 28",
    "sg:postcode":"07312",
    "sg:province":"Islas Baleares",
    "wof:name":"Obispado De Mallorca",
    "wof:placetype":"venue"
},
  "geometry": {"coordinates":[2.8792600632,39.748260498],"type":"Point"}
}