{
  "type": "Feature",
  "properties": {
    "iso:country":"ES",
    "sg:address":"Avda Francisco Montenegro, 11",
    "sg:city":"Huelva",
    "sg:orig_category":"Control T\u00c9cnico De Veh\u00cdculos",
    "sg:phone":"+34 959 25 80 75",
    "sg:postcode":"21001",
    "sg:province":"Huelva",
    "wof:name":"Verificaciones Industrialesde Andalucia S.a.",
    "wof:placetype":"venue"
},
  "geometry": {"coordinates":[-6.9519839287,37.2283668518],"type":"Point"}
}