{
  "type": "Feature",
  "properties": {
    "addr:full":"Av. Da Ponte(pol. Sabon), 24 Arteixo A Coru\u00f1a 15142",
    "addr:housenumber":"24",
    "addr:postcode":"15142",
    "addr:street":"Av. Da Ponte Pol. Sabon;Corun\u0303A",
    "iso:country":"ES",
    "sg:address":"Av. Da Ponte(pol. Sabon), 24",
    "sg:city":"Arteixo",
    "sg:orig_category":"Adaptaciones, Acondicionamientos Especiales Para Veh\u00cdculos, Veh\u00cdculos Industriales",
    "sg:phone":"+34 981 60 28 71",
    "sg:postcode":"15142",
    "sg:province":"A Coru\u00f1a",
    "sg:website":"www.veicar.com",
    "wof:name":"Veicar S. L.",
    "wof:placetype":"venue"
},
  "geometry": {"coordinates":[-8.50552845,43.3100395203],"type":"Point"}
}