{
  "type": "Feature",
  "properties": {
    "addr:full":"Carrer de Arenys De Mar, 1 Sentmenat Barcelona 08181",
    "addr:housenumber":"1",
    "addr:postcode":"08181",
    "addr:street":"Carrer De Arenys De Mar",
    "iso:country":"ES",
    "sg:address":"Carrer de Arenys De Mar, 1",
    "sg:city":"Sentmenat",
    "sg:orig_category":"Zapatos (al Por Menor)",
    "sg:phone":"+34 937 15 06 63",
    "sg:postcode":"08181",
    "sg:province":"Barcelona",
    "wof:name":"Nu\u00f1ez Cara Yolanda",
    "wof:placetype":"venue"
},
  "geometry": {"coordinates":[2.1331028938,41.6102371216],"type":"Point"}
}