{
  "type": "Feature",
  "properties": {
    "addr:full":"Avda Encina (de La), 17 Fuenlabrada Madrid 28942",
    "addr:housenumber":"17",
    "addr:postcode":"28942",
    "addr:street":"Avda Encina De La",
    "iso:country":"ES",
    "sg:address":"Avda Encina (de La), 17",
    "sg:city":"Fuenlabrada",
    "sg:orig_category":"Electricidad: Instaladores",
    "sg:phone":"+34 916 07 27 29",
    "sg:postcode":"28942",
    "sg:province":"Madrid",
    "wof:name":"Instalfire S.l.",
    "wof:placetype":"venue"
},
  "geometry": {"coordinates":[-3.8144409657,40.2979774475],"type":"Point"}
}