{
  "type": "Feature",
  "properties": {
    "addr:full":"Calle de San Sebastian (de), 7 Boadilla Del Monte Madrid 28660",
    "addr:postcode":"28660",
    "addr:street":"Calle De",
    "iso:country":"ES",
    "sg:address":"Calle de San Sebastian (de), 7",
    "sg:city":"Boadilla Del Monte",
    "sg:orig_category":"Pescader\u00cdas (al Por Menor)",
    "sg:phone":"+34 916 33 13 35",
    "sg:postcode":"28660",
    "sg:province":"Madrid",
    "wof:name":"Aparicio Freire Juan",
    "wof:placetype":"venue"
},
  "geometry": {"coordinates":[-3.8774454594,40.4060401917],"type":"Point"}
}