{
  "type": "Feature",
  "properties": {
    "iso:country":"ES",
    "sg:address":"Avda Vilari\u00d1o, 23",
    "sg:city":"Cambados",
    "sg:orig_category":"Asociaciones Y Clubs Deportivos",
    "sg:phone":"+34 986 52 49 38",
    "sg:postcode":"36630",
    "sg:province":"Pontevedra",
    "wof:name":"Vital Sport Cambados C.b",
    "wof:placetype":"venue"
},
  "geometry": {"coordinates":[-8.8133602142,42.515712738],"type":"Point"}
}