{
  "type": "Feature",
  "properties": {
    "addr:full":"Calle de Txirula, 6 Vitoria-gasteiz \u00c1lava 01006",
    "addr:housenumber":"6",
    "addr:postcode":"01006",
    "addr:street":"Calle De Txirula",
    "iso:country":"ES",
    "sg:address":"Calle de Txirula, 6",
    "sg:city":"Vitoria-gasteiz",
    "sg:orig_category":"Molduras, Junquillos, Listones Y Molduras Perforadas",
    "sg:phone":"+34 945 13 25 01",
    "sg:postcode":"01006",
    "sg:province":"\u00c1lava",
    "wof:name":"Ladritel Gasteiz S.l.",
    "wof:placetype":"venue"
},
  "geometry": {"coordinates":[-2.6659440994,42.8377418518],"type":"Point"}
}