{
  "type": "Feature",
  "properties": {
    "iso:country":"ES",
    "sg:address":"Avda Juan De Austria, 11",
    "sg:city":"Laguna Duero",
    "sg:orig_category":"Peluquer\u00cdas, Peluquer\u00cda Mixta",
    "sg:phone":"+34 983 52 78 96",
    "sg:postcode":"47140",
    "sg:province":"Valladolid",
    "wof:name":"Criado Morales Clara",
    "wof:placetype":"venue"
},
  "geometry": {"coordinates":[-4.725938797,41.5854034424],"type":"Point"}
}