{
  "type": "Feature",
  "properties": {
    "addr:full":"Calle de Poeta Trillo Figueroa, 5 Coru\u00d1a La Coru\u00f1a 15009",
    "addr:housenumber":"5",
    "addr:postcode":"15009",
    "addr:street":"Calle De Poeta Trillo Figueroa;La Corun\u0303A",
    "iso:country":"ES",
    "sg:address":"Calle de Poeta Trillo Figueroa, 5",
    "sg:city":"Coru\u00d1a",
    "sg:orig_category":"Sellos De Goma Y Met\u00c1licos",
    "sg:phone":"+34 981 13 20 77",
    "sg:postcode":"15009",
    "sg:province":"La Coru\u00f1a",
    "sg:website":"www.sminfante.com",
    "wof:name":"Infante Calvo Jose Maria Ramon",
    "wof:placetype":"venue"
},
  "geometry": {"coordinates":[-8.397687912,43.3540725708],"type":"Point"}
}