{
  "type": "Feature",
  "properties": {
    "addr:full":"Calle de Gibraltar, 19 Huesca Huesca 22006",
    "addr:housenumber":"19",
    "addr:postcode":"22006",
    "addr:street":"Calle De Gibraltar",
    "iso:country":"ES",
    "sg:address":"Calle de Gibraltar, 19",
    "sg:city":"Huesca",
    "sg:orig_category":"Frutas, Legumbres Frescas Y Tempranas (al Por Menor)",
    "sg:phone":"+34 974 22 15 40",
    "sg:postcode":"22006",
    "sg:province":"Huesca",
    "wof:name":"Fruterias Del Alto Gallego S. L.",
    "wof:placetype":"venue"
},
  "geometry": {"coordinates":[-0.3975462914,42.1422424316],"type":"Point"}
}