{
  "type": "Feature",
  "properties": {
    "iso:country":"ES",
    "sg:address":"Dehesa De Valdemimbre, S/n",
    "sg:city":"Sanzoles",
    "sg:orig_category":"Cr\u00cda De Animales",
    "sg:phone":"+34 980 56 91 79",
    "sg:postcode":"49152",
    "sg:province":"Zamora",
    "wof:name":"Fincas Agricolas Y Ganaderas En Explotacion S.a.",
    "wof:placetype":"venue"
},
  "geometry": {"coordinates":[-5.5670919418,41.4321861267],"type":"Point"}
}