{
  "type": "Feature",
  "properties": {
    "iso:country":"ES",
    "sg:address":"Lersundi Kalea, 23",
    "sg:city":"Deba",
    "sg:orig_category":"Molduras, Junquillos, Listones Y Molduras Perforadas",
    "sg:phone":"+34 943 19 13 55",
    "sg:postcode":"20820",
    "sg:province":"Guip\u00f9zcoa",
    "wof:name":"Irastorza Iriondo Karmele",
    "wof:placetype":"venue"
},
  "geometry": {"coordinates":[-2.3539190292,43.2945747375],"type":"Point"}
}