{
  "type": "Feature",
  "properties": {
    "addr:full":"Calle de San Francisco, S/n Molina Guadalajara 19300",
    "addr:postcode":"19300",
    "addr:street":"Calle De San Francisco S / N Molina",
    "iso:country":"ES",
    "sg:address":"Calle de San Francisco, S/n",
    "sg:city":"Molina",
    "sg:orig_category":"M\u00dasica Diversa",
    "sg:phone":"+34 949 83 17 25",
    "sg:postcode":"19300",
    "sg:province":"Guadalajara",
    "wof:name":"Asociacion De Padres De Alumnos E G B",
    "wof:placetype":"venue"
},
  "geometry": {"coordinates":[-1.8919634819,40.8426170349],"type":"Point"}
}