{
  "type": "Feature",
  "properties": {
    "iso:country":"ES",
    "sg:address":"Ptda Algoda, 149",
    "sg:city":"Algoda",
    "sg:orig_category":"Zapatos: Material, Suministros, Accesorios (fabricaci\u00d3n, Al Por Mayor)",
    "sg:phone":"+34 966 63 60 79",
    "sg:postcode":"03296",
    "sg:province":"Alicante",
    "wof:name":"Irefrank S.l.",
    "wof:placetype":"venue"
},
  "geometry": {"coordinates":[-0.7447530031,38.227268219],"type":"Point"}
}