{
  "type": "Feature",
  "properties": {
    "addr:full":"Avda Papa Luna, 4 Pe\u00f1iscola Castell\u00f3n 12598",
    "addr:housenumber":"4",
    "addr:postcode":"12598",
    "addr:street":"Avda Papa Luna;Castello\u0301N",
    "iso:country":"ES",
    "sg:address":"Avda Papa Luna, 4",
    "sg:city":"Pe\u00f1iscola",
    "sg:orig_category":"Inmobiliaria (agencias)",
    "sg:phone":"+34 964 48 97 85",
    "sg:postcode":"12598",
    "sg:province":"Castell\u00f3n",
    "wof:name":"Medimar Levante S.l.",
    "wof:placetype":"venue"
},
  "geometry": {"coordinates":[0.4023019969,40.3623390198],"type":"Point"}
}