{
  "type": "Feature",
  "properties": {
    "iso:country":"ES",
    "sg:address":"Calle de Antonio Machado, 19",
    "sg:city":"Madrid",
    "sg:orig_category":"Telas Y Sedas (al Por Menor)",
    "sg:phone":"+34 913 73 79 81",
    "sg:postcode":"28035",
    "sg:province":"Madrid",
    "wof:name":"Rivera Castro Maria Angeles",
    "wof:placetype":"venue"
},
  "geometry": {"coordinates":[-3.7197546959,40.4651145935],"type":"Point"}
}