{
  "type": "Feature",
  "properties": {
    "iso:country":"ES",
    "sg:address":"Calle de San Diego De Alcala, 5",
    "sg:city":"Palmas De Gran Canaria",
    "sg:orig_category":"Obras Y Organismos Sociales",
    "sg:phone":"+34 928 36 76 02",
    "sg:postcode":"35001",
    "sg:province":"Las Palmas",
    "wof:name":"A.f.a.e.s.",
    "wof:placetype":"venue"
},
  "geometry": {"coordinates":[-15.4174118042,28.1009426117],"type":"Point"}
}