{
  "type": "Feature",
  "properties": {
    "iso:country":"ES",
    "sg:address":"Avda Independencia (de La), 45",
    "sg:city":"San Sebastian De Los Reyes",
    "sg:orig_category":"Promotores Constructores",
    "sg:phone":"+34 916 53 70 20",
    "sg:postcode":"28700",
    "sg:province":"Madrid",
    "wof:name":"Procim Instalaciones S.l.",
    "wof:placetype":"venue"
},
  "geometry": {"coordinates":[-3.6348218918,40.5541572571],"type":"Point"}
}