{
  "type": "Feature",
  "properties": {
    "addr:full":"Calle de Corredera, 3 San Mateo Murcia 30800",
    "addr:housenumber":"3",
    "addr:postcode":"30800",
    "addr:street":"Calle De Corredera",
    "iso:country":"ES",
    "sg:address":"Calle de Corredera, 3",
    "sg:city":"San Mateo",
    "sg:orig_category":"Ropa Para Se\u00d1oras Y Caballeros (al Por Menor)",
    "sg:phone":"+34 968 44 37 33",
    "sg:postcode":"30800",
    "sg:province":"Murcia",
    "wof:name":"Comercial Montoya S. A.",
    "wof:placetype":"venue"
},
  "geometry": {"coordinates":[-1.1298867464,37.9834747314],"type":"Point"}
}