{
  "type": "Feature",
  "properties": {
    "addr:full":"Calle de Placido Pe\u00d1a, 21 Vilalba Lugo 27800",
    "addr:housenumber":"21",
    "addr:postcode":"27800",
    "addr:street":"Calle De Placido Pen\u0303A",
    "iso:country":"ES",
    "sg:address":"Calle de Placido Pe\u00d1a, 21",
    "sg:city":"Vilalba",
    "sg:orig_category":"Bancos",
    "sg:phone":"+34 982 51 03 87",
    "sg:postcode":"27800",
    "sg:province":"Lugo",
    "wof:name":"Banco Gallego S.a.",
    "wof:placetype":"venue"
},
  "geometry": {"coordinates":[-7.6788358688,43.3003425598],"type":"Point"}
}