{
  "type": "Feature",
  "properties": {
    "addr:full":"Carrer de B Pons I Fabregues, 16 Palma Islas Baleares 07007",
    "addr:housenumber":"16",
    "addr:postcode":"07007",
    "addr:street":"Carrer De;Fabregues",
    "iso:country":"ES",
    "sg:address":"Carrer de B Pons I Fabregues, 16",
    "sg:city":"Palma",
    "sg:orig_category":"Heladeros",
    "sg:phone":"+34 971 24 52 57",
    "sg:postcode":"07007",
    "sg:province":"Islas Baleares",
    "wof:name":"Aznar Domenech Juan Francisco",
    "wof:placetype":"venue"
},
  "geometry": {"coordinates":[2.667798996,39.5727615356],"type":"Point"}
}