{
  "type": "Feature",
  "properties": {
    "iso:country":"ES",
    "sg:address":"Calle de Albero Burillo, 16",
    "sg:city":"Zaragoza",
    "sg:orig_category":"Ingenier\u00cda, Centros De Estudios (diversos)",
    "sg:phone":"+34 976 39 14 21",
    "sg:postcode":"50001",
    "sg:province":"Zaragoza",
    "wof:name":"Sanagustin Sanz Mariano",
    "wof:placetype":"venue"
},
  "geometry": {"coordinates":[-0.8675833941,41.6509666443],"type":"Point"}
}