{
  "type": "Feature",
  "properties": {
    "iso:country":"ES",
    "sg:address":"Avda Bravo Murillo, 14",
    "sg:city":"Santa Cruz De Tenerife",
    "sg:orig_category":"Peluquer\u00cdas, Peluquer\u00cda Mixta",
    "sg:phone":"+34 922 21 23 55",
    "sg:postcode":"38003",
    "sg:province":"Santa Cruz De Tenerife",
    "wof:name":"Aguilera Amate Concepcion",
    "wof:placetype":"venue"
},
  "geometry": {"coordinates":[-16.2487430573,28.4637641907],"type":"Point"}
}