{
  "type": "Feature",
  "properties": {
    "iso:country":"ES",
    "sg:address":"Calle de Real, 3",
    "sg:city":"Ceuta",
    "sg:orig_category":"Bisuter\u00cda, Joyer\u00cda, Relojer\u00cda (al Por Menor)",
    "sg:phone":"+34 956 51 30 78",
    "sg:postcode":"51001",
    "sg:province":"Ceuta",
    "wof:name":"Antonio Benitez E Hijos S.l.",
    "wof:placetype":"venue"
},
  "geometry": {"coordinates":[-5.3078536987,35.8873901367],"type":"Point"}
}