{
  "type": "Feature",
  "properties": {
    "addr:full":"Av Esports (dels), 19 Agramunt Lleida 25310",
    "addr:housenumber":"19",
    "addr:postcode":"25310",
    "addr:street":"Av Esports Dels",
    "iso:country":"ES",
    "sg:address":"Av Esports (dels), 19",
    "sg:city":"Agramunt",
    "sg:orig_category":"Electricidad: Instaladores",
    "sg:phone":"+34 973 39 10 53",
    "sg:postcode":"25310",
    "sg:province":"Lleida",
    "wof:name":"Electricitat Josep Guixe S.c.p.",
    "wof:placetype":"venue"
},
  "geometry": {"coordinates":[1.1040879488,41.7831192017],"type":"Point"}
}