{
  "type": "Feature",
  "properties": {
    "addr:full":"Avda Espa\u00d1a (de), 36 Dos Hermanas Sevilla 41700",
    "addr:housenumber":"36",
    "addr:postcode":"41700",
    "addr:street":"Avda Espan\u0303A De",
    "iso:country":"ES",
    "sg:address":"Avda Espa\u00d1a (de), 36",
    "sg:city":"Dos Hermanas",
    "sg:orig_category":"Molduras, Junquillos, Listones Y Molduras Perforadas",
    "sg:phone":"+34 955 67 92 74",
    "sg:postcode":"41700",
    "sg:province":"Sevilla",
    "wof:name":"Ayllon Torres Carmen",
    "wof:placetype":"venue"
},
  "geometry": {"coordinates":[-5.9262709618,37.2919311523],"type":"Point"}
}