{
  "type": "Feature",
  "properties": {
    "addr:full":"Urb. Las Moreras, S/n Algaba Sevilla 41980",
    "addr:housenumber":"s / n",
    "addr:postcode":"41980",
    "addr:street":"Urb. Las Moreras",
    "iso:country":"ES",
    "sg:address":"Urb. Las Moreras, S/n",
    "sg:city":"Algaba",
    "sg:orig_category":"Centros De Educaci\u00d3n Especial",
    "sg:phone":"+34 955 78 86 94",
    "sg:postcode":"41980",
    "sg:province":"Sevilla",
    "wof:name":"Ayuntamiento De La Algaba",
    "wof:placetype":"venue"
},
  "geometry": {"coordinates":[-6.0153942108,37.4607162476],"type":"Point"}
}