{
  "type": "Feature",
  "properties": {
    "addr:full":"Calle de Cristo De La Sed, 74 Sevilla Sevilla 41005",
    "addr:housenumber":"74",
    "addr:postcode":"41005",
    "addr:street":"Calle De Cristo De La Sed",
    "iso:country":"ES",
    "sg:address":"Calle de Cristo De La Sed, 74",
    "sg:city":"Sevilla",
    "sg:orig_category":"Diet\u00c9tica: Productos Biol\u00d3gicos, Naturales Y Diet\u00c9ticos (fabricaci\u00d3n, Al Por Mayor)",
    "sg:phone":"+34 954 58 29 74",
    "sg:postcode":"41005",
    "sg:province":"Sevilla",
    "sg:website":"www.santiveri.es",
    "wof:name":"Casa Santiveri S.l.",
    "wof:placetype":"venue"
},
  "geometry": {"coordinates":[-5.9634594917,37.3827934265],"type":"Point"}
}