{
  "type": "Feature",
  "properties": {
    "addr:full":"Calle de Severo Ochoa, 18 Parla Madrid 28980",
    "addr:housenumber":"18",
    "addr:postcode":"28980",
    "addr:street":"Calle De Severo Ochoa",
    "iso:country":"ES",
    "sg:address":"Calle de Severo Ochoa, 18",
    "sg:city":"Parla",
    "sg:orig_category":"Agentes, Concesionarios Y Sucursales De Veh\u00cdculos",
    "sg:phone":"+34 916 05 54 48",
    "sg:postcode":"28980",
    "sg:province":"Madrid",
    "wof:name":"Garaje Centro S.l.",
    "wof:placetype":"venue"
},
  "geometry": {"coordinates":[-3.7718360424,40.2361679077],"type":"Point"}
}