{
  "type": "Feature",
  "properties": {
    "addr:full":"Carrer de Muntaner, 335 Barcelona Barcelona 08021",
    "addr:housenumber":"335",
    "addr:postcode":"08021",
    "addr:street":"Carrer De Muntaner",
    "iso:country":"ES",
    "sg:address":"Carrer de Muntaner, 335",
    "sg:city":"Barcelona",
    "sg:orig_category":"M\u00c9dicos: Cirug\u00cda General",
    "sg:phone":"+34 932 09 73 92",
    "sg:postcode":"08021",
    "sg:province":"Barcelona",
    "wof:name":"Alkhadra Suan Movin",
    "wof:placetype":"venue"
},
  "geometry": {"coordinates":[2.1445207596,41.3978691101],"type":"Point"}
}