{
  "type": "Feature",
  "properties": {
    "iso:country":"ES",
    "sg:address":"Plaz Vecinos, 8",
    "sg:city":"Toledo",
    "sg:orig_category":"Electricidad: Instaladores",
    "sg:phone":"+34 925 25 38 29",
    "sg:postcode":"45003",
    "sg:province":"Toledo",
    "wof:name":"Instalaciones Antonio De Los Reyes S.l.",
    "wof:placetype":"venue"
},
  "geometry": {"coordinates":[-4.0223407745,39.8701095581],"type":"Point"}
}