{
  "type": "Feature",
  "properties": {
    "addr:full":"Ctra Nacional Ii, 26 Jonquera Girona 17700",
    "addr:housenumber":"26",
    "addr:postcode":"17700",
    "addr:street":"Ctra Nacional Ii",
    "iso:country":"ES",
    "sg:address":"Ctra Nacional Ii, 26",
    "sg:city":"Jonquera",
    "sg:orig_category":"Productores Recolectores, Venta Directa De Vinos",
    "sg:phone":"+34 972 55 55 90",
    "sg:postcode":"17700",
    "sg:province":"Girona",
    "wof:name":"Cellers Catalans S.c.",
    "wof:placetype":"venue"
},
  "geometry": {"coordinates":[2.8718750477,42.4159698486],"type":"Point"}
}