{
  "type": "Feature",
  "properties": {
    "addr:full":"Avda Andalucia, 12 Punta Umbria Huelva 21100",
    "addr:housenumber":"12",
    "addr:postcode":"21100",
    "addr:street":"Avda Andalucia",
    "iso:country":"ES",
    "sg:address":"Avda Andalucia, 12",
    "sg:city":"Punta Umbria",
    "sg:orig_category":"Laboratorios Y Trabajos De Fotograf\u00cda, V\u00cddeo Y Cine",
    "sg:phone":"+34 959 31 42 56",
    "sg:postcode":"21100",
    "sg:province":"Huelva",
    "wof:name":"Alfonso Ramos Maria Del Rosario",
    "wof:placetype":"venue"
},
  "geometry": {"coordinates":[-6.9656820297,37.1834945679],"type":"Point"}
}