{
  "type": "Feature",
  "properties": {
    "addr:full":"Calle de Antonio Cumella, 23 Madrid Madrid 28030",
    "addr:housenumber":"23",
    "addr:postcode":"madrid;28030",
    "addr:street":"Calle De Antonio Cumella",
    "iso:country":"ES",
    "sg:address":"Calle de Antonio Cumella, 23",
    "sg:city":"Madrid",
    "sg:orig_category":"Frutas, Legumbres Frescas Y Tempranas (al Por Menor)",
    "sg:phone":"+34 913 71 02 37",
    "sg:postcode":"28030",
    "sg:province":"Madrid",
    "wof:name":"Wang  Shuangjing",
    "wof:placetype":"venue"
},
  "geometry": {"coordinates":[-3.6356630325,40.4106712341],"type":"Point"}
}