{
  "type": "Feature",
  "properties": {
    "iso:country":"ES",
    "sg:address":"Avda Salvador Allende, 61",
    "sg:city":"Gijon",
    "sg:orig_category":"Peluqueros: De Se\u00d1oras",
    "sg:phone":"+34 985 38 45 05",
    "sg:postcode":"33211",
    "sg:province":"Asturias",
    "wof:name":"Garcia Gonzalez Guadalupe",
    "wof:placetype":"venue"
},
  "geometry": {"coordinates":[-5.6863942146,43.5233383179],"type":"Point"}
}