{
  "type": "Feature",
  "properties": {
    "addr:full":"Carrer de Domenec Fins, 2 Montcada Centre Barcelona 08110",
    "addr:housenumber":"2",
    "addr:postcode":"08110",
    "addr:street":"Carrer De Domenec Fins",
    "iso:country":"ES",
    "sg:address":"Carrer de Domenec Fins, 2",
    "sg:city":"Montcada Centre",
    "sg:orig_category":"Imprenta",
    "sg:phone":"+34 935 64 28 22",
    "sg:postcode":"08110",
    "sg:province":"Barcelona",
    "wof:name":"Chaverri Arnal Luis",
    "wof:placetype":"venue"
},
  "geometry": {"coordinates":[2.1873528957,41.4866104126],"type":"Point"}
}