{
  "type": "Feature",
  "properties": {
    "iso:country":"ES",
    "sg:address":"Carretera De Peloche, S/n",
    "sg:city":"Herrera Duque",
    "sg:orig_category":"Bebidas",
    "sg:phone":"+34 924 65 08 58",
    "sg:postcode":"06670",
    "sg:province":"Badajoz",
    "wof:name":"Almacenes Las Cumbres De Herrera S.l.l.",
    "wof:placetype":"venue"
},
  "geometry": {"coordinates":[-5.0577521324,39.1685943604],"type":"Point"}
}