{
  "type": "Feature",
  "properties": {
    "addr:full":"Calle de Don Lope De Sosa, 34 Cordoba C\u00f3rdoba 14004",
    "addr:housenumber":"34",
    "addr:postcode":"14004",
    "addr:street":"Calle De Don Lope De Sosa;Co\u0301Rdoba",
    "iso:country":"ES",
    "sg:address":"Calle de Don Lope De Sosa, 34",
    "sg:city":"Cordoba",
    "sg:orig_category":"Bricolaje, Herramientas (al Por Menor)",
    "sg:phone":"+34 957 23 73 98",
    "sg:postcode":"14004",
    "sg:province":"C\u00f3rdoba",
    "wof:name":"Arcoase S.l.",
    "wof:placetype":"venue"
},
  "geometry": {"coordinates":[-4.7915530205,37.8799209595],"type":"Point"}
}