{
  "type": "Feature",
  "properties": {
    "addr:full":"Avda Fresnos, 24 Torrejon Ardoz Madrid 28850",
    "addr:housenumber":"24",
    "addr:postcode":"28850",
    "addr:street":"Avda Fresnos",
    "iso:country":"ES",
    "sg:address":"Avda Fresnos, 24",
    "sg:city":"Torrejon Ardoz",
    "sg:orig_category":"Escuelas De Maternidad P\u00dablicas",
    "sg:phone":"+34 916 77 58 95",
    "sg:postcode":"28850",
    "sg:province":"Madrid",
    "wof:name":"Andrea Y Sergio S.l",
    "wof:placetype":"venue"
},
  "geometry": {"coordinates":[-3.7003455162,40.4166908264],"type":"Point"}
}