{
  "type": "Feature",
  "properties": {
    "addr:full":"Avda Doctor Fleming, 32 Le\u00f3n Le\u00f3n 24009",
    "addr:housenumber":"32",
    "addr:postcode":"24009",
    "addr:street":"Avda Doctor Fleming;Leo\u0301N",
    "iso:country":"ES",
    "sg:address":"Avda Doctor Fleming, 32",
    "sg:city":"Le\u00f3n",
    "sg:orig_category":"Panader\u00cdas, Panader\u00cdas",
    "sg:phone":"+34 987 26 06 56",
    "sg:postcode":"24009",
    "sg:province":"Le\u00f3n",
    "wof:name":"Ablanedo Garcia Angel",
    "wof:placetype":"venue"
},
  "geometry": {"coordinates":[-5.585455,42.597111],"type":"Point"}
}