{
  "type": "Feature",
  "properties": {
    "addr:full":"Calle de Calvo, S/n Malaga M\u00e1laga 29007",
    "addr:housenumber":"s / n",
    "addr:postcode":"29007",
    "addr:street":"Calle De Calvo;Ma\u0301Laga",
    "iso:country":"ES",
    "sg:address":"Calle de Calvo, S/n",
    "sg:city":"Malaga",
    "sg:orig_category":"Cajas De Ahorro",
    "sg:phone":"+34 952 61 18 96",
    "sg:postcode":"29007",
    "sg:province":"M\u00e1laga",
    "wof:name":"Unicaja",
    "wof:placetype":"venue"
},
  "geometry": {"coordinates":[-4.4284172058,36.7182426453],"type":"Point"}
}