{
  "type": "Feature",
  "properties": {
    "iso:country":"ES",
    "sg:address":"P I Jaime I, S/n",
    "sg:city":"Benifaio",
    "sg:orig_category":"Sales (al Por Mayor)",
    "sg:phone":"+34 961 79 40 43",
    "sg:postcode":"46450",
    "sg:province":"Valencia",
    "wof:name":"Fabrica De Patatas Peladas S.l.",
    "wof:placetype":"venue"
},
  "geometry": {"coordinates":[-0.4321439862,39.2860641479],"type":"Point"}
}