{
  "type": "Feature",
  "properties": {
    "addr:full":"Calle de Joaquin Costa, 4 Utebo Zaragoza 50180",
    "addr:housenumber":"4",
    "addr:postcode":"50180",
    "addr:street":"Calle De Joaquin Costa",
    "iso:country":"ES",
    "sg:address":"Calle de Joaquin Costa, 4",
    "sg:city":"Utebo",
    "sg:orig_category":"Mercer\u00cda, Lencer\u00cda (al Por Menor)",
    "sg:phone":"+34 976 77 02 37",
    "sg:postcode":"50180",
    "sg:province":"Zaragoza",
    "wof:name":"Tame Borao Laura",
    "wof:placetype":"venue"
},
  "geometry": {"coordinates":[-0.995065093,41.7140922546],"type":"Point"}
}