{
  "type": "Feature",
  "properties": {
    "addr:full":"Cimadevilla, S/n Cimadevilla Asturias 33880",
    "addr:postcode":"33880",
    "addr:street":"Cimadevilla S / N Cimadevilla Asturias",
    "iso:country":"ES",
    "sg:address":"Cimadevilla, S/n",
    "sg:city":"Cimadevilla",
    "sg:orig_category":"Ambulancias",
    "sg:phone":"+34 985 80 73 55",
    "sg:postcode":"33880",
    "sg:province":"Asturias",
    "wof:name":"Alvarez Marcos Manuel",
    "wof:placetype":"venue"
},
  "geometry": {"coordinates":[-5.5425314903,43.531867981],"type":"Point"}
}