{
  "type": "Feature",
  "properties": {
    "iso:country":"ES",
    "sg:address":"Avda Jose Antonio, 17",
    "sg:city":"Suances",
    "sg:orig_category":"Florister\u00cdas",
    "sg:phone":"+34 942 84 43 55",
    "sg:postcode":"39340",
    "sg:province":"Cantabria",
    "wof:name":"Roiz Alonso Jose Manuel",
    "wof:placetype":"venue"
},
  "geometry": {"coordinates":[-4.0397157669,43.4230194092],"type":"Point"}
}