{
  "type": "Feature",
  "properties": {
    "iso:country":"ES",
    "sg:address":"Carrer de Estalvi (l'), 5",
    "sg:city":"Sitges",
    "sg:orig_category":"Empresas De Pintura Y Revestimientos",
    "sg:phone":"+34 938 94 22 45",
    "sg:postcode":"08870",
    "sg:province":"Barcelona",
    "wof:name":"Arbones Rubin Francisco",
    "wof:placetype":"venue"
},
  "geometry": {"coordinates":[1.8110184669,41.2421684265],"type":"Point"}
}