{
  "type": "Feature",
  "properties": {
    "addr:full":"Calle de Zumalakarregi, 11 Pasai Antxo Guip\u00f9zcoa 20110",
    "addr:housenumber":"11",
    "addr:postcode":"20110",
    "addr:street":"Calle De Zumalakarregi;Guipu\u0300Zcoa",
    "iso:country":"ES",
    "sg:address":"Calle de Zumalakarregi, 11",
    "sg:city":"Pasai Antxo",
    "sg:orig_category":"Centros De Coordinaci\u00d3n",
    "sg:phone":"+34 943 34 06 68",
    "sg:postcode":"20110",
    "sg:province":"Guip\u00f9zcoa",
    "wof:name":"Pasai Asesores C.b.",
    "wof:placetype":"venue"
},
  "geometry": {"coordinates":[-1.9177069664,43.3179740906],"type":"Point"}
}