{
  "type": "Feature",
  "properties": {
    "iso:country":"ES",
    "sg:address":"Sbid Hospital, 7",
    "sg:city":"Toledo",
    "sg:orig_category":"Promotores Constructores",
    "sg:phone":"+34 925 21 37 39",
    "sg:postcode":"45006",
    "sg:province":"Toledo",
    "wof:name":"Hijos De Victorino Ramos S.l.",
    "wof:placetype":"venue"
},
  "geometry": {"coordinates":[-4.0113267899,39.8610496521],"type":"Point"}
}