{
  "type": "Feature",
  "properties": {
    "addr:full":"Rbla Brasil, 49 Barcelona Barcelona 08028",
    "addr:housenumber":"49",
    "addr:postcode":"08028",
    "addr:street":"Rbla Brasil",
    "iso:country":"ES",
    "sg:address":"Rbla Brasil, 49",
    "sg:city":"Barcelona",
    "sg:orig_category":"Empresas De Portes Y Mensajer\u00cda",
    "sg:phone":"+34 934 11 05 34",
    "sg:postcode":"08028",
    "sg:province":"Barcelona",
    "wof:name":"Mittag Serveis S.l.",
    "wof:placetype":"venue"
},
  "geometry": {"coordinates":[2.1290569305,41.3784637451],"type":"Point"}
}