{
  "type": "Feature",
  "properties": {
    "iso:country":"ES",
    "sg:address":"Pg Doctor Moragas, 247",
    "sg:city":"Barbera Valles",
    "sg:orig_category":"Agencias De Viajes",
    "sg:phone":"+34 937 29 22 03",
    "sg:postcode":"08210",
    "sg:province":"Barcelona",
    "sg:website":"www.marsans.es",
    "wof:name":"Viajes Marsans S.a.",
    "wof:placetype":"venue"
},
  "geometry": {"coordinates":[2.1271760464,41.5150566101],"type":"Point"}
}