{
  "type": "Feature",
  "properties": {
    "addr:full":"Avda Costa Blanca, 51 Alacant Alicante 03540",
    "addr:housenumber":"51",
    "addr:postcode":"03540",
    "addr:street":"Avda Costa Blanca",
    "iso:country":"ES",
    "sg:address":"Avda Costa Blanca, 51",
    "sg:city":"Alacant",
    "sg:orig_category":"Agencias Y Agentes Comerciales, Representantes",
    "sg:phone":"+34 965 15 31 20",
    "sg:postcode":"03540",
    "sg:province":"Alicante",
    "wof:name":"Negrache Valero Agustin",
    "wof:placetype":"venue"
},
  "geometry": {"coordinates":[-0.4221999943,38.3568000793],"type":"Point"}
}