{
  "type": "Feature",
  "properties": {
    "addr:full":"Carrer de Velez Rubio, 34 Terrassa Barcelona 08225",
    "addr:housenumber":"34",
    "addr:postcode":"08225",
    "addr:street":"Carrer De Velez Rubio",
    "iso:country":"ES",
    "sg:address":"Carrer de Velez Rubio, 34",
    "sg:city":"Terrassa",
    "sg:orig_category":"Empresas De Carpinter\u00cda De Madera",
    "sg:phone":"+34 937 88 81 41",
    "sg:postcode":"08225",
    "sg:province":"Barcelona",
    "wof:name":"Granado Gonzalez Jose Luis",
    "wof:placetype":"venue"
},
  "geometry": {"coordinates":[2.0060989857,41.5799865723],"type":"Point"}
}