{
  "type": "Feature",
  "properties": {
    "iso:country":"ES",
    "sg:address":"Avda Furs, 32",
    "sg:city":"Aduanas",
    "sg:orig_category":"Inmobiliaria (agencias)",
    "sg:phone":"+34 966 46 24 12",
    "sg:postcode":"03730",
    "sg:province":"Alicante",
    "wof:name":"Port Maricel S.l.",
    "wof:placetype":"venue"
},
  "geometry": {"coordinates":[0.179727003,38.7924423218],"type":"Point"}
}