{
  "type": "Feature",
  "properties": {
    "iso:country":"ES",
    "sg:address":"Pase Estacion (de La), 5",
    "sg:city":"Navalcarnero",
    "sg:orig_category":"Agencias Y Asesores De Publicidad",
    "sg:phone":"+34 918 11 44 81",
    "sg:postcode":"28600",
    "sg:province":"Madrid",
    "wof:name":"Sanchez Sanchez Bego\u00f1a",
    "wof:placetype":"venue"
},
  "geometry": {"coordinates":[-4.0109210014,40.2931785583],"type":"Point"}
}