{
  "type": "Feature",
  "properties": {
    "addr:full":"Avda Pedro Morales Deniz, 173 Cardones Las Palmas 35400",
    "addr:housenumber":"173",
    "addr:postcode":"35400",
    "addr:street":"Avda Pedro Morales Deniz",
    "iso:country":"ES",
    "sg:address":"Avda Pedro Morales Deniz, 173",
    "sg:city":"Cardones",
    "sg:classifiers":[
        {
            "category":"Autos & Motor Vehicles",
            "subcategory":"Automobile Sales",
            "type":"Retail Goods"
        }
    ],
    "sg:phone":"+34 928 62 24 73",
    "sg:postcode":"35400",
    "sg:province":"Las Palmas",
    "sg:website":"www. autoescuelacarmelo.com",
    "wof:name":"Autoescuela Carmelo S.l.",
    "wof:placetype":"venue"
},
  "geometry": {"coordinates":[-15.5101318359,28.1140670776],"type":"Point"}
}