{
  "type": "Feature",
  "properties": {
    "addr:full":"Agustin Leitza Kalea, 5 Andoain Guip\u00f9zcoa 20140",
    "addr:housenumber":"5",
    "addr:postcode":"20140",
    "addr:street":"Agustin Leitza Kalea;Guipu\u0300Zcoa",
    "iso:country":"ES",
    "sg:address":"Agustin Leitza Kalea, 5",
    "sg:city":"Andoain",
    "sg:orig_category":"Panader\u00cdas, Panader\u00cdas",
    "sg:phone":"+34 943 59 03 03",
    "sg:postcode":"20140",
    "sg:province":"Guip\u00f9zcoa",
    "wof:name":"Jose Maria Galparsoro Maiza - Gozotegia I\u00f1axi",
    "wof:placetype":"venue"
},
  "geometry": {"coordinates":[-2.0204489231,43.2193183899],"type":"Point"}
}