{
  "type": "Feature",
  "properties": {
    "addr:full":"Calle de Jesus, 3 Mairena Alcor Sevilla 41510",
    "addr:housenumber":"3",
    "addr:postcode":"41510",
    "addr:street":"Calle De Jesus",
    "iso:country":"ES",
    "sg:address":"Calle de Jesus, 3",
    "sg:city":"Mairena Alcor",
    "sg:orig_category":"Cl\u00cdnicas Dentales",
    "sg:phone":"+34 955 74 44 87",
    "sg:postcode":"41510",
    "sg:province":"Sevilla",
    "wof:name":"Maidental S.l.",
    "wof:placetype":"venue"
},
  "geometry": {"coordinates":[-5.7525720596,37.373626709],"type":"Point"}
}