{
  "type": "Feature",
  "properties": {
    "addr:full":"Calle de Sorbas, 40 Carboneras Almer\u00eda 04140",
    "addr:housenumber":"40",
    "addr:postcode":"04140",
    "addr:street":"Calle De Sorbas",
    "iso:country":"ES",
    "sg:address":"Calle de Sorbas, 40",
    "sg:city":"Carboneras",
    "sg:orig_category":"Droguer\u00cdas (al Por Menor)",
    "sg:phone":"+34 950 13 03 23",
    "sg:postcode":"04140",
    "sg:province":"Almer\u00eda",
    "wof:name":"Frabelca Y Pealmer S.l.",
    "wof:placetype":"venue"
},
  "geometry": {"coordinates":[-1.8926390409,36.9983406067],"type":"Point"}
}