{
  "type": "Feature",
  "properties": {
    "addr:full":"Ctra Nacional 420, Km. 0143,7 Brazatortas Ciudad Real 13450",
    "addr:postcode":"13450",
    "addr:street":"Ctra Nacional 420 Km. 0143,7",
    "iso:country":"ES",
    "sg:address":"Ctra Nacional 420, Km. 0143,7",
    "sg:city":"Brazatortas",
    "sg:orig_category":"Distribuci\u00d3n De Petr\u00d3leo Y Derivados",
    "sg:phone":"+34 926 47 13 07",
    "sg:postcode":"13450",
    "sg:province":"Ciudad Real",
    "sg:website":"www.cepsa.es",
    "wof:name":"Calvo Camacho Victoriano",
    "wof:placetype":"venue"
},
  "geometry": {"coordinates":[-4.2914190292,38.6598701477],"type":"Point"}
}