{
  "type": "Feature",
  "properties": {
    "iso:country":"ES",
    "sg:address":"Calle de Burriana, 27",
    "sg:city":"Valencia",
    "sg:orig_category":"Abogados",
    "sg:phone":"+34 963 33 79 46",
    "sg:postcode":"46005",
    "sg:province":"Valencia",
    "wof:name":"Bort Llop Carlos",
    "wof:placetype":"venue"
},
  "geometry": {"coordinates":[-0.3660550117,39.4655532837],"type":"Point"}
}