{
  "type": "Feature",
  "properties": {
    "addr:full":"Rua Ramon Puga, 11 Ourense Ourense 32005",
    "addr:housenumber":"11",
    "addr:postcode":"32005",
    "addr:street":"Rua Ramon Puga",
    "iso:country":"ES",
    "sg:address":"Rua Ramon Puga, 11",
    "sg:city":"Ourense",
    "sg:orig_category":"Bisuter\u00cda, Joyer\u00cda, Relojer\u00cda (al Por Menor)",
    "sg:phone":"+34 988 23 49 04",
    "sg:postcode":"32005",
    "sg:province":"Ourense",
    "wof:name":"Lailia Joyas S.l.",
    "wof:placetype":"venue"
},
  "geometry": {"coordinates":[-7.8621168137,42.3291397095],"type":"Point"}
}