{
  "type": "Feature",
  "properties": {
    "iso:country":"ES",
    "sg:address":"Calle de San Marcos, 42",
    "sg:city":"Huelva",
    "sg:orig_category":"Muebles",
    "sg:phone":"+34 959 23 67 22",
    "sg:postcode":"21006",
    "sg:province":"Huelva",
    "wof:name":"Dorrego Reyes Israel",
    "wof:placetype":"venue"
},
  "geometry": {"coordinates":[-6.9354629517,37.2608680725],"type":"Point"}
}