{
  "type": "Feature",
  "properties": {
    "addr:full":"Txiplao Kalea, 15 Hondarribia Guip\u00f9zcoa 20280",
    "addr:housenumber":"15",
    "addr:postcode":"20280",
    "addr:street":"Txiplao Kalea;Guipu\u0300Zcoa",
    "iso:country":"ES",
    "sg:address":"Txiplao Kalea, 15",
    "sg:city":"Hondarribia",
    "sg:orig_category":"Cristaler\u00cdas",
    "sg:phone":"+34 943 64 31 83",
    "sg:postcode":"20280",
    "sg:province":"Guip\u00f9zcoa",
    "wof:name":"Oyarzabal Mu\u00f1oz I\u00f1aki",
    "wof:placetype":"venue"
},
  "geometry": {"coordinates":[-1.7975929976,43.3616867065],"type":"Point"}
}