{
  "type": "Feature",
  "properties": {
    "iso:country":"ES",
    "sg:address":"Calle de Padre Claret, 13",
    "sg:city":"Madrid",
    "sg:orig_category":"Aparcamientos (infraestructuras, Accesorios)",
    "sg:phone":"+34 914 13 75 55",
    "sg:postcode":"28002",
    "sg:province":"Madrid",
    "wof:name":"Puecon S.a.",
    "wof:placetype":"venue"
},
  "geometry": {"coordinates":[-3.6646990776,40.4468421936],"type":"Point"}
}