{
  "type": "Feature",
  "properties": {
    "iso:country":"ES",
    "sg:address":"Avda Rambleta, 38",
    "sg:city":"Catarroja",
    "sg:orig_category":"Carnicer\u00cdas, Carnicer\u00cdas",
    "sg:phone":"+34 961 27 27 86",
    "sg:postcode":"46470",
    "sg:province":"Valencia",
    "wof:name":"Carnicas Siglo Xxi",
    "wof:placetype":"venue"
},
  "geometry": {"coordinates":[-0.4059019983,39.4054069519],"type":"Point"}
}