{
  "type": "Feature",
  "properties": {
    "addr:full":"Estd Malata, S/n Ferrol La Coru\u00f1a 15401",
    "addr:housenumber":"s / n",
    "addr:postcode":"15401",
    "addr:street":"Malata;La Corun\u0303A",
    "iso:country":"ES",
    "sg:address":"Estd Malata, S/n",
    "sg:city":"Ferrol",
    "sg:orig_category":"Deportes Diversos",
    "sg:phone":"+34 981 37 06 00",
    "sg:postcode":"15401",
    "sg:province":"La Coru\u00f1a",
    "wof:name":"Federacion Gallega De Atletismo - Delegacion",
    "wof:placetype":"venue"
},
  "geometry": {"coordinates":[-8.2273387909,43.4868507385],"type":"Point"}
}