{
  "type": "Feature",
  "properties": {
    "addr:full":"Carrer de Vilamar, 2 Playa De Calafell Tarragona 43820",
    "addr:housenumber":"2",
    "addr:postcode":"43820",
    "addr:street":"Carrer De Vilamar",
    "iso:country":"ES",
    "sg:address":"Carrer de Vilamar, 2",
    "sg:city":"Playa De Calafell",
    "sg:orig_category":"Laboratorios Y Trabajos De Fotograf\u00cda, V\u00cddeo Y Cine",
    "sg:phone":"+34 977 69 23 02",
    "sg:postcode":"43820",
    "sg:province":"Tarragona",
    "wof:name":"De Heras Galiano Carlos",
    "wof:placetype":"venue"
},
  "geometry": {"coordinates":[1.5684100389,41.1977844238],"type":"Point"}
}