{
  "type": "Feature",
  "properties": {
    "addr:full":"Ctra. Menoyo, 22 Kexaa \u00c1lava 01478",
    "addr:housenumber":"22",
    "addr:postcode":"01478",
    "addr:street":"Ctra. Menoyo;A\u0301Lava",
    "iso:country":"ES",
    "sg:address":"Ctra. Menoyo, 22",
    "sg:city":"Kexaa",
    "sg:orig_category":"Ingeniero",
    "sg:phone":"+34 945 39 92 16",
    "sg:postcode":"01478",
    "sg:province":"\u00c1lava",
    "wof:name":"Galindez Aldecoa Luis",
    "wof:placetype":"venue"
},
  "geometry": {"coordinates":[-3.0630936623,43.0814857483],"type":"Point"}
}