{
  "type": "Feature",
  "properties": {
    "iso:country":"ES",
    "sg:address":"Herreria, S/n",
    "sg:city":"Hernan-perez",
    "sg:orig_category":"Cerrajer\u00cda, Ferrallista",
    "sg:phone":"+34 927 44 51 55",
    "sg:postcode":"10868",
    "sg:province":"C\u00e1ceres",
    "wof:name":"Jorge Tello Celedonio",
    "wof:placetype":"venue"
},
  "geometry": {"coordinates":[-6.4642438889,40.2120704651],"type":"Point"}
}