{
  "type": "Feature",
  "properties": {
    "iso:country":"ES",
    "sg:address":"Particular, S/n",
    "sg:city":"Villares Reina",
    "sg:orig_category":"Comercio De Muebles De Estilo Y Contempor\u00c1neos",
    "sg:phone":"+34 923 25 77 70",
    "sg:postcode":"37184",
    "sg:province":"Salamanca",
    "sg:website":"www.epocainternacional.com",
    "wof:name":"Epoca Internacional S.a.",
    "wof:placetype":"venue"
},
  "geometry": {"coordinates":[-5.6469841003,41.0071716309],"type":"Point"}
}