{
  "type": "Feature",
  "properties": {
    "addr:full":"Avda Ntra. Se\u00d1ora Del Carmen, 44 Corralejo Playa Las Palmas 35660",
    "addr:housenumber":"44",
    "addr:postcode":"35660",
    "addr:street":"Avda Ntra. Sen\u0303Ora Del Carmen;Playa Las Palmas",
    "iso:country":"ES",
    "sg:address":"Avda Ntra. Se\u00d1ora Del Carmen, 44",
    "sg:city":"Corralejo Playa",
    "sg:orig_category":"Farmacias",
    "sg:phone":"+34 928 86 60 20",
    "sg:postcode":"35660",
    "sg:province":"Las Palmas",
    "wof:name":"Soto Velazquez Maria Asuncion Paula",
    "wof:placetype":"venue"
},
  "geometry": {"coordinates":[-13.8689365387,28.736284256],"type":"Point"}
}