{
  "type": "Feature",
  "properties": {
    "iso:country":"ES",
    "sg:address":"Avda Reyes Catolicos, 16",
    "sg:city":"Alcala Henares",
    "sg:orig_category":"Pescader\u00cdas (al Por Menor)",
    "sg:phone":"+34 918 80 01 96",
    "sg:postcode":"28802",
    "sg:province":"Madrid",
    "wof:name":"Benito Fernandez Felipe",
    "wof:placetype":"venue"
},
  "geometry": {"coordinates":[-3.3738269806,40.477481842],"type":"Point"}
}