{
  "type": "Feature",
  "properties": {
    "addr:full":"Carrer de Prudenci, 24 Sabadell Barcelona 08206",
    "addr:housenumber":"24",
    "addr:postcode":"08206",
    "addr:street":"Carrer De Prudenci",
    "iso:country":"ES",
    "sg:address":"Carrer de Prudenci, 24",
    "sg:city":"Sabadell",
    "sg:orig_category":"Carnicer\u00cdas, Carnicer\u00cdas",
    "sg:phone":"+34 937 23 00 67",
    "sg:postcode":"08206",
    "sg:province":"Barcelona",
    "wof:name":"Diaz Gomez Luis",
    "wof:placetype":"venue"
},
  "geometry": {"coordinates":[2.0856449604,41.555393219],"type":"Point"}
}