{
  "type": "Feature",
  "properties": {
    "iso:country":"ES",
    "sg:address":"Calle de Necora, 7",
    "sg:city":"Granada",
    "sg:orig_category":"Psic\u00d3logos",
    "sg:phone":"+34 958 29 53 42",
    "sg:postcode":"18003",
    "sg:province":"Granada",
    "wof:name":"Centro De Psicologia Leblanc Y Mayo C.b.",
    "wof:placetype":"venue"
},
  "geometry": {"coordinates":[-3.6054260731,37.1703987122],"type":"Point"}
}