{
  "type": "Feature",
  "properties": {
    "addr:full":"Mallecina, S/n Mallecina Asturias 33867",
    "addr:postcode":"33867",
    "addr:street":"Mallecina S / N Mallecina Asturias",
    "iso:country":"ES",
    "sg:address":"Mallecina, S/n",
    "sg:city":"Mallecina",
    "sg:orig_category":"Charcuter\u00cdas (al Por Mayor)",
    "sg:phone":"+34 985 50 91 16",
    "sg:postcode":"33867",
    "sg:province":"Asturias",
    "wof:name":"Embuntidos La Venta C.b.",
    "wof:placetype":"venue"
},
  "geometry": {"coordinates":[-6.2219939232,43.4258537292],"type":"Point"}
}