{
  "type": "Feature",
  "properties": {
    "iso:country":"ES",
    "sg:address":"Calle de Chile, 10",
    "sg:city":"Matas-pinar-monte Rozas",
    "sg:orig_category":"Inform\u00c1tica Equipo Y Programas (al Por Mayor)",
    "sg:phone":"+34 916 30 66 36",
    "sg:postcode":"28290",
    "sg:province":"Madrid",
    "wof:name":"Avnet Iberia S.a.u.",
    "wof:placetype":"venue"
},
  "geometry": {"coordinates":[-3.9000730515,40.5436782837],"type":"Point"}
}