{
  "type": "Feature",
  "properties": {
    "iso:country":"ES",
    "sg:address":"Avda Angeles (de Los), 35",
    "sg:city":"Getafe",
    "sg:orig_category":"Trabajos De Fotocomposici\u00d3n",
    "sg:phone":"+34 916 01 80 23",
    "sg:postcode":"28903",
    "sg:province":"Madrid",
    "wof:name":"Tordesillas Sanchez Maria Montserrat",
    "wof:placetype":"venue"
},
  "geometry": {"coordinates":[-3.7196938992,40.3095169067],"type":"Point"}
}