{
  "type": "Feature",
  "properties": {
    "addr:full":"Ctra. Burgos, S/n Najera La Rioja 26300",
    "addr:housenumber":"s / n",
    "addr:postcode":"26300",
    "addr:street":"Ctra. Burgos;Najera La Rioja",
    "iso:country":"ES",
    "sg:address":"Ctra. Burgos, S/n",
    "sg:city":"Najera",
    "sg:orig_category":"Productores Recolectores, Venta Directa De Vinos",
    "sg:phone":"+34 941 36 02 45",
    "sg:postcode":"26300",
    "sg:province":"La Rioja",
    "wof:name":"Bodega Interlocal Cooperativa",
    "wof:placetype":"venue"
},
  "geometry": {"coordinates":[-2.7250440121,42.4189338684],"type":"Point"}
}