{
  "type": "Feature",
  "properties": {
    "addr:full":"Calle de Puerta De Cordoba, 26 Baeza Ja\u00e9n 23440",
    "addr:housenumber":"26",
    "addr:postcode":"23440",
    "addr:street":"Calle De Puerta De Cordoba",
    "iso:country":"ES",
    "sg:address":"Calle de Puerta De Cordoba, 26",
    "sg:city":"Baeza",
    "sg:orig_category":"Mec\u00c1nico Del Autom\u00d3vil",
    "sg:phone":"+34 953 74 18 80",
    "sg:postcode":"23440",
    "sg:province":"Ja\u00e9n",
    "wof:name":"Moreno Canovas Andres",
    "wof:placetype":"venue"
},
  "geometry": {"coordinates":[-3.4770739079,37.9920310974],"type":"Point"}
}