{
  "type": "Feature",
  "properties": {
    "addr:full":"Carretera De Magallon, Km. 0037,5 Ricla Zaragoza 50270",
    "addr:housenumber":"ricla",
    "addr:postcode":"50270",
    "addr:street":"Carretera De Magallon Km. 0037,5",
    "iso:country":"ES",
    "sg:address":"Carretera De Magallon, Km. 0037,5",
    "sg:city":"Ricla",
    "sg:orig_category":"Distribuci\u00d3n De Petr\u00d3leo Y Derivados",
    "sg:phone":"+34 976 60 63 55",
    "sg:postcode":"50270",
    "sg:province":"Zaragoza",
    "wof:name":"Estacion De Servicio Lusan S.cv.",
    "wof:placetype":"venue"
},
  "geometry": {"coordinates":[-1.3978689909,41.5160255432],"type":"Point"}
}