{
  "type": "Feature",
  "properties": {
    "iso:country":"ES",
    "sg:address":"D Juan De Austria, S/n",
    "sg:city":"Torrevieja",
    "sg:orig_category":"Muebles, Minoristas",
    "sg:phone":"+34 965 70 46 46",
    "sg:postcode":"03180",
    "sg:province":"Alicante",
    "wof:name":"Dowsing  Karen",
    "wof:placetype":"venue"
},
  "geometry": {"coordinates":[-0.6536790133,38.0173606873],"type":"Point"}
}