{
  "type": "Feature",
  "properties": {
    "addr:full":"Av Jaume I, 111 Mollet Valles Barcelona 08100",
    "addr:housenumber":"111",
    "addr:postcode":"08100",
    "addr:street":"Av Jaume I",
    "iso:country":"ES",
    "sg:address":"Av Jaume I, 111",
    "sg:city":"Mollet Valles",
    "sg:orig_category":"Venta, Alquiler De Instrumentos Y Accesorios De M\u00dasica",
    "sg:phone":"+34 935 93 25 97",
    "sg:postcode":"08100",
    "sg:province":"Barcelona",
    "sg:website":"www.mdvnet.com/musicalmollet",
    "wof:name":"Zarrias Torrico S.a.l.",
    "wof:placetype":"venue"
},
  "geometry": {"coordinates":[2.2140951157,41.5412635803],"type":"Point"}
}