{
  "type": "Feature",
  "properties": {
    "addr:full":"Tamadaba, 7 Cruce Y Playa Arinaga Las Palmas 35118",
    "addr:housenumber":"7",
    "addr:postcode":"35118",
    "addr:street":"Tamadaba;Y;Arinaga",
    "iso:country":"ES",
    "sg:address":"Tamadaba, 7",
    "sg:city":"Cruce Y Playa Arinaga",
    "sg:orig_category":"Asesor\u00cda Sobre Comunicaci\u00d3n De Empresas",
    "sg:phone":"+34 928 18 40 02",
    "sg:postcode":"35118",
    "sg:province":"Las Palmas",
    "wof:name":"Consulting Mari Carmen Viera S.l.",
    "wof:placetype":"venue"
},
  "geometry": {"coordinates":[-15.4311962128,27.8799304962],"type":"Point"}
}