{
  "type": "Feature",
  "properties": {
    "addr:full":"Carrer de Creu Roja, 42 Hospitalet Llobregat Barcelona 08904",
    "addr:housenumber":"42",
    "addr:postcode":"08904",
    "addr:street":"Carrer De Creu Roja",
    "iso:country":"ES",
    "sg:address":"Carrer de Creu Roja, 42",
    "sg:city":"Hospitalet Llobregat",
    "sg:orig_category":"Plomeros",
    "sg:phone":"+34 934 48 29 23",
    "sg:postcode":"08904",
    "sg:province":"Barcelona",
    "wof:name":"Martinez Cardo Isidoro",
    "wof:placetype":"venue"
},
  "geometry": {"coordinates":[2.1161019802,41.3756942749],"type":"Point"}
}