{
  "type": "Feature",
  "properties": {
    "addr:full":"Real, 161 El Higueral C\u00f3rdoba 14979",
    "addr:housenumber":"161",
    "addr:postcode":"14979",
    "addr:street":"Real;El Higueral Co\u0301Rdoba",
    "iso:country":"ES",
    "sg:address":"Real, 161",
    "sg:city":"El Higueral",
    "sg:orig_category":"Cajas Para Embalar",
    "sg:phone":"+34 957 59 20 51",
    "sg:postcode":"14979",
    "sg:province":"C\u00f3rdoba",
    "sg:website":"www.cajarural.com",
    "wof:name":"Caja Rural De Cordoba",
    "wof:placetype":"venue"
},
  "geometry": {"coordinates":[-4.2527389526,37.3176651001],"type":"Point"}
}