{
  "type": "Feature",
  "properties": {
    "addr:full":"Calle de Eugenio Caxes, 4 Madrid Madrid 28026",
    "addr:housenumber":"4",
    "addr:postcode":"28026",
    "addr:street":"Calle De Eugenio Caxes",
    "iso:country":"ES",
    "sg:address":"Calle de Eugenio Caxes, 4",
    "sg:city":"Madrid",
    "sg:orig_category":"Agencias Y Agentes Comerciales, Representantes",
    "sg:phone":"+34 914 76 30 89",
    "sg:postcode":"28026",
    "sg:province":"Madrid",
    "wof:name":"Jimenez Galvez Santiago",
    "wof:placetype":"venue"
},
  "geometry": {"coordinates":[-3.7029280663,40.3918380737],"type":"Point"}
}