{
  "type": "Feature",
  "properties": {
    "addr:full":"Carrer de Roger De Flor, 231 Barcelona Barcelona 08025",
    "addr:housenumber":"231",
    "addr:postcode":"08025",
    "addr:street":"Carrer De Roger De Flor",
    "iso:country":"ES",
    "sg:address":"Carrer de Roger De Flor, 231",
    "sg:city":"Barcelona",
    "sg:orig_category":"Centros Empresariales",
    "sg:phone":"+34 932 07 27 25",
    "sg:postcode":"08025",
    "sg:province":"Barcelona",
    "wof:name":"Hi - Print Sl",
    "wof:placetype":"venue"
},
  "geometry": {"coordinates":[2.1679129601,41.4022216797],"type":"Point"}
}