{
  "type": "Feature",
  "properties": {
    "addr:full":"Ctra. Murguia, 8 Apodaka \u00c1lava 01140",
    "addr:housenumber":"8",
    "addr:postcode":"01140",
    "addr:street":"Ctra. Murguia;A\u0301Lava",
    "iso:country":"ES",
    "sg:address":"Ctra. Murguia, 8",
    "sg:city":"Apodaka",
    "sg:orig_category":"Serrer\u00cdas De Madera",
    "sg:phone":"+34 945 46 01 52",
    "sg:postcode":"01140",
    "sg:province":"\u00c1lava",
    "wof:name":"Cengotitabengoa Aldama Ignacio",
    "wof:placetype":"venue"
},
  "geometry": {"coordinates":[-2.7300798893,42.917049408],"type":"Point"}
}