{
  "type": "Feature",
  "properties": {
    "iso:country":"ES",
    "sg:address":"Ptge Merce Rodoreda, 40",
    "sg:city":"Calella",
    "sg:orig_category":"Reposter\u00cdas",
    "sg:phone":"+34 937 66 19 84",
    "sg:postcode":"08370",
    "sg:province":"Barcelona",
    "wof:name":"Garriga Quintana Jose",
    "wof:placetype":"venue"
},
  "geometry": {"coordinates":[2.6659049988,41.619644165],"type":"Point"}
}