{
  "type": "Feature",
  "properties": {
    "addr:full":"Rua Dr. Carracido, 119 Vigo Pontevedra 36205",
    "addr:housenumber":"119",
    "addr:postcode":"36205",
    "addr:street":"Rua Dr. Carracido",
    "iso:country":"ES",
    "sg:address":"Rua Dr. Carracido, 119",
    "sg:city":"Vigo",
    "sg:orig_category":"Promotores Constructores",
    "sg:phone":"+34 986 37 22 17",
    "sg:postcode":"36205",
    "sg:province":"Pontevedra",
    "wof:name":"Alvarez Crespo S.l.",
    "wof:placetype":"venue"
},
  "geometry": {"coordinates":[-8.7023267746,42.2271118164],"type":"Point"}
}