{
  "type": "Feature",
  "properties": {
    "addr:full":"Calle de Erreka, 20 Elorrio Vizcaya 48230",
    "addr:housenumber":"20",
    "addr:postcode":"48230",
    "addr:street":"Calle De Erreka",
    "iso:country":"ES",
    "sg:address":"Calle de Erreka, 20",
    "sg:city":"Elorrio",
    "sg:orig_category":"Arquitectos",
    "sg:phone":"+34 946 23 18 47",
    "sg:postcode":"48230",
    "sg:province":"Vizcaya",
    "wof:name":"Urruchi Arcarazo Silvia",
    "wof:placetype":"venue"
},
  "geometry": {"coordinates":[-2.5442519188,43.1312904358],"type":"Point"}
}