{
  "type": "Feature",
  "properties": {
    "addr:full":"Carrer de Joan Xxiii, 9 Terrassa Barcelona 08227",
    "addr:housenumber":"9",
    "addr:postcode":"08227",
    "addr:street":"Carrer De Joan Xxiii",
    "iso:country":"ES",
    "sg:address":"Carrer de Joan Xxiii, 9",
    "sg:city":"Terrassa",
    "sg:orig_category":"Zapatos (al Por Menor)",
    "sg:phone":"+34 937 31 58 78",
    "sg:postcode":"08227",
    "sg:province":"Barcelona",
    "wof:name":"Aparicio Latorre Eleuterio",
    "wof:placetype":"venue"
},
  "geometry": {"coordinates":[2.0357131958,41.5696754456],"type":"Point"}
}