{
  "type": "Feature",
  "properties": {
    "iso:country":"ES",
    "sg:address":"Calle de Redondela, 1",
    "sg:city":"Zamora",
    "sg:orig_category":"Empresas De Carpinter\u00cda De Madera",
    "sg:phone":"+34 980 53 41 72",
    "sg:postcode":"49027",
    "sg:province":"Zamora",
    "wof:name":"Alvarez Gomez Antonio",
    "wof:placetype":"venue"
},
  "geometry": {"coordinates":[-5.7469620705,41.4936943054],"type":"Point"}
}