{
  "type": "Feature",
  "properties": {
    "addr:full":"Calle de Caveda, 43 Gijon Asturias 33209",
    "addr:housenumber":"43",
    "addr:postcode":"33209",
    "addr:street":"Calle De Caveda",
    "iso:country":"ES",
    "sg:address":"Calle de Caveda, 43",
    "sg:city":"Gijon",
    "sg:orig_category":"Art\u00cdculos De Regalo (al Por Menor)",
    "sg:phone":"+34 985 38 09 55",
    "sg:postcode":"33209",
    "sg:province":"Asturias",
    "wof:name":"Servicios Urbanisticos Asturias S.l.",
    "wof:placetype":"venue"
},
  "geometry": {"coordinates":[-5.6617269516,43.5340156555],"type":"Point"}
}