{
  "type": "Feature",
  "properties": {
    "iso:country":"ES",
    "sg:address":"Avda Jose Maria Del Campo Llarena, 19",
    "sg:city":"Puerto Cruz",
    "sg:orig_category":"Sindicatos De Trabajadores",
    "sg:phone":"+34 922 38 53 38",
    "sg:postcode":"38400",
    "sg:province":"Santa Cruz De Tenerife",
    "wof:name":"Union General De Trabajadores De Canarias",
    "wof:placetype":"venue"
},
  "geometry": {"coordinates":[-16.5570335388,28.4135951996],"type":"Point"}
}