{
  "type": "Feature",
  "properties": {
    "iso:country":"ES",
    "sg:address":"Calle de Fuerte De Navidad, 30",
    "sg:city":"Madrid",
    "sg:orig_category":"Asociaciones Y Clubs Deportivos",
    "sg:phone":"+34 917 05 76 89",
    "sg:postcode":"28044",
    "sg:province":"Madrid",
    "wof:name":"Gimenez Ruiz Mirian",
    "wof:placetype":"venue"
},
  "geometry": {"coordinates":[-3.7662680149,40.3826637268],"type":"Point"}
}