{
  "type": "Feature",
  "properties": {
    "iso:country":"ES",
    "sg:address":"Carr Comtes D'urgell, 13",
    "sg:city":"Lleida",
    "sg:orig_category":"Promotores Constructores",
    "sg:phone":"+34 973 23 57 04",
    "sg:postcode":"25004",
    "sg:province":"Lleida",
    "wof:name":"Escarp Miranda Manuel",
    "wof:placetype":"venue"
},
  "geometry": {"coordinates":[0.6294059753,41.6208381653],"type":"Point"}
}