{
  "type": "Feature",
  "properties": {
    "addr:full":"Calle de Brujula, 30 Mairena Aljarafe Sevilla 41927",
    "addr:housenumber":"30",
    "addr:postcode":"41927",
    "addr:street":"Calle De Brujula",
    "iso:country":"ES",
    "sg:address":"Calle de Brujula, 30",
    "sg:city":"Mairena Aljarafe",
    "sg:orig_category":"Chapister\u00cda",
    "sg:phone":"+34 954 18 70 47",
    "sg:postcode":"41927",
    "sg:province":"Sevilla",
    "wof:name":"Hijos De A. Ruiz Roman S.l.",
    "wof:placetype":"venue"
},
  "geometry": {"coordinates":[-6.0567994118,37.3557357788],"type":"Point"}
}