{
  "type": "Feature",
  "properties": {
    "iso:country":"ES",
    "sg:address":"Calle de Julio Moreno Davila, 9",
    "sg:city":"Granada",
    "sg:orig_category":"Carnicer\u00cdas, Carnicer\u00cdas",
    "sg:phone":"+34 958 15 63 06",
    "sg:postcode":"18011",
    "sg:province":"Granada",
    "wof:name":"Fernandez Quiros Aurelio",
    "wof:placetype":"venue"
},
  "geometry": {"coordinates":[-3.5993249416,37.2032737732],"type":"Point"}
}