{
  "type": "Feature",
  "properties": {
    "iso:country":"ES",
    "sg:address":"Av Diagonal, 433",
    "sg:city":"Barcelona",
    "sg:orig_category":"M\u00c9dicos: Neurolog\u00cda",
    "sg:phone":"+34 932 00 75 34",
    "sg:postcode":"08036",
    "sg:province":"Barcelona",
    "wof:name":"Subirana Cantarell Manuel",
    "wof:placetype":"venue"
},
  "geometry": {"coordinates":[2.1512110233,41.3941192627],"type":"Point"}
}