{
  "type": "Feature",
  "properties": {
    "addr:full":"Avda Conde De Guadalhorce, 37 Aviles Asturias 33401",
    "addr:housenumber":"37",
    "addr:postcode":"33401",
    "addr:street":"Avda Conde De Guadalhorce",
    "iso:country":"ES",
    "sg:address":"Avda Conde De Guadalhorce, 37",
    "sg:city":"Aviles",
    "sg:orig_category":"Chapister\u00cda",
    "sg:phone":"+34 985 56 78 63",
    "sg:postcode":"33401",
    "sg:province":"Asturias",
    "wof:name":"Garcia Zu\u00f1iga Francisco",
    "wof:placetype":"venue"
},
  "geometry": {"coordinates":[-5.9221143723,43.5646057129],"type":"Point"}
}