{
  "type": "Feature",
  "properties": {
    "addr:full":"Barr Vallejas, 3 Ace\u00d1a Vizcaya 48191",
    "addr:housenumber":"3",
    "addr:postcode":"48191",
    "addr:street":"Vallejas",
    "iso:country":"ES",
    "sg:address":"Barr Vallejas, 3",
    "sg:city":"Ace\u00d1a",
    "sg:orig_category":"Montaje (empresas De)",
    "sg:phone":"+34 946 10 01 00",
    "sg:postcode":"48191",
    "sg:province":"Vizcaya",
    "wof:name":"Euskamon S.a.",
    "wof:placetype":"venue"
},
  "geometry": {"coordinates":[-3.0992720127,43.2543907166],"type":"Point"}
}