{
  "type": "Feature",
  "properties": {
    "iso:country":"ES",
    "sg:address":"Ptge Rosers, 1",
    "sg:city":"Argentona",
    "sg:orig_category":"Pod\u00d3logos: Pedicuros",
    "sg:phone":"+34 937 97 02 60",
    "sg:postcode":"08310",
    "sg:province":"Barcelona",
    "wof:name":"Ramon Belon Marian",
    "wof:placetype":"venue"
},
  "geometry": {"coordinates":[2.4012460709,41.5552139282],"type":"Point"}
}