{
  "type": "Feature",
  "properties": {
    "addr:full":"Calle de Rollo, 67 Tui Pontevedra 36712",
    "addr:housenumber":"67",
    "addr:postcode":"36712",
    "addr:street":"Calle De Rollo",
    "iso:country":"ES",
    "sg:address":"Calle de Rollo, 67",
    "sg:city":"Tui",
    "sg:orig_category":"Alimentaci\u00d3n General (al Por Menor)",
    "sg:phone":"+34 986 60 19 38",
    "sg:postcode":"36712",
    "sg:province":"Pontevedra",
    "wof:name":"Martinez Rodriguez Josefina",
    "wof:placetype":"venue"
},
  "geometry": {"coordinates":[-8.6441287994,42.0515594482],"type":"Point"}
}