{
  "type": "Feature",
  "properties": {
    "addr:full":"Av Rei Pere I (del), 1 Arbo\u00e7 Tarragona 43720",
    "addr:housenumber":"1",
    "addr:postcode":"43720",
    "addr:street":"Av Rei Pere I Del",
    "iso:country":"ES",
    "sg:address":"Av Rei Pere I (del), 1",
    "sg:city":"Arbo\u00e7",
    "sg:orig_category":"Construcci\u00d3n Mec\u00c1nica",
    "sg:phone":"+34 977 67 12 05",
    "sg:postcode":"43720",
    "sg:province":"Tarragona",
    "wof:name":"Daro Construccions Mecaniques S.l.",
    "wof:placetype":"venue"
},
  "geometry": {"coordinates":[1.5991439819,41.2648620605],"type":"Point"}
}