{
  "type": "Feature",
  "properties": {
    "addr:full":"C. Serreria (p I Villarrosa), 20 Malaga M\u00e1laga 29002",
    "addr:housenumber":"20",
    "addr:postcode":"29002",
    "addr:street":"Villarrosa;Ma\u0301Laga",
    "iso:country":"ES",
    "sg:address":"C. Serreria (p I Villarrosa), 20",
    "sg:city":"Malaga",
    "sg:orig_category":"Electricidad: Instaladores",
    "sg:phone":"+34 952 17 36 89",
    "sg:postcode":"29002",
    "sg:province":"M\u00e1laga",
    "wof:name":"Pinsapos De Malaga S.l.",
    "wof:placetype":"venue"
},
  "geometry": {"coordinates":[-4.4739179611,36.6738395691],"type":"Point"}
}