{
  "type": "Feature",
  "properties": {
    "iso:country":"ES",
    "sg:address":"Carr Nou D'octubre, 55",
    "sg:city":"Gandia",
    "sg:orig_category":"Alimentaci\u00d3n General (al Por Menor)",
    "sg:phone":"+34 962 87 05 53",
    "sg:postcode":"46700",
    "sg:province":"Valencia",
    "wof:name":"Telepollo Express S.l.",
    "wof:placetype":"venue"
},
  "geometry": {"coordinates":[-0.1934490055,38.9626426697],"type":"Point"}
}