{
  "type": "Feature",
  "properties": {
    "addr:full":"Calle de Virgen De Aranzazu, 35 Madrid Madrid 28034",
    "addr:housenumber":"35",
    "addr:postcode":"madrid;28034",
    "addr:street":"Calle De Virgen De Aranzazu",
    "iso:country":"ES",
    "sg:address":"Calle de Virgen De Aranzazu, 35",
    "sg:city":"Madrid",
    "sg:orig_category":"Ebanister\u00cda",
    "sg:phone":"+34 913 58 32 51",
    "sg:postcode":"28034",
    "sg:province":"Madrid",
    "wof:name":"Galan Fuentes Fermin",
    "wof:placetype":"venue"
},
  "geometry": {"coordinates":[-3.6895320415,40.4870948792],"type":"Point"}
}