{
  "type": "Feature",
  "properties": {
    "addr:full":"Calle de Arce, 53 Poligono Industrial De Arinaga Las Palmas 35118",
    "addr:housenumber":"53 poligono",
    "addr:postcode":"35118",
    "addr:street":"Calle De Arce;Industrial De Arinaga Las",
    "iso:country":"ES",
    "sg:address":"Calle de Arce, 53",
    "sg:city":"Poligono Industrial De Arinaga",
    "sg:orig_category":"Fabricaci\u00d3n De Juguetes Autom\u00c1ticos",
    "sg:phone":"+34 928 75 21 49",
    "sg:postcode":"35118",
    "sg:province":"Las Palmas",
    "wof:name":"Automaticos Cefoblal S.l.",
    "wof:placetype":"venue"
},
  "geometry": {"coordinates":[-15.3927698135,27.8557987213],"type":"Point"}
}