{
  "type": "Feature",
  "properties": {
    "iso:country":"ES",
    "sg:address":"Carr Federico Garcia Lorca, 36",
    "sg:city":"Alfas Pi",
    "sg:orig_category":"Pintura Y Barniz (al Por Menor)",
    "sg:phone":"+34 966 86 05 09",
    "sg:postcode":"03580",
    "sg:province":"Alicante",
    "wof:name":"Devesa Such Miguel",
    "wof:placetype":"venue"
},
  "geometry": {"coordinates":[-0.1014759988,38.5785675049],"type":"Point"}
}