{
  "type": "Feature",
  "properties": {
    "iso:country":"ES",
    "sg:address":"Calle de Aire, 2",
    "sg:city":"Albatana",
    "sg:orig_category":"Centros De Educaci\u00d3n Especial",
    "sg:phone":"+34 967 32 32 63",
    "sg:postcode":"02653",
    "sg:province":"Albacete",
    "wof:name":"Laguna De Alboraj",
    "wof:placetype":"venue"
},
  "geometry": {"coordinates":[-1.5209563971,38.571144104],"type":"Point"}
}