{
  "type": "Feature",
  "properties": {
    "iso:country":"ES",
    "sg:address":"Carrer de Marques De Monistrol, 14",
    "sg:city":"Sant Feliu Llobregat",
    "sg:orig_category":"Ortopedia General",
    "sg:phone":"+34 936 66 55 23",
    "sg:postcode":"08980",
    "sg:province":"Barcelona",
    "wof:name":"Assessorament I Mobilitat S.l.",
    "wof:placetype":"venue"
},
  "geometry": {"coordinates":[2.0541396141,41.3842697144],"type":"Point"}
}