{
  "type": "Feature",
  "properties": {
    "iso:country":"ES",
    "sg:address":"Foru Kalea, 58",
    "sg:city":"Beasain",
    "sg:orig_category":"Plomeros",
    "sg:phone":"+34 943 88 94 41",
    "sg:postcode":"20200",
    "sg:province":"Guip\u00f9zcoa",
    "wof:name":"Gorostidi Echeverria Jose Miguel",
    "wof:placetype":"venue"
},
  "geometry": {"coordinates":[-2.2094089985,43.0488014221],"type":"Point"}
}