{
  "type": "Feature",
  "properties": {
    "addr:full":"Avda Puente De Carlos Iii, 48 Reinosa Cantabria 39200",
    "addr:housenumber":"48",
    "addr:postcode":"39200",
    "addr:street":"Avda Puente De Carlos Iii",
    "iso:country":"ES",
    "sg:address":"Avda Puente De Carlos Iii, 48",
    "sg:city":"Reinosa",
    "sg:orig_category":"Carnicer\u00cdas, Carnicer\u00cdas",
    "sg:phone":"+34 942 75 44 38",
    "sg:postcode":"39200",
    "sg:province":"Cantabria",
    "wof:name":"Argueso Valenciaga Jose Manuel",
    "wof:placetype":"venue"
},
  "geometry": {"coordinates":[-4.1399154663,42.9967803955],"type":"Point"}
}