{
  "type": "Feature",
  "properties": {
    "addr:full":"Plaz Reyes Catolicos, 13 Ba\u00d1eza Le\u00f3n 24750",
    "addr:housenumber":"13",
    "addr:postcode":"24750",
    "addr:street":"Plaz Reyes Catolicos;Leo\u0301N",
    "iso:country":"ES",
    "sg:address":"Plaz Reyes Catolicos, 13",
    "sg:city":"Ba\u00d1eza",
    "sg:orig_category":"Electrodom\u00c9sticos (al Por Menor)",
    "sg:phone":"+34 987 64 12 54",
    "sg:postcode":"24750",
    "sg:province":"Le\u00f3n",
    "wof:name":"Castro Lobato Elias",
    "wof:placetype":"venue"
},
  "geometry": {"coordinates":[-5.9242091179,42.3069114685],"type":"Point"}
}