{
  "type": "Feature",
  "properties": {
    "addr:full":"Carretera Galera, 4 Sta. Barbara Tarragona 43570",
    "addr:housenumber":"4 sta.",
    "addr:postcode":"43570",
    "addr:street":"Carretera Galera;Barbara Tarragona",
    "iso:country":"ES",
    "sg:address":"Carretera Galera, 4",
    "sg:city":"Sta. Barbara",
    "sg:orig_category":"Empresas De Carpinter\u00cda De Madera",
    "sg:phone":"+34 977 71 82 38",
    "sg:postcode":"43570",
    "sg:province":"Tarragona",
    "wof:name":"Moline Mobiliari S.l.",
    "wof:placetype":"venue"
},
  "geometry": {"coordinates":[0.490209192,40.7140274048],"type":"Point"}
}