{
  "type": "Feature",
  "properties": {
    "iso:country":"ES",
    "sg:address":"Calle de Cura Jesus Zaragoza, 2",
    "sg:city":"Petrer",
    "sg:orig_category":"Caf\u00c9s, Bares, Cervecer\u00cdas",
    "sg:phone":"+34 965 37 37 00",
    "sg:postcode":"03610",
    "sg:province":"Alicante",
    "wof:name":"Ramon Martinez Miguel Angel",
    "wof:placetype":"venue"
},
  "geometry": {"coordinates":[-0.7776303291,38.4838104248],"type":"Point"}
}