{
  "type": "Feature",
  "properties": {
    "iso:country":"ES",
    "sg:address":"Pg Estacio, 8",
    "sg:city":"Cellera Ter",
    "sg:orig_category":"Electrodom\u00c9sticos (fabricaci\u00d3n, Al Por Mayor)",
    "sg:phone":"+34 972 42 30 85",
    "sg:postcode":"17165",
    "sg:province":"Girona",
    "wof:name":"Collell Vila Joan",
    "wof:placetype":"venue"
},
  "geometry": {"coordinates":[2.6224799156,41.9692459106],"type":"Point"}
}