{
  "type": "Feature",
  "properties": {
    "addr:full":"Calle de Rafael Quintana Rosado, 13 Torremolinos M\u00e1laga 29620",
    "addr:housenumber":"13",
    "addr:postcode":"29620",
    "addr:street":"Calle De Rafael Quintana Rosado;Ma\u0301Laga",
    "iso:country":"ES",
    "sg:address":"Calle de Rafael Quintana Rosado, 13",
    "sg:city":"Torremolinos",
    "sg:orig_category":"Albergues",
    "sg:phone":"+34 952 38 66 08",
    "sg:postcode":"29620",
    "sg:province":"M\u00e1laga",
    "wof:name":"Mu\u00f1oz Ramos Manuel",
    "wof:placetype":"venue"
},
  "geometry": {"coordinates":[-4.504899025,36.6223373413],"type":"Point"}
}