{
  "type": "Feature",
  "properties": {
    "iso:country":"ES",
    "sg:address":"Calle de Palancia, 39",
    "sg:city":"Puerto",
    "sg:orig_category":"Peluquer\u00cdas, Peluquer\u00cda Mixta",
    "sg:phone":"+34 962 68 35 12",
    "sg:postcode":"46520",
    "sg:province":"Valencia",
    "wof:name":"Villarroya Martinez Silvia",
    "wof:placetype":"venue"
},
  "geometry": {"coordinates":[-0.218911007,39.6620445251],"type":"Point"}
}