{
  "type": "Feature",
  "properties": {
    "addr:full":"Calle de Federico Baraibar, 36 Vitoria-gasteiz \u00c1lava 01003",
    "addr:housenumber":"36",
    "addr:postcode":"01003",
    "addr:street":"Calle De Federico Baraibar",
    "iso:country":"ES",
    "sg:address":"Calle de Federico Baraibar, 36",
    "sg:city":"Vitoria-gasteiz",
    "sg:orig_category":"Internados & Ense\u00d1anza Privada",
    "sg:phone":"+34 945 28 40 00",
    "sg:postcode":"01003",
    "sg:province":"\u00c1lava",
    "wof:name":"Colegio Calasanz De Vitoria",
    "wof:placetype":"venue"
},
  "geometry": {"coordinates":[-2.6605389118,42.8428688049],"type":"Point"}
}