{
  "type": "Feature",
  "properties": {
    "addr:full":"Calle de Cavia, Mariano, 5 Huesca Huesca 22005",
    "addr:housenumber":"5",
    "addr:postcode":"22005",
    "addr:street":"Calle De Cavia Mariano",
    "iso:country":"ES",
    "sg:address":"Calle de Cavia, Mariano, 5",
    "sg:city":"Huesca",
    "sg:orig_category":"Construcci\u00d3n De Edificios Residenciales Y No Residenciales",
    "sg:phone":"+34 974 21 41 31",
    "sg:postcode":"22005",
    "sg:province":"Huesca",
    "wof:name":"Construcciones Y Promociones Fuster Y Mur S.l.",
    "wof:placetype":"venue"
},
  "geometry": {"coordinates":[-0.3983829021,42.1219940186],"type":"Point"}
}