{
  "type": "Feature",
  "properties": {
    "iso:country":"ES",
    "sg:address":"Calle de Capitan Fillol, 37",
    "sg:city":"Valdepe\u00f1as",
    "sg:orig_category":"Abogados",
    "sg:phone":"+34 926 32 08 50",
    "sg:postcode":"13300",
    "sg:province":"Ciudad Real",
    "wof:name":"Galan Rubio Salvador",
    "wof:placetype":"venue"
},
  "geometry": {"coordinates":[-3.3887937069,38.7617835999],"type":"Point"}
}