{
  "type": "Feature",
  "properties": {
    "addr:full":"Calle de Tiburcio (el), 12 Arrecife Las Palmas 35500",
    "addr:postcode":"35500",
    "addr:street":"Calle De Tiburcio",
    "iso:country":"ES",
    "sg:address":"Calle de Tiburcio (el), 12",
    "sg:city":"Arrecife",
    "sg:orig_category":"Reposter\u00cdas",
    "sg:phone":"+34 928 80 71 96",
    "sg:postcode":"35500",
    "sg:province":"Las Palmas",
    "wof:name":"Jaizme Cardoso Jose",
    "wof:placetype":"venue"
},
  "geometry": {"coordinates":[-13.5544595718,28.9585819244],"type":"Point"}
}