{
  "type": "Feature",
  "properties": {
    "iso:country":"ES",
    "sg:address":"Calle de Libertad (de La), 7",
    "sg:city":"Velilla S.antonio",
    "sg:orig_category":"Bricolaje, Herramientas (al Por Menor)",
    "sg:phone":"+34 916 60 83 49",
    "sg:postcode":"28891",
    "sg:province":"Madrid",
    "wof:name":"Armarios Liber C.b.",
    "wof:placetype":"venue"
},
  "geometry": {"coordinates":[-3.4857134819,40.3683013916],"type":"Point"}
}