{
  "type": "Feature",
  "properties": {
    "iso:country":"ES",
    "sg:address":"Avda Constitucion (la), 6",
    "sg:city":"Olivos-la Postura",
    "sg:orig_category":"Ropa Para Se\u00d1oras (al Por Menor)",
    "sg:phone":"+34 922 71 05 76",
    "sg:postcode":"38670",
    "sg:province":"Santa Cruz De Tenerife",
    "wof:name":"Trujillo Galvan Pedro",
    "wof:placetype":"venue"
},
  "geometry": {"coordinates":[-16.727935791,28.121887207],"type":"Point"}
}