{
  "type": "Feature",
  "properties": {
    "addr:full":"Rua Xulian Estevez, 18 Vigo Pontevedra 36207",
    "addr:housenumber":"18",
    "addr:postcode":"36207",
    "addr:street":"Rua Xulian Estevez",
    "iso:country":"ES",
    "sg:address":"Rua Xulian Estevez, 18",
    "sg:city":"Vigo",
    "sg:orig_category":"Institutos De Belleza",
    "sg:phone":"+34 986 43 01 42",
    "sg:postcode":"36207",
    "sg:province":"Pontevedra",
    "wof:name":"Lorenzo Lage Rosana",
    "wof:placetype":"venue"
},
  "geometry": {"coordinates":[-8.7062520981,42.243812561],"type":"Point"}
}