{
  "type": "Feature",
  "properties": {
    "addr:full":"Avda Constitucion (de La), 27 Mostoles Madrid 28931",
    "addr:housenumber":"27",
    "addr:postcode":"28931",
    "addr:street":"Avda Constitucion De La",
    "iso:country":"ES",
    "sg:address":"Avda Constitucion (de La), 27",
    "sg:city":"Mostoles",
    "sg:orig_category":"M\u00c9dicos: Estomatolog\u00cda",
    "sg:phone":"+34 916 18 30 76",
    "sg:postcode":"28931",
    "sg:province":"Madrid",
    "wof:name":"Rubio Marin Jose Manuel",
    "wof:placetype":"venue"
},
  "geometry": {"coordinates":[-3.8630979061,40.3247833252],"type":"Point"}
}