{
  "type": "Feature",
  "properties": {
    "iso:country":"ES",
    "sg:address":"Avda Abrigos (los), 31",
    "sg:city":"Abrigos",
    "sg:orig_category":"Supermercados Y Hipermercados",
    "sg:phone":"+34 922 17 03 93",
    "sg:postcode":"38639",
    "sg:province":"Santa Cruz De Tenerife",
    "wof:name":"Hernandez Martin Candelaria",
    "wof:placetype":"venue"
},
  "geometry": {"coordinates":[-16.5880699158,28.0302257538],"type":"Point"}
}