{
  "type": "Feature",
  "properties": {
    "iso:country":"ES",
    "sg:address":"Calle de Princesa De Eboli, 9",
    "sg:city":"Madrid",
    "sg:orig_category":"Ingenier\u00cda, Centros De Estudios (diversos)",
    "sg:phone":"+34 917 67 84 55",
    "sg:postcode":"28050",
    "sg:province":"Madrid",
    "wof:name":"Cervantes Mu\u00f1oz Juan Antonio",
    "wof:placetype":"venue"
},
  "geometry": {"coordinates":[-3.6557719707,40.4868545532],"type":"Point"}
}