{
  "type": "Feature",
  "properties": {
    "addr:full":"Calle de Carretera, 16 Mata De Los Olmos Teruel 44557",
    "addr:housenumber":"16",
    "addr:postcode":"44557",
    "addr:street":"Calle De Carretera",
    "iso:country":"ES",
    "sg:address":"Calle de Carretera, 16",
    "sg:city":"Mata De Los Olmos",
    "sg:orig_category":"Molduras, Junquillos, Listones Y Molduras Perforadas",
    "sg:phone":"+34 978 84 94 85",
    "sg:postcode":"44557",
    "sg:province":"Teruel",
    "wof:name":"Monforte Gascon Rosa",
    "wof:placetype":"venue"
},
  "geometry": {"coordinates":[-0.5202140808,40.8646850586],"type":"Point"}
}