{
  "type": "Feature",
  "properties": {
    "iso:country":"ES",
    "sg:address":"Carrer de Isabel Vilella, 3",
    "sg:city":"Bellvei",
    "sg:orig_category":"Laboratorios Y Trabajos De Fotograf\u00cda, V\u00cddeo Y Cine",
    "sg:phone":"+34 977 16 82 58",
    "sg:postcode":"43719",
    "sg:province":"Tarragona",
    "wof:name":"Vidal Fototrans S.l.",
    "wof:placetype":"venue"
},
  "geometry": {"coordinates":[1.5751069784,41.2390823364],"type":"Point"}
}