{
  "type": "Feature",
  "properties": {
    "iso:country":"ES",
    "sg:address":"Carrer de Galicia, 86",
    "sg:city":"Terrassa",
    "sg:orig_category":"Industria Qu\u00cdmica",
    "sg:phone":"+34 937 84 07 00",
    "sg:postcode":"08223",
    "sg:province":"Barcelona",
    "wof:name":"Lederplus Quimica S.l.",
    "wof:placetype":"venue"
},
  "geometry": {"coordinates":[2.0130178928,41.5511322021],"type":"Point"}
}