{
  "type": "Feature",
  "properties": {
    "addr:full":"Avda Rodriguez De Ledesma, S/n Caceres C\u00e1ceres 10001",
    "addr:housenumber":"s / n",
    "addr:postcode":"10001",
    "addr:street":"Avda Rodriguez De Ledesma;Ca\u0301Ceres",
    "iso:country":"ES",
    "sg:address":"Avda Rodriguez De Ledesma, S/n",
    "sg:city":"Caceres",
    "sg:orig_category":"Agricultores, Agricultores",
    "sg:phone":"+34 927 22 54 93",
    "sg:postcode":"10001",
    "sg:province":"C\u00e1ceres",
    "wof:name":"Asociacion De Criadores De Limusines De Extremadura",
    "wof:placetype":"venue"
},
  "geometry": {"coordinates":[-6.3851647377,39.4713096619],"type":"Point"}
}