{
  "type": "Feature",
  "properties": {
    "addr:full":"Calle de Campo, 110 Tomelloso Ciudad Real 13700",
    "addr:housenumber":"110",
    "addr:postcode":"13700",
    "addr:street":"Calle De Campo",
    "iso:country":"ES",
    "sg:address":"Calle de Campo, 110",
    "sg:city":"Tomelloso",
    "sg:orig_category":"Maquinaria Para Industrias Diversas",
    "sg:phone":"+34 926 51 58 41",
    "sg:postcode":"13700",
    "sg:province":"Ciudad Real",
    "wof:name":"Perona Lara Jesus",
    "wof:placetype":"venue"
},
  "geometry": {"coordinates":[-3.0225090981,39.1650619507],"type":"Point"}
}