{
  "type": "Feature",
  "properties": {
    "addr:full":"Calle de Rio Duero, 3 Arganda Madrid 28500",
    "addr:housenumber":"3",
    "addr:postcode":"28500",
    "addr:street":"Calle De Rio Duero",
    "iso:country":"ES",
    "sg:address":"Calle de Rio Duero, 3",
    "sg:city":"Arganda",
    "sg:orig_category":"Veh\u00cdculos De Ocasi\u00d3n",
    "sg:phone":"+34 918 71 78 73",
    "sg:postcode":"28500",
    "sg:province":"Madrid",
    "wof:name":"Talleres Carpel S.l.",
    "wof:placetype":"venue"
},
  "geometry": {"coordinates":[-3.4607005119,40.3012161255],"type":"Point"}
}