{
  "type": "Feature",
  "properties": {
    "addr:full":"Ctra Cortes, 17 Borja Zaragoza 50540",
    "addr:housenumber":"17",
    "addr:postcode":"50540",
    "addr:street":"Ctra Cortes",
    "iso:country":"ES",
    "sg:address":"Ctra Cortes, 17",
    "sg:city":"Borja",
    "sg:orig_category":"Cervezas (negociantes Y Depositarios)",
    "sg:phone":"+34 976 85 21 41",
    "sg:postcode":"50540",
    "sg:province":"Zaragoza",
    "wof:name":"La Zaragozana S.a.",
    "wof:placetype":"venue"
},
  "geometry": {"coordinates":[-1.5298639536,41.8342857361],"type":"Point"}
}