{
  "type": "Feature",
  "properties": {
    "addr:full":"Calle de Sierra De Quilama, S/n Guijuelo Salamanca 37770",
    "addr:housenumber":"s / n",
    "addr:postcode":"37770",
    "addr:street":"Calle De Sierra De Quilama",
    "iso:country":"ES",
    "sg:address":"Calle de Sierra De Quilama, S/n",
    "sg:city":"Guijuelo",
    "sg:orig_category":"Art\u00cdculos De Aluminio",
    "sg:phone":"+34 923 58 03 39",
    "sg:postcode":"37770",
    "sg:province":"Salamanca",
    "wof:name":"Cerrajeria Y Montajes Elices S.l.",
    "wof:placetype":"venue"
},
  "geometry": {"coordinates":[-5.6754989624,40.5379981995],"type":"Point"}
}