{
  "type": "Feature",
  "properties": {
    "addr:full":"Calle de Pedro Perez Fernandez, 25 Sevilla Sevilla 41011",
    "addr:housenumber":"25",
    "addr:postcode":"41011",
    "addr:street":"Calle De Pedro Perez Fernandez",
    "iso:country":"ES",
    "sg:address":"Calle de Pedro Perez Fernandez, 25",
    "sg:city":"Sevilla",
    "sg:orig_category":"Comercio De Muebles De Estilo Y Contempor\u00c1neos",
    "sg:phone":"+34 954 45 05 60",
    "sg:postcode":"41011",
    "sg:province":"Sevilla",
    "sg:website":"www.loscertalesmlb.com",
    "wof:name":"Barrio Brun Maria Luisa",
    "wof:placetype":"venue"
},
  "geometry": {"coordinates":[-6.0006141663,37.3744659424],"type":"Point"}
}