{
  "type": "Feature",
  "properties": {
    "addr:full":"Trav. Babia, S/n Villaseca Laciana Le\u00f3n 24140",
    "addr:housenumber":"s / n",
    "addr:postcode":"24140",
    "addr:street":"Babia;Villaseca Laciana Leo\u0301N",
    "iso:country":"ES",
    "sg:address":"Trav. Babia, S/n",
    "sg:city":"Villaseca Laciana",
    "sg:orig_category":"Cajas De Ahorro",
    "sg:phone":"+34 987 48 36 50",
    "sg:postcode":"24140",
    "sg:province":"Le\u00f3n",
    "sg:website":"www.cajaespana.es",
    "wof:name":"Caja Espa\u00f1a De Inversiones Caja De Ahorros Y Monte De Piedad",
    "wof:placetype":"venue"
},
  "geometry": {"coordinates":[-6.2490539551,42.9433898926],"type":"Point"}
}