{
  "type": "Feature",
  "properties": {
    "iso:country":"ES",
    "sg:address":"Calle de Santa Teresa, 4",
    "sg:city":"Almansa",
    "sg:orig_category":"Asistencia Social",
    "sg:phone":"+34 967 31 23 60",
    "sg:postcode":"02640",
    "sg:province":"Albacete",
    "wof:name":"Asprona-centro Ocupacional",
    "wof:placetype":"venue"
},
  "geometry": {"coordinates":[-1.0937124491,38.8658218384],"type":"Point"}
}