{
  "type": "Feature",
  "properties": {
    "iso:country":"ES",
    "sg:address":"Calle de Ribera Del Loira, 12",
    "sg:city":"Madrid",
    "sg:orig_category":"Centros Empresariales",
    "sg:phone":"+34 914 11 96 61",
    "sg:postcode":"28042",
    "sg:province":"Madrid",
    "wof:name":"Ac Camerfirma S.a.",
    "wof:placetype":"venue"
},
  "geometry": {"coordinates":[-3.625150919,40.4671821594],"type":"Point"}
}