{
  "type": "Feature",
  "properties": {
    "iso:country":"ES",
    "sg:address":"Calle de Padre Manjon, 29",
    "sg:city":"Elda",
    "sg:orig_category":"Reposter\u00cdas",
    "sg:phone":"+34 965 38 16 84",
    "sg:postcode":"03600",
    "sg:province":"Alicante",
    "wof:name":"Pan J H S.l.",
    "wof:placetype":"venue"
},
  "geometry": {"coordinates":[-0.7941560149,38.4752540588],"type":"Point"}
}