{
  "type": "Feature",
  "properties": {
    "iso:country":"ES",
    "sg:address":"Calle de Fuenterrabia, 20",
    "sg:city":"Donostia-san Sebastian",
    "sg:orig_category":"Peluquer\u00cdas, Peluquer\u00cda Mixta",
    "sg:phone":"+34 943 42 07 85",
    "sg:postcode":"20005",
    "sg:province":"Guip\u00f9zcoa",
    "wof:name":"Garmendia Gorostizu Victor",
    "wof:placetype":"venue"
},
  "geometry": {"coordinates":[-1.9816198349,43.3179779053],"type":"Point"}
}