{
  "type": "Feature",
  "properties": {
    "addr:full":"Carr Guillem Santandreu, 30 Lloseta Islas Baleares 07360",
    "addr:housenumber":"30",
    "addr:postcode":"07360",
    "addr:street":"Carr Guillem Santandreu",
    "iso:country":"ES",
    "sg:address":"Carr Guillem Santandreu, 30",
    "sg:city":"Lloseta",
    "sg:orig_category":"Bisuter\u00cda, Joyer\u00cda, Relojer\u00cda (al Por Menor)",
    "sg:phone":"+34 971 51 46 91",
    "sg:postcode":"07360",
    "sg:province":"Islas Baleares",
    "wof:name":"Cerezo Moragues S.l.",
    "wof:placetype":"venue"
},
  "geometry": {"coordinates":[2.8661179543,39.7179107666],"type":"Point"}
}