{
  "type": "Feature",
  "properties": {
    "iso:country":"ES",
    "sg:address":"Trva Zaldoko, 4",
    "sg:city":"Ola",
    "sg:orig_category":"Plomeros",
    "sg:phone":"+34 948 33 72 60",
    "sg:postcode":"31486",
    "sg:province":"Navarra",
    "wof:name":"Machicot Aznar Jose Miguel",
    "wof:placetype":"venue"
},
  "geometry": {"coordinates":[-1.5519039631,42.8252906799],"type":"Point"}
}