{
  "type": "Feature",
  "properties": {
    "addr:full":"Calle de Elias Serrano, 36 Minas Riotinto Huelva 21660",
    "addr:housenumber":"36",
    "addr:postcode":"21660",
    "addr:street":"Calle De Elias Serrano",
    "iso:country":"ES",
    "sg:address":"Calle de Elias Serrano, 36",
    "sg:city":"Minas Riotinto",
    "sg:classifiers":[
        {
            "category":"Autos & Motor Vehicles",
            "subcategory":"Automobile Sales",
            "type":"Retail Goods"
        }
    ],
    "sg:phone":"+34 959 59 17 10",
    "sg:postcode":"21660",
    "sg:province":"Huelva",
    "wof:name":"Autoescuela L-matamoros (gilabert L-matamoros S.c.",
    "wof:placetype":"venue"
},
  "geometry": {"coordinates":[-6.5930275917,37.6919975281],"type":"Point"}
}