{
  "type": "Feature",
  "properties": {
    "addr:full":"Ctra Loeches-alcala De Henares (de), 3 Cantos Azules Madrid 28890",
    "addr:postcode":"28890",
    "addr:street":"Ctra Loeches-Alcala",
    "iso:country":"ES",
    "sg:address":"Ctra Loeches-alcala De Henares (de), 3",
    "sg:city":"Cantos Azules",
    "sg:orig_category":"Tintes (fabricaci\u00d3n, Al Por Mayor)",
    "sg:phone":"+34 918 86 20 84",
    "sg:postcode":"28890",
    "sg:province":"Madrid",
    "wof:name":"Siegwerk Spain S.a.u.",
    "wof:placetype":"venue"
},
  "geometry": {"coordinates":[-3.4122691154,40.3848457336],"type":"Point"}
}