{
  "type": "Feature",
  "properties": {
    "iso:country":"ES",
    "sg:address":"Calle de Zarautz, 66",
    "sg:city":"Donostia-san Sebastian",
    "sg:orig_category":"Ense\u00d1anza: Idiomas",
    "sg:phone":"+34 943 21 74 19",
    "sg:postcode":"20018",
    "sg:province":"Guip\u00f9zcoa",
    "wof:name":"Elorza Bereciartu Maria Carmen Isabel",
    "wof:placetype":"venue"
},
  "geometry": {"coordinates":[-2.0068159103,43.3069534302],"type":"Point"}
}