{
  "type": "Feature",
  "properties": {
    "addr:full":"Avda Vega (p I Antequera), 5 Antequera M\u00e1laga 29200",
    "addr:housenumber":"5",
    "addr:postcode":"29200",
    "addr:street":"Avda Vega P;Antequera",
    "iso:country":"ES",
    "sg:address":"Avda Vega (p I Antequera), 5",
    "sg:city":"Antequera",
    "sg:orig_category":"Chapister\u00cda",
    "sg:phone":"+34 952 84 46 43",
    "sg:postcode":"29200",
    "sg:province":"M\u00e1laga",
    "wof:name":"Auto Hermanos Herrera S.l.",
    "wof:placetype":"venue"
},
  "geometry": {"coordinates":[-4.5397868156,37.0284004211],"type":"Point"}
}