{
  "type": "Feature",
  "properties": {
    "addr:full":"Calle de Roger De Flor, 12 Zaragoza Zaragoza 50017",
    "addr:housenumber":"12",
    "addr:postcode":"50017",
    "addr:street":"Calle De Roger De Flor",
    "iso:country":"ES",
    "sg:address":"Calle de Roger De Flor, 12",
    "sg:city":"Zaragoza",
    "sg:orig_category":"Administradores De Bienes Y Delegados De Comunidades De Propietarios",
    "sg:phone":"+34 976 53 59 54",
    "sg:postcode":"50017",
    "sg:province":"Zaragoza",
    "wof:name":"Admyges S. Coop.",
    "wof:placetype":"venue"
},
  "geometry": {"coordinates":[-0.9166668057,41.6480827332],"type":"Point"}
}