{
  "type": "Feature",
  "properties": {
    "iso:country":"ES",
    "sg:address":"Calle de Gonzalez Giron, 7",
    "sg:city":"Carmona",
    "sg:orig_category":"Pr\u00c9stamos Personales E Hipotecarios",
    "sg:phone":"+34 954 14 01 57",
    "sg:postcode":"41410",
    "sg:province":"Sevilla",
    "wof:name":"Rojo Guerra Enrique",
    "wof:placetype":"venue"
},
  "geometry": {"coordinates":[-5.6421451569,37.4717826843],"type":"Point"}
}