{
  "type": "Feature",
  "properties": {
    "addr:full":"Calle de Maria, 8 Gevora Caudillo Badajoz 06180",
    "addr:housenumber":"8",
    "addr:postcode":"06180",
    "addr:street":"Calle De Maria",
    "iso:country":"ES",
    "sg:address":"Calle de Maria, 8",
    "sg:city":"Gevora Caudillo",
    "sg:orig_category":"Cajas De Ahorro",
    "sg:phone":"+34 924 43 02 54",
    "sg:postcode":"06180",
    "sg:province":"Badajoz",
    "sg:website":"www.elmonte.es",
    "wof:name":"Caja De Badajoz",
    "wof:placetype":"venue"
},
  "geometry": {"coordinates":[-6.9463391304,38.9193687439],"type":"Point"}
}