{
  "type": "Feature",
  "properties": {
    "addr:full":"Carrer de Teodor Gonzalez (de), 26 Tortosa Tarragona 43500",
    "addr:housenumber":"26",
    "addr:postcode":"43500",
    "addr:street":"Carrer De Teodor Gonzalez De",
    "iso:country":"ES",
    "sg:address":"Carrer de Teodor Gonzalez (de), 26",
    "sg:city":"Tortosa",
    "sg:orig_category":"Muebles Y Accesorios Para Cocinas Y Cuartos De Ba\u00d1o (al Por Menor)",
    "sg:phone":"+34 977 44 44 19",
    "sg:postcode":"43500",
    "sg:province":"Tarragona",
    "wof:name":"Exclusives Llar S.l.",
    "wof:placetype":"venue"
},
  "geometry": {"coordinates":[0.5213320255,40.8101043701],"type":"Point"}
}