{
  "type": "Feature",
  "properties": {
    "addr:full":"Urb Solana Dehesa, 33 Tortola De Henares Guadalajara 19198",
    "addr:housenumber":"33",
    "addr:postcode":"19198",
    "addr:street":"Urb;Dehesa",
    "iso:country":"ES",
    "sg:address":"Urb Solana Dehesa, 33",
    "sg:city":"Tortola De Henares",
    "sg:orig_category":"Promotores Constructores",
    "sg:phone":"+34 949 32 31 74",
    "sg:postcode":"19198",
    "sg:province":"Guadalajara",
    "wof:name":"Satir Servicios Integrales S.l.",
    "wof:placetype":"venue"
},
  "geometry": {"coordinates":[-3.1267039776,40.70677948],"type":"Point"}
}