{
  "type": "Feature",
  "properties": {
    "iso:country":"ES",
    "sg:address":"Calle de Magallanes, 15",
    "sg:city":"Ubrique",
    "sg:orig_category":"Art\u00cdculos Funerarios (al Por Menor)",
    "sg:phone":"+34 956 46 38 04",
    "sg:postcode":"11600",
    "sg:province":"C\u00e1diz",
    "wof:name":"Peinado Campos Milagros",
    "wof:placetype":"venue"
},
  "geometry": {"coordinates":[-5.4457559586,36.6751670837],"type":"Point"}
}