{
  "type": "Feature",
  "properties": {
    "addr:full":"Calle de Rosales, 2 Motilla Palancar Cuenca 16200",
    "addr:housenumber":"2",
    "addr:postcode":"16200",
    "addr:street":"Calle De Rosales",
    "iso:country":"ES",
    "sg:address":"Calle de Rosales, 2",
    "sg:city":"Motilla Palancar",
    "sg:orig_category":"Perfumer\u00cda (al Por Menor)",
    "sg:phone":"+34 969 33 11 42",
    "sg:postcode":"16200",
    "sg:province":"Cuenca",
    "wof:name":"Rubio Cejalvo Maximo",
    "wof:placetype":"venue"
},
  "geometry": {"coordinates":[-1.9149650335,39.56300354],"type":"Point"}
}