{
  "type": "Feature",
  "properties": {
    "addr:full":"Carretera De Avileses, Km. 0001,0 Sucina Murcia 30590",
    "addr:postcode":"30590",
    "addr:street":"Carretera De Avileses Km. 0001,0",
    "iso:country":"ES",
    "sg:address":"Carretera De Avileses, Km. 0001,0",
    "sg:city":"Sucina",
    "sg:orig_category":"Fabricaci\u00d3n, Venta De Productos Base Farmac\u00c9uticos",
    "sg:phone":"+34 968 37 10 27",
    "sg:postcode":"30590",
    "sg:province":"Murcia",
    "wof:name":"Preparados Y Extractos Botanicos S.l.",
    "wof:placetype":"venue"
},
  "geometry": {"coordinates":[-0.9423689842,37.8906135559],"type":"Point"}
}