{
  "type": "Feature",
  "properties": {
    "iso:country":"ES",
    "sg:address":"Calle de A\u00d1astro, 64",
    "sg:city":"Madrid",
    "sg:orig_category":"Enfermeras: Consultas, Atenci\u00d3n A Domicilio",
    "sg:phone":"+34 913 83 07 82",
    "sg:postcode":"28033",
    "sg:province":"Madrid",
    "wof:name":"Medina Rodriguez Felisa",
    "wof:placetype":"venue"
},
  "geometry": {"coordinates":[-3.6608700752,40.4688796997],"type":"Point"}
}