{
  "type": "Feature",
  "properties": {
    "addr:full":"Calle de Harinas, 10 Marchena Sevilla 41620",
    "addr:housenumber":"10",
    "addr:postcode":"41620",
    "addr:street":"Calle De Harinas",
    "iso:country":"ES",
    "sg:address":"Calle de Harinas, 10",
    "sg:city":"Marchena",
    "sg:orig_category":"Panader\u00cdas, Panader\u00cdas",
    "sg:phone":"+34 954 84 37 32",
    "sg:postcode":"41620",
    "sg:province":"Sevilla",
    "wof:name":"Salvador Carre\u00f1o Antonio",
    "wof:placetype":"venue"
},
  "geometry": {"coordinates":[-5.4146161079,37.3276786804],"type":"Point"}
}