{
  "type": "Feature",
  "properties": {
    "addr:full":"Carrer de Carrer de Europa, S/n Puerto Rico Las Palmas 35130",
    "addr:housenumber":"s / n",
    "addr:postcode":"35130",
    "addr:street":"Carrer;Carrer De Europa;Rico",
    "iso:country":"ES",
    "sg:address":"Carrer de Carrer de Europa, S/n",
    "sg:city":"Puerto Rico",
    "sg:orig_category":"Laboratorios Y Trabajos De Fotograf\u00cda, V\u00cddeo Y Cine",
    "sg:phone":"+34 928 56 05 65",
    "sg:postcode":"35130",
    "sg:province":"Las Palmas",
    "wof:name":"Shamnani  Nirmala",
    "wof:placetype":"venue"
},
  "geometry": {"coordinates":[-13.9036235809,28.6303958893],"type":"Point"}
}