{
  "type": "Feature",
  "properties": {
    "iso:country":"ES",
    "sg:address":"Calle de Guatiza, 4",
    "sg:city":"Cruce I",
    "sg:orig_category":"Masajistas Kinesiterapeutas",
    "sg:phone":"+34 928 75 83 47",
    "sg:postcode":"35110",
    "sg:province":"Las Palmas",
    "sg:website":"www.esferopuntura.com",
    "wof:name":"Ramos Santos Guillermo Carlos",
    "wof:placetype":"venue"
},
  "geometry": {"coordinates":[-15.4442224503,27.8540172577],"type":"Point"}
}