{
  "type": "Feature",
  "properties": {
    "addr:full":"Calle de Santiago, 41 Llerena Badajoz 06900",
    "addr:housenumber":"41",
    "addr:postcode":"06900",
    "addr:street":"Calle De Santiago",
    "iso:country":"ES",
    "sg:address":"Calle de Santiago, 41",
    "sg:city":"Llerena",
    "sg:orig_category":"Librer\u00cdas",
    "sg:phone":"+34 924 87 22 51",
    "sg:postcode":"06900",
    "sg:province":"Badajoz",
    "wof:name":"Martinez Mena Manuela",
    "wof:placetype":"venue"
},
  "geometry": {"coordinates":[-6.0161700249,38.2371101379],"type":"Point"}
}