{
  "type": "Feature",
  "properties": {
    "addr:full":"Av Matadepera, 37 Sabadell Barcelona 08207",
    "addr:housenumber":"37",
    "addr:postcode":"08207",
    "addr:street":"Av Matadepera",
    "iso:country":"ES",
    "sg:address":"Av Matadepera, 37",
    "sg:city":"Sabadell",
    "sg:orig_category":"Electrodom\u00c9sticos (al Por Menor)",
    "sg:phone":"+34 937 23 37 07",
    "sg:postcode":"08207",
    "sg:province":"Barcelona",
    "sg:website":"www.redelite.es",
    "wof:name":"Electro Calbet S.a.",
    "wof:placetype":"venue"
},
  "geometry": {"coordinates":[2.0901861191,41.5644226074],"type":"Point"}
}