{
  "type": "Feature",
  "properties": {
    "addr:full":"Calle de Eduardo Bosca, 1 Valencia Valencia 46023",
    "addr:housenumber":"1",
    "addr:postcode":"46023",
    "addr:street":"Calle De Eduardo Bosca",
    "iso:country":"ES",
    "sg:address":"Calle de Eduardo Bosca, 1",
    "sg:city":"Valencia",
    "sg:orig_category":"Doctores En Medicina",
    "sg:phone":"+34 963 37 18 16",
    "sg:postcode":"46023",
    "sg:province":"Valencia",
    "wof:name":"Fenoy Cruz Angel",
    "wof:placetype":"venue"
},
  "geometry": {"coordinates":[-0.3565948904,39.4667053223],"type":"Point"}
}