{
  "type": "Feature",
  "properties": {
    "iso:country":"ES",
    "sg:address":"A Peroxa, 166",
    "sg:city":"Peroxa",
    "sg:orig_category":"Quincaller\u00cda (al Por Menor)",
    "sg:phone":"+34 988 20 66 02",
    "sg:postcode":"32150",
    "sg:province":"Ourense",
    "wof:name":"Seferama S.l.",
    "wof:placetype":"venue"
},
  "geometry": {"coordinates":[-7.7977061272,42.4440727234],"type":"Point"}
}