{
  "type": "Feature",
  "properties": {
    "addr:full":"Calle de Conde De Gondomar, 9 Cordoba C\u00f3rdoba 14003",
    "addr:housenumber":"9",
    "addr:postcode":"14003",
    "addr:street":"Calle De Conde De Gondomar;Co\u0301Rdoba",
    "iso:country":"ES",
    "sg:address":"Calle de Conde De Gondomar, 9",
    "sg:city":"Cordoba",
    "sg:orig_category":"Financiaci\u00d3n Y Cr\u00c9ditos",
    "sg:phone":"+34 957 49 10 17",
    "sg:postcode":"14003",
    "sg:province":"C\u00f3rdoba",
    "wof:name":"Finanmadrid",
    "wof:placetype":"venue"
},
  "geometry": {"coordinates":[-4.7809090614,37.8845748901],"type":"Point"}
}