{
  "type": "Feature",
  "properties": {
    "iso:country":"ES",
    "sg:address":"Calle de San Isidro, 19",
    "sg:city":"San Vicente Del Raspeig-sant Vicent Del Raspeig",
    "sg:orig_category":"Institutos De Belleza",
    "sg:phone":"+34 965 67 43 45",
    "sg:postcode":"03690",
    "sg:province":"Alicante",
    "wof:name":"Marin Garcia Sonia",
    "wof:placetype":"venue"
},
  "geometry": {"coordinates":[-0.5189304948,38.3970184326],"type":"Point"}
}