{
  "type": "Feature",
  "properties": {
    "addr:full":"Ctra Cunchillos, 17 Tarazona Zaragoza 50500",
    "addr:housenumber":"17",
    "addr:postcode":"50500",
    "addr:street":"Ctra Cunchillos",
    "iso:country":"ES",
    "sg:address":"Ctra Cunchillos, 17",
    "sg:city":"Tarazona",
    "sg:orig_category":"Promotores Constructores",
    "sg:phone":"+34 976 19 92 00",
    "sg:postcode":"50500",
    "sg:province":"Zaragoza",
    "wof:name":"Construcciones Hermanos Garcia Perez S.a.",
    "wof:placetype":"venue"
},
  "geometry": {"coordinates":[-1.7178590298,41.9048042297],"type":"Point"}
}