{
  "type": "Feature",
  "properties": {
    "addr:full":"Avda Miguel Servet, 59 Utebo Zaragoza 50180",
    "addr:housenumber":"59",
    "addr:postcode":"50180",
    "addr:street":"Avda Miguel Servet",
    "iso:country":"ES",
    "sg:address":"Avda Miguel Servet, 59",
    "sg:city":"Utebo",
    "sg:orig_category":"Ebanister\u00cda",
    "sg:phone":"+34 976 77 43 73",
    "sg:postcode":"50180",
    "sg:province":"Zaragoza",
    "wof:name":"Ignapisa S.l.",
    "wof:placetype":"venue"
},
  "geometry": {"coordinates":[-1.0170890093,41.7150382996],"type":"Point"}
}