{
  "type": "Feature",
  "properties": {
    "addr:full":"Praz Galicia (de), S/n Santiago De Compostela La Coru\u00f1a 15706",
    "addr:housenumber":"s",
    "addr:postcode":"15706",
    "addr:street":"/ N;Corun\u0303A",
    "iso:country":"ES",
    "sg:address":"Praz Galicia (de), S/n",
    "sg:city":"Santiago De Compostela",
    "sg:orig_category":"Aparcamientos (infraestructuras, Accesorios)",
    "sg:phone":"+34 981 56 34 07",
    "sg:postcode":"15706",
    "sg:province":"La Coru\u00f1a",
    "wof:name":"Interparking Hispania S.a.",
    "wof:placetype":"venue"
},
  "geometry": {"coordinates":[-8.54454422,42.876411438],"type":"Point"}
}