{
  "type": "Feature",
  "properties": {
    "addr:full":"Calle de Cienfuegos, 39 Gijon Asturias 33205",
    "addr:housenumber":"39",
    "addr:postcode":"33205",
    "addr:street":"Calle De Cienfuegos",
    "iso:country":"ES",
    "sg:address":"Calle de Cienfuegos, 39",
    "sg:city":"Gijon",
    "sg:orig_category":"Electricidad (montaje, Ensamblaje De Componentes)",
    "sg:phone":"+34 985 36 97 68",
    "sg:postcode":"33205",
    "sg:province":"Asturias",
    "wof:name":"Garcia Garcia Luis",
    "wof:placetype":"venue"
},
  "geometry": {"coordinates":[-5.6553077698,43.5352859497],"type":"Point"}
}