{
  "type": "Feature",
  "properties": {
    "iso:country":"ES",
    "sg:address":"C\u00f1o Castelo Pequeno, S/n",
    "sg:city":"Monforte De Lemos",
    "sg:orig_category":"Negocio De Materiales De Construcci\u00d3n",
    "sg:phone":"+34 982 40 42 89",
    "sg:postcode":"27400",
    "sg:province":"Lugo",
    "wof:name":"Vidal Fernandez Gilberto",
    "wof:placetype":"venue"
},
  "geometry": {"coordinates":[-7.5172939301,42.5221710205],"type":"Point"}
}