{
  "type": "Feature",
  "properties": {
    "addr:full":"Pg Estacio (l'), 3 Crevillent Alicante 03330",
    "addr:housenumber":"3",
    "addr:postcode":"03330",
    "addr:street":"Pg Estacio L '",
    "iso:country":"ES",
    "sg:address":"Pg Estacio (l'), 3",
    "sg:city":"Crevillent",
    "sg:orig_category":"Cooperativas Agr\u00cdcolas",
    "sg:phone":"+34 965 40 21 01",
    "sg:postcode":"03330",
    "sg:province":"Alicante",
    "wof:name":"Cooperativa Electrica Benefica San Francisco De Asis",
    "wof:placetype":"venue"
},
  "geometry": {"coordinates":[-0.802496016,38.2467765808],"type":"Point"}
}