{
  "type": "Feature",
  "properties": {
    "addr:full":"Calle de Transportistas, 17 Salamanca Salamanca 37006",
    "addr:housenumber":"17",
    "addr:postcode":"37006",
    "addr:street":"Calle De Transportistas",
    "iso:country":"ES",
    "sg:address":"Calle de Transportistas, 17",
    "sg:city":"Salamanca",
    "sg:orig_category":"Suministros Y Materiales Industriales",
    "sg:phone":"+34 923 22 71 60",
    "sg:postcode":"37006",
    "sg:province":"Salamanca",
    "wof:name":"Suministros Industriales Iglesias S. L.",
    "wof:placetype":"venue"
},
  "geometry": {"coordinates":[-5.6674757004,40.9751319885],"type":"Point"}
}