{
  "type": "Feature",
  "properties": {
    "iso:country":"ES",
    "sg:address":"Carrer de Gaia (del), 5",
    "sg:city":"Plana",
    "sg:orig_category":"Supermercados Y Hipermercados",
    "sg:phone":"+34 977 39 07 51",
    "sg:postcode":"43480",
    "sg:province":"Tarragona",
    "wof:name":"Velazquez Perez Maria Asuncion",
    "wof:placetype":"venue"
},
  "geometry": {"coordinates":[1.1441899538,41.1080245972],"type":"Point"}
}