{
  "type": "Feature",
  "properties": {
    "addr:full":"Avda Estacion, 14 Laguna Duero Valladolid 47140",
    "addr:housenumber":"14",
    "addr:postcode":"47140",
    "addr:street":"Avda Estacion",
    "iso:country":"ES",
    "sg:address":"Avda Estacion, 14",
    "sg:city":"Laguna Duero",
    "sg:orig_category":"Ense\u00d1anza Variada",
    "sg:phone":"+34 983 54 04 51",
    "sg:postcode":"47140",
    "sg:province":"Valladolid",
    "wof:name":"Marcos Rodriguez Jose Luis",
    "wof:placetype":"venue"
},
  "geometry": {"coordinates":[-4.7202939987,41.5809707642],"type":"Point"}
}