{
  "type": "Feature",
  "properties": {
    "iso:country":"ES",
    "sg:address":"Calle de Marques De San Esteban, 49",
    "sg:city":"Gijon",
    "sg:orig_category":"Inversiones",
    "sg:phone":"+34 985 17 16 67",
    "sg:postcode":"33206",
    "sg:province":"Asturias",
    "wof:name":"Jose Norberto Suarez Gomez Y Cia. Src",
    "wof:placetype":"venue"
},
  "geometry": {"coordinates":[-5.6695399284,43.5415382385],"type":"Point"}
}