{
  "type": "Feature",
  "properties": {
    "iso:country":"ES",
    "sg:address":"Rbla Rambla, 162",
    "sg:city":"Sabadell",
    "sg:orig_category":"Centros De Coordinaci\u00d3n",
    "sg:phone":"+34 937 25 92 01",
    "sg:postcode":"08201",
    "sg:province":"Barcelona",
    "wof:name":"Dauder Soler Magdalena",
    "wof:placetype":"venue"
},
  "geometry": {"coordinates":[2.1113500595,41.5418510437],"type":"Point"}
}