{
  "type": "Feature",
  "properties": {
    "iso:country":"ES",
    "sg:address":"Plaz Iglesia (de La), 1",
    "sg:city":"Fabara",
    "sg:orig_category":"Talleres: Ropa A Medida",
    "sg:phone":"+34 976 63 50 54",
    "sg:postcode":"50793",
    "sg:province":"Zaragoza",
    "wof:name":"Benages Camarasa Maria",
    "wof:placetype":"venue"
},
  "geometry": {"coordinates":[0.1674340069,41.1793403625],"type":"Point"}
}