{
  "type": "Feature",
  "properties": {
    "iso:country":"ES",
    "sg:address":"Calle de Angel Guimera, 40",
    "sg:city":"Valencia",
    "sg:orig_category":"Animales (al Por Menor)",
    "sg:phone":"+34 963 84 81 99",
    "sg:postcode":"46008",
    "sg:province":"Valencia",
    "wof:name":"Domingo Meco Miguel",
    "wof:placetype":"venue"
},
  "geometry": {"coordinates":[-0.3879401982,39.4698143005],"type":"Point"}
}