{
  "type": "Feature",
  "properties": {
    "iso:country":"ES",
    "sg:address":"Carrer de Corsega, 175",
    "sg:city":"Barcelona",
    "sg:orig_category":"Reposter\u00cdas",
    "sg:phone":"+34 934 19 62 71",
    "sg:postcode":"08036",
    "sg:province":"Barcelona",
    "wof:name":"Vivo Araujo Ana Maria",
    "wof:placetype":"venue"
},
  "geometry": {"coordinates":[2.1500012875,41.3895225525],"type":"Point"}
}