{
  "type": "Feature",
  "properties": {
    "addr:full":"Calle de Arzobispo Perez Platero, 11 Burgos Burgos 09007",
    "addr:housenumber":"11",
    "addr:postcode":"09007",
    "addr:street":"Calle De Arzobispo Perez Platero",
    "iso:country":"ES",
    "sg:address":"Calle de Arzobispo Perez Platero, 11",
    "sg:city":"Burgos",
    "sg:orig_category":"Centros Comerciales Y Grandes Tiendas",
    "sg:phone":"+34 947 21 53 21",
    "sg:postcode":"09007",
    "sg:province":"Burgos",
    "wof:name":"Vallejera Barriocanal Maria Del Pilar",
    "wof:placetype":"venue"
},
  "geometry": {"coordinates":[-3.6685659885,42.3506584167],"type":"Point"}
}