{
  "type": "Feature",
  "properties": {
    "iso:country":"ES",
    "sg:address":"Carr Santa Victoria, 28",
    "sg:city":"Mao",
    "sg:orig_category":"Electrodom\u00c9sticos (al Por Menor)",
    "sg:phone":"+34 971 35 60 55",
    "sg:postcode":"07701",
    "sg:province":"Islas Baleares",
    "wof:name":"German Pons S.c.",
    "wof:placetype":"venue"
},
  "geometry": {"coordinates":[4.2576231956,39.8913116455],"type":"Point"}
}