{
  "type": "Feature",
  "properties": {
    "iso:country":"ES",
    "sg:address":"Calle de Tarrasa, 1",
    "sg:city":"Madrid",
    "sg:orig_category":"Animales (al Por Menor)",
    "sg:phone":"+34 915 69 92 95",
    "sg:postcode":"28026",
    "sg:province":"Madrid",
    "wof:name":"Rodriguez Lopez Cesar",
    "wof:placetype":"venue"
},
  "geometry": {"coordinates":[-3.711879015,40.3825836182],"type":"Point"}
}