{
  "type": "Feature",
  "properties": {
    "iso:country":"ES",
    "sg:address":"Calle de Fernando Vi, 4",
    "sg:city":"Santander",
    "sg:orig_category":"Electricidad: Instaladores",
    "sg:phone":"+34 942 37 39 51",
    "sg:postcode":"39008",
    "sg:province":"Cantabria",
    "wof:name":"Becam S.l",
    "wof:placetype":"venue"
},
  "geometry": {"coordinates":[-3.8212161064,43.4579048157],"type":"Point"}
}