{
  "type": "Feature",
  "properties": {
    "addr:full":"Cmno Real De La Verdellada, S/n San Cristobal De La Laguna Santa Cruz De Tenerife 38207",
    "addr:housenumber":"s / n",
    "addr:postcode":"38207",
    "addr:street":"Cmno Real De La Verdellada",
    "iso:country":"ES",
    "sg:address":"Cmno Real De La Verdellada, S/n",
    "sg:city":"San Cristobal De La Laguna",
    "sg:orig_category":"Restaurantes",
    "sg:phone":"+34 922 25 07 34",
    "sg:postcode":"38207",
    "sg:province":"Santa Cruz De Tenerife",
    "sg:website":"www.eurest.colectividades.com",
    "wof:name":"Eurest Colectividades S.a.",
    "wof:placetype":"venue"
},
  "geometry": {"coordinates":[-16.30991745,28.4811191559],"type":"Point"}
}