{
  "type": "Feature",
  "properties": {
    "addr:full":"Carrer de Magallanes, 3 Terrassa Barcelona 08225",
    "addr:housenumber":"3",
    "addr:postcode":"08225",
    "addr:street":"Carrer De Magallanes",
    "iso:country":"ES",
    "sg:address":"Carrer de Magallanes, 3",
    "sg:city":"Terrassa",
    "sg:orig_category":"Hilaturas, Hilos Y Actividades Relacionadas",
    "sg:phone":"+34 937 80 57 05",
    "sg:postcode":"08225",
    "sg:province":"Barcelona",
    "wof:name":"Rodellar Fumanal Antonio",
    "wof:placetype":"venue"
},
  "geometry": {"coordinates":[2.0004360676,41.5683135986],"type":"Point"}
}