{
  "type": "Feature",
  "properties": {
    "iso:country":"ES",
    "sg:address":"Mendigorritxu Kalea, 132",
    "sg:city":"Jundiz",
    "sg:orig_category":"Distribuci\u00d3n De Petr\u00d3leo Y Derivados",
    "sg:phone":"+34 945 29 00 35",
    "sg:postcode":"01015",
    "sg:province":"\u00c1lava",
    "wof:name":"Gasocentro Vitoria S.a.",
    "wof:placetype":"venue"
},
  "geometry": {"coordinates":[-6.1999697685,43.3617782593],"type":"Point"}
}