{
  "type": "Feature",
  "properties": {
    "addr:full":"Calle de Socuellamos, 109 Tomelloso Ciudad Real 13700",
    "addr:housenumber":"109",
    "addr:postcode":"13700",
    "addr:street":"Calle De Socuellamos",
    "iso:country":"ES",
    "sg:address":"Calle de Socuellamos, 109",
    "sg:city":"Tomelloso",
    "sg:orig_category":"Frutas, Legumbres Frescas Y Tempranas (al Por Menor)",
    "sg:phone":"+34 926 50 65 13",
    "sg:postcode":"13700",
    "sg:province":"Ciudad Real",
    "wof:name":"Cano Jareo Francisca",
    "wof:placetype":"venue"
},
  "geometry": {"coordinates":[-3.0126190186,39.1682281494],"type":"Point"}
}