{
  "type": "Feature",
  "properties": {
    "addr:full":"Pque Nicolas Salmeron (de), S/n Almeria Almer\u00eda 04002",
    "addr:housenumber":"s / n",
    "addr:postcode":"04002",
    "addr:street":"Salmeron",
    "iso:country":"ES",
    "sg:address":"Pque Nicolas Salmeron (de), S/n",
    "sg:city":"Almeria",
    "sg:orig_category":"Molduras, Junquillos, Listones Y Molduras Perforadas",
    "sg:phone":"+34 950 23 56 01",
    "sg:postcode":"04002",
    "sg:province":"Almer\u00eda",
    "wof:name":"Lopez Parra Jose",
    "wof:placetype":"venue"
},
  "geometry": {"coordinates":[-2.5148420334,36.8469619751],"type":"Point"}
}