{
  "type": "Feature",
  "properties": {
    "iso:country":"ES",
    "sg:address":"Pso. Maritimo, 6",
    "sg:city":"Torrox-costa",
    "sg:orig_category":"Caf\u00c9s, Bares, Cervecer\u00cdas",
    "sg:phone":"+34 952 53 27 59",
    "sg:postcode":"29793",
    "sg:province":"M\u00e1laga",
    "wof:name":"Lopez Baena Rafael",
    "wof:placetype":"venue"
},
  "geometry": {"coordinates":[-3.9873039722,36.7375984192],"type":"Point"}
}