{
  "type": "Feature",
  "properties": {
    "addr:full":"Avda Europa, 15 Pozuelo De Alarcon Madrid 28224",
    "addr:housenumber":"15",
    "addr:postcode":"28224",
    "addr:street":"Avda Europa",
    "iso:country":"ES",
    "sg:address":"Avda Europa, 15",
    "sg:city":"Pozuelo De Alarcon",
    "sg:orig_category":"Asesor\u00cda Sobre Comunicaci\u00d3n De Empresas",
    "sg:phone":"+34 917 15 18 75",
    "sg:postcode":"28224",
    "sg:province":"Madrid",
    "wof:name":"Cuerda Y Telon S.l.",
    "wof:placetype":"venue"
},
  "geometry": {"coordinates":[-3.7898540497,40.4400367737],"type":"Point"}
}