{
  "type": "Feature",
  "properties": {
    "iso:country":"ES",
    "sg:address":"Carr Bonaire, 27",
    "sg:city":"Lleida",
    "sg:orig_category":"Molduras, Junquillos, Listones Y Molduras Perforadas",
    "sg:phone":"+34 973 23 10 77",
    "sg:postcode":"25004",
    "sg:province":"Lleida",
    "wof:name":"Vives Garde\u00f1es Margarita",
    "wof:placetype":"venue"
},
  "geometry": {"coordinates":[0.6215013266,41.6190109253],"type":"Point"}
}