{
  "type": "Feature",
  "properties": {
    "iso:country":"ES",
    "sg:address":"Calle de Ronda, 44",
    "sg:city":"Iscar",
    "sg:orig_category":"Frutas Y Legumbres Secas (al Por Mayor)",
    "sg:phone":"+34 983 61 10 38",
    "sg:postcode":"47420",
    "sg:province":"Valladolid",
    "wof:name":"San Miguel Ballesteros Jesus",
    "wof:placetype":"venue"
},
  "geometry": {"coordinates":[-4.5323839188,41.3612861633],"type":"Point"}
}