{
  "type": "Feature",
  "properties": {
    "iso:country":"ES",
    "sg:address":"Calle de Padre Huesca, 17",
    "sg:city":"Huesca",
    "sg:orig_category":"M\u00c9dicos: Oftalmolog\u00cda",
    "sg:phone":"+34 974 23 04 19",
    "sg:postcode":"22002",
    "sg:province":"Huesca",
    "wof:name":"Nogues Gazo Julio",
    "wof:placetype":"venue"
},
  "geometry": {"coordinates":[-0.4070110023,42.1361618042],"type":"Point"}
}