{
  "type": "Feature",
  "properties": {
    "addr:full":"Plaz Palillero (del), S/n Cadiz C\u00e1diz 11001",
    "addr:housenumber":"/ n",
    "addr:postcode":"11001",
    "addr:street":"Plaz;Del S",
    "iso:country":"ES",
    "sg:address":"Plaz Palillero (del), S/n",
    "sg:city":"Cadiz",
    "sg:orig_category":"Cajas Para Embalar",
    "sg:phone":"+34 956 21 22 65",
    "sg:postcode":"11001",
    "sg:province":"C\u00e1diz",
    "wof:name":"Caja Rural Del Sur Sociedad Cooperativa",
    "wof:placetype":"venue"
},
  "geometry": {"coordinates":[-6.29626894,36.5321083069],"type":"Point"}
}