{
  "type": "Feature",
  "properties": {
    "iso:country":"ES",
    "sg:address":"C/ Vila-real, 2",
    "sg:city":"Moncofa",
    "sg:orig_category":"Ense\u00d1anza Variada",
    "sg:phone":"+34 964 57 78 25",
    "sg:postcode":"12593",
    "sg:province":"Castell\u00f3n",
    "wof:name":"Espinos",
    "wof:placetype":"venue"
},
  "geometry": {"coordinates":[-0.1468389928,39.8087272644],"type":"Point"}
}