{
  "type": "Feature",
  "properties": {
    "iso:country":"ES",
    "sg:address":"Calle de Fray Juan De Zumarraga Kalea, 4",
    "sg:city":"Durango",
    "sg:orig_category":"Ense\u00d1anza Variada",
    "sg:phone":"+34 946 81 66 16",
    "sg:postcode":"48200",
    "sg:province":"Vizcaya",
    "wof:name":"Adria Ma\u00f1ez Amparo",
    "wof:placetype":"venue"
},
  "geometry": {"coordinates":[-2.6345000267,43.1715698242],"type":"Point"}
}