{
  "type": "Feature",
  "properties": {
    "iso:country":"ES",
    "sg:address":"Pol. Rajolar, S/n",
    "sg:city":"S. Carles Rapita",
    "sg:orig_category":"Producci\u00d3n De Abonos Y De Fertilizantes",
    "sg:phone":"+34 977 74 03 22",
    "sg:postcode":"43540",
    "sg:province":"Tarragona",
    "wof:name":"Fertilizantes Gombau S.l.",
    "wof:placetype":"venue"
},
  "geometry": {"coordinates":[1.2454571724,41.11901474],"type":"Point"}
}