{
  "type": "Feature",
  "properties": {
    "addr:full":"Calle de Cptan Gral Gtrrez Mellado, 6 Alacant Alicante 03006",
    "addr:housenumber":"6",
    "addr:postcode":"03006",
    "addr:street":"Calle De Cptan Gral Gtrrez Mellado",
    "iso:country":"ES",
    "sg:address":"Calle de Cptan Gral Gtrrez Mellado, 6",
    "sg:city":"Alacant",
    "sg:orig_category":"Promotores Constructores",
    "sg:phone":"+34 965 12 29 99",
    "sg:postcode":"03006",
    "sg:province":"Alicante",
    "wof:name":"J Cris Obras Y Servicios S.l.",
    "wof:placetype":"venue"
},
  "geometry": {"coordinates":[-0.573071301,38.367855072],"type":"Point"}
}