{
  "type": "Feature",
  "properties": {
    "addr:full":"Urb. Port Addaia, S/n Port Addaia Islas Baleares 07730",
    "addr:housenumber":"s / n",
    "addr:postcode":"07730",
    "addr:street":"Port Addaia",
    "iso:country":"ES",
    "sg:address":"Urb. Port Addaia, S/n",
    "sg:city":"Port Addaia",
    "sg:orig_category":"Transporte En General",
    "sg:phone":"+34 971 18 88 71",
    "sg:postcode":"07730",
    "sg:province":"Islas Baleares",
    "wof:name":"Addaya S.a.",
    "wof:placetype":"venue"
},
  "geometry": {"coordinates":[2.8577105999,39.5341796875],"type":"Point"}
}