{
  "type": "Feature",
  "properties": {
    "iso:country":"ES",
    "sg:address":"El Romeral, 9",
    "sg:city":"Guardia",
    "sg:orig_category":"Panader\u00cdas, Panader\u00cdas",
    "sg:phone":"+34 925 13 81 16",
    "sg:postcode":"45760",
    "sg:province":"Toledo",
    "wof:name":"Panasu C.b.",
    "wof:placetype":"venue"
},
  "geometry": {"coordinates":[-3.4759860039,39.7854347229],"type":"Point"}
}