{
  "type": "Feature",
  "properties": {
    "addr:full":"Urb Mies Del Calero, S/n Mortera Cantabria 39120",
    "addr:housenumber":"s / n",
    "addr:postcode":"39120",
    "iso:country":"ES",
    "sg:address":"Urb Mies Del Calero, S/n",
    "sg:city":"Mortera",
    "sg:orig_category":"Ense\u00d1anza Variada",
    "sg:phone":"+34 942 58 12 25",
    "sg:postcode":"39120",
    "sg:province":"Cantabria",
    "wof:name":"Pe\u00f1a Seoane Silvia",
    "wof:placetype":"venue"
},
  "geometry": {"coordinates":[-3.9328329563,43.4454727173],"type":"Point"}
}