{
  "type": "Feature",
  "properties": {
    "iso:country":"ES",
    "sg:address":"Cuesta De La Merced, 32",
    "sg:city":"Ubeda",
    "sg:orig_category":"Alfarer\u00cda",
    "sg:phone":"+34 953 75 46 05",
    "sg:postcode":"23400",
    "sg:province":"Ja\u00e9n",
    "wof:name":"Hidalgo Gongora Pedro Jose",
    "wof:placetype":"venue"
},
  "geometry": {"coordinates":[-3.3652205467,38.0118217468],"type":"Point"}
}