{
  "type": "Feature",
  "properties": {
    "iso:country":"ES",
    "sg:address":"Avgd Gregorio Molina, 9",
    "sg:city":"Xativa",
    "sg:orig_category":"Agencias De Viajes",
    "sg:phone":"+34 962 28 30 19",
    "sg:postcode":"46800",
    "sg:province":"Valencia",
    "sg:website":"www.viajeselcorteingles.es",
    "wof:name":"Viajes El Corte Ingles S.a.",
    "wof:placetype":"venue"
},
  "geometry": {"coordinates":[-0.5230050087,38.9914703369],"type":"Point"}
}