{
  "type": "Feature",
  "properties": {
    "addr:full":"Calle de Enrique Granados, 7 Linares Ja\u00e9n 23700",
    "addr:housenumber":"7",
    "addr:postcode":"23700",
    "addr:street":"Calle De Enrique Granados;Jae\u0301N",
    "iso:country":"ES",
    "sg:address":"Calle de Enrique Granados, 7",
    "sg:city":"Linares",
    "sg:orig_category":"Ingenier\u00cda, Centros De Estudios (diversos)",
    "sg:phone":"+34 953 69 41 38",
    "sg:postcode":"23700",
    "sg:province":"Ja\u00e9n",
    "wof:name":"Garrido Caravante Francisco Javier",
    "wof:placetype":"venue"
},
  "geometry": {"coordinates":[-3.6402935982,38.1013031006],"type":"Point"}
}