{
  "type": "Feature",
  "properties": {
    "addr:full":"San Simon, 13 San Simon Pontevedra 36614",
    "addr:housenumber":"13",
    "addr:postcode":"36614",
    "addr:street":"San Simon",
    "iso:country":"ES",
    "sg:address":"San Simon, 13",
    "sg:city":"San Simon",
    "sg:orig_category":"Molduras, Junquillos, Listones Y Molduras Perforadas",
    "sg:phone":"+34 986 50 67 10",
    "sg:postcode":"36614",
    "sg:province":"Pontevedra",
    "wof:name":"Mondragon Castro Felix",
    "wof:placetype":"venue"
},
  "geometry": {"coordinates":[-7.6374740601,43.6283531189],"type":"Point"}
}