{
  "type": "Feature",
  "properties": {
    "iso:country":"ES",
    "sg:address":"Av Constitucio, 43",
    "sg:city":"Xixona",
    "sg:orig_category":"Pescader\u00cdas (al Por Menor)",
    "sg:phone":"+34 965 61 21 46",
    "sg:postcode":"03100",
    "sg:province":"Alicante",
    "wof:name":"Llorens Ayela Jose",
    "wof:placetype":"venue"
},
  "geometry": {"coordinates":[-0.5064049959,38.5415992737],"type":"Point"}
}