{
  "type": "Feature",
  "properties": {
    "iso:country":"ES",
    "sg:address":"Carrer de Rafael Casanova, 70",
    "sg:city":"Granollers",
    "sg:orig_category":"Mec\u00c1nico Del Autom\u00d3vil",
    "sg:phone":"+34 938 49 91 71",
    "sg:postcode":"08401",
    "sg:province":"Barcelona",
    "wof:name":"Luengo Alonso Pelayo",
    "wof:placetype":"venue"
},
  "geometry": {"coordinates":[2.2867939472,41.6139144897],"type":"Point"}
}