{
  "type": "Feature",
  "properties": {
    "iso:country":"ES",
    "sg:address":"Pase Velilla (de), 10",
    "sg:city":"Velilla-taramay",
    "sg:orig_category":"Chapister\u00cda",
    "sg:phone":"+34 958 63 03 43",
    "sg:postcode":"18690",
    "sg:province":"Granada",
    "wof:name":"Garcia Fernandez Eduardo",
    "wof:placetype":"venue"
},
  "geometry": {"coordinates":[-3.6882688999,36.736743927],"type":"Point"}
}