{
  "type": "Feature",
  "properties": {
    "iso:country":"ES",
    "sg:address":"Av Roureda, 27",
    "sg:city":"Viladecans",
    "sg:orig_category":"Venta, Instalaci\u00d3n De Calefacci\u00d3n",
    "sg:phone":"+34 936 37 68 85",
    "sg:postcode":"08840",
    "sg:province":"Barcelona",
    "wof:name":"Instalaciones Garbu S.l",
    "wof:placetype":"venue"
},
  "geometry": {"coordinates":[2.0105021,41.3225326538],"type":"Point"}
}