{
  "type": "Feature",
  "properties": {
    "addr:full":"Carr Caba\u00d1al, 6 Cullera Valencia 46400",
    "addr:housenumber":"6",
    "addr:postcode":"46400",
    "addr:street":"Carr Caban\u0303Al",
    "iso:country":"ES",
    "sg:address":"Carr Caba\u00d1al, 6",
    "sg:city":"Cullera",
    "sg:orig_category":"Alimentaci\u00d3n General (al Por Menor)",
    "sg:phone":"+34 961 72 05 41",
    "sg:postcode":"46400",
    "sg:province":"Valencia",
    "wof:name":"Madue\u00f1o Cu\u00f1ado Magdalena",
    "wof:placetype":"venue"
},
  "geometry": {"coordinates":[-0.2455440015,39.1645393372],"type":"Point"}
}