{
  "type": "Feature",
  "properties": {
    "iso:country":"ES",
    "sg:address":"Avda Pintor Joaquin Sorolla, 125",
    "sg:city":"Malaga",
    "sg:orig_category":"Electricidad: Equipos Industriales, Componentes (fabricaci\u00d3n)",
    "sg:phone":"+34 952 29 56 48",
    "sg:postcode":"29017",
    "sg:province":"M\u00e1laga",
    "sg:website":"www.abb.es",
    "wof:name":"Asea Brown Boveri S.a.",
    "wof:placetype":"venue"
},
  "geometry": {"coordinates":[-4.3843708038,36.7217750549],"type":"Point"}
}