{
  "type": "Feature",
  "properties": {
    "addr:full":"Calle de San Enrique, 16 Torrent Valencia 46900",
    "addr:housenumber":"16",
    "addr:postcode":"46900",
    "addr:street":"Calle De San Enrique;Valencia",
    "iso:country":"ES",
    "sg:address":"Calle de San Enrique, 16",
    "sg:city":"Torrent",
    "sg:orig_category":"Empresarios",
    "sg:phone":"+34 961 56 73 63",
    "sg:postcode":"46900",
    "sg:province":"Valencia",
    "wof:name":"Fundacion Hogares San Martin De Porres De La Comunidad Valenciana",
    "wof:placetype":"venue"
},
  "geometry": {"coordinates":[-0.4825449884,39.4336242676],"type":"Point"}
}