{
  "type": "Feature",
  "properties": {
    "iso:country":"ES",
    "sg:address":"Carrer de Pep Ventura, 34",
    "sg:city":"Olesa Montserrat",
    "sg:orig_category":"Instalaci\u00d3n De Aspiraci\u00d3n De Gases Y Humos",
    "sg:phone":"+34 937 78 40 03",
    "sg:postcode":"08640",
    "sg:province":"Barcelona",
    "wof:name":"Progres Instalaciones S.c.p.",
    "wof:placetype":"venue"
},
  "geometry": {"coordinates":[1.8932650089,41.5387153625],"type":"Point"}
}