{
  "type": "Feature",
  "properties": {
    "addr:full":"Desvio Distante, S/n Motril Granada 18600",
    "addr:housenumber":"s",
    "addr:postcode":"18600",
    "addr:street":"/ N;Granada",
    "iso:country":"ES",
    "sg:address":"Desvio Distante, S/n",
    "sg:city":"Motril",
    "sg:orig_category":"Electrodom\u00c9sticos (al Por Menor)",
    "sg:phone":"+34 958 60 25 98",
    "sg:postcode":"18600",
    "sg:province":"Granada",
    "wof:name":"Fernandez Maya Emilio",
    "wof:placetype":"venue"
},
  "geometry": {"coordinates":[-3.5152790546,36.7456130981],"type":"Point"}
}