{
  "type": "Feature",
  "properties": {
    "addr:full":"Av Santa Barbara, 65 Amposta Tarragona 43870",
    "addr:housenumber":"65",
    "addr:postcode":"43870",
    "addr:street":"Av Santa Barbara",
    "iso:country":"ES",
    "sg:address":"Av Santa Barbara, 65",
    "sg:city":"Amposta",
    "sg:orig_category":"Comercio De Mobiliario De Oficina",
    "sg:phone":"+34 977 70 03 08",
    "sg:postcode":"43870",
    "sg:province":"Tarragona",
    "wof:name":"Roig Papertecnic S.l.",
    "wof:placetype":"venue"
},
  "geometry": {"coordinates":[0.5785999894,40.7119483948],"type":"Point"}
}