{
  "type": "Feature",
  "properties": {
    "iso:country":"ES",
    "sg:address":"Rua D, 1",
    "sg:city":"Laredo",
    "sg:orig_category":"Cerrajer\u00cda, Ferrallista",
    "sg:phone":"+34 986 45 00 84",
    "sg:postcode":"36320",
    "sg:province":"Pontevedra",
    "wof:name":"Perez Lago Angel",
    "wof:placetype":"venue"
},
  "geometry": {"coordinates":[-8.6428003311,42.4304618835],"type":"Point"}
}