{
  "type": "Feature",
  "properties": {
    "iso:country":"ES",
    "sg:address":"Compa\u00f1ia, S/n",
    "sg:city":"Molina Segura",
    "sg:orig_category":"Peluquer\u00cdas, Peluquer\u00cda Mixta",
    "sg:phone":"+34 968 64 50 40",
    "sg:postcode":"30500",
    "sg:province":"Murcia",
    "wof:name":"Rocky Belda S.l.",
    "wof:placetype":"venue"
},
  "geometry": {"coordinates":[-1.2119740248,38.0535736084],"type":"Point"}
}