{
  "type": "Feature",
  "properties": {
    "iso:country":"ES",
    "sg:address":"Carrer de Jacint Verdaguer, 53",
    "sg:city":"Sabadell",
    "sg:orig_category":"Moda",
    "sg:phone":"+34 937 10 13 50",
    "sg:postcode":"08205",
    "sg:province":"Barcelona",
    "wof:name":"Comercial J. S. D. S. A.",
    "wof:placetype":"venue"
},
  "geometry": {"coordinates":[2.1018979549,41.5394058228],"type":"Point"}
}