{
  "type": "Feature",
  "properties": {
    "addr:full":"Calle de Decano Jose Gomez Rando, S/n Torremolinos M\u00e1laga 29620",
    "addr:housenumber":"s / n",
    "addr:postcode":"29620",
    "addr:street":"Calle De Decano Jose Gomez Rando;Ma\u0301Laga",
    "iso:country":"ES",
    "sg:address":"Calle de Decano Jose Gomez Rando, S/n",
    "sg:city":"Torremolinos",
    "sg:orig_category":"Restaurantes",
    "sg:phone":"+34 952 38 04 50",
    "sg:postcode":"29620",
    "sg:province":"M\u00e1laga",
    "wof:name":"Bar Playa Larry S.l.",
    "wof:placetype":"venue"
},
  "geometry": {"coordinates":[-4.511297226,36.6018791199],"type":"Point"}
}