{
  "type": "Feature",
  "properties": {
    "iso:country":"ES",
    "sg:address":"Calle de Sanchonu\u00d1o, 9",
    "sg:city":"Madrid",
    "sg:orig_category":"Mec\u00c1nico Del Autom\u00d3vil",
    "sg:phone":"+34 917 34 94 00",
    "sg:postcode":"28034",
    "sg:province":"Madrid",
    "wof:name":"Talleres Luis Martin E Hijos S.l.",
    "wof:placetype":"venue"
},
  "geometry": {"coordinates":[-3.6897768974,40.4917068481],"type":"Point"}
}