{
  "type": "Feature",
  "properties": {
    "iso:country":"ES",
    "sg:address":"Carrer de Major (sant Celoni), 19",
    "sg:city":"S. Celoni",
    "sg:orig_category":"Inmobiliaria (agencias)",
    "sg:phone":"+34 938 48 44 40",
    "sg:postcode":"08470",
    "sg:province":"Barcelona",
    "wof:name":"Fincas Corral Halias.l.",
    "wof:placetype":"venue"
},
  "geometry": {"coordinates":[2.4880719185,41.6868782043],"type":"Point"}
}