{
  "type": "Feature",
  "properties": {
    "addr:full":"Pl Salvador Espriu, 3 Terrassa Barcelona 08221",
    "addr:housenumber":"3",
    "addr:postcode":"08221",
    "addr:street":"Pl Salvador Espriu",
    "iso:country":"ES",
    "sg:address":"Pl Salvador Espriu, 3",
    "sg:city":"Terrassa",
    "sg:orig_category":"Peluquer\u00cdas, Peluquer\u00cda Mixta",
    "sg:phone":"+34 937 89 31 11",
    "sg:postcode":"08221",
    "sg:province":"Barcelona",
    "wof:name":"Valenzuela Perez Carmen",
    "wof:placetype":"venue"
},
  "geometry": {"coordinates":[2.0087099075,41.5624504089],"type":"Point"}
}