{
  "type": "Feature",
  "properties": {
    "iso:country":"ES",
    "sg:address":"Barr Hoya (la), 51",
    "sg:city":"Argo\u00f1os",
    "sg:orig_category":"Ense\u00d1anza Variada",
    "sg:phone":"+34 942 62 65 69",
    "sg:postcode":"39197",
    "sg:province":"Cantabria",
    "wof:name":"Centro De Estudios Argo\u00f1os S.c",
    "wof:placetype":"venue"
},
  "geometry": {"coordinates":[-3.4864890575,43.4572067261],"type":"Point"}
}