{
  "type": "Feature",
  "properties": {
    "iso:country":"ES",
    "sg:address":"Ctra Guadalix (de), Km. 0001,0",
    "sg:city":"Colmenar Viejo",
    "sg:orig_category":"Barbacoas Y Accesorios",
    "sg:phone":"+34 918 45 41 77",
    "sg:postcode":"28770",
    "sg:province":"Madrid",
    "wof:name":"Asador Las Vegas S.l.",
    "wof:placetype":"venue"
},
  "geometry": {"coordinates":[-3.7694671154,40.6917114258],"type":"Point"}
}