{
  "type": "Feature",
  "properties": {
    "addr:full":"Erribera Kalea, 16 Usurbil Guip\u00f9zcoa 20170",
    "addr:housenumber":"16",
    "addr:postcode":"20170",
    "addr:street":"Erribera Kalea;Guipu\u0300Zcoa",
    "iso:country":"ES",
    "sg:address":"Erribera Kalea, 16",
    "sg:city":"Usurbil",
    "sg:orig_category":"Charcuter\u00cdas (al Por Mayor)",
    "sg:phone":"+34 943 37 23 13",
    "sg:postcode":"20170",
    "sg:province":"Guip\u00f9zcoa",
    "wof:name":"Comercial Guipuzcoa S.l.u.",
    "wof:placetype":"venue"
},
  "geometry": {"coordinates":[-2.0492010117,43.2693595886],"type":"Point"}
}