{
  "type": "Feature",
  "properties": {
    "iso:country":"ES",
    "sg:address":"Cami Roig, 247",
    "sg:city":"Indioteria",
    "sg:orig_category":"Deportes N\u00c1uticos, Acu\u00c1ticos Y Subacu\u00c1ticos: Art\u00cdculos Y Equipo (al Por Menor)",
    "sg:phone":"+34 971 43 13 34",
    "sg:postcode":"07009",
    "sg:province":"Islas Baleares",
    "wof:name":"Dragamon S.l.",
    "wof:placetype":"venue"
},
  "geometry": {"coordinates":[2.6766200066,39.6112518311],"type":"Point"}
}