{
  "type": "Feature",
  "properties": {
    "addr:full":"Calle de Garcia Lorca, 25 Arroyo S Servan Badajoz 06850",
    "addr:housenumber":"25",
    "addr:postcode":"06850",
    "addr:street":"Calle De Garcia Lorca;Arroyo S Servan",
    "iso:country":"ES",
    "sg:address":"Calle de Garcia Lorca, 25",
    "sg:city":"Arroyo S Servan",
    "sg:orig_category":"Laboratorios Farmac\u00c9uticos",
    "sg:phone":"+34 924 34 26 42",
    "sg:postcode":"06850",
    "sg:province":"Badajoz",
    "wof:name":"Folgado Fernandez Marino",
    "wof:placetype":"venue"
},
  "geometry": {"coordinates":[-6.4525327682,38.8548583984],"type":"Point"}
}