{
  "type": "Feature",
  "properties": {
    "iso:country":"ES",
    "sg:address":"Calle de Toledo, 28",
    "sg:city":"Ciudad Real",
    "sg:orig_category":"Cl\u00cdnicas Dentales",
    "sg:phone":"+34 926 23 15 64",
    "sg:postcode":"13003",
    "sg:province":"Ciudad Real",
    "wof:name":"Serrano Pumarega Silvia",
    "wof:placetype":"venue"
},
  "geometry": {"coordinates":[-3.9280788898,38.9897918701],"type":"Point"}
}