{
  "type": "Feature",
  "properties": {
    "addr:full":"Senda Bueno, S/n Albuixech Valencia 46550",
    "addr:housenumber":"s",
    "addr:postcode":"46550",
    "addr:street":"Senda Bueno;/ N",
    "iso:country":"ES",
    "sg:address":"Senda Bueno, S/n",
    "sg:city":"Albuixech",
    "sg:orig_category":"Cine: Pel\u00cdculas Educativas, Industriales Y Publicitarias (producci\u00d3n)",
    "sg:phone":"+34 961 40 20 65",
    "sg:postcode":"46550",
    "sg:province":"Valencia",
    "wof:name":"Linares Ramirez Alejandro",
    "wof:placetype":"venue"
},
  "geometry": {"coordinates":[-0.3256070018,39.5474662781],"type":"Point"}
}