{
  "type": "Feature",
  "properties": {
    "addr:full":"Carr Maestro Giner, 2 Burjassot Valencia 46100",
    "addr:housenumber":"2",
    "addr:postcode":"46100",
    "addr:street":"Carr Maestro Giner",
    "iso:country":"ES",
    "sg:address":"Carr Maestro Giner, 2",
    "sg:city":"Burjassot",
    "sg:orig_category":"Piscinas, Accesorios, Suministros (fabricaci\u00d3n, Al Por Mayor)",
    "sg:phone":"+34 963 90 30 31",
    "sg:postcode":"46100",
    "sg:province":"Valencia",
    "wof:name":"Naturagua 2000 S.l.",
    "wof:placetype":"venue"
},
  "geometry": {"coordinates":[-0.4083659947,39.5043983459],"type":"Point"}
}