{
  "type": "Feature",
  "properties": {
    "iso:country":"ES",
    "sg:address":"Av Concordia, 65",
    "sg:city":"Sabadell",
    "sg:orig_category":"Muebles",
    "sg:phone":"+34 937 16 33 87",
    "sg:postcode":"08206",
    "sg:province":"Barcelona",
    "wof:name":"Muebles Izquierdo S.a.",
    "wof:placetype":"venue"
},
  "geometry": {"coordinates":[2.0930519104,41.5610237122],"type":"Point"}
}