{
  "type": "Feature",
  "properties": {
    "addr:full":"Calle de Corredera, S/n Ampudia Palencia 34160",
    "addr:housenumber":"s / n",
    "addr:postcode":"34160",
    "addr:street":"Calle De Corredera",
    "iso:country":"ES",
    "sg:address":"Calle de Corredera, S/n",
    "sg:city":"Ampudia",
    "sg:orig_category":"Cajas De Ahorro",
    "sg:phone":"+34 979 76 81 16",
    "sg:postcode":"34160",
    "sg:province":"Palencia",
    "sg:website":"www.cajaespana.es",
    "wof:name":"Caja Espa\u00f1a De Inversiones Caja De Ahorros Y Monte De Piedad",
    "wof:placetype":"venue"
},
  "geometry": {"coordinates":[-4.7797737122,41.9149780273],"type":"Point"}
}