{
  "type": "Feature",
  "properties": {
    "addr:full":"Carrer de Matilde Diez, 17 Barcelona Barcelona 08006",
    "addr:housenumber":"17",
    "addr:postcode":"08006",
    "addr:street":"Carrer De Matilde Diez",
    "iso:country":"ES",
    "sg:address":"Carrer de Matilde Diez, 17",
    "sg:city":"Barcelona",
    "sg:orig_category":"Bisuter\u00cda, Joyer\u00cda, Relojer\u00cda (al Por Menor)",
    "sg:phone":"+34 932 37 30 95",
    "sg:postcode":"08006",
    "sg:province":"Barcelona",
    "wof:name":"Maristany Pujol Ramon",
    "wof:placetype":"venue"
},
  "geometry": {"coordinates":[2.14844203,41.4016571045],"type":"Point"}
}