{
  "type": "Feature",
  "properties": {
    "iso:country":"ES",
    "sg:address":"Calle de Alonso De Ojeda, 4",
    "sg:city":"Marbella",
    "sg:orig_category":"Panader\u00cdas, Panader\u00cdas",
    "sg:phone":"+34 952 82 75 73",
    "sg:postcode":"29600",
    "sg:province":"M\u00e1laga",
    "wof:name":"Escobar Hermosilla Miguel Angel",
    "wof:placetype":"venue"
},
  "geometry": {"coordinates":[-4.8768105507,36.5096702576],"type":"Point"}
}