{
  "type": "Feature",
  "properties": {
    "addr:full":"Calle de Canteras (de Las), 15 El Cruce Madrid 28860",
    "addr:housenumber":"15",
    "addr:postcode":"28860",
    "addr:street":"Calle De Canteras De Las",
    "iso:country":"ES",
    "sg:address":"Calle de Canteras (de Las), 15",
    "sg:city":"El Cruce",
    "sg:orig_category":"Electrodom\u00c9sticos (al Por Menor)",
    "sg:phone":"+34 916 58 13 80",
    "sg:postcode":"28860",
    "sg:province":"Madrid",
    "wof:name":"Bs Disarco S.l.",
    "wof:placetype":"venue"
},
  "geometry": {"coordinates":[-3.5498759747,40.5093269348],"type":"Point"}
}