{
  "type": "Feature",
  "properties": {
    "iso:country":"ES",
    "sg:address":"Calle de Jose De La Torre Cobos, 5",
    "sg:city":"Villacarrillo",
    "sg:orig_category":"Cooperativas Agr\u00cdcolas",
    "sg:phone":"+34 953 44 00 58",
    "sg:postcode":"23300",
    "sg:province":"Ja\u00e9n",
    "wof:name":"Cooperativa Nuestra Senora Del Pilar",
    "wof:placetype":"venue"
},
  "geometry": {"coordinates":[-3.0878789425,38.1153488159],"type":"Point"}
}