{
  "type": "Feature",
  "properties": {
    "iso:country":"ES",
    "sg:address":"Cabo Cope, 8",
    "sg:city":"Urb. Golf",
    "sg:orig_category":"Centros Empresariales",
    "sg:phone":"+34 916 30 34 14",
    "sg:postcode":"28290",
    "sg:province":"Madrid",
    "wof:name":"F.j.safont Y Asociados S.l.",
    "wof:placetype":"venue"
},
  "geometry": {"coordinates":[-3.910615921,40.5451660156],"type":"Point"}
}