{
  "type": "Feature",
  "properties": {
    "iso:country":"ES",
    "sg:address":"Carrer de Havanera, 8",
    "sg:city":"Crevillent",
    "sg:orig_category":"Encuadernaci\u00d3n E Impresi\u00d3n De Folletos",
    "sg:phone":"+34 965 40 65 99",
    "sg:postcode":"03330",
    "sg:province":"Alicante",
    "wof:name":"Enmarcaciones Gabriel S.l.",
    "wof:placetype":"venue"
},
  "geometry": {"coordinates":[-0.8052690029,38.2463111877],"type":"Point"}
}