{
  "type": "Feature",
  "properties": {
    "addr:full":"Calle de Meira, 12 Coru\u00d1a La Coru\u00f1a 15010",
    "addr:housenumber":"12",
    "addr:postcode":"15010",
    "addr:street":"Calle De Meira;La Corun\u0303A",
    "iso:country":"ES",
    "sg:address":"Calle de Meira, 12",
    "sg:city":"Coru\u00d1a",
    "sg:orig_category":"Alquiler De V\u00cddeo",
    "sg:phone":"+34 981 25 73 26",
    "sg:postcode":"15010",
    "sg:province":"La Coru\u00f1a",
    "wof:name":"Raquel Y Mari Luz Marcos Rodriguez S.c.",
    "wof:placetype":"venue"
},
  "geometry": {"coordinates":[-8.419470787,43.3621902466],"type":"Point"}
}