{
  "type": "Feature",
  "properties": {
    "addr:full":"Trav Corts (les), 24 Hospitalet Llobregat Barcelona 08903",
    "addr:housenumber":"24",
    "addr:postcode":"08903",
    "addr:street":"Trav Corts Les",
    "iso:country":"ES",
    "sg:address":"Trav Corts (les), 24",
    "sg:city":"Hospitalet Llobregat",
    "sg:orig_category":"Muebles, Minoristas",
    "sg:phone":"+34 934 48 38 12",
    "sg:postcode":"08903",
    "sg:province":"Barcelona",
    "wof:name":"Leal Gallego Juan Manuel",
    "wof:placetype":"venue"
},
  "geometry": {"coordinates":[2.1194779873,41.3766136169],"type":"Point"}
}