{
  "type": "Feature",
  "properties": {
    "iso:country":"ES",
    "sg:address":"Av Estatut, 91",
    "sg:city":"Rubi",
    "sg:orig_category":"Arreglo, Reparaci\u00d3n, Piezas Sueltas De Televisi\u00d3n, V\u00cddeo, Hi",
    "sg:phone":"+34 936 97 33 53",
    "sg:postcode":"08191",
    "sg:province":"Barcelona",
    "wof:name":"Colell Blanco Jorge",
    "wof:placetype":"venue"
},
  "geometry": {"coordinates":[2.0385739803,41.492641449],"type":"Point"}
}