{
  "type": "Feature",
  "properties": {
    "iso:country":"ES",
    "sg:address":"Avda Madrid, 21",
    "sg:city":"Brihuega",
    "sg:orig_category":"Asilos De Ancianos. Centros Privados",
    "sg:phone":"+34 949 28 02 47",
    "sg:postcode":"19400",
    "sg:province":"Guadalajara",
    "wof:name":"Centro Geriatrico Europeo S.a.",
    "wof:placetype":"venue"
},
  "geometry": {"coordinates":[-2.8722980022,40.7631835938],"type":"Point"}
}