{
  "type": "Feature",
  "properties": {
    "iso:country":"ES",
    "sg:address":"Urb George Sand, 1",
    "sg:city":"Son Ferrandell",
    "sg:orig_category":"Inversiones",
    "sg:phone":"+34 971 61 28 80",
    "sg:postcode":"07170",
    "sg:province":"Islas Baleares",
    "wof:name":"Dudevant Inversiones S.l.",
    "wof:placetype":"venue"
},
  "geometry": {"coordinates":[2.613722086,39.7096595764],"type":"Point"}
}