{
  "type": "Feature",
  "properties": {
    "addr:full":"Praz Mari\u00d1a (da), 13 Burela Lugo 27880",
    "addr:housenumber":"13",
    "addr:postcode":"27880",
    "addr:street":"Praz Marin\u0303A Da",
    "iso:country":"ES",
    "sg:address":"Praz Mari\u00d1a (da), 13",
    "sg:city":"Burela",
    "sg:orig_category":"Ingeniero",
    "sg:phone":"+34 982 58 63 30",
    "sg:postcode":"27880",
    "sg:province":"Lugo",
    "wof:name":"Tecnologias Y Servicios Agrarios S.a.",
    "wof:placetype":"venue"
},
  "geometry": {"coordinates":[-7.3604969978,43.658657074],"type":"Point"}
}