{
  "type": "Feature",
  "properties": {
    "iso:country":"ES",
    "sg:address":"Calle de San Pelayo, 2",
    "sg:city":"Aranda Duero",
    "sg:orig_category":"Bazares, Art\u00cdculos De Limpieza Y De Cocina (al Por Menor)",
    "sg:phone":"+34 947 50 08 51",
    "sg:postcode":"09400",
    "sg:province":"Burgos",
    "wof:name":"Acebes Arranz Antonio",
    "wof:placetype":"venue"
},
  "geometry": {"coordinates":[-3.6867814064,41.6701927185],"type":"Point"}
}