{
  "type": "Feature",
  "properties": {
    "addr:full":"Av Tenes, S/n Pla Barcelona 08185",
    "addr:housenumber":"s",
    "addr:postcode":"08185",
    "addr:street":"Av Tenes;/ N Pla Barcelona",
    "iso:country":"ES",
    "sg:address":"Av Tenes, S/n",
    "sg:city":"Pla",
    "sg:orig_category":"Rectificaci\u00d3n, Mecanizado, Fresado",
    "sg:phone":"+34 938 43 82 20",
    "sg:postcode":"08185",
    "sg:province":"Barcelona",
    "wof:name":"Mecanitzats Fergrin S.l.",
    "wof:placetype":"venue"
},
  "geometry": {"coordinates":[2.2325119972,41.5866622925],"type":"Point"}
}