{
  "type": "Feature",
  "properties": {
    "iso:country":"ES",
    "sg:address":"Rua Seselle, 14",
    "sg:city":"Ferrol",
    "sg:orig_category":"Ense\u00d1anza Variada",
    "sg:phone":"+34 981 31 21 50",
    "sg:postcode":"15403",
    "sg:province":"La Coru\u00f1a",
    "wof:name":"Premir-oposiciones Medicas S.l.",
    "wof:placetype":"venue"
},
  "geometry": {"coordinates":[-8.2217674255,43.4913978577],"type":"Point"}
}