{
  "type": "Feature",
  "properties": {
    "iso:country":"ES",
    "sg:address":"Cra. Olot, 75",
    "sg:city":"Manlleu",
    "sg:orig_category":"Reposter\u00cdas",
    "sg:phone":"+34 938 51 17 52",
    "sg:postcode":"08560",
    "sg:province":"Barcelona",
    "wof:name":"Forn De Pa Altarriba S.l.",
    "wof:placetype":"venue"
},
  "geometry": {"coordinates":[2.2941789627,42.003818512],"type":"Point"}
}