{
  "type": "Feature",
  "properties": {
    "iso:country":"ES",
    "sg:address":"Carr Correu Vell, 8",
    "sg:city":"Lleida",
    "sg:orig_category":"Ropa De Ocasi\u00d3n (al Por Mayor)",
    "sg:phone":"+34 973 27 35 19",
    "sg:postcode":"25002",
    "sg:province":"Lleida",
    "wof:name":"Diagonal Franquicias S.l.",
    "wof:placetype":"venue"
},
  "geometry": {"coordinates":[0.6228219867,41.6119918823],"type":"Point"}
}