{
  "type": "Feature",
  "properties": {
    "addr:full":"Carrer de Guillem De Palafolls, 13 Malgrat Mar Barcelona 08380",
    "addr:housenumber":"13",
    "addr:postcode":"08380",
    "addr:street":"Carrer De Guillem De Palafolls",
    "iso:country":"ES",
    "sg:address":"Carrer de Guillem De Palafolls, 13",
    "sg:city":"Malgrat Mar",
    "sg:orig_category":"Molduras, Junquillos, Listones Y Molduras Perforadas",
    "sg:phone":"+34 937 65 42 52",
    "sg:postcode":"08380",
    "sg:province":"Barcelona",
    "wof:name":"Jaen Cote Miguel",
    "wof:placetype":"venue"
},
  "geometry": {"coordinates":[2.7359969616,41.6486091614],"type":"Point"}
}