{
  "type": "Feature",
  "properties": {
    "iso:country":"ES",
    "sg:address":"Carretera De Aranda-salas, S/n",
    "sg:city":"Coru\u00f1a Conde",
    "sg:orig_category":"Transportes Especiales",
    "sg:phone":"+34 947 52 72 47",
    "sg:postcode":"09410",
    "sg:province":"Burgos",
    "wof:name":"Lopez Calvo Isaac",
    "wof:placetype":"venue"
},
  "geometry": {"coordinates":[-3.4278891087,41.7380714417],"type":"Point"}
}