{
  "type": "Feature",
  "properties": {
    "addr:full":"Carrer de Formentera, 5 Gloria -calvari -gialma Alicante 03110",
    "addr:housenumber":"5",
    "addr:postcode":"03110",
    "addr:street":"Carrer De Formentera",
    "iso:country":"ES",
    "sg:address":"Carrer de Formentera, 5",
    "sg:city":"Gloria -calvari -gialma",
    "sg:orig_category":"Prot\u00c9sicos Dentales",
    "sg:phone":"+34 965 95 07 62",
    "sg:postcode":"03110",
    "sg:province":"Alicante",
    "wof:name":"Mate Calderoni Pedro",
    "wof:placetype":"venue"
},
  "geometry": {"coordinates":[-0.4494589865,38.4053878784],"type":"Point"}
}