{
  "type": "Feature",
  "properties": {
    "iso:country":"ES",
    "sg:address":"Avda Natividad Sanz De Lezaun Lorente, 35",
    "sg:city":"Librilla",
    "sg:orig_category":"Aguas (distribuci\u00d3n, Servicios)",
    "sg:phone":"+34 968 65 76 49",
    "sg:postcode":"30892",
    "sg:province":"Murcia",
    "wof:name":"Aqualia Gestion Integral Del Agua S.a.",
    "wof:placetype":"venue"
},
  "geometry": {"coordinates":[-1.3372823,37.8967056274],"type":"Point"}
}