{
  "type": "Feature",
  "properties": {
    "iso:country":"ES",
    "sg:address":"Avgd Pintor Gomar, S/n",
    "sg:city":"Beniganim",
    "sg:orig_category":"Frutas Y Legumbres Frescas (al Por Mayor)",
    "sg:phone":"+34 962 21 53 66",
    "sg:postcode":"46830",
    "sg:province":"Valencia",
    "wof:name":"Garcia Llopis Miguel",
    "wof:placetype":"venue"
},
  "geometry": {"coordinates":[-0.447863996,38.9413452148],"type":"Point"}
}