{
  "type": "Feature",
  "properties": {
    "addr:full":"Calle de Vicente Blasco Iba\u00d1ez, 18 Sestao Vizcaya 48910",
    "addr:housenumber":"18",
    "addr:postcode":"48910",
    "addr:street":"Calle De Vicente Blasco Iban\u0303Ez",
    "iso:country":"ES",
    "sg:address":"Calle de Vicente Blasco Iba\u00d1ez, 18",
    "sg:city":"Sestao",
    "sg:orig_category":"Centros Empresariales",
    "sg:phone":"+34 944 72 31 03",
    "sg:postcode":"48910",
    "sg:province":"Vizcaya",
    "wof:name":"Consulting Sestao S.l.",
    "wof:placetype":"venue"
},
  "geometry": {"coordinates":[-3.0020720959,43.3079185486],"type":"Point"}
}