{
  "type": "Feature",
  "properties": {
    "addr:full":"Ctra Cabezas Rubias, S/n Santa Barbara De Casa Huelva 21570",
    "addr:housenumber":"s / n",
    "addr:postcode":"21570",
    "addr:street":"Ctra Cabezas Rubias",
    "iso:country":"ES",
    "sg:address":"Ctra Cabezas Rubias, S/n",
    "sg:city":"Santa Barbara De Casa",
    "sg:orig_category":"Producci\u00d3n, Venta De Productos De Agricultura Biol\u00d3gica",
    "sg:phone":"+34 959 57 02 07",
    "sg:postcode":"21570",
    "sg:province":"Huelva",
    "wof:name":"Moron Macias Juan Manuel",
    "wof:placetype":"venue"
},
  "geometry": {"coordinates":[-7.1895809174,37.7967605591],"type":"Point"}
}