{
  "type": "Feature",
  "properties": {
    "addr:full":"Carrer de Duero, 4 Terrassa Barcelona 08223",
    "addr:housenumber":"4",
    "addr:postcode":"08223",
    "addr:street":"Carrer De Duero",
    "iso:country":"ES",
    "sg:address":"Carrer de Duero, 4",
    "sg:city":"Terrassa",
    "sg:orig_category":"Discotecas Y Salas De Baile",
    "sg:phone":"+34 937 36 00 92",
    "sg:postcode":"08223",
    "sg:province":"Barcelona",
    "wof:name":"Salsodromo Latino S.l.",
    "wof:placetype":"venue"
},
  "geometry": {"coordinates":[2.0304749012,41.5577507019],"type":"Point"}
}