{
  "type": "Feature",
  "properties": {
    "iso:country":"ES",
    "sg:address":"Cra Laurea Miro, 348",
    "sg:city":"Sant Feliu Llobregat",
    "sg:orig_category":"Agencias Y Agentes Comerciales, Representantes",
    "sg:phone":"+34 936 66 97 80",
    "sg:postcode":"08980",
    "sg:province":"Barcelona",
    "wof:name":"Coll Ruiz Rosa",
    "wof:placetype":"venue"
},
  "geometry": {"coordinates":[2.0410881042,41.3845291138],"type":"Point"}
}