{
  "type": "Feature",
  "properties": {
    "iso:country":"ES",
    "sg:address":"San Roman, Km. 0003,0",
    "sg:city":"Toro",
    "sg:orig_category":"Cr\u00cda De Animales",
    "sg:phone":"+34 980 56 80 27",
    "sg:postcode":"49800",
    "sg:province":"Zamora",
    "wof:name":"Pelayo Ruiz Tomas",
    "wof:placetype":"venue"
},
  "geometry": {"coordinates":[-5.3860092163,41.5202484131],"type":"Point"}
}