{
  "type": "Feature",
  "properties": {
    "iso:country":"ES",
    "sg:address":"Calle de Manuel Cantos, 8",
    "sg:city":"San Pedro Alcantara",
    "sg:orig_category":"Peluquer\u00cdas, Peluquer\u00cda Mixta",
    "sg:phone":"+34 952 78 24 93",
    "sg:postcode":"29670",
    "sg:province":"M\u00e1laga",
    "wof:name":"Reina Rivero Miguel",
    "wof:placetype":"venue"
},
  "geometry": {"coordinates":[-4.9903540611,36.4859161377],"type":"Point"}
}