{
  "type": "Feature",
  "properties": {
    "iso:country":"ES",
    "sg:address":"Carr Llibertat, 23",
    "sg:city":"Vilanova I La Geltru",
    "sg:orig_category":"Asesor\u00cda Fiscal Y Jur\u00cddica",
    "sg:phone":"+34 938 93 44 16",
    "sg:postcode":"08800",
    "sg:province":"Barcelona",
    "wof:name":"Gabinet D'assessorament I Gestio De Vilanova S.l.",
    "wof:placetype":"venue"
},
  "geometry": {"coordinates":[1.7276610136,41.2221221924],"type":"Point"}
}