{
  "type": "Feature",
  "properties": {
    "iso:country":"ES",
    "sg:address":"Rua Numero 7, S/n",
    "sg:city":"Poligono Industrial",
    "sg:orig_category":"Limpieza Industrial",
    "sg:phone":"+34 988 25 68 11",
    "sg:postcode":"32901",
    "sg:province":"Ourense",
    "wof:name":"Nieto Atrio Ramiro",
    "wof:placetype":"venue"
},
  "geometry": {"coordinates":[-7.8334488869,42.2905006409],"type":"Point"}
}