{
  "type": "Feature",
  "properties": {
    "addr:full":"Avda Constitucion (la), 6 Villablino Le\u00f3n 24100",
    "addr:housenumber":"6",
    "addr:postcode":"24100",
    "addr:street":"Avda Constitucion La",
    "iso:country":"ES",
    "sg:address":"Avda Constitucion (la), 6",
    "sg:city":"Villablino",
    "sg:orig_category":"M\u00c9dicos: Estomatolog\u00cda",
    "sg:phone":"+34 987 47 09 08",
    "sg:postcode":"24100",
    "sg:province":"Le\u00f3n",
    "wof:name":"Garcia Polo Virgilio",
    "wof:placetype":"venue"
},
  "geometry": {"coordinates":[-6.3177394867,42.9393157959],"type":"Point"}
}