{
  "type": "Feature",
  "properties": {
    "iso:country":"ES",
    "sg:address":"Carrer de Cases Noves (les), 61",
    "sg:city":"Cases Noves",
    "sg:orig_category":"Deportes N\u00c1uticos, Acu\u00c1ticos Y Subacu\u00c1ticos: Art\u00cdculos Y Equipo (al Por Menor)",
    "sg:phone":"+34 937 79 35 46",
    "sg:postcode":"08790",
    "sg:province":"Barcelona",
    "wof:name":"Marine Business S. A.",
    "wof:placetype":"venue"
},
  "geometry": {"coordinates":[1.8617899418,41.4394607544],"type":"Point"}
}