{
  "type": "Feature",
  "properties": {
    "iso:country":"ES",
    "sg:address":"Plaz Espa\u00d1a, 5",
    "sg:city":"Andratx",
    "sg:orig_category":"\u00d3ptica: Instrumentos (fabricaci\u00d3n)",
    "sg:phone":"+34 971 13 68 00",
    "sg:postcode":"07150",
    "sg:province":"Islas Baleares",
    "wof:name":"Jorge Sampedro S.l.",
    "wof:placetype":"venue"
},
  "geometry": {"coordinates":[2.420511961,39.5750541687],"type":"Point"}
}