{
  "type": "Feature",
  "properties": {
    "addr:full":"Carr Pla De L'arc (del), 27 Lliria Valencia 46160",
    "addr:housenumber":"27",
    "addr:postcode":"46160",
    "addr:street":"Carr Pla De L'Arc Del",
    "iso:country":"ES",
    "sg:address":"Carr Pla De L'arc (del), 27",
    "sg:city":"Lliria",
    "sg:orig_category":"Comercio, Reparaci\u00d3n De Motocicletas, Bicicletas Y Piezas Sueltas",
    "sg:phone":"+34 962 78 27 01",
    "sg:postcode":"46160",
    "sg:province":"Valencia",
    "wof:name":"Blanch Perez Daniel",
    "wof:placetype":"venue"
},
  "geometry": {"coordinates":[-0.5938966274,39.6315498352],"type":"Point"}
}