{
  "type": "Feature",
  "properties": {
    "iso:country":"ES",
    "sg:address":"Calle de Ermita, 10",
    "sg:city":"Burlada",
    "sg:orig_category":"Peluqueros: De Se\u00d1oras",
    "sg:phone":"+34 948 23 09 17",
    "sg:postcode":"31600",
    "sg:province":"Navarra",
    "wof:name":"Agirre Vila Cristina",
    "wof:placetype":"venue"
},
  "geometry": {"coordinates":[-1.6136356592,42.825378418],"type":"Point"}
}