{
  "type": "Feature",
  "properties": {
    "addr:full":"Pase Sagasta, 62 Zaragoza Zaragoza 50006",
    "addr:housenumber":"62",
    "addr:postcode":"50006",
    "iso:country":"ES",
    "sg:address":"Pase Sagasta, 62",
    "sg:city":"Zaragoza",
    "sg:orig_category":"Institutos De Belleza",
    "sg:phone":"+34 976 27 32 63",
    "sg:postcode":"50006",
    "sg:province":"Zaragoza",
    "wof:name":"Gonzalez Perez Maria Del Pilar",
    "wof:placetype":"venue"
},
  "geometry": {"coordinates":[-0.8866540194,41.6407661438],"type":"Point"}
}