{
  "type": "Feature",
  "properties": {
    "addr:full":"Carrer de Gurb, 2 Vic Barcelona 08500",
    "addr:housenumber":"2",
    "addr:postcode":"08500",
    "addr:street":"Carrer De Gurb",
    "iso:country":"ES",
    "sg:address":"Carrer de Gurb, 2",
    "sg:city":"Vic",
    "sg:orig_category":"Fabricaci\u00d3n, Importaci\u00d3n De L\u00c1mparas Y Bombillas",
    "sg:phone":"+34 938 86 04 35",
    "sg:postcode":"08500",
    "sg:province":"Barcelona",
    "wof:name":"Clos Rovira Alberto",
    "wof:placetype":"venue"
},
  "geometry": {"coordinates":[2.2536129951,41.9314041138],"type":"Point"}
}