{
  "type": "Feature",
  "properties": {
    "iso:country":"ES",
    "sg:address":"Carr Josep Tarradellas, 18",
    "sg:city":"Blanes",
    "sg:orig_category":"Poller\u00cda Y Caza (al Por Menor)",
    "sg:phone":"+34 972 33 05 20",
    "sg:postcode":"17300",
    "sg:province":"Girona",
    "wof:name":"Bancells Barnes Rafael",
    "wof:placetype":"venue"
},
  "geometry": {"coordinates":[2.7863221169,41.6687927246],"type":"Point"}
}