{
  "type": "Feature",
  "properties": {
    "iso:country":"ES",
    "sg:address":"Avda Paz De (la), 33",
    "sg:city":"Riba-roja Turia",
    "sg:orig_category":"Mercer\u00cda, Lencer\u00cda (al Por Menor)",
    "sg:phone":"+34 962 77 14 15",
    "sg:postcode":"46190",
    "sg:province":"Valencia",
    "wof:name":"Chaparro Verdeguer Jose",
    "wof:placetype":"venue"
},
  "geometry": {"coordinates":[-0.5698940158,39.5458450317],"type":"Point"}
}