{
  "type": "Feature",
  "properties": {
    "addr:full":"Cmn Fuente Clerigo, 5 Lupiana Guadalajara 19142",
    "addr:housenumber":"5",
    "addr:postcode":"19142",
    "addr:street":"Fuente Clerigo",
    "iso:country":"ES",
    "sg:address":"Cmn Fuente Clerigo, 5",
    "sg:city":"Lupiana",
    "sg:orig_category":"Ingeniero",
    "sg:phone":"+34 949 29 12 13",
    "sg:postcode":"19142",
    "sg:province":"Guadalajara",
    "wof:name":"Cchamb I D S.l.",
    "wof:placetype":"venue"
},
  "geometry": {"coordinates":[-2.9693589211,40.6648216248],"type":"Point"}
}