{
  "type": "Feature",
  "properties": {
    "addr:full":"Carr Progres, 226 Badalona Barcelona 08918",
    "addr:housenumber":"226",
    "addr:postcode":"08918",
    "addr:street":"Carr Progres",
    "iso:country":"ES",
    "sg:address":"Carr Progres, 226",
    "sg:city":"Badalona",
    "sg:orig_category":"Muebles, Minoristas",
    "sg:phone":"+34 933 99 51 05",
    "sg:postcode":"08918",
    "sg:province":"Barcelona",
    "wof:name":"Aplitex Sl",
    "wof:placetype":"venue"
},
  "geometry": {"coordinates":[2.2364726067,41.4375648499],"type":"Point"}
}