{
  "type": "Feature",
  "properties": {
    "addr:full":"Calle de San Pedro, S/n Benasque Huesca 22440",
    "addr:housenumber":"/ n",
    "addr:postcode":"22440",
    "addr:street":"Calle De San Pedro S",
    "iso:country":"ES",
    "sg:address":"Calle de San Pedro, S/n",
    "sg:city":"Benasque",
    "sg:orig_category":"Caf\u00c9s, Bares, Cervecer\u00cdas",
    "sg:phone":"+34 974 55 12 79",
    "sg:postcode":"22440",
    "sg:province":"Huesca",
    "wof:name":"Hotel Guerri S. A.",
    "wof:placetype":"venue"
},
  "geometry": {"coordinates":[0.5229349732,42.6034965515],"type":"Point"}
}