{
  "type": "Feature",
  "properties": {
    "addr:full":"Pla\u00c7 Francisca Navarro, 8 Burjassot Valencia 46100",
    "addr:housenumber":"8",
    "addr:postcode":"46100",
    "addr:street":"Navarro",
    "iso:country":"ES",
    "sg:address":"Pla\u00c7 Francisca Navarro, 8",
    "sg:city":"Burjassot",
    "sg:orig_category":"Florister\u00cdas",
    "sg:phone":"+34 963 90 36 92",
    "sg:postcode":"46100",
    "sg:province":"Valencia",
    "wof:name":"Alvarez Cerda Elena",
    "wof:placetype":"venue"
},
  "geometry": {"coordinates":[-0.4101619124,39.5090026855],"type":"Point"}
}