{
  "type": "Feature",
  "properties": {
    "addr:full":"Abejeras, 5 Iru\u00f1a Navarra 31007",
    "addr:housenumber":"5",
    "addr:postcode":"31007",
    "addr:street":"Abejeras",
    "iso:country":"ES",
    "sg:address":"Abejeras, 5",
    "sg:city":"Iru\u00f1a",
    "sg:orig_category":"Internados & Ense\u00d1anza Privada",
    "sg:phone":"+34 948 19 92 03",
    "sg:postcode":"31007",
    "sg:province":"Navarra",
    "wof:name":"Hijas De La Caridad De San Vicente De Paul",
    "wof:placetype":"venue"
},
  "geometry": {"coordinates":[-1.6452333927,42.8072013855],"type":"Point"}
}