{
  "type": "Feature",
  "properties": {
    "addr:full":"Calle de Adolfo Diaz Ambrona, 23 Villanueva Serena Badajoz 06700",
    "addr:housenumber":"23",
    "addr:postcode":"06700",
    "addr:street":"Calle De Adolfo Diaz Ambrona",
    "iso:country":"ES",
    "sg:address":"Calle de Adolfo Diaz Ambrona, 23",
    "sg:city":"Villanueva Serena",
    "sg:orig_category":"Agencias De Viajes",
    "sg:phone":"+34 924 84 31 00",
    "sg:postcode":"06700",
    "sg:province":"Badajoz",
    "sg:website":"www.halconviajes.com",
    "wof:name":"Viajes Halcon S.a.",
    "wof:placetype":"venue"
},
  "geometry": {"coordinates":[-5.798014164,38.9725990295],"type":"Point"}
}