{
  "type": "Feature",
  "properties": {
    "addr:full":"Rua San Diego, 19 Ferrol La Coru\u00f1a 15401",
    "addr:housenumber":"19",
    "addr:postcode":"15401",
    "addr:street":"Rua San Diego;La Corun\u0303A",
    "iso:country":"ES",
    "sg:address":"Rua San Diego, 19",
    "sg:city":"Ferrol",
    "sg:orig_category":"Asociaciones, Organismos Culturales Y Socioeducativos",
    "sg:phone":"+34 981 35 28 90",
    "sg:postcode":"15401",
    "sg:province":"La Coru\u00f1a",
    "wof:name":"Asociacion Cultural Mundo Danza",
    "wof:placetype":"venue"
},
  "geometry": {"coordinates":[-8.2397146225,43.4821166992],"type":"Point"}
}