{
  "type": "Feature",
  "properties": {
    "iso:country":"ES",
    "sg:address":"Pase Maritimo, 35",
    "sg:city":"Torremolinos",
    "sg:orig_category":"Art\u00cdculos De Regalo (al Por Menor)",
    "sg:phone":"+34 952 37 59 48",
    "sg:postcode":"29620",
    "sg:province":"M\u00e1laga",
    "wof:name":"Josefranci S.l.",
    "wof:placetype":"venue"
},
  "geometry": {"coordinates":[-4.492978096,36.6251068115],"type":"Point"}
}