{
  "type": "Feature",
  "properties": {
    "iso:country":"ES",
    "sg:address":"Calle de Santa Clara, 2",
    "sg:city":"Avila",
    "sg:orig_category":"T\u00c9cnicos Veterinarios",
    "sg:phone":"+34 920 22 07 14",
    "sg:postcode":"05001",
    "sg:province":"\u00c1vila",
    "wof:name":"Reviriego Reviriego Genaro",
    "wof:placetype":"venue"
},
  "geometry": {"coordinates":[-4.690223217,40.6538238525],"type":"Point"}
}