{
  "type": "Feature",
  "properties": {
    "iso:country":"ES",
    "sg:address":"Calle de Lapislazuli, 5",
    "sg:city":"Estacion",
    "sg:orig_category":"Mec\u00c1nico Del Autom\u00d3vil",
    "sg:phone":"+34 918 40 63 35",
    "sg:postcode":"28400",
    "sg:province":"Madrid",
    "wof:name":"Diez Villarroel Jesus",
    "wof:placetype":"venue"
},
  "geometry": {"coordinates":[-4.0185031891,40.6242218018],"type":"Point"}
}