{
  "type": "Feature",
  "properties": {
    "addr:full":"Avda Miajadas, 6 Trujillo C\u00e1ceres 10200",
    "addr:housenumber":"6",
    "addr:postcode":"10200",
    "addr:street":"Avda Miajadas;Ca\u0301Ceres",
    "iso:country":"ES",
    "sg:address":"Avda Miajadas, 6",
    "sg:city":"Trujillo",
    "sg:orig_category":"Contenedores (mercanc\u00cdas)",
    "sg:phone":"+34 927 32 18 73",
    "sg:postcode":"10200",
    "sg:province":"C\u00e1ceres",
    "wof:name":"Seur Caceres S.a.",
    "wof:placetype":"venue"
},
  "geometry": {"coordinates":[-5.8812861443,39.4555015564],"type":"Point"}
}