{
  "type": "Feature",
  "properties": {
    "addr:full":"Carrer de Gran De Sant Andreu, 208 Barcelona Barcelona 08030",
    "addr:housenumber":"208",
    "addr:postcode":"08030",
    "addr:street":"Carrer De Gran De Sant Andreu",
    "iso:country":"ES",
    "sg:address":"Carrer de Gran De Sant Andreu, 208",
    "sg:city":"Barcelona",
    "sg:orig_category":"Ropa Para Se\u00d1oras Y Caballeros (al Por Menor)",
    "sg:phone":"+34 933 11 00 74",
    "sg:postcode":"08030",
    "sg:province":"Barcelona",
    "wof:name":"M S Mode Spain,sucursal En Espa\u00d1a",
    "wof:placetype":"venue"
},
  "geometry": {"coordinates":[2.1895558834,41.433719635],"type":"Point"}
}