{
  "type": "Feature",
  "properties": {
    "iso:country":"ES",
    "sg:address":"Calle de Renteria Reyes, 12",
    "sg:city":"Santo\u00f1a",
    "sg:orig_category":"Colchones (fabricaci\u00d3n, Al Por Mayor, Al Por Menor)",
    "sg:phone":"+34 942 66 10 96",
    "sg:postcode":"39740",
    "sg:province":"Cantabria",
    "wof:name":"Artcon Muebles S.l.",
    "wof:placetype":"venue"
},
  "geometry": {"coordinates":[-3.4572684765,43.4424591064],"type":"Point"}
}