{
  "type": "Feature",
  "properties": {
    "iso:country":"ES",
    "sg:address":"Avda Castrelos, 424",
    "sg:city":"Vigo",
    "sg:orig_category":"Empresas De Carpinter\u00cda De Madera",
    "sg:phone":"+34 986 23 70 60",
    "sg:postcode":"36213",
    "sg:province":"Pontevedra",
    "wof:name":"Fernandez Perez Manuel",
    "wof:placetype":"venue"
},
  "geometry": {"coordinates":[-8.7217006683,42.1961593628],"type":"Point"}
}