{
  "type": "Feature",
  "properties": {
    "iso:country":"ES",
    "sg:address":"Carrer de Pau Casals, 7",
    "sg:city":"S. Cugat Valles",
    "sg:orig_category":"Agencias Y Agentes Comerciales, Representantes",
    "sg:phone":"+34 936 75 45 01",
    "sg:postcode":"08172",
    "sg:province":"Barcelona",
    "wof:name":"Tric Tac Tresc S.l.",
    "wof:placetype":"venue"
},
  "geometry": {"coordinates":[2.0910449028,41.4711074829],"type":"Point"}
}