{
  "type": "Feature",
  "properties": {
    "addr:full":"Carrer de Sant Jaume, 51 Granollers Barcelona 08401",
    "addr:housenumber":"51",
    "addr:postcode":"08401",
    "addr:street":"Carrer De Sant Jaume",
    "iso:country":"ES",
    "sg:address":"Carrer de Sant Jaume, 51",
    "sg:city":"Granollers",
    "sg:orig_category":"Fabricaci\u00d3n De Motores El\u00c9ctricos",
    "sg:phone":"+34 938 70 56 48",
    "sg:postcode":"08401",
    "sg:province":"Barcelona",
    "sg:website":"www.paginasamarillas.es",
    "wof:name":"Cassart Puig Josep",
    "wof:placetype":"venue"
},
  "geometry": {"coordinates":[2.2858450413,41.6057243347],"type":"Point"}
}