{
  "type": "Feature",
  "properties": {
    "iso:country":"ES",
    "sg:address":"Calle de Sangenis, 7",
    "sg:city":"Zaragoza",
    "sg:orig_category":"Lencer\u00cda Femenina, Corseter\u00cda, Trajes De Ba\u00d1o (al Por Menor)",
    "sg:phone":"+34 976 33 32 38",
    "sg:postcode":"50010",
    "sg:province":"Zaragoza",
    "wof:name":"Remolar Perez Arturo",
    "wof:placetype":"venue"
},
  "geometry": {"coordinates":[-0.9045190215,41.6526985168],"type":"Point"}
}