{
  "type": "Feature",
  "properties": {
    "iso:country":"ES",
    "sg:address":"Calle de Breton De Los Herreros, 9",
    "sg:city":"Lardero",
    "sg:orig_category":"Reposter\u00cdas",
    "sg:phone":"+34 941 44 86 74",
    "sg:postcode":"26140",
    "sg:province":"La Rioja",
    "wof:name":"Sanpedro Vallejo Purificacion",
    "wof:placetype":"venue"
},
  "geometry": {"coordinates":[-2.4612729549,42.4273109436],"type":"Point"}
}