{
  "type": "Feature",
  "properties": {
    "iso:country":"ES",
    "sg:address":"Calle de Estacion, 59",
    "sg:city":"Almanzora",
    "sg:orig_category":"Estancos",
    "sg:phone":"+34 950 12 05 46",
    "sg:postcode":"04815",
    "sg:province":"Almer\u00eda",
    "wof:name":"Garcia Pi\u00f1ero Ramon",
    "wof:placetype":"venue"
},
  "geometry": {"coordinates":[-2.1366150379,37.3473739624],"type":"Point"}
}