{
  "type": "Feature",
  "properties": {
    "addr:full":"Calle de Ferrandiz, 16 Malaga M\u00e1laga 29012",
    "addr:housenumber":"16",
    "addr:postcode":"29012",
    "addr:street":"Calle De Ferrandiz;Ma\u0301Laga",
    "iso:country":"ES",
    "sg:address":"Calle de Ferrandiz, 16",
    "sg:city":"Malaga",
    "sg:orig_category":"Confecci\u00d3n De Trajes Para Se\u00d1oras",
    "sg:phone":"+34 952 26 70 40",
    "sg:postcode":"29012",
    "sg:province":"M\u00e1laga",
    "wof:name":"Sanchez Fernandez Encarnacion",
    "wof:placetype":"venue"
},
  "geometry": {"coordinates":[-4.4125771523,36.7270507812],"type":"Point"}
}