{
  "type": "Feature",
  "properties": {
    "addr:full":"Calle de Daban, 15 Peralta Navarra 31350",
    "addr:housenumber":"15",
    "addr:postcode":"31350",
    "addr:street":"Calle De Daban",
    "iso:country":"ES",
    "sg:address":"Calle de Daban, 15",
    "sg:city":"Peralta",
    "sg:orig_category":"Carnicer\u00cdas, Carnicer\u00cdas",
    "sg:phone":"+34 948 75 02 82",
    "sg:postcode":"31350",
    "sg:province":"Navarra",
    "wof:name":"Biurrun Rodriguez Carlos",
    "wof:placetype":"venue"
},
  "geometry": {"coordinates":[-1.7954339981,42.3382034302],"type":"Point"}
}