{
  "type": "Feature",
  "properties": {
    "addr:full":"Calle de General Alaminos, 117 Lucena C\u00f3rdoba 14900",
    "addr:housenumber":"117",
    "addr:postcode":"14900",
    "addr:street":"Calle De General Alaminos",
    "iso:country":"ES",
    "sg:address":"Calle de General Alaminos, 117",
    "sg:city":"Lucena",
    "sg:orig_category":"Reposter\u00cdas",
    "sg:phone":"+34 957 50 03 21",
    "sg:postcode":"14900",
    "sg:province":"C\u00f3rdoba",
    "wof:name":"Fernandez Tienda Antonio",
    "wof:placetype":"venue"
},
  "geometry": {"coordinates":[-4.4837632179,37.4142341614],"type":"Point"}
}