{
  "type": "Feature",
  "properties": {
    "iso:country":"ES",
    "sg:address":"Calle de Juan Mu\u00d1oz, 19",
    "sg:city":"Leganes",
    "sg:orig_category":"Lencer\u00cda Femenina, Corseter\u00cda, Trajes De Ba\u00d1o (al Por Menor)",
    "sg:phone":"+34 916 94 60 25",
    "sg:postcode":"28911",
    "sg:province":"Madrid",
    "wof:name":"Condisalva S.l.",
    "wof:placetype":"venue"
},
  "geometry": {"coordinates":[-3.7670199871,40.3296318054],"type":"Point"}
}