{
  "type": "Feature",
  "properties": {
    "iso:country":"ES",
    "sg:address":"Carrer de Capita Vila, 8",
    "sg:city":"Palma",
    "sg:orig_category":"Alimentaci\u00d3n General (al Por Menor)",
    "sg:phone":"+34 971 27 59 69",
    "sg:postcode":"07007",
    "sg:province":"Islas Baleares",
    "wof:name":"Vidal Rossello Maria",
    "wof:placetype":"venue"
},
  "geometry": {"coordinates":[2.6645569801,39.5735664368],"type":"Point"}
}