{
  "type": "Feature",
  "properties": {
    "addr:full":"Opera, 4 Valladolid Valladolid 47009",
    "addr:postcode":"47009",
    "addr:street":"Opera",
    "iso:country":"ES",
    "sg:address":"Opera, 4",
    "sg:city":"Valladolid",
    "sg:orig_category":"Librer\u00cdas",
    "sg:phone":"+34 983 34 91 09",
    "sg:postcode":"47009",
    "sg:province":"Valladolid",
    "wof:name":"Fabricacion Y Distribucion De Pan S.l.",
    "wof:placetype":"venue"
},
  "geometry": {"coordinates":[-4.7416100502,41.6846084595],"type":"Point"}
}