{
  "type": "Feature",
  "properties": {
    "addr:full":"Avda Blas Infante, 6 Sevilla Sevilla 41011",
    "addr:housenumber":"6",
    "addr:postcode":"41011",
    "addr:street":"Avda Blas Infante",
    "iso:country":"ES",
    "sg:address":"Avda Blas Infante, 6",
    "sg:city":"Sevilla",
    "sg:orig_category":"Arquitectos",
    "sg:phone":"+34 954 45 34 00",
    "sg:postcode":"41011",
    "sg:province":"Sevilla",
    "wof:name":"Lopez Amate Francisco Jose",
    "wof:placetype":"venue"
},
  "geometry": {"coordinates":[-6.0066189766,37.3753166199],"type":"Point"}
}