{
  "type": "Feature",
  "properties": {
    "iso:country":"ES",
    "sg:address":"Avda Conde De Guadalhorce, S/n",
    "sg:city":"Aviles",
    "sg:orig_category":"Distribuci\u00d3n De Petr\u00d3leo Y Derivados",
    "sg:phone":"+34 985 56 56 83",
    "sg:postcode":"33401",
    "sg:province":"Asturias",
    "wof:name":"Marpesca C.b.",
    "wof:placetype":"venue"
},
  "geometry": {"coordinates":[-5.9242491722,43.577583313],"type":"Point"}
}