{
  "type": "Feature",
  "properties": {
    "addr:full":"Carrer de Jaume I, 67 S. Celoni Barcelona 08470",
    "addr:housenumber":"67",
    "addr:postcode":"08470",
    "addr:street":"Carrer De Jaume I;S. Celoni Barcelona",
    "iso:country":"ES",
    "sg:address":"Carrer de Jaume I, 67",
    "sg:city":"S. Celoni",
    "sg:orig_category":"Supermercados Y Hipermercados",
    "sg:phone":"+34 938 67 39 92",
    "sg:postcode":"08470",
    "sg:province":"Barcelona",
    "sg:website":"www.mercadona.es",
    "wof:name":"Mercadona S.a.",
    "wof:placetype":"venue"
},
  "geometry": {"coordinates":[2.4975349903,41.6933441162],"type":"Point"}
}