{
  "type": "Feature",
  "properties": {
    "addr:full":"Carrer de Pere Puig, 133 Martorell Barcelona 08760",
    "addr:housenumber":"133",
    "addr:postcode":"08760",
    "addr:street":"Carrer De Pere Puig",
    "iso:country":"ES",
    "sg:address":"Carrer de Pere Puig, 133",
    "sg:city":"Martorell",
    "sg:orig_category":"Comercio De Piezas De Recambio Y De Accesorios De Veh\u00cdculos, Veh\u00cdculos Industriales",
    "sg:phone":"+34 937 75 38 00",
    "sg:postcode":"08760",
    "sg:province":"Barcelona",
    "sg:website":"www.mavisa.es",
    "wof:name":"Motores Automoviles Y Vehiculos Industriales S.a.",
    "wof:placetype":"venue"
},
  "geometry": {"coordinates":[1.9384429455,41.4727401733],"type":"Point"}
}