{
  "type": "Feature",
  "properties": {
    "addr:full":"Sa Placeta, 4 Alaior Islas Baleares 07730",
    "addr:housenumber":"4",
    "addr:postcode":"07730",
    "addr:street":"Placeta",
    "iso:country":"ES",
    "sg:address":"Sa Placeta, 4",
    "sg:city":"Alaior",
    "sg:orig_category":"Confecci\u00d3n De Zapatos",
    "sg:phone":"+34 971 37 14 14",
    "sg:postcode":"07730",
    "sg:province":"Islas Baleares",
    "wof:name":"Esbert Lopez Marga",
    "wof:placetype":"venue"
},
  "geometry": {"coordinates":[4.1419200897,39.9265403748],"type":"Point"}
}