{
  "type": "Feature",
  "properties": {
    "iso:country":"ES",
    "sg:address":"Calle de Saladillo, 4",
    "sg:city":"Chauchina",
    "sg:orig_category":"Loter\u00cda Y T\u00d3mbola",
    "sg:phone":"+34 958 44 61 35",
    "sg:postcode":"18330",
    "sg:province":"Granada",
    "wof:name":"Sanchez Fernandez Miguel",
    "wof:placetype":"venue"
},
  "geometry": {"coordinates":[-3.7720489502,37.2018966675],"type":"Point"}
}