{
  "type": "Feature",
  "properties": {
    "iso:country":"ES",
    "sg:address":"Avda Region De Murcia, 38",
    "sg:city":"Abanilla",
    "sg:orig_category":"Alimentaci\u00d3n General (al Por Mayor)",
    "sg:phone":"+34 968 68 03 57",
    "sg:postcode":"30640",
    "sg:province":"Murcia",
    "wof:name":"Rivera Tenza Margarita",
    "wof:placetype":"venue"
},
  "geometry": {"coordinates":[-1.0423090458,38.2029685974],"type":"Point"}
}