{
  "type": "Feature",
  "properties": {
    "addr:full":"Calle de Manuel Llaneza, 24 Mieres Asturias 33600",
    "addr:housenumber":"24",
    "addr:postcode":"33600",
    "addr:street":"Calle De Manuel Llaneza",
    "iso:country":"ES",
    "sg:address":"Calle de Manuel Llaneza, 24",
    "sg:city":"Mieres",
    "sg:orig_category":"Mercer\u00cda (fabricaci\u00d3n, Al Por Mayor)",
    "sg:phone":"+34 985 46 42 75",
    "sg:postcode":"33600",
    "sg:province":"Asturias",
    "wof:name":"Fernandez Menendez Josefina",
    "wof:placetype":"venue"
},
  "geometry": {"coordinates":[-5.7745780945,43.2502975464],"type":"Point"}
}