{
  "type": "Feature",
  "properties": {
    "iso:country":"ES",
    "sg:address":"Calle de Pancho Cossio, 30",
    "sg:city":"Torrelavega",
    "sg:orig_category":"Marmolistas Funerarios",
    "sg:phone":"+34 942 80 75 94",
    "sg:postcode":"39300",
    "sg:province":"Cantabria",
    "wof:name":"Albia Gestion De Servicios S.l.",
    "wof:placetype":"venue"
},
  "geometry": {"coordinates":[-4.0517635345,43.3526039124],"type":"Point"}
}