{
  "type": "Feature",
  "properties": {
    "iso:country":"ES",
    "sg:address":"Calle de Jardines, 44",
    "sg:city":"Moraleja",
    "sg:orig_category":"Molduras, Junquillos, Listones Y Molduras Perforadas",
    "sg:phone":"+34 927 14 74 16",
    "sg:postcode":"10840",
    "sg:province":"C\u00e1ceres",
    "wof:name":"Torralvo Hernandez Maria Jesus",
    "wof:placetype":"venue"
},
  "geometry": {"coordinates":[-6.6576638222,40.065788269],"type":"Point"}
}