{
  "type": "Feature",
  "properties": {
    "addr:full":"Calle de Santa Ana, 63 Villarrubia De Los Ojos Ciudad Real 13670",
    "addr:housenumber":"63",
    "addr:postcode":"13670",
    "addr:street":"Calle De Santa Ana",
    "iso:country":"ES",
    "sg:address":"Calle de Santa Ana, 63",
    "sg:city":"Villarrubia De Los Ojos",
    "sg:orig_category":"Peluqueros: De Se\u00d1oras",
    "sg:phone":"+34 926 89 74 80",
    "sg:postcode":"13670",
    "sg:province":"Ciudad Real",
    "wof:name":"Urda Fernandez Florencia",
    "wof:placetype":"venue"
},
  "geometry": {"coordinates":[-3.6060400009,39.2197380066],"type":"Point"}
}