{
  "type": "Feature",
  "properties": {
    "iso:country":"ES",
    "sg:address":"Rua Pi Y Margall, 125",
    "sg:city":"Vigo",
    "sg:orig_category":"Herboristas (al Por Menor)",
    "sg:phone":"+34 986 23 90 29",
    "sg:postcode":"36202",
    "sg:province":"Pontevedra",
    "wof:name":"Alvarez Crucio Bernardo",
    "wof:placetype":"venue"
},
  "geometry": {"coordinates":[-8.7315759659,42.2302055359],"type":"Point"}
}