{
  "type": "Feature",
  "properties": {
    "iso:country":"ES",
    "sg:address":"Calle de Ronda De La Villa, S/n",
    "sg:city":"Longares",
    "sg:orig_category":"Bosques (trabajos, Asesor\u00cda, Gesti\u00d3n)",
    "sg:phone":"+34 976 14 51 03",
    "sg:postcode":"50460",
    "sg:province":"Zaragoza",
    "wof:name":"Agromastral S.l.",
    "wof:placetype":"venue"
},
  "geometry": {"coordinates":[-1.169895,41.402237],"type":"Point"}
}