{
  "type": "Feature",
  "properties": {
    "addr:full":"Calle de Obispo Rabadan, 11 Palmas De Gran Canaria Las Palmas 35003",
    "addr:housenumber":"11",
    "addr:postcode":"35003",
    "addr:street":"Calle De Obispo Rabadan",
    "iso:country":"ES",
    "sg:address":"Calle de Obispo Rabadan, 11",
    "sg:city":"Palmas De Gran Canaria",
    "sg:orig_category":"Internados & Ense\u00d1anza Privada",
    "sg:phone":"+34 928 38 12 88",
    "sg:postcode":"35003",
    "sg:province":"Las Palmas",
    "wof:name":"Religiosos Claretianos.colegio Claret",
    "wof:placetype":"venue"
},
  "geometry": {"coordinates":[-15.4204730988,28.1121940613],"type":"Point"}
}