{
  "type": "Feature",
  "properties": {
    "iso:country":"ES",
    "sg:address":"Calle de Maria Dolores Agirre, 6",
    "sg:city":"Donostia-san Sebastian",
    "sg:orig_category":"Aparcamientos (infraestructuras, Accesorios)",
    "sg:phone":"+34 943 29 80 54",
    "sg:postcode":"20012",
    "sg:province":"Guip\u00f9zcoa",
    "wof:name":"Estacionamientos Guipuzcoanos S. A.",
    "wof:placetype":"venue"
},
  "geometry": {"coordinates":[-1.9760290384,43.3185081482],"type":"Point"}
}