{
  "type": "Feature",
  "properties": {
    "iso:country":"ES",
    "sg:address":"Pla\u00c7 Doctor Fleming, 4",
    "sg:city":"Estartit",
    "sg:orig_category":"Cajas De Ahorro",
    "sg:phone":"+34 972 75 04 69",
    "sg:postcode":"17258",
    "sg:province":"Girona",
    "sg:website":"www.lacaixa.es",
    "wof:name":"Caixa D'estalvis I Pensions De Barcelona",
    "wof:placetype":"venue"
},
  "geometry": {"coordinates":[3.1989519596,42.0540313721],"type":"Point"}
}