{
  "type": "Feature",
  "properties": {
    "iso:country":"ES",
    "sg:address":"Calle de Real, 45",
    "sg:city":"San Sebastian De Los Reyes",
    "sg:orig_category":"Frutas, Legumbres Frescas Y Tempranas (al Por Menor)",
    "sg:phone":"+34 916 52 92 02",
    "sg:postcode":"28700",
    "sg:province":"Madrid",
    "wof:name":"Cabrero Rivero Juan",
    "wof:placetype":"venue"
},
  "geometry": {"coordinates":[-3.6250510216,40.5477218628],"type":"Point"}
}