{
  "type": "Feature",
  "properties": {
    "addr:full":"Carrer de Esteve Brunell, 2 S. Celoni Barcelona 08470",
    "addr:housenumber":"2",
    "addr:postcode":"08470",
    "addr:street":"Carrer De Esteve Brunell",
    "iso:country":"ES",
    "sg:address":"Carrer de Esteve Brunell, 2",
    "sg:city":"S. Celoni",
    "sg:orig_category":"Quincaller\u00cda (al Por Menor)",
    "sg:phone":"+34 938 67 52 34",
    "sg:postcode":"08470",
    "sg:province":"Barcelona",
    "wof:name":"Ferreteria Roig Scp",
    "wof:placetype":"venue"
},
  "geometry": {"coordinates":[2.4855759144,41.6855392456],"type":"Point"}
}