{
  "type": "Feature",
  "properties": {
    "iso:country":"ES",
    "sg:address":"Carrer de Casanova, 37",
    "sg:city":"Barcelona",
    "sg:orig_category":"Asesor\u00cda Fiscal Y Jur\u00cddica",
    "sg:phone":"+34 934 15 54 53",
    "sg:postcode":"08011",
    "sg:province":"Barcelona",
    "wof:name":"Amdalt Consultores S.l.",
    "wof:placetype":"venue"
},
  "geometry": {"coordinates":[2.1604967117,41.3841056824],"type":"Point"}
}