{
  "type": "Feature",
  "properties": {
    "iso:country":"ES",
    "sg:address":"Rua Vila De Noia, S/n",
    "sg:city":"Carballo",
    "sg:orig_category":"Asociaciones Y Clubs Deportivos",
    "sg:phone":"+34 981 70 04 68",
    "sg:postcode":"15100",
    "sg:province":"La Coru\u00f1a",
    "wof:name":"Patronato Deportivo Municipal",
    "wof:placetype":"venue"
},
  "geometry": {"coordinates":[-8.6834392548,43.2178535461],"type":"Point"}
}