{
  "type": "Feature",
  "properties": {
    "iso:country":"ES",
    "sg:address":"Calle de Floridablanca, S/n",
    "sg:city":"Palencia",
    "sg:orig_category":"Peluquer\u00cdas, Peluquer\u00cda Mixta",
    "sg:phone":"+34 979 75 23 23",
    "sg:postcode":"34003",
    "sg:province":"Palencia",
    "wof:name":"Estebanez Merino Maria Yolanda",
    "wof:placetype":"venue"
},
  "geometry": {"coordinates":[-4.5322089195,42.017829895],"type":"Point"}
}