{
  "type": "Feature",
  "properties": {
    "addr:full":"Carrer de Santiago Rusi\u00d1ol, 51 Prat Llobregat Barcelona 08820",
    "addr:housenumber":"51",
    "addr:postcode":"08820",
    "addr:street":"Carrer De Santiago Rusin\u0303Ol;Llobregat",
    "iso:country":"ES",
    "sg:address":"Carrer de Santiago Rusi\u00d1ol, 51",
    "sg:city":"Prat Llobregat",
    "sg:orig_category":"Estancos",
    "sg:phone":"+34 933 79 07 38",
    "sg:postcode":"08820",
    "sg:province":"Barcelona",
    "wof:name":"Torres Navas Jose",
    "wof:placetype":"venue"
},
  "geometry": {"coordinates":[2.0931479931,41.3271903992],"type":"Point"}
}