{
  "type": "Feature",
  "properties": {
    "addr:full":"Calle de Poeta Querol, 5 Valencia Valencia 46002",
    "addr:housenumber":"5",
    "addr:postcode":"46002",
    "addr:street":"Calle De Poeta Querol",
    "iso:country":"ES",
    "sg:address":"Calle de Poeta Querol, 5",
    "sg:city":"Valencia",
    "sg:orig_category":"Abogados",
    "sg:phone":"+34 963 51 33 35",
    "sg:postcode":"46002",
    "sg:province":"Valencia",
    "wof:name":"Ferrer Monforte Luis",
    "wof:placetype":"venue"
},
  "geometry": {"coordinates":[-0.3741819859,39.4721260071],"type":"Point"}
}