{
  "type": "Feature",
  "properties": {
    "addr:full":"Calle de Artajona, 15 Madrid Madrid 28039",
    "addr:housenumber":"15",
    "addr:postcode":"madrid;28039",
    "addr:street":"Calle De Artajona",
    "iso:country":"ES",
    "sg:address":"Calle de Artajona, 15",
    "sg:city":"Madrid",
    "sg:orig_category":"Herboristas (al Por Menor)",
    "sg:phone":"+34 914 50 30 11",
    "sg:postcode":"28039",
    "sg:province":"Madrid",
    "wof:name":"Fernandez Teba Aurora",
    "wof:placetype":"venue"
},
  "geometry": {"coordinates":[-3.7181499004,40.463394165],"type":"Point"}
}