{
  "type": "Feature",
  "properties": {
    "addr:full":"Carrer de Santa Natalia, 21 Sant Moritz Barcelona 08185",
    "addr:housenumber":"21",
    "addr:postcode":"08185",
    "addr:street":"Carrer De Santa Natalia",
    "iso:country":"ES",
    "sg:address":"Carrer de Santa Natalia, 21",
    "sg:city":"Sant Moritz",
    "sg:orig_category":"Organizaciones Profesionales",
    "sg:phone":"+34 938 43 77 17",
    "sg:postcode":"08185",
    "sg:province":"Barcelona",
    "wof:name":"Rexach Perez Jordi",
    "wof:placetype":"venue"
},
  "geometry": {"coordinates":[2.2406799793,41.5862312317],"type":"Point"}
}