{
  "type": "Feature",
  "properties": {
    "iso:country":"ES",
    "sg:address":"Calle de Virgen, 4",
    "sg:city":"Madrid",
    "sg:orig_category":"Maquinaria Para Industrias Diversas",
    "sg:phone":"+34 914 33 90 58",
    "sg:postcode":"28053",
    "sg:province":"Madrid",
    "wof:name":"Saturnino Y Elias Grande Alonso C.b",
    "wof:placetype":"venue"
},
  "geometry": {"coordinates":[-3.6666920185,40.3967628479],"type":"Point"}
}