{
  "type": "Feature",
  "properties": {
    "iso:country":"ES",
    "sg:address":"Avda Madrid, 174",
    "sg:city":"Zaragoza",
    "sg:orig_category":"Colchones (fabricaci\u00d3n, Al Por Mayor, Al Por Menor)",
    "sg:phone":"+34 976 31 60 46",
    "sg:postcode":"50017",
    "sg:province":"Zaragoza",
    "wof:name":"Martinez Fernandez Serafin",
    "wof:placetype":"venue"
},
  "geometry": {"coordinates":[-0.9142460227,41.6513404846],"type":"Point"}
}