{
  "type": "Feature",
  "properties": {
    "iso:country":"ES",
    "sg:address":"Ctra. Granada, Km. 0053,5",
    "sg:city":"Castillo Locubin",
    "sg:orig_category":"Distribuci\u00d3n De Petr\u00d3leo Y Derivados",
    "sg:phone":"+34 953 59 12 40",
    "sg:postcode":"23670",
    "sg:province":"Ja\u00e9n",
    "wof:name":"Morales Burgos Antonia",
    "wof:placetype":"venue"
},
  "geometry": {"coordinates":[-3.9412829876,37.5313835144],"type":"Point"}
}