{
  "type": "Feature",
  "properties": {
    "iso:country":"ES",
    "sg:address":"Carrer de Navas De Tolosa, 253",
    "sg:city":"Barcelona",
    "sg:orig_category":"Pescader\u00cdas (al Por Menor)",
    "sg:phone":"+34 934 08 46 94",
    "sg:postcode":"08026",
    "sg:province":"Barcelona",
    "wof:name":"Ruiz Gomez Francisca",
    "wof:placetype":"venue"
},
  "geometry": {"coordinates":[2.1899750233,41.4128761292],"type":"Point"}
}