{
  "type": "Feature",
  "properties": {
    "iso:country":"ES",
    "sg:address":"Calle de Marques Alonso Martinez, 9",
    "sg:city":"Alcala Henares",
    "sg:orig_category":"Farmacias",
    "sg:phone":"+34 918 89 35 97",
    "sg:postcode":"28804",
    "sg:province":"Madrid",
    "wof:name":"Martinez Garcia Luis Ignacio",
    "wof:placetype":"venue"
},
  "geometry": {"coordinates":[-3.3572590351,40.4852676392],"type":"Point"}
}