{
  "type": "Feature",
  "properties": {
    "iso:country":"ES",
    "sg:address":"Carrer de Enric Prat De La Riba, 201",
    "sg:city":"Hospitalet Llobregat",
    "sg:orig_category":"Delegados, Agentes De Tr\u00c1nsito, Auxiliares De Transporte Internacional",
    "sg:phone":"+34 933 38 47 10",
    "sg:postcode":"08901",
    "sg:province":"Barcelona",
    "wof:name":"Delgado Garcia Manuel",
    "wof:placetype":"venue"
},
  "geometry": {"coordinates":[2.1073849201,41.3615531921],"type":"Point"}
}