{
  "type": "Feature",
  "properties": {
    "addr:full":"Las Lisas, 14 Cuevas Almanzora Almer\u00eda 04610",
    "addr:housenumber":"14",
    "addr:postcode":"04610",
    "addr:street":"Lisas;Almeri\u0301A",
    "iso:country":"ES",
    "sg:address":"Las Lisas, 14",
    "sg:city":"Cuevas Almanzora",
    "sg:orig_category":"Servicios Gsm",
    "sg:phone":"+34 950 45 81 79",
    "sg:postcode":"04610",
    "sg:province":"Almer\u00eda",
    "wof:name":"Hispacom Almeria S.l.",
    "wof:placetype":"venue"
},
  "geometry": {"coordinates":[-1.8781139851,37.2911911011],"type":"Point"}
}