{
  "type": "Feature",
  "properties": {
    "addr:full":"Carrer de Corts D'arago, 50 Sitges Barcelona 08870",
    "addr:housenumber":"50",
    "addr:postcode":"08870",
    "addr:street":"Carrer De Corts D'Arago",
    "iso:country":"ES",
    "sg:address":"Carrer de Corts D'arago, 50",
    "sg:city":"Sitges",
    "sg:orig_category":"Centros Empresariales",
    "sg:phone":"+34 938 11 22 12",
    "sg:postcode":"08870",
    "sg:province":"Barcelona",
    "sg:website":"www.mga.com",
    "wof:name":"Mga Business Consulting S.l.",
    "wof:placetype":"venue"
},
  "geometry": {"coordinates":[1.8215876818,41.2424240112],"type":"Point"}
}