{
  "type": "Feature",
  "properties": {
    "addr:full":"Ctra Aeroport, Km. 0005,4 Sant Jordi De Ses Salines Islas Baleares 07817",
    "addr:postcode":"07817",
    "addr:street":"Ctra Aeroport Km. 0005,4",
    "iso:country":"ES",
    "sg:address":"Ctra Aeroport, Km. 0005,4",
    "sg:city":"Sant Jordi De Ses Salines",
    "sg:orig_category":"Librer\u00cdas",
    "sg:phone":"+34 971 30 85 42",
    "sg:postcode":"07817",
    "sg:province":"Islas Baleares",
    "wof:name":"Julian Sanz Megino Y Jacinta Padilla Lopez Cdad.",
    "wof:placetype":"venue"
},
  "geometry": {"coordinates":[1.4075000286,38.8912010193],"type":"Point"}
}