{
  "type": "Feature",
  "properties": {
    "addr:full":"Calle de Redolins, 26 Palmar Valencia 46012",
    "addr:housenumber":"26",
    "addr:postcode":"46012",
    "addr:street":"Calle De Redolins",
    "iso:country":"ES",
    "sg:address":"Calle de Redolins, 26",
    "sg:city":"Palmar",
    "sg:orig_category":"Estancos",
    "sg:phone":"+34 961 62 02 03",
    "sg:postcode":"46012",
    "sg:province":"Valencia",
    "wof:name":"Bru Torrent Maria",
    "wof:placetype":"venue"
},
  "geometry": {"coordinates":[-0.3181200027,39.3088912964],"type":"Point"}
}