{
  "type": "Feature",
  "properties": {
    "iso:country":"ES",
    "sg:address":"Masia Llueca, S/n",
    "sg:city":"Betera",
    "sg:orig_category":"Producci\u00d3n, Venta De Productos De Agricultura Biol\u00d3gica",
    "sg:phone":"+34 961 60 00 14",
    "sg:postcode":"46117",
    "sg:province":"Valencia",
    "wof:name":"Alvarez-ossorio Sebastian Fernando",
    "wof:placetype":"venue"
},
  "geometry": {"coordinates":[-0.4313729107,39.5890541077],"type":"Point"}
}