{
  "type": "Feature",
  "properties": {
    "addr:full":"Parque Empresarial Monasterio Del Prado, S/n Arroyo De La Encomienda Valladolid 47195",
    "addr:housenumber":"s / n",
    "addr:postcode":"47195",
    "addr:street":"Del Prado",
    "iso:country":"ES",
    "sg:address":"Parque Empresarial Monasterio Del Prado, S/n",
    "sg:city":"Arroyo De La Encomienda",
    "sg:orig_category":"Empresarios",
    "sg:phone":"+34 983 40 73 76",
    "sg:postcode":"47195",
    "sg:province":"Valladolid",
    "sg:website":"www.slccyl.com",
    "wof:name":"Fundacion Laboral De La Construccion",
    "wof:placetype":"venue"
},
  "geometry": {"coordinates":[-4.7710337639,41.62109375],"type":"Point"}
}