{
  "type": "Feature",
  "properties": {
    "iso:country":"ES",
    "sg:address":"Av Doctor Francesc Massana, 16",
    "sg:city":"Martorell",
    "sg:orig_category":"Librer\u00cdas",
    "sg:phone":"+34 937 75 49 59",
    "sg:postcode":"08760",
    "sg:province":"Barcelona",
    "wof:name":"Busquets Gasulla Antonio",
    "wof:placetype":"venue"
},
  "geometry": {"coordinates":[1.9184720516,41.4787254333],"type":"Point"}
}