{
  "type": "Feature",
  "properties": {
    "iso:country":"ES",
    "sg:address":"Cmno Rey, S/n",
    "sg:city":"Sonseca",
    "sg:orig_category":"Art\u00cdculos Funerarios (al Por Menor)",
    "sg:phone":"+34 925 38 13 97",
    "sg:postcode":"45100",
    "sg:province":"Toledo",
    "wof:name":"Funeraria De Sonseca Sl",
    "wof:placetype":"venue"
},
  "geometry": {"coordinates":[-3.9706120491,39.6791915894],"type":"Point"}
}