{
  "type": "Feature",
  "properties": {
    "addr:full":"Cmno Alfageme, 27 Oteruelo De La Valdoncina Le\u00f3n 24190",
    "addr:housenumber":"27",
    "addr:postcode":"24190",
    "addr:street":"Cmno Alfageme;Leo\u0301N",
    "iso:country":"ES",
    "sg:address":"Cmno Alfageme, 27",
    "sg:city":"Oteruelo De La Valdoncina",
    "sg:orig_category":"Distribuci\u00d3n De Petr\u00d3leo Y Derivados",
    "sg:phone":"+34 987 80 45 57",
    "sg:postcode":"24190",
    "sg:province":"Le\u00f3n",
    "sg:website":"www.paginasamarillas.es",
    "wof:name":"Carbunor Torio S.l.",
    "wof:placetype":"venue"
},
  "geometry": {"coordinates":[-5.6166391373,42.6111564636],"type":"Point"}
}