{
  "type": "Feature",
  "properties": {
    "iso:country":"ES",
    "sg:address":"Carrer de Buri, 1",
    "sg:city":"Cornella Llobregat",
    "sg:orig_category":"Molduras, Junquillos, Listones Y Molduras Perforadas",
    "sg:phone":"+34 933 75 13 33",
    "sg:postcode":"08940",
    "sg:province":"Barcelona",
    "wof:name":"Vallejo Lara Miguel",
    "wof:placetype":"venue"
},
  "geometry": {"coordinates":[2.080395937,41.3602371216],"type":"Point"}
}