{
  "type": "Feature",
  "properties": {
    "addr:full":"Avda Sancho El Sabio, 26 Donostia-san Sebastian Guip\u00f9zcoa 20010",
    "addr:housenumber":"26",
    "addr:postcode":"20010",
    "addr:street":"Avda Sancho El Sabio",
    "iso:country":"ES",
    "sg:address":"Avda Sancho El Sabio, 26",
    "sg:city":"Donostia-san Sebastian",
    "sg:orig_category":"Librer\u00cdas",
    "sg:phone":"+34 943 45 63 50",
    "sg:postcode":"20010",
    "sg:province":"Guip\u00f9zcoa",
    "wof:name":"Jimenez Cruz Francisco",
    "wof:placetype":"venue"
},
  "geometry": {"coordinates":[-1.9798893929,43.3085861206],"type":"Point"}
}