{
  "type": "Feature",
  "properties": {
    "iso:country":"ES",
    "sg:address":"Carrer de Carretera Marina, 4",
    "sg:city":"Prat Llobregat",
    "sg:orig_category":"Cristaler\u00cdas",
    "sg:phone":"+34 933 79 43 41",
    "sg:postcode":"08820",
    "sg:province":"Barcelona",
    "wof:name":"Ramos Mula Angel",
    "wof:placetype":"venue"
},
  "geometry": {"coordinates":[2.0987100601,41.3287849426],"type":"Point"}
}