{
  "type": "Feature",
  "properties": {
    "addr:full":"Carrer de Autonomia, 56 Terrassa Barcelona 08225",
    "addr:housenumber":"56",
    "addr:postcode":"08225",
    "addr:street":"Carrer De Autonomia",
    "iso:country":"ES",
    "sg:address":"Carrer de Autonomia, 56",
    "sg:city":"Terrassa",
    "sg:orig_category":"Motocicletas (agentes, Concesionarios)",
    "sg:phone":"+34 937 35 35 30",
    "sg:postcode":"08225",
    "sg:province":"Barcelona",
    "wof:name":"Enjoy Quads S.l.",
    "wof:placetype":"venue"
},
  "geometry": {"coordinates":[2.0137751102,41.5739440918],"type":"Point"}
}