{
  "type": "Feature",
  "properties": {
    "addr:full":"Pl. Nueva, 6 Poyales Del Hoyo \u00c1vila 05492",
    "addr:housenumber":"6",
    "addr:postcode":"05492",
    "addr:street":"Pl. Nueva",
    "iso:country":"ES",
    "sg:address":"Pl. Nueva, 6",
    "sg:city":"Poyales Del Hoyo",
    "sg:orig_category":"Cajas De Ahorro",
    "sg:phone":"+34 920 39 01 88",
    "sg:postcode":"05492",
    "sg:province":"\u00c1vila",
    "wof:name":"Caja De Avila",
    "wof:placetype":"venue"
},
  "geometry": {"coordinates":[-5.1657791138,40.1725120544],"type":"Point"}
}