{
  "type": "Feature",
  "properties": {
    "iso:country":"ES",
    "sg:address":"Avda Cardenal Cisneros, 10",
    "sg:city":"Palencia",
    "sg:orig_category":"Pescader\u00cdas (al Por Menor)",
    "sg:phone":"+34 979 73 01 39",
    "sg:postcode":"34004",
    "sg:province":"Palencia",
    "wof:name":"Pescomar 2000 S.l.",
    "wof:placetype":"venue"
},
  "geometry": {"coordinates":[-4.5250401497,42.0032081604],"type":"Point"}
}