{
  "type": "Feature",
  "properties": {
    "iso:country":"ES",
    "sg:address":"Carrer de Galileu, 306",
    "sg:city":"Barcelona",
    "sg:orig_category":"Aparatos, Sistemas De Tele",
    "sg:phone":"+34 934 19 55 54",
    "sg:postcode":"08028",
    "sg:province":"Barcelona",
    "sg:website":"www.casella-es.com",
    "wof:name":"Casella Espa\u00f1a S.a.",
    "wof:placetype":"venue"
},
  "geometry": {"coordinates":[2.1318619251,41.3850440979],"type":"Point"}
}