{
  "type": "Feature",
  "properties": {
    "iso:country":"ES",
    "sg:address":"Plaz Txurruka, 3",
    "sg:city":"Mutriku",
    "sg:orig_category":"Librer\u00cdas",
    "sg:phone":"+34 943 60 35 43",
    "sg:postcode":"20830",
    "sg:province":"Guip\u00f9zcoa",
    "wof:name":"Guadalupe Gatzagaetxeberria Urreisti",
    "wof:placetype":"venue"
},
  "geometry": {"coordinates":[-2.3847780228,43.3075294495],"type":"Point"}
}