{
  "type": "Feature",
  "properties": {
    "addr:full":"Calle de Nueve De Mayo, 2 Oviedo Asturias 33002",
    "addr:housenumber":"2",
    "addr:postcode":"33002",
    "addr:street":"Calle De Nueve De Mayo",
    "iso:country":"ES",
    "sg:address":"Calle de Nueve De Mayo, 2",
    "sg:city":"Oviedo",
    "sg:orig_category":"Caf\u00c9s, Bares, Cervecer\u00cdas",
    "sg:phone":"+34 985 22 99 87",
    "sg:postcode":"33002",
    "sg:province":"Asturias",
    "wof:name":"Darling Hosteleria S.l.",
    "wof:placetype":"venue"
},
  "geometry": {"coordinates":[-5.8502011299,43.3656921387],"type":"Point"}
}