{
  "type": "Feature",
  "properties": {
    "iso:country":"ES",
    "sg:address":"Calle de Ramon Perez De Ayala, 38",
    "sg:city":"Madrid",
    "sg:orig_category":"Tapicer\u00cdas",
    "sg:phone":"+34 914 37 19 72",
    "sg:postcode":"28038",
    "sg:province":"Madrid",
    "wof:name":"Navio Pallares Amador",
    "wof:placetype":"venue"
},
  "geometry": {"coordinates":[-3.6544110775,40.3992805481],"type":"Point"}
}