{
  "type": "Feature",
  "properties": {
    "addr:full":"Calle de Profesor Jimenez Diaz, 16 Santander Cantabria 39007",
    "addr:housenumber":"16",
    "addr:postcode":"39007",
    "addr:street":"Calle De Profesor Jimenez Diaz",
    "iso:country":"ES",
    "sg:address":"Calle de Profesor Jimenez Diaz, 16",
    "sg:city":"Santander",
    "sg:orig_category":"Prot\u00c9sicos Dentales",
    "sg:phone":"+34 942 23 14 22",
    "sg:postcode":"39007",
    "sg:province":"Cantabria",
    "wof:name":"Saiz Marina Fernando",
    "wof:placetype":"venue"
},
  "geometry": {"coordinates":[-3.8233969212,43.4612503052],"type":"Point"}
}