{
  "type": "Feature",
  "properties": {
    "addr:full":"Calle de Senija, 5 Denia Alicante 03700",
    "addr:housenumber":"5",
    "addr:postcode":"03700",
    "addr:street":"Calle De Senija",
    "iso:country":"ES",
    "sg:address":"Calle de Senija, 5",
    "sg:city":"Denia",
    "sg:orig_category":"Bares, Piano",
    "sg:phone":"+34 966 42 03 21",
    "sg:postcode":"03700",
    "sg:province":"Alicante",
    "wof:name":"Ciber Cafe C.b.",
    "wof:placetype":"venue"
},
  "geometry": {"coordinates":[0.1036799997,38.8368148804],"type":"Point"}
}