{
  "type": "Feature",
  "properties": {
    "iso:country":"ES",
    "sg:address":"Luga Cortijo El Potril, S/n",
    "sg:city":"Triana",
    "sg:orig_category":"Asesor\u00cda, Estudio Y Control Medioambiental",
    "sg:phone":"+34 952 11 52 70",
    "sg:postcode":"29718",
    "sg:province":"M\u00e1laga",
    "wof:name":"Gamez Martin Jose Luis",
    "wof:placetype":"venue"
},
  "geometry": {"coordinates":[-4.1665549278,36.8184738159],"type":"Point"}
}