{
  "type": "Feature",
  "properties": {
    "addr:full":"Calle de Sinfonia, 1 Chiclana De La Frontera C\u00e1diz 11130",
    "addr:housenumber":"1",
    "addr:postcode":"11130",
    "addr:street":"Calle De Sinfonia",
    "iso:country":"ES",
    "sg:address":"Calle de Sinfonia, 1",
    "sg:city":"Chiclana De La Frontera",
    "sg:orig_category":"Confecci\u00d3n De Zapatos",
    "sg:phone":"+34 956 53 71 61",
    "sg:postcode":"11130",
    "sg:province":"C\u00e1diz",
    "wof:name":"Alonso Calvente Miguel",
    "wof:placetype":"venue"
},
  "geometry": {"coordinates":[-6.1457686424,36.4113082886],"type":"Point"}
}