{
  "type": "Feature",
  "properties": {
    "addr:full":"Carr Bunyoli, 10 Pont D'inca Islas Baleares 07009",
    "addr:housenumber":"10",
    "addr:postcode":"07009",
    "addr:street":"Carr Bunyoli",
    "iso:country":"ES",
    "sg:address":"Carr Bunyoli, 10",
    "sg:city":"Pont D'inca",
    "sg:orig_category":"Agencias Y Agentes Comerciales, Representantes",
    "sg:phone":"+34 971 60 82 63",
    "sg:postcode":"07009",
    "sg:province":"Islas Baleares",
    "wof:name":"Albons Mena Antonio",
    "wof:placetype":"venue"
},
  "geometry": {"coordinates":[2.6954066753,39.6017875671],"type":"Point"}
}