{
  "type": "Feature",
  "properties": {
    "addr:full":"Plaz Mercado, 8 Salamanca Salamanca 37001",
    "addr:housenumber":"8",
    "addr:postcode":"37001",
    "addr:street":"Mercado",
    "iso:country":"ES",
    "sg:address":"Plaz Mercado, 8",
    "sg:city":"Salamanca",
    "sg:orig_category":"Carnicer\u00cdas, Carnicer\u00cdas",
    "sg:phone":"+34 923 21 27 35",
    "sg:postcode":"37001",
    "sg:province":"Salamanca",
    "wof:name":"Salchicherias Iglesias S.l.",
    "wof:placetype":"venue"
},
  "geometry": {"coordinates":[-5.6627449989,40.9650306702],"type":"Point"}
}