{
  "type": "Feature",
  "properties": {
    "iso:country":"ES",
    "sg:address":"Avda Luis Espada, 99",
    "sg:city":"Verin",
    "sg:orig_category":"Muebles, Minoristas",
    "sg:phone":"+34 988 41 44 63",
    "sg:postcode":"32600",
    "sg:province":"Ourense",
    "wof:name":"Vega Gago Carmen",
    "wof:placetype":"venue"
},
  "geometry": {"coordinates":[-7.4363908768,41.9401855469],"type":"Point"}
}