{
  "type": "Feature",
  "properties": {
    "addr:full":"Avda Vera, 30 Plasencia C\u00e1ceres 10600",
    "addr:housenumber":"30",
    "addr:postcode":"10600",
    "addr:street":"Avda Vera;Ca\u0301Ceres",
    "iso:country":"ES",
    "sg:address":"Avda Vera, 30",
    "sg:city":"Plasencia",
    "sg:orig_category":"Congelados: Productos Alimentarios (al Por Menor)",
    "sg:phone":"+34 927 41 57 07",
    "sg:postcode":"10600",
    "sg:province":"C\u00e1ceres",
    "wof:name":"Disanfrio S.l.",
    "wof:placetype":"venue"
},
  "geometry": {"coordinates":[-6.083398819,40.0317382812],"type":"Point"}
}