{
  "type": "Feature",
  "properties": {
    "iso:country":"ES",
    "sg:address":"Calle de Armada Espa\u00d1ola, 1",
    "sg:city":"Isla Cristina",
    "sg:orig_category":"Zapatos (al Por Menor)",
    "sg:phone":"+34 959 34 34 76",
    "sg:postcode":"21410",
    "sg:province":"Huelva",
    "wof:name":"Calzados Y Complementos Charol C.b.",
    "wof:placetype":"venue"
},
  "geometry": {"coordinates":[-7.3254261017,37.2031059265],"type":"Point"}
}