{
  "type": "Feature",
  "properties": {
    "addr:full":"Calle de Aita Donostia, 12 Errenteria Guip\u00f9zcoa 20100",
    "addr:housenumber":"12",
    "addr:postcode":"20100",
    "addr:street":"Calle De Aita Donostia;Guipu\u0300Zcoa",
    "iso:country":"ES",
    "sg:address":"Calle de Aita Donostia, 12",
    "sg:city":"Errenteria",
    "sg:orig_category":"Molduras, Junquillos, Listones Y Molduras Perforadas",
    "sg:phone":"+34 943 51 10 46",
    "sg:postcode":"20100",
    "sg:province":"Guip\u00f9zcoa",
    "wof:name":"Lucas Mu\u00f1oz Pizarro-bar Las Cazuelas",
    "wof:placetype":"venue"
},
  "geometry": {"coordinates":[-1.9116069078,43.3105278015],"type":"Point"}
}