{
  "type": "Feature",
  "properties": {
    "iso:country":"ES",
    "sg:address":"Avda Zaragoza, S/n",
    "sg:city":"Campamento",
    "sg:orig_category":"Inmobiliaria (agencias)",
    "sg:phone":"+34 956 69 70 45",
    "sg:postcode":"11314",
    "sg:province":"C\u00e1diz",
    "wof:name":"Hostan S.l.",
    "wof:placetype":"venue"
},
  "geometry": {"coordinates":[-5.368719101,36.1771888733],"type":"Point"}
}