{
  "type": "Feature",
  "properties": {
    "addr:full":"Ctra Lerin, Km. 0019,0 Larraga Navarra 31251",
    "addr:postcode":"31251",
    "addr:street":"Ctra Lerin Km. 0019,0",
    "iso:country":"ES",
    "sg:address":"Ctra Lerin, Km. 0019,0",
    "sg:city":"Larraga",
    "sg:orig_category":"Bebidas",
    "sg:phone":"+34 948 71 10 45",
    "sg:postcode":"31251",
    "sg:province":"Navarra",
    "wof:name":"Conservas Asensio S.a.",
    "wof:placetype":"venue"
},
  "geometry": {"coordinates":[-1.8498539925,42.5579833984],"type":"Point"}
}