{
  "type": "Feature",
  "properties": {
    "addr:full":"Via Laietana, 50 Barcelona Barcelona 08003",
    "addr:housenumber":"50",
    "addr:postcode":"08003",
    "addr:street":"Via Laietana",
    "iso:country":"ES",
    "sg:address":"Via Laietana, 50",
    "sg:city":"Barcelona",
    "sg:orig_category":"Farmacias",
    "sg:phone":"+34 932 68 00 66",
    "sg:postcode":"08003",
    "sg:province":"Barcelona",
    "wof:name":"Estrany Delsors Maria Teresa",
    "wof:placetype":"venue"
},
  "geometry": {"coordinates":[2.1749410629,41.3869514465],"type":"Point"}
}