{
  "type": "Feature",
  "properties": {
    "addr:full":"Avda Constitucion, 82 Cistierna Le\u00f3n 24800",
    "addr:housenumber":"82",
    "addr:postcode":"24800",
    "addr:street":"Avda Constitucion;Leo\u0301N",
    "iso:country":"ES",
    "sg:address":"Avda Constitucion, 82",
    "sg:city":"Cistierna",
    "sg:classifiers":[
        {
            "category":"Autos & Motor Vehicles",
            "subcategory":"Automobile Sales",
            "type":"Retail Goods"
        }
    ],
    "sg:phone":"+34 987 70 00 51",
    "sg:postcode":"24800",
    "sg:province":"Le\u00f3n",
    "wof:name":"Baron Fernandez S.l.",
    "wof:placetype":"venue"
},
  "geometry": {"coordinates":[-5.1286687851,42.8040084839],"type":"Point"}
}