{
  "type": "Feature",
  "properties": {
    "addr:full":"Calle de Real De Motril, 121 Armilla Granada 18100",
    "addr:housenumber":"121",
    "addr:postcode":"18100",
    "addr:street":"Calle De Real De Motril",
    "iso:country":"ES",
    "sg:address":"Calle de Real De Motril, 121",
    "sg:city":"Armilla",
    "sg:orig_category":"Agentes Generales De Seguros",
    "sg:phone":"+34 958 55 15 60",
    "sg:postcode":"18100",
    "sg:province":"Granada",
    "wof:name":"Bernal Ruiz Maria",
    "wof:placetype":"venue"
},
  "geometry": {"coordinates":[-3.6280889511,37.1404304504],"type":"Point"}
}