{
  "type": "Feature",
  "properties": {
    "iso:country":"ES",
    "sg:address":"Rbla Poblenou, 67",
    "sg:city":"Barcelona",
    "sg:orig_category":"Fabricaci\u00d3n, Venta De Cuadros, Accesorios Para Enmarcar",
    "sg:phone":"+34 934 85 31 99",
    "sg:postcode":"08005",
    "sg:province":"Barcelona",
    "wof:name":"Olaria Riera Manuel",
    "wof:placetype":"venue"
},
  "geometry": {"coordinates":[2.2009649277,41.4010353088],"type":"Point"}
}