{
  "type": "Feature",
  "properties": {
    "addr:full":"Plaz Mayor, 8 Valladolid Valladolid 47001",
    "addr:housenumber":"8",
    "addr:postcode":"47001",
    "addr:street":"Plaz Mayor",
    "iso:country":"ES",
    "sg:address":"Plaz Mayor, 8",
    "sg:city":"Valladolid",
    "sg:orig_category":"Loter\u00cda Y T\u00d3mbola",
    "sg:phone":"+34 983 35 47 43",
    "sg:postcode":"47001",
    "sg:province":"Valladolid",
    "wof:name":"Medina Martin Edelmira",
    "wof:placetype":"venue"
},
  "geometry": {"coordinates":[-4.7280468941,41.6516571045],"type":"Point"}
}