{
  "type": "Feature",
  "properties": {
    "iso:country":"ES",
    "sg:address":"Avda Gran Via Rey Juan Carlos I, 54",
    "sg:city":"Logro\u00f1o",
    "sg:orig_category":"Ingenier\u00cda, Centros De Estudios (diversos)",
    "sg:phone":"+34 941 22 20 35",
    "sg:postcode":"26005",
    "sg:province":"La Rioja",
    "wof:name":"Pe\u00f1a Navaridas Jose Miguel",
    "wof:placetype":"venue"
},
  "geometry": {"coordinates":[-2.4532499313,42.4650344849],"type":"Point"}
}