{
  "type": "Feature",
  "properties": {
    "iso:country":"ES",
    "sg:address":"Calle de San Anton, 47",
    "sg:city":"Granada",
    "sg:orig_category":"Muebles, Minoristas",
    "sg:phone":"+34 958 52 32 18",
    "sg:postcode":"18005",
    "sg:province":"Granada",
    "wof:name":"Fernandez Molero Juan",
    "wof:placetype":"venue"
},
  "geometry": {"coordinates":[-3.599558115,37.1706161499],"type":"Point"}
}