{
  "type": "Feature",
  "properties": {
    "addr:full":"Plaz Juan Carlos I, S/n Getafe Madrid 28905",
    "addr:housenumber":"s / n",
    "addr:postcode":"28905",
    "addr:street":"Plaz Juan Carlos I",
    "iso:country":"ES",
    "sg:address":"Plaz Juan Carlos I, S/n",
    "sg:city":"Getafe",
    "sg:orig_category":"Frutas Y Legumbres Frescas (al Por Mayor)",
    "sg:phone":"+34 916 82 94 27",
    "sg:postcode":"28905",
    "sg:province":"Madrid",
    "wof:name":"Aguilar De Los Santos Francisco",
    "wof:placetype":"venue"
},
  "geometry": {"coordinates":[-3.744841814,40.297618866],"type":"Point"}
}