{
  "type": "Feature",
  "properties": {
    "addr:full":"Calle de Virgen, 42 Villarrobledo Albacete 02600",
    "addr:housenumber":"42",
    "addr:postcode":"02600",
    "addr:street":"Calle De Virgen",
    "iso:country":"ES",
    "sg:address":"Calle de Virgen, 42",
    "sg:city":"Villarrobledo",
    "sg:orig_category":"Laboratorios Y Asesor\u00cda En Enolog\u00cda",
    "sg:phone":"+34 967 14 00 93",
    "sg:postcode":"02600",
    "sg:province":"Albacete",
    "wof:name":"Marchante Fernandez Juan",
    "wof:placetype":"venue"
},
  "geometry": {"coordinates":[-2.6057600975,39.2685470581],"type":"Point"}
}