{
  "type": "Feature",
  "properties": {
    "iso:country":"ES",
    "sg:address":"Avda Dos De Mayo, 8",
    "sg:city":"Vilamarxant",
    "sg:orig_category":"Pirotecnia (espect\u00c1culos)",
    "sg:phone":"+34 961 65 02 14",
    "sg:postcode":"46191",
    "sg:province":"Valencia",
    "wof:name":"Giner Faus Olga",
    "wof:placetype":"venue"
},
  "geometry": {"coordinates":[-0.6231889725,39.5711135864],"type":"Point"}
}