{
  "type": "Feature",
  "properties": {
    "addr:full":"Calle de Pintor Ferrer, 12 Alcora Castell\u00f3n 12110",
    "addr:housenumber":"12",
    "addr:postcode":"12110",
    "addr:street":"Calle De Pintor Ferrer;Castello\u0301N",
    "iso:country":"ES",
    "sg:address":"Calle de Pintor Ferrer, 12",
    "sg:city":"Alcora",
    "sg:orig_category":"Cer\u00c1mica Art\u00cdstica Y Decorativa",
    "sg:phone":"+34 964 36 10 03",
    "sg:postcode":"12110",
    "sg:province":"Castell\u00f3n",
    "wof:name":"La Muy Noble Y Artistica Ceramica De Alcora S. A.",
    "wof:placetype":"venue"
},
  "geometry": {"coordinates":[-0.2137800008,40.0738220215],"type":"Point"}
}