{
  "type": "Feature",
  "properties": {
    "iso:country":"ES",
    "sg:address":"Plaz Constitucion, 14",
    "sg:city":"Sari\u00f1ena",
    "sg:orig_category":"Asesor\u00cda Fiscal Y Jur\u00cddica",
    "sg:phone":"+34 974 57 05 47",
    "sg:postcode":"22200",
    "sg:province":"Huesca",
    "wof:name":"Asesoria Fiscal Sari\u00f1ena S.cv.",
    "wof:placetype":"venue"
},
  "geometry": {"coordinates":[-0.1682271063,41.7804260254],"type":"Point"}
}