{
  "type": "Feature",
  "properties": {
    "iso:country":"ES",
    "sg:address":"Carr Miquel De Veri, 14",
    "sg:city":"Mao",
    "sg:orig_category":"Supermercados Y Hipermercados",
    "sg:phone":"+34 971 36 02 71",
    "sg:postcode":"07703",
    "sg:province":"Islas Baleares",
    "wof:name":"Pons Olives Rafael",
    "wof:placetype":"venue"
},
  "geometry": {"coordinates":[4.2567090988,39.8882026672],"type":"Point"}
}