{
  "type": "Feature",
  "properties": {
    "iso:country":"ES",
    "sg:address":"Ctra Tarragona, 9",
    "sg:city":"Lleida",
    "sg:classifiers":[
        {
            "category":"Shopping",
            "subcategory":"Clothing, Apparel, & Fashions",
            "type":"Retail Goods"
        }
    ],
    "sg:phone":"+34 973 24 70 26",
    "sg:postcode":"25005",
    "sg:province":"Lleida",
    "sg:tags":[
        "boutique"
    ],
    "wof:name":"Capo Falco Carolina",
    "wof:placetype":"venue"
},
  "geometry": {"coordinates":[0.6390810013,41.623336792],"type":"Point"}
}