{
  "type": "Feature",
  "properties": {
    "iso:country":"ES",
    "sg:address":"Plaz Andramariko, 3",
    "sg:city":"Amorebieta",
    "sg:orig_category":"Herboristas (al Por Menor)",
    "sg:phone":"+34 946 30 86 23",
    "sg:postcode":"48340",
    "sg:province":"Vizcaya",
    "wof:name":"Azurmendi Bilbao Sabin",
    "wof:placetype":"venue"
},
  "geometry": {"coordinates":[-2.7333345413,43.2179641724],"type":"Point"}
}