{
  "type": "Feature",
  "properties": {
    "addr:full":"Calle de Ca\u00d1adilla, 7 Caracenilla Cuenca 16540",
    "addr:housenumber":"7",
    "addr:postcode":"16540",
    "addr:street":"Calle De Can\u0303Adilla",
    "iso:country":"ES",
    "sg:address":"Calle de Ca\u00d1adilla, 7",
    "sg:city":"Caracenilla",
    "sg:orig_category":"Deportes Y Programas De Aventura",
    "sg:phone":"+34 969 27 26 64",
    "sg:postcode":"16540",
    "sg:province":"Cuenca",
    "sg:website":"www.tressesenta.net",
    "wof:name":"Tres Sesenta S.l.",
    "wof:placetype":"venue"
},
  "geometry": {"coordinates":[-2.5502479076,40.1932678223],"type":"Point"}
}