{
  "type": "Feature",
  "properties": {
    "addr:full":"Av Ave Maria, 19 Escala Girona 17130",
    "addr:housenumber":"19",
    "addr:postcode":"17130",
    "addr:street":"Av Ave Maria",
    "iso:country":"ES",
    "sg:address":"Av Ave Maria, 19",
    "sg:city":"Escala",
    "sg:orig_category":"Asesor\u00cdas Y Estudios Financieros",
    "sg:phone":"+34 972 77 00 13",
    "sg:postcode":"17130",
    "sg:province":"Girona",
    "wof:name":"Orcera Martinez Ramon",
    "wof:placetype":"venue"
},
  "geometry": {"coordinates":[3.1344389915,42.1235427856],"type":"Point"}
}