{
  "type": "Feature",
  "properties": {
    "iso:country":"ES",
    "sg:address":"Calle de Hospital, 7",
    "sg:city":"Torrejon Ardoz",
    "sg:orig_category":"Ropa Para Ni\u00d1os (al Por Menor)",
    "sg:phone":"+34 916 75 13 15",
    "sg:postcode":"28850",
    "sg:province":"Madrid",
    "wof:name":"Garcia Soldado Gomez Antonia",
    "wof:placetype":"venue"
},
  "geometry": {"coordinates":[-3.4777870178,40.4590873718],"type":"Point"}
}