{
  "type": "Feature",
  "properties": {
    "addr:full":"Avda Ciudad Jardin, 58 Callosa Segura Alicante 03360",
    "addr:housenumber":"58",
    "addr:postcode":"03360",
    "addr:street":"Avda Ciudad Jardin",
    "iso:country":"ES",
    "sg:address":"Avda Ciudad Jardin, 58",
    "sg:city":"Callosa Segura",
    "sg:orig_category":"Alquiler De Gr\u00daas",
    "sg:phone":"+34 965 31 09 16",
    "sg:postcode":"03360",
    "sg:province":"Alicante",
    "wof:name":"Serrano Tebar S. L.",
    "wof:placetype":"venue"
},
  "geometry": {"coordinates":[-0.884600997,38.1172142029],"type":"Point"}
}