{
  "type": "Feature",
  "properties": {
    "iso:country":"ES",
    "sg:address":"Carrer de Rodos, 3",
    "sg:city":"Estany",
    "sg:orig_category":"Granos Y Forrajes",
    "sg:phone":"+34 938 30 30 10",
    "sg:postcode":"08148",
    "sg:province":"Barcelona",
    "wof:name":"Padros Franquesa Joaquin",
    "wof:placetype":"venue"
},
  "geometry": {"coordinates":[2.1109199524,41.868522644],"type":"Point"}
}