{
  "type": "Feature",
  "properties": {
    "addr:full":"Calle de Mar Del Caribe, 1 Vista Alegre Murcia 30007",
    "addr:housenumber":"1",
    "addr:postcode":"30007",
    "addr:street":"Calle De;Del Caribe",
    "iso:country":"ES",
    "sg:address":"Calle de Mar Del Caribe, 1",
    "sg:city":"Vista Alegre",
    "sg:orig_category":"Panader\u00cdas, Panader\u00cdas",
    "sg:phone":"+34 968 23 06 33",
    "sg:postcode":"30007",
    "sg:province":"Murcia",
    "wof:name":"Ortiz Manzano Monserrat",
    "wof:placetype":"venue"
},
  "geometry": {"coordinates":[-1.1298867464,37.9834747314],"type":"Point"}
}