{
  "type": "Feature",
  "properties": {
    "iso:country":"ES",
    "sg:address":"Rbla Rafael Casanova, 26",
    "sg:city":"S. Boi Llobregat",
    "sg:orig_category":"Molduras, Junquillos, Listones Y Molduras Perforadas",
    "sg:phone":"+34 936 30 70 57",
    "sg:postcode":"08830",
    "sg:province":"Barcelona",
    "wof:name":"Franco Reus Francisco",
    "wof:placetype":"venue"
},
  "geometry": {"coordinates":[2.0417070389,41.3478240967],"type":"Point"}
}