{
  "type": "Feature",
  "properties": {
    "iso:country":"ES",
    "sg:address":"Rond Farinera, S/n",
    "sg:city":"Mollet Valles",
    "sg:classifiers":[
        {
            "category":"Taxi",
            "type":"Transportation"
        }
    ],
    "sg:phone":"+34 935 93 74 01",
    "sg:postcode":"08100",
    "sg:province":"Barcelona",
    "wof:name":"Radio Taxi Mollet",
    "wof:placetype":"venue"
},
  "geometry": {"coordinates":[2.2166249752,41.5438613892],"type":"Point"}
}