{
  "type": "Feature",
  "properties": {
    "iso:country":"ES",
    "sg:address":"Avda Escaleritas, 70",
    "sg:city":"Palmas De Gran Canaria",
    "sg:orig_category":"M\u00c9dicos: Estomatolog\u00cda",
    "sg:phone":"+34 928 20 14 82",
    "sg:postcode":"35011",
    "sg:province":"Las Palmas",
    "wof:name":"Holcer Sutler Carlos",
    "wof:placetype":"venue"
},
  "geometry": {"coordinates":[-15.4373064041,28.1184406281],"type":"Point"}
}