{
  "type": "Feature",
  "properties": {
    "iso:country":"ES",
    "sg:address":"Residencia Los Tilos, 3",
    "sg:city":"Ramales Victoria",
    "sg:orig_category":"M\u00c9dicos: Estomatolog\u00cda",
    "sg:phone":"+34 942 67 83 96",
    "sg:postcode":"39800",
    "sg:province":"Cantabria",
    "wof:name":"Madrazo San Roman Luis Andres",
    "wof:placetype":"venue"
},
  "geometry": {"coordinates":[-3.442991972,43.2613754272],"type":"Point"}
}