{
  "type": "Feature",
  "properties": {
    "addr:full":"Av Alameda (l'), 69 Alcoi Alicante 03803",
    "addr:housenumber":"69",
    "addr:postcode":"03803",
    "addr:street":"Av Alameda L '",
    "iso:country":"ES",
    "sg:address":"Av Alameda (l'), 69",
    "sg:city":"Alcoi",
    "sg:orig_category":"Servicio De Salud",
    "sg:phone":"+34 965 33 02 85",
    "sg:postcode":"03803",
    "sg:province":"Alicante",
    "wof:name":"Saneamientos La Alameda S. L.",
    "wof:placetype":"venue"
},
  "geometry": {"coordinates":[-0.4756299853,38.7035865784],"type":"Point"}
}