{
  "type": "Feature",
  "properties": {
    "addr:full":"Carrer de Torrijos, 3 Rubi Barcelona 08191",
    "addr:housenumber":"3",
    "addr:postcode":"08191",
    "addr:street":"Carrer De Torrijos",
    "iso:country":"ES",
    "sg:address":"Carrer de Torrijos, 3",
    "sg:city":"Rubi",
    "sg:orig_category":"Abogados",
    "sg:phone":"+34 936 97 53 08",
    "sg:postcode":"08191",
    "sg:province":"Barcelona",
    "wof:name":"Roses Albiol Josep Maria",
    "wof:placetype":"venue"
},
  "geometry": {"coordinates":[2.0288550854,41.4900627136],"type":"Point"}
}