{
  "type": "Feature",
  "properties": {
    "iso:country":"ES",
    "sg:address":"Carrer de Girona, 92",
    "sg:city":"Barcelona",
    "sg:orig_category":"Agencias Y Agentes Comerciales, Representantes",
    "sg:phone":"+34 932 07 19 45",
    "sg:postcode":"08009",
    "sg:province":"Barcelona",
    "wof:name":"Mu\u00f1oz Torres Jose Tomas",
    "wof:placetype":"venue"
},
  "geometry": {"coordinates":[2.1697409153,41.3960990906],"type":"Point"}
}