{
  "type": "Feature",
  "properties": {
    "addr:full":"Campalet, 1 Benasque Huesca 22440",
    "addr:housenumber":"1",
    "addr:postcode":"22440",
    "addr:street":"Campalet",
    "iso:country":"ES",
    "sg:address":"Campalet, 1",
    "sg:city":"Benasque",
    "sg:orig_category":"Agencias Y Agentes Comerciales, Representantes",
    "sg:phone":"+34 974 55 28 35",
    "sg:postcode":"22440",
    "sg:province":"Huesca",
    "wof:name":"Sanchez Garcia Antonio",
    "wof:placetype":"venue"
},
  "geometry": {"coordinates":[0.518862009,42.6033668518],"type":"Point"}
}