{
  "type": "Feature",
  "properties": {
    "addr:full":"Av Barcelona, 15 Portbou Girona 17497",
    "addr:housenumber":"15",
    "addr:postcode":"17497",
    "addr:street":"Av Barcelona",
    "iso:country":"ES",
    "sg:address":"Av Barcelona, 15",
    "sg:city":"Portbou",
    "sg:orig_category":"Pescader\u00cdas (al Por Menor)",
    "sg:phone":"+34 972 12 50 43",
    "sg:postcode":"17497",
    "sg:province":"Girona",
    "wof:name":"Cortada Guday Miquel",
    "wof:placetype":"venue"
},
  "geometry": {"coordinates":[3.1613900661,42.4258995056],"type":"Point"}
}