{
  "type": "Feature",
  "properties": {
    "iso:country":"ES",
    "sg:address":"Rua Ecuador, 89",
    "sg:city":"Vigo",
    "sg:orig_category":"M\u00c9dicos: Medicina General Orientada A La Acupuntura",
    "sg:phone":"+34 986 41 23 84",
    "sg:postcode":"36204",
    "sg:province":"Pontevedra",
    "wof:name":"Chang Kim I Seung",
    "wof:placetype":"venue"
},
  "geometry": {"coordinates":[-8.7152891159,42.2319526672],"type":"Point"}
}