{
  "type": "Feature",
  "properties": {
    "addr:full":"Carr Tulipes, 5 Igualada Barcelona 08700",
    "addr:housenumber":"5",
    "addr:postcode":"08700",
    "addr:street":"Carr Tulipes",
    "iso:country":"ES",
    "sg:address":"Carr Tulipes, 5",
    "sg:city":"Igualada",
    "sg:orig_category":"Arquitectos",
    "sg:phone":"+34 938 04 13 82",
    "sg:postcode":"08700",
    "sg:province":"Barcelona",
    "wof:name":"Albareda Mussons Antonio",
    "wof:placetype":"venue"
},
  "geometry": {"coordinates":[1.6297831535,41.5811042786],"type":"Point"}
}