{
  "type": "Feature",
  "properties": {
    "addr:full":"Calle de Loreto Y Chicote, 13 Madrid Madrid 28004",
    "addr:housenumber":"13",
    "addr:postcode":"madrid;28004",
    "addr:street":"Calle De Loreto Y Chicote",
    "iso:country":"ES",
    "sg:address":"Calle de Loreto Y Chicote, 13",
    "sg:city":"Madrid",
    "sg:orig_category":"Plomeros",
    "sg:phone":"+34 915 22 08 08",
    "sg:postcode":"28004",
    "sg:province":"Madrid",
    "wof:name":"Pe\u00f1as Alarnes Blas De Las",
    "wof:placetype":"venue"
},
  "geometry": {"coordinates":[-3.7045030594,40.421661377],"type":"Point"}
}