{
  "type": "Feature",
  "properties": {
    "addr:full":"Roldan, 18 Torre-pacheco Murcia 30700",
    "addr:housenumber":"18",
    "addr:postcode":"30700",
    "addr:street":"Roldan",
    "iso:country":"ES",
    "sg:address":"Roldan, 18",
    "sg:city":"Torre-pacheco",
    "sg:orig_category":"Mec\u00c1nico Del Autom\u00d3vil",
    "sg:phone":"+34 968 57 81 08",
    "sg:postcode":"30700",
    "sg:province":"Murcia",
    "wof:name":"Gestion Patrimonial Izquimar S.l.",
    "wof:placetype":"venue"
},
  "geometry": {"coordinates":[-0.9535620213,37.7442855835],"type":"Point"}
}