{
  "type": "Feature",
  "properties": {
    "addr:full":"Pg Bisbe Guillamet, 2 Olot Girona 17800",
    "addr:housenumber":"2",
    "addr:postcode":"17800",
    "addr:street":"Pg Bisbe Guillamet",
    "iso:country":"ES",
    "sg:address":"Pg Bisbe Guillamet, 2",
    "sg:city":"Olot",
    "sg:orig_category":"Cajas De Ahorro",
    "sg:phone":"+34 972 26 63 40",
    "sg:postcode":"17800",
    "sg:province":"Girona",
    "sg:website":"www.lacaixa.es",
    "wof:name":"Caixa D'estalvis I Pensions De Barcelona",
    "wof:placetype":"venue"
},
  "geometry": {"coordinates":[2.4855051041,42.1831169128],"type":"Point"}
}