{
  "type": "Feature",
  "properties": {
    "addr:full":"Estrabon, 2 Malaga M\u00e1laga 29004",
    "addr:housenumber":"2",
    "addr:postcode":"29004",
    "addr:street":"Estrabon;Ma\u0301Laga",
    "iso:country":"ES",
    "sg:address":"Estrabon, 2",
    "sg:city":"Malaga",
    "sg:orig_category":"Alquiler De Veh\u00cdculos: Turismos Y Utilitarios",
    "sg:phone":"+34 952 17 44 98",
    "sg:postcode":"29004",
    "sg:province":"M\u00e1laga",
    "wof:name":"Aurigacrown Car Hire S.l.",
    "wof:placetype":"venue"
},
  "geometry": {"coordinates":[-4.4925761223,36.6806221008],"type":"Point"}
}