{
  "type": "Feature",
  "properties": {
    "addr:full":"Antxuenea Plaza - Plaza Antxuenea, 5 Lasarte Guip\u00f9zcoa 20160",
    "addr:housenumber":"5",
    "addr:postcode":"20160",
    "addr:street":"Antxuenea;Plaza Antxuenea;Lasarte Guipu\u0300Zcoa",
    "iso:country":"ES",
    "sg:address":"Antxuenea Plaza - Plaza Antxuenea, 5",
    "sg:city":"Lasarte",
    "sg:orig_category":"Reparaci\u00d3n, Mantenimiento De Calefacciones",
    "sg:phone":"+34 943 37 19 01",
    "sg:postcode":"20160",
    "sg:province":"Guip\u00f9zcoa",
    "wof:name":"Urbegi Zerbitzu Teknikoak S.l",
    "wof:placetype":"venue"
},
  "geometry": {"coordinates":[-2.020414114,43.2698173523],"type":"Point"}
}