{
  "type": "Feature",
  "properties": {
    "iso:country":"ES",
    "sg:address":"Pase Herrera De, 49",
    "sg:city":"Donostia-san Sebastian",
    "sg:orig_category":"Fabricaci\u00d3n De Muebles",
    "sg:phone":"+34 943 35 23 95",
    "sg:postcode":"20017",
    "sg:province":"Guip\u00f9zcoa",
    "wof:name":"Ergobia Mobel S.l.",
    "wof:placetype":"venue"
},
  "geometry": {"coordinates":[-1.9333100319,43.3189735413],"type":"Point"}
}