{
  "type": "Feature",
  "properties": {
    "iso:country":"ES",
    "sg:address":"Tabardo, 12",
    "sg:city":"Beniparrell",
    "sg:orig_category":"Fabricaci\u00d3n De Moldes Y Modelos",
    "sg:phone":"+34 961 20 25 95",
    "sg:postcode":"46469",
    "sg:province":"Valencia",
    "wof:name":"Jose Francisco Boluda Leiva Y Jose Joaquin Sobrino Jordan Cdad.",
    "wof:placetype":"venue"
},
  "geometry": {"coordinates":[-0.4132609963,39.3873786926],"type":"Point"}
}