{
  "type": "Feature",
  "properties": {
    "iso:country":"ES",
    "sg:address":"Calle de Remedio, 11",
    "sg:city":"Cifuentes",
    "sg:orig_category":"Alimentaci\u00d3n General (al Por Menor)",
    "sg:phone":"+34 949 81 00 31",
    "sg:postcode":"19420",
    "sg:province":"Guadalajara",
    "wof:name":"Cabellos Llorente Cristobal",
    "wof:placetype":"venue"
},
  "geometry": {"coordinates":[-2.6204230785,40.7860488892],"type":"Point"}
}