{
  "type": "Feature",
  "properties": {
    "iso:country":"ES",
    "sg:address":"Plaz Constitucion, 12",
    "sg:city":"Torrecilla En Cameros",
    "sg:orig_category":"Charcuter\u00cdas (al Por Mayor)",
    "sg:phone":"+34 941 46 01 90",
    "sg:postcode":"26100",
    "sg:province":"La Rioja",
    "wof:name":"Muro Gonzalez Santiago",
    "wof:placetype":"venue"
},
  "geometry": {"coordinates":[-2.5899960995,42.2450408936],"type":"Point"}
}