{
  "type": "Feature",
  "properties": {
    "iso:country":"ES",
    "sg:address":"Barr Herreria (la), 10",
    "sg:city":"Quijano",
    "sg:orig_category":"Ense\u00d1anza, Formaci\u00d3n Profesional: Aprendizaje",
    "sg:phone":"+34 942 57 08 37",
    "sg:postcode":"39477",
    "sg:province":"Cantabria",
    "wof:name":"Ayuntamiento De Pielagos",
    "wof:placetype":"venue"
},
  "geometry": {"coordinates":[-3.951841116,43.4026947021],"type":"Point"}
}