{
  "type": "Feature",
  "properties": {
    "iso:country":"ES",
    "sg:address":"Denune, 13",
    "sg:city":"Denune",
    "sg:orig_category":"Supermercados Y Hipermercados",
    "sg:phone":"+34 982 17 68 95",
    "sg:postcode":"27379",
    "sg:province":"Lugo",
    "wof:name":"Garcia Veiga Ines",
    "wof:placetype":"venue"
},
  "geometry": {"coordinates":[-7.5793681145,43.167263031],"type":"Point"}
}