{
  "type": "Feature",
  "properties": {
    "addr:full":"Avda Pais Valenciano, 3 Albatera Alicante 03340",
    "addr:housenumber":"3",
    "addr:postcode":"03340",
    "addr:street":"Avda Pais Valenciano",
    "iso:country":"ES",
    "sg:address":"Avda Pais Valenciano, 3",
    "sg:city":"Albatera",
    "sg:orig_category":"Cerrajer\u00cda, Ferrallista",
    "sg:phone":"+34 965 48 51 24",
    "sg:postcode":"03340",
    "sg:province":"Alicante",
    "wof:name":"Carbonell Gomez Antonio",
    "wof:placetype":"venue"
},
  "geometry": {"coordinates":[-0.8748859763,38.1775131226],"type":"Point"}
}