{
  "type": "Feature",
  "properties": {
    "iso:country":"ES",
    "sg:address":"Calle de Castillo De Aroche, 6",
    "sg:city":"Alcala Guadaira",
    "sg:orig_category":"Bisuter\u00cda, Joyer\u00cda, Relojer\u00cda (al Por Menor)",
    "sg:phone":"+34 955 68 39 75",
    "sg:postcode":"41500",
    "sg:province":"Sevilla",
    "wof:name":"Toledo Galan Francisco",
    "wof:placetype":"venue"
},
  "geometry": {"coordinates":[-5.8513021469,37.3408622742],"type":"Point"}
}