{
  "type": "Feature",
  "properties": {
    "addr:full":"Carrer de Bolos, 16 Olot Girona 17800",
    "addr:housenumber":"16",
    "addr:postcode":"17800",
    "addr:street":"Carrer De Bolos",
    "iso:country":"ES",
    "sg:address":"Carrer de Bolos, 16",
    "sg:city":"Olot",
    "sg:orig_category":"Empresarios",
    "sg:phone":"+34 972 26 22 21",
    "sg:postcode":"17800",
    "sg:province":"Girona",
    "wof:name":"Reixach Fuste Miguel",
    "wof:placetype":"venue"
},
  "geometry": {"coordinates":[2.4838120937,42.1822242737],"type":"Point"}
}