{
  "type": "Feature",
  "properties": {
    "addr:full":"Carrer de Arnau D'oms, 66 Barcelona Barcelona 08016",
    "addr:housenumber":"66",
    "addr:postcode":"08016",
    "addr:street":"Carrer De;D'Oms",
    "iso:country":"ES",
    "sg:address":"Carrer de Arnau D'oms, 66",
    "sg:city":"Barcelona",
    "sg:orig_category":"Cr\u00cda De Animales",
    "sg:phone":"+34 933 40 45 17",
    "sg:postcode":"08016",
    "sg:province":"Barcelona",
    "wof:name":"Montclus Arque Carles",
    "wof:placetype":"venue"
},
  "geometry": {"coordinates":[2.1773836613,41.4313430786],"type":"Point"}
}