{
  "type": "Feature",
  "properties": {
    "addr:full":"Av Valencia, 8 Gandesa Tarragona 43780",
    "addr:housenumber":"8",
    "addr:postcode":"43780",
    "addr:street":"Av Valencia",
    "iso:country":"ES",
    "sg:address":"Av Valencia, 8",
    "sg:city":"Gandesa",
    "sg:orig_category":"Fotograf\u00cda Y Cine: Aparatos, Pel\u00cdculas Y Accesorios (fabricaci\u00d3n, Al Por Mayor)",
    "sg:phone":"+34 977 42 12 65",
    "sg:postcode":"43780",
    "sg:province":"Tarragona",
    "sg:website":"fotoimatge2001.cjb.net",
    "wof:name":"Laboratori Fotografic Fotoimatge 2001 S.l.",
    "wof:placetype":"venue"
},
  "geometry": {"coordinates":[0.4388340116,41.0536727905],"type":"Point"}
}