{
  "type": "Feature",
  "properties": {
    "iso:country":"ES",
    "sg:address":"Arco, 8",
    "sg:city":"Arroyo De La Encomienda",
    "sg:orig_category":"Electricidad: Equipos Industriales, Componentes (fabricaci\u00d3n)",
    "sg:phone":"+34 983 40 95 36",
    "sg:postcode":"47195",
    "sg:province":"Valladolid",
    "wof:name":"Cubino Balula Miguel",
    "wof:placetype":"venue"
},
  "geometry": {"coordinates":[-4.7954587936,41.6099090576],"type":"Point"}
}