{
  "type": "Feature",
  "properties": {
    "addr:full":"Calle de Santa Justa, 6 Gijon Asturias 33208",
    "addr:housenumber":"6",
    "addr:postcode":"33208",
    "addr:street":"Calle De Santa Justa",
    "iso:country":"ES",
    "sg:address":"Calle de Santa Justa, 6",
    "sg:city":"Gijon",
    "sg:orig_category":"Lavado, Limpieza De Veh\u00cdculos",
    "sg:phone":"+34 985 14 54 19",
    "sg:postcode":"33208",
    "sg:province":"Asturias",
    "wof:name":"Tuero Noval Jose Ramon",
    "wof:placetype":"venue"
},
  "geometry": {"coordinates":[-5.6645212173,43.5369567871],"type":"Point"}
}