{
  "type": "Feature",
  "properties": {
    "addr:full":"Luga Carretera De Granada, S/n Guadix Granada 18500",
    "addr:postcode":"18500",
    "addr:street":"Carretera De Granada S / N",
    "iso:country":"ES",
    "sg:address":"Luga Carretera De Granada, S/n",
    "sg:city":"Guadix",
    "sg:orig_category":"Fabricaci\u00d3n De Tapices Y Moquetas Para Suelos Y Paredes",
    "sg:phone":"+34 958 66 33 59",
    "sg:postcode":"18500",
    "sg:province":"Granada",
    "wof:name":"Bailon Jimenez Carlos",
    "wof:placetype":"venue"
},
  "geometry": {"coordinates":[-3.1343688965,37.303894043],"type":"Point"}
}