{
  "type": "Feature",
  "properties": {
    "addr:full":"Calle de Aniceto Coloma, 25 Almansa Albacete 02640",
    "addr:housenumber":"25",
    "addr:postcode":"02640",
    "addr:street":"Calle De Aniceto Coloma",
    "iso:country":"ES",
    "sg:address":"Calle de Aniceto Coloma, 25",
    "sg:city":"Almansa",
    "sg:orig_category":"Centros De Coordinaci\u00d3n",
    "sg:phone":"+34 967 34 29 11",
    "sg:postcode":"02640",
    "sg:province":"Albacete",
    "wof:name":"Roca Iba\u00f1ez Maria Pilar",
    "wof:placetype":"venue"
},
  "geometry": {"coordinates":[-1.0976752043,38.8694419861],"type":"Point"}
}