{
  "type": "Feature",
  "properties": {
    "addr:full":"Calle de Zuloaga Margolari, 4 Kurtzea Vizcaya 48960",
    "addr:housenumber":"4",
    "addr:postcode":"48960",
    "addr:street":"Calle De Zuloaga Margolari",
    "iso:country":"ES",
    "sg:address":"Calle de Zuloaga Margolari, 4",
    "sg:city":"Kurtzea",
    "sg:orig_category":"Frutas, Legumbres Frescas Y Tempranas (al Por Menor)",
    "sg:phone":"+34 944 56 28 03",
    "sg:postcode":"48960",
    "sg:province":"Vizcaya",
    "wof:name":"Maza Ortiz Juan Enrique",
    "wof:placetype":"venue"
},
  "geometry": {"coordinates":[-2.8436601162,43.2297897339],"type":"Point"}
}