{
  "type": "Feature",
  "properties": {
    "iso:country":"ES",
    "sg:address":"Calle de Eucalipto, 6",
    "sg:city":"Leganes",
    "sg:orig_category":"Ingenier\u00cda, Centros De Estudios (diversos)",
    "sg:phone":"+34 916 94 28 59",
    "sg:postcode":"28918",
    "sg:province":"Madrid",
    "wof:name":"Fernandez Araujo Felix Alvaro",
    "wof:placetype":"venue"
},
  "geometry": {"coordinates":[-3.7760488987,40.3390541077],"type":"Point"}
}