{
  "type": "Feature",
  "properties": {
    "addr:full":"Calle de Real, 14 Sanfelismo Le\u00f3n 24227",
    "addr:housenumber":"14",
    "addr:postcode":"24227",
    "addr:street":"Calle De Real;Leo\u0301N",
    "iso:country":"ES",
    "sg:address":"Calle de Real, 14",
    "sg:city":"Sanfelismo",
    "sg:orig_category":"Empresas De Electricidad En General",
    "sg:phone":"+34 987 20 63 11",
    "sg:postcode":"24227",
    "sg:province":"Le\u00f3n",
    "wof:name":"Embutidos Anjos S. L.",
    "wof:placetype":"venue"
},
  "geometry": {"coordinates":[-5.4802489281,42.5667266846],"type":"Point"}
}