{
  "type": "Feature",
  "properties": {
    "addr:full":"Calle de Levante, 15 Castellar-oliveral Valencia 46026",
    "addr:housenumber":"15",
    "addr:postcode":"46026",
    "addr:street":"Calle De Levante",
    "iso:country":"ES",
    "sg:address":"Calle de Levante, 15",
    "sg:city":"Castellar-oliveral",
    "sg:orig_category":"Venta, Montaje De Neum\u00c1ticos",
    "sg:phone":"+34 963 96 18 89",
    "sg:postcode":"46026",
    "sg:province":"Valencia",
    "wof:name":"Neumaticos Tamarit S.l.",
    "wof:placetype":"venue"
},
  "geometry": {"coordinates":[-0.3628099859,39.4258308411],"type":"Point"}
}