{
  "type": "Feature",
  "properties": {
    "addr:full":"Pda Castell, 25 Figueres Girona 17600",
    "addr:postcode":"17600",
    "iso:country":"ES",
    "sg:address":"Pda Castell, 25",
    "sg:city":"Figueres",
    "sg:orig_category":"Fisioterapia",
    "sg:phone":"+34 972 50 53 43",
    "sg:postcode":"17600",
    "sg:province":"Girona",
    "wof:name":"Jacomet Carrasco Arturo",
    "wof:placetype":"venue"
},
  "geometry": {"coordinates":[2.9589960575,42.2673568726],"type":"Point"}
}