{
  "type": "Feature",
  "properties": {
    "iso:country":"ES",
    "sg:address":"Calle de Sevilla, 31",
    "sg:city":"Madridejos",
    "sg:orig_category":"Promotores Constructores",
    "sg:phone":"+34 925 46 09 69",
    "sg:postcode":"45710",
    "sg:province":"Toledo",
    "wof:name":"Galan Rodriguez Angel",
    "wof:placetype":"venue"
},
  "geometry": {"coordinates":[-3.53215909,39.4659881592],"type":"Point"}
}