{
  "type": "Feature",
  "properties": {
    "iso:country":"ES",
    "sg:address":"Calle de Puerto, 9",
    "sg:city":"Huelva",
    "sg:orig_category":"Peluquer\u00cdas, Peluquer\u00cda Mixta",
    "sg:phone":"+34 959 28 31 32",
    "sg:postcode":"21001",
    "sg:province":"Huelva",
    "wof:name":"Claro Peluqueria De Huelva S.l.",
    "wof:placetype":"venue"
},
  "geometry": {"coordinates":[-6.9516158104,37.2583465576],"type":"Point"}
}