{
  "type": "Feature",
  "properties": {
    "addr:full":"Pg Pla\u00c7a Major, 21 Sabadell Barcelona 08201",
    "addr:housenumber":"21",
    "addr:postcode":"08201",
    "addr:street":"Pg Plac\u0327A Major",
    "iso:country":"ES",
    "sg:address":"Pg Pla\u00c7a Major, 21",
    "sg:city":"Sabadell",
    "sg:orig_category":"Camiser\u00cda Y Ropa Interior Masculina (al Por Menor)",
    "sg:phone":"+34 937 26 20 12",
    "sg:postcode":"08201",
    "sg:province":"Barcelona",
    "sg:website":"www.intimissimi.com",
    "wof:name":"Calzintimi S.l.",
    "wof:placetype":"venue"
},
  "geometry": {"coordinates":[2.1086521149,41.5481071472],"type":"Point"}
}