{
  "type": "Feature",
  "properties": {
    "iso:country":"ES",
    "sg:address":"Plaz Cervantes, 2",
    "sg:city":"Ruidera",
    "sg:orig_category":"Carnicer\u00cdas, Carnicer\u00cdas",
    "sg:phone":"+34 926 52 81 67",
    "sg:postcode":"13249",
    "sg:province":"Ciudad Real",
    "wof:name":"Rodriguez Capdevila Juana",
    "wof:placetype":"venue"
},
  "geometry": {"coordinates":[-2.8850429058,38.9766159058],"type":"Point"}
}