{
  "type": "Feature",
  "properties": {
    "iso:country":"ES",
    "sg:address":"Ctra Turro, 15",
    "sg:city":"Moraleda Zafayona",
    "sg:orig_category":"Empresarios",
    "sg:phone":"+34 958 44 33 66",
    "sg:postcode":"18370",
    "sg:province":"Granada",
    "wof:name":"Perez Arcalladas Jose",
    "wof:placetype":"venue"
},
  "geometry": {"coordinates":[-3.9653298855,37.1661605835],"type":"Point"}
}