{
  "type": "Feature",
  "properties": {
    "addr:full":"Plaz Altozano (del), 17 Trebujena C\u00e1diz 11560",
    "addr:postcode":"11560",
    "addr:street":"Plaz;Del;Ca\u0301Diz",
    "iso:country":"ES",
    "sg:address":"Plaz Altozano (del), 17",
    "sg:city":"Trebujena",
    "sg:orig_category":"M\u00c9dicos: Salud P\u00dablica",
    "sg:phone":"+34 956 39 51 68",
    "sg:postcode":"11560",
    "sg:province":"C\u00e1diz",
    "wof:name":"Martinez Uceda Rafael",
    "wof:placetype":"venue"
},
  "geometry": {"coordinates":[-6.1772689819,36.8707580566],"type":"Point"}
}