{
  "type": "Feature",
  "properties": {
    "addr:full":"Ruiz De Alda, 2 Iru\u00f1a Navarra 31004",
    "addr:housenumber":"2",
    "addr:postcode":"31004",
    "addr:street":"Ruiz De Alda",
    "iso:country":"ES",
    "sg:address":"Ruiz De Alda, 2",
    "sg:city":"Iru\u00f1a",
    "sg:orig_category":"Peluqueros: De Se\u00d1oras",
    "sg:phone":"+34 948 23 57 27",
    "sg:postcode":"31004",
    "sg:province":"Navarra",
    "wof:name":"Anaut Martinez Ana Maria",
    "wof:placetype":"venue"
},
  "geometry": {"coordinates":[-1.632843852,42.8113746643],"type":"Point"}
}