{
  "type": "Feature",
  "properties": {
    "iso:country":"ES",
    "sg:address":"Calle de Cola Y Goiti, 4",
    "sg:city":"Vitoria-gasteiz",
    "sg:orig_category":"Imprenta",
    "sg:phone":"+34 945 06 05 25",
    "sg:postcode":"01003",
    "sg:province":"\u00c1lava",
    "wof:name":"Imprenta Faro",
    "wof:placetype":"venue"
},
  "geometry": {"coordinates":[-2.6633806229,42.8468360901],"type":"Point"}
}