{
  "type": "Feature",
  "properties": {
    "addr:full":"C/ Canal, 20 Banyoles Girona 17820",
    "addr:housenumber":"20",
    "addr:postcode":"17820",
    "addr:street":"C / Canal",
    "iso:country":"ES",
    "sg:address":"C/ Canal, 20",
    "sg:city":"Banyoles",
    "sg:orig_category":"Confecci\u00d3n De Trajes Para Se\u00d1oras",
    "sg:phone":"+34 972 57 03 69",
    "sg:postcode":"17820",
    "sg:province":"Girona",
    "wof:name":"Vinardell Capell Dolors",
    "wof:placetype":"venue"
},
  "geometry": {"coordinates":[2.7644820213,42.1184654236],"type":"Point"}
}