{
  "type": "Feature",
  "properties": {
    "addr:full":"Union, 49 Vecindario Las Palmas 35110",
    "addr:housenumber":"49",
    "addr:postcode":"35110",
    "addr:street":"Vecindario Las Palmas",
    "iso:country":"ES",
    "sg:address":"Union, 49",
    "sg:city":"Vecindario",
    "sg:orig_category":"Asociaciones Y Clubs Deportivos",
    "sg:phone":"+34 928 79 03 69",
    "sg:postcode":"35110",
    "sg:province":"Las Palmas",
    "wof:name":"Union Deportiva Vecindario",
    "wof:placetype":"venue"
},
  "geometry": {"coordinates":[-15.446518898,27.8484344482],"type":"Point"}
}