{
  "type": "Feature",
  "properties": {
    "addr:full":"Carrer de Barcelona, 98 Granollers Barcelona 08401",
    "addr:housenumber":"98",
    "addr:postcode":"08401",
    "addr:street":"Carrer De Barcelona",
    "iso:country":"ES",
    "sg:address":"Carrer de Barcelona, 98",
    "sg:city":"Granollers",
    "sg:orig_category":"Institutos De Belleza",
    "sg:phone":"+34 902 11 31 11",
    "sg:postcode":"08401",
    "sg:province":"Barcelona",
    "wof:name":"Laser Touch S.l.",
    "wof:placetype":"venue"
},
  "geometry": {"coordinates":[2.2869501114,41.6051597595],"type":"Point"}
}