{
  "type": "Feature",
  "properties": {
    "iso:country":"ES",
    "sg:address":"Treinta Enero 1964, 14",
    "sg:city":"Burgos",
    "sg:orig_category":"Empresas De Demolici\u00d3n",
    "sg:phone":"+34 947 48 27 78",
    "sg:postcode":"09007",
    "sg:province":"Burgos",
    "wof:name":"Excavaciones Hersan S.c.",
    "wof:placetype":"venue"
},
  "geometry": {"coordinates":[-3.6465480328,42.3613739014],"type":"Point"}
}