{
  "type": "Feature",
  "properties": {
    "addr:full":"Calle de Conde De Salvatierra, 3 Valencia Valencia 46004",
    "addr:housenumber":"3",
    "addr:postcode":"46004",
    "addr:street":"Calle De Conde De Salvatierra",
    "iso:country":"ES",
    "sg:address":"Calle de Conde De Salvatierra, 3",
    "sg:city":"Valencia",
    "sg:orig_category":"Abogados",
    "sg:phone":"+34 963 52 52 48",
    "sg:postcode":"46004",
    "sg:province":"Valencia",
    "wof:name":"Latorre Adell Antonio",
    "wof:placetype":"venue"
},
  "geometry": {"coordinates":[-0.3691542149,39.4711112976],"type":"Point"}
}