{
  "type": "Feature",
  "properties": {
    "addr:full":"Afores, S/n Celra Girona 17460",
    "addr:housenumber":"s / n",
    "addr:postcode":"17460",
    "addr:street":"Afores",
    "iso:country":"ES",
    "sg:address":"Afores, S/n",
    "sg:city":"Celra",
    "sg:orig_category":"Teatro, Ballet, Danza (agrupaciones, Compa\u00d1\u00cdas)",
    "sg:phone":"+34 972 49 41 27",
    "sg:postcode":"17460",
    "sg:province":"Girona",
    "wof:name":"Mal Pelo S.c.c.l.",
    "wof:placetype":"venue"
},
  "geometry": {"coordinates":[2.8774399757,42.0285110474],"type":"Point"}
}