{
  "type": "Feature",
  "properties": {
    "iso:country":"ES",
    "sg:address":"Calle de Javerianas, 1",
    "sg:city":"Rozas De Madrid",
    "sg:orig_category":"Abogados",
    "sg:phone":"+34 917 10 30 64",
    "sg:postcode":"28230",
    "sg:province":"Madrid",
    "wof:name":"Babarro Bueno Gisleno",
    "wof:placetype":"venue"
},
  "geometry": {"coordinates":[-3.8710081577,40.4916038513],"type":"Point"}
}