{
  "type": "Feature",
  "properties": {
    "addr:full":"Avda Bilbao, 1 Medina Pomar Burgos 09500",
    "addr:housenumber":"1",
    "addr:postcode":"09500",
    "addr:street":"Avda Bilbao",
    "iso:country":"ES",
    "sg:address":"Avda Bilbao, 1",
    "sg:city":"Medina Pomar",
    "sg:orig_category":"Cajas De Ahorro",
    "sg:phone":"+34 947 14 71 96",
    "sg:postcode":"09500",
    "sg:province":"Burgos",
    "sg:website":"www.lacaixa.es",
    "wof:name":"Caixa D'estalvis I Pensions De Barcelona",
    "wof:placetype":"venue"
},
  "geometry": {"coordinates":[-3.4861359596,42.9326133728],"type":"Point"}
}