{
  "type": "Feature",
  "properties": {
    "addr:full":"Calle de Fernando El Catolico, 11 Madrid Madrid 28015",
    "addr:housenumber":"11",
    "addr:postcode":"madrid;28015",
    "addr:street":"Calle De Fernando El Catolico",
    "iso:country":"ES",
    "sg:address":"Calle de Fernando El Catolico, 11",
    "sg:city":"Madrid",
    "sg:orig_category":"Arquitectos",
    "sg:phone":"+34 914 48 34 83",
    "sg:postcode":"28015",
    "sg:province":"Madrid",
    "sg:website":"www.arquide.es",
    "wof:name":"Arquide Estudio S.l.",
    "wof:placetype":"venue"
},
  "geometry": {"coordinates":[-3.7071328163,40.4338569641],"type":"Point"}
}