{
  "type": "Feature",
  "properties": {
    "addr:full":"Avda Mediterraneo (del), S/n Almeria Almer\u00eda 04007",
    "addr:housenumber":"/ n",
    "addr:postcode":"04007",
    "addr:street":"Avda Mediterraneo Del S",
    "iso:country":"ES",
    "sg:address":"Avda Mediterraneo (del), S/n",
    "sg:city":"Almeria",
    "sg:orig_category":"Zapatos (al Por Menor)",
    "sg:phone":"+34 950 14 39 44",
    "sg:postcode":"04007",
    "sg:province":"Almer\u00eda",
    "wof:name":"Vicente Nu\u00f1ez Jose Juan",
    "wof:placetype":"venue"
},
  "geometry": {"coordinates":[-2.4460990429,36.8307914734],"type":"Point"}
}