{
  "type": "Feature",
  "properties": {
    "addr:full":"Ctra Camposancos, 165 Verdeal Pontevedra 36330",
    "addr:housenumber":"165",
    "addr:postcode":"36330",
    "addr:street":"Ctra Camposancos",
    "iso:country":"ES",
    "sg:address":"Ctra Camposancos, 165",
    "sg:city":"Verdeal",
    "sg:orig_category":"Electrodom\u00c9sticos (al Por Menor)",
    "sg:phone":"+34 986 29 56 50",
    "sg:postcode":"36330",
    "sg:province":"Pontevedra",
    "wof:name":"Electro Alpra C.b.",
    "wof:placetype":"venue"
},
  "geometry": {"coordinates":[-8.694773674,42.6678962708],"type":"Point"}
}