{
  "type": "Feature",
  "properties": {
    "addr:full":"Carrer de Pau Claris, 131 Barcelona Barcelona 08009",
    "addr:housenumber":"131",
    "addr:postcode":"08009",
    "addr:street":"Carrer De Pau Claris",
    "iso:country":"ES",
    "sg:address":"Carrer de Pau Claris, 131",
    "sg:city":"Barcelona",
    "sg:orig_category":"Internados & Ense\u00d1anza Privada",
    "sg:phone":"+34 934 87 54 79",
    "sg:postcode":"08009",
    "sg:province":"Barcelona",
    "wof:name":"Col.legi Lestonnac",
    "wof:placetype":"venue"
},
  "geometry": {"coordinates":[2.1664040089,41.3931312561],"type":"Point"}
}