{
  "type": "Feature",
  "properties": {
    "iso:country":"ES",
    "sg:address":"Calle de Santo Tomas, 21",
    "sg:city":"Avila",
    "sg:orig_category":"Plomeros",
    "sg:phone":"+34 920 22 76 17",
    "sg:postcode":"05003",
    "sg:province":"\u00c1vila",
    "wof:name":"Martin Ramos Luis",
    "wof:placetype":"venue"
},
  "geometry": {"coordinates":[-4.6920318604,40.646194458],"type":"Point"}
}