{
  "type": "Feature",
  "properties": {
    "addr:full":"Calle de Javier De Miguel, 7 Madrid Madrid 28018",
    "addr:housenumber":"7",
    "addr:postcode":"madrid;28018",
    "addr:street":"Calle De Javier De Miguel",
    "iso:country":"ES",
    "sg:address":"Calle de Javier De Miguel, 7",
    "sg:city":"Madrid",
    "sg:orig_category":"Peluquer\u00cdas, Peluquer\u00cda Mixta",
    "sg:phone":"+34 914 77 27 37",
    "sg:postcode":"28018",
    "sg:province":"Madrid",
    "wof:name":"Zache Peluqueros",
    "wof:placetype":"venue"
},
  "geometry": {"coordinates":[-3.6635520458,40.3890075684],"type":"Point"}
}