{
  "type": "Feature",
  "properties": {
    "iso:country":"ES",
    "sg:address":"Calle de Santiago, 13",
    "sg:city":"Valladolid",
    "sg:orig_category":"Promotores Constructores",
    "sg:phone":"+34 983 36 31 20",
    "sg:postcode":"47001",
    "sg:province":"Valladolid",
    "wof:name":"Silver Eagle De Desarrollos Inmobiliarios",
    "wof:placetype":"venue"
},
  "geometry": {"coordinates":[-4.728512764,41.6503105164],"type":"Point"}
}