{
  "type": "Feature",
  "properties": {
    "addr:full":"Carrer de Dante Alighieri, 66 Barcelona Barcelona 08032",
    "addr:housenumber":"66",
    "addr:postcode":"08032",
    "addr:street":"Carrer De Dante Alighieri",
    "iso:country":"ES",
    "sg:address":"Carrer de Dante Alighieri, 66",
    "sg:city":"Barcelona",
    "sg:orig_category":"Alimentaci\u00d3n General (al Por Menor)",
    "sg:phone":"+34 934 20 83 91",
    "sg:postcode":"08032",
    "sg:province":"Barcelona",
    "wof:name":"Mir Villanova Pedro",
    "wof:placetype":"venue"
},
  "geometry": {"coordinates":[2.1584730148,41.427947998],"type":"Point"}
}