{
  "type": "Feature",
  "properties": {
    "iso:country":"ES",
    "sg:address":"Calle de Calvario, 1",
    "sg:city":"Murillo El Fruto",
    "sg:orig_category":"Cooperativas Agr\u00cdcolas",
    "sg:phone":"+34 948 72 52 39",
    "sg:postcode":"31313",
    "sg:province":"Navarra",
    "wof:name":"Cooperativa Agricola San Isidro Labrador",
    "wof:placetype":"venue"
},
  "geometry": {"coordinates":[-1.461273551,42.3924942017],"type":"Point"}
}