{
  "type": "Feature",
  "properties": {
    "iso:country":"ES",
    "sg:address":"Calle de Diego Vazquez Otero, 3",
    "sg:city":"Malaga",
    "sg:orig_category":"Empresas De Hormig\u00d3n, Hormig\u00d3n Armado Y Pretensado",
    "sg:phone":"+34 952 28 33 14",
    "sg:postcode":"29007",
    "sg:province":"M\u00e1laga",
    "wof:name":"Consolidada De Inversiones S.a.",
    "wof:placetype":"venue"
},
  "geometry": {"coordinates":[-4.4389419556,36.7177810669],"type":"Point"}
}