{
  "type": "Feature",
  "properties": {
    "addr:full":"Calle de Mendibile, 8 Leioa Vizcaya 48940",
    "addr:housenumber":"8",
    "addr:postcode":"48940",
    "addr:street":"Calle De Mendibile",
    "iso:country":"ES",
    "sg:address":"Calle de Mendibile, 8",
    "sg:city":"Leioa",
    "sg:orig_category":"Caf\u00c9s, Bares, Cervecer\u00cdas",
    "sg:phone":"+34 944 02 29 12",
    "sg:postcode":"48940",
    "sg:province":"Vizcaya",
    "wof:name":"Juan Luis Ruiz Nieto",
    "wof:placetype":"venue"
},
  "geometry": {"coordinates":[-2.9826788902,43.3242683411],"type":"Point"}
}