{
  "type": "Feature",
  "properties": {
    "addr:full":"Rua Ines De Castro, 1 Monforte De Lemos Lugo 27400",
    "addr:housenumber":"1",
    "addr:postcode":"27400",
    "addr:street":"Rua Ines De Castro",
    "iso:country":"ES",
    "sg:address":"Rua Ines De Castro, 1",
    "sg:city":"Monforte De Lemos",
    "sg:orig_category":"Alquiler De V\u00cddeo",
    "sg:phone":"+34 982 40 27 11",
    "sg:postcode":"27400",
    "sg:province":"Lugo",
    "wof:name":"Seri C.b.",
    "wof:placetype":"venue"
},
  "geometry": {"coordinates":[-7.5129728317,42.5206184387],"type":"Point"}
}