{
  "type": "Feature",
  "properties": {
    "iso:country":"ES",
    "sg:address":"Calle de Eladio Laredo, 5",
    "sg:city":"Castro Urdiales",
    "sg:orig_category":"Caf\u00c9s, Bares, Cervecer\u00cdas",
    "sg:phone":"+34 942 86 23 72",
    "sg:postcode":"39700",
    "sg:province":"Cantabria",
    "wof:name":"Martin Cortes Pablo",
    "wof:placetype":"venue"
},
  "geometry": {"coordinates":[-3.2217183113,43.382938385],"type":"Point"}
}