{
  "type": "Feature",
  "properties": {
    "addr:full":"Carr Verge De Montserrat, 10 Rossello Lleida 25124",
    "addr:housenumber":"10",
    "addr:postcode":"25124",
    "addr:street":"Carr Verge De Montserrat",
    "iso:country":"ES",
    "sg:address":"Carr Verge De Montserrat, 10",
    "sg:city":"Rossello",
    "sg:orig_category":"Mec\u00c1nico Del Autom\u00d3vil",
    "sg:phone":"+34 973 73 04 83",
    "sg:postcode":"25124",
    "sg:province":"Lleida",
    "wof:name":"Rafael Fernandez Ballesta-josefa Gallart Mayoral Cdad.",
    "wof:placetype":"venue"
},
  "geometry": {"coordinates":[0.5941299796,41.6937103271],"type":"Point"}
}