{
  "type": "Feature",
  "properties": {
    "addr:full":"Calle de Vazquez De Mella, 11 Oviedo Asturias 33012",
    "addr:housenumber":"11",
    "addr:postcode":"33012",
    "addr:street":"Calle De Vazquez De Mella",
    "iso:country":"ES",
    "sg:address":"Calle de Vazquez De Mella, 11",
    "sg:city":"Oviedo",
    "sg:orig_category":"Electricidad, Electr\u00d3nica: Material Y Suministros (al Por Mayor)",
    "sg:phone":"+34 985 23 75 18",
    "sg:postcode":"33012",
    "sg:province":"Asturias",
    "wof:name":"Dirmo S. A.",
    "wof:placetype":"venue"
},
  "geometry": {"coordinates":[-5.8617210388,43.3644714355],"type":"Point"}
}