{
  "type": "Feature",
  "properties": {
    "addr:full":"Calle de Salazar General, 6 Bilbao Vizcaya 48012",
    "addr:housenumber":"6",
    "addr:postcode":"48012",
    "addr:street":"Calle De Salazar General",
    "iso:country":"ES",
    "sg:address":"Calle de Salazar General, 6",
    "sg:city":"Bilbao",
    "sg:orig_category":"Comercio, Reparaci\u00d3n De Motocicletas, Bicicletas Y Piezas Sueltas",
    "sg:phone":"+34 944 43 26 00",
    "sg:postcode":"48012",
    "sg:province":"Vizcaya",
    "wof:name":"Hesperia Internacional S.l.",
    "wof:placetype":"venue"
},
  "geometry": {"coordinates":[-2.9395470619,43.256023407],"type":"Point"}
}