{
  "type": "Feature",
  "properties": {
    "addr:full":"Carrer de Torrent De L'olla, 20 Barcelona Barcelona 08012",
    "addr:housenumber":"20",
    "addr:postcode":"08012",
    "addr:street":"Carrer De Torrent De L'Olla",
    "iso:country":"ES",
    "sg:address":"Carrer de Torrent De L'olla, 20",
    "sg:city":"Barcelona",
    "sg:orig_category":"Molduras, Junquillos, Listones Y Molduras Perforadas",
    "sg:phone":"+34 934 58 96 61",
    "sg:postcode":"08012",
    "sg:province":"Barcelona",
    "wof:name":"Navarro Codina Antoni",
    "wof:placetype":"venue"
},
  "geometry": {"coordinates":[2.1608390808,41.3989334106],"type":"Point"}
}