{
  "type": "Feature",
  "properties": {
    "iso:country":"ES",
    "sg:address":"Carrer de Secretari Coloma, 1",
    "sg:city":"Barcelona",
    "sg:orig_category":"Costureras",
    "sg:phone":"+34 934 59 20 01",
    "sg:postcode":"08025",
    "sg:province":"Barcelona",
    "wof:name":"Casafont Torrebadella Florencia",
    "wof:placetype":"venue"
},
  "geometry": {"coordinates":[2.1657879353,41.406578064],"type":"Point"}
}