{
  "type": "Feature",
  "properties": {
    "iso:country":"ES",
    "sg:address":"Calle de Enrique Segura Ota\u00d1o, 10",
    "sg:city":"Badajoz",
    "sg:orig_category":"Cl\u00cdnicas Dentales",
    "sg:phone":"+34 924 22 90 17",
    "sg:postcode":"06004",
    "sg:province":"Badajoz",
    "wof:name":"Lubangodent S.l.",
    "wof:placetype":"venue"
},
  "geometry": {"coordinates":[-6.9702987671,38.8731803894],"type":"Point"}
}