{
  "type": "Feature",
  "properties": {
    "addr:full":"Carrer de Barcelona, 1 Mora D'ebre Tarragona 43740",
    "addr:housenumber":"1",
    "addr:postcode":"43740",
    "addr:street":"Carrer De Barcelona;D'Ebre",
    "iso:country":"ES",
    "sg:address":"Carrer de Barcelona, 1",
    "sg:city":"Mora D'ebre",
    "sg:orig_category":"Supermercados Y Hipermercados",
    "sg:phone":"+34 977 40 01 95",
    "sg:postcode":"43740",
    "sg:province":"Tarragona",
    "wof:name":"Garcia Valverde Mercedes",
    "wof:placetype":"venue"
},
  "geometry": {"coordinates":[0.6425781846,41.0880432129],"type":"Point"}
}