{
  "type": "Feature",
  "properties": {
    "addr:full":"Calle de Teniente Oyaga, 36 Palma Islas Baleares 07004",
    "addr:housenumber":"36",
    "addr:postcode":"07004",
    "addr:street":"Calle De Teniente Oyaga",
    "iso:country":"ES",
    "sg:address":"Calle de Teniente Oyaga, 36",
    "sg:city":"Palma",
    "sg:orig_category":"Instalaci\u00d3n, Reparaci\u00d3n De Ascensores Y Montacargas",
    "sg:phone":"+34 971 76 22 23",
    "sg:postcode":"07004",
    "sg:province":"Islas Baleares",
    "wof:name":"Mecano Y Elevacion Ascensores S.l.",
    "wof:placetype":"venue"
},
  "geometry": {"coordinates":[2.6610789299,39.5861930847],"type":"Point"}
}