{
  "type": "Feature",
  "properties": {
    "addr:full":"Avgd Catalunya, 65 Badalona Barcelona 08917",
    "addr:housenumber":"65",
    "addr:postcode":"08917",
    "iso:country":"ES",
    "sg:address":"Avgd Catalunya, 65",
    "sg:city":"Badalona",
    "sg:orig_category":"Cajas De Ahorro",
    "sg:phone":"+34 933 97 34 03",
    "sg:postcode":"08917",
    "sg:province":"Barcelona",
    "sg:website":"www.laietana.net",
    "wof:name":"Caixa D'estalvis Laietana",
    "wof:placetype":"venue"
},
  "geometry": {"coordinates":[2.2310209274,41.4515838623],"type":"Point"}
}