{
  "type": "Feature",
  "properties": {
    "iso:country":"ES",
    "sg:address":"Rua Calvo Sotelo, 184",
    "sg:city":"Sarria",
    "sg:orig_category":"Asistencia Social",
    "sg:phone":"+34 982 53 00 92",
    "sg:postcode":"27600",
    "sg:province":"Lugo",
    "wof:name":"Cruz Roja Espa\u00f1ola",
    "wof:placetype":"venue"
},
  "geometry": {"coordinates":[-7.4082288742,42.7770118713],"type":"Point"}
}