{
  "type": "Feature",
  "properties": {
    "iso:country":"ES",
    "sg:address":"Pase Curas (de Los), 19",
    "sg:city":"Alcala Henares",
    "sg:orig_category":"Cajas De Ahorro",
    "sg:phone":"+34 918 77 04 81",
    "sg:postcode":"28803",
    "sg:province":"Madrid",
    "wof:name":"Caixa D'estalvis Laietana",
    "wof:placetype":"venue"
},
  "geometry": {"coordinates":[-3.7057700157,40.42029953],"type":"Point"}
}