{
  "type": "Feature",
  "properties": {
    "addr:full":"Rond Segovia, 14 Madrid Madrid 28005",
    "addr:housenumber":"14",
    "addr:postcode":"madrid;28005",
    "addr:street":"Segovia",
    "iso:country":"ES",
    "sg:address":"Rond Segovia, 14",
    "sg:city":"Madrid",
    "sg:orig_category":"Ropa Para Se\u00d1oras Y Caballeros (al Por Menor)",
    "sg:phone":"+34 913 66 78 06",
    "sg:postcode":"28005",
    "sg:province":"Madrid",
    "wof:name":"Other Time S.l.",
    "wof:placetype":"venue"
},
  "geometry": {"coordinates":[-3.7111589909,40.4138336182],"type":"Point"}
}