{
  "type": "Feature",
  "properties": {
    "iso:country":"ES",
    "sg:address":"Carr Joaquim Maria Masramon I De Ventos, 4",
    "sg:city":"Girona",
    "sg:orig_category":"Transportes Por V\u00cdas Navegables",
    "sg:phone":"+34 972 22 53 57",
    "sg:postcode":"17003",
    "sg:province":"Girona",
    "wof:name":"Bruguera Bellvehi Jaume",
    "wof:placetype":"venue"
},
  "geometry": {"coordinates":[2.8226749897,41.9601249695],"type":"Point"}
}