{
  "type": "Feature",
  "properties": {
    "addr:full":"Avda Carlos I De, 28 Donostia-san Sebastian Guip\u00f9zcoa 20011",
    "addr:housenumber":"28",
    "addr:postcode":"20011",
    "addr:street":"Avda Carlos I De",
    "iso:country":"ES",
    "sg:address":"Avda Carlos I De, 28",
    "sg:city":"Donostia-san Sebastian",
    "sg:orig_category":"Ropa Para Se\u00d1oras (al Por Menor)",
    "sg:phone":"+34 943 46 54 97",
    "sg:postcode":"20011",
    "sg:province":"Guip\u00f9zcoa",
    "wof:name":"Breton Sarasola Emma",
    "wof:placetype":"venue"
},
  "geometry": {"coordinates":[-1.9790170193,43.3030815125],"type":"Point"}
}