{
  "type": "Feature",
  "properties": {
    "iso:country":"ES",
    "sg:address":"Avda Burgos, 94",
    "sg:city":"Logro\u00f1o",
    "sg:orig_category":"Muebles, Minoristas",
    "sg:phone":"+34 941 20 67 52",
    "sg:postcode":"26006",
    "sg:province":"La Rioja",
    "wof:name":"Santamaria Maga\u00f1a Josefa",
    "wof:placetype":"venue"
},
  "geometry": {"coordinates":[-2.475769043,42.4604034424],"type":"Point"}
}