{
  "type": "Feature",
  "properties": {
    "iso:country":"ES",
    "sg:address":"Calle de Andalucia, 27",
    "sg:city":"Molina Segura",
    "sg:orig_category":"Agencias Y Agentes Comerciales, Representantes",
    "sg:phone":"+34 968 61 18 03",
    "sg:postcode":"30500",
    "sg:province":"Murcia",
    "wof:name":"Parra Cayuela Antonio",
    "wof:placetype":"venue"
},
  "geometry": {"coordinates":[-1.2013914585,38.05727005],"type":"Point"}
}