{
  "type": "Feature",
  "properties": {
    "iso:country":"ES",
    "sg:address":"Calle de Mendiko Kalea, 61",
    "sg:city":"Amurrio",
    "sg:orig_category":"Plomeros",
    "sg:phone":"+34 945 39 37 42",
    "sg:postcode":"01470",
    "sg:province":"\u00c1lava",
    "wof:name":"Puertas Balboa Mateo",
    "wof:placetype":"venue"
},
  "geometry": {"coordinates":[-3.0217339993,43.0432891846],"type":"Point"}
}