{
  "type": "Feature",
  "properties": {
    "iso:country":"ES",
    "sg:address":"Calle de Pintor Renau, 42",
    "sg:city":"Torrent",
    "sg:orig_category":"Productos Qu\u00cdmicos (fabricaci\u00d3n, Al Por Mayor)",
    "sg:phone":"+34 961 57 05 23",
    "sg:postcode":"46900",
    "sg:province":"Valencia",
    "sg:website":"www.labaqua.es",
    "wof:name":"Labaqua S.a.",
    "wof:placetype":"venue"
},
  "geometry": {"coordinates":[-0.4778394103,39.4333381653],"type":"Point"}
}