{
  "type": "Feature",
  "properties": {
    "addr:full":"Carr Cami Des Castell, 34 Mao Islas Baleares 07702",
    "addr:housenumber":"34",
    "addr:postcode":"07702",
    "addr:street":"Carr Cami Des Castell",
    "iso:country":"ES",
    "sg:address":"Carr Cami Des Castell, 34",
    "sg:city":"Mao",
    "sg:orig_category":"Cester\u00cda (fabricaci\u00d3n)",
    "sg:phone":"+34 971 36 40 65",
    "sg:postcode":"07702",
    "sg:province":"Islas Baleares",
    "wof:name":"Pons Tuduri Manuela",
    "wof:placetype":"venue"
},
  "geometry": {"coordinates":[4.2672038078,39.8874320984],"type":"Point"}
}