{
  "type": "Feature",
  "properties": {
    "addr:full":"Calle de Jesus Hernandez, 3 Cehegin Murcia 30430",
    "addr:housenumber":"3",
    "addr:postcode":"30430",
    "addr:street":"Calle De Jesus Hernandez",
    "iso:country":"ES",
    "sg:address":"Calle de Jesus Hernandez, 3",
    "sg:city":"Cehegin",
    "sg:orig_category":"Florister\u00cdas",
    "sg:phone":"+34 968 74 03 84",
    "sg:postcode":"30430",
    "sg:province":"Murcia",
    "wof:name":"Carmona Valera Jose Antonio",
    "wof:placetype":"venue"
},
  "geometry": {"coordinates":[-1.7875219584,38.0923995972],"type":"Point"}
}