{
  "type": "Feature",
  "properties": {
    "addr:full":"Calle de Arriero, S/n Alcala Guadaira Sevilla 41500",
    "addr:postcode":"41500",
    "addr:street":"Calle De Arriero S / N",
    "iso:country":"ES",
    "sg:address":"Calle de Arriero, S/n",
    "sg:city":"Alcala Guadaira",
    "sg:orig_category":"Centros De Educaci\u00d3n Especial",
    "sg:phone":"+34 955 68 63 20",
    "sg:postcode":"41500",
    "sg:province":"Sevilla",
    "wof:name":"Junta De Andalucia- Ceip Reina Fabiola",
    "wof:placetype":"venue"
},
  "geometry": {"coordinates":[-5.8373026848,37.3295478821],"type":"Point"}
}