{
  "type": "Feature",
  "properties": {
    "addr:full":"Calle de Iglesia, 60 Fuengirola M\u00e1laga 29640",
    "addr:housenumber":"60",
    "addr:postcode":"29640",
    "addr:street":"Calle De Iglesia;Ma\u0301Laga",
    "iso:country":"ES",
    "sg:address":"Calle de Iglesia, 60",
    "sg:city":"Fuengirola",
    "sg:orig_category":"Abogados",
    "sg:phone":"+34 952 47 31 86",
    "sg:postcode":"29640",
    "sg:province":"M\u00e1laga",
    "wof:name":"Moreno Rodriguez Eduardo",
    "wof:placetype":"venue"
},
  "geometry": {"coordinates":[-4.615457058,36.5524711609],"type":"Point"}
}