{
  "type": "Feature",
  "properties": {
    "addr:full":"Urb. Almendral, S/n Jerez C\u00e1diz 11407",
    "addr:housenumber":"s / n",
    "addr:postcode":"11407",
    "addr:street":"Almendral",
    "iso:country":"ES",
    "sg:address":"Urb. Almendral, S/n",
    "sg:city":"Jerez",
    "sg:orig_category":"Empresas De Desmonte",
    "sg:phone":"+34 956 30 29 15",
    "sg:postcode":"11407",
    "sg:province":"C\u00e1diz",
    "wof:name":"Oliva Duran Jose",
    "wof:placetype":"venue"
},
  "geometry": {"coordinates":[-6.1390857697,36.7034568787],"type":"Point"}
}