{
  "type": "Feature",
  "properties": {
    "iso:country":"ES",
    "sg:address":"Rond Sant Antoni, 13",
    "sg:city":"Barcelona",
    "sg:orig_category":"Inmobiliaria (agencias)",
    "sg:phone":"+34 934 43 62 62",
    "sg:postcode":"08011",
    "sg:province":"Barcelona",
    "wof:name":"Fincas Corral S.l.",
    "wof:placetype":"venue"
},
  "geometry": {"coordinates":[2.163077116,41.3799324036],"type":"Point"}
}