{
  "type": "Feature",
  "properties": {
    "addr:full":"Avda Arteijo, 4 Coru\u00d1a A Coru\u00f1a 15004",
    "addr:housenumber":"4",
    "addr:postcode":"15004",
    "addr:street":"Avda Arteijo;Corun\u0303A",
    "iso:country":"ES",
    "sg:address":"Avda Arteijo, 4",
    "sg:city":"Coru\u00d1a",
    "sg:orig_category":"Electricidad, Electr\u00d3nica: Suministros (al Por Menor)",
    "sg:phone":"+34 981 25 99 02",
    "sg:postcode":"15004",
    "sg:province":"A Coru\u00f1a",
    "wof:name":"Sonytel Galicia S. A.",
    "wof:placetype":"venue"
},
  "geometry": {"coordinates":[-8.4116697311,43.3660888672],"type":"Point"}
}