{
  "type": "Feature",
  "properties": {
    "iso:country":"ES",
    "sg:address":"Calle de Manuel Laguna, 25",
    "sg:city":"Madrid",
    "sg:orig_category":"Ebanister\u00cda",
    "sg:phone":"+34 915 07 59 23",
    "sg:postcode":"28018",
    "sg:province":"Madrid",
    "wof:name":"Tamayo Rodriguez Alejandro",
    "wof:placetype":"venue"
},
  "geometry": {"coordinates":[-3.6647388935,40.382106781],"type":"Point"}
}