{
  "type": "Feature",
  "properties": {
    "iso:country":"ES",
    "sg:address":"Rama Hoyo, 1",
    "sg:city":"Torremolinos",
    "sg:orig_category":"Servicios De Telecomunicaciones",
    "sg:phone":"+34 952 37 57 68",
    "sg:postcode":"29620",
    "sg:province":"M\u00e1laga",
    "wof:name":"Anduphone S.l.",
    "wof:placetype":"venue"
},
  "geometry": {"coordinates":[-4.5160393715,36.6265563965],"type":"Point"}
}