{
  "type": "Feature",
  "properties": {
    "iso:country":"ES",
    "sg:address":"Carr Sequiota, 15",
    "sg:city":"Benicasim",
    "sg:orig_category":"Fachadas",
    "sg:phone":"+34 964 30 00 39",
    "sg:postcode":"12560",
    "sg:province":"Castell\u00f3n",
    "wof:name":"Rocabe 2003 S.l.",
    "wof:placetype":"venue"
},
  "geometry": {"coordinates":[0.0457400009,40.0510292053],"type":"Point"}
}