{
  "type": "Feature",
  "properties": {
    "addr:full":"Calle de Libertad (de La), 115 Navalcarnero Madrid 28600",
    "addr:housenumber":"115",
    "addr:postcode":"28600",
    "addr:street":"Calle De Libertad De La",
    "iso:country":"ES",
    "sg:address":"Calle de Libertad (de La), 115",
    "sg:city":"Navalcarnero",
    "sg:orig_category":"Telas Para Tapizar, Cortinas, Pasamaner\u00cda (fabricaci\u00d3n, Al Por Mayor)",
    "sg:phone":"+34 918 10 15 96",
    "sg:postcode":"28600",
    "sg:province":"Madrid",
    "wof:name":"Navarro Gomez Evangelina",
    "wof:placetype":"venue"
},
  "geometry": {"coordinates":[-4.0118718147,40.2925682068],"type":"Point"}
}