{
  "type": "Feature",
  "properties": {
    "addr:full":"C/ Sant Antoni Maria Claret, 3 Tarrega Lleida 25300",
    "addr:housenumber":"3",
    "addr:postcode":"25300",
    "addr:street":"C / Sant Antoni Maria Claret",
    "iso:country":"ES",
    "sg:address":"C/ Sant Antoni Maria Claret, 3",
    "sg:city":"Tarrega",
    "sg:orig_category":"Molduras, Junquillos, Listones Y Molduras Perforadas",
    "sg:phone":"+34 973 31 32 14",
    "sg:postcode":"25300",
    "sg:province":"Lleida",
    "wof:name":"Serrano Toro Gabriel",
    "wof:placetype":"venue"
},
  "geometry": {"coordinates":[1.1400740147,41.6472625732],"type":"Point"}
}