{
  "type": "Feature",
  "properties": {
    "iso:country":"ES",
    "sg:address":"Avda Cardenal Herrera Oria, 267",
    "sg:city":"Madrid",
    "sg:orig_category":"Piscinas, Accesorios, Suministros (fabricaci\u00d3n, Al Por Mayor)",
    "sg:phone":"+34 913 78 08 03",
    "sg:postcode":"28035",
    "sg:province":"Madrid",
    "wof:name":"Rain-land S. A.",
    "wof:placetype":"venue"
},
  "geometry": {"coordinates":[-3.7237670422,40.4797439575],"type":"Point"}
}