{
  "type": "Feature",
  "properties": {
    "iso:country":"ES",
    "sg:address":"F Rguez De La Fuente(p I Saladas), 16",
    "sg:city":"Torrellano",
    "sg:orig_category":"Mec\u00c1nico Del Autom\u00d3vil",
    "sg:phone":"+34 965 68 22 45",
    "sg:postcode":"03320",
    "sg:province":"Alicante",
    "wof:name":"Miguel Jerez S.l.",
    "wof:placetype":"venue"
},
  "geometry": {"coordinates":[-0.5883839726,38.2929649353],"type":"Point"}
}