{
  "type": "Feature",
  "properties": {
    "addr:full":"V. Castillo, 9 Iru\u00f1a Navarra 31007",
    "addr:housenumber":"9",
    "addr:postcode":"31007",
    "addr:street":"V. Castillo",
    "iso:country":"ES",
    "sg:address":"V. Castillo, 9",
    "sg:city":"Iru\u00f1a",
    "sg:orig_category":"Administradores De Bienes Y Delegados De Comunidades De Propietarios",
    "sg:phone":"+34 948 17 16 46",
    "sg:postcode":"31007",
    "sg:province":"Navarra",
    "wof:name":"De Gomis Casas Francisco",
    "wof:placetype":"venue"
},
  "geometry": {"coordinates":[-1.6420680285,42.817150116],"type":"Point"}
}