{
  "type": "Feature",
  "properties": {
    "iso:country":"ES",
    "sg:address":"Calle de Paz, 1",
    "sg:city":"Torrelavega",
    "sg:orig_category":"Alquiler De Salones",
    "sg:phone":"+34 942 88 18 30",
    "sg:postcode":"39300",
    "sg:province":"Cantabria",
    "wof:name":"Inmobiliaria Monta\u00f1esa S.l.",
    "wof:placetype":"venue"
},
  "geometry": {"coordinates":[-4.048620224,43.3510894775],"type":"Point"}
}