{
  "type": "Feature",
  "properties": {
    "iso:country":"ES",
    "sg:address":"Calle de Zarzamora, 12",
    "sg:city":"Madrid",
    "sg:orig_category":"Deportes Diversos",
    "sg:phone":"+34 914 22 05 07",
    "sg:postcode":"28044",
    "sg:province":"Madrid",
    "wof:name":"Martin Pelayo Carlos",
    "wof:placetype":"venue"
},
  "geometry": {"coordinates":[-3.7461431026,40.37342453],"type":"Point"}
}