{
  "type": "Feature",
  "properties": {
    "iso:country":"ES",
    "sg:address":"Calle de Lledoner, 2",
    "sg:city":"Meliana",
    "sg:orig_category":"Bisuter\u00cda, Joyer\u00cda, Relojer\u00cda (al Por Menor)",
    "sg:phone":"+34 961 49 07 07",
    "sg:postcode":"46133",
    "sg:province":"Valencia",
    "wof:name":"Beltran Carrera Enrique",
    "wof:placetype":"venue"
},
  "geometry": {"coordinates":[-0.3500489891,39.527381897],"type":"Point"}
}