{
  "type": "Feature",
  "properties": {
    "iso:country":"ES",
    "sg:address":"Carrer de Lluis Auguet, S/n",
    "sg:city":"Esparreguera",
    "sg:orig_category":"Mec\u00c1nico Del Autom\u00d3vil",
    "sg:phone":"+34 937 77 48 19",
    "sg:postcode":"08292",
    "sg:province":"Barcelona",
    "wof:name":"Guixa Auge Josep",
    "wof:placetype":"venue"
},
  "geometry": {"coordinates":[1.8719550371,41.5331306458],"type":"Point"}
}