{
  "type": "Feature",
  "properties": {
    "iso:country":"ES",
    "sg:address":"Calle de Dionisio Martin, 26",
    "sg:city":"Peal Becerro",
    "sg:orig_category":"Farmacias",
    "sg:phone":"+34 953 73 03 38",
    "sg:postcode":"23460",
    "sg:province":"Ja\u00e9n",
    "wof:name":"Cervera Bachiller Jose",
    "wof:placetype":"venue"
},
  "geometry": {"coordinates":[-3.1186089516,37.9137191772],"type":"Point"}
}