{
  "type": "Feature",
  "properties": {
    "addr:full":"C/ Eivissa-sant Antoni, Km. 0012,0 S. Antoni Portmany Islas Baleares 07820",
    "addr:postcode":"07820",
    "addr:street":"C / Eivissa-Sant Antoni Km. 0012,0 S. Antoni Portmany",
    "iso:country":"ES",
    "sg:address":"C/ Eivissa-sant Antoni, Km. 0012,0",
    "sg:city":"S. Antoni Portmany",
    "sg:orig_category":"Carb\u00d3n, Carb\u00d3n De Madera (al Por Mayor)",
    "sg:phone":"+34 971 34 44 41",
    "sg:postcode":"07820",
    "sg:province":"Islas Baleares",
    "wof:name":"Bonet Torres Antonio",
    "wof:placetype":"venue"
},
  "geometry": {"coordinates":[1.5188339949,39.1094055176],"type":"Point"}
}