{
  "type": "Feature",
  "properties": {
    "iso:country":"ES",
    "sg:address":"Rua Magnolia, 61",
    "sg:city":"Lugo",
    "sg:orig_category":"Empresas De Carpinter\u00cda De Madera",
    "sg:phone":"+34 982 21 11 90",
    "sg:postcode":"27003",
    "sg:province":"Lugo",
    "wof:name":"Lopez Gonzalez Angel",
    "wof:placetype":"venue"
},
  "geometry": {"coordinates":[-7.5708150864,43.0284233093],"type":"Point"}
}