{
  "type": "Feature",
  "properties": {
    "addr:full":"Calle de Siete Revueltas, 9 Linea De La Concepcion C\u00e1diz 11300",
    "addr:housenumber":"9",
    "addr:postcode":"11300",
    "addr:street":"Calle De Siete Revueltas;Ca\u0301Diz",
    "iso:country":"ES",
    "sg:address":"Calle de Siete Revueltas, 9",
    "sg:city":"Linea De La Concepcion",
    "sg:orig_category":"Iglesia Cat\u00d3lica",
    "sg:phone":"+34 956 17 11 42",
    "sg:postcode":"11300",
    "sg:province":"C\u00e1diz",
    "wof:name":"Parroquia De San Pedro",
    "wof:placetype":"venue"
},
  "geometry": {"coordinates":[-5.3544359207,36.1666526794],"type":"Point"}
}