{
  "type": "Feature",
  "properties": {
    "iso:country":"ES",
    "sg:address":"Calle de Rosal, 2",
    "sg:city":"Aracena",
    "sg:orig_category":"Panader\u00cdas, Panader\u00cdas",
    "sg:phone":"+34 959 12 64 00",
    "sg:postcode":"21200",
    "sg:province":"Huelva",
    "wof:name":"Confiteria Rufino S.l.",
    "wof:placetype":"venue"
},
  "geometry": {"coordinates":[-6.563120842,37.8929328918],"type":"Point"}
}