{
  "type": "Feature",
  "properties": {
    "addr:full":"Calle de Agustin Millares Torres, 32 Canario Las Palmas 35110",
    "addr:housenumber":"32",
    "addr:postcode":"35110",
    "addr:street":"Calle De Agustin Millares Torres;Las Palmas",
    "iso:country":"ES",
    "sg:address":"Calle de Agustin Millares Torres, 32",
    "sg:city":"Canario",
    "sg:orig_category":"Cl\u00cdnicas M\u00c9dicas",
    "sg:phone":"+34 928 75 66 58",
    "sg:postcode":"35110",
    "sg:province":"Las Palmas",
    "wof:name":"Policlinico Santa Barbara S.l.",
    "wof:placetype":"venue"
},
  "geometry": {"coordinates":[-15.4300060272,28.1248226166],"type":"Point"}
}