{
  "type": "Feature",
  "properties": {
    "addr:full":"Carrer de Anoia, S/n Santa Perpetua De Mogoda Barcelona 08130",
    "addr:housenumber":"s / n",
    "addr:postcode":"08130",
    "addr:street":"Carrer De Anoia",
    "iso:country":"ES",
    "sg:address":"Carrer de Anoia, S/n",
    "sg:city":"Santa Perpetua De Mogoda",
    "sg:orig_category":"Construcci\u00d3n Mec\u00c1nica",
    "sg:phone":"+34 935 60 31 66",
    "sg:postcode":"08130",
    "sg:province":"Barcelona",
    "wof:name":"Stemp Industrial S. A.",
    "wof:placetype":"venue"
},
  "geometry": {"coordinates":[2.1755599976,41.5544815063],"type":"Point"}
}