{
  "type": "Feature",
  "properties": {
    "addr:full":"Calle de Olivilla, S/n Puebla Del Principe Ciudad Real 13342",
    "addr:housenumber":"s",
    "addr:postcode":"13342",
    "addr:street":"Calle De Olivilla;/ N;Del Principe",
    "iso:country":"ES",
    "sg:address":"Calle de Olivilla, S/n",
    "sg:city":"Puebla Del Principe",
    "sg:orig_category":"Aceites Y Grasas Alimentarias (fabricaci\u00d3n, Al Por Mayor)",
    "sg:phone":"+34 926 35 91 25",
    "sg:postcode":"13342",
    "sg:province":"Ciudad Real",
    "wof:name":"Cooperativa Nuestra Se\u00f1ora De Mairena",
    "wof:placetype":"venue"
},
  "geometry": {"coordinates":[-2.9234910011,38.5657272339],"type":"Point"}
}