{
  "type": "Feature",
  "properties": {
    "addr:full":"Calle de Alminares Del Genil, 3 Granada Granada 18006",
    "addr:housenumber":"3",
    "addr:postcode":"18006",
    "addr:street":"Calle De Alminares Del Genil",
    "iso:country":"ES",
    "sg:address":"Calle de Alminares Del Genil, 3",
    "sg:city":"Granada",
    "sg:orig_category":"Gu\u00cdas Y Gu\u00cdas",
    "sg:phone":"+34 958 12 18 64",
    "sg:postcode":"18006",
    "sg:province":"Granada",
    "wof:name":"Rodriguez Rodriguez Felix Jesus",
    "wof:placetype":"venue"
},
  "geometry": {"coordinates":[-3.596010685,37.1667251587],"type":"Point"}
}