{
  "type": "Feature",
  "properties": {
    "addr:full":"Calle de Caracas, 11 Palmas De Gran Canaria Las Palmas 35010",
    "addr:housenumber":"11",
    "addr:postcode":"35010",
    "addr:street":"Calle De Caracas",
    "iso:country":"ES",
    "sg:address":"Calle de Caracas, 11",
    "sg:city":"Palmas De Gran Canaria",
    "sg:orig_category":"Sindicatos Y Colegios Profesionales",
    "sg:phone":"+34 928 22 44 65",
    "sg:postcode":"35010",
    "sg:province":"Las Palmas",
    "wof:name":"Asociacion Espa\u00d1ola De Tecnicos De Labor",
    "wof:placetype":"venue"
},
  "geometry": {"coordinates":[-15.440202713,28.128824234],"type":"Point"}
}