{
  "type": "Feature",
  "properties": {
    "iso:country":"ES",
    "sg:address":"Avda Alfonso El Sabio, 27",
    "sg:city":"Novelda",
    "sg:orig_category":"Quincaller\u00cda (al Por Menor)",
    "sg:phone":"+34 965 62 48 78",
    "sg:postcode":"03660",
    "sg:province":"Alicante",
    "wof:name":"Ferreteria Leopoldo S.l.",
    "wof:placetype":"venue"
},
  "geometry": {"coordinates":[-0.7738639712,38.3815841675],"type":"Point"}
}