{
  "type": "Feature",
  "properties": {
    "iso:country":"ES",
    "sg:address":"Outeiro-cruz, 55",
    "sg:city":"Outeiro-cruz",
    "sg:orig_category":"Cajas De Ahorro",
    "sg:phone":"+34 988 49 29 37",
    "sg:postcode":"32417",
    "sg:province":"Ourense",
    "wof:name":"Caixa De Aforros De Vigo Ourense E Pontevedra",
    "wof:placetype":"venue"
},
  "geometry": {"coordinates":[-8.1362161636,42.2448577881],"type":"Point"}
}