{
  "type": "Feature",
  "properties": {
    "addr:full":"Carrer de Ponent, 28 Castellbisbal Barcelona 08755",
    "addr:housenumber":"28",
    "addr:postcode":"08755",
    "addr:street":"Carrer De Ponent",
    "iso:country":"ES",
    "sg:address":"Carrer de Ponent, 28",
    "sg:city":"Castellbisbal",
    "sg:orig_category":"Construcciones Met\u00c1licas",
    "sg:phone":"+34 937 72 24 52",
    "sg:postcode":"08755",
    "sg:province":"Barcelona",
    "wof:name":"Balsells Escoda Rafael",
    "wof:placetype":"venue"
},
  "geometry": {"coordinates":[1.9797170162,41.4782104492],"type":"Point"}
}