{
  "type": "Feature",
  "properties": {
    "iso:country":"ES",
    "sg:address":"Rua Urzaiz, 172",
    "sg:city":"Vigo",
    "sg:orig_category":"Pescader\u00cdas (al Por Menor)",
    "sg:phone":"+34 986 28 11 19",
    "sg:postcode":"36205",
    "sg:province":"Pontevedra",
    "wof:name":"Solo Fresco S.l.",
    "wof:placetype":"venue"
},
  "geometry": {"coordinates":[-8.7032051086,42.2309417725],"type":"Point"}
}