{
  "type": "Feature",
  "properties": {
    "iso:country":"ES",
    "sg:address":"Calle de Wenceslao De La Cruz, 9",
    "sg:city":"Orcera",
    "sg:orig_category":"Imprenta",
    "sg:phone":"+34 953 48 00 02",
    "sg:postcode":"23370",
    "sg:province":"Ja\u00e9n",
    "wof:name":"Graficas Veracruz",
    "wof:placetype":"venue"
},
  "geometry": {"coordinates":[-2.6596610546,38.3179740906],"type":"Point"}
}