{
  "type": "Feature",
  "properties": {
    "addr:full":"Calle de Lepanto, 5 Irun Guip\u00f9zcoa 20301",
    "addr:housenumber":"5",
    "addr:postcode":"20301",
    "addr:street":"Calle De Lepanto;Guipu\u0300Zcoa",
    "iso:country":"ES",
    "sg:address":"Calle de Lepanto, 5",
    "sg:city":"Irun",
    "sg:orig_category":"Accesorios De Gr\u00daas Y Estibados",
    "sg:phone":"+34 943 61 28 57",
    "sg:postcode":"20301",
    "sg:province":"Guip\u00f9zcoa",
    "wof:name":"Gruas Bidasoa S.a.l.",
    "wof:placetype":"venue"
},
  "geometry": {"coordinates":[-1.8007810116,43.3428573608],"type":"Point"}
}