{
  "type": "Feature",
  "properties": {
    "iso:country":"ES",
    "sg:address":"Calle de Infante Don Fernando, 29",
    "sg:city":"Antequera",
    "sg:orig_category":"Loter\u00cda Y T\u00d3mbola",
    "sg:phone":"+34 952 84 20 78",
    "sg:postcode":"29200",
    "sg:province":"M\u00e1laga",
    "wof:name":"Mu\u00f1oz Martinez Antonio",
    "wof:placetype":"venue"
},
  "geometry": {"coordinates":[-4.5616512299,37.0181770325],"type":"Point"}
}