{
  "type": "Feature",
  "properties": {
    "addr:full":"Calle de Juan Bravo, 25 Segovia Segovia 40001",
    "addr:housenumber":"25",
    "addr:postcode":"40001",
    "addr:street":"Calle De Juan Bravo",
    "iso:country":"ES",
    "sg:address":"Calle de Juan Bravo, 25",
    "sg:city":"Segovia",
    "sg:orig_category":"Asociaciones Y Clubs Deportivos",
    "sg:phone":"+34 921 46 29 29",
    "sg:postcode":"40001",
    "sg:province":"Segovia",
    "wof:name":"Goal Sport S.l.",
    "wof:placetype":"venue"
},
  "geometry": {"coordinates":[-4.1210660934,40.9482154846],"type":"Point"}
}