{
  "type": "Feature",
  "properties": {
    "iso:country":"ES",
    "sg:address":"Calle de San Jose, 12",
    "sg:city":"Hoyo De Pinares",
    "sg:orig_category":"Estilistas Y Estudios De Estilo De Corte Y Confecci\u00d3n",
    "sg:phone":"+34 918 63 81 70",
    "sg:postcode":"05250",
    "sg:province":"\u00c1vila",
    "wof:name":"Garcia Galan Mariano",
    "wof:placetype":"venue"
},
  "geometry": {"coordinates":[-4.4239411354,40.5020751953],"type":"Point"}
}