{
  "type": "Feature",
  "properties": {
    "addr:full":"Calle de Pages Del Corro, 67 Sevilla Sevilla 41010",
    "addr:housenumber":"67",
    "addr:postcode":"41010",
    "addr:street":"Calle De Pages Del Corro",
    "iso:country":"ES",
    "sg:address":"Calle de Pages Del Corro, 67",
    "sg:city":"Sevilla",
    "sg:orig_category":"Laboratorios Y Trabajos De Fotograf\u00cda, V\u00cddeo Y Cine",
    "sg:phone":"+34 954 34 44 18",
    "sg:postcode":"41010",
    "sg:province":"Sevilla",
    "wof:name":"Prieto Jimenez Rosario",
    "wof:placetype":"venue"
},
  "geometry": {"coordinates":[-6.0047941208,37.3836174011],"type":"Point"}
}