{
  "type": "Feature",
  "properties": {
    "addr:full":"Calle de Palafox, S/n Puertollano Ciudad Real 13500",
    "addr:housenumber":"s / n",
    "addr:postcode":"13500",
    "addr:street":"Calle De Palafox",
    "iso:country":"ES",
    "sg:address":"Calle de Palafox, S/n",
    "sg:city":"Puertollano",
    "sg:orig_category":"Cl\u00cdnicas M\u00c9dicas",
    "sg:phone":"+34 926 44 14 78",
    "sg:postcode":"13500",
    "sg:province":"Ciudad Real",
    "wof:name":"Proyectos Medicos Sanitarios Integrales S.l.",
    "wof:placetype":"venue"
},
  "geometry": {"coordinates":[-4.0987138748,38.682258606],"type":"Point"}
}