{
  "type": "Feature",
  "properties": {
    "iso:country":"ES",
    "sg:address":"Pla\u00c7 Fossar, Es, 14",
    "sg:city":"Sineu",
    "sg:orig_category":"Agencias Y Agentes Comerciales, Representantes",
    "sg:phone":"+34 971 52 10 28",
    "sg:postcode":"07510",
    "sg:province":"Islas Baleares",
    "wof:name":"Germans Jorda C.b.",
    "wof:placetype":"venue"
},
  "geometry": {"coordinates":[3.0275802612,39.6434516907],"type":"Point"}
}