{
  "type": "Feature",
  "properties": {
    "addr:full":"Ctra Terrinches, S/n Albaladejo Ciudad Real 13340",
    "addr:housenumber":"s / n",
    "addr:postcode":"albaladejo;13340",
    "addr:street":"Ctra Terrinches",
    "iso:country":"ES",
    "sg:address":"Ctra Terrinches, S/n",
    "sg:city":"Albaladejo",
    "sg:orig_category":"Distribuci\u00d3n De Petr\u00d3leo Y Derivados",
    "sg:phone":"+34 926 38 74 14",
    "sg:postcode":"13340",
    "sg:province":"Ciudad Real",
    "wof:name":"Relucio Lopez Pedro",
    "wof:placetype":"venue"
},
  "geometry": {"coordinates":[-2.8066170216,38.6201667786],"type":"Point"}
}