{
  "type": "Feature",
  "properties": {
    "addr:full":"Calle de Sierra Nevada De Illora, 10 Illora Granada 18260",
    "addr:housenumber":"10",
    "addr:postcode":"18260",
    "addr:street":"Calle De Sierra Nevada De Illora",
    "iso:country":"ES",
    "sg:address":"Calle de Sierra Nevada De Illora, 10",
    "sg:city":"Illora",
    "sg:orig_category":"Institutos De Belleza",
    "sg:phone":"+34 958 46 33 04",
    "sg:postcode":"18260",
    "sg:province":"Granada",
    "wof:name":"Perez Jimenez Antonia",
    "wof:placetype":"venue"
},
  "geometry": {"coordinates":[-3.8782160282,37.2848968506],"type":"Point"}
}