{
  "type": "Feature",
  "properties": {
    "iso:country":"ES",
    "sg:address":"Carr Guernica, 13",
    "sg:city":"Cervera",
    "sg:orig_category":"Periodistas Profesionales",
    "sg:phone":"+34 973 53 17 37",
    "sg:postcode":"25200",
    "sg:province":"Lleida",
    "wof:name":"Boquet Estruch Jaume",
    "wof:placetype":"venue"
},
  "geometry": {"coordinates":[1.2714600563,41.6712989807],"type":"Point"}
}