{
  "type": "Feature",
  "properties": {
    "addr:full":"Calle de Calvario Bajo, S/n Monreal Campo Teruel 44300",
    "addr:housenumber":"s",
    "addr:postcode":"44300",
    "addr:street":"Calle De Calvario Bajo;/ N",
    "iso:country":"ES",
    "sg:address":"Calle de Calvario Bajo, S/n",
    "sg:city":"Monreal Campo",
    "sg:orig_category":"Barnizadores",
    "sg:phone":"+34 978 86 42 05",
    "sg:postcode":"44300",
    "sg:province":"Teruel",
    "wof:name":"Hermanos Rando S.c.",
    "wof:placetype":"venue"
},
  "geometry": {"coordinates":[-1.3547072411,40.7856788635],"type":"Point"}
}