{
  "type": "Feature",
  "properties": {
    "addr:full":"Calle de Silla Del Rey, 5 Oviedo Asturias 33013",
    "addr:housenumber":"5",
    "addr:postcode":"33013",
    "addr:street":"Calle De Silla Del Rey",
    "iso:country":"ES",
    "sg:address":"Calle de Silla Del Rey, 5",
    "sg:city":"Oviedo",
    "sg:orig_category":"Peluquer\u00cdas, Peluquer\u00cda Mixta",
    "sg:phone":"+34 985 27 02 46",
    "sg:postcode":"33013",
    "sg:province":"Asturias",
    "wof:name":"Garcia Cifuentes Maria Rogelia",
    "wof:placetype":"venue"
},
  "geometry": {"coordinates":[-5.862719059,43.3616294861],"type":"Point"}
}