{
  "type": "Feature",
  "properties": {
    "addr:full":"Carr Frederic Mompou, 6 Badalona Barcelona 08915",
    "addr:housenumber":"6",
    "addr:postcode":"08915",
    "addr:street":"Carr Frederic Mompou",
    "iso:country":"ES",
    "sg:address":"Carr Frederic Mompou, 6",
    "sg:city":"Badalona",
    "sg:orig_category":"Prot\u00c9sicos Dentales",
    "sg:phone":"+34 933 99 06 46",
    "sg:postcode":"08915",
    "sg:province":"Barcelona",
    "wof:name":"Urbano Gutierrez Rafael",
    "wof:placetype":"venue"
},
  "geometry": {"coordinates":[2.2399859428,41.4622993469],"type":"Point"}
}