{
  "type": "Feature",
  "properties": {
    "addr:full":"Carrer de Bernat De Bell.lloc, 3 Reus Tarragona 43203",
    "addr:housenumber":"3",
    "addr:postcode":"43203",
    "addr:street":"Carrer De Bernat De Bell.Lloc",
    "iso:country":"ES",
    "sg:address":"Carrer de Bernat De Bell.lloc, 3",
    "sg:city":"Reus",
    "sg:orig_category":"Carnicer\u00cdas, Carnicer\u00cdas",
    "sg:phone":"+34 977 31 70 37",
    "sg:postcode":"43203",
    "sg:province":"Tarragona",
    "wof:name":"Molina Gil Carlos",
    "wof:placetype":"venue"
},
  "geometry": {"coordinates":[1.1061689854,41.161605835],"type":"Point"}
}