{
  "type": "Feature",
  "properties": {
    "iso:country":"ES",
    "sg:address":"Carr Nuria, 14",
    "sg:city":"Centre Urba",
    "sg:orig_category":"Electricidad (montaje, Ensamblaje De Componentes)",
    "sg:phone":"+34 972 70 15 20",
    "sg:postcode":"17500",
    "sg:province":"Girona",
    "wof:name":"Puigvert Ricart Jaime",
    "wof:placetype":"venue"
},
  "geometry": {"coordinates":[2.1959049702,42.1965866089],"type":"Point"}
}