{
  "type": "Feature",
  "properties": {
    "addr:full":"Calle de Luis Bu\u00d1uel, 31 Elda Alicante 03600",
    "addr:housenumber":"31",
    "addr:postcode":"03600",
    "addr:street":"Calle De Luis Bun\u0303Uel",
    "iso:country":"ES",
    "sg:address":"Calle de Luis Bu\u00d1uel, 31",
    "sg:city":"Elda",
    "sg:orig_category":"Forja Y Embutici\u00d3n",
    "sg:phone":"+34 965 39 48 35",
    "sg:postcode":"03600",
    "sg:province":"Alicante",
    "wof:name":"Cerrajeria Casmi S.l.",
    "wof:placetype":"venue"
},
  "geometry": {"coordinates":[-0.7957379818,38.4806137085],"type":"Point"}
}