{
  "type": "Feature",
  "properties": {
    "addr:full":"Carrer de Roma Piera I Arcal, 4 Premia Mar Barcelona 08330",
    "addr:housenumber":"4",
    "addr:postcode":"08330",
    "addr:street":"Carrer De Roma;Arcal",
    "iso:country":"ES",
    "sg:address":"Carrer de Roma Piera I Arcal, 4",
    "sg:city":"Premia Mar",
    "sg:orig_category":"Electrodom\u00c9sticos (al Por Menor)",
    "sg:phone":"+34 937 51 26 98",
    "sg:postcode":"08330",
    "sg:province":"Barcelona",
    "wof:name":"Soldevila Martinez Manuel",
    "wof:placetype":"venue"
},
  "geometry": {"coordinates":[2.3600459099,41.4919776917],"type":"Point"}
}