{
  "type": "Feature",
  "properties": {
    "iso:country":"ES",
    "sg:address":"Pg Francesc Macia, 61",
    "sg:city":"S. Cugat Valles",
    "sg:orig_category":"Perfumer\u00cda (al Por Menor)",
    "sg:phone":"+34 935 89 82 64",
    "sg:postcode":"08173",
    "sg:province":"Barcelona",
    "wof:name":"Perfumerias Zarranz S.l.",
    "wof:placetype":"venue"
},
  "geometry": {"coordinates":[2.08334589,41.4778823853],"type":"Point"}
}