{
  "type": "Feature",
  "properties": {
    "iso:country":"ES",
    "sg:address":"Calle de San Nicolas, 13",
    "sg:city":"Malaga",
    "sg:orig_category":"Asesor\u00cda Fiscal Y Jur\u00cddica",
    "sg:phone":"+34 952 21 65 74",
    "sg:postcode":"29016",
    "sg:province":"M\u00e1laga",
    "wof:name":"Andres Reina Trinidad",
    "wof:placetype":"venue"
},
  "geometry": {"coordinates":[-4.411801815,36.7185440063],"type":"Point"}
}