{
  "type": "Feature",
  "properties": {
    "addr:full":"Calle de Diecinueve De Julio, S/n Bailen Ja\u00e9n 23710",
    "addr:housenumber":"s / n",
    "addr:postcode":"23710",
    "addr:street":"Calle De Diecinueve De Julio;Jae\u0301N",
    "iso:country":"ES",
    "sg:address":"Calle de Diecinueve De Julio, S/n",
    "sg:city":"Bailen",
    "sg:orig_category":"Iglesia Cat\u00d3lica",
    "sg:phone":"+34 953 67 14 03",
    "sg:postcode":"23710",
    "sg:province":"Ja\u00e9n",
    "wof:name":"Parroquia San Jose Obrero",
    "wof:placetype":"venue"
},
  "geometry": {"coordinates":[-3.7762355804,38.0992393494],"type":"Point"}
}