{
  "type": "Feature",
  "properties": {
    "iso:country":"ES",
    "sg:address":"Calle de Magdalena La, 1",
    "sg:city":"Grado",
    "sg:orig_category":"Abogados",
    "sg:phone":"+34 985 75 34 86",
    "sg:postcode":"33820",
    "sg:province":"Asturias",
    "wof:name":"Ocejo Alvarez Elena",
    "wof:placetype":"venue"
},
  "geometry": {"coordinates":[-6.0704259872,43.3890151978],"type":"Point"}
}