{
  "type": "Feature",
  "properties": {
    "addr:full":"Pl Major, 11 Montblanc Tarragona 43400",
    "addr:housenumber":"11",
    "addr:postcode":"43400",
    "addr:street":"Pl Major",
    "iso:country":"ES",
    "sg:address":"Pl Major, 11",
    "sg:city":"Montblanc",
    "sg:orig_category":"Cajas De Ahorro",
    "sg:phone":"+34 977 86 29 05",
    "sg:postcode":"43400",
    "sg:province":"Tarragona",
    "wof:name":"Caixa D'estalvis De Tarragona",
    "wof:placetype":"venue"
},
  "geometry": {"coordinates":[1.1613830328,41.3764381409],"type":"Point"}
}