{
  "type": "Feature",
  "properties": {
    "addr:full":"Carr Ample, 32 Blanes Girona 17300",
    "addr:housenumber":"32",
    "addr:postcode":"17300",
    "addr:street":"Carr Ample",
    "iso:country":"ES",
    "sg:address":"Carr Ample, 32",
    "sg:city":"Blanes",
    "sg:orig_category":"Relojer\u00cda (al Por Menor, Reparaci\u00d3n)",
    "sg:phone":"+34 972 33 26 81",
    "sg:postcode":"17300",
    "sg:province":"Girona",
    "sg:website":"www.swatch.com",
    "wof:name":"Grau Lloret S.l.",
    "wof:placetype":"venue"
},
  "geometry": {"coordinates":[2.7913429737,41.6753425598],"type":"Point"}
}