{
  "type": "Feature",
  "properties": {
    "addr:full":"Julian Gayarre, 1 Iru\u00f1a Navarra 31005",
    "addr:housenumber":"1",
    "addr:postcode":"31005",
    "addr:street":"Julian Gayarre",
    "iso:country":"ES",
    "sg:address":"Julian Gayarre, 1",
    "sg:city":"Iru\u00f1a",
    "sg:orig_category":"Televisi\u00d3n, V\u00cddeo: Aparatos Y Accesorios (venta)",
    "sg:phone":"+34 948 24 19 50",
    "sg:postcode":"31005",
    "sg:province":"Navarra",
    "wof:name":"Lohe Servicios Tecnicos S.l.",
    "wof:placetype":"venue"
},
  "geometry": {"coordinates":[-1.6398069859,42.8058357239],"type":"Point"}
}