{
  "type": "Feature",
  "properties": {
    "iso:country":"ES",
    "sg:address":"Pase Profesor Tierno Galvan, 27",
    "sg:city":"Carlota",
    "sg:orig_category":"Alquiler De V\u00cddeo",
    "sg:phone":"+34 957 30 20 49",
    "sg:postcode":"14100",
    "sg:province":"C\u00f3rdoba",
    "wof:name":"Ortiz Villamor Francisco Javier",
    "wof:placetype":"venue"
},
  "geometry": {"coordinates":[-4.9374890327,37.6685142517],"type":"Point"}
}