{
  "type": "Feature",
  "properties": {
    "addr:full":"Carrer de Escipio, 6 Barcelona Barcelona 08023",
    "addr:housenumber":"6",
    "addr:postcode":"08023",
    "addr:street":"Carrer De Escipio",
    "iso:country":"ES",
    "sg:address":"Carrer de Escipio, 6",
    "sg:city":"Barcelona",
    "sg:orig_category":"Carnicer\u00cdas, Carnicer\u00cdas",
    "sg:phone":"+34 932 12 66 55",
    "sg:postcode":"08023",
    "sg:province":"Barcelona",
    "wof:name":"Montmant Villalonga Juan",
    "wof:placetype":"venue"
},
  "geometry": {"coordinates":[2.1466319561,41.4082832336],"type":"Point"}
}