{
  "type": "Feature",
  "properties": {
    "addr:full":"Calle de Barredo, 2 San Juan De La Mata Le\u00f3n 24545",
    "addr:housenumber":"2",
    "addr:postcode":"24545",
    "addr:street":"Calle De Barredo;Juan",
    "iso:country":"ES",
    "sg:address":"Calle de Barredo, 2",
    "sg:city":"San Juan De La Mata",
    "sg:orig_category":"Negocio De Madera",
    "sg:phone":"+34 987 56 31 18",
    "sg:postcode":"24545",
    "sg:province":"Le\u00f3n",
    "wof:name":"Santalla Carro Felix",
    "wof:placetype":"venue"
},
  "geometry": {"coordinates":[-6.6657700539,42.6461868286],"type":"Point"}
}