{
  "type": "Feature",
  "properties": {
    "iso:country":"ES",
    "sg:address":"Calle de Akilino Arriola, 59",
    "sg:city":"Moreaga",
    "sg:orig_category":"T\u00c9cnicos Veterinarios",
    "sg:phone":"+34 946 76 28 02",
    "sg:postcode":"48600",
    "sg:province":"Vizcaya",
    "wof:name":"Lopez Fernandez Roberto",
    "wof:placetype":"venue"
},
  "geometry": {"coordinates":[-2.9881563187,43.3784866333],"type":"Point"}
}