{
  "type": "Feature",
  "properties": {
    "addr:full":"Calle de San Enrique De Osso, 32 Madrid Madrid 28050",
    "addr:housenumber":"32",
    "addr:postcode":"madrid;28050",
    "addr:street":"Calle De San Enrique De Osso",
    "iso:country":"ES",
    "sg:address":"Calle de San Enrique De Osso, 32",
    "sg:city":"Madrid",
    "sg:orig_category":"Agencias Y Asesores De Publicidad",
    "sg:phone":"+34 916 25 21 84",
    "sg:postcode":"28050",
    "sg:province":"Madrid",
    "wof:name":"Promociones Siguero S.a.",
    "wof:placetype":"venue"
},
  "geometry": {"coordinates":[-3.6426138878,40.5050888062],"type":"Point"}
}