{
  "type": "Feature",
  "properties": {
    "addr:full":"Carrer de Sants, 277 Barcelona Barcelona 08028",
    "addr:housenumber":"277",
    "addr:postcode":"08028",
    "addr:street":"Carrer De Sants",
    "iso:country":"ES",
    "sg:address":"Carrer de Sants, 277",
    "sg:city":"Barcelona",
    "sg:orig_category":"Carnicer\u00cdas, Carnicer\u00cdas",
    "sg:phone":"+34 934 31 85 12",
    "sg:postcode":"08028",
    "sg:province":"Barcelona",
    "wof:name":"Gracia Monzon Joaquin",
    "wof:placetype":"venue"
},
  "geometry": {"coordinates":[2.1296389103,41.3754882812],"type":"Point"}
}