{
  "type": "Feature",
  "properties": {
    "iso:country":"ES",
    "sg:address":"Rua Antonio Puga, 20",
    "sg:city":"Ourense",
    "sg:orig_category":"Venta, Instalaci\u00d3n De Calefacci\u00d3n",
    "sg:phone":"+34 988 36 63 33",
    "sg:postcode":"32002",
    "sg:province":"Ourense",
    "wof:name":"Nortermica S.a.",
    "wof:placetype":"venue"
},
  "geometry": {"coordinates":[-7.8689517975,42.3408126831],"type":"Point"}
}