{
  "type": "Feature",
  "properties": {
    "addr:full":"Calle de Felipe Hernandez, 5 Utiel Valencia 46300",
    "addr:housenumber":"5",
    "addr:postcode":"46300",
    "addr:street":"Calle De Felipe Hernandez",
    "iso:country":"ES",
    "sg:address":"Calle de Felipe Hernandez, 5",
    "sg:city":"Utiel",
    "sg:orig_category":"Plomeros",
    "sg:phone":"+34 962 17 07 69",
    "sg:postcode":"46300",
    "sg:province":"Valencia",
    "wof:name":"Moya Cano Miguel Gregorio",
    "wof:placetype":"venue"
},
  "geometry": {"coordinates":[-1.2031060457,39.5693473816],"type":"Point"}
}