{
  "type": "Feature",
  "properties": {
    "addr:full":"Calle de Egidazu Kaia, 7 Ondarroa Vizcaya 48700",
    "addr:housenumber":"7",
    "addr:postcode":"48700",
    "addr:street":"Calle De Egidazu Kaia",
    "iso:country":"ES",
    "sg:address":"Calle de Egidazu Kaia, 7",
    "sg:city":"Ondarroa",
    "sg:orig_category":"Distribuci\u00d3n De Petr\u00d3leo Y Derivados",
    "sg:phone":"+34 946 83 00 89",
    "sg:postcode":"48700",
    "sg:province":"Vizcaya",
    "wof:name":"Urlapesca, S.a.",
    "wof:placetype":"venue"
},
  "geometry": {"coordinates":[-2.4228200912,43.3255386353],"type":"Point"}
}