{
  "type": "Feature",
  "properties": {
    "addr:full":"Calle de Periodista Eduardo Molina Fajardo, 6 Granada Granada 18015",
    "addr:housenumber":"6",
    "addr:postcode":"18015",
    "addr:street":"Calle De Periodista Eduardo Molina Fajardo",
    "iso:country":"ES",
    "sg:address":"Calle de Periodista Eduardo Molina Fajardo, 6",
    "sg:city":"Granada",
    "sg:orig_category":"Agencias Y Agentes Comerciales, Representantes",
    "sg:phone":"+34 958 16 15 30",
    "sg:postcode":"18015",
    "sg:province":"Granada",
    "wof:name":"Contreras Mu\u00f1oz Juan Jose",
    "wof:placetype":"venue"
},
  "geometry": {"coordinates":[-3.6302540302,37.197429657],"type":"Point"}
}