{
  "type": "Feature",
  "properties": {
    "iso:country":"ES",
    "sg:address":"Avda Ramon Valdes, 14",
    "sg:city":"Navia",
    "sg:orig_category":"Lencer\u00cda Femenina, Corseter\u00cda, Trajes De Ba\u00d1o (al Por Menor)",
    "sg:phone":"+34 985 63 09 22",
    "sg:postcode":"33710",
    "sg:province":"Asturias",
    "wof:name":"Alvarez Rodriguez Maria Belen",
    "wof:placetype":"venue"
},
  "geometry": {"coordinates":[-6.7240166664,43.5408592224],"type":"Point"}
}