{
  "type": "Feature",
  "properties": {
    "iso:country":"ES",
    "sg:address":"Calle de Santa Maria, 11",
    "sg:city":"Malaga",
    "sg:orig_category":"Arquitectos",
    "sg:phone":"+34 952 22 07 61",
    "sg:postcode":"29015",
    "sg:province":"M\u00e1laga",
    "wof:name":"Tudela Von Schmiterlow Augusto",
    "wof:placetype":"venue"
},
  "geometry": {"coordinates":[-4.4209008217,36.7211837769],"type":"Point"}
}