{
  "type": "Feature",
  "properties": {
    "iso:country":"ES",
    "sg:address":"Plaz Huerta Herrera, 1",
    "sg:city":"Cuellar",
    "sg:orig_category":"Asesor\u00cdas Y Estudios Financieros",
    "sg:phone":"+34 921 14 25 31",
    "sg:postcode":"40200",
    "sg:province":"Segovia",
    "wof:name":"Sanz Alvarez Juan Jose",
    "wof:placetype":"venue"
},
  "geometry": {"coordinates":[-4.3132138252,41.399105072],"type":"Point"}
}