{
  "type": "Feature",
  "properties": {
    "iso:country":"ES",
    "sg:address":"Avda De Alemania, 1",
    "sg:city":"Castalla",
    "sg:orig_category":"Poli\u00c9ster",
    "sg:phone":"+34 965 56 14 19",
    "sg:postcode":"03420",
    "sg:province":"Alicante",
    "wof:name":"Poliuresan S.l.",
    "wof:placetype":"venue"
},
  "geometry": {"coordinates":[-0.6720280051,38.6039924622],"type":"Point"}
}