{
  "type": "Feature",
  "properties": {
    "addr:full":"Lg Codeso(codeso), S/n Ardesende La Coru\u00f1a 15881",
    "addr:housenumber":"s / n",
    "addr:postcode":"15881",
    "addr:street":"La Corun\u0303A",
    "iso:country":"ES",
    "sg:address":"Lg Codeso(codeso), S/n",
    "sg:city":"Ardesende",
    "sg:orig_category":"Empresarios",
    "sg:phone":"+34 981 51 21 51",
    "sg:postcode":"15881",
    "sg:province":"La Coru\u00f1a",
    "wof:name":"Fundacion San Rosendo",
    "wof:placetype":"venue"
},
  "geometry": {"coordinates":[-8.4128170013,42.8135566711],"type":"Point"}
}