{
  "type": "Feature",
  "properties": {
    "iso:country":"ES",
    "sg:address":"Jose Maria Gironella, 15",
    "sg:city":"Marbella",
    "sg:orig_category":"Muebles Y Accesorios Para Cocinas Y Cuartos De Ba\u00d1o (al Por Menor)",
    "sg:phone":"+34 952 90 15 01",
    "sg:postcode":"29600",
    "sg:province":"M\u00e1laga",
    "wof:name":"Abad Romero Juan Manuel",
    "wof:placetype":"venue"
},
  "geometry": {"coordinates":[-4.894011,36.514736],"type":"Point"}
}