{
  "type": "Feature",
  "properties": {
    "addr:full":"Calle de Magallanes, 21 Salamanca Salamanca 37004",
    "addr:housenumber":"21",
    "addr:postcode":"37004",
    "addr:street":"Calle De Magallanes",
    "iso:country":"ES",
    "sg:address":"Calle de Magallanes, 21",
    "sg:city":"Salamanca",
    "sg:orig_category":"Peluquer\u00cdas, Peluquer\u00cda Mixta",
    "sg:phone":"+34 923 23 20 55",
    "sg:postcode":"37004",
    "sg:province":"Salamanca",
    "wof:name":"Fernandez Hernandez Maria Luz",
    "wof:placetype":"venue"
},
  "geometry": {"coordinates":[-5.6494631767,40.972366333],"type":"Point"}
}