{
  "type": "Feature",
  "properties": {
    "iso:country":"ES",
    "sg:address":"Plaz Iglesia (la), S/n",
    "sg:city":"Traiguera",
    "sg:orig_category":"Iglesia Cat\u00d3lica",
    "sg:phone":"+34 964 49 50 04",
    "sg:postcode":"12330",
    "sg:province":"Castell\u00f3n",
    "wof:name":"Bisbat De Tortosa",
    "wof:placetype":"venue"
},
  "geometry": {"coordinates":[0.2892799973,40.5237693787],"type":"Point"}
}