{
  "type": "Feature",
  "properties": {
    "iso:country":"ES",
    "sg:address":"Carrer de Migdia, 61",
    "sg:city":"Corro D'avall",
    "sg:orig_category":"Electrodom\u00c9sticos (al Por Menor)",
    "sg:phone":"+34 938 46 47 01",
    "sg:postcode":"08520",
    "sg:province":"Barcelona",
    "wof:name":"Lopez Casta\u00f1o Elena",
    "wof:placetype":"venue"
},
  "geometry": {"coordinates":[2.2946157455,41.624584198],"type":"Point"}
}