{
  "type": "Feature",
  "properties": {
    "iso:country":"ES",
    "sg:address":"Avda Andalucia (de), 41",
    "sg:city":"Valdemoro",
    "sg:orig_category":"Tapiceros Y Tapiceros",
    "sg:phone":"+34 918 09 57 98",
    "sg:postcode":"28340",
    "sg:province":"Madrid",
    "wof:name":"Menna Medina Jose Vicente",
    "wof:placetype":"venue"
},
  "geometry": {"coordinates":[-3.6751680374,40.1936187744],"type":"Point"}
}