{
  "type": "Feature",
  "properties": {
    "addr:full":"Carr Pintor Sorolla, 42 Moncada Valencia 46113",
    "addr:housenumber":"42",
    "addr:postcode":"46113",
    "addr:street":"Carr Pintor Sorolla",
    "iso:country":"ES",
    "sg:address":"Carr Pintor Sorolla, 42",
    "sg:city":"Moncada",
    "sg:orig_category":"Promotores Constructores",
    "sg:phone":"+34 961 30 33 24",
    "sg:postcode":"46113",
    "sg:province":"Valencia",
    "wof:name":"Ripoll Ivars S.l.",
    "wof:placetype":"venue"
},
  "geometry": {"coordinates":[-0.3899160028,39.5444297791],"type":"Point"}
}