{
  "type": "Feature",
  "properties": {
    "iso:country":"ES",
    "sg:address":"Calle de Horno, 8",
    "sg:city":"Maracena",
    "sg:orig_category":"Materias Pl\u00c1sticas: Productos De Consumo Masivo (fabricaci\u00d3n, Al Por Mayor)",
    "sg:phone":"+34 958 40 41 19",
    "sg:postcode":"18200",
    "sg:province":"Granada",
    "wof:name":"Plasticos Genil S.l.",
    "wof:placetype":"venue"
},
  "geometry": {"coordinates":[-3.6345489025,37.2068481445],"type":"Point"}
}