{
  "type": "Feature",
  "properties": {
    "addr:full":"Av Catalunya, 6 Ivars D'urgell Lleida 25260",
    "addr:housenumber":"6",
    "addr:postcode":"25260",
    "addr:street":"Av Catalunya",
    "iso:country":"ES",
    "sg:address":"Av Catalunya, 6",
    "sg:city":"Ivars D'urgell",
    "sg:orig_category":"Venta, Instalaci\u00d3n De Cocinas",
    "sg:phone":"+34 973 58 00 09",
    "sg:postcode":"25260",
    "sg:province":"Lleida",
    "wof:name":"Ricart Llanes Modesto",
    "wof:placetype":"venue"
},
  "geometry": {"coordinates":[0.6213930249,41.6112174988],"type":"Point"}
}