{
  "type": "Feature",
  "properties": {
    "iso:country":"ES",
    "sg:address":"Avda Mediterraneo, 28",
    "sg:city":"Salobre\u00f1a",
    "sg:orig_category":"Alquiler De V\u00cddeo",
    "sg:phone":"+34 958 61 24 84",
    "sg:postcode":"18680",
    "sg:province":"Granada",
    "wof:name":"Marquez Jeronimo Luis Carlos",
    "wof:placetype":"venue"
},
  "geometry": {"coordinates":[-3.5846910477,36.7404251099],"type":"Point"}
}