{
  "type": "Feature",
  "properties": {
    "addr:full":"Ctra. Salamanca, 1 Pinofranqueado C\u00e1ceres 10630",
    "addr:housenumber":"1",
    "addr:postcode":"10630",
    "addr:street":"Ctra. Salamanca;Ca\u0301Ceres",
    "iso:country":"ES",
    "sg:address":"Ctra. Salamanca, 1",
    "sg:city":"Pinofranqueado",
    "sg:orig_category":"Mec\u00c1nico Del Autom\u00d3vil",
    "sg:phone":"+34 927 67 43 42",
    "sg:postcode":"10630",
    "sg:province":"C\u00e1ceres",
    "wof:name":"Benito Encinas Benedicto",
    "wof:placetype":"venue"
},
  "geometry": {"coordinates":[-6.2804641724,40.3323440552],"type":"Point"}
}