{
  "type": "Feature",
  "properties": {
    "addr:full":"Carrer de Valles, 4 S. Cugat Valles Barcelona 08172",
    "addr:housenumber":"4",
    "addr:postcode":"08172",
    "addr:street":"Carrer De Valles;Barcelona",
    "iso:country":"ES",
    "sg:address":"Carrer de Valles, 4",
    "sg:city":"S. Cugat Valles",
    "sg:orig_category":"Asociaciones, Organismos Culturales Y Socioeducativos",
    "sg:phone":"+34 935 89 70 03",
    "sg:postcode":"08172",
    "sg:province":"Barcelona",
    "wof:name":"Centro Castellano Manchego",
    "wof:placetype":"venue"
},
  "geometry": {"coordinates":[2.0870189667,41.472858429],"type":"Point"}
}