{
  "type": "Feature",
  "properties": {
    "addr:full":"Calle de Seguidillas (las), 20 Uga Las Palmas 35570",
    "addr:housenumber":"20",
    "addr:postcode":"35570",
    "addr:street":"Calle De Seguidillas Las",
    "iso:country":"ES",
    "sg:address":"Calle de Seguidillas (las), 20",
    "sg:city":"Uga",
    "sg:orig_category":"Grafistas",
    "sg:phone":"+34 928 83 01 95",
    "sg:postcode":"35570",
    "sg:province":"Las Palmas",
    "wof:name":"Zona Visual S.l.",
    "wof:placetype":"venue"
},
  "geometry": {"coordinates":[-13.7659454346,28.9523696899],"type":"Point"}
}