{
  "type": "Feature",
  "properties": {
    "iso:country":"ES",
    "sg:address":"Calle de Canovas Del Castillo, 2",
    "sg:city":"Totana",
    "sg:orig_category":"Fabricaci\u00d3n De Sobres, Bolsas Y Fundas",
    "sg:phone":"+34 968 42 52 89",
    "sg:postcode":"30850",
    "sg:province":"Murcia",
    "wof:name":"Mu\u00f1oz Belmonte Ana",
    "wof:placetype":"venue"
},
  "geometry": {"coordinates":[-1.5018255711,37.7688560486],"type":"Point"}
}