{
  "type": "Feature",
  "properties": {
    "iso:country":"ES",
    "sg:address":"Calle de Teruel, 2",
    "sg:city":"Cuenca",
    "sg:orig_category":"Promotores Constructores",
    "sg:phone":"+34 969 23 11 99",
    "sg:postcode":"16004",
    "sg:province":"Cuenca",
    "wof:name":"Martinez Fernandez Toribio",
    "wof:placetype":"venue"
},
  "geometry": {"coordinates":[-2.1351130009,40.0683708191],"type":"Point"}
}