{
  "type": "Feature",
  "properties": {
    "iso:country":"ES",
    "sg:address":"Calle de Andres Vazquez, 2",
    "sg:city":"Candas",
    "sg:orig_category":"Ense\u00d1anza: Profesiones Art\u00cdsticas",
    "sg:phone":"+34 985 87 29 80",
    "sg:postcode":"33430",
    "sg:province":"Asturias",
    "sg:website":"www.av-tec.net",
    "wof:name":"Fernandez Garcia Alberto",
    "wof:placetype":"venue"
},
  "geometry": {"coordinates":[-5.7685623169,43.5888519287],"type":"Point"}
}