{
  "type": "Feature",
  "properties": {
    "iso:country":"ES",
    "sg:address":"Rua Rans, 41",
    "sg:city":"Playa America",
    "sg:orig_category":"Pescader\u00cdas (al Por Menor)",
    "sg:phone":"+34 986 35 48 19",
    "sg:postcode":"36379",
    "sg:province":"Pontevedra",
    "wof:name":"Iglesias De Sa Marina",
    "wof:placetype":"venue"
},
  "geometry": {"coordinates":[-8.8124990463,42.1194648743],"type":"Point"}
}