{
  "type": "Feature",
  "properties": {
    "addr:full":"Plaz Espa\u00d1a, 1 Friol Lugo 27220",
    "addr:housenumber":"1",
    "addr:postcode":"27220",
    "addr:street":"Plaz Espan\u0303A",
    "iso:country":"ES",
    "sg:address":"Plaz Espa\u00d1a, 1",
    "sg:city":"Friol",
    "sg:orig_category":"Centros De Educaci\u00d3n Especial",
    "sg:phone":"+34 982 37 50 81",
    "sg:postcode":"27220",
    "sg:province":"Lugo",
    "wof:name":"Colexio Publico Doctor Lopez Suarez",
    "wof:placetype":"venue"
},
  "geometry": {"coordinates":[-7.7911257744,43.0295600891],"type":"Point"}
}