{
  "type": "Feature",
  "properties": {
    "addr:full":"Calle de Jorge Juan, 16 Madrid Madrid 28001",
    "addr:housenumber":"16",
    "addr:postcode":"madrid;28001",
    "addr:street":"Calle De Jorge Juan",
    "iso:country":"ES",
    "sg:address":"Calle de Jorge Juan, 16",
    "sg:city":"Madrid",
    "sg:orig_category":"Agencias Y Agentes Comerciales, Representantes",
    "sg:phone":"+34 914 26 04 77",
    "sg:postcode":"28001",
    "sg:province":"Madrid",
    "wof:name":"Tous Aguilo Bartolome",
    "wof:placetype":"venue"
},
  "geometry": {"coordinates":[-3.6856639385,40.4238319397],"type":"Point"}
}