{
  "type": "Feature",
  "properties": {
    "addr:full":"Calle de Castillo De Simancas, 20 Madrid Madrid 28037",
    "addr:housenumber":"20",
    "addr:postcode":"madrid;28037",
    "addr:street":"Calle De Castillo De Simancas",
    "iso:country":"ES",
    "sg:address":"Calle de Castillo De Simancas, 20",
    "sg:city":"Madrid",
    "sg:classifiers":[
        {
            "category":"Personal",
            "subcategory":"Barber",
            "type":"Services"
        }
    ],
    "sg:phone":"+34 913 04 51 23",
    "sg:postcode":"28037",
    "sg:province":"Madrid",
    "sg:tags":[
        "caballeros",
        "de",
        "peluqueros"
    ],
    "wof:name":"Gomez Mu\u00f1oz Comunidad De Bienes",
    "wof:placetype":"venue"
},
  "geometry": {"coordinates":[-3.6268949509,40.4293632507],"type":"Point"}
}