{
  "type": "Feature",
  "properties": {
    "iso:country":"ES",
    "sg:address":"Calle de Aurora, 1",
    "sg:city":"San Miguel",
    "sg:orig_category":"Fabricaci\u00d3n, Comercio De Muebles Para Ni\u00d1os",
    "sg:phone":"+34 968 20 05 80",
    "sg:postcode":"30001",
    "sg:province":"Murcia",
    "wof:name":"Santos Brandys Veronica",
    "wof:placetype":"venue"
},
  "geometry": {"coordinates":[-1.1312760115,37.9880752563],"type":"Point"}
}