{
  "type": "Feature",
  "properties": {
    "iso:country":"ES",
    "sg:address":"Avda Iparraguirre(ed Cantabrico), 59",
    "sg:city":"Santurtzi",
    "sg:orig_category":"Aceros Inoxidables",
    "sg:phone":"+34 944 93 70 24",
    "sg:postcode":"48980",
    "sg:province":"Vizcaya",
    "wof:name":"Outokumpu S.a.",
    "wof:placetype":"venue"
},
  "geometry": {"coordinates":[-3.0402920246,43.3344573975],"type":"Point"}
}