{
  "type": "Feature",
  "properties": {
    "addr:full":"Avda Aragon De, 30 Fraga Huesca 22520",
    "addr:housenumber":"30",
    "addr:postcode":"22520",
    "addr:street":"Avda Aragon De",
    "iso:country":"ES",
    "sg:address":"Avda Aragon De, 30",
    "sg:city":"Fraga",
    "sg:orig_category":"Institutos De Belleza",
    "sg:phone":"+34 974 47 34 53",
    "sg:postcode":"22520",
    "sg:province":"Huesca",
    "wof:name":"Orus Surroca Virginia",
    "wof:placetype":"venue"
},
  "geometry": {"coordinates":[0.3416459858,41.521812439],"type":"Point"}
}