{
  "type": "Feature",
  "properties": {
    "iso:country":"ES",
    "sg:address":"Calle de Italia, 9",
    "sg:city":"Fregenal Sierra",
    "sg:orig_category":"Electrodom\u00c9sticos (al Por Menor)",
    "sg:phone":"+34 924 72 01 94",
    "sg:postcode":"06340",
    "sg:province":"Badajoz",
    "sg:website":"www.masterbautista.com",
    "wof:name":"Manuel Bautista Morales S.l.",
    "wof:placetype":"venue"
},
  "geometry": {"coordinates":[-6.6505317688,38.1659088135],"type":"Point"}
}