{
  "type": "Feature",
  "properties": {
    "addr:full":"Avda Marques De Corbera, 39 Madrid Madrid 28017",
    "addr:housenumber":"39",
    "addr:postcode":"madrid;28017",
    "addr:street":"Avda Marques De Corbera",
    "iso:country":"ES",
    "sg:address":"Avda Marques De Corbera, 39",
    "sg:city":"Madrid",
    "sg:orig_category":"Bisuter\u00cda, Joyer\u00cda, Relojer\u00cda (al Por Menor)",
    "sg:phone":"+34 913 55 61 41",
    "sg:postcode":"28017",
    "sg:province":"Madrid",
    "wof:name":"Gomez Huerta Edelmira",
    "wof:placetype":"venue"
},
  "geometry": {"coordinates":[-3.6528589725,40.4252967834],"type":"Point"}
}