{
  "type": "Feature",
  "properties": {
    "addr:full":"Calle de Mayor, 31 Riba-roja Turia Valencia 46190",
    "addr:housenumber":"31",
    "addr:postcode":"46190",
    "addr:street":"Calle De Mayor",
    "iso:country":"ES",
    "sg:address":"Calle de Mayor, 31",
    "sg:city":"Riba-roja Turia",
    "sg:orig_category":"Asesor\u00cda Fiscal Y Jur\u00cddica",
    "sg:phone":"+34 962 77 03 58",
    "sg:postcode":"46190",
    "sg:province":"Valencia",
    "wof:name":"Maria Asuncion Alonso Sanchis-maria Dolores Alonso Sanchis Cdad",
    "wof:placetype":"venue"
},
  "geometry": {"coordinates":[-0.5698940158,39.5458450317],"type":"Point"}
}