{
  "type": "Feature",
  "properties": {
    "iso:country":"ES",
    "sg:address":"Calle de Conde Cabarrus, 55",
    "sg:city":"Salamanca",
    "sg:orig_category":"Centros P\u00dablicos De Formaci\u00d3n Profesional Y T\u00c9cnica",
    "sg:phone":"+34 923 25 16 56",
    "sg:postcode":"37005",
    "sg:province":"Salamanca",
    "wof:name":"Colegio Oficial De Ingenieros Tecnicos Agricolas Y Peritos Agricolas De Castilla La Vieja",
    "wof:placetype":"venue"
},
  "geometry": {"coordinates":[-5.6603055,40.9756851196],"type":"Point"}
}