{
  "type": "Feature",
  "properties": {
    "addr:full":"Avda Guadalquivir, S/n Dos Hermanas Sevilla 41700",
    "addr:postcode":"41700",
    "addr:street":"Avda Guadalquivir S / N Dos",
    "iso:country":"ES",
    "sg:address":"Avda Guadalquivir, S/n",
    "sg:city":"Dos Hermanas",
    "sg:orig_category":"Plomeros",
    "sg:phone":"+34 955 66 87 68",
    "sg:postcode":"41700",
    "sg:province":"Sevilla",
    "wof:name":"Camacho Palacin Ricardo",
    "wof:placetype":"venue"
},
  "geometry": {"coordinates":[-5.9170298576,37.2875556946],"type":"Point"}
}