{
  "type": "Feature",
  "properties": {
    "addr:full":"Calle de Julian Romea, 11 Cieza Murcia 30530",
    "addr:housenumber":"11",
    "addr:postcode":"30530",
    "addr:street":"Calle De Julian Romea",
    "iso:country":"ES",
    "sg:address":"Calle de Julian Romea, 11",
    "sg:city":"Cieza",
    "sg:orig_category":"Agencias Y Agentes Comerciales, Representantes",
    "sg:phone":"+34 968 76 05 14",
    "sg:postcode":"30530",
    "sg:province":"Murcia",
    "wof:name":"Gonzalez Lopez Alfonso",
    "wof:placetype":"venue"
},
  "geometry": {"coordinates":[-1.4250290394,38.2414169312],"type":"Point"}
}