{
  "type": "Feature",
  "properties": {
    "iso:country":"ES",
    "sg:address":"Plaz Pablo Picasso, 9",
    "sg:city":"Valencia",
    "sg:orig_category":"M\u00c9dicos: Otorrinolaringolog\u00cda",
    "sg:phone":"+34 963 46 81 81",
    "sg:postcode":"46015",
    "sg:province":"Valencia",
    "wof:name":"Leon Garcia Maria Dolores",
    "wof:placetype":"venue"
},
  "geometry": {"coordinates":[-0.3987950087,39.4771194458],"type":"Point"}
}