{
  "type": "Feature",
  "properties": {
    "iso:country":"ES",
    "sg:address":"Rua Carcere Vella, 5",
    "sg:city":"Vigo",
    "sg:orig_category":"Fabricaci\u00d3n, Importaci\u00d3n De Material Y Sistemas De Telecomunicaciones",
    "sg:phone":"+34 986 43 12 40",
    "sg:postcode":"36202",
    "sg:province":"Pontevedra",
    "sg:website":"www.irisana.com",
    "wof:name":"Irisana S. A.",
    "wof:placetype":"venue"
},
  "geometry": {"coordinates":[-8.7260513306,42.2395133972],"type":"Point"}
}