{
  "type": "Feature",
  "properties": {
    "addr:full":"Ctra Cabra, S/n Lucena C\u00f3rdoba 14900",
    "addr:postcode":"14900",
    "addr:street":"Ctra Cabra S / N",
    "iso:country":"ES",
    "sg:address":"Ctra Cabra, S/n",
    "sg:city":"Lucena",
    "sg:orig_category":"Adaptaciones, Acondicionamientos Especiales Para Veh\u00cdculos, Veh\u00cdculos Industriales",
    "sg:phone":"+34 957 51 32 36",
    "sg:postcode":"14900",
    "sg:province":"C\u00f3rdoba",
    "wof:name":"Talleres Hermanos Olea S.l.",
    "wof:placetype":"venue"
},
  "geometry": {"coordinates":[-4.4833388329,37.42137146],"type":"Point"}
}