{
  "type": "Feature",
  "properties": {
    "addr:full":"Calle de Nuestra Se\u00d1ora De La Macarena, 1 Leganes Madrid 28911",
    "addr:housenumber":"1",
    "addr:postcode":"28911",
    "addr:street":"Calle De Nuestra Sen\u0303Ora De La Macarena",
    "iso:country":"ES",
    "sg:address":"Calle de Nuestra Se\u00d1ora De La Macarena, 1",
    "sg:city":"Leganes",
    "sg:orig_category":"Detectives, Agentes Investigadores Privados",
    "sg:phone":"+34 916 94 75 01",
    "sg:postcode":"28911",
    "sg:province":"Madrid",
    "wof:name":"Gomez Antolin Denis",
    "wof:placetype":"venue"
},
  "geometry": {"coordinates":[-3.7729229927,40.3256797791],"type":"Point"}
}