{
  "type": "Feature",
  "properties": {
    "addr:full":"Calle de Jose Zorrilla, 3 Burgos Burgos 09005",
    "addr:housenumber":"3",
    "addr:postcode":"09005",
    "addr:street":"Calle De Jose Zorrilla",
    "iso:country":"ES",
    "sg:address":"Calle de Jose Zorrilla, 3",
    "sg:city":"Burgos",
    "sg:orig_category":"Molduras, Junquillos, Listones Y Molduras Perforadas",
    "sg:phone":"+34 947 27 50 35",
    "sg:postcode":"09005",
    "sg:province":"Burgos",
    "wof:name":"Jose Carlos Martinez Gonzalez Y Otros S.cv.",
    "wof:placetype":"venue"
},
  "geometry": {"coordinates":[-3.6988999844,42.3456573486],"type":"Point"}
}