{
  "type": "Feature",
  "properties": {
    "addr:full":"Calle de Sancho El Sabio, 8 Vitoria-gasteiz \u00c1lava 01008",
    "addr:housenumber":"8",
    "addr:postcode":"01008",
    "addr:street":"Calle De Sancho El Sabio",
    "iso:country":"ES",
    "sg:address":"Calle de Sancho El Sabio, 8",
    "sg:city":"Vitoria-gasteiz",
    "sg:orig_category":"Abogados",
    "sg:phone":"+34 945 13 09 58",
    "sg:postcode":"01008",
    "sg:province":"\u00c1lava",
    "wof:name":"Parrilla Llamas Faustino",
    "wof:placetype":"venue"
},
  "geometry": {"coordinates":[-2.6795229912,42.8474693298],"type":"Point"}
}