{
  "type": "Feature",
  "properties": {
    "iso:country":"ES",
    "sg:address":"Carr Palafrugell, 1",
    "sg:city":"Escala",
    "sg:orig_category":"Ahumados Y Salazones",
    "sg:phone":"+34 972 77 03 57",
    "sg:postcode":"17130",
    "sg:province":"Girona",
    "sg:website":"www.anchovex.com",
    "wof:name":"Salaons Soles S. A.",
    "wof:placetype":"venue"
},
  "geometry": {"coordinates":[3.1321649551,42.1229934692],"type":"Point"}
}