{
  "type": "Feature",
  "properties": {
    "iso:country":"ES",
    "sg:address":"Calle de Ancha De La Magdalena, 9",
    "sg:city":"Cordoba",
    "sg:orig_category":"Bisuter\u00cda, Joyer\u00cda, Relojer\u00cda (al Por Menor)",
    "sg:phone":"+34 957 48 47 79",
    "sg:postcode":"14002",
    "sg:province":"C\u00f3rdoba",
    "wof:name":"Luque Garcia Francisca",
    "wof:placetype":"venue"
},
  "geometry": {"coordinates":[-4.7688288689,37.8849105835],"type":"Point"}
}