{
  "type": "Feature",
  "properties": {
    "iso:country":"ES",
    "sg:address":"Ctra. De Cullar, Km. 0013,5",
    "sg:city":"Benamaurel",
    "sg:orig_category":"Maquinaria, Instalaci\u00d3n Y Equipo Para Garajes Y Estaciones De Servicio",
    "sg:phone":"+34 958 34 43 53",
    "sg:postcode":"18817",
    "sg:province":"Granada",
    "sg:website":"www.cepsa.es",
    "wof:name":"Cabrera Cabrera Ramon",
    "wof:placetype":"venue"
},
  "geometry": {"coordinates":[-2.6881558895,37.601020813],"type":"Point"}
}