{
  "type": "Feature",
  "properties": {
    "iso:country":"ES",
    "sg:address":"Calle de Goya, 39",
    "sg:city":"Balos I",
    "sg:orig_category":"Chapister\u00cda",
    "sg:phone":"+34 928 79 05 74",
    "sg:postcode":"35110",
    "sg:province":"Las Palmas",
    "wof:name":"Castellano Perez Rosendo Juan",
    "wof:placetype":"venue"
},
  "geometry": {"coordinates":[-15.4485340118,27.8392906189],"type":"Point"}
}