{
  "type": "Feature",
  "properties": {
    "iso:country":"ES",
    "sg:address":"Calle de Cervantes, 9",
    "sg:city":"Ceuta",
    "sg:orig_category":"Molduras, Junquillos, Listones Y Molduras Perforadas",
    "sg:phone":"+34 956 51 40 23",
    "sg:postcode":"51001",
    "sg:province":"Ceuta",
    "wof:name":"Pecino Chacon Aurelio",
    "wof:placetype":"venue"
},
  "geometry": {"coordinates":[-5.3097805977,35.886505127],"type":"Point"}
}