{
  "type": "Feature",
  "properties": {
    "iso:country":"ES",
    "sg:address":"Zubiarte, 18",
    "sg:city":"Huarte",
    "sg:orig_category":"Bancos",
    "sg:phone":"+34 948 33 16 38",
    "sg:postcode":"31620",
    "sg:province":"Navarra",
    "wof:name":"Banco Espa\u00f1ol De Credito S.a.",
    "wof:placetype":"venue"
},
  "geometry": {"coordinates":[-1.5924630165,42.8312530518],"type":"Point"}
}