{
  "type": "Feature",
  "properties": {
    "addr:full":"Avda Generalisimo, S/n Presencio Burgos 09228",
    "addr:housenumber":"s",
    "addr:postcode":"09228",
    "addr:street":"Avda Generalisimo;/ N Presencio",
    "iso:country":"ES",
    "sg:address":"Avda Generalisimo, S/n",
    "sg:city":"Presencio",
    "sg:orig_category":"Construcciones Met\u00c1licas",
    "sg:phone":"+34 947 16 01 55",
    "sg:postcode":"09228",
    "sg:province":"Burgos",
    "wof:name":"Bermejo Barrio Heliodoro",
    "wof:placetype":"venue"
},
  "geometry": {"coordinates":[-3.8986189365,42.1850318909],"type":"Point"}
}