{
  "type": "Feature",
  "properties": {
    "iso:country":"ES",
    "sg:address":"Calle de Varaderos, 2",
    "sg:city":"Punta Umbria",
    "sg:orig_category":"Deportes N\u00c1uticos, Acu\u00c1ticos Y Subacu\u00c1ticos: Art\u00cdculos Y Equipo (al Por Menor)",
    "sg:phone":"+34 959 31 25 74",
    "sg:postcode":"21100",
    "sg:province":"Huelva",
    "wof:name":"Diaz Olivares Crisanto",
    "wof:placetype":"venue"
},
  "geometry": {"coordinates":[-6.9673848152,37.1888084412],"type":"Point"}
}