{
  "type": "Feature",
  "properties": {
    "addr:full":"Calle de Mirasierra, 36 Paracuellos De Jarama Madrid 28860",
    "addr:housenumber":"36",
    "addr:postcode":"28860",
    "addr:street":"Calle De Mirasierra",
    "iso:country":"ES",
    "sg:address":"Calle de Mirasierra, 36",
    "sg:city":"Paracuellos De Jarama",
    "sg:orig_category":"Asociaciones Y Clubs Deportivos",
    "sg:phone":"+34 916 58 16 15",
    "sg:postcode":"28860",
    "sg:province":"Madrid",
    "wof:name":"Tie-break Tenis.s.l.",
    "wof:placetype":"venue"
},
  "geometry": {"coordinates":[-3.5319640636,40.508644104],"type":"Point"}
}