{
  "type": "Feature",
  "properties": {
    "iso:country":"ES",
    "sg:address":"Av Pais Valencia, 27",
    "sg:city":"Alcoi",
    "sg:orig_category":"\u00d3ptica: Instrumentos (fabricaci\u00d3n)",
    "sg:phone":"+34 965 54 33 07",
    "sg:postcode":"03801",
    "sg:province":"Alicante",
    "wof:name":"Optica Dami S.l.",
    "wof:placetype":"venue"
},
  "geometry": {"coordinates":[-0.476752013,38.6962776184],"type":"Point"}
}