{
  "type": "Feature",
  "properties": {
    "addr:full":"Calle de Padre Larroca, 14 Donostia-san Sebastian Guip\u00f9zcoa 20001",
    "addr:housenumber":"14",
    "addr:postcode":"20001",
    "addr:street":"Calle De Padre Larroca",
    "iso:country":"ES",
    "sg:address":"Calle de Padre Larroca, 14",
    "sg:city":"Donostia-san Sebastian",
    "sg:orig_category":"Administradores De Bienes Y Delegados De Comunidades De Propietarios",
    "sg:phone":"+34 943 32 30 91",
    "sg:postcode":"20001",
    "sg:province":"Guip\u00f9zcoa",
    "wof:name":"Lasa Ramirez Elena",
    "wof:placetype":"venue"
},
  "geometry": {"coordinates":[-1.9741729498,43.323097229],"type":"Point"}
}