{
  "type": "Feature",
  "properties": {
    "addr:full":"Pg Bonanova, 43 Barcelona Barcelona 08022",
    "addr:housenumber":"43",
    "addr:postcode":"08022",
    "addr:street":"Pg Bonanova",
    "iso:country":"ES",
    "sg:address":"Pg Bonanova, 43",
    "sg:city":"Barcelona",
    "sg:orig_category":"Cajas De Ahorro",
    "sg:phone":"+34 934 18 81 40",
    "sg:postcode":"08022",
    "sg:province":"Barcelona",
    "sg:website":"www.caixacatalunya.es",
    "wof:name":"Caixa D'estalvis De Catalunya",
    "wof:placetype":"venue"
},
  "geometry": {"coordinates":[2.1299378872,41.404510498],"type":"Point"}
}