{
  "type": "Feature",
  "properties": {
    "iso:country":"ES",
    "sg:address":"Kale Nagusia, 16",
    "sg:city":"Idiazabal",
    "sg:orig_category":"Carnicer\u00cdas, Carnicer\u00cdas",
    "sg:phone":"+34 943 18 72 37",
    "sg:postcode":"20213",
    "sg:province":"Guip\u00f9zcoa",
    "wof:name":"Goya Eciolaza Luis Maria",
    "wof:placetype":"venue"
},
  "geometry": {"coordinates":[-2.2322790623,43.0144882202],"type":"Point"}
}