{
  "type": "Feature",
  "properties": {
    "iso:country":"ES",
    "sg:address":"Avda De Las Artes, S/n",
    "sg:city":"Salamanca",
    "sg:orig_category":"Cr\u00cda De Animales",
    "sg:phone":"+34 923 18 33 45",
    "sg:postcode":"37003",
    "sg:province":"Salamanca",
    "wof:name":"Agajiro S.l.",
    "wof:placetype":"venue"
},
  "geometry": {"coordinates":[-5.6431660652,40.9695701599],"type":"Point"}
}