{
  "type": "Feature",
  "properties": {
    "addr:full":"Ribera De Los Molinos, S/n Antequera M\u00e1laga 29200",
    "addr:housenumber":"s",
    "addr:postcode":"29200",
    "addr:street":"Ribera;Los Molinos;/ N;Ma\u0301Laga",
    "iso:country":"ES",
    "sg:address":"Ribera De Los Molinos, S/n",
    "sg:city":"Antequera",
    "sg:orig_category":"Transporte En General",
    "sg:phone":"+34 952 84 21 73",
    "sg:postcode":"29200",
    "sg:province":"M\u00e1laga",
    "wof:name":"Melero Marin Miguel",
    "wof:placetype":"venue"
},
  "geometry": {"coordinates":[-4.5636138916,37.0203018188],"type":"Point"}
}