{
  "type": "Feature",
  "properties": {
    "iso:country":"ES",
    "sg:address":"Carrer de Juan De La Cierva, 40",
    "sg:city":"Castelldefels",
    "sg:orig_category":"Molduras, Junquillos, Listones Y Molduras Perforadas",
    "sg:phone":"+34 936 65 00 65",
    "sg:postcode":"08860",
    "sg:province":"Barcelona",
    "wof:name":"Sanchez Gallardo Juan Vicente",
    "wof:placetype":"venue"
},
  "geometry": {"coordinates":[1.9817099571,41.2852516174],"type":"Point"}
}