{
  "type": "Feature",
  "properties": {
    "addr:full":"Tilve, 49 Pontevedra Pontevedra 36152",
    "addr:housenumber":"49",
    "addr:postcode":"36152",
    "addr:street":"Tilve",
    "iso:country":"ES",
    "sg:address":"Tilve, 49",
    "sg:city":"Pontevedra",
    "sg:orig_category":"Producci\u00d3n, Comercio De Cereales",
    "sg:phone":"+34 986 87 00 50",
    "sg:postcode":"36152",
    "sg:province":"Pontevedra",
    "wof:name":"Ucha Martinez Camilo",
    "wof:placetype":"venue"
},
  "geometry": {"coordinates":[-8.6156921387,42.4924125671],"type":"Point"}
}