{
  "type": "Feature",
  "properties": {
    "iso:country":"ES",
    "sg:address":"Calle de Batalla Del Salado, 37",
    "sg:city":"Albacete",
    "sg:orig_category":"Arquitectos",
    "sg:phone":"+34 967 19 12 69",
    "sg:postcode":"02006",
    "sg:province":"Albacete",
    "wof:name":"Domiciano Lopez Arquitectos S.l.",
    "wof:placetype":"venue"
},
  "geometry": {"coordinates":[-1.8504633904,38.9883460999],"type":"Point"}
}