{
  "type": "Feature",
  "properties": {
    "iso:country":"ES",
    "sg:address":"Castillo-gazteleku, 33",
    "sg:city":"Iru\u00f1a",
    "sg:orig_category":"Papeler\u00cdas, Librer\u00cdas",
    "sg:phone":"+34 948 22 01 84",
    "sg:postcode":"31001",
    "sg:province":"Navarra",
    "wof:name":"Anton Zuasti Jesus",
    "wof:placetype":"venue"
},
  "geometry": {"coordinates":[-1.6432837248,42.8191337585],"type":"Point"}
}