{
  "type": "Feature",
  "properties": {
    "addr:full":"Ctra Segovia, 28 Valladolid Valladolid 47012",
    "addr:housenumber":"28",
    "addr:postcode":"47012",
    "addr:street":"Ctra Segovia",
    "iso:country":"ES",
    "sg:address":"Ctra Segovia, 28",
    "sg:city":"Valladolid",
    "sg:orig_category":"Art\u00cdculos De Regalo (al Por Menor)",
    "sg:phone":"+34 983 23 58 07",
    "sg:postcode":"47012",
    "sg:province":"Valladolid",
    "wof:name":"Blanco Verdugo Galo",
    "wof:placetype":"venue"
},
  "geometry": {"coordinates":[-4.7162060738,41.6223602295],"type":"Point"}
}