{
  "type": "Feature",
  "properties": {
    "addr:full":"Carrer de Progres, 69 Gava Barcelona 08850",
    "addr:housenumber":"69",
    "addr:postcode":"08850",
    "addr:street":"Carrer De Progres",
    "iso:country":"ES",
    "sg:address":"Carrer de Progres, 69",
    "sg:city":"Gava",
    "sg:orig_category":"Fabricaci\u00d3n, Distribuci\u00d3n De Discos, V\u00cddeodiscos Y Musicassettes",
    "sg:phone":"+34 936 38 45 73",
    "sg:postcode":"08850",
    "sg:province":"Barcelona",
    "sg:website":"www.discoscastello.es",
    "wof:name":"Discos Castello S. A.",
    "wof:placetype":"venue"
},
  "geometry": {"coordinates":[2.0115170479,41.2989578247],"type":"Point"}
}