{
  "type": "Feature",
  "properties": {
    "addr:full":"Carr Dr Fleming, 19 Balaguer Lleida 25600",
    "addr:housenumber":"19",
    "addr:postcode":"25600",
    "addr:street":"Carr Dr Fleming",
    "iso:country":"ES",
    "sg:address":"Carr Dr Fleming, 19",
    "sg:city":"Balaguer",
    "sg:orig_category":"Laboratorios",
    "sg:phone":"+34 973 44 66 99",
    "sg:postcode":"25600",
    "sg:province":"Lleida",
    "wof:name":"Anlisis Drs.massip/peremiquel",
    "wof:placetype":"venue"
},
  "geometry": {"coordinates":[0.8103330135,41.790802002],"type":"Point"}
}