{
  "type": "Feature",
  "properties": {
    "addr:full":"Avda Industria (de La), 55 Alcobendas Madrid 28108",
    "addr:housenumber":"55",
    "addr:postcode":"28108",
    "addr:street":"Avda Industria De La",
    "iso:country":"ES",
    "sg:address":"Avda Industria (de La), 55",
    "sg:city":"Alcobendas",
    "sg:orig_category":"Construcci\u00d3n Mec\u00c1nica",
    "sg:phone":"+34 914 90 37 62",
    "sg:postcode":"28108",
    "sg:province":"Madrid",
    "wof:name":"Kimotor 2005 S.l.",
    "wof:placetype":"venue"
},
  "geometry": {"coordinates":[-3.6564230919,40.5335388184],"type":"Point"}
}