{
  "type": "Feature",
  "properties": {
    "iso:country":"ES",
    "sg:address":"Harizti Industrialdea, 4",
    "sg:city":"Ihurre",
    "sg:orig_category":"Rectificaci\u00d3n, Mecanizado, Fresado",
    "sg:phone":"+34 943 80 50 77",
    "sg:postcode":"20212",
    "sg:province":"Guip\u00f9zcoa",
    "wof:name":"Talleres Lau Lagun S.a.",
    "wof:placetype":"venue"
},
  "geometry": {"coordinates":[-2.2013700008,43.0282554626],"type":"Point"}
}