{
  "type": "Feature",
  "properties": {
    "addr:full":"Calle de El Arroyo, 16 Balmaseda Vizcaya 48800",
    "addr:housenumber":"16",
    "addr:postcode":"48800",
    "addr:street":"Calle De El Arroyo",
    "iso:country":"ES",
    "sg:address":"Calle de El Arroyo, 16",
    "sg:city":"Balmaseda",
    "sg:orig_category":"Escayola Y Productos De Escayola (fabricaci\u00d3n, Al Por Mayor)",
    "sg:phone":"+34 946 80 04 03",
    "sg:postcode":"48800",
    "sg:province":"Vizcaya",
    "wof:name":"Dopazo Regueira Antonio",
    "wof:placetype":"venue"
},
  "geometry": {"coordinates":[-3.1955230236,43.1978340149],"type":"Point"}
}