{
  "type": "Feature",
  "properties": {
    "addr:full":"Rua Mui\u00d1o, 31 Carballo La Coru\u00f1a 15100",
    "addr:housenumber":"31",
    "addr:postcode":"15100",
    "addr:street":"Rua Muin\u0303O;La Corun\u0303A",
    "iso:country":"ES",
    "sg:address":"Rua Mui\u00d1o, 31",
    "sg:city":"Carballo",
    "sg:orig_category":"Talleres De Corte Y Confecci\u00d3n",
    "sg:phone":"+34 981 75 74 53",
    "sg:postcode":"15100",
    "sg:province":"La Coru\u00f1a",
    "wof:name":"Confecciones Herdil S.l.",
    "wof:placetype":"venue"
},
  "geometry": {"coordinates":[-8.69049263,43.2201538086],"type":"Point"}
}