{
  "type": "Feature",
  "properties": {
    "iso:country":"ES",
    "sg:address":"Calle de Portal De Castilla, 56 C",
    "sg:city":"Vitoria-gasteiz",
    "sg:orig_category":"Promotores Constructores",
    "sg:phone":"+34 945 13 49 23",
    "sg:postcode":"01007",
    "sg:province":"\u00c1lava",
    "wof:name":"Construcciones Jose Rodriguez Dieguez",
    "wof:placetype":"venue"
},
  "geometry": {"coordinates":[-2.6853740215,42.8416213989],"type":"Point"}
}