{
  "type": "Feature",
  "properties": {
    "iso:country":"ES",
    "sg:address":"As Madorras, S/n",
    "sg:city":"Madorras",
    "sg:orig_category":"Iglesia Cat\u00d3lica",
    "sg:phone":"+34 986 33 28 88",
    "sg:postcode":"36413",
    "sg:province":"Pontevedra",
    "wof:name":"Obispado Tui-vigo. Parroquia De San Xurxo De Mosende",
    "wof:placetype":"venue"
},
  "geometry": {"coordinates":[-8.6597137451,42.1184768677],"type":"Point"}
}