{
  "type": "Feature",
  "properties": {
    "addr:full":"Pla\u00c7 Venecia, 10 Lloret Mar Girona 17310",
    "addr:housenumber":"10",
    "addr:postcode":"17310",
    "addr:street":"Venecia",
    "iso:country":"ES",
    "sg:address":"Pla\u00c7 Venecia, 10",
    "sg:city":"Lloret Mar",
    "sg:orig_category":"Peluquer\u00cdas, Peluquer\u00cda Mixta",
    "sg:phone":"+34 972 36 21 63",
    "sg:postcode":"17310",
    "sg:province":"Girona",
    "wof:name":"Domenech Riera Maria",
    "wof:placetype":"venue"
},
  "geometry": {"coordinates":[2.846834898,41.6981697083],"type":"Point"}
}