{
  "type": "Feature",
  "properties": {
    "iso:country":"ES",
    "sg:address":"Calle de Luis Rosales, 21",
    "sg:city":"Albacete",
    "sg:orig_category":"Marroquiner\u00cda (confecci\u00d3n)",
    "sg:phone":"+34 967 50 23 82",
    "sg:postcode":"02004",
    "sg:province":"Albacete",
    "wof:name":"Angel Piqueras Cortijo Y Diego Piqueras Cortijo C.b.",
    "wof:placetype":"venue"
},
  "geometry": {"coordinates":[-1.8624889851,38.9915657043],"type":"Point"}
}