{
  "type": "Feature",
  "properties": {
    "iso:country":"ES",
    "sg:address":"Calle de Manuel Bobadilla, 53",
    "sg:city":"Palma",
    "sg:orig_category":"Ense\u00d1anza Secundaria: Colegios Y Escuelas Privadas",
    "sg:phone":"+34 968 55 41 80",
    "sg:postcode":"30593",
    "sg:province":"Murcia",
    "wof:name":"Instituto De Educacion Secundaria De La Palma",
    "wof:placetype":"venue"
},
  "geometry": {"coordinates":[-0.9674500227,37.6888885498],"type":"Point"}
}