{
  "type": "Feature",
  "properties": {
    "addr:full":"Pl Guernica, 11 Hospitalet Llobregat Barcelona 08903",
    "addr:housenumber":"11",
    "addr:postcode":"08903",
    "addr:street":"Pl Guernica",
    "iso:country":"ES",
    "sg:address":"Pl Guernica, 11",
    "sg:city":"Hospitalet Llobregat",
    "sg:orig_category":"Asociaciones, Organismos Culturales Y Socioeducativos",
    "sg:phone":"+34 933 34 96 92",
    "sg:postcode":"08903",
    "sg:province":"Barcelona",
    "wof:name":"Centro Aragones De Hospitalet",
    "wof:placetype":"venue"
},
  "geometry": {"coordinates":[2.1226580143,41.3740615845],"type":"Point"}
}