{
  "type": "Feature",
  "properties": {
    "iso:country":"ES",
    "sg:address":"Calle de Divino Valles, 16",
    "sg:city":"Madrid",
    "sg:orig_category":"Ropa Para Se\u00d1oras (al Por Menor)",
    "sg:phone":"+34 914 73 94 85",
    "sg:postcode":"28045",
    "sg:province":"Madrid",
    "wof:name":"Tajuelo Romero Adolfo",
    "wof:placetype":"venue"
},
  "geometry": {"coordinates":[-3.6963629723,40.3964614868],"type":"Point"}
}