{
  "type": "Feature",
  "properties": {
    "addr:full":"Avda El Ferrol, 39 Madrid Madrid 28029",
    "addr:housenumber":"39",
    "addr:postcode":"madrid;28029",
    "addr:street":"Avda El Ferrol",
    "iso:country":"ES",
    "sg:address":"Avda El Ferrol, 39",
    "sg:city":"Madrid",
    "sg:orig_category":"Ense\u00d1anza: Idiomas",
    "sg:phone":"+34 913 23 02 44",
    "sg:postcode":"28029",
    "sg:province":"Madrid",
    "wof:name":"Benito Regalado Elena",
    "wof:placetype":"venue"
},
  "geometry": {"coordinates":[-3.7053771019,40.4740562439],"type":"Point"}
}