{
  "type": "Feature",
  "properties": {
    "iso:country":"ES",
    "sg:address":"Calle de Teniente Braulio Laportilla, 4",
    "sg:city":"Cordoba",
    "sg:orig_category":"Administradores De Bienes Y Delegados De Comunidades De Propietarios",
    "sg:phone":"+34 957 48 82 63",
    "sg:postcode":"14008",
    "sg:province":"C\u00f3rdoba",
    "wof:name":"Palacios Molina Aurelia",
    "wof:placetype":"venue"
},
  "geometry": {"coordinates":[-4.7811541557,37.8856773376],"type":"Point"}
}