{
  "type": "Feature",
  "properties": {
    "addr:full":"Carrer de Albareda, 10 Barcelona Barcelona 08004",
    "addr:housenumber":"10",
    "addr:postcode":"08004",
    "addr:street":"Carrer De Albareda",
    "iso:country":"ES",
    "sg:address":"Carrer de Albareda, 10",
    "sg:city":"Barcelona",
    "sg:orig_category":"Agencias Y Agentes Comerciales, Representantes",
    "sg:phone":"+34 934 41 74 40",
    "sg:postcode":"08004",
    "sg:province":"Barcelona",
    "wof:name":"Representaciones Villanueva S.l.",
    "wof:placetype":"venue"
},
  "geometry": {"coordinates":[2.1741418839,41.3738327026],"type":"Point"}
}