{
  "type": "Feature",
  "properties": {
    "iso:country":"ES",
    "sg:address":"Calle de Vicente Aleixandre, 10",
    "sg:city":"Almansa",
    "sg:classifiers":[
        {
            "category":"Autos & Motor Vehicles",
            "subcategory":"Automobile Sales",
            "type":"Retail Goods"
        }
    ],
    "sg:phone":"+34 967 34 23 16",
    "sg:postcode":"02640",
    "sg:province":"Albacete",
    "wof:name":"Autoescuela Almansa S.l.",
    "wof:placetype":"venue"
},
  "geometry": {"coordinates":[-1.0910890102,38.8688316345],"type":"Point"}
}