{
  "type": "Feature",
  "properties": {
    "iso:country":"ES",
    "sg:address":"Avda Manuel Rivera, 1",
    "sg:city":"Palencia",
    "sg:orig_category":"Institutos De Belleza",
    "sg:phone":"+34 979 72 35 45",
    "sg:postcode":"34002",
    "sg:province":"Palencia",
    "wof:name":"Llorente Paredes Valentina",
    "wof:placetype":"venue"
},
  "geometry": {"coordinates":[-4.5286946297,42.0095672607],"type":"Point"}
}