{
  "type": "Feature",
  "properties": {
    "addr:full":"Calle de Juan De Urbieta, 13 Madrid Madrid 28007",
    "addr:housenumber":"13",
    "addr:postcode":"madrid;28007",
    "addr:street":"Calle De Juan De Urbieta",
    "iso:country":"ES",
    "sg:address":"Calle de Juan De Urbieta, 13",
    "sg:city":"Madrid",
    "sg:orig_category":"Administradores De Bienes Y Delegados De Comunidades De Propietarios",
    "sg:phone":"+34 914 33 08 10",
    "sg:postcode":"28007",
    "sg:province":"Madrid",
    "wof:name":"Azuagra S.l.",
    "wof:placetype":"venue"
},
  "geometry": {"coordinates":[-3.6775040627,40.4045639038],"type":"Point"}
}