{
  "type": "Feature",
  "properties": {
    "addr:full":"Calle de Tablas, 1 Granada Granada 18002",
    "addr:housenumber":"1",
    "addr:postcode":"18002",
    "addr:street":"Calle De Tablas",
    "iso:country":"ES",
    "sg:address":"Calle de Tablas, 1",
    "sg:city":"Granada",
    "sg:orig_category":"Ropa Para Se\u00d1oras (al Por Menor)",
    "sg:phone":"+34 958 26 62 54",
    "sg:postcode":"18002",
    "sg:province":"Granada",
    "wof:name":"Fernandez Vigil Maria Angustias",
    "wof:placetype":"venue"
},
  "geometry": {"coordinates":[-3.6025209427,37.1760902405],"type":"Point"}
}