{
  "type": "Feature",
  "properties": {
    "addr:full":"Rbla Sant Jordi (de), 59 Ripollet Barcelona 08291",
    "addr:housenumber":"59",
    "addr:postcode":"08291",
    "addr:street":"Rbla Sant Jordi De",
    "iso:country":"ES",
    "sg:address":"Rbla Sant Jordi (de), 59",
    "sg:city":"Ripollet",
    "sg:orig_category":"Ropa Para Se\u00d1oras (al Por Menor)",
    "sg:phone":"+34 935 94 22 30",
    "sg:postcode":"08291",
    "sg:province":"Barcelona",
    "wof:name":"Sellrio S.a.",
    "wof:placetype":"venue"
},
  "geometry": {"coordinates":[2.1634740829,41.4961013794],"type":"Point"}
}