{
  "type": "Feature",
  "properties": {
    "addr:full":"Avda Galtzaraborda, 45 Errenteria Guip\u00f9zcoa 20100",
    "addr:housenumber":"45",
    "addr:postcode":"20100",
    "addr:street":"Avda Galtzaraborda;Guipu\u0300Zcoa",
    "iso:country":"ES",
    "sg:address":"Avda Galtzaraborda, 45",
    "sg:city":"Errenteria",
    "sg:orig_category":"Mercer\u00cda, Lencer\u00cda (al Por Menor)",
    "sg:phone":"+34 943 51 42 81",
    "sg:postcode":"20100",
    "sg:province":"Guip\u00f9zcoa",
    "wof:name":"Miriam Diaz Erzibengoa",
    "wof:placetype":"venue"
},
  "geometry": {"coordinates":[-1.9098720551,43.3108558655],"type":"Point"}
}