{
  "type": "Feature",
  "properties": {
    "iso:country":"ES",
    "sg:address":"Calle de Subida Al Moral, 18",
    "sg:city":"Cervera Del Rio Alhama",
    "sg:orig_category":"Confecci\u00d3n De Zapatos",
    "sg:phone":"+34 941 19 90 16",
    "sg:postcode":"26520",
    "sg:province":"La Rioja",
    "wof:name":"Guerra Alonso Indalecio",
    "wof:placetype":"venue"
},
  "geometry": {"coordinates":[-1.9488830566,42.0076942444],"type":"Point"}
}