{
  "type": "Feature",
  "properties": {
    "addr:full":"Avda Beiramar, 2 Vigo Pontevedra 36208",
    "addr:housenumber":"2",
    "addr:postcode":"36208",
    "addr:street":"Avda Beiramar",
    "iso:country":"ES",
    "sg:address":"Avda Beiramar, 2",
    "sg:city":"Vigo",
    "sg:orig_category":"Fabricaci\u00d3n, Reparaci\u00d3n Y Mantenimiento De Construcciones Navales Y Fluviales",
    "sg:phone":"+34 986 24 18 25",
    "sg:postcode":"36208",
    "sg:province":"Pontevedra",
    "wof:name":"Global Equipos Navales S L",
    "wof:placetype":"venue"
},
  "geometry": {"coordinates":[-8.7395744324,42.2257804871],"type":"Point"}
}