{
  "type": "Feature",
  "properties": {
    "iso:country":"ES",
    "sg:address":"Avda Lisboa (de), 12",
    "sg:city":"Coslada",
    "sg:orig_category":"Oficinas Y Gesti\u00d3n De Inmuebles",
    "sg:phone":"+34 916 73 64 15",
    "sg:postcode":"28820",
    "sg:province":"Madrid",
    "wof:name":"Zenitram Silber",
    "wof:placetype":"venue"
},
  "geometry": {"coordinates":[-3.5413777828,40.4178314209],"type":"Point"}
}