{
  "type": "Feature",
  "properties": {
    "addr:full":"Calle de Clariano, 6 Valencia Valencia 46021",
    "addr:housenumber":"6",
    "addr:postcode":"46021",
    "addr:street":"Calle De Clariano",
    "iso:country":"ES",
    "sg:address":"Calle de Clariano, 6",
    "sg:city":"Valencia",
    "sg:orig_category":"Abogados",
    "sg:phone":"+34 963 60 88 92",
    "sg:postcode":"46021",
    "sg:province":"Valencia",
    "wof:name":"Sanchez Martinez Julio",
    "wof:placetype":"venue"
},
  "geometry": {"coordinates":[-0.3518922031,39.4764289856],"type":"Point"}
}