{
  "type": "Feature",
  "properties": {
    "iso:country":"ES",
    "sg:address":"Calle de Angel Ganivet, 21",
    "sg:city":"Madrid",
    "sg:orig_category":"Internados & Ense\u00d1anza Privada",
    "sg:phone":"+34 915 52 35 25",
    "sg:postcode":"28007",
    "sg:province":"Madrid",
    "wof:name":"Educacion Activa S.l.",
    "wof:placetype":"venue"
},
  "geometry": {"coordinates":[-3.6716413498,40.4085121155],"type":"Point"}
}