{
  "type": "Feature",
  "properties": {
    "iso:country":"ES",
    "sg:address":"Calle de Garcia Ximenez, 22",
    "sg:city":"Alsasua",
    "sg:orig_category":"Notarios",
    "sg:phone":"+34 948 56 29 03",
    "sg:postcode":"31800",
    "sg:province":"Navarra",
    "wof:name":"Fuentes Abad Francisco Javier De Las",
    "wof:placetype":"venue"
},
  "geometry": {"coordinates":[-2.1675419807,42.8939094543],"type":"Point"}
}