{
  "type": "Feature",
  "properties": {
    "iso:country":"ES",
    "sg:address":"Rua Real, 91",
    "sg:city":"Ferrol",
    "sg:orig_category":"Lencer\u00cda Femenina, Corseter\u00cda, Trajes De Ba\u00d1o (al Por Menor)",
    "sg:phone":"+34 981 30 01 82",
    "sg:postcode":"15402",
    "sg:province":"La Coru\u00f1a",
    "wof:name":"Nicler De Cantabria S.l.",
    "wof:placetype":"venue"
},
  "geometry": {"coordinates":[-8.2325515747,43.4839782715],"type":"Point"}
}