{
  "type": "Feature",
  "properties": {
    "iso:country":"ES",
    "sg:address":"Calle de Jose Ortega Y Gasset, 86",
    "sg:city":"Madrid",
    "sg:orig_category":"Panader\u00cdas, Panader\u00cdas",
    "sg:phone":"+34 914 01 26 56",
    "sg:postcode":"28006",
    "sg:province":"Madrid",
    "sg:website":"www.animari.com",
    "wof:name":"Apicola Animari S. A.",
    "wof:placetype":"venue"
},
  "geometry": {"coordinates":[-3.6725802422,40.4297599792],"type":"Point"}
}