{
  "type": "Feature",
  "properties": {
    "iso:country":"ES",
    "sg:address":"Avda Bulevar De El Ejido, 301",
    "sg:city":"Ejido",
    "sg:orig_category":"Abogados",
    "sg:phone":"+34 950 57 30 25",
    "sg:postcode":"04700",
    "sg:province":"Almer\u00eda",
    "wof:name":"Balaguer Gutierrez Maria Soledad",
    "wof:placetype":"venue"
},
  "geometry": {"coordinates":[-2.8123414516,36.7735214233],"type":"Point"}
}