{
  "type": "Feature",
  "properties": {
    "iso:country":"ES",
    "sg:address":"Calle de Valientes, 7",
    "sg:city":"Jerez De La Frontera",
    "sg:orig_category":"Negocio De Metales No Ferrosos",
    "sg:phone":"+34 956 34 95 65",
    "sg:postcode":"11402",
    "sg:province":"C\u00e1diz",
    "wof:name":"Roman Solano Antonio",
    "wof:placetype":"venue"
},
  "geometry": {"coordinates":[-6.1339669228,36.685634613],"type":"Point"}
}