{
  "type": "Feature",
  "properties": {
    "addr:full":"Calle de Ayala, 7 Madrid Madrid 28001",
    "addr:housenumber":"7",
    "addr:postcode":"madrid;28001",
    "addr:street":"Calle De Ayala",
    "iso:country":"ES",
    "sg:address":"Calle de Ayala, 7",
    "sg:city":"Madrid",
    "sg:orig_category":"Compraventa De Antig\u00dcedades",
    "sg:phone":"+34 915 76 40 63",
    "sg:postcode":"28001",
    "sg:province":"Madrid",
    "sg:website":"www.isabellara.com",
    "wof:name":"Lara Yotti Maria Isabel",
    "wof:placetype":"venue"
},
  "geometry": {"coordinates":[-3.6881608963,40.4279594421],"type":"Point"}
}