{
  "type": "Feature",
  "properties": {
    "addr:full":"Calle de Hilario Suarez, 8 Grado Asturias 33820",
    "addr:housenumber":"8",
    "addr:postcode":"33820",
    "addr:street":"Calle De Hilario Suarez",
    "iso:country":"ES",
    "sg:address":"Calle de Hilario Suarez, 8",
    "sg:city":"Grado",
    "sg:orig_category":"Discotecas Y Salas De Baile",
    "sg:phone":"+34 985 75 31 16",
    "sg:postcode":"33820",
    "sg:province":"Asturias",
    "wof:name":"New Spook S.l.",
    "wof:placetype":"venue"
},
  "geometry": {"coordinates":[-6.0686812401,43.3914909363],"type":"Point"}
}