{
  "type": "Feature",
  "properties": {
    "iso:country":"ES",
    "sg:address":"Calle de Espronceda, 18",
    "sg:city":"Madrid",
    "sg:orig_category":"Muebles Y Accesorios Para Cocinas Y Cuartos De Ba\u00d1o (al Por Menor)",
    "sg:phone":"+34 914 42 40 80",
    "sg:postcode":"28003",
    "sg:province":"Madrid",
    "wof:name":"Tu Cocina S.l.",
    "wof:placetype":"venue"
},
  "geometry": {"coordinates":[-3.697343111,40.4404907227],"type":"Point"}
}