{
  "type": "Feature",
  "properties": {
    "iso:country":"ES",
    "sg:address":"O Cruceiro, S/n",
    "sg:city":"Barcela",
    "sg:orig_category":"Iglesia Cat\u00d3lica",
    "sg:phone":"+34 986 66 55 34",
    "sg:postcode":"36435",
    "sg:province":"Pontevedra",
    "wof:name":"Besada Paraje Alfonso",
    "wof:placetype":"venue"
},
  "geometry": {"coordinates":[-8.32924366,42.1040763855],"type":"Point"}
}