{
  "type": "Feature",
  "properties": {
    "iso:country":"ES",
    "sg:address":"Praj Carretera De Almansa, Km. 0005,0",
    "sg:city":"Campo Arriba",
    "sg:orig_category":"Centros Empresariales",
    "sg:phone":"+34 968 71 93 21",
    "sg:postcode":"30510",
    "sg:province":"Murcia",
    "wof:name":"Soriano Paya Francisco",
    "wof:placetype":"venue"
},
  "geometry": {"coordinates":[-1.1149940491,38.6145591736],"type":"Point"}
}