{
  "type": "Feature",
  "properties": {
    "iso:country":"ES",
    "sg:address":"Calle de Hermanas Alonso Barcelo, 10",
    "sg:city":"Madrid",
    "sg:orig_category":"Inform\u00c1tica, Ofim\u00c1tica (estudios, Asesor\u00cda, Ingenier\u00cda, Formaci\u00d3n)",
    "sg:phone":"+34 914 61 66 47",
    "sg:postcode":"28025",
    "sg:province":"Madrid",
    "wof:name":"Organizacion Y Mantenimientos Informaticos S.l.",
    "wof:placetype":"venue"
},
  "geometry": {"coordinates":[-3.7389481068,40.3874473572],"type":"Point"}
}