{
  "type": "Feature",
  "properties": {
    "addr:full":"Calle de San Torcuato, 41 Zamora Zamora 49014",
    "addr:housenumber":"41",
    "addr:postcode":"49014",
    "addr:street":"Calle De San Torcuato",
    "iso:country":"ES",
    "sg:address":"Calle de San Torcuato, 41",
    "sg:city":"Zamora",
    "sg:orig_category":"Iglesia Cat\u00d3lica",
    "sg:phone":"+34 980 53 16 12",
    "sg:postcode":"49014",
    "sg:province":"Zamora",
    "wof:name":"Obispado De Zamora",
    "wof:placetype":"venue"
},
  "geometry": {"coordinates":[-5.7437047958,41.5070838928],"type":"Point"}
}