{
  "type": "Feature",
  "properties": {
    "iso:country":"ES",
    "sg:address":"Calle de Pilar (el), 24",
    "sg:city":"Chiva",
    "sg:orig_category":"Carnicer\u00cdas, Carnicer\u00cdas",
    "sg:phone":"+34 962 52 03 15",
    "sg:postcode":"46370",
    "sg:province":"Valencia",
    "wof:name":"Martinez Cere Maria Teresa",
    "wof:placetype":"venue"
},
  "geometry": {"coordinates":[-0.7191069722,39.4736862183],"type":"Point"}
}