{
  "type": "Feature",
  "properties": {
    "iso:country":"ES",
    "sg:address":"Avda Dilar (de), 65",
    "sg:city":"Granada",
    "sg:orig_category":"Caf\u00c9s, Bares, Cervecer\u00cdas",
    "sg:phone":"+34 958 12 45 66",
    "sg:postcode":"18007",
    "sg:province":"Granada",
    "wof:name":"Do\u00f1a Rosquita S.l.",
    "wof:placetype":"venue"
},
  "geometry": {"coordinates":[-3.600039959,37.1568145752],"type":"Point"}
}