{
  "type": "Feature",
  "properties": {
    "iso:country":"ES",
    "sg:address":"Calle de Albuera, 1",
    "sg:city":"Alzira",
    "sg:orig_category":"Cl\u00cdnicas Dentales",
    "sg:phone":"+34 962 40 19 50",
    "sg:postcode":"46600",
    "sg:province":"Valencia",
    "wof:name":"Sifre Balaguer Rafael",
    "wof:placetype":"venue"
},
  "geometry": {"coordinates":[-0.4352790117,39.1493721008],"type":"Point"}
}