{
  "type": "Feature",
  "properties": {
    "iso:country":"ES",
    "sg:address":"Pl. Sang, 3",
    "sg:city":"Reus",
    "sg:orig_category":"Centros Empresariales",
    "sg:phone":"+34 977 77 53 15",
    "sg:postcode":"43204",
    "sg:province":"Tarragona",
    "wof:name":"Associacio De Marxants Provincia De Tarragona",
    "wof:placetype":"venue"
},
  "geometry": {"coordinates":[1.1120080948,41.1556091309],"type":"Point"}
}