{
  "type": "Feature",
  "properties": {
    "addr:full":"Pol Ind Castillo, 3 Lebrija Sevilla 41740",
    "addr:housenumber":"3",
    "addr:postcode":"41740",
    "addr:street":"Castillo",
    "iso:country":"ES",
    "sg:address":"Pol Ind Castillo, 3",
    "sg:city":"Lebrija",
    "sg:orig_category":"Ebanister\u00cda",
    "sg:phone":"+34 955 97 59 01",
    "sg:postcode":"41740",
    "sg:province":"Sevilla",
    "sg:website":"www.cuadrosyenmarcacionesemj.com",
    "wof:name":"Cuadros Y Enmarcaciones Emj S.l.",
    "wof:placetype":"venue"
},
  "geometry": {"coordinates":[-6.0658698082,36.9205932617],"type":"Point"}
}