{
  "type": "Feature",
  "properties": {
    "addr:full":"Ventosa, S/n Covas La Coru\u00f1a 15864",
    "addr:housenumber":"s / n",
    "addr:postcode":"15864",
    "addr:street":"Ventosa",
    "iso:country":"ES",
    "sg:address":"Ventosa, S/n",
    "sg:city":"Covas",
    "sg:orig_category":"Cer\u00c1mica Art\u00cdstica Y Decorativa",
    "sg:phone":"+34 981 89 00 69",
    "sg:postcode":"15864",
    "sg:province":"La Coru\u00f1a",
    "wof:name":"Caama\u00f1o A\u00f1on Manuel",
    "wof:placetype":"venue"
},
  "geometry": {"coordinates":[-8.6849870682,42.8890686035],"type":"Point"}
}