{
  "type": "Feature",
  "properties": {
    "addr:full":"Plaz Espa\u00d1a, 11 Medellin Badajoz 06411",
    "addr:housenumber":"11",
    "addr:postcode":"06411",
    "addr:street":"Plaz Espan\u0303A",
    "iso:country":"ES",
    "sg:address":"Plaz Espa\u00d1a, 11",
    "sg:city":"Medellin",
    "sg:orig_category":"Cajas Para Embalar",
    "sg:phone":"+34 924 82 26 14",
    "sg:postcode":"06411",
    "sg:province":"Badajoz",
    "wof:name":"Caja Rural De Extremadura",
    "wof:placetype":"venue"
},
  "geometry": {"coordinates":[-5.9577040672,38.9618453979],"type":"Point"}
}