{
  "type": "Feature",
  "properties": {
    "addr:full":"Caracola, S/n Manga Mar Menor Murcia 30380",
    "addr:housenumber":"s / n",
    "addr:postcode":"30380",
    "addr:street":"Caracola",
    "iso:country":"ES",
    "sg:address":"Caracola, S/n",
    "sg:city":"Manga Mar Menor",
    "sg:orig_category":"Cristaler\u00cdas",
    "sg:phone":"+34 968 56 41 50",
    "sg:postcode":"30380",
    "sg:province":"Murcia",
    "wof:name":"Marin Moreno Francisco",
    "wof:placetype":"venue"
},
  "geometry": {"coordinates":[-0.7281540036,37.6686553955],"type":"Point"}
}