{
  "type": "Feature",
  "properties": {
    "addr:full":"Avda Mediterraneo (del), 201 Rincon Victoria M\u00e1laga 29730",
    "addr:housenumber":"201",
    "addr:postcode":"29730",
    "addr:street":"Avda Mediterraneo Del;Ma\u0301Laga",
    "iso:country":"ES",
    "sg:address":"Avda Mediterraneo (del), 201",
    "sg:city":"Rincon Victoria",
    "sg:orig_category":"Institutos De Belleza",
    "sg:phone":"+34 952 97 35 68",
    "sg:postcode":"29730",
    "sg:province":"M\u00e1laga",
    "wof:name":"Antunez Berran Maria Jose",
    "wof:placetype":"venue"
},
  "geometry": {"coordinates":[-4.2868151665,36.7152824402],"type":"Point"}
}