{
  "type": "Feature",
  "properties": {
    "iso:country":"ES",
    "sg:address":"Avda Seneca, 4",
    "sg:city":"Madrid",
    "sg:orig_category":"Ense\u00d1anza Superior Privada",
    "sg:phone":"+34 915 43 42 51",
    "sg:postcode":"28040",
    "sg:province":"Madrid",
    "wof:name":"Asociacion De Antiguos Colegiales Del Colegio Mayor Guadalupe",
    "wof:placetype":"venue"
},
  "geometry": {"coordinates":[-3.7257916927,40.4363708496],"type":"Point"}
}