{
  "type": "Feature",
  "properties": {
    "iso:country":"ES",
    "sg:address":"Avda Reina Victoria, 61",
    "sg:city":"Santander",
    "sg:orig_category":"Centros De Educaci\u00d3n Especial",
    "sg:phone":"+34 942 27 03 18",
    "sg:postcode":"39005",
    "sg:province":"Cantabria",
    "wof:name":"Nuevo Tagore S. Cooperativa L.",
    "wof:placetype":"venue"
},
  "geometry": {"coordinates":[-3.7854459286,43.4639282227],"type":"Point"}
}