{
  "type": "Feature",
  "properties": {
    "addr:full":"Calle de Tinte, 10 Albacete Albacete 02001",
    "addr:housenumber":"10",
    "addr:postcode":"02001",
    "addr:street":"Calle De Tinte",
    "iso:country":"ES",
    "sg:address":"Calle de Tinte, 10",
    "sg:city":"Albacete",
    "sg:orig_category":"Ropa Para Ni\u00d1os (al Por Menor)",
    "sg:phone":"+34 967 23 80 97",
    "sg:postcode":"02001",
    "sg:province":"Albacete",
    "sg:website":"www.amichi.com",
    "wof:name":"Distramichi S.l.",
    "wof:placetype":"venue"
},
  "geometry": {"coordinates":[-1.8559770584,38.9928321838],"type":"Point"}
}