{
  "type": "Feature",
  "properties": {
    "addr:full":"Av Francesc Macia, 60 Vilanova I La Geltru Barcelona 08800",
    "addr:housenumber":"60",
    "addr:postcode":"08800",
    "addr:street":"Av Francesc Macia",
    "iso:country":"ES",
    "sg:address":"Av Francesc Macia, 60",
    "sg:city":"Vilanova I La Geltru",
    "sg:orig_category":"Talleres: Ropa A Medida",
    "sg:phone":"+34 938 93 91 54",
    "sg:postcode":"08800",
    "sg:province":"Barcelona",
    "wof:name":"Hong Fu  Chun",
    "wof:placetype":"venue"
},
  "geometry": {"coordinates":[1.7211731672,41.2227096558],"type":"Point"}
}