{
  "type": "Feature",
  "properties": {
    "addr:full":"Calle de Ikea, 8 Leioa Vizcaya 48940",
    "addr:housenumber":"8",
    "addr:postcode":"48940",
    "addr:street":"Calle De Ikea",
    "iso:country":"ES",
    "sg:address":"Calle de Ikea, 8",
    "sg:city":"Leioa",
    "sg:orig_category":"Servicios De Telecomunicaciones",
    "sg:phone":"+34 944 02 85 29",
    "sg:postcode":"48940",
    "sg:province":"Vizcaya",
    "wof:name":"Lantelko Bilbao Sll",
    "wof:placetype":"venue"
},
  "geometry": {"coordinates":[-2.984208107,43.326133728],"type":"Point"}
}