{
  "type": "Feature",
  "properties": {
    "addr:full":"Calle de Audiencia, 20 Galdar Las Palmas 35460",
    "addr:housenumber":"20",
    "addr:postcode":"35460",
    "addr:street":"Calle De Audiencia",
    "iso:country":"ES",
    "sg:address":"Calle de Audiencia, 20",
    "sg:city":"Galdar",
    "sg:orig_category":"Doctores En Medicina",
    "sg:phone":"+34 928 88 01 70",
    "sg:postcode":"35460",
    "sg:province":"Las Palmas",
    "wof:name":"Castro Pol Francisco Javier",
    "wof:placetype":"venue"
},
  "geometry": {"coordinates":[-15.6543588638,28.143661499],"type":"Point"}
}