{
  "type": "Feature",
  "properties": {
    "addr:full":"Carr Cristofol Grober, 2 Girona Girona 17001",
    "addr:housenumber":"2",
    "addr:postcode":"17001",
    "addr:street":"Carr Cristofol Grober",
    "iso:country":"ES",
    "sg:address":"Carr Cristofol Grober, 2",
    "sg:city":"Girona",
    "sg:orig_category":"Abogados",
    "sg:phone":"+34 972 21 25 63",
    "sg:postcode":"17001",
    "sg:province":"Girona",
    "wof:name":"Pages Heras Isabel",
    "wof:placetype":"venue"
},
  "geometry": {"coordinates":[2.8210349083,41.9827690125],"type":"Point"}
}