{
  "type": "Feature",
  "properties": {
    "addr:full":"Avda Finisterre, 66 Carballo La Coru\u00f1a 15100",
    "addr:housenumber":"66",
    "addr:postcode":"15100",
    "addr:street":"Avda Finisterre;La Corun\u0303A",
    "iso:country":"ES",
    "sg:address":"Avda Finisterre, 66",
    "sg:city":"Carballo",
    "sg:orig_category":"Ropa Para Se\u00d1oras (al Por Menor)",
    "sg:phone":"+34 981 75 73 35",
    "sg:postcode":"15100",
    "sg:province":"La Coru\u00f1a",
    "wof:name":"Confecciones Chorima S.l.l.",
    "wof:placetype":"venue"
},
  "geometry": {"coordinates":[-8.6915636063,43.2116165161],"type":"Point"}
}