{
  "type": "Feature",
  "properties": {
    "addr:full":"C/ Mario Pastor Sempere, 3 Elche Alicante 03206",
    "addr:housenumber":"3",
    "addr:postcode":"03206",
    "addr:street":"C / Mario Pastor Sempere",
    "iso:country":"ES",
    "sg:address":"C/ Mario Pastor Sempere, 3",
    "sg:city":"Elche",
    "sg:orig_category":"Plomeros",
    "sg:phone":"+34 965 46 40 43",
    "sg:postcode":"03206",
    "sg:province":"Alicante",
    "wof:name":"Maza Jimenez Jose",
    "wof:placetype":"venue"
},
  "geometry": {"coordinates":[-0.7019569874,38.2728691101],"type":"Point"}
}