{
  "type": "Feature",
  "properties": {
    "addr:full":"Calle de Rabida, 6 Huelva Huelva 21001",
    "addr:housenumber":"6",
    "addr:postcode":"21001",
    "addr:street":"Calle De Rabida",
    "iso:country":"ES",
    "sg:address":"Calle de Rabida, 6",
    "sg:city":"Huelva",
    "sg:orig_category":"Lencer\u00cda Femenina, Corseter\u00cda, Trajes De Ba\u00d1o (al Por Menor)",
    "sg:phone":"+34 959 24 90 17",
    "sg:postcode":"21001",
    "sg:province":"Huelva",
    "wof:name":"Coto  Maria Jose",
    "wof:placetype":"venue"
},
  "geometry": {"coordinates":[-6.9509019852,37.2559394836],"type":"Point"}
}