{
  "type": "Feature",
  "properties": {
    "iso:country":"ES",
    "sg:address":"Ctra. Toledo, 12",
    "sg:city":"Galvez",
    "sg:orig_category":"Estilistas Y Estudios De Estilo De Corte Y Confecci\u00d3n",
    "sg:phone":"+34 925 40 02 62",
    "sg:postcode":"45164",
    "sg:province":"Toledo",
    "wof:name":"Cooperativa Nueva Juventud",
    "wof:placetype":"venue"
},
  "geometry": {"coordinates":[-4.2757091522,39.7027244568],"type":"Point"}
}