{
  "type": "Feature",
  "properties": {
    "iso:country":"ES",
    "sg:address":"Pol Ind Los Corrales, S/n",
    "sg:city":"Corrales",
    "sg:orig_category":"M\u00c1rmoles, Granitos Y Piedras Naturales",
    "sg:phone":"+34 955 91 74 80",
    "sg:postcode":"41657",
    "sg:province":"Sevilla",
    "wof:name":"Marmoles Izquierdo Los Corrales S.l.",
    "wof:placetype":"venue"
},
  "geometry": {"coordinates":[-4.9842991829,37.1002807617],"type":"Point"}
}