{
  "type": "Feature",
  "properties": {
    "iso:country":"ES",
    "sg:address":"Calle de Hortaleza, 108",
    "sg:city":"Madrid",
    "sg:orig_category":"Asesor\u00cda Sobre Comunicaci\u00d3n De Empresas",
    "sg:phone":"+34 913 19 60 32",
    "sg:postcode":"28004",
    "sg:province":"Madrid",
    "wof:name":"Cano Martinez Carlos",
    "wof:placetype":"venue"
},
  "geometry": {"coordinates":[-3.6973359585,40.4254493713],"type":"Point"}
}