{
  "type": "Feature",
  "properties": {
    "addr:full":"Pol Ind Alhaurin Torre, 57 Alhaurin Torre M\u00e1laga 29130",
    "addr:postcode":"29130",
    "iso:country":"ES",
    "sg:address":"Pol Ind Alhaurin Torre, 57",
    "sg:city":"Alhaurin Torre",
    "sg:orig_category":"Frutas, Legumbres Frescas Y Tempranas (al Por Menor)",
    "sg:phone":"+34 952 41 18 19",
    "sg:postcode":"29130",
    "sg:province":"M\u00e1laga",
    "wof:name":"Sanchez Becerra Hermanos S.l.",
    "wof:placetype":"venue"
},
  "geometry": {"coordinates":[-4.5667190552,36.6618614197],"type":"Point"}
}