{
  "type": "Feature",
  "properties": {
    "iso:country":"ES",
    "sg:address":"Ctra. Sagunto-burgos, Km. 0403,6",
    "sg:city":"S. Leonardo Yag\u00fce",
    "sg:orig_category":"Fabricaci\u00d3n Y Venta De Volquetes Y Remolques",
    "sg:phone":"+34 975 37 64 02",
    "sg:postcode":"42140",
    "sg:province":"Soria",
    "wof:name":"Leon Carretero Jaime",
    "wof:placetype":"venue"
},
  "geometry": {"coordinates":[-3.0625391006,41.8294868469],"type":"Point"}
}