{
  "type": "Feature",
  "properties": {
    "iso:country":"ES",
    "sg:address":"P. Arsenio, S/n",
    "sg:city":"La Alberca",
    "sg:orig_category":"Albergues",
    "sg:phone":"+34 923 41 51 16",
    "sg:postcode":"37624",
    "sg:province":"Salamanca",
    "wof:name":"Hostal La Alberca S.l.",
    "wof:placetype":"venue"
},
  "geometry": {"coordinates":[-6.107945919,40.4883308411],"type":"Point"}
}