{
  "type": "Feature",
  "properties": {
    "iso:country":"ES",
    "sg:address":"Zapateria, 58",
    "sg:city":"Iru\u00f1a",
    "sg:orig_category":"Venta, Alquiler De Instrumentos Y Accesorios De M\u00dasica",
    "sg:phone":"+34 948 22 43 82",
    "sg:postcode":"31001",
    "sg:province":"Navarra",
    "wof:name":"Arilla Piudo Rafael",
    "wof:placetype":"venue"
},
  "geometry": {"coordinates":[-1.6450976133,42.8168563843],"type":"Point"}
}