{
  "type": "Feature",
  "properties": {
    "iso:country":"ES",
    "sg:address":"Col Ducal, S/n",
    "sg:city":"Grau I Platja",
    "sg:orig_category":"M\u00c1quinas De Caf\u00c9 (fabricaci\u00d3n, Al Por Mayor)",
    "sg:phone":"+34 962 84 01 83",
    "sg:postcode":"46730",
    "sg:province":"Valencia",
    "wof:name":"Berzosa Usero Andres",
    "wof:placetype":"venue"
},
  "geometry": {"coordinates":[-0.1666309983,39.0064888],"type":"Point"}
}