{
  "type": "Feature",
  "properties": {
    "addr:full":"Calle de Reyes Amador, 2 Toscas Santa Cruz De Tenerife 38280",
    "addr:housenumber":"2",
    "addr:postcode":"38280",
    "addr:street":"Calle De Reyes Amador",
    "iso:country":"ES",
    "sg:address":"Calle de Reyes Amador, 2",
    "sg:city":"Toscas",
    "sg:orig_category":"Servicios Gsm",
    "sg:phone":"+34 922 15 05 47",
    "sg:postcode":"38280",
    "sg:province":"Santa Cruz De Tenerife",
    "wof:name":"Telecomunicaciones Tegueste S.l.",
    "wof:placetype":"venue"
},
  "geometry": {"coordinates":[-16.3384094238,28.5215549469],"type":"Point"}
}