{
  "type": "Feature",
  "properties": {
    "addr:full":"Carr Joan Lluis Vives, 6 Manises Valencia 46940",
    "addr:housenumber":"6",
    "addr:postcode":"46940",
    "addr:street":"Carr Joan Lluis Vives",
    "iso:country":"ES",
    "sg:address":"Carr Joan Lluis Vives, 6",
    "sg:city":"Manises",
    "sg:orig_category":"Electricidad, Electr\u00d3nica: Suministros (al Por Menor)",
    "sg:phone":"+34 961 54 34 56",
    "sg:postcode":"46940",
    "sg:province":"Valencia",
    "wof:name":"Tecnologia De Sistemas Electronicos Sl",
    "wof:placetype":"venue"
},
  "geometry": {"coordinates":[-0.4521040022,39.4897727966],"type":"Point"}
}