{
  "type": "Feature",
  "properties": {
    "iso:country":"ES",
    "sg:address":"Carrer de Industria, 7",
    "sg:city":"Mas Rampinyo",
    "sg:orig_category":"Metacrilato: Art\u00cdculos (fabricaci\u00d3n Y Al Por Mayor)",
    "sg:phone":"+34 935 75 13 67",
    "sg:postcode":"08110",
    "sg:province":"Barcelona",
    "wof:name":"Artesania Bellmunt S.l.",
    "wof:placetype":"venue"
},
  "geometry": {"coordinates":[2.1792805195,41.4921989441],"type":"Point"}
}