{
  "type": "Feature",
  "properties": {
    "iso:country":"ES",
    "sg:address":"Calle de Chao Do Marco, S/n",
    "sg:city":"Puente De Domingo Florez",
    "sg:orig_category":"Serrer\u00cdas De Madera",
    "sg:phone":"+34 987 46 00 87",
    "sg:postcode":"24380",
    "sg:province":"Le\u00f3n",
    "wof:name":"Maderas Del Rio Cabrera S.l.",
    "wof:placetype":"venue"
},
  "geometry": {"coordinates":[-6.7601056099,42.4204368591],"type":"Point"}
}