{
  "type": "Feature",
  "properties": {
    "addr:full":"Calle de Posito, 10 Adamuz C\u00f3rdoba 14430",
    "addr:housenumber":"10",
    "addr:postcode":"14430",
    "addr:street":"Calle De Posito",
    "iso:country":"ES",
    "sg:address":"Calle de Posito, 10",
    "sg:city":"Adamuz",
    "sg:orig_category":"Asesor\u00cda Sobre Comunicaci\u00d3n De Empresas",
    "sg:phone":"+34 957 16 72 34",
    "sg:postcode":"14430",
    "sg:province":"C\u00f3rdoba",
    "wof:name":"Grac Asesores S.l",
    "wof:placetype":"venue"
},
  "geometry": {"coordinates":[-4.5240907669,38.0272521973],"type":"Point"}
}