{
  "type": "Feature",
  "properties": {
    "addr:full":"Avda Toreros (de Los), 5 Puerto De Santa Maria C\u00e1diz 11500",
    "addr:postcode":"11500",
    "addr:street":"Avda Toreros De Los 5;Ca\u0301Diz",
    "iso:country":"ES",
    "sg:address":"Avda Toreros (de Los), 5",
    "sg:city":"Puerto De Santa Maria",
    "sg:orig_category":"Ropa Para Caballeros (al Por Menor)",
    "sg:phone":"+34 956 87 30 90",
    "sg:postcode":"11500",
    "sg:province":"C\u00e1diz",
    "wof:name":"Robles Cairon Fatima",
    "wof:placetype":"venue"
},
  "geometry": {"coordinates":[-6.2368597984,36.5966072083],"type":"Point"}
}