{
  "type": "Feature",
  "properties": {
    "addr:full":"Calle de Pintor Juan Ruiz, 9 Santa Fe Granada 18320",
    "addr:housenumber":"9",
    "addr:postcode":"18320",
    "addr:street":"Calle De Pintor Juan Ruiz;Fe",
    "iso:country":"ES",
    "sg:address":"Calle de Pintor Juan Ruiz, 9",
    "sg:city":"Santa Fe",
    "sg:orig_category":"Asilos De Ancianos. Centros Privados",
    "sg:phone":"+34 958 44 06 13",
    "sg:postcode":"18320",
    "sg:province":"Granada",
    "wof:name":"Hermanas De Ntra Sra De La Consolacion",
    "wof:placetype":"venue"
},
  "geometry": {"coordinates":[-3.7167060375,37.1869888306],"type":"Point"}
}