{
  "type": "Feature",
  "properties": {
    "iso:country":"ES",
    "sg:address":"Calle de Nueva, 7",
    "sg:city":"Vilamarxant",
    "sg:orig_category":"Ropa De Hogar (al Por Menor)",
    "sg:phone":"+34 962 71 03 23",
    "sg:postcode":"46191",
    "sg:province":"Valencia",
    "wof:name":"Herrero Sanchis Manuel",
    "wof:placetype":"venue"
},
  "geometry": {"coordinates":[-0.6235160232,39.5683670044],"type":"Point"}
}