{
  "type": "Feature",
  "properties": {
    "addr:full":"Avda Talgo, 204 Madrid Madrid 28023",
    "addr:housenumber":"204",
    "addr:postcode":"28023",
    "addr:street":"Avda Talgo",
    "iso:country":"ES",
    "sg:address":"Avda Talgo, 204",
    "sg:city":"Madrid",
    "sg:orig_category":"Centros Empresariales",
    "sg:phone":"+34 913 07 94 28",
    "sg:postcode":"28023",
    "sg:province":"Madrid",
    "wof:name":"Mc Vivar Consultores S.l.",
    "wof:placetype":"venue"
},
  "geometry": {"coordinates":[-3.783798933,40.4475746155],"type":"Point"}
}