{
  "type": "Feature",
  "properties": {
    "addr:full":"Carrer de Creu Dels Molers, 30 Barcelona Barcelona 08004",
    "addr:housenumber":"30",
    "addr:postcode":"08004",
    "addr:street":"Carrer De Creu Dels Molers",
    "iso:country":"ES",
    "sg:address":"Carrer de Creu Dels Molers, 30",
    "sg:city":"Barcelona",
    "sg:orig_category":"Alumbrados",
    "sg:phone":"+34 934 41 61 01",
    "sg:postcode":"08004",
    "sg:province":"Barcelona",
    "wof:name":"Gasch Fernandez Miguel",
    "wof:placetype":"venue"
},
  "geometry": {"coordinates":[2.1614160538,41.3735198975],"type":"Point"}
}