{
  "type": "Feature",
  "properties": {
    "iso:country":"ES",
    "sg:address":"Ctra. P. Alcocer, S/n",
    "sg:city":"Cabeza Buey",
    "sg:orig_category":"Ense\u00d1anza, Formaci\u00d3n Profesional: Aprendizaje",
    "sg:phone":"+34 924 63 23 03",
    "sg:postcode":"06600",
    "sg:province":"Badajoz",
    "wof:name":"Cruz Roja Espa\u00f1ola Asamblea Local",
    "wof:placetype":"venue"
},
  "geometry": {"coordinates":[-5.2242388725,38.7196540833],"type":"Point"}
}