{
  "type": "Feature",
  "properties": {
    "iso:country":"ES",
    "sg:address":"Pla\u00c7 Font De Santa Margalida, S/n",
    "sg:city":"Felanitx",
    "sg:orig_category":"Iglesia Cat\u00d3lica",
    "sg:phone":"+34 971 58 00 56",
    "sg:postcode":"07200",
    "sg:province":"Islas Baleares",
    "wof:name":"Obispado De Mallorca",
    "wof:placetype":"venue"
},
  "geometry": {"coordinates":[3.1478869915,39.4685134888],"type":"Point"}
}