{
  "type": "Feature",
  "properties": {
    "iso:country":"ES",
    "sg:address":"Calle de Castilla, 1",
    "sg:city":"Madrid",
    "sg:orig_category":"Animales (al Por Menor)",
    "sg:phone":"+34 914 50 05 03",
    "sg:postcode":"28039",
    "sg:province":"Madrid",
    "wof:name":"Fuente Hernan Andres De La",
    "wof:placetype":"venue"
},
  "geometry": {"coordinates":[-3.7035245895,40.4528808594],"type":"Point"}
}