{
  "type": "Feature",
  "properties": {
    "addr:full":"Del Sol-sotrondio, 3 Rey Aurelio Asturias 33950",
    "addr:housenumber":"3",
    "addr:postcode":"33950",
    "addr:street":"Rey Aurelio Asturias",
    "iso:country":"ES",
    "sg:address":"Del Sol-sotrondio, 3",
    "sg:city":"Rey Aurelio",
    "sg:orig_category":"Relojer\u00cda (al Por Menor, Reparaci\u00d3n)",
    "sg:phone":"+34 985 67 07 46",
    "sg:postcode":"33950",
    "sg:province":"Asturias",
    "wof:name":"Perez Fernandez Mariana Marta",
    "wof:placetype":"venue"
},
  "geometry": {"coordinates":[-5.6041841507,43.2750015259],"type":"Point"}
}