{
  "type": "Feature",
  "properties": {
    "iso:country":"ES",
    "sg:address":"Calle de Carmelo Gil Doctores, 8",
    "sg:city":"Bilbao",
    "sg:orig_category":"Agencias Y Agentes Comerciales, Representantes",
    "sg:phone":"+34 944 21 18 92",
    "sg:postcode":"48012",
    "sg:province":"Vizcaya",
    "wof:name":"Vega Ruiz Jose Antonio",
    "wof:placetype":"venue"
},
  "geometry": {"coordinates":[-2.9401919842,43.2564964294],"type":"Point"}
}