{
  "type": "Feature",
  "properties": {
    "addr:full":"Ctra Madrid-cadiz, Km. 0509,0 Carmona Sevilla 41410",
    "addr:postcode":"41410",
    "addr:street":"Ctra Madrid-Cadiz Km. 0509,0",
    "iso:country":"ES",
    "sg:address":"Ctra Madrid-cadiz, Km. 0509,0",
    "sg:city":"Carmona",
    "sg:orig_category":"Venta, Montaje De Neum\u00c1ticos",
    "sg:phone":"+34 954 14 25 80",
    "sg:postcode":"41410",
    "sg:province":"Sevilla",
    "wof:name":"Perez Perez Manuel",
    "wof:placetype":"venue"
},
  "geometry": {"coordinates":[-5.6433792114,37.4708709717],"type":"Point"}
}