{
  "type": "Feature",
  "properties": {
    "addr:full":"Calle de Presbitero Emilio Garcia, 7 San Mateo Murcia 30800",
    "addr:housenumber":"7",
    "addr:postcode":"30800",
    "addr:street":"Calle De Presbitero Emilio Garcia",
    "iso:country":"ES",
    "sg:address":"Calle de Presbitero Emilio Garcia, 7",
    "sg:city":"San Mateo",
    "sg:orig_category":"Promotores Constructores",
    "sg:phone":"+34 968 46 16 25",
    "sg:postcode":"30800",
    "sg:province":"Murcia",
    "wof:name":"Construcciones Martin Carrillo S. A.",
    "wof:placetype":"venue"
},
  "geometry": {"coordinates":[-1.6905640364,37.680557251],"type":"Point"}
}