{
  "type": "Feature",
  "properties": {
    "iso:country":"ES",
    "sg:address":"Carrer de Girona, 155",
    "sg:city":"Barcelona",
    "sg:orig_category":"Perfumer\u00cda Y Cosm\u00c9tica (fabricaci\u00d3n, Al Por Mayor)",
    "sg:phone":"+34 932 07 33 94",
    "sg:postcode":"08037",
    "sg:province":"Barcelona",
    "wof:name":"Abba Cosmetics S.l.",
    "wof:placetype":"venue"
},
  "geometry": {"coordinates":[2.165717,41.398891],"type":"Point"}
}