{
  "type": "Feature",
  "properties": {
    "iso:country":"ES",
    "sg:address":"Rua Castelao, 177",
    "sg:city":"Grove",
    "sg:orig_category":"Inmobiliaria (agencias)",
    "sg:phone":"+34 986 73 31 20",
    "sg:postcode":"36980",
    "sg:province":"Pontevedra",
    "sg:website":"www.calumbra.com",
    "wof:name":"C'alumbra Service S.l.",
    "wof:placetype":"venue"
},
  "geometry": {"coordinates":[-8.858259201,42.4904518127],"type":"Point"}
}