{
  "type": "Feature",
  "properties": {
    "addr:full":"Paulo Vi Auzunea, 14 Azpeitia Guip\u00f9zcoa 20730",
    "addr:housenumber":"14",
    "addr:postcode":"20730",
    "addr:street":"Paulo Vi Auzunea;Guipu\u0300Zcoa",
    "iso:country":"ES",
    "sg:address":"Paulo Vi Auzunea, 14",
    "sg:city":"Azpeitia",
    "sg:orig_category":"Panader\u00cdas, Panader\u00cdas",
    "sg:phone":"+34 943 81 66 70",
    "sg:postcode":"20730",
    "sg:province":"Guip\u00f9zcoa",
    "wof:name":"Luloaga Aguirre Margarita",
    "wof:placetype":"venue"
},
  "geometry": {"coordinates":[-2.2665359974,43.1807174683],"type":"Point"}
}