{
  "type": "Feature",
  "properties": {
    "iso:country":"ES",
    "sg:address":"Calle de Islas Cies, 11",
    "sg:city":"Madrid",
    "sg:orig_category":"Producci\u00d3n De Abonos Y De Fertilizantes",
    "sg:phone":"+34 917 30 02 08",
    "sg:postcode":"28035",
    "sg:province":"Madrid",
    "wof:name":"Garrido Godino Pedro",
    "wof:placetype":"venue"
},
  "geometry": {"coordinates":[-3.7179439068,40.480884552],"type":"Point"}
}