{
  "type": "Feature",
  "properties": {
    "addr:full":"Avda Cid, 25 Valencia Valencia 46018",
    "addr:housenumber":"25",
    "addr:postcode":"46018",
    "addr:street":"Avda Cid",
    "iso:country":"ES",
    "sg:address":"Avda Cid, 25",
    "sg:city":"Valencia",
    "sg:orig_category":"Agentes, Concesionarios Y Sucursales De Veh\u00cdculos",
    "sg:phone":"+34 963 84 37 04",
    "sg:postcode":"46018",
    "sg:province":"Valencia",
    "sg:website":"www.mmcelevante.com",
    "wof:name":"Mmc Levante",
    "wof:placetype":"venue"
},
  "geometry": {"coordinates":[-0.3941400051,39.4675941467],"type":"Point"}
}