{
  "type": "Feature",
  "properties": {
    "iso:country":"ES",
    "sg:address":"Avda Manantiales De Los, 25",
    "sg:city":"Torremolinos",
    "sg:orig_category":"Electrodom\u00c9sticos (al Por Menor)",
    "sg:phone":"+34 952 38 78 21",
    "sg:postcode":"29620",
    "sg:province":"M\u00e1laga",
    "wof:name":"Bazar San Juan S.a.",
    "wof:placetype":"venue"
},
  "geometry": {"coordinates":[-4.5031270981,36.6274871826],"type":"Point"}
}