{
  "type": "Feature",
  "properties": {
    "addr:full":"Calle de Real, 63 Lanjaron Granada 18420",
    "addr:housenumber":"63",
    "addr:postcode":"18420",
    "addr:street":"Calle De Real",
    "iso:country":"ES",
    "sg:address":"Calle de Real, 63",
    "sg:city":"Lanjaron",
    "sg:orig_category":"Formaci\u00d3n Continuada (variada)",
    "sg:phone":"+34 958 77 21 81",
    "sg:postcode":"18420",
    "sg:province":"Granada",
    "wof:name":"Rodriguez Perez Francisco",
    "wof:placetype":"venue"
},
  "geometry": {"coordinates":[-3.4827239513,36.9177207947],"type":"Point"}
}