{
  "type": "Feature",
  "properties": {
    "iso:country":"ES",
    "sg:address":"Del Mar, 27",
    "sg:city":"Torre Mar",
    "sg:orig_category":"Inmobiliaria (agencias)",
    "sg:phone":"+34 952 54 64 39",
    "sg:postcode":"29740",
    "sg:province":"M\u00e1laga",
    "wof:name":"Hermanos Jaime Sanchez C.b.",
    "wof:placetype":"venue"
},
  "geometry": {"coordinates":[-4.3588647842,36.7196998596],"type":"Point"}
}