{
  "type": "Feature",
  "properties": {
    "iso:country":"ES",
    "sg:address":"Avda Coru\u00d1a (a), S/n",
    "sg:city":"Santa Uxia De Ribeira",
    "sg:orig_category":"Bisuter\u00cda, Joyer\u00cda, Relojer\u00cda (al Por Menor)",
    "sg:phone":"+34 981 83 52 23",
    "sg:postcode":"15960",
    "sg:province":"La Coru\u00f1a",
    "wof:name":"Joyeria Jose Luis S. L.",
    "wof:placetype":"venue"
},
  "geometry": {"coordinates":[-8.9924879074,42.5627288818],"type":"Point"}
}