{
  "type": "Feature",
  "properties": {
    "addr:full":"Calle de Real, 83 Calzada Calatrava Ciudad Real 13370",
    "addr:housenumber":"83",
    "addr:postcode":"13370",
    "addr:street":"Calle De Real",
    "iso:country":"ES",
    "sg:address":"Calle de Real, 83",
    "sg:city":"Calzada Calatrava",
    "sg:orig_category":"Farmacias",
    "sg:phone":"+34 926 87 53 63",
    "sg:postcode":"13370",
    "sg:province":"Ciudad Real",
    "wof:name":"Ciudad Gonzalez Maria Luisa",
    "wof:placetype":"venue"
},
  "geometry": {"coordinates":[-3.7789990902,38.7063713074],"type":"Point"}
}