{
  "type": "Feature",
  "properties": {
    "iso:country":"ES",
    "sg:address":"Calle de Alfonso Arguelles, 14",
    "sg:city":"Langreo",
    "sg:orig_category":"Bazares, Art\u00cdculos De Limpieza Y De Cocina (al Por Menor)",
    "sg:phone":"+34 985 67 45 45",
    "sg:postcode":"33930",
    "sg:province":"Asturias",
    "wof:name":"Garcia Fernandez C.b.",
    "wof:placetype":"venue"
},
  "geometry": {"coordinates":[-5.6922287941,43.3117370605],"type":"Point"}
}