{
  "type": "Feature",
  "properties": {
    "iso:country":"ES",
    "sg:address":"Calle de Sociedad, 11",
    "sg:city":"San Bartolome",
    "sg:orig_category":"Ropa Para Ni\u00d1os (al Por Menor)",
    "sg:phone":"+34 968 21 74 69",
    "sg:postcode":"30004",
    "sg:province":"Murcia",
    "wof:name":"Dolores Martinez Perez Isabel Martinez Alcantara C.b.",
    "wof:placetype":"venue"
},
  "geometry": {"coordinates":[-1.1306350231,37.9846191406],"type":"Point"}
}