{
  "type": "Feature",
  "properties": {
    "addr:full":"Av Meridiana, 386 Barcelona Barcelona 08030",
    "addr:housenumber":"386",
    "addr:postcode":"08030",
    "addr:street":"Meridiana",
    "iso:country":"ES",
    "sg:address":"Av Meridiana, 386",
    "sg:city":"Barcelona",
    "sg:orig_category":"Reposter\u00cdas",
    "sg:phone":"+34 933 53 47 99",
    "sg:postcode":"08030",
    "sg:province":"Barcelona",
    "wof:name":"Jaime Bou S.a.",
    "wof:placetype":"venue"
},
  "geometry": {"coordinates":[2.1834919453,41.4299087524],"type":"Point"}
}