{
  "type": "Feature",
  "properties": {
    "addr:full":"Calle de Conde De Santa Barbara De Lugones, S/n Pola De Siero Asturias 33510",
    "addr:housenumber":"s / n",
    "addr:postcode":"33510",
    "addr:street":"Calle De Conde De Santa;Lugones",
    "iso:country":"ES",
    "sg:address":"Calle de Conde De Santa Barbara De Lugones, S/n",
    "sg:city":"Pola De Siero",
    "sg:orig_category":"Bisuter\u00cda, Joyer\u00cda, Relojer\u00cda (al Por Menor)",
    "sg:phone":"+34 985 72 05 47",
    "sg:postcode":"33510",
    "sg:province":"Asturias",
    "wof:name":"Alvarez Quiros S.l.",
    "wof:placetype":"venue"
},
  "geometry": {"coordinates":[-5.6619114876,43.3930053711],"type":"Point"}
}