{
  "type": "Feature",
  "properties": {
    "addr:full":"Calle de San Blas, 41 Granada Granada 18013",
    "addr:housenumber":"41",
    "addr:postcode":"18013",
    "addr:street":"Calle De San Blas",
    "iso:country":"ES",
    "sg:address":"Calle de San Blas, 41",
    "sg:city":"Granada",
    "sg:orig_category":"Asociaciones Humanitarias, De Cooperaci\u00d3n, De Acci\u00d3n Social",
    "sg:phone":"+34 958 15 94 87",
    "sg:postcode":"18013",
    "sg:province":"Granada",
    "wof:name":"Asociacion Ocrem",
    "wof:placetype":"venue"
},
  "geometry": {"coordinates":[-3.6056900024,37.1958961487],"type":"Point"}
}