{
  "type": "Feature",
  "properties": {
    "addr:full":"Carr Santa Eugenia, 36 Girona Girona 17005",
    "addr:housenumber":"36",
    "addr:postcode":"17005",
    "addr:street":"Carr Santa Eugenia",
    "iso:country":"ES",
    "sg:address":"Carr Santa Eugenia, 36",
    "sg:city":"Girona",
    "sg:orig_category":"Molduras, Junquillos, Listones Y Molduras Perforadas",
    "sg:phone":"+34 972 20 30 85",
    "sg:postcode":"17005",
    "sg:province":"Girona",
    "wof:name":"Alonso Soms Pedro",
    "wof:placetype":"venue"
},
  "geometry": {"coordinates":[2.8171629906,41.9816055298],"type":"Point"}
}