{
  "type": "Feature",
  "properties": {
    "iso:country":"ES",
    "sg:address":"C/ Industria, 16",
    "sg:city":"Ripollet",
    "sg:orig_category":"Ferreter\u00cda (diversos)",
    "sg:phone":"+34 935 80 11 88",
    "sg:postcode":"08291",
    "sg:province":"Barcelona",
    "wof:name":"Maquirecsa S.l.",
    "wof:placetype":"venue"
},
  "geometry": {"coordinates":[2.1636760235,41.4934501648],"type":"Point"}
}