{
  "type": "Feature",
  "properties": {
    "addr:full":"Calle de Ciudad De Toledo, 21 Miranda Ebro Burgos 09200",
    "addr:housenumber":"21",
    "addr:postcode":"09200",
    "addr:street":"Calle De Ciudad De Toledo",
    "iso:country":"ES",
    "sg:address":"Calle de Ciudad De Toledo, 21",
    "sg:city":"Miranda Ebro",
    "sg:orig_category":"Venta, Colocaci\u00d3n, Reparaci\u00d3n De Parabrisas, Techos Descapotables",
    "sg:phone":"+34 947 33 21 97",
    "sg:postcode":"09200",
    "sg:province":"Burgos",
    "wof:name":"Fernandez Aja Luis Carlos",
    "wof:placetype":"venue"
},
  "geometry": {"coordinates":[-2.9504711628,42.6870040894],"type":"Point"}
}