{
  "type": "Feature",
  "properties": {
    "addr:full":"Plaz Vicente B. Iba\u00d1ez, 3 Paiporta Valencia 46200",
    "addr:housenumber":"3",
    "addr:postcode":"46200",
    "addr:street":"Plaz;B. Iban\u0303Ez",
    "iso:country":"ES",
    "sg:address":"Plaz Vicente B. Iba\u00d1ez, 3",
    "sg:city":"Paiporta",
    "sg:orig_category":"Agencias Y Agentes Comerciales, Representantes",
    "sg:phone":"+34 963 97 00 73",
    "sg:postcode":"46200",
    "sg:province":"Valencia",
    "wof:name":"Ribes Mateu Antonio Carlos",
    "wof:placetype":"venue"
},
  "geometry": {"coordinates":[-0.4180389941,39.4297714233],"type":"Point"}
}