{
  "type": "Feature",
  "properties": {
    "iso:country":"ES",
    "sg:address":"Calle de Alonso Nu\u00d1ez, 1",
    "sg:city":"Sanlucar De Barrameda",
    "sg:orig_category":"Abogados",
    "sg:phone":"+34 956 38 31 86",
    "sg:postcode":"11540",
    "sg:province":"C\u00e1diz",
    "wof:name":"Palma Macias Isabel Maria",
    "wof:placetype":"venue"
},
  "geometry": {"coordinates":[-6.3543815613,36.7797050476],"type":"Point"}
}