{
  "type": "Feature",
  "properties": {
    "addr:full":"Carrer de Joan Carles I, 14 Roda De Bara Tarragona 43883",
    "addr:housenumber":"14",
    "addr:postcode":"43883",
    "addr:street":"Carrer De Joan Carles I",
    "iso:country":"ES",
    "sg:address":"Carrer de Joan Carles I, 14",
    "sg:city":"Roda De Bara",
    "sg:orig_category":"Empresas De Pintura Y Revestimientos",
    "sg:phone":"+34 977 65 70 34",
    "sg:postcode":"43883",
    "sg:province":"Tarragona",
    "wof:name":"Ciuro G\u00fcell Luis",
    "wof:placetype":"venue"
},
  "geometry": {"coordinates":[1.4562339783,41.1852416992],"type":"Point"}
}