{
  "type": "Feature",
  "properties": {
    "addr:full":"Carr Pavello, S/n Begur Girona 17255",
    "addr:housenumber":"s / n",
    "addr:postcode":"17255",
    "addr:street":"Carr Pavello",
    "iso:country":"ES",
    "sg:address":"Carr Pavello, S/n",
    "sg:city":"Begur",
    "sg:orig_category":"Ense\u00d1anza, Formaci\u00d3n Profesional: Aprendizaje",
    "sg:phone":"+34 972 62 34 84",
    "sg:postcode":"17255",
    "sg:province":"Girona",
    "wof:name":"Ajuntament De Begur",
    "wof:placetype":"venue"
},
  "geometry": {"coordinates":[3.2027256489,41.9517631531],"type":"Point"}
}