{
  "type": "Feature",
  "properties": {
    "iso:country":"ES",
    "sg:address":"Calle de Carmen La Suspira, 19",
    "sg:city":"San Jose Rinconada",
    "sg:orig_category":"Molduras, Junquillos, Listones Y Molduras Perforadas",
    "sg:phone":"+34 955 79 12 87",
    "sg:postcode":"41300",
    "sg:province":"Sevilla",
    "wof:name":"Caballero Gallego Encarnacion",
    "wof:placetype":"venue"
},
  "geometry": {"coordinates":[-5.9421591759,37.4862365723],"type":"Point"}
}