{
  "type": "Feature",
  "properties": {
    "addr:full":"Calle de Fuentevaqueros (de), 47 Fuenlabrada Madrid 28944",
    "addr:housenumber":"47",
    "addr:postcode":"28944",
    "addr:street":"Calle De Fuentevaqueros De",
    "iso:country":"ES",
    "sg:address":"Calle de Fuentevaqueros (de), 47",
    "sg:city":"Fuenlabrada",
    "sg:orig_category":"Peluqueros: De Se\u00d1oras",
    "sg:phone":"+34 916 97 40 97",
    "sg:postcode":"28944",
    "sg:province":"Madrid",
    "wof:name":"Fashion Hair Estilistas S.l.",
    "wof:placetype":"venue"
},
  "geometry": {"coordinates":[-3.7895181179,40.2755279541],"type":"Point"}
}