{
  "type": "Feature",
  "properties": {
    "addr:full":"Calle de Lavaderos, 3 Cuellar Segovia 40200",
    "addr:housenumber":"3",
    "addr:postcode":"40200",
    "addr:street":"Calle De Lavaderos",
    "iso:country":"ES",
    "sg:address":"Calle de Lavaderos, 3",
    "sg:city":"Cuellar",
    "sg:orig_category":"Contenedores (mercanc\u00cdas)",
    "sg:phone":"+34 921 14 09 77",
    "sg:postcode":"40200",
    "sg:province":"Segovia",
    "wof:name":"Sanfesa S.l.",
    "wof:placetype":"venue"
},
  "geometry": {"coordinates":[-4.3134989738,41.4028968811],"type":"Point"}
}