{
  "type": "Feature",
  "properties": {
    "addr:full":"Rua Aragon, 236 Vigo Pontevedra 36207",
    "addr:housenumber":"236",
    "addr:postcode":"36207",
    "addr:street":"Rua Aragon",
    "iso:country":"ES",
    "sg:address":"Rua Aragon, 236",
    "sg:city":"Vigo",
    "sg:orig_category":"Revisi\u00d3n, Reconstrucci\u00d3n De M\u00c1quinas Y Herramientas",
    "sg:phone":"+34 986 37 29 83",
    "sg:postcode":"36207",
    "sg:province":"Pontevedra",
    "wof:name":"Asnigo 2 S.l.",
    "wof:placetype":"venue"
},
  "geometry": {"coordinates":[-8.6979532242,42.2429084778],"type":"Point"}
}