{
  "type": "Feature",
  "properties": {
    "addr:full":"Rambla (la), 405 Mataro Barcelona 08301",
    "addr:housenumber":"405",
    "addr:postcode":"08301",
    "addr:street":"Rambla La",
    "iso:country":"ES",
    "sg:address":"Rambla (la), 405",
    "sg:city":"Mataro",
    "sg:orig_category":"Bisuter\u00cda, Joyer\u00cda, Relojer\u00cda (al Por Menor)",
    "sg:phone":"+34 937 90 39 49",
    "sg:postcode":"08301",
    "sg:province":"Barcelona",
    "sg:website":"www.yellowpages.coil/ayala-bar",
    "wof:name":"Amselem  Salomon",
    "wof:placetype":"venue"
},
  "geometry": {"coordinates":[2.4437954426,41.5367469788],"type":"Point"}
}