{
  "type": "Feature",
  "properties": {
    "addr:full":"Pase Serapio Mugica De, 31 Donostia-san Sebastian Guip\u00f9zcoa 20016",
    "addr:housenumber":"31",
    "addr:postcode":"20016",
    "addr:street":"Serapio Mugica De",
    "iso:country":"ES",
    "sg:address":"Pase Serapio Mugica De, 31",
    "sg:city":"Donostia-san Sebastian",
    "sg:orig_category":"Ense\u00d1anza Secundaria: Colegios Y Escuelas Privadas",
    "sg:phone":"+34 943 39 02 40",
    "sg:postcode":"20016",
    "sg:province":"Guip\u00f9zcoa",
    "wof:name":"Bidebietako Batxiler Institutoa",
    "wof:placetype":"venue"
},
  "geometry": {"coordinates":[-1.9446959496,43.3238601685],"type":"Point"}
}