{
  "type": "Feature",
  "properties": {
    "iso:country":"ES",
    "sg:address":"Avda Comandante Benitez, 14",
    "sg:city":"Malaga",
    "sg:orig_category":"Producci\u00d3n, Distribuci\u00d3n De Gas Butano Y Propano",
    "sg:phone":"+34 952 21 15 21",
    "sg:postcode":"29001",
    "sg:province":"M\u00e1laga",
    "wof:name":"Gibralfaro Gas. S.l.",
    "wof:placetype":"venue"
},
  "geometry": {"coordinates":[-4.4257054329,36.7144126892],"type":"Point"}
}