{
  "type": "Feature",
  "properties": {
    "iso:country":"ES",
    "sg:address":"Carrer de Sant Rafel, 24",
    "sg:city":"Olot",
    "sg:orig_category":"Panader\u00cdas, Panader\u00cdas",
    "sg:phone":"+34 972 26 04 92",
    "sg:postcode":"17800",
    "sg:province":"Girona",
    "wof:name":"Rougel S.cv.",
    "wof:placetype":"venue"
},
  "geometry": {"coordinates":[2.4867470264,42.1815605164],"type":"Point"}
}