{
  "type": "Feature",
  "properties": {
    "iso:country":"ES",
    "sg:address":"Calle de Principe De Vergara, 42",
    "sg:city":"Madrid",
    "sg:orig_category":"Ense\u00d1anza Variada",
    "sg:phone":"+34 915 77 50 62",
    "sg:postcode":"28001",
    "sg:province":"Madrid",
    "wof:name":"Ceaec",
    "wof:placetype":"venue"
},
  "geometry": {"coordinates":[-3.6797330379,40.4282035828],"type":"Point"}
}