{
  "type": "Feature",
  "properties": {
    "iso:country":"ES",
    "sg:address":"Carr Estatut, 53",
    "sg:city":"Benicasim",
    "sg:orig_category":"T\u00c9cnicos Veterinarios",
    "sg:phone":"+34 964 30 55 64",
    "sg:postcode":"12560",
    "sg:province":"Castell\u00f3n",
    "wof:name":"Gargallo Gargallo Luis Miguel",
    "wof:placetype":"venue"
},
  "geometry": {"coordinates":[0.0607100017,40.052482605],"type":"Point"}
}