{
  "type": "Feature",
  "properties": {
    "addr:full":"Calle de Arandillas, 17 Ba\u00e7os De Valdearados Burgos 09450",
    "addr:housenumber":"17",
    "addr:postcode":"09450",
    "addr:street":"Calle De Arandillas",
    "iso:country":"ES",
    "sg:address":"Calle de Arandillas, 17",
    "sg:city":"Ba\u00e7os De Valdearados",
    "sg:orig_category":"Iglesia Cat\u00d3lica",
    "sg:phone":"+34 947 53 43 87",
    "sg:postcode":"09450",
    "sg:province":"Burgos",
    "wof:name":"Parroquia Nuestra Se\u00f1ora De La Asuncion",
    "wof:placetype":"venue"
},
  "geometry": {"coordinates":[-3.6997311115,42.3408737183],"type":"Point"}
}