{
  "type": "Feature",
  "properties": {
    "iso:country":"ES",
    "sg:address":"Carr Guilleries, 23",
    "sg:city":"Blanes",
    "sg:orig_category":"Peluquer\u00cdas, Peluquer\u00cda Mixta",
    "sg:phone":"+34 972 35 28 06",
    "sg:postcode":"17300",
    "sg:province":"Girona",
    "wof:name":"Mollfulleda Floris Dolores",
    "wof:placetype":"venue"
},
  "geometry": {"coordinates":[2.7809910774,41.6715087891],"type":"Point"}
}