{
  "type": "Feature",
  "properties": {
    "addr:full":"Plaz Alfonso El Magnanimo, 11 Valencia Valencia 46003",
    "addr:housenumber":"11",
    "addr:postcode":"46003",
    "addr:street":"Plaz Alfonso El Magnanimo",
    "iso:country":"ES",
    "sg:address":"Plaz Alfonso El Magnanimo, 11",
    "sg:city":"Valencia",
    "sg:orig_category":"Asociaciones, Organismos Culturales Y Socioeducativos",
    "sg:phone":"+34 963 51 61 06",
    "sg:postcode":"46003",
    "sg:province":"Valencia",
    "wof:name":"Sociedad Filarmonica",
    "wof:placetype":"venue"
},
  "geometry": {"coordinates":[-0.3711490035,39.4717903137],"type":"Point"}
}