{
  "type": "Feature",
  "properties": {
    "addr:full":"Calle de Calibre, 52 Estacion Madrid 28400",
    "addr:housenumber":"52",
    "addr:postcode":"28400",
    "addr:street":"Calle De Calibre",
    "iso:country":"ES",
    "sg:address":"Calle de Calibre, 52",
    "sg:city":"Estacion",
    "sg:orig_category":"Venta, Colocaci\u00d3n, Reparaci\u00d3n De Radiadores Para Veh\u00cdculos",
    "sg:phone":"+34 918 50 85 72",
    "sg:postcode":"28400",
    "sg:province":"Madrid",
    "wof:name":"Matias Cruz Esteban",
    "wof:placetype":"venue"
},
  "geometry": {"coordinates":[-3.7003455162,40.4166908264],"type":"Point"}
}