{
  "type": "Feature",
  "properties": {
    "addr:full":"Avda Alfonso Vi, 12 Salamanca Salamanca 37005",
    "addr:housenumber":"12",
    "addr:postcode":"37005",
    "addr:street":"Avda Alfonso Vi",
    "iso:country":"ES",
    "sg:address":"Avda Alfonso Vi, 12",
    "sg:city":"Salamanca",
    "sg:orig_category":"Estancos",
    "sg:phone":"+34 923 22 24 98",
    "sg:postcode":"37005",
    "sg:province":"Salamanca",
    "wof:name":"Lucas Arenales Alberto",
    "wof:placetype":"venue"
},
  "geometry": {"coordinates":[-5.660610199,40.9760513306],"type":"Point"}
}