{
  "type": "Feature",
  "properties": {
    "iso:country":"ES",
    "sg:address":"Plaz Alcalde Agatangelo Soler, 7",
    "sg:city":"Alacant",
    "sg:orig_category":"Promotores Constructores",
    "sg:phone":"+34 965 24 06 31",
    "sg:postcode":"03012",
    "sg:province":"Alicante",
    "wof:name":"Acsa Obras E Infraestructuras S.a.",
    "wof:placetype":"venue"
},
  "geometry": {"coordinates":[-0.4804682136,38.3654060364],"type":"Point"}
}