{
  "type": "Feature",
  "properties": {
    "iso:country":"ES",
    "sg:address":"Calle de Samaniego, 12",
    "sg:city":"Valencia",
    "sg:orig_category":"Bronces Y Cobre Para Amueblado",
    "sg:phone":"+34 963 91 61 26",
    "sg:postcode":"46003",
    "sg:province":"Valencia",
    "wof:name":"Herrera Rodriguez Luis",
    "wof:placetype":"venue"
},
  "geometry": {"coordinates":[-0.3758960068,39.4777069092],"type":"Point"}
}