{
  "type": "Feature",
  "properties": {
    "addr:full":"Carrer de Numancia, 143 Barcelona Barcelona 08029",
    "addr:housenumber":"143",
    "addr:postcode":"08029",
    "addr:street":"Carrer De Numancia",
    "iso:country":"ES",
    "sg:address":"Carrer de Numancia, 143",
    "sg:city":"Barcelona",
    "sg:orig_category":"Grafistas",
    "sg:phone":"+34 933 63 07 97",
    "sg:postcode":"08029",
    "sg:province":"Barcelona",
    "wof:name":"Movi-grup-disseny S.l.",
    "wof:placetype":"venue"
},
  "geometry": {"coordinates":[2.1342670918,41.3877563477],"type":"Point"}
}