{
  "type": "Feature",
  "properties": {
    "iso:country":"ES",
    "sg:address":"Avda General Sanjurjo, 290",
    "sg:city":"Coru\u00d1a",
    "sg:orig_category":"Fabricaci\u00d3n De Art\u00cdculos Y Equipos Deportivos Y De Ocio",
    "sg:phone":"+34 981 13 32 67",
    "sg:postcode":"15006",
    "sg:province":"La Coru\u00f1a",
    "wof:name":"Ocio Galicia S.l.",
    "wof:placetype":"venue"
},
  "geometry": {"coordinates":[-8.3891096115,43.3508300781],"type":"Point"}
}