{
  "type": "Feature",
  "properties": {
    "iso:country":"ES",
    "sg:address":"Calle de Sol, 30",
    "sg:city":"Pe\u00e7arroya-pueblonuevo",
    "sg:orig_category":"Bares, Piano",
    "sg:phone":"+34 957 57 10 80",
    "sg:postcode":"14200",
    "sg:province":"C\u00f3rdoba",
    "wof:name":"Monterroso Madue\u00f1o Elena",
    "wof:placetype":"venue"
},
  "geometry": {"coordinates":[-5.2624988556,38.296421051],"type":"Point"}
}