{
  "type": "Feature",
  "properties": {
    "iso:country":"ES",
    "sg:address":"Calle de Padilla, 10",
    "sg:city":"Villafranca De Los Caballeros",
    "sg:orig_category":"Cr\u00cda De Animales",
    "sg:phone":"+34 926 57 80 85",
    "sg:postcode":"45730",
    "sg:province":"Toledo",
    "wof:name":"Jimeno Sanchez Rosalia",
    "wof:placetype":"venue"
},
  "geometry": {"coordinates":[-3.362308979,39.4288482666],"type":"Point"}
}