{
  "type": "Feature",
  "properties": {
    "addr:full":"Calle de Estartetxe, 14 Estartetxe Vizcaya 48940",
    "addr:housenumber":"14",
    "addr:postcode":"48940",
    "addr:street":"Calle De Estartetxe",
    "iso:country":"ES",
    "sg:address":"Calle de Estartetxe, 14",
    "sg:city":"Estartetxe",
    "sg:orig_category":"Ense\u00d1anza Variada",
    "sg:phone":"+34 944 63 63 80",
    "sg:postcode":"48940",
    "sg:province":"Vizcaya",
    "wof:name":"Lete Lombardero Isabel",
    "wof:placetype":"venue"
},
  "geometry": {"coordinates":[-2.9860789776,43.3275489807],"type":"Point"}
}