{
  "type": "Feature",
  "properties": {
    "addr:full":"Avenida De Cabuerniga, 12 Torrelavega Cantabria 39300",
    "addr:housenumber":"12",
    "addr:postcode":"39300",
    "addr:street":"Avenida De Cabuerniga",
    "iso:country":"ES",
    "sg:address":"Avenida De Cabuerniga, 12",
    "sg:city":"Torrelavega",
    "sg:orig_category":"Zapatos (al Por Menor)",
    "sg:phone":"+34 942 80 36 51",
    "sg:postcode":"39300",
    "sg:province":"Cantabria",
    "wof:name":"Ruiloba Sordo Francisco Javier",
    "wof:placetype":"venue"
},
  "geometry": {"coordinates":[-4.0522031784,43.3405952454],"type":"Point"}
}