{
  "type": "Feature",
  "properties": {
    "iso:country":"ES",
    "sg:address":"Carrer de Pujos, 48",
    "sg:city":"Hospitalet Llobregat",
    "sg:orig_category":"Puertas Y Portales",
    "sg:phone":"+34 933 33 61 79",
    "sg:postcode":"08904",
    "sg:province":"Barcelona",
    "wof:name":"Gonzalez Dominguez Antonio",
    "wof:placetype":"venue"
},
  "geometry": {"coordinates":[2.1178939342,41.3730926514],"type":"Point"}
}