{
  "type": "Feature",
  "properties": {
    "iso:country":"ES",
    "sg:address":"Calle de Nueve De Febrero, 5",
    "sg:city":"Le\u00f3n",
    "sg:orig_category":"Metalurgia",
    "sg:phone":"+34 987 20 48 52",
    "sg:postcode":"24005",
    "sg:province":"Le\u00f3n",
    "wof:name":"Garcia Fernandez Gabino",
    "wof:placetype":"venue"
},
  "geometry": {"coordinates":[-5.5678272247,42.5878334045],"type":"Point"}
}