{
  "type": "Feature",
  "properties": {
    "iso:country":"ES",
    "sg:address":"Plaz San Pedro, 3",
    "sg:city":"Sestao",
    "sg:orig_category":"Librer\u00cdas",
    "sg:phone":"+34 944 01 39 26",
    "sg:postcode":"48910",
    "sg:province":"Vizcaya",
    "wof:name":"Milagros Somovilla Aranjuelo (libreria Lizartza)",
    "wof:placetype":"venue"
},
  "geometry": {"coordinates":[-3.005407095,43.3081970215],"type":"Point"}
}