{
  "type": "Feature",
  "properties": {
    "iso:country":"ES",
    "sg:address":"Rua Horreo (do), 21",
    "sg:city":"Santiago De Compostela",
    "sg:orig_category":"Inmobiliaria (agencias)",
    "sg:phone":"+34 981 56 15 87",
    "sg:postcode":"15702",
    "sg:province":"A Coru\u00f1a",
    "wof:name":"Zielsa S.a.",
    "wof:placetype":"venue"
},
  "geometry": {"coordinates":[-8.5439796448,42.8757362366],"type":"Point"}
}