{
  "type": "Feature",
  "properties": {
    "iso:country":"ES",
    "sg:address":"Carrer de Muntaner, 388",
    "sg:city":"Barcelona",
    "sg:classifiers":[
        {
            "category":"Arts & Performance",
            "subcategory":"Art Gallery",
            "type":"Entertainment"
        }
    ],
    "sg:phone":"+34 932 01 77 51",
    "sg:postcode":"08006",
    "sg:province":"Barcelona",
    "sg:tags":[
        "arte",
        "de",
        "galer\u00cdas"
    ],
    "sg:website":"www.frm.es/davidcervello",
    "wof:name":"Cervello Ros David",
    "wof:placetype":"venue"
},
  "geometry": {"coordinates":[2.1421210766,41.3997955322],"type":"Point"}
}