{
  "type": "Feature",
  "properties": {
    "addr:full":"Avda Rosalia De Castro, S/n Vilagarcia Pontevedra 36600",
    "addr:housenumber":"s / n",
    "addr:postcode":"36600",
    "addr:street":"Avda Rosalia De Castro",
    "iso:country":"ES",
    "sg:address":"Avda Rosalia De Castro, S/n",
    "sg:city":"Vilagarcia",
    "sg:orig_category":"Ense\u00d1anza Secundaria: Colegios Y Escuelas Privadas",
    "sg:phone":"+34 986 50 62 98",
    "sg:postcode":"36600",
    "sg:province":"Pontevedra",
    "wof:name":"Xunta De Galicia",
    "wof:placetype":"venue"
},
  "geometry": {"coordinates":[-8.8242120743,42.5629348755],"type":"Point"}
}