{
  "type": "Feature",
  "properties": {
    "iso:country":"ES",
    "sg:address":"Calle de San Juan Bautista, S/n",
    "sg:city":"Guillena",
    "sg:orig_category":"Cl\u00cdnicas M\u00c9dicas",
    "sg:phone":"+34 955 78 55 82",
    "sg:postcode":"41210",
    "sg:province":"Sevilla",
    "wof:name":"Medicur S.l.",
    "wof:placetype":"venue"
},
  "geometry": {"coordinates":[-6.0549240112,37.5477561951],"type":"Point"}
}