{
  "type": "Feature",
  "properties": {
    "iso:country":"ES",
    "sg:address":"Calle de Republica Argentina, 15",
    "sg:city":"Irun",
    "sg:orig_category":"Farmacias",
    "sg:phone":"+34 943 62 30 28",
    "sg:postcode":"20302",
    "sg:province":"Guip\u00f9zcoa",
    "wof:name":"Troconiz Ortiz De Zarate Maria",
    "wof:placetype":"venue"
},
  "geometry": {"coordinates":[-1.7919310331,43.3403778076],"type":"Point"}
}