{
  "type": "Feature",
  "properties": {
    "addr:full":"Plaz Pozo Del Tio Raimundo, 9 Madrid Madrid 28053",
    "addr:housenumber":"9",
    "addr:postcode":"28053",
    "addr:street":"Madrid",
    "iso:country":"ES",
    "sg:address":"Plaz Pozo Del Tio Raimundo, 9",
    "sg:city":"Madrid",
    "sg:orig_category":"Droguer\u00cdas (al Por Menor)",
    "sg:phone":"+34 915 07 51 78",
    "sg:postcode":"28053",
    "sg:province":"Madrid",
    "wof:name":"Rodriguez Arema Ines",
    "wof:placetype":"venue"
},
  "geometry": {"coordinates":[-3.6593968868,40.3728790283],"type":"Point"}
}