{
  "type": "Feature",
  "properties": {
    "addr:full":"Carr Creu, 1 Alcudia Islas Baleares 07400",
    "addr:housenumber":"1",
    "addr:postcode":"07400",
    "addr:street":"Carr Creu",
    "iso:country":"ES",
    "sg:address":"Carr Creu, 1",
    "sg:city":"Alcudia",
    "sg:orig_category":"Inmobiliaria (agencias)",
    "sg:phone":"+34 971 89 72 72",
    "sg:postcode":"07400",
    "sg:province":"Islas Baleares",
    "wof:name":"Inmobiliaria Farrutx 2000 S.l.",
    "wof:placetype":"venue"
},
  "geometry": {"coordinates":[3.1242699623,39.8452415466],"type":"Point"}
}