{
  "type": "Feature",
  "properties": {
    "addr:full":"Ctra Aldealengua, S/n Cabrerizos Salamanca 37193",
    "addr:housenumber":"s / n",
    "addr:postcode":"37193",
    "addr:street":"Ctra Aldealengua",
    "iso:country":"ES",
    "sg:address":"Ctra Aldealengua, S/n",
    "sg:city":"Cabrerizos",
    "sg:orig_category":"Semiller\u00cdas",
    "sg:phone":"+34 923 17 01 31",
    "sg:postcode":"37193",
    "sg:province":"Salamanca",
    "wof:name":"Cooperativa De Trabajo Viveros Tormes",
    "wof:placetype":"venue"
},
  "geometry": {"coordinates":[-5.6213741302,40.9721908569],"type":"Point"}
}