{
  "type": "Feature",
  "properties": {
    "iso:country":"ES",
    "sg:address":"Ctra Castellar, 102",
    "sg:city":"Terrassa",
    "sg:orig_category":"Sociedades, Compa\u00d1\u00cdas Aseguradoras",
    "sg:phone":"+34 937 86 13 09",
    "sg:postcode":"08222",
    "sg:province":"Barcelona",
    "sg:website":"www.mapfre.com",
    "wof:name":"Mapfre Servicios De Informatica",
    "wof:placetype":"venue"
},
  "geometry": {"coordinates":[2.0244150162,41.5664863586],"type":"Point"}
}