{
  "type": "Feature",
  "properties": {
    "iso:country":"ES",
    "sg:address":"Calle de Monasterio De Bergondo, 18",
    "sg:city":"Coru\u00d1a",
    "sg:orig_category":"Bisuter\u00cda, Joyer\u00cda, Relojer\u00cda (al Por Menor)",
    "sg:phone":"+34 981 27 13 52",
    "sg:postcode":"15010",
    "sg:province":"La Coru\u00f1a",
    "wof:name":"Candame Areosa Juan Manuel",
    "wof:placetype":"venue"
},
  "geometry": {"coordinates":[-8.424747467,43.361946106],"type":"Point"}
}