{
  "type": "Feature",
  "properties": {
    "iso:country":"ES",
    "sg:address":"Poligon Industrial Ford, S/n",
    "sg:city":"Almussafes",
    "sg:orig_category":"Contenedores (mercanc\u00cdas)",
    "sg:phone":"+34 961 79 70 43",
    "sg:postcode":"46440",
    "sg:province":"Valencia",
    "wof:name":"Valautomocion S.l.",
    "wof:placetype":"venue"
},
  "geometry": {"coordinates":[-0.4122039974,39.2929763794],"type":"Point"}
}