{
  "type": "Feature",
  "properties": {
    "iso:country":"ES",
    "sg:address":"Calle de Virgen Del Portillo, 47",
    "sg:city":"Madrid",
    "sg:orig_category":"Fabricaci\u00d3n, Importaci\u00d3n, Venta De Material De Telefon\u00cda, Peritelefon\u00cda",
    "sg:phone":"+34 913 77 03 02",
    "sg:postcode":"28027",
    "sg:province":"Madrid",
    "wof:name":"Panafonic S.l.",
    "wof:placetype":"venue"
},
  "geometry": {"coordinates":[-3.6472427845,40.4392051697],"type":"Point"}
}