{
  "type": "Feature",
  "properties": {
    "addr:full":"Calle de Poeta Josep Cervera I Grifol, 12 Valencia Valencia 46013",
    "addr:housenumber":"12",
    "addr:postcode":"46013",
    "addr:street":"Calle De Poeta Josep Cervera I Grifol",
    "iso:country":"ES",
    "sg:address":"Calle de Poeta Josep Cervera I Grifol, 12",
    "sg:city":"Valencia",
    "sg:orig_category":"Abogados",
    "sg:phone":"+34 963 33 76 32",
    "sg:postcode":"46013",
    "sg:province":"Valencia",
    "wof:name":"Mora Pla Maria Angeles",
    "wof:placetype":"venue"
},
  "geometry": {"coordinates":[-0.3590730131,39.454246521],"type":"Point"}
}