{
  "type": "Feature",
  "properties": {
    "addr:full":"Avda Yunquera (de), 18 Malaga Del Fresno Guadalajara 19219",
    "addr:housenumber":"18",
    "addr:postcode":"19219",
    "addr:street":"Avda Yunquera De",
    "iso:country":"ES",
    "sg:address":"Avda Yunquera (de), 18",
    "sg:city":"Malaga Del Fresno",
    "sg:orig_category":"Cr\u00cda De Animales",
    "sg:phone":"+34 949 33 85 00",
    "sg:postcode":"19219",
    "sg:province":"Guadalajara",
    "wof:name":"Hocajo Manzano C.b.",
    "wof:placetype":"venue"
},
  "geometry": {"coordinates":[-3.2483079433,40.7889900208],"type":"Point"}
}