{
  "type": "Feature",
  "properties": {
    "iso:country":"ES",
    "sg:address":"Okobio, 10",
    "sg:city":"Belauntza",
    "sg:orig_category":"Imprenta",
    "sg:phone":"+34 943 67 27 40",
    "sg:postcode":"20491",
    "sg:province":"Guip\u00f9zcoa",
    "wof:name":"Aitor Maiza Lete Y Otro C.b.",
    "wof:placetype":"venue"
},
  "geometry": {"coordinates":[-2.0537774563,43.1333847046],"type":"Point"}
}