{
  "type": "Feature",
  "properties": {
    "iso:country":"ES",
    "sg:address":"Calle de Esteve Victoria, 7",
    "sg:city":"Valencia",
    "sg:orig_category":"Cueros Y Pieles (al Por Mayor)",
    "sg:phone":"+34 963 33 40 93",
    "sg:postcode":"46006",
    "sg:province":"Valencia",
    "wof:name":"Curtits Victoria-bosca S. L.",
    "wof:placetype":"venue"
},
  "geometry": {"coordinates":[-0.3722159863,39.4573097229],"type":"Point"}
}