{
  "type": "Feature",
  "properties": {
    "addr:full":"Sanguesa, 27 Iru\u00f1a Navarra 31005",
    "addr:housenumber":"27",
    "addr:postcode":"31005",
    "addr:street":"Sanguesa",
    "iso:country":"ES",
    "sg:address":"Sanguesa, 27",
    "sg:city":"Iru\u00f1a",
    "sg:orig_category":"Molduras, Junquillos, Listones Y Molduras Perforadas",
    "sg:phone":"+34 948 24 02 75",
    "sg:postcode":"31005",
    "sg:province":"Navarra",
    "wof:name":"Aguerrebere Iturralde Jone",
    "wof:placetype":"venue"
},
  "geometry": {"coordinates":[-1.6405265331,42.806854248],"type":"Point"}
}