{
  "type": "Feature",
  "properties": {
    "addr:full":"Calle de Doctor Cardus Llanas, 9 Huesca Huesca 22005",
    "addr:housenumber":"9",
    "addr:postcode":"22005",
    "addr:street":"Calle De Doctor Cardus Llanas",
    "iso:country":"ES",
    "sg:address":"Calle de Doctor Cardus Llanas, 9",
    "sg:city":"Huesca",
    "sg:orig_category":"Prot\u00c9sicos Dentales",
    "sg:phone":"+34 974 24 19 43",
    "sg:postcode":"22005",
    "sg:province":"Huesca",
    "wof:name":"Martinez Garcia Santiago",
    "wof:placetype":"venue"
},
  "geometry": {"coordinates":[-0.4085513949,42.1320762634],"type":"Point"}
}