{
  "type": "Feature",
  "properties": {
    "addr:full":"Calle de A\u00d1aza (la), S/n Arrecife Las Palmas 35500",
    "addr:postcode":"35500",
    "addr:street":"Calle De An\u0303Aza La S / N",
    "iso:country":"ES",
    "sg:address":"Calle de A\u00d1aza (la), S/n",
    "sg:city":"Arrecife",
    "sg:orig_category":"Venta, Montaje De Neum\u00c1ticos",
    "sg:phone":"+34 928 81 28 27",
    "sg:postcode":"35500",
    "sg:province":"Las Palmas",
    "wof:name":"Auto Accesorios Arrecife S. L.",
    "wof:placetype":"venue"
},
  "geometry": {"coordinates":[-13.5446186066,28.9636459351],"type":"Point"}
}