{
  "type": "Feature",
  "properties": {
    "addr:full":"Ctra Benagalbon, 3 Rincon Victoria M\u00e1laga 29730",
    "addr:housenumber":"3",
    "addr:postcode":"29730",
    "addr:street":"Ctra Benagalbon;Ma\u0301Laga",
    "iso:country":"ES",
    "sg:address":"Ctra Benagalbon, 3",
    "sg:city":"Rincon Victoria",
    "sg:orig_category":"Molduras, Junquillos, Listones Y Molduras Perforadas",
    "sg:phone":"+34 952 40 10 13",
    "sg:postcode":"29730",
    "sg:province":"M\u00e1laga",
    "wof:name":"Rando Navarro Jose",
    "wof:placetype":"venue"
},
  "geometry": {"coordinates":[-4.2756009102,36.7216148376],"type":"Point"}
}