{
  "type": "Feature",
  "properties": {
    "iso:country":"ES",
    "sg:address":"Calle de Croacia, 20",
    "sg:city":"Malaga",
    "sg:orig_category":"Fabricaci\u00d3n, Venta, Instalaci\u00d3n De R\u00d3tulos, De R\u00d3tulos Luminosos",
    "sg:phone":"+34 952 96 07 47",
    "sg:postcode":"29196",
    "sg:province":"M\u00e1laga",
    "wof:name":"Tecnica De Acero Y Luminosos S.a.",
    "wof:placetype":"venue"
},
  "geometry": {"coordinates":[-4.4954590797,36.6957168579],"type":"Point"}
}