{
  "type": "Feature",
  "properties": {
    "addr:full":"Plaz San Francisco, 7 Ciudad Real Ciudad Real 13001",
    "addr:housenumber":"7",
    "addr:postcode":"13001",
    "addr:street":"Plaz San Francisco",
    "iso:country":"ES",
    "sg:address":"Plaz San Francisco, 7",
    "sg:city":"Ciudad Real",
    "sg:orig_category":"Peluquer\u00cdas, Peluquer\u00cda Mixta",
    "sg:phone":"+34 926 22 99 34",
    "sg:postcode":"13001",
    "sg:province":"Ciudad Real",
    "wof:name":"Romero Rodriguez Anastasia",
    "wof:placetype":"venue"
},
  "geometry": {"coordinates":[-3.9271609783,38.981552124],"type":"Point"}
}