{
  "type": "Feature",
  "properties": {
    "iso:country":"ES",
    "sg:address":"Carrer de Corsega, 372",
    "sg:city":"Barcelona",
    "sg:orig_category":"Reposter\u00cdas",
    "sg:phone":"+34 932 07 65 90",
    "sg:postcode":"08037",
    "sg:province":"Barcelona",
    "wof:name":"Forn Nou S.a.",
    "wof:placetype":"venue"
},
  "geometry": {"coordinates":[2.162719965,41.3988952637],"type":"Point"}
}