{
  "type": "Feature",
  "properties": {
    "addr:full":"Calle de Pedro Campos, 11 Madrid Madrid 28019",
    "addr:housenumber":"11",
    "addr:postcode":"madrid;28019",
    "addr:street":"Calle De Pedro Campos",
    "iso:country":"ES",
    "sg:address":"Calle de Pedro Campos, 11",
    "sg:city":"Madrid",
    "sg:orig_category":"Fabricaci\u00d3n, Instalaci\u00d3n Y Reparaci\u00d3n De Bombas",
    "sg:phone":"+34 915 65 06 06",
    "sg:postcode":"28019",
    "sg:province":"Madrid",
    "sg:website":"www.tallerescuenca.com",
    "wof:name":"Talleres Cuenca Malmierca S.l.",
    "wof:placetype":"venue"
},
  "geometry": {"coordinates":[-3.7189309597,40.3908081055],"type":"Point"}
}