{
  "type": "Feature",
  "properties": {
    "addr:full":"Calle de La Ba\u00d1eza, 10 Madrid Madrid 28029",
    "addr:housenumber":"10",
    "addr:postcode":"madrid;28029",
    "addr:street":"Calle De La Ban\u0303Eza",
    "iso:country":"ES",
    "sg:address":"Calle de La Ba\u00d1eza, 10",
    "sg:city":"Madrid",
    "sg:orig_category":"Abogados",
    "sg:phone":"+34 917 30 81 57",
    "sg:postcode":"28029",
    "sg:province":"Madrid",
    "wof:name":"Alfaya Vazquez Lucia",
    "wof:placetype":"venue"
},
  "geometry": {"coordinates":[-3.7126624584,40.4765319824],"type":"Point"}
}