{
  "type": "Feature",
  "properties": {
    "iso:country":"ES",
    "sg:address":"Carrer de Bruc, 85",
    "sg:city":"Barcelona",
    "sg:orig_category":"\u00d3ptica: Instrumentos (fabricaci\u00d3n)",
    "sg:phone":"+34 934 57 67 16",
    "sg:postcode":"08009",
    "sg:province":"Barcelona",
    "wof:name":"Boixadera Cunilleras Juan",
    "wof:placetype":"venue"
},
  "geometry": {"coordinates":[2.1684401035,41.3950233459],"type":"Point"}
}