{
  "type": "Feature",
  "properties": {
    "iso:country":"ES",
    "sg:address":"Carrer de Roger De Flor, 76",
    "sg:city":"Granollers",
    "sg:orig_category":"Peluquer\u00cdas, Peluquer\u00cda Mixta",
    "sg:phone":"+34 938 70 70 59",
    "sg:postcode":"08401",
    "sg:province":"Barcelona",
    "wof:name":"Quintana Villarino Laura",
    "wof:placetype":"venue"
},
  "geometry": {"coordinates":[2.2829799652,41.6064300537],"type":"Point"}
}