{
  "type": "Feature",
  "properties": {
    "iso:country":"ES",
    "sg:address":"Calle de Iriarte, 9",
    "sg:city":"Madrid",
    "sg:orig_category":"Concepci\u00d3n Y Realizaci\u00d3n De Maquetas Profesionales Y Prototipos",
    "sg:phone":"+34 913 55 92 54",
    "sg:postcode":"28028",
    "sg:province":"Madrid",
    "wof:name":"Juan De Dios Hernandez Y Jesus Rey S.l.",
    "wof:placetype":"venue"
},
  "geometry": {"coordinates":[-3.6710860729,40.4364585876],"type":"Point"}
}