{
  "type": "Feature",
  "properties": {
    "iso:country":"ES",
    "sg:address":"Ptge Can Faixina, 1",
    "sg:city":"Palma",
    "sg:orig_category":"Internados & Ense\u00d1anza Privada",
    "sg:phone":"+34 971 46 94 15",
    "sg:postcode":"07005",
    "sg:province":"Islas Baleares",
    "wof:name":"Colegio San Francisco De Asis",
    "wof:placetype":"venue"
},
  "geometry": {"coordinates":[2.6619679928,39.5752105713],"type":"Point"}
}