{
  "type": "Feature",
  "properties": {
    "iso:country":"ES",
    "sg:address":"Calle de Vega De Infanzones, 10",
    "sg:city":"Le\u00f3n",
    "sg:orig_category":"Explotaci\u00d3n De Bosques",
    "sg:phone":"+34 987 80 53 47",
    "sg:postcode":"24008",
    "sg:province":"Le\u00f3n",
    "wof:name":"Leon Forestal S.l.",
    "wof:placetype":"venue"
},
  "geometry": {"coordinates":[-5.588891983,42.609752655],"type":"Point"}
}