{
  "type": "Feature",
  "properties": {
    "iso:country":"ES",
    "sg:address":"Ctra. Valdepe\u00f1as, 20",
    "sg:city":"Cozar",
    "sg:orig_category":"Productores Recolectores, Venta Directa De Vinos",
    "sg:phone":"+34 926 69 40 98",
    "sg:postcode":"13345",
    "sg:province":"Ciudad Real",
    "wof:name":"Societe Viticole De Espa\u00f1a S. A.",
    "wof:placetype":"venue"
},
  "geometry": {"coordinates":[-3.07447505,38.6575469971],"type":"Point"}
}