{
  "type": "Feature",
  "properties": {
    "iso:country":"ES",
    "sg:address":"Av Ventura Gassol, 3",
    "sg:city":"Hospitalet Llobregat",
    "sg:orig_category":"Aparcamientos (infraestructuras, Accesorios)",
    "sg:phone":"+34 933 37 25 90",
    "sg:postcode":"08901",
    "sg:province":"Barcelona",
    "wof:name":"Garage Maycar S.l.",
    "wof:placetype":"venue"
},
  "geometry": {"coordinates":[2.1105954647,41.363658905],"type":"Point"}
}