{
  "type": "Feature",
  "properties": {
    "iso:country":"ES",
    "sg:address":"Carr Pelegri Ballester, 18",
    "sg:city":"Vilanova I La Geltru",
    "sg:orig_category":"Institutos De Belleza",
    "sg:phone":"+34 938 93 84 17",
    "sg:postcode":"08800",
    "sg:province":"Barcelona",
    "wof:name":"Estevez Escobar Maria Del Carmen",
    "wof:placetype":"venue"
},
  "geometry": {"coordinates":[1.7220950127,41.2223587036],"type":"Point"}
}