{
  "type": "Feature",
  "properties": {
    "addr:full":"Calle de Esperanto, 2 Malaga M\u00e1laga 29007",
    "addr:housenumber":"2",
    "addr:postcode":"29007",
    "addr:street":"Calle De Esperanto;Ma\u0301Laga",
    "iso:country":"ES",
    "sg:address":"Calle de Esperanto, 2",
    "sg:city":"Malaga",
    "sg:orig_category":"Reposter\u00cdas",
    "sg:phone":"+34 952 30 35 65",
    "sg:postcode":"29007",
    "sg:province":"M\u00e1laga",
    "wof:name":"Perez Martin Rafael",
    "wof:placetype":"venue"
},
  "geometry": {"coordinates":[-4.4320001602,36.7188453674],"type":"Point"}
}