{
  "type": "Feature",
  "properties": {
    "iso:country":"ES",
    "sg:address":"Calle de Vargas, 65",
    "sg:city":"Santander",
    "sg:orig_category":"Reposter\u00cdas",
    "sg:phone":"+34 942 37 16 60",
    "sg:postcode":"39010",
    "sg:province":"Cantabria",
    "wof:name":"El Obrador Artesano De Cantabria S. A.",
    "wof:placetype":"venue"
},
  "geometry": {"coordinates":[-3.8235740662,43.4588470459],"type":"Point"}
}