{
  "type": "Feature",
  "properties": {
    "iso:country":"ES",
    "sg:address":"Calle de Salvador Escandon, 20",
    "sg:city":"Luanco",
    "sg:orig_category":"Peluquer\u00cdas, Peluquer\u00cda Mixta",
    "sg:phone":"+34 985 88 29 30",
    "sg:postcode":"33440",
    "sg:province":"Asturias",
    "wof:name":"Miangolarra Zabaleta Maria Soledad",
    "wof:placetype":"venue"
},
  "geometry": {"coordinates":[-5.7915887833,43.6161613464],"type":"Point"}
}