{
  "type": "Feature",
  "properties": {
    "iso:country":"ES",
    "sg:address":"Avda Roquetas, 14",
    "sg:city":"Roquetas Mar",
    "sg:orig_category":"Cr\u00cda De Animales",
    "sg:phone":"+34 950 32 00 63",
    "sg:postcode":"04740",
    "sg:province":"Almer\u00eda",
    "wof:name":"Clinica Veterinaria Roquetas S.",
    "wof:placetype":"venue"
},
  "geometry": {"coordinates":[-2.6124989986,36.7638435364],"type":"Point"}
}