{
  "type": "Feature",
  "properties": {
    "iso:country":"ES",
    "sg:address":"Calle de Miguel Hernandez, 7",
    "sg:city":"Astillero",
    "sg:orig_category":"Molduras, Junquillos, Listones Y Molduras Perforadas",
    "sg:phone":"+34 942 54 23 61",
    "sg:postcode":"39610",
    "sg:province":"Cantabria",
    "wof:name":"Malanda Montes Jesus",
    "wof:placetype":"venue"
},
  "geometry": {"coordinates":[-3.8238949776,43.4024047852],"type":"Point"}
}