{
  "type": "Feature",
  "properties": {
    "addr:full":"Calle de Camilo Alonso Vega, 1 Recas Toledo 45211",
    "addr:housenumber":"1",
    "addr:postcode":"45211",
    "addr:street":"Calle De Camilo Alonso Vega",
    "iso:country":"ES",
    "sg:address":"Calle de Camilo Alonso Vega, 1",
    "sg:city":"Recas",
    "sg:orig_category":"Inform\u00c1tica: Mantenimiento Y Reparaci\u00d3n De Ordenadores",
    "sg:phone":"+34 925 52 29 84",
    "sg:postcode":"45211",
    "sg:province":"Toledo",
    "sg:website":"www.zacosan.com",
    "wof:name":"Informatica Zacosan S.c.",
    "wof:placetype":"venue"
},
  "geometry": {"coordinates":[-3.9926781654,40.0540504456],"type":"Point"}
}