{
  "type": "Feature",
  "properties": {
    "addr:full":"Plaz San Antonio, 20 Vinaros Castell\u00f3n 12500",
    "addr:housenumber":"20",
    "addr:postcode":"12500",
    "addr:street":"Plaz San Antonio",
    "iso:country":"ES",
    "sg:address":"Plaz San Antonio, 20",
    "sg:city":"Vinaros",
    "sg:orig_category":"Arquitectos",
    "sg:phone":"+34 964 45 17 21",
    "sg:postcode":"12500",
    "sg:province":"Castell\u00f3n",
    "wof:name":"Gimeno Codorniu Oscar",
    "wof:placetype":"venue"
},
  "geometry": {"coordinates":[0.4749450088,40.4711990356],"type":"Point"}
}