{
  "type": "Feature",
  "properties": {
    "iso:country":"ES",
    "sg:address":"Carrer de Muntaner, 60",
    "sg:city":"Barcelona",
    "sg:orig_category":"Asesor\u00cda Fiscal Y Jur\u00cddica",
    "sg:phone":"+34 934 54 61 28",
    "sg:postcode":"08011",
    "sg:province":"Barcelona",
    "wof:name":"Asesoria Zorrilla Muntaner Gestion S.l.",
    "wof:placetype":"venue"
},
  "geometry": {"coordinates":[2.1592953205,41.3867416382],"type":"Point"}
}