{
  "type": "Feature",
  "properties": {
    "addr:full":"Calle de Vista Alegre, 8 Villarrobledo Albacete 02600",
    "addr:housenumber":"8",
    "addr:postcode":"02600",
    "addr:street":"Calle De Vista Alegre",
    "iso:country":"ES",
    "sg:address":"Calle de Vista Alegre, 8",
    "sg:city":"Villarrobledo",
    "sg:orig_category":"Transportes Por V\u00cdas Navegables",
    "sg:phone":"+34 967 14 17 37",
    "sg:postcode":"02600",
    "sg:province":"Albacete",
    "wof:name":"Martinez Clemente Angel",
    "wof:placetype":"venue"
},
  "geometry": {"coordinates":[-2.5922648907,39.2697868347],"type":"Point"}
}