{
  "type": "Feature",
  "properties": {
    "iso:country":"ES",
    "sg:address":"Avda Virgen De Lidon, S/n",
    "sg:city":"Castellon",
    "sg:orig_category":"M\u00c9dicos: Ginecolog\u00cda Y Obstetricia",
    "sg:phone":"+34 964 22 38 21",
    "sg:postcode":"12003",
    "sg:province":"Castell\u00f3n",
    "wof:name":"Folch Beltran Antonio",
    "wof:placetype":"venue"
},
  "geometry": {"coordinates":[-0.0077,39.9836883545],"type":"Point"}
}