{
  "type": "Feature",
  "properties": {
    "addr:full":"Calle de Conchita Piquer, 4 Valencia Valencia 46015",
    "addr:postcode":"46015",
    "addr:street":"Calle De;Piquer;Valencia",
    "iso:country":"ES",
    "sg:address":"Calle de Conchita Piquer, 4",
    "sg:city":"Valencia",
    "sg:orig_category":"Ropa Para Ni\u00d1os (al Por Menor)",
    "sg:phone":"+34 963 47 35 60",
    "sg:postcode":"46015",
    "sg:province":"Valencia",
    "wof:name":"Fernandez Perez Eva Maria",
    "wof:placetype":"venue"
},
  "geometry": {"coordinates":[-0.3910877109,39.4863815308],"type":"Point"}
}