{
  "type": "Feature",
  "properties": {
    "iso:country":"ES",
    "sg:address":"Calle de Toledo, 58",
    "sg:city":"Ciudad Real",
    "sg:orig_category":"M\u00c9dicos: Medicina General Orientada A La Homeopat\u00cda",
    "sg:phone":"+34 926 21 66 09",
    "sg:postcode":"13003",
    "sg:province":"Ciudad Real",
    "wof:name":"Benitez Sanchez Cid Natalia",
    "wof:placetype":"venue"
},
  "geometry": {"coordinates":[-3.9278690815,38.9928512573],"type":"Point"}
}