{
  "type": "Feature",
  "properties": {
    "addr:full":"Rua Bouza Xusta, 26 Trabanca Badi\u00e7a Pontevedra 36613",
    "addr:housenumber":"26",
    "addr:postcode":"36613",
    "addr:street":"Rua Bouza Xusta",
    "iso:country":"ES",
    "sg:address":"Rua Bouza Xusta, 26",
    "sg:city":"Trabanca Badi\u00e7a",
    "sg:orig_category":"Madera Para Construcci\u00d3n E Industria",
    "sg:phone":"+34 986 50 85 51",
    "sg:postcode":"36613",
    "sg:province":"Pontevedra",
    "wof:name":"Maderas Urupe S.l.",
    "wof:placetype":"venue"
},
  "geometry": {"coordinates":[-8.7695436478,42.6105308533],"type":"Point"}
}