{
  "type": "Feature",
  "properties": {
    "addr:full":"Pase Palmeras (de Las), S/n Bailen Ja\u00e9n 23710",
    "addr:postcode":"23710",
    "addr:street":"S / N;Jae\u0301N",
    "iso:country":"ES",
    "sg:address":"Pase Palmeras (de Las), S/n",
    "sg:city":"Bailen",
    "sg:orig_category":"Ba\u00d1os Y Duchas P\u00dablicos",
    "sg:phone":"+34 953 67 26 85",
    "sg:postcode":"23710",
    "sg:province":"Ja\u00e9n",
    "wof:name":"Criado Soriano Luis",
    "wof:placetype":"venue"
},
  "geometry": {"coordinates":[-3.7814741135,38.0945281982],"type":"Point"}
}