{
  "type": "Feature",
  "properties": {
    "iso:country":"ES",
    "sg:address":"Ctra. Del Embalse, Km. 0003,0",
    "sg:city":"Tembleque",
    "sg:orig_category":"Molduras, Junquillos, Listones Y Molduras Perforadas",
    "sg:phone":"+34 925 59 50 28",
    "sg:postcode":"45780",
    "sg:province":"Toledo",
    "wof:name":"Jimenez Moreno Cipriano",
    "wof:placetype":"venue"
},
  "geometry": {"coordinates":[-3.5035789013,39.6947860718],"type":"Point"}
}