{
  "type": "Feature",
  "properties": {
    "iso:country":"ES",
    "sg:address":"Calle de Badaia, 7",
    "sg:city":"Vitoria-gasteiz",
    "sg:orig_category":"Comercio, Reparaci\u00d3n De Bicicletas, De Motocicletas, De Accesorios",
    "sg:phone":"+34 945 14 00 54",
    "sg:postcode":"01012",
    "sg:province":"\u00c1lava",
    "wof:name":"Jorge Romero Valle",
    "wof:placetype":"venue"
},
  "geometry": {"coordinates":[-2.6763484478,42.8505592346],"type":"Point"}
}