{
  "type": "Feature",
  "properties": {
    "iso:country":"ES",
    "sg:address":"Calle de Vallehermoso, 80",
    "sg:city":"Madrid",
    "sg:orig_category":"Peluquer\u00cdas, Peluquer\u00cda Mixta",
    "sg:phone":"+34 915 54 48 37",
    "sg:postcode":"28015",
    "sg:province":"Madrid",
    "wof:name":"Rodriguez Palacios Yolanda",
    "wof:placetype":"venue"
},
  "geometry": {"coordinates":[-3.7081570625,40.4380569458],"type":"Point"}
}