{
  "type": "Feature",
  "properties": {
    "iso:country":"ES",
    "sg:address":"C/ Mirador Del Codolar, S/n",
    "sg:city":"Tossa",
    "sg:orig_category":"Agencias De Viajes",
    "sg:phone":"+34 972 34 05 46",
    "sg:postcode":"17320",
    "sg:province":"Girona",
    "wof:name":"Viajes Eurotossa S.a.",
    "wof:placetype":"venue"
},
  "geometry": {"coordinates":[2.9295940399,41.7164306641],"type":"Point"}
}