{
  "type": "Feature",
  "properties": {
    "addr:full":"Ugaldeguren Ii Poligonoa, 2 Arteaga Vizcaya 48170",
    "addr:housenumber":"2",
    "addr:postcode":"48170",
    "addr:street":"Poligonoa",
    "iso:country":"ES",
    "sg:address":"Ugaldeguren Ii Poligonoa, 2",
    "sg:city":"Arteaga",
    "sg:orig_category":"Electricidad: Equipos Industriales, Componentes (fabricaci\u00d3n)",
    "sg:phone":"+34 944 52 25 27",
    "sg:postcode":"48170",
    "sg:province":"Vizcaya",
    "sg:website":"www.amara.es",
    "wof:name":"Amara S. A.",
    "wof:placetype":"venue"
},
  "geometry": {"coordinates":[-2.7841410637,43.1337165833],"type":"Point"}
}