{
  "type": "Feature",
  "properties": {
    "iso:country":"ES",
    "sg:address":"Calle de San Juan, 10",
    "sg:city":"Amorebieta-etxano",
    "sg:orig_category":"Quincaller\u00cda (al Por Menor)",
    "sg:phone":"+34 946 73 17 41",
    "sg:postcode":"48340",
    "sg:province":"Vizcaya",
    "wof:name":"Ferreteria I\u00f1igo Prellezo Arrieta",
    "wof:placetype":"venue"
},
  "geometry": {"coordinates":[-2.7293200493,43.2190971375],"type":"Point"}
}