{
  "type": "Feature",
  "properties": {
    "iso:country":"ES",
    "sg:address":"Calle de Murcia, 16",
    "sg:city":"Calasparra",
    "sg:orig_category":"Droguer\u00cdas (al Por Menor)",
    "sg:phone":"+34 968 72 03 48",
    "sg:postcode":"30420",
    "sg:province":"Murcia",
    "wof:name":"Lopez Sanchez Placido",
    "wof:placetype":"venue"
},
  "geometry": {"coordinates":[-1.6955909729,38.2291107178],"type":"Point"}
}