{
  "type": "Feature",
  "properties": {
    "iso:country":"ES",
    "sg:address":"Avda Mari\u00d1a (da), 40",
    "sg:city":"Foz",
    "sg:orig_category":"Librer\u00cdas",
    "sg:phone":"+34 982 14 04 34",
    "sg:postcode":"27780",
    "sg:province":"Lugo",
    "wof:name":"Jugueterias Reunidas S.l.",
    "wof:placetype":"venue"
},
  "geometry": {"coordinates":[-7.2581009865,43.5686683655],"type":"Point"}
}