{
  "type": "Feature",
  "properties": {
    "iso:country":"ES",
    "sg:address":"Avda Industria (de La), 21",
    "sg:city":"Daganzo Arriba",
    "sg:orig_category":"Guarda",
    "sg:phone":"+34 918 86 78 22",
    "sg:postcode":"28814",
    "sg:province":"Madrid",
    "wof:name":"Palomo Morillo Rafael",
    "wof:placetype":"venue"
},
  "geometry": {"coordinates":[-3.4612190723,40.5405197144],"type":"Point"}
}