{
  "type": "Feature",
  "properties": {
    "addr:full":"Calle de Doctor Pedro Velez, S/n Chiclana De La Frontera C\u00e1diz 11130",
    "addr:housenumber":"s",
    "addr:postcode":"11130",
    "addr:street":"Calle De Doctor Pedro Velez;/ N",
    "iso:country":"ES",
    "sg:address":"Calle de Doctor Pedro Velez, S/n",
    "sg:city":"Chiclana De La Frontera",
    "sg:orig_category":"Carnicer\u00cdas, Carnicer\u00cdas",
    "sg:phone":"+34 956 40 21 78",
    "sg:postcode":"11130",
    "sg:province":"C\u00e1diz",
    "wof:name":"Ariza Guerra Luis Miguel",
    "wof:placetype":"venue"
},
  "geometry": {"coordinates":[-6.1538805962,36.4185829163],"type":"Point"}
}