{
  "type": "Feature",
  "properties": {
    "iso:country":"ES",
    "sg:address":"Carr Raval, 53",
    "sg:city":"Quart",
    "sg:orig_category":"Fabrica De Cer\u00c1micas",
    "sg:phone":"+34 972 46 94 88",
    "sg:postcode":"17242",
    "sg:province":"Girona",
    "wof:name":"Prats Saura Jesus",
    "wof:placetype":"venue"
},
  "geometry": {"coordinates":[2.8420550823,41.9365539551],"type":"Point"}
}