{
  "type": "Feature",
  "properties": {
    "iso:country":"ES",
    "sg:address":"Avda Bartolome Esteban, 30",
    "sg:city":"Alca\u00f1iz",
    "sg:orig_category":"Mec\u00c1nico Del Autom\u00d3vil",
    "sg:phone":"+34 978 87 01 48",
    "sg:postcode":"44600",
    "sg:province":"Teruel",
    "wof:name":"Tractores Agricolas Alca\u00f1iz S.l",
    "wof:placetype":"venue"
},
  "geometry": {"coordinates":[-0.1419360042,41.0557670593],"type":"Point"}
}