{
  "type": "Feature",
  "properties": {
    "iso:country":"ES",
    "sg:address":"Calle de Dehesas (las), 21",
    "sg:city":"Granada",
    "sg:orig_category":"Urbanistas",
    "sg:phone":"+34 958 18 31 35",
    "sg:postcode":"18008",
    "sg:province":"Granada",
    "wof:name":"Coan 2001 S.l.",
    "wof:placetype":"venue"
},
  "geometry": {"coordinates":[-3.5845174789,37.1601829529],"type":"Point"}
}