{
  "type": "Feature",
  "properties": {
    "iso:country":"ES",
    "sg:address":"Rbla Passeig, 4",
    "sg:city":"Vic",
    "sg:orig_category":"Ropa Para Se\u00d1oras (al Por Menor)",
    "sg:phone":"+34 938 86 04 05",
    "sg:postcode":"08500",
    "sg:province":"Barcelona",
    "wof:name":"Sitjes Farre Juan",
    "wof:placetype":"venue"
},
  "geometry": {"coordinates":[2.2554121017,41.9307250977],"type":"Point"}
}