{
  "type": "Feature",
  "properties": {
    "addr:full":"Calle de Soledad (la), 7 Lupiana Guadalajara 19142",
    "addr:housenumber":"7",
    "addr:postcode":"19142",
    "addr:street":"Calle De Soledad La",
    "iso:country":"ES",
    "sg:address":"Calle de Soledad (la), 7",
    "sg:city":"Lupiana",
    "sg:orig_category":"Farmacias",
    "sg:phone":"+34 949 29 00 07",
    "sg:postcode":"19142",
    "sg:province":"Guadalajara",
    "wof:name":"Mu\u00f1ana Fuentes Francisco Jose",
    "wof:placetype":"venue"
},
  "geometry": {"coordinates":[-3.054008007,40.6100273132],"type":"Point"}
}