{
  "type": "Feature",
  "properties": {
    "addr:full":"Calle de Llanes, 2 San Fernando De Henares Madrid 28830",
    "addr:housenumber":"2",
    "addr:postcode":"28830",
    "addr:street":"Calle De Llanes",
    "iso:country":"ES",
    "sg:address":"Calle de Llanes, 2",
    "sg:city":"San Fernando De Henares",
    "sg:orig_category":"Centros De Educaci\u00d3n Especial",
    "sg:phone":"+34 916 60 10 14",
    "sg:postcode":"28830",
    "sg:province":"Madrid",
    "wof:name":"Ebet Educacion S.l.",
    "wof:placetype":"venue"
},
  "geometry": {"coordinates":[-3.5320210457,40.4241905212],"type":"Point"}
}