{
  "type": "Feature",
  "properties": {
    "addr:full":"Barr Torres Arriba, 2 Torres Cantabria 39300",
    "addr:housenumber":"2",
    "addr:postcode":"39300",
    "addr:street":"Arriba",
    "iso:country":"ES",
    "sg:address":"Barr Torres Arriba, 2",
    "sg:city":"Torres",
    "sg:orig_category":"Centros De Educaci\u00d3n Especial",
    "sg:phone":"+34 942 81 31 88",
    "sg:postcode":"39300",
    "sg:province":"Cantabria",
    "wof:name":"Colegio Jose Maria Caba\u00d1as",
    "wof:placetype":"venue"
},
  "geometry": {"coordinates":[-4.0520391464,43.34897995],"type":"Point"}
}