{
  "type": "Feature",
  "properties": {
    "addr:full":"Calle de Postigo De San Martin, 6 Madrid Madrid 28013",
    "addr:housenumber":"6",
    "addr:postcode":"28013",
    "addr:street":"Calle De Postigo De San Martin",
    "iso:country":"ES",
    "sg:address":"Calle de Postigo De San Martin, 6",
    "sg:city":"Madrid",
    "sg:orig_category":"Restaurantes",
    "sg:phone":"+34 915 24 08 41",
    "sg:postcode":"28013",
    "sg:province":"Madrid",
    "wof:name":"El Cucurucho Del Mar S.l.",
    "wof:placetype":"venue"
},
  "geometry": {"coordinates":[-3.7059669495,40.419216156],"type":"Point"}
}