{
  "type": "Feature",
  "properties": {
    "addr:full":"Carr Pi I Margall, 52 Lleida Lleida 25004",
    "addr:housenumber":"52",
    "addr:postcode":"25004",
    "addr:street":"Carr Pi I Margall",
    "iso:country":"ES",
    "sg:address":"Carr Pi I Margall, 52",
    "sg:city":"Lleida",
    "sg:orig_category":"\u00d3ptica: Instrumentos (fabricaci\u00d3n)",
    "sg:phone":"+34 973 23 86 45",
    "sg:postcode":"25004",
    "sg:province":"Lleida",
    "wof:name":"Ull D'or S.l.",
    "wof:placetype":"venue"
},
  "geometry": {"coordinates":[0.6268789768,41.6226234436],"type":"Point"}
}