{
  "type": "Feature",
  "properties": {
    "iso:country":"ES",
    "sg:address":"Calle de Carretera, 7",
    "sg:city":"Jimenez Jamuz",
    "sg:orig_category":"Plomeros",
    "sg:phone":"+34 987 66 43 60",
    "sg:postcode":"24767",
    "sg:province":"Le\u00f3n",
    "wof:name":"Pe\u00f1in Vivas Segundo",
    "wof:placetype":"venue"
},
  "geometry": {"coordinates":[-5.9328532219,42.2659416199],"type":"Point"}
}