{
  "type": "Feature",
  "properties": {
    "addr:full":"Calle de Rojo Hermogenes, 10 Bilbao Vizcaya 48013",
    "addr:housenumber":"10",
    "addr:postcode":"48013",
    "addr:street":"Calle De Rojo Hermogenes",
    "iso:country":"ES",
    "sg:address":"Calle de Rojo Hermogenes, 10",
    "sg:city":"Bilbao",
    "sg:orig_category":"M\u00c1quinas Y Material Para La Industria De La Alimentaci\u00d3n",
    "sg:phone":"+34 944 99 41 20",
    "sg:postcode":"48013",
    "sg:province":"Vizcaya",
    "wof:name":"Covertri,  S.l.",
    "wof:placetype":"venue"
},
  "geometry": {"coordinates":[-2.9717071056,43.2795143127],"type":"Point"}
}