{
  "type": "Feature",
  "properties": {
    "iso:country":"ES",
    "sg:address":"Carrer de Catalunya, 40",
    "sg:city":"Terrassa",
    "sg:orig_category":"Empresas De Pintura Y Revestimientos",
    "sg:phone":"+34 937 35 14 44",
    "sg:postcode":"08225",
    "sg:province":"Barcelona",
    "wof:name":"Pinturas Borras S.c.c.l.",
    "wof:placetype":"venue"
},
  "geometry": {"coordinates":[2.0119419098,41.5716094971],"type":"Point"}
}