{
  "type": "Feature",
  "properties": {
    "addr:full":"Rier Miro (de), 63 Reus Tarragona 43202",
    "addr:postcode":"43202",
    "iso:country":"ES",
    "sg:address":"Rier Miro (de), 63",
    "sg:city":"Reus",
    "sg:orig_category":"Venta, Instalaci\u00d3n De Cocinas",
    "sg:phone":"+34 977 34 50 42",
    "sg:postcode":"43202",
    "sg:province":"Tarragona",
    "wof:name":"Vivesw Gallart Salvador",
    "wof:placetype":"venue"
},
  "geometry": {"coordinates":[1.1118546724,41.1583518982],"type":"Point"}
}