{
  "type": "Feature",
  "properties": {
    "addr:full":"Pg Vilanova, 53 Sitges Barcelona 08870",
    "addr:housenumber":"53",
    "addr:postcode":"08870",
    "addr:street":"Vilanova",
    "iso:country":"ES",
    "sg:address":"Pg Vilanova, 53",
    "sg:city":"Sitges",
    "sg:orig_category":"Mec\u00c1nico Del Autom\u00d3vil",
    "sg:phone":"+34 938 94 36 46",
    "sg:postcode":"08870",
    "sg:province":"Barcelona",
    "wof:name":"Suburense Del Automovil S.c.p.",
    "wof:placetype":"venue"
},
  "geometry": {"coordinates":[1.8044749498,41.2374649048],"type":"Point"}
}