{
  "type": "Feature",
  "properties": {
    "iso:country":"ES",
    "sg:address":"Avda Ramon Pradera, 10",
    "sg:city":"Valladolid",
    "sg:orig_category":"Caf\u00c9s, Bares, Cervecer\u00cdas",
    "sg:phone":"+34 983 33 48 15",
    "sg:postcode":"47009",
    "sg:province":"Valladolid",
    "wof:name":"Lopez Matito Juan Pedro",
    "wof:placetype":"venue"
},
  "geometry": {"coordinates":[-4.737247467,41.656665802],"type":"Point"}
}