{
  "type": "Feature",
  "properties": {
    "iso:country":"ES",
    "sg:address":"Calle de Cabeza, 2",
    "sg:city":"Baza",
    "sg:orig_category":"Ense\u00d1anza: Profesiones Art\u00cdsticas",
    "sg:phone":"+34 958 70 04 07",
    "sg:postcode":"18800",
    "sg:province":"Granada",
    "sg:website":"www.retratoscaparros.com",
    "wof:name":"Retratos Caparros S.l.",
    "wof:placetype":"venue"
},
  "geometry": {"coordinates":[-2.7734968662,37.4899559021],"type":"Point"}
}