{
  "type": "Feature",
  "properties": {
    "iso:country":"ES",
    "sg:address":"Carrer de Mallorca, 172",
    "sg:city":"Barcelona",
    "sg:orig_category":"Centros De Educaci\u00d3n Especial",
    "sg:phone":"+34 934 53 17 31",
    "sg:postcode":"08036",
    "sg:province":"Barcelona",
    "wof:name":"Institut Municipal D'educacio De Barcelona",
    "wof:placetype":"venue"
},
  "geometry": {"coordinates":[2.1560440063,41.3887443542],"type":"Point"}
}