{
  "type": "Feature",
  "properties": {
    "iso:country":"ES",
    "sg:address":"Av Baix Penedes, 25",
    "sg:city":"Vendrell",
    "sg:orig_category":"Empresas De Desmonte",
    "sg:phone":"+34 977 66 43 44",
    "sg:postcode":"43700",
    "sg:province":"Tarragona",
    "wof:name":"Excavaciones Marbe S.c.p.",
    "wof:placetype":"venue"
},
  "geometry": {"coordinates":[1.5285580158,41.2168922424],"type":"Point"}
}