{
  "type": "Feature",
  "properties": {
    "iso:country":"ES",
    "sg:address":"Calle de Hernan Cortes, 174",
    "sg:city":"Villanueva Serena",
    "sg:orig_category":"Farmacias",
    "sg:phone":"+34 924 84 19 35",
    "sg:postcode":"06700",
    "sg:province":"Badajoz",
    "wof:name":"Cardenal Parejo Trinidad",
    "wof:placetype":"venue"
},
  "geometry": {"coordinates":[-5.7931489944,38.975151062],"type":"Point"}
}