{
  "type": "Feature",
  "properties": {
    "addr:full":"Carr Murcia, 4 Moncada Valencia 46113",
    "addr:housenumber":"4",
    "addr:postcode":"46113",
    "addr:street":"Carr Murcia",
    "iso:country":"ES",
    "sg:address":"Carr Murcia, 4",
    "sg:city":"Moncada",
    "sg:orig_category":"Rectificaci\u00d3n, Mecanizado, Fresado",
    "sg:phone":"+34 961 39 47 30",
    "sg:postcode":"46113",
    "sg:province":"Valencia",
    "wof:name":"Mecanizados Castan S.l.",
    "wof:placetype":"venue"
},
  "geometry": {"coordinates":[-0.3917819858,39.5498542786],"type":"Point"}
}