{
  "type": "Feature",
  "properties": {
    "iso:country":"ES",
    "sg:address":"Ptda Olivar, 8",
    "sg:city":"Orxeta",
    "sg:orig_category":"Agencias Y Asesores De Publicidad",
    "sg:phone":"+34 966 85 52 99",
    "sg:postcode":"03579",
    "sg:province":"Alicante",
    "wof:name":"Lamyman  Owen",
    "wof:placetype":"venue"
},
  "geometry": {"coordinates":[-0.2748140097,38.609539032],"type":"Point"}
}