{
  "type": "Feature",
  "properties": {
    "addr:full":"Calle de Ronda Pilar, 2 Olivenza Badajoz 06100",
    "addr:housenumber":"2",
    "addr:postcode":"06100",
    "addr:street":"Calle De Ronda Pilar",
    "iso:country":"ES",
    "sg:address":"Calle de Ronda Pilar, 2",
    "sg:city":"Olivenza",
    "sg:orig_category":"Florister\u00cdas",
    "sg:phone":"+34 924 49 27 47",
    "sg:postcode":"06100",
    "sg:province":"Badajoz",
    "wof:name":"Marquez Rodriguez Joaquin",
    "wof:placetype":"venue"
},
  "geometry": {"coordinates":[-7.0980839729,38.6843605042],"type":"Point"}
}