{
  "type": "Feature",
  "properties": {
    "addr:full":"Calle de Bomba, 8 Badajoz Badajoz 06004",
    "addr:housenumber":"8",
    "addr:postcode":"06004",
    "addr:street":"Calle De Bomba",
    "iso:country":"ES",
    "sg:address":"Calle de Bomba, 8",
    "sg:city":"Badajoz",
    "sg:orig_category":"M\u00c9dicos: Estomatolog\u00cda",
    "sg:phone":"+34 924 24 00 53",
    "sg:postcode":"06004",
    "sg:province":"Badajoz",
    "wof:name":"Maestre Alvarez Anastasio",
    "wof:placetype":"venue"
},
  "geometry": {"coordinates":[-6.9726510048,38.8745422363],"type":"Point"}
}