{
  "type": "Feature",
  "properties": {
    "addr:full":"Calle de Tudela, 33 Alfaro La Rioja 26540",
    "addr:housenumber":"33",
    "addr:postcode":"26540",
    "addr:street":"Calle De Tudela;Rioja",
    "iso:country":"ES",
    "sg:address":"Calle de Tudela, 33",
    "sg:city":"Alfaro",
    "sg:orig_category":"Caf\u00c9s, Bares, Cervecer\u00cdas",
    "sg:phone":"+34 941 18 42 00",
    "sg:postcode":"26540",
    "sg:province":"La Rioja",
    "wof:name":"Benito Gonzalez Francisco Javier",
    "wof:placetype":"venue"
},
  "geometry": {"coordinates":[-1.7498290539,42.1750869751],"type":"Point"}
}