{
  "type": "Feature",
  "properties": {
    "iso:country":"ES",
    "sg:address":"Ctra Noves Derecha, Km. 0014,7",
    "sg:city":"Torrijos",
    "sg:orig_category":"Producci\u00d3n, Comercio De Cereales",
    "sg:phone":"+34 925 77 50 19",
    "sg:postcode":"45500",
    "sg:province":"Toledo",
    "sg:website":"www.cepasa.com",
    "wof:name":"Cereales Palomo S. A.",
    "wof:placetype":"venue"
},
  "geometry": {"coordinates":[-4.2818388939,39.9835548401],"type":"Point"}
}