{
  "type": "Feature",
  "properties": {
    "addr:full":"Fnc Perotes, 1 Mentrida Toledo 45930",
    "addr:housenumber":"1",
    "addr:postcode":"45930",
    "addr:street":"Perotes",
    "iso:country":"ES",
    "sg:address":"Fnc Perotes, 1",
    "sg:city":"Mentrida",
    "sg:orig_category":"Agricultores, Agricultores",
    "sg:phone":"+34 918 14 52 65",
    "sg:postcode":"45930",
    "sg:province":"Toledo",
    "wof:name":"Perotes S.a.",
    "wof:placetype":"venue"
},
  "geometry": {"coordinates":[-4.1951050758,40.2356834412],"type":"Point"}
}