{
  "type": "Feature",
  "properties": {
    "addr:full":"Avda Pe\u00d1ota, 2 Portugalete Vizcaya 48920",
    "addr:housenumber":"2",
    "addr:postcode":"48920",
    "addr:street":"Avda Pen\u0303Ota",
    "iso:country":"ES",
    "sg:address":"Avda Pe\u00d1ota, 2",
    "sg:city":"Portugalete",
    "sg:orig_category":"Equipo De Refrigeraci\u00d3n Industrial",
    "sg:phone":"+34 944 61 87 47",
    "sg:postcode":"48920",
    "sg:province":"Vizcaya",
    "wof:name":"Maria Rosa Valdazo Garcia",
    "wof:placetype":"venue"
},
  "geometry": {"coordinates":[-3.0245420933,43.3234138489],"type":"Point"}
}