{
  "type": "Feature",
  "properties": {
    "addr:full":"Rua San Antoni\u00d1o, 30 Pontevedra Pontevedra 36002",
    "addr:housenumber":"30",
    "addr:postcode":"36002",
    "addr:street":"Rua San Antonin\u0303O",
    "iso:country":"ES",
    "sg:address":"Rua San Antoni\u00d1o, 30",
    "sg:city":"Pontevedra",
    "sg:orig_category":"Instalaci\u00d3n, Reparaci\u00d3n De Ascensores Y Montacargas",
    "sg:phone":"+34 986 86 44 16",
    "sg:postcode":"36002",
    "sg:province":"Pontevedra",
    "sg:website":"www.otis.com",
    "wof:name":"Zardoya Otis S.a.",
    "wof:placetype":"venue"
},
  "geometry": {"coordinates":[-8.6360836029,42.4297981262],"type":"Point"}
}