{
  "type": "Feature",
  "properties": {
    "iso:country":"ES",
    "sg:address":"Calle de Sese\u00d1a, 32",
    "sg:city":"Madrid",
    "sg:orig_category":"Agencias Y Agentes Comerciales, Representantes",
    "sg:phone":"+34 915 18 29 00",
    "sg:postcode":"28024",
    "sg:province":"Madrid",
    "wof:name":"Fernandez Perez Miguel Angel",
    "wof:placetype":"venue"
},
  "geometry": {"coordinates":[-3.7647519112,40.3976020813],"type":"Point"}
}