{
  "type": "Feature",
  "properties": {
    "iso:country":"ES",
    "sg:address":"Calle de Camino Del Cura, 10",
    "sg:city":"Alcobendas",
    "sg:orig_category":"Laboratorios Y Cl\u00cdnicas Veterinarias",
    "sg:phone":"+34 916 25 53 66",
    "sg:postcode":"28109",
    "sg:province":"Madrid",
    "wof:name":"Cano Polo Manuel Jose",
    "wof:placetype":"venue"
},
  "geometry": {"coordinates":[-3.6361064911,40.508266449],"type":"Point"}
}