{
  "type": "Feature",
  "properties": {
    "iso:country":"ES",
    "sg:address":"Calle de Palos, 2",
    "sg:city":"Moguer",
    "sg:orig_category":"Asociaciones, Organismos Culturales Y Socioeducativos",
    "sg:phone":"+34 959 37 05 14",
    "sg:postcode":"21800",
    "sg:province":"Huelva",
    "wof:name":"Pe\u00f1a De Cante Jondo",
    "wof:placetype":"venue"
},
  "geometry": {"coordinates":[-6.8363437653,37.2765617371],"type":"Point"}
}