{
  "type": "Feature",
  "properties": {
    "addr:full":"Calle de Horno, 7 Valjunquera Teruel 44595",
    "addr:housenumber":"7",
    "addr:postcode":"44595",
    "addr:street":"Calle De Horno",
    "iso:country":"ES",
    "sg:address":"Calle de Horno, 7",
    "sg:city":"Valjunquera",
    "sg:orig_category":"Supermercados Y Hipermercados",
    "sg:phone":"+34 978 85 45 72",
    "sg:postcode":"44595",
    "sg:province":"Teruel",
    "wof:name":"Autoservicio Margatijel Sl",
    "wof:placetype":"venue"
},
  "geometry": {"coordinates":[0.0256501995,40.9528503418],"type":"Point"}
}