{
  "type": "Feature",
  "properties": {
    "addr:full":"Ctra Nova, 125 Garriga Barcelona 08530",
    "addr:housenumber":"125",
    "addr:postcode":"08530",
    "addr:street":"Ctra Nova",
    "iso:country":"ES",
    "sg:address":"Ctra Nova, 125",
    "sg:city":"Garriga",
    "sg:orig_category":"Agencias Y Agentes Comerciales, Representantes",
    "sg:phone":"+34 938 71 74 44",
    "sg:postcode":"08530",
    "sg:province":"Barcelona",
    "wof:name":"Caldentey Gimenez Miguel",
    "wof:placetype":"venue"
},
  "geometry": {"coordinates":[2.2840359211,41.6830787659],"type":"Point"}
}