{
  "type": "Feature",
  "properties": {
    "iso:country":"ES",
    "sg:address":"Carrer de Joan Miro, 18",
    "sg:city":"Mataro",
    "sg:orig_category":"Papeler\u00cdas, Librer\u00cdas",
    "sg:phone":"+34 937 55 18 36",
    "sg:postcode":"08304",
    "sg:province":"Barcelona",
    "wof:name":"Vilalta Vilalta Carmen",
    "wof:placetype":"venue"
},
  "geometry": {"coordinates":[2.4502921104,41.5496902466],"type":"Point"}
}