{
  "type": "Feature",
  "properties": {
    "iso:country":"ES",
    "sg:address":"Nande, 10",
    "sg:city":"Gondomar",
    "sg:orig_category":"Trabajos De Topograf\u00cda",
    "sg:phone":"+34 986 36 93 46",
    "sg:postcode":"36388",
    "sg:province":"Pontevedra",
    "wof:name":"Topag Gabinete De Topografia Y Cartografia S.l.",
    "wof:placetype":"venue"
},
  "geometry": {"coordinates":[-8.778837204,42.0906448364],"type":"Point"}
}