{
  "type": "Feature",
  "properties": {
    "addr:full":"Calle de Everardo Villamil, S/n Boal Asturias 33720",
    "addr:housenumber":"s / n",
    "addr:postcode":"33720",
    "addr:street":"Calle De Everardo Villamil",
    "iso:country":"ES",
    "sg:address":"Calle de Everardo Villamil, S/n",
    "sg:city":"Boal",
    "sg:orig_category":"Asesor\u00cda De Formaci\u00d3n Y Gesti\u00d3n De Personal",
    "sg:phone":"+34 985 62 01 08",
    "sg:postcode":"33720",
    "sg:province":"Asturias",
    "wof:name":"Pedro Bulnes S.l.u.",
    "wof:placetype":"venue"
},
  "geometry": {"coordinates":[-6.8179659843,43.4308776855],"type":"Point"}
}