{
  "type": "Feature",
  "properties": {
    "iso:country":"ES",
    "sg:address":"Calle de Floridablanca, 3",
    "sg:city":"Palencia",
    "sg:orig_category":"Carnicer\u00cdas, Carnicer\u00cdas",
    "sg:phone":"+34 979 74 32 88",
    "sg:postcode":"34003",
    "sg:province":"Palencia",
    "wof:name":"Monje Martin Oscar",
    "wof:placetype":"venue"
},
  "geometry": {"coordinates":[-4.5322823524,42.017829895],"type":"Point"}
}