{
  "type": "Feature",
  "properties": {
    "iso:country":"ES",
    "sg:address":"Calle de Gaspar De Cepeda, 1",
    "sg:city":"Fuentes De Ropel",
    "sg:orig_category":"Bancos",
    "sg:phone":"+34 980 66 31 62",
    "sg:postcode":"49670",
    "sg:province":"Zamora",
    "wof:name":"Caja Rural De Zamora",
    "wof:placetype":"venue"
},
  "geometry": {"coordinates":[-5.5453791618,42.0019798279],"type":"Point"}
}