{
  "type": "Feature",
  "properties": {
    "addr:full":"Av Costa Brava, 14 Platja D'aro Girona 17250",
    "addr:housenumber":"14",
    "addr:postcode":"17250",
    "addr:street":"Av Costa Brava",
    "iso:country":"ES",
    "sg:address":"Av Costa Brava, 14",
    "sg:city":"Platja D'aro",
    "sg:orig_category":"Panader\u00cdas, Panader\u00cdas",
    "sg:phone":"+34 972 81 97 19",
    "sg:postcode":"17250",
    "sg:province":"Girona",
    "wof:name":"Roig Campmany Rosa Maria",
    "wof:placetype":"venue"
},
  "geometry": {"coordinates":[2.8086669445,41.9683265686],"type":"Point"}
}