{
  "type": "Feature",
  "properties": {
    "addr:full":"Carrer de Rambla (la), 5 Vendrell Tarragona 43700",
    "addr:housenumber":"5",
    "addr:postcode":"43700",
    "addr:street":"Carrer De Rambla La",
    "iso:country":"ES",
    "sg:address":"Carrer de Rambla (la), 5",
    "sg:city":"Vendrell",
    "sg:orig_category":"Florister\u00cdas",
    "sg:phone":"+34 977 66 07 39",
    "sg:postcode":"43700",
    "sg:province":"Tarragona",
    "wof:name":"Lleo Rueda Maria Dolores",
    "wof:placetype":"venue"
},
  "geometry": {"coordinates":[1.5361969471,41.2207756042],"type":"Point"}
}