{
  "type": "Feature",
  "properties": {
    "addr:full":"Carr Fabrica Ciments, 26 San Vicente Del Raspeig-sant Vicent Del Raspeig Alicante 03690",
    "addr:housenumber":"26",
    "addr:postcode":"03690",
    "addr:street":"Carr Fabrica Ciments",
    "iso:country":"ES",
    "sg:address":"Carr Fabrica Ciments, 26",
    "sg:city":"San Vicente Del Raspeig-sant Vicent Del Raspeig",
    "sg:orig_category":"Carnicer\u00cdas, Carnicer\u00cdas",
    "sg:phone":"+34 965 66 75 59",
    "sg:postcode":"03690",
    "sg:province":"Alicante",
    "wof:name":"Carnicas Campanilla S.l.",
    "wof:placetype":"venue"
},
  "geometry": {"coordinates":[-0.5231339931,38.3981590271],"type":"Point"}
}