{
  "type": "Feature",
  "properties": {
    "addr:full":"Av Catalunya, 29 Pobla Segur Lleida 25500",
    "addr:housenumber":"29",
    "addr:postcode":"25500",
    "addr:street":"Av Catalunya",
    "iso:country":"ES",
    "sg:address":"Av Catalunya, 29",
    "sg:city":"Pobla Segur",
    "sg:orig_category":"Frutas Y Legumbres Frescas (al Por Mayor)",
    "sg:phone":"+34 973 68 04 11",
    "sg:postcode":"25500",
    "sg:province":"Lleida",
    "wof:name":"Sanchez Juarez Pedro",
    "wof:placetype":"venue"
},
  "geometry": {"coordinates":[0.9643499851,42.2502479553],"type":"Point"}
}