{
  "type": "Feature",
  "properties": {
    "addr:full":"Calle de Cara, 1 Cordoba C\u00f3rdoba 14003",
    "addr:housenumber":"1",
    "addr:postcode":"14003",
    "addr:street":"Calle De Cara;Co\u0301Rdoba",
    "iso:country":"ES",
    "sg:address":"Calle de Cara, 1",
    "sg:city":"Cordoba",
    "sg:orig_category":"Arquitectos",
    "sg:phone":"+34 957 48 85 69",
    "sg:postcode":"14003",
    "sg:province":"C\u00f3rdoba",
    "wof:name":"Povedano Ortiz Antonio",
    "wof:placetype":"venue"
},
  "geometry": {"coordinates":[-4.7765851021,37.8793869019],"type":"Point"}
}