{
  "type": "Feature",
  "properties": {
    "iso:country":"ES",
    "sg:address":"Calle de San Francisco, S/n",
    "sg:city":"Castro Urdiales",
    "sg:orig_category":"Distribuci\u00d3n De Petr\u00d3leo Y Derivados",
    "sg:phone":"+34 942 87 13 28",
    "sg:postcode":"39700",
    "sg:province":"Cantabria",
    "wof:name":"Quinser S.cv.",
    "wof:placetype":"venue"
},
  "geometry": {"coordinates":[-3.2209188938,43.3838615417],"type":"Point"}
}