{
  "type": "Feature",
  "properties": {
    "addr:full":"Ctra Jerez-cartagena, Km. 0076,0 Algodonales C\u00e1diz 11680",
    "addr:postcode":"11680",
    "addr:street":"Ctra Jerez-Cartagena Km. 0076,0;Ca\u0301Diz",
    "iso:country":"ES",
    "sg:address":"Ctra Jerez-cartagena, Km. 0076,0",
    "sg:city":"Algodonales",
    "sg:orig_category":"Arquitectos",
    "sg:phone":"+34 956 13 75 36",
    "sg:postcode":"11680",
    "sg:province":"C\u00e1diz",
    "wof:name":"Ortiz Ramos Jose Luis",
    "wof:placetype":"venue"
},
  "geometry": {"coordinates":[-5.405064106,36.8808784485],"type":"Point"}
}