{
  "type": "Feature",
  "properties": {
    "iso:country":"ES",
    "sg:address":"Carrer de Major, 22",
    "sg:city":"Santa Coloma De Queralt",
    "sg:orig_category":"Laboratorios Y Trabajos De Fotograf\u00cda, V\u00cddeo Y Cine",
    "sg:phone":"+34 977 88 04 88",
    "sg:postcode":"43420",
    "sg:province":"Tarragona",
    "wof:name":"Plaza Serra Pedro",
    "wof:placetype":"venue"
},
  "geometry": {"coordinates":[1.3835279942,41.5316505432],"type":"Point"}
}