{
  "type": "Feature",
  "properties": {
    "iso:country":"ES",
    "sg:address":"Avda Abrantes, 40",
    "sg:city":"Madrid",
    "sg:orig_category":"Librer\u00cdas",
    "sg:phone":"+34 915 60 58 03",
    "sg:postcode":"28025",
    "sg:province":"Madrid",
    "wof:name":"Exposito Tierno Juan Jose",
    "wof:placetype":"venue"
},
  "geometry": {"coordinates":[-3.7269330025,40.3817901611],"type":"Point"}
}