{
  "type": "Feature",
  "properties": {
    "addr:full":"Calle de Amigos Del Pais, 2 Tudela Navarra 31500",
    "addr:housenumber":"2",
    "addr:postcode":"31500",
    "addr:street":"Calle De Amigos Del Pais",
    "iso:country":"ES",
    "sg:address":"Calle de Amigos Del Pais, 2",
    "sg:city":"Tudela",
    "sg:orig_category":"Farmacias",
    "sg:phone":"+34 948 82 85 88",
    "sg:postcode":"31500",
    "sg:province":"Navarra",
    "wof:name":"Margallo Lana Rosario Pilar",
    "wof:placetype":"venue"
},
  "geometry": {"coordinates":[-1.6125549078,42.0594100952],"type":"Point"}
}