{
  "type": "Feature",
  "properties": {
    "addr:full":"Carr Sueca, 26 Mareny De Barraquetes Valencia 46419",
    "addr:housenumber":"26",
    "addr:postcode":"46419",
    "addr:street":"Carr Sueca",
    "iso:country":"ES",
    "sg:address":"Carr Sueca, 26",
    "sg:city":"Mareny De Barraquetes",
    "sg:orig_category":"Fabricaci\u00d3n De Mobiliario De Oficina",
    "sg:phone":"+34 961 76 24 69",
    "sg:postcode":"46419",
    "sg:province":"Valencia",
    "wof:name":"Mareny 2004 S.l.",
    "wof:placetype":"venue"
},
  "geometry": {"coordinates":[-0.2640939951,39.2566146851],"type":"Point"}
}