{
  "type": "Feature",
  "properties": {
    "addr:full":"Pl Espanya, 14 Pineda Mar Barcelona 08397",
    "addr:housenumber":"14",
    "addr:postcode":"08397",
    "addr:street":"Pl Espanya;Barcelona",
    "iso:country":"ES",
    "sg:address":"Pl Espanya, 14",
    "sg:city":"Pineda Mar",
    "sg:orig_category":"Carnicer\u00cdas, Carnicer\u00cdas",
    "sg:phone":"+34 937 67 19 39",
    "sg:postcode":"08397",
    "sg:province":"Barcelona",
    "wof:name":"Sala Medico Josep Maria",
    "wof:placetype":"venue"
},
  "geometry": {"coordinates":[2.6879639626,41.6261978149],"type":"Point"}
}