{
  "type": "Feature",
  "properties": {
    "addr:full":"Calle de Acapulco, 21 Grao Castell\u00f3n 12100",
    "addr:housenumber":"21",
    "addr:postcode":"12100",
    "addr:street":"Calle De Acapulco;Castello\u0301N",
    "iso:country":"ES",
    "sg:address":"Calle de Acapulco, 21",
    "sg:city":"Grao",
    "sg:orig_category":"Agencias Y Agentes Comerciales, Representantes",
    "sg:phone":"+34 964 28 07 45",
    "sg:postcode":"12100",
    "sg:province":"Castell\u00f3n",
    "wof:name":"Castells Badenes Juan",
    "wof:placetype":"venue"
},
  "geometry": {"coordinates":[0.0220144,39.9843254089],"type":"Point"}
}