{
  "type": "Feature",
  "properties": {
    "iso:country":"ES",
    "sg:address":"Calle de Vicente Gallego, 8",
    "sg:city":"Ajalvir",
    "sg:orig_category":"Art\u00cdculos De Decoraci\u00d3n (fabricaci\u00d3n Y Al Por Mayor)",
    "sg:phone":"+34 918 84 44 47",
    "sg:postcode":"28864",
    "sg:province":"Madrid",
    "wof:name":"Arq Arquitectura Interior S.l.",
    "wof:placetype":"venue"
},
  "geometry": {"coordinates":[-3.4902391434,40.5313453674],"type":"Point"}
}