{
  "type": "Feature",
  "properties": {
    "addr:full":"Ferreiros, 1 Pontedeume La Coru\u00f1a 15600",
    "addr:housenumber":"1",
    "addr:postcode":"15600",
    "addr:street":"Ferreiros;La Corun\u0303A",
    "iso:country":"ES",
    "sg:address":"Ferreiros, 1",
    "sg:city":"Pontedeume",
    "sg:orig_category":"Transporte En General",
    "sg:phone":"+34 981 43 07 93",
    "sg:postcode":"15600",
    "sg:province":"La Coru\u00f1a",
    "wof:name":"Buyo Amado Joaquin",
    "wof:placetype":"venue"
},
  "geometry": {"coordinates":[-8.1699361801,43.4068984985],"type":"Point"}
}