{
  "type": "Feature",
  "properties": {
    "iso:country":"ES",
    "sg:address":"Calle de Rio Jarama, S/n",
    "sg:city":"Poligono Sta M. De Benquerencia",
    "sg:orig_category":"Empresas De Carpinter\u00cda De Madera",
    "sg:phone":"+34 925 24 04 04",
    "sg:postcode":"45007",
    "sg:province":"Toledo",
    "wof:name":"Manufacturas Madereras Del Tajo S.l.l.",
    "wof:placetype":"venue"
},
  "geometry": {"coordinates":[-3.9589040279,39.8693008423],"type":"Point"}
}