{
  "type": "Feature",
  "properties": {
    "addr:full":"Avda San Juan De La Salle, 71 Sevilla Sevilla 41008",
    "addr:housenumber":"71",
    "addr:postcode":"41008",
    "addr:street":"Avda San Juan De La Salle",
    "iso:country":"ES",
    "sg:address":"Avda San Juan De La Salle, 71",
    "sg:city":"Sevilla",
    "sg:orig_category":"Quincaller\u00cda (al Por Menor)",
    "sg:phone":"+34 954 94 39 60",
    "sg:postcode":"41008",
    "sg:province":"Sevilla",
    "wof:name":"Herrero Rivero Jose",
    "wof:placetype":"venue"
},
  "geometry": {"coordinates":[-5.9711298943,37.4082107544],"type":"Point"}
}