{
  "type": "Feature",
  "properties": {
    "iso:country":"ES",
    "sg:address":"Ctra Marmoles (de Los), S/n",
    "sg:city":"Arrecife",
    "sg:orig_category":"Transportes Por V\u00cdas Navegables",
    "sg:phone":"+34 928 81 68 00",
    "sg:postcode":"35500",
    "sg:province":"Las Palmas",
    "wof:name":"Transportes Brito S. L.",
    "wof:placetype":"venue"
},
  "geometry": {"coordinates":[-13.5436439514,28.9689598083],"type":"Point"}
}