{
  "type": "Feature",
  "properties": {
    "addr:full":"Calle de Juan Carlos I Rey De Espa\u00d1a, 8 Badajoz Badajoz 06001",
    "addr:housenumber":"8",
    "addr:postcode":"06001",
    "addr:street":"Calle De Juan Carlos I Rey;Espan\u0303A",
    "iso:country":"ES",
    "sg:address":"Calle de Juan Carlos I Rey De Espa\u00d1a, 8",
    "sg:city":"Badajoz",
    "sg:orig_category":"Abogados",
    "sg:phone":"+34 924 24 30 83",
    "sg:postcode":"06001",
    "sg:province":"Badajoz",
    "wof:name":"Giralt Ramirez Mateo",
    "wof:placetype":"venue"
},
  "geometry": {"coordinates":[-6.9725251198,38.8782501221],"type":"Point"}
}