{
  "type": "Feature",
  "properties": {
    "iso:country":"ES",
    "sg:address":"Carr Sant Francesc De Borja, 38",
    "sg:city":"Gandia",
    "sg:orig_category":"Ropa Para Caballeros (al Por Menor)",
    "sg:phone":"+34 962 87 36 10",
    "sg:postcode":"46700",
    "sg:province":"Valencia",
    "wof:name":"Antoni Gomar S.l.",
    "wof:placetype":"venue"
},
  "geometry": {"coordinates":[-0.1824833006,38.9673995972],"type":"Point"}
}