{
  "type": "Feature",
  "properties": {
    "iso:country":"ES",
    "sg:address":"Trujillo, 2",
    "sg:city":"Miajadas",
    "sg:orig_category":"Droguer\u00cdas (al Por Menor)",
    "sg:phone":"+34 927 34 70 17",
    "sg:postcode":"10100",
    "sg:province":"C\u00e1ceres",
    "wof:name":"Sauceda Babiano Martina",
    "wof:placetype":"venue"
},
  "geometry": {"coordinates":[-5.9067378044,39.1518516541],"type":"Point"}
}