{
  "type": "Feature",
  "properties": {
    "addr:full":"Ctra Fermoselle, S/n Bermillo Sayago Zamora 49200",
    "addr:housenumber":"s",
    "addr:postcode":"49200",
    "addr:street":"Ctra Fermoselle;/ N;Zamora",
    "iso:country":"ES",
    "sg:address":"Ctra Fermoselle, S/n",
    "sg:city":"Bermillo Sayago",
    "sg:orig_category":"Supermercados Y Hipermercados",
    "sg:phone":"+34 980 61 02 43",
    "sg:postcode":"49200",
    "sg:province":"Zamora",
    "wof:name":"Robles Cortes Jesus",
    "wof:placetype":"venue"
},
  "geometry": {"coordinates":[-6.0249538422,41.3903694153],"type":"Point"}
}