{
  "type": "Feature",
  "properties": {
    "addr:full":"Calle de Arroyuelo, 15 Nogales De Pisuerga Palencia 34489",
    "addr:housenumber":"15",
    "addr:postcode":"34489",
    "addr:street":"Calle De Arroyuelo",
    "iso:country":"ES",
    "sg:address":"Calle de Arroyuelo, 15",
    "sg:city":"Nogales De Pisuerga",
    "sg:classifiers":[
        {
            "category":"Taxi",
            "type":"Transportation"
        }
    ],
    "sg:phone":"+34 979 13 31 55",
    "sg:postcode":"34489",
    "sg:province":"Palencia",
    "wof:name":"Jimeno Iba\u00f1ez Angel Miguel",
    "wof:placetype":"venue"
},
  "geometry": {"coordinates":[-4.3072075844,42.6708717346],"type":"Point"}
}