{
  "type": "Feature",
  "properties": {
    "iso:country":"ES",
    "sg:address":"Calle de Diaz De Mendoza, 17",
    "sg:city":"Zaragoza",
    "sg:orig_category":"Lencer\u00cda Femenina, Corseter\u00cda, Trajes De Ba\u00d1o (al Por Menor)",
    "sg:phone":"+34 976 75 41 48",
    "sg:postcode":"50009",
    "sg:province":"Zaragoza",
    "wof:name":"Iberjace S.l.",
    "wof:placetype":"venue"
},
  "geometry": {"coordinates":[-0.9103469253,41.6431999207],"type":"Point"}
}