{
  "type": "Feature",
  "properties": {
    "iso:country":"ES",
    "sg:address":"Calle de Covarrubias, 38",
    "sg:city":"Madrid",
    "sg:orig_category":"Agencias De Viajes",
    "sg:phone":"+34 915 94 17 00",
    "sg:postcode":"28010",
    "sg:province":"Madrid",
    "sg:website":"www.maferias.com",
    "wof:name":"Agencia Solymar Peninsular De Viajes S.a.l.",
    "wof:placetype":"venue"
},
  "geometry": {"coordinates":[-3.6982195377,40.4315452576],"type":"Point"}
}