{
  "type": "Feature",
  "properties": {
    "iso:country":"ES",
    "sg:address":"Carr Carme Verdaguer, 24",
    "sg:city":"Igualada",
    "sg:orig_category":"Urbanistas",
    "sg:phone":"+34 938 04 09 04",
    "sg:postcode":"08700",
    "sg:province":"Barcelona",
    "wof:name":"Planas Vilella Jose Maria",
    "wof:placetype":"venue"
},
  "geometry": {"coordinates":[1.6167069674,41.5833435059],"type":"Point"}
}