{
  "type": "Feature",
  "properties": {
    "iso:country":"ES",
    "sg:address":"Calle de Jaime I El Conquistador, 3",
    "sg:city":"San Miguel",
    "sg:orig_category":"Cl\u00cdnicas Dentales",
    "sg:phone":"+34 968 24 79 25",
    "sg:postcode":"30008",
    "sg:province":"Murcia",
    "wof:name":"Bravo Gonzalez Luis Alberto",
    "wof:placetype":"venue"
},
  "geometry": {"coordinates":[-1.1305160522,37.9896011353],"type":"Point"}
}