{
  "type": "Feature",
  "properties": {
    "addr:full":"Cmno Paredes, Km. 0004,5 Paredes Asturias 33420",
    "addr:postcode":"33420",
    "addr:street":"Cmno Paredes Km. 0004,5",
    "iso:country":"ES",
    "sg:address":"Cmno Paredes, Km. 0004,5",
    "sg:city":"Paredes",
    "sg:orig_category":"Muebles, Minoristas",
    "sg:phone":"+34 985 73 20 91",
    "sg:postcode":"33420",
    "sg:province":"Asturias",
    "sg:website":"www.natuzzi.es",
    "wof:name":"Natuzzi Iberica S.a.",
    "wof:placetype":"venue"
},
  "geometry": {"coordinates":[-5.8106489182,43.4009132385],"type":"Point"}
}