{
  "type": "Feature",
  "properties": {
    "addr:full":"Calle de Niebla, 18 Sevilla Sevilla 41011",
    "addr:housenumber":"18",
    "addr:postcode":"41011",
    "addr:street":"Calle De Niebla",
    "iso:country":"ES",
    "sg:address":"Calle de Niebla, 18",
    "sg:city":"Sevilla",
    "sg:orig_category":"Artes Gr\u00c1ficas, Artes Pl\u00c1sticas (curso)",
    "sg:phone":"+34 954 27 69 80",
    "sg:postcode":"41011",
    "sg:province":"Sevilla",
    "wof:name":"Franco Cardo Francisco",
    "wof:placetype":"venue"
},
  "geometry": {"coordinates":[-6.0006518364,37.3777885437],"type":"Point"}
}