{
  "type": "Feature",
  "properties": {
    "iso:country":"ES",
    "sg:address":"Calle de Aquilino Sanchez, 2",
    "sg:city":"Tudela Duero",
    "sg:orig_category":"Inform\u00c1tica, Ofim\u00c1tica (estudios, Asesor\u00cda, Ingenier\u00cda, Formaci\u00d3n)",
    "sg:phone":"+34 983 52 06 70",
    "sg:postcode":"47320",
    "sg:province":"Valladolid",
    "wof:name":"Mendez Santa Cruz Ignacio",
    "wof:placetype":"venue"
},
  "geometry": {"coordinates":[-4.5823979378,41.5872840881],"type":"Point"}
}