{
  "type": "Feature",
  "properties": {
    "iso:country":"ES",
    "sg:address":"Trva Etxesakan-zeharkalea, S/n",
    "sg:city":"Zizur Mayor",
    "sg:orig_category":"Empresas De Vigilancia, Guardia Y Protecci\u00d3n",
    "sg:phone":"+34 948 18 28 09",
    "sg:postcode":"31180",
    "sg:province":"Navarra",
    "wof:name":"Cis Compa\u00d1ia Integral De Seguridad S.a.",
    "wof:placetype":"venue"
},
  "geometry": {"coordinates":[-1.6957240105,42.7915496826],"type":"Point"}
}