{
  "type": "Feature",
  "properties": {
    "addr:full":"Avda Buenos Aires, 135 Ourense Ourense 32004",
    "addr:housenumber":"135",
    "addr:postcode":"32004",
    "addr:street":"Avda Buenos Aires",
    "iso:country":"ES",
    "sg:address":"Avda Buenos Aires, 135",
    "sg:city":"Ourense",
    "sg:orig_category":"Molduras, Junquillos, Listones Y Molduras Perforadas",
    "sg:phone":"+34 988 24 07 36",
    "sg:postcode":"32004",
    "sg:province":"Ourense",
    "wof:name":"Gayo De Andres Luis",
    "wof:placetype":"venue"
},
  "geometry": {"coordinates":[-7.8564119339,42.3424034119],"type":"Point"}
}