{
  "type": "Feature",
  "properties": {
    "iso:country":"ES",
    "sg:address":"Calle de Gobernador Fernandez Jimenez (del), 17",
    "sg:city":"Segovia",
    "sg:orig_category":"Arquitectos",
    "sg:phone":"+34 921 42 89 31",
    "sg:postcode":"40002",
    "sg:province":"Segovia",
    "wof:name":"Sousa Sancho Carlos De",
    "wof:placetype":"venue"
},
  "geometry": {"coordinates":[-4.1189317703,40.9445381165],"type":"Point"}
}