{
  "type": "Feature",
  "properties": {
    "iso:country":"ES",
    "sg:address":"Calle de Gibraltar Espa\u00d1ol, 58",
    "sg:city":"Torrijos",
    "sg:orig_category":"Molduras, Junquillos, Listones Y Molduras Perforadas",
    "sg:phone":"+34 925 76 05 23",
    "sg:postcode":"45500",
    "sg:province":"Toledo",
    "wof:name":"Lopez Rodriguez Francisco Javier",
    "wof:placetype":"venue"
},
  "geometry": {"coordinates":[-4.2820892334,39.9802818298],"type":"Point"}
}