{
  "type": "Feature",
  "properties": {
    "iso:country":"ES",
    "sg:address":"Calle de Elena Montagut, 1",
    "sg:city":"Huelva",
    "sg:orig_category":"M\u00c9dicos: An\u00c1lisis Cl\u00cdnicos",
    "sg:phone":"+34 959 15 94 31",
    "sg:postcode":"21005",
    "sg:province":"Huelva",
    "wof:name":"Pascual Martinez Magdalena",
    "wof:placetype":"venue"
},
  "geometry": {"coordinates":[-6.9427042007,37.2803421021],"type":"Point"}
}