{
  "type": "Feature",
  "properties": {
    "addr:full":"Carrer de Picasso, 2 Sant Feliu Llobregat Barcelona 08980",
    "addr:housenumber":"2",
    "addr:postcode":"08980",
    "addr:street":"Carrer De Picasso",
    "iso:country":"ES",
    "sg:address":"Carrer de Picasso, 2",
    "sg:city":"Sant Feliu Llobregat",
    "sg:orig_category":"Art\u00cdculos De Decoraci\u00d3n",
    "sg:phone":"+34 936 66 35 59",
    "sg:postcode":"08980",
    "sg:province":"Barcelona",
    "wof:name":"Aguilella Fernandez Maria Dolores",
    "wof:placetype":"venue"
},
  "geometry": {"coordinates":[2.0437073708,41.3868637085],"type":"Point"}
}