{
  "type": "Feature",
  "properties": {
    "addr:full":"Calle de Canos, 4 Alameda M\u00e1laga 29530",
    "addr:housenumber":"4",
    "addr:postcode":"29530",
    "addr:street":"Calle De Canos;Alameda Ma\u0301Laga",
    "iso:country":"ES",
    "sg:address":"Calle de Canos, 4",
    "sg:city":"Alameda",
    "sg:orig_category":"Quincaller\u00cda (al Por Menor)",
    "sg:phone":"+34 952 71 01 82",
    "sg:postcode":"29530",
    "sg:province":"M\u00e1laga",
    "wof:name":"Aviles Lopez Benito Jesus",
    "wof:placetype":"venue"
},
  "geometry": {"coordinates":[-4.6609358788,37.2078475952],"type":"Point"}
}