{
  "type": "Feature",
  "properties": {
    "addr:full":"Calle de Landako Kalea, 28 Amurrio \u00c1lava 01470",
    "addr:housenumber":"28",
    "addr:postcode":"01470",
    "addr:street":"Calle De Landako Kalea",
    "iso:country":"ES",
    "sg:address":"Calle de Landako Kalea, 28",
    "sg:city":"Amurrio",
    "sg:orig_category":"Farmacias",
    "sg:phone":"+34 945 39 37 68",
    "sg:postcode":"01470",
    "sg:province":"\u00c1lava",
    "wof:name":"Pereda Garcia Jose Luis",
    "wof:placetype":"venue"
},
  "geometry": {"coordinates":[-2.9978060722,43.0499382019],"type":"Point"}
}