{
  "type": "Feature",
  "properties": {
    "addr:full":"Plaz Xuquer, 4 Valencia Valencia 46021",
    "addr:housenumber":"4",
    "addr:postcode":"46021",
    "addr:street":"Plaz Xuquer",
    "iso:country":"ES",
    "sg:address":"Plaz Xuquer, 4",
    "sg:city":"Valencia",
    "sg:orig_category":"Material Y Suministros Para Peluquer\u00cda",
    "sg:phone":"+34 963 62 92 31",
    "sg:postcode":"46021",
    "sg:province":"Valencia",
    "wof:name":"Cromozona Valencia S.l.",
    "wof:placetype":"venue"
},
  "geometry": {"coordinates":[-0.3505600095,39.4760665894],"type":"Point"}
}