{
  "type": "Feature",
  "properties": {
    "addr:full":"Calle de Sangenjo, 5 Madrid Madrid 28034",
    "addr:housenumber":"5",
    "addr:postcode":"28034",
    "addr:street":"Calle De Sangenjo",
    "iso:country":"ES",
    "sg:address":"Calle de Sangenjo, 5",
    "sg:city":"Madrid",
    "sg:orig_category":"M\u00c9dicos: Estomatolog\u00cda",
    "sg:phone":"+34 917 38 00 48",
    "sg:postcode":"28034",
    "sg:province":"Madrid",
    "wof:name":"Cassan Schor Walter Horacio",
    "wof:placetype":"venue"
},
  "geometry": {"coordinates":[-3.7009179592,40.4847412109],"type":"Point"}
}