{
  "type": "Feature",
  "properties": {
    "addr:full":"Plaz Madrid, 2 Valladolid Valladolid 47001",
    "addr:housenumber":"2",
    "addr:postcode":"47001",
    "addr:street":"Madrid",
    "iso:country":"ES",
    "sg:address":"Plaz Madrid, 2",
    "sg:city":"Valladolid",
    "sg:orig_category":"Ropa Para Ni\u00d1os (al Por Menor)",
    "sg:phone":"+34 983 30 35 32",
    "sg:postcode":"47001",
    "sg:province":"Valladolid",
    "wof:name":"Herrero Calvo Felix",
    "wof:placetype":"venue"
},
  "geometry": {"coordinates":[-4.7254872322,41.6482582092],"type":"Point"}
}