{
  "type": "Feature",
  "properties": {
    "addr:full":"Puntarenas, S/n Maspalomas Las Palmas 35100",
    "addr:housenumber":"s / n",
    "addr:postcode":"35100",
    "iso:country":"ES",
    "sg:address":"Puntarenas, S/n",
    "sg:city":"Maspalomas",
    "sg:orig_category":"Organismos Y Centros De Vacaciones Y Esparcimiento Para Ni\u00d1os Y Adolescentes",
    "sg:phone":"+34 928 14 85 25",
    "sg:postcode":"35100",
    "sg:province":"Las Palmas",
    "wof:name":"Demitz  Gerhard",
    "wof:placetype":"venue"
},
  "geometry": {"coordinates":[-15.5830888748,27.7700748444],"type":"Point"}
}