{
  "type": "Feature",
  "properties": {
    "addr:full":"Carrer de Roser, 41 Reus Tarragona 43201",
    "addr:housenumber":"41",
    "addr:postcode":"43201",
    "addr:street":"Carrer De Roser",
    "iso:country":"ES",
    "sg:address":"Carrer de Roser, 41",
    "sg:city":"Reus",
    "sg:orig_category":"Empresas De Carpinter\u00cda",
    "sg:phone":"+34 977 34 20 93",
    "sg:postcode":"43201",
    "sg:province":"Tarragona",
    "wof:name":"Vila Gomis Josep",
    "wof:placetype":"venue"
},
  "geometry": {"coordinates":[1.1120699644,41.1573295593],"type":"Point"}
}