{
  "type": "Feature",
  "properties": {
    "addr:full":"Calle de Colegiata La, 7 Nava Asturias 33520",
    "addr:housenumber":"7",
    "addr:postcode":"33520",
    "addr:street":"Calle De Colegiata La",
    "iso:country":"ES",
    "sg:address":"Calle de Colegiata La, 7",
    "sg:city":"Nava",
    "sg:orig_category":"Parafarmacias",
    "sg:phone":"+34 985 71 66 33",
    "sg:postcode":"33520",
    "sg:province":"Asturias",
    "wof:name":"Rodriguez Ribeiro Marta Susana",
    "wof:placetype":"venue"
},
  "geometry": {"coordinates":[-5.5098028183,43.3586387634],"type":"Point"}
}