{
  "type": "Feature",
  "properties": {
    "addr:full":"Rond Prim, 59 Mataro Barcelona 08302",
    "addr:housenumber":"59",
    "addr:postcode":"08302",
    "addr:street":"Mataro Barcelona",
    "iso:country":"ES",
    "sg:address":"Rond Prim, 59",
    "sg:city":"Mataro",
    "sg:orig_category":"M\u00c9dicos: Cirug\u00cda Ortop\u00c9dica Y Traumatolog\u00cda",
    "sg:phone":"+34 937 57 90 69",
    "sg:postcode":"08302",
    "sg:province":"Barcelona",
    "wof:name":"Babot Andreu Eduardo",
    "wof:placetype":"venue"
},
  "geometry": {"coordinates":[2.4358332157,41.5392799377],"type":"Point"}
}