{
  "type": "Feature",
  "properties": {
    "addr:full":"Pase San Juan Bosco, 53 Monzon Huesca 22400",
    "addr:housenumber":"53",
    "addr:postcode":"22400",
    "addr:street":"San Juan Bosco",
    "iso:country":"ES",
    "sg:address":"Pase San Juan Bosco, 53",
    "sg:city":"Monzon",
    "sg:orig_category":"Aparatos E Instalaci\u00d3n De Regad\u00cdos",
    "sg:phone":"+34 974 40 18 53",
    "sg:postcode":"22400",
    "sg:province":"Huesca",
    "wof:name":"Pe\u00f1a-uruel S.l.",
    "wof:placetype":"venue"
},
  "geometry": {"coordinates":[0.1852879971,41.9168357849],"type":"Point"}
}