{
  "type": "Feature",
  "properties": {
    "addr:full":"Calle de Mayor, 36 Albacete Albacete 02002",
    "addr:housenumber":"36",
    "addr:postcode":"02002",
    "addr:street":"Calle De Mayor",
    "iso:country":"ES",
    "sg:address":"Calle de Mayor, 36",
    "sg:city":"Albacete",
    "sg:orig_category":"Centros De Coordinaci\u00d3n",
    "sg:phone":"+34 967 52 41 28",
    "sg:postcode":"02002",
    "sg:province":"Albacete",
    "wof:name":"Martinez Corcoles Ana",
    "wof:placetype":"venue"
},
  "geometry": {"coordinates":[-1.8538589478,38.9929885864],"type":"Point"}
}