{
  "type": "Feature",
  "properties": {
    "addr:full":"Rua Pi Y Margall, 62 Vigo Pontevedra 36202",
    "addr:housenumber":"62",
    "addr:postcode":"36202",
    "addr:street":"Rua Pi Y Margall",
    "iso:country":"ES",
    "sg:address":"Rua Pi Y Margall, 62",
    "sg:city":"Vigo",
    "sg:orig_category":"Inversiones",
    "sg:phone":"+34 986 24 18 62",
    "sg:postcode":"36202",
    "sg:province":"Pontevedra",
    "wof:name":"Inversiones 8102 S.l.",
    "wof:placetype":"venue"
},
  "geometry": {"coordinates":[-8.7310142517,42.2320251465],"type":"Point"}
}