{
  "type": "Feature",
  "properties": {
    "addr:full":"Ctr. De La Roda, 37 Motilla Palancar Cuenca 16200",
    "addr:housenumber":"37",
    "addr:postcode":"16200",
    "addr:street":"La Roda",
    "iso:country":"ES",
    "sg:address":"Ctr. De La Roda, 37",
    "sg:city":"Motilla Palancar",
    "sg:classifiers":[
        {
            "category":"Communications",
            "type":"Services"
        }
    ],
    "sg:phone":"+34 969 33 21 30",
    "sg:postcode":"16200",
    "sg:province":"Cuenca",
    "sg:tags":[
        "televisiones",
        "y",
        "radio"
    ],
    "wof:name":"Coyseas S.l.-radio 90",
    "wof:placetype":"venue"
},
  "geometry": {"coordinates":[-1.9062039852,39.5607185364],"type":"Point"}
}