{
  "type": "Feature",
  "properties": {
    "iso:country":"ES",
    "sg:address":"Calle de Paz, 3",
    "sg:city":"Ciudad Real",
    "sg:orig_category":"Locales Y Clases De Danza",
    "sg:phone":"+34 926 22 87 41",
    "sg:postcode":"13003",
    "sg:province":"Ciudad Real",
    "wof:name":"Navas Arriaga Maria Aranzazu",
    "wof:placetype":"venue"
},
  "geometry": {"coordinates":[-3.9289009571,38.9889602661],"type":"Point"}
}