{
  "type": "Feature",
  "properties": {
    "iso:country":"ES",
    "sg:address":"Carrer de Joaquin Costa, 71",
    "sg:city":"Sabadell",
    "sg:orig_category":"Maquinaria Para Industrias Diversas",
    "sg:phone":"+34 937 26 09 66",
    "sg:postcode":"08206",
    "sg:province":"Barcelona",
    "sg:website":"www.paifer.com",
    "wof:name":"Paifer S. A.",
    "wof:placetype":"venue"
},
  "geometry": {"coordinates":[2.0961129665,41.547290802],"type":"Point"}
}