{
  "type": "Feature",
  "properties": {
    "iso:country":"ES",
    "sg:address":"Port Empuries-a, 7",
    "sg:city":"Empuriabrava",
    "sg:orig_category":"Asesor\u00cda Fiscal Y Jur\u00cddica",
    "sg:phone":"+34 972 45 25 45",
    "sg:postcode":"17487",
    "sg:province":"Girona",
    "wof:name":"Assesorament I Gestio Trevol 6 S.l.",
    "wof:placetype":"venue"
},
  "geometry": {"coordinates":[3.1211709976,42.2478675842],"type":"Point"}
}