{
  "type": "Feature",
  "properties": {
    "addr:full":"Huertas, S/n Fuentes Cuenca 16193",
    "addr:housenumber":"/ n",
    "addr:postcode":"16193",
    "addr:street":"Huertas S",
    "iso:country":"ES",
    "sg:address":"Huertas, S/n",
    "sg:city":"Fuentes",
    "sg:orig_category":"Piscinas (establecimientos)",
    "sg:phone":"+34 969 25 71 39",
    "sg:postcode":"16193",
    "sg:province":"Cuenca",
    "wof:name":"Ayuntamiento",
    "wof:placetype":"venue"
},
  "geometry": {"coordinates":[-2.0223650932,39.9503517151],"type":"Point"}
}