{
  "type": "Feature",
  "properties": {
    "addr:full":"Cuarzo, 18 Arganda Madrid 28500",
    "addr:housenumber":"18",
    "addr:postcode":"28500",
    "addr:street":"Cuarzo",
    "iso:country":"ES",
    "sg:address":"Cuarzo, 18",
    "sg:city":"Arganda",
    "sg:orig_category":"Panader\u00cdas, Panader\u00cdas",
    "sg:phone":"+34 918 72 91 83",
    "sg:postcode":"28500",
    "sg:province":"Madrid",
    "wof:name":"Horno Madripan La Vallecana",
    "wof:placetype":"venue"
},
  "geometry": {"coordinates":[-3.4406979084,40.2999954224],"type":"Point"}
}