{
  "type": "Feature",
  "properties": {
    "addr:full":"Calle de Pirita, 33 Valladolid Valladolid 47012",
    "addr:housenumber":"33",
    "addr:postcode":"47012",
    "addr:street":"Calle De Pirita",
    "iso:country":"ES",
    "sg:address":"Calle de Pirita, 33",
    "sg:city":"Valladolid",
    "sg:orig_category":"Promotores Constructores",
    "sg:phone":"+34 983 20 37 30",
    "sg:postcode":"47012",
    "sg:province":"Valladolid",
    "wof:name":"Collosa",
    "wof:placetype":"venue"
},
  "geometry": {"coordinates":[-4.705851078,41.6233787537],"type":"Point"}
}