{
  "type": "Feature",
  "properties": {
    "addr:full":"J Jnez Lopez-vquz, S/n Peligros Granada 18210",
    "addr:housenumber":"s / n",
    "addr:postcode":"18210",
    "iso:country":"ES",
    "sg:address":"J Jnez Lopez-vquz, S/n",
    "sg:city":"Peligros",
    "sg:orig_category":"Asesor\u00cda Sobre Comunicaci\u00d3n De Empresas",
    "sg:phone":"+34 958 40 10 26",
    "sg:postcode":"18210",
    "sg:province":"Granada",
    "wof:name":"Asesoriaalvarez&friass.l.",
    "wof:placetype":"venue"
},
  "geometry": {"coordinates":[-3.6268463135,37.2365036011],"type":"Point"}
}