{
  "type": "Feature",
  "properties": {
    "iso:country":"ES",
    "sg:address":"Carr Castella, 30",
    "sg:city":"Eivissa",
    "sg:orig_category":"Ropa Para Beb\u00c9s Y Ni\u00d1os (confecci\u00d3n, Al Por Mayor)",
    "sg:phone":"+34 971 30 48 91",
    "sg:postcode":"07800",
    "sg:province":"Islas Baleares",
    "wof:name":"Baidi Abid Sadia",
    "wof:placetype":"venue"
},
  "geometry": {"coordinates":[1.4271787405,38.9095115662],"type":"Point"}
}