{
  "type": "Feature",
  "properties": {
    "addr:full":"Avda Bruselas (de), 12 Alcobendas Madrid 28108",
    "addr:housenumber":"12",
    "addr:postcode":"28108",
    "addr:street":"Avda Bruselas De",
    "iso:country":"ES",
    "sg:address":"Avda Bruselas (de), 12",
    "sg:city":"Alcobendas",
    "sg:orig_category":"Fabricaci\u00d3n De Bibliotecas Y Estanter\u00cdas",
    "sg:phone":"+34 916 62 30 32",
    "sg:postcode":"28108",
    "sg:province":"Madrid",
    "sg:website":"www.esfidelity.com",
    "wof:name":"Aramark S.l.",
    "wof:placetype":"venue"
},
  "geometry": {"coordinates":[-3.6340632439,40.5314903259],"type":"Point"}
}