{
  "type": "Feature",
  "properties": {
    "iso:country":"ES",
    "sg:address":"Calle de Postas, 16",
    "sg:city":"Ciudad Real",
    "sg:orig_category":"Complementos De Vestir (al Por Menor)",
    "sg:phone":"+34 926 21 48 54",
    "sg:postcode":"13001",
    "sg:province":"Ciudad Real",
    "wof:name":"Herguido Delgado Maria Jose",
    "wof:placetype":"venue"
},
  "geometry": {"coordinates":[-3.9298670292,38.9848861694],"type":"Point"}
}