{
  "type": "Feature",
  "properties": {
    "iso:country":"ES",
    "sg:address":"Bda Viladecols, 2",
    "sg:city":"Barcelona",
    "sg:orig_category":"Caf\u00c9s, Bares, Cervecer\u00cdas",
    "sg:phone":"+34 933 19 05 33",
    "sg:postcode":"08002",
    "sg:province":"Barcelona",
    "wof:name":"Segui Domingo Estel",
    "wof:placetype":"venue"
},
  "geometry": {"coordinates":[2.1793711185,41.3819961548],"type":"Point"}
}