{
  "type": "Feature",
  "properties": {
    "addr:full":"Carr Ramon De Cabrera, 5 Bisbal D'emporda Girona 17100",
    "addr:housenumber":"5",
    "addr:postcode":"17100",
    "addr:street":"Carr Ramon De Cabrera",
    "iso:country":"ES",
    "sg:address":"Carr Ramon De Cabrera, 5",
    "sg:city":"Bisbal D'emporda",
    "sg:orig_category":"Institutos De Belleza (productos Y Aparatos)",
    "sg:phone":"+34 972 64 21 76",
    "sg:postcode":"17100",
    "sg:province":"Girona",
    "wof:name":"Llenas Torrent Anna",
    "wof:placetype":"venue"
},
  "geometry": {"coordinates":[2.813131094,41.9749221802],"type":"Point"}
}