{
  "type": "Feature",
  "properties": {
    "iso:country":"ES",
    "sg:address":"Calle de Mateo Errota, 3",
    "sg:city":"Donostia-san Sebastian",
    "sg:orig_category":"Fabricaci\u00d3n, Instalaci\u00d3n De Armarios",
    "sg:phone":"+34 943 47 22 17",
    "sg:postcode":"20014",
    "sg:province":"Guip\u00f9zcoa",
    "sg:website":"www.lauzzeta.com",
    "wof:name":"Lauzeta S.l.",
    "wof:placetype":"venue"
},
  "geometry": {"coordinates":[-1.9457269907,43.3015060425],"type":"Point"}
}