{
  "type": "Feature",
  "properties": {
    "addr:full":"Calle de Juan Agapito Y Revilla, 12 Valladolid Valladolid 47004",
    "addr:housenumber":"12",
    "addr:postcode":"47004",
    "addr:street":"Calle De Juan Agapito Y Revilla",
    "iso:country":"ES",
    "sg:address":"Calle de Juan Agapito Y Revilla, 12",
    "sg:city":"Valladolid",
    "sg:orig_category":"Molduras, Junquillos, Listones Y Molduras Perforadas",
    "sg:phone":"+34 983 20 35 64",
    "sg:postcode":"47004",
    "sg:province":"Valladolid",
    "wof:name":"Fernandez-pacheco Lopez Juan Antonio",
    "wof:placetype":"venue"
},
  "geometry": {"coordinates":[-4.7215151787,41.6473388672],"type":"Point"}
}