{
  "type": "Feature",
  "properties": {
    "iso:country":"ES",
    "sg:address":"Arc S. Marti, 3",
    "sg:city":"Almenar",
    "sg:orig_category":"Empresarios",
    "sg:phone":"+34 973 77 04 67",
    "sg:postcode":"25126",
    "sg:province":"Lleida",
    "wof:name":"Soriano Mateo Jose Antonio",
    "wof:placetype":"venue"
},
  "geometry": {"coordinates":[0.5701000094,41.7965431213],"type":"Point"}
}