{
  "type": "Feature",
  "properties": {
    "addr:full":"Calle de Texidor, 4 Barakaldo Vizcaya 48903",
    "addr:housenumber":"4",
    "addr:postcode":"48903",
    "addr:street":"Calle De Texidor",
    "iso:country":"ES",
    "sg:address":"Calle de Texidor, 4",
    "sg:city":"Barakaldo",
    "sg:orig_category":"Farmacias",
    "sg:phone":"+34 944 90 12 76",
    "sg:postcode":"48903",
    "sg:province":"Vizcaya",
    "wof:name":"Marta Ceberio (farmacia)",
    "wof:placetype":"venue"
},
  "geometry": {"coordinates":[-2.9804430008,43.287776947],"type":"Point"}
}