{
  "type": "Feature",
  "properties": {
    "iso:country":"ES",
    "sg:address":"Del Salt, 5",
    "sg:city":"Palamos",
    "sg:orig_category":"Cr\u00cda De Animales",
    "sg:phone":"+34 972 60 23 09",
    "sg:postcode":"17230",
    "sg:province":"Girona",
    "wof:name":"Tropic Zoo S.c.p.",
    "wof:placetype":"venue"
},
  "geometry": {"coordinates":[3.1279499531,41.8473548889],"type":"Point"}
}