{
  "type": "Feature",
  "properties": {
    "iso:country":"ES",
    "sg:address":"Avda Espa\u00d1a, 43",
    "sg:city":"Aldehuela De Yeltes",
    "sg:orig_category":"Empresas De Pintura Y Revestimientos",
    "sg:phone":"+34 923 16 40 58",
    "sg:postcode":"37639",
    "sg:province":"Salamanca",
    "wof:name":"Santos Pereira Jose Manuel",
    "wof:placetype":"venue"
},
  "geometry": {"coordinates":[-6.2440171242,40.6618423462],"type":"Point"}
}