{
  "type": "Feature",
  "properties": {
    "addr:full":"Avda Logro\u00d1o, 40 Arnedo La Rioja 26580",
    "addr:housenumber":"40",
    "addr:postcode":"26580",
    "addr:street":"Avda Logron\u0303O;Rioja",
    "iso:country":"ES",
    "sg:address":"Avda Logro\u00d1o, 40",
    "sg:city":"Arnedo",
    "sg:orig_category":"Confecci\u00d3n De Zapatos",
    "sg:phone":"+34 941 38 50 29",
    "sg:postcode":"26580",
    "sg:province":"La Rioja",
    "sg:website":"www.calzadoshimalaya.com",
    "wof:name":"Himalaya Sociedad Cooperativa Limitada",
    "wof:placetype":"venue"
},
  "geometry": {"coordinates":[-2.0944299698,42.2295227051],"type":"Point"}
}