{
  "type": "Feature",
  "properties": {
    "iso:country":"ES",
    "sg:address":"Avda Mariana Pineda, 4",
    "sg:city":"Carpio",
    "sg:orig_category":"Maquinaria Para Industrias Diversas",
    "sg:phone":"+34 957 18 02 12",
    "sg:postcode":"14620",
    "sg:province":"C\u00f3rdoba",
    "wof:name":"Talleres Puente Garcia S.l.l.",
    "wof:placetype":"venue"
},
  "geometry": {"coordinates":[-4.4922800064,37.9413986206],"type":"Point"}
}