{
  "type": "Feature",
  "properties": {
    "addr:full":"Av. Costa Llum, 1 Calella Palafrugell Girona 17210",
    "addr:housenumber":"1",
    "addr:postcode":"17210",
    "addr:street":"Av. Costa Llum",
    "iso:country":"ES",
    "sg:address":"Av. Costa Llum, 1",
    "sg:city":"Calella Palafrugell",
    "sg:orig_category":"Alquiler De Oficinas Equipadas",
    "sg:phone":"+34 972 61 56 55",
    "sg:postcode":"17210",
    "sg:province":"Girona",
    "wof:name":"Lugarco S.a.",
    "wof:placetype":"venue"
},
  "geometry": {"coordinates":[3.1871829033,41.8926353455],"type":"Point"}
}