{
  "type": "Feature",
  "properties": {
    "iso:country":"ES",
    "sg:address":"Plaz Albert Einstein, S/n",
    "sg:city":"Granada",
    "sg:orig_category":"Ingenier\u00cda, Centros De Estudios (diversos)",
    "sg:phone":"+34 958 29 00 22",
    "sg:postcode":"18002",
    "sg:province":"Granada",
    "sg:website":"www.atriumgestion.com",
    "wof:name":"Atrium Consulting Gestion Y Desarrollo De Proyectos S.l.",
    "wof:placetype":"venue"
},
  "geometry": {"coordinates":[-3.609525919,37.1781044006],"type":"Point"}
}