{
  "type": "Feature",
  "properties": {
    "addr:full":"Rua Campo De La Compa\u00d1ia, 14 Monforte De Lemos Lugo 27400",
    "addr:housenumber":"14",
    "addr:postcode":"27400",
    "addr:street":"Rua Campo De La Compan\u0303Ia",
    "iso:country":"ES",
    "sg:address":"Rua Campo De La Compa\u00d1ia, 14",
    "sg:city":"Monforte De Lemos",
    "sg:orig_category":"Productores Recolectores, Venta Directa De Vinos",
    "sg:phone":"+34 982 41 07 78",
    "sg:postcode":"27400",
    "sg:province":"Lugo",
    "wof:name":"Bodega Soutelo Sl",
    "wof:placetype":"venue"
},
  "geometry": {"coordinates":[-7.5152921677,42.5178260803],"type":"Point"}
}