{
  "type": "Feature",
  "properties": {
    "iso:country":"ES",
    "sg:address":"Carrer de Viladordis, 98",
    "sg:city":"Manresa",
    "sg:orig_category":"\u00d3ptica: Instrumentos (fabricaci\u00d3n)",
    "sg:phone":"+34 938 77 21 19",
    "sg:postcode":"08241",
    "sg:province":"Barcelona",
    "wof:name":"Sanchez Casadesus Irene",
    "wof:placetype":"venue"
},
  "geometry": {"coordinates":[1.8364830017,41.7255744934],"type":"Point"}
}