{
  "type": "Feature",
  "properties": {
    "iso:country":"ES",
    "sg:address":"Calle de Lamuza, 3",
    "sg:city":"Llodio",
    "sg:orig_category":"Farmacias",
    "sg:phone":"+34 946 72 00 02",
    "sg:postcode":"01400",
    "sg:province":"\u00c1lava",
    "wof:name":"Solaun Martinez Iranzu",
    "wof:placetype":"venue"
},
  "geometry": {"coordinates":[-2.9631149769,43.1435089111],"type":"Point"}
}