{
  "type": "Feature",
  "properties": {
    "addr:full":"Avda Malvarrosa, 65 Valencia Valencia 46011",
    "addr:housenumber":"65",
    "addr:postcode":"46011",
    "addr:street":"Avda Malvarrosa",
    "iso:country":"ES",
    "sg:address":"Avda Malvarrosa, 65",
    "sg:city":"Valencia",
    "sg:orig_category":"Artesan\u00cda",
    "sg:phone":"+34 963 55 37 55",
    "sg:postcode":"46011",
    "sg:province":"Valencia",
    "wof:name":"Artesania Viana S.l.",
    "wof:placetype":"venue"
},
  "geometry": {"coordinates":[-0.3281278014,39.4797668457],"type":"Point"}
}