{
  "type": "Feature",
  "properties": {
    "iso:country":"ES",
    "sg:address":"Avda Espa\u00d1a (de), 39",
    "sg:city":"Ubrique",
    "sg:orig_category":"Ropa Para Ni\u00d1os (al Por Menor)",
    "sg:phone":"+34 956 46 48 33",
    "sg:postcode":"11600",
    "sg:province":"C\u00e1diz",
    "sg:website":"www.benetton.com",
    "wof:name":"Beneubrique S.l.",
    "wof:placetype":"venue"
},
  "geometry": {"coordinates":[-5.4469981194,36.6744918823],"type":"Point"}
}