{
  "type": "Feature",
  "properties": {
    "addr:full":"Carr Sueca, S/n Cullera Valencia 46400",
    "addr:housenumber":"s / n",
    "addr:postcode":"46400",
    "addr:street":"Carr Sueca",
    "iso:country":"ES",
    "sg:address":"Carr Sueca, S/n",
    "sg:city":"Cullera",
    "sg:orig_category":"Semiller\u00cdas",
    "sg:phone":"+34 961 72 05 26",
    "sg:postcode":"46400",
    "sg:province":"Valencia",
    "wof:name":"Viveros Borras C.b.",
    "wof:placetype":"venue"
},
  "geometry": {"coordinates":[-0.2615965009,39.1729774475],"type":"Point"}
}