{
  "type": "Feature",
  "properties": {
    "iso:country":"ES",
    "sg:address":"Calle de Periodista Roberto Castrovido, 3",
    "sg:city":"Valencia",
    "sg:orig_category":"Mec\u00c1nico Del Autom\u00d3vil",
    "sg:phone":"+34 963 77 61 26",
    "sg:postcode":"46014",
    "sg:province":"Valencia",
    "wof:name":"Autochame S.l.",
    "wof:placetype":"venue"
},
  "geometry": {"coordinates":[-0.4014639854,39.4613685608],"type":"Point"}
}