{
  "type": "Feature",
  "properties": {
    "iso:country":"ES",
    "sg:address":"Navajata, 15",
    "sg:city":"S. Martin Pusa",
    "sg:orig_category":"Tapicer\u00cdas",
    "sg:phone":"+34 925 42 01 03",
    "sg:postcode":"45170",
    "sg:province":"Toledo",
    "wof:name":"Hidalgo Jimenez Pio",
    "wof:placetype":"venue"
},
  "geometry": {"coordinates":[-4.6322441101,39.783531189],"type":"Point"}
}