{
  "type": "Feature",
  "properties": {
    "iso:country":"ES",
    "sg:address":"Calle de Calvario, S/n",
    "sg:city":"Marbella",
    "sg:orig_category":"Iglesia Cat\u00d3lica",
    "sg:phone":"+34 952 77 48 99",
    "sg:postcode":"29600",
    "sg:province":"M\u00e1laga",
    "wof:name":"Obispado De Malaga",
    "wof:placetype":"venue"
},
  "geometry": {"coordinates":[-4.8910388947,36.5136909485],"type":"Point"}
}