{
  "type": "Feature",
  "properties": {
    "iso:country":"ES",
    "sg:address":"Calle de Anaca, 13",
    "sg:city":"Irun",
    "sg:orig_category":"Transportes Internacionales",
    "sg:phone":"+34 943 61 59 21",
    "sg:postcode":"20301",
    "sg:province":"Guip\u00f9zcoa",
    "wof:name":"Depositos De Comercio Exterior S.a.",
    "wof:placetype":"venue"
},
  "geometry": {"coordinates":[-1.7902339697,43.3395233154],"type":"Point"}
}