{
  "type": "Feature",
  "properties": {
    "iso:country":"ES",
    "sg:address":"El Pincho, 20",
    "sg:city":"Carral",
    "sg:orig_category":"Caf\u00c9s, Bares, Cervecer\u00cdas",
    "sg:phone":"+34 981 67 01 03",
    "sg:postcode":"15175",
    "sg:province":"La Coru\u00f1a",
    "wof:name":"Barallobre Pazos Fernando",
    "wof:placetype":"venue"
},
  "geometry": {"coordinates":[-8.3555793762,43.2302589417],"type":"Point"}
}