{
  "type": "Feature",
  "properties": {
    "addr:full":"Calle de Fray Jose Casanova, 2 Zaragoza Zaragoza 50010",
    "addr:housenumber":"2",
    "addr:postcode":"50010",
    "addr:street":"Calle De Fray Jose Casanova",
    "iso:country":"ES",
    "sg:address":"Calle de Fray Jose Casanova, 2",
    "sg:city":"Zaragoza",
    "sg:orig_category":"Cl\u00cdnicas Dentales",
    "sg:phone":"+34 976 53 06 22",
    "sg:postcode":"50010",
    "sg:province":"Zaragoza",
    "wof:name":"Huarte Arenaz Maria Jesus",
    "wof:placetype":"venue"
},
  "geometry": {"coordinates":[-0.9042159915,41.6553039551],"type":"Point"}
}