{
  "type": "Feature",
  "properties": {
    "addr:full":"Calle de Doctor Federico Del Castillo, S/n Jaen Ja\u00e9n 23005",
    "addr:housenumber":"s / n;jae\u0301n",
    "addr:postcode":"23005",
    "addr:street":"Calle De Doctor Federico Del Castillo",
    "iso:country":"ES",
    "sg:address":"Calle de Doctor Federico Del Castillo, S/n",
    "sg:city":"Jaen",
    "sg:orig_category":"Billares Y Accesorios",
    "sg:phone":"+34 953 27 14 00",
    "sg:postcode":"23005",
    "sg:province":"Ja\u00e9n",
    "wof:name":"Club Billar Jaen",
    "wof:placetype":"venue"
},
  "geometry": {"coordinates":[-3.7949910164,37.7764892578],"type":"Point"}
}