{
  "type": "Feature",
  "properties": {
    "iso:country":"ES",
    "sg:address":"Carrer de Mare De Deu Del Pilar, 38",
    "sg:city":"Mutxamel",
    "sg:orig_category":"Estudios, Instalaci\u00d3n De Climatizaci\u00d3n",
    "sg:phone":"+34 965 95 63 73",
    "sg:postcode":"03110",
    "sg:province":"Alicante",
    "wof:name":"Electrofrio E-tres S.l.",
    "wof:placetype":"venue"
},
  "geometry": {"coordinates":[-0.4446470141,38.4160346985],"type":"Point"}
}