{
  "type": "Feature",
  "properties": {
    "iso:country":"ES",
    "sg:address":"A. S-huelva, Km. 0630,0",
    "sg:city":"Huelva",
    "sg:orig_category":"Energ\u00cda Solar Y Nuevas Energ\u00cdas (equipo, Estudios)",
    "sg:phone":"+34 959 22 03 38",
    "sg:postcode":"21007",
    "sg:province":"Huelva",
    "sg:website":"www.apeh.org",
    "wof:name":"Agencia Provincial De La Energia De Huelva",
    "wof:placetype":"venue"
},
  "geometry": {"coordinates":[-6.956764698,37.2568893433],"type":"Point"}
}