{
  "type": "Feature",
  "properties": {
    "addr:full":"Calle de Pino, 14 Casillas Murcia 30007",
    "addr:housenumber":"14",
    "addr:postcode":"30007",
    "addr:street":"Calle De Pino",
    "iso:country":"ES",
    "sg:address":"Calle de Pino, 14",
    "sg:city":"Casillas",
    "sg:orig_category":"Electrodom\u00c9sticos (al Por Menor)",
    "sg:phone":"+34 968 30 20 86",
    "sg:postcode":"30007",
    "sg:province":"Murcia",
    "wof:name":"Sanz Lago Enrique",
    "wof:placetype":"venue"
},
  "geometry": {"coordinates":[-1.0912380219,38.0079803467],"type":"Point"}
}