{
  "type": "Feature",
  "properties": {
    "addr:full":"Ctra. Nal. 340, S/n Silla Valencia 46460",
    "addr:housenumber":"s / n",
    "addr:postcode":"46460",
    "addr:street":"Ctra. Nal. 340",
    "iso:country":"ES",
    "sg:address":"Ctra. Nal. 340, S/n",
    "sg:city":"Silla",
    "sg:orig_category":"Ingeniero",
    "sg:phone":"+34 961 21 24 95",
    "sg:postcode":"46460",
    "sg:province":"Valencia",
    "wof:name":"Instalaciones De Tendidos Telefonicos S. A.",
    "wof:placetype":"venue"
},
  "geometry": {"coordinates":[-0.417858988,39.3685531616],"type":"Point"}
}