{
  "type": "Feature",
  "properties": {
    "iso:country":"ES",
    "sg:address":"Pol. Ind. Las Salinas, S/n",
    "sg:city":"Coca",
    "sg:orig_category":"Fabrica, Negocio De Vidrieras, Productos Vidriados Y Espejos",
    "sg:phone":"+34 921 58 65 04",
    "sg:postcode":"40480",
    "sg:province":"Segovia",
    "wof:name":"Aluminios Coca S.l.",
    "wof:placetype":"venue"
},
  "geometry": {"coordinates":[-4.5315027237,41.2220344543],"type":"Point"}
}