{
  "type": "Feature",
  "properties": {
    "iso:country":"ES",
    "sg:address":"Calle de Felipe Ii, 119",
    "sg:city":"Yuncos",
    "sg:orig_category":"Mec\u00c1nico Del Autom\u00d3vil",
    "sg:phone":"+34 925 55 37 17",
    "sg:postcode":"45210",
    "sg:province":"Toledo",
    "wof:name":"Talleres Mecanicos Hidalgo Yuncos S.l.",
    "wof:placetype":"venue"
},
  "geometry": {"coordinates":[-3.870609045,40.0945091248],"type":"Point"}
}