{
  "type": "Feature",
  "properties": {
    "iso:country":"ES",
    "sg:address":"Carrer de Mossen Josep Gudiol, 13",
    "sg:city":"Vic",
    "sg:orig_category":"Impermeabilizantes",
    "sg:phone":"+34 938 85 40 03",
    "sg:postcode":"08500",
    "sg:province":"Barcelona",
    "sg:website":"www.numaindustrial.es",
    "wof:name":"Numa Industrial S. A.",
    "wof:placetype":"venue"
},
  "geometry": {"coordinates":[2.2492809296,41.9296646118],"type":"Point"}
}