{
  "type": "Feature",
  "properties": {
    "addr:full":"Calle de Garrido Lestache, 56 Elda Alicante 03600",
    "addr:housenumber":"56",
    "addr:postcode":"03600",
    "addr:street":"Calle De Garrido Lestache",
    "iso:country":"ES",
    "sg:address":"Calle de Garrido Lestache, 56",
    "sg:city":"Elda",
    "sg:orig_category":"Cueros Y Pieles (al Por Mayor)",
    "sg:phone":"+34 965 38 01 84",
    "sg:postcode":"03600",
    "sg:province":"Alicante",
    "wof:name":"Curtidos Sanchez Y Carrillo S.l.",
    "wof:placetype":"venue"
},
  "geometry": {"coordinates":[-0.7973359823,38.4749755859],"type":"Point"}
}