{
  "type": "Feature",
  "properties": {
    "addr:full":"Calle de Fernan Gonzalez, 18 Miranda Ebro Burgos 09200",
    "addr:housenumber":"18",
    "addr:postcode":"09200",
    "addr:street":"Calle De Fernan Gonzalez",
    "iso:country":"ES",
    "sg:address":"Calle de Fernan Gonzalez, 18",
    "sg:city":"Miranda Ebro",
    "sg:orig_category":"Confecci\u00d3n (fabricaci\u00d3n, Al Por Mayor)",
    "sg:phone":"+34 947 31 06 35",
    "sg:postcode":"09200",
    "sg:province":"Burgos",
    "wof:name":"Garcia Lopez Maria Del Rosario",
    "wof:placetype":"venue"
},
  "geometry": {"coordinates":[-2.9374203682,42.6887931824],"type":"Point"}
}