{
  "type": "Feature",
  "properties": {
    "addr:full":"Carr Sant Antoni, 6 Palamos Girona 17230",
    "addr:housenumber":"6",
    "addr:postcode":"17230",
    "addr:street":"Carr Sant Antoni",
    "iso:country":"ES",
    "sg:address":"Carr Sant Antoni, 6",
    "sg:city":"Palamos",
    "sg:orig_category":"Organismos Y Centros De Vacaciones Y Esparcimiento Para Ni\u00d1os Y Adolescentes",
    "sg:phone":"+34 972 60 06 45",
    "sg:postcode":"17230",
    "sg:province":"Girona",
    "wof:name":"Mu\u00d1oz Soriano Palamos S.c.",
    "wof:placetype":"venue"
},
  "geometry": {"coordinates":[3.1285939217,41.8494567871],"type":"Point"}
}