{
  "type": "Feature",
  "properties": {
    "iso:country":"ES",
    "sg:address":"Calle de Las Huertas, 10",
    "sg:city":"Robledollano",
    "sg:orig_category":"Cerrajer\u00cda, Ferrallista",
    "sg:phone":"+34 927 15 21 35",
    "sg:postcode":"10371",
    "sg:province":"C\u00e1ceres",
    "wof:name":"Collado Cerezo Emilio",
    "wof:placetype":"venue"
},
  "geometry": {"coordinates":[-5.5087528229,39.6107788086],"type":"Point"}
}