{
  "type": "Feature",
  "properties": {
    "iso:country":"ES",
    "sg:address":"Carr Sant Carles (de), 10",
    "sg:city":"Albaida",
    "sg:orig_category":"Peluqueros: De Se\u00d1oras",
    "sg:phone":"+34 962 39 07 79",
    "sg:postcode":"46860",
    "sg:province":"Valencia",
    "wof:name":"Borderia Soler Adela",
    "wof:placetype":"venue"
},
  "geometry": {"coordinates":[-0.5166199803,38.8377151489],"type":"Point"}
}