{
  "type": "Feature",
  "properties": {
    "addr:full":"Goiko Kalea, 4 Azpeitia Guip\u00f9zcoa 20730",
    "addr:housenumber":"4",
    "addr:postcode":"20730",
    "addr:street":"Goiko Kalea;Guipu\u0300Zcoa",
    "iso:country":"ES",
    "sg:address":"Goiko Kalea, 4",
    "sg:city":"Azpeitia",
    "sg:orig_category":"Relojer\u00cda (al Por Menor, Reparaci\u00d3n)",
    "sg:phone":"+34 943 81 13 49",
    "sg:postcode":"20730",
    "sg:province":"Guip\u00f9zcoa",
    "wof:name":"Otamendi Etxabe Jesus Maria",
    "wof:placetype":"venue"
},
  "geometry": {"coordinates":[-2.2664310932,43.1832923889],"type":"Point"}
}