{
  "type": "Feature",
  "properties": {
    "addr:full":"Calle de Meson De Pa\u00d1os, 6 Madrid Madrid 28013",
    "addr:housenumber":"6",
    "addr:postcode":"28013",
    "addr:street":"Calle De Meson De Pan\u0303Os",
    "iso:country":"ES",
    "sg:address":"Calle de Meson De Pa\u00d1os, 6",
    "sg:city":"Madrid",
    "sg:orig_category":"Caf\u00c9s, Bares, Cervecer\u00cdas",
    "sg:phone":"+34 915 41 70 06",
    "sg:postcode":"28013",
    "sg:province":"Madrid",
    "wof:name":"Candevera S.l.",
    "wof:placetype":"venue"
},
  "geometry": {"coordinates":[-3.7091369629,40.4167442322],"type":"Point"}
}