{
  "type": "Feature",
  "properties": {
    "addr:full":"Lazkaibar Kalea, 7 Beasain Guip\u00f9zcoa 20200",
    "addr:housenumber":"7",
    "addr:postcode":"20200",
    "addr:street":"Lazkaibar Kalea;Guipu\u0300Zcoa",
    "iso:country":"ES",
    "sg:address":"Lazkaibar Kalea, 7",
    "sg:city":"Beasain",
    "sg:orig_category":"Empresas De Carpinter\u00cda De Madera",
    "sg:phone":"+34 943 16 25 06",
    "sg:postcode":"20200",
    "sg:province":"Guip\u00f9zcoa",
    "wof:name":"Cabido Puertas Enrique",
    "wof:placetype":"venue"
},
  "geometry": {"coordinates":[-2.1910400391,43.0493011475],"type":"Point"}
}