{
  "type": "Feature",
  "properties": {
    "iso:country":"ES",
    "sg:address":"Carrer de Rusi\u00d1ol, 6",
    "sg:city":"Pineda Mar",
    "sg:orig_category":"Fabricaci\u00d3n, Importaci\u00d3n De L\u00c1mparas Y Bombillas",
    "sg:phone":"+34 937 62 39 38",
    "sg:postcode":"08397",
    "sg:province":"Barcelona",
    "wof:name":"Lampisteria Rite S.l.",
    "wof:placetype":"venue"
},
  "geometry": {"coordinates":[2.6826798916,41.6266517639],"type":"Point"}
}