{
  "type": "Feature",
  "properties": {
    "addr:full":"Avda Garcia Barbon, 101 Vigo Pontevedra 36201",
    "addr:housenumber":"101",
    "addr:postcode":"36201",
    "addr:street":"Avda Garcia Barbon",
    "iso:country":"ES",
    "sg:address":"Avda Garcia Barbon, 101",
    "sg:city":"Vigo",
    "sg:orig_category":"Promotores Constructores",
    "sg:phone":"+34 986 22 08 47",
    "sg:postcode":"36201",
    "sg:province":"Pontevedra",
    "wof:name":"Promalar S.l.",
    "wof:placetype":"venue"
},
  "geometry": {"coordinates":[-8.712225914,42.2371788025],"type":"Point"}
}