{
  "type": "Feature",
  "properties": {
    "addr:full":"Calle de Campo, 4 Jerez De Los Caballeros Badajoz 06380",
    "addr:housenumber":"4",
    "addr:postcode":"06380",
    "addr:street":"Calle De Campo",
    "iso:country":"ES",
    "sg:address":"Calle de Campo, 4",
    "sg:city":"Jerez De Los Caballeros",
    "sg:orig_category":"Bisuter\u00cda, Joyer\u00cda, Relojer\u00cda (al Por Menor)",
    "sg:phone":"+34 924 75 11 45",
    "sg:postcode":"06380",
    "sg:province":"Badajoz",
    "wof:name":"Berjano Vazquez Julia",
    "wof:placetype":"venue"
},
  "geometry": {"coordinates":[-6.7711820602,38.3226470947],"type":"Point"}
}