{
  "type": "Feature",
  "properties": {
    "iso:country":"ES",
    "sg:address":"Calle de Matadero, 12",
    "sg:city":"Alcorcon",
    "sg:orig_category":"Fabricaci\u00d3n De Peines Y De Accesorios De Peluquer\u00cda",
    "sg:phone":"+34 916 44 31 84",
    "sg:postcode":"28921",
    "sg:province":"Madrid",
    "wof:name":"Gil Grande Agustin",
    "wof:placetype":"venue"
},
  "geometry": {"coordinates":[-3.8256380558,40.3462142944],"type":"Point"}
}