{
  "type": "Feature",
  "properties": {
    "iso:country":"ES",
    "sg:address":"Avda Tres Cruces, 17",
    "sg:city":"Valencia",
    "sg:orig_category":"Financiaci\u00d3n Y Cr\u00c9ditos",
    "sg:phone":"+34 963 13 49 55",
    "sg:postcode":"46018",
    "sg:province":"Valencia",
    "wof:name":"Caixa Popular Cooperativa De Credito Valenciana",
    "wof:placetype":"venue"
},
  "geometry": {"coordinates":[-0.405862987,39.4678115845],"type":"Point"}
}