{
  "type": "Feature",
  "properties": {
    "addr:full":"Calle de Carmen, 17 Zaragoza Zaragoza 50005",
    "addr:housenumber":"17",
    "addr:postcode":"50005",
    "addr:street":"Calle De Carmen",
    "iso:country":"ES",
    "sg:address":"Calle de Carmen, 17",
    "sg:city":"Zaragoza",
    "sg:orig_category":"Peluquer\u00cdas, Peluquer\u00cda Mixta",
    "sg:phone":"+34 976 22 35 19",
    "sg:postcode":"50005",
    "sg:province":"Zaragoza",
    "wof:name":"Berges Sanz Roberto",
    "wof:placetype":"venue"
},
  "geometry": {"coordinates":[-0.8930979967,41.646522522],"type":"Point"}
}