{
  "type": "Feature",
  "properties": {
    "iso:country":"ES",
    "sg:address":"Carrer de Montevideo, 49",
    "sg:city":"S. Boi Llobregat",
    "sg:orig_category":"Serigraf\u00cda (material Y Suministros)",
    "sg:phone":"+34 936 54 08 45",
    "sg:postcode":"08830",
    "sg:province":"Barcelona",
    "wof:name":"Rodriguez Torres Borja",
    "wof:placetype":"venue"
},
  "geometry": {"coordinates":[2.0431060791,41.3442497253],"type":"Point"}
}