{
  "type": "Feature",
  "properties": {
    "addr:full":"Ribera De Guaso, 2 Ainsa Huesca 22330",
    "addr:housenumber":"2",
    "addr:postcode":"22330",
    "addr:street":"Ribera;Guaso",
    "iso:country":"ES",
    "sg:address":"Ribera De Guaso, 2",
    "sg:city":"Ainsa",
    "sg:orig_category":"Cr\u00cda De Animales",
    "sg:phone":"+34 974 50 03 06",
    "sg:postcode":"22330",
    "sg:province":"Huesca",
    "wof:name":"L'albeitar S.cv.",
    "wof:placetype":"venue"
},
  "geometry": {"coordinates":[0.1396619976,42.4145011902],"type":"Point"}
}