{
  "type": "Feature",
  "properties": {
    "addr:full":"Ctra Pamplona, 44 Villafranca Navarra 31330",
    "addr:housenumber":"44",
    "addr:postcode":"31330",
    "addr:street":"Ctra Pamplona",
    "iso:country":"ES",
    "sg:address":"Ctra Pamplona, 44",
    "sg:city":"Villafranca",
    "sg:orig_category":"Muebles, Minoristas",
    "sg:phone":"+34 948 84 51 36",
    "sg:postcode":"31330",
    "sg:province":"Navarra",
    "wof:name":"Irigoyen Alonso Angel",
    "wof:placetype":"venue"
},
  "geometry": {"coordinates":[-1.7444989681,42.2784118652],"type":"Point"}
}