{
  "type": "Feature",
  "properties": {
    "iso:country":"ES",
    "sg:address":"C/ Monovar, 37",
    "sg:city":"Elche",
    "sg:orig_category":"Zapater\u00cdas",
    "sg:phone":"+34 965 44 15 58",
    "sg:postcode":"03205",
    "sg:province":"Alicante",
    "sg:website":"www.calzadosroan.com",
    "wof:name":"Calzados Roan S.l.",
    "wof:placetype":"venue"
},
  "geometry": {"coordinates":[-0.6995239854,38.2634811401],"type":"Point"}
}