{
  "type": "Feature",
  "properties": {
    "addr:full":"Carrer de Estany (de L'), 39 Floresta Tarragona 43006",
    "addr:housenumber":"39",
    "addr:postcode":"43006",
    "addr:street":"Carrer De Estany De L '",
    "iso:country":"ES",
    "sg:address":"Carrer de Estany (de L'), 39",
    "sg:city":"Floresta",
    "sg:orig_category":"Empresas De Portes Y Mensajer\u00cda",
    "sg:phone":"+34 977 55 13 67",
    "sg:postcode":"43006",
    "sg:province":"Tarragona",
    "wof:name":"Mensajeria Aplicada S.l.",
    "wof:placetype":"venue"
},
  "geometry": {"coordinates":[1.2209249735,41.1154441833],"type":"Point"}
}