{
  "type": "Feature",
  "properties": {
    "addr:full":"Calle de Martires Salesianos, 6 Moron Frontera Sevilla 41530",
    "addr:housenumber":"6",
    "addr:postcode":"41530",
    "addr:street":"Calle De Martires Salesianos",
    "iso:country":"ES",
    "sg:address":"Calle de Martires Salesianos, 6",
    "sg:city":"Moron Frontera",
    "sg:orig_category":"Ingeniero",
    "sg:phone":"+34 955 85 15 53",
    "sg:postcode":"41530",
    "sg:province":"Sevilla",
    "wof:name":"Oliva Morillo Jose Maria",
    "wof:placetype":"venue"
},
  "geometry": {"coordinates":[-5.4592862129,37.1198158264],"type":"Point"}
}