{
  "type": "Feature",
  "properties": {
    "iso:country":"ES",
    "sg:address":"Sarrola Auzoa, 16",
    "sg:city":"Sarrola",
    "sg:orig_category":"Aceites Y Grasas Industriales (fabricaci\u00d3n, Al Por Mayor)",
    "sg:phone":"+34 948 63 76 06",
    "sg:postcode":"31790",
    "sg:province":"Navarra",
    "wof:name":"Ecogras Recuperacion Y Reciclado S.l.",
    "wof:placetype":"venue"
},
  "geometry": {"coordinates":[-1.701794982,43.2253036499],"type":"Point"}
}