{
  "type": "Feature",
  "properties": {
    "addr:full":"Calle de Hilario Marco, 1 Cazorla Ja\u00e9n 23470",
    "addr:housenumber":"1",
    "addr:postcode":"23470",
    "addr:street":"Calle De Hilario Marco",
    "iso:country":"ES",
    "sg:address":"Calle de Hilario Marco, 1",
    "sg:city":"Cazorla",
    "sg:orig_category":"Estancos",
    "sg:phone":"+34 953 72 20 13",
    "sg:postcode":"23470",
    "sg:province":"Ja\u00e9n",
    "wof:name":"Amores Barrero Mari Carmen",
    "wof:placetype":"venue"
},
  "geometry": {"coordinates":[-3.0029211044,37.9132728577],"type":"Point"}
}