{
  "type": "Feature",
  "properties": {
    "iso:country":"ES",
    "sg:address":"Calle de Benecharo, 19",
    "sg:city":"Paredilla I",
    "sg:orig_category":"Reposter\u00cdas",
    "sg:phone":"+34 928 75 20 06",
    "sg:postcode":"35110",
    "sg:province":"Las Palmas",
    "wof:name":"Aleman Ortega Maria Dolores",
    "wof:placetype":"venue"
},
  "geometry": {"coordinates":[-15.4478702545,27.8430614471],"type":"Point"}
}