{
  "type": "Feature",
  "properties": {
    "addr:full":"Avda Brocense (el), 5 Caceres C\u00e1ceres 10002",
    "addr:housenumber":"5",
    "addr:postcode":"10002",
    "addr:street":"Avda Brocense El;Ca\u0301Ceres",
    "iso:country":"ES",
    "sg:address":"Avda Brocense (el), 5",
    "sg:city":"Caceres",
    "sg:orig_category":"Molduras, Junquillos, Listones Y Molduras Perforadas",
    "sg:phone":"+34 927 22 04 16",
    "sg:postcode":"10002",
    "sg:province":"C\u00e1ceres",
    "wof:name":"Garcia Fuentes Fernando",
    "wof:placetype":"venue"
},
  "geometry": {"coordinates":[-6.3722681999,39.4693756104],"type":"Point"}
}