{
  "type": "Feature",
  "properties": {
    "iso:country":"ES",
    "sg:address":"Carrer de Doctor Ulles, 2",
    "sg:city":"Terrassa",
    "sg:orig_category":"M\u00c9dicos: Cirug\u00cda Vascular",
    "sg:phone":"+34 937 88 45 80",
    "sg:postcode":"08224",
    "sg:province":"Barcelona",
    "wof:name":"Mu\u00f1oz Vicen Aurelio",
    "wof:placetype":"venue"
},
  "geometry": {"coordinates":[2.0075099468,41.561920166],"type":"Point"}
}