{
  "type": "Feature",
  "properties": {
    "addr:full":"Calle de Cuatro Postes, 1 Avila \u00c1vila 05002",
    "addr:housenumber":"1",
    "addr:postcode":"05002",
    "addr:street":"Calle De Cuatro Postes;A\u0301Vila",
    "iso:country":"ES",
    "sg:address":"Calle de Cuatro Postes, 1",
    "sg:city":"Avila",
    "sg:orig_category":"Maquinaria Para Industrias Diversas",
    "sg:phone":"+34 920 21 17 10",
    "sg:postcode":"05002",
    "sg:province":"\u00c1vila",
    "wof:name":"Berrojalbiz E Hijos S.a.",
    "wof:placetype":"venue"
},
  "geometry": {"coordinates":[-4.7110548019,40.6587905884],"type":"Point"}
}