{
  "type": "Feature",
  "properties": {
    "iso:country":"ES",
    "sg:address":"Avda Villarrasa, 13",
    "sg:city":"Rociana Condado",
    "sg:orig_category":"Radiocomunicaciones, Telefon\u00cda M\u00d3vil, Radiomensajer\u00cda: Servicios, Comercializaci\u00d3n",
    "sg:phone":"+34 959 41 72 85",
    "sg:postcode":"21720",
    "sg:province":"Huelva",
    "sg:website":"www.empresasdeespana.com",
    "wof:name":"Segurtel Espa\u00f1a Grupo Duran S.l.u.",
    "wof:placetype":"venue"
},
  "geometry": {"coordinates":[-6.5996518135,37.3116149902],"type":"Point"}
}