{
  "type": "Feature",
  "properties": {
    "iso:country":"ES",
    "sg:address":"Carrer de Numancia, 1",
    "sg:city":"Barcelona",
    "sg:orig_category":"Grafistas",
    "sg:phone":"+34 933 63 36 95",
    "sg:postcode":"08029",
    "sg:province":"Barcelona",
    "sg:website":"www.wolff-olins.com",
    "wof:name":"Wolff Olins S.a.",
    "wof:placetype":"venue"
},
  "geometry": {"coordinates":[2.1418964863,41.3808479309],"type":"Point"}
}