{
  "type": "Feature",
  "properties": {
    "iso:country":"ES",
    "sg:address":"Rua Doctor Mara\u00d1on, 21",
    "sg:city":"Ourense",
    "sg:orig_category":"Bisuter\u00cda, Joyer\u00cda, Relojer\u00cda (al Por Menor)",
    "sg:phone":"+34 988 22 34 77",
    "sg:postcode":"32005",
    "sg:province":"Ourense",
    "wof:name":"Martinez Gonzalez Jose",
    "wof:placetype":"venue"
},
  "geometry": {"coordinates":[-7.8651328087,42.3351860046],"type":"Point"}
}