{
  "type": "Feature",
  "properties": {
    "addr:full":"Calle de Castilla La Vieja (de), 3 Fuenlabrada Madrid 28941",
    "addr:postcode":"28941",
    "addr:street":"Calle De Castilla La",
    "iso:country":"ES",
    "sg:address":"Calle de Castilla La Vieja (de), 3",
    "sg:city":"Fuenlabrada",
    "sg:orig_category":"Molduras, Junquillos, Listones Y Molduras Perforadas",
    "sg:phone":"+34 916 97 80 22",
    "sg:postcode":"28941",
    "sg:province":"Madrid",
    "wof:name":"Del Olmo Moreno Gerardo Ulises",
    "wof:placetype":"venue"
},
  "geometry": {"coordinates":[-3.800620079,40.2904930115],"type":"Point"}
}