{
  "type": "Feature",
  "properties": {
    "addr:full":"Afueras, S/n Alia C\u00e1ceres 10137",
    "addr:postcode":"10137",
    "addr:street":"Afueras S / N;Ca\u0301Ceres",
    "iso:country":"ES",
    "sg:address":"Afueras, S/n",
    "sg:city":"Alia",
    "sg:orig_category":"Producci\u00d3n, Venta De Productos De Agricultura Biol\u00d3gica",
    "sg:phone":"+34 927 19 50 14",
    "sg:postcode":"10137",
    "sg:province":"C\u00e1ceres",
    "wof:name":"La Corceruela S.l.",
    "wof:placetype":"venue"
},
  "geometry": {"coordinates":[-5.2166538239,39.4477157593],"type":"Point"}
}