{
  "type": "Feature",
  "properties": {
    "addr:full":"Pase Canalejas, 63 Santander Cantabria 39004",
    "addr:housenumber":"63",
    "addr:postcode":"39004",
    "addr:street":"Canalejas",
    "iso:country":"ES",
    "sg:address":"Pase Canalejas, 63",
    "sg:city":"Santander",
    "sg:orig_category":"Tintorer\u00cdas, Limpieza En Seco",
    "sg:phone":"+34 942 27 28 87",
    "sg:postcode":"39004",
    "sg:province":"Cantabria",
    "wof:name":"Superseco Martinau S.l.",
    "wof:placetype":"venue"
},
  "geometry": {"coordinates":[-3.7894990444,43.465171814],"type":"Point"}
}