{
  "type": "Feature",
  "properties": {
    "addr:full":"Calle de Fuente Del Rey, 33 Madrid Madrid 28023",
    "addr:housenumber":"33",
    "addr:postcode":"madrid;28023",
    "addr:street":"Calle De Fuente Del Rey",
    "iso:country":"ES",
    "sg:address":"Calle de Fuente Del Rey, 33",
    "sg:city":"Madrid",
    "sg:orig_category":"Asociaciones Y Clubs Deportivos",
    "sg:phone":"+34 913 57 30 12",
    "sg:postcode":"28023",
    "sg:province":"Madrid",
    "wof:name":"Aravaca C.f.",
    "wof:placetype":"venue"
},
  "geometry": {"coordinates":[-3.7777318954,40.4586143494],"type":"Point"}
}