{
  "type": "Feature",
  "properties": {
    "addr:full":"Pase Carmelitas, 4 Salamanca Salamanca 37007",
    "addr:housenumber":"4",
    "addr:postcode":"37007",
    "addr:street":"Carmelitas",
    "iso:country":"ES",
    "sg:address":"Pase Carmelitas, 4",
    "sg:city":"Salamanca",
    "sg:orig_category":"M\u00c9dicos: Gastroenterolog\u00cda Y Hepatolog\u00cda (aparato Digestivo)",
    "sg:phone":"+34 923 12 10 13",
    "sg:postcode":"37007",
    "sg:province":"Salamanca",
    "wof:name":"Rodrigo Rodriguez Maximiliano",
    "wof:placetype":"venue"
},
  "geometry": {"coordinates":[-5.663918972,40.9700393677],"type":"Point"}
}