{
  "type": "Feature",
  "properties": {
    "iso:country":"ES",
    "sg:address":"C/ Quarter, 81",
    "sg:city":"Inca",
    "sg:orig_category":"Pintura Y Barniz (al Por Menor)",
    "sg:phone":"+34 971 88 15 81",
    "sg:postcode":"07300",
    "sg:province":"Islas Baleares",
    "sg:website":"www.pinturasgarcia.com",
    "wof:name":"Pinturas Garcia De Inca S.l.",
    "wof:placetype":"venue"
},
  "geometry": {"coordinates":[2.9209609032,39.7178268433],"type":"Point"}
}