{
  "type": "Feature",
  "properties": {
    "addr:full":"Calle de Valladolid, S/n Barbate C\u00e1diz 11160",
    "addr:housenumber":"/ n",
    "addr:postcode":"11160",
    "addr:street":"Calle De Valladolid S",
    "iso:country":"ES",
    "sg:address":"Calle de Valladolid, S/n",
    "sg:city":"Barbate",
    "sg:orig_category":"Establecimientos De Cura, Prevenci\u00d3n Y Readaptaci\u00d3n",
    "sg:phone":"+34 956 43 31 35",
    "sg:postcode":"11160",
    "sg:province":"C\u00e1diz",
    "wof:name":"Ayuntamiento De Barbate",
    "wof:placetype":"venue"
},
  "geometry": {"coordinates":[-5.9166140556,36.1937942505],"type":"Point"}
}