{
  "type": "Feature",
  "properties": {
    "iso:country":"ES",
    "sg:address":"Calle de Concepcion, 13",
    "sg:city":"Cordoba",
    "sg:orig_category":"Abogados",
    "sg:phone":"+34 957 29 47 66",
    "sg:postcode":"14003",
    "sg:province":"C\u00f3rdoba",
    "wof:name":"Gosalbez Coca Jesus",
    "wof:placetype":"venue"
},
  "geometry": {"coordinates":[-4.7843375206,37.8849525452],"type":"Point"}
}