{
  "type": "Feature",
  "properties": {
    "addr:full":"Errebal Kalea, 18 Eibar Guip\u00f9zcoa 20600",
    "addr:housenumber":"18",
    "addr:postcode":"20600",
    "addr:street":"Errebal Kalea;Guipu\u0300Zcoa",
    "iso:country":"ES",
    "sg:address":"Errebal Kalea, 18",
    "sg:city":"Eibar",
    "sg:orig_category":"Bancos",
    "sg:phone":"+34 943 82 00 43",
    "sg:postcode":"20600",
    "sg:province":"Guip\u00f9zcoa",
    "sg:website":"www.bancozaragozano.es",
    "wof:name":"Barclays Bank S.a.e.",
    "wof:placetype":"venue"
},
  "geometry": {"coordinates":[-2.4696118832,43.1859359741],"type":"Point"}
}