{
  "type": "Feature",
  "properties": {
    "addr:full":"Calle de Artxube, S/n G\u00fce\u00f1es Vizcaya 48840",
    "addr:housenumber":"s",
    "addr:postcode":"48840",
    "addr:street":"Calle De Artxube;/ N",
    "iso:country":"ES",
    "sg:address":"Calle de Artxube, S/n",
    "sg:city":"G\u00fce\u00f1es",
    "sg:orig_category":"Carb\u00d3n, Carb\u00d3n De Madera (al Por Mayor)",
    "sg:phone":"+34 946 69 03 77",
    "sg:postcode":"48840",
    "sg:province":"Vizcaya",
    "wof:name":"Fernandez Nieto Enedina",
    "wof:placetype":"venue"
},
  "geometry": {"coordinates":[-3.0673816204,43.1987228394],"type":"Point"}
}