{
  "type": "Feature",
  "properties": {
    "iso:country":"ES",
    "sg:address":"Carrer de Vapor (d'el), 19",
    "sg:city":"Tarragona",
    "sg:orig_category":"Seguridad En El Trabajo Y Prevenci\u00d3n De Riesgos Laborales",
    "sg:phone":"+34 977 25 26 36",
    "sg:postcode":"43004",
    "sg:province":"Tarragona",
    "wof:name":"Centre De Prevencio De Riscos Laborals",
    "wof:placetype":"venue"
},
  "geometry": {"coordinates":[1.2453449965,41.1113433838],"type":"Point"}
}