{
  "type": "Feature",
  "properties": {
    "iso:country":"ES",
    "sg:address":"Calle de Paseo Del Rio Guadarrama, 2",
    "sg:city":"Estacion",
    "sg:orig_category":"M\u00c9dicos: Estomatolog\u00cda",
    "sg:phone":"+34 918 51 74 26",
    "sg:postcode":"28400",
    "sg:province":"Madrid",
    "wof:name":"Gomez Del Torno Emilio",
    "wof:placetype":"venue"
},
  "geometry": {"coordinates":[-3.9919650555,40.6455612183],"type":"Point"}
}