{
  "type": "Feature",
  "properties": {
    "iso:country":"ES",
    "sg:address":"G.v. Manuel Lopez Carre\u00d1o, S/n",
    "sg:city":"Bullas",
    "sg:orig_category":"Alimentaci\u00d3n General (al Por Menor)",
    "sg:phone":"+34 968 65 49 89",
    "sg:postcode":"30180",
    "sg:province":"Murcia",
    "wof:name":"Amor Gimenez Ana Maria",
    "wof:placetype":"venue"
},
  "geometry": {"coordinates":[-1.6675640345,38.0488357544],"type":"Point"}
}