{
  "type": "Feature",
  "properties": {
    "iso:country":"ES",
    "sg:address":"Huerta Del Conde, 34",
    "sg:city":"El Viso Alcor",
    "sg:orig_category":"Agencias Y Asesores De Publicidad",
    "sg:phone":"+34 955 94 56 68",
    "sg:postcode":"41520",
    "sg:province":"Sevilla",
    "wof:name":"Cortes Falcon Dionisia",
    "wof:placetype":"venue"
},
  "geometry": {"coordinates":[-5.7224740982,37.3872108459],"type":"Point"}
}