{
  "type": "Feature",
  "properties": {
    "addr:full":"Calle de Concepcion Arenal, 10 Malaga M\u00e1laga 29004",
    "addr:housenumber":"10",
    "addr:postcode":"29004",
    "addr:street":"Calle De Concepcion Arenal;Ma\u0301Laga",
    "iso:country":"ES",
    "sg:address":"Calle de Concepcion Arenal, 10",
    "sg:city":"Malaga",
    "sg:orig_category":"Maquinaria Para Industrias Diversas",
    "sg:phone":"+34 952 23 99 55",
    "sg:postcode":"29004",
    "sg:province":"M\u00e1laga",
    "wof:name":"Comercial Doysa S.l.",
    "wof:placetype":"venue"
},
  "geometry": {"coordinates":[-4.4811439514,36.6919212341],"type":"Point"}
}