{
  "type": "Feature",
  "properties": {
    "addr:full":"Avda Andalucia (de), 26 Granada Granada 18014",
    "addr:housenumber":"26",
    "addr:postcode":"18014",
    "addr:street":"Avda Andalucia De",
    "iso:country":"ES",
    "sg:address":"Avda Andalucia (de), 26",
    "sg:city":"Granada",
    "sg:orig_category":"Muebles Y Accesorios Para Cocinas Y Cuartos De Ba\u00d1o (al Por Menor)",
    "sg:phone":"+34 958 20 81 52",
    "sg:postcode":"18014",
    "sg:province":"Granada",
    "sg:website":"www.scavolini.com",
    "wof:name":"Byblos Decoracion Sl",
    "wof:placetype":"venue"
},
  "geometry": {"coordinates":[-3.612719059,37.1884117126],"type":"Point"}
}