{
  "type": "Feature",
  "properties": {
    "iso:country":"ES",
    "sg:address":"Calle de Rio Esla (del), 3",
    "sg:city":"Colmenar Viejo",
    "sg:orig_category":"Ense\u00d1anza: Idiomas",
    "sg:phone":"+34 918 46 31 44",
    "sg:postcode":"28770",
    "sg:province":"Madrid",
    "wof:name":"Veiga Cuevas S.r.l.",
    "wof:placetype":"venue"
},
  "geometry": {"coordinates":[-3.7740938663,40.6626319885],"type":"Point"}
}