{
  "type": "Feature",
  "properties": {
    "addr:full":"Calle de Baias, 5 Llodio \u00c1lava 01400",
    "addr:housenumber":"5",
    "addr:postcode":"01400",
    "addr:street":"Calle De Baias",
    "iso:country":"ES",
    "sg:address":"Calle de Baias, 5",
    "sg:city":"Llodio",
    "sg:orig_category":"M\u00c9dicos: Estomatolog\u00cda",
    "sg:phone":"+34 946 72 49 49",
    "sg:postcode":"01400",
    "sg:province":"\u00c1lava",
    "wof:name":"Petralanda Escalada Joaquin",
    "wof:placetype":"venue"
},
  "geometry": {"coordinates":[-2.9647374153,43.1402893066],"type":"Point"}
}