{
  "type": "Feature",
  "properties": {
    "addr:full":"Calle de Alberto Larzabal, 12 Irun Guip\u00f9zcoa 20303",
    "addr:housenumber":"12",
    "addr:postcode":"20303",
    "addr:street":"Calle De Alberto Larzabal;Guipu\u0300Zcoa",
    "iso:country":"ES",
    "sg:address":"Calle de Alberto Larzabal, 12",
    "sg:city":"Irun",
    "sg:orig_category":"Dise\u00d1o Industrial",
    "sg:phone":"+34 943 61 62 42",
    "sg:postcode":"20303",
    "sg:province":"Guip\u00f9zcoa",
    "wof:name":"Antonio Maria Martin Castellano",
    "wof:placetype":"venue"
},
  "geometry": {"coordinates":[-1.7994725704,43.3368415833],"type":"Point"}
}