{
  "type": "Feature",
  "properties": {
    "iso:country":"ES",
    "sg:address":"Calle de Santa Ana, 55",
    "sg:city":"Albal",
    "sg:orig_category":"Agencias Y Agentes Comerciales, Representantes",
    "sg:phone":"+34 961 26 01 94",
    "sg:postcode":"46470",
    "sg:province":"Valencia",
    "wof:name":"Chilet Fabra Jesus Salvador",
    "wof:placetype":"venue"
},
  "geometry": {"coordinates":[-0.4178180099,39.3982391357],"type":"Point"}
}