{
  "type": "Feature",
  "properties": {
    "addr:full":"Calle de Platero Sanchez De La Cruz, 3 Cordoba C\u00f3rdoba 14010",
    "addr:housenumber":"3",
    "addr:postcode":"14010",
    "addr:street":"Calle De Platero Sanchez De La Cruz;Co\u0301Rdoba",
    "iso:country":"ES",
    "sg:address":"Calle de Platero Sanchez De La Cruz, 3",
    "sg:city":"Cordoba",
    "sg:orig_category":"Alquiler De Apartamentos",
    "sg:phone":"+34 957 25 30 03",
    "sg:postcode":"14010",
    "sg:province":"C\u00f3rdoba",
    "wof:name":"Fincamania Saysa Cordoba S.l.",
    "wof:placetype":"venue"
},
  "geometry": {"coordinates":[-4.764772892,37.8894920349],"type":"Point"}
}