{
  "type": "Feature",
  "properties": {
    "addr:full":"Calle de Dels Fusters, 8 Paiporta Valencia 46200",
    "addr:housenumber":"8",
    "addr:postcode":"46200",
    "addr:street":"Calle De Dels Fusters",
    "iso:country":"ES",
    "sg:address":"Calle de Dels Fusters, 8",
    "sg:city":"Paiporta",
    "sg:orig_category":"Muebles",
    "sg:phone":"+34 963 97 42 61",
    "sg:postcode":"46200",
    "sg:province":"Valencia",
    "sg:website":"www.tapigrup.com",
    "wof:name":"Tapigrup S. L.",
    "wof:placetype":"venue"
},
  "geometry": {"coordinates":[-0.4083090127,39.425201416],"type":"Point"}
}