{
  "type": "Feature",
  "properties": {
    "addr:full":"Carrer de Bassegoda, 20 Barcelona Barcelona 08028",
    "addr:housenumber":"20",
    "addr:postcode":"08028",
    "addr:street":"Carrer De Bassegoda",
    "iso:country":"ES",
    "sg:address":"Carrer de Bassegoda, 20",
    "sg:city":"Barcelona",
    "sg:orig_category":"Importaci\u00d3n, Exportaci\u00d3n Y Comercios De Productos Textiles",
    "sg:phone":"+34 934 40 12 38",
    "sg:postcode":"08028",
    "sg:province":"Barcelona",
    "wof:name":"Guerola Vilalta Maria Asuncion",
    "wof:placetype":"venue"
},
  "geometry": {"coordinates":[2.1256139278,41.3752365112],"type":"Point"}
}