{
  "type": "Feature",
  "properties": {
    "iso:country":"ES",
    "sg:address":"Calle de Ruiz De Padron, 9",
    "sg:city":"S. Sebastian Gomera",
    "sg:orig_category":"Agencias De Viajes",
    "sg:phone":"+34 922 14 13 02",
    "sg:postcode":"38800",
    "sg:province":"Santa Cruz De Tenerife",
    "sg:website":"www.iberoservice.com",
    "wof:name":"Iberoservice S.a.",
    "wof:placetype":"venue"
},
  "geometry": {"coordinates":[-17.1112308502,28.0910453796],"type":"Point"}
}