{
  "type": "Feature",
  "properties": {
    "addr:full":"Avda Espa\u00d1a (de), 5 Ubrique C\u00e1diz 11600",
    "addr:housenumber":"5",
    "addr:postcode":"11600",
    "addr:street":"Avda Espan\u0303A De;Ca\u0301Diz",
    "iso:country":"ES",
    "sg:address":"Avda Espa\u00d1a (de), 5",
    "sg:city":"Ubrique",
    "sg:orig_category":"Marroquiner\u00cda (confecci\u00d3n)",
    "sg:phone":"+34 956 46 00 62",
    "sg:postcode":"11600",
    "sg:province":"C\u00e1diz",
    "wof:name":"Coronel Fernandez Luis",
    "wof:placetype":"venue"
},
  "geometry": {"coordinates":[-5.4459891319,36.6769981384],"type":"Point"}
}