{
  "type": "Feature",
  "properties": {
    "iso:country":"ES",
    "sg:address":"Calle de Alvaro Fernandez Suarez, 7",
    "sg:city":"Vegadeo",
    "sg:orig_category":"Carnicer\u00cdas, Carnicer\u00cdas",
    "sg:phone":"+34 985 47 62 24",
    "sg:postcode":"33770",
    "sg:province":"Asturias",
    "wof:name":"Carniceria Silvallana S.l.",
    "wof:placetype":"venue"
},
  "geometry": {"coordinates":[-7.0479469299,43.4639167786],"type":"Point"}
}