{
  "type": "Feature",
  "properties": {
    "iso:country":"ES",
    "sg:address":"Carrer de Jose Antonio Larramendi, 24",
    "sg:city":"Guardamar Segura",
    "sg:orig_category":"Peluquer\u00cdas, Peluquer\u00cda Mixta",
    "sg:phone":"+34 965 72 98 18",
    "sg:postcode":"03140",
    "sg:province":"Alicante",
    "sg:website":"www.cebado.es",
    "wof:name":"Aldeguer Barbera Mercedes",
    "wof:placetype":"venue"
},
  "geometry": {"coordinates":[-0.6553882957,38.0913887024],"type":"Point"}
}