{
  "type": "Feature",
  "properties": {
    "iso:country":"ES",
    "sg:address":"Carrer de Rubiroles, 1",
    "sg:city":"Olesa Montserrat",
    "sg:orig_category":"Asilos De Ancianos. Centros Privados",
    "sg:phone":"+34 937 78 61 92",
    "sg:postcode":"08640",
    "sg:province":"Barcelona",
    "wof:name":"Tancol S.l.",
    "wof:placetype":"venue"
},
  "geometry": {"coordinates":[1.8962249756,41.5419998169],"type":"Point"}
}