{
  "type": "Feature",
  "properties": {
    "addr:full":"Calle de Bentades, 7 Mungia Vizcaya 48100",
    "addr:housenumber":"7",
    "addr:postcode":"48100",
    "addr:street":"Calle De Bentades",
    "iso:country":"ES",
    "sg:address":"Calle de Bentades, 7",
    "sg:city":"Mungia",
    "sg:orig_category":"Internados & Ense\u00d1anza Privada",
    "sg:phone":"+34 946 74 01 37",
    "sg:postcode":"48100",
    "sg:province":"Vizcaya",
    "wof:name":"Fundacion Escuelas Ventades De Munguia",
    "wof:placetype":"venue"
},
  "geometry": {"coordinates":[-2.8277962208,43.3621711731],"type":"Point"}
}