{
  "type": "Feature",
  "properties": {
    "iso:country":"ES",
    "sg:address":"Plaz Ondarreta, 1",
    "sg:city":"Alcorcon",
    "sg:orig_category":"Fotocopias, Reprograf\u00cda",
    "sg:phone":"+34 916 10 21 05",
    "sg:postcode":"28923",
    "sg:province":"Madrid",
    "wof:name":"G.p. Zona Sur S.l.",
    "wof:placetype":"venue"
},
  "geometry": {"coordinates":[-3.8178060055,40.3435401917],"type":"Point"}
}