{
  "type": "Feature",
  "properties": {
    "addr:full":"Calle de Orbigo, 9 Virgen Camino Le\u00f3n 24198",
    "addr:housenumber":"9",
    "addr:postcode":"24198",
    "addr:street":"Calle De Orbigo;Camino Leo\u0301N",
    "iso:country":"ES",
    "sg:address":"Calle de Orbigo, 9",
    "sg:city":"Virgen Camino",
    "sg:orig_category":"Limpieza Industrial",
    "sg:phone":"+34 987 30 05 77",
    "sg:postcode":"24198",
    "sg:province":"Le\u00f3n",
    "wof:name":"Romero Benavides Tomas Maurilio",
    "wof:placetype":"venue"
},
  "geometry": {"coordinates":[-5.6397590637,42.5822296143],"type":"Point"}
}