{
  "type": "Feature",
  "properties": {
    "iso:country":"ES",
    "sg:address":"Eritas B, 2",
    "sg:city":"Cortegana",
    "sg:orig_category":"Comercio, Reparaci\u00d3n De Bicicletas, De Motocicletas, De Accesorios",
    "sg:phone":"+34 959 13 10 50",
    "sg:postcode":"21230",
    "sg:province":"Huelva",
    "wof:name":"Motos Garcia Capitan S.l.",
    "wof:placetype":"venue"
},
  "geometry": {"coordinates":[-6.8191590309,37.9141197205],"type":"Point"}
}