{
  "type": "Feature",
  "properties": {
    "iso:country":"ES",
    "sg:address":"Av Salvatella, 6",
    "sg:city":"Barbera Valles",
    "sg:orig_category":"Art\u00cdculos De Decoraci\u00d3n (fabricaci\u00d3n Y Al Por Mayor)",
    "sg:phone":"+34 937 29 03 13",
    "sg:postcode":"08210",
    "sg:province":"Barcelona",
    "wof:name":"Dein Interdecor S.a.",
    "wof:placetype":"venue"
},
  "geometry": {"coordinates":[2.1543390751,41.5182571411],"type":"Point"}
}