{
  "type": "Feature",
  "properties": {
    "addr:full":"Calle de Ferrocarril, 14 Zamora Zamora 49023",
    "addr:housenumber":"14",
    "addr:postcode":"49023",
    "addr:street":"Calle De Ferrocarril",
    "iso:country":"ES",
    "sg:address":"Calle de Ferrocarril, 14",
    "sg:city":"Zamora",
    "sg:orig_category":"Fabricaci\u00d3n, Distribuci\u00d3n De Material Para La Climatizaci\u00d3n, Aireaci\u00d3n Y Ventilaci\u00d3n",
    "sg:phone":"+34 980 51 33 05",
    "sg:postcode":"49023",
    "sg:province":"Zamora",
    "sg:website":"www.frimay.com",
    "wof:name":"Frimayo S.l.",
    "wof:placetype":"venue"
},
  "geometry": {"coordinates":[-5.7443990707,41.5131492615],"type":"Point"}
}