{
  "type": "Feature",
  "properties": {
    "addr:full":"Calle de Virgen Del Pilar, 21 Ubeda Ja\u00e9n 23400",
    "addr:housenumber":"21",
    "addr:postcode":"23400",
    "addr:street":"Calle De Virgen Del Pilar;Jae\u0301N",
    "iso:country":"ES",
    "sg:address":"Calle de Virgen Del Pilar, 21",
    "sg:city":"Ubeda",
    "sg:orig_category":"Electricidad (montaje, Ensamblaje De Componentes)",
    "sg:phone":"+34 953 75 67 89",
    "sg:postcode":"23400",
    "sg:province":"Ja\u00e9n",
    "wof:name":"Auto Electricidad Rodriguez S.l.",
    "wof:placetype":"venue"
},
  "geometry": {"coordinates":[-3.3732171059,38.0166625977],"type":"Point"}
}