{
  "type": "Feature",
  "properties": {
    "addr:full":"Calle de Nunneaton, 2 Guadalajara Guadalajara 19004",
    "addr:housenumber":"2",
    "addr:postcode":"19004",
    "addr:street":"Calle De Nunneaton",
    "iso:country":"ES",
    "sg:address":"Calle de Nunneaton, 2",
    "sg:city":"Guadalajara",
    "sg:orig_category":"Arenas, Guijarros Y Granulados",
    "sg:phone":"+34 949 24 85 05",
    "sg:postcode":"19004",
    "sg:province":"Guadalajara",
    "wof:name":"Hormigones Efaye S.l",
    "wof:placetype":"venue"
},
  "geometry": {"coordinates":[-3.1825459003,40.6535835266],"type":"Point"}
}