{
  "type": "Feature",
  "properties": {
    "addr:full":"Bascuas, 27 Dornelas Pontevedra 36579",
    "addr:housenumber":"27",
    "addr:postcode":"36579",
    "addr:street":"Bascuas",
    "iso:country":"ES",
    "sg:address":"Bascuas, 27",
    "sg:city":"Dornelas",
    "sg:orig_category":"Explotaci\u00d3n De Canteras",
    "sg:phone":"+34 986 58 52 21",
    "sg:postcode":"36579",
    "sg:province":"Pontevedra",
    "wof:name":"Minas De Bandeira S.a.",
    "wof:placetype":"venue"
},
  "geometry": {"coordinates":[-8.3462181091,42.7670593262],"type":"Point"}
}