{
  "type": "Feature",
  "properties": {
    "iso:country":"ES",
    "sg:address":"Calle de Serrano, 110",
    "sg:city":"Madrid",
    "sg:orig_category":"Arquitectos",
    "sg:phone":"+34 915 61 69 93",
    "sg:postcode":"28006",
    "sg:province":"Madrid",
    "wof:name":"Serrano-suner Polo Jose",
    "wof:placetype":"venue"
},
  "geometry": {"coordinates":[-3.6863229275,40.43567276],"type":"Point"}
}