{
  "type": "Feature",
  "properties": {
    "iso:country":"ES",
    "sg:address":"Calle de Barrio La Hoya, 36",
    "sg:city":"Cox",
    "sg:orig_category":"Insecticidas, Fumigaci\u00d3n",
    "sg:phone":"+34 966 75 03 69",
    "sg:postcode":"03350",
    "sg:province":"Alicante",
    "wof:name":"Gallego Gallego Antonio",
    "wof:placetype":"venue"
},
  "geometry": {"coordinates":[-0.8870500922,38.1416015625],"type":"Point"}
}