{
  "type": "Feature",
  "properties": {
    "addr:full":"Calle de Ruiz De Alda, 4 Palmas De Gran Canaria Las Palmas 35007",
    "addr:housenumber":"4",
    "addr:postcode":"35007",
    "addr:street":"Calle De Ruiz De Alda",
    "iso:country":"ES",
    "sg:address":"Calle de Ruiz De Alda, 4",
    "sg:city":"Palmas De Gran Canaria",
    "sg:orig_category":"Inform\u00c1tica (estudios, Servicios, Asesor\u00cda, Formaci\u00d3n)",
    "sg:phone":"+34 928 27 42 46",
    "sg:postcode":"35007",
    "sg:province":"Las Palmas",
    "wof:name":"Mu\u00f1oz Silla Maria Elena",
    "wof:placetype":"venue"
},
  "geometry": {"coordinates":[-15.4326076508,28.1356182098],"type":"Point"}
}