{
  "type": "Feature",
  "properties": {
    "iso:country":"ES",
    "sg:address":"Calle de Piamonte, 17",
    "sg:city":"Madrid",
    "sg:orig_category":"Ropa Para Se\u00d1oras Y Caballeros (al Por Menor)",
    "sg:phone":"+34 913 08 06 54",
    "sg:postcode":"28004",
    "sg:province":"Madrid",
    "wof:name":"Amore E Psiches S.l.",
    "wof:placetype":"venue"
},
  "geometry": {"coordinates":[-3.6950361729,40.4230957031],"type":"Point"}
}