{
  "type": "Feature",
  "properties": {
    "addr:full":"Calle de Huerto, 3 Puebla Montalban Toledo 45516",
    "addr:housenumber":"3",
    "addr:postcode":"45516",
    "addr:street":"Calle De Huerto",
    "iso:country":"ES",
    "sg:address":"Calle de Huerto, 3",
    "sg:city":"Puebla Montalban",
    "sg:orig_category":"Transportes De Animales Vivos",
    "sg:phone":"+34 925 75 05 89",
    "sg:postcode":"45516",
    "sg:province":"Toledo",
    "wof:name":"Ladera Ipi\u00f1a Julian",
    "wof:placetype":"venue"
},
  "geometry": {"coordinates":[-4.3588690758,39.8725013733],"type":"Point"}
}