{
  "type": "Feature",
  "properties": {
    "iso:country":"ES",
    "sg:address":"Calle de San Agustin, 43",
    "sg:city":"Requena",
    "sg:orig_category":"Confecci\u00d3n De Trajes Para Se\u00d1oras",
    "sg:phone":"+34 962 30 15 63",
    "sg:postcode":"46340",
    "sg:province":"Valencia",
    "wof:name":"Santano Grados Estefania",
    "wof:placetype":"venue"
},
  "geometry": {"coordinates":[-1.1035740376,39.4889068604],"type":"Point"}
}