{
  "type": "Feature",
  "properties": {
    "addr:full":"Calle de Alemania, 9 San Gabriel Alicante 03710",
    "addr:housenumber":"9",
    "addr:postcode":"03710",
    "addr:street":"Calle De Alemania",
    "iso:country":"ES",
    "sg:address":"Calle de Alemania, 9",
    "sg:city":"San Gabriel",
    "sg:orig_category":"Inmobiliaria (agencias)",
    "sg:phone":"+34 965 83 00 50",
    "sg:postcode":"03710",
    "sg:province":"Alicante",
    "wof:name":"Vives E Hijos S.l.",
    "wof:placetype":"venue"
},
  "geometry": {"coordinates":[0.0535200015,38.6515808105],"type":"Point"}
}