{
  "type": "Feature",
  "properties": {
    "addr:full":"D. Blas Carruez, 4 Zuera Zaragoza 50800",
    "addr:housenumber":"4",
    "addr:postcode":"50800",
    "addr:street":"D. Blas Carruez",
    "iso:country":"ES",
    "sg:address":"D. Blas Carruez, 4",
    "sg:city":"Zuera",
    "sg:orig_category":"Zapatos (al Por Menor)",
    "sg:phone":"+34 976 68 01 17",
    "sg:postcode":"50800",
    "sg:province":"Zaragoza",
    "wof:name":"Cuartero Moreno Rosa Maria",
    "wof:placetype":"venue"
},
  "geometry": {"coordinates":[-0.7886149883,41.8684997559],"type":"Point"}
}