{
  "type": "Feature",
  "properties": {
    "addr:full":"Calle de Azucena, 11 Palmas De Gran Canaria Las Palmas 35010",
    "addr:postcode":"35010",
    "addr:street":"Calle De Azucena 11",
    "iso:country":"ES",
    "sg:address":"Calle de Azucena, 11",
    "sg:city":"Palmas De Gran Canaria",
    "sg:orig_category":"Audiovisuales (producci\u00d3n, Edici\u00d3n, Realizaci\u00d3n)",
    "sg:phone":"+34 928 48 12 49",
    "sg:postcode":"35010",
    "sg:province":"Las Palmas",
    "wof:name":"Telecomunicacion Activa Canaria S.l.",
    "wof:placetype":"venue"
},
  "geometry": {"coordinates":[-15.4397087097,28.1302242279],"type":"Point"}
}