{
  "type": "Feature",
  "properties": {
    "iso:country":"ES",
    "sg:address":"Ps San Martin, 1",
    "sg:city":"Villarquemado",
    "sg:orig_category":"Cooperativas Agr\u00cdcolas",
    "sg:phone":"+34 978 86 72 73",
    "sg:postcode":"44380",
    "sg:province":"Teruel",
    "wof:name":"Cereales Teruel Sociedad Cooperativa",
    "wof:placetype":"venue"
},
  "geometry": {"coordinates":[-1.2636640072,40.5183944702],"type":"Point"}
}