{
  "type": "Feature",
  "properties": {
    "addr:full":"Pl Centre, 11 Barcelona Barcelona 08014",
    "addr:housenumber":"11",
    "addr:postcode":"08014",
    "addr:street":"Pl",
    "iso:country":"ES",
    "sg:address":"Pl Centre, 11",
    "sg:city":"Barcelona",
    "sg:orig_category":"Ingeniero",
    "sg:phone":"+34 934 11 12 96",
    "sg:postcode":"08014",
    "sg:province":"Barcelona",
    "wof:name":"Safiratec S.l.",
    "wof:placetype":"venue"
},
  "geometry": {"coordinates":[2.1357550621,41.3823280334],"type":"Point"}
}