{
  "type": "Feature",
  "properties": {
    "iso:country":"ES",
    "sg:address":"Calle de Canovas Del Castillo, 13",
    "sg:city":"Tarifa",
    "sg:orig_category":"Inform\u00c1tica (estudios, Servicios, Asesor\u00cda, Formaci\u00d3n)",
    "sg:phone":"+34 956 68 17 83",
    "sg:postcode":"11380",
    "sg:province":"C\u00e1diz",
    "sg:website":"www.windtarifa.com",
    "wof:name":"Gomez Rubio Enriqueta",
    "wof:placetype":"venue"
},
  "geometry": {"coordinates":[-5.6063957214,36.0168190002],"type":"Point"}
}