{
  "type": "Feature",
  "properties": {
    "iso:country":"ES",
    "sg:address":"Las Escuelas, 2",
    "sg:city":"Estacion Ferrea",
    "sg:orig_category":"Guarder\u00cdas",
    "sg:phone":"+34 956 61 10 69",
    "sg:postcode":"11368",
    "sg:province":"C\u00e1diz",
    "wof:name":"Federacion De Mujeres El Despertar",
    "wof:placetype":"venue"
},
  "geometry": {"coordinates":[-5.4300951958,36.2128601074],"type":"Point"}
}