{
  "type": "Feature",
  "properties": {
    "addr:full":"Carrer de Pinoses, 12 Ibi Alicante 03440",
    "addr:housenumber":"12",
    "addr:postcode":"03440",
    "addr:street":"Carrer De Pinoses",
    "iso:country":"ES",
    "sg:address":"Carrer de Pinoses, 12",
    "sg:city":"Ibi",
    "sg:orig_category":"Fabricaci\u00d3n De Moldes Y Modelos",
    "sg:phone":"+34 965 55 48 98",
    "sg:postcode":"03440",
    "sg:province":"Alicante",
    "wof:name":"Talleres Tres C. B.",
    "wof:placetype":"venue"
},
  "geometry": {"coordinates":[-0.5785239935,38.6207046509],"type":"Point"}
}