{
  "type": "Feature",
  "properties": {
    "iso:country":"ES",
    "sg:address":"Carr Favareta, 2",
    "sg:city":"Cullera",
    "sg:orig_category":"Empresas De Carpinter\u00cda",
    "sg:phone":"+34 961 73 07 31",
    "sg:postcode":"46400",
    "sg:province":"Valencia",
    "wof:name":"Aluminios Futura 2000 S.l.",
    "wof:placetype":"venue"
},
  "geometry": {"coordinates":[-0.261621207,39.1645469666],"type":"Point"}
}