{
  "type": "Feature",
  "properties": {
    "iso:country":"ES",
    "sg:address":"Calle de Carmen (del), 11",
    "sg:city":"Segovia",
    "sg:orig_category":"Molduras, Junquillos, Listones Y Molduras Perforadas",
    "sg:phone":"+34 921 46 39 40",
    "sg:postcode":"40001",
    "sg:province":"Segovia",
    "wof:name":"Taberna Tendido 7 C.b.",
    "wof:placetype":"venue"
},
  "geometry": {"coordinates":[-4.1194000244,40.9470901489],"type":"Point"}
}