{
  "type": "Feature",
  "properties": {
    "addr:full":"Carrer de Eivissa, 5 Palma Islas Baleares 07011",
    "addr:housenumber":"5",
    "addr:postcode":"07011",
    "addr:street":"Carrer De Eivissa",
    "iso:country":"ES",
    "sg:address":"Carrer de Eivissa, 5",
    "sg:city":"Palma",
    "sg:orig_category":"Arreglo, Reparaci\u00d3n, Piezas Sueltas De Televisi\u00d3n, V\u00cddeo, Hi",
    "sg:phone":"+34 971 73 38 86",
    "sg:postcode":"07011",
    "sg:province":"Islas Baleares",
    "wof:name":"Urbisat S.l.",
    "wof:placetype":"venue"
},
  "geometry": {"coordinates":[2.6427080631,39.575138092],"type":"Point"}
}