{
  "type": "Feature",
  "properties": {
    "iso:country":"ES",
    "sg:address":"Aceria, 5",
    "sg:city":"Puerto Sagunto",
    "sg:orig_category":"Organizaciones Profesionales",
    "sg:phone":"+34 962 69 13 46",
    "sg:postcode":"46520",
    "sg:province":"Valencia",
    "wof:name":"Transportes Maritimos Alcudia S.a.",
    "wof:placetype":"venue"
},
  "geometry": {"coordinates":[-0.2227890044,39.6554031372],"type":"Point"}
}