{
  "type": "Feature",
  "properties": {
    "iso:country":"ES",
    "sg:address":"Cami Ca La Madrona (de), S/n",
    "sg:city":"Mataro",
    "sg:orig_category":"Negocio De Materiales De Construcci\u00d3n",
    "sg:phone":"+34 937 90 65 99",
    "sg:postcode":"08304",
    "sg:province":"Barcelona",
    "wof:name":"Chacosa Construccions S.a.",
    "wof:placetype":"venue"
},
  "geometry": {"coordinates":[2.4537498951,41.554271698],"type":"Point"}
}