{
  "type": "Feature",
  "properties": {
    "addr:full":"Pol Ind Almargen, 13 Bormujos Sevilla 41930",
    "addr:housenumber":"13",
    "addr:postcode":"41930",
    "addr:street":"Almargen",
    "iso:country":"ES",
    "sg:address":"Pol Ind Almargen, 13",
    "sg:city":"Bormujos",
    "sg:orig_category":"Empresas De Carpinter\u00cda",
    "sg:phone":"+34 955 72 52 98",
    "sg:postcode":"41930",
    "sg:province":"Sevilla",
    "wof:name":"Aluminios Bormujos S.l.",
    "wof:placetype":"venue"
},
  "geometry": {"coordinates":[-6.0838065147,37.3599433899],"type":"Point"}
}