{
  "type": "Feature",
  "properties": {
    "addr:full":"Calle de San Juan, 29 Valdemorillo Madrid 28210",
    "addr:housenumber":"29",
    "addr:postcode":"28210",
    "addr:street":"Calle De San Juan",
    "iso:country":"ES",
    "sg:address":"Calle de San Juan, 29",
    "sg:city":"Valdemorillo",
    "sg:orig_category":"Porcelanas, Azulejos (fabricaci\u00d3n, Al Por Mayor)",
    "sg:phone":"+34 918 99 02 40",
    "sg:postcode":"28210",
    "sg:province":"Madrid",
    "wof:name":"Martin Gamella Cb",
    "wof:placetype":"venue"
},
  "geometry": {"coordinates":[-4.0655760765,40.5002365112],"type":"Point"}
}