{
  "type": "Feature",
  "properties": {
    "iso:country":"ES",
    "sg:address":"Calle de Cavanilles, 20",
    "sg:city":"Madrid",
    "sg:orig_category":"Reparaci\u00d3n De Aparatos A Gas",
    "sg:phone":"+34 914 33 70 47",
    "sg:postcode":"28007",
    "sg:province":"Madrid",
    "wof:name":"Lp Gas S. A.",
    "wof:placetype":"venue"
},
  "geometry": {"coordinates":[-3.677056551,40.4065170288],"type":"Point"}
}