{
  "type": "Feature",
  "properties": {
    "iso:country":"ES",
    "sg:address":"Calle de Meson De Paredes, 39",
    "sg:city":"Madrid",
    "sg:orig_category":"Organizaciones Internacionales",
    "sg:phone":"+34 915 28 51 04",
    "sg:postcode":"28012",
    "sg:province":"Madrid",
    "wof:name":"Asociacion Cultural Jovenes Contra La Intolerancia",
    "wof:placetype":"venue"
},
  "geometry": {"coordinates":[-3.7039000988,40.4095039368],"type":"Point"}
}