{
  "type": "Feature",
  "properties": {
    "addr:full":"Avda Navarra, 65 Errenteria Guip\u00f9zcoa 20100",
    "addr:housenumber":"65",
    "addr:postcode":"20100",
    "addr:street":"Avda Navarra;Guipu\u0300Zcoa",
    "iso:country":"ES",
    "sg:address":"Avda Navarra, 65",
    "sg:city":"Errenteria",
    "sg:orig_category":"Molduras, Junquillos, Listones Y Molduras Perforadas",
    "sg:phone":"+34 943 51 23 36",
    "sg:postcode":"20100",
    "sg:province":"Guip\u00f9zcoa",
    "wof:name":"Barbarin Leon Agustin",
    "wof:placetype":"venue"
},
  "geometry": {"coordinates":[-1.9010519981,43.3147621155],"type":"Point"}
}