{
  "type": "Feature",
  "properties": {
    "addr:full":"Avda Asturias, S/n Guardo Palencia 34880",
    "addr:housenumber":"s / n",
    "addr:postcode":"34880",
    "addr:street":"Avda Asturias",
    "iso:country":"ES",
    "sg:address":"Avda Asturias, S/n",
    "sg:city":"Guardo",
    "sg:orig_category":"Organizaciones Internacionales",
    "sg:phone":"+34 979 85 03 24",
    "sg:postcode":"34880",
    "sg:province":"Palencia",
    "wof:name":"Cruz Roja Espa\u00f1ola Nuevo Modulo",
    "wof:placetype":"venue"
},
  "geometry": {"coordinates":[-4.8471841812,42.7969398499],"type":"Point"}
}