{
  "type": "Feature",
  "properties": {
    "addr:full":"Avda. Finisterre, 211 A Coru\u00f1a La Coru\u00f1a 15010",
    "addr:housenumber":"211 a",
    "addr:postcode":"15010",
    "addr:street":"Avda. Finisterre;Corun\u0303A La Corun\u0303A",
    "iso:country":"ES",
    "sg:address":"Avda. Finisterre, 211",
    "sg:city":"A Coru\u00f1a",
    "sg:orig_category":"Bancos",
    "sg:phone":"+34 981 15 42 45",
    "sg:postcode":"15010",
    "sg:province":"La Coru\u00f1a",
    "wof:name":"Banco De Galicia",
    "wof:placetype":"venue"
},
  "geometry": {"coordinates":[-8.4171133041,43.3601264954],"type":"Point"}
}