{
  "type": "Feature",
  "properties": {
    "iso:country":"ES",
    "sg:address":"Trav Dalt, 34",
    "sg:city":"Barcelona",
    "sg:orig_category":"Ingenier\u00cda, Centros De Estudios (diversos)",
    "sg:phone":"+34 932 38 04 58",
    "sg:postcode":"08024",
    "sg:province":"Barcelona",
    "wof:name":"Garcia Homs Alejandro",
    "wof:placetype":"venue"
},
  "geometry": {"coordinates":[2.1533799171,41.4088287354],"type":"Point"}
}