{
  "type": "Feature",
  "properties": {
    "iso:country":"ES",
    "sg:address":"Calle de Don Domingo Martin, 14",
    "sg:city":"Mocejon",
    "sg:orig_category":"Abogados",
    "sg:phone":"+34 925 27 04 97",
    "sg:postcode":"45270",
    "sg:province":"Toledo",
    "wof:name":"Fari\u00f1as Martinez Jose Antonio",
    "wof:placetype":"venue"
},
  "geometry": {"coordinates":[-3.9186825752,39.9392623901],"type":"Point"}
}