{
  "type": "Feature",
  "properties": {
    "addr:full":"Av Europa, 19 Olot Girona 17800",
    "addr:housenumber":"19",
    "addr:postcode":"17800",
    "addr:street":"Av Europa",
    "iso:country":"ES",
    "sg:address":"Av Europa, 19",
    "sg:city":"Olot",
    "sg:orig_category":"Fabricaci\u00d3n De Fundas",
    "sg:phone":"+34 972 26 29 06",
    "sg:postcode":"17800",
    "sg:province":"Girona",
    "sg:website":"www.fundasjb.com",
    "wof:name":"Fundes J.b.cdad.",
    "wof:placetype":"venue"
},
  "geometry": {"coordinates":[2.4797840118,42.1911849976],"type":"Point"}
}