{
  "type": "Feature",
  "properties": {
    "iso:country":"ES",
    "sg:address":"Calle de Reyes Catolicos (de Los), 10",
    "sg:city":"Alcobendas",
    "sg:orig_category":"Carnes De Carnicer\u00cda (al Por Mayor)",
    "sg:phone":"+34 916 62 09 94",
    "sg:postcode":"28108",
    "sg:province":"Madrid",
    "sg:website":"www.dompal.es",
    "wof:name":"Domingo Del Palacio S.a.",
    "wof:placetype":"venue"
},
  "geometry": {"coordinates":[-3.6528670788,40.5367851257],"type":"Point"}
}