{
  "type": "Feature",
  "properties": {
    "iso:country":"ES",
    "sg:address":"Calle de San Miguel, S/n",
    "sg:city":"Sastago",
    "sg:orig_category":"Poller\u00cda Y Caza (al Por Menor)",
    "sg:phone":"+34 976 17 20 09",
    "sg:postcode":"50780",
    "sg:province":"Zaragoza",
    "wof:name":"Calvo Sari\u00f1ena Maria De Monler",
    "wof:placetype":"venue"
},
  "geometry": {"coordinates":[-0.3475039899,41.3231544495],"type":"Point"}
}