{
  "type": "Feature",
  "properties": {
    "addr:full":"Av Sant Jordi (de), 15 Montbrio Del Camp Tarragona 43340",
    "addr:housenumber":"15",
    "addr:postcode":"43340",
    "addr:street":"Av Sant Jordi De",
    "iso:country":"ES",
    "sg:address":"Av Sant Jordi (de), 15",
    "sg:city":"Montbrio Del Camp",
    "sg:orig_category":"Cajas De Ahorro",
    "sg:phone":"+34 977 82 60 56",
    "sg:postcode":"43340",
    "sg:province":"Tarragona",
    "sg:website":"www.caixatarragona.es",
    "wof:name":"Caixa D'estalvis De Tarragona",
    "wof:placetype":"venue"
},
  "geometry": {"coordinates":[1.0048780441,41.1214828491],"type":"Point"}
}