{
  "type": "Feature",
  "properties": {
    "addr:full":"Carrer de Gimbernat, 15 Hospitalet De L'infant Tarragona 43890",
    "addr:housenumber":"15",
    "addr:postcode":"43890",
    "addr:street":"Carrer De Gimbernat",
    "iso:country":"ES",
    "sg:address":"Carrer de Gimbernat, 15",
    "sg:city":"Hospitalet De L'infant",
    "sg:orig_category":"Energ\u00cda Solar Y Nuevas Energ\u00cdas (equipo, Estudios)",
    "sg:phone":"+34 977 17 27 02",
    "sg:postcode":"43890",
    "sg:province":"Tarragona",
    "wof:name":"Enwesa Operaciones S.a.",
    "wof:placetype":"venue"
},
  "geometry": {"coordinates":[1.2595800161,41.1175498962],"type":"Point"}
}