{
  "type": "Feature",
  "properties": {
    "iso:country":"ES",
    "sg:address":"Calle de Pilar (el), 5",
    "sg:city":"Santa Cruz De Tenerife",
    "sg:orig_category":"Asesor\u00cda Fiscal Y Jur\u00cddica",
    "sg:phone":"+34 922 24 10 72",
    "sg:postcode":"38002",
    "sg:province":"Santa Cruz De Tenerife",
    "wof:name":"Pradera Mendivil Telmo",
    "wof:placetype":"venue"
},
  "geometry": {"coordinates":[-16.2512950897,28.4682312012],"type":"Point"}
}