{
  "type": "Feature",
  "properties": {
    "iso:country":"ES",
    "sg:address":"Plaz Elias Ahuja (de), 1",
    "sg:city":"Puerto De Santa Maria",
    "sg:orig_category":"Producci\u00d3n, Comercio De Cereales",
    "sg:phone":"+34 956 54 02 39",
    "sg:postcode":"11500",
    "sg:province":"C\u00e1diz",
    "wof:name":"Agropuerto S.l.",
    "wof:placetype":"venue"
},
  "geometry": {"coordinates":[-6.2269763947,36.6302452087],"type":"Point"}
}