{
  "type": "Feature",
  "properties": {
    "iso:country":"ES",
    "sg:address":"Calle de Maestranza, 20",
    "sg:city":"Malaga",
    "sg:orig_category":"Detectives, Agentes Investigadores Privados",
    "sg:phone":"+34 952 06 02 01",
    "sg:postcode":"29016",
    "sg:province":"M\u00e1laga",
    "wof:name":"Portillo Cruz Jose Antonio",
    "wof:placetype":"venue"
},
  "geometry": {"coordinates":[-4.4085879326,36.7195358276],"type":"Point"}
}