{
  "type": "Feature",
  "properties": {
    "iso:country":"ES",
    "sg:address":"Carrer de Laurea Miro, 256",
    "sg:city":"Esplugues Llobregat",
    "sg:orig_category":"Carnicer\u00cdas, Carnicer\u00cdas",
    "sg:phone":"+34 933 71 01 57",
    "sg:postcode":"08950",
    "sg:province":"Barcelona",
    "wof:name":"Casellas Tor Juan",
    "wof:placetype":"venue"
},
  "geometry": {"coordinates":[2.0854990482,41.3778305054],"type":"Point"}
}