{
  "type": "Feature",
  "properties": {
    "addr:full":"Avda Fernandez Ladreda, 13 Segovia Segovia 40001",
    "addr:housenumber":"13",
    "addr:postcode":"40001",
    "addr:street":"Avda Fernandez Ladreda",
    "iso:country":"ES",
    "sg:address":"Avda Fernandez Ladreda, 13",
    "sg:city":"Segovia",
    "sg:orig_category":"Droguer\u00cdas (al Por Menor)",
    "sg:phone":"+34 921 41 28 02",
    "sg:postcode":"40001",
    "sg:province":"Segovia",
    "sg:website":"www.bodybell.com",
    "wof:name":"Iberica De Drogueria Y Perfumeria S.a",
    "wof:placetype":"venue"
},
  "geometry": {"coordinates":[-4.1185932159,40.9472122192],"type":"Point"}
}