{
  "type": "Feature",
  "properties": {
    "addr:full":"Calle de Cervantes, 1 Arriate M\u00e1laga 29350",
    "addr:housenumber":"1",
    "addr:postcode":"29350",
    "addr:street":"Calle De Cervantes;Ma\u0301Laga",
    "iso:country":"ES",
    "sg:address":"Calle de Cervantes, 1",
    "sg:city":"Arriate",
    "sg:classifiers":[
        {
            "category":"Autos & Motor Vehicles",
            "subcategory":"Automobile Sales",
            "type":"Retail Goods"
        }
    ],
    "sg:phone":"+34 952 16 60 16",
    "sg:postcode":"29350",
    "sg:province":"M\u00e1laga",
    "wof:name":"Dominguez Castillo Salvador",
    "wof:placetype":"venue"
},
  "geometry": {"coordinates":[-5.1397089958,36.7966461182],"type":"Point"}
}