{
  "type": "Feature",
  "properties": {
    "iso:country":"ES",
    "sg:address":"Calle de Doctor Garcia Sanchez, S/n",
    "sg:city":"Jabugo",
    "sg:orig_category":"Farmacias",
    "sg:phone":"+34 959 12 12 05",
    "sg:postcode":"21290",
    "sg:province":"Huelva",
    "wof:name":"Mota Sanchez Francisco Javier",
    "wof:placetype":"venue"
},
  "geometry": {"coordinates":[-6.7284798622,37.9158363342],"type":"Point"}
}