{
  "type": "Feature",
  "properties": {
    "iso:country":"ES",
    "sg:address":"Calle de Sinai, 43",
    "sg:city":"Sevilla",
    "sg:orig_category":"Farmacias",
    "sg:phone":"+34 954 57 63 83",
    "sg:postcode":"41007",
    "sg:province":"Sevilla",
    "wof:name":"Garcia Trigueros Carmen",
    "wof:placetype":"venue"
},
  "geometry": {"coordinates":[-5.9687790871,37.3914718628],"type":"Point"}
}