{
  "type": "Feature",
  "properties": {
    "iso:country":"ES",
    "sg:address":"Sorolla, 34",
    "sg:city":"Rincon Victoria",
    "sg:orig_category":"Arquitectos",
    "sg:phone":"+34 952 97 31 55",
    "sg:postcode":"29730",
    "sg:province":"M\u00e1laga",
    "wof:name":"Hernandez De Marco Sergio",
    "wof:placetype":"venue"
},
  "geometry": {"coordinates":[-4.2807641029,36.714641571],"type":"Point"}
}