{
  "type": "Feature",
  "properties": {
    "addr:full":"Trva Igrexa (da), 2 Estrada Pontevedra 36680",
    "addr:housenumber":"2",
    "addr:postcode":"36680",
    "addr:street":"Trva Igrexa Da;Estrada Pontevedra",
    "iso:country":"ES",
    "sg:address":"Trva Igrexa (da), 2",
    "sg:city":"Estrada",
    "sg:orig_category":"Ense\u00d1anza, Formaci\u00d3n Profesional: Aprendizaje",
    "sg:phone":"+34 986 57 02 09",
    "sg:postcode":"36680",
    "sg:province":"Pontevedra",
    "wof:name":"Parroquia De San Pelayo",
    "wof:placetype":"venue"
},
  "geometry": {"coordinates":[-8.4921388626,42.6899147034],"type":"Point"}
}