{
  "type": "Feature",
  "properties": {
    "iso:country":"ES",
    "sg:address":"Carrer de Miguel Hernandez, 23",
    "sg:city":"Guardamar Segura",
    "sg:orig_category":"Inmobiliaria (agencias)",
    "sg:phone":"+34 965 72 44 46",
    "sg:postcode":"03140",
    "sg:province":"Alicante",
    "wof:name":"Moncayo Properties International S.l",
    "wof:placetype":"venue"
},
  "geometry": {"coordinates":[-0.6536440253,38.0888633728],"type":"Point"}
}