{
  "type": "Feature",
  "properties": {
    "iso:country":"ES",
    "sg:address":"Pl Comercial, S/n",
    "sg:city":"Barcelona",
    "sg:orig_category":"Aparcamientos (infraestructuras, Accesorios)",
    "sg:phone":"+34 932 68 45 08",
    "sg:postcode":"08003",
    "sg:province":"Barcelona",
    "wof:name":"Acciona Aparcamientos S.l.",
    "wof:placetype":"venue"
},
  "geometry": {"coordinates":[2.1834793091,41.3854560852],"type":"Point"}
}