{
  "type": "Feature",
  "properties": {
    "iso:country":"ES",
    "sg:address":"Calle de Alfonso Gomez, 55",
    "sg:city":"Madrid",
    "sg:orig_category":"Agencias Y Agentes Comerciales, Representantes",
    "sg:phone":"+34 913 27 41 51",
    "sg:postcode":"28037",
    "sg:province":"Madrid",
    "wof:name":"Herradon Alvarez Teresa",
    "wof:placetype":"venue"
},
  "geometry": {"coordinates":[-3.6258265972,40.4336624146],"type":"Point"}
}