{
  "type": "Feature",
  "properties": {
    "addr:full":"Carrer de Simancas, 28 Hospitalet Llobregat Barcelona 08906",
    "addr:housenumber":"28",
    "addr:postcode":"08906",
    "addr:street":"Carrer De Simancas",
    "iso:country":"ES",
    "sg:address":"Carrer de Simancas, 28",
    "sg:city":"Hospitalet Llobregat",
    "sg:orig_category":"Supermercados Y Hipermercados",
    "sg:phone":"+34 934 38 02 82",
    "sg:postcode":"08906",
    "sg:province":"Barcelona",
    "wof:name":"Cs Establiments De Proximitat S.l.",
    "wof:placetype":"venue"
},
  "geometry": {"coordinates":[2.1035430431,41.3744163513],"type":"Point"}
}