{
  "type": "Feature",
  "properties": {
    "addr:full":"Pl Llibertat, 3 Reus Tarragona 43201",
    "addr:housenumber":"3",
    "addr:postcode":"43201",
    "addr:street":"Pl Llibertat",
    "iso:country":"ES",
    "sg:address":"Pl Llibertat, 3",
    "sg:city":"Reus",
    "sg:classifiers":[
        {
            "category":"Sports & Exercise",
            "subcategory":"Golf",
            "type":"Entertainment"
        }
    ],
    "sg:phone":"+34 977 34 63 52",
    "sg:postcode":"43201",
    "sg:province":"Tarragona",
    "sg:tags":[
        "y",
        "de",
        "campos",
        "clases"
    ],
    "wof:name":"Ca?ellas Golf",
    "wof:placetype":"venue"
},
  "geometry": {"coordinates":[1.1058909893,41.157749176],"type":"Point"}
}