{
  "type": "Feature",
  "properties": {
    "addr:full":"Calle de Daniel Chaver Gomez, S/n Baamonde Lugo 27370",
    "addr:housenumber":"s / n",
    "addr:postcode":"27370",
    "addr:street":"Calle De Daniel Chaver Gomez",
    "iso:country":"ES",
    "sg:address":"Calle de Daniel Chaver Gomez, S/n",
    "sg:city":"Baamonde",
    "sg:orig_category":"Reposter\u00cdas",
    "sg:phone":"+34 982 39 82 51",
    "sg:postcode":"27370",
    "sg:province":"Lugo",
    "wof:name":"Vazquez Caama\u00f1o Jose",
    "wof:placetype":"venue"
},
  "geometry": {"coordinates":[-7.6279511452,43.1205711365],"type":"Point"}
}