{
  "type": "Feature",
  "properties": {
    "iso:country":"ES",
    "sg:address":"Calle de Bendicion De Dios, 9",
    "sg:city":"Cadiz",
    "sg:orig_category":"Droguer\u00cdas (al Por Menor)",
    "sg:phone":"+34 956 21 44 27",
    "sg:postcode":"11003",
    "sg:province":"C\u00e1diz",
    "wof:name":"Alburquerque Paez Manuel",
    "wof:placetype":"venue"
},
  "geometry": {"coordinates":[-6.3000788689,36.5363769531],"type":"Point"}
}