{
  "type": "Feature",
  "properties": {
    "iso:country":"ES",
    "sg:address":"Plaz Maria Cristina, 7",
    "sg:city":"Tortuera",
    "sg:orig_category":"Cajas De Ahorro",
    "sg:phone":"+34 949 84 30 74",
    "sg:postcode":"19338",
    "sg:province":"Guadalajara",
    "wof:name":"Caja Provincial De Ahorros De Guadalajara",
    "wof:placetype":"venue"
},
  "geometry": {"coordinates":[-1.7933199406,40.9709587097],"type":"Point"}
}