{
  "type": "Feature",
  "properties": {
    "addr:full":"Urb Parral (el), S/n Parral M\u00e1laga 29120",
    "addr:postcode":"29120",
    "addr:street":"Urb Parral El S / N;Ma\u0301Laga",
    "iso:country":"ES",
    "sg:address":"Urb Parral (el), S/n",
    "sg:city":"Parral",
    "sg:orig_category":"Electricidad: Equipos Industriales, Componentes (fabricaci\u00d3n)",
    "sg:phone":"+34 952 49 13 97",
    "sg:postcode":"29120",
    "sg:province":"M\u00e1laga",
    "wof:name":"Marmolejo Y Navarro S.l.",
    "wof:placetype":"venue"
},
  "geometry": {"coordinates":[-4.4200186729,36.7196464539],"type":"Point"}
}