{
  "type": "Feature",
  "properties": {
    "addr:full":"Calle de Camarena, 90 Madrid Madrid 28047",
    "addr:housenumber":"90",
    "addr:postcode":"madrid;28047",
    "addr:street":"Calle De Camarena",
    "iso:country":"ES",
    "sg:address":"Calle de Camarena, 90",
    "sg:city":"Madrid",
    "sg:orig_category":"Peluquer\u00cdas, Peluquer\u00cda Mixta",
    "sg:phone":"+34 915 09 85 49",
    "sg:postcode":"28047",
    "sg:province":"Madrid",
    "wof:name":"Carreira Zazo Alicia",
    "wof:placetype":"venue"
},
  "geometry": {"coordinates":[-3.7571282387,40.3935508728],"type":"Point"}
}