{
  "type": "Feature",
  "properties": {
    "addr:full":"Carrer de Angel Guimera, 126 Esplugues Llobregat Barcelona 08950",
    "addr:housenumber":"126",
    "addr:postcode":"08950",
    "addr:street":"Carrer De Angel Guimera",
    "iso:country":"ES",
    "sg:address":"Carrer de Angel Guimera, 126",
    "sg:city":"Esplugues Llobregat",
    "sg:orig_category":"Venta, Montaje De Neum\u00c1ticos",
    "sg:phone":"+34 934 73 07 63",
    "sg:postcode":"08950",
    "sg:province":"Barcelona",
    "wof:name":"Latorre Cuadros Daniel",
    "wof:placetype":"venue"
},
  "geometry": {"coordinates":[2.0808498859,41.3755683899],"type":"Point"}
}