{
  "type": "Feature",
  "properties": {
    "iso:country":"ES",
    "sg:address":"Calle de Carril Tercero, 5",
    "sg:city":"Totana",
    "sg:orig_category":"Reposter\u00cdas",
    "sg:phone":"+34 968 42 28 24",
    "sg:postcode":"30850",
    "sg:province":"Murcia",
    "wof:name":"Zamora Martinez Rogelio",
    "wof:placetype":"venue"
},
  "geometry": {"coordinates":[-1.4986740351,37.7713165283],"type":"Point"}
}