{
  "type": "Feature",
  "properties": {
    "addr:full":"Carrer de Abat Llort, 22 Valls Tarragona 43800",
    "addr:housenumber":"22",
    "addr:postcode":"43800",
    "addr:street":"Carrer De Abat Llort",
    "iso:country":"ES",
    "sg:address":"Carrer de Abat Llort, 22",
    "sg:city":"Valls",
    "sg:orig_category":"Panader\u00cdas, Panader\u00cdas",
    "sg:phone":"+34 977 60 35 04",
    "sg:postcode":"43800",
    "sg:province":"Tarragona",
    "wof:name":"Fabra Climent Esteban",
    "wof:placetype":"venue"
},
  "geometry": {"coordinates":[1.2488919497,41.2867546082],"type":"Point"}
}