{
  "type": "Feature",
  "properties": {
    "iso:country":"ES",
    "sg:address":"Calle de Ancha, 66",
    "sg:city":"Sanlucar De Barrameda",
    "sg:orig_category":"Confecci\u00d3n De Trajes Para Se\u00d1oras",
    "sg:phone":"+34 956 38 30 94",
    "sg:postcode":"11540",
    "sg:province":"C\u00e1diz",
    "wof:name":"Sanchez Sala Jose",
    "wof:placetype":"venue"
},
  "geometry": {"coordinates":[-6.3524413109,36.7792854309],"type":"Point"}
}