{
  "type": "Feature",
  "properties": {
    "iso:country":"ES",
    "sg:address":"Carrer de Putget, 56",
    "sg:city":"Barcelona",
    "sg:orig_category":"Servicios De Telecomunicaciones",
    "sg:phone":"+34 932 12 76 74",
    "sg:postcode":"08023",
    "sg:province":"Barcelona",
    "sg:website":"www.nadir.es",
    "wof:name":"Nadir Ingenieria Sistemas Moviles S.l.",
    "wof:placetype":"venue"
},
  "geometry": {"coordinates":[2.144256115,41.406829834],"type":"Point"}
}