{
  "type": "Feature",
  "properties": {
    "iso:country":"ES",
    "sg:address":"Avgd Reis Catolics, 116",
    "sg:city":"Benifaio",
    "sg:orig_category":"Ropa De Trabajo Y Profesionales (fabricaci\u00d3n, Al Por Mayor)",
    "sg:phone":"+34 961 78 25 29",
    "sg:postcode":"46450",
    "sg:province":"Valencia",
    "sg:website":"www.dkey.es/esplugues/",
    "wof:name":"Vestuario Industrial Esplugues S.l.",
    "wof:placetype":"venue"
},
  "geometry": {"coordinates":[-0.4272589982,39.2886810303],"type":"Point"}
}