{
  "type": "Feature",
  "properties": {
    "addr:full":"Calle de Juan Xxiii, 2 Santurtzi Vizcaya 48980",
    "addr:housenumber":"2",
    "addr:postcode":"48980",
    "addr:street":"Calle De Juan Xxiii",
    "iso:country":"ES",
    "sg:address":"Calle de Juan Xxiii, 2",
    "sg:city":"Santurtzi",
    "sg:orig_category":"Laboratorios Y Trabajos De Fotograf\u00cda, V\u00cddeo Y Cine",
    "sg:phone":"+34 944 61 18 82",
    "sg:postcode":"48980",
    "sg:province":"Vizcaya",
    "wof:name":"Bidaurrazaga Basterrica Marta",
    "wof:placetype":"venue"
},
  "geometry": {"coordinates":[-3.0336420536,43.3301811218],"type":"Point"}
}