{
  "type": "Feature",
  "properties": {
    "iso:country":"ES",
    "sg:address":"Avda Juan Carlos I, 25",
    "sg:city":"Corralejo",
    "sg:orig_category":"Alquiler De Veh\u00cdculos: Turismos Y Utilitarios",
    "sg:phone":"+34 928 53 51 17",
    "sg:postcode":"35660",
    "sg:province":"Las Palmas",
    "sg:website":"www.betacar.biz",
    "wof:name":"Betacar Tenerife S.a.",
    "wof:placetype":"venue"
},
  "geometry": {"coordinates":[-13.8708152771,28.7397327423],"type":"Point"}
}