{
  "type": "Feature",
  "properties": {
    "addr:full":"Carrer de Concili De Trento, 123 Barcelona Barcelona 08020",
    "addr:housenumber":"123",
    "addr:postcode":"08020",
    "addr:street":"Carrer De Concili De Trento",
    "iso:country":"ES",
    "sg:address":"Carrer de Concili De Trento, 123",
    "sg:city":"Barcelona",
    "sg:orig_category":"Electrodom\u00c9sticos (fabricaci\u00d3n, Al Por Mayor)",
    "sg:phone":"+34 933 07 65 00",
    "sg:postcode":"08020",
    "sg:province":"Barcelona",
    "wof:name":"Gumper S. L.",
    "wof:placetype":"venue"
},
  "geometry": {"coordinates":[2.1977720261,41.4155769348],"type":"Point"}
}