{
  "type": "Feature",
  "properties": {
    "addr:full":"Carrer de Alts Forns, 87 Barcelona Barcelona 08038",
    "addr:housenumber":"87",
    "addr:postcode":"08038",
    "addr:street":"Carrer De Alts Forns",
    "iso:country":"ES",
    "sg:address":"Carrer de Alts Forns, 87",
    "sg:city":"Barcelona",
    "sg:classifiers":[
        {
            "category":"Personal",
            "subcategory":"Barber",
            "type":"Services"
        }
    ],
    "sg:phone":"+34 932 96 89 69",
    "sg:postcode":"08038",
    "sg:province":"Barcelona",
    "sg:tags":[
        "caballeros",
        "de",
        "peluqueros"
    ],
    "wof:name":"Sotillo Balcells Fernando",
    "wof:placetype":"venue"
},
  "geometry": {"coordinates":[2.1427240372,41.3602561951],"type":"Point"}
}