{
  "type": "Feature",
  "properties": {
    "addr:full":"Calle de Camino Real, 87 Colloto Asturias 33010",
    "addr:housenumber":"87",
    "addr:postcode":"33010",
    "addr:street":"Calle De Camino Real",
    "iso:country":"ES",
    "sg:address":"Calle de Camino Real, 87",
    "sg:city":"Colloto",
    "sg:orig_category":"Electromedicina: Servicios",
    "sg:phone":"+34 985 98 59 46",
    "sg:postcode":"33010",
    "sg:province":"Asturias",
    "wof:name":"Huerta Del Rey Juan Alberto",
    "wof:placetype":"venue"
},
  "geometry": {"coordinates":[-5.7954902649,43.3778877258],"type":"Point"}
}