{
  "type": "Feature",
  "properties": {
    "iso:country":"ES",
    "sg:address":"Av Prat De La Riba, 37",
    "sg:city":"Tarragona",
    "sg:orig_category":"Periodistas Profesionales",
    "sg:phone":"+34 977 21 11 95",
    "sg:postcode":"43001",
    "sg:province":"Tarragona",
    "wof:name":"Castillo Biesa David",
    "wof:placetype":"venue"
},
  "geometry": {"coordinates":[1.2461049557,41.117931366],"type":"Point"}
}