{
  "type": "Feature",
  "properties": {
    "iso:country":"ES",
    "sg:address":"Portobravo, S/n",
    "sg:city":"Lousame-portobravo",
    "sg:orig_category":"Asociaciones, Organismos Culturales Y Socioeducativos",
    "sg:phone":"+34 981 82 57 80",
    "sg:postcode":"15214",
    "sg:province":"La Coru\u00f1a",
    "wof:name":"Ayuntamiento De Lousame",
    "wof:placetype":"venue"
},
  "geometry": {"coordinates":[-8.8666620255,42.7850608826],"type":"Point"}
}