{
  "type": "Feature",
  "properties": {
    "addr:full":"Finca, S/n Zayas Bascones Soria 42353",
    "addr:housenumber":"s / n",
    "addr:postcode":"42353",
    "addr:street":"Zayas",
    "iso:country":"ES",
    "sg:address":"Finca, S/n",
    "sg:city":"Zayas Bascones",
    "sg:orig_category":"Producci\u00d3n, Venta De Productos De Agricultura Biol\u00d3gica",
    "sg:phone":"+34 975 18 61 94",
    "sg:postcode":"42353",
    "sg:province":"Soria",
    "wof:name":"Bruno Mesa S.l.",
    "wof:placetype":"venue"
},
  "geometry": {"coordinates":[-2.46916008,41.7646484375],"type":"Point"}
}