{
  "type": "Feature",
  "properties": {
    "iso:country":"ES",
    "sg:address":"Avda Cuba, S/n",
    "sg:city":"Palencia",
    "sg:orig_category":"Bebidas",
    "sg:phone":"+34 979 72 48 87",
    "sg:postcode":"34003",
    "sg:province":"Palencia",
    "wof:name":"Compa\u00d1ia De Bebidas Pepsico S.l.",
    "wof:placetype":"venue"
},
  "geometry": {"coordinates":[-4.5192189217,42.0143508911],"type":"Point"}
}