{
  "type": "Feature",
  "properties": {
    "iso:country":"ES",
    "sg:address":"Carrer de Floridablanca, 80",
    "sg:city":"Mataro",
    "sg:orig_category":"Puertas Autom\u00c1ticas, Puertas De Garaje",
    "sg:phone":"+34 937 90 85 42",
    "sg:postcode":"08301",
    "sg:province":"Barcelona",
    "wof:name":"Aluminio Y Desarrollos Boral S.l.",
    "wof:placetype":"venue"
},
  "geometry": {"coordinates":[2.4516038895,41.542766571],"type":"Point"}
}