{
  "type": "Feature",
  "properties": {
    "addr:full":"Calle de Ronda Mijares, 170 Castellon Castell\u00f3n 12002",
    "addr:housenumber":"170",
    "addr:postcode":"12002",
    "addr:street":"Calle De Ronda Mijares",
    "iso:country":"ES",
    "sg:address":"Calle de Ronda Mijares, 170",
    "sg:city":"Castellon",
    "sg:orig_category":"Ropa Para Caballeros (al Por Menor)",
    "sg:phone":"+34 964 24 24 09",
    "sg:postcode":"12002",
    "sg:province":"Castell\u00f3n",
    "wof:name":"Gozalbo Ruiz Manuel",
    "wof:placetype":"venue"
},
  "geometry": {"coordinates":[-0.0417400002,39.9835395813],"type":"Point"}
}