{
  "type": "Feature",
  "properties": {
    "addr:full":"Rava Jesus, 19 Reus Tarragona 43201",
    "addr:postcode":"43201",
    "iso:country":"ES",
    "sg:address":"Rava Jesus, 19",
    "sg:city":"Reus",
    "sg:orig_category":"Inversiones",
    "sg:phone":"+34 977 34 25 59",
    "sg:postcode":"43201",
    "sg:province":"Tarragona",
    "wof:name":"Retonic S.l.",
    "wof:placetype":"venue"
},
  "geometry": {"coordinates":[1.107951045,41.1545562744],"type":"Point"}
}