{
  "type": "Feature",
  "properties": {
    "iso:country":"ES",
    "sg:address":"Barr Leiz-mi\u00d1ota, 2",
    "sg:city":"Leiz-mi\u00e7ota",
    "sg:orig_category":"Material Y Herramientas Agr\u00cdcolas",
    "sg:phone":"+34 946 23 15 43",
    "sg:postcode":"48230",
    "sg:province":"Vizcaya",
    "wof:name":"Leanitz Tresnak S.l.",
    "wof:placetype":"venue"
},
  "geometry": {"coordinates":[-2.5447890759,43.1305541992],"type":"Point"}
}