{
  "type": "Feature",
  "properties": {
    "addr:full":"Calle de Lonja (la), 4 Mancha Real Ja\u00e9n 23100",
    "addr:housenumber":"4",
    "addr:postcode":"23100",
    "addr:street":"Calle De Lonja La",
    "iso:country":"ES",
    "sg:address":"Calle de Lonja (la), 4",
    "sg:city":"Mancha Real",
    "sg:orig_category":"Aceites Y Grasas Alimentarias (fabricaci\u00d3n, Al Por Mayor)",
    "sg:phone":"+34 953 35 00 71",
    "sg:postcode":"23100",
    "sg:province":"Ja\u00e9n",
    "wof:name":"Cooperativa De Aceites San Isidro",
    "wof:placetype":"venue"
},
  "geometry": {"coordinates":[-3.6150290966,37.7886810303],"type":"Point"}
}