{
  "type": "Feature",
  "properties": {
    "addr:full":"Anboto Kalea, 5 Legizamon Vizcaya 48450",
    "addr:housenumber":"5",
    "addr:postcode":"48450",
    "addr:street":"Anboto Kalea",
    "iso:country":"ES",
    "sg:address":"Anboto Kalea, 5",
    "sg:city":"Legizamon",
    "sg:orig_category":"Contenedores (mercanc\u00cdas)",
    "sg:phone":"+34 944 40 91 11",
    "sg:postcode":"48450",
    "sg:province":"Vizcaya",
    "wof:name":"Aukera Logistica S.l.",
    "wof:placetype":"venue"
},
  "geometry": {"coordinates":[-2.8941779137,43.2487335205],"type":"Point"}
}