{
  "type": "Feature",
  "properties": {
    "iso:country":"ES",
    "sg:address":"Calle de Lope De Rueda, 59",
    "sg:city":"Malaga",
    "sg:orig_category":"Papeler\u00cdas, Librer\u00cdas",
    "sg:phone":"+34 952 43 87 43",
    "sg:postcode":"29190",
    "sg:province":"M\u00e1laga",
    "wof:name":"Gallardo Gutierrez Silvia",
    "wof:placetype":"venue"
},
  "geometry": {"coordinates":[-4.4804120064,36.7375831604],"type":"Point"}
}