{
  "type": "Feature",
  "properties": {
    "addr:full":"Enparan Kalea, 27 Azpeitia Guip\u00f9zcoa 20730",
    "addr:housenumber":"27",
    "addr:postcode":"20730",
    "addr:street":"Enparan Kalea;Guipu\u0300Zcoa",
    "iso:country":"ES",
    "sg:address":"Enparan Kalea, 27",
    "sg:city":"Azpeitia",
    "sg:orig_category":"Centros De Coordinaci\u00d3n",
    "sg:phone":"+34 943 15 02 43",
    "sg:postcode":"20730",
    "sg:province":"Guip\u00f9zcoa",
    "wof:name":"Gestoria Asiain",
    "wof:placetype":"venue"
},
  "geometry": {"coordinates":[-2.2644240856,43.1847419739],"type":"Point"}
}