{
  "type": "Feature",
  "properties": {
    "iso:country":"ES",
    "sg:address":"Plaz San Juan, 3",
    "sg:city":"Valladolid",
    "sg:orig_category":"Supermercados Y Hipermercados",
    "sg:phone":"+34 983 39 90 47",
    "sg:postcode":"47002",
    "sg:province":"Valladolid",
    "wof:name":"Grupo El Arbol Distribucion Y Supermercados S.a. Unipersonal",
    "wof:placetype":"venue"
},
  "geometry": {"coordinates":[-4.7177410126,41.6514816284],"type":"Point"}
}