{
  "type": "Feature",
  "properties": {
    "iso:country":"ES",
    "sg:address":"Ctra. Benavente-puebla, 63",
    "sg:city":"Camarzana Tera",
    "sg:orig_category":"Carnicer\u00cdas, Carnicer\u00cdas",
    "sg:phone":"+34 980 64 94 77",
    "sg:postcode":"49332",
    "sg:province":"Zamora",
    "wof:name":"Casgar Xxi S.l.",
    "wof:placetype":"venue"
},
  "geometry": {"coordinates":[-6.0767960548,41.9845962524],"type":"Point"}
}