{
  "type": "Feature",
  "properties": {
    "addr:full":"Rua San Roque, 12 Xinzo De Limia Ourense 32630",
    "addr:housenumber":"12",
    "addr:postcode":"32630",
    "addr:street":"Rua San Roque",
    "iso:country":"ES",
    "sg:address":"Rua San Roque, 12",
    "sg:city":"Xinzo De Limia",
    "sg:orig_category":"Quincaller\u00cda (al Por Menor)",
    "sg:phone":"+34 988 46 04 17",
    "sg:postcode":"32630",
    "sg:province":"Ourense",
    "wof:name":"Valdeiras Alonso Maria",
    "wof:placetype":"venue"
},
  "geometry": {"coordinates":[-7.727104187,42.0611190796],"type":"Point"}
}