{
  "type": "Feature",
  "properties": {
    "addr:full":"Calle de Orestes Gomez, 6 Porzuna Ciudad Real 13120",
    "addr:housenumber":"6",
    "addr:postcode":"13120",
    "addr:street":"Calle De Orestes Gomez",
    "iso:country":"ES",
    "sg:address":"Calle de Orestes Gomez, 6",
    "sg:city":"Porzuna",
    "sg:orig_category":"Empresas De Demolici\u00d3n",
    "sg:phone":"+34 926 78 01 94",
    "sg:postcode":"13120",
    "sg:province":"Ciudad Real",
    "wof:name":"Garrido Palomares Florentino",
    "wof:placetype":"venue"
},
  "geometry": {"coordinates":[-4.1553301811,39.1480445862],"type":"Point"}
}