{
  "type": "Feature",
  "properties": {
    "addr:full":"Calle de Cantalejo, 7 Madrid Madrid 28035",
    "addr:housenumber":"7",
    "addr:postcode":"madrid;28035",
    "addr:street":"Calle De Cantalejo",
    "iso:country":"ES",
    "sg:address":"Calle de Cantalejo, 7",
    "sg:city":"Madrid",
    "sg:orig_category":"Art\u00cdculos De Decoraci\u00d3n (fabricaci\u00d3n Y Al Por Mayor)",
    "sg:phone":"+34 913 73 32 14",
    "sg:postcode":"28035",
    "sg:province":"Madrid",
    "wof:name":"Nuevo Estudio C.b.",
    "wof:placetype":"venue"
},
  "geometry": {"coordinates":[-3.7403144836,40.4750862122],"type":"Point"}
}