{
  "type": "Feature",
  "properties": {
    "iso:country":"ES",
    "sg:address":"Calle de Pozas (de Las), 36",
    "sg:city":"San Lorenzo De El Escorial",
    "sg:orig_category":"M\u00c9dicos: Estomatolog\u00cda",
    "sg:phone":"+34 918 90 83 38",
    "sg:postcode":"28200",
    "sg:province":"Madrid",
    "wof:name":"Carre\u00f1o Mercau Carlos Alberto",
    "wof:placetype":"venue"
},
  "geometry": {"coordinates":[-4.1462368965,40.5939903259],"type":"Point"}
}