{
  "type": "Feature",
  "properties": {
    "addr:full":"Avda Beire, S/n Olite Navarra 31390",
    "addr:housenumber":"s / n",
    "addr:postcode":"31390",
    "addr:street":"Avda Beire",
    "iso:country":"ES",
    "sg:address":"Avda Beire, S/n",
    "sg:city":"Olite",
    "sg:orig_category":"Chapa Y Pintura Veh\u00cdculos",
    "sg:phone":"+34 948 74 07 75",
    "sg:postcode":"31390",
    "sg:province":"Navarra",
    "wof:name":"Espila Perez Miguel Y Flamarique Alcalde Javier S.cv.",
    "wof:placetype":"venue"
},
  "geometry": {"coordinates":[-1.6481460333,42.4772644043],"type":"Point"}
}