{
  "type": "Feature",
  "properties": {
    "iso:country":"ES",
    "sg:address":"Avda Sabande\u00d1os (los), S/n",
    "sg:city":"Cristianos",
    "sg:orig_category":"Bazares, Art\u00cdculos De Limpieza Y De Cocina (al Por Menor)",
    "sg:phone":"+34 922 79 71 06",
    "sg:postcode":"38650",
    "sg:province":"Santa Cruz De Tenerife",
    "wof:name":"Ramis Santana Pablo",
    "wof:placetype":"venue"
},
  "geometry": {"coordinates":[-16.7148838043,28.0541305542],"type":"Point"}
}