{
  "type": "Feature",
  "properties": {
    "iso:country":"ES",
    "sg:address":"Carretera De Salda\u00f1a-bilbao, S/n",
    "sg:city":"Villadiego",
    "sg:orig_category":"Alimentaci\u00d3n General (al Por Mayor)",
    "sg:phone":"+34 947 36 01 60",
    "sg:postcode":"09120",
    "sg:province":"Burgos",
    "wof:name":"Saiz Aparicio Javier",
    "wof:placetype":"venue"
},
  "geometry": {"coordinates":[-4.0098638535,42.5155296326],"type":"Point"}
}