{
  "type": "Feature",
  "properties": {
    "iso:country":"ES",
    "sg:address":"Calle de Independencia, 3",
    "sg:city":"Ceuta",
    "sg:orig_category":"Bazares, Art\u00cdculos De Limpieza Y De Cocina (al Por Menor)",
    "sg:phone":"+34 956 51 34 68",
    "sg:postcode":"51001",
    "sg:province":"Ceuta",
    "wof:name":"Naraindas Buxani Jai",
    "wof:placetype":"venue"
},
  "geometry": {"coordinates":[-5.3151888847,35.887512207],"type":"Point"}
}