{
  "type": "Feature",
  "properties": {
    "iso:country":"ES",
    "sg:address":"Quintana, 23",
    "sg:city":"Lucena",
    "sg:orig_category":"M\u00c9dicos: Otorrinolaringolog\u00cda",
    "sg:phone":"+34 957 50 25 24",
    "sg:postcode":"14900",
    "sg:province":"C\u00f3rdoba",
    "wof:name":"Ramirez Ponferrada Rafael",
    "wof:placetype":"venue"
},
  "geometry": {"coordinates":[-4.4839801788,37.4107933044],"type":"Point"}
}