{
  "type": "Feature",
  "properties": {
    "addr:full":"Pase Maritimo, 44 Torremolinos M\u00e1laga 29620",
    "addr:housenumber":"44",
    "addr:postcode":"29620",
    "addr:street":"Maritimo;Ma\u0301Laga",
    "iso:country":"ES",
    "sg:address":"Pase Maritimo, 44",
    "sg:city":"Torremolinos",
    "sg:orig_category":"Art\u00cdculos De Regalo (al Por Menor)",
    "sg:phone":"+34 952 38 33 32",
    "sg:postcode":"29620",
    "sg:province":"M\u00e1laga",
    "wof:name":"Exclusivas Garcia Torres S.l.",
    "wof:placetype":"venue"
},
  "geometry": {"coordinates":[-4.4998540878,36.6244087219],"type":"Point"}
}