{
  "type": "Feature",
  "properties": {
    "iso:country":"ES",
    "sg:address":"Trva Ronda Saliente, 5",
    "sg:city":"Valdelacalzada",
    "sg:orig_category":"M\u00c1rmoles, Granitos Y Piedras Naturales",
    "sg:phone":"+34 924 44 62 07",
    "sg:postcode":"06185",
    "sg:province":"Badajoz",
    "wof:name":"Hijos De Sanchez Duarte S.l.",
    "wof:placetype":"venue"
},
  "geometry": {"coordinates":[-6.6972727776,38.8901748657],"type":"Point"}
}