{
  "type": "Feature",
  "properties": {
    "addr:full":"Plaz Trinidad (de La), 3 Cordoba C\u00f3rdoba 14003",
    "addr:postcode":"14003",
    "addr:street":"Plaz;Co\u0301Rdoba",
    "iso:country":"ES",
    "sg:address":"Plaz Trinidad (de La), 3",
    "sg:city":"Cordoba",
    "sg:classifiers":[
        {
            "category":"Arts & Performance",
            "subcategory":"Art Gallery",
            "type":"Entertainment"
        }
    ],
    "sg:phone":"+34 957 20 20 11",
    "sg:postcode":"14003",
    "sg:province":"C\u00f3rdoba",
    "sg:tags":[
        "arte",
        "de",
        "galer\u00cdas"
    ],
    "wof:name":"Recap S.l.",
    "wof:placetype":"venue"
},
  "geometry": {"coordinates":[-4.7830929756,37.8827667236],"type":"Point"}
}