{
  "type": "Feature",
  "properties": {
    "iso:country":"ES",
    "sg:address":"Av Dr. Fleming, De, 54",
    "sg:city":"S. Antoni Portmany",
    "sg:orig_category":"Plomeros",
    "sg:phone":"+34 971 34 57 14",
    "sg:postcode":"07820",
    "sg:province":"Islas Baleares",
    "wof:name":"Torres Gimenez Juan",
    "wof:placetype":"venue"
},
  "geometry": {"coordinates":[1.3099570274,38.9708557129],"type":"Point"}
}