{
  "type": "Feature",
  "properties": {
    "addr:full":"Avda Ejercito Y Marina, 7 Marin Pontevedra 36900",
    "addr:housenumber":"7",
    "addr:postcode":"36900",
    "addr:street":"Avda Ejercito Y Marina",
    "iso:country":"ES",
    "sg:address":"Avda Ejercito Y Marina, 7",
    "sg:city":"Marin",
    "sg:orig_category":"Comercio De Minerales, F\u00d3siles Y Conchas",
    "sg:phone":"+34 986 88 00 07",
    "sg:postcode":"36900",
    "sg:province":"Pontevedra",
    "wof:name":"Perez Tomas Ramon",
    "wof:placetype":"venue"
},
  "geometry": {"coordinates":[-8.7048225403,42.3928718567],"type":"Point"}
}