{
  "type": "Feature",
  "properties": {
    "iso:country":"ES",
    "sg:address":"Rua Ecuador, 69",
    "sg:city":"Vigo",
    "sg:orig_category":"Complementos De Vestir (al Por Menor)",
    "sg:phone":"+34 986 41 10 85",
    "sg:postcode":"36204",
    "sg:province":"Pontevedra",
    "wof:name":"Mundo Complementos S.l.",
    "wof:placetype":"venue"
},
  "geometry": {"coordinates":[-8.716840744,42.2324638367],"type":"Point"}
}