{
  "type": "Feature",
  "properties": {
    "addr:full":"Astigarrako Bidea, 2 Ugaldetxo Guip\u00f9zcoa 20180",
    "addr:housenumber":"2",
    "addr:postcode":"20180",
    "addr:street":"Astigarrako Bidea;Guipu\u0300Zcoa",
    "iso:country":"ES",
    "sg:address":"Astigarrako Bidea, 2",
    "sg:city":"Ugaldetxo",
    "sg:orig_category":"Asesor\u00cda Sobre Comunicaci\u00d3n De Empresas",
    "sg:phone":"+34 943 26 10 43",
    "sg:postcode":"20180",
    "sg:province":"Guip\u00f9zcoa",
    "sg:website":"www.irurak.com",
    "wof:name":"Irurak Servicios Administrativos S.a.l.",
    "wof:placetype":"venue"
},
  "geometry": {"coordinates":[-1.8629590273,43.2992401123],"type":"Point"}
}