{
  "type": "Feature",
  "properties": {
    "addr:full":"Carrer de Pau Casals, 17 Cambrils Tarragona 43850",
    "addr:housenumber":"17",
    "addr:postcode":"43850",
    "addr:street":"Carrer De Pau Casals",
    "iso:country":"ES",
    "sg:address":"Carrer de Pau Casals, 17",
    "sg:city":"Cambrils",
    "sg:orig_category":"Cajas De Ahorro",
    "sg:phone":"+34 977 79 34 16",
    "sg:postcode":"43850",
    "sg:province":"Tarragona",
    "wof:name":"Caixa D'estalvis De Manresa",
    "wof:placetype":"venue"
},
  "geometry": {"coordinates":[1.0598100424,41.0664482117],"type":"Point"}
}