{
  "type": "Feature",
  "properties": {
    "addr:full":"Calle de Calasparra, 2 Madrid Madrid 28033",
    "addr:housenumber":"2",
    "addr:postcode":"28033",
    "addr:street":"Calle De Calasparra",
    "iso:country":"ES",
    "sg:address":"Calle de Calasparra, 2",
    "sg:city":"Madrid",
    "sg:orig_category":"Empresas De Carpinter\u00cda Met\u00c1lica",
    "sg:phone":"+34 917 63 42 74",
    "sg:postcode":"28033",
    "sg:province":"Madrid",
    "wof:name":"Venterpal Pvc S.l.",
    "wof:placetype":"venue"
},
  "geometry": {"coordinates":[-3.6567270756,40.471862793],"type":"Point"}
}