{
  "type": "Feature",
  "properties": {
    "addr:full":"Carrer de Domenech I Montaner, 2 Barcelona Barcelona 08035",
    "addr:housenumber":"2",
    "addr:postcode":"08035",
    "addr:street":"Carrer De Domenech I Montaner",
    "iso:country":"ES",
    "sg:address":"Carrer de Domenech I Montaner, 2",
    "sg:city":"Barcelona",
    "sg:orig_category":"Asilos De Ancianos. Centros Privados",
    "sg:phone":"+34 934 27 70 01",
    "sg:postcode":"08035",
    "sg:province":"Barcelona",
    "wof:name":"Residencial Bacumar S.l.",
    "wof:placetype":"venue"
},
  "geometry": {"coordinates":[2.1424980164,41.4297904968],"type":"Point"}
}