{
  "type": "Feature",
  "properties": {
    "addr:full":"Calle de Cadiz, 3 Burguillos Sevilla 41220",
    "addr:housenumber":"3",
    "addr:postcode":"41220",
    "addr:street":"Calle De Cadiz",
    "iso:country":"ES",
    "sg:address":"Calle de Cadiz, 3",
    "sg:city":"Burguillos",
    "sg:orig_category":"Fabricaci\u00d3n De Tapices Y Moquetas Para Suelos Y Paredes",
    "sg:phone":"+34 955 73 85 50",
    "sg:postcode":"41220",
    "sg:province":"Sevilla",
    "wof:name":"Estucados Burguillos S.l.",
    "wof:placetype":"venue"
},
  "geometry": {"coordinates":[-5.9671759605,37.5813369751],"type":"Point"}
}