{
  "type": "Feature",
  "properties": {
    "iso:country":"ES",
    "sg:address":"Carrer de Alt De Gironella, 7",
    "sg:city":"Barcelona",
    "sg:orig_category":"Internados & Ense\u00d1anza Privada",
    "sg:phone":"+34 932 03 54 59",
    "sg:postcode":"08017",
    "sg:province":"Barcelona",
    "wof:name":"Misioneras Hermanas De Betania",
    "wof:placetype":"venue"
},
  "geometry": {"coordinates":[2.1297519207,41.3947525024],"type":"Point"}
}