{
  "type": "Feature",
  "properties": {
    "addr:full":"Calle de Ortega Y Gasset, 2 Elda Alicante 03600",
    "addr:housenumber":"2",
    "addr:postcode":"03600",
    "addr:street":"Calle De Ortega Y Gasset",
    "iso:country":"ES",
    "sg:address":"Calle de Ortega Y Gasset, 2",
    "sg:city":"Elda",
    "sg:orig_category":"Quincaller\u00cda (al Por Menor)",
    "sg:phone":"+34 965 38 15 96",
    "sg:postcode":"03600",
    "sg:province":"Alicante",
    "wof:name":"Rosique Amat Francisco",
    "wof:placetype":"venue"
},
  "geometry": {"coordinates":[-0.7944059968,38.4777374268],"type":"Point"}
}