{
  "type": "Feature",
  "properties": {
    "addr:full":"Calle de Piedad, 24 Zumarraga Guip\u00f9zcoa 20700",
    "addr:housenumber":"24",
    "addr:postcode":"20700",
    "addr:street":"Calle De Piedad;Guipu\u0300Zcoa",
    "iso:country":"ES",
    "sg:address":"Calle de Piedad, 24",
    "sg:city":"Zumarraga",
    "sg:orig_category":"Contenedores Para Transporte De Mercanc\u00cdas",
    "sg:phone":"+34 943 72 03 87",
    "sg:postcode":"20700",
    "sg:province":"Guip\u00f9zcoa",
    "wof:name":"Transportes Ezkizu S.l.",
    "wof:placetype":"venue"
},
  "geometry": {"coordinates":[-2.313587904,43.0893058777],"type":"Point"}
}