{
  "type": "Feature",
  "properties": {
    "iso:country":"ES",
    "sg:address":"Carrer de Frederic Soler, 4",
    "sg:city":"Cornella Llobregat",
    "sg:orig_category":"Reposter\u00cdas",
    "sg:phone":"+34 934 71 01 21",
    "sg:postcode":"08940",
    "sg:province":"Barcelona",
    "wof:name":"Garcia Garcia Cayo",
    "wof:placetype":"venue"
},
  "geometry": {"coordinates":[2.076100111,41.359954834],"type":"Point"}
}