{
  "type": "Feature",
  "properties": {
    "addr:full":"C/ Reina Victoria, 16 Elche Alicante 03201",
    "addr:housenumber":"16",
    "addr:postcode":"03201",
    "addr:street":"C / Reina Victoria",
    "iso:country":"ES",
    "sg:address":"C/ Reina Victoria, 16",
    "sg:city":"Elche",
    "sg:orig_category":"Frutas Y Legumbres Frescas (al Por Mayor)",
    "sg:phone":"+34 965 44 11 46",
    "sg:postcode":"03201",
    "sg:province":"Alicante",
    "wof:name":"Pascual Macia Antonio",
    "wof:placetype":"venue"
},
  "geometry": {"coordinates":[-0.7017089725,38.265335083],"type":"Point"}
}