{
  "type": "Feature",
  "properties": {
    "iso:country":"ES",
    "sg:address":"Avda Juan De Austria, 15",
    "sg:city":"Alcala Henares",
    "sg:orig_category":"Zapatos (al Por Menor)",
    "sg:phone":"+34 918 88 14 62",
    "sg:postcode":"28804",
    "sg:province":"Madrid",
    "wof:name":"Calzados Austria Y Complementos S.l.",
    "wof:placetype":"venue"
},
  "geometry": {"coordinates":[-3.3510570526,40.4874458313],"type":"Point"}
}