{
  "type": "Feature",
  "properties": {
    "iso:country":"ES",
    "sg:address":"Avda San Juan De La Cruz, 7",
    "sg:city":"Infante Juan Manuel",
    "sg:orig_category":"Material Y Herramientas Agr\u00cdcolas",
    "sg:phone":"+34 968 25 28 98",
    "sg:postcode":"30011",
    "sg:province":"Murcia",
    "wof:name":"Marin Perez Manuel",
    "wof:placetype":"venue"
},
  "geometry": {"coordinates":[-1.123973012,37.9794464111],"type":"Point"}
}