{
  "type": "Feature",
  "properties": {
    "addr:full":"Calle de Rio Esva, 2 Oviedo Asturias 33010",
    "addr:housenumber":"2",
    "addr:postcode":"33010",
    "addr:street":"Calle De Rio Esva",
    "iso:country":"ES",
    "sg:address":"Calle de Rio Esva, 2",
    "sg:city":"Oviedo",
    "sg:orig_category":"Supermercados Y Hipermercados",
    "sg:phone":"+34 985 11 86 34",
    "sg:postcode":"33010",
    "sg:province":"Asturias",
    "wof:name":"Alimerka S.a.",
    "wof:placetype":"venue"
},
  "geometry": {"coordinates":[-5.821803093,43.3697128296],"type":"Point"}
}