{
  "type": "Feature",
  "properties": {
    "addr:full":"Avda Fisterra, 88 Cee La Coru\u00f1a 15270",
    "addr:housenumber":"88",
    "addr:postcode":"15270",
    "addr:street":"Avda Fisterra;La",
    "iso:country":"ES",
    "sg:address":"Avda Fisterra, 88",
    "sg:city":"Cee",
    "sg:orig_category":"Art\u00cdculos De Decoraci\u00d3n",
    "sg:phone":"+34 981 74 53 66",
    "sg:postcode":"15270",
    "sg:province":"La Coru\u00f1a",
    "wof:name":"Rodriguez Blanco Fernando",
    "wof:placetype":"venue"
},
  "geometry": {"coordinates":[-9.1937494278,42.9625587463],"type":"Point"}
}