{
  "type": "Feature",
  "properties": {
    "iso:country":"ES",
    "sg:address":"Calle de Mazas, 13",
    "sg:city":"Salamanca",
    "sg:orig_category":"Fotocopias, Reprograf\u00cda",
    "sg:phone":"+34 923 21 37 27",
    "sg:postcode":"37008",
    "sg:province":"Salamanca",
    "wof:name":"Gonzalez Sanchez Bernardino",
    "wof:placetype":"venue"
},
  "geometry": {"coordinates":[-5.6683712006,40.9606552124],"type":"Point"}
}