{
  "type": "Feature",
  "properties": {
    "addr:full":"Carr Cassia Costal, S/n Girona Girona 17003",
    "addr:housenumber":"s / n",
    "addr:postcode":"17003",
    "addr:street":"Carr Cassia Costal",
    "iso:country":"ES",
    "sg:address":"Carr Cassia Costal, S/n",
    "sg:city":"Girona",
    "sg:orig_category":"Centros De Educaci\u00d3n Especial",
    "sg:phone":"+34 972 20 21 91",
    "sg:postcode":"17003",
    "sg:province":"Girona",
    "wof:name":"Ceip Cassia Costal",
    "wof:placetype":"venue"
},
  "geometry": {"coordinates":[2.8155450821,41.9737510681],"type":"Point"}
}