{
  "type": "Feature",
  "properties": {
    "addr:full":"Casa Pujol, S/n Naves Lleida 25286",
    "addr:housenumber":"/ n",
    "addr:postcode":"25286",
    "addr:street":"S",
    "iso:country":"ES",
    "sg:address":"Casa Pujol, S/n",
    "sg:city":"Naves",
    "sg:orig_category":"Alquiler De Casas Y Habitaciones Amuebladas",
    "sg:phone":"+34 973 29 90 45",
    "sg:postcode":"25286",
    "sg:province":"Lleida",
    "wof:name":"Saturn",
    "wof:placetype":"venue"
},
  "geometry": {"coordinates":[1.4181050062,41.9509010315],"type":"Point"}
}