{
  "type": "Feature",
  "properties": {
    "addr:full":"Av Ignasi Wallis, 33 Eivissa Islas Baleares 07800",
    "addr:housenumber":"33",
    "addr:postcode":"07800",
    "addr:street":"Av Ignasi Wallis",
    "iso:country":"ES",
    "sg:address":"Av Ignasi Wallis, 33",
    "sg:city":"Eivissa",
    "sg:orig_category":"Ense\u00d1anza Secundaria: Colegios Y Escuelas Privadas",
    "sg:phone":"+34 971 19 00 18",
    "sg:postcode":"07800",
    "sg:province":"Islas Baleares",
    "wof:name":"Instituto De Bachillerato Santa Maria De Eivissa",
    "wof:placetype":"venue"
},
  "geometry": {"coordinates":[1.4305360317,38.911529541],"type":"Point"}
}