{
  "type": "Feature",
  "properties": {
    "addr:full":"Carrer de Sant Adria, 40 Barcelona Barcelona 08030",
    "addr:housenumber":"40",
    "addr:postcode":"08030",
    "addr:street":"Carrer De Sant Adria",
    "iso:country":"ES",
    "sg:address":"Carrer de Sant Adria, 40",
    "sg:city":"Barcelona",
    "sg:orig_category":"Energ\u00cda Solar Y Nuevas Energ\u00cdas (equipo, Estudios)",
    "sg:phone":"+34 933 45 78 32",
    "sg:postcode":"08030",
    "sg:province":"Barcelona",
    "wof:name":"Marcos Rodriguez Luis",
    "wof:placetype":"venue"
},
  "geometry": {"coordinates":[2.1943330765,41.4350700378],"type":"Point"}
}