{
  "type": "Feature",
  "properties": {
    "iso:country":"ES",
    "sg:address":"Plaz Pontevedra, 17",
    "sg:city":"Coru\u00d1a",
    "sg:orig_category":"Empresarios",
    "sg:phone":"+34 981 25 75 43",
    "sg:postcode":"15003",
    "sg:province":"La Coru\u00f1a",
    "wof:name":"Fernandez Alvarez Jose",
    "wof:placetype":"venue"
},
  "geometry": {"coordinates":[-8.4063863754,43.3679389954],"type":"Point"}
}