{
  "type": "Feature",
  "properties": {
    "iso:country":"ES",
    "sg:address":"Carrer de Marie Curie, 5",
    "sg:city":"S. Esteve Sesrovires",
    "sg:orig_category":"Marketing Directo",
    "sg:phone":"+34 937 71 46 27",
    "sg:postcode":"08635",
    "sg:province":"Barcelona",
    "wof:name":"Joy Novelty S.l.",
    "wof:placetype":"venue"
},
  "geometry": {"coordinates":[1.8823900223,41.4792747498],"type":"Point"}
}