{
  "type": "Feature",
  "properties": {
    "iso:country":"ES",
    "sg:address":"Abejeras, 49",
    "sg:city":"Iru\u00f1a",
    "sg:orig_category":"Peluquer\u00cdas, Peluquer\u00cda Mixta",
    "sg:phone":"+34 948 15 08 80",
    "sg:postcode":"31007",
    "sg:province":"Navarra",
    "wof:name":"Lopez Delgado Isabel Y Mugueta Burguete Cristina S.cv.",
    "wof:placetype":"venue"
},
  "geometry": {"coordinates":[-1.6474540234,42.8037948608],"type":"Point"}
}