{
  "type": "Feature",
  "properties": {
    "iso:country":"ES",
    "sg:address":"Pase Reina Cristina, 30",
    "sg:city":"Madrid",
    "sg:orig_category":"Confecci\u00d3n De Trajes Para Se\u00d1oras",
    "sg:phone":"+34 915 01 17 48",
    "sg:postcode":"28014",
    "sg:province":"Madrid",
    "wof:name":"Cuadrado Torres Maria Francisca",
    "wof:placetype":"venue"
},
  "geometry": {"coordinates":[-3.6799120903,40.4071273804],"type":"Point"}
}