{
  "type": "Feature",
  "properties": {
    "iso:country":"ES",
    "sg:address":"Calle de Sagasta, 18",
    "sg:city":"Cadiz",
    "sg:orig_category":"Mutuas De Seguros",
    "sg:phone":"+34 956 21 24 70",
    "sg:postcode":"11001",
    "sg:province":"C\u00e1diz",
    "wof:name":"Union Mutua Asistencial De Seguros",
    "wof:placetype":"venue"
},
  "geometry": {"coordinates":[-6.298099041,36.5330238342],"type":"Point"}
}