{
  "type": "Feature",
  "properties": {
    "addr:full":"Calle de Pintor Ramos Rosas, 5 Malaga M\u00e1laga 29014",
    "addr:housenumber":"5",
    "addr:postcode":"29014",
    "addr:street":"Calle De Pintor Ramos Rosas;Ma\u0301Laga",
    "iso:country":"ES",
    "sg:address":"Calle de Pintor Ramos Rosas, 5",
    "sg:city":"Malaga",
    "sg:classifiers":[
        {
            "category":"Personal",
            "subcategory":"Barber",
            "type":"Services"
        }
    ],
    "sg:phone":"+34 952 25 22 32",
    "sg:postcode":"29014",
    "sg:province":"M\u00e1laga",
    "sg:tags":[
        "caballeros",
        "de",
        "peluqueros"
    ],
    "wof:name":"Prados Molina Jose Antonio",
    "wof:placetype":"venue"
},
  "geometry": {"coordinates":[-4.4170641899,36.7497253418],"type":"Point"}
}