{
  "type": "Feature",
  "properties": {
    "addr:full":"Calle de Parque De San Fernando, 2 Alcala Henares Madrid 28807",
    "addr:housenumber":"2",
    "addr:postcode":"28807",
    "addr:street":"Calle De Parque De San Fernando",
    "iso:country":"ES",
    "sg:address":"Calle de Parque De San Fernando, 2",
    "sg:city":"Alcala Henares",
    "sg:orig_category":"Abogados",
    "sg:phone":"+34 918 79 64 35",
    "sg:postcode":"28807",
    "sg:province":"Madrid",
    "wof:name":"Vadillo Ortega Esther",
    "wof:placetype":"venue"
},
  "geometry": {"coordinates":[-3.3645970821,40.4864311218],"type":"Point"}
}