{
  "type": "Feature",
  "properties": {
    "iso:country":"ES",
    "sg:address":"Calle de Giralda, 1",
    "sg:city":"Jerez De La Frontera",
    "sg:orig_category":"Farmacias",
    "sg:phone":"+34 956 34 77 37",
    "sg:postcode":"11406",
    "sg:province":"C\u00e1diz",
    "wof:name":"Zajara Espinosa Juan",
    "wof:placetype":"venue"
},
  "geometry": {"coordinates":[-6.111038208,36.6749610901],"type":"Point"}
}