{
  "type": "Feature",
  "properties": {
    "addr:full":"Real, 10 Almu\u00f1ecar Granada 18690",
    "addr:housenumber":"10",
    "addr:postcode":"18690",
    "addr:street":"Real",
    "iso:country":"ES",
    "sg:address":"Real, 10",
    "sg:city":"Almu\u00f1ecar",
    "sg:orig_category":"Librer\u00cdas",
    "sg:phone":"+34 958 63 01 01",
    "sg:postcode":"18690",
    "sg:province":"Granada",
    "wof:name":"Contreras Martin Juan",
    "wof:placetype":"venue"
},
  "geometry": {"coordinates":[-3.690584898,36.7331733704],"type":"Point"}
}