{
  "type": "Feature",
  "properties": {
    "iso:country":"ES",
    "sg:address":"C/ Mancor, 14",
    "sg:city":"Inca",
    "sg:orig_category":"Electricidad (montaje, Ensamblaje De Componentes)",
    "sg:phone":"+34 971 50 32 73",
    "sg:postcode":"07300",
    "sg:province":"Islas Baleares",
    "wof:name":"Electrica Lupino S.l.",
    "wof:placetype":"venue"
},
  "geometry": {"coordinates":[2.9056529999,39.7222824097],"type":"Point"}
}