{
  "type": "Feature",
  "properties": {
    "addr:full":"Calle de Huesca (de), 5 Fuenlabrada Madrid 28941",
    "addr:housenumber":"5",
    "addr:postcode":"28941",
    "addr:street":"Calle De Huesca De",
    "iso:country":"ES",
    "sg:address":"Calle de Huesca (de), 5",
    "sg:city":"Fuenlabrada",
    "sg:orig_category":"Ense\u00d1anza: Profesiones Art\u00cdsticas",
    "sg:phone":"+34 916 15 38 75",
    "sg:postcode":"28941",
    "sg:province":"Madrid",
    "wof:name":"Mu\u00f1oz Gamarra Miguel",
    "wof:placetype":"venue"
},
  "geometry": {"coordinates":[-3.7957930565,40.2947845459],"type":"Point"}
}