{
  "type": "Feature",
  "properties": {
    "iso:country":"ES",
    "sg:address":"Rua Pintor Xenaro Carrero, 25",
    "sg:city":"Noia",
    "sg:orig_category":"Parques De Atracciones Y Centros De Esparcimiento",
    "sg:phone":"+34 981 82 27 11",
    "sg:postcode":"15200",
    "sg:province":"La Coru\u00f1a",
    "wof:name":"Moreno Hermida Ricardo Franco",
    "wof:placetype":"venue"
},
  "geometry": {"coordinates":[-8.8896656036,42.7887458801],"type":"Point"}
}