{
  "type": "Feature",
  "properties": {
    "iso:country":"ES",
    "sg:address":"Carrer de Sant Joaquim, 113",
    "sg:city":"Santa Coloma De Gramenet",
    "sg:orig_category":"Frutas, Legumbres Frescas Y Tempranas (al Por Menor)",
    "sg:phone":"+34 933 86 86 36",
    "sg:postcode":"08922",
    "sg:province":"Barcelona",
    "wof:name":"Gallardo Bonillo Rosario",
    "wof:placetype":"venue"
},
  "geometry": {"coordinates":[2.2075181007,41.4464607239],"type":"Point"}
}