{
  "type": "Feature",
  "properties": {
    "iso:country":"ES",
    "sg:address":"Calle de Pedro Mu\u00d1oz Seca, 13",
    "sg:city":"Puerto De Santa Maria",
    "sg:orig_category":"Fabricaci\u00d3n, Importaci\u00d3n, Venta De Material De Telefon\u00cda, Peritelefon\u00cda",
    "sg:phone":"+34 956 86 09 12",
    "sg:postcode":"11500",
    "sg:province":"C\u00e1diz",
    "wof:name":"Jecomtel Comunicaciones S.l.",
    "wof:placetype":"venue"
},
  "geometry": {"coordinates":[-6.2262268066,36.5991516113],"type":"Point"}
}