{
  "type": "Feature",
  "properties": {
    "iso:country":"ES",
    "sg:address":"Ptda Altabix, 122",
    "sg:city":"Elche",
    "sg:orig_category":"Industria Qu\u00cdmica",
    "sg:phone":"+34 965 42 16 46",
    "sg:postcode":"03291",
    "sg:province":"Alicante",
    "wof:name":"Recuperacion De Aceites Vegetales Costa Blanca S.l.",
    "wof:placetype":"venue"
},
  "geometry": {"coordinates":[-0.6765189767,38.2994346619],"type":"Point"}
}