{
  "type": "Feature",
  "properties": {
    "iso:country":"ES",
    "sg:address":"Calle de Mayor, 13",
    "sg:city":"Irun",
    "sg:orig_category":"Molduras, Junquillos, Listones Y Molduras Perforadas",
    "sg:phone":"+34 943 62 11 95",
    "sg:postcode":"20304",
    "sg:province":"Guip\u00f9zcoa",
    "wof:name":"Gonzalez Jimenez Jose Maria",
    "wof:placetype":"venue"
},
  "geometry": {"coordinates":[-1.7900589705,43.338142395],"type":"Point"}
}