{
  "type": "Feature",
  "properties": {
    "iso:country":"ES",
    "sg:address":"Av. Scho Fuerte, 81",
    "sg:city":"Iru\u00f1a",
    "sg:orig_category":"Parques De Atracciones Y Centros De Esparcimiento",
    "sg:phone":"+34 948 17 28 09",
    "sg:postcode":"31008",
    "sg:province":"Navarra",
    "wof:name":"Recreativos Cenzano S.a.",
    "wof:placetype":"venue"
},
  "geometry": {"coordinates":[-1.66159904,42.8115653992],"type":"Point"}
}