{
  "type": "Feature",
  "properties": {
    "addr:full":"Carrer de Miguel Hernandez, 28 Viladecans Barcelona 08840",
    "addr:housenumber":"28",
    "addr:postcode":"08840",
    "addr:street":"Carrer De Miguel Hernandez",
    "iso:country":"ES",
    "sg:address":"Carrer de Miguel Hernandez, 28",
    "sg:city":"Viladecans",
    "sg:orig_category":"Zapatos (al Por Menor)",
    "sg:phone":"+34 936 37 49 84",
    "sg:postcode":"08840",
    "sg:province":"Barcelona",
    "wof:name":"Mu\u00f1oz Serrano Maria Manuela",
    "wof:placetype":"venue"
},
  "geometry": {"coordinates":[2.0132861137,41.321975708],"type":"Point"}
}