{
  "type": "Feature",
  "properties": {
    "iso:country":"ES",
    "sg:address":"Poli Industrial Morea Sur, S/n",
    "sg:city":"Casco Viejo",
    "sg:orig_category":"Inform\u00c1tica: Soportes De Informaci\u00d3n, Suministros & Accesorios",
    "sg:phone":"+34 948 35 07 01",
    "sg:postcode":"31191",
    "sg:province":"Navarra",
    "wof:name":"Ciclotoner System S.l.",
    "wof:placetype":"venue"
},
  "geometry": {"coordinates":[-1.6518089771,42.7533912659],"type":"Point"}
}