{
  "type": "Feature",
  "properties": {
    "addr:full":"Calle de Historiador Diago, 10 Valencia Valencia 46007",
    "addr:housenumber":"10",
    "addr:postcode":"46007",
    "addr:street":"Calle De Historiador Diago",
    "iso:country":"ES",
    "sg:address":"Calle de Historiador Diago, 10",
    "sg:city":"Valencia",
    "sg:orig_category":"Cristaler\u00cdas",
    "sg:phone":"+34 963 85 32 23",
    "sg:postcode":"46007",
    "sg:province":"Valencia",
    "wof:name":"Cristaleria Crisnacar S.l.",
    "wof:placetype":"venue"
},
  "geometry": {"coordinates":[-0.384344995,39.4674110413],"type":"Point"}
}