{
  "type": "Feature",
  "properties": {
    "addr:full":"Avda Lugo (de), 3 Santiago De Compostela La Coru\u00f1a 15702",
    "addr:housenumber":"3",
    "addr:postcode":"15702",
    "addr:street":"Avda Lugo De;Corun\u0303A",
    "iso:country":"ES",
    "sg:address":"Avda Lugo (de), 3",
    "sg:city":"Santiago De Compostela",
    "sg:orig_category":"Quincaller\u00cda (al Por Menor)",
    "sg:phone":"+34 981 56 31 99",
    "sg:postcode":"15702",
    "sg:province":"La Coru\u00f1a",
    "wof:name":"Ferrecal S. A.",
    "wof:placetype":"venue"
},
  "geometry": {"coordinates":[-8.5439386368,42.8720359802],"type":"Point"}
}