{
  "type": "Feature",
  "properties": {
    "iso:country":"ES",
    "sg:address":"Calle de Xenpelar, 4",
    "sg:city":"Bilbao",
    "sg:orig_category":"Pescader\u00cdas (al Por Menor)",
    "sg:phone":"+34 944 43 01 60",
    "sg:postcode":"48003",
    "sg:province":"Vizcaya",
    "wof:name":"Otazua Ocerin Maria Bego\u00f1a",
    "wof:placetype":"venue"
},
  "geometry": {"coordinates":[-2.9335868359,43.2529754639],"type":"Point"}
}