{
  "type": "Feature",
  "properties": {
    "iso:country":"ES",
    "sg:address":"Salegi Kalea, 5",
    "sg:city":"Zarautz",
    "sg:orig_category":"Zapatos (al Por Menor)",
    "sg:phone":"+34 943 89 42 35",
    "sg:postcode":"20800",
    "sg:province":"Guip\u00f9zcoa",
    "wof:name":"Leunda Uria Maria Teresa",
    "wof:placetype":"venue"
},
  "geometry": {"coordinates":[-2.1729390621,43.2852096558],"type":"Point"}
}