{
  "type": "Feature",
  "properties": {
    "addr:full":"Calle de Alenza, 3 Madrid Madrid 28003",
    "addr:housenumber":"3",
    "addr:postcode":"28003",
    "addr:street":"Calle De Alenza",
    "iso:country":"ES",
    "sg:address":"Calle de Alenza, 3",
    "sg:city":"Madrid",
    "sg:classifiers":[
        {
            "category":"Professional",
            "subcategory":"Management & Consulting",
            "type":"Services"
        }
    ],
    "sg:phone":"+34 915 54 11 10",
    "sg:postcode":"28003",
    "sg:province":"Madrid",
    "sg:tags":[
        "asesor\u00cda",
        "en",
        "marketing"
    ],
    "wof:name":"Regalos Difer S.l.",
    "wof:placetype":"venue"
},
  "geometry": {"coordinates":[-3.7006502151,40.4432144165],"type":"Point"}
}