{
  "type": "Feature",
  "properties": {
    "iso:country":"ES",
    "sg:address":"Calle de San Mateo, 2",
    "sg:city":"Salamanca",
    "sg:orig_category":"M\u00c9dicos: Estomatolog\u00cda",
    "sg:phone":"+34 923 21 53 93",
    "sg:postcode":"37002",
    "sg:province":"Salamanca",
    "wof:name":"Centro Aleman De Estomatologia Y Cirugia",
    "wof:placetype":"venue"
},
  "geometry": {"coordinates":[-5.6644701958,40.9694328308],"type":"Point"}
}