{
  "type": "Feature",
  "properties": {
    "addr:full":"Calle de Porvenir, 32 Sevilla Sevilla 41013",
    "addr:housenumber":"32",
    "addr:postcode":"41013",
    "addr:street":"Calle De Porvenir",
    "iso:country":"ES",
    "sg:address":"Calle de Porvenir, 32",
    "sg:city":"Sevilla",
    "sg:orig_category":"Ingenier\u00cda, Centros De Estudios (diversos)",
    "sg:phone":"+34 954 29 69 55",
    "sg:postcode":"41013",
    "sg:province":"Sevilla",
    "sg:website":"www.ima-e.com",
    "wof:name":"Integracion Medioambiental S.l.",
    "wof:placetype":"venue"
},
  "geometry": {"coordinates":[-5.981303215,37.3721961975],"type":"Point"}
}