{
  "type": "Feature",
  "properties": {
    "addr:full":"Carrer de Rius I Taulet, 15 S. Joan Despi Barcelona 08970",
    "addr:housenumber":"15",
    "addr:postcode":"08970",
    "addr:street":"Carrer De Rius I Taulet;S. Joan Despi",
    "iso:country":"ES",
    "sg:address":"Carrer de Rius I Taulet, 15",
    "sg:city":"S. Joan Despi",
    "sg:orig_category":"Cr\u00cda De Animales",
    "sg:phone":"+34 933 73 22 66",
    "sg:postcode":"08970",
    "sg:province":"Barcelona",
    "wof:name":"Miguel Doblas Jose Antonio",
    "wof:placetype":"venue"
},
  "geometry": {"coordinates":[2.0611739159,41.3652153015],"type":"Point"}
}