{
  "type": "Feature",
  "properties": {
    "iso:country":"ES",
    "sg:address":"Arafo-guimar, 7",
    "sg:city":"Arafo",
    "sg:orig_category":"Alimentaci\u00d3n Animal (fabricaci\u00d3n, Al Por Mayor)",
    "sg:phone":"+34 922 51 36 64",
    "sg:postcode":"38550",
    "sg:province":"Santa Cruz De Tenerife",
    "wof:name":"Batista Garcia Rosendo Elias",
    "wof:placetype":"venue"
},
  "geometry": {"coordinates":[-16.418806076,28.3398151398],"type":"Point"}
}