{
  "type": "Feature",
  "properties": {
    "addr:full":"Avgd Ricard Hernandez, 26 Alcasser Valencia 46290",
    "addr:housenumber":"26",
    "addr:postcode":"46290",
    "addr:street":"Hernandez",
    "iso:country":"ES",
    "sg:address":"Avgd Ricard Hernandez, 26",
    "sg:city":"Alcasser",
    "sg:orig_category":"Molduras, Junquillos, Listones Y Molduras Perforadas",
    "sg:phone":"+34 961 24 10 81",
    "sg:postcode":"46290",
    "sg:province":"Valencia",
    "wof:name":"Sanchez Vargas Evaristo",
    "wof:placetype":"venue"
},
  "geometry": {"coordinates":[-0.4483970106,39.3694801331],"type":"Point"}
}