{
  "type": "Feature",
  "properties": {
    "iso:country":"ES",
    "sg:address":"Calle de Isabel Allende, 2",
    "sg:city":"Getafe",
    "sg:orig_category":"Ropa Para Ni\u00d1os (al Por Menor)",
    "sg:phone":"+34 916 95 34 50",
    "sg:postcode":"28903",
    "sg:province":"Madrid",
    "sg:website":"www.mango.es",
    "wof:name":"Punto Fa S.l.",
    "wof:placetype":"venue"
},
  "geometry": {"coordinates":[-3.7222640514,40.3242492676],"type":"Point"}
}