{
  "type": "Feature",
  "properties": {
    "addr:full":"Calle de Agosto, 5 Madrid Madrid 28022",
    "addr:housenumber":"5",
    "addr:postcode":"28022",
    "addr:street":"Calle De Agosto",
    "iso:country":"ES",
    "sg:address":"Calle de Agosto, 5",
    "sg:city":"Madrid",
    "sg:orig_category":"Escultores, Estatuarios E Imagineros",
    "sg:phone":"+34 917 47 86 93",
    "sg:postcode":"28022",
    "sg:province":"Madrid",
    "wof:name":"Esculturas Y Metales Artisticos S.l.",
    "wof:placetype":"venue"
},
  "geometry": {"coordinates":[-3.5715546608,40.4419975281],"type":"Point"}
}