{
  "type": "Feature",
  "properties": {
    "addr:full":"Calle de Veronica, 1 Valverde Camino Huelva 21600",
    "addr:housenumber":"1",
    "addr:postcode":"21600",
    "addr:street":"Calle De Veronica;Camino Huelva",
    "iso:country":"ES",
    "sg:address":"Calle de Veronica, 1",
    "sg:city":"Valverde Camino",
    "sg:orig_category":"Doctores En Medicina",
    "sg:phone":"+34 959 55 30 40",
    "sg:postcode":"21600",
    "sg:province":"Huelva",
    "wof:name":"Dominguez Garrido Claudio",
    "wof:placetype":"venue"
},
  "geometry": {"coordinates":[-6.7554340363,37.56823349],"type":"Point"}
}