{
  "type": "Feature",
  "properties": {
    "iso:country":"ES",
    "sg:address":"Trva Marraco, 32",
    "sg:city":"Hecho",
    "sg:orig_category":"Reposter\u00cdas",
    "sg:phone":"+34 974 37 50 47",
    "sg:postcode":"22720",
    "sg:province":"Huesca",
    "wof:name":"J.l. Brun S.c.v",
    "wof:placetype":"venue"
},
  "geometry": {"coordinates":[-0.7493690252,42.7384414673],"type":"Point"}
}