{
  "type": "Feature",
  "properties": {
    "addr:full":"Ctra Manlleu, 59 Vic Barcelona 08500",
    "addr:housenumber":"59",
    "addr:postcode":"08500",
    "addr:street":"Ctra Manlleu",
    "iso:country":"ES",
    "sg:address":"Ctra Manlleu, 59",
    "sg:city":"Vic",
    "sg:orig_category":"Venta, Instalaci\u00d3n De Quemadores",
    "sg:phone":"+34 938 89 15 34",
    "sg:postcode":"08500",
    "sg:province":"Barcelona",
    "wof:name":"Termibarna S.a.",
    "wof:placetype":"venue"
},
  "geometry": {"coordinates":[2.2580399513,41.9449653625],"type":"Point"}
}