{
  "type": "Feature",
  "properties": {
    "addr:full":"Carrer de Florida, 134 Hospitalet Llobregat Barcelona 08905",
    "addr:housenumber":"134",
    "addr:postcode":"08905",
    "addr:street":"Carrer De Florida",
    "iso:country":"ES",
    "sg:address":"Carrer de Florida, 134",
    "sg:city":"Hospitalet Llobregat",
    "sg:orig_category":"Desinfecci\u00d3n, Desinsectaci\u00d3n, Desratizaci\u00d3n",
    "sg:phone":"+34 934 47 00 18",
    "sg:postcode":"08905",
    "sg:province":"Barcelona",
    "wof:name":"Comarc Fumigaciones S.c.p.",
    "wof:placetype":"venue"
},
  "geometry": {"coordinates":[2.1081390381,41.3688583374],"type":"Point"}
}