{
  "type": "Feature",
  "properties": {
    "iso:country":"ES",
    "sg:address":"Calle de Domingo Beltran De Otazu, 39",
    "sg:city":"Vitoria-gasteiz",
    "sg:orig_category":"Ropa Para Caballeros (al Por Menor)",
    "sg:phone":"+34 945 24 30 47",
    "sg:postcode":"01012",
    "sg:province":"\u00c1lava",
    "wof:name":"Larrucea Lopez Angel Maria",
    "wof:placetype":"venue"
},
  "geometry": {"coordinates":[-2.6768507957,42.8535346985],"type":"Point"}
}