{
  "type": "Feature",
  "properties": {
    "iso:country":"ES",
    "sg:address":"Calle de Espejo, 17",
    "sg:city":"Sevilla",
    "sg:orig_category":"Farmacias",
    "sg:phone":"+34 954 69 09 21",
    "sg:postcode":"41014",
    "sg:province":"Sevilla",
    "wof:name":"Illanes Fraile Julio Jose",
    "wof:placetype":"venue"
},
  "geometry": {"coordinates":[-5.9663105011,37.3192024231],"type":"Point"}
}