{
  "type": "Feature",
  "properties": {
    "addr:full":"Carrer de Industria, 16 Buvisa Barcelona 08329",
    "addr:housenumber":"16",
    "addr:postcode":"08329",
    "addr:street":"Carrer De Industria;Barcelona",
    "iso:country":"ES",
    "sg:address":"Carrer de Industria, 16",
    "sg:city":"Buvisa",
    "sg:orig_category":"Limpieza Con Chorro De Arena Y Con Granalla, Pulido",
    "sg:phone":"+34 935 40 79 80",
    "sg:postcode":"08329",
    "sg:province":"Barcelona",
    "wof:name":"Marpul S.l.",
    "wof:placetype":"venue"
},
  "geometry": {"coordinates":[2.3220500946,41.498260498],"type":"Point"}
}