{
  "type": "Feature",
  "properties": {
    "iso:country":"ES",
    "sg:address":"Calle de Felipe Ii, 6",
    "sg:city":"Espinosa De Los Monteros",
    "sg:orig_category":"Supermercados Y Hipermercados",
    "sg:phone":"+34 947 12 01 11",
    "sg:postcode":"09560",
    "sg:province":"Burgos",
    "wof:name":"Baranda Pereda Gumersindo",
    "wof:placetype":"venue"
},
  "geometry": {"coordinates":[-3.5553660393,43.0790252686],"type":"Point"}
}