{
  "type": "Feature",
  "properties": {
    "iso:country":"ES",
    "sg:address":"Calle de Salvador Minguijon, 56",
    "sg:city":"Zaragoza",
    "sg:orig_category":"Centros Comerciales Y Grandes Tiendas",
    "sg:phone":"+34 976 41 29 71",
    "sg:postcode":"50002",
    "sg:province":"Zaragoza",
    "wof:name":"Douh  Driss",
    "wof:placetype":"venue"
},
  "geometry": {"coordinates":[-0.8611009717,41.6493911743],"type":"Point"}
}