{
  "type": "Feature",
  "properties": {
    "addr:full":"Avda Republica Argentina, 6 Logro\u00f1o La Rioja 26002",
    "addr:housenumber":"6",
    "addr:postcode":"26002",
    "addr:street":"Avda Republica Argentina;Rioja",
    "iso:country":"ES",
    "sg:address":"Avda Republica Argentina, 6",
    "sg:city":"Logro\u00f1o",
    "sg:orig_category":"Ropa Para Se\u00d1oras Y Caballeros (al Por Menor)",
    "sg:phone":"+34 941 21 14 72",
    "sg:postcode":"26002",
    "sg:province":"La Rioja",
    "wof:name":"Action Quads S.l.",
    "wof:placetype":"venue"
},
  "geometry": {"coordinates":[-2.4482576847,42.463218689],"type":"Point"}
}