{
  "type": "Feature",
  "properties": {
    "iso:country":"ES",
    "sg:address":"Edras(pol Ind Milladoiro), S/n",
    "sg:city":"Milladoiro",
    "sg:orig_category":"Aluminio Y Aleaciones (producci\u00d3n, Transformaci\u00d3n, Negocio)",
    "sg:phone":"+34 981 53 63 25",
    "sg:postcode":"15895",
    "sg:province":"La Coru\u00f1a",
    "sg:website":"www.euralex.es",
    "wof:name":"Comercial De Metales Malaga S.l.",
    "wof:placetype":"venue"
},
  "geometry": {"coordinates":[-8.585144043,42.8543205261],"type":"Point"}
}