{
  "type": "Feature",
  "properties": {
    "iso:country":"ES",
    "sg:address":"Carrer de Juan Sebastian Elcano, 10",
    "sg:city":"Cambrils",
    "sg:orig_category":"Agencias De Viajes",
    "sg:phone":"+34 977 79 49 20",
    "sg:postcode":"43850",
    "sg:province":"Tarragona",
    "wof:name":"Capitol Viatges S.l.",
    "wof:placetype":"venue"
},
  "geometry": {"coordinates":[1.0592360497,41.0666618347],"type":"Point"}
}