{
  "type": "Feature",
  "properties": {
    "addr:full":"Carr Aguila-montemar, 10 Montemar-la Vi\u00e7a Alicante 03720",
    "addr:housenumber":"10",
    "addr:postcode":"03720",
    "addr:street":"Carr Aguila-Montemar",
    "iso:country":"ES",
    "sg:address":"Carr Aguila-montemar, 10",
    "sg:city":"Montemar-la Vi\u00e7a",
    "sg:orig_category":"Inmobiliaria (agencias)",
    "sg:phone":"+34 965 74 92 29",
    "sg:postcode":"03720",
    "sg:province":"Alicante",
    "wof:name":"Wenger  Joerg",
    "wof:placetype":"venue"
},
  "geometry": {"coordinates":[-0.4810059965,38.3452033997],"type":"Point"}
}