{
  "type": "Feature",
  "properties": {
    "addr:full":"Calle de San Jose Obrero, 10 Casas-iba\u00e7ez Albacete 02200",
    "addr:housenumber":"10",
    "addr:postcode":"02200",
    "addr:street":"Calle De;Obrero",
    "iso:country":"ES",
    "sg:address":"Calle de San Jose Obrero, 10",
    "sg:city":"Casas-iba\u00e7ez",
    "sg:orig_category":"Fisioterapia",
    "sg:phone":"+34 967 46 20 09",
    "sg:postcode":"02200",
    "sg:province":"Albacete",
    "wof:name":"Cambronero Martinez Maria",
    "wof:placetype":"venue"
},
  "geometry": {"coordinates":[-1.4753619432,39.2876472473],"type":"Point"}
}