{
  "type": "Feature",
  "properties": {
    "iso:country":"ES",
    "sg:address":"Calle de Miguel De Cervantes, 8",
    "sg:city":"Melilla",
    "sg:orig_category":"Administradores De Bienes Y Delegados De Comunidades De Propietarios",
    "sg:phone":"+34 952 68 14 35",
    "sg:postcode":"52001",
    "sg:province":"Melilla",
    "wof:name":"Losana Romero Francisco Javier",
    "wof:placetype":"venue"
},
  "geometry": {"coordinates":[-2.9385950565,35.2936668396],"type":"Point"}
}