{
  "type": "Feature",
  "properties": {
    "addr:full":"Portaine, S/n Rialp Lleida 25594",
    "addr:housenumber":"/ n",
    "addr:postcode":"25594",
    "addr:street":"Portaine S",
    "iso:country":"ES",
    "sg:address":"Portaine, S/n",
    "sg:city":"Rialp",
    "sg:orig_category":"Gu\u00cdas De Monta\u00d1a, Monitores De Esqu\u00cd, Acompa\u00d1antes En Monta\u00d1a",
    "sg:phone":"+34 973 25 00 64",
    "sg:postcode":"25594",
    "sg:province":"Lleida",
    "sg:website":"www.port-aine.com",
    "wof:name":"Pallars Industrial S. A.",
    "wof:placetype":"venue"
},
  "geometry": {"coordinates":[1.134945035,42.4431915283],"type":"Point"}
}