{
  "type": "Feature",
  "properties": {
    "addr:full":"Calle de San Francisco, 4 Baza Granada 18800",
    "addr:housenumber":"4",
    "addr:postcode":"18800",
    "addr:street":"Calle De San Francisco",
    "iso:country":"ES",
    "sg:address":"Calle de San Francisco, 4",
    "sg:city":"Baza",
    "sg:orig_category":"Asesor\u00cda Fiscal Y Jur\u00cddica",
    "sg:phone":"+34 958 70 22 49",
    "sg:postcode":"18800",
    "sg:province":"Granada",
    "wof:name":"Peregrin Martinez Juan Jose",
    "wof:placetype":"venue"
},
  "geometry": {"coordinates":[-2.7758016586,37.4920539856],"type":"Point"}
}