{
  "type": "Feature",
  "properties": {
    "addr:full":"Calle de Alcala, 282 Madrid Madrid 28027",
    "addr:housenumber":"282",
    "addr:postcode":"28027",
    "addr:street":"Calle De Alcala",
    "iso:country":"ES",
    "sg:address":"Calle de Alcala, 282",
    "sg:city":"Madrid",
    "sg:orig_category":"Supermercados Y Hipermercados",
    "sg:phone":"+34 913 26 26 25",
    "sg:postcode":"28027",
    "sg:province":"Madrid",
    "sg:website":"www.repsolypf.es",
    "wof:name":"Repsol Ypf S.a.",
    "wof:placetype":"venue"
},
  "geometry": {"coordinates":[-3.6524972916,40.4324798584],"type":"Point"}
}