{
  "type": "Feature",
  "properties": {
    "addr:full":"Plaz Cervantes, 4 Osuna Sevilla 41640",
    "addr:housenumber":"4",
    "addr:postcode":"41640",
    "addr:street":"Plaz Cervantes",
    "iso:country":"ES",
    "sg:address":"Plaz Cervantes, 4",
    "sg:city":"Osuna",
    "sg:orig_category":"Abogados",
    "sg:phone":"+34 954 81 07 02",
    "sg:postcode":"41640",
    "sg:province":"Sevilla",
    "wof:name":"Lozano Vizcaino Jose",
    "wof:placetype":"venue"
},
  "geometry": {"coordinates":[-5.1067547798,37.2414474487],"type":"Point"}
}