{
  "type": "Feature",
  "properties": {
    "iso:country":"ES",
    "sg:address":"Ctra Goloso (del), Km. 0002,0",
    "sg:city":"Alcobendas",
    "sg:orig_category":"Distribuci\u00d3n De Petr\u00d3leo Y Derivados",
    "sg:phone":"+34 916 61 28 36",
    "sg:postcode":"28108",
    "sg:province":"Madrid",
    "wof:name":"Trasomonte S.l.",
    "wof:placetype":"venue"
},
  "geometry": {"coordinates":[-3.6767470837,40.5532798767],"type":"Point"}
}