{
  "type": "Feature",
  "properties": {
    "addr:full":"Rond Ponent, S/n Terrassa Barcelona 08225",
    "addr:housenumber":"s / n",
    "addr:postcode":"08225",
    "addr:street":"Rond Ponent",
    "iso:country":"ES",
    "sg:address":"Rond Ponent, S/n",
    "sg:city":"Terrassa",
    "sg:orig_category":"Ingeniero",
    "sg:phone":"+34 937 80 78 99",
    "sg:postcode":"08225",
    "sg:province":"Barcelona",
    "wof:name":"Pi\u00f1ol Peritacions S.l.",
    "wof:placetype":"venue"
},
  "geometry": {"coordinates":[2.0176799297,41.5714149475],"type":"Point"}
}