{
  "type": "Feature",
  "properties": {
    "iso:country":"ES",
    "sg:address":"Calle de Manuela Estelles, 87",
    "sg:city":"Valencia",
    "sg:orig_category":"Molduras, Junquillos, Listones Y Molduras Perforadas",
    "sg:phone":"+34 963 71 12 32",
    "sg:postcode":"46022",
    "sg:province":"Valencia",
    "wof:name":"Domingo Mateo Jose",
    "wof:placetype":"venue"
},
  "geometry": {"coordinates":[-0.334841013,39.4722061157],"type":"Point"}
}