{
  "type": "Feature",
  "properties": {
    "iso:country":"ES",
    "sg:address":"Calle de Cerveteri, 2",
    "sg:city":"Almu\u00f1ecar",
    "sg:orig_category":"Albergues",
    "sg:phone":"+34 958 63 56 54",
    "sg:postcode":"18690",
    "sg:province":"Granada",
    "wof:name":"Medina Castillo Carmen",
    "wof:placetype":"venue"
},
  "geometry": {"coordinates":[-3.6884782314,36.7329444885],"type":"Point"}
}