{
  "type": "Feature",
  "properties": {
    "addr:full":"Plaz Campillo El, 8 Huelva Huelva 21002",
    "addr:postcode":"21002",
    "iso:country":"ES",
    "sg:address":"Plaz Campillo El, 8",
    "sg:city":"Huelva",
    "sg:orig_category":"Centros Comerciales Y Grandes Tiendas",
    "sg:phone":"+34 959 24 77 27",
    "sg:postcode":"21002",
    "sg:province":"Huelva",
    "wof:name":"Musica Arte Y Sonido S.l.",
    "wof:placetype":"venue"
},
  "geometry": {"coordinates":[-6.9558358192,37.2621612549],"type":"Point"}
}