{
  "type": "Feature",
  "properties": {
    "iso:country":"ES",
    "sg:address":"Calle de Jorge Juan, 20",
    "sg:city":"Madrid",
    "sg:orig_category":"Discotecas Y Salas De Baile",
    "sg:phone":"+34 915 77 25 71",
    "sg:postcode":"28001",
    "sg:province":"Madrid",
    "wof:name":"Valdes Escalante Trinidad",
    "wof:placetype":"venue"
},
  "geometry": {"coordinates":[-3.6850399971,40.4236907959],"type":"Point"}
}