{
  "type": "Feature",
  "properties": {
    "addr:full":"Carrer de Idumea, 10 Barcelona Barcelona 08035",
    "addr:housenumber":"10",
    "addr:postcode":"08035",
    "addr:street":"Carrer De Idumea",
    "iso:country":"ES",
    "sg:address":"Carrer de Idumea, 10",
    "sg:city":"Barcelona",
    "sg:orig_category":"Mec\u00c1nico Del Autom\u00d3vil",
    "sg:phone":"+34 934 34 03 98",
    "sg:postcode":"08035",
    "sg:province":"Barcelona",
    "wof:name":"Idumea Motors S.l. Laboral",
    "wof:placetype":"venue"
},
  "geometry": {"coordinates":[2.1382119656,41.427406311],"type":"Point"}
}