{
  "type": "Feature",
  "properties": {
    "addr:full":"Rua Domingo Fontan, 2 Caeira Pontevedra 36005",
    "addr:housenumber":"2",
    "addr:postcode":"36005",
    "addr:street":"Rua Domingo Fontan",
    "iso:country":"ES",
    "sg:address":"Rua Domingo Fontan, 2",
    "sg:city":"Caeira",
    "sg:orig_category":"Lavado, Limpieza De Veh\u00cdculos",
    "sg:phone":"+34 986 87 08 35",
    "sg:postcode":"36005",
    "sg:province":"Pontevedra",
    "wof:name":"Area De Servicio A Barca S.l.",
    "wof:placetype":"venue"
},
  "geometry": {"coordinates":[-8.6480531693,42.4336204529],"type":"Point"}
}