{
  "type": "Feature",
  "properties": {
    "addr:full":"Carrer de Laurea Miro, 203 Esplugues Llobregat Barcelona 08950",
    "addr:housenumber":"203",
    "addr:postcode":"08950",
    "addr:street":"Carrer De Laurea Miro",
    "iso:country":"ES",
    "sg:address":"Carrer de Laurea Miro, 203",
    "sg:city":"Esplugues Llobregat",
    "sg:orig_category":"Molduras, Junquillos, Listones Y Molduras Perforadas",
    "sg:phone":"+34 933 71 43 62",
    "sg:postcode":"08950",
    "sg:province":"Barcelona",
    "wof:name":"Garcia Zamora Juan",
    "wof:placetype":"venue"
},
  "geometry": {"coordinates":[2.087980032,41.3772926331],"type":"Point"}
}