{
  "type": "Feature",
  "properties": {
    "addr:full":"Calle de Ca\u00d1o, S/n Numancia Sagra Toledo 45230",
    "addr:housenumber":"s",
    "addr:postcode":"45230",
    "addr:street":"Calle De Can\u0303O;/ N",
    "iso:country":"ES",
    "sg:address":"Calle de Ca\u00d1o, S/n",
    "sg:city":"Numancia Sagra",
    "sg:orig_category":"Centros De Educaci\u00d3n Especial",
    "sg:phone":"+34 925 53 72 58",
    "sg:postcode":"45230",
    "sg:province":"Toledo",
    "wof:name":"Colegio Publico Santo Cristo De La Misericordia",
    "wof:placetype":"venue"
},
  "geometry": {"coordinates":[-3.8554189205,40.0744361877],"type":"Point"}
}