{
  "type": "Feature",
  "properties": {
    "addr:full":"Calle de Lopez De Ayala, 33 Montijo Badajoz 06480",
    "addr:housenumber":"33",
    "addr:postcode":"06480",
    "addr:street":"Calle De Lopez De Ayala",
    "iso:country":"ES",
    "sg:address":"Calle de Lopez De Ayala, 33",
    "sg:city":"Montijo",
    "sg:orig_category":"Ense\u00d1anza, Formaci\u00d3n Profesional: Aprendizaje",
    "sg:phone":"+34 924 45 37 29",
    "sg:postcode":"06480",
    "sg:province":"Badajoz",
    "wof:name":"Asociacion De Empresarios De Montijo Y Comarca",
    "wof:placetype":"venue"
},
  "geometry": {"coordinates":[-6.613574028,38.9101028442],"type":"Point"}
}