{
  "type": "Feature",
  "properties": {
    "addr:full":"Carrer de Rusi\u00d1ol, 93 Pineda Mar Barcelona 08397",
    "addr:housenumber":"93",
    "addr:postcode":"08397",
    "addr:street":"Carrer De Rusin\u0303Ol;Barcelona",
    "iso:country":"ES",
    "sg:address":"Carrer de Rusi\u00d1ol, 93",
    "sg:city":"Pineda Mar",
    "sg:orig_category":"Hilaturas, Hilos Y Actividades Relacionadas",
    "sg:phone":"+34 937 62 92 40",
    "sg:postcode":"08397",
    "sg:province":"Barcelona",
    "wof:name":"Chabirtex S.l.",
    "wof:placetype":"venue"
},
  "geometry": {"coordinates":[2.6827499866,41.6266441345],"type":"Point"}
}