{
  "type": "Feature",
  "properties": {
    "iso:country":"ES",
    "sg:address":"Las Moredas, 30",
    "sg:city":"Durcal",
    "sg:orig_category":"Inmobiliaria (agencias)",
    "sg:phone":"+34 958 78 04 79",
    "sg:postcode":"18650",
    "sg:province":"Granada",
    "wof:name":"Hiberflor S.a.",
    "wof:placetype":"venue"
},
  "geometry": {"coordinates":[-3.5632860661,36.9855804443],"type":"Point"}
}