{
  "type": "Feature",
  "properties": {
    "addr:full":"Calle de Manuel Iradier, 3 Vitoria-gasteiz \u00c1lava 01005",
    "addr:housenumber":"3",
    "addr:postcode":"01005",
    "addr:street":"Calle De Manuel Iradier",
    "iso:country":"ES",
    "sg:address":"Calle de Manuel Iradier, 3",
    "sg:city":"Vitoria-gasteiz",
    "sg:orig_category":"Arquitectos",
    "sg:phone":"+34 945 23 03 30",
    "sg:postcode":"01005",
    "sg:province":"\u00c1lava",
    "wof:name":"Aspiazu Iza Ignacio Sebastian",
    "wof:placetype":"venue"
},
  "geometry": {"coordinates":[-2.6759998798,42.8426322937],"type":"Point"}
}