{
  "type": "Feature",
  "properties": {
    "addr:full":"Calle de Calvo Sotelo, 31 Tui Pontevedra 36700",
    "addr:housenumber":"31",
    "addr:postcode":"36700",
    "addr:street":"Calle De Calvo Sotelo",
    "iso:country":"ES",
    "sg:address":"Calle de Calvo Sotelo, 31",
    "sg:city":"Tui",
    "sg:orig_category":"Deportes Diversos",
    "sg:phone":"+34 986 60 08 99",
    "sg:postcode":"36700",
    "sg:province":"Pontevedra",
    "wof:name":"Tuinercia Sl",
    "wof:placetype":"venue"
},
  "geometry": {"coordinates":[-8.6435489655,42.0489311218],"type":"Point"}
}