{
  "type": "Feature",
  "properties": {
    "addr:full":"Calle de Concejo, 3 Montijo Badajoz 06480",
    "addr:housenumber":"3",
    "addr:postcode":"06480",
    "addr:street":"Calle De Concejo",
    "iso:country":"ES",
    "sg:address":"Calle de Concejo, 3",
    "sg:city":"Montijo",
    "sg:orig_category":"Sociedades, Compa\u00d1\u00cdas Aseguradoras",
    "sg:phone":"+34 924 45 21 42",
    "sg:postcode":"06480",
    "sg:province":"Badajoz",
    "wof:name":"Gonzalez Gonzalez Luis",
    "wof:placetype":"venue"
},
  "geometry": {"coordinates":[-6.6171345711,38.9087867737],"type":"Point"}
}