{
  "type": "Feature",
  "properties": {
    "iso:country":"ES",
    "sg:address":"Avda Concordia (de La), 25",
    "sg:city":"Pozo Ca\u00e7ada",
    "sg:orig_category":"Asesor\u00cda Fiscal Y Jur\u00cddica",
    "sg:phone":"+34 967 25 03 56",
    "sg:postcode":"02510",
    "sg:province":"Albacete",
    "wof:name":"Contabilidad Y Seguros Pozo Ca\u00f1ada S.l.",
    "wof:placetype":"venue"
},
  "geometry": {"coordinates":[-1.7305660248,38.8011512756],"type":"Point"}
}