{
  "type": "Feature",
  "properties": {
    "addr:full":"Calle de Manuel Garcia, 2 Coin M\u00e1laga 29100",
    "addr:housenumber":"2",
    "addr:postcode":"29100",
    "addr:street":"Calle De Manuel Garcia;Ma\u0301Laga",
    "iso:country":"ES",
    "sg:address":"Calle de Manuel Garcia, 2",
    "sg:city":"Coin",
    "sg:orig_category":"Asesor\u00cda De Formaci\u00d3n Y Gesti\u00d3n De Personal",
    "sg:phone":"+34 952 45 39 63",
    "sg:postcode":"29100",
    "sg:province":"M\u00e1laga",
    "wof:name":"Colorado Y Dominguez Asesores S.l.",
    "wof:placetype":"venue"
},
  "geometry": {"coordinates":[-4.7536020279,36.659992218],"type":"Point"}
}