{
  "type": "Feature",
  "properties": {
    "addr:full":"Calle de Cavas, 16 Calahorra La Rioja 26500",
    "addr:housenumber":"16",
    "addr:postcode":"26500",
    "addr:street":"Calle De Cavas",
    "iso:country":"ES",
    "sg:address":"Calle de Cavas, 16",
    "sg:city":"Calahorra",
    "sg:orig_category":"Institutos De Belleza",
    "sg:phone":"+34 941 14 70 42",
    "sg:postcode":"26500",
    "sg:province":"La Rioja",
    "wof:name":"Celorrio Jimenez Consuelo",
    "wof:placetype":"venue"
},
  "geometry": {"coordinates":[-1.9623895884,42.3027458191],"type":"Point"}
}