{
  "type": "Feature",
  "properties": {
    "iso:country":"ES",
    "sg:address":"Carrer de Verge De Montserrat, 8",
    "sg:city":"Sant Feliu Raco",
    "sg:orig_category":"M\u00c9dicos: Cirug\u00cda Ortop\u00c9dica Y Traumatolog\u00cda",
    "sg:phone":"+34 937 14 56 32",
    "sg:postcode":"08211",
    "sg:province":"Barcelona",
    "wof:name":"Montane Sorigue Jose Maria",
    "wof:placetype":"venue"
},
  "geometry": {"coordinates":[2.0824799538,41.6114387512],"type":"Point"}
}