{
  "type": "Feature",
  "properties": {
    "iso:country":"ES",
    "sg:address":"Calle de Fermin Palma, 1",
    "sg:city":"Jaen",
    "sg:orig_category":"Arquitectos",
    "sg:phone":"+34 953 25 49 01",
    "sg:postcode":"23008",
    "sg:province":"Ja\u00e9n",
    "wof:name":"Salmeron Mayol Andres",
    "wof:placetype":"venue"
},
  "geometry": {"coordinates":[-3.7874629498,37.7738876343],"type":"Point"}
}