{
  "type": "Feature",
  "properties": {
    "addr:full":"Rbla Generalitat, 41 S. Feliu Guixols Girona 17220",
    "addr:housenumber":"41",
    "addr:postcode":"17220",
    "addr:street":"Rbla Generalitat;S. Feliu Guixols",
    "iso:country":"ES",
    "sg:address":"Rbla Generalitat, 41",
    "sg:city":"S. Feliu Guixols",
    "sg:orig_category":"Fisioterapia",
    "sg:phone":"+34 972 82 19 33",
    "sg:postcode":"17220",
    "sg:province":"Girona",
    "wof:name":"Vendrell Turon Josep",
    "wof:placetype":"venue"
},
  "geometry": {"coordinates":[3.0378599167,41.7843742371],"type":"Point"}
}