{
  "type": "Feature",
  "properties": {
    "addr:full":"Rbla Catalunya, 17 Barcelona Barcelona 08007",
    "addr:housenumber":"17",
    "addr:postcode":"08007",
    "addr:street":"Rbla Catalunya",
    "iso:country":"ES",
    "sg:address":"Rbla Catalunya, 17",
    "sg:city":"Barcelona",
    "sg:orig_category":"Bisuter\u00cda, Joyer\u00cda, Relojer\u00cda (al Por Menor)",
    "sg:phone":"+34 933 18 20 38",
    "sg:postcode":"08007",
    "sg:province":"Barcelona",
    "sg:website":"www.unionsuiza.com",
    "wof:name":"Union Suiza S.a.",
    "wof:placetype":"venue"
},
  "geometry": {"coordinates":[2.1665220261,41.3885307312],"type":"Point"}
}