{
  "type": "Feature",
  "properties": {
    "addr:full":"Calle de Santa Maria, 20 Utiel Valencia 46300",
    "addr:housenumber":"20",
    "addr:postcode":"46300",
    "addr:street":"Calle De Santa Maria",
    "iso:country":"ES",
    "sg:address":"Calle de Santa Maria, 20",
    "sg:city":"Utiel",
    "sg:orig_category":"Ropa De Hogar (al Por Menor)",
    "sg:phone":"+34 962 17 33 18",
    "sg:postcode":"46300",
    "sg:province":"Valencia",
    "wof:name":"Herrero Perez Fausto",
    "wof:placetype":"venue"
},
  "geometry": {"coordinates":[-1.205047965,39.5678138733],"type":"Point"}
}