{
  "type": "Feature",
  "properties": {
    "addr:full":"Crta. Trespaderne-puentelarra, 3 Quintana Martin Galindez Burgos 09210",
    "addr:housenumber":"3",
    "addr:postcode":"09210",
    "addr:street":"Crta. Trespaderne-Puentelarra",
    "iso:country":"ES",
    "sg:address":"Crta. Trespaderne-puentelarra, 3",
    "sg:city":"Quintana Martin Galindez",
    "sg:orig_category":"Distribuci\u00d3n De Petr\u00d3leo Y Derivados",
    "sg:phone":"+34 947 35 87 07",
    "sg:postcode":"09210",
    "sg:province":"Burgos",
    "wof:name":"Hijos De Juan Gonzalez S.l.",
    "wof:placetype":"venue"
},
  "geometry": {"coordinates":[-3.278208971,42.7991638184],"type":"Point"}
}