{
  "type": "Feature",
  "properties": {
    "addr:full":"Urune, 12 Lezo Guip\u00f9zcoa 20100",
    "addr:housenumber":"12",
    "addr:postcode":"20100",
    "addr:street":"Urune;Guipu\u0300Zcoa",
    "iso:country":"ES",
    "sg:address":"Urune, 12",
    "sg:city":"Lezo",
    "sg:orig_category":"Maquinaria Neum\u00c1tica",
    "sg:phone":"+34 943 52 46 49",
    "sg:postcode":"20100",
    "sg:province":"Guip\u00f9zcoa",
    "wof:name":"Trebeak S.l.",
    "wof:placetype":"venue"
},
  "geometry": {"coordinates":[-1.8776099682,43.3254547119],"type":"Point"}
}