{
  "type": "Feature",
  "properties": {
    "addr:full":"Carrer de Maladeta, 4 Sabadell Barcelona 08207",
    "addr:housenumber":"4",
    "addr:postcode":"08207",
    "addr:street":"Carrer De Maladeta",
    "iso:country":"ES",
    "sg:address":"Carrer de Maladeta, 4",
    "sg:city":"Sabadell",
    "sg:orig_category":"Institutos De Belleza",
    "sg:phone":"+34 937 24 21 67",
    "sg:postcode":"08207",
    "sg:province":"Barcelona",
    "wof:name":"Martinez Miralles Maria Piedad",
    "wof:placetype":"venue"
},
  "geometry": {"coordinates":[2.0889120102,41.5678672791],"type":"Point"}
}