{
  "type": "Feature",
  "properties": {
    "iso:country":"ES",
    "sg:address":"Ilicitano Ausente, 10",
    "sg:city":"Elche",
    "sg:orig_category":"Alimentaci\u00d3n General (al Por Menor)",
    "sg:phone":"+34 965 42 92 36",
    "sg:postcode":"03202",
    "sg:province":"Alicante",
    "wof:name":"Asadero Cocinados Y Pizzas La Casona S.l.",
    "wof:placetype":"venue"
},
  "geometry": {"coordinates":[-0.6488505006,38.3253250122],"type":"Point"}
}