{
  "type": "Feature",
  "properties": {
    "iso:country":"ES",
    "sg:address":"Calle de Jerusalen, 24",
    "sg:city":"Parla",
    "sg:orig_category":"Inmobiliaria (agencias)",
    "sg:phone":"+34 916 64 40 59",
    "sg:postcode":"28980",
    "sg:province":"Madrid",
    "wof:name":"Vazquez Martin Angel Manuel",
    "wof:placetype":"venue"
},
  "geometry": {"coordinates":[-3.7761538029,40.2373428345],"type":"Point"}
}