{
  "type": "Feature",
  "properties": {
    "addr:full":"Calvario, 70 Espinardo Murcia 30100",
    "addr:housenumber":"70",
    "addr:postcode":"30100",
    "addr:street":"Calvario",
    "iso:country":"ES",
    "sg:address":"Calvario, 70",
    "sg:city":"Espinardo",
    "sg:orig_category":"Agencias Y Agentes Comerciales, Representantes",
    "sg:phone":"+34 968 83 01 21",
    "sg:postcode":"30100",
    "sg:province":"Murcia",
    "wof:name":"Nicolas Garcia Antonio",
    "wof:placetype":"venue"
},
  "geometry": {"coordinates":[-1.1566179991,38.0090866089],"type":"Point"}
}