{
  "type": "Feature",
  "properties": {
    "iso:country":"ES",
    "sg:address":"Calle de Ruamayor, 4",
    "sg:city":"Santander",
    "sg:orig_category":"Procuradores",
    "sg:phone":"+34 942 21 17 82",
    "sg:postcode":"39008",
    "sg:province":"Cantabria",
    "wof:name":"Gonzalez Morales Juan Antonio",
    "wof:placetype":"venue"
},
  "geometry": {"coordinates":[-3.8097829819,43.4611434937],"type":"Point"}
}