{
  "type": "Feature",
  "properties": {
    "iso:country":"ES",
    "sg:address":"Avda Barcelona (de), 12",
    "sg:city":"Cordoba",
    "sg:orig_category":"Bazares, Art\u00cdculos De Limpieza Y De Cocina (al Por Menor)",
    "sg:phone":"+34 957 44 00 57",
    "sg:postcode":"14010",
    "sg:province":"C\u00f3rdoba",
    "wof:name":"Tamrani  Maati",
    "wof:placetype":"venue"
},
  "geometry": {"coordinates":[-4.7645711899,37.8889274597],"type":"Point"}
}