{
  "type": "Feature",
  "properties": {
    "addr:full":"Grup Villegas, S/n Sevilla Sevilla 41008",
    "addr:housenumber":"s / n",
    "addr:postcode":"41008",
    "addr:street":"Villegas",
    "iso:country":"ES",
    "sg:address":"Grup Villegas, S/n",
    "sg:city":"Sevilla",
    "sg:orig_category":"Transportes Por Carretera: Lotes Completos, Mercanc\u00cdas Diversas",
    "sg:phone":"+34 954 35 45 13",
    "sg:postcode":"41008",
    "sg:province":"Sevilla",
    "wof:name":"Garcia Matas Feliciano",
    "wof:placetype":"venue"
},
  "geometry": {"coordinates":[-5.992623806,37.3897209167],"type":"Point"}
}