{
  "type": "Feature",
  "properties": {
    "iso:country":"ES",
    "sg:address":"Carr Doctor Julio Sanchez Juan, 4",
    "sg:city":"Olleria",
    "sg:orig_category":"Torneros Sobre Madera",
    "sg:phone":"+34 962 20 23 49",
    "sg:postcode":"46850",
    "sg:province":"Valencia",
    "wof:name":"Inmader L'olleria S.l.",
    "wof:placetype":"venue"
},
  "geometry": {"coordinates":[-0.5585477948,38.9163856506],"type":"Point"}
}