{
  "type": "Feature",
  "properties": {
    "iso:country":"ES",
    "sg:address":"Barr Vinueva, S/n",
    "sg:city":"Quijas",
    "sg:orig_category":"Electricidad Veh\u00cdculo",
    "sg:phone":"+34 942 82 06 31",
    "sg:postcode":"39590",
    "sg:province":"Cantabria",
    "wof:name":"Auto-electricidad Luis Gonzalez S.l.",
    "wof:placetype":"venue"
},
  "geometry": {"coordinates":[-4.1317028999,43.3504219055],"type":"Point"}
}