{
  "type": "Feature",
  "properties": {
    "iso:country":"ES",
    "sg:address":"Avda Naciones, 78",
    "sg:city":"Ciudad Quesada",
    "sg:orig_category":"Inversiones",
    "sg:phone":"+34 965 72 55 99",
    "sg:postcode":"03170",
    "sg:province":"Alicante",
    "wof:name":"Medved  Leonid",
    "wof:placetype":"venue"
},
  "geometry": {"coordinates":[-0.7209050059,38.0634765625],"type":"Point"}
}