{
  "type": "Feature",
  "properties": {
    "iso:country":"ES",
    "sg:address":"Avda Paris, 3",
    "sg:city":"Caceres",
    "sg:orig_category":"Administradores De Bienes Y Delegados De Comunidades De Propietarios",
    "sg:phone":"+34 927 62 96 05",
    "sg:postcode":"10005",
    "sg:province":"C\u00e1ceres",
    "wof:name":"Administracion De Fincas Casares S.l.",
    "wof:placetype":"venue"
},
  "geometry": {"coordinates":[-6.3862690926,39.4681282043],"type":"Point"}
}