{
  "type": "Feature",
  "properties": {
    "iso:country":"ES",
    "sg:address":"Carrer de Diputacio, 238",
    "sg:city":"Barcelona",
    "sg:orig_category":"Ingenier\u00cda, Centros De Estudios (diversos)",
    "sg:phone":"+34 932 70 13 71",
    "sg:postcode":"08007",
    "sg:province":"Barcelona",
    "wof:name":"Amatria Ingenieria, S.l.",
    "wof:placetype":"venue"
},
  "geometry": {"coordinates":[2.1646978855,41.3886146545],"type":"Point"}
}