{
  "type": "Feature",
  "properties": {
    "addr:full":"Calle de Angel Lozano, 3 Alacant Alicante 03001",
    "addr:housenumber":"3",
    "addr:postcode":"03001",
    "addr:street":"Calle De Angel Lozano",
    "iso:country":"ES",
    "sg:address":"Calle de Angel Lozano, 3",
    "sg:city":"Alacant",
    "sg:orig_category":"Molduras, Junquillos, Listones Y Molduras Perforadas",
    "sg:phone":"+34 965 21 25 16",
    "sg:postcode":"03001",
    "sg:province":"Alicante",
    "wof:name":"Eurotel Sur S L",
    "wof:placetype":"venue"
},
  "geometry": {"coordinates":[-0.4881899953,38.3453292847],"type":"Point"}
}