{
  "type": "Feature",
  "properties": {
    "addr:full":"Carr Ulla, 21 Torroella Montgri Girona 17257",
    "addr:housenumber":"21",
    "addr:postcode":"17257",
    "addr:street":"Carr Ulla",
    "iso:country":"ES",
    "sg:address":"Carr Ulla, 21",
    "sg:city":"Torroella Montgri",
    "sg:orig_category":"Molduras, Junquillos, Listones Y Molduras Perforadas",
    "sg:phone":"+34 972 75 75 12",
    "sg:postcode":"17257",
    "sg:province":"Girona",
    "wof:name":"Cafe Patmon S.c",
    "wof:placetype":"venue"
},
  "geometry": {"coordinates":[3.1277420521,42.042766571],"type":"Point"}
}