{
  "type": "Feature",
  "properties": {
    "iso:country":"ES",
    "sg:address":"Avda Gaspar Garcia Laviana, 8",
    "sg:city":"Gijon",
    "sg:orig_category":"Institutos De Belleza",
    "sg:phone":"+34 985 15 25 32",
    "sg:postcode":"33210",
    "sg:province":"Asturias",
    "wof:name":"Lopez Perez Maria Dolores",
    "wof:placetype":"venue"
},
  "geometry": {"coordinates":[-5.6675477028,43.5258178711],"type":"Point"}
}