{
  "type": "Feature",
  "properties": {
    "addr:full":"Carrer de Doctor Joaquim Masmitja, 17 Olot Girona 17800",
    "addr:housenumber":"17",
    "addr:postcode":"17800",
    "addr:street":"Carrer De Doctor Joaquim Masmitja",
    "iso:country":"ES",
    "sg:address":"Carrer de Doctor Joaquim Masmitja, 17",
    "sg:city":"Olot",
    "sg:orig_category":"Peluquer\u00cdas, Peluquer\u00cda Mixta",
    "sg:phone":"+34 972 26 22 67",
    "sg:postcode":"17800",
    "sg:province":"Girona",
    "wof:name":"Ruiz Ramirez Amelia",
    "wof:placetype":"venue"
},
  "geometry": {"coordinates":[2.4879970551,42.1847038269],"type":"Point"}
}