{
  "type": "Feature",
  "properties": {
    "iso:country":"ES",
    "sg:address":"Calle de Laguna, 99",
    "sg:city":"Madrid",
    "sg:orig_category":"Art\u00cdculos De Regalo (al Por Menor)",
    "sg:phone":"+34 914 61 05 51",
    "sg:postcode":"28025",
    "sg:province":"Madrid",
    "wof:name":"Garcia Balcones Carlos",
    "wof:placetype":"venue"
},
  "geometry": {"coordinates":[-3.7420349121,40.3902397156],"type":"Point"}
}