{
  "type": "Feature",
  "properties": {
    "addr:full":"Avda Nuestra Se\u00d1ora De La Soledad, 81 Cantillana Sevilla 41320",
    "addr:housenumber":"81",
    "addr:postcode":"41320",
    "addr:street":"Avda Nuestra Sen\u0303Ora De La Soledad",
    "iso:country":"ES",
    "sg:address":"Avda Nuestra Se\u00d1ora De La Soledad, 81",
    "sg:city":"Cantillana",
    "sg:orig_category":"Negocio De Materiales De Construcci\u00d3n",
    "sg:phone":"+34 955 73 16 74",
    "sg:postcode":"41320",
    "sg:province":"Sevilla",
    "wof:name":"Materiales De Construccion Hermanos Duran S.l.",
    "wof:placetype":"venue"
},
  "geometry": {"coordinates":[-5.8226351738,37.6121139526],"type":"Point"}
}