{
  "type": "Feature",
  "properties": {
    "addr:full":"Ctra Rubi, Km. 0000,1 Mira-sol Barcelona 08173",
    "addr:postcode":"08173",
    "addr:street":"Ctra Rubi Km. 0000,1",
    "iso:country":"ES",
    "sg:address":"Ctra Rubi, Km. 0000,1",
    "sg:city":"Mira-sol",
    "sg:orig_category":"Art\u00cdculos De Limpieza Y De Cocina (fabricaci\u00d3n, Al Por Mayor)",
    "sg:phone":"+34 935 90 11 78",
    "sg:postcode":"08173",
    "sg:province":"Barcelona",
    "wof:name":"Velox Trading S.l.",
    "wof:placetype":"venue"
},
  "geometry": {"coordinates":[2.0622999668,41.4687690735],"type":"Point"}
}