{
  "type": "Feature",
  "properties": {
    "iso:country":"ES",
    "sg:address":"Cno. Angel, S/n",
    "sg:city":"Nueva Andalucia",
    "sg:orig_category":"Promotores Constructores",
    "sg:phone":"+34 952 81 08 70",
    "sg:postcode":"29660",
    "sg:province":"M\u00e1laga",
    "sg:website":"www.alzambra.com",
    "wof:name":"Eurobuildings S.l.",
    "wof:placetype":"venue"
},
  "geometry": {"coordinates":[-4.9590201378,36.5124473572],"type":"Point"}
}