{
  "type": "Feature",
  "properties": {
    "iso:country":"ES",
    "sg:address":"Calle de Calatrava, 7",
    "sg:city":"Madrid",
    "sg:orig_category":"Alimentaci\u00d3n General (al Por Menor)",
    "sg:phone":"+34 913 66 26 92",
    "sg:postcode":"28005",
    "sg:province":"Madrid",
    "wof:name":"Guo  Suhua",
    "wof:placetype":"venue"
},
  "geometry": {"coordinates":[-3.7107810974,40.4091911316],"type":"Point"}
}