{
  "type": "Feature",
  "properties": {
    "iso:country":"ES",
    "sg:address":"Calle de Antonio Concha, 23",
    "sg:city":"Navalmoral Mata",
    "sg:orig_category":"Fabricaci\u00d3n De Sobres, Bolsas Y Fundas",
    "sg:phone":"+34 927 53 81 25",
    "sg:postcode":"10300",
    "sg:province":"C\u00e1ceres",
    "wof:name":"La Casa De Los Bolsos Extreme\u00d1os S.l.",
    "wof:placetype":"venue"
},
  "geometry": {"coordinates":[-5.5394945145,39.8910560608],"type":"Point"}
}