{
  "type": "Feature",
  "properties": {
    "addr:full":"Avda. De San Vicente, 2 Benalmadena-costa M\u00e1laga 29630",
    "addr:housenumber":"2",
    "addr:postcode":"29630",
    "addr:street":"Avda. De San Vicente;Ma\u0301Laga",
    "iso:country":"ES",
    "sg:address":"Avda. De San Vicente, 2",
    "sg:city":"Benalmadena-costa",
    "sg:orig_category":"Supermercados Y Hipermercados",
    "sg:phone":"+34 952 56 23 87",
    "sg:postcode":"29630",
    "sg:province":"M\u00e1laga",
    "wof:name":"Dinosol Supermercados S.l.",
    "wof:placetype":"venue"
},
  "geometry": {"coordinates":[-4.521381855,36.5971374512],"type":"Point"}
}