{
  "type": "Feature",
  "properties": {
    "addr:full":"Calle de Pelicano, 8 Valladolid Valladolid 47012",
    "addr:housenumber":"8",
    "addr:postcode":"47012",
    "addr:street":"Calle De Pelicano",
    "iso:country":"ES",
    "sg:address":"Calle de Pelicano, 8",
    "sg:city":"Valladolid",
    "sg:orig_category":"Molduras, Junquillos, Listones Y Molduras Perforadas",
    "sg:phone":"+34 983 29 24 42",
    "sg:postcode":"47012",
    "sg:province":"Valladolid",
    "wof:name":"Rodriguez Mazariego Eusebio",
    "wof:placetype":"venue"
},
  "geometry": {"coordinates":[-4.709564209,41.6466407776],"type":"Point"}
}