{
  "type": "Feature",
  "properties": {
    "iso:country":"ES",
    "sg:address":"Calle de Hernan Cortes, 15",
    "sg:city":"Linares",
    "sg:orig_category":"Electricidad, Electr\u00d3nica: Material Y Suministros (al Por Mayor)",
    "sg:phone":"+34 953 60 15 05",
    "sg:postcode":"23700",
    "sg:province":"Ja\u00e9n",
    "wof:name":"Briones Medina Diego",
    "wof:placetype":"venue"
},
  "geometry": {"coordinates":[-3.6351120472,38.0984764099],"type":"Point"}
}