{
  "type": "Feature",
  "properties": {
    "addr:full":"Carr Retiro, 1 Cullera Valencia 46400",
    "addr:housenumber":"1",
    "addr:postcode":"46400",
    "addr:street":"Carr Retiro",
    "iso:country":"ES",
    "sg:address":"Carr Retiro, 1",
    "sg:city":"Cullera",
    "sg:orig_category":"Agentes Generales De Seguros",
    "sg:phone":"+34 961 72 67 04",
    "sg:postcode":"46400",
    "sg:province":"Valencia",
    "wof:name":"Intec 2000 S.l.",
    "wof:placetype":"venue"
},
  "geometry": {"coordinates":[-0.2567149997,39.1664962769],"type":"Point"}
}