{
  "type": "Feature",
  "properties": {
    "iso:country":"ES",
    "sg:address":"Rua Santa Catalina, 16",
    "sg:city":"Amoeiro",
    "sg:orig_category":"Cristaler\u00cda: Suministros",
    "sg:phone":"+34 988 28 10 65",
    "sg:postcode":"32170",
    "sg:province":"Ourense",
    "sg:website":"www.cristaleriapaco.com",
    "wof:name":"Almacenes Y Cristaleria Paco S. L.",
    "wof:placetype":"venue"
},
  "geometry": {"coordinates":[-7.9480538368,42.4176826477],"type":"Point"}
}