{
  "type": "Feature",
  "properties": {
    "iso:country":"ES",
    "sg:address":"Alfonso El Batallador, 2",
    "sg:city":"Iru\u00f1a",
    "sg:orig_category":"Arquitectos",
    "sg:phone":"+34 948 27 93 04",
    "sg:postcode":"31007",
    "sg:province":"Navarra",
    "wof:name":"Busto Barcos Jesus",
    "wof:placetype":"venue"
},
  "geometry": {"coordinates":[-1.6492819786,42.8029060364],"type":"Point"}
}