{
  "type": "Feature",
  "properties": {
    "addr:full":"Calle de Sigfrido, 4 Malaga M\u00e1laga 29006",
    "addr:housenumber":"4",
    "addr:postcode":"29006",
    "addr:street":"Calle De Sigfrido;Ma\u0301Laga",
    "iso:country":"ES",
    "sg:address":"Calle de Sigfrido, 4",
    "sg:city":"Malaga",
    "sg:orig_category":"Prendas Deportivas (fabricaci\u00d3n)",
    "sg:phone":"+34 952 36 10 51",
    "sg:postcode":"29006",
    "sg:province":"M\u00e1laga",
    "wof:name":"Generos De Punto Estycor S.l.",
    "wof:placetype":"venue"
},
  "geometry": {"coordinates":[-4.4690752029,36.7069702148],"type":"Point"}
}