{
  "type": "Feature",
  "properties": {
    "addr:full":"Calle de Aldapa, 2 Mutiloagoiti Navarra 31192",
    "addr:housenumber":"2",
    "addr:postcode":"31192",
    "addr:street":"Calle De Aldapa",
    "iso:country":"ES",
    "sg:address":"Calle de Aldapa, 2",
    "sg:city":"Mutiloagoiti",
    "sg:orig_category":"Iglesia Cat\u00d3lica",
    "sg:phone":"+34 948 23 74 67",
    "sg:postcode":"31192",
    "sg:province":"Navarra",
    "wof:name":"Parroquia De San Saturnino",
    "wof:placetype":"venue"
},
  "geometry": {"coordinates":[-1.6189903021,42.8008880615],"type":"Point"}
}