{
  "type": "Feature",
  "properties": {
    "iso:country":"ES",
    "sg:address":"Calle de Licenciado Bellogin, 2",
    "sg:city":"Valladolid",
    "sg:orig_category":"Transportes Por V\u00cdas Navegables",
    "sg:phone":"+34 983 47 67 12",
    "sg:postcode":"47008",
    "sg:province":"Valladolid",
    "wof:name":"Villafa\u00f1ez Ruiz Juan Carlos",
    "wof:placetype":"venue"
},
  "geometry": {"coordinates":[-4.7412958145,41.6238670349],"type":"Point"}
}