{
  "type": "Feature",
  "properties": {
    "iso:country":"ES",
    "sg:address":"Calle de Eduardo Dato, 7",
    "sg:city":"Constantina",
    "sg:orig_category":"Centros P\u00dablicos De Formaci\u00d3n Profesional Y T\u00c9cnica",
    "sg:phone":"+34 955 88 38 90",
    "sg:postcode":"41450",
    "sg:province":"Sevilla",
    "wof:name":"Colegio Oficial De Aparejadores Y Arquitectos Tecnicos De Sevilla",
    "wof:placetype":"venue"
},
  "geometry": {"coordinates":[-5.619161129,37.8724822998],"type":"Point"}
}