{
  "type": "Feature",
  "properties": {
    "iso:country":"ES",
    "sg:address":"Carrer de Watt, 117",
    "sg:city":"Terrassa",
    "sg:orig_category":"Molduras, Junquillos, Listones Y Molduras Perforadas",
    "sg:phone":"+34 937 88 10 53",
    "sg:postcode":"08224",
    "sg:province":"Barcelona",
    "wof:name":"Lozano Male Pilar",
    "wof:placetype":"venue"
},
  "geometry": {"coordinates":[2.0014629364,41.5566368103],"type":"Point"}
}