{
  "type": "Feature",
  "properties": {
    "iso:country":"ES",
    "sg:address":"Avda Santa Marina, 13",
    "sg:city":"Badajoz",
    "sg:orig_category":"Doctores En Medicina",
    "sg:phone":"+34 924 23 16 48",
    "sg:postcode":"06005",
    "sg:province":"Badajoz",
    "wof:name":"Mu\u00f1oz Bayon Alberto",
    "wof:placetype":"venue"
},
  "geometry": {"coordinates":[-6.9770407677,38.8740005493],"type":"Point"}
}