{
  "type": "Feature",
  "properties": {
    "iso:country":"ES",
    "sg:address":"Calle de Constantino, 6",
    "sg:city":"Palmas De Gran Canaria",
    "sg:orig_category":"Comercio De Piezas De Recambio Y De Accesorios De Veh\u00cdculos, Veh\u00cdculos Industriales",
    "sg:phone":"+34 928 36 33 73",
    "sg:postcode":"35002",
    "sg:province":"Las Palmas",
    "wof:name":"Cabrera Lopez Juan Alonso",
    "wof:placetype":"venue"
},
  "geometry": {"coordinates":[-15.4169359207,28.1058254242],"type":"Point"}
}