{
  "type": "Feature",
  "properties": {
    "iso:country":"ES",
    "sg:address":"Barr Lega\u00d1o, 2",
    "sg:city":"Berriz-olakueta",
    "sg:classifiers":[
        {
            "category":"Autos & Motor Vehicles",
            "subcategory":"Automobile Sales",
            "type":"Retail Goods"
        }
    ],
    "sg:phone":"+34 946 82 42 29",
    "sg:postcode":"48240",
    "sg:province":"Vizcaya",
    "wof:name":"Echevarria Arriaga Ignacio",
    "wof:placetype":"venue"
},
  "geometry": {"coordinates":[-2.5762600899,43.1714019775],"type":"Point"}
}