{
  "type": "Feature",
  "properties": {
    "addr:full":"Calle de Vital Aza, 48 Madrid Madrid 28017",
    "addr:housenumber":"48",
    "addr:postcode":"madrid;28017",
    "addr:street":"Calle De Vital Aza",
    "iso:country":"ES",
    "sg:address":"Calle de Vital Aza, 48",
    "sg:city":"Madrid",
    "sg:orig_category":"Sociedades, Compa\u00d1\u00cdas Aseguradoras",
    "sg:phone":"+34 914 08 14 11",
    "sg:postcode":"28017",
    "sg:province":"Madrid",
    "wof:name":"Gestion Y Servicios Romes S.l.",
    "wof:placetype":"venue"
},
  "geometry": {"coordinates":[-3.6406428814,40.4324073792],"type":"Point"}
}