{
  "type": "Feature",
  "properties": {
    "iso:country":"ES",
    "sg:address":"Calle de Poeta Alonso De Bonilla, S/n",
    "sg:city":"Cordoba",
    "sg:orig_category":"Ingenier\u00cda, Centros De Estudios (diversos)",
    "sg:phone":"+34 957 40 20 02",
    "sg:postcode":"14012",
    "sg:province":"C\u00f3rdoba",
    "wof:name":"Lovera Sanchez De Puerta Juan",
    "wof:placetype":"venue"
},
  "geometry": {"coordinates":[-4.8027071953,37.9161453247],"type":"Point"}
}