{
  "type": "Feature",
  "properties": {
    "iso:country":"ES",
    "sg:address":"Calle de Doctor Adelardo Mora, 12",
    "sg:city":"Granada",
    "sg:orig_category":"Abogados",
    "sg:phone":"+34 958 27 19 95",
    "sg:postcode":"18012",
    "sg:province":"Granada",
    "wof:name":"Ruiz Fernandez Jose Angel",
    "wof:placetype":"venue"
},
  "geometry": {"coordinates":[-3.6090316772,37.1875152588],"type":"Point"}
}