{
  "type": "Feature",
  "properties": {
    "iso:country":"ES",
    "sg:address":"Av Pelegrina (la), 102",
    "sg:city":"Vilafranca Penedes",
    "sg:orig_category":"Oficinas: Suministros Para (fabricaci\u00d3n, Al Por Mayor)",
    "sg:phone":"+34 938 92 30 11",
    "sg:postcode":"08720",
    "sg:province":"Barcelona",
    "wof:name":"Sistemas De Oficina Del Penedes S.a.",
    "wof:placetype":"venue"
},
  "geometry": {"coordinates":[1.710801959,41.3503952026],"type":"Point"}
}