{
  "type": "Feature",
  "properties": {
    "iso:country":"ES",
    "sg:address":"Cra. Carme-santa Maria De Miralles, Km. 0010,4",
    "sg:city":"Orpi",
    "sg:orig_category":"Aguas (distribuci\u00d3n, Servicios)",
    "sg:phone":"+34 937 44 60 60",
    "sg:postcode":"08787",
    "sg:province":"Barcelona",
    "wof:name":"Font D'abaix S.l.",
    "wof:placetype":"venue"
},
  "geometry": {"coordinates":[1.5248030424,41.5180282593],"type":"Point"}
}