{
  "type": "Feature",
  "properties": {
    "addr:full":"Pase Acacias, S/n Madrid Madrid 28005",
    "addr:housenumber":"s / n",
    "addr:postcode":"28005",
    "addr:street":"Acacias",
    "iso:country":"ES",
    "sg:address":"Pase Acacias, S/n",
    "sg:city":"Madrid",
    "sg:orig_category":"Librer\u00cdas",
    "sg:phone":"+34 914 74 88 65",
    "sg:postcode":"28005",
    "sg:province":"Madrid",
    "wof:name":"Cerro Doblado Jose Luis Del",
    "wof:placetype":"venue"
},
  "geometry": {"coordinates":[-3.7043089867,40.4045562744],"type":"Point"}
}