{
  "type": "Feature",
  "properties": {
    "iso:country":"ES",
    "sg:address":"Cmno San Lazaro, S/n",
    "sg:city":"San Lazaro",
    "sg:orig_category":"Ense\u00d1anza, Formaci\u00d3n Profesional: Aprendizaje",
    "sg:phone":"+34 922 25 32 36",
    "sg:postcode":"38206",
    "sg:province":"Santa Cruz De Tenerife",
    "wof:name":"Consorcio De Prevencion Extincion De Incendios Y Salvamento De La Isla De Tenerife",
    "wof:placetype":"venue"
},
  "geometry": {"coordinates":[-16.3254089355,28.4842090607],"type":"Point"}
}