{
  "type": "Feature",
  "properties": {
    "addr:full":"Avda Habana (de La), 42 Ourense Ourense 32004",
    "addr:housenumber":"42",
    "addr:postcode":"32004",
    "addr:street":"Avda Habana De La",
    "iso:country":"ES",
    "sg:address":"Avda Habana (de La), 42",
    "sg:city":"Ourense",
    "sg:orig_category":"Dietistas",
    "sg:phone":"+34 988 22 92 36",
    "sg:postcode":"32004",
    "sg:province":"Ourense",
    "wof:name":"Housediet S.l. Sociedad Unipersonal",
    "wof:placetype":"venue"
},
  "geometry": {"coordinates":[-7.8596291542,42.3408889771],"type":"Point"}
}