{
  "type": "Feature",
  "properties": {
    "addr:full":"Ctra General Mao - Ciutadella, Km. 0042,2 Tudons Islas Baleares 07760",
    "addr:postcode":"07760",
    "addr:street":"Ctra General Mao Ciutadella Km. 0042,2 Tudons",
    "iso:country":"ES",
    "sg:address":"Ctra General Mao - Ciutadella, Km. 0042,2",
    "sg:city":"Tudons",
    "sg:orig_category":"Cueros Y Pieles (al Por Mayor)",
    "sg:phone":"+34 971 38 03 54",
    "sg:postcode":"07760",
    "sg:province":"Islas Baleares",
    "sg:website":"www.munper.com",
    "wof:name":"Pells Del Pla S.l.",
    "wof:placetype":"venue"
},
  "geometry": {"coordinates":[3.8382499218,39.9930915833],"type":"Point"}
}