{
  "type": "Feature",
  "properties": {
    "addr:full":"Carrer de Narcis Monturiol (de), 23 Vilassar De Mar Barcelona 08340",
    "addr:housenumber":"23",
    "addr:postcode":"08340",
    "addr:street":"Carrer De Narcis Monturiol De",
    "iso:country":"ES",
    "sg:address":"Carrer de Narcis Monturiol (de), 23",
    "sg:city":"Vilassar De Mar",
    "sg:orig_category":"Clases De M\u00dasica Y Canto",
    "sg:phone":"+34 937 50 64 75",
    "sg:postcode":"08340",
    "sg:province":"Barcelona",
    "wof:name":"Associacio Aula De Musica De Vilassar De",
    "wof:placetype":"venue"
},
  "geometry": {"coordinates":[2.3518257141,41.4912414551],"type":"Point"}
}