{
  "type": "Feature",
  "properties": {
    "addr:full":"Ctra Muel, 49 Epila Zaragoza 50290",
    "addr:housenumber":"49",
    "addr:postcode":"50290",
    "addr:street":"Ctra Muel",
    "iso:country":"ES",
    "sg:address":"Ctra Muel, 49",
    "sg:city":"Epila",
    "sg:orig_category":"Agentes, Concesionarios Y Sucursales De Veh\u00cdculos",
    "sg:phone":"+34 976 60 34 03",
    "sg:postcode":"50290",
    "sg:province":"Zaragoza",
    "wof:name":"Garcia Filera Octavio",
    "wof:placetype":"venue"
},
  "geometry": {"coordinates":[-1.2849140167,41.6030502319],"type":"Point"}
}