{
  "type": "Feature",
  "properties": {
    "iso:country":"ES",
    "sg:address":"Av Josep M Marcet, 23",
    "sg:city":"Cerdanyola Valles",
    "sg:orig_category":"Asesor\u00cda, Estudio Y Control Medioambiental",
    "sg:phone":"+34 935 89 31 32",
    "sg:postcode":"08193",
    "sg:province":"Barcelona",
    "wof:name":"Expografic S.a.",
    "wof:placetype":"venue"
},
  "geometry": {"coordinates":[2.0911829472,41.50182724],"type":"Point"}
}