{
  "type": "Feature",
  "properties": {
    "addr:full":"Carrer de Sardenya, 75 Barcelona Barcelona 08018",
    "addr:housenumber":"75",
    "addr:postcode":"08018",
    "addr:street":"Carrer De Sardenya",
    "iso:country":"ES",
    "sg:address":"Carrer de Sardenya, 75",
    "sg:city":"Barcelona",
    "sg:orig_category":"Librer\u00cdas",
    "sg:phone":"+34 934 85 44 36",
    "sg:postcode":"08018",
    "sg:province":"Barcelona",
    "wof:name":"Les Punxes Distribuidora S.l.",
    "wof:placetype":"venue"
},
  "geometry": {"coordinates":[2.1866660118,41.3932647705],"type":"Point"}
}