{
  "type": "Feature",
  "properties": {
    "addr:full":"Carr Punta (la), 102 Sueca Valencia 46410",
    "addr:housenumber":"102",
    "addr:postcode":"46410",
    "addr:street":"Carr Punta La",
    "iso:country":"ES",
    "sg:address":"Carr Punta (la), 102",
    "sg:city":"Sueca",
    "sg:orig_category":"Bisuter\u00cda, Joyer\u00cda, Relojer\u00cda (al Por Menor)",
    "sg:phone":"+34 961 70 38 33",
    "sg:postcode":"46410",
    "sg:province":"Valencia",
    "wof:name":"Sanchis Serrano Maria Del Carmen",
    "wof:placetype":"venue"
},
  "geometry": {"coordinates":[-0.3080050051,39.2045860291],"type":"Point"}
}