{
  "type": "Feature",
  "properties": {
    "iso:country":"ES",
    "sg:address":"Calle de Arzobispo Loaces, 17",
    "sg:city":"Alacant",
    "sg:orig_category":"Supermercados Y Hipermercados",
    "sg:phone":"+34 965 22 88 74",
    "sg:postcode":"03003",
    "sg:province":"Alicante",
    "wof:name":"Consum Sociedad Cooperativa Limitada",
    "wof:placetype":"venue"
},
  "geometry": {"coordinates":[-0.4898914993,38.3403701782],"type":"Point"}
}