{
  "type": "Feature",
  "properties": {
    "iso:country":"ES",
    "sg:address":"Carrer de Jaume I, 7",
    "sg:city":"Manresa",
    "sg:orig_category":"Supermercados Y Hipermercados",
    "sg:phone":"+34 938 72 17 52",
    "sg:postcode":"08241",
    "sg:province":"Barcelona",
    "wof:name":"Supermercados Llobet S.a.",
    "wof:placetype":"venue"
},
  "geometry": {"coordinates":[1.8232300282,41.724811554],"type":"Point"}
}