{
  "type": "Feature",
  "properties": {
    "addr:full":"Plaz Republica Dominicana, 1 Madrid Madrid 28016",
    "addr:housenumber":"1",
    "addr:postcode":"28016",
    "addr:street":"Dominicana",
    "iso:country":"ES",
    "sg:address":"Plaz Republica Dominicana, 1",
    "sg:city":"Madrid",
    "sg:orig_category":"Organismos De Turismo",
    "sg:phone":"+34 914 57 61 06",
    "sg:postcode":"28016",
    "sg:province":"Madrid",
    "wof:name":"Empresas Turisticas S.a.",
    "wof:placetype":"venue"
},
  "geometry": {"coordinates":[-3.6769380569,40.4583435059],"type":"Point"}
}