{
  "type": "Feature",
  "properties": {
    "iso:country":"ES",
    "sg:address":"Carr Sta Caterina, 31",
    "sg:city":"Igualada",
    "sg:orig_category":"Fabricaci\u00d3n De Su\u00c9ters Y Chalecos De Punto",
    "sg:phone":"+34 938 04 94 32",
    "sg:postcode":"08700",
    "sg:province":"Barcelona",
    "wof:name":"Balcells Llenas Juan",
    "wof:placetype":"venue"
},
  "geometry": {"coordinates":[1.6154197454,41.5811767578],"type":"Point"}
}