{
  "type": "Feature",
  "properties": {
    "addr:full":"Carrer de Paisos Catalans, 16 S. Just Desvern Barcelona 08960",
    "addr:housenumber":"16",
    "addr:postcode":"08960",
    "addr:street":"Carrer De Paisos Catalans",
    "iso:country":"ES",
    "sg:address":"Carrer de Paisos Catalans, 16",
    "sg:city":"S. Just Desvern",
    "sg:orig_category":"Servicios De Telecomunicaciones",
    "sg:phone":"+34 934 73 88 88",
    "sg:postcode":"08960",
    "sg:province":"Barcelona",
    "wof:name":"Applied Microelectronica, S.l.",
    "wof:placetype":"venue"
},
  "geometry": {"coordinates":[2.0773293972,41.3776702881],"type":"Point"}
}