{
  "type": "Feature",
  "properties": {
    "iso:country":"ES",
    "sg:address":"Zubiondo Poligonoa, 2",
    "sg:city":"Hernani",
    "sg:orig_category":"Fabricaci\u00d3n De Bibliotecas Y Estanter\u00cdas",
    "sg:phone":"+34 943 55 52 50",
    "sg:postcode":"20120",
    "sg:province":"Guip\u00f9zcoa",
    "wof:name":"Entramados Metalicos S.a.",
    "wof:placetype":"venue"
},
  "geometry": {"coordinates":[-1.9798289537,43.2647514343],"type":"Point"}
}