{
  "type": "Feature",
  "properties": {
    "iso:country":"ES",
    "sg:address":"Pereira (torneiros), 19",
    "sg:city":"Pereira",
    "sg:orig_category":"Montaje (empresas De)",
    "sg:phone":"+34 986 34 48 18",
    "sg:postcode":"36410",
    "sg:province":"Pontevedra",
    "wof:name":"Sercomet S.l.",
    "wof:placetype":"venue"
},
  "geometry": {"coordinates":[-8.6478204727,42.1431007385],"type":"Point"}
}