{
  "type": "Feature",
  "properties": {
    "addr:full":"Plaz Gran Teatro (del), S/n Manzanares Ciudad Real 13200",
    "addr:postcode":"13200",
    "addr:street":"S / N",
    "iso:country":"ES",
    "sg:address":"Plaz Gran Teatro (del), S/n",
    "sg:city":"Manzanares",
    "sg:orig_category":"Iglesia Cat\u00d3lica",
    "sg:phone":"+34 926 61 05 54",
    "sg:postcode":"13200",
    "sg:province":"Ciudad Real",
    "wof:name":"Parroquia Nuestra Se\u00f1ora De Altagracia",
    "wof:placetype":"venue"
},
  "geometry": {"coordinates":[-3.3685789108,39.0012168884],"type":"Point"}
}