{
  "type": "Feature",
  "properties": {
    "iso:country":"ES",
    "sg:address":"Ctra General C-830 Izquierda, 51",
    "sg:city":"Sauces",
    "sg:orig_category":"Laboratorios Farmac\u00c9uticos",
    "sg:phone":"+34 922 45 04 39",
    "sg:postcode":"38720",
    "sg:province":"Santa Cruz De Tenerife",
    "wof:name":"Rodriguez Fuertes Marcelo Mauricio",
    "wof:placetype":"venue"
},
  "geometry": {"coordinates":[-17.7735347748,28.8032951355],"type":"Point"}
}