{
  "type": "Feature",
  "properties": {
    "iso:country":"ES",
    "sg:address":"Calle de Nectar, 35",
    "sg:city":"Madrid",
    "sg:orig_category":"Institutos De Belleza (productos Y Aparatos)",
    "sg:phone":"+34 917 42 99 68",
    "sg:postcode":"28022",
    "sg:province":"Madrid",
    "wof:name":"Lledin Gra\u00f1a Elena",
    "wof:placetype":"venue"
},
  "geometry": {"coordinates":[-3.6116831303,40.4424095154],"type":"Point"}
}