{
  "type": "Feature",
  "properties": {
    "addr:full":"Pg Taulat, 263 Barcelona Barcelona 08019",
    "addr:housenumber":"263",
    "addr:postcode":"08019",
    "addr:street":"Pg Taulat",
    "iso:country":"ES",
    "sg:address":"Pg Taulat, 263",
    "sg:city":"Barcelona",
    "sg:orig_category":"Cajas De Ahorro",
    "sg:phone":"+34 932 66 50 60",
    "sg:postcode":"08019",
    "sg:province":"Barcelona",
    "wof:name":"Caixa D'estalvis De Catalunya",
    "wof:placetype":"venue"
},
  "geometry": {"coordinates":[2.2122271061,41.4048194885],"type":"Point"}
}