{
  "type": "Feature",
  "properties": {
    "addr:full":"Calle de Soria, 1 San Fernando De Henares Madrid 28830",
    "addr:housenumber":"1",
    "addr:postcode":"28830",
    "addr:street":"Calle De Soria",
    "iso:country":"ES",
    "sg:address":"Calle de Soria, 1",
    "sg:city":"San Fernando De Henares",
    "sg:orig_category":"Fabricaci\u00d3n De Juegos Y Juguetes",
    "sg:phone":"+34 916 73 01 37",
    "sg:postcode":"28830",
    "sg:province":"Madrid",
    "wof:name":"Manipulados Aries S.l.",
    "wof:placetype":"venue"
},
  "geometry": {"coordinates":[-3.5312678814,40.4315223694],"type":"Point"}
}