{
  "type": "Feature",
  "properties": {
    "iso:country":"ES",
    "sg:address":"Calle de Don Pedro Infinito, 8",
    "sg:city":"Palmas De Gran Canaria",
    "sg:orig_category":"Panader\u00cdas, Panader\u00cdas",
    "sg:phone":"+34 928 20 73 24",
    "sg:postcode":"35012",
    "sg:province":"Las Palmas",
    "wof:name":"Abad Lopez Marcial",
    "wof:placetype":"venue"
},
  "geometry": {"coordinates":[-15.43022,28.111473],"type":"Point"}
}