{
  "type": "Feature",
  "properties": {
    "iso:country":"ES",
    "sg:address":"Avda Santa Ana, 12",
    "sg:city":"Tudela",
    "sg:orig_category":"El Hogar: Amueblado, Acondicionamiento, Decoraci\u00d3n Y Mantenimiento",
    "sg:phone":"+34 948 82 18 78",
    "sg:postcode":"31500",
    "sg:province":"Navarra",
    "wof:name":"Saez Riancho Felicidad",
    "wof:placetype":"venue"
},
  "geometry": {"coordinates":[-1.602208972,42.0558815002],"type":"Point"}
}