{
  "type": "Feature",
  "properties": {
    "addr:full":"Carrer de Forn, 7 Caldes Montbui Barcelona 08140",
    "addr:housenumber":"7",
    "addr:postcode":"08140",
    "addr:street":"Carrer De Forn;Montbui Barcelona",
    "iso:country":"ES",
    "sg:address":"Carrer de Forn, 7",
    "sg:city":"Caldes Montbui",
    "sg:orig_category":"Farmacias",
    "sg:phone":"+34 938 65 00 97",
    "sg:postcode":"08140",
    "sg:province":"Barcelona",
    "wof:name":"Codina Casabayo Salvador",
    "wof:placetype":"venue"
},
  "geometry": {"coordinates":[2.1621909142,41.6340103149],"type":"Point"}
}