{
  "type": "Feature",
  "properties": {
    "addr:full":"Calle de Magallanes, 3 Madrid Madrid 28015",
    "addr:housenumber":"3",
    "addr:postcode":"28015",
    "addr:street":"Calle De Magallanes",
    "iso:country":"ES",
    "sg:address":"Calle de Magallanes, 3",
    "sg:city":"Madrid",
    "sg:orig_category":"Agencias De Viajes",
    "sg:phone":"+34 915 93 42 39",
    "sg:postcode":"28015",
    "sg:province":"Madrid",
    "sg:website":"www.viajeselcorteingles.es",
    "wof:name":"Viajes El Corte Ingles S.a.",
    "wof:placetype":"venue"
},
  "geometry": {"coordinates":[-3.7056109905,40.433052063],"type":"Point"}
}