{
  "type": "Feature",
  "properties": {
    "addr:full":"Calle de Cecilio Marrero, 9 Agua Garcia Santa Cruz De Tenerife 38355",
    "addr:housenumber":"9",
    "addr:postcode":"38355",
    "addr:street":"Calle De Cecilio Marrero",
    "iso:country":"ES",
    "sg:address":"Calle de Cecilio Marrero, 9",
    "sg:city":"Agua Garcia",
    "sg:orig_category":"Art\u00cdculos Funerarios (al Por Menor)",
    "sg:phone":"+34 922 58 49 01",
    "sg:postcode":"38355",
    "sg:province":"Santa Cruz De Tenerife",
    "wof:name":"Servicios Especiales S.a.",
    "wof:placetype":"venue"
},
  "geometry": {"coordinates":[-16.4026832581,28.4665565491],"type":"Point"}
}