{
  "type": "Feature",
  "properties": {
    "addr:full":"Calle de Real, 8 Almeria Almer\u00eda 04003",
    "addr:housenumber":"8",
    "addr:postcode":"04003",
    "addr:street":"Calle De Real",
    "iso:country":"ES",
    "sg:address":"Calle de Real, 8",
    "sg:city":"Almeria",
    "sg:orig_category":"Agencias Y Agentes Comerciales, Representantes",
    "sg:phone":"+34 950 23 50 96",
    "sg:postcode":"04003",
    "sg:province":"Almer\u00eda",
    "wof:name":"Valverde Perez Justo",
    "wof:placetype":"venue"
},
  "geometry": {"coordinates":[-2.4658670425,36.8403396606],"type":"Point"}
}