{
  "type": "Feature",
  "properties": {
    "addr:full":"Av Pas D'arro, S/n Vielha Lleida 25530",
    "addr:housenumber":"s / n",
    "addr:postcode":"25530",
    "addr:street":"Av Pas D'Arro",
    "iso:country":"ES",
    "sg:address":"Av Pas D'arro, S/n",
    "sg:city":"Vielha",
    "sg:orig_category":"Reposter\u00cdas",
    "sg:phone":"+34 973 64 01 38",
    "sg:postcode":"25530",
    "sg:province":"Lleida",
    "wof:name":"Montes Garcia Francisco",
    "wof:placetype":"venue"
},
  "geometry": {"coordinates":[0.8470500112,42.7534484863],"type":"Point"}
}