{
  "type": "Feature",
  "properties": {
    "iso:country":"ES",
    "sg:address":"Calle de Francisco De Diego, 2",
    "sg:city":"Madrid",
    "sg:orig_category":"Relojer\u00cda (al Por Menor, Reparaci\u00d3n)",
    "sg:phone":"+34 913 11 66 38",
    "sg:postcode":"28040",
    "sg:province":"Madrid",
    "wof:name":"Juan Luengo Garcia S.l.",
    "wof:placetype":"venue"
},
  "geometry": {"coordinates":[-3.714525938,40.4551239014],"type":"Point"}
}