{
  "type": "Feature",
  "properties": {
    "addr:full":"Calle de Gordoniz, 44 Bilbao Vizcaya 48002",
    "addr:housenumber":"44",
    "addr:postcode":"48002",
    "addr:street":"Calle De Gordoniz",
    "iso:country":"ES",
    "sg:address":"Calle de Gordoniz, 44",
    "sg:city":"Bilbao",
    "sg:orig_category":"Seguridad En El Trabajo Y Prevenci\u00d3n De Riesgos Laborales",
    "sg:phone":"+34 944 10 27 03",
    "sg:postcode":"48002",
    "sg:province":"Vizcaya",
    "sg:website":"www.tesysal.com",
    "wof:name":"Tecnicos En Seguridad Y Salud Laboral S.l.",
    "wof:placetype":"venue"
},
  "geometry": {"coordinates":[-2.9454913139,43.2535324097],"type":"Point"}
}