{
  "type": "Feature",
  "properties": {
    "addr:full":"Avda San Juan De La Salle, 49 Sevilla Sevilla 41008",
    "addr:housenumber":"49",
    "addr:postcode":"41008",
    "addr:street":"Avda San Juan De La Salle",
    "iso:country":"ES",
    "sg:address":"Avda San Juan De La Salle, 49",
    "sg:city":"Sevilla",
    "sg:orig_category":"Institutos De Belleza",
    "sg:phone":"+34 954 35 51 31",
    "sg:postcode":"41008",
    "sg:province":"Sevilla",
    "wof:name":"Salon De Belleza Campano S.l.",
    "wof:placetype":"venue"
},
  "geometry": {"coordinates":[-5.9720511436,37.4074020386],"type":"Point"}
}