{
  "type": "Feature",
  "properties": {
    "iso:country":"ES",
    "sg:address":"Calle de San Valeriano, 3",
    "sg:city":"Torrent",
    "sg:orig_category":"Cadenas, Estaciones, Cableados Para Radio Y Televisi\u00d3n",
    "sg:phone":"+34 961 56 12 96",
    "sg:postcode":"46900",
    "sg:province":"Valencia",
    "wof:name":"Comunicaciones Torrent S.l.",
    "wof:placetype":"venue"
},
  "geometry": {"coordinates":[-0.4741260111,39.4308280945],"type":"Point"}
}