{
  "type": "Feature",
  "properties": {
    "addr:full":"Calle de Mayor, 60 Cangas Narcea Asturias 33800",
    "addr:housenumber":"60",
    "addr:postcode":"33800",
    "addr:street":"Calle De Mayor",
    "iso:country":"ES",
    "sg:address":"Calle de Mayor, 60",
    "sg:city":"Cangas Narcea",
    "sg:classifiers":[
        {
            "category":"Communications",
            "type":"Services"
        }
    ],
    "sg:phone":"+34 985 81 26 46",
    "sg:postcode":"33800",
    "sg:province":"Asturias",
    "sg:tags":[
        "televisiones",
        "y",
        "radio"
    ],
    "wof:name":"Uniprex-onda Cero",
    "wof:placetype":"venue"
},
  "geometry": {"coordinates":[-6.5513038635,43.178691864],"type":"Point"}
}