{
  "type": "Feature",
  "properties": {
    "iso:country":"ES",
    "sg:address":"Garagartza Auzoa, 49",
    "sg:city":"Garagartza",
    "sg:orig_category":"Molduras, Junquillos, Listones Y Molduras Perforadas",
    "sg:phone":"+34 943 79 61 14",
    "sg:postcode":"20509",
    "sg:province":"Guip\u00f9zcoa",
    "wof:name":"Zabarte Eriz Maria Jesus",
    "wof:placetype":"venue"
},
  "geometry": {"coordinates":[-2.5292959213,43.0634117126],"type":"Point"}
}