{
  "type": "Feature",
  "properties": {
    "iso:country":"ES",
    "sg:address":"Carr Tito Cittadini, 3",
    "sg:city":"Pollen\u00e7a",
    "sg:orig_category":"Tintes (fabricaci\u00d3n, Al Por Mayor)",
    "sg:phone":"+34 971 53 28 59",
    "sg:postcode":"07460",
    "sg:province":"Islas Baleares",
    "wof:name":"Tintoreria Pollensa S.l.",
    "wof:placetype":"venue"
},
  "geometry": {"coordinates":[3.0190660954,39.8783416748],"type":"Point"}
}