{
  "type": "Feature",
  "properties": {
    "addr:full":"Arana Kalea, 11 Azpeitia Guip\u00f9zcoa 20730",
    "addr:housenumber":"11",
    "addr:postcode":"20730",
    "addr:street":"Arana Kalea;Guipu\u0300Zcoa",
    "iso:country":"ES",
    "sg:address":"Arana Kalea, 11",
    "sg:city":"Azpeitia",
    "sg:orig_category":"Muebles, Minoristas",
    "sg:phone":"+34 943 81 16 72",
    "sg:postcode":"20730",
    "sg:province":"Guip\u00f9zcoa",
    "wof:name":"Arocena Gurruchaga Joaquin",
    "wof:placetype":"venue"
},
  "geometry": {"coordinates":[-2.2689819336,43.181804657],"type":"Point"}
}