{
  "type": "Feature",
  "properties": {
    "addr:full":"Avda Arana Sabino, 28 Bilbao Vizcaya 48013",
    "addr:housenumber":"28",
    "addr:postcode":"48013",
    "addr:street":"Avda Arana Sabino",
    "iso:country":"ES",
    "sg:address":"Avda Arana Sabino, 28",
    "sg:city":"Bilbao",
    "sg:orig_category":"\u00c1rboles Frutales",
    "sg:phone":"+34 944 41 69 39",
    "sg:postcode":"48013",
    "sg:province":"Vizcaya",
    "wof:name":"Navarro Murga Juan Manuel",
    "wof:placetype":"venue"
},
  "geometry": {"coordinates":[-2.9467489719,43.2618331909],"type":"Point"}
}