{
  "type": "Feature",
  "properties": {
    "addr:full":"Pol Ind Los Pollitos, S/n Puebla Cazalla Sevilla 41540",
    "addr:housenumber":"s",
    "addr:postcode":"41540",
    "addr:street":"/ N",
    "iso:country":"ES",
    "sg:address":"Pol Ind Los Pollitos, S/n",
    "sg:city":"Puebla Cazalla",
    "sg:orig_category":"Chapister\u00cda",
    "sg:phone":"+34 954 84 65 46",
    "sg:postcode":"41540",
    "sg:province":"Sevilla",
    "wof:name":"Mena Ortiz Francisco",
    "wof:placetype":"venue"
},
  "geometry": {"coordinates":[-5.3132190704,37.2229957581],"type":"Point"}
}