{
  "type": "Feature",
  "properties": {
    "addr:full":"Carrer de Riera Gran (de La), 4 Vilafranca Penedes Barcelona 08720",
    "addr:housenumber":"4",
    "addr:postcode":"08720",
    "addr:street":"Carrer De Riera Gran De La;Penedes Barcelona",
    "iso:country":"ES",
    "sg:address":"Carrer de Riera Gran (de La), 4",
    "sg:city":"Vilafranca Penedes",
    "sg:orig_category":"Maquinaria Para Industrias Diversas",
    "sg:phone":"+34 938 90 23 71",
    "sg:postcode":"08720",
    "sg:province":"Barcelona",
    "wof:name":"Tecno Air Penedes S.l.",
    "wof:placetype":"venue"
},
  "geometry": {"coordinates":[1.6805310249,41.3349189758],"type":"Point"}
}