{
  "type": "Feature",
  "properties": {
    "addr:full":"Electricidad, 28 Leganes Madrid 28918",
    "addr:housenumber":"28",
    "addr:postcode":"28918",
    "iso:country":"ES",
    "sg:address":"Electricidad, 28",
    "sg:city":"Leganes",
    "sg:orig_category":"Imprenta",
    "sg:phone":"+34 916 12 02 11",
    "sg:postcode":"28918",
    "sg:province":"Madrid",
    "wof:name":"Imprenta Cruces S.a.",
    "wof:placetype":"venue"
},
  "geometry": {"coordinates":[-3.7996480465,40.3503379822],"type":"Point"}
}