{
  "type": "Feature",
  "properties": {
    "iso:country":"ES",
    "sg:address":"Calle de San Salvador, 18",
    "sg:city":"Alcora",
    "sg:orig_category":"Transportes Por V\u00cdas Navegables",
    "sg:phone":"+34 964 36 00 16",
    "sg:postcode":"12110",
    "sg:province":"Castell\u00f3n",
    "wof:name":"Albaro Benlliure Francisco",
    "wof:placetype":"venue"
},
  "geometry": {"coordinates":[-0.2181914002,40.0728721619],"type":"Point"}
}