{
  "type": "Feature",
  "properties": {
    "iso:country":"ES",
    "sg:address":"Merkatondoa, 4",
    "sg:city":"Estella",
    "sg:orig_category":"Mec\u00c1nico Del Autom\u00d3vil",
    "sg:phone":"+34 948 55 40 50",
    "sg:postcode":"31200",
    "sg:province":"Navarra",
    "wof:name":"Segura Hermoso De Mendoza Alberto",
    "wof:placetype":"venue"
},
  "geometry": {"coordinates":[-2.0302510262,42.6601715088],"type":"Point"}
}