{
  "type": "Feature",
  "properties": {
    "iso:country":"ES",
    "sg:address":"Carrer de Salvador Espriu, 16",
    "sg:city":"S. Just Desvern",
    "sg:orig_category":"Materias Pl\u00c1sticas: Productos De Consumo Masivo (fabricaci\u00d3n, Al Por Mayor)",
    "sg:phone":"+34 934 99 04 86",
    "sg:postcode":"08960",
    "sg:province":"Barcelona",
    "wof:name":"Oller Viladrosa Jordi",
    "wof:placetype":"venue"
},
  "geometry": {"coordinates":[2.0701699257,41.3811416626],"type":"Point"}
}