{
  "type": "Feature",
  "properties": {
    "iso:country":"ES",
    "sg:address":"Calle de Juan Llorens, 11",
    "sg:city":"Valencia",
    "sg:orig_category":"Animales (al Por Menor)",
    "sg:phone":"+34 963 82 08 82",
    "sg:postcode":"46008",
    "sg:province":"Valencia",
    "wof:name":"Fores Va\u00f1o Lourdes",
    "wof:placetype":"venue"
},
  "geometry": {"coordinates":[-0.3909800053,39.4732551575],"type":"Point"}
}