{
  "type": "Feature",
  "properties": {
    "addr:full":"Avda Generalisimo, Km. 0044,6 Meira Lugo 27240",
    "addr:postcode":"27240",
    "addr:street":"Avda Generalisimo Km. 0044,6 Meira",
    "iso:country":"ES",
    "sg:address":"Avda Generalisimo, Km. 0044,6",
    "sg:city":"Meira",
    "sg:orig_category":"Mec\u00c1nico Del Autom\u00d3vil",
    "sg:phone":"+34 982 33 02 82",
    "sg:postcode":"27240",
    "sg:province":"Lugo",
    "wof:name":"Bartolome Calderon Eduardo",
    "wof:placetype":"venue"
},
  "geometry": {"coordinates":[-7.2940421104,43.2163162231],"type":"Point"}
}