{
  "type": "Feature",
  "properties": {
    "addr:full":"Calle de San Francisco, S/n Cogolludo Guadalajara 19230",
    "addr:housenumber":"/ n",
    "addr:postcode":"19230",
    "addr:street":"Calle De San Francisco S",
    "iso:country":"ES",
    "sg:address":"Calle de San Francisco, S/n",
    "sg:city":"Cogolludo",
    "sg:orig_category":"Promotores Constructores",
    "sg:phone":"+34 949 85 50 18",
    "sg:postcode":"19230",
    "sg:province":"Guadalajara",
    "wof:name":"Bartolome Martinez Ramon",
    "wof:placetype":"venue"
},
  "geometry": {"coordinates":[-3.0903289318,40.9461097717],"type":"Point"}
}