{
  "type": "Feature",
  "properties": {
    "iso:country":"ES",
    "sg:address":"Carrer de Folgueroles, 4",
    "sg:city":"Barcelona",
    "sg:orig_category":"Inmobiliaria (agencias)",
    "sg:phone":"+34 934 17 46 32",
    "sg:postcode":"08022",
    "sg:province":"Barcelona",
    "wof:name":"Ita-illar S.l.",
    "wof:placetype":"venue"
},
  "geometry": {"coordinates":[2.1351599693,41.4085960388],"type":"Point"}
}