{
  "type": "Feature",
  "properties": {
    "iso:country":"ES",
    "sg:address":"Calle de Vallehermoso, 33",
    "sg:city":"Madrid",
    "sg:orig_category":"Tintorer\u00cdas, Limpieza En Seco",
    "sg:phone":"+34 915 94 50 59",
    "sg:postcode":"28015",
    "sg:province":"Madrid",
    "wof:name":"Gamarra Mu\u00f1oz Jose Luis",
    "wof:placetype":"venue"
},
  "geometry": {"coordinates":[-3.7089400291,40.4331207275],"type":"Point"}
}