{
  "type": "Feature",
  "properties": {
    "iso:country":"ES",
    "sg:address":"Calle de Concha General, 7",
    "sg:city":"Bilbao",
    "sg:orig_category":"Peluquer\u00cdas, Peluquer\u00cda Mixta",
    "sg:phone":"+34 944 10 04 73",
    "sg:postcode":"48008",
    "sg:province":"Vizcaya",
    "wof:name":"Enexo Bisness Network S.a",
    "wof:placetype":"venue"
},
  "geometry": {"coordinates":[-2.9344739914,43.2598800659],"type":"Point"}
}