{
  "type": "Feature",
  "properties": {
    "iso:country":"ES",
    "sg:address":"Avgd Corts Valencianes, 54",
    "sg:city":"Turis",
    "sg:orig_category":"Empresas De Desmonte",
    "sg:phone":"+34 962 52 72 41",
    "sg:postcode":"46389",
    "sg:province":"Valencia",
    "wof:name":"Jose Juan",
    "wof:placetype":"venue"
},
  "geometry": {"coordinates":[-0.7086669803,39.3914489746],"type":"Point"}
}