{
  "type": "Feature",
  "properties": {
    "iso:country":"ES",
    "sg:address":"Carrer de Moli, 30",
    "sg:city":"Caldes Montbui",
    "sg:orig_category":"Centros Empresariales",
    "sg:phone":"+34 938 65 00 61",
    "sg:postcode":"08140",
    "sg:province":"Barcelona",
    "wof:name":"Gaia Consultoria Y Gestion S.l.",
    "wof:placetype":"venue"
},
  "geometry": {"coordinates":[2.1643190384,41.626247406],"type":"Point"}
}