{
  "type": "Feature",
  "properties": {
    "iso:country":"ES",
    "sg:address":"Carrer de Lepant, 220",
    "sg:city":"Barcelona",
    "sg:orig_category":"El Hogar: Amueblado, Acondicionamiento, Decoraci\u00d3n Y Mantenimiento",
    "sg:phone":"+34 932 65 63 20",
    "sg:postcode":"08013",
    "sg:province":"Barcelona",
    "wof:name":"Instalaciones Kone S.l.",
    "wof:placetype":"venue"
},
  "geometry": {"coordinates":[2.1807310581,41.4015693665],"type":"Point"}
}