{
  "type": "Feature",
  "properties": {
    "iso:country":"ES",
    "sg:address":"Plaz Espa\u00d1a (de), 20",
    "sg:city":"Barco De Avila",
    "sg:orig_category":"Alimentaci\u00d3n General (al Por Menor)",
    "sg:phone":"+34 920 34 00 32",
    "sg:postcode":"05600",
    "sg:province":"\u00c1vila",
    "wof:name":"Coronado Garcia Juan",
    "wof:placetype":"venue"
},
  "geometry": {"coordinates":[-5.5218648911,40.3584060669],"type":"Point"}
}