{
  "type": "Feature",
  "properties": {
    "addr:full":"Pl Francesc Macia, 1 Cardedeu Barcelona 08440",
    "addr:housenumber":"1",
    "addr:postcode":"08440",
    "addr:street":"Pl Francesc Macia",
    "iso:country":"ES",
    "sg:address":"Pl Francesc Macia, 1",
    "sg:city":"Cardedeu",
    "sg:orig_category":"Asociaciones Y Clubs Deportivos",
    "sg:phone":"+34 938 71 19 76",
    "sg:postcode":"08440",
    "sg:province":"Barcelona",
    "wof:name":"Bellido-lara S.l.",
    "wof:placetype":"venue"
},
  "geometry": {"coordinates":[2.3577709198,41.6394996643],"type":"Point"}
}