{
  "type": "Feature",
  "properties": {
    "iso:country":"ES",
    "sg:address":"Avda Via Roma (la), 68",
    "sg:city":"Segovia",
    "sg:orig_category":"T\u00c9cnicos Veterinarios",
    "sg:phone":"+34 921 44 33 37",
    "sg:postcode":"40003",
    "sg:province":"Segovia",
    "wof:name":"General Ganadera Segoviana S.l.",
    "wof:placetype":"venue"
},
  "geometry": {"coordinates":[-4.1083059311,40.9549980164],"type":"Point"}
}