{
  "type": "Feature",
  "properties": {
    "addr:full":"Rua Porvir, 31 Sarria Lugo 27600",
    "addr:housenumber":"31",
    "addr:postcode":"27600",
    "addr:street":"Rua Porvir",
    "iso:country":"ES",
    "sg:address":"Rua Porvir, 31",
    "sg:city":"Sarria",
    "sg:orig_category":"Pintura Y Barniz (al Por Menor)",
    "sg:phone":"+34 982 53 08 68",
    "sg:postcode":"27600",
    "sg:province":"Lugo",
    "wof:name":"Latas Castro Jose",
    "wof:placetype":"venue"
},
  "geometry": {"coordinates":[-7.4175491333,42.7800216675],"type":"Point"}
}