{
  "type": "Feature",
  "properties": {
    "addr:full":"Prol. De Ollerias, S/n Llerena Badajoz 06900",
    "addr:housenumber":"s / n",
    "addr:postcode":"06900",
    "addr:street":"Prol. De Ollerias",
    "iso:country":"ES",
    "sg:address":"Prol. De Ollerias, S/n",
    "sg:city":"Llerena",
    "sg:orig_category":"Piscinas, Accesorios, Suministros (fabricaci\u00d3n, Al Por Mayor)",
    "sg:phone":"+34 924 87 00 39",
    "sg:postcode":"06900",
    "sg:province":"Badajoz",
    "wof:name":"Centro De Iniciativas Y Turismo",
    "wof:placetype":"venue"
},
  "geometry": {"coordinates":[-6.0109610558,38.2334671021],"type":"Point"}
}