{
  "type": "Feature",
  "properties": {
    "iso:country":"ES",
    "sg:address":"Lugar San Lourenzo(bembibre), S/n",
    "sg:city":"Val Do Dubra-bembibre",
    "sg:orig_category":"Electricidad (montaje, Ensamblaje De Componentes)",
    "sg:phone":"+34 981 88 93 32",
    "sg:postcode":"15873",
    "sg:province":"A Coru\u00f1a",
    "wof:name":"Talleres Xixirey S.l.",
    "wof:placetype":"venue"
},
  "geometry": {"coordinates":[-8.6559801102,43.0241699219],"type":"Point"}
}