{
  "type": "Feature",
  "properties": {
    "iso:country":"ES",
    "sg:address":"Rua Remedios (dos), 68",
    "sg:city":"Ourense",
    "sg:orig_category":"Electricidad, Electr\u00d3nica: Material Y Suministros (al Por Mayor)",
    "sg:phone":"+34 988 22 31 85",
    "sg:postcode":"32002",
    "sg:province":"Ourense",
    "wof:name":"Inverexpan",
    "wof:placetype":"venue"
},
  "geometry": {"coordinates":[-7.8757481575,42.3435134888],"type":"Point"}
}