{
  "type": "Feature",
  "properties": {
    "iso:country":"ES",
    "sg:address":"Calle de Diego Polo, 8",
    "sg:city":"Burgos",
    "sg:orig_category":"Instalaci\u00d3n, Reparaci\u00d3n De Ascensores Y Montacargas",
    "sg:phone":"+34 947 25 20 29",
    "sg:postcode":"09001",
    "sg:province":"Burgos",
    "wof:name":"Thyssenkrupp Elevadores S.l.",
    "wof:placetype":"venue"
},
  "geometry": {"coordinates":[-3.7063648701,42.3311157227],"type":"Point"}
}