{
  "type": "Feature",
  "properties": {
    "addr:full":"Carrer de Miralles, S/n Malgrat Mar Barcelona 08380",
    "addr:housenumber":"s / n",
    "addr:postcode":"08380",
    "addr:street":"Carrer De Miralles",
    "iso:country":"ES",
    "sg:address":"Carrer de Miralles, S/n",
    "sg:city":"Malgrat Mar",
    "sg:orig_category":"Limpieza Industrial",
    "sg:phone":"+34 902 36 07 57",
    "sg:postcode":"08380",
    "sg:province":"Barcelona",
    "wof:name":"Oehalennia S.l.",
    "wof:placetype":"venue"
},
  "geometry": {"coordinates":[2.7417299747,41.6557159424],"type":"Point"}
}