{
  "type": "Feature",
  "properties": {
    "iso:country":"ES",
    "sg:address":"Carrer de Barcelones, 26",
    "sg:city":"Poligono Industrial Ramasa",
    "sg:orig_category":"Laboratorios Y Cl\u00cdnicas Veterinarias",
    "sg:phone":"+34 938 49 51 33",
    "sg:postcode":"08520",
    "sg:province":"Barcelona",
    "wof:name":"Laboratorios Calier S.a.",
    "wof:placetype":"venue"
},
  "geometry": {"coordinates":[2.2992899418,41.6361808777],"type":"Point"}
}