{
  "type": "Feature",
  "properties": {
    "addr:full":"Calle de Santo Angel, 19 Aviles Asturias 33403",
    "addr:housenumber":"19",
    "addr:postcode":"33403",
    "addr:street":"Calle De Santo Angel",
    "iso:country":"ES",
    "sg:address":"Calle de Santo Angel, 19",
    "sg:city":"Aviles",
    "sg:orig_category":"Peluqueros: De Se\u00d1oras",
    "sg:phone":"+34 985 57 15 05",
    "sg:postcode":"33403",
    "sg:province":"Asturias",
    "wof:name":"Peluqueria Nedi S.l.",
    "wof:placetype":"venue"
},
  "geometry": {"coordinates":[-5.9075632095,43.5456924438],"type":"Point"}
}