{
  "type": "Feature",
  "properties": {
    "iso:country":"ES",
    "sg:address":"Calle de Poeta Manuel Gongora, 4",
    "sg:city":"Granada",
    "sg:classifiers":[
        {
            "category":"Autos & Motor Vehicles",
            "subcategory":"Automobile Sales",
            "type":"Retail Goods"
        }
    ],
    "sg:phone":"+34 958 18 35 84",
    "sg:postcode":"18006",
    "sg:province":"Granada",
    "sg:website":"www.grupoguia.es",
    "wof:name":"Formacion Vial Arrayanes S.l.",
    "wof:placetype":"venue"
},
  "geometry": {"coordinates":[-3.5959630013,37.1673355103],"type":"Point"}
}