{
  "type": "Feature",
  "properties": {
    "iso:country":"ES",
    "sg:address":"Calle de Ancora, 42",
    "sg:city":"Madrid",
    "sg:orig_category":"Internados & Ense\u00d1anza Privada",
    "sg:phone":"+34 915 39 27 39",
    "sg:postcode":"28045",
    "sg:province":"Madrid",
    "wof:name":"Congregaciones Marianas Maria Inmaculada",
    "wof:placetype":"venue"
},
  "geometry": {"coordinates":[-3.6890966892,40.402759552],"type":"Point"}
}