{
  "type": "Feature",
  "properties": {
    "iso:country":"ES",
    "sg:address":"Calle de Zaragoza, 59",
    "sg:city":"Binefar",
    "sg:orig_category":"Mec\u00c1nico Del Autom\u00d3vil",
    "sg:phone":"+34 974 42 96 89",
    "sg:postcode":"22500",
    "sg:province":"Huesca",
    "wof:name":"Motor Dos 2004 S.l",
    "wof:placetype":"venue"
},
  "geometry": {"coordinates":[0.2864190042,41.8536148071],"type":"Point"}
}