{
  "type": "Feature",
  "properties": {
    "iso:country":"ES",
    "sg:address":"Avda Torreon Del Alcazar, 3",
    "sg:city":"Ciudad Real",
    "sg:orig_category":"M\u00c9dicos: Psiquiatr\u00cda",
    "sg:phone":"+34 926 22 85 22",
    "sg:postcode":"13004",
    "sg:province":"Ciudad Real",
    "wof:name":"Bernardo Barrio Pedro De",
    "wof:placetype":"venue"
},
  "geometry": {"coordinates":[-3.9238340855,38.9844207764],"type":"Point"}
}