{
  "type": "Feature",
  "properties": {
    "addr:full":"Calle de Valle De Broto, 3 Zaragoza Zaragoza 50015",
    "addr:housenumber":"3",
    "addr:postcode":"50015",
    "addr:street":"Calle De Valle De Broto",
    "iso:country":"ES",
    "sg:address":"Calle de Valle De Broto, 3",
    "sg:city":"Zaragoza",
    "sg:orig_category":"M\u00c9dicos: Estomatolog\u00cda",
    "sg:phone":"+34 976 73 12 74",
    "sg:postcode":"50015",
    "sg:province":"Zaragoza",
    "wof:name":"Garcia Galan Aurora",
    "wof:placetype":"venue"
},
  "geometry": {"coordinates":[-0.8729299903,41.6663665771],"type":"Point"}
}