{
  "type": "Feature",
  "properties": {
    "addr:full":"Plaz Iglesia, 1 Cati Castell\u00f3n 12513",
    "addr:housenumber":"1",
    "addr:postcode":"12513",
    "addr:street":"Iglesia;Castello\u0301N",
    "iso:country":"ES",
    "sg:address":"Plaz Iglesia, 1",
    "sg:city":"Cati",
    "sg:orig_category":"Iglesia Cat\u00d3lica",
    "sg:phone":"+34 964 40 90 07",
    "sg:postcode":"12513",
    "sg:province":"Castell\u00f3n",
    "wof:name":"Iglesia Parroquial De La Asuncion",
    "wof:placetype":"venue"
},
  "geometry": {"coordinates":[0.0224900004,40.4711837769],"type":"Point"}
}