{
  "type": "Feature",
  "properties": {
    "iso:country":"ES",
    "sg:address":"Avda Constitucion (la), 9",
    "sg:city":"Bollullos Mitacion",
    "sg:orig_category":"Electricidad Veh\u00cdculo",
    "sg:phone":"+34 955 76 53 67",
    "sg:postcode":"41110",
    "sg:province":"Sevilla",
    "wof:name":"Guzman Romero Manuel",
    "wof:placetype":"venue"
},
  "geometry": {"coordinates":[-6.1366839409,37.3362617493],"type":"Point"}
}