{
  "type": "Feature",
  "properties": {
    "addr:full":"Calle de Jorge Juan, 30 Madrid Madrid 28001",
    "addr:housenumber":"30",
    "addr:postcode":"madrid;28001",
    "addr:street":"Calle De Jorge Juan",
    "iso:country":"ES",
    "sg:address":"Calle de Jorge Juan, 30",
    "sg:city":"Madrid",
    "sg:orig_category":"El Hogar: Amueblado, Acondicionamiento, Decoraci\u00d3n Y Mantenimiento",
    "sg:phone":"+34 915 78 00 92",
    "sg:postcode":"28001",
    "sg:province":"Madrid",
    "wof:name":"Le Murier Espa\u00f1a S.a.",
    "wof:placetype":"venue"
},
  "geometry": {"coordinates":[-3.6835858822,40.4236221313],"type":"Point"}
}