{
  "type": "Feature",
  "properties": {
    "addr:full":"Playa Duque-granada, 1 Nueva Andalucia M\u00e1laga 29660",
    "addr:housenumber":"1",
    "addr:postcode":"29660",
    "addr:street":"Duque-Granada;Ma\u0301Laga",
    "iso:country":"ES",
    "sg:address":"Playa Duque-granada, 1",
    "sg:city":"Nueva Andalucia",
    "sg:orig_category":"Promotores Constructores",
    "sg:phone":"+34 952 81 67 34",
    "sg:postcode":"29660",
    "sg:province":"M\u00e1laga",
    "wof:name":"Club Playas Del Duque S.l.",
    "wof:placetype":"venue"
},
  "geometry": {"coordinates":[-4.9572491646,36.4902381897],"type":"Point"}
}