{
  "type": "Feature",
  "properties": {
    "iso:country":"ES",
    "sg:address":"O Chao De Pousadoiro, S/n",
    "sg:city":"San Xurxo De Piquin",
    "sg:orig_category":"Centros De Educaci\u00d3n Especial",
    "sg:phone":"+34 982 33 36 04",
    "sg:postcode":"27242",
    "sg:province":"Lugo",
    "wof:name":"Centro Educacion Infantil Primaria Anibal Otero",
    "wof:placetype":"venue"
},
  "geometry": {"coordinates":[-7.2072591782,43.2048416138],"type":"Point"}
}