{
  "type": "Feature",
  "properties": {
    "addr:full":"Calle de Venus, 9 Callejones-san Silvestre Almer\u00eda 04230",
    "addr:housenumber":"9",
    "addr:postcode":"04230",
    "addr:street":"Calle De Venus;Silvestre Almeri\u0301A",
    "iso:country":"ES",
    "sg:address":"Calle de Venus, 9",
    "sg:city":"Callejones-san Silvestre",
    "sg:orig_category":"M\u00c1rmoles, Granitos Y Piedras Naturales",
    "sg:phone":"+34 950 14 34 68",
    "sg:postcode":"04230",
    "sg:province":"Almer\u00eda",
    "wof:name":"Marmoles San Silvestre S.l.",
    "wof:placetype":"venue"
},
  "geometry": {"coordinates":[-2.4470589161,36.8753395081],"type":"Point"}
}