{
  "type": "Feature",
  "properties": {
    "addr:full":"Calle de Antonio Machado, 7 Carmona Sevilla 41410",
    "addr:housenumber":"7",
    "addr:postcode":"41410",
    "addr:street":"Calle De Antonio Machado",
    "iso:country":"ES",
    "sg:address":"Calle de Antonio Machado, 7",
    "sg:city":"Carmona",
    "sg:orig_category":"Contenedores (mercanc\u00cdas)",
    "sg:phone":"+34 954 14 90 27",
    "sg:postcode":"41410",
    "sg:province":"Sevilla",
    "wof:name":"Dimar Cargo S.l.",
    "wof:placetype":"venue"
},
  "geometry": {"coordinates":[-5.6452536583,37.4670600891],"type":"Point"}
}