{
  "type": "Feature",
  "properties": {
    "addr:full":"Avda Logro\u00d1o, 4 Alfaro La Rioja 26540",
    "addr:housenumber":"4",
    "addr:postcode":"26540",
    "addr:street":"Avda Logron\u0303O;Rioja",
    "iso:country":"ES",
    "sg:address":"Avda Logro\u00d1o, 4",
    "sg:city":"Alfaro",
    "sg:orig_category":"Material Y Suministros Para Perforaciones, Sondeos",
    "sg:phone":"+34 941 18 20 16",
    "sg:postcode":"26540",
    "sg:province":"La Rioja",
    "wof:name":"Pe\u00f1a Vidaurreta Jose Luis",
    "wof:placetype":"venue"
},
  "geometry": {"coordinates":[-1.7606790066,42.1813468933],"type":"Point"}
}