{
  "type": "Feature",
  "properties": {
    "addr:full":"Calle de Casa\u00d1e, 1 Palencia Palencia 34002",
    "addr:housenumber":"1",
    "addr:postcode":"34002",
    "addr:street":"Calle De Casan\u0303E",
    "iso:country":"ES",
    "sg:address":"Calle de Casa\u00d1e, 1",
    "sg:city":"Palencia",
    "sg:classifiers":[
        {
            "category":"Shopping",
            "subcategory":"Crafts & Fabrics",
            "type":"Retail Goods"
        }
    ],
    "sg:phone":"+34 979 72 67 03",
    "sg:postcode":"34002",
    "sg:province":"Palencia",
    "sg:tags":[
        "manta",
        "de",
        "fabricaci\u00d3n"
    ],
    "wof:name":"Luis Casa\u00f1e C.b.",
    "wof:placetype":"venue"
},
  "geometry": {"coordinates":[-4.5278539658,42.0033149719],"type":"Point"}
}