{
  "type": "Feature",
  "properties": {
    "iso:country":"ES",
    "sg:address":"Carr Vall De Carrasquer, 7",
    "sg:city":"Sueca",
    "sg:orig_category":"Comercio De Piezas De Recambio Y De Accesorios De Veh\u00cdculos, Veh\u00cdculos Industriales",
    "sg:phone":"+34 961 70 09 50",
    "sg:postcode":"46410",
    "sg:province":"Valencia",
    "wof:name":"Dinamica Del Repuesto S. L.",
    "wof:placetype":"venue"
},
  "geometry": {"coordinates":[-0.3048599958,39.2008132935],"type":"Point"}
}