{
  "type": "Feature",
  "properties": {
    "iso:country":"ES",
    "sg:address":"Calle de Labradores, 21",
    "sg:city":"Valladolid",
    "sg:orig_category":"Art\u00cdculos De Regalo (al Por Menor)",
    "sg:phone":"+34 983 39 46 93",
    "sg:postcode":"47004",
    "sg:province":"Valladolid",
    "wof:name":"Torres Garcia Maria Milagros",
    "wof:placetype":"venue"
},
  "geometry": {"coordinates":[-4.7206149101,41.6469192505],"type":"Point"}
}