{
  "type": "Feature",
  "properties": {
    "iso:country":"ES",
    "sg:address":"Calle de Tejon Y Marin, 8",
    "sg:city":"Cordoba",
    "sg:orig_category":"Comunidades Religiosas",
    "sg:phone":"+34 957 29 52 88",
    "sg:postcode":"14003",
    "sg:province":"C\u00f3rdoba",
    "wof:name":"Obra Pia Stma Trinidad",
    "wof:placetype":"venue"
},
  "geometry": {"coordinates":[-4.7846260071,37.8823699951],"type":"Point"}
}