{
  "type": "Feature",
  "properties": {
    "iso:country":"ES",
    "sg:address":"Calle de Francisco Villaespesa, 3",
    "sg:city":"Ejido",
    "sg:orig_category":"Bares, Piano",
    "sg:phone":"+34 950 48 38 55",
    "sg:postcode":"04700",
    "sg:province":"Almer\u00eda",
    "wof:name":"Hermanos Bautista Romero S.l.",
    "wof:placetype":"venue"
},
  "geometry": {"coordinates":[-2.8176419735,36.7740058899],"type":"Point"}
}