{
  "type": "Feature",
  "properties": {
    "iso:country":"ES",
    "sg:address":"C/ Doctor Ferran, 70",
    "sg:city":"Elche",
    "sg:orig_category":"Aparcamientos (infraestructuras, Accesorios)",
    "sg:phone":"+34 965 46 46 19",
    "sg:postcode":"03201",
    "sg:province":"Alicante",
    "wof:name":"Garaje Carlos S.l.",
    "wof:placetype":"venue"
},
  "geometry": {"coordinates":[-0.7078670263,38.2639198303],"type":"Point"}
}