{
  "type": "Feature",
  "properties": {
    "iso:country":"ES",
    "sg:address":"Calle de Vitoria, 21",
    "sg:orig_category":"Inform\u00c1tica (estudios, Servicios, Asesor\u00cda, Formaci\u00d3n)",
    "sg:phone":"+34 944 05 55 85",
    "sg:postcode":"01400",
    "sg:province":"\u00c1lava",
    "sg:website":"www.aplicagrupo.com",
    "wof:name":"Aplica Soluciones Sl",
    "wof:placetype":"venue"
},
  "geometry": {"coordinates":[-3.0688686371,42.8367958069],"type":"Point"}
}