{
  "type": "Feature",
  "properties": {
    "addr:full":"Pase Hernando De Soto, 14 Olivenza Badajoz 06100",
    "addr:housenumber":"14",
    "addr:postcode":"06100",
    "addr:street":"Hernando De Soto",
    "iso:country":"ES",
    "sg:address":"Pase Hernando De Soto, 14",
    "sg:city":"Olivenza",
    "sg:orig_category":"Empresas De Carpinter\u00cda De Madera",
    "sg:phone":"+34 924 49 02 85",
    "sg:postcode":"06100",
    "sg:province":"Badajoz",
    "wof:name":"Borrego Cordero Federico",
    "wof:placetype":"venue"
},
  "geometry": {"coordinates":[-7.0972537994,38.6838607788],"type":"Point"}
}