{
  "type": "Feature",
  "properties": {
    "addr:full":"Rua Montero Rios, 81 Lugo Lugo 27002",
    "addr:housenumber":"81",
    "addr:postcode":"27002",
    "addr:street":"Rua Montero Rios",
    "iso:country":"ES",
    "sg:address":"Rua Montero Rios, 81",
    "sg:city":"Lugo",
    "sg:orig_category":"Farmacias",
    "sg:phone":"+34 982 22 21 59",
    "sg:postcode":"27002",
    "sg:province":"Lugo",
    "wof:name":"Herrero Iba\u00f1ez Blanca Maria",
    "wof:placetype":"venue"
},
  "geometry": {"coordinates":[-7.5508489609,43.0139770508],"type":"Point"}
}