{
  "type": "Feature",
  "properties": {
    "addr:full":"Carrer de Figuereta De La, 36 Valls Tarragona 43800",
    "addr:housenumber":"36",
    "addr:postcode":"43800",
    "addr:street":"Carrer De Figuereta De La",
    "iso:country":"ES",
    "sg:address":"Carrer de Figuereta De La, 36",
    "sg:city":"Valls",
    "sg:orig_category":"Equipos De Marcado, Etiquetado",
    "sg:phone":"+34 977 60 08 16",
    "sg:postcode":"43800",
    "sg:province":"Tarragona",
    "wof:name":"Sanroma Sentelles Jose Maria",
    "wof:placetype":"venue"
},
  "geometry": {"coordinates":[1.2502499819,41.2833976746],"type":"Point"}
}