{
  "type": "Feature",
  "properties": {
    "iso:country":"ES",
    "sg:address":"Avgd Pi Y Margall, 43",
    "sg:city":"Burjassot",
    "sg:orig_category":"Internados & Ense\u00d1anza Privada",
    "sg:phone":"+34 963 64 19 58",
    "sg:postcode":"46100",
    "sg:province":"Valencia",
    "wof:name":"Patronato De Promocion Humana Y Social Juan Xxiii",
    "wof:placetype":"venue"
},
  "geometry": {"coordinates":[-0.4167529941,39.5167274475],"type":"Point"}
}