{
  "type": "Feature",
  "properties": {
    "iso:country":"ES",
    "sg:address":"Rua Pizarro, 8",
    "sg:city":"Vigo",
    "sg:orig_category":"Ortopedia General",
    "sg:phone":"+34 986 48 34 40",
    "sg:postcode":"36204",
    "sg:province":"Pontevedra",
    "wof:name":"Caama\u00f1o Garcia Guillermo Jose",
    "wof:placetype":"venue"
},
  "geometry": {"coordinates":[-8.7174577713,42.229763031],"type":"Point"}
}