{
  "type": "Feature",
  "properties": {
    "addr:full":"Carrer de Pare Roca, 1 Olot Girona 17800",
    "addr:housenumber":"1",
    "addr:postcode":"17800",
    "addr:street":"Carrer De Pare Roca",
    "iso:country":"ES",
    "sg:address":"Carrer de Pare Roca, 1",
    "sg:city":"Olot",
    "sg:orig_category":"Fabricaci\u00d3n, Venta De Cuadros, Accesorios Para Enmarcar",
    "sg:phone":"+34 972 27 00 81",
    "sg:postcode":"17800",
    "sg:province":"Girona",
    "wof:name":"Portell Montero Jordi",
    "wof:placetype":"venue"
},
  "geometry": {"coordinates":[2.4842131138,42.1812705994],"type":"Point"}
}