{
  "type": "Feature",
  "properties": {
    "iso:country":"ES",
    "sg:address":"Calle de Panaderia, 4",
    "sg:city":"Marbella",
    "sg:orig_category":"Confecci\u00d3n De Sombreros Y Tocados",
    "sg:phone":"+34 952 77 60 41",
    "sg:postcode":"29600",
    "sg:province":"M\u00e1laga",
    "wof:name":"Leon Espinosa Francisco Javier",
    "wof:placetype":"venue"
},
  "geometry": {"coordinates":[-4.8846168518,36.5106811523],"type":"Point"}
}