{
  "type": "Feature",
  "properties": {
    "addr:full":"Calle de Roble (del), 8 Segovia Segovia 40002",
    "addr:housenumber":"8",
    "addr:postcode":"40002",
    "addr:street":"Calle De Roble Del",
    "iso:country":"ES",
    "sg:address":"Calle de Roble (del), 8",
    "sg:city":"Segovia",
    "sg:orig_category":"Telas Y Sedas (al Por Menor)",
    "sg:phone":"+34 921 44 03 14",
    "sg:postcode":"40002",
    "sg:province":"Segovia",
    "wof:name":"Navajo Perez Eva",
    "wof:placetype":"venue"
},
  "geometry": {"coordinates":[-4.1172437668,40.944770813],"type":"Point"}
}