{
  "type": "Feature",
  "properties": {
    "iso:country":"ES",
    "sg:address":"Calle de Santa Lucia, 39",
    "sg:city":"Mora",
    "sg:orig_category":"Fabricaci\u00d3n De Quesos",
    "sg:phone":"+34 925 30 03 45",
    "sg:postcode":"45400",
    "sg:province":"Toledo",
    "wof:name":"Quesos El Chozo S.l.",
    "wof:placetype":"venue"
},
  "geometry": {"coordinates":[-3.7755639553,39.685585022],"type":"Point"}
}