{
  "type": "Feature",
  "properties": {
    "addr:full":"Cno. Vell Bunyola, 43 Pol.ind.son Castello Islas Baleares 07009",
    "addr:housenumber":"43",
    "addr:postcode":"07009",
    "addr:street":"Cno. Vell Bunyola;Islas",
    "iso:country":"ES",
    "sg:address":"Cno. Vell Bunyola, 43",
    "sg:city":"Pol.ind.son Castello",
    "sg:classifiers":[
        {
            "category":"Home & Garden",
            "subcategory":"Household Appliances",
            "type":"Retail Goods"
        }
    ],
    "sg:phone":"+34 971 29 94 50",
    "sg:postcode":"07009",
    "sg:province":"Islas Baleares",
    "sg:tags":[
        "bodega",
        "de",
        "vino",
        "acondicionamiento"
    ],
    "wof:name":"Codorniu S.a.",
    "wof:placetype":"venue"
},
  "geometry": {"coordinates":[2.6776249409,39.6072845459],"type":"Point"}
}