{
  "type": "Feature",
  "properties": {
    "iso:country":"ES",
    "sg:address":"Carr Malva, 65",
    "sg:city":"Santa Coloma De Farners",
    "sg:orig_category":"Agencias Y Agentes Comerciales, Representantes",
    "sg:phone":"+34 972 87 70 14",
    "sg:postcode":"17430",
    "sg:province":"Girona",
    "wof:name":"Casali Silvestre Maria Isabel",
    "wof:placetype":"venue"
},
  "geometry": {"coordinates":[2.6650629044,41.8586883545],"type":"Point"}
}