{
  "type": "Feature",
  "properties": {
    "iso:country":"ES",
    "sg:address":"Avgd Prat De La Riba, 59",
    "sg:city":"Lleida",
    "sg:orig_category":"M\u00c9dicos: Neumolog\u00cda",
    "sg:phone":"+34 973 23 64 10",
    "sg:postcode":"25004",
    "sg:province":"Lleida",
    "wof:name":"Vila Justribo Manuel",
    "wof:placetype":"venue"
},
  "geometry": {"coordinates":[0.6252419949,41.6216888428],"type":"Point"}
}