{
  "type": "Feature",
  "properties": {
    "addr:full":"Calle de Federico Salmon, 3 Madrid Madrid 28016",
    "addr:housenumber":"3",
    "addr:postcode":"28016",
    "addr:street":"Calle De Federico Salmon",
    "iso:country":"ES",
    "sg:address":"Calle de Federico Salmon, 3",
    "sg:city":"Madrid",
    "sg:orig_category":"Importaci\u00d3n",
    "sg:phone":"+34 913 59 02 38",
    "sg:postcode":"28016",
    "sg:province":"Madrid",
    "wof:name":"Algan Internacional S. A.",
    "wof:placetype":"venue"
},
  "geometry": {"coordinates":[-3.6681468487,40.4606437683],"type":"Point"}
}