{
  "type": "Feature",
  "properties": {
    "addr:full":"Zubiarte, 29 Huarte Navarra 31620",
    "addr:housenumber":"29",
    "addr:postcode":"31620",
    "addr:street":"Zubiarte;Navarra",
    "iso:country":"ES",
    "sg:address":"Zubiarte, 29",
    "sg:city":"Huarte",
    "sg:orig_category":"Electricidad: Instaladores",
    "sg:phone":"+34 948 33 06 07",
    "sg:postcode":"31620",
    "sg:province":"Navarra",
    "wof:name":"Electricidad Echeverria S.l.",
    "wof:placetype":"venue"
},
  "geometry": {"coordinates":[-1.590644002,42.8317756653],"type":"Point"}
}