{
  "type": "Feature",
  "properties": {
    "addr:full":"Pol. Industrial, 2 Preses Girona 17178",
    "addr:housenumber":"2",
    "addr:postcode":"17178",
    "addr:street":"Pol. Industrial",
    "iso:country":"ES",
    "sg:address":"Pol. Industrial, 2",
    "sg:city":"Preses",
    "sg:orig_category":"Quincaller\u00cda (al Por Menor)",
    "sg:phone":"+34 972 69 38 12",
    "sg:postcode":"17178",
    "sg:province":"Girona",
    "wof:name":"Canalones Y Complementos S.l.",
    "wof:placetype":"venue"
},
  "geometry": {"coordinates":[2.4583799839,42.1440010071],"type":"Point"}
}