{
  "type": "Feature",
  "properties": {
    "addr:full":"Pl Carles Iii (de), 40 S. Carles Rapita Tarragona 43540",
    "addr:housenumber":"40",
    "addr:postcode":"43540",
    "addr:street":"Pl Carles Iii De;S. Carles Rapita",
    "iso:country":"ES",
    "sg:address":"Pl Carles Iii (de), 40",
    "sg:city":"S. Carles Rapita",
    "sg:orig_category":"Ropa Para Caballeros (al Por Menor)",
    "sg:phone":"+34 977 74 01 16",
    "sg:postcode":"43540",
    "sg:province":"Tarragona",
    "wof:name":"Carles Balague Lazaro",
    "wof:placetype":"venue"
},
  "geometry": {"coordinates":[0.5930380225,40.6196060181],"type":"Point"}
}