{
  "type": "Feature",
  "properties": {
    "addr:full":"Calle de Gutenberg, 15 Zaragoza Zaragoza 50015",
    "addr:housenumber":"15",
    "addr:postcode":"50015",
    "addr:street":"Calle De Gutenberg",
    "iso:country":"ES",
    "sg:address":"Calle de Gutenberg, 15",
    "sg:city":"Zaragoza",
    "sg:orig_category":"Mec\u00c1nico Del Autom\u00d3vil",
    "sg:phone":"+34 976 52 25 03",
    "sg:postcode":"50015",
    "sg:province":"Zaragoza",
    "wof:name":"Talleres Mecanica Carlos S.l.",
    "wof:placetype":"venue"
},
  "geometry": {"coordinates":[-0.8660389781,41.6780700684],"type":"Point"}
}