{
  "type": "Feature",
  "properties": {
    "addr:full":"Ctra Granada, 30 Purullena Granada 18519",
    "addr:housenumber":"30",
    "addr:postcode":"18519",
    "addr:street":"Ctra Granada",
    "iso:country":"ES",
    "sg:address":"Ctra Granada, 30",
    "sg:city":"Purullena",
    "sg:orig_category":"Albergues",
    "sg:phone":"+34 958 69 01 54",
    "sg:postcode":"18519",
    "sg:province":"Granada",
    "wof:name":"Sanchez Praena Mari Luz",
    "wof:placetype":"venue"
},
  "geometry": {"coordinates":[-3.1862640381,37.31615448],"type":"Point"}
}