{
  "type": "Feature",
  "properties": {
    "addr:full":"C/ Esglesia, 1 Cerdanyola Valles Barcelona 08290",
    "addr:housenumber":"1",
    "addr:postcode":"08290",
    "addr:street":"C / Esglesia;Valles Barcelona",
    "iso:country":"ES",
    "sg:address":"C/ Esglesia, 1",
    "sg:city":"Cerdanyola Valles",
    "sg:orig_category":"Cajas De Ahorro",
    "sg:phone":"+34 936 92 19 25",
    "sg:postcode":"08290",
    "sg:province":"Barcelona",
    "wof:name":"Caixa D'estalvis Sabadell",
    "wof:placetype":"venue"
},
  "geometry": {"coordinates":[2.1470150948,41.4924812317],"type":"Point"}
}