{
  "type": "Feature",
  "properties": {
    "addr:full":"Carrer de Maresme, 261 Barcelona Barcelona 08020",
    "addr:housenumber":"261",
    "addr:postcode":"08020",
    "addr:street":"Carrer De Maresme",
    "iso:country":"ES",
    "sg:address":"Carrer de Maresme, 261",
    "sg:city":"Barcelona",
    "sg:orig_category":"Supermercados Y Hipermercados",
    "sg:phone":"+34 933 13 69 98",
    "sg:postcode":"08020",
    "sg:province":"Barcelona",
    "wof:name":"Rodriguez Gonzalez Gloria",
    "wof:placetype":"venue"
},
  "geometry": {"coordinates":[2.2021460533,41.4223556519],"type":"Point"}
}