{
  "type": "Feature",
  "properties": {
    "addr:full":"Barrosa, 39 Barrosa Pontevedra 36979",
    "addr:housenumber":"39",
    "addr:postcode":"36979",
    "addr:street":"Barrosa",
    "iso:country":"ES",
    "sg:address":"Barrosa, 39",
    "sg:city":"Barrosa",
    "sg:orig_category":"Molduras, Junquillos, Listones Y Molduras Perforadas",
    "sg:phone":"+34 986 72 37 62",
    "sg:postcode":"36979",
    "sg:province":"Pontevedra",
    "wof:name":"Rodriguez Barcia Jose Ramon",
    "wof:placetype":"venue"
},
  "geometry": {"coordinates":[-8.8151941299,42.4157600403],"type":"Point"}
}