{
  "type": "Feature",
  "properties": {
    "iso:country":"ES",
    "sg:address":"Benjamin Franklin, S/n",
    "sg:city":"Gijon",
    "sg:orig_category":"Empresas De Carpinter\u00cda Met\u00c1lica",
    "sg:phone":"+34 985 30 73 58",
    "sg:postcode":"33211",
    "sg:province":"Asturias",
    "wof:name":"Aluminios Dieguez S.l.",
    "wof:placetype":"venue"
},
  "geometry": {"coordinates":[-5.6924033165,43.5053443909],"type":"Point"}
}