{
  "type": "Feature",
  "properties": {
    "addr:full":"Calle de Real, 98 Corral Almaguer Toledo 45880",
    "addr:housenumber":"98",
    "addr:postcode":"45880",
    "addr:street":"Calle De Real",
    "iso:country":"ES",
    "sg:address":"Calle de Real, 98",
    "sg:city":"Corral Almaguer",
    "sg:orig_category":"\u00d3ptica: Instrumentos (fabricaci\u00d3n)",
    "sg:phone":"+34 925 20 72 00",
    "sg:postcode":"45880",
    "sg:province":"Toledo",
    "wof:name":"Gonzalez Moreno Alfredo",
    "wof:placetype":"venue"
},
  "geometry": {"coordinates":[-3.1651539803,39.7596817017],"type":"Point"}
}