{
  "type": "Feature",
  "properties": {
    "iso:country":"ES",
    "sg:address":"Calle de Ramon Y Cajal, 3",
    "sg:city":"Laguna Duero",
    "sg:orig_category":"Guarder\u00cdas",
    "sg:phone":"+34 983 54 28 50",
    "sg:postcode":"47140",
    "sg:province":"Valladolid",
    "wof:name":"Mu\u00f1oz-repiso Fernandez Loida",
    "wof:placetype":"venue"
},
  "geometry": {"coordinates":[-4.724419117,41.580581665],"type":"Point"}
}