{
  "type": "Feature",
  "properties": {
    "addr:full":"Calle de Alemania, 22 Alcala Henares Madrid 28802",
    "addr:housenumber":"22",
    "addr:postcode":"28802",
    "addr:street":"Calle De Alemania",
    "iso:country":"ES",
    "sg:address":"Calle de Alemania, 22",
    "sg:city":"Alcala Henares",
    "sg:orig_category":"Transporte En General",
    "sg:phone":"+34 918 83 60 49",
    "sg:postcode":"28802",
    "sg:province":"Madrid",
    "sg:website":"www.lasin.es",
    "wof:name":"Sistemas Lasin Sl",
    "wof:placetype":"venue"
},
  "geometry": {"coordinates":[9.0760097504,52.7750091553],"type":"Point"}
}