{
  "type": "Feature",
  "properties": {
    "iso:country":"ES",
    "sg:address":"Rua San Francisco, 8",
    "sg:city":"Cambados",
    "sg:orig_category":"Comercio, Reparaci\u00d3n De Motocicletas, Bicicletas Y Piezas Sueltas",
    "sg:phone":"+34 986 52 08 87",
    "sg:postcode":"36630",
    "sg:province":"Pontevedra",
    "wof:name":"Noya Pi\u00f1eiro Francisco Javier",
    "wof:placetype":"venue"
},
  "geometry": {"coordinates":[-8.7817115784,42.2641181946],"type":"Point"}
}