{
  "type": "Feature",
  "properties": {
    "addr:full":"Calle de Guardia Civil, 25 Guijuelo Salamanca 37770",
    "addr:housenumber":"25",
    "addr:postcode":"37770",
    "addr:street":"Calle De Guardia Civil",
    "iso:country":"ES",
    "sg:address":"Calle de Guardia Civil, 25",
    "sg:city":"Guijuelo",
    "sg:orig_category":"Charcuter\u00cdas (al Por Mayor)",
    "sg:phone":"+34 923 58 16 01",
    "sg:postcode":"37770",
    "sg:province":"Salamanca",
    "wof:name":"Moises Alonso Martin S.l.",
    "wof:placetype":"venue"
},
  "geometry": {"coordinates":[-5.6694030762,40.5562820435],"type":"Point"}
}