{
  "type": "Feature",
  "properties": {
    "iso:country":"ES",
    "sg:address":"Plaz Nueva, 7",
    "sg:city":"Bilbao",
    "sg:orig_category":"Asociaciones, Instituciones De Consumidores Y Usuarios",
    "sg:phone":"+34 944 15 00 50",
    "sg:postcode":"48005",
    "sg:province":"Vizcaya",
    "wof:name":"Organizacion De Consumidores Y Usuarios Vasca Eka",
    "wof:placetype":"venue"
},
  "geometry": {"coordinates":[-2.9222950935,43.2588539124],"type":"Point"}
}