{
  "type": "Feature",
  "properties": {
    "iso:country":"ES",
    "sg:address":"Ctra Santo Domingo, 50",
    "sg:city":"Bilbao",
    "sg:orig_category":"Asistencia Y Seguros De Automovilistas Y Turistas",
    "sg:phone":"+34 944 13 24 80",
    "sg:postcode":"48015",
    "sg:province":"Vizcaya",
    "wof:name":"Gruas Iratxe S. L.",
    "wof:placetype":"venue"
},
  "geometry": {"coordinates":[-2.900980711,43.2779426575],"type":"Point"}
}