{
  "type": "Feature",
  "properties": {
    "iso:country":"ES",
    "sg:address":"Av Mare De Deu De Montserrat, 5",
    "sg:city":"S. Joan Despi",
    "sg:orig_category":"Papel (al Por Mayor)",
    "sg:phone":"+34 934 80 80 39",
    "sg:postcode":"08970",
    "sg:province":"Barcelona",
    "wof:name":"Casas Mara\u00f1on Enrique",
    "wof:placetype":"venue"
},
  "geometry": {"coordinates":[2.0654399395,41.3688316345],"type":"Point"}
}