{
  "type": "Feature",
  "properties": {
    "iso:country":"ES",
    "sg:address":"Calle de Traviesa, 2",
    "sg:city":"Paredes Nava",
    "sg:orig_category":"Promotores Constructores",
    "sg:phone":"+34 979 83 06 98",
    "sg:postcode":"34300",
    "sg:province":"Palencia",
    "wof:name":"Pajares Alvarez Eugenio",
    "wof:placetype":"venue"
},
  "geometry": {"coordinates":[-4.6902828217,42.1510505676],"type":"Point"}
}