{
  "type": "Feature",
  "properties": {
    "iso:country":"ES",
    "sg:address":"F. Gorriti, 35",
    "sg:city":"Iru\u00f1a",
    "sg:orig_category":"Librer\u00cdas",
    "sg:phone":"+34 948 24 81 27",
    "sg:postcode":"31004",
    "sg:province":"Navarra",
    "wof:name":"Video Club Amaya S. Cv.",
    "wof:placetype":"venue"
},
  "geometry": {"coordinates":[-1.6366620064,42.8114051819],"type":"Point"}
}