{
  "type": "Feature",
  "properties": {
    "addr:full":"Calle de Isidoro Mi\u00d1on, 10 Andujar Ja\u00e9n 23740",
    "addr:housenumber":"10",
    "addr:postcode":"23740",
    "addr:street":"Calle De Isidoro Min\u0303On",
    "iso:country":"ES",
    "sg:address":"Calle de Isidoro Mi\u00d1on, 10",
    "sg:city":"Andujar",
    "sg:orig_category":"Urbanistas",
    "sg:phone":"+34 953 50 15 63",
    "sg:postcode":"23740",
    "sg:province":"Ja\u00e9n",
    "wof:name":"Rubio Marmol Javier",
    "wof:placetype":"venue"
},
  "geometry": {"coordinates":[-4.0563759804,38.0390014648],"type":"Point"}
}