{
  "type": "Feature",
  "properties": {
    "addr:full":"Carrer de Vall D'ordesa, 31 Barcelona Barcelona 08031",
    "addr:housenumber":"31",
    "addr:postcode":"08031",
    "addr:street":"Carrer De Vall D'Ordesa",
    "iso:country":"ES",
    "sg:address":"Carrer de Vall D'ordesa, 31",
    "sg:city":"Barcelona",
    "sg:orig_category":"Iglesias Evang\u00c9licas",
    "sg:phone":"+34 934 20 56 04",
    "sg:postcode":"08031",
    "sg:province":"Barcelona",
    "wof:name":"Asambleas De Dios De Espa\u00f1a",
    "wof:placetype":"venue"
},
  "geometry": {"coordinates":[2.1643993855,41.4315338135],"type":"Point"}
}