{
  "type": "Feature",
  "properties": {
    "addr:full":"Calle de Mariano Lui\u00d1a, 18 Navia Asturias 33710",
    "addr:housenumber":"18",
    "addr:postcode":"33710",
    "addr:street":"Calle De Mariano Luin\u0303A",
    "iso:country":"ES",
    "sg:address":"Calle de Mariano Lui\u00d1a, 18",
    "sg:city":"Navia",
    "sg:orig_category":"Panader\u00cdas, Panader\u00cdas",
    "sg:phone":"+34 985 63 14 53",
    "sg:postcode":"33710",
    "sg:province":"Asturias",
    "wof:name":"Pasteleria Bomboneria Santa Maria S.l.",
    "wof:placetype":"venue"
},
  "geometry": {"coordinates":[-6.7235212326,43.5395393372],"type":"Point"}
}