{
  "type": "Feature",
  "properties": {
    "iso:country":"ES",
    "sg:address":"Calle de Goya, 5",
    "sg:city":"Pedro Mu\u00e7oz",
    "sg:orig_category":"Productores Recolectores, Venta Directa De Vinos",
    "sg:phone":"+34 926 58 60 27",
    "sg:postcode":"13620",
    "sg:province":"Ciudad Real",
    "wof:name":"Grupo Cervantino S.a.t. Num. 3760",
    "wof:placetype":"venue"
},
  "geometry": {"coordinates":[-2.9516630173,39.4006271362],"type":"Point"}
}