{
  "type": "Feature",
  "properties": {
    "iso:country":"ES",
    "sg:address":"C/ Concepcion Arenal, 95",
    "sg:city":"Elche",
    "sg:orig_category":"Propiedad Industrial: Patentes De Inventos, Marcas, Modelos, Dise\u00d1os",
    "sg:phone":"+34 966 67 55 73",
    "sg:postcode":"03201",
    "sg:province":"Alicante",
    "sg:website":"www.ibidem.es",
    "wof:name":"Ibidem Consulting S.l.",
    "wof:placetype":"venue"
},
  "geometry": {"coordinates":[-0.7073889971,38.2624092102],"type":"Point"}
}