{
  "type": "Feature",
  "properties": {
    "iso:country":"ES",
    "sg:address":"Carrer de Camp De Mar, 16",
    "sg:city":"Premia Mar",
    "sg:classifiers":[
        {
            "category":"Tea Room",
            "subcategory":"None",
            "type":"Food & Drink"
        }
    ],
    "sg:phone":"+34 937 51 11 78",
    "sg:postcode":"08330",
    "sg:province":"Barcelona",
    "sg:tags":[
        "snack"
    ],
    "wof:name":"Soto Aguilera Trinidad",
    "wof:placetype":"venue"
},
  "geometry": {"coordinates":[2.3738191128,41.4944877625],"type":"Point"}
}