{
  "type": "Feature",
  "properties": {
    "iso:country":"ES",
    "sg:address":"Calle de San Isidro, 12",
    "sg:city":"Tarancon",
    "sg:orig_category":"Agencias Y Agentes Comerciales, Representantes",
    "sg:phone":"+34 969 32 00 79",
    "sg:postcode":"16400",
    "sg:province":"Cuenca",
    "wof:name":"De Los Rios Serrano Vicente",
    "wof:placetype":"venue"
},
  "geometry": {"coordinates":[-3.0140690804,40.0063934326],"type":"Point"}
}