{
  "type": "Feature",
  "properties": {
    "addr:full":"Rua Curros Enriquez, 14 Carballi\u00f1o Ourense 32500",
    "addr:housenumber":"14",
    "addr:postcode":"32500",
    "addr:street":"Rua Curros Enriquez",
    "iso:country":"ES",
    "sg:address":"Rua Curros Enriquez, 14",
    "sg:city":"Carballi\u00f1o",
    "sg:orig_category":"Panader\u00cdas, Panader\u00cdas",
    "sg:phone":"+34 988 27 31 22",
    "sg:postcode":"32500",
    "sg:province":"Ourense",
    "wof:name":"De La Iglesia Barros Jose Manuel",
    "wof:placetype":"venue"
},
  "geometry": {"coordinates":[-8.0758314133,42.4324302673],"type":"Point"}
}