{
  "type": "Feature",
  "properties": {
    "iso:country":"ES",
    "sg:address":"Calle de Bravo Murillo, 211",
    "sg:city":"Madrid",
    "sg:orig_category":"Inmobiliaria (agencias)",
    "sg:phone":"+34 914 59 06 93",
    "sg:postcode":"28020",
    "sg:province":"Madrid",
    "wof:name":"Encaru",
    "wof:placetype":"venue"
},
  "geometry": {"coordinates":[-3.7024035454,40.4559211731],"type":"Point"}
}