{
  "type": "Feature",
  "properties": {
    "iso:country":"ES",
    "sg:address":"Calle de Jose Luis Mesias Iglesias, 5",
    "sg:city":"Almendralejo",
    "sg:orig_category":"Sociedades, Compa\u00d1\u00cdas Aseguradoras",
    "sg:phone":"+34 924 67 17 19",
    "sg:postcode":"06200",
    "sg:province":"Badajoz",
    "wof:name":"Jose Cortes Ortiz S.l.",
    "wof:placetype":"venue"
},
  "geometry": {"coordinates":[-6.402053833,38.6836509705],"type":"Point"}
}