{
  "type": "Feature",
  "properties": {
    "iso:country":"ES",
    "sg:address":"Calle de Parque Andalucia, 7",
    "sg:city":"Velez-malaga",
    "sg:orig_category":"Librer\u00cdas",
    "sg:phone":"+34 952 50 10 15",
    "sg:postcode":"29700",
    "sg:province":"M\u00e1laga",
    "wof:name":"Libreria Yerma S.l.",
    "wof:placetype":"venue"
},
  "geometry": {"coordinates":[-4.098772049,36.7737045288],"type":"Point"}
}