{
  "type": "Feature",
  "properties": {
    "addr:full":"Avda Federico Garcia Lorca, 3 Arroyo De La Miel-benalmadena Costa M\u00e1laga 29630",
    "addr:housenumber":"3",
    "addr:postcode":"29630",
    "addr:street":"Avda Federico Garcia Lorca;Arroyo De La Miel-Benalmadena Costa Ma\u0301Laga",
    "iso:country":"ES",
    "sg:address":"Avda Federico Garcia Lorca, 3",
    "sg:city":"Arroyo De La Miel-benalmadena Costa",
    "sg:orig_category":"Supermercados Y Hipermercados",
    "sg:phone":"+34 952 44 08 28",
    "sg:postcode":"29630",
    "sg:province":"M\u00e1laga",
    "wof:name":"Granja De San Martin S.l.",
    "wof:placetype":"venue"
},
  "geometry": {"coordinates":[-4.526365757,36.591545105],"type":"Point"}
}