{
  "type": "Feature",
  "properties": {
    "iso:country":"ES",
    "sg:address":"Avda Cipreses, 3",
    "sg:city":"Utiel",
    "sg:orig_category":"Muebles, Minoristas",
    "sg:phone":"+34 962 17 05 36",
    "sg:postcode":"46300",
    "sg:province":"Valencia",
    "wof:name":"Viana Herrera Francisco",
    "wof:placetype":"venue"
},
  "geometry": {"coordinates":[-1.2005059719,39.5702171326],"type":"Point"}
}