{
  "type": "Feature",
  "properties": {
    "addr:full":"Arenteiro, 21 Arenteiro Ourense 32137",
    "addr:housenumber":"21",
    "addr:postcode":"32137",
    "addr:street":"Arenteiro",
    "iso:country":"ES",
    "sg:address":"Arenteiro, 21",
    "sg:city":"Arenteiro",
    "sg:orig_category":"Barnizadores",
    "sg:phone":"+34 988 40 33 38",
    "sg:postcode":"32137",
    "sg:province":"Ourense",
    "wof:name":"Vernizados Irmans Otero Sll",
    "wof:placetype":"venue"
},
  "geometry": {"coordinates":[-7.9983568192,42.49061203],"type":"Point"}
}