{
  "type": "Feature",
  "properties": {
    "addr:full":"Carrer de Cami Ral Del Camp De Sa Mar, 25 Arenys Mar Barcelona 08350",
    "addr:housenumber":"25",
    "addr:postcode":"08350",
    "addr:street":"Carrer De;Ral Del Camp De Sa Mar",
    "iso:country":"ES",
    "sg:address":"Carrer de Cami Ral Del Camp De Sa Mar, 25",
    "sg:city":"Arenys Mar",
    "sg:orig_category":"Textil",
    "sg:phone":"+34 937 92 11 94",
    "sg:postcode":"08350",
    "sg:province":"Barcelona",
    "wof:name":"Rebollo Martinez Pedro",
    "wof:placetype":"venue"
},
  "geometry": {"coordinates":[2.548361063,41.5822410583],"type":"Point"}
}