{
  "type": "Feature",
  "properties": {
    "addr:full":"Carrer de Enten\u00c7a, 15 Barcelona Barcelona 08015",
    "addr:housenumber":"15",
    "addr:postcode":"08015",
    "addr:street":"Carrer De Entenc\u0327A",
    "iso:country":"ES",
    "sg:address":"Carrer de Enten\u00c7a, 15",
    "sg:city":"Barcelona",
    "sg:orig_category":"Ropa Para Ni\u00d1os (al Por Menor)",
    "sg:phone":"+34 933 25 24 69",
    "sg:postcode":"08015",
    "sg:province":"Barcelona",
    "wof:name":"Bernabeu Castellanos Montserrat",
    "wof:placetype":"venue"
},
  "geometry": {"coordinates":[2.155411005,41.3758239746],"type":"Point"}
}