{
  "type": "Feature",
  "properties": {
    "addr:full":"Calle de La Rioja, 13 Madrid Madrid 28042",
    "addr:housenumber":"13",
    "addr:postcode":"madrid;28042",
    "addr:street":"Calle De La Rioja",
    "iso:country":"ES",
    "sg:address":"Calle de La Rioja, 13",
    "sg:city":"Madrid",
    "sg:orig_category":"Inmobiliaria (agencias)",
    "sg:phone":"+34 917 47 08 21",
    "sg:postcode":"28042",
    "sg:province":"Madrid",
    "sg:website":"www.comprarcasa.com",
    "wof:name":"Lady Casa Asesores Inmobiliarios S.l.",
    "wof:placetype":"venue"
},
  "geometry": {"coordinates":[-3.5880486965,40.457988739],"type":"Point"}
}