{
  "type": "Feature",
  "properties": {
    "addr:full":"Ctra Burgos-portugal, Km. 0114,6 Cigales Valladolid 47270",
    "addr:postcode":"47270",
    "addr:street":"Ctra Burgos-Portugal Km. 0114,6",
    "iso:country":"ES",
    "sg:address":"Ctra Burgos-portugal, Km. 0114,6",
    "sg:city":"Cigales",
    "sg:orig_category":"Postigos, Persianas Y Celos\u00cdas",
    "sg:phone":"+34 983 58 60 01",
    "sg:postcode":"47270",
    "sg:province":"Valladolid",
    "wof:name":"Faperplast S.a.",
    "wof:placetype":"venue"
},
  "geometry": {"coordinates":[-4.6960468292,41.7578849792],"type":"Point"}
}