{
  "type": "Feature",
  "properties": {
    "iso:country":"ES",
    "sg:address":"Calle de Comedia, 6",
    "sg:city":"Puerto De Santa Maria",
    "sg:orig_category":"Ense\u00d1ante, Direcci\u00d3n",
    "sg:phone":"+34 956 85 48 28",
    "sg:postcode":"11500",
    "sg:province":"C\u00e1diz",
    "wof:name":"Jimenez Rodriguez Guillermo",
    "wof:placetype":"venue"
},
  "geometry": {"coordinates":[-6.2269763947,36.6302452087],"type":"Point"}
}