{
  "type": "Feature",
  "properties": {
    "addr:full":"Carrer de Morato (dels), S/n Vic Barcelona 08500",
    "addr:postcode":"08500",
    "addr:street":"Carrer De Morato Dels S / N",
    "iso:country":"ES",
    "sg:address":"Carrer de Morato (dels), S/n",
    "sg:city":"Vic",
    "sg:orig_category":"Carnicer\u00cdas, Carnicer\u00cdas",
    "sg:phone":"+34 938 89 50 54",
    "sg:postcode":"08500",
    "sg:province":"Barcelona",
    "wof:name":"Andreu Trabal Laura",
    "wof:placetype":"venue"
},
  "geometry": {"coordinates":[2.2505638599,41.929889679],"type":"Point"}
}