{
  "type": "Feature",
  "properties": {
    "addr:full":"Calle de Aluminio, 280 Valladolid Valladolid 47012",
    "addr:housenumber":"280",
    "addr:postcode":"47012",
    "addr:street":"Calle De Aluminio",
    "iso:country":"ES",
    "sg:address":"Calle de Aluminio, 280",
    "sg:city":"Valladolid",
    "sg:orig_category":"Empresas De Limpieza",
    "sg:phone":"+34 983 21 24 40",
    "sg:postcode":"47012",
    "sg:province":"Valladolid",
    "wof:name":"Servicios Contenedores Higienicos Sanitarios S.a.",
    "wof:placetype":"venue"
},
  "geometry": {"coordinates":[-4.7138371468,41.620475769],"type":"Point"}
}