{
  "type": "Feature",
  "properties": {
    "iso:country":"ES",
    "sg:address":"Avda Campo De Calatrava, 31",
    "sg:city":"Madrid",
    "sg:orig_category":"Papeler\u00cdas, Librer\u00cdas",
    "sg:phone":"+34 917 35 29 39",
    "sg:postcode":"28034",
    "sg:province":"Madrid",
    "wof:name":"Sipe Suministros Integrales S.l.",
    "wof:placetype":"venue"
},
  "geometry": {"coordinates":[-3.6883890629,40.5008163452],"type":"Point"}
}