{
  "type": "Feature",
  "properties": {
    "iso:country":"ES",
    "sg:address":"Avda Gomez Laguna, 25",
    "sg:city":"Zaragoza",
    "sg:orig_category":"Notarios",
    "sg:phone":"+34 976 45 80 63",
    "sg:postcode":"50009",
    "sg:province":"Zaragoza",
    "wof:name":"Ari\u00f1o Garcia-belenguer Augusto",
    "wof:placetype":"venue"
},
  "geometry": {"coordinates":[-0.9100835919,41.6416778564],"type":"Point"}
}