{
  "type": "Feature",
  "properties": {
    "addr:full":"Calle de Sacramento Esteve, 10 Xirivella Valencia 46950",
    "addr:housenumber":"10",
    "addr:postcode":"46950",
    "addr:street":"Calle De Sacramento Esteve",
    "iso:country":"ES",
    "sg:address":"Calle de Sacramento Esteve, 10",
    "sg:city":"Xirivella",
    "sg:orig_category":"Centros De Educaci\u00d3n Especial",
    "sg:phone":"+34 963 13 20 53",
    "sg:postcode":"46950",
    "sg:province":"Valencia",
    "wof:name":"Generalitat Valenciana",
    "wof:placetype":"venue"
},
  "geometry": {"coordinates":[-0.4291119874,39.4652290344],"type":"Point"}
}