{
  "type": "Feature",
  "properties": {
    "addr:full":"Av Parc, 1 Granollers Barcelona 08402",
    "addr:housenumber":"1",
    "addr:postcode":"08402",
    "addr:street":"Av Parc",
    "iso:country":"ES",
    "sg:address":"Av Parc, 1",
    "sg:city":"Granollers",
    "sg:orig_category":"M\u00c9dicos: Ginecolog\u00cda Y Obstetricia",
    "sg:phone":"+34 938 70 96 60",
    "sg:postcode":"08402",
    "sg:province":"Barcelona",
    "wof:name":"Bermudez Flores Jorge Rene",
    "wof:placetype":"venue"
},
  "geometry": {"coordinates":[2.290405035,41.6061019897],"type":"Point"}
}