{
  "type": "Feature",
  "properties": {
    "iso:country":"ES",
    "sg:address":"Avda Andes (de Los), 13",
    "sg:city":"Fuenlabrada",
    "sg:orig_category":"Farmacias",
    "sg:phone":"+34 916 15 18 65",
    "sg:postcode":"28945",
    "sg:province":"Madrid",
    "wof:name":"Ramos Cerezo Felipe Jose",
    "wof:placetype":"venue"
},
  "geometry": {"coordinates":[-3.787072897,40.2952423096],"type":"Point"}
}