{
  "type": "Feature",
  "properties": {
    "iso:country":"ES",
    "sg:address":"Calle de Arzobispo Barroeta, 37",
    "sg:city":"Ezcaray",
    "sg:orig_category":"Carnicer\u00cdas, Carnicer\u00cdas",
    "sg:phone":"+34 941 42 73 40",
    "sg:postcode":"26280",
    "sg:province":"La Rioja",
    "wof:name":"Valle Perez-vazquez Angelita",
    "wof:placetype":"venue"
},
  "geometry": {"coordinates":[-3.0161020756,42.3244895935],"type":"Point"}
}