{
  "type": "Feature",
  "properties": {
    "addr:full":"Calle de Amazabal, S/n Leitza Navarra 31880",
    "addr:housenumber":"s",
    "addr:postcode":"31880",
    "addr:street":"Calle De Amazabal;/ N",
    "iso:country":"ES",
    "sg:address":"Calle de Amazabal, S/n",
    "sg:city":"Leitza",
    "sg:orig_category":"Centros De Educaci\u00d3n Especial",
    "sg:phone":"+34 948 51 02 76",
    "sg:postcode":"31880",
    "sg:province":"Navarra",
    "wof:name":"Zabaleta Zabaleta Maria",
    "wof:placetype":"venue"
},
  "geometry": {"coordinates":[-1.9129650593,43.0833015442],"type":"Point"}
}