{
  "type": "Feature",
  "properties": {
    "iso:country":"ES",
    "sg:address":"Carrer de Eugeni D'ors, 12",
    "sg:city":"Vilafranca Penedes",
    "sg:orig_category":"Asociaciones Y Clubs Deportivos",
    "sg:phone":"+34 938 90 12 46",
    "sg:postcode":"08720",
    "sg:province":"Barcelona",
    "wof:name":"Esport Esprint S.l.",
    "wof:placetype":"venue"
},
  "geometry": {"coordinates":[1.6928533316,41.3444595337],"type":"Point"}
}