{
  "type": "Feature",
  "properties": {
    "addr:full":"Calle de Real, 55 Estacion Madrid 28400",
    "addr:housenumber":"55",
    "addr:postcode":"28400",
    "addr:street":"Calle De Real",
    "iso:country":"ES",
    "sg:address":"Calle de Real, 55",
    "sg:city":"Estacion",
    "sg:classifiers":[
        {
            "category":"Autos & Motor Vehicles",
            "subcategory":"Automobile Sales",
            "type":"Retail Goods"
        }
    ],
    "sg:phone":"+34 918 50 61 53",
    "sg:postcode":"28400",
    "sg:province":"Madrid",
    "wof:name":"Sociedad Cooperativa Limitada M. M.",
    "wof:placetype":"venue"
},
  "geometry": {"coordinates":[-3.9919650555,40.6455612183],"type":"Point"}
}