{
  "type": "Feature",
  "properties": {
    "iso:country":"ES",
    "sg:address":"Carrer de Jaume Balmes, 59",
    "sg:city":"S. Boi Llobregat",
    "sg:orig_category":"Fabricaci\u00d3n, Distribuci\u00d3n De Material Para La Climatizaci\u00d3n, Aireaci\u00d3n Y Ventilaci\u00d3n",
    "sg:phone":"+34 936 52 96 10",
    "sg:postcode":"08830",
    "sg:province":"Barcelona",
    "sg:website":"www.handteibericasl.com",
    "wof:name":"Tecnologia Ambiental Hadte Iberica S.l.",
    "wof:placetype":"venue"
},
  "geometry": {"coordinates":[2.0438780785,41.3369140625],"type":"Point"}
}