{
  "type": "Feature",
  "properties": {
    "addr:full":"C/ Llobregat, 22 Ripollet Barcelona 08291",
    "addr:housenumber":"22",
    "addr:postcode":"08291",
    "addr:street":"C / Llobregat",
    "iso:country":"ES",
    "sg:address":"C/ Llobregat, 22",
    "sg:city":"Ripollet",
    "sg:orig_category":"Metales (labores, Pulido)",
    "sg:phone":"+34 935 80 84 12",
    "sg:postcode":"08291",
    "sg:province":"Barcelona",
    "wof:name":"Mecanizats Albiac Freixa S.l.",
    "wof:placetype":"venue"
},
  "geometry": {"coordinates":[2.1569299698,41.4926986694],"type":"Point"}
}