{
  "type": "Feature",
  "properties": {
    "iso:country":"ES",
    "sg:address":"Av Borbo, 72",
    "sg:city":"Barcelona",
    "sg:orig_category":"Tejidos (al Por Menor)",
    "sg:phone":"+34 933 49 36 30",
    "sg:postcode":"08016",
    "sg:province":"Barcelona",
    "wof:name":"Cistero Bahima Jordi",
    "wof:placetype":"venue"
},
  "geometry": {"coordinates":[2.1746211052,41.4287490845],"type":"Point"}
}