{
  "type": "Feature",
  "properties": {
    "iso:country":"ES",
    "sg:address":"Calle de Salobral B (cha), 20",
    "sg:city":"Madrid",
    "sg:orig_category":"Cr\u00cda De Perros Y De Gatos",
    "sg:phone":"+34 913 41 01 85",
    "sg:postcode":"28041",
    "sg:province":"Madrid",
    "wof:name":"Zamorano Garcia Yobanka",
    "wof:placetype":"venue"
},
  "geometry": {"coordinates":[-3.6978263855,40.3570404053],"type":"Point"}
}