{
  "type": "Feature",
  "properties": {
    "addr:full":"Calle de Real, 173 S. Fernando C\u00e1diz 11100",
    "addr:housenumber":"173",
    "addr:postcode":"11100",
    "addr:street":"Calle De Real;S. Fernando Ca\u0301Diz",
    "iso:country":"ES",
    "sg:address":"Calle de Real, 173",
    "sg:city":"S. Fernando",
    "sg:orig_category":"Ropa Para Se\u00d1oras (al Por Menor)",
    "sg:phone":"+34 956 59 70 21",
    "sg:postcode":"11100",
    "sg:province":"C\u00e1diz",
    "wof:name":"Aparicio Segundo Angel",
    "wof:placetype":"venue"
},
  "geometry": {"coordinates":[-6.2008490562,36.4606781006],"type":"Point"}
}