{
  "type": "Feature",
  "properties": {
    "addr:full":"Calle de Maspe, 2 Iurreta Vizcaya 48215",
    "addr:housenumber":"2",
    "addr:postcode":"48215",
    "addr:street":"Calle De Maspe",
    "iso:country":"ES",
    "sg:address":"Calle de Maspe, 2",
    "sg:city":"Iurreta",
    "sg:orig_category":"Peluquer\u00cdas, Peluquer\u00cda Mixta",
    "sg:phone":"+34 946 20 08 28",
    "sg:postcode":"48215",
    "sg:province":"Vizcaya",
    "wof:name":"Itxaso Albizuri Mendizabal",
    "wof:placetype":"venue"
},
  "geometry": {"coordinates":[-2.6411969662,43.1749229431],"type":"Point"}
}