{
  "type": "Feature",
  "properties": {
    "iso:country":"ES",
    "sg:address":"Calle de Madera, 32",
    "sg:city":"Madrid",
    "sg:orig_category":"Peluquer\u00cdas, Peluquer\u00cda Mixta",
    "sg:phone":"+34 915 22 28 31",
    "sg:postcode":"28004",
    "sg:province":"Madrid",
    "wof:name":"Alonso Rodriguez Maria Elena",
    "wof:placetype":"venue"
},
  "geometry": {"coordinates":[-3.7037215233,40.4241523743],"type":"Point"}
}