{
  "type": "Feature",
  "properties": {
    "addr:full":"Carrer de Andreu Feliu, 32 Palma Islas Baleares 07010",
    "addr:housenumber":"32",
    "addr:postcode":"07010",
    "addr:street":"Carrer De Andreu Feliu",
    "iso:country":"ES",
    "sg:address":"Carrer de Andreu Feliu, 32",
    "sg:city":"Palma",
    "sg:orig_category":"Servicios Diversos",
    "sg:phone":"+34 971 75 25 47",
    "sg:postcode":"07010",
    "sg:province":"Islas Baleares",
    "wof:name":"Setecal S.l.",
    "wof:placetype":"venue"
},
  "geometry": {"coordinates":[2.647300005,39.5831565857],"type":"Point"}
}