{
  "type": "Feature",
  "properties": {
    "iso:country":"ES",
    "sg:address":"Calle de Infanta Beatriz, 3",
    "sg:city":"Sanlucar De Barrameda",
    "sg:orig_category":"Papeler\u00cdas, Librer\u00cdas",
    "sg:phone":"+34 956 36 78 65",
    "sg:postcode":"11540",
    "sg:province":"C\u00e1diz",
    "wof:name":"Calvo Torres Milagrosa",
    "wof:placetype":"venue"
},
  "geometry": {"coordinates":[-6.3545050621,36.7811698914],"type":"Point"}
}