{
  "type": "Feature",
  "properties": {
    "iso:country":"ES",
    "sg:address":"Calle de Zamakoa, 23",
    "sg:city":"Galdakao",
    "sg:orig_category":"Psic\u00d3logos",
    "sg:phone":"+34 944 57 01 63",
    "sg:postcode":"48960",
    "sg:province":"Vizcaya",
    "wof:name":"Azucena Larrea Urrutia",
    "wof:placetype":"venue"
},
  "geometry": {"coordinates":[-2.84273839,43.2326774597],"type":"Point"}
}