{
  "type": "Feature",
  "properties": {
    "addr:full":"Calle de Sierpes, 60 Sevilla Sevilla 41004",
    "addr:housenumber":"60",
    "addr:postcode":"41004",
    "addr:street":"Calle De Sierpes",
    "iso:country":"ES",
    "sg:address":"Calle de Sierpes, 60",
    "sg:city":"Sevilla",
    "sg:orig_category":"Ropa Para Se\u00d1oras (al Por Menor)",
    "sg:phone":"+34 954 50 11 00",
    "sg:postcode":"41004",
    "sg:province":"Sevilla",
    "sg:website":"www.hermesgovantes.com",
    "wof:name":"Love Child S.l.",
    "wof:placetype":"venue"
},
  "geometry": {"coordinates":[-5.9944162369,37.3901367188],"type":"Point"}
}