{
  "type": "Feature",
  "properties": {
    "addr:full":"Calle de Caleruega, 67 Madrid Madrid 28033",
    "addr:housenumber":"67",
    "addr:postcode":"madrid;28033",
    "addr:street":"Calle De Caleruega",
    "iso:country":"ES",
    "sg:address":"Calle de Caleruega, 67",
    "sg:city":"Madrid",
    "sg:orig_category":"Ingenier\u00cda, Centros De Estudios (diversos)",
    "sg:phone":"+34 917 66 18 22",
    "sg:postcode":"28033",
    "sg:province":"Madrid",
    "wof:name":"Apoyo Tecnico Y Estudios S.l.",
    "wof:placetype":"venue"
},
  "geometry": {"coordinates":[-3.6706035137,40.4824371338],"type":"Point"}
}