{
  "type": "Feature",
  "properties": {
    "iso:country":"ES",
    "sg:address":"Calle de Luis Mariano, 33",
    "sg:city":"Irun",
    "sg:orig_category":"Sociedades, Compa\u00d1\u00cdas Aseguradoras",
    "sg:phone":"+34 943 62 37 98",
    "sg:postcode":"20302",
    "sg:province":"Guip\u00f9zcoa",
    "wof:name":"Beunza Uranga S.l.",
    "wof:placetype":"venue"
},
  "geometry": {"coordinates":[-1.792075038,43.3397521973],"type":"Point"}
}