{
  "type": "Feature",
  "properties": {
    "addr:full":"Calle de Juan Alvarez Mendizabal, 30 Madrid Madrid 28008",
    "addr:housenumber":"30",
    "addr:postcode":"madrid;28008",
    "addr:street":"Calle De Juan Alvarez Mendizabal",
    "iso:country":"ES",
    "sg:address":"Calle de Juan Alvarez Mendizabal, 30",
    "sg:city":"Madrid",
    "sg:orig_category":"Electricidad: Instaladores",
    "sg:phone":"+34 915 47 43 30",
    "sg:postcode":"28008",
    "sg:province":"Madrid",
    "wof:name":"Ca\u00f1averas Garcia Antonio",
    "wof:placetype":"venue"
},
  "geometry": {"coordinates":[-3.7153759003,40.425567627],"type":"Point"}
}