{
  "type": "Feature",
  "properties": {
    "iso:country":"ES",
    "sg:address":"Avda Reyes Catolicos, 141",
    "sg:city":"Villarrobledo",
    "sg:orig_category":"Frutas Y Legumbres Frescas (al Por Mayor)",
    "sg:phone":"+34 967 14 18 51",
    "sg:postcode":"02600",
    "sg:province":"Albacete",
    "wof:name":"Grupo Sindical De Colonizacion N\u00ba 13069",
    "wof:placetype":"venue"
},
  "geometry": {"coordinates":[-2.5946490765,39.2715187073],"type":"Point"}
}