{
  "type": "Feature",
  "properties": {
    "addr:full":"Bizkaia Kalea, 63 Zarautz Guip\u00f9zcoa 20800",
    "addr:housenumber":"63",
    "addr:postcode":"20800",
    "addr:street":"Bizkaia Kalea;Guipu\u0300Zcoa",
    "iso:country":"ES",
    "sg:address":"Bizkaia Kalea, 63",
    "sg:city":"Zarautz",
    "sg:orig_category":"Muebles, Minoristas",
    "sg:phone":"+34 943 13 35 16",
    "sg:postcode":"20800",
    "sg:province":"Guip\u00f9zcoa",
    "wof:name":"Larra\u00f1aga Azpiroz Arancha",
    "wof:placetype":"venue"
},
  "geometry": {"coordinates":[-2.1646258831,43.2821769714],"type":"Point"}
}