{
  "type": "Feature",
  "properties": {
    "iso:country":"ES",
    "sg:address":"Calle de Huerto De Los Claveles, 14",
    "sg:city":"Malaga",
    "sg:orig_category":"Artes Gr\u00c1ficas, Artes Pl\u00c1sticas (curso)",
    "sg:phone":"+34 952 25 13 58",
    "sg:postcode":"29013",
    "sg:province":"M\u00e1laga",
    "wof:name":"L. Dominguez S.a.",
    "wof:placetype":"venue"
},
  "geometry": {"coordinates":[-4.4254231453,36.7283325195],"type":"Point"}
}