{
  "type": "Feature",
  "properties": {
    "addr:full":"Azara Kalea, 17 Zarautz Guip\u00f9zcoa 20800",
    "addr:housenumber":"17",
    "addr:postcode":"20800",
    "addr:street":"Azara Kalea;Guipu\u0300Zcoa",
    "iso:country":"ES",
    "sg:address":"Azara Kalea, 17",
    "sg:city":"Zarautz",
    "sg:orig_category":"Cajas Para Embalar",
    "sg:phone":"+34 943 89 55 14",
    "sg:postcode":"20800",
    "sg:province":"Guip\u00f9zcoa",
    "sg:website":"www.cajarural.com",
    "wof:name":"Caja Rural Provincial De Navarra",
    "wof:placetype":"venue"
},
  "geometry": {"coordinates":[-2.1757190228,43.286190033],"type":"Point"}
}