{
  "type": "Feature",
  "properties": {
    "addr:full":"Carr Pujol, 33 Badalona Barcelona 08911",
    "addr:housenumber":"33",
    "addr:postcode":"08911",
    "addr:street":"Carr Pujol",
    "iso:country":"ES",
    "sg:address":"Carr Pujol, 33",
    "sg:city":"Badalona",
    "sg:orig_category":"Estancos",
    "sg:phone":"+34 933 84 55 54",
    "sg:postcode":"08911",
    "sg:province":"Barcelona",
    "wof:name":"Garcia Ya\u00f1ez Ines",
    "wof:placetype":"venue"
},
  "geometry": {"coordinates":[2.2489581108,41.4462776184],"type":"Point"}
}