{
  "type": "Feature",
  "properties": {
    "iso:country":"ES",
    "sg:address":"Calle de Lopez, 1",
    "sg:city":"Desamparados",
    "sg:orig_category":"\u00d3pticos Optometristas (al Por Menor)",
    "sg:phone":"+34 965 30 53 08",
    "sg:postcode":"03312",
    "sg:province":"Alicante",
    "wof:name":"Pardo Lopez Clara Maria",
    "wof:placetype":"venue"
},
  "geometry": {"coordinates":[-0.982163012,38.0626296997],"type":"Point"}
}