{
  "type": "Feature",
  "properties": {
    "iso:country":"ES",
    "sg:address":"Av Madrid, 20",
    "sg:city":"Barcelona",
    "sg:orig_category":"Negocio De Madera",
    "sg:phone":"+34 933 34 73 26",
    "sg:postcode":"08028",
    "sg:province":"Barcelona",
    "wof:name":"Rios Creus Manuel",
    "wof:placetype":"venue"
},
  "geometry": {"coordinates":[2.1241230965,41.376335144],"type":"Point"}
}