{
  "type": "Feature",
  "properties": {
    "iso:country":"ES",
    "sg:address":"Ptda Alberca (l'), 1",
    "sg:city":"Nucia",
    "sg:orig_category":"Empresas De Carpinter\u00cda",
    "sg:phone":"+34 966 89 56 61",
    "sg:postcode":"03530",
    "sg:province":"Alicante",
    "wof:name":"Aluminios Jucrima S.l.",
    "wof:placetype":"venue"
},
  "geometry": {"coordinates":[-0.1259891987,38.6142196655],"type":"Point"}
}