{
  "type": "Feature",
  "properties": {
    "iso:country":"ES",
    "sg:address":"Calle de Ebro, 49",
    "sg:city":"Bosque",
    "sg:orig_category":"Procuradores",
    "sg:phone":"+34 916 16 78 16",
    "sg:postcode":"28670",
    "sg:province":"Madrid",
    "wof:name":"Martinez Parra Maria Luisa",
    "wof:placetype":"venue"
},
  "geometry": {"coordinates":[-3.928072691,40.3730430603],"type":"Point"}
}