{
  "type": "Feature",
  "properties": {
    "addr:full":"Avda Virgen De La Cabeza, 4 Antas Almer\u00eda 04628",
    "addr:housenumber":"4",
    "addr:postcode":"04628",
    "addr:street":"Avda Virgen De La Cabeza",
    "iso:country":"ES",
    "sg:address":"Avda Virgen De La Cabeza, 4",
    "sg:city":"Antas",
    "sg:orig_category":"Inmobiliaria (agencias)",
    "sg:phone":"+34 950 45 32 40",
    "sg:postcode":"04628",
    "sg:province":"Almer\u00eda",
    "wof:name":"Argar Consultores S.l.",
    "wof:placetype":"venue"
},
  "geometry": {"coordinates":[-1.9177788496,37.243938446],"type":"Point"}
}