{
  "type": "Feature",
  "properties": {
    "addr:full":"Pol Ind Torrelavid, S/n Lavit Barcelona 08775",
    "addr:housenumber":"s / n",
    "addr:postcode":"08775",
    "iso:country":"ES",
    "sg:address":"Pol Ind Torrelavid, S/n",
    "sg:city":"Lavit",
    "sg:orig_category":"Material Y Suministros Para Dentistas, Cirujanos",
    "sg:phone":"+34 938 99 54 84",
    "sg:postcode":"08775",
    "sg:province":"Barcelona",
    "wof:name":"Paver Prefabricados S. A.",
    "wof:placetype":"venue"
},
  "geometry": {"coordinates":[1.7272900343,41.4427185059],"type":"Point"}
}