{
  "type": "Feature",
  "properties": {
    "iso:country":"ES",
    "sg:address":"Calle de Maestro Ramon Sanchis Rovira, 40",
    "sg:city":"Albal",
    "sg:orig_category":"Caf\u00c9s, Bares, Cervecer\u00cdas",
    "sg:phone":"+34 961 27 30 92",
    "sg:postcode":"46470",
    "sg:province":"Valencia",
    "wof:name":"Zacares Fort Sacramento",
    "wof:placetype":"venue"
},
  "geometry": {"coordinates":[-0.4121969044,39.3970947266],"type":"Point"}
}