{
  "type": "Feature",
  "properties": {
    "addr:full":"Avda Diputacion (la), 3 Alovera Guadalajara 19208",
    "addr:housenumber":"3",
    "addr:postcode":"19208",
    "addr:street":"Avda Diputacion La",
    "iso:country":"ES",
    "sg:address":"Avda Diputacion (la), 3",
    "sg:city":"Alovera",
    "sg:orig_category":"Caf\u00c9s, Bares, Cervecer\u00cdas",
    "sg:phone":"+34 949 29 72 43",
    "sg:postcode":"19208",
    "sg:province":"Guadalajara",
    "wof:name":"Jofaelpa Sl",
    "wof:placetype":"venue"
},
  "geometry": {"coordinates":[-3.2479109764,40.59740448],"type":"Point"}
}