{
  "type": "Feature",
  "properties": {
    "iso:country":"ES",
    "sg:address":"Calle de Carrera, 11",
    "sg:city":"Villanueva Serena",
    "sg:orig_category":"Sindicatos De Trabajadores",
    "sg:phone":"+34 924 84 63 22",
    "sg:postcode":"06700",
    "sg:province":"Badajoz",
    "wof:name":"Union De Peque\u00d1os Agricultores De Extrem",
    "wof:placetype":"venue"
},
  "geometry": {"coordinates":[-5.7998418808,38.9750022888],"type":"Point"}
}