{
  "type": "Feature",
  "properties": {
    "addr:full":"Rua Zamora, 51 Vigo Pontevedra 36203",
    "addr:housenumber":"51",
    "addr:postcode":"36203",
    "addr:street":"Rua Zamora",
    "iso:country":"ES",
    "sg:address":"Rua Zamora, 51",
    "sg:city":"Vigo",
    "sg:orig_category":"Doctores En Medicina",
    "sg:phone":"+34 986 42 03 50",
    "sg:postcode":"36203",
    "sg:province":"Pontevedra",
    "wof:name":"Mari\u00f1o Campos Pedro Manuel",
    "wof:placetype":"venue"
},
  "geometry": {"coordinates":[-8.7236480713,42.2249145508],"type":"Point"}
}