{
  "type": "Feature",
  "properties": {
    "iso:country":"ES",
    "sg:address":"Calle de Ponce De Leon, 1",
    "sg:city":"Utrera",
    "sg:orig_category":"Cl\u00cdnicas M\u00c9dicas",
    "sg:phone":"+34 954 86 10 02",
    "sg:postcode":"41710",
    "sg:province":"Sevilla",
    "wof:name":"Utremedi S.l.",
    "wof:placetype":"venue"
},
  "geometry": {"coordinates":[-5.7817578316,37.1814842224],"type":"Point"}
}