{
  "type": "Feature",
  "properties": {
    "iso:country":"ES",
    "sg:address":"Ctra Castilblanco, S/n",
    "sg:city":"Herrera Duque",
    "sg:orig_category":"Producci\u00d3n, Venta De Productos De Agricultura Biol\u00d3gica",
    "sg:phone":"+34 924 14 50 18",
    "sg:postcode":"06670",
    "sg:province":"Badajoz",
    "wof:name":"Benazaire S.a.",
    "wof:placetype":"venue"
},
  "geometry": {"coordinates":[-5.049038887,39.1718788147],"type":"Point"}
}