{
  "type": "Feature",
  "properties": {
    "iso:country":"ES",
    "sg:address":"G.v. Corts Catalanes, 515",
    "sg:city":"Barcelona",
    "sg:orig_category":"Guarder\u00cdas",
    "sg:phone":"+34 933 23 34 77",
    "sg:postcode":"08015",
    "sg:province":"Barcelona",
    "wof:name":"Blanch Romero Maria Isabel",
    "wof:placetype":"venue"
},
  "geometry": {"coordinates":[2.1576590538,41.3818855286],"type":"Point"}
}