{
  "type": "Feature",
  "properties": {
    "iso:country":"ES",
    "sg:address":"Calle de Q, 3",
    "sg:city":"Mutiloabeiti",
    "sg:orig_category":"Plomeros",
    "sg:phone":"+34 948 23 73 59",
    "sg:postcode":"31192",
    "sg:province":"Navarra",
    "wof:name":"Hilario Quel Alzueta Juan Antonio Gomez Sarabia S.cv.",
    "wof:placetype":"venue"
},
  "geometry": {"coordinates":[-1.6285539865,42.7857246399],"type":"Point"}
}