{
  "type": "Feature",
  "properties": {
    "iso:country":"ES",
    "sg:address":"Ctra. Fuente Tojar, S/n",
    "sg:city":"Almedinilla",
    "sg:orig_category":"Aceites Y Grasas Alimentarias (fabricaci\u00d3n, Al Por Mayor)",
    "sg:phone":"+34 957 70 34 61",
    "sg:postcode":"14812",
    "sg:province":"C\u00f3rdoba",
    "wof:name":"Aceites El Palomar S.a.",
    "wof:placetype":"venue"
},
  "geometry": {"coordinates":[-4.059325695,37.4306602478],"type":"Point"}
}