{
  "type": "Feature",
  "properties": {
    "addr:full":"Carrer de Carrio, 17 Manresa Barcelona 08242",
    "addr:housenumber":"17",
    "addr:postcode":"08242",
    "addr:street":"Carrer De Carrio",
    "iso:country":"ES",
    "sg:address":"Carrer de Carrio, 17",
    "sg:city":"Manresa",
    "sg:orig_category":"Inmobiliaria (agencias)",
    "sg:phone":"+34 938 75 07 04",
    "sg:postcode":"08242",
    "sg:province":"Barcelona",
    "wof:name":"Carrio 17 Finques S.l.",
    "wof:placetype":"venue"
},
  "geometry": {"coordinates":[1.8224799633,41.7281990051],"type":"Point"}
}