{
  "type": "Feature",
  "properties": {
    "addr:full":"Avgd Republica Argentina, 122 Gandia Valencia 46700",
    "addr:housenumber":"122",
    "addr:postcode":"46700",
    "addr:street":"Argentina;Valencia",
    "iso:country":"ES",
    "sg:address":"Avgd Republica Argentina, 122",
    "sg:city":"Gandia",
    "sg:orig_category":"Almacenes Para Venta: Muebles Y Varios",
    "sg:phone":"+34 962 87 94 45",
    "sg:postcode":"46700",
    "sg:province":"Valencia",
    "sg:website":"www.muebleselrebajon.com",
    "wof:name":"Grupo De Empresas Del Mueble S.a.",
    "wof:placetype":"venue"
},
  "geometry": {"coordinates":[-0.1913339943,38.960735321],"type":"Point"}
}