{
  "type": "Feature",
  "properties": {
    "iso:country":"ES",
    "sg:address":"Calle de General Mu\u00d1oz Grandes, 2",
    "sg:city":"Socuellamos",
    "sg:orig_category":"M\u00c9dicos: An\u00c1lisis Cl\u00cdnicos",
    "sg:phone":"+34 926 53 02 12",
    "sg:postcode":"13630",
    "sg:province":"Ciudad Real",
    "wof:name":"Galiana Izquierdo Antonio",
    "wof:placetype":"venue"
},
  "geometry": {"coordinates":[-2.7916340828,39.2841262817],"type":"Point"}
}