{
  "type": "Feature",
  "properties": {
    "iso:country":"ES",
    "sg:address":"Rua Entins, S/n",
    "sg:city":"Serra De Outes",
    "sg:orig_category":"Bares, Piano",
    "sg:phone":"+34 981 85 01 47",
    "sg:postcode":"15230",
    "sg:province":"La Coru\u00f1a",
    "wof:name":"Juan Antonio Del Rio E Hijos S.l.",
    "wof:placetype":"venue"
},
  "geometry": {"coordinates":[-8.9017477036,42.8406600952],"type":"Point"}
}