{
  "type": "Feature",
  "properties": {
    "addr:full":"Carrer de Jaume I (de), 6 Tarragona Tarragona 43005",
    "addr:postcode":"43005",
    "addr:street":"Carrer De Jaume I De 6",
    "iso:country":"ES",
    "sg:address":"Carrer de Jaume I (de), 6",
    "sg:city":"Tarragona",
    "sg:orig_category":"Comerciantes Al Por Mayor De Vinos, Licores Y Alcoholes",
    "sg:phone":"+34 977 22 06 17",
    "sg:postcode":"43005",
    "sg:province":"Tarragona",
    "wof:name":"Jorda Ane Eduardo",
    "wof:placetype":"venue"
},
  "geometry": {"coordinates":[1.2451839447,41.1155738831],"type":"Point"}
}