{
  "type": "Feature",
  "properties": {
    "addr:full":"Cmno Puente Virrey, 10 Zaragoza Zaragoza 50008",
    "addr:housenumber":"10",
    "addr:postcode":"50008",
    "addr:street":"Cmno Puente Virrey",
    "iso:country":"ES",
    "sg:address":"Cmno Puente Virrey, 10",
    "sg:city":"Zaragoza",
    "sg:orig_category":"Peluquer\u00cdas, Peluquer\u00cda Mixta",
    "sg:phone":"+34 976 49 63 19",
    "sg:postcode":"50008",
    "sg:province":"Zaragoza",
    "wof:name":"Berne Lazaro Elda",
    "wof:placetype":"venue"
},
  "geometry": {"coordinates":[-0.8741710186,41.638999939],"type":"Point"}
}