{
  "type": "Feature",
  "properties": {
    "addr:full":"Calle de Sevilla, 25 Pinto Madrid 28320",
    "addr:housenumber":"25",
    "addr:postcode":"28320",
    "addr:street":"Calle De Sevilla",
    "iso:country":"ES",
    "sg:address":"Calle de Sevilla, 25",
    "sg:city":"Pinto",
    "sg:orig_category":"Polideportivos",
    "sg:phone":"+34 917 65 21 49",
    "sg:postcode":"28320",
    "sg:province":"Madrid",
    "wof:name":"Ayuntamiento De Pinto",
    "wof:placetype":"venue"
},
  "geometry": {"coordinates":[-3.6915664673,40.242389679],"type":"Point"}
}