{
  "type": "Feature",
  "properties": {
    "addr:full":"Calle de San Millan, 27 Malaga M\u00e1laga 29013",
    "addr:housenumber":"27",
    "addr:postcode":"29013",
    "addr:street":"Calle De San Millan;Ma\u0301Laga",
    "iso:country":"ES",
    "sg:address":"Calle de San Millan, 27",
    "sg:city":"Malaga",
    "sg:orig_category":"Venta, Alquiler De Instrumentos Y Accesorios De M\u00dasica",
    "sg:phone":"+34 952 26 76 23",
    "sg:postcode":"29013",
    "sg:province":"M\u00e1laga",
    "sg:website":"www.polifonia.es",
    "wof:name":"Polifonia Sonido S.l.",
    "wof:placetype":"venue"
},
  "geometry": {"coordinates":[-4.4191050529,36.7293968201],"type":"Point"}
}