{
  "type": "Feature",
  "properties": {
    "addr:full":"Plaz Santa Maria De Guadalupe, 30 Guadalupe C\u00e1ceres 10140",
    "addr:postcode":"10140",
    "addr:street":"Guadalupe 30;Ca\u0301Ceres",
    "iso:country":"ES",
    "sg:address":"Plaz Santa Maria De Guadalupe, 30",
    "sg:city":"Guadalupe",
    "sg:orig_category":"Carnicer\u00cdas, Carnicer\u00cdas",
    "sg:phone":"+34 927 36 72 49",
    "sg:postcode":"10140",
    "sg:province":"C\u00e1ceres",
    "wof:name":"Montero Becerra Manuel",
    "wof:placetype":"venue"
},
  "geometry": {"coordinates":[-5.3263068199,39.4509429932],"type":"Point"}
}