{
  "type": "Feature",
  "properties": {
    "iso:country":"ES",
    "sg:address":"Cust Loreto, S/n",
    "sg:city":"Tudela",
    "sg:orig_category":"Hoteles",
    "sg:phone":"+34 948 40 26 82",
    "sg:postcode":"31500",
    "sg:province":"Navarra",
    "wof:name":"Hostal Torre Monreal S.l.",
    "wof:placetype":"venue"
},
  "geometry": {"coordinates":[-1.6076760292,42.0592460632],"type":"Point"}
}