{
  "type": "Feature",
  "properties": {
    "iso:country":"ES",
    "sg:address":"Calle de Santa Ana, 15",
    "sg:city":"Le\u00f3n",
    "sg:orig_category":"Asociaciones Y Clubs Deportivos",
    "sg:phone":"+34 987 25 76 64",
    "sg:postcode":"24006",
    "sg:province":"Le\u00f3n",
    "sg:website":"www.bodyfactory.es",
    "wof:name":"Perfil Leon S.l.l.",
    "wof:placetype":"venue"
},
  "geometry": {"coordinates":[-5.5656471252,42.5944824219],"type":"Point"}
}