{
  "type": "Feature",
  "properties": {
    "iso:country":"ES",
    "sg:address":"Carrer de Gessami, 14",
    "sg:city":"Santa Perpetua De Mogoda",
    "sg:orig_category":"Asesores De Gesti\u00d3n Del Patrimonio",
    "sg:phone":"+34 935 74 23 31",
    "sg:postcode":"08130",
    "sg:province":"Barcelona",
    "wof:name":"Insitel Inversiones 2000 S.l",
    "wof:placetype":"venue"
},
  "geometry": {"coordinates":[2.1801888943,41.526184082],"type":"Point"}
}