{
  "type": "Feature",
  "properties": {
    "iso:country":"ES",
    "sg:address":"Calle de Cruce Del Solanillo, S/n",
    "sg:city":"Mojonera",
    "sg:orig_category":"Empresas De Carpinter\u00cda Met\u00c1lica",
    "sg:phone":"+34 950 33 05 10",
    "sg:postcode":"04745",
    "sg:province":"Almer\u00eda",
    "wof:name":"Solera Hierros Y Aluminios S.l.",
    "wof:placetype":"venue"
},
  "geometry": {"coordinates":[-2.6811990738,36.7550849915],"type":"Point"}
}