{
  "type": "Feature",
  "properties": {
    "iso:country":"ES",
    "sg:address":"Avda Fuerzas Armadas, 8",
    "sg:city":"Algeciras",
    "sg:orig_category":"Centros De Coordinaci\u00d3n",
    "sg:phone":"+34 956 66 11 88",
    "sg:postcode":"11202",
    "sg:province":"C\u00e1diz",
    "wof:name":"Lopez Lopez Ines Maria",
    "wof:placetype":"venue"
},
  "geometry": {"coordinates":[-5.44952631,36.1339836121],"type":"Point"}
}