{
  "type": "Feature",
  "properties": {
    "addr:full":"Sta Teresa Jornet, 1 Merida Badajoz 06800",
    "addr:housenumber":"1",
    "addr:postcode":"06800",
    "addr:street":"Sta Teresa Jornet",
    "iso:country":"ES",
    "sg:address":"Sta Teresa Jornet, 1",
    "sg:city":"Merida",
    "sg:orig_category":"Autob\u00das (explotaci\u00d3n Y Servicios De)",
    "sg:phone":"+34 924 31 91 05",
    "sg:postcode":"06800",
    "sg:province":"Badajoz",
    "wof:name":"Morcillo Nieto Pedro",
    "wof:placetype":"venue"
},
  "geometry": {"coordinates":[-6.337428093,38.9056434631],"type":"Point"}
}