{
  "type": "Feature",
  "properties": {
    "addr:full":"Calle de Blas Infante, 3 Cabezas S. Juan Sevilla 41730",
    "addr:housenumber":"3",
    "addr:postcode":"41730",
    "addr:street":"Calle De Blas Infante;S.",
    "iso:country":"ES",
    "sg:address":"Calle de Blas Infante, 3",
    "sg:city":"Cabezas S. Juan",
    "sg:orig_category":"Caf\u00c9s, Bares, Cervecer\u00cdas",
    "sg:phone":"+34 955 87 32 62",
    "sg:postcode":"41730",
    "sg:province":"Sevilla",
    "wof:name":"Mayorga Fabian Marisol",
    "wof:placetype":"venue"
},
  "geometry": {"coordinates":[-5.9374256134,36.9861106873],"type":"Point"}
}