{
  "type": "Feature",
  "properties": {
    "iso:country":"ES",
    "sg:address":"Po. Maritim, 31",
    "sg:city":"Cala Bona",
    "sg:orig_category":"Librer\u00cdas",
    "sg:phone":"+34 971 58 58 29",
    "sg:postcode":"07559",
    "sg:province":"Islas Baleares",
    "wof:name":"Nova Area S. A.",
    "wof:placetype":"venue"
},
  "geometry": {"coordinates":[3.3896319866,39.612953186],"type":"Point"}
}