{
  "type": "Feature",
  "properties": {
    "iso:country":"ES",
    "sg:address":"Calle de Pelota, 6",
    "sg:city":"Cadiz",
    "sg:orig_category":"Confecci\u00d3n De Zapatos",
    "sg:phone":"+34 956 28 79 52",
    "sg:postcode":"11005",
    "sg:province":"C\u00e1diz",
    "wof:name":"Conde Rodriguez Enrique",
    "wof:placetype":"venue"
},
  "geometry": {"coordinates":[-6.2940788269,36.5298118591],"type":"Point"}
}