{
  "type": "Feature",
  "properties": {
    "iso:country":"ES",
    "sg:address":"Calle de Real, 52",
    "sg:city":"Neila",
    "sg:orig_category":"Cr\u00cda De Animales",
    "sg:phone":"+34 947 39 51 95",
    "sg:postcode":"09679",
    "sg:province":"Burgos",
    "wof:name":"Ayuso Ortiz Vicente",
    "wof:placetype":"venue"
},
  "geometry": {"coordinates":[-2.9972000122,42.0601997375],"type":"Point"}
}