{
  "type": "Feature",
  "properties": {
    "addr:full":"Calle de Fuenlabrada, 4 Alcorcon Madrid 28921",
    "addr:housenumber":"4",
    "addr:postcode":"28921",
    "addr:street":"Calle De Fuenlabrada",
    "iso:country":"ES",
    "sg:address":"Calle de Fuenlabrada, 4",
    "sg:city":"Alcorcon",
    "sg:orig_category":"Ense\u00d1anza Variada",
    "sg:phone":"+34 916 43 24 18",
    "sg:postcode":"28921",
    "sg:province":"Madrid",
    "wof:name":"Fernandez Culebras Daniel",
    "wof:placetype":"venue"
},
  "geometry": {"coordinates":[-3.8271985054,40.3460502625],"type":"Point"}
}