{
  "type": "Feature",
  "properties": {
    "addr:full":"Avda Goya, 8 Zaragoza Zaragoza 50006",
    "addr:housenumber":"8",
    "addr:postcode":"50006",
    "addr:street":"Avda Goya",
    "iso:country":"ES",
    "sg:address":"Avda Goya, 8",
    "sg:city":"Zaragoza",
    "sg:orig_category":"Peluquer\u00cdas, Peluquer\u00cda Mixta",
    "sg:phone":"+34 976 22 01 03",
    "sg:postcode":"50006",
    "sg:province":"Zaragoza",
    "wof:name":"Moure Cueto Angel",
    "wof:placetype":"venue"
},
  "geometry": {"coordinates":[-1.0287350416,41.7223625183],"type":"Point"}
}