{
  "type": "Feature",
  "properties": {
    "iso:country":"ES",
    "sg:address":"Avda Sardi\u00d1eira, 36",
    "sg:city":"Coru\u00d1a",
    "sg:orig_category":"Inform\u00c1tica: Material Y Suministros",
    "sg:phone":"+34 981 23 00 12",
    "sg:postcode":"15008",
    "sg:province":"A Coru\u00f1a",
    "wof:name":"T-systems Eytc S. A.",
    "wof:placetype":"venue"
},
  "geometry": {"coordinates":[-8.4145116806,43.3498649597],"type":"Point"}
}