{
  "type": "Feature",
  "properties": {
    "addr:full":"Calle de Grilo, 23 Malaga M\u00e1laga 29006",
    "addr:housenumber":"23",
    "addr:postcode":"29006",
    "addr:street":"Calle De Grilo;Ma\u0301Laga",
    "iso:country":"ES",
    "sg:address":"Calle de Grilo, 23",
    "sg:city":"Malaga",
    "sg:orig_category":"Ingenier\u00cda, Centros De Estudios (diversos)",
    "sg:phone":"+34 952 35 44 55",
    "sg:postcode":"29006",
    "sg:province":"M\u00e1laga",
    "wof:name":"Hidrotopo S.cv",
    "wof:placetype":"venue"
},
  "geometry": {"coordinates":[-4.4367918968,36.7142829895],"type":"Point"}
}