{
  "type": "Feature",
  "properties": {
    "iso:country":"ES",
    "sg:address":"Pla\u00c7 Esglesia (de L'), 6",
    "sg:city":"Agramunt",
    "sg:orig_category":"Carnicer\u00cdas, Carnicer\u00cdas",
    "sg:phone":"+34 973 39 02 78",
    "sg:postcode":"25310",
    "sg:province":"Lleida",
    "wof:name":"Castella Boncompte Simon",
    "wof:placetype":"venue"
},
  "geometry": {"coordinates":[1.0987650156,41.7872428894],"type":"Point"}
}