{
  "type": "Feature",
  "properties": {
    "addr:full":"Calle de Alfonso El Sabio, 2 San Vicente Del Raspeig-sant Vicent Del Raspeig Alicante 03690",
    "addr:housenumber":"2",
    "addr:postcode":"03690",
    "addr:street":"Calle De Alfonso El Sabio",
    "iso:country":"ES",
    "sg:address":"Calle de Alfonso El Sabio, 2",
    "sg:city":"San Vicente Del Raspeig-sant Vicent Del Raspeig",
    "sg:orig_category":"Tapicer\u00cdas",
    "sg:phone":"+34 965 66 24 15",
    "sg:postcode":"03690",
    "sg:province":"Alicante",
    "wof:name":"Gonzalez Gonzalez Manuel",
    "wof:placetype":"venue"
},
  "geometry": {"coordinates":[-0.5212144256,38.3978996277],"type":"Point"}
}