{
  "type": "Feature",
  "properties": {
    "addr:full":"Calle de Carrera, S/n Motril Granada 18600",
    "addr:housenumber":"/ n",
    "addr:postcode":"18600",
    "addr:street":"Calle De Carrera S",
    "iso:country":"ES",
    "sg:address":"Calle de Carrera, S/n",
    "sg:city":"Motril",
    "sg:orig_category":"Quincaller\u00cda (al Por Menor)",
    "sg:phone":"+34 958 60 27 47",
    "sg:postcode":"18600",
    "sg:province":"Granada",
    "wof:name":"Jeronimo Bustos Jose Antonio",
    "wof:placetype":"venue"
},
  "geometry": {"coordinates":[-3.5185289383,36.744644165],"type":"Point"}
}