{
  "type": "Feature",
  "properties": {
    "iso:country":"ES",
    "sg:address":"Carr Sant Felip Neri, 31",
    "sg:city":"Vilanova I La Geltru",
    "sg:orig_category":"Electricidad: Instaladores",
    "sg:phone":"+34 938 93 00 28",
    "sg:postcode":"08800",
    "sg:province":"Barcelona",
    "wof:name":"Cabrero Rovira Juan",
    "wof:placetype":"venue"
},
  "geometry": {"coordinates":[1.7272980213,41.2236022949],"type":"Point"}
}