{
  "type": "Feature",
  "properties": {
    "iso:country":"ES",
    "sg:address":"Calle de Antonio Machado, 56",
    "sg:city":"Torres Cotillas",
    "sg:orig_category":"Ropa Para Se\u00d1oras Y Caballeros (al Por Menor)",
    "sg:phone":"+34 968 62 86 52",
    "sg:postcode":"30565",
    "sg:province":"Murcia",
    "wof:name":"Modas Frason S.l.l.",
    "wof:placetype":"venue"
},
  "geometry": {"coordinates":[-1.2431422472,38.0291862488],"type":"Point"}
}