{
  "type": "Feature",
  "properties": {
    "iso:country":"ES",
    "sg:address":"Carrer de Tenor Vi\u00d1as, 12",
    "sg:city":"Barcelona",
    "sg:orig_category":"Zapatos (al Por Menor)",
    "sg:phone":"+34 932 01 31 15",
    "sg:postcode":"08021",
    "sg:province":"Barcelona",
    "wof:name":"Marga Goma S. A.",
    "wof:placetype":"venue"
},
  "geometry": {"coordinates":[2.1424589157,41.3950614929],"type":"Point"}
}