{
  "type": "Feature",
  "properties": {
    "addr:full":"Calle de Neveritas, 3 Piedrahita \u00c1vila 05500",
    "addr:housenumber":"3",
    "addr:postcode":"05500",
    "addr:street":"Calle De Neveritas",
    "iso:country":"ES",
    "sg:address":"Calle de Neveritas, 3",
    "sg:city":"Piedrahita",
    "sg:orig_category":"Carnicer\u00cdas, Carnicer\u00cdas",
    "sg:phone":"+34 920 36 03 89",
    "sg:postcode":"05500",
    "sg:province":"\u00c1vila",
    "wof:name":"Manuel Sanchez Hernandez-evelio Sanchez Hernandez C.b.",
    "wof:placetype":"venue"
},
  "geometry": {"coordinates":[-5.3270101547,40.464969635],"type":"Point"}
}