{
  "type": "Feature",
  "properties": {
    "iso:country":"ES",
    "sg:address":"Rua Outonil, 19",
    "sg:city":"Noia",
    "sg:orig_category":"Fabricaci\u00d3n, Venta, Instalaci\u00d3n De R\u00d3tulos, De R\u00d3tulos Luminosos",
    "sg:phone":"+34 981 82 25 70",
    "sg:postcode":"15200",
    "sg:province":"La Coru\u00f1a",
    "wof:name":"Ajeitos Roo Jose Luis",
    "wof:placetype":"venue"
},
  "geometry": {"coordinates":[-8.8852071762,42.7878074646],"type":"Point"}
}