{
  "type": "Feature",
  "properties": {
    "addr:full":"Calle de Espa\u00d1oleto, 21 Cartagena Murcia 30204",
    "addr:housenumber":"21",
    "addr:postcode":"30204",
    "addr:street":"Calle De Espan\u0303Oleto",
    "iso:country":"ES",
    "sg:address":"Calle de Espa\u00d1oleto, 21",
    "sg:city":"Cartagena",
    "sg:orig_category":"Asesores De Gesti\u00d3n Del Patrimonio",
    "sg:phone":"+34 968 53 00 71",
    "sg:postcode":"30204",
    "sg:province":"Murcia",
    "wof:name":"Gesincarsa S.l",
    "wof:placetype":"venue"
},
  "geometry": {"coordinates":[-0.9894438982,37.6134033203],"type":"Point"}
}