{
  "type": "Feature",
  "properties": {
    "iso:country":"ES",
    "sg:address":"Plaz Marcelino Perez, 1",
    "sg:city":"Fontiveros",
    "sg:orig_category":"Agentes Generales De Seguros",
    "sg:phone":"+34 920 24 51 66",
    "sg:postcode":"05310",
    "sg:province":"\u00c1vila",
    "wof:name":"Pintor Gonzalez Isabel",
    "wof:placetype":"venue"
},
  "geometry": {"coordinates":[-4.9646692276,40.9281311035],"type":"Point"}
}