{
  "type": "Feature",
  "properties": {
    "addr:full":"Calle de Jose Salarrullana, 1 Fraga Huesca 22520",
    "addr:housenumber":"1",
    "addr:postcode":"22520",
    "addr:street":"Calle De Jose Salarrullana",
    "iso:country":"ES",
    "sg:address":"Calle de Jose Salarrullana, 1",
    "sg:city":"Fraga",
    "sg:orig_category":"M\u00c9dicos: Estomatolog\u00cda",
    "sg:phone":"+34 974 47 21 10",
    "sg:postcode":"22520",
    "sg:province":"Huesca",
    "wof:name":"Ibarz Vera Silvia",
    "wof:placetype":"venue"
},
  "geometry": {"coordinates":[0.3373320103,41.5218582153],"type":"Point"}
}