{
  "type": "Feature",
  "properties": {
    "addr:full":"Alam Areilza Doctor, 39 Bilbao Vizcaya 48010",
    "addr:housenumber":"39",
    "addr:postcode":"48010",
    "addr:street":"Alam;Doctor",
    "iso:country":"ES",
    "sg:address":"Alam Areilza Doctor, 39",
    "sg:city":"Bilbao",
    "sg:orig_category":"Ense\u00d1anza Variada",
    "sg:phone":"+34 944 22 21 48",
    "sg:postcode":"48010",
    "sg:province":"Vizcaya",
    "sg:website":"www.upformacion.com",
    "wof:name":"Nuevas Promociones Gorapen Berriak S.l.",
    "wof:placetype":"venue"
},
  "geometry": {"coordinates":[-2.9427909851,43.259853363],"type":"Point"}
}