{
  "type": "Feature",
  "properties": {
    "addr:full":"Urb Polig Ind La Ermita, 5 Poligono Industrial La Ermita Toledo 45215",
    "addr:housenumber":"5",
    "addr:postcode":"45215",
    "addr:street":"Urb Polig;La Ermita;Poligono Industrial",
    "iso:country":"ES",
    "sg:address":"Urb Polig Ind La Ermita, 5",
    "sg:city":"Poligono Industrial La Ermita",
    "sg:orig_category":"Fabricaci\u00d3n De Muebles",
    "sg:phone":"+34 925 55 97 00",
    "sg:postcode":"45215",
    "sg:province":"Toledo",
    "wof:name":"Artemisa Mueble Sl.",
    "wof:placetype":"venue"
},
  "geometry": {"coordinates":[-4.0244760513,39.8567771912],"type":"Point"}
}