{
  "type": "Feature",
  "properties": {
    "addr:full":"Avda. Finisterre, 98 A Coru\u00f1a La Coru\u00f1a 15004",
    "addr:housenumber":"98 a",
    "addr:postcode":"15004",
    "addr:street":"Avda. Finisterre;Corun\u0303A La Corun\u0303A",
    "iso:country":"ES",
    "sg:address":"Avda. Finisterre, 98",
    "sg:city":"A Coru\u00f1a",
    "sg:orig_category":"Loter\u00cda Y T\u00d3mbola",
    "sg:phone":"+34 981 27 55 85",
    "sg:postcode":"15004",
    "sg:province":"La Coru\u00f1a",
    "wof:name":"Brun Pintor Pablo",
    "wof:placetype":"venue"
},
  "geometry": {"coordinates":[-8.4128236771,43.3640975952],"type":"Point"}
}