{
  "type": "Feature",
  "properties": {
    "iso:country":"ES",
    "sg:address":"Ctra Betera-olocau, 5",
    "sg:city":"Olocau",
    "sg:orig_category":"Distribuci\u00d3n De Petr\u00d3leo Y Derivados",
    "sg:phone":"+34 961 66 43 13",
    "sg:postcode":"46169",
    "sg:province":"Valencia",
    "sg:website":"www.ventadegasoleo.com",
    "wof:name":"Estaciones De Servicio J. Nu\u00f1ez S.l.",
    "wof:placetype":"venue"
},
  "geometry": {"coordinates":[-0.5312510133,39.702671051],"type":"Point"}
}