{
  "type": "Feature",
  "properties": {
    "addr:full":"Calle de Doctor Horno Alcorta, 3 Zaragoza Zaragoza 50004",
    "addr:housenumber":"3",
    "addr:postcode":"50004",
    "addr:street":"Calle De Doctor Horno Alcorta",
    "iso:country":"ES",
    "sg:address":"Calle de Doctor Horno Alcorta, 3",
    "sg:city":"Zaragoza",
    "sg:orig_category":"Molduras, Junquillos, Listones Y Molduras Perforadas",
    "sg:phone":"+34 976 23 25 46",
    "sg:postcode":"50004",
    "sg:province":"Zaragoza",
    "wof:name":"Aragonesa De Sistemas Telefonicos S.l.",
    "wof:placetype":"venue"
},
  "geometry": {"coordinates":[-0.8905531764,41.6497688293],"type":"Point"}
}