{
  "type": "Feature",
  "properties": {
    "iso:country":"ES",
    "sg:address":"Calle de Gallegos, 8",
    "sg:city":"Tarazona Mancha",
    "sg:orig_category":"Oficinas: Suministros Para (fabricaci\u00d3n, Al Por Mayor)",
    "sg:phone":"+34 967 48 08 32",
    "sg:postcode":"02100",
    "sg:province":"Albacete",
    "wof:name":"Sanchez Panadero Maria Vicenta",
    "wof:placetype":"venue"
},
  "geometry": {"coordinates":[-1.911831975,39.2641792297],"type":"Point"}
}