{
  "type": "Feature",
  "properties": {
    "iso:country":"ES",
    "sg:address":"Poligono Industrial La Soledad, S/n",
    "sg:city":"Cuacos Yuste",
    "sg:orig_category":"Condimentos, Especias, Vinagres, Salsas Preparadas (fabricaci\u00d3n, Al Por Mayor)",
    "sg:phone":"+34 927 17 22 14",
    "sg:postcode":"10430",
    "sg:province":"C\u00e1ceres",
    "wof:name":"Jose L.mateos S.l.",
    "wof:placetype":"venue"
},
  "geometry": {"coordinates":[-5.7389121056,40.1141433716],"type":"Point"}
}