{
  "type": "Feature",
  "properties": {
    "addr:full":"Carrer de Llull, 70 Barcelona Barcelona 08005",
    "addr:housenumber":"70",
    "addr:postcode":"08005",
    "addr:street":"Carrer De Llull",
    "iso:country":"ES",
    "sg:address":"Carrer de Llull, 70",
    "sg:city":"Barcelona",
    "sg:orig_category":"Confecci\u00d3n (fabricaci\u00d3n, Al Por Mayor)",
    "sg:phone":"+34 934 85 24 80",
    "sg:postcode":"08005",
    "sg:province":"Barcelona",
    "wof:name":"Textil Vime S.l.",
    "wof:placetype":"venue"
},
  "geometry": {"coordinates":[2.193614006,41.39453125],"type":"Point"}
}