{
  "type": "Feature",
  "properties": {
    "iso:country":"ES",
    "sg:address":"Pl Pontos, 5",
    "sg:city":"Elche",
    "sg:orig_category":"Plomeros",
    "sg:phone":"+34 965 45 11 24",
    "sg:postcode":"03203",
    "sg:province":"Alicante",
    "wof:name":"Fontaneria Pelegrin C.b.",
    "wof:placetype":"venue"
},
  "geometry": {"coordinates":[-0.6995239854,38.2634811401],"type":"Point"}
}