{
  "type": "Feature",
  "properties": {
    "iso:country":"ES",
    "sg:address":"Avda Badajoz, 11",
    "sg:city":"Madrid",
    "sg:orig_category":"Alimentaci\u00d3n General (al Por Menor)",
    "sg:phone":"+34 914 04 07 92",
    "sg:postcode":"28027",
    "sg:province":"Madrid",
    "wof:name":"Hu  Kes",
    "wof:placetype":"venue"
},
  "geometry": {"coordinates":[-3.655244112,40.4416046143],"type":"Point"}
}