{
  "type": "Feature",
  "properties": {
    "addr:full":"Calle de Avila, 5 Burgos Burgos 09001",
    "addr:housenumber":"5",
    "addr:postcode":"09001",
    "addr:street":"Calle De Avila",
    "iso:country":"ES",
    "sg:address":"Calle de Avila, 5",
    "sg:city":"Burgos",
    "sg:orig_category":"Panader\u00cdas, Panader\u00cdas",
    "sg:phone":"+34 947 26 20 75",
    "sg:postcode":"09001",
    "sg:province":"Burgos",
    "wof:name":"Pastcal Artesanos S.l.",
    "wof:placetype":"venue"
},
  "geometry": {"coordinates":[-3.7026782036,42.3309288025],"type":"Point"}
}