{
  "type": "Feature",
  "properties": {
    "addr:full":"Rua Fonte De San Miguel (da), 8 Santiago De Compostela La Coru\u00f1a 15704",
    "addr:postcode":"15704",
    "addr:street":"Rua Fonte De San;Da;Corun\u0303A",
    "iso:country":"ES",
    "sg:address":"Rua Fonte De San Miguel (da), 8",
    "sg:city":"Santiago De Compostela",
    "sg:orig_category":"Electrodom\u00c9sticos (al Por Menor)",
    "sg:phone":"+34 981 57 50 13",
    "sg:postcode":"15704",
    "sg:province":"La Coru\u00f1a",
    "wof:name":"Jose Luis Jimenez Fuentes Y Alberto Leis Conde S.c.",
    "wof:placetype":"venue"
},
  "geometry": {"coordinates":[-8.5433635712,42.8819007874],"type":"Point"}
}