{
  "type": "Feature",
  "properties": {
    "addr:full":"Calle de Arroyo Gadea, 12 Poligono Sta M. De Benquerencia Toledo 45007",
    "addr:housenumber":"12 poligono",
    "addr:postcode":"45007",
    "addr:street":"Calle De Arroyo Gadea;Sta M. De Benquerencia",
    "iso:country":"ES",
    "sg:address":"Calle de Arroyo Gadea, 12",
    "sg:city":"Poligono Sta M. De Benquerencia",
    "sg:orig_category":"Transportes Por Carretera: Lotes Completos, Mercanc\u00cdas Diversas",
    "sg:phone":"+34 925 23 13 36",
    "sg:postcode":"45007",
    "sg:province":"Toledo",
    "wof:name":"Disjevi Cdad",
    "wof:placetype":"venue"
},
  "geometry": {"coordinates":[-4.0244760513,39.8567771912],"type":"Point"}
}