{
  "type": "Feature",
  "properties": {
    "iso:country":"ES",
    "sg:address":"Avda Pais Valencia, 16",
    "sg:city":"Torrent",
    "sg:orig_category":"Arquitectos",
    "sg:phone":"+34 961 56 36 92",
    "sg:postcode":"46900",
    "sg:province":"Valencia",
    "wof:name":"Mu\u00f1oz Fernandez Jesus",
    "wof:placetype":"venue"
},
  "geometry": {"coordinates":[-0.4661119878,39.4360580444],"type":"Point"}
}