{
  "type": "Feature",
  "properties": {
    "iso:country":"ES",
    "sg:address":"Calle de Noria, 12",
    "sg:city":"Cartaya",
    "sg:orig_category":"Institutos De Belleza",
    "sg:phone":"+34 959 39 28 21",
    "sg:postcode":"21450",
    "sg:province":"Huelva",
    "wof:name":"Rodriguez Ruiz Maria Julia",
    "wof:placetype":"venue"
},
  "geometry": {"coordinates":[-7.1479492188,37.2832183838],"type":"Point"}
}