{
  "type": "Feature",
  "properties": {
    "iso:country":"ES",
    "sg:address":"Calle de Ibaigane, 15",
    "sg:city":"Getxo",
    "sg:orig_category":"Fabricaci\u00d3n, Venta, Instalaci\u00d3n De R\u00d3tulos, De R\u00d3tulos Luminosos",
    "sg:phone":"+34 944 64 84 76",
    "sg:postcode":"48930",
    "sg:province":"Vizcaya",
    "wof:name":"Grama Rotulaciones",
    "wof:placetype":"venue"
},
  "geometry": {"coordinates":[-3.009360075,43.3259735107],"type":"Point"}
}