{
  "type": "Feature",
  "properties": {
    "addr:full":"Plaz Garcia Moreno, 4 Orgiva Granada 18400",
    "addr:housenumber":"4",
    "addr:postcode":"18400",
    "addr:street":"Garcia Moreno",
    "iso:country":"ES",
    "sg:address":"Plaz Garcia Moreno, 4",
    "sg:city":"Orgiva",
    "sg:orig_category":"M\u00c9dicos: Estomatolog\u00cda",
    "sg:phone":"+34 958 78 56 52",
    "sg:postcode":"18400",
    "sg:province":"Granada",
    "wof:name":"Romera Ruiz Manuel",
    "wof:placetype":"venue"
},
  "geometry": {"coordinates":[-3.4240720272,36.9012565613],"type":"Point"}
}