{
  "type": "Feature",
  "properties": {
    "iso:country":"ES",
    "sg:address":"Avda Do\u00d1a Francisquita, 14",
    "sg:city":"Sevilla",
    "sg:orig_category":"\u00d3ptica: Instrumentos (fabricaci\u00d3n)",
    "sg:phone":"+34 954 64 26 15",
    "sg:postcode":"41006",
    "sg:province":"Sevilla",
    "wof:name":"Valero Lozano S.l.",
    "wof:placetype":"venue"
},
  "geometry": {"coordinates":[-5.9483737946,37.3746795654],"type":"Point"}
}