{
  "type": "Feature",
  "properties": {
    "iso:country":"ES",
    "sg:address":"Carr Torroella, 57",
    "sg:city":"Palafrugell",
    "sg:orig_category":"Plomeros",
    "sg:phone":"+34 972 30 49 62",
    "sg:postcode":"17200",
    "sg:province":"Girona",
    "wof:name":"Sani-elec Caballe S.a.",
    "wof:placetype":"venue"
},
  "geometry": {"coordinates":[3.1573059559,41.9192047119],"type":"Point"}
}