{
  "type": "Feature",
  "properties": {
    "iso:country":"ES",
    "sg:address":"Calle de Gipuzkoa, 21",
    "sg:city":"Portugalete",
    "sg:orig_category":"Caf\u00c9s, Bares, Cervecer\u00cdas",
    "sg:phone":"+34 944 62 02 50",
    "sg:postcode":"48920",
    "sg:province":"Vizcaya",
    "wof:name":"Garcia Arranz Maria Concepcion",
    "wof:placetype":"venue"
},
  "geometry": {"coordinates":[-3.0219860077,43.3201751709],"type":"Point"}
}