{
  "type": "Feature",
  "properties": {
    "iso:country":"ES",
    "sg:address":"Carr Ulla, 7",
    "sg:city":"Torroella Montgri",
    "sg:orig_category":"Gastronom\u00cda: Especialidades Regionales (al Por Menor)",
    "sg:phone":"+34 972 75 87 80",
    "sg:postcode":"17257",
    "sg:province":"Girona",
    "wof:name":"Figueras Reig Pedro",
    "wof:placetype":"venue"
},
  "geometry": {"coordinates":[3.1277420521,42.042766571],"type":"Point"}
}