{
  "type": "Feature",
  "properties": {
    "addr:full":"Praj Boqueron (el), 2 Boqueron Murcia 30559",
    "addr:postcode":"30559",
    "iso:country":"ES",
    "sg:address":"Praj Boqueron (el), 2",
    "sg:city":"Boqueron",
    "sg:orig_category":"Psic\u00d3logos",
    "sg:phone":"+34 968 43 40 26",
    "sg:postcode":"30559",
    "sg:province":"Murcia",
    "wof:name":"Bernal Palazon Carmelo",
    "wof:placetype":"venue"
},
  "geometry": {"coordinates":[-1.3365139961,38.2396888733],"type":"Point"}
}