{
  "type": "Feature",
  "properties": {
    "addr:full":"C/ Antonio Mora Ferrandez, 26 Elche Alicante 03202",
    "addr:housenumber":"26",
    "addr:postcode":"03202",
    "addr:street":"C / Antonio Mora Ferrandez",
    "iso:country":"ES",
    "sg:address":"C/ Antonio Mora Ferrandez, 26",
    "sg:city":"Elche",
    "sg:orig_category":"Reposter\u00cdas",
    "sg:phone":"+34 965 45 14 76",
    "sg:postcode":"03202",
    "sg:province":"Alicante",
    "wof:name":"Matarredona Bao Juan Ramon",
    "wof:placetype":"venue"
},
  "geometry": {"coordinates":[-0.6845520139,38.2716827393],"type":"Point"}
}