{
  "type": "Feature",
  "properties": {
    "addr:full":"Carrer de Ermita De Bellvitge, 20 Hospitalet Llobregat Barcelona 08907",
    "addr:housenumber":"20",
    "addr:postcode":"08907",
    "addr:street":"Carrer De Ermita De Bellvitge",
    "iso:country":"ES",
    "sg:address":"Carrer de Ermita De Bellvitge, 20",
    "sg:city":"Hospitalet Llobregat",
    "sg:orig_category":"Promotores Constructores",
    "sg:phone":"+34 933 35 05 16",
    "sg:postcode":"08907",
    "sg:province":"Barcelona",
    "wof:name":"Marbore 2000 S.l.",
    "wof:placetype":"venue"
},
  "geometry": {"coordinates":[2.1097779274,41.3482322693],"type":"Point"}
}