{
  "type": "Feature",
  "properties": {
    "addr:full":"Carr Costera (de La), 9 Alaquas Valencia 46970",
    "addr:housenumber":"9",
    "addr:postcode":"46970",
    "addr:street":"Carr Costera De La",
    "iso:country":"ES",
    "sg:address":"Carr Costera (de La), 9",
    "sg:city":"Alaquas",
    "sg:orig_category":"Contenedores (mercanc\u00cdas)",
    "sg:phone":"+34 961 51 51 78",
    "sg:postcode":"46970",
    "sg:province":"Valencia",
    "wof:name":"Transportes Zari\u00d1ena S.l.",
    "wof:placetype":"venue"
},
  "geometry": {"coordinates":[-0.4578439891,39.4546356201],"type":"Point"}
}