{
  "type": "Feature",
  "properties": {
    "addr:full":"Calle de Canal, 30 Igualeja M\u00e1laga 29440",
    "addr:housenumber":"30",
    "addr:postcode":"29440",
    "addr:street":"Calle De Canal",
    "iso:country":"ES",
    "sg:address":"Calle de Canal, 30",
    "sg:city":"Igualeja",
    "sg:orig_category":"Charcuter\u00cdas (al Por Mayor)",
    "sg:phone":"+34 952 18 15 45",
    "sg:postcode":"29440",
    "sg:province":"M\u00e1laga",
    "wof:name":"Cooperativa Embutidos Serrania",
    "wof:placetype":"venue"
},
  "geometry": {"coordinates":[-5.121158123,36.6314315796],"type":"Point"}
}