{
  "type": "Feature",
  "properties": {
    "iso:country":"ES",
    "sg:address":"Calle de Luis Cernuda, 1",
    "sg:city":"Gilena",
    "sg:orig_category":"Producci\u00d3n De Abonos Y De Fertilizantes",
    "sg:phone":"+34 955 82 66 57",
    "sg:postcode":"41565",
    "sg:province":"Sevilla",
    "wof:name":"Fertilizantes Organicos Monta\u00f1o S.l.",
    "wof:placetype":"venue"
},
  "geometry": {"coordinates":[-4.9169387817,37.2543182373],"type":"Point"}
}