{
  "type": "Feature",
  "properties": {
    "addr:full":"Calle de Balsas, 9 Santa Eulalia Murcia 30001",
    "addr:housenumber":"9",
    "addr:postcode":"30001",
    "addr:street":"Calle De Balsas",
    "iso:country":"ES",
    "sg:address":"Calle de Balsas, 9",
    "sg:city":"Santa Eulalia",
    "sg:orig_category":"Traductores",
    "sg:phone":"+34 968 21 49 95",
    "sg:postcode":"30001",
    "sg:province":"Murcia",
    "wof:name":"Gallego Mayordomo Juan Luis",
    "wof:placetype":"venue"
},
  "geometry": {"coordinates":[-1.5738861561,37.7936096191],"type":"Point"}
}