{
  "type": "Feature",
  "properties": {
    "addr:full":"Avda Jose Maria Fernandez, 33 Le\u00f3n Le\u00f3n 24006",
    "addr:housenumber":"33",
    "addr:postcode":"24006",
    "addr:street":"Avda Jose Maria Fernandez;Leo\u0301N",
    "iso:country":"ES",
    "sg:address":"Avda Jose Maria Fernandez, 33",
    "sg:city":"Le\u00f3n",
    "sg:orig_category":"Laboratorios Y Trabajos De Fotograf\u00cda, V\u00cddeo Y Cine",
    "sg:phone":"+34 987 25 53 45",
    "sg:postcode":"24006",
    "sg:province":"Le\u00f3n",
    "wof:name":"Gallego Tejedor Julio Domingo",
    "wof:placetype":"venue"
},
  "geometry": {"coordinates":[-5.5615010262,42.5985527039],"type":"Point"}
}