{
  "type": "Feature",
  "properties": {
    "addr:full":"Calle de General Alvarez De Castro, 17 Madrid Madrid 28010",
    "addr:housenumber":"17",
    "addr:postcode":"madrid;28010",
    "addr:street":"Calle De General Alvarez De Castro",
    "iso:country":"ES",
    "sg:address":"Calle de General Alvarez De Castro, 17",
    "sg:city":"Madrid",
    "sg:orig_category":"Centros Empresariales",
    "sg:phone":"+34 914 48 44 73",
    "sg:postcode":"28010",
    "sg:province":"Madrid",
    "wof:name":"Gutierrez Bada Montserrat",
    "wof:placetype":"venue"
},
  "geometry": {"coordinates":[-3.7023999691,40.4354515076],"type":"Point"}
}