{
  "type": "Feature",
  "properties": {
    "iso:country":"ES",
    "sg:address":"Calle de Suerte (la), 6",
    "sg:city":"Cruz Santa",
    "sg:orig_category":"Tapicer\u00cdas",
    "sg:phone":"+34 922 34 49 04",
    "sg:postcode":"38413",
    "sg:province":"Santa Cruz De Tenerife",
    "sg:website":"www.iespana.es/tapiceriacruzsantattapiceria@terra.es",
    "wof:name":"Tapiceria Cruz Santa S.l.",
    "wof:placetype":"venue"
},
  "geometry": {"coordinates":[-16.5606460571,28.3570613861],"type":"Point"}
}