{
  "type": "Feature",
  "properties": {
    "iso:country":"ES",
    "sg:address":"Carrer de Martorell, 1",
    "sg:city":"S. Cugat Valles",
    "sg:orig_category":"Lencer\u00cda Femenina, Corseter\u00cda, Trajes De Ba\u00d1o (al Por Menor)",
    "sg:phone":"+34 935 89 72 04",
    "sg:postcode":"08172",
    "sg:province":"Barcelona",
    "wof:name":"Aiqueguapa S.l.",
    "wof:placetype":"venue"
},
  "geometry": {"coordinates":[2.0803508759,41.4706764221],"type":"Point"}
}