{
  "type": "Feature",
  "properties": {
    "addr:full":"C/ Alvarez De Castro, 96 Banyoles Girona 17820",
    "addr:housenumber":"96",
    "addr:postcode":"17820",
    "addr:street":"C / Alvarez De Castro",
    "iso:country":"ES",
    "sg:address":"C/ Alvarez De Castro, 96",
    "sg:city":"Banyoles",
    "sg:orig_category":"Sociedades, Compa\u00d1\u00cdas Aseguradoras",
    "sg:phone":"+34 972 57 39 84",
    "sg:postcode":"17820",
    "sg:province":"Girona",
    "wof:name":"Jordi Corbalan Corredoria D'assegurances",
    "wof:placetype":"venue"
},
  "geometry": {"coordinates":[2.7672970295,42.1158943176],"type":"Point"}
}