{
  "type": "Feature",
  "properties": {
    "iso:country":"ES",
    "sg:address":"Calle de Historiador Palau, 7",
    "sg:city":"Denia",
    "sg:orig_category":"Sindicatos De Trabajadores",
    "sg:phone":"+34 965 78 80 06",
    "sg:postcode":"03700",
    "sg:province":"Alicante",
    "wof:name":"U.g.t",
    "wof:placetype":"venue"
},
  "geometry": {"coordinates":[0.1056630015,38.8385467529],"type":"Point"}
}