{
  "type": "Feature",
  "properties": {
    "addr:full":"Rbla Catalana, 68 Hospitalet Llobregat Barcelona 08903",
    "addr:housenumber":"68",
    "addr:postcode":"08903",
    "addr:street":"Rbla Catalana",
    "iso:country":"ES",
    "sg:address":"Rbla Catalana, 68",
    "sg:city":"Hospitalet Llobregat",
    "sg:orig_category":"Herboristas (al Por Menor)",
    "sg:phone":"+34 934 40 50 78",
    "sg:postcode":"08903",
    "sg:province":"Barcelona",
    "wof:name":"Tomas Jane Maria Angels",
    "wof:placetype":"venue"
},
  "geometry": {"coordinates":[2.1234400272,41.3702278137],"type":"Point"}
}