{
  "type": "Feature",
  "properties": {
    "addr:full":"Calle de Arbidea, 1 Bilbao Vizcaya 48004",
    "addr:housenumber":"1",
    "addr:postcode":"48004",
    "addr:street":"Calle De Arbidea",
    "iso:country":"ES",
    "sg:address":"Calle de Arbidea, 1",
    "sg:city":"Bilbao",
    "sg:orig_category":"Asociaciones, Organismos Culturales Y Socioeducativos",
    "sg:phone":"+34 944 16 23 93",
    "sg:postcode":"48004",
    "sg:province":"Vizcaya",
    "sg:website":"www.bizkaie.biz",
    "wof:name":"Asociacion Bizkai Alkarte Kulturala",
    "wof:placetype":"venue"
},
  "geometry": {"coordinates":[-2.9082098007,43.2556037903],"type":"Point"}
}