{
  "type": "Feature",
  "properties": {
    "addr:full":"Calle de Ciscar, 62 Valencia Valencia 46005",
    "addr:housenumber":"62",
    "addr:postcode":"46005",
    "addr:street":"Calle De Ciscar",
    "iso:country":"ES",
    "sg:address":"Calle de Ciscar, 62",
    "sg:city":"Valencia",
    "sg:orig_category":"Ingeniero",
    "sg:phone":"+34 963 95 02 05",
    "sg:postcode":"46005",
    "sg:province":"Valencia",
    "wof:name":"Diaz Planells Carlos",
    "wof:placetype":"venue"
},
  "geometry": {"coordinates":[-0.3640106916,39.463634491],"type":"Point"}
}