{
  "type": "Feature",
  "properties": {
    "addr:full":"Calle de Sierra De Fondon, 78 Almeria Almer\u00eda 04009",
    "addr:housenumber":"78",
    "addr:postcode":"04009",
    "addr:street":"Calle De Sierra De Fondon",
    "iso:country":"ES",
    "sg:address":"Calle de Sierra De Fondon, 78",
    "sg:city":"Almeria",
    "sg:orig_category":"Agencias Y Agentes Comerciales, Representantes",
    "sg:phone":"+34 950 14 51 25",
    "sg:postcode":"04009",
    "sg:province":"Almer\u00eda",
    "wof:name":"Dionis Cabezas Juan",
    "wof:placetype":"venue"
},
  "geometry": {"coordinates":[-2.4500310421,36.8582687378],"type":"Point"}
}