{
  "type": "Feature",
  "properties": {
    "addr:full":"Pque San Adrian, 12 Logro\u00f1o La Rioja 26006",
    "addr:housenumber":"12",
    "addr:postcode":"26006",
    "addr:street":"Adrian;Rioja",
    "iso:country":"ES",
    "sg:address":"Pque San Adrian, 12",
    "sg:city":"Logro\u00f1o",
    "sg:orig_category":"Panader\u00cdas, Panader\u00cdas",
    "sg:phone":"+34 941 21 32 80",
    "sg:postcode":"26006",
    "sg:province":"La Rioja",
    "wof:name":"Guirlache Iripai S.l.",
    "wof:placetype":"venue"
},
  "geometry": {"coordinates":[-2.3912363052,42.4574165344],"type":"Point"}
}