{
  "type": "Feature",
  "properties": {
    "iso:country":"ES",
    "sg:address":"Carrer de Rutlla (la), 2",
    "sg:city":"Terrassa",
    "sg:orig_category":"Reposter\u00cdas",
    "sg:phone":"+34 937 80 27 28",
    "sg:postcode":"08221",
    "sg:province":"Barcelona",
    "wof:name":"Forn De La Rutlla C.b.",
    "wof:placetype":"venue"
},
  "geometry": {"coordinates":[2.0116729736,41.5613365173],"type":"Point"}
}