{
  "type": "Feature",
  "properties": {
    "iso:country":"ES",
    "sg:address":"Carrer de Jocs Florals, 18",
    "sg:city":"Barcelona",
    "sg:orig_category":"Asesor\u00cda Sobre Comunicaci\u00d3n De Empresas",
    "sg:phone":"+34 934 90 29 34",
    "sg:postcode":"08028",
    "sg:province":"Barcelona",
    "wof:name":"Bolea Utreras Miguel Angel",
    "wof:placetype":"venue"
},
  "geometry": {"coordinates":[2.1343100071,41.3750114441],"type":"Point"}
}