{
  "type": "Feature",
  "properties": {
    "addr:full":"Ptge Rossello, 17 S. Cugat Valles Barcelona 08172",
    "addr:housenumber":"17",
    "addr:postcode":"08172",
    "addr:street":"Ptge Rossello;S. Cugat Valles Barcelona",
    "iso:country":"ES",
    "sg:address":"Ptge Rossello, 17",
    "sg:city":"S. Cugat Valles",
    "sg:orig_category":"Asociaciones Y Clubs Deportivos",
    "sg:phone":"+34 935 89 53 48",
    "sg:postcode":"08172",
    "sg:province":"Barcelona",
    "wof:name":"Raventos Llorenc C.b.",
    "wof:placetype":"venue"
},
  "geometry": {"coordinates":[2.0793271065,41.4693450928],"type":"Point"}
}