{
  "type": "Feature",
  "properties": {
    "addr:full":"Calle de San Juan De Ortega, 15 Burgos Burgos 09007",
    "addr:housenumber":"15",
    "addr:postcode":"09007",
    "addr:street":"Calle De San Juan De Ortega",
    "iso:country":"ES",
    "sg:address":"Calle de San Juan De Ortega, 15",
    "sg:city":"Burgos",
    "sg:orig_category":"Pescader\u00cdas (al Por Menor)",
    "sg:phone":"+34 947 22 31 67",
    "sg:postcode":"09007",
    "sg:province":"Burgos",
    "wof:name":"Due\u00f1as Llana Victor",
    "wof:placetype":"venue"
},
  "geometry": {"coordinates":[-3.6682879925,42.3491439819],"type":"Point"}
}