{
  "type": "Feature",
  "properties": {
    "iso:country":"ES",
    "sg:address":"Plaz Balcon De Europa, 2",
    "sg:city":"Nerja",
    "sg:orig_category":"Caf\u00c9s, Bares, Cervecer\u00cdas",
    "sg:phone":"+34 952 52 16 82",
    "sg:postcode":"29780",
    "sg:province":"M\u00e1laga",
    "wof:name":"Albi\u00f1ana Lopez Juan-luis",
    "wof:placetype":"venue"
},
  "geometry": {"coordinates":[-3.834997654,36.7956962585],"type":"Point"}
}