{
  "type": "Feature",
  "properties": {
    "addr:full":"Kale Nagusia, 21 Usurbil Guip\u00f9zcoa 20170",
    "addr:housenumber":"21",
    "addr:postcode":"20170",
    "addr:street":"Kale Nagusia;Guipu\u0300Zcoa",
    "iso:country":"ES",
    "sg:address":"Kale Nagusia, 21",
    "sg:city":"Usurbil",
    "sg:orig_category":"Carnicer\u00cdas, Carnicer\u00cdas",
    "sg:phone":"+34 943 36 48 00",
    "sg:postcode":"20170",
    "sg:province":"Guip\u00f9zcoa",
    "wof:name":"Chapartegui Sarasola Eusebio",
    "wof:placetype":"venue"
},
  "geometry": {"coordinates":[-2.0539140701,43.2733459473],"type":"Point"}
}