{
  "type": "Feature",
  "properties": {
    "iso:country":"ES",
    "sg:address":"Pl Doctor Letamendi, 37",
    "sg:city":"Barcelona",
    "sg:orig_category":"M\u00c9dicos: Otorrinolaringolog\u00cda",
    "sg:phone":"+34 934 53 30 37",
    "sg:postcode":"08007",
    "sg:province":"Barcelona",
    "wof:name":"Ezcurra Arbulu Angel Isaac",
    "wof:placetype":"venue"
},
  "geometry": {"coordinates":[2.1613759995,41.3887863159],"type":"Point"}
}