{
  "type": "Feature",
  "properties": {
    "addr:full":"Ctra Olesa, Km. 0006,0 Can Trias Barcelona 08232",
    "addr:postcode":"08232",
    "addr:street":"Ctra Olesa Km. 0006,0;Barcelona",
    "iso:country":"ES",
    "sg:address":"Ctra Olesa, Km. 0006,0",
    "sg:city":"Can Trias",
    "sg:orig_category":"Fabricaci\u00d3n De Enlosados, Soler\u00cdas",
    "sg:phone":"+34 937 34 19 20",
    "sg:postcode":"08232",
    "sg:province":"Barcelona",
    "wof:name":"Tecnova De Catalunya S.l.",
    "wof:placetype":"venue"
},
  "geometry": {"coordinates":[1.9540849924,41.5552368164],"type":"Point"}
}