{
  "type": "Feature",
  "properties": {
    "addr:full":"Calle de Sor Angela De La Cruz, 17 Madrid Madrid 28020",
    "addr:housenumber":"17",
    "addr:postcode":"madrid;28020",
    "addr:street":"Calle De Sor Angela De La Cruz",
    "iso:country":"ES",
    "sg:address":"Calle de Sor Angela De La Cruz, 17",
    "sg:city":"Madrid",
    "sg:orig_category":"Cajas De Ahorro",
    "sg:phone":"+34 915 70 43 93",
    "sg:postcode":"28020",
    "sg:province":"Madrid",
    "sg:website":"www.lacaixa.es",
    "wof:name":"Caixa D'estalvis I Pensions De Barcelona",
    "wof:placetype":"venue"
},
  "geometry": {"coordinates":[-3.6963028908,40.4598274231],"type":"Point"}
}