{
  "type": "Feature",
  "properties": {
    "iso:country":"ES",
    "sg:address":"Pol Ind Saprelorca, S/n",
    "sg:city":"Lorca",
    "sg:orig_category":"Cueros Y Pieles (al Por Mayor)",
    "sg:phone":"+34 968 47 12 23",
    "sg:postcode":"30800",
    "sg:province":"Murcia",
    "wof:name":"Krambel Roms S.l",
    "wof:placetype":"venue"
},
  "geometry": {"coordinates":[-1.6905640364,37.680557251],"type":"Point"}
}