{
  "type": "Feature",
  "properties": {
    "addr:full":"Ctra Puig Major, Des, Km. 0050,0 Horta Islas Baleares 07100",
    "addr:postcode":"07100",
    "addr:street":"Ctra Puig Major Des Km. 0050,0",
    "iso:country":"ES",
    "sg:address":"Ctra Puig Major, Des, Km. 0050,0",
    "sg:city":"Horta",
    "sg:orig_category":"Producci\u00d3n, Venta De Productos De Agricultura Biol\u00d3gica",
    "sg:phone":"+34 971 63 08 80",
    "sg:postcode":"07100",
    "sg:province":"Islas Baleares",
    "wof:name":"Cusenat S.a.",
    "wof:placetype":"venue"
},
  "geometry": {"coordinates":[2.7147779465,39.7659072876],"type":"Point"}
}