{
  "type": "Feature",
  "properties": {
    "iso:country":"ES",
    "sg:address":"Calle de Infantado (del), 3",
    "sg:city":"Buitrago Del Lozoya",
    "sg:orig_category":"Alquiler De Casas Y Habitaciones Amuebladas",
    "sg:phone":"+34 918 68 00 83",
    "sg:postcode":"28730",
    "sg:province":"Madrid",
    "wof:name":"Religiosas De Maria Inmaculada",
    "wof:placetype":"venue"
},
  "geometry": {"coordinates":[-3.6349918842,40.9951782227],"type":"Point"}
}