{
  "type": "Feature",
  "properties": {
    "addr:full":"Calle de Oca\u00d1a, 124 Madrid Madrid 28047",
    "addr:housenumber":"124",
    "addr:postcode":"28047",
    "addr:street":"Calle De Ocan\u0303A",
    "iso:country":"ES",
    "sg:address":"Calle de Oca\u00d1a, 124",
    "sg:city":"Madrid",
    "sg:orig_category":"Librer\u00cdas",
    "sg:phone":"+34 917 19 48 29",
    "sg:postcode":"28047",
    "sg:province":"Madrid",
    "wof:name":"Gibaja Valiente Virginia",
    "wof:placetype":"venue"
},
  "geometry": {"coordinates":[-3.7556500435,40.386920929],"type":"Point"}
}