{
  "type": "Feature",
  "properties": {
    "addr:full":"Av Montevideo, 55 Vilassar De Mar Barcelona 08340",
    "addr:housenumber":"55",
    "addr:postcode":"08340",
    "addr:street":"Av Montevideo",
    "iso:country":"ES",
    "sg:address":"Av Montevideo, 55",
    "sg:city":"Vilassar De Mar",
    "sg:orig_category":"Librer\u00cdas",
    "sg:phone":"+34 937 59 07 35",
    "sg:postcode":"08340",
    "sg:province":"Barcelona",
    "wof:name":"Cuquet Guimera Maria Teresa",
    "wof:placetype":"venue"
},
  "geometry": {"coordinates":[2.3884000778,41.5076217651],"type":"Point"}
}