{
  "type": "Feature",
  "properties": {
    "addr:full":"Barr Larra, S/n Amorebieta Vizcaya 48340",
    "addr:housenumber":"s / n",
    "addr:postcode":"48340",
    "addr:street":"Larra",
    "iso:country":"ES",
    "sg:address":"Barr Larra, S/n",
    "sg:city":"Amorebieta",
    "sg:orig_category":"Centros De Educaci\u00d3n Especial",
    "sg:phone":"+34 946 73 04 30",
    "sg:postcode":"48340",
    "sg:province":"Vizcaya",
    "wof:name":"Gobierno Vasco-eusko Jaurlaritza",
    "wof:placetype":"venue"
},
  "geometry": {"coordinates":[-2.7367351055,43.2294998169],"type":"Point"}
}