{
  "type": "Feature",
  "properties": {
    "iso:country":"ES",
    "sg:address":"Calle de Plaza (de La), 196",
    "sg:city":"Pto Real",
    "sg:orig_category":"Peluquer\u00cdas, Peluquer\u00cda Mixta",
    "sg:phone":"+34 956 47 51 11",
    "sg:postcode":"11510",
    "sg:province":"C\u00e1diz",
    "wof:name":"Fernandez Corcoles Maria Del Carmen",
    "wof:placetype":"venue"
},
  "geometry": {"coordinates":[-6.1939368248,36.5290603638],"type":"Point"}
}