{
  "type": "Feature",
  "properties": {
    "iso:country":"ES",
    "sg:address":"Calle de Estacion, 21",
    "sg:city":"Valladolid",
    "sg:orig_category":"M\u00c9dicos: Medicina Legal, Peritajes M\u00c9dicos",
    "sg:phone":"+34 983 20 00 89",
    "sg:postcode":"47004",
    "sg:province":"Valladolid",
    "wof:name":"Diez Otero Eduardo Luis",
    "wof:placetype":"venue"
},
  "geometry": {"coordinates":[-4.7232351303,41.6441268921],"type":"Point"}
}