{
  "type": "Feature",
  "properties": {
    "iso:country":"ES",
    "sg:address":"Balcaide, 4",
    "sg:city":"Balcaide",
    "sg:orig_category":"Quincaller\u00cda (al Por Menor)",
    "sg:phone":"+34 981 54 81 67",
    "sg:postcode":"15895",
    "sg:province":"A Coru\u00f1a",
    "wof:name":"Varela Bujan German",
    "wof:placetype":"venue"
},
  "geometry": {"coordinates":[-8.5794343948,42.8416137695],"type":"Point"}
}