{
  "type": "Feature",
  "properties": {
    "iso:country":"ES",
    "sg:address":"Carrer de Bergueda, 1",
    "sg:city":"S. Andreu Barca",
    "sg:orig_category":"Carnicer\u00cdas, Carnicer\u00cdas",
    "sg:phone":"+34 936 53 04 04",
    "sg:postcode":"08740",
    "sg:province":"Barcelona",
    "wof:name":"Aguilar Delgado Antonio",
    "wof:placetype":"venue"
},
  "geometry": {"coordinates":[1.9643739462,41.4532661438],"type":"Point"}
}