{
  "type": "Feature",
  "properties": {
    "iso:country":"ES",
    "sg:address":"Calle de Baltasar Gracian, 6",
    "sg:city":"Zaragoza",
    "sg:classifiers":[
        {
            "category":"Personal",
            "subcategory":"Barber",
            "type":"Services"
        }
    ],
    "sg:phone":"+34 976 35 84 96",
    "sg:postcode":"50005",
    "sg:province":"Zaragoza",
    "sg:tags":[
        "caballeros",
        "de",
        "peluqueros"
    ],
    "wof:name":"Lostal Martinez Pedro",
    "wof:placetype":"venue"
},
  "geometry": {"coordinates":[-0.8932862282,41.643913269],"type":"Point"}
}