{
  "type": "Feature",
  "properties": {
    "iso:country":"ES",
    "sg:address":"Ctra Madrid Toledo (izquierda), Km. 0044,6",
    "sg:city":"Yuncos",
    "sg:orig_category":"Pintura, Barniz, Productos Asimilables (fabricaci\u00d3n, Al Por Mayor)",
    "sg:phone":"+34 925 55 70 18",
    "sg:postcode":"45210",
    "sg:province":"Toledo",
    "wof:name":"Exclusivas Dibar S.l.",
    "wof:placetype":"venue"
},
  "geometry": {"coordinates":[-3.8721139431,40.0867118835],"type":"Point"}
}