{
  "type": "Feature",
  "properties": {
    "addr:full":"Carr Ample, 9 Petra Islas Baleares 07520",
    "addr:housenumber":"9",
    "addr:postcode":"07520",
    "addr:street":"Carr Ample",
    "iso:country":"ES",
    "sg:address":"Carr Ample, 9",
    "sg:city":"Petra",
    "sg:orig_category":"Electrodom\u00c9sticos (al Por Menor)",
    "sg:phone":"+34 971 56 11 05",
    "sg:postcode":"07520",
    "sg:province":"Islas Baleares",
    "wof:name":"Gual Bauza Rafael",
    "wof:placetype":"venue"
},
  "geometry": {"coordinates":[3.112003088,39.615737915],"type":"Point"}
}