{
  "type": "Feature",
  "properties": {
    "addr:full":"Calle de Loiola, 11 Donostia-san Sebastian Guip\u00f9zcoa 20005",
    "addr:housenumber":"11",
    "addr:postcode":"20005",
    "addr:street":"Calle De Loiola",
    "iso:country":"ES",
    "sg:address":"Calle de Loiola, 11",
    "sg:city":"Donostia-san Sebastian",
    "sg:orig_category":"Ropa Para Ni\u00d1os (al Por Menor)",
    "sg:phone":"+34 943 42 16 42",
    "sg:postcode":"20005",
    "sg:province":"Guip\u00f9zcoa",
    "wof:name":"Arsuaga Rubio Maria Luisa",
    "wof:placetype":"venue"
},
  "geometry": {"coordinates":[-1.9827096462,43.3182487488],"type":"Point"}
}