{
  "type": "Feature",
  "properties": {
    "addr:full":"Calle de Perez Diaz, 3 Victoria Acentejo Santa Cruz De Tenerife 38380",
    "addr:housenumber":"3",
    "addr:postcode":"38380",
    "addr:street":"Calle De Perez Diaz",
    "iso:country":"ES",
    "sg:address":"Calle de Perez Diaz, 3",
    "sg:city":"Victoria Acentejo",
    "sg:orig_category":"Laboratorios Y Trabajos De Fotograf\u00cda, V\u00cddeo Y Cine",
    "sg:phone":"+34 922 58 21 31",
    "sg:postcode":"38380",
    "sg:province":"Santa Cruz De Tenerife",
    "wof:name":"Garcia Gutierrez Angel Miguel",
    "wof:placetype":"venue"
},
  "geometry": {"coordinates":[-16.4665660858,28.4356803894],"type":"Point"}
}