{
  "type": "Feature",
  "properties": {
    "addr:full":"Ctra Tavernes Valldigna-lliria, Km. 0088,4 Vilamarxant Valencia 46191",
    "addr:postcode":"46191",
    "addr:street":"Ctra Tavernes Valldigna-Lliria Km. 0088,4",
    "iso:country":"ES",
    "sg:address":"Ctra Tavernes Valldigna-lliria, Km. 0088,4",
    "sg:city":"Vilamarxant",
    "sg:orig_category":"Fabrica De Cer\u00c1micas",
    "sg:phone":"+34 962 71 03 17",
    "sg:postcode":"46191",
    "sg:province":"Valencia",
    "wof:name":"Platart S.l.",
    "wof:placetype":"venue"
},
  "geometry": {"coordinates":[-0.6272540092,39.5677604675],"type":"Point"}
}