{
  "type": "Feature",
  "properties": {
    "addr:full":"Avda Aureliano San Roman, 23 Oviedo Asturias 33011",
    "addr:housenumber":"23",
    "addr:postcode":"33011",
    "addr:street":"Avda Aureliano San Roman",
    "iso:country":"ES",
    "sg:address":"Avda Aureliano San Roman, 23",
    "sg:city":"Oviedo",
    "sg:orig_category":"Inmobiliaria (agencias)",
    "sg:phone":"+34 985 11 57 35",
    "sg:postcode":"33011",
    "sg:province":"Asturias",
    "wof:name":"G.i.ga, Sl",
    "wof:placetype":"venue"
},
  "geometry": {"coordinates":[-5.8409070969,43.3704948425],"type":"Point"}
}