{
  "type": "Feature",
  "properties": {
    "iso:country":"ES",
    "sg:address":"Calle de Santa Lucia, 9",
    "sg:city":"Santa Engracia De Loarre",
    "sg:orig_category":"Agencias Y Agentes Comerciales, Representantes",
    "sg:phone":"+34 974 38 26 46",
    "sg:postcode":"22809",
    "sg:province":"Huesca",
    "wof:name":"Girasolar S.c.",
    "wof:placetype":"venue"
},
  "geometry": {"coordinates":[-0.644464016,42.313293457],"type":"Point"}
}