{
  "type": "Feature",
  "properties": {
    "iso:country":"ES",
    "sg:address":"Calle de Santiago Cuadrado, 5",
    "sg:city":"San Cristobal De La Laguna",
    "sg:orig_category":"M\u00c9dicos: An\u00c1lisis Cl\u00cdnicos",
    "sg:phone":"+34 922 26 32 12",
    "sg:postcode":"38201",
    "sg:province":"Santa Cruz De Tenerife",
    "wof:name":"Sanchez Gamarro Nelly Del Carmen",
    "wof:placetype":"venue"
},
  "geometry": {"coordinates":[-16.3154506683,28.4914455414],"type":"Point"}
}