{
  "type": "Feature",
  "properties": {
    "addr:full":"C/ Hermanos Navarro Caracena, 31 Elche Alicante 03206",
    "addr:housenumber":"31",
    "addr:postcode":"03206",
    "addr:street":"C / Hermanos Navarro Caracena",
    "iso:country":"ES",
    "sg:address":"C/ Hermanos Navarro Caracena, 31",
    "sg:city":"Elche",
    "sg:orig_category":"Chapister\u00cda",
    "sg:phone":"+34 965 43 32 44",
    "sg:postcode":"03206",
    "sg:province":"Alicante",
    "wof:name":"Maestre Perez Francisco",
    "wof:placetype":"venue"
},
  "geometry": {"coordinates":[-0.7077090144,38.2714004517],"type":"Point"}
}