{
  "type": "Feature",
  "properties": {
    "iso:country":"ES",
    "sg:address":"Carr Major, 126",
    "sg:city":"Benifaio",
    "sg:orig_category":"Reposter\u00cdas",
    "sg:phone":"+34 961 78 13 46",
    "sg:postcode":"46450",
    "sg:province":"Valencia",
    "wof:name":"Pellicer Campos Carlos",
    "wof:placetype":"venue"
},
  "geometry": {"coordinates":[-0.4227479994,39.2867622375],"type":"Point"}
}