{
  "type": "Feature",
  "properties": {
    "iso:country":"ES",
    "sg:address":"Avda Maria Auxiliadora, 14",
    "sg:city":"Utrera",
    "sg:orig_category":"Reposter\u00cdas",
    "sg:phone":"+34 955 86 52 93",
    "sg:postcode":"41710",
    "sg:province":"Sevilla",
    "wof:name":"Obando Lopez Francisco De Paula",
    "wof:placetype":"venue"
},
  "geometry": {"coordinates":[-5.7784919739,37.1834716797],"type":"Point"}
}