{
  "type": "Feature",
  "properties": {
    "addr:full":"Betanzos, 5 Pontedeume La Coru\u00f1a 15600",
    "addr:postcode":"15600",
    "addr:street":"Pontedeume;Corun\u0303A",
    "iso:country":"ES",
    "sg:address":"Betanzos, 5",
    "sg:city":"Pontedeume",
    "sg:orig_category":"Ropa Para Ni\u00d1os (al Por Menor)",
    "sg:phone":"+34 981 43 38 08",
    "sg:postcode":"15600",
    "sg:province":"La Coru\u00f1a",
    "wof:name":"Feal Noche Victoria",
    "wof:placetype":"venue"
},
  "geometry": {"coordinates":[-8.1719465256,43.4070129395],"type":"Point"}
}