{
  "type": "Feature",
  "properties": {
    "addr:full":"Pol Ind La Celulosa, S/n Almeria Almer\u00eda 04006",
    "addr:housenumber":"s / n",
    "addr:postcode":"04006",
    "iso:country":"ES",
    "sg:address":"Pol Ind La Celulosa, S/n",
    "sg:city":"Almeria",
    "sg:orig_category":"Frutas Y Legumbres Frescas (al Por Mayor)",
    "sg:phone":"+34 950 22 12 30",
    "sg:postcode":"04006",
    "sg:province":"Almer\u00eda",
    "wof:name":"Salcedo Jimenez Manuel",
    "wof:placetype":"venue"
},
  "geometry": {"coordinates":[-2.4608390331,36.8422698975],"type":"Point"}
}