{
  "type": "Feature",
  "properties": {
    "addr:full":"Calle de Ramon Jimenez, 3 Pozuelo De Alarcon Madrid 28223",
    "addr:housenumber":"3",
    "addr:postcode":"28223",
    "addr:street":"Calle De Ramon Jimenez",
    "iso:country":"ES",
    "sg:address":"Calle de Ramon Jimenez, 3",
    "sg:city":"Pozuelo De Alarcon",
    "sg:orig_category":"Florister\u00cdas",
    "sg:phone":"+34 917 15 80 40",
    "sg:postcode":"28223",
    "sg:province":"Madrid",
    "wof:name":"Magdaleno Lorenzo Jose Miguel",
    "wof:placetype":"venue"
},
  "geometry": {"coordinates":[-3.8150010109,40.4350967407],"type":"Point"}
}