{
  "type": "Feature",
  "properties": {
    "iso:country":"ES",
    "sg:address":"Kale Nagusia, 24",
    "sg:city":"Idiazabal",
    "sg:orig_category":"Molduras, Junquillos, Listones Y Molduras Perforadas",
    "sg:phone":"+34 943 18 71 25",
    "sg:postcode":"20213",
    "sg:province":"Guip\u00f9zcoa",
    "wof:name":"Aramburu Telleria Jose Maria",
    "wof:placetype":"venue"
},
  "geometry": {"coordinates":[-2.2326641083,43.0135421753],"type":"Point"}
}