{
  "type": "Feature",
  "properties": {
    "addr:full":"Avgd De Magallanes, 1 Benicarlo Castell\u00f3n 12580",
    "addr:housenumber":"1",
    "addr:postcode":"12580",
    "iso:country":"ES",
    "sg:address":"Avgd De Magallanes, 1",
    "sg:city":"Benicarlo",
    "sg:orig_category":"Agentes, Concesionarios Y Sucursales De Veh\u00cdculos",
    "sg:phone":"+34 964 46 72 40",
    "sg:postcode":"12580",
    "sg:province":"Castell\u00f3n",
    "wof:name":"Esteller Import S.l.",
    "wof:placetype":"venue"
},
  "geometry": {"coordinates":[0.4042100012,40.4457893372],"type":"Point"}
}