{
  "type": "Feature",
  "properties": {
    "addr:full":"Calle de Fuencarral, 90 Madrid Madrid 28004",
    "addr:housenumber":"90",
    "addr:postcode":"madrid;28004",
    "addr:street":"Calle De Fuencarral",
    "iso:country":"ES",
    "sg:address":"Calle de Fuencarral, 90",
    "sg:city":"Madrid",
    "sg:orig_category":"Doctores En Medicina",
    "sg:phone":"+34 915 23 51 85",
    "sg:postcode":"28004",
    "sg:province":"Madrid",
    "wof:name":"Lopez Chollet Carlos",
    "wof:placetype":"venue"
},
  "geometry": {"coordinates":[-3.7016294003,40.4271888733],"type":"Point"}
}