{
  "type": "Feature",
  "properties": {
    "iso:country":"ES",
    "sg:address":"Calle de Joaquin Del Pielago, S/n",
    "sg:city":"Comillas",
    "sg:orig_category":"Supermercados Y Hipermercados",
    "sg:phone":"+34 942 72 25 35",
    "sg:postcode":"39520",
    "sg:province":"Cantabria",
    "wof:name":"Grupo El Arbol Distribucion Y Supermercados S.a. Unipersonal",
    "wof:placetype":"venue"
},
  "geometry": {"coordinates":[-4.2915391922,43.3854484558],"type":"Point"}
}