{
  "type": "Feature",
  "properties": {
    "iso:country":"ES",
    "sg:address":"Avda Carde\u00d1a (de), S/n",
    "sg:city":"Villanueva Cordoba",
    "sg:orig_category":"Veh\u00cdculos De Ocasi\u00d3n",
    "sg:phone":"+34 957 12 90 68",
    "sg:postcode":"14440",
    "sg:province":"C\u00f3rdoba",
    "wof:name":"Autos Genesis S.c.p.",
    "wof:placetype":"venue"
},
  "geometry": {"coordinates":[-4.571390152,38.3127403259],"type":"Point"}
}