{
  "type": "Feature",
  "properties": {
    "addr:full":"Calle de Maestro Calles, 7 Santurtzi Vizcaya 48980",
    "addr:postcode":"48980",
    "addr:street":"Calle De Maestro Calles 7",
    "iso:country":"ES",
    "sg:address":"Calle de Maestro Calles, 7",
    "sg:city":"Santurtzi",
    "sg:orig_category":"Molduras, Junquillos, Listones Y Molduras Perforadas",
    "sg:phone":"+34 944 83 75 28",
    "sg:postcode":"48980",
    "sg:province":"Vizcaya",
    "wof:name":"Jose Luis Landera Benito",
    "wof:placetype":"venue"
},
  "geometry": {"coordinates":[-3.0333940983,43.3299484253],"type":"Point"}
}