{
  "type": "Feature",
  "properties": {
    "iso:country":"ES",
    "sg:address":"Carrer de Abat Guillem D'avinyo, 8",
    "sg:city":"S. Cugat Valles",
    "sg:orig_category":"Arquitectos",
    "sg:phone":"+34 936 74 30 15",
    "sg:postcode":"08172",
    "sg:province":"Barcelona",
    "wof:name":"Alvacor S.a.",
    "wof:placetype":"venue"
},
  "geometry": {"coordinates":[2.0867261887,41.4749298096],"type":"Point"}
}