{
  "type": "Feature",
  "properties": {
    "addr:full":"Pla\u00c7 Independencia, 11 Girona Girona 17001",
    "addr:housenumber":"11",
    "addr:postcode":"17001",
    "addr:street":"Independencia",
    "iso:country":"ES",
    "sg:address":"Pla\u00c7 Independencia, 11",
    "sg:city":"Girona",
    "sg:orig_category":"M\u00c9dicos: Oftalmolog\u00cda",
    "sg:phone":"+34 972 21 80 18",
    "sg:postcode":"17001",
    "sg:province":"Girona",
    "wof:name":"Teruel Maicas Carlos",
    "wof:placetype":"venue"
},
  "geometry": {"coordinates":[2.8235468864,41.9862709045],"type":"Point"}
}