{
  "type": "Feature",
  "properties": {
    "addr:full":"Av Llometes, 2 Tibi Alicante 03109",
    "addr:housenumber":"2",
    "addr:postcode":"03109",
    "addr:street":"Av Llometes",
    "iso:country":"ES",
    "sg:address":"Av Llometes, 2",
    "sg:city":"Tibi",
    "sg:orig_category":"Inmobiliaria (agencias)",
    "sg:phone":"+34 965 61 72 52",
    "sg:postcode":"03109",
    "sg:province":"Alicante",
    "wof:name":"Arraez Paya Jose",
    "wof:placetype":"venue"
},
  "geometry": {"coordinates":[-0.5806086063,38.5316162109],"type":"Point"}
}