{
  "type": "Feature",
  "properties": {
    "addr:full":"Carrer de Sepulveda, 137 Barcelona Barcelona 08011",
    "addr:housenumber":"137",
    "addr:postcode":"08011",
    "addr:street":"Carrer De Sepulveda",
    "iso:country":"ES",
    "sg:address":"Carrer de Sepulveda, 137",
    "sg:city":"Barcelona",
    "sg:orig_category":"Molduras, Junquillos, Listones Y Molduras Perforadas",
    "sg:phone":"+34 934 51 23 69",
    "sg:postcode":"08011",
    "sg:province":"Barcelona",
    "wof:name":"Els Amics De Sepulveda S.l.",
    "wof:placetype":"venue"
},
  "geometry": {"coordinates":[2.1601951122,41.3816566467],"type":"Point"}
}