{
  "type": "Feature",
  "properties": {
    "addr:full":"Ctra Vinyols, 4 Riudoms Tarragona 43330",
    "addr:housenumber":"4",
    "addr:postcode":"43330",
    "addr:street":"Ctra Vinyols",
    "iso:country":"ES",
    "sg:address":"Ctra Vinyols, 4",
    "sg:city":"Riudoms",
    "sg:orig_category":"Aceites Y Grasas Alimentarias (fabricaci\u00d3n, Al Por Mayor)",
    "sg:phone":"+34 977 85 00 36",
    "sg:postcode":"43330",
    "sg:province":"Tarragona",
    "wof:name":"Arboreto S.a.t. Limitada",
    "wof:placetype":"venue"
},
  "geometry": {"coordinates":[1.0567939281,41.1378860474],"type":"Point"}
}