{
  "type": "Feature",
  "properties": {
    "iso:country":"ES",
    "sg:address":"Avda General Franco, 30",
    "sg:city":"Santa Uxia De Ribeira",
    "sg:orig_category":"Agencias De Viajes",
    "sg:phone":"+34 981 87 07 67",
    "sg:postcode":"15960",
    "sg:province":"La Coru\u00f1a",
    "wof:name":"Mario Lorenzo Oscar",
    "wof:placetype":"venue"
},
  "geometry": {"coordinates":[-8.9933700562,42.5599899292],"type":"Point"}
}