{
  "type": "Feature",
  "properties": {
    "addr:full":"C/ Major, 308 Salt Girona 17190",
    "addr:housenumber":"308",
    "addr:postcode":"17190",
    "addr:street":"C / Major",
    "iso:country":"ES",
    "sg:address":"C/ Major, 308",
    "sg:city":"Salt",
    "sg:orig_category":"Servicios De Higiene Y Peluquer\u00cda Para Perros Y Gatos",
    "sg:phone":"+34 972 23 25 51",
    "sg:postcode":"17190",
    "sg:province":"Girona",
    "wof:name":"Llop Puig Jaime",
    "wof:placetype":"venue"
},
  "geometry": {"coordinates":[2.7977600098,41.9759254456],"type":"Point"}
}