{
  "type": "Feature",
  "properties": {
    "iso:country":"ES",
    "sg:address":"Calle de Murga, 29",
    "sg:city":"Palmas De Gran Canaria",
    "sg:orig_category":"Reposter\u00cdas",
    "sg:phone":"+34 928 37 23 79",
    "sg:postcode":"35003",
    "sg:province":"Las Palmas",
    "wof:name":"Frade Perdomo Juan Miguel",
    "wof:placetype":"venue"
},
  "geometry": {"coordinates":[-15.4190130234,28.1112728119],"type":"Point"}
}