{
  "type": "Feature",
  "properties": {
    "iso:country":"ES",
    "sg:address":"Calle de Ramirez De Madrid, 7",
    "sg:city":"Malaga",
    "sg:orig_category":"M\u00c9dicos: Estomatolog\u00cda",
    "sg:phone":"+34 952 26 74 59",
    "sg:postcode":"29013",
    "sg:province":"M\u00e1laga",
    "wof:name":"Repetto Fernandez German Jesus",
    "wof:placetype":"venue"
},
  "geometry": {"coordinates":[-4.4146990776,36.7328109741],"type":"Point"}
}