{
  "type": "Feature",
  "properties": {
    "iso:country":"ES",
    "sg:address":"Av Catalunya (de), 63",
    "sg:city":"Llivia",
    "sg:orig_category":"Centros De Coordinaci\u00d3n",
    "sg:phone":"+34 972 89 63 85",
    "sg:postcode":"17527",
    "sg:province":"Girona",
    "wof:name":"Esta\u00f1ol Prat Enrique",
    "wof:placetype":"venue"
},
  "geometry": {"coordinates":[1.98624897,42.4624023438],"type":"Point"}
}