{
  "type": "Feature",
  "properties": {
    "iso:country":"ES",
    "sg:address":"Cami Rafalet, De, 65",
    "sg:city":"Trebaluger",
    "sg:orig_category":"Empresas De Limpieza",
    "sg:phone":"+34 971 15 00 60",
    "sg:postcode":"07713",
    "sg:province":"Islas Baleares",
    "wof:name":"Toomey  Carole Lesley",
    "wof:placetype":"venue"
},
  "geometry": {"coordinates":[4.2787947655,39.8168907166],"type":"Point"}
}