{
  "type": "Feature",
  "properties": {
    "iso:country":"ES",
    "sg:address":"Pase La Florida, 1",
    "sg:city":"Vitoria-gasteiz",
    "sg:orig_category":"Panader\u00cdas, Panader\u00cdas",
    "sg:phone":"+34 945 23 19 51",
    "sg:postcode":"01005",
    "sg:province":"\u00c1lava",
    "wof:name":"Fernandez De Barrena Lecuona Maria Aranzazu",
    "wof:placetype":"venue"
},
  "geometry": {"coordinates":[-2.675714016,42.8432388306],"type":"Point"}
}