{
  "type": "Feature",
  "properties": {
    "addr:full":"Rua Redondo, 74 Redondo Pontevedra 36649",
    "addr:housenumber":"74",
    "addr:postcode":"36649",
    "addr:street":"Rua Redondo",
    "iso:country":"ES",
    "sg:address":"Rua Redondo, 74",
    "sg:city":"Redondo",
    "sg:orig_category":"Comercio, Reparaci\u00d3n De Motocicletas, Bicicletas Y Piezas Sueltas",
    "sg:phone":"+34 986 55 70 94",
    "sg:postcode":"36649",
    "sg:province":"Pontevedra",
    "sg:website":"www.tx-motor.com",
    "wof:name":"Magari\u00f1os Iglesias Jose Antonio",
    "wof:placetype":"venue"
},
  "geometry": {"coordinates":[-8.7386341095,42.2920913696],"type":"Point"}
}