{
  "type": "Feature",
  "properties": {
    "iso:country":"ES",
    "sg:address":"Calle de Donibane, 84",
    "sg:city":"Pasai Donibane",
    "sg:orig_category":"Molduras, Junquillos, Listones Y Molduras Perforadas",
    "sg:phone":"+34 943 52 39 94",
    "sg:postcode":"20110",
    "sg:province":"Guip\u00f9zcoa",
    "wof:name":"Zaramalilea Barriocanal Juan Carlos",
    "wof:placetype":"venue"
},
  "geometry": {"coordinates":[-1.9197640419,43.3260993958],"type":"Point"}
}