{
  "type": "Feature",
  "properties": {
    "iso:country":"ES",
    "sg:address":"Carrer de Anselm Clave, 2",
    "sg:city":"Mollet Valles",
    "sg:orig_category":"Abogados",
    "sg:phone":"+34 935 70 20 05",
    "sg:postcode":"08100",
    "sg:province":"Barcelona",
    "wof:name":"Mayolas Garcia Rafael",
    "wof:placetype":"venue"
},
  "geometry": {"coordinates":[2.2139439583,41.5376968384],"type":"Point"}
}