{
  "type": "Feature",
  "properties": {
    "addr:full":"Gavian, S/n Lagoa Lugo 27775",
    "addr:postcode":"27775",
    "addr:street":"Gavian S / N",
    "iso:country":"ES",
    "sg:address":"Gavian, S/n",
    "sg:city":"Lagoa",
    "sg:orig_category":"Empresas De Electricidad En General",
    "sg:phone":"+34 982 55 85 14",
    "sg:postcode":"27775",
    "sg:province":"Lugo",
    "wof:name":"Hidroelectrica De La Onza",
    "wof:placetype":"venue"
},
  "geometry": {"coordinates":[-7.4250159264,43.5214004517],"type":"Point"}
}