{
  "type": "Feature",
  "properties": {
    "addr:full":"Calle de Santiago De Compostela, 46 Madrid Madrid 28034",
    "addr:housenumber":"46",
    "addr:postcode":"madrid;28034",
    "addr:street":"Calle De Santiago De Compostela",
    "iso:country":"ES",
    "sg:address":"Calle de Santiago De Compostela, 46",
    "sg:city":"Madrid",
    "sg:orig_category":"Asociaciones, Organismos Culturales Y Socioeducativos",
    "sg:phone":"+34 917 39 80 53",
    "sg:postcode":"28034",
    "sg:province":"Madrid",
    "wof:name":"Grupo Scout 456 Hesperia",
    "wof:placetype":"venue"
},
  "geometry": {"coordinates":[-3.7111389637,40.4809913635],"type":"Point"}
}