{
  "type": "Feature",
  "properties": {
    "iso:country":"ES",
    "sg:address":"Pl Carme, 3",
    "sg:city":"Tarrega",
    "sg:orig_category":"Asociaciones, Organismos Culturales Y Socioeducativos",
    "sg:phone":"+34 973 31 07 34",
    "sg:postcode":"25300",
    "sg:province":"Lleida",
    "wof:name":"Ateneo De Tarrega",
    "wof:placetype":"venue"
},
  "geometry": {"coordinates":[1.1402276754,41.6484107971],"type":"Point"}
}