{
  "type": "Feature",
  "properties": {
    "addr:full":"Calle de Carmen, 26 Zaragoza Zaragoza 50005",
    "addr:housenumber":"26",
    "addr:postcode":"50005",
    "addr:street":"Calle De Carmen",
    "iso:country":"ES",
    "sg:address":"Calle de Carmen, 26",
    "sg:city":"Zaragoza",
    "sg:orig_category":"Librer\u00cdas",
    "sg:phone":"+34 976 21 04 87",
    "sg:postcode":"50005",
    "sg:province":"Zaragoza",
    "wof:name":"Hechos Y Dichos S.coop.l.",
    "wof:placetype":"venue"
},
  "geometry": {"coordinates":[-0.893306613,41.6466140747],"type":"Point"}
}