{
  "type": "Feature",
  "properties": {
    "addr:full":"Avda Cruz Del Campo (la), 33 Sevilla Sevilla 41005",
    "addr:housenumber":"33",
    "addr:postcode":"41005",
    "addr:street":"Avda Cruz Del Campo La",
    "iso:country":"ES",
    "sg:address":"Avda Cruz Del Campo (la), 33",
    "sg:city":"Sevilla",
    "sg:orig_category":"Comadronas",
    "sg:phone":"+34 954 57 89 94",
    "sg:postcode":"41005",
    "sg:province":"Sevilla",
    "wof:name":"Benitez Millan Concepcion",
    "wof:placetype":"venue"
},
  "geometry": {"coordinates":[-5.9655089378,37.3843994141],"type":"Point"}
}