{
  "type": "Feature",
  "properties": {
    "iso:country":"ES",
    "sg:address":"Calle de Buendia, 41",
    "sg:city":"Madrid",
    "sg:orig_category":"Molduras, Junquillos, Listones Y Molduras Perforadas",
    "sg:phone":"+34 915 07 02 30",
    "sg:postcode":"28053",
    "sg:province":"Madrid",
    "wof:name":"Sanz Calvo Simon",
    "wof:placetype":"venue"
},
  "geometry": {"coordinates":[-3.6718521118,40.3812561035],"type":"Point"}
}