{
  "type": "Feature",
  "properties": {
    "addr:full":"Carrer de Sant Antoni Maria Claret, 500 Barcelona Barcelona 08027",
    "addr:housenumber":"500",
    "addr:postcode":"08027",
    "addr:street":"Carrer De Sant Antoni Maria Claret",
    "iso:country":"ES",
    "sg:address":"Carrer de Sant Antoni Maria Claret, 500",
    "sg:city":"Barcelona",
    "sg:orig_category":"Arquitectos",
    "sg:phone":"+34 934 08 72 02",
    "sg:postcode":"08027",
    "sg:province":"Barcelona",
    "wof:name":"A. Barbero Studi D'arquitectura S.l.",
    "wof:placetype":"venue"
},
  "geometry": {"coordinates":[2.083564,41.369175],"type":"Point"}
}