{
  "type": "Feature",
  "properties": {
    "iso:country":"ES",
    "sg:address":"Calle de Chapatal, 15",
    "sg:city":"Castellar Frontera",
    "sg:classifiers":[
        {
            "category":"Autos & Motor Vehicles",
            "subcategory":"Automobile Sales",
            "type":"Retail Goods"
        }
    ],
    "sg:phone":"+34 956 64 70 45",
    "sg:postcode":"11350",
    "sg:province":"C\u00e1diz",
    "wof:name":"Autoescuela Almoraima 2003 S.l.",
    "wof:placetype":"venue"
},
  "geometry": {"coordinates":[-5.4155721664,36.2852973938],"type":"Point"}
}