{
  "type": "Feature",
  "properties": {
    "iso:country":"ES",
    "sg:address":"Carrer de Riu Ter, 15",
    "sg:city":"Mataro",
    "sg:orig_category":"Importaci\u00d3n",
    "sg:phone":"+34 937 41 41 49",
    "sg:postcode":"08304",
    "sg:province":"Barcelona",
    "wof:name":"Mora Queralt S.l.",
    "wof:placetype":"venue"
},
  "geometry": {"coordinates":[2.4335889816,41.561542511],"type":"Point"}
}