{
  "type": "Feature",
  "properties": {
    "addr:full":"Calle de San Rafael, 44 S. Fernando C\u00e1diz 11100",
    "addr:housenumber":"44",
    "addr:postcode":"11100",
    "addr:street":"Calle De San Rafael;S. Fernando Ca\u0301Diz",
    "iso:country":"ES",
    "sg:address":"Calle de San Rafael, 44",
    "sg:city":"S. Fernando",
    "sg:orig_category":"Ropa Para Ni\u00d1os (al Por Menor)",
    "sg:phone":"+34 956 89 95 12",
    "sg:postcode":"11100",
    "sg:province":"C\u00e1diz",
    "wof:name":"Baixant Tinoco Milagros",
    "wof:placetype":"venue"
},
  "geometry": {"coordinates":[-6.1955752373,36.4693450928],"type":"Point"}
}