{
  "type": "Feature",
  "properties": {
    "iso:country":"ES",
    "sg:address":"Calle de Ciudad De Sevilla, 2",
    "sg:city":"Montilla",
    "sg:orig_category":"Florister\u00cdas",
    "sg:phone":"+34 957 65 13 73",
    "sg:postcode":"14550",
    "sg:province":"C\u00f3rdoba",
    "wof:name":"Flores Eva S.l.",
    "wof:placetype":"venue"
},
  "geometry": {"coordinates":[-4.6376209259,37.5896911621],"type":"Point"}
}