{
  "type": "Feature",
  "properties": {
    "addr:full":"Calle de Eduardo Lozano Garcia, 6 Navalmoral Mata C\u00e1ceres 10300",
    "addr:housenumber":"6",
    "addr:postcode":"10300",
    "addr:street":"Calle De Eduardo Lozano Garcia;Ca\u0301Ceres",
    "iso:country":"ES",
    "sg:address":"Calle de Eduardo Lozano Garcia, 6",
    "sg:city":"Navalmoral Mata",
    "sg:orig_category":"Librer\u00cdas",
    "sg:phone":"+34 927 53 56 94",
    "sg:postcode":"10300",
    "sg:province":"C\u00e1ceres",
    "wof:name":"Rubio Toribio Raquel",
    "wof:placetype":"venue"
},
  "geometry": {"coordinates":[-5.5375142097,39.8904418945],"type":"Point"}
}