{
  "type": "Feature",
  "properties": {
    "iso:country":"ES",
    "sg:address":"Carrer de Migjorn, S/n",
    "sg:city":"Terrassa",
    "sg:orig_category":"Colorantes, Colores Y Pigmentos (fabricaci\u00d3n, Al Por Mayor)",
    "sg:phone":"+34 937 35 58 45",
    "sg:postcode":"08226",
    "sg:province":"Barcelona",
    "sg:website":"www.modacolor.com",
    "wof:name":"Modacolor S. A.",
    "wof:placetype":"venue"
},
  "geometry": {"coordinates":[2.0231850147,41.5836410522],"type":"Point"}
}