{
  "type": "Feature",
  "properties": {
    "addr:full":"Calle de Plazarejo, 3 Villanueva Cordoba C\u00f3rdoba 14440",
    "addr:housenumber":"3;cordoba co\u0301rdoba",
    "addr:postcode":"14440",
    "addr:street":"Calle De Plazarejo",
    "iso:country":"ES",
    "sg:address":"Calle de Plazarejo, 3",
    "sg:city":"Villanueva Cordoba",
    "sg:orig_category":"Bisuter\u00cda, Joyer\u00cda, Relojer\u00cda (al Por Menor)",
    "sg:phone":"+34 957 12 09 93",
    "sg:postcode":"14440",
    "sg:province":"C\u00f3rdoba",
    "wof:name":"Alcobendas Amor Joaquina",
    "wof:placetype":"venue"
},
  "geometry": {"coordinates":[-4.7791519165,37.884727478],"type":"Point"}
}