{
  "type": "Feature",
  "properties": {
    "addr:full":"Calle de Arzobispo Apaolaza, 24 Zaragoza Zaragoza 50009",
    "addr:housenumber":"24",
    "addr:postcode":"50009",
    "addr:street":"Calle De Arzobispo Apaolaza",
    "iso:country":"ES",
    "sg:address":"Calle de Arzobispo Apaolaza, 24",
    "sg:city":"Zaragoza",
    "sg:orig_category":"Farmacias",
    "sg:phone":"+34 976 55 04 70",
    "sg:postcode":"50009",
    "sg:province":"Zaragoza",
    "wof:name":"Catalan Calvo Manuel",
    "wof:placetype":"venue"
},
  "geometry": {"coordinates":[-0.8974410892,41.6394615173],"type":"Point"}
}