{
  "type": "Feature",
  "properties": {
    "iso:country":"ES",
    "sg:address":"Ctra. Jarandilla, Km. 0001,0",
    "sg:city":"Talayuela",
    "sg:orig_category":"Producci\u00d3n, Venta De Productos De Agricultura Biol\u00d3gica",
    "sg:phone":"+34 927 55 13 20",
    "sg:postcode":"10310",
    "sg:province":"C\u00e1ceres",
    "wof:name":"Sat Asociaciones Agrupadas Tab",
    "wof:placetype":"venue"
},
  "geometry": {"coordinates":[-5.610019207,39.9897003174],"type":"Point"}
}