{
  "type": "Feature",
  "properties": {
    "addr:full":"Dos Hermanas-bi Ahizpe Kalea, S/n Irurtzun Navarra 31860",
    "addr:housenumber":"s / n",
    "addr:postcode":"31860",
    "addr:street":"Ahizpe Kalea",
    "iso:country":"ES",
    "sg:address":"Dos Hermanas-bi Ahizpe Kalea, S/n",
    "sg:city":"Irurtzun",
    "sg:orig_category":"M\u00c9dicos: Estomatolog\u00cda",
    "sg:phone":"+34 948 50 00 95",
    "sg:postcode":"31860",
    "sg:province":"Navarra",
    "wof:name":"Echarri Urquizu I\u00f1aki",
    "wof:placetype":"venue"
},
  "geometry": {"coordinates":[-1.8309140205,42.921913147],"type":"Point"}
}