{
  "type": "Feature",
  "properties": {
    "iso:country":"ES",
    "sg:address":"Calle de Josefina Mayor, 36",
    "sg:city":"Goro",
    "sg:orig_category":"Congelados: Productos Alimentarios (fabricaci\u00d3n, Al Por Mayor)",
    "sg:phone":"+34 928 70 06 36",
    "sg:postcode":"35215",
    "sg:province":"Las Palmas",
    "wof:name":"Bofrost Sau",
    "wof:placetype":"venue"
},
  "geometry": {"coordinates":[-15.398223877,27.9939899445],"type":"Point"}
}