{
  "type": "Feature",
  "properties": {
    "addr:full":"Rua Oporto, 10 Vigo Pontevedra 36201",
    "addr:housenumber":"10",
    "addr:postcode":"36201",
    "addr:street":"Rua Oporto",
    "iso:country":"ES",
    "sg:address":"Rua Oporto, 10",
    "sg:city":"Vigo",
    "sg:orig_category":"Alimentaci\u00d3n General (al Por Menor)",
    "sg:phone":"+34 986 22 27 87",
    "sg:postcode":"36201",
    "sg:province":"Pontevedra",
    "wof:name":"Vego Supermercados S.a.",
    "wof:placetype":"venue"
},
  "geometry": {"coordinates":[-8.7165050507,42.2383918762],"type":"Point"}
}