{
  "type": "Feature",
  "properties": {
    "addr:full":"Calle de Encarnacion Oviol, 18 Madrid Madrid 28021",
    "addr:housenumber":"18",
    "addr:postcode":"madrid;28021",
    "addr:street":"Calle De;Oviol",
    "iso:country":"ES",
    "sg:address":"Calle de Encarnacion Oviol, 18",
    "sg:city":"Madrid",
    "sg:orig_category":"Comerciantes Al Por Mayor De Vinos, Licores Y Alcoholes",
    "sg:phone":"+34 917 97 80 56",
    "sg:postcode":"28021",
    "sg:province":"Madrid",
    "wof:name":"Del Rey Del Rey Alejandro Javier",
    "wof:placetype":"venue"
},
  "geometry": {"coordinates":[-3.6898379326,40.3500747681],"type":"Point"}
}