{
  "type": "Feature",
  "properties": {
    "iso:country":"ES",
    "sg:address":"Calle de Beato Tomas De Zumarraga, 36",
    "sg:city":"Vitoria-gasteiz",
    "sg:orig_category":"Fabricaci\u00d3n De Bebidas No Alcoh\u00d3licas",
    "sg:phone":"+34 945 21 30 62",
    "sg:postcode":"01009",
    "sg:province":"\u00c1lava",
    "sg:website":"www.aquanatur.es",
    "wof:name":"Vendiplay S. L.",
    "wof:placetype":"venue"
},
  "geometry": {"coordinates":[-2.6869499683,42.854850769],"type":"Point"}
}