{
  "type": "Feature",
  "properties": {
    "iso:country":"ES",
    "sg:address":"Avda Carril (del), 6",
    "sg:city":"Archena",
    "sg:orig_category":"Peluquer\u00cdas, Peluquer\u00cda Mixta",
    "sg:phone":"+34 968 67 34 81",
    "sg:postcode":"30600",
    "sg:province":"Murcia",
    "wof:name":"Espinosa Medina Inmaculada",
    "wof:placetype":"venue"
},
  "geometry": {"coordinates":[-1.2963980436,38.1152992249],"type":"Point"}
}