{
  "type": "Feature",
  "properties": {
    "addr:full":"Av Sant Joan De Deu, 53 Playa De Calafell Tarragona 43820",
    "addr:housenumber":"53",
    "addr:postcode":"43820",
    "addr:street":"Av Sant Joan De Deu",
    "iso:country":"ES",
    "sg:address":"Av Sant Joan De Deu, 53",
    "sg:city":"Playa De Calafell",
    "sg:orig_category":"Serigraf\u00cda (material Y Suministros)",
    "sg:phone":"+34 977 69 47 89",
    "sg:postcode":"43820",
    "sg:province":"Tarragona",
    "wof:name":"Marin Fernandez Pedro Jose",
    "wof:placetype":"venue"
},
  "geometry": {"coordinates":[1.5711569786,41.1870880127],"type":"Point"}
}