{
  "type": "Feature",
  "properties": {
    "addr:full":"Avda Aduana (la), 11 Roquetas Mar Almer\u00eda 04740",
    "addr:housenumber":"11",
    "addr:postcode":"04740",
    "addr:street":"Avda Aduana La",
    "iso:country":"ES",
    "sg:address":"Avda Aduana (la), 11",
    "sg:city":"Roquetas Mar",
    "sg:orig_category":"Ense\u00d1anza Variada",
    "sg:phone":"+34 950 32 80 44",
    "sg:postcode":"04740",
    "sg:province":"Almer\u00eda",
    "wof:name":"Marin Carvajal Maria Angeles",
    "wof:placetype":"venue"
},
  "geometry": {"coordinates":[-2.6140048504,36.7666511536],"type":"Point"}
}