{
  "type": "Feature",
  "properties": {
    "addr:full":"Carrer de Sant Ildefons (de), 7 Tortosa Tarragona 43500",
    "addr:postcode":"43500",
    "addr:street":"Carrer De Sant Ildefons De",
    "iso:country":"ES",
    "sg:address":"Carrer de Sant Ildefons (de), 7",
    "sg:city":"Tortosa",
    "sg:orig_category":"Ropa Y Art\u00cdculos Pre",
    "sg:phone":"+34 977 44 05 92",
    "sg:postcode":"43500",
    "sg:province":"Tarragona",
    "wof:name":"Ferrer Orenga Maria Jose",
    "wof:placetype":"venue"
},
  "geometry": {"coordinates":[0.5208699703,40.8100738525],"type":"Point"}
}