{
  "type": "Feature",
  "properties": {
    "iso:country":"ES",
    "sg:address":"Avda Constitucion, 32",
    "sg:city":"Villena",
    "sg:orig_category":"Mercer\u00cda, Lencer\u00cda (al Por Menor)",
    "sg:phone":"+34 965 80 03 82",
    "sg:postcode":"03400",
    "sg:province":"Alicante",
    "wof:name":"Casa Angelica S.l.",
    "wof:placetype":"venue"
},
  "geometry": {"coordinates":[-0.8647639751,38.6338386536],"type":"Point"}
}