{
  "type": "Feature",
  "properties": {
    "addr:full":"Pase Hombre Pez, 8 Lierganes Cantabria 39727",
    "addr:housenumber":"8",
    "addr:postcode":"39727",
    "addr:street":"Pez",
    "iso:country":"ES",
    "sg:address":"Pase Hombre Pez, 8",
    "sg:city":"Lierganes",
    "sg:orig_category":"Venta, Instalaci\u00d3n De Cocinas",
    "sg:phone":"+34 942 52 80 48",
    "sg:postcode":"39727",
    "sg:province":"Cantabria",
    "wof:name":"Hotel Cantabrico S A",
    "wof:placetype":"venue"
},
  "geometry": {"coordinates":[-3.7443940639,43.3425941467],"type":"Point"}
}