{
  "type": "Feature",
  "properties": {
    "iso:country":"ES",
    "sg:address":"Calle de Ibiza, 33",
    "sg:city":"Madrid",
    "sg:orig_category":"M\u00c9dicos: Pediatr\u00cda. Enfermedades De Los Ni\u00d1os",
    "sg:phone":"+34 914 09 04 78",
    "sg:postcode":"28009",
    "sg:province":"Madrid",
    "wof:name":"Saez Perez Ernesto Antonio",
    "wof:placetype":"venue"
},
  "geometry": {"coordinates":[-3.6743950844,40.418384552],"type":"Point"}
}