{
  "type": "Feature",
  "properties": {
    "iso:country":"ES",
    "sg:address":"Calle de Barrio Viejo, 1",
    "sg:city":"Valverde Camino",
    "sg:orig_category":"Dibujantes (diversos)",
    "sg:phone":"+34 959 55 04 56",
    "sg:postcode":"21600",
    "sg:province":"Huelva",
    "wof:name":"Batanero Franco Diego",
    "wof:placetype":"venue"
},
  "geometry": {"coordinates":[-6.7534661293,37.576335907],"type":"Point"}
}