{
  "type": "Feature",
  "properties": {
    "addr:full":"Calle de Polonia, 1 Leganes Madrid 28916",
    "addr:housenumber":"1",
    "addr:postcode":"28916",
    "addr:street":"Calle De Polonia",
    "iso:country":"ES",
    "sg:address":"Calle de Polonia, 1",
    "sg:city":"Leganes",
    "sg:orig_category":"Panader\u00cdas, Panader\u00cdas",
    "sg:phone":"+34 916 80 36 07",
    "sg:postcode":"28916",
    "sg:province":"Madrid",
    "wof:name":"Abdelkebir El Kira",
    "wof:placetype":"venue"
},
  "geometry": {"coordinates":[-3.746047,40.339199],"type":"Point"}
}