{
  "type": "Feature",
  "properties": {
    "iso:country":"ES",
    "sg:address":"Carrer de Santiago Rusi\u00d1ol, 30",
    "sg:city":"S. Quirze Valles",
    "sg:orig_category":"Fabricaci\u00d3n, Distribuci\u00d3n De Material Para La Climatizaci\u00d3n, Aireaci\u00d3n Y Ventilaci\u00d3n",
    "sg:phone":"+34 937 21 06 41",
    "sg:postcode":"08192",
    "sg:province":"Barcelona",
    "wof:name":"Aliguer Sq S.l.",
    "wof:placetype":"venue"
},
  "geometry": {"coordinates":[2.0837693214,41.5305709839],"type":"Point"}
}