{
  "type": "Feature",
  "properties": {
    "iso:country":"ES",
    "sg:address":"Calle de Sacedon, 2",
    "sg:city":"Madrid",
    "sg:orig_category":"Centros De Educaci\u00d3n Especial",
    "sg:phone":"+34 917 98 39 44",
    "sg:postcode":"28021",
    "sg:province":"Madrid",
    "wof:name":"Gorriones Sur S.l.",
    "wof:placetype":"venue"
},
  "geometry": {"coordinates":[-3.6979908943,40.3494224548],"type":"Point"}
}