{
  "type": "Feature",
  "properties": {
    "iso:country":"ES",
    "sg:address":"Calle de Caballeros, 14",
    "sg:city":"Avila",
    "sg:orig_category":"Confecci\u00d3n (fabricaci\u00d3n, Al Por Mayor)",
    "sg:phone":"+34 920 21 17 57",
    "sg:postcode":"05001",
    "sg:province":"\u00c1vila",
    "wof:name":"Crespo Salcedo Eterio",
    "wof:placetype":"venue"
},
  "geometry": {"coordinates":[-4.7000379562,40.6556091309],"type":"Point"}
}