{
  "type": "Feature",
  "properties": {
    "addr:full":"Avda Peris Y Valero, 73 Valencia Valencia 46006",
    "addr:housenumber":"73",
    "addr:postcode":"46006",
    "addr:street":"Avda Peris Y Valero",
    "iso:country":"ES",
    "sg:address":"Avda Peris Y Valero, 73",
    "sg:city":"Valencia",
    "sg:orig_category":"Estancos",
    "sg:phone":"+34 963 34 12 26",
    "sg:postcode":"46006",
    "sg:province":"Valencia",
    "wof:name":"Moreno Fernandez Jose Vicente",
    "wof:placetype":"venue"
},
  "geometry": {"coordinates":[-0.373010993,39.4582366943],"type":"Point"}
}