{
  "type": "Feature",
  "properties": {
    "iso:country":"ES",
    "sg:address":"Calle de Pablo Neruda, S/n",
    "sg:city":"Mairena Alcor",
    "sg:orig_category":"Institutos De Belleza",
    "sg:phone":"+34 955 94 21 52",
    "sg:postcode":"41510",
    "sg:province":"Sevilla",
    "wof:name":"Morales Marin Jose Manuel",
    "wof:placetype":"venue"
},
  "geometry": {"coordinates":[-5.7554788589,37.3731803894],"type":"Point"}
}