{
  "type": "Feature",
  "properties": {
    "addr:full":"Avda Valladolid, 52 S. Esteban Gormaz Soria 42330",
    "addr:housenumber":"52",
    "addr:postcode":"42330",
    "addr:street":"Avda Valladolid;S. Esteban Gormaz",
    "iso:country":"ES",
    "sg:address":"Avda Valladolid, 52",
    "sg:city":"S. Esteban Gormaz",
    "sg:orig_category":"Cerrajer\u00cda, Ferrallista",
    "sg:phone":"+34 975 35 03 14",
    "sg:postcode":"42330",
    "sg:province":"Soria",
    "wof:name":"Santos Perez Javier",
    "wof:placetype":"venue"
},
  "geometry": {"coordinates":[-3.1942191124,41.5698204041],"type":"Point"}
}