{
  "type": "Feature",
  "properties": {
    "addr:full":"Calle de Claudio Coello, 86 Madrid Madrid 28006",
    "addr:housenumber":"86",
    "addr:postcode":"madrid;28006",
    "addr:street":"Calle De Claudio Coello",
    "iso:country":"ES",
    "sg:address":"Calle de Claudio Coello, 86",
    "sg:city":"Madrid",
    "sg:orig_category":"Notarios",
    "sg:phone":"+34 915 78 23 23",
    "sg:postcode":"28006",
    "sg:province":"Madrid",
    "wof:name":"Romero-giron Deleito Juan",
    "wof:placetype":"venue"
},
  "geometry": {"coordinates":[-3.6857514381,40.4310264587],"type":"Point"}
}