{
  "type": "Feature",
  "properties": {
    "addr:full":"Calle de Doctor Garcia Castrillo, 19 Palmas De Gran Canaria Las Palmas 35005",
    "addr:housenumber":"19",
    "addr:postcode":"35005",
    "addr:street":"Calle De Doctor Garcia Castrillo",
    "iso:country":"ES",
    "sg:address":"Calle de Doctor Garcia Castrillo, 19",
    "sg:city":"Palmas De Gran Canaria",
    "sg:orig_category":"Escuelas De Maternidad P\u00dablicas",
    "sg:phone":"+34 928 24 53 85",
    "sg:postcode":"35005",
    "sg:province":"Las Palmas",
    "wof:name":"Conrad  Anita",
    "wof:placetype":"venue"
},
  "geometry": {"coordinates":[-15.4333295822,28.1246623993],"type":"Point"}
}