{
  "type": "Feature",
  "properties": {
    "iso:country":"ES",
    "sg:address":"Calle de Duque De Gaeta, 54",
    "sg:city":"Valencia",
    "sg:orig_category":"Venta, Montaje De Neum\u00c1ticos",
    "sg:phone":"+34 963 30 83 27",
    "sg:postcode":"46022",
    "sg:province":"Valencia",
    "wof:name":"Neumaticos Del Maritimo S.l.",
    "wof:placetype":"venue"
},
  "geometry": {"coordinates":[-0.3486042023,39.4690818787],"type":"Point"}
}