{
  "type": "Feature",
  "properties": {
    "addr:full":"Carr Colom, 6 Figueres Girona 17600",
    "addr:housenumber":"6",
    "addr:postcode":"17600",
    "addr:street":"Carr Colom",
    "iso:country":"ES",
    "sg:address":"Carr Colom, 6",
    "sg:city":"Figueres",
    "sg:orig_category":"Tapicer\u00cdas",
    "sg:phone":"+34 972 50 54 71",
    "sg:postcode":"17600",
    "sg:province":"Girona",
    "wof:name":"Clotas Roura Narcis",
    "wof:placetype":"venue"
},
  "geometry": {"coordinates":[2.9678800106,42.2667045593],"type":"Point"}
}