{
  "type": "Feature",
  "properties": {
    "addr:full":"Ctra Bilbao-galdakao, 2 Bilbao Vizcaya 48004",
    "addr:housenumber":"2",
    "addr:postcode":"48004",
    "addr:street":"Ctra Bilbao-Galdakao",
    "iso:country":"ES",
    "sg:address":"Ctra Bilbao-galdakao, 2",
    "sg:city":"Bilbao",
    "sg:orig_category":"Ingenier\u00cda, Centros De Estudios (diversos)",
    "sg:phone":"+34 944 59 73 51",
    "sg:postcode":"48004",
    "sg:province":"Vizcaya",
    "wof:name":"Inargest S.l.",
    "wof:placetype":"venue"
},
  "geometry": {"coordinates":[-2.9015851021,43.2501564026],"type":"Point"}
}