{
  "type": "Feature",
  "properties": {
    "addr:full":"Calle de Venerable Beferull, 2 Alginet Valencia 46230",
    "addr:housenumber":"2",
    "addr:postcode":"46230",
    "addr:street":"Calle De Venerable Beferull",
    "iso:country":"ES",
    "sg:address":"Calle de Venerable Beferull, 2",
    "sg:city":"Alginet",
    "sg:orig_category":"Perfumer\u00cda Y Cosm\u00c9tica (fabricaci\u00d3n, Al Por Mayor)",
    "sg:phone":"+34 961 75 12 41",
    "sg:postcode":"46230",
    "sg:province":"Valencia",
    "wof:name":"Machi Primo Joaquina",
    "wof:placetype":"venue"
},
  "geometry": {"coordinates":[-0.4689199924,39.2615013123],"type":"Point"}
}