{
  "type": "Feature",
  "properties": {
    "iso:country":"ES",
    "sg:address":"Av Catalunya, 2",
    "sg:city":"Munia",
    "sg:orig_category":"Bordado, Marcado A Medida",
    "sg:phone":"+34 938 91 91 19",
    "sg:postcode":"08732",
    "sg:province":"Barcelona",
    "wof:name":"Trade Eurobor S.l.",
    "wof:placetype":"venue"
},
  "geometry": {"coordinates":[1.6189709902,41.3272857666],"type":"Point"}
}