{
  "type": "Feature",
  "properties": {
    "iso:country":"ES",
    "sg:address":"Carrer de L'almirall Cervera, 5",
    "sg:city":"Barcelona",
    "sg:orig_category":"Importaci\u00d3n",
    "sg:phone":"+34 932 24 77 34",
    "sg:postcode":"08003",
    "sg:province":"Barcelona",
    "wof:name":"Inversiones Aragua S.l.",
    "wof:placetype":"venue"
},
  "geometry": {"coordinates":[2.1888370514,41.3782081604],"type":"Point"}
}