{
  "type": "Feature",
  "properties": {
    "iso:country":"ES",
    "sg:address":"Calle de Francisco Silvela, 19",
    "sg:city":"Madrid",
    "sg:orig_category":"Abogados",
    "sg:phone":"+34 914 01 16 64",
    "sg:postcode":"28028",
    "sg:province":"Madrid",
    "wof:name":"Barrena Sanchez Abel",
    "wof:placetype":"venue"
},
  "geometry": {"coordinates":[-3.6711809635,40.4304962158],"type":"Point"}
}