{
  "type": "Feature",
  "properties": {
    "addr:full":"Calle de Francia, S/n Torrejon Ardoz Madrid 28850",
    "addr:housenumber":"s / n",
    "addr:postcode":"28850",
    "addr:street":"Calle De Francia",
    "iso:country":"ES",
    "sg:address":"Calle de Francia, S/n",
    "sg:city":"Torrejon Ardoz",
    "sg:orig_category":"Asilos De Ancianos. Centros Privados",
    "sg:phone":"+34 916 75 91 56",
    "sg:postcode":"28850",
    "sg:province":"Madrid",
    "sg:website":"www.adavir.com",
    "wof:name":"Planiger S.a.",
    "wof:placetype":"venue"
},
  "geometry": {"coordinates":[-3.4522740841,40.4588661194],"type":"Point"}
}