{
  "type": "Feature",
  "properties": {
    "iso:country":"ES",
    "sg:address":"Rua San Lazaro (de), 24",
    "sg:city":"Santiago De Compostela",
    "sg:orig_category":"Molduras, Junquillos, Listones Y Molduras Perforadas",
    "sg:phone":"+34 981 58 47 47",
    "sg:postcode":"15703",
    "sg:province":"La Coru\u00f1a",
    "wof:name":"Fernandez Sanchez Maria Rosa",
    "wof:placetype":"venue"
},
  "geometry": {"coordinates":[-8.5204591751,42.8866996765],"type":"Point"}
}