{
  "type": "Feature",
  "properties": {
    "iso:country":"ES",
    "sg:address":"Bard Almendros (los), S/n",
    "sg:city":"Estacion",
    "sg:orig_category":"Empresas De Carpinter\u00cda De Madera",
    "sg:phone":"+34 952 42 00 13",
    "sg:postcode":"29580",
    "sg:province":"M\u00e1laga",
    "wof:name":"Carpinteria Postigo Y Vazquez S.l.",
    "wof:placetype":"venue"
},
  "geometry": {"coordinates":[-4.6139087677,36.7314491272],"type":"Point"}
}