{
  "type": "Feature",
  "properties": {
    "addr:full":"Carrer de Escocia, 13 Barcelona Barcelona 08016",
    "addr:housenumber":"13",
    "addr:postcode":"08016",
    "addr:street":"Carrer De Escocia",
    "iso:country":"ES",
    "sg:address":"Carrer de Escocia, 13",
    "sg:city":"Barcelona",
    "sg:orig_category":"Aparcamientos (infraestructuras, Accesorios)",
    "sg:phone":"+34 933 52 73 05",
    "sg:postcode":"08016",
    "sg:province":"Barcelona",
    "wof:name":"Renga S.l.",
    "wof:placetype":"venue"
},
  "geometry": {"coordinates":[2.1834130287,41.4285011292],"type":"Point"}
}