{
  "type": "Feature",
  "properties": {
    "addr:full":"Carr Occitania, 58 Badalona Barcelona 08911",
    "addr:housenumber":"58",
    "addr:postcode":"08911",
    "addr:street":"Carr Occitania",
    "iso:country":"ES",
    "sg:address":"Carr Occitania, 58",
    "sg:city":"Badalona",
    "sg:orig_category":"Fabricaci\u00d3n De Moldes Y Modelos",
    "sg:phone":"+34 934 64 23 44",
    "sg:postcode":"08911",
    "sg:province":"Barcelona",
    "wof:name":"Bademol S.a.l",
    "wof:placetype":"venue"
},
  "geometry": {"coordinates":[2.2628936768,41.4609489441],"type":"Point"}
}