{
  "type": "Feature",
  "properties": {
    "iso:country":"ES",
    "sg:address":"Plaz San Marcos, 18",
    "sg:city":"Jerez De La Frontera",
    "sg:orig_category":"M\u00c9dicos: Psiquiatr\u00cda",
    "sg:phone":"+34 956 34 12 05",
    "sg:postcode":"11403",
    "sg:province":"C\u00e1diz",
    "wof:name":"Fernandez Garcia-figueras Francisco",
    "wof:placetype":"venue"
},
  "geometry": {"coordinates":[-6.1379342079,36.686000824],"type":"Point"}
}