{
  "type": "Feature",
  "properties": {
    "iso:country":"ES",
    "sg:address":"Calle de Nueva, 27",
    "sg:city":"Viso",
    "sg:orig_category":"Carnicer\u00cdas, Carnicer\u00cdas",
    "sg:phone":"+34 957 12 74 40",
    "sg:postcode":"14470",
    "sg:province":"C\u00f3rdoba",
    "wof:name":"Ramirez Mu\u00f1oz Jose",
    "wof:placetype":"venue"
},
  "geometry": {"coordinates":[-4.9543890953,38.4852867126],"type":"Point"}
}