{
  "type": "Feature",
  "properties": {
    "iso:country":"ES",
    "sg:address":"Calle de Asuncion, 21",
    "sg:city":"Sevilla",
    "sg:orig_category":"Ropa Para Se\u00d1oras (al Por Menor)",
    "sg:phone":"+34 954 27 50 55",
    "sg:postcode":"41011",
    "sg:province":"Sevilla",
    "sg:website":"www.tintoretto.es",
    "wof:name":"Seinve S.a.",
    "wof:placetype":"venue"
},
  "geometry": {"coordinates":[-5.9973487854,37.3778266907],"type":"Point"}
}