{
  "type": "Feature",
  "properties": {
    "addr:full":"Ctra Granada (de), S/n Venta Del Coronel Murcia 30817",
    "addr:postcode":"30817",
    "addr:street":"Ctra Granada De S / N Venta Del Coronel",
    "iso:country":"ES",
    "sg:address":"Ctra Granada (de), S/n",
    "sg:city":"Venta Del Coronel",
    "sg:orig_category":"Fabricaci\u00d3n, Distribuci\u00d3n De Material Para La Climatizaci\u00d3n, Aireaci\u00d3n Y Ventilaci\u00d3n",
    "sg:phone":"+34 968 47 73 39",
    "sg:postcode":"30817",
    "sg:province":"Murcia",
    "wof:name":"Frio Calor Y Electricidad S.l.",
    "wof:placetype":"venue"
},
  "geometry": {"coordinates":[-1.7245190144,37.6462936401],"type":"Point"}
}