{
  "type": "Feature",
  "properties": {
    "iso:country":"ES",
    "sg:address":"Carrer de Pont, 19",
    "sg:city":"Reus",
    "sg:orig_category":"Mec\u00c1nico Del Autom\u00d3vil",
    "sg:phone":"+34 977 31 84 95",
    "sg:postcode":"43205",
    "sg:province":"Tarragona",
    "wof:name":"Planas Baiget Antonio",
    "wof:placetype":"venue"
},
  "geometry": {"coordinates":[1.0966370106,41.1493682861],"type":"Point"}
}