{
  "type": "Feature",
  "properties": {
    "addr:full":"Calle de Cid, 42 Alaquas Valencia 46970",
    "addr:housenumber":"42",
    "addr:postcode":"46970",
    "addr:street":"Calle De Cid",
    "iso:country":"ES",
    "sg:address":"Calle de Cid, 42",
    "sg:city":"Alaquas",
    "sg:orig_category":"M\u00c1rmoles, Granitos Y Piedras Naturales",
    "sg:phone":"+34 961 50 94 19",
    "sg:postcode":"46970",
    "sg:province":"Valencia",
    "wof:name":"Marmoles Hermanos Garcia S.l.",
    "wof:placetype":"venue"
},
  "geometry": {"coordinates":[-0.4661231935,39.4548988342],"type":"Point"}
}