{
  "type": "Feature",
  "properties": {
    "iso:country":"ES",
    "sg:address":"Calle de Alfonso Trujillo, 3",
    "sg:city":"Orotava",
    "sg:orig_category":"Ropa Para Se\u00d1oras (al Por Menor)",
    "sg:phone":"+34 922 33 11 20",
    "sg:postcode":"38300",
    "sg:province":"Santa Cruz De Tenerife",
    "wof:name":"Heredia Heredia Raquel",
    "wof:placetype":"venue"
},
  "geometry": {"coordinates":[-16.5195827484,28.3930149078],"type":"Point"}
}