{
  "type": "Feature",
  "properties": {
    "addr:full":"Carretera De Valmuel, S/n Puigmoreno Teruel 44660",
    "addr:housenumber":"s",
    "addr:postcode":"44660",
    "addr:street":"Carretera De Valmuel;/ N",
    "iso:country":"ES",
    "sg:address":"Carretera De Valmuel, S/n",
    "sg:city":"Puigmoreno",
    "sg:orig_category":"Cooperativas Agr\u00cdcolas",
    "sg:phone":"+34 978 83 80 00",
    "sg:postcode":"44660",
    "sg:province":"Teruel",
    "sg:website":"www.cofrugal.com",
    "wof:name":"Cooperativa Del Campo San Miguel",
    "wof:placetype":"venue"
},
  "geometry": {"coordinates":[-0.2500289977,41.1078109741],"type":"Point"}
}