{
  "type": "Feature",
  "properties": {
    "addr:full":"Ctra Torre Pacheco, S/n Los Alcazares Murcia 30710",
    "addr:housenumber":"s / n",
    "addr:postcode":"30710",
    "addr:street":"Ctra Torre Pacheco;Los Alcazares",
    "iso:country":"ES",
    "sg:address":"Ctra Torre Pacheco, S/n",
    "sg:city":"Los Alcazares",
    "sg:orig_category":"Venta, Montaje De Neum\u00c1ticos",
    "sg:phone":"+34 968 58 25 11",
    "sg:postcode":"30710",
    "sg:province":"Murcia",
    "wof:name":"Nicolas Conesa Juan Jose",
    "wof:placetype":"venue"
},
  "geometry": {"coordinates":[-0.8489990234,37.7447319031],"type":"Point"}
}