{
  "type": "Feature",
  "properties": {
    "addr:full":"Calle de Martires Fuenlabrada (de Los), 35 Fuenlabrada Madrid 28944",
    "addr:postcode":"28944",
    "addr:street":"Calle De Martires;Los",
    "iso:country":"ES",
    "sg:address":"Calle de Martires Fuenlabrada (de Los), 35",
    "sg:city":"Fuenlabrada",
    "sg:orig_category":"Escayola Y Productos De Escayola (fabricaci\u00d3n, Al Por Mayor)",
    "sg:phone":"+34 916 15 88 66",
    "sg:postcode":"28944",
    "sg:province":"Madrid",
    "wof:name":"A & C Asistecnic S.l.",
    "wof:placetype":"venue"
},
  "geometry": {"coordinates":[-3.7907772064,40.2815322876],"type":"Point"}
}