{
  "type": "Feature",
  "properties": {
    "iso:country":"ES",
    "sg:address":"Calle de Suerte Larga, 5",
    "sg:city":"Torrijos",
    "sg:orig_category":"Inmobiliaria (agencias)",
    "sg:phone":"+34 925 76 10 47",
    "sg:postcode":"45500",
    "sg:province":"Toledo",
    "wof:name":"Jimenez-ortiz Vega Ruben",
    "wof:placetype":"venue"
},
  "geometry": {"coordinates":[-4.276113987,39.9815864563],"type":"Point"}
}