{
  "type": "Feature",
  "properties": {
    "iso:country":"ES",
    "sg:address":"Calle de Badajoz, 23",
    "sg:city":"Santa Marta",
    "sg:orig_category":"Estancos",
    "sg:phone":"+34 924 69 00 67",
    "sg:postcode":"06150",
    "sg:province":"Badajoz",
    "wof:name":"Hernandez Barroso Ramon",
    "wof:placetype":"venue"
},
  "geometry": {"coordinates":[-6.6324548721,38.6075286865],"type":"Point"}
}