{
  "type": "Feature",
  "properties": {
    "iso:country":"ES",
    "sg:address":"San Anton, 40",
    "sg:city":"Iru\u00f1a",
    "sg:orig_category":"Abogados",
    "sg:phone":"+34 948 21 00 43",
    "sg:postcode":"31001",
    "sg:province":"Navarra",
    "sg:website":"www.dsabogados.com",
    "wof:name":"Borda Ochotorena Abogados S.cv",
    "wof:placetype":"venue"
},
  "geometry": {"coordinates":[-1.6467850208,42.8161125183],"type":"Point"}
}