{
  "type": "Feature",
  "properties": {
    "iso:country":"ES",
    "sg:address":"Avda Goya, 16",
    "sg:city":"Zaragoza",
    "sg:orig_category":"M\u00c9dicos: Estomatolog\u00cda",
    "sg:phone":"+34 976 22 80 69",
    "sg:postcode":"50006",
    "sg:province":"Zaragoza",
    "wof:name":"Guridi Rodriguez Maria Del Coro",
    "wof:placetype":"venue"
},
  "geometry": {"coordinates":[-1.0290249586,41.7227897644],"type":"Point"}
}