{
  "type": "Feature",
  "properties": {
    "addr:full":"Cra San Jeronimo, 32 Madrid Madrid 28014",
    "addr:housenumber":"32",
    "addr:postcode":"madrid;28014",
    "addr:street":"Jeronimo",
    "iso:country":"ES",
    "sg:address":"Cra San Jeronimo, 32",
    "sg:city":"Madrid",
    "sg:orig_category":"Pensiones Familiares",
    "sg:phone":"+34 914 29 67 79",
    "sg:postcode":"28014",
    "sg:province":"Madrid",
    "wof:name":"Estevez Alvarez Domingo",
    "wof:placetype":"venue"
},
  "geometry": {"coordinates":[-3.6987888813,40.4165382385],"type":"Point"}
}