{
  "type": "Feature",
  "properties": {
    "addr:full":"Calle de Nuestra Se\u00d1ora, 2 Pe\u00e7aranda De Bracamonte Salamanca 37300",
    "addr:housenumber":"2",
    "addr:postcode":"37300",
    "addr:street":"Calle De Nuestra Sen\u0303Ora",
    "iso:country":"ES",
    "sg:address":"Calle de Nuestra Se\u00d1ora, 2",
    "sg:city":"Pe\u00e7aranda De Bracamonte",
    "sg:orig_category":"Albergues",
    "sg:phone":"+34 923 54 01 96",
    "sg:postcode":"37300",
    "sg:province":"Salamanca",
    "wof:name":"Nabalpesa Figon S.l.",
    "wof:placetype":"venue"
},
  "geometry": {"coordinates":[-5.2015991211,40.9019393921],"type":"Point"}
}