{
  "type": "Feature",
  "properties": {
    "addr:full":"L. Bravo, S/n Villalonquejar Burgos 09001",
    "addr:postcode":"09001",
    "addr:street":"L. Bravo S / N Villalonquejar",
    "iso:country":"ES",
    "sg:address":"L. Bravo, S/n",
    "sg:city":"Villalonquejar",
    "sg:orig_category":"Artes Gr\u00c1ficas, Artes Pl\u00c1sticas (curso)",
    "sg:phone":"+34 947 29 87 13",
    "sg:postcode":"09001",
    "sg:province":"Burgos",
    "wof:name":"Imprenta Santos S.l.",
    "wof:placetype":"venue"
},
  "geometry": {"coordinates":[-3.7283790112,42.3722801208],"type":"Point"}
}