{
  "type": "Feature",
  "properties": {
    "addr:full":"Calle de Carlos I, 51 Yuncos Toledo 45210",
    "addr:housenumber":"51",
    "addr:postcode":"45210",
    "addr:street":"Calle De Carlos I",
    "iso:country":"ES",
    "sg:address":"Calle de Carlos I, 51",
    "sg:city":"Yuncos",
    "sg:orig_category":"Fabricaci\u00d3n, Venta De Cuadros, Accesorios Para Enmarcar",
    "sg:phone":"+34 925 55 71 18",
    "sg:postcode":"45210",
    "sg:province":"Toledo",
    "sg:website":"www.fabriarte.com",
    "wof:name":"Jimenez Terrel Felix",
    "wof:placetype":"venue"
},
  "geometry": {"coordinates":[-3.8679184914,40.0962409973],"type":"Point"}
}