{
  "type": "Feature",
  "properties": {
    "addr:full":"Plaz Tirso De Molina, 3 Madrid Madrid 28012",
    "addr:housenumber":"3",
    "addr:postcode":"28012",
    "addr:street":"Plaz Tirso De Molina",
    "iso:country":"ES",
    "sg:address":"Plaz Tirso De Molina, 3",
    "sg:city":"Madrid",
    "sg:orig_category":"Importaci\u00d3n",
    "sg:phone":"+34 914 29 83 49",
    "sg:postcode":"28012",
    "sg:province":"Madrid",
    "wof:name":"Jaguai Modas Y Complementos S.l.",
    "wof:placetype":"venue"
},
  "geometry": {"coordinates":[-3.7035629749,40.4122390747],"type":"Point"}
}