{
  "type": "Feature",
  "properties": {
    "addr:full":"Calle de Francos Rodriguez, 31 Madrid Madrid 28039",
    "addr:housenumber":"31",
    "addr:postcode":"madrid;28039",
    "addr:street":"Calle De Francos Rodriguez",
    "iso:country":"ES",
    "sg:address":"Calle de Francos Rodriguez, 31",
    "sg:city":"Madrid",
    "sg:orig_category":"Ropa Para Ni\u00d1os (al Por Menor)",
    "sg:phone":"+34 913 11 29 23",
    "sg:postcode":"28039",
    "sg:province":"Madrid",
    "wof:name":"Shang Nogues Agueda",
    "wof:placetype":"venue"
},
  "geometry": {"coordinates":[-3.7060780525,40.4564590454],"type":"Point"}
}