{
  "type": "Feature",
  "properties": {
    "iso:country":"ES",
    "sg:address":"Calle de Santa Cristina, 1",
    "sg:city":"Pedrosa Del Principe",
    "sg:orig_category":"Delegados, Agentes De Tr\u00c1nsito, Auxiliares De Transporte Internacional",
    "sg:phone":"+34 947 37 53 21",
    "sg:postcode":"09119",
    "sg:province":"Burgos",
    "wof:name":"Gallardo Borro Pedro",
    "wof:placetype":"venue"
},
  "geometry": {"coordinates":[-4.1999459267,42.2496528625],"type":"Point"}
}