{
  "type": "Feature",
  "properties": {
    "iso:country":"ES",
    "sg:address":"Pl Vella, 9",
    "sg:city":"Vendrell",
    "sg:orig_category":"Alimentaci\u00d3n General (al Por Menor)",
    "sg:phone":"+34 977 66 09 40",
    "sg:postcode":"43700",
    "sg:province":"Tarragona",
    "wof:name":"Mercader G\u00fcell Amador",
    "wof:placetype":"venue"
},
  "geometry": {"coordinates":[1.5348459482,41.2203369141],"type":"Point"}
}