{
  "type": "Feature",
  "properties": {
    "iso:country":"ES",
    "sg:address":"Calle de Ramon Y Cajal, 2",
    "sg:city":"Tomares",
    "sg:orig_category":"Sales (al Por Mayor)",
    "sg:phone":"+34 954 15 16 89",
    "sg:postcode":"41940",
    "sg:province":"Sevilla",
    "sg:website":"www.jolca.es",
    "wof:name":"Jolca S. A.",
    "wof:placetype":"venue"
},
  "geometry": {"coordinates":[-6.0430703163,37.3735733032],"type":"Point"}
}