{
  "type": "Feature",
  "properties": {
    "iso:country":"ES",
    "sg:address":"Av Pau (de La), 35",
    "sg:city":"Mollerussa",
    "sg:orig_category":"Albergues",
    "sg:phone":"+34 973 71 05 66",
    "sg:postcode":"25230",
    "sg:province":"Lleida",
    "wof:name":"Torres Vico Antonio",
    "wof:placetype":"venue"
},
  "geometry": {"coordinates":[0.8990960121,41.6277008057],"type":"Point"}
}