{
  "type": "Feature",
  "properties": {
    "addr:full":"Plaz Tenerias, 10 Valladolid Valladolid 47006",
    "addr:housenumber":"10",
    "addr:postcode":"47006",
    "addr:street":"Plaz Tenerias",
    "iso:country":"ES",
    "sg:address":"Plaz Tenerias, 10",
    "sg:city":"Valladolid",
    "sg:orig_category":"Tejidos (al Por Menor)",
    "sg:phone":"+34 983 33 11 33",
    "sg:postcode":"47006",
    "sg:province":"Valladolid",
    "wof:name":"Aurum Regalos Publicitarios S.l",
    "wof:placetype":"venue"
},
  "geometry": {"coordinates":[-4.7331857681,41.648235321],"type":"Point"}
}