{
  "type": "Feature",
  "properties": {
    "iso:country":"ES",
    "sg:address":"Plaz Constitucion (de La), 7",
    "sg:city":"Miguelturra",
    "sg:orig_category":"Molduras, Junquillos, Listones Y Molduras Perforadas",
    "sg:phone":"+34 926 24 03 05",
    "sg:postcode":"13170",
    "sg:province":"Ciudad Real",
    "wof:name":"Jurado Gonzalez Zacarias",
    "wof:placetype":"venue"
},
  "geometry": {"coordinates":[-3.8970448971,38.968372345],"type":"Point"}
}