{
  "type": "Feature",
  "properties": {
    "addr:full":"Calle de General Aguilera, 11 Ciudad Real Ciudad Real 13001",
    "addr:housenumber":"11",
    "addr:postcode":"13001",
    "addr:street":"Calle De General Aguilera",
    "iso:country":"ES",
    "sg:address":"Calle de General Aguilera, 11",
    "sg:city":"Ciudad Real",
    "sg:orig_category":"M\u00c9dicos: Anestesiolog\u00cda Y Reanimaci\u00d3n Quir\u00dargica",
    "sg:phone":"+34 926 22 27 28",
    "sg:postcode":"13001",
    "sg:province":"Ciudad Real",
    "wof:name":"Mu\u00f1oz Tomas Jose Joaquin",
    "wof:placetype":"venue"
},
  "geometry": {"coordinates":[-3.9282603264,38.984539032],"type":"Point"}
}