{
  "type": "Feature",
  "properties": {
    "iso:country":"ES",
    "sg:address":"Calle de Lapurdi, 42",
    "sg:city":"Kurtzea",
    "sg:orig_category":"Caf\u00c9s, Bares, Cervecer\u00cdas",
    "sg:phone":"+34 944 57 06 69",
    "sg:postcode":"48960",
    "sg:province":"Vizcaya",
    "wof:name":"Phone Euskadi S. L.",
    "wof:placetype":"venue"
},
  "geometry": {"coordinates":[-2.8441851139,43.2327384949],"type":"Point"}
}