{
  "type": "Feature",
  "properties": {
    "iso:country":"ES",
    "sg:address":"Av Barcelona, 17",
    "sg:city":"S. Joan Despi",
    "sg:orig_category":"Agencias De Viajes",
    "sg:phone":"+34 934 77 27 60",
    "sg:postcode":"08970",
    "sg:province":"Barcelona",
    "wof:name":"Viatges Tram S.l.",
    "wof:placetype":"venue"
},
  "geometry": {"coordinates":[2.0736498833,41.3695793152],"type":"Point"}
}