{
  "type": "Feature",
  "properties": {
    "iso:country":"ES",
    "sg:address":"Calle de Dion Cassio, S/n",
    "sg:city":"Merida",
    "sg:orig_category":"Discapacitados",
    "sg:phone":"+34 924 30 12 47",
    "sg:postcode":"06800",
    "sg:province":"Badajoz",
    "wof:name":"Asociacion De Discapacitados Para La Integracion Social",
    "wof:placetype":"venue"
},
  "geometry": {"coordinates":[-6.3428521156,38.9107933044],"type":"Point"}
}