{
  "type": "Feature",
  "properties": {
    "iso:country":"ES",
    "sg:address":"Barr Mesterika, S/n",
    "sg:city":"Mesterika",
    "sg:orig_category":"Refiner\u00cdas De Petr\u00d3leo",
    "sg:phone":"+34 946 74 87 44",
    "sg:postcode":"48120",
    "sg:province":"Vizcaya",
    "wof:name":"Marinoil Service S. A.",
    "wof:placetype":"venue"
},
  "geometry": {"coordinates":[-2.801060915,43.3647575378],"type":"Point"}
}