{
  "type": "Feature",
  "properties": {
    "addr:full":"Carrer de Sant Pere, 29 Malgrat Mar Barcelona 08380",
    "addr:housenumber":"29",
    "addr:postcode":"08380",
    "addr:street":"Carrer De Sant Pere",
    "iso:country":"ES",
    "sg:address":"Carrer de Sant Pere, 29",
    "sg:city":"Malgrat Mar",
    "sg:orig_category":"Bricolaje, Herramientas (al Por Menor)",
    "sg:phone":"+34 937 61 20 52",
    "sg:postcode":"08380",
    "sg:province":"Barcelona",
    "wof:name":"Davila Correa Antonio",
    "wof:placetype":"venue"
},
  "geometry": {"coordinates":[2.745677948,41.6442108154],"type":"Point"}
}