{
  "type": "Feature",
  "properties": {
    "addr:full":"Calle de Lerida, 13 Alacant Alicante 03012",
    "addr:housenumber":"13",
    "addr:postcode":"03012",
    "addr:street":"Calle De Lerida",
    "iso:country":"ES",
    "sg:address":"Calle de Lerida, 13",
    "sg:city":"Alacant",
    "sg:orig_category":"Fabricaci\u00d3n De Quesos",
    "sg:phone":"+34 965 25 02 68",
    "sg:postcode":"03012",
    "sg:province":"Alicante",
    "wof:name":"Exclusivas Abellan S.c.",
    "wof:placetype":"venue"
},
  "geometry": {"coordinates":[-0.4771560133,38.3611106873],"type":"Point"}
}