{
  "type": "Feature",
  "properties": {
    "iso:country":"ES",
    "sg:address":"Calle de San Jose, 36",
    "sg:city":"Alcala Guadaira",
    "sg:orig_category":"Electromec\u00c1nica",
    "sg:phone":"+34 955 68 27 02",
    "sg:postcode":"41500",
    "sg:province":"Sevilla",
    "wof:name":"Cliza Electromecanica S.l.",
    "wof:placetype":"venue"
},
  "geometry": {"coordinates":[-5.8499112129,37.3364295959],"type":"Point"}
}