{
  "type": "Feature",
  "properties": {
    "iso:country":"ES",
    "sg:address":"Ptda Algoros, 30",
    "sg:city":"Elche",
    "sg:orig_category":"Frutas, Legumbres Frescas Y Tempranas (al Por Menor)",
    "sg:phone":"+34 966 63 08 69",
    "sg:postcode":"03293",
    "sg:province":"Alicante",
    "wof:name":"Frutas Boix S.l.",
    "wof:placetype":"venue"
},
  "geometry": {"coordinates":[-0.6995239854,38.2634811401],"type":"Point"}
}