{
  "type": "Feature",
  "properties": {
    "iso:country":"ES",
    "sg:address":"Calle de Mayor, 2",
    "sg:city":"Castellon",
    "sg:orig_category":"Bisuter\u00cda, Joyer\u00cda, Relojer\u00cda (al Por Menor)",
    "sg:phone":"+34 964 22 91 99",
    "sg:postcode":"12001",
    "sg:province":"Castell\u00f3n",
    "wof:name":"Joyeria Mayor S.l.",
    "wof:placetype":"venue"
},
  "geometry": {"coordinates":[-0.0390900001,39.9866714478],"type":"Point"}
}