{
  "type": "Feature",
  "properties": {
    "addr:full":"Ctra Olivenza, S/n Cheles Badajoz 06105",
    "addr:housenumber":"s / n",
    "addr:postcode":"06105",
    "addr:street":"Ctra Olivenza",
    "iso:country":"ES",
    "sg:address":"Ctra Olivenza, S/n",
    "sg:city":"Cheles",
    "sg:orig_category":"Distribuci\u00d3n De Petr\u00d3leo Y Derivados",
    "sg:phone":"+34 924 42 30 05",
    "sg:postcode":"06105",
    "sg:province":"Badajoz",
    "wof:name":"Conde Cambero Juan Carlos",
    "wof:placetype":"venue"
},
  "geometry": {"coordinates":[-7.2788238525,38.5129699707],"type":"Point"}
}