{
  "type": "Feature",
  "properties": {
    "addr:full":"Calle de Garay Juan De, 53 Bilbao Vizcaya 48003",
    "addr:housenumber":"53",
    "addr:postcode":"48003",
    "addr:street":"Calle De Garay Juan De",
    "iso:country":"ES",
    "sg:address":"Calle de Garay Juan De, 53",
    "sg:city":"Bilbao",
    "sg:orig_category":"Bancos",
    "sg:phone":"+34 944 70 21 66",
    "sg:postcode":"48003",
    "sg:province":"Vizcaya",
    "wof:name":"Banco Guipuzcoano S.a.",
    "wof:placetype":"venue"
},
  "geometry": {"coordinates":[-2.9340469837,43.2510261536],"type":"Point"}
}