{
  "type": "Feature",
  "properties": {
    "addr:full":"Carr Josep Tarradellas, 44 Blanes Girona 17300",
    "addr:housenumber":"44",
    "addr:postcode":"17300",
    "addr:street":"Carr Josep Tarradellas",
    "iso:country":"ES",
    "sg:address":"Carr Josep Tarradellas, 44",
    "sg:city":"Blanes",
    "sg:orig_category":"Asilos De Ancianos. Centros Privados",
    "sg:phone":"+34 972 33 73 51",
    "sg:postcode":"17300",
    "sg:province":"Girona",
    "wof:name":"Residencial Blanes S.l.",
    "wof:placetype":"venue"
},
  "geometry": {"coordinates":[2.784637928,41.6683273315],"type":"Point"}
}