{
  "type": "Feature",
  "properties": {
    "addr:full":"Carrer de Sant Francesc Xavier, 2 Costa D'en Blanes Islas Baleares 07181",
    "addr:housenumber":"2",
    "addr:postcode":"07181",
    "addr:street":"Carrer De Sant Francesc Xavier;Costa D'En Blanes Islas",
    "iso:country":"ES",
    "sg:address":"Carrer de Sant Francesc Xavier, 2",
    "sg:city":"Costa D'en Blanes",
    "sg:orig_category":"Agencias Y Agentes Comerciales, Representantes",
    "sg:phone":"+34 971 67 57 27",
    "sg:postcode":"07181",
    "sg:province":"Islas Baleares",
    "wof:name":"Lopez Garcia Vicente",
    "wof:placetype":"venue"
},
  "geometry": {"coordinates":[2.9117100239,39.6136398315],"type":"Point"}
}