{
  "type": "Feature",
  "properties": {
    "addr:full":"Carr Guernica, 24 Cervera Lleida 25200",
    "addr:housenumber":"24",
    "addr:postcode":"25200",
    "addr:street":"Carr Guernica",
    "iso:country":"ES",
    "sg:address":"Carr Guernica, 24",
    "sg:city":"Cervera",
    "sg:orig_category":"Empresas De Pintura Y Revestimientos",
    "sg:phone":"+34 973 53 09 06",
    "sg:postcode":"25200",
    "sg:province":"Lleida",
    "wof:name":"Villar Ramos Pedro",
    "wof:placetype":"venue"
},
  "geometry": {"coordinates":[1.2714600563,41.6712989807],"type":"Point"}
}