{
  "type": "Feature",
  "properties": {
    "iso:country":"ES",
    "sg:address":"Calle de Don Hipolito Ezquerra, 29",
    "sg:city":"Fuensalida",
    "sg:orig_category":"Servicios De Higiene Y Peluquer\u00cda Para Perros Y Gatos",
    "sg:phone":"+34 925 78 55 96",
    "sg:postcode":"45510",
    "sg:province":"Toledo",
    "wof:name":"Clinica Veterinaria Tu Mascota S.l.",
    "wof:placetype":"venue"
},
  "geometry": {"coordinates":[-4.2075896263,40.0540046692],"type":"Point"}
}