{
  "type": "Feature",
  "properties": {
    "iso:country":"ES",
    "sg:address":"Calle de Almu\u00d1ecar, S/n",
    "sg:city":"Albolote",
    "sg:orig_category":"Frutas Y Legumbres Secas (al Por Mayor)",
    "sg:phone":"+34 958 46 50 39",
    "sg:postcode":"18220",
    "sg:province":"Granada",
    "wof:name":"Importaco S.a.",
    "wof:placetype":"venue"
},
  "geometry": {"coordinates":[-3.6434030533,37.2244758606],"type":"Point"}
}