{
  "type": "Feature",
  "properties": {
    "iso:country":"ES",
    "sg:address":"Calle de San Luis, 4",
    "sg:city":"Valladolid",
    "sg:orig_category":"Muebles, Minoristas",
    "sg:phone":"+34 983 30 75 58",
    "sg:postcode":"47004",
    "sg:province":"Valladolid",
    "sg:website":"www.roche-bobois.com",
    "wof:name":"Ausin Perez Jesus Fernando",
    "wof:placetype":"venue"
},
  "geometry": {"coordinates":[-4.7199211121,41.6471939087],"type":"Point"}
}