{
  "type": "Feature",
  "properties": {
    "addr:full":"P Salinas, 5 Aljaraque Huelva 21110",
    "addr:housenumber":"5",
    "addr:postcode":"21110",
    "addr:street":"Salinas",
    "iso:country":"ES",
    "sg:address":"P Salinas, 5",
    "sg:city":"Aljaraque",
    "sg:orig_category":"Fabricaci\u00d3n, Reparaci\u00d3n Y Mantenimiento De Construcciones Navales Y Fluviales",
    "sg:phone":"+34 959 52 12 87",
    "sg:postcode":"21110",
    "sg:province":"Huelva",
    "wof:name":"Aage Hempel International S.a.",
    "wof:placetype":"venue"
},
  "geometry": {"coordinates":[-6.997445,37.277653],"type":"Point"}
}