{
  "type": "Feature",
  "properties": {
    "iso:country":"ES",
    "sg:address":"Carrer de Viladomat, 174",
    "sg:city":"Barcelona",
    "sg:orig_category":"Ingeniero",
    "sg:phone":"+34 934 51 01 60",
    "sg:postcode":"08015",
    "sg:province":"Barcelona",
    "sg:website":"www.feceminte.es",
    "wof:name":"Federacio Catalana D'empresaris Instaladors De Telecomunicacions",
    "wof:placetype":"venue"
},
  "geometry": {"coordinates":[2.1524329185,41.3835487366],"type":"Point"}
}