{
  "type": "Feature",
  "properties": {
    "addr:full":"Calle de Castellon, 15 Sevilla Sevilla 41006",
    "addr:housenumber":"15",
    "addr:postcode":"41006",
    "addr:street":"Calle De Castellon",
    "iso:country":"ES",
    "sg:address":"Calle de Castellon, 15",
    "sg:city":"Sevilla",
    "sg:orig_category":"Talleres De Corte Y Confecci\u00d3n",
    "sg:phone":"+34 954 92 14 94",
    "sg:postcode":"41006",
    "sg:province":"Sevilla",
    "wof:name":"Xu  Aiying",
    "wof:placetype":"venue"
},
  "geometry": {"coordinates":[-5.953772068,37.3707771301],"type":"Point"}
}