{
  "type": "Feature",
  "properties": {
    "iso:country":"ES",
    "sg:address":"Carrer de Vallespir, 25",
    "sg:city":"Barcelona",
    "sg:orig_category":"Bisuter\u00cda, Joyer\u00cda, Relojer\u00cda (al Por Menor)",
    "sg:phone":"+34 933 30 63 94",
    "sg:postcode":"08014",
    "sg:province":"Barcelona",
    "wof:name":"La Guardiola D'or S.l.",
    "wof:placetype":"venue"
},
  "geometry": {"coordinates":[2.1374440193,41.3787193298],"type":"Point"}
}