{
  "type": "Feature",
  "properties": {
    "addr:full":"Avda Pico Ocejon (de), S/n Villanueva Torre Guadalajara 19209",
    "addr:postcode":"19209",
    "addr:street":"Avda Pico Ocejon De S / N Villanueva Torre",
    "iso:country":"ES",
    "sg:address":"Avda Pico Ocejon (de), S/n",
    "sg:city":"Villanueva Torre",
    "sg:orig_category":"Papeler\u00cdas, Librer\u00cdas",
    "sg:phone":"+34 949 27 30 21",
    "sg:postcode":"19209",
    "sg:province":"Guadalajara",
    "wof:name":"Zarco Aguilar Ezequiel Eloy",
    "wof:placetype":"venue"
},
  "geometry": {"coordinates":[-3.2999801636,40.580368042],"type":"Point"}
}