{
  "type": "Feature",
  "properties": {
    "addr:full":"Calle de Jose Luis Castro, 4 Cortegada Ourense 32200",
    "addr:housenumber":"4",
    "addr:postcode":"32200",
    "addr:street":"Calle De Jose Luis Castro",
    "iso:country":"ES",
    "sg:address":"Calle de Jose Luis Castro, 4",
    "sg:city":"Cortegada",
    "sg:orig_category":"Muebles, Minoristas",
    "sg:phone":"+34 988 48 30 22",
    "sg:postcode":"32200",
    "sg:province":"Ourense",
    "wof:name":"Viso Losada Manuel",
    "wof:placetype":"venue"
},
  "geometry": {"coordinates":[-8.1720438004,42.2064094543],"type":"Point"}
}