{
  "type": "Feature",
  "properties": {
    "addr:full":"Calle de Ledas (las), S/n Ledas Santa Cruz De Tenerife 38712",
    "addr:postcode":"38712",
    "addr:street":"Calle De Ledas Las S / N Ledas",
    "iso:country":"ES",
    "sg:address":"Calle de Ledas (las), S/n",
    "sg:city":"Ledas",
    "sg:orig_category":"Cooperativas Agr\u00cdcolas",
    "sg:phone":"+34 922 43 40 61",
    "sg:postcode":"38712",
    "sg:province":"Santa Cruz De Tenerife",
    "wof:name":"Morales Sicilia Jose Francisco",
    "wof:placetype":"venue"
},
  "geometry": {"coordinates":[-17.7672138214,28.6476554871],"type":"Point"}
}