{
  "type": "Feature",
  "properties": {
    "addr:full":"Avda Buenos Aires, 68 Santa Cruz De Tenerife Santa Cruz De Tenerife 38003",
    "addr:housenumber":"68",
    "addr:postcode":"38003",
    "addr:street":"Avda Buenos Aires",
    "iso:country":"ES",
    "sg:address":"Avda Buenos Aires, 68",
    "sg:city":"Santa Cruz De Tenerife",
    "sg:orig_category":"Materiales De Construcci\u00d3n (en General)",
    "sg:phone":"+34 922 20 48 41",
    "sg:postcode":"38003",
    "sg:province":"Santa Cruz De Tenerife",
    "wof:name":"Las Chafiras S. A.",
    "wof:placetype":"venue"
},
  "geometry": {"coordinates":[-16.3326644897,28.4846744537],"type":"Point"}
}