{
  "type": "Feature",
  "properties": {
    "addr:full":"Calle de Fundacion Concha, 6 Navalmoral Mata C\u00e1ceres 10300",
    "addr:housenumber":"6",
    "addr:postcode":"10300",
    "addr:street":"Calle De Fundacion Concha;Ca\u0301Ceres",
    "iso:country":"ES",
    "sg:address":"Calle de Fundacion Concha, 6",
    "sg:city":"Navalmoral Mata",
    "sg:orig_category":"M\u00c9dicos: Ginecolog\u00cda Y Obstetricia",
    "sg:phone":"+34 927 53 31 85",
    "sg:postcode":"10300",
    "sg:province":"C\u00e1ceres",
    "wof:name":"Prudencio Paris Calixto",
    "wof:placetype":"venue"
},
  "geometry": {"coordinates":[-5.5389990807,39.8913154602],"type":"Point"}
}