{
  "type": "Feature",
  "properties": {
    "addr:full":"Calle de Morella, 36 Sant Mateu Castell\u00f3n 12170",
    "addr:housenumber":"36",
    "addr:postcode":"12170",
    "addr:street":"Calle De Morella",
    "iso:country":"ES",
    "sg:address":"Calle de Morella, 36",
    "sg:city":"Sant Mateu",
    "sg:orig_category":"Carnicer\u00cdas, Carnicer\u00cdas",
    "sg:phone":"+34 964 41 62 45",
    "sg:postcode":"12170",
    "sg:province":"Castell\u00f3n",
    "wof:name":"Riba Cucala Filadelfo",
    "wof:placetype":"venue"
},
  "geometry": {"coordinates":[0.1785899997,40.4668502808],"type":"Point"}
}