{
  "type": "Feature",
  "properties": {
    "addr:full":"Calle de Ferroviarios, 11 Madrid Madrid 28026",
    "addr:housenumber":"11",
    "addr:postcode":"madrid;28026",
    "addr:street":"Calle De Ferroviarios",
    "iso:country":"ES",
    "sg:address":"Calle de Ferroviarios, 11",
    "sg:city":"Madrid",
    "sg:orig_category":"Charcuter\u00cdas (al Por Mayor)",
    "sg:phone":"+34 915 00 41 51",
    "sg:postcode":"28026",
    "sg:province":"Madrid",
    "wof:name":"Lin  Yun",
    "wof:placetype":"venue"
},
  "geometry": {"coordinates":[-3.7051010132,40.3865890503],"type":"Point"}
}