{
  "type": "Feature",
  "properties": {
    "addr:full":"Calle de Carretera De Fuensanta, 51 Ciudad Real Ciudad Real 13004",
    "addr:housenumber":"51",
    "addr:postcode":"13004",
    "addr:street":"Calle De Carretera De Fuensanta",
    "iso:country":"ES",
    "sg:address":"Calle de Carretera De Fuensanta, 51",
    "sg:city":"Ciudad Real",
    "sg:orig_category":"Montaje (empresas De)",
    "sg:phone":"+34 926 22 56 40",
    "sg:postcode":"13004",
    "sg:province":"Ciudad Real",
    "wof:name":"Mata Fernandez Hilario",
    "wof:placetype":"venue"
},
  "geometry": {"coordinates":[-3.9267222881,38.9739112854],"type":"Point"}
}