{
  "type": "Feature",
  "properties": {
    "addr:full":"Carrer de Energia, 37 Almeda Mercader Barcelona 08940",
    "addr:housenumber":"37",
    "addr:postcode":"08940",
    "addr:street":"Carrer De Energia;Mercader Barcelona",
    "iso:country":"ES",
    "sg:address":"Carrer de Energia, 37",
    "sg:city":"Almeda Mercader",
    "sg:orig_category":"Embalajes",
    "sg:phone":"+34 933 77 21 03",
    "sg:postcode":"08940",
    "sg:province":"Barcelona",
    "wof:name":"Del Rio Embalatges S.l.",
    "wof:placetype":"venue"
},
  "geometry": {"coordinates":[2.0708940029,41.3559417725],"type":"Point"}
}