{
  "type": "Feature",
  "properties": {
    "addr:full":"Av En Joan Carles I, 11 Elche Alicante 03203",
    "addr:housenumber":"11",
    "addr:postcode":"03203",
    "addr:street":"Av En Joan Carles I",
    "iso:country":"ES",
    "sg:address":"Av En Joan Carles I, 11",
    "sg:city":"Elche",
    "sg:orig_category":"Asociaciones Y Clubs Deportivos",
    "sg:phone":"+34 965 42 72 62",
    "sg:postcode":"03203",
    "sg:province":"Alicante",
    "wof:name":"Loop Machina S.l.",
    "wof:placetype":"venue"
},
  "geometry": {"coordinates":[-0.6944710016,38.266746521],"type":"Point"}
}