{
  "type": "Feature",
  "properties": {
    "addr:full":"Calle de Cervantes, 18 Almodovar Campo Ciudad Real 13580",
    "addr:housenumber":"18",
    "addr:postcode":"13580",
    "addr:street":"Calle De Cervantes",
    "iso:country":"ES",
    "sg:address":"Calle de Cervantes, 18",
    "sg:city":"Almodovar Campo",
    "sg:orig_category":"Bisuter\u00cda, Joyer\u00cda, Relojer\u00cda (al Por Menor)",
    "sg:phone":"+34 926 48 40 95",
    "sg:postcode":"13580",
    "sg:province":"Ciudad Real",
    "wof:name":"Rios Joyeros S.l.",
    "wof:placetype":"venue"
},
  "geometry": {"coordinates":[-4.1807188988,38.7074928284],"type":"Point"}
}