{
  "type": "Feature",
  "properties": {
    "iso:country":"ES",
    "sg:address":"Avda General Sanjurjo, 39",
    "sg:city":"Coru\u00d1a",
    "sg:orig_category":"M\u00c9dicos: Cirug\u00cda General",
    "sg:phone":"+34 981 13 34 34",
    "sg:postcode":"15006",
    "sg:province":"La Coru\u00f1a",
    "wof:name":"Sanchez Gonzalez Federico",
    "wof:placetype":"venue"
},
  "geometry": {"coordinates":[-8.3913040161,43.353061676],"type":"Point"}
}