{
  "type": "Feature",
  "properties": {
    "addr:full":"Calle de Mayorga, 32 Madrid Madrid 28043",
    "addr:housenumber":"32",
    "addr:postcode":"madrid;28043",
    "addr:street":"Calle De Mayorga",
    "iso:country":"ES",
    "sg:address":"Calle de Mayorga, 32",
    "sg:city":"Madrid",
    "sg:orig_category":"Contenedores (mercanc\u00cdas)",
    "sg:phone":"+34 913 00 14 09",
    "sg:postcode":"28043",
    "sg:province":"Madrid",
    "wof:name":"Lopez Herranz Antonio",
    "wof:placetype":"venue"
},
  "geometry": {"coordinates":[-3.6526589394,40.4610214233],"type":"Point"}
}