{
  "type": "Feature",
  "properties": {
    "addr:full":"Carrer de Valencia, 222 Barcelona Barcelona 08011",
    "addr:housenumber":"222",
    "addr:postcode":"08011",
    "addr:street":"Carrer De Valencia",
    "iso:country":"ES",
    "sg:address":"Carrer de Valencia, 222",
    "sg:city":"Barcelona",
    "sg:orig_category":"Psic\u00d3logos",
    "sg:phone":"+34 934 54 09 81",
    "sg:postcode":"08011",
    "sg:province":"Barcelona",
    "wof:name":"Cepsiap S.c.p.",
    "wof:placetype":"venue"
},
  "geometry": {"coordinates":[2.1594460011,41.3896102905],"type":"Point"}
}