{
  "type": "Feature",
  "properties": {
    "addr:full":"Calle de Ermita, 18 Burlada Navarra 31600",
    "addr:housenumber":"18",
    "addr:postcode":"31600",
    "addr:street":"Calle De Ermita",
    "iso:country":"ES",
    "sg:address":"Calle de Ermita, 18",
    "sg:city":"Burlada",
    "sg:orig_category":"Centros De Educaci\u00d3n Especial",
    "sg:phone":"+34 948 13 66 68",
    "sg:postcode":"31600",
    "sg:province":"Navarra",
    "wof:name":"Ayuntamiento De Burlada",
    "wof:placetype":"venue"
},
  "geometry": {"coordinates":[-1.6144223213,42.8248939514],"type":"Point"}
}