{
  "type": "Feature",
  "properties": {
    "iso:country":"ES",
    "sg:address":"Avda Angel Marquez Escobar, 33",
    "sg:city":"Villafranca De Los Barros",
    "sg:orig_category":"Producci\u00d3n De Abonos Y De Fertilizantes",
    "sg:phone":"+34 924 52 53 32",
    "sg:postcode":"06220",
    "sg:province":"Badajoz",
    "wof:name":"Garcia Dominguez Angel",
    "wof:placetype":"venue"
},
  "geometry": {"coordinates":[-6.3416090012,38.5633010864],"type":"Point"}
}