{
  "type": "Feature",
  "properties": {
    "iso:country":"ES",
    "sg:address":"Carrer de Duc Estremera, 7",
    "sg:city":"Palmanova",
    "sg:orig_category":"Vinos Y Licores (venta Al Por Menor)",
    "sg:phone":"+34 971 13 52 09",
    "sg:postcode":"07181",
    "sg:province":"Islas Baleares",
    "wof:name":"Supermercados Superdeal S.l.",
    "wof:placetype":"venue"
},
  "geometry": {"coordinates":[2.5657799244,39.5388221741],"type":"Point"}
}