{
  "type": "Feature",
  "properties": {
    "iso:country":"ES",
    "sg:address":"Av Onze De Setembre (de L'), 6",
    "sg:city":"Montornes Centre",
    "sg:orig_category":"Peluqueros: De Se\u00d1oras",
    "sg:phone":"+34 935 68 18 38",
    "sg:postcode":"08170",
    "sg:province":"Barcelona",
    "wof:name":"Barba Martinez Antoni Jesus",
    "wof:placetype":"venue"
},
  "geometry": {"coordinates":[2.2637119293,41.542388916],"type":"Point"}
}