{
  "type": "Feature",
  "properties": {
    "iso:country":"ES",
    "sg:address":"Carrer de Mare De Deu De Port, 70",
    "sg:city":"Barcelona",
    "sg:orig_category":"Molduras, Junquillos, Listones Y Molduras Perforadas",
    "sg:phone":"+34 932 23 10 33",
    "sg:postcode":"08038",
    "sg:province":"Barcelona",
    "wof:name":"Garcia Ortega Ignacio",
    "wof:placetype":"venue"
},
  "geometry": {"coordinates":[2.1463420391,41.3553695679],"type":"Point"}
}