{
  "type": "Feature",
  "properties": {
    "iso:country":"ES",
    "sg:address":"Calle de Federico Garcia Lorca, 9",
    "sg:city":"Algeciras",
    "sg:orig_category":"Panader\u00cdas, Panader\u00cdas",
    "sg:phone":"+34 956 60 23 21",
    "sg:postcode":"11207",
    "sg:province":"C\u00e1diz",
    "wof:name":"La Dulce Campesina S.l.",
    "wof:placetype":"venue"
},
  "geometry": {"coordinates":[-5.4523100853,36.1143875122],"type":"Point"}
}