{
  "type": "Feature",
  "properties": {
    "addr:full":"Ctra Sevilla-huelva, Km. 0577,0 Sanlucar Mayor Sevilla 41800",
    "addr:postcode":"41800",
    "addr:street":"Ctra Sevilla-Huelva Km. 0577,0",
    "iso:country":"ES",
    "sg:address":"Ctra Sevilla-huelva, Km. 0577,0",
    "sg:city":"Sanlucar Mayor",
    "sg:orig_category":"Producci\u00d3n, Venta De Productos De Agricultura Biol\u00d3gica",
    "sg:phone":"+34 955 95 09 28",
    "sg:postcode":"41800",
    "sg:province":"Sevilla",
    "wof:name":"Agarca S.a.",
    "wof:placetype":"venue"
},
  "geometry": {"coordinates":[-6.2064390182,37.3923377991],"type":"Point"}
}