{
  "type": "Feature",
  "properties": {
    "addr:full":"Rua Montero Rios (de), 33 Santiago De Compostela La Coru\u00f1a 15706",
    "addr:housenumber":"33",
    "addr:postcode":"15706",
    "addr:street":"Rua Montero Rios De;Corun\u0303A",
    "iso:country":"ES",
    "sg:address":"Rua Montero Rios (de), 33",
    "sg:city":"Santiago De Compostela",
    "sg:orig_category":"Abogados",
    "sg:phone":"+34 981 59 30 66",
    "sg:postcode":"15706",
    "sg:province":"La Coru\u00f1a",
    "wof:name":"Guillan Fajardo Juan",
    "wof:placetype":"venue"
},
  "geometry": {"coordinates":[-8.5497951508,42.8755531311],"type":"Point"}
}