{
  "type": "Feature",
  "properties": {
    "iso:country":"ES",
    "sg:address":"A Zamorana, S/n",
    "sg:city":"S. Cibrao Vi\u00f1as",
    "sg:orig_category":"Empresas De Hormig\u00d3n, Hormig\u00d3n Armado Y Pretensado",
    "sg:phone":"+34 988 40 56 25",
    "sg:postcode":"32911",
    "sg:province":"Ourense",
    "sg:website":"www.mosaicosperez.com",
    "wof:name":"Mosaicos Perez S. L.",
    "wof:placetype":"venue"
},
  "geometry": {"coordinates":[-7.872358799,42.2972106934],"type":"Point"}
}