{
  "type": "Feature",
  "properties": {
    "addr:full":"Calle de Varaderos, S/n Punta Umbria Huelva 21100",
    "addr:housenumber":"s / n",
    "addr:postcode":"21100",
    "addr:street":"Calle De Varaderos",
    "iso:country":"ES",
    "sg:address":"Calle de Varaderos, S/n",
    "sg:city":"Punta Umbria",
    "sg:orig_category":"Empresas De Carpinter\u00cda",
    "sg:phone":"+34 959 31 14 41",
    "sg:postcode":"21100",
    "sg:province":"Huelva",
    "wof:name":"Hierro Alvarez Domingo",
    "wof:placetype":"venue"
},
  "geometry": {"coordinates":[-6.9673891068,37.189540863],"type":"Point"}
}