{
  "type": "Feature",
  "properties": {
    "iso:country":"ES",
    "sg:address":"Plaz Austria, S/n",
    "sg:city":"Arroyo De La Miel-benalmadena Costa",
    "sg:orig_category":"Asociaciones, Organismos Culturales Y Socioeducativos",
    "sg:phone":"+34 952 56 04 28",
    "sg:postcode":"29631",
    "sg:province":"M\u00e1laga",
    "wof:name":"Ayuntamiento De Benalmadena",
    "wof:placetype":"venue"
},
  "geometry": {"coordinates":[-4.52206707,36.5950202942],"type":"Point"}
}