{
  "type": "Feature",
  "properties": {
    "addr:full":"Avda Primero De Mayo, 6 Valle Trapaga Vizcaya 48510",
    "addr:housenumber":"6",
    "addr:postcode":"48510",
    "addr:street":"Avda Primero De Mayo;Trapaga",
    "iso:country":"ES",
    "sg:address":"Avda Primero De Mayo, 6",
    "sg:city":"Valle Trapaga",
    "sg:orig_category":"Peluquer\u00cdas, Peluquer\u00cda Mixta",
    "sg:phone":"+34 944 92 20 55",
    "sg:postcode":"48510",
    "sg:province":"Vizcaya",
    "wof:name":"Jose Maria Fuentes Guerrero",
    "wof:placetype":"venue"
},
  "geometry": {"coordinates":[-3.0366528034,43.3044128418],"type":"Point"}
}