{
  "type": "Feature",
  "properties": {
    "iso:country":"ES",
    "sg:address":"Pl. Espa\u00f1a, 1",
    "sg:city":"Porreres",
    "sg:orig_category":"Caf\u00c9s, Bares, Cervecer\u00cdas",
    "sg:phone":"+34 971 64 71 34",
    "sg:postcode":"07260",
    "sg:province":"Islas Baleares",
    "wof:name":"Rigo Riera Andres",
    "wof:placetype":"venue"
},
  "geometry": {"coordinates":[3.0283200741,39.512298584],"type":"Point"}
}