{
  "type": "Feature",
  "properties": {
    "addr:full":"Cmno Molino (del), S/n Camarma Esteruelas Madrid 28816",
    "addr:housenumber":"/ n",
    "addr:postcode":"esteruelas;28816",
    "addr:street":"Cmno Molino Del S",
    "iso:country":"ES",
    "sg:address":"Cmno Molino (del), S/n",
    "sg:city":"Camarma Esteruelas",
    "sg:orig_category":"Polideportivos",
    "sg:phone":"+34 918 85 71 12",
    "sg:postcode":"28816",
    "sg:province":"Madrid",
    "wof:name":"Ayuntamiento De Camarma De Esteruelas",
    "wof:placetype":"venue"
},
  "geometry": {"coordinates":[-3.375825882,40.5455513],"type":"Point"}
}