{
  "type": "Feature",
  "properties": {
    "addr:full":"Calle de Joaquin Blume, 14 Torrejon Ardoz Madrid 28850",
    "addr:housenumber":"14",
    "addr:postcode":"28850",
    "addr:street":"Calle De Joaquin Blume",
    "iso:country":"ES",
    "sg:address":"Calle de Joaquin Blume, 14",
    "sg:city":"Torrejon Ardoz",
    "sg:orig_category":"Centros Empresariales",
    "sg:phone":"+34 916 56 81 90",
    "sg:postcode":"28850",
    "sg:province":"Madrid",
    "wof:name":"Fernandez Garcia-cuevas Jose Luis",
    "wof:placetype":"venue"
},
  "geometry": {"coordinates":[-3.4712131023,40.4430084229],"type":"Point"}
}