{
  "type": "Feature",
  "properties": {
    "iso:country":"ES",
    "sg:address":"Rua Anxeles, 33",
    "sg:city":"Betanzos",
    "sg:orig_category":"Peluqueros: De Se\u00d1oras",
    "sg:phone":"+34 981 77 40 48",
    "sg:postcode":"15300",
    "sg:province":"La Coru\u00f1a",
    "wof:name":"Carneiro Medin Maria Susana",
    "wof:placetype":"venue"
},
  "geometry": {"coordinates":[-8.2088165283,43.2788619995],"type":"Point"}
}