{
  "type": "Feature",
  "properties": {
    "addr:full":"Calle de Fuencarral, 33 Madrid Madrid 28004",
    "addr:housenumber":"33",
    "addr:postcode":"madrid;28004",
    "addr:street":"Calle De Fuencarral",
    "iso:country":"ES",
    "sg:address":"Calle de Fuencarral, 33",
    "sg:city":"Madrid",
    "sg:orig_category":"Inmobiliaria (agencias)",
    "sg:phone":"+34 915 22 79 10",
    "sg:postcode":"28004",
    "sg:province":"Madrid",
    "wof:name":"Fapersa S.l.",
    "wof:placetype":"venue"
},
  "geometry": {"coordinates":[-3.7009010315,40.422203064],"type":"Point"}
}