{
  "type": "Feature",
  "properties": {
    "addr:full":"Calle de Bernardo Mulleras, 3 Ciudad Real Ciudad Real 13001",
    "addr:housenumber":"3",
    "addr:postcode":"13001",
    "addr:street":"Calle De Bernardo Mulleras",
    "iso:country":"ES",
    "sg:address":"Calle de Bernardo Mulleras, 3",
    "sg:city":"Ciudad Real",
    "sg:orig_category":"Molduras, Junquillos, Listones Y Molduras Perforadas",
    "sg:phone":"+34 926 21 30 30",
    "sg:postcode":"13001",
    "sg:province":"Ciudad Real",
    "wof:name":"Velarde Castellanos Antonio",
    "wof:placetype":"venue"
},
  "geometry": {"coordinates":[-3.9300589561,38.9841995239],"type":"Point"}
}