{
  "type": "Feature",
  "properties": {
    "iso:country":"ES",
    "sg:address":"Av Pere Vaquer, 2",
    "sg:city":"Magaluf",
    "sg:orig_category":"Caf\u00c9s, Bares, Cervecer\u00cdas",
    "sg:phone":"+34 971 13 07 46",
    "sg:postcode":"07181",
    "sg:province":"Islas Baleares",
    "wof:name":"Navarrete Vilches Eduardo",
    "wof:placetype":"venue"
},
  "geometry": {"coordinates":[2.5351901054,39.5094108582],"type":"Point"}
}