{
  "type": "Feature",
  "properties": {
    "iso:country":"ES",
    "sg:address":"Calle de General Moscardo, S/n",
    "sg:city":"Iglesuela",
    "sg:orig_category":"Energ\u00cda Solar Y Nuevas Energ\u00cdas (equipo, Estudios)",
    "sg:phone":"+34 925 87 46 53",
    "sg:postcode":"45633",
    "sg:province":"Toledo",
    "wof:name":"Luz Verde Energia Solar Sociedad Cooperativa",
    "wof:placetype":"venue"
},
  "geometry": {"coordinates":[-4.7520418167,40.2323379517],"type":"Point"}
}