{
  "type": "Feature",
  "properties": {
    "addr:full":"Pla\u00c7 Cubilot, 4 Vilanova I La Geltru Barcelona 08800",
    "addr:housenumber":"4",
    "addr:postcode":"08800",
    "addr:street":"Cubilot",
    "iso:country":"ES",
    "sg:address":"Pla\u00c7 Cubilot, 4",
    "sg:city":"Vilanova I La Geltru",
    "sg:orig_category":"Empresas De Electricidad En General",
    "sg:phone":"+34 938 16 54 59",
    "sg:postcode":"08800",
    "sg:province":"Barcelona",
    "wof:name":"Enginova S.l.",
    "wof:placetype":"venue"
},
  "geometry": {"coordinates":[1.7189840078,41.2272224426],"type":"Point"}
}