{
  "type": "Feature",
  "properties": {
    "iso:country":"ES",
    "sg:address":"Calle de Diego De Torres, 6",
    "sg:city":"Alcala Henares",
    "sg:orig_category":"Abogados",
    "sg:phone":"+34 918 81 90 55",
    "sg:postcode":"28801",
    "sg:province":"Madrid",
    "wof:name":"Torres Marin Maria Del Sagrario",
    "wof:placetype":"venue"
},
  "geometry": {"coordinates":[-3.3679659367,40.4836616516],"type":"Point"}
}