{
  "type": "Feature",
  "properties": {
    "addr:full":"C/ Antoni Duran, 26 Manacor Islas Baleares 07500",
    "addr:housenumber":"26",
    "addr:postcode":"07500",
    "addr:street":"C / Antoni Duran",
    "iso:country":"ES",
    "sg:address":"C/ Antoni Duran, 26",
    "sg:city":"Manacor",
    "sg:orig_category":"Frutas Y Legumbres Frescas (al Por Mayor)",
    "sg:phone":"+34 971 55 07 89",
    "sg:postcode":"07500",
    "sg:province":"Islas Baleares",
    "wof:name":"Frutas Lluisset C.b.",
    "wof:placetype":"venue"
},
  "geometry": {"coordinates":[3.2091879845,39.5677871704],"type":"Point"}
}