{
  "type": "Feature",
  "properties": {
    "addr:full":"Pase Independencia, 42 Huelva Huelva 21002",
    "addr:housenumber":"42",
    "addr:postcode":"21002",
    "addr:street":"Independencia",
    "iso:country":"ES",
    "sg:address":"Pase Independencia, 42",
    "sg:city":"Huelva",
    "sg:orig_category":"Fabricaci\u00d3n De Bolsos Y Bolsos De Tela",
    "sg:phone":"+34 959 24 46 96",
    "sg:postcode":"21002",
    "sg:province":"Huelva",
    "wof:name":"Garcia Martinez Blas",
    "wof:placetype":"venue"
},
  "geometry": {"coordinates":[-6.9522190094,37.2643470764],"type":"Point"}
}