{
  "type": "Feature",
  "properties": {
    "iso:country":"ES",
    "sg:address":"Pla\u00c7 Treball, 3",
    "sg:city":"Lleida",
    "sg:orig_category":"Peluqueros: De Se\u00d1oras",
    "sg:phone":"+34 973 23 98 19",
    "sg:postcode":"25008",
    "sg:province":"Lleida",
    "wof:name":"Avilla Durich Pilar",
    "wof:placetype":"venue"
},
  "geometry": {"coordinates":[0.6216008067,41.6232070923],"type":"Point"}
}