{
  "type": "Feature",
  "properties": {
    "addr:full":"Calle de Arias, 15 Zaragoza Zaragoza 50010",
    "addr:housenumber":"15",
    "addr:postcode":"50010",
    "addr:street":"Calle De Arias",
    "iso:country":"ES",
    "sg:address":"Calle de Arias, 15",
    "sg:city":"Zaragoza",
    "sg:orig_category":"Agentes, Concesionarios Y Sucursales De Camiones Y Veh\u00cdculos Industriales",
    "sg:phone":"+34 976 33 95 79",
    "sg:postcode":"50010",
    "sg:province":"Zaragoza",
    "wof:name":"Ara Quero Jose",
    "wof:placetype":"venue"
},
  "geometry": {"coordinates":[-0.9086031914,41.6534614563],"type":"Point"}
}