{
  "type": "Feature",
  "properties": {
    "iso:country":"ES",
    "sg:address":"Calle de San Ciriaco, 5",
    "sg:city":"Madrid",
    "sg:orig_category":"Farmacias",
    "sg:phone":"+34 917 76 01 58",
    "sg:postcode":"28032",
    "sg:province":"Madrid",
    "wof:name":"Zaragoza Alejo Isabel",
    "wof:placetype":"venue"
},
  "geometry": {"coordinates":[-3.6045777798,40.4057579041],"type":"Point"}
}