{
  "type": "Feature",
  "properties": {
    "iso:country":"ES",
    "sg:address":"Calle de Tomas Zarracina, 1",
    "sg:city":"Gijon",
    "sg:orig_category":"Inversiones",
    "sg:phone":"+34 985 34 80 92",
    "sg:postcode":"33206",
    "sg:province":"Asturias",
    "wof:name":"Inversiones Riera S.a.",
    "wof:placetype":"venue"
},
  "geometry": {"coordinates":[-5.6624999046,43.5410461426],"type":"Point"}
}