{
  "type": "Feature",
  "properties": {
    "iso:country":"ES",
    "sg:address":"Vent Sere (pol Campllong), 3",
    "sg:city":"Balaguer",
    "sg:orig_category":"Calderer\u00cda",
    "sg:phone":"+34 973 45 06 36",
    "sg:postcode":"25600",
    "sg:province":"Lleida",
    "wof:name":"Tallers Vinicoles Vent-sere S.l.",
    "wof:placetype":"venue"
},
  "geometry": {"coordinates":[0.8151400089,41.7742195129],"type":"Point"}
}