{
  "type": "Feature",
  "properties": {
    "iso:country":"ES",
    "sg:address":"Ptge Estacio (l'), S/n",
    "sg:city":"Montmelo",
    "sg:orig_category":"Pescader\u00cdas (al Por Menor)",
    "sg:phone":"+34 935 68 04 92",
    "sg:postcode":"08160",
    "sg:province":"Barcelona",
    "wof:name":"Torne Escarre Serafin",
    "wof:placetype":"venue"
},
  "geometry": {"coordinates":[2.2474451065,41.5508842468],"type":"Point"}
}