{
  "type": "Feature",
  "properties": {
    "addr:full":"Calle de Julian Camarillo, 14 Madrid Madrid 28037",
    "addr:housenumber":"14",
    "addr:postcode":"madrid;28037",
    "addr:street":"Calle De Julian Camarillo",
    "iso:country":"ES",
    "sg:address":"Calle de Julian Camarillo, 14",
    "sg:city":"Madrid",
    "sg:orig_category":"Negocio De Materiales De Construcci\u00d3n",
    "sg:phone":"+34 913 04 96 19",
    "sg:postcode":"28037",
    "sg:province":"Madrid",
    "wof:name":"Macotrans 2 Sl",
    "wof:placetype":"venue"
},
  "geometry": {"coordinates":[-3.6285190582,40.4344558716],"type":"Point"}
}