{
  "type": "Feature",
  "properties": {
    "iso:country":"ES",
    "sg:address":"Carr Major, S/n",
    "sg:city":"Gandia",
    "sg:orig_category":"Electrodom\u00c9sticos (fabricaci\u00d3n, Al Por Mayor)",
    "sg:phone":"+34 962 96 50 77",
    "sg:postcode":"46700",
    "sg:province":"Valencia",
    "wof:name":"Comercializadora De Electrodomesticos S.a.",
    "wof:placetype":"venue"
},
  "geometry": {"coordinates":[-0.1913339943,38.960735321],"type":"Point"}
}