{
  "type": "Feature",
  "properties": {
    "addr:full":"Pol. Palancares, S/n Cuenca Cuenca 16003",
    "addr:housenumber":"/ n",
    "addr:postcode":"16003",
    "addr:street":"Palancares S",
    "iso:country":"ES",
    "sg:address":"Pol. Palancares, S/n",
    "sg:city":"Cuenca",
    "sg:orig_category":"Venta, Colocaci\u00d3n, Reparaci\u00d3n De Radiadores Para Veh\u00cdculos",
    "sg:phone":"+34 969 22 51 20",
    "sg:postcode":"16003",
    "sg:province":"Cuenca",
    "wof:name":"Sanchez Campos Andres",
    "wof:placetype":"venue"
},
  "geometry": {"coordinates":[-2.1361989975,40.0586967468],"type":"Point"}
}