{
  "type": "Feature",
  "properties": {
    "iso:country":"ES",
    "sg:address":"Luga Poligono Industrial El Palmar, S/n",
    "sg:city":"Poligono Industrial El Palmar",
    "sg:orig_category":"Suministros Y Materiales Industriales",
    "sg:phone":"+34 956 87 35 06",
    "sg:postcode":"11500",
    "sg:province":"C\u00e1diz",
    "wof:name":"Kit Cocinas S. A.",
    "wof:placetype":"venue"
},
  "geometry": {"coordinates":[-6.2197542191,36.6056632996],"type":"Point"}
}