{
  "type": "Feature",
  "properties": {
    "addr:full":"Mig, 23 Tremp Lleida 25620",
    "addr:postcode":"25620",
    "iso:country":"ES",
    "sg:address":"Mig, 23",
    "sg:city":"Tremp",
    "sg:orig_category":"Inform\u00c1tica, Ofim\u00c1tica (estudios, Asesor\u00cda, Ingenier\u00cda, Formaci\u00d3n)",
    "sg:phone":"+34 973 65 32 14",
    "sg:postcode":"25620",
    "sg:province":"Lleida",
    "wof:name":"Civera Salto Esteve",
    "wof:placetype":"venue"
},
  "geometry": {"coordinates":[0.8972769976,42.1664619446],"type":"Point"}
}