{
  "type": "Feature",
  "properties": {
    "addr:full":"Calle de Tagoror, 22 G\u00fcimar Santa Cruz De Tenerife 38500",
    "addr:housenumber":"22",
    "addr:postcode":"38500",
    "addr:street":"Calle De Tagoror",
    "iso:country":"ES",
    "sg:address":"Calle de Tagoror, 22",
    "sg:city":"G\u00fcimar",
    "sg:orig_category":"Empresas De Carpinter\u00cda",
    "sg:phone":"+34 922 51 24 58",
    "sg:postcode":"38500",
    "sg:province":"Santa Cruz De Tenerife",
    "wof:name":"Tejera Coello Jose Domingo",
    "wof:placetype":"venue"
},
  "geometry": {"coordinates":[-16.3996391296,28.3310527802],"type":"Point"}
}