{
  "type": "Feature",
  "properties": {
    "addr:full":"Carrer de Girona, 186 S. Feliu Guixols Girona 17220",
    "addr:housenumber":"186",
    "addr:postcode":"17220",
    "addr:street":"Carrer De Girona;S. Feliu Guixols",
    "iso:country":"ES",
    "sg:address":"Carrer de Girona, 186",
    "sg:city":"S. Feliu Guixols",
    "sg:orig_category":"Asesor\u00cda Sobre Comunicaci\u00d3n De Empresas",
    "sg:phone":"+34 972 82 28 02",
    "sg:postcode":"17220",
    "sg:province":"Girona",
    "wof:name":"Faya Benitez Antonio",
    "wof:placetype":"venue"
},
  "geometry": {"coordinates":[3.0288300514,41.7870903015],"type":"Point"}
}