{
  "type": "Feature",
  "properties": {
    "addr:full":"Calle de Orense, 11 Madrid Madrid 28020",
    "addr:housenumber":"11",
    "addr:postcode":"madrid;28020",
    "addr:street":"Calle De Orense",
    "iso:country":"ES",
    "sg:address":"Calle de Orense, 11",
    "sg:city":"Madrid",
    "sg:orig_category":"Fabricaci\u00d3n, Importaci\u00d3n, Venta De Material De Telefon\u00cda, Peritelefon\u00cda",
    "sg:phone":"+34 914 17 03 78",
    "sg:postcode":"28020",
    "sg:province":"Madrid",
    "wof:name":"Bt Espa\u00d1a Compa\u00d1ia De Servicios Globales De Telecomunicaciones S.a.u.",
    "wof:placetype":"venue"
},
  "geometry": {"coordinates":[-3.6955590248,40.4483299255],"type":"Point"}
}