{
  "type": "Feature",
  "properties": {
    "iso:country":"ES",
    "sg:address":"Ptda Adsubia, 280",
    "sg:city":"Javea",
    "sg:orig_category":"Centros De Coordinaci\u00d3n",
    "sg:phone":"+34 966 47 05 91",
    "sg:postcode":"03730",
    "sg:province":"Alicante",
    "wof:name":"Trecepicaso S.l.",
    "wof:placetype":"venue"
},
  "geometry": {"coordinates":[0.1668650061,38.7890739441],"type":"Point"}
}