{
  "type": "Feature",
  "properties": {
    "iso:country":"ES",
    "sg:address":"Pl. Rafael Cavestany, S/n",
    "sg:city":"Torrelobaton",
    "sg:orig_category":"Cajas De Ahorro",
    "sg:phone":"+34 983 56 35 06",
    "sg:postcode":"47134",
    "sg:province":"Valladolid",
    "sg:website":"www.cajaespana.es",
    "wof:name":"Caja Espa\u00f1a De Inversiones Caja De Ahorros Y Monte De Piedad",
    "wof:placetype":"venue"
},
  "geometry": {"coordinates":[-5.024971962,41.6491394043],"type":"Point"}
}