{
  "type": "Feature",
  "properties": {
    "iso:country":"ES",
    "sg:address":"Acueducto, 12",
    "sg:city":"Sevilla",
    "sg:orig_category":"Reposter\u00cdas",
    "sg:phone":"+34 954 95 38 39",
    "sg:postcode":"41008",
    "sg:province":"Sevilla",
    "wof:name":"Martinez Moreno Jose Antonio",
    "wof:placetype":"venue"
},
  "geometry": {"coordinates":[-5.9774241447,37.4067268372],"type":"Point"}
}