{
  "type": "Feature",
  "properties": {
    "addr:full":"Trva Trauko, 3 Bilbao Vizcaya 48007",
    "addr:housenumber":"3",
    "addr:postcode":"48007",
    "addr:street":"Trva Trauko",
    "iso:country":"ES",
    "sg:address":"Trva Trauko, 3",
    "sg:city":"Bilbao",
    "sg:orig_category":"Frutas, Legumbres Frescas Y Tempranas (al Por Menor)",
    "sg:phone":"+34 944 13 00 58",
    "sg:postcode":"48007",
    "sg:province":"Vizcaya",
    "wof:name":"Bajeneta Landa Maria Lourdes",
    "wof:placetype":"venue"
},
  "geometry": {"coordinates":[-2.9209580421,43.2675933838],"type":"Point"}
}