{
  "type": "Feature",
  "properties": {
    "iso:country":"ES",
    "sg:address":"Calle de Valencia, 7",
    "sg:city":"Mislata",
    "sg:orig_category":"Comercio De Piezas De Recambio Y De Accesorios De Veh\u00cdculos, Veh\u00cdculos Industriales",
    "sg:phone":"+34 963 58 71 00",
    "sg:postcode":"46920",
    "sg:province":"Valencia",
    "wof:name":"Recambios De Coches S. A.",
    "wof:placetype":"venue"
},
  "geometry": {"coordinates":[-0.411619097,39.4736404419],"type":"Point"}
}