{
  "type": "Feature",
  "properties": {
    "iso:country":"ES",
    "sg:address":"Calle de Martinez De La Rosa, 149",
    "sg:city":"Malaga",
    "sg:orig_category":"Panader\u00cdas, Panader\u00cdas",
    "sg:phone":"+34 952 30 53 88",
    "sg:postcode":"29010",
    "sg:province":"M\u00e1laga",
    "wof:name":"Confiteria La Trufita S. L. L.",
    "wof:placetype":"venue"
},
  "geometry": {"coordinates":[-4.441327095,36.7272796631],"type":"Point"}
}