{
  "type": "Feature",
  "properties": {
    "iso:country":"ES",
    "sg:address":"Calle de Don Pio Coronado, 91",
    "sg:city":"Palmas De Gran Canaria",
    "sg:orig_category":"Armas Y Municiones (fabricaci\u00d3n, Al Por Mayor)",
    "sg:phone":"+34 928 25 76 58",
    "sg:postcode":"35012",
    "sg:province":"Las Palmas",
    "wof:name":"Perez Estupi\u00f1an Domingo",
    "wof:placetype":"venue"
},
  "geometry": {"coordinates":[-15.4341421127,28.1092205048],"type":"Point"}
}