{
  "type": "Feature",
  "properties": {
    "addr:full":"Calle de Marques Del, S/n Aviles Asturias 33402",
    "addr:housenumber":"/ n",
    "addr:postcode":"33402",
    "addr:street":"Calle De Marques Del S",
    "iso:country":"ES",
    "sg:address":"Calle de Marques Del, S/n",
    "sg:city":"Aviles",
    "sg:orig_category":"Sindicatos Y Colegios Profesionales",
    "sg:phone":"+34 985 54 29 11",
    "sg:postcode":"33402",
    "sg:province":"Asturias",
    "wof:name":"Asociacion De Maestros Industriales Y Tecnicos De Formacion",
    "wof:placetype":"venue"
},
  "geometry": {"coordinates":[-5.9215426445,43.5520629883],"type":"Point"}
}