{
  "type": "Feature",
  "properties": {
    "addr:full":"Avgd Republica Argentina, 14 Gandia Valencia 46700",
    "addr:housenumber":"14",
    "addr:postcode":"46700",
    "addr:street":"Argentina;Valencia",
    "iso:country":"ES",
    "sg:address":"Avgd Republica Argentina, 14",
    "sg:city":"Gandia",
    "sg:orig_category":"Estancos",
    "sg:phone":"+34 962 86 20 21",
    "sg:postcode":"46700",
    "sg:province":"Valencia",
    "wof:name":"Segui Ferrer Maria Amparo",
    "wof:placetype":"venue"
},
  "geometry": {"coordinates":[-0.1913339943,38.960735321],"type":"Point"}
}