{
  "type": "Feature",
  "properties": {
    "iso:country":"ES",
    "sg:address":"Calle de Lopez Leiva, 4",
    "sg:city":"Alhama De Almeria",
    "sg:orig_category":"Alimentaci\u00d3n General (al Por Menor)",
    "sg:phone":"+34 950 64 01 59",
    "sg:postcode":"04400",
    "sg:province":"Almer\u00eda",
    "wof:name":"Gonzalez Granero Maria",
    "wof:placetype":"venue"
},
  "geometry": {"coordinates":[-2.5701038837,36.9565200806],"type":"Point"}
}