{
  "type": "Feature",
  "properties": {
    "iso:country":"ES",
    "sg:address":"Calle de Florida, 1",
    "sg:city":"Funes",
    "sg:orig_category":"Plomeros",
    "sg:phone":"+34 948 75 40 45",
    "sg:postcode":"31360",
    "sg:province":"Navarra",
    "wof:name":"Celorrio Carrion S.l.",
    "wof:placetype":"venue"
},
  "geometry": {"coordinates":[-1.7987420559,42.3147621155],"type":"Point"}
}