{
  "type": "Feature",
  "properties": {
    "iso:country":"ES",
    "sg:address":"Carrer de Bobila, 4",
    "sg:city":"Barcelona",
    "sg:orig_category":"Promotores Constructores",
    "sg:phone":"+34 934 23 66 63",
    "sg:postcode":"08004",
    "sg:province":"Barcelona",
    "wof:name":"Instalacions Sarrob S.c.c.l",
    "wof:placetype":"venue"
},
  "geometry": {"coordinates":[2.1584379673,41.3735275269],"type":"Point"}
}