{
  "type": "Feature",
  "properties": {
    "addr:full":"Ctra Ledesma, 96 Salamanca Salamanca 37006",
    "addr:housenumber":"96",
    "addr:postcode":"37006",
    "addr:street":"Ctra Ledesma",
    "iso:country":"ES",
    "sg:address":"Ctra Ledesma, 96",
    "sg:city":"Salamanca",
    "sg:orig_category":"Herboristas (al Por Menor)",
    "sg:phone":"+34 923 25 54 40",
    "sg:postcode":"37006",
    "sg:province":"Salamanca",
    "wof:name":"Sanchez Quiroga David",
    "wof:placetype":"venue"
},
  "geometry": {"coordinates":[-5.6750569344,40.9765167236],"type":"Point"}
}