{
  "type": "Feature",
  "properties": {
    "iso:country":"ES",
    "sg:address":"S. Bartolome, 55",
    "sg:city":"Moncada",
    "sg:orig_category":"Ense\u00d1anza Variada",
    "sg:phone":"+34 961 30 09 77",
    "sg:postcode":"46113",
    "sg:province":"Valencia",
    "sg:website":"www.ceu.es",
    "wof:name":"Centro De Estudios Universitarios San Pablo",
    "wof:placetype":"venue"
},
  "geometry": {"coordinates":[-0.3982529938,39.5452728271],"type":"Point"}
}