{
  "type": "Feature",
  "properties": {
    "iso:country":"ES",
    "sg:address":"Calle de Padre Arrupe, 61",
    "sg:city":"Madrid",
    "sg:orig_category":"Ingenier\u00cda, Centros De Estudios (diversos)",
    "sg:phone":"+34 916 50 43 44",
    "sg:postcode":"28050",
    "sg:province":"Madrid",
    "wof:name":"Wildschut  Louw",
    "wof:placetype":"venue"
},
  "geometry": {"coordinates":[-3.6374974251,40.5053634644],"type":"Point"}
}