{
  "type": "Feature",
  "properties": {
    "iso:country":"ES",
    "sg:address":"Calle de Andres Cortina, 3",
    "sg:city":"Getxo",
    "sg:orig_category":"Molduras, Junquillos, Listones Y Molduras Perforadas",
    "sg:phone":"+34 944 91 07 16",
    "sg:postcode":"48990",
    "sg:province":"Vizcaya",
    "wof:name":"M\u00aa Sol Gomez Antolin (bar Erreatxu)",
    "wof:placetype":"venue"
},
  "geometry": {"coordinates":[-3.0134129524,43.3522109985],"type":"Point"}
}