{
  "type": "Feature",
  "properties": {
    "addr:full":"Av Roma, 220 Manlleu Barcelona 08560",
    "addr:housenumber":"220",
    "addr:postcode":"08560",
    "addr:street":"Av Roma",
    "iso:country":"ES",
    "sg:address":"Av Roma, 220",
    "sg:city":"Manlleu",
    "sg:orig_category":"Molduras, Junquillos, Listones Y Molduras Perforadas",
    "sg:phone":"+34 938 51 00 09",
    "sg:postcode":"08560",
    "sg:province":"Barcelona",
    "wof:name":"Molist Sitja Gabriel",
    "wof:placetype":"venue"
},
  "geometry": {"coordinates":[2.27678895,42.0025978088],"type":"Point"}
}