{
  "type": "Feature",
  "properties": {
    "iso:country":"ES",
    "sg:address":"Avda Mancha (de La), 25",
    "sg:city":"Leganes",
    "sg:orig_category":"Suministros Para Hoteles",
    "sg:phone":"+34 916 88 73 99",
    "sg:postcode":"28911",
    "sg:province":"Madrid",
    "wof:name":"Fayma Legasur S.l.",
    "wof:placetype":"venue"
},
  "geometry": {"coordinates":[-3.7590839863,40.3320198059],"type":"Point"}
}