{
  "type": "Feature",
  "properties": {
    "addr:full":"Carrer de Ribes, 27 Barcelona Barcelona 08013",
    "addr:housenumber":"27",
    "addr:postcode":"08013",
    "addr:street":"Carrer De Ribes",
    "iso:country":"ES",
    "sg:address":"Carrer de Ribes, 27",
    "sg:city":"Barcelona",
    "sg:orig_category":"Extinci\u00d3n De Incendios: Material Y Suministros (fabricaci\u00d3n, Al Por Mayor)",
    "sg:phone":"+34 932 45 26 08",
    "sg:postcode":"08013",
    "sg:province":"Barcelona",
    "wof:name":"M Y J Andres S.a.",
    "wof:placetype":"venue"
},
  "geometry": {"coordinates":[2.1815769672,41.3947906494],"type":"Point"}
}