{
  "type": "Feature",
  "properties": {
    "addr:full":"M. Servet, 18 Gava Barcelona 08850",
    "addr:housenumber":"18",
    "addr:postcode":"08850",
    "addr:street":"M. Servet",
    "iso:country":"ES",
    "sg:address":"M. Servet, 18",
    "sg:city":"Gava",
    "sg:orig_category":"Hilaturas, Hilos Y Actividades Relacionadas",
    "sg:phone":"+34 936 33 38 38",
    "sg:postcode":"08850",
    "sg:province":"Barcelona",
    "sg:website":"www.lineahogar.com",
    "wof:name":"Linea Hogar Deco S.l.",
    "wof:placetype":"venue"
},
  "geometry": {"coordinates":[1.9996210337,41.2960395813],"type":"Point"}
}