{
  "type": "Feature",
  "properties": {
    "iso:country":"ES",
    "sg:address":"Calle de Mayor, 13",
    "sg:city":"Ribaforada",
    "sg:orig_category":"Peluquer\u00cdas, Peluquer\u00cda Mixta",
    "sg:phone":"+34 948 86 41 80",
    "sg:postcode":"31550",
    "sg:province":"Navarra",
    "wof:name":"Ramos Jimenez Julia",
    "wof:placetype":"venue"
},
  "geometry": {"coordinates":[-1.5086950064,41.9974136353],"type":"Point"}
}