{
  "type": "Feature",
  "properties": {
    "addr:full":"A (p I Aeropuerto), S/n Sevilla Sevilla 41020",
    "addr:housenumber":"s / n",
    "addr:postcode":"41020",
    "addr:street":"Aeropuerto",
    "iso:country":"ES",
    "sg:address":"A (p I Aeropuerto), S/n",
    "sg:city":"Sevilla",
    "sg:orig_category":"Mutuas De Seguros",
    "sg:phone":"+34 954 51 50 80",
    "sg:postcode":"41020",
    "sg:province":"Sevilla",
    "wof:name":"Ibermutuamur",
    "wof:placetype":"venue"
},
  "geometry": {"coordinates":[-5.9011440277,37.4260406494],"type":"Point"}
}