{
  "type": "Feature",
  "properties": {
    "iso:country":"ES",
    "sg:address":"Carrer de Escoles (les), S/n",
    "sg:city":"Santpedor",
    "sg:orig_category":"Fabricaci\u00d3n De Pernos, Tornillos Y Clavos",
    "sg:phone":"+34 938 32 16 13",
    "sg:postcode":"08251",
    "sg:province":"Barcelona",
    "wof:name":"G.m.d. S.c.c.l.",
    "wof:placetype":"venue"
},
  "geometry": {"coordinates":[1.8459889889,41.7856674194],"type":"Point"}
}