{
  "type": "Feature",
  "properties": {
    "addr:full":"Calvario, 1 Gares Navarra 31100",
    "addr:housenumber":"1",
    "addr:postcode":"31100",
    "addr:street":"Calvario;Navarra",
    "iso:country":"ES",
    "sg:address":"Calvario, 1",
    "sg:city":"Gares",
    "sg:orig_category":"M\u00c9dicos: Estomatolog\u00cda",
    "sg:phone":"+34 948 34 12 40",
    "sg:postcode":"31100",
    "sg:province":"Navarra",
    "wof:name":"Alonso Ciappa Osvaldo Horacio",
    "wof:placetype":"venue"
},
  "geometry": {"coordinates":[-1.8107696772,42.6740722656],"type":"Point"}
}