{
  "type": "Feature",
  "properties": {
    "iso:country":"ES",
    "sg:address":"Calle de San Roque, 12",
    "sg:city":"Coru\u00d1a",
    "sg:orig_category":"Edici\u00d3n De Diarios, Revistas, Boletines",
    "sg:phone":"+34 981 20 53 36",
    "sg:postcode":"15002",
    "sg:province":"La Coru\u00f1a",
    "wof:name":"Editorial Oceano S.l.",
    "wof:placetype":"venue"
},
  "geometry": {"coordinates":[-8.3975973129,43.3737373352],"type":"Point"}
}