{
  "type": "Feature",
  "properties": {
    "iso:country":"ES",
    "sg:address":"Calle de Matia, 2",
    "sg:city":"Donostia-san Sebastian",
    "sg:orig_category":"Bancos",
    "sg:phone":"+34 943 21 62 35",
    "sg:postcode":"20008",
    "sg:province":"Guip\u00f9zcoa",
    "sg:website":"www.bancopopular.es",
    "wof:name":"Banco Popular Espa\u00f1ol",
    "wof:placetype":"venue"
},
  "geometry": {"coordinates":[-2.0006489754,43.3147659302],"type":"Point"}
}