{
  "type": "Feature",
  "properties": {
    "iso:country":"ES",
    "sg:address":"Federico Garcia Lorca, 16",
    "sg:city":"Haro",
    "sg:orig_category":"Controles De Edificaci\u00d3n (construcci\u00d3n, Seguridad)",
    "sg:phone":"+34 941 31 09 74",
    "sg:postcode":"26200",
    "sg:province":"La Rioja",
    "wof:name":"Arranz Torres Jose Antonio",
    "wof:placetype":"venue"
},
  "geometry": {"coordinates":[-2.910861969,42.5482444763],"type":"Point"}
}