{
  "type": "Feature",
  "properties": {
    "addr:full":"Carrer de Travesseres, 3 Granollers Barcelona 08401",
    "addr:housenumber":"3",
    "addr:postcode":"08401",
    "addr:street":"Carrer De Travesseres",
    "iso:country":"ES",
    "sg:address":"Carrer de Travesseres, 3",
    "sg:city":"Granollers",
    "sg:orig_category":"Bisuter\u00cda, Joyer\u00cda, Relojer\u00cda (al Por Menor)",
    "sg:phone":"+34 938 79 52 10",
    "sg:postcode":"08401",
    "sg:province":"Barcelona",
    "wof:name":"Cano Cabeza Merce",
    "wof:placetype":"venue"
},
  "geometry": {"coordinates":[2.2876520157,41.6090316772],"type":"Point"}
}