{
  "type": "Feature",
  "properties": {
    "iso:country":"ES",
    "sg:address":"C. Cruzcampo (p I Villarrosa), 74",
    "sg:city":"Malaga",
    "sg:orig_category":"Agencias Y Agentes Comerciales, Representantes",
    "sg:phone":"+34 952 17 68 12",
    "sg:postcode":"29004",
    "sg:province":"M\u00e1laga",
    "wof:name":"Garcia Espinar Santiago",
    "wof:placetype":"venue"
},
  "geometry": {"coordinates":[-4.469408989,36.6736831665],"type":"Point"}
}