{
  "type": "Feature",
  "properties": {
    "iso:country":"ES",
    "sg:address":"Calle de Colmenas, S/n",
    "sg:city":"Almazul",
    "sg:orig_category":"Agencias Y Asesores De Publicidad",
    "sg:phone":"+34 975 38 00 36",
    "sg:postcode":"42126",
    "sg:province":"Soria",
    "wof:name":"Miguel Velazquez Almudena",
    "wof:placetype":"venue"
},
  "geometry": {"coordinates":[-2.146481514,41.575088501],"type":"Point"}
}