{
  "type": "Feature",
  "properties": {
    "addr:full":"Calle de Goya, 18 Madrid Madrid 28001",
    "addr:housenumber":"18",
    "addr:postcode":"madrid;28001",
    "addr:street":"Calle De Goya",
    "iso:country":"ES",
    "sg:address":"Calle de Goya, 18",
    "sg:city":"Madrid",
    "sg:orig_category":"Centros Empresariales",
    "sg:phone":"+34 914 26 19 74",
    "sg:postcode":"28001",
    "sg:province":"Madrid",
    "wof:name":"Ruiz Y Paredes Urbanismo Comercial S.l.",
    "wof:placetype":"venue"
},
  "geometry": {"coordinates":[-3.683868885,40.4250526428],"type":"Point"}
}