{
  "type": "Feature",
  "properties": {
    "iso:country":"ES",
    "sg:address":"Rua Gerona, 2",
    "sg:city":"Vigo",
    "sg:orig_category":"Fotocopias, Reprograf\u00cda",
    "sg:phone":"+34 986 23 54 77",
    "sg:postcode":"36211",
    "sg:province":"Pontevedra",
    "wof:name":"Gomez Casal Antonio",
    "wof:placetype":"venue"
},
  "geometry": {"coordinates":[-8.7301368713,42.2228050232],"type":"Point"}
}