{
  "type": "Feature",
  "properties": {
    "iso:country":"ES",
    "sg:address":"Calle de Real, 32",
    "sg:city":"S. Bartolome Abiertas",
    "sg:orig_category":"Cajas Para Embalar",
    "sg:phone":"+34 925 70 40 11",
    "sg:postcode":"45654",
    "sg:province":"Toledo",
    "wof:name":"Caja Rural Provincial De Toledo",
    "wof:placetype":"venue"
},
  "geometry": {"coordinates":[-4.7197737694,39.8286018372],"type":"Point"}
}