{
  "type": "Feature",
  "properties": {
    "addr:full":"Cami Can Biosca, 14 S. Just Desvern Barcelona 08960",
    "addr:housenumber":"14",
    "addr:postcode":"08960",
    "addr:street":"S. Just Desvern Barcelona",
    "iso:country":"ES",
    "sg:address":"Cami Can Biosca, 14",
    "sg:city":"S. Just Desvern",
    "sg:orig_category":"Centros Empresariales",
    "sg:phone":"+34 933 71 85 99",
    "sg:postcode":"08960",
    "sg:province":"Barcelona",
    "wof:name":"Lalibela S.l.",
    "wof:placetype":"venue"
},
  "geometry": {"coordinates":[2.0824029446,41.3905677795],"type":"Point"}
}