{
  "type": "Feature",
  "properties": {
    "iso:country":"ES",
    "sg:address":"Ctra Bigastro, Km. 0002,0",
    "sg:city":"Correntias Medias",
    "sg:orig_category":"Molduras, Junquillos, Listones Y Molduras Perforadas",
    "sg:phone":"+34 965 30 30 81",
    "sg:postcode":"03300",
    "sg:province":"Alicante",
    "wof:name":"Conesa Mo\u00f1ino Mercedes",
    "wof:placetype":"venue"
},
  "geometry": {"coordinates":[-0.9460989833,38.0866203308],"type":"Point"}
}