{
  "type": "Feature",
  "properties": {
    "iso:country":"ES",
    "sg:address":"Calle de Brisa, 4",
    "sg:city":"Madrid",
    "sg:orig_category":"Ense\u00d1anza, Formaci\u00d3n Profesional: Aprendizaje",
    "sg:phone":"+34 915 35 95 58",
    "sg:postcode":"28003",
    "sg:province":"Madrid",
    "wof:name":"Fundacion Taller De Solidaridad S.a.",
    "wof:placetype":"venue"
},
  "geometry": {"coordinates":[-3.7171576023,40.443862915],"type":"Point"}
}