{
  "type": "Feature",
  "properties": {
    "iso:country":"ES",
    "sg:address":"Corredoira, S/n",
    "sg:city":"S. Martin Casta\u00f1eda",
    "sg:orig_category":"Alquiler De Casas Y Habitaciones Amuebladas",
    "sg:phone":"+34 980 62 20 06",
    "sg:postcode":"49361",
    "sg:province":"Zamora",
    "wof:name":"Alonso Sotillo Maria Ines",
    "wof:placetype":"venue"
},
  "geometry": {"coordinates":[-5.7462787628,41.5033454895],"type":"Point"}
}