{
  "type": "Feature",
  "properties": {
    "addr:full":"Calle de Sudafrica, 121 Jerez De La Frontera C\u00e1diz 11408",
    "addr:housenumber":"121",
    "addr:postcode":"11408",
    "addr:street":"Calle De Sudafrica",
    "iso:country":"ES",
    "sg:address":"Calle de Sudafrica, 121",
    "sg:city":"Jerez De La Frontera",
    "sg:orig_category":"Promotores Constructores",
    "sg:phone":"+34 956 14 41 15",
    "sg:postcode":"11408",
    "sg:province":"C\u00e1diz",
    "wof:name":"Martin Casillas S.l.",
    "wof:placetype":"venue"
},
  "geometry": {"coordinates":[-6.1293869019,36.6491279602],"type":"Point"}
}