{
  "type": "Feature",
  "properties": {
    "iso:country":"ES",
    "sg:address":"Avda Caldas (das), 14",
    "sg:city":"Ourense",
    "sg:orig_category":"Florister\u00cdas",
    "sg:phone":"+34 988 21 91 63",
    "sg:postcode":"32001",
    "sg:province":"Ourense",
    "wof:name":"Paz Y Menchu Floristas S.l.",
    "wof:placetype":"venue"
},
  "geometry": {"coordinates":[-7.8701629639,42.3486709595],"type":"Point"}
}