{
  "type": "Feature",
  "properties": {
    "iso:country":"ES",
    "sg:address":"Rua Ines De Castro, 8",
    "sg:city":"Monforte De Lemos",
    "sg:orig_category":"Florister\u00cdas",
    "sg:phone":"+34 982 40 33 50",
    "sg:postcode":"27400",
    "sg:province":"Lugo",
    "wof:name":"Fernandez Pereiro Marina Carmen",
    "wof:placetype":"venue"
},
  "geometry": {"coordinates":[-7.5034179688,42.5307655334],"type":"Point"}
}