{
  "type": "Feature",
  "properties": {
    "addr:full":"Calle de Lorenzo Rivas, 34 Alcazar S. Juan Ciudad Real 13600",
    "addr:housenumber":"34",
    "addr:postcode":"13600",
    "addr:street":"Calle De Lorenzo Rivas;Alcazar S. Juan Ciudad Real",
    "iso:country":"ES",
    "sg:address":"Calle de Lorenzo Rivas, 34",
    "sg:city":"Alcazar S. Juan",
    "sg:classifiers":[
        {
            "category":"Personal",
            "subcategory":"Barber",
            "type":"Services"
        }
    ],
    "sg:phone":"+34 926 54 48 09",
    "sg:postcode":"13600",
    "sg:province":"Ciudad Real",
    "sg:tags":[
        "caballeros",
        "de",
        "peluqueros"
    ],
    "wof:name":"Moreno-opo Gomez-calcerrada Rafael",
    "wof:placetype":"venue"
},
  "geometry": {"coordinates":[-3.2173841,39.3897514343],"type":"Point"}
}