{
  "type": "Feature",
  "properties": {
    "iso:country":"ES",
    "sg:address":"Finca Cuevas Altas, S/n",
    "sg:city":"Villarrubia",
    "sg:orig_category":"\u00c1rboles Frutales",
    "sg:phone":"+34 957 45 86 86",
    "sg:postcode":"14710",
    "sg:province":"C\u00f3rdoba",
    "wof:name":"Viveros La Conchuela S.l.",
    "wof:placetype":"venue"
},
  "geometry": {"coordinates":[-4.9000496864,37.8542518616],"type":"Point"}
}