{
  "type": "Feature",
  "properties": {
    "iso:country":"ES",
    "sg:address":"Calle de Joaquin Turina, 7",
    "sg:city":"Brenes",
    "sg:orig_category":"Bordado, Marcado A Medida",
    "sg:phone":"+34 954 79 71 71",
    "sg:postcode":"41310",
    "sg:province":"Sevilla",
    "wof:name":"Rama Palomo Maria Jose",
    "wof:placetype":"venue"
},
  "geometry": {"coordinates":[-5.8733248711,37.5468101501],"type":"Point"}
}