{
  "type": "Feature",
  "properties": {
    "addr:full":"Calle de Tomas Murube, 9 Sevilla Sevilla 41007",
    "addr:housenumber":"9",
    "addr:postcode":"41007",
    "addr:street":"Calle De Tomas Murube",
    "iso:country":"ES",
    "sg:address":"Calle de Tomas Murube, 9",
    "sg:city":"Sevilla",
    "sg:orig_category":"Asesor\u00cda Fiscal Y Jur\u00cddica",
    "sg:phone":"+34 954 57 51 68",
    "sg:postcode":"41007",
    "sg:province":"Sevilla",
    "wof:name":"Fundacion Prolibertas",
    "wof:placetype":"venue"
},
  "geometry": {"coordinates":[-5.9679040909,37.3884544373],"type":"Point"}
}