{
  "type": "Feature",
  "properties": {
    "iso:country":"ES",
    "sg:address":"C/ Pascual Campos Garcia, 10",
    "sg:city":"Elche",
    "sg:orig_category":"Zapatos: Material, Suministros, Accesorios (fabricaci\u00d3n, Al Por Mayor)",
    "sg:phone":"+34 966 67 55 72",
    "sg:postcode":"03206",
    "sg:province":"Alicante",
    "wof:name":"Articas Componentes S.l.",
    "wof:placetype":"venue"
},
  "geometry": {"coordinates":[-0.7046036124,38.2761192322],"type":"Point"}
}