{
  "type": "Feature",
  "properties": {
    "addr:full":"Avda Cuba, 15 Badolatosa Sevilla 41570",
    "addr:housenumber":"15",
    "addr:postcode":"41570",
    "addr:street":"Avda Cuba",
    "iso:country":"ES",
    "sg:address":"Avda Cuba, 15",
    "sg:city":"Badolatosa",
    "sg:orig_category":"Centros De Coordinaci\u00d3n",
    "sg:phone":"+34 954 01 72 04",
    "sg:postcode":"41570",
    "sg:province":"Sevilla",
    "wof:name":"Asesoria Dorado S.l.",
    "wof:placetype":"venue"
},
  "geometry": {"coordinates":[-4.6720690727,37.3090248108],"type":"Point"}
}