{
  "type": "Feature",
  "properties": {
    "iso:country":"ES",
    "sg:address":"Avda Angeles (los), 41",
    "sg:city":"Loja",
    "sg:orig_category":"Abogados",
    "sg:phone":"+34 958 32 06 73",
    "sg:postcode":"18300",
    "sg:province":"Granada",
    "wof:name":"Mejias Tallon Jesus",
    "wof:placetype":"venue"
},
  "geometry": {"coordinates":[-4.1454071999,37.1643943787],"type":"Point"}
}