{
  "type": "Feature",
  "properties": {
    "addr:full":"Calle de Marcilla, S/n Tafalla Navarra 31300",
    "addr:housenumber":"s / n",
    "addr:postcode":"31300",
    "addr:street":"Calle De Marcilla",
    "iso:country":"ES",
    "sg:address":"Calle de Marcilla, S/n",
    "sg:city":"Tafalla",
    "sg:orig_category":"Molduras, Junquillos, Listones Y Molduras Perforadas",
    "sg:phone":"+34 948 70 19 03",
    "sg:postcode":"31300",
    "sg:province":"Navarra",
    "wof:name":"Ozcariz Arana Javier",
    "wof:placetype":"venue"
},
  "geometry": {"coordinates":[-1.678779006,42.5239105225],"type":"Point"}
}