{
  "type": "Feature",
  "properties": {
    "addr:full":"Calle de Luis Amigo, 20 Alacant Alicante 03009",
    "addr:housenumber":"20",
    "addr:postcode":"03009",
    "addr:street":"Calle De Luis Amigo",
    "iso:country":"ES",
    "sg:address":"Calle de Luis Amigo, 20",
    "sg:city":"Alacant",
    "sg:orig_category":"Droguer\u00cdas (al Por Menor)",
    "sg:phone":"+34 965 17 24 55",
    "sg:postcode":"03009",
    "sg:province":"Alicante",
    "wof:name":"Alvarez Moya Matilde",
    "wof:placetype":"venue"
},
  "geometry": {"coordinates":[-0.5043845177,38.3721122742],"type":"Point"}
}