{
  "type": "Feature",
  "properties": {
    "addr:full":"Avda Castilleja De La Cuesta, 16 Bollullos Mitacion Sevilla 41110",
    "addr:housenumber":"16",
    "addr:postcode":"41110",
    "addr:street":"Avda Castilleja De La Cuesta",
    "iso:country":"ES",
    "sg:address":"Avda Castilleja De La Cuesta, 16",
    "sg:city":"Bollullos Mitacion",
    "sg:orig_category":"Centros Empresariales",
    "sg:phone":"+34 955 60 15 45",
    "sg:postcode":"41110",
    "sg:province":"Sevilla",
    "wof:name":"Arpri G.c.a. S.l.",
    "wof:placetype":"venue"
},
  "geometry": {"coordinates":[-6.1455388069,37.35779953],"type":"Point"}
}