{
  "type": "Feature",
  "properties": {
    "iso:country":"ES",
    "sg:address":"Avda Navarra, S/n",
    "sg:city":"Irun",
    "sg:orig_category":"Textil",
    "sg:phone":"+34 943 62 90 66",
    "sg:postcode":"20300",
    "sg:province":"Guip\u00f9zcoa",
    "wof:name":"Arrupe Arandia Maria Soledad",
    "wof:placetype":"venue"
},
  "geometry": {"coordinates":[-1.8903882504,43.3105583191],"type":"Point"}
}