{
  "type": "Feature",
  "properties": {
    "addr:full":"Calle de Ciudad De Andujar, 12 Malaga M\u00e1laga 29006",
    "addr:housenumber":"12",
    "addr:postcode":"29006",
    "addr:street":"Calle De Ciudad De Andujar;Ma\u0301Laga",
    "iso:country":"ES",
    "sg:address":"Calle de Ciudad De Andujar, 12",
    "sg:city":"Malaga",
    "sg:orig_category":"Confecci\u00d3n (fabricaci\u00d3n, Al Por Mayor)",
    "sg:phone":"+34 952 33 89 92",
    "sg:postcode":"29006",
    "sg:province":"M\u00e1laga",
    "wof:name":"Torres Alcantara Salvador",
    "wof:placetype":"venue"
},
  "geometry": {"coordinates":[-4.4468431473,36.7104682922],"type":"Point"}
}