{
  "type": "Feature",
  "properties": {
    "addr:full":"Calle de Colon, 19 Olivenza Badajoz 06100",
    "addr:housenumber":"19",
    "addr:postcode":"06100",
    "addr:street":"Calle De Colon",
    "iso:country":"ES",
    "sg:address":"Calle de Colon, 19",
    "sg:city":"Olivenza",
    "sg:orig_category":"Abogados",
    "sg:phone":"+34 924 49 00 34",
    "sg:postcode":"06100",
    "sg:province":"Badajoz",
    "wof:name":"Asensio Rodriguez Maria Del Carmen",
    "wof:placetype":"venue"
},
  "geometry": {"coordinates":[-7.1025657654,38.6829376221],"type":"Point"}
}