{
  "type": "Feature",
  "properties": {
    "addr:full":"Calle de Cuatro Cantones, 2 Mayorga Valladolid 47680",
    "addr:housenumber":"2",
    "addr:postcode":"47680",
    "addr:street":"Calle De Cuatro Cantones",
    "iso:country":"ES",
    "sg:address":"Calle de Cuatro Cantones, 2",
    "sg:city":"Mayorga",
    "sg:orig_category":"Telas Y Sedas (al Por Menor)",
    "sg:phone":"+34 983 75 10 68",
    "sg:postcode":"47680",
    "sg:province":"Valladolid",
    "wof:name":"Fernandez Bernardo Fernando",
    "wof:placetype":"venue"
},
  "geometry": {"coordinates":[-5.2631735802,42.1666145325],"type":"Point"}
}