{
  "type": "Feature",
  "properties": {
    "iso:country":"ES",
    "sg:address":"Av Catalunya, 91",
    "sg:city":"Sant Joan De Palamos",
    "sg:orig_category":"Negocio De Materiales De Construcci\u00d3n",
    "sg:phone":"+34 972 31 22 50",
    "sg:postcode":"17230",
    "sg:province":"Girona",
    "wof:name":"T.g. Nova Arquitectura S.l.",
    "wof:placetype":"venue"
},
  "geometry": {"coordinates":[3.1219539642,41.8527870178],"type":"Point"}
}