{
  "type": "Feature",
  "properties": {
    "addr:full":"Carrer de Costa Brava, 113 Torreta Barcelona 08430",
    "addr:housenumber":"113",
    "addr:postcode":"08430",
    "addr:street":"Carrer De Costa Brava;Barcelona",
    "iso:country":"ES",
    "sg:address":"Carrer de Costa Brava, 113",
    "sg:city":"Torreta",
    "sg:orig_category":"Institutos De Belleza",
    "sg:phone":"+34 938 70 20 03",
    "sg:postcode":"08430",
    "sg:province":"Barcelona",
    "wof:name":"Sanchez Otero Maria",
    "wof:placetype":"venue"
},
  "geometry": {"coordinates":[2.3016400337,41.600063324],"type":"Point"}
}