{
  "type": "Feature",
  "properties": {
    "addr:full":"Calle de Elorri, 6 Getxo Vizcaya 48990",
    "addr:housenumber":"6",
    "addr:postcode":"48990",
    "addr:street":"Calle De Elorri",
    "iso:country":"ES",
    "sg:address":"Calle de Elorri, 6",
    "sg:city":"Getxo",
    "sg:orig_category":"Tapicer\u00cdas",
    "sg:phone":"+34 944 30 72 08",
    "sg:postcode":"48990",
    "sg:province":"Vizcaya",
    "wof:name":"Tapicerias Toral, S.l.",
    "wof:placetype":"venue"
},
  "geometry": {"coordinates":[-3.008605957,43.3539848328],"type":"Point"}
}