{
  "type": "Feature",
  "properties": {
    "addr:full":"Avda Novelista Vte Blasco Iba\u00d1ez, S/n Massalfassar Valencia 46560",
    "addr:housenumber":"s / n",
    "addr:postcode":"46560",
    "addr:street":"Avda Novelista Vte Blasco Iban\u0303Ez",
    "iso:country":"ES",
    "sg:address":"Avda Novelista Vte Blasco Iba\u00d1ez, S/n",
    "sg:city":"Massalfassar",
    "sg:orig_category":"Aceites Y Grasas Industriales (fabricaci\u00d3n, Al Por Mayor)",
    "sg:phone":"+34 961 40 02 34",
    "sg:postcode":"46560",
    "sg:province":"Valencia",
    "wof:name":"Reciclado De Residuos Alimentarios S.c.v",
    "wof:placetype":"venue"
},
  "geometry": {"coordinates":[-0.3273440003,39.556854248],"type":"Point"}
}