{
  "type": "Feature",
  "properties": {
    "iso:country":"ES",
    "sg:address":"Calle de Muro Bajo, 3",
    "sg:city":"Sanlucar De Barrameda",
    "sg:orig_category":"Discotecas Y Salas De Baile",
    "sg:phone":"+34 956 36 65 02",
    "sg:postcode":"11540",
    "sg:province":"C\u00e1diz",
    "wof:name":"Lara Cuevas Jose Joaquin",
    "wof:placetype":"venue"
},
  "geometry": {"coordinates":[-6.3545279503,36.7735939026],"type":"Point"}
}