{
  "type": "Feature",
  "properties": {
    "addr:full":"Calle de Cantabria (de), 6 Jaen Ja\u00e9n 23008",
    "addr:housenumber":"6;jae\u0301n",
    "addr:postcode":"23008",
    "addr:street":"Calle De Cantabria De",
    "iso:country":"ES",
    "sg:address":"Calle de Cantabria (de), 6",
    "sg:city":"Jaen",
    "sg:orig_category":"Asesor\u00cda Sobre Comunicaci\u00d3n De Empresas",
    "sg:phone":"+34 953 27 34 67",
    "sg:postcode":"23008",
    "sg:province":"Ja\u00e9n",
    "wof:name":"Asesores Empresariales Garcia Romero S.l.",
    "wof:placetype":"venue"
},
  "geometry": {"coordinates":[-3.7928454876,37.7836532593],"type":"Point"}
}