{
  "type": "Feature",
  "properties": {
    "addr:full":"Calle de Ancha, 54 Punta Umbria Huelva 21100",
    "addr:housenumber":"54",
    "addr:postcode":"21100",
    "addr:street":"Calle De Ancha",
    "iso:country":"ES",
    "sg:address":"Calle de Ancha, 54",
    "sg:city":"Punta Umbria",
    "sg:orig_category":"Ropa Para Se\u00d1oras Y Caballeros (al Por Menor)",
    "sg:phone":"+34 959 31 06 90",
    "sg:postcode":"21100",
    "sg:province":"Huelva",
    "wof:name":"Vaz Y Gon S.l.",
    "wof:placetype":"venue"
},
  "geometry": {"coordinates":[-6.9602890015,37.1814193726],"type":"Point"}
}