{
  "type": "Feature",
  "properties": {
    "addr:full":"Plaz Constitucion, 10 Fuengirola M\u00e1laga 29640",
    "addr:housenumber":"10",
    "addr:postcode":"29640",
    "addr:street":"Constitucion;Ma\u0301Laga",
    "iso:country":"ES",
    "sg:address":"Plaz Constitucion, 10",
    "sg:city":"Fuengirola",
    "sg:orig_category":"Abogados",
    "sg:phone":"+34 952 47 39 96",
    "sg:postcode":"29640",
    "sg:province":"M\u00e1laga",
    "wof:name":"Garcia Gamez Joaquin",
    "wof:placetype":"venue"
},
  "geometry": {"coordinates":[-4.6218910217,36.5384902954],"type":"Point"}
}