{
  "type": "Feature",
  "properties": {
    "addr:full":"Ctra. Talavera, S/n Puente Arzobispo Toledo 45570",
    "addr:housenumber":"s / n",
    "addr:postcode":"45570",
    "addr:street":"Ctra. Talavera",
    "iso:country":"ES",
    "sg:address":"Ctra. Talavera, S/n",
    "sg:city":"Puente Arzobispo",
    "sg:orig_category":"Empresas De Carpinter\u00cda Met\u00c1lica",
    "sg:phone":"+34 925 43 68 18",
    "sg:postcode":"45570",
    "sg:province":"Toledo",
    "wof:name":"Barquin Bodas Angel",
    "wof:placetype":"venue"
},
  "geometry": {"coordinates":[-5.172039032,39.8030891418],"type":"Point"}
}