{
  "type": "Feature",
  "properties": {
    "addr:full":"Calle de Casta\u00d1os, 10 Alacant Alicante 03001",
    "addr:housenumber":"10",
    "addr:postcode":"03001",
    "addr:street":"Calle De Castan\u0303Os",
    "iso:country":"ES",
    "sg:address":"Calle de Casta\u00d1os, 10",
    "sg:city":"Alacant",
    "sg:orig_category":"Electrodom\u00c9sticos (al Por Menor)",
    "sg:phone":"+34 965 20 96 47",
    "sg:postcode":"03001",
    "sg:province":"Alicante",
    "wof:name":"Hegora\u00f1o S.l.",
    "wof:placetype":"venue"
},
  "geometry": {"coordinates":[-0.4850183129,38.3444252014],"type":"Point"}
}