{
  "type": "Feature",
  "properties": {
    "iso:country":"ES",
    "sg:address":"Pg Ferrocarrils Catalans, 63",
    "sg:city":"Cornella Llobregat",
    "sg:orig_category":"Fabricaci\u00d3n De Distribuidores Autom\u00c1ticos",
    "sg:phone":"+34 933 77 39 93",
    "sg:postcode":"08940",
    "sg:province":"Barcelona",
    "wof:name":"Gracia Canovas Juan Antonio",
    "wof:placetype":"venue"
},
  "geometry": {"coordinates":[2.0734839439,41.3516807556],"type":"Point"}
}