{
  "type": "Feature",
  "properties": {
    "addr:full":"Ctra. B-motril, Km. 0040,2 La Yuca Ja\u00e9n 23001",
    "addr:postcode":"23001",
    "addr:street":"Ctra. B-Motril Km. 0040,2 La;Jae\u0301N",
    "iso:country":"ES",
    "sg:address":"Ctra. B-motril, Km. 0040,2",
    "sg:city":"La Yuca",
    "sg:orig_category":"Asociaciones Humanitarias, De Cooperaci\u00d3n, De Acci\u00d3n Social",
    "sg:phone":"+34 953 32 22 50",
    "sg:postcode":"23001",
    "sg:province":"Ja\u00e9n",
    "wof:name":"Asociacion Provincial Pro Minusvalidos Psiquicos Jaen-aprompsi",
    "wof:placetype":"venue"
},
  "geometry": {"coordinates":[-3.7895176411,37.7657394409],"type":"Point"}
}