{
  "type": "Feature",
  "properties": {
    "addr:full":"Calle de Jose Zorrilla, 118 Segovia Segovia 40002",
    "addr:housenumber":"118",
    "addr:postcode":"40002",
    "addr:street":"Calle De Jose Zorrilla",
    "iso:country":"ES",
    "sg:address":"Calle de Jose Zorrilla, 118",
    "sg:city":"Segovia",
    "sg:orig_category":"Loter\u00cda Y T\u00d3mbola",
    "sg:phone":"+34 921 43 80 45",
    "sg:postcode":"40002",
    "sg:province":"Segovia",
    "wof:name":"Del Barrio Martin Jose Maria",
    "wof:placetype":"venue"
},
  "geometry": {"coordinates":[-4.1135721207,40.9374771118],"type":"Point"}
}