{
  "type": "Feature",
  "properties": {
    "iso:country":"ES",
    "sg:address":"Av Catalunya, 325",
    "sg:city":"Aldea",
    "sg:orig_category":"Molduras, Junquillos, Listones Y Molduras Perforadas",
    "sg:phone":"+34 977 45 11 71",
    "sg:postcode":"43896",
    "sg:province":"Tarragona",
    "wof:name":"Abril Ferrer Jordi",
    "wof:placetype":"venue"
},
  "geometry": {"coordinates":[0.6175916195,40.7449417114],"type":"Point"}
}