{
  "type": "Feature",
  "properties": {
    "iso:country":"ES",
    "sg:address":"Carrer de Mila I Fontanals, 106",
    "sg:city":"Santa Coloma De Gramenet",
    "sg:orig_category":"Molduras, Junquillos, Listones Y Molduras Perforadas",
    "sg:phone":"+34 933 91 53 92",
    "sg:postcode":"08922",
    "sg:province":"Barcelona",
    "wof:name":"Ruiz Lopez Francisco Javier",
    "wof:placetype":"venue"
},
  "geometry": {"coordinates":[2.2177870274,41.4503326416],"type":"Point"}
}