{
  "type": "Feature",
  "properties": {
    "iso:country":"ES",
    "sg:address":"Calle de Cruces, 61",
    "sg:city":"Villarrobledo",
    "sg:orig_category":"M\u00c1rmoles, Granitos Y Piedras Naturales",
    "sg:phone":"+34 967 14 21 12",
    "sg:postcode":"02600",
    "sg:province":"Albacete",
    "wof:name":"Caballero Castellanos Juan",
    "wof:placetype":"venue"
},
  "geometry": {"coordinates":[-2.6113789082,39.26953125],"type":"Point"}
}