{
  "type": "Feature",
  "properties": {
    "addr:full":"Ctra Del Palmar, Km. 0049,0 Mazarron Murcia 30870",
    "addr:postcode":"30870",
    "addr:street":"Ctra Del Palmar;0049,0",
    "iso:country":"ES",
    "sg:address":"Ctra Del Palmar, Km. 0049,0",
    "sg:city":"Mazarron",
    "sg:orig_category":"Hormigonados",
    "sg:phone":"+34 968 59 25 11",
    "sg:postcode":"30870",
    "sg:province":"Murcia",
    "sg:website":"www.hortisa.com",
    "wof:name":"Hormigones Plazas Y Saura S. A.",
    "wof:placetype":"venue"
},
  "geometry": {"coordinates":[-1.31378901,37.598865509],"type":"Point"}
}