{
  "type": "Feature",
  "properties": {
    "addr:full":"Calle de Bocinegro, 13 Corralejo Las Palmas 35660",
    "addr:housenumber":"13",
    "addr:postcode":"35660",
    "addr:street":"Calle De Bocinegro",
    "iso:country":"ES",
    "sg:address":"Calle de Bocinegro, 13",
    "sg:city":"Corralejo",
    "sg:orig_category":"Empresas De Carpinter\u00cda Met\u00c1lica",
    "sg:phone":"+34 928 53 56 74",
    "sg:postcode":"35660",
    "sg:province":"Las Palmas",
    "wof:name":"Construcciones Metalicas S.l.",
    "wof:placetype":"venue"
},
  "geometry": {"coordinates":[-13.8705692291,28.7394790649],"type":"Point"}
}