{
  "type": "Feature",
  "properties": {
    "addr:full":"Calle de Alcalde Sanz Noguer, 6 Cordoba C\u00f3rdoba 14005",
    "addr:housenumber":"6",
    "addr:postcode":"14005",
    "addr:street":"Calle De Alcalde Sanz Noguer;Co\u0301Rdoba",
    "iso:country":"ES",
    "sg:address":"Calle de Alcalde Sanz Noguer, 6",
    "sg:city":"Cordoba",
    "sg:orig_category":"Productos Fitosanitarios (negocio, Aplicaci\u00d3n)",
    "sg:phone":"+34 957 41 38 89",
    "sg:postcode":"14005",
    "sg:province":"C\u00f3rdoba",
    "wof:name":"Fitosanitarios Torralbo Hnos S.l.",
    "wof:placetype":"venue"
},
  "geometry": {"coordinates":[-4.7911133766,37.8847084045],"type":"Point"}
}