{
  "type": "Feature",
  "properties": {
    "addr:full":"Calle de Miguel Villanueva, 2 Logro\u00f1o La Rioja 26001",
    "addr:housenumber":"2",
    "addr:postcode":"26001",
    "addr:street":"Calle De Miguel Villanueva;Rioja",
    "iso:country":"ES",
    "sg:address":"Calle de Miguel Villanueva, 2",
    "sg:city":"Logro\u00f1o",
    "sg:orig_category":"Asesor\u00cda Sobre Comunicaci\u00d3n De Empresas",
    "sg:phone":"+34 941 26 34 59",
    "sg:postcode":"26001",
    "sg:province":"La Rioja",
    "wof:name":"Santamaria Rubio Francisco Javier",
    "wof:placetype":"venue"
},
  "geometry": {"coordinates":[-2.4461929798,42.4640235901],"type":"Point"}
}