{
  "type": "Feature",
  "properties": {
    "iso:country":"ES",
    "sg:address":"Calle de Felix Valverde Lillo, 21",
    "sg:city":"Merida",
    "sg:orig_category":"Peluqueros: De Se\u00d1oras",
    "sg:phone":"+34 924 31 43 03",
    "sg:postcode":"06800",
    "sg:province":"Badajoz",
    "wof:name":"Aza Barrero Faustina",
    "wof:placetype":"venue"
},
  "geometry": {"coordinates":[-6.3444199562,38.9181060791],"type":"Point"}
}