{
  "type": "Feature",
  "properties": {
    "iso:country":"ES",
    "sg:address":"Calle de Peligros, 2",
    "sg:city":"Ausejo",
    "sg:orig_category":"Asociaciones, Organismos Culturales Y Socioeducativos",
    "sg:phone":"+34 941 43 02 90",
    "sg:postcode":"26513",
    "sg:province":"La Rioja",
    "wof:name":"Sociedad De Cazadores De Ausejo",
    "wof:placetype":"venue"
},
  "geometry": {"coordinates":[-2.1706988811,42.3446884155],"type":"Point"}
}