{
  "type": "Feature",
  "properties": {
    "iso:country":"ES",
    "sg:address":"Carrer de Marti L'huma, 2",
    "sg:city":"Mollet Valles",
    "sg:orig_category":"Frutas Y Legumbres Frescas (al Por Mayor)",
    "sg:phone":"+34 935 93 38 47",
    "sg:postcode":"08100",
    "sg:province":"Barcelona",
    "wof:name":"Luxa Fruits S.l.",
    "wof:placetype":"venue"
},
  "geometry": {"coordinates":[2.2088069916,41.5326957703],"type":"Point"}
}