{
  "type": "Feature",
  "properties": {
    "addr:full":"Pg Catalunya, 39 Torroella Montgri Girona 17257",
    "addr:housenumber":"39",
    "addr:postcode":"17257",
    "addr:street":"Pg Catalunya",
    "iso:country":"ES",
    "sg:address":"Pg Catalunya, 39",
    "sg:city":"Torroella Montgri",
    "sg:orig_category":"Asesor\u00cda Fiscal Y Jur\u00cddica",
    "sg:phone":"+34 972 76 06 23",
    "sg:postcode":"17257",
    "sg:province":"Girona",
    "wof:name":"Gestio Emporda S.l.",
    "wof:placetype":"venue"
},
  "geometry": {"coordinates":[3.12768507,42.0403404236],"type":"Point"}
}