{
  "type": "Feature",
  "properties": {
    "iso:country":"ES",
    "sg:address":"Calle de San Gregorio (de), 30",
    "sg:city":"Galapagar",
    "sg:orig_category":"Administradores De Bienes Y Delegados De Comunidades De Propietarios",
    "sg:phone":"+34 918 58 41 03",
    "sg:postcode":"28260",
    "sg:province":"Madrid",
    "wof:name":"Rodriguez Casa\u00f1ez Ruth",
    "wof:placetype":"venue"
},
  "geometry": {"coordinates":[-4.0025129318,40.5796890259],"type":"Point"}
}