{
  "type": "Feature",
  "properties": {
    "iso:country":"ES",
    "sg:address":"Calle de Moros, 5",
    "sg:city":"Escurial Sierra",
    "sg:orig_category":"Asilos De Ancianos. Centros Privados",
    "sg:phone":"+34 923 44 20 86",
    "sg:postcode":"37762",
    "sg:province":"Salamanca",
    "wof:name":"Villas Residenciales S.l.",
    "wof:placetype":"venue"
},
  "geometry": {"coordinates":[-5.957531929,40.6175804138],"type":"Point"}
}