{
  "type": "Feature",
  "properties": {
    "addr:full":"Calle de Dos Hermanas, 45 Camas Sevilla 41900",
    "addr:housenumber":"45",
    "addr:postcode":"41900",
    "addr:street":"Calle De Dos Hermanas",
    "iso:country":"ES",
    "sg:address":"Calle de Dos Hermanas, 45",
    "sg:city":"Camas",
    "sg:orig_category":"Estudios, Instalaci\u00d3n De Climatizaci\u00d3n",
    "sg:phone":"+34 955 98 19 81",
    "sg:postcode":"41900",
    "sg:province":"Sevilla",
    "wof:name":"Refrigeracion Contreras S. L.",
    "wof:placetype":"venue"
},
  "geometry": {"coordinates":[-6.0324344635,37.3870391846],"type":"Point"}
}