{
  "type": "Feature",
  "properties": {
    "addr:full":"Calle de Alvaro De Albornoz, 35 Gijon Asturias 33207",
    "addr:housenumber":"35",
    "addr:postcode":"33207",
    "addr:street":"Calle De Alvaro De Albornoz",
    "iso:country":"ES",
    "sg:address":"Calle de Alvaro De Albornoz, 35",
    "sg:city":"Gijon",
    "sg:orig_category":"Alquiler De Material Y De Programas Audiovisuales",
    "sg:phone":"+34 985 35 49 69",
    "sg:postcode":"33207",
    "sg:province":"Asturias",
    "sg:website":"www.pronorte.es",
    "wof:name":"Pronorte Sonido S.l.",
    "wof:placetype":"venue"
},
  "geometry": {"coordinates":[-5.6682815552,43.5357055664],"type":"Point"}
}