{
  "type": "Feature",
  "properties": {
    "addr:full":"Ctra. Suroeste, S/n Allo Navarra 31262",
    "addr:housenumber":"s / n",
    "addr:postcode":"31262",
    "addr:street":"Ctra. Suroeste",
    "iso:country":"ES",
    "sg:address":"Ctra. Suroeste, S/n",
    "sg:city":"Allo",
    "sg:orig_category":"Bosques (trabajos, Asesor\u00cda, Gesti\u00d3n)",
    "sg:phone":"+34 948 52 30 65",
    "sg:postcode":"31262",
    "sg:province":"Navarra",
    "wof:name":"Opnatel",
    "wof:placetype":"venue"
},
  "geometry": {"coordinates":[-2.0217089653,42.5686645508],"type":"Point"}
}