{
  "type": "Feature",
  "properties": {
    "iso:country":"ES",
    "sg:address":"Ronda Norte, S/n",
    "sg:city":"Valladolid",
    "sg:orig_category":"Frutas Y Legumbres Frescas (al Por Mayor)",
    "sg:phone":"+34 983 38 01 34",
    "sg:postcode":"47009",
    "sg:province":"Valladolid",
    "sg:website":"www.angelvagagrupofernandez.es",
    "wof:name":"Angel Vaca S.l.",
    "wof:placetype":"venue"
},
  "geometry": {"coordinates":[-4.7174787521,41.6750717163],"type":"Point"}
}