{
  "type": "Feature",
  "properties": {
    "addr:full":"Carrer de Diputacio, 235 Barcelona Barcelona 08007",
    "addr:housenumber":"235",
    "addr:postcode":"08007",
    "addr:street":"Carrer De Diputacio",
    "iso:country":"ES",
    "sg:address":"Carrer de Diputacio, 235",
    "sg:city":"Barcelona",
    "sg:orig_category":"Sociedades, Compa\u00d1\u00cdas Aseguradoras",
    "sg:phone":"+34 934 87 85 52",
    "sg:postcode":"08007",
    "sg:province":"Barcelona",
    "wof:name":"Ingenieria Y Planificacion S.l.",
    "wof:placetype":"venue"
},
  "geometry": {"coordinates":[2.1643049717,41.3885269165],"type":"Point"}
}