{
  "type": "Feature",
  "properties": {
    "iso:country":"ES",
    "sg:address":"Avda Rafael Alberti, 53",
    "sg:city":"Madrid",
    "sg:orig_category":"Ropa Para Se\u00d1oras Y Caballeros (al Por Menor)",
    "sg:phone":"+34 917 78 56 54",
    "sg:postcode":"28038",
    "sg:province":"Madrid",
    "wof:name":"Gomez Gonzalez Joaquin",
    "wof:placetype":"venue"
},
  "geometry": {"coordinates":[-3.6447029114,40.382598877],"type":"Point"}
}