{
  "type": "Feature",
  "properties": {
    "iso:country":"ES",
    "sg:address":"Carrer de Macarnau, 7",
    "sg:city":"Olot",
    "sg:orig_category":"Artesan\u00cda",
    "sg:phone":"+34 972 26 95 75",
    "sg:postcode":"17800",
    "sg:province":"Girona",
    "wof:name":"Comercial Stylart S.a.",
    "wof:placetype":"venue"
},
  "geometry": {"coordinates":[2.4879539013,42.1830940247],"type":"Point"}
}