{
  "type": "Feature",
  "properties": {
    "addr:full":"Calle de Ruiz Blaser, 4 Malaga M\u00e1laga 29016",
    "addr:housenumber":"4",
    "addr:postcode":"29016",
    "addr:street":"Calle De Ruiz Blaser;Ma\u0301Laga",
    "iso:country":"ES",
    "sg:address":"Calle de Ruiz Blaser, 4",
    "sg:city":"Malaga",
    "sg:classifiers":[
        {
            "category":"Banks & Credit Unions",
            "subcategory":"Bureau De Change",
            "type":"Services"
        }
    ],
    "sg:phone":"+34 952 21 77 94",
    "sg:postcode":"29016",
    "sg:province":"M\u00e1laga",
    "sg:tags":[
        "organismos",
        "control"
    ],
    "wof:name":"Oliconttol Espa\u00f1a S.l.",
    "wof:placetype":"venue"
},
  "geometry": {"coordinates":[-4.4085969925,36.719417572],"type":"Point"}
}