{
  "type": "Feature",
  "properties": {
    "iso:country":"ES",
    "sg:address":"Av Generalitat (de La), 22",
    "sg:city":"Tortosa",
    "sg:orig_category":"Centros Empresariales",
    "sg:phone":"+34 977 44 87 65",
    "sg:postcode":"43500",
    "sg:province":"Tarragona",
    "wof:name":"Verpla Seguretat S.l.",
    "wof:placetype":"venue"
},
  "geometry": {"coordinates":[0.5203769803,40.8117141724],"type":"Point"}
}