{
  "type": "Feature",
  "properties": {
    "iso:country":"ES",
    "sg:address":"Calle de San Jose, 11",
    "sg:city":"Yecla",
    "sg:orig_category":"Ropa Para Ni\u00d1os (al Por Menor)",
    "sg:phone":"+34 968 75 17 40",
    "sg:postcode":"30510",
    "sg:province":"Murcia",
    "wof:name":"Molina Mu\u00f1oz Maria Dolores",
    "wof:placetype":"venue"
},
  "geometry": {"coordinates":[-1.1143219471,38.6140708923],"type":"Point"}
}