{
  "type": "Feature",
  "properties": {
    "addr:full":"Calle de Antonio Zapata, 12 Madrid Madrid 28002",
    "addr:housenumber":"12",
    "addr:postcode":"madrid;28002",
    "addr:street":"Calle De Antonio Zapata",
    "iso:country":"ES",
    "sg:address":"Calle de Antonio Zapata, 12",
    "sg:city":"Madrid",
    "sg:orig_category":"Comercio De Piezas De Recambio Y De Accesorios De Veh\u00cdculos, Veh\u00cdculos Industriales",
    "sg:phone":"+34 915 19 07 07",
    "sg:postcode":"28002",
    "sg:province":"Madrid",
    "wof:name":"Perez Cabrejas Juan Jose",
    "wof:placetype":"venue"
},
  "geometry": {"coordinates":[-3.6707828045,40.4453964233],"type":"Point"}
}