{
  "type": "Feature",
  "properties": {
    "iso:country":"ES",
    "sg:address":"P Sarasate, 18",
    "sg:city":"Iru\u00f1a",
    "sg:orig_category":"Abogados",
    "sg:phone":"+34 948 22 82 95",
    "sg:postcode":"31001",
    "sg:province":"Navarra",
    "wof:name":"Araluce Letamendia Javier Maria",
    "wof:placetype":"venue"
},
  "geometry": {"coordinates":[-1.6444653273,42.8156738281],"type":"Point"}
}