{
  "type": "Feature",
  "properties": {
    "iso:country":"ES",
    "sg:address":"Sarries, S/n",
    "sg:city":"Iru\u00f1a",
    "sg:orig_category":"Mataderos De Poller\u00cda",
    "sg:phone":"+34 948 12 04 38",
    "sg:postcode":"31014",
    "sg:province":"Navarra",
    "wof:name":"Granja Esparza S. L.",
    "wof:placetype":"venue"
},
  "geometry": {"coordinates":[-1.6518511772,42.82264328],"type":"Point"}
}