{
  "type": "Feature",
  "properties": {
    "iso:country":"ES",
    "sg:address":"Calle de Carmen, 17",
    "sg:city":"Albacete",
    "sg:orig_category":"Seguridad En El Trabajo Y Prevenci\u00d3n De Riesgos Laborales",
    "sg:phone":"+34 967 19 16 94",
    "sg:postcode":"02005",
    "sg:province":"Albacete",
    "sg:website":"www.albasalud.com",
    "wof:name":"Albasalud Sll",
    "wof:placetype":"venue"
},
  "geometry": {"coordinates":[-1.855670929,38.9981155396],"type":"Point"}
}