{
  "type": "Feature",
  "properties": {
    "iso:country":"ES",
    "sg:address":"Carrer de Vallparda, 9",
    "sg:city":"Hospitalet Llobregat",
    "sg:orig_category":"Asesor\u00cda Fiscal Y Jur\u00cddica",
    "sg:phone":"+34 934 40 59 62",
    "sg:postcode":"08904",
    "sg:province":"Barcelona",
    "wof:name":"Vidal De Torres Guerrero Daniel",
    "wof:placetype":"venue"
},
  "geometry": {"coordinates":[2.1157250404,41.374332428],"type":"Point"}
}