{
  "type": "Feature",
  "properties": {
    "addr:full":"Calle de Embalse Del Luna, 12 Santa Maria Del Paramo Le\u00f3n 24240",
    "addr:housenumber":"12",
    "addr:postcode":"24240",
    "addr:street":"Calle De Embalse Del Luna",
    "iso:country":"ES",
    "sg:address":"Calle de Embalse Del Luna, 12",
    "sg:city":"Santa Maria Del Paramo",
    "sg:orig_category":"Empresas De Carpinter\u00cda De Madera",
    "sg:phone":"+34 987 35 07 64",
    "sg:postcode":"24240",
    "sg:province":"Le\u00f3n",
    "wof:name":"Vazquez Castellanos Francisco",
    "wof:placetype":"venue"
},
  "geometry": {"coordinates":[-5.7423758507,42.3574638367],"type":"Point"}
}