{
  "type": "Feature",
  "properties": {
    "iso:country":"ES",
    "sg:address":"Avda Arlanzon, 35",
    "sg:city":"Burgos",
    "sg:orig_category":"Doctores En Medicina",
    "sg:phone":"+34 947 20 20 19",
    "sg:postcode":"09004",
    "sg:province":"Burgos",
    "wof:name":"Arriba Casado Eugenio De",
    "wof:placetype":"venue"
},
  "geometry": {"coordinates":[-3.6883404255,42.3426361084],"type":"Point"}
}