{
  "type": "Feature",
  "properties": {
    "addr:full":"Parque Corredor, S/n Torrejon Ardoz Madrid 28850",
    "addr:postcode":"28850",
    "addr:street":"S / N",
    "iso:country":"ES",
    "sg:address":"Parque Corredor, S/n",
    "sg:city":"Torrejon Ardoz",
    "sg:orig_category":"Ropa Para Se\u00d1oras (al Por Menor)",
    "sg:phone":"+34 916 56 81 16",
    "sg:postcode":"28850",
    "sg:province":"Madrid",
    "sg:website":"www.mango.com",
    "wof:name":"Punto Fa S.l.",
    "wof:placetype":"venue"
},
  "geometry": {"coordinates":[-3.4763290882,40.4592514038],"type":"Point"}
}