{
  "type": "Feature",
  "properties": {
    "addr:full":"Carrer de Muntaner, 102 Barcelona Barcelona 08036",
    "addr:housenumber":"102",
    "addr:postcode":"08036",
    "addr:street":"Carrer De Muntaner",
    "iso:country":"ES",
    "sg:address":"Carrer de Muntaner, 102",
    "sg:city":"Barcelona",
    "sg:classifiers":[
        {
            "category":"Arts & Performance",
            "subcategory":"Art Gallery",
            "type":"Entertainment"
        }
    ],
    "sg:phone":"+34 934 53 49 20",
    "sg:postcode":"08036",
    "sg:province":"Barcelona",
    "sg:tags":[
        "arte",
        "de",
        "galer\u00cdas"
    ],
    "wof:name":"Bonet Rosich Pedro",
    "wof:placetype":"venue"
},
  "geometry": {"coordinates":[2.1568410397,41.3887557983],"type":"Point"}
}