{
  "type": "Feature",
  "properties": {
    "iso:country":"ES",
    "sg:address":"Cmno Puebla (de La), 40",
    "sg:city":"Villamayor",
    "sg:orig_category":"Obras Y Organismos Sociales",
    "sg:phone":"+34 976 58 94 62",
    "sg:postcode":"50162",
    "sg:province":"Zaragoza",
    "wof:name":"Fundacion Virgen Del Pueyo",
    "wof:placetype":"venue"
},
  "geometry": {"coordinates":[-0.7721989751,41.6848487854],"type":"Point"}
}