{
  "type": "Feature",
  "properties": {
    "addr:full":"C/ Doctor Piguillem, 3 Puigcerda Girona 17520",
    "addr:housenumber":"3",
    "addr:postcode":"17520",
    "addr:street":"C / Doctor Piguillem",
    "iso:country":"ES",
    "sg:address":"C/ Doctor Piguillem, 3",
    "sg:city":"Puigcerda",
    "sg:orig_category":"Peluqueros: De Se\u00d1oras",
    "sg:phone":"+34 972 88 07 81",
    "sg:postcode":"17520",
    "sg:province":"Girona",
    "wof:name":"Mora Hernandez Encarnita",
    "wof:placetype":"venue"
},
  "geometry": {"coordinates":[1.9266170263,42.4345054626],"type":"Point"}
}