{
  "type": "Feature",
  "properties": {
    "iso:country":"ES",
    "sg:address":"Pl Monasterio Iranzu, 5",
    "sg:city":"Iru\u00f1a",
    "sg:orig_category":"Quincaller\u00cda (al Por Menor)",
    "sg:phone":"+34 948 17 84 03",
    "sg:postcode":"31011",
    "sg:province":"Navarra",
    "wof:name":"La Ferretera Navarra S.l.",
    "wof:placetype":"venue"
},
  "geometry": {"coordinates":[-1.6622459888,42.8157501221],"type":"Point"}
}