{
  "type": "Feature",
  "properties": {
    "iso:country":"ES",
    "sg:address":"Av. Parada Seca, S/n",
    "sg:city":"Villafranca Bierzo",
    "sg:orig_category":"Centros Pms (psico",
    "sg:phone":"+34 987 54 26 54",
    "sg:postcode":"24500",
    "sg:province":"Le\u00f3n",
    "wof:name":"Servicio De Orientacion Escolar Y Vocacional",
    "wof:placetype":"venue"
},
  "geometry": {"coordinates":[-6.8031439781,42.6110343933],"type":"Point"}
}