{
  "type": "Feature",
  "properties": {
    "addr:full":"Plaz Doctor Laguna, 11 Madrid Madrid 28009",
    "addr:housenumber":"11",
    "addr:postcode":"madrid;28009",
    "addr:street":"Doctor Laguna",
    "iso:country":"ES",
    "sg:address":"Plaz Doctor Laguna, 11",
    "sg:city":"Madrid",
    "sg:orig_category":"Tintes (fabricaci\u00d3n, Al Por Mayor)",
    "sg:phone":"+34 915 04 57 35",
    "sg:postcode":"28009",
    "sg:province":"Madrid",
    "wof:name":"Codemaxre S.l.",
    "wof:placetype":"venue"
},
  "geometry": {"coordinates":[-3.6714410782,40.4153022766],"type":"Point"}
}