{
  "type": "Feature",
  "properties": {
    "iso:country":"ES",
    "sg:address":"Rbla Carmel, 106",
    "sg:city":"Barcelona",
    "sg:classifiers":[
        {
            "category":"Personal",
            "subcategory":"Barber",
            "type":"Services"
        }
    ],
    "sg:phone":"+34 934 20 98 48",
    "sg:postcode":"08032",
    "sg:province":"Barcelona",
    "sg:tags":[
        "caballeros",
        "de",
        "peluqueros"
    ],
    "wof:name":"Centro De Peluqueria Y Belleza Alpe S.l.",
    "wof:placetype":"venue"
},
  "geometry": {"coordinates":[2.1582429409,41.4219665527],"type":"Point"}
}