{
  "type": "Feature",
  "properties": {
    "addr:full":"Avda Luis Rodriguez De Miguel, 17 Toro Zamora 49800",
    "addr:housenumber":"17",
    "addr:postcode":"49800",
    "addr:street":"Avda Luis Rodriguez De Miguel",
    "iso:country":"ES",
    "sg:address":"Avda Luis Rodriguez De Miguel, 17",
    "sg:city":"Toro",
    "sg:orig_category":"Negocio De Materiales De Construcci\u00d3n",
    "sg:phone":"+34 980 69 01 96",
    "sg:postcode":"49800",
    "sg:province":"Zamora",
    "wof:name":"Garvisa Decor-interiores S.l.",
    "wof:placetype":"venue"
},
  "geometry": {"coordinates":[-5.3867702484,41.5236282349],"type":"Point"}
}