{
  "type": "Feature",
  "properties": {
    "addr:full":"Calle de Parra (la), 3 Jaen Ja\u00e9n 23003",
    "addr:housenumber":"3;jae\u0301n",
    "addr:postcode":"23003",
    "addr:street":"Calle De Parra La",
    "iso:country":"ES",
    "sg:address":"Calle de Parra (la), 3",
    "sg:city":"Jaen",
    "sg:orig_category":"Bisuter\u00cda, Joyer\u00cda, Relojer\u00cda (al Por Menor)",
    "sg:phone":"+34 953 23 08 88",
    "sg:postcode":"23003",
    "sg:province":"Ja\u00e9n",
    "wof:name":"Calet Estepa Marcelino",
    "wof:placetype":"venue"
},
  "geometry": {"coordinates":[-3.7269899845,37.7898101807],"type":"Point"}
}