{
  "type": "Feature",
  "properties": {
    "iso:country":"ES",
    "sg:address":"Calle de Perales, 29",
    "sg:city":"Pinto",
    "sg:orig_category":"Paletas",
    "sg:phone":"+34 916 92 08 40",
    "sg:postcode":"28320",
    "sg:province":"Madrid",
    "wof:name":"Mebe Industrial S.l.",
    "wof:placetype":"venue"
},
  "geometry": {"coordinates":[-3.6967790127,40.2462768555],"type":"Point"}
}