{
  "type": "Feature",
  "properties": {
    "addr:full":"Bard Peraltas (los), S/n Peraltas Almer\u00eda 04660",
    "addr:postcode":"04660",
    "addr:street":"Los S / N Peraltas Almeri\u0301A",
    "iso:country":"ES",
    "sg:address":"Bard Peraltas (los), S/n",
    "sg:city":"Peraltas",
    "sg:orig_category":"Grabados Y Decoraci\u00d3n De Metales",
    "sg:phone":"+34 950 16 33 46",
    "sg:postcode":"04660",
    "sg:province":"Almer\u00eda",
    "wof:name":"Asociacion Alectoris Rufa",
    "wof:placetype":"venue"
},
  "geometry": {"coordinates":[-2.4679217339,36.8401641846],"type":"Point"}
}