{
  "type": "Feature",
  "properties": {
    "addr:full":"Carrer de Francesc Macia, 80 S. Boi Llobregat Barcelona 08830",
    "addr:housenumber":"80",
    "addr:postcode":"08830",
    "addr:street":"Carrer De Francesc Macia",
    "iso:country":"ES",
    "sg:address":"Carrer de Francesc Macia, 80",
    "sg:city":"S. Boi Llobregat",
    "sg:orig_category":"Cajas De Ahorro",
    "sg:phone":"+34 936 52 17 05",
    "sg:postcode":"08830",
    "sg:province":"Barcelona",
    "wof:name":"Caixa D'estalvis Sabadell",
    "wof:placetype":"venue"
},
  "geometry": {"coordinates":[2.0436499119,41.3394508362],"type":"Point"}
}