{
  "type": "Feature",
  "properties": {
    "addr:full":"Calle de Mayor, 81 Sang\u00fcesa Navarra 31400",
    "addr:housenumber":"81",
    "addr:postcode":"31400",
    "addr:street":"Calle De Mayor",
    "iso:country":"ES",
    "sg:address":"Calle de Mayor, 81",
    "sg:city":"Sang\u00fcesa",
    "sg:orig_category":"Asesor\u00cda Sobre Comunicaci\u00d3n De Empresas",
    "sg:phone":"+34 948 43 01 36",
    "sg:postcode":"31400",
    "sg:province":"Navarra",
    "wof:name":"Asesoria Larra\u00f1eta S.l.",
    "wof:placetype":"venue"
},
  "geometry": {"coordinates":[-1.2819758654,42.5761489868],"type":"Point"}
}