{
  "type": "Feature",
  "properties": {
    "addr:full":"Avda Aragon De, 1 Fraga Huesca 22520",
    "addr:postcode":"22520",
    "addr:street":"Avda Aragon De 1 Fraga",
    "iso:country":"ES",
    "sg:address":"Avda Aragon De, 1",
    "sg:city":"Fraga",
    "sg:orig_category":"Frutas Y Legumbres Frescas (al Por Mayor)",
    "sg:phone":"+34 974 45 38 64",
    "sg:postcode":"22520",
    "sg:province":"Huesca",
    "wof:name":"Asociacion Profesional Frutas",
    "wof:placetype":"venue"
},
  "geometry": {"coordinates":[0.3438872993,41.5222702026],"type":"Point"}
}