{
  "type": "Feature",
  "properties": {
    "addr:full":"Calle de Jesus Maria, 26 Andujar Ja\u00e9n 23740",
    "addr:housenumber":"26",
    "addr:postcode":"23740",
    "addr:street":"Calle De Jesus Maria",
    "iso:country":"ES",
    "sg:address":"Calle de Jesus Maria, 26",
    "sg:city":"Andujar",
    "sg:orig_category":"Mercer\u00cda, Lencer\u00cda (al Por Menor)",
    "sg:phone":"+34 953 50 37 73",
    "sg:postcode":"23740",
    "sg:province":"Ja\u00e9n",
    "wof:name":"Collado Diaz Carmen",
    "wof:placetype":"venue"
},
  "geometry": {"coordinates":[-4.0581607819,38.041595459],"type":"Point"}
}