{
  "type": "Feature",
  "properties": {
    "iso:country":"ES",
    "sg:address":"Trva Marina (da), 29",
    "sg:city":"Viveiro",
    "sg:orig_category":"Asesor\u00cda Fiscal Y Jur\u00cddica",
    "sg:phone":"+34 982 55 16 95",
    "sg:postcode":"27850",
    "sg:province":"Lugo",
    "wof:name":"Valle Rey Jose Francisco",
    "wof:placetype":"venue"
},
  "geometry": {"coordinates":[-7.5967850685,43.6610298157],"type":"Point"}
}