{
  "type": "Feature",
  "properties": {
    "iso:country":"ES",
    "sg:address":"Carrer de Corsega, 426",
    "sg:city":"Barcelona",
    "sg:orig_category":"Ense\u00d1anza Variada",
    "sg:phone":"+34 934 59 03 46",
    "sg:postcode":"08037",
    "sg:province":"Barcelona",
    "wof:name":"Asociacion Pilotos Y Propietarios De Aviones De Espa\u00f1a",
    "wof:placetype":"venue"
},
  "geometry": {"coordinates":[2.1655201912,41.4011611938],"type":"Point"}
}