{
  "type": "Feature",
  "properties": {
    "iso:country":"ES",
    "sg:address":"Calle de Santa Emilia, 65",
    "sg:city":"Brenes",
    "sg:orig_category":"Promotores Constructores",
    "sg:phone":"+34 955 65 34 45",
    "sg:postcode":"41310",
    "sg:province":"Sevilla",
    "wof:name":"Construcciones Noa E Hijos S.l.",
    "wof:placetype":"venue"
},
  "geometry": {"coordinates":[-5.8682842255,37.5475387573],"type":"Point"}
}