{
  "type": "Feature",
  "properties": {
    "addr:full":"Calle de San Jose, 20 Puerto Valencia 46520",
    "addr:postcode":"46520",
    "addr:street":"Calle De San;20 Puerto",
    "iso:country":"ES",
    "sg:address":"Calle de San Jose, 20",
    "sg:city":"Puerto",
    "sg:orig_category":"Molduras, Junquillos, Listones Y Molduras Perforadas",
    "sg:phone":"+34 962 67 95 09",
    "sg:postcode":"46520",
    "sg:province":"Valencia",
    "wof:name":"Sanchez Garcia Maria Isabel",
    "wof:placetype":"venue"
},
  "geometry": {"coordinates":[-0.2260919958,39.663394928],"type":"Point"}
}