{
  "type": "Feature",
  "properties": {
    "addr:full":"Ctra Canillas, 122 Madrid Madrid 28043",
    "addr:housenumber":"122",
    "addr:postcode":"28043",
    "addr:street":"Ctra Canillas",
    "iso:country":"ES",
    "sg:address":"Ctra Canillas, 122",
    "sg:city":"Madrid",
    "sg:orig_category":"Droguer\u00cdas (al Por Menor)",
    "sg:phone":"+34 913 00 29 93",
    "sg:postcode":"28043",
    "sg:province":"Madrid",
    "wof:name":"Correa Monasterio Miguel",
    "wof:placetype":"venue"
},
  "geometry": {"coordinates":[-3.643269062,40.4645004272],"type":"Point"}
}