{
  "type": "Feature",
  "properties": {
    "addr:full":"Calle de San Diego De Alcala, 1 Palmas De Gran Canaria Las Palmas 35001",
    "addr:housenumber":"1",
    "addr:postcode":"35001",
    "addr:street":"Calle De San;De Alcala",
    "iso:country":"ES",
    "sg:address":"Calle de San Diego De Alcala, 1",
    "sg:city":"Palmas De Gran Canaria",
    "sg:orig_category":"Psic\u00d3logos",
    "sg:phone":"+34 928 36 19 07",
    "sg:postcode":"35001",
    "sg:province":"Las Palmas",
    "wof:name":"Ley Elizalde Maria Dolores",
    "wof:placetype":"venue"
},
  "geometry": {"coordinates":[-15.416973114,28.1012382507],"type":"Point"}
}