{
  "type": "Feature",
  "properties": {
    "iso:country":"ES",
    "sg:address":"Carr Figuerola, 35",
    "sg:city":"Girona",
    "sg:orig_category":"Restaurantes",
    "sg:phone":"+34 972 21 84 24",
    "sg:postcode":"17001",
    "sg:province":"Girona",
    "wof:name":"R Ludic 02 S.l.",
    "wof:placetype":"venue"
},
  "geometry": {"coordinates":[2.8192980289,41.9851608276],"type":"Point"}
}