{
  "type": "Feature",
  "properties": {
    "addr:full":"Carrer de Angli, 31 Barcelona Barcelona 08017",
    "addr:housenumber":"31",
    "addr:postcode":"08017",
    "addr:street":"Carrer De Angli",
    "iso:country":"ES",
    "sg:address":"Carrer de Angli, 31",
    "sg:city":"Barcelona",
    "sg:orig_category":"Poli\u00c9ster",
    "sg:phone":"+34 932 04 69 68",
    "sg:postcode":"08017",
    "sg:province":"Barcelona",
    "wof:name":"Todofil S.l.",
    "wof:placetype":"venue"
},
  "geometry": {"coordinates":[2.1257109642,41.4001312256],"type":"Point"}
}