{
  "type": "Feature",
  "properties": {
    "iso:country":"ES",
    "sg:address":"Calle de Golondrina, S/n",
    "sg:city":"Fuensalida",
    "sg:orig_category":"Restaurantes",
    "sg:phone":"+34 925 73 12 64",
    "sg:postcode":"45510",
    "sg:province":"Toledo",
    "wof:name":"Complejo Paramo S.l.",
    "wof:placetype":"venue"
},
  "geometry": {"coordinates":[-4.2070240974,40.0474357605],"type":"Point"}
}