{
  "type": "Feature",
  "properties": {
    "addr:full":"Carrer de Fusina, 15 Vic Barcelona 08500",
    "addr:housenumber":"15",
    "addr:postcode":"08500",
    "addr:street":"Carrer De Fusina",
    "iso:country":"ES",
    "sg:address":"Carrer de Fusina, 15",
    "sg:city":"Vic",
    "sg:orig_category":"Papeler\u00cdas, Librer\u00cdas",
    "sg:phone":"+34 938 86 08 27",
    "sg:postcode":"08500",
    "sg:province":"Barcelona",
    "wof:name":"Blancafort 2000 S. L.",
    "wof:placetype":"venue"
},
  "geometry": {"coordinates":[2.2576160431,41.9307594299],"type":"Point"}
}