{
  "type": "Feature",
  "properties": {
    "addr:full":"Ctra. Villafranqueza, 5 Alacant Alicante 03012",
    "addr:housenumber":"5",
    "addr:postcode":"03012",
    "addr:street":"Ctra. Villafranqueza",
    "iso:country":"ES",
    "sg:address":"Ctra. Villafranqueza, 5",
    "sg:city":"Alacant",
    "sg:orig_category":"Asociaciones, Organismos Culturales Y Socioeducativos",
    "sg:phone":"+34 965 17 92 03",
    "sg:postcode":"03012",
    "sg:province":"Alicante",
    "wof:name":"Asociacion Juvenil La Sal De La Tierra",
    "wof:placetype":"venue"
},
  "geometry": {"coordinates":[-0.489151597,38.3822402954],"type":"Point"}
}