{
  "type": "Feature",
  "properties": {
    "iso:country":"ES",
    "sg:address":"Calle de Doctor Velez, 31",
    "sg:city":"Santa Marina Del Rey",
    "sg:orig_category":"Pescader\u00cdas (al Por Menor)",
    "sg:phone":"+34 987 37 73 77",
    "sg:postcode":"24393",
    "sg:province":"Le\u00f3n",
    "wof:name":"Dominguez Marcos Jesus",
    "wof:placetype":"venue"
},
  "geometry": {"coordinates":[-5.8114190102,42.4938812256],"type":"Point"}
}