{
  "type": "Feature",
  "properties": {
    "addr:full":"Calle de Jorge Guillen, 2 Valladolid Valladolid 47003",
    "addr:housenumber":"2",
    "addr:postcode":"47003",
    "addr:street":"Calle De Jorge Guillen",
    "iso:country":"ES",
    "sg:address":"Calle de Jorge Guillen, 2",
    "sg:city":"Valladolid",
    "sg:orig_category":"Farmacias",
    "sg:phone":"+34 983 33 12 02",
    "sg:postcode":"47003",
    "sg:province":"Valladolid",
    "wof:name":"Santos Bobillo Maria Dolores",
    "wof:placetype":"venue"
},
  "geometry": {"coordinates":[-4.7306599617,41.6539649963],"type":"Point"}
}