{
  "type": "Feature",
  "properties": {
    "iso:country":"ES",
    "sg:address":"Calle de Carmen, 27",
    "sg:city":"Coru\u00d1a",
    "sg:orig_category":"Peluqueros: De Se\u00d1oras",
    "sg:phone":"+34 981 20 06 61",
    "sg:postcode":"15002",
    "sg:province":"A Coru\u00f1a",
    "wof:name":"Souto Ulloa Maria Paz",
    "wof:placetype":"venue"
},
  "geometry": {"coordinates":[-8.4009113312,43.3780517578],"type":"Point"}
}