{
  "type": "Feature",
  "properties": {
    "addr:full":"Calle de Pablo Neruda, 8 Fortuna Murcia 30620",
    "addr:housenumber":"8",
    "addr:postcode":"30620",
    "addr:street":"Calle De Pablo Neruda",
    "iso:country":"ES",
    "sg:address":"Calle de Pablo Neruda, 8",
    "sg:city":"Fortuna",
    "sg:orig_category":"Molduras, Junquillos, Listones Y Molduras Perforadas",
    "sg:phone":"+34 968 68 60 76",
    "sg:postcode":"30620",
    "sg:province":"Murcia",
    "wof:name":"Arnau Martinez Noelia",
    "wof:placetype":"venue"
},
  "geometry": {"coordinates":[-1.1244819164,38.1785888672],"type":"Point"}
}