{
  "type": "Feature",
  "properties": {
    "addr:full":"Avda Alfonso R. Castelao, 74 Calle Pontevedra 36690",
    "addr:housenumber":"74",
    "addr:postcode":"36690",
    "addr:street":"Avda Alfonso R. Castelao;Calle Pontevedra",
    "iso:country":"ES",
    "sg:address":"Avda Alfonso R. Castelao, 74",
    "sg:city":"Calle",
    "sg:orig_category":"Molduras, Junquillos, Listones Y Molduras Perforadas",
    "sg:phone":"+34 986 70 00 69",
    "sg:postcode":"36690",
    "sg:province":"Pontevedra",
    "wof:name":"Gonzalez Perez Maria Rita",
    "wof:placetype":"venue"
},
  "geometry": {"coordinates":[-8.6055440903,42.3392410278],"type":"Point"}
}