{
  "type": "Feature",
  "properties": {
    "iso:country":"ES",
    "sg:address":"Avda Cerro Del Aguila (del), 11",
    "sg:city":"San Sebastian De Los Reyes",
    "sg:orig_category":"Alimentaci\u00d3n General (al Por Mayor)",
    "sg:phone":"+34 916 59 37 90",
    "sg:postcode":"28700",
    "sg:province":"Madrid",
    "wof:name":"Cooperativa De Fabricantes Espa\u00d1oles De Pienso Compuestos",
    "wof:placetype":"venue"
},
  "geometry": {"coordinates":[-3.6144509315,40.546497345],"type":"Point"}
}