{
  "type": "Feature",
  "properties": {
    "addr:full":"Calle de Amparo, 23 Madrid Madrid 28012",
    "addr:housenumber":"23",
    "addr:postcode":"madrid;28012",
    "addr:street":"Calle De Amparo",
    "iso:country":"ES",
    "sg:address":"Calle de Amparo, 23",
    "sg:city":"Madrid",
    "sg:orig_category":"Bisuteros (fabricaci\u00d3n, Al Por Mayor)",
    "sg:phone":"+34 915 28 97 87",
    "sg:postcode":"28012",
    "sg:province":"Madrid",
    "wof:name":"Barbolla Y Castillo Cdad.",
    "wof:placetype":"venue"
},
  "geometry": {"coordinates":[-3.7034509182,40.4103813171],"type":"Point"}
}