{
  "type": "Feature",
  "properties": {
    "addr:full":"Calle de Americo Vespucio, S/n Sevilla Sevilla 41...",
    "addr:housenumber":"s / n;41 ...",
    "addr:street":"Calle De Americo Vespucio;Sevilla",
    "iso:country":"ES",
    "sg:address":"Calle de Americo Vespucio, S/n",
    "sg:city":"Sevilla",
    "sg:orig_category":"Organismos De Investigaciones Cient\u00cdficas Y T\u00c9cnicas",
    "sg:phone":"+34 954 48 95 00",
    "sg:postcode":"41...",
    "sg:province":"Sevilla",
    "sg:website":"www.cartuja.csic.es",
    "wof:name":"Consejo Superior De Investigaciones Cientificas",
    "wof:placetype":"venue"
},
  "geometry": {"coordinates":[-6.008907795,37.4025344849],"type":"Point"}
}