{
  "type": "Feature",
  "properties": {
    "iso:country":"ES",
    "sg:address":"Plaz Arriola, 1",
    "sg:city":"Malaga",
    "sg:orig_category":"Vinos Y Licores (venta Al Por Menor)",
    "sg:phone":"+34 952 21 24 08",
    "sg:postcode":"29005",
    "sg:province":"M\u00e1laga",
    "sg:website":"www.trujalvino.net",
    "wof:name":"Gutierrez Blanco Antonio Jesus",
    "wof:placetype":"venue"
},
  "geometry": {"coordinates":[-4.4249510765,36.7191352844],"type":"Point"}
}