{
  "type": "Feature",
  "properties": {
    "iso:country":"ES",
    "sg:address":"Urb Camposol, 164",
    "sg:city":"Camposol",
    "sg:orig_category":"Controles De Edificaci\u00d3n (construcci\u00d3n, Seguridad)",
    "sg:phone":"+34 954 14 81 33",
    "sg:postcode":"41410",
    "sg:province":"Sevilla",
    "wof:name":"Servinst Bau S.l.",
    "wof:placetype":"venue"
},
  "geometry": {"coordinates":[-5.6433792114,37.4708709717],"type":"Point"}
}