{
  "type": "Feature",
  "properties": {
    "addr:full":"Avda Navarra, 49 Tarazona Zaragoza 50500",
    "addr:housenumber":"49",
    "addr:postcode":"50500",
    "addr:street":"Avda Navarra",
    "iso:country":"ES",
    "sg:address":"Avda Navarra, 49",
    "sg:city":"Tarazona",
    "sg:orig_category":"Inmobiliaria (agencias)",
    "sg:phone":"+34 976 19 00 00",
    "sg:postcode":"50500",
    "sg:province":"Zaragoza",
    "wof:name":"Bancal S.a.",
    "wof:placetype":"venue"
},
  "geometry": {"coordinates":[-1.7246769667,41.9085273743],"type":"Point"}
}