{
  "type": "Feature",
  "properties": {
    "iso:country":"ES",
    "sg:address":"Ctra S Jose De La Vega, S/n",
    "sg:city":"Murcia",
    "sg:orig_category":"Comercio, Reparaci\u00d3n De Bicicletas, De Motocicletas, De Accesorios",
    "sg:phone":"+34 968 25 98 85",
    "sg:postcode":"30011",
    "sg:province":"Murcia",
    "wof:name":"Belando Perez Antonio",
    "wof:placetype":"venue"
},
  "geometry": {"coordinates":[-1.1055790186,37.9783668518],"type":"Point"}
}