{
  "type": "Feature",
  "properties": {
    "iso:country":"ES",
    "sg:address":"Avda Andalucia, 32",
    "sg:city":"Cadiz",
    "sg:orig_category":"Abogados",
    "sg:phone":"+34 956 25 26 27",
    "sg:postcode":"11008",
    "sg:province":"C\u00e1diz",
    "wof:name":"Ribon Seisdedos Amparo",
    "wof:placetype":"venue"
},
  "geometry": {"coordinates":[-6.2853560448,36.5207748413],"type":"Point"}
}