{
  "type": "Feature",
  "properties": {
    "iso:country":"ES",
    "sg:address":"Plaz Angel (del), 2",
    "sg:city":"Granada",
    "sg:orig_category":"Congelados: Productos Alimentarios (al Por Menor)",
    "sg:phone":"+34 958 81 71 02",
    "sg:postcode":"18006",
    "sg:province":"Granada",
    "sg:website":"www.pastelerialaconcordia.com",
    "wof:name":"Pasteleria La Concordia S.l.l.",
    "wof:placetype":"venue"
},
  "geometry": {"coordinates":[-3.5961499214,37.1638450623],"type":"Point"}
}