{
  "type": "Feature",
  "properties": {
    "iso:country":"ES",
    "sg:address":"Carrer de Sant Fermi, S/n",
    "sg:city":"S. Celoni",
    "sg:orig_category":"Rectificaci\u00d3n, Mecanizado, Fresado",
    "sg:phone":"+34 938 67 33 24",
    "sg:postcode":"08470",
    "sg:province":"Barcelona",
    "wof:name":"Tarridas Pascual Pedro",
    "wof:placetype":"venue"
},
  "geometry": {"coordinates":[2.4873299599,41.6802558899],"type":"Point"}
}