{
  "type": "Feature",
  "properties": {
    "iso:country":"ES",
    "sg:address":"Calle de Jacinto Benavente, 6",
    "sg:city":"Marbella",
    "sg:orig_category":"Reposter\u00cdas",
    "sg:phone":"+34 952 77 06 08",
    "sg:postcode":"29600",
    "sg:province":"M\u00e1laga",
    "wof:name":"Luna Brenes Manuela",
    "wof:placetype":"venue"
},
  "geometry": {"coordinates":[-4.8878121376,36.5111198425],"type":"Point"}
}