{
  "type": "Feature",
  "properties": {
    "addr:full":"Calle de San Pascual, 1 Alaquas Valencia 46970",
    "addr:housenumber":"1",
    "addr:postcode":"46970",
    "addr:street":"Calle De San Pascual",
    "iso:country":"ES",
    "sg:address":"Calle de San Pascual, 1",
    "sg:city":"Alaquas",
    "sg:orig_category":"Maquinaria Para Industrias Diversas",
    "sg:phone":"+34 961 51 76 29",
    "sg:postcode":"46970",
    "sg:province":"Valencia",
    "wof:name":"Almader S.l.",
    "wof:placetype":"venue"
},
  "geometry": {"coordinates":[-0.4542680979,39.4564552307],"type":"Point"}
}