{
  "type": "Feature",
  "properties": {
    "iso:country":"ES",
    "sg:address":"Avda Pio Xii, 1",
    "sg:city":"Valencia",
    "sg:orig_category":"Centros De Coordinaci\u00d3n",
    "sg:phone":"+34 963 49 47 99",
    "sg:postcode":"46009",
    "sg:province":"Valencia",
    "wof:name":"Carrera Cavaller Juan Antonio",
    "wof:placetype":"venue"
},
  "geometry": {"coordinates":[-0.3914279938,39.4789161682],"type":"Point"}
}