{
  "type": "Feature",
  "properties": {
    "addr:full":"Calle de Juan Manuel Duran Gonzalez, 35 Palmas De Gran Canaria Las Palmas 35007",
    "addr:housenumber":"35",
    "addr:postcode":"35007",
    "addr:street":"Calle De Juan Manuel Duran Gonzalez",
    "iso:country":"ES",
    "sg:address":"Calle de Juan Manuel Duran Gonzalez, 35",
    "sg:city":"Palmas De Gran Canaria",
    "sg:orig_category":"Ropa Para Se\u00d1oras Y Caballeros (al Por Menor)",
    "sg:phone":"+34 928 22 62 66",
    "sg:postcode":"35007",
    "sg:province":"Las Palmas",
    "wof:name":"Construcciones Jusan Canarias S.a.",
    "wof:placetype":"venue"
},
  "geometry": {"coordinates":[-15.4323205948,28.1355304718],"type":"Point"}
}