{
  "type": "Feature",
  "properties": {
    "iso:country":"ES",
    "sg:address":"Av Paral.lel, 91",
    "sg:city":"Barcelona",
    "sg:classifiers":[
        {
            "category":"Casinos & Gambling",
            "type":"Entertainment"
        }
    ],
    "sg:phone":"+34 934 43 30 53",
    "sg:postcode":"08004",
    "sg:province":"Barcelona",
    "sg:tags":[
        "locale",
        "de",
        "juego"
    ],
    "wof:name":"Bicondal S.a.",
    "wof:placetype":"venue"
},
  "geometry": {"coordinates":[2.1649479866,41.3747901917],"type":"Point"}
}