{
  "type": "Feature",
  "properties": {
    "addr:full":"Calle de Pintada, 31 Nerja M\u00e1laga 29780",
    "addr:housenumber":"31",
    "addr:postcode":"29780",
    "addr:street":"Calle De Pintada",
    "iso:country":"ES",
    "sg:address":"Calle de Pintada, 31",
    "sg:city":"Nerja",
    "sg:orig_category":"Cueros Y Pieles (al Por Mayor)",
    "sg:phone":"+34 952 52 24 08",
    "sg:postcode":"29780",
    "sg:province":"M\u00e1laga",
    "wof:name":"Olmos Fernandez Pilar",
    "wof:placetype":"venue"
},
  "geometry": {"coordinates":[-3.8763370514,36.7469596863],"type":"Point"}
}