{
  "type": "Feature",
  "properties": {
    "iso:country":"ES",
    "sg:address":"San Marino, S/n",
    "sg:city":"San Pedro Alcantara",
    "sg:orig_category":"Armas Y Municiones (fabricaci\u00d3n, Al Por Mayor)",
    "sg:phone":"+34 952 78 73 32",
    "sg:postcode":"29670",
    "sg:province":"M\u00e1laga",
    "wof:name":"Castrero Barragan Luis Miguel",
    "wof:placetype":"venue"
},
  "geometry": {"coordinates":[-4.9902391434,36.4866333008],"type":"Point"}
}