{
  "type": "Feature",
  "properties": {
    "iso:country":"ES",
    "sg:address":"Calle de Carretera, 7",
    "sg:city":"Pancrudo",
    "sg:orig_category":"Producci\u00d3n De Abonos Y De Fertilizantes",
    "sg:phone":"+34 978 77 50 66",
    "sg:postcode":"44720",
    "sg:province":"Teruel",
    "wof:name":"Casa Garzon S.l.",
    "wof:placetype":"venue"
},
  "geometry": {"coordinates":[-1.0284787416,40.7622566223],"type":"Point"}
}