{
  "type": "Feature",
  "properties": {
    "iso:country":"ES",
    "sg:address":"Calle de Mayor De Ramon Y Cajal, 9",
    "sg:city":"Orihuela",
    "sg:orig_category":"Moda",
    "sg:phone":"+34 966 74 02 77",
    "sg:postcode":"03300",
    "sg:province":"Alicante",
    "wof:name":"Micuna C.b.",
    "wof:placetype":"venue"
},
  "geometry": {"coordinates":[-0.9475269914,38.0855674744],"type":"Point"}
}