{
  "type": "Feature",
  "properties": {
    "addr:full":"Avda Mediterraneo, 9 Madrid Madrid 28007",
    "addr:housenumber":"9",
    "addr:postcode":"madrid;28007",
    "addr:street":"Avda Mediterraneo",
    "iso:country":"ES",
    "sg:address":"Avda Mediterraneo, 9",
    "sg:city":"Madrid",
    "sg:orig_category":"Promotores Constructores",
    "sg:phone":"+34 914 34 38 40",
    "sg:postcode":"28007",
    "sg:province":"Madrid",
    "wof:name":"Promociones Torreon S.a.",
    "wof:placetype":"venue"
},
  "geometry": {"coordinates":[-3.6768710613,40.407535553],"type":"Point"}
}