{
  "type": "Feature",
  "properties": {
    "iso:country":"ES",
    "sg:address":"Carr Pla\u00c7a, De, 5",
    "sg:city":"Campos",
    "sg:orig_category":"Bisuter\u00cda, Joyer\u00cda, Relojer\u00cda (al Por Menor)",
    "sg:phone":"+34 971 16 01 13",
    "sg:postcode":"07630",
    "sg:province":"Islas Baleares",
    "wof:name":"Mulet Vanrell Damia",
    "wof:placetype":"venue"
},
  "geometry": {"coordinates":[2.998032093,39.4063224792],"type":"Point"}
}