{
  "type": "Feature",
  "properties": {
    "addr:full":"Calle de Centelles, Los, 7 Valencia Valencia 46006",
    "addr:housenumber":"7",
    "addr:postcode":"46006",
    "addr:street":"Calle De Centelles Los",
    "iso:country":"ES",
    "sg:address":"Calle de Centelles, Los, 7",
    "sg:city":"Valencia",
    "sg:orig_category":"Peluqueros: De Se\u00d1oras",
    "sg:phone":"+34 963 34 03 56",
    "sg:postcode":"46006",
    "sg:province":"Valencia",
    "wof:name":"Garcia Dasi Jesus",
    "wof:placetype":"venue"
},
  "geometry": {"coordinates":[-0.3703815937,39.4603614807],"type":"Point"}
}