{
  "type": "Feature",
  "properties": {
    "iso:country":"ES",
    "sg:address":"Carrer de Mila I Fontanals, S/n",
    "sg:city":"Reus",
    "sg:classifiers":[
        {
            "category":"Personal",
            "subcategory":"Barber",
            "type":"Services"
        }
    ],
    "sg:phone":"+34 977 77 22 32",
    "sg:postcode":"43205",
    "sg:province":"Tarragona",
    "sg:tags":[
        "caballeros",
        "de",
        "peluqueros"
    ],
    "wof:name":"Parra Martinez Salvador",
    "wof:placetype":"venue"
},
  "geometry": {"coordinates":[1.1125899553,41.1417541504],"type":"Point"}
}