{
  "type": "Feature",
  "properties": {
    "iso:country":"ES",
    "sg:address":"Partida El Monastil, S/n",
    "sg:city":"Elda",
    "sg:orig_category":"Formaci\u00d3n Continuada (variada)",
    "sg:phone":"+34 965 39 72 79",
    "sg:postcode":"03600",
    "sg:province":"Alicante",
    "wof:name":"Servei Valencia D'ocupacio I Formacio",
    "wof:placetype":"venue"
},
  "geometry": {"coordinates":[-0.7961040139,38.475315094],"type":"Point"}
}