{
  "type": "Feature",
  "properties": {
    "iso:country":"ES",
    "sg:address":"Pase Felix R. De La Fuente, 2",
    "sg:city":"Medina Pomar",
    "sg:orig_category":"Frutas Y Legumbres Frescas (al Por Mayor)",
    "sg:phone":"+34 947 19 11 17",
    "sg:postcode":"09500",
    "sg:province":"Burgos",
    "wof:name":"Hortalizas Angel Santamaria Ortega S.l",
    "wof:placetype":"venue"
},
  "geometry": {"coordinates":[-3.4865150452,42.9343261719],"type":"Point"}
}