{
  "type": "Feature",
  "properties": {
    "addr:full":"Calle de Alferez Provisional, 33 Talavera Reina Toledo 45600",
    "addr:housenumber":"33",
    "addr:postcode":"45600",
    "addr:street":"Calle De Alferez Provisional",
    "iso:country":"ES",
    "sg:address":"Calle de Alferez Provisional, 33",
    "sg:city":"Talavera Reina",
    "sg:orig_category":"Venta, Instalaci\u00d3n, Reparaci\u00d3n De Antenas Para Televisi\u00d3n",
    "sg:phone":"+34 925 82 33 94",
    "sg:postcode":"45600",
    "sg:province":"Toledo",
    "wof:name":"Heras Martin Jesus Andres",
    "wof:placetype":"venue"
},
  "geometry": {"coordinates":[-4.8293852806,39.9664611816],"type":"Point"}
}