{
  "type": "Feature",
  "properties": {
    "addr:full":"Calle de Fray Junipero Serra, 2 Andujar Ja\u00e9n 23740",
    "addr:housenumber":"2",
    "addr:postcode":"23740",
    "addr:street":"Calle De Fray Junipero Serra",
    "iso:country":"ES",
    "sg:address":"Calle de Fray Junipero Serra, 2",
    "sg:city":"Andujar",
    "sg:orig_category":"Asociaciones Humanitarias, De Cooperaci\u00d3n, De Acci\u00d3n Social",
    "sg:phone":"+34 953 51 09 32",
    "sg:postcode":"23740",
    "sg:province":"Ja\u00e9n",
    "wof:name":"Andujar Contra La Droga",
    "wof:placetype":"venue"
},
  "geometry": {"coordinates":[-4.0517072678,38.044960022],"type":"Point"}
}