{
  "type": "Feature",
  "properties": {
    "addr:full":"Calle de Ensenada, 2 Valladolid Valladolid 47008",
    "addr:housenumber":"2",
    "addr:postcode":"47008",
    "addr:street":"Calle De Ensenada",
    "iso:country":"ES",
    "sg:address":"Calle de Ensenada, 2",
    "sg:city":"Valladolid",
    "sg:orig_category":"Aguas (distribuci\u00d3n, Servicios)",
    "sg:phone":"+34 983 22 82 89",
    "sg:postcode":"47008",
    "sg:province":"Valladolid",
    "sg:website":"www.adiquimica.com",
    "wof:name":"Adiquimica S. A.",
    "wof:placetype":"venue"
},
  "geometry": {"coordinates":[-4.820959568,41.5502471924],"type":"Point"}
}