{
  "type": "Feature",
  "properties": {
    "addr:full":"Avda Pais Valencia (del), 116 Onda Castell\u00f3n 12200",
    "addr:postcode":"12200",
    "addr:street":"Avda Pais;Del;Castello\u0301N",
    "iso:country":"ES",
    "sg:address":"Avda Pais Valencia (del), 116",
    "sg:city":"Onda",
    "sg:orig_category":"Porcelanas, Azulejos (fabricaci\u00d3n, Al Por Mayor)",
    "sg:phone":"+34 964 60 11 35",
    "sg:postcode":"12200",
    "sg:province":"Castell\u00f3n",
    "wof:name":"Aguilella Ortells Vicente Y Otro Cdad.",
    "wof:placetype":"venue"
},
  "geometry": {"coordinates":[-0.2655782104,39.9650764465],"type":"Point"}
}