{
  "type": "Feature",
  "properties": {
    "iso:country":"ES",
    "sg:address":"Calle de Julio Montero, 31",
    "sg:city":"Madrid",
    "sg:orig_category":"Transportes Por Carretera: Lotes Completos, Mercanc\u00cdas Diversas",
    "sg:phone":"+34 917 35 06 81",
    "sg:postcode":"28034",
    "sg:province":"Madrid",
    "wof:name":"Veguillas Mateos David",
    "wof:placetype":"venue"
},
  "geometry": {"coordinates":[-3.6880939007,40.4971199036],"type":"Point"}
}