{
  "type": "Feature",
  "properties": {
    "addr:full":"Calle de Sotera De La Mier, 18 Sestao Vizcaya 48910",
    "addr:housenumber":"18",
    "addr:postcode":"48910",
    "addr:street":"Calle De Sotera De La Mier",
    "iso:country":"ES",
    "sg:address":"Calle de Sotera De La Mier, 18",
    "sg:city":"Sestao",
    "sg:orig_category":"Suministros Para Carrocer\u00cdas",
    "sg:phone":"+34 944 06 90 77",
    "sg:postcode":"48910",
    "sg:province":"Vizcaya",
    "wof:name":"Carrocerias Kaiku, S.l.",
    "wof:placetype":"venue"
},
  "geometry": {"coordinates":[-3.0053079128,43.3123664856],"type":"Point"}
}