{
  "type": "Feature",
  "properties": {
    "addr:full":"Calle de Salas Quiroga, 4 Valencia Valencia 46007",
    "addr:housenumber":"4",
    "addr:postcode":"46007",
    "addr:street":"Calle De Salas Quiroga",
    "iso:country":"ES",
    "sg:address":"Calle de Salas Quiroga, 4",
    "sg:city":"Valencia",
    "sg:orig_category":"Peluquer\u00cdas, Peluquer\u00cda Mixta",
    "sg:phone":"+34 963 84 89 20",
    "sg:postcode":"46007",
    "sg:province":"Valencia",
    "wof:name":"Ruiz Garcia Jose Luis",
    "wof:placetype":"venue"
},
  "geometry": {"coordinates":[-0.3850609958,39.4650306702],"type":"Point"}
}