{
  "type": "Feature",
  "properties": {
    "addr:full":"Rua Francisco Sanchez, 1 Ourense Ourense 32002",
    "addr:housenumber":"1",
    "addr:postcode":"32002",
    "addr:street":"Rua Francisco Sanchez",
    "iso:country":"ES",
    "sg:address":"Rua Francisco Sanchez, 1",
    "sg:city":"Ourense",
    "sg:orig_category":"Publicidad (soportes Y Gesti\u00d3n)",
    "sg:phone":"+34 902 15 22 19",
    "sg:postcode":"32002",
    "sg:province":"Ourense",
    "wof:name":"Inforpubli S.l.",
    "wof:placetype":"venue"
},
  "geometry": {"coordinates":[-7.8685417175,42.3339080811],"type":"Point"}
}