{
  "type": "Feature",
  "properties": {
    "addr:full":"Ctra Benalua, S/n Purullena Granada 18519",
    "addr:housenumber":"s / n",
    "addr:postcode":"18519",
    "addr:street":"Ctra Benalua",
    "iso:country":"ES",
    "sg:address":"Ctra Benalua, S/n",
    "sg:city":"Purullena",
    "sg:orig_category":"Materias Pl\u00c1sticas: Productos De Consumo Masivo (fabricaci\u00d3n, Al Por Mayor)",
    "sg:phone":"+34 958 69 05 54",
    "sg:postcode":"18519",
    "sg:province":"Granada",
    "wof:name":"Sanchez Y Cabrera S.l.",
    "wof:placetype":"venue"
},
  "geometry": {"coordinates":[-3.1880590916,37.3193016052],"type":"Point"}
}