{
  "type": "Feature",
  "properties": {
    "addr:full":"Carrer de Portell, 12 Barcelona Barcelona 08023",
    "addr:housenumber":"12",
    "addr:postcode":"08023",
    "addr:street":"Carrer De Portell",
    "iso:country":"ES",
    "sg:address":"Carrer de Portell, 12",
    "sg:city":"Barcelona",
    "sg:orig_category":"Marroquiner\u00cda (confecci\u00d3n)",
    "sg:phone":"+34 932 10 04 88",
    "sg:postcode":"08023",
    "sg:province":"Barcelona",
    "wof:name":"Aranat S.l.",
    "wof:placetype":"venue"
},
  "geometry": {"coordinates":[2.1511032581,41.4183082581],"type":"Point"}
}