{
  "type": "Feature",
  "properties": {
    "addr:full":"Ernio Bidea, 23 Elbarrena Guip\u00f9zcoa 20159",
    "addr:housenumber":"23",
    "addr:postcode":"20159",
    "addr:street":"Ernio Bidea;Guipu\u0300Zcoa",
    "iso:country":"ES",
    "sg:address":"Ernio Bidea, 23",
    "sg:city":"Elbarrena",
    "sg:orig_category":"Empresas De Desmonte",
    "sg:phone":"+34 943 69 12 61",
    "sg:postcode":"20159",
    "sg:province":"Guip\u00f9zcoa",
    "wof:name":"Sagastibelza Villabona Pedro Maria",
    "wof:placetype":"venue"
},
  "geometry": {"coordinates":[-2.0742990971,43.1991958618],"type":"Point"}
}