{
  "type": "Feature",
  "properties": {
    "addr:full":"Calle de Londres, S/n Caceres C\u00e1ceres 10005",
    "addr:housenumber":"s / n",
    "addr:postcode":"10005",
    "addr:street":"Calle De Londres;Ca\u0301Ceres",
    "iso:country":"ES",
    "sg:address":"Calle de Londres, S/n",
    "sg:city":"Caceres",
    "sg:classifiers":[
        {
            "category":"Shopping",
            "subcategory":"Clothing, Apparel, & Fashions",
            "type":"Retail Goods"
        }
    ],
    "sg:phone":"+34 927 23 68 54",
    "sg:postcode":"10005",
    "sg:province":"C\u00e1ceres",
    "sg:tags":[
        "boutique"
    ],
    "sg:website":"www.pamadyna.com",
    "wof:name":"Pamadyna Sl",
    "wof:placetype":"venue"
},
  "geometry": {"coordinates":[-6.3887991905,39.4685592651],"type":"Point"}
}