{
  "type": "Feature",
  "properties": {
    "iso:country":"ES",
    "sg:address":"Calle de Arxentina, 11",
    "sg:city":"Esfarrapada",
    "sg:orig_category":"Cristaler\u00cdas",
    "sg:phone":"+34 986 34 30 32",
    "sg:postcode":"36470",
    "sg:province":"Pontevedra",
    "wof:name":"Cristaleria Bisel S.c.",
    "wof:placetype":"venue"
},
  "geometry": {"coordinates":[-8.5566053391,42.1008682251],"type":"Point"}
}