{
  "type": "Feature",
  "properties": {
    "addr:full":"Plaz Costa (joaquin), 13 Calatayud Zaragoza 50300",
    "addr:housenumber":"13",
    "addr:postcode":"50300",
    "addr:street":"Plaz Costa Joaquin",
    "iso:country":"ES",
    "sg:address":"Plaz Costa (joaquin), 13",
    "sg:city":"Calatayud",
    "sg:orig_category":"Inform\u00c1tica (estudios, Servicios, Asesor\u00cda, Formaci\u00d3n)",
    "sg:phone":"+34 976 88 76 77",
    "sg:postcode":"50300",
    "sg:province":"Zaragoza",
    "wof:name":"Gestion Tributaria Territorial",
    "wof:placetype":"venue"
},
  "geometry": {"coordinates":[-1.6394540071,41.3522415161],"type":"Point"}
}