{
  "type": "Feature",
  "properties": {
    "iso:country":"ES",
    "sg:address":"Calle de Virgen De Guadalupe, 4",
    "sg:city":"Huelva",
    "sg:orig_category":"Pescader\u00cdas (al Por Menor)",
    "sg:phone":"+34 959 22 39 98",
    "sg:postcode":"21006",
    "sg:province":"Huelva",
    "wof:name":"Arrazola Alejandro Jesus Manuel",
    "wof:placetype":"venue"
},
  "geometry": {"coordinates":[-6.9395508766,37.2599716187],"type":"Point"}
}