{
  "type": "Feature",
  "properties": {
    "addr:full":"Carrer de Germa Joaquim, 73 Terrassa Barcelona 08223",
    "addr:housenumber":"73",
    "addr:postcode":"08223",
    "addr:street":"Carrer De Germa Joaquim",
    "iso:country":"ES",
    "sg:address":"Carrer de Germa Joaquim, 73",
    "sg:city":"Terrassa",
    "sg:orig_category":"Contenedores (mercanc\u00cdas)",
    "sg:phone":"+34 937 85 28 37",
    "sg:postcode":"08223",
    "sg:province":"Barcelona",
    "wof:name":"Allepuz Ulldemolins Florencio",
    "wof:placetype":"venue"
},
  "geometry": {"coordinates":[2.0215022564,41.5535507202],"type":"Point"}
}