{
  "type": "Feature",
  "properties": {
    "addr:full":"Calle de Euskalerria, 18 Zaldibar Vizcaya 48250",
    "addr:housenumber":"18",
    "addr:postcode":"48250",
    "addr:street":"Calle De Euskalerria",
    "iso:country":"ES",
    "sg:address":"Calle de Euskalerria, 18",
    "sg:city":"Zaldibar",
    "sg:orig_category":"Sanatorios M\u00c9dico",
    "sg:phone":"+34 946 82 70 01",
    "sg:postcode":"48250",
    "sg:province":"Vizcaya",
    "wof:name":"Servicio Vasco De Salud",
    "wof:placetype":"venue"
},
  "geometry": {"coordinates":[-2.5489070415,43.1698875427],"type":"Point"}
}