{
  "type": "Feature",
  "properties": {
    "addr:full":"Isaac Albeniz, 5 Caravaca Cruz Murcia 30400",
    "addr:housenumber":"5",
    "addr:postcode":"30400",
    "addr:street":"Isaac Albeniz",
    "iso:country":"ES",
    "sg:address":"Isaac Albeniz, 5",
    "sg:city":"Caravaca Cruz",
    "sg:orig_category":"Doctores En Medicina",
    "sg:phone":"+34 968 70 82 78",
    "sg:postcode":"30400",
    "sg:province":"Murcia",
    "wof:name":"Carazo Melero Manuel Julio",
    "wof:placetype":"venue"
},
  "geometry": {"coordinates":[-1.8652490377,38.0991363525],"type":"Point"}
}