{
  "type": "Feature",
  "properties": {
    "iso:country":"ES",
    "sg:address":"Calle-cuatro P I Valdeferrin, S/n",
    "sg:city":"Ejea Caballeros",
    "sg:orig_category":"Adaptaciones, Acondicionamientos Especiales Para Veh\u00cdculos, Veh\u00cdculos Industriales",
    "sg:phone":"+34 976 66 75 08",
    "sg:postcode":"50600",
    "sg:province":"Zaragoza",
    "wof:name":"Soteras Esteban Jose Miguel",
    "wof:placetype":"venue"
},
  "geometry": {"coordinates":[-1.1382750273,42.1269798279],"type":"Point"}
}