{
  "type": "Feature",
  "properties": {
    "addr:full":"Concordia, 25 Arganda Madrid 28500",
    "addr:housenumber":"25",
    "addr:postcode":"28500",
    "addr:street":"Concordia",
    "iso:country":"ES",
    "sg:address":"Concordia, 25",
    "sg:city":"Arganda",
    "sg:orig_category":"Contenedores (mercanc\u00cdas)",
    "sg:phone":"+34 918 71 11 63",
    "sg:postcode":"28500",
    "sg:province":"Madrid",
    "wof:name":"Garcia Moreno Pedro",
    "wof:placetype":"venue"
},
  "geometry": {"coordinates":[-3.4418969154,40.3070716858],"type":"Point"}
}