{
  "type": "Feature",
  "properties": {
    "addr:full":"Pardi\u00f1as, 14 Bejar Salamanca 37700",
    "addr:housenumber":"14",
    "addr:postcode":"37700",
    "addr:street":"Pardin\u0303As",
    "iso:country":"ES",
    "sg:address":"Pardi\u00f1as, 14",
    "sg:city":"Bejar",
    "sg:orig_category":"Librer\u00cdas",
    "sg:phone":"+34 923 40 19 05",
    "sg:postcode":"37700",
    "sg:province":"Salamanca",
    "wof:name":"Mazo De Arriba Ricardo",
    "wof:placetype":"venue"
},
  "geometry": {"coordinates":[-5.7720708847,40.387840271],"type":"Point"}
}