{
  "type": "Feature",
  "properties": {
    "addr:full":"Calle de Monte Sueve, 4 Arriondas Asturias 33540",
    "addr:housenumber":"4",
    "addr:postcode":"33540",
    "addr:street":"Calle De Monte Sueve",
    "iso:country":"ES",
    "sg:address":"Calle de Monte Sueve, 4",
    "sg:city":"Arriondas",
    "sg:orig_category":"Peluquer\u00cdas, Peluquer\u00cda Mixta",
    "sg:phone":"+34 985 84 09 36",
    "sg:postcode":"33540",
    "sg:province":"Asturias",
    "wof:name":"Solares Suarez Alejandra",
    "wof:placetype":"venue"
},
  "geometry": {"coordinates":[-5.1867289543,43.390296936],"type":"Point"}
}