{
  "type": "Feature",
  "properties": {
    "iso:country":"ES",
    "sg:address":"Avda Camara De La Industria, 24",
    "sg:city":"Mostoles",
    "sg:classifiers":[
        {
            "category":"Manufacturing",
            "subcategory":"Metals",
            "type":"Manufacturing & Wholesale Goods"
        }
    ],
    "sg:phone":"+34 916 47 62 92",
    "sg:postcode":"28938",
    "sg:province":"Madrid",
    "sg:tags":[
        "en",
        "fundiciones"
    ],
    "wof:name":"Tafime S.a.",
    "wof:placetype":"venue"
},
  "geometry": {"coordinates":[-3.8740520477,40.3108901978],"type":"Point"}
}