{
  "type": "Feature",
  "properties": {
    "iso:country":"ES",
    "sg:address":"Pase Alberto Palacios, 42",
    "sg:city":"Madrid",
    "sg:orig_category":"Juegos Y Juguetes (al Por Menor)",
    "sg:phone":"+34 917 97 17 09",
    "sg:postcode":"28021",
    "sg:province":"Madrid",
    "wof:name":"Jugueteria Poli S.l.",
    "wof:placetype":"venue"
},
  "geometry": {"coordinates":[-3.71291399,40.3449401855],"type":"Point"}
}