{
  "type": "Feature",
  "properties": {
    "iso:country":"ES",
    "sg:address":"Calle de Becquer, 6",
    "sg:city":"Mostoles",
    "sg:orig_category":"Ense\u00d1anza Variada",
    "sg:phone":"+34 916 18 95 61",
    "sg:postcode":"28932",
    "sg:province":"Madrid",
    "wof:name":"Abad Martinez Pedro",
    "wof:placetype":"venue"
},
  "geometry": {"coordinates":[-3.857925,40.330837],"type":"Point"}
}