{
  "type": "Feature",
  "properties": {
    "iso:country":"ES",
    "sg:address":"Calle de Rio Arevalillo (del), 2",
    "sg:city":"Arevalo",
    "sg:orig_category":"Carb\u00d3n, Carb\u00d3n De Madera (al Por Mayor)",
    "sg:phone":"+34 920 30 23 15",
    "sg:postcode":"05200",
    "sg:province":"\u00c1vila",
    "wof:name":"Tesorero Del Rio Isabel",
    "wof:placetype":"venue"
},
  "geometry": {"coordinates":[-4.7178821564,41.0429878235],"type":"Point"}
}