{
  "type": "Feature",
  "properties": {
    "addr:full":"Calle de Jesus Ferrer Jimeno, 10 Palmas De Gran Canaria Las Palmas 35010",
    "addr:housenumber":"10",
    "addr:postcode":"35010",
    "addr:street":"Calle De Jesus Ferrer Jimeno",
    "iso:country":"ES",
    "sg:address":"Calle de Jesus Ferrer Jimeno, 10",
    "sg:city":"Palmas De Gran Canaria",
    "sg:orig_category":"Restaurantes",
    "sg:phone":"+34 928 27 46 91",
    "sg:postcode":"35010",
    "sg:province":"Las Palmas",
    "wof:name":"Mario Y Colombina S.l.",
    "wof:placetype":"venue"
},
  "geometry": {"coordinates":[-15.4376678467,28.1314220428],"type":"Point"}
}