{
  "type": "Feature",
  "properties": {
    "addr:full":"Calle de Junto A Campanario, 9 Almazan Soria 42200",
    "addr:housenumber":"9",
    "addr:postcode":"42200",
    "addr:street":"Calle De Junto A Campanario",
    "iso:country":"ES",
    "sg:address":"Calle de Junto A Campanario, 9",
    "sg:city":"Almazan",
    "sg:orig_category":"Empresarios",
    "sg:phone":"+34 975 30 12 03",
    "sg:postcode":"42200",
    "sg:province":"Soria",
    "wof:name":"Romero Borque Felipe",
    "wof:placetype":"venue"
},
  "geometry": {"coordinates":[-2.5348091125,41.4839324951],"type":"Point"}
}