{
  "type": "Feature",
  "properties": {
    "iso:country":"ES",
    "sg:address":"Carrer de Gabriel Maura, 4",
    "sg:city":"Palma",
    "sg:orig_category":"Cajas De Ahorro",
    "sg:phone":"+34 971 27 45 56",
    "sg:postcode":"07005",
    "sg:province":"Islas Baleares",
    "sg:website":"www.lacaixa.es",
    "wof:name":"Caixa D'estalvis I Pensions De Barcelona",
    "wof:placetype":"venue"
},
  "geometry": {"coordinates":[2.6598050594,39.5771903992],"type":"Point"}
}