{
  "type": "Feature",
  "properties": {
    "addr:full":"Avda Ferrandis Salvador, S/n Mas Dels Frares Castell\u00f3n 12560",
    "addr:housenumber":"s",
    "addr:postcode":"12560",
    "addr:street":"Avda Ferrandis Salvador;/ N Mas Dels Frares Castello\u0301N",
    "iso:country":"ES",
    "sg:address":"Avda Ferrandis Salvador, S/n",
    "sg:city":"Mas Dels Frares",
    "sg:orig_category":"Relojer\u00cda (al Por Menor, Reparaci\u00d3n)",
    "sg:phone":"+34 964 39 40 59",
    "sg:postcode":"12560",
    "sg:province":"Castell\u00f3n",
    "wof:name":"Navarro Naches Arcadio",
    "wof:placetype":"venue"
},
  "geometry": {"coordinates":[0.0590550005,40.0523414612],"type":"Point"}
}