{
  "type": "Feature",
  "properties": {
    "iso:country":"ES",
    "sg:address":"Calle de Juan Ramon Jimenez, S/n",
    "sg:city":"Burgos",
    "sg:orig_category":"Colocaci\u00d3n, Mantenimiento De Canalizaciones",
    "sg:phone":"+34 947 47 46 53",
    "sg:postcode":"09007",
    "sg:province":"Burgos",
    "wof:name":"Aspecto Re-formas S.l.",
    "wof:placetype":"venue"
},
  "geometry": {"coordinates":[-3.6618552208,42.352848053],"type":"Point"}
}