{
  "type": "Feature",
  "properties": {
    "addr:full":"Urb Torre Morales, S/n Garrapinillos Zaragoza 50190",
    "addr:housenumber":"s / n",
    "addr:postcode":"50190",
    "addr:street":"Urb Torre Morales;Garrapinillos",
    "iso:country":"ES",
    "sg:address":"Urb Torre Morales, S/n",
    "sg:city":"Garrapinillos",
    "sg:orig_category":"Arenas, Guijarros Y Granulados",
    "sg:phone":"+34 976 78 00 15",
    "sg:postcode":"50190",
    "sg:province":"Zaragoza",
    "wof:name":"Aricemex S.a.",
    "wof:placetype":"venue"
},
  "geometry": {"coordinates":[-1.0273573399,41.6837768555],"type":"Point"}
}