{
  "type": "Feature",
  "properties": {
    "iso:country":"ES",
    "sg:address":"Calle de A(requena), 10",
    "sg:city":"Cedillo Condado",
    "sg:orig_category":"Cerrajer\u00cda, Ferrallista",
    "sg:phone":"+34 925 50 10 07",
    "sg:postcode":"45214",
    "sg:province":"Toledo",
    "wof:name":"Pinillos Rodriguez Juan Carlos",
    "wof:placetype":"venue"
},
  "geometry": {"coordinates":[-3.9065086842,40.1041221619],"type":"Point"}
}