{
  "type": "Feature",
  "properties": {
    "iso:country":"ES",
    "sg:address":"Calle de Miguel Castillejo, 12",
    "sg:city":"Jaen",
    "sg:orig_category":"Electrodom\u00c9sticos (al Por Menor)",
    "sg:phone":"+34 953 26 56 10",
    "sg:postcode":"23009",
    "sg:province":"Ja\u00e9n",
    "wof:name":"Garcia Sanchez Alonso",
    "wof:placetype":"venue"
},
  "geometry": {"coordinates":[-3.78738904,37.7801017761],"type":"Point"}
}