{
  "type": "Feature",
  "properties": {
    "addr:full":"Pl Major, 26 Vic Barcelona 08500",
    "addr:housenumber":"26",
    "addr:postcode":"08500",
    "addr:street":"Pl Major",
    "iso:country":"ES",
    "sg:address":"Pl Major, 26",
    "sg:city":"Vic",
    "sg:orig_category":"Heladeros",
    "sg:phone":"+34 938 86 06 16",
    "sg:postcode":"08500",
    "sg:province":"Barcelona",
    "wof:name":"Daniel Sirvent Llorens Laura Sirvent Llorens Sociedad Civil Particul",
    "wof:placetype":"venue"
},
  "geometry": {"coordinates":[2.2547230721,41.9308052063],"type":"Point"}
}