{
  "type": "Feature",
  "properties": {
    "iso:country":"ES",
    "sg:address":"Calle de Trobika, 13",
    "sg:city":"Mungia",
    "sg:orig_category":"Inmobiliaria (agencias)",
    "sg:phone":"+34 946 15 52 08",
    "sg:postcode":"48100",
    "sg:province":"Vizcaya",
    "wof:name":"Txantxanesa, S.l.",
    "wof:placetype":"venue"
},
  "geometry": {"coordinates":[-2.8443629742,43.3545570374],"type":"Point"}
}