{
  "type": "Feature",
  "properties": {
    "iso:country":"ES",
    "sg:address":"Pl Catalunya, 8",
    "sg:city":"Gava",
    "sg:orig_category":"Empresas De Carpinter\u00cda Met\u00c1lica",
    "sg:phone":"+34 936 38 28 24",
    "sg:postcode":"08850",
    "sg:province":"Barcelona",
    "wof:name":"Caparros Asuar Diego",
    "wof:placetype":"venue"
},
  "geometry": {"coordinates":[2.0016899109,41.3087806702],"type":"Point"}
}