{
  "type": "Feature",
  "properties": {
    "addr:full":"Calle de Caballeros, 1 Plasencia C\u00e1ceres 10600",
    "addr:housenumber":"1",
    "addr:postcode":"10600",
    "addr:street":"Calle De Caballeros;Ca\u0301Ceres",
    "iso:country":"ES",
    "sg:address":"Calle de Caballeros, 1",
    "sg:city":"Plasencia",
    "sg:orig_category":"Bisuteros (fabricaci\u00d3n, Al Por Mayor)",
    "sg:phone":"+34 927 41 38 17",
    "sg:postcode":"10600",
    "sg:province":"C\u00e1ceres",
    "wof:name":"Rodilla Elizo Hermanos S.a.l.",
    "wof:placetype":"venue"
},
  "geometry": {"coordinates":[-6.0872445107,40.0308418274],"type":"Point"}
}