{
  "type": "Feature",
  "properties": {
    "addr:full":"Calle de Luis Montoto, 85 Sevilla Sevilla 41018",
    "addr:housenumber":"85",
    "addr:postcode":"41018",
    "addr:street":"Calle De Luis Montoto",
    "iso:country":"ES",
    "sg:address":"Calle de Luis Montoto, 85",
    "sg:city":"Sevilla",
    "sg:orig_category":"Agencias De Viajes",
    "sg:phone":"+34 954 57 05 06",
    "sg:postcode":"41018",
    "sg:province":"Sevilla",
    "sg:website":"www.viajestriana.com",
    "wof:name":"Viajes Triana S.a.",
    "wof:placetype":"venue"
},
  "geometry": {"coordinates":[-5.9747138023,37.3873443604],"type":"Point"}
}