{
  "type": "Feature",
  "properties": {
    "addr:full":"Calle de Ana Teresa, 33 Madrid Madrid 28023",
    "addr:housenumber":"33",
    "addr:postcode":"madrid;28023",
    "addr:street":"Calle De Ana Teresa",
    "iso:country":"ES",
    "sg:address":"Calle de Ana Teresa, 33",
    "sg:city":"Madrid",
    "sg:orig_category":"Centros Empresariales",
    "sg:phone":"+34 913 07 94 72",
    "sg:postcode":"28023",
    "sg:province":"Madrid",
    "wof:name":"Colima Consultores S.l.",
    "wof:placetype":"venue"
},
  "geometry": {"coordinates":[-3.7848126888,40.4613227844],"type":"Point"}
}