{
  "type": "Feature",
  "properties": {
    "iso:country":"ES",
    "sg:address":"Ctra Alicante, 53",
    "sg:city":"Barrio Del Puente De La Muleta",
    "sg:orig_category":"Electrodom\u00c9sticos (al Por Menor)",
    "sg:phone":"+34 968 24 90 43",
    "sg:postcode":"30007",
    "sg:province":"Murcia",
    "wof:name":"Comercial Parraga S.l.",
    "wof:placetype":"venue"
},
  "geometry": {"coordinates":[-1.1157979965,37.9952926636],"type":"Point"}
}