{
  "type": "Feature",
  "properties": {
    "iso:country":"ES",
    "sg:address":"Calle de San Francisco, 30",
    "sg:city":"Donostia-san Sebastian",
    "sg:orig_category":"Carnicer\u00cdas, Carnicer\u00cdas",
    "sg:phone":"+34 943 27 24 19",
    "sg:postcode":"20002",
    "sg:province":"Guip\u00f9zcoa",
    "wof:name":"Eraso Oliva Jose Ignacio",
    "wof:placetype":"venue"
},
  "geometry": {"coordinates":[-1.9728989601,43.3243484497],"type":"Point"}
}