{
  "type": "Feature",
  "properties": {
    "iso:country":"ES",
    "sg:address":"Carrer de Torrent De L'olla, 55",
    "sg:city":"Barcelona",
    "sg:orig_category":"Cueros Y Pieles (al Por Mayor)",
    "sg:phone":"+34 932 18 92 85",
    "sg:postcode":"08012",
    "sg:province":"Barcelona",
    "wof:name":"Ribas Vilabru Jose",
    "wof:placetype":"venue"
},
  "geometry": {"coordinates":[2.1592292786,41.4004898071],"type":"Point"}
}