{
  "type": "Feature",
  "properties": {
    "iso:country":"ES",
    "sg:address":"Carr Nou, 50",
    "sg:city":"Mercadal",
    "sg:classifiers":[
        {
            "category":"Autos & Motor Vehicles",
            "subcategory":"Automobile Sales",
            "type":"Retail Goods"
        }
    ],
    "sg:phone":"+34 971 37 50 50",
    "sg:postcode":"07740",
    "sg:province":"Islas Baleares",
    "wof:name":"Febrer Coll Juana",
    "wof:placetype":"venue"
},
  "geometry": {"coordinates":[4.0921797752,39.9863700867],"type":"Point"}
}