{
  "type": "Feature",
  "properties": {
    "iso:country":"ES",
    "sg:address":"Calle de Puerto De La Bonaigua, 44",
    "sg:city":"Madrid",
    "sg:orig_category":"Puertas Y Portales",
    "sg:phone":"+34 914 77 93 30",
    "sg:postcode":"28018",
    "sg:province":"Madrid",
    "sg:website":"www.qdq.com",
    "wof:name":"Ferrera Garcia Rosario",
    "wof:placetype":"venue"
},
  "geometry": {"coordinates":[-3.6651968956,40.386592865],"type":"Point"}
}