{
  "type": "Feature",
  "properties": {
    "addr:full":"Avda Andalucia (de), 135 Valdemoro Madrid 28340",
    "addr:housenumber":"135",
    "addr:postcode":"28340",
    "addr:street":"Avda Andalucia De",
    "iso:country":"ES",
    "sg:address":"Avda Andalucia (de), 135",
    "sg:city":"Valdemoro",
    "sg:orig_category":"Fabricaci\u00d3n De Etiquetas",
    "sg:phone":"+34 918 95 11 32",
    "sg:postcode":"28340",
    "sg:province":"Madrid",
    "wof:name":"Servicios Dam S.a.",
    "wof:placetype":"venue"
},
  "geometry": {"coordinates":[-3.6816630363,40.2081413269],"type":"Point"}
}