{
  "type": "Feature",
  "properties": {
    "iso:country":"ES",
    "sg:address":"Calle de Santo Tome, 25",
    "sg:city":"Toledo",
    "sg:orig_category":"Artesan\u00cda",
    "sg:phone":"+34 925 25 06 23",
    "sg:postcode":"45002",
    "sg:province":"Toledo",
    "wof:name":"San Jose Santos Luz Divina",
    "wof:placetype":"venue"
},
  "geometry": {"coordinates":[-4.0283298492,39.856967926],"type":"Point"}
}