{
  "type": "Feature",
  "properties": {
    "iso:country":"ES",
    "sg:address":"Calle de Escuelas, 2",
    "sg:city":"Albalat Dels Sorells",
    "sg:orig_category":"Pescader\u00cdas (al Por Menor)",
    "sg:phone":"+34 961 49 43 03",
    "sg:postcode":"46135",
    "sg:province":"Valencia",
    "wof:name":"Crespo Ronquillo Consuelo",
    "wof:placetype":"venue"
},
  "geometry": {"coordinates":[-0.3387640119,39.5539360046],"type":"Point"}
}