{
  "type": "Feature",
  "properties": {
    "addr:full":"Carrer de Poetes Bertran (dels), 34 Canonja Tarragona 43110",
    "addr:housenumber":"34",
    "addr:postcode":"43110",
    "addr:street":"Carrer De Poetes Bertran Dels",
    "iso:country":"ES",
    "sg:address":"Carrer de Poetes Bertran (dels), 34",
    "sg:city":"Canonja",
    "sg:orig_category":"Arquitectos",
    "sg:phone":"+34 977 54 17 39",
    "sg:postcode":"43110",
    "sg:province":"Tarragona",
    "wof:name":"Arroyo Castro Juan Manuel",
    "wof:placetype":"venue"
},
  "geometry": {"coordinates":[1.1821036339,41.1202545166],"type":"Point"}
}