{
  "type": "Feature",
  "properties": {
    "iso:country":"ES",
    "sg:address":"Calle de Solana, 17",
    "sg:city":"Priego Cordoba",
    "sg:orig_category":"Bisuter\u00cda, Joyer\u00cda, Relojer\u00cda (al Por Menor)",
    "sg:phone":"+34 957 54 32 85",
    "sg:postcode":"14800",
    "sg:province":"C\u00f3rdoba",
    "wof:name":"Porras Wic C.b.",
    "wof:placetype":"venue"
},
  "geometry": {"coordinates":[-4.1938881874,37.4391708374],"type":"Point"}
}