{
  "type": "Feature",
  "properties": {
    "iso:country":"ES",
    "sg:address":"Avda Plata, 10",
    "sg:city":"Valencia",
    "sg:orig_category":"Asociaciones, Organismos Culturales Y Socioeducativos",
    "sg:phone":"+34 963 73 82 99",
    "sg:postcode":"46013",
    "sg:province":"Valencia",
    "wof:name":"Centro Juvenil Entre Amics",
    "wof:placetype":"venue"
},
  "geometry": {"coordinates":[-0.3702929914,39.4531402588],"type":"Point"}
}