{
  "type": "Feature",
  "properties": {
    "iso:country":"ES",
    "sg:address":"Calle de Gerardo Diego, 14",
    "sg:city":"Alcala Henares",
    "sg:orig_category":"Inform\u00c1tica, Ofim\u00c1tica (estudios, Asesor\u00cda, Ingenier\u00cda, Formaci\u00d3n)",
    "sg:phone":"+34 918 30 19 43",
    "sg:postcode":"28806",
    "sg:province":"Madrid",
    "wof:name":"Escobar Albarran Manuel",
    "wof:placetype":"venue"
},
  "geometry": {"coordinates":[-3.3738090992,40.4954185486],"type":"Point"}
}