{
  "type": "Feature",
  "properties": {
    "addr:full":"Carrer de Doctor Robert, 25 Santa Perpetua De Mogoda Barcelona 08130",
    "addr:housenumber":"25",
    "addr:postcode":"08130",
    "addr:street":"Carrer De Doctor Robert",
    "iso:country":"ES",
    "sg:address":"Carrer de Doctor Robert, 25",
    "sg:city":"Santa Perpetua De Mogoda",
    "sg:orig_category":"Cr\u00cda De Animales",
    "sg:phone":"+34 935 60 12 18",
    "sg:postcode":"08130",
    "sg:province":"Barcelona",
    "wof:name":"Jansana Humet Roser",
    "wof:placetype":"venue"
},
  "geometry": {"coordinates":[2.182986021,41.5333824158],"type":"Point"}
}