{
  "type": "Feature",
  "properties": {
    "addr:full":"Calle de Nu\u00d1ez De Balboa, 14 Jaen Ja\u00e9n 23007",
    "addr:housenumber":"14;jae\u0301n",
    "addr:postcode":"23007",
    "addr:street":"Calle De Nun\u0303Ez De Balboa",
    "iso:country":"ES",
    "sg:address":"Calle de Nu\u00d1ez De Balboa, 14",
    "sg:city":"Jaen",
    "sg:orig_category":"Peluqueros: De Se\u00d1oras",
    "sg:phone":"+34 953 27 63 80",
    "sg:postcode":"23007",
    "sg:province":"Ja\u00e9n",
    "wof:name":"Garzon Montesinos Maria Amparo",
    "wof:placetype":"venue"
},
  "geometry": {"coordinates":[-3.7933790684,37.7738418579],"type":"Point"}
}