{
  "type": "Feature",
  "properties": {
    "addr:full":"Calle de Antonio Reyes Huertas, 10 Caceres C\u00e1ceres 10002",
    "addr:housenumber":"10",
    "addr:postcode":"10002",
    "addr:street":"Calle De Antonio Reyes Huertas;Ca\u0301Ceres",
    "iso:country":"ES",
    "sg:address":"Calle de Antonio Reyes Huertas, 10",
    "sg:city":"Caceres",
    "sg:orig_category":"Ense\u00d1anza: Idiomas",
    "sg:phone":"+34 927 21 27 21",
    "sg:postcode":"10002",
    "sg:province":"C\u00e1ceres",
    "wof:name":"Pimienta Rojas Maria Dolores",
    "wof:placetype":"venue"
},
  "geometry": {"coordinates":[-6.3753151894,39.4682044983],"type":"Point"}
}