{
  "type": "Feature",
  "properties": {
    "addr:full":"Pase Reyes, De Los, 15 Isla Cristina Huelva 21410",
    "addr:postcode":"21410",
    "iso:country":"ES",
    "sg:address":"Pase Reyes, De Los, 15",
    "sg:city":"Isla Cristina",
    "sg:orig_category":"Panader\u00cdas, Panader\u00cdas",
    "sg:phone":"+34 959 33 05 48",
    "sg:postcode":"21410",
    "sg:province":"Huelva",
    "wof:name":"Martin Colume Joaquin",
    "wof:placetype":"venue"
},
  "geometry": {"coordinates":[-7.3203940392,37.2019615173],"type":"Point"}
}