{
  "type": "Feature",
  "properties": {
    "iso:country":"ES",
    "sg:address":"Calle de Juan Ramon Jimenez, S/n",
    "sg:city":"Tauste",
    "sg:orig_category":"Material Y Herramientas Agr\u00cdcolas",
    "sg:phone":"+34 976 85 92 47",
    "sg:postcode":"50660",
    "sg:province":"Zaragoza",
    "wof:name":"Brun Maquinaria Agricola S.l.",
    "wof:placetype":"venue"
},
  "geometry": {"coordinates":[-1.2559490204,41.9236946106],"type":"Point"}
}