{
  "type": "Feature",
  "properties": {
    "iso:country":"ES",
    "sg:address":"Calle de Huelva, 119",
    "sg:city":"Ayamonte",
    "sg:orig_category":"Fabricaci\u00d3n, Reparaci\u00d3n Y Mantenimiento De Construcciones Navales Y Fluviales",
    "sg:phone":"+34 959 32 02 69",
    "sg:postcode":"21400",
    "sg:province":"Huelva",
    "wof:name":"Santos Rodriguez Juan De Los",
    "wof:placetype":"venue"
},
  "geometry": {"coordinates":[-7.4022231102,37.2144508362],"type":"Point"}
}