{
  "type": "Feature",
  "properties": {
    "addr:full":"Calle de Francisco Capilla, 10 Albolote Granada 18220",
    "addr:housenumber":"10",
    "addr:postcode":"18220",
    "addr:street":"Calle De Francisco Capilla",
    "iso:country":"ES",
    "sg:address":"Calle de Francisco Capilla, 10",
    "sg:city":"Albolote",
    "sg:orig_category":"Limpieza Con Chorro De Arena Y Con Granalla, Pulido",
    "sg:phone":"+34 958 46 83 74",
    "sg:postcode":"18220",
    "sg:province":"Granada",
    "wof:name":"Caballero Fuentes Maria Isabel",
    "wof:placetype":"venue"
},
  "geometry": {"coordinates":[-3.6513230801,37.2317008972],"type":"Point"}
}