{
  "type": "Feature",
  "properties": {
    "iso:country":"ES",
    "sg:address":"Avda Blas Infante, 21",
    "sg:city":"Mairena Alcor",
    "sg:orig_category":"Almazaras",
    "sg:phone":"+34 955 94 33 43",
    "sg:postcode":"41510",
    "sg:province":"Sevilla",
    "wof:name":"Comainox S.l.",
    "wof:placetype":"venue"
},
  "geometry": {"coordinates":[-5.7547721863,37.3672828674],"type":"Point"}
}