{
  "type": "Feature",
  "properties": {
    "addr:full":"Avda Duque De Najera, 6 Cadiz C\u00e1diz 11002",
    "addr:housenumber":"6",
    "addr:postcode":"11002",
    "addr:street":"Avda Duque De Najera",
    "iso:country":"ES",
    "sg:address":"Avda Duque De Najera, 6",
    "sg:city":"Cadiz",
    "sg:orig_category":"Caf\u00c9s, Bares, Cervecer\u00cdas",
    "sg:phone":"+34 956 22 81 08",
    "sg:postcode":"11002",
    "sg:province":"C\u00e1diz",
    "wof:name":"Jesus Manuel Perez Jimenez S.l",
    "wof:placetype":"venue"
},
  "geometry": {"coordinates":[-6.304954052,36.5301589966],"type":"Point"}
}