{
  "type": "Feature",
  "properties": {
    "addr:full":"Carrer de Consell De Cent, 448 Barcelona Barcelona 08013",
    "addr:housenumber":"448",
    "addr:postcode":"08013",
    "addr:street":"Carrer De Consell De Cent",
    "iso:country":"ES",
    "sg:address":"Carrer de Consell De Cent, 448",
    "sg:city":"Barcelona",
    "sg:orig_category":"Restaurantes",
    "sg:phone":"+34 932 31 38 12",
    "sg:postcode":"08013",
    "sg:province":"Barcelona",
    "wof:name":"Martinez Enriquez Sabino",
    "wof:placetype":"venue"
},
  "geometry": {"coordinates":[2.1759490967,41.3985862732],"type":"Point"}
}