{
  "type": "Feature",
  "properties": {
    "iso:country":"ES",
    "sg:address":"Calle de Castillo, 32",
    "sg:city":"Castillo",
    "sg:orig_category":"Asesor\u00cda Sobre Comunicaci\u00d3n De Empresas",
    "sg:phone":"+34 916 56 11 04",
    "sg:postcode":"28850",
    "sg:province":"Madrid",
    "wof:name":"General De Servicios Decalco S.l.",
    "wof:placetype":"venue"
},
  "geometry": {"coordinates":[-3.4728546143,40.4360313416],"type":"Point"}
}