{
  "type": "Feature",
  "properties": {
    "addr:full":"Calle de Tulipan, 12 Humanes De Madrid Madrid 28970",
    "addr:housenumber":"12",
    "addr:postcode":"28970",
    "addr:street":"Calle De Tulipan",
    "iso:country":"ES",
    "sg:address":"Calle de Tulipan, 12",
    "sg:city":"Humanes De Madrid",
    "sg:orig_category":"Empresas De Carpinter\u00cda De Madera",
    "sg:phone":"+34 916 90 07 61",
    "sg:postcode":"28970",
    "sg:province":"Madrid",
    "wof:name":"Base Decoracion Y Dise\u00f1o S.l.",
    "wof:placetype":"venue"
},
  "geometry": {"coordinates":[-3.8387880325,40.2685585022],"type":"Point"}
}