{
  "type": "Feature",
  "properties": {
    "addr:full":"Carrer de Miquel Sants Olive, 4 Palma Islas Baleares 07011",
    "addr:housenumber":"4",
    "addr:postcode":"07011",
    "addr:street":"Carrer De Miquel Sants Olive",
    "iso:country":"ES",
    "sg:address":"Carrer de Miquel Sants Olive, 4",
    "sg:city":"Palma",
    "sg:orig_category":"Asociaciones Y Clubs Deportivos",
    "sg:phone":"+34 971 73 03 19",
    "sg:postcode":"07011",
    "sg:province":"Islas Baleares",
    "wof:name":"Veloz Sport Balear",
    "wof:placetype":"venue"
},
  "geometry": {"coordinates":[2.6436719894,39.578338623],"type":"Point"}
}