{
  "type": "Feature",
  "properties": {
    "addr:full":"Camino Nuevo, 5 Nules Castell\u00f3n 12520",
    "addr:housenumber":"5",
    "addr:postcode":"12520",
    "addr:street":"Camino Nuevo",
    "iso:country":"ES",
    "sg:address":"Camino Nuevo, 5",
    "sg:city":"Nules",
    "sg:orig_category":"Arboricultura Y Producci\u00d3n De Frutas",
    "sg:phone":"+34 964 67 31 93",
    "sg:postcode":"12520",
    "sg:province":"Castell\u00f3n",
    "wof:name":"Agribur S.l.",
    "wof:placetype":"venue"
},
  "geometry": {"coordinates":[-0.1448819935,39.8475914001],"type":"Point"}
}