{
  "type": "Feature",
  "properties": {
    "iso:country":"ES",
    "sg:address":"Rbla General Franco, 82",
    "sg:city":"Santa Cruz De Tenerife",
    "sg:orig_category":"Asilos De Ancianos. Centros Privados",
    "sg:phone":"+34 922 27 41 83",
    "sg:postcode":"38004",
    "sg:province":"Santa Cruz De Tenerife",
    "wof:name":"Centro Residencial Tenerife S.l.",
    "wof:placetype":"venue"
},
  "geometry": {"coordinates":[-16.2564601898,28.4795894623],"type":"Point"}
}