{
  "type": "Feature",
  "properties": {
    "addr:full":"Carrer de Faisa, 7 Son Ferrer Islas Baleares 07182",
    "addr:housenumber":"7",
    "addr:postcode":"07182",
    "addr:street":"Carrer De Faisa",
    "iso:country":"ES",
    "sg:address":"Carrer de Faisa, 7",
    "sg:city":"Son Ferrer",
    "sg:orig_category":"Promotores Constructores",
    "sg:phone":"+34 971 23 81 56",
    "sg:postcode":"07182",
    "sg:province":"Islas Baleares",
    "wof:name":"Construcciones Benites 34 S L U",
    "wof:placetype":"venue"
},
  "geometry": {"coordinates":[2.4987950325,39.4970779419],"type":"Point"}
}