{
  "type": "Feature",
  "properties": {
    "iso:country":"ES",
    "sg:address":"Calle de Urbieta, 38",
    "sg:city":"Donostia-san Sebastian",
    "sg:orig_category":"Asociaciones, Organismos Culturales Y Socioeducativos",
    "sg:phone":"+34 943 47 31 08",
    "sg:postcode":"20006",
    "sg:province":"Guip\u00f9zcoa",
    "wof:name":"Larrunarri Eskaut-gia Arduradun Heskuntza Eskola",
    "wof:placetype":"venue"
},
  "geometry": {"coordinates":[-1.9822700024,43.3160400391],"type":"Point"}
}