{
  "type": "Feature",
  "properties": {
    "iso:country":"ES",
    "sg:address":"Eix Transversal, Km. 0024,9",
    "sg:city":"Manresa",
    "sg:orig_category":"Distribuci\u00d3n De Petr\u00d3leo Y Derivados",
    "sg:phone":"+34 938 72 47 06",
    "sg:postcode":"08242",
    "sg:province":"Barcelona",
    "sg:website":"www.cepsa.es",
    "wof:name":"Cedipsa Compa\u00d1ia Espa\u00d1ola Distribuidora De Petroleos S.a.",
    "wof:placetype":"venue"
},
  "geometry": {"coordinates":[1.8054080009,41.7362213135],"type":"Point"}
}