{
  "type": "Feature",
  "properties": {
    "iso:country":"ES",
    "sg:address":"Calle de Uruguay, 31",
    "sg:city":"Madrid",
    "sg:classifiers":[
        {
            "category":"Professional",
            "subcategory":"Management & Consulting",
            "type":"Services"
        }
    ],
    "sg:phone":"+34 914 16 44 01",
    "sg:postcode":"28016",
    "sg:province":"Madrid",
    "sg:tags":[
        "asesor\u00cda",
        "en",
        "marketing"
    ],
    "wof:name":"Development Of Animal Nutrition S.l.",
    "wof:placetype":"venue"
},
  "geometry": {"coordinates":[-3.6720499992,40.45520401],"type":"Point"}
}