{
  "type": "Feature",
  "properties": {
    "addr:full":"Calle de Calderon De La Barca, S/n Benamaurel Granada 18817",
    "addr:housenumber":"s / n",
    "addr:postcode":"18817",
    "addr:street":"Calle De Calderon De La Barca",
    "iso:country":"ES",
    "sg:address":"Calle de Calderon De La Barca, S/n",
    "sg:city":"Benamaurel",
    "sg:orig_category":"Charcuter\u00cdas (al Por Mayor)",
    "sg:phone":"+34 958 73 32 13",
    "sg:postcode":"18817",
    "sg:province":"Granada",
    "wof:name":"Trabalon Garcia Bartolome",
    "wof:placetype":"venue"
},
  "geometry": {"coordinates":[-2.7030470371,37.6074790955],"type":"Point"}
}