{
  "type": "Feature",
  "properties": {
    "iso:country":"ES",
    "sg:address":"Luga Finca Piedra Hincada, S/n",
    "sg:city":"Playa San Juan",
    "sg:orig_category":"Semiller\u00cdas",
    "sg:phone":"+34 922 85 75 00",
    "sg:postcode":"38687",
    "sg:province":"Santa Cruz De Tenerife",
    "wof:name":"Viveros Isora S.l.",
    "wof:placetype":"venue"
},
  "geometry": {"coordinates":[-16.6504669189,28.3946437836],"type":"Point"}
}