{
  "type": "Feature",
  "properties": {
    "iso:country":"ES",
    "sg:address":"Avda Ferrol, 37",
    "sg:city":"Pontedeume",
    "sg:orig_category":"Empresas De Carpinter\u00cda De Madera",
    "sg:phone":"+34 981 43 02 58",
    "sg:postcode":"15600",
    "sg:province":"La Coru\u00f1a",
    "wof:name":"Carpinteria Canosa S.l.",
    "wof:placetype":"venue"
},
  "geometry": {"coordinates":[-8.1745119095,43.4087600708],"type":"Point"}
}