{
  "type": "Feature",
  "properties": {
    "iso:country":"ES",
    "sg:address":"Calle de Gallo, 8",
    "sg:city":"Valladolid",
    "sg:orig_category":"Electricidad: Instaladores",
    "sg:phone":"+34 983 29 74 33",
    "sg:postcode":"47012",
    "sg:province":"Valladolid",
    "wof:name":"Perez Perez Jesus Carlos",
    "wof:placetype":"venue"
},
  "geometry": {"coordinates":[-4.7090368271,41.6456222534],"type":"Point"}
}