{
  "type": "Feature",
  "properties": {
    "iso:country":"ES",
    "sg:address":"Calle de Embajadores, 114",
    "sg:city":"Madrid",
    "sg:orig_category":"Agencias De Viajes",
    "sg:phone":"+34 915 17 14 15",
    "sg:postcode":"28045",
    "sg:province":"Madrid",
    "sg:website":"www.barceloviajes.com",
    "wof:name":"Viajes Crisol S A",
    "wof:placetype":"venue"
},
  "geometry": {"coordinates":[-3.6987800598,40.3999137878],"type":"Point"}
}