{
  "type": "Feature",
  "properties": {
    "iso:country":"ES",
    "sg:address":"Pg Maragall, 199",
    "sg:city":"Barcelona",
    "sg:orig_category":"Muebles Y Accesorios Para Cocinas Y Cuartos De Ba\u00d1o (al Por Menor)",
    "sg:phone":"+34 933 52 09 11",
    "sg:postcode":"08041",
    "sg:province":"Barcelona",
    "wof:name":"Cercuines S.l.",
    "wof:placetype":"venue"
},
  "geometry": {"coordinates":[2.1771969795,41.424079895],"type":"Point"}
}