{
  "type": "Feature",
  "properties": {
    "iso:country":"ES",
    "sg:address":"Calle de Uranzu, 20",
    "sg:city":"Irun",
    "sg:orig_category":"Zapatos (al Por Menor)",
    "sg:phone":"+34 943 62 28 20",
    "sg:postcode":"20304",
    "sg:province":"Guip\u00f9zcoa",
    "wof:name":"Calzados Herrero C.b.",
    "wof:placetype":"venue"
},
  "geometry": {"coordinates":[-1.7836179733,43.3384170532],"type":"Point"}
}