{
  "type": "Feature",
  "properties": {
    "addr:full":"Calle de Antonio Huertas Remigio, 13 Maracena Granada 18200",
    "addr:housenumber":"13",
    "addr:postcode":"18200",
    "addr:street":"Calle De Antonio Huertas Remigio",
    "iso:country":"ES",
    "sg:address":"Calle de Antonio Huertas Remigio, 13",
    "sg:city":"Maracena",
    "sg:orig_category":"Telas Y Sedas (al Por Menor)",
    "sg:phone":"+34 958 41 00 24",
    "sg:postcode":"18200",
    "sg:province":"Granada",
    "wof:name":"F. Linares Textifarma S.l.",
    "wof:placetype":"venue"
},
  "geometry": {"coordinates":[-3.6444261074,37.2021827698],"type":"Point"}
}