{
  "type": "Feature",
  "properties": {
    "addr:full":"Coiros De Abajo, 15 Coiros De Abajo La Coru\u00f1a 15316",
    "addr:housenumber":"15",
    "addr:postcode":"15316",
    "addr:street":"Abajo;Corun\u0303A",
    "iso:country":"ES",
    "sg:address":"Coiros De Abajo, 15",
    "sg:city":"Coiros De Abajo",
    "sg:orig_category":"Carpinteros",
    "sg:phone":"+34 981 79 63 46",
    "sg:postcode":"15316",
    "sg:province":"La Coru\u00f1a",
    "wof:name":"Brigalum S.l.",
    "wof:placetype":"venue"
},
  "geometry": {"coordinates":[-8.1742801666,43.2545852661],"type":"Point"}
}