{
  "type": "Feature",
  "properties": {
    "addr:full":"Calle de Ibiza, 15 San Sebastian De Los Reyes Madrid 28700",
    "addr:housenumber":"15",
    "addr:postcode":"28700",
    "addr:street":"Calle De Ibiza",
    "iso:country":"ES",
    "sg:address":"Calle de Ibiza, 15",
    "sg:city":"San Sebastian De Los Reyes",
    "sg:orig_category":"Agentes, Concesionarios Y Sucursales De Veh\u00cdculos",
    "sg:phone":"+34 916 63 60 09",
    "sg:postcode":"28700",
    "sg:province":"Madrid",
    "wof:name":"Talleres Cielo S.l.",
    "wof:placetype":"venue"
},
  "geometry": {"coordinates":[-3.6250429153,40.5569953918],"type":"Point"}
}