{
  "type": "Feature",
  "properties": {
    "iso:country":"ES",
    "sg:address":"Calle de Marquesa Viuda De Aldama (de La), 10",
    "sg:city":"Alcobendas",
    "sg:orig_category":"Cl\u00cdnicas M\u00c9dicas",
    "sg:phone":"+34 916 51 69 73",
    "sg:postcode":"28100",
    "sg:province":"Madrid",
    "wof:name":"Centro Medico Alcobendas",
    "wof:placetype":"venue"
},
  "geometry": {"coordinates":[-3.6330449581,40.5410995483],"type":"Point"}
}