{
  "type": "Feature",
  "properties": {
    "addr:full":"Calle de Santa Barbara, 31 Majadahonda Madrid 28220",
    "addr:housenumber":"31",
    "addr:postcode":"28220",
    "addr:street":"Calle De Santa Barbara",
    "iso:country":"ES",
    "sg:address":"Calle de Santa Barbara, 31",
    "sg:city":"Majadahonda",
    "sg:orig_category":"Semiller\u00cdas",
    "sg:phone":"+34 916 38 42 26",
    "sg:postcode":"28220",
    "sg:province":"Madrid",
    "wof:name":"V.duran Jardineria S.l.",
    "wof:placetype":"venue"
},
  "geometry": {"coordinates":[-3.8679571152,40.4694786072],"type":"Point"}
}