{
  "type": "Feature",
  "properties": {
    "addr:full":"Carrer de Valencia, 565 Barcelona Barcelona 08026",
    "addr:housenumber":"565",
    "addr:postcode":"08026",
    "addr:street":"Carrer De Valencia",
    "iso:country":"ES",
    "sg:address":"Carrer de Valencia, 565",
    "sg:city":"Barcelona",
    "sg:orig_category":"Monedas, Medallas",
    "sg:phone":"+34 932 31 11 62",
    "sg:postcode":"08026",
    "sg:province":"Barcelona",
    "wof:name":"Vera Ceballos Nicolas",
    "wof:placetype":"venue"
},
  "geometry": {"coordinates":[2.1831018925,41.4077568054],"type":"Point"}
}