{
  "type": "Feature",
  "properties": {
    "iso:country":"ES",
    "sg:address":"Urbanizacion Atalaya, 4",
    "sg:city":"Cadrete",
    "sg:orig_category":"Fabricaci\u00d3n, Instalaci\u00d3n De Contadores",
    "sg:phone":"+34 976 12 53 24",
    "sg:postcode":"50420",
    "sg:province":"Zaragoza",
    "wof:name":"Gimenez Solsona Armando",
    "wof:placetype":"venue"
},
  "geometry": {"coordinates":[-0.9601830244,41.5556411743],"type":"Point"}
}