{
  "type": "Feature",
  "properties": {
    "addr:full":"Carr Major, 54 Sort Lleida 25560",
    "addr:housenumber":"54",
    "addr:postcode":"25560",
    "addr:street":"Carr Major",
    "iso:country":"ES",
    "sg:address":"Carr Major, 54",
    "sg:city":"Sort",
    "sg:orig_category":"Quincaller\u00cda (al Por Menor)",
    "sg:phone":"+34 973 62 08 51",
    "sg:postcode":"25560",
    "sg:province":"Lleida",
    "wof:name":"Escur Pujol Aleix",
    "wof:placetype":"venue"
},
  "geometry": {"coordinates":[1.131188035,42.412651062],"type":"Point"}
}