{
  "type": "Feature",
  "properties": {
    "addr:full":"Av Espanya, 111 Eixample Barcelona 08150",
    "addr:housenumber":"111",
    "addr:postcode":"08150",
    "addr:street":"Av Espanya",
    "iso:country":"ES",
    "sg:address":"Av Espanya, 111",
    "sg:city":"Eixample",
    "sg:orig_category":"Electricidad: Instaladores",
    "sg:phone":"+34 935 62 36 26",
    "sg:postcode":"08150",
    "sg:province":"Barcelona",
    "wof:name":"Lopez Barrera Jose",
    "wof:placetype":"venue"
},
  "geometry": {"coordinates":[2.2293000221,41.5678787231],"type":"Point"}
}