{
  "type": "Feature",
  "properties": {
    "iso:country":"ES",
    "sg:address":"Calle de Greco, 3",
    "sg:city":"Salamanca",
    "sg:orig_category":"Electricidad: Equipos Industriales, Componentes (fabricaci\u00d3n)",
    "sg:phone":"+34 923 12 50 04",
    "sg:postcode":"37004",
    "sg:province":"Salamanca",
    "wof:name":"Comercial Hispanofil S.a.",
    "wof:placetype":"venue"
},
  "geometry": {"coordinates":[-5.6534500122,40.9722938538],"type":"Point"}
}