{
  "type": "Feature",
  "properties": {
    "addr:full":"Calle de Granada, S/n Loja Granada 18300",
    "addr:housenumber":"/ n loja",
    "addr:postcode":"18300",
    "addr:street":"Calle De Granada S",
    "iso:country":"ES",
    "sg:address":"Calle de Granada, S/n",
    "sg:city":"Loja",
    "sg:orig_category":"Ropa Para Ni\u00d1os (al Por Menor)",
    "sg:phone":"+34 958 32 72 37",
    "sg:postcode":"18300",
    "sg:province":"Granada",
    "wof:name":"Calvo Yelamo Maria Jose",
    "wof:placetype":"venue"
},
  "geometry": {"coordinates":[-4.1466040611,37.1655883789],"type":"Point"}
}