{
  "type": "Feature",
  "properties": {
    "addr:full":"Argenters, 11 Pol. Ind. Santiga Barcelona 08130",
    "addr:housenumber":"11",
    "addr:postcode":"08130",
    "addr:street":"Argenters;Pol. Ind. Santiga",
    "iso:country":"ES",
    "sg:address":"Argenters, 11",
    "sg:city":"Pol. Ind. Santiga",
    "sg:orig_category":"M\u00c1rmoles, Granitos Y Piedras Naturales",
    "sg:phone":"+34 937 19 19 58",
    "sg:postcode":"08130",
    "sg:province":"Barcelona",
    "wof:name":"Marmoles Agusti E Hijos S.l.",
    "wof:placetype":"venue"
},
  "geometry": {"coordinates":[2.1802799702,41.5371818542],"type":"Point"}
}