{
  "type": "Feature",
  "properties": {
    "iso:country":"ES",
    "sg:address":"Calle de Pascual Martinez, 47",
    "sg:city":"Redovan",
    "sg:orig_category":"Carnicer\u00cdas, Carnicer\u00cdas",
    "sg:phone":"+34 966 75 41 11",
    "sg:postcode":"03370",
    "sg:province":"Alicante",
    "wof:name":"Carniceria Maria Jesus S.l.",
    "wof:placetype":"venue"
},
  "geometry": {"coordinates":[-0.9103400111,38.1157226562],"type":"Point"}
}