{
  "type": "Feature",
  "properties": {
    "iso:country":"ES",
    "sg:address":"Calle de Castelar, 49",
    "sg:city":"Santander",
    "sg:orig_category":"Ropa Para Se\u00d1oras (al Por Menor)",
    "sg:phone":"+34 942 31 16 74",
    "sg:postcode":"39004",
    "sg:province":"Cantabria",
    "wof:name":"Morante Va\u00f1es Margarita",
    "wof:placetype":"venue"
},
  "geometry": {"coordinates":[-3.7900078297,43.4634208679],"type":"Point"}
}