{
  "type": "Feature",
  "properties": {
    "iso:country":"ES",
    "sg:address":"Avda San Agustin, 18",
    "sg:city":"Mayorga",
    "sg:orig_category":"Ambulancias",
    "sg:phone":"+34 983 75 20 41",
    "sg:postcode":"47680",
    "sg:province":"Valladolid",
    "sg:website":"www.ambuiberica.com",
    "wof:name":"Ambulancias Valladolid S. A.",
    "wof:placetype":"venue"
},
  "geometry": {"coordinates":[-5.2688484192,42.1640548706],"type":"Point"}
}