{
  "type": "Feature",
  "properties": {
    "iso:country":"ES",
    "sg:address":"Calle de Calatrava, 27",
    "sg:city":"S. Fernando",
    "sg:orig_category":"Bisuter\u00cda, Joyer\u00cda, Relojer\u00cda (al Por Menor)",
    "sg:phone":"+34 956 89 20 88",
    "sg:postcode":"11100",
    "sg:province":"C\u00e1diz",
    "wof:name":"Cabeza Perez Pedro",
    "wof:placetype":"venue"
},
  "geometry": {"coordinates":[-6.1966490746,36.4708099365],"type":"Point"}
}