{
  "type": "Feature",
  "properties": {
    "addr:full":"Carr Cami De Corbins, 18 Lleida Lleida 25005",
    "addr:housenumber":"18",
    "addr:postcode":"25005",
    "addr:street":"Carr Cami De Corbins",
    "iso:country":"ES",
    "sg:address":"Carr Cami De Corbins, 18",
    "sg:city":"Lleida",
    "sg:orig_category":"Florister\u00cdas",
    "sg:phone":"+34 973 22 51 82",
    "sg:postcode":"25005",
    "sg:province":"Lleida",
    "wof:name":"Flors Sanmartinet S.l.",
    "wof:placetype":"venue"
},
  "geometry": {"coordinates":[0.6353209019,41.6236534119],"type":"Point"}
}