{
  "type": "Feature",
  "properties": {
    "addr:full":"Rbla Josep Tomas Ventosa, 18 Vilanova I La Geltru Barcelona 08800",
    "addr:housenumber":"18",
    "addr:postcode":"08800",
    "addr:street":"Rbla Josep Tomas Ventosa",
    "iso:country":"ES",
    "sg:address":"Rbla Josep Tomas Ventosa, 18",
    "sg:city":"Vilanova I La Geltru",
    "sg:orig_category":"Cr\u00cda De Animales",
    "sg:phone":"+34 938 93 82 32",
    "sg:postcode":"08800",
    "sg:province":"Barcelona",
    "wof:name":"Puig Vila Luis",
    "wof:placetype":"venue"
},
  "geometry": {"coordinates":[1.7279280424,41.2215385437],"type":"Point"}
}