{
  "type": "Feature",
  "properties": {
    "addr:full":"Avda Reyes Catolicos, 4 Burgos Burgos 09004",
    "addr:housenumber":"4",
    "addr:postcode":"09004",
    "addr:street":"Avda Reyes Catolicos",
    "iso:country":"ES",
    "sg:address":"Avda Reyes Catolicos, 4",
    "sg:city":"Burgos",
    "sg:orig_category":"Abogados",
    "sg:phone":"+34 947 26 73 41",
    "sg:postcode":"09004",
    "sg:province":"Burgos",
    "wof:name":"Garcia Larrouy Jose Luis",
    "wof:placetype":"venue"
},
  "geometry": {"coordinates":[-3.6960508823,42.3442344666],"type":"Point"}
}