{
  "type": "Feature",
  "properties": {
    "addr:full":"Calle de Leopoldo Alas, 3 Gijon Asturias 33204",
    "addr:housenumber":"3",
    "addr:postcode":"33204",
    "addr:street":"Calle De Leopoldo Alas",
    "iso:country":"ES",
    "sg:address":"Calle de Leopoldo Alas, 3",
    "sg:city":"Gijon",
    "sg:orig_category":"Agencias Y Agentes Comerciales, Representantes",
    "sg:phone":"+34 985 33 17 52",
    "sg:postcode":"33204",
    "sg:province":"Asturias",
    "wof:name":"Confecciones Y Manufacturas Castilla S.l.",
    "wof:placetype":"venue"
},
  "geometry": {"coordinates":[-5.6522059441,43.5367584229],"type":"Point"}
}