{
  "type": "Feature",
  "properties": {
    "addr:full":"C/ Santa Barbera, 6 Elche Alicante 03203",
    "addr:housenumber":"6",
    "addr:postcode":"03203",
    "addr:street":"C / Santa Barbera",
    "iso:country":"ES",
    "sg:address":"C/ Santa Barbera, 6",
    "sg:city":"Elche",
    "sg:orig_category":"Cl\u00cdnicas Dentales",
    "sg:phone":"+34 965 45 68 88",
    "sg:postcode":"03203",
    "sg:province":"Alicante",
    "wof:name":"Agullo Pi\u00f1ol Ramon",
    "wof:placetype":"venue"
},
  "geometry": {"coordinates":[-0.696960628,38.2647514343],"type":"Point"}
}