{
  "type": "Feature",
  "properties": {
    "iso:country":"ES",
    "sg:address":"Pol Ind Son Llaut, S/n",
    "sg:city":"Sta. Maria Cami",
    "sg:orig_category":"Montaje (empresas De)",
    "sg:phone":"+34 971 62 08 12",
    "sg:postcode":"07320",
    "sg:province":"Islas Baleares",
    "wof:name":"Spark Iberica S.a.",
    "wof:placetype":"venue"
},
  "geometry": {"coordinates":[2.77760005,39.6388893127],"type":"Point"}
}