{
  "type": "Feature",
  "properties": {
    "iso:country":"ES",
    "sg:address":"Os Campos(sigras), 21",
    "sg:city":"Cambre",
    "sg:orig_category":"Centros Y Asociaciones De Gesti\u00d3n Homologados",
    "sg:phone":"+34 981 67 49 54",
    "sg:postcode":"15181",
    "sg:province":"La Coru\u00f1a",
    "wof:name":"Parrillada Peiro S.l.",
    "wof:placetype":"venue"
},
  "geometry": {"coordinates":[-8.3569736481,43.2847442627],"type":"Point"}
}