{
  "type": "Feature",
  "properties": {
    "iso:country":"ES",
    "sg:address":"Avda Castellon, 7",
    "sg:city":"Alcora",
    "sg:orig_category":"Transportes Por V\u00cdas Navegables",
    "sg:phone":"+34 964 36 01 34",
    "sg:postcode":"12110",
    "sg:province":"Castell\u00f3n",
    "wof:name":"Puerto Monfort S.l.",
    "wof:placetype":"venue"
},
  "geometry": {"coordinates":[-0.2113759965,40.0724601746],"type":"Point"}
}