{
  "type": "Feature",
  "properties": {
    "addr:full":"Carrer de Facundo Bacardi I Masso, S/n Mollet Valles Barcelona 08100",
    "addr:housenumber":"s / n",
    "addr:postcode":"08100",
    "addr:street":"Carrer De Facundo Bacardi I Masso",
    "iso:country":"ES",
    "sg:address":"Carrer de Facundo Bacardi I Masso, S/n",
    "sg:city":"Mollet Valles",
    "sg:orig_category":"Construcciones Met\u00c1licas",
    "sg:phone":"+34 935 70 72 27",
    "sg:postcode":"08100",
    "sg:province":"Barcelona",
    "sg:website":"www.mecanotubo.es",
    "wof:name":"Grupo Mecanotubo S. A.",
    "wof:placetype":"venue"
},
  "geometry": {"coordinates":[2.2166249752,41.5438613892],"type":"Point"}
}