{
  "type": "Feature",
  "properties": {
    "addr:full":"Calle de Capitan Daoiz, 2 Talavera Reina Toledo 45600",
    "addr:housenumber":"2",
    "addr:postcode":"45600",
    "addr:street":"Calle De Capitan Daoiz",
    "iso:country":"ES",
    "sg:address":"Calle de Capitan Daoiz, 2",
    "sg:city":"Talavera Reina",
    "sg:orig_category":"Institutos De Belleza",
    "sg:phone":"+34 925 80 55 31",
    "sg:postcode":"45600",
    "sg:province":"Toledo",
    "wof:name":"Sanchez Ordu\u00f1ez Maria Cristina",
    "wof:placetype":"venue"
},
  "geometry": {"coordinates":[-4.8255753517,39.9632644653],"type":"Point"}
}