{
  "type": "Feature",
  "properties": {
    "iso:country":"ES",
    "sg:address":"Carrer de Santa Clara, 6",
    "sg:city":"Palma",
    "sg:orig_category":"Abogados",
    "sg:phone":"+34 971 71 03 99",
    "sg:postcode":"07001",
    "sg:province":"Islas Baleares",
    "wof:name":"Massuti,canals,millan,echevarria,roig,perez Ramos, Abogados Asociados, S.c.",
    "wof:placetype":"venue"
},
  "geometry": {"coordinates":[2.6512179375,39.5675125122],"type":"Point"}
}