{
  "type": "Feature",
  "properties": {
    "iso:country":"ES",
    "sg:address":"Avda Italia, 7",
    "sg:city":"Algeciras",
    "sg:orig_category":"Tapicer\u00cdas",
    "sg:phone":"+34 956 66 87 82",
    "sg:postcode":"11205",
    "sg:province":"C\u00e1diz",
    "wof:name":"Bueno Bautista Cristobal",
    "wof:placetype":"venue"
},
  "geometry": {"coordinates":[-5.4509468079,36.1491851807],"type":"Point"}
}