{
  "type": "Feature",
  "properties": {
    "iso:country":"ES",
    "sg:address":"Calle de Tramontana, 11",
    "sg:city":"Rozas De Madrid",
    "sg:orig_category":"Inmobiliaria (agencias)",
    "sg:phone":"+34 916 39 51 93",
    "sg:postcode":"28230",
    "sg:province":"Madrid",
    "wof:name":"Desarrollo De La Edificacion S.a.",
    "wof:placetype":"venue"
},
  "geometry": {"coordinates":[-3.8529179096,40.4801445007],"type":"Point"}
}