{
  "type": "Feature",
  "properties": {
    "iso:country":"ES",
    "sg:address":"Rua Santiago, 9",
    "sg:city":"Vigo",
    "sg:orig_category":"F\u00c1bricas De Ladrillo Y Tejas",
    "sg:phone":"+34 986 22 58 58",
    "sg:postcode":"36202",
    "sg:province":"Pontevedra",
    "sg:website":"www.euroschiefer.com",
    "wof:name":"Euroschiefer S.l.",
    "wof:placetype":"venue"
},
  "geometry": {"coordinates":[-8.7273254395,42.2364082336],"type":"Point"}
}