{
  "type": "Feature",
  "properties": {
    "addr:full":"Calle de Almorox, 8 Madrid Madrid 28039",
    "addr:housenumber":"8",
    "addr:postcode":"madrid;28039",
    "addr:street":"Calle De Almorox",
    "iso:country":"ES",
    "sg:address":"Calle de Almorox, 8",
    "sg:city":"Madrid",
    "sg:orig_category":"Empresas De Carpinter\u00cda",
    "sg:phone":"+34 914 50 93 22",
    "sg:postcode":"28039",
    "sg:province":"Madrid",
    "wof:name":"Arquitectura De Aluminio Bermejo S.l.",
    "wof:placetype":"venue"
},
  "geometry": {"coordinates":[-3.7118813992,40.4633598328],"type":"Point"}
}