{
  "type": "Feature",
  "properties": {
    "addr:full":"Calle de Jose Maluquer, 17 Sevilla Sevilla 41008",
    "addr:housenumber":"17",
    "addr:postcode":"41008",
    "addr:street":"Calle De Jose Maluquer",
    "iso:country":"ES",
    "sg:address":"Calle de Jose Maluquer, 17",
    "sg:city":"Sevilla",
    "sg:orig_category":"Papeler\u00cdas, Librer\u00cdas",
    "sg:phone":"+34 954 35 74 94",
    "sg:postcode":"41008",
    "sg:province":"Sevilla",
    "wof:name":"Palacios Garcia Josefa",
    "wof:placetype":"venue"
},
  "geometry": {"coordinates":[-5.9795942307,37.4035720825],"type":"Point"}
}