{
  "type": "Feature",
  "properties": {
    "addr:full":"Pol Ind Pelagatos, S/n Chiclana C\u00e1diz 11130",
    "addr:housenumber":"s",
    "addr:postcode":"11130",
    "addr:street":"/ N",
    "iso:country":"ES",
    "sg:address":"Pol Ind Pelagatos, S/n",
    "sg:city":"Chiclana",
    "sg:orig_category":"Veh\u00cdculos De Ocasi\u00d3n",
    "sg:phone":"+34 956 40 93 23",
    "sg:postcode":"11130",
    "sg:province":"C\u00e1diz",
    "wof:name":"Garcia Velez Jose",
    "wof:placetype":"venue"
},
  "geometry": {"coordinates":[-6.0891032219,36.3896331787],"type":"Point"}
}