{
  "type": "Feature",
  "properties": {
    "addr:full":"Pla\u00c7 Carme, 4 Camprodon Girona 17867",
    "addr:housenumber":"4",
    "addr:postcode":"17867",
    "addr:street":"Carme",
    "iso:country":"ES",
    "sg:address":"Pla\u00c7 Carme, 4",
    "sg:city":"Camprodon",
    "sg:orig_category":"Hoteles",
    "sg:phone":"+34 972 74 01 19",
    "sg:postcode":"17867",
    "sg:province":"Girona",
    "wof:name":"Dorca Blanco De Alba Ramon",
    "wof:placetype":"venue"
},
  "geometry": {"coordinates":[2.3650360107,42.3108558655],"type":"Point"}
}