{
  "type": "Feature",
  "properties": {
    "addr:full":"Calle de Martinez Campos, 2 Granada Granada 18005",
    "addr:housenumber":"2",
    "addr:postcode":"18005",
    "addr:street":"Calle De Martinez Campos",
    "iso:country":"ES",
    "sg:address":"Calle de Martinez Campos, 2",
    "sg:city":"Granada",
    "sg:orig_category":"Cl\u00cdnicas M\u00c9dicas",
    "sg:phone":"+34 958 52 21 45",
    "sg:postcode":"18005",
    "sg:province":"Granada",
    "wof:name":"Cobo Martinez Maria Victoria",
    "wof:placetype":"venue"
},
  "geometry": {"coordinates":[-3.6028409004,37.1705322266],"type":"Point"}
}