{
  "type": "Feature",
  "properties": {
    "iso:country":"ES",
    "sg:address":"Calle de Bolarque, 36",
    "sg:city":"Madrid",
    "sg:orig_category":"Inmobiliaria (agencias)",
    "sg:phone":"+34 917 40 04 81",
    "sg:postcode":"28023",
    "sg:province":"Madrid",
    "wof:name":"Benalmadena De Inversiones S.a.",
    "wof:placetype":"venue"
},
  "geometry": {"coordinates":[-3.7629079819,40.4586181641],"type":"Point"}
}