{
  "type": "Feature",
  "properties": {
    "iso:country":"ES",
    "sg:address":"C/ Can Dureta, 32",
    "sg:city":"Inca",
    "sg:orig_category":"Arquitectos",
    "sg:phone":"+34 971 50 51 51",
    "sg:postcode":"07300",
    "sg:province":"Islas Baleares",
    "wof:name":"Ar3 Gual Guasp Lliteras S.l.",
    "wof:placetype":"venue"
},
  "geometry": {"coordinates":[2.9475662708,39.707359314],"type":"Point"}
}