{
  "type": "Feature",
  "properties": {
    "addr:full":"Carrer de Ca N'alzamora, 3 Rubi Barcelona 08191",
    "addr:housenumber":"3",
    "addr:postcode":"08191",
    "addr:street":"Carrer De Ca N'Alzamora",
    "iso:country":"ES",
    "sg:address":"Carrer de Ca N'alzamora, 3",
    "sg:city":"Rubi",
    "sg:orig_category":"Cepiller\u00cdas",
    "sg:phone":"+34 935 88 43 22",
    "sg:postcode":"08191",
    "sg:province":"Barcelona",
    "wof:name":"Roig Vall Francisco",
    "wof:placetype":"venue"
},
  "geometry": {"coordinates":[2.0315570831,41.4798660278],"type":"Point"}
}