{
  "type": "Feature",
  "properties": {
    "addr:full":"Av. Capita F. Batllevell, 4 Martorell Barcelona 08760",
    "addr:housenumber":"4",
    "addr:postcode":"08760",
    "addr:street":"Av. Capita F. Batllevell",
    "iso:country":"ES",
    "sg:address":"Av. Capita F. Batllevell, 4",
    "sg:city":"Martorell",
    "sg:orig_category":"Loter\u00cda Y T\u00d3mbola",
    "sg:phone":"+34 937 75 37 17",
    "sg:postcode":"08760",
    "sg:province":"Barcelona",
    "wof:name":"Tutusaus Cortes Oscar",
    "wof:placetype":"venue"
},
  "geometry": {"coordinates":[1.9265979528,41.474105835],"type":"Point"}
}