{
  "type": "Feature",
  "properties": {
    "addr:full":"Av Sant Jordi, 174 Sant Cristofol Les Fonts Girona 17800",
    "addr:housenumber":"174",
    "addr:postcode":"17800",
    "addr:street":"Av Sant Jordi;Sant Cristofol",
    "iso:country":"ES",
    "sg:address":"Av Sant Jordi, 174",
    "sg:city":"Sant Cristofol Les Fonts",
    "sg:orig_category":"Institutos De Belleza",
    "sg:phone":"+34 972 27 16 14",
    "sg:postcode":"17800",
    "sg:province":"Girona",
    "wof:name":"Infantes Masclans Pilar",
    "wof:placetype":"venue"
},
  "geometry": {"coordinates":[2.4893848896,42.1809463501],"type":"Point"}
}