{
  "type": "Feature",
  "properties": {
    "iso:country":"ES",
    "sg:address":"Avda Andres De Cerezo, 21",
    "sg:city":"Cerezo De Rio Tiron",
    "sg:orig_category":"Ense\u00d1anza, Formaci\u00d3n Profesional: Aprendizaje",
    "sg:phone":"+34 947 58 30 41",
    "sg:postcode":"09270",
    "sg:province":"Burgos",
    "wof:name":"Ayuntamiento De Cerezo De Rio Tiron",
    "wof:placetype":"venue"
},
  "geometry": {"coordinates":[-3.1363720894,42.4910011292],"type":"Point"}
}