{
  "type": "Feature",
  "properties": {
    "addr:full":"Calle de Bienvenida, S/n Fuente Cantos Badajoz 06240",
    "addr:housenumber":"s",
    "addr:postcode":"06240",
    "addr:street":"Calle De Bienvenida;/ N Fuente Cantos",
    "iso:country":"ES",
    "sg:address":"Calle de Bienvenida, S/n",
    "sg:city":"Fuente Cantos",
    "sg:orig_category":"Cooperativas Agr\u00cdcolas",
    "sg:phone":"+34 924 50 01 29",
    "sg:postcode":"06240",
    "sg:province":"Badajoz",
    "wof:name":"Cooperativa De Consumo Nuestra Se\u00f1ora Del Carmen",
    "wof:placetype":"venue"
},
  "geometry": {"coordinates":[-6.2711610794,38.2643699646],"type":"Point"}
}