{
  "type": "Feature",
  "properties": {
    "iso:country":"ES",
    "sg:address":"Av Guiera, 16",
    "sg:city":"Cerdanyola Valles",
    "sg:orig_category":"Laboratorios Y Cl\u00cdnicas Veterinarias",
    "sg:phone":"+34 935 80 67 15",
    "sg:postcode":"08290",
    "sg:province":"Barcelona",
    "wof:name":"Clinica Veterinaria Canaletes Scp",
    "wof:placetype":"venue"
},
  "geometry": {"coordinates":[2.1416430473,41.4830703735],"type":"Point"}
}