{
  "type": "Feature",
  "properties": {
    "iso:country":"ES",
    "sg:address":"Calle de Mayo, 8",
    "sg:city":"Arroyo De La Miel-benalmadena Costa",
    "sg:orig_category":"Inmobiliaria (agencias)",
    "sg:phone":"+34 952 56 31 79",
    "sg:postcode":"29631",
    "sg:province":"M\u00e1laga",
    "wof:name":"Gestion Inmobiliaria Ibc S.l.",
    "wof:placetype":"venue"
},
  "geometry": {"coordinates":[-4.5226769447,36.6039009094],"type":"Point"}
}