{
  "type": "Feature",
  "properties": {
    "iso:country":"ES",
    "sg:address":"Calle de Soto (el), Km. 0007,8",
    "sg:city":"Illana",
    "sg:orig_category":"Estudios Y Construcci\u00d3n De Acuarios Y Viveros",
    "sg:phone":"+34 969 14 82 83",
    "sg:postcode":"19462",
    "sg:province":"Guadalajara",
    "wof:name":"Piscifactoria Piszolla S.l.",
    "wof:placetype":"venue"
},
  "geometry": {"coordinates":[-2.9071102142,40.1827392578],"type":"Point"}
}