{
  "type": "Feature",
  "properties": {
    "addr:full":"Calle de Ramon De Campoamor, 14 Navia Asturias 33710",
    "addr:housenumber":"14",
    "addr:postcode":"33710",
    "addr:street":"Calle De Ramon De Campoamor",
    "iso:country":"ES",
    "sg:address":"Calle de Ramon De Campoamor, 14",
    "sg:city":"Navia",
    "sg:orig_category":"Abogados",
    "sg:phone":"+34 985 63 11 56",
    "sg:postcode":"33710",
    "sg:province":"Asturias",
    "wof:name":"Martinez Campo-osorio Santiago",
    "wof:placetype":"venue"
},
  "geometry": {"coordinates":[-6.7213487625,43.5395851135],"type":"Point"}
}