{
  "type": "Feature",
  "properties": {
    "iso:country":"ES",
    "sg:address":"Carr Huelva, S/n",
    "sg:city":"Cala De Bou",
    "sg:orig_category":"Bazares, Art\u00cdculos De Limpieza Y De Cocina (al Por Menor)",
    "sg:phone":"+34 971 34 57 97",
    "sg:postcode":"07839",
    "sg:province":"Islas Baleares",
    "wof:name":"Serra Segarra Antonio",
    "wof:placetype":"venue"
},
  "geometry": {"coordinates":[1.3025970459,38.8642692566],"type":"Point"}
}