{
  "type": "Feature",
  "properties": {
    "iso:country":"ES",
    "sg:address":"Calle de Ribera Del Loira, 24",
    "sg:city":"Madrid",
    "sg:orig_category":"Agentes, Concesionarios Y Sucursales De Veh\u00cdculos",
    "sg:phone":"+34 917 21 03 36",
    "sg:postcode":"28042",
    "sg:province":"Madrid",
    "sg:website":"www.deysa.com",
    "wof:name":"Dealer Y Servicio Postventa S.a.",
    "wof:placetype":"venue"
},
  "geometry": {"coordinates":[-3.6235229969,40.4650192261],"type":"Point"}
}