{
  "type": "Feature",
  "properties": {
    "addr:full":"Pase Castellana, 288 Madrid Madrid 28046",
    "addr:housenumber":"288",
    "addr:postcode":"28046",
    "addr:street":"Castellana",
    "iso:country":"ES",
    "sg:address":"Pase Castellana, 288",
    "sg:city":"Madrid",
    "sg:orig_category":"Grafistas",
    "sg:phone":"+34 913 14 93 82",
    "sg:postcode":"28046",
    "sg:province":"Madrid",
    "wof:name":"Rex Media S.l.",
    "wof:placetype":"venue"
},
  "geometry": {"coordinates":[-3.6858539581,40.4777946472],"type":"Point"}
}