{
  "type": "Feature",
  "properties": {
    "addr:full":"Carr Cronista Pareja, S/n Canals Valencia 46650",
    "addr:housenumber":"s / n",
    "addr:postcode":"46650",
    "addr:street":"Carr Cronista Pareja",
    "iso:country":"ES",
    "sg:address":"Carr Cronista Pareja, S/n",
    "sg:city":"Canals",
    "sg:orig_category":"Fabricaci\u00d3n De Su\u00c9ters Y Chalecos De Punto",
    "sg:phone":"+34 962 24 46 42",
    "sg:postcode":"46650",
    "sg:province":"Valencia",
    "wof:name":"Emilio Arandiga S.l.",
    "wof:placetype":"venue"
},
  "geometry": {"coordinates":[-0.5798140168,38.9648208618],"type":"Point"}
}