{
  "type": "Feature",
  "properties": {
    "iso:country":"ES",
    "sg:address":"Avda Estacion, 9",
    "sg:city":"Laguna Duero",
    "sg:orig_category":"Lencer\u00cda Femenina, Corseter\u00cda, Trajes De Ba\u00d1o (al Por Menor)",
    "sg:phone":"+34 983 54 51 35",
    "sg:postcode":"47140",
    "sg:province":"Valladolid",
    "wof:name":"Moncada Monedero Pablo",
    "wof:placetype":"venue"
},
  "geometry": {"coordinates":[-4.7202939987,41.5809707642],"type":"Point"}
}