{
  "type": "Feature",
  "properties": {
    "addr:full":"Calle de Gaitan, 30 Posadas C\u00f3rdoba 14730",
    "addr:housenumber":"30;co\u0301rdoba",
    "addr:postcode":"14730",
    "addr:street":"Calle De Gaitan",
    "iso:country":"ES",
    "sg:address":"Calle de Gaitan, 30",
    "sg:city":"Posadas",
    "sg:orig_category":"Molduras, Junquillos, Listones Y Molduras Perforadas",
    "sg:phone":"+34 957 63 02 42",
    "sg:postcode":"14730",
    "sg:province":"C\u00f3rdoba",
    "wof:name":"Osuna Ca\u00f1asveras Antonio",
    "wof:placetype":"venue"
},
  "geometry": {"coordinates":[-5.1061830521,37.8020553589],"type":"Point"}
}