{
  "type": "Feature",
  "properties": {
    "iso:country":"ES",
    "sg:address":"Calle de Ayala, 86",
    "sg:city":"Madrid",
    "sg:orig_category":"M\u00c9dicos: Estomatolog\u00cda",
    "sg:phone":"+34 914 35 95 46",
    "sg:postcode":"28001",
    "sg:province":"Madrid",
    "wof:name":"Ruvinsky  Demian",
    "wof:placetype":"venue"
},
  "geometry": {"coordinates":[-3.6775619984,40.4273872375],"type":"Point"}
}