{
  "type": "Feature",
  "properties": {
    "iso:country":"ES",
    "sg:address":"Calle de Miguel Delibes, 4",
    "sg:city":"Alcala Henares",
    "sg:orig_category":"Centros Empresariales",
    "sg:phone":"+34 918 02 45 40",
    "sg:postcode":"28806",
    "sg:province":"Madrid",
    "wof:name":"Avimaher S.a.l.",
    "wof:placetype":"venue"
},
  "geometry": {"coordinates":[-3.3718795776,40.495136261],"type":"Point"}
}