{
  "type": "Feature",
  "properties": {
    "iso:country":"ES",
    "sg:address":"Edificio Opera, S/n",
    "sg:city":"Vitoria-gasteiz",
    "sg:orig_category":"Promotores Constructores",
    "sg:phone":"+34 945 14 92 73",
    "sg:postcode":"01005",
    "sg:province":"\u00c1lava",
    "wof:name":"Daol S.a.",
    "wof:placetype":"venue"
},
  "geometry": {"coordinates":[-2.6725599766,42.8434410095],"type":"Point"}
}