{
  "type": "Feature",
  "properties": {
    "iso:country":"ES",
    "sg:address":"Pg Joan Carles I, S/n",
    "sg:city":"Eivissa",
    "sg:orig_category":"Peritos Mar\u00cdtimos",
    "sg:phone":"+34 971 31 38 29",
    "sg:postcode":"07800",
    "sg:province":"Islas Baleares",
    "wof:name":"Coral Boats C.b.",
    "wof:placetype":"venue"
},
  "geometry": {"coordinates":[1.4466700554,38.9146118164],"type":"Point"}
}