{
  "type": "Feature",
  "properties": {
    "addr:full":"T. Vidina, 27 Ingenio Las Palmas 35250",
    "addr:housenumber":"27",
    "addr:postcode":"35250",
    "iso:country":"ES",
    "sg:address":"T. Vidina, 27",
    "sg:city":"Ingenio",
    "sg:orig_category":"Equipo De Refrigeraci\u00d3n Industrial",
    "sg:phone":"+34 928 78 91 49",
    "sg:postcode":"35250",
    "sg:province":"Las Palmas",
    "wof:name":"Macfrinox S.l.",
    "wof:placetype":"venue"
},
  "geometry": {"coordinates":[-15.4355688095,27.922290802],"type":"Point"}
}