{
  "type": "Feature",
  "properties": {
    "iso:country":"ES",
    "sg:address":"Calle de Saltillo, 8",
    "sg:city":"Torremolinos",
    "sg:orig_category":"Caf\u00c9s, Bares, Cervecer\u00cdas",
    "sg:phone":"+34 952 37 66 74",
    "sg:postcode":"29620",
    "sg:province":"M\u00e1laga",
    "wof:name":"Allan  Back House",
    "wof:placetype":"venue"
},
  "geometry": {"coordinates":[-4.5140638351,36.6010665894],"type":"Point"}
}