{
  "type": "Feature",
  "properties": {
    "addr:full":"Calle de Lesquinas, 1 Avila \u00c1vila 05001",
    "addr:housenumber":"1",
    "addr:postcode":"05001",
    "addr:street":"Calle De Lesquinas;A\u0301Vila",
    "iso:country":"ES",
    "sg:address":"Calle de Lesquinas, 1",
    "sg:city":"Avila",
    "sg:orig_category":"Guarder\u00cdas",
    "sg:phone":"+34 920 25 07 53",
    "sg:postcode":"05001",
    "sg:province":"\u00c1vila",
    "wof:name":"Palacios Perdiguero Maria Victoria",
    "wof:placetype":"venue"
},
  "geometry": {"coordinates":[-4.6944818497,40.6557884216],"type":"Point"}
}