{
  "type": "Feature",
  "properties": {
    "addr:full":"Calle de Atalaya, S/n Cabra C\u00f3rdoba 14940",
    "addr:housenumber":"s / n",
    "addr:postcode":"14940",
    "addr:street":"Calle De Atalaya;Co\u0301Rdoba",
    "iso:country":"ES",
    "sg:address":"Calle de Atalaya, S/n",
    "sg:city":"Cabra",
    "sg:orig_category":"Mec\u00c1nico Del Autom\u00d3vil",
    "sg:phone":"+34 957 52 47 32",
    "sg:postcode":"14940",
    "sg:province":"C\u00f3rdoba",
    "wof:name":"Camacho Navas Francisco",
    "wof:placetype":"venue"
},
  "geometry": {"coordinates":[-4.4427437782,37.477104187],"type":"Point"}
}