{
  "type": "Feature",
  "properties": {
    "iso:country":"ES",
    "sg:address":"Avda Coto Del, 34",
    "sg:city":"Entrego",
    "sg:orig_category":"Promotores Constructores",
    "sg:phone":"+34 985 65 45 88",
    "sg:postcode":"33940",
    "sg:province":"Asturias",
    "wof:name":"Construcciones Pa\u00f1eda S.l.",
    "wof:placetype":"venue"
},
  "geometry": {"coordinates":[-5.6435742378,43.2864112854],"type":"Point"}
}