{
  "type": "Feature",
  "properties": {
    "iso:country":"ES",
    "sg:address":"Carrer de Joan Palou I Coll, 1",
    "sg:city":"Palma",
    "sg:orig_category":"Papeler\u00cdas: Art\u00cdculos (al Por Mayor)",
    "sg:phone":"+34 971 76 10 85",
    "sg:postcode":"07004",
    "sg:province":"Islas Baleares",
    "wof:name":"Gasllar S.a.",
    "wof:placetype":"venue"
},
  "geometry": {"coordinates":[2.6521859169,39.5888748169],"type":"Point"}
}