{
  "type": "Feature",
  "properties": {
    "addr:full":"Calle de Bravo Murillo, 126 Madrid Madrid 28020",
    "addr:housenumber":"126",
    "addr:postcode":"28020",
    "addr:street":"Calle De Bravo Murillo",
    "iso:country":"ES",
    "sg:address":"Calle de Bravo Murillo, 126",
    "sg:city":"Madrid",
    "sg:orig_category":"Inmobiliaria (agencias)",
    "sg:phone":"+34 915 53 75 59",
    "sg:postcode":"28020",
    "sg:province":"Madrid",
    "sg:website":"www.inmobiliariamaqueda.net",
    "wof:name":"Jg Machuca S.l.",
    "wof:placetype":"venue"
},
  "geometry": {"coordinates":[-3.703599453,40.4493179321],"type":"Point"}
}