{
  "type": "Feature",
  "properties": {
    "addr:full":"Calle de Sevilla, 25 Puertollano Ciudad Real 13500",
    "addr:housenumber":"25",
    "addr:postcode":"13500",
    "addr:street":"Calle De Sevilla",
    "iso:country":"ES",
    "sg:address":"Calle de Sevilla, 25",
    "sg:city":"Puertollano",
    "sg:orig_category":"Fabricaci\u00d3n, Venta, Instalaci\u00d3n De R\u00d3tulos, De R\u00d3tulos Luminosos",
    "sg:phone":"+34 926 41 07 54",
    "sg:postcode":"13500",
    "sg:province":"Ciudad Real",
    "wof:name":"Fernandez-infantes Gomez-limon Miguel Angel",
    "wof:placetype":"venue"
},
  "geometry": {"coordinates":[-4.1131849289,38.6866264343],"type":"Point"}
}