{
  "type": "Feature",
  "properties": {
    "addr:full":"Av Alcodar(pol Alcodar), 14 Gandia Valencia 46700",
    "addr:housenumber":"14",
    "addr:postcode":"46700",
    "addr:street":"Av Alcodar;Alcodar;Valencia",
    "iso:country":"ES",
    "sg:address":"Av Alcodar(pol Alcodar), 14",
    "sg:city":"Gandia",
    "sg:orig_category":"Paneles Diversos",
    "sg:phone":"+34 962 86 79 89",
    "sg:postcode":"46700",
    "sg:province":"Valencia",
    "wof:name":"Neocartel S.l.",
    "wof:placetype":"venue"
},
  "geometry": {"coordinates":[-0.1827200055,38.9826431274],"type":"Point"}
}