{
  "type": "Feature",
  "properties": {
    "iso:country":"ES",
    "sg:address":"Avda Ordesa, 1",
    "sg:city":"Broto",
    "sg:orig_category":"Ense\u00d1anza, Formaci\u00d3n Profesional: Aprendizaje",
    "sg:phone":"+34 974 48 63 06",
    "sg:postcode":"22370",
    "sg:province":"Huesca",
    "wof:name":"Ayuntamiento De Broto",
    "wof:placetype":"venue"
},
  "geometry": {"coordinates":[-0.1230989993,42.6066818237],"type":"Point"}
}