{
  "type": "Feature",
  "properties": {
    "addr:full":"Calle de Magnolio, 8 Villaca\u00f1as Toledo 45860",
    "addr:housenumber":"8",
    "addr:postcode":"45860",
    "addr:street":"Calle De Magnolio",
    "iso:country":"ES",
    "sg:address":"Calle de Magnolio, 8",
    "sg:city":"Villaca\u00f1as",
    "sg:orig_category":"Persianas Interiores, Exteriores",
    "sg:phone":"+34 925 16 13 07",
    "sg:postcode":"45860",
    "sg:province":"Toledo",
    "wof:name":"Mayordomo Tebar Juan",
    "wof:placetype":"venue"
},
  "geometry": {"coordinates":[-3.341698885,39.6213493347],"type":"Point"}
}