{
  "type": "Feature",
  "properties": {
    "addr:full":"Calle de Hermanos Machado, 8 Madrid Madrid 28017",
    "addr:housenumber":"8",
    "addr:postcode":"madrid;28017",
    "addr:street":"Calle De Hermanos Machado",
    "iso:country":"ES",
    "sg:address":"Calle de Hermanos Machado, 8",
    "sg:city":"Madrid",
    "sg:orig_category":"Muebles Y Accesorios Para Cocinas Y Cuartos De Ba\u00d1o (al Por Menor)",
    "sg:phone":"+34 913 67 62 36",
    "sg:postcode":"28017",
    "sg:province":"Madrid",
    "wof:name":"Milano Y Comercio S. A.",
    "wof:placetype":"venue"
},
  "geometry": {"coordinates":[-3.6494879723,40.4325218201],"type":"Point"}
}