{
  "type": "Feature",
  "properties": {
    "iso:country":"ES",
    "sg:address":"Calle de Cocotero, 34",
    "sg:city":"Badajoz",
    "sg:orig_category":"Empresas De Carpinter\u00cda Met\u00c1lica",
    "sg:phone":"+34 924 25 10 06",
    "sg:postcode":"06011",
    "sg:province":"Badajoz",
    "wof:name":"Diaz Hernandez Julian",
    "wof:placetype":"venue"
},
  "geometry": {"coordinates":[-6.9889888763,38.8579406738],"type":"Point"}
}