{
  "type": "Feature",
  "properties": {
    "addr:full":"Carr Barcelona, 13 Girona Girona 17002",
    "addr:housenumber":"13",
    "addr:postcode":"17002",
    "addr:street":"Carr Barcelona",
    "iso:country":"ES",
    "sg:address":"Carr Barcelona, 13",
    "sg:city":"Girona",
    "sg:classifiers":[
        {
            "category":"Tea Room",
            "subcategory":"None",
            "type":"Food & Drink"
        }
    ],
    "sg:phone":"+34 972 22 87 81",
    "sg:postcode":"17002",
    "sg:province":"Girona",
    "sg:tags":[
        "snack"
    ],
    "wof:name":"Pol Cos 2001 S.l.",
    "wof:placetype":"venue"
},
  "geometry": {"coordinates":[2.8188509941,41.9808921814],"type":"Point"}
}