{
  "type": "Feature",
  "properties": {
    "addr:full":"Rua Conde Torrecedeira, 5 Vigo Pontevedra 36202",
    "addr:housenumber":"5",
    "addr:postcode":"36202",
    "addr:street":"Rua Conde Torrecedeira",
    "iso:country":"ES",
    "sg:address":"Rua Conde Torrecedeira, 5",
    "sg:city":"Vigo",
    "sg:orig_category":"Reposter\u00cdas",
    "sg:phone":"+34 986 22 42 68",
    "sg:postcode":"36202",
    "sg:province":"Pontevedra",
    "wof:name":"Riobo Martinez Javier",
    "wof:placetype":"venue"
},
  "geometry": {"coordinates":[-8.73046875,42.235244751],"type":"Point"}
}