{
  "type": "Feature",
  "properties": {
    "addr:full":"Av Barcelona, 54 Rubi Barcelona 08191",
    "addr:housenumber":"54",
    "addr:postcode":"08191",
    "addr:street":"Av Barcelona",
    "iso:country":"ES",
    "sg:address":"Av Barcelona, 54",
    "sg:city":"Rubi",
    "sg:orig_category":"Zapatos (al Por Menor)",
    "sg:phone":"+34 936 97 27 92",
    "sg:postcode":"08191",
    "sg:province":"Barcelona",
    "wof:name":"Riba Alonso Ana Maria",
    "wof:placetype":"venue"
},
  "geometry": {"coordinates":[2.0308699608,41.4878044128],"type":"Point"}
}