{
  "type": "Feature",
  "properties": {
    "iso:country":"ES",
    "sg:address":"Calle de Doctor Don Luis Bilbao Libano, 9",
    "sg:city":"Leioa",
    "sg:orig_category":"Doctores En Medicina",
    "sg:phone":"+34 944 64 86 96",
    "sg:postcode":"48940",
    "sg:province":"Vizcaya",
    "wof:name":"Daniel O\u00f1ate Garcia",
    "wof:placetype":"venue"
},
  "geometry": {"coordinates":[-2.9859642982,43.3215942383],"type":"Point"}
}