{
  "type": "Feature",
  "properties": {
    "iso:country":"ES",
    "sg:address":"Calle de Pescadores, 35",
    "sg:city":"Logro\u00f1o",
    "sg:orig_category":"Serigraf\u00cda (material Y Suministros)",
    "sg:phone":"+34 941 23 90 64",
    "sg:postcode":"26006",
    "sg:province":"La Rioja",
    "wof:name":"Albeniz Saez Jose",
    "wof:placetype":"venue"
},
  "geometry": {"coordinates":[-2.4187335968,42.4714584351],"type":"Point"}
}