{
  "type": "Feature",
  "properties": {
    "addr:full":"Carrer de Casanova, 3 Barcelona Barcelona 08011",
    "addr:housenumber":"3",
    "addr:postcode":"08011",
    "addr:street":"Carrer De Casanova",
    "iso:country":"ES",
    "sg:address":"Carrer de Casanova, 3",
    "sg:city":"Barcelona",
    "sg:orig_category":"Agencias Y Agentes Comerciales, Representantes",
    "sg:phone":"+34 934 25 34 75",
    "sg:postcode":"08011",
    "sg:province":"Barcelona",
    "wof:name":"Jovani Mor Antonio",
    "wof:placetype":"venue"
},
  "geometry": {"coordinates":[2.1629390717,41.3820762634],"type":"Point"}
}