{
  "type": "Feature",
  "properties": {
    "addr:full":"Gmo Franco, 10 Arrecife Las Palmas 35500",
    "addr:housenumber":"10",
    "addr:postcode":"35500",
    "addr:street":"Franco",
    "iso:country":"ES",
    "sg:address":"Gmo Franco, 10",
    "sg:city":"Arrecife",
    "sg:orig_category":"Bisuter\u00cda, Joyer\u00cda, Relojer\u00cda (al Por Menor)",
    "sg:phone":"+34 928 81 51 78",
    "sg:postcode":"35500",
    "sg:province":"Las Palmas",
    "wof:name":"Joyeria Mapy S.a.",
    "wof:placetype":"venue"
},
  "geometry": {"coordinates":[-13.561044693,28.9756126404],"type":"Point"}
}