{
  "type": "Feature",
  "properties": {
    "addr:full":"Vena Bruguera, 19 Veinat De Bruguera Girona 17240",
    "addr:housenumber":"19",
    "addr:postcode":"17240",
    "addr:street":"Veinat De Bruguera",
    "iso:country":"ES",
    "sg:address":"Vena Bruguera, 19",
    "sg:city":"Veinat De Bruguera",
    "sg:orig_category":"Perreras, Pensiones Para Perros, Gatos Y Otros Animales",
    "sg:phone":"+34 972 83 07 89",
    "sg:postcode":"17240",
    "sg:province":"Girona",
    "wof:name":"Hipotragus 2006 S.l",
    "wof:placetype":"venue"
},
  "geometry": {"coordinates":[2.892385006,41.8299255371],"type":"Point"}
}