{
  "type": "Feature",
  "properties": {
    "addr:full":"Calle de Emperador, 1 Nacimiento Almer\u00eda 04540",
    "addr:housenumber":"1",
    "addr:postcode":"04540",
    "addr:street":"Calle De Emperador",
    "iso:country":"ES",
    "sg:address":"Calle de Emperador, 1",
    "sg:city":"Nacimiento",
    "sg:orig_category":"Cajas Para Embalar",
    "sg:phone":"+34 950 35 05 19",
    "sg:postcode":"04540",
    "sg:province":"Almer\u00eda",
    "sg:website":"www.cajamar.es",
    "wof:name":"Cajamar",
    "wof:placetype":"venue"
},
  "geometry": {"coordinates":[-2.648788929,37.1061897278],"type":"Point"}
}