{
  "type": "Feature",
  "properties": {
    "addr:full":"Calle de Mikeldi Kalea, 9 Durango Vizcaya 48200",
    "addr:housenumber":"9",
    "addr:postcode":"48200",
    "addr:street":"Calle De Mikeldi Kalea",
    "iso:country":"ES",
    "sg:address":"Calle de Mikeldi Kalea, 9",
    "sg:city":"Durango",
    "sg:orig_category":"Construcciones Met\u00c1licas",
    "sg:phone":"+34 944 66 86 39",
    "sg:postcode":"48200",
    "sg:province":"Vizcaya",
    "wof:name":"Otaduy Hermanos, S.l.",
    "wof:placetype":"venue"
},
  "geometry": {"coordinates":[-2.6343100071,43.1725006104],"type":"Point"}
}