{
  "type": "Feature",
  "properties": {
    "addr:full":"Calle de Jose A. Primo De Rivera, 1 Mayorga Valladolid 47680",
    "addr:housenumber":"1",
    "addr:postcode":"47680",
    "addr:street":"Calle De Jose A. Primo De Rivera",
    "iso:country":"ES",
    "sg:address":"Calle de Jose A. Primo De Rivera, 1",
    "sg:city":"Mayorga",
    "sg:orig_category":"Asociaciones De Vecinos, Centros De Juventud",
    "sg:phone":"+34 983 75 15 68",
    "sg:postcode":"47680",
    "sg:province":"Valladolid",
    "wof:name":"Centro De Desarrollo Rural Valdecea",
    "wof:placetype":"venue"
},
  "geometry": {"coordinates":[-5.2643089294,42.1640052795],"type":"Point"}
}