{
  "type": "Feature",
  "properties": {
    "addr:full":"Calle de Ni\u00d1a, La, 10 Calpe Alicante 03710",
    "addr:housenumber":"10",
    "addr:postcode":"03710",
    "addr:street":"Calle De Nin\u0303A La",
    "iso:country":"ES",
    "sg:address":"Calle de Ni\u00d1a, La, 10",
    "sg:city":"Calpe",
    "sg:orig_category":"Inmobiliaria (agencias)",
    "sg:phone":"+34 965 83 84 42",
    "sg:postcode":"03710",
    "sg:province":"Alicante",
    "wof:name":"Dhia Selim S.l.",
    "wof:placetype":"venue"
},
  "geometry": {"coordinates":[0.0535200015,38.6515808105],"type":"Point"}
}