{
  "type": "Feature",
  "properties": {
    "addr:full":"Rbla Marina, 264 Hospitalet Llobregat Barcelona 08907",
    "addr:housenumber":"264",
    "addr:postcode":"08907",
    "addr:street":"Rbla Marina",
    "iso:country":"ES",
    "sg:address":"Rbla Marina, 264",
    "sg:city":"Hospitalet Llobregat",
    "sg:orig_category":"Asociaciones Y Clubs Deportivos",
    "sg:phone":"+34 933 36 23 09",
    "sg:postcode":"08907",
    "sg:province":"Barcelona",
    "wof:name":"Hernandez Garcia Luisa Maria",
    "wof:placetype":"venue"
},
  "geometry": {"coordinates":[2.11186409,41.3530273438],"type":"Point"}
}