{
  "type": "Feature",
  "properties": {
    "iso:country":"ES",
    "sg:address":"Calle de General Elorza, 25",
    "sg:city":"Oviedo",
    "sg:orig_category":"Fabricaci\u00d3n, Instalaci\u00d3n De Armarios",
    "sg:phone":"+34 985 22 48 75",
    "sg:postcode":"33001",
    "sg:province":"Asturias",
    "wof:name":"Sistemas Buk S. A.",
    "wof:placetype":"venue"
},
  "geometry": {"coordinates":[-5.8435750008,43.366027832],"type":"Point"}
}