{
  "type": "Feature",
  "properties": {
    "iso:country":"ES",
    "sg:address":"Avda Constitucion (la), S/n",
    "sg:city":"Segovia",
    "sg:orig_category":"Supermercados Y Hipermercados",
    "sg:phone":"+34 921 44 32 86",
    "sg:postcode":"40006",
    "sg:province":"Segovia",
    "wof:name":"Telemensaje S.a.",
    "wof:placetype":"venue"
},
  "geometry": {"coordinates":[-4.1079821587,40.9331207275],"type":"Point"}
}