{
  "type": "Feature",
  "properties": {
    "iso:country":"ES",
    "sg:address":"Rua Xoan Montes, 1",
    "sg:city":"Lugo",
    "sg:orig_category":"Abogados",
    "sg:phone":"+34 982 25 07 44",
    "sg:postcode":"27001",
    "sg:province":"Lugo",
    "wof:name":"Lopez Ferreiro Jose Benito",
    "wof:placetype":"venue"
},
  "geometry": {"coordinates":[-7.5558280945,43.0109405518],"type":"Point"}
}