{
  "type": "Feature",
  "properties": {
    "iso:country":"ES",
    "sg:address":"Calle de Calvario El, S/n",
    "sg:city":"Firgas",
    "sg:orig_category":"Supermercados Y Hipermercados",
    "sg:phone":"+34 928 62 54 09",
    "sg:postcode":"35430",
    "sg:province":"Las Palmas",
    "wof:name":"Supermercados Healde S.l.",
    "wof:placetype":"venue"
},
  "geometry": {"coordinates":[-15.5632791519,28.1062145233],"type":"Point"}
}