{
  "type": "Feature",
  "properties": {
    "iso:country":"ES",
    "sg:address":"Calle de Do\u00d1a Maria Barrabino, 4",
    "sg:city":"Torremolinos",
    "sg:orig_category":"Molduras, Junquillos, Listones Y Molduras Perforadas",
    "sg:phone":"+34 952 38 76 10",
    "sg:postcode":"29620",
    "sg:province":"M\u00e1laga",
    "wof:name":"Vega Trigo Manuel",
    "wof:placetype":"venue"
},
  "geometry": {"coordinates":[-4.5003528595,36.6244277954],"type":"Point"}
}