{
  "type": "Feature",
  "properties": {
    "addr:full":"Calle de Limite (el), 11 Fuensanta -villa Ines Almer\u00eda 04230",
    "addr:postcode":"04230",
    "addr:street":"Calle De Limite El;Fuensanta;Almeri\u0301A",
    "iso:country":"ES",
    "sg:address":"Calle de Limite (el), 11",
    "sg:city":"Fuensanta -villa Ines",
    "sg:orig_category":"Venta, Alquiler, Mantenimiento De Calderas",
    "sg:phone":"+34 950 14 31 76",
    "sg:postcode":"04230",
    "sg:province":"Almer\u00eda",
    "wof:name":"Talleres Indalico C.b.",
    "wof:placetype":"venue"
},
  "geometry": {"coordinates":[-2.4363589287,36.8656349182],"type":"Point"}
}