{
  "type": "Feature",
  "properties": {
    "addr:full":"Calle de Ibarluze, 14 Kurtzea Vizcaya 48960",
    "addr:housenumber":"14",
    "addr:postcode":"48960",
    "addr:street":"Calle De Ibarluze",
    "iso:country":"ES",
    "sg:address":"Calle de Ibarluze, 14",
    "sg:city":"Kurtzea",
    "sg:orig_category":"Alimentaci\u00d3n General (al Por Menor)",
    "sg:phone":"+34 944 56 74 37",
    "sg:postcode":"48960",
    "sg:province":"Vizcaya",
    "wof:name":"Maza Ortiz Ernesto",
    "wof:placetype":"venue"
},
  "geometry": {"coordinates":[-2.6983869076,43.2204284668],"type":"Point"}
}