{
  "type": "Feature",
  "properties": {
    "iso:country":"ES",
    "sg:address":"Avda Alcalde Federico Molina, S/n",
    "sg:city":"Huelva",
    "sg:orig_category":"Supermercados Y Hipermercados",
    "sg:phone":"+34 959 28 20 00",
    "sg:postcode":"21006",
    "sg:province":"Huelva",
    "sg:website":"www.hipercor.es",
    "wof:name":"Hipercor S.a.",
    "wof:placetype":"venue"
},
  "geometry": {"coordinates":[-6.9366841316,37.2569389343],"type":"Point"}
}