{
  "type": "Feature",
  "properties": {
    "iso:country":"ES",
    "sg:address":"Calle de Colombia, 15",
    "sg:city":"Cordoba",
    "sg:orig_category":"Reposter\u00cdas",
    "sg:phone":"+34 957 27 42 92",
    "sg:postcode":"14006",
    "sg:province":"C\u00f3rdoba",
    "wof:name":"Bello Salido Pedro",
    "wof:placetype":"venue"
},
  "geometry": {"coordinates":[-4.7860360146,37.8947563171],"type":"Point"}
}