{
  "type": "Feature",
  "properties": {
    "addr:full":"Rua San Felix, 31 Verin Ourense 32600",
    "addr:housenumber":"31",
    "addr:postcode":"32600",
    "addr:street":"Rua San Felix",
    "iso:country":"ES",
    "sg:address":"Rua San Felix, 31",
    "sg:city":"Verin",
    "sg:orig_category":"Fabricaci\u00d3n De Muebles De Cocina",
    "sg:phone":"+34 988 41 17 55",
    "sg:postcode":"32600",
    "sg:province":"Ourense",
    "wof:name":"Rodriguez Alvarez Bernardino",
    "wof:placetype":"venue"
},
  "geometry": {"coordinates":[-7.4268288612,41.9416694641],"type":"Point"}
}