{
  "type": "Feature",
  "properties": {
    "addr:full":"Calle de Cadiz, 4 Alaquas Valencia 46970",
    "addr:housenumber":"4",
    "addr:postcode":"46970",
    "addr:street":"Calle De Cadiz",
    "iso:country":"ES",
    "sg:address":"Calle de Cadiz, 4",
    "sg:city":"Alaquas",
    "sg:orig_category":"Aguas (distribuci\u00d3n, Servicios)",
    "sg:phone":"+34 961 50 14 39",
    "sg:postcode":"46970",
    "sg:province":"Valencia",
    "wof:name":"Segarra Ortega Virginia",
    "wof:placetype":"venue"
},
  "geometry": {"coordinates":[-0.4573589861,39.4565505981],"type":"Point"}
}