{
  "type": "Feature",
  "properties": {
    "addr:full":"Calle de Ricardo Soriano, 28 Pe\u00e7aranda De Bracamonte Salamanca 37300",
    "addr:housenumber":"28",
    "addr:postcode":"37300",
    "addr:street":"Calle De Ricardo Soriano",
    "iso:country":"ES",
    "sg:address":"Calle de Ricardo Soriano, 28",
    "sg:city":"Pe\u00e7aranda De Bracamonte",
    "sg:orig_category":"Empresas De Limpieza",
    "sg:phone":"+34 923 54 19 50",
    "sg:postcode":"37300",
    "sg:province":"Salamanca",
    "wof:name":"Albaicin S.cop.l.",
    "wof:placetype":"venue"
},
  "geometry": {"coordinates":[-5.1986265182,40.9020500183],"type":"Point"}
}