{
  "type": "Feature",
  "properties": {
    "addr:full":"Carrer de Ripoll, 1 Altea Alicante 03590",
    "addr:housenumber":"1",
    "addr:postcode":"03590",
    "addr:street":"Carrer De Ripoll",
    "iso:country":"ES",
    "sg:address":"Carrer de Ripoll, 1",
    "sg:city":"Altea",
    "sg:orig_category":"Peluquer\u00cdas, Peluquer\u00cda Mixta",
    "sg:phone":"+34 965 84 33 38",
    "sg:postcode":"03590",
    "sg:province":"Alicante",
    "wof:name":"Ortiz Ortiz Andrea",
    "wof:placetype":"venue"
},
  "geometry": {"coordinates":[-0.0492979996,38.5998420715],"type":"Point"}
}