{
  "type": "Feature",
  "properties": {
    "addr:full":"Calle de Real, 14 Sanlucar Mayor Sevilla 41800",
    "addr:housenumber":"14",
    "addr:postcode":"41800",
    "addr:street":"Calle De Real",
    "iso:country":"ES",
    "sg:address":"Calle de Real, 14",
    "sg:city":"Sanlucar Mayor",
    "sg:orig_category":"Agencias De Viajes",
    "sg:phone":"+34 955 70 47 52",
    "sg:postcode":"41800",
    "sg:province":"Sevilla",
    "wof:name":"Viajes Hemisferio Sur S.c.p.",
    "wof:placetype":"venue"
},
  "geometry": {"coordinates":[-6.2005729675,37.3856773376],"type":"Point"}
}