{
  "type": "Feature",
  "properties": {
    "addr:full":"Ptda Lo Garriga, 57 Rojales Alicante 03170",
    "addr:housenumber":"57",
    "addr:postcode":"03170",
    "addr:street":"Ptda Lo Garriga",
    "iso:country":"ES",
    "sg:address":"Ptda Lo Garriga, 57",
    "sg:city":"Rojales",
    "sg:orig_category":"Agencias Y Asesores De Publicidad",
    "sg:phone":"+34 966 71 57 35",
    "sg:postcode":"03170",
    "sg:province":"Alicante",
    "sg:website":"www.portaldiabel.com",
    "wof:name":"Impresiones Cymk S.l.",
    "wof:placetype":"venue"
},
  "geometry": {"coordinates":[-0.7292140126,38.0850296021],"type":"Point"}
}