{
  "type": "Feature",
  "properties": {
    "iso:country":"ES",
    "sg:address":"Calle de Agustin Varo, 1",
    "sg:city":"Barbate",
    "sg:orig_category":"Poller\u00cda Y Caza (al Por Menor)",
    "sg:phone":"+34 956 43 35 77",
    "sg:postcode":"11160",
    "sg:province":"C\u00e1diz",
    "wof:name":"Garcia Perez Natalia",
    "wof:placetype":"venue"
},
  "geometry": {"coordinates":[-5.9209337234,36.1905937195],"type":"Point"}
}