{
  "type": "Feature",
  "properties": {
    "addr:full":"Calle de Antequera, 138 Osuna Sevilla 41640",
    "addr:housenumber":"138",
    "addr:postcode":"41640",
    "addr:street":"Calle De Antequera",
    "iso:country":"ES",
    "sg:address":"Calle de Antequera, 138",
    "sg:city":"Osuna",
    "sg:orig_category":"Quincaller\u00cda (al Por Menor)",
    "sg:phone":"+34 954 81 25 87",
    "sg:postcode":"41640",
    "sg:province":"Sevilla",
    "wof:name":"Lopez Riaza Antonio",
    "wof:placetype":"venue"
},
  "geometry": {"coordinates":[-5.1076798439,37.235786438],"type":"Point"}
}