{
  "type": "Feature",
  "properties": {
    "iso:country":"ES",
    "sg:address":"Pla\u00c7 Mercat, 9",
    "sg:city":"Xativa",
    "sg:orig_category":"Carnicer\u00cdas, Carnicer\u00cdas",
    "sg:phone":"+34 962 27 46 14",
    "sg:postcode":"46800",
    "sg:province":"Valencia",
    "wof:name":"Revert Llacer Adelino",
    "wof:placetype":"venue"
},
  "geometry": {"coordinates":[-0.5200830102,38.9934272766],"type":"Point"}
}