{
  "type": "Feature",
  "properties": {
    "iso:country":"ES",
    "sg:address":"Jose Maria Holgado, 19",
    "sg:city":"Ronda",
    "sg:orig_category":"Hoteles",
    "sg:phone":"+34 952 19 03 92",
    "sg:postcode":"29400",
    "sg:province":"M\u00e1laga",
    "wof:name":"Perez Giron Auxiliadora",
    "wof:placetype":"venue"
},
  "geometry": {"coordinates":[-5.1661992073,36.7386245728],"type":"Point"}
}