{
  "type": "Feature",
  "properties": {
    "iso:country":"ES",
    "sg:address":"C/ Francesc Aulet, S/n",
    "sg:city":"Llucmajor",
    "sg:orig_category":"Negocio De Materiales De Construcci\u00d3n",
    "sg:phone":"+34 971 66 07 01",
    "sg:postcode":"07620",
    "sg:province":"Islas Baleares",
    "sg:website":"www.femenias.com",
    "wof:name":"Almacenes Femenias S.a.",
    "wof:placetype":"venue"
},
  "geometry": {"coordinates":[2.8855302334,39.487739563],"type":"Point"}
}