{
  "type": "Feature",
  "properties": {
    "iso:country":"ES",
    "sg:address":"Pl. Mayor, 3",
    "sg:city":"Galve Sorbe",
    "sg:orig_category":"Transportes Por Carretera: Lotes Completos, Mercanc\u00cdas Diversas",
    "sg:phone":"+34 949 30 30 66",
    "sg:postcode":"19275",
    "sg:province":"Guadalajara",
    "wof:name":"Antonio Sierra Victorino De",
    "wof:placetype":"venue"
},
  "geometry": {"coordinates":[-3.1452176571,41.2668495178],"type":"Point"}
}