{
  "type": "Feature",
  "properties": {
    "addr:full":"Calle de Esperanza, 2 Alhaurin El Grande M\u00e1laga 29120",
    "addr:housenumber":"2",
    "addr:postcode":"29120",
    "addr:street":"Calle De Esperanza",
    "iso:country":"ES",
    "sg:address":"Calle de Esperanza, 2",
    "sg:city":"Alhaurin El Grande",
    "sg:orig_category":"Notarios",
    "sg:phone":"+34 952 49 10 46",
    "sg:postcode":"29120",
    "sg:province":"M\u00e1laga",
    "wof:name":"Planells Del Pozo Maria Cristina",
    "wof:placetype":"venue"
},
  "geometry": {"coordinates":[-4.6811509132,36.6479873657],"type":"Point"}
}