{
  "type": "Feature",
  "properties": {
    "iso:country":"ES",
    "sg:address":"Calle de Luis Vives, 6",
    "sg:city":"Albacete",
    "sg:orig_category":"Papeler\u00cdas: Art\u00cdculos (al Por Mayor)",
    "sg:phone":"+34 967 24 19 95",
    "sg:postcode":"02005",
    "sg:province":"Albacete",
    "wof:name":"Lopher Alba S.l.",
    "wof:placetype":"venue"
},
  "geometry": {"coordinates":[-1.8620330095,39.0020561218],"type":"Point"}
}