{
  "type": "Feature",
  "properties": {
    "addr:full":"Plaz Ventura Rodriguez, 5 Leganes Madrid 28911",
    "addr:housenumber":"5",
    "addr:postcode":"28911",
    "addr:street":"Plaz Ventura Rodriguez",
    "iso:country":"ES",
    "sg:address":"Plaz Ventura Rodriguez, 5",
    "sg:city":"Leganes",
    "sg:orig_category":"Instalaci\u00d3n De Aspiraci\u00d3n De Gases Y Humos",
    "sg:phone":"+34 916 94 11 13",
    "sg:postcode":"28911",
    "sg:province":"Madrid",
    "wof:name":"Bekagas S.l.",
    "wof:placetype":"venue"
},
  "geometry": {"coordinates":[-3.7664759159,40.3300971985],"type":"Point"}
}