{
  "type": "Feature",
  "properties": {
    "iso:country":"ES",
    "sg:address":"Luz De Castilla, S/n",
    "sg:city":"Segovia",
    "sg:orig_category":"Peluquer\u00cdas, Peluquer\u00cda Mixta",
    "sg:phone":"+34 921 44 80 47",
    "sg:postcode":"40006",
    "sg:province":"Segovia",
    "wof:name":"Ebanni Peluquerias S.l.",
    "wof:placetype":"venue"
},
  "geometry": {"coordinates":[-4.1163592339,40.9482116699],"type":"Point"}
}