{
  "type": "Feature",
  "properties": {
    "iso:country":"ES",
    "sg:address":"Pg Font D'en Fargas, 22",
    "sg:city":"Barcelona",
    "sg:classifiers":[
        {
            "category":"Professional",
            "subcategory":"Management & Consulting",
            "type":"Services"
        }
    ],
    "sg:phone":"+34 934 29 23 42",
    "sg:postcode":"08032",
    "sg:province":"Barcelona",
    "sg:tags":[
        "asesor\u00cda",
        "en",
        "marketing"
    ],
    "wof:name":"Tribo Capdevila Joaquim",
    "wof:placetype":"venue"
},
  "geometry": {"coordinates":[2.1643209457,41.4213371277],"type":"Point"}
}