{
  "type": "Feature",
  "properties": {
    "iso:country":"ES",
    "sg:address":"Carrer de Baro De Rocafort, 5",
    "sg:city":"Cambrils",
    "sg:orig_category":"Agencias Y Agentes Comerciales, Representantes",
    "sg:phone":"+34 977 36 66 03",
    "sg:postcode":"43850",
    "sg:province":"Tarragona",
    "wof:name":"Campos Del Amo Maria",
    "wof:placetype":"venue"
},
  "geometry": {"coordinates":[1.0530070066,41.0738983154],"type":"Point"}
}