{
  "type": "Feature",
  "properties": {
    "iso:country":"ES",
    "sg:address":"O Mui\u00f1o, S/n",
    "sg:city":"Cobres",
    "sg:orig_category":"Materiales De Aislamiento T\u00c9rmico Y Ac\u00dastico",
    "sg:phone":"+34 986 67 23 27",
    "sg:postcode":"36141",
    "sg:province":"Pontevedra",
    "wof:name":"Catpol S.l.",
    "wof:placetype":"venue"
},
  "geometry": {"coordinates":[-8.6366939545,42.3592987061],"type":"Point"}
}