{
  "type": "Feature",
  "properties": {
    "iso:country":"ES",
    "sg:address":"Calle de Hilarion Eslava, 26",
    "sg:city":"Madrid",
    "sg:orig_category":"Universidades",
    "sg:phone":"+34 915 49 20 48",
    "sg:postcode":"28015",
    "sg:province":"Madrid",
    "wof:name":"Academia Ferraz S.l.",
    "wof:placetype":"venue"
},
  "geometry": {"coordinates":[-3.7166700363,40.4345970154],"type":"Point"}
}