{
  "type": "Feature",
  "properties": {
    "addr:full":"Ctra. Felanitx, Km. 0006,7 Portocolom Islas Baleares 07670",
    "addr:postcode":"07670",
    "addr:street":"Ctra. Felanitx Km. 0006,7",
    "iso:country":"ES",
    "sg:address":"Ctra. Felanitx, Km. 0006,7",
    "sg:city":"Portocolom",
    "sg:orig_category":"M\u00c1rmoles, Granitos Y Piedras Naturales",
    "sg:phone":"+34 971 82 56 88",
    "sg:postcode":"07670",
    "sg:province":"Islas Baleares",
    "wof:name":"Antonio Fayos Rizo S.l.",
    "wof:placetype":"venue"
},
  "geometry": {"coordinates":[3.2598249912,39.4244842529],"type":"Point"}
}