{
  "type": "Feature",
  "properties": {
    "iso:country":"ES",
    "sg:address":"Calle de Martin Cansado, 3",
    "sg:city":"Badajoz",
    "sg:orig_category":"Asociaciones, Organismos Culturales Y Socioeducativos",
    "sg:phone":"+34 924 22 16 25",
    "sg:postcode":"06002",
    "sg:province":"Badajoz",
    "wof:name":"Club Puentenuevo De Badajoz",
    "wof:placetype":"venue"
},
  "geometry": {"coordinates":[-6.9703388214,38.8768997192],"type":"Point"}
}