{
  "type": "Feature",
  "properties": {
    "addr:full":"Calle de Real, 21 Huercal Almeria Almer\u00eda 04230",
    "addr:housenumber":"21",
    "addr:postcode":"04230",
    "addr:street":"Calle De Real;Almeri\u0301A",
    "iso:country":"ES",
    "sg:address":"Calle de Real, 21",
    "sg:city":"Huercal Almeria",
    "sg:orig_category":"Caf\u00c9s, Bares, Cervecer\u00cdas",
    "sg:phone":"+34 950 30 06 99",
    "sg:postcode":"04230",
    "sg:province":"Almer\u00eda",
    "wof:name":"Fernandez Y Del Aguila S.c.",
    "wof:placetype":"venue"
},
  "geometry": {"coordinates":[-2.4356720448,36.8828926086],"type":"Point"}
}