{
  "type": "Feature",
  "properties": {
    "addr:full":"Calle de Chile, 28 Logro\u00f1o La Rioja 26005",
    "addr:housenumber":"28",
    "addr:postcode":"26005",
    "addr:street":"Calle De Chile;Rioja",
    "iso:country":"ES",
    "sg:address":"Calle de Chile, 28",
    "sg:city":"Logro\u00f1o",
    "sg:orig_category":"Electrodom\u00c9sticos (al Por Menor)",
    "sg:phone":"+34 941 20 72 78",
    "sg:postcode":"26005",
    "sg:province":"La Rioja",
    "wof:name":"Amparo Martinez Santana Y Jose Martinez Santana S.cv.",
    "wof:placetype":"venue"
},
  "geometry": {"coordinates":[-2.4549295902,42.4610023499],"type":"Point"}
}