{
  "type": "Feature",
  "properties": {
    "iso:country":"ES",
    "sg:address":"Calle de Fola, 43",
    "sg:city":"Castellon",
    "sg:orig_category":"Estancos",
    "sg:phone":"+34 964 72 28 98",
    "sg:postcode":"12002",
    "sg:province":"Castell\u00f3n",
    "wof:name":"Meseguer Belles Francisco Javier",
    "wof:placetype":"venue"
},
  "geometry": {"coordinates":[-0.0362440012,39.9818687439],"type":"Point"}
}