{
  "type": "Feature",
  "properties": {
    "addr:full":"Carrer de Sant Adria, 70 Barcelona Barcelona 08030",
    "addr:housenumber":"70",
    "addr:postcode":"08030",
    "addr:street":"Carrer De Sant Adria",
    "iso:country":"ES",
    "sg:address":"Carrer de Sant Adria, 70",
    "sg:city":"Barcelona",
    "sg:orig_category":"Mec\u00c1nico Del Autom\u00d3vil",
    "sg:phone":"+34 933 46 89 53",
    "sg:postcode":"08030",
    "sg:province":"Barcelona",
    "wof:name":"Corral Peralvo Basilio",
    "wof:placetype":"venue"
},
  "geometry": {"coordinates":[2.199461937,41.4353981018],"type":"Point"}
}