{
  "type": "Feature",
  "properties": {
    "addr:full":"Calle de Arco De Avila, 1 Arevalo \u00c1vila 05200",
    "addr:housenumber":"1",
    "addr:postcode":"05200",
    "addr:street":"Calle De Arco De Avila",
    "iso:country":"ES",
    "sg:address":"Calle de Arco De Avila, 1",
    "sg:city":"Arevalo",
    "sg:orig_category":"Molduras, Junquillos, Listones Y Molduras Perforadas",
    "sg:phone":"+34 920 30 01 13",
    "sg:postcode":"05200",
    "sg:province":"\u00c1vila",
    "wof:name":"Senovilla Torres Marceliano",
    "wof:placetype":"venue"
},
  "geometry": {"coordinates":[-4.7187409401,41.061214447],"type":"Point"}
}