{
  "type": "Feature",
  "properties": {
    "addr:full":"Av Costa Brava, 3 S. Antoni Calonge Girona 17252",
    "addr:housenumber":"3",
    "addr:postcode":"17252",
    "addr:street":"Av Costa Brava",
    "iso:country":"ES",
    "sg:address":"Av Costa Brava, 3",
    "sg:city":"S. Antoni Calonge",
    "sg:orig_category":"Caf\u00c9s, Bares, Cervecer\u00cdas",
    "sg:phone":"+34 972 65 00 36",
    "sg:postcode":"17252",
    "sg:province":"Girona",
    "wof:name":"Martin Rivera Teresa",
    "wof:placetype":"venue"
},
  "geometry": {"coordinates":[3.099396944,41.8455543518],"type":"Point"}
}