{
  "type": "Feature",
  "properties": {
    "iso:country":"ES",
    "sg:address":"Sar-cespon, 44",
    "sg:city":"Sar",
    "sg:orig_category":"Comercio, Reparaci\u00d3n De Motocicletas, Bicicletas Y Piezas Sueltas",
    "sg:phone":"+34 981 86 10 91",
    "sg:postcode":"15991",
    "sg:province":"La Coru\u00f1a",
    "wof:name":"Martos Romay Valentin Guillermo",
    "wof:placetype":"venue"
},
  "geometry": {"coordinates":[-8.8562450409,42.6563568115],"type":"Point"}
}