{
  "type": "Feature",
  "properties": {
    "addr:full":"Calle de Prado, 1 Ciudad Real Ciudad Real 13001",
    "addr:housenumber":"1",
    "addr:postcode":"13001",
    "addr:street":"Calle De Prado",
    "iso:country":"ES",
    "sg:address":"Calle de Prado, 1",
    "sg:city":"Ciudad Real",
    "sg:orig_category":"Venta, Alquiler De Instrumentos Y Accesorios De M\u00dasica",
    "sg:phone":"+34 926 23 11 03",
    "sg:postcode":"13001",
    "sg:province":"Ciudad Real",
    "wof:name":"Sobrino Mora Ramon",
    "wof:placetype":"venue"
},
  "geometry": {"coordinates":[-3.9290750027,38.9861793518],"type":"Point"}
}