{
  "type": "Feature",
  "properties": {
    "iso:country":"ES",
    "sg:address":"Calle de Barri Santa Caterina, 39",
    "sg:city":"Alzira",
    "sg:orig_category":"Carnicer\u00cdas, Carnicer\u00cdas",
    "sg:phone":"+34 962 41 43 82",
    "sg:postcode":"46600",
    "sg:province":"Valencia",
    "wof:name":"Tudela Sierra Pascual",
    "wof:placetype":"venue"
},
  "geometry": {"coordinates":[-0.4326280057,39.1522598267],"type":"Point"}
}