{
  "type": "Feature",
  "properties": {
    "addr:full":"Plaz Sancti Petri (de), S/n Barrosa C\u00e1diz 11130",
    "addr:housenumber":"s",
    "addr:postcode":"11130",
    "addr:street":"Plaz;Petri;/ N Barrosa Ca\u0301Diz",
    "iso:country":"ES",
    "sg:address":"Plaz Sancti Petri (de), S/n",
    "sg:city":"Barrosa",
    "sg:orig_category":"Peleter\u00cdas",
    "sg:phone":"+34 956 49 61 10",
    "sg:postcode":"11130",
    "sg:province":"C\u00e1diz",
    "wof:name":"Bellido Enriquez Manuel",
    "wof:placetype":"venue"
},
  "geometry": {"coordinates":[-6.1447038651,36.4212188721],"type":"Point"}
}