{
  "type": "Feature",
  "properties": {
    "iso:country":"ES",
    "sg:address":"Carrer de Mare De Deu De La Merce, 39",
    "sg:city":"Mutxamel",
    "sg:orig_category":"Psic\u00d3logos",
    "sg:phone":"+34 965 95 09 03",
    "sg:postcode":"03110",
    "sg:province":"Alicante",
    "wof:name":"Perez Perez Carmen",
    "wof:placetype":"venue"
},
  "geometry": {"coordinates":[-0.4437440038,38.4162063599],"type":"Point"}
}