{
  "type": "Feature",
  "properties": {
    "iso:country":"ES",
    "sg:address":"Calle de Bisagra (de La), 9",
    "sg:city":"Galapagar",
    "sg:orig_category":"Electricidad: Instaladores",
    "sg:phone":"+34 918 58 38 62",
    "sg:postcode":"28260",
    "sg:province":"Madrid",
    "wof:name":"Proindo S.l.",
    "wof:placetype":"venue"
},
  "geometry": {"coordinates":[-4.0030355453,40.5652885437],"type":"Point"}
}