{
  "type": "Feature",
  "properties": {
    "iso:country":"ES",
    "sg:address":"Calle de Gabilondo, 7",
    "sg:city":"Valladolid",
    "sg:orig_category":"Art\u00cdculos De Madera (fabricaci\u00d3n Y Al Por Mayor)",
    "sg:phone":"+34 983 47 84 73",
    "sg:postcode":"47007",
    "sg:province":"Valladolid",
    "wof:name":"Hijos De German Gomez S.l.",
    "wof:placetype":"venue"
},
  "geometry": {"coordinates":[-4.7344350815,41.6429252625],"type":"Point"}
}