{
  "type": "Feature",
  "properties": {
    "iso:country":"ES",
    "sg:address":"Calle de Alarcon, 47",
    "sg:city":"Gijon",
    "sg:orig_category":"Locales Y Clases De Danza",
    "sg:phone":"+34 985 13 13 23",
    "sg:postcode":"33204",
    "sg:province":"Asturias",
    "wof:name":"Fanjul Arg\u00fcelles Maria Luisa",
    "wof:placetype":"venue"
},
  "geometry": {"coordinates":[-5.6483564377,43.5358314514],"type":"Point"}
}