{
  "type": "Feature",
  "properties": {
    "addr:full":"Irailak Zazpi Kalea, 2 Portua Guip\u00f9zcoa 20280",
    "addr:housenumber":"2",
    "addr:postcode":"20280",
    "addr:street":"Zazpi Kalea;Guipu\u0300Zcoa",
    "iso:country":"ES",
    "sg:address":"Irailak Zazpi Kalea, 2",
    "sg:city":"Portua",
    "sg:orig_category":"Asesor\u00cda Fiscal Y Jur\u00cddica",
    "sg:phone":"+34 943 64 04 74",
    "sg:postcode":"20280",
    "sg:province":"Guip\u00f9zcoa",
    "wof:name":"Acpa S.l.",
    "wof:placetype":"venue"
},
  "geometry": {"coordinates":[-1.7932940722,43.3702964783],"type":"Point"}
}