{
  "type": "Feature",
  "properties": {
    "addr:full":"Calle de Fray Luis De Leon Alta, 41 Mota Cuervo Cuenca 16630",
    "addr:housenumber":"41",
    "addr:postcode":"16630",
    "addr:street":"Calle De Fray Luis De Leon Alta",
    "iso:country":"ES",
    "sg:address":"Calle de Fray Luis De Leon Alta, 41",
    "sg:city":"Mota Cuervo",
    "sg:orig_category":"Inmobiliaria (agencias)",
    "sg:phone":"+34 967 18 01 00",
    "sg:postcode":"16630",
    "sg:province":"Cuenca",
    "wof:name":"Cano Martinez-cruzado Jose Antonio",
    "wof:placetype":"venue"
},
  "geometry": {"coordinates":[-2.8667089939,39.5022888184],"type":"Point"}
}