{
  "type": "Feature",
  "properties": {
    "addr:full":"Calle de Mercedes Manjon, 2 Madrid Madrid 28026",
    "addr:housenumber":"2",
    "addr:postcode":"28026",
    "addr:street":"Calle De Mercedes Manjon",
    "iso:country":"ES",
    "sg:address":"Calle de Mercedes Manjon, 2",
    "sg:city":"Madrid",
    "sg:orig_category":"Asesor\u00cda Fiscal Y Jur\u00cddica",
    "sg:phone":"+34 915 00 12 93",
    "sg:postcode":"28026",
    "sg:province":"Madrid",
    "sg:website":"www.benitomoreno.com",
    "wof:name":"Moreno Lopez Purificacion",
    "wof:placetype":"venue"
},
  "geometry": {"coordinates":[-3.7076020241,40.3860435486],"type":"Point"}
}