{
  "type": "Feature",
  "properties": {
    "addr:full":"C/ Uralita, 12 Ripollet Barcelona 08291",
    "addr:housenumber":"12",
    "addr:postcode":"08291",
    "addr:street":"C / Uralita",
    "iso:country":"ES",
    "sg:address":"C/ Uralita, 12",
    "sg:city":"Ripollet",
    "sg:orig_category":"Rectificaci\u00d3n, Mecanizado, Fresado",
    "sg:phone":"+34 935 80 24 89",
    "sg:postcode":"08291",
    "sg:province":"Barcelona",
    "wof:name":"Decoletajes Igma S.cv.",
    "wof:placetype":"venue"
},
  "geometry": {"coordinates":[2.1417849064,41.5006790161],"type":"Point"}
}