{
  "type": "Feature",
  "properties": {
    "addr:full":"Calle de Manuela Malasa\u00d1a, 21 Madrid Madrid 28004",
    "addr:housenumber":"21",
    "addr:postcode":"madrid;28004",
    "addr:street":"Calle De Manuela Malasan\u0303A",
    "iso:country":"ES",
    "sg:address":"Calle de Manuela Malasa\u00d1a, 21",
    "sg:city":"Madrid",
    "sg:orig_category":"Electricidad, Electr\u00d3nica: Suministros (al Por Menor)",
    "sg:phone":"+34 914 48 90 57",
    "sg:postcode":"28004",
    "sg:province":"Madrid",
    "wof:name":"Razquin Sanchez De Vivar Sonia",
    "wof:placetype":"venue"
},
  "geometry": {"coordinates":[-3.7042069435,40.4285774231],"type":"Point"}
}