{
  "type": "Feature",
  "properties": {
    "addr:full":"Carrer de Ruiz De Padron, 82 Barcelona Barcelona 08026",
    "addr:housenumber":"82",
    "addr:postcode":"08026",
    "addr:street":"Carrer De Ruiz De Padron",
    "iso:country":"ES",
    "sg:address":"Carrer de Ruiz De Padron, 82",
    "sg:city":"Barcelona",
    "sg:orig_category":"Mec\u00c1nico Del Autom\u00d3vil",
    "sg:phone":"+34 933 51 12 01",
    "sg:postcode":"08026",
    "sg:province":"Barcelona",
    "wof:name":"Pereira Salgado Jose Manuel",
    "wof:placetype":"venue"
},
  "geometry": {"coordinates":[2.1847040653,41.4156227112],"type":"Point"}
}