{
  "type": "Feature",
  "properties": {
    "iso:country":"ES",
    "sg:address":"Kale Nagusia, 31",
    "sg:city":"Astigarraga",
    "sg:orig_category":"Panader\u00cdas, Panader\u00cdas",
    "sg:phone":"+34 943 55 41 04",
    "sg:postcode":"20115",
    "sg:province":"Guip\u00f9zcoa",
    "wof:name":"Morla Luengo Rosa",
    "wof:placetype":"venue"
},
  "geometry": {"coordinates":[-1.9507540464,43.2802085876],"type":"Point"}
}