{
  "type": "Feature",
  "properties": {
    "iso:country":"ES",
    "sg:address":"Carrer de Massanella, 8",
    "sg:city":"Vileta -son Rapinya",
    "sg:orig_category":"Empresas De Carpinter\u00cda De Madera",
    "sg:phone":"+34 971 79 21 78",
    "sg:postcode":"07013",
    "sg:province":"Islas Baleares",
    "wof:name":"Fusteria Massanella S.l.",
    "wof:placetype":"venue"
},
  "geometry": {"coordinates":[2.6181070805,39.5910453796],"type":"Point"}
}