{
  "type": "Feature",
  "properties": {
    "iso:country":"ES",
    "sg:address":"Pol Ind San Jorge, S/n",
    "sg:city":"Palos Frontera",
    "sg:orig_category":"Arboricultura Y Producci\u00d3n De Frutas",
    "sg:phone":"+34 959 53 02 96",
    "sg:postcode":"21810",
    "sg:province":"Huelva",
    "wof:name":"Frescolon S.l.",
    "wof:placetype":"venue"
},
  "geometry": {"coordinates":[-6.8923411369,37.2240829468],"type":"Point"}
}