{
  "type": "Feature",
  "properties": {
    "addr:full":"Rbla Guipuscoa, 107 Barcelona Barcelona 08020",
    "addr:housenumber":"107",
    "addr:postcode":"08020",
    "addr:street":"Rbla Guipuscoa",
    "iso:country":"ES",
    "sg:address":"Rbla Guipuscoa, 107",
    "sg:city":"Barcelona",
    "sg:orig_category":"Promotores Constructores",
    "sg:phone":"+34 932 78 82 10",
    "sg:postcode":"08020",
    "sg:province":"Barcelona",
    "wof:name":"Gamma Inmobiliaria S.a.",
    "wof:placetype":"venue"
},
  "geometry": {"coordinates":[2.2018070221,41.4202156067],"type":"Point"}
}