{
  "type": "Feature",
  "properties": {
    "iso:country":"ES",
    "sg:address":"Calle de Almacellas, 60",
    "sg:city":"Binefar",
    "sg:orig_category":"Talleres El\u00c9ctricos Para Veh\u00cdculos",
    "sg:phone":"+34 974 42 85 29",
    "sg:postcode":"22500",
    "sg:province":"Huesca",
    "wof:name":"Auto-electricidad Lumbiarres S.l.",
    "wof:placetype":"venue"
},
  "geometry": {"coordinates":[0.3115510941,41.8281440735],"type":"Point"}
}