{
  "type": "Feature",
  "properties": {
    "iso:country":"ES",
    "sg:address":"Carr Alvarez De Castro, 6",
    "sg:city":"Girona",
    "sg:orig_category":"Librer\u00cdas",
    "sg:phone":"+34 972 20 34 29",
    "sg:postcode":"17001",
    "sg:province":"Girona",
    "wof:name":"Sociedad Anonima De Distribucion Edicion Y Librerias",
    "wof:placetype":"venue"
},
  "geometry": {"coordinates":[2.8197929859,41.9813613892],"type":"Point"}
}