{
  "type": "Feature",
  "properties": {
    "addr:full":"Calle de Carrion, 12 Bosque Madrid 28670",
    "addr:housenumber":"12",
    "addr:postcode":"28670",
    "addr:street":"Calle De Carrion",
    "iso:country":"ES",
    "sg:address":"Calle de Carrion, 12",
    "sg:city":"Bosque",
    "sg:orig_category":"Ropa Y Accesorios",
    "sg:phone":"+34 916 04 47 24",
    "sg:postcode":"28670",
    "sg:province":"Madrid",
    "wof:name":"Belchi Castellano Luis Javier",
    "wof:placetype":"venue"
},
  "geometry": {"coordinates":[-3.9228570461,40.3813972473],"type":"Point"}
}