{
  "type": "Feature",
  "properties": {
    "addr:full":"Carrer de Trafalgar, 64 Barcelona Barcelona 08010",
    "addr:housenumber":"64",
    "addr:postcode":"08010",
    "addr:street":"Carrer De Trafalgar",
    "iso:country":"ES",
    "sg:address":"Carrer de Trafalgar, 64",
    "sg:city":"Barcelona",
    "sg:orig_category":"Psic\u00d3logos",
    "sg:phone":"+34 933 15 28 19",
    "sg:postcode":"08010",
    "sg:province":"Barcelona",
    "wof:name":"Fernandez Pastor Montserrat",
    "wof:placetype":"venue"
},
  "geometry": {"coordinates":[2.1782341003,41.3902854919],"type":"Point"}
}