{
  "type": "Feature",
  "properties": {
    "iso:country":"ES",
    "sg:address":"Calle de Turnero, S/n",
    "sg:city":"Fuentes Bejar",
    "sg:orig_category":"Fabrica De Charcuter\u00cda",
    "sg:phone":"+34 923 15 17 46",
    "sg:postcode":"37790",
    "sg:province":"Salamanca",
    "wof:name":"Elaboracion De Productos Ibericos S.a.l.",
    "wof:placetype":"venue"
},
  "geometry": {"coordinates":[-5.6915998459,40.5089759827],"type":"Point"}
}