{
  "type": "Feature",
  "properties": {
    "iso:country":"ES",
    "sg:address":"Calle de Republica Argentina, 28",
    "sg:city":"Caravaca Cruz",
    "sg:orig_category":"Sindicatos De Trabajadores",
    "sg:phone":"+34 968 70 25 36",
    "sg:postcode":"30400",
    "sg:province":"Murcia",
    "wof:name":"Cc.oo.region De Murcia",
    "wof:placetype":"venue"
},
  "geometry": {"coordinates":[-1.8590190411,38.1014518738],"type":"Point"}
}