{
  "type": "Feature",
  "properties": {
    "addr:full":"Calle de Auditorium, 1 Santa Maria De Gracia Murcia 30008",
    "addr:housenumber":"1",
    "addr:postcode":"30008",
    "addr:street":"Calle De Auditorium",
    "iso:country":"ES",
    "sg:address":"Calle de Auditorium, 1",
    "sg:city":"Santa Maria De Gracia",
    "sg:orig_category":"Fabricaci\u00d3n, Distribuci\u00d3n De Material Para La Climatizaci\u00d3n, Aireaci\u00d3n Y Ventilaci\u00d3n",
    "sg:phone":"+34 968 24 20 15",
    "sg:postcode":"30008",
    "sg:province":"Murcia",
    "wof:name":"Cuartero Lorente Miguel Antonio",
    "wof:placetype":"venue"
},
  "geometry": {"coordinates":[-1.1298867464,37.9834747314],"type":"Point"}
}