{
  "type": "Feature",
  "properties": {
    "addr:full":"Calle de Emilio Thuillier, 40 Malaga M\u00e1laga 29014",
    "addr:housenumber":"40",
    "addr:postcode":"29014",
    "addr:street":"Calle De Emilio Thuillier;Ma\u0301Laga",
    "iso:country":"ES",
    "sg:address":"Calle de Emilio Thuillier, 40",
    "sg:city":"Malaga",
    "sg:orig_category":"Molduras, Junquillos, Listones Y Molduras Perforadas",
    "sg:phone":"+34 952 65 29 26",
    "sg:postcode":"29014",
    "sg:province":"M\u00e1laga",
    "wof:name":"Eurotel Sur",
    "wof:placetype":"venue"
},
  "geometry": {"coordinates":[-4.3667907715,36.8204078674],"type":"Point"}
}