{
  "type": "Feature",
  "properties": {
    "iso:country":"ES",
    "sg:address":"Avda Cristo Del Amparo, 13",
    "sg:city":"Fuensalida",
    "sg:orig_category":"Zapatos: Material, Suministros, Accesorios (fabricaci\u00d3n, Al Por Mayor)",
    "sg:phone":"+34 925 73 00 66",
    "sg:postcode":"45510",
    "sg:province":"Toledo",
    "wof:name":"Torrijos Y Alvarez S.l.",
    "wof:placetype":"venue"
},
  "geometry": {"coordinates":[-4.2110829353,40.0488319397],"type":"Point"}
}