{
  "type": "Feature",
  "properties": {
    "addr:full":"Carrer de Castillejos, 307 Barcelona Barcelona 08025",
    "addr:housenumber":"307",
    "addr:postcode":"08025",
    "addr:street":"Carrer De Castillejos",
    "iso:country":"ES",
    "sg:address":"Carrer de Castillejos, 307",
    "sg:city":"Barcelona",
    "sg:orig_category":"Zapatos (al Por Menor)",
    "sg:phone":"+34 934 35 07 04",
    "sg:postcode":"08025",
    "sg:province":"Barcelona",
    "wof:name":"Jag Dish  Singh",
    "wof:placetype":"venue"
},
  "geometry": {"coordinates":[2.1758050919,41.4086151123],"type":"Point"}
}