{
  "type": "Feature",
  "properties": {
    "iso:country":"ES",
    "sg:address":"Calle de Pedro De Valdivia, 4",
    "sg:city":"Leganes",
    "sg:orig_category":"Colchones (fabricaci\u00d3n, Al Por Mayor, Al Por Menor)",
    "sg:phone":"+34 916 94 57 36",
    "sg:postcode":"28911",
    "sg:province":"Madrid",
    "wof:name":"Torpedo Palomo Carmen",
    "wof:placetype":"venue"
},
  "geometry": {"coordinates":[-3.7671158314,40.3236923218],"type":"Point"}
}