{
  "type": "Feature",
  "properties": {
    "iso:country":"ES",
    "sg:address":"Ctra Almatriche De, 135",
    "sg:city":"Almatriche Alto",
    "sg:orig_category":"Empresas De Carpinter\u00cda Met\u00c1lica",
    "sg:phone":"+34 928 67 05 68",
    "sg:postcode":"35018",
    "sg:province":"Las Palmas",
    "wof:name":"Gonzalez Quintana Elias",
    "wof:placetype":"venue"
},
  "geometry": {"coordinates":[-15.4607486725,28.0851097107],"type":"Point"}
}