{
  "type": "Feature",
  "properties": {
    "addr:full":"Avda Juan Carlos I, 1 Gijon Asturias 33212",
    "addr:housenumber":"1",
    "addr:postcode":"33212",
    "addr:street":"Avda Juan Carlos I",
    "iso:country":"ES",
    "sg:address":"Avda Juan Carlos I, 1",
    "sg:city":"Gijon",
    "sg:orig_category":"Seguridad Social",
    "sg:phone":"+34 985 31 03 88",
    "sg:postcode":"33212",
    "sg:province":"Asturias",
    "sg:website":"www.fremap.es",
    "wof:name":"Fremap Mutua De Accidentes De Trabajo Y Enfermedades",
    "wof:placetype":"venue"
},
  "geometry": {"coordinates":[-5.6766781807,43.5396003723],"type":"Point"}
}