{
  "type": "Feature",
  "properties": {
    "addr:full":"Carrer de Josep Ant Cabanyes, 1 Poligon Industrial De Can Valero Islas Baleares 07011",
    "addr:housenumber":"1",
    "addr:postcode":"07011",
    "addr:street":"Carrer De Josep Ant Cabanyes;Islas",
    "iso:country":"ES",
    "sg:address":"Carrer de Josep Ant Cabanyes, 1",
    "sg:city":"Poligon Industrial De Can Valero",
    "sg:orig_category":"Empresas De Carpinter\u00cda",
    "sg:phone":"+34 971 75 23 61",
    "sg:postcode":"07011",
    "sg:province":"Islas Baleares",
    "wof:name":"Ventanas Y Persianas Aragon S.l",
    "wof:placetype":"venue"
},
  "geometry": {"coordinates":[2.6205170155,39.5930747986],"type":"Point"}
}