{
  "type": "Feature",
  "properties": {
    "addr:full":"Carrer de Pisuerga, 55 Terrassa Barcelona 08223",
    "addr:housenumber":"55",
    "addr:postcode":"08223",
    "addr:street":"Carrer De Pisuerga",
    "iso:country":"ES",
    "sg:address":"Carrer de Pisuerga, 55",
    "sg:city":"Terrassa",
    "sg:orig_category":"Transporte En General",
    "sg:phone":"+34 937 85 30 18",
    "sg:postcode":"08223",
    "sg:province":"Barcelona",
    "wof:name":"Se\u00f1alizaciones Jica S.a.",
    "wof:placetype":"venue"
},
  "geometry": {"coordinates":[2.0356090069,41.5476646423],"type":"Point"}
}