{
  "type": "Feature",
  "properties": {
    "addr:full":"Calle de Mayor, 12 Arenas -areeta Vizcaya 48930",
    "addr:housenumber":"12;areeta",
    "addr:postcode":"48930",
    "addr:street":"Calle De Mayor",
    "iso:country":"ES",
    "sg:address":"Calle de Mayor, 12",
    "sg:city":"Arenas -areeta",
    "sg:orig_category":"Ropa Para Se\u00d1oras (al Por Menor)",
    "sg:phone":"+34 944 64 76 81",
    "sg:postcode":"48930",
    "sg:province":"Vizcaya",
    "wof:name":"Aldigutex S.l.",
    "wof:placetype":"venue"
},
  "geometry": {"coordinates":[-2.6983869076,43.2204284668],"type":"Point"}
}