{
  "type": "Feature",
  "properties": {
    "addr:full":"Pg Maragall, 253 Barcelona Barcelona 08032",
    "addr:housenumber":"253",
    "addr:postcode":"08032",
    "addr:street":"Pg Maragall",
    "iso:country":"ES",
    "sg:address":"Pg Maragall, 253",
    "sg:city":"Barcelona",
    "sg:orig_category":"Ortofonistas",
    "sg:phone":"+34 934 55 55 25",
    "sg:postcode":"08032",
    "sg:province":"Barcelona",
    "wof:name":"Gabinet D'osteopatia I Kinesiologia",
    "wof:placetype":"venue"
},
  "geometry": {"coordinates":[2.1740179062,41.4260025024],"type":"Point"}
}