{
  "type": "Feature",
  "properties": {
    "iso:country":"ES",
    "sg:address":"Avda Europa, 73",
    "sg:city":"Malaga",
    "sg:orig_category":"Muebles Y Accesorios Para Cocinas Y Cuartos De Ba\u00d1o (al Por Menor)",
    "sg:phone":"+34 952 91 97 12",
    "sg:postcode":"29003",
    "sg:province":"M\u00e1laga",
    "wof:name":"Tu Ba\u00d1o Malaga Sl",
    "wof:placetype":"venue"
},
  "geometry": {"coordinates":[-4.4486398697,36.7015380859],"type":"Point"}
}