{
  "type": "Feature",
  "properties": {
    "addr:full":"Calle de Paseo De Espa\u00d1a, 8 Rambla C\u00f3rdoba 14540",
    "addr:housenumber":"8",
    "addr:postcode":"14540",
    "addr:street":"Calle De Paseo De Espan\u0303A;Co\u0301Rdoba",
    "iso:country":"ES",
    "sg:address":"Calle de Paseo De Espa\u00d1a, 8",
    "sg:city":"Rambla",
    "sg:orig_category":"Aceites Y Grasas Alimentarias (fabricaci\u00d3n, Al Por Mayor)",
    "sg:phone":"+34 957 68 41 15",
    "sg:postcode":"14540",
    "sg:province":"C\u00f3rdoba",
    "wof:name":"Cooperativa Olivarera Nuestro Padre Jesus Nazareno",
    "wof:placetype":"venue"
},
  "geometry": {"coordinates":[-4.7416338921,37.6080932617],"type":"Point"}
}