{
  "type": "Feature",
  "properties": {
    "addr:full":"Camino Algudor, S/n Silla Valencia 46460",
    "addr:housenumber":"s",
    "addr:postcode":"46460",
    "addr:street":"Camino Algudor;/ N",
    "iso:country":"ES",
    "sg:address":"Camino Algudor, S/n",
    "sg:city":"Silla",
    "sg:orig_category":"Comercio De Piezas De Recambio Y De Accesorios De Veh\u00cdculos, Veh\u00cdculos Industriales",
    "sg:phone":"+34 961 21 35 07",
    "sg:postcode":"46460",
    "sg:province":"Valencia",
    "wof:name":"Intolmot S.l.",
    "wof:placetype":"venue"
},
  "geometry": {"coordinates":[-0.417858988,39.3685531616],"type":"Point"}
}