{
  "type": "Feature",
  "properties": {
    "iso:country":"ES",
    "sg:address":"Carrer de Reial, 34",
    "sg:city":"Tarragona",
    "sg:orig_category":"Venta, Montaje De Neum\u00c1ticos",
    "sg:phone":"+34 977 21 16 26",
    "sg:postcode":"43004",
    "sg:province":"Tarragona",
    "wof:name":"Neumaticos Sevil S. A.",
    "wof:placetype":"venue"
},
  "geometry": {"coordinates":[1.2456519604,41.1113471985],"type":"Point"}
}