{
  "type": "Feature",
  "properties": {
    "iso:country":"ES",
    "sg:address":"Carrer de Francisco Rodriguez, 31",
    "sg:city":"Ametlla Mar",
    "sg:orig_category":"Empresas De Pintura Y Revestimientos",
    "sg:phone":"+34 977 45 70 24",
    "sg:postcode":"43860",
    "sg:province":"Tarragona",
    "wof:name":"Gracia Garcia Jose Luis De",
    "wof:placetype":"venue"
},
  "geometry": {"coordinates":[0.7991070151,40.8824234009],"type":"Point"}
}