{
  "type": "Feature",
  "properties": {
    "iso:country":"ES",
    "sg:address":"Rua Maria, 31",
    "sg:city":"Ferrol",
    "sg:orig_category":"Pod\u00d3logos: Pedicuros",
    "sg:phone":"+34 981 35 30 68",
    "sg:postcode":"15402",
    "sg:province":"La Coru\u00f1a",
    "wof:name":"Perez Carracedo Maria Clara",
    "wof:placetype":"venue"
},
  "geometry": {"coordinates":[-8.2310171127,43.4855079651],"type":"Point"}
}