{
  "type": "Feature",
  "properties": {
    "iso:country":"ES",
    "sg:address":"Carr Bonavista, 29",
    "sg:city":"Bellcaire D'urgell",
    "sg:orig_category":"Producci\u00d3n, Venta De Productos De Agricultura Biol\u00d3gica",
    "sg:phone":"+34 973 58 60 37",
    "sg:postcode":"25337",
    "sg:province":"Lleida",
    "wof:name":"Aston Consult S.l.",
    "wof:placetype":"venue"
},
  "geometry": {"coordinates":[0.9087305069,41.7579078674],"type":"Point"}
}