{
  "type": "Feature",
  "properties": {
    "addr:full":"Avda General Aviles, 11 Valencia Valencia 46015",
    "addr:housenumber":"11",
    "addr:postcode":"46015",
    "addr:street":"Avda General Aviles",
    "iso:country":"ES",
    "sg:address":"Avda General Aviles, 11",
    "sg:city":"Valencia",
    "sg:orig_category":"Ropa Para Se\u00d1oras (al Por Menor)",
    "sg:phone":"+34 963 47 00 86",
    "sg:postcode":"46015",
    "sg:province":"Valencia",
    "wof:name":"Gallart Gorriz Maria Carmen",
    "wof:placetype":"venue"
},
  "geometry": {"coordinates":[-0.3916719854,39.4875488281],"type":"Point"}
}