{
  "type": "Feature",
  "properties": {
    "addr:full":"Aeport. Barajas Mu\u00f1oza, S/n Madrid Madrid 28042",
    "addr:housenumber":"s / n",
    "addr:postcode":"28042",
    "iso:country":"ES",
    "sg:address":"Aeport. Barajas Mu\u00f1oza, S/n",
    "sg:city":"Madrid",
    "sg:orig_category":"Transportes Internacionales",
    "sg:phone":"+34 913 12 01 22",
    "sg:postcode":"28042",
    "sg:province":"Madrid",
    "sg:website":"www.lamaignere.es",
    "wof:name":"Lamaignere S.a.",
    "wof:placetype":"venue"
},
  "geometry": {"coordinates":[-3.7057740688,40.42029953],"type":"Point"}
}