{
  "type": "Feature",
  "properties": {
    "addr:full":"Carr Santiago Rusi\u00d1ol, 69 Badalona Barcelona 08911",
    "addr:housenumber":"69",
    "addr:postcode":"08911",
    "addr:street":"Carr Santiago Rusin\u0303Ol",
    "iso:country":"ES",
    "sg:address":"Carr Santiago Rusi\u00d1ol, 69",
    "sg:city":"Badalona",
    "sg:orig_category":"Estancos",
    "sg:phone":"+34 933 84 24 95",
    "sg:postcode":"08911",
    "sg:province":"Barcelona",
    "wof:name":"Gomariz Perez Miguel",
    "wof:placetype":"venue"
},
  "geometry": {"coordinates":[2.2537109852,41.4526977539],"type":"Point"}
}