{
  "type": "Feature",
  "properties": {
    "addr:full":"Calle de Milagro, 3 Hellin Albacete 02400",
    "addr:housenumber":"3",
    "addr:postcode":"02400",
    "addr:street":"Calle De Milagro",
    "iso:country":"ES",
    "sg:address":"Calle de Milagro, 3",
    "sg:city":"Hellin",
    "sg:orig_category":"Comunidades Religiosas",
    "sg:phone":"+34 967 30 78 62",
    "sg:postcode":"02400",
    "sg:province":"Albacete",
    "wof:name":"Hermandad San Antonio Abad",
    "wof:placetype":"venue"
},
  "geometry": {"coordinates":[-1.6992299557,38.5149765015],"type":"Point"}
}