{
  "type": "Feature",
  "properties": {
    "iso:country":"ES",
    "sg:address":"Calle de Novena, 2",
    "sg:city":"Cadiz",
    "sg:orig_category":"Confecci\u00d3n De Trajes Para Se\u00d1oras",
    "sg:phone":"+34 956 21 39 95",
    "sg:postcode":"11001",
    "sg:province":"C\u00e1diz",
    "wof:name":"Isidro Tovar S. A.",
    "wof:placetype":"venue"
},
  "geometry": {"coordinates":[-6.2963790894,36.5323982239],"type":"Point"}
}