{
  "type": "Feature",
  "properties": {
    "addr:full":"Avgd Madrid, 18 Lleida Lleida 25002",
    "addr:housenumber":"18",
    "addr:postcode":"25002",
    "addr:street":"Madrid",
    "iso:country":"ES",
    "sg:address":"Avgd Madrid, 18",
    "sg:city":"Lleida",
    "sg:orig_category":"Peluquer\u00cdas, Peluquer\u00cda Mixta",
    "sg:phone":"+34 973 28 21 24",
    "sg:postcode":"25002",
    "sg:province":"Lleida",
    "wof:name":"Top Hair Systems S.l.",
    "wof:placetype":"venue"
},
  "geometry": {"coordinates":[0.6247159839,41.6126556396],"type":"Point"}
}