{
  "type": "Feature",
  "properties": {
    "addr:full":"Carrer de Numero 60 De La Zona Franca, 584 Barcelona Barcelona 08040",
    "addr:housenumber":"584",
    "addr:postcode":"08040",
    "addr:street":"Carrer De Numero 60 De La;Franca",
    "iso:country":"ES",
    "sg:address":"Carrer de Numero 60 De La Zona Franca, 584",
    "sg:city":"Barcelona",
    "sg:orig_category":"Agentes, Concesionarios Y Sucursales De Camiones Y Veh\u00cdculos Industriales",
    "sg:phone":"+34 932 23 45 26",
    "sg:postcode":"08040",
    "sg:province":"Barcelona",
    "wof:name":"Veinsur S.a.",
    "wof:placetype":"venue"
},
  "geometry": {"coordinates":[2.1454870701,41.3474082947],"type":"Point"}
}