{
  "type": "Feature",
  "properties": {
    "iso:country":"ES",
    "sg:address":"Calle de Kristo, S/n",
    "sg:city":"Plentzia",
    "sg:orig_category":"Empresas De Carpinter\u00cda De Madera",
    "sg:phone":"+34 946 77 04 58",
    "sg:postcode":"48620",
    "sg:province":"Vizcaya",
    "wof:name":"Aramayona Esturo Jose Benito",
    "wof:placetype":"venue"
},
  "geometry": {"coordinates":[-2.9462594986,43.4041519165],"type":"Point"}
}