{
  "type": "Feature",
  "properties": {
    "iso:country":"ES",
    "sg:address":"Calle de Becerro De Bengoa, 9",
    "sg:city":"Palencia",
    "sg:orig_category":"Carnicer\u00cdas, Carnicer\u00cdas",
    "sg:phone":"+34 979 70 00 38",
    "sg:postcode":"34002",
    "sg:province":"Palencia",
    "wof:name":"Aguado Del Vado Jesus",
    "wof:placetype":"venue"
},
  "geometry": {"coordinates":[-4.5310091972,42.009059906],"type":"Point"}
}