{
  "type": "Feature",
  "properties": {
    "addr:full":"Calle de Pintor Juan Bautista Porcar, 7 Valencia Valencia 46019",
    "addr:housenumber":"7",
    "addr:postcode":"46019",
    "addr:street":"Calle De Pintor Juan Bautista Porcar",
    "iso:country":"ES",
    "sg:address":"Calle de Pintor Juan Bautista Porcar, 7",
    "sg:city":"Valencia",
    "sg:orig_category":"Agencias Y Asesores De Publicidad",
    "sg:phone":"+34 963 65 11 24",
    "sg:postcode":"46019",
    "sg:province":"Valencia",
    "wof:name":"Denver Iberica S. A.",
    "wof:placetype":"venue"
},
  "geometry": {"coordinates":[-0.377252996,39.4950561523],"type":"Point"}
}