{
  "type": "Feature",
  "properties": {
    "iso:country":"ES",
    "sg:address":"Piececicos, 1",
    "sg:city":"Carboneras",
    "sg:orig_category":"Pr\u00c1ctica Del Submarinismo Y De Deportes Y Actividades Subacu\u00c1ticos",
    "sg:phone":"+34 950 45 44 71",
    "sg:postcode":"04140",
    "sg:province":"Almer\u00eda",
    "wof:name":"Desarrollo Del Ocio Acuatico S.l.",
    "wof:placetype":"venue"
},
  "geometry": {"coordinates":[-1.8962140083,36.9957046509],"type":"Point"}
}