{
  "type": "Feature",
  "properties": {
    "iso:country":"ES",
    "sg:address":"Avda Francia (de), 13",
    "sg:city":"Playa Del Ingles",
    "sg:orig_category":"Supermercados Y Hipermercados",
    "sg:phone":"+34 928 77 18 77",
    "sg:postcode":"35100",
    "sg:province":"Las Palmas",
    "wof:name":"Supermercados Herdisa S.l.",
    "wof:placetype":"venue"
},
  "geometry": {"coordinates":[-15.5794820786,27.7506103516],"type":"Point"}
}