{
  "type": "Feature",
  "properties": {
    "iso:country":"ES",
    "sg:address":"Avda Milan (de), 16",
    "sg:city":"Azuqueca Henares",
    "sg:orig_category":"Venta, Instalaci\u00d3n De Calefacci\u00d3n",
    "sg:phone":"+34 949 26 41 60",
    "sg:postcode":"19200",
    "sg:province":"Guadalajara",
    "wof:name":"Calefaccion Y Fontaneria Antonio Merino S.l.",
    "wof:placetype":"venue"
},
  "geometry": {"coordinates":[-3.2554500103,40.5653114319],"type":"Point"}
}