{
  "type": "Feature",
  "properties": {
    "addr:full":"Carretera De Quintanar, S/n Salas Infantes Burgos 09600",
    "addr:housenumber":"s / n",
    "addr:postcode":"09600",
    "addr:street":"Carretera De Quintanar",
    "iso:country":"ES",
    "sg:address":"Carretera De Quintanar, S/n",
    "sg:city":"Salas Infantes",
    "sg:orig_category":"Ense\u00d1anza Secundaria: Colegios Y Escuelas Privadas",
    "sg:phone":"+34 947 38 02 81",
    "sg:postcode":"09600",
    "sg:province":"Burgos",
    "wof:name":"I.e.s. Alfoz De Lara",
    "wof:placetype":"venue"
},
  "geometry": {"coordinates":[-3.2826690674,42.0228996277],"type":"Point"}
}