{
  "type": "Feature",
  "properties": {
    "addr:full":"Calle de Gerald Brenan, 5 Malaga M\u00e1laga 29005",
    "addr:housenumber":"5",
    "addr:postcode":"29005",
    "addr:street":"Calle De Gerald Brenan;Ma\u0301Laga",
    "iso:country":"ES",
    "sg:address":"Calle de Gerald Brenan, 5",
    "sg:city":"Malaga",
    "sg:orig_category":"Productos Qu\u00cdmicos (fabricaci\u00d3n, Al Por Mayor)",
    "sg:phone":"+34 952 24 24 29",
    "sg:postcode":"29005",
    "sg:province":"M\u00e1laga",
    "wof:name":"Comercial Distribuidora Ia\u00f1ez S.a.",
    "wof:placetype":"venue"
},
  "geometry": {"coordinates":[-4.4732589722,36.6890068054],"type":"Point"}
}