{
  "type": "Feature",
  "properties": {
    "addr:full":"Calle de Villa De Marin, 34 Madrid Madrid 28029",
    "addr:housenumber":"34",
    "addr:postcode":"madrid;28029",
    "addr:street":"Calle De Villa De Marin",
    "iso:country":"ES",
    "sg:address":"Calle de Villa De Marin, 34",
    "sg:city":"Madrid",
    "sg:orig_category":"Vinos (agentes)",
    "sg:phone":"+34 913 14 64 65",
    "sg:postcode":"28029",
    "sg:province":"Madrid",
    "sg:website":"www.labodegadelalcalde.com",
    "wof:name":"Alcalde Jimenez Juan Bautista",
    "wof:placetype":"venue"
},
  "geometry": {"coordinates":[-3.698964119,40.4772071838],"type":"Point"}
}