{
  "type": "Feature",
  "properties": {
    "addr:full":"Pque San Adrian, 5 Logro\u00f1o La Rioja 26006",
    "addr:housenumber":"5",
    "addr:postcode":"26006",
    "addr:street":"Adrian;Rioja",
    "iso:country":"ES",
    "sg:address":"Pque San Adrian, 5",
    "sg:city":"Logro\u00f1o",
    "sg:classifiers":[
        {
            "category":"Arts & Performance",
            "subcategory":"Art Gallery",
            "type":"Entertainment"
        }
    ],
    "sg:phone":"+34 941 51 04 02",
    "sg:postcode":"26006",
    "sg:province":"La Rioja",
    "sg:tags":[
        "arte",
        "de",
        "galer\u00cdas"
    ],
    "wof:name":"Pauters S.c.",
    "wof:placetype":"venue"
},
  "geometry": {"coordinates":[-2.4036989212,42.46043396],"type":"Point"}
}