{
  "type": "Feature",
  "properties": {
    "addr:full":"Calle de San Graciano, 11 Madrid Madrid 28026",
    "addr:housenumber":"11",
    "addr:postcode":"madrid;28026",
    "addr:street":"Calle De San Graciano",
    "iso:country":"ES",
    "sg:address":"Calle de San Graciano, 11",
    "sg:city":"Madrid",
    "sg:orig_category":"Maquinaria Para Industrias Diversas",
    "sg:phone":"+34 914 75 27 97",
    "sg:postcode":"28026",
    "sg:province":"Madrid",
    "wof:name":"Rentecnika Iberica S.a.",
    "wof:placetype":"venue"
},
  "geometry": {"coordinates":[-3.7038197517,40.3922996521],"type":"Point"}
}