{
  "type": "Feature",
  "properties": {
    "iso:country":"ES",
    "sg:address":"Ctra Nova, 73",
    "sg:city":"Garriga",
    "sg:orig_category":"Artes Gr\u00c1ficas, Artes Pl\u00c1sticas (curso)",
    "sg:phone":"+34 938 71 43 82",
    "sg:postcode":"08530",
    "sg:province":"Barcelona",
    "wof:name":"Badia Fernandez Juan",
    "wof:placetype":"venue"
},
  "geometry": {"coordinates":[2.2827236652,41.6824455261],"type":"Point"}
}