{
  "type": "Feature",
  "properties": {
    "iso:country":"ES",
    "sg:address":"Calle de Ramon J. Sender, 2",
    "sg:city":"Alca\u00f1iz",
    "sg:orig_category":"Institutos De Belleza",
    "sg:phone":"+34 978 83 41 31",
    "sg:postcode":"44600",
    "sg:province":"Teruel",
    "wof:name":"Alquezar Lizana Sandra",
    "wof:placetype":"venue"
},
  "geometry": {"coordinates":[-0.1290044039,41.0518569946],"type":"Point"}
}