{
  "type": "Feature",
  "properties": {
    "iso:country":"ES",
    "sg:address":"Calle de Arapiles, 4",
    "sg:city":"Jaraiz Vera",
    "sg:orig_category":"Transportes Por V\u00cdas Navegables",
    "sg:phone":"+34 927 46 04 67",
    "sg:postcode":"10400",
    "sg:province":"C\u00e1ceres",
    "wof:name":"Amor Mu\u00f1oz Juan Carlos",
    "wof:placetype":"venue"
},
  "geometry": {"coordinates":[-5.7508087158,40.0600013733],"type":"Point"}
}