{
  "type": "Feature",
  "properties": {
    "addr:full":"Trva Puente Virrey, 60 Zaragoza Zaragoza 50007",
    "addr:housenumber":"60",
    "addr:postcode":"50007",
    "addr:street":"Trva Puente Virrey",
    "iso:country":"ES",
    "sg:address":"Trva Puente Virrey, 60",
    "sg:city":"Zaragoza",
    "sg:orig_category":"Negocio De Enlosados, Soler\u00cdas",
    "sg:phone":"+34 976 38 65 80",
    "sg:postcode":"50007",
    "sg:province":"Zaragoza",
    "wof:name":"Arguedas Concha Melquiades",
    "wof:placetype":"venue"
},
  "geometry": {"coordinates":[-0.8752650023,41.6347236633],"type":"Point"}
}