{
  "type": "Feature",
  "properties": {
    "iso:country":"ES",
    "sg:address":"Cmno Viejo Del Puerto, 76",
    "sg:city":"Alberquilla",
    "sg:orig_category":"Cuartos De Ba\u00d1o: Aparatos Sanitarios (fabricaci\u00d3n)",
    "sg:phone":"+34 968 47 78 93",
    "sg:postcode":"30800",
    "sg:province":"Murcia",
    "wof:name":"Especialistas En Ba\u00f1o S.l.",
    "wof:placetype":"venue"
},
  "geometry": {"coordinates":[-1.6905640364,37.680557251],"type":"Point"}
}