{
  "type": "Feature",
  "properties": {
    "iso:country":"ES",
    "sg:address":"Calle de Pimienta, 38",
    "sg:city":"Alcala Rio",
    "sg:orig_category":"Caf\u00c9s, Bares, Cervecer\u00cdas",
    "sg:phone":"+34 955 65 07 72",
    "sg:postcode":"41200",
    "sg:province":"Sevilla",
    "wof:name":"Fernandez Mendez Francisco",
    "wof:placetype":"venue"
},
  "geometry": {"coordinates":[-5.9817891121,37.51820755],"type":"Point"}
}