{
  "type": "Feature",
  "properties": {
    "addr:full":"Avda Domingo Bueno, 59 Pontenova Pontevedra 36400",
    "addr:housenumber":"59",
    "addr:postcode":"36400",
    "addr:street":"Avda Domingo Bueno",
    "iso:country":"ES",
    "sg:address":"Avda Domingo Bueno, 59",
    "sg:city":"Pontenova",
    "sg:orig_category":"Tintes (fabricaci\u00d3n, Al Por Mayor)",
    "sg:phone":"+34 986 33 94 26",
    "sg:postcode":"36400",
    "sg:province":"Pontevedra",
    "wof:name":"Rodriguez Martinez Noelia",
    "wof:placetype":"venue"
},
  "geometry": {"coordinates":[-8.6179990768,42.1610298157],"type":"Point"}
}