{
  "type": "Feature",
  "properties": {
    "iso:country":"ES",
    "sg:address":"Carrer de Capita Mirambell, 48",
    "sg:city":"Masnou",
    "sg:orig_category":"Promotores Constructores",
    "sg:phone":"+34 935 40 29 60",
    "sg:postcode":"08320",
    "sg:province":"Barcelona",
    "wof:name":"Nairac Construccion Y Rehabilitacion S. L.",
    "wof:placetype":"venue"
},
  "geometry": {"coordinates":[2.3248460293,41.4813041687],"type":"Point"}
}