{
  "type": "Feature",
  "properties": {
    "addr:full":"Avda Doctor Manuel Lopez Vazquez, 25 Sanlucar De Barrameda C\u00e1diz 11540",
    "addr:housenumber":"25",
    "addr:postcode":"11540",
    "addr:street":"Avda Doctor Manuel;Vazquez;Ca\u0301Diz",
    "iso:country":"ES",
    "sg:address":"Avda Doctor Manuel Lopez Vazquez, 25",
    "sg:city":"Sanlucar De Barrameda",
    "sg:orig_category":"Empresas De Carpinter\u00cda De Madera",
    "sg:phone":"+34 956 36 81 77",
    "sg:postcode":"11540",
    "sg:province":"C\u00e1diz",
    "wof:name":"Muebles Do\u00f1ana S.l.",
    "wof:placetype":"venue"
},
  "geometry": {"coordinates":[-6.3389701843,36.771572113],"type":"Point"}
}