{
  "type": "Feature",
  "properties": {
    "addr:full":"Avda Ramon Y Cajal, 28 Dos Hermanas Sevilla 41700",
    "addr:housenumber":"28",
    "addr:postcode":"41700",
    "addr:street":"Avda Ramon Y Cajal",
    "iso:country":"ES",
    "sg:address":"Avda Ramon Y Cajal, 28",
    "sg:city":"Dos Hermanas",
    "sg:orig_category":"Frutas Y Legumbres Frescas (al Por Mayor)",
    "sg:phone":"+34 954 72 11 16",
    "sg:postcode":"41700",
    "sg:province":"Sevilla",
    "wof:name":"Martin Morro Encarnacion",
    "wof:placetype":"venue"
},
  "geometry": {"coordinates":[-5.924738884,37.2960700989],"type":"Point"}
}