{
  "type": "Feature",
  "properties": {
    "iso:country":"ES",
    "sg:address":"Calle de Nueva, 7",
    "sg:city":"Gilena",
    "sg:orig_category":"Poller\u00cda Y Caza (al Por Menor)",
    "sg:phone":"+34 955 82 65 78",
    "sg:postcode":"41565",
    "sg:province":"Sevilla",
    "wof:name":"Pozo Gomez Carmen",
    "wof:placetype":"venue"
},
  "geometry": {"coordinates":[-4.9138169289,37.251209259],"type":"Point"}
}