{
  "type": "Feature",
  "properties": {
    "addr:full":"Calle de Anton De Medellin, 2 Alcala Guadaira Sevilla 41500",
    "addr:housenumber":"2",
    "addr:postcode":"41500",
    "addr:street":"Calle De Anton De Medellin",
    "iso:country":"ES",
    "sg:address":"Calle de Anton De Medellin, 2",
    "sg:city":"Alcala Guadaira",
    "sg:orig_category":"Parques De Atracciones Y Centros De Esparcimiento",
    "sg:phone":"+34 955 61 17 94",
    "sg:postcode":"41500",
    "sg:province":"Sevilla",
    "wof:name":"Recreativos Sagar S. L.",
    "wof:placetype":"venue"
},
  "geometry": {"coordinates":[-5.8368091583,37.3403625488],"type":"Point"}
}