{
  "type": "Feature",
  "properties": {
    "addr:full":"Carrer de Cartagena, 327 Barcelona Barcelona 08025",
    "addr:housenumber":"327",
    "addr:postcode":"08025",
    "addr:street":"Carrer De Cartagena",
    "iso:country":"ES",
    "sg:address":"Carrer de Cartagena, 327",
    "sg:city":"Barcelona",
    "sg:orig_category":"Artes Gr\u00c1ficas, Artes Pl\u00c1sticas: Material Y Suministros (al Por Menor)",
    "sg:phone":"+34 934 56 45 32",
    "sg:postcode":"08025",
    "sg:province":"Barcelona",
    "wof:name":"Lafuente Muriel Raquel",
    "wof:placetype":"venue"
},
  "geometry": {"coordinates":[2.1734640598,41.4116630554],"type":"Point"}
}