{
  "type": "Feature",
  "properties": {
    "iso:country":"ES",
    "sg:address":"Maritima, 41",
    "sg:city":"Puerto Santiago",
    "sg:orig_category":"Art\u00cdculos De Regalo (al Por Menor)",
    "sg:phone":"+34 922 86 80 34",
    "sg:postcode":"38683",
    "sg:province":"Santa Cruz De Tenerife",
    "wof:name":"Ambama Inversiones S.l.",
    "wof:placetype":"venue"
},
  "geometry": {"coordinates":[-16.8404922485,28.2292499542],"type":"Point"}
}