{
  "type": "Feature",
  "properties": {
    "iso:country":"ES",
    "sg:address":"Carr Galicia, 44",
    "sg:city":"Eivissa",
    "sg:orig_category":"Agencias De Viajes",
    "sg:phone":"+34 971 39 47 86",
    "sg:postcode":"07800",
    "sg:province":"Islas Baleares",
    "wof:name":"Viajes Canora S.a.u.",
    "wof:placetype":"venue"
},
  "geometry": {"coordinates":[1.4203970432,38.9052696228],"type":"Point"}
}