{
  "type": "Feature",
  "properties": {
    "addr:full":"Calle de Bartolome Pancorbo, 4 Malaga M\u00e1laga 29003",
    "addr:housenumber":"4",
    "addr:postcode":"29003",
    "addr:street":"Calle De Bartolome Pancorbo;Ma\u0301Laga",
    "iso:country":"ES",
    "sg:address":"Calle de Bartolome Pancorbo, 4",
    "sg:city":"Malaga",
    "sg:orig_category":"Carnicer\u00cdas, Carnicer\u00cdas",
    "sg:phone":"+34 952 32 07 67",
    "sg:postcode":"29003",
    "sg:province":"M\u00e1laga",
    "wof:name":"Alcaide Moreno Alberto",
    "wof:placetype":"venue"
},
  "geometry": {"coordinates":[-4.4404420853,36.7053604126],"type":"Point"}
}