{
  "type": "Feature",
  "properties": {
    "iso:country":"ES",
    "sg:address":"Lamas, S/n",
    "sg:city":"Lamas",
    "sg:orig_category":"Empresas De Desmonte",
    "sg:phone":"+34 981 80 92 34",
    "sg:postcode":"15885",
    "sg:province":"A Coru\u00f1a",
    "wof:name":"Sobredo Rosende Manuel",
    "wof:placetype":"venue"
},
  "geometry": {"coordinates":[-8.481803894,42.7759590149],"type":"Point"}
}