{
  "type": "Feature",
  "properties": {
    "addr:full":"Calle de Grazalema, 58 Arcos Frontera C\u00e1diz 11630",
    "addr:housenumber":"58",
    "addr:postcode":"11630",
    "addr:street":"Calle De Grazalema",
    "iso:country":"ES",
    "sg:address":"Calle de Grazalema, 58",
    "sg:city":"Arcos Frontera",
    "sg:orig_category":"Molduras, Junquillos, Listones Y Molduras Perforadas",
    "sg:phone":"+34 956 70 40 24",
    "sg:postcode":"11630",
    "sg:province":"C\u00e1diz",
    "wof:name":"Temblador Santana Cristobal",
    "wof:placetype":"venue"
},
  "geometry": {"coordinates":[-5.80849123,36.7527313232],"type":"Point"}
}