{
  "type": "Feature",
  "properties": {
    "iso:country":"ES",
    "sg:address":"Moli Tartareu, S/n",
    "sg:city":"Os De Balaguer",
    "sg:orig_category":"Asociaciones Humanitarias, De Cooperaci\u00d3n, De Acci\u00d3n Social",
    "sg:phone":"+34 973 43 81 18",
    "sg:postcode":"25610",
    "sg:province":"Lleida",
    "wof:name":"Asociacion Amigos De San Jose Del Molino",
    "wof:placetype":"venue"
},
  "geometry": {"coordinates":[0.6867939234,41.8878250122],"type":"Point"}
}