{
  "type": "Feature",
  "properties": {
    "iso:country":"ES",
    "sg:address":"Calle de Condes De Castilfale, 6",
    "sg:city":"Burgos",
    "sg:orig_category":"Fotocopias, Reprograf\u00cda",
    "sg:phone":"+34 947 46 18 48",
    "sg:postcode":"09001",
    "sg:province":"Burgos",
    "wof:name":"Amabardos S.l.",
    "wof:placetype":"venue"
},
  "geometry": {"coordinates":[-3.7257444859,42.3378829956],"type":"Point"}
}