{
  "type": "Feature",
  "properties": {
    "addr:full":"Avda Tres D'abril, 28 Puerto Valencia 46520",
    "addr:housenumber":"28",
    "addr:postcode":"46520",
    "addr:street":"Avda Tres D'Abril",
    "iso:country":"ES",
    "sg:address":"Avda Tres D'abril, 28",
    "sg:city":"Puerto",
    "sg:orig_category":"Mec\u00c1nico Del Autom\u00d3vil",
    "sg:phone":"+34 962 68 02 16",
    "sg:postcode":"46520",
    "sg:province":"Valencia",
    "wof:name":"Ruiz Lopez Mario",
    "wof:placetype":"venue"
},
  "geometry": {"coordinates":[-3.5711700916,40.4225273132],"type":"Point"}
}