{
  "type": "Feature",
  "properties": {
    "addr:full":"Plaz Mayor, S/n Tagarabuena Zamora 49836",
    "addr:housenumber":"s",
    "addr:postcode":"49836",
    "addr:street":"Plaz Mayor;/ N Tagarabuena Zamora",
    "iso:country":"ES",
    "sg:address":"Plaz Mayor, S/n",
    "sg:city":"Tagarabuena",
    "sg:orig_category":"Sanatorios M\u00c9dico",
    "sg:phone":"+34 980 69 13 37",
    "sg:postcode":"49836",
    "sg:province":"Zamora",
    "wof:name":"Ayuntamiento De Toro",
    "wof:placetype":"venue"
},
  "geometry": {"coordinates":[-5.3890790939,41.5409698486],"type":"Point"}
}