{
  "type": "Feature",
  "properties": {
    "addr:full":"Joaquin Beunza, 22 Iru\u00f1a Navarra 31014",
    "addr:housenumber":"22",
    "addr:postcode":"31014",
    "addr:street":"Joaquin Beunza",
    "iso:country":"ES",
    "sg:address":"Joaquin Beunza, 22",
    "sg:city":"Iru\u00f1a",
    "sg:orig_category":"Comercio De Mobiliario De Oficina",
    "sg:phone":"+34 948 38 25 49",
    "sg:postcode":"31014",
    "sg:province":"Navarra",
    "wof:name":"Proyeccion Equipamiento Y Mobiliario S.l.",
    "wof:placetype":"venue"
},
  "geometry": {"coordinates":[-1.6543090343,42.8255271912],"type":"Point"}
}