{
  "type": "Feature",
  "properties": {
    "iso:country":"ES",
    "sg:address":"Ctra. Jinamar, S/n",
    "sg:city":"Jinamar",
    "sg:orig_category":"Control T\u00c9cnico De Veh\u00cdculos",
    "sg:phone":"+34 928 71 00 77",
    "sg:postcode":"35220",
    "sg:province":"Las Palmas",
    "sg:website":"www.appluscor.com",
    "wof:name":"Applus Iteuve Technology S.l.",
    "wof:placetype":"venue"
},
  "geometry": {"coordinates":[-15.4178791046,28.0356445312],"type":"Point"}
}