{
  "type": "Feature",
  "properties": {
    "iso:country":"ES",
    "sg:address":"Calle de Catadores, 11",
    "sg:city":"Conil De La Frontera",
    "sg:orig_category":"Centros Empresariales",
    "sg:phone":"+34 956 44 28 35",
    "sg:postcode":"11140",
    "sg:province":"C\u00e1diz",
    "wof:name":"Rodriguez Guerrero Maria Jose",
    "wof:placetype":"venue"
},
  "geometry": {"coordinates":[-6.0891714096,36.2790679932],"type":"Point"}
}