{
  "type": "Feature",
  "properties": {
    "addr:full":"Calle de Antonio Sacramento (escultor), 17 Valencia Valencia 46013",
    "addr:housenumber":"17",
    "addr:postcode":"46013",
    "addr:street":"Calle De Antonio Sacramento Escultor",
    "iso:country":"ES",
    "sg:address":"Calle de Antonio Sacramento (escultor), 17",
    "sg:city":"Valencia",
    "sg:orig_category":"Molduras, Junquillos, Listones Y Molduras Perforadas",
    "sg:phone":"+34 963 73 92 17",
    "sg:postcode":"46013",
    "sg:province":"Valencia",
    "wof:name":"Valero Y Sanz S. L.",
    "wof:placetype":"venue"
},
  "geometry": {"coordinates":[-0.3577680886,39.4540100098],"type":"Point"}
}