{
  "type": "Feature",
  "properties": {
    "iso:country":"ES",
    "sg:address":"Plaz Uncibay, 9",
    "sg:city":"Malaga",
    "sg:orig_category":"Agencias Y Asesores De Publicidad",
    "sg:phone":"+34 952 06 08 06",
    "sg:postcode":"29008",
    "sg:province":"M\u00e1laga",
    "wof:name":"Ameka Publicidady Comercial Estrategica S.l.",
    "wof:placetype":"venue"
},
  "geometry": {"coordinates":[-4.4227104187,36.7235832214],"type":"Point"}
}