{
  "type": "Feature",
  "properties": {
    "addr:full":"Calle de San Joaquin, 25 Campohermoso Almer\u00eda 04110",
    "addr:housenumber":"25",
    "addr:postcode":"04110",
    "addr:street":"Calle De San Joaquin;Almeri\u0301A",
    "iso:country":"ES",
    "sg:address":"Calle de San Joaquin, 25",
    "sg:city":"Campohermoso",
    "sg:orig_category":"Cajas De Ahorro",
    "sg:phone":"+34 950 38 64 40",
    "sg:postcode":"04110",
    "sg:province":"Almer\u00eda",
    "sg:website":"www.lacaixa.es",
    "wof:name":"Caixa D'estalvis I Pensions De Barcelona",
    "wof:placetype":"venue"
},
  "geometry": {"coordinates":[-2.1322340965,36.9380836487],"type":"Point"}
}