{
  "type": "Feature",
  "properties": {
    "iso:country":"ES",
    "sg:address":"Calle de Real, 6",
    "sg:city":"San Pablo De Buceite",
    "sg:orig_category":"Estancos",
    "sg:phone":"+34 956 64 22 33",
    "sg:postcode":"11320",
    "sg:province":"C\u00e1diz",
    "wof:name":"Rubio Andrades Antonio",
    "wof:placetype":"venue"
},
  "geometry": {"coordinates":[-5.4136428833,36.4661178589],"type":"Point"}
}