{
  "type": "Feature",
  "properties": {
    "addr:full":"Calle de San Juan Bautista, 36 Rozas De Madrid Madrid 28230",
    "addr:housenumber":"36",
    "addr:postcode":"28230",
    "addr:street":"Calle De San;Rozas",
    "iso:country":"ES",
    "sg:address":"Calle de San Juan Bautista, 36",
    "sg:city":"Rozas De Madrid",
    "sg:orig_category":"Ingeniero",
    "sg:phone":"+34 916 37 37 49",
    "sg:postcode":"28230",
    "sg:province":"Madrid",
    "wof:name":"Cauces Consultores S.l.",
    "wof:placetype":"venue"
},
  "geometry": {"coordinates":[-3.8647589684,40.4924621582],"type":"Point"}
}