{
  "type": "Feature",
  "properties": {
    "iso:country":"ES",
    "sg:address":"Calle de Ramon Y Cajal, S/n",
    "sg:city":"Coru\u00d1a",
    "sg:orig_category":"Restaurantes",
    "sg:phone":"+34 981 15 04 77",
    "sg:postcode":"15006",
    "sg:province":"La Coru\u00f1a",
    "wof:name":"O'fogon S.l.",
    "wof:placetype":"venue"
},
  "geometry": {"coordinates":[-8.4033336639,43.3547935486],"type":"Point"}
}