{
  "type": "Feature",
  "properties": {
    "iso:country":"ES",
    "sg:address":"Barr Tantorta, S/n",
    "sg:city":"Amorebieta",
    "sg:orig_category":"Herradores, Herreros, Carreteros",
    "sg:phone":"+34 946 73 09 21",
    "sg:postcode":"48340",
    "sg:province":"Vizcaya",
    "wof:name":"Talleres Aefa S.l.",
    "wof:placetype":"venue"
},
  "geometry": {"coordinates":[-2.7321588993,43.2210960388],"type":"Point"}
}