{
  "type": "Feature",
  "properties": {
    "addr:full":"Carretera De Castril, S/n Huescar Granada 18830",
    "addr:housenumber":"s / n",
    "addr:postcode":"18830",
    "addr:street":"Carretera De Castril",
    "iso:country":"ES",
    "sg:address":"Carretera De Castril, S/n",
    "sg:city":"Huescar",
    "sg:orig_category":"Charcuter\u00cdas (al Por Mayor)",
    "sg:phone":"+34 958 74 21 65",
    "sg:postcode":"18830",
    "sg:province":"Granada",
    "wof:name":"Chillon Puentes Pedro",
    "wof:placetype":"venue"
},
  "geometry": {"coordinates":[-2.5411739349,37.8058433533],"type":"Point"}
}