{
  "type": "Feature",
  "properties": {
    "addr:full":"Avda Habana (de La), 27 Ourense Ourense 32003",
    "addr:housenumber":"27",
    "addr:postcode":"32003",
    "addr:street":"Avda Habana De La",
    "iso:country":"ES",
    "sg:address":"Avda Habana (de La), 27",
    "sg:city":"Ourense",
    "sg:orig_category":"Ingeniero",
    "sg:phone":"+34 988 37 06 66",
    "sg:postcode":"32003",
    "sg:province":"Ourense",
    "wof:name":"Murias Cadavid Eloy",
    "wof:placetype":"venue"
},
  "geometry": {"coordinates":[-7.8653240204,42.342590332],"type":"Point"}
}