{
  "type": "Feature",
  "properties": {
    "iso:country":"ES",
    "sg:address":"Calle de Marquesa De Esquilache, S/n",
    "sg:city":"Alhama Aragon",
    "sg:orig_category":"Poller\u00cda Y Caza (al Por Menor)",
    "sg:phone":"+34 976 84 05 37",
    "sg:postcode":"50230",
    "sg:province":"Zaragoza",
    "wof:name":"Avicola La Venta S.l.",
    "wof:placetype":"venue"
},
  "geometry": {"coordinates":[-1.8952713013,41.3004379272],"type":"Point"}
}