{
  "type": "Feature",
  "properties": {
    "addr:full":"Av Prat De La Riba, 41 Reus Tarragona 43201",
    "addr:housenumber":"41",
    "addr:postcode":"43201",
    "addr:street":"Av Prat De La Riba",
    "iso:country":"ES",
    "sg:address":"Av Prat De La Riba, 41",
    "sg:city":"Reus",
    "sg:orig_category":"Molduras, Junquillos, Listones Y Molduras Perforadas",
    "sg:phone":"+34 977 31 69 02",
    "sg:postcode":"43201",
    "sg:province":"Tarragona",
    "wof:name":"Gomez Tejedor Alejandro",
    "wof:placetype":"venue"
},
  "geometry": {"coordinates":[1.1026389599,41.1574554443],"type":"Point"}
}