{
  "type": "Feature",
  "properties": {
    "iso:country":"ES",
    "sg:address":"Calle de Nuestra Sra De La Poveda, 14",
    "sg:city":"Villa Prado",
    "sg:classifiers":[
        {
            "category":"Taxi",
            "type":"Transportation"
        }
    ],
    "sg:phone":"+34 918 62 11 17",
    "sg:postcode":"28630",
    "sg:province":"Madrid",
    "wof:name":"Martin Garcia Luis",
    "wof:placetype":"venue"
},
  "geometry": {"coordinates":[-4.3049688339,40.2749519348],"type":"Point"}
}