{
  "type": "Feature",
  "properties": {
    "addr:full":"Avda Galicia, 255 Fuentes Nuevas Le\u00f3n 24411",
    "addr:housenumber":"255",
    "addr:postcode":"24411",
    "addr:street":"Avda Galicia",
    "iso:country":"ES",
    "sg:address":"Avda Galicia, 255",
    "sg:city":"Fuentes Nuevas",
    "sg:orig_category":"Veh\u00cdculos De Ocasi\u00d3n",
    "sg:phone":"+34 987 45 57 39",
    "sg:postcode":"24411",
    "sg:province":"Le\u00f3n",
    "sg:website":"www.paginasamarillas.es",
    "wof:name":"Quirmabi S.l.",
    "wof:placetype":"venue"
},
  "geometry": {"coordinates":[-6.6394758224,42.5664558411],"type":"Point"}
}