{
  "type": "Feature",
  "properties": {
    "iso:country":"ES",
    "sg:address":"Avda Constitucion De La, 76",
    "sg:city":"Sotrondio",
    "sg:orig_category":"Muebles, Minoristas",
    "sg:phone":"+34 985 67 00 67",
    "sg:postcode":"33950",
    "sg:province":"Asturias",
    "wof:name":"Extensiones Sabino S. A.",
    "wof:placetype":"venue"
},
  "geometry": {"coordinates":[-5.6041841507,43.2750015259],"type":"Point"}
}