{
  "type": "Feature",
  "properties": {
    "addr:full":"Calle de Herreros De Tejada, 8 Madrid Madrid 28016",
    "addr:housenumber":"8",
    "addr:postcode":"madrid;28016",
    "addr:street":"Calle De Herreros De Tejada",
    "iso:country":"ES",
    "sg:address":"Calle de Herreros De Tejada, 8",
    "sg:city":"Madrid",
    "sg:orig_category":"Suministros Para Exposiciones, Ferias, Salones",
    "sg:phone":"+34 914 58 31 58",
    "sg:postcode":"28016",
    "sg:province":"Madrid",
    "sg:website":"www.ajtdis.com",
    "wof:name":"Ajt Dise\u00f1o Interior S.l.",
    "wof:placetype":"venue"
},
  "geometry": {"coordinates":[-3.6815009117,40.4537086487],"type":"Point"}
}