{
  "type": "Feature",
  "properties": {
    "iso:country":"ES",
    "sg:address":"Avda Andres Segovia, 17",
    "sg:city":"Linares",
    "sg:orig_category":"Agencias De Viajes",
    "sg:phone":"+34 953 65 19 09",
    "sg:postcode":"23700",
    "sg:province":"Ja\u00e9n",
    "sg:website":"www.barceloviajes.com",
    "wof:name":"Viajes Linares S.l.l.",
    "wof:placetype":"venue"
},
  "geometry": {"coordinates":[-3.6395230293,38.0982894897],"type":"Point"}
}