{
  "type": "Feature",
  "properties": {
    "addr:full":"Calle de Ca\u00d1adilla, 16 Huetor-vega Granada 18198",
    "addr:housenumber":"16",
    "addr:postcode":"18198",
    "addr:street":"Calle De Can\u0303Adilla",
    "iso:country":"ES",
    "sg:address":"Calle de Ca\u00d1adilla, 16",
    "sg:city":"Huetor-vega",
    "sg:orig_category":"Laboratorios Y Trabajos De Fotograf\u00cda, V\u00cddeo Y Cine",
    "sg:phone":"+34 958 30 00 00",
    "sg:postcode":"18198",
    "sg:province":"Granada",
    "sg:website":"www.fotoway.net",
    "wof:name":"Laboratorios De Fotografia Profesional S.a.l.",
    "wof:placetype":"venue"
},
  "geometry": {"coordinates":[-3.5702822208,37.1475372314],"type":"Point"}
}