{
  "type": "Feature",
  "properties": {
    "addr:full":"Arquimedes, S/n Gijon Asturias 33211",
    "addr:postcode":"33211",
    "addr:street":"Arquimedes S / N",
    "iso:country":"ES",
    "sg:address":"Arquimedes, S/n",
    "sg:city":"Gijon",
    "sg:orig_category":"Colchones (fabricaci\u00d3n, Al Por Mayor, Al Por Menor)",
    "sg:phone":"+34 985 16 89 63",
    "sg:postcode":"33211",
    "sg:province":"Asturias",
    "wof:name":"Colchones Europa S.l.",
    "wof:placetype":"venue"
},
  "geometry": {"coordinates":[-5.6916589737,43.505695343],"type":"Point"}
}