{
  "type": "Feature",
  "properties": {
    "iso:country":"ES",
    "sg:address":"Calle de Virgen De Criptana, 30",
    "sg:city":"Campo Criptana",
    "sg:orig_category":"Laboratorios Y Trabajos De Fotograf\u00cda, V\u00cddeo Y Cine",
    "sg:phone":"+34 926 56 27 00",
    "sg:postcode":"13610",
    "sg:province":"Ciudad Real",
    "wof:name":"Iris Fotodigital S.l.",
    "wof:placetype":"venue"
},
  "geometry": {"coordinates":[-3.121325016,39.4054794312],"type":"Point"}
}