{
  "type": "Feature",
  "properties": {
    "addr:full":"M\u00e9ndez, 1 Baza Granada 18800",
    "addr:housenumber":"1",
    "addr:postcode":"18800",
    "addr:street":"Me\u0301Ndez",
    "iso:country":"ES",
    "sg:address":"M\u00e9ndez, 1",
    "sg:city":"Baza",
    "sg:orig_category":"Asociaciones Y Clubs Deportivos",
    "sg:phone":"+34 958 70 06 85",
    "sg:postcode":"18800",
    "sg:province":"Granada",
    "wof:name":"Pe\u00f1a Madridista Bastetana",
    "wof:placetype":"venue"
},
  "geometry": {"coordinates":[-2.7731668949,37.4906311035],"type":"Point"}
}