{
  "type": "Feature",
  "properties": {
    "addr:full":"Carr Arbres (dels), 11 Algemesi Valencia 46680",
    "addr:housenumber":"11",
    "addr:postcode":"46680",
    "addr:street":"Carr Arbres Dels",
    "iso:country":"ES",
    "sg:address":"Carr Arbres (dels), 11",
    "sg:city":"Algemesi",
    "sg:orig_category":"Cajas De Ahorro",
    "sg:phone":"+34 962 48 25 40",
    "sg:postcode":"46680",
    "sg:province":"Valencia",
    "sg:website":"www.cam.es",
    "wof:name":"Caja De Ahorros Del Mediterraneo",
    "wof:placetype":"venue"
},
  "geometry": {"coordinates":[-0.4368430078,39.1908721924],"type":"Point"}
}