{
  "type": "Feature",
  "properties": {
    "addr:full":"Avda Andalucia, 14 Punta Umbria Huelva 21100",
    "addr:housenumber":"14",
    "addr:postcode":"21100",
    "addr:street":"Avda Andalucia",
    "iso:country":"ES",
    "sg:address":"Avda Andalucia, 14",
    "sg:city":"Punta Umbria",
    "sg:orig_category":"Cajas De Ahorro",
    "sg:phone":"+34 959 31 25 27",
    "sg:postcode":"21100",
    "sg:province":"Huelva",
    "wof:name":"Caja De Ahorros Y Monte De Piedad De Cordoba",
    "wof:placetype":"venue"
},
  "geometry": {"coordinates":[-6.9748859406,37.1830101013],"type":"Point"}
}