{
  "type": "Feature",
  "properties": {
    "iso:country":"ES",
    "sg:address":"Avda Castrelos, 277",
    "sg:city":"Vigo",
    "sg:orig_category":"Mec\u00c1nico Del Autom\u00d3vil",
    "sg:phone":"+34 986 20 27 20",
    "sg:postcode":"36213",
    "sg:province":"Pontevedra",
    "wof:name":"Lameiro Perez Gonzalo",
    "wof:placetype":"venue"
},
  "geometry": {"coordinates":[-8.7273416519,42.202457428],"type":"Point"}
}