{
  "type": "Feature",
  "properties": {
    "iso:country":"ES",
    "sg:address":"Pg Olot, 22",
    "sg:city":"Girona",
    "sg:orig_category":"Inmobiliaria (agencias)",
    "sg:phone":"+34 972 40 56 91",
    "sg:postcode":"17005",
    "sg:province":"Girona",
    "sg:website":"www.e-dinamic.com",
    "wof:name":"Serveis Inmobiliaris Quimar Girona S.l.",
    "wof:placetype":"venue"
},
  "geometry": {"coordinates":[2.810199976,41.976726532],"type":"Point"}
}