{
  "type": "Feature",
  "properties": {
    "addr:full":"Calle de Cap Martinet, Des, 17 Nuestra Se\u00e7ora De Jesus Islas Baleares 07819",
    "addr:postcode":"07819",
    "addr:street":"Calle De Cap Martinet;Islas Baleares",
    "iso:country":"ES",
    "sg:address":"Calle de Cap Martinet, Des, 17",
    "sg:city":"Nuestra Se\u00e7ora De Jesus",
    "sg:orig_category":"Cajas De Ahorro",
    "sg:phone":"+34 971 19 26 79",
    "sg:postcode":"07819",
    "sg:province":"Islas Baleares",
    "wof:name":"Caja De Ahorros Y Monte De Piedad De Las Baleares",
    "wof:placetype":"venue"
},
  "geometry": {"coordinates":[1.4531309605,38.927318573],"type":"Point"}
}