{
  "type": "Feature",
  "properties": {
    "iso:country":"ES",
    "sg:address":"Barr Lebario, 14",
    "sg:city":"Tra\u00e7a-matiena",
    "sg:orig_category":"Metales (labores, Pulido)",
    "sg:phone":"+34 946 81 71 26",
    "sg:postcode":"48220",
    "sg:province":"Vizcaya",
    "wof:name":"Estampaciones Metalicas Vialsa S.l.",
    "wof:placetype":"venue"
},
  "geometry": {"coordinates":[-2.6079039574,43.1692581177],"type":"Point"}
}