{
  "type": "Feature",
  "properties": {
    "iso:country":"ES",
    "sg:address":"Calle de Dos De Mayo, 15",
    "sg:city":"Calahorra",
    "sg:orig_category":"Inform\u00c1tica (estudios, Servicios, Asesor\u00cda, Formaci\u00d3n)",
    "sg:phone":"+34 941 14 51 65",
    "sg:postcode":"26500",
    "sg:province":"La Rioja",
    "wof:name":"B8088 S.l.",
    "wof:placetype":"venue"
},
  "geometry": {"coordinates":[-1.9659520388,42.306312561],"type":"Point"}
}