{
  "type": "Feature",
  "properties": {
    "addr:full":"Calle de Real De Villafranca, 62 Palacios Y Villafranca Sevilla 41720",
    "addr:housenumber":"62",
    "addr:postcode":"41720",
    "addr:street":"Calle De Real De Villafranca",
    "iso:country":"ES",
    "sg:address":"Calle de Real De Villafranca, 62",
    "sg:city":"Palacios Y Villafranca",
    "sg:classifiers":[
        {
            "category":"Autos & Motor Vehicles",
            "subcategory":"Automobile Sales",
            "type":"Retail Goods"
        }
    ],
    "sg:phone":"+34 955 81 24 70",
    "sg:postcode":"41720",
    "sg:province":"Sevilla",
    "wof:name":"Carvajal Tirado Jose Antonio",
    "wof:placetype":"venue"
},
  "geometry": {"coordinates":[-5.9241790771,37.1630935669],"type":"Point"}
}