{
  "type": "Feature",
  "properties": {
    "addr:full":"Carr Vicente Cuervo, 10 Eivissa Islas Baleares 07800",
    "addr:housenumber":"10",
    "addr:postcode":"07800",
    "addr:street":"Carr Vicente Cuervo",
    "iso:country":"ES",
    "sg:address":"Carr Vicente Cuervo, 10",
    "sg:city":"Eivissa",
    "sg:orig_category":"Inmobiliaria (agencias)",
    "sg:phone":"+34 971 31 00 77",
    "sg:postcode":"07800",
    "sg:province":"Islas Baleares",
    "wof:name":"Oliva Prim Jose Maria",
    "wof:placetype":"venue"
},
  "geometry": {"coordinates":[1.4330519438,38.9099464417],"type":"Point"}
}