{
  "type": "Feature",
  "properties": {
    "iso:country":"ES",
    "sg:address":"Plaz Regimiento Saboya, 5",
    "sg:city":"Villaescusa De Haro",
    "sg:orig_category":"Carnicer\u00cdas, Carnicer\u00cdas",
    "sg:phone":"+34 967 16 85 84",
    "sg:postcode":"16647",
    "sg:province":"Cuenca",
    "wof:name":"Galvan Mena Paulino",
    "wof:placetype":"venue"
},
  "geometry": {"coordinates":[-2.6747729778,39.5997200012],"type":"Point"}
}