{
  "type": "Feature",
  "properties": {
    "iso:country":"ES",
    "sg:address":"Carrer de Raval (de), 13",
    "sg:city":"Canonja",
    "sg:orig_category":"Mercer\u00cda, Lencer\u00cda (al Por Menor)",
    "sg:phone":"+34 977 54 57 80",
    "sg:postcode":"43110",
    "sg:province":"Tarragona",
    "wof:name":"Rion Roig Roser",
    "wof:placetype":"venue"
},
  "geometry": {"coordinates":[1.1789319515,41.1229820251],"type":"Point"}
}