{
  "type": "Feature",
  "properties": {
    "iso:country":"ES",
    "sg:address":"Calle de Colon De Larreategui, 41",
    "sg:city":"Bilbao",
    "sg:orig_category":"Arte, Cultura, Edici\u00d3n",
    "sg:phone":"+34 944 23 54 49",
    "sg:postcode":"48009",
    "sg:province":"Vizcaya",
    "sg:website":"www.euskalnet.net/bae",
    "wof:name":"Bizkaiko Abesbatzen Elkartea",
    "wof:placetype":"venue"
},
  "geometry": {"coordinates":[-2.9352428913,43.2640075684],"type":"Point"}
}