{
  "type": "Feature",
  "properties": {
    "iso:country":"ES",
    "sg:address":"Avda Razo, S/n",
    "sg:city":"Carballo",
    "sg:orig_category":"Peluquer\u00cdas, Peluquer\u00cda Mixta",
    "sg:phone":"+34 981 75 80 39",
    "sg:postcode":"15100",
    "sg:province":"La Coru\u00f1a",
    "wof:name":"Chaudarcas Peluquerias S.l.",
    "wof:placetype":"venue"
},
  "geometry": {"coordinates":[-8.6918792725,43.2225761414],"type":"Point"}
}