{
  "type": "Feature",
  "properties": {
    "iso:country":"ES",
    "sg:address":"Calle de Clara Del Rey, 14",
    "sg:city":"Madrid",
    "sg:orig_category":"Arquitectos",
    "sg:phone":"+34 914 16 58 86",
    "sg:postcode":"28002",
    "sg:province":"Madrid",
    "wof:name":"Rivas Magdaleno Pedro",
    "wof:placetype":"venue"
},
  "geometry": {"coordinates":[-3.6713550091,40.4417533875],"type":"Point"}
}