{
  "type": "Feature",
  "properties": {
    "addr:full":"Calle de Polibea, 6 Madrid Madrid 28027",
    "addr:housenumber":"6",
    "addr:postcode":"28027",
    "addr:street":"Calle De Polibea",
    "iso:country":"ES",
    "sg:address":"Calle de Polibea, 6",
    "sg:city":"Madrid",
    "sg:orig_category":"Desinfecci\u00d3n, Desinsectaci\u00d3n, Desratizaci\u00d3n",
    "sg:phone":"+34 913 67 74 99",
    "sg:postcode":"28027",
    "sg:province":"Madrid",
    "wof:name":"Saniterpen S.l.",
    "wof:placetype":"venue"
},
  "geometry": {"coordinates":[-3.6438059807,40.4408226013],"type":"Point"}
}