{
  "type": "Feature",
  "properties": {
    "addr:full":"Ctra Alca\u00d1iz, Km. 0548,0 Teruel Teruel 44003",
    "addr:postcode":"44003",
    "addr:street":"Ctra Alcan\u0303Iz Km. 0548,0;Teruel",
    "iso:country":"ES",
    "sg:address":"Ctra Alca\u00d1iz, Km. 0548,0",
    "sg:city":"Teruel",
    "sg:orig_category":"Distribuci\u00d3n De Petr\u00d3leo Y Derivados",
    "sg:phone":"+34 978 60 21 62",
    "sg:postcode":"44003",
    "sg:province":"Teruel",
    "wof:name":"Civera Barrachina Y Sucesores S. L.",
    "wof:placetype":"venue"
},
  "geometry": {"coordinates":[-1.1084690094,40.3566017151],"type":"Point"}
}