{
  "type": "Feature",
  "properties": {
    "addr:full":"Carr Carme Carles, 6 Bordeta Girona 17111",
    "addr:housenumber":"6",
    "addr:postcode":"17111",
    "addr:street":"Carr Carme Carles",
    "iso:country":"ES",
    "sg:address":"Carr Carme Carles, 6",
    "sg:city":"Bordeta",
    "sg:orig_category":"Cerrajer\u00cda, Ferrallista",
    "sg:phone":"+34 972 64 03 59",
    "sg:postcode":"17111",
    "sg:province":"Girona",
    "wof:name":"Colls Bahi Lluis",
    "wof:placetype":"venue"
},
  "geometry": {"coordinates":[3.046708107,41.9576644897],"type":"Point"}
}