{
  "type": "Feature",
  "properties": {
    "iso:country":"ES",
    "sg:address":"Psaj Ahillones, S/n",
    "sg:city":"Madrid",
    "sg:orig_category":"Fabricaci\u00d3n De Mantequilla (al Por Mayor)",
    "sg:phone":"+34 917 63 36 41",
    "sg:postcode":"28033",
    "sg:province":"Madrid",
    "wof:name":"Espinosa Sanz Mariano",
    "wof:placetype":"venue"
},
  "geometry": {"coordinates":[-3.6481029987,40.4758491516],"type":"Point"}
}