{
  "type": "Feature",
  "properties": {
    "addr:full":"Calle de Jacinto Verdaguer, 2 Madrid Madrid 28019",
    "addr:housenumber":"2",
    "addr:postcode":"28019",
    "addr:street":"Calle De Jacinto Verdaguer",
    "iso:country":"ES",
    "sg:address":"Calle de Jacinto Verdaguer, 2",
    "sg:city":"Madrid",
    "sg:orig_category":"Abogados",
    "sg:phone":"+34 914 69 24 05",
    "sg:postcode":"28019",
    "sg:province":"Madrid",
    "wof:name":"Tijero Verdugo Pilar",
    "wof:placetype":"venue"
},
  "geometry": {"coordinates":[-3.7138826847,40.3962860107],"type":"Point"}
}