{
  "type": "Feature",
  "properties": {
    "addr:full":"Calle de Jeronimo Bujeda, 2 Tarancon Cuenca 16400",
    "addr:housenumber":"2",
    "addr:postcode":"16400",
    "addr:street":"Calle De Jeronimo Bujeda",
    "iso:country":"ES",
    "sg:address":"Calle de Jeronimo Bujeda, 2",
    "sg:city":"Tarancon",
    "sg:orig_category":"Trajes Y Adornos De Boda (confecci\u00d3n, Al Por Menor)",
    "sg:phone":"+34 969 32 31 26",
    "sg:postcode":"16400",
    "sg:province":"Cuenca",
    "wof:name":"Martinez Garcia-prieto Maria Jose",
    "wof:placetype":"venue"
},
  "geometry": {"coordinates":[-3.0059459209,40.0084457397],"type":"Point"}
}