{
  "type": "Feature",
  "properties": {
    "iso:country":"ES",
    "sg:address":"Erreka, 3",
    "sg:city":"Erreka",
    "sg:orig_category":"Reposter\u00cdas",
    "sg:phone":"+34 948 51 06 14",
    "sg:postcode":"31880",
    "sg:province":"Navarra",
    "wof:name":"Eguzxitza Okindenguia S.l.",
    "wof:placetype":"venue"
},
  "geometry": {"coordinates":[-1.9149940014,43.0805091858],"type":"Point"}
}