{
  "type": "Feature",
  "properties": {
    "iso:country":"ES",
    "sg:address":"Calle de Ebro, 10",
    "sg:city":"Rozas De Madrid",
    "sg:orig_category":"Empresarios",
    "sg:phone":"+34 916 37 54 48",
    "sg:postcode":"28230",
    "sg:province":"Madrid",
    "wof:name":"Decoracion Demolicion Y Dise\u00f1o S.l.",
    "wof:placetype":"venue"
},
  "geometry": {"coordinates":[-3.9066371918,40.5710449219],"type":"Point"}
}