{
  "type": "Feature",
  "properties": {
    "addr:full":"Ctra Bao, S/n Combro Pontevedra 36330",
    "addr:housenumber":"s",
    "addr:postcode":"36330",
    "addr:street":"Ctra Bao;/ N",
    "iso:country":"ES",
    "sg:address":"Ctra Bao, S/n",
    "sg:city":"Combro",
    "sg:orig_category":"Asociaciones Y Clubs Deportivos",
    "sg:phone":"+34 986 46 03 50",
    "sg:postcode":"36330",
    "sg:province":"Pontevedra",
    "wof:name":"Club De Campo De Vigo S. A.",
    "wof:placetype":"venue"
},
  "geometry": {"coordinates":[-8.694773674,42.6678962708],"type":"Point"}
}