{
  "type": "Feature",
  "properties": {
    "addr:full":"Rtda Pitagoras, 1 Alcala Henares Madrid 28800",
    "addr:housenumber":"1",
    "addr:postcode":"28800",
    "addr:street":"Pitagoras",
    "iso:country":"ES",
    "sg:address":"Rtda Pitagoras, 1",
    "sg:city":"Alcala Henares",
    "sg:orig_category":"Venta, Colocaci\u00d3n, Reparaci\u00d3n De Parabrisas, Techos Descapotables",
    "sg:phone":"+34 918 82 52 95",
    "sg:postcode":"28800",
    "sg:province":"Madrid",
    "wof:name":"Gabriel Arevalillo Martinez S.l.",
    "wof:placetype":"venue"
},
  "geometry": {"coordinates":[-3.7057700157,40.42029953],"type":"Point"}
}