{
  "type": "Feature",
  "properties": {
    "addr:full":"Rua Sanjurjo Badia, 177 Vigo Pontevedra 36207",
    "addr:housenumber":"177",
    "addr:postcode":"36207",
    "addr:street":"Rua Sanjurjo Badia",
    "iso:country":"ES",
    "sg:address":"Rua Sanjurjo Badia, 177",
    "sg:city":"Vigo",
    "sg:orig_category":"Molduras, Junquillos, Listones Y Molduras Perforadas",
    "sg:phone":"+34 986 26 04 90",
    "sg:postcode":"36207",
    "sg:province":"Pontevedra",
    "wof:name":"Loson Sanchez Arturo",
    "wof:placetype":"venue"
},
  "geometry": {"coordinates":[-8.6972284317,42.2490577698],"type":"Point"}
}