{
  "type": "Feature",
  "properties": {
    "addr:full":"Calle de Rafael Canogar, 2 Rivas Vaciamadrid Madrid 28529",
    "addr:housenumber":"2",
    "addr:postcode":"28529",
    "addr:street":"Calle De Rafael Canogar",
    "iso:country":"ES",
    "sg:address":"Calle de Rafael Canogar, 2",
    "sg:city":"Rivas Vaciamadrid",
    "sg:orig_category":"Organizaciones Internacionales",
    "sg:phone":"+34 914 99 74 41",
    "sg:postcode":"28529",
    "sg:province":"Madrid",
    "wof:name":"Asociacion Dual",
    "wof:placetype":"venue"
},
  "geometry": {"coordinates":[-3.5204184055,40.3383293152],"type":"Point"}
}