{
  "type": "Feature",
  "properties": {
    "iso:country":"ES",
    "sg:address":"Avda Princesa Juana De Austria, Km. 0005,7",
    "sg:city":"Madrid",
    "sg:orig_category":"Venta, Montaje De Neum\u00c1ticos",
    "sg:phone":"+34 913 41 88 33",
    "sg:postcode":"28021",
    "sg:province":"Madrid",
    "wof:name":"Neumaticos Ceta S.l.",
    "wof:placetype":"venue"
},
  "geometry": {"coordinates":[-3.7189970016,40.3800392151],"type":"Point"}
}