{
  "type": "Feature",
  "properties": {
    "iso:country":"ES",
    "sg:address":"Calle de San Petersburgo, 1",
    "sg:city":"Caceres",
    "sg:orig_category":"Empresas De Limpieza",
    "sg:phone":"+34 927 23 66 06",
    "sg:postcode":"10005",
    "sg:province":"C\u00e1ceres",
    "wof:name":"Villa Mena Jose Maria",
    "wof:placetype":"venue"
},
  "geometry": {"coordinates":[-6.3825139999,39.4570732117],"type":"Point"}
}