{
  "type": "Feature",
  "properties": {
    "addr:full":"Carrer de Sant Pere Mes Alt, 18 Barcelona Barcelona 08003",
    "addr:housenumber":"18",
    "addr:postcode":"08003",
    "addr:street":"Carrer De Sant",
    "iso:country":"ES",
    "sg:address":"Carrer de Sant Pere Mes Alt, 18",
    "sg:city":"Barcelona",
    "sg:orig_category":"Ropa Para Se\u00d1oras (al Por Menor)",
    "sg:phone":"+34 933 10 17 95",
    "sg:postcode":"08003",
    "sg:province":"Barcelona",
    "wof:name":"Fuentes Ropero Jose",
    "wof:placetype":"venue"
},
  "geometry": {"coordinates":[2.1760489941,41.3877487183],"type":"Point"}
}