{
  "type": "Feature",
  "properties": {
    "iso:country":"ES",
    "sg:address":"Avda Ferrol (del), 27",
    "sg:city":"Viveiro",
    "sg:orig_category":"T\u00c9cnicos Veterinarios",
    "sg:phone":"+34 982 55 16 14",
    "sg:postcode":"27850",
    "sg:province":"Lugo",
    "wof:name":"Sanchez Carrion Jesus",
    "wof:placetype":"venue"
},
  "geometry": {"coordinates":[-7.5988898277,43.6568832397],"type":"Point"}
}