{
  "type": "Feature",
  "properties": {
    "addr:full":"Carr Mayor, 13 Aldaia Valencia 46960",
    "addr:housenumber":"13",
    "addr:postcode":"46960",
    "addr:street":"Carr Mayor",
    "iso:country":"ES",
    "sg:address":"Carr Mayor, 13",
    "sg:city":"Aldaia",
    "sg:orig_category":"Peluquer\u00cdas, Peluquer\u00cda Mixta",
    "sg:phone":"+34 961 51 33 68",
    "sg:postcode":"46960",
    "sg:province":"Valencia",
    "wof:name":"Guerra Valero Ana Laura",
    "wof:placetype":"venue"
},
  "geometry": {"coordinates":[-0.460878998,39.4649238586],"type":"Point"}
}