{
  "type": "Feature",
  "properties": {
    "iso:country":"ES",
    "sg:address":"Cno. Cementerio, 11",
    "sg:city":"Atarfe",
    "sg:orig_category":"Plomeros",
    "sg:phone":"+34 958 43 77 97",
    "sg:postcode":"18230",
    "sg:province":"Granada",
    "wof:name":"Iba\u00f1ez Rodriguez Jose",
    "wof:placetype":"venue"
},
  "geometry": {"coordinates":[-3.6870090961,37.2267684937],"type":"Point"}
}