{
  "type": "Feature",
  "properties": {
    "addr:full":"Calle de Casariche, 2 Herrera Sevilla 41567",
    "addr:housenumber":"2",
    "addr:postcode":"41567",
    "addr:street":"Calle De Casariche",
    "iso:country":"ES",
    "sg:address":"Calle de Casariche, 2",
    "sg:city":"Herrera",
    "sg:orig_category":"Cintas Transportadoras",
    "sg:phone":"+34 954 01 33 11",
    "sg:postcode":"41567",
    "sg:province":"Sevilla",
    "wof:name":"Morecinta",
    "wof:placetype":"venue"
},
  "geometry": {"coordinates":[-4.8410043716,37.3612060547],"type":"Point"}
}