{
  "type": "Feature",
  "properties": {
    "addr:full":"Carrer de Saboneria, 127 Sabadell Barcelona 08204",
    "addr:housenumber":"127",
    "addr:postcode":"08204",
    "addr:street":"Carrer De Saboneria",
    "iso:country":"ES",
    "sg:address":"Carrer de Saboneria, 127",
    "sg:city":"Sabadell",
    "sg:orig_category":"Contenedores (mercanc\u00cdas)",
    "sg:phone":"+34 937 10 40 29",
    "sg:postcode":"08204",
    "sg:province":"Barcelona",
    "wof:name":"Gruas Calhitrans S.l.",
    "wof:placetype":"venue"
},
  "geometry": {"coordinates":[2.1228210926,41.5260734558],"type":"Point"}
}