{
  "type": "Feature",
  "properties": {
    "addr:full":"Cmno Puente Viejo (del), 44 Arganda Madrid 28500",
    "addr:housenumber":"44",
    "addr:postcode":"28500",
    "addr:street":"Cmno Puente Viejo Del",
    "iso:country":"ES",
    "sg:address":"Cmno Puente Viejo (del), 44",
    "sg:city":"Arganda",
    "sg:orig_category":"M\u00c1rmoles, Granitos Y Piedras Naturales",
    "sg:phone":"+34 918 71 36 21",
    "sg:postcode":"28500",
    "sg:province":"Madrid",
    "wof:name":"Marmoles Arganda S.l.",
    "wof:placetype":"venue"
},
  "geometry": {"coordinates":[-3.4406979084,40.2999954224],"type":"Point"}
}