{
  "type": "Feature",
  "properties": {
    "iso:country":"ES",
    "sg:address":"Avda Bruselas, S/n",
    "sg:city":"Torreciega",
    "sg:orig_category":"Reciclaje Y Tratamiento De Desechos Varios",
    "sg:phone":"+34 968 32 06 21",
    "sg:postcode":"30392",
    "sg:province":"Murcia",
    "wof:name":"Etrinsa S.a.",
    "wof:placetype":"venue"
},
  "geometry": {"coordinates":[-0.9694439769,37.6158447266],"type":"Point"}
}