{
  "type": "Feature",
  "properties": {
    "addr:full":"Ctra. Estacion, S/n Albox Almer\u00eda 04800",
    "addr:postcode":"04800",
    "addr:street":"Ctra. Estacion S / N Albox Almeri\u0301A",
    "iso:country":"ES",
    "sg:address":"Ctra. Estacion, S/n",
    "sg:city":"Albox",
    "sg:orig_category":"Alimentaci\u00d3n General (al Por Mayor)",
    "sg:phone":"+34 950 43 03 63",
    "sg:postcode":"04800",
    "sg:province":"Almer\u00eda",
    "wof:name":"Galera Carrillo Jose",
    "wof:placetype":"venue"
},
  "geometry": {"coordinates":[-2.1477890015,37.3859863281],"type":"Point"}
}