{
  "type": "Feature",
  "properties": {
    "iso:country":"ES",
    "sg:address":"Calle de Rabida, 14",
    "sg:city":"Huelva",
    "sg:orig_category":"Ropa Para Se\u00d1oras (al Por Menor)",
    "sg:phone":"+34 959 54 01 81",
    "sg:postcode":"21001",
    "sg:province":"Huelva",
    "sg:website":"www.trucco.es",
    "wof:name":"Del Fraile Caballero Ana",
    "wof:placetype":"venue"
},
  "geometry": {"coordinates":[-6.9511561394,37.255569458],"type":"Point"}
}