{
  "type": "Feature",
  "properties": {
    "addr:full":"Carr Rodafam, 3 Platja Valencia 46711",
    "addr:housenumber":"3",
    "addr:postcode":"46711",
    "addr:street":"Carr Rodafam",
    "iso:country":"ES",
    "sg:address":"Carr Rodafam, 3",
    "sg:city":"Platja",
    "sg:orig_category":"Fabricaci\u00d3n De Juguetes Autom\u00c1ticos",
    "sg:phone":"+34 962 81 91 21",
    "sg:postcode":"46711",
    "sg:province":"Valencia",
    "wof:name":"Euro Oriro 2000 S.l.",
    "wof:placetype":"venue"
},
  "geometry": {"coordinates":[-0.1424089968,38.9503593445],"type":"Point"}
}