{
  "type": "Feature",
  "properties": {
    "addr:full":"Calle de Batalla De Belchite, 5 Madrid Madrid 28045",
    "addr:housenumber":"5",
    "addr:postcode":"28045",
    "addr:street":"Calle De Batalla De Belchite",
    "iso:country":"ES",
    "sg:address":"Calle de Batalla De Belchite, 5",
    "sg:city":"Madrid",
    "sg:orig_category":"Agencias Y Agentes Comerciales, Representantes",
    "sg:phone":"+34 915 51 15 94",
    "sg:postcode":"28045",
    "sg:province":"Madrid",
    "wof:name":"Pintado Lopez Antonio",
    "wof:placetype":"venue"
},
  "geometry": {"coordinates":[-3.6927466393,40.3968009949],"type":"Point"}
}