{
  "type": "Feature",
  "properties": {
    "addr:full":"Av Pirineus, 28 Puigcerda Girona 17520",
    "addr:housenumber":"28",
    "addr:postcode":"17520",
    "addr:street":"Av Pirineus",
    "iso:country":"ES",
    "sg:address":"Av Pirineus, 28",
    "sg:city":"Puigcerda",
    "sg:orig_category":"Masajistas Kinesiterapeutas",
    "sg:phone":"+34 972 14 09 51",
    "sg:postcode":"17520",
    "sg:province":"Girona",
    "wof:name":"Nicolau Romero Jose",
    "wof:placetype":"venue"
},
  "geometry": {"coordinates":[1.9255859852,42.4297637939],"type":"Point"}
}