{
  "type": "Feature",
  "properties": {
    "addr:full":"Calle de Barcelona, 3 Palmas De Gran Canaria Las Palmas 35006",
    "addr:housenumber":"3",
    "addr:postcode":"35006",
    "addr:street":"Calle De Barcelona",
    "iso:country":"ES",
    "sg:address":"Calle de Barcelona, 3",
    "sg:city":"Palmas De Gran Canaria",
    "sg:orig_category":"Ense\u00d1anza Variada",
    "sg:phone":"+34 928 29 08 88",
    "sg:postcode":"35006",
    "sg:province":"Las Palmas",
    "wof:name":"Centro De Ense\u00f1anza De Canarias Liceo 20",
    "wof:placetype":"venue"
},
  "geometry": {"coordinates":[-15.4184541702,28.0337486267],"type":"Point"}
}