{
  "type": "Feature",
  "properties": {
    "iso:country":"ES",
    "sg:address":"Mercados Centrales, 55",
    "sg:city":"Pe\u00d1acastillo",
    "sg:orig_category":"Frutas, Legumbres Frescas Y Tempranas (al Por Menor)",
    "sg:phone":"+34 942 33 79 69",
    "sg:postcode":"39011",
    "sg:province":"Cantabria",
    "wof:name":"Frutas Galdos S.a.",
    "wof:placetype":"venue"
},
  "geometry": {"coordinates":[-3.8739891052,43.4491386414],"type":"Point"}
}