{
  "type": "Feature",
  "properties": {
    "iso:country":"ES",
    "sg:address":"Calle de Artazuri\u00d1a, 6",
    "sg:city":"Bilbao",
    "sg:orig_category":"Centros Empresariales",
    "sg:phone":"+34 944 12 74 61",
    "sg:postcode":"48004",
    "sg:province":"Vizcaya",
    "wof:name":"Eyde Iberica S.a.",
    "wof:placetype":"venue"
},
  "geometry": {"coordinates":[-2.9056816101,43.2562675476],"type":"Point"}
}