{
  "type": "Feature",
  "properties": {
    "addr:full":"Campo De Guardamar, 4 Guardamar Segura Alicante 03140",
    "addr:housenumber":"4",
    "addr:postcode":"03140",
    "iso:country":"ES",
    "sg:address":"Campo De Guardamar, 4",
    "sg:city":"Guardamar Segura",
    "sg:orig_category":"Cr\u00cda De Animales",
    "sg:phone":"+34 965 72 77 90",
    "sg:postcode":"03140",
    "sg:province":"Alicante",
    "wof:name":"Ganados Torregrosa Hermanos S.a.",
    "wof:placetype":"venue"
},
  "geometry": {"coordinates":[-0.6540290117,38.086681366],"type":"Point"}
}