{
  "type": "Feature",
  "properties": {
    "addr:full":"Avda Valdelaparra (de), 5 Alcobendas Madrid 28108",
    "addr:postcode":"28108",
    "addr:street":"Avda Valdelaparra De 5",
    "iso:country":"ES",
    "sg:address":"Avda Valdelaparra (de), 5",
    "sg:city":"Alcobendas",
    "sg:orig_category":"Veh\u00cdculos De Ocasi\u00d3n",
    "sg:phone":"+34 914 90 32 60",
    "sg:postcode":"28108",
    "sg:province":"Madrid",
    "wof:name":"Fereato Car S.l.",
    "wof:placetype":"venue"
},
  "geometry": {"coordinates":[-3.6225941181,40.5358009338],"type":"Point"}
}