{
  "type": "Feature",
  "properties": {
    "iso:country":"ES",
    "sg:address":"Praz Figueroa, 5",
    "sg:city":"Redondela",
    "sg:orig_category":"Droguer\u00cdas (al Por Menor)",
    "sg:phone":"+34 986 40 32 98",
    "sg:postcode":"36800",
    "sg:province":"Pontevedra",
    "wof:name":"Decogar S.a.",
    "wof:placetype":"venue"
},
  "geometry": {"coordinates":[-8.6090641022,42.2820243835],"type":"Point"}
}