{
  "type": "Feature",
  "properties": {
    "addr:full":"Calle de Velazquez, S/n Alcaudete Ja\u00e9n 23660",
    "addr:housenumber":"s / n",
    "addr:postcode":"23660",
    "addr:street":"Calle De Velazquez;Jae\u0301N",
    "iso:country":"ES",
    "sg:address":"Calle de Velazquez, S/n",
    "sg:city":"Alcaudete",
    "sg:orig_category":"Ense\u00d1anza, Formaci\u00d3n Profesional: Aprendizaje",
    "sg:phone":"+34 953 56 07 66",
    "sg:postcode":"23660",
    "sg:province":"Ja\u00e9n",
    "wof:name":"Ayuntamiento De Alcaudete",
    "wof:placetype":"venue"
},
  "geometry": {"coordinates":[-4.0796513557,37.5854034424],"type":"Point"}
}