{
  "type": "Feature",
  "properties": {
    "addr:full":"Calle de Asuncion, 49 Sevilla Sevilla 41011",
    "addr:housenumber":"49",
    "addr:postcode":"41011",
    "addr:street":"Calle De Asuncion",
    "iso:country":"ES",
    "sg:address":"Calle de Asuncion, 49",
    "sg:city":"Sevilla",
    "sg:orig_category":"Abogados",
    "sg:phone":"+34 954 27 83 89",
    "sg:postcode":"41011",
    "sg:province":"Sevilla",
    "wof:name":"Navarro Rodriguez Ana Maria",
    "wof:placetype":"venue"
},
  "geometry": {"coordinates":[-5.9975447655,37.3755455017],"type":"Point"}
}