{
  "type": "Feature",
  "properties": {
    "iso:country":"ES",
    "sg:address":"Avda Jose Ortega Y Gasset, 194",
    "sg:city":"Malaga",
    "sg:orig_category":"Promotores Constructores",
    "sg:phone":"+34 952 31 73 84",
    "sg:postcode":"29006",
    "sg:province":"M\u00e1laga",
    "wof:name":"Construcciones Sando S.a.",
    "wof:placetype":"venue"
},
  "geometry": {"coordinates":[-4.4668087959,36.7067184448],"type":"Point"}
}