{
  "type": "Feature",
  "properties": {
    "addr:full":"Avda Aragon, 11 Alca\u00f1iz Teruel 44600",
    "addr:housenumber":"11",
    "addr:postcode":"44600",
    "addr:street":"Avda Aragon",
    "iso:country":"ES",
    "sg:address":"Avda Aragon, 11",
    "sg:city":"Alca\u00f1iz",
    "sg:orig_category":"Abogados",
    "sg:phone":"+34 978 83 18 90",
    "sg:postcode":"44600",
    "sg:province":"Teruel",
    "wof:name":"Concha Gargallo Estela",
    "wof:placetype":"venue"
},
  "geometry": {"coordinates":[-0.1292890012,41.0505104065],"type":"Point"}
}