{
  "type": "Feature",
  "properties": {
    "addr:full":"Calle de Gibraltar Espa\u00d1ol, 8 Torrijos Toledo 45500",
    "addr:housenumber":"8",
    "addr:postcode":"45500",
    "addr:street":"Calle De Gibraltar Espan\u0303Ol",
    "iso:country":"ES",
    "sg:address":"Calle de Gibraltar Espa\u00d1ol, 8",
    "sg:city":"Torrijos",
    "sg:orig_category":"Aceites Y Grasas Industriales (fabricaci\u00d3n, Al Por Mayor)",
    "sg:phone":"+34 925 77 12 67",
    "sg:postcode":"45500",
    "sg:province":"Toledo",
    "wof:name":"Aceites Y Grasas Tecnicas S.l.",
    "wof:placetype":"venue"
},
  "geometry": {"coordinates":[-4.2820839882,39.9801635742],"type":"Point"}
}