{
  "type": "Feature",
  "properties": {
    "iso:country":"ES",
    "sg:address":"Cantoneras, 15",
    "sg:city":"Telde",
    "sg:orig_category":"Empresas De Limpieza",
    "sg:phone":"+34 928 70 30 66",
    "sg:postcode":"35200",
    "sg:province":"Las Palmas",
    "wof:name":"Limpiezas Lucsant7 S.l.",
    "wof:placetype":"venue"
},
  "geometry": {"coordinates":[-15.4130086899,27.9967746735],"type":"Point"}
}