{
  "type": "Feature",
  "properties": {
    "addr:full":"Calle de Jose Antonio Ochaita, 54 Guadalajara Guadalajara 19004",
    "addr:housenumber":"54",
    "addr:postcode":"19004",
    "addr:street":"Calle De Jose Antonio Ochaita",
    "iso:country":"ES",
    "sg:address":"Calle de Jose Antonio Ochaita, 54",
    "sg:city":"Guadalajara",
    "sg:orig_category":"Asesor\u00cda Sobre Comunicaci\u00d3n De Empresas",
    "sg:phone":"+34 949 24 72 58",
    "sg:postcode":"19004",
    "sg:province":"Guadalajara",
    "wof:name":"Ayce Frama S.l.",
    "wof:placetype":"venue"
},
  "geometry": {"coordinates":[-3.185806036,40.6368408203],"type":"Point"}
}