{
  "type": "Feature",
  "properties": {
    "addr:full":"Av Catalunya (cervello), 15 Cervello Barcelona 08758",
    "addr:housenumber":"15",
    "addr:postcode":"08758",
    "addr:street":"Av Catalunya Cervello;Barcelona",
    "iso:country":"ES",
    "sg:address":"Av Catalunya (cervello), 15",
    "sg:city":"Cervello",
    "sg:orig_category":"Metales (labores, Pulido)",
    "sg:phone":"+34 936 60 11 06",
    "sg:postcode":"08758",
    "sg:province":"Barcelona",
    "wof:name":"Alcala Industrial S.a.",
    "wof:placetype":"venue"
},
  "geometry": {"coordinates":[1.9619584084,41.3966789246],"type":"Point"}
}