{
  "type": "Feature",
  "properties": {
    "addr:full":"Carrer de Lluis Puigjaner, 8 Olesa Montserrat Barcelona 08640",
    "addr:housenumber":"8",
    "addr:postcode":"08640",
    "addr:street":"Carrer De Lluis Puigjaner;Barcelona",
    "iso:country":"ES",
    "sg:address":"Carrer de Lluis Puigjaner, 8",
    "sg:city":"Olesa Montserrat",
    "sg:orig_category":"Congelados: Productos Alimentarios (fabricaci\u00d3n, Al Por Mayor)",
    "sg:phone":"+34 937 78 47 92",
    "sg:postcode":"08640",
    "sg:province":"Barcelona",
    "wof:name":"Estel De Neu S.l",
    "wof:placetype":"venue"
},
  "geometry": {"coordinates":[1.8962249756,41.5419998169],"type":"Point"}
}