{
  "type": "Feature",
  "properties": {
    "iso:country":"ES",
    "sg:address":"Rua Orfas (das), 7",
    "sg:city":"Santiago De Compostela",
    "sg:orig_category":"Bisuter\u00cda, Joyer\u00cda, Relojer\u00cda (al Por Menor)",
    "sg:phone":"+34 981 57 13 84",
    "sg:postcode":"15703",
    "sg:province":"La Coru\u00f1a",
    "wof:name":"Ferreiro Iglesias Carmen",
    "wof:placetype":"venue"
},
  "geometry": {"coordinates":[-8.5435171127,42.8777885437],"type":"Point"}
}