{
  "type": "Feature",
  "properties": {
    "addr:full":"Praz San Bieito, 1 Gondomar Pontevedra 36380",
    "addr:housenumber":"1",
    "addr:postcode":"36380",
    "addr:street":"Praz San Bieito",
    "iso:country":"ES",
    "sg:address":"Praz San Bieito, 1",
    "sg:city":"Gondomar",
    "sg:orig_category":"Molduras, Junquillos, Listones Y Molduras Perforadas",
    "sg:phone":"+34 986 36 00 98",
    "sg:postcode":"36380",
    "sg:province":"Pontevedra",
    "wof:name":"Lorenzo Rodriguez Ramon",
    "wof:placetype":"venue"
},
  "geometry": {"coordinates":[-8.7601099014,42.1119918823],"type":"Point"}
}