{
  "type": "Feature",
  "properties": {
    "addr:full":"Rbla Jaume I, 55 Cambrils Tarragona 43850",
    "addr:housenumber":"55",
    "addr:postcode":"43850",
    "addr:street":"Rbla Jaume I",
    "iso:country":"ES",
    "sg:address":"Rbla Jaume I, 55",
    "sg:city":"Cambrils",
    "sg:orig_category":"Administradores De Bienes Y Delegados De Comunidades De Propietarios",
    "sg:phone":"+34 977 36 02 33",
    "sg:postcode":"43850",
    "sg:province":"Tarragona",
    "wof:name":"Gestion De Fincas Fortuna Cambrils S.l.",
    "wof:placetype":"venue"
},
  "geometry": {"coordinates":[1.0629600286,41.0675201416],"type":"Point"}
}