{
  "type": "Feature",
  "properties": {
    "addr:full":"Calle de Rio Tajo, 1 San Vicente Del Raspeig-sant Vicent Del Raspeig Alicante 03690",
    "addr:housenumber":"1",
    "addr:postcode":"03690",
    "addr:street":"Calle De Rio Tajo",
    "iso:country":"ES",
    "sg:address":"Calle de Rio Tajo, 1",
    "sg:city":"San Vicente Del Raspeig-sant Vicent Del Raspeig",
    "sg:orig_category":"Animales (al Por Menor)",
    "sg:phone":"+34 965 67 24 34",
    "sg:postcode":"03690",
    "sg:province":"Alicante",
    "wof:name":"La Boutique Del Gosset S.l.",
    "wof:placetype":"venue"
},
  "geometry": {"coordinates":[-0.5055260062,38.3919143677],"type":"Point"}
}