{
  "type": "Feature",
  "properties": {
    "addr:full":"Pase Sixto Celorrio, 26 Calatayud Zaragoza 50300",
    "addr:housenumber":"26",
    "addr:postcode":"50300",
    "addr:street":"Sixto Celorrio",
    "iso:country":"ES",
    "sg:address":"Pase Sixto Celorrio, 26",
    "sg:city":"Calatayud",
    "sg:orig_category":"Veh\u00cdculos De Ocasi\u00d3n",
    "sg:phone":"+34 976 88 26 50",
    "sg:postcode":"50300",
    "sg:province":"Zaragoza",
    "sg:website":"www.autobernal.com",
    "wof:name":"Bernal Perez Gerardo",
    "wof:placetype":"venue"
},
  "geometry": {"coordinates":[-1.6426689625,41.349609375],"type":"Point"}
}