{
  "type": "Feature",
  "properties": {
    "iso:country":"ES",
    "sg:address":"Avda Aeronautica (la), 10",
    "sg:city":"Sevilla",
    "sg:orig_category":"Inform\u00c1tica (estudios, Servicios, Asesor\u00cda, Formaci\u00d3n)",
    "sg:phone":"+34 954 40 24 83",
    "sg:postcode":"41020",
    "sg:province":"Sevilla",
    "sg:website":"www.lamb-soft.com",
    "wof:name":"Lamb Software S.l.",
    "wof:placetype":"venue"
},
  "geometry": {"coordinates":[-5.9197850227,37.3885612488],"type":"Point"}
}