{
  "type": "Feature",
  "properties": {
    "addr:full":"Calle de Nuestra Se\u00d1ora De Regla, 2 Mairena Alcor Sevilla 41510",
    "addr:housenumber":"2",
    "addr:postcode":"41510",
    "addr:street":"Calle De Nuestra Sen\u0303Ora De Regla",
    "iso:country":"ES",
    "sg:address":"Calle de Nuestra Se\u00d1ora De Regla, 2",
    "sg:city":"Mairena Alcor",
    "sg:orig_category":"Panader\u00cdas, Panader\u00cdas",
    "sg:phone":"+34 955 94 26 60",
    "sg:postcode":"41510",
    "sg:province":"Sevilla",
    "wof:name":"Toro Requena Juan",
    "wof:placetype":"venue"
},
  "geometry": {"coordinates":[-5.7534999847,37.3666610718],"type":"Point"}
}