{
  "type": "Feature",
  "properties": {
    "iso:country":"ES",
    "sg:address":"Rond Sancti Spiritus, 8",
    "sg:city":"Salamanca",
    "sg:orig_category":"Ense\u00d1anza, Formaci\u00d3n Profesional: Aprendizaje",
    "sg:phone":"+34 923 12 77 00",
    "sg:postcode":"37...",
    "sg:province":"Salamanca",
    "wof:name":"Direccion General De La Policia",
    "wof:placetype":"venue"
},
  "geometry": {"coordinates":[-5.659954071,40.9650611877],"type":"Point"}
}