{
  "type": "Feature",
  "properties": {
    "iso:country":"ES",
    "sg:address":"Avda Paz, 17",
    "sg:city":"Martos",
    "sg:orig_category":"Prendas Y Chalecos De Punto (al Por Menor)",
    "sg:phone":"+34 953 55 02 66",
    "sg:postcode":"23600",
    "sg:province":"Ja\u00e9n",
    "wof:name":"Francisco Garcia Aparicio Jose Garcia Aparicio Y Antonio Garcia Aparicio C.b.",
    "wof:placetype":"venue"
},
  "geometry": {"coordinates":[-3.9744689465,37.7198600769],"type":"Point"}
}