{
  "type": "Feature",
  "properties": {
    "iso:country":"ES",
    "sg:address":"Rua Xavier Sensat, 8",
    "sg:city":"Ameixeira",
    "sg:orig_category":"Centros De Educaci\u00d3n Especial",
    "sg:phone":"+34 986 24 11 50",
    "sg:postcode":"36208",
    "sg:province":"Pontevedra",
    "wof:name":"Colexio Publico Javier Sensat",
    "wof:placetype":"venue"
},
  "geometry": {"coordinates":[-8.7332239151,42.2212409973],"type":"Point"}
}