{
  "type": "Feature",
  "properties": {
    "iso:country":"ES",
    "sg:address":"Calle de Monteleon, 18",
    "sg:city":"Madrid",
    "sg:orig_category":"Comidas Por Encargo, Organizaci\u00d3n De Recepciones",
    "sg:phone":"+34 915 93 32 91",
    "sg:postcode":"28004",
    "sg:province":"Madrid",
    "wof:name":"Requena Lozano Jesus",
    "wof:placetype":"venue"
},
  "geometry": {"coordinates":[-3.704791069,40.428352356],"type":"Point"}
}