{
  "type": "Feature",
  "properties": {
    "addr:full":"Calle de Moral (del), S/n Torralba De Ribota Zaragoza 50311",
    "addr:housenumber":"/ n",
    "addr:postcode":"50311",
    "addr:street":"Calle De Moral Del S",
    "iso:country":"ES",
    "sg:address":"Calle de Moral (del), S/n",
    "sg:city":"Torralba De Ribota",
    "sg:orig_category":"Mataderos Y Talleres De Despiezado",
    "sg:phone":"+34 976 89 61 00",
    "sg:postcode":"50311",
    "sg:province":"Zaragoza",
    "wof:name":"Carnicas Kurtz Calatayud S.a.",
    "wof:placetype":"venue"
},
  "geometry": {"coordinates":[-1.6845690012,41.4174308777],"type":"Point"}
}