{
  "type": "Feature",
  "properties": {
    "addr:full":"Calle de Desierto De Las Palmas, 4 Castellon Castell\u00f3n 12006",
    "addr:housenumber":"4",
    "addr:postcode":"12006",
    "addr:street":"Calle De Desierto De Las Palmas;Castello\u0301N",
    "iso:country":"ES",
    "sg:address":"Calle de Desierto De Las Palmas, 4",
    "sg:city":"Castellon",
    "sg:orig_category":"Contenedores (mercanc\u00cdas)",
    "sg:phone":"+34 964 21 21 09",
    "sg:postcode":"12006",
    "sg:province":"Castell\u00f3n",
    "wof:name":"Martinez Gomariz S.l",
    "wof:placetype":"venue"
},
  "geometry": {"coordinates":[-0.0550800003,39.9728736877],"type":"Point"}
}