{
  "type": "Feature",
  "properties": {
    "addr:full":"Ugaldeguren, S/n Ugaldeguren Vizcaya 48160",
    "addr:housenumber":"s / n",
    "addr:postcode":"48160",
    "addr:street":"Ugaldeguren",
    "iso:country":"ES",
    "sg:address":"Ugaldeguren, S/n",
    "sg:city":"Ugaldeguren",
    "sg:orig_category":"Congelados: Productos Alimentarios (fabricaci\u00d3n, Al Por Mayor)",
    "sg:phone":"+34 944 54 00 50",
    "sg:postcode":"48160",
    "sg:province":"Vizcaya",
    "sg:website":"www.searord.co.nz",
    "wof:name":"Europacifico Alimentos Del Mar S.l.",
    "wof:placetype":"venue"
},
  "geometry": {"coordinates":[-2.9316000938,43.2383995056],"type":"Point"}
}