{
  "type": "Feature",
  "properties": {
    "iso:country":"ES",
    "sg:address":"Calle de Mayor, 105",
    "sg:city":"Garrucha",
    "sg:orig_category":"Electrodom\u00c9sticos (al Por Menor)",
    "sg:phone":"+34 950 13 39 36",
    "sg:postcode":"04630",
    "sg:province":"Almer\u00eda",
    "wof:name":"Mapayma S.l.l",
    "wof:placetype":"venue"
},
  "geometry": {"coordinates":[-1.822764039,37.1780128479],"type":"Point"}
}