{
  "type": "Feature",
  "properties": {
    "iso:country":"ES",
    "sg:address":"Carrer de Londres, 85",
    "sg:city":"Barcelona",
    "sg:orig_category":"Peluquer\u00cdas, Peluquer\u00cda Mixta",
    "sg:phone":"+34 934 30 42 64",
    "sg:postcode":"08036",
    "sg:province":"Barcelona",
    "wof:name":"Albert-feixas S.c.p.",
    "wof:placetype":"venue"
},
  "geometry": {"coordinates":[2.1498777866,41.3928413391],"type":"Point"}
}