{
  "type": "Feature",
  "properties": {
    "addr:full":"Carrer de Sauri, 15 Hospitalet Llobregat Barcelona 08901",
    "addr:housenumber":"15",
    "addr:postcode":"08901",
    "addr:street":"Carrer De Sauri",
    "iso:country":"ES",
    "sg:address":"Carrer de Sauri, 15",
    "sg:city":"Hospitalet Llobregat",
    "sg:orig_category":"Rectificaci\u00d3n, Mecanizado, Fresado",
    "sg:phone":"+34 933 37 36 86",
    "sg:postcode":"08901",
    "sg:province":"Barcelona",
    "wof:name":"Talleres Fontoba S.l.",
    "wof:placetype":"venue"
},
  "geometry": {"coordinates":[2.1056129932,41.3596153259],"type":"Point"}
}