{
  "type": "Feature",
  "properties": {
    "iso:country":"ES",
    "sg:address":"Avda Andalucia, 28",
    "sg:city":"Linares",
    "sg:orig_category":"Profesiones M\u00c9dicas, Param\u00c9dicas",
    "sg:phone":"+34 953 69 75 10",
    "sg:postcode":"23700",
    "sg:province":"Ja\u00e9n",
    "wof:name":"Plaza Fernandez Alejandro",
    "wof:placetype":"venue"
},
  "geometry": {"coordinates":[-3.6404490471,38.092716217],"type":"Point"}
}