{
  "type": "Feature",
  "properties": {
    "iso:country":"ES",
    "sg:address":"Calle de Santa Teresa, 38",
    "sg:city":"Hoyo De Pinares",
    "sg:orig_category":"Carnicer\u00cdas, Carnicer\u00cdas",
    "sg:phone":"+34 918 63 80 05",
    "sg:postcode":"05250",
    "sg:province":"\u00c1vila",
    "wof:name":"Herranz Pablo Emiliano",
    "wof:placetype":"venue"
},
  "geometry": {"coordinates":[-4.4220290184,40.5020103455],"type":"Point"}
}