{
  "type": "Feature",
  "properties": {
    "addr:full":"Calle de San Cristobal, 16 Castellon Castell\u00f3n 12002",
    "addr:housenumber":"16",
    "addr:postcode":"12002",
    "addr:street":"Calle De San Cristobal",
    "iso:country":"ES",
    "sg:address":"Calle de San Cristobal, 16",
    "sg:city":"Castellon",
    "sg:orig_category":"Prot\u00c9sicos Dentales",
    "sg:phone":"+34 964 20 17 49",
    "sg:postcode":"12002",
    "sg:province":"Castell\u00f3n",
    "wof:name":"Trenco Aparici Juan",
    "wof:placetype":"venue"
},
  "geometry": {"coordinates":[-0.0405160002,39.9830818176],"type":"Point"}
}