{
  "type": "Feature",
  "properties": {
    "iso:country":"ES",
    "sg:address":"Rua Union, 32",
    "sg:city":"Pobra Do Carami\u00e7al",
    "sg:orig_category":"Peluqueros: De Se\u00d1oras",
    "sg:phone":"+34 981 83 09 50",
    "sg:postcode":"15940",
    "sg:province":"A Coru\u00f1a",
    "wof:name":"Tonseda Ozores Marta",
    "wof:placetype":"venue"
},
  "geometry": {"coordinates":[-8.9376049042,42.6029777527],"type":"Point"}
}