{
  "type": "Feature",
  "properties": {
    "iso:country":"ES",
    "sg:address":"Calle de Torres Cartas, S/n",
    "sg:city":"Sorbas",
    "sg:orig_category":"Promotores Constructores",
    "sg:phone":"+34 950 36 40 20",
    "sg:postcode":"04270",
    "sg:province":"Almer\u00eda",
    "wof:name":"La Cumbre Sorbas S.l",
    "wof:placetype":"venue"
},
  "geometry": {"coordinates":[-2.1253640652,37.0979614258],"type":"Point"}
}