{
  "type": "Feature",
  "properties": {
    "iso:country":"ES",
    "sg:address":"Avda Colonia (de La), 9",
    "sg:city":"Linea De La Concepcion",
    "sg:orig_category":"Servicios Gsm",
    "sg:phone":"+34 956 76 00 69",
    "sg:postcode":"11300",
    "sg:province":"C\u00e1diz",
    "wof:name":"Comunicaciones El Puerto S.l.",
    "wof:placetype":"venue"
},
  "geometry": {"coordinates":[-5.3622441292,36.1733894348],"type":"Point"}
}