{
  "type": "Feature",
  "properties": {
    "addr:full":"Calle de Vicente Camaron, 28 Madrid Madrid 28011",
    "addr:housenumber":"28",
    "addr:postcode":"madrid;28011",
    "addr:street":"Calle De Vicente Camaron",
    "iso:country":"ES",
    "sg:address":"Calle de Vicente Camaron, 28",
    "sg:city":"Madrid",
    "sg:orig_category":"Comercio De Piezas De Recambio Y De Accesorios De Veh\u00cdculos, Veh\u00cdculos Industriales",
    "sg:phone":"+34 915 26 02 65",
    "sg:postcode":"28011",
    "sg:province":"Madrid",
    "wof:name":"Vila Rodriguez Manuel",
    "wof:placetype":"venue"
},
  "geometry": {"coordinates":[-3.7388470173,40.4062232971],"type":"Point"}
}