{
  "type": "Feature",
  "properties": {
    "iso:country":"ES",
    "sg:address":"Calle de Serrano, 93",
    "sg:city":"Madrid",
    "sg:orig_category":"Veh\u00cdculos De Ocasi\u00d3n",
    "sg:phone":"+34 915 15 84 44",
    "sg:postcode":"28006",
    "sg:province":"Madrid",
    "sg:website":"www.manycars.es",
    "wof:name":"Saymo S. L.",
    "wof:placetype":"venue"
},
  "geometry": {"coordinates":[-3.686455965,40.4376144409],"type":"Point"}
}