{
  "type": "Feature",
  "properties": {
    "addr:full":"Calle de Unica (gavin), S/n Gavin Huesca 22639",
    "addr:housenumber":"s / n",
    "addr:postcode":"22639",
    "addr:street":"Calle De Unica Gavin",
    "iso:country":"ES",
    "sg:address":"Calle de Unica (gavin), S/n",
    "sg:city":"Gavin",
    "sg:orig_category":"Venta, Instalaci\u00d3n De Cocinas",
    "sg:phone":"+34 974 49 55 50",
    "sg:postcode":"22639",
    "sg:province":"Huesca",
    "wof:name":"Meson Casa Diego S.cv.",
    "wof:placetype":"venue"
},
  "geometry": {"coordinates":[-0.2966836095,42.6186103821],"type":"Point"}
}