{
  "type": "Feature",
  "properties": {
    "iso:country":"ES",
    "sg:address":"Av Alcodar(pol Alcodar), 31",
    "sg:city":"Gandia",
    "sg:orig_category":"Supermercados Y Hipermercados",
    "sg:phone":"+34 962 96 23 87",
    "sg:postcode":"46700",
    "sg:province":"Valencia",
    "wof:name":"Princesalisimo S.l.",
    "wof:placetype":"venue"
},
  "geometry": {"coordinates":[-0.1836590022,38.9854621887],"type":"Point"}
}