{
  "type": "Feature",
  "properties": {
    "addr:full":"Calle de Fernando Villaamil, 4 Oviedo Asturias 33006",
    "addr:housenumber":"4",
    "addr:postcode":"33006",
    "addr:street":"Calle De Fernando Villaamil",
    "iso:country":"ES",
    "sg:address":"Calle de Fernando Villaamil, 4",
    "sg:city":"Oviedo",
    "sg:orig_category":"Venta, Alquiler De Plataformas Y Barquillas Elevadoras",
    "sg:phone":"+34 985 29 22 92",
    "sg:postcode":"33006",
    "sg:province":"Asturias",
    "wof:name":"Industrial De Elevacion S.a.",
    "wof:placetype":"venue"
},
  "geometry": {"coordinates":[-5.8401780128,43.3710517883],"type":"Point"}
}