{
  "type": "Feature",
  "properties": {
    "iso:country":"ES",
    "sg:address":"Ptge Coma, 1",
    "sg:city":"Poligon Industrial Pla De La Bruguera",
    "sg:orig_category":"Goma: Productos De Uso Industrial (fabricaci\u00d3n, Al Por Mayor)",
    "sg:phone":"+34 937 14 39 36",
    "sg:postcode":"08211",
    "sg:province":"Barcelona",
    "wof:name":"Comercial Gominsa Sabadell S.l.",
    "wof:placetype":"venue"
},
  "geometry": {"coordinates":[2.0857300758,41.6151885986],"type":"Point"}
}