{
  "type": "Feature",
  "properties": {
    "addr:full":"Av Vives Llull, 24 Mao Islas Baleares 07703",
    "addr:housenumber":"24",
    "addr:postcode":"07703",
    "addr:street":"Av Vives Llull",
    "iso:country":"ES",
    "sg:address":"Av Vives Llull, 24",
    "sg:city":"Mao",
    "sg:orig_category":"Relojer\u00cda (al Por Menor, Reparaci\u00d3n)",
    "sg:phone":"+34 971 35 55 78",
    "sg:postcode":"07703",
    "sg:province":"Islas Baleares",
    "wof:name":"Aranda Fuster Ana Maria",
    "wof:placetype":"venue"
},
  "geometry": {"coordinates":[4.2547683716,39.8881721497],"type":"Point"}
}