{
  "type": "Feature",
  "properties": {
    "addr:full":"Avda Fisterra, 90 Arteixo La Coru\u00f1a 15142",
    "addr:housenumber":"90",
    "addr:postcode":"15142",
    "addr:street":"Avda Fisterra;La Corun\u0303A",
    "iso:country":"ES",
    "sg:address":"Avda Fisterra, 90",
    "sg:city":"Arteixo",
    "sg:orig_category":"Fabricaci\u00d3n De Acumuladores Y De Pilas El\u00c9ctricas",
    "sg:phone":"+34 981 64 17 37",
    "sg:postcode":"15142",
    "sg:province":"La Coru\u00f1a",
    "wof:name":"F.c. Gas Arteixo S.l.",
    "wof:placetype":"venue"
},
  "geometry": {"coordinates":[-8.5084037781,43.305770874],"type":"Point"}
}