{
  "type": "Feature",
  "properties": {
    "addr:full":"Calle de Escultor Diego Marquez, 5 Antequera M\u00e1laga 29200",
    "addr:housenumber":"5",
    "addr:postcode":"29200",
    "addr:street":"Calle De Escultor Diego Marquez",
    "iso:country":"ES",
    "sg:address":"Calle de Escultor Diego Marquez, 5",
    "sg:city":"Antequera",
    "sg:classifiers":[
        {
            "category":"Taxi",
            "type":"Transportation"
        }
    ],
    "sg:phone":"+34 952 84 04 59",
    "sg:postcode":"29200",
    "sg:province":"M\u00e1laga",
    "wof:name":"Garcia Rios Antonio",
    "wof:placetype":"venue"
},
  "geometry": {"coordinates":[-4.5696411133,37.0197486877],"type":"Point"}
}