{
  "type": "Feature",
  "properties": {
    "addr:full":"Carretera De Burgos-santander, S/n Villatoro Burgos 09006",
    "addr:housenumber":"s",
    "addr:postcode":"09006",
    "addr:street":"Carretera De Burgos-Santander;/ N",
    "iso:country":"ES",
    "sg:address":"Carretera De Burgos-santander, S/n",
    "sg:city":"Villatoro",
    "sg:orig_category":"Piscinas, Accesorios, Suministros (fabricaci\u00d3n, Al Por Mayor)",
    "sg:phone":"+34 947 29 39 14",
    "sg:postcode":"09006",
    "sg:province":"Burgos",
    "wof:name":"Gardem House Albert S.l.",
    "wof:placetype":"venue"
},
  "geometry": {"coordinates":[-3.6922140121,42.3745231628],"type":"Point"}
}