{
  "type": "Feature",
  "properties": {
    "addr:full":"Carrer de Xile, 133 Amposta Tarragona 43870",
    "addr:housenumber":"133",
    "addr:postcode":"43870",
    "addr:street":"Carrer De Xile",
    "iso:country":"ES",
    "sg:address":"Carrer de Xile, 133",
    "sg:city":"Amposta",
    "sg:orig_category":"Fotograf\u00cda Art\u00cdstica Y Retratos",
    "sg:phone":"+34 977 70 60 24",
    "sg:postcode":"43870",
    "sg:province":"Tarragona",
    "wof:name":"Faus Roig Jose Maria",
    "wof:placetype":"venue"
},
  "geometry": {"coordinates":[0.5732269883,40.703086853],"type":"Point"}
}