{
  "type": "Feature",
  "properties": {
    "iso:country":"ES",
    "sg:address":"Calle de Canonigo Torres, 8",
    "sg:city":"Torrevieja",
    "sg:orig_category":"Grafistas",
    "sg:phone":"+34 966 70 00 02",
    "sg:postcode":"03180",
    "sg:province":"Alicante",
    "wof:name":"Nuevos Medios Creativos Sl",
    "wof:placetype":"venue"
},
  "geometry": {"coordinates":[-0.6830487251,37.9761657715],"type":"Point"}
}