{
  "type": "Feature",
  "properties": {
    "addr:full":"Avda Soria, 2 Sardon Duero Valladolid 47340",
    "addr:housenumber":"2",
    "addr:postcode":"47340",
    "addr:street":"Avda Soria",
    "iso:country":"ES",
    "sg:address":"Avda Soria, 2",
    "sg:city":"Sardon Duero",
    "sg:orig_category":"Hoteles",
    "sg:phone":"+34 983 68 03 07",
    "sg:postcode":"47340",
    "sg:province":"Valladolid",
    "wof:name":"Hostal Sardon S.l.",
    "wof:placetype":"venue"
},
  "geometry": {"coordinates":[-4.4301719666,41.6075782776],"type":"Point"}
}