{
  "type": "Feature",
  "properties": {
    "addr:full":"Ctra Burgos-portugal, 63 Alaejos Valladolid 47510",
    "addr:housenumber":"63",
    "addr:postcode":"47510",
    "addr:street":"Ctra Burgos-Portugal",
    "iso:country":"ES",
    "sg:address":"Ctra Burgos-portugal, 63",
    "sg:city":"Alaejos",
    "sg:orig_category":"Transportes Por V\u00cdas Navegables",
    "sg:phone":"+34 983 86 73 11",
    "sg:postcode":"47510",
    "sg:province":"Valladolid",
    "wof:name":"Garcia Nieto Alfonso",
    "wof:placetype":"venue"
},
  "geometry": {"coordinates":[-5.2201194763,41.3058700562],"type":"Point"}
}