{
  "type": "Feature",
  "properties": {
    "iso:country":"ES",
    "sg:address":"Avda Linares Rivas, 28",
    "sg:city":"Coru\u00d1a",
    "sg:orig_category":"Ingenier\u00cda, Centros De Estudios (diversos)",
    "sg:phone":"+34 981 12 13 99",
    "sg:postcode":"15005",
    "sg:province":"La Coru\u00f1a",
    "wof:name":"Eptisa Servicios De Ingenieria S.a.",
    "wof:placetype":"venue"
},
  "geometry": {"coordinates":[-8.4054718018,43.3629379272],"type":"Point"}
}