{
  "type": "Feature",
  "properties": {
    "addr:full":"Calle de Zurita, 5 Villanueva Gallego Zaragoza 50830",
    "addr:housenumber":"5",
    "addr:postcode":"50830",
    "addr:street":"Calle De Zurita",
    "iso:country":"ES",
    "sg:address":"Calle de Zurita, 5",
    "sg:city":"Villanueva Gallego",
    "sg:orig_category":"Maquinaria Para Industrias Diversas",
    "sg:phone":"+34 976 18 04 90",
    "sg:postcode":"50830",
    "sg:province":"Zaragoza",
    "wof:name":"Abadia Lope Alberto",
    "wof:placetype":"venue"
},
  "geometry": {"coordinates":[-0.826805,41.768475],"type":"Point"}
}