{
  "type": "Feature",
  "properties": {
    "addr:full":"Alba\u00f1iles (pi Las Yeguas), 14 Sanlucar Mayor Sevilla 41800",
    "addr:housenumber":"14",
    "addr:postcode":"41800",
    "addr:street":"Yeguas",
    "iso:country":"ES",
    "sg:address":"Alba\u00f1iles (pi Las Yeguas), 14",
    "sg:city":"Sanlucar Mayor",
    "sg:orig_category":"Empresas De Carpinter\u00cda",
    "sg:phone":"+34 955 70 23 90",
    "sg:postcode":"41800",
    "sg:province":"Sevilla",
    "wof:name":"Cortes Nu\u00f1ez Francisco Javier",
    "wof:placetype":"venue"
},
  "geometry": {"coordinates":[-6.1956338882,37.3855361938],"type":"Point"}
}