{
  "type": "Feature",
  "properties": {
    "addr:full":"Carrer de Font I Quer, 9 Manresa Barcelona 08242",
    "addr:housenumber":"9",
    "addr:postcode":"08242",
    "addr:street":"Carrer De Font I Quer",
    "iso:country":"ES",
    "sg:address":"Carrer de Font I Quer, 9",
    "sg:city":"Manresa",
    "sg:orig_category":"Empresarios Y Productoras De Espect\u00c1culos",
    "sg:phone":"+34 938 73 27 39",
    "sg:postcode":"08242",
    "sg:province":"Barcelona",
    "sg:website":"www.espectacle.org/victori",
    "wof:name":"Produccions Artistiques Victori S.l.",
    "wof:placetype":"venue"
},
  "geometry": {"coordinates":[1.8231099844,41.732219696],"type":"Point"}
}