{
  "type": "Feature",
  "properties": {
    "addr:full":"Calle de Conde De Pe\u00d1alver, 32 Madrid Madrid 28006",
    "addr:housenumber":"32",
    "addr:postcode":"madrid;28006",
    "addr:street":"Calle De Conde De Pen\u0303Alver",
    "iso:country":"ES",
    "sg:address":"Calle de Conde De Pe\u00d1alver, 32",
    "sg:city":"Madrid",
    "sg:orig_category":"Librer\u00cdas",
    "sg:phone":"+34 913 09 39 84",
    "sg:postcode":"28006",
    "sg:province":"Madrid",
    "wof:name":"Cortes Minguez Rosa Maria",
    "wof:placetype":"venue"
},
  "geometry": {"coordinates":[-3.6752550602,40.4282951355],"type":"Point"}
}