{
  "type": "Feature",
  "properties": {
    "iso:country":"ES",
    "sg:address":"Luga Brexo, 21",
    "sg:city":"Brexo-lema",
    "sg:orig_category":"Polideportivos",
    "sg:phone":"+34 981 65 51 42",
    "sg:postcode":"15669",
    "sg:province":"La Coru\u00f1a",
    "wof:name":"Concello De Cambre",
    "wof:placetype":"venue"
},
  "geometry": {"coordinates":[-8.3039340973,43.2731208801],"type":"Point"}
}