{
  "type": "Feature",
  "properties": {
    "iso:country":"ES",
    "sg:address":"Carrer de Montiu, 1",
    "sg:city":"Montcada Centre",
    "sg:orig_category":"Promotores Constructores",
    "sg:phone":"+34 935 64 84 00",
    "sg:postcode":"08110",
    "sg:province":"Barcelona",
    "sg:website":"www.mtcinversion.com",
    "wof:name":"Mtc Inversions S.a.",
    "wof:placetype":"venue"
},
  "geometry": {"coordinates":[2.1876699924,41.4844589233],"type":"Point"}
}