{
  "type": "Feature",
  "properties": {
    "iso:country":"ES",
    "sg:address":"Ctra Badajoz, Km. 0057,2",
    "sg:city":"San Marcos",
    "sg:orig_category":"Mec\u00c1nico Del Autom\u00d3vil",
    "sg:phone":"+34 924 66 22 39",
    "sg:postcode":"06200",
    "sg:province":"Badajoz",
    "wof:name":"Mecanicos Extreme\u00f1os S.l.",
    "wof:placetype":"venue"
},
  "geometry": {"coordinates":[-6.4123888016,38.6829681396],"type":"Point"}
}