{
  "type": "Feature",
  "properties": {
    "addr:full":"Calle de Libertad, 2 Casas De Juan Nu\u00e7ez Albacete 02151",
    "addr:housenumber":"2",
    "addr:postcode":"02151",
    "addr:street":"Calle De Libertad",
    "iso:country":"ES",
    "sg:address":"Calle de Libertad, 2",
    "sg:city":"Casas De Juan Nu\u00e7ez",
    "sg:orig_category":"Cajas Para Embalar",
    "sg:phone":"+34 967 40 50 76",
    "sg:postcode":"02151",
    "sg:province":"Albacete",
    "sg:website":"www.ruralvia.com",
    "wof:name":"Caja Rural De Albacete",
    "wof:placetype":"venue"
},
  "geometry": {"coordinates":[-1.5578780174,39.1017570496],"type":"Point"}
}