{
  "type": "Feature",
  "properties": {
    "addr:full":"Calle de Vejer, 5 Benalup C\u00e1diz 11190",
    "addr:housenumber":"5",
    "addr:postcode":"11190",
    "addr:street":"Calle De Vejer;Ca\u0301Diz",
    "iso:country":"ES",
    "sg:address":"Calle de Vejer, 5",
    "sg:city":"Benalup",
    "sg:orig_category":"Aguas (distribuci\u00d3n, Servicios)",
    "sg:phone":"+34 956 42 41 14",
    "sg:postcode":"11190",
    "sg:province":"C\u00e1diz",
    "wof:name":"Aqualia Gestion Integral Del Agua S.a.",
    "wof:placetype":"venue"
},
  "geometry": {"coordinates":[-5.8228387833,36.3426589966],"type":"Point"}
}