{
  "type": "Feature",
  "properties": {
    "addr:full":"Ctra Villalpando (de), S/n Benegiles Zamora 49123",
    "addr:postcode":"49123",
    "addr:street":"Ctra Villalpando De S / N Benegiles Zamora",
    "iso:country":"ES",
    "sg:address":"Ctra Villalpando (de), S/n",
    "sg:city":"Benegiles",
    "sg:orig_category":"Bancos",
    "sg:phone":"+34 980 50 42 70",
    "sg:postcode":"49123",
    "sg:province":"Zamora",
    "wof:name":"Caja Rural De Zamora",
    "wof:placetype":"venue"
},
  "geometry": {"coordinates":[-5.6345977783,41.6290359497],"type":"Point"}
}