{
  "type": "Feature",
  "properties": {
    "iso:country":"ES",
    "sg:address":"Carrer de Congost, 22",
    "sg:city":"Barcelona",
    "sg:orig_category":"Asociaciones Y Clubs Deportivos",
    "sg:phone":"+34 932 13 58 38",
    "sg:postcode":"08024",
    "sg:province":"Barcelona",
    "wof:name":"Club Colombofil Missatgeras Barcelona",
    "wof:placetype":"venue"
},
  "geometry": {"coordinates":[2.1586101055,41.4062080383],"type":"Point"}
}