{
  "type": "Feature",
  "properties": {
    "iso:country":"ES",
    "sg:address":"Avda Extremadura, S/n",
    "sg:city":"Velada",
    "sg:orig_category":"Plomeros",
    "sg:phone":"+34 925 89 21 05",
    "sg:postcode":"45612",
    "sg:province":"Toledo",
    "wof:name":"Materiales Y Construccion Dasilva Calvo S.l.",
    "wof:placetype":"venue"
},
  "geometry": {"coordinates":[-4.972304821,39.9785308838],"type":"Point"}
}