{
  "type": "Feature",
  "properties": {
    "iso:country":"ES",
    "sg:address":"Rbla San Pedro (de), 7",
    "sg:city":"Biescas",
    "sg:orig_category":"Hoteles",
    "sg:phone":"+34 974 48 51 77",
    "sg:postcode":"22630",
    "sg:province":"Huesca",
    "wof:name":"Hotel La Rambla S.cv.",
    "wof:placetype":"venue"
},
  "geometry": {"coordinates":[-0.3236869872,42.6277885437],"type":"Point"}
}