{
  "type": "Feature",
  "properties": {
    "addr:full":"Calle de Pedro Icaza Aguirre, 9 Santurtzi Vizcaya 48980",
    "addr:housenumber":"9",
    "addr:postcode":"48980",
    "addr:street":"Calle De Pedro Icaza Aguirre",
    "iso:country":"ES",
    "sg:address":"Calle de Pedro Icaza Aguirre, 9",
    "sg:city":"Santurtzi",
    "sg:orig_category":"Abogados",
    "sg:phone":"+34 944 83 77 97",
    "sg:postcode":"48980",
    "sg:province":"Vizcaya",
    "wof:name":"Aldama Zorrilla Maria Beatriz",
    "wof:placetype":"venue"
},
  "geometry": {"coordinates":[-3.0306050777,43.3263587952],"type":"Point"}
}