{
  "type": "Feature",
  "properties": {
    "addr:full":"Calle de Guma, 12 Caspe Zaragoza 50700",
    "addr:housenumber":"12",
    "addr:postcode":"50700",
    "addr:street":"Calle De Guma",
    "iso:country":"ES",
    "sg:address":"Calle de Guma, 12",
    "sg:city":"Caspe",
    "sg:orig_category":"Quincaller\u00cda (al Por Menor)",
    "sg:phone":"+34 976 63 24 21",
    "sg:postcode":"50700",
    "sg:province":"Zaragoza",
    "sg:website":"www.ferrovicmar.com",
    "wof:name":"Tomas Bolufer Vicente Ramon",
    "wof:placetype":"venue"
},
  "geometry": {"coordinates":[-0.0427169986,41.2367591858],"type":"Point"}
}