{
  "type": "Feature",
  "properties": {
    "addr:full":"Rua Fabrica, 89 Carballo La Coru\u00f1a 15100",
    "addr:housenumber":"89",
    "addr:postcode":"15100",
    "addr:street":"Rua Fabrica;La Corun\u0303A",
    "iso:country":"ES",
    "sg:address":"Rua Fabrica, 89",
    "sg:city":"Carballo",
    "sg:orig_category":"Maquinaria Para Industrias Diversas",
    "sg:phone":"+34 981 70 15 22",
    "sg:postcode":"15100",
    "sg:province":"La Coru\u00f1a",
    "wof:name":"Pose Fari\u00f1a Carlos Miguel",
    "wof:placetype":"venue"
},
  "geometry": {"coordinates":[-8.6971302032,43.2157058716],"type":"Point"}
}