{
  "type": "Feature",
  "properties": {
    "iso:country":"ES",
    "sg:address":"Calle de Mayor, 27",
    "sg:city":"Llano De Brujas",
    "sg:orig_category":"Estancos",
    "sg:phone":"+34 968 30 12 92",
    "sg:postcode":"30161",
    "sg:province":"Murcia",
    "wof:name":"Nicolas Mirete Antonio",
    "wof:placetype":"venue"
},
  "geometry": {"coordinates":[-1.0724149942,38.0051345825],"type":"Point"}
}