{
  "type": "Feature",
  "properties": {
    "addr:full":"Bule Jose Prat, 21 Madrid Madrid 28032",
    "addr:housenumber":"21",
    "addr:postcode":"madrid;28032",
    "addr:street":"Prat",
    "iso:country":"ES",
    "sg:address":"Bule Jose Prat, 21",
    "sg:city":"Madrid",
    "sg:orig_category":"Panader\u00cdas, Panader\u00cdas",
    "sg:phone":"+34 917 51 15 39",
    "sg:postcode":"28032",
    "sg:province":"Madrid",
    "wof:name":"Caramel S.l.",
    "wof:placetype":"venue"
},
  "geometry": {"coordinates":[-3.621573925,40.3978347778],"type":"Point"}
}