{
  "type": "Feature",
  "properties": {
    "addr:full":"Calle de Carretera, 57 Martinez \u00c1vila 05152",
    "addr:housenumber":"57",
    "addr:postcode":"05152",
    "addr:street":"Calle De Carretera;A\u0301Vila",
    "iso:country":"ES",
    "sg:address":"Calle de Carretera, 57",
    "sg:city":"Martinez",
    "sg:orig_category":"Farmacias",
    "sg:phone":"+34 920 36 81 75",
    "sg:postcode":"05152",
    "sg:province":"\u00c1vila",
    "wof:name":"Tuesta Rueda Sonia",
    "wof:placetype":"venue"
},
  "geometry": {"coordinates":[-97.78224945069999,45.7040786743],"type":"Point"}
}