{
  "type": "Feature",
  "properties": {
    "iso:country":"ES",
    "sg:address":"Plaz Virgen De Los Reyes, S/n",
    "sg:city":"Sevilla",
    "sg:classifiers":[
        {
            "category":"Communications",
            "type":"Services"
        }
    ],
    "sg:phone":"+34 954 29 31 60",
    "sg:postcode":"41004",
    "sg:province":"Sevilla",
    "sg:tags":[
        "televisiones",
        "y",
        "radio"
    ],
    "wof:name":"Radio Popular S.a.",
    "wof:placetype":"venue"
},
  "geometry": {"coordinates":[-5.9921240807,37.3862876892],"type":"Point"}
}