{
  "type": "Feature",
  "properties": {
    "addr:full":"Pico Machata, 4 Valdemorillo Madrid 28210",
    "addr:housenumber":"4",
    "addr:postcode":"28210",
    "addr:street":"Machata",
    "iso:country":"ES",
    "sg:address":"Pico Machata, 4",
    "sg:city":"Valdemorillo",
    "sg:orig_category":"Servicios De Higiene Y Peluquer\u00cda Para Perros Y Gatos",
    "sg:phone":"+34 918 97 77 62",
    "sg:postcode":"28210",
    "sg:province":"Madrid",
    "wof:name":"Taher Taher Larbi",
    "wof:placetype":"venue"
},
  "geometry": {"coordinates":[-4.0687851906,40.4999160767],"type":"Point"}
}