{
  "type": "Feature",
  "properties": {
    "addr:full":"Calle de Portalet, 4 Valencia Valencia 46025",
    "addr:housenumber":"4",
    "addr:postcode":"46025",
    "addr:street":"Calle De Portalet",
    "iso:country":"ES",
    "sg:address":"Calle de Portalet, 4",
    "sg:city":"Valencia",
    "sg:orig_category":"Iglesia Cat\u00d3lica",
    "sg:phone":"+34 963 40 51 70",
    "sg:postcode":"46025",
    "sg:province":"Valencia",
    "wof:name":"Parroquia De San Roque",
    "wof:placetype":"venue"
},
  "geometry": {"coordinates":[-0.3909089863,39.4927406311],"type":"Point"}
}