{
  "type": "Feature",
  "properties": {
    "iso:country":"ES",
    "sg:address":"Calle de Siete Picos, 13",
    "sg:city":"Rozas De Madrid",
    "sg:orig_category":"Audiovisuales (producci\u00d3n, Edici\u00d3n, Realizaci\u00d3n)",
    "sg:phone":"+34 916 37 79 37",
    "sg:postcode":"28230",
    "sg:province":"Madrid",
    "wof:name":"Malas Compa\u00d1ias Servicios Musicales S.l.",
    "wof:placetype":"venue"
},
  "geometry": {"coordinates":[-3.8736450672,40.4971656799],"type":"Point"}
}