{
  "type": "Feature",
  "properties": {
    "addr:full":"Vicente Alexandre, 27 Jinamar Las Palmas 35220",
    "addr:housenumber":"27",
    "addr:postcode":"35220",
    "addr:street":"Vicente Alexandre;Palmas",
    "iso:country":"ES",
    "sg:address":"Vicente Alexandre, 27",
    "sg:city":"Jinamar",
    "sg:orig_category":"Congelados: Productos Alimentarios (fabricaci\u00d3n, Al Por Mayor)",
    "sg:phone":"+34 928 71 13 52",
    "sg:postcode":"35220",
    "sg:province":"Las Palmas",
    "wof:name":"Atlanta Gran Canaria Ultracongelados S.l.",
    "wof:placetype":"venue"
},
  "geometry": {"coordinates":[-15.4175167084,28.0304584503],"type":"Point"}
}