{
  "type": "Feature",
  "properties": {
    "addr:full":"Calle de Juan Pantoja, 12 Madrid Madrid 28039",
    "addr:housenumber":"12",
    "addr:postcode":"madrid;28039",
    "addr:street":"Calle De Juan Pantoja",
    "iso:country":"ES",
    "sg:address":"Calle de Juan Pantoja, 12",
    "sg:city":"Madrid",
    "sg:orig_category":"Bancos",
    "sg:phone":"+34 915 53 00 83",
    "sg:postcode":"28039",
    "sg:province":"Madrid",
    "wof:name":"Remesas Latinoamericanas S.l.",
    "wof:placetype":"venue"
},
  "geometry": {"coordinates":[-3.7044329643,40.4501838684],"type":"Point"}
}