{
  "type": "Feature",
  "properties": {
    "addr:full":"Pol Ind Pilar De La Dehesa, Km. 0002,5 Jaen Ja\u00e9n 23006",
    "addr:postcode":"23006",
    "addr:street":"Dehesa Km. 0002,5 Jaen Jae\u0301N",
    "iso:country":"ES",
    "sg:address":"Pol Ind Pilar De La Dehesa, Km. 0002,5",
    "sg:city":"Jaen",
    "sg:orig_category":"Material Y Herramientas Agr\u00cdcolas",
    "sg:phone":"+34 953 22 67 49",
    "sg:postcode":"23006",
    "sg:province":"Ja\u00e9n",
    "wof:name":"Gomas Moldeadas Andaluzas",
    "wof:placetype":"venue"
},
  "geometry": {"coordinates":[-3.8146526814,37.8638801575],"type":"Point"}
}