{
  "type": "Feature",
  "properties": {
    "iso:country":"ES",
    "sg:address":"Ctra Sant Cugat, S/n",
    "sg:city":"Cerdanyola Valles",
    "sg:orig_category":"Inmobiliaria (agencias)",
    "sg:phone":"+34 935 86 45 64",
    "sg:postcode":"08290",
    "sg:province":"Barcelona",
    "wof:name":"Meran S.l.",
    "wof:placetype":"venue"
},
  "geometry": {"coordinates":[2.122934103,41.4858055115],"type":"Point"}
}