{
  "type": "Feature",
  "properties": {
    "addr:full":"Av Mas De L'oli, 144 P. I. La Cova Valencia 46940",
    "addr:housenumber":"144",
    "addr:postcode":"46940",
    "addr:street":"Av Mas De L'Oli;P. I. La Cova",
    "iso:country":"ES",
    "sg:address":"Av Mas De L'oli, 144",
    "sg:city":"P. I. La Cova",
    "sg:orig_category":"Insecticidas, Fumigaci\u00d3n",
    "sg:phone":"+34 961 53 61 00",
    "sg:postcode":"46940",
    "sg:province":"Valencia",
    "sg:website":"www.gmbinternacional.com",
    "wof:name":"G.m.b. Internacional S.a.",
    "wof:placetype":"venue"
},
  "geometry": {"coordinates":[-0.4962492883,39.5031318665],"type":"Point"}
}