{
  "type": "Feature",
  "properties": {
    "iso:country":"ES",
    "sg:address":"Calle de Calvo Sotelo, 8",
    "sg:city":"Llanos De Aridane",
    "sg:orig_category":"Ropa Para Se\u00d1oras (al Por Menor)",
    "sg:phone":"+34 922 46 15 90",
    "sg:postcode":"38760",
    "sg:province":"Santa Cruz De Tenerife",
    "wof:name":"Lorenzo Vi\u00f1as Miguel Angel",
    "wof:placetype":"venue"
},
  "geometry": {"coordinates":[-17.9117965698,28.6589012146],"type":"Point"}
}