{
  "type": "Feature",
  "properties": {
    "iso:country":"ES",
    "sg:address":"Avda Juana Jugan, Km. 0001,0",
    "sg:city":"Paz",
    "sg:orig_category":"Bebidas",
    "sg:phone":"+34 968 23 31 67",
    "sg:postcode":"30006",
    "sg:province":"Murcia",
    "wof:name":"Abellan Egea Conrado",
    "wof:placetype":"venue"
},
  "geometry": {"coordinates":[-1.129887,37.983475],"type":"Point"}
}