{
  "type": "Feature",
  "properties": {
    "addr:full":"Av Jorda, 20 Barcelona Barcelona 08035",
    "addr:housenumber":"20",
    "addr:postcode":"08035",
    "addr:street":"Av Jorda",
    "iso:country":"ES",
    "sg:address":"Av Jorda, 20",
    "sg:city":"Barcelona",
    "sg:orig_category":"Agentes, Concesionarios Y Sucursales De Veh\u00cdculos",
    "sg:phone":"+34 932 54 13 70",
    "sg:postcode":"08035",
    "sg:province":"Barcelona",
    "wof:name":"Talleres Aranda S.a.",
    "wof:placetype":"venue"
},
  "geometry": {"coordinates":[2.1381709576,41.4268531799],"type":"Point"}
}