{
  "type": "Feature",
  "properties": {
    "addr:full":"Carretera Sevilla-chipiona, Km. 0008,0 Cabezas S. Juan Sevilla 41730",
    "addr:postcode":"41730",
    "addr:street":"Carretera Sevilla-Chipiona Km. 0008,0 Cabezas S. Juan Sevilla",
    "iso:country":"ES",
    "sg:address":"Carretera Sevilla-chipiona, Km. 0008,0",
    "sg:city":"Cabezas S. Juan",
    "sg:orig_category":"Textil",
    "sg:phone":"+34 955 87 11 23",
    "sg:postcode":"41730",
    "sg:province":"Sevilla",
    "wof:name":"Surcotton S.a.",
    "wof:placetype":"venue"
},
  "geometry": {"coordinates":[-5.9365491867,36.9817962646],"type":"Point"}
}