{
  "type": "Feature",
  "properties": {
    "addr:full":"Calle de Zocotin, 7 Jaca Huesca 22700",
    "addr:housenumber":"7",
    "addr:postcode":"22700",
    "addr:street":"Calle De Zocotin",
    "iso:country":"ES",
    "sg:address":"Calle de Zocotin, 7",
    "sg:city":"Jaca",
    "sg:orig_category":"Muebles, Minoristas",
    "sg:phone":"+34 974 36 17 91",
    "sg:postcode":"22700",
    "sg:province":"Huesca",
    "wof:name":"Climente Lanuza Valeriano",
    "wof:placetype":"venue"
},
  "geometry": {"coordinates":[-0.5490890145,42.5695838928],"type":"Point"}
}