{
  "type": "Feature",
  "properties": {
    "iso:country":"ES",
    "sg:address":"Ctra. Sollana, 7",
    "sg:city":"Almussafes",
    "sg:orig_category":"Arboricultura Y Producci\u00d3n De Frutas",
    "sg:phone":"+34 961 78 16 42",
    "sg:postcode":"46440",
    "sg:province":"Valencia",
    "wof:name":"Duart Blay J.j. S.l.",
    "wof:placetype":"venue"
},
  "geometry": {"coordinates":[-0.4122039974,39.2929763794],"type":"Point"}
}