{
  "type": "Feature",
  "properties": {
    "addr:full":"Pl. Iglesia, S/n S. Josep Talaia Islas Baleares 07830",
    "addr:housenumber":"s / n",
    "addr:postcode":"07830",
    "addr:street":"Pl. Iglesia",
    "iso:country":"ES",
    "sg:address":"Pl. Iglesia, S/n",
    "sg:city":"S. Josep Talaia",
    "sg:orig_category":"Art\u00cdculos De Regalo (al Por Menor)",
    "sg:phone":"+34 971 80 03 11",
    "sg:postcode":"07830",
    "sg:province":"Islas Baleares",
    "wof:name":"Pou C.b.",
    "wof:placetype":"venue"
},
  "geometry": {"coordinates":[1.2473909855,38.9164390564],"type":"Point"}
}