{
  "type": "Feature",
  "properties": {
    "iso:country":"ES",
    "sg:address":"Calle de Mesones, 28",
    "sg:city":"Cieza",
    "sg:orig_category":"Telas Y Sedas (al Por Menor)",
    "sg:phone":"+34 968 76 06 57",
    "sg:postcode":"30530",
    "sg:province":"Murcia",
    "wof:name":"Tejidos El Recobero S.a.",
    "wof:placetype":"venue"
},
  "geometry": {"coordinates":[-1.424276948,38.2381858826],"type":"Point"}
}