{
  "type": "Feature",
  "properties": {
    "iso:country":"ES",
    "sg:address":"Calle de Lepanto, 12",
    "sg:city":"Denia",
    "sg:orig_category":"Mec\u00c1nico Del Autom\u00d3vil",
    "sg:phone":"+34 965 78 48 05",
    "sg:postcode":"03700",
    "sg:province":"Alicante",
    "wof:name":"Dopico Barroso Eligio",
    "wof:placetype":"venue"
},
  "geometry": {"coordinates":[0.1072150022,38.8358802795],"type":"Point"}
}