{
  "type": "Feature",
  "properties": {
    "addr:full":"C/ Doctor Josep Maria Vilaseca, 48 Calonge Girona 17251",
    "addr:housenumber":"48",
    "addr:postcode":"17251",
    "addr:street":"C / Doctor Josep Maria Vilaseca",
    "iso:country":"ES",
    "sg:address":"C/ Doctor Josep Maria Vilaseca, 48",
    "sg:city":"Calonge",
    "sg:orig_category":"Cerrajer\u00cda, Ferrallista",
    "sg:phone":"+34 972 65 00 18",
    "sg:postcode":"17251",
    "sg:province":"Girona",
    "wof:name":"Pares Darnaculleta Joan",
    "wof:placetype":"venue"
},
  "geometry": {"coordinates":[3.0761609077,41.8590698242],"type":"Point"}
}