{
  "type": "Feature",
  "properties": {
    "addr:full":"Bocado, 9 C. Romeral-juan Grande Las Palmas 35107",
    "addr:housenumber":"9",
    "addr:postcode":"35107",
    "addr:street":"C. Romeral-Juan Grande Las",
    "iso:country":"ES",
    "sg:address":"Bocado, 9",
    "sg:city":"C. Romeral-juan Grande",
    "sg:orig_category":"Molduras, Junquillos, Listones Y Molduras Perforadas",
    "sg:phone":"+34 928 72 81 41",
    "sg:postcode":"35107",
    "sg:province":"Las Palmas",
    "wof:name":"Santana Rodriguez Vicente",
    "wof:placetype":"venue"
},
  "geometry": {"coordinates":[-15.471912384,27.8081912994],"type":"Point"}
}