{
  "type": "Feature",
  "properties": {
    "addr:full":"Carrer de Andreu Llambrich, 25 Ametlla Mar Tarragona 43860",
    "addr:housenumber":"25",
    "addr:postcode":"43860",
    "addr:street":"Carrer De Andreu Llambrich",
    "iso:country":"ES",
    "sg:address":"Carrer de Andreu Llambrich, 25",
    "sg:city":"Ametlla Mar",
    "sg:orig_category":"Agencias De Viajes",
    "sg:phone":"+34 977 49 39 36",
    "sg:postcode":"43860",
    "sg:province":"Tarragona",
    "wof:name":"Viatges Calyper S.l.",
    "wof:placetype":"venue"
},
  "geometry": {"coordinates":[0.8016639948,40.8844146729],"type":"Point"}
}