{
  "type": "Feature",
  "properties": {
    "addr:full":"Carrer de Naranjos, 73 Hospitalet Llobregat Barcelona 08906",
    "addr:housenumber":"73",
    "addr:postcode":"08906",
    "addr:street":"Carrer De Naranjos",
    "iso:country":"ES",
    "sg:address":"Carrer de Naranjos, 73",
    "sg:city":"Hospitalet Llobregat",
    "sg:orig_category":"Molduras, Junquillos, Listones Y Molduras Perforadas",
    "sg:phone":"+34 934 37 60 35",
    "sg:postcode":"08906",
    "sg:province":"Barcelona",
    "wof:name":"Carrasco Velarde Victoriano",
    "wof:placetype":"venue"
},
  "geometry": {"coordinates":[2.0998859406,41.3690414429],"type":"Point"}
}