{
  "type": "Feature",
  "properties": {
    "addr:full":"Barr Pedrera La, 2 Cangas Onis Asturias 33550",
    "addr:postcode":"33550",
    "addr:street":"Asturias",
    "iso:country":"ES",
    "sg:address":"Barr Pedrera La, 2",
    "sg:city":"Cangas Onis",
    "sg:orig_category":"Asesor\u00cda De Formaci\u00d3n Y Gesti\u00d3n De Personal",
    "sg:phone":"+34 985 84 95 62",
    "sg:postcode":"33550",
    "sg:province":"Asturias",
    "wof:name":"Martinez Del Valle Asesoria S.l",
    "wof:placetype":"venue"
},
  "geometry": {"coordinates":[-5.1302790642,43.3507957458],"type":"Point"}
}