{
  "type": "Feature",
  "properties": {
    "iso:country":"ES",
    "sg:address":"Garraf (pol. Ind. La Borda), S/n",
    "sg:city":"Caldes Montbui",
    "sg:orig_category":"Cooperativas Agr\u00cdcolas",
    "sg:phone":"+34 938 65 55 33",
    "sg:postcode":"08140",
    "sg:province":"Barcelona",
    "wof:name":"Agropecuaria Comarcal S.c.c.l.",
    "wof:placetype":"venue"
},
  "geometry": {"coordinates":[2.169919,41.387917],"type":"Point"}
}