{
  "type": "Feature",
  "properties": {
    "addr:full":"Calle de Imagen, 8 Sevilla Sevilla 41003",
    "addr:housenumber":"8",
    "addr:postcode":"41003",
    "addr:street":"Calle De Imagen",
    "iso:country":"ES",
    "sg:address":"Calle de Imagen, 8",
    "sg:city":"Sevilla",
    "sg:orig_category":"Caf\u00c9s, Bares, Cervecer\u00cdas",
    "sg:phone":"+34 954 21 03 53",
    "sg:postcode":"41003",
    "sg:province":"Sevilla",
    "wof:name":"Escalona Recuerda Andres",
    "wof:placetype":"venue"
},
  "geometry": {"coordinates":[-5.9900012016,37.3926086426],"type":"Point"}
}