{
  "type": "Feature",
  "properties": {
    "addr:full":"Calle de Acacia, 2 Arges Toledo 45122",
    "addr:housenumber":"2",
    "addr:postcode":"45122",
    "addr:street":"Calle De Acacia",
    "iso:country":"ES",
    "sg:address":"Calle de Acacia, 2",
    "sg:city":"Arges",
    "sg:orig_category":"Fabricaci\u00d3n, Importaci\u00d3n, Venta De Material De Telefon\u00cda, Peritelefon\u00cda",
    "sg:phone":"+34 925 37 71 30",
    "sg:postcode":"45122",
    "sg:province":"Toledo",
    "wof:name":"Villagrasa Nieto Ester",
    "wof:placetype":"venue"
},
  "geometry": {"coordinates":[-4.0651240349,39.8110084534],"type":"Point"}
}