{
  "type": "Feature",
  "properties": {
    "addr:full":"Calle de San Bruno, 34 Valencia Valencia 46009",
    "addr:housenumber":"34",
    "addr:postcode":"46009",
    "addr:street":"Calle De San Bruno",
    "iso:country":"ES",
    "sg:address":"Calle de San Bruno, 34",
    "sg:city":"Valencia",
    "sg:classifiers":[
        {
            "category":"Casinos & Gambling",
            "type":"Entertainment"
        }
    ],
    "sg:phone":"+34 963 65 57 37",
    "sg:postcode":"46009",
    "sg:province":"Valencia",
    "sg:tags":[
        "locale",
        "de",
        "juego"
    ],
    "wof:name":"Anabel Juegos S.a.",
    "wof:placetype":"venue"
},
  "geometry": {"coordinates":[-0.3719475865,39.4901237488],"type":"Point"}
}