{
  "type": "Feature",
  "properties": {
    "addr:full":"Ctra Sierra (de La), S/n Iznalloz Granada 18550",
    "addr:housenumber":"/ n",
    "addr:postcode":"18550",
    "addr:street":"Ctra Sierra De La S",
    "iso:country":"ES",
    "sg:address":"Ctra Sierra (de La), S/n",
    "sg:city":"Iznalloz",
    "sg:orig_category":"Perfumer\u00cda Y Cosm\u00c9tica (fabricaci\u00d3n, Al Por Mayor)",
    "sg:phone":"+34 958 38 48 25",
    "sg:postcode":"18550",
    "sg:province":"Granada",
    "wof:name":"Martin Fernandez Manuel",
    "wof:placetype":"venue"
},
  "geometry": {"coordinates":[-3.5180439949,37.393196106],"type":"Point"}
}