{
  "type": "Feature",
  "properties": {
    "iso:country":"ES",
    "sg:address":"Carrer de Fedanci, 8",
    "sg:city":"S. Cugat Valles",
    "sg:classifiers":[
        {
            "category":"Manufacturing",
            "subcategory":"Building Materials",
            "type":"Manufacturing & Wholesale Goods"
        }
    ],
    "sg:phone":"+34 935 89 70 45",
    "sg:postcode":"08174",
    "sg:province":"Barcelona",
    "sg:tags":[
        "cemento",
        "y",
        "de",
        "fabricaci\u00d3n",
        "cal"
    ],
    "wof:name":"Bulk Mines And Minerals S. L.",
    "wof:placetype":"venue"
},
  "geometry": {"coordinates":[2.0777750015,41.4929351807],"type":"Point"}
}