{
  "type": "Feature",
  "properties": {
    "addr:full":"Plaz Espa\u00d1a, 10 Torredelcampo Ja\u00e9n 23640",
    "addr:housenumber":"10",
    "addr:postcode":"23640",
    "addr:street":"Plaz Espan\u0303A;Jae\u0301N",
    "iso:country":"ES",
    "sg:address":"Plaz Espa\u00d1a, 10",
    "sg:city":"Torredelcampo",
    "sg:orig_category":"Muebles, Minoristas",
    "sg:phone":"+34 953 56 86 83",
    "sg:postcode":"23640",
    "sg:province":"Ja\u00e9n",
    "wof:name":"Moral Fernandez Manuel Jose",
    "wof:placetype":"venue"
},
  "geometry": {"coordinates":[-3.9000020027,37.7705688477],"type":"Point"}
}