{
  "type": "Feature",
  "properties": {
    "addr:full":"Plaz San Sebastian, 1 Lumbrales Salamanca 37240",
    "addr:housenumber":"1",
    "addr:postcode":"37240",
    "addr:street":"Plaz San Sebastian",
    "iso:country":"ES",
    "sg:address":"Plaz San Sebastian, 1",
    "sg:city":"Lumbrales",
    "sg:orig_category":"Asesor\u00cda Fiscal Y Jur\u00cddica",
    "sg:phone":"+34 923 52 50 06",
    "sg:postcode":"37240",
    "sg:province":"Salamanca",
    "wof:name":"Lafisconta S.l.",
    "wof:placetype":"venue"
},
  "geometry": {"coordinates":[-6.7190737724,40.9346542358],"type":"Point"}
}