{
  "type": "Feature",
  "properties": {
    "addr:full":"Calle de Jose Franchy Roca, 5 Palmas De Gran Canaria Las Palmas 35007",
    "addr:housenumber":"5",
    "addr:postcode":"35007",
    "addr:street":"Calle De Jose Franchy Roca",
    "iso:country":"ES",
    "sg:address":"Calle de Jose Franchy Roca, 5",
    "sg:city":"Palmas De Gran Canaria",
    "sg:orig_category":"Cajas De Ahorro",
    "sg:phone":"+34 928 47 27 85",
    "sg:postcode":"35007",
    "sg:province":"Las Palmas",
    "wof:name":"Caja De Ahorros Y Monte De Piedad De Zaragoza Aragon Y Rioja",
    "wof:placetype":"venue"
},
  "geometry": {"coordinates":[-15.431186676,28.1390190125],"type":"Point"}
}