{
  "type": "Feature",
  "properties": {
    "iso:country":"ES",
    "sg:address":"Carrer de Muntaner, 270",
    "sg:city":"Barcelona",
    "sg:orig_category":"Ense\u00d1anza: Idiomas",
    "sg:phone":"+34 934 14 05 48",
    "sg:postcode":"08021",
    "sg:province":"Barcelona",
    "sg:website":"www.sheffield-centre.com",
    "wof:name":"Sheffield Centre S.a.",
    "wof:placetype":"venue"
},
  "geometry": {"coordinates":[2.1475379467,41.3958053589],"type":"Point"}
}