{
  "type": "Feature",
  "properties": {
    "addr:full":"Grup Font Dels Capellans, 15 Manresa Barcelona 08243",
    "addr:housenumber":"15",
    "addr:postcode":"08243",
    "addr:street":"Capellans",
    "iso:country":"ES",
    "sg:address":"Grup Font Dels Capellans, 15",
    "sg:city":"Manresa",
    "sg:orig_category":"Papeler\u00cdas, Librer\u00cdas",
    "sg:phone":"+34 938 36 23 03",
    "sg:postcode":"08243",
    "sg:province":"Barcelona",
    "wof:name":"Garcia Chirveches Lourdes",
    "wof:placetype":"venue"
},
  "geometry": {"coordinates":[1.8379420042,41.7305412292],"type":"Point"}
}