{
  "type": "Feature",
  "properties": {
    "iso:country":"ES",
    "sg:address":"Calle de Hierro (el), 48",
    "sg:city":"Puerto Rico",
    "sg:orig_category":"Bazares, Art\u00cdculos De Limpieza Y De Cocina (al Por Menor)",
    "sg:phone":"+34 928 56 19 19",
    "sg:postcode":"35130",
    "sg:province":"Las Palmas",
    "wof:name":"Singh Modi Ranjit",
    "wof:placetype":"venue"
},
  "geometry": {"coordinates":[-15.7058639526,27.7932033539],"type":"Point"}
}