{
  "type": "Feature",
  "properties": {
    "addr:full":"Avda Antonio Machado, 34 Arroyo De La Miel-benalmadena Costa M\u00e1laga 29630",
    "addr:housenumber":"34",
    "addr:postcode":"29630",
    "addr:street":"Avda Antonio Machado;Ma\u0301Laga",
    "iso:country":"ES",
    "sg:address":"Avda Antonio Machado, 34",
    "sg:city":"Arroyo De La Miel-benalmadena Costa",
    "sg:orig_category":"Ropa Para Se\u00d1oras Y Caballeros (al Por Menor)",
    "sg:phone":"+34 952 57 84 42",
    "sg:postcode":"29630",
    "sg:province":"M\u00e1laga",
    "wof:name":"Shivnani  Dilip",
    "wof:placetype":"venue"
},
  "geometry": {"coordinates":[-4.5191020966,36.5972938538],"type":"Point"}
}