{
  "type": "Feature",
  "properties": {
    "iso:country":"ES",
    "sg:address":"Ferro, S/n",
    "sg:city":"Pol. Ind. Can Pelegri",
    "sg:orig_category":"Bares, Piano",
    "sg:phone":"+34 936 82 09 87",
    "sg:postcode":"08755",
    "sg:province":"Barcelona",
    "wof:name":"Disnerga S.a.",
    "wof:placetype":"venue"
},
  "geometry": {"coordinates":[1.9750679731,41.4769172668],"type":"Point"}
}