{
  "type": "Feature",
  "properties": {
    "addr:full":"Carr Del Music Martinez Valls, 54 Ontinyent Valencia 46870",
    "addr:housenumber":"54",
    "addr:postcode":"46870",
    "addr:street":"Carr Del;Valls",
    "iso:country":"ES",
    "sg:address":"Carr Del Music Martinez Valls, 54",
    "sg:city":"Ontinyent",
    "sg:orig_category":"Muebles Y Accesorios Para Cocinas Y Cuartos De Ba\u00d1o (al Por Menor)",
    "sg:phone":"+34 962 38 53 93",
    "sg:postcode":"46870",
    "sg:province":"Valencia",
    "wof:name":"Trading Hogar S.l.",
    "wof:placetype":"venue"
},
  "geometry": {"coordinates":[-0.5996860266,38.8241157532],"type":"Point"}
}