{
  "type": "Feature",
  "properties": {
    "iso:country":"ES",
    "sg:address":"Ctra Andalucia (de), 6",
    "sg:city":"Aranjuez",
    "sg:orig_category":"Iglesia Cat\u00d3lica",
    "sg:phone":"+34 918 91 66 93",
    "sg:postcode":"28300",
    "sg:province":"Madrid",
    "wof:name":"Parroquia De San Antonio",
    "wof:placetype":"venue"
},
  "geometry": {"coordinates":[-3.6053009033,40.0332984924],"type":"Point"}
}