{
  "type": "Feature",
  "properties": {
    "iso:country":"ES",
    "sg:address":"Barr Telleria, 7",
    "sg:city":"Telleria",
    "sg:orig_category":"Restaurantes",
    "sg:phone":"+34 944 91 20 30",
    "sg:postcode":"48940",
    "sg:province":"Vizcaya",
    "wof:name":"Trattoria La Caseta S.l.",
    "wof:placetype":"venue"
},
  "geometry": {"coordinates":[-2.9860789776,43.3275489807],"type":"Point"}
}