{
  "type": "Feature",
  "properties": {
    "iso:country":"ES",
    "sg:address":"Calle de Virgen De Regla, S/n",
    "sg:city":"Dos Hermanas",
    "sg:orig_category":"Tapiceros Y Tapiceros",
    "sg:phone":"+34 955 67 41 11",
    "sg:postcode":"41700",
    "sg:province":"Sevilla",
    "wof:name":"Tapiza 2 Hermanas S.l.",
    "wof:placetype":"venue"
},
  "geometry": {"coordinates":[-5.931579113,37.2767562866],"type":"Point"}
}