{
  "type": "Feature",
  "properties": {
    "iso:country":"ES",
    "sg:address":"Carr Torroella, 89",
    "sg:city":"Palafrugell",
    "sg:orig_category":"Tapones Y Art\u00cdculos De Corcho",
    "sg:phone":"+34 972 30 03 61",
    "sg:postcode":"17200",
    "sg:province":"Girona",
    "wof:name":"Juan Rutllant S.a.",
    "wof:placetype":"venue"
},
  "geometry": {"coordinates":[3.1559760571,41.9205703735],"type":"Point"}
}