{
  "type": "Feature",
  "properties": {
    "addr:full":"Av Pi I Margall, 125 Caldes Montbui Barcelona 08140",
    "addr:housenumber":"125",
    "addr:postcode":"08140",
    "addr:street":"Av Pi I Margall;Montbui Barcelona",
    "iso:country":"ES",
    "sg:address":"Av Pi I Margall, 125",
    "sg:city":"Caldes Montbui",
    "sg:orig_category":"Charcuter\u00cdas (al Por Mayor)",
    "sg:phone":"+34 938 65 03 54",
    "sg:postcode":"08140",
    "sg:province":"Barcelona",
    "wof:name":"Embutidos Pedragosa S.a.",
    "wof:placetype":"venue"
},
  "geometry": {"coordinates":[2.1673600674,41.6280899048],"type":"Point"}
}