{
  "type": "Feature",
  "properties": {
    "iso:country":"ES",
    "sg:address":"Calle de Obispo Encina, 10",
    "sg:city":"Palmas De Gran Canaria",
    "sg:orig_category":"Flores Y Plantas Naturales (al Por Mayor)",
    "sg:phone":"+34 928 23 21 36",
    "sg:postcode":"35004",
    "sg:province":"Las Palmas",
    "wof:name":"Lopez Vega Antonio",
    "wof:placetype":"venue"
},
  "geometry": {"coordinates":[-15.4245634079,28.1150894165],"type":"Point"}
}