{
  "type": "Feature",
  "properties": {
    "iso:country":"ES",
    "sg:address":"Cmno Huerta De Abajo, S/n",
    "sg:city":"Huerta De Abajo",
    "sg:orig_category":"Aparatos E Instalaci\u00d3n De Regad\u00cdos",
    "sg:phone":"+34 968 62 60 51",
    "sg:postcode":"30565",
    "sg:province":"Murcia",
    "wof:name":"Comunidad Regantes Del Pozo San Jose",
    "wof:placetype":"venue"
},
  "geometry": {"coordinates":[-1.2395490408,38.0263290405],"type":"Point"}
}