{
  "type": "Feature",
  "properties": {
    "iso:country":"ES",
    "sg:address":"Poli Escopar, S/n",
    "sg:city":"Peralta",
    "sg:orig_category":"Pintura Industrial (trabajos De)",
    "sg:phone":"+34 948 75 06 40",
    "sg:postcode":"31350",
    "sg:province":"Navarra",
    "wof:name":"Colores Industriales De Navarra S.l.",
    "wof:placetype":"venue"
},
  "geometry": {"coordinates":[-1.8131040335,42.33385849],"type":"Point"}
}