{
  "type": "Feature",
  "properties": {
    "iso:country":"ES",
    "sg:address":"Rua San Antoni\u00d1o, 1",
    "sg:city":"Pontevedra",
    "sg:classifiers":[
        {
            "category":"Personal",
            "subcategory":"Barber",
            "type":"Services"
        }
    ],
    "sg:phone":"+34 986 84 82 19",
    "sg:postcode":"36002",
    "sg:province":"Pontevedra",
    "sg:tags":[
        "caballeros",
        "de",
        "peluqueros"
    ],
    "wof:name":"Peluqueria Cabelos Pontevedra C.b.",
    "wof:placetype":"venue"
},
  "geometry": {"coordinates":[-8.6468172073,42.4338340759],"type":"Point"}
}