{
  "type": "Feature",
  "properties": {
    "iso:country":"ES",
    "sg:address":"Calle de Antonio Pascual, 4",
    "sg:city":"Aljorra",
    "sg:orig_category":"Empresas De Carpinter\u00cda De Madera",
    "sg:phone":"+34 968 16 41 57",
    "sg:postcode":"30390",
    "sg:province":"Murcia",
    "wof:name":"Martinez Solano Manuel",
    "wof:placetype":"venue"
},
  "geometry": {"coordinates":[-1.0671322346,37.6868743896],"type":"Point"}
}