{
  "type": "Feature",
  "properties": {
    "addr:full":"Pg Terrall, 7 Borges Blanques Lleida 25400",
    "addr:housenumber":"7",
    "addr:postcode":"25400",
    "addr:street":"Pg Terrall",
    "iso:country":"ES",
    "sg:address":"Pg Terrall, 7",
    "sg:city":"Borges Blanques",
    "sg:orig_category":"Promotores Constructores",
    "sg:phone":"+34 973 14 20 07",
    "sg:postcode":"25400",
    "sg:province":"Lleida",
    "wof:name":"Peiro Cortada Jacinto",
    "wof:placetype":"venue"
},
  "geometry": {"coordinates":[0.8711360097,41.5198669434],"type":"Point"}
}