{
  "type": "Feature",
  "properties": {
    "addr:full":"Calle de Palanca (de La), 8 Cordoba C\u00f3rdoba 14012",
    "addr:housenumber":"8",
    "addr:postcode":"14012",
    "addr:street":"Calle De Palanca De La;Co\u0301Rdoba",
    "iso:country":"ES",
    "sg:address":"Calle de Palanca (de La), 8",
    "sg:city":"Cordoba",
    "sg:orig_category":"Confecci\u00d3n De Uniformes",
    "sg:phone":"+34 957 27 23 60",
    "sg:postcode":"14012",
    "sg:province":"C\u00f3rdoba",
    "wof:name":"Cabrera Mu\u00f1oz Jose",
    "wof:placetype":"venue"
},
  "geometry": {"coordinates":[-4.7817950249,37.9099884033],"type":"Point"}
}