{
  "type": "Feature",
  "properties": {
    "iso:country":"ES",
    "sg:address":"Carr Diputat Josep Ribas, 25",
    "sg:city":"Eivissa",
    "sg:orig_category":"Plomeros",
    "sg:phone":"+34 971 19 23 97",
    "sg:postcode":"07800",
    "sg:province":"Islas Baleares",
    "wof:name":"Torres Y Maza S.l.l.",
    "wof:placetype":"venue"
},
  "geometry": {"coordinates":[1.433349967,38.9120788574],"type":"Point"}
}