{
  "type": "Feature",
  "properties": {
    "iso:country":"ES",
    "sg:address":"Calle de Pedro Tezano, 15",
    "sg:city":"Madrid",
    "sg:orig_category":"Carnicer\u00cdas, Carnicer\u00cdas",
    "sg:phone":"+34 913 11 01 41",
    "sg:postcode":"28039",
    "sg:province":"Madrid",
    "wof:name":"Eudaga S.l.",
    "wof:placetype":"venue"
},
  "geometry": {"coordinates":[-3.7078619003,40.4595489502],"type":"Point"}
}