{
  "type": "Feature",
  "properties": {
    "iso:country":"ES",
    "sg:address":"B. San Juan, 59",
    "sg:city":"Villanueva Pe\u00f1a",
    "sg:orig_category":"Controles De Edificaci\u00d3n (construcci\u00d3n, Seguridad)",
    "sg:phone":"+34 942 70 82 85",
    "sg:postcode":"39509",
    "sg:province":"Cantabria",
    "wof:name":"Promociones Ernesto Quintana S L",
    "wof:placetype":"venue"
},
  "geometry": {"coordinates":[-4.2100739479,43.2973518372],"type":"Point"}
}