{
  "type": "Feature",
  "properties": {
    "addr:full":"Carrer de Primer De Maig, 20 Montmelo Barcelona 08160",
    "addr:housenumber":"20",
    "addr:postcode":"08160",
    "addr:street":"Carrer De Primer De Maig",
    "iso:country":"ES",
    "sg:address":"Carrer de Primer De Maig, 20",
    "sg:city":"Montmelo",
    "sg:orig_category":"Ferreter\u00cda (diversos)",
    "sg:phone":"+34 935 72 30 99",
    "sg:postcode":"08160",
    "sg:province":"Barcelona",
    "wof:name":"Gonell Roldan Sebastian",
    "wof:placetype":"venue"
},
  "geometry": {"coordinates":[2.2454938889,41.5492210388],"type":"Point"}
}