{
  "type": "Feature",
  "properties": {
    "iso:country":"ES",
    "sg:address":"Pase Dr Fernandez Iparraguirre, 1",
    "sg:city":"Guadalajara",
    "sg:orig_category":"Asociaciones, Organismos Culturales Y Socioeducativos",
    "sg:phone":"+34 949 23 01 16",
    "sg:postcode":"19001",
    "sg:province":"Guadalajara",
    "wof:name":"A.p.e.r.g",
    "wof:placetype":"venue"
},
  "geometry": {"coordinates":[-3.1651852131,40.6300430298],"type":"Point"}
}