{
  "type": "Feature",
  "properties": {
    "addr:full":"Calle de Francisco Salinas, 31 Burgos Burgos 09003",
    "addr:housenumber":"31",
    "addr:postcode":"09003",
    "addr:street":"Calle De Francisco Salinas",
    "iso:country":"ES",
    "sg:address":"Calle de Francisco Salinas, 31",
    "sg:city":"Burgos",
    "sg:orig_category":"Droguer\u00cdas (al Por Menor)",
    "sg:phone":"+34 947 20 65 79",
    "sg:postcode":"09003",
    "sg:province":"Burgos",
    "wof:name":"Porres Plaza Fernando",
    "wof:placetype":"venue"
},
  "geometry": {"coordinates":[-3.712485075,42.3437728882],"type":"Point"}
}