{
  "type": "Feature",
  "properties": {
    "iso:country":"ES",
    "sg:address":"Calle de 18 De Julio, 26",
    "sg:city":"Astillero",
    "sg:orig_category":"Ropa Para Se\u00d1oras (al Por Menor)",
    "sg:phone":"+34 942 55 86 54",
    "sg:postcode":"39610",
    "sg:province":"Cantabria",
    "wof:name":"Rey Noguera Rosana Tatiana",
    "wof:placetype":"venue"
},
  "geometry": {"coordinates":[-3.8314042091,43.3990859985],"type":"Point"}
}