{
  "type": "Feature",
  "properties": {
    "iso:country":"ES",
    "sg:address":"El Frontin, 3",
    "sg:city":"Labastida Bastida",
    "sg:orig_category":"Oficinas De Turismo, Asociaciones De Iniciativa",
    "sg:phone":"+34 945 33 10 60",
    "sg:postcode":"01330",
    "sg:province":"\u00c1lava",
    "sg:website":"www.thabuca.com",
    "wof:name":"Thabuca S.c.",
    "wof:placetype":"venue"
},
  "geometry": {"coordinates":[-2.8004090786,42.5922889709],"type":"Point"}
}