{
  "type": "Feature",
  "properties": {
    "addr:full":"Ctra Loriguilla, S/n Cheste Valencia 46380",
    "addr:housenumber":"s / n",
    "addr:postcode":"46380",
    "addr:street":"Ctra Loriguilla",
    "iso:country":"ES",
    "sg:address":"Ctra Loriguilla, S/n",
    "sg:city":"Cheste",
    "sg:orig_category":"Material Hidr\u00c1ulico",
    "sg:phone":"+34 962 51 23 93",
    "sg:postcode":"46380",
    "sg:province":"Valencia",
    "wof:name":"Empresa General Valenciana Del Agua S.a.",
    "wof:placetype":"venue"
},
  "geometry": {"coordinates":[-0.6874480247,39.4945602417],"type":"Point"}
}