{
  "type": "Feature",
  "properties": {
    "iso:country":"ES",
    "sg:address":"Plaz Fernando V, 11",
    "sg:city":"Vera",
    "sg:orig_category":"Inmobiliaria (agencias)",
    "sg:phone":"+34 950 39 19 57",
    "sg:postcode":"04620",
    "sg:province":"Almer\u00eda",
    "sg:website":"www.inmocasa.com",
    "wof:name":"Ramirez Jimenez Maria Angustias",
    "wof:placetype":"venue"
},
  "geometry": {"coordinates":[-1.8724600077,37.2477874756],"type":"Point"}
}