{
  "type": "Feature",
  "properties": {
    "iso:country":"ES",
    "sg:address":"Avda Gines, 28",
    "sg:city":"Bollullos Mitacion",
    "sg:orig_category":"Administradores De Bienes Y Delegados De Comunidades De Propietarios",
    "sg:phone":"+34 955 77 65 51",
    "sg:postcode":"41110",
    "sg:province":"Sevilla",
    "wof:name":"Pendragon S.l.",
    "wof:placetype":"venue"
},
  "geometry": {"coordinates":[-6.1422591209,37.3558616638],"type":"Point"}
}