{
  "type": "Feature",
  "properties": {
    "iso:country":"ES",
    "sg:address":"Calle de Serrablo (de), 86",
    "sg:city":"Sabi\u00f1anigo",
    "sg:orig_category":"Art\u00cdculos De Regalo (al Por Menor)",
    "sg:phone":"+34 974 48 02 65",
    "sg:postcode":"22600",
    "sg:province":"Huesca",
    "wof:name":"Marcuello Lafontana Maria Del Carmen",
    "wof:placetype":"venue"
},
  "geometry": {"coordinates":[-0.3651430011,42.5182189941],"type":"Point"}
}