{
  "type": "Feature",
  "properties": {
    "iso:country":"ES",
    "sg:address":"Ramon Irizar Kalea, 3",
    "sg:city":"O\u00f1ati",
    "sg:orig_category":"Asociaciones, Organismos Culturales Y Socioeducativos",
    "sg:phone":"+34 943 78 16 85",
    "sg:postcode":"20560",
    "sg:province":"Guip\u00f9zcoa",
    "wof:name":"Sociedad Cultural Deportiva Makalena",
    "wof:placetype":"venue"
},
  "geometry": {"coordinates":[-2.4128010273,43.0326461792],"type":"Point"}
}