{
  "type": "Feature",
  "properties": {
    "iso:country":"ES",
    "sg:address":"La Vega(pedraces), S/n",
    "sg:city":"Aramil",
    "sg:orig_category":"Flores Y Plantas Naturales (al Por Mayor)",
    "sg:phone":"+34 985 97 14 59",
    "sg:postcode":"33518",
    "sg:province":"Asturias",
    "wof:name":"Simon Arnaus Sara",
    "wof:placetype":"venue"
},
  "geometry": {"coordinates":[-5.5597882271,43.4101409912],"type":"Point"}
}