{
  "type": "Feature",
  "properties": {
    "addr:full":"Carrer de Sallares I Pla, 17 Sabadell Barcelona 08202",
    "addr:housenumber":"17",
    "addr:postcode":"08202",
    "addr:street":"Carrer De Sallares I Pla",
    "iso:country":"ES",
    "sg:address":"Carrer de Sallares I Pla, 17",
    "sg:city":"Sabadell",
    "sg:orig_category":"Fabricaci\u00d3n De Telas Y Sedas",
    "sg:phone":"+34 937 26 03 95",
    "sg:postcode":"08202",
    "sg:province":"Barcelona",
    "wof:name":"Domaine Textile S.l.",
    "wof:placetype":"venue"
},
  "geometry": {"coordinates":[2.1124250889,41.5455055237],"type":"Point"}
}