{
  "type": "Feature",
  "properties": {
    "iso:country":"ES",
    "sg:address":"Plaz Simon Bolivar, 13",
    "sg:city":"Vitoria-gasteiz",
    "sg:orig_category":"Prot\u00c9sicos Dentales",
    "sg:phone":"+34 945 28 00 18",
    "sg:postcode":"01003",
    "sg:province":"\u00c1lava",
    "wof:name":"Saenz De Maturana Blanco Ivan Jose",
    "wof:placetype":"venue"
},
  "geometry": {"coordinates":[-2.6619110107,42.8487548828],"type":"Point"}
}