{
  "type": "Feature",
  "properties": {
    "addr:full":"Carrer de Escudellers, 45 Barcelona Barcelona 08002",
    "addr:housenumber":"45",
    "addr:postcode":"08002",
    "addr:street":"Carrer De Escudellers",
    "iso:country":"ES",
    "sg:address":"Carrer de Escudellers, 45",
    "sg:city":"Barcelona",
    "sg:orig_category":"Carnicer\u00cdas, Carnicer\u00cdas",
    "sg:phone":"+34 933 02 26 79",
    "sg:postcode":"08002",
    "sg:province":"Barcelona",
    "wof:name":"Guibas Bordas Joaquin",
    "wof:placetype":"venue"
},
  "geometry": {"coordinates":[2.1767361164,41.3800468445],"type":"Point"}
}