{
  "type": "Feature",
  "properties": {
    "addr:full":"Afueras, S/n Ejea Caballeros Zaragoza 50600",
    "addr:postcode":"50600",
    "addr:street":"Afueras S / N Ejea",
    "iso:country":"ES",
    "sg:address":"Afueras, S/n",
    "sg:city":"Ejea Caballeros",
    "sg:orig_category":"Ense\u00d1anza, Formaci\u00d3n Profesional: Aprendizaje",
    "sg:phone":"+34 976 66 14 56",
    "sg:postcode":"50600",
    "sg:province":"Zaragoza",
    "wof:name":"Federacion De Centros De Promocion Rural Escuelas Familiares Agra",
    "wof:placetype":"venue"
},
  "geometry": {"coordinates":[-1.1382750273,42.1269798279],"type":"Point"}
}