{
  "type": "Feature",
  "properties": {
    "iso:country":"ES",
    "sg:address":"Calle de Barriguelo, S/n",
    "sg:city":"Logro\u00f1o",
    "sg:orig_category":"Material Y Suministros Para Fotocopiadoras, Reprograf\u00cda",
    "sg:phone":"+34 941 24 41 34",
    "sg:postcode":"26006",
    "sg:province":"La Rioja",
    "wof:name":"Reproducciones Tecnicas S.a.",
    "wof:placetype":"venue"
},
  "geometry": {"coordinates":[-2.412627697,42.4717826843],"type":"Point"}
}