{
  "type": "Feature",
  "properties": {
    "addr:full":"Ptda Barranco Pallares, S/n Alborache Valencia 46369",
    "addr:housenumber":"s / n",
    "addr:postcode":"46369",
    "addr:street":"Ptda Barranco Pallares",
    "iso:country":"ES",
    "sg:address":"Ptda Barranco Pallares, S/n",
    "sg:city":"Alborache",
    "sg:orig_category":"Aguas (distribuci\u00d3n, Servicios)",
    "sg:phone":"+34 962 50 85 82",
    "sg:postcode":"46369",
    "sg:province":"Valencia",
    "wof:name":"Oms Sacede S.a.",
    "wof:placetype":"venue"
},
  "geometry": {"coordinates":[-0.7721949816,39.392906189],"type":"Point"}
}