{
  "type": "Feature",
  "properties": {
    "addr:full":"Calle de Virgen De La Antigua, 5 Hinojosa Del Duque C\u00f3rdoba 14270",
    "addr:housenumber":"5",
    "addr:postcode":"14270",
    "addr:street":"Calle De Virgen De La Antigua;Co\u0301Rdoba",
    "iso:country":"ES",
    "sg:address":"Calle de Virgen De La Antigua, 5",
    "sg:city":"Hinojosa Del Duque",
    "sg:orig_category":"Fotograf\u00cda Art\u00cdstica Y Retratos",
    "sg:phone":"+34 957 14 14 76",
    "sg:postcode":"14270",
    "sg:province":"C\u00f3rdoba",
    "wof:name":"Flores Fernandez Alfonso",
    "wof:placetype":"venue"
},
  "geometry": {"coordinates":[-5.1487221718,38.50025177],"type":"Point"}
}