{
  "type": "Feature",
  "properties": {
    "addr:full":"Av Sant Jaume, 87 Amposta Tarragona 43870",
    "addr:housenumber":"87",
    "addr:postcode":"43870",
    "addr:street":"Av Sant Jaume",
    "iso:country":"ES",
    "sg:address":"Av Sant Jaume, 87",
    "sg:city":"Amposta",
    "sg:orig_category":"Deportes Y Programas De Aventura",
    "sg:phone":"+34 977 70 67 30",
    "sg:postcode":"43870",
    "sg:province":"Tarragona",
    "wof:name":"Deltaventur S.l.",
    "wof:placetype":"venue"
},
  "geometry": {"coordinates":[0.5878400207,40.70911026],"type":"Point"}
}