{
  "type": "Feature",
  "properties": {
    "iso:country":"ES",
    "sg:address":"Calle de Marroquina, 70",
    "sg:city":"Madrid",
    "sg:orig_category":"Farmacias",
    "sg:phone":"+34 914 39 65 89",
    "sg:postcode":"28030",
    "sg:province":"Madrid",
    "wof:name":"Blanmco Lecroisey Alicia",
    "wof:placetype":"venue"
},
  "geometry": {"coordinates":[-3.6468949318,40.4095191956],"type":"Point"}
}