{
  "type": "Feature",
  "properties": {
    "addr:full":"Carrer de Roger De Lluria, 127 Barcelona Barcelona 08037",
    "addr:housenumber":"127",
    "addr:postcode":"08037",
    "addr:street":"Carrer De Roger De Lluria",
    "iso:country":"ES",
    "sg:address":"Carrer de Roger De Lluria, 127",
    "sg:city":"Barcelona",
    "sg:orig_category":"Institutos De Belleza",
    "sg:phone":"+34 934 87 13 31",
    "sg:postcode":"08037",
    "sg:province":"Barcelona",
    "sg:website":"www.dibicosmetic.com",
    "wof:name":"Dibi Cosmetic S.l.",
    "wof:placetype":"venue"
},
  "geometry": {"coordinates":[2.163711071,41.3968353271],"type":"Point"}
}