{
  "type": "Feature",
  "properties": {
    "addr:full":"Calle de Marques De La Valdavia (del), 19 Alcobendas Madrid 28100",
    "addr:postcode":"28100",
    "addr:street":"Calle De Marques De La Valdavia Del;Alcobendas",
    "iso:country":"ES",
    "sg:address":"Calle de Marques De La Valdavia (del), 19",
    "sg:city":"Alcobendas",
    "sg:orig_category":"Ropa Para Ni\u00d1os (al Por Menor)",
    "sg:phone":"+34 916 62 02 06",
    "sg:postcode":"28100",
    "sg:province":"Madrid",
    "wof:name":"Camin Fernandez Maria Belen",
    "wof:placetype":"venue"
},
  "geometry": {"coordinates":[-3.6368858814,40.540687561],"type":"Point"}
}