{
  "type": "Feature",
  "properties": {
    "addr:full":"Calle de Antonio Gaudi (de), 11 Fuenlabrada Madrid 28946",
    "addr:housenumber":"11",
    "addr:postcode":"28946",
    "addr:street":"Calle De Antonio Gaudi De",
    "iso:country":"ES",
    "sg:address":"Calle de Antonio Gaudi (de), 11",
    "sg:city":"Fuenlabrada",
    "sg:orig_category":"Materias Pl\u00c1sticas: Art\u00cdculos Para La Industria",
    "sg:phone":"+34 916 90 11 46",
    "sg:postcode":"28946",
    "sg:province":"Madrid",
    "sg:website":"www.bardera.net",
    "wof:name":"Plasticos Bardera S.l.",
    "wof:placetype":"venue"
},
  "geometry": {"coordinates":[-3.7785954475,40.2810249329],"type":"Point"}
}