{
  "type": "Feature",
  "properties": {
    "iso:country":"ES",
    "sg:address":"Carretera Fabrica De La Luz, 10",
    "sg:city":"Dilar",
    "sg:orig_category":"Artes Gr\u00c1ficas, Artes Pl\u00c1sticas (curso)",
    "sg:phone":"+34 958 59 61 86",
    "sg:postcode":"18152",
    "sg:province":"Granada",
    "wof:name":"Velasco Artes Graficas C.b.",
    "wof:placetype":"venue"
},
  "geometry": {"coordinates":[-3.6037769318,37.0774459839],"type":"Point"}
}