{
  "type": "Feature",
  "properties": {
    "iso:country":"ES",
    "sg:address":"Calle de Cuadro, 1",
    "sg:city":"Piedrabuena",
    "sg:orig_category":"Farmacias",
    "sg:phone":"+34 926 76 00 05",
    "sg:postcode":"13100",
    "sg:province":"Ciudad Real",
    "wof:name":"Rodriguez Balcazar Aurora",
    "wof:placetype":"venue"
},
  "geometry": {"coordinates":[-4.176129818,39.035697937],"type":"Point"}
}