{
  "type": "Feature",
  "properties": {
    "iso:country":"ES",
    "sg:address":"S. Martino, S/n",
    "sg:city":"San Martino",
    "sg:orig_category":"Charcuter\u00cdas (al Por Mayor)",
    "sg:phone":"+34 985 49 19 07",
    "sg:postcode":"33695",
    "sg:province":"Asturias",
    "wof:name":"Embutidos Artesanales San Martin De Lena Sl",
    "wof:placetype":"venue"
},
  "geometry": {"coordinates":[-5.8212342262,43.1781082153],"type":"Point"}
}