{
  "type": "Feature",
  "properties": {
    "addr:full":"Calle de Jose Miguel Galvan Bello, 3 Galletas Santa Cruz De Tenerife 38631",
    "addr:housenumber":"3",
    "addr:postcode":"38631",
    "addr:street":"Calle De Jose Miguel Galvan Bello",
    "iso:country":"ES",
    "sg:address":"Calle de Jose Miguel Galvan Bello, 3",
    "sg:city":"Galletas",
    "sg:orig_category":"Abogados",
    "sg:phone":"+34 922 73 04 62",
    "sg:postcode":"38631",
    "sg:province":"Santa Cruz De Tenerife",
    "wof:name":"Ayala Alfonso Hortensia",
    "wof:placetype":"venue"
},
  "geometry": {"coordinates":[-16.670463562,28.0141906738],"type":"Point"}
}