{
  "type": "Feature",
  "properties": {
    "addr:full":"Calle de Dilar, S/n Otura Granada 18630",
    "addr:housenumber":"s / n",
    "addr:postcode":"18630",
    "addr:street":"Calle De Dilar",
    "iso:country":"ES",
    "sg:address":"Calle de Dilar, S/n",
    "sg:city":"Otura",
    "sg:orig_category":"Mec\u00c1nico Del Autom\u00d3vil",
    "sg:phone":"+34 958 55 52 41",
    "sg:postcode":"18630",
    "sg:province":"Granada",
    "wof:name":"Morales Rodriguez Jesus",
    "wof:placetype":"venue"
},
  "geometry": {"coordinates":[-3.6368229389,37.0890922546],"type":"Point"}
}