{
  "type": "Feature",
  "properties": {
    "iso:country":"ES",
    "sg:address":"Ctra. N. 340, Km. 0210,3",
    "sg:city":"Antas",
    "sg:orig_category":"Aparatos E Instalaci\u00d3n De Regad\u00cdos",
    "sg:phone":"+34 950 45 33 23",
    "sg:postcode":"04628",
    "sg:province":"Almer\u00eda",
    "wof:name":"Riegos Antas S. L.",
    "wof:placetype":"venue"
},
  "geometry": {"coordinates":[-1.9216589928,37.2441215515],"type":"Point"}
}