{
  "type": "Feature",
  "properties": {
    "iso:country":"ES",
    "sg:address":"Calle de Doctor Don Marcelino Roca, 2",
    "sg:city":"Pe\u00f1iscola",
    "sg:orig_category":"Molduras, Junquillos, Listones Y Molduras Perforadas",
    "sg:phone":"+34 964 48 00 62",
    "sg:postcode":"12598",
    "sg:province":"Castell\u00f3n",
    "wof:name":"Oms Albiol Felicidad",
    "wof:placetype":"venue"
},
  "geometry": {"coordinates":[0.4046437144,40.3593673706],"type":"Point"}
}