{
  "type": "Feature",
  "properties": {
    "addr:full":"Calle de Graciano Atienza, 20 Villarrobledo Albacete 02600",
    "addr:housenumber":"20",
    "addr:postcode":"02600",
    "addr:street":"Calle De Graciano Atienza",
    "iso:country":"ES",
    "sg:address":"Calle de Graciano Atienza, 20",
    "sg:city":"Villarrobledo",
    "sg:orig_category":"Telas Y Sedas (al Por Menor)",
    "sg:phone":"+34 967 14 07 37",
    "sg:postcode":"02600",
    "sg:province":"Albacete",
    "wof:name":"Roldan Morcillo Francisco",
    "wof:placetype":"venue"
},
  "geometry": {"coordinates":[-2.6037569046,39.265953064],"type":"Point"}
}