{
  "type": "Feature",
  "properties": {
    "iso:country":"ES",
    "sg:address":"Calle de Miguel Hernandez, 6",
    "sg:city":"Torredonjimeno",
    "sg:orig_category":"Promotores Constructores",
    "sg:phone":"+34 953 57 24 62",
    "sg:postcode":"23650",
    "sg:province":"Ja\u00e9n",
    "wof:name":"Hermanos Navas Lara C.b.",
    "wof:placetype":"venue"
},
  "geometry": {"coordinates":[-3.9521000385,37.7668571472],"type":"Point"}
}