{
  "type": "Feature",
  "properties": {
    "iso:country":"ES",
    "sg:address":"Avda Ancha De Castelar, 106",
    "sg:city":"San Vicente Del Raspeig-sant Vicent Del Raspeig",
    "sg:orig_category":"Cl\u00cdnicas M\u00c9dicas",
    "sg:phone":"+34 965 67 21 02",
    "sg:postcode":"03690",
    "sg:province":"Alicante",
    "wof:name":"Calatayud Monzo Rafael Juan",
    "wof:placetype":"venue"
},
  "geometry": {"coordinates":[-0.5236629844,38.399066925],"type":"Point"}
}