{
  "type": "Feature",
  "properties": {
    "iso:country":"ES",
    "sg:address":"Calle de Garibai, 25",
    "sg:city":"Donostia-san Sebastian",
    "sg:orig_category":"Confecci\u00d3n (fabricaci\u00d3n, Al Por Mayor)",
    "sg:phone":"+34 943 42 70 06",
    "sg:postcode":"20004",
    "sg:province":"Guip\u00f9zcoa",
    "wof:name":"Ignacio Rodriguez Diez (decoracion",
    "wof:placetype":"venue"
},
  "geometry": {"coordinates":[-1.9825810194,43.319732666],"type":"Point"}
}