{
  "type": "Feature",
  "properties": {
    "addr:full":"Carrer de Nou De La Rambla, 138 Barcelona Barcelona 08004",
    "addr:housenumber":"138",
    "addr:postcode":"08004",
    "addr:street":"Carrer De Nou De La Rambla",
    "iso:country":"ES",
    "sg:address":"Carrer de Nou De La Rambla, 138",
    "sg:city":"Barcelona",
    "sg:orig_category":"Prendas Y Chalecos De Punto (al Por Menor)",
    "sg:phone":"+34 934 41 12 77",
    "sg:postcode":"08004",
    "sg:province":"Barcelona",
    "wof:name":"Barrio Cocina Carmen",
    "wof:placetype":"venue"
},
  "geometry": {"coordinates":[2.1680140495,41.3732681274],"type":"Point"}
}