{
  "type": "Feature",
  "properties": {
    "iso:country":"ES",
    "sg:address":"Calle de Lapurbide, 12",
    "sg:city":"Ansoain",
    "sg:orig_category":"Mercer\u00cda (fabricaci\u00d3n, Al Por Mayor)",
    "sg:phone":"+34 948 12 02 52",
    "sg:postcode":"31013",
    "sg:province":"Navarra",
    "wof:name":"Bartolome Gomez Redencion",
    "wof:placetype":"venue"
},
  "geometry": {"coordinates":[-1.6387519836,42.8334350586],"type":"Point"}
}