{
  "type": "Feature",
  "properties": {
    "addr:full":"Calle de Rosa (de La), 21 Aranjuez Madrid 28300",
    "addr:housenumber":"21",
    "addr:postcode":"28300",
    "addr:street":"Calle De Rosa De La",
    "iso:country":"ES",
    "sg:address":"Calle de Rosa (de La), 21",
    "sg:city":"Aranjuez",
    "sg:orig_category":"Pesca Y Caza: Art\u00cdculos (al Por Menor)",
    "sg:phone":"+34 918 92 43 27",
    "sg:postcode":"28300",
    "sg:province":"Madrid",
    "wof:name":"Carvajal Trigo Bego\u00f1a",
    "wof:placetype":"venue"
},
  "geometry": {"coordinates":[-3.6055591106,40.030128479],"type":"Point"}
}