{
  "type": "Feature",
  "properties": {
    "iso:country":"ES",
    "sg:address":"Carr Barcelona, 210",
    "sg:city":"Girona",
    "sg:orig_category":"Acondicionamiento, Mantenimiento De Jardines Y Parques",
    "sg:phone":"+34 972 22 22 41",
    "sg:postcode":"17005",
    "sg:province":"Girona",
    "wof:name":"Centre Verd S.a.",
    "wof:placetype":"venue"
},
  "geometry": {"coordinates":[2.8110918999,41.9624099731],"type":"Point"}
}