{
  "type": "Feature",
  "properties": {
    "addr:full":"Avda Colonia (de La), S/n Linea De La Concepcion C\u00e1diz 11300",
    "addr:postcode":"11300",
    "addr:street":"Avda Colonia De La S / N Linea De La Concepcion Ca\u0301Diz",
    "iso:country":"ES",
    "sg:address":"Avda Colonia (de La), S/n",
    "sg:city":"Linea De La Concepcion",
    "sg:orig_category":"Ropa Para Se\u00d1oras Y Caballeros (al Por Menor)",
    "sg:phone":"+34 956 17 71 96",
    "sg:postcode":"11300",
    "sg:province":"C\u00e1diz",
    "wof:name":"Jimenez Pelayo Manuel Julian",
    "wof:placetype":"venue"
},
  "geometry": {"coordinates":[-5.3622441292,36.1733894348],"type":"Point"}
}