{
  "type": "Feature",
  "properties": {
    "iso:country":"ES",
    "sg:address":"Carrer de Moreres (les), 121",
    "sg:city":"Prat Llobregat",
    "sg:orig_category":"Oficinas: Suministros Para (fabricaci\u00d3n, Al Por Mayor)",
    "sg:phone":"+34 933 70 67 00",
    "sg:postcode":"08820",
    "sg:province":"Barcelona",
    "wof:name":"Corporate Express Espa\u00f1a S.a.u.",
    "wof:placetype":"venue"
},
  "geometry": {"coordinates":[2.1025300026,41.331489563],"type":"Point"}
}