{
  "type": "Feature",
  "properties": {
    "addr:full":"Carrer de Montserrat, 96 Martorell Barcelona 08760",
    "addr:housenumber":"96",
    "addr:postcode":"08760",
    "addr:street":"Carrer De Montserrat",
    "iso:country":"ES",
    "sg:address":"Carrer de Montserrat, 96",
    "sg:city":"Martorell",
    "sg:orig_category":"Cristaler\u00cdas",
    "sg:phone":"+34 937 75 40 22",
    "sg:postcode":"08760",
    "sg:province":"Barcelona",
    "wof:name":"Cristaleria El Pla S.l.",
    "wof:placetype":"venue"
},
  "geometry": {"coordinates":[1.9208710194,41.4827079773],"type":"Point"}
}