{
  "type": "Feature",
  "properties": {
    "addr:full":"Calle de Felix Lafuente, 9 Huesca Huesca 22004",
    "addr:housenumber":"9",
    "addr:postcode":"22004",
    "addr:street":"Calle De Felix Lafuente",
    "iso:country":"ES",
    "sg:address":"Calle de Felix Lafuente, 9",
    "sg:city":"Huesca",
    "sg:orig_category":"M\u00c9dicos: Estomatolog\u00cda",
    "sg:phone":"+34 974 24 40 23",
    "sg:postcode":"22004",
    "sg:province":"Huesca",
    "wof:name":"Ortodoncia Samprieto S.l.",
    "wof:placetype":"venue"
},
  "geometry": {"coordinates":[-0.4195019901,42.138130188],"type":"Point"}
}