{
  "type": "Feature",
  "properties": {
    "iso:country":"ES",
    "sg:address":"Carrer de Alemanya, 136",
    "sg:city":"Terrassa",
    "sg:orig_category":"Colchones (fabricaci\u00d3n, Al Por Mayor, Al Por Menor)",
    "sg:phone":"+34 937 31 78 16",
    "sg:postcode":"08228",
    "sg:province":"Barcelona",
    "wof:name":"Cash Del Colchon S.l.",
    "wof:placetype":"venue"
},
  "geometry": {"coordinates":[2.0461790562,41.5404243469],"type":"Point"}
}