{
  "type": "Feature",
  "properties": {
    "addr:full":"Calle de General Casta\u00d1os, 3 Algeciras C\u00e1diz 11201",
    "addr:housenumber":"3;ca\u0301diz",
    "addr:postcode":"11201",
    "addr:street":"Calle De General Castan\u0303Os",
    "iso:country":"ES",
    "sg:address":"Calle de General Casta\u00d1os, 3",
    "sg:city":"Algeciras",
    "sg:classifiers":[
        {
            "category":"Government",
            "subcategory":"City Hall",
            "type":"Public Place"
        }
    ],
    "sg:phone":"+34 956 58 73 39",
    "sg:postcode":"11201",
    "sg:province":"C\u00e1diz",
    "sg:tags":[
        "el",
        "alquiler",
        "extranjero",
        "villa",
        "de",
        "en"
    ],
    "wof:name":"Amanecer Gestion Inmobiliaria S.c.",
    "wof:placetype":"venue"
},
  "geometry": {"coordinates":[-5.4468255043,36.1303100586],"type":"Point"}
}