{
  "type": "Feature",
  "properties": {
    "addr:full":"Ctra Pardo (del), S/n Pe\u00d1ascales Madrid 28250",
    "addr:postcode":"28250",
    "addr:street":"Ctra Pardo Del S / N Pen\u0303Ascales",
    "iso:country":"ES",
    "sg:address":"Ctra Pardo (del), S/n",
    "sg:city":"Pe\u00d1ascales",
    "sg:orig_category":"Organizaci\u00d3n De Actos, Seminarios Y Congresos",
    "sg:phone":"+34 918 56 31 05",
    "sg:postcode":"28250",
    "sg:province":"Madrid",
    "sg:website":"www.carruajesdelguadarrama.com",
    "wof:name":"Carruajes Del Guadarrama S.l.",
    "wof:placetype":"venue"
},
  "geometry": {"coordinates":[-3.9090900421,40.5818099976],"type":"Point"}
}