{
  "type": "Feature",
  "properties": {
    "iso:country":"ES",
    "sg:address":"Carrer de Monturiol, 3",
    "sg:city":"Playa De Calafell",
    "sg:orig_category":"Agencias Y Agentes Comerciales, Representantes",
    "sg:phone":"+34 977 69 96 10",
    "sg:postcode":"43820",
    "sg:province":"Tarragona",
    "wof:name":"Schroeder  Betina Andrea",
    "wof:placetype":"venue"
},
  "geometry": {"coordinates":[1.5733679533,41.1874504089],"type":"Point"}
}