{
  "type": "Feature",
  "properties": {
    "iso:country":"ES",
    "sg:address":"Calle de Olivina, 26",
    "sg:city":"Norias De Daza",
    "sg:orig_category":"Ingenier\u00cda, Centros De Estudios (diversos)",
    "sg:phone":"+34 950 58 78 47",
    "sg:postcode":"04716",
    "sg:province":"Almer\u00eda",
    "wof:name":"Moreno Alonso Antonio 000466408h Slne",
    "wof:placetype":"venue"
},
  "geometry": {"coordinates":[-2.7523419857,36.758895874],"type":"Point"}
}