{
  "type": "Feature",
  "properties": {
    "addr:full":"Calle de Alonso De Villalpando, 12 Cartuja Baja Zaragoza 50720",
    "addr:housenumber":"12",
    "addr:postcode":"50720",
    "addr:street":"Calle De Alonso De Villalpando;Baja",
    "iso:country":"ES",
    "sg:address":"Calle de Alonso De Villalpando, 12",
    "sg:city":"Cartuja Baja",
    "sg:orig_category":"Cr\u00cda De Animales",
    "sg:phone":"+34 976 50 01 97",
    "sg:postcode":"50720",
    "sg:province":"Zaragoza",
    "wof:name":"Gracia Martinez Bego\u00f1a",
    "wof:placetype":"venue"
},
  "geometry": {"coordinates":[-0.8241500258,41.6057167053],"type":"Point"}
}