{
  "type": "Feature",
  "properties": {
    "iso:country":"ES",
    "sg:address":"Grup A\u00d1orga-txiki, 15",
    "sg:city":"A\u00d1orga",
    "sg:classifiers":[
        {
            "category":"Government",
            "subcategory":"Post Office",
            "type":"Public Place"
        }
    ],
    "sg:phone":"+34 943 37 21 93",
    "sg:postcode":"20018",
    "sg:province":"Guip\u00f9zcoa",
    "sg:tags":[
        "de",
        "yoga",
        "clases"
    ],
    "wof:name":"Urkola Lertxundi I\u00f1aki",
    "wof:placetype":"venue"
},
  "geometry": {"coordinates":[-2.0029520988,43.2836837769],"type":"Point"}
}