{
  "type": "Feature",
  "properties": {
    "addr:full":"Carrer de Calabria, 61 Barcelona Barcelona 08015",
    "addr:housenumber":"61",
    "addr:postcode":"08015",
    "addr:street":"Carrer De Calabria",
    "iso:country":"ES",
    "sg:address":"Carrer de Calabria, 61",
    "sg:city":"Barcelona",
    "sg:orig_category":"Farmacias",
    "sg:phone":"+34 934 23 36 49",
    "sg:postcode":"08015",
    "sg:province":"Barcelona",
    "wof:name":"Rivera Arnandis Javier",
    "wof:placetype":"venue"
},
  "geometry": {"coordinates":[2.1572649479,41.3778038025],"type":"Point"}
}