{
  "type": "Feature",
  "properties": {
    "addr:full":"Pg Enric Sanchis, 44 Barcelona Barcelona 08030",
    "addr:housenumber":"44",
    "addr:postcode":"08030",
    "addr:street":"Pg Enric Sanchis",
    "iso:country":"ES",
    "sg:address":"Pg Enric Sanchis, 44",
    "sg:city":"Barcelona",
    "sg:orig_category":"Construcciones Met\u00c1licas",
    "sg:phone":"+34 932 78 06 47",
    "sg:postcode":"08030",
    "sg:province":"Barcelona",
    "wof:name":"Transmisiones Novatrans S.l.l",
    "wof:placetype":"venue"
},
  "geometry": {"coordinates":[2.2058739662,41.4333686829],"type":"Point"}
}