{
  "type": "Feature",
  "properties": {
    "addr:full":"Rbla Pulido, 32 Santa Cruz De Tenerife Santa Cruz De Tenerife 38004",
    "addr:housenumber":"32",
    "addr:postcode":"38004",
    "addr:street":"Rbla Pulido",
    "iso:country":"ES",
    "sg:address":"Rbla Pulido, 32",
    "sg:city":"Santa Cruz De Tenerife",
    "sg:orig_category":"Telas Y Sedas (al Por Menor)",
    "sg:phone":"+34 922 27 67 58",
    "sg:postcode":"38004",
    "sg:province":"Santa Cruz De Tenerife",
    "wof:name":"Name Enmeir Juan Salomon",
    "wof:placetype":"venue"
},
  "geometry": {"coordinates":[-16.2585849762,28.4677257538],"type":"Point"}
}