{
  "type": "Feature",
  "properties": {
    "addr:full":"Avda Dilar (de), 114 Granada Granada 18007",
    "addr:housenumber":"114",
    "addr:postcode":"18007",
    "addr:street":"Avda Dilar De",
    "iso:country":"ES",
    "sg:address":"Avda Dilar (de), 114",
    "sg:city":"Granada",
    "sg:orig_category":"Molduras, Junquillos, Listones Y Molduras Perforadas",
    "sg:phone":"+34 958 12 86 73",
    "sg:postcode":"18007",
    "sg:province":"Granada",
    "wof:name":"Martinez Ruiz Fernando",
    "wof:placetype":"venue"
},
  "geometry": {"coordinates":[-3.6009619236,37.1527366638],"type":"Point"}
}