{
  "type": "Feature",
  "properties": {
    "iso:country":"ES",
    "sg:address":"Carr Joan Regla, 5",
    "sg:city":"Figueres",
    "sg:orig_category":"Grafistas",
    "sg:phone":"+34 972 51 22 87",
    "sg:postcode":"17600",
    "sg:province":"Girona",
    "sg:website":"www.terradasweb.com",
    "wof:name":"Terradas Comunicacio S.l.",
    "wof:placetype":"venue"
},
  "geometry": {"coordinates":[2.9678070545,42.264503479],"type":"Point"}
}