{
  "type": "Feature",
  "properties": {
    "iso:country":"ES",
    "sg:address":"Calle de Virgen (la), 3",
    "sg:city":"Calamocha",
    "sg:orig_category":"Empresarios Y Productoras De Espect\u00c1culos",
    "sg:phone":"+34 978 73 08 74",
    "sg:postcode":"44200",
    "sg:province":"Teruel",
    "sg:website":"www.audiovisualesaragon.com",
    "wof:name":"Sanroma Latorre Victor Manuel",
    "wof:placetype":"venue"
},
  "geometry": {"coordinates":[-1.2964370251,40.9196929932],"type":"Point"}
}