{
  "type": "Feature",
  "properties": {
    "iso:country":"ES",
    "sg:address":"Calle de San Cristobal, 28",
    "sg:city":"Vinaros",
    "sg:orig_category":"Aparatos, Sistemas De Tele",
    "sg:phone":"+34 964 45 35 56",
    "sg:postcode":"12500",
    "sg:province":"Castell\u00f3n",
    "wof:name":"Sanchez Guijarro Angel",
    "wof:placetype":"venue"
},
  "geometry": {"coordinates":[0.4756140113,40.4718322754],"type":"Point"}
}