{
  "type": "Feature",
  "properties": {
    "iso:country":"ES",
    "sg:address":"Carr Jose Carsi, 18",
    "sg:city":"Burjassot",
    "sg:orig_category":"Administradores De Bienes Y Delegados De Comunidades De Propietarios",
    "sg:phone":"+34 963 63 87 39",
    "sg:postcode":"46100",
    "sg:province":"Valencia",
    "wof:name":"Garcia Abril Maria Josefa",
    "wof:placetype":"venue"
},
  "geometry": {"coordinates":[-0.4091840088,39.5090446472],"type":"Point"}
}