{
  "type": "Feature",
  "properties": {
    "iso:country":"ES",
    "sg:address":"Calle de Reina Sofia, 10",
    "sg:city":"Atarfe",
    "sg:orig_category":"Bares, Piano",
    "sg:phone":"+34 958 43 73 68",
    "sg:postcode":"18230",
    "sg:province":"Granada",
    "wof:name":"Godino Sierra Dolores",
    "wof:placetype":"venue"
},
  "geometry": {"coordinates":[-3.6842489243,37.2270431519],"type":"Point"}
}