{
  "type": "Feature",
  "properties": {
    "addr:full":"Plaz Francisco Perojo Cagigas, 7 Solares Cantabria 39710",
    "addr:housenumber":"7",
    "addr:postcode":"39710",
    "addr:street":"Francisco Perojo Cagigas",
    "iso:country":"ES",
    "sg:address":"Plaz Francisco Perojo Cagigas, 7",
    "sg:city":"Solares",
    "sg:orig_category":"Promotores Constructores",
    "sg:phone":"+34 942 52 09 16",
    "sg:postcode":"39710",
    "sg:province":"Cantabria",
    "wof:name":"Edificaciones El Poligono S. A.",
    "wof:placetype":"venue"
},
  "geometry": {"coordinates":[-3.737844944,43.3837776184],"type":"Point"}
}