{
  "type": "Feature",
  "properties": {
    "iso:country":"ES",
    "sg:address":"Calle de Ambrosio Ballesteros, 7",
    "sg:city":"Torrijos",
    "sg:orig_category":"Supermercados Y Hipermercados",
    "sg:phone":"+34 925 77 02 26",
    "sg:postcode":"45500",
    "sg:province":"Toledo",
    "wof:name":"Ahorraprix S.a.",
    "wof:placetype":"venue"
},
  "geometry": {"coordinates":[-4.2822666168,39.9826698303],"type":"Point"}
}