{
  "type": "Feature",
  "properties": {
    "iso:country":"ES",
    "sg:address":"Carr Ausias March, 22",
    "sg:city":"Oliva",
    "sg:orig_category":"Complementos De Vestir (al Por Menor)",
    "sg:phone":"+34 962 83 95 93",
    "sg:postcode":"46780",
    "sg:province":"Valencia",
    "wof:name":"Jurlow  Louise",
    "wof:placetype":"venue"
},
  "geometry": {"coordinates":[-0.1230589971,38.9237213135],"type":"Point"}
}