{
  "type": "Feature",
  "properties": {
    "addr:full":"Calle de San Andres, 35 Madrid Madrid 28004",
    "addr:housenumber":"35",
    "addr:postcode":"madrid;28004",
    "addr:street":"Calle De San Andres",
    "iso:country":"ES",
    "sg:address":"Calle de San Andres, 35",
    "sg:city":"Madrid",
    "sg:orig_category":"M\u00c9dicos: Endocrinolog\u00cda Y Metabolismo",
    "sg:phone":"+34 914 46 73 02",
    "sg:postcode":"28004",
    "sg:province":"Madrid",
    "wof:name":"Sastre Garcia-rojo Amalia",
    "wof:placetype":"venue"
},
  "geometry": {"coordinates":[-3.7034549713,40.4290237427],"type":"Point"}
}