{
  "type": "Feature",
  "properties": {
    "iso:country":"ES",
    "sg:address":"Calle de Doctor Fleming, 6",
    "sg:city":"Palencia",
    "sg:orig_category":"Electricidad: Instaladores",
    "sg:phone":"+34 979 72 61 44",
    "sg:postcode":"34004",
    "sg:province":"Palencia",
    "wof:name":"Instalaciones Electricas Selec S.l.",
    "wof:placetype":"venue"
},
  "geometry": {"coordinates":[-4.5243759155,42.0013885498],"type":"Point"}
}