{
  "type": "Feature",
  "properties": {
    "iso:country":"ES",
    "sg:address":"Perpendicular Uno Guaza, 18",
    "sg:city":"Guaza",
    "sg:orig_category":"Persianas Interiores, Exteriores",
    "sg:phone":"+34 922 16 91 17",
    "sg:postcode":"38627",
    "sg:province":"Santa Cruz De Tenerife",
    "wof:name":"Ramos Fernandez Amelia",
    "wof:placetype":"venue"
},
  "geometry": {"coordinates":[-16.6800937653,28.0790691376],"type":"Point"}
}