{
  "type": "Feature",
  "properties": {
    "iso:country":"ES",
    "sg:address":"Calle de Monforte, 10",
    "sg:city":"Coru\u00d1a",
    "sg:orig_category":"M\u00c9dicos: Estomatolog\u00cda",
    "sg:phone":"+34 981 24 99 89",
    "sg:postcode":"15007",
    "sg:province":"La Coru\u00f1a",
    "wof:name":"Lorca Codina Maria Inmaculada",
    "wof:placetype":"venue"
},
  "geometry": {"coordinates":[-8.4070386887,43.3563232422],"type":"Point"}
}