{
  "type": "Feature",
  "properties": {
    "addr:full":"Avda Calahorra, 14 Santo Domingo De La Calzada La Rioja 26250",
    "addr:housenumber":"14",
    "addr:postcode":"26250",
    "addr:street":"Avda Calahorra;Rioja",
    "iso:country":"ES",
    "sg:address":"Avda Calahorra, 14",
    "sg:city":"Santo Domingo De La Calzada",
    "sg:orig_category":"Arquitectos",
    "sg:phone":"+34 941 34 24 94",
    "sg:postcode":"26250",
    "sg:province":"La Rioja",
    "wof:name":"Valer Rubio Jesus Domingo",
    "wof:placetype":"venue"
},
  "geometry": {"coordinates":[-2.9509420395,42.4413146973],"type":"Point"}
}