{
  "type": "Feature",
  "properties": {
    "iso:country":"ES",
    "sg:address":"Carrer de Francesc Ferrer I Guardia, 37",
    "sg:city":"Mollet Valles",
    "sg:classifiers":[
        {
            "category":"Personal",
            "subcategory":"Barber",
            "type":"Services"
        }
    ],
    "sg:phone":"+34 935 70 92 34",
    "sg:postcode":"08100",
    "sg:province":"Barcelona",
    "sg:tags":[
        "caballeros",
        "de",
        "peluqueros"
    ],
    "wof:name":"Sanchez Martinez Antonio",
    "wof:placetype":"venue"
},
  "geometry": {"coordinates":[2.204431057,41.547832489],"type":"Point"}
}