{
  "type": "Feature",
  "properties": {
    "iso:country":"ES",
    "sg:address":"Cno Polio, S/n",
    "sg:city":"Beniparrell",
    "sg:orig_category":"Transportes Por V\u00cdas Navegables",
    "sg:phone":"+34 961 21 06 28",
    "sg:postcode":"46469",
    "sg:province":"Valencia",
    "wof:name":"Tussertrans S.a.l.",
    "wof:placetype":"venue"
},
  "geometry": {"coordinates":[-0.4188640118,39.3784294128],"type":"Point"}
}