{
  "type": "Feature",
  "properties": {
    "addr:full":"Carrer de Badalona, 29 Argentona Barcelona 08310",
    "addr:housenumber":"29",
    "addr:postcode":"08310",
    "addr:street":"Carrer De Badalona",
    "iso:country":"ES",
    "sg:address":"Carrer de Badalona, 29",
    "sg:city":"Argentona",
    "sg:orig_category":"Promotores Constructores",
    "sg:phone":"+34 937 97 18 51",
    "sg:postcode":"08310",
    "sg:province":"Barcelona",
    "wof:name":"Vik 7 S.l.",
    "wof:placetype":"venue"
},
  "geometry": {"coordinates":[2.402837038,41.5573425293],"type":"Point"}
}