{
  "type": "Feature",
  "properties": {
    "iso:country":"ES",
    "sg:address":"Av Espanya, 1",
    "sg:city":"Eivissa",
    "sg:orig_category":"Abogados",
    "sg:phone":"+34 971 30 68 11",
    "sg:postcode":"07800",
    "sg:province":"Islas Baleares",
    "wof:name":"Riera Mugica Maria Eulalia",
    "wof:placetype":"venue"
},
  "geometry": {"coordinates":[1.4320950508,38.908657074],"type":"Point"}
}