{
  "type": "Feature",
  "properties": {
    "addr:full":"Carr Eivissa, S/n S. Francesc Formentera Islas Baleares 07860",
    "addr:housenumber":"s",
    "addr:postcode":"07860",
    "addr:street":"Carr Eivissa;/ N S. Francesc",
    "iso:country":"ES",
    "sg:address":"Carr Eivissa, S/n",
    "sg:city":"S. Francesc Formentera",
    "sg:orig_category":"Arquitectos",
    "sg:phone":"+34 971 32 22 87",
    "sg:postcode":"07860",
    "sg:province":"Islas Baleares",
    "wof:name":"Alonso Prieto Tomas Ignacio",
    "wof:placetype":"venue"
},
  "geometry": {"coordinates":[1.4294034243,38.7048187256],"type":"Point"}
}