{
  "type": "Feature",
  "properties": {
    "addr:full":"Calle de San Pedro, 4 Martos Ja\u00e9n 23600",
    "addr:housenumber":"4",
    "addr:postcode":"23600",
    "addr:street":"Calle De San Pedro;Jae\u0301N",
    "iso:country":"ES",
    "sg:address":"Calle de San Pedro, 4",
    "sg:city":"Martos",
    "sg:orig_category":"Iglesia Cat\u00d3lica",
    "sg:phone":"+34 953 55 02 68",
    "sg:postcode":"23600",
    "sg:province":"Ja\u00e9n",
    "wof:name":"Parroquia De Santa Marta",
    "wof:placetype":"venue"
},
  "geometry": {"coordinates":[-3.9650568962,37.7231941223],"type":"Point"}
}