{
  "type": "Feature",
  "properties": {
    "iso:country":"ES",
    "sg:address":"Calle de Adelardo Covarsi, 9",
    "sg:city":"Badajoz",
    "sg:orig_category":"Fabricaci\u00d3n, Venta De Cuadros, Accesorios Para Enmarcar",
    "sg:phone":"+34 924 23 55 38",
    "sg:postcode":"06005",
    "sg:province":"Badajoz",
    "wof:name":"Ba\u00f1os Zapata Angeles",
    "wof:placetype":"venue"
},
  "geometry": {"coordinates":[-6.978079319,38.8734359741],"type":"Point"}
}