{
  "type": "Feature",
  "properties": {
    "iso:country":"ES",
    "sg:address":"Calle de Argentina, 15",
    "sg:city":"Leganes",
    "sg:orig_category":"Caf\u00c9s, Bares, Cervecer\u00cdas",
    "sg:phone":"+34 916 80 79 44",
    "sg:postcode":"28914",
    "sg:province":"Madrid",
    "wof:name":"Solla Marquez Maria Teresa",
    "wof:placetype":"venue"
},
  "geometry": {"coordinates":[-3.7852323055,40.2845458984],"type":"Point"}
}