{
  "type": "Feature",
  "properties": {
    "iso:country":"ES",
    "sg:address":"Dr. D. Juan Rico Faus, 30",
    "sg:city":"Beniarjo",
    "sg:orig_category":"Arquitectos",
    "sg:phone":"+34 962 80 10 56",
    "sg:postcode":"46722",
    "sg:province":"Valencia",
    "wof:name":"Ruiz Sanmateu Borja",
    "wof:placetype":"venue"
},
  "geometry": {"coordinates":[-0.1866499931,38.9286003113],"type":"Point"}
}