{
  "type": "Feature",
  "properties": {
    "iso:country":"ES",
    "sg:address":"Avda Mirat, 23",
    "sg:city":"Salamanca",
    "sg:orig_category":"M\u00c9dicos: Oftalmolog\u00cda",
    "sg:phone":"+34 923 26 03 05",
    "sg:postcode":"37002",
    "sg:province":"Salamanca",
    "wof:name":"Sanchez-jara Luengo Juan",
    "wof:placetype":"venue"
},
  "geometry": {"coordinates":[-5.6611561775,40.9693984985],"type":"Point"}
}