{
  "type": "Feature",
  "properties": {
    "iso:country":"ES",
    "sg:address":"Carrer de Francesc Layret, 17",
    "sg:city":"Sabadell",
    "sg:orig_category":"Peluquer\u00cdas, Peluquer\u00cda Mixta",
    "sg:phone":"+34 937 23 43 77",
    "sg:postcode":"08208",
    "sg:province":"Barcelona",
    "wof:name":"Navarro Martinez Montserrat",
    "wof:placetype":"venue"
},
  "geometry": {"coordinates":[2.0981740952,41.5591468811],"type":"Point"}
}