{
  "type": "Feature",
  "properties": {
    "addr:full":"Mossen Maria Martinez, 1 Canet Mar Barcelona 08360",
    "addr:housenumber":"1",
    "addr:postcode":"08360",
    "addr:street":"Mossen;Martinez",
    "iso:country":"ES",
    "sg:address":"Mossen Maria Martinez, 1",
    "sg:city":"Canet Mar",
    "sg:orig_category":"Ambulancias",
    "sg:phone":"+34 937 94 09 77",
    "sg:postcode":"08360",
    "sg:province":"Barcelona",
    "wof:name":"Transmutua 2003 S.l..",
    "wof:placetype":"venue"
},
  "geometry": {"coordinates":[2.580630064,41.5922012329],"type":"Point"}
}