{
  "type": "Feature",
  "properties": {
    "addr:full":"Calle de Arcos De San Anton, 15 Plasencia C\u00e1ceres 10600",
    "addr:housenumber":"15",
    "addr:postcode":"10600",
    "addr:street":"Calle De Arcos De San Anton;Ca\u0301Ceres",
    "iso:country":"ES",
    "sg:address":"Calle de Arcos De San Anton, 15",
    "sg:city":"Plasencia",
    "sg:orig_category":"Promotores Constructores",
    "sg:phone":"+34 927 41 49 50",
    "sg:postcode":"10600",
    "sg:province":"C\u00e1ceres",
    "wof:name":"S.m. Lopez Clemente S.l.",
    "wof:placetype":"venue"
},
  "geometry": {"coordinates":[-6.0862288475,40.0364608765],"type":"Point"}
}