{
  "type": "Feature",
  "properties": {
    "iso:country":"ES",
    "sg:address":"Rua Bordeiras, 75",
    "sg:city":"Pastoriza",
    "sg:orig_category":"Plomeros",
    "sg:phone":"+34 981 64 40 43",
    "sg:postcode":"15140",
    "sg:province":"A Coru\u00f1a",
    "wof:name":"Tuberias Del Noroeste S.l.",
    "wof:placetype":"venue"
},
  "geometry": {"coordinates":[-8.46671772,43.3288497925],"type":"Point"}
}