{
  "type": "Feature",
  "properties": {
    "iso:country":"ES",
    "sg:address":"Alemania, 1",
    "sg:city":"Tordesillas",
    "sg:orig_category":"Promotores Constructores",
    "sg:phone":"+34 983 77 07 53",
    "sg:postcode":"47100",
    "sg:province":"Valladolid",
    "wof:name":"Construcciones Y Contratas Lumar S.l.",
    "wof:placetype":"venue"
},
  "geometry": {"coordinates":[-4.9957938194,41.5053901672],"type":"Point"}
}