{
  "type": "Feature",
  "properties": {
    "iso:country":"ES",
    "sg:address":"Calle de Vedado, 54",
    "sg:city":"S. Mateo Gallego",
    "sg:orig_category":"Electricidad: Instaladores",
    "sg:phone":"+34 976 68 40 80",
    "sg:postcode":"50840",
    "sg:province":"Zaragoza",
    "wof:name":"Eiman Electricidad Instalaciones Y Mantenimiento S.l.",
    "wof:placetype":"venue"
},
  "geometry": {"coordinates":[-0.7638419867,41.8295593262],"type":"Point"}
}