{
  "type": "Feature",
  "properties": {
    "iso:country":"ES",
    "sg:address":"Carrer de Dante Alighieri, 123",
    "sg:city":"Barcelona",
    "sg:orig_category":"Frutas, Legumbres Frescas Y Tempranas (al Por Menor)",
    "sg:phone":"+34 934 29 86 13",
    "sg:postcode":"08032",
    "sg:province":"Barcelona",
    "wof:name":"Millan Quilez Vicente",
    "wof:placetype":"venue"
},
  "geometry": {"coordinates":[2.1551139355,41.4265403748],"type":"Point"}
}