{
  "type": "Feature",
  "properties": {
    "iso:country":"ES",
    "sg:address":"Calle de Cabezo De Las Aguas, 57",
    "sg:city":"Alcantarilla",
    "sg:orig_category":"Delegados, Agentes De Tr\u00c1nsito, Auxiliares De Transporte Internacional",
    "sg:phone":"+34 968 89 10 32",
    "sg:postcode":"30820",
    "sg:province":"Murcia",
    "wof:name":"Ruiz Del Cerro Diego Antonio",
    "wof:placetype":"venue"
},
  "geometry": {"coordinates":[-1.2216492891,37.9798278809],"type":"Point"}
}