{
  "type": "Feature",
  "properties": {
    "iso:country":"ES",
    "sg:address":"Carr Doctor Trigo, 13",
    "sg:city":"Eliana",
    "sg:orig_category":"Doctores En Medicina",
    "sg:phone":"+34 962 74 23 37",
    "sg:postcode":"46183",
    "sg:province":"Valencia",
    "wof:name":"Perez Clavijo Jose Maria",
    "wof:placetype":"venue"
},
  "geometry": {"coordinates":[-0.5164250135,39.5597801208],"type":"Point"}
}