{
  "type": "Feature",
  "properties": {
    "addr:full":"Calle de Abades, 13 Madrid Madrid 28012",
    "addr:housenumber":"13",
    "addr:postcode":"madrid;28012",
    "addr:street":"Calle De Abades",
    "iso:country":"ES",
    "sg:address":"Calle de Abades, 13",
    "sg:city":"Madrid",
    "sg:orig_category":"Fabricaci\u00d3n De Ropa De Deportes",
    "sg:phone":"+34 915 30 14 71",
    "sg:postcode":"28012",
    "sg:province":"Madrid",
    "wof:name":"Hernando Pineda Jose Maria",
    "wof:placetype":"venue"
},
  "geometry": {"coordinates":[-3.7059621811,40.4097518921],"type":"Point"}
}