{
  "type": "Feature",
  "properties": {
    "addr:full":"Carrer de Francoli, 7 Constanti Tarragona 43120",
    "addr:housenumber":"7",
    "addr:postcode":"43120",
    "addr:street":"Carrer De Francoli",
    "iso:country":"ES",
    "sg:address":"Carrer de Francoli, 7",
    "sg:city":"Constanti",
    "sg:orig_category":"Reposter\u00cdas",
    "sg:phone":"+34 977 52 22 84",
    "sg:postcode":"43120",
    "sg:province":"Tarragona",
    "wof:name":"Gonzalez Flores Primitiva",
    "wof:placetype":"venue"
},
  "geometry": {"coordinates":[1.2171989679,41.1514434814],"type":"Point"}
}