{
  "type": "Feature",
  "properties": {
    "iso:country":"ES",
    "sg:address":"Carrer de Santa Barbara, 14",
    "sg:city":"Cocentaina",
    "sg:orig_category":"Contenedores (mercanc\u00cdas)",
    "sg:phone":"+34 965 59 14 75",
    "sg:postcode":"03820",
    "sg:province":"Alicante",
    "wof:name":"Garcia Reche Florentino",
    "wof:placetype":"venue"
},
  "geometry": {"coordinates":[-0.4387030005,38.7434043884],"type":"Point"}
}