{
  "type": "Feature",
  "properties": {
    "iso:country":"ES",
    "sg:address":"Carrer de Fusina, 7",
    "sg:city":"Vic",
    "sg:classifiers":[
        {
            "category":"Autos & Motor Vehicles",
            "subcategory":"Automobile Sales",
            "type":"Retail Goods"
        }
    ],
    "sg:phone":"+34 938 86 10 59",
    "sg:postcode":"08500",
    "sg:province":"Barcelona",
    "wof:name":"Autoescuela Sarrio S.c.p.",
    "wof:placetype":"venue"
},
  "geometry": {"coordinates":[2.2572100163,41.9308280945],"type":"Point"}
}