{
  "type": "Feature",
  "properties": {
    "iso:country":"ES",
    "sg:address":"Calle de Manigua, 17",
    "sg:city":"Socuellamos",
    "sg:orig_category":"Ingenier\u00cda, Centros De Estudios (diversos)",
    "sg:phone":"+34 926 53 09 71",
    "sg:postcode":"13630",
    "sg:province":"Ciudad Real",
    "wof:name":"Investigacion Y Obras S.l.",
    "wof:placetype":"venue"
},
  "geometry": {"coordinates":[-2.803374052,39.2832260132],"type":"Point"}
}