{
  "type": "Feature",
  "properties": {
    "addr:full":"Calle de Real, 44 Ponton Valencia 46357",
    "addr:housenumber":"44",
    "addr:postcode":"46357",
    "addr:street":"Calle De Real;Valencia",
    "iso:country":"ES",
    "sg:address":"Calle de Real, 44",
    "sg:city":"Ponton",
    "sg:orig_category":"Panader\u00cdas, Pasteler\u00cdas, Boller\u00cda Industriale (fabricaci\u00d3n, Al Por Mayor)",
    "sg:phone":"+34 962 30 05 43",
    "sg:postcode":"46357",
    "sg:province":"Valencia",
    "wof:name":"Perez Sanchez Santiago",
    "wof:placetype":"venue"
},
  "geometry": {"coordinates":[-1.1222490072,39.4759216309],"type":"Point"}
}