{
  "type": "Feature",
  "properties": {
    "addr:full":"Av Cerdanyola, 52 S. Cugat Valles Barcelona 08172",
    "addr:housenumber":"52",
    "addr:postcode":"08172",
    "addr:street":"Av Cerdanyola;S. Cugat Valles Barcelona",
    "iso:country":"ES",
    "sg:address":"Av Cerdanyola, 52",
    "sg:city":"S. Cugat Valles",
    "sg:orig_category":"Molduras, Junquillos, Listones Y Molduras Perforadas",
    "sg:phone":"+34 936 75 06 02",
    "sg:postcode":"08172",
    "sg:province":"Barcelona",
    "wof:name":"Perez Mu\u00f1oz Fernando",
    "wof:placetype":"venue"
},
  "geometry": {"coordinates":[2.0910019875,41.4738006592],"type":"Point"}
}