{
  "type": "Feature",
  "properties": {
    "iso:country":"ES",
    "sg:address":"Avda Valencia, 15",
    "sg:city":"Ibi",
    "sg:orig_category":"Tubos Y Tuber\u00cdas De Metales Ferrosos (fabricaci\u00d3n, Negocio)",
    "sg:phone":"+34 966 55 31 37",
    "sg:postcode":"03440",
    "sg:province":"Alicante",
    "wof:name":"Bornay S.a.",
    "wof:placetype":"venue"
},
  "geometry": {"coordinates":[-0.595559001,38.6184310913],"type":"Point"}
}