{
  "type": "Feature",
  "properties": {
    "addr:full":"Carr Monges (les), 11 Artesa Segre Lleida 25730",
    "addr:housenumber":"11",
    "addr:postcode":"25730",
    "addr:street":"Carr Monges Les",
    "iso:country":"ES",
    "sg:address":"Carr Monges (les), 11",
    "sg:city":"Artesa Segre",
    "sg:classifiers":[
        {
            "category":"Autos & Motor Vehicles",
            "subcategory":"Automobile Sales",
            "type":"Retail Goods"
        }
    ],
    "sg:phone":"+34 973 40 07 95",
    "sg:postcode":"25730",
    "sg:province":"Lleida",
    "wof:name":"Miro Autoscoles S.l.",
    "wof:placetype":"venue"
},
  "geometry": {"coordinates":[1.0498579741,41.8959960938],"type":"Point"}
}