{
  "type": "Feature",
  "properties": {
    "addr:full":"Carrer de Huelva, 94 Barcelona Barcelona 08020",
    "addr:housenumber":"94",
    "addr:postcode":"08020",
    "addr:street":"Carrer De Huelva",
    "iso:country":"ES",
    "sg:address":"Carrer de Huelva, 94",
    "sg:city":"Barcelona",
    "sg:orig_category":"Peluqueros: De Se\u00d1oras",
    "sg:phone":"+34 933 13 64 20",
    "sg:postcode":"08020",
    "sg:province":"Barcelona",
    "wof:name":"Pi\u00f1ar Castillo Jose",
    "wof:placetype":"venue"
},
  "geometry": {"coordinates":[2.1977889538,41.4184684753],"type":"Point"}
}