{
  "type": "Feature",
  "properties": {
    "addr:full":"Avda Ronda, S/n Aguilar Campoo Palencia 34800",
    "addr:postcode":"34800",
    "addr:street":"Avda Ronda S / N",
    "iso:country":"ES",
    "sg:address":"Avda Ronda, S/n",
    "sg:city":"Aguilar Campoo",
    "sg:orig_category":"Laboratorios Y Cl\u00cdnicas Veterinarias",
    "sg:phone":"+34 979 12 60 34",
    "sg:postcode":"34800",
    "sg:province":"Palencia",
    "wof:name":"Hernandez Pablos Agustin",
    "wof:placetype":"venue"
},
  "geometry": {"coordinates":[-4.2607240677,42.795501709],"type":"Point"}
}