{
  "type": "Feature",
  "properties": {
    "iso:country":"ES",
    "sg:address":"Calle de Rio Atras, 14",
    "sg:city":"Alfacar",
    "sg:orig_category":"Reposter\u00cdas",
    "sg:phone":"+34 958 54 36 08",
    "sg:postcode":"18170",
    "sg:province":"Granada",
    "wof:name":"Rojas Y Lopez S.l.",
    "wof:placetype":"venue"
},
  "geometry": {"coordinates":[-3.5659520626,37.2364120483],"type":"Point"}
}