{
  "type": "Feature",
  "properties": {
    "addr:full":"Urb. San Miguel, S/n A Carida Asturias 33750",
    "addr:housenumber":"/ n",
    "addr:postcode":"33750",
    "addr:street":"Miguel S;A Carida Asturias",
    "iso:country":"ES",
    "sg:address":"Urb. San Miguel, S/n",
    "sg:city":"A Carida",
    "sg:orig_category":"Alimentaci\u00d3n General (al Por Mayor)",
    "sg:phone":"+34 985 47 80 24",
    "sg:postcode":"33750",
    "sg:province":"Asturias",
    "wof:name":"Sociedad Asturiana De Servicios Agropecuarios S.l.",
    "wof:placetype":"venue"
},
  "geometry": {"coordinates":[-6.8270339966,43.5506744385],"type":"Point"}
}