{
  "type": "Feature",
  "properties": {
    "addr:full":"Calle de Fuensanta, 7 Aguilas Murcia 30880",
    "addr:housenumber":"7",
    "addr:postcode":"30880",
    "addr:street":"Calle De Fuensanta",
    "iso:country":"ES",
    "sg:address":"Calle de Fuensanta, 7",
    "sg:city":"Aguilas",
    "sg:orig_category":"Fabricaci\u00d3n De Art\u00cdculos Y Equipos Deportivos Y De Ocio",
    "sg:phone":"+34 968 41 05 92",
    "sg:postcode":"30880",
    "sg:province":"Murcia",
    "wof:name":"Lopez Mu\u00f1iz Margarita",
    "wof:placetype":"venue"
},
  "geometry": {"coordinates":[-1.5853321552,37.4056129456],"type":"Point"}
}