{
  "type": "Feature",
  "properties": {
    "addr:full":"Avda Luis Espada, 24 Verin Ourense 32600",
    "addr:housenumber":"24",
    "addr:postcode":"32600",
    "addr:street":"Avda Luis Espada",
    "iso:country":"ES",
    "sg:address":"Avda Luis Espada, 24",
    "sg:city":"Verin",
    "sg:orig_category":"Asesor\u00cda Sobre Comunicaci\u00d3n De Empresas",
    "sg:phone":"+34 988 59 04 56",
    "sg:postcode":"32600",
    "sg:province":"Ourense",
    "wof:name":"Coverlab Sll",
    "wof:placetype":"venue"
},
  "geometry": {"coordinates":[-7.4384818077,41.940322876],"type":"Point"}
}