{
  "type": "Feature",
  "properties": {
    "addr:full":"Carr Comtes D'urgell, 8 Lleida Lleida 25007",
    "addr:housenumber":"8",
    "addr:postcode":"25007",
    "addr:street":"Carr Comtes D'Urgell",
    "iso:country":"ES",
    "sg:address":"Carr Comtes D'urgell, 8",
    "sg:city":"Lleida",
    "sg:orig_category":"Farmacias",
    "sg:phone":"+34 973 23 72 32",
    "sg:postcode":"25007",
    "sg:province":"Lleida",
    "wof:name":"Marti Torres Montserrat",
    "wof:placetype":"venue"
},
  "geometry": {"coordinates":[0.629602015,41.6205062866],"type":"Point"}
}