{
  "type": "Feature",
  "properties": {
    "addr:full":"Calle de Electrodo (del), 4 Partija-santa Monica Madrid 28529",
    "addr:housenumber":"4",
    "addr:postcode":"28529",
    "addr:street":"Calle De Electrodo Del",
    "iso:country":"ES",
    "sg:address":"Calle de Electrodo (del), 4",
    "sg:city":"Partija-santa Monica",
    "sg:orig_category":"Colchones (fabricaci\u00d3n, Al Por Mayor, Al Por Menor)",
    "sg:phone":"+34 916 66 81 41",
    "sg:postcode":"28529",
    "sg:province":"Madrid",
    "wof:name":"Comunidad Colchonera S.l.",
    "wof:placetype":"venue"
},
  "geometry": {"coordinates":[-3.5102670193,40.314289093],"type":"Point"}
}