{
  "type": "Feature",
  "properties": {
    "iso:country":"ES",
    "sg:address":"Av Rei En Jaume, 70",
    "sg:city":"Cardedeu",
    "sg:orig_category":"Inmobiliaria (agencias)",
    "sg:phone":"+34 938 44 42 67",
    "sg:postcode":"08440",
    "sg:province":"Barcelona",
    "wof:name":"Dinmoges 98 S.l.",
    "wof:placetype":"venue"
},
  "geometry": {"coordinates":[2.3579499722,41.6369781494],"type":"Point"}
}