{
  "type": "Feature",
  "properties": {
    "addr:full":"Calle de Pio Del Rio Hortega, 6 Valladolid Valladolid 47014",
    "addr:housenumber":"6",
    "addr:postcode":"47014",
    "addr:street":"Calle De Pio Del Rio Hortega",
    "iso:country":"ES",
    "sg:address":"Calle de Pio Del Rio Hortega, 6",
    "sg:city":"Valladolid",
    "sg:orig_category":"Cajas Para Embalar",
    "sg:phone":"+34 983 37 89 46",
    "sg:postcode":"47014",
    "sg:province":"Valladolid",
    "wof:name":"Caja Rural Del Duero",
    "wof:placetype":"venue"
},
  "geometry": {"coordinates":[-4.7411670685,41.6510429382],"type":"Point"}
}