{
  "type": "Feature",
  "properties": {
    "addr:full":"Carr Cristobal Colon, 8 Benicarlo Castell\u00f3n 12580",
    "addr:housenumber":"8",
    "addr:postcode":"12580",
    "addr:street":"Carr Cristobal Colon",
    "iso:country":"ES",
    "sg:address":"Carr Cristobal Colon, 8",
    "sg:city":"Benicarlo",
    "sg:orig_category":"Agencias De Viajes",
    "sg:phone":"+34 964 47 32 12",
    "sg:postcode":"12580",
    "sg:province":"Castell\u00f3n",
    "wof:name":"Viajes Equus S.a.",
    "wof:placetype":"venue"
},
  "geometry": {"coordinates":[0.4042100012,40.4457893372],"type":"Point"}
}