{
  "type": "Feature",
  "properties": {
    "iso:country":"ES",
    "sg:address":"Avda Africa (de), 40",
    "sg:city":"Ceuta",
    "sg:orig_category":"Molduras, Junquillos, Listones Y Molduras Perforadas",
    "sg:phone":"+34 956 50 83 08",
    "sg:postcode":"51002",
    "sg:province":"Ceuta",
    "wof:name":"Rios Gomez Esteban",
    "wof:placetype":"venue"
},
  "geometry": {"coordinates":[-5.327395916,35.883934021],"type":"Point"}
}