{
  "type": "Feature",
  "properties": {
    "iso:country":"ES",
    "sg:address":"Calle de Vicente Caballero, 10",
    "sg:city":"Madrid",
    "sg:orig_category":"Rectificaci\u00d3n, Mecanizado, Fresado",
    "sg:phone":"+34 915 04 21 96",
    "sg:postcode":"28007",
    "sg:province":"Madrid",
    "wof:name":"Electronic Data System Espa\u00d1a S.a.",
    "wof:placetype":"venue"
},
  "geometry": {"coordinates":[-3.6684830189,40.4196434021],"type":"Point"}
}