{
  "type": "Feature",
  "properties": {
    "iso:country":"ES",
    "sg:address":"Calle de Colon, 2",
    "sg:city":"Palencia",
    "sg:orig_category":"Teatros Y Salas De Espect\u00c1culos",
    "sg:phone":"+34 979 70 70 84",
    "sg:postcode":"34002",
    "sg:province":"Palencia",
    "wof:name":"Palcintea S.l.",
    "wof:placetype":"venue"
},
  "geometry": {"coordinates":[-4.5314221382,42.0093078613],"type":"Point"}
}