{
  "type": "Feature",
  "properties": {
    "iso:country":"ES",
    "sg:address":"Calle de Viera Y Clavijo, 33",
    "sg:city":"Palmas De Gran Canaria",
    "sg:orig_category":"Arreglo, Reparaci\u00d3n, Piezas Sueltas De Televisi\u00d3n, V\u00cddeo, Hi",
    "sg:phone":"+34 928 36 50 68",
    "sg:postcode":"35002",
    "sg:province":"Las Palmas",
    "wof:name":"Marrero Gonzalez Jose Manuel",
    "wof:placetype":"venue"
},
  "geometry": {"coordinates":[-15.4186887741,28.1082782745],"type":"Point"}
}