{
  "type": "Feature",
  "properties": {
    "iso:country":"ES",
    "sg:address":"Carr Fondandana, S/n",
    "sg:city":"Agramunt",
    "sg:orig_category":"Ense\u00d1anza, Formaci\u00d3n Profesional: Aprendizaje",
    "sg:phone":"+34 973 39 22 72",
    "sg:postcode":"25310",
    "sg:province":"Lleida",
    "wof:name":"Patronat Municipal D'esports",
    "wof:placetype":"venue"
},
  "geometry": {"coordinates":[1.0946799517,41.7837638855],"type":"Point"}
}