{
  "type": "Feature",
  "properties": {
    "addr:full":"Calle de Columela, 9 Madrid Madrid 28001",
    "addr:housenumber":"9",
    "addr:postcode":"madrid;28001",
    "addr:street":"Calle De Columela",
    "iso:country":"ES",
    "sg:address":"Calle de Columela, 9",
    "sg:city":"Madrid",
    "sg:orig_category":"Doctores En Medicina",
    "sg:phone":"+34 915 75 05 13",
    "sg:postcode":"28001",
    "sg:province":"Madrid",
    "wof:name":"Poveda De Agustin Jesus",
    "wof:placetype":"venue"
},
  "geometry": {"coordinates":[-3.6868467331,40.4211463928],"type":"Point"}
}