{
  "type": "Feature",
  "properties": {
    "iso:country":"ES",
    "sg:address":"Avda Fundadores Cooperativa, 20",
    "sg:city":"Malagon",
    "sg:orig_category":"Empresas De Carpinter\u00cda Met\u00c1lica",
    "sg:phone":"+34 926 80 10 27",
    "sg:postcode":"13420",
    "sg:province":"Ciudad Real",
    "wof:name":"Hermanos Gabin Sanchez Sl",
    "wof:placetype":"venue"
},
  "geometry": {"coordinates":[-3.8464949131,39.1705474854],"type":"Point"}
}