{
  "type": "Feature",
  "properties": {
    "iso:country":"ES",
    "sg:address":"Calle de Churruca, S/n",
    "sg:city":"Puente-genil",
    "sg:orig_category":"Electricidad: Instaladores",
    "sg:phone":"+34 957 60 26 33",
    "sg:postcode":"14500",
    "sg:province":"C\u00f3rdoba",
    "wof:name":"Aviles Y Gonzalez Instalaciones S.l.",
    "wof:placetype":"venue"
},
  "geometry": {"coordinates":[-4.7634739876,37.3921508789],"type":"Point"}
}