{
  "type": "Feature",
  "properties": {
    "iso:country":"ES",
    "sg:address":"Calle de Alcalde Luis Pascual, 3",
    "sg:city":"Caudete",
    "sg:orig_category":"Aguas (distribuci\u00d3n, Servicios)",
    "sg:phone":"+34 965 82 76 66",
    "sg:postcode":"02660",
    "sg:province":"Albacete",
    "wof:name":"Sociedad Agraria De Transformacion Sierra Oliva",
    "wof:placetype":"venue"
},
  "geometry": {"coordinates":[-0.9879080057,38.7059211731],"type":"Point"}
}