{
  "type": "Feature",
  "properties": {
    "iso:country":"ES",
    "sg:address":"Calle de Miguel Servet, 9",
    "sg:city":"Valencia",
    "sg:orig_category":"Estudios, Instalaci\u00d3n De Climatizaci\u00d3n",
    "sg:phone":"+34 963 46 14 00",
    "sg:postcode":"46015",
    "sg:province":"Valencia",
    "wof:name":"Icra S.l.",
    "wof:placetype":"venue"
},
  "geometry": {"coordinates":[-0.3936589956,39.4872665405],"type":"Point"}
}