{
  "type": "Feature",
  "properties": {
    "addr:full":"Grup San Jose, 7 Castellon Castell\u00f3n 12005",
    "addr:housenumber":"7",
    "addr:postcode":"12005",
    "addr:street":"San Jose;Castello\u0301N",
    "iso:country":"ES",
    "sg:address":"Grup San Jose, 7",
    "sg:city":"Castellon",
    "sg:orig_category":"Centros Empresariales",
    "sg:phone":"+34 964 72 30 50",
    "sg:postcode":"12005",
    "sg:province":"Castell\u00f3n",
    "wof:name":"Link Broker Correduria De Seguros S.a.",
    "wof:placetype":"venue"
},
  "geometry": {"coordinates":[-0.0297400001,39.9624290466],"type":"Point"}
}