{
  "type": "Feature",
  "properties": {
    "iso:country":"ES",
    "sg:address":"Calle de Villanueva, 24",
    "sg:city":"Madrid",
    "sg:orig_category":"Sociedades, Compa\u00d1\u00cdas Aseguradoras",
    "sg:phone":"+34 914 31 06 43",
    "sg:postcode":"28001",
    "sg:province":"Madrid",
    "wof:name":"Agrupacion Mutual Aseguradora",
    "wof:placetype":"venue"
},
  "geometry": {"coordinates":[-3.6863610744,40.4224243164],"type":"Point"}
}