{
  "type": "Feature",
  "properties": {
    "iso:country":"ES",
    "sg:address":"Carrer de Tomas Rul.lan, 16",
    "sg:city":"Palma",
    "sg:orig_category":"Agencias Y Agentes Comerciales, Representantes",
    "sg:phone":"+34 971 24 91 32",
    "sg:postcode":"07007",
    "sg:province":"Islas Baleares",
    "wof:name":"Cliville Vila Pompeyo",
    "wof:placetype":"venue"
},
  "geometry": {"coordinates":[2.6752688885,39.572593689],"type":"Point"}
}