{
  "type": "Feature",
  "properties": {
    "iso:country":"ES",
    "sg:address":"Calle de Granada, 16",
    "sg:city":"Binefar",
    "sg:orig_category":"Construcciones Met\u00c1licas",
    "sg:phone":"+34 974 43 09 99",
    "sg:postcode":"22500",
    "sg:province":"Huesca",
    "wof:name":"Muro Monesma Ramon",
    "wof:placetype":"venue"
},
  "geometry": {"coordinates":[0.2994869947,41.8439254761],"type":"Point"}
}