{
  "type": "Feature",
  "properties": {
    "iso:country":"ES",
    "sg:address":"Calle de Maldonado, 54",
    "sg:city":"Barrios",
    "sg:orig_category":"Fotograf\u00cda Y Cine: Aparatos, Pel\u00cdculas Y Accesorios (al Por Menor)",
    "sg:phone":"+34 956 62 25 55",
    "sg:postcode":"11370",
    "sg:province":"C\u00e1diz",
    "wof:name":"Andrades Machado Jose Antonio",
    "wof:placetype":"venue"
},
  "geometry": {"coordinates":[-5.4905261993,36.1838951111],"type":"Point"}
}