{
  "type": "Feature",
  "properties": {
    "iso:country":"ES",
    "sg:address":"Calle de Concepcion Arenal, 35",
    "sg:city":"Montijo",
    "sg:orig_category":"Comercio De Piezas De Recambio Y De Accesorios De Veh\u00cdculos, Veh\u00cdculos Industriales",
    "sg:phone":"+34 924 45 58 70",
    "sg:postcode":"06480",
    "sg:province":"Badajoz",
    "wof:name":"Trejo Perez Pedro Jose",
    "wof:placetype":"venue"
},
  "geometry": {"coordinates":[-6.6137089729,38.9066886902],"type":"Point"}
}