{
  "type": "Feature",
  "properties": {
    "addr:full":"Barrio De Las Llamas, 23 Llanes Asturias 33500",
    "addr:housenumber":"23",
    "addr:postcode":"33500",
    "addr:street":"Barrio;Las Llamas",
    "iso:country":"ES",
    "sg:address":"Barrio De Las Llamas, 23",
    "sg:city":"Llanes",
    "sg:orig_category":"Carb\u00d3n, Carb\u00d3n De Madera (al Por Mayor)",
    "sg:phone":"+34 985 40 04 13",
    "sg:postcode":"33500",
    "sg:province":"Asturias",
    "wof:name":"Rivero Revilla Francisco",
    "wof:placetype":"venue"
},
  "geometry": {"coordinates":[-4.7549939156,43.4207191467],"type":"Point"}
}