{
  "type": "Feature",
  "properties": {
    "addr:full":"Rbla Sant Sadurni (de), 3 Montornes Centre Barcelona 08170",
    "addr:postcode":"08170",
    "addr:street":"Rbla Sant Sadurni De 3 Montornes Centre Barcelona",
    "iso:country":"ES",
    "sg:address":"Rbla Sant Sadurni (de), 3",
    "sg:city":"Montornes Centre",
    "sg:orig_category":"Peluquer\u00cdas, Peluquer\u00cda Mixta",
    "sg:phone":"+34 935 68 46 03",
    "sg:postcode":"08170",
    "sg:province":"Barcelona",
    "wof:name":"Bermudez Escribano Francisco",
    "wof:placetype":"venue"
},
  "geometry": {"coordinates":[2.2669279575,41.5417823792],"type":"Point"}
}