{
  "type": "Feature",
  "properties": {
    "iso:country":"ES",
    "sg:address":"Calle de Doctor Lopez, 2",
    "sg:city":"Alfambra",
    "sg:orig_category":"Cerrajer\u00cda, Ferrallista",
    "sg:phone":"+34 978 77 02 02",
    "sg:postcode":"44160",
    "sg:province":"Teruel",
    "wof:name":"Hermanos Herrero Minguijon S.l.",
    "wof:placetype":"venue"
},
  "geometry": {"coordinates":[-1.031883955,40.5464057922],"type":"Point"}
}