{
  "type": "Feature",
  "properties": {
    "addr:full":"Calle de Doctor Villacian, 21 Valladolid Valladolid 47014",
    "addr:housenumber":"21",
    "addr:postcode":"47014",
    "addr:street":"Calle De Doctor Villacian",
    "iso:country":"ES",
    "sg:address":"Calle de Doctor Villacian, 21",
    "sg:city":"Valladolid",
    "sg:orig_category":"Arquitectos",
    "sg:phone":"+34 983 35 41 74",
    "sg:postcode":"47014",
    "sg:province":"Valladolid",
    "wof:name":"Gomez Gonzalez Tomas",
    "wof:placetype":"venue"
},
  "geometry": {"coordinates":[-4.7510261536,41.6383323669],"type":"Point"}
}