{
  "type": "Feature",
  "properties": {
    "addr:full":"Carrer de Ramoneda, 72 Cornella Llobregat Barcelona 08940",
    "addr:housenumber":"72",
    "addr:postcode":"08940",
    "addr:street":"Carrer De Ramoneda",
    "iso:country":"ES",
    "sg:address":"Carrer de Ramoneda, 72",
    "sg:city":"Cornella Llobregat",
    "sg:orig_category":"Cajas De Ahorro",
    "sg:phone":"+34 933 75 19 02",
    "sg:postcode":"08940",
    "sg:province":"Barcelona",
    "wof:name":"Caixa D'estalvis I Pensions De Barcelona",
    "wof:placetype":"venue"
},
  "geometry": {"coordinates":[2.0783131123,41.3630104065],"type":"Point"}
}