{
  "type": "Feature",
  "properties": {
    "addr:full":"Pla\u00c7 Espanya, 4 Gimenells Lleida 25112",
    "addr:postcode":"4 gimenells;25112",
    "iso:country":"ES",
    "sg:address":"Pla\u00c7 Espanya, 4",
    "sg:city":"Gimenells",
    "sg:orig_category":"Ingeniero",
    "sg:phone":"+34 973 74 83 62",
    "sg:postcode":"25112",
    "sg:province":"Lleida",
    "wof:name":"Optima Lan S.l.",
    "wof:placetype":"venue"
},
  "geometry": {"coordinates":[0.3899149895,41.6523666382],"type":"Point"}
}