{
  "type": "Feature",
  "properties": {
    "iso:country":"ES",
    "sg:address":"Calle de Alcala, 389",
    "sg:city":"Madrid",
    "sg:orig_category":"Ropa Para Se\u00d1oras (al Por Menor)",
    "sg:phone":"+34 913 68 03 06",
    "sg:postcode":"28027",
    "sg:province":"Madrid",
    "wof:name":"Dewa De Punto S.l.",
    "wof:placetype":"venue"
},
  "geometry": {"coordinates":[-3.6418259144,40.4361610413],"type":"Point"}
}