{
  "type": "Feature",
  "properties": {
    "addr:full":"Carrer de Faraday, 142 Terrassa Barcelona 08224",
    "addr:housenumber":"142",
    "addr:postcode":"08224",
    "addr:street":"Carrer De Faraday",
    "iso:country":"ES",
    "sg:address":"Carrer de Faraday, 142",
    "sg:city":"Terrassa",
    "sg:orig_category":"Inmobiliaria (agencias)",
    "sg:phone":"+34 937 88 78 01",
    "sg:postcode":"08224",
    "sg:province":"Barcelona",
    "wof:name":"Hemisferi S.a.",
    "wof:placetype":"venue"
},
  "geometry": {"coordinates":[2.0029740334,41.5611343384],"type":"Point"}
}