{
  "type": "Feature",
  "properties": {
    "iso:country":"ES",
    "sg:address":"Barrio De San Antonio, S/n",
    "sg:city":"Pradoluengo",
    "sg:orig_category":"Medias Y Calcetines (fabricaci\u00d3n, Al Por Mayor)",
    "sg:phone":"+34 947 58 66 71",
    "sg:postcode":"09260",
    "sg:province":"Burgos",
    "wof:name":"Diego Santamaria Jimenez Y Dos Mas C.b.",
    "wof:placetype":"venue"
},
  "geometry": {"coordinates":[-3.1845591068,42.3166313171],"type":"Point"}
}