{
  "type": "Feature",
  "properties": {
    "iso:country":"ES",
    "sg:address":"Ctra Carretera Nacional, S/n",
    "sg:city":"Peraltilla",
    "sg:orig_category":"Electrodom\u00c9sticos (al Por Menor)",
    "sg:phone":"+34 974 31 90 74",
    "sg:postcode":"22311",
    "sg:province":"Huesca",
    "wof:name":"Baron Laborda Francisco Javier",
    "wof:placetype":"venue"
},
  "geometry": {"coordinates":[-0.0451489985,42.0957565308],"type":"Point"}
}