{
  "type": "Feature",
  "properties": {
    "iso:country":"ES",
    "sg:address":"Calle de Ramon Y Cajal, 27",
    "sg:city":"Aguilas",
    "sg:orig_category":"Alquiler De V\u00cddeo",
    "sg:phone":"+34 968 41 35 25",
    "sg:postcode":"30880",
    "sg:province":"Murcia",
    "wof:name":"Jimenez Millan Francisco",
    "wof:placetype":"venue"
},
  "geometry": {"coordinates":[-1.5866149664,37.4069786072],"type":"Point"}
}