{
  "type": "Feature",
  "properties": {
    "iso:country":"ES",
    "sg:address":"Ctra. Sojo, S/n",
    "sg:city":"Artziniega",
    "sg:orig_category":"Ba\u00d1os Y Duchas P\u00dablicos",
    "sg:phone":"+34 945 39 66 12",
    "sg:postcode":"01474",
    "sg:province":"\u00c1lava",
    "wof:name":"Ayuntamiento De Artziniega",
    "wof:placetype":"venue"
},
  "geometry": {"coordinates":[-3.1277854443,43.1224098206],"type":"Point"}
}