{
  "type": "Feature",
  "properties": {
    "addr:full":"Treinta Enero 1964, S/n Burgos Burgos 09007",
    "addr:housenumber":"1964 s / n",
    "addr:postcode":"09007",
    "addr:street":"Enero",
    "iso:country":"ES",
    "sg:address":"Treinta Enero 1964, S/n",
    "sg:city":"Burgos",
    "sg:orig_category":"Forja Y Embutici\u00d3n",
    "sg:phone":"+34 947 48 69 23",
    "sg:postcode":"09007",
    "sg:province":"Burgos",
    "wof:name":"Benito Guerrero Teodoro",
    "wof:placetype":"venue"
},
  "geometry": {"coordinates":[-3.6467239857,42.3613395691],"type":"Point"}
}