{
  "type": "Feature",
  "properties": {
    "addr:full":"Calle de San Juan, 4 Arevalo \u00c1vila 05200",
    "addr:housenumber":"4",
    "addr:postcode":"05200",
    "addr:street":"Calle De San Juan",
    "iso:country":"ES",
    "sg:address":"Calle de San Juan, 4",
    "sg:city":"Arevalo",
    "sg:orig_category":"Asociaciones, Organismos Culturales Y Socioeducativos",
    "sg:phone":"+34 920 30 00 37",
    "sg:postcode":"05200",
    "sg:province":"\u00c1vila",
    "wof:name":"Circulo Cultural Mercantil",
    "wof:placetype":"venue"
},
  "geometry": {"coordinates":[-4.7208938599,41.0642547607],"type":"Point"}
}