{
  "type": "Feature",
  "properties": {
    "addr:full":"Calle de Fernando El Santo, 3 Madrid Madrid 28010",
    "addr:housenumber":"3",
    "addr:postcode":"28010",
    "addr:street":"Calle De Fernando El Santo",
    "iso:country":"ES",
    "sg:address":"Calle de Fernando El Santo, 3",
    "sg:city":"Madrid",
    "sg:orig_category":"Art\u00cdculos De Decoraci\u00d3n",
    "sg:phone":"+34 913 19 65 99",
    "sg:postcode":"28010",
    "sg:province":"Madrid",
    "wof:name":"Tres Dise\u00f1o Y Decoracion S.l.",
    "wof:placetype":"venue"
},
  "geometry": {"coordinates":[-3.6944859028,40.4283676147],"type":"Point"}
}