{
  "type": "Feature",
  "properties": {
    "addr:full":"Calle de Padre Ramirez, 1 Conil De La Frontera C\u00e1diz 11140",
    "addr:housenumber":"1",
    "addr:postcode":"11140",
    "addr:street":"Calle De Padre Ramirez",
    "iso:country":"ES",
    "sg:address":"Calle de Padre Ramirez, 1",
    "sg:city":"Conil De La Frontera",
    "sg:orig_category":"Molduras, Junquillos, Listones Y Molduras Perforadas",
    "sg:phone":"+34 956 44 02 80",
    "sg:postcode":"11140",
    "sg:province":"C\u00e1diz",
    "wof:name":"Ramirez Brenes Manuel",
    "wof:placetype":"venue"
},
  "geometry": {"coordinates":[-6.0885109901,36.276763916],"type":"Point"}
}