{
  "type": "Feature",
  "properties": {
    "iso:country":"ES",
    "sg:address":"Avda Estacion (de La), 33",
    "sg:city":"Puente-genil",
    "sg:orig_category":"Fotocopias, Reprograf\u00cda",
    "sg:phone":"+34 957 60 10 58",
    "sg:postcode":"14500",
    "sg:province":"C\u00f3rdoba",
    "wof:name":"Reprogedil S.l.",
    "wof:placetype":"venue"
},
  "geometry": {"coordinates":[-4.7624788284,37.3934669495],"type":"Point"}
}