{
  "type": "Feature",
  "properties": {
    "iso:country":"ES",
    "sg:address":"Avda Marconi, 3",
    "sg:city":"Valencia",
    "sg:orig_category":"Alquiler De V\u00cddeo",
    "sg:phone":"+34 963 59 71 70",
    "sg:postcode":"46014",
    "sg:province":"Valencia",
    "wof:name":"Broadway Imagen S.l.",
    "wof:placetype":"venue"
},
  "geometry": {"coordinates":[-0.4140169919,39.4689254761],"type":"Point"}
}