{
  "type": "Feature",
  "properties": {
    "iso:country":"ES",
    "sg:address":"Calle de Maquina, 1",
    "sg:city":"San Vicente Alcantara",
    "sg:orig_category":"Alimentaci\u00d3n General (al Por Mayor)",
    "sg:phone":"+34 924 41 20 34",
    "sg:postcode":"06500",
    "sg:province":"Badajoz",
    "wof:name":"Purisanal S.l.",
    "wof:placetype":"venue"
},
  "geometry": {"coordinates":[-7.131814003,39.3586235046],"type":"Point"}
}