{
  "type": "Feature",
  "properties": {
    "iso:country":"ES",
    "sg:address":"Fca. Noguez, S/n",
    "sg:city":"Noguez",
    "sg:orig_category":"Agricultores, Agricultores",
    "sg:phone":"+34 923 57 01 67",
    "sg:postcode":"37100",
    "sg:province":"Salamanca",
    "wof:name":"Sucesores De Domiciano Garcia S.a.",
    "wof:placetype":"venue"
},
  "geometry": {"coordinates":[-6.047454834,41.1193809509],"type":"Point"}
}