{
  "type": "Feature",
  "properties": {
    "iso:country":"ES",
    "sg:address":"Calle de Guadiana, 74",
    "sg:city":"Don Benito",
    "sg:orig_category":"Promotores Constructores",
    "sg:phone":"+34 924 80 48 55",
    "sg:postcode":"06400",
    "sg:province":"Badajoz",
    "wof:name":"Casado Aparicio Juliana",
    "wof:placetype":"venue"
},
  "geometry": {"coordinates":[-5.8552889824,38.9569702148],"type":"Point"}
}