{
  "type": "Feature",
  "properties": {
    "addr:full":"Carrer de Balmes, 118 Barcelona Barcelona 08008",
    "addr:housenumber":"118",
    "addr:postcode":"08008",
    "addr:street":"Carrer De Balmes",
    "iso:country":"ES",
    "sg:address":"Carrer de Balmes, 118",
    "sg:city":"Barcelona",
    "sg:orig_category":"M\u00c9dicos: Termomedicina (hidrolog\u00cda Y Climatolog\u00cda M\u00c9dicas)",
    "sg:phone":"+34 934 87 89 07",
    "sg:postcode":"08008",
    "sg:province":"Barcelona",
    "wof:name":"Manantial De Salud Termes S.c.c.l.",
    "wof:placetype":"venue"
},
  "geometry": {"coordinates":[2.1581060886,41.392906189],"type":"Point"}
}