{
  "type": "Feature",
  "properties": {
    "addr:full":"Calle de Txermin, 12 Villabona Guip\u00f9zcoa 20150",
    "addr:housenumber":"12",
    "addr:postcode":"20150",
    "addr:street":"Calle De Txermin;Guipu\u0300Zcoa",
    "iso:country":"ES",
    "sg:address":"Calle de Txermin, 12",
    "sg:city":"Villabona",
    "sg:orig_category":"Herboristas (al Por Menor)",
    "sg:phone":"+34 943 69 20 56",
    "sg:postcode":"20150",
    "sg:province":"Guip\u00f9zcoa",
    "wof:name":"Juantorena Jauregui Bego\u00f1a",
    "wof:placetype":"venue"
},
  "geometry": {"coordinates":[-2.052218914,43.1899795532],"type":"Point"}
}