{
  "type": "Feature",
  "properties": {
    "addr:full":"Calle de Wad Ras, 18 Madrid Madrid 28039",
    "addr:housenumber":"18",
    "addr:postcode":"madrid;28039",
    "addr:street":"Calle De Wad Ras",
    "iso:country":"ES",
    "sg:address":"Calle de Wad Ras, 18",
    "sg:city":"Madrid",
    "sg:orig_category":"Agricultura: Abastecimiento Y Cosechado (negocio)",
    "sg:phone":"+34 913 11 56 22",
    "sg:postcode":"28039",
    "sg:province":"Madrid",
    "wof:name":"Demeter Cultivo S.l.",
    "wof:placetype":"venue"
},
  "geometry": {"coordinates":[-3.7075541019,40.4556350708],"type":"Point"}
}