{
  "type": "Feature",
  "properties": {
    "addr:full":"Calle de Postas, 38 Vitoria-gasteiz \u00c1lava 01004",
    "addr:housenumber":"38",
    "addr:postcode":"01004",
    "addr:street":"Calle De Postas",
    "iso:country":"ES",
    "sg:address":"Calle de Postas, 38",
    "sg:city":"Vitoria-gasteiz",
    "sg:orig_category":"Abogados",
    "sg:phone":"+34 945 23 37 87",
    "sg:postcode":"01004",
    "sg:province":"\u00c1lava",
    "wof:name":"Ruiz De Infante Abogados S.l.",
    "wof:placetype":"venue"
},
  "geometry": {"coordinates":[-2.6690878868,42.8455505371],"type":"Point"}
}