{
  "type": "Feature",
  "properties": {
    "addr:full":"Carrer de Trafalgar (de), 7 Tarragona Tarragona 43004",
    "addr:postcode":"43004",
    "addr:street":"Carrer De Trafalgar De 7",
    "iso:country":"ES",
    "sg:address":"Carrer de Trafalgar (de), 7",
    "sg:city":"Tarragona",
    "sg:orig_category":"Fabricaci\u00d3n, Reparaci\u00d3n Y Mantenimiento De Construcciones Navales Y Fluviales",
    "sg:phone":"+34 977 21 97 21",
    "sg:postcode":"43004",
    "sg:province":"Tarragona",
    "wof:name":"Trempat S. A.",
    "wof:placetype":"venue"
},
  "geometry": {"coordinates":[1.2425010204,41.10987854],"type":"Point"}
}