{
  "type": "Feature",
  "properties": {
    "iso:country":"ES",
    "sg:address":"Pg Germanies (de Les), 24",
    "sg:city":"Gandia",
    "sg:orig_category":"Carnicer\u00cdas, Carnicer\u00cdas",
    "sg:phone":"+34 962 86 27 99",
    "sg:postcode":"46700",
    "sg:province":"Valencia",
    "wof:name":"Perez Gea Bauls Ricardo",
    "wof:placetype":"venue"
},
  "geometry": {"coordinates":[-0.1821160018,38.9656448364],"type":"Point"}
}