{
  "type": "Feature",
  "properties": {
    "iso:country":"ES",
    "sg:address":"Calle de Umbria, 5",
    "sg:city":"Caudiel",
    "sg:orig_category":"Venta, Instalaci\u00d3n De Calefacci\u00d3n",
    "sg:phone":"+34 964 14 42 14",
    "sg:postcode":"12440",
    "sg:province":"Castell\u00f3n",
    "wof:name":"Instalaciones Roca Lizondo S.l.",
    "wof:placetype":"venue"
},
  "geometry": {"coordinates":[-0.566652,39.9478607178],"type":"Point"}
}