{
  "type": "Feature",
  "properties": {
    "addr:full":"Avda Cordoba, 15 Madrid Madrid 28026",
    "addr:housenumber":"15",
    "addr:postcode":"madrid;28026",
    "addr:street":"Avda Cordoba",
    "iso:country":"ES",
    "sg:address":"Avda Cordoba, 15",
    "sg:city":"Madrid",
    "sg:orig_category":"Mec\u00c1nica Y Herramientas De Precisi\u00d3n",
    "sg:phone":"+34 915 00 25 41",
    "sg:postcode":"28026",
    "sg:province":"Madrid",
    "wof:name":"Visual Digital S.l.",
    "wof:placetype":"venue"
},
  "geometry": {"coordinates":[-3.6979711056,40.3844223022],"type":"Point"}
}