{
  "type": "Feature",
  "properties": {
    "addr:full":"Calle de Vi\u00d1edo, 39 Palma Islas Baleares 07014",
    "addr:housenumber":"39",
    "addr:postcode":"07014",
    "addr:street":"Calle De Vin\u0303Edo",
    "iso:country":"ES",
    "sg:address":"Calle de Vi\u00d1edo, 39",
    "sg:city":"Palma",
    "sg:orig_category":"Promotores Constructores",
    "sg:phone":"+34 971 28 09 22",
    "sg:postcode":"07014",
    "sg:province":"Islas Baleares",
    "wof:name":"Joan Magi Busquets S.l.u.",
    "wof:placetype":"venue"
},
  "geometry": {"coordinates":[2.6304728985,39.5751037598],"type":"Point"}
}