{
  "type": "Feature",
  "properties": {
    "addr:full":"Calle de Manuel De Falla, 3 Granada Granada 18005",
    "addr:housenumber":"3",
    "addr:postcode":"18005",
    "addr:street":"Calle De Manuel De Falla",
    "iso:country":"ES",
    "sg:address":"Calle de Manuel De Falla, 3",
    "sg:city":"Granada",
    "sg:orig_category":"Ense\u00d1anza Variada",
    "sg:phone":"+34 958 52 36 78",
    "sg:postcode":"18005",
    "sg:province":"Granada",
    "wof:name":"Galilea Centro De Formacion Y Empleo",
    "wof:placetype":"venue"
},
  "geometry": {"coordinates":[-3.6036379337,37.1703186035],"type":"Point"}
}