{
  "type": "Feature",
  "properties": {
    "addr:full":"Carrer de Plana De Vic, 26 Mataro Barcelona 08303",
    "addr:housenumber":"26",
    "addr:postcode":"08303",
    "addr:street":"Carrer De Plana De Vic",
    "iso:country":"ES",
    "sg:address":"Carrer de Plana De Vic, 26",
    "sg:city":"Mataro",
    "sg:orig_category":"Farmacias",
    "sg:phone":"+34 937 41 49 58",
    "sg:postcode":"08303",
    "sg:province":"Barcelona",
    "wof:name":"Comparfarm S.l.",
    "wof:placetype":"venue"
},
  "geometry": {"coordinates":[2.4245369434,41.5444602966],"type":"Point"}
}