{
  "type": "Feature",
  "properties": {
    "addr:full":"Calle de Imeldo Seris, 96 Santa Cruz De Tenerife Santa Cruz De Tenerife 38003",
    "addr:housenumber":"96",
    "addr:postcode":"38003",
    "addr:street":"Calle De Imeldo Seris",
    "iso:country":"ES",
    "sg:address":"Calle de Imeldo Seris, 96",
    "sg:city":"Santa Cruz De Tenerife",
    "sg:orig_category":"Centros Empresariales",
    "sg:phone":"+34 922 27 52 27",
    "sg:postcode":"38003",
    "sg:province":"Santa Cruz De Tenerife",
    "wof:name":"Acm Consulting Empresa Canarias S.l.",
    "wof:placetype":"venue"
},
  "geometry": {"coordinates":[-16.2539196014,28.467206955],"type":"Point"}
}