{
  "type": "Feature",
  "properties": {
    "iso:country":"ES",
    "sg:address":"Calle de Uruguay, S/n",
    "sg:city":"Alcantarilla",
    "sg:orig_category":"Goma: Productos De Uso Industrial (fabricaci\u00d3n, Al Por Mayor)",
    "sg:phone":"+34 968 89 82 89",
    "sg:postcode":"30820",
    "sg:province":"Murcia",
    "wof:name":"Cauchos Fulgencio De Sande",
    "wof:placetype":"venue"
},
  "geometry": {"coordinates":[-1.1980240345,37.9597854614],"type":"Point"}
}