{
  "type": "Feature",
  "properties": {
    "iso:country":"ES",
    "sg:address":"Ptge Albert Pinyol, 17",
    "sg:city":"Barcelona",
    "sg:orig_category":"Arquitectos",
    "sg:phone":"+34 933 21 60 91",
    "sg:postcode":"08029",
    "sg:province":"Barcelona",
    "wof:name":"Escriba Serra Juan",
    "wof:placetype":"venue"
},
  "geometry": {"coordinates":[2.1407649517,41.384552002],"type":"Point"}
}