{
  "type": "Feature",
  "properties": {
    "addr:full":"Pase Jesuitas, 91 Madrid Madrid 28011",
    "addr:housenumber":"91",
    "addr:postcode":"madrid;28011",
    "addr:street":"Jesuitas",
    "iso:country":"ES",
    "sg:address":"Pase Jesuitas, 91",
    "sg:city":"Madrid",
    "sg:orig_category":"Empresarios",
    "sg:phone":"+34 914 64 85 42",
    "sg:postcode":"28011",
    "sg:province":"Madrid",
    "wof:name":"Metroplac S.l.",
    "wof:placetype":"venue"
},
  "geometry": {"coordinates":[-3.7353749275,40.4060745239],"type":"Point"}
}