{
  "type": "Feature",
  "properties": {
    "addr:full":"Calle de Catedral, 22 San Cristobal De La Laguna Santa Cruz De Tenerife 38204",
    "addr:housenumber":"22",
    "addr:postcode":"38204",
    "addr:street":"Calle De Catedral",
    "iso:country":"ES",
    "sg:address":"Calle de Catedral, 22",
    "sg:city":"San Cristobal De La Laguna",
    "sg:orig_category":"Perfumer\u00cda (al Por Menor)",
    "sg:phone":"+34 922 25 12 95",
    "sg:postcode":"38204",
    "sg:province":"Santa Cruz De Tenerife",
    "wof:name":"Perez Suarez Gregoria Maria",
    "wof:placetype":"venue"
},
  "geometry": {"coordinates":[-16.314956665,28.4844093323],"type":"Point"}
}