{
  "type": "Feature",
  "properties": {
    "addr:full":"Czad Egia De, 57 Donostia-san Sebastian Guip\u00f9zcoa 20012",
    "addr:housenumber":"57",
    "addr:postcode":"20012",
    "iso:country":"ES",
    "sg:address":"Czad Egia De, 57",
    "sg:city":"Donostia-san Sebastian",
    "sg:orig_category":"Centro De Estudios",
    "sg:phone":"+34 943 32 08 09",
    "sg:postcode":"20012",
    "sg:province":"Guip\u00f9zcoa",
    "wof:name":"Thordarson  Susan",
    "wof:placetype":"venue"
},
  "geometry": {"coordinates":[-1.9794000387,43.3173789978],"type":"Point"}
}