{
  "type": "Feature",
  "properties": {
    "iso:country":"ES",
    "sg:address":"Calle de Castillo De Utrera, 19",
    "sg:city":"Sevilla",
    "sg:orig_category":"Inmobiliaria (agencias)",
    "sg:phone":"+34 954 29 69 50",
    "sg:postcode":"41013",
    "sg:province":"Sevilla",
    "sg:website":"www.expofinques.com",
    "wof:name":"Expofinques 2000 S.l.",
    "wof:placetype":"venue"
},
  "geometry": {"coordinates":[-5.9784693718,37.3589630127],"type":"Point"}
}