{
  "type": "Feature",
  "properties": {
    "iso:country":"ES",
    "sg:address":"Calle de Jazmin, 12",
    "sg:city":"Melilla",
    "sg:orig_category":"Perfumer\u00cda, Art\u00cdculos De Ba\u00d1o (fabricaci\u00d3n, Al Por Mayor)",
    "sg:phone":"+34 952 67 70 59",
    "sg:postcode":"52006",
    "sg:province":"Melilla",
    "wof:name":"S M Distribucion Melilla S L",
    "wof:placetype":"venue"
},
  "geometry": {"coordinates":[-2.9414439201,35.2723884583],"type":"Point"}
}