{
  "type": "Feature",
  "properties": {
    "iso:country":"ES",
    "sg:address":"Calle de Venancio Bosco, 2",
    "sg:city":"Castro Urdiales",
    "sg:orig_category":"Guarder\u00cdas",
    "sg:phone":"+34 942 86 35 69",
    "sg:postcode":"39700",
    "sg:province":"Cantabria",
    "wof:name":"Diaz Santamaria Ricardo",
    "wof:placetype":"venue"
},
  "geometry": {"coordinates":[-3.2222840786,43.3830528259],"type":"Point"}
}