{
  "type": "Feature",
  "properties": {
    "iso:country":"ES",
    "sg:address":"Carr Comte De Sallent, 7",
    "sg:city":"Ba\u00d1albufar",
    "sg:orig_category":"Farmacias",
    "sg:phone":"+34 971 61 80 31",
    "sg:postcode":"07191",
    "sg:province":"Islas Baleares",
    "wof:name":"Belenguer Marquez Javier",
    "wof:placetype":"venue"
},
  "geometry": {"coordinates":[2.510710001,39.6866493225],"type":"Point"}
}