{
  "type": "Feature",
  "properties": {
    "iso:country":"ES",
    "sg:address":"Muelle Deport. Pesq., S/n",
    "sg:city":"Rota",
    "sg:orig_category":"Cooperativas Agr\u00cdcolas",
    "sg:phone":"+34 956 81 00 11",
    "sg:postcode":"11520",
    "sg:province":"C\u00e1diz",
    "wof:name":"Sociedad Cooperativa De Pescadores Del Mar De Rota",
    "wof:placetype":"venue"
},
  "geometry": {"coordinates":[-6.3688821793,36.6247940063],"type":"Point"}
}