{
  "type": "Feature",
  "properties": {
    "addr:full":"Carr Nou De Juliol, 5 Ciutadella Menorca Islas Baleares 07760",
    "addr:housenumber":"5",
    "addr:postcode":"07760",
    "addr:street":"Carr Nou De Juliol",
    "iso:country":"ES",
    "sg:address":"Carr Nou De Juliol, 5",
    "sg:city":"Ciutadella Menorca",
    "sg:orig_category":"Compraventa De Antig\u00dcedades",
    "sg:phone":"+34 971 38 40 63",
    "sg:postcode":"07760",
    "sg:province":"Islas Baleares",
    "wof:name":"Mayans Carretero Pedro",
    "wof:placetype":"venue"
},
  "geometry": {"coordinates":[3.8366179466,39.9998397827],"type":"Point"}
}