{
  "type": "Feature",
  "properties": {
    "addr:full":"Rond Prado, 33 Villamayor De Campos Zamora 49131",
    "addr:housenumber":"33",
    "addr:postcode":"49131",
    "addr:street":"Prado",
    "iso:country":"ES",
    "sg:address":"Rond Prado, 33",
    "sg:city":"Villamayor De Campos",
    "sg:orig_category":"Mec\u00c1nico Del Autom\u00d3vil",
    "sg:phone":"+34 980 66 26 06",
    "sg:postcode":"49131",
    "sg:province":"Zamora",
    "wof:name":"Carbajo Ramos Dionisio",
    "wof:placetype":"venue"
},
  "geometry": {"coordinates":[-5.3568291664,41.8984184265],"type":"Point"}
}