{
  "type": "Feature",
  "properties": {
    "addr:full":"Calle de Cadarso, 5 Madrid Madrid 28008",
    "addr:housenumber":"5",
    "addr:postcode":"28008",
    "addr:street":"Calle De Cadarso",
    "iso:country":"ES",
    "sg:address":"Calle de Cadarso, 5",
    "sg:city":"Madrid",
    "sg:orig_category":"Ingeniero",
    "sg:phone":"+34 915 40 11 59",
    "sg:postcode":"28008",
    "sg:province":"Madrid",
    "wof:name":"Palma Tools",
    "wof:placetype":"venue"
},
  "geometry": {"coordinates":[-3.7142798901,40.4216766357],"type":"Point"}
}