{
  "type": "Feature",
  "properties": {
    "iso:country":"ES",
    "sg:address":"Nou, 14",
    "sg:city":"Salitja",
    "sg:orig_category":"Triper\u00cdas",
    "sg:phone":"+34 972 47 33 06",
    "sg:postcode":"17184",
    "sg:province":"Girona",
    "wof:name":"Comercial Salitja S.l.",
    "wof:placetype":"venue"
},
  "geometry": {"coordinates":[2.7462880611,41.9073028564],"type":"Point"}
}