{
  "type": "Feature",
  "properties": {
    "iso:country":"ES",
    "sg:address":"Barr Concha (la), S/n",
    "sg:city":"Concha",
    "sg:orig_category":"Fabricaci\u00d3n, Instalaci\u00d3n Y Reparaci\u00d3n De Bombas",
    "sg:phone":"+34 942 55 50 65",
    "sg:postcode":"39690",
    "sg:province":"Cantabria",
    "wof:name":"Torres Borragan Jose Ramon",
    "wof:placetype":"venue"
},
  "geometry": {"coordinates":[-3.8519039154,43.3698806763],"type":"Point"}
}