{
  "type": "Feature",
  "properties": {
    "addr:full":"Calle de Sancho El Sabio, 21 Vitoria-gasteiz \u00c1lava 01008",
    "addr:housenumber":"21",
    "addr:postcode":"01008",
    "addr:street":"Calle De Sancho El Sabio",
    "iso:country":"ES",
    "sg:address":"Calle de Sancho El Sabio, 21",
    "sg:city":"Vitoria-gasteiz",
    "sg:orig_category":"M\u00c9dicos: Dermatolog\u00cda Y Venereolog\u00cda",
    "sg:phone":"+34 945 24 88 98",
    "sg:postcode":"01008",
    "sg:province":"\u00c1lava",
    "wof:name":"Lauzurica Perez Eduardo",
    "wof:placetype":"venue"
},
  "geometry": {"coordinates":[-2.6804609299,42.8485908508],"type":"Point"}
}