{
  "type": "Feature",
  "properties": {
    "iso:country":"ES",
    "sg:address":"Calle de Corregidor Jose De Pasamonte, 23",
    "sg:city":"Madrid",
    "sg:orig_category":"Molduras, Junquillos, Listones Y Molduras Perforadas",
    "sg:phone":"+34 914 39 30 90",
    "sg:postcode":"28030",
    "sg:province":"Madrid",
    "wof:name":"Perez Garcia Antonio",
    "wof:placetype":"venue"
},
  "geometry": {"coordinates":[-3.6475331783,40.4105834961],"type":"Point"}
}