{
  "type": "Feature",
  "properties": {
    "addr:full":"Calle de Barcelona, 28 Palmas De Gran Canaria Las Palmas 35006",
    "addr:postcode":"35006",
    "addr:street":"Calle De Barcelona 28",
    "iso:country":"ES",
    "sg:address":"Calle de Barcelona, 28",
    "sg:city":"Palmas De Gran Canaria",
    "sg:orig_category":"Supermercados Y Hipermercados",
    "sg:phone":"+34 928 24 68 36",
    "sg:postcode":"35006",
    "sg:province":"Las Palmas",
    "wof:name":"Dinosol Supermercados S.l.",
    "wof:placetype":"venue"
},
  "geometry": {"coordinates":[-15.4336338043,28.1331272125],"type":"Point"}
}