{
  "type": "Feature",
  "properties": {
    "addr:full":"Pase Maritimo Rey De Espa\u00d1a, S/n Fuengirola M\u00e1laga 29640",
    "addr:housenumber":"s / n",
    "addr:postcode":"29640",
    "addr:street":"Ma\u0301Laga",
    "iso:country":"ES",
    "sg:address":"Pase Maritimo Rey De Espa\u00d1a, S/n",
    "sg:city":"Fuengirola",
    "sg:orig_category":"Servicios De Telecomunicaciones",
    "sg:phone":"+34 952 66 09 05",
    "sg:postcode":"29640",
    "sg:province":"M\u00e1laga",
    "wof:name":"Costtel Comunications S.l.",
    "wof:placetype":"venue"
},
  "geometry": {"coordinates":[-4.6191391945,36.5422058105],"type":"Point"}
}