{
  "type": "Feature",
  "properties": {
    "addr:full":"Plaz Tomas Morales, 2 Agaete Las Palmas 35480",
    "addr:housenumber":"2",
    "addr:postcode":"35480",
    "addr:street":"Plaz Tomas Morales",
    "iso:country":"ES",
    "sg:address":"Plaz Tomas Morales, 2",
    "sg:city":"Agaete",
    "sg:orig_category":"Cajas De Ahorro",
    "sg:phone":"+34 928 88 62 10",
    "sg:postcode":"35480",
    "sg:province":"Las Palmas",
    "sg:website":"www.lacaixa.es",
    "wof:name":"Caixa D'estalvis I Pensions De Barcelona",
    "wof:placetype":"venue"
},
  "geometry": {"coordinates":[-15.7000665665,28.099817276],"type":"Point"}
}