{
  "type": "Feature",
  "properties": {
    "iso:country":"ES",
    "sg:address":"Calle de Diderot, 56",
    "sg:city":"Malaga",
    "sg:orig_category":"Ropa Y Accesorios",
    "sg:phone":"+34 952 17 36 50",
    "sg:postcode":"29004",
    "sg:province":"M\u00e1laga",
    "wof:name":"Almacenes Mabisa S.l.",
    "wof:placetype":"venue"
},
  "geometry": {"coordinates":[-4.4744930267,36.6940383911],"type":"Point"}
}