{
  "type": "Feature",
  "properties": {
    "addr:full":"Calle de Justo Vilar, 26 Valencia Valencia 46011",
    "addr:housenumber":"26",
    "addr:postcode":"46011",
    "addr:street":"Calle De Justo Vilar",
    "iso:country":"ES",
    "sg:address":"Calle de Justo Vilar, 26",
    "sg:city":"Valencia",
    "sg:orig_category":"Relojer\u00cda (al Por Menor, Reparaci\u00d3n)",
    "sg:phone":"+34 963 71 71 54",
    "sg:postcode":"46011",
    "sg:province":"Valencia",
    "wof:name":"Juan Eced Francisco",
    "wof:placetype":"venue"
},
  "geometry": {"coordinates":[-0.3317019939,39.4669342041],"type":"Point"}
}