{
  "type": "Feature",
  "properties": {
    "iso:country":"ES",
    "sg:address":"Carrer de Santa Perpetua, 21",
    "sg:city":"Castellar Valles",
    "sg:orig_category":"Molduras, Junquillos, Listones Y Molduras Perforadas",
    "sg:phone":"+34 937 14 61 81",
    "sg:postcode":"08211",
    "sg:province":"Barcelona",
    "wof:name":"Tunninger S.l.",
    "wof:placetype":"venue"
},
  "geometry": {"coordinates":[2.0891530514,41.613407135],"type":"Point"}
}