{
  "type": "Feature",
  "properties": {
    "iso:country":"ES",
    "sg:address":"Pase Revellin (del), 13",
    "sg:city":"Ceuta",
    "sg:orig_category":"Transporte En General",
    "sg:phone":"+34 856 20 04 17",
    "sg:postcode":"51001",
    "sg:province":"Ceuta",
    "wof:name":"Almacenes San Pablo Ceuta S. L.",
    "wof:placetype":"venue"
},
  "geometry": {"coordinates":[-5.3114027977,35.8876914978],"type":"Point"}
}