{
  "type": "Feature",
  "properties": {
    "addr:full":"Calle de Molinos (los), 1 Santa Cruz De Tenerife Santa Cruz De Tenerife 38005",
    "addr:housenumber":"1",
    "addr:postcode":"38005",
    "addr:street":"Calle De Molinos Los",
    "iso:country":"ES",
    "sg:address":"Calle de Molinos (los), 1",
    "sg:city":"Santa Cruz De Tenerife",
    "sg:classifiers":[
        {
            "category":"Manufacturing",
            "subcategory":"Building Materials",
            "type":"Manufacturing & Wholesale Goods"
        }
    ],
    "sg:phone":"+34 922 27 76 96",
    "sg:postcode":"38005",
    "sg:province":"Santa Cruz De Tenerife",
    "sg:tags":[
        "bebidas",
        "para",
        "la",
        "de",
        "y",
        "equipo",
        "industria"
    ],
    "sg:website":"www.sharkiberica.com",
    "wof:name":"Shark Iberia S. L.",
    "wof:placetype":"venue"
},
  "geometry": {"coordinates":[-16.2547550201,28.4639396667],"type":"Point"}
}