{
  "type": "Feature",
  "properties": {
    "addr:full":"Calle de Primero De Mayo, 9 Paiporta Valencia 46200",
    "addr:housenumber":"9",
    "addr:postcode":"46200",
    "addr:street":"Calle De Primero;Mayo",
    "iso:country":"ES",
    "sg:address":"Calle de Primero De Mayo, 9",
    "sg:city":"Paiporta",
    "sg:orig_category":"Estancos",
    "sg:phone":"+34 963 97 11 39",
    "sg:postcode":"46200",
    "sg:province":"Valencia",
    "wof:name":"Sorli Alba Jose",
    "wof:placetype":"venue"
},
  "geometry": {"coordinates":[-0.4188897908,39.4283981323],"type":"Point"}
}