{
  "type": "Feature",
  "properties": {
    "iso:country":"ES",
    "sg:address":"Calle de Generalisimo Franco, 21",
    "sg:city":"Oliva",
    "sg:orig_category":"Cajas De Ahorro",
    "sg:phone":"+34 928 86 87 43",
    "sg:postcode":"35640",
    "sg:province":"Las Palmas",
    "wof:name":"Caja Insular De Ahorros De Canarias",
    "wof:placetype":"venue"
},
  "geometry": {"coordinates":[-13.9269266129,28.612329483],"type":"Point"}
}