{
  "type": "Feature",
  "properties": {
    "addr:full":"Avda Barcelona, S/n Jaen Ja\u00e9n 23006",
    "addr:postcode":"23006",
    "addr:street":"Avda Barcelona S / N Jaen Jae\u0301N",
    "iso:country":"ES",
    "sg:address":"Avda Barcelona, S/n",
    "sg:city":"Jaen",
    "sg:orig_category":"Cajas De Ahorro",
    "sg:phone":"+34 953 27 40 10",
    "sg:postcode":"23006",
    "sg:province":"Ja\u00e9n",
    "wof:name":"Caja De Ahorros Y Monte De Piedad De Cordoba",
    "wof:placetype":"venue"
},
  "geometry": {"coordinates":[-3.7984089851,37.7804336548],"type":"Point"}
}