{
  "type": "Feature",
  "properties": {
    "iso:country":"ES",
    "sg:address":"Avda Constitucion, 35",
    "sg:city":"Campanario",
    "sg:orig_category":"Telas Y Sedas (al Por Menor)",
    "sg:phone":"+34 924 83 13 94",
    "sg:postcode":"06460",
    "sg:province":"Badajoz",
    "wof:name":"Diaz Trenado Maria",
    "wof:placetype":"venue"
},
  "geometry": {"coordinates":[-5.6201739311,38.8617973328],"type":"Point"}
}