{
  "type": "Feature",
  "properties": {
    "addr:full":"Calle de Padura Batalla De, 1 Bilbao Vizcaya 48012",
    "addr:housenumber":"1",
    "addr:postcode":"48012",
    "addr:street":"Calle De Padura Batalla De",
    "iso:country":"ES",
    "sg:address":"Calle de Padura Batalla De, 1",
    "sg:city":"Bilbao",
    "sg:orig_category":"Peluqueros: De Se\u00d1oras",
    "sg:phone":"+34 944 21 08 18",
    "sg:postcode":"48012",
    "sg:province":"Vizcaya",
    "wof:name":"Eugenio Bahamonde - Peluqueria",
    "wof:placetype":"venue"
},
  "geometry": {"coordinates":[-2.9381330013,43.2528533936],"type":"Point"}
}