{
  "type": "Feature",
  "properties": {
    "addr:full":"Pl Castell, 9 Benaguasil Valencia 46180",
    "addr:housenumber":"9",
    "addr:postcode":"46180",
    "addr:street":"Pl Castell",
    "iso:country":"ES",
    "sg:address":"Pl Castell, 9",
    "sg:city":"Benaguasil",
    "sg:orig_category":"Molduras, Junquillos, Listones Y Molduras Perforadas",
    "sg:phone":"+34 962 73 12 65",
    "sg:postcode":"46180",
    "sg:province":"Valencia",
    "wof:name":"Union Musical Benaguasil",
    "wof:placetype":"venue"
},
  "geometry": {"coordinates":[-0.5851539969,39.5945587158],"type":"Point"}
}