{
  "type": "Feature",
  "properties": {
    "addr:full":"Calle de Sevilla, 15 Martos Ja\u00e9n 23600",
    "addr:housenumber":"15",
    "addr:postcode":"23600",
    "addr:street":"Calle De Sevilla;Jae\u0301N",
    "iso:country":"ES",
    "sg:address":"Calle de Sevilla, 15",
    "sg:city":"Martos",
    "sg:orig_category":"Carnicer\u00cdas, Carnicer\u00cdas",
    "sg:phone":"+34 953 55 38 68",
    "sg:postcode":"23600",
    "sg:province":"Ja\u00e9n",
    "wof:name":"Rivilla Vico Pedro Jes\u00d9s",
    "wof:placetype":"venue"
},
  "geometry": {"coordinates":[-3.9704360962,37.7161903381],"type":"Point"}
}