{
  "type": "Feature",
  "properties": {
    "iso:country":"ES",
    "sg:address":"Calle de Embajadores, 21",
    "sg:city":"Madrid",
    "sg:orig_category":"Molduras, Junquillos, Listones Y Molduras Perforadas",
    "sg:phone":"+34 915 30 33 24",
    "sg:postcode":"28012",
    "sg:province":"Madrid",
    "wof:name":"Fernandez Garcia Mario",
    "wof:placetype":"venue"
},
  "geometry": {"coordinates":[-3.7054588795,40.4090690613],"type":"Point"}
}