{
  "type": "Feature",
  "properties": {
    "iso:country":"ES",
    "sg:address":"Cm\u00d1o Raposa, 31",
    "sg:city":"Xesteira",
    "sg:orig_category":"Refiner\u00cdas De Petr\u00d3leo",
    "sg:phone":"+34 986 20 26 87",
    "sg:postcode":"36208",
    "sg:province":"Pontevedra",
    "sg:website":"www.repsol.com",
    "wof:name":"Repsol Ypf S.a.",
    "wof:placetype":"venue"
},
  "geometry": {"coordinates":[-8.7332239151,42.2212409973],"type":"Point"}
}