{
  "type": "Feature",
  "properties": {
    "addr:full":"Carr Albera, 16 Figueres Girona 17600",
    "addr:housenumber":"16",
    "addr:postcode":"17600",
    "addr:street":"Carr Albera",
    "iso:country":"ES",
    "sg:address":"Carr Albera, 16",
    "sg:city":"Figueres",
    "sg:orig_category":"Alimentaci\u00d3n General (al Por Menor)",
    "sg:phone":"+34 972 50 45 10",
    "sg:postcode":"17600",
    "sg:province":"Girona",
    "wof:name":"Oriol Cabano Joan",
    "wof:placetype":"venue"
},
  "geometry": {"coordinates":[2.9585149288,42.2734870911],"type":"Point"}
}