{
  "type": "Feature",
  "properties": {
    "addr:full":"Carr. Mijas, 5 Mijas Costa M\u00e1laga 29649",
    "addr:housenumber":"5",
    "addr:postcode":"29649",
    "addr:street":"Mijas",
    "iso:country":"ES",
    "sg:address":"Carr. Mijas, 5",
    "sg:city":"Mijas Costa",
    "sg:orig_category":"Empresas De Carpinter\u00cda De Madera",
    "sg:phone":"+34 952 47 19 56",
    "sg:postcode":"29649",
    "sg:province":"M\u00e1laga",
    "wof:name":"Jaime Rios Antonio",
    "wof:placetype":"venue"
},
  "geometry": {"coordinates":[-4.6310629845,36.5238952637],"type":"Point"}
}