{
  "type": "Feature",
  "properties": {
    "iso:country":"ES",
    "sg:address":"Ameixeira, 28",
    "sg:city":"Redondela",
    "sg:orig_category":"Equipos De Marcado, Etiquetado",
    "sg:phone":"+34 986 40 04 07",
    "sg:postcode":"36800",
    "sg:province":"Pontevedra",
    "wof:name":"Amoedo Alvarez Jose",
    "wof:placetype":"venue"
},
  "geometry": {"coordinates":[-8.63256073,42.2699813843],"type":"Point"}
}