{
  "type": "Feature",
  "properties": {
    "iso:country":"ES",
    "sg:address":"Calle de Bernardino Obregon, 26",
    "sg:city":"Madrid",
    "sg:orig_category":"Asociaciones Humanitarias, De Cooperaci\u00d3n, De Acci\u00d3n Social",
    "sg:phone":"+34 914 67 70 63",
    "sg:postcode":"28012",
    "sg:province":"Madrid",
    "wof:name":"Fundosa Social Consulting S.a.",
    "wof:placetype":"venue"
},
  "geometry": {"coordinates":[-3.6989121437,40.4025611877],"type":"Point"}
}