{
  "type": "Feature",
  "properties": {
    "addr:full":"Avenida Blas Infantes, 8 Valencina Concepcion Sevilla 41907",
    "addr:housenumber":"8",
    "addr:postcode":"41907",
    "addr:street":"Avenida Blas Infantes",
    "iso:country":"ES",
    "sg:address":"Avenida Blas Infantes, 8",
    "sg:city":"Valencina Concepcion",
    "sg:orig_category":"Cajas De Ahorro",
    "sg:phone":"+34 955 72 72 90",
    "sg:postcode":"41907",
    "sg:province":"Sevilla",
    "sg:website":"www.cajasanfernando.es",
    "wof:name":"Caja San Fernando De Sevilla Y Jerez",
    "wof:placetype":"venue"
},
  "geometry": {"coordinates":[-6.0776147842,37.4170455933],"type":"Point"}
}