{
  "type": "Feature",
  "properties": {
    "iso:country":"ES",
    "sg:address":"Calle de Manteria, 26",
    "sg:city":"Valladolid",
    "sg:orig_category":"Restaurantes",
    "sg:phone":"+34 983 29 03 35",
    "sg:postcode":"47004",
    "sg:province":"Valladolid",
    "wof:name":"Plasencia Velez Jose Antonio",
    "wof:placetype":"venue"
},
  "geometry": {"coordinates":[-4.7221941948,41.6483612061],"type":"Point"}
}