{
  "type": "Feature",
  "properties": {
    "addr:full":"Av Pallaresa, 184 Santa Coloma De Gramenet Barcelona 08921",
    "addr:housenumber":"184",
    "addr:postcode":"08921",
    "addr:street":"Av Pallaresa",
    "iso:country":"ES",
    "sg:address":"Av Pallaresa, 184",
    "sg:city":"Santa Coloma De Gramenet",
    "sg:orig_category":"Conservatorios",
    "sg:phone":"+34 933 91 24 51",
    "sg:postcode":"08921",
    "sg:province":"Barcelona",
    "wof:name":"Ajuntament De Santa Coloma De Gramenet",
    "wof:placetype":"venue"
},
  "geometry": {"coordinates":[2.2034215927,41.4535713196],"type":"Point"}
}