{
  "type": "Feature",
  "properties": {
    "addr:full":"C/ Na Saurina D'enten\u00c7a, 99 Alcoi Alicante 03803",
    "addr:housenumber":"99",
    "addr:postcode":"03803",
    "addr:street":"C /;\u0327A",
    "iso:country":"ES",
    "sg:address":"C/ Na Saurina D'enten\u00c7a, 99",
    "sg:city":"Alcoi",
    "sg:orig_category":"Sociedades, Compa\u00d1\u00cdas Aseguradoras",
    "sg:phone":"+34 965 52 38 56",
    "sg:postcode":"03803",
    "sg:province":"Alicante",
    "wof:name":"Nadal Segui Jose Joaquin",
    "wof:placetype":"venue"
},
  "geometry": {"coordinates":[-0.4769740105,38.7042274475],"type":"Point"}
}