{
  "type": "Feature",
  "properties": {
    "addr:full":"Calle de Trench, 19 Valencia Valencia 46001",
    "addr:housenumber":"19",
    "addr:postcode":"46001",
    "addr:street":"Calle De Trench",
    "iso:country":"ES",
    "sg:address":"Calle de Trench, 19",
    "sg:city":"Valencia",
    "sg:orig_category":"Bisuter\u00cda, Joyer\u00cda, Relojer\u00cda (al Por Menor)",
    "sg:phone":"+34 963 92 32 19",
    "sg:postcode":"46001",
    "sg:province":"Valencia",
    "wof:name":"Segarra Fabuel Miguel",
    "wof:placetype":"venue"
},
  "geometry": {"coordinates":[-0.3772259951,39.4733848572],"type":"Point"}
}