{
  "type": "Feature",
  "properties": {
    "addr:full":"Plaz Constitucion (de La), 1 Cuenca Cuenca 16001",
    "addr:postcode":"16001",
    "iso:country":"ES",
    "sg:address":"Plaz Constitucion (de La), 1",
    "sg:city":"Cuenca",
    "sg:orig_category":"Mudanzas",
    "sg:phone":"+34 969 22 68 20",
    "sg:postcode":"16001",
    "sg:province":"Cuenca",
    "wof:name":"Ca\u00f1ada Hortelano Lorenzo",
    "wof:placetype":"venue"
},
  "geometry": {"coordinates":[-2.1362390518,40.0720710754],"type":"Point"}
}