{
  "type": "Feature",
  "properties": {
    "addr:full":"Calle de Deltebre, 7 Reinosa Cantabria 39200",
    "addr:housenumber":"7",
    "addr:postcode":"39200",
    "addr:street":"Calle De Deltebre",
    "iso:country":"ES",
    "sg:address":"Calle de Deltebre, 7",
    "sg:city":"Reinosa",
    "sg:orig_category":"Florister\u00cdas",
    "sg:phone":"+34 942 75 04 99",
    "sg:postcode":"39200",
    "sg:province":"Cantabria",
    "wof:name":"Alcaraz Heredia Maria",
    "wof:placetype":"venue"
},
  "geometry": {"coordinates":[-4.1364197731,43.0007553101],"type":"Point"}
}