{
  "type": "Feature",
  "properties": {
    "addr:full":"Avda Portugal, Km. 0043,9 Valmojado Toledo 45940",
    "addr:postcode":"45940",
    "addr:street":"Avda Portugal Km. 0043,9",
    "iso:country":"ES",
    "sg:address":"Avda Portugal, Km. 0043,9",
    "sg:city":"Valmojado",
    "sg:orig_category":"Molduras, Junquillos, Listones Y Molduras Perforadas",
    "sg:phone":"+34 918 17 00 87",
    "sg:postcode":"45940",
    "sg:province":"Toledo",
    "wof:name":"Gamaz Joya Juan Domingo",
    "wof:placetype":"venue"
},
  "geometry": {"coordinates":[-4.0948400497,40.2040519714],"type":"Point"}
}