{
  "type": "Feature",
  "properties": {
    "iso:country":"ES",
    "sg:address":"Calle de Doctor Jose-m.sarget, 6",
    "sg:city":"Orihuela",
    "sg:orig_category":"Promotores Constructores",
    "sg:phone":"+34 965 30 04 99",
    "sg:postcode":"03300",
    "sg:province":"Alicante",
    "wof:name":"Conproser Levantina S.l.",
    "wof:placetype":"venue"
},
  "geometry": {"coordinates":[-0.9533984065,38.0698738098],"type":"Point"}
}