{
  "type": "Feature",
  "properties": {
    "addr:full":"Avda Espa\u00d1a (de), 6 San Sebastian De Los Reyes Madrid 28700",
    "addr:postcode":"28700",
    "addr:street":"Avda Espan\u0303A De 6",
    "iso:country":"ES",
    "sg:address":"Avda Espa\u00d1a (de), 6",
    "sg:city":"San Sebastian De Los Reyes",
    "sg:orig_category":"Inform\u00c1tica, Ofim\u00c1tica (estudios, Asesor\u00cda, Ingenier\u00cda, Formaci\u00d3n)",
    "sg:phone":"+34 916 52 47 52",
    "sg:postcode":"28700",
    "sg:province":"Madrid",
    "sg:website":"www.contactordenadores.com",
    "wof:name":"Huv Stores S. L.",
    "wof:placetype":"venue"
},
  "geometry": {"coordinates":[-3.6315460205,40.5448722839],"type":"Point"}
}