{
  "type": "Feature",
  "properties": {
    "iso:country":"ES",
    "sg:address":"Pl Ametlla De Mar, 9",
    "sg:city":"Camarles",
    "sg:orig_category":"Abogados",
    "sg:phone":"+34 977 47 08 47",
    "sg:postcode":"43894",
    "sg:province":"Tarragona",
    "wof:name":"Comes Pons Rosa",
    "wof:placetype":"venue"
},
  "geometry": {"coordinates":[0.6733899713,40.7747612],"type":"Point"}
}