{
  "type": "Feature",
  "properties": {
    "addr:full":"Calle de Teramo, 20 Poligono De Santa Ana Murcia 30310",
    "addr:housenumber":"20 poligono",
    "addr:postcode":"30310",
    "addr:street":"Calle De Teramo",
    "iso:country":"ES",
    "sg:address":"Calle de Teramo, 20",
    "sg:city":"Poligono De Santa Ana",
    "sg:orig_category":"Ingenier\u00cda, Centros De Estudios (diversos)",
    "sg:phone":"+34 968 12 68 05",
    "sg:postcode":"30310",
    "sg:province":"Murcia",
    "wof:name":"Alvarez Ortiz Mauricio",
    "wof:placetype":"venue"
},
  "geometry": {"coordinates":[-1.0486426353,38.2051544189],"type":"Point"}
}