{
  "type": "Feature",
  "properties": {
    "addr:full":"Avda Barqueta (la), 61 Puebla Del Rio Sevilla 41130",
    "addr:housenumber":"61",
    "addr:postcode":"41130",
    "addr:street":"Avda Barqueta La",
    "iso:country":"ES",
    "sg:address":"Avda Barqueta (la), 61",
    "sg:city":"Puebla Del Rio",
    "sg:orig_category":"Empresas De Carpinter\u00cda De Madera",
    "sg:phone":"+34 955 77 09 13",
    "sg:postcode":"41130",
    "sg:province":"Sevilla",
    "wof:name":"Carpinteria Garrido E Hijos S.l.",
    "wof:placetype":"venue"
},
  "geometry": {"coordinates":[-6.0644388199,37.2631225586],"type":"Point"}
}