{
  "type": "Feature",
  "properties": {
    "iso:country":"ES",
    "sg:address":"Pase Berio De, 45",
    "sg:city":"Donostia-san Sebastian",
    "sg:orig_category":"Ingeniero",
    "sg:phone":"+34 943 31 40 01",
    "sg:postcode":"20018",
    "sg:province":"Guip\u00f9zcoa",
    "wof:name":"4mih S.l.",
    "wof:placetype":"venue"
},
  "geometry": {"coordinates":[-2.002952,43.283684],"type":"Point"}
}