{
  "type": "Feature",
  "properties": {
    "iso:country":"ES",
    "sg:address":"Avda Dos De Mayo (del), 26",
    "sg:city":"Mostoles",
    "sg:orig_category":"Carnicer\u00cdas, Carnicer\u00cdas",
    "sg:phone":"+34 916 13 80 04",
    "sg:postcode":"28934",
    "sg:province":"Madrid",
    "wof:name":"Prieto De La Calle Juan Carlos",
    "wof:placetype":"venue"
},
  "geometry": {"coordinates":[-3.8672060966,40.3208465576],"type":"Point"}
}