{
  "type": "Feature",
  "properties": {
    "addr:full":"Calle de Luis Planelles, 41 Valdemoro Madrid 28340",
    "addr:housenumber":"41",
    "addr:postcode":"28340",
    "addr:street":"Calle De Luis Planelles",
    "iso:country":"ES",
    "sg:address":"Calle de Luis Planelles, 41",
    "sg:city":"Valdemoro",
    "sg:orig_category":"Adaptaciones, Acondicionamientos Especiales Para Veh\u00cdculos, Veh\u00cdculos Industriales",
    "sg:phone":"+34 918 08 33 46",
    "sg:postcode":"28340",
    "sg:province":"Madrid",
    "wof:name":"Tapiceria Tellez S.l.",
    "wof:placetype":"venue"
},
  "geometry": {"coordinates":[-3.6798141003,40.1884346008],"type":"Point"}
}