{
  "type": "Feature",
  "properties": {
    "addr:full":"Carr Horta (de L'), 8 Grau I Platja Valencia 46730",
    "addr:housenumber":"8",
    "addr:postcode":"46730",
    "addr:street":"Carr Horta De L '",
    "iso:country":"ES",
    "sg:address":"Carr Horta (de L'), 8",
    "sg:city":"Grau I Platja",
    "sg:orig_category":"Agencias Y Agentes Comerciales, Representantes",
    "sg:phone":"+34 962 84 65 88",
    "sg:postcode":"46730",
    "sg:province":"Valencia",
    "wof:name":"Abajo Sanz Ana",
    "wof:placetype":"venue"
},
  "geometry": {"coordinates":[-0.139566,38.951736],"type":"Point"}
}