{
  "type": "Feature",
  "properties": {
    "addr:full":"Calle de Gran Via De Agustin Arguelles, 12 Ribadesella Asturias 33560",
    "addr:housenumber":"12",
    "addr:postcode":"33560",
    "addr:street":"Calle De Gran Via De Agustin Arguelles",
    "iso:country":"ES",
    "sg:address":"Calle de Gran Via De Agustin Arguelles, 12",
    "sg:city":"Ribadesella",
    "sg:orig_category":"Loter\u00cda Y T\u00d3mbola",
    "sg:phone":"+34 985 85 83 24",
    "sg:postcode":"33560",
    "sg:province":"Asturias",
    "wof:name":"Cabo Fernandez Pilar De",
    "wof:placetype":"venue"
},
  "geometry": {"coordinates":[-5.0589909554,43.4618492126],"type":"Point"}
}