{
  "type": "Feature",
  "properties": {
    "addr:full":"Carrer de Montseny, 44 Sabadell Barcelona 08208",
    "addr:housenumber":"44",
    "addr:postcode":"08208",
    "addr:street":"Carrer De Montseny",
    "iso:country":"ES",
    "sg:address":"Carrer de Montseny, 44",
    "sg:city":"Sabadell",
    "sg:orig_category":"Abogados",
    "sg:phone":"+34 937 24 33 03",
    "sg:postcode":"08208",
    "sg:province":"Barcelona",
    "wof:name":"Mor Pallares David",
    "wof:placetype":"venue"
},
  "geometry": {"coordinates":[2.1052370071,41.5551948547],"type":"Point"}
}