{
  "type": "Feature",
  "properties": {
    "addr:full":"Avda Schulz, 49 Gijon Asturias 33208",
    "addr:housenumber":"49",
    "addr:postcode":"33208",
    "addr:street":"Avda Schulz",
    "iso:country":"ES",
    "sg:address":"Avda Schulz, 49",
    "sg:city":"Gijon",
    "sg:orig_category":"Agencias De Viajes",
    "sg:phone":"+34 985 99 00 07",
    "sg:postcode":"33208",
    "sg:province":"Asturias",
    "sg:website":"www.viajeseroski.es",
    "wof:name":"Viajes Eroski S.a.",
    "wof:placetype":"venue"
},
  "geometry": {"coordinates":[-5.6653652191,43.5336112976],"type":"Point"}
}