{
  "type": "Feature",
  "properties": {
    "addr:full":"Major, 1 Belltall Tarragona 43413",
    "addr:housenumber":"1",
    "addr:postcode":"43413",
    "addr:street":"Major",
    "iso:country":"ES",
    "sg:address":"Major, 1",
    "sg:city":"Belltall",
    "sg:orig_category":"Administraciones Regionales, Departamentales Y Locales",
    "sg:phone":"+34 977 89 27 00",
    "sg:postcode":"43413",
    "sg:province":"Tarragona",
    "wof:name":"Ajuntament De Passanant",
    "wof:placetype":"venue"
},
  "geometry": {"coordinates":[1.1865181923,41.5044555664],"type":"Point"}
}