{
  "type": "Feature",
  "properties": {
    "addr:full":"Calle de Luis Benitez Inglott, 10 Palmas De Gran Canaria Las Palmas 35011",
    "addr:housenumber":"10",
    "addr:postcode":"35011",
    "addr:street":"Calle De Luis Benitez Inglott",
    "iso:country":"ES",
    "sg:address":"Calle de Luis Benitez Inglott, 10",
    "sg:city":"Palmas De Gran Canaria",
    "sg:orig_category":"Centros De Educaci\u00d3n Especial",
    "sg:phone":"+34 928 22 02 25",
    "sg:postcode":"35011",
    "sg:province":"Las Palmas",
    "wof:name":"Gobierno De Canarias-c.e.i.p. Gran Canaria",
    "wof:placetype":"venue"
},
  "geometry": {"coordinates":[-15.4387407303,28.1186733246],"type":"Point"}
}