{
  "type": "Feature",
  "properties": {
    "iso:country":"ES",
    "sg:address":"Calle de Luis Misson, 12",
    "sg:city":"Madrid",
    "sg:orig_category":"Guarder\u00cdas",
    "sg:phone":"+34 913 11 52 92",
    "sg:postcode":"28039",
    "sg:province":"Madrid",
    "wof:name":"Obra Misionera De Jesus Y Maria",
    "wof:placetype":"venue"
},
  "geometry": {"coordinates":[-3.7057740688,40.4590988159],"type":"Point"}
}