{
  "type": "Feature",
  "properties": {
    "addr:full":"Calle de Lorca, 12 Cehegin Murcia 30430",
    "addr:housenumber":"12",
    "addr:postcode":"30430",
    "addr:street":"Calle De Lorca",
    "iso:country":"ES",
    "sg:address":"Calle de Lorca, 12",
    "sg:city":"Cehegin",
    "sg:orig_category":"Art\u00cdculos Funerarios (al Por Menor)",
    "sg:phone":"+34 968 74 03 90",
    "sg:postcode":"30430",
    "sg:province":"Murcia",
    "wof:name":"Fernandez Ponce Joaquin",
    "wof:placetype":"venue"
},
  "geometry": {"coordinates":[-1.7972929478,38.0901412964],"type":"Point"}
}