{
  "type": "Feature",
  "properties": {
    "addr:full":"Av Josep Maria Sentis, 14 Riudoms Tarragona 43330",
    "addr:housenumber":"14",
    "addr:postcode":"43330",
    "addr:street":"Av Josep Maria Sentis",
    "iso:country":"ES",
    "sg:address":"Av Josep Maria Sentis, 14",
    "sg:city":"Riudoms",
    "sg:orig_category":"Empresas De Pintura Y Revestimientos",
    "sg:phone":"+34 977 85 05 67",
    "sg:postcode":"43330",
    "sg:province":"Tarragona",
    "wof:name":"Nolla Ferran Jose",
    "wof:placetype":"venue"
},
  "geometry": {"coordinates":[1.0541909933,41.1382713318],"type":"Point"}
}