{
  "type": "Feature",
  "properties": {
    "addr:full":"Calle de Corrida, 46 Gijon Asturias 33206",
    "addr:housenumber":"46",
    "addr:postcode":"33206",
    "addr:street":"Calle De Corrida",
    "iso:country":"ES",
    "sg:address":"Calle de Corrida, 46",
    "sg:city":"Gijon",
    "sg:orig_category":"Abogados",
    "sg:phone":"+34 985 34 36 20",
    "sg:postcode":"33206",
    "sg:province":"Asturias",
    "wof:name":"Vega-arango Vi\u00f1a Margarita",
    "wof:placetype":"venue"
},
  "geometry": {"coordinates":[-5.6631689072,43.5398521423],"type":"Point"}
}