{
  "type": "Feature",
  "properties": {
    "addr:full":"Calle de Duquesa Villahermosa, 28 Zaragoza Zaragoza 50010",
    "addr:housenumber":"28",
    "addr:postcode":"50010",
    "addr:street":"Calle De Duquesa Villahermosa",
    "iso:country":"ES",
    "sg:address":"Calle de Duquesa Villahermosa, 28",
    "sg:city":"Zaragoza",
    "sg:orig_category":"Organizaciones Internacionales",
    "sg:phone":"+34 976 34 84 52",
    "sg:postcode":"50010",
    "sg:province":"Zaragoza",
    "wof:name":"Fundacion Intered",
    "wof:placetype":"venue"
},
  "geometry": {"coordinates":[-0.9016522169,41.6485290527],"type":"Point"}
}