{
  "type": "Feature",
  "properties": {
    "iso:country":"ES",
    "sg:address":"Calle de Jaen, S/n",
    "sg:city":"Trebujena",
    "sg:orig_category":"Mec\u00c1nico Del Autom\u00d3vil",
    "sg:phone":"+34 956 39 52 55",
    "sg:postcode":"11560",
    "sg:province":"C\u00e1diz",
    "wof:name":"Talleres Manuel Silva S.l.",
    "wof:placetype":"venue"
},
  "geometry": {"coordinates":[-6.1706137657,36.8705291748],"type":"Point"}
}