{
  "type": "Feature",
  "properties": {
    "addr:full":"Calle de Juan Mambrilla, 12 Valladolid Valladolid 47003",
    "addr:housenumber":"12",
    "addr:postcode":"47003",
    "addr:street":"Calle De Juan Mambrilla",
    "iso:country":"ES",
    "sg:address":"Calle de Juan Mambrilla, 12",
    "sg:city":"Valladolid",
    "sg:orig_category":"Consultor\u00cdas Diversas",
    "sg:phone":"+34 983 21 83 60",
    "sg:postcode":"47003",
    "sg:province":"Valladolid",
    "wof:name":"Gestion Cim Consultores S.l.",
    "wof:placetype":"venue"
},
  "geometry": {"coordinates":[-4.7203979492,41.6538124084],"type":"Point"}
}