{
  "type": "Feature",
  "properties": {
    "addr:full":"Carrer de Radas, 2 Barcelona Barcelona 08004",
    "addr:housenumber":"2",
    "addr:postcode":"08004",
    "addr:street":"Carrer De Radas",
    "iso:country":"ES",
    "sg:address":"Carrer de Radas, 2",
    "sg:city":"Barcelona",
    "sg:orig_category":"Inmobiliaria (agencias)",
    "sg:phone":"+34 933 24 94 78",
    "sg:postcode":"08004",
    "sg:province":"Barcelona",
    "wof:name":"Graucla S.l.",
    "wof:placetype":"venue"
},
  "geometry": {"coordinates":[2.1608099937,41.3737564087],"type":"Point"}
}