{
  "type": "Feature",
  "properties": {
    "addr:full":"Avda Cervantes (de), 25 Granada Granada 18008",
    "addr:housenumber":"25",
    "addr:postcode":"18008",
    "addr:street":"Avda Cervantes De",
    "iso:country":"ES",
    "sg:address":"Avda Cervantes (de), 25",
    "sg:city":"Granada",
    "sg:orig_category":"Inmobiliaria (agencias)",
    "sg:phone":"+34 958 12 00 64",
    "sg:postcode":"18008",
    "sg:province":"Granada",
    "sg:website":"www.unicasa.es",
    "wof:name":"Union Intermediacion Financiera S.l.",
    "wof:placetype":"venue"
},
  "geometry": {"coordinates":[-3.58832407,37.1646881104],"type":"Point"}
}