{
  "type": "Feature",
  "properties": {
    "iso:country":"ES",
    "sg:address":"Calle de Sol, 16",
    "sg:city":"Villanueva Cordoba",
    "sg:orig_category":"Cristaler\u00cdas",
    "sg:phone":"+34 957 12 19 01",
    "sg:postcode":"14440",
    "sg:province":"C\u00f3rdoba",
    "wof:name":"R.a. Cris-marc S.l.",
    "wof:placetype":"venue"
},
  "geometry": {"coordinates":[-4.6250481606,38.3216400146],"type":"Point"}
}