{
  "type": "Feature",
  "properties": {
    "iso:country":"ES",
    "sg:address":"Carrer de Fiveller, 24",
    "sg:city":"Sabadell",
    "sg:orig_category":"Empresas De Limpieza",
    "sg:phone":"+34 937 12 12 99",
    "sg:postcode":"08205",
    "sg:province":"Barcelona",
    "wof:name":"Centro De Servicios Y Limpiezas Patena S.l.",
    "wof:placetype":"venue"
},
  "geometry": {"coordinates":[2.105850935,41.5396728516],"type":"Point"}
}