{
  "type": "Feature",
  "properties": {
    "iso:country":"ES",
    "sg:address":"Calle de Poeta Campos Vassallo, 43",
    "sg:city":"Alacant",
    "sg:orig_category":"Formaci\u00d3n Continuada (variada)",
    "sg:phone":"+34 965 21 42 70",
    "sg:postcode":"03004",
    "sg:province":"Alicante",
    "wof:name":"Sanchez Fuster Joan Josep",
    "wof:placetype":"venue"
},
  "geometry": {"coordinates":[-0.4883700013,38.3492584229],"type":"Point"}
}