{
  "type": "Feature",
  "properties": {
    "addr:full":"Calle de Isaac Peral, 7 Le\u00f3n Le\u00f3n 24009",
    "addr:housenumber":"7",
    "addr:postcode":"24009",
    "addr:street":"Calle De Isaac Peral;Leo\u0301N",
    "iso:country":"ES",
    "sg:address":"Calle de Isaac Peral, 7",
    "sg:city":"Le\u00f3n",
    "sg:orig_category":"Patatas (al Por Mayor)",
    "sg:phone":"+34 987 20 87 63",
    "sg:postcode":"24009",
    "sg:province":"Le\u00f3n",
    "wof:name":"Garcia Martinez Pedro",
    "wof:placetype":"venue"
},
  "geometry": {"coordinates":[-5.5855278969,42.5927124023],"type":"Point"}
}