{
  "type": "Feature",
  "properties": {
    "addr:full":"Calle de Sorolla, 25 Cadiz C\u00e1diz 11010",
    "addr:housenumber":"25",
    "addr:postcode":"11010",
    "addr:street":"Calle De Sorolla",
    "iso:country":"ES",
    "sg:address":"Calle de Sorolla, 25",
    "sg:city":"Cadiz",
    "sg:orig_category":"Panader\u00cdas, Panader\u00cdas",
    "sg:phone":"+34 956 25 42 02",
    "sg:postcode":"11010",
    "sg:province":"C\u00e1diz",
    "wof:name":"Sucesores De Manuel Ruiz Garcia S. L.",
    "wof:placetype":"venue"
},
  "geometry": {"coordinates":[-6.2730941772,36.5039024353],"type":"Point"}
}