{
  "type": "Feature",
  "properties": {
    "addr:full":"Carr Arzobispo Reig, 4 Oliva Valencia 46780",
    "addr:housenumber":"4",
    "addr:postcode":"46780",
    "addr:street":"Carr Arzobispo Reig",
    "iso:country":"ES",
    "sg:address":"Carr Arzobispo Reig, 4",
    "sg:city":"Oliva",
    "sg:orig_category":"Productores Recolectores, Venta Directa De Vinos",
    "sg:phone":"+34 962 85 14 69",
    "sg:postcode":"46780",
    "sg:province":"Valencia",
    "wof:name":"Marti Ivars Antonio",
    "wof:placetype":"venue"
},
  "geometry": {"coordinates":[-0.1241109967,38.9217185974],"type":"Point"}
}