{
  "type": "Feature",
  "properties": {
    "addr:full":"Avda Castilla Y Leon, 16 Burgos Burgos 09006",
    "addr:housenumber":"16",
    "addr:postcode":"09006",
    "addr:street":"Avda Castilla Y Leon",
    "iso:country":"ES",
    "sg:address":"Avda Castilla Y Leon, 16",
    "sg:city":"Burgos",
    "sg:orig_category":"Ingeniero",
    "sg:phone":"+34 947 22 46 60",
    "sg:postcode":"09006",
    "sg:province":"Burgos",
    "wof:name":"Manso Moneo Miguel Angel",
    "wof:placetype":"venue"
},
  "geometry": {"coordinates":[-3.683257103,42.3476028442],"type":"Point"}
}