{
  "type": "Feature",
  "properties": {
    "addr:full":"Avda Ca\u00d1ada (de La), 15 Coslada Madrid 28820",
    "addr:housenumber":"15",
    "addr:postcode":"28820",
    "addr:street":"Avda Can\u0303Ada De La",
    "iso:country":"ES",
    "sg:address":"Avda Ca\u00d1ada (de La), 15",
    "sg:city":"Coslada",
    "sg:orig_category":"Cristaler\u00cdas",
    "sg:phone":"+34 916 72 92 60",
    "sg:postcode":"28820",
    "sg:province":"Madrid",
    "wof:name":"Roman Luna Julio",
    "wof:placetype":"venue"
},
  "geometry": {"coordinates":[-3.5375680923,40.4264640808],"type":"Point"}
}