{
  "type": "Feature",
  "properties": {
    "addr:full":"Calle de Monte Perdido, 6 Arganda Madrid 28500",
    "addr:housenumber":"6",
    "addr:postcode":"28500",
    "addr:street":"Calle De Monte Perdido",
    "iso:country":"ES",
    "sg:address":"Calle de Monte Perdido, 6",
    "sg:city":"Arganda",
    "sg:orig_category":"Laboratorios Y Cl\u00cdnicas Veterinarias",
    "sg:phone":"+34 918 70 20 05",
    "sg:postcode":"28500",
    "sg:province":"Madrid",
    "wof:name":"Monte Ararat S.l.",
    "wof:placetype":"venue"
},
  "geometry": {"coordinates":[-3.4790289402,40.3153572083],"type":"Point"}
}