{
  "type": "Feature",
  "properties": {
    "addr:full":"Calle de San Sebastian, 30 Torrenueva Ciudad Real 13740",
    "addr:housenumber":"30",
    "addr:postcode":"13740",
    "addr:street":"Calle De San Sebastian",
    "iso:country":"ES",
    "sg:address":"Calle de San Sebastian, 30",
    "sg:city":"Torrenueva",
    "sg:orig_category":"M\u00c9dicos: Estomatolog\u00cda",
    "sg:phone":"+34 926 34 40 60",
    "sg:postcode":"13740",
    "sg:province":"Ciudad Real",
    "wof:name":"Chaves Paz Carlos",
    "wof:placetype":"venue"
},
  "geometry": {"coordinates":[-3.361068964,38.6414413452],"type":"Point"}
}