{
  "type": "Feature",
  "properties": {
    "addr:full":"Calle de Isabel Rodriguez, 5 Pozoantiguo Zamora 49835",
    "addr:housenumber":"5",
    "addr:postcode":"49835",
    "addr:street":"Calle De Isabel Rodriguez;Zamora",
    "iso:country":"ES",
    "sg:address":"Calle de Isabel Rodriguez, 5",
    "sg:city":"Pozoantiguo",
    "sg:orig_category":"Electricidad: Instaladores",
    "sg:phone":"+34 980 69 64 62",
    "sg:postcode":"49835",
    "sg:province":"Zamora",
    "wof:name":"Fabricados Industriales Alema S.l.",
    "wof:placetype":"venue"
},
  "geometry": {"coordinates":[-5.4369268417,41.5981788635],"type":"Point"}
}