{
  "type": "Feature",
  "properties": {
    "addr:full":"Calle de San Valero, 14 Cari\u00f1ena Zaragoza 50400",
    "addr:housenumber":"14",
    "addr:postcode":"50400",
    "addr:street":"Calle De San Valero",
    "iso:country":"ES",
    "sg:address":"Calle de San Valero, 14",
    "sg:city":"Cari\u00f1ena",
    "sg:orig_category":"Productores Recolectores, Venta Directa De Vinos",
    "sg:phone":"+34 976 62 19 68",
    "sg:postcode":"50400",
    "sg:province":"Zaragoza",
    "sg:website":"www.solardeurbezo.es",
    "wof:name":"Bodegas Solar De Urbezo S.l.",
    "wof:placetype":"venue"
},
  "geometry": {"coordinates":[-1.2218519449,41.3389892578],"type":"Point"}
}