{
  "type": "Feature",
  "properties": {
    "iso:country":"ES",
    "sg:address":"Talaia Poligonoa, 3",
    "sg:city":"Arragua",
    "sg:orig_category":"Reciclaje Y Tratamiento De Desechos Varios",
    "sg:phone":"+34 943 49 44 59",
    "sg:postcode":"20180",
    "sg:province":"Guip\u00f9zcoa",
    "wof:name":"Recuperaciones Argenticas Gar S.l.",
    "wof:placetype":"venue"
},
  "geometry": {"coordinates":[-1.8629590273,43.2992401123],"type":"Point"}
}