{
  "type": "Feature",
  "properties": {
    "iso:country":"ES",
    "sg:address":"Urb. Los Almendros, 3",
    "sg:city":"Zamora",
    "sg:orig_category":"Florister\u00cdas",
    "sg:phone":"+34 980 51 12 82",
    "sg:postcode":"49005",
    "sg:province":"Zamora",
    "wof:name":"Campo Blanco Celso Del",
    "wof:placetype":"venue"
},
  "geometry": {"coordinates":[-6.6216888428,42.0623054504],"type":"Point"}
}