{
  "type": "Feature",
  "properties": {
    "iso:country":"ES",
    "sg:address":"Calle de Calvo Sotelo, 22",
    "sg:city":"Morales Rey",
    "sg:orig_category":"Cajas De Ahorro",
    "sg:phone":"+34 980 65 10 28",
    "sg:postcode":"49693",
    "sg:province":"Zamora",
    "wof:name":"Caja Espa\u00f1a De Inversiones Caja De Ahorros Y Monte De Piedad",
    "wof:placetype":"venue"
},
  "geometry": {"coordinates":[-5.7877969742,42.0686416626],"type":"Point"}
}