{
  "type": "Feature",
  "properties": {
    "addr:full":"Calle de La Paz, 23 Barakaldo Vizcaya 48903",
    "addr:housenumber":"23",
    "addr:postcode":"48903",
    "addr:street":"Calle De La Paz",
    "iso:country":"ES",
    "sg:address":"Calle de La Paz, 23",
    "sg:city":"Barakaldo",
    "sg:orig_category":"Iglesia Cat\u00d3lica",
    "sg:phone":"+34 944 90 26 29",
    "sg:postcode":"48903",
    "sg:province":"Vizcaya",
    "wof:name":"Parroquia Ntra S\u00f1ra De La Paz De Barakal",
    "wof:placetype":"venue"
},
  "geometry": {"coordinates":[-2.9885840416,43.2807693481],"type":"Point"}
}