{
  "type": "Feature",
  "properties": {
    "iso:country":"ES",
    "sg:address":"Avda Atlantida, 50",
    "sg:city":"Vigo",
    "sg:orig_category":"Caf\u00c9s, Bares, Cervecer\u00cdas",
    "sg:phone":"+34 986 20 19 95",
    "sg:postcode":"36208",
    "sg:province":"Pontevedra",
    "wof:name":"Blanco Leiros Manuel",
    "wof:placetype":"venue"
},
  "geometry": {"coordinates":[-8.7568454742,42.222618103],"type":"Point"}
}