{
  "type": "Feature",
  "properties": {
    "iso:country":"ES",
    "sg:address":"Avda Andalucia, 67",
    "sg:city":"Cadiz",
    "sg:orig_category":"Cajas De Ahorro",
    "sg:phone":"+34 956 25 96 61",
    "sg:postcode":"11007",
    "sg:province":"C\u00e1diz",
    "sg:website":"www.lacaixa.es",
    "wof:name":"Caixa D'estalvis I Pensions De Barcelona",
    "wof:placetype":"venue"
},
  "geometry": {"coordinates":[-6.2840847969,36.5190925598],"type":"Point"}
}