{
  "type": "Feature",
  "properties": {
    "addr:full":"Pase Comandante Fortea, 48 Madrid Madrid 28008",
    "addr:housenumber":"48",
    "addr:postcode":"madrid;28008",
    "addr:street":"Comandante Fortea",
    "iso:country":"ES",
    "sg:address":"Pase Comandante Fortea, 48",
    "sg:city":"Madrid",
    "sg:orig_category":"Loter\u00cda Y T\u00d3mbola",
    "sg:phone":"+34 915 59 94 95",
    "sg:postcode":"28008",
    "sg:province":"Madrid",
    "wof:name":"Vargas Urraca Maria Soledad",
    "wof:placetype":"venue"
},
  "geometry": {"coordinates":[-3.7326169014,40.4279594421],"type":"Point"}
}