{
  "type": "Feature",
  "properties": {
    "iso:country":"ES",
    "sg:address":"Calle de General Davila, 5",
    "sg:city":"Alcorcon",
    "sg:orig_category":"Arquitectos",
    "sg:phone":"+34 916 10 31 43",
    "sg:postcode":"28924",
    "sg:province":"Madrid",
    "wof:name":"Lopez Martin Miguel Angel",
    "wof:placetype":"venue"
},
  "geometry": {"coordinates":[-3.8146018982,40.3474578857],"type":"Point"}
}