{
  "type": "Feature",
  "properties": {
    "iso:country":"ES",
    "sg:address":"Av Bisbe Iglesias, 68",
    "sg:city":"Tremp",
    "sg:orig_category":"Muebles, Minoristas",
    "sg:phone":"+34 973 65 26 43",
    "sg:postcode":"25620",
    "sg:province":"Lleida",
    "wof:name":"Pascual Sanfeliu Rafael",
    "wof:placetype":"venue"
},
  "geometry": {"coordinates":[0.8969309926,42.1599159241],"type":"Point"}
}