{
  "type": "Feature",
  "properties": {
    "iso:country":"ES",
    "sg:address":"Pl Major, 23",
    "sg:city":"Santa Coloma De Queralt",
    "sg:orig_category":"Panader\u00cdas, Panader\u00cdas",
    "sg:phone":"+34 977 88 14 94",
    "sg:postcode":"43420",
    "sg:province":"Tarragona",
    "wof:name":"Pasteleria Benaiges S.l.",
    "wof:placetype":"venue"
},
  "geometry": {"coordinates":[1.3840429783,41.5322914124],"type":"Point"}
}