{
  "type": "Feature",
  "properties": {
    "iso:country":"ES",
    "sg:address":"Calle de Barichara, 6",
    "sg:city":"Madrid",
    "sg:orig_category":"Cerrajer\u00cda, Ferrallista",
    "sg:phone":"+34 917 63 03 52",
    "sg:postcode":"28033",
    "sg:province":"Madrid",
    "wof:name":"Rodea Razola Miguel",
    "wof:placetype":"venue"
},
  "geometry": {"coordinates":[-3.6374211311,40.4760284424],"type":"Point"}
}