{
  "type": "Feature",
  "properties": {
    "iso:country":"ES",
    "sg:address":"Calle de Silla, 7",
    "sg:city":"Albal",
    "sg:orig_category":"Cajas Y Embalajes De Madera",
    "sg:phone":"+34 961 26 14 82",
    "sg:postcode":"46470",
    "sg:province":"Valencia",
    "wof:name":"Retranspal S.l.",
    "wof:placetype":"venue"
},
  "geometry": {"coordinates":[-0.4079050124,39.395740509],"type":"Point"}
}