{
  "type": "Feature",
  "properties": {
    "addr:full":"C/ Trinitat, 5 Moncofa Castell\u00f3n 12593",
    "addr:housenumber":"5",
    "addr:postcode":"12593",
    "addr:street":"C / Trinitat;Castello\u0301N",
    "iso:country":"ES",
    "sg:address":"C/ Trinitat, 5",
    "sg:city":"Moncofa",
    "sg:orig_category":"Carnicer\u00cdas, Carnicer\u00cdas",
    "sg:phone":"+34 964 58 04 81",
    "sg:postcode":"12593",
    "sg:province":"Castell\u00f3n",
    "wof:name":"Espinos Arnau Francisco",
    "wof:placetype":"venue"
},
  "geometry": {"coordinates":[-0.1451050043,39.8084716797],"type":"Point"}
}