{
  "type": "Feature",
  "properties": {
    "addr:full":"C/ Hospital, 9 Elche Alicante 03203",
    "addr:housenumber":"9",
    "addr:postcode":"03203",
    "addr:street":"C / Hospital",
    "iso:country":"ES",
    "sg:address":"C/ Hospital, 9",
    "sg:city":"Elche",
    "sg:orig_category":"Cl\u00cdnicas Dentales",
    "sg:phone":"+34 965 45 23 98",
    "sg:postcode":"03203",
    "sg:province":"Alicante",
    "wof:name":"Santos Martin Francisco",
    "wof:placetype":"venue"
},
  "geometry": {"coordinates":[-0.6970540285,38.2655754089],"type":"Point"}
}