{
  "type": "Feature",
  "properties": {
    "iso:country":"ES",
    "sg:address":"Calle de Andalucia, 3",
    "sg:city":"Armilla",
    "sg:orig_category":"Inmobiliaria (agencias)",
    "sg:phone":"+34 958 57 13 89",
    "sg:postcode":"18100",
    "sg:province":"Granada",
    "wof:name":"Jiber 2 Inmobiliaria S.l.",
    "wof:placetype":"venue"
},
  "geometry": {"coordinates":[-3.6275351048,37.1422996521],"type":"Point"}
}