{
  "type": "Feature",
  "properties": {
    "iso:country":"ES",
    "sg:address":"Calle de Ildefonso Sanchez Del Rio, 1",
    "sg:city":"Pola De Siero",
    "sg:orig_category":"Librer\u00cdas",
    "sg:phone":"+34 985 72 17 02",
    "sg:postcode":"33510",
    "sg:province":"Asturias",
    "wof:name":"Fernandez Arias Genadio",
    "wof:placetype":"venue"
},
  "geometry": {"coordinates":[-5.6640248299,43.3919372559],"type":"Point"}
}