{
  "type": "Feature",
  "properties": {
    "iso:country":"ES",
    "sg:address":"Calle de Joaquin Blume, 1",
    "sg:city":"Baza",
    "sg:orig_category":"Ingenier\u00cda, Centros De Estudios (diversos)",
    "sg:phone":"+34 958 86 12 59",
    "sg:postcode":"18800",
    "sg:province":"Granada",
    "wof:name":"Agro Tecnica C.b.",
    "wof:placetype":"venue"
},
  "geometry": {"coordinates":[-2.7702550888,37.4928436279],"type":"Point"}
}