{
  "type": "Feature",
  "properties": {
    "addr:full":"Carrer de Floridablanca, 55 Barcelona Barcelona 08015",
    "addr:housenumber":"55",
    "addr:postcode":"08015",
    "addr:street":"Carrer De Floridablanca",
    "iso:country":"ES",
    "sg:address":"Carrer de Floridablanca, 55",
    "sg:city":"Barcelona",
    "sg:orig_category":"Aparcamientos (infraestructuras, Accesorios)",
    "sg:phone":"+34 933 25 38 76",
    "sg:postcode":"08015",
    "sg:province":"Barcelona",
    "wof:name":"Park-quel S.l.",
    "wof:placetype":"venue"
},
  "geometry": {"coordinates":[2.157761097,41.3781318665],"type":"Point"}
}