{
  "type": "Feature",
  "properties": {
    "iso:country":"ES",
    "sg:address":"Carr Republica Del Paraguai, 10",
    "sg:city":"Lleida",
    "sg:orig_category":"Frutas, Legumbres Frescas Y Tempranas (al Por Menor)",
    "sg:phone":"+34 973 28 09 58",
    "sg:postcode":"25002",
    "sg:province":"Lleida",
    "wof:name":"Bosch Solanes Camilo",
    "wof:placetype":"venue"
},
  "geometry": {"coordinates":[0.6191679835,41.6100883484],"type":"Point"}
}