{
  "type": "Feature",
  "properties": {
    "addr:full":"Calle de Profesor Sancho Corbacho, 22 Ecija Sevilla 41400",
    "addr:housenumber":"22",
    "addr:postcode":"41400",
    "addr:street":"Calle De Profesor Sancho Corbacho",
    "iso:country":"ES",
    "sg:address":"Calle de Profesor Sancho Corbacho, 22",
    "sg:city":"Ecija",
    "sg:orig_category":"Inform\u00c1tica: Material Y Suministros",
    "sg:phone":"+34 955 90 10 98",
    "sg:postcode":"41400",
    "sg:province":"Sevilla",
    "sg:website":"www.paginasamarillas.es",
    "wof:name":"Martin Rojano Andres",
    "wof:placetype":"venue"
},
  "geometry": {"coordinates":[-5.0876879692,37.5411338806],"type":"Point"}
}