{
  "type": "Feature",
  "properties": {
    "addr:full":"Calle de Mora, 29 Villasequilla Toledo 45740",
    "addr:housenumber":"29",
    "addr:postcode":"45740",
    "addr:street":"Calle De Mora",
    "iso:country":"ES",
    "sg:address":"Calle de Mora, 29",
    "sg:city":"Villasequilla",
    "sg:orig_category":"Cajas De Ahorro",
    "sg:phone":"+34 925 31 01 47",
    "sg:postcode":"45740",
    "sg:province":"Toledo",
    "wof:name":"Caja De Ahorros De Castilla La Mancha",
    "wof:placetype":"venue"
},
  "geometry": {"coordinates":[-3.7300460339,39.8749008179],"type":"Point"}
}