{
  "type": "Feature",
  "properties": {
    "iso:country":"ES",
    "sg:address":"Calle de Fray Juan, S/n",
    "sg:city":"Ardales",
    "sg:orig_category":"Empresas De Carpinter\u00cda",
    "sg:phone":"+34 952 45 81 75",
    "sg:postcode":"29550",
    "sg:province":"M\u00e1laga",
    "wof:name":"Rey Maldonado Jose Antonio",
    "wof:placetype":"venue"
},
  "geometry": {"coordinates":[-4.8454589844,36.8790550232],"type":"Point"}
}