{
  "type": "Feature",
  "properties": {
    "iso:country":"ES",
    "sg:address":"Carrer de Mercat, 2",
    "sg:city":"S. Joan Despi",
    "sg:orig_category":"Peluqueros: De Se\u00d1oras",
    "sg:phone":"+34 934 77 12 97",
    "sg:postcode":"08970",
    "sg:province":"Barcelona",
    "wof:name":"Porras Latorre Cristina",
    "wof:placetype":"venue"
},
  "geometry": {"coordinates":[2.0557219982,41.3669548035],"type":"Point"}
}