{
  "type": "Feature",
  "properties": {
    "iso:country":"ES",
    "sg:address":"Diseminado, Km. 0083,0",
    "sg:city":"Castejon",
    "sg:orig_category":"Distribuci\u00d3n De Petr\u00d3leo Y Derivados",
    "sg:phone":"+34 948 84 20 43",
    "sg:postcode":"31590",
    "sg:province":"Navarra",
    "wof:name":"Nasermo S.l.",
    "wof:placetype":"venue"
},
  "geometry": {"coordinates":[-1.69807899,42.1733131409],"type":"Point"}
}