{
  "type": "Feature",
  "properties": {
    "iso:country":"ES",
    "sg:address":"Calle de Cartagena, 34",
    "sg:city":"Algar",
    "sg:orig_category":"Chapister\u00cda",
    "sg:phone":"+34 968 13 61 30",
    "sg:postcode":"30366",
    "sg:province":"Murcia",
    "wof:name":"Perez Torrecillas Salvador",
    "wof:placetype":"venue"
},
  "geometry": {"coordinates":[-0.8883702755,37.6204986572],"type":"Point"}
}