{
  "type": "Feature",
  "properties": {
    "iso:country":"ES",
    "sg:address":"Calle de Manzano, 67",
    "sg:city":"Badajoz",
    "sg:orig_category":"Prot\u00c9sicos Dentales",
    "sg:phone":"+34 924 26 17 67",
    "sg:postcode":"06008",
    "sg:province":"Badajoz",
    "wof:name":"Garcia Martinez Miguel Angel",
    "wof:placetype":"venue"
},
  "geometry": {"coordinates":[-6.9534091949,38.8791999817],"type":"Point"}
}