{
  "type": "Feature",
  "properties": {
    "iso:country":"ES",
    "sg:address":"Plaz Altozano (del), 12",
    "sg:city":"Trebujena",
    "sg:orig_category":"Partidos Pol\u00cdticos",
    "sg:phone":"+34 956 39 52 05",
    "sg:postcode":"11560",
    "sg:province":"C\u00e1diz",
    "wof:name":"Partido Socialista Obrero Espa\u00f1ol",
    "wof:placetype":"venue"
},
  "geometry": {"coordinates":[-6.1770057678,36.8703613281],"type":"Point"}
}