{
  "type": "Feature",
  "properties": {
    "iso:country":"ES",
    "sg:address":"Dorada, 44",
    "sg:city":"Tres Caminos",
    "sg:orig_category":"Maquinaria Neum\u00c1tica",
    "sg:phone":"+34 956 80 07 55",
    "sg:postcode":"11510",
    "sg:province":"C\u00e1diz",
    "sg:website":"www.hidromecane.com",
    "wof:name":"Hidromecane S.l.",
    "wof:placetype":"venue"
},
  "geometry": {"coordinates":[-6.1980991364,36.5308990479],"type":"Point"}
}