{
  "type": "Feature",
  "properties": {
    "addr:full":"Calle de Sor Simona, 22 Palmas De Gran Canaria Las Palmas 35012",
    "addr:housenumber":"22",
    "addr:postcode":"35012",
    "addr:street":"Calle De Sor Simona",
    "iso:country":"ES",
    "sg:address":"Calle de Sor Simona, 22",
    "sg:city":"Palmas De Gran Canaria",
    "sg:orig_category":"Farmacias",
    "sg:phone":"+34 928 20 11 32",
    "sg:postcode":"35012",
    "sg:province":"Las Palmas",
    "wof:name":"Lazaro Montelongo Fernando",
    "wof:placetype":"venue"
},
  "geometry": {"coordinates":[-15.4298601151,28.1139526367],"type":"Point"}
}