{
  "type": "Feature",
  "properties": {
    "iso:country":"ES",
    "sg:address":"Calle de Tomas Edison, 14",
    "sg:city":"Estacion Portazgo",
    "sg:orig_category":"Fabricaci\u00d3n, Instalaci\u00d3n De Armarios",
    "sg:phone":"+34 976 69 47 47",
    "sg:postcode":"50800",
    "sg:province":"Zaragoza",
    "sg:website":"www.imor.es",
    "wof:name":"Imaginacion Organizada S.l.",
    "wof:placetype":"venue"
},
  "geometry": {"coordinates":[-0.7865840197,41.867225647],"type":"Point"}
}