{
  "type": "Feature",
  "properties": {
    "addr:full":"Av Ramon I Cajal, 40 Tarragona Tarragona 43001",
    "addr:housenumber":"40",
    "addr:postcode":"43001",
    "addr:street":"Av Ramon I Cajal",
    "iso:country":"ES",
    "sg:address":"Av Ramon I Cajal, 40",
    "sg:city":"Tarragona",
    "sg:orig_category":"Abogados",
    "sg:phone":"+34 977 22 32 14",
    "sg:postcode":"43001",
    "sg:province":"Tarragona",
    "wof:name":"Canals Vilafranca Elisa",
    "wof:placetype":"venue"
},
  "geometry": {"coordinates":[1.2461090088,41.1161384583],"type":"Point"}
}