{
  "type": "Feature",
  "properties": {
    "iso:country":"ES",
    "sg:address":"Quintana, S/n",
    "sg:city":"Somahoz",
    "sg:orig_category":"Distribuci\u00d3n De Petr\u00d3leo Y Derivados",
    "sg:phone":"+34 942 84 17 42",
    "sg:postcode":"39400",
    "sg:province":"Cantabria",
    "wof:name":"Alonso Hurtado S.l.",
    "wof:placetype":"venue"
},
  "geometry": {"coordinates":[-4.6216669083,43.2488899231],"type":"Point"}
}