{
  "type": "Feature",
  "properties": {
    "addr:full":"Calle de Eleizalde, 2 Landa Vizcaya 48610",
    "addr:housenumber":"2",
    "addr:postcode":"48610",
    "addr:street":"Calle De Eleizalde",
    "iso:country":"ES",
    "sg:address":"Calle de Eleizalde, 2",
    "sg:city":"Landa",
    "sg:orig_category":"Panader\u00cdas, Panader\u00cdas",
    "sg:phone":"+34 946 76 29 04",
    "sg:postcode":"48610",
    "sg:province":"Vizcaya",
    "wof:name":"Hijos De Cosme Elguezabal S.a.",
    "wof:placetype":"venue"
},
  "geometry": {"coordinates":[-2.6983869076,43.2204284668],"type":"Point"}
}