{
  "type": "Feature",
  "properties": {
    "addr:full":"Calle de Valladolid, 9 Azuqueca Henares Guadalajara 19200",
    "addr:housenumber":"9",
    "addr:postcode":"19200",
    "addr:street":"Calle De Valladolid",
    "iso:country":"ES",
    "sg:address":"Calle de Valladolid, 9",
    "sg:city":"Azuqueca Henares",
    "sg:orig_category":"Institutos De Belleza",
    "sg:phone":"+34 949 26 55 71",
    "sg:postcode":"19200",
    "sg:province":"Guadalajara",
    "wof:name":"Martin Sanchez Esther",
    "wof:placetype":"venue"
},
  "geometry": {"coordinates":[-3.263297081,40.5634689331],"type":"Point"}
}