{
  "type": "Feature",
  "properties": {
    "addr:full":"Av Francesc Macia, 39 Sabadell Barcelona 08206",
    "addr:housenumber":"39",
    "addr:postcode":"08206",
    "addr:street":"Av Francesc Macia",
    "iso:country":"ES",
    "sg:address":"Av Francesc Macia, 39",
    "sg:city":"Sabadell",
    "sg:orig_category":"Electricidad, Electr\u00d3nica: Suministros (al Por Menor)",
    "sg:phone":"+34 937 23 02 70",
    "sg:postcode":"08206",
    "sg:province":"Barcelona",
    "sg:website":"www.enelec.com",
    "wof:name":"Enelec S.l.",
    "wof:placetype":"venue"
},
  "geometry": {"coordinates":[2.0972299576,41.5571098328],"type":"Point"}
}