{
  "type": "Feature",
  "properties": {
    "addr:full":"Calle de Sayas, 61 Almunia De Do\u00e7a Godina Zaragoza 50100",
    "addr:housenumber":"61",
    "addr:postcode":"50100",
    "addr:street":"Calle De Sayas",
    "iso:country":"ES",
    "sg:address":"Calle de Sayas, 61",
    "sg:city":"Almunia De Do\u00e7a Godina",
    "sg:orig_category":"Carnicer\u00cdas, Carnicer\u00cdas",
    "sg:phone":"+34 976 81 32 72",
    "sg:postcode":"50100",
    "sg:province":"Zaragoza",
    "wof:name":"Montesinos Garcia Arturo",
    "wof:placetype":"venue"
},
  "geometry": {"coordinates":[-1.3718990088,41.4761810303],"type":"Point"}
}