{
  "type": "Feature",
  "properties": {
    "addr:full":"Cm\u00d1o Pinal (do), S/n Igrexa Pontevedra 36320",
    "addr:housenumber":"s",
    "addr:postcode":"36320",
    "addr:street":"Cmn\u0303O;/ N",
    "iso:country":"ES",
    "sg:address":"Cm\u00d1o Pinal (do), S/n",
    "sg:city":"Igrexa",
    "sg:orig_category":"Orquestas Cl\u00c1sicas, Asociaciones De M\u00dasica, Coros Y Corales",
    "sg:phone":"+34 986 45 22 44",
    "sg:postcode":"36320",
    "sg:province":"Pontevedra",
    "wof:name":"Asociacion Cultural Y Social Banda Musica Xuvenil Chapela",
    "wof:placetype":"venue"
},
  "geometry": {"coordinates":[-8.6870603561,42.3997344971],"type":"Point"}
}