{
  "type": "Feature",
  "properties": {
    "iso:country":"ES",
    "sg:address":"Avda Martinez Campos, 12",
    "sg:city":"Alcantarilla",
    "sg:orig_category":"Inmobiliaria (agencias)",
    "sg:phone":"+34 968 80 28 25",
    "sg:postcode":"30820",
    "sg:province":"Murcia",
    "wof:name":"Molina Millan Ramon",
    "wof:placetype":"venue"
},
  "geometry": {"coordinates":[-1.2162690163,37.9696884155],"type":"Point"}
}