{
  "type": "Feature",
  "properties": {
    "addr:full":"Ctra Artesa De Segre (d'), Km. 0012,9 Agramunt Lleida 25310",
    "addr:postcode":"25310",
    "addr:street":"Ctra Artesa De Segre D ' Km. 0012,9",
    "iso:country":"ES",
    "sg:address":"Ctra Artesa De Segre (d'), Km. 0012,9",
    "sg:city":"Agramunt",
    "sg:orig_category":"Centros De Reservas Hoteleras",
    "sg:phone":"+34 973 39 08 25",
    "sg:postcode":"25310",
    "sg:province":"Lleida",
    "wof:name":"Establecimientos Esa S.l.",
    "wof:placetype":"venue"
},
  "geometry": {"coordinates":[1.0919469595,41.7880477905],"type":"Point"}
}