{
  "type": "Feature",
  "properties": {
    "iso:country":"ES",
    "sg:address":"Avda Jose Mesa Y Lopez, 80",
    "sg:city":"Palmas De Gran Canaria",
    "sg:orig_category":"Cine (producci\u00d3n, Realizaci\u00d3n)",
    "sg:phone":"+34 928 22 11 52",
    "sg:postcode":"35010",
    "sg:province":"Las Palmas",
    "wof:name":"Betancor Bautista Alicia",
    "wof:placetype":"venue"
},
  "geometry": {"coordinates":[-15.4376249313,28.1326618195],"type":"Point"}
}