{
  "type": "Feature",
  "properties": {
    "addr:full":"Calle de Bego\u00d1a, 68 Humanes De Madrid Madrid 28970",
    "addr:housenumber":"68",
    "addr:postcode":"28970",
    "addr:street":"Calle De Begon\u0303A",
    "iso:country":"ES",
    "sg:address":"Calle de Bego\u00d1a, 68",
    "sg:city":"Humanes De Madrid",
    "sg:orig_category":"Empresas De Carpinter\u00cda",
    "sg:phone":"+34 916 97 77 07",
    "sg:postcode":"28970",
    "sg:province":"Madrid",
    "wof:name":"Ventanas Termicas Madrile\u00f1as S.l.",
    "wof:placetype":"venue"
},
  "geometry": {"coordinates":[-3.8269588947,40.2540245056],"type":"Point"}
}