{
  "type": "Feature",
  "properties": {
    "iso:country":"ES",
    "sg:address":"Carr Pintor Vergara, 108",
    "sg:city":"Alcudia",
    "sg:orig_category":"Ingeniero",
    "sg:phone":"+34 962 54 05 84",
    "sg:postcode":"46250",
    "sg:province":"Valencia",
    "sg:website":"www.telnetingenieria.com",
    "wof:name":"Marques Pons Francisco Javier",
    "wof:placetype":"venue"
},
  "geometry": {"coordinates":[-0.5035259724,39.1954841614],"type":"Point"}
}