{
  "type": "Feature",
  "properties": {
    "iso:country":"ES",
    "sg:address":"Calle de Ecuador, 10",
    "sg:city":"Majadahonda",
    "sg:orig_category":"Talleres De Corte Y Confecci\u00d3n",
    "sg:phone":"+34 916 39 17 40",
    "sg:postcode":"28220",
    "sg:province":"Madrid",
    "wof:name":"Misstrufitas S.l.",
    "wof:placetype":"venue"
},
  "geometry": {"coordinates":[-3.8700268269,40.4778442383],"type":"Point"}
}