{
  "type": "Feature",
  "properties": {
    "iso:country":"ES",
    "sg:address":"Calle de San Anton, 4",
    "sg:city":"Parla",
    "sg:orig_category":"Muebles, Minoristas",
    "sg:phone":"+34 916 99 22 38",
    "sg:postcode":"28980",
    "sg:province":"Madrid",
    "wof:name":"Estancias Y Habitat S.l",
    "wof:placetype":"venue"
},
  "geometry": {"coordinates":[-3.7721199989,40.2344741821],"type":"Point"}
}