{
  "type": "Feature",
  "properties": {
    "addr:full":"Carr Botines, 17 Palafrugell Girona 17200",
    "addr:housenumber":"17",
    "addr:postcode":"17200",
    "addr:street":"Carr Botines",
    "iso:country":"ES",
    "sg:address":"Carr Botines, 17",
    "sg:city":"Palafrugell",
    "sg:orig_category":"Asociaciones Y Clubs Deportivos",
    "sg:phone":"+34 972 30 04 11",
    "sg:postcode":"17200",
    "sg:province":"Girona",
    "wof:name":"Sports 77 S.l.",
    "wof:placetype":"venue"
},
  "geometry": {"coordinates":[3.1645879745,41.9156799316],"type":"Point"}
}