{
  "type": "Feature",
  "properties": {
    "iso:country":"ES",
    "sg:address":"Av Joan Xxiii, 66",
    "sg:city":"Masnou",
    "sg:orig_category":"Florister\u00cdas",
    "sg:phone":"+34 935 55 01 35",
    "sg:postcode":"08320",
    "sg:province":"Barcelona",
    "wof:name":"Pijoan Esmerats Isabel",
    "wof:placetype":"venue"
},
  "geometry": {"coordinates":[2.3157000542,41.4831085205],"type":"Point"}
}