{
  "type": "Feature",
  "properties": {
    "addr:full":"Calle de Cuenca (de), 21 Humanes De Madrid Madrid 28970",
    "addr:housenumber":"21",
    "addr:postcode":"28970",
    "addr:street":"Calle De Cuenca De",
    "iso:country":"ES",
    "sg:address":"Calle de Cuenca (de), 21",
    "sg:city":"Humanes De Madrid",
    "sg:orig_category":"Aceros Inoxidables",
    "sg:phone":"+34 916 06 55 95",
    "sg:postcode":"28970",
    "sg:province":"Madrid",
    "wof:name":"Inoxidables Y Laton S.l.",
    "wof:placetype":"venue"
},
  "geometry": {"coordinates":[-3.8161492348,40.2745895386],"type":"Point"}
}