{
  "type": "Feature",
  "properties": {
    "iso:country":"ES",
    "sg:address":"Carrer de Enamorats, 4",
    "sg:city":"Santa Coloma De Gramenet",
    "sg:orig_category":"Expositores",
    "sg:phone":"+34 933 91 60 58",
    "sg:postcode":"08921",
    "sg:province":"Barcelona",
    "wof:name":"Muestrarios Encar S.a.",
    "wof:placetype":"venue"
},
  "geometry": {"coordinates":[2.2131309509,41.4540367126],"type":"Point"}
}