{
  "type": "Feature",
  "properties": {
    "iso:country":"ES",
    "sg:address":"Calle de Vinatea, 22",
    "sg:city":"Valencia",
    "sg:orig_category":"Centros Empresariales",
    "sg:phone":"+34 963 15 31 15",
    "sg:postcode":"46001",
    "sg:province":"Valencia",
    "sg:website":"www.anieme.com",
    "wof:name":"Furnifair S.l.",
    "wof:placetype":"venue"
},
  "geometry": {"coordinates":[-0.3808769882,39.4713363647],"type":"Point"}
}