{
  "type": "Feature",
  "properties": {
    "iso:country":"ES",
    "sg:address":"Calle de Muro, 12",
    "sg:city":"Valladolid",
    "sg:orig_category":"Centros De Coordinaci\u00d3n",
    "sg:phone":"+34 983 21 34 92",
    "sg:postcode":"47004",
    "sg:province":"Valladolid",
    "wof:name":"Gestoria Oscar Fernandez S.l.",
    "wof:placetype":"venue"
},
  "geometry": {"coordinates":[-4.7252240181,41.6463356018],"type":"Point"}
}