{
  "type": "Feature",
  "properties": {
    "addr:full":"Avgd Pius Xii, 7 Lleida Lleida 25003",
    "addr:housenumber":"7",
    "addr:postcode":"25003",
    "addr:street":"Xii",
    "iso:country":"ES",
    "sg:address":"Avgd Pius Xii, 7",
    "sg:city":"Lleida",
    "sg:orig_category":"Farmacias",
    "sg:phone":"+34 973 28 05 20",
    "sg:postcode":"25003",
    "sg:province":"Lleida",
    "wof:name":"Farmacia Garcia-isanta C.b.",
    "wof:placetype":"venue"
},
  "geometry": {"coordinates":[0.6160809994,41.6153907776],"type":"Point"}
}