{
  "type": "Feature",
  "properties": {
    "addr:full":"Carrer de Dolores Viudes Blasco, 11 Guardamar Segura Alicante 03140",
    "addr:housenumber":"11",
    "addr:postcode":"03140",
    "addr:street":"Carrer De Dolores Viudes Blasco",
    "iso:country":"ES",
    "sg:address":"Carrer de Dolores Viudes Blasco, 11",
    "sg:city":"Guardamar Segura",
    "sg:orig_category":"Empresas De Limpieza",
    "sg:phone":"+34 965 72 43 94",
    "sg:postcode":"03140",
    "sg:province":"Alicante",
    "wof:name":"Limjairos S.l.",
    "wof:placetype":"venue"
},
  "geometry": {"coordinates":[-0.6525589824,38.0823974609],"type":"Point"}
}