{
  "type": "Feature",
  "properties": {
    "addr:full":"Camino Del Pilon, 133 Zaragoza Zaragoza 50011",
    "addr:housenumber":"133",
    "addr:postcode":"50011",
    "addr:street":"Camino Del Pilon",
    "iso:country":"ES",
    "sg:address":"Camino Del Pilon, 133",
    "sg:city":"Zaragoza",
    "sg:orig_category":"Institutos De Belleza",
    "sg:phone":"+34 976 31 99 05",
    "sg:postcode":"50011",
    "sg:province":"Zaragoza",
    "wof:name":"Salon De Belleza Ascen Casas S.l",
    "wof:placetype":"venue"
},
  "geometry": {"coordinates":[-0.9438260198,41.6587638855],"type":"Point"}
}