{
  "type": "Feature",
  "properties": {
    "iso:country":"ES",
    "sg:address":"Calle de Tercia, 64",
    "sg:city":"Malagon",
    "sg:orig_category":"Asesor\u00cda Fiscal Y Jur\u00cddica",
    "sg:phone":"+34 926 26 60 26",
    "sg:postcode":"13420",
    "sg:province":"Ciudad Real",
    "wof:name":"Bermejo Perez Maria De Los Santos",
    "wof:placetype":"venue"
},
  "geometry": {"coordinates":[-3.8538789749,39.1696891785],"type":"Point"}
}