{
  "type": "Feature",
  "properties": {
    "iso:country":"ES",
    "sg:address":"Rua Orfas (das), 9",
    "sg:city":"Santiago De Compostela",
    "sg:orig_category":"Bazares, Art\u00cdculos De Limpieza Y De Cocina (al Por Menor)",
    "sg:phone":"+34 981 58 04 69",
    "sg:postcode":"15703",
    "sg:province":"La Coru\u00f1a",
    "wof:name":"Caama\u00f1o Casti\u00f1eira Aurora",
    "wof:placetype":"venue"
},
  "geometry": {"coordinates":[-8.5436143875,42.8777427673],"type":"Point"}
}