{
  "type": "Feature",
  "properties": {
    "addr:full":"Calle de Reyes Catolicos, S/n Parla Madrid 28980",
    "addr:housenumber":"s / n",
    "addr:postcode":"28980",
    "addr:street":"Calle De Reyes Catolicos",
    "iso:country":"ES",
    "sg:address":"Calle de Reyes Catolicos, S/n",
    "sg:city":"Parla",
    "sg:orig_category":"Centros De Educaci\u00d3n Especial",
    "sg:phone":"+34 916 98 64 33",
    "sg:postcode":"28980",
    "sg:province":"Madrid",
    "wof:name":"Colegio Publico Maria Moliner",
    "wof:placetype":"venue"
},
  "geometry": {"coordinates":[-3.768558979,40.2310752869],"type":"Point"}
}