{
  "type": "Feature",
  "properties": {
    "addr:full":"Ctra Arbucies, 57 Breda Girona 17400",
    "addr:housenumber":"57",
    "addr:postcode":"17400",
    "addr:street":"Ctra Arbucies",
    "iso:country":"ES",
    "sg:address":"Ctra Arbucies, 57",
    "sg:city":"Breda",
    "sg:orig_category":"Inmobiliaria (agencias)",
    "sg:phone":"+34 972 87 13 06",
    "sg:postcode":"17400",
    "sg:province":"Girona",
    "wof:name":"Habitatges I Promocions Pedraforta S.l.",
    "wof:placetype":"venue"
},
  "geometry": {"coordinates":[2.5585401058,41.7448234558],"type":"Point"}
}