{
  "type": "Feature",
  "properties": {
    "addr:full":"Pg Ter, S/n Manlleu Barcelona 08560",
    "addr:housenumber":"s / n",
    "addr:postcode":"08560",
    "addr:street":"Pg Ter",
    "iso:country":"ES",
    "sg:address":"Pg Ter, S/n",
    "sg:city":"Manlleu",
    "sg:orig_category":"Polideportivos",
    "sg:phone":"+34 938 51 15 50",
    "sg:postcode":"08560",
    "sg:province":"Barcelona",
    "wof:name":"Ajuntament-pavello Poliesportiu",
    "wof:placetype":"venue"
},
  "geometry": {"coordinates":[2.2779159546,41.9984092712],"type":"Point"}
}