{
  "type": "Feature",
  "properties": {
    "addr:full":"Carr Caldereria, 26 Xativa Valencia 46800",
    "addr:housenumber":"26",
    "addr:postcode":"46800",
    "addr:street":"Carr Caldereria",
    "iso:country":"ES",
    "sg:address":"Carr Caldereria, 26",
    "sg:city":"Xativa",
    "sg:orig_category":"Partidos Pol\u00cdticos",
    "sg:phone":"+34 962 27 35 99",
    "sg:postcode":"46800",
    "sg:province":"Valencia",
    "wof:name":"Partido Socialista Obrero Espa\u00f1ol",
    "wof:placetype":"venue"
},
  "geometry": {"coordinates":[-0.5200830102,38.9934272766],"type":"Point"}
}