{
  "type": "Feature",
  "properties": {
    "addr:full":"Carrer de Jaume Casanovas, 135 Prat Llobregat Barcelona 08820",
    "addr:housenumber":"135",
    "addr:postcode":"08820",
    "addr:street":"Carrer De Jaume Casanovas;Llobregat",
    "iso:country":"ES",
    "sg:address":"Carrer de Jaume Casanovas, 135",
    "sg:city":"Prat Llobregat",
    "sg:orig_category":"Fabricaci\u00d3n De Peines Y De Accesorios De Peluquer\u00cda",
    "sg:phone":"+34 933 70 02 46",
    "sg:postcode":"08820",
    "sg:province":"Barcelona",
    "wof:name":"Escruela Verges Alberto",
    "wof:placetype":"venue"
},
  "geometry": {"coordinates":[2.0939130783,41.3239402771],"type":"Point"}
}