{
  "type": "Feature",
  "properties": {
    "addr:full":"Calle de Cespedes, 12 Cordoba C\u00f3rdoba 14003",
    "addr:housenumber":"12",
    "addr:postcode":"14003",
    "addr:street":"Calle De Cespedes;Co\u0301Rdoba",
    "iso:country":"ES",
    "sg:address":"Calle de Cespedes, 12",
    "sg:city":"Cordoba",
    "sg:orig_category":"Dorados, Plater\u00cda (orfebrer\u00cda)",
    "sg:phone":"+34 957 49 17 90",
    "sg:postcode":"14003",
    "sg:province":"C\u00f3rdoba",
    "wof:name":"Gonzalez-espaliu Domingo Maria Teresa",
    "wof:placetype":"venue"
},
  "geometry": {"coordinates":[-4.780166626,37.8802642822],"type":"Point"}
}