{
  "type": "Feature",
  "properties": {
    "iso:country":"ES",
    "sg:address":"Avda Olivar (del), 2",
    "sg:city":"Valdemoro",
    "sg:orig_category":"Calderer\u00cda",
    "sg:phone":"+34 918 95 04 87",
    "sg:postcode":"28340",
    "sg:province":"Madrid",
    "wof:name":"Tecnicald S.c.l.",
    "wof:placetype":"venue"
},
  "geometry": {"coordinates":[-3.6767520905,40.2007980347],"type":"Point"}
}