{
  "type": "Feature",
  "properties": {
    "addr:full":"Calle de Villafranca, 16 Astorga Le\u00f3n 24700",
    "addr:housenumber":"16",
    "addr:postcode":"24700",
    "addr:street":"Calle De Villafranca;Leo\u0301N",
    "iso:country":"ES",
    "sg:address":"Calle de Villafranca, 16",
    "sg:city":"Astorga",
    "sg:orig_category":"Molduras, Junquillos, Listones Y Molduras Perforadas",
    "sg:phone":"+34 987 60 31 97",
    "sg:postcode":"24700",
    "sg:province":"Le\u00f3n",
    "wof:name":"Silva Garcia Juan Miguel",
    "wof:placetype":"venue"
},
  "geometry": {"coordinates":[-6.0574321747,42.4563484192],"type":"Point"}
}