{
  "type": "Feature",
  "properties": {
    "addr:full":"Avda Libertad De La, 40 Donostia-san Sebastian Guip\u00f9zcoa 20004",
    "addr:housenumber":"40",
    "addr:postcode":"20004",
    "addr:street":"Avda Libertad De La",
    "iso:country":"ES",
    "sg:address":"Avda Libertad De La, 40",
    "sg:city":"Donostia-san Sebastian",
    "sg:orig_category":"Cajas De Ahorro",
    "sg:phone":"+34 943 44 02 30",
    "sg:postcode":"20004",
    "sg:province":"Guip\u00f9zcoa",
    "wof:name":"Caja De Ahorros De Valencia Castellon Y Alicante",
    "wof:placetype":"venue"
},
  "geometry": {"coordinates":[-1.983970046,43.3189964294],"type":"Point"}
}