{
  "type": "Feature",
  "properties": {
    "addr:full":"Plaz Cedro Del, 2 Donostia-san Sebastian Guip\u00f9zcoa 20016",
    "addr:housenumber":"2",
    "addr:postcode":"20016",
    "iso:country":"ES",
    "sg:address":"Plaz Cedro Del, 2",
    "sg:city":"Donostia-san Sebastian",
    "sg:orig_category":"Agencias Y Asesores De Publicidad",
    "sg:phone":"+34 943 40 46 36",
    "sg:postcode":"20016",
    "sg:province":"Guip\u00f9zcoa",
    "wof:name":"Esquema Equipo De Dise\u00f1adores Graficos S.l.",
    "wof:placetype":"venue"
},
  "geometry": {"coordinates":[-1.942620039,43.3229598999],"type":"Point"}
}