{
  "type": "Feature",
  "properties": {
    "iso:country":"ES",
    "sg:address":"Carrer de Madrazo, 27",
    "sg:city":"Barcelona",
    "sg:orig_category":"Molduras, Junquillos, Listones Y Molduras Perforadas",
    "sg:phone":"+34 932 37 01 92",
    "sg:postcode":"08006",
    "sg:province":"Barcelona",
    "wof:name":"Pastor Villegas Maria De Los Angeles",
    "wof:placetype":"venue"
},
  "geometry": {"coordinates":[2.1495909691,41.4005737305],"type":"Point"}
}