{
  "type": "Feature",
  "properties": {
    "addr:full":"Calle de Bilibio, 2 Haro La Rioja 26200",
    "addr:housenumber":"2",
    "addr:postcode":"26200",
    "addr:street":"Calle De Bilibio",
    "iso:country":"ES",
    "sg:address":"Calle de Bilibio, 2",
    "sg:city":"Haro",
    "sg:orig_category":"Juegos Y Juguetes (al Por Menor)",
    "sg:phone":"+34 941 31 07 36",
    "sg:postcode":"26200",
    "sg:province":"La Rioja",
    "wof:name":"Lopez Gomez Pedro",
    "wof:placetype":"venue"
},
  "geometry": {"coordinates":[-2.8463821411,42.5773162842],"type":"Point"}
}