{
  "type": "Feature",
  "properties": {
    "addr:full":"Rua Corredoira, 38 Monforte De Lemos Lugo 27400",
    "addr:housenumber":"38",
    "addr:postcode":"27400",
    "addr:street":"Rua Corredoira",
    "iso:country":"ES",
    "sg:address":"Rua Corredoira, 38",
    "sg:city":"Monforte De Lemos",
    "sg:orig_category":"Fabricaci\u00d3n, Instalaci\u00d3n De Armarios",
    "sg:phone":"+34 982 40 16 65",
    "sg:postcode":"27400",
    "sg:province":"Lugo",
    "wof:name":"Rialvi S.l.",
    "wof:placetype":"venue"
},
  "geometry": {"coordinates":[-7.5206990242,42.5265693665],"type":"Point"}
}