{
  "type": "Feature",
  "properties": {
    "addr:full":"Plaz Conde Luna, S/n Le\u00f3n Le\u00f3n 24003",
    "addr:postcode":"24003",
    "addr:street":"Luna S / N Leo\u0301N Leo\u0301N",
    "iso:country":"ES",
    "sg:address":"Plaz Conde Luna, S/n",
    "sg:city":"Le\u00f3n",
    "sg:orig_category":"Casquer\u00cda (al Por Menor)",
    "sg:phone":"+34 987 25 55 91",
    "sg:postcode":"24003",
    "sg:province":"Le\u00f3n",
    "wof:name":"Fernandez Gutierrez Juan",
    "wof:placetype":"venue"
},
  "geometry": {"coordinates":[-5.5683689117,42.5978393555],"type":"Point"}
}