{
  "type": "Feature",
  "properties": {
    "iso:country":"ES",
    "sg:address":"Cami Llavador, 4",
    "sg:city":"Marines",
    "sg:orig_category":"Cerrajer\u00cda, Ferrallista",
    "sg:phone":"+34 965 78 65 59",
    "sg:postcode":"03700",
    "sg:province":"Alicante",
    "wof:name":"Cerrajeria Montiel E Hijo S.l",
    "wof:placetype":"venue"
},
  "geometry": {"coordinates":[0.0983370021,38.8451538086],"type":"Point"}
}