{
  "type": "Feature",
  "properties": {
    "iso:country":"ES",
    "sg:address":"Carr Cadiz, 4",
    "sg:city":"Eliana",
    "sg:orig_category":"Farmacias",
    "sg:phone":"+34 961 65 68 47",
    "sg:postcode":"46183",
    "sg:province":"Valencia",
    "wof:name":"Barrachina Lemos Vicente Manuel",
    "wof:placetype":"venue"
},
  "geometry": {"coordinates":[-0.528208971,39.5667457581],"type":"Point"}
}