{
  "type": "Feature",
  "properties": {
    "iso:country":"ES",
    "sg:address":"Poligon Ind. Pedrosa, S/n",
    "sg:city":"Masquefa",
    "sg:orig_category":"M\u00c1quinas Para Recortar Y Pegar",
    "sg:phone":"+34 937 72 77 05",
    "sg:postcode":"08783",
    "sg:province":"Barcelona",
    "wof:name":"Troymak S.l.",
    "wof:placetype":"venue"
},
  "geometry": {"coordinates":[1.8109899759,41.5002937317],"type":"Point"}
}