{
  "type": "Feature",
  "properties": {
    "addr:full":"Calle de Francisco De Icaza, 1 Madrid Madrid 28025",
    "addr:housenumber":"1",
    "addr:postcode":"28025",
    "addr:street":"Calle De Francisco De Icaza",
    "iso:country":"ES",
    "sg:address":"Calle de Francisco De Icaza, 1",
    "sg:city":"Madrid",
    "sg:orig_category":"Panader\u00cdas, Panader\u00cdas",
    "sg:phone":"+34 914 69 59 04",
    "sg:postcode":"28025",
    "sg:province":"Madrid",
    "wof:name":"Adicon S.l.",
    "wof:placetype":"venue"
},
  "geometry": {"coordinates":[-3.7267358303,40.3857727051],"type":"Point"}
}