{
  "type": "Feature",
  "properties": {
    "iso:country":"ES",
    "sg:address":"Escola, S/n",
    "sg:city":"Escalo",
    "sg:orig_category":"Maquinaria Para Industrias Diversas",
    "sg:phone":"+34 973 62 21 77",
    "sg:postcode":"25596",
    "sg:province":"Lleida",
    "wof:name":"Excarpi S.l.",
    "wof:placetype":"venue"
},
  "geometry": {"coordinates":[1.1560310125,42.549911499],"type":"Point"}
}