{
  "type": "Feature",
  "properties": {
    "iso:country":"ES",
    "sg:address":"Avda Dilar (de), 12",
    "sg:city":"Granada",
    "sg:orig_category":"Audiovisuales (producci\u00d3n, Edici\u00d3n, Realizaci\u00d3n)",
    "sg:phone":"+34 958 12 79 49",
    "sg:postcode":"18007",
    "sg:province":"Granada",
    "wof:name":"Onda Ciudadana Suroeste S.l.",
    "wof:placetype":"venue"
},
  "geometry": {"coordinates":[-3.599807024,37.16015625],"type":"Point"}
}