{
  "type": "Feature",
  "properties": {
    "addr:full":"Plaz Madre De Dios, 12 Jerez De La Frontera C\u00e1diz 11401",
    "addr:postcode":"11401",
    "iso:country":"ES",
    "sg:address":"Plaz Madre De Dios, 12",
    "sg:city":"Jerez De La Frontera",
    "sg:orig_category":"Inform\u00c1tica, Ofim\u00c1tica (estudios, Asesor\u00cda, Ingenier\u00cda, Formaci\u00d3n)",
    "sg:phone":"+34 956 30 21 81",
    "sg:postcode":"11401",
    "sg:province":"C\u00e1diz",
    "sg:website":"www.acominmobiliarias.com",
    "wof:name":"Acompc Informatica Y Comunicaciones Sl",
    "wof:placetype":"venue"
},
  "geometry": {"coordinates":[-6.1301674843,36.6796073914],"type":"Point"}
}