{
  "type": "Feature",
  "properties": {
    "addr:full":"Avda Rector Gustavo Villapalos, 32 Roquetas Mar Almer\u00eda 04740",
    "addr:housenumber":"32",
    "addr:postcode":"04740",
    "addr:street":"Avda Rector Gustavo Villapalos;Mar Almeri\u0301A",
    "iso:country":"ES",
    "sg:address":"Avda Rector Gustavo Villapalos, 32",
    "sg:city":"Roquetas Mar",
    "sg:orig_category":"Electrodom\u00c9sticos (al Por Menor)",
    "sg:phone":"+34 950 32 50 49",
    "sg:postcode":"04740",
    "sg:province":"Almer\u00eda",
    "wof:name":"Garcia Palenzuela Anselmo Juan",
    "wof:placetype":"venue"
},
  "geometry": {"coordinates":[-2.6136145592,36.7631530762],"type":"Point"}
}