{
  "type": "Feature",
  "properties": {
    "iso:country":"ES",
    "sg:address":"Calle de Jesus, 20",
    "sg:city":"Oviedo",
    "sg:orig_category":"Caf\u00c9s, Bares, Cervecer\u00cdas",
    "sg:phone":"+34 985 20 20 29",
    "sg:postcode":"33009",
    "sg:province":"Asturias",
    "wof:name":"Peraria S.l",
    "wof:placetype":"venue"
},
  "geometry": {"coordinates":[-5.8450889587,43.3605384827],"type":"Point"}
}