{
  "type": "Feature",
  "properties": {
    "addr:full":"Avda Monfrag\u00fce, S/n Trujillo C\u00e1ceres 10200",
    "addr:housenumber":"s",
    "addr:postcode":"10200",
    "addr:street":"Avda Monfraguee;/ N;Ca\u0301Ceres",
    "iso:country":"ES",
    "sg:address":"Avda Monfrag\u00fce, S/n",
    "sg:city":"Trujillo",
    "sg:orig_category":"Discapacitados",
    "sg:phone":"+34 927 32 16 11",
    "sg:postcode":"10200",
    "sg:province":"C\u00e1ceres",
    "wof:name":"Aspyam",
    "wof:placetype":"venue"
},
  "geometry": {"coordinates":[-5.875579834,39.4625434875],"type":"Point"}
}