{
  "type": "Feature",
  "properties": {
    "iso:country":"ES",
    "sg:address":"Rua Milagrosa (da), 67",
    "sg:city":"Lugo",
    "sg:orig_category":"Alimentaci\u00d3n General (al Por Menor)",
    "sg:phone":"+34 982 21 10 03",
    "sg:postcode":"27003",
    "sg:province":"Lugo",
    "wof:name":"Vazquez Campelo Manuel",
    "wof:placetype":"venue"
},
  "geometry": {"coordinates":[-7.5660119057,43.0198059082],"type":"Point"}
}