{
  "type": "Feature",
  "properties": {
    "addr:full":"Cra. Seu D'urgell, Km. 0200,0 Prullans Lleida 25727",
    "addr:postcode":"25727",
    "addr:street":"D'Urgell Km. 0200,0",
    "iso:country":"ES",
    "sg:address":"Cra. Seu D'urgell, Km. 0200,0",
    "sg:city":"Prullans",
    "sg:orig_category":"Equitaci\u00d3n Y Centros De H\u00cdpica",
    "sg:phone":"+34 973 51 06 69",
    "sg:postcode":"25727",
    "sg:province":"Lleida",
    "sg:website":"www.xrutapirineo.com",
    "wof:name":"Enrich Vila Mateu",
    "wof:placetype":"venue"
},
  "geometry": {"coordinates":[1.7277799845,42.3959693909],"type":"Point"}
}