{
  "type": "Feature",
  "properties": {
    "iso:country":"ES",
    "sg:address":"Carr Comtes D'urgell, 47",
    "sg:city":"Lleida",
    "sg:orig_category":"Reposter\u00cdas",
    "sg:phone":"+34 973 24 80 61",
    "sg:postcode":"25005",
    "sg:province":"Lleida",
    "wof:name":"Lietos Grau Monica",
    "wof:placetype":"venue"
},
  "geometry": {"coordinates":[0.6326619983,41.624130249],"type":"Point"}
}