{
  "type": "Feature",
  "properties": {
    "addr:full":"Carrer de Sant Domenec, 49 Sabadell Barcelona 08208",
    "addr:housenumber":"49",
    "addr:postcode":"08208",
    "addr:street":"Carrer De Sant Domenec",
    "iso:country":"ES",
    "sg:address":"Carrer de Sant Domenec, 49",
    "sg:city":"Sabadell",
    "sg:orig_category":"Reciclaje, Tratamiento De Tejidos",
    "sg:phone":"+34 937 16 96 34",
    "sg:postcode":"08208",
    "sg:province":"Barcelona",
    "wof:name":"Clop Asens Pedro",
    "wof:placetype":"venue"
},
  "geometry": {"coordinates":[2.1010770798,41.557559967],"type":"Point"}
}