{
  "type": "Feature",
  "properties": {
    "iso:country":"ES",
    "sg:address":"Pol Ind El Tollo, 36",
    "sg:city":"Utiel",
    "sg:orig_category":"Mataderos Y Talleres De Despiezado",
    "sg:phone":"+34 962 17 43 11",
    "sg:postcode":"46300",
    "sg:province":"Valencia",
    "wof:name":"Matadero Comarcal Plana De Utiel S.l.",
    "wof:placetype":"venue"
},
  "geometry": {"coordinates":[-1.2064390182,39.5707588196],"type":"Point"}
}