{
  "type": "Feature",
  "properties": {
    "iso:country":"ES",
    "sg:address":"Carrer de Lluis Companys, 21",
    "sg:city":"Viladecans",
    "sg:orig_category":"Promotores Constructores",
    "sg:phone":"+34 936 59 17 29",
    "sg:postcode":"08840",
    "sg:province":"Barcelona",
    "wof:name":"Serrano Lopez Jose",
    "wof:placetype":"venue"
},
  "geometry": {"coordinates":[2.0088200569,41.3152923584],"type":"Point"}
}