{
  "type": "Feature",
  "properties": {
    "addr:full":"Avda Lancia, 26 Le\u00f3n Le\u00f3n 24004",
    "addr:housenumber":"26",
    "addr:postcode":"24004",
    "addr:street":"Avda Lancia;Leo\u0301N",
    "iso:country":"ES",
    "sg:address":"Avda Lancia, 26",
    "sg:city":"Le\u00f3n",
    "sg:orig_category":"Informaci\u00d3n Financiera Y Comercial",
    "sg:phone":"+34 987 25 97 37",
    "sg:postcode":"24004",
    "sg:province":"Le\u00f3n",
    "sg:website":"www.paginasamarillas.es",
    "wof:name":"Montecarlo Academia Y Servicios S.l.",
    "wof:placetype":"venue"
},
  "geometry": {"coordinates":[-5.5761551857,42.5938644409],"type":"Point"}
}