{
  "type": "Feature",
  "properties": {
    "iso:country":"ES",
    "sg:address":"Carrer de Pau Claris, 166",
    "sg:city":"Barcelona",
    "sg:orig_category":"Embajadas, Consulados Y Otras Representaciones Diplom\u00c1ticas",
    "sg:phone":"+34 934 87 10 00",
    "sg:postcode":"08037",
    "sg:province":"Barcelona",
    "wof:name":"Consulado Honorario De Corea En Barcelona",
    "wof:placetype":"venue"
},
  "geometry": {"coordinates":[2.1640870571,41.3952522278],"type":"Point"}
}