{
  "type": "Feature",
  "properties": {
    "addr:full":"Calle de Pez, 2 Madrid Madrid 28004",
    "addr:housenumber":"2",
    "addr:postcode":"28004",
    "addr:street":"Calle De Pez",
    "iso:country":"ES",
    "sg:address":"Calle de Pez, 2",
    "sg:city":"Madrid",
    "sg:orig_category":"Diarios, Prensa, Revistas (al Por Menor)",
    "sg:phone":"+34 915 23 24 80",
    "sg:postcode":"28004",
    "sg:province":"Madrid",
    "wof:name":"Caballero Segarra Fernando",
    "wof:placetype":"venue"
},
  "geometry": {"coordinates":[-3.7037410736,40.4227485657],"type":"Point"}
}