{
  "type": "Feature",
  "properties": {
    "addr:full":"Pl Font, 9 Santpedor Barcelona 08251",
    "addr:housenumber":"9",
    "addr:postcode":"08251",
    "addr:street":"Pl Font",
    "iso:country":"ES",
    "sg:address":"Pl Font, 9",
    "sg:city":"Santpedor",
    "sg:orig_category":"Sociedades, Compa\u00d1\u00cdas Aseguradoras",
    "sg:phone":"+34 938 32 04 01",
    "sg:postcode":"08251",
    "sg:province":"Barcelona",
    "wof:name":"Mapfre Servicios De Informatica",
    "wof:placetype":"venue"
},
  "geometry": {"coordinates":[1.8398590088,41.7841529846],"type":"Point"}
}