{
  "type": "Feature",
  "properties": {
    "iso:country":"ES",
    "sg:address":"Poli Las Capellanias, S/n",
    "sg:city":"Caceres",
    "sg:orig_category":"Empresas De Carpinter\u00cda De Madera",
    "sg:phone":"+34 927 23 06 53",
    "sg:postcode":"10005",
    "sg:province":"C\u00e1ceres",
    "wof:name":"Construcciones Pinilla S.a.",
    "wof:placetype":"venue"
},
  "geometry": {"coordinates":[-6.5341739655,39.4675254822],"type":"Point"}
}