{
  "type": "Feature",
  "properties": {
    "iso:country":"ES",
    "sg:address":"Montcabrer, 23",
    "sg:city":"Aldaia",
    "sg:orig_category":"Delegados, Agentes De Tr\u00c1nsito, Auxiliares De Transporte Internacional",
    "sg:phone":"+34 961 51 15 29",
    "sg:postcode":"46960",
    "sg:province":"Valencia",
    "wof:name":"Transportes Hermanos Lucas Saiz S.l.",
    "wof:placetype":"venue"
},
  "geometry": {"coordinates":[-0.4654270113,39.4715423584],"type":"Point"}
}