{
  "type": "Feature",
  "properties": {
    "addr:full":"Calle de Ginzo De Limia, 32 Madrid Madrid 28029",
    "addr:housenumber":"32",
    "addr:postcode":"madrid;28029",
    "addr:street":"Calle De Ginzo De Limia",
    "iso:country":"ES",
    "sg:address":"Calle de Ginzo De Limia, 32",
    "sg:city":"Madrid",
    "sg:orig_category":"Escayola Y Productos De Escayola (fabricaci\u00d3n, Al Por Mayor)",
    "sg:phone":"+34 913 78 01 53",
    "sg:postcode":"28029",
    "sg:province":"Madrid",
    "wof:name":"Camino Utrilla Pablo",
    "wof:placetype":"venue"
},
  "geometry": {"coordinates":[-3.7038118839,40.479057312],"type":"Point"}
}