{
  "type": "Feature",
  "properties": {
    "addr:full":"Avgd Balmes, 32 Lleida Lleida 25006",
    "addr:housenumber":"32",
    "addr:postcode":"25006",
    "addr:street":"Avgd Balmes",
    "iso:country":"ES",
    "sg:address":"Avgd Balmes, 32",
    "sg:city":"Lleida",
    "sg:orig_category":"Asesor\u00cda De Formaci\u00d3n Y Gesti\u00d3n De Personal",
    "sg:phone":"+34 973 22 01 82",
    "sg:postcode":"25006",
    "sg:province":"Lleida",
    "wof:name":"Asla 2000 S.l.",
    "wof:placetype":"venue"
},
  "geometry": {"coordinates":[0.6196835041,41.6183891296],"type":"Point"}
}