{
  "type": "Feature",
  "properties": {
    "iso:country":"ES",
    "sg:address":"Calle de Asturias, 43",
    "sg:city":"Granada",
    "sg:orig_category":"Art\u00cdculos De Decoraci\u00d3n",
    "sg:phone":"+34 958 81 67 61",
    "sg:postcode":"18007",
    "sg:province":"Granada",
    "wof:name":"Todo En Madera Y Decoracion Eleuterio S.l",
    "wof:placetype":"venue"
},
  "geometry": {"coordinates":[-3.5988929272,37.1513633728],"type":"Point"}
}