{
  "type": "Feature",
  "properties": {
    "iso:country":"ES",
    "sg:address":"Calle de Calderon De La Barca, 19",
    "sg:city":"Alacant",
    "sg:orig_category":"Ropa Para Caballeros (al Por Menor)",
    "sg:phone":"+34 965 20 97 60",
    "sg:postcode":"03004",
    "sg:province":"Alicante",
    "wof:name":"Pastor Guijarro Vicente",
    "wof:placetype":"venue"
},
  "geometry": {"coordinates":[-0.4857287109,38.3497085571],"type":"Point"}
}