{
  "type": "Feature",
  "properties": {
    "addr:full":"Avda Parque (del), 3 Lucena C\u00f3rdoba 14900",
    "addr:housenumber":"3",
    "addr:postcode":"14900",
    "addr:street":"Avda Parque Del",
    "iso:country":"ES",
    "sg:address":"Avda Parque (del), 3",
    "sg:city":"Lucena",
    "sg:orig_category":"M\u00c9dicos: Estomatolog\u00cda",
    "sg:phone":"+34 957 50 33 20",
    "sg:postcode":"14900",
    "sg:province":"C\u00f3rdoba",
    "wof:name":"Far Martinez Lisardo Juan",
    "wof:placetype":"venue"
},
  "geometry": {"coordinates":[-4.4921860695,37.4085617065],"type":"Point"}
}