{
  "type": "Feature",
  "properties": {
    "iso:country":"ES",
    "sg:address":"Carrer de Vila, 19",
    "sg:city":"Lloret Mar",
    "sg:orig_category":"Estilistas Y Estudios De Estilo De Corte Y Confecci\u00d3n",
    "sg:phone":"+34 972 36 08 71",
    "sg:postcode":"17310",
    "sg:province":"Girona",
    "wof:name":"Confecciones Pupi S.a.",
    "wof:placetype":"venue"
},
  "geometry": {"coordinates":[2.8486130238,41.6998672485],"type":"Point"}
}