{
  "type": "Feature",
  "properties": {
    "iso:country":"ES",
    "sg:address":"Salgueiro Do Mato, S/n",
    "sg:city":"Noalla",
    "sg:orig_category":"Estudios Y Construcci\u00d3n De Acuarios Y Viveros",
    "sg:phone":"+34 986 74 31 64",
    "sg:postcode":"36990",
    "sg:province":"Pontevedra",
    "wof:name":"Gonzalez Casal Manuel",
    "wof:placetype":"venue"
},
  "geometry": {"coordinates":[-8.858045578,42.4337234497],"type":"Point"}
}