{
  "type": "Feature",
  "properties": {
    "iso:country":"ES",
    "sg:address":"Avda Sierra Nevada, 128",
    "sg:city":"Cenes Vega",
    "sg:orig_category":"Electricidad: Instaladores",
    "sg:phone":"+34 958 48 70 47",
    "sg:postcode":"18190",
    "sg:province":"Granada",
    "wof:name":"Nadime Instalaciones S.l.",
    "wof:placetype":"venue"
},
  "geometry": {"coordinates":[-3.5320899487,37.1580123901],"type":"Point"}
}