{
  "type": "Feature",
  "properties": {
    "iso:country":"ES",
    "sg:address":"Calle de San Lesmes, 4",
    "sg:city":"Burgos",
    "sg:orig_category":"M\u00c9dicos: Cirug\u00cda General",
    "sg:phone":"+34 947 20 27 18",
    "sg:postcode":"09004",
    "sg:province":"Burgos",
    "wof:name":"Foro Gastroentereologico Burgales S.l.",
    "wof:placetype":"venue"
},
  "geometry": {"coordinates":[-3.6969549656,42.3418159485],"type":"Point"}
}