{
  "type": "Feature",
  "properties": {
    "addr:full":"Plaz Santo Domingo, 7 San Miguel Murcia 30008",
    "addr:housenumber":"7",
    "addr:postcode":"30008",
    "addr:street":"Santo Domingo",
    "iso:country":"ES",
    "sg:address":"Plaz Santo Domingo, 7",
    "sg:city":"San Miguel",
    "sg:orig_category":"Peluquer\u00cdas, Peluquer\u00cda Mixta",
    "sg:phone":"+34 968 23 88 81",
    "sg:postcode":"30008",
    "sg:province":"Murcia",
    "wof:name":"Garre Garcia Alicia",
    "wof:placetype":"venue"
},
  "geometry": {"coordinates":[-1.128461957,37.9874229431],"type":"Point"}
}