{
  "type": "Feature",
  "properties": {
    "addr:full":"Calle de Jose De Cadalso, 60 Madrid Madrid 28044",
    "addr:housenumber":"60",
    "addr:postcode":"madrid;28044",
    "addr:street":"Calle De Jose De Cadalso",
    "iso:country":"ES",
    "sg:address":"Calle de Jose De Cadalso, 60",
    "sg:city":"Madrid",
    "sg:orig_category":"Fabricaci\u00d3n De Peines Y De Accesorios De Peluquer\u00cda",
    "sg:phone":"+34 917 05 05 32",
    "sg:postcode":"28044",
    "sg:province":"Madrid",
    "sg:website":"www.rizos.es",
    "wof:name":"Saradina S.l.",
    "wof:placetype":"venue"
},
  "geometry": {"coordinates":[-3.768239975,40.3762702942],"type":"Point"}
}