{
  "type": "Feature",
  "properties": {
    "addr:full":"Humilladero, 5 Puerto De Bejar Salamanca 37720",
    "addr:housenumber":"5",
    "addr:postcode":"37720",
    "addr:street":"Humilladero",
    "iso:country":"ES",
    "sg:address":"Humilladero, 5",
    "sg:city":"Puerto De Bejar",
    "sg:orig_category":"Cerrajer\u00cda, Ferrallista",
    "sg:phone":"+34 923 41 40 74",
    "sg:postcode":"37720",
    "sg:province":"Salamanca",
    "wof:name":"Talleres Blanco Garrido S.l.",
    "wof:placetype":"venue"
},
  "geometry": {"coordinates":[-97.78224945069999,45.7040786743],"type":"Point"}
}