{
  "type": "Feature",
  "properties": {
    "iso:country":"ES",
    "sg:address":"Crta. Nal. Quinientas Veinticinco, 151",
    "sg:city":"Canizo",
    "sg:orig_category":"Plomeros",
    "sg:phone":"+34 988 42 11 50",
    "sg:postcode":"32548",
    "sg:province":"Ourense",
    "wof:name":"Bramaraf S.l.",
    "wof:placetype":"venue"
},
  "geometry": {"coordinates":[-7.099984169,42.0523986816],"type":"Point"}
}