{
  "type": "Feature",
  "properties": {
    "addr:full":"Calle de Santuario, 72 Madrid Madrid 28026",
    "addr:housenumber":"72",
    "addr:postcode":"madrid;28026",
    "addr:street":"Calle De Santuario",
    "iso:country":"ES",
    "sg:address":"Calle de Santuario, 72",
    "sg:city":"Madrid",
    "sg:orig_category":"Venta, Instalaci\u00d3n De Calefacci\u00d3n",
    "sg:phone":"+34 914 75 37 90",
    "sg:postcode":"28026",
    "sg:province":"Madrid",
    "wof:name":"Instalaciones Torrijos Y Ruiz C.b.",
    "wof:placetype":"venue"
},
  "geometry": {"coordinates":[-3.6995689869,40.3810424805],"type":"Point"}
}