{
  "type": "Feature",
  "properties": {
    "addr:full":"Calle de Escuelas (las), 3 Guadalcacin Del Caudillo C\u00e1diz 11591",
    "addr:housenumber":"3",
    "addr:postcode":"11591",
    "addr:street":"Calle De Escuelas Las",
    "iso:country":"ES",
    "sg:address":"Calle de Escuelas (las), 3",
    "sg:city":"Guadalcacin Del Caudillo",
    "sg:orig_category":"Bisuter\u00cda, Joyer\u00cda, Relojer\u00cda (al Por Menor)",
    "sg:phone":"+34 956 15 76 33",
    "sg:postcode":"11591",
    "sg:province":"C\u00e1diz",
    "wof:name":"Galera Mariscal Ana Maria",
    "wof:placetype":"venue"
},
  "geometry": {"coordinates":[-6.0871491432,36.7141685486],"type":"Point"}
}