{
  "type": "Feature",
  "properties": {
    "iso:country":"ES",
    "sg:address":"Avda Pirralos (los), 68",
    "sg:city":"Dos Hermanas",
    "sg:orig_category":"Empresas De Carpinter\u00cda De Madera",
    "sg:phone":"+34 955 66 49 38",
    "sg:postcode":"41700",
    "sg:province":"Sevilla",
    "wof:name":"Ferrimadera S.l.",
    "wof:placetype":"venue"
},
  "geometry": {"coordinates":[-5.9284758568,37.2768974304],"type":"Point"}
}