{
  "type": "Feature",
  "properties": {
    "iso:country":"ES",
    "sg:address":"Calle de Bernat Descoll, 66",
    "sg:city":"Valencia",
    "sg:orig_category":"Inform\u00c1tica (estudios, Servicios, Asesor\u00cda, Formaci\u00d3n)",
    "sg:phone":"+34 963 95 90 15",
    "sg:postcode":"46026",
    "sg:province":"Valencia",
    "wof:name":"Odema Levante S.l",
    "wof:placetype":"venue"
},
  "geometry": {"coordinates":[-0.3771448135,39.4513015747],"type":"Point"}
}