{
  "type": "Feature",
  "properties": {
    "iso:country":"ES",
    "sg:address":"Av Diagonal, 678",
    "sg:city":"Barcelona",
    "sg:orig_category":"Peluquer\u00cdas, Peluquer\u00cda Mixta",
    "sg:phone":"+34 932 80 28 73",
    "sg:postcode":"08034",
    "sg:province":"Barcelona",
    "wof:name":"Barnabusiness S.l.",
    "wof:placetype":"venue"
},
  "geometry": {"coordinates":[2.1236569881,41.3879089355],"type":"Point"}
}