{
  "type": "Feature",
  "properties": {
    "addr:full":"Carrer de Calvari Convent, 27 Callosa D'en Sarria Alicante 03510",
    "addr:housenumber":"27",
    "addr:postcode":"03510",
    "addr:street":"Carrer De Calvari Convent",
    "iso:country":"ES",
    "sg:address":"Carrer de Calvari Convent, 27",
    "sg:city":"Callosa D'en Sarria",
    "sg:orig_category":"Motocicletas (agentes, Concesionarios)",
    "sg:phone":"+34 965 88 09 12",
    "sg:postcode":"03510",
    "sg:province":"Alicante",
    "wof:name":"Gomez Castillo Jose Maria",
    "wof:placetype":"venue"
},
  "geometry": {"coordinates":[-0.1211301014,38.6513633728],"type":"Point"}
}