{
  "type": "Feature",
  "properties": {
    "iso:country":"ES",
    "sg:address":"Carr Teodoro Llorente, 10",
    "sg:city":"Burjassot",
    "sg:orig_category":"Perfumer\u00cda Y Cosm\u00c9tica (fabricaci\u00d3n, Al Por Mayor)",
    "sg:phone":"+34 963 90 12 50",
    "sg:postcode":"46100",
    "sg:province":"Valencia",
    "wof:name":"Belloch Hueso Francisco Javier",
    "wof:placetype":"venue"
},
  "geometry": {"coordinates":[-0.4153360128,39.508895874],"type":"Point"}
}