{
  "type": "Feature",
  "properties": {
    "addr:full":"Calle de Ruiz De Moros, 7 Alca\u00f1iz Teruel 44600",
    "addr:housenumber":"7",
    "addr:postcode":"44600",
    "addr:street":"Calle De Ruiz De Moros",
    "iso:country":"ES",
    "sg:address":"Calle de Ruiz De Moros, 7",
    "sg:city":"Alca\u00f1iz",
    "sg:orig_category":"Agencias De Viajes",
    "sg:phone":"+34 978 83 23 05",
    "sg:postcode":"44600",
    "sg:province":"Teruel",
    "sg:website":"www.marsns.com",
    "wof:name":"Viajes Ciberluna S.l.",
    "wof:placetype":"venue"
},
  "geometry": {"coordinates":[-0.127324,41.0456466675],"type":"Point"}
}