{
  "type": "Feature",
  "properties": {
    "addr:full":"Av Raiguer, 63 Inca Islas Baleares 07300",
    "addr:housenumber":"63",
    "addr:postcode":"07300",
    "addr:street":"Av Raiguer",
    "iso:country":"ES",
    "sg:address":"Av Raiguer, 63",
    "sg:city":"Inca",
    "sg:orig_category":"Maquinaria Para Industrias Diversas",
    "sg:phone":"+34 971 88 36 57",
    "sg:postcode":"07300",
    "sg:province":"Islas Baleares",
    "wof:name":"Pol Alorda Francisco",
    "wof:placetype":"venue"
},
  "geometry": {"coordinates":[2.9019999504,39.719329834],"type":"Point"}
}