{
  "type": "Feature",
  "properties": {
    "addr:full":"Ptda Albercoques, 165 Mutxamel Alicante 03110",
    "addr:housenumber":"165",
    "addr:postcode":"03110",
    "addr:street":"Ptda Albercoques",
    "iso:country":"ES",
    "sg:address":"Ptda Albercoques, 165",
    "sg:city":"Mutxamel",
    "sg:orig_category":"Establecimientos De Cura, Prevenci\u00d3n Y Readaptaci\u00d3n",
    "sg:phone":"+34 965 95 06 89",
    "sg:postcode":"03110",
    "sg:province":"Alicante",
    "wof:name":"Reto A La Esperanza",
    "wof:placetype":"venue"
},
  "geometry": {"coordinates":[-0.4448040128,38.4151039124],"type":"Point"}
}