{
  "type": "Feature",
  "properties": {
    "addr:full":"Zona Del Relleno, S/n Cee La Coru\u00f1a 15270",
    "addr:housenumber":"s / n",
    "addr:postcode":"15270",
    "addr:street":"La",
    "iso:country":"ES",
    "sg:address":"Zona Del Relleno, S/n",
    "sg:city":"Cee",
    "sg:orig_category":"Locales Y Clases De Danza",
    "sg:phone":"+34 981 74 52 68",
    "sg:postcode":"15270",
    "sg:province":"La Coru\u00f1a",
    "wof:name":"Arte E Movimento S.l.l.",
    "wof:placetype":"venue"
},
  "geometry": {"coordinates":[-9.1843671799,42.965423584],"type":"Point"}
}