{
  "type": "Feature",
  "properties": {
    "addr:full":"Carrer de Maria Paretas, 6 Barcelona Barcelona 08032",
    "addr:housenumber":"6",
    "addr:postcode":"08032",
    "addr:street":"Carrer De Maria Paretas",
    "iso:country":"ES",
    "sg:address":"Carrer de Maria Paretas, 6",
    "sg:city":"Barcelona",
    "sg:orig_category":"Florister\u00cdas",
    "sg:phone":"+34 934 29 51 22",
    "sg:postcode":"08032",
    "sg:province":"Barcelona",
    "wof:name":"Martinez Mendoza Antonio",
    "wof:placetype":"venue"
},
  "geometry": {"coordinates":[2.1600248814,41.4295883179],"type":"Point"}
}