{
  "type": "Feature",
  "properties": {
    "iso:country":"ES",
    "sg:address":"Calle de Dahellos, 9",
    "sg:city":"Elda",
    "sg:orig_category":"Procuradores",
    "sg:phone":"+34 965 39 43 15",
    "sg:postcode":"03600",
    "sg:province":"Alicante",
    "wof:name":"Rico Perez Emilio",
    "wof:placetype":"venue"
},
  "geometry": {"coordinates":[-0.7941144705,38.4767303467],"type":"Point"}
}