{
  "type": "Feature",
  "properties": {
    "iso:country":"ES",
    "sg:address":"Calle de Iberre Zeharbide, 3",
    "sg:city":"Elexalde Auzoa",
    "sg:orig_category":"Asociaciones Y Clubs Deportivos",
    "sg:phone":"+34 946 77 42 66",
    "sg:postcode":"48630",
    "sg:province":"Vizcaya",
    "wof:name":"Jimenez Onaindi Emilio",
    "wof:placetype":"venue"
},
  "geometry": {"coordinates":[-2.9351952076,43.412902832],"type":"Point"}
}