{
  "type": "Feature",
  "properties": {
    "iso:country":"ES",
    "sg:address":"Carrer de Nena Casas, 36",
    "sg:city":"Barcelona",
    "sg:orig_category":"Guarder\u00cdas",
    "sg:phone":"+34 932 04 55 89",
    "sg:postcode":"08017",
    "sg:province":"Barcelona",
    "wof:name":"Perez-alarcon Oneto Ana Maria",
    "wof:placetype":"venue"
},
  "geometry": {"coordinates":[2.1314270496,41.3954582214],"type":"Point"}
}