{
  "type": "Feature",
  "properties": {
    "iso:country":"ES",
    "sg:address":"Calle de Hilados, 18",
    "sg:city":"Torrejon Ardoz",
    "sg:orig_category":"Inversiones",
    "sg:phone":"+34 916 56 94 09",
    "sg:postcode":"28850",
    "sg:province":"Madrid",
    "wof:name":"Burgos Ballesteros Pedro Antonio",
    "wof:placetype":"venue"
},
  "geometry": {"coordinates":[-3.4609429836,40.4445724487],"type":"Point"}
}