{
  "type": "Feature",
  "properties": {
    "iso:country":"ES",
    "sg:address":"Avda Espa\u00d1a, 17",
    "sg:city":"Caceres",
    "sg:orig_category":"Ropa Para Se\u00d1oras (al Por Menor)",
    "sg:phone":"+34 927 24 24 68",
    "sg:postcode":"10002",
    "sg:province":"C\u00e1ceres",
    "wof:name":"Kimalupe Scaparate S.l.",
    "wof:placetype":"venue"
},
  "geometry": {"coordinates":[-6.3774561882,39.4704055786],"type":"Point"}
}