{
  "type": "Feature",
  "properties": {
    "iso:country":"ES",
    "sg:address":"Calle de Sagrada Familia, 15",
    "sg:city":"Granada",
    "sg:orig_category":"M\u00c9dicos: Estomatolog\u00cda",
    "sg:phone":"+34 958 20 74 45",
    "sg:postcode":"18015",
    "sg:province":"Granada",
    "wof:name":"Luque Torres Maria Del Carmen",
    "wof:placetype":"venue"
},
  "geometry": {"coordinates":[-3.6244440079,37.1913223267],"type":"Point"}
}