{
  "type": "Feature",
  "properties": {
    "iso:country":"ES",
    "sg:address":"Calle de Fuente Vieja, 19",
    "sg:city":"Puente Genave",
    "sg:orig_category":"Inform\u00c1tica, Ofim\u00c1tica (estudios, Asesor\u00cda, Ingenier\u00cda, Formaci\u00d3n)",
    "sg:phone":"+34 953 43 90 16",
    "sg:postcode":"23350",
    "sg:province":"Ja\u00e9n",
    "sg:website":"www.tecnosegura.com",
    "wof:name":"Soluciones Tecnologicas Para Segura S.l.u.",
    "wof:placetype":"venue"
},
  "geometry": {"coordinates":[-2.8041338921,38.3526268005],"type":"Point"}
}