{
  "type": "Feature",
  "properties": {
    "iso:country":"ES",
    "sg:address":"Calle de Do\u00d1a Urraca, S/n",
    "sg:city":"Salda\u00f1a",
    "sg:orig_category":"Molduras, Junquillos, Listones Y Molduras Perforadas",
    "sg:phone":"+34 979 89 11 86",
    "sg:postcode":"34100",
    "sg:province":"Palencia",
    "wof:name":"Robles Fernandez Manuel",
    "wof:placetype":"venue"
},
  "geometry": {"coordinates":[-4.7359228134,42.5220031738],"type":"Point"}
}