{
  "type": "Feature",
  "properties": {
    "iso:country":"ES",
    "sg:address":"Carr Mel, 13",
    "sg:city":"Cassa Selva",
    "sg:orig_category":"Inform\u00c1tica, Ofim\u00c1tica (estudios, Asesor\u00cda, Ingenier\u00cda, Formaci\u00d3n)",
    "sg:phone":"+34 972 46 21 73",
    "sg:postcode":"17244",
    "sg:province":"Girona",
    "sg:website":"www.moncasoft.com",
    "wof:name":"Moncasoft S.l.",
    "wof:placetype":"venue"
},
  "geometry": {"coordinates":[2.8780760765,41.8896598816],"type":"Point"}
}