{
  "type": "Feature",
  "properties": {
    "addr:full":"Calle de Real De San Sebastian, 22 Brunete Madrid 28690",
    "addr:housenumber":"22",
    "addr:postcode":"28690",
    "addr:street":"Calle De Real De San Sebastian",
    "iso:country":"ES",
    "sg:address":"Calle de Real De San Sebastian, 22",
    "sg:city":"Brunete",
    "sg:orig_category":"Energ\u00cda Solar Y Nuevas Energ\u00cdas (equipo, Estudios)",
    "sg:phone":"+34 918 16 43 74",
    "sg:postcode":"28690",
    "sg:province":"Madrid",
    "wof:name":"Zermastec S.l.",
    "wof:placetype":"venue"
},
  "geometry": {"coordinates":[-3.9961316586,40.401714325],"type":"Point"}
}