{
  "type": "Feature",
  "properties": {
    "addr:full":"Camino Viejo, S/n Vilafames Castell\u00f3n 12192",
    "addr:housenumber":"s / n",
    "addr:postcode":"12192",
    "addr:street":"Camino Viejo;Castello\u0301N",
    "iso:country":"ES",
    "sg:address":"Camino Viejo, S/n",
    "sg:city":"Vilafames",
    "sg:orig_category":"Mec\u00c1nico Del Autom\u00d3vil",
    "sg:phone":"+34 964 32 92 07",
    "sg:postcode":"12192",
    "sg:province":"Castell\u00f3n",
    "wof:name":"Andreu Benages Alvaro",
    "wof:placetype":"venue"
},
  "geometry": {"coordinates":[-0.0491511002,40.1162033081],"type":"Point"}
}