{
  "type": "Feature",
  "properties": {
    "addr:full":"Avda Coru\u00d1a (la), S/n Puente Valga Pontevedra 36645",
    "addr:postcode":"36645",
    "addr:street":"Avda Corun\u0303A La S / N Puente",
    "iso:country":"ES",
    "sg:address":"Avda Coru\u00d1a (la), S/n",
    "sg:city":"Puente Valga",
    "sg:orig_category":"Laboratorios Y Trabajos De Fotograf\u00cda, V\u00cddeo Y Cine",
    "sg:phone":"+34 986 55 95 07",
    "sg:postcode":"36645",
    "sg:province":"Pontevedra",
    "wof:name":"Pi\u00f1eiro Losada Maria Del Mar",
    "wof:placetype":"venue"
},
  "geometry": {"coordinates":[-8.6393947601,42.6959877014],"type":"Point"}
}