{
  "type": "Feature",
  "properties": {
    "iso:country":"ES",
    "sg:address":"Calle de Goya, 34",
    "sg:city":"Madrid",
    "sg:orig_category":"Ropa Para Se\u00d1oras (al Por Menor)",
    "sg:phone":"+34 915 76 60 60",
    "sg:postcode":"28001",
    "sg:province":"Madrid",
    "wof:name":"Martinez Martinez Sara De La Cruz",
    "wof:placetype":"venue"
},
  "geometry": {"coordinates":[-3.6812639236,40.4249305725],"type":"Point"}
}