{
  "type": "Feature",
  "properties": {
    "iso:country":"ES",
    "sg:address":"Estda Virxen Da Rocha, 4",
    "sg:city":"Percibilleira",
    "sg:orig_category":"Patatas (al Por Mayor)",
    "sg:phone":"+34 986 35 74 46",
    "sg:postcode":"36300",
    "sg:province":"Pontevedra",
    "wof:name":"Vilar Pedreira Jorge Manuel",
    "wof:placetype":"venue"
},
  "geometry": {"coordinates":[-8.8501644135,42.1211166382],"type":"Point"}
}