{
  "type": "Feature",
  "properties": {
    "iso:country":"ES",
    "sg:address":"Carrer de Argullos, 100",
    "sg:city":"Barcelona",
    "sg:orig_category":"Peluqueros: De Se\u00d1oras",
    "sg:phone":"+34 932 76 40 64",
    "sg:postcode":"08016",
    "sg:province":"Barcelona",
    "wof:name":"I\u00f1iguez Carazo Adela",
    "wof:placetype":"venue"
},
  "geometry": {"coordinates":[2.1792869568,41.4429359436],"type":"Point"}
}