{
  "type": "Feature",
  "properties": {
    "addr:full":"Flassaders, 22 Pol. Ind. Santiga Barcelona 08130",
    "addr:housenumber":"22",
    "addr:postcode":"08130",
    "addr:street":"Flassaders;Ind.",
    "iso:country":"ES",
    "sg:address":"Flassaders, 22",
    "sg:city":"Pol. Ind. Santiga",
    "sg:classifiers":[
        {
            "category":"Manufacturing",
            "subcategory":"Metals",
            "type":"Manufacturing & Wholesale Goods"
        }
    ],
    "sg:phone":"+34 937 29 71 10",
    "sg:postcode":"08130",
    "sg:province":"Barcelona",
    "sg:tags":[
        "en",
        "fundiciones"
    ],
    "wof:name":"Dynacast Espa\u00f1a S.a.",
    "wof:placetype":"venue"
},
  "geometry": {"coordinates":[2.1802799702,41.5371818542],"type":"Point"}
}