{
  "type": "Feature",
  "properties": {
    "addr:full":"Carrer de Sant Isidre (de), 132 S. Carles Rapita Tarragona 43540",
    "addr:housenumber":"132",
    "addr:postcode":"43540",
    "addr:street":"Carrer De Sant Isidre De;S. Carles Rapita",
    "iso:country":"ES",
    "sg:address":"Carrer de Sant Isidre (de), 132",
    "sg:city":"S. Carles Rapita",
    "sg:orig_category":"Quincaller\u00cda (al Por Menor)",
    "sg:phone":"+34 977 74 02 85",
    "sg:postcode":"43540",
    "sg:province":"Tarragona",
    "wof:name":"Gendre Silvestre Juan",
    "wof:placetype":"venue"
},
  "geometry": {"coordinates":[0.5879099965,40.6153106689],"type":"Point"}
}