{
  "type": "Feature",
  "properties": {
    "iso:country":"ES",
    "sg:address":"Urb. Port Addaia, 1",
    "sg:city":"Port Addaia",
    "sg:orig_category":"Supermercados Y Hipermercados",
    "sg:phone":"+34 971 18 89 67",
    "sg:postcode":"07730",
    "sg:province":"Islas Baleares",
    "wof:name":"Luemlo S.l.",
    "wof:placetype":"venue"
},
  "geometry": {"coordinates":[4.1400952339,39.930721283],"type":"Point"}
}