{
  "type": "Feature",
  "properties": {
    "addr:full":"Calle de San Sebastian, 8 Santa Cruz De Mudela Ciudad Real 13730",
    "addr:housenumber":"8",
    "addr:postcode":"13730",
    "addr:street":"Calle De San Sebastian",
    "iso:country":"ES",
    "sg:address":"Calle de San Sebastian, 8",
    "sg:city":"Santa Cruz De Mudela",
    "sg:orig_category":"Perfumer\u00cda (al Por Menor)",
    "sg:phone":"+34 926 34 20 16",
    "sg:postcode":"13730",
    "sg:province":"Ciudad Real",
    "wof:name":"Laguna Valverde Antonio",
    "wof:placetype":"venue"
},
  "geometry": {"coordinates":[-3.4647018909,38.6418457031],"type":"Point"}
}