{
  "type": "Feature",
  "properties": {
    "addr:full":"Carr Francoli, 22 Empuriabrava Girona 17487",
    "addr:housenumber":"22",
    "addr:postcode":"17487",
    "addr:street":"Carr Francoli",
    "iso:country":"ES",
    "sg:address":"Carr Francoli, 22",
    "sg:city":"Empuriabrava",
    "sg:orig_category":"Estudios, Instalaci\u00d3n De Climatizaci\u00d3n",
    "sg:phone":"+34 972 45 48 81",
    "sg:postcode":"17487",
    "sg:province":"Girona",
    "wof:name":"Electric Pablos S.l.",
    "wof:placetype":"venue"
},
  "geometry": {"coordinates":[3.1070549488,42.2568092346],"type":"Point"}
}