{
  "type": "Feature",
  "properties": {
    "addr:full":"Carrer de Mossen Aulet, 27 Manlleu Barcelona 08560",
    "addr:housenumber":"27",
    "addr:postcode":"08560",
    "addr:street":"Carrer De Mossen Aulet",
    "iso:country":"ES",
    "sg:address":"Carrer de Mossen Aulet, 27",
    "sg:city":"Manlleu",
    "sg:orig_category":"Molduras, Junquillos, Listones Y Molduras Perforadas",
    "sg:phone":"+34 938 51 00 24",
    "sg:postcode":"08560",
    "sg:province":"Barcelona",
    "wof:name":"Aviles Ventura Bernabe",
    "wof:placetype":"venue"
},
  "geometry": {"coordinates":[2.283438921,42.0070953369],"type":"Point"}
}