{
  "type": "Feature",
  "properties": {
    "addr:full":"Calle de Bri\u00d1as Luis, 3 Bilbao Vizcaya 48013",
    "addr:housenumber":"3",
    "addr:postcode":"48013",
    "addr:street":"Calle De Brin\u0303As Luis",
    "iso:country":"ES",
    "sg:address":"Calle de Bri\u00d1as Luis, 3",
    "sg:city":"Bilbao",
    "sg:orig_category":"Material Y Suministros Para Fotocopiadoras, Reprograf\u00cda",
    "sg:phone":"+34 944 42 52 16",
    "sg:postcode":"48013",
    "sg:province":"Vizcaya",
    "wof:name":"Selzur Vizcaya S. A.",
    "wof:placetype":"venue"
},
  "geometry": {"coordinates":[-2.9468319416,43.2635726929],"type":"Point"}
}