{
  "type": "Feature",
  "properties": {
    "addr:full":"Barr Auzo-txikia Auzoa, 9 Auzotxikia Guip\u00f9zcoa 20400",
    "addr:housenumber":"9",
    "addr:postcode":"20400",
    "addr:street":"Auzo-Txikia Auzoa;Guipu\u0300Zcoa",
    "iso:country":"ES",
    "sg:address":"Barr Auzo-txikia Auzoa, 9",
    "sg:city":"Auzotxikia",
    "sg:orig_category":"Muebles Y Decoraci\u00d3n De Jardines (fabricaci\u00d3n, Venta)",
    "sg:phone":"+34 943 65 32 10",
    "sg:postcode":"20400",
    "sg:province":"Guip\u00f9zcoa",
    "wof:name":"Eredu S. Coop.",
    "wof:placetype":"venue"
},
  "geometry": {"coordinates":[-2.0789339542,43.1339912415],"type":"Point"}
}