{
  "type": "Feature",
  "properties": {
    "iso:country":"ES",
    "sg:address":"Avda Francfort, 5",
    "sg:city":"Coslada",
    "sg:orig_category":"Empresarios",
    "sg:phone":"+34 916 69 96 36",
    "sg:postcode":"28820",
    "sg:province":"Madrid",
    "wof:name":"Cofran Reformas Y Construcciones S.l.",
    "wof:placetype":"venue"
},
  "geometry": {"coordinates":[-3.5410430431,40.4208030701],"type":"Point"}
}