{
  "type": "Feature",
  "properties": {
    "addr:full":"Carrer de Sagrera, 165 Barcelona Barcelona 08027",
    "addr:housenumber":"165",
    "addr:postcode":"08027",
    "addr:street":"Carrer De Sagrera",
    "iso:country":"ES",
    "sg:address":"Carrer de Sagrera, 165",
    "sg:city":"Barcelona",
    "sg:orig_category":"Zapater\u00cds Y Cordeler\u00cda",
    "sg:phone":"+34 933 52 90 03",
    "sg:postcode":"08027",
    "sg:province":"Barcelona",
    "wof:name":"Ara Perez Miguel",
    "wof:placetype":"venue"
},
  "geometry": {"coordinates":[2.1909666061,41.4260368347],"type":"Point"}
}