{
  "type": "Feature",
  "properties": {
    "iso:country":"ES",
    "sg:address":"Carrer de Francesc Suau, 16",
    "sg:city":"Palma",
    "sg:orig_category":"Quincaller\u00cda (al Por Menor)",
    "sg:phone":"+34 971 29 37 06",
    "sg:postcode":"07010",
    "sg:province":"Islas Baleares",
    "wof:name":"Mesquida Garcia Francisco",
    "wof:placetype":"venue"
},
  "geometry": {"coordinates":[2.6518969536,39.5838851929],"type":"Point"}
}