{
  "type": "Feature",
  "properties": {
    "addr:full":"Avda San Jorge, 65 Andorra Teruel 44500",
    "addr:housenumber":"65",
    "addr:postcode":"44500",
    "addr:street":"Avda San Jorge",
    "iso:country":"ES",
    "sg:address":"Avda San Jorge, 65",
    "sg:city":"Andorra",
    "sg:orig_category":"Heladeros",
    "sg:phone":"+34 978 84 25 52",
    "sg:postcode":"44500",
    "sg:province":"Teruel",
    "wof:name":"Heladeria-cafeteria Tomy",
    "wof:placetype":"venue"
},
  "geometry": {"coordinates":[-0.4449000061,40.9768562317],"type":"Point"}
}