{
  "type": "Feature",
  "properties": {
    "iso:country":"ES",
    "sg:address":"Avda Camelias, 32",
    "sg:city":"Vigo",
    "sg:orig_category":"Farmacias",
    "sg:phone":"+34 986 42 55 10",
    "sg:postcode":"36202",
    "sg:province":"Pontevedra",
    "wof:name":"Farmacia Soli\u00f1o-soutelo C.b.",
    "wof:placetype":"venue"
},
  "geometry": {"coordinates":[-8.7297687531,42.2316741943],"type":"Point"}
}