{
  "type": "Feature",
  "properties": {
    "addr:full":"Avda Paz (la), S/n Sevilla Sevilla 41013",
    "addr:postcode":"41013",
    "addr:street":"Avda Paz La S / N",
    "iso:country":"ES",
    "sg:address":"Avda Paz (la), S/n",
    "sg:city":"Sevilla",
    "sg:orig_category":"Pescader\u00cdas (al Por Menor)",
    "sg:phone":"+34 954 23 95 10",
    "sg:postcode":"41013",
    "sg:province":"Sevilla",
    "wof:name":"Manday Carrion Maria Isabel",
    "wof:placetype":"venue"
},
  "geometry": {"coordinates":[-5.9701337814,37.3707695007],"type":"Point"}
}