{
  "type": "Feature",
  "properties": {
    "addr:full":"Carrer de Rauric, 1 Barcelona Barcelona 08002",
    "addr:housenumber":"1",
    "addr:postcode":"08002",
    "addr:street":"Carrer De Rauric",
    "iso:country":"ES",
    "sg:address":"Carrer de Rauric, 1",
    "sg:city":"Barcelona",
    "sg:orig_category":"Estancos",
    "sg:phone":"+34 934 12 05 68",
    "sg:postcode":"08002",
    "sg:province":"Barcelona",
    "wof:name":"Pich Martinez Rosendo",
    "wof:placetype":"venue"
},
  "geometry": {"coordinates":[2.1748518944,41.3815612793],"type":"Point"}
}