{
  "type": "Feature",
  "properties": {
    "iso:country":"ES",
    "sg:address":"Carrer de Secretari Coloma, 79",
    "sg:city":"Barcelona",
    "sg:orig_category":"Cervecer\u00cdas",
    "sg:phone":"+34 932 84 01 47",
    "sg:postcode":"08024",
    "sg:province":"Barcelona",
    "wof:name":"Marques Castillo Antonio",
    "wof:placetype":"venue"
},
  "geometry": {"coordinates":[2.1625349522,41.409828186],"type":"Point"}
}