{
  "type": "Feature",
  "properties": {
    "iso:country":"ES",
    "sg:address":"Calle de Maria De Guzman, 55",
    "sg:city":"Madrid",
    "sg:orig_category":"Abogados",
    "sg:phone":"+34 915 34 36 71",
    "sg:postcode":"28003",
    "sg:province":"Madrid",
    "wof:name":"Garcia-moya Martin Angel",
    "wof:placetype":"venue"
},
  "geometry": {"coordinates":[-3.697065115,40.444152832],"type":"Point"}
}