{
  "type": "Feature",
  "properties": {
    "iso:country":"ES",
    "sg:address":"Calle de Galicia, 2",
    "sg:city":"Vitoria-gasteiz",
    "sg:orig_category":"Promotores Constructores",
    "sg:phone":"+34 945 28 93 66",
    "sg:postcode":"01003",
    "sg:province":"\u00c1lava",
    "wof:name":"Urbyobras, S.l",
    "wof:placetype":"venue"
},
  "geometry": {"coordinates":[-2.6599988937,42.8494682312],"type":"Point"}
}