{
  "type": "Feature",
  "properties": {
    "iso:country":"ES",
    "sg:address":"Jose Artetxe Kalea, 9",
    "sg:city":"Azpeitia",
    "sg:orig_category":"Asesor\u00cda Sobre Comunicaci\u00d3n De Empresas",
    "sg:phone":"+34 943 81 11 16",
    "sg:postcode":"20730",
    "sg:province":"Guip\u00f9zcoa",
    "wof:name":"Euroi S.a.",
    "wof:placetype":"venue"
},
  "geometry": {"coordinates":[-2.2677059174,43.1816596985],"type":"Point"}
}