{
  "type": "Feature",
  "properties": {
    "iso:country":"ES",
    "sg:address":"Avda Espa\u00d1a, 3",
    "sg:city":"Cedeira",
    "sg:orig_category":"Florister\u00cdas",
    "sg:phone":"+34 981 48 27 45",
    "sg:postcode":"15350",
    "sg:province":"La Coru\u00f1a",
    "wof:name":"Diaz Nebril Catalina",
    "wof:placetype":"venue"
},
  "geometry": {"coordinates":[-8.0532312393,43.6601715088],"type":"Point"}
}