{
  "type": "Feature",
  "properties": {
    "iso:country":"ES",
    "sg:address":"Calle de Tambre, 4",
    "sg:city":"Malaga",
    "sg:orig_category":"Madera Para Construcci\u00d3n E Industria",
    "sg:phone":"+34 952 28 03 48",
    "sg:postcode":"29010",
    "sg:province":"M\u00e1laga",
    "wof:name":"Bricotorlo S.l.",
    "wof:placetype":"venue"
},
  "geometry": {"coordinates":[-4.4509549141,36.7328109741],"type":"Point"}
}