{
  "type": "Feature",
  "properties": {
    "iso:country":"ES",
    "sg:address":"Apto Club Nautico, 1",
    "sg:city":"Manga Mar Menor",
    "sg:orig_category":"Promotores Constructores",
    "sg:phone":"+34 968 56 30 72",
    "sg:postcode":"30380",
    "sg:province":"Murcia",
    "wof:name":"Richard Jhon Keeble Stanley",
    "wof:placetype":"venue"
},
  "geometry": {"coordinates":[-0.7281540036,37.6686553955],"type":"Point"}
}