{
  "type": "Feature",
  "properties": {
    "addr:full":"Av L'hospital Militar, 32 Barcelona Barcelona 08023",
    "addr:housenumber":"32",
    "addr:postcode":"08023",
    "addr:street":"Av L'Hospital Militar",
    "iso:country":"ES",
    "sg:address":"Av L'hospital Militar, 32",
    "sg:city":"Barcelona",
    "sg:orig_category":"Farmacias",
    "sg:phone":"+34 932 17 89 20",
    "sg:postcode":"08023",
    "sg:province":"Barcelona",
    "wof:name":"Farmacia Ferrer-gironella S.c.p.",
    "wof:placetype":"venue"
},
  "geometry": {"coordinates":[2.1406440735,41.4200019836],"type":"Point"}
}