{
  "type": "Feature",
  "properties": {
    "addr:full":"Calle de Jose Calderon, 141 Campanillas M\u00e1laga 29590",
    "addr:housenumber":"141",
    "addr:postcode":"29590",
    "addr:street":"Calle De Jose Calderon;Ma\u0301Laga",
    "iso:country":"ES",
    "sg:address":"Calle de Jose Calderon, 141",
    "sg:city":"Campanillas",
    "sg:orig_category":"Promotores Constructores",
    "sg:phone":"+34 952 43 44 40",
    "sg:postcode":"29590",
    "sg:province":"M\u00e1laga",
    "wof:name":"Construcciones Genix Malaga S.l.",
    "wof:placetype":"venue"
},
  "geometry": {"coordinates":[-4.5224900246,36.7190055847],"type":"Point"}
}