{
  "type": "Feature",
  "properties": {
    "addr:full":"Carrer de Doctor Sanmarti, S/n Calldetenes Barcelona 08519",
    "addr:housenumber":"s / n",
    "addr:postcode":"08519",
    "addr:street":"Carrer De Doctor Sanmarti",
    "iso:country":"ES",
    "sg:address":"Carrer de Doctor Sanmarti, S/n",
    "sg:city":"Calldetenes",
    "sg:orig_category":"Forjas Y Altos Hornos",
    "sg:phone":"+34 938 89 27 99",
    "sg:postcode":"08519",
    "sg:province":"Barcelona",
    "wof:name":"Pampliega Carol Jaume",
    "wof:placetype":"venue"
},
  "geometry": {"coordinates":[-97.78224945069999,45.7040786743],"type":"Point"}
}