{
  "type": "Feature",
  "properties": {
    "addr:full":"Trva Deportes, S/n Campaspero Valladolid 47310",
    "addr:housenumber":"s / n",
    "addr:postcode":"47310",
    "iso:country":"ES",
    "sg:address":"Trva Deportes, S/n",
    "sg:city":"Campaspero",
    "sg:orig_category":"M\u00c1rmoles, Granitos Y Piedras Naturales",
    "sg:phone":"+34 983 69 83 39",
    "sg:postcode":"47310",
    "sg:province":"Valladolid",
    "wof:name":"Piedras Y Marmoles Moclan S.l.",
    "wof:placetype":"venue"
},
  "geometry": {"coordinates":[-4.1933231354,41.4907531738],"type":"Point"}
}