{
  "type": "Feature",
  "properties": {
    "iso:country":"ES",
    "sg:address":"Calle de Lauaxeta, 3",
    "sg:city":"Santurtzi",
    "sg:orig_category":"Molduras, Junquillos, Listones Y Molduras Perforadas",
    "sg:phone":"+34 944 83 79 99",
    "sg:postcode":"48980",
    "sg:province":"Vizcaya",
    "wof:name":"Marina Abasolo Pereira",
    "wof:placetype":"venue"
},
  "geometry": {"coordinates":[-3.0389339924,43.322353363],"type":"Point"}
}