{
  "type": "Feature",
  "properties": {
    "iso:country":"ES",
    "sg:address":"Calle de Ventura Rodriguez, 8",
    "sg:city":"Madrid",
    "sg:orig_category":"Loter\u00cda Y T\u00d3mbola",
    "sg:phone":"+34 915 41 60 74",
    "sg:postcode":"28008",
    "sg:province":"Madrid",
    "wof:name":"Jimenez-alfaro Goma Maria Del Carmen",
    "wof:placetype":"venue"
},
  "geometry": {"coordinates":[-3.7137994766,40.4253692627],"type":"Point"}
}