{
  "type": "Feature",
  "properties": {
    "addr:full":"Calle de Alicante, 10 Arganda Madrid 28500",
    "addr:housenumber":"10",
    "addr:postcode":"28500",
    "addr:street":"Calle De Alicante",
    "iso:country":"ES",
    "sg:address":"Calle de Alicante, 10",
    "sg:city":"Arganda",
    "sg:orig_category":"Construcciones Met\u00c1licas",
    "sg:phone":"+34 918 71 39 96",
    "sg:postcode":"28500",
    "sg:province":"Madrid",
    "wof:name":"Metalisteria Y Construcciones S.a.",
    "wof:placetype":"venue"
},
  "geometry": {"coordinates":[-3.4590699673,40.3072624207],"type":"Point"}
}