{
  "type": "Feature",
  "properties": {
    "addr:full":"Calle de Matilde Sanguesa, 15 Zaragoza Zaragoza 50014",
    "addr:housenumber":"15",
    "addr:postcode":"50014",
    "addr:street":"Calle De Matilde Sanguesa",
    "iso:country":"ES",
    "sg:address":"Calle de Matilde Sanguesa, 15",
    "sg:city":"Zaragoza",
    "sg:orig_category":"Ingenier\u00cda, Centros De Estudios (diversos)",
    "sg:phone":"+34 976 20 39 40",
    "sg:postcode":"50014",
    "sg:province":"Zaragoza",
    "sg:website":"www.gevs.net",
    "wof:name":"Ingenieria Aplicada Gevs S.l.",
    "wof:placetype":"venue"
},
  "geometry": {"coordinates":[-0.8710489869,41.6609611511],"type":"Point"}
}