{
  "type": "Feature",
  "properties": {
    "iso:country":"ES",
    "sg:address":"Rbla Sant Francesc, 21",
    "sg:city":"Vilafranca Penedes",
    "sg:orig_category":"Molduras, Junquillos, Listones Y Molduras Perforadas",
    "sg:phone":"+34 938 18 21 21",
    "sg:postcode":"08720",
    "sg:province":"Barcelona",
    "wof:name":"Jin  Jian Wei",
    "wof:placetype":"venue"
},
  "geometry": {"coordinates":[1.698505044,41.345413208],"type":"Point"}
}