{
  "type": "Feature",
  "properties": {
    "iso:country":"ES",
    "sg:address":"Calle de Calvario, 34",
    "sg:city":"Tomelloso",
    "sg:orig_category":"Inform\u00c1tica, Ofim\u00c1tica (estudios, Asesor\u00cda, Ingenier\u00cda, Formaci\u00d3n)",
    "sg:phone":"+34 926 50 27 58",
    "sg:postcode":"13700",
    "sg:province":"Ciudad Real",
    "wof:name":"Sistemas Informaticos Macha Este S.l.",
    "wof:placetype":"venue"
},
  "geometry": {"coordinates":[-3.0242900848,39.155796051],"type":"Point"}
}