{
  "type": "Feature",
  "properties": {
    "addr:full":"Calle de Albarracin, 29 Cella Teruel 44370",
    "addr:housenumber":"29",
    "addr:postcode":"44370",
    "addr:street":"Calle De Albarracin",
    "iso:country":"ES",
    "sg:address":"Calle de Albarracin, 29",
    "sg:city":"Cella",
    "sg:orig_category":"Albergues",
    "sg:phone":"+34 978 65 02 40",
    "sg:postcode":"44370",
    "sg:province":"Teruel",
    "wof:name":"Hostal Hermanas Miedes C.b.",
    "wof:placetype":"venue"
},
  "geometry": {"coordinates":[-1.2863156796,40.4514770508],"type":"Point"}
}