{
  "type": "Feature",
  "properties": {
    "addr:full":"Rua San Amaro, 19 Ferrol La Coru\u00f1a 15403",
    "addr:housenumber":"19",
    "addr:postcode":"15403",
    "addr:street":"Rua San Amaro;La Corun\u0303A",
    "iso:country":"ES",
    "sg:address":"Rua San Amaro, 19",
    "sg:city":"Ferrol",
    "sg:orig_category":"Psic\u00d3logos",
    "sg:phone":"+34 981 37 27 47",
    "sg:postcode":"15403",
    "sg:province":"La Coru\u00f1a",
    "wof:name":"Garcia Regueira Marcelino Manuel",
    "wof:placetype":"venue"
},
  "geometry": {"coordinates":[-8.2294778824,43.4842948914],"type":"Point"}
}