{
  "type": "Feature",
  "properties": {
    "addr:full":"Carrer de Sant Cristofol, 42 Manresa Barcelona 08243",
    "addr:housenumber":"42",
    "addr:postcode":"08243",
    "addr:street":"Carrer De Sant Cristofol",
    "iso:country":"ES",
    "sg:address":"Carrer de Sant Cristofol, 42",
    "sg:city":"Manresa",
    "sg:orig_category":"Albergues",
    "sg:phone":"+34 938 74 31 02",
    "sg:postcode":"08243",
    "sg:province":"Barcelona",
    "wof:name":"Residencia Asistencial De Manresa",
    "wof:placetype":"venue"
},
  "geometry": {"coordinates":[1.8378939629,41.7276573181],"type":"Point"}
}