{
  "type": "Feature",
  "properties": {
    "iso:country":"ES",
    "sg:address":"Ctra Santiuste, S/n",
    "sg:city":"Nava Asuncion",
    "sg:orig_category":"Empresas De Carpinter\u00cda De Madera",
    "sg:phone":"+34 921 58 08 61",
    "sg:postcode":"40450",
    "sg:province":"Segovia",
    "wof:name":"Molduras Samboal S.l.",
    "wof:placetype":"venue"
},
  "geometry": {"coordinates":[-4.4939489365,41.15599823],"type":"Point"}
}