{
  "type": "Feature",
  "properties": {
    "addr:full":"Calle de Pedro Monago, 2 Arroyo S Servan Badajoz 06850",
    "addr:housenumber":"2",
    "addr:postcode":"06850",
    "addr:street":"Calle De Pedro Monago;Arroyo S Servan",
    "iso:country":"ES",
    "sg:address":"Calle de Pedro Monago, 2",
    "sg:city":"Arroyo S Servan",
    "sg:orig_category":"Cajas De Ahorro",
    "sg:phone":"+34 924 34 23 01",
    "sg:postcode":"06850",
    "sg:province":"Badajoz",
    "sg:website":"www.cajadebadajoz.es",
    "wof:name":"Caja De Badajoz",
    "wof:placetype":"venue"
},
  "geometry": {"coordinates":[-6.4544987679,38.8532409668],"type":"Point"}
}