{
  "type": "Feature",
  "properties": {
    "addr:full":"San J. Bosco, 13 Iru\u00f1a Navarra 31007",
    "addr:housenumber":"13",
    "addr:postcode":"31007",
    "addr:street":"Irun\u0303A Navarra",
    "iso:country":"ES",
    "sg:address":"San J. Bosco, 13",
    "sg:city":"Iru\u00f1a",
    "sg:orig_category":"Barnizadores",
    "sg:phone":"+34 948 26 98 04",
    "sg:postcode":"31007",
    "sg:province":"Navarra",
    "wof:name":"Iriarte Beperet Eusebio",
    "wof:placetype":"venue"
},
  "geometry": {"coordinates":[-1.6484899521,42.8042182922],"type":"Point"}
}