{
  "type": "Feature",
  "properties": {
    "addr:full":"Calle de Barcelona, S/n Burgos Burgos 09007",
    "addr:housenumber":"/ n",
    "addr:postcode":"09007",
    "addr:street":"Calle De Barcelona S",
    "iso:country":"ES",
    "sg:address":"Calle de Barcelona, S/n",
    "sg:city":"Burgos",
    "sg:orig_category":"Agencias De Viajes",
    "sg:phone":"+34 947 24 42 18",
    "sg:postcode":"09007",
    "sg:province":"Burgos",
    "sg:website":"www.barceloviajes.com",
    "wof:name":"Blanco Blanco Carlos Olalla",
    "wof:placetype":"venue"
},
  "geometry": {"coordinates":[-3.6696140766,42.350063324],"type":"Point"}
}