{
  "type": "Feature",
  "properties": {
    "iso:country":"ES",
    "sg:address":"Cami De Benavent, S/n",
    "sg:city":"Rossello",
    "sg:orig_category":"Fabricaci\u00d3n, Alquiler, Venta De Encofrados",
    "sg:phone":"+34 973 73 05 17",
    "sg:postcode":"25124",
    "sg:province":"Lleida",
    "wof:name":"Martinez Exposito Antonia",
    "wof:placetype":"venue"
},
  "geometry": {"coordinates":[0.6130800247,41.6945495605],"type":"Point"}
}