{
  "type": "Feature",
  "properties": {
    "addr:full":"Calle de Real, 105 Padul Granada 18640",
    "addr:housenumber":"105",
    "addr:postcode":"18640",
    "addr:street":"Calle De Real",
    "iso:country":"ES",
    "sg:address":"Calle de Real, 105",
    "sg:city":"Padul",
    "sg:orig_category":"Papeler\u00cdas, Librer\u00cdas",
    "sg:phone":"+34 958 79 03 78",
    "sg:postcode":"18640",
    "sg:province":"Granada",
    "wof:name":"Santiago Molina Lucia",
    "wof:placetype":"venue"
},
  "geometry": {"coordinates":[-3.6249670982,37.0248985291],"type":"Point"}
}