{
  "type": "Feature",
  "properties": {
    "addr:full":"Calle de Vicente Mo\u00d1ux, 16 Sig\u00fcenza Guadalajara 19250",
    "addr:housenumber":"16",
    "addr:postcode":"19250",
    "addr:street":"Calle De Vicente Mon\u0303Ux",
    "iso:country":"ES",
    "sg:address":"Calle de Vicente Mo\u00d1ux, 16",
    "sg:city":"Sig\u00fcenza",
    "sg:orig_category":"Electrodom\u00c9sticos (al Por Menor)",
    "sg:phone":"+34 949 39 18 94",
    "sg:postcode":"19250",
    "sg:province":"Guadalajara",
    "wof:name":"Comunidad De Bienes Ademar",
    "wof:placetype":"venue"
},
  "geometry": {"coordinates":[-2.6441791058,41.0704116821],"type":"Point"}
}