{
  "type": "Feature",
  "properties": {
    "addr:full":"Plaz Primero De Mayo - Aldea M, S/n Caceres C\u00e1ceres 10195",
    "addr:housenumber":"/ n",
    "addr:postcode":"10195",
    "addr:street":"Plaz Primero;Mayo Aldea;Ca\u0301Ceres",
    "iso:country":"ES",
    "sg:address":"Plaz Primero De Mayo - Aldea M, S/n",
    "sg:city":"Caceres",
    "sg:orig_category":"Electricidad: Instaladores",
    "sg:phone":"+34 927 23 52 41",
    "sg:postcode":"10195",
    "sg:province":"C\u00e1ceres",
    "wof:name":"Novillo Galapero Antonio",
    "wof:placetype":"venue"
},
  "geometry": {"coordinates":[-6.3894138336,39.4513931274],"type":"Point"}
}