{
  "type": "Feature",
  "properties": {
    "addr:full":"Avda Ourense (de), 208 Xinzo De Limia Ourense 32630",
    "addr:housenumber":"208",
    "addr:postcode":"32630",
    "addr:street":"Avda Ourense De",
    "iso:country":"ES",
    "sg:address":"Avda Ourense (de), 208",
    "sg:city":"Xinzo De Limia",
    "sg:orig_category":"Producci\u00d3n, Venta De Productos De Agricultura Biol\u00d3gica",
    "sg:phone":"+34 988 46 21 15",
    "sg:postcode":"32630",
    "sg:province":"Ourense",
    "wof:name":"Grupo La Laguna De Orense C.b.",
    "wof:placetype":"venue"
},
  "geometry": {"coordinates":[-7.7259440422,42.0631408691],"type":"Point"}
}