{
  "type": "Feature",
  "properties": {
    "addr:full":"Rua Igrexa, 40 Ferrol La Coru\u00f1a 15402",
    "addr:housenumber":"40",
    "addr:postcode":"15402",
    "addr:street":"Rua Igrexa;La Corun\u0303A",
    "iso:country":"ES",
    "sg:address":"Rua Igrexa, 40",
    "sg:city":"Ferrol",
    "sg:orig_category":"Agentes Generales De Seguros",
    "sg:phone":"+34 981 35 19 34",
    "sg:postcode":"15402",
    "sg:province":"La Coru\u00f1a",
    "wof:name":"Presas Vilar Maria Del Carmen",
    "wof:placetype":"venue"
},
  "geometry": {"coordinates":[-8.2273387909,43.4868507385],"type":"Point"}
}