{
  "type": "Feature",
  "properties": {
    "iso:country":"ES",
    "sg:address":"Calle de San Juan, 9",
    "sg:city":"Amorebieta",
    "sg:orig_category":"Molduras, Junquillos, Listones Y Molduras Perforadas",
    "sg:phone":"+34 946 73 12 61",
    "sg:postcode":"48340",
    "sg:province":"Vizcaya",
    "wof:name":"Gallastegi Bilbao Mikel",
    "wof:placetype":"venue"
},
  "geometry": {"coordinates":[-2.7309389114,43.2186813354],"type":"Point"}
}