{
  "type": "Feature",
  "properties": {
    "addr:full":"Ctra Valladolid, 76 Traspinedo Valladolid 47330",
    "addr:housenumber":"76",
    "addr:postcode":"47330",
    "addr:street":"Ctra Valladolid",
    "iso:country":"ES",
    "sg:address":"Ctra Valladolid, 76",
    "sg:city":"Traspinedo",
    "sg:orig_category":"Empresas De Impermeabilizaci\u00d3n",
    "sg:phone":"+34 983 68 24 86",
    "sg:postcode":"47330",
    "sg:province":"Valladolid",
    "wof:name":"Aguado Nu\u00f1ez Construcciones S.l.",
    "wof:placetype":"venue"
},
  "geometry": {"coordinates":[-4.4791536331,41.579875946],"type":"Point"}
}