{
  "type": "Feature",
  "properties": {
    "addr:full":"Calle de Padre Isla, 45 Cistierna Le\u00f3n 24800",
    "addr:housenumber":"45",
    "addr:postcode":"24800",
    "addr:street":"Calle De Padre Isla;Leo\u0301N",
    "iso:country":"ES",
    "sg:address":"Calle de Padre Isla, 45",
    "sg:city":"Cistierna",
    "sg:orig_category":"Electrodom\u00c9sticos (al Por Menor)",
    "sg:phone":"+34 987 70 12 49",
    "sg:postcode":"24800",
    "sg:province":"Le\u00f3n",
    "wof:name":"Comercial Industrial Aparicio S.l.",
    "wof:placetype":"venue"
},
  "geometry": {"coordinates":[-5.1311588287,42.8044204712],"type":"Point"}
}