{
  "type": "Feature",
  "properties": {
    "iso:country":"ES",
    "sg:address":"Calle de Cardenal Siliceo, 21",
    "sg:city":"Madrid",
    "sg:orig_category":"Fotocopias, Reprograf\u00cda",
    "sg:phone":"+34 915 19 78 56",
    "sg:postcode":"28002",
    "sg:province":"Madrid",
    "sg:website":"www.reproline.com",
    "wof:name":"Repro Line S.l.",
    "wof:placetype":"venue"
},
  "geometry": {"coordinates":[-3.6703290939,40.4443206787],"type":"Point"}
}