{
  "type": "Feature",
  "properties": {
    "addr:full":"Calle de Batalla Del Salado, 6 Plasencia C\u00e1ceres 10600",
    "addr:housenumber":"6",
    "addr:postcode":"10600",
    "addr:street":"Calle De Batalla Del Salado;Ca\u0301Ceres",
    "iso:country":"ES",
    "sg:address":"Calle de Batalla Del Salado, 6",
    "sg:city":"Plasencia",
    "sg:orig_category":"Carnicer\u00cdas, Carnicer\u00cdas",
    "sg:phone":"+34 927 41 11 02",
    "sg:postcode":"10600",
    "sg:province":"C\u00e1ceres",
    "wof:name":"Pizarro Gil Manuel",
    "wof:placetype":"venue"
},
  "geometry": {"coordinates":[-6.0802454948,40.0406913757],"type":"Point"}
}