{
  "type": "Feature",
  "properties": {
    "iso:country":"ES",
    "sg:address":"Calle de Conde De Altea, 57",
    "sg:city":"Altea",
    "sg:orig_category":"Explotaci\u00d3n De Canteras",
    "sg:phone":"+34 965 84 06 50",
    "sg:postcode":"03590",
    "sg:province":"Alicante",
    "wof:name":"Gravera Quintanes S.l.",
    "wof:placetype":"venue"
},
  "geometry": {"coordinates":[-0.0448755994,38.6032028198],"type":"Point"}
}