{
  "type": "Feature",
  "properties": {
    "addr:full":"Calle de Don Bosco, 7 Ubeda Ja\u00e9n 23400",
    "addr:housenumber":"7",
    "addr:postcode":"23400",
    "addr:street":"Calle De Don Bosco;Jae\u0301N",
    "iso:country":"ES",
    "sg:address":"Calle de Don Bosco, 7",
    "sg:city":"Ubeda",
    "sg:orig_category":"Laboratorios Y Trabajos De Fotograf\u00cda, V\u00cddeo Y Cine",
    "sg:phone":"+34 953 75 57 05",
    "sg:postcode":"23400",
    "sg:province":"Ja\u00e9n",
    "wof:name":"Madrid Jurado Jose",
    "wof:placetype":"venue"
},
  "geometry": {"coordinates":[-3.3784775734,38.0159835815],"type":"Point"}
}