{
  "type": "Feature",
  "properties": {
    "addr:full":"Rua Quiroga Ballesteros, 12 Lugo Lugo 27001",
    "addr:housenumber":"12",
    "addr:postcode":"27001",
    "addr:street":"Rua Quiroga Ballesteros",
    "iso:country":"ES",
    "sg:address":"Rua Quiroga Ballesteros, 12",
    "sg:city":"Lugo",
    "sg:orig_category":"Contables",
    "sg:phone":"+34 982 24 16 05",
    "sg:postcode":"27001",
    "sg:province":"Lugo",
    "wof:name":"Fernandez-reija Martinez Federico",
    "wof:placetype":"venue"
},
  "geometry": {"coordinates":[-7.5582327843,43.0126075745],"type":"Point"}
}