{
  "type": "Feature",
  "properties": {
    "iso:country":"ES",
    "sg:address":"Co. Chueca, S/n",
    "sg:city":"Sonseca",
    "sg:orig_category":"Fabricaci\u00d3n De Muebles",
    "sg:phone":"+34 925 38 09 70",
    "sg:postcode":"45100",
    "sg:province":"Toledo",
    "wof:name":"Maderu S.l.",
    "wof:placetype":"venue"
},
  "geometry": {"coordinates":[-3.9704089165,39.685344696],"type":"Point"}
}