{
  "type": "Feature",
  "properties": {
    "iso:country":"ES",
    "sg:address":"Duque De Ahumada, 7",
    "sg:city":"Iru\u00f1a",
    "sg:orig_category":"Peleter\u00cdas",
    "sg:phone":"+34 948 22 20 66",
    "sg:postcode":"31002",
    "sg:province":"Navarra",
    "wof:name":"Echarri Perez Eustaquio",
    "wof:placetype":"venue"
},
  "geometry": {"coordinates":[-1.6420459747,42.8160972595],"type":"Point"}
}