{
  "type": "Feature",
  "properties": {
    "iso:country":"ES",
    "sg:address":"Avda Blas Infante, 44",
    "sg:city":"Villanueva Concepcion",
    "sg:orig_category":"Sociedades, Compa\u00d1\u00cdas Aseguradoras",
    "sg:phone":"+34 952 75 35 11",
    "sg:postcode":"29230",
    "sg:province":"M\u00e1laga",
    "sg:website":"www.mapfre.com",
    "wof:name":"Mapfre Servicios De Informatica S.a.",
    "wof:placetype":"venue"
},
  "geometry": {"coordinates":[-4.5290870667,36.9319877625],"type":"Point"}
}