{
  "type": "Feature",
  "properties": {
    "iso:country":"ES",
    "sg:address":"Ctra Rellinars, 103",
    "sg:city":"Terrassa",
    "sg:orig_category":"Ropa Para Se\u00d1oras (al Por Menor)",
    "sg:phone":"+34 937 89 21 71",
    "sg:postcode":"08225",
    "sg:province":"Barcelona",
    "wof:name":"Fortes Ruiz Mari Carmen",
    "wof:placetype":"venue"
},
  "geometry": {"coordinates":[2.0084929466,41.5728416443],"type":"Point"}
}