{
  "type": "Feature",
  "properties": {
    "iso:country":"ES",
    "sg:address":"Calle de Segundo Izpizua, 17",
    "sg:city":"Donostia-san Sebastian",
    "sg:orig_category":"Psic\u00d3logos",
    "sg:phone":"+34 943 28 51 51",
    "sg:postcode":"20001",
    "sg:province":"Guip\u00f9zcoa",
    "wof:name":"Gonzalez Ibarrola Teresa",
    "wof:placetype":"venue"
},
  "geometry": {"coordinates":[-1.9711500406,43.3249473572],"type":"Point"}
}