{
  "type": "Feature",
  "properties": {
    "addr:full":"Carrer de Roca I Roca, 29 Terrassa Barcelona 08226",
    "addr:housenumber":"29",
    "addr:postcode":"08226",
    "addr:street":"Carrer De Roca I Roca",
    "iso:country":"ES",
    "sg:address":"Carrer de Roca I Roca, 29",
    "sg:city":"Terrassa",
    "sg:orig_category":"Suministros Para Hoteles",
    "sg:phone":"+34 937 35 71 29",
    "sg:postcode":"08226",
    "sg:province":"Barcelona",
    "wof:name":"Predis R&r 29 S.l.",
    "wof:placetype":"venue"
},
  "geometry": {"coordinates":[2.0184071064,41.5738792419],"type":"Point"}
}