{
  "type": "Feature",
  "properties": {
    "iso:country":"ES",
    "sg:address":"Calle de Murillo, 14",
    "sg:city":"Miajadas",
    "sg:orig_category":"Comercio, Reparaci\u00d3n De Motocicletas, Bicicletas Y Piezas Sueltas",
    "sg:phone":"+34 927 34 82 37",
    "sg:postcode":"10100",
    "sg:province":"C\u00e1ceres",
    "wof:name":"Vera Barragan Lorenzo",
    "wof:placetype":"venue"
},
  "geometry": {"coordinates":[-5.912788868,39.1501693726],"type":"Point"}
}