{
  "type": "Feature",
  "properties": {
    "addr:full":"Calle de Verdaguer Y Garcia, 46 Madrid Madrid 28027",
    "addr:housenumber":"46",
    "addr:postcode":"madrid;28027",
    "addr:street":"Calle De Verdaguer Y Garcia",
    "iso:country":"ES",
    "sg:address":"Calle de Verdaguer Y Garcia, 46",
    "sg:city":"Madrid",
    "sg:orig_category":"Asesor\u00cda Fiscal Y Jur\u00cddica",
    "sg:phone":"+34 914 03 27 43",
    "sg:postcode":"28027",
    "sg:province":"Madrid",
    "wof:name":"J.l. Big Consulting S.l.",
    "wof:placetype":"venue"
},
  "geometry": {"coordinates":[-3.6544411182,40.4403419495],"type":"Point"}
}