{
  "type": "Feature",
  "properties": {
    "addr:full":"Calle de Pocillo, 18 Villanueva Serena Badajoz 06700",
    "addr:housenumber":"18",
    "addr:postcode":"06700",
    "addr:street":"Calle De Pocillo",
    "iso:country":"ES",
    "sg:address":"Calle de Pocillo, 18",
    "sg:city":"Villanueva Serena",
    "sg:orig_category":"Peluqueros: De Se\u00d1oras",
    "sg:phone":"+34 924 84 25 14",
    "sg:postcode":"06700",
    "sg:province":"Badajoz",
    "wof:name":"Horrillo Romero Ana Maria",
    "wof:placetype":"venue"
},
  "geometry": {"coordinates":[-5.7927408218,38.9731750488],"type":"Point"}
}