{
  "type": "Feature",
  "properties": {
    "iso:country":"ES",
    "sg:address":"Acc. A Veiga, 10",
    "sg:city":"San Cibrao",
    "sg:orig_category":"Empresas De Limpieza",
    "sg:phone":"+34 982 59 41 05",
    "sg:postcode":"27890",
    "sg:province":"Lugo",
    "wof:name":"Jofra S. A.",
    "wof:placetype":"venue"
},
  "geometry": {"coordinates":[-7.4429941177,43.6938285828],"type":"Point"}
}