{
  "type": "Feature",
  "properties": {
    "addr:full":"Ptge Sant Jordi, 1 Tarrega Lleida 25300",
    "addr:housenumber":"1",
    "addr:postcode":"25300",
    "addr:street":"Ptge Sant Jordi",
    "iso:country":"ES",
    "sg:address":"Ptge Sant Jordi, 1",
    "sg:city":"Tarrega",
    "sg:orig_category":"Pescader\u00cdas (al Por Menor)",
    "sg:phone":"+34 973 31 11 46",
    "sg:postcode":"25300",
    "sg:province":"Lleida",
    "wof:name":"Soteras Barril Maria Del Mar",
    "wof:placetype":"venue"
},
  "geometry": {"coordinates":[1.1388449669,41.6532745361],"type":"Point"}
}