{
  "type": "Feature",
  "properties": {
    "iso:country":"ES",
    "sg:address":"Plaz Antonia Rodriguez, S/n",
    "sg:city":"Villafranca De La Sierra",
    "sg:orig_category":"Promotores Constructores",
    "sg:phone":"+34 920 36 76 26",
    "sg:postcode":"05570",
    "sg:province":"\u00c1vila",
    "wof:name":"Argenta Lopez Julia",
    "wof:placetype":"venue"
},
  "geometry": {"coordinates":[-5.2307291031,40.4977302551],"type":"Point"}
}