{
  "type": "Feature",
  "properties": {
    "iso:country":"ES",
    "sg:address":"Calle de Antonio Lopez Lopez, S/n",
    "sg:city":"Santa Cruz De Tenerife",
    "sg:orig_category":"Bazares, Art\u00cdculos De Limpieza Y De Cocina (al Por Menor)",
    "sg:phone":"+34 922 65 33 33",
    "sg:postcode":"38009",
    "sg:province":"Santa Cruz De Tenerife",
    "wof:name":"Padron Quintero Ernesto",
    "wof:placetype":"venue"
},
  "geometry": {"coordinates":[-16.2769851685,28.4534168243],"type":"Point"}
}