{
  "type": "Feature",
  "properties": {
    "addr:full":"Avda Maestro Rodrigo (musico), 12 Valencia Valencia 46015",
    "addr:housenumber":"12",
    "addr:postcode":"46015",
    "addr:street":"Avda Maestro Rodrigo Musico",
    "iso:country":"ES",
    "sg:address":"Avda Maestro Rodrigo (musico), 12",
    "sg:city":"Valencia",
    "sg:orig_category":"Pintura Y Barniz (al Por Menor)",
    "sg:phone":"+34 963 48 09 09",
    "sg:postcode":"46015",
    "sg:province":"Valencia",
    "wof:name":"Jose Antonio Garcia Suministros Generale",
    "wof:placetype":"venue"
},
  "geometry": {"coordinates":[-0.3974939883,39.4776191711],"type":"Point"}
}