{
  "type": "Feature",
  "properties": {
    "addr:full":"Carrer de Miquel Vives, 5 Terrassa Barcelona 08222",
    "addr:housenumber":"5",
    "addr:postcode":"08222",
    "addr:street":"Carrer De Miquel Vives",
    "iso:country":"ES",
    "sg:address":"Carrer de Miquel Vives, 5",
    "sg:city":"Terrassa",
    "sg:orig_category":"Colchones (fabricaci\u00d3n, Al Por Mayor, Al Por Menor)",
    "sg:phone":"+34 937 85 57 63",
    "sg:postcode":"08222",
    "sg:province":"Barcelona",
    "wof:name":"Parra Pozo Manuel",
    "wof:placetype":"venue"
},
  "geometry": {"coordinates":[2.0194420815,41.5632553101],"type":"Point"}
}