{
  "type": "Feature",
  "properties": {
    "iso:country":"ES",
    "sg:address":"Calle de Behenabarre, 5",
    "sg:city":"Legizamon",
    "sg:orig_category":"Higiene, Belleza: Art\u00cdculos (al Por Menor)",
    "sg:phone":"+34 944 40 24 11",
    "sg:postcode":"48450",
    "sg:province":"Vizcaya",
    "sg:website":"www.coprohi.com",
    "wof:name":"Elementos De Seguridad Coprohi S.l.",
    "wof:placetype":"venue"
},
  "geometry": {"coordinates":[-2.8968265057,43.2497253418],"type":"Point"}
}