{
  "type": "Feature",
  "properties": {
    "iso:country":"ES",
    "sg:address":"Ace\u00f1a, 40",
    "sg:city":"Moguer",
    "sg:orig_category":"Productores Recolectores, Venta Directa De Vinos",
    "sg:phone":"+34 959 37 00 04",
    "sg:postcode":"21800",
    "sg:province":"Huelva",
    "wof:name":"Saenz Jimenez Cosme",
    "wof:placetype":"venue"
},
  "geometry": {"coordinates":[-6.8342490196,37.2783584595],"type":"Point"}
}