{
  "type": "Feature",
  "properties": {
    "iso:country":"ES",
    "sg:address":"Calle de Magistral Dominguez, 17",
    "sg:city":"Almeria",
    "sg:orig_category":"Peluqueros: De Se\u00d1oras",
    "sg:phone":"+34 950 25 17 63",
    "sg:postcode":"04003",
    "sg:province":"Almer\u00eda",
    "wof:name":"Martinez Chacon Antonio",
    "wof:placetype":"venue"
},
  "geometry": {"coordinates":[-2.4646649361,36.8433074951],"type":"Point"}
}