{
  "type": "Feature",
  "properties": {
    "addr:full":"Carrer de Ravells, Dels, 6 Cala D'or Islas Baleares 07660",
    "addr:housenumber":"6",
    "addr:postcode":"07660",
    "addr:street":"Carrer De Ravells Dels",
    "iso:country":"ES",
    "sg:address":"Carrer de Ravells, Dels, 6",
    "sg:city":"Cala D'or",
    "sg:orig_category":"Molduras, Junquillos, Listones Y Molduras Perforadas",
    "sg:phone":"+34 971 64 36 54",
    "sg:postcode":"07660",
    "sg:province":"Islas Baleares",
    "wof:name":"Allo Vali\u00f1a Jose Maria",
    "wof:placetype":"venue"
},
  "geometry": {"coordinates":[3.2323157787,39.3761940002],"type":"Point"}
}