{
  "type": "Feature",
  "properties": {
    "iso:country":"ES",
    "sg:address":"Calle de Nazario Calonge (de), 1",
    "sg:city":"San Fernando De Henares",
    "sg:orig_category":"Molduras, Junquillos, Listones Y Molduras Perforadas",
    "sg:phone":"+34 916 72 10 83",
    "sg:postcode":"28830",
    "sg:province":"Madrid",
    "wof:name":"Rodriguez Menchero Jose Luis",
    "wof:placetype":"venue"
},
  "geometry": {"coordinates":[-3.5302839279,40.4259986877],"type":"Point"}
}