{
  "type": "Feature",
  "properties": {
    "iso:country":"ES",
    "sg:address":"Calle de Sanabria, S/n",
    "sg:city":"Benavente",
    "sg:orig_category":"Promotores Constructores",
    "sg:phone":"+34 980 63 82 69",
    "sg:postcode":"49600",
    "sg:province":"Zamora",
    "wof:name":"Farelo Y Folgueral S.l.",
    "wof:placetype":"venue"
},
  "geometry": {"coordinates":[-5.6713991165,42.0028305054],"type":"Point"}
}