{
  "type": "Feature",
  "properties": {
    "iso:country":"ES",
    "sg:address":"Calle de Hierro (el), 1",
    "sg:city":"Realejo Alto",
    "sg:orig_category":"Ense\u00d1anza, Formaci\u00d3n Profesional: Aprendizaje",
    "sg:phone":"+34 922 34 01 13",
    "sg:postcode":"38410",
    "sg:province":"Santa Cruz De Tenerife",
    "wof:name":"Ayuntamiento De Los Realejos",
    "wof:placetype":"venue"
},
  "geometry": {"coordinates":[-16.5844135284,28.3802261353],"type":"Point"}
}