{
  "type": "Feature",
  "properties": {
    "addr:full":"Carr Paterna, 1 Eliana Valencia 46183",
    "addr:housenumber":"1",
    "addr:postcode":"46183",
    "addr:street":"Carr Paterna",
    "iso:country":"ES",
    "sg:address":"Carr Paterna, 1",
    "sg:city":"Eliana",
    "sg:orig_category":"M\u00c9dicos: Pediatr\u00cda. Enfermedades De Los Ni\u00d1os",
    "sg:phone":"+34 962 74 05 69",
    "sg:postcode":"46183",
    "sg:province":"Valencia",
    "wof:name":"Cuadrado Martinez Pascual",
    "wof:placetype":"venue"
},
  "geometry": {"coordinates":[-0.528208971,39.5667457581],"type":"Point"}
}