{
  "type": "Feature",
  "properties": {
    "addr:full":"Avda Alcoy, 81 Alacant Alicante 03009",
    "addr:housenumber":"81",
    "addr:postcode":"03009",
    "addr:street":"Avda Alcoy",
    "iso:country":"ES",
    "sg:address":"Avda Alcoy, 81",
    "sg:city":"Alacant",
    "sg:orig_category":"Agentes Generales De Seguros",
    "sg:phone":"+34 965 24 87 52",
    "sg:postcode":"03009",
    "sg:province":"Alicante",
    "wof:name":"Forner Gomez Maria Rosario",
    "wof:placetype":"venue"
},
  "geometry": {"coordinates":[-0.4882580042,38.3556861877],"type":"Point"}
}