{
  "type": "Feature",
  "properties": {
    "addr:full":"Calle de Fray Ceferino, 16 Oviedo Asturias 33001",
    "addr:housenumber":"16",
    "addr:postcode":"33001",
    "addr:street":"Calle De Fray Ceferino",
    "iso:country":"ES",
    "sg:address":"Calle de Fray Ceferino, 16",
    "sg:city":"Oviedo",
    "sg:orig_category":"Ropa Para Ni\u00d1os (al Por Menor)",
    "sg:phone":"+34 985 22 55 03",
    "sg:postcode":"33001",
    "sg:province":"Asturias",
    "wof:name":"Gonzalez Navarro Angelina",
    "wof:placetype":"venue"
},
  "geometry": {"coordinates":[-5.8519201279,43.3660049438],"type":"Point"}
}