{
  "type": "Feature",
  "properties": {
    "addr:full":"Carrer de Badajoz, 86 Barcelona Barcelona 08005",
    "addr:housenumber":"86",
    "addr:postcode":"08005",
    "addr:street":"Carrer De Badajoz",
    "iso:country":"ES",
    "sg:address":"Carrer de Badajoz, 86",
    "sg:city":"Barcelona",
    "sg:orig_category":"Molduras, Junquillos, Listones Y Molduras Perforadas",
    "sg:phone":"+34 933 09 40 23",
    "sg:postcode":"08005",
    "sg:province":"Barcelona",
    "wof:name":"Sanahuja Lavernia Alberto",
    "wof:placetype":"venue"
},
  "geometry": {"coordinates":[2.1957359314,41.3985900879],"type":"Point"}
}