{
  "type": "Feature",
  "properties": {
    "addr:full":"Landeta Hiribidea, 1 Azpeitia Guip\u00f9zcoa 20730",
    "addr:housenumber":"1",
    "addr:postcode":"20730",
    "addr:street":"Landeta Hiribidea;Guipu\u0300Zcoa",
    "iso:country":"ES",
    "sg:address":"Landeta Hiribidea, 1",
    "sg:city":"Azpeitia",
    "sg:orig_category":"Herramientas Manuales (fabricaci\u00d3n, Al Por Mayor)",
    "sg:phone":"+34 943 81 20 39",
    "sg:postcode":"20730",
    "sg:province":"Guip\u00f9zcoa",
    "wof:name":"Jose Esnaola Luluaga Y Otro Cdad.",
    "wof:placetype":"venue"
},
  "geometry": {"coordinates":[-2.2592871189,43.1780662537],"type":"Point"}
}