{
  "type": "Feature",
  "properties": {
    "iso:country":"ES",
    "sg:address":"Ptda Fileta, 377",
    "sg:city":"Castellon De La Plana",
    "sg:orig_category":"Promotores Constructores",
    "sg:phone":"+34 964 28 61 34",
    "sg:postcode":"12004",
    "sg:province":"Castell\u00f3n",
    "wof:name":"Construccions Esgarcas S.l.",
    "wof:placetype":"venue"
},
  "geometry": {"coordinates":[0.0330299996,40.0113639832],"type":"Point"}
}