{
  "type": "Feature",
  "properties": {
    "addr:full":"Calle de Garcia Rivero Maestro, 1 Bilbao Vizcaya 48011",
    "addr:housenumber":"1",
    "addr:postcode":"48011",
    "addr:street":"Calle De Garcia Rivero Maestro",
    "iso:country":"ES",
    "sg:address":"Calle de Garcia Rivero Maestro, 1",
    "sg:city":"Bilbao",
    "sg:orig_category":"Molduras, Junquillos, Listones Y Molduras Perforadas",
    "sg:phone":"+34 944 41 22 49",
    "sg:postcode":"48011",
    "sg:province":"Vizcaya",
    "wof:name":"Pereda Ramila Jose Luis",
    "wof:placetype":"venue"
},
  "geometry": {"coordinates":[-2.938740015,43.2624702454],"type":"Point"}
}