{
  "type": "Feature",
  "properties": {
    "addr:full":"Avda Ejercito (del), 13 Arganda Madrid 28500",
    "addr:housenumber":"13",
    "addr:postcode":"28500",
    "addr:street":"Avda Ejercito Del",
    "iso:country":"ES",
    "sg:address":"Avda Ejercito (del), 13",
    "sg:city":"Arganda",
    "sg:orig_category":"Papeler\u00cdas, Librer\u00cdas",
    "sg:phone":"+34 918 71 26 37",
    "sg:postcode":"28500",
    "sg:province":"Madrid",
    "wof:name":"Papeleria Sayri S.l.",
    "wof:placetype":"venue"
},
  "geometry": {"coordinates":[-3.4455060959,40.3015098572],"type":"Point"}
}