{
  "type": "Feature",
  "properties": {
    "iso:country":"ES",
    "sg:address":"Carrer de Guadalquivir, 25",
    "sg:city":"Terrassa",
    "sg:orig_category":"Construcciones Met\u00c1licas",
    "sg:phone":"+34 937 36 10 86",
    "sg:postcode":"08223",
    "sg:province":"Barcelona",
    "wof:name":"Metalisteria Sol Valles S.l.",
    "wof:placetype":"venue"
},
  "geometry": {"coordinates":[2.0315980911,41.5559501648],"type":"Point"}
}