{
  "type": "Feature",
  "properties": {
    "iso:country":"ES",
    "sg:address":"Calle de San Juan De La Cruz, 26",
    "sg:city":"Avila",
    "sg:orig_category":"Centros P\u00dablicos De Formaci\u00d3n Profesional Y T\u00c9cnica",
    "sg:phone":"+34 920 22 29 47",
    "sg:postcode":"05001",
    "sg:province":"\u00c1vila",
    "wof:name":"Colegio Oficial De Medicos De Avila",
    "wof:placetype":"venue"
},
  "geometry": {"coordinates":[-4.6918668747,40.654586792],"type":"Point"}
}