{
  "type": "Feature",
  "properties": {
    "addr:full":"Plaz Libertades (de Las), 1 Benaocaz C\u00e1diz 11612",
    "addr:housenumber":"1",
    "addr:postcode":"11612",
    "addr:street":"Plaz Libertades De Las",
    "iso:country":"ES",
    "sg:address":"Plaz Libertades (de Las), 1",
    "sg:city":"Benaocaz",
    "sg:orig_category":"Administraciones Regionales, Departamentales Y Locales",
    "sg:phone":"+34 956 12 55 00",
    "sg:postcode":"11612",
    "sg:province":"C\u00e1diz",
    "wof:name":"Ayuntamiento De Benaocaz",
    "wof:placetype":"venue"
},
  "geometry": {"coordinates":[-5.4225239754,36.7011413574],"type":"Point"}
}