{
  "type": "Feature",
  "properties": {
    "addr:full":"Calle de Gran Via, 23 Zaragoza Zaragoza 50006",
    "addr:housenumber":"23",
    "addr:postcode":"50006",
    "addr:street":"Calle De Gran Via",
    "iso:country":"ES",
    "sg:address":"Calle de Gran Via, 23",
    "sg:city":"Zaragoza",
    "sg:orig_category":"Abogados",
    "sg:phone":"+34 976 21 78 57",
    "sg:postcode":"50006",
    "sg:province":"Zaragoza",
    "wof:name":"Laguna Aranda Enrique",
    "wof:placetype":"venue"
},
  "geometry": {"coordinates":[-0.8887705207,41.6456756592],"type":"Point"}
}