{
  "type": "Feature",
  "properties": {
    "iso:country":"ES",
    "sg:address":"Avda Generalisimo, 84",
    "sg:city":"Pagan",
    "sg:orig_category":"Hoteles",
    "sg:phone":"+34 968 33 50 22",
    "sg:postcode":"30740",
    "sg:province":"Murcia",
    "wof:name":"Promociones Turisticas Sociales S.l.",
    "wof:placetype":"venue"
},
  "geometry": {"coordinates":[-0.7860090137,37.8153991699],"type":"Point"}
}