{
  "type": "Feature",
  "properties": {
    "addr:full":"Carrer de Sant Lluis, S/n Gava Barcelona 08850",
    "addr:housenumber":"s / n",
    "addr:postcode":"08850",
    "addr:street":"Carrer De Sant Lluis",
    "iso:country":"ES",
    "sg:address":"Carrer de Sant Lluis, S/n",
    "sg:city":"Gava",
    "sg:orig_category":"Iglesias Cristianas Diversas",
    "sg:phone":"+34 936 62 67 74",
    "sg:postcode":"08850",
    "sg:province":"Barcelona",
    "wof:name":"Testigos Cristianos De Jehova",
    "wof:placetype":"venue"
},
  "geometry": {"coordinates":[1.9962450266,41.3069915771],"type":"Point"}
}