{
  "type": "Feature",
  "properties": {
    "iso:country":"ES",
    "sg:address":"Avda Ruzafa, 9",
    "sg:city":"Benidorm",
    "sg:orig_category":"Albergues",
    "sg:phone":"+34 965 85 77 08",
    "sg:postcode":"03500",
    "sg:province":"Alicante",
    "wof:name":"Casta\u00f1o Parra Jose",
    "wof:placetype":"venue"
},
  "geometry": {"coordinates":[-0.1740590036,38.5364303589],"type":"Point"}
}