{
  "type": "Feature",
  "properties": {
    "addr:full":"Calle de Ponce De Leon, 1 Marinas Almer\u00eda 04740",
    "addr:housenumber":"1",
    "addr:postcode":"04740",
    "addr:street":"Calle De Ponce De Leon;Almeri\u0301A",
    "iso:country":"ES",
    "sg:address":"Calle de Ponce De Leon, 1",
    "sg:city":"Marinas",
    "sg:orig_category":"Centros Empresariales",
    "sg:phone":"+34 950 33 41 17",
    "sg:postcode":"04740",
    "sg:province":"Almer\u00eda",
    "wof:name":"Fernandez Mu\u00f1oz Juan Miguel",
    "wof:placetype":"venue"
},
  "geometry": {"coordinates":[-2.6286640167,36.733039856],"type":"Point"}
}