{
  "type": "Feature",
  "properties": {
    "addr:full":"Calle de Visitacion, 11 Valencia Valencia 46009",
    "addr:housenumber":"11",
    "addr:postcode":"46009",
    "addr:street":"Calle De Visitacion",
    "iso:country":"ES",
    "sg:address":"Calle de Visitacion, 11",
    "sg:city":"Valencia",
    "sg:orig_category":"Lencer\u00cda Femenina, Corseter\u00cda, Trajes De Ba\u00d1o (al Por Menor)",
    "sg:phone":"+34 963 47 61 69",
    "sg:postcode":"46009",
    "sg:province":"Valencia",
    "wof:name":"Almacenes Mari Y Compa\u00f1ia S. L.",
    "wof:placetype":"venue"
},
  "geometry": {"coordinates":[-0.3771770895,39.483669281],"type":"Point"}
}