{
  "type": "Feature",
  "properties": {
    "iso:country":"ES",
    "sg:address":"Calle de Felix Rodriguez De La Fuente, 12",
    "sg:city":"Peligros",
    "sg:orig_category":"Promotores Constructores",
    "sg:phone":"+34 958 40 21 12",
    "sg:postcode":"18210",
    "sg:province":"Granada",
    "wof:name":"Fincas Propisa S.l.",
    "wof:placetype":"venue"
},
  "geometry": {"coordinates":[-3.6285641193,37.2301559448],"type":"Point"}
}