{
  "type": "Feature",
  "properties": {
    "addr:full":"Carr Carretera, Km. 0481,0 Sidamon Lleida 25222",
    "addr:postcode":"25222",
    "addr:street":"Carr Carretera Km. 0481,0",
    "iso:country":"ES",
    "sg:address":"Carr Carretera, Km. 0481,0",
    "sg:city":"Sidamon",
    "sg:orig_category":"Ferreter\u00cda (diversos)",
    "sg:phone":"+34 973 56 02 45",
    "sg:postcode":"25222",
    "sg:province":"Lleida",
    "wof:name":"Essin99 S.l.",
    "wof:placetype":"venue"
},
  "geometry": {"coordinates":[0.8337649703,41.6283798218],"type":"Point"}
}