{
  "type": "Feature",
  "properties": {
    "iso:country":"ES",
    "sg:address":"Carrer de Pansa (de La), 10",
    "sg:city":"Pedreguer",
    "sg:orig_category":"Inmobiliaria (agencias)",
    "sg:phone":"+34 966 45 72 28",
    "sg:postcode":"03750",
    "sg:province":"Alicante",
    "wof:name":"Boronat Torres S.l.",
    "wof:placetype":"venue"
},
  "geometry": {"coordinates":[0.0417170003,38.8004493713],"type":"Point"}
}