{
  "type": "Feature",
  "properties": {
    "iso:country":"ES",
    "sg:address":"Calle de Los Frailes, S/n",
    "sg:city":"Frailes",
    "sg:orig_category":"Engranajes Y Elementos De Transmisi\u00d3n",
    "sg:phone":"+34 918 84 54 20",
    "sg:postcode":"28814",
    "sg:province":"Madrid",
    "wof:name":"Sercore Rebuilders S.l.",
    "wof:placetype":"venue"
},
  "geometry": {"coordinates":[-3.4572339058,40.5436286926],"type":"Point"}
}