{
  "type": "Feature",
  "properties": {
    "iso:country":"ES",
    "sg:address":"Avda Antero Lopez, 38",
    "sg:city":"Magan",
    "sg:orig_category":"Frutas Y Legumbres Frescas (al Por Mayor)",
    "sg:phone":"+34 925 36 02 91",
    "sg:postcode":"45590",
    "sg:province":"Toledo",
    "wof:name":"Berenguer Mu\u00f1oz Benito",
    "wof:placetype":"venue"
},
  "geometry": {"coordinates":[-3.9320030212,39.9637451172],"type":"Point"}
}