{
  "type": "Feature",
  "properties": {
    "addr:full":"Calle de Castellar (el), 3 Alagon Zaragoza 50630",
    "addr:housenumber":"3",
    "addr:postcode":"50630",
    "addr:street":"Calle De Castellar El",
    "iso:country":"ES",
    "sg:address":"Calle de Castellar (el), 3",
    "sg:city":"Alagon",
    "sg:orig_category":"Material Y Herramientas Agr\u00cdcolas",
    "sg:phone":"+34 976 61 02 36",
    "sg:postcode":"50630",
    "sg:province":"Zaragoza",
    "wof:name":"Gascon Bazan Cesar",
    "wof:placetype":"venue"
},
  "geometry": {"coordinates":[-1.1200567484,41.7728652954],"type":"Point"}
}