{
  "type": "Feature",
  "properties": {
    "addr:full":"Plaz Castilla Y Leon, 4 Valladolid Valladolid 47008",
    "addr:housenumber":"4",
    "addr:postcode":"47008",
    "addr:street":"Plaz;Leon",
    "iso:country":"ES",
    "sg:address":"Plaz Castilla Y Leon, 4",
    "sg:city":"Valladolid",
    "sg:orig_category":"Asociaciones Y Clubs Deportivos",
    "sg:phone":"+34 983 24 61 08",
    "sg:postcode":"47008",
    "sg:province":"Valladolid",
    "sg:website":"www.movilcenterwellness.com",
    "wof:name":"Torres Reinoso Noemi",
    "wof:placetype":"venue"
},
  "geometry": {"coordinates":[-4.7520952225,41.6103973389],"type":"Point"}
}