{
  "type": "Feature",
  "properties": {
    "addr:full":"Carrer de Londres, 24 Barcelona Barcelona 08029",
    "addr:housenumber":"24",
    "addr:postcode":"08029",
    "addr:street":"Carrer De Londres",
    "iso:country":"ES",
    "sg:address":"Carrer de Londres, 24",
    "sg:city":"Barcelona",
    "sg:orig_category":"Agencias De Viajes",
    "sg:phone":"+34 933 63 10 94",
    "sg:postcode":"08029",
    "sg:province":"Barcelona",
    "wof:name":"Viatjes Confort S.l.l",
    "wof:placetype":"venue"
},
  "geometry": {"coordinates":[2.1447899342,41.3887863159],"type":"Point"}
}