{
  "type": "Feature",
  "properties": {
    "addr:full":"Grup Paz (de La), 13 Cuenca Cuenca 16004",
    "addr:postcode":"16004",
    "iso:country":"ES",
    "sg:address":"Grup Paz (de La), 13",
    "sg:city":"Cuenca",
    "sg:orig_category":"Fabricaci\u00d3n, Importaci\u00d3n, Venta De Material De Telefon\u00cda, Peritelefon\u00cda",
    "sg:phone":"+34 969 23 60 96",
    "sg:postcode":"16004",
    "sg:province":"Cuenca",
    "wof:name":"Anton Parra Jesus",
    "wof:placetype":"venue"
},
  "geometry": {"coordinates":[-2.1331532001,40.0658416748],"type":"Point"}
}