{
  "type": "Feature",
  "properties": {
    "addr:full":"Calle de Fuenterrabia, 4 Donostia-san Sebastian Guip\u00f9zcoa 20005",
    "addr:housenumber":"4",
    "addr:postcode":"20005",
    "addr:street":"Calle De Fuenterrabia",
    "iso:country":"ES",
    "sg:address":"Calle de Fuenterrabia, 4",
    "sg:city":"Donostia-san Sebastian",
    "sg:orig_category":"Doctores En Medicina",
    "sg:phone":"+34 943 42 50 55",
    "sg:postcode":"20005",
    "sg:province":"Guip\u00f9zcoa",
    "wof:name":"Villar Vazquez Francisco Javier",
    "wof:placetype":"venue"
},
  "geometry": {"coordinates":[-1.9825199842,43.3190460205],"type":"Point"}
}