{
  "type": "Feature",
  "properties": {
    "iso:country":"ES",
    "sg:address":"Monasterio Irache, 45",
    "sg:city":"Iru\u00f1a",
    "sg:classifiers":[
        {
            "category":"Personal",
            "subcategory":"Barber",
            "type":"Services"
        }
    ],
    "sg:phone":"+34 948 17 45 93",
    "sg:postcode":"31011",
    "sg:province":"Navarra",
    "sg:tags":[
        "caballeros",
        "de",
        "peluqueros"
    ],
    "wof:name":"Itoiz Abinzano Pedro Jose",
    "wof:placetype":"venue"
},
  "geometry": {"coordinates":[-1.6661915779,42.8141670227],"type":"Point"}
}