{
  "type": "Feature",
  "properties": {
    "addr:full":"Mercado Municipal, S/n Eivissa Islas Baleares 07800",
    "addr:housenumber":"s / n",
    "addr:postcode":"07800",
    "iso:country":"ES",
    "sg:address":"Mercado Municipal, S/n",
    "sg:city":"Eivissa",
    "sg:orig_category":"Pescader\u00cdas (al Por Menor)",
    "sg:phone":"+34 971 30 41 10",
    "sg:postcode":"07800",
    "sg:province":"Islas Baleares",
    "wof:name":"Iglesias Martin Valeriano",
    "wof:placetype":"venue"
},
  "geometry": {"coordinates":[1.4188899994,38.9061164856],"type":"Point"}
}