{
  "type": "Feature",
  "properties": {
    "addr:full":"Calle de Virgen Del Rosario, 38 Mancha Real Ja\u00e9n 23100",
    "addr:housenumber":"38",
    "addr:postcode":"23100",
    "addr:street":"Calle De Virgen Del Rosario",
    "iso:country":"ES",
    "sg:address":"Calle de Virgen Del Rosario, 38",
    "sg:city":"Mancha Real",
    "sg:orig_category":"Abogados",
    "sg:phone":"+34 953 35 23 43",
    "sg:postcode":"23100",
    "sg:province":"Ja\u00e9n",
    "wof:name":"Martinez Ruiz Micaela",
    "wof:placetype":"venue"
},
  "geometry": {"coordinates":[-3.6080770493,37.7869606018],"type":"Point"}
}