{
  "type": "Feature",
  "properties": {
    "iso:country":"ES",
    "sg:address":"Cra Santa Creu De Calafell, 127",
    "sg:city":"Gava",
    "sg:orig_category":"Empresas De Carpinter\u00cda",
    "sg:phone":"+34 936 62 56 68",
    "sg:postcode":"08850",
    "sg:province":"Barcelona",
    "wof:name":"Perez Lima Lisardo",
    "wof:placetype":"venue"
},
  "geometry": {"coordinates":[2.0060529709,41.3008079529],"type":"Point"}
}