{
  "type": "Feature",
  "properties": {
    "iso:country":"ES",
    "sg:address":"Plaz Romeria (de La), 3",
    "sg:city":"Sevilla",
    "sg:orig_category":"Librer\u00cdas",
    "sg:phone":"+34 954 66 37 90",
    "sg:postcode":"41006",
    "sg:province":"Sevilla",
    "wof:name":"Bermudez Alcaide Pastora",
    "wof:placetype":"venue"
},
  "geometry": {"coordinates":[-5.9642629623,37.372844696],"type":"Point"}
}