{
  "type": "Feature",
  "properties": {
    "addr:full":"Ctra Lleida, Km. 0001,0 Tarragona Tarragona 43007",
    "addr:postcode":"43007",
    "addr:street":"Ctra Lleida Km. 0001,0",
    "iso:country":"ES",
    "sg:address":"Ctra Lleida, Km. 0001,0",
    "sg:city":"Tarragona",
    "sg:orig_category":"Aceros Inoxidables",
    "sg:phone":"+34 977 22 28 96",
    "sg:postcode":"43007",
    "sg:province":"Tarragona",
    "wof:name":"C M Aciform Tarragona S. L.",
    "wof:placetype":"venue"
},
  "geometry": {"coordinates":[1.2959779501,41.1377334595],"type":"Point"}
}