{
  "type": "Feature",
  "properties": {
    "iso:country":"ES",
    "sg:address":"Ubitxa Kalea, 11",
    "sg:city":"Eibar",
    "sg:orig_category":"Centros De Coordinaci\u00d3n",
    "sg:phone":"+34 943 20 20 17",
    "sg:postcode":"20600",
    "sg:province":"Guip\u00f9zcoa",
    "wof:name":"Maria Del Carmen Alonso Hernandez",
    "wof:placetype":"venue"
},
  "geometry": {"coordinates":[-2.4717564583,43.180973053],"type":"Point"}
}