{
  "type": "Feature",
  "properties": {
    "addr:full":"Carrer de Verneda Del Congost, 7 Montmelo Barcelona 08160",
    "addr:housenumber":"7",
    "addr:postcode":"08160",
    "addr:street":"Carrer De Verneda Del Congost",
    "iso:country":"ES",
    "sg:address":"Carrer de Verneda Del Congost, 7",
    "sg:city":"Montmelo",
    "sg:orig_category":"Aparatos, M\u00c1quinas Y Procedimientos En Industria Qu\u00cdmica",
    "sg:phone":"+34 935 68 09 07",
    "sg:postcode":"08160",
    "sg:province":"Barcelona",
    "wof:name":"Suphatec S. L.",
    "wof:placetype":"venue"
},
  "geometry": {"coordinates":[2.2602500916,41.5609054565],"type":"Point"}
}