{
  "type": "Feature",
  "properties": {
    "addr:full":"Zaramaga Carrer de Carrer de Boulevard De Vitoria, 1 Vitoria-gasteiz \u00c1lava 01013",
    "addr:housenumber":"1",
    "addr:postcode":"01013",
    "addr:street":"Carrer De Carrer De Boulevard De Vitoria",
    "iso:country":"ES",
    "sg:address":"Zaramaga Carrer de Carrer de Boulevard De Vitoria, 1",
    "sg:city":"Vitoria-gasteiz",
    "sg:orig_category":"Ropa Para Ni\u00d1os (al Por Menor)",
    "sg:phone":"+34 945 06 55 68",
    "sg:postcode":"01013",
    "sg:province":"\u00c1lava",
    "wof:name":"Gildabimba S.l.",
    "wof:placetype":"venue"
},
  "geometry": {"coordinates":[-2.6840889454,42.8761367798],"type":"Point"}
}