{
  "type": "Feature",
  "properties": {
    "addr:full":"Quinta, S/n Quinta A Coru\u00f1a 15541",
    "addr:housenumber":"s / n",
    "addr:postcode":"15541",
    "addr:street":"A Corun\u0303A",
    "iso:country":"ES",
    "sg:address":"Quinta, S/n",
    "sg:city":"Quinta",
    "sg:orig_category":"Asociaciones Y Clubs Deportivos",
    "sg:phone":"+34 981 36 34 81",
    "sg:postcode":"15541",
    "sg:province":"A Coru\u00f1a",
    "wof:name":"Sociedad Deportiva O Val De Naron",
    "wof:placetype":"venue"
},
  "geometry": {"coordinates":[-8.2099151611,43.5525283813],"type":"Point"}
}