{
  "type": "Feature",
  "properties": {
    "addr:full":"Pase Chacora, 1 Chiva Valencia 46370",
    "addr:housenumber":"1",
    "addr:postcode":"46370",
    "addr:street":"Chacora",
    "iso:country":"ES",
    "sg:address":"Pase Chacora, 1",
    "sg:city":"Chiva",
    "sg:orig_category":"Sociedades, Compa\u00d1\u00cdas Aseguradoras",
    "sg:phone":"+34 962 52 16 23",
    "sg:postcode":"46370",
    "sg:province":"Valencia",
    "wof:name":"Criado Hernan Maria Isabel",
    "wof:placetype":"venue"
},
  "geometry": {"coordinates":[-0.7179690003,39.4728012085],"type":"Point"}
}