{
  "type": "Feature",
  "properties": {
    "addr:full":"C/ Sant Nicolau, 29 Alcoi Alicante 03801",
    "addr:housenumber":"29",
    "addr:postcode":"03801",
    "addr:street":"C / Sant Nicolau",
    "iso:country":"ES",
    "sg:address":"C/ Sant Nicolau, 29",
    "sg:city":"Alcoi",
    "sg:orig_category":"Arquitectos",
    "sg:phone":"+34 965 54 00 58",
    "sg:postcode":"03801",
    "sg:province":"Alicante",
    "wof:name":"Domenech Arquitecto S.l.",
    "wof:placetype":"venue"
},
  "geometry": {"coordinates":[-0.4729590118,38.6964797974],"type":"Point"}
}