{
  "type": "Feature",
  "properties": {
    "addr:full":"Trva Delicias, 3 Sada La Coru\u00f1a 15160",
    "addr:housenumber":"3",
    "addr:postcode":"15160",
    "addr:street":"Trva Delicias;La",
    "iso:country":"ES",
    "sg:address":"Trva Delicias, 3",
    "sg:city":"Sada",
    "sg:orig_category":"Carnicer\u00cdas, Carnicer\u00cdas",
    "sg:phone":"+34 981 62 36 59",
    "sg:postcode":"15160",
    "sg:province":"La Coru\u00f1a",
    "wof:name":"Hermanos Folgueira Fernandez De Baralla S.l.",
    "wof:placetype":"venue"
},
  "geometry": {"coordinates":[-8.2506990433,43.348449707],"type":"Point"}
}