{
  "type": "Feature",
  "properties": {
    "iso:country":"ES",
    "sg:address":"Calle de Huertos (los), 6",
    "sg:city":"Andosilla",
    "sg:orig_category":"M\u00c9dicos: Estomatolog\u00cda",
    "sg:phone":"+34 948 69 01 71",
    "sg:postcode":"31261",
    "sg:province":"Navarra",
    "wof:name":"Alonso Ciappa Osvaldo Horacio",
    "wof:placetype":"venue"
},
  "geometry": {"coordinates":[-1.9430495501,42.3758735657],"type":"Point"}
}