{
  "type": "Feature",
  "properties": {
    "addr:full":"Calle de Santa Maria De La Cabeza, 10 Cadiz C\u00e1diz 11007",
    "addr:housenumber":"10",
    "addr:postcode":"11007",
    "addr:street":"Calle De Santa;Cabeza",
    "iso:country":"ES",
    "sg:address":"Calle de Santa Maria De La Cabeza, 10",
    "sg:city":"Cadiz",
    "sg:orig_category":"Promotores Constructores",
    "sg:phone":"+34 956 25 62 61",
    "sg:postcode":"11007",
    "sg:province":"C\u00e1diz",
    "wof:name":"Construcciones Alconsa S.l.",
    "wof:placetype":"venue"
},
  "geometry": {"coordinates":[-6.2837519646,36.5203590393],"type":"Point"}
}