{
  "type": "Feature",
  "properties": {
    "addr:full":"Calle de Dionisio Guardiola, 34 Albacete Albacete 02003",
    "addr:housenumber":"34",
    "addr:postcode":"02003",
    "addr:street":"Calle De Dionisio Guardiola",
    "iso:country":"ES",
    "sg:address":"Calle de Dionisio Guardiola, 34",
    "sg:city":"Albacete",
    "sg:orig_category":"Fabricaci\u00d3n De Juegos Y Juguetes",
    "sg:phone":"+34 967 22 22 33",
    "sg:postcode":"02003",
    "sg:province":"Albacete",
    "wof:name":"Tecnirest Sociedad Limitada",
    "wof:placetype":"venue"
},
  "geometry": {"coordinates":[-1.8585569859,38.9925575256],"type":"Point"}
}