{
  "type": "Feature",
  "properties": {
    "iso:country":"ES",
    "sg:address":"Carrer de Bonaventura Aribau, 55",
    "sg:city":"S. Boi Llobregat",
    "sg:orig_category":"Electricidad: Instaladores",
    "sg:phone":"+34 936 40 15 01",
    "sg:postcode":"08830",
    "sg:province":"Barcelona",
    "wof:name":"Instalaciones Jocri 2005 S.c.p",
    "wof:placetype":"venue"
},
  "geometry": {"coordinates":[2.0422151089,41.3387794495],"type":"Point"}
}