{
  "type": "Feature",
  "properties": {
    "addr:full":"Cami Fondo, S/n Vinaros Castell\u00f3n 12500",
    "addr:housenumber":"s / n",
    "addr:postcode":"12500",
    "addr:street":"Fondo",
    "iso:country":"ES",
    "sg:address":"Cami Fondo, S/n",
    "sg:city":"Vinaros",
    "sg:orig_category":"Frutas Y Legumbres Frescas (al Por Mayor)",
    "sg:phone":"+34 964 45 58 33",
    "sg:postcode":"12500",
    "sg:province":"Castell\u00f3n",
    "wof:name":"Puig Giner Ricardo",
    "wof:placetype":"venue"
},
  "geometry": {"coordinates":[0.4674000144,40.4747543335],"type":"Point"}
}