{
  "type": "Feature",
  "properties": {
    "addr:full":"Calle de Artekalea, 4 Gernika-lumo Vizcaya 48300",
    "addr:housenumber":"4",
    "addr:postcode":"48300",
    "addr:street":"Calle De Artekalea",
    "iso:country":"ES",
    "sg:address":"Calle de Artekalea, 4",
    "sg:city":"Gernika-lumo",
    "sg:orig_category":"Zapatos (al Por Menor)",
    "sg:phone":"+34 946 25 48 67",
    "sg:postcode":"48300",
    "sg:province":"Vizcaya",
    "wof:name":"Ona Oinetakoak S.l.",
    "wof:placetype":"venue"
},
  "geometry": {"coordinates":[-2.6779439449,43.314907074],"type":"Point"}
}