{
  "type": "Feature",
  "properties": {
    "iso:country":"ES",
    "sg:address":"Calle de Juan Bautista De Toledo, 36",
    "sg:city":"Madrid",
    "sg:orig_category":"Restaurantes",
    "sg:phone":"+34 914 13 39 57",
    "sg:postcode":"28002",
    "sg:province":"Madrid",
    "wof:name":"Restaurante Picos De Europa",
    "wof:placetype":"venue"
},
  "geometry": {"coordinates":[-3.6717689037,40.441783905],"type":"Point"}
}