{
  "type": "Feature",
  "properties": {
    "iso:country":"ES",
    "sg:address":"Calle de Gavilanes (blq), 9",
    "sg:city":"Madrid",
    "sg:orig_category":"Venta, Localizaci\u00d3n, Reparaci\u00d3n De Material E Instrumental M\u00c9dico",
    "sg:phone":"+34 913 00 58 55",
    "sg:postcode":"28043",
    "sg:province":"Madrid",
    "wof:name":"Biomet Spain Orthopaedics S.l.",
    "wof:placetype":"venue"
},
  "geometry": {"coordinates":[-3.740883112,40.4796257019],"type":"Point"}
}