{
  "type": "Feature",
  "properties": {
    "addr:full":"Plaz Puente-zubia, 3 Arenas -areeta Vizcaya 48930",
    "addr:housenumber":"3;areeta",
    "addr:postcode":"48930",
    "addr:street":"Plaz Puente-Zubia",
    "iso:country":"ES",
    "sg:address":"Plaz Puente-zubia, 3",
    "sg:city":"Arenas -areeta",
    "sg:orig_category":"Electrodom\u00c9sticos (al Por Menor)",
    "sg:phone":"+34 944 64 22 99",
    "sg:postcode":"48930",
    "sg:province":"Vizcaya",
    "wof:name":"Alonso Martinez Felipe",
    "wof:placetype":"venue"
},
  "geometry": {"coordinates":[-2.6983869076,43.2204284668],"type":"Point"}
}