{
  "type": "Feature",
  "properties": {
    "iso:country":"ES",
    "sg:address":"Avda America (de), 3",
    "sg:city":"Teruel",
    "sg:orig_category":"Doctores En Medicina",
    "sg:phone":"+34 978 62 14 37",
    "sg:postcode":"44002",
    "sg:province":"Teruel",
    "wof:name":"Jimenez Navarro Jesus",
    "wof:placetype":"venue"
},
  "geometry": {"coordinates":[-1.1090049744,40.3334350586],"type":"Point"}
}