{
  "type": "Feature",
  "properties": {
    "iso:country":"ES",
    "sg:address":"Calle de Pan Y Toros, 15",
    "sg:city":"Madrid",
    "sg:orig_category":"Ense\u00d1anza Variada",
    "sg:phone":"+34 913 17 47 09",
    "sg:postcode":"28041",
    "sg:province":"Madrid",
    "wof:name":"Hernandez De La Casa Julian",
    "wof:placetype":"venue"
},
  "geometry": {"coordinates":[-3.6945729256,40.3600196838],"type":"Point"}
}