{
  "type": "Feature",
  "properties": {
    "iso:country":"ES",
    "sg:address":"Pla Montbau, 4",
    "sg:city":"Barcelona",
    "sg:orig_category":"Empresas De Pintura Y Revestimientos",
    "sg:phone":"+34 934 28 47 02",
    "sg:postcode":"08035",
    "sg:province":"Barcelona",
    "wof:name":"Xifreu Rovira Ricardo",
    "wof:placetype":"venue"
},
  "geometry": {"coordinates":[2.1429100037,41.4308815002],"type":"Point"}
}