{
  "type": "Feature",
  "properties": {
    "iso:country":"ES",
    "sg:address":"Carr Jaume Ii, 59",
    "sg:city":"Ca'n Picafort",
    "sg:orig_category":"Empresas De Limpieza",
    "sg:phone":"+34 971 85 27 87",
    "sg:postcode":"07458",
    "sg:province":"Islas Baleares",
    "wof:name":"Pay Bis Nord S.l.",
    "wof:placetype":"venue"
},
  "geometry": {"coordinates":[2.9117100239,39.6136398315],"type":"Point"}
}