{
  "type": "Feature",
  "properties": {
    "addr:full":"Esperanza Tdad Manz 4, 9 Sevilla Sevilla 41008",
    "addr:housenumber":"9",
    "addr:postcode":"41008",
    "iso:country":"ES",
    "sg:address":"Esperanza Tdad Manz 4, 9",
    "sg:city":"Sevilla",
    "sg:orig_category":"Asesor\u00cda Sobre Comunicaci\u00d3n De Empresas",
    "sg:phone":"+34 954 53 99 13",
    "sg:postcode":"41008",
    "sg:province":"Sevilla",
    "wof:name":"Juri Y Asociados S.l.",
    "wof:placetype":"venue"
},
  "geometry": {"coordinates":[-5.9755578041,37.3953170776],"type":"Point"}
}