{
  "type": "Feature",
  "properties": {
    "addr:full":"Ctra Pont Armentera, S/n Tarragona Tarragona 43007",
    "addr:housenumber":"s / n",
    "addr:postcode":"43007",
    "addr:street":"Ctra Pont Armentera",
    "iso:country":"ES",
    "sg:address":"Ctra Pont Armentera, S/n",
    "sg:city":"Tarragona",
    "sg:orig_category":"Distribuci\u00d3n De Petr\u00d3leo Y Derivados",
    "sg:phone":"+34 977 20 00 07",
    "sg:postcode":"43007",
    "sg:province":"Tarragona",
    "wof:name":"Luvirr S.a.",
    "wof:placetype":"venue"
},
  "geometry": {"coordinates":[1.2563489676,41.1385345459],"type":"Point"}
}