{
  "type": "Feature",
  "properties": {
    "addr:full":"Calle de Lladro Y Malli, 25 Valencia Valencia 46007",
    "addr:housenumber":"25",
    "addr:postcode":"46007",
    "addr:street":"Calle De Lladro Y Malli",
    "iso:country":"ES",
    "sg:address":"Calle de Lladro Y Malli, 25",
    "sg:city":"Valencia",
    "sg:orig_category":"Agencias Y Agentes Comerciales, Representantes",
    "sg:phone":"+34 963 17 40 84",
    "sg:postcode":"46007",
    "sg:province":"Valencia",
    "wof:name":"Vanaclocha E Hijos S.l.",
    "wof:placetype":"venue"
},
  "geometry": {"coordinates":[-0.3903391063,39.4611320496],"type":"Point"}
}