{
  "type": "Feature",
  "properties": {
    "iso:country":"ES",
    "sg:address":"Avda Teodomiro, 18",
    "sg:city":"Orihuela",
    "sg:orig_category":"Molduras, Junquillos, Listones Y Molduras Perforadas",
    "sg:phone":"+34 966 74 34 15",
    "sg:postcode":"03300",
    "sg:province":"Alicante",
    "wof:name":"Vergara Huertas Joaquin",
    "wof:placetype":"venue"
},
  "geometry": {"coordinates":[-0.9455220103,38.0811576843],"type":"Point"}
}