{
  "type": "Feature",
  "properties": {
    "iso:country":"ES",
    "sg:address":"Calle de Tozal, 1",
    "sg:city":"Peralta Sal",
    "sg:orig_category":"Sanatorios M\u00c9dico",
    "sg:phone":"+34 974 41 12 82",
    "sg:postcode":"22513",
    "sg:province":"Huesca",
    "wof:name":"Ayuntamiento Peralta De Calasanz",
    "wof:placetype":"venue"
},
  "geometry": {"coordinates":[0.3882017136,41.991771698],"type":"Point"}
}