{
  "type": "Feature",
  "properties": {
    "iso:country":"ES",
    "sg:address":"Calle de Isabel Tintero, 1",
    "sg:city":"Madrid",
    "sg:orig_category":"Estudios Y Construcci\u00d3n De Acuarios Y Viveros",
    "sg:phone":"+34 913 65 91 41",
    "sg:postcode":"28005",
    "sg:province":"Madrid",
    "sg:website":"www.acuariopolinesia.com",
    "wof:name":"Acuario Polinesia S.l.",
    "wof:placetype":"venue"
},
  "geometry": {"coordinates":[-3.7127964497,40.4085998535],"type":"Point"}
}