{
  "type": "Feature",
  "properties": {
    "addr:full":"Pg Estacio De L', 1 Valls Tarragona 43800",
    "addr:housenumber":"1",
    "addr:postcode":"43800",
    "addr:street":"Pg Estacio De L '",
    "iso:country":"ES",
    "sg:address":"Pg Estacio De L', 1",
    "sg:city":"Valls",
    "sg:orig_category":"Confecci\u00d3n De Zapatos",
    "sg:phone":"+34 977 60 14 31",
    "sg:postcode":"43800",
    "sg:province":"Tarragona",
    "wof:name":"Calcats Mallorqui S. A.",
    "wof:placetype":"venue"
},
  "geometry": {"coordinates":[1.2525299788,41.2871513367],"type":"Point"}
}