{
  "type": "Feature",
  "properties": {
    "addr:full":"Av Flora Cadena, S/n Rialp Lleida 25594",
    "addr:housenumber":"s / n",
    "addr:postcode":"25594",
    "addr:street":"Av Flora Cadena",
    "iso:country":"ES",
    "sg:address":"Av Flora Cadena, S/n",
    "sg:city":"Rialp",
    "sg:orig_category":"Supermercados Y Hipermercados",
    "sg:phone":"+34 973 62 03 74",
    "sg:postcode":"25594",
    "sg:province":"Lleida",
    "wof:name":"Sabarich Roset Concepcion",
    "wof:placetype":"venue"
},
  "geometry": {"coordinates":[1.1347049475,42.4428291321],"type":"Point"}
}