{
  "type": "Feature",
  "properties": {
    "addr:full":"Garceiras, 3 Garceiras La Coru\u00f1a 15800",
    "addr:housenumber":"3",
    "addr:postcode":"15800",
    "addr:street":"Garceiras;La Corun\u0303A",
    "iso:country":"ES",
    "sg:address":"Garceiras, 3",
    "sg:city":"Garceiras",
    "sg:orig_category":"Pintura Y Barniz (al Por Menor)",
    "sg:phone":"+34 981 50 63 63",
    "sg:postcode":"15800",
    "sg:province":"La Coru\u00f1a",
    "wof:name":"Castro Pedreira Juan Manuel",
    "wof:placetype":"venue"
},
  "geometry": {"coordinates":[-8.0129041672,42.9135894775],"type":"Point"}
}