{
  "type": "Feature",
  "properties": {
    "addr:full":"Ctra Vertedero Municipal Valdemingomez (km.), 20 Madrid Madrid 28019",
    "addr:postcode":"28019",
    "addr:street":"Ctra Vertedero;Km. 20 Madrid",
    "iso:country":"ES",
    "sg:address":"Ctra Vertedero Municipal Valdemingomez (km.), 20",
    "sg:city":"Madrid",
    "sg:orig_category":"Empresas De Limpieza",
    "sg:phone":"+34 915 69 14 66",
    "sg:postcode":"28019",
    "sg:province":"Madrid",
    "wof:name":"Urbaser S.a.",
    "wof:placetype":"venue"
},
  "geometry": {"coordinates":[-3.7057740688,40.42029953],"type":"Point"}
}