{
  "type": "Feature",
  "properties": {
    "addr:full":"Ctra. Rueda, 39 Valladolid Valladolid 47008",
    "addr:housenumber":"39",
    "addr:postcode":"47008",
    "addr:street":"Ctra. Rueda",
    "iso:country":"ES",
    "sg:address":"Ctra. Rueda, 39",
    "sg:city":"Valladolid",
    "sg:orig_category":"Carnicer\u00cdas, Carnicer\u00cdas",
    "sg:phone":"+34 983 27 52 62",
    "sg:postcode":"47008",
    "sg:province":"Valladolid",
    "wof:name":"Perez Mayo Lorenzo",
    "wof:placetype":"venue"
},
  "geometry": {"coordinates":[-4.7416329384,41.6249542236],"type":"Point"}
}