{
  "type": "Feature",
  "properties": {
    "addr:full":"Calle de Hospital De Mujeres, 18 Cadiz C\u00e1diz 11001",
    "addr:housenumber":"18",
    "addr:postcode":"11001",
    "addr:street":"Calle De Hospital;Cadiz Ca\u0301Diz",
    "iso:country":"ES",
    "sg:address":"Calle de Hospital De Mujeres, 18",
    "sg:city":"Cadiz",
    "sg:orig_category":"Droguer\u00cdas (al Por Menor)",
    "sg:phone":"+34 956 22 30 10",
    "sg:postcode":"11001",
    "sg:province":"C\u00e1diz",
    "wof:name":"Ruiz Gonzalez Luis",
    "wof:placetype":"venue"
},
  "geometry": {"coordinates":[-6.299120903,36.5314102173],"type":"Point"}
}