{
  "type": "Feature",
  "properties": {
    "iso:country":"ES",
    "sg:address":"Cmno Flora, 21",
    "sg:city":"Esparragal",
    "sg:orig_category":"Centros Empresariales",
    "sg:phone":"+34 968 85 30 87",
    "sg:postcode":"30163",
    "sg:province":"Murcia",
    "wof:name":"Mantenimur, Slu.",
    "wof:placetype":"venue"
},
  "geometry": {"coordinates":[-1.0736939907,38.0533943176],"type":"Point"}
}