{
  "type": "Feature",
  "properties": {
    "addr:full":"Calle de Maldonado, 19 Medina Campo Valladolid 47400",
    "addr:housenumber":"19",
    "addr:postcode":"47400",
    "addr:street":"Calle De Maldonado",
    "iso:country":"ES",
    "sg:address":"Calle de Maldonado, 19",
    "sg:city":"Medina Campo",
    "sg:orig_category":"M\u00c9dicos: Estomatolog\u00cda",
    "sg:phone":"+34 983 80 44 33",
    "sg:postcode":"47400",
    "sg:province":"Valladolid",
    "wof:name":"Cacho Casado Alberto",
    "wof:placetype":"venue"
},
  "geometry": {"coordinates":[-4.9142289162,41.3092308044],"type":"Point"}
}