{
  "type": "Feature",
  "properties": {
    "iso:country":"ES",
    "sg:address":"Calle de Bolsa, 66",
    "sg:city":"Sanlucar De Barrameda",
    "sg:orig_category":"Pod\u00d3logos: Pedicuros",
    "sg:phone":"+34 956 36 45 22",
    "sg:postcode":"11540",
    "sg:province":"C\u00e1diz",
    "wof:name":"Perez Tudela Eloy",
    "wof:placetype":"venue"
},
  "geometry": {"coordinates":[-6.3511362076,36.7818641663],"type":"Point"}
}