{
  "type": "Feature",
  "properties": {
    "iso:country":"ES",
    "sg:address":"Calle de Nueva Bayyana, 7",
    "sg:city":"Almeria",
    "sg:orig_category":"Inmobiliaria (agencias)",
    "sg:phone":"+34 950 24 06 30",
    "sg:postcode":"04007",
    "sg:province":"Almer\u00eda",
    "wof:name":"Ventura Bayo S.l.",
    "wof:placetype":"venue"
},
  "geometry": {"coordinates":[-2.4361701012,36.8235588074],"type":"Point"}
}