{
  "type": "Feature",
  "properties": {
    "addr:full":"Avda Avelino Montero Rios, 85 Estribela Pontevedra 36910",
    "addr:housenumber":"85",
    "addr:postcode":"36910",
    "addr:street":"Avda Avelino Montero Rios",
    "iso:country":"ES",
    "sg:address":"Avda Avelino Montero Rios, 85",
    "sg:city":"Estribela",
    "sg:orig_category":"Empresas De Carpinter\u00cda",
    "sg:phone":"+34 986 89 11 22",
    "sg:postcode":"36910",
    "sg:province":"Pontevedra",
    "wof:name":"Aluminios Sorey S.l.",
    "wof:placetype":"venue"
},
  "geometry": {"coordinates":[-8.6893424988,42.3986091614],"type":"Point"}
}