{
  "type": "Feature",
  "properties": {
    "addr:full":"Avda Pedro Manuel Vila, 5 Villarrobledo Albacete 02600",
    "addr:housenumber":"5",
    "addr:postcode":"02600",
    "addr:street":"Avda Pedro Manuel Vila",
    "iso:country":"ES",
    "sg:address":"Avda Pedro Manuel Vila, 5",
    "sg:city":"Villarrobledo",
    "sg:orig_category":"Mec\u00c1nico Del Autom\u00d3vil",
    "sg:phone":"+34 967 14 51 41",
    "sg:postcode":"02600",
    "sg:province":"Albacete",
    "wof:name":"Cromovil S.l.",
    "wof:placetype":"venue"
},
  "geometry": {"coordinates":[-2.592457056,39.2707443237],"type":"Point"}
}