{
  "type": "Feature",
  "properties": {
    "addr:full":"Calle de Alcalde Juan Barranquero, 1 Velez-malaga M\u00e1laga 29700",
    "addr:housenumber":"1",
    "addr:postcode":"29700",
    "addr:street":"Calle De Alcalde Juan Barranquero",
    "iso:country":"ES",
    "sg:address":"Calle de Alcalde Juan Barranquero, 1",
    "sg:city":"Velez-malaga",
    "sg:orig_category":"Bancos",
    "sg:phone":"+34 952 55 81 43",
    "sg:postcode":"29700",
    "sg:province":"M\u00e1laga",
    "wof:name":"Banco Pastor",
    "wof:placetype":"venue"
},
  "geometry": {"coordinates":[-4.1076455116,36.7820205688],"type":"Point"}
}