{
  "type": "Feature",
  "properties": {
    "addr:full":"Calle de Juan De Garay, 58 Alacant Alicante 03015",
    "addr:housenumber":"58",
    "addr:postcode":"03015",
    "addr:street":"Calle De Juan De Garay",
    "iso:country":"ES",
    "sg:address":"Calle de Juan De Garay, 58",
    "sg:city":"Alacant",
    "sg:orig_category":"Chapister\u00cda",
    "sg:phone":"+34 965 25 91 77",
    "sg:postcode":"03015",
    "sg:province":"Alicante",
    "wof:name":"Reparaciones Isi S.l.",
    "wof:placetype":"venue"
},
  "geometry": {"coordinates":[-0.4752939939,38.3648872375],"type":"Point"}
}