{
  "type": "Feature",
  "properties": {
    "addr:full":"Calle de Fuentes, 76 Moguer Huelva 21800",
    "addr:housenumber":"76",
    "addr:postcode":"21800",
    "addr:street":"Calle De Fuentes",
    "iso:country":"ES",
    "sg:address":"Calle de Fuentes, 76",
    "sg:city":"Moguer",
    "sg:orig_category":"Promotores Constructores",
    "sg:phone":"+34 959 37 33 12",
    "sg:postcode":"21800",
    "sg:province":"Huelva",
    "wof:name":"Moguere\u00d1a De Construccion S.l.",
    "wof:placetype":"venue"
},
  "geometry": {"coordinates":[-6.8342962265,37.272277832],"type":"Point"}
}