{
  "type": "Feature",
  "properties": {
    "iso:country":"ES",
    "sg:address":"Ntra. Sra. Del Rosario, 16",
    "sg:city":"Monta\u00d1ana",
    "sg:orig_category":"Bibliotecas, Mediatecas",
    "sg:phone":"+34 976 57 65 00",
    "sg:postcode":"50059",
    "sg:province":"Zaragoza",
    "wof:name":"Ayuntamiento De Zaragoza",
    "wof:placetype":"venue"
},
  "geometry": {"coordinates":[-0.8254101276,41.6847610474],"type":"Point"}
}