{
  "type": "Feature",
  "properties": {
    "addr:full":"Ctra Madrid, 10 Cieza Murcia 30530",
    "addr:housenumber":"10",
    "addr:postcode":"30530",
    "addr:street":"Ctra Madrid",
    "iso:country":"ES",
    "sg:address":"Ctra Madrid, 10",
    "sg:city":"Cieza",
    "sg:orig_category":"Zapater\u00cds Y Cordeler\u00cda",
    "sg:phone":"+34 968 76 04 54",
    "sg:postcode":"30530",
    "sg:province":"Murcia",
    "wof:name":"Egea Hilaturas S.l.",
    "wof:placetype":"venue"
},
  "geometry": {"coordinates":[-1.4228739738,38.243938446],"type":"Point"}
}