{
  "type": "Feature",
  "properties": {
    "addr:full":"Calle de Canalejas, 25 Don Benito Badajoz 06400",
    "addr:housenumber":"25",
    "addr:postcode":"06400",
    "addr:street":"Calle De Canalejas",
    "iso:country":"ES",
    "sg:address":"Calle de Canalejas, 25",
    "sg:city":"Don Benito",
    "sg:orig_category":"Electricidad: Equipos Industriales, Componentes (fabricaci\u00d3n)",
    "sg:phone":"+34 924 81 24 42",
    "sg:postcode":"06400",
    "sg:province":"Badajoz",
    "wof:name":"Especialidades Electricas Lausan S.a.",
    "wof:placetype":"venue"
},
  "geometry": {"coordinates":[-5.8544816971,38.9613113403],"type":"Point"}
}