{
  "type": "Feature",
  "properties": {
    "addr:full":"Plaz San Juan, 1 Monzon Huesca 22400",
    "addr:housenumber":"1",
    "addr:postcode":"22400",
    "addr:street":"Plaz San Juan",
    "iso:country":"ES",
    "sg:address":"Plaz San Juan, 1",
    "sg:city":"Monzon",
    "sg:orig_category":"Molduras, Junquillos, Listones Y Molduras Perforadas",
    "sg:phone":"+34 974 40 38 19",
    "sg:postcode":"22400",
    "sg:province":"Huesca",
    "wof:name":"Hernandez Cardenas Jose Antonio",
    "wof:placetype":"venue"
},
  "geometry": {"coordinates":[0.1905120015,41.9132995605],"type":"Point"}
}