{
  "type": "Feature",
  "properties": {
    "addr:full":"Calle de Rafael Massieu, 69 Castillo Del Romeral Las Palmas 35107",
    "addr:housenumber":"69",
    "addr:postcode":"35107",
    "addr:street":"Calle De Rafael Massieu;Del Romeral",
    "iso:country":"ES",
    "sg:address":"Calle de Rafael Massieu, 69",
    "sg:city":"Castillo Del Romeral",
    "sg:orig_category":"Institutos De Belleza",
    "sg:phone":"+34 928 72 80 71",
    "sg:postcode":"35107",
    "sg:province":"Las Palmas",
    "wof:name":"Godoy Guedes Esther Gloria",
    "wof:placetype":"venue"
},
  "geometry": {"coordinates":[-15.4633636475,27.7981491089],"type":"Point"}
}