{
  "type": "Feature",
  "properties": {
    "iso:country":"ES",
    "sg:address":"Ctra Fuente Amarga (de), S/n",
    "sg:city":"Chiclana De La Frontera",
    "sg:orig_category":"Promotores Constructores",
    "sg:phone":"+34 956 40 92 77",
    "sg:postcode":"11130",
    "sg:province":"C\u00e1diz",
    "wof:name":"Ferralla Elaborada Chiclana S.l.",
    "wof:placetype":"venue"
},
  "geometry": {"coordinates":[-6.1465640068,36.4097633362],"type":"Point"}
}