{
  "type": "Feature",
  "properties": {
    "iso:country":"ES",
    "sg:address":"Avda Sexta Bandera, 31",
    "sg:city":"Ventas Retamosa",
    "sg:orig_category":"Agencias Y Agentes Comerciales, Representantes",
    "sg:phone":"+34 918 17 36 42",
    "sg:postcode":"45183",
    "sg:province":"Toledo",
    "wof:name":"Alvarez Salvador Jose Maria",
    "wof:placetype":"venue"
},
  "geometry": {"coordinates":[-4.1157159805,40.1549224854],"type":"Point"}
}