{
  "type": "Feature",
  "properties": {
    "addr:full":"Carrer de Can Noguera, S/n Poligon Barcelones Barcelona 08630",
    "addr:housenumber":"s / n",
    "addr:postcode":"08630",
    "addr:street":"Carrer De Can Noguera;Poligon Barcelones",
    "iso:country":"ES",
    "sg:address":"Carrer de Can Noguera, S/n",
    "sg:city":"Poligon Barcelones",
    "sg:orig_category":"Fabricaci\u00d3n De Motores El\u00c9ctricos",
    "sg:phone":"+34 937 70 01 84",
    "sg:postcode":"08630",
    "sg:province":"Barcelona",
    "wof:name":"Abrera Metalurgica S.a.",
    "wof:placetype":"venue"
},
  "geometry": {"coordinates":[2.169919,41.387917],"type":"Point"}
}