{
  "type": "Feature",
  "properties": {
    "addr:full":"Carrer de Joaquin Costa, 91 Sabadell Barcelona 08206",
    "addr:housenumber":"91",
    "addr:postcode":"08206",
    "addr:street":"Carrer De Joaquin Costa",
    "iso:country":"ES",
    "sg:address":"Carrer de Joaquin Costa, 91",
    "sg:city":"Sabadell",
    "sg:orig_category":"Caf\u00c9s, Bares, Cervecer\u00cdas",
    "sg:phone":"+34 937 27 45 53",
    "sg:postcode":"08206",
    "sg:province":"Barcelona",
    "wof:name":"Barecat Sbd S.l.",
    "wof:placetype":"venue"
},
  "geometry": {"coordinates":[2.0957570076,41.547996521],"type":"Point"}
}