{
  "type": "Feature",
  "properties": {
    "addr:full":"Calle de Burgos, 2 Alacant Alicante 03015",
    "addr:housenumber":"2",
    "addr:postcode":"03015",
    "addr:street":"Calle De Burgos",
    "iso:country":"ES",
    "sg:address":"Calle de Burgos, 2",
    "sg:city":"Alacant",
    "sg:orig_category":"Chapister\u00cda",
    "sg:phone":"+34 965 25 76 00",
    "sg:postcode":"03015",
    "sg:province":"Alicante",
    "wof:name":"Belmonte Guerrero Antonio",
    "wof:placetype":"venue"
},
  "geometry": {"coordinates":[-0.4746490121,38.3636207581],"type":"Point"}
}