{
  "type": "Feature",
  "properties": {
    "iso:country":"ES",
    "sg:address":"Carr Marques De Caldes De Montbui, 23",
    "sg:city":"Girona",
    "sg:orig_category":"Agencias Y Agentes Comerciales, Representantes",
    "sg:phone":"+34 972 22 21 39",
    "sg:postcode":"17003",
    "sg:province":"Girona",
    "wof:name":"Com Prop Marques De Caldas De Montbui 23-25",
    "wof:placetype":"venue"
},
  "geometry": {"coordinates":[2.815985918,41.9698562622],"type":"Point"}
}