{
  "type": "Feature",
  "properties": {
    "addr:full":"Calle de Castellon, 16 Mislata Valencia 46920",
    "addr:housenumber":"16",
    "addr:postcode":"46920",
    "addr:street":"Calle De Castellon",
    "iso:country":"ES",
    "sg:address":"Calle de Castellon, 16",
    "sg:city":"Mislata",
    "sg:orig_category":"Fabricaci\u00d3n De Etiquetas",
    "sg:phone":"+34 963 83 49 08",
    "sg:postcode":"46920",
    "sg:province":"Valencia",
    "wof:name":"Cordellat Gonzalez Francisco",
    "wof:placetype":"venue"
},
  "geometry": {"coordinates":[-0.4202179909,39.4769859314],"type":"Point"}
}