{
  "type": "Feature",
  "properties": {
    "addr:full":"Calle de Chapineria, 1 Jerez De La Frontera C\u00e1diz 11403",
    "addr:housenumber":"1",
    "addr:postcode":"11403",
    "addr:street":"Calle De Chapineria",
    "iso:country":"ES",
    "sg:address":"Calle de Chapineria, 1",
    "sg:city":"Jerez De La Frontera",
    "sg:orig_category":"Molduras, Junquillos, Listones Y Molduras Perforadas",
    "sg:phone":"+34 956 34 15 21",
    "sg:postcode":"11403",
    "sg:province":"C\u00e1diz",
    "wof:name":"Mu\u00f1oz Perez Jose Luis",
    "wof:placetype":"venue"
},
  "geometry": {"coordinates":[-6.1390423775,36.6837501526],"type":"Point"}
}