{
  "type": "Feature",
  "properties": {
    "iso:country":"ES",
    "sg:address":"Calle de Damaso Alonso, 14",
    "sg:city":"Baeza",
    "sg:orig_category":"Molduras, Junquillos, Listones Y Molduras Perforadas",
    "sg:phone":"+34 953 74 15 55",
    "sg:postcode":"23440",
    "sg:province":"Ja\u00e9n",
    "wof:name":"Quesada Ruiz Bienvenido",
    "wof:placetype":"venue"
},
  "geometry": {"coordinates":[-3.4777550697,37.9976959229],"type":"Point"}
}