{
  "type": "Feature",
  "properties": {
    "addr:full":"Avda Rey Don Jaime, 14 Castellon Castell\u00f3n 12001",
    "addr:housenumber":"14",
    "addr:postcode":"12001",
    "addr:street":"Avda Rey Don Jaime",
    "iso:country":"ES",
    "sg:address":"Avda Rey Don Jaime, 14",
    "sg:city":"Castellon",
    "sg:orig_category":"Dietistas",
    "sg:phone":"+34 964 21 03 93",
    "sg:postcode":"12001",
    "sg:province":"Castell\u00f3n",
    "wof:name":"Montoliu Badenes Maria Teresa",
    "wof:placetype":"venue"
},
  "geometry": {"coordinates":[-0.0390199982,39.9866409302],"type":"Point"}
}