{
  "type": "Feature",
  "properties": {
    "addr:full":"Carretera Del Trapiche, S/n Velez-malaga M\u00e1laga 29700",
    "addr:postcode":"29700",
    "addr:street":"Carretera Del Trapiche S / N Velez-Malaga Ma\u0301Laga",
    "iso:country":"ES",
    "sg:address":"Carretera Del Trapiche, S/n",
    "sg:city":"Velez-malaga",
    "sg:orig_category":"Semiller\u00cdas",
    "sg:phone":"+34 952 55 83 70",
    "sg:postcode":"29700",
    "sg:province":"M\u00e1laga",
    "sg:website":"www.viveroscanarias.com",
    "wof:name":"Vi\u00f1a Perez Jose Antonio",
    "wof:placetype":"venue"
},
  "geometry": {"coordinates":[-4.0752587318,36.7531089783],"type":"Point"}
}