{
  "type": "Feature",
  "properties": {
    "iso:country":"ES",
    "sg:address":"Calle de Rey Don Pedro, 8",
    "sg:city":"Cordoba",
    "sg:orig_category":"Guarder\u00cdas",
    "sg:phone":"+34 957 29 19 02",
    "sg:postcode":"14009",
    "sg:province":"C\u00f3rdoba",
    "wof:name":"Hermanos Garcia Soto S.c.",
    "wof:placetype":"venue"
},
  "geometry": {"coordinates":[-4.7744560242,37.87159729],"type":"Point"}
}