{
  "type": "Feature",
  "properties": {
    "iso:country":"ES",
    "sg:address":"Afores, S/n",
    "sg:city":"Guimera",
    "sg:orig_category":"Agricultura: Abastecimiento Y Cosechado (negocio)",
    "sg:phone":"+34 973 30 30 61",
    "sg:postcode":"25341",
    "sg:province":"Lleida",
    "wof:name":"Bagunya Durich Josep",
    "wof:placetype":"venue"
},
  "geometry": {"coordinates":[1.1844278574,41.5641098022],"type":"Point"}
}