{
  "type": "Feature",
  "properties": {
    "iso:country":"ES",
    "sg:address":"Carr Costa Des Pou, 3",
    "sg:city":"Lloret Vistalegre",
    "sg:orig_category":"Administraciones Regionales, Departamentales Y Locales",
    "sg:phone":"+34 971 52 41 89",
    "sg:postcode":"07518",
    "sg:province":"Islas Baleares",
    "wof:name":"Ajuntament De Lloret De Vistalegre",
    "wof:placetype":"venue"
},
  "geometry": {"coordinates":[2.975356102,39.6178855896],"type":"Point"}
}