{
  "type": "Feature",
  "properties": {
    "addr:full":"Calle de Tajadas, 28 Corella Navarra 31591",
    "addr:housenumber":"28",
    "addr:postcode":"31591",
    "addr:street":"Calle De Tajadas",
    "iso:country":"ES",
    "sg:address":"Calle de Tajadas, 28",
    "sg:city":"Corella",
    "sg:orig_category":"Complementos De Vestir (al Por Menor)",
    "sg:phone":"+34 948 40 19 15",
    "sg:postcode":"31591",
    "sg:province":"Navarra",
    "wof:name":"Itziar Larrainzar S.l.",
    "wof:placetype":"venue"
},
  "geometry": {"coordinates":[-1.7858200073,42.1156692505],"type":"Point"}
}