{
  "type": "Feature",
  "properties": {
    "iso:country":"ES",
    "sg:address":"Avda Diputacion (de La), 36",
    "sg:city":"Castro Rio",
    "sg:orig_category":"Freidur\u00cdas: Equipos Y Suministros",
    "sg:phone":"+34 957 37 20 65",
    "sg:postcode":"14840",
    "sg:province":"C\u00f3rdoba",
    "wof:name":"Rodriguez Gonzalez Cecilio",
    "wof:placetype":"venue"
},
  "geometry": {"coordinates":[-4.4858789444,37.6921310425],"type":"Point"}
}