{
  "type": "Feature",
  "properties": {
    "iso:country":"ES",
    "sg:address":"Carrer de Santa Eulalia, 130",
    "sg:city":"Hospitalet Llobregat",
    "sg:orig_category":"Importaci\u00d3n",
    "sg:phone":"+34 932 98 91 56",
    "sg:postcode":"08902",
    "sg:province":"Barcelona",
    "wof:name":"Rojo Intenso Barcelona S.l.",
    "wof:placetype":"venue"
},
  "geometry": {"coordinates":[2.1258609295,41.3671112061],"type":"Point"}
}