{
  "type": "Feature",
  "properties": {
    "iso:country":"ES",
    "sg:address":"Calle de Miguel De Cervantes, 8",
    "sg:city":"Vilamartin Valdeorras",
    "sg:orig_category":"Semiller\u00cdas",
    "sg:phone":"+34 988 30 00 86",
    "sg:postcode":"32340",
    "sg:province":"Ourense",
    "wof:name":"Viveros Vedo S.l.",
    "wof:placetype":"venue"
},
  "geometry": {"coordinates":[-7.0554718971,42.4153060913],"type":"Point"}
}