{
  "type": "Feature",
  "properties": {
    "iso:country":"ES",
    "sg:address":"Calle de General Mola, 22",
    "sg:city":"Santa Olalla",
    "sg:orig_category":"Inmobiliaria (agencias)",
    "sg:phone":"+34 925 79 79 51",
    "sg:postcode":"45530",
    "sg:province":"Toledo",
    "sg:website":"www.paginasamarillas.es",
    "wof:name":"Gesinap 2000 S.l",
    "wof:placetype":"venue"
},
  "geometry": {"coordinates":[-4.426299572,40.0258712769],"type":"Point"}
}