{
  "type": "Feature",
  "properties": {
    "iso:country":"ES",
    "sg:address":"Rua Republica Argentina, 8",
    "sg:city":"Ordes",
    "sg:orig_category":"Peluqueros: De Se\u00d1oras",
    "sg:phone":"+34 981 68 00 80",
    "sg:postcode":"15680",
    "sg:province":"La Coru\u00f1a",
    "wof:name":"Ramos Dafonte Miguel Carlos",
    "wof:placetype":"venue"
},
  "geometry": {"coordinates":[-8.4067840576,43.0766830444],"type":"Point"}
}