{
  "type": "Feature",
  "properties": {
    "iso:country":"ES",
    "sg:address":"Calle de Alfonso Trujillo, S/n",
    "sg:city":"Orotava",
    "sg:orig_category":"Caf\u00c9s, Bares, Cervecer\u00cdas",
    "sg:phone":"+34 922 33 14 00",
    "sg:postcode":"38300",
    "sg:province":"Santa Cruz De Tenerife",
    "wof:name":"Sanchez Lopez Alejo",
    "wof:placetype":"venue"
},
  "geometry": {"coordinates":[-16.5197200775,28.3932628632],"type":"Point"}
}