{
  "type": "Feature",
  "properties": {
    "iso:country":"ES",
    "sg:address":"Av Cerdanyola, 7",
    "sg:city":"S. Cugat Valles",
    "sg:orig_category":"Bisuter\u00cda, Joyer\u00cda, Relojer\u00cda (al Por Menor)",
    "sg:phone":"+34 936 74 39 54",
    "sg:postcode":"08172",
    "sg:province":"Barcelona",
    "wof:name":"Codo Masana Mercedes",
    "wof:placetype":"venue"
},
  "geometry": {"coordinates":[2.0884931087,41.4739151001],"type":"Point"}
}