{
  "type": "Feature",
  "properties": {
    "addr:full":"Calle de Periodista Azzati, 14 Puerto Valencia 46520",
    "addr:housenumber":"14",
    "addr:postcode":"46520",
    "addr:street":"Calle De Periodista Azzati",
    "iso:country":"ES",
    "sg:address":"Calle de Periodista Azzati, 14",
    "sg:city":"Puerto",
    "sg:orig_category":"Peluqueros: De Se\u00d1oras",
    "sg:phone":"+34 962 67 52 49",
    "sg:postcode":"46520",
    "sg:province":"Valencia",
    "wof:name":"Torres Martin Juan",
    "wof:placetype":"venue"
},
  "geometry": {"coordinates":[-0.2267210037,39.6646537781],"type":"Point"}
}