{
  "type": "Feature",
  "properties": {
    "iso:country":"ES",
    "sg:address":"Rua Serra San Mamede, 50",
    "sg:city":"Ourense",
    "sg:orig_category":"Droguer\u00cdas (al Por Menor)",
    "sg:phone":"+34 988 22 61 19",
    "sg:postcode":"32005",
    "sg:province":"Ourense",
    "wof:name":"Devesa Alvarez Antonio",
    "wof:placetype":"venue"
},
  "geometry": {"coordinates":[-7.8556838036,42.3301811218],"type":"Point"}
}