{
  "type": "Feature",
  "properties": {
    "iso:country":"ES",
    "sg:address":"Calle de Maladeta, 18",
    "sg:city":"Binefar",
    "sg:orig_category":"Empresas De Carpinter\u00cda De Madera",
    "sg:phone":"+34 974 43 09 48",
    "sg:postcode":"22500",
    "sg:province":"Huesca",
    "wof:name":"Biendicho Sanz Mariano",
    "wof:placetype":"venue"
},
  "geometry": {"coordinates":[0.299003005,41.8481140137],"type":"Point"}
}