{
  "type": "Feature",
  "properties": {
    "iso:country":"ES",
    "sg:address":"Bda. Pastores, 18",
    "sg:city":"Algeciras",
    "sg:orig_category":"Herboristas (al Por Menor)",
    "sg:phone":"+34 956 60 44 74",
    "sg:postcode":"11206",
    "sg:province":"C\u00e1diz",
    "wof:name":"Salvador Salvador Jose Francisco",
    "wof:placetype":"venue"
},
  "geometry": {"coordinates":[-5.4577841759,36.1135444641],"type":"Point"}
}