{
  "type": "Feature",
  "properties": {
    "iso:country":"ES",
    "sg:address":"Calle de San Anton, 16",
    "sg:city":"Granada",
    "sg:orig_category":"Telas Para Tapizar, Cortinas, Pasamaner\u00cda (fabricaci\u00d3n, Al Por Mayor)",
    "sg:phone":"+34 958 52 14 37",
    "sg:postcode":"18005",
    "sg:province":"Granada",
    "sg:website":"www.maisondecor.info",
    "wof:name":"Salinas Moreno Juan",
    "wof:placetype":"venue"
},
  "geometry": {"coordinates":[-3.6000270844,37.171913147],"type":"Point"}
}