{
  "type": "Feature",
  "properties": {
    "addr:full":"Calle de Palacio, 11 Ituren Navarra 31745",
    "addr:housenumber":"11",
    "addr:postcode":"31745",
    "addr:street":"Calle De Palacio",
    "iso:country":"ES",
    "sg:address":"Calle de Palacio, 11",
    "sg:city":"Ituren",
    "sg:orig_category":"Iglesia Cat\u00d3lica",
    "sg:phone":"+34 948 45 17 08",
    "sg:postcode":"31745",
    "sg:province":"Navarra",
    "wof:name":"Parroquia De San Martin",
    "wof:placetype":"venue"
},
  "geometry": {"coordinates":[-1.7104239464,43.1302185059],"type":"Point"}
}