{
  "type": "Feature",
  "properties": {
    "addr:full":"Cmno Alto A Los Villares, S/n Villamayor Salamanca 37185",
    "addr:housenumber":"s / n",
    "addr:postcode":"37185",
    "addr:street":"Cmno Alto;Los Villares",
    "iso:country":"ES",
    "sg:address":"Cmno Alto A Los Villares, S/n",
    "sg:city":"Villamayor",
    "sg:orig_category":"Zonas De Acampada, Aparcamiento Para Caravanas",
    "sg:phone":"+34 923 28 95 74",
    "sg:postcode":"37185",
    "sg:province":"Salamanca",
    "wof:name":"Gonzalez Blanco Silvia Maria",
    "wof:placetype":"venue"
},
  "geometry": {"coordinates":[-5.6902890205,41.001914978],"type":"Point"}
}