{
  "type": "Feature",
  "properties": {
    "addr:full":"Avda Canarias, 287 Vecindario Las Palmas 35110",
    "addr:housenumber":"287",
    "addr:postcode":"35110",
    "addr:street":"Avda Canarias;Palmas",
    "iso:country":"ES",
    "sg:address":"Avda Canarias, 287",
    "sg:city":"Vecindario",
    "sg:orig_category":"Molduras, Junquillos, Listones Y Molduras Perforadas",
    "sg:phone":"+34 928 75 48 21",
    "sg:postcode":"35110",
    "sg:province":"Las Palmas",
    "wof:name":"Leon Falcon Maria Emerita",
    "wof:placetype":"venue"
},
  "geometry": {"coordinates":[-15.4435272217,27.8470344543],"type":"Point"}
}