{
  "type": "Feature",
  "properties": {
    "iso:country":"ES",
    "sg:address":"Calle de Santa Fe, 9",
    "sg:city":"Madrid",
    "sg:orig_category":"Alimentaci\u00d3n General (al Por Menor)",
    "sg:phone":"+34 915 42 54 82",
    "sg:postcode":"28008",
    "sg:province":"Madrid",
    "wof:name":"Barajas Gallegos Sergio",
    "wof:placetype":"venue"
},
  "geometry": {"coordinates":[-3.7362511158,40.4308929443],"type":"Point"}
}