{
  "type": "Feature",
  "properties": {
    "addr:full":"Pol. Ind. Hortes Cami Ral, 16 Mataro Barcelona 08302",
    "addr:housenumber":"16",
    "addr:postcode":"08302",
    "addr:street":"Ral",
    "iso:country":"ES",
    "sg:address":"Pol. Ind. Hortes Cami Ral, 16",
    "sg:city":"Mataro",
    "sg:orig_category":"Fabricaci\u00d3n De Su\u00c9ters Y Chalecos De Punto",
    "sg:phone":"+34 937 99 88 18",
    "sg:postcode":"08302",
    "sg:province":"Barcelona",
    "wof:name":"Generes De Punt Casals S.a.",
    "wof:placetype":"venue"
},
  "geometry": {"coordinates":[2.4324100018,41.5336990356],"type":"Point"}
}