{
  "type": "Feature",
  "properties": {
    "addr:full":"Avda Guadarranque (del), 130 Estacion Ferrea C\u00e1diz 11368",
    "addr:housenumber":"130",
    "addr:postcode":"11368",
    "addr:street":"Avda Guadarranque Del;Ca\u0301Diz",
    "iso:country":"ES",
    "sg:address":"Avda Guadarranque (del), 130",
    "sg:city":"Estacion Ferrea",
    "sg:orig_category":"Chapister\u00cda",
    "sg:phone":"+34 956 78 61 60",
    "sg:postcode":"11368",
    "sg:province":"C\u00e1diz",
    "wof:name":"Dianez Paz Luis",
    "wof:placetype":"venue"
},
  "geometry": {"coordinates":[-5.4289870262,36.209564209],"type":"Point"}
}