{
  "type": "Feature",
  "properties": {
    "iso:country":"ES",
    "sg:address":"Carrer de Concepcion Arenal, 191",
    "sg:city":"Barcelona",
    "sg:orig_category":"M\u00c9dicos: Medicina Interna",
    "sg:phone":"+34 933 52 82 60",
    "sg:postcode":"08027",
    "sg:province":"Barcelona",
    "wof:name":"Casta\u00f1er Gargallo Miguel",
    "wof:placetype":"venue"
},
  "geometry": {"coordinates":[2.1841800213,41.4280166626],"type":"Point"}
}