{
  "type": "Feature",
  "properties": {
    "iso:country":"ES",
    "sg:address":"Ptge Rius, 1",
    "sg:city":"Hospitalet Llobregat",
    "sg:orig_category":"Zapatos (al Por Menor)",
    "sg:phone":"+34 934 48 00 22",
    "sg:postcode":"08904",
    "sg:province":"Barcelona",
    "wof:name":"Ruz Conde Francisco",
    "wof:placetype":"venue"
},
  "geometry": {"coordinates":[2.11855793,41.375705719],"type":"Point"}
}