{
  "type": "Feature",
  "properties": {
    "addr:full":"Calle de Alcantara, 6 Lora Rio Sevilla 41440",
    "addr:housenumber":"6",
    "addr:postcode":"41440",
    "addr:street":"Calle De Alcantara;Rio Sevilla",
    "iso:country":"ES",
    "sg:address":"Calle de Alcantara, 6",
    "sg:city":"Lora Rio",
    "sg:orig_category":"Estilistas Y Estudios De Estilo De Corte Y Confecci\u00d3n",
    "sg:phone":"+34 955 80 18 20",
    "sg:postcode":"41440",
    "sg:province":"Sevilla",
    "wof:name":"Vera Varela Manuel",
    "wof:placetype":"venue"
},
  "geometry": {"coordinates":[-5.5290050507,37.656829834],"type":"Point"}
}