{
  "type": "Feature",
  "properties": {
    "addr:full":"Calle de Historiador Clapes, 12 Santa Eulalia Islas Baleares 07840",
    "addr:housenumber":"12",
    "addr:postcode":"07840",
    "addr:street":"Calle De Historiador Clapes",
    "iso:country":"ES",
    "sg:address":"Calle de Historiador Clapes, 12",
    "sg:city":"Santa Eulalia",
    "sg:orig_category":"Panader\u00cdas, Panader\u00cdas",
    "sg:phone":"+34 971 33 08 73",
    "sg:postcode":"07840",
    "sg:province":"Islas Baleares",
    "wof:name":"Bustamante Genova Justo",
    "wof:placetype":"venue"
},
  "geometry": {"coordinates":[1.5346230268,38.986125946],"type":"Point"}
}