{
  "type": "Feature",
  "properties": {
    "iso:country":"ES",
    "sg:address":"Calle de Obispo Rey Redondo, 50",
    "sg:city":"San Cristobal De La Laguna",
    "sg:orig_category":"Panader\u00cdas, Panader\u00cdas",
    "sg:phone":"+34 922 26 11 51",
    "sg:postcode":"38201",
    "sg:province":"Santa Cruz De Tenerife",
    "wof:name":"Lopez Echeto Pasteleria S.l.",
    "wof:placetype":"venue"
},
  "geometry": {"coordinates":[-16.3178939819,28.4893665314],"type":"Point"}
}