{
  "type": "Feature",
  "properties": {
    "addr:full":"Av. B. Aires, 81 Muros A Coru\u00f1a 15250",
    "addr:housenumber":"81",
    "addr:postcode":"15250",
    "addr:street":"Av. B. Aires;A Corun\u0303A",
    "iso:country":"ES",
    "sg:address":"Av. B. Aires, 81",
    "sg:city":"Muros",
    "sg:orig_category":"Lavado, Limpieza De Veh\u00cdculos",
    "sg:phone":"+34 981 76 20 60",
    "sg:postcode":"15250",
    "sg:province":"A Coru\u00f1a",
    "wof:name":"Talleres Fernandez Cama\u00f1o S.l.",
    "wof:placetype":"venue"
},
  "geometry": {"coordinates":[-9.0576505661,42.7748222351],"type":"Point"}
}