{
  "type": "Feature",
  "properties": {
    "addr:full":"Avda Monte Carmelo, 7 Infante Juan Manuel Murcia 30011",
    "addr:housenumber":"7",
    "addr:postcode":"30011",
    "addr:street":"Avda Monte Carmelo",
    "iso:country":"ES",
    "sg:address":"Avda Monte Carmelo, 7",
    "sg:city":"Infante Juan Manuel",
    "sg:orig_category":"Herramientas Y Suministros Para Plomeros",
    "sg:phone":"+34 968 35 11 19",
    "sg:postcode":"30011",
    "sg:province":"Murcia",
    "wof:name":"Eurobridas Y Fittings S.a.",
    "wof:placetype":"venue"
},
  "geometry": {"coordinates":[-1.1176580191,37.977104187],"type":"Point"}
}