{
  "type": "Feature",
  "properties": {
    "addr:full":"Carrer de Peris I Mencheta, 12 Barcelona Barcelona 08032",
    "addr:housenumber":"12",
    "addr:postcode":"08032",
    "addr:street":"Carrer De Peris I Mencheta",
    "iso:country":"ES",
    "sg:address":"Carrer de Peris I Mencheta, 12",
    "sg:city":"Barcelona",
    "sg:orig_category":"Grafistas",
    "sg:phone":"+34 933 57 16 25",
    "sg:postcode":"08032",
    "sg:province":"Barcelona",
    "wof:name":"Lopez Corduente Juana",
    "wof:placetype":"venue"
},
  "geometry": {"coordinates":[2.1632649899,41.4271621704],"type":"Point"}
}