{
  "type": "Feature",
  "properties": {
    "iso:country":"ES",
    "sg:address":"Calle de Colombia, 13",
    "sg:city":"Toledo",
    "sg:orig_category":"Ropa Para Se\u00d1oras Y Caballeros (al Por Menor)",
    "sg:phone":"+34 925 21 30 51",
    "sg:postcode":"45004",
    "sg:province":"Toledo",
    "wof:name":"Lopez Aguado Josefa",
    "wof:placetype":"venue"
},
  "geometry": {"coordinates":[-4.0314254761,39.8673706055],"type":"Point"}
}