{
  "type": "Feature",
  "properties": {
    "iso:country":"ES",
    "sg:address":"Cami Fondo, S/n",
    "sg:city":"Burriana",
    "sg:orig_category":"Servicio De Salud",
    "sg:phone":"+34 964 51 35 53",
    "sg:postcode":"12530",
    "sg:province":"Castell\u00f3n",
    "wof:name":"Beltran Renau Luz Clara",
    "wof:placetype":"venue"
},
  "geometry": {"coordinates":[-0.080686003,39.8811073303],"type":"Point"}
}