{
  "type": "Feature",
  "properties": {
    "iso:country":"ES",
    "sg:address":"Avda Derechos Humanos (de Los), 10",
    "sg:city":"Villares",
    "sg:classifiers":[
        {
            "category":"Personal",
            "subcategory":"Barber",
            "type":"Services"
        }
    ],
    "sg:phone":"+34 918 74 78 92",
    "sg:postcode":"28500",
    "sg:province":"Madrid",
    "sg:tags":[
        "caballeros",
        "de",
        "peluqueros"
    ],
    "wof:name":"Lopez Ventoso Rosa",
    "wof:placetype":"venue"
},
  "geometry": {"coordinates":[-3.4406979084,40.2999954224],"type":"Point"}
}