{
  "type": "Feature",
  "properties": {
    "iso:country":"ES",
    "sg:address":"Calle de Bernabe Soriano, 19",
    "sg:city":"Jaen",
    "sg:orig_category":"Asesor\u00cda Fiscal Y Jur\u00cddica",
    "sg:phone":"+34 953 24 16 36",
    "sg:postcode":"23001",
    "sg:province":"Ja\u00e9n",
    "wof:name":"Merelo Jerez Julio Jesus",
    "wof:placetype":"venue"
},
  "geometry": {"coordinates":[-3.7877941132,37.766746521],"type":"Point"}
}