{
  "type": "Feature",
  "properties": {
    "addr:full":"Calle de Bajio (el), 14 Barranco Grande Santa Cruz De Tenerife 38108",
    "addr:housenumber":"14",
    "addr:postcode":"38108",
    "addr:street":"Calle De Bajio El",
    "iso:country":"ES",
    "sg:address":"Calle de Bajio (el), 14",
    "sg:city":"Barranco Grande",
    "sg:orig_category":"Organizaciones Profesionales",
    "sg:phone":"+34 922 62 23 51",
    "sg:postcode":"38108",
    "sg:province":"Santa Cruz De Tenerife",
    "wof:name":"Navarro Marquez Carlos Jose",
    "wof:placetype":"venue"
},
  "geometry": {"coordinates":[-16.312664032,28.4384231567],"type":"Point"}
}