{
  "type": "Feature",
  "properties": {
    "addr:full":"Avda Juan Perez Villamil, 2 Puerto De Vega Asturias 33790",
    "addr:housenumber":"2",
    "addr:postcode":"33790",
    "addr:street":"Avda Juan Perez Villamil",
    "iso:country":"ES",
    "sg:address":"Avda Juan Perez Villamil, 2",
    "sg:city":"Puerto De Vega",
    "sg:orig_category":"Asociaciones, Organismos Culturales Y Socioeducativos",
    "sg:phone":"+34 985 64 88 05",
    "sg:postcode":"33790",
    "sg:province":"Asturias",
    "sg:website":"www.ccprincipefelipe.tk",
    "wof:name":"Ayuntamiento De Navia",
    "wof:placetype":"venue"
},
  "geometry": {"coordinates":[-6.6466641426,43.5631790161],"type":"Point"}
}