{
  "type": "Feature",
  "properties": {
    "addr:full":"Centro Comercial Copo, S/n Ejido Almer\u00eda 04700",
    "addr:housenumber":"s",
    "addr:postcode":"04700",
    "addr:street":"/ N Ejido Almeri\u0301A",
    "iso:country":"ES",
    "sg:address":"Centro Comercial Copo, S/n",
    "sg:city":"Ejido",
    "sg:orig_category":"Ropa Para Ni\u00d1os (al Por Menor)",
    "sg:phone":"+34 950 48 90 10",
    "sg:postcode":"04700",
    "sg:province":"Almer\u00eda",
    "wof:name":"Garcia Ruiz Francisca",
    "wof:placetype":"venue"
},
  "geometry": {"coordinates":[-2.7580699921,36.7285690308],"type":"Point"}
}