{
  "type": "Feature",
  "properties": {
    "addr:full":"Calle de Toros, 45 Tobarra Albacete 02500",
    "addr:housenumber":"45",
    "addr:postcode":"02500",
    "addr:street":"Calle De Toros",
    "iso:country":"ES",
    "sg:address":"Calle de Toros, 45",
    "sg:city":"Tobarra",
    "sg:orig_category":"Electrodom\u00c9sticos (al Por Menor)",
    "sg:phone":"+34 967 32 82 46",
    "sg:postcode":"02500",
    "sg:province":"Albacete",
    "wof:name":"Perez Gomez Juan",
    "wof:placetype":"venue"
},
  "geometry": {"coordinates":[-1.687548995,38.5948143005],"type":"Point"}
}