{
  "type": "Feature",
  "properties": {
    "addr:full":"Calle de Fueros, 8 Jumilla Murcia 30520",
    "addr:housenumber":"8",
    "addr:postcode":"30520",
    "addr:street":"Calle De Fueros",
    "iso:country":"ES",
    "sg:address":"Calle de Fueros, 8",
    "sg:city":"Jumilla",
    "sg:orig_category":"Asesor\u00cda Fiscal Y Jur\u00cddica",
    "sg:phone":"+34 968 78 00 26",
    "sg:postcode":"30520",
    "sg:province":"Murcia",
    "wof:name":"Guardiola Carrion Antonio Salvador",
    "wof:placetype":"venue"
},
  "geometry": {"coordinates":[-1.3271466494,38.4731063843],"type":"Point"}
}