{
  "type": "Feature",
  "properties": {
    "addr:full":"Ctra Errekalde-larraskitu, 35 Bilbao Vizcaya 48002",
    "addr:housenumber":"35",
    "addr:postcode":"48002",
    "addr:street":"Ctra Errekalde-Larraskitu",
    "iso:country":"ES",
    "sg:address":"Ctra Errekalde-larraskitu, 35",
    "sg:city":"Bilbao",
    "sg:orig_category":"Empresas De Carpinter\u00cda De Madera",
    "sg:phone":"+34 944 44 55 33",
    "sg:postcode":"48002",
    "sg:province":"Vizcaya",
    "wof:name":"Ordosgoiti De La Cruz Lino Manuel",
    "wof:placetype":"venue"
},
  "geometry": {"coordinates":[-2.939759016,43.2495307922],"type":"Point"}
}