{
  "type": "Feature",
  "properties": {
    "iso:country":"ES",
    "sg:address":"Calle de Real Racing Club (del), S/n",
    "sg:city":"Santander",
    "sg:orig_category":"Agencias De Prensa E Informaci\u00d3n",
    "sg:phone":"+34 942 27 71 05",
    "sg:postcode":"39005",
    "sg:province":"Cantabria",
    "wof:name":"Agencia Efe S.a.",
    "wof:placetype":"venue"
},
  "geometry": {"coordinates":[-3.7919290066,43.4757461548],"type":"Point"}
}