{
  "type": "Feature",
  "properties": {
    "iso:country":"ES",
    "sg:address":"C/ Capita Alfons Vives, 98",
    "sg:city":"Elche",
    "sg:orig_category":"Fabricaci\u00d3n De Sobres, Bolsas Y Fundas",
    "sg:phone":"+34 966 65 56 52",
    "sg:postcode":"03204",
    "sg:province":"Alicante",
    "sg:website":"www.cuple.com",
    "wof:name":"Selconet S.a.",
    "wof:placetype":"venue"
},
  "geometry": {"coordinates":[-0.7104499936,38.2598571777],"type":"Point"}
}