{
  "type": "Feature",
  "properties": {
    "addr:full":"Av Roma (de), 7 Tarragona Tarragona 43005",
    "addr:postcode":"43005",
    "addr:street":"Av Roma De 7",
    "iso:country":"ES",
    "sg:address":"Av Roma (de), 7",
    "sg:city":"Tarragona",
    "sg:orig_category":"Abogados",
    "sg:phone":"+34 977 21 20 62",
    "sg:postcode":"43005",
    "sg:province":"Tarragona",
    "wof:name":"Badia Advocats S.l.",
    "wof:placetype":"venue"
},
  "geometry": {"coordinates":[1.2428460121,41.1188621521],"type":"Point"}
}