{
  "type": "Feature",
  "properties": {
    "addr:full":"Ctra Sant Lloren\u00c7, 2 Llagostera Girona 17240",
    "addr:housenumber":"2",
    "addr:postcode":"17240",
    "addr:street":"Ctra Sant Llorenc\u0327",
    "iso:country":"ES",
    "sg:address":"Ctra Sant Lloren\u00c7, 2",
    "sg:city":"Llagostera",
    "sg:orig_category":"Mec\u00c1nico Del Autom\u00d3vil",
    "sg:phone":"+34 972 83 05 78",
    "sg:postcode":"17240",
    "sg:province":"Girona",
    "wof:name":"Corominas Sayols Robert",
    "wof:placetype":"venue"
},
  "geometry": {"coordinates":[2.89311409,41.8220863342],"type":"Point"}
}