{
  "type": "Feature",
  "properties": {
    "addr:full":"Calle de Meson, 29 Albatera Alicante 03340",
    "addr:housenumber":"29",
    "addr:postcode":"03340",
    "addr:street":"Calle De Meson",
    "iso:country":"ES",
    "sg:address":"Calle de Meson, 29",
    "sg:city":"Albatera",
    "sg:orig_category":"Venta, Reparaci\u00d3n De M\u00c1quinas De Coser, Planchadoras Y M\u00c1quinas De Tricotar",
    "sg:phone":"+34 965 48 50 40",
    "sg:postcode":"03340",
    "sg:province":"Alicante",
    "wof:name":"Maquinas De Coser Hermanos Flores S.l.",
    "wof:placetype":"venue"
},
  "geometry": {"coordinates":[-0.8716989756,38.1786193848],"type":"Point"}
}