{
  "type": "Feature",
  "properties": {
    "addr:full":"Calle de Molina Sanchez Lagartijo, S/n Cordoba C\u00f3rdoba 14001",
    "addr:housenumber":"s",
    "addr:postcode":"14001",
    "addr:street":"Calle De Molina Sanchez Lagartijo;/ N;Co\u0301Rdoba",
    "iso:country":"ES",
    "sg:address":"Calle de Molina Sanchez Lagartijo, S/n",
    "sg:city":"Cordoba",
    "sg:orig_category":"Farmacias",
    "sg:phone":"+34 957 47 96 54",
    "sg:postcode":"14001",
    "sg:province":"C\u00f3rdoba",
    "wof:name":"Lucena Valls Maria",
    "wof:placetype":"venue"
},
  "geometry": {"coordinates":[-4.7790441513,37.8921165466],"type":"Point"}
}