{
  "type": "Feature",
  "properties": {
    "iso:country":"ES",
    "sg:address":"Plaz Carmen (del), 8",
    "sg:city":"Almeria",
    "sg:orig_category":"Abogados",
    "sg:phone":"+34 950 23 43 77",
    "sg:postcode":"04003",
    "sg:province":"Almer\u00eda",
    "wof:name":"Romero-miura Gimenez Fausto",
    "wof:placetype":"venue"
},
  "geometry": {"coordinates":[-2.4649391174,36.8421440125],"type":"Point"}
}