{
  "type": "Feature",
  "properties": {
    "iso:country":"ES",
    "sg:address":"Sancho Abarca, 2",
    "sg:city":"Iru\u00f1a",
    "sg:orig_category":"Grafistas",
    "sg:phone":"+34 948 14 30 22",
    "sg:postcode":"31014",
    "sg:province":"Navarra",
    "wof:name":"Ilune Dise\u00f1o S.l.",
    "wof:placetype":"venue"
},
  "geometry": {"coordinates":[-1.6538050175,42.8230361938],"type":"Point"}
}