{
  "type": "Feature",
  "properties": {
    "iso:country":"ES",
    "sg:address":"Calle de Carniceros, 5",
    "sg:city":"San Antolin",
    "sg:orig_category":"Tapicer\u00cdas",
    "sg:phone":"+34 968 29 52 78",
    "sg:postcode":"30004",
    "sg:province":"Murcia",
    "wof:name":"Gomez Romero Juan",
    "wof:placetype":"venue"
},
  "geometry": {"coordinates":[-1.1298867464,37.9834747314],"type":"Point"}
}