{
  "type": "Feature",
  "properties": {
    "iso:country":"ES",
    "sg:address":"Pl Mercadal, 13",
    "sg:city":"Barcelona",
    "sg:orig_category":"Pod\u00d3logos: Pedicuros",
    "sg:phone":"+34 933 46 11 68",
    "sg:postcode":"08030",
    "sg:province":"Barcelona",
    "wof:name":"Casademunt Borja Susana",
    "wof:placetype":"venue"
},
  "geometry": {"coordinates":[2.1882190704,41.4345588684],"type":"Point"}
}