{
  "type": "Feature",
  "properties": {
    "iso:country":"ES",
    "sg:address":"Calle de Pedralba, 95",
    "sg:city":"Vilamarxant",
    "sg:orig_category":"Mec\u00c1nico Del Autom\u00d3vil",
    "sg:phone":"+34 962 71 03 05",
    "sg:postcode":"46191",
    "sg:province":"Valencia",
    "wof:name":"Serafin Lerma Domenech S.l.",
    "wof:placetype":"venue"
},
  "geometry": {"coordinates":[-0.6275759935,39.5676651001],"type":"Point"}
}