{
  "type": "Feature",
  "properties": {
    "addr:full":"Avda Rambleta, 12 Catarroja Valencia 46470",
    "addr:housenumber":"12",
    "addr:postcode":"46470",
    "addr:street":"Avda Rambleta",
    "iso:country":"ES",
    "sg:address":"Avda Rambleta, 12",
    "sg:city":"Catarroja",
    "sg:orig_category":"Ropa Y Art\u00cdculos Pre",
    "sg:phone":"+34 961 26 35 25",
    "sg:postcode":"46470",
    "sg:province":"Valencia",
    "wof:name":"Chust Celda Eduvina",
    "wof:placetype":"venue"
},
  "geometry": {"coordinates":[-0.4063799977,39.4031982422],"type":"Point"}
}