{
  "type": "Feature",
  "properties": {
    "iso:country":"ES",
    "sg:address":"Rda. Belen, 9",
    "sg:city":"Orgaz",
    "sg:orig_category":"Electricidad: Instaladores",
    "sg:phone":"+34 925 31 72 05",
    "sg:postcode":"45450",
    "sg:province":"Toledo",
    "wof:name":"Cuerda Jimenez Antonio De La",
    "wof:placetype":"venue"
},
  "geometry": {"coordinates":[-3.8734390736,39.651008606],"type":"Point"}
}