{
  "type": "Feature",
  "properties": {
    "addr:full":"Mercat Sant Antoni, S/n Barcelona Barcelona 08015",
    "addr:housenumber":"s",
    "addr:postcode":"08015",
    "addr:street":"/ N",
    "iso:country":"ES",
    "sg:address":"Mercat Sant Antoni, S/n",
    "sg:city":"Barcelona",
    "sg:orig_category":"Carnicer\u00cdas, Carnicer\u00cdas",
    "sg:phone":"+34 933 25 79 41",
    "sg:postcode":"08015",
    "sg:province":"Barcelona",
    "wof:name":"Rios Bayona Antonio",
    "wof:placetype":"venue"
},
  "geometry": {"coordinates":[2.1608901024,41.379535675],"type":"Point"}
}