{
  "type": "Feature",
  "properties": {
    "addr:full":"Calle de Gurutzegi, 12 Donostia-san Sebastian Guip\u00f9zcoa 20018",
    "addr:housenumber":"12",
    "addr:postcode":"20018",
    "addr:street":"Calle De Gurutzegi",
    "iso:country":"ES",
    "sg:address":"Calle de Gurutzegi, 12",
    "sg:city":"Donostia-san Sebastian",
    "sg:orig_category":"Centros Empresariales",
    "sg:phone":"+34 943 32 05 04",
    "sg:postcode":"20018",
    "sg:province":"Guip\u00f9zcoa",
    "wof:name":"Asociacion Patronal De Carpinteros E Industrias Similares De Guipuzkoa",
    "wof:placetype":"venue"
},
  "geometry": {"coordinates":[-2.0125694275,43.2793807983],"type":"Point"}
}