{
  "type": "Feature",
  "properties": {
    "addr:full":"Pla\u00c7 Mercadal, 37 Balaguer Lleida 25600",
    "addr:housenumber":"37",
    "addr:postcode":"25600",
    "addr:street":"Mercadal",
    "iso:country":"ES",
    "sg:address":"Pla\u00c7 Mercadal, 37",
    "sg:city":"Balaguer",
    "sg:orig_category":"Peluqueros: De Se\u00d1oras",
    "sg:phone":"+34 973 44 89 39",
    "sg:postcode":"25600",
    "sg:province":"Lleida",
    "wof:name":"Diaz Valera Braulia",
    "wof:placetype":"venue"
},
  "geometry": {"coordinates":[0.8055239916,41.7892608643],"type":"Point"}
}