{
  "type": "Feature",
  "properties": {
    "iso:country":"ES",
    "sg:address":"Carr Espartero, 3",
    "sg:city":"Burjassot",
    "sg:orig_category":"Tratamiento De Metales",
    "sg:phone":"+34 963 90 11 26",
    "sg:postcode":"46100",
    "sg:province":"Valencia",
    "wof:name":"Garcia Pe\u00f1a Jose Maria",
    "wof:placetype":"venue"
},
  "geometry": {"coordinates":[-0.4130850136,39.5024528503],"type":"Point"}
}