{
  "type": "Feature",
  "properties": {
    "addr:full":"Calle de Iturriza, 17 Bilbao Vizcaya 48003",
    "addr:housenumber":"17",
    "addr:postcode":"48003",
    "addr:street":"Calle De Iturriza",
    "iso:country":"ES",
    "sg:address":"Calle de Iturriza, 17",
    "sg:city":"Bilbao",
    "sg:orig_category":"Material Y Suministros Para Dentistas, Cirujanos",
    "sg:phone":"+34 944 10 23 21",
    "sg:postcode":"48003",
    "sg:province":"Vizcaya",
    "wof:name":"Paulino Resines Diez",
    "wof:placetype":"venue"
},
  "geometry": {"coordinates":[-2.9325559139,43.2572479248],"type":"Point"}
}