{
  "type": "Feature",
  "properties": {
    "iso:country":"ES",
    "sg:address":"Calle de Roa De La Vega, 7",
    "sg:city":"Le\u00f3n",
    "sg:orig_category":"Tintorer\u00cdas, Limpieza En Seco",
    "sg:phone":"+34 987 23 63 15",
    "sg:postcode":"24002",
    "sg:province":"Le\u00f3n",
    "wof:name":"Blanco Ruano Primitivo",
    "wof:placetype":"venue"
},
  "geometry": {"coordinates":[-5.576239109,42.6010513306],"type":"Point"}
}