{
  "type": "Feature",
  "properties": {
    "iso:country":"ES",
    "sg:address":"Calle de Gutierre De Cetina, 55",
    "sg:city":"Madrid",
    "sg:orig_category":"Fabricaci\u00d3n De Peines Y De Accesorios De Peluquer\u00cda",
    "sg:phone":"+34 914 08 64 87",
    "sg:postcode":"28017",
    "sg:province":"Madrid",
    "wof:name":"Torres Crespo Mercedes",
    "wof:placetype":"venue"
},
  "geometry": {"coordinates":[-3.6425836086,40.4316635132],"type":"Point"}
}