{
  "type": "Feature",
  "properties": {
    "addr:full":"Calle de Traperia, 6 Catedral Murcia 30001",
    "addr:housenumber":"6",
    "addr:postcode":"30001",
    "addr:street":"Calle De Traperia",
    "iso:country":"ES",
    "sg:address":"Calle de Traperia, 6",
    "sg:city":"Catedral",
    "sg:orig_category":"Torrefactado De Caf\u00c9",
    "sg:phone":"+34 968 22 00 94",
    "sg:postcode":"30001",
    "sg:province":"Murcia",
    "wof:name":"Productos Jamaica S.l.",
    "wof:placetype":"venue"
},
  "geometry": {"coordinates":[-1.128698945,37.9848976135],"type":"Point"}
}