{
  "type": "Feature",
  "properties": {
    "addr:full":"Avda Calderon De La Barca, 7 Cordoba C\u00f3rdoba 14010",
    "addr:housenumber":"7",
    "addr:postcode":"14010",
    "addr:street":"Avda Calderon De La Barca;Co\u0301Rdoba",
    "iso:country":"ES",
    "sg:address":"Avda Calderon De La Barca, 7",
    "sg:city":"Cordoba",
    "sg:orig_category":"Fabricaci\u00d3n De Jabones, Detergentes Y Lej\u00cdas",
    "sg:phone":"+34 957 76 47 57",
    "sg:postcode":"14010",
    "sg:province":"C\u00f3rdoba",
    "wof:name":"Bayer Cropscience S.l.",
    "wof:placetype":"venue"
},
  "geometry": {"coordinates":[-4.7592229843,37.8790245056],"type":"Point"}
}