{
  "type": "Feature",
  "properties": {
    "iso:country":"ES",
    "sg:address":"Av Just Marles Vilarrodona, 45",
    "sg:city":"Lloret Mar",
    "sg:orig_category":"Bazares, Art\u00cdculos De Limpieza Y De Cocina (al Por Menor)",
    "sg:phone":"+34 972 36 66 84",
    "sg:postcode":"17310",
    "sg:province":"Girona",
    "wof:name":"Luis Casagran Nuria",
    "wof:placetype":"venue"
},
  "geometry": {"coordinates":[2.8429300785,41.7000656128],"type":"Point"}
}