{
  "type": "Feature",
  "properties": {
    "iso:country":"ES",
    "sg:address":"Ptda Boqueres-a, 31",
    "sg:city":"Boqueres",
    "sg:orig_category":"Traductores",
    "sg:phone":"+34 965 66 54 43",
    "sg:postcode":"03690",
    "sg:province":"Alicante",
    "wof:name":"Wierleuker Plein Gudrun",
    "wof:placetype":"venue"
},
  "geometry": {"coordinates":[-0.5155332088,38.4112281799],"type":"Point"}
}