{
  "type": "Feature",
  "properties": {
    "iso:country":"ES",
    "sg:address":"Calle de Arzobispo Marcelo Gonzalez, 1",
    "sg:city":"Valladolid",
    "sg:orig_category":"Institutos De Belleza",
    "sg:phone":"+34 983 22 20 46",
    "sg:postcode":"47007",
    "sg:province":"Valladolid",
    "wof:name":"Garcia Ordax Raquel",
    "wof:placetype":"venue"
},
  "geometry": {"coordinates":[-4.737244606,41.6362190247],"type":"Point"}
}