{
  "type": "Feature",
  "properties": {
    "iso:country":"ES",
    "sg:address":"Calle de Marques De Lozoya, 12",
    "sg:city":"Madrid",
    "sg:orig_category":"T\u00c9cnicos Veterinarios",
    "sg:phone":"+34 915 73 54 70",
    "sg:postcode":"28007",
    "sg:province":"Madrid",
    "wof:name":"Lorente Braojos Luis Mariano",
    "wof:placetype":"venue"
},
  "geometry": {"coordinates":[-3.6633360386,40.4183006287],"type":"Point"}
}