{
  "type": "Feature",
  "properties": {
    "addr:full":"Urb. Torrox-costa, S/n Torrox-costa M\u00e1laga 29793",
    "addr:housenumber":"s",
    "addr:postcode":"29793",
    "addr:street":"/ N Torrox-Costa Ma\u0301Laga",
    "iso:country":"ES",
    "sg:address":"Urb. Torrox-costa, S/n",
    "sg:city":"Torrox-costa",
    "sg:orig_category":"Autob\u00das (explotaci\u00d3n Y Servicios De)",
    "sg:phone":"+34 952 53 10 43",
    "sg:postcode":"29793",
    "sg:province":"M\u00e1laga",
    "wof:name":"Autocares Hermanos Nieto S. L.",
    "wof:placetype":"venue"
},
  "geometry": {"coordinates":[-3.9456365108,36.7326087952],"type":"Point"}
}