{
  "type": "Feature",
  "properties": {
    "addr:full":"Carrer de Industria, 146 Barcelona Barcelona 08025",
    "addr:housenumber":"146",
    "addr:postcode":"08025",
    "addr:street":"Carrer De Industria",
    "iso:country":"ES",
    "sg:address":"Carrer de Industria, 146",
    "sg:city":"Barcelona",
    "sg:orig_category":"Ropa Para Se\u00d1oras (al Por Menor)",
    "sg:phone":"+34 934 35 86 88",
    "sg:postcode":"08025",
    "sg:province":"Barcelona",
    "wof:name":"Som S.c.p.",
    "wof:placetype":"venue"
},
  "geometry": {"coordinates":[2.1741299629,41.4091644287],"type":"Point"}
}