{
  "type": "Feature",
  "properties": {
    "iso:country":"ES",
    "sg:address":"Avda Constitucion, S/n",
    "sg:city":"Mas Matas",
    "sg:orig_category":"Material Y Herramientas Agr\u00cdcolas",
    "sg:phone":"+34 978 84 88 51",
    "sg:postcode":"44564",
    "sg:province":"Teruel",
    "wof:name":"Royo Mestre Fidel",
    "wof:placetype":"venue"
},
  "geometry": {"coordinates":[-0.244709,40.8354682922],"type":"Point"}
}