{
  "type": "Feature",
  "properties": {
    "addr:full":"Avda Zurriola De, 8 Donostia-san Sebastian Guip\u00f9zcoa 20002",
    "addr:housenumber":"8",
    "addr:postcode":"20002",
    "addr:street":"Avda Zurriola De",
    "iso:country":"ES",
    "sg:address":"Avda Zurriola De, 8",
    "sg:city":"Donostia-san Sebastian",
    "sg:orig_category":"Asociaciones Y Clubs Deportivos",
    "sg:phone":"+34 943 27 41 89",
    "sg:postcode":"20002",
    "sg:province":"Guip\u00f9zcoa",
    "wof:name":"Sociedad De Caza Y Pesca",
    "wof:placetype":"venue"
},
  "geometry": {"coordinates":[-1.9783680439,43.3239135742],"type":"Point"}
}