{
  "type": "Feature",
  "properties": {
    "addr:full":"Calle de Carabela La Pinta, 20 Baiona Pontevedra 36300",
    "addr:housenumber":"20",
    "addr:postcode":"36300",
    "addr:street":"Calle De Carabela La Pinta",
    "iso:country":"ES",
    "sg:address":"Calle de Carabela La Pinta, 20",
    "sg:city":"Baiona",
    "sg:orig_category":"Comerciantes Al Por Mayor De Vinos, Licores Y Alcoholes",
    "sg:phone":"+34 986 35 58 57",
    "sg:postcode":"36300",
    "sg:province":"Pontevedra",
    "wof:name":"Rodriguez Alvarez Abel",
    "wof:placetype":"venue"
},
  "geometry": {"coordinates":[-8.8508443832,42.1203117371],"type":"Point"}
}