{
  "type": "Feature",
  "properties": {
    "addr:full":"Rua Plateria, 17 Grove Pontevedra 36980",
    "addr:housenumber":"17",
    "addr:postcode":"36980",
    "addr:street":"Rua Plateria;Grove Pontevedra",
    "iso:country":"ES",
    "sg:address":"Rua Plateria, 17",
    "sg:city":"Grove",
    "sg:orig_category":"Transportes Por Carretera: Lotes Completos, Mercanc\u00cdas Diversas",
    "sg:phone":"+34 986 73 10 41",
    "sg:postcode":"36980",
    "sg:province":"Pontevedra",
    "wof:name":"Chaves Pi\u00f1eiro Ernesto",
    "wof:placetype":"venue"
},
  "geometry": {"coordinates":[-8.8633785248,42.4949417114],"type":"Point"}
}