{
  "type": "Feature",
  "properties": {
    "addr:full":"Calle de Elbarren, 34 Leitza Navarra 31880",
    "addr:housenumber":"34",
    "addr:postcode":"31880",
    "addr:street":"Calle De Elbarren",
    "iso:country":"ES",
    "sg:address":"Calle de Elbarren, 34",
    "sg:city":"Leitza",
    "sg:orig_category":"Peluquer\u00cdas, Peluquer\u00cda Mixta",
    "sg:phone":"+34 948 61 06 49",
    "sg:postcode":"31880",
    "sg:province":"Navarra",
    "wof:name":"Peluqueria Eguzki",
    "wof:placetype":"venue"
},
  "geometry": {"coordinates":[-1.9155060053,43.0809288025],"type":"Point"}
}