{
  "type": "Feature",
  "properties": {
    "iso:country":"ES",
    "sg:address":"Calle de Rosaleda, 2",
    "sg:city":"Rua De Valdeorras",
    "sg:orig_category":"Ropa Para Se\u00d1oras Y Caballeros (al Por Menor)",
    "sg:phone":"+34 988 31 00 40",
    "sg:postcode":"32350",
    "sg:province":"Ourense",
    "wof:name":"Lopez Alonso Baltasar",
    "wof:placetype":"venue"
},
  "geometry": {"coordinates":[-7.1205739975,42.392490387],"type":"Point"}
}