{
  "type": "Feature",
  "properties": {
    "iso:country":"ES",
    "sg:address":"Calle de Don Pedro Gambin, S/n",
    "sg:city":"Alhama Murcia",
    "sg:orig_category":"Ense\u00d1anza: Comercio, Gesti\u00d3n, Inform\u00c1tica",
    "sg:phone":"+34 968 63 95 01",
    "sg:postcode":"30840",
    "sg:province":"Murcia",
    "wof:name":"Sanchez Gonzalez Eduvigis",
    "wof:placetype":"venue"
},
  "geometry": {"coordinates":[-1.428435564,37.8495788574],"type":"Point"}
}