{
  "type": "Feature",
  "properties": {
    "addr:full":"Carr Major, 77 Benifaio Valencia 46450",
    "addr:housenumber":"77",
    "addr:postcode":"46450",
    "addr:street":"Carr Major",
    "iso:country":"ES",
    "sg:address":"Carr Major, 77",
    "sg:city":"Benifaio",
    "sg:orig_category":"Empresas De Pintura Y Revestimientos",
    "sg:phone":"+34 961 78 05 65",
    "sg:postcode":"46450",
    "sg:province":"Valencia",
    "wof:name":"Mas Cleriques Alfredo",
    "wof:placetype":"venue"
},
  "geometry": {"coordinates":[-0.424193114,39.2861061096],"type":"Point"}
}