{
  "type": "Feature",
  "properties": {
    "addr:full":"Calle de Alfileritos, 11 Toledo Toledo 45003",
    "addr:housenumber":"11",
    "addr:postcode":"45003",
    "addr:street":"Calle De Alfileritos",
    "iso:country":"ES",
    "sg:address":"Calle de Alfileritos, 11",
    "sg:city":"Toledo",
    "sg:orig_category":"Alimentaci\u00d3n General (al Por Menor)",
    "sg:phone":"+34 925 21 54 88",
    "sg:postcode":"45003",
    "sg:province":"Toledo",
    "wof:name":"Arroyo Bermudez Francisco Vicente",
    "wof:placetype":"venue"
},
  "geometry": {"coordinates":[-4.0241127014,39.8597946167],"type":"Point"}
}