{
  "type": "Feature",
  "properties": {
    "addr:full":"Avda Valle Inclan, 34 Nueva Andalucia M\u00e1laga 29660",
    "addr:housenumber":"34",
    "addr:postcode":"29660",
    "addr:street":"Avda Valle Inclan;Ma\u0301Laga",
    "iso:country":"ES",
    "sg:address":"Avda Valle Inclan, 34",
    "sg:city":"Nueva Andalucia",
    "sg:orig_category":"Muebles, Minoristas",
    "sg:phone":"+34 952 90 77 99",
    "sg:postcode":"29660",
    "sg:province":"M\u00e1laga",
    "wof:name":"Marbella Furnisher Gallery S.l.",
    "wof:placetype":"venue"
},
  "geometry": {"coordinates":[-4.9795079231,36.5019950867],"type":"Point"}
}