{
  "type": "Feature",
  "properties": {
    "addr:full":"Rbla Celler, 29 S. Cugat Valles Barcelona 08172",
    "addr:housenumber":"29",
    "addr:postcode":"08172",
    "addr:street":"Rbla Celler;S. Cugat Valles Barcelona",
    "iso:country":"ES",
    "sg:address":"Rbla Celler, 29",
    "sg:city":"S. Cugat Valles",
    "sg:orig_category":"Molduras, Junquillos, Listones Y Molduras Perforadas",
    "sg:phone":"+34 936 75 96 18",
    "sg:postcode":"08172",
    "sg:province":"Barcelona",
    "wof:name":"Bolos Berges Montserrat",
    "wof:placetype":"venue"
},
  "geometry": {"coordinates":[2.0852100849,41.4714660645],"type":"Point"}
}