{
  "type": "Feature",
  "properties": {
    "addr:full":"Pase Mons De, 111 Donostia-san Sebastian Guip\u00f9zcoa 20015",
    "addr:housenumber":"111",
    "addr:postcode":"20015",
    "iso:country":"ES",
    "sg:address":"Pase Mons De, 111",
    "sg:city":"Donostia-san Sebastian",
    "sg:orig_category":"M\u00c9dicos: Estomatolog\u00cda",
    "sg:phone":"+34 943 29 29 86",
    "sg:postcode":"20015",
    "sg:province":"Guip\u00f9zcoa",
    "wof:name":"Vila Fontan Maria Josefa",
    "wof:placetype":"venue"
},
  "geometry": {"coordinates":[-1.9794000387,43.3173789978],"type":"Point"}
}