{
  "type": "Feature",
  "properties": {
    "addr:full":"Obispos, 2 Xativa Valencia 46800",
    "addr:housenumber":"2",
    "addr:postcode":"46800",
    "addr:street":"Obispos",
    "iso:country":"ES",
    "sg:address":"Obispos, 2",
    "sg:city":"Xativa",
    "sg:orig_category":"Cajas De Ahorro",
    "sg:phone":"+34 962 28 30 97",
    "sg:postcode":"46800",
    "sg:province":"Valencia",
    "wof:name":"Caixa D'estalvis I Pensions De Barcelona",
    "wof:placetype":"venue"
},
  "geometry": {"coordinates":[-0.5200830102,38.9934272766],"type":"Point"}
}