{
  "type": "Feature",
  "properties": {
    "addr:full":"Calle de Galicia, 28 Corralejo Las Palmas 35660",
    "addr:housenumber":"28",
    "addr:postcode":"35660",
    "addr:street":"Calle De Galicia",
    "iso:country":"ES",
    "sg:address":"Calle de Galicia, 28",
    "sg:city":"Corralejo",
    "sg:orig_category":"Arquitectos",
    "sg:phone":"+34 928 53 74 95",
    "sg:postcode":"35660",
    "sg:province":"Las Palmas",
    "wof:name":"Mantecon Gomez Jose Manuel",
    "wof:placetype":"venue"
},
  "geometry": {"coordinates":[-13.8653669357,28.7425327301],"type":"Point"}
}