{
  "type": "Feature",
  "properties": {
    "addr:full":"Calle de Fermin Caballero, 25 Madrid Madrid 28034",
    "addr:housenumber":"25",
    "addr:postcode":"madrid;28034",
    "addr:street":"Calle De Fermin Caballero",
    "iso:country":"ES",
    "sg:address":"Calle de Fermin Caballero, 25",
    "sg:city":"Madrid",
    "sg:orig_category":"Frutas, Legumbres Frescas Y Tempranas (al Por Menor)",
    "sg:phone":"+34 917 30 34 74",
    "sg:postcode":"28034",
    "sg:province":"Madrid",
    "wof:name":"Frutas Los Gallegos C.b.",
    "wof:placetype":"venue"
},
  "geometry": {"coordinates":[-3.7023100853,40.4855461121],"type":"Point"}
}