{
  "type": "Feature",
  "properties": {
    "iso:country":"ES",
    "sg:address":"Carrer de Beethoven, 63",
    "sg:city":"Santa Coloma De Gramenet",
    "sg:orig_category":"Inmobiliaria (agencias)",
    "sg:phone":"+34 933 92 91 33",
    "sg:postcode":"08922",
    "sg:province":"Barcelona",
    "wof:name":"Inmocredit Comas S.l.",
    "wof:placetype":"venue"
},
  "geometry": {"coordinates":[2.2190539837,41.4511222839],"type":"Point"}
}