{
  "type": "Feature",
  "properties": {
    "addr:full":"Calle de Constitucion, 47 Rojales Alicante 03170",
    "addr:housenumber":"47",
    "addr:postcode":"03170",
    "addr:street":"Calle De Constitucion",
    "iso:country":"ES",
    "sg:address":"Calle de Constitucion, 47",
    "sg:city":"Rojales",
    "sg:orig_category":"Cristaler\u00cdas",
    "sg:phone":"+34 966 71 59 92",
    "sg:postcode":"03170",
    "sg:province":"Alicante",
    "wof:name":"Garcia Cano Antonio",
    "wof:placetype":"venue"
},
  "geometry": {"coordinates":[-0.7315186262,38.0840644836],"type":"Point"}
}