{
  "type": "Feature",
  "properties": {
    "iso:country":"ES",
    "sg:address":"Pase Estacion, 9",
    "sg:city":"Illescas",
    "sg:orig_category":"Empresarios",
    "sg:phone":"+34 925 51 16 10",
    "sg:postcode":"45200",
    "sg:province":"Toledo",
    "wof:name":"Fundacion Formacion Y Empleo Castilla La Mancha",
    "wof:placetype":"venue"
},
  "geometry": {"coordinates":[-3.8448040485,40.1226158142],"type":"Point"}
}