{
  "type": "Feature",
  "properties": {
    "iso:country":"ES",
    "sg:address":"Bruguera, S/n",
    "sg:city":"Ribes Freser",
    "sg:orig_category":"Aguas (distribuci\u00d3n, Servicios)",
    "sg:phone":"+34 972 72 72 58",
    "sg:postcode":"17534",
    "sg:province":"Girona",
    "wof:name":"Fontaga S. A.",
    "wof:placetype":"venue"
},
  "geometry": {"coordinates":[2.1667399406,42.3028831482],"type":"Point"}
}