{
  "type": "Feature",
  "properties": {
    "addr:full":"Calle de Rosario, 253 Viso Del Alcor Sevilla 41520",
    "addr:housenumber":"253",
    "addr:postcode":"41520",
    "addr:street":"Calle De Rosario",
    "iso:country":"ES",
    "sg:address":"Calle de Rosario, 253",
    "sg:city":"Viso Del Alcor",
    "sg:orig_category":"Cr\u00cda De Cerdos",
    "sg:phone":"+34 955 95 30 11",
    "sg:postcode":"41520",
    "sg:province":"Sevilla",
    "wof:name":"Granja Ni\u00f1o Cachete S.l.",
    "wof:placetype":"venue"
},
  "geometry": {"coordinates":[-5.7159957886,37.3908233643],"type":"Point"}
}