{
  "type": "Feature",
  "properties": {
    "iso:country":"ES",
    "sg:address":"Calle de Margaritas, Las, 11",
    "sg:city":"Siesta",
    "sg:orig_category":"Tintorer\u00cdas, Limpieza En Seco",
    "sg:phone":"+34 971 33 18 74",
    "sg:postcode":"07840",
    "sg:province":"Islas Baleares",
    "wof:name":"Lavanderia Siesta S.l.",
    "wof:placetype":"venue"
},
  "geometry": {"coordinates":[1.5341850519,38.9850311279],"type":"Point"}
}