{
  "type": "Feature",
  "properties": {
    "iso:country":"ES",
    "sg:address":"Calle de Ejido De La Alcantarilla, 14",
    "sg:city":"Jaen",
    "sg:orig_category":"Empresarios",
    "sg:phone":"+34 953 23 38 08",
    "sg:postcode":"23001",
    "sg:province":"Ja\u00e9n",
    "wof:name":"Fundacion Catalina Mir",
    "wof:placetype":"venue"
},
  "geometry": {"coordinates":[-3.7892155647,37.7637176514],"type":"Point"}
}