{
  "type": "Feature",
  "properties": {
    "iso:country":"ES",
    "sg:address":"Calle de Ezequiel Solana, 5",
    "sg:city":"Madrid",
    "sg:orig_category":"Molduras, Junquillos, Listones Y Molduras Perforadas",
    "sg:phone":"+34 913 67 96 30",
    "sg:postcode":"28017",
    "sg:province":"Madrid",
    "wof:name":"Barreiro Rodriguez Jesus",
    "wof:placetype":"venue"
},
  "geometry": {"coordinates":[-3.6468060017,40.4333457947],"type":"Point"}
}