{
  "type": "Feature",
  "properties": {
    "addr:full":"Calle de Manuel Fernandez Arriola, 2 Ejido Almer\u00eda 04700",
    "addr:housenumber":"2",
    "addr:postcode":"04700",
    "addr:street":"Calle De Manuel Fernandez Arriola;Almeri\u0301A",
    "iso:country":"ES",
    "sg:address":"Calle de Manuel Fernandez Arriola, 2",
    "sg:city":"Ejido",
    "sg:orig_category":"Agencias Y Agentes Comerciales, Representantes",
    "sg:phone":"+34 950 48 09 82",
    "sg:postcode":"04700",
    "sg:province":"Almer\u00eda",
    "wof:name":"Augrofresh Spain S.l.",
    "wof:placetype":"venue"
},
  "geometry": {"coordinates":[-2.8151929379,36.7730102539],"type":"Point"}
}