{
  "type": "Feature",
  "properties": {
    "addr:full":"Rua Nosa Se\u00d1ora Do Carmen, 70 Burela Lugo 27880",
    "addr:housenumber":"70",
    "addr:postcode":"27880",
    "addr:street":"Rua Nosa Sen\u0303Ora;Carmen",
    "iso:country":"ES",
    "sg:address":"Rua Nosa Se\u00d1ora Do Carmen, 70",
    "sg:city":"Burela",
    "sg:orig_category":"Arreglo, Reparaci\u00d3n, Piezas Sueltas De Televisi\u00d3n, V\u00cddeo, Hi",
    "sg:phone":"+34 982 58 18 57",
    "sg:postcode":"27880",
    "sg:province":"Lugo",
    "wof:name":"Televexo C. B.",
    "wof:placetype":"venue"
},
  "geometry": {"coordinates":[-7.3624038696,43.6624679565],"type":"Point"}
}