{
  "type": "Feature",
  "properties": {
    "addr:full":"Calle de Ca\u00d1ada Arboleda, S/n Laguna Duero Valladolid 47140",
    "addr:housenumber":"s / n",
    "addr:postcode":"47140",
    "addr:street":"Calle De Can\u0303Ada Arboleda",
    "iso:country":"ES",
    "sg:address":"Calle de Ca\u00d1ada Arboleda, S/n",
    "sg:city":"Laguna Duero",
    "sg:orig_category":"Asilos De Ancianos. Centros Privados",
    "sg:phone":"+34 983 54 06 12",
    "sg:postcode":"47140",
    "sg:province":"Valladolid",
    "wof:name":"Servicios Sociales De La Junta De Castilla Y Leon",
    "wof:placetype":"venue"
},
  "geometry": {"coordinates":[-4.7260289192,41.5838012695],"type":"Point"}
}