{
  "type": "Feature",
  "properties": {
    "addr:full":"Calle de Miguel Hernandez, 45 Nerva Huelva 21670",
    "addr:housenumber":"45",
    "addr:postcode":"21670",
    "addr:street":"Calle De Miguel Hernandez",
    "iso:country":"ES",
    "sg:address":"Calle de Miguel Hernandez, 45",
    "sg:city":"Nerva",
    "sg:orig_category":"Alimentaci\u00d3n General (al Por Menor)",
    "sg:phone":"+34 959 58 00 66",
    "sg:postcode":"21670",
    "sg:province":"Huelva",
    "wof:name":"Lucas Cumplido Jose",
    "wof:placetype":"venue"
},
  "geometry": {"coordinates":[-6.5451955795,37.6920661926],"type":"Point"}
}