{
  "type": "Feature",
  "properties": {
    "addr:full":"Ctra Almensilla, Km. 0004,7 Mairena Aljarafe Sevilla 41927",
    "addr:postcode":"41927",
    "addr:street":"Ctra Almensilla Km. 0004,7",
    "iso:country":"ES",
    "sg:address":"Ctra Almensilla, Km. 0004,7",
    "sg:city":"Mairena Aljarafe",
    "sg:orig_category":"Mec\u00c1nico Del Autom\u00d3vil",
    "sg:phone":"+34 955 76 83 13",
    "sg:postcode":"41927",
    "sg:province":"Sevilla",
    "wof:name":"Soluciones Del Automovil S.c.",
    "wof:placetype":"venue"
},
  "geometry": {"coordinates":[-6.0626192093,37.3473587036],"type":"Point"}
}