{
  "type": "Feature",
  "properties": {
    "addr:full":"Plaz Abajo De, 2 Pola De Allande Asturias 33880",
    "addr:postcode":"33880",
    "iso:country":"ES",
    "sg:address":"Plaz Abajo De, 2",
    "sg:city":"Pola De Allande",
    "sg:orig_category":"Quincaller\u00cda (al Por Menor)",
    "sg:phone":"+34 985 80 70 70",
    "sg:postcode":"33880",
    "sg:province":"Asturias",
    "wof:name":"Magadan Gonzalez Marcelino",
    "wof:placetype":"venue"
},
  "geometry": {"coordinates":[-6.6110310555,43.2716369629],"type":"Point"}
}