{
  "type": "Feature",
  "properties": {
    "iso:country":"ES",
    "sg:address":"Calle de Nagusia, 9",
    "sg:city":"Basauri",
    "sg:orig_category":"M\u00c1quinas De Escribir, M\u00c1quinas De Oficina (al Por Menor, Reparaci\u00d3n)",
    "sg:phone":"+34 944 49 99 92",
    "sg:postcode":"48970",
    "sg:province":"Vizcaya",
    "wof:name":"Marcos Gandiaga Orue-rementeria",
    "wof:placetype":"venue"
},
  "geometry": {"coordinates":[-2.8863260746,43.2362518311],"type":"Point"}
}