{
  "type": "Feature",
  "properties": {
    "addr:full":"Calle de Buganvilla, 429 San Agustin Las Palmas 35100",
    "addr:housenumber":"429",
    "addr:postcode":"35100",
    "addr:street":"Calle De Buganvilla;Agustin Las",
    "iso:country":"ES",
    "sg:address":"Calle de Buganvilla, 429",
    "sg:city":"San Agustin",
    "sg:orig_category":"Cl\u00cdnicas M\u00c9dicas",
    "sg:phone":"+34 928 76 78 66",
    "sg:postcode":"35100",
    "sg:province":"Las Palmas",
    "wof:name":"Svenska Re Aktiebolag Sucursal En Espa\u00f1a",
    "wof:placetype":"venue"
},
  "geometry": {"coordinates":[-15.5436420441,27.7725048065],"type":"Point"}
}