{
  "type": "Feature",
  "properties": {
    "iso:country":"ES",
    "sg:address":"Calle de Ramon Y Cajal, 2",
    "sg:city":"Torrent",
    "sg:orig_category":"M\u00c9dicos: Ginecolog\u00cda Y Obstetricia",
    "sg:phone":"+34 961 55 33 52",
    "sg:postcode":"46900",
    "sg:province":"Valencia",
    "wof:name":"Puig Miquel Serafin",
    "wof:placetype":"venue"
},
  "geometry": {"coordinates":[-0.4662989974,39.4371185303],"type":"Point"}
}