{
  "type": "Feature",
  "properties": {
    "addr:full":"Calle de Barratxi, 12 Vitoria-gasteiz \u00c1lava 01013",
    "addr:housenumber":"12",
    "addr:postcode":"01013",
    "addr:street":"Calle De Barratxi",
    "iso:country":"ES",
    "sg:address":"Calle de Barratxi, 12",
    "sg:city":"Vitoria-gasteiz",
    "sg:orig_category":"Artes Gr\u00c1ficas, Artes Pl\u00c1sticas (curso)",
    "sg:phone":"+34 945 06 32 07",
    "sg:postcode":"01013",
    "sg:province":"\u00c1lava",
    "wof:name":"Artes Graficas E Impresion Stampa  S.l.u",
    "wof:placetype":"venue"
},
  "geometry": {"coordinates":[-2.6516582966,42.8725662231],"type":"Point"}
}