{
  "type": "Feature",
  "properties": {
    "iso:country":"ES",
    "sg:address":"Carr Mendez Nu\u00d1ez, 21",
    "sg:city":"Figueres",
    "sg:orig_category":"Fabricaci\u00d3n, Distribuci\u00d3n De Material Para La Climatizaci\u00d3n, Aireaci\u00d3n Y Ventilaci\u00d3n",
    "sg:phone":"+34 972 67 38 87",
    "sg:postcode":"17600",
    "sg:province":"Girona",
    "wof:name":"Tikal Serveis A T S.l.",
    "wof:placetype":"venue"
},
  "geometry": {"coordinates":[2.9662649632,42.2644996643],"type":"Point"}
}