{
  "type": "Feature",
  "properties": {
    "addr:full":"Carrer de La Vila, 17 Xixona Alicante 03100",
    "addr:housenumber":"17",
    "addr:postcode":"03100",
    "addr:street":"Carrer De La Vila",
    "iso:country":"ES",
    "sg:address":"Carrer de La Vila, 17",
    "sg:city":"Xixona",
    "sg:orig_category":"Peluquer\u00cdas, Peluquer\u00cda Mixta",
    "sg:phone":"+34 965 61 32 79",
    "sg:postcode":"03100",
    "sg:province":"Alicante",
    "wof:name":"Martinez Gazquez Isabel",
    "wof:placetype":"venue"
},
  "geometry": {"coordinates":[-0.507604003,38.5389213562],"type":"Point"}
}