{
  "type": "Feature",
  "properties": {
    "iso:country":"ES",
    "sg:address":"Calle de Eugenio Salazar, 4",
    "sg:city":"Madrid",
    "sg:orig_category":"Asociaciones Y Clubs Deportivos",
    "sg:phone":"+34 914 15 12 46",
    "sg:postcode":"28002",
    "sg:province":"Madrid",
    "sg:website":"www.manuelmanchado.com",
    "wof:name":"Usa Profitness S.l.",
    "wof:placetype":"venue"
},
  "geometry": {"coordinates":[-3.673017025,40.4446487427],"type":"Point"}
}