{
  "type": "Feature",
  "properties": {
    "addr:full":"Avda Vicenta Ruano, S/n Aguilas Murcia 30880",
    "addr:housenumber":"s / n",
    "addr:postcode":"30880",
    "addr:street":"Avda Vicenta Ruano",
    "iso:country":"ES",
    "sg:address":"Avda Vicenta Ruano, S/n",
    "sg:city":"Aguilas",
    "sg:orig_category":"Cooperativas Agr\u00cdcolas",
    "sg:phone":"+34 968 44 86 31",
    "sg:postcode":"30880",
    "sg:province":"Murcia",
    "wof:name":"Sociedad Cooperativa Limitada Del Campo De Aguilas",
    "wof:placetype":"venue"
},
  "geometry": {"coordinates":[-1.5872089863,37.412853241],"type":"Point"}
}