{
  "type": "Feature",
  "properties": {
    "iso:country":"ES",
    "sg:address":"Calle de Bego\u00d1a, 18",
    "sg:city":"Coslada",
    "sg:orig_category":"Venta, Colocaci\u00d3n, Reparaci\u00d3n De Parabrisas, Techos Descapotables",
    "sg:phone":"+34 916 69 95 80",
    "sg:postcode":"28820",
    "sg:province":"Madrid",
    "wof:name":"Cean Vidriocar S.l.",
    "wof:placetype":"venue"
},
  "geometry": {"coordinates":[-3.5681219101,40.425655365],"type":"Point"}
}