{
  "type": "Feature",
  "properties": {
    "addr:full":"Cmno Viejo De Galvez, S/n Polan Toledo 45161",
    "addr:housenumber":"s",
    "addr:postcode":"45161",
    "addr:street":"Cmno Viejo De Galvez;/ N",
    "iso:country":"ES",
    "sg:address":"Cmno Viejo De Galvez, S/n",
    "sg:city":"Polan",
    "sg:orig_category":"Organizaciones Profesionales",
    "sg:phone":"+34 925 29 01 52",
    "sg:postcode":"45161",
    "sg:province":"Toledo",
    "wof:name":"Garcia Garcia Raquel",
    "wof:placetype":"venue"
},
  "geometry": {"coordinates":[-4.1735191345,39.786151886],"type":"Point"}
}