{
  "type": "Feature",
  "properties": {
    "addr:full":"Ctra N-340, Km. 0130,1 Pe\u00f1iscola Castell\u00f3n 12598",
    "addr:postcode":"12598",
    "addr:street":"Ctra N-340 Km. 0130,1 Pen\u0303Iscola Castello\u0301N",
    "iso:country":"ES",
    "sg:address":"Ctra N-340, Km. 0130,1",
    "sg:city":"Pe\u00f1iscola",
    "sg:orig_category":"Semiller\u00cdas",
    "sg:phone":"+34 964 48 93 54",
    "sg:postcode":"12598",
    "sg:province":"Castell\u00f3n",
    "wof:name":"Beniplant S.l.",
    "wof:placetype":"venue"
},
  "geometry": {"coordinates":[-0.0456800014,39.9851417542],"type":"Point"}
}