{
  "type": "Feature",
  "properties": {
    "iso:country":"ES",
    "sg:address":"Plaz Mayor, 14",
    "sg:city":"Madrid",
    "sg:orig_category":"Molduras, Junquillos, Listones Y Molduras Perforadas",
    "sg:phone":"+34 913 66 45 97",
    "sg:postcode":"28012",
    "sg:province":"Madrid",
    "wof:name":"Garcia Garcia Mariano",
    "wof:placetype":"venue"
},
  "geometry": {"coordinates":[-3.7067389488,40.4157295227],"type":"Point"}
}