{
  "type": "Feature",
  "properties": {
    "addr:full":"Carrer de Independencia, 16 Deltebre Tarragona 43580",
    "addr:housenumber":"16",
    "addr:postcode":"43580",
    "addr:street":"Carrer De Independencia",
    "iso:country":"ES",
    "sg:address":"Carrer de Independencia, 16",
    "sg:city":"Deltebre",
    "sg:orig_category":"Promotores Constructores",
    "sg:phone":"+34 977 48 01 29",
    "sg:postcode":"43580",
    "sg:province":"Tarragona",
    "wof:name":"Construcciones Bertomeu Iglesias S.l.",
    "wof:placetype":"venue"
},
  "geometry": {"coordinates":[0.7334610224,40.7183837891],"type":"Point"}
}