{
  "type": "Feature",
  "properties": {
    "addr:full":"Calle de Corrales, S/n Morales Vino Zamora 49190",
    "addr:housenumber":"s",
    "addr:postcode":"49190",
    "addr:street":"Calle De Corrales;/ N Morales Vino Zamora",
    "iso:country":"ES",
    "sg:address":"Calle de Corrales, S/n",
    "sg:city":"Morales Vino",
    "sg:orig_category":"M\u00c9dicos: An\u00c1lisis Cl\u00cdnicos",
    "sg:phone":"+34 980 57 00 67",
    "sg:postcode":"49190",
    "sg:province":"Zamora",
    "wof:name":"Casta\u00f1o Casanueva Fernando",
    "wof:placetype":"venue"
},
  "geometry": {"coordinates":[-5.7310290337,41.4447021484],"type":"Point"}
}