{
  "type": "Feature",
  "properties": {
    "addr:full":"Carrer de Havana (l'), 64 Deltebre Tarragona 43580",
    "addr:housenumber":"64",
    "addr:postcode":"43580",
    "addr:street":"Carrer De Havana L '",
    "iso:country":"ES",
    "sg:address":"Carrer de Havana (l'), 64",
    "sg:city":"Deltebre",
    "sg:orig_category":"Promotores Constructores",
    "sg:phone":"+34 977 48 13 77",
    "sg:postcode":"43580",
    "sg:province":"Tarragona",
    "wof:name":"Construcions I Facanes Garpide S.l",
    "wof:placetype":"venue"
},
  "geometry": {"coordinates":[0.7353829741,40.7154541016],"type":"Point"}
}