{
  "type": "Feature",
  "properties": {
    "addr:full":"Bo El Baden, 73 Rafal Alicante 03369",
    "addr:housenumber":"73",
    "addr:postcode":"03369",
    "iso:country":"ES",
    "sg:address":"Bo El Baden, 73",
    "sg:city":"Rafal",
    "sg:orig_category":"Mantenimiento Industrial",
    "sg:phone":"+34 966 75 30 40",
    "sg:postcode":"03369",
    "sg:province":"Alicante",
    "wof:name":"Electromecanica Los Albertos S.l.",
    "wof:placetype":"venue"
},
  "geometry": {"coordinates":[-0.8504530191,38.1058616638],"type":"Point"}
}