{
  "type": "Feature",
  "properties": {
    "addr:full":"Avda Aragon, 21 Binefar Huesca 22500",
    "addr:housenumber":"21",
    "addr:postcode":"22500",
    "addr:street":"Avda Aragon",
    "iso:country":"ES",
    "sg:address":"Avda Aragon, 21",
    "sg:city":"Binefar",
    "sg:orig_category":"Doctores En Medicina",
    "sg:phone":"+34 974 43 11 82",
    "sg:postcode":"22500",
    "sg:province":"Huesca",
    "wof:name":"Mu\u00f1oz Gallego Dolores",
    "wof:placetype":"venue"
},
  "geometry": {"coordinates":[0.2939130068,41.8511314392],"type":"Point"}
}