{
  "type": "Feature",
  "properties": {
    "iso:country":"ES",
    "sg:address":"Calle de Prado Tito (del), 30",
    "sg:city":"Colmenar Viejo",
    "sg:orig_category":"Garajes De Veh\u00cdculos",
    "sg:phone":"+34 918 46 27 08",
    "sg:postcode":"28770",
    "sg:province":"Madrid",
    "wof:name":"Inyecsal S.l.",
    "wof:placetype":"venue"
},
  "geometry": {"coordinates":[-3.7596580982,40.6595687866],"type":"Point"}
}