{
  "type": "Feature",
  "properties": {
    "addr:full":"Cefontes, S/n Cabue\u00f1es Asturias 33394",
    "addr:postcode":"33394",
    "addr:street":"Cefontes S / N Cabuen\u0303Es Asturias",
    "iso:country":"ES",
    "sg:address":"Cefontes, S/n",
    "sg:city":"Cabue\u00f1es",
    "sg:orig_category":"Producci\u00d3n De Sidra",
    "sg:phone":"+34 985 33 28 87",
    "sg:postcode":"33394",
    "sg:province":"Asturias",
    "wof:name":"Champanera Villaviciosa S. A.",
    "wof:placetype":"venue"
},
  "geometry": {"coordinates":[-5.7123498917,43.5202293396],"type":"Point"}
}