{
  "type": "Feature",
  "properties": {
    "iso:country":"ES",
    "sg:address":"Calle de Alonso Carrillo De Albornoz, 2",
    "sg:city":"Malaga",
    "sg:classifiers":[
        {
            "category":"Professional",
            "subcategory":"Management & Consulting",
            "type":"Services"
        }
    ],
    "sg:phone":"+34 952 20 28 00",
    "sg:postcode":"29017",
    "sg:province":"M\u00e1laga",
    "sg:tags":[
        "asesor\u00cda",
        "en",
        "marketing"
    ],
    "wof:name":"Solano Sanchez Sara",
    "wof:placetype":"venue"
},
  "geometry": {"coordinates":[-4.3608832359,36.7209091187],"type":"Point"}
}