{
  "type": "Feature",
  "properties": {
    "iso:country":"ES",
    "sg:address":"Calle de Grabador Esteve, 18",
    "sg:city":"Valencia",
    "sg:orig_category":"M\u00c9dicos: Gastroenterolog\u00cda Y Hepatolog\u00cda (aparato Digestivo)",
    "sg:phone":"+34 963 52 47 49",
    "sg:postcode":"46004",
    "sg:province":"Valencia",
    "wof:name":"Tatay Romero Juan",
    "wof:placetype":"venue"
},
  "geometry": {"coordinates":[-0.3674989939,39.4705314636],"type":"Point"}
}