{
  "type": "Feature",
  "properties": {
    "addr:full":"Calle de Jose Maria Martinez Sanchez Arjona, 50 Sevilla Sevilla 41010",
    "addr:housenumber":"50",
    "addr:postcode":"41010",
    "addr:street":"Calle De Jose Maria Martinez;Arjona",
    "iso:country":"ES",
    "sg:address":"Calle de Jose Maria Martinez Sanchez Arjona, 50",
    "sg:city":"Sevilla",
    "sg:orig_category":"Carnicer\u00cdas, Carnicer\u00cdas",
    "sg:phone":"+34 954 28 42 00",
    "sg:postcode":"41010",
    "sg:province":"Sevilla",
    "wof:name":"Valle De Orosierra S.a.",
    "wof:placetype":"venue"
},
  "geometry": {"coordinates":[-6.002904892,37.3782615662],"type":"Point"}
}