{
  "type": "Feature",
  "properties": {
    "addr:full":"Av Catalunya, 16 S. Cugat Valles Barcelona 08172",
    "addr:housenumber":"16",
    "addr:postcode":"08172",
    "addr:street":"Av Catalunya;S. Cugat Valles Barcelona",
    "iso:country":"ES",
    "sg:address":"Av Catalunya, 16",
    "sg:city":"S. Cugat Valles",
    "sg:orig_category":"Cajas De Ahorro",
    "sg:phone":"+34 935 87 93 91",
    "sg:postcode":"08172",
    "sg:province":"Barcelona",
    "wof:name":"Caixa D'estalvis De Manresa",
    "wof:placetype":"venue"
},
  "geometry": {"coordinates":[2.0806820393,41.4728012085],"type":"Point"}
}