{
  "type": "Feature",
  "properties": {
    "addr:full":"Calle de Panama, 6 Toledo Toledo 45004",
    "addr:housenumber":"6",
    "addr:postcode":"45004",
    "addr:street":"Calle De Panama",
    "iso:country":"ES",
    "sg:address":"Calle de Panama, 6",
    "sg:city":"Toledo",
    "sg:orig_category":"Carnicer\u00cdas, Carnicer\u00cdas",
    "sg:phone":"+34 925 25 08 74",
    "sg:postcode":"45004",
    "sg:province":"Toledo",
    "wof:name":"Gourmet El Racimo S.l.",
    "wof:placetype":"venue"
},
  "geometry": {"coordinates":[-4.033908844,39.8694000244],"type":"Point"}
}