{
  "type": "Feature",
  "properties": {
    "iso:country":"ES",
    "sg:address":"Av Montesierra (p I Ctra Amarilla), 28",
    "sg:city":"Sevilla",
    "sg:orig_category":"Organismos Y Centros De Vacaciones Y Esparcimiento Para Ni\u00d1os Y Adolescentes",
    "sg:phone":"+34 954 52 90 19",
    "sg:postcode":"41007",
    "sg:province":"Sevilla",
    "sg:website":"www.indianabill.com",
    "wof:name":"Diverindi Sociedad Limitada Unipersonal",
    "wof:placetype":"venue"
},
  "geometry": {"coordinates":[-5.9487810135,37.3958396912],"type":"Point"}
}