{
  "type": "Feature",
  "properties": {
    "addr:full":"Carrer de Montserrat, 26 Vic Barcelona 08500",
    "addr:housenumber":"26",
    "addr:postcode":"08500",
    "addr:street":"Carrer De Montserrat",
    "iso:country":"ES",
    "sg:address":"Carrer de Montserrat, 26",
    "sg:city":"Vic",
    "sg:orig_category":"Cr\u00cda De Animales",
    "sg:phone":"+34 938 86 07 08",
    "sg:postcode":"08500",
    "sg:province":"Barcelona",
    "wof:name":"Noguera S.l.",
    "wof:placetype":"venue"
},
  "geometry": {"coordinates":[2.2622079849,41.9284057617],"type":"Point"}
}