{
  "type": "Feature",
  "properties": {
    "addr:full":"Carr Cronista Muntaner, 21 Lleida Lleida 25001",
    "addr:housenumber":"21",
    "addr:postcode":"25001",
    "addr:street":"Carr Cronista Muntaner",
    "iso:country":"ES",
    "sg:address":"Carr Cronista Muntaner, 21",
    "sg:city":"Lleida",
    "sg:orig_category":"Empresas De Desmonte",
    "sg:phone":"+34 973 21 16 71",
    "sg:postcode":"25001",
    "sg:province":"Lleida",
    "wof:name":"Excavacines Y Solidos Para Aridos S.a.",
    "wof:placetype":"venue"
},
  "geometry": {"coordinates":[0.6344010234,41.6110649109],"type":"Point"}
}