{
  "type": "Feature",
  "properties": {
    "addr:full":"Calle de Castilla, 40 Malaga M\u00e1laga 29007",
    "addr:housenumber":"40",
    "addr:postcode":"29007",
    "addr:street":"Calle De Castilla;Ma\u0301Laga",
    "iso:country":"ES",
    "sg:address":"Calle de Castilla, 40",
    "sg:city":"Malaga",
    "sg:orig_category":"Inmobiliaria (agencias)",
    "sg:phone":"+34 952 28 03 28",
    "sg:postcode":"29007",
    "sg:province":"M\u00e1laga",
    "sg:website":"www.tecnocasa.es",
    "wof:name":"Estudio Alameda 2004 S.l.",
    "wof:placetype":"venue"
},
  "geometry": {"coordinates":[-4.4543237686,36.7203903198],"type":"Point"}
}