{
  "type": "Feature",
  "properties": {
    "addr:full":"Rua Bedoya, 10 Ourense Ourense 32004",
    "addr:housenumber":"10",
    "addr:postcode":"32004",
    "addr:street":"Rua Bedoya",
    "iso:country":"ES",
    "sg:address":"Rua Bedoya, 10",
    "sg:city":"Ourense",
    "sg:orig_category":"Agencias Y Agentes Comerciales, Representantes",
    "sg:phone":"+34 988 24 88 94",
    "sg:postcode":"32004",
    "sg:province":"Ourense",
    "wof:name":"Castellanos Alvarez Miguel",
    "wof:placetype":"venue"
},
  "geometry": {"coordinates":[-7.861779213,42.3401451111],"type":"Point"}
}