{
  "type": "Feature",
  "properties": {
    "addr:full":"Calle de Maestro Caballero, 43 Alacant Alicante 03009",
    "addr:housenumber":"43",
    "addr:postcode":"03009",
    "addr:street":"Calle De Maestro Caballero",
    "iso:country":"ES",
    "sg:address":"Calle de Maestro Caballero, 43",
    "sg:city":"Alacant",
    "sg:orig_category":"Ingenier\u00cda, Centros De Estudios (diversos)",
    "sg:phone":"+34 965 25 90 89",
    "sg:postcode":"03009",
    "sg:province":"Alicante",
    "wof:name":"Saadeh Altalli Souheil",
    "wof:placetype":"venue"
},
  "geometry": {"coordinates":[-0.487955004,38.3536376953],"type":"Point"}
}