{
  "type": "Feature",
  "properties": {
    "addr:full":"Calle de San Prudencio, 27 Vitoria-gasteiz \u00c1lava 01005",
    "addr:housenumber":"27",
    "addr:postcode":"01005",
    "addr:street":"Calle De San Prudencio",
    "iso:country":"ES",
    "sg:address":"Calle de San Prudencio, 27",
    "sg:city":"Vitoria-gasteiz",
    "sg:orig_category":"Inmobiliaria (agencias)",
    "sg:phone":"+34 945 23 01 00",
    "sg:postcode":"01005",
    "sg:province":"\u00c1lava",
    "wof:name":"Aberasturi Lauzurika Fernando",
    "wof:placetype":"venue"
},
  "geometry": {"coordinates":[-2.670882,42.843925],"type":"Point"}
}