{
  "type": "Feature",
  "properties": {
    "addr:full":"Calle de Virgen Del Pilar, 4 Marbella M\u00e1laga 29600",
    "addr:housenumber":"4",
    "addr:postcode":"29600",
    "addr:street":"Calle De Virgen Del Pilar;Ma\u0301Laga",
    "iso:country":"ES",
    "sg:address":"Calle de Virgen Del Pilar, 4",
    "sg:city":"Marbella",
    "sg:orig_category":"Artes Gr\u00c1ficas, Artes Pl\u00c1sticas (curso)",
    "sg:phone":"+34 952 82 67 60",
    "sg:postcode":"29600",
    "sg:province":"M\u00e1laga",
    "wof:name":"Arevilo Espa\u00f1a S.l.",
    "wof:placetype":"venue"
},
  "geometry": {"coordinates":[-4.8904013634,36.5088996887],"type":"Point"}
}