{
  "type": "Feature",
  "properties": {
    "iso:country":"ES",
    "sg:address":"Calle de Fraguas, S/n",
    "sg:city":"Perilla Castro",
    "sg:orig_category":"Centros De Educaci\u00d3n Especial",
    "sg:phone":"+34 980 59 55 04",
    "sg:postcode":"49145",
    "sg:province":"Zamora",
    "wof:name":"Colegio Rural Agrupado De Tabara",
    "wof:placetype":"venue"
},
  "geometry": {"coordinates":[-5.8760509491,41.7246398926],"type":"Point"}
}