{
  "type": "Feature",
  "properties": {
    "iso:country":"ES",
    "sg:address":"Carrer de Berenguer Iii, 1",
    "sg:city":"Mollet Valles",
    "sg:orig_category":"Transportes Por Carretera: Lotes Completos, Mercanc\u00cdas Diversas",
    "sg:phone":"+34 935 93 01 30",
    "sg:postcode":"08100",
    "sg:province":"Barcelona",
    "wof:name":"Rebull Isern Jordi",
    "wof:placetype":"venue"
},
  "geometry": {"coordinates":[2.2118999958,41.5376548767],"type":"Point"}
}