{
  "type": "Feature",
  "properties": {
    "iso:country":"ES",
    "sg:address":"Av. Pais Valencia, 14",
    "sg:city":"Sedavi",
    "sg:orig_category":"Aguas (distribuci\u00d3n, Servicios)",
    "sg:phone":"+34 963 18 61 47",
    "sg:postcode":"46910",
    "sg:province":"Valencia",
    "wof:name":"Puragua Levante Osmosis Y Descalcificacion S.c.p.",
    "wof:placetype":"venue"
},
  "geometry": {"coordinates":[-0.3770369887,39.4245796204],"type":"Point"}
}