{
  "type": "Feature",
  "properties": {
    "addr:full":"Calle de Cabecico, S/n Caravaca Cruz Murcia 30400",
    "addr:housenumber":"s",
    "addr:postcode":"30400",
    "addr:street":"Calle De Cabecico;/ N Caravaca Cruz",
    "iso:country":"ES",
    "sg:address":"Calle de Cabecico, S/n",
    "sg:city":"Caravaca Cruz",
    "sg:orig_category":"Agencias Y Agentes Comerciales, Representantes",
    "sg:phone":"+34 968 70 30 30",
    "sg:postcode":"30400",
    "sg:province":"Murcia",
    "wof:name":"Hijos De Francisco Lorencio S.l.",
    "wof:placetype":"venue"
},
  "geometry": {"coordinates":[-1.864151001,38.100982666],"type":"Point"}
}