{
  "type": "Feature",
  "properties": {
    "addr:full":"Calle de San Antonio, 11 S. Pedro Pinatar Murcia 30740",
    "addr:housenumber":"11",
    "addr:postcode":"30740",
    "addr:street":"Calle De San Antonio;S. Pedro",
    "iso:country":"ES",
    "sg:address":"Calle de San Antonio, 11",
    "sg:city":"S. Pedro Pinatar",
    "sg:orig_category":"Panader\u00cdas, Panader\u00cdas",
    "sg:phone":"+34 968 17 82 96",
    "sg:postcode":"30740",
    "sg:province":"Murcia",
    "wof:name":"Hermanos Miralles C.b.",
    "wof:placetype":"venue"
},
  "geometry": {"coordinates":[-0.7905709743,37.8345031738],"type":"Point"}
}