{
  "type": "Feature",
  "properties": {
    "addr:full":"Calle de Feria Jerez, 6 Fuengirola M\u00e1laga 29640",
    "addr:housenumber":"6",
    "addr:postcode":"29640",
    "addr:street":"Calle De;Jerez;Ma\u0301Laga",
    "iso:country":"ES",
    "sg:address":"Calle de Feria Jerez, 6",
    "sg:city":"Fuengirola",
    "sg:orig_category":"Molduras, Junquillos, Listones Y Molduras Perforadas",
    "sg:phone":"+34 952 66 45 19",
    "sg:postcode":"29640",
    "sg:province":"M\u00e1laga",
    "wof:name":"Gonzalez Verdugo Antonio",
    "wof:placetype":"venue"
},
  "geometry": {"coordinates":[-4.6216592789,36.547832489],"type":"Point"}
}