{
  "type": "Feature",
  "properties": {
    "addr:full":"Barranco Nogales, 16 Jun Granada 18213",
    "addr:housenumber":"16",
    "addr:postcode":"18213",
    "addr:street":"Nogales",
    "iso:country":"ES",
    "sg:address":"Barranco Nogales, 16",
    "sg:city":"Jun",
    "sg:orig_category":"Sales (al Por Mayor)",
    "sg:phone":"+34 958 41 42 27",
    "sg:postcode":"18213",
    "sg:province":"Granada",
    "wof:name":"Aceitunas Granada S.l",
    "wof:placetype":"venue"
},
  "geometry": {"coordinates":[-3.5888626575,37.2189445496],"type":"Point"}
}