{
  "type": "Feature",
  "properties": {
    "addr:full":"Calle de Torremocha, 1 Sevilla Sevilla 41016",
    "addr:housenumber":"1",
    "addr:postcode":"41016",
    "addr:street":"Calle De Torremocha",
    "iso:country":"ES",
    "sg:address":"Calle de Torremocha, 1",
    "sg:city":"Sevilla",
    "sg:orig_category":"Cl\u00cdnicas M\u00c9dicas",
    "sg:phone":"+34 954 40 55 44",
    "sg:postcode":"41016",
    "sg:province":"Sevilla",
    "wof:name":"Montoro Duran-loriga Juan",
    "wof:placetype":"venue"
},
  "geometry": {"coordinates":[-5.904006958,37.3821678162],"type":"Point"}
}