{
  "type": "Feature",
  "properties": {
    "iso:country":"ES",
    "sg:address":"Barr Peruri, 33",
    "sg:city":"Peruri",
    "sg:orig_category":"Asesor\u00cda Sobre Comunicaci\u00d3n De Empresas",
    "sg:phone":"+34 944 60 79 23",
    "sg:postcode":"48940",
    "sg:province":"Vizcaya",
    "wof:name":"Tuv Internacional Grupo Tuv Rheinland S.l.",
    "wof:placetype":"venue"
},
  "geometry": {"coordinates":[-2.9860789776,43.3275489807],"type":"Point"}
}