{
  "type": "Feature",
  "properties": {
    "iso:country":"ES",
    "sg:address":"Calle de Tomillera (la), S/n",
    "sg:city":"Alcaudique",
    "sg:orig_category":"Producci\u00d3n, Venta De Productos De Agricultura Biol\u00d3gica",
    "sg:phone":"+34 950 49 25 31",
    "sg:postcode":"04760",
    "sg:province":"Almer\u00eda",
    "wof:name":"Hortocampo S. A.",
    "wof:placetype":"venue"
},
  "geometry": {"coordinates":[-2.9501290321,36.8471107483],"type":"Point"}
}