{
  "type": "Feature",
  "properties": {
    "iso:country":"ES",
    "sg:address":"Ctra Coin, 76",
    "sg:city":"Cortijo De Maza-el Olivar",
    "sg:orig_category":"Transportes Por Carretera: Lotes Completos, Mercanc\u00cdas Diversas",
    "sg:phone":"+34 952 43 51 39",
    "sg:postcode":"29140",
    "sg:province":"M\u00e1laga",
    "wof:name":"Clamador 2000 S.l.",
    "wof:placetype":"venue"
},
  "geometry": {"coordinates":[-4.5044879913,36.6618270874],"type":"Point"}
}