{
  "type": "Feature",
  "properties": {
    "addr:full":"Carrer de Sant Pere, 24 Terrassa Barcelona 08221",
    "addr:housenumber":"24",
    "addr:postcode":"08221",
    "addr:street":"Carrer De Sant Pere",
    "iso:country":"ES",
    "sg:address":"Carrer de Sant Pere, 24",
    "sg:city":"Terrassa",
    "sg:orig_category":"Zapatos (al Por Menor)",
    "sg:phone":"+34 937 83 03 48",
    "sg:postcode":"08221",
    "sg:province":"Barcelona",
    "wof:name":"Calzados Lamolla S. A.",
    "wof:placetype":"venue"
},
  "geometry": {"coordinates":[2.0115671158,41.5635871887],"type":"Point"}
}