{
  "type": "Feature",
  "properties": {
    "iso:country":"ES",
    "sg:address":"Calle de Comuneros De Castilla, 3",
    "sg:city":"Mocejon",
    "sg:orig_category":"Limpieza Con Chorro De Arena Y Con Granalla, Pulido",
    "sg:phone":"+34 925 36 05 88",
    "sg:postcode":"45270",
    "sg:province":"Toledo",
    "wof:name":"Ruano Lopez Luis",
    "wof:placetype":"venue"
},
  "geometry": {"coordinates":[-3.9162313938,39.9379730225],"type":"Point"}
}