{
  "type": "Feature",
  "properties": {
    "addr:full":"Trav De Gracia, 187 Barcelona Barcelona 08012",
    "addr:housenumber":"187",
    "addr:postcode":"08012",
    "addr:street":"Trav De Gracia",
    "iso:country":"ES",
    "sg:address":"Trav De Gracia, 187",
    "sg:city":"Barcelona",
    "sg:orig_category":"Fabricaci\u00d3n De Acumuladores Y De Pilas El\u00c9ctricas",
    "sg:phone":"+34 932 13 61 64",
    "sg:postcode":"08012",
    "sg:province":"Barcelona",
    "wof:name":"Solanelles Traveset Rosa Maria",
    "wof:placetype":"venue"
},
  "geometry": {"coordinates":[2.1591091156,41.4023208618],"type":"Point"}
}