{
  "type": "Feature",
  "properties": {
    "addr:full":"Carrer de Montflorit, 17 Gava Barcelona 08850",
    "addr:housenumber":"17",
    "addr:postcode":"08850",
    "addr:street":"Carrer De Montflorit",
    "iso:country":"ES",
    "sg:address":"Carrer de Montflorit, 17",
    "sg:city":"Gava",
    "sg:orig_category":"Reposter\u00cdas",
    "sg:phone":"+34 936 62 01 68",
    "sg:postcode":"08850",
    "sg:province":"Barcelona",
    "wof:name":"Forn M. Cruz S. L.",
    "wof:placetype":"venue"
},
  "geometry": {"coordinates":[2.001871109,41.299659729],"type":"Point"}
}