{
  "type": "Feature",
  "properties": {
    "iso:country":"ES",
    "sg:address":"Cmno Rico, 29",
    "sg:city":"Aspe",
    "sg:orig_category":"Confecci\u00d3n De Zapatos",
    "sg:phone":"+34 965 49 60 36",
    "sg:postcode":"03680",
    "sg:province":"Alicante",
    "wof:name":"Cactus S.l.u.",
    "wof:placetype":"venue"
},
  "geometry": {"coordinates":[-0.7689840198,38.3471984863],"type":"Point"}
}