{
  "type": "Feature",
  "properties": {
    "addr:full":"Avda Perez Galdos, 104 Valencia Valencia 46008",
    "addr:housenumber":"104",
    "addr:postcode":"46008",
    "addr:street":"Avda Perez Galdos",
    "iso:country":"ES",
    "sg:address":"Avda Perez Galdos, 104",
    "sg:city":"Valencia",
    "sg:orig_category":"Alquiler De V\u00cddeo",
    "sg:phone":"+34 963 85 33 45",
    "sg:postcode":"46008",
    "sg:province":"Valencia",
    "wof:name":"Teris Monzo Miguel Angel",
    "wof:placetype":"venue"
},
  "geometry": {"coordinates":[-0.3920690119,39.4699516296],"type":"Point"}
}