{
  "type": "Feature",
  "properties": {
    "iso:country":"ES",
    "sg:address":"Sect Islas, 12",
    "sg:city":"Tres Cantos",
    "sg:orig_category":"Empresas De Desmonte",
    "sg:phone":"+34 918 04 36 69",
    "sg:postcode":"28760",
    "sg:province":"Madrid",
    "wof:name":"Excavaciones Y Transportes Tolteca S.a.",
    "wof:placetype":"venue"
},
  "geometry": {"coordinates":[-3.7012069225,40.5951423645],"type":"Point"}
}