{
  "type": "Feature",
  "properties": {
    "iso:country":"ES",
    "sg:address":"Carrer de Sants, 229",
    "sg:city":"Barcelona",
    "sg:orig_category":"Ropa Para Se\u00d1oras Y Caballeros (al Por Menor)",
    "sg:phone":"+34 933 30 05 73",
    "sg:postcode":"08028",
    "sg:province":"Barcelona",
    "wof:name":"Xianping  Xu",
    "wof:placetype":"venue"
},
  "geometry": {"coordinates":[2.1316719055,41.3753585815],"type":"Point"}
}