{
  "type": "Feature",
  "properties": {
    "addr:full":"Calle de San Juan, 25 Alhaurin Torre M\u00e1laga 29130",
    "addr:housenumber":"25",
    "addr:postcode":"29130",
    "addr:street":"Calle De San Juan",
    "iso:country":"ES",
    "sg:address":"Calle de San Juan, 25",
    "sg:city":"Alhaurin Torre",
    "sg:orig_category":"Herboristas (al Por Menor)",
    "sg:phone":"+34 952 41 45 74",
    "sg:postcode":"29130",
    "sg:province":"M\u00e1laga",
    "wof:name":"Barrales Prieto Juan Jose",
    "wof:placetype":"venue"
},
  "geometry": {"coordinates":[-4.5618839264,36.6618843079],"type":"Point"}
}