{
  "type": "Feature",
  "properties": {
    "addr:full":"Carrer de Comte De Rius, S/n Cornudella Montsant Tarragona 43360",
    "addr:housenumber":"s / n",
    "addr:postcode":"43360",
    "addr:street":"Carrer De Comte De Rius",
    "iso:country":"ES",
    "sg:address":"Carrer de Comte De Rius, S/n",
    "sg:city":"Cornudella Montsant",
    "sg:orig_category":"Fabricaci\u00d3n De Muebles",
    "sg:phone":"+34 977 82 10 29",
    "sg:postcode":"43360",
    "sg:province":"Tarragona",
    "wof:name":"Fusteria Pi\u00d1ol S.c.p.",
    "wof:placetype":"venue"
},
  "geometry": {"coordinates":[0.9042990208,41.2638397217],"type":"Point"}
}