{
  "type": "Feature",
  "properties": {
    "addr:full":"Avda Guadalajara, 29 Alcala Henares Madrid 28805",
    "addr:housenumber":"29",
    "addr:postcode":"28805",
    "addr:street":"Avda Guadalajara",
    "iso:country":"ES",
    "sg:address":"Avda Guadalajara, 29",
    "sg:city":"Alcala Henares",
    "sg:orig_category":"Distribuci\u00d3n De Petr\u00d3leo Y Derivados",
    "sg:phone":"+34 918 89 03 03",
    "sg:postcode":"28805",
    "sg:province":"Madrid",
    "wof:name":"Tres Columnas S.l.",
    "wof:placetype":"venue"
},
  "geometry": {"coordinates":[-3.3574049473,40.4878578186],"type":"Point"}
}