{
  "type": "Feature",
  "properties": {
    "addr:full":"Plaz Jose Ramon Aketxe, 5 Centro Civico Vizcaya 48940",
    "addr:housenumber":"5",
    "addr:postcode":"48940",
    "addr:street":"Jose Ramon Aketxe",
    "iso:country":"ES",
    "sg:address":"Plaz Jose Ramon Aketxe, 5",
    "sg:city":"Centro Civico",
    "sg:orig_category":"Bancos",
    "sg:phone":"+34 944 64 26 19",
    "sg:postcode":"48940",
    "sg:province":"Vizcaya",
    "wof:name":"Banco Popular Espa\u00f1ol S.a.",
    "wof:placetype":"venue"
},
  "geometry": {"coordinates":[-2.9860789776,43.3275489807],"type":"Point"}
}