{
  "type": "Feature",
  "properties": {
    "addr:full":"Calle de Puerto De La Morcuera, 10 Cotos De Monterrey Madrid 28729",
    "addr:housenumber":"10",
    "addr:postcode":"28729",
    "addr:street":"Calle De Puerto De La Morcuera",
    "iso:country":"ES",
    "sg:address":"Calle de Puerto De La Morcuera, 10",
    "sg:city":"Cotos De Monterrey",
    "sg:orig_category":"Centros Empresariales",
    "sg:phone":"+34 918 43 80 98",
    "sg:postcode":"28729",
    "sg:province":"Madrid",
    "wof:name":"S C M S.l.",
    "wof:placetype":"venue"
},
  "geometry": {"coordinates":[-3.6093149185,40.78956604],"type":"Point"}
}