{
  "type": "Feature",
  "properties": {
    "addr:full":"Carr President Macia, 17 Palamos Girona 17230",
    "addr:housenumber":"17",
    "addr:postcode":"17230",
    "addr:street":"Carr President Macia",
    "iso:country":"ES",
    "sg:address":"Carr President Macia, 17",
    "sg:city":"Palamos",
    "sg:orig_category":"Fabricaci\u00d3n De Cortinas Y Visillos",
    "sg:phone":"+34 972 60 15 65",
    "sg:postcode":"17230",
    "sg:province":"Girona",
    "wof:name":"Agell Palli Miquel",
    "wof:placetype":"venue"
},
  "geometry": {"coordinates":[3.1266534328,41.8486633301],"type":"Point"}
}