{
  "type": "Feature",
  "properties": {
    "iso:country":"ES",
    "sg:address":"Ctra Tarragona-san Sebastian, Km. 0131,2",
    "sg:city":"Binefar",
    "sg:orig_category":"Venta, Montaje De Neum\u00c1ticos",
    "sg:phone":"+34 974 42 91 96",
    "sg:postcode":"22500",
    "sg:province":"Huesca",
    "wof:name":"Rodi Tr S.l.",
    "wof:placetype":"venue"
},
  "geometry": {"coordinates":[0.2927800119,41.8499412537],"type":"Point"}
}