{
  "type": "Feature",
  "properties": {
    "addr:full":"Calle de Juan De Castilla, 5 Palencia Palencia 34001",
    "addr:housenumber":"5",
    "addr:postcode":"34001",
    "addr:street":"Calle De Juan De Castilla",
    "iso:country":"ES",
    "sg:address":"Calle de Juan De Castilla, 5",
    "sg:city":"Palencia",
    "sg:orig_category":"Lencer\u00cda Femenina, Corseter\u00cda, Trajes De Ba\u00d1o (al Por Menor)",
    "sg:phone":"+34 979 74 05 50",
    "sg:postcode":"34001",
    "sg:province":"Palencia",
    "wof:name":"Herran Luis Floreal",
    "wof:placetype":"venue"
},
  "geometry": {"coordinates":[-4.5352778435,42.0112838745],"type":"Point"}
}