{
  "type": "Feature",
  "properties": {
    "addr:full":"Carrer de Quatre, 13 Florida Barcelona 08130",
    "addr:housenumber":"13",
    "addr:postcode":"08130",
    "addr:street":"Carrer De Quatre",
    "iso:country":"ES",
    "sg:address":"Carrer de Quatre, 13",
    "sg:city":"Florida",
    "sg:orig_category":"Asilos De Ancianos. Centros Privados",
    "sg:phone":"+34 935 74 23 80",
    "sg:postcode":"08130",
    "sg:province":"Barcelona",
    "wof:name":"Molina Valle Francisco",
    "wof:placetype":"venue"
},
  "geometry": {"coordinates":[2.1919419765,41.5232200623],"type":"Point"}
}