{
  "type": "Feature",
  "properties": {
    "addr:full":"Calle de Mirador, 5 Benidorm Alicante 03500",
    "addr:housenumber":"5",
    "addr:postcode":"03500",
    "addr:street":"Calle De Mirador",
    "iso:country":"ES",
    "sg:address":"Calle de Mirador, 5",
    "sg:city":"Benidorm",
    "sg:orig_category":"Transporte En General",
    "sg:phone":"+34 965 86 83 61",
    "sg:postcode":"03500",
    "sg:province":"Alicante",
    "wof:name":"Valverde Abad Miguel",
    "wof:placetype":"venue"
},
  "geometry": {"coordinates":[-0.1267620027,38.540802002],"type":"Point"}
}