{
  "type": "Feature",
  "properties": {
    "iso:country":"ES",
    "sg:address":"Rua Nogueira, 8",
    "sg:city":"Vigo",
    "sg:orig_category":"Centros De Educaci\u00d3n Especial",
    "sg:phone":"+34 986 41 65 74",
    "sg:postcode":"36204",
    "sg:province":"Pontevedra",
    "wof:name":"Preescolar Couto El Nogal",
    "wof:placetype":"venue"
},
  "geometry": {"coordinates":[-8.7130012512,42.2264137268],"type":"Point"}
}