{
  "type": "Feature",
  "properties": {
    "iso:country":"ES",
    "sg:address":"Cno Hornillos, S/n",
    "sg:city":"Aldaia",
    "sg:orig_category":"Carb\u00d3n, Carb\u00d3n De Madera (al Por Mayor)",
    "sg:phone":"+34 961 50 50 45",
    "sg:postcode":"46960",
    "sg:province":"Valencia",
    "wof:name":"Carratala Gomez Juan",
    "wof:placetype":"venue"
},
  "geometry": {"coordinates":[-0.460878998,39.4649238586],"type":"Point"}
}