{
  "type": "Feature",
  "properties": {
    "addr:full":"Carrer de Sentmenat, 35 Sabadell Barcelona 08203",
    "addr:housenumber":"35",
    "addr:postcode":"08203",
    "addr:street":"Carrer De Sentmenat",
    "iso:country":"ES",
    "sg:address":"Carrer de Sentmenat, 35",
    "sg:city":"Sabadell",
    "sg:orig_category":"Imprenta",
    "sg:phone":"+34 937 27 14 24",
    "sg:postcode":"08203",
    "sg:province":"Barcelona",
    "wof:name":"Impresiones Troqueles Y Manipulaciones S.l.u.",
    "wof:placetype":"venue"
},
  "geometry": {"coordinates":[2.1185851097,41.542339325],"type":"Point"}
}