{
  "type": "Feature",
  "properties": {
    "addr:full":"Carrer de Bernat Metge, 33 Mollet Valles Barcelona 08100",
    "addr:housenumber":"33",
    "addr:postcode":"08100",
    "addr:street":"Carrer De Bernat Metge",
    "iso:country":"ES",
    "sg:address":"Carrer de Bernat Metge, 33",
    "sg:city":"Mollet Valles",
    "sg:orig_category":"Aparatos De Medida, Control, Regulaci\u00d3n Y Detecci\u00d3n",
    "sg:phone":"+34 935 70 46 01",
    "sg:postcode":"08100",
    "sg:province":"Barcelona",
    "sg:website":"www.filsa.es",
    "wof:name":"Talleres Filsa S.a.",
    "wof:placetype":"venue"
},
  "geometry": {"coordinates":[2.2082281113,41.5383377075],"type":"Point"}
}