{
  "type": "Feature",
  "properties": {
    "addr:full":"Calle de Juan Bautista Zabala, 12 Algorta Vizcaya 48991",
    "addr:housenumber":"12",
    "addr:postcode":"48991",
    "addr:street":"Calle De Juan Bautista Zabala",
    "iso:country":"ES",
    "sg:address":"Calle de Juan Bautista Zabala, 12",
    "sg:city":"Algorta",
    "sg:orig_category":"Molduras, Junquillos, Listones Y Molduras Perforadas",
    "sg:phone":"+34 944 60 96 42",
    "sg:postcode":"48991",
    "sg:province":"Vizcaya",
    "wof:name":"Ramos Urrutia Borja Juan",
    "wof:placetype":"venue"
},
  "geometry": {"coordinates":[-3.0100948811,43.3507347107],"type":"Point"}
}