{
  "type": "Feature",
  "properties": {
    "addr:full":"Ctra. Sagunto-burgos, Km. 0405,0 S. Leonardo Yag\u00fce Soria 42140",
    "addr:postcode":"42140",
    "addr:street":"Ctra. Sagunto-Burgos Km. 0405,0 S. Leonardo Yaguee",
    "iso:country":"ES",
    "sg:address":"Ctra. Sagunto-burgos, Km. 0405,0",
    "sg:city":"S. Leonardo Yag\u00fce",
    "sg:orig_category":"Empresas De Carpinter\u00cda De Madera",
    "sg:phone":"+34 975 37 67 44",
    "sg:postcode":"42140",
    "sg:province":"Soria",
    "wof:name":"Hijos De Isabelo Gomez, S.a.",
    "wof:placetype":"venue"
},
  "geometry": {"coordinates":[-3.0625391006,41.8294868469],"type":"Point"}
}