{
  "type": "Feature",
  "properties": {
    "addr:full":"O Casal, S/n Casal La Coru\u00f1a 15189",
    "addr:postcode":"15189",
    "addr:street":"O Casal S / N Casal;Corun\u0303A",
    "iso:country":"ES",
    "sg:address":"O Casal, S/n",
    "sg:city":"Casal",
    "sg:orig_category":"Empresas De Carpinter\u00cda De Madera",
    "sg:phone":"+34 981 67 77 87",
    "sg:postcode":"15189",
    "sg:province":"La Coru\u00f1a",
    "wof:name":"Leston Calo Maria",
    "wof:placetype":"venue"
},
  "geometry": {"coordinates":[-8.3556318283,43.2196540833],"type":"Point"}
}