{
  "type": "Feature",
  "properties": {
    "addr:full":"Carrer de Miquel Barcelo, 36 Falset Tarragona 43730",
    "addr:housenumber":"36",
    "addr:postcode":"43730",
    "addr:street":"Carrer De Miquel Barcelo",
    "iso:country":"ES",
    "sg:address":"Carrer de Miquel Barcelo, 36",
    "sg:city":"Falset",
    "sg:orig_category":"Reposter\u00cdas",
    "sg:phone":"+34 977 83 12 19",
    "sg:postcode":"43730",
    "sg:province":"Tarragona",
    "wof:name":"Rull Pedret Carmen",
    "wof:placetype":"venue"
},
  "geometry": {"coordinates":[0.8174039721,41.1435089111],"type":"Point"}
}