{
  "type": "Feature",
  "properties": {
    "addr:full":"Carrer de Alts Forns, 69 Barcelona Barcelona 08038",
    "addr:housenumber":"69",
    "addr:postcode":"08038",
    "addr:street":"Carrer De Alts Forns",
    "iso:country":"ES",
    "sg:address":"Carrer de Alts Forns, 69",
    "sg:city":"Barcelona",
    "sg:orig_category":"Complementos De Vestir (al Por Menor)",
    "sg:phone":"+34 934 21 90 42",
    "sg:postcode":"08038",
    "sg:province":"Barcelona",
    "wof:name":"Zenon Belda Mercedes",
    "wof:placetype":"venue"
},
  "geometry": {"coordinates":[2.1412258148,41.3590049744],"type":"Point"}
}