{
  "type": "Feature",
  "properties": {
    "addr:full":"Calle de Victoria, 37 Malaga M\u00e1laga 29012",
    "addr:housenumber":"37",
    "addr:postcode":"29012",
    "addr:street":"Calle De Victoria;Ma\u0301Laga",
    "iso:country":"ES",
    "sg:address":"Calle de Victoria, 37",
    "sg:city":"Malaga",
    "sg:orig_category":"M\u00c9dicos: Estomatolog\u00cda",
    "sg:phone":"+34 952 25 31 50",
    "sg:postcode":"29012",
    "sg:province":"M\u00e1laga",
    "wof:name":"Baca Osorio Antonio",
    "wof:placetype":"venue"
},
  "geometry": {"coordinates":[-4.4154019356,36.7248573303],"type":"Point"}
}