{
  "type": "Feature",
  "properties": {
    "iso:country":"ES",
    "sg:address":"Avgd Segre, 3",
    "sg:city":"Lleida",
    "sg:orig_category":"Aparcamientos (infraestructuras, Accesorios)",
    "sg:phone":"+34 973 23 06 77",
    "sg:postcode":"25007",
    "sg:province":"Lleida",
    "wof:name":"Fincas Financo S. A.",
    "wof:placetype":"venue"
},
  "geometry": {"coordinates":[0.630704999,41.6163482666],"type":"Point"}
}