{
  "type": "Feature",
  "properties": {
    "addr:full":"Calle de Fernando Morente, S/n Porcuna Ja\u00e9n 23790",
    "addr:housenumber":"s / n",
    "addr:postcode":"23790",
    "addr:street":"Calle De Fernando Morente",
    "iso:country":"ES",
    "sg:address":"Calle de Fernando Morente, S/n",
    "sg:city":"Porcuna",
    "sg:orig_category":"Molduras, Junquillos, Listones Y Molduras Perforadas",
    "sg:phone":"+34 953 54 55 75",
    "sg:postcode":"23790",
    "sg:province":"Ja\u00e9n",
    "wof:name":"Eurotel Sur",
    "wof:placetype":"venue"
},
  "geometry": {"coordinates":[-4.1858410835,37.871837616],"type":"Point"}
}