{
  "type": "Feature",
  "properties": {
    "addr:full":"Calle de 31 (monte Colorado), 6 Monte Colorado Valencia 46185",
    "addr:housenumber":"31",
    "addr:postcode":"6;46185",
    "addr:street":"Calle De",
    "iso:country":"ES",
    "sg:address":"Calle de 31 (monte Colorado), 6",
    "sg:city":"Monte Colorado",
    "sg:orig_category":"Jardiner\u00cdas, Vegetales, Art\u00cdculos De Jardiner\u00cda (al Por Menor)",
    "sg:phone":"+34 961 66 14 44",
    "sg:postcode":"46185",
    "sg:province":"Valencia",
    "wof:name":"Jorge Cervera Rafael",
    "wof:placetype":"venue"
},
  "geometry": {"coordinates":[-0.3768048882,39.4702377319],"type":"Point"}
}