{
  "type": "Feature",
  "properties": {
    "iso:country":"ES",
    "sg:address":"Calle de Cruz (de La), 4",
    "sg:city":"Alcantarilla",
    "sg:orig_category":"Carnicer\u00cdas, Carnicer\u00cdas",
    "sg:phone":"+34 968 80 78 52",
    "sg:postcode":"30820",
    "sg:province":"Murcia",
    "wof:name":"Lopez Cascales Pedro Jose",
    "wof:placetype":"venue"
},
  "geometry": {"coordinates":[-1.2117701769,37.9725112915],"type":"Point"}
}