{
  "type": "Feature",
  "properties": {
    "iso:country":"ES",
    "sg:address":"Calle de Piquer, 3",
    "sg:city":"Madrid",
    "sg:orig_category":"Electricidad, Electr\u00d3nica: Suministros (al Por Menor)",
    "sg:phone":"+34 917 66 85 19",
    "sg:postcode":"28033",
    "sg:province":"Madrid",
    "wof:name":"Inelcom S.a.",
    "wof:placetype":"venue"
},
  "geometry": {"coordinates":[-3.66456604,40.4656028748],"type":"Point"}
}