{
  "type": "Feature",
  "properties": {
    "addr:full":"Av Beniarda, 18 Benidorm Alicante 03500",
    "addr:housenumber":"18",
    "addr:postcode":"03500",
    "addr:street":"Av Beniarda",
    "iso:country":"ES",
    "sg:address":"Av Beniarda, 18",
    "sg:city":"Benidorm",
    "sg:orig_category":"Plomeros",
    "sg:phone":"+34 965 85 12 22",
    "sg:postcode":"03500",
    "sg:province":"Alicante",
    "wof:name":"Rucosa S.l",
    "wof:placetype":"venue"
},
  "geometry": {"coordinates":[-0.1333660036,38.5478439331],"type":"Point"}
}