{
  "type": "Feature",
  "properties": {
    "addr:full":"Cno. Vjo. Elche, 17 Alacant Alicante 03008",
    "addr:housenumber":"17",
    "addr:postcode":"03008",
    "addr:street":"Vjo. Elche",
    "iso:country":"ES",
    "sg:address":"Cno. Vjo. Elche, 17",
    "sg:city":"Alacant",
    "sg:orig_category":"Venta, Instalaci\u00d3n De Calefacci\u00d3n",
    "sg:phone":"+34 965 28 14 71",
    "sg:postcode":"03008",
    "sg:province":"Alicante",
    "wof:name":"Coalgas S.l.",
    "wof:placetype":"venue"
},
  "geometry": {"coordinates":[-0.5224840045,38.2840309143],"type":"Point"}
}