{
  "type": "Feature",
  "properties": {
    "addr:full":"Calle de Clemente Jordan, 86 Puente De Arucas Las Palmas 35400",
    "addr:housenumber":"86",
    "addr:postcode":"35400",
    "addr:street":"Calle De Clemente Jordan",
    "iso:country":"ES",
    "sg:address":"Calle de Clemente Jordan, 86",
    "sg:city":"Puente De Arucas",
    "sg:orig_category":"Quincaller\u00cda (al Por Menor)",
    "sg:phone":"+34 928 62 15 67",
    "sg:postcode":"35400",
    "sg:province":"Las Palmas",
    "wof:name":"Ramos Garcia Maria Isabel",
    "wof:placetype":"venue"
},
  "geometry": {"coordinates":[-15.5135564804,28.1121940613],"type":"Point"}
}