{
  "type": "Feature",
  "properties": {
    "addr:full":"P. Serena, 15 Peraleda Zaucejo Badajoz 06919",
    "addr:housenumber":"15",
    "addr:postcode":"06919",
    "addr:street":"P. Serena",
    "iso:country":"ES",
    "sg:address":"P. Serena, 15",
    "sg:city":"Peraleda Zaucejo",
    "sg:orig_category":"Hoteles",
    "sg:phone":"+34 924 63 66 57",
    "sg:postcode":"06919",
    "sg:province":"Badajoz",
    "wof:name":"Rey Del Rey Faustino Del",
    "wof:placetype":"venue"
},
  "geometry": {"coordinates":[-5.565264225,38.4723587036],"type":"Point"}
}