{
  "type": "Feature",
  "properties": {
    "addr:full":"Avda Belgica (de), 3 Santa Cruz De Tenerife Santa Cruz De Tenerife 38007",
    "addr:postcode":"38007",
    "addr:street":"Avda Belgica De 3",
    "iso:country":"ES",
    "sg:address":"Avda Belgica (de), 3",
    "sg:city":"Santa Cruz De Tenerife",
    "sg:orig_category":"Agencias Y Agentes Comerciales, Representantes",
    "sg:phone":"+34 922 21 43 01",
    "sg:postcode":"38007",
    "sg:province":"Santa Cruz De Tenerife",
    "wof:name":"Siguero Montes Angel",
    "wof:placetype":"venue"
},
  "geometry": {"coordinates":[-16.2637939453,28.4643974304],"type":"Point"}
}