{
  "type": "Feature",
  "properties": {
    "addr:full":"Calle de Lorenzo Llona, 11 Sestao Vizcaya 48910",
    "addr:housenumber":"11",
    "addr:postcode":"48910",
    "addr:street":"Calle De Lorenzo Llona",
    "iso:country":"ES",
    "sg:address":"Calle de Lorenzo Llona, 11",
    "sg:city":"Sestao",
    "sg:orig_category":"Alimentaci\u00d3n General (al Por Menor)",
    "sg:phone":"+34 944 95 61 87",
    "sg:postcode":"48910",
    "sg:province":"Vizcaya",
    "wof:name":"Maria Isabel Zamarre\u00f1o Montero Y Otras C.b.",
    "wof:placetype":"venue"
},
  "geometry": {"coordinates":[-3.005712986,43.3083000183],"type":"Point"}
}