{
  "type": "Feature",
  "properties": {
    "addr:full":"Avda Ca\u00d1onero Dato, 22 Ceuta Ceuta 51001",
    "addr:housenumber":"22",
    "addr:postcode":"51001",
    "addr:street":"Avda Can\u0303Onero Dato",
    "iso:country":"ES",
    "sg:address":"Avda Ca\u00d1onero Dato, 22",
    "sg:city":"Ceuta",
    "sg:orig_category":"Quincaller\u00cda (al Por Menor)",
    "sg:phone":"+34 956 50 84 67",
    "sg:postcode":"51001",
    "sg:province":"Ceuta",
    "wof:name":"Ferreterias Doncel S.l.",
    "wof:placetype":"venue"
},
  "geometry": {"coordinates":[-5.324037075,35.8944015503],"type":"Point"}
}