{
  "type": "Feature",
  "properties": {
    "iso:country":"ES",
    "sg:address":"Carrer de Calabria, 276",
    "sg:city":"Barcelona",
    "sg:orig_category":"Persianas Interiores, Exteriores",
    "sg:phone":"+34 933 21 33 55",
    "sg:postcode":"08029",
    "sg:province":"Barcelona",
    "wof:name":"Toperal S.l.",
    "wof:placetype":"venue"
},
  "geometry": {"coordinates":[2.1445870399,41.3877754211],"type":"Point"}
}