{
  "type": "Feature",
  "properties": {
    "addr:full":"Calle de Misericordia (de La), S/n Arganda Madrid 28500",
    "addr:postcode":"28500",
    "addr:street":"Calle De Misericordia De La S / N",
    "iso:country":"ES",
    "sg:address":"Calle de Misericordia (de La), S/n",
    "sg:city":"Arganda",
    "sg:orig_category":"Laboratorios Y Trabajos De Fotograf\u00cda, V\u00cddeo Y Cine",
    "sg:phone":"+34 918 71 72 35",
    "sg:postcode":"28500",
    "sg:province":"Madrid",
    "wof:name":"Hernandez Guillen Eduardo",
    "wof:placetype":"venue"
},
  "geometry": {"coordinates":[-3.4415390491,40.3016548157],"type":"Point"}
}