{
  "type": "Feature",
  "properties": {
    "iso:country":"ES",
    "sg:address":"Carr Sequial, 51",
    "sg:city":"Sueca",
    "sg:orig_category":"M\u00c9dicos: Otorrinolaringolog\u00cda",
    "sg:phone":"+34 961 71 09 38",
    "sg:postcode":"46410",
    "sg:province":"Valencia",
    "wof:name":"Benavent Chover Josefa Asuncion",
    "wof:placetype":"venue"
},
  "geometry": {"coordinates":[-0.3103480041,39.2048301697],"type":"Point"}
}