{
  "type": "Feature",
  "properties": {
    "iso:country":"ES",
    "sg:address":"Calle de Dulcinea, 12",
    "sg:city":"Villanueva De Los Infantes",
    "sg:orig_category":"Arquitectos",
    "sg:phone":"+34 926 36 17 50",
    "sg:postcode":"13320",
    "sg:province":"Ciudad Real",
    "wof:name":"Gonzalez Sosa Pablo Guillermo",
    "wof:placetype":"venue"
},
  "geometry": {"coordinates":[-3.0081102848,38.7362174988],"type":"Point"}
}