{
  "type": "Feature",
  "properties": {
    "iso:country":"ES",
    "sg:address":"Carr Guasch, 7",
    "sg:city":"Badalona",
    "sg:orig_category":"Inmobiliaria (agencias)",
    "sg:phone":"+34 934 60 37 00",
    "sg:postcode":"08913",
    "sg:province":"Barcelona",
    "sg:website":"www.gilcarfincas.com",
    "wof:name":"Gilcar Fincas S.l.",
    "wof:placetype":"venue"
},
  "geometry": {"coordinates":[2.2180840969,41.4347076416],"type":"Point"}
}