{
  "type": "Feature",
  "properties": {
    "addr:full":"C/ Bosch, 25 Manacor Islas Baleares 07500",
    "addr:housenumber":"25",
    "addr:postcode":"07500",
    "addr:street":"C / Bosch",
    "iso:country":"ES",
    "sg:address":"C/ Bosch, 25",
    "sg:city":"Manacor",
    "sg:orig_category":"Empleado Administrativo",
    "sg:phone":"+34 971 55 18 89",
    "sg:postcode":"07500",
    "sg:province":"Islas Baleares",
    "wof:name":"Blanquer Gelabert Jeronima",
    "wof:placetype":"venue"
},
  "geometry": {"coordinates":[3.2106881142,39.5695724487],"type":"Point"}
}