{
  "type": "Feature",
  "properties": {
    "addr:full":"Calle de Cesar Gonzalez Ruano, 8 Cuenca Cuenca 16004",
    "addr:housenumber":"8",
    "addr:postcode":"16004",
    "addr:street":"Calle De Cesar Gonzalez Ruano",
    "iso:country":"ES",
    "sg:address":"Calle de Cesar Gonzalez Ruano, 8",
    "sg:city":"Cuenca",
    "sg:orig_category":"Arquitectos",
    "sg:phone":"+34 969 22 73 31",
    "sg:postcode":"16004",
    "sg:province":"Cuenca",
    "wof:name":"Sacristan Montero Manuel",
    "wof:placetype":"venue"
},
  "geometry": {"coordinates":[-2.1325085163,40.0618743896],"type":"Point"}
}