{
  "type": "Feature",
  "properties": {
    "iso:country":"ES",
    "sg:address":"Calle de Arenal, 67",
    "sg:city":"Miranda Ebro",
    "sg:orig_category":"Agencias De Viajes",
    "sg:phone":"+34 947 34 79 80",
    "sg:postcode":"09200",
    "sg:province":"Burgos",
    "sg:website":"www.viajeselcorteingles.es",
    "wof:name":"Viajes El Corte Ingles S.a.",
    "wof:placetype":"venue"
},
  "geometry": {"coordinates":[-2.9442219734,42.6860542297],"type":"Point"}
}