{
  "type": "Feature",
  "properties": {
    "addr:full":"Calle de San Cristobal, 5 San Jose Rinconada Sevilla 41300",
    "addr:housenumber":"5",
    "addr:postcode":"41300",
    "addr:street":"Calle De San Cristobal",
    "iso:country":"ES",
    "sg:address":"Calle de San Cristobal, 5",
    "sg:city":"San Jose Rinconada",
    "sg:orig_category":"Mec\u00c1nico Del Autom\u00d3vil",
    "sg:phone":"+34 955 79 20 98",
    "sg:postcode":"41300",
    "sg:province":"Sevilla",
    "wof:name":"Carmona Sanchez Juan Jose",
    "wof:placetype":"venue"
},
  "geometry": {"coordinates":[-5.940530777,37.4876747131],"type":"Point"}
}