{
  "type": "Feature",
  "properties": {
    "iso:country":"ES",
    "sg:address":"Avda Boliches De Los, 32",
    "sg:city":"Fuengirola",
    "sg:orig_category":"M\u00c9dicos: Estomatolog\u00cda",
    "sg:phone":"+34 952 46 09 48",
    "sg:postcode":"29640",
    "sg:province":"M\u00e1laga",
    "wof:name":"Gonzalez Aragones Maria Jose",
    "wof:placetype":"venue"
},
  "geometry": {"coordinates":[-4.6135778427,36.5546455383],"type":"Point"}
}