{
  "type": "Feature",
  "properties": {
    "iso:country":"ES",
    "sg:address":"Calle de Papin, 18",
    "sg:city":"Salamanca",
    "sg:orig_category":"Sociedades, Compa\u00d1\u00cdas Aseguradoras",
    "sg:phone":"+34 923 22 59 51",
    "sg:postcode":"37007",
    "sg:province":"Salamanca",
    "wof:name":"Finsa Gestion Financiera Slu",
    "wof:placetype":"venue"
},
  "geometry": {"coordinates":[-5.6685609818,40.9702529907],"type":"Point"}
}