{
  "type": "Feature",
  "properties": {
    "addr:full":"Pg Blay, 42 Olot Girona 17800",
    "addr:housenumber":"42",
    "addr:postcode":"17800",
    "addr:street":"Pg Blay",
    "iso:country":"ES",
    "sg:address":"Pg Blay, 42",
    "sg:city":"Olot",
    "sg:orig_category":"Molduras, Junquillos, Listones Y Molduras Perforadas",
    "sg:phone":"+34 972 26 16 05",
    "sg:postcode":"17800",
    "sg:province":"Girona",
    "wof:name":"Servi Firal S.c.c.l.",
    "wof:placetype":"venue"
},
  "geometry": {"coordinates":[2.487126112,42.1832046509],"type":"Point"}
}