{
  "type": "Feature",
  "properties": {
    "iso:country":"ES",
    "sg:address":"Carrer de Isaac Peral, 36",
    "sg:city":"Terrassa",
    "sg:orig_category":"Ense\u00d1ante, Direcci\u00d3n",
    "sg:phone":"+34 937 88 01 16",
    "sg:postcode":"08224",
    "sg:province":"Barcelona",
    "wof:name":"Marti Arus Ernesto",
    "wof:placetype":"venue"
},
  "geometry": {"coordinates":[2.001128912,41.563457489],"type":"Point"}
}