{
  "type": "Feature",
  "properties": {
    "iso:country":"ES",
    "sg:address":"Alta, S/n",
    "sg:city":"Ures",
    "sg:orig_category":"Grafistas",
    "sg:phone":"+34 949 34 70 14",
    "sg:postcode":"19265",
    "sg:province":"Guadalajara",
    "sg:website":"www.casahueca.com",
    "wof:name":"Casa Hueca S.l.",
    "wof:placetype":"venue"
},
  "geometry": {"coordinates":[-2.6742660999,41.1044235229],"type":"Point"}
}