{
  "type": "Feature",
  "properties": {
    "addr:full":"Calle de Concepcion, 1 Solana Ciudad Real 13240",
    "addr:postcode":"13240",
    "addr:street":"Calle De Concepcion 1 Solana;Real",
    "iso:country":"ES",
    "sg:address":"Calle de Concepcion, 1",
    "sg:city":"Solana",
    "sg:orig_category":"\u00d3ptica: Instrumentos (fabricaci\u00d3n)",
    "sg:phone":"+34 926 63 20 26",
    "sg:postcode":"13240",
    "sg:province":"Ciudad Real",
    "wof:name":"Mi\u00f1ano Romero Mariano",
    "wof:placetype":"venue"
},
  "geometry": {"coordinates":[-3.2385346889,38.941696167],"type":"Point"}
}