{
  "type": "Feature",
  "properties": {
    "addr:full":"Calle de Safantia, 1 Argana Baja Las Palmas 35500",
    "addr:housenumber":"1",
    "addr:postcode":"35500",
    "addr:street":"Calle De Safantia",
    "iso:country":"ES",
    "sg:address":"Calle de Safantia, 1",
    "sg:city":"Argana Baja",
    "sg:orig_category":"Art\u00cdculos Funerarios (al Por Menor)",
    "sg:phone":"+34 928 80 01 17",
    "sg:postcode":"35500",
    "sg:province":"Las Palmas",
    "wof:name":"Inversiones Reunidas Funerarias S.r.l.",
    "wof:placetype":"venue"
},
  "geometry": {"coordinates":[-13.5666389465,28.9723834991],"type":"Point"}
}