{
  "type": "Feature",
  "properties": {
    "addr:full":"C/ Alfons I, 14 Puigcerda Girona 17520",
    "addr:housenumber":"14",
    "addr:postcode":"17520",
    "addr:street":"C / Alfons I",
    "iso:country":"ES",
    "sg:address":"C/ Alfons I, 14",
    "sg:city":"Puigcerda",
    "sg:orig_category":"Muebles, Minoristas",
    "sg:phone":"+34 972 88 00 32",
    "sg:postcode":"17520",
    "sg:province":"Girona",
    "wof:name":"Llanas Reguant Miguel",
    "wof:placetype":"venue"
},
  "geometry": {"coordinates":[1.9280669689,42.43176651],"type":"Point"}
}