{
  "type": "Feature",
  "properties": {
    "iso:country":"ES",
    "sg:address":"Avda Reina Mercedes, 41",
    "sg:city":"Sevilla",
    "sg:orig_category":"Estancos",
    "sg:phone":"+34 954 61 08 27",
    "sg:postcode":"41012",
    "sg:province":"Sevilla",
    "wof:name":"Lopez Calatayud Alfonso Enrique",
    "wof:placetype":"venue"
},
  "geometry": {"coordinates":[-5.9859828949,37.3586540222],"type":"Point"}
}