{
  "type": "Feature",
  "properties": {
    "iso:country":"ES",
    "sg:address":"Rua Oliva (la), 4",
    "sg:city":"Pontevedra",
    "sg:orig_category":"Ense\u00d1ante, Direcci\u00d3n",
    "sg:phone":"+34 986 84 34 84",
    "sg:postcode":"36001",
    "sg:province":"Pontevedra",
    "wof:name":"Couselo Filgueira Marina",
    "wof:placetype":"venue"
},
  "geometry": {"coordinates":[-8.64432621,42.4306602478],"type":"Point"}
}