{
  "type": "Feature",
  "properties": {
    "iso:country":"ES",
    "sg:address":"Calle de Javea, 104",
    "sg:city":"Alacant",
    "sg:orig_category":"Producci\u00d3n, Distribuci\u00d3n De Electricidad",
    "sg:phone":"+34 965 12 82 41",
    "sg:postcode":"03009",
    "sg:province":"Alicante",
    "wof:name":"Tortosa Garcia Electricidad S.l.",
    "wof:placetype":"venue"
},
  "geometry": {"coordinates":[-0.4982914031,38.3642425537],"type":"Point"}
}