{
  "type": "Feature",
  "properties": {
    "addr:full":"Calle de San Pedro Del Barco, 5 Barco De Avila \u00c1vila 05600",
    "addr:housenumber":"5",
    "addr:postcode":"05600",
    "addr:street":"Calle De San Pedro Del Barco;A\u0301Vila",
    "iso:country":"ES",
    "sg:address":"Calle de San Pedro Del Barco, 5",
    "sg:city":"Barco De Avila",
    "sg:orig_category":"Relojer\u00cda (al Por Menor, Reparaci\u00d3n)",
    "sg:phone":"+34 920 34 04 06",
    "sg:postcode":"05600",
    "sg:province":"\u00c1vila",
    "wof:name":"Salinas Ferrer Ricardo",
    "wof:placetype":"venue"
},
  "geometry": {"coordinates":[-5.5260891914,40.3563537598],"type":"Point"}
}