{
  "type": "Feature",
  "properties": {
    "addr:full":"Calle de Vitoria, 29 Burgos Burgos 09004",
    "addr:housenumber":"29",
    "addr:postcode":"09004",
    "addr:street":"Calle De Vitoria",
    "iso:country":"ES",
    "sg:address":"Calle de Vitoria, 29",
    "sg:city":"Burgos",
    "sg:orig_category":"Muebles, Minoristas",
    "sg:phone":"+34 947 26 06 49",
    "sg:postcode":"09004",
    "sg:province":"Burgos",
    "sg:website":"www.casayvida.com",
    "wof:name":"Peyma Muebles S.l.",
    "wof:placetype":"venue"
},
  "geometry": {"coordinates":[-3.6961228848,42.3419113159],"type":"Point"}
}