{
  "type": "Feature",
  "properties": {
    "addr:full":"Praz Rei (do), 6 Lugo Lugo 27002",
    "addr:housenumber":"6",
    "addr:postcode":"27002",
    "iso:country":"ES",
    "sg:address":"Praz Rei (do), 6",
    "sg:city":"Lugo",
    "sg:orig_category":"Caf\u00c9s, Bares, Cervecer\u00cdas",
    "sg:phone":"+34 982 24 52 14",
    "sg:postcode":"27002",
    "sg:province":"Lugo",
    "wof:name":"Legaspi Negrelos Alonso",
    "wof:placetype":"venue"
},
  "geometry": {"coordinates":[-7.5502867699,43.0047264099],"type":"Point"}
}