{
  "type": "Feature",
  "properties": {
    "addr:full":"Castellanos Ca\u00f1ada, S/n Castellanos Ca\u00f1ada \u00c1vila 05154",
    "addr:postcode":"05154",
    "addr:street":"Can\u0303Ada S / N Castellanos Can\u0303Ada A\u0301Vila",
    "iso:country":"ES",
    "sg:address":"Castellanos Ca\u00f1ada, S/n",
    "sg:city":"Castellanos Ca\u00f1ada",
    "sg:orig_category":"Cr\u00cda De Animales",
    "sg:phone":"+34 920 20 90 42",
    "sg:postcode":"05154",
    "sg:province":"\u00c1vila",
    "wof:name":"Maria Luisa Fernandez De Cordoba Y Otros C.b.",
    "wof:placetype":"venue"
},
  "geometry": {"coordinates":[-5.2998518944,40.6313018799],"type":"Point"}
}