{
  "type": "Feature",
  "properties": {
    "iso:country":"ES",
    "sg:address":"Alerce, 7",
    "sg:city":"Aljaraque",
    "sg:orig_category":"Institutos De Belleza",
    "sg:phone":"+34 959 31 91 17",
    "sg:postcode":"21110",
    "sg:province":"Huelva",
    "wof:name":"Allepuz Benitez Aurora",
    "wof:placetype":"venue"
},
  "geometry": {"coordinates":[-7.0089845657,37.2820930481],"type":"Point"}
}