{
  "type": "Feature",
  "properties": {
    "addr:full":"Avda Regne De Valencia, 74 Valencia Valencia 46005",
    "addr:housenumber":"74",
    "addr:postcode":"46005",
    "addr:street":"Avda Regne De Valencia",
    "iso:country":"ES",
    "sg:address":"Avda Regne De Valencia, 74",
    "sg:city":"Valencia",
    "sg:orig_category":"Abogados",
    "sg:phone":"+34 963 73 55 59",
    "sg:postcode":"46005",
    "sg:province":"Valencia",
    "wof:name":"Carbonell March Ignacio",
    "wof:placetype":"venue"
},
  "geometry": {"coordinates":[-0.3641749918,39.4627113342],"type":"Point"}
}