{
  "type": "Feature",
  "properties": {
    "addr:full":"Calle de Do\u00d1a Raquel, 4 Vilamartin Valdeorras Ourense 32340",
    "addr:housenumber":"4",
    "addr:postcode":"32340",
    "addr:street":"Calle De Don\u0303A Raquel",
    "iso:country":"ES",
    "sg:address":"Calle de Do\u00d1a Raquel, 4",
    "sg:city":"Vilamartin Valdeorras",
    "sg:orig_category":"Cerrajer\u00cda, Ferrallista",
    "sg:phone":"+34 988 30 01 04",
    "sg:postcode":"32340",
    "sg:province":"Ourense",
    "wof:name":"Fernandez Ares Eloy",
    "wof:placetype":"venue"
},
  "geometry": {"coordinates":[-7.8646407127,42.340007782],"type":"Point"}
}