{
  "type": "Feature",
  "properties": {
    "addr:full":"Calle de San Clemente, 6 Talavera Reina Toledo 45600",
    "addr:housenumber":"6",
    "addr:postcode":"45600",
    "addr:street":"Calle De San Clemente",
    "iso:country":"ES",
    "sg:address":"Calle de San Clemente, 6",
    "sg:city":"Talavera Reina",
    "sg:orig_category":"Mec\u00c1nico Del Autom\u00d3vil",
    "sg:phone":"+34 925 80 37 42",
    "sg:postcode":"45600",
    "sg:province":"Toledo",
    "wof:name":"Planchuelo Fernandez Moises",
    "wof:placetype":"venue"
},
  "geometry": {"coordinates":[-4.8328828812,39.9565429688],"type":"Point"}
}