{
  "type": "Feature",
  "properties": {
    "iso:country":"ES",
    "sg:address":"Carr Francesc Cambo, 3",
    "sg:city":"Verges",
    "sg:orig_category":"Electrodom\u00c9sticos (al Por Menor)",
    "sg:phone":"+34 972 78 03 72",
    "sg:postcode":"17142",
    "sg:province":"Girona",
    "sg:website":"www.redelite.es",
    "wof:name":"Fortia Vidal Alfons",
    "wof:placetype":"venue"
},
  "geometry": {"coordinates":[3.0455670357,42.062210083],"type":"Point"}
}