{
  "type": "Feature",
  "properties": {
    "addr:full":"Carrer de Armand Obiols, 88 Sabadell Barcelona 08207",
    "addr:housenumber":"88",
    "addr:postcode":"08207",
    "addr:street":"Carrer De Armand Obiols",
    "iso:country":"ES",
    "sg:address":"Carrer de Armand Obiols, 88",
    "sg:city":"Sabadell",
    "sg:orig_category":"Promotores Constructores",
    "sg:phone":"+34 937 17 76 99",
    "sg:postcode":"08207",
    "sg:province":"Barcelona",
    "wof:name":"Constructora Mardisal S.l.",
    "wof:placetype":"venue"
},
  "geometry": {"coordinates":[2.0813879967,41.5747184753],"type":"Point"}
}