{
  "type": "Feature",
  "properties": {
    "addr:full":"Rua Rafael Calleja, 20 Pobra Do Carami\u00e7al La Coru\u00f1a 15940",
    "addr:housenumber":"20",
    "addr:postcode":"15940",
    "addr:street":"Rua Rafael Calleja;Corun\u0303A",
    "iso:country":"ES",
    "sg:address":"Rua Rafael Calleja, 20",
    "sg:city":"Pobra Do Carami\u00e7al",
    "sg:orig_category":"Peluqueros: De Se\u00d1oras",
    "sg:phone":"+34 981 83 19 02",
    "sg:postcode":"15940",
    "sg:province":"La Coru\u00f1a",
    "wof:name":"Redondo Agrelo Francisca",
    "wof:placetype":"venue"
},
  "geometry": {"coordinates":[-8.9388132095,42.605255127],"type":"Point"}
}