{
  "type": "Feature",
  "properties": {
    "iso:country":"ES",
    "sg:address":"Ctra Cuatretondeta, S/n",
    "sg:city":"Gorga",
    "sg:orig_category":"Poller\u00cda Y Caza (al Por Menor)",
    "sg:phone":"+34 965 51 11 40",
    "sg:postcode":"03811",
    "sg:province":"Alicante",
    "wof:name":"Avicola Genis C.b.",
    "wof:placetype":"venue"
},
  "geometry": {"coordinates":[-0.357513994,38.7208900452],"type":"Point"}
}