{
  "type": "Feature",
  "properties": {
    "iso:country":"ES",
    "sg:address":"Calle de El Rompedizo, 22",
    "sg:city":"Madrid",
    "sg:orig_category":"Ense\u00d1ante, Direcci\u00d3n",
    "sg:phone":"+34 917 10 79 27",
    "sg:postcode":"28044",
    "sg:province":"Madrid",
    "wof:name":"Ruiz Rodrigo Ester",
    "wof:placetype":"venue"
},
  "geometry": {"coordinates":[-3.7634170055,40.3763618469],"type":"Point"}
}