{
  "type": "Feature",
  "properties": {
    "iso:country":"ES",
    "sg:address":"Casilla, S/n",
    "sg:city":"Capela-neves",
    "sg:orig_category":"Distribuci\u00d3n De Petr\u00d3leo Y Derivados",
    "sg:phone":"+34 981 45 94 09",
    "sg:postcode":"15613",
    "sg:province":"La Coru\u00f1a",
    "wof:name":"Lubricantes Y Carburantes Galaicos S.l.",
    "wof:placetype":"venue"
},
  "geometry": {"coordinates":[-8.0707349777,43.4355812073],"type":"Point"}
}