{
  "type": "Feature",
  "properties": {
    "iso:country":"ES",
    "sg:address":"Calle de San Vicente, 17",
    "sg:city":"Castellon",
    "sg:orig_category":"Muebles, Minoristas",
    "sg:phone":"+34 964 21 43 01",
    "sg:postcode":"12002",
    "sg:province":"Castell\u00f3n",
    "wof:name":"Emilio Amat S.l.",
    "wof:placetype":"venue"
},
  "geometry": {"coordinates":[-0.0412090011,39.9855461121],"type":"Point"}
}