{
  "type": "Feature",
  "properties": {
    "iso:country":"ES",
    "sg:address":"Avda Canovas Del Castillo, S/n",
    "sg:city":"Marbella",
    "sg:orig_category":"Instalaci\u00d3n, Reparaci\u00d3n De Ascensores Y Montacargas",
    "sg:phone":"+34 952 92 51 57",
    "sg:postcode":"29600",
    "sg:province":"M\u00e1laga",
    "wof:name":"Orona Scl",
    "wof:placetype":"venue"
},
  "geometry": {"coordinates":[-4.8966341019,36.5146484375],"type":"Point"}
}