{
  "type": "Feature",
  "properties": {
    "addr:full":"Carrer de Via Del Mil.lenari, 12 Esparreguera Barcelona 08292",
    "addr:housenumber":"12",
    "addr:postcode":"08292",
    "addr:street":"Carrer De Via Del Mil.Lenari",
    "iso:country":"ES",
    "sg:address":"Carrer de Via Del Mil.lenari, 12",
    "sg:city":"Esparreguera",
    "sg:orig_category":"\u00d3ptica: Instrumentos (fabricaci\u00d3n)",
    "sg:phone":"+34 937 70 80 37",
    "sg:postcode":"08292",
    "sg:province":"Barcelona",
    "wof:name":"Milen-optic S.l.",
    "wof:placetype":"venue"
},
  "geometry": {"coordinates":[1.8536789417,41.5242195129],"type":"Point"}
}