{
  "type": "Feature",
  "properties": {
    "addr:full":"Ctra Alfaro (de), S/n Gravalos La Rioja 26587",
    "addr:postcode":"26587",
    "addr:street":"Ctra Alfaro De S / N Gravalos;Rioja",
    "iso:country":"ES",
    "sg:address":"Ctra Alfaro (de), S/n",
    "sg:city":"Gravalos",
    "sg:orig_category":"Ense\u00d1anza, Formaci\u00d3n Profesional: Aprendizaje",
    "sg:phone":"+34 941 39 80 93",
    "sg:postcode":"26587",
    "sg:province":"La Rioja",
    "wof:name":"Ayuntamiento De Gravalos",
    "wof:placetype":"venue"
},
  "geometry": {"coordinates":[-1.9987039566,42.1080780029],"type":"Point"}
}