{
  "type": "Feature",
  "properties": {
    "iso:country":"ES",
    "sg:address":"Calle de San Jeronimo, 42",
    "sg:city":"Granada",
    "sg:orig_category":"Imprenta",
    "sg:phone":"+34 958 29 09 51",
    "sg:postcode":"18001",
    "sg:province":"Granada",
    "wof:name":"Artes Graficas Artistica S.l.",
    "wof:placetype":"venue"
},
  "geometry": {"coordinates":[-3.6019566059,37.1792068481],"type":"Point"}
}