{
  "type": "Feature",
  "properties": {
    "iso:country":"ES",
    "sg:address":"Calle de Dinamarca, 1",
    "sg:city":"Torrevieja",
    "sg:orig_category":"Supermercados Y Hipermercados",
    "sg:phone":"+34 965 71 87 75",
    "sg:postcode":"03180",
    "sg:province":"Alicante",
    "wof:name":"Serrano Hurtado Carmelo",
    "wof:placetype":"venue"
},
  "geometry": {"coordinates":[-0.6536790133,38.0173606873],"type":"Point"}
}