{
  "type": "Feature",
  "properties": {
    "iso:country":"ES",
    "sg:address":"Rua Bispo Romero Lema, S/n",
    "sg:city":"Baio Grande",
    "sg:orig_category":"M\u00c9dicos: Oftalmolog\u00cda",
    "sg:phone":"+34 981 71 90 11",
    "sg:postcode":"15150",
    "sg:province":"La Coru\u00f1a",
    "wof:name":"Berges Pacheco Antonio",
    "wof:placetype":"venue"
},
  "geometry": {"coordinates":[-8.9656591415,43.1480636597],"type":"Point"}
}