{
  "type": "Feature",
  "properties": {
    "addr:full":"Pg Espronceda, 68 Sabadell Barcelona 08204",
    "addr:housenumber":"68",
    "addr:postcode":"08204",
    "addr:street":"Pg Espronceda",
    "iso:country":"ES",
    "sg:address":"Pg Espronceda, 68",
    "sg:city":"Sabadell",
    "sg:orig_category":"Empresarios",
    "sg:phone":"+34 937 10 39 01",
    "sg:postcode":"08204",
    "sg:province":"Barcelona",
    "wof:name":"Solano Velada Jose",
    "wof:placetype":"venue"
},
  "geometry": {"coordinates":[2.1151819229,41.5286254883],"type":"Point"}
}