{
  "type": "Feature",
  "properties": {
    "addr:full":"Plaz Sierra Ministra, 9 Madrid Madrid 28018",
    "addr:housenumber":"9",
    "addr:postcode":"madrid;28018",
    "addr:street":"Ministra",
    "iso:country":"ES",
    "sg:address":"Plaz Sierra Ministra, 9",
    "sg:city":"Madrid",
    "sg:orig_category":"Promotores Constructores",
    "sg:phone":"+34 914 77 19 04",
    "sg:postcode":"28018",
    "sg:province":"Madrid",
    "wof:name":"Tejesa Obras S.l.",
    "wof:placetype":"venue"
},
  "geometry": {"coordinates":[-3.6597089767,40.3924407959],"type":"Point"}
}