{
  "type": "Feature",
  "properties": {
    "addr:full":"Avda Pais Valencia, 68 Torrent Valencia 46900",
    "addr:housenumber":"68",
    "addr:postcode":"46900",
    "addr:street":"Avda Pais Valencia;Valencia",
    "iso:country":"ES",
    "sg:address":"Avda Pais Valencia, 68",
    "sg:city":"Torrent",
    "sg:orig_category":"Administradores De Bienes Y Delegados De Comunidades De Propietarios",
    "sg:phone":"+34 961 56 49 13",
    "sg:postcode":"46900",
    "sg:province":"Valencia",
    "wof:name":"Garcia Fernandez Nicolas",
    "wof:placetype":"venue"
},
  "geometry": {"coordinates":[-0.4694919884,39.4343605042],"type":"Point"}
}