{
  "type": "Feature",
  "properties": {
    "iso:country":"ES",
    "sg:address":"Carrer de Orquidia, 9",
    "sg:city":"Montgo",
    "sg:orig_category":"Centros Empresariales",
    "sg:phone":"+34 966 42 47 25",
    "sg:postcode":"03700",
    "sg:province":"Alicante",
    "wof:name":"Uaga Ser S.l",
    "wof:placetype":"venue"
},
  "geometry": {"coordinates":[0.1280599982,38.8265113831],"type":"Point"}
}