{
  "type": "Feature",
  "properties": {
    "addr:full":"Calle de Lopez De Hoyos, 111 Madrid Madrid 28002",
    "addr:housenumber":"111",
    "addr:postcode":"28002",
    "addr:street":"Calle De Lopez De Hoyos",
    "iso:country":"ES",
    "sg:address":"Calle de Lopez De Hoyos, 111",
    "sg:city":"Madrid",
    "sg:orig_category":"Perfumer\u00cda (al Por Menor)",
    "sg:phone":"+34 914 15 45 96",
    "sg:postcode":"28002",
    "sg:province":"Madrid",
    "sg:website":"www.juteco.es",
    "wof:name":"Blanju S.l.",
    "wof:placetype":"venue"
},
  "geometry": {"coordinates":[-3.6721329689,40.445640564],"type":"Point"}
}