{
  "type": "Feature",
  "properties": {
    "addr:full":"Calle de Cruces, 15 Lumbrales Salamanca 37240",
    "addr:housenumber":"15",
    "addr:postcode":"37240",
    "addr:street":"Calle De Cruces",
    "iso:country":"ES",
    "sg:address":"Calle de Cruces, 15",
    "sg:city":"Lumbrales",
    "sg:orig_category":"Reposter\u00cdas",
    "sg:phone":"+34 923 51 24 12",
    "sg:postcode":"37240",
    "sg:province":"Salamanca",
    "wof:name":"Rio Mayado Luis Enrique Del",
    "wof:placetype":"venue"
},
  "geometry": {"coordinates":[-6.7225708961,40.9379615784],"type":"Point"}
}