{
  "type": "Feature",
  "properties": {
    "iso:country":"ES",
    "sg:address":"Mizkia, 2",
    "sg:city":"Mizkia",
    "sg:orig_category":"Cr\u00cda De Bovinos",
    "sg:phone":"+34 943 60 45 38",
    "sg:postcode":"20830",
    "sg:province":"Guip\u00f9zcoa",
    "wof:name":"Zaldumendi S.c",
    "wof:placetype":"venue"
},
  "geometry": {"coordinates":[-2.38945508,43.3070259094],"type":"Point"}
}