{
  "type": "Feature",
  "properties": {
    "iso:country":"ES",
    "sg:address":"Avda Canarias De, 20",
    "sg:city":"Palmas De Gran Canaria",
    "sg:orig_category":"Cursos Particulares, Asistencia Escolar",
    "sg:phone":"+34 928 38 21 78",
    "sg:postcode":"35002",
    "sg:province":"Las Palmas",
    "wof:name":"Caballero Dominguez Juan Luis",
    "wof:placetype":"venue"
},
  "geometry": {"coordinates":[-15.4137544632,28.1060218811],"type":"Point"}
}