{
  "type": "Feature",
  "properties": {
    "iso:country":"ES",
    "sg:address":"Avda Carlos Iii, 335",
    "sg:city":"Campillo Del Moro",
    "sg:orig_category":"Inmobiliaria (agencias)",
    "sg:phone":"+34 950 34 77 66",
    "sg:postcode":"04720",
    "sg:province":"Almer\u00eda",
    "sg:website":"www.unicasa.es",
    "wof:name":"Sogerem 2000 S.l.",
    "wof:placetype":"venue"
},
  "geometry": {"coordinates":[-2.5974500179,36.801410675],"type":"Point"}
}