{
  "type": "Feature",
  "properties": {
    "addr:full":"Calle de Calvario, S/n Santiba\u00e7ez El Alto C\u00e1ceres 10859",
    "addr:housenumber":"s",
    "addr:postcode":"10859",
    "addr:street":"Calle De Calvario;/ N Santibac\u0327Ez;Ca\u0301Ceres",
    "iso:country":"ES",
    "sg:address":"Calle de Calvario, S/n",
    "sg:city":"Santiba\u00e7ez El Alto",
    "sg:orig_category":"Venta, Instalaci\u00d3n De Calefacci\u00d3n",
    "sg:phone":"+34 927 44 14 03",
    "sg:postcode":"10859",
    "sg:province":"C\u00e1ceres",
    "wof:name":"Gomez Hernandez Jose Antonio",
    "wof:placetype":"venue"
},
  "geometry": {"coordinates":[-6.3707604408,39.4761772156],"type":"Point"}
}