{
  "type": "Feature",
  "properties": {
    "iso:country":"ES",
    "sg:address":"Rbla Egara, 154",
    "sg:city":"Terrassa",
    "sg:orig_category":"Electrodom\u00c9sticos (al Por Menor)",
    "sg:phone":"+34 937 89 21 02",
    "sg:postcode":"08221",
    "sg:province":"Barcelona",
    "wof:name":"Agrupacion Bazar El Regalo S.a.",
    "wof:placetype":"venue"
},
  "geometry": {"coordinates":[2.0078651905,41.5618400574],"type":"Point"}
}