{
  "type": "Feature",
  "properties": {
    "iso:country":"ES",
    "sg:address":"Cmno Yesares, S/n",
    "sg:city":"Javali Nuevo",
    "sg:orig_category":"Cerrajer\u00cda, Ferrallista",
    "sg:phone":"+34 968 80 05 54",
    "sg:postcode":"30832",
    "sg:province":"Murcia",
    "wof:name":"Garcia Fernandez Ramon",
    "wof:placetype":"venue"
},
  "geometry": {"coordinates":[-1.2194490433,37.9899787903],"type":"Point"}
}