{
  "type": "Feature",
  "properties": {
    "iso:country":"ES",
    "sg:address":"Carrer de Cantallops, 2",
    "sg:city":"Llagostera",
    "sg:orig_category":"Delegados, Agentes De Tr\u00c1nsito, Auxiliares De Transporte Internacional",
    "sg:phone":"+34 972 83 02 56",
    "sg:postcode":"17240",
    "sg:province":"Girona",
    "wof:name":"Payret Parramon Jose Francisco",
    "wof:placetype":"venue"
},
  "geometry": {"coordinates":[2.8944849968,41.8289756775],"type":"Point"}
}