{
  "type": "Feature",
  "properties": {
    "iso:country":"ES",
    "sg:address":"Dr. Gassol, 10",
    "sg:city":"Vilanova Bellpuig",
    "sg:orig_category":"Cr\u00cda De Animales",
    "sg:phone":"+34 973 32 42 75",
    "sg:postcode":"25264",
    "sg:province":"Lleida",
    "wof:name":"Solsona-serret S.l.",
    "wof:placetype":"venue"
},
  "geometry": {"coordinates":[0.9616850019,41.6147842407],"type":"Point"}
}