{
  "type": "Feature",
  "properties": {
    "addr:full":"Carrer de Fran\u00c7a (de), 18 Catllar Tarragona 43764",
    "addr:housenumber":"18",
    "addr:postcode":"43764",
    "addr:street":"Carrer De Franc\u0327A De",
    "iso:country":"ES",
    "sg:address":"Carrer de Fran\u00c7a (de), 18",
    "sg:city":"Catllar",
    "sg:orig_category":"Arquitectos",
    "sg:phone":"+34 977 65 33 70",
    "sg:postcode":"43764",
    "sg:province":"Tarragona",
    "wof:name":"Mercade Porta Joan",
    "wof:placetype":"venue"
},
  "geometry": {"coordinates":[1.3257169724,41.1749382019],"type":"Point"}
}