{
  "type": "Feature",
  "properties": {
    "addr:full":"Avgd Born, Des, 5 Soller Islas Baleares 07100",
    "addr:postcode":"07100",
    "iso:country":"ES",
    "sg:address":"Avgd Born, Des, 5",
    "sg:city":"Soller",
    "sg:orig_category":"Centros De Coordinaci\u00d3n",
    "sg:phone":"+34 971 63 05 80",
    "sg:postcode":"07100",
    "sg:province":"Islas Baleares",
    "wof:name":"Sucursal Gestoria Gil De Soller C.b.",
    "wof:placetype":"venue"
},
  "geometry": {"coordinates":[2.7147779465,39.7659072876],"type":"Point"}
}