{
  "type": "Feature",
  "properties": {
    "iso:country":"ES",
    "sg:address":"Calle de Eduardo Requenas, 9",
    "sg:city":"Madrid",
    "sg:orig_category":"Farmacias",
    "sg:phone":"+34 914 78 94 74",
    "sg:postcode":"28053",
    "sg:province":"Madrid",
    "wof:name":"Hernando Valdizan Felipa",
    "wof:placetype":"venue"
},
  "geometry": {"coordinates":[-3.6656172276,40.3905563354],"type":"Point"}
}