{
  "type": "Feature",
  "properties": {
    "iso:country":"ES",
    "sg:address":"Calle de Reina Fabiola, 15",
    "sg:city":"Callosa Segura",
    "sg:orig_category":"Agentes, Concesionarios Y Sucursales De Veh\u00cdculos",
    "sg:phone":"+34 965 31 00 85",
    "sg:postcode":"03360",
    "sg:province":"Alicante",
    "wof:name":"Talleres Cantos S.l.",
    "wof:placetype":"venue"
},
  "geometry": {"coordinates":[-0.8724079728,38.1240348816],"type":"Point"}
}