{
  "type": "Feature",
  "properties": {
    "addr:full":"Calle de Cervantes, 10 Navalmoral Mata C\u00e1ceres 10300",
    "addr:housenumber":"10",
    "addr:postcode":"10300",
    "addr:street":"Calle De Cervantes;Ca\u0301Ceres",
    "iso:country":"ES",
    "sg:address":"Calle de Cervantes, 10",
    "sg:city":"Navalmoral Mata",
    "sg:orig_category":"Molduras, Junquillos, Listones Y Molduras Perforadas",
    "sg:phone":"+34 927 53 01 06",
    "sg:postcode":"10300",
    "sg:province":"C\u00e1ceres",
    "wof:name":"Garcia Gonzalez Angel",
    "wof:placetype":"venue"
},
  "geometry": {"coordinates":[-5.539706707,39.8922042847],"type":"Point"}
}