{
  "type": "Feature",
  "properties": {
    "addr:full":"Ctra Bilbao, 65 Miranda Ebro Burgos 09200",
    "addr:housenumber":"65",
    "addr:postcode":"09200",
    "addr:street":"Ctra Bilbao",
    "iso:country":"ES",
    "sg:address":"Ctra Bilbao, 65",
    "sg:city":"Miranda Ebro",
    "sg:orig_category":"Molduras, Junquillos, Listones Y Molduras Perforadas",
    "sg:phone":"+34 947 31 41 83",
    "sg:postcode":"09200",
    "sg:province":"Burgos",
    "wof:name":"Novoa Arroniz Yolanda",
    "wof:placetype":"venue"
},
  "geometry": {"coordinates":[-2.9516088963,42.6929512024],"type":"Point"}
}