{
  "type": "Feature",
  "properties": {
    "addr:full":"Rbla Ribatallada, 36 S. Cugat Valles Barcelona 08172",
    "addr:housenumber":"36",
    "addr:postcode":"08172",
    "addr:street":"Rbla Ribatallada;S. Cugat Valles Barcelona",
    "iso:country":"ES",
    "sg:address":"Rbla Ribatallada, 36",
    "sg:city":"S. Cugat Valles",
    "sg:orig_category":"Partidos Pol\u00cdticos",
    "sg:phone":"+34 935 89 39 45",
    "sg:postcode":"08172",
    "sg:province":"Barcelona",
    "wof:name":"Partido Popular",
    "wof:placetype":"venue"
},
  "geometry": {"coordinates":[2.0808138847,41.4666824341],"type":"Point"}
}