{
  "type": "Feature",
  "properties": {
    "addr:full":"Calle de Garcia Goyena, 7 Tafalla Navarra 31300",
    "addr:housenumber":"7",
    "addr:postcode":"31300",
    "addr:street":"Calle De Garcia Goyena",
    "iso:country":"ES",
    "sg:address":"Calle de Garcia Goyena, 7",
    "sg:city":"Tafalla",
    "sg:orig_category":"Molduras, Junquillos, Listones Y Molduras Perforadas",
    "sg:phone":"+34 948 70 10 24",
    "sg:postcode":"31300",
    "sg:province":"Navarra",
    "wof:name":"Go\u00f1i Murillo Jose",
    "wof:placetype":"venue"
},
  "geometry": {"coordinates":[-1.6759159565,42.5266799927],"type":"Point"}
}