{
  "type": "Feature",
  "properties": {
    "addr:full":"Calle de Victor Gorzo, 5 Bejar Salamanca 37700",
    "addr:housenumber":"5",
    "addr:postcode":"37700",
    "addr:street":"Calle De Victor Gorzo",
    "iso:country":"ES",
    "sg:address":"Calle de Victor Gorzo, 5",
    "sg:city":"Bejar",
    "sg:orig_category":"Postigos, Persianas Y Celos\u00cdas",
    "sg:phone":"+34 923 40 39 24",
    "sg:postcode":"37700",
    "sg:province":"Salamanca",
    "wof:name":"Garcia Garcia Pablo",
    "wof:placetype":"venue"
},
  "geometry": {"coordinates":[-5.7692890167,40.3880386353],"type":"Point"}
}