{
  "type": "Feature",
  "properties": {
    "addr:full":"Calle de Ingleses, 21 Santovenia Pisuerga Valladolid 47155",
    "addr:housenumber":"21",
    "addr:postcode":"47155",
    "addr:street":"Calle De Ingleses",
    "iso:country":"ES",
    "sg:address":"Calle de Ingleses, 21",
    "sg:city":"Santovenia Pisuerga",
    "sg:orig_category":"Productores Recolectores, Venta Directa De Vinos",
    "sg:phone":"+34 983 25 03 29",
    "sg:postcode":"47155",
    "sg:province":"Valladolid",
    "wof:name":"Compa\u00f1ia De Vino Miguel Martin S.l.",
    "wof:placetype":"venue"
},
  "geometry": {"coordinates":[-4.680398941,41.6904716492],"type":"Point"}
}