{
  "type": "Feature",
  "properties": {
    "addr:full":"Calle de Mayor, 21 Lumbier Navarra 31440",
    "addr:housenumber":"21",
    "addr:postcode":"31440",
    "addr:street":"Calle De Mayor",
    "iso:country":"ES",
    "sg:address":"Calle de Mayor, 21",
    "sg:city":"Lumbier",
    "sg:orig_category":"Electrodom\u00c9sticos (al Por Menor)",
    "sg:phone":"+34 948 88 02 55",
    "sg:postcode":"31440",
    "sg:province":"Navarra",
    "wof:name":"Pedro Ustarroz S.l.",
    "wof:placetype":"venue"
},
  "geometry": {"coordinates":[-1.3073849678,42.6524810791],"type":"Point"}
}