{
  "type": "Feature",
  "properties": {
    "iso:country":"ES",
    "sg:address":"Carrer de L'avenir, 10",
    "sg:city":"Barcelona",
    "sg:orig_category":"Frutas, Legumbres Frescas Y Tempranas (al Por Menor)",
    "sg:phone":"+34 932 09 89 78",
    "sg:postcode":"08006",
    "sg:province":"Barcelona",
    "wof:name":"Hurtado Dominguez Vicente",
    "wof:placetype":"venue"
},
  "geometry": {"coordinates":[2.1492726803,41.3972625732],"type":"Point"}
}