{
  "type": "Feature",
  "properties": {
    "iso:country":"ES",
    "sg:address":"Pg Dintre (de), 23",
    "sg:city":"Blanes",
    "sg:orig_category":"Poller\u00cda Y Caza (al Por Menor)",
    "sg:phone":"+34 972 33 04 59",
    "sg:postcode":"17300",
    "sg:province":"Girona",
    "wof:name":"Maso Pujadas Jaime",
    "wof:placetype":"venue"
},
  "geometry": {"coordinates":[2.7918670177,41.6739768982],"type":"Point"}
}