{
  "type": "Feature",
  "properties": {
    "iso:country":"ES",
    "sg:address":"Calle de Mariana De Pineda, 45",
    "sg:city":"Ibi",
    "sg:orig_category":"Venta, Instalaci\u00d3n De Calefacci\u00d3n",
    "sg:phone":"+34 965 55 07 03",
    "sg:postcode":"03440",
    "sg:province":"Alicante",
    "wof:name":"Fontaneria Bornay S.l.",
    "wof:placetype":"venue"
},
  "geometry": {"coordinates":[-0.5678989887,38.62292099],"type":"Point"}
}