{
  "type": "Feature",
  "properties": {
    "addr:full":"Calle de Aragon, 1 Corrales Cantabria 39400",
    "addr:housenumber":"1",
    "addr:postcode":"39400",
    "addr:street":"Calle De Aragon",
    "iso:country":"ES",
    "sg:address":"Calle de Aragon, 1",
    "sg:city":"Corrales",
    "sg:orig_category":"Abogados",
    "sg:phone":"+34 942 84 18 85",
    "sg:postcode":"39400",
    "sg:province":"Cantabria",
    "wof:name":"Alonso Sanchez Bernardo Maria",
    "wof:placetype":"venue"
},
  "geometry": {"coordinates":[-4.0691828728,43.2588005066],"type":"Point"}
}