{
  "type": "Feature",
  "properties": {
    "iso:country":"ES",
    "sg:address":"Calle de Alferez Provisional, 16",
    "sg:city":"Palmas De Gran Canaria",
    "sg:orig_category":"Fabricaci\u00d3n De Distribuidores Autom\u00c1ticos",
    "sg:phone":"+34 928 42 25 69",
    "sg:postcode":"35019",
    "sg:province":"Las Palmas",
    "wof:name":"Rodriguez Morales Alvaro",
    "wof:placetype":"venue"
},
  "geometry": {"coordinates":[-15.4486722946,28.101026535],"type":"Point"}
}