{
  "type": "Feature",
  "properties": {
    "addr:full":"Rua Peregrino (do), S/n Sarria Lugo 27600",
    "addr:housenumber":"/ n",
    "addr:postcode":"27600",
    "addr:street":"Rua Peregrino Do S",
    "iso:country":"ES",
    "sg:address":"Rua Peregrino (do), S/n",
    "sg:city":"Sarria",
    "sg:orig_category":"Centros De Educaci\u00d3n Especial",
    "sg:phone":"+34 982 53 04 99",
    "sg:postcode":"27600",
    "sg:province":"Lugo",
    "wof:name":"Colexio De Educacion Infantil E Primaria Frei Luis De Granada",
    "wof:placetype":"venue"
},
  "geometry": {"coordinates":[-7.4095158577,42.7754859924],"type":"Point"}
}