{
  "type": "Feature",
  "properties": {
    "addr:full":"Rua Francisco Escaneo, 13 Bueu Pontevedra 36930",
    "addr:housenumber":"13",
    "addr:postcode":"36930",
    "addr:street":"Rua Francisco Escaneo",
    "iso:country":"ES",
    "sg:address":"Rua Francisco Escaneo, 13",
    "sg:city":"Bueu",
    "sg:orig_category":"Comercio, Reparaci\u00d3n De Motocicletas, Bicicletas Y Piezas Sueltas",
    "sg:phone":"+34 986 32 28 26",
    "sg:postcode":"36930",
    "sg:province":"Pontevedra",
    "wof:name":"Rioboo Y Abal C.b.",
    "wof:placetype":"venue"
},
  "geometry": {"coordinates":[-8.7917613983,42.3261985779],"type":"Point"}
}