{
  "type": "Feature",
  "properties": {
    "iso:country":"ES",
    "sg:address":"Playa De Levante, 3",
    "sg:city":"Torre Mar",
    "sg:orig_category":"Centros Empresariales",
    "sg:phone":"+34 952 54 21 12",
    "sg:postcode":"29740",
    "sg:province":"M\u00e1laga",
    "wof:name":"Teditres S.l.",
    "wof:placetype":"venue"
},
  "geometry": {"coordinates":[-4.3522791862,36.7177505493],"type":"Point"}
}