{
  "type": "Feature",
  "properties": {
    "addr:full":"Calle de Larga, 50 Chipiona C\u00e1diz 11550",
    "addr:housenumber":"50",
    "addr:postcode":"11550",
    "addr:street":"Calle De Larga",
    "iso:country":"ES",
    "sg:address":"Calle de Larga, 50",
    "sg:city":"Chipiona",
    "sg:orig_category":"Empresarios",
    "sg:phone":"+34 956 37 16 60",
    "sg:postcode":"11550",
    "sg:province":"C\u00e1diz",
    "wof:name":"Fundacion Red Andalucia Emprende",
    "wof:placetype":"venue"
},
  "geometry": {"coordinates":[-6.4355988503,36.7400627136],"type":"Point"}
}