{
  "type": "Feature",
  "properties": {
    "addr:full":"Calle de Toro, S/n Cubo De Tierra Del Vino Zamora 49710",
    "addr:housenumber":"/ n",
    "addr:postcode":"49710",
    "addr:street":"Calle De Toro S",
    "iso:country":"ES",
    "sg:address":"Calle de Toro, S/n",
    "sg:city":"Cubo De Tierra Del Vino",
    "sg:orig_category":"Supermercados Y Hipermercados",
    "sg:phone":"+34 980 57 73 48",
    "sg:postcode":"49710",
    "sg:province":"Zamora",
    "wof:name":"Hernandez Pozo Manuel",
    "wof:placetype":"venue"
},
  "geometry": {"coordinates":[-5.7103538513,41.2548408508],"type":"Point"}
}