{
  "type": "Feature",
  "properties": {
    "iso:country":"ES",
    "sg:address":"Avda Monegros, 24",
    "sg:city":"Huesca",
    "sg:orig_category":"Aparatos E Instalaci\u00d3n De Regad\u00cdos",
    "sg:phone":"+34 974 22 46 46",
    "sg:postcode":"22005",
    "sg:province":"Huesca",
    "wof:name":"Riegos Y Contratas La Hoya S.l.",
    "wof:placetype":"venue"
},
  "geometry": {"coordinates":[-0.4032329917,42.1320419312],"type":"Point"}
}