{
  "type": "Feature",
  "properties": {
    "addr:full":"Calle de Mayor, 27 Irun Guip\u00f9zcoa 20304",
    "addr:housenumber":"27",
    "addr:postcode":"20304",
    "addr:street":"Calle De Mayor;Guipu\u0300Zcoa",
    "iso:country":"ES",
    "sg:address":"Calle de Mayor, 27",
    "sg:city":"Irun",
    "sg:orig_category":"Escayola Y Productos De Escayola (fabricaci\u00d3n, Al Por Mayor)",
    "sg:phone":"+34 943 62 21 51",
    "sg:postcode":"20304",
    "sg:province":"Guip\u00f9zcoa",
    "wof:name":"Moreno Yesos C.b.",
    "wof:placetype":"venue"
},
  "geometry": {"coordinates":[-1.7907719612,43.3381118774],"type":"Point"}
}