{
  "type": "Feature",
  "properties": {
    "addr:full":"Rua Gomez Ulla (de), 16 Santiago De Compostela La Coru\u00f1a 15702",
    "addr:postcode":"15702",
    "addr:street":"Rua Gomez;Corun\u0303A",
    "iso:country":"ES",
    "sg:address":"Rua Gomez Ulla (de), 16",
    "sg:city":"Santiago De Compostela",
    "sg:orig_category":"Comercio De Piezas De Recambio Y De Accesorios De Veh\u00cdculos, Veh\u00cdculos Industriales",
    "sg:phone":"+34 981 58 80 70",
    "sg:postcode":"15702",
    "sg:province":"La Coru\u00f1a",
    "sg:website":"www.hcvotero.com",
    "wof:name":"Hijos De C. V. Otero S. A.",
    "wof:placetype":"venue"
},
  "geometry": {"coordinates":[-8.5430965424,42.8747558594],"type":"Point"}
}