{
  "type": "Feature",
  "properties": {
    "iso:country":"ES",
    "sg:address":"Calle de Pablo Iglesias, 42",
    "sg:city":"Alacant",
    "sg:orig_category":"Arquitectos",
    "sg:phone":"+34 965 21 26 02",
    "sg:postcode":"03004",
    "sg:province":"Alicante",
    "wof:name":"Bmd Arquitectos S.l.",
    "wof:placetype":"venue"
},
  "geometry": {"coordinates":[-0.4889000058,38.3490371704],"type":"Point"}
}