{
  "type": "Feature",
  "properties": {
    "iso:country":"ES",
    "sg:address":"Calle de Compas, 3",
    "sg:city":"Coin",
    "sg:orig_category":"Papeler\u00cdas, Librer\u00cdas",
    "sg:phone":"+34 952 45 38 33",
    "sg:postcode":"29100",
    "sg:province":"M\u00e1laga",
    "wof:name":"Clavijo Clavijo Gabriel",
    "wof:placetype":"venue"
},
  "geometry": {"coordinates":[-4.7576842308,36.659740448],"type":"Point"}
}