{
  "type": "Feature",
  "properties": {
    "addr:full":"Calle de Arsuaga, 2 Bilbao Vizcaya 48004",
    "addr:housenumber":"2",
    "addr:postcode":"48004",
    "addr:street":"Calle De Arsuaga",
    "iso:country":"ES",
    "sg:address":"Calle de Arsuaga, 2",
    "sg:city":"Bilbao",
    "sg:orig_category":"Molduras, Junquillos, Listones Y Molduras Perforadas",
    "sg:phone":"+34 944 73 48 55",
    "sg:postcode":"48004",
    "sg:province":"Vizcaya",
    "wof:name":"Fano Martin Jose",
    "wof:placetype":"venue"
},
  "geometry": {"coordinates":[-2.9115664959,43.2534980774],"type":"Point"}
}