{
  "type": "Feature",
  "properties": {
    "iso:country":"ES",
    "sg:address":"Calle de Sargento Provisional, 18",
    "sg:city":"Coru\u00d1a",
    "sg:orig_category":"Electrodom\u00c9sticos (al Por Menor)",
    "sg:phone":"+34 981 24 13 09",
    "sg:postcode":"15007",
    "sg:province":"La Coru\u00f1a",
    "wof:name":"Rodriguez Quindimil Jose Maria",
    "wof:placetype":"venue"
},
  "geometry": {"coordinates":[-8.4159069061,43.3571434021],"type":"Point"}
}