{
  "type": "Feature",
  "properties": {
    "iso:country":"ES",
    "sg:address":"Avda Ciudad De Barcelona, 91",
    "sg:city":"Madrid",
    "sg:orig_category":"Aceites Y Grasas Alimentarias (fabricaci\u00d3n, Al Por Mayor)",
    "sg:phone":"+34 915 51 00 00",
    "sg:postcode":"28007",
    "sg:province":"Madrid",
    "wof:name":"Hijos De Valentin Alameda S. L.",
    "wof:placetype":"venue"
},
  "geometry": {"coordinates":[-3.6721670628,40.40001297],"type":"Point"}
}