{
  "type": "Feature",
  "properties": {
    "iso:country":"ES",
    "sg:address":"Calle de Libertad, 12",
    "sg:city":"Arganda",
    "sg:orig_category":"Fotocopias, Reprograf\u00cda",
    "sg:phone":"+34 918 70 31 91",
    "sg:postcode":"28500",
    "sg:province":"Madrid",
    "wof:name":"Copisteria Arganda Documento 2000 S.l",
    "wof:placetype":"venue"
},
  "geometry": {"coordinates":[-3.4372079372,40.3015441895],"type":"Point"}
}