{
  "type": "Feature",
  "properties": {
    "addr:full":"Rua Rosaleda, 11 Melide A Coru\u00f1a 15800",
    "addr:housenumber":"11",
    "addr:postcode":"15800",
    "addr:street":"Rua Rosaleda;Corun\u0303A",
    "iso:country":"ES",
    "sg:address":"Rua Rosaleda, 11",
    "sg:city":"Melide",
    "sg:classifiers":[
        {
            "category":"Manufacturing",
            "subcategory":"Building Materials",
            "type":"Manufacturing & Wholesale Goods"
        }
    ],
    "sg:phone":"+34 981 50 57 97",
    "sg:postcode":"15800",
    "sg:province":"A Coru\u00f1a",
    "sg:tags":[
        "de",
        "industrial",
        "alquiler"
    ],
    "wof:name":"Suministros Industriales Cire S.l.",
    "wof:placetype":"venue"
},
  "geometry": {"coordinates":[-8.014342308,42.9131393433],"type":"Point"}
}