{
  "type": "Feature",
  "properties": {
    "addr:full":"Avda Constitucion (de La), 2 Lorqui Murcia 30564",
    "addr:housenumber":"2",
    "addr:postcode":"30564",
    "addr:street":"Avda Constitucion De La",
    "iso:country":"ES",
    "sg:address":"Avda Constitucion (de La), 2",
    "sg:city":"Lorqui",
    "sg:orig_category":"Bancos",
    "sg:phone":"+34 968 69 08 26",
    "sg:postcode":"30564",
    "sg:province":"Murcia",
    "wof:name":"Banco De Valencia S.a.",
    "wof:placetype":"venue"
},
  "geometry": {"coordinates":[-1.2549489737,38.0817947388],"type":"Point"}
}