{
  "type": "Feature",
  "properties": {
    "iso:country":"ES",
    "sg:address":"Carr Elias Tormo (d'), 7",
    "sg:city":"Albaida",
    "sg:orig_category":"Imprenta",
    "sg:phone":"+34 962 90 14 18",
    "sg:postcode":"46860",
    "sg:province":"Valencia",
    "wof:name":"Imprentas Simo S.l.",
    "wof:placetype":"venue"
},
  "geometry": {"coordinates":[-0.5192750096,38.841091156],"type":"Point"}
}