{
  "type": "Feature",
  "properties": {
    "addr:full":"Calle de Valdecanillas, 27 Madrid Madrid 28037",
    "addr:housenumber":"27",
    "addr:postcode":"madrid;28037",
    "addr:street":"Calle De Valdecanillas",
    "iso:country":"ES",
    "sg:address":"Calle de Valdecanillas, 27",
    "sg:city":"Madrid",
    "sg:orig_category":"Molduras, Junquillos, Listones Y Molduras Perforadas",
    "sg:phone":"+34 913 27 43 44",
    "sg:postcode":"28037",
    "sg:province":"Madrid",
    "wof:name":"H.c.m.restaurante S.l.",
    "wof:placetype":"venue"
},
  "geometry": {"coordinates":[-3.6283969879,40.4312362671],"type":"Point"}
}