{
  "type": "Feature",
  "properties": {
    "addr:full":"Calle de Joaquin Costa, 16 Vall D'uixo Castell\u00f3n 12600",
    "addr:housenumber":"16",
    "addr:postcode":"12600",
    "addr:street":"Calle De Joaquin Costa",
    "iso:country":"ES",
    "sg:address":"Calle de Joaquin Costa, 16",
    "sg:city":"Vall D'uixo",
    "sg:orig_category":"Fabricaci\u00d3n De Cortinas Y Visillos",
    "sg:phone":"+34 964 69 61 64",
    "sg:postcode":"12600",
    "sg:province":"Castell\u00f3n",
    "wof:name":"Bachero Ten Maria Del Pilar",
    "wof:placetype":"venue"
},
  "geometry": {"coordinates":[-0.2338237017,39.8249702454],"type":"Point"}
}