{
  "type": "Feature",
  "properties": {
    "addr:full":"Gerena-aznalcollar, Km. 0004,3 Gerena Sevilla 41860",
    "addr:postcode":"41860",
    "addr:street":"Gerena-Aznalcollar Km. 0004,3",
    "iso:country":"ES",
    "sg:address":"Gerena-aznalcollar, Km. 0004,3",
    "sg:city":"Gerena",
    "sg:orig_category":"Cr\u00cda De Animales",
    "sg:phone":"+34 955 95 07 56",
    "sg:postcode":"41860",
    "sg:province":"Sevilla",
    "wof:name":"Ganaderia Agricola Granja Del Rio S.c.a.",
    "wof:placetype":"venue"
},
  "geometry": {"coordinates":[-6.1739115715,37.5413551331],"type":"Point"}
}