{
  "type": "Feature",
  "properties": {
    "addr:full":"Calle de Zabaleta, 6 Donostia-san Sebastian Guip\u00f9zcoa 20002",
    "addr:housenumber":"6",
    "addr:postcode":"20002",
    "addr:street":"Calle De Zabaleta",
    "iso:country":"ES",
    "sg:address":"Calle de Zabaleta, 6",
    "sg:city":"Donostia-san Sebastian",
    "sg:orig_category":"Institutos De Belleza",
    "sg:phone":"+34 943 28 32 61",
    "sg:postcode":"20002",
    "sg:province":"Guip\u00f9zcoa",
    "wof:name":"Raquel Gonzalez Rada Y Otra C.b.",
    "wof:placetype":"venue"
},
  "geometry": {"coordinates":[-1.9763300419,43.3227653503],"type":"Point"}
}