{
  "type": "Feature",
  "properties": {
    "iso:country":"ES",
    "sg:address":"Calle de Secundino Lorenzo, 1",
    "sg:city":"Marin",
    "sg:orig_category":"M\u00c9dicos: Estomatolog\u00cda",
    "sg:phone":"+34 986 88 14 47",
    "sg:postcode":"36900",
    "sg:province":"Pontevedra",
    "wof:name":"Verdu Casal Juan Antonio",
    "wof:placetype":"venue"
},
  "geometry": {"coordinates":[-8.7035799026,42.3923072815],"type":"Point"}
}