{
  "type": "Feature",
  "properties": {
    "iso:country":"ES",
    "sg:address":"Plaz Antiguo Reino De Valencia, S/n",
    "sg:city":"Aldaia",
    "sg:orig_category":"Sanatorios M\u00c9dico",
    "sg:phone":"+34 961 51 27 98",
    "sg:postcode":"46960",
    "sg:province":"Valencia",
    "wof:name":"Generalitat Valenciana",
    "wof:placetype":"venue"
},
  "geometry": {"coordinates":[-0.4671939909,39.4622802734],"type":"Point"}
}