{
  "type": "Feature",
  "properties": {
    "addr:full":"Plaz Mayor, 12 Villadiego Burgos 09120",
    "addr:housenumber":"12",
    "addr:postcode":"09120",
    "addr:street":"Plaz Mayor",
    "iso:country":"ES",
    "sg:address":"Plaz Mayor, 12",
    "sg:city":"Villadiego",
    "sg:orig_category":"Farmacias",
    "sg:phone":"+34 947 36 03 76",
    "sg:postcode":"09120",
    "sg:province":"Burgos",
    "wof:name":"Martinez De La Mata De Lozar Maria Concepcion",
    "wof:placetype":"venue"
},
  "geometry": {"coordinates":[-4.0110201836,42.5152359009],"type":"Point"}
}