{
  "type": "Feature",
  "properties": {
    "iso:country":"ES",
    "sg:address":"Carrer de Cuba, 66",
    "sg:city":"Mataro",
    "sg:orig_category":"Tintes (fabricaci\u00d3n, Al Por Mayor)",
    "sg:phone":"+34 937 57 59 79",
    "sg:postcode":"08302",
    "sg:province":"Barcelona",
    "wof:name":"Ecologic-net Tintoreria S.l.",
    "wof:placetype":"venue"
},
  "geometry": {"coordinates":[2.4409630299,41.5367431641],"type":"Point"}
}