{
  "type": "Feature",
  "properties": {
    "iso:country":"ES",
    "sg:address":"G.v. Corts Catalanes, 1176",
    "sg:city":"Barcelona",
    "sg:orig_category":"Mudanzas",
    "sg:phone":"+34 933 49 18 71",
    "sg:postcode":"08020",
    "sg:province":"Barcelona",
    "wof:name":"Mudanzas Y Servicios Arnau S.l.",
    "wof:placetype":"venue"
},
  "geometry": {"coordinates":[2.2094969749,41.4196624756],"type":"Point"}
}