{
  "type": "Feature",
  "properties": {
    "addr:full":"Carrer de Valldonzella, 43 Barcelona Barcelona 08001",
    "addr:housenumber":"43",
    "addr:postcode":"08001",
    "addr:street":"Carrer De Valldonzella",
    "iso:country":"ES",
    "sg:address":"Carrer de Valldonzella, 43",
    "sg:city":"Barcelona",
    "sg:orig_category":"Peluqueros: De Se\u00d1oras",
    "sg:phone":"+34 933 18 61 42",
    "sg:postcode":"08001",
    "sg:province":"Barcelona",
    "wof:name":"Martinez Marquez Leonor",
    "wof:placetype":"venue"
},
  "geometry": {"coordinates":[2.1646080017,41.3828582764],"type":"Point"}
}