{
  "type": "Feature",
  "properties": {
    "iso:country":"ES",
    "sg:address":"Glor Sta Barbara, 4",
    "sg:city":"Malaga",
    "sg:orig_category":"Asesor\u00cda Sobre Comunicaci\u00d3n De Empresas",
    "sg:phone":"+34 952 24 53 90",
    "sg:postcode":"29004",
    "sg:province":"M\u00e1laga",
    "wof:name":"Targestur S.l.",
    "wof:placetype":"venue"
},
  "geometry": {"coordinates":[-4.474984169,36.6674613953],"type":"Point"}
}