{
  "type": "Feature",
  "properties": {
    "iso:country":"ES",
    "sg:address":"Carrer de Infant Marti (l'), 119",
    "sg:city":"Terrassa",
    "sg:orig_category":"Molduras, Junquillos, Listones Y Molduras Perforadas",
    "sg:phone":"+34 937 88 10 90",
    "sg:postcode":"08224",
    "sg:province":"Barcelona",
    "wof:name":"Casas Fernandez Jose Manuel",
    "wof:placetype":"venue"
},
  "geometry": {"coordinates":[2.0025210381,41.5577125549],"type":"Point"}
}