{
  "type": "Feature",
  "properties": {
    "addr:full":"Carrer de Sant Josep, 64 S. Celoni Barcelona 08470",
    "addr:housenumber":"64",
    "addr:postcode":"08470",
    "addr:street":"Carrer De Sant Josep;S. Celoni Barcelona",
    "iso:country":"ES",
    "sg:address":"Carrer de Sant Josep, 64",
    "sg:city":"S. Celoni",
    "sg:orig_category":"Librer\u00cdas",
    "sg:phone":"+34 938 67 26 01",
    "sg:postcode":"08470",
    "sg:province":"Barcelona",
    "wof:name":"Barrios Martinez Emilia",
    "wof:placetype":"venue"
},
  "geometry": {"coordinates":[2.4917318821,41.6889266968],"type":"Point"}
}