{
  "type": "Feature",
  "properties": {
    "addr:full":"Ctra Logro\u00d1o Vitoria, 12 Fuenmayor La Rioja 26360",
    "addr:housenumber":"12",
    "addr:postcode":"26360",
    "addr:street":"Ctra Logron\u0303O Vitoria;Rioja",
    "iso:country":"ES",
    "sg:address":"Ctra Logro\u00d1o Vitoria, 12",
    "sg:city":"Fuenmayor",
    "sg:orig_category":"Mec\u00c1nico Del Autom\u00d3vil",
    "sg:phone":"+34 941 45 03 11",
    "sg:postcode":"26360",
    "sg:province":"La Rioja",
    "wof:name":"Alesanco Saez Pedro",
    "wof:placetype":"venue"
},
  "geometry": {"coordinates":[-2.5632781982,42.4640274048],"type":"Point"}
}