{
  "type": "Feature",
  "properties": {
    "iso:country":"ES",
    "sg:address":"Avda Torneo, 68",
    "sg:city":"Sevilla",
    "sg:orig_category":"Molduras, Junquillos, Listones Y Molduras Perforadas",
    "sg:phone":"+34 954 90 68 56",
    "sg:postcode":"41002",
    "sg:province":"Sevilla",
    "wof:name":"Vazquez Tallafel Juan Luis",
    "wof:placetype":"venue"
},
  "geometry": {"coordinates":[-6.0009388924,37.3976707458],"type":"Point"}
}