{
  "type": "Feature",
  "properties": {
    "addr:full":"Carr Petxines, S/n Perello Valencia 46420",
    "addr:housenumber":"s",
    "addr:postcode":"46420",
    "addr:street":"Carr Petxines;/ N",
    "iso:country":"ES",
    "sg:address":"Carr Petxines, S/n",
    "sg:city":"Perello",
    "sg:orig_category":"Electrodom\u00c9sticos (al Por Menor)",
    "sg:phone":"+34 961 77 00 79",
    "sg:postcode":"46420",
    "sg:province":"Valencia",
    "sg:website":"www.electrofont.com",
    "wof:name":"Font Baldovi Juanjose",
    "wof:placetype":"venue"
},
  "geometry": {"coordinates":[-0.2787559927,39.2763328552],"type":"Point"}
}