{
  "type": "Feature",
  "properties": {
    "addr:full":"Avda Nuestra Se\u00d1ora Del Pilar, 8 Binefar Huesca 22500",
    "addr:housenumber":"8",
    "addr:postcode":"22500",
    "addr:street":"Avda Nuestra Sen\u0303Ora Del Pilar",
    "iso:country":"ES",
    "sg:address":"Avda Nuestra Se\u00d1ora Del Pilar, 8",
    "sg:city":"Binefar",
    "sg:orig_category":"Droguer\u00cdas (al Por Menor)",
    "sg:phone":"+34 974 43 10 48",
    "sg:postcode":"22500",
    "sg:province":"Huesca",
    "wof:name":"Hernandez Alfaro Jose",
    "wof:placetype":"venue"
},
  "geometry": {"coordinates":[0.2925373912,41.8518791199],"type":"Point"}
}