{
  "type": "Feature",
  "properties": {
    "iso:country":"ES",
    "sg:address":"Av Sant Miquel Del Pui, 3",
    "sg:city":"Pobla Segur",
    "sg:orig_category":"Panader\u00cdas, Panader\u00cdas",
    "sg:phone":"+34 973 68 01 83",
    "sg:postcode":"25500",
    "sg:province":"Lleida",
    "wof:name":"Gracia Escola Valero",
    "wof:placetype":"venue"
},
  "geometry": {"coordinates":[0.9664350152,42.2486915588],"type":"Point"}
}