{
  "type": "Feature",
  "properties": {
    "iso:country":"ES",
    "sg:address":"Calle de Valle De Tobalina, 30",
    "sg:city":"Madrid",
    "sg:orig_category":"Fabricaci\u00d3n De Etiquetas",
    "sg:phone":"+34 917 97 00 62",
    "sg:postcode":"28021",
    "sg:province":"Madrid",
    "wof:name":"Escayolas Y Aislamientos Villaverde, S.l.",
    "wof:placetype":"venue"
},
  "geometry": {"coordinates":[-3.7151699066,40.3372993469],"type":"Point"}
}