{
  "type": "Feature",
  "properties": {
    "iso:country":"ES",
    "sg:address":"Calle de Venta De La Estrella, 6",
    "sg:city":"Vitoria-gasteiz",
    "sg:orig_category":"Transporte En General",
    "sg:phone":"+34 945 14 69 54",
    "sg:postcode":"01006",
    "sg:province":"\u00c1lava",
    "wof:name":"Exclusivas Jesus Y Javier Sl",
    "wof:placetype":"venue"
},
  "geometry": {"coordinates":[-2.6575090885,42.836151123],"type":"Point"}
}