{
  "type": "Feature",
  "properties": {
    "addr:full":"Calle de La Peza, 239 Albolote Granada 18220",
    "addr:housenumber":"239",
    "addr:postcode":"18220",
    "addr:street":"Calle De La Peza",
    "iso:country":"ES",
    "sg:address":"Calle de La Peza, 239",
    "sg:city":"Albolote",
    "sg:orig_category":"Publicidad (soportes Y Gesti\u00d3n)",
    "sg:phone":"+34 958 46 75 96",
    "sg:postcode":"18220",
    "sg:province":"Granada",
    "wof:name":"Seriyani S.l.",
    "wof:placetype":"venue"
},
  "geometry": {"coordinates":[-3.6379239559,37.2225646973],"type":"Point"}
}