{
  "type": "Feature",
  "properties": {
    "addr:full":"Calle de Doctor Esquerdo, 47 Madrid Madrid 28028",
    "addr:housenumber":"47",
    "addr:postcode":"madrid;28028",
    "addr:street":"Calle De Doctor Esquerdo",
    "iso:country":"ES",
    "sg:address":"Calle de Doctor Esquerdo, 47",
    "sg:city":"Madrid",
    "sg:orig_category":"Apicultura",
    "sg:phone":"+34 915 74 52 40",
    "sg:postcode":"28028",
    "sg:province":"Madrid",
    "wof:name":"La Moderna Apicultura S. A.",
    "wof:placetype":"venue"
},
  "geometry": {"coordinates":[-3.6686763763,40.4234390259],"type":"Point"}
}