{
  "type": "Feature",
  "properties": {
    "iso:country":"ES",
    "sg:address":"Carrer de Mallorca, 496",
    "sg:city":"Barcelona",
    "sg:orig_category":"Cl\u00cdnicas Dentales",
    "sg:phone":"+34 932 47 21 74",
    "sg:postcode":"08013",
    "sg:province":"Barcelona",
    "wof:name":"Clinica Dental Margarit S.a.",
    "wof:placetype":"venue"
},
  "geometry": {"coordinates":[2.1802709103,41.4069442749],"type":"Point"}
}