{
  "type": "Feature",
  "properties": {
    "iso:country":"ES",
    "sg:address":"Avda Cayetano Del Toro, 10",
    "sg:city":"Cadiz",
    "sg:orig_category":"Inmobiliaria (agencias)",
    "sg:phone":"+34 956 26 16 23",
    "sg:postcode":"11010",
    "sg:province":"C\u00e1diz",
    "wof:name":"Hermanos Ramon Y Emilio Rodriguez De Trujillo S.l.",
    "wof:placetype":"venue"
},
  "geometry": {"coordinates":[-6.277630806,36.5071792603],"type":"Point"}
}