{
  "type": "Feature",
  "properties": {
    "addr:full":"Calle de General Valcarcel, 8 Mula Murcia 30170",
    "addr:housenumber":"8",
    "addr:postcode":"30170",
    "addr:street":"Calle De General Valcarcel",
    "iso:country":"ES",
    "sg:address":"Calle de General Valcarcel, 8",
    "sg:city":"Mula",
    "sg:orig_category":"Abogados",
    "sg:phone":"+34 968 63 70 11",
    "sg:postcode":"30170",
    "sg:province":"Murcia",
    "wof:name":"Palazon Garcia Pedro",
    "wof:placetype":"venue"
},
  "geometry": {"coordinates":[-1.5596116781,38.0951423645],"type":"Point"}
}