{
  "type": "Feature",
  "properties": {
    "addr:full":"Calle de Bocangel, 10 Madrid Madrid 28028",
    "addr:housenumber":"10",
    "addr:postcode":"madrid;28028",
    "addr:street":"Calle De Bocangel",
    "iso:country":"ES",
    "sg:address":"Calle de Bocangel, 10",
    "sg:city":"Madrid",
    "sg:orig_category":"Plomeros",
    "sg:phone":"+34 913 56 18 49",
    "sg:postcode":"28028",
    "sg:province":"Madrid",
    "wof:name":"Gordillo Cumplido Remedios",
    "wof:placetype":"venue"
},
  "geometry": {"coordinates":[-3.6636850834,40.4292411804],"type":"Point"}
}