{
  "type": "Feature",
  "properties": {
    "iso:country":"ES",
    "sg:address":"Carrer de Sol, 9",
    "sg:city":"Sitges",
    "sg:orig_category":"Empresas De Carpinter\u00cda",
    "sg:phone":"+34 938 94 28 37",
    "sg:postcode":"08870",
    "sg:province":"Barcelona",
    "wof:name":"Cristaleria Gimenez Subur S.l.",
    "wof:placetype":"venue"
},
  "geometry": {"coordinates":[1.8101969957,41.2397689819],"type":"Point"}
}