{
  "type": "Feature",
  "properties": {
    "addr:full":"Trva Alameda De Solano, S/n Chiclana De La Frontera C\u00e1diz 11130",
    "addr:housenumber":"s / n",
    "addr:postcode":"11130",
    "addr:street":"Trva Alameda De Solano",
    "iso:country":"ES",
    "sg:address":"Trva Alameda De Solano, S/n",
    "sg:city":"Chiclana De La Frontera",
    "sg:orig_category":"Garajes De Veh\u00cdculos",
    "sg:phone":"+34 956 40 09 00",
    "sg:postcode":"11130",
    "sg:province":"C\u00e1diz",
    "wof:name":"Salvado Morales Pedro",
    "wof:placetype":"venue"
},
  "geometry": {"coordinates":[-6.1462450027,36.4207801819],"type":"Point"}
}