{
  "type": "Feature",
  "properties": {
    "addr:full":"Avgd Pau (de La), 1 Grau I Platja Valencia 46730",
    "addr:postcode":"46730",
    "iso:country":"ES",
    "sg:address":"Avgd Pau (de La), 1",
    "sg:city":"Grau I Platja",
    "sg:orig_category":"Centros De Adelgazamiento Y De Est\u00c9tica",
    "sg:phone":"+34 962 84 09 32",
    "sg:postcode":"46730",
    "sg:province":"Valencia",
    "wof:name":"Carbo Borrull Jose Miguel",
    "wof:placetype":"venue"
},
  "geometry": {"coordinates":[-0.1664949954,38.9994888306],"type":"Point"}
}