{
  "type": "Feature",
  "properties": {
    "addr:full":"Carrer de Mallorca, 214 Barcelona Barcelona 08008",
    "addr:housenumber":"214",
    "addr:postcode":"08008",
    "addr:street":"Carrer De Mallorca",
    "iso:country":"ES",
    "sg:address":"Carrer de Mallorca, 214",
    "sg:city":"Barcelona",
    "sg:orig_category":"Centros Empresariales",
    "sg:phone":"+34 934 52 67 50",
    "sg:postcode":"08008",
    "sg:province":"Barcelona",
    "wof:name":"Joan Mons & Associats S.a.",
    "wof:placetype":"venue"
},
  "geometry": {"coordinates":[2.1589229107,41.3909111023],"type":"Point"}
}