{
  "type": "Feature",
  "properties": {
    "iso:country":"ES",
    "sg:address":"Calle de Castilla La Vieja (de), 3",
    "sg:city":"Fuenlabrada",
    "sg:orig_category":"Artes Gr\u00c1ficas, Artes Pl\u00c1sticas: Material Y Suministros (al Por Menor)",
    "sg:phone":"+34 916 15 41 40",
    "sg:postcode":"28941",
    "sg:province":"Madrid",
    "wof:name":"Trituracion Y Clasificacion Movil",
    "wof:placetype":"venue"
},
  "geometry": {"coordinates":[-3.800620079,40.2904930115],"type":"Point"}
}