{
  "type": "Feature",
  "properties": {
    "iso:country":"ES",
    "sg:address":"Pl Lluis Perpinya, 3",
    "sg:city":"Granollers",
    "sg:orig_category":"Talleres: Ropa A Medida",
    "sg:phone":"+34 938 70 05 95",
    "sg:postcode":"08401",
    "sg:province":"Barcelona",
    "wof:name":"Maso Prat Josep Maria",
    "wof:placetype":"venue"
},
  "geometry": {"coordinates":[2.2890119553,41.609287262],"type":"Point"}
}