{
  "type": "Feature",
  "properties": {
    "addr:full":"Calle de Alcala, 337 Madrid Madrid 28027",
    "addr:housenumber":"337",
    "addr:postcode":"28027",
    "addr:street":"Calle De Alcala",
    "iso:country":"ES",
    "sg:address":"Calle de Alcala, 337",
    "sg:city":"Madrid",
    "sg:orig_category":"Agencias De Viajes",
    "sg:phone":"+34 913 26 49 71",
    "sg:postcode":"28027",
    "sg:province":"Madrid",
    "sg:website":"www.halconviajes.com",
    "wof:name":"Viajes Halcon S.a.",
    "wof:placetype":"venue"
},
  "geometry": {"coordinates":[-3.6484439373,40.4332084656],"type":"Point"}
}