{
  "type": "Feature",
  "properties": {
    "addr:full":"Calle de Abrevadero, 10 Villaviciosa Odon Madrid 28670",
    "addr:housenumber":"10",
    "addr:postcode":"28670",
    "addr:street":"Calle De Abrevadero;Odon",
    "iso:country":"ES",
    "sg:address":"Calle de Abrevadero, 10",
    "sg:city":"Villaviciosa Odon",
    "sg:orig_category":"Piscinas, Accesorios, Suministros (fabricaci\u00d3n, Al Por Mayor)",
    "sg:phone":"+34 916 16 53 55",
    "sg:postcode":"28670",
    "sg:province":"Madrid",
    "wof:name":"Piscipool S.l.",
    "wof:placetype":"venue"
},
  "geometry": {"coordinates":[-3.8988358974,40.357219696],"type":"Point"}
}