{
  "type": "Feature",
  "properties": {
    "addr:full":"Avda Fernandez Latorre, 16 Coru\u00d1a La Coru\u00f1a 15006",
    "addr:housenumber":"16",
    "addr:postcode":"15006",
    "addr:street":"Avda Fernandez Latorre;La Corun\u0303A",
    "iso:country":"ES",
    "sg:address":"Avda Fernandez Latorre, 16",
    "sg:city":"Coru\u00d1a",
    "sg:orig_category":"Peluqueros: De Se\u00d1oras",
    "sg:phone":"+34 981 23 59 79",
    "sg:postcode":"15006",
    "sg:province":"La Coru\u00f1a",
    "wof:name":"Gacio Rivas Herminda",
    "wof:placetype":"venue"
},
  "geometry": {"coordinates":[-8.4045219421,43.3597259521],"type":"Point"}
}