{
  "type": "Feature",
  "properties": {
    "iso:country":"ES",
    "sg:address":"Barr Soborvila, S/n",
    "sg:city":"Outeiro Rei",
    "sg:classifiers":[
        {
            "category":"Taxi",
            "type":"Transportation"
        }
    ],
    "sg:phone":"+34 982 39 34 34",
    "sg:postcode":"27150",
    "sg:province":"Lugo",
    "wof:name":"Carballido Dominguez Luis",
    "wof:placetype":"venue"
},
  "geometry": {"coordinates":[-7.6123452187,43.1025810242],"type":"Point"}
}