{
  "type": "Feature",
  "properties": {
    "iso:country":"ES",
    "sg:address":"Calle de Rondalla Santa Cecilia, 1",
    "sg:city":"Molina",
    "sg:orig_category":"Cooperativas Agr\u00cdcolas",
    "sg:phone":"+34 949 83 16 14",
    "sg:postcode":"19300",
    "sg:province":"Guadalajara",
    "wof:name":"S.a.t. Comercial Agropecuaria Alcarre\u00f1a",
    "wof:placetype":"venue"
},
  "geometry": {"coordinates":[-1.8857929707,40.8425445557],"type":"Point"}
}