{
  "type": "Feature",
  "properties": {
    "iso:country":"ES",
    "sg:address":"Carrer de Fran\u00c7a, 45",
    "sg:city":"Terrassa",
    "sg:orig_category":"Promotores Constructores",
    "sg:phone":"+34 937 31 64 02",
    "sg:postcode":"08228",
    "sg:province":"Barcelona",
    "wof:name":"An 6 Hu Empresa Constructora S.l.",
    "wof:placetype":"venue"
},
  "geometry": {"coordinates":[2.0467581749,41.5387458801],"type":"Point"}
}