{
  "type": "Feature",
  "properties": {
    "addr:full":"Avda Jose De Mora, 35 Baza Granada 18800",
    "addr:housenumber":"35",
    "addr:postcode":"18800",
    "addr:street":"Avda Jose De Mora",
    "iso:country":"ES",
    "sg:address":"Avda Jose De Mora, 35",
    "sg:city":"Baza",
    "sg:orig_category":"Librer\u00cdas",
    "sg:phone":"+34 958 70 19 76",
    "sg:postcode":"18800",
    "sg:province":"Granada",
    "wof:name":"Marin Sanchez Carmen",
    "wof:placetype":"venue"
},
  "geometry": {"coordinates":[-2.7696321011,37.4854354858],"type":"Point"}
}