{
  "type": "Feature",
  "properties": {
    "iso:country":"ES",
    "sg:address":"Calle de Veronica, 28",
    "sg:city":"Quintanar Rey",
    "sg:orig_category":"Promotores Constructores",
    "sg:phone":"+34 967 49 56 40",
    "sg:postcode":"16220",
    "sg:province":"Cuenca",
    "wof:name":"Ballesteros Y Escribano S.l.",
    "wof:placetype":"venue"
},
  "geometry": {"coordinates":[-1.9259459972,39.3452110291],"type":"Point"}
}