{
  "type": "Feature",
  "properties": {
    "iso:country":"ES",
    "sg:address":"Calle de Trinidad, 4",
    "sg:city":"Talavera Reina",
    "sg:orig_category":"Estilistas Y Estudios De Estilo De Corte Y Confecci\u00d3n",
    "sg:phone":"+34 925 81 32 58",
    "sg:postcode":"45600",
    "sg:province":"Toledo",
    "wof:name":"Diaz Oliva Julio",
    "wof:placetype":"venue"
},
  "geometry": {"coordinates":[-4.8273210526,39.9628372192],"type":"Point"}
}