{
  "type": "Feature",
  "properties": {
    "iso:country":"ES",
    "sg:address":"Calle de Sevilla, 26",
    "sg:city":"Monesterio",
    "sg:orig_category":"Reposter\u00cdas",
    "sg:phone":"+34 924 51 60 60",
    "sg:postcode":"06260",
    "sg:province":"Badajoz",
    "wof:name":"Delgado Granadero Eladio",
    "wof:placetype":"venue"
},
  "geometry": {"coordinates":[-6.2695660591,38.0868415833],"type":"Point"}
}