{
  "type": "Feature",
  "properties": {
    "addr:full":"Calle de Trinidad, 42 Ubeda Ja\u00e9n 23400",
    "addr:housenumber":"42",
    "addr:postcode":"23400",
    "addr:street":"Calle De Trinidad;Jae\u0301N",
    "iso:country":"ES",
    "sg:address":"Calle de Trinidad, 42",
    "sg:city":"Ubeda",
    "sg:orig_category":"Arquitectos",
    "sg:phone":"+34 953 75 22 48",
    "sg:postcode":"23400",
    "sg:province":"Ja\u00e9n",
    "wof:name":"Torre Roman Rogelio De La",
    "wof:placetype":"venue"
},
  "geometry": {"coordinates":[-3.3710730076,38.012462616],"type":"Point"}
}