{
  "type": "Feature",
  "properties": {
    "addr:full":"Calle de Cehegin, 13 Puerto Lumbreras Murcia 30890",
    "addr:housenumber":"13",
    "addr:postcode":"30890",
    "addr:street":"Calle De Cehegin",
    "iso:country":"ES",
    "sg:address":"Calle de Cehegin, 13",
    "sg:city":"Puerto Lumbreras",
    "sg:orig_category":"Contenedores (mercanc\u00cdas)",
    "sg:phone":"+34 968 40 09 26",
    "sg:postcode":"30890",
    "sg:province":"Murcia",
    "wof:name":"Garcia Garcia Juan Miguel",
    "wof:placetype":"venue"
},
  "geometry": {"coordinates":[-1.8032909632,37.5636062622],"type":"Point"}
}