{
  "type": "Feature",
  "properties": {
    "iso:country":"ES",
    "sg:address":"Calle de Subida Cuesta Piedra, 1",
    "sg:city":"Santa Cruz De Tenerife",
    "sg:classifiers":[
        {
            "category":"Personal",
            "subcategory":"Barber",
            "type":"Services"
        }
    ],
    "sg:phone":"+34 922 23 06 03",
    "sg:postcode":"38008",
    "sg:province":"Santa Cruz De Tenerife",
    "sg:tags":[
        "caballeros",
        "de",
        "peluqueros"
    ],
    "wof:name":"Cruz Corona Rodolfo",
    "wof:placetype":"venue"
},
  "geometry": {"coordinates":[-16.2726783752,28.4713001251],"type":"Point"}
}