{
  "type": "Feature",
  "properties": {
    "addr:full":"Canar Es, S/n Sta. Eularia Riu Islas Baleares 07840",
    "addr:housenumber":"s / n",
    "addr:postcode":"07840",
    "addr:street":"Islas Baleares",
    "iso:country":"ES",
    "sg:address":"Canar Es, S/n",
    "sg:city":"Sta. Eularia Riu",
    "sg:orig_category":"Promotores Constructores",
    "sg:phone":"+34 971 33 81 72",
    "sg:postcode":"07840",
    "sg:province":"Islas Baleares",
    "wof:name":"Construcciones Angel Jove S.a.",
    "wof:placetype":"venue"
},
  "geometry": {"coordinates":[1.547279954,38.9919815063],"type":"Point"}
}