{
  "type": "Feature",
  "properties": {
    "addr:full":"Carrer de Noguer, 3 Peguera Islas Baleares 07160",
    "addr:housenumber":"3",
    "addr:postcode":"07160",
    "addr:street":"Carrer De Noguer",
    "iso:country":"ES",
    "sg:address":"Carrer de Noguer, 3",
    "sg:city":"Peguera",
    "sg:orig_category":"Frutas, Legumbres Frescas Y Tempranas (al Por Menor)",
    "sg:phone":"+34 971 68 75 17",
    "sg:postcode":"07160",
    "sg:province":"Islas Baleares",
    "wof:name":"Fruites Paguera S.l.",
    "wof:placetype":"venue"
},
  "geometry": {"coordinates":[2.446723938,39.537689209],"type":"Point"}
}