{
  "type": "Feature",
  "properties": {
    "addr:full":"Ctra. Logro\u00f1o, Km. 0243,0 Almarza Soria 42160",
    "addr:postcode":"42160",
    "addr:street":"Ctra. Logron\u0303O Km. 0243,0",
    "iso:country":"ES",
    "sg:address":"Ctra. Logro\u00f1o, Km. 0243,0",
    "sg:city":"Almarza",
    "sg:orig_category":"Hoteles",
    "sg:phone":"+34 975 25 00 64",
    "sg:postcode":"42160",
    "sg:province":"Soria",
    "wof:name":"Vallehot S.l.",
    "wof:placetype":"venue"
},
  "geometry": {"coordinates":[-2.4878261089,41.9275436401],"type":"Point"}
}