{
  "type": "Feature",
  "properties": {
    "iso:country":"ES",
    "sg:address":"Calle de Albacete, 11",
    "sg:city":"Malaga",
    "sg:orig_category":"Veh\u00cdculos De Ocasi\u00d3n",
    "sg:phone":"+34 952 61 14 23",
    "sg:postcode":"29010",
    "sg:province":"M\u00e1laga",
    "wof:name":"Nieto Ballesteros Jose Carlos",
    "wof:placetype":"venue"
},
  "geometry": {"coordinates":[-4.4443330765,36.7278366089],"type":"Point"}
}