{
  "type": "Feature",
  "properties": {
    "iso:country":"ES",
    "sg:address":"Calle de Doctor Pulido, 2",
    "sg:city":"Guadix",
    "sg:orig_category":"Asesor\u00cda De Formaci\u00d3n Y Gesti\u00d3n De Personal",
    "sg:phone":"+34 958 66 91 21",
    "sg:postcode":"18500",
    "sg:province":"Granada",
    "wof:name":"Ruiz Obispo Manuel",
    "wof:placetype":"venue"
},
  "geometry": {"coordinates":[-3.1321237087,37.3006973267],"type":"Point"}
}