{
  "type": "Feature",
  "properties": {
    "addr:full":"Rond Doctor Ferran, 4 Mataro Barcelona 08304",
    "addr:housenumber":"4",
    "addr:postcode":"08304",
    "addr:street":"Doctor Ferran",
    "iso:country":"ES",
    "sg:address":"Rond Doctor Ferran, 4",
    "sg:city":"Mataro",
    "sg:classifiers":[
        {
            "category":"Autos & Motor Vehicles",
            "subcategory":"Automobile Sales",
            "type":"Retail Goods"
        }
    ],
    "sg:phone":"+34 937 98 49 93",
    "sg:postcode":"08304",
    "sg:province":"Barcelona",
    "wof:name":"Gregal Mix S.l.",
    "wof:placetype":"venue"
},
  "geometry": {"coordinates":[2.4376449585,41.5488014221],"type":"Point"}
}