{
  "type": "Feature",
  "properties": {
    "iso:country":"ES",
    "sg:address":"Portell, 2",
    "sg:city":"Algerri",
    "sg:orig_category":"Ense\u00d1ante, Direcci\u00d3n",
    "sg:phone":"+34 973 42 61 44",
    "sg:postcode":"25130",
    "sg:province":"Lleida",
    "wof:name":"Gensana Mangues Pablo",
    "wof:placetype":"venue"
},
  "geometry": {"coordinates":[0.6385189891,41.8165168762],"type":"Point"}
}