{
  "type": "Feature",
  "properties": {
    "iso:country":"ES",
    "sg:address":"Plaz Mayor, 10",
    "sg:city":"Elda",
    "sg:orig_category":"Procuradores",
    "sg:phone":"+34 966 98 22 11",
    "sg:postcode":"03600",
    "sg:province":"Alicante",
    "wof:name":"Berbel Ciudad Elizabeth",
    "wof:placetype":"venue"
},
  "geometry": {"coordinates":[-0.7941759825,38.4786491394],"type":"Point"}
}