{
  "type": "Feature",
  "properties": {
    "iso:country":"ES",
    "sg:address":"Carr Migdia, 20",
    "sg:city":"Platja D'aro",
    "sg:orig_category":"Fabricaci\u00d3n, Importaci\u00d3n De L\u00c1mparas Y Bombillas",
    "sg:phone":"+34 972 82 71 95",
    "sg:postcode":"17250",
    "sg:province":"Girona",
    "wof:name":"Tekra Instalacions S.l.",
    "wof:placetype":"venue"
},
  "geometry": {"coordinates":[2.820661068,41.9768104553],"type":"Point"}
}