{
  "type": "Feature",
  "properties": {
    "iso:country":"ES",
    "sg:address":"Pseo. Constitucion, 28",
    "sg:city":"Almaraz",
    "sg:orig_category":"Asesor\u00cda Fiscal Y Jur\u00cddica",
    "sg:phone":"+34 927 54 42 26",
    "sg:postcode":"10350",
    "sg:province":"C\u00e1ceres",
    "wof:name":"S.m.asesores Ara\u00f1uelo S.l.",
    "wof:placetype":"venue"
},
  "geometry": {"coordinates":[-5.6767120361,39.8133277893],"type":"Point"}
}