{
  "type": "Feature",
  "properties": {
    "addr:full":"Avda Diego Ramirez Pastor, 1 Torrevieja Alicante 03180",
    "addr:housenumber":"1",
    "addr:postcode":"03180",
    "addr:street":"Avda Diego Ramirez Pastor",
    "iso:country":"ES",
    "sg:address":"Avda Diego Ramirez Pastor, 1",
    "sg:city":"Torrevieja",
    "sg:orig_category":"Confecci\u00d3n (fabricaci\u00d3n, Al Por Mayor)",
    "sg:phone":"+34 965 70 61 08",
    "sg:postcode":"03180",
    "sg:province":"Alicante",
    "sg:website":"www.textildani.com",
    "wof:name":"Decotex S.c.",
    "wof:placetype":"venue"
},
  "geometry": {"coordinates":[-0.6902070045,37.9795532227],"type":"Point"}
}