{
  "type": "Feature",
  "properties": {
    "iso:country":"ES",
    "sg:address":"Calle de Barranco, 13",
    "sg:city":"Granja De Moreruela",
    "sg:orig_category":"Centros De Educaci\u00d3n Especial",
    "sg:phone":"+34 980 58 71 52",
    "sg:postcode":"49740",
    "sg:province":"Zamora",
    "wof:name":"Colegio Rural Agrupado De Villarrin",
    "wof:placetype":"venue"
},
  "geometry": {"coordinates":[-5.7349619865,41.8131065369],"type":"Point"}
}