{
  "type": "Feature",
  "properties": {
    "addr:full":"Carrer de Almeria (d'), 31 Plana Tarragona 43480",
    "addr:housenumber":"31",
    "addr:postcode":"43480",
    "addr:street":"Carrer De Almeria D '",
    "iso:country":"ES",
    "sg:address":"Carrer de Almeria (d'), 31",
    "sg:city":"Plana",
    "sg:orig_category":"Venta Al Preg\u00d3n",
    "sg:phone":"+34 977 39 19 09",
    "sg:postcode":"43480",
    "sg:province":"Tarragona",
    "wof:name":"Moreno Moreno Andres",
    "wof:placetype":"venue"
},
  "geometry": {"coordinates":[1.1441899538,41.1080245972],"type":"Point"}
}