{
  "type": "Feature",
  "properties": {
    "addr:full":"Calle de Fernando Gutierrez, 11 Villaralbo Zamora 49159",
    "addr:housenumber":"11",
    "addr:postcode":"49159",
    "addr:street":"Calle De Fernando Gutierrez",
    "iso:country":"ES",
    "sg:address":"Calle de Fernando Gutierrez, 11",
    "sg:city":"Villaralbo",
    "sg:orig_category":"Estancos",
    "sg:phone":"+34 980 53 98 84",
    "sg:postcode":"49159",
    "sg:province":"Zamora",
    "wof:name":"Muriel Garcia Agustin",
    "wof:placetype":"venue"
},
  "geometry": {"coordinates":[-5.6848192215,41.4921798706],"type":"Point"}
}