{
  "type": "Feature",
  "properties": {
    "addr:full":"Calle de Olimpio Alonso, 17 Morales Toro Zamora 49810",
    "addr:housenumber":"17",
    "addr:postcode":"49810",
    "addr:street":"Calle De Olimpio Alonso",
    "iso:country":"ES",
    "sg:address":"Calle de Olimpio Alonso, 17",
    "sg:city":"Morales Toro",
    "sg:orig_category":"Iglesia Cat\u00d3lica",
    "sg:phone":"+34 980 69 80 04",
    "sg:postcode":"49810",
    "sg:province":"Zamora",
    "wof:name":"Obispado De Zamora",
    "wof:placetype":"venue"
},
  "geometry": {"coordinates":[-5.3089661598,41.537525177],"type":"Point"}
}