{
  "type": "Feature",
  "properties": {
    "addr:full":"Calle de Consulado De Bilbao Kalea, 4 Erandio Vizcaya 48950",
    "addr:housenumber":"4",
    "addr:postcode":"48950",
    "addr:street":"Calle De Consulado;Bilbao Kalea",
    "iso:country":"ES",
    "sg:address":"Calle de Consulado De Bilbao Kalea, 4",
    "sg:city":"Erandio",
    "sg:orig_category":"Molduras, Junquillos, Listones Y Molduras Perforadas",
    "sg:phone":"+34 944 67 25 89",
    "sg:postcode":"48950",
    "sg:province":"Vizcaya",
    "wof:name":"Sanchez Del Rio Jose Maria",
    "wof:placetype":"venue"
},
  "geometry": {"coordinates":[-2.9839529991,43.3172302246],"type":"Point"}
}