{
  "type": "Feature",
  "properties": {
    "addr:full":"Carr Maria Cristina, 11 Badalona Barcelona 08912",
    "addr:housenumber":"11",
    "addr:postcode":"08912",
    "addr:street":"Carr Maria Cristina",
    "iso:country":"ES",
    "sg:address":"Carr Maria Cristina, 11",
    "sg:city":"Badalona",
    "sg:orig_category":"Fabricaci\u00d3n De Juegos Y Juguetes",
    "sg:phone":"+34 933 83 26 57",
    "sg:postcode":"08912",
    "sg:province":"Barcelona",
    "wof:name":"Mata Sancho Motserrat",
    "wof:placetype":"venue"
},
  "geometry": {"coordinates":[2.242939949,41.4471473694],"type":"Point"}
}