{
  "type": "Feature",
  "properties": {
    "iso:country":"ES",
    "sg:address":"Carr Blasco Iba\u00d1ez, 123",
    "sg:city":"Burjassot",
    "sg:orig_category":"Panader\u00cdas, Panader\u00cdas",
    "sg:phone":"+34 963 63 86 69",
    "sg:postcode":"46100",
    "sg:province":"Valencia",
    "wof:name":"Frechina Benavent Rafael",
    "wof:placetype":"venue"
},
  "geometry": {"coordinates":[-0.4103820026,39.5090484619],"type":"Point"}
}