{
  "type": "Feature",
  "properties": {
    "iso:country":"ES",
    "sg:address":"Calle de Calvo Sotelo, 13",
    "sg:city":"Tineo",
    "sg:orig_category":"Librer\u00cdas",
    "sg:phone":"+34 985 80 19 84",
    "sg:postcode":"33870",
    "sg:province":"Asturias",
    "wof:name":"Quesada Fernandez Jesus Manuel",
    "wof:placetype":"venue"
},
  "geometry": {"coordinates":[-6.4166817665,43.3344230652],"type":"Point"}
}