{
  "type": "Feature",
  "properties": {
    "addr:full":"Calle de Valcarce, 1 Le\u00f3n Le\u00f3n 24010",
    "addr:housenumber":"1",
    "addr:postcode":"24010",
    "addr:street":"Calle De Valcarce;Leo\u0301N",
    "iso:country":"ES",
    "sg:address":"Calle de Valcarce, 1",
    "sg:city":"Le\u00f3n",
    "sg:orig_category":"Molduras, Junquillos, Listones Y Molduras Perforadas",
    "sg:phone":"+34 987 24 59 55",
    "sg:postcode":"24010",
    "sg:province":"Le\u00f3n",
    "wof:name":"Gutierrez Cortizo Jose Manuel",
    "wof:placetype":"venue"
},
  "geometry": {"coordinates":[-5.5917887688,42.6065444946],"type":"Point"}
}