{
  "type": "Feature",
  "properties": {
    "iso:country":"ES",
    "sg:address":"Calle de Palencia, 4",
    "sg:city":"Vitoria-gasteiz",
    "sg:orig_category":"Carnicer\u00cdas, Carnicer\u00cdas",
    "sg:phone":"+34 945 12 02 86",
    "sg:postcode":"01002",
    "sg:province":"\u00c1lava",
    "wof:name":"Embeita Sarasola Javier",
    "wof:placetype":"venue"
},
  "geometry": {"coordinates":[-2.6640229225,42.8517990112],"type":"Point"}
}