{
  "type": "Feature",
  "properties": {
    "addr:full":"Plaz Cofradias (las), 2 Burlada Navarra 31600",
    "addr:postcode":"31600",
    "addr:street":"Plaz;Las",
    "iso:country":"ES",
    "sg:address":"Plaz Cofradias (las), 2",
    "sg:city":"Burlada",
    "sg:orig_category":"Pod\u00d3logos: Pedicuros",
    "sg:phone":"+34 948 13 56 31",
    "sg:postcode":"31600",
    "sg:province":"Navarra",
    "wof:name":"De La Fuente Foncea Maria Del Carmen",
    "wof:placetype":"venue"
},
  "geometry": {"coordinates":[-1.6171430349,42.8263587952],"type":"Point"}
}