{
  "type": "Feature",
  "properties": {
    "iso:country":"ES",
    "sg:address":"Cala Golf, Km. 0001,0",
    "sg:city":"Mijas Costa",
    "sg:orig_category":"Inmobiliaria (agencias)",
    "sg:phone":"+34 952 59 92 95",
    "sg:postcode":"29649",
    "sg:province":"M\u00e1laga",
    "wof:name":"Ainsa",
    "wof:placetype":"venue"
},
  "geometry": {"coordinates":[-4.6802053452,36.5034294128],"type":"Point"}
}