{
  "type": "Feature",
  "properties": {
    "iso:country":"ES",
    "sg:address":"Calle de Fernandez De Los Rios, 2",
    "sg:city":"Madrid",
    "sg:orig_category":"Empresarios Y Productoras De Espect\u00c1culos",
    "sg:phone":"+34 914 45 65 53",
    "sg:postcode":"28015",
    "sg:province":"Madrid",
    "wof:name":"Opera Comica De Madrid S.a.",
    "wof:placetype":"venue"
},
  "geometry": {"coordinates":[-3.704572916,40.4350357056],"type":"Point"}
}