{
  "type": "Feature",
  "properties": {
    "iso:country":"ES",
    "sg:address":"Calle de Cartagena, 71",
    "sg:city":"Madrid",
    "sg:orig_category":"Muebles, Minoristas",
    "sg:phone":"+34 913 55 59 67",
    "sg:postcode":"28028",
    "sg:province":"Madrid",
    "wof:name":"Exclusivas Del Confort S.l.",
    "wof:placetype":"venue"
},
  "geometry": {"coordinates":[-3.6714437008,40.4373893738],"type":"Point"}
}