{
  "type": "Feature",
  "properties": {
    "addr:full":"Ctra Henar, 2 Cuellar Segovia 40200",
    "addr:housenumber":"2",
    "addr:postcode":"40200",
    "addr:street":"Ctra Henar",
    "iso:country":"ES",
    "sg:address":"Ctra Henar, 2",
    "sg:city":"Cuellar",
    "sg:orig_category":"Caf\u00c9s, Bares, Cervecer\u00cdas",
    "sg:phone":"+34 921 14 17 75",
    "sg:postcode":"40200",
    "sg:province":"Segovia",
    "wof:name":"Ortega Medina Victorio",
    "wof:placetype":"venue"
},
  "geometry": {"coordinates":[-4.3196167946,41.4020576477],"type":"Point"}
}