{
  "type": "Feature",
  "properties": {
    "addr:full":"Poligono 4, 283 Son Ametller Islas Baleares 07009",
    "addr:housenumber":"283",
    "addr:postcode":"07009",
    "addr:street":"Poligono 4",
    "iso:country":"ES",
    "sg:address":"Poligono 4, 283",
    "sg:city":"Son Ametller",
    "sg:orig_category":"Promotores Constructores",
    "sg:phone":"+34 971 22 69 88",
    "sg:postcode":"07009",
    "sg:province":"Islas Baleares",
    "wof:name":"Construcciones Asensio Ruiz S.l.",
    "wof:placetype":"venue"
},
  "geometry": {"coordinates":[2.6776249409,39.6072845459],"type":"Point"}
}