{
  "type": "Feature",
  "properties": {
    "iso:country":"ES",
    "sg:address":"Reina Sofia, 1",
    "sg:city":"Quiles",
    "sg:orig_category":"Rejas Y Cortinas Met\u00c1licas",
    "sg:phone":"+34 926 80 40 03",
    "sg:postcode":"13428",
    "sg:province":"Ciudad Real",
    "wof:name":"Fortesercas S.l.",
    "wof:placetype":"venue"
},
  "geometry": {"coordinates":[-4.0121731758,39.2584381104],"type":"Point"}
}