{
  "type": "Feature",
  "properties": {
    "addr:full":"Cmno Lomo Grande, 62 Lomo Grande Las Palmas 35400",
    "addr:housenumber":"62",
    "addr:postcode":"35400",
    "addr:street":"Cmno Lomo Grande",
    "iso:country":"ES",
    "sg:address":"Cmno Lomo Grande, 62",
    "sg:city":"Lomo Grande",
    "sg:classifiers":[
        {
            "category":"Professional",
            "subcategory":"Management & Consulting",
            "type":"Services"
        }
    ],
    "sg:phone":"+34 928 63 43 57",
    "sg:postcode":"35400",
    "sg:province":"Las Palmas",
    "sg:tags":[
        "asesor\u00cda",
        "en",
        "marketing"
    ],
    "wof:name":"Cupones Crena S.l.",
    "wof:placetype":"venue"
},
  "geometry": {"coordinates":[-15.5152540207,28.1135654449],"type":"Point"}
}