{
  "type": "Feature",
  "properties": {
    "addr:full":"El Pontico, 19 Llangreu Asturias 33900",
    "addr:housenumber":"19",
    "addr:postcode":"33900",
    "addr:street":"El Pontico",
    "iso:country":"ES",
    "sg:address":"El Pontico, 19",
    "sg:city":"Llangreu",
    "sg:orig_category":"Bebidas",
    "sg:phone":"+34 985 69 64 76",
    "sg:postcode":"33900",
    "sg:province":"Asturias",
    "wof:name":"Lopez Castro Francisco",
    "wof:placetype":"venue"
},
  "geometry": {"coordinates":[-5.7056746483,43.3038864136],"type":"Point"}
}