{
  "type": "Feature",
  "properties": {
    "addr:full":"Goitia Kalea, 1 Ordizia Guip\u00f9zcoa 20240",
    "addr:housenumber":"1",
    "addr:postcode":"20240",
    "addr:street":"Goitia Kalea;Guipu\u0300Zcoa",
    "iso:country":"ES",
    "sg:address":"Goitia Kalea, 1",
    "sg:city":"Ordizia",
    "sg:orig_category":"Zapatos (al Por Menor)",
    "sg:phone":"+34 943 88 12 10",
    "sg:postcode":"20240",
    "sg:province":"Guip\u00f9zcoa",
    "wof:name":"Ota\u00f1o Gonzalez Maria Asuncion",
    "wof:placetype":"venue"
},
  "geometry": {"coordinates":[-2.1773040295,43.0538711548],"type":"Point"}
}