{
  "type": "Feature",
  "properties": {
    "addr:full":"Huerta Macena, 12 Lebrija Sevilla 41740",
    "addr:housenumber":"12",
    "addr:postcode":"41740",
    "iso:country":"ES",
    "sg:address":"Huerta Macena, 12",
    "sg:city":"Lebrija",
    "sg:orig_category":"Reposter\u00cdas",
    "sg:phone":"+34 955 97 45 68",
    "sg:postcode":"41740",
    "sg:province":"Sevilla",
    "wof:name":"Sociedad Cooperativa Limitada Huerta Macena",
    "wof:placetype":"venue"
},
  "geometry": {"coordinates":[-6.0658698082,36.9205932617],"type":"Point"}
}