{
  "type": "Feature",
  "properties": {
    "iso:country":"ES",
    "sg:address":"Carrer de Castellar, 15",
    "sg:city":"S. Quirze Valles",
    "sg:orig_category":"Guarder\u00cdas",
    "sg:phone":"+34 937 21 33 18",
    "sg:postcode":"08192",
    "sg:province":"Barcelona",
    "wof:name":"El Petit Princep Del Valles",
    "wof:placetype":"venue"
},
  "geometry": {"coordinates":[2.0853099823,41.5287666321],"type":"Point"}
}