{
  "type": "Feature",
  "properties": {
    "addr:full":"Carr Sant Joaquim, 22 Badalona Barcelona 08911",
    "addr:housenumber":"22",
    "addr:postcode":"08911",
    "addr:street":"Carr Sant Joaquim",
    "iso:country":"ES",
    "sg:address":"Carr Sant Joaquim, 22",
    "sg:city":"Badalona",
    "sg:orig_category":"Peluquer\u00cdas, Peluquer\u00cda Mixta",
    "sg:phone":"+34 934 64 44 58",
    "sg:postcode":"08911",
    "sg:province":"Barcelona",
    "wof:name":"Garcia Moreno Celso",
    "wof:placetype":"venue"
},
  "geometry": {"coordinates":[2.2498950958,41.4469871521],"type":"Point"}
}