{
  "type": "Feature",
  "properties": {
    "addr:full":"Castillo-gazteleku, 43 Iru\u00f1a Navarra 31001",
    "addr:housenumber":"43",
    "addr:postcode":"31001",
    "addr:street":"Castillo-Gazteleku",
    "iso:country":"ES",
    "sg:address":"Castillo-gazteleku, 43",
    "sg:city":"Iru\u00f1a",
    "sg:orig_category":"Organizaciones Profesionales",
    "sg:phone":"+34 948 21 07 87",
    "sg:postcode":"31001",
    "sg:province":"Navarra",
    "wof:name":"Comisariado Europeo Del Automovil",
    "wof:placetype":"venue"
},
  "geometry": {"coordinates":[-1.6437540054,42.81275177],"type":"Point"}
}