{
  "type": "Feature",
  "properties": {
    "addr:full":"Avda Sol, 17 Zubia Granada 18140",
    "addr:housenumber":"17",
    "addr:postcode":"18140",
    "addr:street":"Avda Sol",
    "iso:country":"ES",
    "sg:address":"Avda Sol, 17",
    "sg:city":"Zubia",
    "sg:orig_category":"Agentes Generales De Seguros",
    "sg:phone":"+34 958 89 05 96",
    "sg:postcode":"18140",
    "sg:province":"Granada",
    "wof:name":"Martin Cera S.l.",
    "wof:placetype":"venue"
},
  "geometry": {"coordinates":[-3.5778419971,37.1216659546],"type":"Point"}
}