{
  "type": "Feature",
  "properties": {
    "addr:full":"Avda Tren Expreso, S/n Venta De Ba\u00e7os Palencia 34200",
    "addr:housenumber":"s / n",
    "addr:postcode":"34200",
    "addr:street":"Avda Tren Expreso",
    "iso:country":"ES",
    "sg:address":"Avda Tren Expreso, S/n",
    "sg:city":"Venta De Ba\u00e7os",
    "sg:orig_category":"Centros Empresariales",
    "sg:phone":"+34 979 77 10 94",
    "sg:postcode":"34200",
    "sg:province":"Palencia",
    "wof:name":"Contse S. A.",
    "wof:placetype":"venue"
},
  "geometry": {"coordinates":[-4.4883089066,41.9319190979],"type":"Point"}
}