{
  "type": "Feature",
  "properties": {
    "iso:country":"ES",
    "sg:address":"Calle de Alfredo Nobel, 5",
    "sg:city":"Alcorcon",
    "sg:orig_category":"Agencias De Viajes",
    "sg:phone":"+34 916 41 47 75",
    "sg:postcode":"28922",
    "sg:province":"Madrid",
    "wof:name":"Viajes Catania S.l.",
    "wof:placetype":"venue"
},
  "geometry": {"coordinates":[-3.831289053,40.3347892761],"type":"Point"}
}