{
  "type": "Feature",
  "properties": {
    "addr:full":"Avda Bulevar De El Ejido, Km. 0079,0 Ejido Almer\u00eda 04700",
    "addr:postcode":"04700",
    "addr:street":"Bulevar De El Ejido Km. 0079,0 Ejido Almeri\u0301A",
    "iso:country":"ES",
    "sg:address":"Avda Bulevar De El Ejido, Km. 0079,0",
    "sg:city":"Ejido",
    "sg:orig_category":"Caf\u00c9s, Bares, Cervecer\u00cdas",
    "sg:phone":"+34 950 48 47 83",
    "sg:postcode":"04700",
    "sg:province":"Almer\u00eda",
    "wof:name":"Lopez Gutierrez Emilio Miguel",
    "wof:placetype":"venue"
},
  "geometry": {"coordinates":[-2.8176040649,36.7727012634],"type":"Point"}
}