{
  "type": "Feature",
  "properties": {
    "addr:full":"Calle de Pe\u00d1a Tejonera, 149 Dominio De Fontenebro Madrid 28400",
    "addr:housenumber":"149",
    "addr:postcode":"28400",
    "addr:street":"Calle De Pen\u0303A Tejonera",
    "iso:country":"ES",
    "sg:address":"Calle de Pe\u00d1a Tejonera, 149",
    "sg:city":"Dominio De Fontenebro",
    "sg:orig_category":"Centros Empresariales",
    "sg:phone":"+34 918 50 76 99",
    "sg:postcode":"28400",
    "sg:province":"Madrid",
    "wof:name":"Sergontec C.b.",
    "wof:placetype":"venue"
},
  "geometry": {"coordinates":[-3.9919650555,40.6455612183],"type":"Point"}
}