{
  "type": "Feature",
  "properties": {
    "addr:full":"Calle de Villamanin, 48 Madrid Madrid 28011",
    "addr:housenumber":"48",
    "addr:postcode":"madrid;28011",
    "addr:street":"Calle De Villamanin",
    "iso:country":"ES",
    "sg:address":"Calle de Villamanin, 48",
    "sg:city":"Madrid",
    "sg:orig_category":"Venta, Colocaci\u00d3n De Autoradios",
    "sg:phone":"+34 914 79 65 55",
    "sg:postcode":"28011",
    "sg:province":"Madrid",
    "wof:name":"Bernabe Perez Javier",
    "wof:placetype":"venue"
},
  "geometry": {"coordinates":[-3.7532761097,40.4067268372],"type":"Point"}
}