{
  "type": "Feature",
  "properties": {
    "addr:full":"Calle de Panama, 4 Matas-pinar-monte Rozas Madrid 28290",
    "addr:housenumber":"4",
    "addr:postcode":"28290",
    "addr:street":"Calle De Panama",
    "iso:country":"ES",
    "sg:address":"Calle de Panama, 4",
    "sg:city":"Matas-pinar-monte Rozas",
    "sg:orig_category":"Financiaci\u00d3n Y Cr\u00c9ditos",
    "sg:phone":"+34 916 36 91 23",
    "sg:postcode":"28290",
    "sg:province":"Madrid",
    "wof:name":"Consulting Europeo De Gestion E Inversion Empresarial S.l.",
    "wof:placetype":"venue"
},
  "geometry": {"coordinates":[-3.9007530212,40.5417098999],"type":"Point"}
}