{
  "type": "Feature",
  "properties": {
    "iso:country":"ES",
    "sg:address":"Carrer de America, 26",
    "sg:city":"Barcelona",
    "sg:orig_category":"Artes Gr\u00c1ficas, Artes Pl\u00c1sticas (curso)",
    "sg:phone":"+34 933 48 17 76",
    "sg:postcode":"08041",
    "sg:province":"Barcelona",
    "wof:name":"Roda Linia S.c.p.",
    "wof:placetype":"venue"
},
  "geometry": {"coordinates":[2.177396059,41.4161453247],"type":"Point"}
}