{
  "type": "Feature",
  "properties": {
    "iso:country":"ES",
    "sg:address":"Avda Alcalde Jose Fernandin, 6",
    "sg:city":"Piedras Blancas",
    "sg:orig_category":"Panader\u00cdas, Panader\u00cdas",
    "sg:phone":"+34 985 50 70 79",
    "sg:postcode":"33450",
    "sg:province":"Asturias",
    "wof:name":"Castro Fernandez Luis Miguel De",
    "wof:placetype":"venue"
},
  "geometry": {"coordinates":[-5.9740419388,43.5600852966],"type":"Point"}
}