{
  "type": "Feature",
  "properties": {
    "addr:full":"Calle de Calamocha, 5 Valencia Valencia 46007",
    "addr:housenumber":"5",
    "addr:postcode":"46007",
    "addr:street":"Calle De Calamocha",
    "iso:country":"ES",
    "sg:address":"Calle de Calamocha, 5",
    "sg:city":"Valencia",
    "sg:orig_category":"Ense\u00d1anza: Profesiones Art\u00cdsticas",
    "sg:phone":"+34 963 80 71 91",
    "sg:postcode":"46007",
    "sg:province":"Valencia",
    "wof:name":"Estudio Fotografico El Mirador S.l.",
    "wof:placetype":"venue"
},
  "geometry": {"coordinates":[-0.3886336088,39.462348938],"type":"Point"}
}