{
  "type": "Feature",
  "properties": {
    "iso:country":"ES",
    "sg:address":"La Era, S/n",
    "sg:city":"Gines",
    "sg:orig_category":"Carnicer\u00cdas, Carnicer\u00cdas",
    "sg:phone":"+34 954 71 42 03",
    "sg:postcode":"41960",
    "sg:province":"Sevilla",
    "wof:name":"Silmaril S.l.",
    "wof:placetype":"venue"
},
  "geometry": {"coordinates":[-6.0813498497,37.3886833191],"type":"Point"}
}