{
  "type": "Feature",
  "properties": {
    "iso:country":"ES",
    "sg:address":"Pase Profesor Veremundo Nu\u00d1ez (del), 6",
    "sg:city":"Bembibre",
    "sg:orig_category":"Venta, Instalaci\u00d3n De Calefacci\u00d3n",
    "sg:phone":"+34 987 51 14 46",
    "sg:postcode":"24300",
    "sg:province":"Le\u00f3n",
    "wof:name":"Gas Del Valle Instalaciones S.l.",
    "wof:placetype":"venue"
},
  "geometry": {"coordinates":[-6.4609999657,42.6525726318],"type":"Point"}
}