{
  "type": "Feature",
  "properties": {
    "addr:full":"Miguel Servet(p I Las Saladas), 24 Torrellano Alicante 03320",
    "addr:housenumber":"24",
    "addr:postcode":"03320",
    "addr:street":"Miguel Servet P;Las Saladas",
    "iso:country":"ES",
    "sg:address":"Miguel Servet(p I Las Saladas), 24",
    "sg:city":"Torrellano",
    "sg:orig_category":"Fabricaci\u00d3n De Art\u00cdculos Y Equipos Deportivos Y De Ocio",
    "sg:phone":"+34 966 66 73 16",
    "sg:postcode":"03320",
    "sg:province":"Alicante",
    "sg:website":"www.campus-sport.net",
    "wof:name":"Sirach Sport S.l.",
    "wof:placetype":"venue"
},
  "geometry": {"coordinates":[-0.5883839726,38.2929649353],"type":"Point"}
}