{
  "type": "Feature",
  "properties": {
    "addr:full":"Calle de Centro, 9 Urroz Navarra 31420",
    "addr:housenumber":"9",
    "addr:postcode":"31420",
    "addr:street":"Calle De Centro",
    "iso:country":"ES",
    "sg:address":"Calle de Centro, 9",
    "sg:city":"Urroz",
    "sg:orig_category":"Iglesia Cat\u00d3lica",
    "sg:phone":"+34 948 33 81 28",
    "sg:postcode":"31420",
    "sg:province":"Navarra",
    "wof:name":"Arzobispado De Pamplona",
    "wof:placetype":"venue"
},
  "geometry": {"coordinates":[-1.4586104155,42.7779273987],"type":"Point"}
}