{
  "type": "Feature",
  "properties": {
    "addr:full":"Calle de Cid, 4 Majadahonda Madrid 28220",
    "addr:housenumber":"4",
    "addr:postcode":"28220",
    "addr:street":"Calle De Cid",
    "iso:country":"ES",
    "sg:address":"Calle de Cid, 4",
    "sg:city":"Majadahonda",
    "sg:orig_category":"M\u00c9dicos: Estomatolog\u00cda",
    "sg:phone":"+34 916 39 10 56",
    "sg:postcode":"28220",
    "sg:province":"Madrid",
    "wof:name":"Itza Santos Fernando",
    "wof:placetype":"venue"
},
  "geometry": {"coordinates":[-3.8701660633,40.4703330994],"type":"Point"}
}