{
  "type": "Feature",
  "properties": {
    "addr:full":"Resid Cabosol, 52 La Zenia Alicante 03189",
    "addr:housenumber":"52",
    "addr:postcode":"03189",
    "addr:street":"La",
    "iso:country":"ES",
    "sg:address":"Resid Cabosol, 52",
    "sg:city":"La Zenia",
    "sg:orig_category":"Molduras, Junquillos, Listones Y Molduras Perforadas",
    "sg:phone":"+34 966 77 36 92",
    "sg:postcode":"03189",
    "sg:province":"Alicante",
    "wof:name":"Hostelmur S.l.",
    "wof:placetype":"venue"
},
  "geometry": {"coordinates":[-0.7534540296,37.9003753662],"type":"Point"}
}