{
  "type": "Feature",
  "properties": {
    "iso:country":"ES",
    "sg:address":"Avda Playas (las), 59",
    "sg:city":"Puerto Del Carmen",
    "sg:orig_category":"Bazares, Art\u00cdculos De Limpieza Y De Cocina (al Por Menor)",
    "sg:phone":"+34 928 51 39 18",
    "sg:postcode":"35510",
    "sg:province":"Las Palmas",
    "wof:name":"Dodani Dodani Sunder Chelleran",
    "wof:placetype":"venue"
},
  "geometry": {"coordinates":[-13.6543092728,28.9192905426],"type":"Point"}
}