{
  "type": "Feature",
  "properties": {
    "iso:country":"ES",
    "sg:address":"Calle de Castilla, 2",
    "sg:city":"Jaen",
    "sg:orig_category":"Abogados",
    "sg:phone":"+34 953 22 96 06",
    "sg:postcode":"23007",
    "sg:province":"Ja\u00e9n",
    "wof:name":"Salvo Riquelme Jose Del Carmen",
    "wof:placetype":"venue"
},
  "geometry": {"coordinates":[-3.790365696,37.7701759338],"type":"Point"}
}