{
  "type": "Feature",
  "properties": {
    "iso:country":"ES",
    "sg:address":"Carrer de Moli Dels Frares, S/n",
    "sg:city":"Sant Vicen\u00c7 Dels Horts",
    "sg:orig_category":"Art\u00cdculos De Limpieza Y De Cocina (fabricaci\u00d3n, Al Por Mayor)",
    "sg:phone":"+34 936 76 85 45",
    "sg:postcode":"08620",
    "sg:province":"Barcelona",
    "wof:name":"Codibaix S.l.",
    "wof:placetype":"venue"
},
  "geometry": {"coordinates":[1.9983279705,41.4035797119],"type":"Point"}
}