{
  "type": "Feature",
  "properties": {
    "addr:full":"Pla\u00c7 Bassa De La, 22 Xativa Valencia 46800",
    "addr:postcode":"46800",
    "iso:country":"ES",
    "sg:address":"Pla\u00c7 Bassa De La, 22",
    "sg:city":"Xativa",
    "sg:classifiers":[
        {
            "category":"Food & Beverages",
            "subcategory":"Candy",
            "type":"Retail Goods"
        }
    ],
    "sg:phone":"+34 962 28 13 92",
    "sg:postcode":"46800",
    "sg:province":"Valencia",
    "sg:tags":[
        "confiter\u00cdas",
        "y",
        "de",
        "fabricaci\u00d3n",
        "chocolate"
    ],
    "wof:name":"Beamut Milla Palmira",
    "wof:placetype":"venue"
},
  "geometry": {"coordinates":[-0.5200830102,38.9934272766],"type":"Point"}
}