{
  "type": "Feature",
  "properties": {
    "iso:country":"ES",
    "sg:address":"Calle de Jaime I, 9",
    "sg:city":"Alaquas",
    "sg:orig_category":"Art\u00cdculos De Limpieza Y De Cocina (fabricaci\u00d3n, Al Por Mayor)",
    "sg:phone":"+34 961 50 39 12",
    "sg:postcode":"46970",
    "sg:province":"Valencia",
    "wof:name":"Y.josami S.a.",
    "wof:placetype":"venue"
},
  "geometry": {"coordinates":[-0.4688160121,39.4519119263],"type":"Point"}
}