{
  "type": "Feature",
  "properties": {
    "iso:country":"ES",
    "sg:address":"I (pol. Ind. Cami Dels Frares), S/n",
    "sg:city":"Lleida",
    "sg:orig_category":"Triper\u00cdas",
    "sg:phone":"+34 973 23 45 43",
    "sg:postcode":"25190",
    "sg:province":"Lleida",
    "wof:name":"J. Bosch S.l.",
    "wof:placetype":"venue"
},
  "geometry": {"coordinates":[0.6752300262,41.613658905],"type":"Point"}
}