{
  "type": "Feature",
  "properties": {
    "iso:country":"ES",
    "sg:address":"Calle de General Ricardos, 80",
    "sg:city":"Madrid",
    "sg:orig_category":"Chapister\u00cda",
    "sg:phone":"+34 914 71 45 56",
    "sg:postcode":"28019",
    "sg:province":"Madrid",
    "wof:name":"Resino Serrano Angel",
    "wof:placetype":"venue"
},
  "geometry": {"coordinates":[-3.7234110832,40.3937416077],"type":"Point"}
}