{
  "type": "Feature",
  "properties": {
    "addr:full":"C/ Hilarion Eslava, 88 Elche Alicante 03204",
    "addr:housenumber":"88",
    "addr:postcode":"03204",
    "addr:street":"C / Hilarion Eslava",
    "iso:country":"ES",
    "sg:address":"C/ Hilarion Eslava, 88",
    "sg:city":"Elche",
    "sg:orig_category":"Confecci\u00d3n De Zapatos",
    "sg:phone":"+34 966 63 46 55",
    "sg:postcode":"03204",
    "sg:province":"Alicante",
    "wof:name":"Calzados Suyvi S. L.",
    "wof:placetype":"venue"
},
  "geometry": {"coordinates":[-0.6995239854,38.2634811401],"type":"Point"}
}