{
  "type": "Feature",
  "properties": {
    "iso:country":"ES",
    "sg:address":"Cami Sastres, 20",
    "sg:city":"Alfas Pi",
    "sg:orig_category":"Panader\u00cdas, Panader\u00cdas",
    "sg:phone":"+34 965 88 94 39",
    "sg:postcode":"03580",
    "sg:province":"Alicante",
    "wof:name":"Santafe Jarque Tomas",
    "wof:placetype":"venue"
},
  "geometry": {"coordinates":[-0.0862839967,38.5857086182],"type":"Point"}
}