{
  "type": "Feature",
  "properties": {
    "iso:country":"ES",
    "sg:address":"Calle de Medio, 1",
    "sg:city":"Santander",
    "sg:orig_category":"Ropa Para Se\u00d1oras (al Por Menor)",
    "sg:phone":"+34 942 36 49 59",
    "sg:postcode":"39003",
    "sg:province":"Cantabria",
    "wof:name":"Santos Fernandez Ana",
    "wof:placetype":"venue"
},
  "geometry": {"coordinates":[-3.8051810265,43.4627113342],"type":"Point"}
}