{
  "type": "Feature",
  "properties": {
    "iso:country":"ES",
    "sg:address":"Bo La Venta, 2",
    "sg:city":"Igollo",
    "sg:orig_category":"Productos Qu\u00cdmicos (fabricaci\u00d3n, Al Por Mayor)",
    "sg:phone":"+34 942 58 58 64",
    "sg:postcode":"39608",
    "sg:province":"Cantabria",
    "wof:name":"Martinez Gutierrez Francisco",
    "wof:placetype":"venue"
},
  "geometry": {"coordinates":[-3.8830139637,43.4323272705],"type":"Point"}
}