{
  "type": "Feature",
  "properties": {
    "iso:country":"ES",
    "sg:address":"Calle de Angeles (de Los), 2",
    "sg:city":"Fuenlabrada",
    "sg:orig_category":"Panader\u00cdas, Panader\u00cdas",
    "sg:phone":"+34 916 00 03 18",
    "sg:postcode":"28944",
    "sg:province":"Madrid",
    "wof:name":"Cosas De Tina S.l.",
    "wof:placetype":"venue"
},
  "geometry": {"coordinates":[-3.79210186,40.2870330811],"type":"Point"}
}