{
  "type": "Feature",
  "properties": {
    "addr:full":"Avda Perez Galdos, 3 Santander Cantabria 39005",
    "addr:housenumber":"3",
    "addr:postcode":"39005",
    "addr:street":"Avda Perez Galdos",
    "iso:country":"ES",
    "sg:address":"Avda Perez Galdos, 3",
    "sg:city":"Santander",
    "sg:orig_category":"Caf\u00c9s, Bares, Cervecer\u00cdas",
    "sg:phone":"+34 942 27 31 97",
    "sg:postcode":"39005",
    "sg:province":"Cantabria",
    "wof:name":"Moises Fernandez Briz Cd.",
    "wof:placetype":"venue"
},
  "geometry": {"coordinates":[-3.7868340015,43.4672012329],"type":"Point"}
}