{
  "type": "Feature",
  "properties": {
    "iso:country":"ES",
    "sg:address":"Rua Cidade Xardin, S/n",
    "sg:city":"Lalin",
    "sg:orig_category":"Promotores Constructores",
    "sg:phone":"+34 986 78 05 05",
    "sg:postcode":"36500",
    "sg:province":"Pontevedra",
    "wof:name":"Luaces Taboada Jose",
    "wof:placetype":"venue"
},
  "geometry": {"coordinates":[-8.1120290756,42.6662254333],"type":"Point"}
}