{
  "type": "Feature",
  "properties": {
    "addr:full":"Calle de Estibadores, 12 Lepe Huelva 21440",
    "addr:housenumber":"12",
    "addr:postcode":"21440",
    "addr:street":"Calle De Estibadores",
    "iso:country":"ES",
    "sg:address":"Calle de Estibadores, 12",
    "sg:city":"Lepe",
    "sg:orig_category":"Empresas De Carpinter\u00cda De Madera",
    "sg:phone":"+34 959 38 03 51",
    "sg:postcode":"21440",
    "sg:province":"Huelva",
    "wof:name":"Carpinteria Rodriguez Y Vela S. L.",
    "wof:placetype":"venue"
},
  "geometry": {"coordinates":[-7.1974430084,37.2488479614],"type":"Point"}
}