{
  "type": "Feature",
  "properties": {
    "addr:full":"Rua Bolivia, 32 Vigo Pontevedra 36204",
    "addr:housenumber":"32",
    "addr:postcode":"36204",
    "addr:street":"Rua Bolivia",
    "iso:country":"ES",
    "sg:address":"Rua Bolivia, 32",
    "sg:city":"Vigo",
    "sg:orig_category":"M\u00c9dicos: Estomatolog\u00cda",
    "sg:phone":"+34 986 48 08 45",
    "sg:postcode":"36204",
    "sg:province":"Pontevedra",
    "wof:name":"Romero Costas Enrique",
    "wof:placetype":"venue"
},
  "geometry": {"coordinates":[-8.7171278,42.2306861877],"type":"Point"}
}