{
  "type": "Feature",
  "properties": {
    "iso:country":"ES",
    "sg:address":"Calle de Fermin Mota, 18",
    "sg:city":"Pedro\u00d1eras",
    "sg:orig_category":"Arquitectos",
    "sg:phone":"+34 967 16 03 67",
    "sg:postcode":"16660",
    "sg:province":"Cuenca",
    "wof:name":"Pacheco Pacheco Juan Jose",
    "wof:placetype":"venue"
},
  "geometry": {"coordinates":[-2.6769170761,39.4512557983],"type":"Point"}
}