{
  "type": "Feature",
  "properties": {
    "addr:full":"Calle de Angel Guimera, 33 Valencia Valencia 46008",
    "addr:housenumber":"33",
    "addr:postcode":"46008",
    "addr:street":"Calle De Angel Guimera",
    "iso:country":"ES",
    "sg:address":"Calle de Angel Guimera, 33",
    "sg:city":"Valencia",
    "sg:orig_category":"M\u00c9dicos: Ginecolog\u00cda Y Obstetricia",
    "sg:phone":"+34 963 84 91 19",
    "sg:postcode":"46008",
    "sg:province":"Valencia",
    "wof:name":"Domenech Soler Agustin",
    "wof:placetype":"venue"
},
  "geometry": {"coordinates":[-0.387549907,39.4698677063],"type":"Point"}
}