{
  "type": "Feature",
  "properties": {
    "addr:full":"Ctra Tembleque, 24 Villaca\u00f1as Toledo 45860",
    "addr:housenumber":"24",
    "addr:postcode":"45860",
    "addr:street":"Ctra Tembleque",
    "iso:country":"ES",
    "sg:address":"Ctra Tembleque, 24",
    "sg:city":"Villaca\u00f1as",
    "sg:orig_category":"Sindicatos Y Colegios Profesionales",
    "sg:phone":"+34 925 56 03 16",
    "sg:postcode":"45860",
    "sg:province":"Toledo",
    "wof:name":"Asociacion De Fabricantes De Puertas De Castilla",
    "wof:placetype":"venue"
},
  "geometry": {"coordinates":[-3.349947691,39.6168060303],"type":"Point"}
}