{
  "type": "Feature",
  "properties": {
    "iso:country":"ES",
    "sg:address":"Calle de Pereda, 5",
    "sg:city":"Salamanca",
    "sg:orig_category":"Lavado, Limpieza De Veh\u00cdculos",
    "sg:phone":"+34 923 22 30 52",
    "sg:postcode":"37004",
    "sg:province":"Salamanca",
    "wof:name":"Diaz Bonafonte Manuel",
    "wof:placetype":"venue"
},
  "geometry": {"coordinates":[-5.6561260223,40.9710464478],"type":"Point"}
}