{
  "type": "Feature",
  "properties": {
    "addr:full":"Carr Sant Mateu, 12 Bunyola Islas Baleares 07110",
    "addr:housenumber":"12",
    "addr:postcode":"07110",
    "addr:street":"Carr Sant Mateu",
    "iso:country":"ES",
    "sg:address":"Carr Sant Mateu, 12",
    "sg:city":"Bunyola",
    "sg:orig_category":"Formaci\u00d3n Continuada (variada)",
    "sg:phone":"+34 971 61 36 23",
    "sg:postcode":"07110",
    "sg:province":"Islas Baleares",
    "wof:name":"Seassessoria C.b.",
    "wof:placetype":"venue"
},
  "geometry": {"coordinates":[2.6912779808,39.6818656921],"type":"Point"}
}