{
  "type": "Feature",
  "properties": {
    "addr:full":"Prol Avenida Santander, 8 Noja Cantabria 39180",
    "addr:housenumber":"8",
    "addr:postcode":"39180",
    "addr:street":"Prol Avenida Santander",
    "iso:country":"ES",
    "sg:address":"Prol Avenida Santander, 8",
    "sg:city":"Noja",
    "sg:orig_category":"Asociaciones Y Clubs Deportivos",
    "sg:phone":"+34 942 63 13 62",
    "sg:postcode":"39180",
    "sg:province":"Cantabria",
    "wof:name":"Trideport S.l.",
    "wof:placetype":"venue"
},
  "geometry": {"coordinates":[-3.5296189785,43.4792633057],"type":"Point"}
}