{
  "type": "Feature",
  "properties": {
    "iso:country":"ES",
    "sg:address":"Calle de Churruca, 24",
    "sg:city":"Venta De Ba\u00e7os",
    "sg:orig_category":"Carnicer\u00cdas, Carnicer\u00cdas",
    "sg:phone":"+34 979 77 13 12",
    "sg:postcode":"34200",
    "sg:province":"Palencia",
    "wof:name":"Sobradillo Casado Feliciano",
    "wof:placetype":"venue"
},
  "geometry": {"coordinates":[-4.4929690361,41.9175682068],"type":"Point"}
}