{
  "type": "Feature",
  "properties": {
    "addr:full":"Calle de Cervantes, 16 Roda Albacete 02630",
    "addr:housenumber":"16",
    "addr:postcode":"02630",
    "addr:street":"Calle De Cervantes",
    "iso:country":"ES",
    "sg:address":"Calle de Cervantes, 16",
    "sg:city":"Roda",
    "sg:orig_category":"Iglesia Cat\u00d3lica",
    "sg:phone":"+34 967 44 08 77",
    "sg:postcode":"02630",
    "sg:province":"Albacete",
    "wof:name":"Iglesia Parroquial Del Salvador",
    "wof:placetype":"venue"
},
  "geometry": {"coordinates":[-2.1603233814,39.2074203491],"type":"Point"}
}