{
  "type": "Feature",
  "properties": {
    "iso:country":"ES",
    "sg:address":"Calle de Batalla De Brunete, 91",
    "sg:city":"Palmas De Gran Canaria",
    "sg:orig_category":"Centros Empresariales",
    "sg:phone":"+34 928 41 30 62",
    "sg:postcode":"35013",
    "sg:province":"Las Palmas",
    "wof:name":"Comcermovil S.l.",
    "wof:placetype":"venue"
},
  "geometry": {"coordinates":[-15.4485502243,28.0985965729],"type":"Point"}
}