{
  "type": "Feature",
  "properties": {
    "addr:full":"Puntagorda, S/n Taco Santa Cruz De Tenerife 38108",
    "addr:housenumber":"s / n",
    "addr:postcode":"38108",
    "addr:street":"Puntagorda",
    "iso:country":"ES",
    "sg:address":"Puntagorda, S/n",
    "sg:city":"Taco",
    "sg:orig_category":"Imprenta",
    "sg:phone":"+34 922 82 31 24",
    "sg:postcode":"38108",
    "sg:province":"Santa Cruz De Tenerife",
    "wof:name":"Litografia Trujillo S.l.",
    "wof:placetype":"venue"
},
  "geometry": {"coordinates":[-16.2994060516,28.4595127106],"type":"Point"}
}