{
  "type": "Feature",
  "properties": {
    "iso:country":"ES",
    "sg:address":"Calle de Barcelona (de), 5",
    "sg:city":"Alcobendas",
    "sg:orig_category":"Aparatos E Instalaci\u00d3n De Regad\u00cdos",
    "sg:phone":"+34 916 52 14 14",
    "sg:postcode":"28100",
    "sg:province":"Madrid",
    "sg:website":"www.frapimar.com",
    "wof:name":"Martin Lopez Maria Pilar 000520766d",
    "wof:placetype":"venue"
},
  "geometry": {"coordinates":[-3.6295866966,40.5412940979],"type":"Point"}
}