{
  "type": "Feature",
  "properties": {
    "iso:country":"ES",
    "sg:address":"C/ Bosc Tancat, S/n",
    "sg:city":"Cerdanyola Valles",
    "sg:orig_category":"Limpieza Industrial",
    "sg:phone":"+34 935 80 93 92",
    "sg:postcode":"08290",
    "sg:province":"Barcelona",
    "wof:name":"Flisa Catalu\u00f1a S.a.",
    "wof:placetype":"venue"
},
  "geometry": {"coordinates":[2.1340119839,41.5015335083],"type":"Point"}
}