{
  "type": "Feature",
  "properties": {
    "addr:full":"Carrer de Jaume Cantarer, 11 Terrassa Barcelona 08221",
    "addr:housenumber":"11",
    "addr:postcode":"08221",
    "addr:street":"Carrer De Jaume Cantarer",
    "iso:country":"ES",
    "sg:address":"Carrer de Jaume Cantarer, 11",
    "sg:city":"Terrassa",
    "sg:orig_category":"Institutos De Belleza",
    "sg:phone":"+34 937 33 60 10",
    "sg:postcode":"08221",
    "sg:province":"Barcelona",
    "wof:name":"Safrit Safrit Sl",
    "wof:placetype":"venue"
},
  "geometry": {"coordinates":[2.0112769604,41.5614509583],"type":"Point"}
}