{
  "type": "Feature",
  "properties": {
    "addr:full":"Calle de San Miguel, 14 Amorebieta-etxano Vizcaya 48340",
    "addr:housenumber":"14",
    "addr:postcode":"48340",
    "addr:street":"Calle De San Miguel",
    "iso:country":"ES",
    "sg:address":"Calle de San Miguel, 14",
    "sg:city":"Amorebieta-etxano",
    "sg:orig_category":"Quincaller\u00cda (al Por Menor)",
    "sg:phone":"+34 946 73 04 11",
    "sg:postcode":"48340",
    "sg:province":"Vizcaya",
    "wof:name":"Bricolaje Zornotza C.b.",
    "wof:placetype":"venue"
},
  "geometry": {"coordinates":[-2.732104063,43.2193412781],"type":"Point"}
}