{
  "type": "Feature",
  "properties": {
    "addr:full":"Avda Se\u00d1ores Baselga, 8 Utrillas Teruel 44760",
    "addr:housenumber":"8",
    "addr:postcode":"44760",
    "addr:street":"Avda Sen\u0303Ores Baselga",
    "iso:country":"ES",
    "sg:address":"Avda Se\u00d1ores Baselga, 8",
    "sg:city":"Utrillas",
    "sg:orig_category":"Confecci\u00d3n (fabricaci\u00d3n, Al Por Mayor)",
    "sg:phone":"+34 978 75 70 27",
    "sg:postcode":"44760",
    "sg:province":"Teruel",
    "wof:name":"Martin Martin Concepcion",
    "wof:placetype":"venue"
},
  "geometry": {"coordinates":[-0.8489739895,40.8119659424],"type":"Point"}
}