{
  "type": "Feature",
  "properties": {
    "addr:full":"Calle de Javier Ferrero, 8 Madrid Madrid 28002",
    "addr:housenumber":"8",
    "addr:postcode":"madrid;28002",
    "addr:street":"Calle De Javier Ferrero",
    "iso:country":"ES",
    "sg:address":"Calle de Javier Ferrero, 8",
    "sg:city":"Madrid",
    "sg:orig_category":"Traductores",
    "sg:phone":"+34 915 19 50 11",
    "sg:postcode":"28002",
    "sg:province":"Madrid",
    "wof:name":"Cibeles Internacional S.a.",
    "wof:placetype":"venue"
},
  "geometry": {"coordinates":[-3.6706700325,40.4482879639],"type":"Point"}
}