{
  "type": "Feature",
  "properties": {
    "addr:full":"Calle de Juan Ramon Jimenez, 57 Castellon Castell\u00f3n 12006",
    "addr:housenumber":"57",
    "addr:postcode":"12006",
    "addr:street":"Calle De Juan Ramon Jimenez",
    "iso:country":"ES",
    "sg:address":"Calle de Juan Ramon Jimenez, 57",
    "sg:city":"Castellon",
    "sg:orig_category":"Molduras, Junquillos, Listones Y Molduras Perforadas",
    "sg:phone":"+34 964 24 04 69",
    "sg:postcode":"12006",
    "sg:province":"Castell\u00f3n",
    "wof:name":"Lopez Arisa Jose Maria",
    "wof:placetype":"venue"
},
  "geometry": {"coordinates":[-0.1292939931,40.0168533325],"type":"Point"}
}