{
  "type": "Feature",
  "properties": {
    "addr:full":"Calle de Zabalbide, 28 Bilbao Vizcaya 48006",
    "addr:housenumber":"28",
    "addr:postcode":"48006",
    "addr:street":"Calle De Zabalbide",
    "iso:country":"ES",
    "sg:address":"Calle de Zabalbide, 28",
    "sg:city":"Bilbao",
    "sg:orig_category":"Muebles, Minoristas",
    "sg:phone":"+34 944 33 32 42",
    "sg:postcode":"48006",
    "sg:province":"Vizcaya",
    "wof:name":"Roberto De La Red",
    "wof:placetype":"venue"
},
  "geometry": {"coordinates":[-2.9197900295,43.2551765442],"type":"Point"}
}