{
  "type": "Feature",
  "properties": {
    "addr:full":"Avenida General Mola, 51 Cumbres Mayores Huelva 21380",
    "addr:housenumber":"51",
    "addr:postcode":"21380",
    "addr:street":"Avenida General Mola",
    "iso:country":"ES",
    "sg:address":"Avenida General Mola, 51",
    "sg:city":"Cumbres Mayores",
    "sg:orig_category":"Negocio De Materiales De Construcci\u00d3n",
    "sg:phone":"+34 959 71 01 71",
    "sg:postcode":"21380",
    "sg:province":"Huelva",
    "wof:name":"Pastor Franco S.l.",
    "wof:placetype":"venue"
},
  "geometry": {"coordinates":[-6.6494030952,38.0615844727],"type":"Point"}
}