{
  "type": "Feature",
  "properties": {
    "iso:country":"ES",
    "sg:address":"Calle de Juan Ramon Jimenez, 12",
    "sg:city":"Javea",
    "sg:orig_category":"Reposter\u00cdas",
    "sg:phone":"+34 965 79 56 60",
    "sg:postcode":"03730",
    "sg:province":"Alicante",
    "wof:name":"Gutierrez Corbacho Rafael",
    "wof:placetype":"venue"
},
  "geometry": {"coordinates":[0.1677760035,38.7901268005],"type":"Point"}
}