{
  "type": "Feature",
  "properties": {
    "iso:country":"ES",
    "sg:address":"Carrer de Apodaca (d'), 4",
    "sg:city":"Tarragona",
    "sg:orig_category":"Abogados",
    "sg:phone":"+34 977 23 35 32",
    "sg:postcode":"43004",
    "sg:province":"Tarragona",
    "wof:name":"Ventosa Ramon Jose Maria",
    "wof:placetype":"venue"
},
  "geometry": {"coordinates":[1.2510160208,41.1129379272],"type":"Point"}
}