{
  "type": "Feature",
  "properties": {
    "addr:full":"Calle de Andalucia, 20 Malaga M\u00e1laga 29009",
    "addr:housenumber":"20",
    "addr:postcode":"29009",
    "addr:street":"Calle De Andalucia;Ma\u0301Laga",
    "iso:country":"ES",
    "sg:address":"Calle de Andalucia, 20",
    "sg:city":"Malaga",
    "sg:orig_category":"Empresas De Carpinter\u00cda",
    "sg:phone":"+34 952 30 56 93",
    "sg:postcode":"29009",
    "sg:province":"M\u00e1laga",
    "sg:website":"www.costanet.es/sicilia/rafael.htm",
    "wof:name":"Sicilia Povea Rafael",
    "wof:placetype":"venue"
},
  "geometry": {"coordinates":[-4.4347839355,36.7238731384],"type":"Point"}
}