{
  "type": "Feature",
  "properties": {
    "addr:full":"Calle de Naval La, 132 Palmas De Gran Canaria Las Palmas 35008",
    "addr:housenumber":"132",
    "addr:postcode":"35008",
    "addr:street":"Calle De Naval La",
    "iso:country":"ES",
    "sg:address":"Calle de Naval La, 132",
    "sg:city":"Palmas De Gran Canaria",
    "sg:orig_category":"Comercio De Minerales, F\u00d3siles Y Conchas",
    "sg:phone":"+34 928 46 01 39",
    "sg:postcode":"35008",
    "sg:province":"Las Palmas",
    "wof:name":"Bascomoluz S.l.",
    "wof:placetype":"venue"
},
  "geometry": {"coordinates":[-15.4251747131,28.1498374939],"type":"Point"}
}