{
  "type": "Feature",
  "properties": {
    "addr:full":"Rua Romana Baixa, S/n Ramallosa Pontevedra 36379",
    "addr:housenumber":"s / n",
    "addr:postcode":"36379",
    "addr:street":"Rua Romana Baixa",
    "iso:country":"ES",
    "sg:address":"Rua Romana Baixa, S/n",
    "sg:city":"Ramallosa",
    "sg:orig_category":"Cervecer\u00cdas",
    "sg:phone":"+34 986 35 37 30",
    "sg:postcode":"36379",
    "sg:province":"Pontevedra",
    "wof:name":"Otero Cabral Alberto",
    "wof:placetype":"venue"
},
  "geometry": {"coordinates":[-8.8115091324,42.117931366],"type":"Point"}
}