{
  "type": "Feature",
  "properties": {
    "iso:country":"ES",
    "sg:address":"Calle de Colombia, 18",
    "sg:city":"Salamanca",
    "sg:orig_category":"Molduras, Junquillos, Listones Y Molduras Perforadas",
    "sg:phone":"+34 923 18 10 71",
    "sg:postcode":"37003",
    "sg:province":"Salamanca",
    "wof:name":"Martin Rodriguez Francisco",
    "wof:placetype":"venue"
},
  "geometry": {"coordinates":[-5.6457295418,40.9687347412],"type":"Point"}
}