{
  "type": "Feature",
  "properties": {
    "addr:full":"Calle de Ernesto Mendez Luengo, 38 Ba\u00d1eza Le\u00f3n 24750",
    "addr:housenumber":"38",
    "addr:postcode":"24750",
    "addr:street":"Calle De Ernesto Mendez Luengo;Leo\u0301N",
    "iso:country":"ES",
    "sg:address":"Calle de Ernesto Mendez Luengo, 38",
    "sg:city":"Ba\u00d1eza",
    "sg:orig_category":"Venta Al Preg\u00d3n",
    "sg:phone":"+34 987 64 37 92",
    "sg:postcode":"24750",
    "sg:province":"Le\u00f3n",
    "wof:name":"Alvarez Lage Pedro",
    "wof:placetype":"venue"
},
  "geometry": {"coordinates":[-5.9084801674,42.2992782593],"type":"Point"}
}