{
  "type": "Feature",
  "properties": {
    "iso:country":"ES",
    "sg:address":"Pl. Ca\u00f1os, 11",
    "sg:city":"Villacastin",
    "sg:orig_category":"Alimentaci\u00d3n General (al Por Menor)",
    "sg:phone":"+34 921 19 70 44",
    "sg:postcode":"40150",
    "sg:province":"Segovia",
    "wof:name":"Jose Manuel Garcia Rodriguez Y Otros Cdad",
    "wof:placetype":"venue"
},
  "geometry": {"coordinates":[-4.4098091125,40.7774505615],"type":"Point"}
}