{
  "type": "Feature",
  "properties": {
    "addr:full":"Agrovello, S/n Agrovello Pontevedra 36153",
    "addr:postcode":"36153",
    "addr:street":"Agrovello S / N",
    "iso:country":"ES",
    "sg:address":"Agrovello, S/n",
    "sg:city":"Agrovello",
    "sg:orig_category":"Construcci\u00d3n De Edificios Residenciales Y No Residenciales",
    "sg:phone":"+34 986 85 44 50",
    "sg:postcode":"36153",
    "sg:province":"Pontevedra",
    "wof:name":"Moreira Area Luis",
    "wof:placetype":"venue"
},
  "geometry": {"coordinates":[-8.6208295822,42.4854545593],"type":"Point"}
}