{
  "type": "Feature",
  "properties": {
    "addr:full":"Carrer de Jussa (de), 1 Arbo\u00e7 Tarragona 43720",
    "addr:postcode":"43720",
    "addr:street":"Carrer De Jussa De 1 Arboc\u0327",
    "iso:country":"ES",
    "sg:address":"Carrer de Jussa (de), 1",
    "sg:city":"Arbo\u00e7",
    "sg:orig_category":"Ebanister\u00cda",
    "sg:phone":"+34 977 67 04 60",
    "sg:postcode":"43720",
    "sg:province":"Tarragona",
    "wof:name":"Roquer Hugue Jose",
    "wof:placetype":"venue"
},
  "geometry": {"coordinates":[1.6035300493,41.2669296265],"type":"Point"}
}