{
  "type": "Feature",
  "properties": {
    "iso:country":"ES",
    "sg:address":"Calle de Villalobos, 129",
    "sg:city":"Madrid",
    "sg:orig_category":"Frutas Y Legumbres Frescas (al Por Mayor)",
    "sg:phone":"+34 913 03 47 95",
    "sg:postcode":"28018",
    "sg:province":"Madrid",
    "wof:name":"Hernandez Barbero Marcelino",
    "wof:placetype":"venue"
},
  "geometry": {"coordinates":[-3.6512880325,40.3809013367],"type":"Point"}
}