{
  "type": "Feature",
  "properties": {
    "addr:full":"Avda America (de), 7 Cordoba C\u00f3rdoba 14008",
    "addr:housenumber":"7",
    "addr:postcode":"14008",
    "addr:street":"Avda America De;Co\u0301Rdoba",
    "iso:country":"ES",
    "sg:address":"Avda America (de), 7",
    "sg:city":"Cordoba",
    "sg:orig_category":"Suministros Para Pr\u00d3tesis",
    "sg:phone":"+34 957 48 02 73",
    "sg:postcode":"14008",
    "sg:province":"C\u00f3rdoba",
    "wof:name":"Clinica Zenit C.b.",
    "wof:placetype":"venue"
},
  "geometry": {"coordinates":[-4.7829790115,37.8905906677],"type":"Point"}
}