{
  "type": "Feature",
  "properties": {
    "iso:country":"ES",
    "sg:address":"Calle de Mayor, 20",
    "sg:city":"Horcajada",
    "sg:orig_category":"Farmacias",
    "sg:phone":"+34 920 36 40 31",
    "sg:postcode":"05695",
    "sg:province":"\u00c1vila",
    "wof:name":"Sanchez Gil Esther",
    "wof:placetype":"venue"
},
  "geometry": {"coordinates":[-5.4683389664,40.435798645],"type":"Point"}
}