{
  "type": "Feature",
  "properties": {
    "iso:country":"ES",
    "sg:address":"Calle de Convento, 37",
    "sg:city":"Zalamea Serena",
    "sg:orig_category":"Mec\u00c1nico Del Autom\u00d3vil",
    "sg:phone":"+34 924 77 52 87",
    "sg:postcode":"06430",
    "sg:province":"Badajoz",
    "wof:name":"Centeno Davila Ventura",
    "wof:placetype":"venue"
},
  "geometry": {"coordinates":[-5.6565861702,38.6474494934],"type":"Point"}
}