{
  "type": "Feature",
  "properties": {
    "iso:country":"ES",
    "sg:address":"Calle de Santa Marina, 37",
    "sg:city":"Villarcayo",
    "sg:orig_category":"Asesor\u00cda Fiscal Y Jur\u00cddica",
    "sg:phone":"+34 947 13 01 32",
    "sg:postcode":"09550",
    "sg:province":"Burgos",
    "wof:name":"Mafe Asesores S.l.",
    "wof:placetype":"venue"
},
  "geometry": {"coordinates":[-3.5747680664,42.9385871887],"type":"Point"}
}