{
  "type": "Feature",
  "properties": {
    "addr:full":"Ctra Ayora, Km. 0075,5 Albacete Albacete 02001",
    "addr:postcode":"02001",
    "addr:street":"Ctra Ayora Km. 0075,5",
    "iso:country":"ES",
    "sg:address":"Ctra Ayora, Km. 0075,5",
    "sg:city":"Albacete",
    "sg:orig_category":"Autob\u00das (explotaci\u00d3n Y Servicios De)",
    "sg:phone":"+34 967 21 43 78",
    "sg:postcode":"02001",
    "sg:province":"Albacete",
    "sg:website":"www.feda.es/requenen/index.htm",
    "wof:name":"La Requenense De Autobuses C. L. S. A.",
    "wof:placetype":"venue"
},
  "geometry": {"coordinates":[-1.8540610075,38.9950675964],"type":"Point"}
}