{
  "type": "Feature",
  "properties": {
    "addr:full":"Calle de Correo, 12 Bilbao Vizcaya 48005",
    "addr:housenumber":"12",
    "addr:postcode":"48005",
    "addr:street":"Calle De Correo",
    "iso:country":"ES",
    "sg:address":"Calle de Correo, 12",
    "sg:city":"Bilbao",
    "sg:orig_category":"Fabricaci\u00d3n, Importaci\u00d3n, Venta De Material De Telefon\u00cda, Peritelefon\u00cda",
    "sg:phone":"+34 944 15 44 12",
    "sg:postcode":"48005",
    "sg:province":"Vizcaya",
    "wof:name":"Phone Warehouse S.l.",
    "wof:placetype":"venue"
},
  "geometry": {"coordinates":[-2.9235408306,43.2585525513],"type":"Point"}
}