{
  "type": "Feature",
  "properties": {
    "addr:full":"Calle de Carlos Amel, S/n Malaga M\u00e1laga 29006",
    "addr:housenumber":"s",
    "addr:postcode":"29006",
    "addr:street":"Calle De Carlos Amel;/ N;Ma\u0301Laga",
    "iso:country":"ES",
    "sg:address":"Calle de Carlos Amel, S/n",
    "sg:city":"Malaga",
    "sg:orig_category":"Electricidad (montaje, Ensamblaje De Componentes)",
    "sg:phone":"+34 952 33 60 47",
    "sg:postcode":"29006",
    "sg:province":"M\u00e1laga",
    "wof:name":"Rojas Li\u00f1an Alfonso",
    "wof:placetype":"venue"
},
  "geometry": {"coordinates":[-4.4413099289,36.7089309692],"type":"Point"}
}