{
  "type": "Feature",
  "properties": {
    "addr:full":"Calle de Pintor Mendoza, 66 Valdepe\u00f1as Ciudad Real 13300",
    "addr:housenumber":"66",
    "addr:postcode":"13300",
    "addr:street":"Calle De Pintor Mendoza",
    "iso:country":"ES",
    "sg:address":"Calle de Pintor Mendoza, 66",
    "sg:city":"Valdepe\u00f1as",
    "sg:orig_category":"M\u00c9dicos: Cardiolog\u00cda Y Afecciones Cardiovasculares",
    "sg:phone":"+34 926 32 35 32",
    "sg:postcode":"13300",
    "sg:province":"Ciudad Real",
    "wof:name":"Bartolome Piedrabuena Antonio",
    "wof:placetype":"venue"
},
  "geometry": {"coordinates":[-3.383548975,38.7614593506],"type":"Point"}
}