{
  "type": "Feature",
  "properties": {
    "addr:full":"Urb Cumbres Nagueles, 11 Marbella M\u00e1laga 29600",
    "addr:housenumber":"11",
    "addr:postcode":"29600",
    "addr:street":"Urb;Nagueles;Ma\u0301Laga",
    "iso:country":"ES",
    "sg:address":"Urb Cumbres Nagueles, 11",
    "sg:city":"Marbella",
    "sg:orig_category":"Herboristas (al Por Menor)",
    "sg:phone":"+34 952 77 08 74",
    "sg:postcode":"29600",
    "sg:province":"M\u00e1laga",
    "wof:name":"Nazareno Y Carmen S.l.",
    "wof:placetype":"venue"
},
  "geometry": {"coordinates":[-4.8833007812,36.5079956055],"type":"Point"}
}