{
  "type": "Feature",
  "properties": {
    "iso:country":"ES",
    "sg:address":"Calle de Merida, 1",
    "sg:city":"Zarza",
    "sg:orig_category":"Restaurantes",
    "sg:phone":"+34 924 36 63 50",
    "sg:postcode":"06830",
    "sg:province":"Badajoz",
    "wof:name":"Lopez Trinidad Francisco",
    "wof:placetype":"venue"
},
  "geometry": {"coordinates":[-6.2216892242,38.8198890686],"type":"Point"}
}