{
  "type": "Feature",
  "properties": {
    "iso:country":"ES",
    "sg:address":"Pase Parque (del), 4",
    "sg:city":"Alcazar S. Juan",
    "sg:orig_category":"Inmobiliaria (agencias)",
    "sg:phone":"+34 926 54 20 58",
    "sg:postcode":"13600",
    "sg:province":"Ciudad Real",
    "wof:name":"Urbalcazar S.l.",
    "wof:placetype":"venue"
},
  "geometry": {"coordinates":[-3.210203886,39.3900718689],"type":"Point"}
}