{
  "type": "Feature",
  "properties": {
    "iso:country":"ES",
    "sg:address":"Calle de Extramuros De Calatrava, S/n",
    "sg:city":"Ciudad Real",
    "sg:orig_category":"Agencias Y Agentes Comerciales, Representantes",
    "sg:phone":"+34 926 22 34 03",
    "sg:postcode":"13003",
    "sg:province":"Ciudad Real",
    "wof:name":"Morales Morales Luis",
    "wof:placetype":"venue"
},
  "geometry": {"coordinates":[-3.9301741123,38.9844093323],"type":"Point"}
}