{
  "type": "Feature",
  "properties": {
    "addr:full":"Carrer de Vidriers (dels), S/n Vendrell Tarragona 43700",
    "addr:housenumber":"/ n",
    "addr:postcode":"43700",
    "addr:street":"Carrer De Vidriers Dels S",
    "iso:country":"ES",
    "sg:address":"Carrer de Vidriers (dels), S/n",
    "sg:city":"Vendrell",
    "sg:orig_category":"Distribuci\u00d3n De Petr\u00d3leo Y Derivados",
    "sg:phone":"+34 977 66 17 18",
    "sg:postcode":"43700",
    "sg:province":"Tarragona",
    "wof:name":"Distribuidora De Carburantes Vendrell S.l.",
    "wof:placetype":"venue"
},
  "geometry": {"coordinates":[1.5309499502,41.2295150757],"type":"Point"}
}