{
  "type": "Feature",
  "properties": {
    "iso:country":"ES",
    "sg:address":"Calle de Joaquin Cayon, 35",
    "sg:city":"Torrelavega",
    "sg:orig_category":"Bisuter\u00cda, Joyer\u00cda, Relojer\u00cda (al Por Menor)",
    "sg:phone":"+34 942 80 05 53",
    "sg:postcode":"39300",
    "sg:province":"Cantabria",
    "wof:name":"Castillo Calleja Alfredo",
    "wof:placetype":"venue"
},
  "geometry": {"coordinates":[-4.0547571182,43.3474807739],"type":"Point"}
}