{
  "type": "Feature",
  "properties": {
    "addr:full":"Calle de Puerta Del Mercado, 34 Toro Zamora 49800",
    "addr:housenumber":"34",
    "addr:postcode":"49800",
    "addr:street":"Calle De Puerta Del Mercado",
    "iso:country":"ES",
    "sg:address":"Calle de Puerta Del Mercado, 34",
    "sg:city":"Toro",
    "sg:orig_category":"Alimentaci\u00d3n General (al Por Menor)",
    "sg:phone":"+34 980 69 03 79",
    "sg:postcode":"49800",
    "sg:province":"Zamora",
    "wof:name":"Perez Martinez Felix",
    "wof:placetype":"venue"
},
  "geometry": {"coordinates":[-5.3929429054,41.5225601196],"type":"Point"}
}