{
  "type": "Feature",
  "properties": {
    "addr:full":"Carr Liszt, 69 Badalona Barcelona 08917",
    "addr:housenumber":"69",
    "addr:postcode":"08917",
    "addr:street":"Carr Liszt",
    "iso:country":"ES",
    "sg:address":"Carr Liszt, 69",
    "sg:city":"Badalona",
    "sg:orig_category":"Empresas De Carpinter\u00cda",
    "sg:phone":"+34 933 83 90 08",
    "sg:postcode":"08917",
    "sg:province":"Barcelona",
    "wof:name":"Montilla Corral Alfonso",
    "wof:placetype":"venue"
},
  "geometry": {"coordinates":[2.222340107,41.4509086609],"type":"Point"}
}