{
  "type": "Feature",
  "properties": {
    "addr:full":"Martinez Agosti, 22 Infiesto Asturias 33530",
    "addr:housenumber":"22",
    "addr:postcode":"33530",
    "addr:street":"Agosti",
    "iso:country":"ES",
    "sg:address":"Martinez Agosti, 22",
    "sg:city":"Infiesto",
    "sg:orig_category":"Art\u00cdculos Funerarios (al Por Menor)",
    "sg:phone":"+34 985 71 03 02",
    "sg:postcode":"33530",
    "sg:province":"Asturias",
    "wof:name":"Funerarias Del Oriente De Asturias S.a.",
    "wof:placetype":"venue"
},
  "geometry": {"coordinates":[-5.3667430878,43.350933075],"type":"Point"}
}