{
  "type": "Feature",
  "properties": {
    "iso:country":"ES",
    "sg:address":"Carrer de Carreras I Candi, 91",
    "sg:city":"Barcelona",
    "sg:orig_category":"Agencias Y Agentes Comerciales, Representantes",
    "sg:phone":"+34 932 96 40 16",
    "sg:postcode":"08028",
    "sg:province":"Barcelona",
    "wof:name":"Esteve Garcia Montserrat",
    "wof:placetype":"venue"
},
  "geometry": {"coordinates":[2.129019022,41.3717193604],"type":"Point"}
}