{
  "type": "Feature",
  "properties": {
    "addr:full":"Carrer de Pau Vergos, 90 Gava Barcelona 08850",
    "addr:housenumber":"90",
    "addr:postcode":"08850",
    "addr:street":"Carrer De Pau Vergos",
    "iso:country":"ES",
    "sg:address":"Carrer de Pau Vergos, 90",
    "sg:city":"Gava",
    "sg:orig_category":"Mec\u00c1nico Del Autom\u00d3vil",
    "sg:phone":"+34 936 62 98 02",
    "sg:postcode":"08850",
    "sg:province":"Barcelona",
    "wof:name":"Merlo Cano Antonio",
    "wof:placetype":"venue"
},
  "geometry": {"coordinates":[1.9973069429,41.3024139404],"type":"Point"}
}