{
  "type": "Feature",
  "properties": {
    "addr:full":"Calle de Puerto Guadarrama, 22 Nieves-el Lucero Madrid 28935",
    "addr:housenumber":"22",
    "addr:postcode":"28935",
    "addr:street":"Calle De Puerto Guadarrama;Nieves-El",
    "iso:country":"ES",
    "sg:address":"Calle de Puerto Guadarrama, 22",
    "sg:city":"Nieves-el Lucero",
    "sg:orig_category":"Fabricaci\u00d3n, Instalaci\u00d3n Y Reparaci\u00d3n De Bombas",
    "sg:phone":"+34 916 16 90 92",
    "sg:postcode":"28935",
    "sg:province":"Madrid",
    "wof:name":"Grupo Aliser S.a.",
    "wof:placetype":"venue"
},
  "geometry": {"coordinates":[-3.9280939102,40.3081817627],"type":"Point"}
}