{
  "type": "Feature",
  "properties": {
    "iso:country":"ES",
    "sg:address":"Aptos Hermosa, S/n",
    "sg:city":"Alfas Pi",
    "sg:orig_category":"Inversiones",
    "sg:phone":"+34 966 86 58 44",
    "sg:postcode":"03580",
    "sg:province":"Alicante",
    "wof:name":"Salle Investments",
    "wof:placetype":"venue"
},
  "geometry": {"coordinates":[-0.1106439978,38.5881652832],"type":"Point"}
}