{
  "type": "Feature",
  "properties": {
    "addr:full":"B. Clot Moro, S/n Castellar N'hug Barcelona 08696",
    "addr:housenumber":"s / n",
    "addr:postcode":"08696",
    "addr:street":"N'Hug Barcelona",
    "iso:country":"ES",
    "sg:address":"B. Clot Moro, S/n",
    "sg:city":"Castellar N'hug",
    "sg:orig_category":"Museos",
    "sg:phone":"+34 938 25 70 37",
    "sg:postcode":"08696",
    "sg:province":"Barcelona",
    "wof:name":"Ajuntament De Castellar De N'hug",
    "wof:placetype":"venue"
},
  "geometry": {"coordinates":[1.9826562405,42.2613296509],"type":"Point"}
}