{
  "type": "Feature",
  "properties": {
    "iso:country":"ES",
    "sg:address":"Calle de Marques De La Ensenada, 7",
    "sg:city":"Logro\u00f1o",
    "sg:orig_category":"Rectificaci\u00d3n, Mecanizado, Fresado",
    "sg:phone":"+34 941 25 54 24",
    "sg:postcode":"26003",
    "sg:province":"La Rioja",
    "wof:name":"Miguel Angel I\u00f1igo Lopez Y Miguel Martinez Asensio S.cv.",
    "wof:placetype":"venue"
},
  "geometry": {"coordinates":[-2.4378099442,42.4639434814],"type":"Point"}
}