{
  "type": "Feature",
  "properties": {
    "iso:country":"ES",
    "sg:address":"Calle de Agustin Lopez, 22",
    "sg:city":"Villaviciosa Cordoba",
    "sg:orig_category":"Carnicer\u00cdas, Carnicer\u00cdas",
    "sg:phone":"+34 957 36 01 43",
    "sg:postcode":"14300",
    "sg:province":"C\u00f3rdoba",
    "wof:name":"Cano Gonzalez Jose",
    "wof:placetype":"venue"
},
  "geometry": {"coordinates":[-5.0121417046,38.0787315369],"type":"Point"}
}