{
  "type": "Feature",
  "properties": {
    "addr:full":"Calle de Comedias, 16 Malaga M\u00e1laga 29008",
    "addr:housenumber":"16",
    "addr:postcode":"29008",
    "addr:street":"Calle De Comedias;Ma\u0301Laga",
    "iso:country":"ES",
    "sg:address":"Calle de Comedias, 16",
    "sg:city":"Malaga",
    "sg:orig_category":"Edici\u00d3n De Diarios, Revistas, Boletines",
    "sg:phone":"+34 952 60 11 91",
    "sg:postcode":"29008",
    "sg:province":"M\u00e1laga",
    "sg:website":"www.libreriaabadia.com",
    "wof:name":"Soler Fernandez Francisco Manuel",
    "wof:placetype":"venue"
},
  "geometry": {"coordinates":[-4.4213857651,36.7228279114],"type":"Point"}
}