{
  "type": "Feature",
  "properties": {
    "iso:country":"ES",
    "sg:address":"Plaz Alcalde Domingo Torres, 4",
    "sg:city":"Valencia",
    "sg:orig_category":"Arquitectos",
    "sg:phone":"+34 963 61 86 50",
    "sg:postcode":"46020",
    "sg:province":"Valencia",
    "wof:name":"Bonacho Beneyto Antonio",
    "wof:placetype":"venue"
},
  "geometry": {"coordinates":[-0.3582209945,39.4816398621],"type":"Point"}
}