{
  "type": "Feature",
  "properties": {
    "iso:country":"ES",
    "sg:address":"La Hermida, S/n",
    "sg:city":"La Hermida",
    "sg:orig_category":"Empresas De Electricidad En General",
    "sg:phone":"+34 942 73 35 04",
    "sg:postcode":"39580",
    "sg:province":"Cantabria",
    "wof:name":"Enel Viesgo Servicios S.l.",
    "wof:placetype":"venue"
},
  "geometry": {"coordinates":[-4.6132397652,43.2548522949],"type":"Point"}
}