{
  "type": "Feature",
  "properties": {
    "iso:country":"ES",
    "sg:address":"Calle de Miguel Servet, 17",
    "sg:city":"Zaragoza",
    "sg:orig_category":"Molduras, Junquillos, Listones Y Molduras Perforadas",
    "sg:phone":"+34 976 59 55 56",
    "sg:postcode":"50002",
    "sg:province":"Zaragoza",
    "wof:name":"Bielsa Pons S.l.",
    "wof:placetype":"venue"
},
  "geometry": {"coordinates":[-0.873398006,41.6473007202],"type":"Point"}
}