{
  "type": "Feature",
  "properties": {
    "iso:country":"ES",
    "sg:address":"Calle de Zabalza Tajonar, S/n",
    "sg:city":"Pedroso",
    "sg:orig_category":"Empresas De Electricidad En General",
    "sg:phone":"+34 954 88 92 91",
    "sg:postcode":"41360",
    "sg:province":"Sevilla",
    "wof:name":"Endesa Servicios S.l. Sociedad Unipersonal",
    "wof:placetype":"venue"
},
  "geometry": {"coordinates":[-5.7654428482,37.8436012268],"type":"Point"}
}