{
  "type": "Feature",
  "properties": {
    "addr:full":"Av Carles Buigas (de), 14 Salou Tarragona 43840",
    "addr:housenumber":"14",
    "addr:postcode":"43840",
    "addr:street":"Av Carles Buigas De",
    "iso:country":"ES",
    "sg:address":"Av Carles Buigas (de), 14",
    "sg:city":"Salou",
    "sg:orig_category":"Art\u00cdculos De Regalo (al Por Menor)",
    "sg:phone":"+34 977 38 04 77",
    "sg:postcode":"43840",
    "sg:province":"Tarragona",
    "wof:name":"Kumar  Rajesh",
    "wof:placetype":"venue"
},
  "geometry": {"coordinates":[1.1470210552,41.0726928711],"type":"Point"}
}