{
  "type": "Feature",
  "properties": {
    "iso:country":"ES",
    "sg:address":"Calle de Castillo, 37",
    "sg:city":"Topas",
    "sg:orig_category":"Cerrajer\u00cda, Ferrallista",
    "sg:phone":"+34 923 35 50 28",
    "sg:postcode":"37799",
    "sg:province":"Salamanca",
    "wof:name":"Pablos Perez Aristides",
    "wof:placetype":"venue"
},
  "geometry": {"coordinates":[-5.6343970299,41.1566200256],"type":"Point"}
}