{
  "type": "Feature",
  "properties": {
    "iso:country":"ES",
    "sg:address":"El Fresno, 1",
    "sg:city":"Villatoro",
    "sg:orig_category":"Agencias Y Agentes Comerciales, Representantes",
    "sg:phone":"+34 947 29 33 74",
    "sg:postcode":"09006",
    "sg:province":"Burgos",
    "wof:name":"Sebastian Casta\u00f1o David",
    "wof:placetype":"venue"
},
  "geometry": {"coordinates":[-3.6945519447,42.3765716553],"type":"Point"}
}