{
  "type": "Feature",
  "properties": {
    "addr:full":"Av Europa, 176 Hospitalet Llobregat Barcelona 08907",
    "addr:housenumber":"176",
    "addr:postcode":"08907",
    "addr:street":"Av Europa",
    "iso:country":"ES",
    "sg:address":"Av Europa, 176",
    "sg:city":"Hospitalet Llobregat",
    "sg:orig_category":"Asociaciones, Organismos Culturales Y Socioeducativos",
    "sg:phone":"+34 933 36 53 26",
    "sg:postcode":"08907",
    "sg:province":"Barcelona",
    "wof:name":"Centro Andaluz Casa De Huelva",
    "wof:placetype":"venue"
},
  "geometry": {"coordinates":[2.1139600277,41.3565101624],"type":"Point"}
}