{
  "type": "Feature",
  "properties": {
    "addr:full":"Senpere Auzoa, S/n Senpere Guip\u00f9zcoa 20210",
    "addr:housenumber":"s / n",
    "addr:postcode":"20210",
    "addr:street":"Senpere Auzoa;Senpere Guipu\u0300Zcoa",
    "iso:country":"ES",
    "sg:address":"Senpere Auzoa, S/n",
    "sg:city":"Senpere",
    "sg:orig_category":"Panader\u00cdas, Panader\u00cdas",
    "sg:phone":"+34 943 88 70 30",
    "sg:postcode":"20210",
    "sg:province":"Guip\u00f9zcoa",
    "wof:name":"Arruabarrena Arruabarrena Juan Antonio",
    "wof:placetype":"venue"
},
  "geometry": {"coordinates":[-2.1873590946,43.0314903259],"type":"Point"}
}