{
  "type": "Feature",
  "properties": {
    "addr:full":"Calle de San Adrian De Sasabe, 6 Zaragoza Zaragoza 50002",
    "addr:housenumber":"6",
    "addr:postcode":"50002",
    "addr:street":"Calle De San Adrian De Sasabe",
    "iso:country":"ES",
    "sg:address":"Calle de San Adrian De Sasabe, 6",
    "sg:city":"Zaragoza",
    "sg:orig_category":"Empresas De Carpinter\u00cda De Madera",
    "sg:phone":"+34 976 59 00 44",
    "sg:postcode":"50002",
    "sg:province":"Zaragoza",
    "wof:name":"Bueno Lafuente Rafael",
    "wof:placetype":"venue"
},
  "geometry": {"coordinates":[-0.8596889973,41.6420288086],"type":"Point"}
}