{
  "type": "Feature",
  "properties": {
    "iso:country":"ES",
    "sg:address":"Rua Velazquez, 32",
    "sg:city":"Ourense",
    "sg:orig_category":"Peluqueros: De Se\u00d1oras",
    "sg:phone":"+34 988 24 38 66",
    "sg:postcode":"32002",
    "sg:province":"Ourense",
    "wof:name":"Touceda Lamas Carmen",
    "wof:placetype":"venue"
},
  "geometry": {"coordinates":[-7.8741202354,42.3433952332],"type":"Point"}
}