{
  "type": "Feature",
  "properties": {
    "iso:country":"ES",
    "sg:address":"Calle de Carquizano, 11",
    "sg:city":"Donostia-san Sebastian",
    "sg:orig_category":"Par\u00cds",
    "sg:phone":"+34 943 27 83 43",
    "sg:postcode":"20001",
    "sg:province":"Guip\u00f9zcoa",
    "wof:name":"Garcia Escribano Jesus",
    "wof:placetype":"venue"
},
  "geometry": {"coordinates":[-1.9735995531,43.3225288391],"type":"Point"}
}