{
  "type": "Feature",
  "properties": {
    "iso:country":"ES",
    "sg:address":"Calle de Fray Norberto Del Prado, 2",
    "sg:city":"Pola De Laviana",
    "sg:orig_category":"Herboristas (al Por Menor)",
    "sg:phone":"+34 985 61 04 08",
    "sg:postcode":"33980",
    "sg:province":"Asturias",
    "wof:name":"Corral Ferrero Jose Luis",
    "wof:placetype":"venue"
},
  "geometry": {"coordinates":[-5.5604090691,43.2430038452],"type":"Point"}
}