{
  "type": "Feature",
  "properties": {
    "addr:full":"Carr Caama\u00d1o, 8 Figueres Girona 17600",
    "addr:housenumber":"8",
    "addr:postcode":"17600",
    "addr:street":"Carr Caaman\u0303O",
    "iso:country":"ES",
    "sg:address":"Carr Caama\u00d1o, 8",
    "sg:city":"Figueres",
    "sg:orig_category":"Procuradores",
    "sg:phone":"+34 972 50 55 38",
    "sg:postcode":"17600",
    "sg:province":"Girona",
    "wof:name":"Serra Roca Jose Maria",
    "wof:placetype":"venue"
},
  "geometry": {"coordinates":[2.9631519318,42.2665786743],"type":"Point"}
}