{
  "type": "Feature",
  "properties": {
    "iso:country":"ES",
    "sg:address":"Calle de Mayor, 8",
    "sg:city":"Moratalla",
    "sg:orig_category":"Semiller\u00cdas",
    "sg:phone":"+34 968 73 01 83",
    "sg:postcode":"30440",
    "sg:province":"Murcia",
    "wof:name":"Viveros El Rincon S.l.",
    "wof:placetype":"venue"
},
  "geometry": {"coordinates":[-1.8930203915,38.1914024353],"type":"Point"}
}