{
  "type": "Feature",
  "properties": {
    "iso:country":"ES",
    "sg:address":"Calle de Juan Rejon, 89",
    "sg:city":"Palmas De Gran Canaria",
    "sg:orig_category":"Arboricultura Y Producci\u00d3n De Frutas",
    "sg:phone":"+34 928 30 32 02",
    "sg:postcode":"35...",
    "sg:province":"Las Palmas",
    "sg:website":"www.bonnysat.com",
    "wof:name":"S.a.t Juliano Bonny Gomez Num 9592",
    "wof:placetype":"venue"
},
  "geometry": {"coordinates":[-15.4247808456,28.1494636536],"type":"Point"}
}