{
  "type": "Feature",
  "properties": {
    "iso:country":"ES",
    "sg:address":"Calle de General Prim, 24",
    "sg:city":"Alcazar S. Juan",
    "sg:orig_category":"Empresarios",
    "sg:phone":"+34 926 54 00 89",
    "sg:postcode":"13600",
    "sg:province":"Ciudad Real",
    "wof:name":"Abengozar Muela Jesus Cristobal",
    "wof:placetype":"venue"
},
  "geometry": {"coordinates":[-3.218357,39.39365],"type":"Point"}
}