{
  "type": "Feature",
  "properties": {
    "iso:country":"ES",
    "sg:address":"Calle de Encomienda, 15",
    "sg:city":"Solana",
    "sg:orig_category":"Asesor\u00cda Fiscal Y Jur\u00cddica",
    "sg:phone":"+34 926 63 18 96",
    "sg:postcode":"13240",
    "sg:province":"Ciudad Real",
    "wof:name":"Sanchez Lopez De Lerma Francisco",
    "wof:placetype":"venue"
},
  "geometry": {"coordinates":[-3.2394449711,38.9402503967],"type":"Point"}
}