{
  "type": "Feature",
  "properties": {
    "addr:full":"Carr Balaguer, 8 Bellcaire D'urgell Lleida 25337",
    "addr:housenumber":"8",
    "addr:postcode":"25337",
    "addr:street":"Carr Balaguer",
    "iso:country":"ES",
    "sg:address":"Carr Balaguer, 8",
    "sg:city":"Bellcaire D'urgell",
    "sg:orig_category":"Cr\u00cda De Animales",
    "sg:phone":"+34 973 58 64 90",
    "sg:postcode":"25337",
    "sg:province":"Lleida",
    "wof:name":"Granja Feliu Sl",
    "wof:placetype":"venue"
},
  "geometry": {"coordinates":[0.9013043046,41.7613983154],"type":"Point"}
}