{
  "type": "Feature",
  "properties": {
    "iso:country":"ES",
    "sg:address":"Co. Rega\u00f1ados, S/n",
    "sg:city":"Aldeaseca Armu\u00f1a",
    "sg:orig_category":"Semiller\u00cdas",
    "sg:phone":"+34 923 16 01 47",
    "sg:postcode":"37189",
    "sg:province":"Salamanca",
    "wof:name":"Viveros Eriflor S.l.",
    "wof:placetype":"venue"
},
  "geometry": {"coordinates":[-5.6630473137,40.9649734497],"type":"Point"}
}