{
  "type": "Feature",
  "properties": {
    "addr:full":"Carrer de Josep Anselm Clave, 3 Castellar Valles Barcelona 08211",
    "addr:housenumber":"3",
    "addr:postcode":"08211",
    "addr:street":"Carrer De Josep Anselm Clave",
    "iso:country":"ES",
    "sg:address":"Carrer de Josep Anselm Clave, 3",
    "sg:city":"Castellar Valles",
    "sg:orig_category":"Psic\u00d3logos",
    "sg:phone":"+34 937 14 63 52",
    "sg:postcode":"08211",
    "sg:province":"Barcelona",
    "wof:name":"Psico Valles S.c.p.",
    "wof:placetype":"venue"
},
  "geometry": {"coordinates":[2.0857300758,41.6151885986],"type":"Point"}
}