{
  "type": "Feature",
  "properties": {
    "addr:full":"Calle de Isla De Tenerife, 3 Llanos Las Palmas 35330",
    "addr:housenumber":"3",
    "addr:postcode":"35330",
    "addr:street":"Calle De Isla De Tenerife",
    "iso:country":"ES",
    "sg:address":"Calle de Isla De Tenerife, 3",
    "sg:city":"Llanos",
    "sg:orig_category":"Delegados, Agentes De Tr\u00c1nsito, Auxiliares De Transporte Internacional",
    "sg:phone":"+34 928 63 13 17",
    "sg:postcode":"35330",
    "sg:province":"Las Palmas",
    "wof:name":"Quintana Dominguez Jose Ildefonso",
    "wof:placetype":"venue"
},
  "geometry": {"coordinates":[-15.5535802841,28.0600013733],"type":"Point"}
}