{
  "type": "Feature",
  "properties": {
    "addr:full":"Calle de Santuario, 22 Montijo Badajoz 06480",
    "addr:housenumber":"22",
    "addr:postcode":"06480",
    "addr:street":"Calle De Santuario",
    "iso:country":"ES",
    "sg:address":"Calle de Santuario, 22",
    "sg:city":"Montijo",
    "sg:orig_category":"Empresas De Carpinter\u00cda De Madera",
    "sg:phone":"+34 924 45 70 70",
    "sg:postcode":"06480",
    "sg:province":"Badajoz",
    "wof:name":"Alfonso Romero Y Geronimo Pascual C.b.",
    "wof:placetype":"venue"
},
  "geometry": {"coordinates":[-6.6045207977,38.9039649963],"type":"Point"}
}