{
  "type": "Feature",
  "properties": {
    "addr:full":"Carrer de Napols, 188 Barcelona Barcelona 08013",
    "addr:housenumber":"188",
    "addr:postcode":"08013",
    "addr:street":"Carrer De Napols",
    "iso:country":"ES",
    "sg:address":"Carrer de Napols, 188",
    "sg:city":"Barcelona",
    "sg:orig_category":"Telas Y Sedas (al Por Menor)",
    "sg:phone":"+34 932 44 00 02",
    "sg:postcode":"08013",
    "sg:province":"Barcelona",
    "wof:name":"Forincabo Textil S.l.l.",
    "wof:placetype":"venue"
},
  "geometry": {"coordinates":[2.1751520634,41.3987808228],"type":"Point"}
}