{
  "type": "Feature",
  "properties": {
    "iso:country":"ES",
    "sg:address":"Calle de Ribera, 22",
    "sg:city":"Bilbao",
    "sg:orig_category":"Estancos",
    "sg:phone":"+34 944 16 41 21",
    "sg:postcode":"48005",
    "sg:province":"Vizcaya",
    "wof:name":"Aspizua Martinez Piedad",
    "wof:placetype":"venue"
},
  "geometry": {"coordinates":[-2.9235496521,43.2555236816],"type":"Point"}
}