{
  "type": "Feature",
  "properties": {
    "addr:full":"Cra Laurea Miro, 292 Sant Feliu Llobregat Barcelona 08980",
    "addr:housenumber":"292",
    "addr:postcode":"08980",
    "iso:country":"ES",
    "sg:address":"Cra Laurea Miro, 292",
    "sg:city":"Sant Feliu Llobregat",
    "sg:orig_category":"Droguer\u00cdas (al Por Menor)",
    "sg:phone":"+34 936 66 12 81",
    "sg:postcode":"08980",
    "sg:province":"Barcelona",
    "wof:name":"Drogueria Boronat S.l.",
    "wof:placetype":"venue"
},
  "geometry": {"coordinates":[2.0420660973,41.3827705383],"type":"Point"}
}