{
  "type": "Feature",
  "properties": {
    "addr:full":"Calle de Lora Del Rio, 24 Sevilla Sevilla 41013",
    "addr:housenumber":"24",
    "addr:postcode":"41013",
    "addr:street":"Calle De Lora Del Rio",
    "iso:country":"ES",
    "sg:address":"Calle de Lora Del Rio, 24",
    "sg:city":"Sevilla",
    "sg:orig_category":"Asociaciones Y Clubs Deportivos",
    "sg:phone":"+34 954 62 74 39",
    "sg:postcode":"41013",
    "sg:province":"Sevilla",
    "wof:name":"Club Deportivo Jesus Cautivo",
    "wof:placetype":"venue"
},
  "geometry": {"coordinates":[-5.9742188454,37.368888855],"type":"Point"}
}