{
  "type": "Feature",
  "properties": {
    "addr:full":"Calle de Bergantin, 16 Madrid Madrid 28042",
    "addr:housenumber":"16",
    "addr:postcode":"madrid;28042",
    "addr:street":"Calle De Bergantin",
    "iso:country":"ES",
    "sg:address":"Calle de Bergantin, 16",
    "sg:city":"Madrid",
    "sg:orig_category":"Asesor\u00cda Fiscal Y Jur\u00cddica",
    "sg:phone":"+34 913 29 39 96",
    "sg:postcode":"28042",
    "sg:province":"Madrid",
    "wof:name":"Manager Consulting Empresarial S.a.",
    "wof:placetype":"venue"
},
  "geometry": {"coordinates":[-3.5845448971,40.4590492249],"type":"Point"}
}