{
  "type": "Feature",
  "properties": {
    "addr:full":"Pg Estacio, 11 Abrera Barcelona 08630",
    "addr:housenumber":"11",
    "addr:postcode":"08630",
    "addr:street":"Pg Estacio",
    "iso:country":"ES",
    "sg:address":"Pg Estacio, 11",
    "sg:city":"Abrera",
    "sg:orig_category":"Ropa Y Accesorios",
    "sg:phone":"+34 937 70 71 20",
    "sg:postcode":"08630",
    "sg:province":"Barcelona",
    "wof:name":"Perez Cerdan Susana",
    "wof:placetype":"venue"
},
  "geometry": {"coordinates":[1.9009269476,41.520236969],"type":"Point"}
}