{
  "type": "Feature",
  "properties": {
    "iso:country":"ES",
    "sg:address":"Calle de Florentino Ballesteros, 14",
    "sg:city":"Zaragoza",
    "sg:orig_category":"Agentes Generales De Seguros",
    "sg:phone":"+34 976 49 73 08",
    "sg:postcode":"50013",
    "sg:province":"Zaragoza",
    "wof:name":"Dolz Asociados Gestion De Patrimonios S.l.",
    "wof:placetype":"venue"
},
  "geometry": {"coordinates":[-0.8678900003,41.6442451477],"type":"Point"}
}