{
  "type": "Feature",
  "properties": {
    "addr:full":"Calle de Fernandez Victorio, 12 Viveiro Lugo 27850",
    "addr:housenumber":"12",
    "addr:postcode":"27850",
    "addr:street":"Calle De Fernandez Victorio",
    "iso:country":"ES",
    "sg:address":"Calle de Fernandez Victorio, 12",
    "sg:city":"Viveiro",
    "sg:orig_category":"Ropa Para Se\u00d1oras (al Por Menor)",
    "sg:phone":"+34 982 56 06 46",
    "sg:postcode":"27850",
    "sg:province":"Lugo",
    "wof:name":"Vizoso Nu\u00f1ez Berta",
    "wof:placetype":"venue"
},
  "geometry": {"coordinates":[-7.5954546928,43.661605835],"type":"Point"}
}