{
  "type": "Feature",
  "properties": {
    "addr:full":"Calle de Luengo, S/n Algar Murcia 30366",
    "addr:housenumber":"s / n",
    "addr:postcode":"30366",
    "addr:street":"Calle De Luengo",
    "iso:country":"ES",
    "sg:address":"Calle de Luengo, S/n",
    "sg:city":"Algar",
    "sg:orig_category":"Agricultores, Agricultores",
    "sg:phone":"+34 968 13 53 60",
    "sg:postcode":"30366",
    "sg:province":"Murcia",
    "wof:name":"Luengo Sanchez Jose",
    "wof:placetype":"venue"
},
  "geometry": {"coordinates":[-0.8653200269,37.6491928101],"type":"Point"}
}