{
  "type": "Feature",
  "properties": {
    "iso:country":"ES",
    "sg:address":"Cmno O\u00d1atz Bidea, 1",
    "sg:city":"Azpeitia",
    "sg:orig_category":"Contenedores (mercanc\u00cdas)",
    "sg:phone":"+34 943 81 30 14",
    "sg:postcode":"20730",
    "sg:province":"Guip\u00f9zcoa",
    "wof:name":"Larra\u00f1aga Sudupe Angel",
    "wof:placetype":"venue"
},
  "geometry": {"coordinates":[-2.2639229298,43.1775093079],"type":"Point"}
}