{
  "type": "Feature",
  "properties": {
    "iso:country":"ES",
    "sg:address":"Calle de Real, 19",
    "sg:city":"Alcubillas",
    "sg:orig_category":"Cooperativas Agr\u00cdcolas",
    "sg:phone":"+34 926 35 60 03",
    "sg:postcode":"13391",
    "sg:province":"Ciudad Real",
    "wof:name":"Cooperativa Del Campo Nuestra Se\u00f1ora Del Rosario",
    "wof:placetype":"venue"
},
  "geometry": {"coordinates":[-3.1339519024,38.7545585632],"type":"Point"}
}