{
  "type": "Feature",
  "properties": {
    "iso:country":"ES",
    "sg:address":"Calle de Esteban Manuel Villegas, 8",
    "sg:city":"Logro\u00f1o",
    "sg:orig_category":"Ense\u00d1anza Variada",
    "sg:phone":"+34 941 23 29 53",
    "sg:postcode":"26004",
    "sg:province":"La Rioja",
    "wof:name":"Gomez Ilarraza Miguel Angel",
    "wof:placetype":"venue"
},
  "geometry": {"coordinates":[-2.4362533092,42.4655990601],"type":"Point"}
}