{
  "type": "Feature",
  "properties": {
    "iso:country":"ES",
    "sg:address":"Calle de Vicente Andres Estelles, 13",
    "sg:city":"Alaquas",
    "sg:orig_category":"Electricidad: Instaladores",
    "sg:phone":"+34 961 50 76 84",
    "sg:postcode":"46970",
    "sg:province":"Valencia",
    "wof:name":"Montajes Electricos Macias S.l.",
    "wof:placetype":"venue"
},
  "geometry": {"coordinates":[-0.4714694023,39.4518432617],"type":"Point"}
}