{
  "type": "Feature",
  "properties": {
    "iso:country":"ES",
    "sg:address":"Calle de Peru, 49",
    "sg:city":"Bormujos",
    "sg:orig_category":"Empresas De Portes Y Mensajer\u00cda",
    "sg:phone":"+34 955 72 37 99",
    "sg:postcode":"41930",
    "sg:province":"Sevilla",
    "wof:name":"Venegas Romero Antonia",
    "wof:placetype":"venue"
},
  "geometry": {"coordinates":[-6.0798549652,37.3741226196],"type":"Point"}
}