{
  "type": "Feature",
  "properties": {
    "iso:country":"ES",
    "sg:address":"Calle de Fernandez Del Campo, 11",
    "sg:city":"Bilbao",
    "sg:orig_category":"Alquiler De V\u00cddeo",
    "sg:phone":"+34 944 43 85 35",
    "sg:postcode":"48010",
    "sg:province":"Vizcaya",
    "wof:name":"Ipi\u00d1a Palacio Sl",
    "wof:placetype":"venue"
},
  "geometry": {"coordinates":[-2.9336738586,43.2584877014],"type":"Point"}
}