{
  "type": "Feature",
  "properties": {
    "addr:full":"Pla\u00c7 Espa\u00d1a, S/n Xativa Valencia 46800",
    "addr:postcode":"46800",
    "addr:street":"Espan\u0303A S / N",
    "iso:country":"ES",
    "sg:address":"Pla\u00c7 Espa\u00d1a, S/n",
    "sg:city":"Xativa",
    "sg:orig_category":"Ense\u00d1anza Variada",
    "sg:phone":"+34 962 27 61 86",
    "sg:postcode":"46800",
    "sg:province":"Valencia",
    "wof:name":"Taurotoro S.l.",
    "wof:placetype":"venue"
},
  "geometry": {"coordinates":[-0.5128409863,38.9907341003],"type":"Point"}
}