{
  "type": "Feature",
  "properties": {
    "iso:country":"ES",
    "sg:address":"Plaz San Agustin, 1",
    "sg:city":"Cartagena",
    "sg:orig_category":"Agentes Generales De Seguros",
    "sg:phone":"+34 968 52 86 47",
    "sg:postcode":"30201",
    "sg:province":"Murcia",
    "wof:name":"Jimenez Gutierrez Andres",
    "wof:placetype":"venue"
},
  "geometry": {"coordinates":[-0.9867500067,37.5995483398],"type":"Point"}
}