{
  "type": "Feature",
  "properties": {
    "addr:full":"Parateta, 10 El Morell Tarragona 43760",
    "addr:housenumber":"10",
    "addr:postcode":"43760",
    "addr:street":"Parateta;El Morell",
    "iso:country":"ES",
    "sg:address":"Parateta, 10",
    "sg:city":"El Morell",
    "sg:orig_category":"Electricidad: Instaladores",
    "sg:phone":"+34 977 84 20 61",
    "sg:postcode":"43760",
    "sg:province":"Tarragona",
    "wof:name":"Carta\u00f1a Prunera Ramon",
    "wof:placetype":"venue"
},
  "geometry": {"coordinates":[1.2080340385,41.1927528381],"type":"Point"}
}