{
  "type": "Feature",
  "properties": {
    "iso:country":"ES",
    "sg:address":"Cno. Recons, 4",
    "sg:city":"Catadau",
    "sg:orig_category":"Afinadores, Reparadores De Pianos",
    "sg:phone":"+34 962 99 07 30",
    "sg:postcode":"46196",
    "sg:province":"Valencia",
    "wof:name":"Mediterranea De Cactus S.l.",
    "wof:placetype":"venue"
},
  "geometry": {"coordinates":[-0.5747990012,39.2723884583],"type":"Point"}
}