{
  "type": "Feature",
  "properties": {
    "iso:country":"ES",
    "sg:address":"Deiro, 17",
    "sg:city":"Deiro",
    "sg:orig_category":"Alimentaci\u00d3n General (al Por Menor)",
    "sg:phone":"+34 986 55 55 37",
    "sg:postcode":"36628",
    "sg:province":"Pontevedra",
    "wof:name":"Vi\u00f1as Martinez Juan",
    "wof:placetype":"venue"
},
  "geometry": {"coordinates":[-8.8036279678,42.5330543518],"type":"Point"}
}