{
  "type": "Feature",
  "properties": {
    "iso:country":"ES",
    "sg:address":"Calle de Juan De La Cruz, 2",
    "sg:city":"Villa Rio",
    "sg:orig_category":"Carnicer\u00cdas, Carnicer\u00cdas",
    "sg:phone":"+34 957 17 67 83",
    "sg:postcode":"14640",
    "sg:province":"C\u00f3rdoba",
    "wof:name":"Santiago Valcarcel Benito",
    "wof:placetype":"venue"
},
  "geometry": {"coordinates":[-4.2904877663,37.9820289612],"type":"Point"}
}