{
  "type": "Feature",
  "properties": {
    "iso:country":"ES",
    "sg:address":"Calle de Manzanilla, 5",
    "sg:city":"Sevilla",
    "sg:orig_category":"Centros Empresariales",
    "sg:phone":"+34 954 23 51 75",
    "sg:postcode":"41013",
    "sg:province":"Sevilla",
    "wof:name":"Sociedad Andaluza Para El Desarrollo De Las Telecomunicaciones",
    "wof:placetype":"venue"
},
  "geometry": {"coordinates":[-5.9717588425,37.364818573],"type":"Point"}
}