{
  "type": "Feature",
  "properties": {
    "iso:country":"ES",
    "sg:address":"Rbla Poblenou, S/n",
    "sg:city":"Barcelona",
    "sg:orig_category":"Librer\u00cdas",
    "sg:phone":"+34 932 21 39 39",
    "sg:postcode":"08005",
    "sg:province":"Barcelona",
    "wof:name":"Gener Martinez Javier",
    "wof:placetype":"venue"
},
  "geometry": {"coordinates":[2.1984899044,41.4032707214],"type":"Point"}
}