{
  "type": "Feature",
  "properties": {
    "iso:country":"ES",
    "sg:address":"Carrer de Roger De Lluria, 123",
    "sg:city":"Barcelona",
    "sg:orig_category":"Farmacias",
    "sg:phone":"+34 932 15 49 68",
    "sg:postcode":"08037",
    "sg:province":"Barcelona",
    "wof:name":"Bote Carranza Josefa",
    "wof:placetype":"venue"
},
  "geometry": {"coordinates":[2.1639230251,41.3967399597],"type":"Point"}
}