{
  "type": "Feature",
  "properties": {
    "iso:country":"ES",
    "sg:address":"Carr Maestro Torres, 15",
    "sg:city":"Llombai",
    "sg:orig_category":"Peleter\u00cdas",
    "sg:phone":"+34 962 99 09 37",
    "sg:postcode":"46195",
    "sg:province":"Valencia",
    "wof:name":"Pieles Berrocal S.l.",
    "wof:placetype":"venue"
},
  "geometry": {"coordinates":[-0.5705609918,39.2790985107],"type":"Point"}
}