{
  "type": "Feature",
  "properties": {
    "addr:full":"Avgd Ausias March, 31 Burjassot Valencia 46100",
    "addr:housenumber":"31",
    "addr:postcode":"46100",
    "addr:street":"March",
    "iso:country":"ES",
    "sg:address":"Avgd Ausias March, 31",
    "sg:city":"Burjassot",
    "sg:orig_category":"Puertas Y Portales",
    "sg:phone":"+34 963 63 30 20",
    "sg:postcode":"46100",
    "sg:province":"Valencia",
    "wof:name":"Tot Fusta Burjassot S.l.",
    "wof:placetype":"venue"
},
  "geometry": {"coordinates":[-0.411435008,39.5121459961],"type":"Point"}
}