{
  "type": "Feature",
  "properties": {
    "iso:country":"ES",
    "sg:address":"Calle de Cristo Del Calvario, 1",
    "sg:city":"Sevilla",
    "sg:orig_category":"Laboratorios Y Trabajos De Fotograf\u00cda, V\u00cddeo Y Cine",
    "sg:phone":"+34 954 21 61 23",
    "sg:postcode":"41001",
    "sg:province":"Sevilla",
    "wof:name":"Deinm Estudio S.l.",
    "wof:placetype":"venue"
},
  "geometry": {"coordinates":[-5.9988069534,37.390083313],"type":"Point"}
}