{
  "type": "Feature",
  "properties": {
    "iso:country":"ES",
    "sg:address":"Ctra Bacarot, S/n",
    "sg:city":"Bacarot",
    "sg:orig_category":"Explotaci\u00d3n De Canteras",
    "sg:phone":"+34 965 11 09 53",
    "sg:postcode":"03114",
    "sg:province":"Alicante",
    "wof:name":"Dura Ruiz Ramon",
    "wof:placetype":"venue"
},
  "geometry": {"coordinates":[-0.5574979782,38.3208618164],"type":"Point"}
}