{
  "type": "Feature",
  "properties": {
    "iso:country":"ES",
    "sg:address":"Carrer de Torrent De L'olla, 100",
    "sg:city":"Barcelona",
    "sg:orig_category":"Ropa Para Ni\u00d1os (al Por Menor)",
    "sg:phone":"+34 932 13 15 60",
    "sg:postcode":"08012",
    "sg:province":"Barcelona",
    "wof:name":"Goldem Monkey S.l.",
    "wof:placetype":"venue"
},
  "geometry": {"coordinates":[2.1582899094,41.4013290405],"type":"Point"}
}