{
  "type": "Feature",
  "properties": {
    "addr:full":"Rua Campo De Marte, S/n Santa Uxia De Ribeira A Coru\u00f1a 15960",
    "addr:housenumber":"s / n",
    "addr:postcode":"15960",
    "addr:street":"Rua Campo De Marte;Corun\u0303A",
    "iso:country":"ES",
    "sg:address":"Rua Campo De Marte, S/n",
    "sg:city":"Santa Uxia De Ribeira",
    "sg:orig_category":"Caf\u00c9s, Bares, Cervecer\u00cdas",
    "sg:phone":"+34 981 87 02 92",
    "sg:postcode":"15960",
    "sg:province":"A Coru\u00f1a",
    "wof:name":"Treus Otero Gonzalo",
    "wof:placetype":"venue"
},
  "geometry": {"coordinates":[-8.990942955,42.5548019409],"type":"Point"}
}