{
  "type": "Feature",
  "properties": {
    "iso:country":"ES",
    "sg:address":"Avda Vegas Altas, 93",
    "sg:city":"Don Benito",
    "sg:orig_category":"Agentes, Concesionarios Y Sucursales De Veh\u00cdculos",
    "sg:phone":"+34 924 80 80 61",
    "sg:postcode":"06400",
    "sg:province":"Badajoz",
    "sg:website":"www.venssa.com",
    "wof:name":"Ventas Y Servicios S.l.",
    "wof:placetype":"venue"
},
  "geometry": {"coordinates":[-5.8503952026,38.9617843628],"type":"Point"}
}