{
  "type": "Feature",
  "properties": {
    "addr:full":"Calle de Nuestra Se\u00d1ora De La Luz, 2 Coru\u00d1a A Coru\u00f1a 15007",
    "addr:housenumber":"2",
    "addr:postcode":"15007",
    "addr:street":"Calle De Nuestra Sen\u0303Ora De La Luz;Corun\u0303A",
    "iso:country":"ES",
    "sg:address":"Calle de Nuestra Se\u00d1ora De La Luz, 2",
    "sg:city":"Coru\u00d1a",
    "sg:orig_category":"Transportes Por V\u00cdas Navegables",
    "sg:phone":"+34 981 23 75 03",
    "sg:postcode":"15007",
    "sg:province":"A Coru\u00f1a",
    "wof:name":"Viajes Orons S. A.",
    "wof:placetype":"venue"
},
  "geometry": {"coordinates":[-8.4156570435,43.3583259583],"type":"Point"}
}