{
  "type": "Feature",
  "properties": {
    "iso:country":"ES",
    "sg:address":"Plaz Condestable, 12",
    "sg:city":"Salas De Los Infantes",
    "sg:orig_category":"Estancos",
    "sg:phone":"+34 947 38 20 36",
    "sg:postcode":"09600",
    "sg:province":"Burgos",
    "wof:name":"Sebastian Navas Alfredo",
    "wof:placetype":"venue"
},
  "geometry": {"coordinates":[-3.2888009548,42.0225868225],"type":"Point"}
}