{
  "type": "Feature",
  "properties": {
    "addr:full":"Calle de Blas Cabrera Felipe, S/n Arrecife Las Palmas 35500",
    "addr:housenumber":"s / n",
    "addr:postcode":"35500",
    "addr:street":"Calle De Blas Cabrera Felipe",
    "iso:country":"ES",
    "sg:address":"Calle de Blas Cabrera Felipe, S/n",
    "sg:city":"Arrecife",
    "sg:orig_category":"Ense\u00d1anza, Formaci\u00d3n Profesional: Aprendizaje",
    "sg:phone":"+34 928 81 17 62",
    "sg:postcode":"35500",
    "sg:province":"Las Palmas",
    "sg:website":"www.turismolanzarote.com",
    "wof:name":"Cabildo Insular De Lanzarote",
    "wof:placetype":"venue"
},
  "geometry": {"coordinates":[-13.5508432388,28.9574642181],"type":"Point"}
}