{
  "type": "Feature",
  "properties": {
    "addr:full":"Avda Portugal, 9 Zamora Zamora 49016",
    "addr:housenumber":"9",
    "addr:postcode":"49016",
    "addr:street":"Avda Portugal",
    "iso:country":"ES",
    "sg:address":"Avda Portugal, 9",
    "sg:city":"Zamora",
    "sg:orig_category":"Doctores En Medicina",
    "sg:phone":"+34 980 51 84 40",
    "sg:postcode":"49016",
    "sg:province":"Zamora",
    "wof:name":"Ortiz De Murua Lopez Jose Antonio",
    "wof:placetype":"venue"
},
  "geometry": {"coordinates":[-5.7396631241,41.5046730042],"type":"Point"}
}