{
  "type": "Feature",
  "properties": {
    "addr:full":"Calle de Ancha, 9 Noves Toledo 45519",
    "addr:housenumber":"9",
    "addr:postcode":"45519",
    "addr:street":"Calle De Ancha",
    "iso:country":"ES",
    "sg:address":"Calle de Ancha, 9",
    "sg:city":"Noves",
    "sg:orig_category":"Reposter\u00cdas",
    "sg:phone":"+34 925 77 81 39",
    "sg:postcode":"45519",
    "sg:province":"Toledo",
    "wof:name":"Hijos De Julio Valtierra Comunidad De Bienes",
    "wof:placetype":"venue"
},
  "geometry": {"coordinates":[-4.2751021385,40.0461654663],"type":"Point"}
}