{
  "type": "Feature",
  "properties": {
    "addr:full":"C/ Trevol, 9 Palmeres Islas Baleares 07609",
    "addr:housenumber":"9",
    "addr:postcode":"07609",
    "addr:street":"C / Trevol",
    "iso:country":"ES",
    "sg:address":"C/ Trevol, 9",
    "sg:city":"Palmeres",
    "sg:orig_category":"\u00d3ptica: Instrumentos (fabricaci\u00d3n)",
    "sg:phone":"+34 971 74 07 73",
    "sg:postcode":"07609",
    "sg:province":"Islas Baleares",
    "wof:name":"Bautista Campos Maria Del Carmen",
    "wof:placetype":"venue"
},
  "geometry": {"coordinates":[2.7483599186,39.4702262878],"type":"Point"}
}