{
  "type": "Feature",
  "properties": {
    "addr:full":"Calle de Granxas, 82 Covas Lugo 27861",
    "addr:housenumber":"82",
    "addr:postcode":"27861",
    "addr:street":"Calle De Granxas",
    "iso:country":"ES",
    "sg:address":"Calle de Granxas, 82",
    "sg:city":"Covas",
    "sg:orig_category":"Caf\u00c9s, Bares, Cervecer\u00cdas",
    "sg:phone":"+34 982 56 14 40",
    "sg:postcode":"27861",
    "sg:province":"Lugo",
    "wof:name":"Gonzalez Garcia Jose Manuel",
    "wof:placetype":"venue"
},
  "geometry": {"coordinates":[-7.6583218575,43.691734314],"type":"Point"}
}