{
  "type": "Feature",
  "properties": {
    "addr:full":"Carrer de Cordova, 2 Pedreguer Alicante 03750",
    "addr:housenumber":"2",
    "addr:postcode":"03750",
    "addr:street":"Carrer De Cordova",
    "iso:country":"ES",
    "sg:address":"Carrer de Cordova, 2",
    "sg:city":"Pedreguer",
    "sg:orig_category":"Ingenier\u00cda, Centros De Estudios (diversos)",
    "sg:phone":"+34 965 76 02 12",
    "sg:postcode":"03750",
    "sg:province":"Alicante",
    "wof:name":"Pevitec S.l.",
    "wof:placetype":"venue"
},
  "geometry": {"coordinates":[0.0319649987,38.7966003418],"type":"Point"}
}