{
  "type": "Feature",
  "properties": {
    "iso:country":"ES",
    "sg:address":"Sa Placa, 120",
    "sg:city":"Sa Pobla",
    "sg:orig_category":"Promotores Constructores",
    "sg:phone":"+34 971 54 24 27",
    "sg:postcode":"07420",
    "sg:province":"Islas Baleares",
    "wof:name":"Balnorter S.l",
    "wof:placetype":"venue"
},
  "geometry": {"coordinates":[3.027326107,39.7654647827],"type":"Point"}
}