{
  "type": "Feature",
  "properties": {
    "iso:country":"ES",
    "sg:address":"Calle de Hermanos Pinzon, 18",
    "sg:city":"Torrijos",
    "sg:orig_category":"Costureras",
    "sg:phone":"+34 925 76 15 83",
    "sg:postcode":"45500",
    "sg:province":"Toledo",
    "wof:name":"Gallardo Garcia Estrella",
    "wof:placetype":"venue"
},
  "geometry": {"coordinates":[-4.2804088593,39.9850502014],"type":"Point"}
}