{
  "type": "Feature",
  "properties": {
    "addr:full":"Carrer de Viladomat, 232 Sabadell Barcelona 08205",
    "addr:housenumber":"232",
    "addr:postcode":"08205",
    "addr:street":"Carrer De Viladomat",
    "iso:country":"ES",
    "sg:address":"Carrer de Viladomat, 232",
    "sg:city":"Sabadell",
    "sg:orig_category":"Tratamiento De Metales",
    "sg:phone":"+34 937 45 91 56",
    "sg:postcode":"08205",
    "sg:province":"Barcelona",
    "wof:name":"Pulunion S.l.",
    "wof:placetype":"venue"
},
  "geometry": {"coordinates":[2.0968129635,41.5379371643],"type":"Point"}
}