{
  "type": "Feature",
  "properties": {
    "iso:country":"ES",
    "sg:address":"Pol Ind Aldea De Cazalla, S/n",
    "sg:city":"Fuensanta Martos",
    "sg:orig_category":"Muebles",
    "sg:phone":"+34 953 56 30 25",
    "sg:postcode":"23610",
    "sg:province":"Ja\u00e9n",
    "wof:name":"Tapizados La Fuente S.l.",
    "wof:placetype":"venue"
},
  "geometry": {"coordinates":[-3.9120569229,37.6458854675],"type":"Point"}
}