{
  "type": "Feature",
  "properties": {
    "iso:country":"ES",
    "sg:address":"Calle de Rafael Ortega, 16",
    "sg:city":"Fregenal Sierra",
    "sg:orig_category":"Ebanister\u00cda",
    "sg:phone":"+34 924 72 02 60",
    "sg:postcode":"06340",
    "sg:province":"Badajoz",
    "wof:name":"Risco Galvan Joaquin",
    "wof:placetype":"venue"
},
  "geometry": {"coordinates":[-6.6505317688,38.1659088135],"type":"Point"}
}