{
  "type": "Feature",
  "properties": {
    "addr:full":"Calle de Andalucia, 13 Illescas Toledo 45200",
    "addr:housenumber":"13",
    "addr:postcode":"45200",
    "addr:street":"Calle De Andalucia",
    "iso:country":"ES",
    "sg:address":"Calle de Andalucia, 13",
    "sg:city":"Illescas",
    "sg:orig_category":"Muebles, Minoristas",
    "sg:phone":"+34 925 51 23 77",
    "sg:postcode":"45200",
    "sg:province":"Toledo",
    "wof:name":"Alvarez Fernandez Santiago",
    "wof:placetype":"venue"
},
  "geometry": {"coordinates":[-3.8489229679,40.1314048767],"type":"Point"}
}