{
  "type": "Feature",
  "properties": {
    "iso:country":"ES",
    "sg:address":"Carrer de Riu Mogent (del), 8",
    "sg:city":"Montornes Centre",
    "sg:orig_category":"Florister\u00cdas",
    "sg:phone":"+34 935 72 04 46",
    "sg:postcode":"08170",
    "sg:province":"Barcelona",
    "wof:name":"Guardiola Benito Jose Maria",
    "wof:placetype":"venue"
},
  "geometry": {"coordinates":[2.2654349804,41.5428504944],"type":"Point"}
}