{
  "type": "Feature",
  "properties": {
    "addr:full":"Mercat Sants, 88 Barcelona Barcelona 08014",
    "addr:housenumber":"88",
    "addr:postcode":"08014",
    "iso:country":"ES",
    "sg:address":"Mercat Sants, 88",
    "sg:city":"Barcelona",
    "sg:orig_category":"Triper\u00cdas",
    "sg:phone":"+34 934 91 37 17",
    "sg:postcode":"08014",
    "sg:province":"Barcelona",
    "wof:name":"Molina Rueda Emilio",
    "wof:placetype":"venue"
},
  "geometry": {"coordinates":[2.1365020275,41.3754234314],"type":"Point"}
}