{
  "type": "Feature",
  "properties": {
    "addr:full":"Carrer de Sant Esteve, 16 Olot Girona 17800",
    "addr:housenumber":"16",
    "addr:postcode":"17800",
    "addr:street":"Carrer De Sant Esteve",
    "iso:country":"ES",
    "sg:address":"Carrer de Sant Esteve, 16",
    "sg:city":"Olot",
    "sg:orig_category":"Relojer\u00cda (al Por Menor, Reparaci\u00d3n)",
    "sg:phone":"+34 972 26 02 07",
    "sg:postcode":"17800",
    "sg:province":"Girona",
    "wof:name":"Ferrarons Milx S.l.",
    "wof:placetype":"venue"
},
  "geometry": {"coordinates":[2.4886629581,42.1821517944],"type":"Point"}
}