{
  "type": "Feature",
  "properties": {
    "addr:full":"Calle de Casillas, S/n Burgos Burgos 09002",
    "addr:housenumber":"s / n",
    "addr:postcode":"09002",
    "addr:street":"Calle De Casillas",
    "iso:country":"ES",
    "sg:address":"Calle de Casillas, S/n",
    "sg:city":"Burgos",
    "sg:orig_category":"Tiendas De Grano, Frutas Y Legumbres Secas (al Por Menor)",
    "sg:phone":"+34 947 27 83 38",
    "sg:postcode":"09002",
    "sg:province":"Burgos",
    "wof:name":"Olmo Due\u00f1as Maria Del Carmen",
    "wof:placetype":"venue"
},
  "geometry": {"coordinates":[-3.6927914619,42.3376808167],"type":"Point"}
}