{
  "type": "Feature",
  "properties": {
    "iso:country":"ES",
    "sg:address":"Calle de General Yague, 28",
    "sg:city":"Logro\u00f1o",
    "sg:orig_category":"Panader\u00cdas, Panader\u00cdas",
    "sg:phone":"+34 941 51 07 92",
    "sg:postcode":"26006",
    "sg:province":"La Rioja",
    "wof:name":"Horno Del Valle S.cv.",
    "wof:placetype":"venue"
},
  "geometry": {"coordinates":[-2.4680161476,42.4632492065],"type":"Point"}
}