{
  "type": "Feature",
  "properties": {
    "iso:country":"ES",
    "sg:address":"Calle de Mayor, 67",
    "sg:city":"Puente Tocinos",
    "sg:orig_category":"Caf\u00c9s, Bares, Cervecer\u00cdas",
    "sg:phone":"+34 968 23 77 39",
    "sg:postcode":"30006",
    "sg:province":"Murcia",
    "wof:name":"Hermanos Buendia Cdad",
    "wof:placetype":"venue"
},
  "geometry": {"coordinates":[-1.1035929918,37.9931335449],"type":"Point"}
}