{
  "type": "Feature",
  "properties": {
    "iso:country":"ES",
    "sg:address":"Ctra Fondillo Del, S/n",
    "sg:city":"Fondillo",
    "sg:orig_category":"Ense\u00d1anza Variada",
    "sg:phone":"+34 928 35 33 11",
    "sg:postcode":"35017",
    "sg:province":"Las Palmas",
    "sg:website":"www.guaydil.com",
    "wof:name":"Centros Educativos Canarios S. A.",
    "wof:placetype":"venue"
},
  "geometry": {"coordinates":[-15.4646606445,28.054693222],"type":"Point"}
}