{
  "type": "Feature",
  "properties": {
    "iso:country":"ES",
    "sg:address":"Calle de Trespaderne, 10",
    "sg:city":"Madrid",
    "sg:orig_category":"Bancos",
    "sg:phone":"+34 917 47 49 95",
    "sg:postcode":"28042",
    "sg:province":"Madrid",
    "wof:name":"Banco Espa\u00d1ol De Credito S A",
    "wof:placetype":"venue"
},
  "geometry": {"coordinates":[-3.5809819698,40.451751709],"type":"Point"}
}