{
  "type": "Feature",
  "properties": {
    "iso:country":"ES",
    "sg:address":"Calle de Santa Teresa, 8",
    "sg:city":"Fraga",
    "sg:orig_category":"Reposter\u00cdas",
    "sg:phone":"+34 974 47 46 11",
    "sg:postcode":"22520",
    "sg:province":"Huesca",
    "wof:name":"Panaderia Aguilar S.c",
    "wof:placetype":"venue"
},
  "geometry": {"coordinates":[0.3498399854,41.5217285156],"type":"Point"}
}