{
  "type": "Feature",
  "properties": {
    "addr:full":"Calle de Conde Toreno, 42 Gijon Asturias 33204",
    "addr:housenumber":"42",
    "addr:postcode":"33204",
    "addr:street":"Calle De Conde Toreno",
    "iso:country":"ES",
    "sg:address":"Calle de Conde Toreno, 42",
    "sg:city":"Gijon",
    "sg:orig_category":"Asesor\u00cda Sobre Comunicaci\u00d3n De Empresas",
    "sg:phone":"+34 985 13 15 79",
    "sg:postcode":"33204",
    "sg:province":"Asturias",
    "wof:name":"Consultores Roman Y Asociados S.l.",
    "wof:placetype":"venue"
},
  "geometry": {"coordinates":[-5.6498904228,43.5309181213],"type":"Point"}
}