{
  "type": "Feature",
  "properties": {
    "iso:country":"ES",
    "sg:address":"Calle de Martinez Monta\u00d1es, 5",
    "sg:city":"Palacios Y Villafranca",
    "sg:orig_category":"Farmacias",
    "sg:phone":"+34 955 81 57 62",
    "sg:postcode":"41720",
    "sg:province":"Sevilla",
    "wof:name":"R & B Farmeceuticas C.b.",
    "wof:placetype":"venue"
},
  "geometry": {"coordinates":[-5.9239649773,37.1649589539],"type":"Point"}
}