{
  "type": "Feature",
  "properties": {
    "iso:country":"ES",
    "sg:address":"Carrer de Sant Josep, 3",
    "sg:city":"Manresa",
    "sg:orig_category":"Servicios De Higiene Y Peluquer\u00cda Para Perros Y Gatos",
    "sg:phone":"+34 938 73 58 76",
    "sg:postcode":"08242",
    "sg:province":"Barcelona",
    "wof:name":"P E Ekilibri S.c.p",
    "wof:placetype":"venue"
},
  "geometry": {"coordinates":[1.82703197,41.7318344116],"type":"Point"}
}