{
  "type": "Feature",
  "properties": {
    "addr:full":"Carr Sant Iscle, 41 Breda Girona 17400",
    "addr:housenumber":"41",
    "addr:postcode":"17400",
    "addr:street":"Carr Sant Iscle",
    "iso:country":"ES",
    "sg:address":"Carr Sant Iscle, 41",
    "sg:city":"Breda",
    "sg:orig_category":"Cajas De Ahorro",
    "sg:phone":"+34 972 87 01 55",
    "sg:postcode":"17400",
    "sg:province":"Girona",
    "sg:website":"www.lacaixa.es",
    "wof:name":"Caixa D'estalvis I Pensions De Barcelona",
    "wof:placetype":"venue"
},
  "geometry": {"coordinates":[2.5595159531,41.748298645],"type":"Point"}
}