{
  "type": "Feature",
  "properties": {
    "addr:full":"Ctra Sentmenat, 32 Castellar Valles Barcelona 08211",
    "addr:housenumber":"32",
    "addr:postcode":"08211",
    "addr:street":"Ctra Sentmenat",
    "iso:country":"ES",
    "sg:address":"Ctra Sentmenat, 32",
    "sg:city":"Castellar Valles",
    "sg:orig_category":"Cajas De Ahorro",
    "sg:phone":"+34 937 14 47 57",
    "sg:postcode":"08211",
    "sg:province":"Barcelona",
    "sg:website":"www.caixamanresa.es",
    "wof:name":"Caixa D'estalvis De Manresa",
    "wof:placetype":"venue"
},
  "geometry": {"coordinates":[2.0857300758,41.6151885986],"type":"Point"}
}