{
  "type": "Feature",
  "properties": {
    "iso:country":"ES",
    "sg:address":"Carrer de Aleix Aguilera I Ginabreda, 8",
    "sg:city":"Prat Llobregat",
    "sg:orig_category":"Peluquer\u00cdas, Peluquer\u00cda Mixta",
    "sg:phone":"+34 934 78 79 88",
    "sg:postcode":"08820",
    "sg:province":"Barcelona",
    "wof:name":"Lopez Gomez Manuela",
    "wof:placetype":"venue"
},
  "geometry": {"coordinates":[2.0896699429,41.3240318298],"type":"Point"}
}