{
  "type": "Feature",
  "properties": {
    "iso:country":"ES",
    "sg:address":"C/ Reina Victoria, 48",
    "sg:city":"Elche",
    "sg:orig_category":"Propiedad Industrial: Patentes De Inventos, Marcas, Modelos, Dise\u00d1os",
    "sg:phone":"+34 966 66 09 74",
    "sg:postcode":"03201",
    "sg:province":"Alicante",
    "wof:name":"Euromark Patentes S.l.",
    "wof:placetype":"venue"
},
  "geometry": {"coordinates":[-0.7044469714,38.265537262],"type":"Point"}
}