{
  "type": "Feature",
  "properties": {
    "addr:full":"Ctra Naharros, Km. 0019,0 Santa Marta De Tormes Salamanca 37900",
    "addr:postcode":"37900",
    "addr:street":"Ctra Naharros Km. 0019,0",
    "iso:country":"ES",
    "sg:address":"Ctra Naharros, Km. 0019,0",
    "sg:city":"Santa Marta De Tormes",
    "sg:orig_category":"Productos Alimentarios",
    "sg:phone":"+34 923 13 84 83",
    "sg:postcode":"37900",
    "sg:province":"Salamanca",
    "wof:name":"Salmantina De Piensos S. A.",
    "wof:placetype":"venue"
},
  "geometry": {"coordinates":[-5.6265788078,40.9506187439],"type":"Point"}
}