{
  "type": "Feature",
  "properties": {
    "addr:full":"Calle de Joaquin Costa, S/n Ainsa Huesca 22330",
    "addr:housenumber":"s / n",
    "addr:postcode":"22330",
    "addr:street":"Calle De Joaquin Costa",
    "iso:country":"ES",
    "sg:address":"Calle de Joaquin Costa, S/n",
    "sg:city":"Ainsa",
    "sg:orig_category":"Plomeros",
    "sg:phone":"+34 974 51 00 42",
    "sg:postcode":"22330",
    "sg:province":"Huesca",
    "wof:name":"Lerin Pinies Angel",
    "wof:placetype":"venue"
},
  "geometry": {"coordinates":[0.1396619976,42.4145011902],"type":"Point"}
}