{
  "type": "Feature",
  "properties": {
    "addr:full":"Urkizu Pasealekua, 13 Eibar Guip\u00f9zcoa 20600",
    "addr:housenumber":"13",
    "addr:postcode":"20600",
    "addr:street":"Urkizu Pasealekua;Guipu\u0300Zcoa",
    "iso:country":"ES",
    "sg:address":"Urkizu Pasealekua, 13",
    "sg:city":"Eibar",
    "sg:orig_category":"Centros M\u00c9dicos Y Sociales, Dispensarios",
    "sg:phone":"+34 943 12 02 00",
    "sg:postcode":"20600",
    "sg:province":"Guip\u00f9zcoa",
    "wof:name":"Centro Medico De Eibar S.a.",
    "wof:placetype":"venue"
},
  "geometry": {"coordinates":[-2.4637000561,43.1870880127],"type":"Point"}
}