{
  "type": "Feature",
  "properties": {
    "addr:full":"Calle de Urano, S/n Algaba Sevilla 41980",
    "addr:postcode":"41980",
    "addr:street":"Calle De Urano S / N Algaba",
    "iso:country":"ES",
    "sg:address":"Calle de Urano, S/n",
    "sg:city":"Algaba",
    "sg:orig_category":"Condimentos, Especias, Vinagres, Salsas Preparadas (fabricaci\u00d3n, Al Por Mayor)",
    "sg:phone":"+34 955 99 05 81",
    "sg:postcode":"41980",
    "sg:province":"Sevilla",
    "wof:name":"Vargas Torre Maria Francisca",
    "wof:placetype":"venue"
},
  "geometry": {"coordinates":[-6.0133395195,37.4664726257],"type":"Point"}
}