{
  "type": "Feature",
  "properties": {
    "addr:full":"Carrer de Urgell, 23 Prat Llobregat Barcelona 08820",
    "addr:housenumber":"23",
    "addr:postcode":"08820",
    "addr:street":"Carrer De Urgell;Llobregat",
    "iso:country":"ES",
    "sg:address":"Carrer de Urgell, 23",
    "sg:city":"Prat Llobregat",
    "sg:orig_category":"Molduras, Junquillos, Listones Y Molduras Perforadas",
    "sg:phone":"+34 933 70 04 16",
    "sg:postcode":"08820",
    "sg:province":"Barcelona",
    "wof:name":"Mantenimiento Y Servicios Bernal S. L.",
    "wof:placetype":"venue"
},
  "geometry": {"coordinates":[2.0904510021,41.3252716064],"type":"Point"}
}