{
  "type": "Feature",
  "properties": {
    "iso:country":"ES",
    "sg:address":"Avgd Pais Valencia, 3",
    "sg:city":"Xativa",
    "sg:orig_category":"Servicios Gsm",
    "sg:phone":"+34 962 28 35 52",
    "sg:postcode":"46800",
    "sg:province":"Valencia",
    "sg:website":"www.tongas-sl.com",
    "wof:name":"Tonga's S.l.",
    "wof:placetype":"venue"
},
  "geometry": {"coordinates":[-0.5195590258,38.9924736023],"type":"Point"}
}