{
  "type": "Feature",
  "properties": {
    "iso:country":"ES",
    "sg:address":"Calle de San Isidro, S/n",
    "sg:city":"Majadahonda",
    "sg:orig_category":"Confecci\u00d3n De Trajes Para Se\u00d1oras",
    "sg:phone":"+34 916 38 56 16",
    "sg:postcode":"28220",
    "sg:province":"Madrid",
    "wof:name":"Lamuedra Jimenez Amparo",
    "wof:placetype":"venue"
},
  "geometry": {"coordinates":[-3.8702089787,40.4731559753],"type":"Point"}
}