{
  "type": "Feature",
  "properties": {
    "iso:country":"ES",
    "sg:address":"Calle de Tumaco, 14",
    "sg:city":"Madrid",
    "sg:orig_category":"Centros Empresariales",
    "sg:phone":"+34 913 20 56 81",
    "sg:postcode":"28027",
    "sg:province":"Madrid",
    "wof:name":"Alarcon Castan Eloisa",
    "wof:placetype":"venue"
},
  "geometry": {"coordinates":[-3.6349434853,40.4452362061],"type":"Point"}
}