{
  "type": "Feature",
  "properties": {
    "addr:full":"Calle de Alhamar, 50 Granada Granada 18004",
    "addr:housenumber":"50",
    "addr:postcode":"18004",
    "addr:street":"Calle De Alhamar",
    "iso:country":"ES",
    "sg:address":"Calle de Alhamar, 50",
    "sg:city":"Granada",
    "sg:orig_category":"Empresas De Portes Y Mensajer\u00cda",
    "sg:phone":"+34 958 52 00 30",
    "sg:postcode":"18004",
    "sg:province":"Granada",
    "wof:name":"Mensajeros 9 A.m. S.l.",
    "wof:placetype":"venue"
},
  "geometry": {"coordinates":[-3.603767395,37.1690139771],"type":"Point"}
}