{
  "type": "Feature",
  "properties": {
    "iso:country":"ES",
    "sg:address":"Calle de Ursula Mu\u00d1oz, 2",
    "sg:city":"Pozoblanco",
    "sg:orig_category":"T\u00c9cnicos Veterinarios",
    "sg:phone":"+34 957 77 11 62",
    "sg:postcode":"14400",
    "sg:province":"C\u00f3rdoba",
    "wof:name":"Zavala De La Fuente Juan Jose",
    "wof:placetype":"venue"
},
  "geometry": {"coordinates":[-4.8496084213,38.3774871826],"type":"Point"}
}