{
  "type": "Feature",
  "properties": {
    "iso:country":"ES",
    "sg:address":"Calle de Carretas, 12",
    "sg:city":"Villaviciosa Odon",
    "sg:orig_category":"Librer\u00cdas",
    "sg:phone":"+34 916 65 77 13",
    "sg:postcode":"28670",
    "sg:province":"Madrid",
    "wof:name":"Libreria Y Peluqueria Pilma S.l.",
    "wof:placetype":"venue"
},
  "geometry": {"coordinates":[-3.902630806,40.3581809998],"type":"Point"}
}