{
  "type": "Feature",
  "properties": {
    "iso:country":"ES",
    "sg:address":"Calle de Rafael Morales, 1",
    "sg:city":"Badajoz",
    "sg:orig_category":"Ense\u00d1anza Variada",
    "sg:phone":"+34 924 24 96 86",
    "sg:postcode":"06005",
    "sg:province":"Badajoz",
    "wof:name":"Villalon Pla Teresa",
    "wof:placetype":"venue"
},
  "geometry": {"coordinates":[-6.9773159027,38.875],"type":"Point"}
}