{
  "type": "Feature",
  "properties": {
    "iso:country":"ES",
    "sg:address":"Carr Formentor, De, S/n",
    "sg:city":"Puerto De Pollen\u00c7a",
    "sg:orig_category":"Abogados",
    "sg:phone":"+34 971 86 62 78",
    "sg:postcode":"07470",
    "sg:province":"Islas Baleares",
    "wof:name":"De La Cruz Coll Y Asociados C.b.",
    "wof:placetype":"venue"
},
  "geometry": {"coordinates":[3.0821900368,39.9063034058],"type":"Point"}
}