{
  "type": "Feature",
  "properties": {
    "addr:full":"Calle de Jesusa Lara, 39 Estacion Madrid 28250",
    "addr:housenumber":"39",
    "addr:postcode":"28250",
    "addr:street":"Calle De Jesusa Lara",
    "iso:country":"ES",
    "sg:address":"Calle de Jesusa Lara, 39",
    "sg:city":"Estacion",
    "sg:orig_category":"Alimentaci\u00d3n General (al Por Menor)",
    "sg:phone":"+34 918 59 02 06",
    "sg:postcode":"28250",
    "sg:province":"Madrid",
    "wof:name":"Gutierrez Martin Mariano",
    "wof:placetype":"venue"
},
  "geometry": {"coordinates":[-3.9547009468,40.578918457],"type":"Point"}
}