{
  "type": "Feature",
  "properties": {
    "addr:full":"Calle de Juan Bautista Uriarte, 8 Kurtzea Vizcaya 48960",
    "addr:housenumber":"8",
    "addr:postcode":"48960",
    "addr:street":"Calle De Juan Bautista Uriarte",
    "iso:country":"ES",
    "sg:address":"Calle de Juan Bautista Uriarte, 8",
    "sg:city":"Kurtzea",
    "sg:orig_category":"Perfumer\u00cda (al Por Menor)",
    "sg:phone":"+34 944 56 24 01",
    "sg:postcode":"48960",
    "sg:province":"Vizcaya",
    "sg:website":"www.marionnaud.es",
    "wof:name":"Marionnaud Perfumeries Iberica S.l.",
    "wof:placetype":"venue"
},
  "geometry": {"coordinates":[-2.8468689919,43.2297019958],"type":"Point"}
}