{
  "type": "Feature",
  "properties": {
    "addr:full":"Pla\u00c7 Major, 1 Pollen\u00e7a Islas Baleares 07460",
    "addr:housenumber":"1",
    "addr:postcode":"07460",
    "addr:street":"Pollenc\u0327A",
    "iso:country":"ES",
    "sg:address":"Pla\u00c7 Major, 1",
    "sg:city":"Pollen\u00e7a",
    "sg:orig_category":"Asociaciones Y Clubs Deportivos",
    "sg:phone":"+34 971 53 01 63",
    "sg:postcode":"07460",
    "sg:province":"Islas Baleares",
    "wof:name":"Club Pollensa",
    "wof:placetype":"venue"
},
  "geometry": {"coordinates":[3.0059130192,39.8700141907],"type":"Point"}
}