{
  "type": "Feature",
  "properties": {
    "addr:full":"Calle de Gutierrez Herrero De, 52 Aviles Asturias 33402",
    "addr:housenumber":"52",
    "addr:postcode":"33402",
    "addr:street":"Calle De Gutierrez Herrero De",
    "iso:country":"ES",
    "sg:address":"Calle de Gutierrez Herrero De, 52",
    "sg:city":"Aviles",
    "sg:orig_category":"Empresas De Limpieza",
    "sg:phone":"+34 985 55 18 33",
    "sg:postcode":"33402",
    "sg:province":"Asturias",
    "sg:website":"www.curtidora.com",
    "wof:name":"Sociedad De Desarrollo La Curtidora S.a.",
    "wof:placetype":"venue"
},
  "geometry": {"coordinates":[-5.9149069786,43.5475463867],"type":"Point"}
}