{
  "type": "Feature",
  "properties": {
    "iso:country":"ES",
    "sg:address":"Avda Matapi\u00d1onera, 3",
    "sg:city":"San Sebastian De Los Reyes",
    "sg:orig_category":"Estudios, Instalaci\u00d3n De Climatizaci\u00d3n",
    "sg:phone":"+34 916 58 68 73",
    "sg:postcode":"28700",
    "sg:province":"Madrid",
    "sg:website":"www.tubosdominguez.com",
    "wof:name":"Tubos Dominguez S.a.",
    "wof:placetype":"venue"
},
  "geometry": {"coordinates":[-3.6194050312,40.5484313965],"type":"Point"}
}