{
  "type": "Feature",
  "properties": {
    "iso:country":"ES",
    "sg:address":"Calle de Juan Ramon Jimenez, 43",
    "sg:city":"Madrid",
    "sg:orig_category":"\u00d3ptica: Instrumentos (fabricaci\u00d3n)",
    "sg:phone":"+34 913 45 03 39",
    "sg:postcode":"28036",
    "sg:province":"Madrid",
    "wof:name":"Otero Cervera Maria Del Carmen",
    "wof:placetype":"venue"
},
  "geometry": {"coordinates":[-3.6872019768,40.4630126953],"type":"Point"}
}