{
  "type": "Feature",
  "properties": {
    "iso:country":"ES",
    "sg:address":"Mercado Central, 72",
    "sg:city":"Elche",
    "sg:orig_category":"Carnicer\u00cdas, Carnicer\u00cdas",
    "sg:phone":"+34 965 42 68 33",
    "sg:postcode":"03202",
    "sg:province":"Alicante",
    "wof:name":"Quiles Gillermo Diego",
    "wof:placetype":"venue"
},
  "geometry": {"coordinates":[-0.5931239724,38.2568435669],"type":"Point"}
}