{
  "type": "Feature",
  "properties": {
    "addr:full":"Ferrador, 7 Noia A Coru\u00f1a 15200",
    "addr:housenumber":"7",
    "addr:postcode":"15200",
    "addr:street":"Ferrador;A Corun\u0303A",
    "iso:country":"ES",
    "sg:address":"Ferrador, 7",
    "sg:city":"Noia",
    "sg:orig_category":"Peluquer\u00cdas, Peluquer\u00cda Mixta",
    "sg:phone":"+34 981 82 23 79",
    "sg:postcode":"15200",
    "sg:province":"A Coru\u00f1a",
    "wof:name":"Zamunda Peluqueras S.c.",
    "wof:placetype":"venue"
},
  "geometry": {"coordinates":[-8.8888044357,42.783996582],"type":"Point"}
}