{
  "type": "Feature",
  "properties": {
    "addr:full":"Avda Costa Del Sol, 12 Almu\u00f1ecar Granada 18690",
    "addr:housenumber":"12",
    "addr:postcode":"18690",
    "addr:street":"Avda Costa Del Sol",
    "iso:country":"ES",
    "sg:address":"Avda Costa Del Sol, 12",
    "sg:city":"Almu\u00f1ecar",
    "sg:orig_category":"Abogados",
    "sg:phone":"+34 958 63 05 51",
    "sg:postcode":"18690",
    "sg:province":"Granada",
    "wof:name":"Junta De Andalucia Consejeria De Gobernacion Y Justicia Numero 1 Yregistro Civil",
    "wof:placetype":"venue"
},
  "geometry": {"coordinates":[-3.6921520233,36.7360534668],"type":"Point"}
}