{
  "type": "Feature",
  "properties": {
    "iso:country":"ES",
    "sg:address":"Veinat Santa Eugenia, 3",
    "sg:city":"Avinyonet Puigventos",
    "sg:orig_category":"Estudios De Grabaci\u00d3n Sonora",
    "sg:phone":"+34 972 54 70 53",
    "sg:postcode":"17742",
    "sg:province":"Girona",
    "sg:website":"www.musiclan.com",
    "wof:name":"Music Lan S.l.",
    "wof:placetype":"venue"
},
  "geometry": {"coordinates":[2.9131500721,42.2506408691],"type":"Point"}
}