{
  "type": "Feature",
  "properties": {
    "addr:full":"Avda Jose Aguado, 32 Le\u00f3n Le\u00f3n 24005",
    "addr:housenumber":"32",
    "addr:postcode":"24005",
    "addr:street":"Avda Jose Aguado;Leo\u0301N",
    "iso:country":"ES",
    "sg:address":"Avda Jose Aguado, 32",
    "sg:city":"Le\u00f3n",
    "sg:orig_category":"Carnicer\u00cdas, Carnicer\u00cdas",
    "sg:phone":"+34 987 20 82 55",
    "sg:postcode":"24005",
    "sg:province":"Le\u00f3n",
    "wof:name":"Perez Calvo Lucio",
    "wof:placetype":"venue"
},
  "geometry": {"coordinates":[-5.5655422211,42.5886154175],"type":"Point"}
}