{
  "type": "Feature",
  "properties": {
    "iso:country":"ES",
    "sg:address":"Calle de Escuelas, 16",
    "sg:city":"Urracal",
    "sg:orig_category":"Administraciones Regionales, Departamentales Y Locales",
    "sg:phone":"+34 950 42 44 14",
    "sg:postcode":"04879",
    "sg:province":"Almer\u00eda",
    "wof:name":"Ayuntamiento De Urracal",
    "wof:placetype":"venue"
},
  "geometry": {"coordinates":[-2.364623785,37.3973960876],"type":"Point"}
}