{
  "type": "Feature",
  "properties": {
    "addr:full":"Carrer de Gon\u00c7al Pons, 13 Hospitalet Llobregat Barcelona 08902",
    "addr:housenumber":"13",
    "addr:postcode":"08902",
    "addr:street":"Carrer De Gonc\u0327Al Pons",
    "iso:country":"ES",
    "sg:address":"Carrer de Gon\u00c7al Pons, 13",
    "sg:city":"Hospitalet Llobregat",
    "sg:orig_category":"Fabricaci\u00d3n, Importaci\u00d3n De L\u00c1mparas Y Bombillas",
    "sg:phone":"+34 932 98 06 30",
    "sg:postcode":"08902",
    "sg:province":"Barcelona",
    "wof:name":"San Eulalia Iluminacion S.c.p.",
    "wof:placetype":"venue"
},
  "geometry": {"coordinates":[2.1201179028,41.3663787842],"type":"Point"}
}