{
  "type": "Feature",
  "properties": {
    "iso:country":"ES",
    "sg:address":"Calle de Alvaro De Bazan, 23",
    "sg:city":"Valencia",
    "sg:orig_category":"Ropa Para Se\u00d1oras (al Por Menor)",
    "sg:phone":"+34 963 61 40 30",
    "sg:postcode":"46010",
    "sg:province":"Valencia",
    "wof:name":"Villalba Iba\u00f1ez Concepcion",
    "wof:placetype":"venue"
},
  "geometry": {"coordinates":[-0.3609269857,39.4807281494],"type":"Point"}
}