{
  "type": "Feature",
  "properties": {
    "iso:country":"ES",
    "sg:address":"Calle de Carmen Medrano, 41",
    "sg:city":"Logro\u00f1o",
    "sg:orig_category":"Empresas De Vigilancia, Guardia Y Protecci\u00d3n",
    "sg:phone":"+34 941 24 72 04",
    "sg:postcode":"26005",
    "sg:province":"La Rioja",
    "wof:name":"Garda Servicios De Seguridad S.a.",
    "wof:placetype":"venue"
},
  "geometry": {"coordinates":[-2.4612109661,42.4698028564],"type":"Point"}
}