{
  "type": "Feature",
  "properties": {
    "addr:full":"Molino, 9 Medina-sidonia C\u00e1diz 11170",
    "addr:housenumber":"9",
    "addr:postcode":"11170",
    "addr:street":"Molino;Ca\u0301Diz",
    "iso:country":"ES",
    "sg:address":"Molino, 9",
    "sg:city":"Medina-sidonia",
    "sg:orig_category":"Muebles Y Accesorios Para Cocinas Y Cuartos De Ba\u00d1o (al Por Menor)",
    "sg:phone":"+34 956 41 08 81",
    "sg:postcode":"11170",
    "sg:province":"C\u00e1diz",
    "wof:name":"Estucocina S.l.",
    "wof:placetype":"venue"
},
  "geometry": {"coordinates":[-5.9289140701,36.4659576416],"type":"Point"}
}