{
  "type": "Feature",
  "properties": {
    "iso:country":"ES",
    "sg:address":"Calle de Fortuna (privada-poligono), 6",
    "sg:city":"Alcantarilla",
    "sg:orig_category":"Serigraf\u00cda (material Y Suministros)",
    "sg:phone":"+34 968 89 39 49",
    "sg:postcode":"30820",
    "sg:province":"Murcia",
    "wof:name":"Seristop S.l.",
    "wof:placetype":"venue"
},
  "geometry": {"coordinates":[-1.1958090067,37.9580383301],"type":"Point"}
}