{
  "type": "Feature",
  "properties": {
    "iso:country":"ES",
    "sg:address":"Calle de Jose Maria Perez Lozano, 17",
    "sg:city":"Navalmoral Mata",
    "sg:orig_category":"Peluquer\u00cdas",
    "sg:phone":"+34 927 53 26 70",
    "sg:postcode":"10300",
    "sg:province":"C\u00e1ceres",
    "wof:name":"Willians Montero Milagros Esther",
    "wof:placetype":"venue"
},
  "geometry": {"coordinates":[-5.5379896164,39.8896484375],"type":"Point"}
}