{
  "type": "Feature",
  "properties": {
    "iso:country":"ES",
    "sg:address":"Calle de Cardenal Lluch, 5",
    "sg:city":"Sevilla",
    "sg:orig_category":"Artesan\u00cda",
    "sg:phone":"+34 954 57 55 23",
    "sg:postcode":"41005",
    "sg:province":"Sevilla",
    "wof:name":"Morillo Lopez Julio",
    "wof:placetype":"venue"
},
  "geometry": {"coordinates":[-5.967499733,37.3842277527],"type":"Point"}
}