{
  "type": "Feature",
  "properties": {
    "iso:country":"ES",
    "sg:address":"Avda Alcalde Cantos Ropero, 51",
    "sg:city":"Jerez De La Frontera",
    "sg:orig_category":"Panader\u00cdas, Panader\u00cdas",
    "sg:phone":"+34 956 14 45 64",
    "sg:postcode":"11408",
    "sg:province":"C\u00e1diz",
    "wof:name":"Torres Garcia Rocio",
    "wof:placetype":"venue"
},
  "geometry": {"coordinates":[-6.1592831612,36.6686592102],"type":"Point"}
}