{
  "type": "Feature",
  "properties": {
    "iso:country":"ES",
    "sg:address":"Calle de Poza (la), 5",
    "sg:city":"Hervas",
    "sg:orig_category":"Cl\u00cdnicas Dentales",
    "sg:phone":"+34 927 47 30 95",
    "sg:postcode":"10700",
    "sg:province":"C\u00e1ceres",
    "wof:name":"Ruiz Martin Eduardo",
    "wof:placetype":"venue"
},
  "geometry": {"coordinates":[-5.8618941307,40.2744941711],"type":"Point"}
}