{
  "type": "Feature",
  "properties": {
    "addr:full":"Calle de Jose Maria Onieva, S/n Baena C\u00f3rdoba 14850",
    "addr:housenumber":"s",
    "addr:postcode":"14850",
    "addr:street":"Calle De Jose Maria Onieva;/ N;Co\u0301Rdoba",
    "iso:country":"ES",
    "sg:address":"Calle de Jose Maria Onieva, S/n",
    "sg:city":"Baena",
    "sg:orig_category":"Peluquer\u00cdas, Peluquer\u00cda Mixta",
    "sg:phone":"+34 957 67 15 83",
    "sg:postcode":"14850",
    "sg:province":"C\u00f3rdoba",
    "wof:name":"Luque Caballero Hilaria",
    "wof:placetype":"venue"
},
  "geometry": {"coordinates":[-4.3179087639,37.6171150208],"type":"Point"}
}