{
  "type": "Feature",
  "properties": {
    "addr:full":"Avda Chapi, 33 Elda Alicante 03600",
    "addr:housenumber":"33",
    "addr:postcode":"03600",
    "addr:street":"Avda Chapi",
    "iso:country":"ES",
    "sg:address":"Avda Chapi, 33",
    "sg:city":"Elda",
    "sg:orig_category":"Servidores Y Editores De Bases De Datos",
    "sg:phone":"+34 965 39 86 72",
    "sg:postcode":"03600",
    "sg:province":"Alicante",
    "sg:website":"www.adoraglobal.com",
    "wof:name":"Adora Global S..l",
    "wof:placetype":"venue"
},
  "geometry": {"coordinates":[-0.7952163815,38.4740791321],"type":"Point"}
}