{
  "type": "Feature",
  "properties": {
    "iso:country":"ES",
    "sg:address":"Pase Mesones (de Los), 28",
    "sg:city":"Lerma",
    "sg:orig_category":"Procuradores",
    "sg:phone":"+34 947 17 11 94",
    "sg:postcode":"09340",
    "sg:province":"Burgos",
    "wof:name":"Alonso Asenjo Teresa",
    "wof:placetype":"venue"
},
  "geometry": {"coordinates":[-3.7607872486,42.0267715454],"type":"Point"}
}