{
  "type": "Feature",
  "properties": {
    "addr:full":"Somavilla, 3 Medina Pomar Burgos 09500",
    "addr:housenumber":"3",
    "addr:postcode":"09500",
    "addr:street":"Somavilla",
    "iso:country":"ES",
    "sg:address":"Somavilla, 3",
    "sg:city":"Medina Pomar",
    "sg:orig_category":"Ingeniero",
    "sg:phone":"+34 947 14 74 74",
    "sg:postcode":"09500",
    "sg:province":"Burgos",
    "wof:name":"Muga Ezquerra Carlos Maria",
    "wof:placetype":"venue"
},
  "geometry": {"coordinates":[-3.4860041142,42.9317474365],"type":"Point"}
}