{
  "type": "Feature",
  "properties": {
    "addr:full":"Avda Santander (de) (herrera), 50 Herrera Cantabria 39608",
    "addr:housenumber":"50",
    "addr:postcode":"39608",
    "addr:street":"Avda Santander De Herrera",
    "iso:country":"ES",
    "sg:address":"Avda Santander (de) (herrera), 50",
    "sg:city":"Herrera",
    "sg:orig_category":"Carnicer\u00cdas, Carnicer\u00cdas",
    "sg:phone":"+34 942 25 01 48",
    "sg:postcode":"39608",
    "sg:province":"Cantabria",
    "wof:name":"Ramos Sanz Juan Arturo",
    "wof:placetype":"venue"
},
  "geometry": {"coordinates":[-3.8830139637,43.4323272705],"type":"Point"}
}