{
  "type": "Feature",
  "properties": {
    "addr:full":"Avda Valladolid, 30 Valencia Valencia 46020",
    "addr:housenumber":"30",
    "addr:postcode":"46020",
    "addr:street":"Avda Valladolid",
    "iso:country":"ES",
    "sg:address":"Avda Valladolid, 30",
    "sg:city":"Valencia",
    "sg:orig_category":"Reposter\u00cdas",
    "sg:phone":"+34 963 61 96 86",
    "sg:postcode":"46020",
    "sg:province":"Valencia",
    "wof:name":"Panificadora Estelles S.l.",
    "wof:placetype":"venue"
},
  "geometry": {"coordinates":[-0.3594799936,39.4887046814],"type":"Point"}
}