{
  "type": "Feature",
  "properties": {
    "iso:country":"ES",
    "sg:address":"Calle de Grabador Fabregat, 4",
    "sg:city":"Valencia",
    "sg:orig_category":"Laboratorios Farmac\u00c9uticos",
    "sg:phone":"+34 963 66 64 10",
    "sg:postcode":"46019",
    "sg:province":"Valencia",
    "wof:name":"Giner Lluesma Maria Consuelo",
    "wof:placetype":"venue"
},
  "geometry": {"coordinates":[-0.372168988,39.4967346191],"type":"Point"}
}