{
  "type": "Feature",
  "properties": {
    "iso:country":"ES",
    "sg:address":"Calle de Treviana, 19",
    "sg:city":"Madrid",
    "sg:orig_category":"Agencias Y Agentes Comerciales, Representantes",
    "sg:phone":"+34 914 13 78 20",
    "sg:postcode":"28043",
    "sg:province":"Madrid",
    "wof:name":"Jimenez Selas Jose",
    "wof:placetype":"venue"
},
  "geometry": {"coordinates":[-3.6578450203,40.4478340149],"type":"Point"}
}