{
  "type": "Feature",
  "properties": {
    "iso:country":"ES",
    "sg:address":"Plaz Alto Del Rollo, 1",
    "sg:city":"Salamanca",
    "sg:orig_category":"Peluquer\u00cdas, Peluquer\u00cda Mixta",
    "sg:phone":"+34 923 18 50 42",
    "sg:postcode":"37003",
    "sg:province":"Salamanca",
    "wof:name":"Hermanos Santos Herrero Cdad.",
    "wof:placetype":"venue"
},
  "geometry": {"coordinates":[-5.6474571228,40.9686737061],"type":"Point"}
}