{
  "type": "Feature",
  "properties": {
    "iso:country":"ES",
    "sg:address":"Calle de Morales Contreras, 15",
    "sg:city":"Soria",
    "sg:orig_category":"Albergues",
    "sg:phone":"+34 975 21 17 71",
    "sg:postcode":"42003",
    "sg:province":"Soria",
    "wof:name":"Valdenebro De Leon Angel",
    "wof:placetype":"venue"
},
  "geometry": {"coordinates":[-2.467261076,41.7609977722],"type":"Point"}
}