{
  "type": "Feature",
  "properties": {
    "addr:full":"Calle de Concepcion, 10 Petres Valencia 46500",
    "addr:housenumber":"10",
    "addr:postcode":"46500",
    "addr:street":"Calle De Concepcion",
    "iso:country":"ES",
    "sg:address":"Calle de Concepcion, 10",
    "sg:city":"Petres",
    "sg:orig_category":"Peluqueros: De Se\u00d1oras",
    "sg:phone":"+34 962 62 01 67",
    "sg:postcode":"46500",
    "sg:province":"Valencia",
    "wof:name":"Mateu Benet Francisca Filomena",
    "wof:placetype":"venue"
},
  "geometry": {"coordinates":[-0.3102591038,39.6836776733],"type":"Point"}
}