{
  "type": "Feature",
  "properties": {
    "addr:full":"Grup Iturribide, 12 Iturribide Vizcaya 48940",
    "addr:housenumber":"12",
    "addr:postcode":"48940",
    "addr:street":"Iturribide",
    "iso:country":"ES",
    "sg:address":"Grup Iturribide, 12",
    "sg:city":"Iturribide",
    "sg:orig_category":"Quincaller\u00cda (al Por Menor)",
    "sg:phone":"+34 944 63 10 02",
    "sg:postcode":"48940",
    "sg:province":"Vizcaya",
    "wof:name":"Ibarzabal Zabala Juan Felix",
    "wof:placetype":"venue"
},
  "geometry": {"coordinates":[-2.9860789776,43.3275489807],"type":"Point"}
}