{
  "type": "Feature",
  "properties": {
    "iso:country":"ES",
    "sg:address":"Calle de San Vicente Martir, 144",
    "sg:city":"Valencia",
    "sg:orig_category":"Molduras, Junquillos, Listones Y Molduras Perforadas",
    "sg:phone":"+34 963 80 71 72",
    "sg:postcode":"46007",
    "sg:province":"Valencia",
    "wof:name":"Carrion Lopez Francisco",
    "wof:placetype":"venue"
},
  "geometry": {"coordinates":[-0.3823829889,39.4628105164],"type":"Point"}
}