{
  "type": "Feature",
  "properties": {
    "iso:country":"ES",
    "sg:address":"Calle de Venezuela, 16",
    "sg:city":"Vitoria-gasteiz",
    "sg:orig_category":"Alimentaci\u00d3n General (al Por Menor)",
    "sg:phone":"+34 945 26 82 06",
    "sg:postcode":"01012",
    "sg:province":"\u00c1lava",
    "wof:name":"Bernaola Astondoa S.l",
    "wof:placetype":"venue"
},
  "geometry": {"coordinates":[-2.6785800457,42.8582229614],"type":"Point"}
}