{
  "type": "Feature",
  "properties": {
    "addr:full":"Calle de Placida Pedrosa, 6 Fines Almer\u00eda 04869",
    "addr:housenumber":"6",
    "addr:postcode":"04869",
    "addr:street":"Calle De Placida Pedrosa",
    "iso:country":"ES",
    "sg:address":"Calle de Placida Pedrosa, 6",
    "sg:city":"Fines",
    "sg:orig_category":"Empresas De Demolici\u00d3n",
    "sg:phone":"+34 950 44 42 63",
    "sg:postcode":"04869",
    "sg:province":"Almer\u00eda",
    "wof:name":"Excavaciones Garre Tripiana S.l.",
    "wof:placetype":"venue"
},
  "geometry": {"coordinates":[-2.263876915,37.3594207764],"type":"Point"}
}