{
  "type": "Feature",
  "properties": {
    "iso:country":"ES",
    "sg:address":"Calle de Gabriel Miro, 31",
    "sg:city":"Torrevieja",
    "sg:orig_category":"Inmobiliaria (agencias)",
    "sg:phone":"+34 966 70 14 95",
    "sg:postcode":"03180",
    "sg:province":"Alicante",
    "wof:name":"Hurtado Pe\u00f1alver Pedro",
    "wof:placetype":"venue"
},
  "geometry": {"coordinates":[-0.6871711016,37.977771759],"type":"Point"}
}