{
  "type": "Feature",
  "properties": {
    "addr:full":"Calle de Villahermosa, Duquesa De, 2 Huesca Huesca 22001",
    "addr:housenumber":"2",
    "addr:postcode":"22001",
    "addr:street":"Calle De Villahermosa Duquesa De",
    "iso:country":"ES",
    "sg:address":"Calle de Villahermosa, Duquesa De, 2",
    "sg:city":"Huesca",
    "sg:orig_category":"Ropa Para Se\u00d1oras Y Caballeros (al Por Menor)",
    "sg:phone":"+34 974 22 54 75",
    "sg:postcode":"22001",
    "sg:province":"Huesca",
    "wof:name":"Lopez Usieto Jose",
    "wof:placetype":"venue"
},
  "geometry": {"coordinates":[-0.4081290066,42.1374397278],"type":"Point"}
}