{
  "type": "Feature",
  "properties": {
    "iso:country":"ES",
    "sg:address":"Paseo De La Pur\u00edsima, 1",
    "sg:city":"Guadix",
    "sg:orig_category":"M\u00c9dicos: Pediatr\u00cda. Enfermedades De Los Ni\u00d1os",
    "sg:phone":"+34 958 66 46 42",
    "sg:postcode":"18500",
    "sg:province":"Granada",
    "wof:name":"Condor Mu\u00f1oz Francisco Javier",
    "wof:placetype":"venue"
},
  "geometry": {"coordinates":[-3.1327989101,37.3016700745],"type":"Point"}
}