{
  "type": "Feature",
  "properties": {
    "iso:country":"ES",
    "sg:address":"Calle de Jose Antonio, 22",
    "sg:city":"Arcicollar",
    "sg:orig_category":"Supermercados Y Hipermercados",
    "sg:phone":"+34 925 35 08 36",
    "sg:postcode":"45182",
    "sg:province":"Toledo",
    "wof:name":"Ardorosa S.l.",
    "wof:placetype":"venue"
},
  "geometry": {"coordinates":[-4.117128849,40.0560531616],"type":"Point"}
}