{
  "type": "Feature",
  "properties": {
    "addr:full":"Bda. De Torrecuevas, S/n Almu\u00f1ecar Granada 18690",
    "addr:housenumber":"s",
    "addr:postcode":"18690",
    "addr:street":"/ N Almun\u0303Ecar",
    "iso:country":"ES",
    "sg:address":"Bda. De Torrecuevas, S/n",
    "sg:city":"Almu\u00f1ecar",
    "sg:orig_category":"Alquiler De Veh\u00cdculos: Turismos Y Utilitarios",
    "sg:phone":"+34 958 88 11 72",
    "sg:postcode":"18690",
    "sg:province":"Granada",
    "wof:name":"Rodriguez Guerrero Manuel",
    "wof:placetype":"venue"
},
  "geometry": {"coordinates":[-3.6895239353,36.7616157532],"type":"Point"}
}