{
  "type": "Feature",
  "properties": {
    "iso:country":"ES",
    "sg:address":"Zona Aeroport, S/n",
    "sg:city":"Prat Llobregat",
    "sg:orig_category":"Transportes Internacionales",
    "sg:phone":"+34 933 70 27 61",
    "sg:postcode":"08820",
    "sg:province":"Barcelona",
    "wof:name":"Nippon Express Espa\u00d1a S.a.",
    "wof:placetype":"venue"
},
  "geometry": {"coordinates":[2.0864720345,41.3289909363],"type":"Point"}
}