{
  "type": "Feature",
  "properties": {
    "addr:full":"Carr D. Juan Antonio Baldovi, 11 Benidorm Alicante 03500",
    "addr:housenumber":"11",
    "addr:postcode":"03500",
    "addr:street":"Carr D. Juan Antonio Baldovi",
    "iso:country":"ES",
    "sg:address":"Carr D. Juan Antonio Baldovi, 11",
    "sg:city":"Benidorm",
    "sg:orig_category":"Cajas De Ahorro",
    "sg:phone":"+34 966 83 05 91",
    "sg:postcode":"03500",
    "sg:province":"Alicante",
    "sg:website":"www.cam.es",
    "wof:name":"Caja De Ahorros Del Mediterraneo",
    "wof:placetype":"venue"
},
  "geometry": {"coordinates":[-0.1743289977,38.5408058167],"type":"Point"}
}