{
  "type": "Feature",
  "properties": {
    "addr:full":"Calle de Martin Susaeta, S/n Vitoria-gasteiz \u00c1lava 01010",
    "addr:housenumber":"s",
    "addr:postcode":"01010",
    "addr:street":"Calle De Martin Susaeta;/ N",
    "iso:country":"ES",
    "sg:address":"Calle de Martin Susaeta, S/n",
    "sg:city":"Vitoria-gasteiz",
    "sg:orig_category":"Iglesia Cat\u00d3lica",
    "sg:phone":"+34 945 17 18 98",
    "sg:postcode":"01010",
    "sg:province":"\u00c1lava",
    "wof:name":"Parroquia De San Francisco Javier",
    "wof:placetype":"venue"
},
  "geometry": {"coordinates":[-2.6965138912,42.8584251404],"type":"Point"}
}