{
  "type": "Feature",
  "properties": {
    "iso:country":"ES",
    "sg:address":"Carr Buger, De Na, 11",
    "sg:city":"Valldemossa",
    "sg:orig_category":"Ingeniero",
    "sg:phone":"+34 971 61 26 01",
    "sg:postcode":"07170",
    "sg:province":"Islas Baleares",
    "wof:name":"Abac Projectes I Programes S.l.",
    "wof:placetype":"venue"
},
  "geometry": {"coordinates":[2.628852,39.694378],"type":"Point"}
}