{
  "type": "Feature",
  "properties": {
    "iso:country":"ES",
    "sg:address":"Rua Sur, 12",
    "sg:city":"Allariz",
    "sg:orig_category":"Abogados",
    "sg:phone":"+34 988 44 21 25",
    "sg:postcode":"32660",
    "sg:province":"Ourense",
    "wof:name":"Lopez Suarez Maria Angeles",
    "wof:placetype":"venue"
},
  "geometry": {"coordinates":[-7.8030109406,42.1889839172],"type":"Point"}
}