{
  "type": "Feature",
  "properties": {
    "addr:full":"Av Riu Ripoll (del), 51 Ripollet Barcelona 08291",
    "addr:housenumber":"51",
    "addr:postcode":"08291",
    "addr:street":"Av Riu Ripoll Del",
    "iso:country":"ES",
    "sg:address":"Av Riu Ripoll (del), 51",
    "sg:city":"Ripollet",
    "sg:orig_category":"Publicidad (soportes Y Gesti\u00d3n)",
    "sg:phone":"+34 935 92 20 52",
    "sg:postcode":"08291",
    "sg:province":"Barcelona",
    "wof:name":"Gamarti S.l.",
    "wof:placetype":"venue"
},
  "geometry": {"coordinates":[2.1546700001,41.4928512573],"type":"Point"}
}