{
  "type": "Feature",
  "properties": {
    "iso:country":"ES",
    "sg:address":"Plaz Poeta Miguel Hernandez, 7",
    "sg:city":"Barrio Orba",
    "sg:orig_category":"Estancos",
    "sg:phone":"+34 963 75 51 31",
    "sg:postcode":"46910",
    "sg:province":"Valencia",
    "wof:name":"Gasco Puertes Maria Del Don",
    "wof:placetype":"venue"
},
  "geometry": {"coordinates":[-0.063861303,38.7803611755],"type":"Point"}
}