{
  "type": "Feature",
  "properties": {
    "iso:country":"ES",
    "sg:address":"Carrer de Doctor Galban, 12",
    "sg:city":"Asco",
    "sg:orig_category":"Empresarios",
    "sg:phone":"+34 977 40 50 57",
    "sg:postcode":"43791",
    "sg:province":"Tarragona",
    "wof:name":"Miguel Garcia Sabate S.l.",
    "wof:placetype":"venue"
},
  "geometry": {"coordinates":[0.5654950142,41.181602478],"type":"Point"}
}