{
  "type": "Feature",
  "properties": {
    "addr:full":"Calle de Francisco Silvela, 45 Madrid Madrid 28028",
    "addr:housenumber":"45",
    "addr:postcode":"madrid;28028",
    "addr:street":"Calle De Francisco Silvela",
    "iso:country":"ES",
    "sg:address":"Calle de Francisco Silvela, 45",
    "sg:city":"Madrid",
    "sg:orig_category":"Costureras",
    "sg:phone":"+34 914 02 44 94",
    "sg:postcode":"28028",
    "sg:province":"Madrid",
    "wof:name":"Casta\u00f1o Grande Maria Del Mar",
    "wof:placetype":"venue"
},
  "geometry": {"coordinates":[-3.6729130745,40.4327545166],"type":"Point"}
}