{
  "type": "Feature",
  "properties": {
    "addr:full":"Calle de Maria De Molina, 10 Palencia Palencia 34002",
    "addr:housenumber":"10",
    "addr:postcode":"34002",
    "addr:street":"Calle De Maria De Molina",
    "iso:country":"ES",
    "sg:address":"Calle de Maria De Molina, 10",
    "sg:city":"Palencia",
    "sg:orig_category":"Molduras, Junquillos, Listones Y Molduras Perforadas",
    "sg:phone":"+34 979 72 27 37",
    "sg:postcode":"34002",
    "sg:province":"Palencia",
    "wof:name":"Lopez Salcedo Jose Maria",
    "wof:placetype":"venue"
},
  "geometry": {"coordinates":[-4.5264115334,42.0034790039],"type":"Point"}
}