{
  "type": "Feature",
  "properties": {
    "iso:country":"ES",
    "sg:address":"Calle de Ramon Gomez De La Serna, 4",
    "sg:city":"Madrid",
    "sg:orig_category":"Supermercados Y Hipermercados",
    "sg:phone":"+34 917 30 67 52",
    "sg:postcode":"28035",
    "sg:province":"Madrid",
    "wof:name":"Frio Union S.l.",
    "wof:placetype":"venue"
},
  "geometry": {"coordinates":[-3.727627039,40.482257843],"type":"Point"}
}