{
  "type": "Feature",
  "properties": {
    "addr:full":"Calle de Angel Alberquilla Polin, 7 Torrelodones Madrid 28250",
    "addr:housenumber":"7",
    "addr:postcode":"28250",
    "addr:street":"Calle De Angel Alberquilla Polin",
    "iso:country":"ES",
    "sg:address":"Calle de Angel Alberquilla Polin, 7",
    "sg:city":"Torrelodones",
    "sg:classifiers":[
        {
            "category":"Casinos & Gambling",
            "type":"Entertainment"
        }
    ],
    "sg:phone":"+34 918 59 16 77",
    "sg:postcode":"28250",
    "sg:province":"Madrid",
    "sg:tags":[
        "locale",
        "de",
        "juego"
    ],
    "wof:name":"Alberquilla Torres Maria Jose",
    "wof:placetype":"venue"
},
  "geometry": {"coordinates":[-3.9269008636,40.5761871338],"type":"Point"}
}