{
  "type": "Feature",
  "properties": {
    "addr:full":"Pl Rius I Taulet, 1 Barcelona Barcelona 08012",
    "addr:housenumber":"1",
    "addr:postcode":"08012",
    "addr:street":"Pl Rius I Taulet",
    "iso:country":"ES",
    "sg:address":"Pl Rius I Taulet, 1",
    "sg:city":"Barcelona",
    "sg:orig_category":"Molduras, Junquillos, Listones Y Molduras Perforadas",
    "sg:phone":"+34 934 15 04 00",
    "sg:postcode":"08012",
    "sg:province":"Barcelona",
    "wof:name":"Las Euras S.c.p.",
    "wof:placetype":"venue"
},
  "geometry": {"coordinates":[2.1577730179,41.3998947144],"type":"Point"}
}