{
  "type": "Feature",
  "properties": {
    "addr:full":"Plaz Tendillas (de Las), 1 Cordoba C\u00f3rdoba 14002",
    "addr:housenumber":"1",
    "addr:postcode":"14002",
    "addr:street":"Plaz Tendillas De Las;Co\u0301Rdoba",
    "iso:country":"ES",
    "sg:address":"Plaz Tendillas (de Las), 1",
    "sg:city":"Cordoba",
    "sg:orig_category":"Inmobiliaria (agencias)",
    "sg:phone":"+34 957 47 97 10",
    "sg:postcode":"14002",
    "sg:province":"C\u00f3rdoba",
    "wof:name":"Monthisa Residencial S.a.",
    "wof:placetype":"venue"
},
  "geometry": {"coordinates":[-4.7792291641,37.8844032288],"type":"Point"}
}