{
  "type": "Feature",
  "properties": {
    "addr:full":"Calle de Mestikabaso Kalea, 19 Gernika-lumo Vizcaya 48300",
    "addr:housenumber":"19",
    "addr:postcode":"48300",
    "addr:street":"Calle De Mestikabaso Kalea",
    "iso:country":"ES",
    "sg:address":"Calle de Mestikabaso Kalea, 19",
    "sg:city":"Gernika-lumo",
    "sg:orig_category":"Farmacias",
    "sg:phone":"+34 946 25 63 24",
    "sg:postcode":"48300",
    "sg:province":"Vizcaya",
    "wof:name":"Farmacia Maria Bego\u00f1a Izaguirre Ugarte",
    "wof:placetype":"venue"
},
  "geometry": {"coordinates":[-97.78224945069999,45.7040786743],"type":"Point"}
}