{
  "type": "Feature",
  "properties": {
    "iso:country":"ES",
    "sg:address":"Calle de Coso, 77",
    "sg:city":"Zaragoza",
    "sg:orig_category":"Asesor\u00cda Fiscal Y Jur\u00cddica",
    "sg:phone":"+34 976 29 58 46",
    "sg:postcode":"50001",
    "sg:province":"Zaragoza",
    "wof:name":"Artal Lerin Amelia",
    "wof:placetype":"venue"
},
  "geometry": {"coordinates":[-0.878125906,41.6512908936],"type":"Point"}
}