{
  "type": "Feature",
  "properties": {
    "addr:full":"Carr Talaia, 27 Vilanova I La Geltru Barcelona 08800",
    "addr:housenumber":"27",
    "addr:postcode":"08800",
    "addr:street":"Carr Talaia",
    "iso:country":"ES",
    "sg:address":"Carr Talaia, 27",
    "sg:city":"Vilanova I La Geltru",
    "sg:orig_category":"Empresas De Pintura Y Revestimientos",
    "sg:phone":"+34 938 10 30 89",
    "sg:postcode":"08800",
    "sg:province":"Barcelona",
    "wof:name":"Vinagre Lopez Virginio",
    "wof:placetype":"venue"
},
  "geometry": {"coordinates":[1.6929570436,41.2291259766],"type":"Point"}
}