{
  "type": "Feature",
  "properties": {
    "addr:full":"Carrer de Figols, 27 Barcelona Barcelona 08028",
    "addr:housenumber":"27",
    "addr:postcode":"08028",
    "addr:street":"Carrer De Figols",
    "iso:country":"ES",
    "sg:address":"Carrer de Figols, 27",
    "sg:city":"Barcelona",
    "sg:orig_category":"Instalaci\u00d3n, Reparaci\u00d3n De Ascensores Y Montacargas",
    "sg:phone":"+34 933 30 02 60",
    "sg:postcode":"08028",
    "sg:province":"Barcelona",
    "wof:name":"Electro Comercial Toledano S.c.p.",
    "wof:placetype":"venue"
},
  "geometry": {"coordinates":[2.129942894,41.3825721741],"type":"Point"}
}