{
  "type": "Feature",
  "properties": {
    "addr:full":"Lapurdi Kalea, 1 Zarautz Guip\u00f9zcoa 20800",
    "addr:housenumber":"1",
    "addr:postcode":"20800",
    "addr:street":"Lapurdi Kalea;Guipu\u0300Zcoa",
    "iso:country":"ES",
    "sg:address":"Lapurdi Kalea, 1",
    "sg:city":"Zarautz",
    "sg:orig_category":"Delegados, Agentes De Tr\u00c1nsito, Auxiliares De Transporte Internacional",
    "sg:phone":"+34 943 83 32 51",
    "sg:postcode":"20800",
    "sg:province":"Guip\u00f9zcoa",
    "wof:name":"Sirvent Diaz Antonio",
    "wof:placetype":"venue"
},
  "geometry": {"coordinates":[-2.1708030701,43.2845344543],"type":"Point"}
}