{
  "type": "Feature",
  "properties": {
    "iso:country":"ES",
    "sg:address":"Calle de Poeta Quintana, 3",
    "sg:city":"Alacant",
    "sg:orig_category":"Relojer\u00cda (al Por Menor, Reparaci\u00d3n)",
    "sg:phone":"+34 965 21 13 76",
    "sg:postcode":"03004",
    "sg:province":"Alicante",
    "wof:name":"Joyeria Relojeria Vela Rubio S.l.",
    "wof:placetype":"venue"
},
  "geometry": {"coordinates":[-0.4871054888,38.3484725952],"type":"Point"}
}