{
  "type": "Feature",
  "properties": {
    "addr:full":"Calle de Martinez Campos, 20 Granada Granada 18002",
    "addr:housenumber":"20",
    "addr:postcode":"18002",
    "addr:street":"Calle De Martinez Campos",
    "iso:country":"ES",
    "sg:address":"Calle de Martinez Campos, 20",
    "sg:city":"Granada",
    "sg:orig_category":"Producci\u00d3n De Abonos Y De Fertilizantes",
    "sg:phone":"+34 958 25 26 48",
    "sg:postcode":"18002",
    "sg:province":"Granada",
    "wof:name":"Abonos Naturales S.a.",
    "wof:placetype":"venue"
},
  "geometry": {"coordinates":[-3.604234,37.171642],"type":"Point"}
}