{
  "type": "Feature",
  "properties": {
    "iso:country":"ES",
    "sg:address":"Calle de Juan De Austria, 64",
    "sg:city":"S. Fernando",
    "sg:orig_category":"Partidos Pol\u00cdticos",
    "sg:phone":"+34 956 88 05 41",
    "sg:postcode":"11100",
    "sg:province":"C\u00e1diz",
    "wof:name":"Izquierda Unida-los Verdes Convocatoria Por Andalucia",
    "wof:placetype":"venue"
},
  "geometry": {"coordinates":[-6.1967391968,36.4654541016],"type":"Point"}
}