{
  "type": "Feature",
  "properties": {
    "iso:country":"ES",
    "sg:address":"Cust San Francisco, 5",
    "sg:city":"Vitoria-gasteiz",
    "sg:orig_category":"Inmobiliaria (agencias)",
    "sg:phone":"+34 945 23 29 11",
    "sg:postcode":"01001",
    "sg:province":"\u00c1lava",
    "wof:name":"Majuelo Fincas Y Seguros S.c.",
    "wof:placetype":"venue"
},
  "geometry": {"coordinates":[-2.6706368923,42.8489875793],"type":"Point"}
}