{
  "type": "Feature",
  "properties": {
    "addr:full":"General Del Sur, Km. 0011,0 El Castillo Las Palmas 35610",
    "addr:postcode":"35610",
    "addr:street":"Del;Km. 0011,0",
    "iso:country":"ES",
    "sg:address":"General Del Sur, Km. 0011,0",
    "sg:city":"El Castillo",
    "sg:orig_category":"Servicios Gsm",
    "sg:phone":"+34 928 16 01 25",
    "sg:postcode":"35610",
    "sg:province":"Las Palmas",
    "wof:name":"Intro 2000 Top S.l.",
    "wof:placetype":"venue"
},
  "geometry": {"coordinates":[-13.863199234,28.3980941772],"type":"Point"}
}