{
  "type": "Feature",
  "properties": {
    "iso:country":"ES",
    "sg:address":"Calle de Santa Ana, 12",
    "sg:city":"Villares Reina",
    "sg:orig_category":"Molduras, Junquillos, Listones Y Molduras Perforadas",
    "sg:phone":"+34 923 28 83 38",
    "sg:postcode":"37184",
    "sg:province":"Salamanca",
    "wof:name":"Martin Mulas Maria Amparo",
    "wof:placetype":"venue"
},
  "geometry": {"coordinates":[-5.650416851,41.0088500977],"type":"Point"}
}