{
  "type": "Feature",
  "properties": {
    "iso:country":"ES",
    "sg:address":"Calle de Sor Angela De La Cruz, 7",
    "sg:city":"Madrid",
    "sg:orig_category":"Asesor\u00cda Fiscal Y Jur\u00cddica",
    "sg:phone":"+34 915 56 18 41",
    "sg:postcode":"28020",
    "sg:province":"Madrid",
    "wof:name":"Atticus Finch S.l.",
    "wof:placetype":"venue"
},
  "geometry": {"coordinates":[-3.6929678917,40.4591636658],"type":"Point"}
}