{
  "type": "Feature",
  "properties": {
    "addr:full":"Veracruz, 13 Alcala Real Ja\u00e9n 23680",
    "addr:postcode":"23680",
    "addr:street":"Veracruz 13;Jae\u0301N",
    "iso:country":"ES",
    "sg:address":"Veracruz, 13",
    "sg:city":"Alcala Real",
    "sg:orig_category":"Peluqueros: De Se\u00d1oras",
    "sg:phone":"+34 953 58 31 26",
    "sg:postcode":"23680",
    "sg:province":"Ja\u00e9n",
    "wof:name":"Marquez Cano Maria De Los Remedios",
    "wof:placetype":"venue"
},
  "geometry": {"coordinates":[-3.9240620136,37.4628944397],"type":"Point"}
}