{
  "type": "Feature",
  "properties": {
    "addr:full":"Teresa, S/n Roca Llisa Islas Baleares 07800",
    "addr:housenumber":"s / n",
    "addr:postcode":"07800",
    "addr:street":"Teresa;Llisa",
    "iso:country":"ES",
    "sg:address":"Teresa, S/n",
    "sg:city":"Roca Llisa",
    "sg:orig_category":"Inmobiliaria (agencias)",
    "sg:phone":"+34 971 19 60 35",
    "sg:postcode":"07800",
    "sg:province":"Islas Baleares",
    "wof:name":"Carolina Capelli Pia Anna",
    "wof:placetype":"venue"
},
  "geometry": {"coordinates":[1.4188899994,38.9061164856],"type":"Point"}
}