{
  "type": "Feature",
  "properties": {
    "iso:country":"ES",
    "sg:address":"Carr Joanot Martorell, 8",
    "sg:city":"Sueca",
    "sg:orig_category":"Reposter\u00cdas",
    "sg:phone":"+34 961 70 20 55",
    "sg:postcode":"46410",
    "sg:province":"Valencia",
    "wof:name":"Alberola Sieres Y Benedito C.b.",
    "wof:placetype":"venue"
},
  "geometry": {"coordinates":[-0.3141894042,39.1984672546],"type":"Point"}
}