{
  "type": "Feature",
  "properties": {
    "addr:full":"Avgd Flix, 2 Lleida Lleida 25001",
    "addr:housenumber":"2",
    "addr:postcode":"25001",
    "addr:street":"Flix",
    "iso:country":"ES",
    "sg:address":"Avgd Flix, 2",
    "sg:city":"Lleida",
    "sg:orig_category":"Negocio De Materiales De Construcci\u00d3n",
    "sg:phone":"+34 973 20 01 32",
    "sg:postcode":"25001",
    "sg:province":"Lleida",
    "wof:name":"Materials Per A La Contruccio I Adobs J.pi\u00d1ol S.l.",
    "wof:placetype":"venue"
},
  "geometry": {"coordinates":[0.6414020061,41.604057312],"type":"Point"}
}