{
  "type": "Feature",
  "properties": {
    "addr:full":"Carr Mayor, 60 Eliana Valencia 46183",
    "addr:housenumber":"60",
    "addr:postcode":"46183",
    "addr:street":"Carr Mayor",
    "iso:country":"ES",
    "sg:address":"Carr Mayor, 60",
    "sg:city":"Eliana",
    "sg:orig_category":"Ropa Para Ni\u00d1os (al Por Menor)",
    "sg:phone":"+34 962 72 55 98",
    "sg:postcode":"46183",
    "sg:province":"Valencia",
    "wof:name":"Efectos Especiales Peques C B",
    "wof:placetype":"venue"
},
  "geometry": {"coordinates":[-0.528208971,39.5667457581],"type":"Point"}
}