{
  "type": "Feature",
  "properties": {
    "iso:country":"ES",
    "sg:address":"Bidebarrieta Kalea, 33",
    "sg:city":"Eibar",
    "sg:orig_category":"Peluqueros: De Se\u00d1oras",
    "sg:phone":"+34 943 70 19 47",
    "sg:postcode":"20600",
    "sg:province":"Guip\u00f9zcoa",
    "wof:name":"Onaindia Zabala Maria Luz",
    "wof:placetype":"venue"
},
  "geometry": {"coordinates":[-2.4662730694,43.1855545044],"type":"Point"}
}