{
  "type": "Feature",
  "properties": {
    "iso:country":"ES",
    "sg:address":"Calle de Argensola, 10",
    "sg:city":"Madrid",
    "sg:orig_category":"Ropa Para Ni\u00d1os (al Por Menor)",
    "sg:phone":"+34 913 08 49 48",
    "sg:postcode":"28004",
    "sg:province":"Madrid",
    "wof:name":"Ruiz Martin Mercedes",
    "wof:placetype":"venue"
},
  "geometry": {"coordinates":[-3.6949210167,40.4252204895],"type":"Point"}
}