{
  "type": "Feature",
  "properties": {
    "iso:country":"ES",
    "sg:address":"El Rosario, 12",
    "sg:city":"Bocos",
    "sg:orig_category":"Modelistas",
    "sg:phone":"+34 947 13 22 76",
    "sg:postcode":"09553",
    "sg:province":"Burgos",
    "wof:name":"Martinez Gonzalez Fernando",
    "wof:placetype":"venue"
},
  "geometry": {"coordinates":[-3.5457789898,42.9687385559],"type":"Point"}
}