{
  "type": "Feature",
  "properties": {
    "addr:full":"Rua Castro, 4 Betanzos A Coru\u00f1a 15300",
    "addr:housenumber":"4",
    "addr:postcode":"15300",
    "addr:street":"Rua Castro",
    "iso:country":"ES",
    "sg:address":"Rua Castro, 4",
    "sg:city":"Betanzos",
    "sg:orig_category":"\u00d3ptica: Instrumentos (fabricaci\u00d3n)",
    "sg:phone":"+34 981 77 06 57",
    "sg:postcode":"15300",
    "sg:province":"A Coru\u00f1a",
    "wof:name":"Selgas Vidal Juan Antonio",
    "wof:placetype":"venue"
},
  "geometry": {"coordinates":[-8.2105913162,43.2806167603],"type":"Point"}
}