{
  "type": "Feature",
  "properties": {
    "addr:full":"Ctra Vic, 17 Manresa Barcelona 08241",
    "addr:housenumber":"17",
    "addr:postcode":"08241",
    "addr:street":"Ctra Vic",
    "iso:country":"ES",
    "sg:address":"Ctra Vic, 17",
    "sg:city":"Manresa",
    "sg:orig_category":"Abogados",
    "sg:phone":"+34 938 72 11 32",
    "sg:postcode":"08241",
    "sg:province":"Barcelona",
    "wof:name":"Badia Sala Josep Maria",
    "wof:placetype":"venue"
},
  "geometry": {"coordinates":[1.8259810209,41.7259063721],"type":"Point"}
}