{
  "type": "Feature",
  "properties": {
    "iso:country":"ES",
    "sg:address":"Carrer de Lope De Vega, 51",
    "sg:city":"Barcelona",
    "sg:orig_category":"Vinos Y Licores (venta Al Por Menor)",
    "sg:phone":"+34 933 20 92 55",
    "sg:postcode":"08005",
    "sg:province":"Barcelona",
    "wof:name":"Celler Del Mar S.c.p",
    "wof:placetype":"venue"
},
  "geometry": {"coordinates":[2.2054309845,41.4028739929],"type":"Point"}
}