{
  "type": "Feature",
  "properties": {
    "iso:country":"ES",
    "sg:address":"Calle de Tendillas, 16",
    "sg:city":"Toledo",
    "sg:orig_category":"Papeler\u00cdas, Librer\u00cdas",
    "sg:phone":"+34 925 22 10 12",
    "sg:postcode":"45002",
    "sg:province":"Toledo",
    "wof:name":"Moreno Gallarte Alfonso",
    "wof:placetype":"venue"
},
  "geometry": {"coordinates":[-4.0267338753,39.8596305847],"type":"Point"}
}