{
  "type": "Feature",
  "properties": {
    "addr:full":"Calle de La Fabrica, 22 Alcora Castell\u00f3n 12110",
    "addr:housenumber":"22",
    "addr:postcode":"12110",
    "addr:street":"Calle De La Fabrica;Castello\u0301N",
    "iso:country":"ES",
    "sg:address":"Calle de La Fabrica, 22",
    "sg:city":"Alcora",
    "sg:orig_category":"Transportes Por V\u00cdas Navegables",
    "sg:phone":"+34 964 36 20 59",
    "sg:postcode":"12110",
    "sg:province":"Castell\u00f3n",
    "wof:name":"Puerto Monfort S.l.",
    "wof:placetype":"venue"
},
  "geometry": {"coordinates":[-0.2128359973,40.0727081299],"type":"Point"}
}