{
  "type": "Feature",
  "properties": {
    "addr:full":"Calle de Espronceda, 8 Madrid Madrid 28003",
    "addr:housenumber":"8",
    "addr:postcode":"madrid;28003",
    "addr:street":"Calle De Espronceda",
    "iso:country":"ES",
    "sg:address":"Calle de Espronceda, 8",
    "sg:city":"Madrid",
    "sg:orig_category":"Producci\u00d3n, Distribuci\u00d3n De Electricidad",
    "sg:phone":"+34 914 41 94 46",
    "sg:postcode":"28003",
    "sg:province":"Madrid",
    "wof:name":"Dominguez Del Buey Domingo",
    "wof:placetype":"venue"
},
  "geometry": {"coordinates":[-3.6984689236,40.4405517578],"type":"Point"}
}