{
  "type": "Feature",
  "properties": {
    "addr:full":"Rond Francesc Camprodon, 8 Vic Barcelona 08500",
    "addr:housenumber":"8",
    "addr:postcode":"08500",
    "addr:street":"Rond;Camprodon",
    "iso:country":"ES",
    "sg:address":"Rond Francesc Camprodon, 8",
    "sg:city":"Vic",
    "sg:orig_category":"Grafistas",
    "sg:phone":"+34 938 86 20 45",
    "sg:postcode":"08500",
    "sg:province":"Barcelona",
    "wof:name":"Sola Daufi Marc",
    "wof:placetype":"venue"
},
  "geometry": {"coordinates":[2.2552189827,41.9342765808],"type":"Point"}
}