{
  "type": "Feature",
  "properties": {
    "iso:country":"ES",
    "sg:address":"Calle de Bachiller, El, 16",
    "sg:city":"Valencia",
    "sg:orig_category":"M\u00c9dicos: Estomatolog\u00cda",
    "sg:phone":"+34 963 62 57 64",
    "sg:postcode":"46010",
    "sg:province":"Valencia",
    "wof:name":"Rodriguez Gonzalez Ana Maria",
    "wof:placetype":"venue"
},
  "geometry": {"coordinates":[-0.3619506061,39.4820213318],"type":"Point"}
}