{
  "type": "Feature",
  "properties": {
    "iso:country":"ES",
    "sg:address":"Calle de Lepanto, 30",
    "sg:city":"Balsicas",
    "sg:orig_category":"Centros Empresariales",
    "sg:phone":"+34 968 58 04 55",
    "sg:postcode":"30591",
    "sg:province":"Murcia",
    "wof:name":"Almero Mu\u00f1oz Victoriano",
    "wof:placetype":"venue"
},
  "geometry": {"coordinates":[-0.9569808841,37.8168411255],"type":"Point"}
}