{
  "type": "Feature",
  "properties": {
    "addr:full":"Carr Miguel Abriat Canto (de), 2 Lliria Valencia 46160",
    "addr:housenumber":"2",
    "addr:postcode":"46160",
    "addr:street":"Carr Miguel Abriat Canto De",
    "iso:country":"ES",
    "sg:address":"Carr Miguel Abriat Canto (de), 2",
    "sg:city":"Lliria",
    "sg:orig_category":"Electricidad: Instaladores",
    "sg:phone":"+34 962 78 04 42",
    "sg:postcode":"46160",
    "sg:province":"Valencia",
    "wof:name":"Marbeba S.l.",
    "wof:placetype":"venue"
},
  "geometry": {"coordinates":[-0.5985900164,39.6278190613],"type":"Point"}
}