{
  "type": "Feature",
  "properties": {
    "addr:full":"Calle de Lagasca, 27 Madrid Madrid 28001",
    "addr:housenumber":"27",
    "addr:postcode":"madrid;28001",
    "addr:street":"Calle De Lagasca",
    "iso:country":"ES",
    "sg:address":"Calle de Lagasca, 27",
    "sg:city":"Madrid",
    "sg:orig_category":"Muebles, Minoristas",
    "sg:phone":"+34 915 78 37 93",
    "sg:postcode":"28001",
    "sg:province":"Madrid",
    "sg:website":"www.nuevotomares.com",
    "wof:name":"Kalido Mueble Natural S.l.",
    "wof:placetype":"venue"
},
  "geometry": {"coordinates":[-3.6854858398,40.4245491028],"type":"Point"}
}