{
  "type": "Feature",
  "properties": {
    "iso:country":"ES",
    "sg:address":"Calle de Orense, 69",
    "sg:city":"Madrid",
    "sg:orig_category":"Traductores",
    "sg:phone":"+34 915 79 30 17",
    "sg:postcode":"28020",
    "sg:province":"Madrid",
    "sg:website":"www.bowneglobal.es",
    "wof:name":"Lionbridge Espa\u00d1a S.l.",
    "wof:placetype":"venue"
},
  "geometry": {"coordinates":[-3.6946299076,40.4582252502],"type":"Point"}
}