{
  "type": "Feature",
  "properties": {
    "addr:full":"Calle de Gamazo, 14 Valladolid Valladolid 47004",
    "addr:housenumber":"14",
    "addr:postcode":"47004",
    "addr:street":"Calle De Gamazo",
    "iso:country":"ES",
    "sg:address":"Calle de Gamazo, 14",
    "sg:city":"Valladolid",
    "sg:orig_category":"M\u00c9dicos: Estomatolog\u00cda",
    "sg:phone":"+34 983 30 62 81",
    "sg:postcode":"47004",
    "sg:province":"Valladolid",
    "wof:name":"Viloria Garcia Glicerio",
    "wof:placetype":"venue"
},
  "geometry": {"coordinates":[-4.7261896133,41.6463508606],"type":"Point"}
}