{
  "type": "Feature",
  "properties": {
    "iso:country":"ES",
    "sg:address":"Carrer de Sant Iscle, 2",
    "sg:city":"Barcelona",
    "sg:orig_category":"\u00d3ptica: Instrumentos (fabricaci\u00d3n)",
    "sg:phone":"+34 934 08 15 14",
    "sg:postcode":"08031",
    "sg:province":"Barcelona",
    "wof:name":"Optica Del Penedes S.l.",
    "wof:placetype":"venue"
},
  "geometry": {"coordinates":[2.1740980148,41.4305038452],"type":"Point"}
}