{
  "type": "Feature",
  "properties": {
    "addr:full":"Calle de Mayor De Reinoso, 26 Bejar Salamanca 37700",
    "addr:housenumber":"26",
    "addr:postcode":"37700",
    "addr:street":"Calle De Mayor De Reinoso",
    "iso:country":"ES",
    "sg:address":"Calle de Mayor De Reinoso, 26",
    "sg:city":"Bejar",
    "sg:orig_category":"Electrodom\u00c9sticos (fabricaci\u00d3n, Al Por Mayor)",
    "sg:phone":"+34 923 40 46 46",
    "sg:postcode":"37700",
    "sg:province":"Salamanca",
    "wof:name":"Calles Campo Francisco",
    "wof:placetype":"venue"
},
  "geometry": {"coordinates":[-5.7720351219,40.3879852295],"type":"Point"}
}