{
  "type": "Feature",
  "properties": {
    "addr:full":"Cmno Brazal La Mota, S/n Huerta De Alquerias Murcia 30580",
    "addr:housenumber":"s / n",
    "addr:postcode":"30580",
    "addr:street":"Cmno Brazal La Mota",
    "iso:country":"ES",
    "sg:address":"Cmno Brazal La Mota, S/n",
    "sg:city":"Huerta De Alquerias",
    "sg:orig_category":"Muebles",
    "sg:phone":"+34 968 87 00 56",
    "sg:postcode":"30580",
    "sg:province":"Murcia",
    "wof:name":"Tapizados Mu\u00f1oz Robles S.l.",
    "wof:placetype":"venue"
},
  "geometry": {"coordinates":[-1.0310490131,38.0146942139],"type":"Point"}
}