{
  "type": "Feature",
  "properties": {
    "iso:country":"ES",
    "sg:address":"Calle de Newton, 8",
    "sg:city":"Estepona",
    "sg:orig_category":"Electromec\u00c1nica",
    "sg:phone":"+34 952 79 34 04",
    "sg:postcode":"29680",
    "sg:province":"M\u00e1laga",
    "wof:name":"Talleres Newton S.l.",
    "wof:placetype":"venue"
},
  "geometry": {"coordinates":[-5.1691670418,36.4305992126],"type":"Point"}
}