{
  "type": "Feature",
  "properties": {
    "addr:full":"Avda Navarra, 17 Irun Guip\u00f9zcoa 20304",
    "addr:housenumber":"17",
    "addr:postcode":"20304",
    "addr:street":"Avda Navarra;Guipu\u0300Zcoa",
    "iso:country":"ES",
    "sg:address":"Avda Navarra, 17",
    "sg:city":"Irun",
    "sg:orig_category":"Perfumer\u00cda (al Por Menor)",
    "sg:phone":"+34 943 11 53 95",
    "sg:postcode":"20304",
    "sg:province":"Guip\u00f9zcoa",
    "wof:name":"Marisol Alonso Sistiaga",
    "wof:placetype":"venue"
},
  "geometry": {"coordinates":[-1.7843140364,43.3394165039],"type":"Point"}
}