{
  "type": "Feature",
  "properties": {
    "iso:country":"ES",
    "sg:address":"Carrer de Magnolia, 3",
    "sg:city":"Palma",
    "sg:orig_category":"Mudanzas",
    "sg:phone":"+34 971 20 55 39",
    "sg:postcode":"07010",
    "sg:province":"Islas Baleares",
    "wof:name":"Borrego De La Fuente Juan",
    "wof:placetype":"venue"
},
  "geometry": {"coordinates":[2.6490039825,39.5936584473],"type":"Point"}
}