{
  "type": "Feature",
  "properties": {
    "iso:country":"ES",
    "sg:address":"Calle de Ca\u00d1on, 6",
    "sg:city":"Cartagena",
    "sg:orig_category":"Deportes N\u00c1uticos, Acu\u00c1ticos Y Subacu\u00c1ticos: Art\u00cdculos Y Equipo (al Por Menor)",
    "sg:phone":"+34 968 12 37 28",
    "sg:postcode":"30202",
    "sg:province":"Murcia",
    "sg:website":"www.losurrutiascharters.com",
    "wof:name":"Los Urrutias Charters",
    "wof:placetype":"venue"
},
  "geometry": {"coordinates":[-0.985250175,37.5996208191],"type":"Point"}
}