{
  "type": "Feature",
  "properties": {
    "iso:country":"ES",
    "sg:address":"Jose Antonio, 2",
    "sg:city":"Toro",
    "sg:orig_category":"Quincaller\u00cda (al Por Menor)",
    "sg:phone":"+34 980 69 02 66",
    "sg:postcode":"49800",
    "sg:province":"Zamora",
    "wof:name":"Posada Conde Cb",
    "wof:placetype":"venue"
},
  "geometry": {"coordinates":[-5.4017739296,41.5253677368],"type":"Point"}
}