{
  "type": "Feature",
  "properties": {
    "iso:country":"ES",
    "sg:address":"Calle de Isaac Albeniz, 1",
    "sg:city":"Granada",
    "sg:orig_category":"Poller\u00cda Y Caza (al Por Menor)",
    "sg:phone":"+34 958 20 10 27",
    "sg:postcode":"18012",
    "sg:province":"Granada",
    "wof:name":"Villa Fernandez Salvador",
    "wof:placetype":"venue"
},
  "geometry": {"coordinates":[-3.6092689037,37.1868171692],"type":"Point"}
}