{
  "type": "Feature",
  "properties": {
    "iso:country":"ES",
    "sg:address":"Calle de Rioja (de La), 1",
    "sg:city":"Coslada",
    "sg:orig_category":"Tubos Met\u00c1licos",
    "sg:phone":"+34 916 71 37 66",
    "sg:postcode":"28820",
    "sg:province":"Madrid",
    "wof:name":"Industrias Garaeta S.a.",
    "wof:placetype":"venue"
},
  "geometry": {"coordinates":[-3.5507159233,40.4287757874],"type":"Point"}
}