{
  "type": "Feature",
  "properties": {
    "iso:country":"ES",
    "sg:address":"Calle de Pintor Salvador Abril, 11",
    "sg:city":"Valencia",
    "sg:orig_category":"Edici\u00d3n De Diarios, Revistas, Boletines",
    "sg:phone":"+34 963 33 33 09",
    "sg:postcode":"46005",
    "sg:province":"Valencia",
    "sg:website":"www.carenaeditors.es",
    "wof:name":"Carena Editors S.l",
    "wof:placetype":"venue"
},
  "geometry": {"coordinates":[-0.3706249893,39.4636955261],"type":"Point"}
}