{
  "type": "Feature",
  "properties": {
    "addr:full":"Avda Independencia (de La), 22 S. Jose Valle C\u00e1diz 11580",
    "addr:housenumber":"22",
    "addr:postcode":"11580",
    "addr:street":"Avda Independencia De La;S. Jose Valle Ca\u0301Diz",
    "iso:country":"ES",
    "sg:address":"Avda Independencia (de La), 22",
    "sg:city":"S. Jose Valle",
    "sg:orig_category":"Supermercados Y Hipermercados",
    "sg:phone":"+34 956 16 07 85",
    "sg:postcode":"11580",
    "sg:province":"C\u00e1diz",
    "wof:name":"Dinosol Supermercados S.l.",
    "wof:placetype":"venue"
},
  "geometry": {"coordinates":[-5.8015890121,36.6065750122],"type":"Point"}
}