{
  "type": "Feature",
  "properties": {
    "iso:country":"ES",
    "sg:address":"Calle de Castillo De Belmonte, 2",
    "sg:city":"Rozas De Madrid",
    "sg:orig_category":"Peluquer\u00cdas, Peluquer\u00cda Mixta",
    "sg:phone":"+34 916 30 94 46",
    "sg:postcode":"28230",
    "sg:province":"Madrid",
    "wof:name":"Peluquerias Renova S.l.",
    "wof:placetype":"venue"
},
  "geometry": {"coordinates":[-3.8952877522,40.5064277649],"type":"Point"}
}