{
  "type": "Feature",
  "properties": {
    "addr:full":"Calle de San Bernardo (de), 1 Pinto Madrid 28320",
    "addr:postcode":"28320",
    "addr:street":"Calle De San;De;Pinto",
    "iso:country":"ES",
    "sg:address":"Calle de San Bernardo (de), 1",
    "sg:city":"Pinto",
    "sg:orig_category":"Confecci\u00d3n (fabricaci\u00d3n, Al Por Mayor)",
    "sg:phone":"+34 916 92 41 45",
    "sg:postcode":"28320",
    "sg:province":"Madrid",
    "wof:name":"Confecciones Damaho S.l.",
    "wof:placetype":"venue"
},
  "geometry": {"coordinates":[-3.6981959343,40.2465820312],"type":"Point"}
}