{
  "type": "Feature",
  "properties": {
    "addr:full":"Plaz Abad Francisco Navarro, 12 Santillana Cantabria 39330",
    "addr:housenumber":"12",
    "addr:postcode":"39330",
    "addr:street":"Francisco Navarro",
    "iso:country":"ES",
    "sg:address":"Plaz Abad Francisco Navarro, 12",
    "sg:city":"Santillana",
    "sg:orig_category":"Restaurantes",
    "sg:phone":"+34 942 81 83 55",
    "sg:postcode":"39330",
    "sg:province":"Cantabria",
    "wof:name":"Casa Cossio S. Cv.",
    "wof:placetype":"venue"
},
  "geometry": {"coordinates":[-4.1085891724,43.3888092041],"type":"Point"}
}