{
  "type": "Feature",
  "properties": {
    "iso:country":"ES",
    "sg:address":"Calle de Toledo, 69",
    "sg:city":"Madrid",
    "sg:orig_category":"Quincaller\u00cda (al Por Menor)",
    "sg:phone":"+34 913 65 12 37",
    "sg:postcode":"28005",
    "sg:province":"Madrid",
    "sg:website":"www.ferreteriahoyos.com",
    "wof:name":"Ferreteria Hoyos S.l.",
    "wof:placetype":"venue"
},
  "geometry": {"coordinates":[-3.7091639042,40.4101028442],"type":"Point"}
}