{
  "type": "Feature",
  "properties": {
    "iso:country":"ES",
    "sg:address":"Cmno Baden, 217",
    "sg:city":"Torre Salinas",
    "sg:orig_category":"Promotores Constructores",
    "sg:phone":"+34 968 34 32 46",
    "sg:postcode":"30152",
    "sg:province":"Murcia",
    "wof:name":"Lacapin S.l.",
    "wof:placetype":"venue"
},
  "geometry": {"coordinates":[-1.1452490091,37.9643058777],"type":"Point"}
}