{
  "type": "Feature",
  "properties": {
    "addr:full":"Calle de Hernan Perez Del Pulgar, 3 Ciudad Real Ciudad Real 13001",
    "addr:housenumber":"3",
    "addr:postcode":"13001",
    "addr:street":"Calle De Hernan Perez Del Pulgar",
    "iso:country":"ES",
    "sg:address":"Calle de Hernan Perez Del Pulgar, 3",
    "sg:city":"Ciudad Real",
    "sg:orig_category":"Centros De Educaci\u00d3n Especial",
    "sg:phone":"+34 926 25 51 78",
    "sg:postcode":"13001",
    "sg:province":"Ciudad Real",
    "wof:name":"Colegio Publico Perez Molina-comedor",
    "wof:placetype":"venue"
},
  "geometry": {"coordinates":[-3.9278569221,38.9836997986],"type":"Point"}
}