{
  "type": "Feature",
  "properties": {
    "iso:country":"ES",
    "sg:address":"Calle de Casimiro Escrig Montesinos, 20",
    "sg:city":"Redovan",
    "sg:orig_category":"Talleres De Corte Y Confecci\u00d3n",
    "sg:phone":"+34 966 75 53 18",
    "sg:postcode":"03370",
    "sg:province":"Alicante",
    "wof:name":"Creaciones",
    "wof:placetype":"venue"
},
  "geometry": {"coordinates":[-0.911498487,38.1150627136],"type":"Point"}
}