{
  "type": "Feature",
  "properties": {
    "addr:full":"Rua Pe\u00d1a Trevinca, 15 Ourense Ourense 32005",
    "addr:housenumber":"15",
    "addr:postcode":"32005",
    "addr:street":"Rua Pen\u0303A Trevinca",
    "iso:country":"ES",
    "sg:address":"Rua Pe\u00d1a Trevinca, 15",
    "sg:city":"Ourense",
    "sg:orig_category":"Molduras, Junquillos, Listones Y Molduras Perforadas",
    "sg:phone":"+34 988 22 02 35",
    "sg:postcode":"32005",
    "sg:province":"Ourense",
    "wof:name":"Rua Araujo Maria",
    "wof:placetype":"venue"
},
  "geometry": {"coordinates":[-7.8609662056,42.3348274231],"type":"Point"}
}