{
  "type": "Feature",
  "properties": {
    "iso:country":"ES",
    "sg:address":"Plaza Santi Brouard, 3",
    "sg:city":"Galdakao",
    "sg:orig_category":"Institutos De Belleza",
    "sg:phone":"+34 944 57 09 78",
    "sg:postcode":"48960",
    "sg:province":"Vizcaya",
    "wof:name":"Iratxe Echevarria Recalde",
    "wof:placetype":"venue"
},
  "geometry": {"coordinates":[-2.8425729275,43.2299499512],"type":"Point"}
}