{
  "type": "Feature",
  "properties": {
    "iso:country":"ES",
    "sg:address":"Etxeberri Auzoa, 1",
    "sg:city":"Hernani",
    "sg:orig_category":"Alimentaci\u00d3n General (al Por Menor)",
    "sg:phone":"+34 943 55 71 01",
    "sg:postcode":"20120",
    "sg:province":"Guip\u00f9zcoa",
    "wof:name":"Francisco Javier Salaberria Zubeldia",
    "wof:placetype":"venue"
},
  "geometry": {"coordinates":[-1.9658869505,43.2726593018],"type":"Point"}
}