{
  "type": "Feature",
  "properties": {
    "addr:full":"Calle de Oca\u00d1a, 112 Madrid Madrid 28047",
    "addr:housenumber":"112",
    "addr:postcode":"28047",
    "addr:street":"Calle De Ocan\u0303A",
    "iso:country":"ES",
    "sg:address":"Calle de Oca\u00d1a, 112",
    "sg:city":"Madrid",
    "sg:orig_category":"Maquinaria Neum\u00c1tica",
    "sg:phone":"+34 917 19 02 11",
    "sg:postcode":"28047",
    "sg:province":"Madrid",
    "wof:name":"Suministros Industriales Neumaticos S. A.",
    "wof:placetype":"venue"
},
  "geometry": {"coordinates":[-3.7513411045,40.3881034851],"type":"Point"}
}