{
  "type": "Feature",
  "properties": {
    "iso:country":"ES",
    "sg:address":"Ctra Zuazo, S/n",
    "sg:city":"Salvatierra O Agurain",
    "sg:orig_category":"Guarder\u00cdas",
    "sg:phone":"+34 945 30 12 93",
    "sg:postcode":"01200",
    "sg:province":"\u00c1lava",
    "wof:name":"Ayuntamiento De Salvatierra-agurain",
    "wof:placetype":"venue"
},
  "geometry": {"coordinates":[-2.3919839859,42.8527793884],"type":"Point"}
}