{
  "type": "Feature",
  "properties": {
    "addr:full":"Carrer de Oviedo, 23 Sant Vicen\u00c7 Dels Horts Barcelona 08620",
    "addr:housenumber":"23",
    "addr:postcode":"08620",
    "addr:street":"Carrer De Oviedo",
    "iso:country":"ES",
    "sg:address":"Carrer de Oviedo, 23",
    "sg:city":"Sant Vicen\u00c7 Dels Horts",
    "sg:orig_category":"Herramientas Manuales (fabricaci\u00d3n, Al Por Mayor)",
    "sg:phone":"+34 936 56 48 11",
    "sg:postcode":"08620",
    "sg:province":"Barcelona",
    "wof:name":"Afilats Horts S.l.",
    "wof:placetype":"venue"
},
  "geometry": {"coordinates":[1.9993387461,41.3907661438],"type":"Point"}
}