{
  "type": "Feature",
  "properties": {
    "addr:full":"Avda Giorgeta, 20 Valencia Valencia 46007",
    "addr:housenumber":"20",
    "addr:postcode":"46007",
    "addr:street":"Avda Giorgeta",
    "iso:country":"ES",
    "sg:address":"Avda Giorgeta, 20",
    "sg:city":"Valencia",
    "sg:orig_category":"Servicio De Salud",
    "sg:phone":"+34 963 80 69 98",
    "sg:postcode":"46007",
    "sg:province":"Valencia",
    "wof:name":"Saneamientos Orts S. L.",
    "wof:placetype":"venue"
},
  "geometry": {"coordinates":[-0.3852820098,39.460018158],"type":"Point"}
}