{
  "type": "Feature",
  "properties": {
    "iso:country":"ES",
    "sg:address":"Carr Carme, 79",
    "sg:city":"Girona",
    "sg:orig_category":"Agencias Y Asesores De Publicidad",
    "sg:phone":"+34 972 22 36 19",
    "sg:postcode":"17004",
    "sg:province":"Girona",
    "wof:name":"Volcano Comunicacio Grup Sl",
    "wof:placetype":"venue"
},
  "geometry": {"coordinates":[2.8243994713,41.9780807495],"type":"Point"}
}