{
  "type": "Feature",
  "properties": {
    "iso:country":"ES",
    "sg:address":"Carrer de Olzinelles, 25",
    "sg:city":"Barcelona",
    "sg:orig_category":"M\u00c9dicos: Estomatolog\u00cda",
    "sg:phone":"+34 934 21 29 38",
    "sg:postcode":"08014",
    "sg:province":"Barcelona",
    "wof:name":"Alabart Aparici Rosa",
    "wof:placetype":"venue"
},
  "geometry": {"coordinates":[2.1365180016,41.3732681274],"type":"Point"}
}