{
  "type": "Feature",
  "properties": {
    "iso:country":"ES",
    "sg:address":"Eusko Gudarien Kalea, 23",
    "sg:city":"Orio",
    "sg:orig_category":"Pintura Y Barniz (al Por Menor)",
    "sg:phone":"+34 943 83 29 68",
    "sg:postcode":"20810",
    "sg:province":"Guip\u00f9zcoa",
    "wof:name":"Jose Angel Martin Otero",
    "wof:placetype":"venue"
},
  "geometry": {"coordinates":[-2.1276659966,43.2778015137],"type":"Point"}
}