{
  "type": "Feature",
  "properties": {
    "addr:full":"Avda Mar (del), 69 Monteblanco Castell\u00f3n 12200",
    "addr:housenumber":"69",
    "addr:postcode":"12200",
    "addr:street":"Avda Mar Del;Castello\u0301N",
    "iso:country":"ES",
    "sg:address":"Avda Mar (del), 69",
    "sg:city":"Monteblanco",
    "sg:orig_category":"Mec\u00c1nico Del Autom\u00d3vil",
    "sg:phone":"+34 964 77 14 01",
    "sg:postcode":"12200",
    "sg:province":"Castell\u00f3n",
    "wof:name":"Piquer Edo Salvador",
    "wof:placetype":"venue"
},
  "geometry": {"coordinates":[-0.2620640099,39.9651794434],"type":"Point"}
}