{
  "type": "Feature",
  "properties": {
    "iso:country":"ES",
    "sg:address":"Carrer de Sant Sebastia, 293",
    "sg:city":"Sabadell",
    "sg:orig_category":"Rectificaci\u00d3n, Mecanizado, Fresado",
    "sg:phone":"+34 937 11 39 01",
    "sg:postcode":"08203",
    "sg:province":"Barcelona",
    "wof:name":"Mecanizados Navas S.l.",
    "wof:placetype":"venue"
},
  "geometry": {"coordinates":[2.1047298908,41.5336074829],"type":"Point"}
}