{
  "type": "Feature",
  "properties": {
    "iso:country":"ES",
    "sg:address":"Carrer de Ramon Das Neves (de), 53",
    "sg:city":"S. Carles Rapita",
    "sg:orig_category":"Fabricaci\u00d3n De Distribuidores Autom\u00c1ticos",
    "sg:phone":"+34 977 74 12 18",
    "sg:postcode":"43540",
    "sg:province":"Tarragona",
    "wof:name":"Maquinas Automaticas Navarro S.l.",
    "wof:placetype":"venue"
},
  "geometry": {"coordinates":[0.5883899927,40.6146697998],"type":"Point"}
}