{
  "type": "Feature",
  "properties": {
    "addr:full":"Calle de Antonio Machado, 6 Hornachuelos C\u00f3rdoba 14740",
    "addr:housenumber":"6",
    "addr:postcode":"14740",
    "addr:street":"Calle De Antonio Machado",
    "iso:country":"ES",
    "sg:address":"Calle de Antonio Machado, 6",
    "sg:city":"Hornachuelos",
    "sg:orig_category":"Cooperativas Agr\u00cdcolas",
    "sg:phone":"+34 957 64 07 12",
    "sg:postcode":"14740",
    "sg:province":"C\u00f3rdoba",
    "wof:name":"Union De Agricultores Y Ganaderos De Cordoba",
    "wof:placetype":"venue"
},
  "geometry": {"coordinates":[-5.2419261932,37.8307189941],"type":"Point"}
}