{
  "type": "Feature",
  "properties": {
    "addr:full":"Calle de Quintana, 9 Madrid Madrid 28008",
    "addr:housenumber":"9",
    "addr:postcode":"madrid;28008",
    "addr:street":"Calle De Quintana",
    "iso:country":"ES",
    "sg:address":"Calle de Quintana, 9",
    "sg:city":"Madrid",
    "sg:orig_category":"Centros De Coordinaci\u00d3n",
    "sg:phone":"+34 915 59 09 69",
    "sg:postcode":"28008",
    "sg:province":"Madrid",
    "sg:website":"www.darco-spym.com",
    "wof:name":"Darco Spym S.l.",
    "wof:placetype":"venue"
},
  "geometry": {"coordinates":[-3.7169079781,40.4279403687],"type":"Point"}
}