{
  "type": "Feature",
  "properties": {
    "addr:full":"Don Carlos Sanchez La Fuente, 21 Archidona M\u00e1laga 29300",
    "addr:housenumber":"21",
    "addr:postcode":"29300",
    "addr:street":"La Fuente;Ma\u0301Laga",
    "iso:country":"ES",
    "sg:address":"Don Carlos Sanchez La Fuente, 21",
    "sg:city":"Archidona",
    "sg:orig_category":"Iglesia Cat\u00d3lica",
    "sg:phone":"+34 952 71 40 82",
    "sg:postcode":"29300",
    "sg:province":"M\u00e1laga",
    "wof:name":"Obispado De Malaga",
    "wof:placetype":"venue"
},
  "geometry": {"coordinates":[-4.3896942139,37.096660614],"type":"Point"}
}