{
  "type": "Feature",
  "properties": {
    "iso:country":"ES",
    "sg:address":"Calle de San Jose, 15",
    "sg:city":"Laspu\u00d1a",
    "sg:classifiers":[
        {
            "category":"Taxi",
            "type":"Transportation"
        }
    ],
    "sg:phone":"+34 974 50 50 79",
    "sg:postcode":"22361",
    "sg:province":"Huesca",
    "wof:name":"Lavilla Ceresuela Francisco",
    "wof:placetype":"venue"
},
  "geometry": {"coordinates":[0.1538629979,42.5032196045],"type":"Point"}
}