{
  "type": "Feature",
  "properties": {
    "iso:country":"ES",
    "sg:address":"Cami Camp De S'oca, De, 15",
    "sg:city":"Soller",
    "sg:orig_category":"Inmobiliaria (agencias)",
    "sg:phone":"+34 971 63 43 56",
    "sg:postcode":"07100",
    "sg:province":"Islas Baleares",
    "wof:name":"Finques Cabot S.l.",
    "wof:placetype":"venue"
},
  "geometry": {"coordinates":[2.6990559101,39.8055992126],"type":"Point"}
}