{
  "type": "Feature",
  "properties": {
    "addr:full":"Calle de Fernando German, S/n Valmojado Toledo 45940",
    "addr:housenumber":"s / n",
    "addr:postcode":"45940",
    "addr:street":"Calle De Fernando German",
    "iso:country":"ES",
    "sg:address":"Calle de Fernando German, S/n",
    "sg:city":"Valmojado",
    "sg:orig_category":"Farmacias",
    "sg:phone":"+34 918 17 00 79",
    "sg:postcode":"45940",
    "sg:province":"Toledo",
    "wof:name":"Moya Moya Enriqueta",
    "wof:placetype":"venue"
},
  "geometry": {"coordinates":[-4.0887641907,40.2048835754],"type":"Point"}
}