{
  "type": "Feature",
  "properties": {
    "iso:country":"ES",
    "sg:address":"Calle de Pintor Reinoso, S/n",
    "sg:city":"Cordoba",
    "sg:orig_category":"Polideportivos",
    "sg:phone":"+34 957 27 75 31",
    "sg:postcode":"14006",
    "sg:province":"C\u00f3rdoba",
    "wof:name":"Instituto Municipal De Deportes De Cordoba",
    "wof:placetype":"venue"
},
  "geometry": {"coordinates":[-4.7757339478,37.8962516785],"type":"Point"}
}