{
  "type": "Feature",
  "properties": {
    "iso:country":"ES",
    "sg:address":"Carrer de L'aviador Ruiz De Alda, 21",
    "sg:city":"Barcelona",
    "sg:orig_category":"Grabados Y Decoraci\u00d3n De Metales",
    "sg:phone":"+34 933 32 45 98",
    "sg:postcode":"08038",
    "sg:province":"Barcelona",
    "wof:name":"Mayor Mengual Santiago",
    "wof:placetype":"venue"
},
  "geometry": {"coordinates":[2.141566515,41.3601837158],"type":"Point"}
}