{
  "type": "Feature",
  "properties": {
    "addr:full":"Calle de Reyes Catolicos, 48 Alacant Alicante 03003",
    "addr:housenumber":"48",
    "addr:postcode":"03003",
    "addr:street":"Calle De Reyes Catolicos",
    "iso:country":"ES",
    "sg:address":"Calle de Reyes Catolicos, 48",
    "sg:city":"Alacant",
    "sg:orig_category":"Agencias De Trabajo Temporal",
    "sg:phone":"+34 965 92 77 05",
    "sg:postcode":"03003",
    "sg:province":"Alicante",
    "sg:website":"www.adecco.es",
    "wof:name":"Adecco E.t.t. S.a.",
    "wof:placetype":"venue"
},
  "geometry": {"coordinates":[-0.493313998,38.3411178589],"type":"Point"}
}