{
  "type": "Feature",
  "properties": {
    "addr:full":"Calle de Narciso Serra, 12 Madrid Madrid 28007",
    "addr:housenumber":"12",
    "addr:postcode":"madrid;28007",
    "addr:street":"Calle De Narciso Serra",
    "iso:country":"ES",
    "sg:address":"Calle de Narciso Serra, 12",
    "sg:city":"Madrid",
    "sg:orig_category":"Radiocomunicaciones, Telefon\u00cda M\u00d3vil, Radiomensajer\u00cda: Servicios, Comercializaci\u00d3n",
    "sg:phone":"+34 915 52 91 92",
    "sg:postcode":"28007",
    "sg:province":"Madrid",
    "wof:name":"Peguero Agramor Louis",
    "wof:placetype":"venue"
},
  "geometry": {"coordinates":[-3.6787030697,40.4049186707],"type":"Point"}
}