{
  "type": "Feature",
  "properties": {
    "iso:country":"ES",
    "sg:address":"Carrer de Ganduxer, 109",
    "sg:city":"Barcelona",
    "sg:orig_category":"Inform\u00c1tica: Material Y Suministros",
    "sg:phone":"+34 932 11 74 86",
    "sg:postcode":"08022",
    "sg:province":"Barcelona",
    "sg:website":"www.chems.net",
    "wof:name":"Chems S.l.",
    "wof:placetype":"venue"
},
  "geometry": {"coordinates":[2.1310698986,41.403339386],"type":"Point"}
}