{
  "type": "Feature",
  "properties": {
    "iso:country":"ES",
    "sg:address":"Curras, 24",
    "sg:city":"Ponte Do Porto",
    "sg:orig_category":"Prot\u00c9sicos Dentales",
    "sg:phone":"+34 981 73 00 25",
    "sg:postcode":"15122",
    "sg:province":"La Coru\u00f1a",
    "wof:name":"Rodriguez Romero Ramon",
    "wof:placetype":"venue"
},
  "geometry": {"coordinates":[-9.1458740234,43.161190033],"type":"Point"}
}