{
  "type": "Feature",
  "properties": {
    "iso:country":"ES",
    "sg:address":"Calle de Hernan Cortes, 37",
    "sg:city":"Zaragoza",
    "sg:orig_category":"Edici\u00d3n De Diarios, Revistas, Boletines",
    "sg:phone":"+34 976 70 04 00",
    "sg:postcode":"50...",
    "sg:province":"Zaragoza",
    "sg:website":"www.elperiodico.es/aragon",
    "wof:name":"Prensa Diaria Aragonesa S.a.",
    "wof:placetype":"venue"
},
  "geometry": {"coordinates":[-0.8903189898,41.6479797363],"type":"Point"}
}