{
  "type": "Feature",
  "properties": {
    "addr:full":"Calle de Lopez De Hoces, 39 Playa De Arinaga Las Palmas 35118",
    "addr:housenumber":"39",
    "addr:postcode":"35118",
    "addr:street":"Calle De Lopez De Hoces",
    "iso:country":"ES",
    "sg:address":"Calle de Lopez De Hoces, 39",
    "sg:city":"Playa De Arinaga",
    "sg:orig_category":"Asilos De Ancianos. Centros Privados",
    "sg:phone":"+34 928 18 81 25",
    "sg:postcode":"35118",
    "sg:province":"Las Palmas",
    "wof:name":"Ayuntamiento De Aguimes",
    "wof:placetype":"venue"
},
  "geometry": {"coordinates":[-15.3927698135,27.8557987213],"type":"Point"}
}