{
  "type": "Feature",
  "properties": {
    "addr:full":"Calle de Doctor Juan Dominguez Perez, 44 Palmas De Gran Canaria Las Palmas 35008",
    "addr:postcode":"35008",
    "addr:street":"Calle De Doctor Juan Dominguez Perez 44",
    "iso:country":"ES",
    "sg:address":"Calle de Doctor Juan Dominguez Perez, 44",
    "sg:city":"Palmas De Gran Canaria",
    "sg:orig_category":"Fabricaci\u00d3n, Reparaci\u00d3n Y Mantenimiento De Construcciones Navales Y Fluviales",
    "sg:phone":"+34 928 46 52 91",
    "sg:postcode":"35008",
    "sg:province":"Las Palmas",
    "wof:name":"Yoshioka Canarias S.l.",
    "wof:placetype":"venue"
},
  "geometry": {"coordinates":[-15.4097490311,28.1620559692],"type":"Point"}
}