{
  "type": "Feature",
  "properties": {
    "addr:full":"Calle de Jose Maria Del Boto, 10 Madrid Madrid 28011",
    "addr:housenumber":"10",
    "addr:postcode":"madrid;28011",
    "addr:street":"Calle De Jose Maria Del Boto",
    "iso:country":"ES",
    "sg:address":"Calle de Jose Maria Del Boto, 10",
    "sg:city":"Madrid",
    "sg:orig_category":"Grabados Y Decoraci\u00d3n De Metales",
    "sg:phone":"+34 914 79 99 08",
    "sg:postcode":"28011",
    "sg:province":"Madrid",
    "wof:name":"Fernandez Justicia Antonio",
    "wof:placetype":"venue"
},
  "geometry": {"coordinates":[-3.7379128933,40.404838562],"type":"Point"}
}