{
  "type": "Feature",
  "properties": {
    "addr:full":"Calle de Iturribide, 65 Bilbao Vizcaya 48006",
    "addr:housenumber":"65",
    "addr:postcode":"48006",
    "addr:street":"Calle De Iturribide",
    "iso:country":"ES",
    "sg:address":"Calle de Iturribide, 65",
    "sg:city":"Bilbao",
    "sg:orig_category":"Asesor\u00cdas Y Estudios Financieros",
    "sg:phone":"+34 944 33 38 66",
    "sg:postcode":"48006",
    "sg:province":"Vizcaya",
    "wof:name":"Lorda De Los Rios S.l.",
    "wof:placetype":"venue"
},
  "geometry": {"coordinates":[-2.9157099724,43.2563514709],"type":"Point"}
}