{
  "type": "Feature",
  "properties": {
    "addr:full":"Urb. Guadalmina Alta, 39 San Pedro Alcantara M\u00e1laga 29670",
    "addr:housenumber":"39",
    "addr:postcode":"29670",
    "addr:street":"Guadalmina Alta",
    "iso:country":"ES",
    "sg:address":"Urb. Guadalmina Alta, 39",
    "sg:city":"San Pedro Alcantara",
    "sg:orig_category":"Ingenier\u00cda, Centros De Estudios (diversos)",
    "sg:phone":"+34 952 88 81 99",
    "sg:postcode":"29670",
    "sg:province":"M\u00e1laga",
    "wof:name":"Gonzalez Perez-yarza Jose Miguel",
    "wof:placetype":"venue"
},
  "geometry": {"coordinates":[-4.9894766808,36.4856033325],"type":"Point"}
}