{
  "type": "Feature",
  "properties": {
    "iso:country":"ES",
    "sg:address":"Calle de Fernandez De La Hoz, 70",
    "sg:city":"Madrid",
    "sg:orig_category":"Asesor\u00cdas Y Estudios Financieros",
    "sg:phone":"+34 914 41 81 27",
    "sg:postcode":"28003",
    "sg:province":"Madrid",
    "wof:name":"Cobo Casas Pilar",
    "wof:placetype":"venue"
},
  "geometry": {"coordinates":[-3.6943519115,40.4383773804],"type":"Point"}
}