{
  "type": "Feature",
  "properties": {
    "iso:country":"ES",
    "sg:address":"Av Canal, 142",
    "sg:city":"Prat Llobregat",
    "sg:orig_category":"Perfumer\u00cda (al Por Menor)",
    "sg:phone":"+34 933 79 18 14",
    "sg:postcode":"08820",
    "sg:province":"Barcelona",
    "wof:name":"Gonzalez Espada Josefina",
    "wof:placetype":"venue"
},
  "geometry": {"coordinates":[2.0921430588,41.3254089355],"type":"Point"}
}