{
  "type": "Feature",
  "properties": {
    "iso:country":"ES",
    "sg:address":"Plaz Eulogio Carrasco (de), S/n",
    "sg:city":"Colmenar Viejo",
    "sg:orig_category":"Pescader\u00cdas (al Por Menor)",
    "sg:phone":"+34 918 46 36 00",
    "sg:postcode":"28770",
    "sg:province":"Madrid",
    "wof:name":"Martinez Espinosa Marcelino",
    "wof:placetype":"venue"
},
  "geometry": {"coordinates":[-3.7679769993,40.6587867737],"type":"Point"}
}