{
  "type": "Feature",
  "properties": {
    "addr:full":"Trva Porto (do), 5 Burela Lugo 27880",
    "addr:housenumber":"5",
    "addr:postcode":"27880",
    "addr:street":"Trva Porto Do",
    "iso:country":"ES",
    "sg:address":"Trva Porto (do), 5",
    "sg:city":"Burela",
    "sg:orig_category":"Caf\u00c9s, Bares, Cervecer\u00cdas",
    "sg:phone":"+34 982 58 07 13",
    "sg:postcode":"27880",
    "sg:province":"Lugo",
    "wof:name":"Velasco Ya\u00f1ez Esperanza",
    "wof:placetype":"venue"
},
  "geometry": {"coordinates":[-7.355907917,43.6621284485],"type":"Point"}
}