{
  "type": "Feature",
  "properties": {
    "addr:full":"Carrer de Joan Fuster, 3 Crevillent Alicante 03330",
    "addr:housenumber":"3",
    "addr:postcode":"03330",
    "addr:street":"Carrer De Joan Fuster",
    "iso:country":"ES",
    "sg:address":"Carrer de Joan Fuster, 3",
    "sg:city":"Crevillent",
    "sg:orig_category":"Arquitectos",
    "sg:phone":"+34 965 40 54 30",
    "sg:postcode":"03330",
    "sg:province":"Alicante",
    "wof:name":"Brotons Arquitectos S.l.",
    "wof:placetype":"venue"
},
  "geometry": {"coordinates":[-0.8055920005,38.2496070862],"type":"Point"}
}