{
  "type": "Feature",
  "properties": {
    "addr:full":"Pg Maragall, 311 Barcelona Barcelona 08032",
    "addr:housenumber":"311",
    "addr:postcode":"08032",
    "addr:street":"Pg Maragall",
    "iso:country":"ES",
    "sg:address":"Pg Maragall, 311",
    "sg:city":"Barcelona",
    "sg:orig_category":"Empresarios",
    "sg:phone":"+34 934 29 62 22",
    "sg:postcode":"08032",
    "sg:province":"Barcelona",
    "wof:name":"Trabal Cullell Gines",
    "wof:placetype":"venue"
},
  "geometry": {"coordinates":[2.1698288918,41.4270858765],"type":"Point"}
}