{
  "type": "Feature",
  "properties": {
    "iso:country":"ES",
    "sg:address":"Ctra. Malaga, S/n",
    "sg:city":"Chauchina",
    "sg:orig_category":"Garajes De Veh\u00cdculos",
    "sg:phone":"+34 958 44 60 75",
    "sg:postcode":"18330",
    "sg:province":"Granada",
    "wof:name":"Talleres Fernandez Y Ure\u00f1a",
    "wof:placetype":"venue"
},
  "geometry": {"coordinates":[-3.7719919682,37.2014541626],"type":"Point"}
}