{
  "type": "Feature",
  "properties": {
    "iso:country":"ES",
    "sg:address":"Calle de Iglesia, 4",
    "sg:city":"Irun",
    "sg:orig_category":"Carnicer\u00cdas, Carnicer\u00cdas",
    "sg:phone":"+34 943 62 07 86",
    "sg:postcode":"20302",
    "sg:province":"Guip\u00f9zcoa",
    "wof:name":"Urgain S. A.",
    "wof:placetype":"venue"
},
  "geometry": {"coordinates":[-1.7896989584,43.3428001404],"type":"Point"}
}