{
  "type": "Feature",
  "properties": {
    "iso:country":"ES",
    "sg:address":"Calle de San Felipe, 7",
    "sg:city":"Torrejon Ardoz",
    "sg:orig_category":"Inmobiliaria (agencias)",
    "sg:phone":"+34 916 77 50 32",
    "sg:postcode":"28850",
    "sg:province":"Madrid",
    "wof:name":"Garcia Hernandez Miguel Angel",
    "wof:placetype":"venue"
},
  "geometry": {"coordinates":[-3.4780249596,40.457157135],"type":"Point"}
}