{
  "type": "Feature",
  "properties": {
    "addr:full":"Calle de Virgen De Regla, 18 Sevilla Sevilla 41011",
    "addr:housenumber":"18",
    "addr:postcode":"41011",
    "addr:street":"Calle De Virgen De Regla",
    "iso:country":"ES",
    "sg:address":"Calle de Virgen De Regla, 18",
    "sg:city":"Sevilla",
    "sg:orig_category":"Ropa Para Beb\u00c9s Y Ni\u00d1os (confecci\u00d3n, Al Por Mayor)",
    "sg:phone":"+34 954 27 26 86",
    "sg:postcode":"41011",
    "sg:province":"Sevilla",
    "wof:name":"Alvarez Marin Rocio",
    "wof:placetype":"venue"
},
  "geometry": {"coordinates":[-5.9985671043,37.3776054382],"type":"Point"}
}