{
  "type": "Feature",
  "properties": {
    "addr:full":"Carr Can Mas, 28 Pla De Na Tesa Islas Baleares 07009",
    "addr:housenumber":"28",
    "addr:postcode":"07009",
    "addr:street":"Carr Can Mas;Islas",
    "iso:country":"ES",
    "sg:address":"Carr Can Mas, 28",
    "sg:city":"Pla De Na Tesa",
    "sg:orig_category":"Empresas De Carpinter\u00cda De Madera",
    "sg:phone":"+34 971 60 10 37",
    "sg:postcode":"07009",
    "sg:province":"Islas Baleares",
    "wof:name":"Mas Matas Juan",
    "wof:placetype":"venue"
},
  "geometry": {"coordinates":[2.6776249409,39.6072845459],"type":"Point"}
}