{
  "type": "Feature",
  "properties": {
    "addr:full":"Ctra. Nacional 340, Km. 0133,0 Benicarlo Castell\u00f3n 12580",
    "addr:postcode":"12580",
    "addr:street":"Ctra. Nacional 340 Km. 0133,0;Castello\u0301N",
    "iso:country":"ES",
    "sg:address":"Ctra. Nacional 340, Km. 0133,0",
    "sg:city":"Benicarlo",
    "sg:orig_category":"Art\u00cdculos De Regalo (al Por Menor)",
    "sg:phone":"+34 964 46 14 28",
    "sg:postcode":"12580",
    "sg:province":"Castell\u00f3n",
    "sg:website":"www.naturaselection.com",
    "wof:name":"Jejava S.l.",
    "wof:placetype":"venue"
},
  "geometry": {"coordinates":[0.4042100012,40.4457893372],"type":"Point"}
}