{
  "type": "Feature",
  "properties": {
    "addr:full":"Calle de Sierra Ventosa, 66 Guijuelo Salamanca 37770",
    "addr:housenumber":"66",
    "addr:postcode":"37770",
    "addr:street":"Calle De Sierra Ventosa",
    "iso:country":"ES",
    "sg:address":"Calle de Sierra Ventosa, 66",
    "sg:city":"Guijuelo",
    "sg:orig_category":"Carnicer\u00cdas, Carnicer\u00cdas",
    "sg:phone":"+34 923 58 09 91",
    "sg:postcode":"37770",
    "sg:province":"Salamanca",
    "wof:name":"Almacenes Garimari S.l.",
    "wof:placetype":"venue"
},
  "geometry": {"coordinates":[-5.6796226501,40.5382003784],"type":"Point"}
}