{
  "type": "Feature",
  "properties": {
    "addr:full":"Plaz Constitucion, 2 Teulada Alicante 03725",
    "addr:housenumber":"2",
    "addr:postcode":"03725",
    "addr:street":"Constitucion",
    "iso:country":"ES",
    "sg:address":"Plaz Constitucion, 2",
    "sg:city":"Teulada",
    "sg:orig_category":"Asesor\u00cda Fiscal Y Jur\u00cddica",
    "sg:phone":"+34 965 74 15 02",
    "sg:postcode":"03725",
    "sg:province":"Alicante",
    "wof:name":"Malonda Miralles Monica",
    "wof:placetype":"venue"
},
  "geometry": {"coordinates":[0.1040079966,38.7290039062],"type":"Point"}
}