{
  "type": "Feature",
  "properties": {
    "addr:full":"Carrer de Orient, 18 S. Cugat Valles Barcelona 08172",
    "addr:housenumber":"18",
    "addr:postcode":"08172",
    "addr:street":"Carrer De Orient;S. Cugat Valles Barcelona",
    "iso:country":"ES",
    "sg:address":"Carrer de Orient, 18",
    "sg:city":"S. Cugat Valles",
    "sg:orig_category":"Carnicer\u00cdas, Carnicer\u00cdas",
    "sg:phone":"+34 936 74 32 70",
    "sg:postcode":"08172",
    "sg:province":"Barcelona",
    "wof:name":"Vila Sanchez Miquel",
    "wof:placetype":"venue"
},
  "geometry": {"coordinates":[2.0873188972,41.4743766785],"type":"Point"}
}