{
  "type": "Feature",
  "properties": {
    "addr:full":"Calle de Mayor, 104 Fuente-alamo Albacete 02651",
    "addr:housenumber":"104",
    "addr:postcode":"02651",
    "addr:street":"Calle De Mayor",
    "iso:country":"ES",
    "sg:address":"Calle de Mayor, 104",
    "sg:city":"Fuente-alamo",
    "sg:orig_category":"Empresas De Carpinter\u00cda De Madera",
    "sg:phone":"+34 967 32 10 51",
    "sg:postcode":"02651",
    "sg:province":"Albacete",
    "wof:name":"Garcia Del Hoyo Crescencio",
    "wof:placetype":"venue"
},
  "geometry": {"coordinates":[-1.4334670305,38.6943397522],"type":"Point"}
}