{
  "type": "Feature",
  "properties": {
    "addr:full":"Calle de Alinos, S/n Toreno Le\u00f3n 24450",
    "addr:housenumber":"s / n",
    "addr:postcode":"24450",
    "addr:street":"Calle De Alinos",
    "iso:country":"ES",
    "sg:address":"Calle de Alinos, S/n",
    "sg:city":"Toreno",
    "sg:orig_category":"Explotaci\u00d3n De Minas",
    "sg:phone":"+34 987 52 79 00",
    "sg:postcode":"24450",
    "sg:province":"Le\u00f3n",
    "wof:name":"Union Minera Del Norte S.a.",
    "wof:placetype":"venue"
},
  "geometry": {"coordinates":[-6.5149440765,42.6970710754],"type":"Point"}
}