{
  "type": "Feature",
  "properties": {
    "addr:full":"Pase Canalejas, 100 Salamanca Salamanca 37001",
    "addr:housenumber":"100",
    "addr:postcode":"37001",
    "addr:street":"Canalejas",
    "iso:country":"ES",
    "sg:address":"Pase Canalejas, 100",
    "sg:city":"Salamanca",
    "sg:orig_category":"Panader\u00cdas, Panader\u00cdas",
    "sg:phone":"+34 923 26 99 97",
    "sg:postcode":"37001",
    "sg:province":"Salamanca",
    "wof:name":"Argelfe S.l",
    "wof:placetype":"venue"
},
  "geometry": {"coordinates":[-5.6584982872,40.9637413025],"type":"Point"}
}