{
  "type": "Feature",
  "properties": {
    "iso:country":"ES",
    "sg:address":"Calle de Juan Cabrero, 20",
    "sg:city":"Zaragoza",
    "sg:orig_category":"Electrodom\u00c9sticos (al Por Menor)",
    "sg:phone":"+34 976 37 07 01",
    "sg:postcode":"50007",
    "sg:province":"Zaragoza",
    "wof:name":"Servicio Tecnico Lara S.l.",
    "wof:placetype":"venue"
},
  "geometry": {"coordinates":[-0.8847200274,41.6297874451],"type":"Point"}
}