{
  "type": "Feature",
  "properties": {
    "iso:country":"ES",
    "sg:address":"Calle de Sabio, 38",
    "sg:city":"Higuera Real",
    "sg:orig_category":"Molduras, Junquillos, Listones Y Molduras Perforadas",
    "sg:phone":"+34 924 72 37 12",
    "sg:postcode":"06350",
    "sg:province":"Badajoz",
    "wof:name":"Sanchez Vargas Catalina",
    "wof:placetype":"venue"
},
  "geometry": {"coordinates":[-6.6923351288,38.1417617798],"type":"Point"}
}