{
  "type": "Feature",
  "properties": {
    "addr:full":"Calle de Feijoo, 81 Gijon Asturias 33204",
    "addr:housenumber":"81",
    "addr:postcode":"33204",
    "addr:street":"Calle De Feijoo",
    "iso:country":"ES",
    "sg:address":"Calle de Feijoo, 81",
    "sg:city":"Gijon",
    "sg:orig_category":"Negocio De Materiales De Construcci\u00d3n",
    "sg:phone":"+34 985 13 43 05",
    "sg:postcode":"33204",
    "sg:province":"Asturias",
    "wof:name":"Turbodisk S.l.",
    "wof:placetype":"venue"
},
  "geometry": {"coordinates":[-5.6471438408,43.5318107605],"type":"Point"}
}