{
  "type": "Feature",
  "properties": {
    "iso:country":"ES",
    "sg:address":"Calle de San Pedro, 2",
    "sg:city":"Albocasser",
    "sg:orig_category":"Pr\u00c9stamos Personales E Hipotecarios",
    "sg:phone":"+34 964 42 81 51",
    "sg:postcode":"12140",
    "sg:province":"Castell\u00f3n",
    "wof:name":"Martinez Ruiz Cristina",
    "wof:placetype":"venue"
},
  "geometry": {"coordinates":[0.0257799998,40.3567008972],"type":"Point"}
}