{
  "type": "Feature",
  "properties": {
    "iso:country":"ES",
    "sg:address":"Avda Cardenal Costa, 19",
    "sg:city":"Castellon",
    "sg:orig_category":"Fabrica De Cer\u00c1micas",
    "sg:phone":"+34 964 24 39 96",
    "sg:postcode":"12004",
    "sg:province":"Castell\u00f3n",
    "wof:name":"Talleres Agost Sanchez S.l.",
    "wof:placetype":"venue"
},
  "geometry": {"coordinates":[-0.0472330004,39.9904327393],"type":"Point"}
}