{
  "type": "Feature",
  "properties": {
    "addr:full":"Carrer de Flandes, 8 Barcelona Barcelona 08018",
    "addr:housenumber":"8",
    "addr:postcode":"08018",
    "addr:street":"Carrer De Flandes",
    "iso:country":"ES",
    "sg:address":"Carrer de Flandes, 8",
    "sg:city":"Barcelona",
    "sg:orig_category":"Mec\u00c1nico Del Autom\u00d3vil",
    "sg:phone":"+34 932 46 46 97",
    "sg:postcode":"08018",
    "sg:province":"Barcelona",
    "wof:name":"Rodriguez Rodriguez Abelardo",
    "wof:placetype":"venue"
},
  "geometry": {"coordinates":[2.1889929771,41.4083595276],"type":"Point"}
}