{
  "type": "Feature",
  "properties": {
    "iso:country":"ES",
    "sg:address":"Calle de Senda De Los Ingleses, 5",
    "sg:city":"Laguna Duero",
    "sg:orig_category":"Promotores Constructores",
    "sg:phone":"+34 983 54 44 70",
    "sg:postcode":"47140",
    "sg:province":"Valladolid",
    "wof:name":"Quintanilla Caba\u00f1as Mariano",
    "wof:placetype":"venue"
},
  "geometry": {"coordinates":[-4.7260289192,41.5838012695],"type":"Point"}
}