{
  "type": "Feature",
  "properties": {
    "iso:country":"ES",
    "sg:address":"Pla\u00c7 Farners, 1",
    "sg:city":"Santa Coloma De Farners",
    "sg:orig_category":"Carnicer\u00cdas, Carnicer\u00cdas",
    "sg:phone":"+34 972 84 06 25",
    "sg:postcode":"17430",
    "sg:province":"Girona",
    "wof:name":"Negre Geli Maria",
    "wof:placetype":"venue"
},
  "geometry": {"coordinates":[2.6624910831,41.8634605408],"type":"Point"}
}