{
  "type": "Feature",
  "properties": {
    "iso:country":"ES",
    "sg:address":"Calle de Nicolas Lopez De Velasco, 13",
    "sg:city":"Badajoz",
    "sg:orig_category":"Peluqueros: De Se\u00d1oras",
    "sg:phone":"+34 924 23 19 21",
    "sg:postcode":"06004",
    "sg:province":"Badajoz",
    "wof:name":"Rangel Rangel Fructuosa",
    "wof:placetype":"venue"
},
  "geometry": {"coordinates":[-6.9761276245,38.8697471619],"type":"Point"}
}