{
  "type": "Feature",
  "properties": {
    "iso:country":"ES",
    "sg:address":"Ctra. General, S/n",
    "sg:city":"Cadavedo",
    "sg:orig_category":"Cerrajer\u00cda, Ferrallista",
    "sg:phone":"+34 985 64 50 16",
    "sg:postcode":"33788",
    "sg:province":"Asturias",
    "wof:name":"Maderas Garcia Hermanos S. L.",
    "wof:placetype":"venue"
},
  "geometry": {"coordinates":[-6.3870611191,43.5456581116],"type":"Point"}
}