{
  "type": "Feature",
  "properties": {
    "iso:country":"ES",
    "sg:address":"Calle de Balendin Berrio-otxoa, 49",
    "sg:city":"Elorrio",
    "sg:orig_category":"Asesor\u00cda Sobre Comunicaci\u00d3n De Empresas",
    "sg:phone":"+34 946 58 25 02",
    "sg:postcode":"48230",
    "sg:province":"Vizcaya",
    "wof:name":"Inforlan S.coop.",
    "wof:placetype":"venue"
},
  "geometry": {"coordinates":[-2.5296971798,43.1177749634],"type":"Point"}
}