{
  "type": "Feature",
  "properties": {
    "addr:full":"Partida De Hazas, S/n Cella Teruel 44370",
    "addr:housenumber":"s",
    "addr:postcode":"44370",
    "addr:street":"Partida;Hazas;/ N",
    "iso:country":"ES",
    "sg:address":"Partida De Hazas, S/n",
    "sg:city":"Cella",
    "sg:orig_category":"Aguas (distribuci\u00d3n, Servicios)",
    "sg:phone":"+34 978 65 30 23",
    "sg:postcode":"44370",
    "sg:province":"Teruel",
    "wof:name":"Oms Sacede S. A.",
    "wof:placetype":"venue"
},
  "geometry": {"coordinates":[-1.2815389633,40.4547424316],"type":"Point"}
}