{
  "type": "Feature",
  "properties": {
    "addr:full":"Carrer de Metge Juan Bellot, 16 Monovar Alicante 03640",
    "addr:housenumber":"16",
    "addr:postcode":"03640",
    "addr:street":"Carrer De Metge Juan Bellot;Alicante",
    "iso:country":"ES",
    "sg:address":"Carrer de Metge Juan Bellot, 16",
    "sg:city":"Monovar",
    "sg:orig_category":"Audiovisuales (producci\u00d3n, Edici\u00d3n, Realizaci\u00d3n)",
    "sg:phone":"+34 965 47 32 16",
    "sg:postcode":"03640",
    "sg:province":"Alicante",
    "sg:website":"www.digitalgrup.net",
    "wof:name":"Martinez Maestre Juan Ramon",
    "wof:placetype":"venue"
},
  "geometry": {"coordinates":[-0.8426150084,38.4366378784],"type":"Point"}
}