{
  "type": "Feature",
  "properties": {
    "addr:full":"Calle de Virgen De Los Milagros, 71 Puerto De Santa Maria C\u00e1diz 11500",
    "addr:housenumber":"71",
    "addr:postcode":"11500",
    "addr:street":"Calle De Virgen De Los Milagros;Ca\u0301Diz",
    "iso:country":"ES",
    "sg:address":"Calle de Virgen De Los Milagros, 71",
    "sg:city":"Puerto De Santa Maria",
    "sg:orig_category":"Cajas De Ahorro",
    "sg:phone":"+34 956 86 01 60",
    "sg:postcode":"11500",
    "sg:province":"C\u00e1diz",
    "wof:name":"Monte De Piedad Y Caja De Ahorros De Huelva Y Sevilla",
    "wof:placetype":"venue"
},
  "geometry": {"coordinates":[-6.2197542191,36.6056632996],"type":"Point"}
}