{
  "type": "Feature",
  "properties": {
    "iso:country":"ES",
    "sg:address":"Carr Preciosissima Sang, 19",
    "sg:city":"Picanya",
    "sg:orig_category":"Perfumer\u00cda (al Por Menor)",
    "sg:phone":"+34 961 59 08 26",
    "sg:postcode":"46210",
    "sg:province":"Valencia",
    "wof:name":"Baviera Barbera Carmen",
    "wof:placetype":"venue"
},
  "geometry": {"coordinates":[-0.4349240065,39.4362945557],"type":"Point"}
}