{
  "type": "Feature",
  "properties": {
    "iso:country":"ES",
    "sg:address":"Calle de Diego Vega Sarmiento, 25",
    "sg:city":"Palmas De Gran Canaria",
    "sg:orig_category":"Empresas De Carpinter\u00cda De Madera",
    "sg:phone":"+34 928 41 88 87",
    "sg:postcode":"35014",
    "sg:province":"Las Palmas",
    "wof:name":"Industrias De Carpinteria Espino Y Cabrera S. L.",
    "wof:placetype":"venue"
},
  "geometry": {"coordinates":[-15.4395494461,28.0997924805],"type":"Point"}
}