{
  "type": "Feature",
  "properties": {
    "addr:full":"Calle de Mayor, 166 Raal Murcia 30139",
    "addr:housenumber":"166",
    "addr:postcode":"30139",
    "addr:street":"Calle De Mayor",
    "iso:country":"ES",
    "sg:address":"Calle de Mayor, 166",
    "sg:city":"Raal",
    "sg:orig_category":"Librer\u00cdas",
    "sg:phone":"+34 968 81 20 14",
    "sg:postcode":"30139",
    "sg:province":"Murcia",
    "wof:name":"Martinez Franco Amparo",
    "wof:placetype":"venue"
},
  "geometry": {"coordinates":[-1.0294680595,38.039150238],"type":"Point"}
}