{
  "type": "Feature",
  "properties": {
    "iso:country":"ES",
    "sg:address":"Calle de Serrablo (de), 25",
    "sg:city":"Sabi\u00f1anigo",
    "sg:orig_category":"Asociaciones Y Clubs Deportivos",
    "sg:phone":"+34 974 48 06 60",
    "sg:postcode":"22600",
    "sg:province":"Huesca",
    "wof:name":"Club Ciclista Edelweis",
    "wof:placetype":"venue"
},
  "geometry": {"coordinates":[-0.3693290055,42.5188674927],"type":"Point"}
}