{
  "type": "Feature",
  "properties": {
    "iso:country":"ES",
    "sg:address":"Estacion Ferrocarril, S/n",
    "sg:city":"Estacion",
    "sg:orig_category":"Alimentaci\u00d3n General (al Por Menor)",
    "sg:phone":"+34 918 97 23 95",
    "sg:postcode":"05230",
    "sg:province":"\u00c1vila",
    "wof:name":"Alvarez Martin Eleuterio",
    "wof:placetype":"venue"
},
  "geometry": {"coordinates":[-4.700322628,40.6564216614],"type":"Point"}
}