{
  "type": "Feature",
  "properties": {
    "iso:country":"ES",
    "sg:address":"Carrer de Montcada, 14",
    "sg:city":"Castellar Valles",
    "sg:orig_category":"Internados & Ense\u00d1anza Privada",
    "sg:phone":"+34 937 14 52 47",
    "sg:postcode":"08211",
    "sg:province":"Barcelona",
    "wof:name":"Sanchez Moreno Gregorio Pio",
    "wof:placetype":"venue"
},
  "geometry": {"coordinates":[2.0890419483,41.6152915955],"type":"Point"}
}