{
  "type": "Feature",
  "properties": {
    "iso:country":"ES",
    "sg:address":"Calle de Almolda, 8",
    "sg:city":"Caspe",
    "sg:orig_category":"Cerrajer\u00cda, Ferrallista",
    "sg:phone":"+34 976 63 03 12",
    "sg:postcode":"50700",
    "sg:province":"Zaragoza",
    "wof:name":"Fernando Bonastre S.l.",
    "wof:placetype":"venue"
},
  "geometry": {"coordinates":[-0.036424201,41.2267951965],"type":"Point"}
}