{
  "type": "Feature",
  "properties": {
    "iso:country":"ES",
    "sg:address":"Calle de Jaime Segarra, 58",
    "sg:city":"Alacant",
    "sg:classifiers":[
        {
            "category":"Personal",
            "subcategory":"Barber",
            "type":"Services"
        }
    ],
    "sg:phone":"+34 965 25 40 44",
    "sg:postcode":"03012",
    "sg:province":"Alicante",
    "sg:tags":[
        "caballeros",
        "de",
        "peluqueros"
    ],
    "wof:name":"Martinez Valero Emilio",
    "wof:placetype":"venue"
},
  "geometry": {"coordinates":[-0.4811510146,38.3565406799],"type":"Point"}
}