{
  "type": "Feature",
  "properties": {
    "addr:full":"Calle de Emilio Castelar, 20 Algeciras C\u00e1diz 11201",
    "addr:housenumber":"20;ca\u0301diz",
    "addr:postcode":"11201",
    "addr:street":"Calle De Emilio Castelar",
    "iso:country":"ES",
    "sg:address":"Calle de Emilio Castelar, 20",
    "sg:city":"Algeciras",
    "sg:orig_category":"Material Y Suministros Para Peluquer\u00cda",
    "sg:phone":"+34 956 65 64 01",
    "sg:postcode":"11201",
    "sg:province":"C\u00e1diz",
    "wof:name":"Paco Oca\u00f1a C.b.",
    "wof:placetype":"venue"
},
  "geometry": {"coordinates":[-5.4473366737,36.1287765503],"type":"Point"}
}