{
  "type": "Feature",
  "properties": {
    "iso:country":"ES",
    "sg:address":"Calle de Ramon Del Valle, 5",
    "sg:city":"Arriondas",
    "sg:orig_category":"Art\u00cdculos De Regalo (al Por Menor)",
    "sg:phone":"+34 985 84 12 48",
    "sg:postcode":"33540",
    "sg:province":"Asturias",
    "wof:name":"Natalia Suarez Solis-norma Suarez Solis C.b.",
    "wof:placetype":"venue"
},
  "geometry": {"coordinates":[-5.1871137619,43.3903846741],"type":"Point"}
}