{
  "type": "Feature",
  "properties": {
    "addr:full":"Ctra Palmar, 42 Murcia Murcia 30010",
    "addr:housenumber":"42",
    "addr:postcode":"30010",
    "addr:street":"Ctra Palmar",
    "iso:country":"ES",
    "sg:address":"Ctra Palmar, 42",
    "sg:city":"Murcia",
    "sg:orig_category":"Automatizaci\u00d3n De Procesos Industriales Y De Edificaci\u00d3n (estudios, Instalaci\u00d3n)",
    "sg:phone":"+34 968 25 90 37",
    "sg:postcode":"30010",
    "sg:province":"Murcia",
    "wof:name":"Tooltechnic Systems S.l.",
    "wof:placetype":"venue"
},
  "geometry": {"coordinates":[-1.135866046,37.9727325439],"type":"Point"}
}