{
  "type": "Feature",
  "properties": {
    "iso:country":"ES",
    "sg:address":"Carrer de Valls, 81",
    "sg:city":"Terrassa",
    "sg:orig_category":"Muebles Y Accesorios Para Cocinas Y Cuartos De Ba\u00d1o (al Por Menor)",
    "sg:phone":"+34 937 83 15 11",
    "sg:postcode":"08223",
    "sg:province":"Barcelona",
    "wof:name":"Vertice Interiorismo S.a.",
    "wof:placetype":"venue"
},
  "geometry": {"coordinates":[2.0127100945,41.5527381897],"type":"Point"}
}