{
  "type": "Feature",
  "properties": {
    "addr:full":"Poligono San Lazaro, 16 Sto. Domingo Calzada La Rioja 26250",
    "addr:housenumber":"16",
    "addr:postcode":"26250",
    "addr:street":"San Lazaro;Calzada;Rioja",
    "iso:country":"ES",
    "sg:address":"Poligono San Lazaro, 16",
    "sg:city":"Sto. Domingo Calzada",
    "sg:orig_category":"Cristaler\u00cdas",
    "sg:phone":"+34 941 34 31 38",
    "sg:postcode":"26250",
    "sg:province":"La Rioja",
    "wof:name":"Cristaleria Murillo S.l.",
    "wof:placetype":"venue"
},
  "geometry": {"coordinates":[-2.9541339874,42.4394760132],"type":"Point"}
}