{
  "type": "Feature",
  "properties": {
    "addr:full":"Avda Cristobal De Murrieta, 58 Santurtzi Vizcaya 48980",
    "addr:housenumber":"58",
    "addr:postcode":"48980",
    "addr:street":"Avda Cristobal De Murrieta",
    "iso:country":"ES",
    "sg:address":"Avda Cristobal De Murrieta, 58",
    "sg:city":"Santurtzi",
    "sg:orig_category":"Asociaciones Y Clubs Deportivos",
    "sg:phone":"+34 944 61 66 66",
    "sg:postcode":"48980",
    "sg:province":"Vizcaya",
    "wof:name":"World Fitness Center S.l.",
    "wof:placetype":"venue"
},
  "geometry": {"coordinates":[-3.0289163589,43.3275756836],"type":"Point"}
}