{
  "type": "Feature",
  "properties": {
    "addr:full":"Pase Estacion, 92 Torredelcampo Ja\u00e9n 23640",
    "addr:housenumber":"92",
    "addr:postcode":"23640",
    "addr:street":"Estacion;Jae\u0301N",
    "iso:country":"ES",
    "sg:address":"Pase Estacion, 92",
    "sg:city":"Torredelcampo",
    "sg:orig_category":"Asesor\u00cda Fiscal Y Jur\u00cddica",
    "sg:phone":"+34 953 56 76 23",
    "sg:postcode":"23640",
    "sg:province":"Ja\u00e9n",
    "wof:name":"Arroyo Colomo Catalina",
    "wof:placetype":"venue"
},
  "geometry": {"coordinates":[-3.9266502857,37.8072166443],"type":"Point"}
}