{
  "type": "Feature",
  "properties": {
    "iso:country":"ES",
    "sg:address":"Plaz San Nicolas, S/n",
    "sg:city":"San Nicolas",
    "sg:orig_category":"Abogados",
    "sg:phone":"+34 968 21 28 48",
    "sg:postcode":"30005",
    "sg:province":"Murcia",
    "wof:name":"Ballesteros Perez Miguel",
    "wof:placetype":"venue"
},
  "geometry": {"coordinates":[-1.1358850002,37.9868392944],"type":"Point"}
}