{
  "type": "Feature",
  "properties": {
    "iso:country":"ES",
    "sg:address":"Carr. De Alozaina Ronda, Km. 0040,0",
    "sg:city":"Alozaina",
    "sg:orig_category":"Asociaciones Ecologistas",
    "sg:phone":"+34 952 48 05 58",
    "sg:postcode":"29567",
    "sg:province":"M\u00e1laga",
    "sg:website":"www.arroyodelasvinas.com",
    "wof:name":"Antonio Jorge Reina Small",
    "wof:placetype":"venue"
},
  "geometry": {"coordinates":[-4.8436484337,36.7837791443],"type":"Point"}
}