{
  "type": "Feature",
  "properties": {
    "addr:full":"Av Gava, 14 Viladecans Barcelona 08840",
    "addr:housenumber":"14",
    "addr:postcode":"08840",
    "addr:street":"Av Gava",
    "iso:country":"ES",
    "sg:address":"Av Gava, 14",
    "sg:city":"Viladecans",
    "sg:orig_category":"Alimentaci\u00d3n General (al Por Menor)",
    "sg:phone":"+34 936 58 57 96",
    "sg:postcode":"08840",
    "sg:province":"Barcelona",
    "wof:name":"Lligadas Marti Jaime",
    "wof:placetype":"venue"
},
  "geometry": {"coordinates":[2.0170850754,41.3136940002],"type":"Point"}
}