{
  "type": "Feature",
  "properties": {
    "iso:country":"ES",
    "sg:address":"Plaz Espa\u00d1a, 13",
    "sg:city":"Montoro",
    "sg:orig_category":"Molduras, Junquillos, Listones Y Molduras Perforadas",
    "sg:phone":"+34 957 16 00 74",
    "sg:postcode":"14600",
    "sg:province":"C\u00f3rdoba",
    "wof:name":"Magdaleno Cepas Francisco",
    "wof:placetype":"venue"
},
  "geometry": {"coordinates":[-4.3810811043,38.0260734558],"type":"Point"}
}