{
  "type": "Feature",
  "properties": {
    "iso:country":"ES",
    "sg:address":"Calle de Rodriguez San Pedro, 15",
    "sg:city":"Madrid",
    "sg:orig_category":"Fotograf\u00cda Publicitaria E Industrial",
    "sg:phone":"+34 914 45 28 04",
    "sg:postcode":"28015",
    "sg:province":"Madrid",
    "wof:name":"Amigo Gonzalez Carlos",
    "wof:placetype":"venue"
},
  "geometry": {"coordinates":[-3.7098488808,40.431640625],"type":"Point"}
}