{
  "type": "Feature",
  "properties": {
    "addr:full":"Calle de Isabel La Catolica, 22 Fuente Cantos Badajoz 06240",
    "addr:housenumber":"22",
    "addr:postcode":"06240",
    "addr:street":"Calle De Isabel La Catolica",
    "iso:country":"ES",
    "sg:address":"Calle de Isabel La Catolica, 22",
    "sg:city":"Fuente Cantos",
    "sg:orig_category":"Asesor\u00cda Sobre Comunicaci\u00d3n De Empresas",
    "sg:phone":"+34 924 50 02 81",
    "sg:postcode":"06240",
    "sg:province":"Badajoz",
    "wof:name":"J. Mo\u00f1ino Asesoria Integral S.l.",
    "wof:placetype":"venue"
},
  "geometry": {"coordinates":[-6.2997288704,38.2481498718],"type":"Point"}
}