{
  "type": "Feature",
  "properties": {
    "iso:country":"ES",
    "sg:address":"Poli Industrial Francoli, S/n",
    "sg:city":"Campsa",
    "sg:orig_category":"Transportes Por Carretera: Lotes Completos, Mercanc\u00cdas Diversas",
    "sg:phone":"+34 977 55 15 92",
    "sg:postcode":"43006",
    "sg:province":"Tarragona",
    "wof:name":"Vincent Food Tarragona S.l.u.",
    "wof:placetype":"venue"
},
  "geometry": {"coordinates":[1.2209249735,41.1154441833],"type":"Point"}
}