{
  "type": "Feature",
  "properties": {
    "addr:full":"Calle de Cuevas Amarillas, S/n Pozo Alcon Ja\u00e9n 23485",
    "addr:housenumber":"s",
    "addr:postcode":"23485",
    "addr:street":"Calle De Cuevas Amarillas;/ N Pozo Alcon Jae\u0301N",
    "iso:country":"ES",
    "sg:address":"Calle de Cuevas Amarillas, S/n",
    "sg:city":"Pozo Alcon",
    "sg:orig_category":"Negocio De Materiales De Construcci\u00d3n",
    "sg:phone":"+34 953 71 81 02",
    "sg:postcode":"23485",
    "sg:province":"Ja\u00e9n",
    "wof:name":"Valera Garcia Angel",
    "wof:placetype":"venue"
},
  "geometry": {"coordinates":[-2.9302039146,37.7026748657],"type":"Point"}
}