{
  "type": "Feature",
  "properties": {
    "addr:full":"Avda Cidacos (del), 58 Arnedillo La Rioja 26589",
    "addr:housenumber":"58",
    "addr:postcode":"26589",
    "addr:street":"Avda Cidacos Del;Rioja",
    "iso:country":"ES",
    "sg:address":"Avda Cidacos (del), 58",
    "sg:city":"Arnedillo",
    "sg:orig_category":"Molduras, Junquillos, Listones Y Molduras Perforadas",
    "sg:phone":"+34 941 39 42 23",
    "sg:postcode":"26589",
    "sg:province":"La Rioja",
    "wof:name":"Bar La Huella S.c.",
    "wof:placetype":"venue"
},
  "geometry": {"coordinates":[-2.2361779213,42.2133636475],"type":"Point"}
}