{
  "type": "Feature",
  "properties": {
    "addr:full":"Carrer de Paris, 46 Barcelona Barcelona 08029",
    "addr:housenumber":"46",
    "addr:postcode":"08029",
    "addr:street":"Carrer De Paris",
    "iso:country":"ES",
    "sg:address":"Carrer de Paris, 46",
    "sg:city":"Barcelona",
    "sg:orig_category":"Abogados",
    "sg:phone":"+34 933 22 00 24",
    "sg:postcode":"08029",
    "sg:province":"Barcelona",
    "wof:name":"Perez Ortiz Carlos",
    "wof:placetype":"venue"
},
  "geometry": {"coordinates":[2.1435899734,41.3862800598],"type":"Point"}
}