{
  "type": "Feature",
  "properties": {
    "iso:country":"ES",
    "sg:address":"Cmno Prado, S/n",
    "sg:city":"Fuensalda\u00d1a",
    "sg:orig_category":"Centros De Educaci\u00d3n Especial",
    "sg:phone":"+34 983 58 31 64",
    "sg:postcode":"47194",
    "sg:province":"Valladolid",
    "wof:name":"Colegio Publico Comarcal Ana De Austria De Cigales Mec",
    "wof:placetype":"venue"
},
  "geometry": {"coordinates":[-4.7619590759,41.7062339783],"type":"Point"}
}