{
  "type": "Feature",
  "properties": {
    "addr:full":"Avda Alcalde Manuel De La Pinta, 27 Cadiz C\u00e1diz 11011",
    "addr:housenumber":"27",
    "addr:postcode":"11011",
    "addr:street":"Avda Alcalde Manuel De La Pinta",
    "iso:country":"ES",
    "sg:address":"Avda Alcalde Manuel De La Pinta, 27",
    "sg:city":"Cadiz",
    "sg:orig_category":"Acero: Productos Sider\u00dargicos Y Transformados (fabricaci\u00d3n, Negocio)",
    "sg:phone":"+34 956 25 10 45",
    "sg:postcode":"11011",
    "sg:province":"C\u00e1diz",
    "wof:name":"Reparaciones Y Mantenimientos Narvaez S.l.",
    "wof:placetype":"venue"
},
  "geometry": {"coordinates":[-6.2699308395,36.5016822815],"type":"Point"}
}