{
  "type": "Feature",
  "properties": {
    "iso:country":"ES",
    "sg:address":"Ronda De La Hispanidad, S/n",
    "sg:city":"Villanueva Serena",
    "sg:orig_category":"Veh\u00cdculos De Ocasi\u00d3n",
    "sg:phone":"+34 924 84 52 55",
    "sg:postcode":"06700",
    "sg:province":"Badajoz",
    "wof:name":"Autos Rayego S.l.",
    "wof:placetype":"venue"
},
  "geometry": {"coordinates":[-5.8042984009,38.9788246155],"type":"Point"}
}