{
  "type": "Feature",
  "properties": {
    "iso:country":"ES",
    "sg:address":"Calle de Jupiter, S/n",
    "sg:city":"Alacant",
    "sg:orig_category":"Transportes Por V\u00cdas Navegables",
    "sg:phone":"+34 965 28 84 03",
    "sg:postcode":"03006",
    "sg:province":"Alicante",
    "wof:name":"Guillen Santa Rita De Transportes S.l.",
    "wof:placetype":"venue"
},
  "geometry": {"coordinates":[-0.5262839794,38.3391189575],"type":"Point"}
}