{
  "type": "Feature",
  "properties": {
    "iso:country":"ES",
    "sg:address":"Calle de Fresa, 2",
    "sg:city":"Majadahonda",
    "sg:orig_category":"Importaci\u00d3n",
    "sg:phone":"+34 916 38 85 70",
    "sg:postcode":"28220",
    "sg:province":"Madrid",
    "wof:name":"Catracchia Mayol Francisco Cesar",
    "wof:placetype":"venue"
},
  "geometry": {"coordinates":[-3.8737430573,40.4556007385],"type":"Point"}
}