{
  "type": "Feature",
  "properties": {
    "iso:country":"ES",
    "sg:address":"Calle de Hermanos Zerolo, 22",
    "sg:city":"Arrecife",
    "sg:orig_category":"Zapatos (al Por Menor)",
    "sg:phone":"+34 928 81 36 10",
    "sg:postcode":"35500",
    "sg:province":"Las Palmas",
    "wof:name":"Hernandez Saavedra Felix Jesus",
    "wof:placetype":"venue"
},
  "geometry": {"coordinates":[-13.5507707596,28.9615535736],"type":"Point"}
}