{
  "type": "Feature",
  "properties": {
    "iso:country":"ES",
    "sg:address":"Avda Ayora, 9",
    "sg:city":"Casas De Juan Nu\u00e7ez",
    "sg:orig_category":"Bares, Piano",
    "sg:phone":"+34 967 40 53 56",
    "sg:postcode":"02151",
    "sg:province":"Albacete",
    "wof:name":"Oms Sacede S.a.",
    "wof:placetype":"venue"
},
  "geometry": {"coordinates":[-1.5569859743,39.1001625061],"type":"Point"}
}