{
  "type": "Feature",
  "properties": {
    "addr:full":"Calle de Cadena, 22 Brihuega Guadalajara 19400",
    "addr:housenumber":"22",
    "addr:postcode":"19400",
    "addr:street":"Calle De Cadena",
    "iso:country":"ES",
    "sg:address":"Calle de Cadena, 22",
    "sg:city":"Brihuega",
    "sg:orig_category":"Peluquer\u00cdas, Peluquer\u00cda Mixta",
    "sg:phone":"+34 949 28 06 73",
    "sg:postcode":"19400",
    "sg:province":"Guadalajara",
    "wof:name":"Cortijo Garcia Antonio",
    "wof:placetype":"venue"
},
  "geometry": {"coordinates":[-2.8695120811,40.7620658875],"type":"Point"}
}