{
  "type": "Feature",
  "properties": {
    "addr:full":"Albaina, S/n Albaina Burgos 09216",
    "addr:postcode":"09216",
    "addr:street":"Albaina S / N Albaina",
    "iso:country":"ES",
    "sg:address":"Albaina, S/n",
    "sg:city":"Albaina",
    "sg:orig_category":"Ense\u00d1anza, Formaci\u00d3n Profesional: Aprendizaje",
    "sg:phone":"+34 945 37 90 73",
    "sg:postcode":"09216",
    "sg:province":"Burgos",
    "wof:name":"Ayuntamiento",
    "wof:placetype":"venue"
},
  "geometry": {"coordinates":[-2.6325984001,42.6893844604],"type":"Point"}
}