{
  "type": "Feature",
  "properties": {
    "addr:full":"Calle de Lagasca, 75 Madrid Madrid 28001",
    "addr:housenumber":"75",
    "addr:postcode":"madrid;28001",
    "addr:street":"Calle De Lagasca",
    "iso:country":"ES",
    "sg:address":"Calle de Lagasca, 75",
    "sg:city":"Madrid",
    "sg:orig_category":"Ropa Para Se\u00d1oras (al Por Menor)",
    "sg:phone":"+34 914 31 87 86",
    "sg:postcode":"28001",
    "sg:province":"Madrid",
    "sg:website":"www.victorioylucchino.com",
    "wof:name":"V & L Costura Dise\u00d1o Y Moda S.a.",
    "wof:placetype":"venue"
},
  "geometry": {"coordinates":[-3.6850030422,40.4301338196],"type":"Point"}
}