{
  "type": "Feature",
  "properties": {
    "addr:full":"Avda Constitucion, 91 Villena Alicante 03400",
    "addr:housenumber":"91",
    "addr:postcode":"03400",
    "addr:street":"Avda Constitucion",
    "iso:country":"ES",
    "sg:address":"Avda Constitucion, 91",
    "sg:city":"Villena",
    "sg:orig_category":"Cajas De Ahorro",
    "sg:phone":"+34 965 80 50 49",
    "sg:postcode":"03400",
    "sg:province":"Alicante",
    "wof:name":"Caja De Ahorros De Valencia Castellon Y Alicante",
    "wof:placetype":"venue"
},
  "geometry": {"coordinates":[-0.8667590022,38.6374816895],"type":"Point"}
}