{
  "type": "Feature",
  "properties": {
    "addr:full":"Calle de Sanguino Michel, 2 Caceres C\u00e1ceres 10001",
    "addr:housenumber":"2",
    "addr:postcode":"10001",
    "addr:street":"Calle De Sanguino Michel;Ca\u0301Ceres",
    "iso:country":"ES",
    "sg:address":"Calle de Sanguino Michel, 2",
    "sg:city":"Caceres",
    "sg:orig_category":"Asesor\u00cda Sobre Comunicaci\u00d3n De Empresas",
    "sg:phone":"+34 927 21 13 72",
    "sg:postcode":"10001",
    "sg:province":"C\u00e1ceres",
    "wof:name":"Asesoria Empresarial Serfico S.l.",
    "wof:placetype":"venue"
},
  "geometry": {"coordinates":[-6.3824334145,39.4669876099],"type":"Point"}
}