{
  "type": "Feature",
  "properties": {
    "addr:full":"Pago La Lobita, Km. 0021,0 Conil C\u00e1diz 11140",
    "addr:postcode":"11140",
    "addr:street":"Pago La Lobita Km. 0021,0",
    "iso:country":"ES",
    "sg:address":"Pago La Lobita, Km. 0021,0",
    "sg:city":"Conil",
    "sg:orig_category":"Alimentaci\u00d3n General (al Por Mayor)",
    "sg:phone":"+34 956 44 00 67",
    "sg:postcode":"11140",
    "sg:province":"C\u00e1diz",
    "wof:name":"Carlos Romero Mora-figueroa S.l.",
    "wof:placetype":"venue"
},
  "geometry": {"coordinates":[-6.0870790482,36.2767066956],"type":"Point"}
}