{
  "type": "Feature",
  "properties": {
    "addr:full":"Calle de Islas Britanicas, 10 Fuenlabrada Madrid 28942",
    "addr:housenumber":"10",
    "addr:postcode":"28942",
    "addr:street":"Calle De Islas Britanicas",
    "iso:country":"ES",
    "sg:address":"Calle de Islas Britanicas, 10",
    "sg:city":"Fuenlabrada",
    "sg:orig_category":"Caf\u00c9s, Bares, Cervecer\u00cdas",
    "sg:phone":"+34 916 08 01 75",
    "sg:postcode":"28942",
    "sg:province":"Madrid",
    "wof:name":"Aguado Gutierrez Marina",
    "wof:placetype":"venue"
},
  "geometry": {"coordinates":[-3.8098225594,40.2889175415],"type":"Point"}
}