{
  "type": "Feature",
  "properties": {
    "addr:full":"Plaz Paseito Ramiro, 1 Alacant Alicante 03002",
    "addr:housenumber":"1",
    "addr:postcode":"03002",
    "addr:street":"Plaz;Ramiro",
    "iso:country":"ES",
    "sg:address":"Plaz Paseito Ramiro, 1",
    "sg:city":"Alacant",
    "sg:orig_category":"Edici\u00d3n De Diarios, Revistas, Boletines",
    "sg:phone":"+34 965 23 08 60",
    "sg:postcode":"03002",
    "sg:province":"Alicante",
    "sg:website":"www.quediario.com",
    "wof:name":"Factoria De Informacion S.a.",
    "wof:placetype":"venue"
},
  "geometry": {"coordinates":[-0.4786730111,38.34557724],"type":"Point"}
}