{
  "type": "Feature",
  "properties": {
    "addr:full":"Av Catalunya, 3 Pobla Segur Lleida 25500",
    "addr:housenumber":"3",
    "addr:postcode":"25500",
    "addr:street":"Av Catalunya",
    "iso:country":"ES",
    "sg:address":"Av Catalunya, 3",
    "sg:city":"Pobla Segur",
    "sg:orig_category":"Carnicer\u00cdas, Carnicer\u00cdas",
    "sg:phone":"+34 973 68 02 56",
    "sg:postcode":"25500",
    "sg:province":"Lleida",
    "wof:name":"Guardia Sansalvado Antoni",
    "wof:placetype":"venue"
},
  "geometry": {"coordinates":[0.9661793709,42.2489395142],"type":"Point"}
}