{
  "type": "Feature",
  "properties": {
    "addr:full":"Av Fra Juniper Serra, 39 Manacor Islas Baleares 07500",
    "addr:housenumber":"39",
    "addr:postcode":"07500",
    "addr:street":"Av Fra Juniper Serra",
    "iso:country":"ES",
    "sg:address":"Av Fra Juniper Serra, 39",
    "sg:city":"Manacor",
    "sg:orig_category":"Muebles, Minoristas",
    "sg:phone":"+34 971 55 99 36",
    "sg:postcode":"07500",
    "sg:province":"Islas Baleares",
    "wof:name":"Destempo S.l.",
    "wof:placetype":"venue"
},
  "geometry": {"coordinates":[3.2014620304,39.5739822388],"type":"Point"}
}