{
  "type": "Feature",
  "properties": {
    "addr:full":"Pl Lluis Casassas, 6 Sabadell Barcelona 08201",
    "addr:housenumber":"6",
    "addr:postcode":"08201",
    "addr:street":"Pl;Casassas",
    "iso:country":"ES",
    "sg:address":"Pl Lluis Casassas, 6",
    "sg:city":"Sabadell",
    "sg:orig_category":"Papeler\u00cdas, Librer\u00cdas",
    "sg:phone":"+34 937 23 37 11",
    "sg:postcode":"08201",
    "sg:province":"Barcelona",
    "wof:name":"Martinez Gomez Francisco",
    "wof:placetype":"venue"
},
  "geometry": {"coordinates":[2.1044499874,41.5473213196],"type":"Point"}
}