{
  "type": "Feature",
  "properties": {
    "iso:country":"ES",
    "sg:address":"Calle de Luis Correa Medina, 13",
    "sg:city":"Palmas De Gran Canaria",
    "sg:orig_category":"Equipo De Refrigeraci\u00d3n Industrial",
    "sg:phone":"+34 928 41 91 48",
    "sg:postcode":"35013",
    "sg:province":"Las Palmas",
    "wof:name":"Grupo Kalise Menorquina S.a.",
    "wof:placetype":"venue"
},
  "geometry": {"coordinates":[-15.4359035492,28.1025791168],"type":"Point"}
}