{
  "type": "Feature",
  "properties": {
    "addr:full":"Carrer de Sant Isidre, 107 Sabadell Barcelona 08208",
    "addr:housenumber":"107",
    "addr:postcode":"08208",
    "addr:street":"Carrer De Sant Isidre",
    "iso:country":"ES",
    "sg:address":"Carrer de Sant Isidre, 107",
    "sg:city":"Sabadell",
    "sg:orig_category":"Molduras, Junquillos, Listones Y Molduras Perforadas",
    "sg:phone":"+34 937 23 19 79",
    "sg:postcode":"08208",
    "sg:province":"Barcelona",
    "wof:name":"Inmobiliarios Asociados Gia-fm S.l.",
    "wof:placetype":"venue"
},
  "geometry": {"coordinates":[2.1003980637,41.5536308289],"type":"Point"}
}