{
  "type": "Feature",
  "properties": {
    "iso:country":"ES",
    "sg:address":"Rua Rois De La Pe\u00d1a, 4",
    "sg:city":"Fonsagrada",
    "sg:orig_category":"Procuradores",
    "sg:phone":"+34 982 34 03 18",
    "sg:postcode":"27100",
    "sg:province":"Lugo",
    "wof:name":"Sierra Villaverde Soledad",
    "wof:placetype":"venue"
},
  "geometry": {"coordinates":[-7.0673189163,43.125995636],"type":"Point"}
}