{
  "type": "Feature",
  "properties": {
    "addr:full":"Pje Poeta L Cernuda, S/n Ronda M\u00e1laga 29400",
    "addr:housenumber":"s / n",
    "addr:postcode":"29400",
    "addr:street":"Pje Poeta L Cernuda;Ronda Ma\u0301Laga",
    "iso:country":"ES",
    "sg:address":"Pje Poeta L Cernuda, S/n",
    "sg:city":"Ronda",
    "sg:orig_category":"Agencias Y Agentes Comerciales, Representantes",
    "sg:phone":"+34 952 87 74 76",
    "sg:postcode":"29400",
    "sg:province":"M\u00e1laga",
    "wof:name":"Sierra Ronda Sl",
    "wof:placetype":"venue"
},
  "geometry": {"coordinates":[-5.1662788391,36.7417945862],"type":"Point"}
}