{
  "type": "Feature",
  "properties": {
    "addr:full":"Avda Gesto Por La Paz, 33 Algeciras C\u00e1diz 11206",
    "addr:housenumber":"33;ca\u0301diz",
    "addr:postcode":"11206",
    "addr:street":"Avda Gesto Por La Paz",
    "iso:country":"ES",
    "sg:address":"Avda Gesto Por La Paz, 33",
    "sg:city":"Algeciras",
    "sg:orig_category":"Alquiler De Gr\u00daas",
    "sg:phone":"+34 956 60 00 22",
    "sg:postcode":"11206",
    "sg:province":"C\u00e1diz",
    "wof:name":"Cabeza Elevaciones Y Transportes S.l.",
    "wof:placetype":"venue"
},
  "geometry": {"coordinates":[-5.4543828964,36.1143951416],"type":"Point"}
}