{
  "type": "Feature",
  "properties": {
    "addr:full":"Ctra Malaga, S/n Lucena C\u00f3rdoba 14900",
    "addr:postcode":"14900",
    "addr:street":"Ctra Malaga S / N",
    "iso:country":"ES",
    "sg:address":"Ctra Malaga, S/n",
    "sg:city":"Lucena",
    "sg:orig_category":"Electricidad (montaje, Ensamblaje De Componentes)",
    "sg:phone":"+34 957 50 12 68",
    "sg:postcode":"14900",
    "sg:province":"C\u00f3rdoba",
    "wof:name":"Hermanos Servian Mu\u00f1oz",
    "wof:placetype":"venue"
},
  "geometry": {"coordinates":[-4.4906687737,37.3586082458],"type":"Point"}
}