{
  "type": "Feature",
  "properties": {
    "addr:full":"Calle de Urquijo Julio, 8 Bilbao Vizcaya 48014",
    "addr:housenumber":"8",
    "addr:postcode":"48014",
    "addr:street":"Calle De Urquijo Julio",
    "iso:country":"ES",
    "sg:address":"Calle de Urquijo Julio, 8",
    "sg:city":"Bilbao",
    "sg:orig_category":"Restaurantes",
    "sg:phone":"+34 944 47 35 76",
    "sg:postcode":"48014",
    "sg:province":"Vizcaya",
    "wof:name":"Luis Ferruelo Barrio",
    "wof:placetype":"venue"
},
  "geometry": {"coordinates":[-2.9529221058,43.2702941895],"type":"Point"}
}