{
  "type": "Feature",
  "properties": {
    "iso:country":"ES",
    "sg:address":"Calle de Sargento Del Rio Llamas, 9",
    "sg:city":"Alacant",
    "sg:orig_category":"Agencias Y Agentes Comerciales, Representantes",
    "sg:phone":"+34 965 24 20 73",
    "sg:postcode":"03009",
    "sg:province":"Alicante",
    "wof:name":"Bou Fuentes Ivan",
    "wof:placetype":"venue"
},
  "geometry": {"coordinates":[-0.4880549908,38.3543624878],"type":"Point"}
}