{
  "type": "Feature",
  "properties": {
    "addr:full":"Calle de Union, 22 Valladolid Valladolid 47005",
    "addr:housenumber":"22",
    "addr:postcode":"47005",
    "addr:street":"Calle De",
    "iso:country":"ES",
    "sg:address":"Calle de Union, 22",
    "sg:city":"Valladolid",
    "sg:orig_category":"Mec\u00c1nico Del Autom\u00d3vil",
    "sg:phone":"+34 983 29 06 83",
    "sg:postcode":"47005",
    "sg:province":"Valladolid",
    "sg:website":"www.paginasamarillas.es",
    "wof:name":"Tunyva S.l",
    "wof:placetype":"venue"
},
  "geometry": {"coordinates":[-4.7139225006,41.6488761902],"type":"Point"}
}