{
  "type": "Feature",
  "properties": {
    "addr:full":"Avda Corchaito, 1 Viso C\u00f3rdoba 14470",
    "addr:housenumber":"1",
    "addr:postcode":"14470",
    "addr:street":"Avda Corchaito;Co\u0301Rdoba",
    "iso:country":"ES",
    "sg:address":"Avda Corchaito, 1",
    "sg:city":"Viso",
    "sg:orig_category":"Empresas De Electricidad En General",
    "sg:phone":"+34 957 12 73 09",
    "sg:postcode":"14470",
    "sg:province":"C\u00f3rdoba",
    "wof:name":"Electrica Los Pelayos S.a.",
    "wof:placetype":"venue"
},
  "geometry": {"coordinates":[-4.9570431709,38.4826545715],"type":"Point"}
}