{
  "type": "Feature",
  "properties": {
    "addr:full":"Calle de Nicasio Gallego, 5 Madrid Madrid 28010",
    "addr:housenumber":"5",
    "addr:postcode":"28010",
    "addr:street":"Calle De Nicasio Gallego",
    "iso:country":"ES",
    "sg:address":"Calle de Nicasio Gallego, 5",
    "sg:city":"Madrid",
    "sg:orig_category":"Instalaci\u00d3n, Reparaci\u00d3n De Ascensores Y Montacargas",
    "sg:phone":"+34 914 48 81 84",
    "sg:postcode":"28010",
    "sg:province":"Madrid",
    "wof:name":"Sociedad Espa\u00f1ola De Ascensores S. A.",
    "wof:placetype":"venue"
},
  "geometry": {"coordinates":[-3.6999158859,40.4295501709],"type":"Point"}
}