{
  "type": "Feature",
  "properties": {
    "addr:full":"La Rigueira, 3 Mi\u00f1o La Coru\u00f1a 15630",
    "addr:housenumber":"3",
    "addr:postcode":"15630",
    "addr:street":"Min\u0303O La Corun\u0303A",
    "iso:country":"ES",
    "sg:address":"La Rigueira, 3",
    "sg:city":"Mi\u00f1o",
    "sg:orig_category":"Asociaciones, Organismos Culturales Y Socioeducativos",
    "sg:phone":"+34 981 78 20 52",
    "sg:postcode":"15630",
    "sg:province":"La Coru\u00f1a",
    "wof:name":"Fundacion Rita Ramos Portal",
    "wof:placetype":"venue"
},
  "geometry": {"coordinates":[-8.2058076859,43.3499221802],"type":"Point"}
}