{
  "type": "Feature",
  "properties": {
    "addr:full":"Luis Morondo Urra, 12 Iru\u00f1a Navarra 31006",
    "addr:housenumber":"12",
    "addr:postcode":"31006",
    "addr:street":"Luis;Urra",
    "iso:country":"ES",
    "sg:address":"Luis Morondo Urra, 12",
    "sg:city":"Iru\u00f1a",
    "sg:orig_category":"Barcos",
    "sg:phone":"+34 948 29 22 22",
    "sg:postcode":"31006",
    "sg:province":"Navarra",
    "sg:website":"www.iruinpromociones.com",
    "wof:name":"Iru.in.naves Industriales S.l.",
    "wof:placetype":"venue"
},
  "geometry": {"coordinates":[-1.6463717222,42.8008766174],"type":"Point"}
}