{
  "type": "Feature",
  "properties": {
    "iso:country":"ES",
    "sg:address":"Ctra Fuensanta, 242",
    "sg:city":"Ermita De Pati\u00e7o",
    "sg:orig_category":"Muebles, Minoristas",
    "sg:phone":"+34 968 35 20 37",
    "sg:postcode":"30012",
    "sg:province":"Murcia",
    "sg:website":"www.sucesoredejuanmarmolmoreno.com",
    "wof:name":"Sucesores De Juan Marmol Moreno S.l.",
    "wof:placetype":"venue"
},
  "geometry": {"coordinates":[-1.1263819933,37.9585227966],"type":"Point"}
}