{
  "type": "Feature",
  "properties": {
    "iso:country":"ES",
    "sg:address":"Ctra. P. Alcocer, S/n",
    "sg:city":"Cabeza Buey",
    "sg:orig_category":"Cr\u00cda De Animales",
    "sg:phone":"+34 924 60 10 32",
    "sg:postcode":"06600",
    "sg:province":"Badajoz",
    "wof:name":"Alanser Sociedad Cooperativa Limitada",
    "wof:placetype":"venue"
},
  "geometry": {"coordinates":[-5.2033619881,38.7991867065],"type":"Point"}
}