{
  "type": "Feature",
  "properties": {
    "addr:full":"Carrer de Montsia, 91 Poligono Industrial Can Carner Barcelona 08211",
    "addr:housenumber":"91",
    "addr:postcode":"08211",
    "addr:street":"Carrer De Montsia;Industrial",
    "iso:country":"ES",
    "sg:address":"Carrer de Montsia, 91",
    "sg:city":"Poligono Industrial Can Carner",
    "sg:orig_category":"Cajas Y Embalajes De Pl\u00c1stico",
    "sg:phone":"+34 937 14 48 96",
    "sg:postcode":"08211",
    "sg:province":"Barcelona",
    "wof:name":"Envasats Abl Sl",
    "wof:placetype":"venue"
},
  "geometry": {"coordinates":[2.0857300758,41.6151885986],"type":"Point"}
}