{
  "type": "Feature",
  "properties": {
    "addr:full":"Calle de Alferez Provisional, 10 Chantada Lugo 27500",
    "addr:housenumber":"10",
    "addr:postcode":"27500",
    "addr:street":"Calle De Alferez Provisional",
    "iso:country":"ES",
    "sg:address":"Calle de Alferez Provisional, 10",
    "sg:city":"Chantada",
    "sg:orig_category":"Administradores De Bienes Y Delegados De Comunidades De Propietarios",
    "sg:phone":"+34 982 44 18 94",
    "sg:postcode":"27500",
    "sg:province":"Lugo",
    "wof:name":"Arias Lence S.l.",
    "wof:placetype":"venue"
},
  "geometry": {"coordinates":[-7.7704615593,42.610660553],"type":"Point"}
}