{
  "type": "Feature",
  "properties": {
    "addr:full":"Calle de Ramon Marquet, 15 Valencia Valencia 46022",
    "addr:housenumber":"15",
    "addr:postcode":"46022",
    "addr:street":"Calle De Ramon Marquet",
    "iso:country":"ES",
    "sg:address":"Calle de Ramon Marquet, 15",
    "sg:city":"Valencia",
    "sg:orig_category":"Confecci\u00d3n (fabricaci\u00d3n, Al Por Mayor)",
    "sg:phone":"+34 963 30 04 52",
    "sg:postcode":"46022",
    "sg:province":"Valencia",
    "wof:name":"Estircort S.l.",
    "wof:placetype":"venue"
},
  "geometry": {"coordinates":[-0.3454140127,39.4644393921],"type":"Point"}
}