{
  "type": "Feature",
  "properties": {
    "addr:full":"Carrer de Pare Roca, 12 Olot Girona 17800",
    "addr:housenumber":"12",
    "addr:postcode":"17800",
    "addr:street":"Carrer De Pare Roca",
    "iso:country":"ES",
    "sg:address":"Carrer de Pare Roca, 12",
    "sg:city":"Olot",
    "sg:orig_category":"Cl\u00cdnicas Dentales",
    "sg:phone":"+34 972 26 27 18",
    "sg:postcode":"17800",
    "sg:province":"Girona",
    "wof:name":"Clinica Dental Drs. Llagostera I Concellon S.c.",
    "wof:placetype":"venue"
},
  "geometry": {"coordinates":[2.482863903,42.182220459],"type":"Point"}
}