{
  "type": "Feature",
  "properties": {
    "addr:full":"Carrer de Joan Xxiii, 10 Esplugues Llobregat Barcelona 08950",
    "addr:housenumber":"10",
    "addr:postcode":"08950",
    "addr:street":"Carrer De Joan Xxiii",
    "iso:country":"ES",
    "sg:address":"Carrer de Joan Xxiii, 10",
    "sg:city":"Esplugues Llobregat",
    "sg:orig_category":"Laboratorios Farmac\u00c9uticos",
    "sg:phone":"+34 934 73 19 10",
    "sg:postcode":"08950",
    "sg:province":"Barcelona",
    "sg:website":"www.gelos.es",
    "wof:name":"Laboratorios Gelos S.l.",
    "wof:placetype":"venue"
},
  "geometry": {"coordinates":[2.0842609406,41.3737335205],"type":"Point"}
}