{
  "type": "Feature",
  "properties": {
    "addr:full":"Carrer de Masricart (de), 8 Canonja Tarragona 43110",
    "addr:housenumber":"8",
    "addr:postcode":"43110",
    "addr:street":"Carrer De Masricart De",
    "iso:country":"ES",
    "sg:address":"Carrer de Masricart (de), 8",
    "sg:city":"Canonja",
    "sg:orig_category":"Cajas De Ahorro",
    "sg:phone":"+34 977 54 38 70",
    "sg:postcode":"43110",
    "sg:province":"Tarragona",
    "sg:website":"www.caixatarragona.es",
    "wof:name":"Caixa D'estalvis De Tarragona",
    "wof:placetype":"venue"
},
  "geometry": {"coordinates":[1.1817840338,41.1208381653],"type":"Point"}
}