{
  "type": "Feature",
  "properties": {
    "iso:country":"ES",
    "sg:address":"Avda Diputacion, 28",
    "sg:city":"Lepe",
    "sg:orig_category":"Muebles Y Accesorios Para Cocinas Y Cuartos De Ba\u00d1o (al Por Menor)",
    "sg:phone":"+34 959 38 40 14",
    "sg:postcode":"21440",
    "sg:province":"Huelva",
    "wof:name":"Cocinas El Molino S.l",
    "wof:placetype":"venue"
},
  "geometry": {"coordinates":[-7.2031970024,37.2484588623],"type":"Point"}
}