{
  "type": "Feature",
  "properties": {
    "iso:country":"ES",
    "sg:address":"Llaviada, S/n",
    "sg:city":"Llaviada",
    "sg:orig_category":"Quincaller\u00cda (al Por Menor)",
    "sg:phone":"+34 985 62 04 81",
    "sg:postcode":"33720",
    "sg:province":"Asturias",
    "wof:name":"Fernandez Fernandez Manuel",
    "wof:placetype":"venue"
},
  "geometry": {"coordinates":[-6.81873703,43.4276847839],"type":"Point"}
}