{
  "type": "Feature",
  "properties": {
    "addr:full":"Carrer de Galdent, 6 Son Vida Islas Baleares 07013",
    "addr:housenumber":"6",
    "addr:postcode":"07013",
    "addr:street":"Carrer De Galdent",
    "iso:country":"ES",
    "sg:address":"Carrer de Galdent, 6",
    "sg:city":"Son Vida",
    "sg:orig_category":"Financiaci\u00d3n Y Cr\u00c9ditos",
    "sg:phone":"+34 971 79 13 37",
    "sg:postcode":"07013",
    "sg:province":"Islas Baleares",
    "wof:name":"Benno Invest S.l.",
    "wof:placetype":"venue"
},
  "geometry": {"coordinates":[2.9117100239,39.6136398315],"type":"Point"}
}