{
  "type": "Feature",
  "properties": {
    "addr:full":"Calle de Santa Ana, 9 Puertollano Ciudad Real 13500",
    "addr:housenumber":"9",
    "addr:postcode":"13500",
    "addr:street":"Calle De Santa Ana",
    "iso:country":"ES",
    "sg:address":"Calle de Santa Ana, 9",
    "sg:city":"Puertollano",
    "sg:orig_category":"Bisuter\u00cda, Joyer\u00cda, Relojer\u00cda (al Por Menor)",
    "sg:phone":"+34 926 42 86 82",
    "sg:postcode":"13500",
    "sg:province":"Ciudad Real",
    "wof:name":"Palacios Salinas Pilar",
    "wof:placetype":"venue"
},
  "geometry": {"coordinates":[-4.1083707809,38.688331604],"type":"Point"}
}