{
  "type": "Feature",
  "properties": {
    "addr:full":"Carrer de Sant Pere Mitja, 1 Barcelona Barcelona 08003",
    "addr:housenumber":"1",
    "addr:postcode":"08003",
    "addr:street":"Carrer De Sant;Mitja",
    "iso:country":"ES",
    "sg:address":"Carrer de Sant Pere Mitja, 1",
    "sg:city":"Barcelona",
    "sg:orig_category":"Molduras, Junquillos, Listones Y Molduras Perforadas",
    "sg:phone":"+34 933 19 10 26",
    "sg:postcode":"08003",
    "sg:province":"Barcelona",
    "wof:name":"Pavan Ciutat Maria Cruz",
    "wof:placetype":"venue"
},
  "geometry": {"coordinates":[2.1762440205,41.3869552612],"type":"Point"}
}