{
  "type": "Feature",
  "properties": {
    "addr:full":"Calle de Jaen, 2 Alacant Alicante 03005",
    "addr:housenumber":"2",
    "addr:postcode":"03005",
    "addr:street":"Calle De Jaen",
    "iso:country":"ES",
    "sg:address":"Calle de Jaen, 2",
    "sg:city":"Alacant",
    "sg:orig_category":"Art\u00cdculos De Limpieza Y De Cocina (fabricaci\u00d3n, Al Por Mayor)",
    "sg:phone":"+34 965 22 71 03",
    "sg:postcode":"03005",
    "sg:province":"Alicante",
    "wof:name":"Cortes Santamaria Jose Ramon",
    "wof:placetype":"venue"
},
  "geometry": {"coordinates":[-0.4953680038,38.3508911133],"type":"Point"}
}