{
  "type": "Feature",
  "properties": {
    "addr:full":"Carrer de Bartolome Esteban Murillo, 64 Granollers Barcelona 08402",
    "addr:housenumber":"64",
    "addr:postcode":"08402",
    "addr:street":"Carrer De Bartolome Esteban Murillo",
    "iso:country":"ES",
    "sg:address":"Carrer de Bartolome Esteban Murillo, 64",
    "sg:city":"Granollers",
    "sg:orig_category":"Alimentaci\u00d3n General (al Por Menor)",
    "sg:phone":"+34 938 79 44 41",
    "sg:postcode":"08402",
    "sg:province":"Barcelona",
    "wof:name":"Martin Escribano Manuel",
    "wof:placetype":"venue"
},
  "geometry": {"coordinates":[2.2912108898,41.6018943787],"type":"Point"}
}