{
  "type": "Feature",
  "properties": {
    "iso:country":"ES",
    "sg:address":"Ctra. Aracena, S/n",
    "sg:city":"Zufre",
    "sg:orig_category":"Producci\u00d3n, Venta De Productos De Agricultura Biol\u00d3gica",
    "sg:phone":"+34 959 50 70 34",
    "sg:postcode":"21210",
    "sg:province":"Huelva",
    "wof:name":"Aguilar Explotaciones Agricolas S.c.",
    "wof:placetype":"venue"
},
  "geometry": {"coordinates":[-6.3503212929,37.7321243286],"type":"Point"}
}