{
  "type": "Feature",
  "properties": {
    "iso:country":"ES",
    "sg:address":"Carrer de Santa Creu, 6",
    "sg:city":"Sant Feliu Llobregat",
    "sg:orig_category":"Complementos De Vestir (al Por Menor)",
    "sg:phone":"+34 936 85 40 72",
    "sg:postcode":"08980",
    "sg:province":"Barcelona",
    "wof:name":"Ribas Nolla Concepcion",
    "wof:placetype":"venue"
},
  "geometry": {"coordinates":[2.0466310978,41.3850784302],"type":"Point"}
}