{
  "type": "Feature",
  "properties": {
    "iso:country":"ES",
    "sg:address":"Carrer de Bonvei, 1",
    "sg:city":"Cornella Llobregat",
    "sg:orig_category":"Artes Gr\u00c1ficas, Artes Pl\u00c1sticas (curso)",
    "sg:phone":"+34 934 71 40 25",
    "sg:postcode":"08940",
    "sg:province":"Barcelona",
    "wof:name":"Carteleria Big Trama S.l.",
    "wof:placetype":"venue"
},
  "geometry": {"coordinates":[2.0752699375,41.3584098816],"type":"Point"}
}