{
  "type": "Feature",
  "properties": {
    "addr:full":"Calle de Lombia, 3 Madrid Madrid 28009",
    "addr:housenumber":"3",
    "addr:postcode":"28009",
    "addr:street":"Calle De Lombia",
    "iso:country":"ES",
    "sg:address":"Calle de Lombia, 3",
    "sg:city":"Madrid",
    "sg:orig_category":"Peleter\u00cdas",
    "sg:phone":"+34 914 02 63 49",
    "sg:postcode":"28009",
    "sg:province":"Madrid",
    "wof:name":"Garrigos Espino Jaime",
    "wof:placetype":"venue"
},
  "geometry": {"coordinates":[-3.6723489761,40.4255371094],"type":"Point"}
}