{
  "type": "Feature",
  "properties": {
    "addr:full":"Fusteria (pol Goules), 52 Tona Barcelona 08551",
    "addr:housenumber":"52",
    "addr:postcode":"08551",
    "addr:street":"Goules",
    "iso:country":"ES",
    "sg:address":"Fusteria (pol Goules), 52",
    "sg:city":"Tona",
    "sg:orig_category":"Fabricaci\u00d3n De Muebles",
    "sg:phone":"+34 938 12 55 20",
    "sg:postcode":"08551",
    "sg:province":"Barcelona",
    "sg:website":"www.planethair.biz",
    "wof:name":"Ambients Profesionals S.l.",
    "wof:placetype":"venue"
},
  "geometry": {"coordinates":[2.2138288021,41.8487472534],"type":"Point"}
}