{
  "type": "Feature",
  "properties": {
    "addr:full":"Avda Maria Auxiliadora, 15 Badajoz Badajoz 06011",
    "addr:housenumber":"15",
    "addr:postcode":"06011",
    "addr:street":"Avda Maria Auxiliadora",
    "iso:country":"ES",
    "sg:address":"Avda Maria Auxiliadora, 15",
    "sg:city":"Badajoz",
    "sg:orig_category":"Motocicletas (agentes, Concesionarios)",
    "sg:phone":"+34 924 24 10 00",
    "sg:postcode":"06011",
    "sg:province":"Badajoz",
    "wof:name":"Auto Recambio Moto Luis S. A.",
    "wof:placetype":"venue"
},
  "geometry": {"coordinates":[-6.9797410965,38.8689346313],"type":"Point"}
}