{
  "type": "Feature",
  "properties": {
    "addr:full":"Gta Musico E. Alvarez Anton, 5 Alacant Alicante 03006",
    "addr:housenumber":"5",
    "addr:postcode":"03006",
    "addr:street":"Gta Musico E. Alvarez Anton",
    "iso:country":"ES",
    "sg:address":"Gta Musico E. Alvarez Anton, 5",
    "sg:city":"Alacant",
    "sg:orig_category":"Asesor\u00cda Sobre Comunicaci\u00d3n De Empresas",
    "sg:phone":"+34 965 28 82 73",
    "sg:postcode":"03006",
    "sg:province":"Alicante",
    "wof:name":"Bernabeu & Llorens Tecnics Tributaris I Comptables S.l.",
    "wof:placetype":"venue"
},
  "geometry": {"coordinates":[-0.5070059896,38.3445701599],"type":"Point"}
}