{
  "type": "Feature",
  "properties": {
    "addr:full":"Carrer de Rambla (la), 20 Vendrell Tarragona 43700",
    "addr:housenumber":"20",
    "addr:postcode":"43700",
    "addr:street":"Carrer De Rambla La",
    "iso:country":"ES",
    "sg:address":"Carrer de Rambla (la), 20",
    "sg:city":"Vendrell",
    "sg:orig_category":"Psic\u00d3logos",
    "sg:phone":"+34 977 66 47 37",
    "sg:postcode":"43700",
    "sg:province":"Tarragona",
    "wof:name":"Ferrer Vila Josefa",
    "wof:placetype":"venue"
},
  "geometry": {"coordinates":[1.5369449854,41.2205543518],"type":"Point"}
}