{
  "type": "Feature",
  "properties": {
    "iso:country":"ES",
    "sg:address":"Av Catalunya, 24",
    "sg:city":"Sant Joan De Palamos",
    "sg:orig_category":"Muebles, Minoristas",
    "sg:phone":"+34 972 31 46 78",
    "sg:postcode":"17230",
    "sg:province":"Girona",
    "wof:name":"Muebles Palamos S. A.",
    "wof:placetype":"venue"
},
  "geometry": {"coordinates":[3.1247339249,41.8522338867],"type":"Point"}
}