{
  "type": "Feature",
  "properties": {
    "iso:country":"ES",
    "sg:address":"Calle de Monjas, S/n",
    "sg:city":"Valladolid",
    "sg:orig_category":"Charcuter\u00cdas (al Por Mayor)",
    "sg:phone":"+34 983 37 93 43",
    "sg:postcode":"47009",
    "sg:province":"Valladolid",
    "wof:name":"Distribuciones Miguel Y Morejon S.l.",
    "wof:placetype":"venue"
},
  "geometry": {"coordinates":[-4.7342839241,41.6618804932],"type":"Point"}
}