{
  "type": "Feature",
  "properties": {
    "iso:country":"ES",
    "sg:address":"Calle de Escolapios, 4",
    "sg:city":"Ca\u00f1izal",
    "sg:orig_category":"Iglesia Cat\u00d3lica",
    "sg:phone":"+34 980 60 41 63",
    "sg:postcode":"49440",
    "sg:province":"Zamora",
    "wof:name":"Obispado De Zamora",
    "wof:placetype":"venue"
},
  "geometry": {"coordinates":[-5.3691010475,41.1656455994],"type":"Point"}
}