{
  "type": "Feature",
  "properties": {
    "iso:country":"ES",
    "sg:address":"Avda Pintor Felo Monzon, 14",
    "sg:city":"Palmas De Gran Canaria",
    "sg:orig_category":"Cl\u00cdnicas Dentales",
    "sg:phone":"+34 928 41 48 19",
    "sg:postcode":"35019",
    "sg:province":"Las Palmas",
    "wof:name":"Diaz Martinez Ivette",
    "wof:placetype":"venue"
},
  "geometry": {"coordinates":[-15.4521389008,28.1068000793],"type":"Point"}
}