{
  "type": "Feature",
  "properties": {
    "addr:full":"Ernio Bidea, S/n Elbarrena Guip\u00f9zcoa 20159",
    "addr:housenumber":"s / n",
    "addr:postcode":"20159",
    "addr:street":"Ernio Bidea;Elbarrena Guipu\u0300Zcoa",
    "iso:country":"ES",
    "sg:address":"Ernio Bidea, S/n",
    "sg:city":"Elbarrena",
    "sg:orig_category":"Maquinaria Para Industrias Diversas",
    "sg:phone":"+34 943 69 60 23",
    "sg:postcode":"20159",
    "sg:province":"Guip\u00f9zcoa",
    "wof:name":"Talleres Leibi S.a.",
    "wof:placetype":"venue"
},
  "geometry": {"coordinates":[-2.0742990971,43.1991958618],"type":"Point"}
}