{
  "type": "Feature",
  "properties": {
    "addr:full":"Calle de Gorbea, 27 Vitoria-gasteiz \u00c1lava 01012",
    "addr:housenumber":"27",
    "addr:postcode":"01012",
    "addr:street":"Calle De Gorbea",
    "iso:country":"ES",
    "sg:address":"Calle de Gorbea, 27",
    "sg:city":"Vitoria-gasteiz",
    "sg:orig_category":"Fabricaci\u00d3n De Productos Textiles Sin Tejer",
    "sg:phone":"+34 945 22 15 89",
    "sg:postcode":"01012",
    "sg:province":"\u00c1lava",
    "wof:name":"Gorbea 27 S.l.",
    "wof:placetype":"venue"
},
  "geometry": {"coordinates":[-2.6794705391,42.8522872925],"type":"Point"}
}