{
  "type": "Feature",
  "properties": {
    "addr:full":"Carr Font, 1 Besalu Girona 17850",
    "addr:housenumber":"1",
    "addr:postcode":"17850",
    "addr:street":"Carr Font",
    "iso:country":"ES",
    "sg:address":"Carr Font, 1",
    "sg:city":"Besalu",
    "sg:orig_category":"Centros Empresariales",
    "sg:phone":"+34 972 59 07 80",
    "sg:postcode":"17850",
    "sg:province":"Girona",
    "wof:name":"Insta%acions Quintana Prat S.l.",
    "wof:placetype":"venue"
},
  "geometry": {"coordinates":[2.6986780167,42.1977920532],"type":"Point"}
}