{
  "type": "Feature",
  "properties": {
    "iso:country":"ES",
    "sg:address":"Calle de Ca\u00d1o, 35",
    "sg:city":"Calvarrasa Arriba",
    "sg:orig_category":"Cerrajer\u00cda, Ferrallista",
    "sg:phone":"+34 923 37 33 59",
    "sg:postcode":"37191",
    "sg:province":"Salamanca",
    "wof:name":"Paz Rodero Bibiano",
    "wof:placetype":"venue"
},
  "geometry": {"coordinates":[-5.5925502777,40.9076690674],"type":"Point"}
}