{
  "type": "Feature",
  "properties": {
    "addr:full":"Calle de Joaquin Pascual Fernandez, S/n Caudete Albacete 02660",
    "addr:housenumber":"s / n",
    "addr:postcode":"02660",
    "addr:street":"Calle De Joaquin Pascual Fernandez",
    "iso:country":"ES",
    "sg:address":"Calle de Joaquin Pascual Fernandez, S/n",
    "sg:city":"Caudete",
    "sg:orig_category":"Supermercados Y Hipermercados",
    "sg:phone":"+34 965 82 56 67",
    "sg:postcode":"02660",
    "sg:province":"Albacete",
    "sg:website":"www.mercadona.es",
    "wof:name":"Mercadona S.a.",
    "wof:placetype":"venue"
},
  "geometry": {"coordinates":[-0.9854040146,38.7081184387],"type":"Point"}
}