{
  "type": "Feature",
  "properties": {
    "addr:full":"Avda Zodiaco, S/n Alacant Alicante 03006",
    "addr:housenumber":"s / n",
    "addr:postcode":"03006",
    "addr:street":"Avda Zodiaco",
    "iso:country":"ES",
    "sg:address":"Avda Zodiaco, S/n",
    "sg:city":"Alacant",
    "sg:orig_category":"Aceros Inoxidables",
    "sg:phone":"+34 965 10 78 04",
    "sg:postcode":"03006",
    "sg:province":"Alicante",
    "wof:name":"Inoxcenter S.a.",
    "wof:placetype":"venue"
},
  "geometry": {"coordinates":[-0.5238490105,38.3478393555],"type":"Point"}
}