{
  "type": "Feature",
  "properties": {
    "addr:full":"Santa Marina Kalea, 16 Zarautz Guip\u00f9zcoa 20800",
    "addr:housenumber":"16",
    "addr:postcode":"20800",
    "addr:street":"Santa Marina Kalea;Guipu\u0300Zcoa",
    "iso:country":"ES",
    "sg:address":"Santa Marina Kalea, 16",
    "sg:city":"Zarautz",
    "sg:orig_category":"Supermercados Y Hipermercados",
    "sg:phone":"+34 943 13 05 40",
    "sg:postcode":"20800",
    "sg:province":"Guip\u00f9zcoa",
    "wof:name":"Eroski Sociedad Cooperativa",
    "wof:placetype":"venue"
},
  "geometry": {"coordinates":[-2.1767790318,43.285118103],"type":"Point"}
}