{
  "type": "Feature",
  "properties": {
    "addr:full":"Carrer de Verge Del Cami, 19 Cambrils Tarragona 43850",
    "addr:housenumber":"19",
    "addr:postcode":"43850",
    "addr:street":"Carrer De Verge Del Cami",
    "iso:country":"ES",
    "sg:address":"Carrer de Verge Del Cami, 19",
    "sg:city":"Cambrils",
    "sg:orig_category":"Peluqueros: De Se\u00d1oras",
    "sg:phone":"+34 977 79 15 18",
    "sg:postcode":"43850",
    "sg:province":"Tarragona",
    "wof:name":"Princep Cros Jaime",
    "wof:placetype":"venue"
},
  "geometry": {"coordinates":[1.0515229702,41.0724487305],"type":"Point"}
}