{
  "type": "Feature",
  "properties": {
    "addr:full":"Calle de Daganzo, 15 Madrid Madrid 28002",
    "addr:housenumber":"15",
    "addr:postcode":"madrid;28002",
    "addr:street":"Calle De Daganzo",
    "iso:country":"ES",
    "sg:address":"Calle de Daganzo, 15",
    "sg:city":"Madrid",
    "sg:orig_category":"Cursos Particulares, Asistencia Escolar",
    "sg:phone":"+34 915 19 33 01",
    "sg:postcode":"28002",
    "sg:province":"Madrid",
    "wof:name":"Mu\u00f1oz Martin Josefa",
    "wof:placetype":"venue"
},
  "geometry": {"coordinates":[-3.6724162102,40.4418983459],"type":"Point"}
}