{
  "type": "Feature",
  "properties": {
    "iso:country":"ES",
    "sg:address":"Calle de Emilio Baro, 5",
    "sg:city":"Valencia",
    "sg:orig_category":"Quincaller\u00cda (al Por Menor)",
    "sg:phone":"+34 963 93 02 30",
    "sg:postcode":"46020",
    "sg:province":"Valencia",
    "wof:name":"Ferreteria Aurelio S.l",
    "wof:placetype":"venue"
},
  "geometry": {"coordinates":[-0.3626219928,39.4844970703],"type":"Point"}
}