{
  "type": "Feature",
  "properties": {
    "addr:full":"Carrer de Demestre, 15 Barcelona Barcelona 08017",
    "addr:housenumber":"15",
    "addr:postcode":"08017",
    "addr:street":"Carrer De Demestre",
    "iso:country":"ES",
    "sg:address":"Carrer de Demestre, 15",
    "sg:city":"Barcelona",
    "sg:orig_category":"Tintes (fabricaci\u00d3n, Al Por Mayor)",
    "sg:phone":"+34 932 03 51 59",
    "sg:postcode":"08017",
    "sg:province":"Barcelona",
    "sg:website":"www.solucion.net/aserp/asociacion/grupo.htm",
    "wof:name":"Conduraru  Gigel",
    "wof:placetype":"venue"
},
  "geometry": {"coordinates":[2.1268420219,41.3987846375],"type":"Point"}
}