{
  "type": "Feature",
  "properties": {
    "addr:full":"Avgd Castello (de), 39 Atzeneta Maestrat Castell\u00f3n 12132",
    "addr:postcode":"12132",
    "addr:street":"Castello\u0301N",
    "iso:country":"ES",
    "sg:address":"Avgd Castello (de), 39",
    "sg:city":"Atzeneta Maestrat",
    "sg:orig_category":"Cooperativas Agr\u00cdcolas",
    "sg:phone":"+34 964 37 01 47",
    "sg:postcode":"12132",
    "sg:province":"Castell\u00f3n",
    "wof:name":"Cooperativa Agricola San Bartolome",
    "wof:placetype":"venue"
},
  "geometry": {"coordinates":[-0.1707289964,40.2165145874],"type":"Point"}
}