{
  "type": "Feature",
  "properties": {
    "iso:country":"ES",
    "sg:address":"Calle de Arenal, 4",
    "sg:city":"Palacios Y Villafranca",
    "sg:orig_category":"Centros De Coordinaci\u00d3n",
    "sg:phone":"+34 955 81 08 65",
    "sg:postcode":"41720",
    "sg:province":"Sevilla",
    "wof:name":"Sanchez-barrios Asesores S.l.",
    "wof:placetype":"venue"
},
  "geometry": {"coordinates":[-5.9277729988,37.1602554321],"type":"Point"}
}