{
  "type": "Feature",
  "properties": {
    "addr:full":"Calle de Hinojal, S/n Madrid Madrid 28037",
    "addr:housenumber":"s / n",
    "addr:postcode":"28037",
    "addr:street":"Calle De Hinojal",
    "iso:country":"ES",
    "sg:address":"Calle de Hinojal, S/n",
    "sg:city":"Madrid",
    "sg:orig_category":"Internados & Ense\u00d1anza Privada",
    "sg:phone":"+34 913 20 26 07",
    "sg:postcode":"28037",
    "sg:province":"Madrid",
    "wof:name":"Religiosas De La Inmaculada",
    "wof:placetype":"venue"
},
  "geometry": {"coordinates":[-3.6131789684,40.4320487976],"type":"Point"}
}