{
  "type": "Feature",
  "properties": {
    "iso:country":"ES",
    "sg:address":"Carrer de Jacquard, 26",
    "sg:city":"Barcelona",
    "sg:orig_category":"Ense\u00d1ante, Direcci\u00d3n",
    "sg:phone":"+34 934 90 60 19",
    "sg:postcode":"08028",
    "sg:province":"Barcelona",
    "wof:name":"Aguilar De La Parte Carlos",
    "wof:placetype":"venue"
},
  "geometry": {"coordinates":[2.1341187954,41.3781585693],"type":"Point"}
}