{
  "type": "Feature",
  "properties": {
    "iso:country":"ES",
    "sg:address":"Camino Viejo Simancas, Km. 0001,5",
    "sg:city":"Valladolid",
    "sg:orig_category":"Promotores Constructores",
    "sg:phone":"+34 983 24 71 86",
    "sg:postcode":"47008",
    "sg:province":"Valladolid",
    "wof:name":"Begar Construcciones Y Contratas S.a.",
    "wof:placetype":"venue"
},
  "geometry": {"coordinates":[-4.7443699837,41.6278991699],"type":"Point"}
}