{
  "type": "Feature",
  "properties": {
    "iso:country":"ES",
    "sg:address":"Calle de Salvia, 8",
    "sg:city":"Badajoz",
    "sg:orig_category":"Asociaciones Humanitarias, De Cooperaci\u00d3n, De Acci\u00d3n Social",
    "sg:phone":"+34 924 26 31 78",
    "sg:postcode":"06010",
    "sg:province":"Badajoz",
    "wof:name":"Asociacion De Hogares Funcionales Asociados.hofa",
    "wof:placetype":"venue"
},
  "geometry": {"coordinates":[-6.9698066711,38.8657798767],"type":"Point"}
}