{
  "type": "Feature",
  "properties": {
    "addr:full":"Avda Aurora, 28 Malaga M\u00e1laga 29002",
    "addr:housenumber":"28",
    "addr:postcode":"29002",
    "addr:street":"Avda Aurora;Ma\u0301Laga",
    "iso:country":"ES",
    "sg:address":"Avda Aurora, 28",
    "sg:city":"Malaga",
    "sg:orig_category":"Artes Gr\u00c1ficas, Artes Pl\u00c1sticas (curso)",
    "sg:phone":"+34 952 33 00 10",
    "sg:postcode":"29002",
    "sg:province":"M\u00e1laga",
    "wof:name":"Inversiones Gatellco 3 S.l.",
    "wof:placetype":"venue"
},
  "geometry": {"coordinates":[-4.4321522713,36.7164230347],"type":"Point"}
}