{
  "type": "Feature",
  "properties": {
    "iso:country":"ES",
    "sg:address":"Calle de Fray Albino, 3",
    "sg:city":"Priego Cordoba",
    "sg:orig_category":"Abogados",
    "sg:phone":"+34 957 70 05 70",
    "sg:postcode":"14800",
    "sg:province":"C\u00f3rdoba",
    "wof:name":"Alferez Molina Manuel Maria",
    "wof:placetype":"venue"
},
  "geometry": {"coordinates":[-4.1951613426,37.4363861084],"type":"Point"}
}