{
  "type": "Feature",
  "properties": {
    "iso:country":"ES",
    "sg:address":"Calle de Iturribide, 4",
    "sg:city":"Bilbao",
    "sg:orig_category":"Caf\u00c9s, Bares, Cervecer\u00cdas",
    "sg:phone":"+34 944 33 38 78",
    "sg:postcode":"48006",
    "sg:province":"Vizcaya",
    "wof:name":"Mari Carmen Guisado Diaz",
    "wof:placetype":"venue"
},
  "geometry": {"coordinates":[-2.9212429523,43.2581367493],"type":"Point"}
}