{
  "type": "Feature",
  "properties": {
    "addr:full":"Calle de Eduardo Torroja, 33 Leganes Madrid 28914",
    "addr:housenumber":"33",
    "addr:postcode":"28914",
    "addr:street":"Calle De Eduardo Torroja",
    "iso:country":"ES",
    "sg:address":"Calle de Eduardo Torroja, 33",
    "sg:city":"Leganes",
    "sg:orig_category":"Alimentaci\u00d3n General (al Por Menor)",
    "sg:phone":"+34 916 85 01 70",
    "sg:postcode":"28914",
    "sg:province":"Madrid",
    "wof:name":"Disma Distribucion S.a.",
    "wof:placetype":"venue"
},
  "geometry": {"coordinates":[-3.7353730202,40.3293533325],"type":"Point"}
}