{
  "type": "Feature",
  "properties": {
    "addr:full":"C/ Ample, 8 Elche Alicante 03202",
    "addr:housenumber":"8",
    "addr:postcode":"03202",
    "addr:street":"C / Ample",
    "iso:country":"ES",
    "sg:address":"C/ Ample, 8",
    "sg:city":"Elche",
    "sg:orig_category":"Lencer\u00cda Femenina, Corseter\u00cda, Trajes De Ba\u00d1o (al Por Menor)",
    "sg:phone":"+34 965 45 98 19",
    "sg:postcode":"03202",
    "sg:province":"Alicante",
    "wof:name":"Escandell Martinez Maria Carmen",
    "wof:placetype":"venue"
},
  "geometry": {"coordinates":[-0.696047008,38.2665214539],"type":"Point"}
}