{
  "type": "Feature",
  "properties": {
    "addr:full":"Pla\u00c7 Solidaritat (de La), 7 Blanes Girona 17300",
    "addr:postcode":"17300",
    "iso:country":"ES",
    "sg:address":"Pla\u00c7 Solidaritat (de La), 7",
    "sg:city":"Blanes",
    "sg:orig_category":"\u00d3ptica: Instrumentos (fabricaci\u00d3n)",
    "sg:phone":"+34 972 33 68 79",
    "sg:postcode":"17300",
    "sg:province":"Girona",
    "wof:name":"Inverlents S.l.",
    "wof:placetype":"venue"
},
  "geometry": {"coordinates":[2.7906849384,41.6724243164],"type":"Point"}
}