{
  "type": "Feature",
  "properties": {
    "addr:full":"Trav De Gracia, 207 Barcelona Barcelona 08012",
    "addr:housenumber":"207",
    "addr:postcode":"08012",
    "addr:street":"Trav De Gracia",
    "iso:country":"ES",
    "sg:address":"Trav De Gracia, 207",
    "sg:city":"Barcelona",
    "sg:orig_category":"Perfumer\u00cda (al Por Menor)",
    "sg:phone":"+34 932 13 56 88",
    "sg:postcode":"08012",
    "sg:province":"Barcelona",
    "wof:name":"Rosello Ortigas Josep",
    "wof:placetype":"venue"
},
  "geometry": {"coordinates":[2.1602458954,41.4029350281],"type":"Point"}
}