{
  "type": "Feature",
  "properties": {
    "addr:full":"Carr Constitucio, De Sa, 18 Andratx Islas Baleares 07150",
    "addr:housenumber":"18",
    "addr:postcode":"07150",
    "addr:street":"Carr Constitucio De Sa",
    "iso:country":"ES",
    "sg:address":"Carr Constitucio, De Sa, 18",
    "sg:city":"Andratx",
    "sg:orig_category":"Reposter\u00cdas",
    "sg:phone":"+34 971 23 63 86",
    "sg:postcode":"07150",
    "sg:province":"Islas Baleares",
    "wof:name":"La Consigna De Andratx S.l.",
    "wof:placetype":"venue"
},
  "geometry": {"coordinates":[2.4207279682,39.5735168457],"type":"Point"}
}