{
  "type": "Feature",
  "properties": {
    "addr:full":"Cami Riereta, 32 Hospitalet Llobregat Barcelona 08901",
    "addr:housenumber":"32",
    "addr:postcode":"08901",
    "addr:street":"Riereta",
    "iso:country":"ES",
    "sg:address":"Cami Riereta, 32",
    "sg:city":"Hospitalet Llobregat",
    "sg:orig_category":"Electricidad: Equipos Industriales, Componentes (fabricaci\u00d3n)",
    "sg:phone":"+34 933 38 76 36",
    "sg:postcode":"08901",
    "sg:province":"Barcelona",
    "wof:name":"Inmobiliaria Clotas S.l.",
    "wof:placetype":"venue"
},
  "geometry": {"coordinates":[2.0993309021,41.3552856445],"type":"Point"}
}