{
  "type": "Feature",
  "properties": {
    "addr:full":"Calle de San Marcos, 35 Miajadas C\u00e1ceres 10100",
    "addr:housenumber":"35",
    "addr:postcode":"10100",
    "addr:street":"Calle De San Marcos;Ca\u0301Ceres",
    "iso:country":"ES",
    "sg:address":"Calle de San Marcos, 35",
    "sg:city":"Miajadas",
    "sg:orig_category":"Distribuci\u00d3n De Petr\u00d3leo Y Derivados",
    "sg:phone":"+34 927 34 86 98",
    "sg:postcode":"10100",
    "sg:province":"C\u00e1ceres",
    "wof:name":"Casoleos Comarca De Trujillo S.l.",
    "wof:placetype":"venue"
},
  "geometry": {"coordinates":[-5.9117941856,39.1531867981],"type":"Point"}
}