{
  "type": "Feature",
  "properties": {
    "addr:full":"Carr Congost, 6 Pobla Segur Lleida 25500",
    "addr:housenumber":"6",
    "addr:postcode":"25500",
    "addr:street":"Carr Congost",
    "iso:country":"ES",
    "sg:address":"Carr Congost, 6",
    "sg:city":"Pobla Segur",
    "sg:orig_category":"Alimentaci\u00d3n General (al Por Menor)",
    "sg:phone":"+34 973 68 02 54",
    "sg:postcode":"25500",
    "sg:province":"Lleida",
    "wof:name":"Prio Cardona Jose",
    "wof:placetype":"venue"
},
  "geometry": {"coordinates":[0.9664350152,42.2486915588],"type":"Point"}
}