{
  "type": "Feature",
  "properties": {
    "addr:full":"Cami Font Del Pic, S/n S. Hilari Sacalm Girona 17403",
    "addr:housenumber":"s",
    "addr:postcode":"17403",
    "addr:street":"/ N S.",
    "iso:country":"ES",
    "sg:address":"Cami Font Del Pic, S/n",
    "sg:city":"S. Hilari Sacalm",
    "sg:orig_category":"Arquitectos",
    "sg:phone":"+34 972 86 88 09",
    "sg:postcode":"17403",
    "sg:province":"Girona",
    "wof:name":"Pacheco Perez Carlos",
    "wof:placetype":"venue"
},
  "geometry": {"coordinates":[2.5054121017,41.8780632019],"type":"Point"}
}