{
  "type": "Feature",
  "properties": {
    "addr:full":"Calle de Jose Franchy Roca, 70 Palmas De Gran Canaria Las Palmas 35007",
    "addr:housenumber":"70",
    "addr:postcode":"35007",
    "addr:street":"Calle De Jose Franchy Roca",
    "iso:country":"ES",
    "sg:address":"Calle de Jose Franchy Roca, 70",
    "sg:city":"Palmas De Gran Canaria",
    "sg:orig_category":"Arquitectos",
    "sg:phone":"+34 928 27 12 47",
    "sg:postcode":"35007",
    "sg:province":"Las Palmas",
    "wof:name":"Cabrera Valido Arquitectos S.l.",
    "wof:placetype":"venue"
},
  "geometry": {"coordinates":[-15.4359397888,28.1385440826],"type":"Point"}
}