{
  "type": "Feature",
  "properties": {
    "addr:full":"Carrer de Irlanda, 29 Mataro Barcelona 08303",
    "addr:housenumber":"29",
    "addr:postcode":"08303",
    "addr:street":"Carrer De Irlanda",
    "iso:country":"ES",
    "sg:address":"Carrer de Irlanda, 29",
    "sg:city":"Mataro",
    "sg:orig_category":"Venta, Instalaci\u00d3n De Calefacci\u00d3n",
    "sg:phone":"+34 937 57 25 68",
    "sg:postcode":"08303",
    "sg:province":"Barcelona",
    "wof:name":"Instalaciones Morillas E Hijos S.l.",
    "wof:placetype":"venue"
},
  "geometry": {"coordinates":[2.4296250343,41.5467567444],"type":"Point"}
}