{
  "type": "Feature",
  "properties": {
    "iso:country":"ES",
    "sg:address":"Calle de San Vicente, S/n",
    "sg:city":"Villar Arzobispo",
    "sg:orig_category":"Discapacitados",
    "sg:phone":"+34 962 72 00 68",
    "sg:postcode":"46170",
    "sg:province":"Valencia",
    "wof:name":"Residencia Las Suertes",
    "wof:placetype":"venue"
},
  "geometry": {"coordinates":[-0.8257690072,39.7308006287],"type":"Point"}
}