{
  "type": "Feature",
  "properties": {
    "iso:country":"ES",
    "sg:address":"Plaz Mayor, 3",
    "sg:city":"Becerril Campos",
    "sg:orig_category":"Farmacias",
    "sg:phone":"+34 979 83 32 18",
    "sg:postcode":"34310",
    "sg:province":"Palencia",
    "wof:name":"Gonzalez Sanchez Maria Antonia",
    "wof:placetype":"venue"
},
  "geometry": {"coordinates":[-4.5726118088,42.15883255],"type":"Point"}
}