{
  "type": "Feature",
  "properties": {
    "iso:country":"ES",
    "sg:address":"Meloxo, 74",
    "sg:city":"Meloxo",
    "sg:orig_category":"Estudios Y Construcci\u00d3n De Acuarios Y Viveros",
    "sg:phone":"+34 986 73 13 24",
    "sg:postcode":"36989",
    "sg:province":"Pontevedra",
    "wof:name":"Mejilloneras Fontoira E Hijos S.l.",
    "wof:placetype":"venue"
},
  "geometry": {"coordinates":[-8.8799791336,42.4873313904],"type":"Point"}
}