{
  "type": "Feature",
  "properties": {
    "iso:country":"ES",
    "sg:address":"Calle de Camino De Malaga, 40",
    "sg:city":"Velez-malaga",
    "sg:orig_category":"Complementos De Vestir (al Por Menor)",
    "sg:phone":"+34 952 50 41 04",
    "sg:postcode":"29700",
    "sg:province":"M\u00e1laga",
    "wof:name":"Ariana Modas S.l.",
    "wof:placetype":"venue"
},
  "geometry": {"coordinates":[-4.1033024788,36.7782974243],"type":"Point"}
}