{
  "type": "Feature",
  "properties": {
    "iso:country":"ES",
    "sg:address":"Calle de Hospital, 2",
    "sg:city":"Olmedo",
    "sg:orig_category":"Alimentaci\u00d3n General (al Por Menor)",
    "sg:phone":"+34 983 60 10 14",
    "sg:postcode":"47410",
    "sg:province":"Valladolid",
    "wof:name":"J.j. Hijos 99 S.l.",
    "wof:placetype":"venue"
},
  "geometry": {"coordinates":[-4.6851201057,41.2871170044],"type":"Point"}
}