{
  "type": "Feature",
  "properties": {
    "addr:full":"Calle de Puerto De Cerredo, 20 Gijon Asturias 33207",
    "addr:housenumber":"20",
    "addr:postcode":"33207",
    "addr:street":"Calle De Puerto De Cerredo",
    "iso:country":"ES",
    "sg:address":"Calle de Puerto De Cerredo, 20",
    "sg:city":"Gijon",
    "sg:orig_category":"Reposter\u00cdas",
    "sg:phone":"+34 985 14 32 33",
    "sg:postcode":"33207",
    "sg:province":"Asturias",
    "wof:name":"Mu\u00f1oz Rodriguez Jose Manuel",
    "wof:placetype":"venue"
},
  "geometry": {"coordinates":[-5.677532196,43.53358078],"type":"Point"}
}