{
  "type": "Feature",
  "properties": {
    "addr:full":"Calle de Cid Campeador, S/n Linares Ja\u00e9n 23700",
    "addr:housenumber":"s / n",
    "addr:postcode":"23700",
    "addr:street":"Calle De Cid Campeador;Jae\u0301N",
    "iso:country":"ES",
    "sg:address":"Calle de Cid Campeador, S/n",
    "sg:city":"Linares",
    "sg:orig_category":"Reparaci\u00d3n, Mantenimiento De Calefacciones",
    "sg:phone":"+34 953 69 08 47",
    "sg:postcode":"23700",
    "sg:province":"Ja\u00e9n",
    "wof:name":"Diaz Vera Isaac",
    "wof:placetype":"venue"
},
  "geometry": {"coordinates":[-3.6397790909,38.0920257568],"type":"Point"}
}