{
  "type": "Feature",
  "properties": {
    "addr:full":"Carrer de Tous I Maroto, 4 Palma Islas Baleares 07001",
    "addr:housenumber":"4",
    "addr:postcode":"07001",
    "addr:street":"Carrer De Tous I Maroto",
    "iso:country":"ES",
    "sg:address":"Carrer de Tous I Maroto, 4",
    "sg:city":"Palma",
    "sg:orig_category":"Cajas De Ahorro",
    "sg:phone":"+34 971 22 90 08",
    "sg:postcode":"07001",
    "sg:province":"Islas Baleares",
    "sg:website":"www.bancaja.es",
    "wof:name":"Caja De Ahorros De Valencia Castellon Y Alicante",
    "wof:placetype":"venue"
},
  "geometry": {"coordinates":[2.6479790211,39.5694274902],"type":"Point"}
}