{
  "type": "Feature",
  "properties": {
    "addr:full":"Calle de Arquitecto Morell, 27 Alacant Alicante 03003",
    "addr:housenumber":"27",
    "addr:postcode":"03003",
    "addr:street":"Calle De Arquitecto Morell",
    "iso:country":"ES",
    "sg:address":"Calle de Arquitecto Morell, 27",
    "sg:city":"Alacant",
    "sg:orig_category":"Ropa Para Se\u00d1oras Y Caballeros (al Por Menor)",
    "sg:phone":"+34 965 92 20 31",
    "sg:postcode":"03003",
    "sg:province":"Alicante",
    "sg:website":"www.lacoste.es",
    "wof:name":"Soler Aracil Jose Salvador",
    "wof:placetype":"venue"
},
  "geometry": {"coordinates":[-0.4933417141,38.3417015076],"type":"Point"}
}