{
  "type": "Feature",
  "properties": {
    "addr:full":"Pla\u00c7 Sant Joan, 10 Lleida Lleida 25007",
    "addr:housenumber":"10",
    "addr:postcode":"25007",
    "addr:street":"Sant Joan",
    "iso:country":"ES",
    "sg:address":"Pla\u00c7 Sant Joan, 10",
    "sg:city":"Lleida",
    "sg:orig_category":"Abogados",
    "sg:phone":"+34 973 22 89 98",
    "sg:postcode":"25007",
    "sg:province":"Lleida",
    "wof:name":"Badal Ribes Neus",
    "wof:placetype":"venue"
},
  "geometry": {"coordinates":[0.6310768723,41.6181678772],"type":"Point"}
}