{
  "type": "Feature",
  "properties": {
    "addr:full":"Calle de Cassola, 1 Aguilas Murcia 30880",
    "addr:housenumber":"1",
    "addr:postcode":"30880",
    "addr:street":"Calle De Cassola",
    "iso:country":"ES",
    "sg:address":"Calle de Cassola, 1",
    "sg:city":"Aguilas",
    "sg:orig_category":"Pod\u00d3logos: Pedicuros",
    "sg:phone":"+34 968 44 82 53",
    "sg:postcode":"30880",
    "sg:province":"Murcia",
    "wof:name":"Montalban Oliver Catalina",
    "wof:placetype":"venue"
},
  "geometry": {"coordinates":[-1.5826480389,37.4037437439],"type":"Point"}
}