{
  "type": "Feature",
  "properties": {
    "addr:full":"Redonda, S/n Quintanavides Burgos 09292",
    "addr:postcode":"09292",
    "addr:street":"Redonda S / N Quintanavides",
    "iso:country":"ES",
    "sg:address":"Redonda, S/n",
    "sg:city":"Quintanavides",
    "sg:orig_category":"Distribuci\u00d3n De Petr\u00d3leo Y Derivados",
    "sg:phone":"+34 947 59 26 26",
    "sg:postcode":"09292",
    "sg:province":"Burgos",
    "sg:website":"www.cepsa.es",
    "wof:name":"Cedipsa Compa\u00d1ia Espa\u00d1ola Distribuidora De Petroleos S.a.",
    "wof:placetype":"venue"
},
  "geometry": {"coordinates":[-3.4358489513,42.4431800842],"type":"Point"}
}