{
  "type": "Feature",
  "properties": {
    "iso:country":"ES",
    "sg:address":"Carrer de Asensi Vega, 1",
    "sg:city":"Caldes Montbui",
    "sg:orig_category":"Electrodom\u00c9sticos (al Por Menor)",
    "sg:phone":"+34 938 65 25 12",
    "sg:postcode":"08140",
    "sg:province":"Barcelona",
    "wof:name":"Iba\u00f1ez Asensio Mercedes",
    "wof:placetype":"venue"
},
  "geometry": {"coordinates":[2.1629788876,41.6324577332],"type":"Point"}
}