{
  "type": "Feature",
  "properties": {
    "iso:country":"ES",
    "sg:address":"Pl Sant Ramon, 17",
    "sg:city":"Cerdanyola Valles",
    "sg:orig_category":"M\u00c9dicos: Estomatolog\u00cda",
    "sg:phone":"+34 936 92 51 08",
    "sg:postcode":"08290",
    "sg:province":"Barcelona",
    "wof:name":"Aristoy Lopez Eduardo Oscar",
    "wof:placetype":"venue"
},
  "geometry": {"coordinates":[2.136431694,41.4889183044],"type":"Point"}
}