{
  "type": "Feature",
  "properties": {
    "addr:full":"Cno. Caba\u00f1as, S/n Oca\u00f1a Toledo 45300",
    "addr:postcode":"45300",
    "addr:street":"Caban\u0303As S / N Ocan\u0303A",
    "iso:country":"ES",
    "sg:address":"Cno. Caba\u00f1as, S/n",
    "sg:city":"Oca\u00f1a",
    "sg:orig_category":"Chapister\u00cda",
    "sg:phone":"+34 925 13 00 64",
    "sg:postcode":"45300",
    "sg:province":"Toledo",
    "wof:name":"Talleres Tizon Y Chele S.a.l.",
    "wof:placetype":"venue"
},
  "geometry": {"coordinates":[-3.5018639565,39.9540939331],"type":"Point"}
}