{
  "type": "Feature",
  "properties": {
    "addr:full":"Calle de Vilaragut, 7 Valencia Valencia 46002",
    "addr:housenumber":"7",
    "addr:postcode":"46002",
    "addr:street":"Calle De Vilaragut",
    "iso:country":"ES",
    "sg:address":"Calle de Vilaragut, 7",
    "sg:city":"Valencia",
    "sg:orig_category":"Confecci\u00d3n De Trajes Para Se\u00d1oras",
    "sg:phone":"+34 963 51 12 25",
    "sg:postcode":"46002",
    "sg:province":"Valencia",
    "wof:name":"Montoro Blasco Patricia",
    "wof:placetype":"venue"
},
  "geometry": {"coordinates":[-0.3747366965,39.4717292786],"type":"Point"}
}