{
  "type": "Feature",
  "properties": {
    "iso:country":"ES",
    "sg:address":"Calle de Antonia Lancha, 15",
    "sg:city":"Madrid",
    "sg:orig_category":"Peluqueros: De Se\u00d1oras",
    "sg:phone":"+34 915 60 60 16",
    "sg:postcode":"28019",
    "sg:province":"Madrid",
    "wof:name":"Rodriguez Portilla Jose Alberto",
    "wof:placetype":"venue"
},
  "geometry": {"coordinates":[-3.7204298973,40.3856811523],"type":"Point"}
}