{
  "type": "Feature",
  "properties": {
    "iso:country":"ES",
    "sg:address":"Calle de Orihuela, 36",
    "sg:city":"Albatera",
    "sg:orig_category":"Promotores Constructores",
    "sg:phone":"+34 965 48 52 34",
    "sg:postcode":"03340",
    "sg:province":"Alicante",
    "wof:name":"Construcciones Alba Prima S.l.",
    "wof:placetype":"venue"
},
  "geometry": {"coordinates":[-0.8710989952,38.1773872375],"type":"Point"}
}