{
  "type": "Feature",
  "properties": {
    "iso:country":"ES",
    "sg:address":"Carrer de Creu Coberta, 39",
    "sg:city":"Barcelona",
    "sg:orig_category":"Colchones (fabricaci\u00d3n, Al Por Mayor, Al Por Menor)",
    "sg:phone":"+34 934 23 46 06",
    "sg:postcode":"08014",
    "sg:province":"Barcelona",
    "sg:website":"www.miescaparate.com/c-castel",
    "wof:name":"Castel Reboredo Carmen",
    "wof:placetype":"venue"
},
  "geometry": {"coordinates":[2.1469049454,41.3750457764],"type":"Point"}
}