{
  "type": "Feature",
  "properties": {
    "iso:country":"ES",
    "sg:address":"Calle de Mayor, S/n",
    "sg:city":"Diego Alvaro",
    "sg:orig_category":"Negocio De Materiales De Construcci\u00d3n",
    "sg:phone":"+34 920 36 50 42",
    "sg:postcode":"05151",
    "sg:province":"\u00c1vila",
    "wof:name":"Mu\u00f1oz Jimenez Lorenzo",
    "wof:placetype":"venue"
},
  "geometry": {"coordinates":[-5.3245458603,40.6627883911],"type":"Point"}
}