{
  "type": "Feature",
  "properties": {
    "iso:country":"ES",
    "sg:address":"Calle de Ortiz Alfau Angel, 4",
    "sg:city":"Bilbao",
    "sg:orig_category":"Fabricaci\u00d3n De Muebles",
    "sg:phone":"+34 944 43 49 80",
    "sg:postcode":"48003",
    "sg:province":"Vizcaya",
    "wof:name":"Lauko Maibea S.l.",
    "wof:placetype":"venue"
},
  "geometry": {"coordinates":[-2.9301486015,43.2499580383],"type":"Point"}
}