{
  "type": "Feature",
  "properties": {
    "iso:country":"ES",
    "sg:address":"Calle de General Zuvillaga, 16",
    "sg:city":"Oviedo",
    "sg:orig_category":"Electrodom\u00c9sticos (al Por Menor)",
    "sg:phone":"+34 985 23 13 36",
    "sg:postcode":"33005",
    "sg:province":"Asturias",
    "wof:name":"Rodriguez Cachero Celestino",
    "wof:placetype":"venue"
},
  "geometry": {"coordinates":[-5.8578190804,43.3626747131],"type":"Point"}
}