{
  "type": "Feature",
  "properties": {
    "addr:full":"Calle de Fernando Guanarteme, 13 Cruce I Las Palmas 35110",
    "addr:housenumber":"13",
    "addr:postcode":"35110",
    "addr:street":"Calle De Fernando Guanarteme;I Las",
    "iso:country":"ES",
    "sg:address":"Calle de Fernando Guanarteme, 13",
    "sg:city":"Cruce I",
    "sg:orig_category":"Comercio De Piezas De Recambio Y De Accesorios De Veh\u00cdculos, Veh\u00cdculos Industriales",
    "sg:phone":"+34 928 79 51 21",
    "sg:postcode":"35110",
    "sg:province":"Las Palmas",
    "wof:name":"Autos Repuestos J. Suarez S.l.",
    "wof:placetype":"venue"
},
  "geometry": {"coordinates":[-15.4391145706,27.8562412262],"type":"Point"}
}