{
  "type": "Feature",
  "properties": {
    "iso:country":"ES",
    "sg:address":"Carr Miracle, 11",
    "sg:city":"Balaguer",
    "sg:orig_category":"Abogados",
    "sg:phone":"+34 973 45 14 02",
    "sg:postcode":"25600",
    "sg:province":"Lleida",
    "wof:name":"Serveis Juridics Rubinat S.c.p.",
    "wof:placetype":"venue"
},
  "geometry": {"coordinates":[0.8055559993,41.7889938354],"type":"Point"}
}