{
  "type": "Feature",
  "properties": {
    "addr:full":"Calle de Cirilo Montero, 3 Torrijos Toledo 45500",
    "addr:housenumber":"3",
    "addr:postcode":"45500",
    "addr:street":"Calle De Cirilo Montero",
    "iso:country":"ES",
    "sg:address":"Calle de Cirilo Montero, 3",
    "sg:city":"Torrijos",
    "sg:orig_category":"Arquitectos",
    "sg:phone":"+34 925 76 16 70",
    "sg:postcode":"45500",
    "sg:province":"Toledo",
    "wof:name":"Juan Antonio Garcia Carpio S.l.",
    "wof:placetype":"venue"
},
  "geometry": {"coordinates":[-4.2861480713,39.9798126221],"type":"Point"}
}