{
  "type": "Feature",
  "properties": {
    "iso:country":"ES",
    "sg:address":"Calle de San Vicente De Paul, 11",
    "sg:city":"Valencia",
    "sg:orig_category":"Lencer\u00cda Femenina, Corseter\u00cda, Trajes De Ba\u00d1o (al Por Menor)",
    "sg:phone":"+34 963 66 24 54",
    "sg:postcode":"46019",
    "sg:province":"Valencia",
    "wof:name":"Pi\u00f1ango Ripolles Maria Dolores",
    "wof:placetype":"venue"
},
  "geometry": {"coordinates":[-0.3706920147,39.4908866882],"type":"Point"}
}