{
  "type": "Feature",
  "properties": {
    "iso:country":"ES",
    "sg:address":"Calle de Diego De Leon, 15",
    "sg:city":"Madrid",
    "sg:orig_category":"Inmobiliaria (agencias)",
    "sg:phone":"+34 914 23 00 50",
    "sg:postcode":"28...",
    "sg:province":"Madrid",
    "sg:website":"www.gilmarinmobiliaria.com",
    "wof:name":"Consulting Inmobiliario Gilmar S.a.",
    "wof:placetype":"venue"
},
  "geometry": {"coordinates":[-3.6837491989,40.4349937439],"type":"Point"}
}