{
  "type": "Feature",
  "properties": {
    "iso:country":"ES",
    "sg:address":"Ctra Olesa, 240",
    "sg:city":"Terrassa",
    "sg:orig_category":"Distribuci\u00d3n De Petr\u00d3leo Y Derivados",
    "sg:phone":"+34 937 89 10 11",
    "sg:postcode":"08221",
    "sg:province":"Barcelona",
    "wof:name":"Agip Espa\u00d1a S.a.",
    "wof:placetype":"venue"
},
  "geometry": {"coordinates":[1.9920850992,41.5558929443],"type":"Point"}
}