{
  "type": "Feature",
  "properties": {
    "addr:full":"Calle de Dalmacio Garcia Izcara, 5 Cuenca Cuenca 16004",
    "addr:housenumber":"5",
    "addr:postcode":"16004",
    "addr:street":"Calle De Dalmacio Garcia Izcara",
    "iso:country":"ES",
    "sg:address":"Calle de Dalmacio Garcia Izcara, 5",
    "sg:city":"Cuenca",
    "sg:orig_category":"Almacenes Frigor\u00cdficos",
    "sg:phone":"+34 969 22 76 44",
    "sg:postcode":"16004",
    "sg:province":"Cuenca",
    "wof:name":"Cesar Y Gregorio Ramirez S.l.l.",
    "wof:placetype":"venue"
},
  "geometry": {"coordinates":[-2.1365633011,40.068901062],"type":"Point"}
}