{
  "type": "Feature",
  "properties": {
    "addr:full":"Calle de Penitencia, 2 Valladolid Valladolid 47011",
    "addr:housenumber":"2",
    "addr:postcode":"47011",
    "addr:street":"Calle De Penitencia",
    "iso:country":"ES",
    "sg:address":"Calle de Penitencia, 2",
    "sg:city":"Valladolid",
    "sg:orig_category":"Negocio De Materiales De Construcci\u00d3n",
    "sg:phone":"+34 983 25 16 49",
    "sg:postcode":"47011",
    "sg:province":"Valladolid",
    "wof:name":"Velasco Arranz Federico",
    "wof:placetype":"venue"
},
  "geometry": {"coordinates":[-4.7166280746,41.6605224609],"type":"Point"}
}