{
  "type": "Feature",
  "properties": {
    "iso:country":"ES",
    "sg:address":"Carr Sant Isidre, 6",
    "sg:city":"Casavells",
    "sg:orig_category":"Electricidad: Instaladores",
    "sg:phone":"+34 972 63 01 66",
    "sg:postcode":"17121",
    "sg:province":"Girona",
    "wof:name":"Bahi Masso Gumersindo",
    "wof:placetype":"venue"
},
  "geometry": {"coordinates":[3.0331468582,42.0002326965],"type":"Point"}
}