{
  "type": "Feature",
  "properties": {
    "addr:full":"Avda Europa (de), 2 Pinto Madrid 28320",
    "addr:housenumber":"2",
    "addr:postcode":"28320",
    "addr:street":"Avda Europa De;Pinto",
    "iso:country":"ES",
    "sg:address":"Avda Europa (de), 2",
    "sg:city":"Pinto",
    "sg:orig_category":"Cajas De Ahorro",
    "sg:phone":"+34 916 92 17 93",
    "sg:postcode":"28320",
    "sg:province":"Madrid",
    "wof:name":"Caja De Ahorros De Valencia Castellon Y Alicante",
    "wof:placetype":"venue"
},
  "geometry": {"coordinates":[-3.694879055,40.2486495972],"type":"Point"}
}