{
  "type": "Feature",
  "properties": {
    "iso:country":"ES",
    "sg:address":"El Carmen, 40",
    "sg:city":"Horcajo Santiago",
    "sg:orig_category":"Negocio De Materiales De Construcci\u00d3n",
    "sg:phone":"+34 969 12 70 73",
    "sg:postcode":"16410",
    "sg:province":"Cuenca",
    "wof:name":"Campanero Martinez Fernando",
    "wof:placetype":"venue"
},
  "geometry": {"coordinates":[-2.9966509342,39.8418273926],"type":"Point"}
}