{
  "type": "Feature",
  "properties": {
    "addr:full":"Calle de Roquetes, 21 Benasal Castell\u00f3n 12160",
    "addr:housenumber":"21",
    "addr:postcode":"12160",
    "addr:street":"Calle De Roquetes;Castello\u0301N",
    "iso:country":"ES",
    "sg:address":"Calle de Roquetes, 21",
    "sg:city":"Benasal",
    "sg:orig_category":"Molduras, Junquillos, Listones Y Molduras Perforadas",
    "sg:phone":"+34 964 43 10 59",
    "sg:postcode":"12160",
    "sg:province":"Castell\u00f3n",
    "wof:name":"Andreu Pallares Carlos",
    "wof:placetype":"venue"
},
  "geometry": {"coordinates":[-0.1411318034,40.3799743652],"type":"Point"}
}