{
  "type": "Feature",
  "properties": {
    "iso:country":"ES",
    "sg:address":"Calle de Vallespin, 3",
    "sg:city":"Avila",
    "sg:orig_category":"Ingenier\u00cda, Centros De Estudios (diversos)",
    "sg:phone":"+34 920 22 63 06",
    "sg:postcode":"05001",
    "sg:province":"\u00c1vila",
    "wof:name":"Rodriguez Tocino Francisco",
    "wof:placetype":"venue"
},
  "geometry": {"coordinates":[-4.7004718781,40.6563568115],"type":"Point"}
}