{
  "type": "Feature",
  "properties": {
    "addr:full":"Afores, S/n Ciutadilla Lleida 25341",
    "addr:housenumber":"s / n",
    "addr:postcode":"25341",
    "addr:street":"Afores",
    "iso:country":"ES",
    "sg:address":"Afores, S/n",
    "sg:city":"Ciutadilla",
    "sg:orig_category":"Centros De Educaci\u00d3n Especial",
    "sg:phone":"+34 973 30 33 36",
    "sg:postcode":"25341",
    "sg:province":"Lleida",
    "wof:name":"Ajuntament De Ciutadilla",
    "wof:placetype":"venue"
},
  "geometry": {"coordinates":[1.1371393204,41.5614471436],"type":"Point"}
}