{
  "type": "Feature",
  "properties": {
    "addr:full":"C/ Antoni Flores, 5 Elche Alicante 03202",
    "addr:housenumber":"5",
    "addr:postcode":"03202",
    "addr:street":"C / Antoni Flores",
    "iso:country":"ES",
    "sg:address":"C/ Antoni Flores, 5",
    "sg:city":"Elche",
    "sg:orig_category":"Abogados",
    "sg:phone":"+34 966 61 13 80",
    "sg:postcode":"03202",
    "sg:province":"Alicante",
    "wof:name":"Illice Abogadas Sc",
    "wof:placetype":"venue"
},
  "geometry": {"coordinates":[-0.694149971,38.2681274414],"type":"Point"}
}