{
  "type": "Feature",
  "properties": {
    "iso:country":"ES",
    "sg:address":"Plaz Monse\u00d1or Bocanegra, S/n",
    "sg:city":"Malaga",
    "sg:orig_category":"Papeler\u00cdas, Librer\u00cdas",
    "sg:phone":"+34 952 28 93 41",
    "sg:postcode":"29011",
    "sg:province":"M\u00e1laga",
    "wof:name":"Gonzalez Fernandez Juan",
    "wof:placetype":"venue"
},
  "geometry": {"coordinates":[-4.4336438179,36.7910690308],"type":"Point"}
}