{
  "type": "Feature",
  "properties": {
    "iso:country":"ES",
    "sg:address":"Carr Dato, 40",
    "sg:city":"Pobla",
    "sg:orig_category":"Frutas Y Legumbres Frescas (al Por Mayor)",
    "sg:phone":"+34 971 54 04 34",
    "sg:postcode":"07420",
    "sg:province":"Islas Baleares",
    "wof:name":"Frespi S.a.t Ba 08",
    "wof:placetype":"venue"
},
  "geometry": {"coordinates":[3.0273399353,39.7708282471],"type":"Point"}
}