{
  "type": "Feature",
  "properties": {
    "addr:full":"Psaj San Fernando, 2 Malaga M\u00e1laga 29002",
    "addr:housenumber":"2",
    "addr:postcode":"29002",
    "addr:street":"San Fernando;Ma\u0301Laga",
    "iso:country":"ES",
    "sg:address":"Psaj San Fernando, 2",
    "sg:city":"Malaga",
    "sg:orig_category":"Prot\u00c9sicos Dentales",
    "sg:phone":"+34 952 31 51 45",
    "sg:postcode":"29002",
    "sg:province":"M\u00e1laga",
    "wof:name":"Protesis Dental Mu\u00f1oz S.a.",
    "wof:placetype":"venue"
},
  "geometry": {"coordinates":[-4.4269142151,36.7137184143],"type":"Point"}
}