{
  "type": "Feature",
  "properties": {
    "addr:full":"Calle de Sebastian Arozena, 28 Santa Cruz Palma Santa Cruz De Tenerife 38700",
    "addr:housenumber":"28",
    "addr:postcode":"38700",
    "addr:street":"Calle De Sebastian Arozena",
    "iso:country":"ES",
    "sg:address":"Calle de Sebastian Arozena, 28",
    "sg:city":"Santa Cruz Palma",
    "sg:orig_category":"Mec\u00c1nico Del Autom\u00d3vil",
    "sg:phone":"+34 922 41 33 04",
    "sg:postcode":"38700",
    "sg:province":"Santa Cruz De Tenerife",
    "wof:name":"Todomecanica S.l.",
    "wof:placetype":"venue"
},
  "geometry": {"coordinates":[-17.7706794739,28.6780605316],"type":"Point"}
}