{
  "type": "Feature",
  "properties": {
    "addr:full":"Avda Juan Ramon Ramirez, 12 Roda Albacete 02630",
    "addr:housenumber":"12",
    "addr:postcode":"02630",
    "addr:street":"Avda Juan Ramon Ramirez",
    "iso:country":"ES",
    "sg:address":"Avda Juan Ramon Ramirez, 12",
    "sg:city":"Roda",
    "sg:orig_category":"Muebles, Minoristas",
    "sg:phone":"+34 967 44 15 63",
    "sg:postcode":"02630",
    "sg:province":"Albacete",
    "wof:name":"Bautista Simarro Rafael",
    "wof:placetype":"venue"
},
  "geometry": {"coordinates":[-2.155659914,39.202671051],"type":"Point"}
}