{
  "type": "Feature",
  "properties": {
    "iso:country":"ES",
    "sg:address":"Carrer de Bastio Sanoguera, 4",
    "sg:city":"Palma",
    "sg:orig_category":"Financiaci\u00d3n Y Cr\u00c9ditos",
    "sg:phone":"+34 971 71 12 87",
    "sg:postcode":"07002",
    "sg:province":"Islas Baleares",
    "wof:name":"Oliver Llado Francisco",
    "wof:placetype":"venue"
},
  "geometry": {"coordinates":[2.6541950703,39.5748100281],"type":"Point"}
}