{
  "type": "Feature",
  "properties": {
    "iso:country":"ES",
    "sg:address":"Urb Puerto Pino, 42",
    "sg:city":"Almeria",
    "sg:orig_category":"Doctores En Medicina",
    "sg:phone":"+34 950 23 47 10",
    "sg:postcode":"04007",
    "sg:province":"Almer\u00eda",
    "wof:name":"Clavero Farre Carlos",
    "wof:placetype":"venue"
},
  "geometry": {"coordinates":[-2.4139039516,36.8265609741],"type":"Point"}
}