{
  "type": "Feature",
  "properties": {
    "iso:country":"ES",
    "sg:address":"Pol. Polinasa, S/n",
    "sg:city":"Alcarras",
    "sg:orig_category":"Mec\u00c1nico Del Autom\u00d3vil",
    "sg:phone":"+34 973 79 52 75",
    "sg:postcode":"25180",
    "sg:province":"Lleida",
    "wof:name":"Talleres Autorapid S.l.",
    "wof:placetype":"venue"
},
  "geometry": {"coordinates":[0.5282099843,41.5634155273],"type":"Point"}
}