{
  "type": "Feature",
  "properties": {
    "addr:full":"Carr Alberes, 47 Blanes Girona 17300",
    "addr:housenumber":"47",
    "addr:postcode":"17300",
    "addr:street":"Carr Alberes",
    "iso:country":"ES",
    "sg:address":"Carr Alberes, 47",
    "sg:city":"Blanes",
    "sg:orig_category":"Ense\u00d1anza Industrial Y T\u00c9cnica",
    "sg:phone":"+34 972 35 21 33",
    "sg:postcode":"17300",
    "sg:province":"Girona",
    "wof:name":"Retamal Vila Raquel",
    "wof:placetype":"venue"
},
  "geometry": {"coordinates":[2.7906849384,41.6724243164],"type":"Point"}
}