{
  "type": "Feature",
  "properties": {
    "addr:full":"Rua Roma, 32 Roma Ourense 32930",
    "addr:housenumber":"32",
    "addr:postcode":"32930",
    "addr:street":"Rua Roma",
    "iso:country":"ES",
    "sg:address":"Rua Roma, 32",
    "sg:city":"Roma",
    "sg:orig_category":"Aguas (distribuci\u00d3n, Servicios)",
    "sg:phone":"+34 988 38 23 39",
    "sg:postcode":"32930",
    "sg:province":"Ourense",
    "wof:name":"Fernandez Gallego Teofilo",
    "wof:placetype":"venue"
},
  "geometry": {"coordinates":[-7.9522171021,42.3144187927],"type":"Point"}
}