{
  "type": "Feature",
  "properties": {
    "addr:full":"Avda Kansas City, 6 Sevilla Sevilla 41007",
    "addr:housenumber":"6",
    "addr:postcode":"41007",
    "addr:street":"Avda Kansas City",
    "iso:country":"ES",
    "sg:address":"Avda Kansas City, 6",
    "sg:city":"Sevilla",
    "sg:orig_category":"Alquiler De Veh\u00cdculos: Turismos Y Utilitarios",
    "sg:phone":"+34 954 57 36 45",
    "sg:postcode":"41007",
    "sg:province":"Sevilla",
    "sg:website":"www.recordrent.com",
    "wof:name":"Record Rent A Car S.a.",
    "wof:placetype":"venue"
},
  "geometry": {"coordinates":[-5.9724068642,37.3880157471],"type":"Point"}
}