{
  "type": "Feature",
  "properties": {
    "addr:full":"C/ Bons Aires, 24 Llucmajor Islas Baleares 07620",
    "addr:housenumber":"24",
    "addr:postcode":"07620",
    "addr:street":"C / Bons Aires",
    "iso:country":"ES",
    "sg:address":"C/ Bons Aires, 24",
    "sg:city":"Llucmajor",
    "sg:orig_category":"Ingenier\u00cda, Centros De Estudios (industria)",
    "sg:phone":"+34 971 66 08 14",
    "sg:postcode":"07620",
    "sg:province":"Islas Baleares",
    "wof:name":"Monserrat Salva Antonio",
    "wof:placetype":"venue"
},
  "geometry": {"coordinates":[2.8916819096,39.4897193909],"type":"Point"}
}