{
  "type": "Feature",
  "properties": {
    "addr:full":"Carrer de De Les Eres, 74 Castalla Alicante 03420",
    "addr:housenumber":"74",
    "addr:postcode":"03420",
    "addr:street":"Carrer De De Les Eres",
    "iso:country":"ES",
    "sg:address":"Carrer de De Les Eres, 74",
    "sg:city":"Castalla",
    "sg:orig_category":"Comercio, Reparaci\u00d3n De Motocicletas, Bicicletas Y Piezas Sueltas",
    "sg:phone":"+34 965 56 03 28",
    "sg:postcode":"03420",
    "sg:province":"Alicante",
    "wof:name":"Paya Bodi Antonio Pablo",
    "wof:placetype":"venue"
},
  "geometry": {"coordinates":[-0.6758319736,38.5918693542],"type":"Point"}
}