{
  "type": "Feature",
  "properties": {
    "iso:country":"ES",
    "sg:address":"Calle de Gran Via De Colon, 8",
    "sg:city":"Granada",
    "sg:orig_category":"Notarios",
    "sg:phone":"+34 958 22 42 62",
    "sg:postcode":"18010",
    "sg:province":"Granada",
    "wof:name":"Garcia-valdecasas Fernandez Alberto",
    "wof:placetype":"venue"
},
  "geometry": {"coordinates":[-3.5978634357,37.1764030457],"type":"Point"}
}