{
  "type": "Feature",
  "properties": {
    "addr:full":"Santiago, 10 Pontedeume La Coru\u00f1a 15600",
    "addr:housenumber":"10",
    "addr:postcode":"15600",
    "addr:street":"Santiago;La Corun\u0303A",
    "iso:country":"ES",
    "sg:address":"Santiago, 10",
    "sg:city":"Pontedeume",
    "sg:orig_category":"Panader\u00cdas, Panader\u00cdas",
    "sg:phone":"+34 981 43 15 03",
    "sg:postcode":"15600",
    "sg:province":"La Coru\u00f1a",
    "wof:name":"Cabana Diaz Juan",
    "wof:placetype":"venue"
},
  "geometry": {"coordinates":[-8.1704874039,43.4068832397],"type":"Point"}
}