{
  "type": "Feature",
  "properties": {
    "addr:full":"Calle de Alonso Mingo, 46 Sevilla Sevilla 41014",
    "addr:housenumber":"46",
    "addr:postcode":"41014",
    "addr:street":"Calle De Alonso Mingo",
    "iso:country":"ES",
    "sg:address":"Calle de Alonso Mingo, 46",
    "sg:city":"Sevilla",
    "sg:orig_category":"Peluquer\u00cdas, Peluquer\u00cda Mixta",
    "sg:phone":"+34 954 69 22 86",
    "sg:postcode":"41014",
    "sg:province":"Sevilla",
    "wof:name":"Salvatierra Rivera Alberto",
    "wof:placetype":"venue"
},
  "geometry": {"coordinates":[-5.9671711922,37.3221168518],"type":"Point"}
}