{
  "type": "Feature",
  "properties": {
    "iso:country":"ES",
    "sg:address":"Calle de Administrador Gutierrez Anaya, 1",
    "sg:city":"Sevilla",
    "sg:orig_category":"Centros Empresariales",
    "sg:phone":"+34 954 26 07 88",
    "sg:postcode":"41020",
    "sg:province":"Sevilla",
    "wof:name":"Ajf Asociados S.c.",
    "wof:placetype":"venue"
},
  "geometry": {"coordinates":[-5.9344186783,37.4060020447],"type":"Point"}
}