{
  "type": "Feature",
  "properties": {
    "iso:country":"ES",
    "sg:address":"Carrer de Sant Pere, 23",
    "sg:city":"Cambrils",
    "sg:orig_category":"Zapater\u00cdas",
    "sg:phone":"+34 977 36 14 14",
    "sg:postcode":"43850",
    "sg:province":"Tarragona",
    "wof:name":"Torne Domenech Rosa",
    "wof:placetype":"venue"
},
  "geometry": {"coordinates":[1.0620900393,41.0665893555],"type":"Point"}
}