{
  "type": "Feature",
  "properties": {
    "addr:full":"Bda Sagrera, 7 Barcelona Barcelona 08027",
    "addr:housenumber":"7",
    "addr:postcode":"08027",
    "addr:street":"Sagrera",
    "iso:country":"ES",
    "sg:address":"Bda Sagrera, 7",
    "sg:city":"Barcelona",
    "sg:orig_category":"Contenedores (mercanc\u00cdas)",
    "sg:phone":"+34 934 08 51 42",
    "sg:postcode":"08027",
    "sg:province":"Barcelona",
    "wof:name":"Rodriguez Rajo Antonio",
    "wof:placetype":"venue"
},
  "geometry": {"coordinates":[2.191272974,41.4173698425],"type":"Point"}
}