{
  "type": "Feature",
  "properties": {
    "addr:full":"Calle de Cifuentes, 43 Guadalajara Guadalajara 19003",
    "addr:housenumber":"43",
    "addr:postcode":"19003",
    "addr:street":"Calle De Cifuentes",
    "iso:country":"ES",
    "sg:address":"Calle de Cifuentes, 43",
    "sg:city":"Guadalajara",
    "sg:orig_category":"Confecci\u00d3n De Trajes Para Se\u00d1oras",
    "sg:phone":"+34 949 22 59 30",
    "sg:postcode":"19003",
    "sg:province":"Guadalajara",
    "wof:name":"Notario Ruiz Pilar",
    "wof:placetype":"venue"
},
  "geometry": {"coordinates":[-3.1730647087,40.6308288574],"type":"Point"}
}