{
  "type": "Feature",
  "properties": {
    "iso:country":"ES",
    "sg:address":"Pase Estacion (la), 15",
    "sg:city":"Jaen",
    "sg:orig_category":"Ense\u00d1anza, Formaci\u00d3n Profesional: Aprendizaje",
    "sg:phone":"+34 953 22 25 75",
    "sg:postcode":"23007",
    "sg:province":"Ja\u00e9n",
    "wof:name":"Junta De Andalucia - Consejeria De Salud",
    "wof:placetype":"venue"
},
  "geometry": {"coordinates":[-3.7911388874,37.7738571167],"type":"Point"}
}