{
  "type": "Feature",
  "properties": {
    "iso:country":"ES",
    "sg:address":"Rua Ribeiro (do), 36",
    "sg:city":"Ribadavia",
    "sg:orig_category":"Perfumer\u00cda Y Cosm\u00c9tica (fabricaci\u00d3n, Al Por Mayor)",
    "sg:phone":"+34 988 47 07 22",
    "sg:postcode":"32400",
    "sg:province":"Ourense",
    "wof:name":"Gomez Villar Maria Belen",
    "wof:placetype":"venue"
},
  "geometry": {"coordinates":[-8.1432886124,42.2903938293],"type":"Point"}
}