{
  "type": "Feature",
  "properties": {
    "iso:country":"ES",
    "sg:address":"Av Alginet(plgno Viii), 51",
    "sg:city":"Silla",
    "sg:orig_category":"Pintura Y Barniz (al Por Menor)",
    "sg:phone":"+34 961 21 02 77",
    "sg:postcode":"46460",
    "sg:province":"Valencia",
    "wof:name":"Industrias Sambara S.l.",
    "wof:placetype":"venue"
},
  "geometry": {"coordinates":[-0.4252749979,39.3578834534],"type":"Point"}
}