{
  "type": "Feature",
  "properties": {
    "iso:country":"ES",
    "sg:address":"Av Prat De La Riba, 41",
    "sg:city":"Reus",
    "sg:orig_category":"Notarios",
    "sg:phone":"+34 977 31 26 46",
    "sg:postcode":"43201",
    "sg:province":"Tarragona",
    "wof:name":"Ochoa De Olza Vidal Joaquin",
    "wof:placetype":"venue"
},
  "geometry": {"coordinates":[1.1026389599,41.1574554443],"type":"Point"}
}