{
  "type": "Feature",
  "properties": {
    "addr:full":"Calle de Cuesta De Las Perdices, 58 Aranjuez Madrid 28300",
    "addr:housenumber":"58",
    "addr:postcode":"28300",
    "addr:street":"Calle De Cuesta De Las Perdices",
    "iso:country":"ES",
    "sg:address":"Calle de Cuesta De Las Perdices, 58",
    "sg:city":"Aranjuez",
    "sg:orig_category":"Asociaciones Humanitarias, De Cooperaci\u00d3n, De Acci\u00d3n Social",
    "sg:phone":"+34 918 91 81 97",
    "sg:postcode":"28300",
    "sg:province":"Madrid",
    "wof:name":"Enfermos Del Corazon Del Hospital Doce De Octubre",
    "wof:placetype":"venue"
},
  "geometry": {"coordinates":[-3.6125020981,40.0283050537],"type":"Point"}
}