{
  "type": "Feature",
  "properties": {
    "addr:full":"Martin Azpilcueta, 7 Iru\u00f1a Navarra 31011",
    "addr:housenumber":"7",
    "addr:postcode":"31011",
    "addr:street":"Azpilcueta",
    "iso:country":"ES",
    "sg:address":"Martin Azpilcueta, 7",
    "sg:city":"Iru\u00f1a",
    "sg:orig_category":"Farmacias",
    "sg:phone":"+34 948 25 13 48",
    "sg:postcode":"31011",
    "sg:province":"Navarra",
    "wof:name":"Sola Casas Maria Jesus",
    "wof:placetype":"venue"
},
  "geometry": {"coordinates":[-1.662637949,42.8140678406],"type":"Point"}
}