{
  "type": "Feature",
  "properties": {
    "addr:full":"Avda Jota (la), 57 Zaragoza Zaragoza 50014",
    "addr:housenumber":"57",
    "addr:postcode":"50014",
    "addr:street":"Avda Jota La",
    "iso:country":"ES",
    "sg:address":"Avda Jota (la), 57",
    "sg:city":"Zaragoza",
    "sg:orig_category":"Colchones (fabricaci\u00d3n, Al Por Mayor, Al Por Menor)",
    "sg:phone":"+34 976 47 16 40",
    "sg:postcode":"50014",
    "sg:province":"Zaragoza",
    "wof:name":"Hermanas Pallas S.c",
    "wof:placetype":"venue"
},
  "geometry": {"coordinates":[-0.8584550023,41.661655426],"type":"Point"}
}