{
  "type": "Feature",
  "properties": {
    "addr:full":"Avda San Valero, S/n Velilla Cinca Huesca 22528",
    "addr:housenumber":"s / n",
    "addr:postcode":"22528",
    "addr:street":"Avda San Valero",
    "iso:country":"ES",
    "sg:address":"Avda San Valero, S/n",
    "sg:city":"Velilla Cinca",
    "sg:orig_category":"Asilos De Ancianos. Centros Privados",
    "sg:phone":"+34 974 46 10 05",
    "sg:postcode":"22528",
    "sg:province":"Huesca",
    "wof:name":"Ayuntamiento",
    "wof:placetype":"venue"
},
  "geometry": {"coordinates":[0.2594299912,41.5861244202],"type":"Point"}
}