{
  "type": "Feature",
  "properties": {
    "iso:country":"ES",
    "sg:address":"Calle de Cornatel, 7",
    "sg:city":"Fabero",
    "sg:orig_category":"Ropa Para Se\u00d1oras Y Caballeros (al Por Menor)",
    "sg:phone":"+34 987 55 16 92",
    "sg:postcode":"24420",
    "sg:province":"Le\u00f3n",
    "wof:name":"Rodriguez Canda\u00f1edo Mari Luz",
    "wof:placetype":"venue"
},
  "geometry": {"coordinates":[-6.6273565292,42.7669525146],"type":"Point"}
}