{
  "type": "Feature",
  "properties": {
    "addr:full":"Ctra Esplugues, 169 Fatjo Barcelona 08940",
    "addr:housenumber":"169",
    "addr:postcode":"08940",
    "addr:street":"Ctra Esplugues;Barcelona",
    "iso:country":"ES",
    "sg:address":"Ctra Esplugues, 169",
    "sg:city":"Fatjo",
    "sg:orig_category":"Barnizadores",
    "sg:phone":"+34 934 71 15 45",
    "sg:postcode":"08940",
    "sg:province":"Barcelona",
    "wof:name":"Perez Montes Miguel Angel",
    "wof:placetype":"venue"
},
  "geometry": {"coordinates":[2.0740599632,41.356880188],"type":"Point"}
}