{
  "type": "Feature",
  "properties": {
    "addr:full":"Plaz Ramon Y Cajal, 9 Linares Ja\u00e9n 23700",
    "addr:housenumber":"9",
    "addr:postcode":"23700",
    "addr:street":"Ramon Y Cajal;Jae\u0301N",
    "iso:country":"ES",
    "sg:address":"Plaz Ramon Y Cajal, 9",
    "sg:city":"Linares",
    "sg:orig_category":"Molduras, Junquillos, Listones Y Molduras Perforadas",
    "sg:phone":"+34 953 65 35 07",
    "sg:postcode":"23700",
    "sg:province":"Ja\u00e9n",
    "wof:name":"Najera Fernandez Diego",
    "wof:placetype":"venue"
},
  "geometry": {"coordinates":[-3.6353640556,38.0941467285],"type":"Point"}
}