{
  "type": "Feature",
  "properties": {
    "iso:country":"ES",
    "sg:address":"Calle de Salvador De Madariaga, 3",
    "sg:city":"Santa Maria De Gracia",
    "sg:orig_category":"Peluqueros: De Se\u00d1oras",
    "sg:phone":"+34 968 28 55 86",
    "sg:postcode":"30009",
    "sg:province":"Murcia",
    "wof:name":"Martinez Martinez Maria Isabel",
    "wof:placetype":"venue"
},
  "geometry": {"coordinates":[-1.138111949,37.9950141907],"type":"Point"}
}