{
  "type": "Feature",
  "properties": {
    "addr:full":"Carr Llevant, De, 20 Casco Urbano Valencia 46760",
    "addr:housenumber":"20",
    "addr:postcode":"46760",
    "addr:street":"Carr Llevant De",
    "iso:country":"ES",
    "sg:address":"Carr Llevant, De, 20",
    "sg:city":"Casco Urbano",
    "sg:orig_category":"Inmobiliaria (agencias)",
    "sg:phone":"+34 962 82 23 94",
    "sg:postcode":"46760",
    "sg:province":"Valencia",
    "sg:website":"www.grausol.com",
    "wof:name":"Grausol Sl",
    "wof:placetype":"venue"
},
  "geometry": {"coordinates":[-0.2594090104,39.0749702454],"type":"Point"}
}