{
  "type": "Feature",
  "properties": {
    "iso:country":"ES",
    "sg:address":"Lomba (budi\u00f1o), S/n",
    "sg:city":"Salceda Caselas",
    "sg:orig_category":"Empresas De Carpinter\u00cda Met\u00c1lica",
    "sg:phone":"+34 986 34 65 43",
    "sg:postcode":"36475",
    "sg:province":"Pontevedra",
    "sg:website":"www.masemasl.com",
    "wof:name":"Cerrajeria Masema S.l.",
    "wof:placetype":"venue"
},
  "geometry": {"coordinates":[-8.6081037521,42.0910682678],"type":"Point"}
}