{
  "type": "Feature",
  "properties": {
    "iso:country":"ES",
    "sg:address":"Carrer de Pansa (de La), 1",
    "sg:city":"Pedreguer",
    "sg:orig_category":"Molduras, Junquillos, Listones Y Molduras Perforadas",
    "sg:phone":"+34 965 76 10 40",
    "sg:postcode":"03750",
    "sg:province":"Alicante",
    "wof:name":"Serrat Mu\u00f1oz Angeles",
    "wof:placetype":"venue"
},
  "geometry": {"coordinates":[0.0410719998,38.799987793],"type":"Point"}
}