{
  "type": "Feature",
  "properties": {
    "iso:country":"ES",
    "sg:address":"Calle de Huertas, 6",
    "sg:city":"Majadahonda",
    "sg:orig_category":"Abogados",
    "sg:phone":"+34 916 38 69 40",
    "sg:postcode":"28220",
    "sg:province":"Madrid",
    "wof:name":"Ramos Arana Abogados S.l.",
    "wof:placetype":"venue"
},
  "geometry": {"coordinates":[-3.8718590736,40.4783439636],"type":"Point"}
}