{
  "type": "Feature",
  "properties": {
    "iso:country":"ES",
    "sg:address":"Ctra Peraleda, 2",
    "sg:city":"Toledo",
    "sg:orig_category":"Venta, Montaje De Neum\u00c1ticos",
    "sg:phone":"+34 925 21 07 68",
    "sg:postcode":"45004",
    "sg:province":"Toledo",
    "sg:website":"www paginasamarillas.es",
    "wof:name":"Neumaticos Guty S.a.",
    "wof:placetype":"venue"
},
  "geometry": {"coordinates":[-4.0409498215,39.8727493286],"type":"Point"}
}