{
  "type": "Feature",
  "properties": {
    "addr:full":"Calle de Afueras, S/n Robres Huesca 22252",
    "addr:postcode":"22252",
    "addr:street":"Calle De Afueras S / N Robres",
    "iso:country":"ES",
    "sg:address":"Calle de Afueras, S/n",
    "sg:city":"Robres",
    "sg:orig_category":"Agricultura: Abastecimiento Y Cosechado (negocio)",
    "sg:phone":"+34 974 39 21 76",
    "sg:postcode":"22252",
    "sg:province":"Huesca",
    "wof:name":"Cooperativa San Blas De Robres",
    "wof:placetype":"venue"
},
  "geometry": {"coordinates":[-0.4785495102,41.86901474],"type":"Point"}
}