{
  "type": "Feature",
  "properties": {
    "iso:country":"ES",
    "sg:address":"Calle de Duque De Gaeta, 45",
    "sg:city":"Valencia",
    "sg:orig_category":"Estancos",
    "sg:phone":"+34 963 55 21 95",
    "sg:postcode":"46022",
    "sg:province":"Valencia",
    "wof:name":"Rubiano Santos Manuel",
    "wof:placetype":"venue"
},
  "geometry": {"coordinates":[-0.3490310013,39.4685592651],"type":"Point"}
}