{
  "type": "Feature",
  "properties": {
    "addr:full":"Calle de Linares, 11 Valencia Valencia 46018",
    "addr:housenumber":"11",
    "addr:postcode":"46018",
    "addr:street":"Calle De Linares",
    "iso:country":"ES",
    "sg:address":"Calle de Linares, 11",
    "sg:city":"Valencia",
    "sg:orig_category":"Institutos De Belleza",
    "sg:phone":"+34 963 85 58 01",
    "sg:postcode":"46018",
    "sg:province":"Valencia",
    "wof:name":"Perez Igual Maria Amparo",
    "wof:placetype":"venue"
},
  "geometry": {"coordinates":[-0.3928990066,39.4687919617],"type":"Point"}
}