{
  "type": "Feature",
  "properties": {
    "iso:country":"ES",
    "sg:address":"Carrer de Autovia De Castelldefels, Km. 0016,5",
    "sg:city":"Gava",
    "sg:orig_category":"Farmacias",
    "sg:phone":"+34 936 33 21 33",
    "sg:postcode":"08850",
    "sg:province":"Barcelona",
    "wof:name":"Lauroba Canaleta Carolina",
    "wof:placetype":"venue"
},
  "geometry": {"coordinates":[2.0012850761,41.3040237427],"type":"Point"}
}