{
  "type": "Feature",
  "properties": {
    "addr:full":"Calle de Estacion Renfe, S/n Escorial Madrid 28280",
    "addr:housenumber":"s / n",
    "addr:postcode":"28280",
    "addr:street":"Calle De Estacion Renfe",
    "iso:country":"ES",
    "sg:address":"Calle de Estacion Renfe, S/n",
    "sg:city":"Escorial",
    "sg:classifiers":[
        {
            "category":"Taxi",
            "type":"Transportation"
        }
    ],
    "sg:phone":"+34 918 90 00 15",
    "sg:postcode":"28280",
    "sg:province":"Madrid",
    "wof:name":"Ayuntamiento El Escorial",
    "wof:placetype":"venue"
},
  "geometry": {"coordinates":[-4.1002168655,40.5925712585],"type":"Point"}
}