{
  "type": "Feature",
  "properties": {
    "iso:country":"ES",
    "sg:address":"Calle de San Anton, 15",
    "sg:city":"Burgos",
    "sg:orig_category":"Sales (al Por Mayor)",
    "sg:phone":"+34 947 48 44 89",
    "sg:postcode":"09007",
    "sg:province":"Burgos",
    "wof:name":"Perez Hernando Antonio",
    "wof:placetype":"venue"
},
  "geometry": {"coordinates":[-3.666727066,42.3550605774],"type":"Point"}
}