{
  "type": "Feature",
  "properties": {
    "addr:full":"Crt. Albacete, Km. 0096,0 Villapalacios Albacete 02350",
    "addr:postcode":"02350",
    "addr:street":"Albacete Km. 0096,0",
    "iso:country":"ES",
    "sg:address":"Crt. Albacete, Km. 0096,0",
    "sg:city":"Villapalacios",
    "sg:orig_category":"Distribuci\u00d3n De Petr\u00d3leo Y Derivados",
    "sg:phone":"+34 967 39 81 02",
    "sg:postcode":"02350",
    "sg:province":"Albacete",
    "wof:name":"Estacion De Servicio Villaflores S.l.",
    "wof:placetype":"venue"
},
  "geometry": {"coordinates":[-2.6297490597,38.5754318237],"type":"Point"}
}