{
  "type": "Feature",
  "properties": {
    "addr:full":"Av Prat De La Riba, 19 Reus Tarragona 43201",
    "addr:housenumber":"19",
    "addr:postcode":"43201",
    "addr:street":"Av Prat De La Riba",
    "iso:country":"ES",
    "sg:address":"Av Prat De La Riba, 19",
    "sg:city":"Reus",
    "sg:orig_category":"Productos Alimentarios",
    "sg:phone":"+34 977 31 49 02",
    "sg:postcode":"43201",
    "sg:province":"Tarragona",
    "wof:name":"Colas Y Gine S. A.",
    "wof:placetype":"venue"
},
  "geometry": {"coordinates":[1.1038240194,41.1575393677],"type":"Point"}
}