{
  "type": "Feature",
  "properties": {
    "addr:full":"Calle de Claudio Coello, 91 Madrid Madrid 28006",
    "addr:housenumber":"91",
    "addr:postcode":"madrid;28006",
    "addr:street":"Calle De Claudio Coello",
    "iso:country":"ES",
    "sg:address":"Calle de Claudio Coello, 91",
    "sg:city":"Madrid",
    "sg:orig_category":"Zapatos (al Por Menor)",
    "sg:phone":"+34 914 35 38 21",
    "sg:postcode":"28006",
    "sg:province":"Madrid",
    "sg:website":"www.lalique.fr",
    "wof:name":"Lalique Iberica S.l.",
    "wof:placetype":"venue"
},
  "geometry": {"coordinates":[-3.6858315468,40.4305229187],"type":"Point"}
}