{
  "type": "Feature",
  "properties": {
    "addr:full":"Calle de Niza, 8 Caceres C\u00e1ceres 10001",
    "addr:housenumber":"8",
    "addr:postcode":"10001",
    "addr:street":"Calle De Niza;Ca\u0301Ceres",
    "iso:country":"ES",
    "sg:address":"Calle de Niza, 8",
    "sg:city":"Caceres",
    "sg:orig_category":"Molduras, Junquillos, Listones Y Molduras Perforadas",
    "sg:phone":"+34 927 22 63 44",
    "sg:postcode":"10001",
    "sg:province":"C\u00e1ceres",
    "wof:name":"Garcia Acedo Domingo",
    "wof:placetype":"venue"
},
  "geometry": {"coordinates":[-6.3806400299,39.4730224609],"type":"Point"}
}