{
  "type": "Feature",
  "properties": {
    "addr:full":"Calle de Cristo, 7 Torrejon Ardoz Madrid 28850",
    "addr:housenumber":"7",
    "addr:postcode":"28850",
    "addr:street":"Calle De Cristo",
    "iso:country":"ES",
    "sg:address":"Calle de Cristo, 7",
    "sg:city":"Torrejon Ardoz",
    "sg:orig_category":"Abogados",
    "sg:phone":"+34 916 77 05 95",
    "sg:postcode":"28850",
    "sg:province":"Madrid",
    "wof:name":"De Mesa Del Hoyo Maria Cristina",
    "wof:placetype":"venue"
},
  "geometry": {"coordinates":[-3.479665041,40.4561080933],"type":"Point"}
}