{
  "type": "Feature",
  "properties": {
    "addr:full":"Avda Casalduch, 47 Castellon Castell\u00f3n 12005",
    "addr:housenumber":"47",
    "addr:postcode":"12005",
    "addr:street":"Avda Casalduch",
    "iso:country":"ES",
    "sg:address":"Avda Casalduch, 47",
    "sg:city":"Castellon",
    "sg:orig_category":"Pod\u00d3logos: Pedicuros",
    "sg:phone":"+34 964 20 70 00",
    "sg:postcode":"12005",
    "sg:province":"Castell\u00f3n",
    "wof:name":"Redo Bueso Jorge",
    "wof:placetype":"venue"
},
  "geometry": {"coordinates":[-0.0398189984,39.97838974],"type":"Point"}
}