{
  "type": "Feature",
  "properties": {
    "addr:full":"Carr Major, 51 Felanitx Islas Baleares 07200",
    "addr:housenumber":"51",
    "addr:postcode":"07200",
    "addr:street":"Carr Major",
    "iso:country":"ES",
    "sg:address":"Carr Major, 51",
    "sg:city":"Felanitx",
    "sg:orig_category":"Bancos",
    "sg:phone":"+34 971 58 00 65",
    "sg:postcode":"07200",
    "sg:province":"Islas Baleares",
    "wof:name":"Banca March S.a.",
    "wof:placetype":"venue"
},
  "geometry": {"coordinates":[3.1496200562,39.4706306458],"type":"Point"}
}