{
  "type": "Feature",
  "properties": {
    "iso:country":"ES",
    "sg:address":"Rua Ribadeo, S/n",
    "sg:city":"Vilalba",
    "sg:orig_category":"Sanatorios M\u00c9dico",
    "sg:phone":"+34 982 51 25 84",
    "sg:postcode":"27800",
    "sg:province":"Lugo",
    "wof:name":"Ayuntamiento De Vilalba-centro De Saude",
    "wof:placetype":"venue"
},
  "geometry": {"coordinates":[-7.6776409149,43.2983818054],"type":"Point"}
}