{
  "type": "Feature",
  "properties": {
    "iso:country":"ES",
    "sg:address":"Calle de Lucena, 22",
    "sg:city":"Huetor-vega",
    "sg:orig_category":"Empresas De Pintura Y Revestimientos",
    "sg:phone":"+34 958 30 09 20",
    "sg:postcode":"18198",
    "sg:province":"Granada",
    "wof:name":"Dieguez Almagro Jose",
    "wof:placetype":"venue"
},
  "geometry": {"coordinates":[-3.5669291019,37.1488990784],"type":"Point"}
}