{
  "type": "Feature",
  "properties": {
    "addr:full":"Calle de Granada, 15 Rute C\u00f3rdoba 14960",
    "addr:housenumber":"15",
    "addr:postcode":"14960",
    "addr:street":"Calle De Granada;Co\u0301Rdoba",
    "iso:country":"ES",
    "sg:address":"Calle de Granada, 15",
    "sg:city":"Rute",
    "sg:orig_category":"Electrodom\u00c9sticos (al Por Menor)",
    "sg:phone":"+34 957 53 25 89",
    "sg:postcode":"14960",
    "sg:province":"C\u00f3rdoba",
    "wof:name":"Hermanos Garcia Comino S.l.",
    "wof:placetype":"venue"
},
  "geometry": {"coordinates":[-4.3703460693,37.3244972229],"type":"Point"}
}