{
  "type": "Feature",
  "properties": {
    "iso:country":"ES",
    "sg:address":"Pla\u00c7 De La Concepci\u00e9, 20",
    "sg:city":"Ontinyent",
    "sg:orig_category":"Arquitectos",
    "sg:phone":"+34 962 91 01 74",
    "sg:postcode":"46870",
    "sg:province":"Valencia",
    "wof:name":"Vidal Tolsa Vicente",
    "wof:placetype":"venue"
},
  "geometry": {"coordinates":[-0.6030989885,38.8258895874],"type":"Point"}
}