{
  "type": "Feature",
  "properties": {
    "addr:full":"Los Meridas, 11 Ugijar Granada 18480",
    "addr:housenumber":"11",
    "addr:postcode":"18480",
    "addr:street":"Meridas",
    "iso:country":"ES",
    "sg:address":"Los Meridas, 11",
    "sg:city":"Ugijar",
    "sg:orig_category":"\u00d3ptica: Instrumentos (fabricaci\u00d3n)",
    "sg:phone":"+34 958 85 40 73",
    "sg:postcode":"18480",
    "sg:province":"Granada",
    "wof:name":"De Haro Martinez Eugenia",
    "wof:placetype":"venue"
},
  "geometry": {"coordinates":[-3.0543808937,36.9621772766],"type":"Point"}
}