{
  "type": "Feature",
  "properties": {
    "iso:country":"ES",
    "sg:address":"Carrer de Barcelona, 5",
    "sg:city":"Sant Vicen\u00c7 Dels Horts",
    "sg:orig_category":"Venta, Alquiler De Instrumentos Y Accesorios De M\u00dasica",
    "sg:phone":"+34 936 56 72 15",
    "sg:postcode":"08620",
    "sg:province":"Barcelona",
    "wof:name":"Pianos Catalunya Sl",
    "wof:placetype":"venue"
},
  "geometry": {"coordinates":[2.0034840107,41.4002418518],"type":"Point"}
}