{
  "type": "Feature",
  "properties": {
    "iso:country":"ES",
    "sg:address":"Carrer de Alcalde Ferrer I Mones, 11",
    "sg:city":"Prat Llobregat",
    "sg:orig_category":"Empresas De Carpinter\u00cda Met\u00c1lica",
    "sg:phone":"+34 933 70 59 12",
    "sg:postcode":"08820",
    "sg:province":"Barcelona",
    "wof:name":"Mu\u00f1oz Diaz Elias",
    "wof:placetype":"venue"
},
  "geometry": {"coordinates":[2.1055150032,41.324054718],"type":"Point"}
}