{
  "type": "Feature",
  "properties": {
    "iso:country":"ES",
    "sg:address":"Calle de Santa Cecilia, 30",
    "sg:city":"Ronda",
    "sg:orig_category":"Fabricaci\u00d3n De Quesos",
    "sg:phone":"+34 952 87 48 76",
    "sg:postcode":"29400",
    "sg:province":"M\u00e1laga",
    "wof:name":"Rey Cabra S.a.",
    "wof:placetype":"venue"
},
  "geometry": {"coordinates":[-5.1625828743,36.7421112061],"type":"Point"}
}