{
  "type": "Feature",
  "properties": {
    "addr:full":"Calle de Txapinene, 6 Donostia-san Sebastian Guip\u00f9zcoa 20016",
    "addr:housenumber":"6",
    "addr:postcode":"20016",
    "addr:street":"Calle De Txapinene",
    "iso:country":"ES",
    "sg:address":"Calle de Txapinene, 6",
    "sg:city":"Donostia-san Sebastian",
    "sg:orig_category":"Asociaciones, Organismos Culturales Y Socioeducativos",
    "sg:phone":"+34 943 35 31 29",
    "sg:postcode":"20016",
    "sg:province":"Guip\u00f9zcoa",
    "wof:name":"Astindari Topa Lekua",
    "wof:placetype":"venue"
},
  "geometry": {"coordinates":[-1.9344460964,43.3158760071],"type":"Point"}
}