{
  "type": "Feature",
  "properties": {
    "iso:country":"ES",
    "sg:address":"Calle de Royo, 42",
    "sg:city":"Guare\u00f1a",
    "sg:orig_category":"Refiner\u00cdas De Petr\u00d3leo",
    "sg:phone":"+34 924 35 06 71",
    "sg:postcode":"06470",
    "sg:province":"Badajoz",
    "wof:name":"Procesos Empresariales De Mercados S.a.",
    "wof:placetype":"venue"
},
  "geometry": {"coordinates":[-6.1033029556,38.8639717102],"type":"Point"}
}