{
  "type": "Feature",
  "properties": {
    "iso:country":"ES",
    "sg:address":"Pase Lucas Mallada, 7",
    "sg:city":"Huesca",
    "sg:orig_category":"Empresas De Desmonte",
    "sg:phone":"+34 974 23 02 02",
    "sg:postcode":"22006",
    "sg:province":"Huesca",
    "wof:name":"Excavaciones Vicente S. L",
    "wof:placetype":"venue"
},
  "geometry": {"coordinates":[-0.4016970098,42.1411933899],"type":"Point"}
}