{
  "type": "Feature",
  "properties": {
    "addr:full":"Ctra. Zaragoza, Km. 0002,2 Belchite Zaragoza 50130",
    "addr:postcode":"50130",
    "addr:street":"Ctra. Zaragoza Km. 0002,2",
    "iso:country":"ES",
    "sg:address":"Ctra. Zaragoza, Km. 0002,2",
    "sg:city":"Belchite",
    "sg:orig_category":"Distribuci\u00d3n De Petr\u00d3leo Y Derivados",
    "sg:phone":"+34 976 83 00 95",
    "sg:postcode":"50130",
    "sg:province":"Zaragoza",
    "wof:name":"Estacion De Servicio Nuestra Se\u00f1ora Del Pueyo S. A.",
    "wof:placetype":"venue"
},
  "geometry": {"coordinates":[-0.7530030012,41.3031921387],"type":"Point"}
}