{
  "type": "Feature",
  "properties": {
    "addr:full":"Avda Alisas, 8 Valdecilla Cantabria 39724",
    "addr:housenumber":"8",
    "addr:postcode":"39724",
    "addr:street":"Avda Alisas",
    "iso:country":"ES",
    "sg:address":"Avda Alisas, 8",
    "sg:city":"Valdecilla",
    "sg:orig_category":"Florister\u00cdas",
    "sg:phone":"+34 942 52 00 10",
    "sg:postcode":"39724",
    "sg:province":"Cantabria",
    "wof:name":"Jardi-huerta S.l.",
    "wof:placetype":"venue"
},
  "geometry": {"coordinates":[-3.7323169708,43.3816566467],"type":"Point"}
}