{
  "type": "Feature",
  "properties": {
    "addr:full":"Calle de Enrique Amat, 22 Montefrio Granada 18270",
    "addr:housenumber":"22",
    "addr:postcode":"18270",
    "addr:street":"Calle De Enrique Amat",
    "iso:country":"ES",
    "sg:address":"Calle de Enrique Amat, 22",
    "sg:city":"Montefrio",
    "sg:orig_category":"Pr\u00c9stamos Personales E Hipotecarios",
    "sg:phone":"+34 958 33 60 42",
    "sg:postcode":"18270",
    "sg:province":"Granada",
    "wof:name":"Pellon Gonzalez Luis Fernando",
    "wof:placetype":"venue"
},
  "geometry": {"coordinates":[-4.0087695122,37.3209609985],"type":"Point"}
}