{
  "type": "Feature",
  "properties": {
    "iso:country":"ES",
    "sg:address":"Calle de Bebricio, 35",
    "sg:city":"Calahorra",
    "sg:orig_category":"Alquiler De V\u00cddeo",
    "sg:phone":"+34 941 14 70 81",
    "sg:postcode":"26500",
    "sg:province":"La Rioja",
    "wof:name":"Lopez Lopez Teodoro",
    "wof:placetype":"venue"
},
  "geometry": {"coordinates":[-1.9661141634,42.3040809631],"type":"Point"}
}