{
  "type": "Feature",
  "properties": {
    "addr:full":"Calle de Sirio, 62 Madrid Madrid 28007",
    "addr:housenumber":"62",
    "addr:postcode":"madrid;28007",
    "addr:street":"Calle De Sirio",
    "iso:country":"ES",
    "sg:address":"Calle de Sirio, 62",
    "sg:city":"Madrid",
    "sg:orig_category":"Grafistas",
    "sg:phone":"+34 915 73 79 80",
    "sg:postcode":"28007",
    "sg:province":"Madrid",
    "wof:name":"Jv Dise\u00f1o Grafico Sl",
    "wof:placetype":"venue"
},
  "geometry": {"coordinates":[-3.6650440693,40.4092025757],"type":"Point"}
}