{
  "type": "Feature",
  "properties": {
    "addr:full":"Carrer de Torres I Bages, 25 Mas Rampinyo Barcelona 08110",
    "addr:housenumber":"25",
    "addr:postcode":"08110",
    "addr:street":"Carrer De Torres I Bages",
    "iso:country":"ES",
    "sg:address":"Carrer de Torres I Bages, 25",
    "sg:city":"Mas Rampinyo",
    "sg:orig_category":"Peluqueros: De Se\u00d1oras",
    "sg:phone":"+34 935 64 04 63",
    "sg:postcode":"08110",
    "sg:province":"Barcelona",
    "wof:name":"Escudero Lirola Francisco",
    "wof:placetype":"venue"
},
  "geometry": {"coordinates":[2.1817660332,41.4890899658],"type":"Point"}
}