{
  "type": "Feature",
  "properties": {
    "addr:full":"Calle de Ascao, 3 Madrid Madrid 28017",
    "addr:housenumber":"3",
    "addr:postcode":"28017",
    "addr:street":"Calle De Ascao",
    "iso:country":"ES",
    "sg:address":"Calle de Ascao, 3",
    "sg:city":"Madrid",
    "sg:orig_category":"Tintes (fabricaci\u00d3n, Al Por Mayor)",
    "sg:phone":"+34 914 08 18 64",
    "sg:postcode":"28017",
    "sg:province":"Madrid",
    "sg:website":"www.pressto.es",
    "wof:name":"Pil-art Y Mases S.l",
    "wof:placetype":"venue"
},
  "geometry": {"coordinates":[-3.642136097,40.4296989441],"type":"Point"}
}