{
  "type": "Feature",
  "properties": {
    "addr:full":"Luga Lugarejo (el), 15 Lugarejo Las Palmas 35300",
    "addr:postcode":"35300",
    "addr:street":"Palmas",
    "iso:country":"ES",
    "sg:address":"Luga Lugarejo (el), 15",
    "sg:city":"Lugarejo",
    "sg:orig_category":"Molduras, Junquillos, Listones Y Molduras Perforadas",
    "sg:phone":"+34 928 64 23 99",
    "sg:postcode":"35300",
    "sg:province":"Las Palmas",
    "wof:name":"Santana Motesdeoca Benito",
    "wof:placetype":"venue"
},
  "geometry": {"coordinates":[-15.4988956451,28.0369472504],"type":"Point"}
}