{
  "type": "Feature",
  "properties": {
    "addr:full":"Calle de Ramon Y Cajal, 39 Sonseca Toledo 45100",
    "addr:housenumber":"39",
    "addr:postcode":"45100",
    "addr:street":"Calle De Ramon Y Cajal",
    "iso:country":"ES",
    "sg:address":"Calle de Ramon Y Cajal, 39",
    "sg:city":"Sonseca",
    "sg:orig_category":"Sales (al Por Mayor)",
    "sg:phone":"+34 925 38 01 50",
    "sg:postcode":"45100",
    "sg:province":"Toledo",
    "wof:name":"Turrones Mazapanes Y Dulces De Sonseca S.l.",
    "wof:placetype":"venue"
},
  "geometry": {"coordinates":[-3.9766619205,39.6781616211],"type":"Point"}
}