{
  "type": "Feature",
  "properties": {
    "addr:full":"Calle de Istua, 2 Bermeo Vizcaya 48370",
    "addr:housenumber":"2",
    "addr:postcode":"48370",
    "addr:street":"Calle De Istua",
    "iso:country":"ES",
    "sg:address":"Calle de Istua, 2",
    "sg:city":"Bermeo",
    "sg:orig_category":"Fabricaci\u00d3n, Reparaci\u00d3n Y Mantenimiento De Construcciones Navales Y Fluviales",
    "sg:phone":"+34 946 88 40 52",
    "sg:postcode":"48370",
    "sg:province":"Vizcaya",
    "wof:name":"Juan Ramon Garro Jimenez E Ignacio Garro Jim Cdad",
    "wof:placetype":"venue"
},
  "geometry": {"coordinates":[-2.7213227749,43.4199028015],"type":"Point"}
}