{
  "type": "Feature",
  "properties": {
    "iso:country":"ES",
    "sg:address":"Lagos De Coronas, 14",
    "sg:city":"Zaragoza",
    "sg:orig_category":"Peluquer\u00cdas, Peluquer\u00cda Mixta",
    "sg:phone":"+34 976 54 17 17",
    "sg:postcode":"50011",
    "sg:province":"Zaragoza",
    "wof:name":"Esencia Peluqueros S.l.",
    "wof:placetype":"venue"
},
  "geometry": {"coordinates":[-0.9336749911,41.6573410034],"type":"Point"}
}