{
  "type": "Feature",
  "properties": {
    "addr:full":"Bernard Vicent (p I Dos Octubre), 8 Santa Fe Granada 18320",
    "addr:housenumber":"8",
    "addr:postcode":"18320",
    "addr:street":"Bernard Vicent P;Dos Octubre;Fe",
    "iso:country":"ES",
    "sg:address":"Bernard Vicent (p I Dos Octubre), 8",
    "sg:city":"Santa Fe",
    "sg:orig_category":"Carpinteros",
    "sg:phone":"+34 958 51 31 27",
    "sg:postcode":"18320",
    "sg:province":"Granada",
    "wof:name":"Jauvent Granada S.l.",
    "wof:placetype":"venue"
},
  "geometry": {"coordinates":[-3.7343680859,37.1921691895],"type":"Point"}
}