{
  "type": "Feature",
  "properties": {
    "iso:country":"ES",
    "sg:address":"Calle de Sagastia, 21",
    "sg:city":"Ezcaray",
    "sg:orig_category":"Venta, Instalaci\u00d3n De Cocinas",
    "sg:phone":"+34 941 42 73 80",
    "sg:postcode":"26280",
    "sg:province":"La Rioja",
    "wof:name":"Lladito S.l.",
    "wof:placetype":"venue"
},
  "geometry": {"coordinates":[-3.0147130489,42.3239173889],"type":"Point"}
}