{
  "type": "Feature",
  "properties": {
    "addr:full":"Avda Gran Via Parque, 22 Cordoba C\u00f3rdoba 14005",
    "addr:housenumber":"22",
    "addr:postcode":"14005",
    "addr:street":"Avda Gran Via Parque;Co\u0301Rdoba",
    "iso:country":"ES",
    "sg:address":"Avda Gran Via Parque, 22",
    "sg:city":"Cordoba",
    "sg:orig_category":"Agencias Y Agentes Comerciales, Representantes",
    "sg:phone":"+34 957 23 61 57",
    "sg:postcode":"14005",
    "sg:province":"C\u00f3rdoba",
    "wof:name":"Ruano De Miguel Jorge",
    "wof:placetype":"venue"
},
  "geometry": {"coordinates":[-4.7924909592,37.8784103394],"type":"Point"}
}