{
  "type": "Feature",
  "properties": {
    "iso:country":"ES",
    "sg:address":"Carrer de Castellet, S/n",
    "sg:city":"Manresa",
    "sg:orig_category":"Reposter\u00cdas",
    "sg:phone":"+34 938 77 38 57",
    "sg:postcode":"08243",
    "sg:province":"Barcelona",
    "wof:name":"Baylina Prat Josep",
    "wof:placetype":"venue"
},
  "geometry": {"coordinates":[1.8425250053,41.7368011475],"type":"Point"}
}