{
  "type": "Feature",
  "properties": {
    "iso:country":"ES",
    "sg:address":"Avda Ciudad De Almeria, 37",
    "sg:city":"Purisima -barriomar",
    "sg:orig_category":"Empresas De Limpieza",
    "sg:phone":"+34 968 34 08 70",
    "sg:postcode":"30010",
    "sg:province":"Murcia",
    "wof:name":"Proyectos Integrales De Limpieza S.a.",
    "wof:placetype":"venue"
},
  "geometry": {"coordinates":[-1.1492689848,37.9747200012],"type":"Point"}
}