{
  "type": "Feature",
  "properties": {
    "iso:country":"ES",
    "sg:address":"Nafarroa Kalea, 4",
    "sg:city":"Zarautz",
    "sg:orig_category":"Asesor\u00cda Sobre Comunicaci\u00d3n De Empresas",
    "sg:phone":"+34 943 89 02 00",
    "sg:postcode":"20800",
    "sg:province":"Guip\u00f9zcoa",
    "wof:name":"Antonio Ega\u00f1a Hormias (asesoria Ega\u00f1a)",
    "wof:placetype":"venue"
},
  "geometry": {"coordinates":[-2.1757259369,43.2865562439],"type":"Point"}
}