{
  "type": "Feature",
  "properties": {
    "iso:country":"ES",
    "sg:address":"Carrer de Villarroel, 180",
    "sg:city":"Barcelona",
    "sg:orig_category":"Droguer\u00cdas (al Por Menor)",
    "sg:phone":"+34 933 63 01 41",
    "sg:postcode":"08036",
    "sg:province":"Barcelona",
    "wof:name":"Quimics Dalmau S.l.",
    "wof:placetype":"venue"
},
  "geometry": {"coordinates":[2.1500489712,41.3904685974],"type":"Point"}
}