{
  "type": "Feature",
  "properties": {
    "addr:full":"Pol Ind Pje La Nava, S/n Los Santos Maimona Badajoz 06230",
    "addr:housenumber":"s / n",
    "addr:postcode":"06230",
    "addr:street":"Pje La Nava",
    "iso:country":"ES",
    "sg:address":"Pol Ind Pje La Nava, S/n",
    "sg:city":"Los Santos Maimona",
    "sg:orig_category":"Charcuter\u00cdas (al Por Mayor)",
    "sg:phone":"+34 924 57 11 93",
    "sg:postcode":"06230",
    "sg:province":"Badajoz",
    "wof:name":"Embutidos Morato S.a.l",
    "wof:placetype":"venue"
},
  "geometry": {"coordinates":[-6.3725099564,38.4434814453],"type":"Point"}
}