{
  "type": "Feature",
  "properties": {
    "addr:full":"Carr Pi I Margall, 51 Lleida Lleida 25004",
    "addr:housenumber":"51",
    "addr:postcode":"25004",
    "addr:street":"Carr Pi I Margall",
    "iso:country":"ES",
    "sg:address":"Carr Pi I Margall, 51",
    "sg:city":"Lleida",
    "sg:orig_category":"Ense\u00d1anza Secundaria: Colegios Y Escuelas Privadas",
    "sg:phone":"+34 973 23 15 49",
    "sg:postcode":"25004",
    "sg:province":"Lleida",
    "wof:name":"I.e.s.escola Del Treball",
    "wof:placetype":"venue"
},
  "geometry": {"coordinates":[0.6260960102,41.6231575012],"type":"Point"}
}