{
  "type": "Feature",
  "properties": {
    "addr:full":"Carrer de Jesus, 18 Sitges Barcelona 08870",
    "addr:housenumber":"18",
    "addr:postcode":"08870",
    "addr:street":"Carrer De Jesus",
    "iso:country":"ES",
    "sg:address":"Carrer de Jesus, 18",
    "sg:city":"Sitges",
    "sg:orig_category":"Bancos",
    "sg:phone":"+34 938 94 98 00",
    "sg:postcode":"08870",
    "sg:province":"Barcelona",
    "wof:name":"Banco Popular Espa\u00f1ol S.a.",
    "wof:placetype":"venue"
},
  "geometry": {"coordinates":[1.8102539778,41.2370071411],"type":"Point"}
}