{
  "type": "Feature",
  "properties": {
    "iso:country":"ES",
    "sg:address":"Calle de Lagasca, 105",
    "sg:city":"Madrid",
    "sg:orig_category":"Inmobiliaria (agencias)",
    "sg:phone":"+34 914 11 95 11",
    "sg:postcode":"28006",
    "sg:province":"Madrid",
    "wof:name":"Rodriguez Cabrera Francisco Jose",
    "wof:placetype":"venue"
},
  "geometry": {"coordinates":[-3.6846199036,40.4344787598],"type":"Point"}
}