{
  "type": "Feature",
  "properties": {
    "iso:country":"ES",
    "sg:address":"Calle de Sancho Davila, S/n",
    "sg:city":"Jerez De La Frontera",
    "sg:orig_category":"Carnicer\u00cdas, Carnicer\u00cdas",
    "sg:phone":"+34 956 31 09 55",
    "sg:postcode":"11407",
    "sg:province":"C\u00e1diz",
    "wof:name":"Gil Cala Juan",
    "wof:placetype":"venue"
},
  "geometry": {"coordinates":[-6.1358342171,36.6995849609],"type":"Point"}
}