{
  "type": "Feature",
  "properties": {
    "iso:country":"ES",
    "sg:address":"Avda Los Olmos, 1",
    "sg:city":"Vitoria-gasteiz",
    "sg:orig_category":"M\u00c1quinas Para Recortar Y Pegar",
    "sg:phone":"+34 945 12 36 67",
    "sg:postcode":"01013",
    "sg:province":"\u00c1lava",
    "wof:name":"Iglesias Froufe Jose Luis",
    "wof:placetype":"venue"
},
  "geometry": {"coordinates":[-2.651304245,42.8729362488],"type":"Point"}
}