{
  "type": "Feature",
  "properties": {
    "iso:country":"ES",
    "sg:address":"San Juanito, S/n",
    "sg:city":"Candelaria",
    "sg:orig_category":"Delegados, Agentes De Tr\u00c1nsito, Auxiliares De Transporte Internacional",
    "sg:phone":"+34 922 50 62 93",
    "sg:postcode":"38530",
    "sg:province":"Santa Cruz De Tenerife",
    "wof:name":"Morales Paz Numancia",
    "wof:placetype":"venue"
},
  "geometry": {"coordinates":[-16.3681564331,28.3405780792],"type":"Point"}
}