{
  "type": "Feature",
  "properties": {
    "iso:country":"ES",
    "sg:address":"Calle de Hernan Cortes, 17",
    "sg:city":"Santander",
    "sg:orig_category":"Acondicionamiento De Techumbres Y Bodegas",
    "sg:phone":"+34 942 21 07 18",
    "sg:postcode":"39003",
    "sg:province":"Cantabria",
    "wof:name":"Comercial Grupo Freixenet S.a.",
    "wof:placetype":"venue"
},
  "geometry": {"coordinates":[-3.8028540611,43.4627723694],"type":"Point"}
}