{
  "type": "Feature",
  "properties": {
    "iso:country":"ES",
    "sg:address":"Avda Vi\u00d1uela (de La), 12",
    "sg:city":"Cordoba",
    "sg:orig_category":"Mercer\u00cda, Lencer\u00cda (al Por Menor)",
    "sg:phone":"+34 957 25 18 28",
    "sg:postcode":"14010",
    "sg:province":"C\u00f3rdoba",
    "wof:name":"Cabello Diaz Sociedad Civil",
    "wof:placetype":"venue"
},
  "geometry": {"coordinates":[-4.7630939484,37.8897895813],"type":"Point"}
}