{
  "type": "Feature",
  "properties": {
    "iso:country":"ES",
    "sg:address":"Rbla Guipuscoa, 177",
    "sg:city":"Barcelona",
    "sg:orig_category":"Comercio De Piezas De Recambio Y De Accesorios De Veh\u00cdculos, Veh\u00cdculos Industriales",
    "sg:phone":"+34 933 14 63 08",
    "sg:postcode":"08020",
    "sg:province":"Barcelona",
    "sg:website":"www.cocisaalcor.citroen.es",
    "wof:name":"Comercial Citroen S. A.",
    "wof:placetype":"venue"
},
  "geometry": {"coordinates":[2.2073400021,41.4243278503],"type":"Point"}
}