{
  "type": "Feature",
  "properties": {
    "addr:full":"Calle de Principe, 3 Quintanar Orden Toledo 45800",
    "addr:housenumber":"3",
    "addr:postcode":"45800",
    "addr:street":"Calle De Principe",
    "iso:country":"ES",
    "sg:address":"Calle de Principe, 3",
    "sg:city":"Quintanar Orden",
    "sg:orig_category":"Ropa De Hogar (al Por Menor)",
    "sg:phone":"+34 925 18 01 29",
    "sg:postcode":"45800",
    "sg:province":"Toledo",
    "wof:name":"Villalobos Villasante Alfredo",
    "wof:placetype":"venue"
},
  "geometry": {"coordinates":[-3.0410449505,39.5910644531],"type":"Point"}
}