{
  "type": "Feature",
  "properties": {
    "iso:country":"ES",
    "sg:address":"Calle de Francisco Villaespesa, 10",
    "sg:city":"Madrid",
    "sg:orig_category":"Revestimiento De Suelos Industriales",
    "sg:phone":"+34 914 07 66 50",
    "sg:postcode":"28017",
    "sg:province":"Madrid",
    "wof:name":"Artigo Iberica S.l.",
    "wof:placetype":"venue"
},
  "geometry": {"coordinates":[-3.64544034,40.4290885925],"type":"Point"}
}