{
  "type": "Feature",
  "properties": {
    "iso:country":"ES",
    "sg:address":"Pase Barron -cegonyer-, 6",
    "sg:city":"Fraga",
    "sg:orig_category":"Cooperativas Agr\u00cdcolas",
    "sg:phone":"+34 974 47 00 58",
    "sg:postcode":"22520",
    "sg:province":"Huesca",
    "wof:name":"Union De Agricultores Y Ganaderos De Aragon",
    "wof:placetype":"venue"
},
  "geometry": {"coordinates":[0.3502210081,41.5206375122],"type":"Point"}
}