{
  "type": "Feature",
  "properties": {
    "addr:full":"Calle de Nectar, 12 Madrid Madrid 28022",
    "addr:housenumber":"12",
    "addr:postcode":"madrid;28022",
    "addr:street":"Calle De Nectar",
    "iso:country":"ES",
    "sg:address":"Calle de Nectar, 12",
    "sg:city":"Madrid",
    "sg:orig_category":"Chapister\u00cda",
    "sg:phone":"+34 917 41 80 34",
    "sg:postcode":"28022",
    "sg:province":"Madrid",
    "wof:name":"Talleres Nectar S.l.l",
    "wof:placetype":"venue"
},
  "geometry": {"coordinates":[-3.6142334938,40.4414978027],"type":"Point"}
}