{
  "type": "Feature",
  "properties": {
    "iso:country":"ES",
    "sg:address":"Calle de Baja Del Mar, 14",
    "sg:city":"Almu\u00f1ecar",
    "sg:orig_category":"Bisuter\u00cda, Joyer\u00cda, Relojer\u00cda (al Por Menor)",
    "sg:phone":"+34 958 63 11 91",
    "sg:postcode":"18690",
    "sg:province":"Granada",
    "wof:name":"Garcia Boyano Alejandro",
    "wof:placetype":"venue"
},
  "geometry": {"coordinates":[-3.6899700165,36.7323913574],"type":"Point"}
}