{
  "type": "Feature",
  "properties": {
    "iso:country":"ES",
    "sg:address":"Calle de Azalea (de La), 195",
    "sg:city":"Alcobendas",
    "sg:orig_category":"Pintores",
    "sg:phone":"+34 916 50 42 91",
    "sg:postcode":"28109",
    "sg:province":"Madrid",
    "wof:name":"Biler & T Internacional S.l.",
    "wof:placetype":"venue"
},
  "geometry": {"coordinates":[-3.6492080688,40.5211830139],"type":"Point"}
}