{
  "type": "Feature",
  "properties": {
    "addr:full":"A Pol Ind Comarca I (agustinos), S/n Iru\u00f1a Navarra 31013",
    "addr:housenumber":"s",
    "addr:postcode":"31013",
    "addr:street":"/ N Irun\u0303A Navarra",
    "iso:country":"ES",
    "sg:address":"A Pol Ind Comarca I (agustinos), S/n",
    "sg:city":"Iru\u00f1a",
    "sg:orig_category":"Florister\u00cdas",
    "sg:phone":"+34 948 30 30 46",
    "sg:postcode":"31013",
    "sg:province":"Navarra",
    "wof:name":"Jardineria Adaxka S.l.",
    "wof:placetype":"venue"
},
  "geometry": {"coordinates":[-1.6442149878,42.8179893494],"type":"Point"}
}