{
  "type": "Feature",
  "properties": {
    "addr:full":"C/ Major, 30 Ribes Freser Girona 17534",
    "addr:housenumber":"30",
    "addr:postcode":"17534",
    "addr:street":"C / Major",
    "iso:country":"ES",
    "sg:address":"C/ Major, 30",
    "sg:city":"Ribes Freser",
    "sg:orig_category":"Agentes Generales De Seguros",
    "sg:phone":"+34 972 72 77 04",
    "sg:postcode":"17534",
    "sg:province":"Girona",
    "wof:name":"Rodriguez Sidera Ricardo",
    "wof:placetype":"venue"
},
  "geometry": {"coordinates":[2.1643021107,42.3507347107],"type":"Point"}
}