{
  "type": "Feature",
  "properties": {
    "addr:full":"Bergazos, S/n Donsion Pontevedra 36519",
    "addr:postcode":"36519",
    "addr:street":"Bergazos S / N",
    "iso:country":"ES",
    "sg:address":"Bergazos, S/n",
    "sg:city":"Donsion",
    "sg:orig_category":"Servicio De Salud",
    "sg:phone":"+34 986 78 75 48",
    "sg:postcode":"36519",
    "sg:province":"Pontevedra",
    "sg:website":"www.sumiagua.com",
    "wof:name":"Suministro Integral Del Agua S.l. Sumiagua S.l.",
    "wof:placetype":"venue"
},
  "geometry": {"coordinates":[-8.1627492905,42.5798492432],"type":"Point"}
}