{
  "type": "Feature",
  "properties": {
    "addr:full":"Pla\u00c7 Enric Fajarnes I Tur, 5 Eivissa Islas Baleares 07800",
    "addr:housenumber":"5",
    "addr:postcode":"07800",
    "addr:street":"Tur",
    "iso:country":"ES",
    "sg:address":"Pla\u00c7 Enric Fajarnes I Tur, 5",
    "sg:city":"Eivissa",
    "sg:orig_category":"Ropa Para Se\u00d1oras (al Por Menor)",
    "sg:phone":"+34 971 31 26 26",
    "sg:postcode":"07800",
    "sg:province":"Islas Baleares",
    "wof:name":"Ibicenca De Confecciones S. A.",
    "wof:placetype":"venue"
},
  "geometry": {"coordinates":[1.4289549589,38.9107208252],"type":"Point"}
}