{
  "type": "Feature",
  "properties": {
    "addr:full":"Calle de Antonia Maria De Oviedo, 12 Alaquas Valencia 46970",
    "addr:housenumber":"12",
    "addr:postcode":"46970",
    "addr:street":"Calle De Antonia Maria De Oviedo",
    "iso:country":"ES",
    "sg:address":"Calle de Antonia Maria De Oviedo, 12",
    "sg:city":"Alaquas",
    "sg:orig_category":"Supermercados Y Hipermercados",
    "sg:phone":"+34 961 50 38 54",
    "sg:postcode":"46970",
    "sg:province":"Valencia",
    "sg:website":"www.consum.es",
    "wof:name":"Consum Sociedad Cooperativa Limitada",
    "wof:placetype":"venue"
},
  "geometry": {"coordinates":[-0.4620763063,39.4564476013],"type":"Point"}
}