{
  "type": "Feature",
  "properties": {
    "addr:full":"Calle de Chile, 23 Madrid Madrid 28016",
    "addr:housenumber":"23",
    "addr:postcode":"madrid;28016",
    "addr:street":"Calle De Chile",
    "iso:country":"ES",
    "sg:address":"Calle de Chile, 23",
    "sg:city":"Madrid",
    "sg:orig_category":"Empresas De Carpinter\u00cda De Madera",
    "sg:phone":"+34 913 45 01 91",
    "sg:postcode":"28016",
    "sg:province":"Madrid",
    "wof:name":"Jirod Sl",
    "wof:placetype":"venue"
},
  "geometry": {"coordinates":[-3.6756412983,40.4593353271],"type":"Point"}
}