{
  "type": "Feature",
  "properties": {
    "iso:country":"ES",
    "sg:address":"Avda Brasilia, 23",
    "sg:city":"Madrid",
    "sg:orig_category":"M\u00c9dicos: Neurocirug\u00cda",
    "sg:phone":"+34 917 26 04 38",
    "sg:postcode":"28028",
    "sg:province":"Madrid",
    "wof:name":"Arguello Valentin Cesar",
    "wof:placetype":"venue"
},
  "geometry": {"coordinates":[-3.6612086296,40.4397964478],"type":"Point"}
}