{
  "type": "Feature",
  "properties": {
    "iso:country":"ES",
    "sg:address":"Carrer de Sant Lluis, 55",
    "sg:city":"Santa Coloma De Gramenet",
    "sg:orig_category":"Asesor\u00cda De Comercio Exterior",
    "sg:phone":"+34 934 68 12 48",
    "sg:postcode":"08921",
    "sg:province":"Barcelona",
    "wof:name":"United Europhil S.a.",
    "wof:placetype":"venue"
},
  "geometry": {"coordinates":[2.2164809704,41.4516677856],"type":"Point"}
}