{
  "type": "Feature",
  "properties": {
    "addr:full":"Calle de Nardos, 1 Salamanca Salamanca 37004",
    "addr:housenumber":"1",
    "addr:postcode":"37004",
    "addr:street":"Calle De Nardos",
    "iso:country":"ES",
    "sg:address":"Calle de Nardos, 1",
    "sg:city":"Salamanca",
    "sg:orig_category":"Ferreter\u00cda (diversos)",
    "sg:phone":"+34 923 23 80 36",
    "sg:postcode":"37004",
    "sg:province":"Salamanca",
    "wof:name":"Fayolup S.l.",
    "wof:placetype":"venue"
},
  "geometry": {"coordinates":[-5.6516270638,40.977684021],"type":"Point"}
}