{
  "type": "Feature",
  "properties": {
    "iso:country":"ES",
    "sg:address":"Pase Maritimo Rey De Espa\u00d1a, 146",
    "sg:city":"Fuengirola",
    "sg:orig_category":"Telas Y Sedas (al Por Menor)",
    "sg:phone":"+34 952 66 21 07",
    "sg:postcode":"29640",
    "sg:province":"M\u00e1laga",
    "wof:name":"Multiservicios Barbados S.c.",
    "wof:placetype":"venue"
},
  "geometry": {"coordinates":[-4.615831852,36.5488815308],"type":"Point"}
}