{
  "type": "Feature",
  "properties": {
    "iso:country":"ES",
    "sg:address":"Calle de Habana (la), 15",
    "sg:city":"Muela",
    "sg:orig_category":"Agentes, Concesionarios Y Sucursales De Camiones Y Veh\u00cdculos Industriales",
    "sg:phone":"+34 976 14 45 15",
    "sg:postcode":"50196",
    "sg:province":"Zaragoza",
    "wof:name":"Corporacion Upwards 98 S.a.",
    "wof:placetype":"venue"
},
  "geometry": {"coordinates":[-1.115334034,41.5763931274],"type":"Point"}
}