{
  "type": "Feature",
  "properties": {
    "addr:full":"Carrer de Joan D'austria, 66 Barcelona Barcelona 08005",
    "addr:housenumber":"66",
    "addr:postcode":"08005",
    "addr:street":"Carrer De Joan D'Austria",
    "iso:country":"ES",
    "sg:address":"Carrer de Joan D'austria, 66",
    "sg:city":"Barcelona",
    "sg:orig_category":"Imprenta",
    "sg:phone":"+34 933 00 18 69",
    "sg:postcode":"08005",
    "sg:province":"Barcelona",
    "wof:name":"Servicios Graficos Jamsa S.a.",
    "wof:placetype":"venue"
},
  "geometry": {"coordinates":[2.1913650036,41.3931732178],"type":"Point"}
}