{
  "type": "Feature",
  "properties": {
    "iso:country":"ES",
    "sg:address":"Calle de Mies (la), S/n",
    "sg:city":"Malia\u00d1o",
    "sg:orig_category":"Centros De Educaci\u00d3n Especial",
    "sg:phone":"+34 942 25 15 43",
    "sg:postcode":"39600",
    "sg:province":"Cantabria",
    "wof:name":"Colegio Nacional Mixto Juan De Herrera",
    "wof:placetype":"venue"
},
  "geometry": {"coordinates":[-3.8350639343,43.4173545837],"type":"Point"}
}