{
  "type": "Feature",
  "properties": {
    "addr:full":"Calle de Vallehermoso, 68 Madrid Madrid 28015",
    "addr:housenumber":"68",
    "addr:postcode":"madrid;28015",
    "addr:street":"Calle De Vallehermoso",
    "iso:country":"ES",
    "sg:address":"Calle de Vallehermoso, 68",
    "sg:city":"Madrid",
    "sg:orig_category":"Cursos Particulares, Asistencia Escolar",
    "sg:phone":"+34 914 46 97 52",
    "sg:postcode":"28015",
    "sg:province":"Madrid",
    "wof:name":"Alcina Franch Jose",
    "wof:placetype":"venue"
},
  "geometry": {"coordinates":[-3.7084040642,40.4371795654],"type":"Point"}
}