{
  "type": "Feature",
  "properties": {
    "iso:country":"ES",
    "sg:address":"Calle de Alvaro De Bazan, 9",
    "sg:city":"Granada",
    "sg:orig_category":"Asesor\u00cda Fiscal Y Jur\u00cddica",
    "sg:phone":"+34 958 22 59 49",
    "sg:postcode":"18010",
    "sg:province":"Granada",
    "wof:name":"Gallego Galvez Braulio",
    "wof:placetype":"venue"
},
  "geometry": {"coordinates":[-3.5992882252,37.1781044006],"type":"Point"}
}