{
  "type": "Feature",
  "properties": {
    "addr:full":"Plaz Andalucia, 1 Aljaraque Huelva 21110",
    "addr:housenumber":"1",
    "addr:postcode":"21110",
    "addr:street":"Plaz Andalucia",
    "iso:country":"ES",
    "sg:address":"Plaz Andalucia, 1",
    "sg:city":"Aljaraque",
    "sg:orig_category":"Ense\u00d1anza, Formaci\u00d3n Profesional: Aprendizaje",
    "sg:phone":"+34 959 31 63 23",
    "sg:postcode":"21110",
    "sg:province":"Huelva",
    "wof:name":"Ayuntamiento De Aljaraque",
    "wof:placetype":"venue"
},
  "geometry": {"coordinates":[-7.0216941833,37.2712097168],"type":"Point"}
}