{
  "type": "Feature",
  "properties": {
    "iso:country":"ES",
    "sg:address":"Calle de San Pedro, 1",
    "sg:city":"Vegadeo",
    "sg:orig_category":"Librer\u00cdas",
    "sg:phone":"+34 985 47 64 47",
    "sg:postcode":"33770",
    "sg:province":"Asturias",
    "wof:name":"Soria Lopez Julio",
    "wof:placetype":"venue"
},
  "geometry": {"coordinates":[-7.0460991859,43.4638404846],"type":"Point"}
}