{
  "type": "Feature",
  "properties": {
    "addr:full":"Calle de Santa Maria, 14 Bilbao Vizcaya 48005",
    "addr:housenumber":"14",
    "addr:postcode":"48005",
    "addr:street":"Calle De Santa Maria",
    "iso:country":"ES",
    "sg:address":"Calle de Santa Maria, 14",
    "sg:city":"Bilbao",
    "sg:orig_category":"Tintorer\u00cdas, Limpieza En Seco",
    "sg:phone":"+34 944 16 04 63",
    "sg:postcode":"48005",
    "sg:province":"Vizcaya",
    "wof:name":"Aguirre Urquijo Inmaculada",
    "wof:placetype":"venue"
},
  "geometry": {"coordinates":[-2.9825174809,43.3162536621],"type":"Point"}
}