{
  "type": "Feature",
  "properties": {
    "addr:full":"Carrer de Bonavista, 44 Cornella Llobregat Barcelona 08940",
    "addr:housenumber":"44",
    "addr:postcode":"08940",
    "addr:street":"Carrer De Bonavista",
    "iso:country":"ES",
    "sg:address":"Carrer de Bonavista, 44",
    "sg:city":"Cornella Llobregat",
    "sg:orig_category":"Cl\u00cdnicas Dentales",
    "sg:phone":"+34 933 75 51 32",
    "sg:postcode":"08940",
    "sg:province":"Barcelona",
    "wof:name":"Sanfeliz Zurita Maia Del Pilar",
    "wof:placetype":"venue"
},
  "geometry": {"coordinates":[2.0762820244,41.3578338623],"type":"Point"}
}