{
  "type": "Feature",
  "properties": {
    "addr:full":"Carrer de Llunetes, 8 Cornella Llobregat Barcelona 08940",
    "addr:housenumber":"8",
    "addr:postcode":"08940",
    "addr:street":"Carrer De Llunetes",
    "iso:country":"ES",
    "sg:address":"Carrer de Llunetes, 8",
    "sg:city":"Cornella Llobregat",
    "sg:orig_category":"Laboratorios Y Trabajos De Fotograf\u00cda, V\u00cddeo Y Cine",
    "sg:phone":"+34 934 71 13 28",
    "sg:postcode":"08940",
    "sg:province":"Barcelona",
    "wof:name":"Garcia Cardenas Diego",
    "wof:placetype":"venue"
},
  "geometry": {"coordinates":[2.0817360878,41.3599205017],"type":"Point"}
}