{
  "type": "Feature",
  "properties": {
    "iso:country":"ES",
    "sg:address":"Luis Morondo Urra, 1",
    "sg:city":"Iru\u00f1a",
    "sg:orig_category":"Pescader\u00cdas (al Por Menor)",
    "sg:phone":"+34 948 24 51 65",
    "sg:postcode":"31006",
    "sg:province":"Navarra",
    "wof:name":"Pescaderia Itarte S.l.",
    "wof:placetype":"venue"
},
  "geometry": {"coordinates":[-1.6452549696,42.801738739],"type":"Point"}
}