{
  "type": "Feature",
  "properties": {
    "addr:full":"Calle de Atocha, 46 Madrid Madrid 28012",
    "addr:housenumber":"46",
    "addr:postcode":"madrid;28012",
    "addr:street":"Calle De Atocha",
    "iso:country":"ES",
    "sg:address":"Calle de Atocha, 46",
    "sg:city":"Madrid",
    "sg:orig_category":"Farmacias",
    "sg:phone":"+34 913 69 20 00",
    "sg:postcode":"28012",
    "sg:province":"Madrid",
    "wof:name":"Nestares Lopez Lourdes",
    "wof:placetype":"venue"
},
  "geometry": {"coordinates":[-3.6997182369,40.4126625061],"type":"Point"}
}