{
  "type": "Feature",
  "properties": {
    "addr:full":"Ctra Nacional Ii, Km. 0757,0 Vilamalla Girona 17469",
    "addr:postcode":"17469",
    "addr:street":"Ctra Nacional Ii Km. 0757,0",
    "iso:country":"ES",
    "sg:address":"Ctra Nacional Ii, Km. 0757,0",
    "sg:city":"Vilamalla",
    "sg:orig_category":"Construcciones Met\u00c1licas",
    "sg:phone":"+34 972 52 58 97",
    "sg:postcode":"17469",
    "sg:province":"Girona",
    "wof:name":"Neteges Bimsa S.l",
    "wof:placetype":"venue"
},
  "geometry": {"coordinates":[2.9704549313,42.2177505493],"type":"Point"}
}