{
  "type": "Feature",
  "properties": {
    "iso:country":"ES",
    "sg:address":"Carrer de Sant Vicent Ferrer, 40",
    "sg:city":"Crevillent",
    "sg:orig_category":"Ropa Para Se\u00d1oras Y Caballeros (al Por Menor)",
    "sg:phone":"+34 965 40 26 32",
    "sg:postcode":"03330",
    "sg:province":"Alicante",
    "wof:name":"Gomis Hurtado Maria Milagros",
    "wof:placetype":"venue"
},
  "geometry": {"coordinates":[-0.8037570119,38.2467422485],"type":"Point"}
}