{
  "type": "Feature",
  "properties": {
    "iso:country":"ES",
    "sg:address":"Calle de Carrera, 2",
    "sg:city":"Campanario",
    "sg:orig_category":"Ense\u00d1anza, Formaci\u00d3n Profesional: Aprendizaje",
    "sg:phone":"+34 924 85 15 75",
    "sg:postcode":"06460",
    "sg:province":"Badajoz",
    "wof:name":"Ayuntamiento De Campanario",
    "wof:placetype":"venue"
},
  "geometry": {"coordinates":[-5.6160778999,38.8616638184],"type":"Point"}
}