{
  "type": "Feature",
  "properties": {
    "addr:full":"Avda Pablo Neruda, 91 Madrid Madrid 28018",
    "addr:housenumber":"91",
    "addr:postcode":"madrid;28018",
    "addr:street":"Avda Pablo Neruda",
    "iso:country":"ES",
    "sg:address":"Avda Pablo Neruda, 91",
    "sg:city":"Madrid",
    "sg:orig_category":"Material Did\u00c1ctico",
    "sg:phone":"+34 917 86 70 06",
    "sg:postcode":"28018",
    "sg:province":"Madrid",
    "sg:website":"www.abacus.es",
    "wof:name":"Abacus Iberia S.a.",
    "wof:placetype":"venue"
},
  "geometry": {"coordinates":[-3.661305,40.381248],"type":"Point"}
}