{
  "type": "Feature",
  "properties": {
    "addr:full":"Calle de Eras, 26 Cisterniga Valladolid 47193",
    "addr:housenumber":"26",
    "addr:postcode":"47193",
    "addr:street":"Calle De Eras",
    "iso:country":"ES",
    "sg:address":"Calle de Eras, 26",
    "sg:city":"Cisterniga",
    "sg:orig_category":"Automatizaci\u00d3n De Procesos Industriales Y De Edificaci\u00d3n (estudios, Instalaci\u00d3n)",
    "sg:phone":"+34 983 40 14 59",
    "sg:postcode":"47193",
    "sg:province":"Valladolid",
    "wof:name":"Automatizacion Y Tecnologia De Organizacion Industrial S.l.",
    "wof:placetype":"venue"
},
  "geometry": {"coordinates":[-4.6813049316,41.6085777283],"type":"Point"}
}