{
  "type": "Feature",
  "properties": {
    "addr:full":"Avda Juan Sebastian Elcano, 74 Malaga M\u00e1laga 29017",
    "addr:housenumber":"74",
    "addr:postcode":"29017",
    "addr:street":"Avda Juan Sebastian Elcano;Ma\u0301Laga",
    "iso:country":"ES",
    "sg:address":"Avda Juan Sebastian Elcano, 74",
    "sg:city":"Malaga",
    "sg:classifiers":[
        {
            "category":"Personal",
            "subcategory":"Barber",
            "type":"Services"
        }
    ],
    "sg:phone":"+34 952 29 45 98",
    "sg:postcode":"29017",
    "sg:province":"M\u00e1laga",
    "sg:tags":[
        "caballeros",
        "de",
        "peluqueros"
    ],
    "wof:name":"Salguero Ramirez Oscar",
    "wof:placetype":"venue"
},
  "geometry": {"coordinates":[-4.3743047714,36.7222747803],"type":"Point"}
}