{
  "type": "Feature",
  "properties": {
    "iso:country":"ES",
    "sg:address":"Calle de Sanchez Barcaiztegui, 34",
    "sg:city":"Madrid",
    "sg:orig_category":"Doctores En Medicina",
    "sg:phone":"+34 915 52 53 64",
    "sg:postcode":"28007",
    "sg:province":"Madrid",
    "wof:name":"Madrigal Fernandez Roldan Arturo",
    "wof:placetype":"venue"
},
  "geometry": {"coordinates":[-3.6733500957,40.4053115845],"type":"Point"}
}