{
  "type": "Feature",
  "properties": {
    "iso:country":"ES",
    "sg:address":"Carr Gandia, 22",
    "sg:city":"Alfauir",
    "sg:orig_category":"Cooperativas Agr\u00cdcolas",
    "sg:phone":"+34 962 83 55 00",
    "sg:postcode":"46725",
    "sg:province":"Valencia",
    "wof:name":"Cooperativa Agricola Y Caja Rural Virgen Del Rosario",
    "wof:placetype":"venue"
},
  "geometry": {"coordinates":[-0.2518270016,38.929397583],"type":"Point"}
}