{
  "type": "Feature",
  "properties": {
    "addr:full":"Ctra. Escorial, Km. 0000,3 Las Rozas Madrid 28230",
    "addr:postcode":"28230",
    "addr:street":"Ctra. Escorial Km. 0000,3",
    "iso:country":"ES",
    "sg:address":"Ctra. Escorial, Km. 0000,3",
    "sg:city":"Las Rozas",
    "sg:orig_category":"Inmobiliaria (agencias)",
    "sg:phone":"+34 915 76 73 27",
    "sg:postcode":"28230",
    "sg:province":"Madrid",
    "sg:website":"www.grupo22.com",
    "wof:name":"Konin 22 S.a.",
    "wof:placetype":"venue"
},
  "geometry": {"coordinates":[-3.8913800716,40.5247497559],"type":"Point"}
}