{
  "type": "Feature",
  "properties": {
    "iso:country":"ES",
    "sg:address":"Av Doctor Gallart I Mones, 8",
    "sg:city":"Prat Llobregat",
    "sg:orig_category":"Droguer\u00cdas (al Por Menor)",
    "sg:phone":"+34 934 78 35 64",
    "sg:postcode":"08820",
    "sg:province":"Barcelona",
    "sg:website":"www.schlecker.com",
    "wof:name":"Schlecker S.a.",
    "wof:placetype":"venue"
},
  "geometry": {"coordinates":[2.0915110111,41.324005127],"type":"Point"}
}