{
  "type": "Feature",
  "properties": {
    "addr:full":"Calle de Tamarindo (del), S/n Parque Coimbra Madrid 28935",
    "addr:postcode":"28935",
    "addr:street":"Calle De Tamarindo Del S / N Parque",
    "iso:country":"ES",
    "sg:address":"Calle de Tamarindo (del), S/n",
    "sg:city":"Parque Coimbra",
    "sg:orig_category":"Peluquer\u00cdas, Peluquer\u00cda Mixta",
    "sg:phone":"+34 916 46 08 36",
    "sg:postcode":"28935",
    "sg:province":"Madrid",
    "wof:name":"Duran Criado Hermanos S.l",
    "wof:placetype":"venue"
},
  "geometry": {"coordinates":[-3.9230461121,40.3097991943],"type":"Point"}
}