{
  "type": "Feature",
  "properties": {
    "addr:full":"Calle de Venerable Carabantes, 1 Soria Soria 42003",
    "addr:housenumber":"1",
    "addr:postcode":"42003",
    "addr:street":"Calle De Venerable Carabantes",
    "iso:country":"ES",
    "sg:address":"Calle de Venerable Carabantes, 1",
    "sg:city":"Soria",
    "sg:orig_category":"Procuradores",
    "sg:phone":"+34 975 22 16 08",
    "sg:postcode":"42003",
    "sg:province":"Soria",
    "wof:name":"Lavilla Campo Elena",
    "wof:placetype":"venue"
},
  "geometry": {"coordinates":[-2.469367981,41.7616386414],"type":"Point"}
}