{
  "type": "Feature",
  "properties": {
    "iso:country":"ES",
    "sg:address":"Avda Alto De Las Atalayas, 55",
    "sg:city":"Cabezo Torres",
    "sg:orig_category":"Mercer\u00cda, Lencer\u00cda (al Por Menor)",
    "sg:phone":"+34 968 30 63 59",
    "sg:postcode":"30110",
    "sg:province":"Murcia",
    "wof:name":"Andreu Mu\u00f1oz Dolores",
    "wof:placetype":"venue"
},
  "geometry": {"coordinates":[-1.1247570515,38.0287437439],"type":"Point"}
}