{
  "type": "Feature",
  "properties": {
    "addr:full":"Avda Eladio Perlado, 31 Burgos Burgos 09007",
    "addr:housenumber":"31",
    "addr:postcode":"09007",
    "addr:street":"Avda Eladio Perlado",
    "iso:country":"ES",
    "sg:address":"Avda Eladio Perlado, 31",
    "sg:city":"Burgos",
    "sg:orig_category":"Molduras, Junquillos, Listones Y Molduras Perforadas",
    "sg:phone":"+34 947 48 93 36",
    "sg:postcode":"09007",
    "sg:province":"Burgos",
    "wof:name":"Talamillo Ausin Rafael",
    "wof:placetype":"venue"
},
  "geometry": {"coordinates":[-3.6668419838,42.351360321],"type":"Point"}
}