{
  "type": "Feature",
  "properties": {
    "addr:full":"Rua Nova, S/n Xunqueira Ambia Ourense 32670",
    "addr:housenumber":"s / n",
    "addr:postcode":"32670",
    "addr:street":"Rua Nova;Xunqueira Ambia",
    "iso:country":"ES",
    "sg:address":"Rua Nova, S/n",
    "sg:city":"Xunqueira Ambia",
    "sg:orig_category":"Molduras, Junquillos, Listones Y Molduras Perforadas",
    "sg:phone":"+34 988 43 61 26",
    "sg:postcode":"32670",
    "sg:province":"Ourense",
    "wof:name":"Cabido Quintas Antonio",
    "wof:placetype":"venue"
},
  "geometry": {"coordinates":[-7.7344098091,42.2057037354],"type":"Point"}
}