{
  "type": "Feature",
  "properties": {
    "addr:full":"Calle de Santa Catalina De Laboure, 15 Madrid Madrid 28019",
    "addr:housenumber":"15",
    "addr:postcode":"madrid;28019",
    "addr:street":"Calle De Santa",
    "iso:country":"ES",
    "sg:address":"Calle de Santa Catalina De Laboure, 15",
    "sg:city":"Madrid",
    "sg:orig_category":"Arquitectos",
    "sg:phone":"+34 915 60 79 98",
    "sg:postcode":"28019",
    "sg:province":"Madrid",
    "wof:name":"Jimenez Aguilar Jesus",
    "wof:placetype":"venue"
},
  "geometry": {"coordinates":[-3.7197489738,40.3872489929],"type":"Point"}
}