{
  "type": "Feature",
  "properties": {
    "addr:full":"Calle de Nicolas Morales, 38 Madrid Madrid 28019",
    "addr:housenumber":"38",
    "addr:postcode":"madrid;28019",
    "addr:street":"Calle De Nicolas Morales",
    "iso:country":"ES",
    "sg:address":"Calle de Nicolas Morales, 38",
    "sg:city":"Madrid",
    "sg:orig_category":"Inform\u00c1tica (estudios, Servicios, Asesor\u00cda, Formaci\u00d3n)",
    "sg:phone":"+34 913 64 39 60",
    "sg:postcode":"28019",
    "sg:province":"Madrid",
    "wof:name":"Sermo Informatica S.l.",
    "wof:placetype":"venue"
},
  "geometry": {"coordinates":[-3.7322850227,40.3910179138],"type":"Point"}
}