{
  "type": "Feature",
  "properties": {
    "iso:country":"ES",
    "sg:address":"Calle de Alferez Provisional, 2",
    "sg:city":"Le\u00f3n",
    "sg:orig_category":"Ropa Para Se\u00d1oras (al Por Menor)",
    "sg:phone":"+34 987 23 16 95",
    "sg:postcode":"24001",
    "sg:province":"Le\u00f3n",
    "wof:name":"Vigoree C.b",
    "wof:placetype":"venue"
},
  "geometry": {"coordinates":[-5.5755929947,42.5987014771],"type":"Point"}
}