{
  "type": "Feature",
  "properties": {
    "iso:country":"ES",
    "sg:address":"Calle de Larga, 3",
    "sg:city":"Navares Enmedio",
    "sg:orig_category":"Asilos De Ancianos. Centros Privados",
    "sg:phone":"+34 921 53 20 51",
    "sg:postcode":"40532",
    "sg:province":"Segovia",
    "wof:name":"Residencia Nuestra Casa La Grande",
    "wof:placetype":"venue"
},
  "geometry": {"coordinates":[-3.7217183113,41.3810348511],"type":"Point"}
}