{
  "type": "Feature",
  "properties": {
    "iso:country":"ES",
    "sg:address":"Av Duran I Sanpere, 9",
    "sg:city":"Cervera",
    "sg:orig_category":"Electrodom\u00c9sticos (al Por Menor)",
    "sg:phone":"+34 973 53 20 90",
    "sg:postcode":"25200",
    "sg:province":"Lleida",
    "wof:name":"Ermengol Armengol S.l.",
    "wof:placetype":"venue"
},
  "geometry": {"coordinates":[1.2707589865,41.6678276062],"type":"Point"}
}