{
  "type": "Feature",
  "properties": {
    "addr:full":"Rbla Llibertat, 30 Girona Girona 17004",
    "addr:housenumber":"30",
    "addr:postcode":"17004",
    "addr:street":"Rbla Llibertat",
    "iso:country":"ES",
    "sg:address":"Rbla Llibertat, 30",
    "sg:city":"Girona",
    "sg:orig_category":"Peluquer\u00cdas, Peluquer\u00cda Mixta",
    "sg:phone":"+34 972 22 31 63",
    "sg:postcode":"17004",
    "sg:province":"Girona",
    "wof:name":"Girame Pla Immaculada",
    "wof:placetype":"venue"
},
  "geometry": {"coordinates":[2.8241798878,41.983795166],"type":"Point"}
}