{
  "type": "Feature",
  "properties": {
    "addr:full":"Avda Fuerzas Armadas, 7 Algeciras C\u00e1diz 11202",
    "addr:housenumber":"7;ca\u0301diz",
    "addr:postcode":"11202",
    "addr:street":"Avda Fuerzas Armadas",
    "iso:country":"ES",
    "sg:address":"Avda Fuerzas Armadas, 7",
    "sg:city":"Algeciras",
    "sg:orig_category":"Asociaciones Y Clubs Deportivos",
    "sg:phone":"+34 956 66 43 43",
    "sg:postcode":"11202",
    "sg:province":"C\u00e1diz",
    "wof:name":"Bandera Sanchez Maria Teresa",
    "wof:placetype":"venue"
},
  "geometry": {"coordinates":[-5.4494137764,36.1337280273],"type":"Point"}
}