{
  "type": "Feature",
  "properties": {
    "addr:full":"Calle de Jacinto Benavente (de), 20 Humanes De Madrid Madrid 28970",
    "addr:housenumber":"20",
    "addr:postcode":"28970",
    "addr:street":"Calle De Jacinto Benavente De",
    "iso:country":"ES",
    "sg:address":"Calle de Jacinto Benavente (de), 20",
    "sg:city":"Humanes De Madrid",
    "sg:orig_category":"Tiendas De Grano, Frutas Y Legumbres Secas (al Por Menor)",
    "sg:phone":"+34 916 04 89 19",
    "sg:postcode":"28970",
    "sg:province":"Madrid",
    "wof:name":"El Jebary  Rachida",
    "wof:placetype":"venue"
},
  "geometry": {"coordinates":[-3.8225679398,40.2599945068],"type":"Point"}
}