{
  "type": "Feature",
  "properties": {
    "addr:full":"Pase Ubarburu De, 32 Donostia-san Sebastian Guip\u00f9zcoa 20014",
    "addr:housenumber":"32",
    "addr:postcode":"20014",
    "iso:country":"ES",
    "sg:address":"Pase Ubarburu De, 32",
    "sg:city":"Donostia-san Sebastian",
    "sg:orig_category":"Comercio De Piezas De Recambio Y De Accesorios De Veh\u00cdculos, Veh\u00cdculos Industriales",
    "sg:phone":"+34 943 46 48 90",
    "sg:postcode":"20014",
    "sg:province":"Guip\u00f9zcoa",
    "sg:website":"www.audioracing.com",
    "wof:name":"Pinilla San Maximo Juan Carlos",
    "wof:placetype":"venue"
},
  "geometry": {"coordinates":[-1.9009970427,43.2548027039],"type":"Point"}
}