{
  "type": "Feature",
  "properties": {
    "addr:full":"Pg Santa Coloma, 27 Barcelona Barcelona 08030",
    "addr:housenumber":"27",
    "addr:postcode":"08030",
    "addr:street":"Pg Santa Coloma",
    "iso:country":"ES",
    "sg:address":"Pg Santa Coloma, 27",
    "sg:city":"Barcelona",
    "sg:orig_category":"Venta, Montaje De Neum\u00c1ticos",
    "sg:phone":"+34 933 11 22 55",
    "sg:postcode":"08030",
    "sg:province":"Barcelona",
    "wof:name":"Llansa Tarda Juan",
    "wof:placetype":"venue"
},
  "geometry": {"coordinates":[2.1896729469,41.4451255798],"type":"Point"}
}