{
  "type": "Feature",
  "properties": {
    "addr:full":"Carrer de Maragall, 15 Senia Tarragona 43560",
    "addr:housenumber":"15",
    "addr:postcode":"43560",
    "addr:street":"Carrer De Maragall",
    "iso:country":"ES",
    "sg:address":"Carrer de Maragall, 15",
    "sg:city":"Senia",
    "sg:orig_category":"Alquiler De V\u00cddeo",
    "sg:phone":"+34 977 57 00 32",
    "sg:postcode":"43560",
    "sg:province":"Tarragona",
    "sg:website":"www.cinemacvideo.com",
    "wof:name":"Cinemac La Senia S.l.",
    "wof:placetype":"venue"
},
  "geometry": {"coordinates":[0.2839699984,40.6353416443],"type":"Point"}
}