{
  "type": "Feature",
  "properties": {
    "addr:full":"Benicarlo, 4 Burriana Castell\u00f3n 12530",
    "addr:housenumber":"4",
    "addr:postcode":"12530",
    "addr:street":"Benicarlo",
    "iso:country":"ES",
    "sg:address":"Benicarlo, 4",
    "sg:city":"Burriana",
    "sg:orig_category":"Negocio De Enlosados, Soler\u00cdas",
    "sg:phone":"+34 964 58 70 07",
    "sg:postcode":"12530",
    "sg:province":"Castell\u00f3n",
    "wof:name":"Burrianense De Inversiones S.a.",
    "wof:placetype":"venue"
},
  "geometry": {"coordinates":[-0.0563829988,39.8767318726],"type":"Point"}
}