{
  "type": "Feature",
  "properties": {
    "iso:country":"ES",
    "sg:address":"Avda Granada (de), 10",
    "sg:city":"Cordoba",
    "sg:orig_category":"Inmobiliaria (agencias)",
    "sg:phone":"+34 957 29 39 14",
    "sg:postcode":"14009",
    "sg:province":"C\u00f3rdoba",
    "sg:website":"www.tempocasa.com",
    "wof:name":"Estudio Sur S.l.",
    "wof:placetype":"venue"
},
  "geometry": {"coordinates":[-4.7729730606,37.8743400574],"type":"Point"}
}