{
  "type": "Feature",
  "properties": {
    "addr:full":"Calle de Gran Via, S/n Blanca Murcia 30540",
    "addr:postcode":"30540",
    "addr:street":"Calle De Gran Via S / N Blanca",
    "iso:country":"ES",
    "sg:address":"Calle de Gran Via, S/n",
    "sg:city":"Blanca",
    "sg:orig_category":"Cajas De Ahorro",
    "sg:phone":"+34 968 77 80 00",
    "sg:postcode":"30540",
    "sg:province":"Murcia",
    "wof:name":"Caja De Ahorros De Murcia",
    "wof:placetype":"venue"
},
  "geometry": {"coordinates":[-1.3735259771,38.1792373657],"type":"Point"}
}