{
  "type": "Feature",
  "properties": {
    "iso:country":"ES",
    "sg:address":"Avda Ricardo Soriano, 27",
    "sg:city":"Marbella",
    "sg:orig_category":"Farmacias",
    "sg:phone":"+34 952 77 22 87",
    "sg:postcode":"29600",
    "sg:province":"M\u00e1laga",
    "wof:name":"Farmacia Homeopharma S.c.",
    "wof:placetype":"venue"
},
  "geometry": {"coordinates":[-4.8906168938,36.5102539062],"type":"Point"}
}