{
  "type": "Feature",
  "properties": {
    "addr:full":"Carrer de Velazquez, 4 Palma Islas Baleares 07002",
    "addr:housenumber":"4",
    "addr:postcode":"07002",
    "addr:street":"Carrer De Velazquez",
    "iso:country":"ES",
    "sg:address":"Carrer de Velazquez, 4",
    "sg:city":"Palma",
    "sg:orig_category":"Asesor\u00cda De Formaci\u00d3n Y Gesti\u00d3n De Personal",
    "sg:phone":"+34 971 71 24 11",
    "sg:postcode":"07002",
    "sg:province":"Islas Baleares",
    "wof:name":"Uxio Digital S.l.",
    "wof:placetype":"venue"
},
  "geometry": {"coordinates":[2.6541690826,39.5734634399],"type":"Point"}
}