{
  "type": "Feature",
  "properties": {
    "iso:country":"ES",
    "sg:address":"Ptge Prudencia, 29",
    "sg:city":"Terrassa",
    "sg:orig_category":"Radiocomunicaciones, Telefon\u00cda M\u00d3vil, Radiomensajer\u00cda: Servicios, Comercializaci\u00d3n",
    "sg:phone":"+34 937 84 54 47",
    "sg:postcode":"08222",
    "sg:province":"Barcelona",
    "wof:name":"Lacono De Calatraba Graciela Ana",
    "wof:placetype":"venue"
},
  "geometry": {"coordinates":[2.029779911,41.5668296814],"type":"Point"}
}