{
  "type": "Feature",
  "properties": {
    "iso:country":"ES",
    "sg:address":"Avda Galicia (de), 33",
    "sg:city":"Ribadeo",
    "sg:orig_category":"Juegos Y Juguetes (al Por Menor)",
    "sg:phone":"+34 982 12 89 95",
    "sg:postcode":"27700",
    "sg:province":"Lugo",
    "wof:name":"Ili C.b.",
    "wof:placetype":"venue"
},
  "geometry": {"coordinates":[-7.0477337837,43.5367736816],"type":"Point"}
}