{
  "type": "Feature",
  "properties": {
    "addr:full":"Urb Yuca De La Font, 7 S. Juan Alicante Alicante 03550",
    "addr:housenumber":"7",
    "addr:postcode":"03550",
    "addr:street":"Urb;De La Font;S. Juan",
    "iso:country":"ES",
    "sg:address":"Urb Yuca De La Font, 7",
    "sg:city":"S. Juan Alicante",
    "sg:orig_category":"Centros Empresariales",
    "sg:phone":"+34 965 65 31 82",
    "sg:postcode":"03550",
    "sg:province":"Alicante",
    "wof:name":"Alamo Badillo Aurelio",
    "wof:placetype":"venue"
},
  "geometry": {"coordinates":[-0.4810059965,38.3452033997],"type":"Point"}
}