{
  "type": "Feature",
  "properties": {
    "addr:full":"Tiburzio Anitua Kalea, 6 Eibar Guip\u00f9zcoa 20600",
    "addr:housenumber":"6",
    "addr:postcode":"20600",
    "addr:street":"Tiburzio Anitua Kalea;Guipu\u0300Zcoa",
    "iso:country":"ES",
    "sg:address":"Tiburzio Anitua Kalea, 6",
    "sg:city":"Eibar",
    "sg:orig_category":"Reposter\u00cdas",
    "sg:phone":"+34 943 20 04 04",
    "sg:postcode":"20600",
    "sg:province":"Guip\u00f9zcoa",
    "wof:name":"Panaderia Zubizarreta Sl",
    "wof:placetype":"venue"
},
  "geometry": {"coordinates":[-2.4822320938,43.1834793091],"type":"Point"}
}