{
  "type": "Feature",
  "properties": {
    "iso:country":"ES",
    "sg:address":"Calle de Rio Ebro, 13",
    "sg:city":"Fuenlabrada",
    "sg:orig_category":"F\u00c1bricas De Ladrillo Y Tejas",
    "sg:phone":"+34 916 21 40 41",
    "sg:postcode":"28947",
    "sg:province":"Madrid",
    "sg:website":"www.tejasborja.es",
    "wof:name":"Tejas Borja S. A.",
    "wof:placetype":"venue"
},
  "geometry": {"coordinates":[-3.7560911179,40.2671394348],"type":"Point"}
}