{
  "type": "Feature",
  "properties": {
    "iso:country":"ES",
    "sg:address":"La Pinta, S/n",
    "sg:city":"Churriana Vega",
    "sg:orig_category":"Barnizadores",
    "sg:phone":"+34 958 55 31 34",
    "sg:postcode":"18194",
    "sg:province":"Granada",
    "wof:name":"Barniz Actual 2005 S.l.",
    "wof:placetype":"venue"
},
  "geometry": {"coordinates":[-3.6305289268,37.1487998962],"type":"Point"}
}