{
  "type": "Feature",
  "properties": {
    "addr:full":"Calle de Doce De Octubre, 7 Cordoba C\u00f3rdoba 14001",
    "addr:housenumber":"7",
    "addr:postcode":"14001",
    "addr:street":"Calle De Doce De Octubre;Co\u0301Rdoba",
    "iso:country":"ES",
    "sg:address":"Calle de Doce De Octubre, 7",
    "sg:city":"Cordoba",
    "sg:orig_category":"Perfumer\u00cda (al Por Menor)",
    "sg:phone":"+34 957 48 52 07",
    "sg:postcode":"14001",
    "sg:province":"C\u00f3rdoba",
    "wof:name":"Serrano Gomez Mercedes Elvira C.b.",
    "wof:placetype":"venue"
},
  "geometry": {"coordinates":[-4.7815170288,37.8894233704],"type":"Point"}
}