{
  "type": "Feature",
  "properties": {
    "iso:country":"ES",
    "sg:address":"Calle de Calvario, 51",
    "sg:city":"Olvera",
    "sg:orig_category":"Asesor\u00cda Fiscal Y Jur\u00cddica",
    "sg:phone":"+34 956 12 07 54",
    "sg:postcode":"11690",
    "sg:province":"C\u00e1diz",
    "wof:name":"Olvegest-s.xxi S.l.",
    "wof:placetype":"venue"
},
  "geometry": {"coordinates":[-5.2610359192,36.9350814819],"type":"Point"}
}