{
  "type": "Feature",
  "properties": {
    "addr:full":"Calle de Arturo Soria, 31 Madrid Madrid 28027",
    "addr:housenumber":"31",
    "addr:postcode":"madrid;28027",
    "addr:street":"Calle De Arturo Soria",
    "iso:country":"ES",
    "sg:address":"Calle de Arturo Soria, 31",
    "sg:city":"Madrid",
    "sg:orig_category":"Agricultura: Abastecimiento Y Cosechado (negocio)",
    "sg:phone":"+34 913 68 19 45",
    "sg:postcode":"28027",
    "sg:province":"Madrid",
    "wof:name":"Vi\u00f1as De Arriba S.a.",
    "wof:placetype":"venue"
},
  "geometry": {"coordinates":[-3.6409459114,40.44165802],"type":"Point"}
}