{
  "type": "Feature",
  "properties": {
    "addr:full":"Plaz San Antonio, 21 Vinaros Castell\u00f3n 12500",
    "addr:housenumber":"21",
    "addr:postcode":"12500",
    "addr:street":"Plaz San Antonio",
    "iso:country":"ES",
    "sg:address":"Plaz San Antonio, 21",
    "sg:city":"Vinaros",
    "sg:orig_category":"Estancos",
    "sg:phone":"+34 964 45 40 93",
    "sg:postcode":"12500",
    "sg:province":"Castell\u00f3n",
    "wof:name":"Lopez Meseguer Francisca",
    "wof:placetype":"venue"
},
  "geometry": {"coordinates":[0.4749450088,40.4711990356],"type":"Point"}
}