{
  "type": "Feature",
  "properties": {
    "iso:country":"ES",
    "sg:address":"Carr Badia, 53",
    "sg:city":"Moncada",
    "sg:orig_category":"Alimentaci\u00d3n General (al Por Menor)",
    "sg:phone":"+34 961 39 22 62",
    "sg:postcode":"46113",
    "sg:province":"Valencia",
    "wof:name":"Martinez Talaya Antonio",
    "wof:placetype":"venue"
},
  "geometry": {"coordinates":[-0.3996559978,39.5423851013],"type":"Point"}
}