{
  "type": "Feature",
  "properties": {
    "addr:full":"Av Albir (l'), 28 Albir Alicante 03580",
    "addr:housenumber":"28",
    "addr:postcode":"03580",
    "addr:street":"Av Albir L ';Alicante",
    "iso:country":"ES",
    "sg:address":"Av Albir (l'), 28",
    "sg:city":"Albir",
    "sg:orig_category":"Financiaci\u00d3n Y Cr\u00c9ditos",
    "sg:phone":"+34 966 86 50 75",
    "sg:postcode":"03580",
    "sg:province":"Alicante",
    "wof:name":"Caixa Rural Altea",
    "wof:placetype":"venue"
},
  "geometry": {"coordinates":[-0.0678000003,38.5715827942],"type":"Point"}
}