{
  "type": "Feature",
  "properties": {
    "addr:full":"Avda Carlos I De, 38 Donostia-san Sebastian Guip\u00f9zcoa 20011",
    "addr:housenumber":"38",
    "addr:postcode":"20011",
    "addr:street":"Avda Carlos I De",
    "iso:country":"ES",
    "sg:address":"Avda Carlos I De, 38",
    "sg:city":"Donostia-san Sebastian",
    "sg:orig_category":"Abogados",
    "sg:phone":"+34 943 46 90 45",
    "sg:postcode":"20011",
    "sg:province":"Guip\u00f9zcoa",
    "wof:name":"Antonio  Mugica  Iraola (abogado)",
    "wof:placetype":"venue"
},
  "geometry": {"coordinates":[-1.9788395166,43.3028182983],"type":"Point"}
}