{
  "type": "Feature",
  "properties": {
    "addr:full":"Calle de Mantas, 7 Valencia Valencia 46001",
    "addr:housenumber":"7",
    "addr:postcode":"46001",
    "addr:street":"Calle De Mantas",
    "iso:country":"ES",
    "sg:address":"Calle de Mantas, 7",
    "sg:city":"Valencia",
    "sg:orig_category":"Bancos",
    "sg:phone":"+34 963 92 31 55",
    "sg:postcode":"46001",
    "sg:province":"Valencia",
    "wof:name":"Banco De Valencia S.a.",
    "wof:placetype":"venue"
},
  "geometry": {"coordinates":[-0.3774890006,39.4735221863],"type":"Point"}
}