{
  "type": "Feature",
  "properties": {
    "iso:country":"ES",
    "sg:address":"Rua Cultura (da), S/n",
    "sg:city":"Figueroa De Arriba",
    "sg:classifiers":[
        {
            "category":"Community Center",
            "subcategory":"Youth",
            "type":"Public Place"
        }
    ],
    "sg:phone":"+34 986 57 26 31",
    "sg:postcode":"36681",
    "sg:province":"Pontevedra",
    "sg:tags":[
        "juventud",
        "administraci\u00d3n",
        "la",
        "en",
        "deporte",
        "el",
        "y"
    ],
    "sg:website":"www.gaiagd.com",
    "wof:name":"Dinamik Scd S.l.",
    "wof:placetype":"venue"
},
  "geometry": {"coordinates":[-8.7190141678,42.6886940002],"type":"Point"}
}