{
  "type": "Feature",
  "properties": {
    "addr:full":"Calle de Archiduque Carlos, 58 Valencia Valencia 46014",
    "addr:housenumber":"58",
    "addr:postcode":"46014",
    "addr:street":"Calle De Archiduque Carlos",
    "iso:country":"ES",
    "sg:address":"Calle de Archiduque Carlos, 58",
    "sg:city":"Valencia",
    "sg:orig_category":"Empresas De Carpinter\u00cda",
    "sg:phone":"+34 963 57 35 87",
    "sg:postcode":"46014",
    "sg:province":"Valencia",
    "wof:name":"Cristaleria Fortuna S.l.",
    "wof:placetype":"venue"
},
  "geometry": {"coordinates":[-0.3987990022,39.4614982605],"type":"Point"}
}