{
  "type": "Feature",
  "properties": {
    "addr:full":"Carr Sant Carles, 11 Lleida Lleida 25002",
    "addr:housenumber":"11",
    "addr:postcode":"25002",
    "addr:street":"Carr Sant Carles",
    "iso:country":"ES",
    "sg:address":"Carr Sant Carles, 11",
    "sg:city":"Lleida",
    "sg:orig_category":"Inmobiliaria (agencias)",
    "sg:phone":"+34 973 26 51 90",
    "sg:postcode":"25002",
    "sg:province":"Lleida",
    "wof:name":"Projectes I Serveis Fincalex S.l.",
    "wof:placetype":"venue"
},
  "geometry": {"coordinates":[0.6216490269,41.6168212891],"type":"Point"}
}