{
  "type": "Feature",
  "properties": {
    "addr:full":"Av J Carlos I(bda H America), S/n Los Dolores Murcia 30310",
    "addr:housenumber":"s / n",
    "addr:postcode":"30310",
    "addr:street":"Av J Carlos I Bda H America",
    "iso:country":"ES",
    "sg:address":"Av J Carlos I(bda H America), S/n",
    "sg:city":"Los Dolores",
    "sg:orig_category":"Agentes, Concesionarios Y Sucursales De Veh\u00cdculos",
    "sg:phone":"+34 968 33 00 80",
    "sg:postcode":"30310",
    "sg:province":"Murcia",
    "wof:name":"Automenor S.a.",
    "wof:placetype":"venue"
},
  "geometry": {"coordinates":[-1.0032459497,37.6396369934],"type":"Point"}
}