{
  "type": "Feature",
  "properties": {
    "iso:country":"ES",
    "sg:address":"Carrer de Corro, 166",
    "sg:city":"Granollers",
    "sg:orig_category":"M\u00c9dicos: Pediatr\u00cda. Enfermedades De Los Ni\u00d1os",
    "sg:phone":"+34 938 49 11 62",
    "sg:postcode":"08401",
    "sg:province":"Barcelona",
    "wof:name":"Bosch Marcet Joaquin",
    "wof:placetype":"venue"
},
  "geometry": {"coordinates":[2.2898240089,41.6132774353],"type":"Point"}
}