{
  "type": "Feature",
  "properties": {
    "addr:full":"Donramiro, 11 Donramiro Pontevedra 36500",
    "addr:housenumber":"11",
    "addr:postcode":"36500",
    "addr:street":"Donramiro",
    "iso:country":"ES",
    "sg:address":"Donramiro, 11",
    "sg:city":"Donramiro",
    "sg:orig_category":"Parques De Atracciones Y Centros De Esparcimiento",
    "sg:phone":"+34 986 78 70 69",
    "sg:postcode":"36500",
    "sg:province":"Pontevedra",
    "wof:name":"Automaticos Antyoli S.l.",
    "wof:placetype":"venue"
},
  "geometry": {"coordinates":[-8.1106138229,42.6577606201],"type":"Point"}
}