{
  "type": "Feature",
  "properties": {
    "iso:country":"ES",
    "sg:address":"Bard Ruini (el), 10",
    "sg:city":"Ruini",
    "sg:orig_category":"Cajas Y Embalajes De Madera",
    "sg:phone":"+34 950 64 51 96",
    "sg:postcode":"04560",
    "sg:province":"Almer\u00eda",
    "wof:name":"Envases Forte S.a.",
    "wof:placetype":"venue"
},
  "geometry": {"coordinates":[-2.4912369251,36.9528274536],"type":"Point"}
}