{
  "type": "Feature",
  "properties": {
    "addr:full":"Cmno San Juan, S/n Corella Navarra 31591",
    "addr:housenumber":"s / n",
    "addr:postcode":"31591",
    "addr:street":"Cmno San Juan",
    "iso:country":"ES",
    "sg:address":"Cmno San Juan, S/n",
    "sg:city":"Corella",
    "sg:orig_category":"Art\u00cdculos Funerarios (al Por Menor)",
    "sg:phone":"+34 948 40 16 40",
    "sg:postcode":"31591",
    "sg:province":"Navarra",
    "wof:name":"Tanatorio Y Funeraria La Tudelana S.l.",
    "wof:placetype":"venue"
},
  "geometry": {"coordinates":[-1.7851239443,42.1136436462],"type":"Point"}
}