{
  "type": "Feature",
  "properties": {
    "addr:full":"Calle de Jose Payan Garrido, 26 San Juan De Aznalfarache Sevilla 41920",
    "addr:housenumber":"26",
    "addr:postcode":"41920",
    "addr:street":"Calle De Jose Payan Garrido",
    "iso:country":"ES",
    "sg:address":"Calle de Jose Payan Garrido, 26",
    "sg:city":"San Juan De Aznalfarache",
    "sg:orig_category":"Supermercados Y Hipermercados",
    "sg:phone":"+34 954 76 39 83",
    "sg:postcode":"41920",
    "sg:province":"Sevilla",
    "wof:name":"Mateo Martin Catalina",
    "wof:placetype":"venue"
},
  "geometry": {"coordinates":[-6.0358991623,37.3597183228],"type":"Point"}
}