{
  "type": "Feature",
  "properties": {
    "addr:full":"Carr Federico Garcia Lorca, 23 Alfas Pi Alicante 03580",
    "addr:housenumber":"23",
    "addr:postcode":"03580",
    "addr:street":"Carr Federico Garcia Lorca",
    "iso:country":"ES",
    "sg:address":"Carr Federico Garcia Lorca, 23",
    "sg:city":"Alfas Pi",
    "sg:orig_category":"Inform\u00c1tica, Ofim\u00c1tica (estudios, Asesor\u00cda, Ingenier\u00cda, Formaci\u00d3n)",
    "sg:phone":"+34 965 88 94 29",
    "sg:postcode":"03580",
    "sg:province":"Alicante",
    "wof:name":"Caceres  Marcelo",
    "wof:placetype":"venue"
},
  "geometry": {"coordinates":[-0.1106439978,38.5881652832],"type":"Point"}
}