{
  "type": "Feature",
  "properties": {
    "iso:country":"ES",
    "sg:address":"Avda Condesa Sagasta, 8",
    "sg:city":"Le\u00f3n",
    "sg:orig_category":"M\u00c9dicos: Cirug\u00cda Ortop\u00c9dica Y Traumatolog\u00cda",
    "sg:phone":"+34 987 23 72 57",
    "sg:postcode":"24001",
    "sg:province":"Le\u00f3n",
    "wof:name":"Fidalgo Calzadilla Enrique",
    "wof:placetype":"venue"
},
  "geometry": {"coordinates":[-5.578868866,42.5976982117],"type":"Point"}
}