{
  "type": "Feature",
  "properties": {
    "iso:country":"ES",
    "sg:address":"Calle de Claudio Coello, 60",
    "sg:city":"Madrid",
    "sg:orig_category":"Asesor\u00cda Fiscal Y Jur\u00cddica",
    "sg:phone":"+34 915 77 95 18",
    "sg:postcode":"28001",
    "sg:province":"Madrid",
    "wof:name":"Fidentia Asesores S.c.",
    "wof:placetype":"venue"
},
  "geometry": {"coordinates":[-3.6861145496,40.4283676147],"type":"Point"}
}