{
  "type": "Feature",
  "properties": {
    "iso:country":"ES",
    "sg:address":"Calle de Castilla, 77",
    "sg:city":"Sevilla",
    "sg:orig_category":"Centros De Educaci\u00d3n Especial",
    "sg:phone":"+34 954 34 25 74",
    "sg:postcode":"41010",
    "sg:province":"Sevilla",
    "wof:name":"Castibor S.l.",
    "wof:placetype":"venue"
},
  "geometry": {"coordinates":[-6.0070471764,37.3882293701],"type":"Point"}
}