{
  "type": "Feature",
  "properties": {
    "addr:full":"Carrer de Pla De Fornells, 69 Barcelona Barcelona 08042",
    "addr:housenumber":"69",
    "addr:postcode":"08042",
    "addr:street":"Carrer De Pla De Fornells",
    "iso:country":"ES",
    "sg:address":"Carrer de Pla De Fornells, 69",
    "sg:city":"Barcelona",
    "sg:orig_category":"Alimentaci\u00d3n General (al Por Menor)",
    "sg:phone":"+34 933 53 15 58",
    "sg:postcode":"08042",
    "sg:province":"Barcelona",
    "wof:name":"Paspuel Velarde Sandra",
    "wof:placetype":"venue"
},
  "geometry": {"coordinates":[2.1745519638,41.4483032227],"type":"Point"}
}