{
  "type": "Feature",
  "properties": {
    "iso:country":"ES",
    "sg:address":"Carr Vila Antonia, 8",
    "sg:city":"Lleida",
    "sg:orig_category":"Peluquer\u00cdas, Peluquer\u00cda Mixta",
    "sg:phone":"+34 973 24 67 86",
    "sg:postcode":"25007",
    "sg:province":"Lleida",
    "wof:name":"Hair Studio S.c.p.",
    "wof:placetype":"venue"
},
  "geometry": {"coordinates":[0.6313089728,41.6177558899],"type":"Point"}
}