{
  "type": "Feature",
  "properties": {
    "addr:full":"Calle de Triana, 84 Palmas De Gran Canaria Las Palmas 35002",
    "addr:housenumber":"84",
    "addr:postcode":"35002",
    "addr:street":"Calle De Triana",
    "iso:country":"ES",
    "sg:address":"Calle de Triana, 84",
    "sg:city":"Palmas De Gran Canaria",
    "sg:orig_category":"Abogados",
    "sg:phone":"+34 928 36 34 32",
    "sg:postcode":"35002",
    "sg:province":"Las Palmas",
    "wof:name":"Rosario Rosario Maria Esther Del",
    "wof:placetype":"venue"
},
  "geometry": {"coordinates":[-15.4163093567,28.106388092],"type":"Point"}
}