{
  "type": "Feature",
  "properties": {
    "addr:full":"Calle de Fernando H. Guzman, 5 Santa Cruz De Tenerife Santa Cruz De Tenerife 38001",
    "addr:housenumber":"5",
    "addr:postcode":"38001",
    "addr:street":"Calle De Fernando H. Guzman",
    "iso:country":"ES",
    "sg:address":"Calle de Fernando H. Guzman, 5",
    "sg:city":"Santa Cruz De Tenerife",
    "sg:orig_category":"Inmobiliaria (agencias)",
    "sg:phone":"+34 922 24 57 51",
    "sg:postcode":"38001",
    "sg:province":"Santa Cruz De Tenerife",
    "wof:name":"Maca Canarias S.a.",
    "wof:placetype":"venue"
},
  "geometry": {"coordinates":[-16.2475318909,28.4788188934],"type":"Point"}
}