{
  "type": "Feature",
  "properties": {
    "addr:full":"Plaz San Rafael, 13 Vecindario Las Palmas 35110",
    "addr:housenumber":"13",
    "addr:postcode":"35110",
    "addr:street":"Plaz San Rafael;Palmas",
    "iso:country":"ES",
    "sg:address":"Plaz San Rafael, 13",
    "sg:city":"Vecindario",
    "sg:orig_category":"Inmobiliaria (agencias)",
    "sg:phone":"+34 928 79 37 97",
    "sg:postcode":"35110",
    "sg:province":"Las Palmas",
    "sg:website":"www.principainmobiliaria.com",
    "wof:name":"Canarias Principal Service S.l.",
    "wof:placetype":"venue"
},
  "geometry": {"coordinates":[-15.4424037933,27.847442627],"type":"Point"}
}