{
  "type": "Feature",
  "properties": {
    "iso:country":"ES",
    "sg:address":"Calle de Virgen De Lourdes, 26",
    "sg:city":"Madrid",
    "sg:orig_category":"Arreglo, Reparaci\u00d3n, Piezas Sueltas De Televisi\u00d3n, V\u00cddeo, Hi",
    "sg:phone":"+34 914 03 09 31",
    "sg:postcode":"28027",
    "sg:province":"Madrid",
    "wof:name":"Electronica Tejedor S.l.",
    "wof:placetype":"venue"
},
  "geometry": {"coordinates":[-3.656965971,40.4358520508],"type":"Point"}
}