{
  "type": "Feature",
  "properties": {
    "addr:full":"Plaz Paz (de La), 1 Orotava Santa Cruz De Tenerife 38300",
    "addr:housenumber":"1",
    "addr:postcode":"38300",
    "addr:street":"Plaz;Orotava",
    "iso:country":"ES",
    "sg:address":"Plaz Paz (de La), 1",
    "sg:city":"Orotava",
    "sg:orig_category":"Mataderos De Poller\u00cda",
    "sg:phone":"+34 922 33 11 71",
    "sg:postcode":"38300",
    "sg:province":"Santa Cruz De Tenerife",
    "wof:name":"Gonzalez Vera Manuel",
    "wof:placetype":"venue"
},
  "geometry": {"coordinates":[-16.5189990997,28.3903846741],"type":"Point"}
}