{
  "type": "Feature",
  "properties": {
    "addr:full":"Avda Coronel Baeza, 1 Toledo Toledo 45004",
    "addr:housenumber":"1",
    "addr:postcode":"45004",
    "addr:street":"Avda Coronel Baeza",
    "iso:country":"ES",
    "sg:address":"Avda Coronel Baeza, 1",
    "sg:city":"Toledo",
    "sg:orig_category":"M\u00c9dicos: An\u00c1lisis Cl\u00cdnicos",
    "sg:phone":"+34 925 22 44 34",
    "sg:postcode":"45004",
    "sg:province":"Toledo",
    "wof:name":"Diaz Santafe Jose",
    "wof:placetype":"venue"
},
  "geometry": {"coordinates":[-4.0317549706,39.8687896729],"type":"Point"}
}