{
  "type": "Feature",
  "properties": {
    "addr:full":"Doctor Simonena, 1 Iru\u00f1a Navarra 31012",
    "addr:housenumber":"1",
    "addr:postcode":"31012",
    "addr:street":"Doctor Simonena",
    "iso:country":"ES",
    "sg:address":"Doctor Simonena, 1",
    "sg:city":"Iru\u00f1a",
    "sg:orig_category":"Cl\u00cdnicas Dentales",
    "sg:phone":"+34 948 14 80 18",
    "sg:postcode":"31012",
    "sg:province":"Navarra",
    "wof:name":"Vasquez Ramirez Ricardo",
    "wof:placetype":"venue"
},
  "geometry": {"coordinates":[-1.668462038,42.8207054138],"type":"Point"}
}