{
  "type": "Feature",
  "properties": {
    "addr:full":"Carrer de Bisbe Campins, 8 Palma Islas Baleares 07012",
    "addr:housenumber":"8",
    "addr:postcode":"07012",
    "addr:street":"Carrer De Bisbe Campins",
    "iso:country":"ES",
    "sg:address":"Carrer de Bisbe Campins, 8",
    "sg:city":"Palma",
    "sg:orig_category":"Confiter\u00cdas, Chocolater\u00cdas (al Por Menor)",
    "sg:phone":"+34 971 71 05 99",
    "sg:postcode":"07012",
    "sg:province":"Islas Baleares",
    "wof:name":"Cladera Pomar Miguel Angel",
    "wof:placetype":"venue"
},
  "geometry": {"coordinates":[2.6461889744,39.575340271],"type":"Point"}
}