{
  "type": "Feature",
  "properties": {
    "addr:full":"Carrer de Cirerer, 21 Palma Islas Baleares 07008",
    "addr:housenumber":"21",
    "addr:postcode":"07008",
    "addr:street":"Carrer De Cirerer",
    "iso:country":"ES",
    "sg:address":"Carrer de Cirerer, 21",
    "sg:city":"Palma",
    "sg:orig_category":"Inform\u00c1tica (estudios, Servicios, Asesor\u00cda, Formaci\u00d3n)",
    "sg:phone":"+34 971 47 53 48",
    "sg:postcode":"07008",
    "sg:province":"Islas Baleares",
    "wof:name":"Jimenez Jimenez Angel",
    "wof:placetype":"venue"
},
  "geometry": {"coordinates":[2.6767408848,39.5855407715],"type":"Point"}
}