{
  "type": "Feature",
  "properties": {
    "addr:full":"Avda Vi\u00d1uelas (de), 34 Tres Cantos Madrid 28760",
    "addr:housenumber":"34",
    "addr:postcode":"28760",
    "addr:street":"Avda Vin\u0303Uelas De",
    "iso:country":"ES",
    "sg:address":"Avda Vi\u00d1uelas (de), 34",
    "sg:city":"Tres Cantos",
    "sg:orig_category":"Laboratorios Y Trabajos De Fotograf\u00cda, V\u00cddeo Y Cine",
    "sg:phone":"+34 918 04 40 45",
    "sg:postcode":"28760",
    "sg:province":"Madrid",
    "wof:name":"Mayor Foto S.l.",
    "wof:placetype":"venue"
},
  "geometry": {"coordinates":[-3.7021830082,40.5960922241],"type":"Point"}
}