{
  "type": "Feature",
  "properties": {
    "addr:full":"Carrer de Riu Tordera, 9 Prat Llobregat Barcelona 08820",
    "addr:housenumber":"9",
    "addr:postcode":"08820",
    "addr:street":"Carrer De Riu Tordera;Llobregat",
    "iso:country":"ES",
    "sg:address":"Carrer de Riu Tordera, 9",
    "sg:city":"Prat Llobregat",
    "sg:orig_category":"Empresas De Carpinter\u00cda De Madera",
    "sg:phone":"+34 933 70 97 52",
    "sg:postcode":"08820",
    "sg:province":"Barcelona",
    "wof:name":"Juarez Martinez Jesus",
    "wof:placetype":"venue"
},
  "geometry": {"coordinates":[2.0888381004,41.3153839111],"type":"Point"}
}