{
  "type": "Feature",
  "properties": {
    "iso:country":"ES",
    "sg:address":"Avda Constitucion (de La), 27",
    "sg:city":"Granada",
    "sg:orig_category":"M\u00c9dicos: Reumatolog\u00cda",
    "sg:phone":"+34 958 20 50 33",
    "sg:postcode":"18014",
    "sg:province":"Granada",
    "wof:name":"Aguilar Salvatierra Jose",
    "wof:placetype":"venue"
},
  "geometry": {"coordinates":[-3.6081163883,37.1857948303],"type":"Point"}
}