{
  "type": "Feature",
  "properties": {
    "iso:country":"ES",
    "sg:address":"Avda Sancho El Sabio, 11",
    "sg:city":"Donostia-san Sebastian",
    "sg:classifiers":[
        {
            "category":"Tea Room",
            "subcategory":"None",
            "type":"Food & Drink"
        }
    ],
    "sg:phone":"+34 943 45 52 11",
    "sg:postcode":"20010",
    "sg:province":"Guip\u00f9zcoa",
    "sg:tags":[
        "snack"
    ],
    "wof:name":"Diaz Mogollon Francisca",
    "wof:placetype":"venue"
},
  "geometry": {"coordinates":[-1.9798159599,43.3103981018],"type":"Point"}
}