{
  "type": "Feature",
  "properties": {
    "addr:full":"Calle de Despe\u00d1adero, 2 Horcajo Santiago Cuenca 16410",
    "addr:housenumber":"2",
    "addr:postcode":"16410",
    "addr:street":"Calle De Despen\u0303Adero;Cuenca",
    "iso:country":"ES",
    "sg:address":"Calle de Despe\u00d1adero, 2",
    "sg:city":"Horcajo Santiago",
    "sg:orig_category":"Transporte En General",
    "sg:phone":"+34 969 12 71 87",
    "sg:postcode":"16410",
    "sg:province":"Cuenca",
    "wof:name":"Horcampo S.l.",
    "wof:placetype":"venue"
},
  "geometry": {"coordinates":[-2.9966623783,39.8424263],"type":"Point"}
}