{
  "type": "Feature",
  "properties": {
    "addr:full":"Calle de Doctor Calatayud, 34 Moraira Alicante 03724",
    "addr:housenumber":"34",
    "addr:postcode":"03724",
    "addr:street":"Calle De Doctor Calatayud",
    "iso:country":"ES",
    "sg:address":"Calle de Doctor Calatayud, 34",
    "sg:city":"Moraira",
    "sg:orig_category":"\u00d3ptica: Instrumentos (fabricaci\u00d3n)",
    "sg:phone":"+34 966 49 21 71",
    "sg:postcode":"03724",
    "sg:province":"Alicante",
    "wof:name":"Grupo De Vision Llamusi S.l.",
    "wof:placetype":"venue"
},
  "geometry": {"coordinates":[0.1347983032,38.688205719],"type":"Point"}
}