{
  "type": "Feature",
  "properties": {
    "iso:country":"ES",
    "sg:address":"Calle de Gran Via, 42",
    "sg:city":"Sax",
    "sg:classifiers":[
        {
            "category":"Autos & Motor Vehicles",
            "subcategory":"Automobile Sales",
            "type":"Retail Goods"
        }
    ],
    "sg:phone":"+34 965 47 40 46",
    "sg:postcode":"03630",
    "sg:province":"Alicante",
    "wof:name":"Lluch Diaz Jose",
    "wof:placetype":"venue"
},
  "geometry": {"coordinates":[-0.8200029731,38.5354499817],"type":"Point"}
}