{
  "type": "Feature",
  "properties": {
    "iso:country":"ES",
    "sg:address":"Carr Maestro Serrano, 27",
    "sg:city":"Canals",
    "sg:orig_category":"Reposter\u00cdas",
    "sg:phone":"+34 962 24 34 63",
    "sg:postcode":"46650",
    "sg:province":"Valencia",
    "wof:name":"Panaderia Monzo Iba\u00f1ez S.l.",
    "wof:placetype":"venue"
},
  "geometry": {"coordinates":[-0.5856750011,38.9649467468],"type":"Point"}
}