{
  "type": "Feature",
  "properties": {
    "iso:country":"ES",
    "sg:address":"Av Girona, S/n",
    "sg:city":"Riudellots Selva",
    "sg:orig_category":"Maquinaria Neum\u00c1tica",
    "sg:phone":"+34 972 47 76 54",
    "sg:postcode":"17457",
    "sg:province":"Girona",
    "sg:website":"www.smoothsanders.com",
    "wof:name":"Smooth Sander S.l.",
    "wof:placetype":"venue"
},
  "geometry": {"coordinates":[2.8004848957,41.8961181641],"type":"Point"}
}