{
  "type": "Feature",
  "properties": {
    "iso:country":"ES",
    "sg:address":"Ctra Ayamonte (p I Colmenilla), Km. 0653,0",
    "sg:city":"Gibraleon",
    "sg:orig_category":"Insecticidas, Fumigaci\u00d3n",
    "sg:phone":"+34 959 30 05 06",
    "sg:postcode":"21500",
    "sg:province":"Huelva",
    "sg:website":"www.agrogal.com",
    "wof:name":"Agroquimicos Gallardo S.l.",
    "wof:placetype":"venue"
},
  "geometry": {"coordinates":[-6.985347271,37.4111785889],"type":"Point"}
}