{
  "type": "Feature",
  "properties": {
    "addr:full":"Plaz Corrillo, 11 Salamanca Salamanca 37002",
    "addr:housenumber":"11",
    "addr:postcode":"37002",
    "addr:street":"Plaz Corrillo",
    "iso:country":"ES",
    "sg:address":"Plaz Corrillo, 11",
    "sg:city":"Salamanca",
    "sg:orig_category":"Confecci\u00d3n De Sombreros Y Tocados",
    "sg:phone":"+34 923 26 67 83",
    "sg:postcode":"37002",
    "sg:province":"Salamanca",
    "sg:website":"www.sombrereria.net",
    "wof:name":"Cura Argueso Lorenzo",
    "wof:placetype":"venue"
},
  "geometry": {"coordinates":[-5.6647891998,40.9640197754],"type":"Point"}
}