{
  "type": "Feature",
  "properties": {
    "addr:full":"Calle de Veracruz, 17 Alora M\u00e1laga 29500",
    "addr:housenumber":"17",
    "addr:postcode":"29500",
    "addr:street":"Calle De Veracruz;Ma\u0301Laga",
    "iso:country":"ES",
    "sg:address":"Calle de Veracruz, 17",
    "sg:city":"Alora",
    "sg:orig_category":"Florister\u00cdas",
    "sg:phone":"+34 952 49 84 67",
    "sg:postcode":"29500",
    "sg:province":"M\u00e1laga",
    "wof:name":"Chamizo Perez Salvador",
    "wof:placetype":"venue"
},
  "geometry": {"coordinates":[-4.7058849335,36.8241271973],"type":"Point"}
}