{
  "type": "Feature",
  "properties": {
    "addr:full":"Avda Club Deportivo, 22 Logro\u00f1o La Rioja 26007",
    "addr:housenumber":"22",
    "addr:postcode":"26007",
    "addr:street":"Avda Club Deportivo;Rioja",
    "iso:country":"ES",
    "sg:address":"Avda Club Deportivo, 22",
    "sg:city":"Logro\u00f1o",
    "sg:orig_category":"T\u00c9cnicos Veterinarios",
    "sg:phone":"+34 941 21 00 48",
    "sg:postcode":"26007",
    "sg:province":"La Rioja",
    "wof:name":"Tricio Toribio Yolanda",
    "wof:placetype":"venue"
},
  "geometry": {"coordinates":[-2.453275919,42.4568710327],"type":"Point"}
}