{
  "type": "Feature",
  "properties": {
    "addr:full":"Calle de Cirilo Amoros, 71 Valencia Valencia 46004",
    "addr:housenumber":"71",
    "addr:postcode":"46004",
    "addr:street":"Calle De Cirilo Amoros",
    "iso:country":"ES",
    "sg:address":"Calle de Cirilo Amoros, 71",
    "sg:city":"Valencia",
    "sg:orig_category":"M\u00c9dicos: Cirug\u00cda Ortop\u00c9dica Y Traumatolog\u00cda",
    "sg:phone":"+34 963 52 07 02",
    "sg:postcode":"46004",
    "sg:province":"Valencia",
    "wof:name":"Peiro Gonzalez Angel",
    "wof:placetype":"venue"
},
  "geometry": {"coordinates":[-0.3667410016,39.469329834],"type":"Point"}
}