{
  "type": "Feature",
  "properties": {
    "iso:country":"ES",
    "sg:address":"Labeaga Kalea, 31",
    "sg:city":"Urretxu",
    "sg:orig_category":"Ense\u00d1anza: Comercio, Gesti\u00d3n, Inform\u00c1tica",
    "sg:phone":"+34 943 53 24 97",
    "sg:postcode":"20700",
    "sg:province":"Guip\u00f9zcoa",
    "wof:name":"Julio Pastrian Mateos Y Otro, C.b.",
    "wof:placetype":"venue"
},
  "geometry": {"coordinates":[-2.3172390461,43.0906486511],"type":"Point"}
}