{
  "type": "Feature",
  "properties": {
    "addr:full":"Calle de Pinar, 13 Irun Guip\u00f9zcoa 20301",
    "addr:housenumber":"13",
    "addr:postcode":"20301",
    "addr:street":"Calle De Pinar;Guipu\u0300Zcoa",
    "iso:country":"ES",
    "sg:address":"Calle de Pinar, 13",
    "sg:city":"Irun",
    "sg:orig_category":"Maquinaria Para Industrias Diversas",
    "sg:phone":"+34 943 61 63 31",
    "sg:postcode":"20301",
    "sg:province":"Guip\u00f9zcoa",
    "wof:name":"Jose Maria Zuazu Foruria S.l.u.",
    "wof:placetype":"venue"
},
  "geometry": {"coordinates":[-1.8000830412,43.3441009521],"type":"Point"}
}