{
  "type": "Feature",
  "properties": {
    "addr:full":"Cami Escorxador (de L'), S/n Sort Lleida 25560",
    "addr:housenumber":"s / n",
    "addr:postcode":"25560",
    "iso:country":"ES",
    "sg:address":"Cami Escorxador (de L'), S/n",
    "sg:city":"Sort",
    "sg:orig_category":"Bares, Piano",
    "sg:phone":"+34 973 62 13 59",
    "sg:postcode":"25560",
    "sg:province":"Lleida",
    "wof:name":"Oriol Ponsico S.l.",
    "wof:placetype":"venue"
},
  "geometry": {"coordinates":[1.1309039593,42.4089012146],"type":"Point"}
}