{
  "type": "Feature",
  "properties": {
    "addr:full":"Calle de Alfonso, 45 Alginet Valencia 46230",
    "addr:housenumber":"45",
    "addr:postcode":"46230",
    "addr:street":"Calle De Alfonso",
    "iso:country":"ES",
    "sg:address":"Calle de Alfonso, 45",
    "sg:city":"Alginet",
    "sg:orig_category":"Reposter\u00cdas",
    "sg:phone":"+34 961 75 31 74",
    "sg:postcode":"46230",
    "sg:province":"Valencia",
    "wof:name":"Ramirez Criado Milagros",
    "wof:placetype":"venue"
},
  "geometry": {"coordinates":[-0.4689224064,39.2592773438],"type":"Point"}
}