{
  "type": "Feature",
  "properties": {
    "addr:full":"Avda Compromiso De Caspe, 68 Zaragoza Zaragoza 50002",
    "addr:housenumber":"68",
    "addr:postcode":"50002",
    "addr:street":"Avda Compromiso De Caspe",
    "iso:country":"ES",
    "sg:address":"Avda Compromiso De Caspe, 68",
    "sg:city":"Zaragoza",
    "sg:orig_category":"Abogados",
    "sg:phone":"+34 976 49 56 89",
    "sg:postcode":"50002",
    "sg:province":"Zaragoza",
    "wof:name":"Marin Iba\u00f1ez Belen",
    "wof:placetype":"venue"
},
  "geometry": {"coordinates":[-0.8624979854,41.6451377869],"type":"Point"}
}