{
  "type": "Feature",
  "properties": {
    "addr:full":"Calle de Actor Mateo Cerdan Sanchez-fortun, 17 Aguilas Murcia 30880",
    "addr:housenumber":"17",
    "addr:postcode":"30880",
    "addr:street":"Calle De Actor Mateo Cerdan Sanchez-Fortun",
    "iso:country":"ES",
    "sg:address":"Calle de Actor Mateo Cerdan Sanchez-fortun, 17",
    "sg:city":"Aguilas",
    "sg:orig_category":"Reposter\u00cdas",
    "sg:phone":"+34 968 41 41 09",
    "sg:postcode":"30880",
    "sg:province":"Murcia",
    "wof:name":"Soler Soler Rosa",
    "wof:placetype":"venue"
},
  "geometry": {"coordinates":[-1.5729477406,37.4111480713],"type":"Point"}
}