{
  "type": "Feature",
  "properties": {
    "addr:full":"Calle de Galileo, 5 Madrid Madrid 28015",
    "addr:housenumber":"5",
    "addr:postcode":"28015",
    "addr:street":"Calle De Galileo",
    "iso:country":"ES",
    "sg:address":"Calle de Galileo, 5",
    "sg:city":"Madrid",
    "sg:orig_category":"Arquitectos",
    "sg:phone":"+34 915 93 08 58",
    "sg:postcode":"28015",
    "sg:province":"Madrid",
    "wof:name":"Gimenez Gimenez Obdulio",
    "wof:placetype":"venue"
},
  "geometry": {"coordinates":[-3.7106509209,40.4306030273],"type":"Point"}
}