{
  "type": "Feature",
  "properties": {
    "iso:country":"ES",
    "sg:address":"Calle de Adela Lastra, 2",
    "sg:city":"Salamanca",
    "sg:orig_category":"Higiene, Belleza: Art\u00cdculos (al Por Menor)",
    "sg:phone":"+34 923 23 78 59",
    "sg:postcode":"37005",
    "sg:province":"Salamanca",
    "wof:name":"Lucas Polo Angel",
    "wof:placetype":"venue"
},
  "geometry": {"coordinates":[-5.6589412689,40.9838905334],"type":"Point"}
}