{
  "type": "Feature",
  "properties": {
    "iso:country":"ES",
    "sg:address":"Avda Mari\u00d1a, 57",
    "sg:city":"Sada",
    "sg:orig_category":"Empresas De Limpieza",
    "sg:phone":"+34 981 62 15 88",
    "sg:postcode":"15160",
    "sg:province":"La Coru\u00f1a",
    "wof:name":"Limpiezas Sada S L.",
    "wof:placetype":"venue"
},
  "geometry": {"coordinates":[-8.2530088425,43.35105896],"type":"Point"}
}