{
  "type": "Feature",
  "properties": {
    "iso:country":"ES",
    "sg:address":"Avda Segunda Aguada, 5",
    "sg:city":"Cadiz",
    "sg:orig_category":"Peluquer\u00cdas, Peluquer\u00cda Mixta",
    "sg:phone":"+34 956 25 08 59",
    "sg:postcode":"11012",
    "sg:province":"C\u00e1diz",
    "wof:name":"Atenea Navega S.l",
    "wof:placetype":"venue"
},
  "geometry": {"coordinates":[-6.2764987946,36.5132980347],"type":"Point"}
}