{
  "type": "Feature",
  "properties": {
    "iso:country":"ES",
    "sg:address":"Calle de Artunduaga, 22",
    "sg:city":"Urbi",
    "sg:orig_category":"Agencias Y Agentes Comerciales, Representantes",
    "sg:phone":"+34 944 26 23 23",
    "sg:postcode":"48970",
    "sg:province":"Vizcaya",
    "wof:name":"T.p.e. Kemmen S.l.",
    "wof:placetype":"venue"
},
  "geometry": {"coordinates":[-2.8790209293,43.2242546082],"type":"Point"}
}