{
  "type": "Feature",
  "properties": {
    "addr:full":"Calle de Fika, 60 Bilbao Vizcaya 48004",
    "addr:housenumber":"60",
    "addr:postcode":"48004",
    "addr:street":"Calle De Fika",
    "iso:country":"ES",
    "sg:address":"Calle de Fika, 60",
    "sg:city":"Bilbao",
    "sg:orig_category":"Carnicer\u00cdas, Carnicer\u00cdas",
    "sg:phone":"+34 944 33 95 66",
    "sg:postcode":"48004",
    "sg:province":"Vizcaya",
    "wof:name":"Gomez Gonzalez Agustin",
    "wof:placetype":"venue"
},
  "geometry": {"coordinates":[-2.9169929028,43.2529792786],"type":"Point"}
}