{
  "type": "Feature",
  "properties": {
    "iso:country":"ES",
    "sg:address":"Calle de Fidelio, 2",
    "sg:city":"Sevilla",
    "sg:orig_category":"M\u00c9dicos: Cirug\u00cda General",
    "sg:phone":"+34 954 51 41 70",
    "sg:postcode":"41007",
    "sg:province":"Sevilla",
    "wof:name":"Martinez Obrado Domingo",
    "wof:placetype":"venue"
},
  "geometry": {"coordinates":[-5.9498720169,37.4054222107],"type":"Point"}
}