{
  "type": "Feature",
  "properties": {
    "addr:full":"Calle de Barrio Nuevo, 34 Aranda Duero Burgos 09400",
    "addr:housenumber":"34",
    "addr:postcode":"09400",
    "addr:street":"Calle De Barrio Nuevo",
    "iso:country":"ES",
    "sg:address":"Calle de Barrio Nuevo, 34",
    "sg:city":"Aranda Duero",
    "sg:orig_category":"Carnicer\u00cdas, Carnicer\u00cdas",
    "sg:phone":"+34 947 50 12 21",
    "sg:postcode":"09400",
    "sg:province":"Burgos",
    "wof:name":"Rozas Alonso Manuel",
    "wof:placetype":"venue"
},
  "geometry": {"coordinates":[-3.6865699291,41.6721992493],"type":"Point"}
}