{
  "type": "Feature",
  "properties": {
    "iso:country":"ES",
    "sg:address":"Calle de Pedro Icaza Aguirre, 35",
    "sg:city":"Santurtzi",
    "sg:orig_category":"Asociaciones, Organismos Culturales Y Socioeducativos",
    "sg:phone":"+34 944 83 61 84",
    "sg:postcode":"48980",
    "sg:province":"Vizcaya",
    "wof:name":"Hijos De Andalucia",
    "wof:placetype":"venue"
},
  "geometry": {"coordinates":[-3.027354002,43.3259010315],"type":"Point"}
}