{
  "type": "Feature",
  "properties": {
    "addr:full":"Avda Reina Sofia, S/n Gibraleon Huelva 21500",
    "addr:housenumber":"s / n",
    "addr:postcode":"21500",
    "addr:street":"Avda Reina Sofia",
    "iso:country":"ES",
    "sg:address":"Avda Reina Sofia, S/n",
    "sg:city":"Gibraleon",
    "sg:orig_category":"Mec\u00c1nico Del Autom\u00d3vil",
    "sg:phone":"+34 959 30 02 84",
    "sg:postcode":"21500",
    "sg:province":"Huelva",
    "wof:name":"Fernandez Marin Sebastian",
    "wof:placetype":"venue"
},
  "geometry": {"coordinates":[-6.9652938843,37.3760108948],"type":"Point"}
}