{
  "type": "Feature",
  "properties": {
    "addr:full":"Plaz Padre Cervos, 4 Principe Alfonso Ceuta 51003",
    "addr:housenumber":"4",
    "addr:postcode":"51003",
    "addr:street":"Cervos",
    "iso:country":"ES",
    "sg:address":"Plaz Padre Cervos, 4",
    "sg:city":"Principe Alfonso",
    "sg:orig_category":"Carnicer\u00cdas, Carnicer\u00cdas",
    "sg:phone":"+34 956 50 14 98",
    "sg:postcode":"51003",
    "sg:province":"Ceuta",
    "wof:name":"Sel-lam  Mohamed Ahmed",
    "wof:placetype":"venue"
},
  "geometry": {"coordinates":[-5.3157300949,35.8891601562],"type":"Point"}
}