{
  "type": "Feature",
  "properties": {
    "addr:full":"Las Norias, S/n Las Norias Almer\u00eda 04716",
    "addr:postcode":"04716",
    "addr:street":"Las Norias S / N Las Norias Almeri\u0301A",
    "iso:country":"ES",
    "sg:address":"Las Norias, S/n",
    "sg:city":"Las Norias",
    "sg:orig_category":"Cajas Para Embalar",
    "sg:phone":"+34 950 58 70 61",
    "sg:postcode":"04716",
    "sg:province":"Almer\u00eda",
    "wof:name":"Cajamar",
    "wof:placetype":"venue"
},
  "geometry": {"coordinates":[-2.7460141182,36.7571296692],"type":"Point"}
}