{
  "type": "Feature",
  "properties": {
    "iso:country":"ES",
    "sg:address":"Elkano Kalea, 18",
    "sg:city":"Hernani",
    "sg:orig_category":"Peluquer\u00cdas, Peluquer\u00cda Mixta",
    "sg:phone":"+34 943 33 30 32",
    "sg:postcode":"20120",
    "sg:province":"Guip\u00f9zcoa",
    "wof:name":"Peluqueria Biok C.b.",
    "wof:placetype":"venue"
},
  "geometry": {"coordinates":[-1.9760299921,43.2684822083],"type":"Point"}
}