{
  "type": "Feature",
  "properties": {
    "addr:full":"Aurora, 6 Lucena C\u00f3rdoba 14900",
    "addr:housenumber":"6",
    "addr:postcode":"14900",
    "addr:street":"Aurora",
    "iso:country":"ES",
    "sg:address":"Aurora, 6",
    "sg:city":"Lucena",
    "sg:orig_category":"Peluqueros: De Se\u00d1oras",
    "sg:phone":"+34 957 50 11 06",
    "sg:postcode":"14900",
    "sg:province":"C\u00f3rdoba",
    "wof:name":"Caballero Saunet Francisca",
    "wof:placetype":"venue"
},
  "geometry": {"coordinates":[-4.4847187996,37.4150352478],"type":"Point"}
}