{
  "type": "Feature",
  "properties": {
    "iso:country":"ES",
    "sg:address":"Calle de Garcia Ximenez, 28",
    "sg:city":"Alsasua",
    "sg:classifiers":[
        {
            "category":"Shopping",
            "subcategory":"Clothing, Apparel, & Fashions",
            "type":"Retail Goods"
        }
    ],
    "sg:phone":"+34 948 46 79 32",
    "sg:postcode":"31800",
    "sg:province":"Navarra",
    "sg:tags":[
        "boutique"
    ],
    "wof:name":"Asensio Vaquerizo Juan Alonso",
    "wof:placetype":"venue"
},
  "geometry": {"coordinates":[-2.1680047512,42.8946456909],"type":"Point"}
}