{
  "type": "Feature",
  "properties": {
    "addr:full":"Avda Galicia, 75 Gijon Asturias 33212",
    "addr:housenumber":"75",
    "addr:postcode":"33212",
    "addr:street":"Avda Galicia",
    "iso:country":"ES",
    "sg:address":"Avda Galicia, 75",
    "sg:city":"Gijon",
    "sg:orig_category":"Empresarios",
    "sg:phone":"+34 985 31 33 74",
    "sg:postcode":"33212",
    "sg:province":"Asturias",
    "wof:name":"Campo Carro Felix",
    "wof:placetype":"venue"
},
  "geometry": {"coordinates":[-5.68957901,43.5398483276],"type":"Point"}
}