{
  "type": "Feature",
  "properties": {
    "iso:country":"ES",
    "sg:address":"C/ Rutlla, 12",
    "sg:city":"Calonge",
    "sg:orig_category":"Panader\u00cdas, Panader\u00cdas",
    "sg:phone":"+34 972 65 00 35",
    "sg:postcode":"17251",
    "sg:province":"Girona",
    "wof:name":"Robert Quintana Jose",
    "wof:placetype":"venue"
},
  "geometry": {"coordinates":[3.0752260685,41.86170578],"type":"Point"}
}