{
  "type": "Feature",
  "properties": {
    "iso:country":"ES",
    "sg:address":"Carr Noguera (la), 35",
    "sg:city":"Almacelles",
    "sg:orig_category":"Mec\u00c1nico Del Autom\u00d3vil",
    "sg:phone":"+34 973 74 10 99",
    "sg:postcode":"25100",
    "sg:province":"Lleida",
    "wof:name":"Demetri Automocio S.l.",
    "wof:placetype":"venue"
},
  "geometry": {"coordinates":[0.4451920092,41.729095459],"type":"Point"}
}