{
  "type": "Feature",
  "properties": {
    "iso:country":"ES",
    "sg:address":"Rbla Pompeu Fabra, 81",
    "sg:city":"Mollet Valles",
    "sg:orig_category":"Empresas De Carpinter\u00cda",
    "sg:phone":"+34 935 70 50 60",
    "sg:postcode":"08100",
    "sg:province":"Barcelona",
    "wof:name":"Tendals I Alumini Masip S.l.",
    "wof:placetype":"venue"
},
  "geometry": {"coordinates":[2.2189719677,41.5422897339],"type":"Point"}
}