{
  "type": "Feature",
  "properties": {
    "iso:country":"ES",
    "sg:address":"Calle de Juan De Bethencourt Dominguez, 11",
    "sg:city":"Arucas",
    "sg:orig_category":"Animales (al Por Menor)",
    "sg:phone":"+34 928 60 33 81",
    "sg:postcode":"35400",
    "sg:province":"Las Palmas",
    "wof:name":"Armas Perez Mario",
    "wof:placetype":"venue"
},
  "geometry": {"coordinates":[-15.5252752304,28.1179904938],"type":"Point"}
}