{
  "type": "Feature",
  "properties": {
    "iso:country":"ES",
    "sg:address":"Calle de Oliva (la), 32",
    "sg:city":"Mas Matas",
    "sg:orig_category":"Promotores Constructores",
    "sg:phone":"+34 978 84 86 71",
    "sg:postcode":"44564",
    "sg:province":"Teruel",
    "wof:name":"Construcciones Y Restauraciones Aznar Pastor S.l",
    "wof:placetype":"venue"
},
  "geometry": {"coordinates":[-0.2439060062,40.8346099854],"type":"Point"}
}