{
  "type": "Feature",
  "properties": {
    "iso:country":"ES",
    "sg:address":"Carrer de Cadis, 65",
    "sg:city":"Terrassa",
    "sg:orig_category":"Transportes Por Carretera: Lotes Completos, Mercanc\u00cdas Diversas",
    "sg:phone":"+34 937 85 02 68",
    "sg:postcode":"08226",
    "sg:province":"Barcelona",
    "wof:name":"Empresa De Logistica I Transport S.l.",
    "wof:placetype":"venue"
},
  "geometry": {"coordinates":[2.0314350128,41.5717468262],"type":"Point"}
}