{
  "type": "Feature",
  "properties": {
    "iso:country":"ES",
    "sg:address":"Ctra. Girona S. Feliu, Km. 0025,0",
    "sg:city":"Llagostera",
    "sg:orig_category":"Restaurantes",
    "sg:phone":"+34 972 83 01 75",
    "sg:postcode":"17240",
    "sg:province":"Girona",
    "wof:name":"Tinars S. A.",
    "wof:placetype":"venue"
},
  "geometry": {"coordinates":[2.9727549553,41.8591918945],"type":"Point"}
}