{
  "type": "Feature",
  "properties": {
    "addr:full":"Calle de Brocal, 21 Granadilla Abona Santa Cruz De Tenerife 38600",
    "addr:housenumber":"21",
    "addr:postcode":"38600",
    "addr:street":"Calle De Brocal",
    "iso:country":"ES",
    "sg:address":"Calle de Brocal, 21",
    "sg:city":"Granadilla Abona",
    "sg:orig_category":"Farmacias",
    "sg:phone":"+34 922 77 12 53",
    "sg:postcode":"38600",
    "sg:province":"Santa Cruz De Tenerife",
    "wof:name":"Trujillo Garcia Horacio",
    "wof:placetype":"venue"
},
  "geometry": {"coordinates":[-16.5770683289,28.114566803],"type":"Point"}
}