{
  "type": "Feature",
  "properties": {
    "addr:full":"Calle de Zurita, 13 Zaragoza Zaragoza 50001",
    "addr:housenumber":"13",
    "addr:postcode":"50001",
    "addr:street":"Calle De Zurita",
    "iso:country":"ES",
    "sg:address":"Calle de Zurita, 13",
    "sg:city":"Zaragoza",
    "sg:orig_category":"Inmobiliaria (agencias)",
    "sg:phone":"+34 976 23 00 69",
    "sg:postcode":"50001",
    "sg:province":"Zaragoza",
    "wof:name":"Taosza S.l.",
    "wof:placetype":"venue"
},
  "geometry": {"coordinates":[-0.8805603981,41.6500473022],"type":"Point"}
}