{
  "type": "Feature",
  "properties": {
    "iso:country":"ES",
    "sg:address":"Cmno Madrona, S/n",
    "sg:city":"Abades",
    "sg:orig_category":"Centros De Educaci\u00d3n Especial",
    "sg:phone":"+34 921 49 52 02",
    "sg:postcode":"40141",
    "sg:province":"Segovia",
    "wof:name":"Colegio Rural Agrupado Valverde - Aula De Abades",
    "wof:placetype":"venue"
},
  "geometry": {"coordinates":[-4.2641739845,40.9147872925],"type":"Point"}
}