{
  "type": "Feature",
  "properties": {
    "iso:country":"ES",
    "sg:address":"Plaz Comunidades Autonomas (de Las), 19",
    "sg:city":"Puerto Mazarron",
    "sg:orig_category":"Fabricaci\u00d3n De Juegos Y Juguetes",
    "sg:phone":"+34 968 15 57 00",
    "sg:postcode":"30860",
    "sg:province":"Murcia",
    "sg:website":"www.juguetilandia.com",
    "wof:name":"Juguetes Pastor S.l.",
    "wof:placetype":"venue"
},
  "geometry": {"coordinates":[-1.2610340118,37.5667037964],"type":"Point"}
}