{
  "type": "Feature",
  "properties": {
    "iso:country":"ES",
    "sg:address":"Calle de Emiliano Barral, 14",
    "sg:city":"Madrid",
    "sg:orig_category":"Tintes (fabricaci\u00d3n, Al Por Mayor)",
    "sg:phone":"+34 915 19 91 80",
    "sg:postcode":"28043",
    "sg:province":"Madrid",
    "wof:name":"Inversiones K S.l.",
    "wof:placetype":"venue"
},
  "geometry": {"coordinates":[-3.6603200436,40.450012207],"type":"Point"}
}