{
  "type": "Feature",
  "properties": {
    "iso:country":"ES",
    "sg:address":"C/ Vicente Blasco Iba\u00d1ez, 58",
    "sg:city":"Elche",
    "sg:orig_category":"Televisi\u00d3n, V\u00cddeo: Aparatos Y Accesorios (venta)",
    "sg:phone":"+34 965 43 42 97",
    "sg:postcode":"03201",
    "sg:province":"Alicante",
    "wof:name":"Audio Rivera-7 S.l.u",
    "wof:placetype":"venue"
},
  "geometry": {"coordinates":[-0.7043817043,38.2679176331],"type":"Point"}
}