{
  "type": "Feature",
  "properties": {
    "iso:country":"ES",
    "sg:address":"Barr Okin-zuri, 1",
    "sg:city":"Ermua",
    "sg:orig_category":"Marketing Directo",
    "sg:phone":"+34 943 17 47 33",
    "sg:postcode":"48260",
    "sg:province":"Vizcaya",
    "wof:name":"Lopez Sanz Luis Miguel",
    "wof:placetype":"venue"
},
  "geometry": {"coordinates":[-2.5021159649,43.1915435791],"type":"Point"}
}