{
  "type": "Feature",
  "properties": {
    "iso:country":"ES",
    "sg:address":"Enlace, 1",
    "sg:city":"Paracuellos",
    "sg:orig_category":"Empresas De Limpieza",
    "sg:phone":"+34 916 58 20 02",
    "sg:postcode":"28860",
    "sg:province":"Madrid",
    "wof:name":"Salveco Proyectos S.l.",
    "wof:placetype":"venue"
},
  "geometry": {"coordinates":[-3.5396831036,40.5252685547],"type":"Point"}
}