{
  "type": "Feature",
  "properties": {
    "addr:full":"Calle de Malmasin, 2 Bilbao Vizcaya 48003",
    "addr:housenumber":"2",
    "addr:postcode":"48003",
    "addr:street":"Calle De Malmasin",
    "iso:country":"ES",
    "sg:address":"Calle de Malmasin, 2",
    "sg:city":"Bilbao",
    "sg:orig_category":"Carnicer\u00cdas, Carnicer\u00cdas",
    "sg:phone":"+34 944 16 34 90",
    "sg:postcode":"48003",
    "sg:province":"Vizcaya",
    "wof:name":"Perea Sanchez Manuel",
    "wof:placetype":"venue"
},
  "geometry": {"coordinates":[-2.9231903553,43.2407417297],"type":"Point"}
}