{
  "type": "Feature",
  "properties": {
    "addr:full":"Calle de Luis Rodriguez Figueroa, 6 Tope Santa Cruz De Tenerife 38400",
    "addr:housenumber":"6",
    "addr:postcode":"38400",
    "addr:street":"Calle De Luis Rodriguez Figueroa",
    "iso:country":"ES",
    "sg:address":"Calle de Luis Rodriguez Figueroa, 6",
    "sg:city":"Tope",
    "sg:orig_category":"Centros M\u00c9dicos Y Sociales, Dispensarios",
    "sg:phone":"+34 922 37 63 44",
    "sg:postcode":"38400",
    "sg:province":"Santa Cruz De Tenerife",
    "wof:name":"Flag Tenerife S.l.",
    "wof:placetype":"venue"
},
  "geometry": {"coordinates":[-16.540643692,28.4122276306],"type":"Point"}
}