{
  "type": "Feature",
  "properties": {
    "addr:full":"Tabardo, 6 Beniparrell Valencia 46469",
    "addr:housenumber":"6",
    "addr:postcode":"46469",
    "addr:street":"Tabardo",
    "iso:country":"ES",
    "sg:address":"Tabardo, 6",
    "sg:city":"Beniparrell",
    "sg:orig_category":"Industria Qu\u00cdmica",
    "sg:phone":"+34 961 20 06 90",
    "sg:postcode":"46469",
    "sg:province":"Valencia",
    "wof:name":"Gestiones De Residuos Alimentarios Del Mediteraneo S.l.",
    "wof:placetype":"venue"
},
  "geometry": {"coordinates":[-0.4139220119,39.387462616],"type":"Point"}
}