{
  "type": "Feature",
  "properties": {
    "iso:country":"ES",
    "sg:address":"Calle de Barranquillo Hondo, 2",
    "sg:city":"Espinos",
    "sg:orig_category":"Poller\u00cda Y Caza (al Por Menor)",
    "sg:phone":"+34 928 89 22 12",
    "sg:postcode":"35470",
    "sg:province":"Las Palmas",
    "wof:name":"Ramirez Segura Ana Maria",
    "wof:placetype":"venue"
},
  "geometry": {"coordinates":[-15.7916707993,27.98777771],"type":"Point"}
}