{
  "type": "Feature",
  "properties": {
    "addr:full":"Carrer de Arquitecte Gaudi, 22 Canyelles-almadrava-puig-rom Girona 17480",
    "addr:housenumber":"22",
    "addr:postcode":"17480",
    "addr:street":"Carrer De Arquitecte Gaudi",
    "iso:country":"ES",
    "sg:address":"Carrer de Arquitecte Gaudi, 22",
    "sg:city":"Canyelles-almadrava-puig-rom",
    "sg:orig_category":"Ingeniero",
    "sg:phone":"+34 972 15 45 72",
    "sg:postcode":"17480",
    "sg:province":"Girona",
    "wof:name":"Bt Espa\u00d1a Compa\u00d1ia De Servicios Globales De Telecomunicaciones S.a.u.",
    "wof:placetype":"venue"
},
  "geometry": {"coordinates":[3.1663351059,42.2661399841],"type":"Point"}
}