{
  "type": "Feature",
  "properties": {
    "iso:country":"ES",
    "sg:address":"Calle de San Juan, 14",
    "sg:city":"Belones",
    "sg:orig_category":"Promotores Constructores",
    "sg:phone":"+34 968 13 71 33",
    "sg:postcode":"30385",
    "sg:province":"Murcia",
    "wof:name":"Odicela S.l.",
    "wof:placetype":"venue"
},
  "geometry": {"coordinates":[-0.7777199745,37.6252479553],"type":"Point"}
}