{
  "type": "Feature",
  "properties": {
    "iso:country":"ES",
    "sg:address":"Carr Sant Marti De Malda, 5",
    "sg:city":"Cervera",
    "sg:classifiers":[
        {
            "category":"Taxi",
            "type":"Transportation"
        }
    ],
    "sg:phone":"+34 973 53 32 01",
    "sg:postcode":"25200",
    "sg:province":"Lleida",
    "wof:name":"Gutierrez Bosch Eduard",
    "wof:placetype":"venue"
},
  "geometry": {"coordinates":[1.2679949999,41.6724662781],"type":"Point"}
}