{
  "type": "Feature",
  "properties": {
    "addr:full":"Calle de Arzobispos (los), 12 Comillas Cantabria 39520",
    "addr:housenumber":"12",
    "addr:postcode":"39520",
    "addr:street":"Calle De Arzobispos Los",
    "iso:country":"ES",
    "sg:address":"Calle de Arzobispos (los), 12",
    "sg:city":"Comillas",
    "sg:orig_category":"Heladeros",
    "sg:phone":"+34 942 72 03 77",
    "sg:postcode":"39520",
    "sg:province":"Cantabria",
    "wof:name":"Setien Fernandez Rosa",
    "wof:placetype":"venue"
},
  "geometry": {"coordinates":[-4.2916088104,43.3856506348],"type":"Point"}
}