{
  "type": "Feature",
  "properties": {
    "addr:full":"Calle de Vazquez De Menchaca, 133 Valladolid Valladolid 47008",
    "addr:housenumber":"133",
    "addr:postcode":"47008",
    "addr:street":"Calle De Vazquez De Menchaca",
    "iso:country":"ES",
    "sg:address":"Calle de Vazquez De Menchaca, 133",
    "sg:city":"Valladolid",
    "sg:orig_category":"Muebles",
    "sg:phone":"+34 983 47 26 75",
    "sg:postcode":"47008",
    "sg:province":"Valladolid",
    "wof:name":"Ceylo S.a.",
    "wof:placetype":"venue"
},
  "geometry": {"coordinates":[-4.7321009636,41.6243438721],"type":"Point"}
}