{
  "type": "Feature",
  "properties": {
    "iso:country":"ES",
    "sg:address":"Av Diputacio, 172",
    "sg:city":"Cambrils",
    "sg:orig_category":"Art\u00cdculos De Regalo (al Por Menor)",
    "sg:phone":"+34 977 35 27 73",
    "sg:postcode":"43850",
    "sg:province":"Tarragona",
    "wof:name":"Alame Bekouri Fouad",
    "wof:placetype":"venue"
},
  "geometry": {"coordinates":[1.1107213497,41.0732383728],"type":"Point"}
}