{
  "type": "Feature",
  "properties": {
    "iso:country":"ES",
    "sg:address":"Plaz Libertad La, 4",
    "sg:city":"Mieres",
    "sg:orig_category":"Frutas Y Legumbres Frescas (al Por Mayor)",
    "sg:phone":"+34 985 46 83 79",
    "sg:postcode":"33600",
    "sg:province":"Asturias",
    "wof:name":"Frutas La Amistad S. L.",
    "wof:placetype":"venue"
},
  "geometry": {"coordinates":[-5.774682045,43.2475090027],"type":"Point"}
}