{
  "type": "Feature",
  "properties": {
    "addr:full":"Av Generalitat (de La), 19 Tortosa Tarragona 43500",
    "addr:housenumber":"19",
    "addr:postcode":"43500",
    "addr:street":"Av Generalitat De La",
    "iso:country":"ES",
    "sg:address":"Av Generalitat (de La), 19",
    "sg:city":"Tortosa",
    "sg:orig_category":"Tintes (fabricaci\u00d3n, Al Por Mayor)",
    "sg:phone":"+34 977 44 58 01",
    "sg:postcode":"43500",
    "sg:province":"Tarragona",
    "wof:name":"Besalduch Fava Juan Antonio",
    "wof:placetype":"venue"
},
  "geometry": {"coordinates":[0.520721972,40.8116455078],"type":"Point"}
}