{
  "type": "Feature",
  "properties": {
    "addr:full":"Carrer de Progres, 69 Gava Barcelona 08850",
    "addr:housenumber":"69",
    "addr:postcode":"08850",
    "addr:street":"Carrer De Progres",
    "iso:country":"ES",
    "sg:address":"Carrer de Progres, 69",
    "sg:city":"Gava",
    "sg:orig_category":"Cajas De Ahorro",
    "sg:phone":"+34 936 38 41 29",
    "sg:postcode":"08850",
    "sg:province":"Barcelona",
    "wof:name":"Caixa D'estalvis De Catalunya",
    "wof:placetype":"venue"
},
  "geometry": {"coordinates":[2.0115170479,41.2989578247],"type":"Point"}
}