{
  "type": "Feature",
  "properties": {
    "addr:full":"Calle de Melilla, 35 Alcala Henares Madrid 28805",
    "addr:housenumber":"35",
    "addr:postcode":"28805",
    "addr:street":"Calle De Melilla",
    "iso:country":"ES",
    "sg:address":"Calle de Melilla, 35",
    "sg:city":"Alcala Henares",
    "sg:orig_category":"Mec\u00c1nico Del Autom\u00d3vil",
    "sg:phone":"+34 918 81 92 04",
    "sg:postcode":"28805",
    "sg:province":"Madrid",
    "wof:name":"Maurazos Elola Manuel",
    "wof:placetype":"venue"
},
  "geometry": {"coordinates":[-3.3416523933,40.4944610596],"type":"Point"}
}