{
  "type": "Feature",
  "properties": {
    "iso:country":"ES",
    "sg:address":"Avda Maria Auxiliadora, 3",
    "sg:city":"Badajoz",
    "sg:orig_category":"Asociaciones, Organismos Culturales Y Socioeducativos",
    "sg:phone":"+34 924 23 18 28",
    "sg:postcode":"06011",
    "sg:province":"Badajoz",
    "wof:name":"Alternativa Joven De Extremadura",
    "wof:placetype":"venue"
},
  "geometry": {"coordinates":[-6.9787826538,38.870136261],"type":"Point"}
}