{
  "type": "Feature",
  "properties": {
    "iso:country":"ES",
    "sg:address":"C/ Josep Maria Buch, 28",
    "sg:city":"Elche",
    "sg:orig_category":"Periodistas Profesionales",
    "sg:phone":"+34 965 46 37 26",
    "sg:postcode":"03201",
    "sg:province":"Alicante",
    "wof:name":"Pastor Chilar Vicente",
    "wof:placetype":"venue"
},
  "geometry": {"coordinates":[-0.7035620213,38.2671813965],"type":"Point"}
}