{
  "type": "Feature",
  "properties": {
    "addr:full":"Cm Vell Vila Real-onda, Km. 0003,5 Vila-real Castell\u00f3n 12540",
    "addr:housenumber":"castello\u0301n",
    "addr:postcode":"12540",
    "addr:street":"Km. 0003,5 Vila-Real",
    "iso:country":"ES",
    "sg:address":"Cm Vell Vila Real-onda, Km. 0003,5",
    "sg:city":"Vila-real",
    "sg:orig_category":"Mec\u00c1nico Del Autom\u00d3vil",
    "sg:phone":"+34 964 53 75 29",
    "sg:postcode":"12540",
    "sg:province":"Castell\u00f3n",
    "sg:website":"www.camaracs.es/galaix.htm",
    "wof:name":"Talleres Galaix S.l.",
    "wof:placetype":"venue"
},
  "geometry": {"coordinates":[-0.0952899978,39.9453010559],"type":"Point"}
}