{
  "type": "Feature",
  "properties": {
    "iso:country":"ES",
    "sg:address":"Calle de Lope De Rueda, 66",
    "sg:city":"Malaga",
    "sg:orig_category":"Iglesia Cat\u00d3lica",
    "sg:phone":"+34 952 43 11 41",
    "sg:postcode":"29190",
    "sg:province":"M\u00e1laga",
    "wof:name":"Obispado De Malaga",
    "wof:placetype":"venue"
},
  "geometry": {"coordinates":[-4.478553772,36.7354240417],"type":"Point"}
}