{
  "type": "Feature",
  "properties": {
    "addr:full":"Carrer de Duc De Cardona, 13 Hospitalet De L'infant Tarragona 43890",
    "addr:housenumber":"13",
    "addr:postcode":"43890",
    "addr:street":"Carrer De Duc De Cardona",
    "iso:country":"ES",
    "sg:address":"Carrer de Duc De Cardona, 13",
    "sg:city":"Hospitalet De L'infant",
    "sg:orig_category":"Art\u00cdculos De Regalo (al Por Menor)",
    "sg:phone":"+34 977 82 35 49",
    "sg:postcode":"43890",
    "sg:province":"Tarragona",
    "wof:name":"Perez Escribano Gertrudis",
    "wof:placetype":"venue"
},
  "geometry": {"coordinates":[1.2455840111,41.1117019653],"type":"Point"}
}