{
  "type": "Feature",
  "properties": {
    "addr:full":"Carr Verge Del Carme, 37 Puerto De Pollen\u00c7a Islas Baleares 07470",
    "addr:housenumber":"37",
    "addr:postcode":"07470",
    "addr:street":"Carr Verge Del Carme",
    "iso:country":"ES",
    "sg:address":"Carr Verge Del Carme, 37",
    "sg:city":"Puerto De Pollen\u00c7a",
    "sg:orig_category":"Artesan\u00cda",
    "sg:phone":"+34 971 86 43 43",
    "sg:postcode":"07470",
    "sg:province":"Islas Baleares",
    "wof:name":"Godoy Montero Francisco Jose",
    "wof:placetype":"venue"
},
  "geometry": {"coordinates":[3.0810570717,39.9047584534],"type":"Point"}
}