{
  "type": "Feature",
  "properties": {
    "addr:full":"Calle de Doctor Gines De Paco Y De Gea, 22 Cehegin Murcia 30430",
    "addr:housenumber":"22",
    "addr:postcode":"30430",
    "addr:street":"Calle De Doctor Gines De Paco Y De Gea",
    "iso:country":"ES",
    "sg:address":"Calle de Doctor Gines De Paco Y De Gea, 22",
    "sg:city":"Cehegin",
    "sg:orig_category":"Zapatos (al Por Menor)",
    "sg:phone":"+34 968 74 01 64",
    "sg:postcode":"30430",
    "sg:province":"Murcia",
    "wof:name":"Dgea Moya Ana Maria",
    "wof:placetype":"venue"
},
  "geometry": {"coordinates":[-1.7987689972,38.0928916931],"type":"Point"}
}