{
  "type": "Feature",
  "properties": {
    "iso:country":"ES",
    "sg:address":"Rua Irida, 9",
    "sg:city":"Estrada",
    "sg:orig_category":"Contenedores (mercanc\u00cdas)",
    "sg:phone":"+34 986 57 18 02",
    "sg:postcode":"36680",
    "sg:province":"Pontevedra",
    "wof:name":"Martinez Martinez Jose",
    "wof:placetype":"venue"
},
  "geometry": {"coordinates":[-8.4910736084,42.6887664795],"type":"Point"}
}