{
  "type": "Feature",
  "properties": {
    "addr:full":"Barr San Lazaro, S/n Viveiro Lugo 27850",
    "addr:housenumber":"/ n",
    "addr:postcode":"27850",
    "addr:street":"Lazaro S",
    "iso:country":"ES",
    "sg:address":"Barr San Lazaro, S/n",
    "sg:city":"Viveiro",
    "sg:orig_category":"Mec\u00c1nico Del Autom\u00d3vil",
    "sg:phone":"+34 982 57 00 32",
    "sg:postcode":"27850",
    "sg:province":"Lugo",
    "wof:name":"Talleres San Lazaro S. L.",
    "wof:placetype":"venue"
},
  "geometry": {"coordinates":[-7.5959348679,43.6629714966],"type":"Point"}
}