{
  "type": "Feature",
  "properties": {
    "addr:full":"Carrer de Caseta, 10 Mataro Barcelona 08304",
    "addr:housenumber":"10",
    "addr:postcode":"08304",
    "addr:street":"Carrer De Caseta",
    "iso:country":"ES",
    "sg:address":"Carrer de Caseta, 10",
    "sg:city":"Mataro",
    "sg:orig_category":"Molduras, Junquillos, Listones Y Molduras Perforadas",
    "sg:phone":"+34 937 98 68 61",
    "sg:postcode":"08304",
    "sg:province":"Barcelona",
    "wof:name":"Cebrian Valencia Rafael",
    "wof:placetype":"venue"
},
  "geometry": {"coordinates":[2.437087059,41.5483627319],"type":"Point"}
}