{
  "type": "Feature",
  "properties": {
    "iso:country":"ES",
    "sg:address":"Calle de Infancia, 3",
    "sg:city":"Alcala Henares",
    "sg:orig_category":"Pr\u00c9stamos Personales E Hipotecarios",
    "sg:phone":"+34 918 88 00 32",
    "sg:postcode":"28807",
    "sg:province":"Madrid",
    "wof:name":"Registro De La Propiedad N\u00ba 1",
    "wof:placetype":"venue"
},
  "geometry": {"coordinates":[-3.3702480793,40.4861221313],"type":"Point"}
}