{
  "type": "Feature",
  "properties": {
    "iso:country":"ES",
    "sg:address":"Rcial Parque Aracena, 41",
    "sg:city":"Aracena",
    "sg:orig_category":"Agencias De Prensa E Informaci\u00d3n",
    "sg:phone":"+34 959 12 65 36",
    "sg:postcode":"21200",
    "sg:province":"Huelva",
    "wof:name":"Info Imagen Del Tinto S.l.u",
    "wof:placetype":"venue"
},
  "geometry": {"coordinates":[-6.5563879013,37.8901901245],"type":"Point"}
}