{
  "type": "Feature",
  "properties": {
    "iso:country":"ES",
    "sg:address":"Calle de Moratin, 14",
    "sg:city":"Valencia",
    "sg:orig_category":"Sindicatos Y Colegios Profesionales",
    "sg:phone":"+34 963 51 71 05",
    "sg:postcode":"46002",
    "sg:province":"Valencia",
    "wof:name":"Asociacion Valenciana De Directores De Personal",
    "wof:placetype":"venue"
},
  "geometry": {"coordinates":[-0.3756588995,39.4705734253],"type":"Point"}
}