{
  "type": "Feature",
  "properties": {
    "addr:full":"Calle de Olivo, 113 Jaen Ja\u00e9n 23006",
    "addr:housenumber":"113;jae\u0301n",
    "addr:postcode":"23006",
    "addr:street":"Calle De Olivo",
    "iso:country":"ES",
    "sg:address":"Calle de Olivo, 113",
    "sg:city":"Jaen",
    "sg:orig_category":"Ingeniero",
    "sg:phone":"+34 953 25 22 32",
    "sg:postcode":"23006",
    "sg:province":"Ja\u00e9n",
    "wof:name":"Escudero Piedra Manuel",
    "wof:placetype":"venue"
},
  "geometry": {"coordinates":[-3.8187050819,37.7815666199],"type":"Point"}
}