{
  "type": "Feature",
  "properties": {
    "addr:full":"Calle de Pablo Leon (a), 5 Monte Lentiscal Las Palmas 35310",
    "addr:housenumber":"5",
    "addr:postcode":"35310",
    "addr:street":"Calle De Pablo Leon A;Palmas",
    "iso:country":"ES",
    "sg:address":"Calle de Pablo Leon (a), 5",
    "sg:city":"Monte Lentiscal",
    "sg:orig_category":"M\u00c9dicos: Ginecolog\u00cda Y Obstetricia",
    "sg:phone":"+34 928 35 17 46",
    "sg:postcode":"35310",
    "sg:province":"Las Palmas",
    "wof:name":"Leon Espino Juan",
    "wof:placetype":"venue"
},
  "geometry": {"coordinates":[-15.4785747528,28.0462970734],"type":"Point"}
}