{
  "type": "Feature",
  "properties": {
    "iso:country":"ES",
    "sg:address":"Pg Maragall, 104",
    "sg:city":"Barcelona",
    "sg:orig_category":"Empresarios",
    "sg:phone":"+34 933 40 80 05",
    "sg:postcode":"08027",
    "sg:province":"Barcelona",
    "sg:website":"www.lineasinteriorismo.com",
    "wof:name":"Lineas Cuines I Banys S.l.",
    "wof:placetype":"venue"
},
  "geometry": {"coordinates":[2.1805899143,41.420841217],"type":"Point"}
}