{
  "type": "Feature",
  "properties": {
    "addr:full":"Calle de Monjas (las), 10 Andujar Ja\u00e9n 23740",
    "addr:housenumber":"10",
    "addr:postcode":"23740",
    "addr:street":"Calle De Monjas Las",
    "iso:country":"ES",
    "sg:address":"Calle de Monjas (las), 10",
    "sg:city":"Andujar",
    "sg:orig_category":"Aparcamientos (infraestructuras, Accesorios)",
    "sg:phone":"+34 953 51 30 25",
    "sg:postcode":"23740",
    "sg:province":"Ja\u00e9n",
    "wof:name":"Gestiopar S.l.",
    "wof:placetype":"venue"
},
  "geometry": {"coordinates":[-4.0517959595,38.0383682251],"type":"Point"}
}