{
  "type": "Feature",
  "properties": {
    "iso:country":"ES",
    "sg:address":"Trva Lope De Figueroa, 1",
    "sg:city":"Alcala Henares",
    "sg:orig_category":"Centros De Coordinaci\u00d3n",
    "sg:phone":"+34 918 78 91 02",
    "sg:postcode":"28804",
    "sg:province":"Madrid",
    "wof:name":"Garcia Gutierrez Alfonso",
    "wof:placetype":"venue"
},
  "geometry": {"coordinates":[-3.3535370827,40.4831581116],"type":"Point"}
}