{
  "type": "Feature",
  "properties": {
    "iso:country":"ES",
    "sg:address":"Carrer de Mallorca, 27",
    "sg:city":"S. Boi Llobregat",
    "sg:orig_category":"Molduras, Junquillos, Listones Y Molduras Perforadas",
    "sg:phone":"+34 936 52 08 52",
    "sg:postcode":"08830",
    "sg:province":"Barcelona",
    "wof:name":"Puertas Albea Maria Del Carmen",
    "wof:placetype":"venue"
},
  "geometry": {"coordinates":[2.0436980724,41.3421516418],"type":"Point"}
}