{
  "type": "Feature",
  "properties": {
    "iso:country":"ES",
    "sg:address":"Carrer de Josep Anselm Clave, 8",
    "sg:city":"Palma",
    "sg:orig_category":"Sociedades, Compa\u00d1\u00cdas Aseguradoras",
    "sg:phone":"+34 971 71 02 41",
    "sg:postcode":"07002",
    "sg:province":"Islas Baleares",
    "wof:name":"Llobera Sastre Joan Miquel",
    "wof:placetype":"venue"
},
  "geometry": {"coordinates":[2.6549708843,39.5733070374],"type":"Point"}
}