{
  "type": "Feature",
  "properties": {
    "addr:full":"Avda Portugal, 59 Salamanca Salamanca 37005",
    "addr:housenumber":"59",
    "addr:postcode":"37005",
    "addr:street":"Avda Portugal",
    "iso:country":"ES",
    "sg:address":"Avda Portugal, 59",
    "sg:city":"Salamanca",
    "sg:orig_category":"Abogados",
    "sg:phone":"+34 923 22 00 01",
    "sg:postcode":"37005",
    "sg:province":"Salamanca",
    "wof:name":"Fernandez Segura Julio",
    "wof:placetype":"venue"
},
  "geometry": {"coordinates":[-5.6580491066,40.9712905884],"type":"Point"}
}