{
  "type": "Feature",
  "properties": {
    "iso:country":"ES",
    "sg:address":"Carrer de Mar (la), 51",
    "sg:city":"Altea",
    "sg:orig_category":"Ropa Para Se\u00d1oras Y Caballeros (al Por Menor)",
    "sg:phone":"+34 965 84 15 17",
    "sg:postcode":"03590",
    "sg:province":"Alicante",
    "wof:name":"Martinez Alvado Feliciana",
    "wof:placetype":"venue"
},
  "geometry": {"coordinates":[-0.0490330011,38.5981063843],"type":"Point"}
}