{
  "type": "Feature",
  "properties": {
    "iso:country":"ES",
    "sg:address":"Calle de Cartagena, 129",
    "sg:city":"Madrid",
    "sg:orig_category":"Bisuter\u00cda, Joyer\u00cda, Relojer\u00cda (al Por Menor)",
    "sg:phone":"+34 915 63 22 71",
    "sg:postcode":"28002",
    "sg:province":"Madrid",
    "wof:name":"Vesperinas Castillo Felipe",
    "wof:placetype":"venue"
},
  "geometry": {"coordinates":[-3.6757810116,40.4423408508],"type":"Point"}
}