{
  "type": "Feature",
  "properties": {
    "iso:country":"ES",
    "sg:address":"Av Pais Valencia, 2",
    "sg:city":"Alfas Pi",
    "sg:orig_category":"Cl\u00cdnicas Dentales",
    "sg:phone":"+34 966 86 00 16",
    "sg:postcode":"03580",
    "sg:province":"Alicante",
    "wof:name":"Centro Dental Alfaz Del Pi S.l.",
    "wof:placetype":"venue"
},
  "geometry": {"coordinates":[-0.1005859971,38.5767669678],"type":"Point"}
}