{
  "type": "Feature",
  "properties": {
    "iso:country":"ES",
    "sg:address":"Estacion De Feve, S/n",
    "sg:city":"Figaredo",
    "sg:orig_category":"Transportes Ferroviarios",
    "sg:phone":"+34 985 42 66 94",
    "sg:postcode":"33683",
    "sg:province":"Asturias",
    "wof:name":"Ferrocarriles De Via Estrecha",
    "wof:placetype":"venue"
},
  "geometry": {"coordinates":[-5.7497859001,43.2142066956],"type":"Point"}
}