{
  "type": "Feature",
  "properties": {
    "addr:full":"Carr Ros De Palau, 5 Girona Girona 17003",
    "addr:housenumber":"5",
    "addr:postcode":"17003",
    "addr:street":"Carr Ros De Palau",
    "iso:country":"ES",
    "sg:address":"Carr Ros De Palau, 5",
    "sg:city":"Girona",
    "sg:orig_category":"Ingeniero",
    "sg:phone":"+34 972 20 05 46",
    "sg:postcode":"17003",
    "sg:province":"Girona",
    "wof:name":"At 90 S.l.",
    "wof:placetype":"venue"
},
  "geometry": {"coordinates":[2.8214998245,41.9547119141],"type":"Point"}
}