{
  "type": "Feature",
  "properties": {
    "iso:country":"ES",
    "sg:address":"Calle de Prado, S/n",
    "sg:city":"Alaejos",
    "sg:orig_category":"Empresas De Electricidad En General",
    "sg:phone":"+34 983 86 70 04",
    "sg:postcode":"47510",
    "sg:province":"Valladolid",
    "wof:name":"Hijo De Jorge Martin S. A.",
    "wof:placetype":"venue"
},
  "geometry": {"coordinates":[-5.2150697708,41.3096199036],"type":"Point"}
}