{
  "type": "Feature",
  "properties": {
    "iso:country":"ES",
    "sg:address":"Carrer de Mas Duran, 26",
    "sg:city":"Barcelona",
    "sg:orig_category":"Asociaciones, Organismos Culturales Y Socioeducativos",
    "sg:phone":"+34 933 53 11 79",
    "sg:postcode":"08016",
    "sg:province":"Barcelona",
    "wof:name":"Centro Andaluz Manuel De Falla",
    "wof:placetype":"venue"
},
  "geometry": {"coordinates":[2.1792960167,41.4437255859],"type":"Point"}
}