{
  "type": "Feature",
  "properties": {
    "iso:country":"ES",
    "sg:address":"Calle de Emilia Pardo Bazan, 22",
    "sg:city":"Coru\u00d1a",
    "sg:orig_category":"Alquiler De Veh\u00cdculos: Turismos Y Utilitarios",
    "sg:phone":"+34 981 12 16 76",
    "sg:postcode":"15005",
    "sg:province":"La Coru\u00f1a",
    "wof:name":"Grupo Clave Consultores S.a.",
    "wof:placetype":"venue"
},
  "geometry": {"coordinates":[-8.4072542191,43.3626060486],"type":"Point"}
}