{
  "type": "Feature",
  "properties": {
    "iso:country":"ES",
    "sg:address":"Cullerers, 4",
    "sg:city":"Alaquas",
    "sg:orig_category":"Madera Para Chapado",
    "sg:phone":"+34 961 50 70 01",
    "sg:postcode":"46970",
    "sg:province":"Valencia",
    "wof:name":"Negocios De Madera Y Sus Derivados S.l.",
    "wof:placetype":"venue"
},
  "geometry": {"coordinates":[-0.4785439968,39.4476203918],"type":"Point"}
}