{
  "type": "Feature",
  "properties": {
    "addr:full":"Calle de Ciscar, 61 Valencia Valencia 46005",
    "addr:housenumber":"61",
    "addr:postcode":"46005",
    "addr:street":"Calle De Ciscar",
    "iso:country":"ES",
    "sg:address":"Calle de Ciscar, 61",
    "sg:city":"Valencia",
    "sg:orig_category":"M\u00c9dicos: Cardiolog\u00cda Y Afecciones Cardiovasculares",
    "sg:phone":"+34 963 34 60 61",
    "sg:postcode":"46005",
    "sg:province":"Valencia",
    "wof:name":"Grima Serrano Alberto",
    "wof:placetype":"venue"
},
  "geometry": {"coordinates":[-0.3637200892,39.4632797241],"type":"Point"}
}