{
  "type": "Feature",
  "properties": {
    "addr:full":"Av Carles Buigas (de), 37 Salou Tarragona 43840",
    "addr:housenumber":"37",
    "addr:postcode":"43840",
    "addr:street":"Av Carles Buigas De",
    "iso:country":"ES",
    "sg:address":"Av Carles Buigas (de), 37",
    "sg:city":"Salou",
    "sg:orig_category":"Molduras, Junquillos, Listones Y Molduras Perforadas",
    "sg:phone":"+34 977 38 82 74",
    "sg:postcode":"43840",
    "sg:province":"Tarragona",
    "wof:name":"Ocio Salou S.l.",
    "wof:placetype":"venue"
},
  "geometry": {"coordinates":[1.1490180492,41.0718841553],"type":"Point"}
}