{
  "type": "Feature",
  "properties": {
    "addr:full":"Avda Constitucion, 10 Callosa Segura Alicante 03360",
    "addr:housenumber":"10",
    "addr:postcode":"03360",
    "addr:street":"Avda Constitucion",
    "iso:country":"ES",
    "sg:address":"Avda Constitucion, 10",
    "sg:city":"Callosa Segura",
    "sg:orig_category":"Semiller\u00cdas",
    "sg:phone":"+34 966 75 63 42",
    "sg:postcode":"03360",
    "sg:province":"Alicante",
    "wof:name":"Egio Berenguer Alberto",
    "wof:placetype":"venue"
},
  "geometry": {"coordinates":[-0.8775449991,38.1261177063],"type":"Point"}
}