{
  "type": "Feature",
  "properties": {
    "addr:full":"Carrer de Maravall, S/n Benidorm Alicante 03500",
    "addr:housenumber":"s / n",
    "addr:postcode":"03500",
    "addr:street":"Carrer De Maravall",
    "iso:country":"ES",
    "sg:address":"Carrer de Maravall, S/n",
    "sg:city":"Benidorm",
    "sg:orig_category":"Cajas De Ahorro",
    "sg:phone":"+34 966 81 25 12",
    "sg:postcode":"03500",
    "sg:province":"Alicante",
    "sg:website":"www.lacaixa.es",
    "wof:name":"Caixa D'estalvis I Pensions De Barcelona",
    "wof:placetype":"venue"
},
  "geometry": {"coordinates":[-0.1336289942,38.5404815674],"type":"Point"}
}