{
  "type": "Feature",
  "properties": {
    "addr:full":"Calle de Ramon Y Cajal, 4 Azagra Navarra 31560",
    "addr:housenumber":"4",
    "addr:postcode":"31560",
    "addr:street":"Calle De Ramon Y Cajal",
    "iso:country":"ES",
    "sg:address":"Calle de Ramon Y Cajal, 4",
    "sg:city":"Azagra",
    "sg:orig_category":"Conservas De Legumbres (fabricaci\u00d3n, Al Por Mayor)",
    "sg:phone":"+34 948 69 21 56",
    "sg:postcode":"31560",
    "sg:province":"Navarra",
    "wof:name":"Pastor Murgui S.i.",
    "wof:placetype":"venue"
},
  "geometry": {"coordinates":[-1.8972300291,42.3077316284],"type":"Point"}
}