{
  "type": "Feature",
  "properties": {
    "iso:country":"ES",
    "sg:address":"Calle de Santa Ana, 26",
    "sg:city":"Cuarte Huerva",
    "sg:orig_category":"Droguer\u00cdas (al Por Menor)",
    "sg:phone":"+34 976 50 36 28",
    "sg:postcode":"50410",
    "sg:province":"Zaragoza",
    "wof:name":"Sego 2000 S.l.l.",
    "wof:placetype":"venue"
},
  "geometry": {"coordinates":[-0.9312289953,41.5959014893],"type":"Point"}
}