{
  "type": "Feature",
  "properties": {
    "addr:full":"Calle de Rosario, 3 Ricla Zaragoza 50270",
    "addr:housenumber":"3",
    "addr:postcode":"50270",
    "addr:street":"Calle De Rosario",
    "iso:country":"ES",
    "sg:address":"Calle de Rosario, 3",
    "sg:city":"Ricla",
    "sg:orig_category":"Ingeniero",
    "sg:phone":"+34 976 60 63 70",
    "sg:postcode":"50270",
    "sg:province":"Zaragoza",
    "wof:name":"Asimec Electricidad S. L.",
    "wof:placetype":"venue"
},
  "geometry": {"coordinates":[-1.4050557613,41.5034484863],"type":"Point"}
}