{
  "type": "Feature",
  "properties": {
    "addr:full":"Ctra Zaragoza, Km. 0072,7 Alfaro La Rioja 26540",
    "addr:postcode":"26540",
    "addr:street":"Ctra Zaragoza Km. 0072,7 Alfaro;Rioja",
    "iso:country":"ES",
    "sg:address":"Ctra Zaragoza, Km. 0072,7",
    "sg:city":"Alfaro",
    "sg:orig_category":"Cooperativas Agr\u00cdcolas",
    "sg:phone":"+34 941 18 22 65",
    "sg:postcode":"26540",
    "sg:province":"La Rioja",
    "wof:name":"Cosimesa Sociedad Cooperativa Limitada",
    "wof:placetype":"venue"
},
  "geometry": {"coordinates":[-1.7591480017,42.1801643372],"type":"Point"}
}