{
  "type": "Feature",
  "properties": {
    "addr:full":"Avda Ricardo Soriano, 1 Marbella M\u00e1laga 29600",
    "addr:housenumber":"1",
    "addr:postcode":"29600",
    "addr:street":"Avda Ricardo Soriano;Ma\u0301Laga",
    "iso:country":"ES",
    "sg:address":"Avda Ricardo Soriano, 1",
    "sg:city":"Marbella",
    "sg:orig_category":"Asesor\u00cda Fiscal Y Jur\u00cddica",
    "sg:phone":"+34 952 82 83 99",
    "sg:postcode":"29600",
    "sg:province":"M\u00e1laga",
    "wof:name":"Ric Maiz Bego\u00f1a",
    "wof:placetype":"venue"
},
  "geometry": {"coordinates":[-4.8868179321,36.5092964172],"type":"Point"}
}