{
  "type": "Feature",
  "properties": {
    "addr:full":"Calle de Ruiz Zorrilla, 19 Castellon Castell\u00f3n 12001",
    "addr:housenumber":"19",
    "addr:postcode":"12001",
    "addr:street":"Calle De Ruiz Zorrilla",
    "iso:country":"ES",
    "sg:address":"Calle de Ruiz Zorrilla, 19",
    "sg:city":"Castellon",
    "sg:orig_category":"Deportes Y Ocio: Art\u00cdculos Y Ropas (al Por Menor Y Accesorios)",
    "sg:phone":"+34 964 24 12 24",
    "sg:postcode":"12001",
    "sg:province":"Castell\u00f3n",
    "wof:name":"Agut Agut Esther",
    "wof:placetype":"venue"
},
  "geometry": {"coordinates":[-0.0401939005,39.9848594666],"type":"Point"}
}