{
  "type": "Feature",
  "properties": {
    "iso:country":"ES",
    "sg:address":"Pl. Gleisa, 1",
    "sg:city":"Bossost",
    "sg:orig_category":"Ense\u00d1anza, Formaci\u00d3n Profesional: Aprendizaje",
    "sg:phone":"+34 973 64 81 57",
    "sg:postcode":"25550",
    "sg:province":"Lleida",
    "wof:name":"Ajuntament De Bossost",
    "wof:placetype":"venue"
},
  "geometry": {"coordinates":[0.7128055096,42.8120956421],"type":"Point"}
}