{
  "type": "Feature",
  "properties": {
    "iso:country":"ES",
    "sg:address":"Trva Ugarte, 2",
    "sg:city":"Ugarte",
    "sg:orig_category":"Suministros Y Materiales Industriales",
    "sg:phone":"+34 944 86 26 68",
    "sg:postcode":"48510",
    "sg:province":"Vizcaya",
    "wof:name":"Ambytecno S.a.",
    "wof:placetype":"venue"
},
  "geometry": {"coordinates":[-3.0158412457,43.2911567688],"type":"Point"}
}