{
  "type": "Feature",
  "properties": {
    "addr:full":"Carr Ignasi Bastus, 2 Lleida Lleida 25001",
    "addr:housenumber":"2",
    "addr:postcode":"25001",
    "addr:street":"Carr Ignasi Bastus",
    "iso:country":"ES",
    "sg:address":"Carr Ignasi Bastus, 2",
    "sg:city":"Lleida",
    "sg:orig_category":"Electricidad: Instaladores",
    "sg:phone":"+34 973 20 35 29",
    "sg:postcode":"25001",
    "sg:province":"Lleida",
    "wof:name":"Bosch Prim Antonio",
    "wof:placetype":"venue"
},
  "geometry": {"coordinates":[0.6429499984,41.6025695801],"type":"Point"}
}