{
  "type": "Feature",
  "properties": {
    "iso:country":"ES",
    "sg:address":"Barrio Nuevo, S/n",
    "sg:city":"Valsain",
    "sg:orig_category":"Cajas De Ahorro",
    "sg:phone":"+34 921 47 13 33",
    "sg:postcode":"40109",
    "sg:province":"Segovia",
    "wof:name":"Caja De Ahorros Y Monte De Piedad De Segovia",
    "wof:placetype":"venue"
},
  "geometry": {"coordinates":[-4.0267820358,40.8787117004],"type":"Point"}
}