{
  "type": "Feature",
  "properties": {
    "addr:full":"Carrer de Barcelona, S/n Lloren\u00e7 Penedes Tarragona 43712",
    "addr:postcode":"43712",
    "addr:street":"Carrer De Barcelona S / N Llorenc\u0327 Penedes",
    "iso:country":"ES",
    "sg:address":"Carrer de Barcelona, S/n",
    "sg:city":"Lloren\u00e7 Penedes",
    "sg:orig_category":"M\u00c1rmoles, Granitos Y Piedras Naturales",
    "sg:phone":"+34 977 67 72 17",
    "sg:postcode":"43712",
    "sg:province":"Tarragona",
    "wof:name":"Marmols Y Granits Agape S.l.",
    "wof:placetype":"venue"
},
  "geometry": {"coordinates":[1.5574849844,41.2874641418],"type":"Point"}
}