{
  "type": "Feature",
  "properties": {
    "iso:country":"ES",
    "sg:address":"Carrer de Argimon, 2",
    "sg:city":"Barcelona",
    "sg:orig_category":"Papeler\u00cdas, Librer\u00cdas",
    "sg:phone":"+34 934 29 40 55",
    "sg:postcode":"08032",
    "sg:province":"Barcelona",
    "wof:name":"Aran Pascual Ramon",
    "wof:placetype":"venue"
},
  "geometry": {"coordinates":[2.1565551758,41.427482605],"type":"Point"}
}