{
  "type": "Feature",
  "properties": {
    "addr:full":"Calle de Reina (de La), 68 Aranjuez Madrid 28300",
    "addr:housenumber":"68",
    "addr:postcode":"28300",
    "addr:street":"Calle De Reina De La",
    "iso:country":"ES",
    "sg:address":"Calle de Reina (de La), 68",
    "sg:city":"Aranjuez",
    "sg:orig_category":"Empresas De Portes Y Mensajer\u00cda",
    "sg:phone":"+34 918 01 16 27",
    "sg:postcode":"28300",
    "sg:province":"Madrid",
    "wof:name":"Arrogante Rojas Valeriano",
    "wof:placetype":"venue"
},
  "geometry": {"coordinates":[-3.5933532715,40.0382461548],"type":"Point"}
}