{
  "type": "Feature",
  "properties": {
    "addr:full":"Calle de Mar Adriatico (del), 1 Poligono De San Fernando De Henares Madrid 28830",
    "addr:housenumber":"1",
    "addr:postcode":"28830",
    "addr:street":"Calle De Mar Adriatico Del",
    "iso:country":"ES",
    "sg:address":"Calle de Mar Adriatico (del), 1",
    "sg:city":"Poligono De San Fernando De Henares",
    "sg:orig_category":"Centros Empresariales",
    "sg:phone":"+34 916 76 59 04",
    "sg:postcode":"28830",
    "sg:province":"Madrid",
    "wof:name":"Plataformas Aereas De Trabajo Cristina Alonso S.l.",
    "wof:placetype":"venue"
},
  "geometry": {"coordinates":[-3.5353159904,40.4256858826],"type":"Point"}
}