{
  "type": "Feature",
  "properties": {
    "addr:full":"Calle de Ba\u00d1os, 13 Sanlucar De Barrameda C\u00e1diz 11540",
    "addr:housenumber":"13",
    "addr:postcode":"11540",
    "addr:street":"Calle De Ban\u0303Os;Ca\u0301Diz",
    "iso:country":"ES",
    "sg:address":"Calle de Ba\u00d1os, 13",
    "sg:city":"Sanlucar De Barrameda",
    "sg:orig_category":"Centros Empresariales",
    "sg:phone":"+34 956 38 45 02",
    "sg:postcode":"11540",
    "sg:province":"C\u00e1diz",
    "wof:name":"Rosario Segura Pe\u00f1alosa",
    "wof:placetype":"venue"
},
  "geometry": {"coordinates":[-6.3566651344,36.7764587402],"type":"Point"}
}