{
  "type": "Feature",
  "properties": {
    "addr:full":"Calle de Antonio Leal Del Ojo, 1 Puerto De Santa Maria C\u00e1diz 11500",
    "addr:housenumber":"1",
    "addr:postcode":"11500",
    "addr:street":"Calle De Antonio Leal Del Ojo;Ca\u0301Diz",
    "iso:country":"ES",
    "sg:address":"Calle de Antonio Leal Del Ojo, 1",
    "sg:city":"Puerto De Santa Maria",
    "sg:orig_category":"Albergues",
    "sg:phone":"+34 956 87 32 70",
    "sg:postcode":"11500",
    "sg:province":"C\u00e1diz",
    "wof:name":"Hogar Luisa De Marillac",
    "wof:placetype":"venue"
},
  "geometry": {"coordinates":[-6.2394213676,36.5945549011],"type":"Point"}
}