{
  "type": "Feature",
  "properties": {
    "addr:full":"Aita Larramendi Kalea, 10 Andoain Guip\u00f9zcoa 20140",
    "addr:housenumber":"10",
    "addr:postcode":"20140",
    "addr:street":"Aita Larramendi Kalea;Guipu\u0300Zcoa",
    "iso:country":"ES",
    "sg:address":"Aita Larramendi Kalea, 10",
    "sg:city":"Andoain",
    "sg:orig_category":"Materias Pl\u00c1sticas: Productos De Consumo Masivo (fabricaci\u00d3n, Al Por Mayor)",
    "sg:phone":"+34 943 59 04 44",
    "sg:postcode":"20140",
    "sg:province":"Guip\u00f9zcoa",
    "wof:name":"Moreda Holgado Francisco",
    "wof:placetype":"venue"
},
  "geometry": {"coordinates":[-2.0279490948,43.2110824585],"type":"Point"}
}