{
  "type": "Feature",
  "properties": {
    "iso:country":"ES",
    "sg:address":"Calle de Gran Via, 22",
    "sg:city":"Madrid",
    "sg:classifiers":[
        {
            "category":"Communications",
            "type":"Services"
        }
    ],
    "sg:phone":"+34 915 22 97 15",
    "sg:postcode":"28013",
    "sg:province":"Madrid",
    "sg:tags":[
        "televisiones",
        "y",
        "radio"
    ],
    "wof:name":"Grupo Latino De Radio",
    "wof:placetype":"venue"
},
  "geometry": {"coordinates":[-3.7005279064,40.4200592041],"type":"Point"}
}