{
  "type": "Feature",
  "properties": {
    "addr:full":"Calle de Real, 26 Ciudad Real Ciudad Real 13002",
    "addr:housenumber":"26",
    "addr:postcode":"13002",
    "addr:street":"Calle De Real",
    "iso:country":"ES",
    "sg:address":"Calle de Real, 26",
    "sg:city":"Ciudad Real",
    "sg:orig_category":"Supermercados Y Hipermercados",
    "sg:phone":"+34 926 22 68 23",
    "sg:postcode":"13002",
    "sg:province":"Ciudad Real",
    "sg:website":"www.mercadona.es",
    "wof:name":"Mercadona S.a.",
    "wof:placetype":"venue"
},
  "geometry": {"coordinates":[-3.9324541092,38.987613678],"type":"Point"}
}