{
  "type": "Feature",
  "properties": {
    "addr:full":"Calle de Melgares, 14 Villaluenga Sagra Toledo 45520",
    "addr:housenumber":"14",
    "addr:postcode":"45520",
    "addr:street":"Calle De Melgares",
    "iso:country":"ES",
    "sg:address":"Calle de Melgares, 14",
    "sg:city":"Villaluenga Sagra",
    "sg:orig_category":"Comercio De Hierro",
    "sg:phone":"+34 925 53 15 39",
    "sg:postcode":"45520",
    "sg:province":"Toledo",
    "wof:name":"Sidercen S.a.",
    "wof:placetype":"venue"
},
  "geometry": {"coordinates":[-3.9184570312,40.0272941589],"type":"Point"}
}