{
  "type": "Feature",
  "properties": {
    "addr:full":"Sames, S/n Llomba Asturias 33558",
    "addr:postcode":"33558",
    "addr:street":"S / N Llomba Asturias",
    "iso:country":"ES",
    "sg:address":"Sames, S/n",
    "sg:city":"Llomba",
    "sg:classifiers":[
        {
            "category":"Taxi",
            "type":"Transportation"
        }
    ],
    "sg:phone":"+34 985 94 47 57",
    "sg:postcode":"33558",
    "sg:province":"Asturias",
    "wof:name":"Fuente Blanco Felix De La",
    "wof:placetype":"venue"
},
  "geometry": {"coordinates":[-5.1289191246,43.2689743042],"type":"Point"}
}