{
  "type": "Feature",
  "properties": {
    "iso:country":"ES",
    "sg:address":"Calle de Doctor Fleming, S/n",
    "sg:city":"Requena",
    "sg:orig_category":"Papeler\u00cdas, Librer\u00cdas",
    "sg:phone":"+34 962 30 28 48",
    "sg:postcode":"46340",
    "sg:province":"Valencia",
    "wof:name":"Dise\u00f1o Y Gestion C.b.",
    "wof:placetype":"venue"
},
  "geometry": {"coordinates":[-1.1010040045,39.4896240234],"type":"Point"}
}