{
  "type": "Feature",
  "properties": {
    "addr:full":"Calle de Buleria (la), 2 Jerez De La Frontera C\u00e1diz 11404",
    "addr:housenumber":"2",
    "addr:postcode":"11404",
    "addr:street":"Calle De Buleria La",
    "iso:country":"ES",
    "sg:address":"Calle de Buleria (la), 2",
    "sg:city":"Jerez De La Frontera",
    "sg:orig_category":"Estilistas Y Estudios De Estilo De Corte Y Confecci\u00d3n",
    "sg:phone":"+34 956 18 34 90",
    "sg:postcode":"11404",
    "sg:province":"C\u00e1diz",
    "wof:name":"Confecciones Nieves Puerto S.l.",
    "wof:placetype":"venue"
},
  "geometry": {"coordinates":[-6.1445708275,36.6938552856],"type":"Point"}
}