{
  "type": "Feature",
  "properties": {
    "iso:country":"ES",
    "sg:address":"Calle de Via Carpetana, 141",
    "sg:city":"Madrid",
    "sg:orig_category":"Farmacias",
    "sg:phone":"+34 914 61 79 57",
    "sg:postcode":"28047",
    "sg:province":"Madrid",
    "wof:name":"Garcia Naranjo Jonas",
    "wof:placetype":"venue"
},
  "geometry": {"coordinates":[-3.7360029221,40.397403717],"type":"Point"}
}