{
  "type": "Feature",
  "properties": {
    "iso:country":"ES",
    "sg:address":"Calle de Luis I, 53",
    "sg:city":"Madrid",
    "sg:orig_category":"Ebanister\u00cda",
    "sg:phone":"+34 913 80 33 51",
    "sg:postcode":"28031",
    "sg:province":"Madrid",
    "wof:name":"Barranco Gomez Alfonso",
    "wof:placetype":"venue"
},
  "geometry": {"coordinates":[-3.6465239525,40.375038147],"type":"Point"}
}