{
  "type": "Feature",
  "properties": {
    "iso:country":"ES",
    "sg:address":"Avda Angeles (de Los), 12",
    "sg:city":"Getafe",
    "sg:orig_category":"Lencer\u00cda Femenina, Corseter\u00cda, Trajes De Ba\u00d1o (al Por Menor)",
    "sg:phone":"+34 916 83 60 20",
    "sg:postcode":"28903",
    "sg:province":"Madrid",
    "wof:name":"Madrigal Alonso Maria Rosa",
    "wof:placetype":"venue"
},
  "geometry": {"coordinates":[-3.7229590416,40.3094596863],"type":"Point"}
}