{
  "type": "Feature",
  "properties": {
    "addr:full":"Calle de Mocejon, 1 Santander Cantabria 39009",
    "addr:housenumber":"1",
    "addr:postcode":"39009",
    "addr:street":"Calle De Mocejon",
    "iso:country":"ES",
    "sg:address":"Calle de Mocejon, 1",
    "sg:city":"Santander",
    "sg:orig_category":"Molduras, Junquillos, Listones Y Molduras Perforadas",
    "sg:phone":"+34 942 22 20 74",
    "sg:postcode":"39009",
    "sg:province":"Cantabria",
    "wof:name":"Sociedad Regional De Informatica S.a.",
    "wof:placetype":"venue"
},
  "geometry": {"coordinates":[-3.8195464611,43.4516105652],"type":"Point"}
}