{
  "type": "Feature",
  "properties": {
    "addr:full":"Cra. Dosrius, 130 Cardedeu Barcelona 08440",
    "addr:housenumber":"130",
    "addr:postcode":"08440",
    "iso:country":"ES",
    "sg:address":"Cra. Dosrius, 130",
    "sg:city":"Cardedeu",
    "sg:orig_category":"Caf\u00c9s, Bares, Cervecer\u00cdas",
    "sg:phone":"+34 938 46 18 46",
    "sg:postcode":"08440",
    "sg:province":"Barcelona",
    "wof:name":"Sanchez Rubio Concepcion",
    "wof:placetype":"venue"
},
  "geometry": {"coordinates":[2.3563768864,41.6445159912],"type":"Point"}
}