{
  "type": "Feature",
  "properties": {
    "iso:country":"ES",
    "sg:address":"Ctra Suspiro Moro, 17",
    "sg:city":"Almu\u00f1ecar",
    "sg:orig_category":"Empresas De Carpinter\u00cda Met\u00c1lica",
    "sg:phone":"+34 958 63 22 04",
    "sg:postcode":"18690",
    "sg:province":"Granada",
    "wof:name":"Ferrolum S.l.",
    "wof:placetype":"venue"
},
  "geometry": {"coordinates":[-3.6895558834,36.7387619019],"type":"Point"}
}