{
  "type": "Feature",
  "properties": {
    "iso:country":"ES",
    "sg:address":"Calle de Linares, 21",
    "sg:city":"Martos",
    "sg:orig_category":"Caf\u00c9s, Bares, Cervecer\u00cdas",
    "sg:phone":"+34 953 55 39 98",
    "sg:postcode":"23600",
    "sg:province":"Ja\u00e9n",
    "wof:name":"Jimenez Rodriguez Antonio Manuel",
    "wof:placetype":"venue"
},
  "geometry": {"coordinates":[-3.9721839428,37.7081184387],"type":"Point"}
}