{
  "type": "Feature",
  "properties": {
    "iso:country":"ES",
    "sg:address":"Calle de Tierra De Barros (de La), 2",
    "sg:city":"Coslada",
    "sg:orig_category":"Delegados, Agentes De Tr\u00c1nsito, Auxiliares De Transporte Internacional",
    "sg:phone":"+34 916 74 18 02",
    "sg:postcode":"28820",
    "sg:province":"Madrid",
    "wof:name":"Arrendamiento De Terrenos Y Minerales S.a.",
    "wof:placetype":"venue"
},
  "geometry": {"coordinates":[-3.5439155102,40.4326095581],"type":"Point"}
}