{
  "type": "Feature",
  "properties": {
    "iso:country":"ES",
    "sg:address":"Trav De Gracia, 96",
    "sg:city":"Barcelona",
    "sg:orig_category":"Fotograf\u00cda Art\u00cdstica Y Retratos",
    "sg:phone":"+34 932 37 09 02",
    "sg:postcode":"08006",
    "sg:province":"Barcelona",
    "wof:name":"Morini  Stefano",
    "wof:placetype":"venue"
},
  "geometry": {"coordinates":[2.1537179947,41.3986930847],"type":"Point"}
}