{
  "type": "Feature",
  "properties": {
    "addr:full":"Avgd Espioca, 114 Silla Valencia 46460",
    "addr:housenumber":"114",
    "addr:postcode":"46460",
    "addr:street":"Silla",
    "iso:country":"ES",
    "sg:address":"Avgd Espioca, 114",
    "sg:city":"Silla",
    "sg:orig_category":"Art\u00cdculos De Madera (fabricaci\u00d3n Y Al Por Mayor)",
    "sg:phone":"+34 961 20 21 01",
    "sg:postcode":"46460",
    "sg:province":"Valencia",
    "wof:name":"Mig Punt Coop. V.",
    "wof:placetype":"venue"
},
  "geometry": {"coordinates":[-0.417858988,39.3685531616],"type":"Point"}
}