{
  "type": "Feature",
  "properties": {
    "addr:full":"Calle de Santa Ana, 41 Estepa Sevilla 41560",
    "addr:housenumber":"41",
    "addr:postcode":"41560",
    "addr:street":"Calle De Santa Ana;Sevilla",
    "iso:country":"ES",
    "sg:address":"Calle de Santa Ana, 41",
    "sg:city":"Estepa",
    "sg:orig_category":"Peluquer\u00cdas, Peluquer\u00cda Mixta",
    "sg:phone":"+34 955 91 45 12",
    "sg:postcode":"41560",
    "sg:province":"Sevilla",
    "wof:name":"Amoros Trillo Gema",
    "wof:placetype":"venue"
},
  "geometry": {"coordinates":[-4.8754439354,37.2914733887],"type":"Point"}
}