{
  "type": "Feature",
  "properties": {
    "iso:country":"ES",
    "sg:address":"Calle de Luis Ibarra Landete, 6",
    "sg:city":"Guadalajara",
    "sg:orig_category":"Comunidades Religiosas",
    "sg:phone":"+34 949 22 37 04",
    "sg:postcode":"19004",
    "sg:province":"Guadalajara",
    "wof:name":"Parroquia De San Pascual Bailon",
    "wof:placetype":"venue"
},
  "geometry": {"coordinates":[-3.1717939377,40.6319694519],"type":"Point"}
}