{
  "type": "Feature",
  "properties": {
    "addr:full":"Avda Alcalde Leoncio Fdez Real, 25 Sobradelo Ourense 32330",
    "addr:housenumber":"25",
    "addr:postcode":"32330",
    "addr:street":"Avda Alcalde Leoncio Fdez Real",
    "iso:country":"ES",
    "sg:address":"Avda Alcalde Leoncio Fdez Real, 25",
    "sg:city":"Sobradelo",
    "sg:orig_category":"Reposter\u00cdas",
    "sg:phone":"+34 988 33 51 52",
    "sg:postcode":"32330",
    "sg:province":"Ourense",
    "wof:name":"Mendez Vega Julia",
    "wof:placetype":"venue"
},
  "geometry": {"coordinates":[-6.9119110107,42.4156227112],"type":"Point"}
}