{
  "type": "Feature",
  "properties": {
    "addr:full":"C/ Jacinto Benavente, 1 Moncofa Castell\u00f3n 12593",
    "addr:housenumber":"1",
    "addr:postcode":"12593",
    "addr:street":"C / Jacinto Benavente;Castello\u0301N",
    "iso:country":"ES",
    "sg:address":"C/ Jacinto Benavente, 1",
    "sg:city":"Moncofa",
    "sg:orig_category":"Peluquer\u00cdas, Peluquer\u00cda Mixta",
    "sg:phone":"+34 964 58 03 57",
    "sg:postcode":"12593",
    "sg:province":"Castell\u00f3n",
    "wof:name":"Esteve Mecho Leonardo",
    "wof:placetype":"venue"
},
  "geometry": {"coordinates":[-0.1459770054,39.8085899353],"type":"Point"}
}