{
  "type": "Feature",
  "properties": {
    "iso:country":"ES",
    "sg:address":"Calle de Realejo, 6",
    "sg:city":"Cordoba",
    "sg:orig_category":"Bisuter\u00cda, Joyer\u00cda, Relojer\u00cda (al Por Menor)",
    "sg:phone":"+34 957 48 21 96",
    "sg:postcode":"14002",
    "sg:province":"C\u00f3rdoba",
    "wof:name":"Notario Gomez Jose",
    "wof:placetype":"venue"
},
  "geometry": {"coordinates":[-4.7723650932,37.8862762451],"type":"Point"}
}