{
  "type": "Feature",
  "properties": {
    "iso:country":"ES",
    "sg:address":"H, 14",
    "sg:city":"Alcoi",
    "sg:orig_category":"Maquinaria Para Industrias Diversas",
    "sg:phone":"+34 966 52 27 32",
    "sg:postcode":"03800",
    "sg:province":"Alicante",
    "wof:name":"Espinosa Esteban Jesus",
    "wof:placetype":"venue"
},
  "geometry": {"coordinates":[-0.4557060003,38.7139015198],"type":"Point"}
}