{
  "type": "Feature",
  "properties": {
    "addr:full":"Carrer de Floridablanca, 145 Barcelona Barcelona 08011",
    "addr:housenumber":"145",
    "addr:postcode":"08011",
    "addr:street":"Carrer De Floridablanca",
    "iso:country":"ES",
    "sg:address":"Carrer de Floridablanca, 145",
    "sg:city":"Barcelona",
    "sg:orig_category":"Material De Ocasi\u00d3n Para Particulares (compra, Reventa)",
    "sg:phone":"+34 934 23 99 00",
    "sg:postcode":"08011",
    "sg:province":"Barcelona",
    "wof:name":"Olimpic Tot Serveis S. L.",
    "wof:placetype":"venue"
},
  "geometry": {"coordinates":[2.1629331112,41.382019043],"type":"Point"}
}