{
  "type": "Feature",
  "properties": {
    "addr:full":"Carrer de Valencia (de), 22 Salou Tarragona 43840",
    "addr:housenumber":"22",
    "addr:postcode":"43840",
    "addr:street":"Carrer De Valencia De",
    "iso:country":"ES",
    "sg:address":"Carrer de Valencia (de), 22",
    "sg:city":"Salou",
    "sg:orig_category":"Asociaciones Y Clubs Deportivos",
    "sg:phone":"+34 977 35 08 56",
    "sg:postcode":"43840",
    "sg:province":"Tarragona",
    "sg:website":"www.saloubeach.com",
    "wof:name":"Calcats Sport Virginia S.c.p.",
    "wof:placetype":"venue"
},
  "geometry": {"coordinates":[1.1301089525,41.0767288208],"type":"Point"}
}