{
  "type": "Feature",
  "properties": {
    "addr:full":"C/ Lope De Vega, 59 Elche Alicante 03201",
    "addr:housenumber":"59",
    "addr:postcode":"03201",
    "addr:street":"C / Lope De Vega",
    "iso:country":"ES",
    "sg:address":"C/ Lope De Vega, 59",
    "sg:city":"Elche",
    "sg:orig_category":"Empresas De Carpinter\u00cda De Madera",
    "sg:phone":"+34 965 43 59 32",
    "sg:postcode":"03201",
    "sg:province":"Alicante",
    "wof:name":"Tora Pastor Emilio",
    "wof:placetype":"venue"
},
  "geometry": {"coordinates":[-0.7049900293,38.2682189941],"type":"Point"}
}