{
  "type": "Feature",
  "properties": {
    "addr:full":"Carr Pep Ventura, 4 Figueres Girona 17600",
    "addr:housenumber":"4",
    "addr:postcode":"17600",
    "addr:street":"Carr Pep Ventura",
    "iso:country":"ES",
    "sg:address":"Carr Pep Ventura, 4",
    "sg:city":"Figueres",
    "sg:orig_category":"Arboricultura Y Producci\u00d3n De Frutas",
    "sg:phone":"+34 972 51 46 00",
    "sg:postcode":"17600",
    "sg:province":"Girona",
    "wof:name":"Poupart Figueres S.l.",
    "wof:placetype":"venue"
},
  "geometry": {"coordinates":[2.9593410492,42.2670440674],"type":"Point"}
}