{
  "type": "Feature",
  "properties": {
    "iso:country":"ES",
    "sg:address":"Calle de Solera, S/n",
    "sg:city":"Mojonera",
    "sg:classifiers":[
        {
            "category":"Autos & Motor Vehicles",
            "subcategory":"Automobile Sales",
            "type":"Retail Goods"
        }
    ],
    "sg:phone":"+34 950 33 13 68",
    "sg:postcode":"04745",
    "sg:province":"Almer\u00eda",
    "wof:name":"Buendia Cerezuela Gregorio",
    "wof:placetype":"venue"
},
  "geometry": {"coordinates":[-2.6807188988,36.754119873],"type":"Point"}
}