{
  "type": "Feature",
  "properties": {
    "addr:full":"Calle de Cervantes, 53 Coria C\u00e1ceres 10800",
    "addr:housenumber":"53",
    "addr:postcode":"10800",
    "addr:street":"Calle De Cervantes;Ca\u0301Ceres",
    "iso:country":"ES",
    "sg:address":"Calle de Cervantes, 53",
    "sg:city":"Coria",
    "sg:orig_category":"Abogados",
    "sg:phone":"+34 927 50 42 41",
    "sg:postcode":"10800",
    "sg:province":"C\u00e1ceres",
    "wof:name":"Mateos Hernandez Maria De Navelonga",
    "wof:placetype":"venue"
},
  "geometry": {"coordinates":[-6.540430069,39.9901237488],"type":"Point"}
}