{
  "type": "Feature",
  "properties": {
    "iso:country":"ES",
    "sg:address":"Calle de Teruel, 31",
    "sg:city":"Caspe",
    "sg:orig_category":"Cueros Y Pieles (al Por Mayor)",
    "sg:phone":"+34 976 63 11 61",
    "sg:postcode":"50700",
    "sg:province":"Zaragoza",
    "wof:name":"Pieles Domingo S.a.l.",
    "wof:placetype":"venue"
},
  "geometry": {"coordinates":[-0.0417210013,41.2329216003],"type":"Point"}
}