{
  "type": "Feature",
  "properties": {
    "iso:country":"ES",
    "sg:address":"Calle de Santisimo, 15",
    "sg:city":"Barrios",
    "sg:orig_category":"Imprenta",
    "sg:phone":"+34 956 62 00 85",
    "sg:postcode":"11370",
    "sg:province":"C\u00e1diz",
    "wof:name":"Graficas La Palma C.b.",
    "wof:placetype":"venue"
},
  "geometry": {"coordinates":[-5.4919347763,36.1860961914],"type":"Point"}
}