{
  "type": "Feature",
  "properties": {
    "addr:full":"Calle de Ramon Ortiz De Zarate, 9 Vitoria-gasteiz \u00c1lava 01005",
    "addr:housenumber":"9",
    "addr:postcode":"01005",
    "addr:street":"Calle De Ramon Ortiz De Zarate",
    "iso:country":"ES",
    "sg:address":"Calle de Ramon Ortiz De Zarate, 9",
    "sg:city":"Vitoria-gasteiz",
    "sg:orig_category":"Abogados",
    "sg:phone":"+34 945 14 04 14",
    "sg:postcode":"01005",
    "sg:province":"\u00c1lava",
    "wof:name":"Saez De Asteasu Lopez De Alda Angel",
    "wof:placetype":"venue"
},
  "geometry": {"coordinates":[-2.6698551178,42.8434715271],"type":"Point"}
}