{
  "type": "Feature",
  "properties": {
    "addr:full":"Calle de Gaspar De Montellano, 15 Priego Cordoba C\u00f3rdoba 14800",
    "addr:housenumber":"15",
    "addr:postcode":"14800",
    "addr:street":"Calle De Gaspar De Montellano;Cordoba Co\u0301Rdoba",
    "iso:country":"ES",
    "sg:address":"Calle de Gaspar De Montellano, 15",
    "sg:city":"Priego Cordoba",
    "sg:orig_category":"Estilistas Y Estudios De Estilo De Corte Y Confecci\u00d3n",
    "sg:phone":"+34 957 70 07 00",
    "sg:postcode":"14800",
    "sg:province":"C\u00f3rdoba",
    "wof:name":"Rivera Merida Francisco",
    "wof:placetype":"venue"
},
  "geometry": {"coordinates":[-4.1974258423,37.4416542053],"type":"Point"}
}