{
  "type": "Feature",
  "properties": {
    "iso:country":"ES",
    "sg:address":"Calle de Mateo Seoane Sobral, 22",
    "sg:city":"Valladolid",
    "sg:orig_category":"Reposter\u00cdas",
    "sg:phone":"+34 983 37 61 49",
    "sg:postcode":"47014",
    "sg:province":"Valladolid",
    "wof:name":"Tahona Parquesol S.l.",
    "wof:placetype":"venue"
},
  "geometry": {"coordinates":[-4.7553272247,41.6367454529],"type":"Point"}
}