{
  "type": "Feature",
  "properties": {
    "addr:full":"C/ Alpuixarra, 14 Elche Alicante 03202",
    "addr:housenumber":"14",
    "addr:postcode":"03202",
    "addr:street":"C / Alpuixarra",
    "iso:country":"ES",
    "sg:address":"C/ Alpuixarra, 14",
    "sg:city":"Elche",
    "sg:orig_category":"Electricidad: Equipos Industriales, Componentes (fabricaci\u00d3n)",
    "sg:phone":"+34 965 45 46 46",
    "sg:postcode":"03202",
    "sg:province":"Alicante",
    "wof:name":"Electricidad Carri S.l.",
    "wof:placetype":"venue"
},
  "geometry": {"coordinates":[-0.6942780018,38.2671775818],"type":"Point"}
}