{
  "type": "Feature",
  "properties": {
    "iso:country":"ES",
    "sg:address":"Calle de Pio Baroja, 1",
    "sg:city":"Granada",
    "sg:orig_category":"Molduras, Junquillos, Listones Y Molduras Perforadas",
    "sg:phone":"+34 958 27 07 44",
    "sg:postcode":"18003",
    "sg:province":"Granada",
    "wof:name":"Eurotel Sur S.l.",
    "wof:placetype":"venue"
},
  "geometry": {"coordinates":[-3.6110179424,37.1796913147],"type":"Point"}
}