{
  "type": "Feature",
  "properties": {
    "iso:country":"ES",
    "sg:address":"Ctra Medina, 5",
    "sg:city":"Pe\u00e7aranda De Bracamonte",
    "sg:orig_category":"Mec\u00c1nico Del Autom\u00d3vil",
    "sg:phone":"+34 923 54 18 31",
    "sg:postcode":"37300",
    "sg:province":"Salamanca",
    "wof:name":"Perez Perez Roman",
    "wof:placetype":"venue"
},
  "geometry": {"coordinates":[-5.1993021965,40.9030456543],"type":"Point"}
}