{
  "type": "Feature",
  "properties": {
    "addr:full":"El Maderao, S/n Cervera Pisuerga Palencia 34840",
    "addr:housenumber":"s / n",
    "addr:postcode":"34840",
    "iso:country":"ES",
    "sg:address":"El Maderao, S/n",
    "sg:city":"Cervera Pisuerga",
    "sg:orig_category":"Reposter\u00cdas",
    "sg:phone":"+34 979 87 00 22",
    "sg:postcode":"34840",
    "sg:province":"Palencia",
    "wof:name":"Agrupacion De Panaderos Del Pisuerga S. L.",
    "wof:placetype":"venue"
},
  "geometry": {"coordinates":[-4.5311746597,42.0124588013],"type":"Point"}
}