{
  "type": "Feature",
  "properties": {
    "addr:full":"Avda Teniente Dominguez, 84 Grove Pontevedra 36980",
    "addr:housenumber":"84",
    "addr:postcode":"36980",
    "addr:street":"Avda Teniente Dominguez;Grove Pontevedra",
    "iso:country":"ES",
    "sg:address":"Avda Teniente Dominguez, 84",
    "sg:city":"Grove",
    "sg:orig_category":"Molduras, Junquillos, Listones Y Molduras Perforadas",
    "sg:phone":"+34 986 73 34 47",
    "sg:postcode":"36980",
    "sg:province":"Pontevedra",
    "wof:name":"Hosteleria De Dberto S.l.",
    "wof:placetype":"venue"
},
  "geometry": {"coordinates":[-8.86282444,42.4956588745],"type":"Point"}
}