{
  "type": "Feature",
  "properties": {
    "iso:country":"ES",
    "sg:address":"Rua Doctor Perez Lista, 3",
    "sg:city":"Barco",
    "sg:orig_category":"Ropa Para Se\u00d1oras (al Por Menor)",
    "sg:phone":"+34 988 32 29 75",
    "sg:postcode":"32300",
    "sg:province":"Ourense",
    "wof:name":"Pilardos Moda S.cv",
    "wof:placetype":"venue"
},
  "geometry": {"coordinates":[-6.9813299179,42.4148788452],"type":"Point"}
}