{
  "type": "Feature",
  "properties": {
    "iso:country":"ES",
    "sg:address":"Calle de Posada Herrera, 3",
    "sg:city":"Oviedo",
    "sg:orig_category":"Centros P\u00dablicos De Formaci\u00d3n Profesional Y T\u00c9cnica",
    "sg:phone":"+34 985 22 43 73",
    "sg:postcode":"33002",
    "sg:province":"Asturias",
    "wof:name":"Colegio Oficial De Biologos",
    "wof:placetype":"venue"
},
  "geometry": {"coordinates":[-5.8488249779,43.3637771606],"type":"Point"}
}