{
  "type": "Feature",
  "properties": {
    "addr:full":"Calle de Carlos Marx, 22 Gijon Asturias 33207",
    "addr:housenumber":"22",
    "addr:postcode":"33207",
    "addr:street":"Calle De Carlos Marx",
    "iso:country":"ES",
    "sg:address":"Calle de Carlos Marx, 22",
    "sg:city":"Gijon",
    "sg:orig_category":"M\u00c9dicos: Estomatolog\u00cda",
    "sg:phone":"+34 985 34 28 47",
    "sg:postcode":"33207",
    "sg:province":"Asturias",
    "wof:name":"Alonso Casta\u00f1o Margarita",
    "wof:placetype":"venue"
},
  "geometry": {"coordinates":[-5.6719255447,43.5359764099],"type":"Point"}
}