{
  "type": "Feature",
  "properties": {
    "iso:country":"ES",
    "sg:address":"Carrer de Sant Agusti (de), 19",
    "sg:city":"Tarragona",
    "sg:orig_category":"Caf\u00c9s, Bares, Cervecer\u00cdas",
    "sg:phone":"+34 977 23 69 06",
    "sg:postcode":"43003",
    "sg:province":"Tarragona",
    "wof:name":"Fernandez-rajal Garriga Silvia",
    "wof:placetype":"venue"
},
  "geometry": {"coordinates":[1.2545930147,41.1153678894],"type":"Point"}
}