{
  "type": "Feature",
  "properties": {
    "iso:country":"ES",
    "sg:address":"Carr Cami De Corbins, 23",
    "sg:city":"Lleida",
    "sg:orig_category":"Institutos De Belleza",
    "sg:phone":"+34 973 22 36 58",
    "sg:postcode":"25005",
    "sg:province":"Lleida",
    "wof:name":"Rodriguez Marselles S.l",
    "wof:placetype":"venue"
},
  "geometry": {"coordinates":[0.6346570253,41.6229972839],"type":"Point"}
}