{
  "type": "Feature",
  "properties": {
    "iso:country":"ES",
    "sg:address":"Ctra Zorrotza-kastrexana, 4",
    "sg:city":"Bilbao",
    "sg:orig_category":"Florister\u00cdas",
    "sg:phone":"+34 944 27 03 70",
    "sg:postcode":"48013",
    "sg:province":"Vizcaya",
    "wof:name":"Ana Isabel Montero Prieto (floristeria Omega)",
    "wof:placetype":"venue"
},
  "geometry": {"coordinates":[-2.9715816975,43.2759246826],"type":"Point"}
}