{
  "type": "Feature",
  "properties": {
    "addr:full":"Carrer de Vallparadis, 53 Terrassa Barcelona 08222",
    "addr:housenumber":"53",
    "addr:postcode":"08222",
    "addr:street":"Carrer De Vallparadis",
    "iso:country":"ES",
    "sg:address":"Carrer de Vallparadis, 53",
    "sg:city":"Terrassa",
    "sg:orig_category":"Empresas De Carpinter\u00cda De Madera",
    "sg:phone":"+34 937 83 93 15",
    "sg:postcode":"08222",
    "sg:province":"Barcelona",
    "wof:name":"Garcia Pastor Jose",
    "wof:placetype":"venue"
},
  "geometry": {"coordinates":[2.0209400654,41.5643196106],"type":"Point"}
}