{
  "type": "Feature",
  "properties": {
    "iso:country":"ES",
    "sg:address":"Calle de Real, S/n",
    "sg:city":"Malaha",
    "sg:orig_category":"Iglesia Cat\u00d3lica",
    "sg:phone":"+34 958 58 71 12",
    "sg:postcode":"18130",
    "sg:province":"Granada",
    "wof:name":"Parroquia La Inmaculada",
    "wof:placetype":"venue"
},
  "geometry": {"coordinates":[-3.7220740318,37.1019706726],"type":"Point"}
}