{
  "type": "Feature",
  "properties": {
    "addr:full":"Calle de Angosta, 3 Arevalillo De Cega Segovia 40185",
    "addr:housenumber":"3",
    "addr:postcode":"40185",
    "addr:street":"Calle De Angosta",
    "iso:country":"ES",
    "sg:address":"Calle de Angosta, 3",
    "sg:city":"Arevalillo De Cega",
    "sg:orig_category":"Plomeros",
    "sg:phone":"+34 921 50 02 37",
    "sg:postcode":"40185",
    "sg:province":"Segovia",
    "wof:name":"San Faustino Blanco Antonio",
    "wof:placetype":"venue"
},
  "geometry": {"coordinates":[-3.8907470703,41.1616325378],"type":"Point"}
}