{
  "type": "Feature",
  "properties": {
    "iso:country":"ES",
    "sg:address":"Carrer de Circumval.lacio, 13",
    "sg:city":"Manresa",
    "sg:orig_category":"Ropa Para Se\u00d1oras Y Caballeros (al Por Menor)",
    "sg:phone":"+34 938 73 43 26",
    "sg:postcode":"08241",
    "sg:province":"Barcelona",
    "wof:name":"Hobbs  Christobelle",
    "wof:placetype":"venue"
},
  "geometry": {"coordinates":[1.8249850273,41.7280464172],"type":"Point"}
}