{
  "type": "Feature",
  "properties": {
    "addr:full":"Calle de Isaac Peral, 50 Madrid Madrid 28040",
    "addr:housenumber":"50",
    "addr:postcode":"madrid;28040",
    "addr:street":"Calle De Isaac Peral",
    "iso:country":"ES",
    "sg:address":"Calle de Isaac Peral, 50",
    "sg:city":"Madrid",
    "sg:orig_category":"Abogados",
    "sg:phone":"+34 915 44 05 60",
    "sg:postcode":"28040",
    "sg:province":"Madrid",
    "wof:name":"Fernandez Lude\u00f1a Jose Maria",
    "wof:placetype":"venue"
},
  "geometry": {"coordinates":[-3.7175428867,40.4396743774],"type":"Point"}
}