{
  "type": "Feature",
  "properties": {
    "iso:country":"ES",
    "sg:address":"Calle de San Alejandro, 107",
    "sg:city":"Pto Real",
    "sg:orig_category":"Comercio, Reparaci\u00d3n De Motocicletas, Bicicletas Y Piezas Sueltas",
    "sg:phone":"+34 956 83 45 05",
    "sg:postcode":"11510",
    "sg:province":"C\u00e1diz",
    "wof:name":"Barea Chacon Carlos",
    "wof:placetype":"venue"
},
  "geometry": {"coordinates":[-6.1934738159,36.5327224731],"type":"Point"}
}