{
  "type": "Feature",
  "properties": {
    "iso:country":"ES",
    "sg:address":"Rond San Francisco (de), 46",
    "sg:city":"Lucena",
    "sg:orig_category":"Comercio De Mobiliario De Oficina",
    "sg:phone":"+34 957 51 33 89",
    "sg:postcode":"14900",
    "sg:province":"C\u00f3rdoba",
    "wof:name":"Osuna Egea Rafael",
    "wof:placetype":"venue"
},
  "geometry": {"coordinates":[-4.4869098663,37.413192749],"type":"Point"}
}