{
  "type": "Feature",
  "properties": {
    "addr:full":"Amillaga Kalea, 31 Bergara Guip\u00f9zcoa 20570",
    "addr:housenumber":"31",
    "addr:postcode":"20570",
    "addr:street":"Amillaga Kalea;Guipu\u0300Zcoa",
    "iso:country":"ES",
    "sg:address":"Amillaga Kalea, 31",
    "sg:city":"Bergara",
    "sg:orig_category":"Reparaci\u00d3n, Mantenimiento De Calefacciones",
    "sg:phone":"+34 943 76 15 35",
    "sg:postcode":"20570",
    "sg:province":"Guip\u00f9zcoa",
    "wof:name":"Rene Gomez S.l.",
    "wof:placetype":"venue"
},
  "geometry": {"coordinates":[-2.4217040539,43.1278915405],"type":"Point"}
}