{
  "type": "Feature",
  "properties": {
    "addr:full":"Avda Saavedra Meneses, 25 Ares La Coru\u00f1a 15624",
    "addr:housenumber":"25",
    "addr:postcode":"15624",
    "addr:street":"Avda Saavedra Meneses;La Corun\u0303A",
    "iso:country":"ES",
    "sg:address":"Avda Saavedra Meneses, 25",
    "sg:city":"Ares",
    "sg:orig_category":"\u00d3ptica: Instrumentos (fabricaci\u00d3n)",
    "sg:phone":"+34 981 46 86 27",
    "sg:postcode":"15624",
    "sg:province":"La Coru\u00f1a",
    "wof:name":"Opticas Noroeste S.l.",
    "wof:placetype":"venue"
},
  "geometry": {"coordinates":[-8.2420473099,43.4275932312],"type":"Point"}
}