{
  "type": "Feature",
  "properties": {
    "iso:country":"ES",
    "sg:address":"Cno. Muntanya, 406",
    "sg:city":"Espillari",
    "sg:orig_category":"Fabricaci\u00d3n, Importaci\u00d3n De Material Y Sistemas De Telecomunicaciones",
    "sg:phone":"+34 971 26 49 33",
    "sg:postcode":"07608",
    "sg:province":"Islas Baleares",
    "wof:name":"Vidal Lara Bernardo",
    "wof:placetype":"venue"
},
  "geometry": {"coordinates":[2.7551910877,39.5277099609],"type":"Point"}
}