{
  "type": "Feature",
  "properties": {
    "addr:full":"Avgd Caritg, S/n Badalona Barcelona 08911",
    "addr:housenumber":"s / n",
    "addr:postcode":"08911",
    "iso:country":"ES",
    "sg:address":"Avgd Caritg, S/n",
    "sg:city":"Badalona",
    "sg:orig_category":"Distribuci\u00d3n De Petr\u00d3leo Y Derivados",
    "sg:phone":"+34 933 88 95 03",
    "sg:postcode":"08911",
    "sg:province":"Barcelona",
    "wof:name":"Markoil S. A.",
    "wof:placetype":"venue"
},
  "geometry": {"coordinates":[2.2450649738,41.4503440857],"type":"Point"}
}