{
  "type": "Feature",
  "properties": {
    "iso:country":"ES",
    "sg:address":"Calle de Granada, 49",
    "sg:city":"Palmas De Gran Canaria",
    "sg:orig_category":"Tapiceros Y Tapiceros",
    "sg:phone":"+34 928 31 94 74",
    "sg:postcode":"35016",
    "sg:province":"Las Palmas",
    "wof:name":"Perez Suarez Arturo",
    "wof:placetype":"venue"
},
  "geometry": {"coordinates":[-15.4294595718,28.0664253235],"type":"Point"}
}