{
  "type": "Feature",
  "properties": {
    "iso:country":"ES",
    "sg:address":"Avda Juan Carlos I, 3",
    "sg:city":"Carolina",
    "sg:orig_category":"Zapatos (al Por Menor)",
    "sg:phone":"+34 953 66 21 46",
    "sg:postcode":"23200",
    "sg:province":"Ja\u00e9n",
    "wof:name":"Martinez Martinez Domingo",
    "wof:placetype":"venue"
},
  "geometry": {"coordinates":[-3.614577055,38.2733306885],"type":"Point"}
}