{
  "type": "Feature",
  "properties": {
    "iso:country":"ES",
    "sg:address":"Pl Caserna, 4",
    "sg:city":"Granollers",
    "sg:orig_category":"Reposter\u00cdas",
    "sg:phone":"+34 938 79 59 73",
    "sg:postcode":"08401",
    "sg:province":"Barcelona",
    "wof:name":"El Fornet De Sant Carles Sccl",
    "wof:placetype":"venue"
},
  "geometry": {"coordinates":[2.2860100269,41.6089935303],"type":"Point"}
}