{
  "type": "Feature",
  "properties": {
    "iso:country":"ES",
    "sg:address":"Joaquin Sorolla, 120",
    "sg:city":"Rivas Vaciamadrid",
    "sg:orig_category":"Art\u00cdculos De Decoraci\u00d3n",
    "sg:phone":"+34 914 99 04 81",
    "sg:postcode":"28529",
    "sg:province":"Madrid",
    "sg:website":"www.donotello.es",
    "wof:name":"Nedotti S.l.",
    "wof:placetype":"venue"
},
  "geometry": {"coordinates":[-3.5321679115,40.3464241028],"type":"Point"}
}