{
  "type": "Feature",
  "properties": {
    "iso:country":"ES",
    "sg:address":"Cno. Vell Bunyola, S/n",
    "sg:city":"Pol.ind.son Castello",
    "sg:orig_category":"Empresas De Carpinter\u00cda De Madera",
    "sg:phone":"+34 971 43 04 05",
    "sg:postcode":"07009",
    "sg:province":"Islas Baleares",
    "wof:name":"Vasco Perez Francisco",
    "wof:placetype":"venue"
},
  "geometry": {"coordinates":[2.6776249409,39.6072845459],"type":"Point"}
}