{
  "type": "Feature",
  "properties": {
    "iso:country":"ES",
    "sg:address":"Pol. Ind. Fuensanta, S/n",
    "sg:city":"Mostoles",
    "sg:orig_category":"Estudios, Instalaci\u00d3n De Climatizaci\u00d3n",
    "sg:phone":"+34 916 45 00 33",
    "sg:postcode":"28936",
    "sg:province":"Madrid",
    "wof:name":"Koolair S. A.",
    "wof:placetype":"venue"
},
  "geometry": {"coordinates":[-3.8649389744,40.3230667114],"type":"Point"}
}