{
  "type": "Feature",
  "properties": {
    "addr:full":"Calle de Cristobal Colon, 38 Utrera Sevilla 41710",
    "addr:housenumber":"38",
    "addr:postcode":"41710",
    "addr:street":"Calle De Cristobal Colon",
    "iso:country":"ES",
    "sg:address":"Calle de Cristobal Colon, 38",
    "sg:city":"Utrera",
    "sg:orig_category":"Cajas De Ahorro",
    "sg:phone":"+34 954 87 35 34",
    "sg:postcode":"41710",
    "sg:province":"Sevilla",
    "wof:name":"Caixa D'estalvis I Pensions De Barcelona",
    "wof:placetype":"venue"
},
  "geometry": {"coordinates":[-5.7765607834,37.1839904785],"type":"Point"}
}