{
  "type": "Feature",
  "properties": {
    "addr:full":"Carrer de Roger De Flor, 2 Granollers Barcelona 08401",
    "addr:housenumber":"2",
    "addr:postcode":"08401",
    "addr:street":"Carrer De Roger De Flor",
    "iso:country":"ES",
    "sg:address":"Carrer de Roger De Flor, 2",
    "sg:city":"Granollers",
    "sg:orig_category":"M\u00c9dicos: Medicina General",
    "sg:phone":"+34 938 70 31 47",
    "sg:postcode":"08401",
    "sg:province":"Barcelona",
    "wof:name":"Vaisman Sluvis Felix",
    "wof:placetype":"venue"
},
  "geometry": {"coordinates":[2.2833840847,41.6104927063],"type":"Point"}
}