{
  "type": "Feature",
  "properties": {
    "iso:country":"ES",
    "sg:address":"Los Santos, 19",
    "sg:city":"Miguelturra",
    "sg:orig_category":"Negocio De Materiales De Construcci\u00d3n",
    "sg:phone":"+34 926 24 10 46",
    "sg:postcode":"13170",
    "sg:province":"Ciudad Real",
    "wof:name":"Sanchez Mu\u00f1oz Antonio Dionisio",
    "wof:placetype":"venue"
},
  "geometry": {"coordinates":[-3.8883891106,38.9583930969],"type":"Point"}
}