{
  "type": "Feature",
  "properties": {
    "iso:country":"ES",
    "sg:address":"Sant Domenech, 16",
    "sg:city":"Arnes",
    "sg:orig_category":"Renovaci\u00d3n Inmobiliaria",
    "sg:phone":"+34 977 43 56 88",
    "sg:postcode":"43597",
    "sg:province":"Tarragona",
    "wof:name":"Construccions Sabate S.cooperativa",
    "wof:placetype":"venue"
},
  "geometry": {"coordinates":[0.2613869905,40.9112205505],"type":"Point"}
}