{
  "type": "Feature",
  "properties": {
    "addr:full":"Calle de Feria, 110 Sevilla Sevilla 41002",
    "addr:housenumber":"110",
    "addr:postcode":"41002",
    "addr:street":"Calle De Feria",
    "iso:country":"ES",
    "sg:address":"Calle de Feria, 110",
    "sg:city":"Sevilla",
    "sg:orig_category":"Librer\u00cdas",
    "sg:phone":"+34 954 90 13 21",
    "sg:postcode":"41002",
    "sg:province":"Sevilla",
    "wof:name":"Alcaide Rico Esperanza",
    "wof:placetype":"venue"
},
  "geometry": {"coordinates":[-5.991736412,37.4000396729],"type":"Point"}
}