{
  "type": "Feature",
  "properties": {
    "addr:full":"Av Alacant, 74 Elche Alicante 03203",
    "addr:housenumber":"74",
    "addr:postcode":"03203",
    "addr:street":"Alacant",
    "iso:country":"ES",
    "sg:address":"Av Alacant, 74",
    "sg:city":"Elche",
    "sg:orig_category":"Mec\u00c1nico Del Autom\u00d3vil",
    "sg:phone":"+34 966 61 51 70",
    "sg:postcode":"03203",
    "sg:province":"Alicante",
    "wof:name":"Sobejano Servicios S.l.",
    "wof:placetype":"venue"
},
  "geometry": {"coordinates":[-0.6819949746,38.269569397],"type":"Point"}
}