{
  "type": "Feature",
  "properties": {
    "addr:full":"Calle de Manresa, 60 Madrid Madrid 28034",
    "addr:housenumber":"60",
    "addr:postcode":"madrid;28034",
    "addr:street":"Calle De Manresa",
    "iso:country":"ES",
    "sg:address":"Calle de Manresa, 60",
    "sg:city":"Madrid",
    "sg:orig_category":"Iglesia Cat\u00d3lica",
    "sg:phone":"+34 917 34 87 04",
    "sg:postcode":"28034",
    "sg:province":"Madrid",
    "wof:name":"Parroquia Virgen Del Refugio",
    "wof:placetype":"venue"
},
  "geometry": {"coordinates":[-3.6908240318,40.4919281006],"type":"Point"}
}