{
  "type": "Feature",
  "properties": {
    "addr:full":"Carr Torner, 5 Badalona Barcelona 08912",
    "addr:housenumber":"5",
    "addr:postcode":"08912",
    "addr:street":"Carr Torner",
    "iso:country":"ES",
    "sg:address":"Carr Torner, 5",
    "sg:city":"Badalona",
    "sg:orig_category":"Supermercados Y Hipermercados",
    "sg:phone":"+34 934 61 07 70",
    "sg:postcode":"08912",
    "sg:province":"Barcelona",
    "wof:name":"Cipres Piqueras S.l.",
    "wof:placetype":"venue"
},
  "geometry": {"coordinates":[2.241574049,41.4446563721],"type":"Point"}
}