{
  "type": "Feature",
  "properties": {
    "addr:full":"Av Catalunya, 94 Casc Antic Barcelona 08150",
    "addr:housenumber":"94",
    "addr:postcode":"08150",
    "addr:street":"Av Catalunya",
    "iso:country":"ES",
    "sg:address":"Av Catalunya, 94",
    "sg:city":"Casc Antic",
    "sg:orig_category":"Carnicer\u00cdas, Carnicer\u00cdas",
    "sg:phone":"+34 935 73 03 28",
    "sg:postcode":"08150",
    "sg:province":"Barcelona",
    "wof:name":"Lopez Vega David",
    "wof:placetype":"venue"
},
  "geometry": {"coordinates":[2.2293000221,41.5678787231],"type":"Point"}
}