{
  "type": "Feature",
  "properties": {
    "iso:country":"ES",
    "sg:address":"Calle de Jardintxikerra, 4",
    "sg:city":"Bilbao",
    "sg:orig_category":"Agencias Y Agentes Comerciales, Representantes",
    "sg:phone":"+34 944 27 37 22",
    "sg:postcode":"48012",
    "sg:province":"Vizcaya",
    "wof:name":"Saenz Alvarez Javier",
    "wof:placetype":"venue"
},
  "geometry": {"coordinates":[-2.9451739788,43.2551956177],"type":"Point"}
}