{
  "type": "Feature",
  "properties": {
    "iso:country":"ES",
    "sg:address":"Calle de San Juan De Avila, 11",
    "sg:city":"Almodovar Campo",
    "sg:orig_category":"Talleres: Ropa A Medida",
    "sg:phone":"+34 926 48 30 56",
    "sg:postcode":"13580",
    "sg:province":"Ciudad Real",
    "wof:name":"Lopez Lara Jacinto",
    "wof:placetype":"venue"
},
  "geometry": {"coordinates":[-4.178940773,38.7098503113],"type":"Point"}
}