{
  "type": "Feature",
  "properties": {
    "iso:country":"ES",
    "sg:address":"Pl Gal.la Placidia, 11",
    "sg:city":"Barcelona",
    "sg:orig_category":"M\u00c9dicos: Estomatolog\u00cda",
    "sg:phone":"+34 932 18 36 47",
    "sg:postcode":"08006",
    "sg:province":"Barcelona",
    "wof:name":"Vicens Hernandez Eduardo",
    "wof:placetype":"venue"
},
  "geometry": {"coordinates":[2.1526129246,41.3989448547],"type":"Point"}
}