{
  "type": "Feature",
  "properties": {
    "addr:full":"Cm\u00d1o Curras, 5 Curras Pontevedra 36206",
    "addr:housenumber":"5",
    "addr:postcode":"36206",
    "addr:street":"Curras",
    "iso:country":"ES",
    "sg:address":"Cm\u00d1o Curras, 5",
    "sg:city":"Curras",
    "sg:orig_category":"Alimentaci\u00d3n General (al Por Menor)",
    "sg:phone":"+34 986 27 10 03",
    "sg:postcode":"36206",
    "sg:province":"Pontevedra",
    "wof:name":"Salgado Fernandez Maria Del Carmen",
    "wof:placetype":"venue"
},
  "geometry": {"coordinates":[-8.6592998505,42.5835418701],"type":"Point"}
}