{
  "type": "Feature",
  "properties": {
    "iso:country":"ES",
    "sg:address":"Carr Ferrer I Busquets, 8",
    "sg:city":"Mollerussa",
    "sg:orig_category":"Peluqueros: De Se\u00d1oras",
    "sg:phone":"+34 973 60 18 05",
    "sg:postcode":"25230",
    "sg:province":"Lleida",
    "wof:name":"Peluqueria Paquita S.c.p.",
    "wof:placetype":"venue"
},
  "geometry": {"coordinates":[0.8924800158,41.6300086975],"type":"Point"}
}