{
  "type": "Feature",
  "properties": {
    "iso:country":"ES",
    "sg:address":"Calle de Serrablo (de), 76",
    "sg:city":"Sabi\u00f1anigo",
    "sg:orig_category":"Librer\u00cdas",
    "sg:phone":"+34 974 48 02 71",
    "sg:postcode":"22600",
    "sg:province":"Huesca",
    "wof:name":"Pueyo Navarro Francisco Javier",
    "wof:placetype":"venue"
},
  "geometry": {"coordinates":[-0.366317004,42.5181007385],"type":"Point"}
}