{
  "type": "Feature",
  "properties": {
    "addr:full":"Poligono Ind. Vincios, S/n Vincios Pontevedra 36316",
    "addr:housenumber":"s",
    "addr:postcode":"36316",
    "addr:street":"Poligono Ind. Vincios;/ N",
    "iso:country":"ES",
    "sg:address":"Poligono Ind. Vincios, S/n",
    "sg:city":"Vincios",
    "sg:orig_category":"M\u00c1rmoles, Granitos Y Piedras Naturales",
    "sg:phone":"+34 986 46 99 83",
    "sg:postcode":"36316",
    "sg:province":"Pontevedra",
    "wof:name":"Granitos Y Canteras Mi\u00d1or S.a.",
    "wof:placetype":"venue"
},
  "geometry": {"coordinates":[-8.7297039032,42.1394195557],"type":"Point"}
}