{
  "type": "Feature",
  "properties": {
    "iso:country":"ES",
    "sg:address":"Plaz Zaragoza, 3",
    "sg:city":"Monzon",
    "sg:classifiers":[
        {
            "category":"Autos & Motor Vehicles",
            "subcategory":"Automobile Sales",
            "type":"Retail Goods"
        }
    ],
    "sg:phone":"+34 974 40 39 09",
    "sg:postcode":"22400",
    "sg:province":"Huesca",
    "wof:name":"Auto Escuela Monzon 2000 S.l.",
    "wof:placetype":"venue"
},
  "geometry": {"coordinates":[0.1945448071,41.9165077209],"type":"Point"}
}