{
  "type": "Feature",
  "properties": {
    "iso:country":"ES",
    "sg:address":"Calle de San Juan, 60",
    "sg:city":"Molina Segura",
    "sg:orig_category":"Bancos",
    "sg:phone":"+34 968 64 60 31",
    "sg:postcode":"30500",
    "sg:province":"Murcia",
    "sg:website":"www.bancodevalencia.es",
    "wof:name":"Banco De Valencia S.a.",
    "wof:placetype":"venue"
},
  "geometry": {"coordinates":[-1.2100889683,38.0564918518],"type":"Point"}
}