{
  "type": "Feature",
  "properties": {
    "addr:full":"Calle de San Agustin, 2 Le\u00f3n Le\u00f3n 24001",
    "addr:housenumber":"2",
    "addr:postcode":"24001",
    "addr:street":"Calle De San Agustin;Leo\u0301N",
    "iso:country":"ES",
    "sg:address":"Calle de San Agustin, 2",
    "sg:city":"Le\u00f3n",
    "sg:orig_category":"Centros Comerciales Y Grandes Tiendas",
    "sg:phone":"+34 987 24 58 15",
    "sg:postcode":"24001",
    "sg:province":"Le\u00f3n",
    "wof:name":"Alonso Martinez Luis Miguel",
    "wof:placetype":"venue"
},
  "geometry": {"coordinates":[-5.574637413,42.5985870361],"type":"Point"}
}