{
  "type": "Feature",
  "properties": {
    "iso:country":"ES",
    "sg:address":"Calle de Aeronave, 10",
    "sg:city":"Madrid",
    "sg:orig_category":"Promotores Constructores",
    "sg:phone":"+34 913 29 43 09",
    "sg:postcode":"28042",
    "sg:province":"Madrid",
    "wof:name":"Gordillo Dominguez Manuel",
    "wof:placetype":"venue"
},
  "geometry": {"coordinates":[-3.586391449,40.4698448181],"type":"Point"}
}