{
  "type": "Feature",
  "properties": {
    "addr:full":"Calle de Delicias, 37 Madrid Madrid 28045",
    "addr:housenumber":"37",
    "addr:postcode":"madrid;28045",
    "addr:street":"Calle De Delicias",
    "iso:country":"ES",
    "sg:address":"Calle de Delicias, 37",
    "sg:city":"Madrid",
    "sg:orig_category":"Administradores De Bienes Y Delegados De Comunidades De Propietarios",
    "sg:phone":"+34 915 39 81 87",
    "sg:postcode":"28045",
    "sg:province":"Madrid",
    "wof:name":"Fincasen Gestion Sl",
    "wof:placetype":"venue"
},
  "geometry": {"coordinates":[-3.6912600994,40.4040031433],"type":"Point"}
}