{
  "type": "Feature",
  "properties": {
    "addr:full":"Praz Concello, 18 Santa Uxia De Ribeira La Coru\u00f1a 15960",
    "addr:housenumber":"18",
    "addr:postcode":"15960",
    "addr:street":"Concello;Corun\u0303A",
    "iso:country":"ES",
    "sg:address":"Praz Concello, 18",
    "sg:city":"Santa Uxia De Ribeira",
    "sg:orig_category":"Servicios De Telecomunicaciones",
    "sg:phone":"+34 981 87 40 74",
    "sg:postcode":"15960",
    "sg:province":"La Coru\u00f1a",
    "wof:name":"Otero Insua Amador",
    "wof:placetype":"venue"
},
  "geometry": {"coordinates":[-8.9925737381,42.555355072],"type":"Point"}
}