{
  "type": "Feature",
  "properties": {
    "iso:country":"ES",
    "sg:address":"Pol Industrial, S/n",
    "sg:city":"Calasparra",
    "sg:orig_category":"Empresas De Carpinter\u00cda Met\u00c1lica",
    "sg:phone":"+34 968 74 62 15",
    "sg:postcode":"30420",
    "sg:province":"Murcia",
    "wof:name":"Jose Sanchez Garcia Y Otros C.b.",
    "wof:placetype":"venue"
},
  "geometry": {"coordinates":[-1.6999490261,38.2315101624],"type":"Point"}
}