{
  "type": "Feature",
  "properties": {
    "addr:full":"Calle de Mejico (de), 1 Fuenlabrada Madrid 28945",
    "addr:housenumber":"1",
    "addr:postcode":"28945",
    "addr:street":"Calle De Mejico De",
    "iso:country":"ES",
    "sg:address":"Calle de Mejico (de), 1",
    "sg:city":"Fuenlabrada",
    "sg:orig_category":"Producci\u00d3n, Venta De Productos De Agricultura Biol\u00d3gica",
    "sg:phone":"+34 914 92 00 50",
    "sg:postcode":"28945",
    "sg:province":"Madrid",
    "sg:website":"www.tabacodominicano.com",
    "wof:name":"Mapfre Servicios De Informatica S.a.",
    "wof:placetype":"venue"
},
  "geometry": {"coordinates":[-3.7890589237,40.2941360474],"type":"Point"}
}