{
  "type": "Feature",
  "properties": {
    "addr:full":"Calle de Pablo Iglesias, 8 Palomares Rio Sevilla 41928",
    "addr:housenumber":"8",
    "addr:postcode":"41928",
    "addr:street":"Calle De Pablo Iglesias;Rio Sevilla",
    "iso:country":"ES",
    "sg:address":"Calle de Pablo Iglesias, 8",
    "sg:city":"Palomares Rio",
    "sg:orig_category":"Ingenier\u00cda, Centros De Estudios (diversos)",
    "sg:phone":"+34 955 76 40 67",
    "sg:postcode":"41928",
    "sg:province":"Sevilla",
    "wof:name":"Ingenieria Y Control De Obras S. L.",
    "wof:placetype":"venue"
},
  "geometry": {"coordinates":[-6.0670619011,37.3225402832],"type":"Point"}
}