{
  "type": "Feature",
  "properties": {
    "iso:country":"ES",
    "sg:address":"Calle de Saponaria, 1",
    "sg:city":"Almeria",
    "sg:orig_category":"Plomeros",
    "sg:phone":"+34 950 25 28 14",
    "sg:postcode":"04005",
    "sg:province":"Almer\u00eda",
    "wof:name":"Diaz Hernandez Antonio",
    "wof:placetype":"venue"
},
  "geometry": {"coordinates":[-2.4564390182,36.8463249207],"type":"Point"}
}