{
  "type": "Feature",
  "properties": {
    "iso:country":"ES",
    "sg:address":"Pase Carolinas, S/n",
    "sg:city":"Santa Uxia De Ribeira",
    "sg:orig_category":"Vinos Y Licores (venta Al Por Menor)",
    "sg:phone":"+34 981 87 45 11",
    "sg:postcode":"15960",
    "sg:province":"A Coru\u00f1a",
    "wof:name":"Tucho Sampedro",
    "wof:placetype":"venue"
},
  "geometry": {"coordinates":[-8.9908485413,42.5553665161],"type":"Point"}
}