{
  "type": "Feature",
  "properties": {
    "iso:country":"ES",
    "sg:address":"Calle de Guipuzcoa, 16",
    "sg:city":"Gijon",
    "sg:orig_category":"Aparcamientos (infraestructuras, Accesorios)",
    "sg:phone":"+34 985 16 40 64",
    "sg:postcode":"33210",
    "sg:province":"Asturias",
    "wof:name":"Fernandez Lopez Arsenio",
    "wof:placetype":"venue"
},
  "geometry": {"coordinates":[-5.6729693413,43.5252990723],"type":"Point"}
}