{
  "type": "Feature",
  "properties": {
    "addr:full":"Edisson (p I Jose Martin Mendez), 18 Estepona M\u00e1laga 29680",
    "addr:housenumber":"18",
    "addr:postcode":"29680",
    "addr:street":"Edisson;Mendez",
    "iso:country":"ES",
    "sg:address":"Edisson (p I Jose Martin Mendez), 18",
    "sg:city":"Estepona",
    "sg:orig_category":"Empresas De Carpinter\u00cda",
    "sg:phone":"+34 952 80 28 43",
    "sg:postcode":"29680",
    "sg:province":"M\u00e1laga",
    "wof:name":"Absolute Windows S.l.",
    "wof:placetype":"venue"
},
  "geometry": {"coordinates":[-5.17449,36.443512],"type":"Point"}
}