{
  "type": "Feature",
  "properties": {
    "iso:country":"ES",
    "sg:address":"Rua San Clemente (de), 6",
    "sg:city":"Santiago De Compostela",
    "sg:orig_category":"Restaurantes",
    "sg:phone":"+34 981 56 54 26",
    "sg:postcode":"15705",
    "sg:province":"La Coru\u00f1a",
    "wof:name":"Restaurante San Clemente S. L.",
    "wof:placetype":"venue"
},
  "geometry": {"coordinates":[-8.5469169617,42.8791389465],"type":"Point"}
}