{
  "type": "Feature",
  "properties": {
    "addr:full":"Escuelas, S/n Pradanos De Ojeda Palencia 34487",
    "addr:housenumber":"s",
    "addr:postcode":"34487",
    "addr:street":"Escuelas;/ N",
    "iso:country":"ES",
    "sg:address":"Escuelas, S/n",
    "sg:city":"Pradanos De Ojeda",
    "sg:orig_category":"Iglesia Cat\u00d3lica",
    "sg:phone":"+34 979 13 32 08",
    "sg:postcode":"34487",
    "sg:province":"Palencia",
    "wof:name":"Parroquia De Pradanos De Ojeda",
    "wof:placetype":"venue"
},
  "geometry": {"coordinates":[-97.78224945069999,45.7040786743],"type":"Point"}
}