{
  "type": "Feature",
  "properties": {
    "iso:country":"ES",
    "sg:address":"Avda San Sebastian, 51",
    "sg:city":"Santa Cruz De Tenerife",
    "sg:orig_category":"Tiendas De Grano, Frutas Y Legumbres Secas (al Por Menor)",
    "sg:phone":"+34 922 21 56 16",
    "sg:postcode":"38003",
    "sg:province":"Santa Cruz De Tenerife",
    "wof:name":"Casa Ricardo S.a.",
    "wof:placetype":"venue"
},
  "geometry": {"coordinates":[-16.3326644897,28.4846744537],"type":"Point"}
}