{
  "type": "Feature",
  "properties": {
    "addr:full":"Av Antoni Gaudi, 59 S. Quirze Valles Barcelona 08192",
    "addr:housenumber":"59",
    "addr:postcode":"08192",
    "addr:street":"Av Antoni Gaudi",
    "iso:country":"ES",
    "sg:address":"Av Antoni Gaudi, 59",
    "sg:city":"S. Quirze Valles",
    "sg:orig_category":"Farmacias",
    "sg:phone":"+34 937 21 39 33",
    "sg:postcode":"08192",
    "sg:province":"Barcelona",
    "wof:name":"Oliveras Masana Maria Angeles",
    "wof:placetype":"venue"
},
  "geometry": {"coordinates":[2.0770950317,41.535243988],"type":"Point"}
}