{
  "type": "Feature",
  "properties": {
    "iso:country":"ES",
    "sg:address":"Calle de Victor Pe\u00d1asco (don), 6",
    "sg:city":"Tomelloso",
    "sg:orig_category":"Heladeros",
    "sg:phone":"+34 926 51 07 82",
    "sg:postcode":"13700",
    "sg:province":"Ciudad Real",
    "wof:name":"Cremades Monerris Ana",
    "wof:placetype":"venue"
},
  "geometry": {"coordinates":[-3.0238559246,39.1515426636],"type":"Point"}
}