{
  "type": "Feature",
  "properties": {
    "addr:full":"Av Can Nicolau, S/n Cunit Tarragona 43881",
    "addr:housenumber":"/ n",
    "addr:postcode":"43881",
    "addr:street":"Av Can;S",
    "iso:country":"ES",
    "sg:address":"Av Can Nicolau, S/n",
    "sg:city":"Cunit",
    "sg:orig_category":"Urbanistas",
    "sg:phone":"+34 977 67 26 29",
    "sg:postcode":"43881",
    "sg:province":"Tarragona",
    "wof:name":"Area Residencial Cunit S. A.",
    "wof:placetype":"venue"
},
  "geometry": {"coordinates":[1.6200997829,41.196056366],"type":"Point"}
}