{
  "type": "Feature",
  "properties": {
    "iso:country":"ES",
    "sg:address":"Calle de Embajadores, 116",
    "sg:city":"Madrid",
    "sg:orig_category":"Peluqueros: De Se\u00d1oras",
    "sg:phone":"+34 914 74 98 22",
    "sg:postcode":"28045",
    "sg:province":"Madrid",
    "wof:name":"Marchese Turrero Maria Del Carmen",
    "wof:placetype":"venue"
},
  "geometry": {"coordinates":[-3.6987569332,40.3997955322],"type":"Point"}
}