{
  "type": "Feature",
  "properties": {
    "iso:country":"ES",
    "sg:address":"Calle de Bolivia, 26",
    "sg:city":"Caceres",
    "sg:orig_category":"Cr\u00cda De Animales",
    "sg:phone":"+34 927 21 03 63",
    "sg:postcode":"10005",
    "sg:province":"C\u00e1ceres",
    "wof:name":"Polo Picapiedra Benito",
    "wof:placetype":"venue"
},
  "geometry": {"coordinates":[-6.3734135628,39.4594802856],"type":"Point"}
}