{
  "type": "Feature",
  "properties": {
    "iso:country":"ES",
    "sg:address":"Carrer de Francesc Macia, 15",
    "sg:city":"Garriga",
    "sg:orig_category":"Comercio De Piezas De Recambio Y De Accesorios De Veh\u00cdculos, Veh\u00cdculos Industriales",
    "sg:phone":"+34 938 71 76 67",
    "sg:postcode":"08530",
    "sg:province":"Barcelona",
    "wof:name":"Gwr S.a.",
    "wof:placetype":"venue"
},
  "geometry": {"coordinates":[2.2818510532,41.6740112305],"type":"Point"}
}