{
  "type": "Feature",
  "properties": {
    "iso:country":"ES",
    "sg:address":"Calle de Avenida De La Estacion, 27",
    "sg:city":"Cintruenigo",
    "sg:orig_category":"Florister\u00cdas",
    "sg:phone":"+34 948 81 18 49",
    "sg:postcode":"31592",
    "sg:province":"Navarra",
    "wof:name":"Carbones Y Le\u00f1as Perla S. L.",
    "wof:placetype":"venue"
},
  "geometry": {"coordinates":[-1.8035886288,42.0813522339],"type":"Point"}
}