{
  "type": "Feature",
  "properties": {
    "iso:country":"ES",
    "sg:address":"Av Montblanc, 212",
    "sg:city":"Reus",
    "sg:orig_category":"Embalajes",
    "sg:phone":"+34 977 34 18 54",
    "sg:postcode":"43206",
    "sg:province":"Tarragona",
    "wof:name":"Covepal S.l.",
    "wof:placetype":"venue"
},
  "geometry": {"coordinates":[1.1219400167,41.1646156311],"type":"Point"}
}