{
  "type": "Feature",
  "properties": {
    "addr:full":"Calle de Luis Sauquillo, 73 Fuenlabrada Madrid 28944",
    "addr:housenumber":"73",
    "addr:postcode":"28944",
    "addr:street":"Calle De Luis Sauquillo",
    "iso:country":"ES",
    "sg:address":"Calle de Luis Sauquillo, 73",
    "sg:city":"Fuenlabrada",
    "sg:orig_category":"Molduras, Junquillos, Listones Y Molduras Perforadas",
    "sg:phone":"+34 916 97 86 18",
    "sg:postcode":"28944",
    "sg:province":"Madrid",
    "wof:name":"Pinel Calvo Pablo Manuel",
    "wof:placetype":"venue"
},
  "geometry": {"coordinates":[-3.7984549999,40.2807884216],"type":"Point"}
}