{
  "type": "Feature",
  "properties": {
    "iso:country":"ES",
    "sg:address":"Av Alemanya, 3",
    "sg:city":"Palma",
    "sg:orig_category":"M\u00c9dicos: Cardiolog\u00cda Y Afecciones Cardiovasculares",
    "sg:phone":"+34 971 72 26 80",
    "sg:postcode":"07003",
    "sg:province":"Islas Baleares",
    "wof:name":"Orellana Mas Jorge",
    "wof:placetype":"venue"
},
  "geometry": {"coordinates":[2.6488230228,39.5782928467],"type":"Point"}
}