{
  "type": "Feature",
  "properties": {
    "iso:country":"ES",
    "sg:address":"Avda Cid Campeador, 3",
    "sg:city":"Burgos",
    "sg:orig_category":"Seguridad En El Trabajo Y Prevenci\u00d3n De Riesgos Laborales",
    "sg:phone":"+34 947 25 21 31",
    "sg:postcode":"09003",
    "sg:province":"Burgos",
    "sg:website":"www.grupomgo.es",
    "wof:name":"Grupo Mgo S. A.",
    "wof:placetype":"venue"
},
  "geometry": {"coordinates":[-3.6986489296,42.3440284729],"type":"Point"}
}