{
  "type": "Feature",
  "properties": {
    "addr:full":"Calle de Cruz Verde, 3 Fuentenovilla Guadalajara 19113",
    "addr:housenumber":"3",
    "addr:postcode":"19113",
    "addr:street":"Calle De Cruz Verde",
    "iso:country":"ES",
    "sg:address":"Calle de Cruz Verde, 3",
    "sg:city":"Fuentenovilla",
    "sg:orig_category":"Empresas De Electricidad En General",
    "sg:phone":"+34 949 38 97 21",
    "sg:postcode":"19113",
    "sg:province":"Guadalajara",
    "wof:name":"Distribucion Electrica Las Mercedes S.l",
    "wof:placetype":"venue"
},
  "geometry": {"coordinates":[-3.0946879387,40.3661956787],"type":"Point"}
}