{
  "type": "Feature",
  "properties": {
    "addr:full":"Carretera, Km. 0060,5 Fermoselle Zamora 49220",
    "addr:postcode":"49220",
    "addr:street":"Carretera Km. 0060,5",
    "iso:country":"ES",
    "sg:address":"Carretera, Km. 0060,5",
    "sg:city":"Fermoselle",
    "sg:orig_category":"Reposter\u00cdas",
    "sg:phone":"+34 980 61 40 07",
    "sg:postcode":"49220",
    "sg:province":"Zamora",
    "wof:name":"Diez Diez Roberto",
    "wof:placetype":"venue"
},
  "geometry": {"coordinates":[-6.3993067741,41.3167610168],"type":"Point"}
}