{
  "type": "Feature",
  "properties": {
    "addr:full":"Calle de Pedre\u00d1a, 3 Roquetas Mar Almer\u00eda 04740",
    "addr:housenumber":"3",
    "addr:postcode":"04740",
    "addr:street":"Calle De Pedren\u0303A",
    "iso:country":"ES",
    "sg:address":"Calle de Pedre\u00d1a, 3",
    "sg:city":"Roquetas Mar",
    "sg:orig_category":"Promotores Constructores",
    "sg:phone":"+34 950 32 96 83",
    "sg:postcode":"04740",
    "sg:province":"Almer\u00eda",
    "wof:name":"Jesus Pomares S.l.n.e",
    "wof:placetype":"venue"
},
  "geometry": {"coordinates":[-2.6140019894,36.7569160461],"type":"Point"}
}