{
  "type": "Feature",
  "properties": {
    "addr:full":"Carrer de Tarragona, 11 Senia Tarragona 43560",
    "addr:housenumber":"11",
    "addr:postcode":"43560",
    "addr:street":"Carrer De Tarragona",
    "iso:country":"ES",
    "sg:address":"Carrer de Tarragona, 11",
    "sg:city":"Senia",
    "sg:orig_category":"Cristaler\u00cdas",
    "sg:phone":"+34 977 57 00 49",
    "sg:postcode":"43560",
    "sg:province":"Tarragona",
    "wof:name":"Cristall Bany S.c.c.l.",
    "wof:placetype":"venue"
},
  "geometry": {"coordinates":[0.282795012,40.6354026794],"type":"Point"}
}