{
  "type": "Feature",
  "properties": {
    "iso:country":"ES",
    "sg:address":"Calle de Puerto San Isidro, 15",
    "sg:city":"Oviedo",
    "sg:orig_category":"Empresarios",
    "sg:phone":"+34 985 28 94 60",
    "sg:postcode":"33011",
    "sg:province":"Asturias",
    "wof:name":"Borgolla Inigoya Reformas S.l.l.",
    "wof:placetype":"venue"
},
  "geometry": {"coordinates":[-5.8353390694,43.3713378906],"type":"Point"}
}