{
  "type": "Feature",
  "properties": {
    "addr:full":"Calle de Miguel Servet, 4 Monzon Huesca 22400",
    "addr:housenumber":"4",
    "addr:postcode":"22400",
    "addr:street":"Calle De Miguel Servet",
    "iso:country":"ES",
    "sg:address":"Calle de Miguel Servet, 4",
    "sg:city":"Monzon",
    "sg:orig_category":"Agencias De Viajes",
    "sg:phone":"+34 974 41 60 74",
    "sg:postcode":"22400",
    "sg:province":"Huesca",
    "sg:website":"www.viajesnortesur.com",
    "wof:name":"Viajes Norte Sur S.a.",
    "wof:placetype":"venue"
},
  "geometry": {"coordinates":[0.1915639937,41.9106254578],"type":"Point"}
}