{
  "type": "Feature",
  "properties": {
    "addr:full":"Ctra. Bejar, S/n Ledrada Salamanca 37730",
    "addr:postcode":"37730",
    "addr:street":"Ctra. Bejar S / N Ledrada",
    "iso:country":"ES",
    "sg:address":"Ctra. Bejar, S/n",
    "sg:city":"Ledrada",
    "sg:orig_category":"Mataderos Y Talleres De Despiezado",
    "sg:phone":"+34 923 59 11 46",
    "sg:postcode":"37730",
    "sg:province":"Salamanca",
    "wof:name":"Union De Industriales De Ledrada S. A.",
    "wof:placetype":"venue"
},
  "geometry": {"coordinates":[-5.7208709717,40.467830658],"type":"Point"}
}