{
  "type": "Feature",
  "properties": {
    "addr:full":"Las Lomas, 17 Motilla Palancar Cuenca 16200",
    "addr:housenumber":"17",
    "addr:postcode":"16200",
    "addr:street":"Las Lomas",
    "iso:country":"ES",
    "sg:address":"Las Lomas, 17",
    "sg:city":"Motilla Palancar",
    "sg:orig_category":"Promotores Constructores",
    "sg:phone":"+34 969 33 24 51",
    "sg:postcode":"16200",
    "sg:province":"Cuenca",
    "wof:name":"Copcisa S.a.",
    "wof:placetype":"venue"
},
  "geometry": {"coordinates":[-1.9043300152,39.5558586121],"type":"Point"}
}