{
  "type": "Feature",
  "properties": {
    "addr:full":"Avda Juan Xxiii, 46 Cabezo Torres Murcia 30110",
    "addr:housenumber":"46",
    "addr:postcode":"30110",
    "addr:street":"Avda Juan Xxiii",
    "iso:country":"ES",
    "sg:address":"Avda Juan Xxiii, 46",
    "sg:city":"Cabezo Torres",
    "sg:orig_category":"Electricidad: Instaladores",
    "sg:phone":"+34 968 89 97 00",
    "sg:postcode":"30110",
    "sg:province":"Murcia",
    "wof:name":"Electricidad Habi S.l.",
    "wof:placetype":"venue"
},
  "geometry": {"coordinates":[-1.1235940456,38.0185699463],"type":"Point"}
}