{
  "type": "Feature",
  "properties": {
    "iso:country":"ES",
    "sg:address":"Avda Carlos Pelaez, 3",
    "sg:city":"Navia",
    "sg:orig_category":"Complementos De Vestir (al Por Menor)",
    "sg:phone":"+34 985 63 05 92",
    "sg:postcode":"33710",
    "sg:province":"Asturias",
    "wof:name":"Sanchez Martinez Maria Luz",
    "wof:placetype":"venue"
},
  "geometry": {"coordinates":[-6.7192988396,43.5425834656],"type":"Point"}
}