{
  "type": "Feature",
  "properties": {
    "addr:full":"Calle de Fray Francisco, 20 Munera Albacete 02612",
    "addr:housenumber":"20",
    "addr:postcode":"02612",
    "addr:street":"Calle De Fray Francisco",
    "iso:country":"ES",
    "sg:address":"Calle de Fray Francisco, 20",
    "sg:city":"Munera",
    "sg:orig_category":"Electrodom\u00c9sticos (al Por Menor)",
    "sg:phone":"+34 967 37 21 34",
    "sg:postcode":"02612",
    "sg:province":"Albacete",
    "wof:name":"Melero Solana Pedro",
    "wof:placetype":"venue"
},
  "geometry": {"coordinates":[-2.4762690067,39.0419311523],"type":"Point"}
}