{
  "type": "Feature",
  "properties": {
    "addr:full":"Calle de San Juan Bosco, 1 Rota C\u00e1diz 11520",
    "addr:housenumber":"1",
    "addr:postcode":"11520",
    "addr:street":"Calle De San Juan Bosco;Ca\u0301Diz",
    "iso:country":"ES",
    "sg:address":"Calle de San Juan Bosco, 1",
    "sg:city":"Rota",
    "sg:orig_category":"Alquiler De Veh\u00cdculos: Turismos Y Utilitarios",
    "sg:phone":"+34 956 81 18 48",
    "sg:postcode":"11520",
    "sg:province":"C\u00e1diz",
    "wof:name":"Astarothrent M.j.s.l.",
    "wof:placetype":"venue"
},
  "geometry": {"coordinates":[-6.3577165604,36.6267585754],"type":"Point"}
}