{
  "type": "Feature",
  "properties": {
    "addr:full":"Avda Jose Antonio Tavio, 8 Costa Del Silencio Santa Cruz De Tenerife 38630",
    "addr:housenumber":"8",
    "addr:postcode":"38630",
    "addr:street":"Avda Jose Antonio Tavio",
    "iso:country":"ES",
    "sg:address":"Avda Jose Antonio Tavio, 8",
    "sg:city":"Costa Del Silencio",
    "sg:orig_category":"Art\u00cdculos De Regalo (al Por Menor)",
    "sg:phone":"+34 922 73 37 59",
    "sg:postcode":"38630",
    "sg:province":"Santa Cruz De Tenerife",
    "wof:name":"Globe Distributers S.l.",
    "wof:placetype":"venue"
},
  "geometry": {"coordinates":[-16.6466293335,28.0117092133],"type":"Point"}
}