{
  "type": "Feature",
  "properties": {
    "addr:full":"Afores, S/n Riudarenes Girona 17421",
    "addr:housenumber":"s / n",
    "addr:postcode":"17421",
    "addr:street":"Afores",
    "iso:country":"ES",
    "sg:address":"Afores, S/n",
    "sg:city":"Riudarenes",
    "sg:orig_category":"Explotaci\u00d3n De Canteras",
    "sg:phone":"+34 972 85 36 34",
    "sg:postcode":"17421",
    "sg:province":"Girona",
    "wof:name":"Arids Guixeras S. L.",
    "wof:placetype":"venue"
},
  "geometry": {"coordinates":[2.6685736179,41.8192481995],"type":"Point"}
}