{
  "type": "Feature",
  "properties": {
    "iso:country":"ES",
    "sg:address":"Av Carrilet, 44",
    "sg:city":"Hospitalet Llobregat",
    "sg:orig_category":"Empresarios",
    "sg:phone":"+34 934 32 26 45",
    "sg:postcode":"08902",
    "sg:province":"Barcelona",
    "wof:name":"Myda S.c.p.",
    "wof:placetype":"venue"
},
  "geometry": {"coordinates":[2.1293640137,41.3649368286],"type":"Point"}
}