{
  "type": "Feature",
  "properties": {
    "iso:country":"ES",
    "sg:address":"Avda Seara, 16",
    "sg:city":"Seara",
    "sg:classifiers":[
        {
            "category":"Autos & Motor Vehicles",
            "subcategory":"Automobile Sales",
            "type":"Retail Goods"
        }
    ],
    "sg:phone":"+34 986 77 03 99",
    "sg:postcode":"36995",
    "sg:province":"Pontevedra",
    "wof:name":"Autoescuela Poyo-san Juan S.l.",
    "wof:placetype":"venue"
},
  "geometry": {"coordinates":[-8.685341835,42.4420814514],"type":"Point"}
}