{
  "type": "Feature",
  "properties": {
    "addr:full":"Carrer de Monti-sion, 24 Palma Islas Baleares 07001",
    "addr:housenumber":"24",
    "addr:postcode":"07001",
    "addr:street":"Carrer De Monti-Sion",
    "iso:country":"ES",
    "sg:address":"Carrer de Monti-sion, 24",
    "sg:city":"Palma",
    "sg:orig_category":"Internados & Ense\u00d1anza Privada",
    "sg:phone":"+34 971 71 13 00",
    "sg:postcode":"07001",
    "sg:province":"Islas Baleares",
    "wof:name":"Colegio De Montesion",
    "wof:placetype":"venue"
},
  "geometry": {"coordinates":[2.6529290676,39.5671386719],"type":"Point"}
}