{
  "type": "Feature",
  "properties": {
    "addr:full":"Avgd Marti Pujol, 230 Badalona Barcelona 08911",
    "addr:housenumber":"230",
    "addr:postcode":"08911",
    "addr:street":"Pujol",
    "iso:country":"ES",
    "sg:address":"Avgd Marti Pujol, 230",
    "sg:city":"Badalona",
    "sg:orig_category":"Farmacias",
    "sg:phone":"+34 933 84 47 54",
    "sg:postcode":"08911",
    "sg:province":"Barcelona",
    "wof:name":"Gotzens Busquets Jaime",
    "wof:placetype":"venue"
},
  "geometry": {"coordinates":[2.2444360256,41.4515762329],"type":"Point"}
}