{
  "type": "Feature",
  "properties": {
    "iso:country":"ES",
    "sg:address":"Carretera Sastago Bujaraloz, Km. 0005,0",
    "sg:city":"Sastago",
    "sg:orig_category":"Poller\u00cda Y Caza (al Por Menor)",
    "sg:phone":"+34 976 17 40 06",
    "sg:postcode":"50780",
    "sg:province":"Zaragoza",
    "wof:name":"Ferruz Eroles S.cv",
    "wof:placetype":"venue"
},
  "geometry": {"coordinates":[-0.346803993,41.3222999573],"type":"Point"}
}