{
  "type": "Feature",
  "properties": {
    "addr:full":"Avgd Alfons Xiii, 227 Badalona Barcelona 08918",
    "addr:housenumber":"227",
    "addr:postcode":"08918",
    "addr:street":"Alfons Xiii",
    "iso:country":"ES",
    "sg:address":"Avgd Alfons Xiii, 227",
    "sg:city":"Badalona",
    "sg:orig_category":"Agentes, Concesionarios Y Sucursales De Veh\u00cdculos",
    "sg:phone":"+34 933 87 24 12",
    "sg:postcode":"08918",
    "sg:province":"Barcelona",
    "wof:name":"Nordisauto S.l.",
    "wof:placetype":"venue"
},
  "geometry": {"coordinates":[2.2304339409,41.4404907227],"type":"Point"}
}