{
  "type": "Feature",
  "properties": {
    "iso:country":"ES",
    "sg:address":"Cmno Molinos (de Los), S/n",
    "sg:city":"Zaragoza",
    "sg:orig_category":"Metalizados",
    "sg:phone":"+34 976 51 47 49",
    "sg:postcode":"50015",
    "sg:province":"Zaragoza",
    "wof:name":"Talleres Aranguren S. L.",
    "wof:placetype":"venue"
},
  "geometry": {"coordinates":[-0.8684489727,41.6773452759],"type":"Point"}
}