{
  "type": "Feature",
  "properties": {
    "iso:country":"ES",
    "sg:address":"Avda Gran Capitan (del), 2",
    "sg:city":"Cordoba",
    "sg:orig_category":"Ropa Para Beb\u00c9s Y Ni\u00d1os (confecci\u00d3n, Al Por Mayor)",
    "sg:phone":"+34 957 47 12 30",
    "sg:postcode":"14006",
    "sg:province":"C\u00f3rdoba",
    "wof:name":"Mothercare Iberica S.a.",
    "wof:placetype":"venue"
},
  "geometry": {"coordinates":[-4.7818851471,37.8852653503],"type":"Point"}
}