{
  "type": "Feature",
  "properties": {
    "addr:full":"Carrer de Pont, 27 Manlleu Barcelona 08560",
    "addr:housenumber":"27",
    "addr:postcode":"08560",
    "addr:street":"Carrer De Pont",
    "iso:country":"ES",
    "sg:address":"Carrer de Pont, 27",
    "sg:city":"Manlleu",
    "sg:orig_category":"Productores Recolectores, Venta Directa De Vinos",
    "sg:phone":"+34 938 51 31 67",
    "sg:postcode":"08560",
    "sg:province":"Barcelona",
    "wof:name":"Riera Pinto S.a.",
    "wof:placetype":"venue"
},
  "geometry": {"coordinates":[2.2850489616,41.9995117188],"type":"Point"}
}