{
  "type": "Feature",
  "properties": {
    "iso:country":"ES",
    "sg:address":"Avda Doctor Gregorio Mara\u00d1on, 7",
    "sg:city":"Torrevieja",
    "sg:orig_category":"Heladeros",
    "sg:phone":"+34 965 70 84 58",
    "sg:postcode":"03180",
    "sg:province":"Alicante",
    "wof:name":"Alemany Baeza Josefa",
    "wof:placetype":"venue"
},
  "geometry": {"coordinates":[-0.6869580746,37.976890564],"type":"Point"}
}