{
  "type": "Feature",
  "properties": {
    "iso:country":"ES",
    "sg:address":"Pla\u00c7 Peixateria, 17",
    "sg:city":"Vilanova I La Geltru",
    "sg:orig_category":"Inmobiliaria (agencias)",
    "sg:phone":"+34 938 14 44 28",
    "sg:postcode":"08800",
    "sg:province":"Barcelona",
    "wof:name":"Esteve Carrera S.l.",
    "wof:placetype":"venue"
},
  "geometry": {"coordinates":[1.7269899845,41.226474762],"type":"Point"}
}