{
  "type": "Feature",
  "properties": {
    "addr:full":"Carrer de Unio (de La), 16 Tarragona Tarragona 43001",
    "addr:housenumber":"16",
    "addr:postcode":"43001",
    "addr:street":"Carrer De Unio De La",
    "iso:country":"ES",
    "sg:address":"Carrer de Unio (de La), 16",
    "sg:city":"Tarragona",
    "sg:orig_category":"Ropa Para Se\u00d1oras (al Por Menor)",
    "sg:phone":"+34 977 24 19 45",
    "sg:postcode":"43001",
    "sg:province":"Tarragona",
    "wof:name":"Espejo Arroyo Luis",
    "wof:placetype":"venue"
},
  "geometry": {"coordinates":[1.2519750595,41.1147422791],"type":"Point"}
}