{
  "type": "Feature",
  "properties": {
    "addr:full":"Traviata, 10 Valladolid Valladolid 47009",
    "addr:housenumber":"10",
    "addr:postcode":"47009",
    "addr:street":"Traviata",
    "iso:country":"ES",
    "sg:address":"Traviata, 10",
    "sg:city":"Valladolid",
    "sg:orig_category":"Artes Gr\u00c1ficas, Artes Pl\u00c1sticas (curso)",
    "sg:phone":"+34 983 34 92 73",
    "sg:postcode":"47009",
    "sg:province":"Valladolid",
    "wof:name":"Cayfo Y Asociados A.i.e.",
    "wof:placetype":"venue"
},
  "geometry": {"coordinates":[-4.7313489914,41.6870689392],"type":"Point"}
}