{
  "type": "Feature",
  "properties": {
    "iso:country":"ES",
    "sg:address":"Calle de Albacete, 2",
    "sg:city":"Valmojado",
    "sg:orig_category":"Cerrajer\u00cda, Ferrallista",
    "sg:phone":"+34 918 17 09 75",
    "sg:postcode":"45940",
    "sg:province":"Toledo",
    "wof:name":"Cantalapiedra Arroyo Alberto",
    "wof:placetype":"venue"
},
  "geometry": {"coordinates":[-4.0878591537,40.2093582153],"type":"Point"}
}