{
  "type": "Feature",
  "properties": {
    "addr:full":"Patxiku Kalea, 10 Zarautz Guip\u00f9zcoa 20800",
    "addr:housenumber":"10",
    "addr:postcode":"20800",
    "addr:street":"Patxiku Kalea;Guipu\u0300Zcoa",
    "iso:country":"ES",
    "sg:address":"Patxiku Kalea, 10",
    "sg:city":"Zarautz",
    "sg:orig_category":"Restaurantes",
    "sg:phone":"+34 943 13 34 57",
    "sg:postcode":"20800",
    "sg:province":"Guip\u00f9zcoa",
    "wof:name":"Arritxa-zhitex S.l.",
    "wof:placetype":"venue"
},
  "geometry": {"coordinates":[-2.1762290001,43.2850036621],"type":"Point"}
}