{
  "type": "Feature",
  "properties": {
    "iso:country":"ES",
    "sg:address":"Calle de Luis Pando, 10",
    "sg:city":"Madrid",
    "sg:orig_category":"Molduras, Junquillos, Listones Y Molduras Perforadas",
    "sg:phone":"+34 914 63 30 31",
    "sg:postcode":"28047",
    "sg:province":"Madrid",
    "wof:name":"Abad Nonidez Juan Carlos",
    "wof:placetype":"venue"
},
  "geometry": {"coordinates":[-3.745759,40.403095],"type":"Point"}
}