{
  "type": "Feature",
  "properties": {
    "iso:country":"ES",
    "sg:address":"Avda Cardenal Benlloch, 31",
    "sg:city":"Valencia",
    "sg:orig_category":"Talleres: Ropa A Medida",
    "sg:phone":"+34 963 69 88 26",
    "sg:postcode":"46021",
    "sg:province":"Valencia",
    "wof:name":"Perez Bueno Maximino",
    "wof:placetype":"venue"
},
  "geometry": {"coordinates":[-0.3560119867,39.4684753418],"type":"Point"}
}