{
  "type": "Feature",
  "properties": {
    "addr:full":"Carrer de Terra Alta, 14 Poligono Industrial Can Carner Barcelona 08211",
    "addr:housenumber":"14",
    "addr:postcode":"08211",
    "addr:street":"Carrer De Terra Alta;Poligono Industrial",
    "iso:country":"ES",
    "sg:address":"Carrer de Terra Alta, 14",
    "sg:city":"Poligono Industrial Can Carner",
    "sg:orig_category":"Freidur\u00cdas: Equipos Y Suministros",
    "sg:phone":"+34 937 15 88 75",
    "sg:postcode":"08211",
    "sg:province":"Barcelona",
    "wof:name":"Frit Delartsl S.l.",
    "wof:placetype":"venue"
},
  "geometry": {"coordinates":[2.0824799538,41.6114387512],"type":"Point"}
}