{
  "type": "Feature",
  "properties": {
    "iso:country":"ES",
    "sg:address":"Calle de Real, 39",
    "sg:city":"Otura",
    "sg:orig_category":"Peluqueros: De Se\u00d1oras",
    "sg:phone":"+34 958 55 53 52",
    "sg:postcode":"18630",
    "sg:province":"Granada",
    "wof:name":"Velasco Muros Maria Del Mar",
    "wof:placetype":"venue"
},
  "geometry": {"coordinates":[-3.63438797,37.0928421021],"type":"Point"}
}