{
  "type": "Feature",
  "properties": {
    "iso:country":"ES",
    "sg:address":"Pza Mayor, 16",
    "sg:city":"Movera",
    "sg:orig_category":"Lubrificantes (fabricaci\u00d3n, Al Por Mayor)",
    "sg:phone":"+34 976 58 66 00",
    "sg:postcode":"50194",
    "sg:province":"Zaragoza",
    "wof:name":"Grassa Aracues Maria Dolores",
    "wof:placetype":"venue"
},
  "geometry": {"coordinates":[-0.8217319846,41.6489944458],"type":"Point"}
}