{
  "type": "Feature",
  "properties": {
    "iso:country":"ES",
    "sg:address":"Rua Rambla, 3",
    "sg:city":"Portosin",
    "sg:orig_category":"Guarder\u00cdas",
    "sg:phone":"+34 981 76 67 05",
    "sg:postcode":"15999",
    "sg:province":"La Coru\u00f1a",
    "wof:name":"Oparque S.c.",
    "wof:placetype":"venue"
},
  "geometry": {"coordinates":[-8.9493789673,42.7565155029],"type":"Point"}
}