{
  "type": "Feature",
  "properties": {
    "addr:full":"Ctra Basurtu-kastrexana, 252 Bilbao Vizcaya 48013",
    "addr:housenumber":"252",
    "addr:postcode":"48013",
    "addr:street":"Ctra Basurtu-Kastrexana",
    "iso:country":"ES",
    "sg:address":"Ctra Basurtu-kastrexana, 252",
    "sg:city":"Bilbao",
    "sg:orig_category":"Importaci\u00d3n",
    "sg:phone":"+34 944 98 20 63",
    "sg:postcode":"48013",
    "sg:province":"Vizcaya",
    "wof:name":"Watch Orient Distribuciones S.l.",
    "wof:placetype":"venue"
},
  "geometry": {"coordinates":[-2.9757304192,43.25],"type":"Point"}
}