{
  "type": "Feature",
  "properties": {
    "iso:country":"ES",
    "sg:address":"Ptge. M. Llevant, S/n",
    "sg:city":"Mataro",
    "sg:orig_category":"Fabricaci\u00d3n De Su\u00c9ters Y Chalecos De Punto",
    "sg:phone":"+34 937 57 79 17",
    "sg:postcode":"08301",
    "sg:province":"Barcelona",
    "wof:name":"Balboa Alcala Gerardo",
    "wof:placetype":"venue"
},
  "geometry": {"coordinates":[2.4497408867,41.5370292664],"type":"Point"}
}