{
  "type": "Feature",
  "properties": {
    "addr:full":"Expl Aeropuerto Carlos Haya, S/n Basozabal Vizcaya 48150",
    "addr:housenumber":"s",
    "addr:postcode":"48150",
    "addr:street":"/ N",
    "iso:country":"ES",
    "sg:address":"Expl Aeropuerto Carlos Haya, S/n",
    "sg:city":"Basozabal",
    "sg:orig_category":"Transporte En General",
    "sg:phone":"+34 944 53 05 08",
    "sg:postcode":"48150",
    "sg:province":"Vizcaya",
    "sg:website":"www.tavasa.com",
    "wof:name":"Trabajos Aereos Vascos S.a.",
    "wof:placetype":"venue"
},
  "geometry": {"coordinates":[-2.9244790077,43.2990455627],"type":"Point"}
}