{
  "type": "Feature",
  "properties": {
    "iso:country":"ES",
    "sg:address":"Valdeallin, 9",
    "sg:city":"Estella",
    "sg:orig_category":"Comercio, Reparaci\u00d3n De Motocicletas, Bicicletas Y Piezas Sueltas",
    "sg:phone":"+34 948 54 63 93",
    "sg:postcode":"31200",
    "sg:province":"Navarra",
    "wof:name":"Arrastia Echegaray Miguel Angel",
    "wof:placetype":"venue"
},
  "geometry": {"coordinates":[-2.0303533077,42.6726341248],"type":"Point"}
}