{
  "type": "Feature",
  "properties": {
    "addr:full":"Calle de Luchana, 7 Madrid Madrid 28010",
    "addr:housenumber":"7",
    "addr:postcode":"madrid;28010",
    "addr:street":"Calle De Luchana",
    "iso:country":"ES",
    "sg:address":"Calle de Luchana, 7",
    "sg:city":"Madrid",
    "sg:orig_category":"Molduras, Junquillos, Listones Y Molduras Perforadas",
    "sg:phone":"+34 915 94 46 11",
    "sg:postcode":"28010",
    "sg:province":"Madrid",
    "wof:name":"Alcematic S.l.",
    "wof:placetype":"venue"
},
  "geometry": {"coordinates":[-3.7013344765,40.4295158386],"type":"Point"}
}