{
  "type": "Feature",
  "properties": {
    "iso:country":"ES",
    "sg:address":"Calle de Doctor Buenaventura Carreras, 11",
    "sg:city":"Granada",
    "sg:orig_category":"Empresas De Limpieza",
    "sg:phone":"+34 958 52 36 14",
    "sg:postcode":"18004",
    "sg:province":"Granada",
    "sg:website":"www.dragados.com",
    "wof:name":"Clecer S.a.",
    "wof:placetype":"venue"
},
  "geometry": {"coordinates":[-3.6081011295,37.1662254333],"type":"Point"}
}