{
  "type": "Feature",
  "properties": {
    "addr:full":"Calle de San Miguel, 28 Catarroja Valencia 46470",
    "addr:housenumber":"28",
    "addr:postcode":"46470",
    "addr:street":"Calle De San Miguel",
    "iso:country":"ES",
    "sg:address":"Calle de San Miguel, 28",
    "sg:city":"Catarroja",
    "sg:orig_category":"Laboratorios Farmac\u00c9uticos",
    "sg:phone":"+34 961 27 47 49",
    "sg:postcode":"46470",
    "sg:province":"Valencia",
    "wof:name":"Martinez Bou Jose",
    "wof:placetype":"venue"
},
  "geometry": {"coordinates":[-0.4026390016,39.3982124329],"type":"Point"}
}