{
  "type": "Feature",
  "properties": {
    "addr:full":"Calle de Pio Xii (de), 1 San Sebastian De Los Reyes Madrid 28700",
    "addr:postcode":"28700",
    "addr:street":"Calle De Pio Xii De 1",
    "iso:country":"ES",
    "sg:address":"Calle de Pio Xii (de), 1",
    "sg:city":"San Sebastian De Los Reyes",
    "sg:orig_category":"Bancos",
    "sg:phone":"+34 916 59 37 00",
    "sg:postcode":"28700",
    "sg:province":"Madrid",
    "sg:website":"www.bancogallego.es",
    "wof:name":"Banco Gallego S.a.",
    "wof:placetype":"venue"
},
  "geometry": {"coordinates":[-3.6278669834,40.5455245972],"type":"Point"}
}