{
  "type": "Feature",
  "properties": {
    "addr:full":"Calle de Lozano, 37 Albacete Albacete 02002",
    "addr:housenumber":"37",
    "addr:postcode":"02002",
    "addr:street":"Calle De Lozano",
    "iso:country":"ES",
    "sg:address":"Calle de Lozano, 37",
    "sg:city":"Albacete",
    "sg:orig_category":"Complementos Para Pasteler\u00cdas, Confiter\u00cdas Y Chocolater\u00cdas",
    "sg:phone":"+34 967 21 11 65",
    "sg:postcode":"02002",
    "sg:province":"Albacete",
    "wof:name":"Comodin Suministros De Accesorios Y Productos Alimenticios S.a.",
    "wof:placetype":"venue"
},
  "geometry": {"coordinates":[-1.848721981,38.9898414612],"type":"Point"}
}