{
  "type": "Feature",
  "properties": {
    "addr:full":"Calle de Alfonso Solans, 3 Zaragoza Zaragoza 50014",
    "addr:housenumber":"3",
    "addr:postcode":"50014",
    "addr:street":"Calle De Alfonso Solans",
    "iso:country":"ES",
    "sg:address":"Calle de Alfonso Solans, 3",
    "sg:city":"Zaragoza",
    "sg:orig_category":"Cl\u00cdnicas Dentales",
    "sg:phone":"+34 976 20 57 55",
    "sg:postcode":"50014",
    "sg:province":"Zaragoza",
    "wof:name":"Denmorl S.l.",
    "wof:placetype":"venue"
},
  "geometry": {"coordinates":[-0.8685594201,41.656829834],"type":"Point"}
}