{
  "type": "Feature",
  "properties": {
    "addr:full":"Avda Habana (de La), 3 Ourense Ourense 32003",
    "addr:postcode":"32003",
    "addr:street":"Avda Habana De La 3",
    "iso:country":"ES",
    "sg:address":"Avda Habana (de La), 3",
    "sg:city":"Ourense",
    "sg:orig_category":"Asesor\u00cda De Formaci\u00d3n Y Gesti\u00d3n De Personal",
    "sg:phone":"+34 988 21 75 70",
    "sg:postcode":"32003",
    "sg:province":"Ourense",
    "wof:name":"Laborase S.l.",
    "wof:placetype":"venue"
},
  "geometry": {"coordinates":[-7.8670620918,42.3429908752],"type":"Point"}
}