{
  "type": "Feature",
  "properties": {
    "addr:full":"Carrer de Sant Isidor, 21 Sabadell Barcelona 08206",
    "addr:housenumber":"21",
    "addr:postcode":"08206",
    "addr:street":"Carrer De Sant Isidor",
    "iso:country":"ES",
    "sg:address":"Carrer de Sant Isidor, 21",
    "sg:city":"Sabadell",
    "sg:orig_category":"Cajas De Ahorro",
    "sg:phone":"+34 937 16 30 73",
    "sg:postcode":"08206",
    "sg:province":"Barcelona",
    "wof:name":"Caixa D'estalvis I Pensions De Barcelona",
    "wof:placetype":"venue"
},
  "geometry": {"coordinates":[2.0868968964,41.5545005798],"type":"Point"}
}