{
  "type": "Feature",
  "properties": {
    "iso:country":"ES",
    "sg:address":"Av Roma (de), 6",
    "sg:city":"Tarragona",
    "sg:orig_category":"Doctores En Medicina",
    "sg:phone":"+34 977 24 13 77",
    "sg:postcode":"43005",
    "sg:province":"Tarragona",
    "wof:name":"Sobrino Perez Francisco Javier",
    "wof:placetype":"venue"
},
  "geometry": {"coordinates":[1.2430249453,41.1183815002],"type":"Point"}
}