{
  "type": "Feature",
  "properties": {
    "addr:full":"Carrer de Pau (la), 8 S. Pere Ribes Barcelona 08810",
    "addr:postcode":"08810",
    "addr:street":"Carrer De Pau La 8 S. Pere Ribes Barcelona",
    "iso:country":"ES",
    "sg:address":"Carrer de Pau (la), 8",
    "sg:city":"S. Pere Ribes",
    "sg:orig_category":"Pescader\u00cdas (al Por Menor)",
    "sg:phone":"+34 938 96 29 34",
    "sg:postcode":"08810",
    "sg:province":"Barcelona",
    "wof:name":"Peixateries Noves S.l.",
    "wof:placetype":"venue"
},
  "geometry": {"coordinates":[1.7730280161,41.2611122131],"type":"Point"}
}