{
  "type": "Feature",
  "properties": {
    "iso:country":"ES",
    "sg:address":"Urb Poeta Ruiz, 2",
    "sg:city":"Cabra",
    "sg:orig_category":"Inform\u00c1tica, Ofim\u00c1tica (estudios, Asesor\u00cda, Ingenier\u00cda, Formaci\u00d3n)",
    "sg:phone":"+34 957 52 43 78",
    "sg:postcode":"14940",
    "sg:province":"C\u00f3rdoba",
    "wof:name":"Asociacion Cabra Solidaria",
    "wof:placetype":"venue"
},
  "geometry": {"coordinates":[-4.4593791962,37.4908409119],"type":"Point"}
}