{
  "type": "Feature",
  "properties": {
    "iso:country":"ES",
    "sg:address":"Calle de Tirso De Molina, 69",
    "sg:city":"Yebenes",
    "sg:orig_category":"Abogados",
    "sg:phone":"+34 925 32 12 82",
    "sg:postcode":"45470",
    "sg:province":"Toledo",
    "wof:name":"Lopez-rey Garcia-rojo Santiago",
    "wof:placetype":"venue"
},
  "geometry": {"coordinates":[-3.8773179054,39.5761795044],"type":"Point"}
}