{
  "type": "Feature",
  "properties": {
    "iso:country":"ES",
    "sg:address":"Rua Cidade De Viveiro, 3",
    "sg:city":"Lugo",
    "sg:orig_category":"M\u00c9dicos: Estomatolog\u00cda",
    "sg:phone":"+34 982 25 15 50",
    "sg:postcode":"27002",
    "sg:province":"Lugo",
    "wof:name":"Quiroga Garcia Jose",
    "wof:placetype":"venue"
},
  "geometry": {"coordinates":[-7.5594987869,43.0079612732],"type":"Point"}
}