{
  "type": "Feature",
  "properties": {
    "addr:full":"Luga Ribera De La Necora, S/n Puerto Sotogrande C\u00e1diz 11310",
    "addr:housenumber":"s / n",
    "addr:postcode":"11310",
    "addr:street":"Ca\u0301Diz",
    "iso:country":"ES",
    "sg:address":"Luga Ribera De La Necora, S/n",
    "sg:city":"Puerto Sotogrande",
    "sg:orig_category":"Alquiler De Veh\u00cdculos: Turismos Y Utilitarios",
    "sg:phone":"+34 956 61 65 58",
    "sg:postcode":"11310",
    "sg:province":"C\u00e1diz",
    "wof:name":"Marin Fortes Juan",
    "wof:placetype":"venue"
},
  "geometry": {"coordinates":[-5.2829370499,36.2767448425],"type":"Point"}
}