{
  "type": "Feature",
  "properties": {
    "iso:country":"ES",
    "sg:address":"Calle de Albarracin, 4",
    "sg:city":"Utrillas",
    "sg:orig_category":"Hoteles",
    "sg:phone":"+34 978 75 80 81",
    "sg:postcode":"44760",
    "sg:province":"Teruel",
    "wof:name":"Camacho Ayora Pedro Jose",
    "wof:placetype":"venue"
},
  "geometry": {"coordinates":[-0.8433418274,40.8123664856],"type":"Point"}
}