{
  "type": "Feature",
  "properties": {
    "iso:country":"ES",
    "sg:address":"Avda Isabel La Catolica, 2",
    "sg:city":"Coria",
    "sg:orig_category":"Asociaciones Y Clubs Deportivos",
    "sg:phone":"+34 927 50 30 64",
    "sg:postcode":"10800",
    "sg:province":"C\u00e1ceres",
    "wof:name":"Domingo Viste S.l.",
    "wof:placetype":"venue"
},
  "geometry": {"coordinates":[-6.5380530357,39.9879341125],"type":"Point"}
}