{
  "type": "Feature",
  "properties": {
    "iso:country":"ES",
    "sg:address":"Calle de Tirant Lo Blanc, 8",
    "sg:city":"Javea",
    "sg:classifiers":[
        {
            "category":"Personal",
            "subcategory":"Barber",
            "type":"Services"
        }
    ],
    "sg:phone":"+34 966 46 09 19",
    "sg:postcode":"03730",
    "sg:province":"Alicante",
    "sg:tags":[
        "caballeros",
        "de",
        "peluqueros"
    ],
    "wof:name":"Perruqueria Irene S.l.",
    "wof:placetype":"venue"
},
  "geometry": {"coordinates":[0.1662649959,38.7894058228],"type":"Point"}
}