{
  "type": "Feature",
  "properties": {
    "iso:country":"ES",
    "sg:address":"Pg Doctor Moragas, 184",
    "sg:city":"Barbera Valles",
    "sg:orig_category":"Laboratorios De An\u00c1lisis Biom\u00c9dicos",
    "sg:phone":"+34 937 19 02 52",
    "sg:postcode":"08210",
    "sg:province":"Barcelona",
    "wof:name":"Galseran Catafau Salvador",
    "wof:placetype":"venue"
},
  "geometry": {"coordinates":[2.1250290871,41.5146942139],"type":"Point"}
}