{
  "type": "Feature",
  "properties": {
    "addr:full":"Rua Do Cesteiro, 14 Poio Pontevedra 36994",
    "addr:housenumber":"14",
    "addr:postcode":"36994",
    "addr:street":"Rua Do Cesteiro",
    "iso:country":"ES",
    "sg:address":"Rua Do Cesteiro, 14",
    "sg:city":"Poio",
    "sg:orig_category":"Venta, Montaje De Neum\u00c1ticos",
    "sg:phone":"+34 986 77 00 19",
    "sg:postcode":"36994",
    "sg:province":"Pontevedra",
    "wof:name":"Garaje Paco S.l.",
    "wof:placetype":"venue"
},
  "geometry": {"coordinates":[-8.6823453903,42.4439353943],"type":"Point"}
}