{
  "type": "Feature",
  "properties": {
    "iso:country":"ES",
    "sg:address":"Carrer de Sant Silvestre, 23",
    "sg:city":"Santa Coloma De Gramenet",
    "sg:orig_category":"Alquiler De V\u00cddeo",
    "sg:phone":"+34 933 85 73 58",
    "sg:postcode":"08922",
    "sg:province":"Barcelona",
    "wof:name":"Chacon Navas Manuel",
    "wof:placetype":"venue"
},
  "geometry": {"coordinates":[2.2120699883,41.4502487183],"type":"Point"}
}