{
  "type": "Feature",
  "properties": {
    "iso:country":"ES",
    "sg:address":"Av Central, 59",
    "sg:city":"Calafell-park",
    "sg:orig_category":"Promotores Constructores",
    "sg:phone":"+34 977 69 44 56",
    "sg:postcode":"43820",
    "sg:province":"Tarragona",
    "wof:name":"Construcciones Gaon Plaza S.l.",
    "wof:placetype":"venue"
},
  "geometry": {"coordinates":[1.5956890583,41.2297668457],"type":"Point"}
}