{
  "type": "Feature",
  "properties": {
    "iso:country":"ES",
    "sg:address":"Avda Colon, 20",
    "sg:city":"Logro\u00f1o",
    "sg:orig_category":"Fabricaci\u00d3n, Venta De Cuadros, Accesorios Para Enmarcar",
    "sg:phone":"+34 941 23 16 62",
    "sg:postcode":"26003",
    "sg:province":"La Rioja",
    "wof:name":"Esteban Ezquerro Armando",
    "wof:placetype":"venue"
},
  "geometry": {"coordinates":[-2.440418005,42.4619827271],"type":"Point"}
}