{
  "type": "Feature",
  "properties": {
    "addr:full":"Avgd Constitucio, 61 Alaro Islas Baleares 07340",
    "addr:housenumber":"61",
    "addr:postcode":"07340",
    "addr:street":"Avgd Constitucio",
    "iso:country":"ES",
    "sg:address":"Avgd Constitucio, 61",
    "sg:city":"Alaro",
    "sg:orig_category":"Perfumer\u00cda Y Cosm\u00c9tica (fabricaci\u00d3n, Al Por Mayor)",
    "sg:phone":"+34 971 51 04 22",
    "sg:postcode":"07340",
    "sg:province":"Islas Baleares",
    "wof:name":"Folla Escudero Alfonso",
    "wof:placetype":"venue"
},
  "geometry": {"coordinates":[2.7936739922,39.7031745911],"type":"Point"}
}