{
  "type": "Feature",
  "properties": {
    "addr:full":"Calle de Sollube Kalea, 6 Arteaga Derio Vizcaya 48160",
    "addr:housenumber":"6",
    "addr:postcode":"48160",
    "addr:street":"Calle De Sollube Kalea",
    "iso:country":"ES",
    "sg:address":"Calle de Sollube Kalea, 6",
    "sg:city":"Arteaga Derio",
    "sg:orig_category":"Sociedades, Compa\u00d1\u00cdas Aseguradoras",
    "sg:phone":"+34 944 54 18 12",
    "sg:postcode":"48160",
    "sg:province":"Vizcaya",
    "wof:name":"Bilbao Compa\u00f1ia Anonima De Seguros",
    "wof:placetype":"venue"
},
  "geometry": {"coordinates":[-2.8864560127,43.2923126221],"type":"Point"}
}