{
  "type": "Feature",
  "properties": {
    "addr:full":"Av Tarragona, 85 Cunit Tarragona 43881",
    "addr:housenumber":"85",
    "addr:postcode":"43881",
    "addr:street":"Av Tarragona",
    "iso:country":"ES",
    "sg:address":"Av Tarragona, 85",
    "sg:city":"Cunit",
    "sg:orig_category":"Plomeros",
    "sg:phone":"+34 977 16 42 73",
    "sg:postcode":"43881",
    "sg:province":"Tarragona",
    "wof:name":"Ca\u00f1adillas Navarro Francisco Jesus",
    "wof:placetype":"venue"
},
  "geometry": {"coordinates":[1.6276210546,41.193447113],"type":"Point"}
}