{
  "type": "Feature",
  "properties": {
    "iso:country":"ES",
    "sg:address":"Avda Espa\u00d1a, 36",
    "sg:city":"Isla Cristina",
    "sg:orig_category":"Farmacias",
    "sg:phone":"+34 959 33 19 92",
    "sg:postcode":"21410",
    "sg:province":"Huelva",
    "wof:name":"Mu\u00f1oz Mendez Jaime",
    "wof:placetype":"venue"
},
  "geometry": {"coordinates":[-7.3234992027,37.2008743286],"type":"Point"}
}