{
  "type": "Feature",
  "properties": {
    "iso:country":"ES",
    "sg:address":"Rua Vila De Noia, 64",
    "sg:city":"Carballo",
    "sg:orig_category":"Alumbrados",
    "sg:phone":"+34 981 70 20 05",
    "sg:postcode":"15100",
    "sg:province":"La Coru\u00f1a",
    "wof:name":"Pombo Fraga Horacio",
    "wof:placetype":"venue"
},
  "geometry": {"coordinates":[-8.6834392548,43.2178535461],"type":"Point"}
}