{
  "type": "Feature",
  "properties": {
    "iso:country":"ES",
    "sg:address":"Calle de Constitucion (de La), 47",
    "sg:city":"Alcobendas",
    "sg:orig_category":"Ropa Para Se\u00d1oras (al Por Menor)",
    "sg:phone":"+34 916 51 48 77",
    "sg:postcode":"28100",
    "sg:province":"Madrid",
    "wof:name":"Macias Hernandez Antonio",
    "wof:placetype":"venue"
},
  "geometry": {"coordinates":[-3.6372807026,40.5428123474],"type":"Point"}
}