{
  "type": "Feature",
  "properties": {
    "iso:country":"ES",
    "sg:address":"Rua Rosalia De Castro, 9",
    "sg:city":"Gondomar",
    "sg:orig_category":"Supermercados Y Hipermercados",
    "sg:phone":"+34 986 36 95 73",
    "sg:postcode":"36380",
    "sg:province":"Pontevedra",
    "wof:name":"Peixoto Freiria Esperanza",
    "wof:placetype":"venue"
},
  "geometry": {"coordinates":[-8.7633981705,42.1106719971],"type":"Point"}
}