{
  "type": "Feature",
  "properties": {
    "addr:full":"Puerta Osuna, 8 Ecija Sevilla 41400",
    "addr:housenumber":"8",
    "addr:postcode":"41400",
    "addr:street":"Osuna",
    "iso:country":"ES",
    "sg:address":"Puerta Osuna, 8",
    "sg:city":"Ecija",
    "sg:orig_category":"Librer\u00cdas",
    "sg:phone":"+34 955 90 46 24",
    "sg:postcode":"41400",
    "sg:province":"Sevilla",
    "wof:name":"Serrano Zurita Jose Antonio",
    "wof:placetype":"venue"
},
  "geometry": {"coordinates":[-5.0782690048,37.5395584106],"type":"Point"}
}