{
  "type": "Feature",
  "properties": {
    "iso:country":"ES",
    "sg:address":"Pol Ind L'alter, 3",
    "sg:city":"Alcacer",
    "sg:orig_category":"Fabricaci\u00d3n De Moldes Y Modelos",
    "sg:phone":"+34 961 23 46 29",
    "sg:postcode":"46290",
    "sg:province":"Valencia",
    "wof:name":"Industrias Jomiplast S.l",
    "wof:placetype":"venue"
},
  "geometry": {"coordinates":[-0.4493550062,39.3561897278],"type":"Point"}
}