{
  "type": "Feature",
  "properties": {
    "iso:country":"ES",
    "sg:address":"Calle de Lora Del Rio, 3",
    "sg:city":"Arahal",
    "sg:orig_category":"Alimentaci\u00d3n General (al Por Menor)",
    "sg:phone":"+34 954 84 12 79",
    "sg:postcode":"41600",
    "sg:province":"Sevilla",
    "wof:name":"Jimenez Benitez Carmen",
    "wof:placetype":"venue"
},
  "geometry": {"coordinates":[-5.5440039635,37.266998291],"type":"Point"}
}