{
  "type": "Feature",
  "properties": {
    "iso:country":"ES",
    "sg:address":"Calle de Cuba, 6",
    "sg:city":"Coslada",
    "sg:orig_category":"Licores (fabricaci\u00d3n, Al Por Mayor)",
    "sg:phone":"+34 916 69 41 46",
    "sg:postcode":"28820",
    "sg:province":"Madrid",
    "wof:name":"Merca Xxi S.l.",
    "wof:placetype":"venue"
},
  "geometry": {"coordinates":[-3.5573039055,40.4250526428],"type":"Point"}
}