{
  "type": "Feature",
  "properties": {
    "iso:country":"ES",
    "sg:address":"Calle de Antonio Lopez, 10",
    "sg:city":"S. Fernando",
    "sg:orig_category":"Zapatos (al Por Menor)",
    "sg:phone":"+34 956 88 20 70",
    "sg:postcode":"11100",
    "sg:province":"C\u00e1diz",
    "wof:name":"Cabrera Luca Eulogio",
    "wof:placetype":"venue"
},
  "geometry": {"coordinates":[-6.1987700462,36.4656410217],"type":"Point"}
}