{
  "type": "Feature",
  "properties": {
    "addr:full":"C/ Jose Bernad Amoros, 29 Elche Alicante 03205",
    "addr:housenumber":"29",
    "addr:postcode":"03205",
    "addr:street":"C / Jose Bernad Amoros",
    "iso:country":"ES",
    "sg:address":"C/ Jose Bernad Amoros, 29",
    "sg:city":"Elche",
    "sg:orig_category":"Zapatos (al Por Mayor)",
    "sg:phone":"+34 965 44 98 46",
    "sg:postcode":"03205",
    "sg:province":"Alicante",
    "wof:name":"J'hoaquinetti S.l",
    "wof:placetype":"venue"
},
  "geometry": {"coordinates":[-0.7100660205,38.2683753967],"type":"Point"}
}