{
  "type": "Feature",
  "properties": {
    "iso:country":"ES",
    "sg:address":"Rua Vilalba (de), 1",
    "sg:city":"Ribadeo",
    "sg:orig_category":"Caf\u00c9s, Bares, Cervecer\u00cdas",
    "sg:phone":"+34 982 13 08 76",
    "sg:postcode":"27700",
    "sg:province":"Lugo",
    "wof:name":"Agro Y Alimentacion Panta S.l.",
    "wof:placetype":"venue"
},
  "geometry": {"coordinates":[-7.0453691483,43.5366020203],"type":"Point"}
}