{
  "type": "Feature",
  "properties": {
    "iso:country":"ES",
    "sg:address":"Avda Castilla, 11",
    "sg:city":"Guadalajara",
    "sg:orig_category":"Laboratorios Y Trabajos De Fotograf\u00cda, V\u00cddeo Y Cine",
    "sg:phone":"+34 949 22 57 25",
    "sg:postcode":"19002",
    "sg:province":"Guadalajara",
    "wof:name":"Xu  Zhiyuan",
    "wof:placetype":"venue"
},
  "geometry": {"coordinates":[-3.1673400402,40.6260795593],"type":"Point"}
}