{
  "type": "Feature",
  "properties": {
    "iso:country":"ES",
    "sg:address":"Plaz Pintor Lucas, 10",
    "sg:city":"Madrid",
    "sg:orig_category":"Librer\u00cdas",
    "sg:phone":"+34 915 69 23 36",
    "sg:postcode":"28026",
    "sg:province":"Madrid",
    "wof:name":"Zoilo Gomez Luisa Antonia",
    "wof:placetype":"venue"
},
  "geometry": {"coordinates":[-3.7098135948,40.3886375427],"type":"Point"}
}