{
  "type": "Feature",
  "properties": {
    "addr:full":"Carrer de Enten\u00c7a, 202 Barcelona Barcelona 08029",
    "addr:housenumber":"202",
    "addr:postcode":"08029",
    "addr:street":"Carrer De Entenc\u0327A",
    "iso:country":"ES",
    "sg:address":"Carrer de Enten\u00c7a, 202",
    "sg:city":"Barcelona",
    "sg:orig_category":"Abogados",
    "sg:phone":"+34 933 21 64 26",
    "sg:postcode":"08029",
    "sg:province":"Barcelona",
    "wof:name":"Luce\u00f1o Serrano Juan Antonio",
    "wof:placetype":"venue"
},
  "geometry": {"coordinates":[2.143611908,41.3851089478],"type":"Point"}
}