{
  "type": "Feature",
  "properties": {
    "iso:country":"ES",
    "sg:address":"Pase Florencia, 1",
    "sg:city":"Santiago El Mayor",
    "sg:orig_category":"Promotores Constructores",
    "sg:phone":"+34 968 34 78 05",
    "sg:postcode":"30012",
    "sg:province":"Murcia",
    "wof:name":"Residencial Teixereta S.l.",
    "wof:placetype":"venue"
},
  "geometry": {"coordinates":[-1.1206640005,37.9650650024],"type":"Point"}
}