{
  "type": "Feature",
  "properties": {
    "addr:full":"C/ Joaquin Garcia Mora, 13 Elche Alicante 03206",
    "addr:housenumber":"13",
    "addr:postcode":"03206",
    "addr:street":"C / Joaquin Garcia Mora",
    "iso:country":"ES",
    "sg:address":"C/ Joaquin Garcia Mora, 13",
    "sg:city":"Elche",
    "sg:orig_category":"Reposter\u00cdas",
    "sg:phone":"+34 965 46 00 03",
    "sg:postcode":"03206",
    "sg:province":"Alicante",
    "wof:name":"Antonio Guilabert Y Otros C.b.",
    "wof:placetype":"venue"
},
  "geometry": {"coordinates":[-0.7109357715,38.2759742737],"type":"Point"}
}