{
  "type": "Feature",
  "properties": {
    "addr:full":"C/ Unio, 50 Llucmajor Islas Baleares 07620",
    "addr:housenumber":"50",
    "addr:postcode":"07620",
    "addr:street":"C / Unio",
    "iso:country":"ES",
    "sg:address":"C/ Unio, 50",
    "sg:city":"Llucmajor",
    "sg:orig_category":"Alimentaci\u00d3n General (al Por Menor)",
    "sg:phone":"+34 971 12 06 55",
    "sg:postcode":"07620",
    "sg:province":"Islas Baleares",
    "wof:name":"Superunion S.l",
    "wof:placetype":"venue"
},
  "geometry": {"coordinates":[2.8943929672,39.4924736023],"type":"Point"}
}