{
  "type": "Feature",
  "properties": {
    "iso:country":"ES",
    "sg:address":"Avda Victoria, 6",
    "sg:city":"Flota",
    "sg:orig_category":"Procuradores",
    "sg:phone":"+34 968 24 06 90",
    "sg:postcode":"30007",
    "sg:province":"Murcia",
    "wof:name":"Alba Y Vega  Inmaculada De",
    "wof:placetype":"venue"
},
  "geometry": {"coordinates":[-1.1298867464,37.9834747314],"type":"Point"}
}