{
  "type": "Feature",
  "properties": {
    "addr:full":"Carrer de Daro, 1 Canyelles-almadrava-puig-rom Girona 17480",
    "addr:housenumber":"1",
    "addr:postcode":"17480",
    "addr:street":"Carrer De Daro",
    "iso:country":"ES",
    "sg:address":"Carrer de Daro, 1",
    "sg:city":"Canyelles-almadrava-puig-rom",
    "sg:orig_category":"Sales (al Por Mayor)",
    "sg:phone":"+34 972 25 74 93",
    "sg:postcode":"17480",
    "sg:province":"Girona",
    "wof:name":"Borras Garcia Jose Maria",
    "wof:placetype":"venue"
},
  "geometry": {"coordinates":[3.1663351059,42.2661399841],"type":"Point"}
}