{
  "type": "Feature",
  "properties": {
    "addr:full":"Calle de Lope De Vega, 6 Arenas -areeta Vizcaya 48930",
    "addr:housenumber":"6;areeta",
    "addr:postcode":"48930",
    "addr:street":"Calle De Lope De Vega",
    "iso:country":"ES",
    "sg:address":"Calle de Lope De Vega, 6",
    "sg:city":"Arenas -areeta",
    "sg:orig_category":"Peluqueros: De Se\u00d1oras",
    "sg:phone":"+34 944 64 33 17",
    "sg:postcode":"48930",
    "sg:province":"Vizcaya",
    "wof:name":"Miguel Del Blanco Mari Carmen",
    "wof:placetype":"venue"
},
  "geometry": {"coordinates":[-3.0082640648,43.3286476135],"type":"Point"}
}