{
  "type": "Feature",
  "properties": {
    "addr:full":"Calle de Rey (del), 19 Aranjuez Madrid 28300",
    "addr:housenumber":"19",
    "addr:postcode":"28300",
    "addr:street":"Calle De Rey Del",
    "iso:country":"ES",
    "sg:address":"Calle de Rey (del), 19",
    "sg:city":"Aranjuez",
    "sg:orig_category":"Muebles, Minoristas",
    "sg:phone":"+34 918 92 43 36",
    "sg:postcode":"28300",
    "sg:province":"Madrid",
    "wof:name":"Almamobel S.l.",
    "wof:placetype":"venue"
},
  "geometry": {"coordinates":[-3.6001417637,40.0337600708],"type":"Point"}
}