{
  "type": "Feature",
  "properties": {
    "addr:full":"Illobre(vi\u00f1as), 6 Illobre A Coru\u00f1a 15319",
    "addr:housenumber":"6",
    "addr:postcode":"15319",
    "addr:street":"Vin\u0303As;Corun\u0303A",
    "iso:country":"ES",
    "sg:address":"Illobre(vi\u00f1as), 6",
    "sg:city":"Illobre",
    "sg:orig_category":"Contenedores (mercanc\u00cdas)",
    "sg:phone":"+34 981 77 03 15",
    "sg:postcode":"15319",
    "sg:province":"A Coru\u00f1a",
    "wof:name":"Vidal Fernandez Xose Oscar",
    "wof:placetype":"venue"
},
  "geometry": {"coordinates":[-8.0784473419,43.3035011292],"type":"Point"}
}