{
  "type": "Feature",
  "properties": {
    "addr:full":"Asomada, 7 Icod Vinos Santa Cruz De Tenerife 38430",
    "addr:housenumber":"7",
    "addr:postcode":"38430",
    "addr:street":"Asomada",
    "iso:country":"ES",
    "sg:address":"Asomada, 7",
    "sg:city":"Icod Vinos",
    "sg:orig_category":"Agencias Y Agentes Comerciales, Representantes",
    "sg:phone":"+34 922 12 18 90",
    "sg:postcode":"38430",
    "sg:province":"Santa Cruz De Tenerife",
    "wof:name":"Machado Afonso Jose Raul",
    "wof:placetype":"venue"
},
  "geometry": {"coordinates":[-16.7185840607,28.3666362762],"type":"Point"}
}