{
  "type": "Feature",
  "properties": {
    "iso:country":"ES",
    "sg:address":"Avda Alemania (de), 16",
    "sg:city":"Caceres",
    "sg:orig_category":"Farmacias",
    "sg:phone":"+34 927 22 13 69",
    "sg:postcode":"10001",
    "sg:province":"C\u00e1ceres",
    "wof:name":"Optitutto S.l.",
    "wof:placetype":"venue"
},
  "geometry": {"coordinates":[-6.3801188469,39.4669303894],"type":"Point"}
}