{
  "type": "Feature",
  "properties": {
    "addr:full":"Ctra Loeches, Km. 0001,6 Torrejon Ardoz Madrid 28850",
    "addr:postcode":"28850",
    "addr:street":"Ctra Loeches Km. 0001,6",
    "iso:country":"ES",
    "sg:address":"Ctra Loeches, Km. 0001,6",
    "sg:city":"Torrejon Ardoz",
    "sg:orig_category":"Rectificaci\u00d3n, Mecanizado, Fresado",
    "sg:phone":"+34 916 75 54 50",
    "sg:postcode":"28850",
    "sg:province":"Madrid",
    "wof:name":"Gomez Martin Gabriel",
    "wof:placetype":"venue"
},
  "geometry": {"coordinates":[-3.4763290882,40.4592514038],"type":"Point"}
}