{
  "type": "Feature",
  "properties": {
    "iso:country":"ES",
    "sg:address":"Calle de Donoso Cortes, 82",
    "sg:city":"Madrid",
    "sg:orig_category":"Colchones (fabricaci\u00d3n, Al Por Mayor, Al Por Menor)",
    "sg:phone":"+34 915 43 14 73",
    "sg:postcode":"28015",
    "sg:province":"Madrid",
    "wof:name":"Tirado Lozano Concepcion",
    "wof:placetype":"venue"
},
  "geometry": {"coordinates":[-3.715528965,40.4365348816],"type":"Point"}
}