{
  "type": "Feature",
  "properties": {
    "addr:full":"Av. Paz, 12 Bollullos Par Condado Huelva 21710",
    "addr:housenumber":"12",
    "addr:postcode":"21710",
    "addr:street":"Av. Paz",
    "iso:country":"ES",
    "sg:address":"Av. Paz, 12",
    "sg:city":"Bollullos Par Condado",
    "sg:orig_category":"Doctores En Medicina",
    "sg:phone":"+34 959 41 28 84",
    "sg:postcode":"21710",
    "sg:province":"Huelva",
    "wof:name":"Garcia Fernandez Manuel",
    "wof:placetype":"venue"
},
  "geometry": {"coordinates":[-6.5415668488,37.3339424133],"type":"Point"}
}