{
  "type": "Feature",
  "properties": {
    "addr:full":"Carrer de Mercat, 11 Barcelona Barcelona 08030",
    "addr:housenumber":"11",
    "addr:postcode":"08030",
    "addr:street":"Carrer De Mercat",
    "iso:country":"ES",
    "sg:address":"Carrer de Mercat, 11",
    "sg:city":"Barcelona",
    "sg:orig_category":"Postigos, Persianas Y Celos\u00cdas",
    "sg:phone":"+34 933 11 62 46",
    "sg:postcode":"08030",
    "sg:province":"Barcelona",
    "wof:name":"Covalper S.l.l.",
    "wof:placetype":"venue"
},
  "geometry": {"coordinates":[2.1891489029,41.4345855713],"type":"Point"}
}