{
  "type": "Feature",
  "properties": {
    "addr:full":"Avda Nocedo, 42 Le\u00f3n Le\u00f3n 24007",
    "addr:housenumber":"42",
    "addr:postcode":"24007",
    "addr:street":"Avda Nocedo;Leo\u0301N",
    "iso:country":"ES",
    "sg:address":"Avda Nocedo, 42",
    "sg:city":"Le\u00f3n",
    "sg:orig_category":"Peluqueros: De Se\u00d1oras",
    "sg:phone":"+34 987 24 81 21",
    "sg:postcode":"24007",
    "sg:province":"Le\u00f3n",
    "wof:name":"Cuesta Provecho Ana Maria",
    "wof:placetype":"venue"
},
  "geometry": {"coordinates":[-5.5682878494,42.6064758301],"type":"Point"}
}