{
  "type": "Feature",
  "properties": {
    "iso:country":"ES",
    "sg:address":"Carrer de Botanica, 146",
    "sg:city":"Hospitalet Llobregat",
    "sg:orig_category":"Venta, Localizaci\u00d3n, Reparaci\u00d3n De Material E Instrumental M\u00c9dico",
    "sg:phone":"+34 933 36 43 58",
    "sg:postcode":"08908",
    "sg:province":"Barcelona",
    "wof:name":"Invernessmedicalibericas.a.",
    "wof:placetype":"venue"
},
  "geometry": {"coordinates":[2.1217160225,41.347202301],"type":"Point"}
}