{
  "type": "Feature",
  "properties": {
    "addr:full":"Avda Carlota Alessandri, 105 Torremolinos M\u00e1laga 29620",
    "addr:housenumber":"105",
    "addr:postcode":"29620",
    "addr:street":"Avda Carlota Alessandri;Ma\u0301Laga",
    "iso:country":"ES",
    "sg:address":"Avda Carlota Alessandri, 105",
    "sg:city":"Torremolinos",
    "sg:orig_category":"Inmobiliaria (agencias)",
    "sg:phone":"+34 952 38 41 30",
    "sg:postcode":"29620",
    "sg:province":"M\u00e1laga",
    "wof:name":"Chouben Travaux S.l.",
    "wof:placetype":"venue"
},
  "geometry": {"coordinates":[-4.511425972,36.6050262451],"type":"Point"}
}