{
  "type": "Feature",
  "properties": {
    "iso:country":"ES",
    "sg:address":"Avda Africa (de), S/n",
    "sg:city":"Ceuta",
    "sg:orig_category":"Centros De Educaci\u00d3n Especial",
    "sg:phone":"+34 956 50 64 42",
    "sg:postcode":"51001",
    "sg:province":"Ceuta",
    "wof:name":"Colegio Publico Maestro Juan Morejon",
    "wof:placetype":"venue"
},
  "geometry": {"coordinates":[-5.3219590187,35.8885383606],"type":"Point"}
}