{
  "type": "Feature",
  "properties": {
    "addr:full":"Elechas, S/n Elechas Cantabria 39130",
    "addr:postcode":"39130",
    "addr:street":"Elechas S / N",
    "iso:country":"ES",
    "sg:address":"Elechas, S/n",
    "sg:city":"Elechas",
    "sg:orig_category":"Refiner\u00cdas De Petr\u00d3leo",
    "sg:phone":"+34 942 50 10 33",
    "sg:postcode":"39130",
    "sg:province":"Cantabria",
    "wof:name":"Gasolinera Elechas S.l.",
    "wof:placetype":"venue"
},
  "geometry": {"coordinates":[-3.7824635506,43.4160804749],"type":"Point"}
}