{
  "type": "Feature",
  "properties": {
    "addr:full":"Calle de Valladolid, 2 Parla Madrid 28980",
    "addr:housenumber":"2",
    "addr:postcode":"28980",
    "addr:street":"Calle De Valladolid",
    "iso:country":"ES",
    "sg:address":"Calle de Valladolid, 2",
    "sg:city":"Parla",
    "sg:orig_category":"Muebles, Minoristas",
    "sg:phone":"+34 916 99 93 14",
    "sg:postcode":"28980",
    "sg:province":"Madrid",
    "wof:name":"Zamorano Bardera Marcial",
    "wof:placetype":"venue"
},
  "geometry": {"coordinates":[-3.7643182278,40.2420959473],"type":"Point"}
}