{
  "type": "Feature",
  "properties": {
    "iso:country":"ES",
    "sg:address":"Avgd Pinar, Del, S/n",
    "sg:city":"Costa De Los Pinos",
    "sg:orig_category":"Electrodom\u00c9sticos (al Por Menor)",
    "sg:phone":"+34 971 84 02 48",
    "sg:postcode":"07559",
    "sg:province":"Islas Baleares",
    "wof:name":"Nicolau Roig Juan",
    "wof:placetype":"venue"
},
  "geometry": {"coordinates":[3.3866999149,39.6109313965],"type":"Point"}
}