{
  "type": "Feature",
  "properties": {
    "addr:full":"Pl. Ezpeleta, 3 Huarte Navarra 31620",
    "addr:housenumber":"3",
    "addr:postcode":"31620",
    "addr:street":"Ezpeleta;Navarra",
    "iso:country":"ES",
    "sg:address":"Pl. Ezpeleta, 3",
    "sg:city":"Huarte",
    "sg:orig_category":"Serrer\u00cdas De Madera",
    "sg:phone":"+34 948 33 02 06",
    "sg:postcode":"31620",
    "sg:province":"Navarra",
    "wof:name":"Serreria Barberena S.l.",
    "wof:placetype":"venue"
},
  "geometry": {"coordinates":[-1.5941380262,42.8306427002],"type":"Point"}
}