{
  "type": "Feature",
  "properties": {
    "addr:full":"Calle de Francisco Garcia Pavon, 10 Tomelloso Ciudad Real 13700",
    "addr:housenumber":"10",
    "addr:postcode":"13700",
    "addr:street":"Calle De Francisco Garcia Pavon",
    "iso:country":"ES",
    "sg:address":"Calle de Francisco Garcia Pavon, 10",
    "sg:city":"Tomelloso",
    "sg:orig_category":"Abogados",
    "sg:phone":"+34 926 51 44 07",
    "sg:postcode":"13700",
    "sg:province":"Ciudad Real",
    "wof:name":"Hurtado Tudela Eduardo",
    "wof:placetype":"venue"
},
  "geometry": {"coordinates":[-3.0088040829,39.1575126648],"type":"Point"}
}