{
  "type": "Feature",
  "properties": {
    "iso:country":"ES",
    "sg:address":"Send Alquiton (del), 7",
    "sg:city":"Arganda",
    "sg:orig_category":"Suministros Para Exposiciones, Ferias, Salones",
    "sg:phone":"+34 918 71 92 25",
    "sg:postcode":"28500",
    "sg:province":"Madrid",
    "wof:name":"Cayft S.a.",
    "wof:placetype":"venue"
},
  "geometry": {"coordinates":[-3.4406979084,40.2999954224],"type":"Point"}
}