{
  "type": "Feature",
  "properties": {
    "addr:full":"Av Doctor Severo Ochoa, 38 Benidorm Alicante 03500",
    "addr:housenumber":"38",
    "addr:postcode":"03500",
    "addr:street":"Av Doctor Severo Ochoa",
    "iso:country":"ES",
    "sg:address":"Av Doctor Severo Ochoa, 38",
    "sg:city":"Benidorm",
    "sg:orig_category":"Venta De Caravanas, Casas M\u00d3viles, Camping",
    "sg:phone":"+34 965 85 06 54",
    "sg:postcode":"03500",
    "sg:province":"Alicante",
    "wof:name":"Sanchez Garcimartin Francisco Javier",
    "wof:placetype":"venue"
},
  "geometry": {"coordinates":[-0.0988880023,38.547416687],"type":"Point"}
}