{
  "type": "Feature",
  "properties": {
    "iso:country":"ES",
    "sg:address":"Calle de Vinader, 13",
    "sg:city":"Santa Catalina",
    "sg:orig_category":"Platos Preparados Refrigerados (fabricaci\u00d3n, Al Por Mayor)",
    "sg:phone":"+34 968 21 47 53",
    "sg:postcode":"30004",
    "sg:province":"Murcia",
    "wof:name":"Cocina Popular De Murcia S.l.",
    "wof:placetype":"venue"
},
  "geometry": {"coordinates":[-1.1333090067,37.9862976074],"type":"Point"}
}