{
  "type": "Feature",
  "properties": {
    "addr:full":"Calle de Aralia, 2 Almeria Almer\u00eda 04009",
    "addr:housenumber":"2",
    "addr:postcode":"04009",
    "addr:street":"Calle De Aralia",
    "iso:country":"ES",
    "sg:address":"Calle de Aralia, 2",
    "sg:city":"Almeria",
    "sg:orig_category":"Limpieza Y Vaciado De Fosas",
    "sg:phone":"+34 950 22 27 32",
    "sg:postcode":"04009",
    "sg:province":"Almer\u00eda",
    "wof:name":"Morales Cuervas Manuel",
    "wof:placetype":"venue"
},
  "geometry": {"coordinates":[-2.4439070225,36.8451690674],"type":"Point"}
}