{
  "type": "Feature",
  "properties": {
    "iso:country":"ES",
    "sg:address":"Calle de Miguel Servet, 4",
    "sg:city":"Estepona",
    "sg:orig_category":"Chapister\u00cda",
    "sg:phone":"+34 952 80 76 09",
    "sg:postcode":"29680",
    "sg:province":"M\u00e1laga",
    "wof:name":"Automobile Restorations S.l.",
    "wof:placetype":"venue"
},
  "geometry": {"coordinates":[-5.1705322266,36.4316368103],"type":"Point"}
}