{
  "type": "Feature",
  "properties": {
    "iso:country":"ES",
    "sg:address":"Calle de Fuertes Acevedo, 18",
    "sg:city":"Oviedo",
    "sg:orig_category":"Peluqueros: De Se\u00d1oras",
    "sg:phone":"+34 985 23 88 66",
    "sg:postcode":"33006",
    "sg:province":"Asturias",
    "wof:name":"Gafarelo Salinas Lidia",
    "wof:placetype":"venue"
},
  "geometry": {"coordinates":[-5.8644838333,43.3598709106],"type":"Point"}
}