{
  "type": "Feature",
  "properties": {
    "addr:full":"Calle de Borao, 7 Zaragoza Zaragoza 50004",
    "addr:housenumber":"7",
    "addr:postcode":"50004",
    "addr:street":"Calle De Borao",
    "iso:country":"ES",
    "sg:address":"Calle de Borao, 7",
    "sg:city":"Zaragoza",
    "sg:orig_category":"Agencias Y Asesores De Publicidad",
    "sg:phone":"+34 976 43 02 37",
    "sg:postcode":"50004",
    "sg:province":"Zaragoza",
    "wof:name":"Saa Mu\u00f1oz Felix Antonio",
    "wof:placetype":"venue"
},
  "geometry": {"coordinates":[-0.8944270015,41.6547660828],"type":"Point"}
}