{
  "type": "Feature",
  "properties": {
    "iso:country":"ES",
    "sg:address":"Carrer de Mar, 27",
    "sg:city":"Vendrell",
    "sg:orig_category":"Fabricaci\u00d3n, Importaci\u00d3n De L\u00c1mparas Y Bombillas",
    "sg:phone":"+34 977 66 01 68",
    "sg:postcode":"43700",
    "sg:province":"Tarragona",
    "wof:name":"Electricitat Guell 2001 S.l.",
    "wof:placetype":"venue"
},
  "geometry": {"coordinates":[1.5346590281,41.2191772461],"type":"Point"}
}