{
  "type": "Feature",
  "properties": {
    "iso:country":"ES",
    "sg:address":"Calle de San Marcelino, 17",
    "sg:city":"Valencia",
    "sg:orig_category":"Laboratorios Y Trabajos De Fotograf\u00cda, V\u00cddeo Y Cine",
    "sg:phone":"+34 963 57 82 10",
    "sg:postcode":"46017",
    "sg:province":"Valencia",
    "wof:name":"Foto Estudio Art S.l.",
    "wof:placetype":"venue"
},
  "geometry": {"coordinates":[-0.3903360069,39.4453010559],"type":"Point"}
}