{
  "type": "Feature",
  "properties": {
    "iso:country":"ES",
    "sg:address":"Kale Nagusia-calle Mayor, 2",
    "sg:city":"Lasarte",
    "sg:orig_category":"Cadenas, Estaciones, Cableados Para Radio Y Televisi\u00d3n",
    "sg:phone":"+34 943 37 69 24",
    "sg:postcode":"20160",
    "sg:province":"Guip\u00f9zcoa",
    "wof:name":"Lan Mikro Lasarte-oria S.l.",
    "wof:placetype":"venue"
},
  "geometry": {"coordinates":[-2.020414114,43.2698173523],"type":"Point"}
}