{
  "type": "Feature",
  "properties": {
    "iso:country":"ES",
    "sg:address":"Carr Truiola, 7",
    "sg:city":"Lloseta",
    "sg:orig_category":"Negocio De Materiales De Construcci\u00d3n",
    "sg:phone":"+34 971 87 30 11",
    "sg:postcode":"07360",
    "sg:province":"Islas Baleares",
    "wof:name":"Coll Fiol Miguel",
    "wof:placetype":"venue"
},
  "geometry": {"coordinates":[2.8697690964,39.717086792],"type":"Point"}
}