{
  "type": "Feature",
  "properties": {
    "iso:country":"ES",
    "sg:address":"Rua Marques De Rodil, 6",
    "sg:city":"Fonsagrada",
    "sg:orig_category":"Negocio De Materiales De Construcci\u00d3n",
    "sg:phone":"+34 982 34 03 56",
    "sg:postcode":"27100",
    "sg:province":"Lugo",
    "wof:name":"Regueiro Diaz Ovidio",
    "wof:placetype":"venue"
},
  "geometry": {"coordinates":[-7.0673189163,43.125995636],"type":"Point"}
}