{
  "type": "Feature",
  "properties": {
    "addr:full":"Calle de Reyes Catolicos, 9 Vitoria-gasteiz \u00c1lava 01013",
    "addr:housenumber":"9",
    "addr:postcode":"01013",
    "addr:street":"Calle De Reyes Catolicos",
    "iso:country":"ES",
    "sg:address":"Calle de Reyes Catolicos, 9",
    "sg:city":"Vitoria-gasteiz",
    "sg:orig_category":"Venta, Instalaci\u00d3n, Reparaci\u00d3n De Antenas Para Televisi\u00d3n",
    "sg:phone":"+34 945 26 86 89",
    "sg:postcode":"01013",
    "sg:province":"\u00c1lava",
    "wof:name":"Fernando Ruiz Garcia",
    "wof:placetype":"venue"
},
  "geometry": {"coordinates":[-2.6840889454,42.8761367798],"type":"Point"}
}