{
  "type": "Feature",
  "properties": {
    "iso:country":"ES",
    "sg:address":"Carrer de Garrigues (de Les) - La Canonja, 18",
    "sg:city":"Canonja",
    "sg:orig_category":"Lencer\u00cda Femenina, Corseter\u00cda, Trajes De Ba\u00d1o (al Por Menor)",
    "sg:phone":"+34 977 54 74 51",
    "sg:postcode":"43110",
    "sg:province":"Tarragona",
    "wof:name":"Colas Campor Susana",
    "wof:placetype":"venue"
},
  "geometry": {"coordinates":[1.1817840338,41.1208381653],"type":"Point"}
}