{
  "type": "Feature",
  "properties": {
    "addr:full":"Avda Cinca, 14 Barbastro Huesca 22300",
    "addr:housenumber":"14",
    "addr:postcode":"22300",
    "addr:street":"Avda Cinca",
    "iso:country":"ES",
    "sg:address":"Avda Cinca, 14",
    "sg:city":"Barbastro",
    "sg:orig_category":"Cajas De Ahorro",
    "sg:phone":"+34 974 31 39 93",
    "sg:postcode":"22300",
    "sg:province":"Huesca",
    "wof:name":"Caja De Ahorros Y Monte De Piedad De Zaragoza Aragon Y Rioja",
    "wof:placetype":"venue"
},
  "geometry": {"coordinates":[0.1307229996,42.0343933105],"type":"Point"}
}