{
  "type": "Feature",
  "properties": {
    "iso:country":"ES",
    "sg:address":"Carr Tendes (les), 34",
    "sg:city":"Oliva",
    "sg:orig_category":"Estancos",
    "sg:phone":"+34 962 85 15 59",
    "sg:postcode":"46780",
    "sg:province":"Valencia",
    "wof:name":"Aunion Perez Rosa Teresa",
    "wof:placetype":"venue"
},
  "geometry": {"coordinates":[-0.1238479987,38.9210281372],"type":"Point"}
}