{
  "type": "Feature",
  "properties": {
    "iso:country":"ES",
    "sg:address":"Calle de San Miguel, 11",
    "sg:city":"Trujillo",
    "sg:orig_category":"Farmacias",
    "sg:phone":"+34 927 32 29 77",
    "sg:postcode":"10200",
    "sg:province":"C\u00e1ceres",
    "wof:name":"Montero Bejarano Jaime",
    "wof:placetype":"venue"
},
  "geometry": {"coordinates":[-5.8805260658,39.4592437744],"type":"Point"}
}