{
  "type": "Feature",
  "properties": {
    "iso:country":"ES",
    "sg:address":"Calle de Antonio Ramos, 21",
    "sg:city":"Palma",
    "sg:orig_category":"Empresas De Carpinter\u00cda De Madera",
    "sg:phone":"+34 968 55 42 39",
    "sg:postcode":"30593",
    "sg:province":"Murcia",
    "wof:name":"Sanchez Hernandez Mariano",
    "wof:placetype":"venue"
},
  "geometry": {"coordinates":[-0.9641839862,37.6916885376],"type":"Point"}
}