{
  "type": "Feature",
  "properties": {
    "addr:full":"Carrer de Gaieta Vinzia, 66 Mollet Valles Barcelona 08100",
    "addr:housenumber":"66",
    "addr:postcode":"08100",
    "addr:street":"Carrer De Gaieta Vinzia",
    "iso:country":"ES",
    "sg:address":"Carrer de Gaieta Vinzia, 66",
    "sg:city":"Mollet Valles",
    "sg:orig_category":"Farmacias",
    "sg:phone":"+34 935 93 11 27",
    "sg:postcode":"08100",
    "sg:province":"Barcelona",
    "wof:name":"Barbero Castellvi Montserrat",
    "wof:placetype":"venue"
},
  "geometry": {"coordinates":[2.2101221085,41.5414886475],"type":"Point"}
}