{
  "type": "Feature",
  "properties": {
    "iso:country":"ES",
    "sg:address":"Foru Plaza Enparantza, 4",
    "sg:city":"Zestoa",
    "sg:orig_category":"Molduras, Junquillos, Listones Y Molduras Perforadas",
    "sg:phone":"+34 943 14 70 95",
    "sg:postcode":"20740",
    "sg:province":"Guip\u00f9zcoa",
    "wof:name":"Iceta Aizpurua I\u00f1aki",
    "wof:placetype":"venue"
},
  "geometry": {"coordinates":[-2.2549140453,43.2378883362],"type":"Point"}
}