{
  "type": "Feature",
  "properties": {
    "addr:full":"Calle de Virgen Del Socorro, 53 Alacant Alicante 03002",
    "addr:housenumber":"53",
    "addr:postcode":"03002",
    "addr:street":"Calle De Virgen Del Socorro",
    "iso:country":"ES",
    "sg:address":"Calle de Virgen Del Socorro, 53",
    "sg:city":"Alacant",
    "sg:orig_category":"Cajas De Ahorro",
    "sg:phone":"+34 965 16 35 00",
    "sg:postcode":"03002",
    "sg:province":"Alicante",
    "wof:name":"Caja De Ahorros Del Mediterraneo",
    "wof:placetype":"venue"
},
  "geometry": {"coordinates":[-0.4736689925,38.3496398926],"type":"Point"}
}