{
  "type": "Feature",
  "properties": {
    "iso:country":"ES",
    "sg:address":"Avda Castilleja De La Cuesta, 2",
    "sg:city":"Bollullos Mitacion",
    "sg:orig_category":"Productos Qu\u00cdmicos (fabricaci\u00d3n, Al Por Mayor)",
    "sg:phone":"+34 955 77 66 33",
    "sg:postcode":"41110",
    "sg:province":"Sevilla",
    "wof:name":"Agro Aljarafe S.a.",
    "wof:placetype":"venue"
},
  "geometry": {"coordinates":[-6.1455388069,37.35779953],"type":"Point"}
}