{
  "type": "Feature",
  "properties": {
    "iso:country":"ES",
    "sg:address":"Calle de Mentrida, 16",
    "sg:city":"Madrid",
    "sg:orig_category":"Herboristas (al Por Menor)",
    "sg:phone":"+34 917 59 62 62",
    "sg:postcode":"28043",
    "sg:province":"Madrid",
    "wof:name":"Navarro Martin Rafael",
    "wof:placetype":"venue"
},
  "geometry": {"coordinates":[-3.6496350765,40.4638175964],"type":"Point"}
}