{
  "type": "Feature",
  "properties": {
    "iso:country":"ES",
    "sg:address":"Avda Enrique Mederos, 118",
    "sg:city":"Llanos De Aridane",
    "sg:orig_category":"Alquiler De Veh\u00cdculos: Turismos Y Utilitarios",
    "sg:phone":"+34 922 40 21 97",
    "sg:postcode":"38760",
    "sg:province":"Santa Cruz De Tenerife",
    "wof:name":"Sponsoring Car S.l.",
    "wof:placetype":"venue"
},
  "geometry": {"coordinates":[-17.9085597992,28.6563796997],"type":"Point"}
}