{
  "type": "Feature",
  "properties": {
    "iso:country":"ES",
    "sg:address":"Calle de Celleruelo, 2",
    "sg:city":"Pola De Siero",
    "sg:orig_category":"Farmacias",
    "sg:phone":"+34 985 72 00 85",
    "sg:postcode":"33510",
    "sg:province":"Asturias",
    "wof:name":"Cabezas De Herrera Estrada Maria Angeles Esparanza",
    "wof:placetype":"venue"
},
  "geometry": {"coordinates":[-5.668279171,43.3927116394],"type":"Point"}
}