{
  "type": "Feature",
  "properties": {
    "iso:country":"ES",
    "sg:address":"Ctra Torrelles, 52",
    "sg:city":"Sant Vicen\u00c7 Dels Horts",
    "sg:orig_category":"Construcciones Met\u00c1licas",
    "sg:phone":"+34 936 56 00 11",
    "sg:postcode":"08620",
    "sg:province":"Barcelona",
    "wof:name":"Cercados Metalicos Ricma S.l.",
    "wof:placetype":"venue"
},
  "geometry": {"coordinates":[1.9929020405,41.3786888123],"type":"Point"}
}