{
  "type": "Feature",
  "properties": {
    "addr:full":"Rua Rio Tamega, 37 Ourense Ourense 32001",
    "addr:housenumber":"37",
    "addr:postcode":"32001",
    "addr:street":"Rua;Tamega",
    "iso:country":"ES",
    "sg:address":"Rua Rio Tamega, 37",
    "sg:city":"Ourense",
    "sg:orig_category":"Pintura, Barniz, Productos Asimilables (fabricaci\u00d3n, Al Por Mayor)",
    "sg:phone":"+34 988 21 65 26",
    "sg:postcode":"32001",
    "sg:province":"Ourense",
    "wof:name":"Rodriguez Vazquez Elier",
    "wof:placetype":"venue"
},
  "geometry": {"coordinates":[-7.8664669991,42.3530693054],"type":"Point"}
}