{
  "type": "Feature",
  "properties": {
    "addr:full":"Ziobi, 11 Alkaiaga Navarra 31789",
    "addr:housenumber":"11",
    "addr:postcode":"31789",
    "addr:street":"Ziobi",
    "iso:country":"ES",
    "sg:address":"Ziobi, 11",
    "sg:city":"Alkaiaga",
    "sg:orig_category":"M\u00c1rmoles, Granitos Y Piedras Naturales",
    "sg:phone":"+34 948 63 10 63",
    "sg:postcode":"31789",
    "sg:province":"Navarra",
    "wof:name":"Marmoles Alkaiaga S.l.",
    "wof:placetype":"venue"
},
  "geometry": {"coordinates":[-1.6932047606,43.2776565552],"type":"Point"}
}