{
  "type": "Feature",
  "properties": {
    "addr:full":"Calle de Felipe Ii, 1 Hinojosa Del Duque C\u00f3rdoba 14270",
    "addr:housenumber":"1",
    "addr:postcode":"14270",
    "addr:street":"Calle De Felipe Ii;Co\u0301Rdoba",
    "iso:country":"ES",
    "sg:address":"Calle de Felipe Ii, 1",
    "sg:city":"Hinojosa Del Duque",
    "sg:orig_category":"Sociedades, Compa\u00d1\u00cdas Aseguradoras",
    "sg:phone":"+34 957 14 15 23",
    "sg:postcode":"14270",
    "sg:province":"C\u00f3rdoba",
    "wof:name":"Seguros Revaliente Ortega Cb",
    "wof:placetype":"venue"
},
  "geometry": {"coordinates":[-5.1466288567,38.5002708435],"type":"Point"}
}