{
  "type": "Feature",
  "properties": {
    "addr:full":"Pol Ind L'alfas, 3 Ibi Alicante 03440",
    "addr:housenumber":"3",
    "addr:postcode":"03440",
    "addr:street":"L'Alfas",
    "iso:country":"ES",
    "sg:address":"Pol Ind L'alfas, 3",
    "sg:city":"Ibi",
    "sg:orig_category":"Bazares, Art\u00cdculos De Limpieza Y De Cocina (al Por Menor)",
    "sg:phone":"+34 965 55 15 03",
    "sg:postcode":"03440",
    "sg:province":"Alicante",
    "wof:name":"Plastimodul S.l.",
    "wof:placetype":"venue"
},
  "geometry": {"coordinates":[-0.57852,38.6207008362],"type":"Point"}
}