{
  "type": "Feature",
  "properties": {
    "iso:country":"ES",
    "sg:address":"Carrer de Craywinckel, 25",
    "sg:city":"Barcelona",
    "sg:orig_category":"Papeler\u00cdas, Librer\u00cdas",
    "sg:phone":"+34 932 12 60 45",
    "sg:postcode":"08022",
    "sg:province":"Barcelona",
    "wof:name":"Kernell Hill S.l.",
    "wof:placetype":"venue"
},
  "geometry": {"coordinates":[2.138876915,41.4114646912],"type":"Point"}
}