{
  "type": "Feature",
  "properties": {
    "iso:country":"ES",
    "sg:address":"Avda Levante (de), 34",
    "sg:city":"Jumilla",
    "sg:orig_category":"Asociaciones Y Clubs Deportivos",
    "sg:phone":"+34 968 75 79 53",
    "sg:postcode":"30520",
    "sg:province":"Murcia",
    "wof:name":"Sosriano Herrero Miguel Angel",
    "wof:placetype":"venue"
},
  "geometry": {"coordinates":[-1.3229089975,38.4744682312],"type":"Point"}
}