{
  "type": "Feature",
  "properties": {
    "addr:full":"Calle de Luis Braille, S/n Malaga M\u00e1laga 29007",
    "addr:housenumber":"s / n",
    "addr:postcode":"29007",
    "addr:street":"Calle De Luis Braille;Ma\u0301Laga",
    "iso:country":"ES",
    "sg:address":"Calle de Luis Braille, S/n",
    "sg:city":"Malaga",
    "sg:orig_category":"Papeler\u00cdas, Librer\u00cdas",
    "sg:phone":"+34 952 61 14 28",
    "sg:postcode":"29007",
    "sg:province":"M\u00e1laga",
    "wof:name":"Papeleria Alvarez S.l.",
    "wof:placetype":"venue"
},
  "geometry": {"coordinates":[-4.4351539612,36.7213287354],"type":"Point"}
}