{
  "type": "Feature",
  "properties": {
    "iso:country":"ES",
    "sg:address":"Calle de Musico Jose Maria Merino, 26",
    "sg:city":"Torrent",
    "sg:orig_category":"Electrodom\u00c9sticos (al Por Menor)",
    "sg:phone":"+34 961 55 54 20",
    "sg:postcode":"46900",
    "sg:province":"Valencia",
    "wof:name":"Peris Verdejo Jose Rafael",
    "wof:placetype":"venue"
},
  "geometry": {"coordinates":[-0.4683840871,39.4360656738],"type":"Point"}
}