{
  "type": "Feature",
  "properties": {
    "addr:full":"Prag Partida De Les Creus, 5 Banyeres Mariola Alicante 03450",
    "addr:housenumber":"5",
    "addr:postcode":"03450",
    "addr:street":"Partida De Les Creus",
    "iso:country":"ES",
    "sg:address":"Prag Partida De Les Creus, 5",
    "sg:city":"Banyeres Mariola",
    "sg:orig_category":"Papel (al Por Mayor)",
    "sg:phone":"+34 966 56 72 29",
    "sg:postcode":"03450",
    "sg:province":"Alicante",
    "wof:name":"Manipulados Vazquez S.l.",
    "wof:placetype":"venue"
},
  "geometry": {"coordinates":[-0.6580740213,38.7120857239],"type":"Point"}
}