{
  "type": "Feature",
  "properties": {
    "addr:full":"Calle de Estame\u00d1eria Vieja, 2 Valencia Valencia 46001",
    "addr:housenumber":"2",
    "addr:postcode":"46001",
    "addr:street":"Calle De Estamen\u0303Eria Vieja",
    "iso:country":"ES",
    "sg:address":"Calle de Estame\u00d1eria Vieja, 2",
    "sg:city":"Valencia",
    "sg:orig_category":"Caf\u00c9s, Bares, Cervecer\u00cdas",
    "sg:phone":"+34 963 91 80 94",
    "sg:postcode":"46001",
    "sg:province":"Valencia",
    "sg:website":"www.theloungecafebar.com",
    "wof:name":"Gingles Gregan C.b.",
    "wof:placetype":"venue"
},
  "geometry": {"coordinates":[-0.3776699901,39.4749336243],"type":"Point"}
}