{
  "type": "Feature",
  "properties": {
    "addr:full":"Calle de Domingo Doreste, 17 Palmas De Gran Canaria Las Palmas 35001",
    "addr:housenumber":"17",
    "addr:postcode":"35001",
    "addr:street":"Calle De Domingo Doreste",
    "iso:country":"ES",
    "sg:address":"Calle de Domingo Doreste, 17",
    "sg:city":"Palmas De Gran Canaria",
    "sg:orig_category":"Abogados",
    "sg:phone":"+34 928 31 21 88",
    "sg:postcode":"35001",
    "sg:province":"Las Palmas",
    "wof:name":"Diaz Marrero Jose Antonio",
    "wof:placetype":"venue"
},
  "geometry": {"coordinates":[-15.4132137299,28.098482132],"type":"Point"}
}