{
  "type": "Feature",
  "properties": {
    "iso:country":"ES",
    "sg:address":"La Rosa, 49",
    "sg:city":"El Bosque",
    "sg:orig_category":"Promotores Constructores",
    "sg:phone":"+34 956 71 61 80",
    "sg:postcode":"11670",
    "sg:province":"C\u00e1diz",
    "wof:name":"Construcciones Ca\u00f1ino S.l.",
    "wof:placetype":"venue"
},
  "geometry": {"coordinates":[-5.5038790703,36.7587203979],"type":"Point"}
}