{
  "type": "Feature",
  "properties": {
    "iso:country":"ES",
    "sg:address":"Calle de Bailen, 8",
    "sg:city":"Almendralejo",
    "sg:orig_category":"Agencias Y Agentes Comerciales, Representantes",
    "sg:phone":"+34 924 66 65 52",
    "sg:postcode":"06200",
    "sg:province":"Badajoz",
    "wof:name":"Hera Olgado Zacarias De La",
    "wof:placetype":"venue"
},
  "geometry": {"coordinates":[-6.4078412056,38.6820106506],"type":"Point"}
}