{
  "type": "Feature",
  "properties": {
    "addr:full":"Calle de Portal De Bergara, 32 Vitoria-gasteiz \u00c1lava 01013",
    "addr:housenumber":"32",
    "addr:postcode":"01013",
    "addr:street":"Calle De Portal De Bergara",
    "iso:country":"ES",
    "sg:address":"Calle de Portal De Bergara, 32",
    "sg:city":"Vitoria-gasteiz",
    "sg:orig_category":"Comercio De Piezas De Recambio Y De Accesorios De Veh\u00cdculos, Veh\u00cdculos Industriales",
    "sg:phone":"+34 945 00 04 26",
    "sg:postcode":"01013",
    "sg:province":"\u00c1lava",
    "sg:website":"www.gruposdiferenciales.com",
    "wof:name":"Grupos Diferenciales, S.a.",
    "wof:placetype":"venue"
},
  "geometry": {"coordinates":[-2.6488640308,42.8702087402],"type":"Point"}
}