{
  "type": "Feature",
  "properties": {
    "addr:full":"Avda Fragata Lealtad, 12 Real Pontevedra 36950",
    "addr:housenumber":"12",
    "addr:postcode":"36950",
    "addr:street":"Avda Fragata Lealtad",
    "iso:country":"ES",
    "sg:address":"Avda Fragata Lealtad, 12",
    "sg:city":"Real",
    "sg:orig_category":"Herboristas (al Por Menor)",
    "sg:phone":"+34 986 31 41 07",
    "sg:postcode":"36950",
    "sg:province":"Pontevedra",
    "wof:name":"Pousada Calvar Ruben",
    "wof:placetype":"venue"
},
  "geometry": {"coordinates":[-8.738442421,42.2772254944],"type":"Point"}
}