{
  "type": "Feature",
  "properties": {
    "addr:full":"Calle de Cervantes, 20 Oviedo Asturias 33004",
    "addr:housenumber":"20",
    "addr:postcode":"33004",
    "addr:street":"Calle De Cervantes",
    "iso:country":"ES",
    "sg:address":"Calle de Cervantes, 20",
    "sg:city":"Oviedo",
    "sg:orig_category":"M\u00c9dicos: Medicina Y Biolog\u00cda Del Deporte",
    "sg:phone":"+34 985 23 64 63",
    "sg:postcode":"33004",
    "sg:province":"Asturias",
    "wof:name":"Clinica Cervantes-asistencia Medico-sanitaria S.l.",
    "wof:placetype":"venue"
},
  "geometry": {"coordinates":[-5.8564829826,43.3634986877],"type":"Point"}
}