{
  "type": "Feature",
  "properties": {
    "addr:full":"Carrer de Zamenhoff (de), 3 Tarragona Tarragona 43001",
    "addr:postcode":"43001",
    "addr:street":"Carrer De Zamenhoff De 3",
    "iso:country":"ES",
    "sg:address":"Carrer de Zamenhoff (de), 3",
    "sg:city":"Tarragona",
    "sg:orig_category":"Ense\u00d1anza, Formaci\u00d3n Profesional: Aprendizaje",
    "sg:phone":"+34 977 22 08 90",
    "sg:postcode":"43001",
    "sg:province":"Tarragona",
    "wof:name":"Centros De Formacion Disced S.l.",
    "wof:placetype":"venue"
},
  "geometry": {"coordinates":[1.2473900318,41.1130180359],"type":"Point"}
}