{
  "type": "Feature",
  "properties": {
    "iso:country":"ES",
    "sg:address":"Rego Do Campo, 9",
    "sg:city":"Pontes Garcia Rodriguez",
    "sg:classifiers":[
        {
            "category":"Taxi",
            "type":"Transportation"
        }
    ],
    "sg:phone":"+34 981 45 07 87",
    "sg:postcode":"15320",
    "sg:province":"La Coru\u00f1a",
    "wof:name":"Bouza Sierra Adolfo",
    "wof:placetype":"venue"
},
  "geometry": {"coordinates":[-7.8519802094,43.4437828064],"type":"Point"}
}