{
  "type": "Feature",
  "properties": {
    "iso:country":"ES",
    "sg:address":"Calle de Ramona Cinto, 16",
    "sg:city":"Ayerbe",
    "sg:orig_category":"Asilos De Ancianos. Centros Privados",
    "sg:phone":"+34 974 38 06 37",
    "sg:postcode":"22800",
    "sg:province":"Huesca",
    "wof:name":"Residencia Nuestra Se\u00f1ora De Casbas",
    "wof:placetype":"venue"
},
  "geometry": {"coordinates":[-0.6877989769,42.2769813538],"type":"Point"}
}