{
  "type": "Feature",
  "properties": {
    "addr:full":"Carrer de Sant Albert Magne, 6 Esplugues Llobregat Barcelona 08950",
    "addr:housenumber":"6",
    "addr:postcode":"08950",
    "addr:street":"Carrer De Sant Albert Magne",
    "iso:country":"ES",
    "sg:address":"Carrer de Sant Albert Magne, 6",
    "sg:city":"Esplugues Llobregat",
    "sg:orig_category":"Copas, Insignias, Trofeos",
    "sg:phone":"+34 934 73 03 70",
    "sg:postcode":"08950",
    "sg:province":"Barcelona",
    "wof:name":"Pujol Pujol Miguel",
    "wof:placetype":"venue"
},
  "geometry": {"coordinates":[2.0876939297,41.3707427979],"type":"Point"}
}