{
  "type": "Feature",
  "properties": {
    "addr:full":"Carrer de Diputacio, 132 Barcelona Barcelona 08015",
    "addr:housenumber":"132",
    "addr:postcode":"08015",
    "addr:street":"Carrer De Diputacio",
    "iso:country":"ES",
    "sg:address":"Carrer de Diputacio, 132",
    "sg:city":"Barcelona",
    "sg:orig_category":"Chapister\u00cda",
    "sg:phone":"+34 934 54 63 13",
    "sg:postcode":"08015",
    "sg:province":"Barcelona",
    "wof:name":"Tallers Granvia, Scp",
    "wof:placetype":"venue"
},
  "geometry": {"coordinates":[2.1566970348,41.3824234009],"type":"Point"}
}