{
  "type": "Feature",
  "properties": {
    "iso:country":"ES",
    "sg:address":"Calle de Domingo Perez Del Val, 2",
    "sg:city":"Madrid",
    "sg:orig_category":"Empresas De Carpinter\u00cda De Madera",
    "sg:phone":"+34 914 74 64 33",
    "sg:postcode":"28045",
    "sg:province":"Madrid",
    "wof:name":"Armada Pierruguez Arturo",
    "wof:placetype":"venue"
},
  "geometry": {"coordinates":[-3.6960513592,40.3934707642],"type":"Point"}
}