{
  "type": "Feature",
  "properties": {
    "iso:country":"ES",
    "sg:address":"Pla\u00c7 Major, 19",
    "sg:city":"Lliria",
    "sg:orig_category":"Farmacias",
    "sg:phone":"+34 962 78 03 70",
    "sg:postcode":"46160",
    "sg:province":"Valencia",
    "wof:name":"Farmacia Cerda C.b.",
    "wof:placetype":"venue"
},
  "geometry": {"coordinates":[-0.596446991,39.6259765625],"type":"Point"}
}