{
  "type": "Feature",
  "properties": {
    "addr:full":"Pase Doctor Torres Villarroel, 20 Salamanca Salamanca 37005",
    "addr:housenumber":"20",
    "addr:postcode":"37005",
    "addr:street":"Doctor Torres Villarroel",
    "iso:country":"ES",
    "sg:address":"Pase Doctor Torres Villarroel, 20",
    "sg:city":"Salamanca",
    "sg:orig_category":"Perfumer\u00cda (al Por Menor)",
    "sg:phone":"+34 923 22 73 63",
    "sg:postcode":"37005",
    "sg:province":"Salamanca",
    "wof:name":"Promotora De Tiendas Droper S.l.",
    "wof:placetype":"venue"
},
  "geometry": {"coordinates":[-5.6632599831,40.9718933105],"type":"Point"}
}