{
  "type": "Feature",
  "properties": {
    "addr:full":"Calle de Puente De Muerte Y Vida (del), 2 Segovia Segovia 40005",
    "addr:housenumber":"2",
    "addr:postcode":"40005",
    "addr:street":"Calle De Puente De Muerte Y Vida Del",
    "iso:country":"ES",
    "sg:address":"Calle de Puente De Muerte Y Vida (del), 2",
    "sg:city":"Segovia",
    "sg:orig_category":"Juegos Y Juguetes (al Por Menor)",
    "sg:phone":"+34 921 43 43 35",
    "sg:postcode":"40005",
    "sg:province":"Segovia",
    "sg:website":"www.tiendas-asi.com",
    "wof:name":"Pe\u00f1as Escobar Ana",
    "wof:placetype":"venue"
},
  "geometry": {"coordinates":[-4.1165018082,40.9447555542],"type":"Point"}
}