{
  "type": "Feature",
  "properties": {
    "addr:full":"Calle de Carrabahabon, Km. 0012,0 Cogeces Monte Valladolid 47313",
    "addr:postcode":"47313",
    "addr:street":"Calle De Carrabahabon Km. 0012,0 Cogeces",
    "iso:country":"ES",
    "sg:address":"Calle de Carrabahabon, Km. 0012,0",
    "sg:city":"Cogeces Monte",
    "sg:orig_category":"Frutas Y Legumbres Frescas (al Por Mayor)",
    "sg:phone":"+34 983 69 93 55",
    "sg:postcode":"47313",
    "sg:province":"Valladolid",
    "wof:name":"Productos Naturales Agricolas S.l.",
    "wof:placetype":"venue"
},
  "geometry": {"coordinates":[-4.3139119148,41.5085067749],"type":"Point"}
}