{
  "type": "Feature",
  "properties": {
    "iso:country":"ES",
    "sg:address":"Carrer de Alou, 18",
    "sg:city":"S. Boi Llobregat",
    "sg:orig_category":"Partidos Pol\u00cdticos",
    "sg:phone":"+34 936 54 49 01",
    "sg:postcode":"08830",
    "sg:province":"Barcelona",
    "wof:name":"Partit Socialista Unificat De Catalunya",
    "wof:placetype":"venue"
},
  "geometry": {"coordinates":[2.0440020561,41.3468437195],"type":"Point"}
}