{
  "type": "Feature",
  "properties": {
    "addr:full":"Calle de Sevilla, S/n Peligros Granada 18210",
    "addr:housenumber":"s / n",
    "addr:postcode":"18210",
    "addr:street":"Calle De Sevilla",
    "iso:country":"ES",
    "sg:address":"Calle de Sevilla, S/n",
    "sg:city":"Peligros",
    "sg:orig_category":"Agentes, Concesionarios Y Sucursales De Veh\u00cdculos",
    "sg:phone":"+34 958 40 08 53",
    "sg:postcode":"18210",
    "sg:province":"Granada",
    "wof:name":"Mora Ruiz Joaquin",
    "wof:placetype":"venue"
},
  "geometry": {"coordinates":[-3.6239690781,37.2346382141],"type":"Point"}
}