{
  "type": "Feature",
  "properties": {
    "iso:country":"ES",
    "sg:address":"Calle de Menacho, 28",
    "sg:city":"Badajoz",
    "sg:orig_category":"Psic\u00d3logos",
    "sg:phone":"+34 924 22 28 38",
    "sg:postcode":"06001",
    "sg:province":"Badajoz",
    "wof:name":"Talavera Zamora Angeles",
    "wof:placetype":"venue"
},
  "geometry": {"coordinates":[-6.9743318558,38.8770217896],"type":"Point"}
}