{
  "type": "Feature",
  "properties": {
    "iso:country":"ES",
    "sg:address":"Avda Portugal, 6",
    "sg:city":"Zamora",
    "sg:orig_category":"Ropa Para Se\u00d1oras Y Caballeros (al Por Menor)",
    "sg:phone":"+34 980 53 39 02",
    "sg:postcode":"49015",
    "sg:province":"Zamora",
    "wof:name":"Barba Pardal S.l.",
    "wof:placetype":"venue"
},
  "geometry": {"coordinates":[-5.7405920029,41.5066871643],"type":"Point"}
}