{
  "type": "Feature",
  "properties": {
    "iso:country":"ES",
    "sg:address":"Tudela, 16",
    "sg:city":"Iru\u00f1a",
    "sg:orig_category":"Ense\u00d1ante, Direcci\u00d3n",
    "sg:phone":"+34 948 24 91 63",
    "sg:postcode":"31003",
    "sg:province":"Navarra",
    "wof:name":"Goizueta Zarag\u00fceta Jesus",
    "wof:placetype":"venue"
},
  "geometry": {"coordinates":[-1.6440830231,42.8118553162],"type":"Point"}
}