{
  "type": "Feature",
  "properties": {
    "iso:country":"ES",
    "sg:address":"Calle de Rio Tera, 2",
    "sg:city":"Soria",
    "sg:orig_category":"Carnicer\u00cdas, Carnicer\u00cdas",
    "sg:phone":"+34 975 22 17 80",
    "sg:postcode":"42004",
    "sg:province":"Soria",
    "wof:name":"Ciria Morales Martin",
    "wof:placetype":"venue"
},
  "geometry": {"coordinates":[-2.474216938,41.7599220276],"type":"Point"}
}