{
  "type": "Feature",
  "properties": {
    "addr:full":"Calle de Fernando El Catolico, 56 Riba-roja Turia Valencia 46190",
    "addr:housenumber":"56",
    "addr:postcode":"46190",
    "addr:street":"Calle De Fernando El Catolico",
    "iso:country":"ES",
    "sg:address":"Calle de Fernando El Catolico, 56",
    "sg:city":"Riba-roja Turia",
    "sg:orig_category":"Peluquer\u00cdas, Peluquer\u00cda Mixta",
    "sg:phone":"+34 961 65 34 25",
    "sg:postcode":"46190",
    "sg:province":"Valencia",
    "wof:name":"Cucciardi Oliet Carlos",
    "wof:placetype":"venue"
},
  "geometry": {"coordinates":[-0.5698940158,39.5458450317],"type":"Point"}
}