{
  "type": "Feature",
  "properties": {
    "iso:country":"ES",
    "sg:address":"Carr San Jorge, 2",
    "sg:city":"Oliva",
    "sg:orig_category":"Reposter\u00cdas",
    "sg:phone":"+34 962 85 05 70",
    "sg:postcode":"46780",
    "sg:province":"Valencia",
    "wof:name":"Camopan Safor S.l",
    "wof:placetype":"venue"
},
  "geometry": {"coordinates":[-0.1179220006,38.9189491272],"type":"Point"}
}