{
  "type": "Feature",
  "properties": {
    "iso:country":"ES",
    "sg:address":"Calle de Alba (del), 8",
    "sg:city":"Marbella",
    "sg:orig_category":"Ense\u00d1anza: Idiomas",
    "sg:phone":"+34 952 92 40 97",
    "sg:postcode":"29600",
    "sg:province":"M\u00e1laga",
    "wof:name":"La Escuela Ac Sc",
    "wof:placetype":"venue"
},
  "geometry": {"coordinates":[-4.8811078072,36.5122146606],"type":"Point"}
}