{
  "type": "Feature",
  "properties": {
    "addr:full":"Calle de Pablo Picasso Kalea, 7 Gernika-lumo Vizcaya 48300",
    "addr:housenumber":"7",
    "addr:postcode":"48300",
    "addr:street":"Calle De Pablo Picasso Kalea",
    "iso:country":"ES",
    "sg:address":"Calle de Pablo Picasso Kalea, 7",
    "sg:city":"Gernika-lumo",
    "sg:orig_category":"M\u00c9dicos: Oftalmolog\u00cda",
    "sg:phone":"+34 946 25 04 28",
    "sg:postcode":"48300",
    "sg:province":"Vizcaya",
    "sg:website":"www.paginasamarillas.es",
    "wof:name":"Uribarrena Barrecheguren Javier",
    "wof:placetype":"venue"
},
  "geometry": {"coordinates":[-2.5366230011,43.3311347961],"type":"Point"}
}