{
  "type": "Feature",
  "properties": {
    "iso:country":"ES",
    "sg:address":"Calle de Don Tomas, 10",
    "sg:city":"Motilla Palancar",
    "sg:orig_category":"Iglesia Cat\u00d3lica",
    "sg:phone":"+34 969 33 14 77",
    "sg:postcode":"16200",
    "sg:province":"Cuenca",
    "wof:name":"Parroquia San Gil Uno",
    "wof:placetype":"venue"
},
  "geometry": {"coordinates":[-1.9096226692,39.5608253479],"type":"Point"}
}