{
  "type": "Feature",
  "properties": {
    "iso:country":"ES",
    "sg:address":"Calle de Comandante Vallespin, 28",
    "sg:city":"Oviedo",
    "sg:orig_category":"Universidades",
    "sg:phone":"+34 985 25 89 62",
    "sg:postcode":"33013",
    "sg:province":"Asturias",
    "sg:website":"www.mavicesbir.com",
    "wof:name":"Gutierrez Villar Maria Victoria",
    "wof:placetype":"venue"
},
  "geometry": {"coordinates":[-5.8612265587,43.3629150391],"type":"Point"}
}