{
  "type": "Feature",
  "properties": {
    "iso:country":"ES",
    "sg:address":"Calle de Arrabal, 94",
    "sg:city":"Mas Matas",
    "sg:orig_category":"Empresas De Desmonte",
    "sg:phone":"+34 978 84 83 95",
    "sg:postcode":"44564",
    "sg:province":"Teruel",
    "wof:name":"Ezague S.l.",
    "wof:placetype":"venue"
},
  "geometry": {"coordinates":[-0.2442145944,40.8338737488],"type":"Point"}
}