{
  "type": "Feature",
  "properties": {
    "iso:country":"ES",
    "sg:address":"Calle de Santiago, S/n",
    "sg:city":"Villalba De Los Alcores",
    "sg:orig_category":"Material Y Herramientas Agr\u00cdcolas",
    "sg:phone":"+34 983 72 15 15",
    "sg:postcode":"47639",
    "sg:province":"Valladolid",
    "wof:name":"Equipos Ganaderos S. A.",
    "wof:placetype":"venue"
},
  "geometry": {"coordinates":[-4.8593888283,41.8649559021],"type":"Point"}
}