{
  "type": "Feature",
  "properties": {
    "iso:country":"ES",
    "sg:address":"Calle de Santa Rita, 8",
    "sg:city":"Madrid",
    "sg:orig_category":"Peluquer\u00cdas, Peluquer\u00cda Mixta",
    "sg:phone":"+34 914 15 97 46",
    "sg:postcode":"28002",
    "sg:province":"Madrid",
    "wof:name":"Fernandez Romero Juan Alberto",
    "wof:placetype":"venue"
},
  "geometry": {"coordinates":[-3.6678259373,40.4452819824],"type":"Point"}
}