{
  "type": "Feature",
  "properties": {
    "addr:full":"Pla\u00c7 Major, Pla\u00c7a, 41 Casco Urbano Valencia 46760",
    "addr:housenumber":"41",
    "addr:postcode":"46760",
    "addr:street":"Plac\u0327A",
    "iso:country":"ES",
    "sg:address":"Pla\u00c7 Major, Pla\u00c7a, 41",
    "sg:city":"Casco Urbano",
    "sg:orig_category":"Aguas (distribuci\u00d3n, Servicios)",
    "sg:phone":"+34 962 82 20 18",
    "sg:postcode":"46760",
    "sg:province":"Valencia",
    "wof:name":"Aquagest Levante S A",
    "wof:placetype":"venue"
},
  "geometry": {"coordinates":[-0.3768048882,39.4702377319],"type":"Point"}
}