{
  "type": "Feature",
  "properties": {
    "addr:full":"Avda Casta\u00d1eda, S/n Santander Cantabria 39005",
    "addr:housenumber":"s / n",
    "addr:postcode":"39005",
    "addr:street":"Avda Castan\u0303Eda",
    "iso:country":"ES",
    "sg:address":"Avda Casta\u00d1eda, S/n",
    "sg:city":"Santander",
    "sg:orig_category":"Restaurantes",
    "sg:phone":"+34 942 28 00 06",
    "sg:postcode":"39005",
    "sg:province":"Cantabria",
    "wof:name":"Chiringuito Rema S.l.",
    "wof:placetype":"venue"
},
  "geometry": {"coordinates":[-3.788944006,43.4757614136],"type":"Point"}
}