{
  "type": "Feature",
  "properties": {
    "iso:country":"ES",
    "sg:address":"Calle de Bajada De San Vicente, S/n",
    "sg:city":"Albacete",
    "sg:orig_category":"Autob\u00das (explotaci\u00d3n Y Servicios De)",
    "sg:phone":"+34 967 52 29 65",
    "sg:postcode":"02006",
    "sg:province":"Albacete",
    "wof:name":"Granda Garrido Ignacio",
    "wof:placetype":"venue"
},
  "geometry": {"coordinates":[-1.8430855274,38.9862937927],"type":"Point"}
}