{
  "type": "Feature",
  "properties": {
    "addr:full":"Pase Serapio Mugica De, 8 Donostia-san Sebastian Guip\u00f9zcoa 20016",
    "addr:housenumber":"8",
    "addr:postcode":"20016",
    "addr:street":"Serapio Mugica De",
    "iso:country":"ES",
    "sg:address":"Pase Serapio Mugica De, 8",
    "sg:city":"Donostia-san Sebastian",
    "sg:orig_category":"Ense\u00d1anza Agr\u00cdcola",
    "sg:phone":"+34 943 39 90 42",
    "sg:postcode":"20016",
    "sg:province":"Guip\u00f9zcoa",
    "wof:name":"Fundacion Social Y Cultural Kutxa",
    "wof:placetype":"venue"
},
  "geometry": {"coordinates":[-1.9452079535,43.3222961426],"type":"Point"}
}