{
  "type": "Feature",
  "properties": {
    "iso:country":"ES",
    "sg:address":"Calle de Cruz De Piedra, 126",
    "sg:city":"Yecla",
    "sg:orig_category":"Molduras, Junquillos, Listones Y Molduras Perforadas",
    "sg:phone":"+34 968 79 63 54",
    "sg:postcode":"30510",
    "sg:province":"Murcia",
    "wof:name":"Mu\u00f1oz Garcia Constantino",
    "wof:placetype":"venue"
},
  "geometry": {"coordinates":[-1.1077202559,38.608959198],"type":"Point"}
}