{
  "type": "Feature",
  "properties": {
    "iso:country":"ES",
    "sg:address":"Calle de Puente Colgante, 11",
    "sg:city":"Valladolid",
    "sg:orig_category":"Clubes, Asociaciones De Ocio",
    "sg:phone":"+34 983 22 13 42",
    "sg:postcode":"47007",
    "sg:province":"Valladolid",
    "wof:name":"Martinez Sebastian Maria Luisa",
    "wof:placetype":"venue"
},
  "geometry": {"coordinates":[-4.7327518463,41.6409225464],"type":"Point"}
}