{
  "type": "Feature",
  "properties": {
    "addr:full":"Calle de Almirante Cadarso, 5 Valencia Valencia 46005",
    "addr:housenumber":"5",
    "addr:postcode":"46005",
    "addr:street":"Calle De Almirante Cadarso",
    "iso:country":"ES",
    "sg:address":"Calle de Almirante Cadarso, 5",
    "sg:city":"Valencia",
    "sg:orig_category":"Abogados",
    "sg:phone":"+34 963 95 53 07",
    "sg:postcode":"46005",
    "sg:province":"Valencia",
    "wof:name":"Ortu\u00f1o Montesinos Adolfo",
    "wof:placetype":"venue"
},
  "geometry": {"coordinates":[-0.368788898,39.466381073],"type":"Point"}
}