{
  "type": "Feature",
  "properties": {
    "iso:country":"ES",
    "sg:address":"Avda Orense (de), 8",
    "sg:city":"San Sebastian De Los Reyes",
    "sg:orig_category":"Sociedades, Compa\u00d1\u00cdas Aseguradoras",
    "sg:phone":"+34 916 54 03 79",
    "sg:postcode":"28700",
    "sg:province":"Madrid",
    "wof:name":"Morales Broker S.l",
    "wof:placetype":"venue"
},
  "geometry": {"coordinates":[-3.6276540756,40.5605392456],"type":"Point"}
}