{
  "type": "Feature",
  "properties": {
    "addr:full":"Calle de Cordoba, S/n Palmones C\u00e1diz 11379",
    "addr:housenumber":"s / n",
    "addr:postcode":"11379",
    "addr:street":"Calle De Cordoba;Ca\u0301Diz",
    "iso:country":"ES",
    "sg:address":"Calle de Cordoba, S/n",
    "sg:city":"Palmones",
    "sg:orig_category":"Asociaciones Y Clubs Deportivos",
    "sg:phone":"+34 956 67 84 03",
    "sg:postcode":"11379",
    "sg:province":"C\u00e1diz",
    "wof:name":"Juventud Popular De Palmones Club De Futbol",
    "wof:placetype":"venue"
},
  "geometry": {"coordinates":[-5.4354553223,36.1758880615],"type":"Point"}
}