{
  "type": "Feature",
  "properties": {
    "iso:country":"ES",
    "sg:address":"Calle de Virgen Del Castillo, 10",
    "sg:city":"Valencia De Don Juan",
    "sg:orig_category":"Cajas Para Embalar",
    "sg:phone":"+34 987 75 25 63",
    "sg:postcode":"24200",
    "sg:province":"Le\u00f3n",
    "wof:name":"Caja Rural De Zamora",
    "wof:placetype":"venue"
},
  "geometry": {"coordinates":[-5.5207052231,42.2926902771],"type":"Point"}
}