{
  "type": "Feature",
  "properties": {
    "iso:country":"ES",
    "sg:address":"Av Mare De Deu De Bellvitge, 293",
    "sg:city":"Hospitalet Llobregat",
    "sg:orig_category":"Artes Gr\u00c1ficas, Artes Pl\u00c1sticas: Material Y Suministros (al Por Menor)",
    "sg:phone":"+34 932 61 24 47",
    "sg:postcode":"08907",
    "sg:province":"Barcelona",
    "wof:name":"Mirabet Marti Gabriel",
    "wof:placetype":"venue"
},
  "geometry": {"coordinates":[2.1079950333,41.3476676941],"type":"Point"}
}