{
  "type": "Feature",
  "properties": {
    "addr:full":"Avda Buenos Aires, 80 Lalin Pontevedra 36500",
    "addr:housenumber":"80",
    "addr:postcode":"36500",
    "addr:street":"Avda Buenos Aires",
    "iso:country":"ES",
    "sg:address":"Avda Buenos Aires, 80",
    "sg:city":"Lalin",
    "sg:orig_category":"Centros Comerciales Y Grandes Tiendas",
    "sg:phone":"+34 986 78 74 59",
    "sg:postcode":"36500",
    "sg:province":"Pontevedra",
    "wof:name":"Gonzalez Gonzalez Maria De La Luz",
    "wof:placetype":"venue"
},
  "geometry": {"coordinates":[-8.1126489639,42.6599311829],"type":"Point"}
}