{
  "type": "Feature",
  "properties": {
    "addr:full":"Calle de Puerto De Oncala, 5 Sevilla Sevilla 41006",
    "addr:housenumber":"5",
    "addr:postcode":"41006",
    "addr:street":"Calle De Puerto De Oncala",
    "iso:country":"ES",
    "sg:address":"Calle de Puerto De Oncala, 5",
    "sg:city":"Sevilla",
    "sg:classifiers":[
        {
            "category":"Personal",
            "subcategory":"Barber",
            "type":"Services"
        }
    ],
    "sg:phone":"+34 954 65 57 13",
    "sg:postcode":"41006",
    "sg:province":"Sevilla",
    "sg:tags":[
        "caballeros",
        "de",
        "peluqueros"
    ],
    "wof:name":"Toledo Garcia Manuel",
    "wof:placetype":"venue"
},
  "geometry": {"coordinates":[-5.9527430534,37.3762435913],"type":"Point"}
}