{
  "type": "Feature",
  "properties": {
    "addr:full":"Carr Triquet, 3 Sineu Islas Baleares 07510",
    "addr:housenumber":"3",
    "addr:postcode":"07510",
    "addr:street":"Carr Triquet",
    "iso:country":"ES",
    "sg:address":"Carr Triquet, 3",
    "sg:city":"Sineu",
    "sg:orig_category":"Cooperativas Agr\u00cdcolas",
    "sg:phone":"+34 971 52 03 24",
    "sg:postcode":"07510",
    "sg:province":"Islas Baleares",
    "wof:name":"Cooperativa De Productors D'aliments Ecologics",
    "wof:placetype":"venue"
},
  "geometry": {"coordinates":[3.0102500916,39.6449584961],"type":"Point"}
}