{
  "type": "Feature",
  "properties": {
    "addr:full":"Cercado, S/n San Andres Santa Cruz De Tenerife 38120",
    "addr:housenumber":"s / n",
    "addr:postcode":"38120",
    "addr:street":"Cercado",
    "iso:country":"ES",
    "sg:address":"Cercado, S/n",
    "sg:city":"San Andres",
    "sg:orig_category":"Orquestas Cl\u00c1sicas, Asociaciones De M\u00dasica, Coros Y Corales",
    "sg:phone":"+34 922 59 10 84",
    "sg:postcode":"38120",
    "sg:province":"Santa Cruz De Tenerife",
    "wof:name":"Banda De Musica Amigos Del Arte San Andres",
    "wof:placetype":"venue"
},
  "geometry": {"coordinates":[-16.1940078735,28.5062446594],"type":"Point"}
}