{
  "type": "Feature",
  "properties": {
    "iso:country":"ES",
    "sg:address":"Carr Llaurador Valencia, 2",
    "sg:city":"Massamagrell",
    "sg:orig_category":"Peluqueros: De Se\u00d1oras",
    "sg:phone":"+34 961 45 01 08",
    "sg:postcode":"46130",
    "sg:province":"Valencia",
    "wof:name":"Cordoba Benitez Ramona",
    "wof:placetype":"venue"
},
  "geometry": {"coordinates":[-0.3351289928,39.568611145],"type":"Point"}
}