{
  "type": "Feature",
  "properties": {
    "iso:country":"ES",
    "sg:address":"La Virgen, S/n",
    "sg:city":"Panticosa",
    "sg:orig_category":"Abogados",
    "sg:phone":"+34 974 48 70 23",
    "sg:postcode":"22661",
    "sg:province":"Huesca",
    "wof:name":"Ruiz Galbe Jose Antonio",
    "wof:placetype":"venue"
},
  "geometry": {"coordinates":[-0.2867589891,42.7238616943],"type":"Point"}
}