{
  "type": "Feature",
  "properties": {
    "iso:country":"ES",
    "sg:address":"C\u00aa Valencia, S/n",
    "sg:city":"Teruel",
    "sg:orig_category":"Alumbrados",
    "sg:phone":"+34 978 60 73 12",
    "sg:postcode":"44002",
    "sg:province":"Teruel",
    "wof:name":"Santiago Cercos Sanchez Y Otra Cdad.",
    "wof:placetype":"venue"
},
  "geometry": {"coordinates":[-1.1045490503,40.3420944214],"type":"Point"}
}