{
  "type": "Feature",
  "properties": {
    "addr:full":"Calle de Poeta Juan Ramon Jimenez, 11 Cordoba C\u00f3rdoba 14012",
    "addr:housenumber":"11",
    "addr:postcode":"14012",
    "addr:street":"Calle De Poeta Juan Ramon Jimenez;Co\u0301Rdoba",
    "iso:country":"ES",
    "sg:address":"Calle de Poeta Juan Ramon Jimenez, 11",
    "sg:city":"Cordoba",
    "sg:orig_category":"Arquitectos",
    "sg:phone":"+34 957 27 73 09",
    "sg:postcode":"14012",
    "sg:province":"C\u00f3rdoba",
    "wof:name":"Valdelomar De Prado Luis",
    "wof:placetype":"venue"
},
  "geometry": {"coordinates":[-4.7923440933,37.9014778137],"type":"Point"}
}