{
  "type": "Feature",
  "properties": {
    "addr:full":"Avda Mediterraneo, 47 Madrid Madrid 28007",
    "addr:housenumber":"47",
    "addr:postcode":"madrid;28007",
    "addr:street":"Avda Mediterraneo",
    "iso:country":"ES",
    "sg:address":"Avda Mediterraneo, 47",
    "sg:city":"Madrid",
    "sg:orig_category":"Centros M\u00c9dicos Y Sociales, Dispensarios",
    "sg:phone":"+34 914 09 58 12",
    "sg:postcode":"28007",
    "sg:province":"Madrid",
    "wof:name":"Gutierrez Santos Angel",
    "wof:placetype":"venue"
},
  "geometry": {"coordinates":[-3.6686871052,40.4069519043],"type":"Point"}
}