{
  "type": "Feature",
  "properties": {
    "iso:country":"ES",
    "sg:address":"Carrer de Diagonal, 75",
    "sg:city":"Can Sant Joan",
    "sg:orig_category":"Promotores Constructores",
    "sg:phone":"+34 935 65 01 94",
    "sg:postcode":"08110",
    "sg:province":"Barcelona",
    "wof:name":"Montbif S.l.",
    "wof:placetype":"venue"
},
  "geometry": {"coordinates":[2.1817660332,41.4890899658],"type":"Point"}
}