{
  "type": "Feature",
  "properties": {
    "addr:full":"Trva Motilla, 20 Fuensalda\u00d1a Valladolid 47194",
    "addr:housenumber":"20",
    "addr:postcode":"47194",
    "addr:street":"Trva Motilla",
    "iso:country":"ES",
    "sg:address":"Trva Motilla, 20",
    "sg:city":"Fuensalda\u00d1a",
    "sg:orig_category":"Comerciantes Al Por Mayor De Vinos, Licores Y Alcoholes",
    "sg:phone":"+34 983 58 30 53",
    "sg:postcode":"47194",
    "sg:province":"Valladolid",
    "wof:name":"Parrado Garcia Felix",
    "wof:placetype":"venue"
},
  "geometry": {"coordinates":[-4.7653517723,41.7060127258],"type":"Point"}
}