{
  "type": "Feature",
  "properties": {
    "addr:full":"Carrer de Santuari, 49 Barcelona Barcelona 08032",
    "addr:housenumber":"49",
    "addr:postcode":"08032",
    "addr:street":"Carrer De Santuari",
    "iso:country":"ES",
    "sg:address":"Carrer de Santuari, 49",
    "sg:city":"Barcelona",
    "sg:orig_category":"Postigos, Persianas Y Celos\u00cdas",
    "sg:phone":"+34 934 20 66 10",
    "sg:postcode":"08032",
    "sg:province":"Barcelona",
    "wof:name":"Lopez Romero Aurelio",
    "wof:placetype":"venue"
},
  "geometry": {"coordinates":[2.1522290707,41.4207267761],"type":"Point"}
}