{
  "type": "Feature",
  "properties": {
    "addr:full":"Calle de La Bondad, 7 Barakaldo Vizcaya 48901",
    "addr:housenumber":"7",
    "addr:postcode":"48901",
    "addr:street":"Calle De La Bondad",
    "iso:country":"ES",
    "sg:address":"Calle de La Bondad, 7",
    "sg:city":"Barakaldo",
    "sg:orig_category":"Cl\u00cdnicas Dentales",
    "sg:phone":"+34 944 37 42 15",
    "sg:postcode":"48901",
    "sg:province":"Vizcaya",
    "wof:name":"Clinica Odontologica Barakaldo. Eduardo Sanz Gonzalez",
    "wof:placetype":"venue"
},
  "geometry": {"coordinates":[-2.992153883,43.2972373962],"type":"Point"}
}