{
  "type": "Feature",
  "properties": {
    "addr:full":"Calle de Barberan Y Collar, 3 Getafe Madrid 28903",
    "addr:housenumber":"3",
    "addr:postcode":"28903",
    "addr:street":"Calle De Barberan Y Collar",
    "iso:country":"ES",
    "sg:address":"Calle de Barberan Y Collar, 3",
    "sg:city":"Getafe",
    "sg:orig_category":"Confecci\u00d3n (fabricaci\u00d3n, Al Por Mayor)",
    "sg:phone":"+34 916 95 94 57",
    "sg:postcode":"28903",
    "sg:province":"Madrid",
    "wof:name":"Sanchez Ruiz-gollerizo Manuel",
    "wof:placetype":"venue"
},
  "geometry": {"coordinates":[-3.7250893116,40.3112831116],"type":"Point"}
}