{
  "type": "Feature",
  "properties": {
    "iso:country":"ES",
    "sg:address":"Trva San Roque, 5",
    "sg:city":"Toledo",
    "sg:orig_category":"Arreglo, Reparaci\u00d3n, Piezas Sueltas De Televisi\u00d3n, V\u00cddeo, Hi",
    "sg:phone":"+34 925 22 01 83",
    "sg:postcode":"45003",
    "sg:province":"Toledo",
    "wof:name":"Fernandez Garcia Pablo",
    "wof:placetype":"venue"
},
  "geometry": {"coordinates":[-4.0220518112,39.871509552],"type":"Point"}
}