{
  "type": "Feature",
  "properties": {
    "addr:full":"Ctra. Illora-estacion, 7 Illora Granada 18260",
    "addr:housenumber":"7",
    "addr:postcode":"18260",
    "addr:street":"Ctra. Illora-Estacion",
    "iso:country":"ES",
    "sg:address":"Ctra. Illora-estacion, 7",
    "sg:city":"Illora",
    "sg:orig_category":"Distribuci\u00d3n De Petr\u00d3leo Y Derivados",
    "sg:phone":"+34 958 46 30 56",
    "sg:postcode":"18260",
    "sg:province":"Granada",
    "sg:website":"www.cepsa.es",
    "wof:name":"Estacin De Servicio Ele Illora S.l",
    "wof:placetype":"venue"
},
  "geometry": {"coordinates":[-3.8784790039,37.285774231],"type":"Point"}
}