{
  "type": "Feature",
  "properties": {
    "iso:country":"ES",
    "sg:address":"Pase Parque Del, 115",
    "sg:city":"Sotogrande",
    "sg:orig_category":"Agencias Y Agentes Comerciales, Representantes",
    "sg:phone":"+34 956 79 48 23",
    "sg:postcode":"11310",
    "sg:province":"C\u00e1diz",
    "wof:name":"San Juan 36 Sl",
    "wof:placetype":"venue"
},
  "geometry": {"coordinates":[-5.2829370499,36.2767448425],"type":"Point"}
}