{
  "type": "Feature",
  "properties": {
    "iso:country":"ES",
    "sg:address":"Ctra Alija Del Infantado, 70",
    "sg:city":"Ba\u00d1eza",
    "sg:orig_category":"Patatas (al Por Mayor)",
    "sg:phone":"+34 987 64 16 54",
    "sg:postcode":"24750",
    "sg:province":"Le\u00f3n",
    "wof:name":"Patatas Turrado S.l.",
    "wof:placetype":"venue"
},
  "geometry": {"coordinates":[-5.8933901787,42.288269043],"type":"Point"}
}