{
  "type": "Feature",
  "properties": {
    "iso:country":"ES",
    "sg:address":"Avda Reina Mercedes, 21",
    "sg:city":"Sevilla",
    "sg:orig_category":"Peluquer\u00cdas, Peluquer\u00cda Mixta",
    "sg:phone":"+34 954 62 12 01",
    "sg:postcode":"41012",
    "sg:province":"Sevilla",
    "sg:website":"www.hairdreams.com",
    "wof:name":"Gutierrez Claramunt Angeles",
    "wof:placetype":"venue"
},
  "geometry": {"coordinates":[-5.9860019684,37.3605613708],"type":"Point"}
}