{
  "type": "Feature",
  "properties": {
    "addr:full":"Calle de Calderon De La Barca (de), 11 Navalcarnero Madrid 28600",
    "addr:housenumber":"11",
    "addr:postcode":"28600",
    "addr:street":"Calle De Calderon De La Barca De",
    "iso:country":"ES",
    "sg:address":"Calle de Calderon De La Barca (de), 11",
    "sg:city":"Navalcarnero",
    "sg:orig_category":"Caf\u00c9s, Bares, Cervecer\u00cdas",
    "sg:phone":"+34 918 11 27 00",
    "sg:postcode":"28600",
    "sg:province":"Madrid",
    "wof:name":"Gamboa Iba\u00f1ez Hipolito",
    "wof:placetype":"venue"
},
  "geometry": {"coordinates":[-4.0131793022,40.2861404419],"type":"Point"}
}