{
  "type": "Feature",
  "properties": {
    "iso:country":"ES",
    "sg:address":"Calle de Rosario, 4",
    "sg:city":"Albacete",
    "sg:orig_category":"Material Hidr\u00c1ulico",
    "sg:phone":"+34 967 24 00 49",
    "sg:postcode":"02001",
    "sg:province":"Albacete",
    "wof:name":"Saico Inteagua De Construcciones S.a.",
    "wof:placetype":"venue"
},
  "geometry": {"coordinates":[-1.8553689718,38.9955825806],"type":"Point"}
}