{
  "type": "Feature",
  "properties": {
    "addr:full":"Avda Cervantes, 110 Caceres C\u00e1ceres 10005",
    "addr:housenumber":"110",
    "addr:postcode":"10005",
    "addr:street":"Avda Cervantes;Ca\u0301Ceres",
    "iso:country":"ES",
    "sg:address":"Avda Cervantes, 110",
    "sg:city":"Caceres",
    "sg:orig_category":"Cajas De Ahorro",
    "sg:phone":"+34 927 26 02 75",
    "sg:postcode":"10005",
    "sg:province":"C\u00e1ceres",
    "sg:website":"www.cajaextremadura.es",
    "wof:name":"Caja De Ahorros Y Monte De Piedad De Extremadura",
    "wof:placetype":"venue"
},
  "geometry": {"coordinates":[-6.3689889908,39.4573707581],"type":"Point"}
}