{
  "type": "Feature",
  "properties": {
    "iso:country":"ES",
    "sg:address":"Ctra Constantina, Km. 0004,0",
    "sg:city":"Villanueva Rio Y Minas",
    "sg:orig_category":"Agricultura: Abastecimiento Y Cosechado (negocio)",
    "sg:phone":"+34 955 95 34 57",
    "sg:postcode":"41350",
    "sg:province":"Sevilla",
    "wof:name":"Cortijo Miramontes S.a.",
    "wof:placetype":"venue"
},
  "geometry": {"coordinates":[-5.7183542252,37.6519584656],"type":"Point"}
}