{
  "type": "Feature",
  "properties": {
    "addr:full":"Calle de Sierra (de La), 1 Soto Real Madrid 28791",
    "addr:housenumber":"1",
    "addr:postcode":"28791",
    "addr:street":"Calle De Sierra De La",
    "iso:country":"ES",
    "sg:address":"Calle de Sierra (de La), 1",
    "sg:city":"Soto Real",
    "sg:classifiers":[
        {
            "category":"Taxi",
            "type":"Transportation"
        }
    ],
    "sg:phone":"+34 918 47 60 44",
    "sg:postcode":"28791",
    "sg:province":"Madrid",
    "wof:name":"Tablado Alvarez Manuel",
    "wof:placetype":"venue"
},
  "geometry": {"coordinates":[-3.7903635502,40.7523574829],"type":"Point"}
}