{
  "type": "Feature",
  "properties": {
    "iso:country":"ES",
    "sg:address":"Avda Juan Xxiii, 2",
    "sg:city":"Malaga",
    "sg:orig_category":"Herramientas Y Suministros Para Plomeros",
    "sg:phone":"+34 952 31 37 62",
    "sg:postcode":"29003",
    "sg:province":"M\u00e1laga",
    "wof:name":"Diaz Ruiz Purificacion",
    "wof:placetype":"venue"
},
  "geometry": {"coordinates":[-4.4411458969,36.7045822144],"type":"Point"}
}