{
  "type": "Feature",
  "properties": {
    "iso:country":"ES",
    "sg:address":"Calle de Juan Ramon Jimenez, 26",
    "sg:city":"Valencia",
    "sg:orig_category":"Caf\u00c9s, Bares, Cervecer\u00cdas",
    "sg:phone":"+34 963 73 97 54",
    "sg:postcode":"46006",
    "sg:province":"Valencia",
    "wof:name":"Bailo Lopez Jesus",
    "wof:placetype":"venue"
},
  "geometry": {"coordinates":[-0.3753960133,39.4537773132],"type":"Point"}
}