{
  "type": "Feature",
  "properties": {
    "addr:full":"Ctra Aldealengua, Km. 0003,0 Cabrerizos Salamanca 37193",
    "addr:postcode":"37193",
    "addr:street":"Ctra Aldealengua Km. 0003,0",
    "iso:country":"ES",
    "sg:address":"Ctra Aldealengua, Km. 0003,0",
    "sg:city":"Cabrerizos",
    "sg:orig_category":"Empresas De Carpinter\u00cda De Madera",
    "sg:phone":"+34 923 18 23 13",
    "sg:postcode":"37193",
    "sg:province":"Salamanca",
    "wof:name":"Gonzalez Sanchez Enrique",
    "wof:placetype":"venue"
},
  "geometry": {"coordinates":[-5.6213741302,40.9721908569],"type":"Point"}
}