{
  "type": "Feature",
  "properties": {
    "iso:country":"ES",
    "sg:address":"Calle de Puerto De Herrera, 2",
    "sg:city":"Vitoria-gasteiz",
    "sg:orig_category":"Molduras, Junquillos, Listones Y Molduras Perforadas",
    "sg:phone":"+34 945 25 05 83",
    "sg:postcode":"01013",
    "sg:province":"\u00c1lava",
    "wof:name":"Pilar Montoya Montoya",
    "wof:placetype":"venue"
},
  "geometry": {"coordinates":[-2.6701610088,42.8602333069],"type":"Point"}
}