{
  "type": "Feature",
  "properties": {
    "iso:country":"ES",
    "sg:address":"Carrer de Italia, 10",
    "sg:city":"Masnou",
    "sg:orig_category":"Chapister\u00cda",
    "sg:phone":"+34 935 55 51 53",
    "sg:postcode":"08320",
    "sg:province":"Barcelona",
    "wof:name":"Auto Ramber S.l.",
    "wof:placetype":"venue"
},
  "geometry": {"coordinates":[2.3168480396,41.4823265076],"type":"Point"}
}