{
  "type": "Feature",
  "properties": {
    "addr:full":"Carrer de Sant Pere, 13 Terrassa Barcelona 08221",
    "addr:housenumber":"13",
    "addr:postcode":"08221",
    "addr:street":"Carrer De Sant Pere",
    "iso:country":"ES",
    "sg:address":"Carrer de Sant Pere, 13",
    "sg:city":"Terrassa",
    "sg:orig_category":"Caf\u00c9s, Bares, Cervecer\u00cdas",
    "sg:phone":"+34 937 89 20 19",
    "sg:postcode":"08221",
    "sg:province":"Barcelona",
    "wof:name":"Tarasca S.c.p.",
    "wof:placetype":"venue"
},
  "geometry": {"coordinates":[2.0124509335,41.5664634705],"type":"Point"}
}