{
  "type": "Feature",
  "properties": {
    "addr:full":"G.v. Marques Del Turia, 79 Valencia Valencia 46005",
    "addr:housenumber":"79",
    "addr:postcode":"46005",
    "addr:street":"Turia",
    "iso:country":"ES",
    "sg:address":"G.v. Marques Del Turia, 79",
    "sg:city":"Valencia",
    "sg:orig_category":"Confiter\u00cdas, Chocolater\u00cdas (al Por Menor)",
    "sg:phone":"+34 963 33 54 51",
    "sg:postcode":"46005",
    "sg:province":"Valencia",
    "sg:website":"www.valor.es",
    "wof:name":"Chocolates Valor S.a.",
    "wof:placetype":"venue"
},
  "geometry": {"coordinates":[-0.3645449877,39.4690361023],"type":"Point"}
}