{
  "type": "Feature",
  "properties": {
    "iso:country":"ES",
    "sg:address":"Carrer de Cardenal Sentmenat, 37",
    "sg:city":"Barcelona",
    "sg:orig_category":"Ense\u00d1anza: Idiomas",
    "sg:phone":"+34 932 04 63 41",
    "sg:postcode":"08017",
    "sg:province":"Barcelona",
    "sg:website":"www.qualityenglishcompany.com",
    "wof:name":"Snow Bailet Constance",
    "wof:placetype":"venue"
},
  "geometry": {"coordinates":[2.1249480247,41.39818573],"type":"Point"}
}