{
  "type": "Feature",
  "properties": {
    "addr:full":"Rua Vizconde San Alberto Bergondo, S/n Noia La Coru\u00f1a 15200",
    "addr:housenumber":"s / n",
    "addr:postcode":"15200",
    "addr:street":"Rua Vizconde San Alberto Bergondo;La Corun\u0303A",
    "iso:country":"ES",
    "sg:address":"Rua Vizconde San Alberto Bergondo, S/n",
    "sg:city":"Noia",
    "sg:orig_category":"Internados & Ense\u00d1anza Privada",
    "sg:phone":"+34 981 82 05 00",
    "sg:postcode":"15200",
    "sg:province":"La Coru\u00f1a",
    "wof:name":"Colegio Maria Assumpta De Noya Hijas De Jesus Provincia Centro",
    "wof:placetype":"venue"
},
  "geometry": {"coordinates":[-8.8908538818,42.7782440186],"type":"Point"}
}