{
  "type": "Feature",
  "properties": {
    "iso:country":"ES",
    "sg:address":"Calle de Salvador Minguijon, 4",
    "sg:city":"Zaragoza",
    "sg:orig_category":"Alquiler De V\u00cddeo",
    "sg:phone":"+34 976 59 70 20",
    "sg:postcode":"50002",
    "sg:province":"Zaragoza",
    "wof:name":"Fernandez Y Fernandez S.cv.",
    "wof:placetype":"venue"
},
  "geometry": {"coordinates":[-0.8619350195,41.6447563171],"type":"Point"}
}