{
  "type": "Feature",
  "properties": {
    "addr:full":"Calle de Toledo, 2 Fuengirola M\u00e1laga 29640",
    "addr:housenumber":"2",
    "addr:postcode":"29640",
    "addr:street":"Calle De Toledo;Ma\u0301Laga",
    "iso:country":"ES",
    "sg:address":"Calle de Toledo, 2",
    "sg:city":"Fuengirola",
    "sg:orig_category":"Empresas De Carpinter\u00cda De Madera",
    "sg:phone":"+34 952 47 53 95",
    "sg:postcode":"29640",
    "sg:province":"M\u00e1laga",
    "wof:name":"Ruiz Jimenez Jose",
    "wof:placetype":"venue"
},
  "geometry": {"coordinates":[-4.6149611473,36.5564193726],"type":"Point"}
}