{
  "type": "Feature",
  "properties": {
    "iso:country":"ES",
    "sg:address":"Psaj Villagarcia De Arosa, 15",
    "sg:city":"San Sebastian De Los Reyes",
    "sg:orig_category":"Refiner\u00cdas De Petr\u00d3leo",
    "sg:phone":"+34 916 53 76 31",
    "sg:postcode":"28700",
    "sg:province":"Madrid",
    "wof:name":"Disa Peninsula S.l.u.",
    "wof:placetype":"venue"
},
  "geometry": {"coordinates":[-3.6270439625,40.5617828369],"type":"Point"}
}