{
  "type": "Feature",
  "properties": {
    "iso:country":"ES",
    "sg:address":"Calle de Rio Corcoles, 6",
    "sg:city":"Tomelloso",
    "sg:orig_category":"Delegados, Agentes De Tr\u00c1nsito, Auxiliares De Transporte Internacional",
    "sg:phone":"+34 926 51 10 47",
    "sg:postcode":"13700",
    "sg:province":"Ciudad Real",
    "wof:name":"Tranlara S.l.",
    "wof:placetype":"venue"
},
  "geometry": {"coordinates":[-3.0252490044,39.1462287903],"type":"Point"}
}