{
  "type": "Feature",
  "properties": {
    "iso:country":"ES",
    "sg:address":"Calle de Luis Sauquillo, 66",
    "sg:city":"Fuenlabrada",
    "sg:orig_category":"Fabricaci\u00d3n De Ropa De Deportes",
    "sg:phone":"+34 916 15 38 92",
    "sg:postcode":"28944",
    "sg:province":"Madrid",
    "wof:name":"Sport Reybol S.l.",
    "wof:placetype":"venue"
},
  "geometry": {"coordinates":[-3.7990903854,40.2806663513],"type":"Point"}
}