{
  "type": "Feature",
  "properties": {
    "addr:full":"Plaz Cuartel, S/n Campamento C\u00e1diz 11314",
    "addr:housenumber":"s / n",
    "addr:postcode":"11314",
    "addr:street":"Plaz Cuartel;Ca\u0301Diz",
    "iso:country":"ES",
    "sg:address":"Plaz Cuartel, S/n",
    "sg:city":"Campamento",
    "sg:orig_category":"Ense\u00d1anza, Formaci\u00d3n Profesional: Aprendizaje",
    "sg:phone":"+34 956 69 81 91",
    "sg:postcode":"11314",
    "sg:province":"C\u00e1diz",
    "wof:name":"Ayuntamiento",
    "wof:placetype":"venue"
},
  "geometry": {"coordinates":[-5.3786039352,36.178188324],"type":"Point"}
}