{
  "type": "Feature",
  "properties": {
    "addr:full":"Carrer de Joaquim Valls, 36 Barcelona Barcelona 08016",
    "addr:housenumber":"36",
    "addr:postcode":"08016",
    "addr:street":"Carrer De Joaquim Valls",
    "iso:country":"ES",
    "sg:address":"Carrer de Joaquim Valls, 36",
    "sg:city":"Barcelona",
    "sg:orig_category":"Ense\u00d1anza: Comercio, Gesti\u00d3n, Inform\u00c1tica",
    "sg:phone":"+34 932 76 92 63",
    "sg:postcode":"08016",
    "sg:province":"Barcelona",
    "wof:name":"Esteban Barrot Juan Manuel",
    "wof:placetype":"venue"
},
  "geometry": {"coordinates":[2.1818480492,41.4431533813],"type":"Point"}
}