{
  "type": "Feature",
  "properties": {
    "addr:full":"Calle de Ribera, 17 Cintruenigo Navarra 31592",
    "addr:housenumber":"17",
    "addr:postcode":"31592",
    "addr:street":"Calle De Ribera",
    "iso:country":"ES",
    "sg:address":"Calle de Ribera, 17",
    "sg:city":"Cintruenigo",
    "sg:orig_category":"Cueros Y Pieles (al Por Mayor)",
    "sg:phone":"+34 948 81 20 98",
    "sg:postcode":"31592",
    "sg:province":"Navarra",
    "wof:name":"Cintruenigo Piel S. L.",
    "wof:placetype":"venue"
},
  "geometry": {"coordinates":[-1.8052870035,42.0835609436],"type":"Point"}
}