{
  "type": "Feature",
  "properties": {
    "addr:full":"Plaz Espa\u00d1a, S/n Bienvenida Badajoz 06250",
    "addr:housenumber":"s / n",
    "addr:postcode":"06250",
    "addr:street":"Plaz Espan\u0303A",
    "iso:country":"ES",
    "sg:address":"Plaz Espa\u00d1a, S/n",
    "sg:city":"Bienvenida",
    "sg:orig_category":"Administraciones Regionales, Departamentales Y Locales",
    "sg:phone":"+34 924 50 60 11",
    "sg:postcode":"06250",
    "sg:province":"Badajoz",
    "wof:name":"Ayuntamiento De Bienvenida",
    "wof:placetype":"venue"
},
  "geometry": {"coordinates":[-6.2057447433,38.3105697632],"type":"Point"}
}