{
  "type": "Feature",
  "properties": {
    "addr:full":"Calle de Telletxe, 9 Getxo Vizcaya 48990",
    "addr:housenumber":"9",
    "addr:postcode":"48990",
    "addr:street":"Calle De Telletxe",
    "iso:country":"ES",
    "sg:address":"Calle de Telletxe, 9",
    "sg:city":"Getxo",
    "sg:orig_category":"Bisuter\u00cda, Joyer\u00cda, Relojer\u00cda (al Por Menor)",
    "sg:phone":"+34 944 60 72 80",
    "sg:postcode":"48990",
    "sg:province":"Vizcaya",
    "wof:name":"Joyeria-relojeria  Lerbus, S.l.",
    "wof:placetype":"venue"
},
  "geometry": {"coordinates":[-3.0101709366,43.3517913818],"type":"Point"}
}