{
  "type": "Feature",
  "properties": {
    "addr:full":"Calle de Rio Guadalquivir, 1 Parla Madrid 28980",
    "addr:housenumber":"1",
    "addr:postcode":"28980",
    "addr:street":"Calle De Rio Guadalquivir",
    "iso:country":"ES",
    "sg:address":"Calle de Rio Guadalquivir, 1",
    "sg:city":"Parla",
    "sg:orig_category":"Peluquer\u00cdas, Peluquer\u00cda Mixta",
    "sg:phone":"+34 916 05 77 96",
    "sg:postcode":"28980",
    "sg:province":"Madrid",
    "wof:name":"Fernandez Abelleira Ana Belen",
    "wof:placetype":"venue"
},
  "geometry": {"coordinates":[-3.7718200684,40.2409973145],"type":"Point"}
}