{
  "type": "Feature",
  "properties": {
    "addr:full":"Calle de Ventura Rodriguez, 5 Madrid Madrid 28008",
    "addr:housenumber":"5",
    "addr:postcode":"28008",
    "addr:street":"Calle De Ventura Rodriguez",
    "iso:country":"ES",
    "sg:address":"Calle de Ventura Rodriguez, 5",
    "sg:city":"Madrid",
    "sg:orig_category":"Caf\u00c9s, Bares, Cervecer\u00cdas",
    "sg:phone":"+34 915 42 13 17",
    "sg:postcode":"28008",
    "sg:province":"Madrid",
    "wof:name":"Bueno Garcia Jose Luis",
    "wof:placetype":"venue"
},
  "geometry": {"coordinates":[-3.7133738995,40.425743103],"type":"Point"}
}