{
  "type": "Feature",
  "properties": {
    "iso:country":"ES",
    "sg:address":"Ctra Madrid, Km. 0159,4",
    "sg:city":"Alcazaren",
    "sg:orig_category":"Distribuci\u00d3n De Petr\u00d3leo Y Derivados",
    "sg:phone":"+34 983 60 91 47",
    "sg:postcode":"47238",
    "sg:province":"Valladolid",
    "wof:name":"Rico Mateo S.l.",
    "wof:placetype":"venue"
},
  "geometry": {"coordinates":[-4.6759338379,41.3696556091],"type":"Point"}
}