{
  "type": "Feature",
  "properties": {
    "addr:full":"Calle de Elfo, 129 Madrid Madrid 28027",
    "addr:housenumber":"129",
    "addr:postcode":"28027",
    "addr:street":"Calle De Elfo",
    "iso:country":"ES",
    "sg:address":"Calle de Elfo, 129",
    "sg:city":"Madrid",
    "sg:orig_category":"Negocio De Madera",
    "sg:phone":"+34 913 67 12 48",
    "sg:postcode":"28027",
    "sg:province":"Madrid",
    "wof:name":"Maria Dolores Martinez-vara De Rey S. A.",
    "wof:placetype":"venue"
},
  "geometry": {"coordinates":[-3.6440598965,40.4367103577],"type":"Point"}
}