{
  "type": "Feature",
  "properties": {
    "addr:full":"Carrer de Alsina (de L'), 41 Vilassar De Mar Barcelona 08340",
    "addr:housenumber":"41",
    "addr:postcode":"08340",
    "addr:street":"Carrer De Alsina De L '",
    "iso:country":"ES",
    "sg:address":"Carrer de Alsina (de L'), 41",
    "sg:city":"Vilassar De Mar",
    "sg:orig_category":"Ebanister\u00cda",
    "sg:phone":"+34 937 54 01 44",
    "sg:postcode":"08340",
    "sg:province":"Barcelona",
    "wof:name":"Ribes Gelada Joan",
    "wof:placetype":"venue"
},
  "geometry": {"coordinates":[2.3881409168,41.5027198792],"type":"Point"}
}