{
  "type": "Feature",
  "properties": {
    "addr:full":"Crtj Buenavista, S/n Oca\u00f1a Almer\u00eda 04530",
    "addr:housenumber":"s",
    "addr:postcode":"04530",
    "addr:street":"Buenavista;/ N Ocan\u0303A Almeri\u0301A",
    "iso:country":"ES",
    "sg:address":"Crtj Buenavista, S/n",
    "sg:city":"Oca\u00f1a",
    "sg:orig_category":"Agricultores, Agricultores",
    "sg:phone":"+34 950 35 08 19",
    "sg:postcode":"04530",
    "sg:province":"Almer\u00eda",
    "wof:name":"Pe\u00f1a Alcalde S.l.",
    "wof:placetype":"venue"
},
  "geometry": {"coordinates":[-2.7175989151,37.1386604309],"type":"Point"}
}