{
  "type": "Feature",
  "properties": {
    "iso:country":"ES",
    "sg:address":"Calle de Luxemburgo, S/n",
    "sg:city":"Monta\u00e7a Roja",
    "sg:orig_category":"Maquinaria Para Industrias Diversas",
    "sg:phone":"+34 928 51 73 38",
    "sg:postcode":"35580",
    "sg:province":"Las Palmas",
    "wof:name":"Maxorata Recreativa S L",
    "wof:placetype":"venue"
},
  "geometry": {"coordinates":[-13.8307790756,28.8657550812],"type":"Point"}
}