{
  "type": "Feature",
  "properties": {
    "addr:full":"Carrer de Sant Sebastia (de), 47 S. Carles Rapita Tarragona 43540",
    "addr:housenumber":"47",
    "addr:postcode":"43540",
    "addr:street":"Carrer De Sant Sebastia De;S. Carles Rapita",
    "iso:country":"ES",
    "sg:address":"Carrer de Sant Sebastia (de), 47",
    "sg:city":"S. Carles Rapita",
    "sg:orig_category":"Orquestas De Variedades",
    "sg:phone":"+34 977 74 11 50",
    "sg:postcode":"43540",
    "sg:province":"Tarragona",
    "wof:name":"Agrupacion Musical Rapitense",
    "wof:placetype":"venue"
},
  "geometry": {"coordinates":[0.5917667747,40.6214637756],"type":"Point"}
}