{
  "type": "Feature",
  "properties": {
    "iso:country":"ES",
    "sg:address":"Calle de Nueva, 21",
    "sg:city":"Malpartida Caceres",
    "sg:orig_category":"Farmacias",
    "sg:phone":"+34 927 27 64 31",
    "sg:postcode":"10910",
    "sg:province":"C\u00e1ceres",
    "wof:name":"Cerro Pantoja Francisco",
    "wof:placetype":"venue"
},
  "geometry": {"coordinates":[-6.5097589493,39.4463195801],"type":"Point"}
}