{
  "type": "Feature",
  "properties": {
    "addr:full":"Calle de Felipe Castillo, 18 Tejina Santa Cruz De Tenerife 38260",
    "addr:housenumber":"18",
    "addr:postcode":"38260",
    "addr:street":"Calle De Felipe Castillo",
    "iso:country":"ES",
    "sg:address":"Calle de Felipe Castillo, 18",
    "sg:city":"Tejina",
    "sg:orig_category":"Agentes Generales De Seguros",
    "sg:phone":"+34 922 54 60 17",
    "sg:postcode":"38260",
    "sg:province":"Santa Cruz De Tenerife",
    "wof:name":"Campos Alvarez Maria De Las Nieves",
    "wof:placetype":"venue"
},
  "geometry": {"coordinates":[-16.3609542847,28.5350093842],"type":"Point"}
}