{
  "type": "Feature",
  "properties": {
    "addr:full":"C/ Joan Lliteras, 10 Manacor Islas Baleares 07500",
    "addr:housenumber":"10",
    "addr:postcode":"07500",
    "addr:street":"C / Joan Lliteras",
    "iso:country":"ES",
    "sg:address":"C/ Joan Lliteras, 10",
    "sg:city":"Manacor",
    "sg:orig_category":"Doctores En Medicina",
    "sg:phone":"+34 971 55 01 23",
    "sg:postcode":"07500",
    "sg:province":"Islas Baleares",
    "wof:name":"Lliteras Rossello Sebastian",
    "wof:placetype":"venue"
},
  "geometry": {"coordinates":[3.2090029716,39.5703353882],"type":"Point"}
}