{
  "type": "Feature",
  "properties": {
    "iso:country":"ES",
    "sg:address":"Pl. Constitucion, 4",
    "sg:city":"Cartama",
    "sg:orig_category":"Iglesia Cat\u00d3lica",
    "sg:phone":"+34 952 42 22 17",
    "sg:postcode":"29570",
    "sg:province":"M\u00e1laga",
    "wof:name":"Obispado De Malaga",
    "wof:placetype":"venue"
},
  "geometry": {"coordinates":[-4.6312727928,36.7102584839],"type":"Point"}
}