{
  "type": "Feature",
  "properties": {
    "iso:country":"ES",
    "sg:address":"Carrer de Santa Llucia (de), 9",
    "sg:city":"Arbo\u00e7",
    "sg:orig_category":"Equitaci\u00d3n Y Centros De H\u00cdpica",
    "sg:phone":"+34 977 16 71 22",
    "sg:postcode":"43720",
    "sg:province":"Tarragona",
    "wof:name":"Eurofarrier S.l.",
    "wof:placetype":"venue"
},
  "geometry": {"coordinates":[1.6004149914,41.2643699646],"type":"Point"}
}