{
  "type": "Feature",
  "properties": {
    "addr:full":"Rua Paz, 10 Vigo Pontevedra 36202",
    "addr:housenumber":"10",
    "addr:postcode":"36202",
    "addr:street":"Rua Paz",
    "iso:country":"ES",
    "sg:address":"Rua Paz, 10",
    "sg:city":"Vigo",
    "sg:orig_category":"Pintura, Barniz, Productos Asimilables (fabricaci\u00d3n, Al Por Mayor)",
    "sg:phone":"+34 986 20 49 40",
    "sg:postcode":"36202",
    "sg:province":"Pontevedra",
    "wof:name":"Lapin S. L.",
    "wof:placetype":"venue"
},
  "geometry": {"coordinates":[-8.7344923019,42.2279930115],"type":"Point"}
}