{
  "type": "Feature",
  "properties": {
    "addr:full":"Calle de Carlos V, 8 Parla Madrid 28980",
    "addr:housenumber":"8",
    "addr:postcode":"28980",
    "addr:street":"Calle De Carlos V",
    "iso:country":"ES",
    "sg:address":"Calle de Carlos V, 8",
    "sg:city":"Parla",
    "sg:orig_category":"Inmobiliaria (agencias)",
    "sg:phone":"+34 916 05 29 19",
    "sg:postcode":"28980",
    "sg:province":"Madrid",
    "sg:website":"www.esalje.net",
    "wof:name":"Navarro Peinado Juan",
    "wof:placetype":"venue"
},
  "geometry": {"coordinates":[-3.7704451084,40.2347640991],"type":"Point"}
}