{
  "type": "Feature",
  "properties": {
    "addr:full":"Plza Guitarrista Sabicas, 5 Iru\u00f1a Navarra 31015",
    "addr:housenumber":"5",
    "addr:postcode":"31015",
    "addr:street":"Sabicas",
    "iso:country":"ES",
    "sg:address":"Plza Guitarrista Sabicas, 5",
    "sg:city":"Iru\u00f1a",
    "sg:orig_category":"Administradores De Bienes Y Delegados De Comunidades De Propietarios",
    "sg:phone":"+34 948 38 20 79",
    "sg:postcode":"31015",
    "sg:province":"Navarra",
    "wof:name":"Aranguren Ausejo Olga",
    "wof:placetype":"venue"
},
  "geometry": {"coordinates":[-1.6299338341,42.830291748],"type":"Point"}
}