{
  "type": "Feature",
  "properties": {
    "iso:country":"ES",
    "sg:address":"Av Goles De L'ebre, 302",
    "sg:city":"Deltebre",
    "sg:orig_category":"Librer\u00cdas",
    "sg:phone":"+34 977 48 00 35",
    "sg:postcode":"43580",
    "sg:province":"Tarragona",
    "wof:name":"Soler Subirats Laureano Javier",
    "wof:placetype":"venue"
},
  "geometry": {"coordinates":[0.7427960038,40.7161941528],"type":"Point"}
}