{
  "type": "Feature",
  "properties": {
    "addr:full":"Avda Mijas, 24 Fuengirola M\u00e1laga 29640",
    "addr:housenumber":"24",
    "addr:postcode":"29640",
    "addr:street":"Avda Mijas;Ma\u0301Laga",
    "iso:country":"ES",
    "sg:address":"Avda Mijas, 24",
    "sg:city":"Fuengirola",
    "sg:orig_category":"Asociaciones Y Clubs Deportivos",
    "sg:phone":"+34 952 59 29 22",
    "sg:postcode":"29640",
    "sg:province":"M\u00e1laga",
    "wof:name":"Vaquer Fernandez S.l.",
    "wof:placetype":"venue"
},
  "geometry": {"coordinates":[-4.6250109673,36.5409965515],"type":"Point"}
}