{
  "type": "Feature",
  "properties": {
    "addr:full":"Ctra Loja Torre Del Mar (pi Antequera), S/n Antequera M\u00e1laga 29200",
    "addr:housenumber":"s / n",
    "addr:postcode":"29200",
    "addr:street":"Ctra Loja;Antequera",
    "iso:country":"ES",
    "sg:address":"Ctra Loja Torre Del Mar (pi Antequera), S/n",
    "sg:city":"Antequera",
    "sg:orig_category":"Puertas Y Portales",
    "sg:phone":"+34 902 11 13 05",
    "sg:postcode":"29200",
    "sg:province":"M\u00e1laga",
    "sg:website":"www.puertastht.com",
    "wof:name":"Puertas Tht S.l.",
    "wof:placetype":"venue"
},
  "geometry": {"coordinates":[-4.5636138916,37.0203018188],"type":"Point"}
}