{
  "type": "Feature",
  "properties": {
    "iso:country":"ES",
    "sg:address":"Rua Marques De Ugena, 45",
    "sg:city":"Sarria",
    "sg:orig_category":"Mec\u00c1nico Del Autom\u00d3vil",
    "sg:phone":"+34 982 53 03 55",
    "sg:postcode":"27600",
    "sg:province":"Lugo",
    "wof:name":"Talleres Galicia Sarria S.l.",
    "wof:placetype":"venue"
},
  "geometry": {"coordinates":[-7.4162359238,42.7793502808],"type":"Point"}
}