{
  "type": "Feature",
  "properties": {
    "addr:full":"Calle de Herreria, S/n Somo Cantabria 39140",
    "addr:postcode":"39140",
    "addr:street":"Calle De Herreria S / N",
    "iso:country":"ES",
    "sg:address":"Calle de Herreria, S/n",
    "sg:city":"Somo",
    "sg:orig_category":"Guarder\u00cdas",
    "sg:phone":"+34 942 51 04 97",
    "sg:postcode":"39140",
    "sg:province":"Cantabria",
    "wof:name":"Ayuntamiento De Ribamontan Al Mar",
    "wof:placetype":"venue"
},
  "geometry": {"coordinates":[-3.7345426083,43.450050354],"type":"Point"}
}