{
  "type": "Feature",
  "properties": {
    "iso:country":"ES",
    "sg:address":"Avda Santiago, 29",
    "sg:city":"Vitoria-gasteiz",
    "sg:orig_category":"Peluqueros: De Se\u00d1oras",
    "sg:phone":"+34 945 26 67 40",
    "sg:postcode":"01003",
    "sg:province":"\u00c1lava",
    "wof:name":"Merino Marcos Nuria",
    "wof:placetype":"venue"
},
  "geometry": {"coordinates":[-2.6636333466,42.847366333],"type":"Point"}
}