{
  "type": "Feature",
  "properties": {
    "addr:full":"Calle de San Ildefonso, 9 Utiel Valencia 46300",
    "addr:housenumber":"9",
    "addr:postcode":"46300",
    "addr:street":"Calle De San Ildefonso",
    "iso:country":"ES",
    "sg:address":"Calle de San Ildefonso, 9",
    "sg:city":"Utiel",
    "sg:orig_category":"Tintes (fabricaci\u00d3n, Al Por Mayor)",
    "sg:phone":"+34 962 17 43 79",
    "sg:postcode":"46300",
    "sg:province":"Valencia",
    "wof:name":"Fibra-tintoreria Coop.v.",
    "wof:placetype":"venue"
},
  "geometry": {"coordinates":[-1.2016899586,39.5661277771],"type":"Point"}
}