{
  "type": "Feature",
  "properties": {
    "iso:country":"ES",
    "sg:address":"Calle de Santa Ana, 27",
    "sg:city":"Villanueva Arzobispo",
    "sg:orig_category":"Fabricaci\u00d3n De Muebles",
    "sg:phone":"+34 953 45 03 95",
    "sg:postcode":"23330",
    "sg:province":"Ja\u00e9n",
    "wof:name":"Artesania Y Muebles Gomez S.l.",
    "wof:placetype":"venue"
},
  "geometry": {"coordinates":[-3.0128147602,38.1684875488],"type":"Point"}
}