{
  "type": "Feature",
  "properties": {
    "addr:full":"Calle de Zuera, 4 Madrid Madrid 28037",
    "addr:housenumber":"4",
    "addr:postcode":"28037",
    "addr:street":"Calle De Zuera",
    "iso:country":"ES",
    "sg:address":"Calle de Zuera, 4",
    "sg:city":"Madrid",
    "sg:orig_category":"Tintes (fabricaci\u00d3n, Al Por Mayor)",
    "sg:phone":"+34 913 04 11 08",
    "sg:postcode":"28037",
    "sg:province":"Madrid",
    "wof:name":"Guerrero Loma Osorio Magdalena",
    "wof:placetype":"venue"
},
  "geometry": {"coordinates":[-3.6262431145,40.4295959473],"type":"Point"}
}