{
  "type": "Feature",
  "properties": {
    "iso:country":"ES",
    "sg:address":"Carrer de Francesc Duran I Reynals, 9",
    "sg:city":"Granollers",
    "sg:orig_category":"Comercio, Reparaci\u00d3n De Motocicletas, Bicicletas Y Piezas Sueltas",
    "sg:phone":"+34 938 79 51 12",
    "sg:postcode":"08403",
    "sg:province":"Barcelona",
    "sg:website":"www.motofashion.es",
    "wof:name":"On Two Weel's Moto Fashion S.l.",
    "wof:placetype":"venue"
},
  "geometry": {"coordinates":[2.279804945,41.6144218445],"type":"Point"}
}