{
  "type": "Feature",
  "properties": {
    "addr:full":"Pol Mun Zafra, S/n Zafra Badajoz 06300",
    "addr:housenumber":"s / n",
    "addr:postcode":"06300",
    "iso:country":"ES",
    "sg:address":"Pol Mun Zafra, S/n",
    "sg:city":"Zafra",
    "sg:orig_category":"Veh\u00cdculos De Ocasi\u00d3n",
    "sg:phone":"+34 924 55 14 47",
    "sg:postcode":"06300",
    "sg:province":"Badajoz",
    "wof:name":"Carrasco Silgado Rafael",
    "wof:placetype":"venue"
},
  "geometry": {"coordinates":[-6.4134092331,38.4236793518],"type":"Point"}
}