{
  "type": "Feature",
  "properties": {
    "iso:country":"ES",
    "sg:address":"Calle de Jardines, 28",
    "sg:city":"Do\u00e7inos De Salamanca",
    "sg:orig_category":"Casas Con Estructura De Madera",
    "sg:phone":"+34 923 33 01 45",
    "sg:postcode":"37120",
    "sg:province":"Salamanca",
    "sg:website":"www.sitmon.com",
    "wof:name":"Caravanas Simon S.l.",
    "wof:placetype":"venue"
},
  "geometry": {"coordinates":[-5.7425260544,40.9601211548],"type":"Point"}
}