{
  "type": "Feature",
  "properties": {
    "addr:full":"Carrer de Alcoi, 124 Terrassa Barcelona 08225",
    "addr:housenumber":"124",
    "addr:postcode":"08225",
    "addr:street":"Carrer De Alcoi",
    "iso:country":"ES",
    "sg:address":"Carrer de Alcoi, 124",
    "sg:city":"Terrassa",
    "sg:orig_category":"Confiter\u00cda, Galletas Y Pastas, Chocolater\u00cda (al Por Mayor)",
    "sg:phone":"+34 937 35 60 26",
    "sg:postcode":"08225",
    "sg:province":"Barcelona",
    "wof:name":"Cabello Cabello Juan Jose",
    "wof:placetype":"venue"
},
  "geometry": {"coordinates":[2.0157198906,41.5792198181],"type":"Point"}
}