{
  "type": "Feature",
  "properties": {
    "addr:full":"Ctra Alcala Del Rio, S/n Algaba Sevilla 41980",
    "addr:postcode":"41980",
    "addr:street":"Ctra Alcala Del Rio S / N Algaba",
    "iso:country":"ES",
    "sg:address":"Ctra Alcala Del Rio, S/n",
    "sg:city":"Algaba",
    "sg:orig_category":"Electrodom\u00c9sticos (al Por Menor)",
    "sg:phone":"+34 955 78 01 86",
    "sg:postcode":"41980",
    "sg:province":"Sevilla",
    "wof:name":"Audio Confort S.l.",
    "wof:placetype":"venue"
},
  "geometry": {"coordinates":[-6.0153942108,37.4607162476],"type":"Point"}
}