{
  "type": "Feature",
  "properties": {
    "iso:country":"ES",
    "sg:address":"Plaz Soledad, 15",
    "sg:city":"Vinuesa",
    "sg:orig_category":"Cajas Para Embalar",
    "sg:phone":"+34 975 37 81 71",
    "sg:postcode":"42150",
    "sg:province":"Soria",
    "sg:website":"www.cajarural.com",
    "wof:name":"Caja Rural Provincial De Soria",
    "wof:placetype":"venue"
},
  "geometry": {"coordinates":[-2.7598340511,41.9107093811],"type":"Point"}
}