{
  "type": "Feature",
  "properties": {
    "iso:country":"ES",
    "sg:address":"Calle de Martin De La Plaza, 36",
    "sg:city":"Malaga",
    "sg:orig_category":"Centros De Coordinaci\u00d3n",
    "sg:phone":"+34 952 10 39 79",
    "sg:postcode":"29010",
    "sg:province":"M\u00e1laga",
    "wof:name":"Perez Fernandez Armando",
    "wof:placetype":"venue"
},
  "geometry": {"coordinates":[-4.457420826,36.7232589722],"type":"Point"}
}