{
  "type": "Feature",
  "properties": {
    "iso:country":"ES",
    "sg:address":"Avda Cruz Roja (la), 15",
    "sg:city":"Jerez De La Frontera",
    "sg:orig_category":"T\u00c9cnicos Veterinarios",
    "sg:phone":"+34 956 30 84 85",
    "sg:postcode":"11407",
    "sg:province":"C\u00e1diz",
    "wof:name":"Clinica Veterinaria Cruz Roja S.c.",
    "wof:placetype":"venue"
},
  "geometry": {"coordinates":[-6.1341910362,36.696937561],"type":"Point"}
}