{
  "type": "Feature",
  "properties": {
    "addr:full":"Rua Real, 219 Ferrol La Coru\u00f1a 15402",
    "addr:housenumber":"219",
    "addr:postcode":"15402",
    "addr:street":"Rua Real;La Corun\u0303A",
    "iso:country":"ES",
    "sg:address":"Rua Real, 219",
    "sg:city":"Ferrol",
    "sg:orig_category":"Reposter\u00cdas",
    "sg:phone":"+34 981 35 72 14",
    "sg:postcode":"15402",
    "sg:province":"La Coru\u00f1a",
    "wof:name":"Monica Y Consuelo Calvo Cendan Sc",
    "wof:placetype":"venue"
},
  "geometry": {"coordinates":[-8.2379894257,43.4818305969],"type":"Point"}
}