{
  "type": "Feature",
  "properties": {
    "addr:full":"Jose Artetxe Kalea, 3 Azpeitia Guip\u00f9zcoa 20730",
    "addr:housenumber":"3",
    "addr:postcode":"20730",
    "addr:street":"Jose Artetxe Kalea;Guipu\u0300Zcoa",
    "iso:country":"ES",
    "sg:address":"Jose Artetxe Kalea, 3",
    "sg:city":"Azpeitia",
    "sg:orig_category":"Fisioterapia",
    "sg:phone":"+34 943 81 37 49",
    "sg:postcode":"20730",
    "sg:province":"Guip\u00f9zcoa",
    "wof:name":"Lasa Rezola Ignacio",
    "wof:placetype":"venue"
},
  "geometry": {"coordinates":[-2.2685830593,43.1809921265],"type":"Point"}
}