{
  "type": "Feature",
  "properties": {
    "iso:country":"ES",
    "sg:address":"Calle de Marques Del Robrero, 4",
    "sg:city":"Santo\u00f1a",
    "sg:orig_category":"Ropa Para Se\u00d1oras (al Por Menor)",
    "sg:phone":"+34 942 67 17 26",
    "sg:postcode":"39740",
    "sg:province":"Cantabria",
    "wof:name":"Lasa Larra\u00f1aga Ione",
    "wof:placetype":"venue"
},
  "geometry": {"coordinates":[-3.4567430019,43.441734314],"type":"Point"}
}