{
  "type": "Feature",
  "properties": {
    "addr:full":"Lagos De Millares (mrl), 36 Zaragoza Zaragoza 50011",
    "addr:housenumber":"36",
    "addr:postcode":"50011",
    "addr:street":"Lagos De Millares Mrl",
    "iso:country":"ES",
    "sg:address":"Lagos De Millares (mrl), 36",
    "sg:city":"Zaragoza",
    "sg:orig_category":"Formaci\u00d3n A Distancia, Por Correspondencia",
    "sg:phone":"+34 976 50 83 12",
    "sg:postcode":"50011",
    "sg:province":"Zaragoza",
    "wof:name":"Advantia Global Solutions S.l.",
    "wof:placetype":"venue"
},
  "geometry": {"coordinates":[-1.0011901855,41.6566925049],"type":"Point"}
}