{
  "type": "Feature",
  "properties": {
    "iso:country":"ES",
    "sg:address":"Calle de Pinta, La, 11",
    "sg:city":"Calpe",
    "sg:orig_category":"Molduras, Junquillos, Listones Y Molduras Perforadas",
    "sg:phone":"+34 965 83 73 86",
    "sg:postcode":"03710",
    "sg:province":"Alicante",
    "wof:name":"Weekes  Vivian",
    "wof:placetype":"venue"
},
  "geometry": {"coordinates":[0.0535200015,38.6515808105],"type":"Point"}
}