{
  "type": "Feature",
  "properties": {
    "iso:country":"ES",
    "sg:address":"Calle de Perez Galdos, 20",
    "sg:city":"Valladolid",
    "sg:orig_category":"Carnicer\u00cdas, Carnicer\u00cdas",
    "sg:phone":"+34 983 29 28 06",
    "sg:postcode":"47005",
    "sg:province":"Valladolid",
    "wof:name":"Rodriguez Gonzalez Anastasio",
    "wof:placetype":"venue"
},
  "geometry": {"coordinates":[-4.7162308693,41.648891449],"type":"Point"}
}