{
  "type": "Feature",
  "properties": {
    "addr:full":"Calle de Virgen De La Piedad, S/n Baza Granada 18800",
    "addr:housenumber":"s",
    "addr:postcode":"18800",
    "addr:street":"Calle De Virgen De La Piedad;/ N",
    "iso:country":"ES",
    "sg:address":"Calle de Virgen De La Piedad, S/n",
    "sg:city":"Baza",
    "sg:orig_category":"M\u00c9dicos: Otorrinolaringolog\u00cda",
    "sg:phone":"+34 958 70 46 00",
    "sg:postcode":"18800",
    "sg:province":"Granada",
    "wof:name":"Policlinica Baza C.b.",
    "wof:placetype":"venue"
},
  "geometry": {"coordinates":[-2.7812469006,37.4904823303],"type":"Point"}
}