{
  "type": "Feature",
  "properties": {
    "addr:full":"Calle de Baja, 12 Maella Zaragoza 50710",
    "addr:housenumber":"12",
    "addr:postcode":"50710",
    "addr:street":"Calle De Baja",
    "iso:country":"ES",
    "sg:address":"Calle de Baja, 12",
    "sg:city":"Maella",
    "sg:orig_category":"Telas Y Sedas (al Por Menor)",
    "sg:phone":"+34 976 63 83 48",
    "sg:postcode":"50710",
    "sg:province":"Zaragoza",
    "wof:name":"Ballo Godina Luis",
    "wof:placetype":"venue"
},
  "geometry": {"coordinates":[0.1435180008,41.1222724915],"type":"Point"}
}