{
  "type": "Feature",
  "properties": {
    "iso:country":"ES",
    "sg:address":"Calle de Mar, S/n",
    "sg:city":"Sevilla",
    "sg:orig_category":"Fabricaci\u00d3n De Juguetes Autom\u00c1ticos",
    "sg:phone":"+34 954 25 47 45",
    "sg:postcode":"41020",
    "sg:province":"Sevilla",
    "wof:name":"Billares Y Futbolines S.l.",
    "wof:placetype":"venue"
},
  "geometry": {"coordinates":[-5.9388189316,37.4050102234],"type":"Point"}
}