{
  "type": "Feature",
  "properties": {
    "addr:full":"Calle de Francisco Lujan, 16 Badajoz Badajoz 06004",
    "addr:housenumber":"16",
    "addr:postcode":"06004",
    "addr:street":"Calle De Francisco Lujan",
    "iso:country":"ES",
    "sg:address":"Calle de Francisco Lujan, 16",
    "sg:city":"Badajoz",
    "sg:orig_category":"Ropa Para Ni\u00d1os (al Por Menor)",
    "sg:phone":"+34 924 23 16 50",
    "sg:postcode":"06004",
    "sg:province":"Badajoz",
    "sg:website":"www.prenatal.es",
    "wof:name":"Catalina Ballesteros S.l.",
    "wof:placetype":"venue"
},
  "geometry": {"coordinates":[-6.9745798111,38.8702964783],"type":"Point"}
}