{
  "type": "Feature",
  "properties": {
    "addr:full":"C/ Girona, 155 Banyoles Girona 17820",
    "addr:housenumber":"155",
    "addr:postcode":"17820",
    "addr:street":"C / Girona",
    "iso:country":"ES",
    "sg:address":"C/ Girona, 155",
    "sg:city":"Banyoles",
    "sg:orig_category":"Empresas De Electricidad En General",
    "sg:phone":"+34 972 58 00 58",
    "sg:postcode":"17820",
    "sg:province":"Girona",
    "sg:website":"www.agrienergia.com",
    "wof:name":"Agri-energia S. A.",
    "wof:placetype":"venue"
},
  "geometry": {"coordinates":[2.7703442574,42.115737915],"type":"Point"}
}