{
  "type": "Feature",
  "properties": {
    "addr:full":"Calle de Parra (la), S/n Urrea Jalon Zaragoza 50296",
    "addr:postcode":"50296",
    "addr:street":"Calle De Parra La S / N",
    "iso:country":"ES",
    "sg:address":"Calle de Parra (la), S/n",
    "sg:city":"Urrea Jalon",
    "sg:orig_category":"Supermercados Y Hipermercados",
    "sg:phone":"+34 976 65 41 04",
    "sg:postcode":"50296",
    "sg:province":"Zaragoza",
    "wof:name":"Supermercados Hermanas Garcia",
    "wof:placetype":"venue"
},
  "geometry": {"coordinates":[-1.234243989,41.6671257019],"type":"Point"}
}