{
  "type": "Feature",
  "properties": {
    "addr:full":"Calle de Machaquito, 2 Cordoba C\u00f3rdoba 14005",
    "addr:housenumber":"2",
    "addr:postcode":"14005",
    "addr:street":"Calle De Machaquito;Co\u0301Rdoba",
    "iso:country":"ES",
    "sg:address":"Calle de Machaquito, 2",
    "sg:city":"Cordoba",
    "sg:orig_category":"Abogados",
    "sg:phone":"+34 957 45 18 49",
    "sg:postcode":"14005",
    "sg:province":"C\u00f3rdoba",
    "wof:name":"Alcalde Rodriguez Ezequiel",
    "wof:placetype":"venue"
},
  "geometry": {"coordinates":[-4.7946014404,37.8829803467],"type":"Point"}
}