{
  "type": "Feature",
  "properties": {
    "iso:country":"ES",
    "sg:address":"Vista Fermosa Vella, S/n",
    "sg:city":"Ourense",
    "sg:orig_category":"Autob\u00das (explotaci\u00d3n Y Servicios De)",
    "sg:phone":"+34 988 22 98 03",
    "sg:postcode":"32940",
    "sg:province":"Ourense",
    "wof:name":"Villamarin Pe\u00f1a Benigno",
    "wof:placetype":"venue"
},
  "geometry": {"coordinates":[-7.9811987877,42.3352203369],"type":"Point"}
}