{
  "type": "Feature",
  "properties": {
    "addr:full":"Avgd President Companys, 262 Badalona Barcelona 08915",
    "addr:housenumber":"262",
    "addr:postcode":"08915",
    "addr:street":"Companys",
    "iso:country":"ES",
    "sg:address":"Avgd President Companys, 262",
    "sg:city":"Badalona",
    "sg:orig_category":"Peluqueros: De Se\u00d1oras",
    "sg:phone":"+34 933 95 25 54",
    "sg:postcode":"08915",
    "sg:province":"Barcelona",
    "wof:name":"Belmonte Moreno Martirio",
    "wof:placetype":"venue"
},
  "geometry": {"coordinates":[2.248650074,41.4593086243],"type":"Point"}
}