{
  "type": "Feature",
  "properties": {
    "addr:full":"Txalaka Pasealekua, 6 Astigarraga Guip\u00f9zcoa 20115",
    "addr:housenumber":"6",
    "addr:postcode":"20115",
    "addr:street":"Txalaka Pasealekua;Guipu\u0300Zcoa",
    "iso:country":"ES",
    "sg:address":"Txalaka Pasealekua, 6",
    "sg:city":"Astigarraga",
    "sg:orig_category":"Mec\u00c1nico Del Autom\u00d3vil",
    "sg:phone":"+34 943 55 19 08",
    "sg:postcode":"20115",
    "sg:province":"Guip\u00f9zcoa",
    "wof:name":"Penas Miguez Luis",
    "wof:placetype":"venue"
},
  "geometry": {"coordinates":[-1.9560309649,43.275428772],"type":"Point"}
}