{
  "type": "Feature",
  "properties": {
    "iso:country":"ES",
    "sg:address":"Calle de Donibane, 22",
    "sg:city":"Pasai Donibane",
    "sg:orig_category":"Farmacias",
    "sg:phone":"+34 943 51 46 45",
    "sg:postcode":"20110",
    "sg:province":"Guip\u00f9zcoa",
    "wof:name":"Campo Iriondo Fernando Xabier",
    "wof:placetype":"venue"
},
  "geometry": {"coordinates":[-1.9176939726,43.3250350952],"type":"Point"}
}