{
  "type": "Feature",
  "properties": {
    "addr:full":"Carrer de Paris, 149 Barcelona Barcelona 08036",
    "addr:housenumber":"149",
    "addr:postcode":"08036",
    "addr:street":"Carrer De Paris",
    "iso:country":"ES",
    "sg:address":"Carrer de Paris, 149",
    "sg:city":"Barcelona",
    "sg:orig_category":"Reposter\u00cdas",
    "sg:phone":"+34 934 30 90 29",
    "sg:postcode":"08036",
    "sg:province":"Barcelona",
    "wof:name":"Moli Vell S.l.",
    "wof:placetype":"venue"
},
  "geometry": {"coordinates":[2.1502590179,41.3915977478],"type":"Point"}
}