{
  "type": "Feature",
  "properties": {
    "iso:country":"ES",
    "sg:address":"Avda Espa\u00d1a, 85",
    "sg:city":"Rozas De Madrid",
    "sg:orig_category":"Inmobiliaria (agencias)",
    "sg:phone":"+34 916 39 41 31",
    "sg:postcode":"28231",
    "sg:province":"Madrid",
    "wof:name":"Azavit S.a.",
    "wof:placetype":"venue"
},
  "geometry": {"coordinates":[-3.8787593842,40.4879570007],"type":"Point"}
}