{
  "type": "Feature",
  "properties": {
    "addr:full":"Poligono, S/n Beniparrell Valencia 46469",
    "addr:postcode":"46469",
    "addr:street":"Poligono S / N Beniparrell",
    "iso:country":"ES",
    "sg:address":"Poligono, S/n",
    "sg:city":"Beniparrell",
    "sg:orig_category":"Madera Para Construcci\u00d3n E Industria",
    "sg:phone":"+34 961 21 38 28",
    "sg:postcode":"46469",
    "sg:province":"Valencia",
    "sg:website":"www.maderpark2000.com",
    "wof:name":"Maderpark 2000 S.l.",
    "wof:placetype":"venue"
},
  "geometry": {"coordinates":[-0.4501920044,39.35704422],"type":"Point"}
}