{
  "type": "Feature",
  "properties": {
    "addr:full":"German Bernacer(pol Ind), 67 Torrellano Alicante 03320",
    "addr:housenumber":"67",
    "addr:postcode":"03320",
    "addr:street":"Ind",
    "iso:country":"ES",
    "sg:address":"German Bernacer(pol Ind), 67",
    "sg:city":"Torrellano",
    "sg:orig_category":"Zapatos (al Por Mayor)",
    "sg:phone":"+34 965 68 57 08",
    "sg:postcode":"03320",
    "sg:province":"Alicante",
    "wof:name":"Jesus Samper S.l.",
    "wof:placetype":"venue"
},
  "geometry": {"coordinates":[-0.5883839726,38.2929649353],"type":"Point"}
}