{
  "type": "Feature",
  "properties": {
    "addr:full":"Carrer de Montnegre, 15 Barcelona Barcelona 08029",
    "addr:housenumber":"15",
    "addr:postcode":"08029",
    "addr:street":"Carrer De Montnegre",
    "iso:country":"ES",
    "sg:address":"Carrer de Montnegre, 15",
    "sg:city":"Barcelona",
    "sg:orig_category":"Importaci\u00d3n",
    "sg:phone":"+34 934 39 13 64",
    "sg:postcode":"08029",
    "sg:province":"Barcelona",
    "sg:website":"comercial@euramex.net",
    "wof:name":"Gomez Perez Juan",
    "wof:placetype":"venue"
},
  "geometry": {"coordinates":[2.1383008957,41.3871116638],"type":"Point"}
}