{
  "type": "Feature",
  "properties": {
    "iso:country":"ES",
    "sg:address":"Ctra. Andalucia, Km. 0094,0",
    "sg:city":"Tembleque",
    "sg:orig_category":"Otros Trabajos De Limpieza Y Mantenimiento (extracci\u00d3n De Polvo, Recogida De Amianto Y Desespumado)",
    "sg:phone":"+34 925 14 51 17",
    "sg:postcode":"45780",
    "sg:province":"Toledo",
    "wof:name":"Oliveros Rodriguez Manuel Agustin",
    "wof:placetype":"venue"
},
  "geometry": {"coordinates":[-3.5035789013,39.6947860718],"type":"Point"}
}