{
  "type": "Feature",
  "properties": {
    "addr:full":"Calle de Nuestra Se\u00d1ora Del Aguila, 15 Alcala Guadaira Sevilla 41500",
    "addr:housenumber":"15",
    "addr:postcode":"41500",
    "addr:street":"Calle De Nuestra;Del Aguila",
    "iso:country":"ES",
    "sg:address":"Calle de Nuestra Se\u00d1ora Del Aguila, 15",
    "sg:city":"Alcala Guadaira",
    "sg:orig_category":"Restaurantes",
    "sg:phone":"+34 955 68 08 32",
    "sg:postcode":"41500",
    "sg:province":"Sevilla",
    "wof:name":"Churreria Nuestra Se\u00f1ora Del Aguila",
    "wof:placetype":"venue"
},
  "geometry": {"coordinates":[-5.8460578918,37.336265564],"type":"Point"}
}