{
  "type": "Feature",
  "properties": {
    "addr:full":"Calle de Nicanor Villalta, 6 Zaragoza Zaragoza 50017",
    "addr:housenumber":"6",
    "addr:postcode":"50017",
    "addr:street":"Calle De Nicanor Villalta",
    "iso:country":"ES",
    "sg:address":"Calle de Nicanor Villalta, 6",
    "sg:city":"Zaragoza",
    "sg:orig_category":"Institutos De Belleza",
    "sg:phone":"+34 976 32 74 13",
    "sg:postcode":"50017",
    "sg:province":"Zaragoza",
    "wof:name":"Lazaro Nula Marisa",
    "wof:placetype":"venue"
},
  "geometry": {"coordinates":[-0.9117879868,41.6529655457],"type":"Point"}
}