{
  "type": "Feature",
  "properties": {
    "iso:country":"ES",
    "sg:address":"Plaz Espa\u00d1a, 4",
    "sg:city":"Due\u00f1as",
    "sg:orig_category":"Molduras, Junquillos, Listones Y Molduras Perforadas",
    "sg:phone":"+34 979 78 01 07",
    "sg:postcode":"34210",
    "sg:province":"Palencia",
    "wof:name":"Caballero Murillo Jose Antonio",
    "wof:placetype":"venue"
},
  "geometry": {"coordinates":[-4.5456790924,41.8751182556],"type":"Point"}
}