{
  "type": "Feature",
  "properties": {
    "iso:country":"ES",
    "sg:address":"Czad Medina, S/n",
    "sg:city":"Salamanca",
    "sg:orig_category":"Frutas Y Legumbres Frescas (al Por Mayor)",
    "sg:phone":"+34 923 25 35 93",
    "sg:postcode":"37004",
    "sg:province":"Salamanca",
    "wof:name":"Aceitunas Dominguez S.a.",
    "wof:placetype":"venue"
},
  "geometry": {"coordinates":[-5.6375212669,40.9766044617],"type":"Point"}
}