{
  "type": "Feature",
  "properties": {
    "addr:full":"Pase Basilios (de Los), 11 Granada Granada 18008",
    "addr:postcode":"18008",
    "iso:country":"ES",
    "sg:address":"Pase Basilios (de Los), 11",
    "sg:city":"Granada",
    "sg:orig_category":"Doctores En Medicina",
    "sg:phone":"+34 958 12 21 03",
    "sg:postcode":"18008",
    "sg:province":"Granada",
    "wof:name":"Laborde Vallverdu Agustin",
    "wof:placetype":"venue"
},
  "geometry": {"coordinates":[-3.5911090374,37.16822052],"type":"Point"}
}