{
  "type": "Feature",
  "properties": {
    "addr:full":"Calle de Cervantes, 13 Campo Criptana Ciudad Real 13610",
    "addr:housenumber":"13",
    "addr:postcode":"13610",
    "addr:street":"Calle De Cervantes;Criptana",
    "iso:country":"ES",
    "sg:address":"Calle de Cervantes, 13",
    "sg:city":"Campo Criptana",
    "sg:orig_category":"Dise\u00d1o Industrial",
    "sg:phone":"+34 926 56 22 91",
    "sg:postcode":"13610",
    "sg:province":"Ciudad Real",
    "wof:name":"Fernandez Lucas Francisco",
    "wof:placetype":"venue"
},
  "geometry": {"coordinates":[-3.1273863316,39.4048538208],"type":"Point"}
}