{
  "type": "Feature",
  "properties": {
    "addr:full":"Calle de Navarra, 19 Castellon Castell\u00f3n 12002",
    "addr:housenumber":"19",
    "addr:postcode":"12002",
    "addr:street":"Calle De Navarra",
    "iso:country":"ES",
    "sg:address":"Calle de Navarra, 19",
    "sg:city":"Castellon",
    "sg:orig_category":"Asesor\u00cda De Comercio Exterior",
    "sg:phone":"+34 964 34 23 20",
    "sg:postcode":"12002",
    "sg:province":"Castell\u00f3n",
    "wof:name":"Edo Sanz Maria Lourdes",
    "wof:placetype":"venue"
},
  "geometry": {"coordinates":[-0.0402240008,39.9842567444],"type":"Point"}
}