{
  "type": "Feature",
  "properties": {
    "iso:country":"ES",
    "sg:address":"Carrer de Dos De Maig, 311",
    "sg:city":"Barcelona",
    "sg:orig_category":"Ropa Para Se\u00d1oras (al Por Menor)",
    "sg:phone":"+34 934 35 92 86",
    "sg:postcode":"08025",
    "sg:province":"Barcelona",
    "wof:name":"Jimenez Benito Milagros",
    "wof:placetype":"venue"
},
  "geometry": {"coordinates":[2.1763780117,41.411190033],"type":"Point"}
}