{
  "type": "Feature",
  "properties": {
    "addr:full":"Carrer de Valldoreix, 35 S. Cugat Valles Barcelona 08172",
    "addr:housenumber":"35",
    "addr:postcode":"08172",
    "addr:street":"Carrer De Valldoreix;S. Cugat Valles Barcelona",
    "iso:country":"ES",
    "sg:address":"Carrer de Valldoreix, 35",
    "sg:city":"S. Cugat Valles",
    "sg:orig_category":"Inmobiliaria (agencias)",
    "sg:phone":"+34 935 44 28 29",
    "sg:postcode":"08172",
    "sg:province":"Barcelona",
    "sg:website":"www.lookandfind.es",
    "wof:name":"Patron-net S.o.r. S.l.",
    "wof:placetype":"venue"
},
  "geometry": {"coordinates":[2.0842399597,41.4679336548],"type":"Point"}
}