{
  "type": "Feature",
  "properties": {
    "addr:full":"Avenida Puentecesures, 15 Padron La Coru\u00f1a 15900",
    "addr:housenumber":"15",
    "addr:postcode":"15900",
    "addr:street":"Avenida Puentecesures;Padron La Corun\u0303A",
    "iso:country":"ES",
    "sg:address":"Avenida Puentecesures, 15",
    "sg:city":"Padron",
    "sg:orig_category":"Quincaller\u00cda (al Por Menor)",
    "sg:phone":"+34 981 81 04 64",
    "sg:postcode":"15900",
    "sg:province":"La Coru\u00f1a",
    "wof:name":"Riperfer S.l.",
    "wof:placetype":"venue"
},
  "geometry": {"coordinates":[-8.6599035263,42.7348175049],"type":"Point"}
}