{
  "type": "Feature",
  "properties": {
    "addr:full":"Calle de Santa Susana, 20 Madrid Madrid 28033",
    "addr:housenumber":"20",
    "addr:postcode":"madrid;28033",
    "addr:street":"Calle De Santa Susana",
    "iso:country":"ES",
    "sg:address":"Calle de Santa Susana, 20",
    "sg:city":"Madrid",
    "sg:orig_category":"Molduras, Junquillos, Listones Y Molduras Perforadas",
    "sg:phone":"+34 917 64 49 84",
    "sg:postcode":"28033",
    "sg:province":"Madrid",
    "wof:name":"Ortiz Gonzalez Eva Maria",
    "wof:placetype":"venue"
},
  "geometry": {"coordinates":[-3.6467428207,40.4783706665],"type":"Point"}
}