{
  "type": "Feature",
  "properties": {
    "iso:country":"ES",
    "sg:address":"Calle de Cefeo, 34",
    "sg:city":"Alacant",
    "sg:orig_category":"Plomeros",
    "sg:phone":"+34 965 28 44 05",
    "sg:postcode":"03006",
    "sg:province":"Alicante",
    "wof:name":"Fontaneria Due\u00f1as C.b.",
    "wof:placetype":"venue"
},
  "geometry": {"coordinates":[-0.5115274191,38.3473052979],"type":"Point"}
}