{
  "type": "Feature",
  "properties": {
    "iso:country":"ES",
    "sg:address":"Avda Castilla La Mancha, 87",
    "sg:city":"Illescas",
    "sg:orig_category":"Promotores Constructores",
    "sg:phone":"+34 925 54 07 69",
    "sg:postcode":"45200",
    "sg:province":"Toledo",
    "wof:name":"Inmopromociones Illesmad S.l.",
    "wof:placetype":"venue"
},
  "geometry": {"coordinates":[-3.8458390236,40.1251296997],"type":"Point"}
}