{
  "type": "Feature",
  "properties": {
    "addr:full":"Calle de Ermita, 15 Hueneja Granada 18512",
    "addr:housenumber":"15",
    "addr:postcode":"18512",
    "addr:street":"Calle De Ermita",
    "iso:country":"ES",
    "sg:address":"Calle de Ermita, 15",
    "sg:city":"Hueneja",
    "sg:orig_category":"Empresarios",
    "sg:phone":"+34 958 68 30 31",
    "sg:postcode":"18512",
    "sg:province":"Granada",
    "wof:name":"Cascales Moya Juan",
    "wof:placetype":"venue"
},
  "geometry": {"coordinates":[-2.9545590878,37.1759910583],"type":"Point"}
}