{
  "type": "Feature",
  "properties": {
    "addr:full":"Rua Rosalia De Castro, 26 Pontevedra Pontevedra 36001",
    "addr:housenumber":"26",
    "addr:postcode":"36001",
    "addr:street":"Rua Rosalia De Castro",
    "iso:country":"ES",
    "sg:address":"Rua Rosalia De Castro, 26",
    "sg:city":"Pontevedra",
    "sg:orig_category":"Cajas De Ahorro",
    "sg:phone":"+34 986 86 90 09",
    "sg:postcode":"36001",
    "sg:province":"Pontevedra",
    "wof:name":"Caja De Ahorros De Valencia Castellon Y Alicante",
    "wof:placetype":"venue"
},
  "geometry": {"coordinates":[-8.6474103928,42.4284133911],"type":"Point"}
}