{
  "type": "Feature",
  "properties": {
    "addr:full":"C/ 624, 8 Ca\u00d1ada Valencia 46182",
    "addr:housenumber":"8",
    "addr:postcode":"46182",
    "addr:street":"C / 624",
    "iso:country":"ES",
    "sg:address":"C/ 624, 8",
    "sg:city":"Ca\u00d1ada",
    "sg:orig_category":"Fotograf\u00cda Art\u00cdstica Y Retratos",
    "sg:phone":"+34 961 32 48 55",
    "sg:postcode":"46182",
    "sg:province":"Valencia",
    "sg:website":"www.juanmonti.com",
    "wof:name":"Monta\u00f1ana Vizcaino Juan",
    "wof:placetype":"venue"
},
  "geometry": {"coordinates":[-0.4852339923,39.5221443176],"type":"Point"}
}