{
  "type": "Feature",
  "properties": {
    "iso:country":"ES",
    "sg:address":"Av Valencia, 55",
    "sg:city":"Molins Rei",
    "sg:orig_category":"Materias Pl\u00c1sticas: Art\u00cdculos Para La Industria",
    "sg:phone":"+34 936 68 23 59",
    "sg:postcode":"08750",
    "sg:province":"Barcelona",
    "wof:name":"Royo Alcaire Feliciano",
    "wof:placetype":"venue"
},
  "geometry": {"coordinates":[2.0167720318,41.4096641541],"type":"Point"}
}