{
  "type": "Feature",
  "properties": {
    "addr:full":"Avda Lorca, 27 Totana Murcia 30850",
    "addr:housenumber":"27",
    "addr:postcode":"30850",
    "addr:street":"Avda Lorca",
    "iso:country":"ES",
    "sg:address":"Avda Lorca, 27",
    "sg:city":"Totana",
    "sg:orig_category":"Ropa Y Art\u00cdculos Pre",
    "sg:phone":"+34 968 42 39 27",
    "sg:postcode":"30850",
    "sg:province":"Murcia",
    "wof:name":"Canovas Canovas Pilar",
    "wof:placetype":"venue"
},
  "geometry": {"coordinates":[-1.5030390024,37.7726860046],"type":"Point"}
}