{
  "type": "Feature",
  "properties": {
    "addr:full":"Calle de J Guttemberg, 11 Chorrillo Santa Cruz De Tenerife 38108",
    "addr:housenumber":"11",
    "addr:postcode":"38108",
    "addr:street":"Calle De J Guttemberg",
    "iso:country":"ES",
    "sg:address":"Calle de J Guttemberg, 11",
    "sg:city":"Chorrillo",
    "sg:orig_category":"Transporte En General",
    "sg:phone":"+34 922 68 41 12",
    "sg:postcode":"38108",
    "sg:province":"Santa Cruz De Tenerife",
    "wof:name":"Leoter Tenerife S.l.",
    "wof:placetype":"venue"
},
  "geometry": {"coordinates":[-16.3180427551,28.4147777557],"type":"Point"}
}