{
  "type": "Feature",
  "properties": {
    "iso:country":"ES",
    "sg:address":"Avda Constitucion, 40",
    "sg:city":"Torrejon Ardoz",
    "sg:orig_category":"Agentes Y Bufetes De Negocio",
    "sg:phone":"+34 916 56 40 10",
    "sg:postcode":"28850",
    "sg:province":"Madrid",
    "wof:name":"Personal 7 Ett S.a.",
    "wof:placetype":"venue"
},
  "geometry": {"coordinates":[-3.4780321121,40.4560089111],"type":"Point"}
}