{
  "type": "Feature",
  "properties": {
    "iso:country":"ES",
    "sg:address":"Calle de Seguras (los), S/n",
    "sg:city":"San Javier",
    "sg:orig_category":"Negocio De Materiales De Construcci\u00d3n",
    "sg:phone":"+34 968 19 09 70",
    "sg:postcode":"30730",
    "sg:province":"Murcia",
    "wof:name":"Francisco Carrique Ros Y Joaquin-gerardo Castejon Gomez C.b.",
    "wof:placetype":"venue"
},
  "geometry": {"coordinates":[-0.8368890285,37.8077659607],"type":"Point"}
}