{
  "type": "Feature",
  "properties": {
    "addr:full":"Carr Creu, 8 Ciutadella Menorca Islas Baleares 07760",
    "addr:housenumber":"8",
    "addr:postcode":"07760",
    "addr:street":"Carr Creu",
    "iso:country":"ES",
    "sg:address":"Carr Creu, 8",
    "sg:city":"Ciutadella Menorca",
    "sg:orig_category":"Ebanister\u00cda",
    "sg:phone":"+34 971 38 39 16",
    "sg:postcode":"07760",
    "sg:province":"Islas Baleares",
    "wof:name":"Mobles A Mida C. B.",
    "wof:placetype":"venue"
},
  "geometry": {"coordinates":[3.8416149616,40.0027542114],"type":"Point"}
}