{
  "type": "Feature",
  "properties": {
    "addr:full":"Queipo De Llano, 1 Ribadavia Ourense 32400",
    "addr:housenumber":"1",
    "addr:postcode":"32400",
    "addr:street":"Queipo;Llano",
    "iso:country":"ES",
    "sg:address":"Queipo De Llano, 1",
    "sg:city":"Ribadavia",
    "sg:orig_category":"Confecci\u00d3n (fabricaci\u00d3n, Al Por Mayor)",
    "sg:phone":"+34 988 47 01 29",
    "sg:postcode":"32400",
    "sg:province":"Ourense",
    "wof:name":"Escudero Alvarez Paulino",
    "wof:placetype":"venue"
},
  "geometry": {"coordinates":[-8.1434307098,42.2893867493],"type":"Point"}
}