{
  "type": "Feature",
  "properties": {
    "iso:country":"ES",
    "sg:address":"Calle de Rector Diego Ramirez, 46",
    "sg:city":"Osuna",
    "sg:orig_category":"Formaci\u00d3n Continuada (variada)",
    "sg:phone":"+34 954 81 52 29",
    "sg:postcode":"41640",
    "sg:province":"Sevilla",
    "wof:name":"Asociacion Protectora De Deficientes Psiquicos Paz Y Bien De Sevilla",
    "wof:placetype":"venue"
},
  "geometry": {"coordinates":[-5.1087217331,37.2316322327],"type":"Point"}
}