{
  "type": "Feature",
  "properties": {
    "addr:full":"Avda Angel Guimera, 54 Santa Cruz De Tenerife Santa Cruz De Tenerife 38003",
    "addr:housenumber":"54",
    "addr:postcode":"38003",
    "addr:street":"Avda Angel Guimera",
    "iso:country":"ES",
    "sg:address":"Avda Angel Guimera, 54",
    "sg:city":"Santa Cruz De Tenerife",
    "sg:orig_category":"Asesor\u00cda De Formaci\u00d3n Y Gesti\u00d3n De Personal",
    "sg:phone":"+34 922 24 03 11",
    "sg:postcode":"38003",
    "sg:province":"Santa Cruz De Tenerife",
    "wof:name":"Arbey Asesores S.l.",
    "wof:placetype":"venue"
},
  "geometry": {"coordinates":[-16.2529296875,28.4666423798],"type":"Point"}
}