{
  "type": "Feature",
  "properties": {
    "addr:full":"Afores, 11 Lleida Lleida 25191",
    "addr:housenumber":"11",
    "addr:postcode":"25191",
    "addr:street":"Afores",
    "iso:country":"ES",
    "sg:address":"Afores, 11",
    "sg:city":"Lleida",
    "sg:orig_category":"Centros De Educaci\u00d3n Especial",
    "sg:phone":"+34 973 20 02 96",
    "sg:postcode":"25191",
    "sg:province":"Lleida",
    "wof:name":"Co%egi Public Magraners",
    "wof:placetype":"venue"
},
  "geometry": {"coordinates":[0.6831650138,41.5832138062],"type":"Point"}
}