{
  "type": "Feature",
  "properties": {
    "iso:country":"ES",
    "sg:address":"Calle de Puerta De Aguilar, 45",
    "sg:city":"Montilla",
    "sg:orig_category":"Muebles, Minoristas",
    "sg:phone":"+34 957 65 53 48",
    "sg:postcode":"14550",
    "sg:province":"C\u00f3rdoba",
    "wof:name":"Espejo Ruz Nicolas",
    "wof:placetype":"venue"
},
  "geometry": {"coordinates":[-4.6412382126,37.5852088928],"type":"Point"}
}