{
  "type": "Feature",
  "properties": {
    "addr:full":"Ctra. Port Des Torrent, S/n S. Agusti Vedra Islas Baleares 07839",
    "addr:housenumber":"s",
    "addr:postcode":"07839",
    "addr:street":"Ctra. Port Des Torrent;/ N S. Agusti",
    "iso:country":"ES",
    "sg:address":"Ctra. Port Des Torrent, S/n",
    "sg:city":"S. Agusti Vedra",
    "sg:orig_category":"Electrodom\u00c9sticos (al Por Menor)",
    "sg:phone":"+34 971 34 45 19",
    "sg:postcode":"07839",
    "sg:province":"Islas Baleares",
    "wof:name":"Serra Roig Antonia",
    "wof:placetype":"venue"
},
  "geometry": {"coordinates":[1.3025970459,38.8642692566],"type":"Point"}
}