{
  "type": "Feature",
  "properties": {
    "iso:country":"ES",
    "sg:address":"Poligono Berroa, 4",
    "sg:city":"Tajonar",
    "sg:orig_category":"Ingenier\u00cda, Centros De Estudios (diversos)",
    "sg:phone":"+34 948 07 33 01",
    "sg:postcode":"31192",
    "sg:province":"Navarra",
    "wof:name":"Ingenieria Lacuza San Martin S.l.",
    "wof:placetype":"venue"
},
  "geometry": {"coordinates":[-1.6151809692,42.7892303467],"type":"Point"}
}