{
  "type": "Feature",
  "properties": {
    "addr:full":"Avda Republica Argentina, 25 Cuenca Cuenca 16002",
    "addr:housenumber":"25",
    "addr:postcode":"16002",
    "addr:street":"Avda Republica Argentina",
    "iso:country":"ES",
    "sg:address":"Avda Republica Argentina, 25",
    "sg:city":"Cuenca",
    "sg:orig_category":"Asociaciones, Instituciones De Consumidores Y Usuarios",
    "sg:phone":"+34 969 23 42 35",
    "sg:postcode":"16002",
    "sg:province":"Cuenca",
    "wof:name":"Asociacion De Amas De Casa Consumidores Y Usuarios Luzan",
    "wof:placetype":"venue"
},
  "geometry": {"coordinates":[-2.1405351162,40.0716934204],"type":"Point"}
}