{
  "type": "Feature",
  "properties": {
    "iso:country":"ES",
    "sg:address":"Rbla Catalunya, 15",
    "sg:city":"Camarles",
    "sg:orig_category":"Materiales De Aislamiento T\u00c9rmico Y Ac\u00dastico",
    "sg:phone":"+34 977 47 07 52",
    "sg:postcode":"43894",
    "sg:province":"Tarragona",
    "wof:name":"Aislamientos Tarraco S.l.",
    "wof:placetype":"venue"
},
  "geometry": {"coordinates":[0.6709731817,40.772403717],"type":"Point"}
}