{
  "type": "Feature",
  "properties": {
    "addr:full":"Carr Comandant Hernandez, Del, 10 Carcaixent Valencia 46740",
    "addr:housenumber":"10",
    "addr:postcode":"46740",
    "addr:street":"Carr Comandant Hernandez Del",
    "iso:country":"ES",
    "sg:address":"Carr Comandant Hernandez, Del, 10",
    "sg:city":"Carcaixent",
    "sg:orig_category":"Loter\u00cda Y T\u00d3mbola",
    "sg:phone":"+34 962 46 06 51",
    "sg:postcode":"46740",
    "sg:province":"Valencia",
    "wof:name":"Albelda Diert Jose Salvador",
    "wof:placetype":"venue"
},
  "geometry": {"coordinates":[-0.451194495,39.1221847534],"type":"Point"}
}