{
  "type": "Feature",
  "properties": {
    "addr:full":"Calle de Gerardo Cordon, 2 Madrid Madrid 28017",
    "addr:housenumber":"2",
    "addr:postcode":"28017",
    "addr:street":"Calle De Gerardo Cordon",
    "iso:country":"ES",
    "sg:address":"Calle de Gerardo Cordon, 2",
    "sg:city":"Madrid",
    "sg:orig_category":"Confecci\u00d3n De Trajes Para Se\u00d1oras",
    "sg:phone":"+34 914 03 68 60",
    "sg:postcode":"28017",
    "sg:province":"Madrid",
    "wof:name":"Boni Charel S.l.",
    "wof:placetype":"venue"
},
  "geometry": {"coordinates":[-3.6554820538,40.4255523682],"type":"Point"}
}