{
  "type": "Feature",
  "properties": {
    "iso:country":"ES",
    "sg:address":"Urb Guindal (el), 60",
    "sg:city":"Cebreros",
    "sg:orig_category":"Energ\u00cda Solar Y Nuevas Energ\u00cdas (equipo, Estudios)",
    "sg:phone":"+34 918 63 07 07",
    "sg:postcode":"05260",
    "sg:province":"\u00c1vila",
    "wof:name":"Gonzalez Garcia-caro Ignacio",
    "wof:placetype":"venue"
},
  "geometry": {"coordinates":[-4.4618000984,40.4614715576],"type":"Point"}
}