{
  "type": "Feature",
  "properties": {
    "addr:full":"Los Angeles, 15 Oropesa Mar Castell\u00f3n 12594",
    "addr:housenumber":"15",
    "addr:postcode":"12594",
    "addr:street":"Los Angeles",
    "iso:country":"ES",
    "sg:address":"Los Angeles, 15",
    "sg:city":"Oropesa Mar",
    "sg:orig_category":"Molduras, Junquillos, Listones Y Molduras Perforadas",
    "sg:phone":"+34 964 31 09 70",
    "sg:postcode":"12594",
    "sg:province":"Castell\u00f3n",
    "wof:name":"Centelles Fores Adoracion",
    "wof:placetype":"venue"
},
  "geometry": {"coordinates":[0.1415199935,40.0908470154],"type":"Point"}
}