{
  "type": "Feature",
  "properties": {
    "iso:country":"ES",
    "sg:address":"Pje Alguero, S/n",
    "sg:city":"Onda",
    "sg:orig_category":"M\u00c9dicos: Estomatolog\u00cda",
    "sg:phone":"+34 964 60 02 98",
    "sg:postcode":"12200",
    "sg:province":"Castell\u00f3n",
    "wof:name":"Vidal Jove Jose Luis",
    "wof:placetype":"venue"
},
  "geometry": {"coordinates":[-0.2620640099,39.9651794434],"type":"Point"}
}