{
  "type": "Feature",
  "properties": {
    "iso:country":"ES",
    "sg:address":"Avda Vigo, 48",
    "sg:city":"Cangas",
    "sg:orig_category":"Mec\u00c1nico Del Autom\u00d3vil",
    "sg:phone":"+34 986 30 27 45",
    "sg:postcode":"36940",
    "sg:province":"Pontevedra",
    "wof:name":"Electroauto Cangas Sl",
    "wof:placetype":"venue"
},
  "geometry": {"coordinates":[-8.7873926163,42.2635536194],"type":"Point"}
}