{
  "type": "Feature",
  "properties": {
    "addr:full":"Sanguesa, 16 Iru\u00f1a Navarra 31003",
    "addr:housenumber":"16",
    "addr:postcode":"31003",
    "addr:street":"Sanguesa",
    "iso:country":"ES",
    "sg:address":"Sanguesa, 16",
    "sg:city":"Iru\u00f1a",
    "sg:orig_category":"M\u00c9dicos: Medicina General",
    "sg:phone":"+34 948 24 02 00",
    "sg:postcode":"31003",
    "sg:province":"Navarra",
    "wof:name":"Navarro Aragonesa De Servicios Del Conductor S. L.",
    "wof:placetype":"venue"
},
  "geometry": {"coordinates":[-1.6411700249,42.8110847473],"type":"Point"}
}