{
  "type": "Feature",
  "properties": {
    "iso:country":"ES",
    "sg:address":"Carrer de Princep Jordi, 16",
    "sg:city":"Barcelona",
    "sg:orig_category":"Inmobiliaria (agencias)",
    "sg:phone":"+34 934 26 87 20",
    "sg:postcode":"08014",
    "sg:province":"Barcelona",
    "wof:name":"Llobet Gimenez Joaquina",
    "wof:placetype":"venue"
},
  "geometry": {"coordinates":[2.1471540928,41.3759346008],"type":"Point"}
}