{
  "type": "Feature",
  "properties": {
    "iso:country":"ES",
    "sg:address":"Tecina, S/n",
    "sg:city":"S. Sebastian Gomera",
    "sg:orig_category":"Inmobiliaria (agencias)",
    "sg:phone":"+34 922 89 58 26",
    "sg:postcode":"38800",
    "sg:province":"Santa Cruz De Tenerife",
    "wof:name":"Terra Fortunata S.a.",
    "wof:placetype":"venue"
},
  "geometry": {"coordinates":[-17.1105136871,28.0907344818],"type":"Point"}
}