{
  "type": "Feature",
  "properties": {
    "addr:full":"Plaz Espa\u00d1a, 9 Badajoz Badajoz 06002",
    "addr:housenumber":"9",
    "addr:postcode":"06002",
    "addr:street":"Plaz Espan\u0303A",
    "iso:country":"ES",
    "sg:address":"Plaz Espa\u00d1a, 9",
    "sg:city":"Badajoz",
    "sg:orig_category":"Herboristas (al Por Menor)",
    "sg:phone":"+34 924 24 78 79",
    "sg:postcode":"06002",
    "sg:province":"Badajoz",
    "wof:name":"Trigo Ansola Antonia",
    "wof:placetype":"venue"
},
  "geometry": {"coordinates":[-6.9704060555,38.8780937195],"type":"Point"}
}