{
  "type": "Feature",
  "properties": {
    "iso:country":"ES",
    "sg:address":"Ctra Malaga, S/n",
    "sg:city":"Coin",
    "sg:orig_category":"Ropa Para Ni\u00d1os (al Por Menor)",
    "sg:phone":"+34 952 45 58 45",
    "sg:postcode":"29100",
    "sg:province":"M\u00e1laga",
    "wof:name":"Kiddys's Class S.a.",
    "wof:placetype":"venue"
},
  "geometry": {"coordinates":[-4.7551879883,36.6623802185],"type":"Point"}
}