{
  "type": "Feature",
  "properties": {
    "addr:full":"Doctor Castelo 10 Madrid 28009",
    "addr:housenumber":"10",
    "addr:postcode":"28009",
    "addr:street":"Doctor Castelo",
    "iso:country":"ES",
    "sg:address":"Doctor Castelo 10",
    "sg:city":"Madrid",
    "sg:classifiers":[
        {
            "category":"Professional",
            "subcategory":"Computer Services",
            "type":"Services"
        }
    ],
    "sg:postcode":"28009",
    "sg:tags":[
        "business",
        "models",
        "process",
        "procedure",
        "documentation"
    ],
    "sg:website":"http://metocube.com",
    "wof:name":"metoCube",
    "wof:placetype":"venue"
},
  "geometry": {"coordinates":[-3.6781213,40.4204601],"type":"Point"}
}