{
  "type": "Feature",
  "properties": {
    "addr:full":"Las Dalias, S/n S. Agustin-playa Ingles Las Palmas 35100",
    "addr:postcode":"35100",
    "addr:street":"Las Dalias S / N S. Agustin-Playa",
    "iso:country":"ES",
    "sg:address":"Las Dalias, S/n",
    "sg:city":"S. Agustin-playa Ingles",
    "sg:orig_category":"Supermercados Y Hipermercados",
    "sg:phone":"+34 928 76 52 07",
    "sg:postcode":"35100",
    "sg:province":"Las Palmas",
    "wof:name":"Alvymat S.a.",
    "wof:placetype":"venue"
},
  "geometry": {"coordinates":[-15.5478563309,27.767911911],"type":"Point"}
}