{
  "type": "Feature",
  "properties": {
    "addr:full":"Avda Almirante Bastarreche, 67 Alhama Murcia Murcia 30840",
    "addr:housenumber":"67",
    "addr:postcode":"30840",
    "addr:street":"Avda Almirante Bastarreche",
    "iso:country":"ES",
    "sg:address":"Avda Almirante Bastarreche, 67",
    "sg:city":"Alhama Murcia",
    "sg:orig_category":"Ingenier\u00cda, Centros De Estudios (industria)",
    "sg:phone":"+34 968 63 12 26",
    "sg:postcode":"30840",
    "sg:province":"Murcia",
    "wof:name":"Canales Hernandez Juan Antonio",
    "wof:placetype":"venue"
},
  "geometry": {"coordinates":[-1.4224460125,37.8471336365],"type":"Point"}
}