{
  "type": "Feature",
  "properties": {
    "iso:country":"ES",
    "sg:address":"Av Palma, 3",
    "sg:city":"Tossa",
    "sg:orig_category":"Supermercados Y Hipermercados",
    "sg:phone":"+34 972 34 22 19",
    "sg:postcode":"17320",
    "sg:province":"Girona",
    "wof:name":"Pares Artau Rosendo",
    "wof:placetype":"venue"
},
  "geometry": {"coordinates":[2.9324030876,41.7210350037],"type":"Point"}
}