{
  "type": "Feature",
  "properties": {
    "addr:full":"Calle de Estacion, 34 Miranda Ebro Burgos 09200",
    "addr:housenumber":"34",
    "addr:postcode":"09200",
    "addr:street":"Calle De Estacion",
    "iso:country":"ES",
    "sg:address":"Calle de Estacion, 34",
    "sg:city":"Miranda Ebro",
    "sg:orig_category":"Procuradores",
    "sg:phone":"+34 947 31 08 08",
    "sg:postcode":"09200",
    "sg:province":"Burgos",
    "wof:name":"Yela Ortiz Domingo",
    "wof:placetype":"venue"
},
  "geometry": {"coordinates":[-2.9450039864,42.6872062683],"type":"Point"}
}