{
  "type": "Feature",
  "properties": {
    "iso:country":"ES",
    "sg:address":"Calle de Duquesa De Parcent, 2",
    "sg:city":"Madrid",
    "sg:orig_category":"Tiendas De Grano, Frutas Y Legumbres Secas (al Por Menor)",
    "sg:phone":"+34 915 25 69 98",
    "sg:postcode":"28047",
    "sg:province":"Madrid",
    "wof:name":"Delfa Fernandez Yolanda",
    "wof:placetype":"venue"
},
  "geometry": {"coordinates":[-3.7479410172,40.3962135315],"type":"Point"}
}