{
  "type": "Feature",
  "properties": {
    "iso:country":"ES",
    "sg:address":"C/ Corredora, 4",
    "sg:city":"Elche",
    "sg:orig_category":"Confecci\u00d3n De Zapatos",
    "sg:phone":"+34 966 61 29 45",
    "sg:postcode":"03202",
    "sg:province":"Alicante",
    "wof:name":"Rumbo S.a.",
    "wof:placetype":"venue"
},
  "geometry": {"coordinates":[-0.5931239724,38.2568435669],"type":"Point"}
}