{
  "type": "Feature",
  "properties": {
    "iso:country":"ES",
    "sg:address":"Calle de Tibonidas, 21",
    "sg:city":"Granada",
    "sg:orig_category":"Barnizadores",
    "sg:phone":"+34 958 15 53 64",
    "sg:postcode":"18011",
    "sg:province":"Granada",
    "wof:name":"Cordobilla Martinez Manuel",
    "wof:placetype":"venue"
},
  "geometry": {"coordinates":[-3.6014831066,37.1958198547],"type":"Point"}
}