{
  "type": "Feature",
  "properties": {
    "addr:full":"Los Marinos, 3 Pasai S. Pedro Guip\u00f9zcoa 20110",
    "addr:housenumber":"3",
    "addr:postcode":"20110",
    "addr:street":"Los Marinos;Guipu\u0300Zcoa",
    "iso:country":"ES",
    "sg:address":"Los Marinos, 3",
    "sg:city":"Pasai S. Pedro",
    "sg:orig_category":"Asociaciones, Organismos Culturales Y Socioeducativos",
    "sg:phone":"+34 943 39 66 08",
    "sg:postcode":"20110",
    "sg:province":"Guip\u00f9zcoa",
    "wof:name":"Club Del Jubilado De Trintxerpe",
    "wof:placetype":"venue"
},
  "geometry": {"coordinates":[-1.9291290045,43.323348999],"type":"Point"}
}