{
  "type": "Feature",
  "properties": {
    "addr:full":"Calle de Nueva, 27 Archidona M\u00e1laga 29300",
    "addr:housenumber":"27",
    "addr:postcode":"29300",
    "addr:street":"Calle De Nueva;Ma\u0301Laga",
    "iso:country":"ES",
    "sg:address":"Calle de Nueva, 27",
    "sg:city":"Archidona",
    "sg:orig_category":"Producci\u00d3n, Distribuci\u00d3n De Gas Butano Y Propano",
    "sg:phone":"+34 952 71 49 34",
    "sg:postcode":"29300",
    "sg:province":"M\u00e1laga",
    "wof:name":"Cruz Sanchez S.l.",
    "wof:placetype":"venue"
},
  "geometry": {"coordinates":[-4.3884510994,37.0945053101],"type":"Point"}
}