{
  "type": "Feature",
  "properties": {
    "iso:country":"ES",
    "sg:address":"Nafarroa Etorbidea, 15",
    "sg:city":"Pasai Antxo",
    "sg:orig_category":"Muebles Y Accesorios Para Cocinas Y Cuartos De Ba\u00d1o (al Por Menor)",
    "sg:phone":"+34 943 51 03 89",
    "sg:postcode":"20110",
    "sg:province":"Guip\u00f9zcoa",
    "wof:name":"Muebles Ruiztegui S.a.",
    "wof:placetype":"venue"
},
  "geometry": {"coordinates":[-1.9172650576,43.3186759949],"type":"Point"}
}