{
  "type": "Feature",
  "properties": {
    "iso:country":"ES",
    "sg:address":"C/ Jose Mas Esteve, 43",
    "sg:city":"Elche",
    "sg:orig_category":"Ropa Y Accesorios",
    "sg:phone":"+34 965 43 74 09",
    "sg:postcode":"03201",
    "sg:province":"Alicante",
    "wof:name":"Jamstex S.l.l.",
    "wof:placetype":"venue"
},
  "geometry": {"coordinates":[-0.7111570239,38.2618789673],"type":"Point"}
}