{
  "type": "Feature",
  "properties": {
    "iso:country":"ES",
    "sg:address":"Calle de Lopez De Hoyos, 249",
    "sg:city":"Madrid",
    "sg:orig_category":"Quincaller\u00cda (al Por Mayor)",
    "sg:phone":"+34 914 15 84 74",
    "sg:postcode":"28043",
    "sg:province":"Madrid",
    "wof:name":"Roza-grapi S.a.",
    "wof:placetype":"venue"
},
  "geometry": {"coordinates":[-3.6625509262,40.4552726746],"type":"Point"}
}