{
  "type": "Feature",
  "properties": {
    "iso:country":"ES",
    "sg:address":"Calle de Santiago, 23",
    "sg:city":"Mengibar",
    "sg:orig_category":"Chapister\u00cda",
    "sg:phone":"+34 953 37 12 39",
    "sg:postcode":"23620",
    "sg:province":"Ja\u00e9n",
    "wof:name":"Cintas Millan Juan",
    "wof:placetype":"venue"
},
  "geometry": {"coordinates":[-3.80803895,37.972530365],"type":"Point"}
}