{
  "type": "Feature",
  "properties": {
    "addr:full":"Calle de Marqueses, S/n Samper Calanda Teruel 44520",
    "addr:housenumber":"s / n",
    "addr:postcode":"44520",
    "addr:street":"Calle De Marqueses",
    "iso:country":"ES",
    "sg:address":"Calle de Marqueses, S/n",
    "sg:city":"Samper Calanda",
    "sg:orig_category":"Molduras, Junquillos, Listones Y Molduras Perforadas",
    "sg:phone":"+34 978 82 28 18",
    "sg:postcode":"44520",
    "sg:province":"Teruel",
    "wof:name":"Biel Almolda Antonio",
    "wof:placetype":"venue"
},
  "geometry": {"coordinates":[-0.3900699914,41.1904640198],"type":"Point"}
}