{
  "type": "Feature",
  "properties": {
    "iso:country":"ES",
    "sg:address":"Calle de Martires Salesianos, 1",
    "sg:city":"Moron Frontera",
    "sg:orig_category":"Comercio, Reparaci\u00d3n De Motocicletas, Bicicletas Y Piezas Sueltas",
    "sg:phone":"+34 955 85 26 24",
    "sg:postcode":"41530",
    "sg:province":"Sevilla",
    "wof:name":"Alvarez Cabeza Maria Del Carmen",
    "wof:placetype":"venue"
},
  "geometry": {"coordinates":[-5.4591531754,37.1208724976],"type":"Point"}
}