{
  "type": "Feature",
  "properties": {
    "addr:full":"Calle de Camino De Malaga, 13 Velez-malaga M\u00e1laga 29700",
    "addr:housenumber":"13",
    "addr:postcode":"29700",
    "addr:street":"Calle De Camino De Malaga",
    "iso:country":"ES",
    "sg:address":"Calle de Camino De Malaga, 13",
    "sg:city":"Velez-malaga",
    "sg:orig_category":"Ropa Para Se\u00d1oras Y Caballeros (al Por Menor)",
    "sg:phone":"+34 952 50 77 34",
    "sg:postcode":"29700",
    "sg:province":"M\u00e1laga",
    "wof:name":"Guirado Lara Antonio",
    "wof:placetype":"venue"
},
  "geometry": {"coordinates":[-4.1037983894,36.7792701721],"type":"Point"}
}