{
  "type": "Feature",
  "properties": {
    "addr:full":"Aldea Casa Nueva, S/n Sta. Marta Albacete 02639",
    "addr:housenumber":"s / n",
    "addr:postcode":"02639",
    "iso:country":"ES",
    "sg:address":"Aldea Casa Nueva, S/n",
    "sg:city":"Sta. Marta",
    "sg:orig_category":"Cr\u00cda De Animales",
    "sg:phone":"+34 967 57 00 27",
    "sg:postcode":"02639",
    "sg:province":"Albacete",
    "wof:name":"Agropecuaria Marte\u00f1a S.a.",
    "wof:placetype":"venue"
},
  "geometry": {"coordinates":[-1.8600701094,38.9976501465],"type":"Point"}
}