{
  "type": "Feature",
  "properties": {
    "addr:full":"Calle de Barcelona, 49 Alacant Alicante 03013",
    "addr:housenumber":"49",
    "addr:postcode":"03013",
    "addr:street":"Calle De Barcelona",
    "iso:country":"ES",
    "sg:address":"Calle de Barcelona, 49",
    "sg:city":"Alacant",
    "sg:orig_category":"Iglesias Cristianas Diversas",
    "sg:phone":"+34 965 14 48 05",
    "sg:postcode":"03013",
    "sg:province":"Alicante",
    "wof:name":"Lectorium Rosicrucianum",
    "wof:placetype":"venue"
},
  "geometry": {"coordinates":[-0.4758014977,38.3562278748],"type":"Point"}
}