{
  "type": "Feature",
  "properties": {
    "addr:full":"Calle de Afrechos (los), S/n Puerto Del Carmen Las Palmas 35510",
    "addr:housenumber":"s / n",
    "addr:postcode":"35510",
    "addr:street":"Calle De Afrechos Los",
    "iso:country":"ES",
    "sg:address":"Calle de Afrechos (los), S/n",
    "sg:city":"Puerto Del Carmen",
    "sg:orig_category":"Asesor\u00cda Fiscal Y Jur\u00cddica",
    "sg:phone":"+34 928 51 02 50",
    "sg:postcode":"35510",
    "sg:province":"Las Palmas",
    "wof:name":"Callero Asesores S.l.",
    "wof:placetype":"venue"
},
  "geometry": {"coordinates":[-13.6737661362,28.9230098724],"type":"Point"}
}