{
  "type": "Feature",
  "properties": {
    "iso:country":"ES",
    "sg:address":"Calle de Navalmoral De La Mata, 2",
    "sg:city":"Coria",
    "sg:orig_category":"Internados & Ense\u00d1anza Privada",
    "sg:phone":"+34 927 50 11 95",
    "sg:postcode":"10800",
    "sg:province":"C\u00e1ceres",
    "wof:name":"Esclavas Del Divino Corazon Provincia Espa\u00d1a Norte Curia Provincial",
    "wof:placetype":"venue"
},
  "geometry": {"coordinates":[-6.5307588577,39.9837265015],"type":"Point"}
}