{
  "type": "Feature",
  "properties": {
    "iso:country":"ES",
    "sg:address":"Calle de Alonso De Ojeda, 6",
    "sg:city":"Flota",
    "sg:orig_category":"Administradores De Bienes Y Delegados De Comunidades De Propietarios",
    "sg:phone":"+34 968 27 18 88",
    "sg:postcode":"30007",
    "sg:province":"Murcia",
    "wof:name":"1959 Asesores S. L.",
    "wof:placetype":"venue"
},
  "geometry": {"coordinates":[-1.119955,37.993504],"type":"Point"}
}