{
  "type": "Feature",
  "properties": {
    "iso:country":"ES",
    "sg:address":"Calle de Fray Junipero Serra, 71",
    "sg:city":"Valencia",
    "sg:orig_category":"Venta, Instalaci\u00d3n, Reparaci\u00d3n De Antenas Para Televisi\u00d3n",
    "sg:phone":"+34 963 57 86 62",
    "sg:postcode":"46014",
    "sg:province":"Valencia",
    "wof:name":"Grupo Lasser Iberica De Comercio S.a.",
    "wof:placetype":"venue"
},
  "geometry": {"coordinates":[-0.4006989896,39.4618110657],"type":"Point"}
}