{
  "type": "Feature",
  "properties": {
    "addr:full":"Ctra Ronda (de), 155 Almeria Almer\u00eda 04004",
    "addr:housenumber":"155",
    "addr:postcode":"04004",
    "addr:street":"Ctra Ronda De",
    "iso:country":"ES",
    "sg:address":"Ctra Ronda (de), 155",
    "sg:city":"Almeria",
    "sg:orig_category":"Electricidad: Material Y Suministros De Instalaci\u00d3n (fabricaci\u00d3n)",
    "sg:phone":"+34 950 22 31 51",
    "sg:postcode":"04004",
    "sg:province":"Almer\u00eda",
    "wof:name":"Juan Galindo S.l.",
    "wof:placetype":"venue"
},
  "geometry": {"coordinates":[-2.4564709663,36.8360519409],"type":"Point"}
}