{
  "type": "Feature",
  "properties": {
    "iso:country":"ES",
    "sg:address":"Avda Fred Olsen, 4",
    "sg:city":"Arrecife",
    "sg:orig_category":"Agencias De Viajes",
    "sg:phone":"+34 928 80 71 77",
    "sg:postcode":"35500",
    "sg:province":"Las Palmas",
    "wof:name":"Club Viajes Las Salinas S.l.",
    "wof:placetype":"venue"
},
  "geometry": {"coordinates":[-13.5570516586,28.9586448669],"type":"Point"}
}