{
  "type": "Feature",
  "properties": {
    "iso:country":"ES",
    "sg:address":"C/ Pau Casals, 56",
    "sg:city":"Salt",
    "sg:orig_category":"Tapicer\u00cdas",
    "sg:phone":"+34 972 23 36 16",
    "sg:postcode":"17190",
    "sg:province":"Girona",
    "wof:name":"Gazquez Oliveras Juan",
    "wof:placetype":"venue"
},
  "geometry": {"coordinates":[2.7931699753,41.9762115479],"type":"Point"}
}