{
  "type": "Feature",
  "properties": {
    "addr:full":"Calle de Diego Llorente, 47 Palacios Y Villafranca Sevilla 41720",
    "addr:housenumber":"47",
    "addr:postcode":"41720",
    "addr:street":"Calle De Diego Llorente",
    "iso:country":"ES",
    "sg:address":"Calle de Diego Llorente, 47",
    "sg:city":"Palacios Y Villafranca",
    "sg:orig_category":"Tapicer\u00cdas",
    "sg:phone":"+34 955 81 34 45",
    "sg:postcode":"41720",
    "sg:province":"Sevilla",
    "wof:name":"Lovera Garcia Jose Maria",
    "wof:placetype":"venue"
},
  "geometry": {"coordinates":[-5.9245090485,37.1603431702],"type":"Point"}
}