{
  "type": "Feature",
  "properties": {
    "addr:full":"Calle de Castrojeriz, 22 Madrid Madrid 28025",
    "addr:housenumber":"22",
    "addr:postcode":"madrid;28025",
    "addr:street":"Calle De Castrojeriz",
    "iso:country":"ES",
    "sg:address":"Calle de Castrojeriz, 22",
    "sg:city":"Madrid",
    "sg:orig_category":"Molduras, Junquillos, Listones Y Molduras Perforadas",
    "sg:phone":"+34 914 65 47 58",
    "sg:postcode":"28025",
    "sg:province":"Madrid",
    "wof:name":"Dimas Burgos C.b",
    "wof:placetype":"venue"
},
  "geometry": {"coordinates":[-3.728276968,40.3764381409],"type":"Point"}
}