{
  "type": "Feature",
  "properties": {
    "addr:full":"Calle de Beato Jacinto Orfanell, 11 Sant Mateu Castell\u00f3n 12170",
    "addr:housenumber":"11",
    "addr:postcode":"12170",
    "addr:street":"Calle De Beato Jacinto Orfanell",
    "iso:country":"ES",
    "sg:address":"Calle de Beato Jacinto Orfanell, 11",
    "sg:city":"Sant Mateu",
    "sg:orig_category":"Supermercados Y Hipermercados",
    "sg:phone":"+34 964 41 60 07",
    "sg:postcode":"12170",
    "sg:province":"Castell\u00f3n",
    "wof:name":"Fragadis S.l.",
    "wof:placetype":"venue"
},
  "geometry": {"coordinates":[0.1793050021,40.4640235901],"type":"Point"}
}