{
  "type": "Feature",
  "properties": {
    "iso:country":"ES",
    "sg:address":"Avda Madariaga, 29",
    "sg:city":"Bilbao",
    "sg:orig_category":"Pintores",
    "sg:phone":"+34 944 05 53 34",
    "sg:postcode":"48014",
    "sg:province":"Vizcaya",
    "wof:name":"Estudio De Dibujo Y Pintura I\u00f1aki Arce Sagarduy",
    "wof:placetype":"venue"
},
  "geometry": {"coordinates":[-2.9485518932,43.2708816528],"type":"Point"}
}