{
  "type": "Feature",
  "properties": {
    "iso:country":"ES",
    "sg:address":"Calle de Cullera, S/n",
    "sg:city":"Madrid",
    "sg:orig_category":"Frutas, Legumbres Frescas Y Tempranas (al Por Menor)",
    "sg:phone":"+34 914 62 28 37",
    "sg:postcode":"28047",
    "sg:province":"Madrid",
    "wof:name":"Velasco Alvaro Teresa",
    "wof:placetype":"venue"
},
  "geometry": {"coordinates":[-3.7464718819,40.3967285156],"type":"Point"}
}