{
  "type": "Feature",
  "properties": {
    "iso:country":"ES",
    "sg:address":"Calle de Claudio Moyano, 4",
    "sg:city":"Valladolid",
    "sg:orig_category":"Asesor\u00cda Sobre Comunicaci\u00d3n De Empresas",
    "sg:phone":"+34 983 35 50 41",
    "sg:postcode":"47001",
    "sg:province":"Valladolid",
    "wof:name":"Garcia De Blas Emiliano",
    "wof:placetype":"venue"
},
  "geometry": {"coordinates":[-4.7290606499,41.6488990784],"type":"Point"}
}