{
  "type": "Feature",
  "properties": {
    "addr:full":"Ctra Molino El, 7 Firgas Las Palmas 35430",
    "addr:housenumber":"7",
    "addr:postcode":"35430",
    "addr:street":"Ctra Molino El",
    "iso:country":"ES",
    "sg:address":"Ctra Molino El, 7",
    "sg:city":"Firgas",
    "sg:orig_category":"Peluquer\u00cdas, Peluquer\u00cda Mixta",
    "sg:phone":"+34 928 62 52 61",
    "sg:postcode":"35430",
    "sg:province":"Las Palmas",
    "wof:name":"Delafe Falcon Raquel",
    "wof:placetype":"venue"
},
  "geometry": {"coordinates":[-15.5624837875,28.1076145172],"type":"Point"}
}