{
  "type": "Feature",
  "properties": {
    "iso:country":"ES",
    "sg:address":"Avda Ramon Y Cajal, 74",
    "sg:city":"Portugalete",
    "sg:orig_category":"Maquinaria Para Industrias Diversas",
    "sg:phone":"+34 944 95 72 61",
    "sg:postcode":"48920",
    "sg:province":"Vizcaya",
    "wof:name":"Aplicaciones Nuevas Tecnologias A.n.t.e.c. S.a.",
    "wof:placetype":"venue"
},
  "geometry": {"coordinates":[-3.018150568,43.314781189],"type":"Point"}
}