{
  "type": "Feature",
  "properties": {
    "iso:country":"ES",
    "sg:address":"Calle de General Aranda, 12",
    "sg:city":"Ceuta",
    "sg:orig_category":"Confecci\u00d3n (fabricaci\u00d3n, Al Por Mayor)",
    "sg:phone":"+34 956 51 47 02",
    "sg:postcode":"51001",
    "sg:province":"Ceuta",
    "wof:name":"Israel Laredo Moises",
    "wof:placetype":"venue"
},
  "geometry": {"coordinates":[-5.3074469566,35.8878326416],"type":"Point"}
}