{
  "type": "Feature",
  "properties": {
    "addr:full":"Calle de Felipe Ii, 4 Sevilla Sevilla 41013",
    "addr:housenumber":"4",
    "addr:postcode":"41013",
    "addr:street":"Calle De Felipe Ii",
    "iso:country":"ES",
    "sg:address":"Calle de Felipe Ii, 4",
    "sg:city":"Sevilla",
    "sg:orig_category":"Arquitectos",
    "sg:phone":"+34 954 23 61 63",
    "sg:postcode":"41013",
    "sg:province":"Sevilla",
    "wof:name":"Rodriguez Merchan Carmelo",
    "wof:placetype":"venue"
},
  "geometry": {"coordinates":[-5.9848570824,37.3718070984],"type":"Point"}
}