{
  "type": "Feature",
  "properties": {
    "addr:full":"Pase Primero De Mayo, 22 Jodar Ja\u00e9n 23500",
    "addr:housenumber":"22",
    "addr:postcode":"23500",
    "addr:street":"Primero De Mayo;Jae\u0301N",
    "iso:country":"ES",
    "sg:address":"Pase Primero De Mayo, 22",
    "sg:city":"Jodar",
    "sg:orig_category":"Productos Qu\u00cdmicos (fabricaci\u00d3n, Al Por Mayor)",
    "sg:phone":"+34 953 78 68 80",
    "sg:postcode":"23500",
    "sg:province":"Ja\u00e9n",
    "wof:name":"Bioferba S.l.",
    "wof:placetype":"venue"
},
  "geometry": {"coordinates":[-3.3526499271,37.839553833],"type":"Point"}
}