{
  "type": "Feature",
  "properties": {
    "addr:full":"Avda Aureliano San Roman, 42 Oviedo Asturias 33011",
    "addr:housenumber":"42",
    "addr:postcode":"33011",
    "addr:street":"Avda Aureliano San Roman",
    "iso:country":"ES",
    "sg:address":"Avda Aureliano San Roman, 42",
    "sg:city":"Oviedo",
    "sg:orig_category":"Cajas De Ahorro",
    "sg:phone":"+34 985 28 23 38",
    "sg:postcode":"33011",
    "sg:province":"Asturias",
    "wof:name":"Caja De Ahorros De Asturias",
    "wof:placetype":"venue"
},
  "geometry": {"coordinates":[-5.838092804,43.3705253601],"type":"Point"}
}