{
  "type": "Feature",
  "properties": {
    "addr:full":"La Ina, 21 Torrecera C\u00e1diz 11595",
    "addr:housenumber":"21",
    "addr:postcode":"11595",
    "addr:street":"Torrecera Ca\u0301Diz",
    "iso:country":"ES",
    "sg:address":"La Ina, 21",
    "sg:city":"Torrecera",
    "sg:orig_category":"Producci\u00d3n, Venta De Productos De Agricultura Biol\u00d3gica",
    "sg:phone":"+34 956 16 17 70",
    "sg:postcode":"11595",
    "sg:province":"C\u00e1diz",
    "wof:name":"Sociedad Cooperativa Andaluza Vegabermeja",
    "wof:placetype":"venue"
},
  "geometry": {"coordinates":[-5.9441328049,36.6098365784],"type":"Point"}
}