{
  "type": "Feature",
  "properties": {
    "iso:country":"ES",
    "sg:address":"Rbla Poblenou, 11",
    "sg:city":"Barcelona",
    "sg:orig_category":"Albergues",
    "sg:phone":"+34 932 25 26 60",
    "sg:postcode":"08005",
    "sg:province":"Barcelona",
    "wof:name":"Guss-disseny S.l.",
    "wof:placetype":"venue"
},
  "geometry": {"coordinates":[2.2046890259,41.398223877],"type":"Point"}
}