{
  "type": "Feature",
  "properties": {
    "iso:country":"ES",
    "sg:address":"Av Catalunya, 34",
    "sg:city":"Bellpuig",
    "sg:orig_category":"Asociaciones Y Clubs Deportivos",
    "sg:phone":"+34 973 32 23 33",
    "sg:postcode":"25250",
    "sg:province":"Lleida",
    "wof:name":"Penya Blaugrana Bellpuig",
    "wof:placetype":"venue"
},
  "geometry": {"coordinates":[1.0115410089,41.628326416],"type":"Point"}
}