{
  "type": "Feature",
  "properties": {
    "iso:country":"ES",
    "sg:address":"Urb Miradores (los), 15",
    "sg:city":"Ecija",
    "sg:orig_category":"Mec\u00c1nico Del Autom\u00d3vil",
    "sg:phone":"+34 954 83 36 07",
    "sg:postcode":"41400",
    "sg:province":"Sevilla",
    "wof:name":"Autorecambios Rayjo S.l.",
    "wof:placetype":"venue"
},
  "geometry": {"coordinates":[-5.0836591721,37.5329704285],"type":"Point"}
}