{
  "type": "Feature",
  "properties": {
    "iso:country":"ES",
    "sg:address":"Calle de Zabaleta, 18",
    "sg:city":"Donostia-san Sebastian",
    "sg:orig_category":"Iglesia Cat\u00d3lica",
    "sg:phone":"+34 943 27 04 20",
    "sg:postcode":"20002",
    "sg:province":"Guip\u00f9zcoa",
    "wof:name":"Parroquia De San Ignacio",
    "wof:placetype":"venue"
},
  "geometry": {"coordinates":[-1.9752550125,43.3235321045],"type":"Point"}
}