{
  "type": "Feature",
  "properties": {
    "addr:full":"Avda Lope De Vega, 1 Infante Juan Manuel Murcia 30011",
    "addr:housenumber":"1",
    "addr:postcode":"30011",
    "addr:street":"Avda Lope De Vega;Juan",
    "iso:country":"ES",
    "sg:address":"Avda Lope De Vega, 1",
    "sg:city":"Infante Juan Manuel",
    "sg:orig_category":"Peluquer\u00cdas, Peluquer\u00cda Mixta",
    "sg:phone":"+34 968 34 16 41",
    "sg:postcode":"30011",
    "sg:province":"Murcia",
    "sg:website":"www.ramonpeluqueros.com",
    "wof:name":"Ramon Peluqueros S.l.",
    "wof:placetype":"venue"
},
  "geometry": {"coordinates":[-1.1138839722,37.9804992676],"type":"Point"}
}