{
  "type": "Feature",
  "properties": {
    "addr:full":"Calle de Plaza (la), 2 Alcala Santa Cruz De Tenerife 38686",
    "addr:postcode":"38686",
    "addr:street":"Calle De Plaza La 2",
    "iso:country":"ES",
    "sg:address":"Calle de Plaza (la), 2",
    "sg:city":"Alcala",
    "sg:orig_category":"Librer\u00cdas",
    "sg:phone":"+34 922 86 59 76",
    "sg:postcode":"38686",
    "sg:province":"Santa Cruz De Tenerife",
    "wof:name":"Herrera Alvarez Juan Francisco",
    "wof:placetype":"venue"
},
  "geometry": {"coordinates":[-16.8268890381,28.2005367279],"type":"Point"}
}