{
  "type": "Feature",
  "properties": {
    "iso:country":"ES",
    "sg:address":"Avda Castelao, S/n",
    "sg:city":"Cedeira",
    "sg:orig_category":"Mercer\u00cda, Lencer\u00cda (al Por Menor)",
    "sg:phone":"+34 981 48 03 46",
    "sg:postcode":"15350",
    "sg:province":"La Coru\u00f1a",
    "wof:name":"Iglesias Bereijo Antonia",
    "wof:placetype":"venue"
},
  "geometry": {"coordinates":[-8.0536136627,43.6602706909],"type":"Point"}
}