{
  "type": "Feature",
  "properties": {
    "iso:country":"ES",
    "sg:address":"Pase Maritimo, 65",
    "sg:city":"Torremolinos",
    "sg:orig_category":"Ropa Para Se\u00d1oras Y Caballeros (al Por Menor)",
    "sg:phone":"+34 952 38 33 43",
    "sg:postcode":"29620",
    "sg:province":"M\u00e1laga",
    "wof:name":"Exclusivas Garcia Torres S.l.",
    "wof:placetype":"venue"
},
  "geometry": {"coordinates":[-4.4879169464,36.6325759888],"type":"Point"}
}