{
  "type": "Feature",
  "properties": {
    "iso:country":"ES",
    "sg:address":"Carrer de Sagrament, 10",
    "sg:city":"Sant Feliu Llobregat",
    "sg:orig_category":"Reposter\u00cdas",
    "sg:phone":"+34 936 66 77 18",
    "sg:postcode":"08980",
    "sg:province":"Barcelona",
    "wof:name":"Torrents Olive Maria Del Carmen",
    "wof:placetype":"venue"
},
  "geometry": {"coordinates":[2.0456490517,41.3881797791],"type":"Point"}
}