{
  "type": "Feature",
  "properties": {
    "iso:country":"ES",
    "sg:address":"Avda Reina Sofia, 22",
    "sg:city":"Gibraleon",
    "sg:orig_category":"Empresas De Pintura Y Revestimientos",
    "sg:phone":"+34 959 30 18 14",
    "sg:postcode":"21500",
    "sg:province":"Huelva",
    "wof:name":"Decoraciones Hermanos Palanco S.l.",
    "wof:placetype":"venue"
},
  "geometry": {"coordinates":[-6.9619407654,37.3766212463],"type":"Point"}
}