{
  "type": "Feature",
  "properties": {
    "addr:full":"Muel Ca\u00d1onero Dato, 1 Ceuta Ceuta 51001",
    "addr:housenumber":"1",
    "addr:postcode":"51001",
    "addr:street":"Dato",
    "iso:country":"ES",
    "sg:address":"Muel Ca\u00d1onero Dato, 1",
    "sg:city":"Ceuta",
    "sg:orig_category":"Alimentaci\u00d3n General (al Por Mayor)",
    "sg:phone":"+34 956 52 23 06",
    "sg:postcode":"51001",
    "sg:province":"Ceuta",
    "wof:name":"Chapela Ceuta Distribucion S.l.",
    "wof:placetype":"venue"
},
  "geometry": {"coordinates":[-5.3262000084,35.8962478638],"type":"Point"}
}