{
  "type": "Feature",
  "properties": {
    "iso:country":"ES",
    "sg:address":"Miravalles, 15",
    "sg:city":"Iru\u00f1a",
    "sg:classifiers":[
        {
            "category":"Autos & Motor Vehicles",
            "subcategory":"Automobile Sales",
            "type":"Retail Goods"
        }
    ],
    "sg:phone":"+34 948 13 17 84",
    "sg:postcode":"31015",
    "sg:province":"Navarra",
    "wof:name":"Plaza Inversiones S.l.",
    "wof:placetype":"venue"
},
  "geometry": {"coordinates":[-1.6252930164,42.8305015564],"type":"Point"}
}