{
  "type": "Feature",
  "properties": {
    "iso:country":"ES",
    "sg:address":"Av Sant Esteve, 35",
    "sg:city":"Granollers",
    "sg:orig_category":"Zapatos (al Por Menor)",
    "sg:phone":"+34 938 79 06 37",
    "sg:postcode":"08402",
    "sg:province":"Barcelona",
    "wof:name":"Castinon S.l.",
    "wof:placetype":"venue"
},
  "geometry": {"coordinates":[2.2906999588,41.6037940979],"type":"Point"}
}