{
  "type": "Feature",
  "properties": {
    "iso:country":"ES",
    "sg:address":"Poligono Siresa, S/n",
    "sg:city":"Reinosa",
    "sg:orig_category":"Formaci\u00d3n Continuada (variada)",
    "sg:phone":"+34 942 75 38 58",
    "sg:postcode":"39200",
    "sg:province":"Cantabria",
    "wof:name":"Ampros-c.o.r.",
    "wof:placetype":"venue"
},
  "geometry": {"coordinates":[-4.1391539574,43.000705719],"type":"Point"}
}