{
  "type": "Feature",
  "properties": {
    "addr:full":"Pase Olmos De Los, 5 Donostia-san Sebastian Guip\u00f9zcoa 20016",
    "addr:postcode":"20016",
    "iso:country":"ES",
    "sg:address":"Pase Olmos De Los, 5",
    "sg:city":"Donostia-san Sebastian",
    "sg:orig_category":"Maquinaria Para Industrias Diversas",
    "sg:phone":"+34 943 39 62 47",
    "sg:postcode":"20016",
    "sg:province":"Guip\u00f9zcoa",
    "sg:website":"www.roverasteca.com",
    "wof:name":"Productos Asteca S A",
    "wof:placetype":"venue"
},
  "geometry": {"coordinates":[-1.942620039,43.3229598999],"type":"Point"}
}