{
  "type": "Feature",
  "properties": {
    "iso:country":"ES",
    "sg:address":"Pol. Industrial, S/n",
    "sg:city":"Osorno",
    "sg:orig_category":"Mataderos Y Talleres De Despiezado",
    "sg:phone":"+34 979 81 74 40",
    "sg:postcode":"34460",
    "sg:province":"Palencia",
    "wof:name":"Sociedad Cooperativa Carnicas Osorno",
    "wof:placetype":"venue"
},
  "geometry": {"coordinates":[-4.361468792,42.4103851318],"type":"Point"}
}