{
  "type": "Feature",
  "properties": {
    "iso:country":"ES",
    "sg:address":"Q. Llano, 19",
    "sg:city":"Fuente S. Esteban",
    "sg:orig_category":"Reposter\u00cdas",
    "sg:phone":"+34 923 44 02 19",
    "sg:postcode":"37200",
    "sg:province":"Salamanca",
    "wof:name":"Sucesores De M Fraile C.b.",
    "wof:placetype":"venue"
},
  "geometry": {"coordinates":[-6.1650328636,40.826171875],"type":"Point"}
}