{
  "type": "Feature",
  "properties": {
    "addr:full":"Ctra Plasencia, 25 Tejeda Tietar C\u00e1ceres 10420",
    "addr:housenumber":"25",
    "addr:postcode":"10420",
    "addr:street":"Ctra Plasencia;Ca\u0301Ceres",
    "iso:country":"ES",
    "sg:address":"Ctra Plasencia, 25",
    "sg:city":"Tejeda Tietar",
    "sg:orig_category":"Otros Trabajos De Limpieza Y Mantenimiento (extracci\u00d3n De Polvo, Recogida De Amianto Y Desespumado)",
    "sg:phone":"+34 927 46 91 28",
    "sg:postcode":"10420",
    "sg:province":"C\u00e1ceres",
    "wof:name":"Calle Suarez Francisco De La",
    "wof:placetype":"venue"
},
  "geometry": {"coordinates":[-5.8671169281,40.018157959],"type":"Point"}
}