{
  "type": "Feature",
  "properties": {
    "iso:country":"ES",
    "sg:address":"Poli Poligono Industrial Fuente Santa, S/n",
    "sg:city":"Loja",
    "sg:orig_category":"Comercio De Piezas De Recambio Y De Accesorios De Veh\u00cdculos, Veh\u00cdculos Industriales",
    "sg:phone":"+34 958 32 74 17",
    "sg:postcode":"18300",
    "sg:province":"Granada",
    "wof:name":"Francisco Salas E Hijos S.l.",
    "wof:placetype":"venue"
},
  "geometry": {"coordinates":[-4.1505270004,37.1690177917],"type":"Point"}
}