{
  "type": "Feature",
  "properties": {
    "iso:country":"ES",
    "sg:address":"Carr Bisbe Lorenzana, 44",
    "sg:city":"Girona",
    "sg:orig_category":"Tapiceros Y Tapiceros",
    "sg:phone":"+34 972 21 02 28",
    "sg:postcode":"17002",
    "sg:province":"Girona",
    "wof:name":"Sole Farro Josep",
    "wof:placetype":"venue"
},
  "geometry": {"coordinates":[2.8187348843,41.979019165],"type":"Point"}
}