{
  "type": "Feature",
  "properties": {
    "addr:full":"Calle de Pe\u00d1a Herbosa, 31 Santander Cantabria 39003",
    "addr:housenumber":"31",
    "addr:postcode":"39003",
    "addr:street":"Calle De Pen\u0303A Herbosa",
    "iso:country":"ES",
    "sg:address":"Calle de Pe\u00d1a Herbosa, 31",
    "sg:city":"Santander",
    "sg:orig_category":"Empresas De Carpinter\u00cda De Madera",
    "sg:phone":"+34 942 21 53 15",
    "sg:postcode":"39003",
    "sg:province":"Cantabria",
    "wof:name":"Cruz Gonzalez Bernardo",
    "wof:placetype":"venue"
},
  "geometry": {"coordinates":[-3.7970159054,43.4636993408],"type":"Point"}
}