{
  "type": "Feature",
  "properties": {
    "addr:full":"Covadonga, 15 Infiesto Asturias 33530",
    "addr:housenumber":"15",
    "addr:postcode":"33530",
    "addr:street":"Covadonga",
    "iso:country":"ES",
    "sg:address":"Covadonga, 15",
    "sg:city":"Infiesto",
    "sg:orig_category":"Loter\u00cda Y T\u00d3mbola",
    "sg:phone":"+34 985 71 06 33",
    "sg:postcode":"33530",
    "sg:province":"Asturias",
    "wof:name":"Guisasola Eguibar Josefa",
    "wof:placetype":"venue"
},
  "geometry": {"coordinates":[-5.3624849319,43.3464012146],"type":"Point"}
}