{
  "type": "Feature",
  "properties": {
    "iso:country":"ES",
    "sg:address":"Via Trafico Pesado-p I La Paz, S/n",
    "sg:city":"Huelva",
    "sg:orig_category":"Arboricultura Y Producci\u00d3n De Frutas",
    "sg:phone":"+34 959 22 73 54",
    "sg:postcode":"21003",
    "sg:province":"Huelva",
    "wof:name":"Frutemsa S.a.",
    "wof:placetype":"venue"
},
  "geometry": {"coordinates":[-6.9364490509,37.2522010803],"type":"Point"}
}