{
  "type": "Feature",
  "properties": {
    "addr:full":"Calle de Astillero, 6 Bilbao Vizcaya 48013",
    "addr:housenumber":"6",
    "addr:postcode":"48013",
    "addr:street":"Calle De Astillero",
    "iso:country":"ES",
    "sg:address":"Calle de Astillero, 6",
    "sg:city":"Bilbao",
    "sg:orig_category":"Estancos",
    "sg:phone":"+34 944 90 45 67",
    "sg:postcode":"48013",
    "sg:province":"Vizcaya",
    "wof:name":"Escanciano Riero Felipe",
    "wof:placetype":"venue"
},
  "geometry": {"coordinates":[-2.9814510345,43.303604126],"type":"Point"}
}