{
  "type": "Feature",
  "properties": {
    "addr:full":"Ctra N-152, Km. 0023,2 Can Gosc Barcelona 08150",
    "addr:postcode":"08150",
    "addr:street":"Ctra N-152 Km. 0023,2",
    "iso:country":"ES",
    "sg:address":"Ctra N-152, Km. 0023,2",
    "sg:city":"Can Gosc",
    "sg:orig_category":"Aceros Especiales",
    "sg:phone":"+34 935 73 10 03",
    "sg:postcode":"08150",
    "sg:province":"Barcelona",
    "sg:website":"www.schroder-int.com",
    "wof:name":"Schroder Internacional S.l.",
    "wof:placetype":"venue"
},
  "geometry": {"coordinates":[2.2319469452,41.5694198608],"type":"Point"}
}