{
  "type": "Feature",
  "properties": {
    "addr:full":"Calle de Perez Galdos, 6 Bilbao Vizcaya 48010",
    "addr:housenumber":"6",
    "addr:postcode":"48010",
    "addr:street":"Calle De Perez Galdos",
    "iso:country":"ES",
    "sg:address":"Calle de Perez Galdos, 6",
    "sg:city":"Bilbao",
    "sg:orig_category":"Pescader\u00cdas (al Por Menor)",
    "sg:phone":"+34 944 21 68 60",
    "sg:postcode":"48010",
    "sg:province":"Vizcaya",
    "wof:name":"Maria Pilar Gonzalez Torrecilla",
    "wof:placetype":"venue"
},
  "geometry": {"coordinates":[-2.9416270256,43.2590255737],"type":"Point"}
}