{
  "type": "Feature",
  "properties": {
    "addr:full":"Ctra. Gibraleon, 9 Huelva Huelva 21002",
    "addr:housenumber":"9",
    "addr:postcode":"21002",
    "addr:street":"Ctra. Gibraleon",
    "iso:country":"ES",
    "sg:address":"Ctra. Gibraleon, 9",
    "sg:city":"Huelva",
    "sg:orig_category":"Mec\u00c1nico Del Autom\u00d3vil",
    "sg:phone":"+34 959 15 04 06",
    "sg:postcode":"21002",
    "sg:province":"Huelva",
    "wof:name":"Bernal Blanco Juan Ramon",
    "wof:placetype":"venue"
},
  "geometry": {"coordinates":[-6.9350690842,37.2549057007],"type":"Point"}
}