{
  "type": "Feature",
  "properties": {
    "addr:full":"Ctra. Almaden, S/n Cerro Muriano C\u00f3rdoba 14350",
    "addr:housenumber":"s / n",
    "addr:postcode":"14350",
    "addr:street":"Ctra. Almaden;Cerro Muriano Co\u0301Rdoba",
    "iso:country":"ES",
    "sg:address":"Ctra. Almaden, S/n",
    "sg:city":"Cerro Muriano",
    "sg:classifiers":[
        {
            "category":"Autos & Motor Vehicles",
            "subcategory":"Automobile Sales",
            "type":"Retail Goods"
        }
    ],
    "sg:phone":"+34 957 35 04 44",
    "sg:postcode":"14350",
    "sg:province":"C\u00f3rdoba",
    "wof:name":"Perez Oliva Diego",
    "wof:placetype":"venue"
},
  "geometry": {"coordinates":[-4.7704291344,38.0036849976],"type":"Point"}
}