{
  "type": "Feature",
  "properties": {
    "addr:full":"Pg Cementiri, S/n Valls Tarragona 43800",
    "addr:housenumber":"s / n",
    "addr:postcode":"43800",
    "addr:street":"Pg Cementiri",
    "iso:country":"ES",
    "sg:address":"Pg Cementiri, S/n",
    "sg:city":"Valls",
    "sg:orig_category":"Servicios Y Funcionarios De Polic\u00cda",
    "sg:phone":"+34 977 60 91 14",
    "sg:postcode":"43800",
    "sg:province":"Tarragona",
    "wof:name":"Direccion General De La Guardia Civil",
    "wof:placetype":"venue"
},
  "geometry": {"coordinates":[1.2525299788,41.2871513367],"type":"Point"}
}