{
  "type": "Feature",
  "properties": {
    "iso:country":"ES",
    "sg:address":"Avda Oporto, 30",
    "sg:city":"Madrid",
    "sg:orig_category":"Par\u00cds",
    "sg:phone":"+34 914 60 05 46",
    "sg:postcode":"28019",
    "sg:province":"Madrid",
    "wof:name":"Corcoles Gomariz Isabel",
    "wof:placetype":"venue"
},
  "geometry": {"coordinates":[-3.7230329514,40.385471344],"type":"Point"}
}