{
  "type": "Feature",
  "properties": {
    "iso:country":"ES",
    "sg:address":"Avda Asturias, 1",
    "sg:city":"Palencia",
    "sg:orig_category":"Cajas De Ahorro",
    "sg:phone":"+34 979 70 72 50",
    "sg:postcode":"34005",
    "sg:province":"Palencia",
    "sg:website":"www.cajaespana.es",
    "wof:name":"Caja Espa\u00f1a De Inversiones Caja De Ahorros Y Monte De Piedad",
    "wof:placetype":"venue"
},
  "geometry": {"coordinates":[-4.5405659676,42.0175361633],"type":"Point"}
}