{
  "type": "Feature",
  "properties": {
    "addr:full":"Avda Mairena, 1 Mairena Aljarafe Sevilla 41927",
    "addr:housenumber":"1",
    "addr:postcode":"41927",
    "addr:street":"Avda Mairena",
    "iso:country":"ES",
    "sg:address":"Avda Mairena, 1",
    "sg:city":"Mairena Aljarafe",
    "sg:orig_category":"Arquitectos",
    "sg:phone":"+34 954 17 12 58",
    "sg:postcode":"41927",
    "sg:province":"Sevilla",
    "wof:name":"Rodriguez Lazaga Maria Luisa",
    "wof:placetype":"venue"
},
  "geometry": {"coordinates":[-6.0380191803,37.3573493958],"type":"Point"}
}