{
  "type": "Feature",
  "properties": {
    "addr:full":"Avda Jose Antonio, 11 Plasencia C\u00e1ceres 10600",
    "addr:housenumber":"11",
    "addr:postcode":"10600",
    "addr:street":"Avda Jose Antonio;Ca\u0301Ceres",
    "iso:country":"ES",
    "sg:address":"Avda Jose Antonio, 11",
    "sg:city":"Plasencia",
    "sg:orig_category":"Art\u00cdculos De Decoraci\u00d3n",
    "sg:phone":"+34 927 42 63 66",
    "sg:postcode":"10600",
    "sg:province":"C\u00e1ceres",
    "sg:website":"www.ka-international.com",
    "wof:name":"Ka Internacional S.c.",
    "wof:placetype":"venue"
},
  "geometry": {"coordinates":[-6.0858178139,40.0310821533],"type":"Point"}
}