{
  "type": "Feature",
  "properties": {
    "addr:full":"Calle de Caridad, 17 Olivenza Badajoz 06100",
    "addr:housenumber":"17",
    "addr:postcode":"06100",
    "addr:street":"Calle De Caridad",
    "iso:country":"ES",
    "sg:address":"Calle de Caridad, 17",
    "sg:city":"Olivenza",
    "sg:orig_category":"Alquiler De V\u00cddeo",
    "sg:phone":"+34 924 49 25 92",
    "sg:postcode":"06100",
    "sg:province":"Badajoz",
    "wof:name":"Sagitario Video Cb",
    "wof:placetype":"venue"
},
  "geometry": {"coordinates":[-7.1003212929,38.6845436096],"type":"Point"}
}