{
  "type": "Feature",
  "properties": {
    "iso:country":"ES",
    "sg:address":"Carretera De Burgos, S/n",
    "sg:city":"Vargas",
    "sg:orig_category":"Fabricaci\u00d3n Y Venta De Volquetes Y Remolques",
    "sg:phone":"+34 942 59 83 57",
    "sg:postcode":"39679",
    "sg:province":"Cantabria",
    "wof:name":"Agricola Y Remolques Esva Sl",
    "wof:placetype":"venue"
},
  "geometry": {"coordinates":[-3.9610619545,43.3225898743],"type":"Point"}
}