{
  "type": "Feature",
  "properties": {
    "iso:country":"ES",
    "sg:address":"Calle de General Ricardos, 95",
    "sg:city":"Madrid",
    "sg:orig_category":"Alimentaci\u00d3n General (al Por Menor)",
    "sg:phone":"+34 914 72 01 40",
    "sg:postcode":"28019",
    "sg:province":"Madrid",
    "wof:name":"Jiang  Shaojun",
    "wof:placetype":"venue"
},
  "geometry": {"coordinates":[-3.7238609791,40.3932342529],"type":"Point"}
}