{
  "type": "Feature",
  "properties": {
    "addr:full":"Carrer de Francesc Layret, 4 Sabadell Barcelona 08208",
    "addr:housenumber":"4",
    "addr:postcode":"08208",
    "addr:street":"Carrer De Francesc Layret",
    "iso:country":"ES",
    "sg:address":"Carrer de Francesc Layret, 4",
    "sg:city":"Sabadell",
    "sg:orig_category":"Promotores Constructores",
    "sg:phone":"+34 937 24 30 89",
    "sg:postcode":"08208",
    "sg:province":"Barcelona",
    "wof:name":"Promillet S.l.",
    "wof:placetype":"venue"
},
  "geometry": {"coordinates":[2.0974080563,41.5588264465],"type":"Point"}
}