{
  "type": "Feature",
  "properties": {
    "iso:country":"ES",
    "sg:address":"Calle de Remedio, 5",
    "sg:city":"Cifuentes",
    "sg:orig_category":"Electrodom\u00c9sticos (al Por Menor)",
    "sg:phone":"+34 949 81 01 02",
    "sg:postcode":"19420",
    "sg:province":"Guadalajara",
    "wof:name":"Cabellos Viejo Jose Luis",
    "wof:placetype":"venue"
},
  "geometry": {"coordinates":[-2.620912075,40.7859077454],"type":"Point"}
}