{
  "type": "Feature",
  "properties": {
    "addr:full":"Carrer de Seu (la), 9 Rasquera Tarragona 43513",
    "addr:housenumber":"9",
    "addr:postcode":"43513",
    "addr:street":"Carrer De Seu La",
    "iso:country":"ES",
    "sg:address":"Carrer de Seu (la), 9",
    "sg:city":"Rasquera",
    "sg:orig_category":"Aparatos, Material Y Suministros Para Laboratorios",
    "sg:phone":"+34 977 40 47 97",
    "sg:postcode":"43513",
    "sg:province":"Tarragona",
    "wof:name":"Gloria Pellisa I J.a.f. S.l",
    "wof:placetype":"venue"
},
  "geometry": {"coordinates":[0.6007710099,41.0045928955],"type":"Point"}
}