{
  "type": "Feature",
  "properties": {
    "iso:country":"ES",
    "sg:address":"Tosal, S/n",
    "sg:city":"Olleria",
    "sg:orig_category":"Artes Gr\u00c1ficas, Artes Pl\u00c1sticas: Material Y Suministros (al Por Menor)",
    "sg:phone":"+34 962 20 02 37",
    "sg:postcode":"46850",
    "sg:province":"Valencia",
    "wof:name":"Agricola Tosalt S.a.",
    "wof:placetype":"venue"
},
  "geometry": {"coordinates":[-0.554148972,38.9132995605],"type":"Point"}
}