{
  "type": "Feature",
  "properties": {
    "iso:country":"ES",
    "sg:address":"Calle de Poeta Gracian, 15",
    "sg:city":"Granada",
    "sg:orig_category":"Tapicer\u00cdas",
    "sg:phone":"+34 958 12 92 34",
    "sg:postcode":"18007",
    "sg:province":"Granada",
    "wof:name":"Esquitino Garcia Antonio Miguel",
    "wof:placetype":"venue"
},
  "geometry": {"coordinates":[-3.5980069637,37.1535682678],"type":"Point"}
}