{
  "type": "Feature",
  "properties": {
    "iso:country":"ES",
    "sg:address":"Bda Gloria, 3",
    "sg:city":"Barcelona",
    "sg:orig_category":"Ingeniero",
    "sg:phone":"+34 932 10 88 52",
    "sg:postcode":"08023",
    "sg:province":"Barcelona",
    "wof:name":"Merce Mozo Juan",
    "wof:placetype":"venue"
},
  "geometry": {"coordinates":[2.1473340988,41.4102897644],"type":"Point"}
}