{
  "type": "Feature",
  "properties": {
    "iso:country":"ES",
    "sg:address":"Avda Balsicas, 19",
    "sg:city":"Roldan",
    "sg:orig_category":"Farmacias",
    "sg:phone":"+34 968 58 91 51",
    "sg:postcode":"30709",
    "sg:province":"Murcia",
    "wof:name":"Castellon De Arce Maria Luisa",
    "wof:placetype":"venue"
},
  "geometry": {"coordinates":[-1.0067909956,37.7994041443],"type":"Point"}
}