{
  "type": "Feature",
  "properties": {
    "iso:country":"ES",
    "sg:address":"Calle de Ruiz De Alda, 14",
    "sg:city":"Santander",
    "sg:orig_category":"Estudios, Instalaci\u00d3n De Climatizaci\u00d3n",
    "sg:phone":"+34 942 22 68 25",
    "sg:postcode":"39009",
    "sg:province":"Cantabria",
    "wof:name":"Auto Encendido S. A.",
    "wof:placetype":"venue"
},
  "geometry": {"coordinates":[-3.8153429031,43.4553833008],"type":"Point"}
}