{
  "type": "Feature",
  "properties": {
    "iso:country":"ES",
    "sg:address":"Calle de Mediodia, 19",
    "sg:city":"Almorox",
    "sg:orig_category":"Forjas Y Altos Hornos",
    "sg:phone":"+34 918 62 31 15",
    "sg:postcode":"45900",
    "sg:province":"Toledo",
    "wof:name":"Cecilio Vera Zamorano S.l.",
    "wof:placetype":"venue"
},
  "geometry": {"coordinates":[-4.3859381676,40.2333183289],"type":"Point"}
}