{
  "type": "Feature",
  "properties": {
    "iso:country":"ES",
    "sg:address":"Calle de Segre, 27",
    "sg:city":"Madrid",
    "sg:orig_category":"Promotores Constructores",
    "sg:phone":"+34 914 11 11 48",
    "sg:postcode":"28002",
    "sg:province":"Madrid",
    "wof:name":"Arda S.l.",
    "wof:placetype":"venue"
},
  "geometry": {"coordinates":[-3.6853647232,40.4514465332],"type":"Point"}
}