{
  "type": "Feature",
  "properties": {
    "iso:country":"ES",
    "sg:address":"Ctra De Frailes (p I El Chaparral), Km. 0004,0",
    "sg:city":"Santa Ana",
    "sg:orig_category":"Fabricaci\u00d3n De Cajas De Cart\u00d3n",
    "sg:phone":"+34 953 59 70 83",
    "sg:postcode":"23692",
    "sg:province":"Ja\u00e9n",
    "wof:name":"Envases Alcasur S.l",
    "wof:placetype":"venue"
},
  "geometry": {"coordinates":[-3.8862950802,37.4635848999],"type":"Point"}
}