{
  "type": "Feature",
  "properties": {
    "iso:country":"ES",
    "sg:address":"Plaz Marisa Martinez, 10",
    "sg:city":"S. Pedro Pinatar",
    "sg:orig_category":"Promotores Constructores",
    "sg:phone":"+34 968 17 86 09",
    "sg:postcode":"30740",
    "sg:province":"Murcia",
    "wof:name":"Arpo Empresa Constructora S.a.",
    "wof:placetype":"venue"
},
  "geometry": {"coordinates":[-0.7912976146,37.8367385864],"type":"Point"}
}