{
  "type": "Feature",
  "properties": {
    "addr:full":"Rond O'donnell, 51 Mataro Barcelona 08303",
    "addr:housenumber":"51",
    "addr:postcode":"08303",
    "addr:street":"O'Donnell",
    "iso:country":"ES",
    "sg:address":"Rond O'donnell, 51",
    "sg:city":"Mataro",
    "sg:orig_category":"Tintes (fabricaci\u00d3n, Al Por Mayor)",
    "sg:phone":"+34 937 99 35 20",
    "sg:postcode":"08303",
    "sg:province":"Barcelona",
    "wof:name":"Ainori S.l.",
    "wof:placetype":"venue"
},
  "geometry": {"coordinates":[2.4330878258,41.538734436],"type":"Point"}
}