{
  "type": "Feature",
  "properties": {
    "addr:full":"Rua San Salvador, S/n Forte Novo La Coru\u00f1a 15800",
    "addr:housenumber":"s / n",
    "addr:postcode":"15800",
    "addr:street":"Rua San Salvador;Corun\u0303A",
    "iso:country":"ES",
    "sg:address":"Rua San Salvador, S/n",
    "sg:city":"Forte Novo",
    "sg:orig_category":"Agricultores, Agricultores",
    "sg:phone":"+34 981 50 62 89",
    "sg:postcode":"15800",
    "sg:province":"La Coru\u00f1a",
    "wof:name":"Garcia Mato Angel",
    "wof:placetype":"venue"
},
  "geometry": {"coordinates":[-8.3959693909,43.3714904785],"type":"Point"}
}