{
  "type": "Feature",
  "properties": {
    "iso:country":"ES",
    "sg:address":"Carrer de Arago, 208",
    "sg:city":"Barcelona",
    "sg:orig_category":"Aparcamientos (infraestructuras, Accesorios)",
    "sg:phone":"+34 933 23 35 13",
    "sg:postcode":"08011",
    "sg:province":"Barcelona",
    "wof:name":"Aramunt S. A.",
    "wof:placetype":"venue"
},
  "geometry": {"coordinates":[2.1593761444,41.3880348206],"type":"Point"}
}