{
  "type": "Feature",
  "properties": {
    "iso:country":"ES",
    "sg:address":"Carrer de Cadaques, 53",
    "sg:city":"Llagosta",
    "sg:orig_category":"M\u00c1quinas, Material Y Suministros Para Cajas Y Embalajes",
    "sg:phone":"+34 935 60 55 01",
    "sg:postcode":"08120",
    "sg:province":"Barcelona",
    "wof:name":"Suministros Industriales Y Del Embalaje S.a.",
    "wof:placetype":"venue"
},
  "geometry": {"coordinates":[2.2008609772,41.5136756897],"type":"Point"}
}