{
  "type": "Feature",
  "properties": {
    "iso:country":"ES",
    "sg:address":"Pase San Antonio (de), 31",
    "sg:city":"Cuenca",
    "sg:orig_category":"Molduras, Junquillos, Listones Y Molduras Perforadas",
    "sg:phone":"+34 969 23 19 49",
    "sg:postcode":"16003",
    "sg:province":"Cuenca",
    "wof:name":"Orejon Ortega Manuel",
    "wof:placetype":"venue"
},
  "geometry": {"coordinates":[-2.1368050575,40.0643119812],"type":"Point"}
}