{
  "type": "Feature",
  "properties": {
    "iso:country":"ES",
    "sg:address":"Avgd Virgen Del Rosario, 14",
    "sg:city":"Massamagrell",
    "sg:orig_category":"Servicio De Salud",
    "sg:phone":"+34 961 44 11 15",
    "sg:postcode":"46130",
    "sg:province":"Valencia",
    "sg:website":"www.geberit.es",
    "wof:name":"Geberit S.a.",
    "wof:placetype":"venue"
},
  "geometry": {"coordinates":[-0.3329139948,39.5671310425],"type":"Point"}
}