{
  "type": "Feature",
  "properties": {
    "addr:full":"Calle de Arriba (de), 25 Calaceite Teruel 44610",
    "addr:housenumber":"25",
    "addr:postcode":"44610",
    "addr:street":"Calle De Arriba De",
    "iso:country":"ES",
    "sg:address":"Calle de Arriba (de), 25",
    "sg:city":"Calaceite",
    "sg:orig_category":"Empresas De Pintura Y Revestimientos",
    "sg:phone":"+34 978 85 10 87",
    "sg:postcode":"44610",
    "sg:province":"Teruel",
    "wof:name":"Vidal Llovet Daniel",
    "wof:placetype":"venue"
},
  "geometry": {"coordinates":[0.1874585003,41.0162277222],"type":"Point"}
}