{
  "type": "Feature",
  "properties": {
    "addr:full":"Calle de Sevilla, 9 Pozuelo De Alarcon Madrid 28223",
    "addr:housenumber":"9",
    "addr:postcode":"28223",
    "addr:street":"Calle De Sevilla",
    "iso:country":"ES",
    "sg:address":"Calle de Sevilla, 9",
    "sg:city":"Pozuelo De Alarcon",
    "sg:orig_category":"Promotores Constructores",
    "sg:phone":"+34 917 15 21 27",
    "sg:postcode":"28223",
    "sg:province":"Madrid",
    "wof:name":"Camino De Valdenigriales S. A.",
    "wof:placetype":"venue"
},
  "geometry": {"coordinates":[-3.8090929985,40.4363327026],"type":"Point"}
}