{
  "type": "Feature",
  "properties": {
    "addr:full":"Calle de San Mateo, 14 Alacant Alicante 03013",
    "addr:housenumber":"14",
    "addr:postcode":"03013",
    "addr:street":"Calle De San Mateo",
    "iso:country":"ES",
    "sg:address":"Calle de San Mateo, 14",
    "sg:city":"Alacant",
    "sg:orig_category":"Edici\u00d3n De Diarios, Revistas, Boletines",
    "sg:phone":"+34 965 20 13 63",
    "sg:postcode":"03013",
    "sg:province":"Alicante",
    "wof:name":"Martin Garcia Perfecto",
    "wof:placetype":"venue"
},
  "geometry": {"coordinates":[-0.478888005,38.357131958],"type":"Point"}
}