{
  "type": "Feature",
  "properties": {
    "iso:country":"ES",
    "sg:address":"Carrer de Gurrea, 4",
    "sg:city":"Sabadell",
    "sg:orig_category":"Aparcamientos (infraestructuras, Accesorios)",
    "sg:phone":"+34 937 25 21 59",
    "sg:postcode":"08202",
    "sg:province":"Barcelona",
    "wof:name":"Parking Gurrea S.l.",
    "wof:placetype":"venue"
},
  "geometry": {"coordinates":[2.1112539768,41.5425834656],"type":"Point"}
}