{
  "type": "Feature",
  "properties": {
    "addr:full":"Calle de Santa Teresa, 69 Lerma Burgos 09340",
    "addr:housenumber":"69",
    "addr:postcode":"09340",
    "addr:street":"Calle De Santa Teresa",
    "iso:country":"ES",
    "sg:address":"Calle de Santa Teresa, 69",
    "sg:city":"Lerma",
    "sg:classifiers":[
        {
            "category":"Communications",
            "type":"Services"
        }
    ],
    "sg:phone":"+34 947 17 06 53",
    "sg:postcode":"09340",
    "sg:province":"Burgos",
    "sg:tags":[
        "televisiones",
        "y",
        "radio"
    ],
    "wof:name":"A.c. Anda Onda Lerma",
    "wof:placetype":"venue"
},
  "geometry": {"coordinates":[-3.7609038353,42.0260772705],"type":"Point"}
}