{
  "type": "Feature",
  "properties": {
    "iso:country":"ES",
    "sg:address":"Calle de Calderon De La Barca, 24",
    "sg:city":"San Vicente Del Raspeig-sant Vicent Del Raspeig",
    "sg:orig_category":"Ropa Para Ni\u00d1os (al Por Menor)",
    "sg:phone":"+34 965 67 38 74",
    "sg:postcode":"03690",
    "sg:province":"Alicante",
    "wof:name":"Roche Molina Gregorio",
    "wof:placetype":"venue"
},
  "geometry": {"coordinates":[-0.5216816068,38.3994140625],"type":"Point"}
}