{
  "type": "Feature",
  "properties": {
    "addr:full":"Pg Vilanova, 27 Sitges Barcelona 08870",
    "addr:housenumber":"27",
    "addr:postcode":"08870",
    "addr:street":"Vilanova",
    "iso:country":"ES",
    "sg:address":"Pg Vilanova, 27",
    "sg:city":"Sitges",
    "sg:orig_category":"Supermercados Y Hipermercados",
    "sg:phone":"+34 938 94 77 26",
    "sg:postcode":"08870",
    "sg:province":"Barcelona",
    "wof:name":"Romero Navarrete S.l.",
    "wof:placetype":"venue"
},
  "geometry": {"coordinates":[1.8059910536,41.2378501892],"type":"Point"}
}