{
  "type": "Feature",
  "properties": {
    "iso:country":"ES",
    "sg:address":"Calle de Ruise\u00d1or, 16",
    "sg:city":"Valderrubio",
    "sg:orig_category":"Telas Y Sedas (al Por Menor)",
    "sg:phone":"+34 958 45 44 81",
    "sg:postcode":"18250",
    "sg:province":"Granada",
    "wof:name":"Textiles Valderrubio S.l.",
    "wof:placetype":"venue"
},
  "geometry": {"coordinates":[-3.8189020157,37.2359275818],"type":"Point"}
}