{
  "type": "Feature",
  "properties": {
    "iso:country":"ES",
    "sg:address":"Av Madrid, 1",
    "sg:city":"Crevillent",
    "sg:orig_category":"Papeler\u00cdas, Librer\u00cdas",
    "sg:phone":"+34 965 40 55 54",
    "sg:postcode":"03330",
    "sg:province":"Alicante",
    "wof:name":"Espinosa Mas Asuncion Del Carmen",
    "wof:placetype":"venue"
},
  "geometry": {"coordinates":[-0.8072699904,38.246761322],"type":"Point"}
}