{
  "type": "Feature",
  "properties": {
    "iso:country":"ES",
    "sg:address":"Ctra. Quart A Dome\u00f1o, Km. 0011,3",
    "sg:city":"Riba-roja Turia",
    "sg:orig_category":"Mec\u00c1nico Del Autom\u00d3vil",
    "sg:phone":"+34 962 77 12 73",
    "sg:postcode":"46190",
    "sg:province":"Valencia",
    "wof:name":"Jumicar Rapid S.l.",
    "wof:placetype":"venue"
},
  "geometry": {"coordinates":[-0.5698940158,39.5458450317],"type":"Point"}
}