{
  "type": "Feature",
  "properties": {
    "iso:country":"ES",
    "sg:address":"Calle de Padre Llansol, 30",
    "sg:city":"Mislata",
    "sg:orig_category":"Promotores Constructores",
    "sg:phone":"+34 963 83 31 07",
    "sg:postcode":"46920",
    "sg:province":"Valencia",
    "wof:name":"Duvicensa S.l.",
    "wof:placetype":"venue"
},
  "geometry": {"coordinates":[-0.4148199856,39.4772148132],"type":"Point"}
}