{
  "type": "Feature",
  "properties": {
    "iso:country":"ES",
    "sg:address":"Calle de Hierro, 1",
    "sg:city":"Madrid",
    "sg:orig_category":"Promotores Constructores",
    "sg:phone":"+34 914 67 36 66",
    "sg:postcode":"28045",
    "sg:province":"Madrid",
    "wof:name":"Comercializadora Vemusa S.l.",
    "wof:placetype":"venue"
},
  "geometry": {"coordinates":[-3.6900589466,40.3900108337],"type":"Point"}
}