{
  "type": "Feature",
  "properties": {
    "iso:country":"ES",
    "sg:address":"Calle de Compositor Lehmberg Ruiz, 5",
    "sg:city":"Malaga",
    "sg:orig_category":"M\u00c9dicos: Evaluaci\u00d3n Y Tratamiento Del Dolor",
    "sg:phone":"+34 952 27 39 04",
    "sg:postcode":"29007",
    "sg:province":"M\u00e1laga",
    "wof:name":"Leiva Jimenez Miguel",
    "wof:placetype":"venue"
},
  "geometry": {"coordinates":[-4.4318413734,36.7177429199],"type":"Point"}
}