{
  "type": "Feature",
  "properties": {
    "addr:full":"Aitzkorri Kalea, 22 Legazpi Guip\u00f9zcoa 20230",
    "addr:housenumber":"22",
    "addr:postcode":"20230",
    "addr:street":"Aitzkorri Kalea;Guipu\u0300Zcoa",
    "iso:country":"ES",
    "sg:address":"Aitzkorri Kalea, 22",
    "sg:city":"Legazpi",
    "sg:orig_category":"Venta, Alquiler De Instrumentos Y Accesorios De M\u00dasica",
    "sg:phone":"+34 943 73 72 38",
    "sg:postcode":"20230",
    "sg:province":"Guip\u00f9zcoa",
    "wof:name":"Musical Legazpi",
    "wof:placetype":"venue"
},
  "geometry": {"coordinates":[-2.3356409073,43.0483551025],"type":"Point"}
}