{
  "type": "Feature",
  "properties": {
    "addr:full":"Rbla Jaume I, 16 Cambrils Tarragona 43850",
    "addr:housenumber":"16",
    "addr:postcode":"43850",
    "addr:street":"Rbla Jaume I",
    "iso:country":"ES",
    "sg:address":"Rbla Jaume I, 16",
    "sg:city":"Cambrils",
    "sg:orig_category":"\u00d3ptica: Instrumentos (fabricaci\u00d3n)",
    "sg:phone":"+34 977 36 83 34",
    "sg:postcode":"43850",
    "sg:province":"Tarragona",
    "wof:name":"L'ull Content S.l.",
    "wof:placetype":"venue"
},
  "geometry": {"coordinates":[1.0585830212,41.0670394897],"type":"Point"}
}