{
  "type": "Feature",
  "properties": {
    "iso:country":"ES",
    "sg:address":"Calle de Real, 6",
    "sg:city":"Juarros De Riomoros",
    "sg:orig_category":"Arenas, Guijarros Y Granulados",
    "sg:phone":"+34 921 49 55 77",
    "sg:postcode":"40130",
    "sg:province":"Segovia",
    "wof:name":"Jabres Manes S.l.",
    "wof:placetype":"venue"
},
  "geometry": {"coordinates":[-97.78224945069999,45.7040786743],"type":"Point"}
}