{
  "type": "Feature",
  "properties": {
    "addr:full":"Finc Estiviel, S/n Toledo Toledo 45004",
    "addr:housenumber":"s / n",
    "addr:postcode":"45004",
    "iso:country":"ES",
    "sg:address":"Finc Estiviel, S/n",
    "sg:city":"Toledo",
    "sg:orig_category":"Agricultores, Agricultores",
    "sg:phone":"+34 925 22 08 93",
    "sg:postcode":"45004",
    "sg:province":"Toledo",
    "wof:name":"Estiviel, S. A.",
    "wof:placetype":"venue"
},
  "geometry": {"coordinates":[-4.0680837631,39.8566055298],"type":"Point"}
}