{
  "type": "Feature",
  "properties": {
    "iso:country":"ES",
    "sg:address":"Calle de Padre Claret, 7",
    "sg:city":"Calatayud",
    "sg:orig_category":"\u00d3ptica: Instrumentos (fabricaci\u00d3n)",
    "sg:phone":"+34 976 88 61 56",
    "sg:postcode":"50300",
    "sg:province":"Zaragoza",
    "wof:name":"Perez Calahorra Antonio",
    "wof:placetype":"venue"
},
  "geometry": {"coordinates":[-1.6402209997,41.3530044556],"type":"Point"}
}