{
  "type": "Feature",
  "properties": {
    "addr:full":"Rua Nova, 3 Milladoiro A Coru\u00f1a 15895",
    "addr:housenumber":"3",
    "addr:postcode":"15895",
    "addr:street":"Rua Nova;A Corun\u0303A",
    "iso:country":"ES",
    "sg:address":"Rua Nova, 3",
    "sg:city":"Milladoiro",
    "sg:orig_category":"Muebles, Minoristas",
    "sg:phone":"+34 981 53 50 92",
    "sg:postcode":"15895",
    "sg:province":"A Coru\u00f1a",
    "wof:name":"Sucesores De Jose Fernandez Quintas Cdad",
    "wof:placetype":"venue"
},
  "geometry": {"coordinates":[-8.5794343948,42.8416137695],"type":"Point"}
}