{
  "type": "Feature",
  "properties": {
    "addr:full":"German Bernacer(pol Ind), 47 Torrellano Alicante 03320",
    "addr:housenumber":"47",
    "addr:postcode":"03320",
    "addr:street":"Ind",
    "iso:country":"ES",
    "sg:address":"German Bernacer(pol Ind), 47",
    "sg:city":"Torrellano",
    "sg:orig_category":"Confecci\u00d3n De Zapatos",
    "sg:phone":"+34 965 68 57 23",
    "sg:postcode":"03320",
    "sg:province":"Alicante",
    "sg:website":"www.inter-fargo.com",
    "wof:name":"Alboixer S.l.",
    "wof:placetype":"venue"
},
  "geometry": {"coordinates":[-0.586401701,38.2937545776],"type":"Point"}
}