{
  "type": "Feature",
  "properties": {
    "addr:full":"C/ Sant Quinti, 26 Ribes Freser Girona 17534",
    "addr:housenumber":"26",
    "addr:postcode":"17534",
    "addr:street":"C / Sant Quinti",
    "iso:country":"ES",
    "sg:address":"C/ Sant Quinti, 26",
    "sg:city":"Ribes Freser",
    "sg:orig_category":"Reposter\u00cdas",
    "sg:phone":"+34 972 72 71 58",
    "sg:postcode":"17534",
    "sg:province":"Girona",
    "wof:name":"Comerma Pares Jose",
    "wof:placetype":"venue"
},
  "geometry": {"coordinates":[2.1671769619,42.3048934937],"type":"Point"}
}