{
  "type": "Feature",
  "properties": {
    "addr:full":"Calle de Sandalo, 5 Alcala Henares Madrid 28803",
    "addr:housenumber":"5",
    "addr:postcode":"28803",
    "addr:street":"Calle De Sandalo",
    "iso:country":"ES",
    "sg:address":"Calle de Sandalo, 5",
    "sg:city":"Alcala Henares",
    "sg:orig_category":"Radiocomunicaciones, Telefon\u00cda M\u00d3vil, Radiomensajer\u00cda: Servicios, Comercializaci\u00d3n",
    "sg:phone":"+34 918 79 78 76",
    "sg:postcode":"28803",
    "sg:province":"Madrid",
    "wof:name":"Boggy 26 S.l.",
    "wof:placetype":"venue"
},
  "geometry": {"coordinates":[-3.3749780655,40.4759521484],"type":"Point"}
}