{
  "type": "Feature",
  "properties": {
    "addr:full":"Rua Galicia, 40 Noia La Coru\u00f1a 15200",
    "addr:housenumber":"40",
    "addr:postcode":"15200",
    "addr:street":"Rua Galicia;La Corun\u0303A",
    "iso:country":"ES",
    "sg:address":"Rua Galicia, 40",
    "sg:city":"Noia",
    "sg:orig_category":"Panader\u00cdas, Panader\u00cdas",
    "sg:phone":"+34 981 82 20 01",
    "sg:postcode":"15200",
    "sg:province":"La Coru\u00f1a",
    "wof:name":"Costell Y Vilas S.l.",
    "wof:placetype":"venue"
},
  "geometry": {"coordinates":[-8.8851413727,42.7850418091],"type":"Point"}
}