{
  "type": "Feature",
  "properties": {
    "iso:country":"ES",
    "sg:address":"Rbla Nova, 43",
    "sg:city":"Igualada",
    "sg:orig_category":"Panader\u00cdas, Panader\u00cdas",
    "sg:phone":"+34 938 03 78 50",
    "sg:postcode":"08700",
    "sg:province":"Barcelona",
    "wof:name":"Pla Vich Hermini",
    "wof:placetype":"venue"
},
  "geometry": {"coordinates":[1.6148999929,41.5799102783],"type":"Point"}
}