{
  "type": "Feature",
  "properties": {
    "addr:full":"Calle de Rita Nicolau, 1 Martos Ja\u00e9n 23600",
    "addr:housenumber":"1",
    "addr:postcode":"23600",
    "addr:street":"Calle De Rita Nicolau;Jae\u0301N",
    "iso:country":"ES",
    "sg:address":"Calle de Rita Nicolau, 1",
    "sg:city":"Martos",
    "sg:orig_category":"Asilos De Ancianos. Centros Privados",
    "sg:phone":"+34 953 55 42 00",
    "sg:postcode":"23600",
    "sg:province":"Ja\u00e9n",
    "wof:name":"Residencia Para Ancianos Nuestra Se\u00f1ora De Los Desamparados",
    "wof:placetype":"venue"
},
  "geometry": {"coordinates":[-3.9724280834,37.7252044678],"type":"Point"}
}