{
  "type": "Feature",
  "properties": {
    "iso:country":"ES",
    "sg:address":"Ctra Alicante, 32",
    "sg:city":"Elche",
    "sg:orig_category":"Dietistas",
    "sg:phone":"+34 966 61 30 96",
    "sg:postcode":"03203",
    "sg:province":"Alicante",
    "wof:name":"Fidiet S.l.",
    "wof:placetype":"venue"
},
  "geometry": {"coordinates":[-0.6726120114,38.2719192505],"type":"Point"}
}