{
  "type": "Feature",
  "properties": {
    "addr:full":"Barr Arteaga, 25 Arteaga Derio Vizcaya 48160",
    "addr:housenumber":"25",
    "addr:postcode":"48160",
    "addr:street":"Arteaga",
    "iso:country":"ES",
    "sg:address":"Barr Arteaga, 25",
    "sg:city":"Arteaga Derio",
    "sg:orig_category":"Laboratorios Y Cl\u00cdnicas Veterinarias",
    "sg:phone":"+34 944 54 21 02",
    "sg:postcode":"48160",
    "sg:province":"Vizcaya",
    "sg:website":"www.aberekin.com",
    "wof:name":"Aberekin S. A.",
    "wof:placetype":"venue"
},
  "geometry": {"coordinates":[-2.888137,43.291523],"type":"Point"}
}