{
  "type": "Feature",
  "properties": {
    "addr:full":"J. Ramon Jimenez, S/n Parque Empresarial Madrid 28232",
    "addr:postcode":"28232",
    "addr:street":"Jimenez S / N Parque Empresarial",
    "iso:country":"ES",
    "sg:address":"J. Ramon Jimenez, S/n",
    "sg:city":"Parque Empresarial",
    "sg:orig_category":"Ropa Y Accesorios",
    "sg:phone":"+34 916 40 08 03",
    "sg:postcode":"28232",
    "sg:province":"Madrid",
    "wof:name":"Marcosin S. A.",
    "wof:placetype":"venue"
},
  "geometry": {"coordinates":[-3.899435997,40.5183067322],"type":"Point"}
}