{
  "type": "Feature",
  "properties": {
    "addr:full":"Carrer de Tren (del), 10 Valls Tarragona 43800",
    "addr:housenumber":"10",
    "addr:postcode":"43800",
    "addr:street":"Carrer De Tren Del",
    "iso:country":"ES",
    "sg:address":"Carrer de Tren (del), 10",
    "sg:city":"Valls",
    "sg:orig_category":"Animales (al Por Menor)",
    "sg:phone":"+34 977 60 67 57",
    "sg:postcode":"43800",
    "sg:province":"Tarragona",
    "wof:name":"Prozovalls Center S.l.",
    "wof:placetype":"venue"
},
  "geometry": {"coordinates":[1.2554379702,41.2910041809],"type":"Point"}
}