{
  "type": "Feature",
  "properties": {
    "addr:full":"Carrer de Doctor Balari I Jovany, 6 Barcelona Barcelona 08030",
    "addr:housenumber":"6",
    "addr:postcode":"08030",
    "addr:street":"Carrer De Doctor Balari;Jovany",
    "iso:country":"ES",
    "sg:address":"Carrer de Doctor Balari I Jovany, 6",
    "sg:city":"Barcelona",
    "sg:orig_category":"Peluquer\u00cdas, Peluquer\u00cda Mixta",
    "sg:phone":"+34 933 45 09 71",
    "sg:postcode":"08030",
    "sg:province":"Barcelona",
    "wof:name":"Campoy Moreno Juan",
    "wof:placetype":"venue"
},
  "geometry": {"coordinates":[2.1904189587,41.4353675842],"type":"Point"}
}