{
  "type": "Feature",
  "properties": {
    "addr:full":"Avda Alvaro Lopez Nu\u00d1ez, 6 Le\u00f3n Le\u00f3n 24002",
    "addr:housenumber":"6",
    "addr:postcode":"24002",
    "addr:street":"Avda Alvaro Lopez Nun\u0303Ez;Leo\u0301N",
    "iso:country":"ES",
    "sg:address":"Avda Alvaro Lopez Nu\u00d1ez, 6",
    "sg:city":"Le\u00f3n",
    "sg:orig_category":"Electrodom\u00c9sticos (al Por Menor)",
    "sg:phone":"+34 987 23 28 23",
    "sg:postcode":"24002",
    "sg:province":"Le\u00f3n",
    "wof:name":"Caon Rodriguez Miguel Angel",
    "wof:placetype":"venue"
},
  "geometry": {"coordinates":[-5.5705189705,42.6029472351],"type":"Point"}
}