{
  "type": "Feature",
  "properties": {
    "addr:full":"Calle de San Sebastian (de), 10 Colmenar Viejo Madrid 28770",
    "addr:postcode":"28770",
    "addr:street":"Calle De",
    "iso:country":"ES",
    "sg:address":"Calle de San Sebastian (de), 10",
    "sg:city":"Colmenar Viejo",
    "sg:orig_category":"Ropa Y Accesorios",
    "sg:phone":"+34 918 46 17 82",
    "sg:postcode":"28770",
    "sg:province":"Madrid",
    "wof:name":"Tiendas El Pantalon S.l.",
    "wof:placetype":"venue"
},
  "geometry": {"coordinates":[-3.767868042,40.6622161865],"type":"Point"}
}