{
  "type": "Feature",
  "properties": {
    "iso:country":"ES",
    "sg:address":"Carr Torres I Jonama, 18",
    "sg:city":"Palafrugell",
    "sg:orig_category":"Alimentaci\u00d3n General (al Por Menor)",
    "sg:phone":"+34 972 30 03 88",
    "sg:postcode":"17200",
    "sg:province":"Girona",
    "wof:name":"Cervera Coderch Maria",
    "wof:placetype":"venue"
},
  "geometry": {"coordinates":[3.1628890038,41.9182434082],"type":"Point"}
}