{
  "type": "Feature",
  "properties": {
    "addr:full":"Barranquet, 1 Aldaia Valencia 46960",
    "addr:housenumber":"1",
    "addr:postcode":"46960",
    "addr:street":"Barranquet",
    "iso:country":"ES",
    "sg:address":"Barranquet, 1",
    "sg:city":"Aldaia",
    "sg:orig_category":"Farmacias (repartici\u00d3n Y Al Por Mayor)",
    "sg:phone":"+34 961 51 06 61",
    "sg:postcode":"46960",
    "sg:province":"Valencia",
    "wof:name":"Hefamecom S.a.",
    "wof:placetype":"venue"
},
  "geometry": {"coordinates":[-0.4715470076,39.4671630859],"type":"Point"}
}