{
  "type": "Feature",
  "properties": {
    "addr:full":"Oarso Kalea, 6 Hernani Guip\u00f9zcoa 20120",
    "addr:housenumber":"6",
    "addr:postcode":"20120",
    "addr:street":"Oarso Kalea;Guipu\u0300Zcoa",
    "iso:country":"ES",
    "sg:address":"Oarso Kalea, 6",
    "sg:city":"Hernani",
    "sg:orig_category":"Comerciantes Al Por Mayor De Vinos, Licores Y Alcoholes",
    "sg:phone":"+34 943 55 02 30",
    "sg:postcode":"20120",
    "sg:province":"Guip\u00f9zcoa",
    "wof:name":"Fernando Lopez Illarramendi",
    "wof:placetype":"venue"
},
  "geometry": {"coordinates":[-1.9774270058,43.2663612366],"type":"Point"}
}