{
  "type": "Feature",
  "properties": {
    "addr:full":"Calle de Cristo, 69 Valdepe\u00f1as Ciudad Real 13300",
    "addr:housenumber":"69",
    "addr:postcode":"13300",
    "addr:street":"Calle De Cristo",
    "iso:country":"ES",
    "sg:address":"Calle de Cristo, 69",
    "sg:city":"Valdepe\u00f1as",
    "sg:orig_category":"Reposter\u00cdas",
    "sg:phone":"+34 926 31 01 43",
    "sg:postcode":"13300",
    "sg:province":"Ciudad Real",
    "wof:name":"Lor-pan Valdepe\u00f1as S.l.",
    "wof:placetype":"venue"
},
  "geometry": {"coordinates":[-3.3899333477,38.7592926025],"type":"Point"}
}