{
  "type": "Feature",
  "properties": {
    "iso:country":"ES",
    "sg:address":"Calle de Musico Francisco De Salinas, S/n",
    "sg:city":"Cordoba",
    "sg:orig_category":"Asociaciones, Organismos Culturales Y Socioeducativos",
    "sg:phone":"+34 957 27 63 98",
    "sg:postcode":"14011",
    "sg:province":"C\u00f3rdoba",
    "wof:name":"Asociacion De Mujeres Romanies Upre Romnja",
    "wof:placetype":"venue"
},
  "geometry": {"coordinates":[-4.7908539772,37.892780304],"type":"Point"}
}