{
  "type": "Feature",
  "properties": {
    "iso:country":"ES",
    "sg:address":"Carr Alfarras, 6",
    "sg:city":"Lleida",
    "sg:orig_category":"Electricidad: Equipos Industriales, Componentes (fabricaci\u00d3n)",
    "sg:phone":"+34 973 23 95 95",
    "sg:postcode":"25005",
    "sg:province":"Lleida",
    "sg:website":"www.suepratalarte.es",
    "wof:name":"Sueprat Y Alarte S.l.",
    "wof:placetype":"venue"
},
  "geometry": {"coordinates":[0.6297569871,41.6248054504],"type":"Point"}
}