{
  "type": "Feature",
  "properties": {
    "iso:country":"ES",
    "sg:address":"Luga Diseminado San Felipe, 3",
    "sg:city":"San Felipe",
    "sg:orig_category":"Enfermeras: Consultas, Atenci\u00d3n A Domicilio",
    "sg:phone":"+34 928 55 61 43",
    "sg:postcode":"35450",
    "sg:province":"Las Palmas",
    "wof:name":"Alvarez Sos Maria Del Mar",
    "wof:placetype":"venue"
},
  "geometry": {"coordinates":[-15.5946302414,28.1451244354],"type":"Point"}
}