{
  "type": "Feature",
  "properties": {
    "addr:full":"Carr Guixeres, 48 Badalona Barcelona 08912",
    "addr:housenumber":"48",
    "addr:postcode":"08912",
    "addr:street":"Carr Guixeres",
    "iso:country":"ES",
    "sg:address":"Carr Guixeres, 48",
    "sg:city":"Badalona",
    "sg:orig_category":"Transportes Por Carretera: Lotes Completos, Mercanc\u00cdas Diversas",
    "sg:phone":"+34 933 87 73 14",
    "sg:postcode":"08912",
    "sg:province":"Barcelona",
    "wof:name":"Gasull Jane Jordi",
    "wof:placetype":"venue"
},
  "geometry": {"coordinates":[2.2394599915,41.4451293945],"type":"Point"}
}