{
  "type": "Feature",
  "properties": {
    "addr:full":"Carrer de Adria Gual, 58 Reus Tarragona 43206",
    "addr:housenumber":"58",
    "addr:postcode":"43206",
    "addr:street":"Carrer De Adria Gual",
    "iso:country":"ES",
    "sg:address":"Carrer de Adria Gual, 58",
    "sg:city":"Reus",
    "sg:orig_category":"Droguer\u00cdas (al Por Menor)",
    "sg:phone":"+34 977 32 22 10",
    "sg:postcode":"43206",
    "sg:province":"Tarragona",
    "wof:name":"Distribucions I Exclusives Decopin S.a.",
    "wof:placetype":"venue"
},
  "geometry": {"coordinates":[1.1039400101,41.1745300293],"type":"Point"}
}