{
  "type": "Feature",
  "properties": {
    "addr:full":"Ctra. Jerez-sanlucar, Km. 0010,0 Jerez C\u00e1diz 11408",
    "addr:postcode":"11408",
    "addr:street":"Ctra. Jerez-Sanlucar Km. 0010,0",
    "iso:country":"ES",
    "sg:address":"Ctra. Jerez-sanlucar, Km. 0010,0",
    "sg:city":"Jerez",
    "sg:classifiers":[
        {
            "category":"Manufacturing",
            "subcategory":"Building Materials",
            "type":"Manufacturing & Wholesale Goods"
        }
    ],
    "sg:phone":"+34 956 23 74 24",
    "sg:postcode":"11408",
    "sg:province":"C\u00e1diz",
    "sg:tags":[
        "cemento",
        "y",
        "de",
        "fabricaci\u00d3n",
        "cal"
    ],
    "wof:name":"Diceba S. A.",
    "wof:placetype":"venue"
},
  "geometry": {"coordinates":[-6.1592831612,36.6686592102],"type":"Point"}
}