{
  "type": "Feature",
  "properties": {
    "iso:country":"ES",
    "sg:address":"Plaz Alicante, Km. 0002,3",
    "sg:city":"Barriada San Gines",
    "sg:orig_category":"Transportes Por Carretera: Lotes Completos, Mercanc\u00cdas Diversas",
    "sg:phone":"+34 968 32 13 49",
    "sg:postcode":"30392",
    "sg:province":"Murcia",
    "wof:name":"Dialsur S.a.",
    "wof:placetype":"venue"
},
  "geometry": {"coordinates":[-0.9694439769,37.6158447266],"type":"Point"}
}