{
  "type": "Feature",
  "properties": {
    "addr:full":"Offenbach (ctm), S/n Malaga M\u00e1laga 29006",
    "addr:housenumber":"s / n",
    "addr:postcode":"29006",
    "addr:street":"Ma\u0301Laga",
    "iso:country":"ES",
    "sg:address":"Offenbach (ctm), S/n",
    "sg:city":"Malaga",
    "sg:orig_category":"Caf\u00c9s, Bares, Cervecer\u00cdas",
    "sg:phone":"+34 952 17 96 49",
    "sg:postcode":"29006",
    "sg:province":"M\u00e1laga",
    "wof:name":"Nevasur Restauracion S.l.",
    "wof:placetype":"venue"
},
  "geometry": {"coordinates":[-4.5133938789,36.7125244141],"type":"Point"}
}