{
  "type": "Feature",
  "properties": {
    "addr:full":"Avda Asuncion (de La), 2 Santa Cruz De Tenerife Santa Cruz De Tenerife 38006",
    "addr:housenumber":"2",
    "addr:postcode":"38006",
    "addr:street":"Avda Asuncion De La",
    "iso:country":"ES",
    "sg:address":"Avda Asuncion (de La), 2",
    "sg:city":"Santa Cruz De Tenerife",
    "sg:classifiers":[
        {
            "category":"Personal",
            "subcategory":"Barber",
            "type":"Services"
        }
    ],
    "sg:phone":"+34 922 28 73 64",
    "sg:postcode":"38006",
    "sg:province":"Santa Cruz De Tenerife",
    "sg:tags":[
        "caballeros",
        "de",
        "peluqueros"
    ],
    "wof:name":"Mesas Gorrin Jose",
    "wof:placetype":"venue"
},
  "geometry": {"coordinates":[-16.261674881,28.46758461],"type":"Point"}
}