{
  "type": "Feature",
  "properties": {
    "iso:country":"ES",
    "sg:address":"Ptda Pla De La Vallonga, S/n",
    "sg:city":"Pla De La Vallonga",
    "sg:orig_category":"Transportes Por V\u00cdas Navegables",
    "sg:phone":"+34 965 10 51 00",
    "sg:postcode":"03113",
    "sg:province":"Alicante",
    "sg:website":"www.chronoexpress.es",
    "wof:name":"Chronopost Express Espa\u00f1a S.a",
    "wof:placetype":"venue"
},
  "geometry": {"coordinates":[-0.5904179811,38.3435401917],"type":"Point"}
}