{
  "type": "Feature",
  "properties": {
    "addr:full":"Calle de San Jose, 11 S. Mateo Gallego Zaragoza 50840",
    "addr:postcode":"50840",
    "addr:street":"Calle De San;11 S. Mateo Gallego",
    "iso:country":"ES",
    "sg:address":"Calle de San Jose, 11",
    "sg:city":"S. Mateo Gallego",
    "sg:orig_category":"Sociedades, Compa\u00d1\u00cdas Aseguradoras",
    "sg:phone":"+34 976 68 40 43",
    "sg:postcode":"50840",
    "sg:province":"Zaragoza",
    "wof:name":"Raelba, S.l.",
    "wof:placetype":"venue"
},
  "geometry": {"coordinates":[-0.7689570189,41.827583313],"type":"Point"}
}