{
  "type": "Feature",
  "properties": {
    "addr:full":"Plaz Mayor, S/n Fayon Zaragoza 50795",
    "addr:housenumber":"s",
    "addr:postcode":"50795",
    "addr:street":"Plaz Mayor;/ N Fayon",
    "iso:country":"ES",
    "sg:address":"Plaz Mayor, S/n",
    "sg:city":"Fayon",
    "sg:orig_category":"Cooperativas Agr\u00cdcolas",
    "sg:phone":"+34 976 63 56 74",
    "sg:postcode":"50795",
    "sg:province":"Zaragoza",
    "wof:name":"Cooperativa Del Campo San Sebastian",
    "wof:placetype":"venue"
},
  "geometry": {"coordinates":[0.3330129981,41.2402038574],"type":"Point"}
}