{
  "type": "Feature",
  "properties": {
    "iso:country":"ES",
    "sg:address":"Avgd Pau Casals, 42",
    "sg:city":"Igualada",
    "sg:orig_category":"Ense\u00d1anza: Profesiones Art\u00cdsticas",
    "sg:phone":"+34 938 04 04 51",
    "sg:postcode":"08700",
    "sg:province":"Barcelona",
    "wof:name":"Izquierdo Canas Josep",
    "wof:placetype":"venue"
},
  "geometry": {"coordinates":[1.6170699596,41.5795402527],"type":"Point"}
}