{
  "type": "Feature",
  "properties": {
    "addr:full":"Calle de Ruise\u00d1or, 6 Fuenlabrada Madrid 28946",
    "addr:housenumber":"6",
    "addr:postcode":"28946",
    "addr:street":"Calle De Ruisen\u0303Or",
    "iso:country":"ES",
    "sg:address":"Calle de Ruise\u00d1or, 6",
    "sg:city":"Fuenlabrada",
    "sg:classifiers":[
        {
            "category":"Manufacturing",
            "subcategory":"Metals",
            "type":"Manufacturing & Wholesale Goods"
        }
    ],
    "sg:phone":"+34 916 42 26 66",
    "sg:postcode":"28946",
    "sg:province":"Madrid",
    "sg:tags":[
        "en",
        "fundiciones"
    ],
    "wof:name":"Sociedad Iberica De Fundiciones S.a.",
    "wof:placetype":"venue"
},
  "geometry": {"coordinates":[-3.7620449066,40.2628631592],"type":"Point"}
}