{
  "type": "Feature",
  "properties": {
    "iso:country":"ES",
    "sg:address":"Calle de Mayor, 36",
    "sg:city":"Molina Segura",
    "sg:orig_category":"Lencer\u00cda Femenina, Corseter\u00cda, Trajes De Ba\u00d1o (al Por Menor)",
    "sg:phone":"+34 968 64 08 76",
    "sg:postcode":"30500",
    "sg:province":"Murcia",
    "wof:name":"Perea Carpef Rosa Maria",
    "wof:placetype":"venue"
},
  "geometry": {"coordinates":[-1.2112890482,38.0520401001],"type":"Point"}
}