{
  "type": "Feature",
  "properties": {
    "addr:full":"Calle de Sansomendi, 7 Vitoria-gasteiz \u00c1lava 01010",
    "addr:housenumber":"7",
    "addr:postcode":"01010",
    "addr:street":"Calle De Sansomendi",
    "iso:country":"ES",
    "sg:address":"Calle de Sansomendi, 7",
    "sg:city":"Vitoria-gasteiz",
    "sg:orig_category":"Peluquer\u00cdas, Peluquer\u00cda Mixta",
    "sg:phone":"+34 945 21 98 19",
    "sg:postcode":"01010",
    "sg:province":"\u00c1lava",
    "wof:name":"Tejado Busto Marta",
    "wof:placetype":"venue"
},
  "geometry": {"coordinates":[-2.6990358829,42.8548164368],"type":"Point"}
}