{
  "type": "Feature",
  "properties": {
    "iso:country":"ES",
    "sg:address":"Ctra Arevalo, Km. 0026,8",
    "sg:city":"Madrigal Altas Torres",
    "sg:orig_category":"Fabricaci\u00d3n, Instalaci\u00d3n Y Reparaci\u00d3n De Bombas",
    "sg:phone":"+34 920 32 00 05",
    "sg:postcode":"05220",
    "sg:province":"\u00c1vila",
    "sg:website":"www.bombasperalcb.com",
    "wof:name":"Anselmo Peral Salinas Y Jose Peral Salinas Cdad",
    "wof:placetype":"venue"
},
  "geometry": {"coordinates":[-4.9964056015,41.0940475464],"type":"Point"}
}