{
  "type": "Feature",
  "properties": {
    "addr:full":"Carrer de Sakura, 5 S. Fruitos Bages Barcelona 08272",
    "addr:housenumber":"5",
    "addr:postcode":"08272",
    "addr:street":"Carrer De Sakura;S. Fruitos Bages Barcelona",
    "iso:country":"ES",
    "sg:address":"Carrer de Sakura, 5",
    "sg:city":"S. Fruitos Bages",
    "sg:orig_category":"Marketing Directo",
    "sg:phone":"+34 938 78 97 20",
    "sg:postcode":"08272",
    "sg:province":"Barcelona",
    "sg:website":"www.arcadiashop.com",
    "wof:name":"Arcadia Internacional S.a.",
    "wof:placetype":"venue"
},
  "geometry": {"coordinates":[1.8662550449,41.7770729065],"type":"Point"}
}