{
  "type": "Feature",
  "properties": {
    "iso:country":"ES",
    "sg:address":"Avda San Julian, 1",
    "sg:city":"Cuenca",
    "sg:orig_category":"M\u00c9dicos: Gastroenterolog\u00cda Y Hepatolog\u00cda (aparato Digestivo)",
    "sg:phone":"+34 969 23 64 72",
    "sg:postcode":"16003",
    "sg:province":"Cuenca",
    "wof:name":"Jimenez Torrijos Amador",
    "wof:placetype":"venue"
},
  "geometry": {"coordinates":[-2.1448569298,40.0672950745],"type":"Point"}
}