{
  "type": "Feature",
  "properties": {
    "iso:country":"ES",
    "sg:address":"Calle de Rio Tietar, 1280",
    "sg:city":"Coto",
    "sg:orig_category":"T\u00c9cnicos Veterinarios",
    "sg:phone":"+34 949 33 57 12",
    "sg:postcode":"19170",
    "sg:province":"Guadalajara",
    "wof:name":"Quintana Martin Carolina",
    "wof:placetype":"venue"
},
  "geometry": {"coordinates":[-3.4308691025,40.7028961182],"type":"Point"}
}