{
  "type": "Feature",
  "properties": {
    "iso:country":"ES",
    "sg:address":"Avda Salle (de La), 38",
    "sg:city":"Santa Cruz De Tenerife",
    "sg:orig_category":"Relojer\u00cda (al Por Menor, Reparaci\u00d3n)",
    "sg:phone":"+34 922 22 95 82",
    "sg:postcode":"38005",
    "sg:province":"Santa Cruz De Tenerife",
    "wof:name":"Fernandez Trujillo Del Castillo Celedonio",
    "wof:placetype":"venue"
},
  "geometry": {"coordinates":[-16.2572402954,28.4593486786],"type":"Point"}
}