{
  "type": "Feature",
  "properties": {
    "iso:country":"ES",
    "sg:address":"Calle de Hoyamoros, S/n",
    "sg:city":"Salamanca",
    "sg:orig_category":"Transportes Por V\u00cdas Navegables",
    "sg:phone":"+34 923 19 36 99",
    "sg:postcode":"37008",
    "sg:province":"Salamanca",
    "sg:website":"www.cotradisa.com",
    "wof:name":"Cotradisa",
    "wof:placetype":"venue"
},
  "geometry": {"coordinates":[-5.6620588303,40.939125061],"type":"Point"}
}