{
  "type": "Feature",
  "properties": {
    "addr:full":"Calle de Francisco Silvela, 72 Madrid Madrid 28028",
    "addr:housenumber":"72",
    "addr:postcode":"madrid;28028",
    "addr:street":"Calle De Francisco Silvela",
    "iso:country":"ES",
    "sg:address":"Calle de Francisco Silvela, 72",
    "sg:city":"Madrid",
    "sg:orig_category":"Laboratorios Y Trabajos De Fotograf\u00cda, V\u00cddeo Y Cine",
    "sg:phone":"+34 917 26 10 25",
    "sg:postcode":"28028",
    "sg:province":"Madrid",
    "wof:name":"Ming Tze  Chiu",
    "wof:placetype":"venue"
},
  "geometry": {"coordinates":[-3.6753659248,40.4357795715],"type":"Point"}
}