{
  "type": "Feature",
  "properties": {
    "addr:full":"Calle de Carmen, 2 Logro\u00f1o La Rioja 26001",
    "addr:housenumber":"2",
    "addr:postcode":"26001",
    "addr:street":"Calle De Carmen;Rioja",
    "iso:country":"ES",
    "sg:address":"Calle de Carmen, 2",
    "sg:city":"Logro\u00f1o",
    "sg:orig_category":"Librer\u00cdas",
    "sg:phone":"+34 941 25 52 99",
    "sg:postcode":"26001",
    "sg:province":"La Rioja",
    "wof:name":"Barquin Villar Pablo",
    "wof:placetype":"venue"
},
  "geometry": {"coordinates":[-2.4417009354,42.4608268738],"type":"Point"}
}