{
  "type": "Feature",
  "properties": {
    "addr:full":"Calle de Marques De Santa Maria Del Villar, 16 Le\u00f3n Le\u00f3n 24007",
    "addr:housenumber":"16",
    "addr:postcode":"24007",
    "addr:street":"Calle De Marques De Santa;Del Villar;Leo\u0301N",
    "iso:country":"ES",
    "sg:address":"Calle de Marques De Santa Maria Del Villar, 16",
    "sg:city":"Le\u00f3n",
    "sg:orig_category":"Alimentaci\u00d3n General (al Por Menor)",
    "sg:phone":"+34 987 23 80 72",
    "sg:postcode":"24007",
    "sg:province":"Le\u00f3n",
    "wof:name":"Barreales Barriales Javier Carlos",
    "wof:placetype":"venue"
},
  "geometry": {"coordinates":[-5.5691409111,42.6079406738],"type":"Point"}
}