{
  "type": "Feature",
  "properties": {
    "addr:full":"Acella-azella, 3 Iru\u00f1a Navarra 31008",
    "addr:housenumber":"3",
    "addr:postcode":"31008",
    "addr:street":"Acella-Azella",
    "iso:country":"ES",
    "sg:address":"Acella-azella, 3",
    "sg:city":"Iru\u00f1a",
    "sg:orig_category":"Peluquer\u00cdas",
    "sg:phone":"+34 948 17 38 44",
    "sg:postcode":"31008",
    "sg:province":"Navarra",
    "wof:name":"Orella De Anitua Maria Victoria",
    "wof:placetype":"venue"
},
  "geometry": {"coordinates":[-1.6620459557,42.8066711426],"type":"Point"}
}