{
  "type": "Feature",
  "properties": {
    "addr:full":"Calle de Conde De Vistahermosa, 37 Madrid Madrid 28019",
    "addr:housenumber":"37",
    "addr:postcode":"madrid;28019",
    "addr:street":"Calle De Conde De Vistahermosa",
    "iso:country":"ES",
    "sg:address":"Calle de Conde De Vistahermosa, 37",
    "sg:city":"Madrid",
    "sg:orig_category":"Mec\u00c1nico Del Autom\u00d3vil",
    "sg:phone":"+34 915 65 06 33",
    "sg:postcode":"28019",
    "sg:province":"Madrid",
    "wof:name":"Rodriguez Alvarez Manuel Baldomero",
    "wof:placetype":"venue"
},
  "geometry": {"coordinates":[-3.7104306221,40.3934440613],"type":"Point"}
}