{
  "type": "Feature",
  "properties": {
    "addr:full":"Calle de Fuente, 36 Vitigudino Salamanca 37210",
    "addr:housenumber":"36",
    "addr:postcode":"37210",
    "addr:street":"Calle De Fuente",
    "iso:country":"ES",
    "sg:address":"Calle de Fuente, 36",
    "sg:city":"Vitigudino",
    "sg:orig_category":"Arreglo, Reparaci\u00d3n, Piezas Sueltas De Televisi\u00d3n, V\u00cddeo, Hi",
    "sg:phone":"+34 923 50 12 15",
    "sg:postcode":"37210",
    "sg:province":"Salamanca",
    "wof:name":"Martin Martin Valeriano",
    "wof:placetype":"venue"
},
  "geometry": {"coordinates":[-6.4375038147,41.0091705322],"type":"Point"}
}