{
  "type": "Feature",
  "properties": {
    "addr:full":"Calle de Poniente, 9 Logro\u00f1o La Rioja 26005",
    "addr:housenumber":"9",
    "addr:postcode":"26005",
    "addr:street":"Calle De Poniente;Rioja",
    "iso:country":"ES",
    "sg:address":"Calle de Poniente, 9",
    "sg:city":"Logro\u00f1o",
    "sg:orig_category":"Centros De Educaci\u00d3n Especial",
    "sg:phone":"+34 941 22 70 05",
    "sg:postcode":"26005",
    "sg:province":"La Rioja",
    "wof:name":"Comunidad Autonoma De La Rioja",
    "wof:placetype":"venue"
},
  "geometry": {"coordinates":[-2.4603440762,42.4669952393],"type":"Point"}
}