{
  "type": "Feature",
  "properties": {
    "addr:full":"Calle de Tejinera (la), S/n Araya Santa Cruz De Tenerife 38540",
    "addr:postcode":"38540",
    "addr:street":"Calle De Tejinera La S / N Araya",
    "iso:country":"ES",
    "sg:address":"Calle de Tejinera (la), S/n",
    "sg:city":"Araya",
    "sg:orig_category":"Plomeros",
    "sg:phone":"+34 922 50 47 41",
    "sg:postcode":"38540",
    "sg:province":"Santa Cruz De Tenerife",
    "wof:name":"Aqualia Gestion Integral Del Agua S.a.",
    "wof:placetype":"venue"
},
  "geometry": {"coordinates":[-16.3754138947,28.3648872375],"type":"Point"}
}