{
  "type": "Feature",
  "properties": {
    "iso:country":"ES",
    "sg:address":"Carrer de Barcelona, 28",
    "sg:city":"Masnou",
    "sg:orig_category":"Bisuter\u00cda, Joyer\u00cda, Relojer\u00cda (al Por Menor)",
    "sg:phone":"+34 935 55 64 51",
    "sg:postcode":"08320",
    "sg:province":"Barcelona",
    "wof:name":"Tena Vilalta Joan",
    "wof:placetype":"venue"
},
  "geometry": {"coordinates":[2.3150970936,41.478263855],"type":"Point"}
}