{
  "type": "Feature",
  "properties": {
    "iso:country":"ES",
    "sg:address":"Calle de Jose Ortega Y Gasset, 12",
    "sg:city":"Montilla",
    "sg:orig_category":"Plomeros",
    "sg:phone":"+34 957 65 32 08",
    "sg:postcode":"14550",
    "sg:province":"C\u00f3rdoba",
    "wof:name":"Ba\u00f1os Portero Jose",
    "wof:placetype":"venue"
},
  "geometry": {"coordinates":[-4.6428031921,37.5889778137],"type":"Point"}
}