{
  "type": "Feature",
  "properties": {
    "iso:country":"ES",
    "sg:address":"Pol Ind Rio Gallego, 27",
    "sg:city":"S. Mateo Gallego",
    "sg:orig_category":"Metalurgia: Maquinaria Y Equipos",
    "sg:phone":"+34 976 69 08 12",
    "sg:postcode":"50840",
    "sg:province":"Zaragoza",
    "wof:name":"Talleres Daga S. A.",
    "wof:placetype":"venue"
},
  "geometry": {"coordinates":[-0.7679479718,41.8305587769],"type":"Point"}
}