{
  "type": "Feature",
  "properties": {
    "addr:full":"Avda Lope De Figueroa, 18 Alcala Henares Madrid 28804",
    "addr:housenumber":"18",
    "addr:postcode":"28804",
    "addr:street":"Avda Lope De Figueroa",
    "iso:country":"ES",
    "sg:address":"Avda Lope De Figueroa, 18",
    "sg:city":"Alcala Henares",
    "sg:orig_category":"Cl\u00cdnicas Dentales",
    "sg:phone":"+34 918 83 14 97",
    "sg:postcode":"28804",
    "sg:province":"Madrid",
    "wof:name":"Eveama S.l.",
    "wof:placetype":"venue"
},
  "geometry": {"coordinates":[-3.3476829529,40.4887771606],"type":"Point"}
}