{
  "type": "Feature",
  "properties": {
    "addr:full":"Carrer de Cavite, 10 Rubi Barcelona 08191",
    "addr:housenumber":"10",
    "addr:postcode":"08191",
    "addr:street":"Carrer De Cavite",
    "iso:country":"ES",
    "sg:address":"Carrer de Cavite, 10",
    "sg:city":"Rubi",
    "sg:orig_category":"Peluquer\u00cdas, Peluquer\u00cda Mixta",
    "sg:phone":"+34 935 88 27 17",
    "sg:postcode":"08191",
    "sg:province":"Barcelona",
    "wof:name":"Corredera Prieto Manuel",
    "wof:placetype":"venue"
},
  "geometry": {"coordinates":[2.0364029408,41.5018386841],"type":"Point"}
}