{
  "type": "Feature",
  "properties": {
    "iso:country":"ES",
    "sg:address":"Calle de Juan Sebastian Elcano, S/n",
    "sg:city":"Radazul Bajo",
    "sg:orig_category":"Librer\u00cdas",
    "sg:phone":"+34 922 68 27 12",
    "sg:postcode":"38109",
    "sg:province":"Santa Cruz De Tenerife",
    "wof:name":"Huete Mingorance Maria Isabel",
    "wof:placetype":"venue"
},
  "geometry": {"coordinates":[-16.3266086578,28.4033489227],"type":"Point"}
}