{
  "type": "Feature",
  "properties": {
    "iso:country":"ES",
    "sg:address":"Avda Vi\u00d1uelas (de), 17",
    "sg:city":"Tres Cantos",
    "sg:orig_category":"Discotecas Y Salas De Baile",
    "sg:phone":"+34 918 03 37 25",
    "sg:postcode":"28760",
    "sg:province":"Madrid",
    "wof:name":"Dehra Dunsl S.l.",
    "wof:placetype":"venue"
},
  "geometry": {"coordinates":[-3.7050991058,40.5960617065],"type":"Point"}
}