{
  "type": "Feature",
  "properties": {
    "addr:full":"Praj Ombatillo, S/n Corella Navarra 31591",
    "addr:housenumber":"s",
    "addr:postcode":"31591",
    "addr:street":"/ N",
    "iso:country":"ES",
    "sg:address":"Praj Ombatillo, S/n",
    "sg:city":"Corella",
    "sg:orig_category":"Coches Y Camiones (caja De Cambios, Embrague Y Frenos)",
    "sg:phone":"+34 948 78 20 00",
    "sg:postcode":"31591",
    "sg:province":"Navarra",
    "wof:name":"Trw Automotive Espa\u00f1a S. L.",
    "wof:placetype":"venue"
},
  "geometry": {"coordinates":[-1.7880990505,42.1150436401],"type":"Point"}
}