{
  "type": "Feature",
  "properties": {
    "addr:full":"Carrer de Sant Pere Mes Baix, 17 Barcelona Barcelona 08003",
    "addr:housenumber":"17",
    "addr:postcode":"08003",
    "addr:street":"Carrer De Sant",
    "iso:country":"ES",
    "sg:address":"Carrer de Sant Pere Mes Baix, 17",
    "sg:city":"Barcelona",
    "sg:orig_category":"Asociaciones Y Clubs Deportivos",
    "sg:phone":"+34 933 19 04 28",
    "sg:postcode":"08003",
    "sg:province":"Barcelona",
    "wof:name":"Quintana Francia Javier",
    "wof:placetype":"venue"
},
  "geometry": {"coordinates":[2.1767570972,41.3867607117],"type":"Point"}
}