{
  "type": "Feature",
  "properties": {
    "iso:country":"ES",
    "sg:address":"Cmno Losa (la), 16",
    "sg:city":"Madrona",
    "sg:orig_category":"Florister\u00cdas",
    "sg:phone":"+34 921 48 52 57",
    "sg:postcode":"40154",
    "sg:province":"Segovia",
    "wof:name":"Garcia Perela Marcos",
    "wof:placetype":"venue"
},
  "geometry": {"coordinates":[-4.1714987755,40.8973388672],"type":"Point"}
}