{
  "type": "Feature",
  "properties": {
    "addr:full":"Rosal(urb Priorat Banyeres), 57 Lloren\u00e7 Penedes Tarragona 43712",
    "addr:housenumber":"57",
    "addr:postcode":"43712",
    "addr:street":"Urb Priorat Banyeres",
    "iso:country":"ES",
    "sg:address":"Rosal(urb Priorat Banyeres), 57",
    "sg:city":"Lloren\u00e7 Penedes",
    "sg:orig_category":"Delegados, Agentes De Tr\u00c1nsito, Auxiliares De Transporte Internacional",
    "sg:phone":"+34 977 67 86 35",
    "sg:postcode":"43712",
    "sg:province":"Tarragona",
    "wof:name":"Transports Xavi-inma S.l.l.",
    "wof:placetype":"venue"
},
  "geometry": {"coordinates":[1.5535449982,41.281288147],"type":"Point"}
}