{
  "type": "Feature",
  "properties": {
    "iso:country":"ES",
    "sg:address":"L. Bravo, 97",
    "sg:city":"Villalonquejar",
    "sg:orig_category":"Metalurgia",
    "sg:phone":"+34 947 29 82 29",
    "sg:postcode":"09001",
    "sg:province":"Burgos",
    "wof:name":"Inoxidables Castilla S.l.",
    "wof:placetype":"venue"
},
  "geometry": {"coordinates":[-3.7634589672,42.3621253967],"type":"Point"}
}