{
  "type": "Feature",
  "properties": {
    "iso:country":"ES",
    "sg:address":"Carrer de Duran I Sors, 4",
    "sg:city":"Sabadell",
    "sg:orig_category":"Madera Para Construcci\u00d3n E Industria",
    "sg:phone":"+34 937 27 77 12",
    "sg:postcode":"08201",
    "sg:province":"Barcelona",
    "wof:name":"Uzuriate Pallargas Vidal",
    "wof:placetype":"venue"
},
  "geometry": {"coordinates":[2.1114909649,41.5404052734],"type":"Point"}
}