{
  "type": "Feature",
  "properties": {
    "addr:full":"Carrer de Menendez Y Pelayo, 207 Terrassa Barcelona 08223",
    "addr:housenumber":"207",
    "addr:postcode":"08223",
    "addr:street":"Carrer De Menendez Y Pelayo",
    "iso:country":"ES",
    "sg:address":"Carrer de Menendez Y Pelayo, 207",
    "sg:city":"Terrassa",
    "sg:orig_category":"Quincaller\u00cda (al Por Menor)",
    "sg:phone":"+34 937 86 03 21",
    "sg:postcode":"08223",
    "sg:province":"Barcelona",
    "wof:name":"Zarza Gallego Josefa",
    "wof:placetype":"venue"
},
  "geometry": {"coordinates":[2.0245490074,41.553768158],"type":"Point"}
}