{
  "type": "Feature",
  "properties": {
    "iso:country":"ES",
    "sg:address":"Calle de Carabela La Pinta, S/n",
    "sg:city":"Baiona",
    "sg:orig_category":"Carnicer\u00cdas, Carnicer\u00cdas",
    "sg:phone":"+34 986 35 67 70",
    "sg:postcode":"36300",
    "sg:province":"Pontevedra",
    "wof:name":"Rodriguez Trigo Manuel",
    "wof:placetype":"venue"
},
  "geometry": {"coordinates":[-8.8508443832,42.1203117371],"type":"Point"}
}