{
  "type": "Feature",
  "properties": {
    "iso:country":"ES",
    "sg:address":"Calle de Tramontana, 47",
    "sg:city":"Humera-somosaguas-prado Del Rey",
    "sg:orig_category":"Inmobiliaria (agencias)",
    "sg:phone":"+34 915 18 25 03",
    "sg:postcode":"28223",
    "sg:province":"Madrid",
    "wof:name":"Ses Pedretes S.l.",
    "wof:placetype":"venue"
},
  "geometry": {"coordinates":[-3.795814991,40.4067573547],"type":"Point"}
}