{
  "type": "Feature",
  "properties": {
    "iso:country":"ES",
    "sg:address":"Calle de Peru, 1",
    "sg:city":"Puertollano",
    "sg:orig_category":"Arquitectos",
    "sg:phone":"+34 926 41 15 79",
    "sg:postcode":"13500",
    "sg:province":"Ciudad Real",
    "wof:name":"Alvarez De Los Corrales Fernandez Diego Alejandro",
    "wof:placetype":"venue"
},
  "geometry": {"coordinates":[-4.0991754532,38.6867446899],"type":"Point"}
}