{
  "type": "Feature",
  "properties": {
    "addr:full":"Carr Llibertat, 9 Cervera Lleida 25200",
    "addr:housenumber":"9",
    "addr:postcode":"25200",
    "addr:street":"Carr Llibertat",
    "iso:country":"ES",
    "sg:address":"Carr Llibertat, 9",
    "sg:city":"Cervera",
    "sg:orig_category":"Molduras, Junquillos, Listones Y Molduras Perforadas",
    "sg:phone":"+34 973 53 36 40",
    "sg:postcode":"25200",
    "sg:province":"Lleida",
    "wof:name":"Miret Navarro Pere",
    "wof:placetype":"venue"
},
  "geometry": {"coordinates":[1.2745150328,41.672958374],"type":"Point"}
}