{
  "type": "Feature",
  "properties": {
    "iso:country":"ES",
    "sg:address":"Calle de Alcala, 183",
    "sg:city":"Madrid",
    "sg:orig_category":"Zapatos (al Por Menor)",
    "sg:phone":"+34 914 01 40 32",
    "sg:postcode":"28009",
    "sg:province":"Madrid",
    "wof:name":"Buzon Moya Julia",
    "wof:placetype":"venue"
},
  "geometry": {"coordinates":[-3.6708488464,40.4270973206],"type":"Point"}
}