{
  "type": "Feature",
  "properties": {
    "addr:full":"Ctra Cami D'albalat, S/n Alzira Valencia 46600",
    "addr:housenumber":"s",
    "addr:postcode":"46600",
    "addr:street":"Ctra Cami D'Albalat;/ N;Valencia",
    "iso:country":"ES",
    "sg:address":"Ctra Cami D'albalat, S/n",
    "sg:city":"Alzira",
    "sg:orig_category":"Servicios De Higiene Y Peluquer\u00cda Para Perros Y Gatos",
    "sg:phone":"+34 962 40 04 11",
    "sg:postcode":"46600",
    "sg:province":"Valencia",
    "wof:name":"Canut Gregori James Javier",
    "wof:placetype":"venue"
},
  "geometry": {"coordinates":[-0.417396009,39.1734542847],"type":"Point"}
}