{
  "type": "Feature",
  "properties": {
    "addr:full":"Plaz Padre Jeronimo De Cordoba, 14 Sevilla Sevilla 41003",
    "addr:housenumber":"14",
    "addr:postcode":"41003",
    "addr:street":"Jeronimo;Cordoba",
    "iso:country":"ES",
    "sg:address":"Plaz Padre Jeronimo De Cordoba, 14",
    "sg:city":"Sevilla",
    "sg:orig_category":"Hoteles",
    "sg:phone":"+34 954 50 13 73",
    "sg:postcode":"41003",
    "sg:province":"Sevilla",
    "wof:name":"Hotel Blagru S.cv.",
    "wof:placetype":"venue"
},
  "geometry": {"coordinates":[-5.9865131378,37.3932342529],"type":"Point"}
}