{
  "type": "Feature",
  "properties": {
    "iso:country":"ES",
    "sg:address":"Calle de Portal De Gamarra, 32",
    "sg:city":"Vitoria-gasteiz",
    "sg:orig_category":"Electromec\u00c1nica",
    "sg:phone":"+34 945 26 14 93",
    "sg:postcode":"01013",
    "sg:province":"\u00c1lava",
    "wof:name":"Gamarauto S.c.",
    "wof:placetype":"venue"
},
  "geometry": {"coordinates":[-2.6616930962,42.8616600037],"type":"Point"}
}