{
  "type": "Feature",
  "properties": {
    "iso:country":"ES",
    "sg:address":"Avda Arrabal, 55",
    "sg:city":"Requena",
    "sg:orig_category":"Agencias De Viajes",
    "sg:phone":"+34 962 30 48 49",
    "sg:postcode":"46340",
    "sg:province":"Valencia",
    "wof:name":"Martinez Aspas Angeles",
    "wof:placetype":"venue"
},
  "geometry": {"coordinates":[-1.1072540283,39.4888114929],"type":"Point"}
}