{
  "type": "Feature",
  "properties": {
    "iso:country":"ES",
    "sg:address":"M. Heredia, 18",
    "sg:city":"Malaga",
    "sg:orig_category":"Inmobiliaria (agencias)",
    "sg:phone":"+34 952 22 50 15",
    "sg:postcode":"29001",
    "sg:province":"M\u00e1laga",
    "wof:name":"V.saez Y Monchon C.b.",
    "wof:placetype":"venue"
},
  "geometry": {"coordinates":[-4.422908783,36.715675354],"type":"Point"}
}