{
  "type": "Feature",
  "properties": {
    "addr:full":"Praj Cucuch - B, 27 Novelda Alicante 03660",
    "addr:housenumber":"27",
    "addr:postcode":"03660",
    "iso:country":"ES",
    "sg:address":"Praj Cucuch - B, 27",
    "sg:city":"Novelda",
    "sg:orig_category":"Delegados, Agentes De Tr\u00c1nsito, Auxiliares De Transporte Internacional",
    "sg:phone":"+34 965 60 14 87",
    "sg:postcode":"03660",
    "sg:province":"Alicante",
    "wof:name":"Crespo Gomez Daniel",
    "wof:placetype":"venue"
},
  "geometry": {"coordinates":[-0.7718489766,38.389251709],"type":"Point"}
}