{
  "type": "Feature",
  "properties": {
    "iso:country":"ES",
    "sg:address":"Czad San Pedro, S/n",
    "sg:city":"Ledesma",
    "sg:orig_category":"Ense\u00d1anza Secundaria: Colegios Y Escuelas Privadas",
    "sg:phone":"+34 923 57 00 31",
    "sg:postcode":"37100",
    "sg:province":"Salamanca",
    "wof:name":"I.e.s.o. Miguel De Unamuno",
    "wof:placetype":"venue"
},
  "geometry": {"coordinates":[-5.9996261597,41.0875434875],"type":"Point"}
}