{
  "type": "Feature",
  "properties": {
    "iso:country":"ES",
    "sg:address":"Avda Jose Mu\u00d1oz De Vargas, 6",
    "sg:city":"Huelva",
    "sg:orig_category":"Lavado, Limpieza De Veh\u00cdculos",
    "sg:phone":"+34 959 22 69 46",
    "sg:postcode":"21006",
    "sg:province":"Huelva",
    "wof:name":"Lirio Vera Juan Bautista",
    "wof:placetype":"venue"
},
  "geometry": {"coordinates":[-6.9354071617,37.2588272095],"type":"Point"}
}