{
  "type": "Feature",
  "properties": {
    "iso:country":"ES",
    "sg:address":"Calle de Virgen De La Paz, 31",
    "sg:city":"Manzanares",
    "sg:orig_category":"Perfumer\u00cda (al Por Menor)",
    "sg:phone":"+34 926 61 18 15",
    "sg:postcode":"13200",
    "sg:province":"Ciudad Real",
    "wof:name":"Villa Garcia-noblejas Maria Jesus",
    "wof:placetype":"venue"
},
  "geometry": {"coordinates":[-3.3725042343,39.0000686646],"type":"Point"}
}