{
  "type": "Feature",
  "properties": {
    "iso:country":"ES",
    "sg:address":"Calle de Jose Ortega Y Gasset, 33",
    "sg:city":"Madrid",
    "sg:orig_category":"Carnicer\u00cdas, Carnicer\u00cdas",
    "sg:phone":"+34 914 35 62 27",
    "sg:postcode":"28006",
    "sg:province":"Madrid",
    "wof:name":"Moreno Garcia Ribera S.a.",
    "wof:placetype":"venue"
},
  "geometry": {"coordinates":[-3.6806559563,40.4302902222],"type":"Point"}
}