{
  "type": "Feature",
  "properties": {
    "iso:country":"ES",
    "sg:address":"Calle de General Diaz Porlier, 32",
    "sg:city":"Madrid",
    "sg:orig_category":"Alimentaci\u00d3n General (al Por Menor)",
    "sg:phone":"+34 914 02 47 15",
    "sg:postcode":"28001",
    "sg:province":"Madrid",
    "wof:name":"Ruiz Infantes Francisco",
    "wof:placetype":"venue"
},
  "geometry": {"coordinates":[-3.6768128872,40.4277381897],"type":"Point"}
}