{
  "type": "Feature",
  "properties": {
    "addr:full":"Ptda Devadillo, S/n Picassent Valencia 46220",
    "addr:housenumber":"s",
    "addr:postcode":"46220",
    "addr:street":"Ptda Devadillo;/ N",
    "iso:country":"ES",
    "sg:address":"Ptda Devadillo, S/n",
    "sg:city":"Picassent",
    "sg:orig_category":"Equitaci\u00d3n Y Centros De H\u00cdpica",
    "sg:phone":"+34 961 24 24 45",
    "sg:postcode":"46220",
    "sg:province":"Valencia",
    "wof:name":"Club Hipico Alarcon",
    "wof:placetype":"venue"
},
  "geometry": {"coordinates":[-0.4668090045,39.3567085266],"type":"Point"}
}