{
  "type": "Feature",
  "properties": {
    "addr:full":"Calle de Cirilo Palomo, 16 Pozuelo De Alarcon Madrid 28223",
    "addr:housenumber":"16",
    "addr:postcode":"28223",
    "addr:street":"Calle De Cirilo Palomo",
    "iso:country":"ES",
    "sg:address":"Calle de Cirilo Palomo, 16",
    "sg:city":"Pozuelo De Alarcon",
    "sg:orig_category":"Farmacias",
    "sg:phone":"+34 917 15 51 67",
    "sg:postcode":"28223",
    "sg:province":"Madrid",
    "wof:name":"Boccio Jimenez Maria Dolores",
    "wof:placetype":"venue"
},
  "geometry": {"coordinates":[-3.8106210232,40.4343681335],"type":"Point"}
}