{
  "type": "Feature",
  "properties": {
    "addr:full":"Calle de Gabriel Ciscar, 40 Albacete Albacete 02005",
    "addr:housenumber":"40",
    "addr:postcode":"02005",
    "addr:street":"Calle De Gabriel Ciscar",
    "iso:country":"ES",
    "sg:address":"Calle de Gabriel Ciscar, 40",
    "sg:city":"Albacete",
    "sg:orig_category":"Comercio, Reparaci\u00d3n De Motocicletas, Bicicletas Y Piezas Sueltas",
    "sg:phone":"+34 967 52 20 56",
    "sg:postcode":"02005",
    "sg:province":"Albacete",
    "wof:name":"Gomez Martinez Angel",
    "wof:placetype":"venue"
},
  "geometry": {"coordinates":[-1.8618037701,39.002166748],"type":"Point"}
}