{
  "type": "Feature",
  "properties": {
    "iso:country":"ES",
    "sg:address":"Calle de Pedro Ortiz Ramos, 19",
    "sg:city":"Santa Olalla",
    "sg:orig_category":"Cerrajer\u00cda, Ferrallista",
    "sg:phone":"+34 925 79 79 89",
    "sg:postcode":"45530",
    "sg:province":"Toledo",
    "wof:name":"Rojugar S.l.",
    "wof:placetype":"venue"
},
  "geometry": {"coordinates":[-4.4363288879,40.0238342285],"type":"Point"}
}