{
  "type": "Feature",
  "properties": {
    "addr:full":"A Carrasqueira, S/n Ribadumia Pontevedra 36638",
    "addr:housenumber":"s / n",
    "addr:postcode":"36638",
    "addr:street":"Carrasqueira",
    "iso:country":"ES",
    "sg:address":"A Carrasqueira, S/n",
    "sg:city":"Ribadumia",
    "sg:orig_category":"Venta, Instalaci\u00d3n De Calefacci\u00d3n",
    "sg:phone":"+34 986 71 84 05",
    "sg:postcode":"36638",
    "sg:province":"Pontevedra",
    "wof:name":"Instalito S.l.u.",
    "wof:placetype":"venue"
},
  "geometry": {"coordinates":[-8.7900333405,42.4946594238],"type":"Point"}
}