{
  "type": "Feature",
  "properties": {
    "addr:full":"Pase Imperial, 37 Madrid Madrid 28005",
    "addr:housenumber":"37",
    "addr:postcode":"madrid;28005",
    "iso:country":"ES",
    "sg:address":"Pase Imperial, 37",
    "sg:city":"Madrid",
    "sg:orig_category":"Organismos Y Centros De Vacaciones Y Esparcimiento Para Ni\u00d1os Y Adolescentes",
    "sg:phone":"+34 913 66 75 53",
    "sg:postcode":"28005",
    "sg:province":"Madrid",
    "wof:name":"Venijuega Ven S.l.",
    "wof:placetype":"venue"
},
  "geometry": {"coordinates":[-3.7165699005,40.4065513611],"type":"Point"}
}