{
  "type": "Feature",
  "properties": {
    "iso:country":"ES",
    "sg:address":"Calle de Diputacion Provincial, 23",
    "sg:city":"Nerja",
    "sg:orig_category":"Agencias De Viajes",
    "sg:phone":"+34 952 52 61 53",
    "sg:postcode":"29780",
    "sg:province":"M\u00e1laga",
    "sg:website":"www.halconviajes.com",
    "wof:name":"Viajes Halcon S.a.",
    "wof:placetype":"venue"
},
  "geometry": {"coordinates":[-3.8794329166,36.7453842163],"type":"Point"}
}