{
  "type": "Feature",
  "properties": {
    "addr:full":"Avda Cervantes, 51 Arizgoiti Vizcaya 48970",
    "addr:housenumber":"51",
    "addr:postcode":"48970",
    "addr:street":"Avda Cervantes",
    "iso:country":"ES",
    "sg:address":"Avda Cervantes, 51",
    "sg:city":"Arizgoiti",
    "sg:orig_category":"Inform\u00c1tica (estudios, Servicios, Asesor\u00cda, Formaci\u00d3n)",
    "sg:phone":"+34 944 73 50 05",
    "sg:postcode":"48970",
    "sg:province":"Vizcaya",
    "wof:name":"Cbl Informatica S.l.",
    "wof:placetype":"venue"
},
  "geometry": {"coordinates":[-2.8774580956,43.2388687134],"type":"Point"}
}