{
  "type": "Feature",
  "properties": {
    "addr:full":"Avda Canillejas A Vicalvaro, 49 Madrid Madrid 28022",
    "addr:housenumber":"49",
    "addr:postcode":"madrid;28022",
    "addr:street":"Avda Canillejas A Vicalvaro",
    "iso:country":"ES",
    "sg:address":"Avda Canillejas A Vicalvaro, 49",
    "sg:city":"Madrid",
    "sg:orig_category":"Cristaler\u00cdas",
    "sg:phone":"+34 913 20 80 53",
    "sg:postcode":"28022",
    "sg:province":"Madrid",
    "wof:name":"Calero Glass S.l.",
    "wof:placetype":"venue"
},
  "geometry": {"coordinates":[-3.6133511066,40.4376564026],"type":"Point"}
}