{
  "type": "Feature",
  "properties": {
    "addr:full":"Calle de Mauricio Legendre, 2 Madrid Madrid 28046",
    "addr:housenumber":"2",
    "addr:postcode":"28046",
    "addr:street":"Calle De Mauricio Legendre",
    "iso:country":"ES",
    "sg:address":"Calle de Mauricio Legendre, 2",
    "sg:city":"Madrid",
    "sg:orig_category":"Tapiceros Y Tapiceros",
    "sg:phone":"+34 913 15 91 23",
    "sg:postcode":"28046",
    "sg:province":"Madrid",
    "wof:name":"Diaz Iglesias Sanchez Emilio",
    "wof:placetype":"venue"
},
  "geometry": {"coordinates":[-3.6858971119,40.4711074829],"type":"Point"}
}