{
  "type": "Feature",
  "properties": {
    "addr:full":"Calle de Real, 137 S. Fernando C\u00e1diz 11100",
    "addr:housenumber":"137",
    "addr:postcode":"11100",
    "addr:street":"Calle De Real;S. Fernando Ca\u0301Diz",
    "iso:country":"ES",
    "sg:address":"Calle de Real, 137",
    "sg:city":"S. Fernando",
    "sg:orig_category":"M\u00c9dicos: Ginecolog\u00cda Y Obstetricia",
    "sg:phone":"+34 956 59 53 75",
    "sg:postcode":"11100",
    "sg:province":"C\u00e1diz",
    "wof:name":"Andres Menacho Quevedo, C.b.",
    "wof:placetype":"venue"
},
  "geometry": {"coordinates":[-6.1993556023,36.4627914429],"type":"Point"}
}