{
  "type": "Feature",
  "properties": {
    "iso:country":"ES",
    "sg:address":"Crrl San Nicolas, 4",
    "sg:city":"Segovia",
    "sg:orig_category":"Arquitectos",
    "sg:phone":"+34 921 46 01 37",
    "sg:postcode":"40001",
    "sg:province":"Segovia",
    "wof:name":"Beltran Rodriguez Pablo",
    "wof:placetype":"venue"
},
  "geometry": {"coordinates":[-4.1211647987,40.9513435364],"type":"Point"}
}