{
  "type": "Feature",
  "properties": {
    "iso:country":"ES",
    "sg:address":"Avda Doctor Oloriz, 14",
    "sg:city":"Granada",
    "sg:orig_category":"Farmacias",
    "sg:phone":"+34 958 20 10 37",
    "sg:postcode":"18012",
    "sg:province":"Granada",
    "wof:name":"Saenz De Buruaga Lerena Felisa Maria",
    "wof:placetype":"venue"
},
  "geometry": {"coordinates":[-3.6070919037,37.1879005432],"type":"Point"}
}