{
  "type": "Feature",
  "properties": {
    "iso:country":"ES",
    "sg:address":"Cami Ral, 565",
    "sg:city":"Mataro",
    "sg:orig_category":"Edici\u00d3n De Diarios, Revistas, Boletines",
    "sg:phone":"+34 937 41 56 29",
    "sg:postcode":"08302",
    "sg:province":"Barcelona",
    "wof:name":"Edicions 44 S.l",
    "wof:placetype":"venue"
},
  "geometry": {"coordinates":[2.4397320747,41.5334815979],"type":"Point"}
}