{
  "type": "Feature",
  "properties": {
    "iso:country":"ES",
    "sg:address":"Plaz Ignacio Mercader, 2",
    "sg:city":"Donostia-san Sebastian",
    "sg:orig_category":"Molduras, Junquillos, Listones Y Molduras Perforadas",
    "sg:phone":"+34 943 45 61 94",
    "sg:postcode":"20011",
    "sg:province":"Guip\u00f9zcoa",
    "wof:name":"Sorazu Aramberri Roman",
    "wof:placetype":"venue"
},
  "geometry": {"coordinates":[-1.973976016,43.304725647],"type":"Point"}
}