{
  "type": "Feature",
  "properties": {
    "iso:country":"ES",
    "sg:address":"Calle de Alcalde Sainz De Baranda, 40",
    "sg:city":"Madrid",
    "sg:orig_category":"Abogados",
    "sg:phone":"+34 915 73 80 04",
    "sg:postcode":"28009",
    "sg:province":"Madrid",
    "wof:name":"Arribas Hernaez Fernando",
    "wof:placetype":"venue"
},
  "geometry": {"coordinates":[-3.6731188297,40.4166870117],"type":"Point"}
}