{
  "type": "Feature",
  "properties": {
    "addr:full":"Avda Argentina (la), 34 Ayora Valencia 46620",
    "addr:housenumber":"34",
    "addr:postcode":"46620",
    "addr:street":"Avda Argentina La",
    "iso:country":"ES",
    "sg:address":"Avda Argentina (la), 34",
    "sg:city":"Ayora",
    "sg:orig_category":"Equipo De Refrigeraci\u00d3n Industrial",
    "sg:phone":"+34 962 19 14 32",
    "sg:postcode":"46620",
    "sg:province":"Valencia",
    "wof:name":"Futurfrio S.l.",
    "wof:placetype":"venue"
},
  "geometry": {"coordinates":[-1.0581539869,39.0614471436],"type":"Point"}
}