{
  "type": "Feature",
  "properties": {
    "iso:country":"ES",
    "sg:address":"Rbla Lluis Companys, 2",
    "sg:city":"Mas Duran",
    "sg:orig_category":"Promotores Constructores",
    "sg:phone":"+34 937 21 08 80",
    "sg:postcode":"08192",
    "sg:province":"Barcelona",
    "wof:name":"Rasuns S.l.u.",
    "wof:placetype":"venue"
},
  "geometry": {"coordinates":[2.0770950317,41.535243988],"type":"Point"}
}