{
  "type": "Feature",
  "properties": {
    "addr:full":"Calle de Libertad, 4 Torrejon Ardoz Madrid 28850",
    "addr:housenumber":"4",
    "addr:postcode":"28850",
    "addr:street":"Calle De Libertad",
    "iso:country":"ES",
    "sg:address":"Calle de Libertad, 4",
    "sg:city":"Torrejon Ardoz",
    "sg:orig_category":"Agencias De Viajes",
    "sg:phone":"+34 916 76 18 97",
    "sg:postcode":"28850",
    "sg:province":"Madrid",
    "sg:website":"www.marsans.es",
    "wof:name":"Viajes Marsans S.a.",
    "wof:placetype":"venue"
},
  "geometry": {"coordinates":[-3.4797921181,40.4594726562],"type":"Point"}
}