{
  "type": "Feature",
  "properties": {
    "addr:full":"Carr Estrella, S/n Arenal D'en Castell Islas Baleares 07740",
    "addr:housenumber":"s",
    "addr:postcode":"07740",
    "addr:street":"Carr Estrella;/ N Arenal D'En Castell",
    "iso:country":"ES",
    "sg:address":"Carr Estrella, S/n",
    "sg:city":"Arenal D'en Castell",
    "sg:orig_category":"Alquiler De Oficinas Equipadas",
    "sg:phone":"+34 971 35 80 77",
    "sg:postcode":"07740",
    "sg:province":"Islas Baleares",
    "wof:name":"Mur Gisbert Joaquin",
    "wof:placetype":"venue"
},
  "geometry": {"coordinates":[2.8577105999,39.5341796875],"type":"Point"}
}