{
  "type": "Feature",
  "properties": {
    "iso:country":"ES",
    "sg:address":"Avda Santiago, 40",
    "sg:city":"Balazote",
    "sg:orig_category":"Abogados",
    "sg:phone":"+34 967 36 10 57",
    "sg:postcode":"02320",
    "sg:province":"Albacete",
    "wof:name":"Instalaciones Saez Castillo Sl",
    "wof:placetype":"venue"
},
  "geometry": {"coordinates":[-2.1527481079,38.882396698],"type":"Point"}
}