{
  "type": "Feature",
  "properties": {
    "iso:country":"ES",
    "sg:address":"Avda Padre Isla, 35",
    "sg:city":"Le\u00f3n",
    "sg:orig_category":"Peluqueros: De Se\u00d1oras",
    "sg:phone":"+34 987 22 64 21",
    "sg:postcode":"24002",
    "sg:province":"Le\u00f3n",
    "wof:name":"Sobrin Cabero Camino",
    "wof:placetype":"venue"
},
  "geometry": {"coordinates":[-5.5739269257,42.6008529663],"type":"Point"}
}