{
  "type": "Feature",
  "properties": {
    "addr:full":"Alam San Mames, 31 Bilbao Vizcaya 48010",
    "addr:housenumber":"31",
    "addr:postcode":"48010",
    "addr:street":"Alam San Mames",
    "iso:country":"ES",
    "sg:address":"Alam San Mames, 31",
    "sg:city":"Bilbao",
    "sg:orig_category":"Material Y Suministros Para Dentistas, Cirujanos",
    "sg:phone":"+34 944 10 09 03",
    "sg:postcode":"48010",
    "sg:province":"Vizcaya",
    "wof:name":"Galident S. A.",
    "wof:placetype":"venue"
},
  "geometry": {"coordinates":[-2.9375770092,43.2589530945],"type":"Point"}
}