{
  "type": "Feature",
  "properties": {
    "addr:full":"Ctra Binefar, 64 Tamarite Litera Huesca 22550",
    "addr:housenumber":"64",
    "addr:postcode":"22550",
    "addr:street":"Ctra Binefar",
    "iso:country":"ES",
    "sg:address":"Ctra Binefar, 64",
    "sg:city":"Tamarite Litera",
    "sg:orig_category":"Electricidad: Instaladores",
    "sg:phone":"+34 974 42 14 59",
    "sg:postcode":"22550",
    "sg:province":"Huesca",
    "wof:name":"Litelec S.l.l.",
    "wof:placetype":"venue"
},
  "geometry": {"coordinates":[0.4211159945,41.8660469055],"type":"Point"}
}