{
  "type": "Feature",
  "properties": {
    "addr:full":"Rond Levante, 1 Vista Alegre Murcia 30008",
    "addr:housenumber":"1",
    "addr:postcode":"30008",
    "addr:street":"Rond Levante",
    "iso:country":"ES",
    "sg:address":"Rond Levante, 1",
    "sg:city":"Vista Alegre",
    "sg:orig_category":"Restaurantes",
    "sg:phone":"+34 968 23 19 91",
    "sg:postcode":"30008",
    "sg:province":"Murcia",
    "wof:name":"Guerma S.l.",
    "wof:placetype":"venue"
},
  "geometry": {"coordinates":[-1.1298867464,37.9834747314],"type":"Point"}
}