{
  "type": "Feature",
  "properties": {
    "iso:country":"ES",
    "sg:address":"Calle de Correos, 1",
    "sg:city":"Navaconcejo",
    "sg:orig_category":"Arreglo, Reparaci\u00d3n, Piezas Sueltas De Televisi\u00d3n, V\u00cddeo, Hi",
    "sg:phone":"+34 927 17 32 86",
    "sg:postcode":"10613",
    "sg:province":"C\u00e1ceres",
    "wof:name":"Adan Castro Javier",
    "wof:placetype":"venue"
},
  "geometry": {"coordinates":[-5.8290266991,40.1805419922],"type":"Point"}
}