{
  "type": "Feature",
  "properties": {
    "iso:country":"ES",
    "sg:address":"Avda Diputacion, 23",
    "sg:city":"Palma Rio",
    "sg:orig_category":"Papeler\u00cdas, Librer\u00cdas",
    "sg:phone":"+34 957 64 60 13",
    "sg:postcode":"14700",
    "sg:province":"C\u00f3rdoba",
    "wof:name":"Martinez Torres Francisca",
    "wof:placetype":"venue"
},
  "geometry": {"coordinates":[-5.2795991898,37.7004241943],"type":"Point"}
}