{
  "type": "Feature",
  "properties": {
    "iso:country":"ES",
    "sg:address":"Avda Carlos V (de), 31",
    "sg:city":"Mostoles",
    "sg:orig_category":"Caf\u00c9s, Bares, Cervecer\u00cdas",
    "sg:phone":"+34 916 46 33 47",
    "sg:postcode":"28936",
    "sg:province":"Madrid",
    "wof:name":"Sanchez Nu\u00f1ez Emilio",
    "wof:placetype":"venue"
},
  "geometry": {"coordinates":[-3.8512759209,40.3181495667],"type":"Point"}
}