{
  "type": "Feature",
  "properties": {
    "addr:full":"Cadiz, 3 Cornella Llobregat Barcelona 08940",
    "addr:housenumber":"3",
    "addr:postcode":"08940",
    "addr:street":"Cadiz",
    "iso:country":"ES",
    "sg:address":"Cadiz, 3",
    "sg:city":"Cornella Llobregat",
    "sg:orig_category":"Droguer\u00cdas (al Por Menor)",
    "sg:phone":"+34 934 75 16 68",
    "sg:postcode":"08940",
    "sg:province":"Barcelona",
    "wof:name":"Fuentes Valverde Purificacion",
    "wof:placetype":"venue"
},
  "geometry": {"coordinates":[2.0708940029,41.3559417725],"type":"Point"}
}