{
  "type": "Feature",
  "properties": {
    "iso:country":"ES",
    "sg:address":"Calle de Viaducto Marquina, 4",
    "sg:city":"Oviedo",
    "sg:orig_category":"Alumbrados",
    "sg:phone":"+34 985 23 93 78",
    "sg:postcode":"33004",
    "sg:province":"Asturias",
    "wof:name":"Tu\u00f1on Caunedo Leonardo",
    "wof:placetype":"venue"
},
  "geometry": {"coordinates":[-5.8542561531,43.3653755188],"type":"Point"}
}