{
  "type": "Feature",
  "properties": {
    "addr:full":"Calle de Juan Xxiii, 9 Santurtzi Vizcaya 48980",
    "addr:housenumber":"9",
    "addr:postcode":"48980",
    "addr:street":"Calle De Juan Xxiii",
    "iso:country":"ES",
    "sg:address":"Calle de Juan Xxiii, 9",
    "sg:city":"Santurtzi",
    "sg:orig_category":"\u00d3ptica: Instrumentos (fabricaci\u00d3n)",
    "sg:phone":"+34 944 83 15 00",
    "sg:postcode":"48980",
    "sg:province":"Vizcaya",
    "wof:name":"Elicen S.l.",
    "wof:placetype":"venue"
},
  "geometry": {"coordinates":[-3.0343608856,43.3307266235],"type":"Point"}
}