{
  "type": "Feature",
  "properties": {
    "addr:full":"Calle de Martin Rey, 1 Cantillana Sevilla 41320",
    "addr:housenumber":"1",
    "addr:postcode":"41320",
    "addr:street":"Calle De Martin Rey",
    "iso:country":"ES",
    "sg:address":"Calle de Martin Rey, 1",
    "sg:city":"Cantillana",
    "sg:orig_category":"Perfumer\u00cda (al Por Menor)",
    "sg:phone":"+34 955 73 17 12",
    "sg:postcode":"41320",
    "sg:province":"Sevilla",
    "wof:name":"Rondon Lopez Manuel",
    "wof:placetype":"venue"
},
  "geometry": {"coordinates":[-5.8248391151,37.6077003479],"type":"Point"}
}