{
  "type": "Feature",
  "properties": {
    "iso:country":"ES",
    "sg:address":"Calle de Asdrubal, 51",
    "sg:city":"Puertollano",
    "sg:orig_category":"Ense\u00d1anza Secundaria: Colegios Y Escuelas Privadas",
    "sg:phone":"+34 926 41 12 05",
    "sg:postcode":"13500",
    "sg:province":"Ciudad Real",
    "wof:name":"I.e.s. Comendador Juan De Tavora",
    "wof:placetype":"venue"
},
  "geometry": {"coordinates":[-4.0491075516,38.6460075378],"type":"Point"}
}