{
  "type": "Feature",
  "properties": {
    "iso:country":"ES",
    "sg:address":"Calle de Santander, 4",
    "sg:city":"Melilla",
    "sg:orig_category":"M\u00c9dicos: Pediatr\u00cda. Enfermedades De Los Ni\u00d1os",
    "sg:phone":"+34 952 69 19 07",
    "sg:postcode":"52005",
    "sg:province":"Melilla",
    "wof:name":"Rico Monedero Antonia",
    "wof:placetype":"venue"
},
  "geometry": {"coordinates":[-2.9531469345,35.289264679],"type":"Point"}
}