{
  "type": "Feature",
  "properties": {
    "addr:full":"Carrer de Major, 15 S. Andreu Barca Barcelona 08740",
    "addr:housenumber":"15",
    "addr:postcode":"08740",
    "addr:street":"Carrer De Major;S. Andreu;Barcelona",
    "iso:country":"ES",
    "sg:address":"Carrer de Major, 15",
    "sg:city":"S. Andreu Barca",
    "sg:orig_category":"Frutas, Legumbres Frescas Y Tempranas (al Por Menor)",
    "sg:phone":"+34 936 82 95 06",
    "sg:postcode":"08740",
    "sg:province":"Barcelona",
    "wof:name":"Fernandez Valero Jose",
    "wof:placetype":"venue"
},
  "geometry": {"coordinates":[1.9737600088,41.4475898743],"type":"Point"}
}