{
  "type": "Feature",
  "properties": {
    "iso:country":"ES",
    "sg:address":"Alamo, 10",
    "sg:city":"Santo Angel",
    "sg:orig_category":"Fabricaci\u00d3n De Moldes Y Modelos",
    "sg:phone":"+34 968 84 70 98",
    "sg:postcode":"30151",
    "sg:province":"Murcia",
    "wof:name":"Fabricacion Especial De Articulos Mediterraneos S.l.",
    "wof:placetype":"venue"
},
  "geometry": {"coordinates":[-1.1302360296,37.9434127808],"type":"Point"}
}