{
  "type": "Feature",
  "properties": {
    "iso:country":"ES",
    "sg:address":"Avda San Juan De La Cruz, 14",
    "sg:city":"Infante Juan Manuel",
    "sg:orig_category":"Clubes, Asociaciones De Ocio",
    "sg:phone":"+34 968 25 72 99",
    "sg:postcode":"30011",
    "sg:province":"Murcia",
    "wof:name":"Melgar Jara Pedro",
    "wof:placetype":"venue"
},
  "geometry": {"coordinates":[-1.1157150269,37.9807624817],"type":"Point"}
}