{
  "type": "Feature",
  "properties": {
    "iso:country":"ES",
    "sg:address":"Plaz Jose Maria Orense, 10",
    "sg:city":"Valencia",
    "sg:orig_category":"M\u00c9dicos: Ginecolog\u00cda Y Obstetricia",
    "sg:phone":"+34 963 56 44 56",
    "sg:postcode":"46022",
    "sg:province":"Valencia",
    "wof:name":"Casells Hernandez Jose Luis",
    "wof:placetype":"venue"
},
  "geometry": {"coordinates":[-0.3394950032,39.4727516174],"type":"Point"}
}