{
  "type": "Feature",
  "properties": {
    "iso:country":"ES",
    "sg:address":"Calle de San Simeon, S/n",
    "sg:city":"Cabredo",
    "sg:orig_category":"Fabrica De Charcuter\u00cda",
    "sg:phone":"+34 948 44 40 08",
    "sg:postcode":"31118",
    "sg:province":"Navarra",
    "wof:name":"Corres Antonana Alfredo",
    "wof:placetype":"venue"
},
  "geometry": {"coordinates":[-2.4121890068,42.6293144226],"type":"Point"}
}