{
  "type": "Feature",
  "properties": {
    "addr:full":"Calle de Arenal, 43 Alcala Valle C\u00e1diz 11693",
    "addr:housenumber":"43",
    "addr:postcode":"11693",
    "addr:street":"Calle De Arenal;Ca\u0301Diz",
    "iso:country":"ES",
    "sg:address":"Calle de Arenal, 43",
    "sg:city":"Alcala Valle",
    "sg:orig_category":"Carnicer\u00cdas, Carnicer\u00cdas",
    "sg:phone":"+34 956 13 50 65",
    "sg:postcode":"11693",
    "sg:province":"C\u00e1diz",
    "wof:name":"Corchero Jimenez Antonio",
    "wof:placetype":"venue"
},
  "geometry": {"coordinates":[-5.1740794182,36.9058609009],"type":"Point"}
}