{
  "type": "Feature",
  "properties": {
    "iso:country":"ES",
    "sg:address":"Carrer de Moli, 47",
    "sg:city":"Esplugues Llobregat",
    "sg:orig_category":"Electrodom\u00c9sticos (al Por Menor)",
    "sg:phone":"+34 933 72 52 31",
    "sg:postcode":"08950",
    "sg:province":"Barcelona",
    "wof:name":"Linea Blanca Burguillos S.l.",
    "wof:placetype":"venue"
},
  "geometry": {"coordinates":[2.0975189209,41.3711891174],"type":"Point"}
}