{
  "type": "Feature",
  "properties": {
    "addr:full":"Carrer de Blasco De Garay, 127 Terrassa Barcelona 08224",
    "addr:housenumber":"127",
    "addr:postcode":"08224",
    "addr:street":"Carrer De Blasco De Garay",
    "iso:country":"ES",
    "sg:address":"Carrer de Blasco De Garay, 127",
    "sg:city":"Terrassa",
    "sg:orig_category":"Delineantes",
    "sg:phone":"+34 937 80 00 53",
    "sg:postcode":"08224",
    "sg:province":"Barcelona",
    "wof:name":"Cadmecanicus S.l.",
    "wof:placetype":"venue"
},
  "geometry": {"coordinates":[2.0029850006,41.5594711304],"type":"Point"}
}