{
  "type": "Feature",
  "properties": {
    "addr:full":"Polig. Ind. Valnalon, S/n Llangreu Asturias 33900",
    "addr:housenumber":"s / n",
    "addr:postcode":"33900",
    "addr:street":"Polig. Ind. Valnalon",
    "iso:country":"ES",
    "sg:address":"Polig. Ind. Valnalon, S/n",
    "sg:city":"Llangreu",
    "sg:orig_category":"Distribuci\u00d3n De Petr\u00d3leo Y Derivados",
    "sg:phone":"+34 985 69 49 97",
    "sg:postcode":"33900",
    "sg:province":"Asturias",
    "wof:name":"Gestora Madrile\u00f1a De Estaciones S.a.",
    "wof:placetype":"venue"
},
  "geometry": {"coordinates":[-5.649711132,43.2761459351],"type":"Point"}
}