{
  "type": "Feature",
  "properties": {
    "iso:country":"ES",
    "sg:address":"Calle de Rio Valcavero, 5",
    "sg:city":"Toledo",
    "sg:orig_category":"Chapister\u00cda",
    "sg:phone":"+34 925 23 21 94",
    "sg:postcode":"45007",
    "sg:province":"Toledo",
    "wof:name":"Maestre Bazaga Calixto",
    "wof:placetype":"venue"
},
  "geometry": {"coordinates":[-3.962143898,39.86693573],"type":"Point"}
}