{
  "type": "Feature",
  "properties": {
    "addr:full":"Calle de L, 184 Pol. Malpica Zaragoza 50057",
    "addr:housenumber":"184",
    "addr:postcode":"50057",
    "addr:street":"Calle De L;Pol. Malpica",
    "iso:country":"ES",
    "sg:address":"Calle de L, 184",
    "sg:city":"Pol. Malpica",
    "sg:orig_category":"Rectificaci\u00d3n, Mecanizado, Fresado",
    "sg:phone":"+34 976 46 54 89",
    "sg:postcode":"50057",
    "sg:province":"Zaragoza",
    "wof:name":"Hidrometal-gon S.l.",
    "wof:placetype":"venue"
},
  "geometry": {"coordinates":[-0.8813199997,41.6517295837],"type":"Point"}
}