{
  "type": "Feature",
  "properties": {
    "addr:full":"Ctra. Alicante, 94 S. Vicente Raspeig Alicante 03690",
    "addr:housenumber":"94",
    "addr:postcode":"03690",
    "addr:street":"Ctra. Alicante;S. Vicente Raspeig",
    "iso:country":"ES",
    "sg:address":"Ctra. Alicante, 94",
    "sg:city":"S. Vicente Raspeig",
    "sg:orig_category":"Fabricaci\u00d3n De Sobres, Bolsas Y Fundas",
    "sg:phone":"+34 965 67 05 43",
    "sg:postcode":"03690",
    "sg:province":"Alicante",
    "wof:name":"Tiendas Jaslen S. L.",
    "wof:placetype":"venue"
},
  "geometry": {"coordinates":[-0.5231339931,38.3981590271],"type":"Point"}
}