{
  "type": "Feature",
  "properties": {
    "iso:country":"ES",
    "sg:address":"Ctra Playas, 31",
    "sg:city":"Tias",
    "sg:orig_category":"Supermercados Y Hipermercados",
    "sg:phone":"+34 928 51 08 53",
    "sg:postcode":"35572",
    "sg:province":"Las Palmas",
    "wof:name":"Rodriguez Santana Daniel",
    "wof:placetype":"venue"
},
  "geometry": {"coordinates":[-13.6521291733,28.9543895721],"type":"Point"}
}