{
  "type": "Feature",
  "properties": {
    "addr:full":"Carrer de Olivera, 79 Mada Barcelona 08310",
    "addr:housenumber":"79",
    "addr:postcode":"08310",
    "addr:street":"Carrer De Olivera;Barcelona",
    "iso:country":"ES",
    "sg:address":"Carrer de Olivera, 79",
    "sg:city":"Mada",
    "sg:orig_category":"Maquinaria Para Industrias Diversas",
    "sg:phone":"+34 937 98 45 14",
    "sg:postcode":"08310",
    "sg:province":"Barcelona",
    "wof:name":"Ortega Lopez Julian",
    "wof:placetype":"venue"
},
  "geometry": {"coordinates":[2.4036650658,41.5564155579],"type":"Point"}
}