{
  "type": "Feature",
  "properties": {
    "addr:full":"Calle de Estacion, 76 Miranda Ebro Burgos 09200",
    "addr:housenumber":"76",
    "addr:postcode":"09200",
    "addr:street":"Calle De Estacion",
    "iso:country":"ES",
    "sg:address":"Calle de Estacion, 76",
    "sg:city":"Miranda Ebro",
    "sg:orig_category":"Art\u00cdculos De Decoraci\u00d3n",
    "sg:phone":"+34 947 32 13 49",
    "sg:postcode":"09200",
    "sg:province":"Burgos",
    "wof:name":"Lopez Olano Avelino",
    "wof:placetype":"venue"
},
  "geometry": {"coordinates":[-2.9418027401,42.6891593933],"type":"Point"}
}