{
  "type": "Feature",
  "properties": {
    "addr:full":"Carrer de Major, 30 Montcada Centre Barcelona 08110",
    "addr:housenumber":"30",
    "addr:postcode":"08110",
    "addr:street":"Carrer De Major",
    "iso:country":"ES",
    "sg:address":"Carrer de Major, 30",
    "sg:city":"Montcada Centre",
    "sg:orig_category":"Asesor\u00cda Fiscal Y Jur\u00cddica",
    "sg:phone":"+34 935 64 31 16",
    "sg:postcode":"08110",
    "sg:province":"Barcelona",
    "wof:name":"Toro Caballero Roberto",
    "wof:placetype":"venue"
},
  "geometry": {"coordinates":[2.1878840923,41.4855804443],"type":"Point"}
}