{
  "type": "Feature",
  "properties": {
    "iso:country":"ES",
    "sg:address":"Avda Valencia, 45",
    "sg:city":"Castellon",
    "sg:orig_category":"Molduras, Junquillos, Listones Y Molduras Perforadas",
    "sg:phone":"+34 964 21 73 20",
    "sg:postcode":"12005",
    "sg:province":"Castell\u00f3n",
    "wof:name":"Pitarch Prats Maria Dolores",
    "wof:placetype":"venue"
},
  "geometry": {"coordinates":[-0.0461230017,39.9773368835],"type":"Point"}
}