{
  "type": "Feature",
  "properties": {
    "addr:full":"Carrer de Riera Canals, 34 S. Andreu Barca Barcelona 08740",
    "addr:housenumber":"34",
    "addr:postcode":"08740",
    "addr:street":"Carrer De Riera Canals;S. Andreu;Barcelona",
    "iso:country":"ES",
    "sg:address":"Carrer de Riera Canals, 34",
    "sg:city":"S. Andreu Barca",
    "sg:orig_category":"Bazares, Art\u00cdculos De Limpieza Y De Cocina (al Por Menor)",
    "sg:phone":"+34 936 82 93 02",
    "sg:postcode":"08740",
    "sg:province":"Barcelona",
    "wof:name":"Nogueras Medina Rafael",
    "wof:placetype":"venue"
},
  "geometry": {"coordinates":[1.9760969877,41.448474884],"type":"Point"}
}