{
  "type": "Feature",
  "properties": {
    "addr:full":"Calle de Santa Victoria, 6 Cordoba C\u00f3rdoba 14003",
    "addr:housenumber":"6",
    "addr:postcode":"14003",
    "addr:street":"Calle De Santa Victoria;Co\u0301Rdoba",
    "iso:country":"ES",
    "sg:address":"Calle de Santa Victoria, 6",
    "sg:city":"Cordoba",
    "sg:orig_category":"Fiesta: Art\u00cdculos De (al Por Menor)",
    "sg:phone":"+34 957 47 45 80",
    "sg:postcode":"14003",
    "sg:province":"C\u00f3rdoba",
    "wof:name":"Mondejar Ortega Antonio",
    "wof:placetype":"venue"
},
  "geometry": {"coordinates":[-4.7789621353,37.8830528259],"type":"Point"}
}