{
  "type": "Feature",
  "properties": {
    "iso:country":"ES",
    "sg:address":"Calle de Cebreros, 36",
    "sg:city":"Madrid",
    "sg:orig_category":"Herboristas (al Por Menor)",
    "sg:phone":"+34 914 79 77 29",
    "sg:postcode":"28011",
    "sg:province":"Madrid",
    "wof:name":"Herbolario La Colmena S.l.",
    "wof:placetype":"venue"
},
  "geometry": {"coordinates":[-3.7452139854,40.4049224854],"type":"Point"}
}