{
  "type": "Feature",
  "properties": {
    "iso:country":"ES",
    "sg:address":"Avgd Ponent, 12",
    "sg:city":"Rossello",
    "sg:orig_category":"Ense\u00d1anza, Formaci\u00d3n Profesional: Aprendizaje",
    "sg:phone":"+34 973 73 03 06",
    "sg:postcode":"25124",
    "sg:province":"Lleida",
    "wof:name":"Ajuntament. Ceip La Rossella",
    "wof:placetype":"venue"
},
  "geometry": {"coordinates":[0.5938478708,41.6946144104],"type":"Point"}
}