{
  "type": "Feature",
  "properties": {
    "iso:country":"ES",
    "sg:address":"Calle de Camino Real, 86",
    "sg:city":"Yecla",
    "sg:orig_category":"Radiocomunicaciones, Telefon\u00cda M\u00d3vil, Radiomensajer\u00cda: Servicios, Comercializaci\u00d3n",
    "sg:phone":"+34 968 79 44 36",
    "sg:postcode":"30510",
    "sg:province":"Murcia",
    "wof:name":"Componentes Digital Yecla S.l.",
    "wof:placetype":"venue"
},
  "geometry": {"coordinates":[-1.1102256775,38.6142082214],"type":"Point"}
}