{
  "type": "Feature",
  "properties": {
    "addr:full":"Calle de San Juan, 20 Badajoz Badajoz 06002",
    "addr:housenumber":"20",
    "addr:postcode":"06002",
    "addr:street":"Calle De San Juan",
    "iso:country":"ES",
    "sg:address":"Calle de San Juan, 20",
    "sg:city":"Badajoz",
    "sg:orig_category":"Fiesta: Art\u00cdculos De (al Por Menor)",
    "sg:phone":"+34 924 23 97 04",
    "sg:postcode":"06002",
    "sg:province":"Badajoz",
    "wof:name":"Pereira Real Sergio",
    "wof:placetype":"venue"
},
  "geometry": {"coordinates":[-6.9690818787,38.8795471191],"type":"Point"}
}