{
  "type": "Feature",
  "properties": {
    "addr:full":"Av Meridiana, 450 Barcelona Barcelona 08030",
    "addr:housenumber":"450",
    "addr:postcode":"08030",
    "addr:street":"Meridiana",
    "iso:country":"ES",
    "sg:address":"Av Meridiana, 450",
    "sg:city":"Barcelona",
    "sg:orig_category":"Molduras, Junquillos, Listones Y Molduras Perforadas",
    "sg:phone":"+34 933 45 75 25",
    "sg:postcode":"08030",
    "sg:province":"Barcelona",
    "wof:name":"Pastor Descalzo Eva Maria",
    "wof:placetype":"venue"
},
  "geometry": {"coordinates":[2.1840720177,41.4345664978],"type":"Point"}
}