{
  "type": "Feature",
  "properties": {
    "addr:full":"Calle de Miguel Arredondo, 4 Madrid Madrid 28045",
    "addr:housenumber":"4",
    "addr:postcode":"28045",
    "addr:street":"Calle De Miguel Arredondo",
    "iso:country":"ES",
    "sg:address":"Calle de Miguel Arredondo, 4",
    "sg:city":"Madrid",
    "sg:orig_category":"Carnicer\u00cdas, Carnicer\u00cdas",
    "sg:phone":"+34 914 73 23 84",
    "sg:postcode":"28045",
    "sg:province":"Madrid",
    "wof:name":"Morales Fernandez Miguel Angel",
    "wof:placetype":"venue"
},
  "geometry": {"coordinates":[-3.6960179806,40.3950004578],"type":"Point"}
}