{
  "type": "Feature",
  "properties": {
    "addr:full":"Calle de Legua, S/n Merida Badajoz 06800",
    "addr:housenumber":"s",
    "addr:postcode":"06800",
    "addr:street":"Calle De Legua;/ N",
    "iso:country":"ES",
    "sg:address":"Calle de Legua, S/n",
    "sg:city":"Merida",
    "sg:orig_category":"Grafistas",
    "sg:phone":"+34 924 38 80 69",
    "sg:postcode":"06800",
    "sg:province":"Badajoz",
    "wof:name":"Luque Rojo Jose Maria",
    "wof:placetype":"venue"
},
  "geometry": {"coordinates":[-6.3472089767,38.9337310791],"type":"Point"}
}