{
  "type": "Feature",
  "properties": {
    "addr:full":"Calle de Castilla, 18 Donostia-san Sebastian Guip\u00f9zcoa 20015",
    "addr:housenumber":"18",
    "addr:postcode":"20015",
    "addr:street":"Calle De Castilla",
    "iso:country":"ES",
    "sg:address":"Calle de Castilla, 18",
    "sg:city":"Donostia-san Sebastian",
    "sg:orig_category":"Fabricaci\u00d3n, Venta De Cuadros, Accesorios Para Enmarcar",
    "sg:phone":"+34 943 28 94 18",
    "sg:postcode":"20015",
    "sg:province":"Guip\u00f9zcoa",
    "sg:website":"www.fragilenmarcacion.com",
    "wof:name":"Fontan Agorreta Ana",
    "wof:placetype":"venue"
},
  "geometry": {"coordinates":[-1.9575600624,43.3119621277],"type":"Point"}
}