{
  "type": "Feature",
  "properties": {
    "iso:country":"ES",
    "sg:address":"Carrer de Alberes, 23",
    "sg:city":"Barcelona",
    "sg:orig_category":"Limpieza Con Chorro De Arena Y Con Granalla, Pulido",
    "sg:phone":"+34 934 06 90 47",
    "sg:postcode":"08017",
    "sg:province":"Barcelona",
    "wof:name":"Arabit Gomez Jose",
    "wof:placetype":"venue"
},
  "geometry": {"coordinates":[2.1052060127,41.4144973755],"type":"Point"}
}