{
  "type": "Feature",
  "properties": {
    "addr:full":"Pase Sancho Abarca, 30 Laguardia \u00c1lava 01300",
    "addr:housenumber":"30",
    "addr:postcode":"01300",
    "addr:street":"Abarca",
    "iso:country":"ES",
    "sg:address":"Pase Sancho Abarca, 30",
    "sg:city":"Laguardia",
    "sg:orig_category":"Distribuci\u00d3n De Petr\u00d3leo Y Derivados",
    "sg:phone":"+34 945 60 07 98",
    "sg:postcode":"01300",
    "sg:province":"\u00c1lava",
    "wof:name":"Santamaria Martinez Gregorio",
    "wof:placetype":"venue"
},
  "geometry": {"coordinates":[-2.5841290951,42.5535812378],"type":"Point"}
}