{
  "type": "Feature",
  "properties": {
    "iso:country":"ES",
    "sg:address":"Calle de Obispo Rincon, 88",
    "sg:city":"Guadix",
    "sg:orig_category":"Arquitectos",
    "sg:phone":"+34 958 66 46 10",
    "sg:postcode":"18500",
    "sg:province":"Granada",
    "wof:name":"Fuentes Escudero Francisco Javier",
    "wof:placetype":"venue"
},
  "geometry": {"coordinates":[-3.1328690052,37.2969284058],"type":"Point"}
}