{
  "type": "Feature",
  "properties": {
    "iso:country":"ES",
    "sg:address":"C/ Almirall Cervera, 29",
    "sg:city":"Grao",
    "sg:orig_category":"Empresas De Limpieza",
    "sg:phone":"+34 964 58 83 15",
    "sg:postcode":"12593",
    "sg:province":"Castell\u00f3n",
    "wof:name":"Serviman Moncofa S.l.",
    "wof:placetype":"venue"
},
  "geometry": {"coordinates":[-0.1299870014,39.8020591736],"type":"Point"}
}