{
  "type": "Feature",
  "properties": {
    "addr:full":"Pg Mossen Lluis Constans, 240 Banyoles Girona 17820",
    "addr:housenumber":"240",
    "addr:postcode":"17820",
    "addr:street":"Pg Mossen Lluis Constans",
    "iso:country":"ES",
    "sg:address":"Pg Mossen Lluis Constans, 240",
    "sg:city":"Banyoles",
    "sg:orig_category":"Alquiler De V\u00cddeo",
    "sg:phone":"+34 972 57 40 92",
    "sg:postcode":"17820",
    "sg:province":"Girona",
    "wof:name":"Narvaez Muntet Lluis",
    "wof:placetype":"venue"
},
  "geometry": {"coordinates":[2.7653889656,42.1131896973],"type":"Point"}
}