{
  "type": "Feature",
  "properties": {
    "iso:country":"ES",
    "sg:address":"Plaz Santa Teresa, 4",
    "sg:city":"Avila",
    "sg:orig_category":"Perfumer\u00cda (al Por Menor)",
    "sg:phone":"+34 920 25 55 23",
    "sg:postcode":"05001",
    "sg:province":"\u00c1vila",
    "wof:name":"Rodrigo Garcia Emilia",
    "wof:placetype":"venue"
},
  "geometry": {"coordinates":[-4.7072339058,40.6581344604],"type":"Point"}
}