{
  "type": "Feature",
  "properties": {
    "iso:country":"ES",
    "sg:address":"Mart\u00edn De Lugones, 12",
    "sg:city":"Pola De Siero",
    "sg:orig_category":"Bisuter\u00cda, Joyer\u00cda, Relojer\u00cda (al Por Menor)",
    "sg:phone":"+34 985 72 07 46",
    "sg:postcode":"33510",
    "sg:province":"Asturias",
    "wof:name":"Cezon Quiros Mario",
    "wof:placetype":"venue"
},
  "geometry": {"coordinates":[-5.6616539955,43.3922042847],"type":"Point"}
}