{
  "type": "Feature",
  "properties": {
    "addr:full":"G.v. Corts Catalanes, 586 Barcelona Barcelona 08011",
    "addr:housenumber":"586",
    "addr:postcode":"08011",
    "addr:street":"Catalanes",
    "iso:country":"ES",
    "sg:address":"G.v. Corts Catalanes, 586",
    "sg:city":"Barcelona",
    "sg:orig_category":"Abogados",
    "sg:phone":"+34 933 23 56 08",
    "sg:postcode":"08011",
    "sg:province":"Barcelona",
    "wof:name":"Estruch Esteban Joaquin",
    "wof:placetype":"venue"
},
  "geometry": {"coordinates":[2.1629788876,41.3850097656],"type":"Point"}
}