{
  "type": "Feature",
  "properties": {
    "addr:full":"Calle de Maria De Lezo, 5 Errenteria Guip\u00f9zcoa 20100",
    "addr:housenumber":"5",
    "addr:postcode":"20100",
    "addr:street":"Calle De Maria De Lezo;Guipu\u0300Zcoa",
    "iso:country":"ES",
    "sg:address":"Calle de Maria De Lezo, 5",
    "sg:city":"Errenteria",
    "sg:orig_category":"Bisuter\u00cda, Joyer\u00cda, Relojer\u00cda (al Por Menor)",
    "sg:phone":"+34 943 34 10 79",
    "sg:postcode":"20100",
    "sg:province":"Guip\u00f9zcoa",
    "wof:name":"Joyeria Ayerdi C.b.",
    "wof:placetype":"venue"
},
  "geometry": {"coordinates":[-1.9005080462,43.3122444153],"type":"Point"}
}