{
  "type": "Feature",
  "properties": {
    "addr:full":"Calle de Doctor Esquerdo, 18 Madrid Madrid 28028",
    "addr:housenumber":"18",
    "addr:postcode":"madrid;28028",
    "addr:street":"Calle De Doctor Esquerdo",
    "iso:country":"ES",
    "sg:address":"Calle de Doctor Esquerdo, 18",
    "sg:city":"Madrid",
    "sg:orig_category":"Inform\u00c1tica (estudios, Servicios, Asesor\u00cda, Formaci\u00d3n)",
    "sg:phone":"+34 913 09 10 19",
    "sg:postcode":"28028",
    "sg:province":"Madrid",
    "sg:website":"www.deiser.com",
    "wof:name":"Deiser Desarrollo E Integracion De Sistemas S.l.",
    "wof:placetype":"venue"
},
  "geometry": {"coordinates":[-3.6688201427,40.4255371094],"type":"Point"}
}