{
  "type": "Feature",
  "properties": {
    "iso:country":"ES",
    "sg:address":"San Roque, 11",
    "sg:city":"Valles Ortega",
    "sg:classifiers":[
        {
            "category":"Taxi",
            "type":"Transportation"
        }
    ],
    "sg:phone":"+34 928 87 80 62",
    "sg:postcode":"35638",
    "sg:province":"Las Palmas",
    "wof:name":"Vera Dominguez Francisco",
    "wof:placetype":"venue"
},
  "geometry": {"coordinates":[-14.0084943771,28.3784255981],"type":"Point"}
}