{
  "type": "Feature",
  "properties": {
    "addr:full":"Plaz San Telmo, 8 Vinaros Castell\u00f3n 12500",
    "addr:housenumber":"8",
    "addr:postcode":"12500",
    "addr:street":"Plaz San Telmo",
    "iso:country":"ES",
    "sg:address":"Plaz San Telmo, 8",
    "sg:city":"Vinaros",
    "sg:orig_category":"Concepci\u00d3n Y Realizaci\u00d3n De Maquetas Profesionales Y Prototipos",
    "sg:phone":"+34 964 45 67 50",
    "sg:postcode":"12500",
    "sg:province":"Castell\u00f3n",
    "wof:name":"Promociones Hermanos Zaragoza Farnos S.l.",
    "wof:placetype":"venue"
},
  "geometry": {"coordinates":[0.4749450088,40.4711990356],"type":"Point"}
}