{
  "type": "Feature",
  "properties": {
    "addr:full":"Calle de Playa Samil, 18 Estacion Madrid 28400",
    "addr:housenumber":"18 estacion",
    "addr:postcode":"28400",
    "addr:street":"Calle De Playa Samil",
    "iso:country":"ES",
    "sg:address":"Calle de Playa Samil, 18",
    "sg:city":"Estacion",
    "sg:orig_category":"Quincaller\u00cda (al Por Menor)",
    "sg:phone":"+34 918 50 64 16",
    "sg:postcode":"28400",
    "sg:province":"Madrid",
    "wof:name":"Perez Rodriguez Jose Maria",
    "wof:placetype":"venue"
},
  "geometry": {"coordinates":[-4.0118079185,40.6172142029],"type":"Point"}
}