{
  "type": "Feature",
  "properties": {
    "addr:full":"Avda Schulz, 53 Gijon Asturias 33208",
    "addr:housenumber":"53",
    "addr:postcode":"33208",
    "addr:street":"Avda Schulz",
    "iso:country":"ES",
    "sg:address":"Avda Schulz, 53",
    "sg:city":"Gijon",
    "sg:orig_category":"Florister\u00cdas",
    "sg:phone":"+34 985 39 42 21",
    "sg:postcode":"33208",
    "sg:province":"Asturias",
    "wof:name":"Flores Y Plantas Gijon, S.l.",
    "wof:placetype":"venue"
},
  "geometry": {"coordinates":[-5.6654868126,43.5334472656],"type":"Point"}
}