{
  "type": "Feature",
  "properties": {
    "addr:full":"Av. Catalunya, 2 Benifallet Tarragona 43512",
    "addr:housenumber":"2",
    "addr:postcode":"43512",
    "addr:street":"Av. Catalunya",
    "iso:country":"ES",
    "sg:address":"Av. Catalunya, 2",
    "sg:city":"Benifallet",
    "sg:orig_category":"Arquitectos",
    "sg:phone":"+34 977 46 21 12",
    "sg:postcode":"43512",
    "sg:province":"Tarragona",
    "wof:name":"Pi\u00f1ol Folque Juan Jose",
    "wof:placetype":"venue"
},
  "geometry": {"coordinates":[0.5159019828,40.9731445312],"type":"Point"}
}