{
  "type": "Feature",
  "properties": {
    "iso:country":"ES",
    "sg:address":"Calle de Borneo, 9",
    "sg:city":"Salamanca",
    "sg:orig_category":"Contenedores Para Transporte De Mercanc\u00cdas",
    "sg:phone":"+34 923 18 62 23",
    "sg:postcode":"37003",
    "sg:province":"Salamanca",
    "wof:name":"Guinaldo Alvarez Saturnino",
    "wof:placetype":"venue"
},
  "geometry": {"coordinates":[-5.6436319351,40.9712257385],"type":"Point"}
}