{
  "type": "Feature",
  "properties": {
    "iso:country":"ES",
    "sg:address":"Calle de Artes De Arcos Marco, 6",
    "sg:city":"Alhama De Almeria",
    "sg:orig_category":"M\u00c9dicos: Estomatolog\u00cda",
    "sg:phone":"+34 950 64 15 00",
    "sg:postcode":"04400",
    "sg:province":"Almer\u00eda",
    "wof:name":"Rodriguez Perez Nicolas Francisco",
    "wof:placetype":"venue"
},
  "geometry": {"coordinates":[-2.5693337917,36.9586524963],"type":"Point"}
}