{
  "type": "Feature",
  "properties": {
    "iso:country":"ES",
    "sg:address":"Avda Menendez Pelayo, 12",
    "sg:city":"Sevilla",
    "sg:orig_category":"M\u00c9dicos: Otorrinolaringolog\u00cda",
    "sg:phone":"+34 954 41 11 12",
    "sg:postcode":"41004",
    "sg:province":"Sevilla",
    "wof:name":"Garcia Iriarte Maria Teresa",
    "wof:placetype":"venue"
},
  "geometry": {"coordinates":[-5.9869689941,37.3835487366],"type":"Point"}
}