{
  "type": "Feature",
  "properties": {
    "iso:country":"ES",
    "sg:address":"Calle de Pau Casals, 2",
    "sg:city":"Yecla",
    "sg:orig_category":"Peluquer\u00cdas, Peluquer\u00cda Mixta",
    "sg:phone":"+34 968 75 15 92",
    "sg:postcode":"30510",
    "sg:province":"Murcia",
    "wof:name":"Agueda Y Maria Angeles Ortega Diaz C.b.",
    "wof:placetype":"venue"
},
  "geometry": {"coordinates":[-1.173699379,38.6051635742],"type":"Point"}
}