{
  "type": "Feature",
  "properties": {
    "iso:country":"ES",
    "sg:address":"Calle de Jesus, 13",
    "sg:city":"Aldeanueva Ebro",
    "sg:orig_category":"Plomeros",
    "sg:phone":"+34 941 14 40 84",
    "sg:postcode":"26559",
    "sg:province":"La Rioja",
    "wof:name":"Leon Miranda Emilio",
    "wof:placetype":"venue"
},
  "geometry": {"coordinates":[-1.8801590204,42.2278594971],"type":"Point"}
}