{
  "type": "Feature",
  "properties": {
    "iso:country":"ES",
    "sg:address":"Calle de Princesa Guayarmina, 12",
    "sg:city":"Galdar",
    "sg:orig_category":"Empresas De Carpinter\u00cda De Madera",
    "sg:phone":"+34 928 88 06 63",
    "sg:postcode":"35460",
    "sg:province":"Las Palmas",
    "wof:name":"Rodriguez Guzman Mariano",
    "wof:placetype":"venue"
},
  "geometry": {"coordinates":[-15.6499414444,28.1462402344],"type":"Point"}
}