{
  "type": "Feature",
  "properties": {
    "addr:full":"Calle de Cuadra Saboner, S/n Castellon De La Plana Castell\u00f3n 12006",
    "addr:housenumber":"s / n",
    "addr:postcode":"12006",
    "addr:street":"Calle De Cuadra Saboner",
    "iso:country":"ES",
    "sg:address":"Calle de Cuadra Saboner, S/n",
    "sg:city":"Castellon De La Plana",
    "sg:orig_category":"Internados & Ense\u00d1anza Privada",
    "sg:phone":"+34 964 21 84 04",
    "sg:postcode":"12006",
    "sg:province":"Castell\u00f3n",
    "wof:name":"E.g.b.ramiro Izquierdo S.a.",
    "wof:placetype":"venue"
},
  "geometry": {"coordinates":[-0.0727590024,39.9778022766],"type":"Point"}
}