{
  "type": "Feature",
  "properties": {
    "addr:full":"Carrer de Freser, 29 Barcelona Barcelona 08026",
    "addr:housenumber":"29",
    "addr:postcode":"08026",
    "addr:street":"Carrer De Freser",
    "iso:country":"ES",
    "sg:address":"Carrer de Freser, 29",
    "sg:city":"Barcelona",
    "sg:orig_category":"Electromedicina: Equipo",
    "sg:phone":"+34 934 36 54 11",
    "sg:postcode":"08026",
    "sg:province":"Barcelona",
    "wof:name":"Raigs X Electromedicina S.c.p.",
    "wof:placetype":"venue"
},
  "geometry": {"coordinates":[2.1797850132,41.4111213684],"type":"Point"}
}