{
  "type": "Feature",
  "properties": {
    "addr:full":"Ctra Montesinos, Km. 0004,0 Algorfa Alicante 03169",
    "addr:postcode":"03169",
    "addr:street":"Ctra Montesinos Km. 0004,0",
    "iso:country":"ES",
    "sg:address":"Ctra Montesinos, Km. 0004,0",
    "sg:city":"Algorfa",
    "sg:orig_category":"Paletas",
    "sg:phone":"+34 966 78 14 16",
    "sg:postcode":"03169",
    "sg:province":"Alicante",
    "wof:name":"Fabrica Pales Garcia Ferrandez S.l.",
    "wof:placetype":"venue"
},
  "geometry": {"coordinates":[-0.7954850197,38.0876045227],"type":"Point"}
}