{
  "type": "Feature",
  "properties": {
    "iso:country":"ES",
    "sg:address":"Ctra. Calvario, Km. 0007,0",
    "sg:city":"Jerez",
    "sg:orig_category":"Fibras De Vidrio",
    "sg:phone":"+34 956 31 15 61",
    "sg:postcode":"11408",
    "sg:province":"C\u00e1diz",
    "sg:website":"www.sierrasur.com",
    "wof:name":"Sierra Sur-servicios De Obras S. A.",
    "wof:placetype":"venue"
},
  "geometry": {"coordinates":[-6.1479291916,36.6909103394],"type":"Point"}
}