{
  "type": "Feature",
  "properties": {
    "iso:country":"ES",
    "sg:address":"Calle de Camarena, 320",
    "sg:city":"Madrid",
    "sg:orig_category":"M\u00c9dicos: Gastroenterolog\u00cda Y Hepatolog\u00cda (aparato Digestivo)",
    "sg:phone":"+34 917 18 00 00",
    "sg:postcode":"28047",
    "sg:province":"Madrid",
    "wof:name":"Lopez Puertas Luis",
    "wof:placetype":"venue"
},
  "geometry": {"coordinates":[-3.7578356266,40.385433197],"type":"Point"}
}