{
  "type": "Feature",
  "properties": {
    "addr:full":"Calle de Mayor Baja, 10 Galve Teruel 44168",
    "addr:housenumber":"10",
    "addr:postcode":"44168",
    "addr:street":"Calle De Mayor Baja",
    "iso:country":"ES",
    "sg:address":"Calle de Mayor Baja, 10",
    "sg:city":"Galve",
    "sg:orig_category":"Organismos De Turismo",
    "sg:phone":"+34 978 77 61 55",
    "sg:postcode":"44168",
    "sg:province":"Teruel",
    "wof:name":"Guias De Galve S.l.",
    "wof:placetype":"venue"
},
  "geometry": {"coordinates":[-0.8826140165,40.6538162231],"type":"Point"}
}