{
  "type": "Feature",
  "properties": {
    "iso:country":"ES",
    "sg:address":"Pase Santo Domingo De Guzman, 1",
    "sg:city":"Baena",
    "sg:orig_category":"Iglesia Cat\u00d3lica",
    "sg:phone":"+34 957 67 09 44",
    "sg:postcode":"14850",
    "sg:province":"C\u00f3rdoba",
    "wof:name":"Parroquia De Nuestra Se\u00f1ora De Guadalupe Accion Catolica",
    "wof:placetype":"venue"
},
  "geometry": {"coordinates":[-4.3219118118,37.6156463623],"type":"Point"}
}