{
  "type": "Feature",
  "properties": {
    "iso:country":"ES",
    "sg:address":"Soldevila, 13",
    "sg:city":"Tremp",
    "sg:orig_category":"Farmacias",
    "sg:phone":"+34 973 65 00 32",
    "sg:postcode":"25620",
    "sg:province":"Lleida",
    "wof:name":"Martinez Borras Nuria",
    "wof:placetype":"venue"
},
  "geometry": {"coordinates":[0.8946769834,42.1663665771],"type":"Point"}
}