{
  "type": "Feature",
  "properties": {
    "addr:full":"Rua Doctor Loureiro Crespo, 7 Pontevedra Pontevedra 36001",
    "addr:housenumber":"7",
    "addr:postcode":"36001",
    "addr:street":"Rua Doctor Loureiro Crespo",
    "iso:country":"ES",
    "sg:address":"Rua Doctor Loureiro Crespo, 7",
    "sg:city":"Pontevedra",
    "sg:orig_category":"Servicios De Telecomunicaciones",
    "sg:phone":"+34 986 86 66 82",
    "sg:postcode":"36001",
    "sg:province":"Pontevedra",
    "wof:name":"Ministerio De Industria Turismo Y Comercio",
    "wof:placetype":"venue"
},
  "geometry": {"coordinates":[-8.6370706558,42.4292449951],"type":"Point"}
}