{
  "type": "Feature",
  "properties": {
    "addr:full":"Avda Ronda, 11 Aguilar Campoo Palencia 34800",
    "addr:housenumber":"11",
    "addr:postcode":"34800",
    "addr:street":"Avda Ronda",
    "iso:country":"ES",
    "sg:address":"Avda Ronda, 11",
    "sg:city":"Aguilar Campoo",
    "sg:orig_category":"Distribuci\u00d3n De Petr\u00d3leo Y Derivados",
    "sg:phone":"+34 979 12 25 26",
    "sg:postcode":"34800",
    "sg:province":"Palencia",
    "wof:name":"Diez Serrano Manuel",
    "wof:placetype":"venue"
},
  "geometry": {"coordinates":[-4.2655711174,42.7932624817],"type":"Point"}
}