{
  "type": "Feature",
  "properties": {
    "addr:full":"Ctra Murcia, 89 Mula Murcia 30170",
    "addr:housenumber":"89",
    "addr:postcode":"30170",
    "addr:street":"Ctra Murcia",
    "iso:country":"ES",
    "sg:address":"Ctra Murcia, 89",
    "sg:city":"Mula",
    "sg:orig_category":"Chapister\u00cda",
    "sg:phone":"+34 968 66 04 51",
    "sg:postcode":"30170",
    "sg:province":"Murcia",
    "wof:name":"Hijos De Antonio Garcia Sanchez S.l.",
    "wof:placetype":"venue"
},
  "geometry": {"coordinates":[-1.4816889763,38.0410118103],"type":"Point"}
}