{
  "type": "Feature",
  "properties": {
    "iso:country":"ES",
    "sg:address":"Calle de Vega Del Mar, 1",
    "sg:city":"San Pedro Alcantara",
    "sg:orig_category":"Promotores Constructores",
    "sg:phone":"+34 952 78 38 26",
    "sg:postcode":"29670",
    "sg:province":"M\u00e1laga",
    "wof:name":"Inversiones Fak S.l.",
    "wof:placetype":"venue"
},
  "geometry": {"coordinates":[-4.9938240051,36.4893188477],"type":"Point"}
}