{
  "type": "Feature",
  "properties": {
    "addr:full":"Rua Foz, 1 Ribadavia Ourense 32400",
    "addr:housenumber":"1",
    "addr:postcode":"32400",
    "addr:street":"Rua Foz",
    "iso:country":"ES",
    "sg:address":"Rua Foz, 1",
    "sg:city":"Ribadavia",
    "sg:orig_category":"Mec\u00c1nico Del Autom\u00d3vil",
    "sg:phone":"+34 988 47 03 01",
    "sg:postcode":"32400",
    "sg:province":"Ourense",
    "wof:name":"Canitrot Perez Fernando",
    "wof:placetype":"venue"
},
  "geometry": {"coordinates":[-8.1409893036,42.2891082764],"type":"Point"}
}