{
  "type": "Feature",
  "properties": {
    "addr:full":"Plaz General Vara De Rey, 5 Vara De Rey Cuenca 16709",
    "addr:housenumber":"5",
    "addr:postcode":"16709",
    "addr:street":"Vara;Rey",
    "iso:country":"ES",
    "sg:address":"Plaz General Vara De Rey, 5",
    "sg:city":"Vara De Rey",
    "sg:orig_category":"Sanatorios M\u00c9dico",
    "sg:phone":"+34 969 38 60 96",
    "sg:postcode":"16709",
    "sg:province":"Cuenca",
    "wof:name":"Ayuntamiento De Vara De Rey",
    "wof:placetype":"venue"
},
  "geometry": {"coordinates":[-2.2827384472,39.4434204102],"type":"Point"}
}