{
  "type": "Feature",
  "properties": {
    "addr:full":"Calle de Alfredo Truan, 7 Gijon Asturias 33205",
    "addr:housenumber":"7",
    "addr:postcode":"33205",
    "addr:street":"Calle De Alfredo Truan",
    "iso:country":"ES",
    "sg:address":"Calle de Alfredo Truan, 7",
    "sg:city":"Gijon",
    "sg:orig_category":"Asesor\u00cda Fiscal Y Jur\u00cddica",
    "sg:phone":"+34 985 34 07 45",
    "sg:postcode":"33205",
    "sg:province":"Asturias",
    "wof:name":"Freycon S.l.",
    "wof:placetype":"venue"
},
  "geometry": {"coordinates":[-5.6618456841,43.5377502441],"type":"Point"}
}