{
  "type": "Feature",
  "properties": {
    "iso:country":"ES",
    "sg:address":"Carr Pedret, 11",
    "sg:city":"Girona",
    "sg:orig_category":"Peluquer\u00cdas, Peluquer\u00cda Mixta",
    "sg:phone":"+34 972 22 23 92",
    "sg:postcode":"17007",
    "sg:province":"Girona",
    "wof:name":"Sanchez Piedra Maria Pilar",
    "wof:placetype":"venue"
},
  "geometry": {"coordinates":[2.8258850574,41.9909591675],"type":"Point"}
}