{
  "type": "Feature",
  "properties": {
    "addr:full":"Calle de San Jose De Calasanz, 21 Zaragoza Zaragoza 50008",
    "addr:housenumber":"21",
    "addr:postcode":"50008",
    "addr:street":"Calle De San;De Calasanz",
    "iso:country":"ES",
    "sg:address":"Calle de San Jose De Calasanz, 21",
    "sg:city":"Zaragoza",
    "sg:orig_category":"Mec\u00c1nico Del Autom\u00d3vil",
    "sg:phone":"+34 976 41 42 04",
    "sg:postcode":"50008",
    "sg:province":"Zaragoza",
    "wof:name":"Millan Garcia Eliseo",
    "wof:placetype":"venue"
},
  "geometry": {"coordinates":[-0.8754860163,41.6372184753],"type":"Point"}
}