{
  "type": "Feature",
  "properties": {
    "addr:full":"San Juan, 83 Lekunberri Navarra 31870",
    "addr:housenumber":"83",
    "addr:postcode":"31870",
    "addr:street":"San Juan",
    "iso:country":"ES",
    "sg:address":"San Juan, 83",
    "sg:city":"Lekunberri",
    "sg:orig_category":"Pescader\u00cdas (al Por Menor)",
    "sg:phone":"+34 948 50 40 71",
    "sg:postcode":"31870",
    "sg:province":"Navarra",
    "wof:name":"Itziar Mendia Barriola",
    "wof:placetype":"venue"
},
  "geometry": {"coordinates":[-1.8956489563,43.0057182312],"type":"Point"}
}