{
  "type": "Feature",
  "properties": {
    "addr:full":"Rua Curros Enriquez, 3 Cambados Pontevedra 36630",
    "addr:housenumber":"3",
    "addr:postcode":"36630",
    "addr:street":"Rua Curros Enriquez",
    "iso:country":"ES",
    "sg:address":"Rua Curros Enriquez, 3",
    "sg:city":"Cambados",
    "sg:orig_category":"Bancos",
    "sg:phone":"+34 986 52 08 54",
    "sg:postcode":"36630",
    "sg:province":"Pontevedra",
    "wof:name":"Banco Espa\u00d1ol De Credito S.a.",
    "wof:placetype":"venue"
},
  "geometry": {"coordinates":[-8.7775831223,42.2643013],"type":"Point"}
}