{
  "type": "Feature",
  "properties": {
    "addr:full":"Pl. Major, 1 Sa Pobla Islas Baleares 07420",
    "addr:housenumber":"1",
    "addr:postcode":"07420",
    "addr:street":"Pl. Major",
    "iso:country":"ES",
    "sg:address":"Pl. Major, 1",
    "sg:city":"Sa Pobla",
    "sg:orig_category":"Bancos",
    "sg:phone":"+34 971 54 01 50",
    "sg:postcode":"07420",
    "sg:province":"Islas Baleares",
    "sg:website":"www.bancamarch.es",
    "wof:name":"Banca March S.a.",
    "wof:placetype":"venue"
},
  "geometry": {"coordinates":[3.0241849422,39.7696609497],"type":"Point"}
}