{
  "type": "Feature",
  "properties": {
    "iso:country":"ES",
    "sg:address":"Carr Alemanya, 58",
    "sg:city":"Igualada",
    "sg:orig_category":"Hilaturas, Hilos Y Actividades Relacionadas",
    "sg:phone":"+34 938 03 15 46",
    "sg:postcode":"08700",
    "sg:province":"Barcelona",
    "wof:name":"Filex S.cp.",
    "wof:placetype":"venue"
},
  "geometry": {"coordinates":[1.6338289976,41.5847854614],"type":"Point"}
}