{
  "type": "Feature",
  "properties": {
    "iso:country":"ES",
    "sg:address":"Avda Ramon Menendez Pidal, 2",
    "sg:city":"Albacete",
    "sg:orig_category":"Administradores De Bienes Y Delegados De Comunidades De Propietarios",
    "sg:phone":"+34 967 21 20 14",
    "sg:postcode":"02005",
    "sg:province":"Albacete",
    "sg:website":"www.rexportal.com",
    "wof:name":"Rexportal Gestion S.l.",
    "wof:placetype":"venue"
},
  "geometry": {"coordinates":[-1.8613679409,39.000453949],"type":"Point"}
}