{
  "type": "Feature",
  "properties": {
    "addr:full":"Calle de Pedro Llamas Ruiz, S/n Mula Murcia 30170",
    "addr:postcode":"30170",
    "addr:street":"Calle De Pedro Llamas Ruiz S / N",
    "iso:country":"ES",
    "sg:address":"Calle de Pedro Llamas Ruiz, S/n",
    "sg:city":"Mula",
    "sg:orig_category":"Promotores Constructores",
    "sg:phone":"+34 968 63 71 23",
    "sg:postcode":"30170",
    "sg:province":"Murcia",
    "wof:name":"Construcciones Adricris Mu\u00f1oz S.l.",
    "wof:placetype":"venue"
},
  "geometry": {"coordinates":[-1.4876389503,38.040058136],"type":"Point"}
}