{
  "type": "Feature",
  "properties": {
    "addr:full":"Calle de Teodoro Camino, 28 Albacete Albacete 02002",
    "addr:housenumber":"28",
    "addr:postcode":"02002",
    "addr:street":"Calle De Teodoro Camino",
    "iso:country":"ES",
    "sg:address":"Calle de Teodoro Camino, 28",
    "sg:city":"Albacete",
    "sg:orig_category":"Asesor\u00cda Sobre Comunicaci\u00d3n De Empresas",
    "sg:phone":"+34 967 23 21 13",
    "sg:postcode":"02002",
    "sg:province":"Albacete",
    "wof:name":"Adade Albacete S.l.",
    "wof:placetype":"venue"
},
  "geometry": {"coordinates":[-1.8555643559,38.9905052185],"type":"Point"}
}