{
  "type": "Feature",
  "properties": {
    "addr:full":"Calle de Villaamil, 1 Mostoles Madrid 28934",
    "addr:housenumber":"1",
    "addr:postcode":"28934",
    "addr:street":"Calle De Villaamil",
    "iso:country":"ES",
    "sg:address":"Calle de Villaamil, 1",
    "sg:city":"Mostoles",
    "sg:orig_category":"Telas Y Sedas (al Por Menor)",
    "sg:phone":"+34 916 14 19 11",
    "sg:postcode":"28934",
    "sg:province":"Madrid",
    "wof:name":"Paredes Novillo Francisco",
    "wof:placetype":"venue"
},
  "geometry": {"coordinates":[-3.8669259548,40.3219528198],"type":"Point"}
}