{
  "type": "Feature",
  "properties": {
    "iso:country":"ES",
    "sg:address":"Calle de Santa Elena, 5",
    "sg:city":"Irun",
    "sg:orig_category":"Pescader\u00cdas (al Por Menor)",
    "sg:phone":"+34 943 62 28 10",
    "sg:postcode":"20304",
    "sg:province":"Guip\u00f9zcoa",
    "wof:name":"Pescaderia Amua",
    "wof:placetype":"venue"
},
  "geometry": {"coordinates":[-1.785730958,43.3369674683],"type":"Point"}
}