{
  "type": "Feature",
  "properties": {
    "addr:full":"Andres Segovia, 23 Xirivella Valencia 46950",
    "addr:housenumber":"23",
    "addr:postcode":"46950",
    "addr:street":"Segovia",
    "iso:country":"ES",
    "sg:address":"Andres Segovia, 23",
    "sg:city":"Xirivella",
    "sg:orig_category":"Talleres: Ropa A Medida",
    "sg:phone":"+34 963 70 43 70",
    "sg:postcode":"46950",
    "sg:province":"Valencia",
    "wof:name":"Lopez Bachiller Jose",
    "wof:placetype":"venue"
},
  "geometry": {"coordinates":[-0.41564399,39.4660835266],"type":"Point"}
}