{
  "type": "Feature",
  "properties": {
    "iso:country":"ES",
    "sg:address":"Calle de Doctor Mara\u00d1on, 26",
    "sg:city":"Mislata",
    "sg:orig_category":"Iglesia Cat\u00d3lica",
    "sg:phone":"+34 963 50 19 84",
    "sg:postcode":"46920",
    "sg:province":"Valencia",
    "wof:name":"Parroquia De San Carlos Borromeo",
    "wof:placetype":"venue"
},
  "geometry": {"coordinates":[-0.4218086898,39.4730873108],"type":"Point"}
}