{
  "type": "Feature",
  "properties": {
    "iso:country":"ES",
    "sg:address":"Calle de Puerta Real, S/n",
    "sg:city":"Zalamea Real",
    "sg:orig_category":"Chapa Y Pintura Veh\u00cdculos",
    "sg:phone":"+34 959 56 11 38",
    "sg:postcode":"21640",
    "sg:province":"Huelva",
    "wof:name":"Talleres Hermanos Gonzalez S.l.",
    "wof:placetype":"venue"
},
  "geometry": {"coordinates":[-6.6581058502,37.6776924133],"type":"Point"}
}