{
  "type": "Feature",
  "properties": {
    "iso:country":"ES",
    "sg:address":"Carrer de Santiago Rusi\u00d1ol, 2",
    "sg:city":"Castelldefels",
    "sg:orig_category":"Aparcamientos (infraestructuras, Accesorios)",
    "sg:phone":"+34 936 45 25 87",
    "sg:postcode":"08860",
    "sg:province":"Barcelona",
    "wof:name":"Inmoltra Sl",
    "wof:placetype":"venue"
},
  "geometry": {"coordinates":[1.9758199453,41.2809410095],"type":"Point"}
}