{
  "type": "Feature",
  "properties": {
    "addr:full":"Calle de Apatel, 24 Bigastro Alicante 03380",
    "addr:housenumber":"24",
    "addr:postcode":"03380",
    "addr:street":"Calle De Apatel",
    "iso:country":"ES",
    "sg:address":"Calle de Apatel, 24",
    "sg:city":"Bigastro",
    "sg:orig_category":"Insecticidas, Fumigaci\u00d3n",
    "sg:phone":"+34 965 35 09 08",
    "sg:postcode":"03380",
    "sg:province":"Alicante",
    "wof:name":"Agroquimicos De La Vega S. L.",
    "wof:placetype":"venue"
},
  "geometry": {"coordinates":[-0.8918713927,38.0619773865],"type":"Point"}
}