{
  "type": "Feature",
  "properties": {
    "addr:full":"Avda Navarra De, 36 Donostia-san Sebastian Guip\u00f9zcoa 20013",
    "addr:housenumber":"36",
    "addr:postcode":"20013",
    "addr:street":"Avda Navarra De",
    "iso:country":"ES",
    "sg:address":"Avda Navarra De, 36",
    "sg:city":"Donostia-san Sebastian",
    "sg:orig_category":"Abogados",
    "sg:phone":"+34 943 28 02 12",
    "sg:postcode":"20013",
    "sg:province":"Guip\u00f9zcoa",
    "wof:name":"Amiano Guevara Ignacio",
    "wof:placetype":"venue"
},
  "geometry": {"coordinates":[-1.9676624537,43.3232879639],"type":"Point"}
}