{
  "type": "Feature",
  "properties": {
    "addr:full":"Plaz Espa\u00d1a, 1 Utebo Zaragoza 50180",
    "addr:housenumber":"1",
    "addr:postcode":"50180",
    "addr:street":"Plaz Espan\u0303A",
    "iso:country":"ES",
    "sg:address":"Plaz Espa\u00d1a, 1",
    "sg:city":"Utebo",
    "sg:orig_category":"Iglesia Cat\u00d3lica",
    "sg:phone":"+34 976 77 01 82",
    "sg:postcode":"50180",
    "sg:province":"Zaragoza",
    "wof:name":"Parroquia Ntra Sra De La Asuncion",
    "wof:placetype":"venue"
},
  "geometry": {"coordinates":[-0.9950749874,41.7149543762],"type":"Point"}
}