{
  "type": "Feature",
  "properties": {
    "iso:country":"ES",
    "sg:address":"Calle de Toro, 6",
    "sg:city":"Salamanca",
    "sg:orig_category":"Art\u00cdculos De Regalo (al Por Menor)",
    "sg:phone":"+34 923 26 34 21",
    "sg:postcode":"37002",
    "sg:province":"Salamanca",
    "wof:name":"Perez Zarza Julian",
    "wof:placetype":"venue"
},
  "geometry": {"coordinates":[-5.6633467674,40.9653701782],"type":"Point"}
}