{
  "type": "Feature",
  "properties": {
    "addr:full":"Ctra Esplugues, S/n Fatjo Barcelona 08940",
    "addr:housenumber":"s",
    "addr:postcode":"08940",
    "addr:street":"Ctra Esplugues;/ N Fatjo",
    "iso:country":"ES",
    "sg:address":"Ctra Esplugues, S/n",
    "sg:city":"Fatjo",
    "sg:orig_category":"Transportes Por Carretera: Lotes Completos, Mercanc\u00cdas Diversas",
    "sg:phone":"+34 934 74 41 12",
    "sg:postcode":"08940",
    "sg:province":"Barcelona",
    "wof:name":"Productos Alimenticios Belros S.a.",
    "wof:placetype":"venue"
},
  "geometry": {"coordinates":[2.0708940029,41.3559417725],"type":"Point"}
}