{
  "type": "Feature",
  "properties": {
    "iso:country":"ES",
    "sg:address":"Trva San Antonio, 18",
    "sg:city":"Llerena",
    "sg:orig_category":"M\u00c9dicos: Oftalmolog\u00cda",
    "sg:phone":"+34 924 87 22 58",
    "sg:postcode":"06900",
    "sg:province":"Badajoz",
    "wof:name":"Ruiz Gonzalez Juan",
    "wof:placetype":"venue"
},
  "geometry": {"coordinates":[-6.0203762054,38.2380256653],"type":"Point"}
}