{
  "type": "Feature",
  "properties": {
    "addr:full":"Plaz Jupiter, 1 Jerez De La Frontera C\u00e1diz 11407",
    "addr:housenumber":"1",
    "addr:postcode":"11407",
    "addr:street":"Jupiter",
    "iso:country":"ES",
    "sg:address":"Plaz Jupiter, 1",
    "sg:city":"Jerez De La Frontera",
    "sg:orig_category":"Asesor\u00cda Fiscal Y Jur\u00cddica",
    "sg:phone":"+34 956 30 43 04",
    "sg:postcode":"11407",
    "sg:province":"C\u00e1diz",
    "wof:name":"Asesoria Jerez S.l.",
    "wof:placetype":"venue"
},
  "geometry": {"coordinates":[-6.1367936134,36.7047843933],"type":"Point"}
}