{
  "type": "Feature",
  "properties": {
    "addr:full":"Mas Canonges (pol Entrevias), 1 Tarragona Tarragona 43006",
    "addr:housenumber":"1",
    "addr:postcode":"43006",
    "addr:street":"Entrevias",
    "iso:country":"ES",
    "sg:address":"Mas Canonges (pol Entrevias), 1",
    "sg:city":"Tarragona",
    "sg:orig_category":"Transporte En General",
    "sg:phone":"+34 977 55 31 15",
    "sg:postcode":"43006",
    "sg:province":"Tarragona",
    "wof:name":"Miasa Logistica S.l",
    "wof:placetype":"venue"
},
  "geometry": {"coordinates":[1.2062180042,41.1080703735],"type":"Point"}
}