{
  "type": "Feature",
  "properties": {
    "addr:full":"Calle de Santiago, 41 Granada Granada 18009",
    "addr:housenumber":"41",
    "addr:postcode":"18009",
    "addr:street":"Calle De Santiago",
    "iso:country":"ES",
    "sg:address":"Calle de Santiago, 41",
    "sg:city":"Granada",
    "sg:orig_category":"Molduras, Junquillos, Listones Y Molduras Perforadas",
    "sg:phone":"+34 958 25 13 86",
    "sg:postcode":"18009",
    "sg:province":"Granada",
    "wof:name":"Gamaza Cueto Antonio",
    "wof:placetype":"venue"
},
  "geometry": {"coordinates":[-3.5923790932,37.1716651917],"type":"Point"}
}