{
  "type": "Feature",
  "properties": {
    "addr:full":"Calle de Ricardo Dacosta, 1 Porcuna Ja\u00e9n 23790",
    "addr:housenumber":"1",
    "addr:postcode":"23790",
    "addr:street":"Calle De Ricardo Dacosta",
    "iso:country":"ES",
    "sg:address":"Calle de Ricardo Dacosta, 1",
    "sg:city":"Porcuna",
    "sg:orig_category":"Transportes Por Carretera: Lotes Completos, Mercanc\u00cdas Diversas",
    "sg:phone":"+34 953 54 54 97",
    "sg:postcode":"23790",
    "sg:province":"Ja\u00e9n",
    "wof:name":"Luis Pi\u00f1a S.a.",
    "wof:placetype":"venue"
},
  "geometry": {"coordinates":[-4.1865692139,37.8722305298],"type":"Point"}
}