{
  "type": "Feature",
  "properties": {
    "iso:country":"ES",
    "sg:address":"Real, 1",
    "sg:city":"Berchules",
    "sg:orig_category":"Agricultores, Agricultores",
    "sg:phone":"+34 958 76 90 67",
    "sg:postcode":"18451",
    "sg:province":"Granada",
    "wof:name":"Baena Garcia Miguel",
    "wof:placetype":"venue"
},
  "geometry": {"coordinates":[-3.1902608871,36.9768943787],"type":"Point"}
}