{
  "type": "Feature",
  "properties": {
    "iso:country":"ES",
    "sg:address":"Carr Galicia, 47",
    "sg:city":"Eivissa",
    "sg:orig_category":"Asesor\u00cda Sobre Comunicaci\u00d3n De Empresas",
    "sg:phone":"+34 971 39 48 68",
    "sg:postcode":"07800",
    "sg:province":"Islas Baleares",
    "wof:name":"Consulta De Construcciones Pituasas S. L.",
    "wof:placetype":"venue"
},
  "geometry": {"coordinates":[1.4188899994,38.9061164856],"type":"Point"}
}