{
  "type": "Feature",
  "properties": {
    "addr:full":"Calle de Buen Maestro, 11 Lumbrales Salamanca 37240",
    "addr:housenumber":"11",
    "addr:postcode":"37240",
    "addr:street":"Calle De Buen Maestro",
    "iso:country":"ES",
    "sg:address":"Calle de Buen Maestro, 11",
    "sg:city":"Lumbrales",
    "sg:orig_category":"Ense\u00d1anza Secundaria: Colegios Y Escuelas Privadas",
    "sg:phone":"+34 923 51 21 15",
    "sg:postcode":"37240",
    "sg:province":"Salamanca",
    "wof:name":"I.e.s.tierras De Abadengo",
    "wof:placetype":"venue"
},
  "geometry": {"coordinates":[-6.7167701721,40.9368858337],"type":"Point"}
}