{
  "type": "Feature",
  "properties": {
    "iso:country":"ES",
    "sg:address":"Carr Pere Iii, 5",
    "sg:city":"Figueres",
    "sg:orig_category":"Fotocopias, Reprograf\u00cda",
    "sg:phone":"+34 972 50 12 90",
    "sg:postcode":"17600",
    "sg:province":"Girona",
    "wof:name":"Alcazar Santaella Maria Dolores",
    "wof:placetype":"venue"
},
  "geometry": {"coordinates":[2.9647164345,42.2625427246],"type":"Point"}
}