{
  "type": "Feature",
  "properties": {
    "addr:full":"Calle de Francisco Aritio, 66 Guadalajara Guadalajara 19004",
    "addr:housenumber":"66",
    "addr:postcode":"19004",
    "addr:street":"Calle De Francisco Aritio",
    "iso:country":"ES",
    "sg:address":"Calle de Francisco Aritio, 66",
    "sg:city":"Guadalajara",
    "sg:orig_category":"Art\u00cdculos De Decoraci\u00d3n",
    "sg:phone":"+34 949 25 47 82",
    "sg:postcode":"19004",
    "sg:province":"Guadalajara",
    "wof:name":"Garcia Viejo Maria",
    "wof:placetype":"venue"
},
  "geometry": {"coordinates":[-3.1848893166,40.6404266357],"type":"Point"}
}