{
  "type": "Feature",
  "properties": {
    "addr:full":"Carrer de Cadi, 33 Barcelona Barcelona 08031",
    "addr:housenumber":"33",
    "addr:postcode":"08031",
    "addr:street":"Carrer De Cadi",
    "iso:country":"ES",
    "sg:address":"Carrer de Cadi, 33",
    "sg:city":"Barcelona",
    "sg:orig_category":"Bazares, Art\u00cdculos De Limpieza Y De Cocina (al Por Menor)",
    "sg:phone":"+34 934 07 14 92",
    "sg:postcode":"08031",
    "sg:province":"Barcelona",
    "wof:name":"Flores Escribano Eva",
    "wof:placetype":"venue"
},
  "geometry": {"coordinates":[2.1693720818,41.4323425293],"type":"Point"}
}