{
  "type": "Feature",
  "properties": {
    "addr:full":"Calle de Hoz La, 37 Malaga M\u00e1laga 29002",
    "addr:housenumber":"37",
    "addr:postcode":"29002",
    "addr:street":"Calle De Hoz La;Ma\u0301Laga",
    "iso:country":"ES",
    "sg:address":"Calle de Hoz La, 37",
    "sg:city":"Malaga",
    "sg:orig_category":"Fabricaci\u00d3n, Importaci\u00d3n, Venta De Material De Telefon\u00cda, Peritelefon\u00cda",
    "sg:phone":"+34 952 35 92 45",
    "sg:postcode":"29002",
    "sg:province":"M\u00e1laga",
    "wof:name":"R S V D",
    "wof:placetype":"venue"
},
  "geometry": {"coordinates":[-4.4382538795,36.7026557922],"type":"Point"}
}