{
  "type": "Feature",
  "properties": {
    "iso:country":"ES",
    "sg:address":"Calle de Plaza (de La), 7",
    "sg:city":"Ca\u00e7ete De Las Torres",
    "sg:orig_category":"Zapatos (al Por Menor)",
    "sg:phone":"+34 957 18 31 02",
    "sg:postcode":"14660",
    "sg:province":"C\u00f3rdoba",
    "wof:name":"Torralbo Morena Diego",
    "wof:placetype":"venue"
},
  "geometry": {"coordinates":[-4.31828022,37.8679275513],"type":"Point"}
}