{
  "type": "Feature",
  "properties": {
    "iso:country":"ES",
    "sg:address":"Carrer de Castillejos, 298",
    "sg:city":"Barcelona",
    "sg:orig_category":"Montaje (empresas De)",
    "sg:phone":"+34 934 36 63 06",
    "sg:postcode":"08025",
    "sg:province":"Barcelona",
    "wof:name":"Grupo Conector S.a.",
    "wof:placetype":"venue"
},
  "geometry": {"coordinates":[2.1763091087,41.4082336426],"type":"Point"}
}