{
  "type": "Feature",
  "properties": {
    "iso:country":"ES",
    "sg:address":"Av Paisos Catalans, 26",
    "sg:city":"Zona Educacional",
    "sg:orig_category":"Molduras, Junquillos, Listones Y Molduras Perforadas",
    "sg:phone":"+34 977 24 90 78",
    "sg:postcode":"43007",
    "sg:province":"Tarragona",
    "wof:name":"Concesiones De Bares Y Restaurantes S.l.",
    "wof:placetype":"venue"
},
  "geometry": {"coordinates":[1.246029973,41.1325912476],"type":"Point"}
}