{
  "type": "Feature",
  "properties": {
    "addr:full":"Calle de Agricola Rodriguez, 6 Mora Toledo 45400",
    "addr:housenumber":"6",
    "addr:postcode":"45400",
    "addr:street":"Calle De Agricola Rodriguez",
    "iso:country":"ES",
    "sg:address":"Calle de Agricola Rodriguez, 6",
    "sg:city":"Mora",
    "sg:orig_category":"Piscinas, Accesorios, Suministros (fabricaci\u00d3n, Al Por Mayor)",
    "sg:phone":"+34 925 34 15 57",
    "sg:postcode":"45400",
    "sg:province":"Toledo",
    "wof:name":"Juan Rodriguez Marchan Sl",
    "wof:placetype":"venue"
},
  "geometry": {"coordinates":[-3.7767367363,39.6896705627],"type":"Point"}
}