{
  "type": "Feature",
  "properties": {
    "addr:full":"Avda Constitucion, S/n Segorbe Castell\u00f3n 12400",
    "addr:postcode":"12400",
    "addr:street":"Avda Constitucion S / N;Castello\u0301N",
    "iso:country":"ES",
    "sg:address":"Avda Constitucion, S/n",
    "sg:city":"Segorbe",
    "sg:orig_category":"T\u00c9cnicos Veterinarios",
    "sg:phone":"+34 964 71 28 57",
    "sg:postcode":"12400",
    "sg:province":"Castell\u00f3n",
    "wof:name":"Gamon Ovejero Maria Jesus",
    "wof:placetype":"venue"
},
  "geometry": {"coordinates":[-0.4897401035,39.8459014893],"type":"Point"}
}