{
  "type": "Feature",
  "properties": {
    "addr:full":"Carrer de Muntaner, 193 Barcelona Barcelona 08036",
    "addr:housenumber":"193",
    "addr:postcode":"08036",
    "addr:street":"Carrer De Muntaner",
    "iso:country":"ES",
    "sg:address":"Carrer de Muntaner, 193",
    "sg:city":"Barcelona",
    "sg:orig_category":"Venta, Alquiler De V\u00cddeo",
    "sg:phone":"+34 933 22 09 53",
    "sg:postcode":"08036",
    "sg:province":"Barcelona",
    "wof:name":"Games Workshop S.l.",
    "wof:placetype":"venue"
},
  "geometry": {"coordinates":[2.1506090164,41.3930854797],"type":"Point"}
}