{
  "type": "Feature",
  "properties": {
    "addr:full":"Calle de Alcantara, 71 Madrid Madrid 28006",
    "addr:housenumber":"71",
    "addr:postcode":"madrid;28006",
    "addr:street":"Calle De Alcantara",
    "iso:country":"ES",
    "sg:address":"Calle de Alcantara, 71",
    "sg:city":"Madrid",
    "sg:orig_category":"Centros M\u00c9dicos Y Sociales, Dispensarios",
    "sg:phone":"+34 913 09 01 49",
    "sg:postcode":"28006",
    "sg:province":"Madrid",
    "wof:name":"Naval Gias Luis",
    "wof:placetype":"venue"
},
  "geometry": {"coordinates":[-3.6734240055,40.4331436157],"type":"Point"}
}