{
  "type": "Feature",
  "properties": {
    "addr:full":"Calle de Almendro, 12 Jerez De La Frontera C\u00e1diz 11406",
    "addr:housenumber":"12",
    "addr:postcode":"11406",
    "addr:street":"Calle De Almendro",
    "iso:country":"ES",
    "sg:address":"Calle de Almendro, 12",
    "sg:city":"Jerez De La Frontera",
    "sg:orig_category":"Vallados Y Barreras",
    "sg:phone":"+34 956 33 52 50",
    "sg:postcode":"11406",
    "sg:province":"C\u00e1diz",
    "wof:name":"Pe\u00f1a Navarro Francisco",
    "wof:placetype":"venue"
},
  "geometry": {"coordinates":[-6.1123995781,36.6811790466],"type":"Point"}
}