{
  "type": "Feature",
  "properties": {
    "addr:full":"C/ Filet De Fora, 22 Elche Alicante 03203",
    "addr:housenumber":"22",
    "addr:postcode":"03203",
    "addr:street":"C / Filet De Fora",
    "iso:country":"ES",
    "sg:address":"C/ Filet De Fora, 22",
    "sg:city":"Elche",
    "sg:orig_category":"Abogados",
    "sg:phone":"+34 966 61 01 04",
    "sg:postcode":"03203",
    "sg:province":"Alicante",
    "wof:name":"Sanchez Garcia Alfredo",
    "wof:placetype":"venue"
},
  "geometry": {"coordinates":[-0.695915997,38.2635002136],"type":"Point"}
}