{
  "type": "Feature",
  "properties": {
    "addr:full":"Avda Alfonso El Sabio, 14 Alacant Alicante 03004",
    "addr:housenumber":"14",
    "addr:postcode":"03004",
    "addr:street":"Avda Alfonso El Sabio",
    "iso:country":"ES",
    "sg:address":"Avda Alfonso El Sabio, 14",
    "sg:city":"Alacant",
    "sg:orig_category":"M\u00c9dicos: Estomatolog\u00cda",
    "sg:phone":"+34 965 20 59 85",
    "sg:postcode":"03004",
    "sg:province":"Alicante",
    "wof:name":"Villena Serrano Julian",
    "wof:placetype":"venue"
},
  "geometry": {"coordinates":[-0.486947,38.3475074768],"type":"Point"}
}