{
  "type": "Feature",
  "properties": {
    "iso:country":"ES",
    "sg:address":"Cra. Calafell-bellvei, S/n",
    "sg:city":"Calafell",
    "sg:orig_category":"Ferreter\u00cda (diversos)",
    "sg:phone":"+34 977 69 21 14",
    "sg:postcode":"43820",
    "sg:province":"Tarragona",
    "wof:name":"Jurado Garcera Manuel",
    "wof:placetype":"venue"
},
  "geometry": {"coordinates":[1.5741369724,41.2140197754],"type":"Point"}
}