{
  "type": "Feature",
  "properties": {
    "addr:full":"Guntin, 11 Guntin Pontevedra 36378",
    "addr:housenumber":"11",
    "addr:postcode":"36378",
    "addr:street":"Guntin",
    "iso:country":"ES",
    "sg:address":"Guntin, 11",
    "sg:city":"Guntin",
    "sg:orig_category":"Empresas De Desmonte",
    "sg:phone":"+34 986 35 05 65",
    "sg:postcode":"36378",
    "sg:province":"Pontevedra",
    "wof:name":"Excavaciones Y Montajes Gonfer Sl",
    "wof:placetype":"venue"
},
  "geometry": {"coordinates":[-8.8027610779,42.109413147],"type":"Point"}
}