{
  "type": "Feature",
  "properties": {
    "addr:full":"San Juan Auzoa, 2 Bergara Guip\u00f9zcoa 20570",
    "addr:housenumber":"2",
    "addr:postcode":"20570",
    "addr:street":"San Juan Auzoa;Guipu\u0300Zcoa",
    "iso:country":"ES",
    "sg:address":"San Juan Auzoa, 2",
    "sg:city":"Bergara",
    "sg:orig_category":"Calderer\u00cda",
    "sg:phone":"+34 943 76 23 62",
    "sg:postcode":"20570",
    "sg:province":"Guip\u00f9zcoa",
    "wof:name":"Calderia Semar S.l.l.",
    "wof:placetype":"venue"
},
  "geometry": {"coordinates":[-2.4288430214,43.1266899109],"type":"Point"}
}