{
  "type": "Feature",
  "properties": {
    "addr:full":"C/ Benito Perez Galdos, 2 Elche Alicante 03201",
    "addr:housenumber":"2",
    "addr:postcode":"03201",
    "addr:street":"C / Benito Perez Galdos",
    "iso:country":"ES",
    "sg:address":"C/ Benito Perez Galdos, 2",
    "sg:city":"Elche",
    "sg:orig_category":"Abogados",
    "sg:phone":"+34 965 43 21 32",
    "sg:postcode":"03201",
    "sg:province":"Alicante",
    "wof:name":"Alberdi Garrido Ignacio",
    "wof:placetype":"venue"
},
  "geometry": {"coordinates":[-0.7041314244,38.2661437988],"type":"Point"}
}