{
  "type": "Feature",
  "properties": {
    "addr:full":"Calle de Ave Maria, 37 Madrid Madrid 28012",
    "addr:housenumber":"37",
    "addr:postcode":"madrid;28012",
    "addr:street":"Calle De Ave Maria",
    "iso:country":"ES",
    "sg:address":"Calle de Ave Maria, 37",
    "sg:city":"Madrid",
    "sg:orig_category":"Edici\u00d3n De Diarios, Revistas, Boletines",
    "sg:phone":"+34 915 27 19 78",
    "sg:postcode":"28012",
    "sg:province":"Madrid",
    "wof:name":"Via Xxi Ediciones S.l.",
    "wof:placetype":"venue"
},
  "geometry": {"coordinates":[-3.700797081,40.4097709656],"type":"Point"}
}