{
  "type": "Feature",
  "properties": {
    "iso:country":"ES",
    "sg:address":"Carrer de Batista I Roca, 44",
    "sg:city":"Mataro",
    "sg:orig_category":"Centros Empresariales",
    "sg:phone":"+34 937 41 47 77",
    "sg:postcode":"08302",
    "sg:province":"Barcelona",
    "wof:name":"Kisunex S.l.",
    "wof:placetype":"venue"
},
  "geometry": {"coordinates":[2.4231979847,41.5318756104],"type":"Point"}
}