{
  "type": "Feature",
  "properties": {
    "iso:country":"ES",
    "sg:address":"Calle de Pascal, 1",
    "sg:city":"Palmas De Gran Canaria",
    "sg:orig_category":"Inmobiliaria (agencias)",
    "sg:phone":"+34 928 22 81 90",
    "sg:postcode":"35007",
    "sg:province":"Las Palmas",
    "wof:name":"Consulting Inmobiliario Zona Norte S.l.",
    "wof:placetype":"venue"
},
  "geometry": {"coordinates":[-15.4349689484,28.1373596191],"type":"Point"}
}