{
  "type": "Feature",
  "properties": {
    "addr:full":"Calle de Doctor Jimenez Rueda, 55 Atarfe Granada 18230",
    "addr:housenumber":"55",
    "addr:postcode":"18230",
    "addr:street":"Calle De Doctor Jimenez Rueda",
    "iso:country":"ES",
    "sg:address":"Calle de Doctor Jimenez Rueda, 55",
    "sg:city":"Atarfe",
    "sg:orig_category":"Reposter\u00cdas",
    "sg:phone":"+34 958 43 77 52",
    "sg:postcode":"18230",
    "sg:province":"Granada",
    "wof:name":"Diaz Castellanos Francisco",
    "wof:placetype":"venue"
},
  "geometry": {"coordinates":[-3.6849091053,37.2241783142],"type":"Point"}
}