{
  "type": "Feature",
  "properties": {
    "addr:full":"Pl Santa Anna, 5 Montblanc Tarragona 43400",
    "addr:housenumber":"5",
    "addr:postcode":"43400",
    "addr:street":"Pl Santa Anna",
    "iso:country":"ES",
    "sg:address":"Pl Santa Anna, 5",
    "sg:city":"Montblanc",
    "sg:orig_category":"Vinagre Y Mostaza (fabricaci\u00d3n, Al Por Mayor)",
    "sg:phone":"+34 977 86 01 32",
    "sg:postcode":"43400",
    "sg:province":"Tarragona",
    "wof:name":"Mateu Guarro Jordi",
    "wof:placetype":"venue"
},
  "geometry": {"coordinates":[1.1615730524,41.3791923523],"type":"Point"}
}