{
  "type": "Feature",
  "properties": {
    "addr:full":"Avda Escaleritas, 33 Palmas De Gran Canaria Las Palmas 35011",
    "addr:housenumber":"33",
    "addr:postcode":"35011",
    "addr:street":"Avda Escaleritas",
    "iso:country":"ES",
    "sg:address":"Avda Escaleritas, 33",
    "sg:city":"Palmas De Gran Canaria",
    "sg:orig_category":"Quiropr\u00c1cticos",
    "sg:phone":"+34 928 20 67 75",
    "sg:postcode":"35011",
    "sg:province":"Las Palmas",
    "wof:name":"Camar Also Carlos Javier",
    "wof:placetype":"venue"
},
  "geometry": {"coordinates":[-15.4362287521,28.1228065491],"type":"Point"}
}