{
  "type": "Feature",
  "properties": {
    "iso:country":"ES",
    "sg:address":"Calle de Panaderas, 30",
    "sg:city":"Coru\u00d1a",
    "sg:orig_category":"Aparcamientos (infraestructuras, Accesorios)",
    "sg:phone":"+34 981 21 66 94",
    "sg:postcode":"15001",
    "sg:province":"La Coru\u00f1a",
    "wof:name":"Construccion De Aparcamientos Viviendas Y Locales S.l.",
    "wof:placetype":"venue"
},
  "geometry": {"coordinates":[-8.398733139,43.3728294373],"type":"Point"}
}