{
  "type": "Feature",
  "properties": {
    "iso:country":"ES",
    "sg:address":"Calle de Hermandad, 2",
    "sg:city":"Guajara",
    "sg:orig_category":"Ingenier\u00cda, Centros De Estudios (diversos)",
    "sg:phone":"+34 922 82 12 80",
    "sg:postcode":"38296",
    "sg:province":"Santa Cruz De Tenerife",
    "wof:name":"N.a.n.gabinete De Ingenieria S.l.",
    "wof:placetype":"venue"
},
  "geometry": {"coordinates":[-16.3148498535,28.4583091736],"type":"Point"}
}