{
  "type": "Feature",
  "properties": {
    "iso:country":"ES",
    "sg:address":"Avda Azahar (del), 25",
    "sg:city":"Jerez De La Frontera",
    "sg:orig_category":"Inform\u00c1tica Equipo Y Programas (al Por Mayor)",
    "sg:phone":"+34 956 32 63 27",
    "sg:postcode":"11408",
    "sg:province":"C\u00e1diz",
    "wof:name":"Igea Informatica S.l.",
    "wof:placetype":"venue"
},
  "geometry": {"coordinates":[-6.1514601707,36.6871566772],"type":"Point"}
}