{
  "type": "Feature",
  "properties": {
    "iso:country":"ES",
    "sg:address":"Galileo Galilei, 4",
    "sg:city":"Porceyo",
    "sg:orig_category":"Mudanzas",
    "sg:phone":"+34 985 19 50 50",
    "sg:postcode":"33392",
    "sg:province":"Asturias",
    "sg:website":"www.regueramudanzas.com",
    "wof:name":"Mudanzas Asturias S.l.",
    "wof:placetype":"venue"
},
  "geometry": {"coordinates":[-5.7052330971,43.5063514709],"type":"Point"}
}