{
  "type": "Feature",
  "properties": {
    "addr:full":"Avda. Finisterre, 277 A Coru\u00f1a La Coru\u00f1a 15008",
    "addr:housenumber":"277 a",
    "addr:postcode":"15008",
    "addr:street":"Avda. Finisterre;Corun\u0303A La Corun\u0303A",
    "iso:country":"ES",
    "sg:address":"Avda. Finisterre, 277",
    "sg:city":"A Coru\u00f1a",
    "sg:orig_category":"Cristaler\u00cdas",
    "sg:phone":"+34 981 27 97 57",
    "sg:postcode":"15008",
    "sg:province":"La Coru\u00f1a",
    "wof:name":"Cristaleria El Reflejo S.l.",
    "wof:placetype":"venue"
},
  "geometry": {"coordinates":[-8.4253416061,43.3563613892],"type":"Point"}
}