{
  "type": "Feature",
  "properties": {
    "addr:full":"Calle de Do\u00d1a Eloya, 22 Santa Marta De Tormes Salamanca 37900",
    "addr:housenumber":"22",
    "addr:postcode":"37900",
    "addr:street":"Calle De Don\u0303A Eloya",
    "iso:country":"ES",
    "sg:address":"Calle de Do\u00d1a Eloya, 22",
    "sg:city":"Santa Marta De Tormes",
    "sg:orig_category":"Librer\u00cdas",
    "sg:phone":"+34 923 13 89 73",
    "sg:postcode":"37900",
    "sg:province":"Salamanca",
    "wof:name":"Libreria Bustos S.l.",
    "wof:placetype":"venue"
},
  "geometry": {"coordinates":[-5.6219339371,40.9511833191],"type":"Point"}
}