{
  "type": "Feature",
  "properties": {
    "iso:country":"ES",
    "sg:address":"Psos Del Espino, 9",
    "sg:city":"Membrilla",
    "sg:orig_category":"Asociaciones, Instituciones De Consumidores Y Usuarios",
    "sg:phone":"+34 926 63 76 65",
    "sg:postcode":"13230",
    "sg:province":"Ciudad Real",
    "wof:name":"Asociacion Amas De Casa Consumidores Y Usuarios",
    "wof:placetype":"venue"
},
  "geometry": {"coordinates":[-3.3187470436,38.9197921753],"type":"Point"}
}