{
  "type": "Feature",
  "properties": {
    "iso:country":"ES",
    "sg:address":"Pl. Santiago, 53",
    "sg:city":"Estella",
    "sg:orig_category":"Molduras, Junquillos, Listones Y Molduras Perforadas",
    "sg:phone":"+34 948 55 30 65",
    "sg:postcode":"31200",
    "sg:province":"Navarra",
    "wof:name":"Garcia Flores Visitacion",
    "wof:placetype":"venue"
},
  "geometry": {"coordinates":[-2.0328929424,42.67237854],"type":"Point"}
}