{
  "type": "Feature",
  "properties": {
    "addr:full":"Ctra. Arta, Km. 0005,0 Son Servera Islas Baleares 07550",
    "addr:postcode":"07550",
    "addr:street":"Ctra. Arta;0005,0",
    "iso:country":"ES",
    "sg:address":"Ctra. Arta, Km. 0005,0",
    "sg:city":"Son Servera",
    "sg:orig_category":"Servicios Gsm",
    "sg:phone":"+34 971 18 30 22",
    "sg:postcode":"07550",
    "sg:province":"Islas Baleares",
    "wof:name":"Telefonica Moviles Espa\u00f1a S.a.",
    "wof:placetype":"venue"
},
  "geometry": {"coordinates":[3.3548560143,39.6253509521],"type":"Point"}
}