{
  "type": "Feature",
  "properties": {
    "iso:country":"ES",
    "sg:address":"Calle de Trinidad, 9",
    "sg:city":"Lebrija",
    "sg:orig_category":"Fabricaci\u00d3n, Importaci\u00d3n, Venta De Material De Telefon\u00cda, Peritelefon\u00cda",
    "sg:phone":"+34 955 97 15 06",
    "sg:postcode":"41740",
    "sg:province":"Sevilla",
    "wof:name":"Jaen Dominguez Antonio",
    "wof:placetype":"venue"
},
  "geometry": {"coordinates":[-6.0784702301,36.9188423157],"type":"Point"}
}