{
  "type": "Feature",
  "properties": {
    "iso:country":"ES",
    "sg:address":"Calle de Alcocer, 34",
    "sg:city":"Madrid",
    "sg:orig_category":"Alimentaci\u00d3n General (al Por Menor)",
    "sg:phone":"+34 915 05 39 59",
    "sg:postcode":"28041",
    "sg:province":"Madrid",
    "wof:name":"Hoyos Serrano Florentina",
    "wof:placetype":"venue"
},
  "geometry": {"coordinates":[-3.6999361515,40.3495521545],"type":"Point"}
}