{
  "type": "Feature",
  "properties": {
    "addr:full":"Calle de Palmito, 1 Algeciras C\u00e1diz 11204",
    "addr:housenumber":"1;ca\u0301diz",
    "addr:postcode":"11204",
    "addr:street":"Calle De Palmito",
    "iso:country":"ES",
    "sg:address":"Calle de Palmito, 1",
    "sg:city":"Algeciras",
    "sg:orig_category":"Agencias Y Agentes Comerciales, Representantes",
    "sg:phone":"+34 956 63 23 39",
    "sg:postcode":"11204",
    "sg:province":"C\u00e1diz",
    "wof:name":"Productos De La Sierra De Los Alcornocales S.l.",
    "wof:placetype":"venue"
},
  "geometry": {"coordinates":[-5.4582509995,36.1413993835],"type":"Point"}
}