{
  "type": "Feature",
  "properties": {
    "addr:full":"Calle de Azafran, 46 Monreal Campo Teruel 44300",
    "addr:housenumber":"46",
    "addr:postcode":"44300",
    "addr:street":"Calle De Azafran",
    "iso:country":"ES",
    "sg:address":"Calle de Azafran, 46",
    "sg:city":"Monreal Campo",
    "sg:orig_category":"Chapister\u00cda",
    "sg:phone":"+34 978 86 36 59",
    "sg:postcode":"44300",
    "sg:province":"Teruel",
    "wof:name":"Martin Plumed Francisco",
    "wof:placetype":"venue"
},
  "geometry": {"coordinates":[-1.3569054604,40.7887573242],"type":"Point"}
}