{
  "type": "Feature",
  "properties": {
    "addr:full":"Calle de Lorenzo Pausa, 3 San Miguel Murcia 30005",
    "addr:housenumber":"3",
    "addr:postcode":"30005",
    "addr:street":"Calle De Lorenzo Pausa",
    "iso:country":"ES",
    "sg:address":"Calle de Lorenzo Pausa, 3",
    "sg:city":"San Miguel",
    "sg:orig_category":"Deportes Y Programas De Aventura",
    "sg:phone":"+34 968 28 36 05",
    "sg:postcode":"30005",
    "sg:province":"Murcia",
    "wof:name":"Xai Sport Werld S.l.",
    "wof:placetype":"venue"
},
  "geometry": {"coordinates":[-1.1333979368,37.9874534607],"type":"Point"}
}