{
  "type": "Feature",
  "properties": {
    "addr:full":"Carrer de Guilleries, 20 Mas Mates Girona 17480",
    "addr:housenumber":"20",
    "addr:postcode":"17480",
    "addr:street":"Carrer De Guilleries;Mates",
    "iso:country":"ES",
    "sg:address":"Carrer de Guilleries, 20",
    "sg:city":"Mas Mates",
    "sg:orig_category":"Peluquer\u00cdas, Peluquer\u00cda Mixta",
    "sg:phone":"+34 972 15 31 44",
    "sg:postcode":"17480",
    "sg:province":"Girona",
    "wof:name":"Rodriguez Rodriguez Raquel",
    "wof:placetype":"venue"
},
  "geometry": {"coordinates":[3.1663351059,42.2661399841],"type":"Point"}
}