{
  "type": "Feature",
  "properties": {
    "addr:full":"Avda Oroel, 6 Jaca Huesca 22700",
    "addr:housenumber":"6",
    "addr:postcode":"22700",
    "addr:street":"Avda Oroel",
    "iso:country":"ES",
    "sg:address":"Avda Oroel, 6",
    "sg:city":"Jaca",
    "sg:classifiers":[
        {
            "category":"Autos & Motor Vehicles",
            "subcategory":"Automobile Sales",
            "type":"Retail Goods"
        }
    ],
    "sg:phone":"+34 974 36 21 01",
    "sg:postcode":"22700",
    "sg:province":"Huesca",
    "wof:name":"Autoescuela La Pe\u00f1a",
    "wof:placetype":"venue"
},
  "geometry": {"coordinates":[-0.5478848815,42.5675048828],"type":"Point"}
}