{
  "type": "Feature",
  "properties": {
    "iso:country":"ES",
    "sg:address":"Ctra Valadares, 528",
    "sg:city":"Gandara",
    "sg:orig_category":"Ropa De Casa (fabricaci\u00d3n, Al Por Mayor)",
    "sg:phone":"+34 986 46 52 15",
    "sg:postcode":"36315",
    "sg:province":"Pontevedra",
    "wof:name":"Fio Textil S.l.",
    "wof:placetype":"venue"
},
  "geometry": {"coordinates":[-8.7240085602,42.1735153198],"type":"Point"}
}