{
  "type": "Feature",
  "properties": {
    "iso:country":"ES",
    "sg:address":"Calle de Duque De La Victoria, 17",
    "sg:city":"Valladolid",
    "sg:orig_category":"Farmacias",
    "sg:phone":"+34 983 30 18 51",
    "sg:postcode":"47001",
    "sg:province":"Valladolid",
    "wof:name":"Sobrino Hebrero Carmen Maria",
    "wof:placetype":"venue"
},
  "geometry": {"coordinates":[-4.7262539864,41.6502304077],"type":"Point"}
}