{
  "type": "Feature",
  "properties": {
    "iso:country":"ES",
    "sg:address":"Pl Progres, 16",
    "sg:city":"Terrassa",
    "sg:orig_category":"Florister\u00cdas",
    "sg:phone":"+34 937 80 81 16",
    "sg:postcode":"08224",
    "sg:province":"Barcelona",
    "wof:name":"Clapes Carreras Gloria",
    "wof:placetype":"venue"
},
  "geometry": {"coordinates":[2.0057320595,41.5608596802],"type":"Point"}
}