{
  "type": "Feature",
  "properties": {
    "iso:country":"ES",
    "sg:address":"Carrer de Garrofes, 13",
    "sg:city":"Vendrell",
    "sg:orig_category":"Gas: Botellas Y Contenedores",
    "sg:phone":"+34 977 66 01 31",
    "sg:postcode":"43700",
    "sg:province":"Tarragona",
    "wof:name":"Soler Castellvi Eduardo",
    "wof:placetype":"venue"
},
  "geometry": {"coordinates":[1.5348290205,41.2211112976],"type":"Point"}
}