{
  "type": "Feature",
  "properties": {
    "iso:country":"ES",
    "sg:address":"Calle de Gomez Ore\u00d1a, 15",
    "sg:city":"Santander",
    "sg:orig_category":"M\u00c9dicos: Psiquiatr\u00cda",
    "sg:phone":"+34 942 31 40 10",
    "sg:postcode":"39003",
    "sg:province":"Cantabria",
    "wof:name":"Manrique Solana Rafael",
    "wof:placetype":"venue"
},
  "geometry": {"coordinates":[-3.8017885685,43.4636192322],"type":"Point"}
}