{
  "type": "Feature",
  "properties": {
    "addr:full":"Calle de B, 25 Gines Sevilla 41960",
    "addr:housenumber":"25",
    "addr:postcode":"41960",
    "addr:street":"Calle De B;Sevilla",
    "iso:country":"ES",
    "sg:address":"Calle de B, 25",
    "sg:city":"Gines",
    "sg:orig_category":"Fabricaci\u00d3n, Instalaci\u00d3n De Contadores",
    "sg:phone":"+34 954 71 77 36",
    "sg:postcode":"41960",
    "sg:province":"Sevilla",
    "wof:name":"Complementos Hidraulicos S.a.",
    "wof:placetype":"venue"
},
  "geometry": {"coordinates":[-6.0855193138,37.3810768127],"type":"Point"}
}