{
  "type": "Feature",
  "properties": {
    "iso:country":"ES",
    "sg:address":"Calle de Malfu, 6",
    "sg:city":"Palmas De Gran Canaria",
    "sg:orig_category":"Asociaciones Y Clubs Deportivos",
    "sg:phone":"+34 928 46 17 35",
    "sg:postcode":"35009",
    "sg:province":"Las Palmas",
    "wof:name":"Club De Futbol Ferreras",
    "wof:placetype":"venue"
},
  "geometry": {"coordinates":[-15.4223890305,28.1522808075],"type":"Point"}
}