{
  "type": "Feature",
  "properties": {
    "iso:country":"ES",
    "sg:address":"Finca Moratan, S/n",
    "sg:city":"Monda",
    "sg:orig_category":"Cr\u00cda De Animales",
    "sg:phone":"+34 952 11 20 93",
    "sg:postcode":"29110",
    "sg:province":"M\u00e1laga",
    "wof:name":"Hatrans S.l.",
    "wof:placetype":"venue"
},
  "geometry": {"coordinates":[-4.8280038834,36.6316719055],"type":"Point"}
}