{
  "type": "Feature",
  "properties": {
    "addr:full":"Calle de Calatrava, 49 Ciudad Real Ciudad Real 13003",
    "addr:housenumber":"49",
    "addr:postcode":"13003",
    "addr:street":"Calle De Calatrava",
    "iso:country":"ES",
    "sg:address":"Calle de Calatrava, 49",
    "sg:city":"Ciudad Real",
    "sg:orig_category":"Oficinas: Suministros Para (fabricaci\u00d3n, Al Por Mayor)",
    "sg:phone":"+34 926 23 26 98",
    "sg:postcode":"13003",
    "sg:province":"Ciudad Real",
    "wof:name":"Pick Ofimatica S.l.",
    "wof:placetype":"venue"
},
  "geometry": {"coordinates":[-3.9237222672,38.9908943176],"type":"Point"}
}