{
  "type": "Feature",
  "properties": {
    "addr:full":"Calle de Cruz Verde, 14 Torreperogil Ja\u00e9n 23320",
    "addr:housenumber":"14",
    "addr:postcode":"23320",
    "addr:street":"Calle De Cruz Verde",
    "iso:country":"ES",
    "sg:address":"Calle de Cruz Verde, 14",
    "sg:city":"Torreperogil",
    "sg:orig_category":"Aguas (distribuci\u00d3n, Servicios)",
    "sg:phone":"+34 953 77 71 40",
    "sg:postcode":"23320",
    "sg:province":"Ja\u00e9n",
    "wof:name":"Aguas Jaen S.a.",
    "wof:placetype":"venue"
},
  "geometry": {"coordinates":[-3.2891790867,38.0350189209],"type":"Point"}
}