{
  "type": "Feature",
  "properties": {
    "addr:full":"Calle de Monte Olivetti, 19 Madrid Madrid 28038",
    "addr:housenumber":"19",
    "addr:postcode":"madrid;28038",
    "addr:street":"Calle De Monte Olivetti",
    "iso:country":"ES",
    "sg:address":"Calle de Monte Olivetti, 19",
    "sg:city":"Madrid",
    "sg:orig_category":"Trajes Y Adornos De Boda (confecci\u00d3n, Al Por Menor)",
    "sg:phone":"+34 915 01 32 76",
    "sg:postcode":"28038",
    "sg:province":"Madrid",
    "sg:website":"www.parottinovias.com",
    "wof:name":"Talisman Novias S.l.",
    "wof:placetype":"venue"
},
  "geometry": {"coordinates":[-3.6669540405,40.3980331421],"type":"Point"}
}