{
  "type": "Feature",
  "properties": {
    "iso:country":"ES",
    "sg:address":"Calle de Santo Nicasio, 4",
    "sg:city":"Viana",
    "sg:orig_category":"Peluqueros: De Se\u00d1oras",
    "sg:phone":"+34 948 64 54 27",
    "sg:postcode":"31230",
    "sg:province":"Navarra",
    "wof:name":"Bonafau Ochoa Marta",
    "wof:placetype":"venue"
},
  "geometry": {"coordinates":[-2.3699159622,42.5160064697],"type":"Point"}
}