{
  "type": "Feature",
  "properties": {
    "addr:full":"Calle de Cervantes, 31 Santa Cruz De Mudela Ciudad Real 13730",
    "addr:housenumber":"31",
    "addr:postcode":"13730",
    "addr:street":"Calle De Cervantes",
    "iso:country":"ES",
    "sg:address":"Calle de Cervantes, 31",
    "sg:city":"Santa Cruz De Mudela",
    "sg:orig_category":"Agentes Generales De Seguros",
    "sg:phone":"+34 926 34 28 87",
    "sg:postcode":"13730",
    "sg:province":"Ciudad Real",
    "wof:name":"Fuentes Gavilan Miguel",
    "wof:placetype":"venue"
},
  "geometry": {"coordinates":[-3.4675729275,38.6409835815],"type":"Point"}
}