{
  "type": "Feature",
  "properties": {
    "addr:full":"Barr Portuondo, 6 Portuondo-basaran Vizcaya 48360",
    "addr:housenumber":"6",
    "addr:postcode":"48360",
    "addr:street":"Portuondo",
    "iso:country":"ES",
    "sg:address":"Barr Portuondo, 6",
    "sg:city":"Portuondo-basaran",
    "sg:orig_category":"Arquitectos",
    "sg:phone":"+34 946 87 69 36",
    "sg:postcode":"48360",
    "sg:province":"Vizcaya",
    "wof:name":"I.a.z.estudioa S.l.",
    "wof:placetype":"venue"
},
  "geometry": {"coordinates":[-2.7003688812,43.4094314575],"type":"Point"}
}