{
  "type": "Feature",
  "properties": {
    "addr:full":"Carrer de Roger De Lluria, 90 Mataro Barcelona 08303",
    "addr:housenumber":"90",
    "addr:postcode":"08303",
    "addr:street":"Carrer De Roger De Lluria",
    "iso:country":"ES",
    "sg:address":"Carrer de Roger De Lluria, 90",
    "sg:city":"Mataro",
    "sg:orig_category":"Fabricaci\u00d3n De Su\u00c9ters Y Chalecos De Punto",
    "sg:phone":"+34 937 99 00 19",
    "sg:postcode":"08303",
    "sg:province":"Barcelona",
    "wof:name":"Moraleda Cacho S.r.c.",
    "wof:placetype":"venue"
},
  "geometry": {"coordinates":[2.4219999313,41.539226532],"type":"Point"}
}