{
  "type": "Feature",
  "properties": {
    "iso:country":"ES",
    "sg:address":"Rbla Llibertat, 41",
    "sg:city":"Girona",
    "sg:orig_category":"Fabricaci\u00d3n, Distribuci\u00d3n De Discos, V\u00cddeodiscos Y Musicassettes",
    "sg:phone":"+34 972 22 37 70",
    "sg:postcode":"17004",
    "sg:province":"Girona",
    "sg:website":"www.noudisc.com",
    "wof:name":"Menamusic Berdala S.l.",
    "wof:placetype":"venue"
},
  "geometry": {"coordinates":[2.8242900372,41.9845466614],"type":"Point"}
}