{
  "type": "Feature",
  "properties": {
    "addr:full":"Cmno Rechazos (los), 33 Rechazos Santa Cruz De Tenerife 38311",
    "addr:housenumber":"33",
    "addr:postcode":"38311",
    "addr:street":"Cmno Rechazos Los",
    "iso:country":"ES",
    "sg:address":"Cmno Rechazos (los), 33",
    "sg:city":"Rechazos",
    "sg:orig_category":"Venta, Montaje De Neum\u00c1ticos",
    "sg:phone":"+34 922 33 44 08",
    "sg:postcode":"38311",
    "sg:province":"Santa Cruz De Tenerife",
    "wof:name":"Trujillo Garcia Domingo",
    "wof:placetype":"venue"
},
  "geometry": {"coordinates":[-16.4920501709,28.3701782227],"type":"Point"}
}