{
  "type": "Feature",
  "properties": {
    "addr:full":"Calle de Hoya Del Molino, 2 Lucena C\u00f3rdoba 14900",
    "addr:housenumber":"2",
    "addr:postcode":"14900",
    "addr:street":"Calle De Hoya Del Molino",
    "iso:country":"ES",
    "sg:address":"Calle de Hoya Del Molino, 2",
    "sg:city":"Lucena",
    "sg:orig_category":"Deportes Y Programas De Aventura",
    "sg:phone":"+34 957 51 64 94",
    "sg:postcode":"14900",
    "sg:province":"C\u00f3rdoba",
    "wof:name":"Ciclos Jimenez S.l.",
    "wof:placetype":"venue"
},
  "geometry": {"coordinates":[-4.4893488884,37.4063987732],"type":"Point"}
}