{
  "type": "Feature",
  "properties": {
    "addr:full":"Pase Prado, 24 Madrid Madrid 28014",
    "addr:housenumber":"24",
    "addr:postcode":"madrid;28014",
    "addr:street":"Prado",
    "iso:country":"ES",
    "sg:address":"Pase Prado, 24",
    "sg:city":"Madrid",
    "sg:orig_category":"Artes Gr\u00c1ficas, Artes Pl\u00c1sticas: Material Y Suministros (al Por Menor)",
    "sg:phone":"+34 914 20 28 89",
    "sg:postcode":"28014",
    "sg:province":"Madrid",
    "wof:name":"Produccion Y Promocion Cultural S.a.",
    "wof:placetype":"venue"
},
  "geometry": {"coordinates":[-3.6972920895,40.4151763916],"type":"Point"}
}