{
  "type": "Feature",
  "properties": {
    "addr:full":"Calle de Modistas, 20 Madrid Madrid 28037",
    "addr:housenumber":"20",
    "addr:postcode":"madrid;28037",
    "addr:street":"Calle De Modistas",
    "iso:country":"ES",
    "sg:address":"Calle de Modistas, 20",
    "sg:city":"Madrid",
    "sg:orig_category":"Plomeros",
    "sg:phone":"+34 913 06 31 76",
    "sg:postcode":"28037",
    "sg:province":"Madrid",
    "wof:name":"Mota Cardenosa Gregorio",
    "wof:placetype":"venue"
},
  "geometry": {"coordinates":[-3.6193909645,40.4273872375],"type":"Point"}
}