{
  "type": "Feature",
  "properties": {
    "addr:full":"Carrer de Emporda, 13 Hospitalet Llobregat Barcelona 08906",
    "addr:housenumber":"13",
    "addr:postcode":"08906",
    "addr:street":"Carrer De Emporda",
    "iso:country":"ES",
    "sg:address":"Carrer de Emporda, 13",
    "sg:city":"Hospitalet Llobregat",
    "sg:orig_category":"Agencias Y Asesores De Publicidad",
    "sg:phone":"+34 934 49 60 76",
    "sg:postcode":"08906",
    "sg:province":"Barcelona",
    "wof:name":"C.i.moya Sociedad Limitada",
    "wof:placetype":"venue"
},
  "geometry": {"coordinates":[2.1059570312,41.3744773865],"type":"Point"}
}