{
  "type": "Feature",
  "properties": {
    "iso:country":"ES",
    "sg:address":"Calle de Ancha, 14",
    "sg:city":"Ambroz",
    "sg:orig_category":"Aparatos E Instalaci\u00d3n De Regad\u00cdos",
    "sg:phone":"+34 958 44 50 43",
    "sg:postcode":"18194",
    "sg:province":"Granada",
    "wof:name":"Mingorance Salamanca Dolores",
    "wof:placetype":"venue"
},
  "geometry": {"coordinates":[-3.6620669365,37.1653823853],"type":"Point"}
}