{
  "type": "Feature",
  "properties": {
    "addr:full":"Calle de Navalcan, 34 Talavera Reina Toledo 45600",
    "addr:housenumber":"34",
    "addr:postcode":"45600",
    "addr:street":"Calle De Navalcan",
    "iso:country":"ES",
    "sg:address":"Calle de Navalcan, 34",
    "sg:city":"Talavera Reina",
    "sg:orig_category":"Puertas Y Portales",
    "sg:phone":"+34 925 82 13 38",
    "sg:postcode":"45600",
    "sg:province":"Toledo",
    "sg:website":"www.artepuerta.com",
    "wof:name":"Gonzalez Del Castillo Jose Luis",
    "wof:placetype":"venue"
},
  "geometry": {"coordinates":[-4.8440790176,39.9607048035],"type":"Point"}
}