{
  "type": "Feature",
  "properties": {
    "iso:country":"ES",
    "sg:address":"Calle de Tres Peces, 32",
    "sg:city":"Madrid",
    "sg:orig_category":"Bisuter\u00cda, Joyer\u00cda, Relojer\u00cda (al Por Menor)",
    "sg:phone":"+34 914 67 10 36",
    "sg:postcode":"28012",
    "sg:province":"Madrid",
    "wof:name":"Dise\u00f1os Montero S.l.",
    "wof:placetype":"venue"
},
  "geometry": {"coordinates":[-3.6987519264,40.4108085632],"type":"Point"}
}