{
  "type": "Feature",
  "properties": {
    "addr:full":"Calle de Andikoetxe, 2 Getxo Vizcaya 48990",
    "addr:housenumber":"2",
    "addr:postcode":"48990",
    "addr:street":"Calle De Andikoetxe",
    "iso:country":"ES",
    "sg:address":"Calle de Andikoetxe, 2",
    "sg:city":"Getxo",
    "sg:classifiers":[
        {
            "category":"Autos & Motor Vehicles",
            "subcategory":"Automobile Sales",
            "type":"Retail Goods"
        }
    ],
    "sg:phone":"+34 944 60 94 43",
    "sg:postcode":"48990",
    "sg:province":"Vizcaya",
    "wof:name":"Luis Fernandez Pereiras",
    "wof:placetype":"venue"
},
  "geometry": {"coordinates":[-3.0126554966,43.3518371582],"type":"Point"}
}