{
  "type": "Feature",
  "properties": {
    "addr:full":"Pol Ind Juncales, 8 La Puebla Rio Sevilla 41130",
    "addr:housenumber":"8",
    "addr:postcode":"41130",
    "addr:street":"Juncales",
    "iso:country":"ES",
    "sg:address":"Pol Ind Juncales, 8",
    "sg:city":"La Puebla Rio",
    "sg:orig_category":"Carros Elevadores, Carros De Operaciones Portuarias",
    "sg:phone":"+34 955 77 77 03",
    "sg:postcode":"41130",
    "sg:province":"Sevilla",
    "sg:website":"www.elevasur.com",
    "wof:name":"Elevasur S.l.",
    "wof:placetype":"venue"
},
  "geometry": {"coordinates":[-6.0651087761,37.2680435181],"type":"Point"}
}