{
  "type": "Feature",
  "properties": {
    "iso:country":"ES",
    "sg:address":"Calle de Merced, 86",
    "sg:city":"Coru\u00d1a",
    "sg:orig_category":"Albergues",
    "sg:phone":"+34 981 29 09 31",
    "sg:postcode":"15009",
    "sg:province":"La Coru\u00f1a",
    "wof:name":"Jose Maria Vazquez Gomez Y Otro S.c.",
    "wof:placetype":"venue"
},
  "geometry": {"coordinates":[-8.391784668,43.3521156311],"type":"Point"}
}