{
  "type": "Feature",
  "properties": {
    "iso:country":"ES",
    "sg:address":"Calle de San Francisco, 7",
    "sg:city":"Segovia",
    "sg:orig_category":"Charcuter\u00cdas (al Por Menor)",
    "sg:phone":"+34 921 42 82 21",
    "sg:postcode":"40001",
    "sg:province":"Segovia",
    "wof:name":"Briz Sanchez Isidoro",
    "wof:placetype":"venue"
},
  "geometry": {"coordinates":[-4.1177430153,40.9475326538],"type":"Point"}
}