{
  "type": "Feature",
  "properties": {
    "iso:country":"ES",
    "sg:address":"Calle de Lope De Vega, 18",
    "sg:city":"Ayamonte",
    "sg:orig_category":"Partidos Pol\u00cdticos",
    "sg:phone":"+34 959 47 16 21",
    "sg:postcode":"21400",
    "sg:province":"Huelva",
    "wof:name":"Izquierda Unida Convocatoria Por Andalucia",
    "wof:placetype":"venue"
},
  "geometry": {"coordinates":[-7.4015789032,37.2121086121],"type":"Point"}
}