{
  "type": "Feature",
  "properties": {
    "iso:country":"ES",
    "sg:address":"Calle de Bolivia, 10",
    "sg:city":"Baena",
    "sg:orig_category":"Servicios Gsm",
    "sg:phone":"+34 957 69 14 94",
    "sg:postcode":"14850",
    "sg:province":"C\u00f3rdoba",
    "sg:website":"www.serviciostelefonicos.com",
    "wof:name":"Servicios Telefonicos C.b.",
    "wof:placetype":"venue"
},
  "geometry": {"coordinates":[-4.3175768852,37.6175956726],"type":"Point"}
}