{
  "type": "Feature",
  "properties": {
    "iso:country":"ES",
    "sg:address":"Calle de Atalaya, 53",
    "sg:city":"Palmas De Gran Canaria",
    "sg:orig_category":"Charcuter\u00cdas (al Por Mayor)",
    "sg:phone":"+34 928 48 09 19",
    "sg:postcode":"35010",
    "sg:province":"Las Palmas",
    "wof:name":"Embutidos Y Productos Carnicos Los Canarios S.l.",
    "wof:placetype":"venue"
},
  "geometry": {"coordinates":[-15.4540500641,28.1077404022],"type":"Point"}
}