{
  "type": "Feature",
  "properties": {
    "iso:country":"ES",
    "sg:address":"Carrer de Manuel Aza\u00d1a, 34",
    "sg:city":"Palma",
    "sg:orig_category":"Inmobiliaria (agencias)",
    "sg:phone":"+34 971 46 31 28",
    "sg:postcode":"07006",
    "sg:province":"Islas Baleares",
    "sg:website":"www.piso-joven.com",
    "wof:name":"Mateo Cano Jose",
    "wof:placetype":"venue"
},
  "geometry": {"coordinates":[2.6635210514,39.5669212341],"type":"Point"}
}