{
  "type": "Feature",
  "properties": {
    "addr:full":"Calle de Rico Cejudo, 6 Sevilla Sevilla 41005",
    "addr:housenumber":"6",
    "addr:postcode":"41005",
    "addr:street":"Calle De Rico Cejudo",
    "iso:country":"ES",
    "sg:address":"Calle de Rico Cejudo, 6",
    "sg:city":"Sevilla",
    "sg:orig_category":"M\u00c9dicos: Psiquiatr\u00cda",
    "sg:phone":"+34 954 57 73 79",
    "sg:postcode":"41005",
    "sg:province":"Sevilla",
    "wof:name":"Elias Levato Leopoldo Angel",
    "wof:placetype":"venue"
},
  "geometry": {"coordinates":[-5.9675331116,37.3858032227],"type":"Point"}
}