{
  "type": "Feature",
  "properties": {
    "iso:country":"ES",
    "sg:address":"Carrer de Aribau, 77",
    "sg:city":"Barcelona",
    "sg:orig_category":"Reposter\u00cdas",
    "sg:phone":"+34 933 23 29 45",
    "sg:postcode":"08036",
    "sg:province":"Barcelona",
    "wof:name":"Rosendo Mila S.l.",
    "wof:placetype":"venue"
},
  "geometry": {"coordinates":[2.1578791142,41.3893432617],"type":"Point"}
}