{
  "type": "Feature",
  "properties": {
    "iso:country":"ES",
    "sg:address":"Carr Font (la), 27",
    "sg:city":"Pobla Segur",
    "sg:orig_category":"Chapister\u00cda",
    "sg:phone":"+34 973 68 08 91",
    "sg:postcode":"25500",
    "sg:province":"Lleida",
    "wof:name":"Gasa Figuera Miquel",
    "wof:placetype":"venue"
},
  "geometry": {"coordinates":[0.9664350152,42.2486915588],"type":"Point"}
}