{
  "type": "Feature",
  "properties": {
    "addr:full":"Psaj Zaidin, 18 Campillo Del Moro Almer\u00eda 04720",
    "addr:housenumber":"18",
    "addr:postcode":"04720",
    "addr:street":"Zaidin",
    "iso:country":"ES",
    "sg:address":"Psaj Zaidin, 18",
    "sg:city":"Campillo Del Moro",
    "sg:orig_category":"Asesor\u00cda Sobre Comunicaci\u00d3n De Empresas",
    "sg:phone":"+34 950 34 76 58",
    "sg:postcode":"04720",
    "sg:province":"Almer\u00eda",
    "wof:name":"Car & Led 2005 S.l.",
    "wof:placetype":"venue"
},
  "geometry": {"coordinates":[-2.5741510391,36.8138160706],"type":"Point"}
}