{
  "type": "Feature",
  "properties": {
    "iso:country":"ES",
    "sg:address":"Plaz Lealtad, 1",
    "sg:city":"Madrid",
    "sg:orig_category":"Inversiones",
    "sg:phone":"+34 915 24 04 82",
    "sg:postcode":"28014",
    "sg:province":"Madrid",
    "wof:name":"Link Securities A.v.b. S.a.",
    "wof:placetype":"venue"
},
  "geometry": {"coordinates":[-3.692497015,40.4169654846],"type":"Point"}
}