{
  "type": "Feature",
  "properties": {
    "addr:full":"Carrer de Frederica Montseny, S/n Prat Llobregat Barcelona 08820",
    "addr:housenumber":"s / n",
    "addr:postcode":"08820",
    "addr:street":"Carrer De Frederica Montseny;Llobregat",
    "iso:country":"ES",
    "sg:address":"Carrer de Frederica Montseny, S/n",
    "sg:city":"Prat Llobregat",
    "sg:orig_category":"Asociaciones Y Clubs Deportivos",
    "sg:phone":"+34 934 78 13 00",
    "sg:postcode":"08820",
    "sg:province":"Barcelona",
    "wof:name":"Centre D'activitats Subaquatiques El Prat",
    "wof:placetype":"venue"
},
  "geometry": {"coordinates":[2.0834479332,41.3221855164],"type":"Point"}
}