{
  "type": "Feature",
  "properties": {
    "addr:full":"Rond San Pancracio, 10 Garray Soria 42162",
    "addr:housenumber":"10",
    "addr:postcode":"42162",
    "iso:country":"ES",
    "sg:address":"Rond San Pancracio, 10",
    "sg:city":"Garray",
    "sg:orig_category":"Madera Para Construcci\u00d3n E Industria",
    "sg:phone":"+34 975 25 20 72",
    "sg:postcode":"42162",
    "sg:province":"Soria",
    "wof:name":"Estructuras De Madera Ancaso S.l.",
    "wof:placetype":"venue"
},
  "geometry": {"coordinates":[-2.4426970482,41.8164634705],"type":"Point"}
}