{
  "type": "Feature",
  "properties": {
    "addr:full":"Calle de Pelayo, 21 Valencia Valencia 46007",
    "addr:housenumber":"21",
    "addr:postcode":"46007",
    "addr:street":"Calle De Pelayo",
    "iso:country":"ES",
    "sg:address":"Calle de Pelayo, 21",
    "sg:city":"Valencia",
    "sg:orig_category":"Abogados",
    "sg:phone":"+34 963 94 28 22",
    "sg:postcode":"46007",
    "sg:province":"Valencia",
    "wof:name":"Teodoro Peris Merce",
    "wof:placetype":"venue"
},
  "geometry": {"coordinates":[-0.3788020015,39.4663505554],"type":"Point"}
}