{
  "type": "Feature",
  "properties": {
    "addr:full":"Carr General Guell, 22 Cervera Lleida 25200",
    "addr:housenumber":"22",
    "addr:postcode":"25200",
    "addr:street":"Carr General Guell",
    "iso:country":"ES",
    "sg:address":"Carr General Guell, 22",
    "sg:city":"Cervera",
    "sg:orig_category":"Fotograf\u00cda Art\u00cdstica Y Retratos",
    "sg:phone":"+34 973 53 05 61",
    "sg:postcode":"25200",
    "sg:province":"Lleida",
    "wof:name":"Caus Rius Sebastia",
    "wof:placetype":"venue"
},
  "geometry": {"coordinates":[1.2743370533,41.6718330383],"type":"Point"}
}