{
  "type": "Feature",
  "properties": {
    "addr:full":"Ctra Nacional 340, 144 Vinaros Castell\u00f3n 12500",
    "addr:housenumber":"144",
    "addr:postcode":"12500",
    "addr:street":"Ctra Nacional 340",
    "iso:country":"ES",
    "sg:address":"Ctra Nacional 340, 144",
    "sg:city":"Vinaros",
    "sg:orig_category":"Muebles, Minoristas",
    "sg:phone":"+34 964 45 18 99",
    "sg:postcode":"12500",
    "sg:province":"Castell\u00f3n",
    "wof:name":"Muebles Barlo S.l.",
    "wof:placetype":"venue"
},
  "geometry": {"coordinates":[0.4749450088,40.4711990356],"type":"Point"}
}