{
  "type": "Feature",
  "properties": {
    "iso:country":"ES",
    "sg:address":"Carrer de Montjuic, 23",
    "sg:city":"Can Rial",
    "sg:orig_category":"Delegados, Agentes De Tr\u00c1nsito, Auxiliares De Transporte Internacional",
    "sg:phone":"+34 937 77 34 62",
    "sg:postcode":"08292",
    "sg:province":"Barcelona",
    "wof:name":"Alarcon Ruiz Emilio",
    "wof:placetype":"venue"
},
  "geometry": {"coordinates":[1.8535723686,41.5295715332],"type":"Point"}
}