{
  "type": "Feature",
  "properties": {
    "addr:full":"Calle de Comedias, 9 Malaga M\u00e1laga 29008",
    "addr:housenumber":"9",
    "addr:postcode":"29008",
    "addr:street":"Calle De Comedias;Ma\u0301Laga",
    "iso:country":"ES",
    "sg:address":"Calle de Comedias, 9",
    "sg:city":"Malaga",
    "sg:orig_category":"Asesor\u00cda De Formaci\u00d3n Y Gesti\u00d3n De Personal",
    "sg:phone":"+34 952 22 14 82",
    "sg:postcode":"29008",
    "sg:province":"M\u00e1laga",
    "wof:name":"Gutierrez Tellez Jesus",
    "wof:placetype":"venue"
},
  "geometry": {"coordinates":[-4.4216856956,36.7227668762],"type":"Point"}
}