{
  "type": "Feature",
  "properties": {
    "iso:country":"ES",
    "sg:address":"Campa\u00f1o De Arriba, 46",
    "sg:city":"Campa\u00e7o De Arriba",
    "sg:orig_category":"Centros Empresariales",
    "sg:phone":"+34 986 87 70 02",
    "sg:postcode":"36157",
    "sg:province":"Pontevedra",
    "sg:website":"www.tasoga.com",
    "wof:name":"Tasoga S.l.",
    "wof:placetype":"venue"
},
  "geometry": {"coordinates":[-8.6582126617,42.4889144897],"type":"Point"}
}