{
  "type": "Feature",
  "properties": {
    "addr:full":"Pase San Cristobal, 14 Almu\u00f1ecar Granada 18690",
    "addr:housenumber":"14",
    "addr:postcode":"18690",
    "addr:street":"San Cristobal",
    "iso:country":"ES",
    "sg:address":"Pase San Cristobal, 14",
    "sg:city":"Almu\u00f1ecar",
    "sg:orig_category":"Inmobiliaria (agencias)",
    "sg:phone":"+34 958 63 97 33",
    "sg:postcode":"18690",
    "sg:province":"Granada",
    "wof:name":"Rafco Inmuebles",
    "wof:placetype":"venue"
},
  "geometry": {"coordinates":[-3.7040250301,36.7368774414],"type":"Point"}
}