{
  "type": "Feature",
  "properties": {
    "iso:country":"ES",
    "sg:address":"Calle de Toneleros, 33",
    "sg:city":"Miguelturra",
    "sg:orig_category":"Empresas De Carpinter\u00cda Met\u00c1lica",
    "sg:phone":"+34 926 27 20 51",
    "sg:postcode":"13170",
    "sg:province":"Ciudad Real",
    "wof:name":"Metalicas Bernardo S.l.",
    "wof:placetype":"venue"
},
  "geometry": {"coordinates":[-3.9007809162,38.9725227356],"type":"Point"}
}