{
  "type": "Feature",
  "properties": {
    "iso:country":"ES",
    "sg:address":"Calle de Marismas De Galindo, 7",
    "sg:city":"Sestao",
    "sg:orig_category":"Maquinaria Para Industrias Diversas",
    "sg:phone":"+34 944 72 42 49",
    "sg:postcode":"48910",
    "sg:province":"Vizcaya",
    "wof:name":"Sus Talleres 2003 S.l.",
    "wof:placetype":"venue"
},
  "geometry": {"coordinates":[-2.9875400066,43.3055839539],"type":"Point"}
}