{
  "type": "Feature",
  "properties": {
    "iso:country":"ES",
    "sg:address":"Avda Aeroporto, 92",
    "sg:city":"Vigo",
    "sg:orig_category":"Suministros Para Hoteles",
    "sg:phone":"+34 986 28 82 84",
    "sg:postcode":"36206",
    "sg:province":"Pontevedra",
    "wof:name":"Gabriel Salvador Moreno Pascual S.l.",
    "wof:placetype":"venue"
},
  "geometry": {"coordinates":[-8.6952781677,42.2343101501],"type":"Point"}
}