{
  "type": "Feature",
  "properties": {
    "iso:country":"ES",
    "sg:address":"Av Onze De Setembre (de L'), 23",
    "sg:city":"Montornes Centre",
    "sg:orig_category":"Partidos Pol\u00cdticos",
    "sg:phone":"+34 935 72 00 70",
    "sg:postcode":"08170",
    "sg:province":"Barcelona",
    "wof:name":"Convergencia Democratica De Catalunya",
    "wof:placetype":"venue"
},
  "geometry": {"coordinates":[2.2644779682,41.5432701111],"type":"Point"}
}