{
  "type": "Feature",
  "properties": {
    "addr:full":"Plaz Cortes, 2 Tafalla Navarra 31300",
    "addr:housenumber":"2",
    "addr:postcode":"31300",
    "addr:street":"Plaz Cortes",
    "iso:country":"ES",
    "sg:address":"Plaz Cortes, 2",
    "sg:city":"Tafalla",
    "sg:orig_category":"Zapatos (al Por Menor)",
    "sg:phone":"+34 948 70 02 28",
    "sg:postcode":"31300",
    "sg:province":"Navarra",
    "wof:name":"Calvo Varona Aurora",
    "wof:placetype":"venue"
},
  "geometry": {"coordinates":[-1.6751769781,42.5264205933],"type":"Point"}
}