{
  "type": "Feature",
  "properties": {
    "iso:country":"ES",
    "sg:address":"L. Vega, 7",
    "sg:city":"Fuente Obejuna",
    "sg:orig_category":"Caf\u00c9s, Bares, Cervecer\u00cdas",
    "sg:phone":"+34 957 58 50 25",
    "sg:postcode":"14290",
    "sg:province":"C\u00f3rdoba",
    "wof:name":"Rubio Ortiz Antonio Manuel",
    "wof:placetype":"venue"
},
  "geometry": {"coordinates":[-5.4202508926,38.2668571472],"type":"Point"}
}