{
  "type": "Feature",
  "properties": {
    "iso:country":"ES",
    "sg:address":"Carrer de Cala Agulla, 3",
    "sg:city":"Palma",
    "sg:orig_category":"Cl\u00cdnicas Dentales",
    "sg:phone":"+34 971 47 33 41",
    "sg:postcode":"07009",
    "sg:province":"Islas Baleares",
    "wof:name":"Clinica Dental Son Cladera C.b.",
    "wof:placetype":"venue"
},
  "geometry": {"coordinates":[2.6788749695,39.5962181091],"type":"Point"}
}