{
  "type": "Feature",
  "properties": {
    "iso:country":"ES",
    "sg:address":"Calle de Arias Montano, 1",
    "sg:city":"Alcala Henares",
    "sg:orig_category":"Inform\u00c1tica: Consultores",
    "sg:phone":"+34 918 82 31 86",
    "sg:postcode":"28805",
    "sg:province":"Madrid",
    "wof:name":"Ntceo Consultores S.a.",
    "wof:placetype":"venue"
},
  "geometry": {"coordinates":[-3.3595628738,40.4891204834],"type":"Point"}
}