{
  "type": "Feature",
  "properties": {
    "addr:full":"Aluminio, 4 Sevilla Sevilla 41007",
    "addr:housenumber":"4",
    "addr:postcode":"41007",
    "addr:street":"Aluminio",
    "iso:country":"ES",
    "sg:address":"Aluminio, 4",
    "sg:city":"Sevilla",
    "sg:orig_category":"Suministros Y Materiales Industriales",
    "sg:phone":"+34 954 43 20 21",
    "sg:postcode":"41007",
    "sg:province":"Sevilla",
    "sg:website":"www.graserva.com",
    "wof:name":"Dana Automocion S. A.",
    "wof:placetype":"venue"
},
  "geometry": {"coordinates":[-5.9565792084,37.4104309082],"type":"Point"}
}