{
  "type": "Feature",
  "properties": {
    "iso:country":"ES",
    "sg:address":"Kontseju Zarra Kalea, 9",
    "sg:city":"Usurbil",
    "sg:classifiers":[
        {
            "category":"Taxi",
            "type":"Transportation"
        }
    ],
    "sg:phone":"+34 943 36 21 78",
    "sg:postcode":"20170",
    "sg:province":"Guip\u00f9zcoa",
    "wof:name":"Tolarechipi Roteta Antonio",
    "wof:placetype":"venue"
},
  "geometry": {"coordinates":[-2.0539140701,43.2733459473],"type":"Point"}
}