{
  "type": "Feature",
  "properties": {
    "iso:country":"ES",
    "sg:address":"Ctra Solana (de La), 15",
    "sg:city":"Manzanares",
    "sg:orig_category":"Farmacias",
    "sg:phone":"+34 926 61 48 19",
    "sg:postcode":"13200",
    "sg:province":"Ciudad Real",
    "wof:name":"Galiani Leal Rosa Maria",
    "wof:placetype":"venue"
},
  "geometry": {"coordinates":[-3.3674829006,39.0016479492],"type":"Point"}
}