{
  "type": "Feature",
  "properties": {
    "iso:country":"ES",
    "sg:address":"Pase Duque De Mandas, 42",
    "sg:city":"Donostia-san Sebastian",
    "sg:orig_category":"Administradores De Bienes Y Delegados De Comunidades De Propietarios",
    "sg:phone":"+34 943 27 08 16",
    "sg:postcode":"20012",
    "sg:province":"Guip\u00f9zcoa",
    "wof:name":"Administracion De Fincas, Ana Pereda Fernandez",
    "wof:placetype":"venue"
},
  "geometry": {"coordinates":[-1.9746299982,43.3192977905],"type":"Point"}
}