{
  "type": "Feature",
  "properties": {
    "addr:full":"Carr Valeri Serra, 2 Bellpuig Lleida 25250",
    "addr:housenumber":"2",
    "addr:postcode":"25250",
    "addr:street":"Carr Valeri Serra",
    "iso:country":"ES",
    "sg:address":"Carr Valeri Serra, 2",
    "sg:city":"Bellpuig",
    "sg:orig_category":"Fabricaci\u00d3n De Muebles",
    "sg:phone":"+34 973 32 03 12",
    "sg:postcode":"25250",
    "sg:province":"Lleida",
    "wof:name":"Mobles Tudela S.l.",
    "wof:placetype":"venue"
},
  "geometry": {"coordinates":[1.0107899904,41.6270828247],"type":"Point"}
}