{
  "type": "Feature",
  "properties": {
    "iso:country":"ES",
    "sg:address":"Urb Vista Paloma, S/n",
    "sg:city":"Tarifa",
    "sg:orig_category":"Alimentaci\u00d3n Animal (fabricaci\u00d3n, Al Por Mayor)",
    "sg:phone":"+34 956 68 02 42",
    "sg:postcode":"11380",
    "sg:province":"C\u00e1diz",
    "wof:name":"Jimenez Estevez Leandro",
    "wof:placetype":"venue"
},
  "geometry": {"coordinates":[-5.6063737869,36.0190048218],"type":"Point"}
}