{
  "type": "Feature",
  "properties": {
    "addr:full":"Calle de Doctor Molina, 94 Abaran Murcia 30550",
    "addr:housenumber":"94",
    "addr:postcode":"30550",
    "addr:street":"Calle De Doctor Molina",
    "iso:country":"ES",
    "sg:address":"Calle de Doctor Molina, 94",
    "sg:city":"Abaran",
    "sg:orig_category":"Panader\u00cdas, Panader\u00cdas",
    "sg:phone":"+34 968 77 00 61",
    "sg:postcode":"30550",
    "sg:province":"Murcia",
    "wof:name":"Gomez Gomez Joaquin",
    "wof:placetype":"venue"
},
  "geometry": {"coordinates":[-1.3990314007,38.205165863],"type":"Point"}
}