{
  "type": "Feature",
  "properties": {
    "addr:full":"Carr Rutlla, 43 Girona Girona 17002",
    "addr:housenumber":"43",
    "addr:postcode":"17002",
    "addr:street":"Carr Rutlla",
    "iso:country":"ES",
    "sg:address":"Carr Rutlla, 43",
    "sg:city":"Girona",
    "sg:orig_category":"Arquitectos",
    "sg:phone":"+34 972 20 55 36",
    "sg:postcode":"17002",
    "sg:province":"Girona",
    "wof:name":"Casellas Figa Marta",
    "wof:placetype":"venue"
},
  "geometry": {"coordinates":[2.8229699135,41.9765892029],"type":"Point"}
}