{
  "type": "Feature",
  "properties": {
    "iso:country":"ES",
    "sg:address":"Calle de Gil De Jasa, 4",
    "sg:city":"Zaragoza",
    "sg:orig_category":"Doctores En Medicina",
    "sg:phone":"+34 976 22 02 03",
    "sg:postcode":"50006",
    "sg:province":"Zaragoza",
    "wof:name":"Marin Salcedo Juan Carlos",
    "wof:placetype":"venue"
},
  "geometry": {"coordinates":[-0.8867059946,41.6446113586],"type":"Point"}
}