{
  "type": "Feature",
  "properties": {
    "iso:country":"ES",
    "sg:address":"Calle de Juntas Generales, 2",
    "sg:city":"San Vicente De Barakaldo",
    "sg:orig_category":"Reposter\u00cdas",
    "sg:phone":"+34 944 37 36 97",
    "sg:postcode":"48901",
    "sg:province":"Vizcaya",
    "wof:name":"San Telmo Panificables 2001 S.l.",
    "wof:placetype":"venue"
},
  "geometry": {"coordinates":[-2.9869000912,43.2974243164],"type":"Point"}
}