{
  "type": "Feature",
  "properties": {
    "iso:country":"ES",
    "sg:address":"Rua Placer (do), 77",
    "sg:city":"Pazos",
    "sg:orig_category":"Promotores Constructores",
    "sg:phone":"+34 988 41 36 64",
    "sg:postcode":"32619",
    "sg:province":"Ourense",
    "wof:name":"Salgado Sanchez Jacinto",
    "wof:placetype":"venue"
},
  "geometry": {"coordinates":[-7.4539890289,41.9380149841],"type":"Point"}
}