{
  "type": "Feature",
  "properties": {
    "iso:country":"ES",
    "sg:address":"Calle de Comandante Ernesto 'che' Guevara, 1",
    "sg:city":"Getafe",
    "sg:orig_category":"M\u00c9dicos: Ginecolog\u00cda Y Obstetricia",
    "sg:phone":"+34 916 83 65 41",
    "sg:postcode":"28901",
    "sg:province":"Madrid",
    "wof:name":"Ginegetafe S.l.",
    "wof:placetype":"venue"
},
  "geometry": {"coordinates":[-3.7320845127,40.3062553406],"type":"Point"}
}