{
  "type": "Feature",
  "properties": {
    "iso:country":"ES",
    "sg:address":"Ctra Pinos Puente, Km. 0436,0",
    "sg:city":"Bobadilla",
    "sg:orig_category":"Comercio De Piezas De Recambio Y De Accesorios De Veh\u00cdculos, Veh\u00cdculos Industriales",
    "sg:phone":"+34 958 28 20 20",
    "sg:postcode":"18015",
    "sg:province":"Granada",
    "wof:name":"Luis Moleon S.l.",
    "wof:placetype":"venue"
},
  "geometry": {"coordinates":[-3.6230063438,37.1926651001],"type":"Point"}
}