{
  "type": "Feature",
  "properties": {
    "addr:full":"Avgd Del Cami Nou, 209 Xirivella Valencia 46950",
    "addr:housenumber":"209",
    "addr:postcode":"46950",
    "addr:street":"Nou",
    "iso:country":"ES",
    "sg:address":"Avgd Del Cami Nou, 209",
    "sg:city":"Xirivella",
    "sg:orig_category":"Cueros Y Pieles (al Por Mayor)",
    "sg:phone":"+34 963 79 17 22",
    "sg:postcode":"46950",
    "sg:province":"Valencia",
    "wof:name":"Curtidos Devis S.a.",
    "wof:placetype":"venue"
},
  "geometry": {"coordinates":[-0.4380910099,39.4626045227],"type":"Point"}
}