{
  "type": "Feature",
  "properties": {
    "iso:country":"ES",
    "sg:address":"Avda Zurriola De, 16",
    "sg:city":"Donostia-san Sebastian",
    "sg:orig_category":"Molduras, Junquillos, Listones Y Molduras Perforadas",
    "sg:phone":"+34 943 32 60 33",
    "sg:postcode":"20002",
    "sg:province":"Guip\u00f9zcoa",
    "wof:name":"Bar Ondarra Bat 16 Y 16 Bis S.l.",
    "wof:placetype":"venue"
},
  "geometry": {"coordinates":[-1.9771720171,43.3243560791],"type":"Point"}
}