{
  "type": "Feature",
  "properties": {
    "iso:country":"ES",
    "sg:address":"Carrer de Bruc, 126",
    "sg:city":"Manresa",
    "sg:orig_category":"Promotores Constructores",
    "sg:phone":"+34 938 72 47 02",
    "sg:postcode":"08241",
    "sg:province":"Barcelona",
    "wof:name":"Habitatges Torra S. L.",
    "wof:placetype":"venue"
},
  "geometry": {"coordinates":[1.8200399876,41.7258300781],"type":"Point"}
}