{
  "type": "Feature",
  "properties": {
    "iso:country":"ES",
    "sg:address":"Carrer de Concili De Trento, 47",
    "sg:city":"Barcelona",
    "sg:orig_category":"Periodistas Profesionales",
    "sg:phone":"+34 933 03 49 29",
    "sg:postcode":"08018",
    "sg:province":"Barcelona",
    "wof:name":"Wysocka  Eva",
    "wof:placetype":"venue"
},
  "geometry": {"coordinates":[2.1940009594,41.4125175476],"type":"Point"}
}