{
  "type": "Feature",
  "properties": {
    "addr:full":"Ctra. Casas Iba\u00f1ez, 3 Albacete Albacete 02006",
    "addr:housenumber":"3",
    "addr:postcode":"02006",
    "addr:street":"Ctra. Casas Iban\u0303Ez",
    "iso:country":"ES",
    "sg:address":"Ctra. Casas Iba\u00f1ez, 3",
    "sg:city":"Albacete",
    "sg:orig_category":"Reciclaje, Desguace De Veh\u00cdculos",
    "sg:phone":"+34 967 21 49 37",
    "sg:postcode":"02006",
    "sg:province":"Albacete",
    "wof:name":"Auto Desguace Los Faisanes S.l.",
    "wof:placetype":"venue"
},
  "geometry": {"coordinates":[-1.8665416241,39.0125617981],"type":"Point"}
}