{
  "type": "Feature",
  "properties": {
    "iso:country":"ES",
    "sg:address":"Avda Americas (las), 9",
    "sg:city":"Playa Americas",
    "sg:orig_category":"Ropa Para Se\u00d1oras (al Por Menor)",
    "sg:phone":"+34 922 78 75 67",
    "sg:postcode":"38660",
    "sg:province":"Santa Cruz De Tenerife",
    "wof:name":"Zara Espa\u00f1a S. A.",
    "wof:placetype":"venue"
},
  "geometry": {"coordinates":[-16.7304515839,28.0547847748],"type":"Point"}
}