{
  "type": "Feature",
  "properties": {
    "iso:country":"ES",
    "sg:address":"Ctra. Talavera, Km. 0135,0",
    "sg:city":"Montearagon",
    "sg:orig_category":"Distribuci\u00d3n De Petr\u00d3leo Y Derivados",
    "sg:phone":"+34 925 86 50 45",
    "sg:postcode":"45555",
    "sg:province":"Toledo",
    "wof:name":"Esteban S.l.",
    "wof:placetype":"venue"
},
  "geometry": {"coordinates":[-4.6330699921,39.9548797607],"type":"Point"}
}