{
  "type": "Feature",
  "properties": {
    "addr:full":"Av Mare Deu De Montserrat, 252 Barcelona Barcelona 08041",
    "addr:housenumber":"252",
    "addr:postcode":"08041",
    "addr:street":"Av Mare;De Montserrat",
    "iso:country":"ES",
    "sg:address":"Av Mare Deu De Montserrat, 252",
    "sg:city":"Barcelona",
    "sg:orig_category":"Alimentaci\u00d3n General (al Por Menor)",
    "sg:phone":"+34 934 55 22 50",
    "sg:postcode":"08041",
    "sg:province":"Barcelona",
    "wof:name":"Montse Y Susana Pamias, S.c.p.",
    "wof:placetype":"venue"
},
  "geometry": {"coordinates":[2.1752240658,41.4229011536],"type":"Point"}
}