{
  "type": "Feature",
  "properties": {
    "iso:country":"ES",
    "sg:address":"Av Coloma, 73",
    "sg:city":"Coloma",
    "sg:orig_category":"Teatro, Ballet, Danza (agrupaciones, Compa\u00d1\u00cdas)",
    "sg:phone":"+34 965 87 32 31",
    "sg:postcode":"03530",
    "sg:province":"Alicante",
    "wof:name":"Producciones Y Contrataciones Artisticas Racord S.l.",
    "wof:placetype":"venue"
},
  "geometry": {"coordinates":[-0.1213990003,38.594619751],"type":"Point"}
}