{
  "type": "Feature",
  "properties": {
    "iso:country":"ES",
    "sg:address":"Calle de Tartanga, 72",
    "sg:city":"Altzaga",
    "sg:orig_category":"Empresas De Carpinter\u00cda De Madera",
    "sg:phone":"+34 944 67 04 48",
    "sg:postcode":"48950",
    "sg:province":"Vizcaya",
    "wof:name":"Carpinteria La Union De Erandio S.l.",
    "wof:placetype":"venue"
},
  "geometry": {"coordinates":[-2.9780890942,43.3101882935],"type":"Point"}
}