{
  "type": "Feature",
  "properties": {
    "iso:country":"ES",
    "sg:address":"Calle de Torija, 8",
    "sg:city":"Madrid",
    "sg:orig_category":"Promotores Constructores",
    "sg:phone":"+34 915 59 65 99",
    "sg:postcode":"28013",
    "sg:province":"Madrid",
    "sg:website":"www.lobfre.com",
    "wof:name":"Lobfre Promocion Y Gestion S.l.",
    "wof:placetype":"venue"
},
  "geometry": {"coordinates":[-3.7099380493,40.4209098816],"type":"Point"}
}