{
  "type": "Feature",
  "properties": {
    "addr:full":"Calle de Delicias, 2 Zaragoza Zaragoza 50017",
    "addr:housenumber":"2",
    "addr:postcode":"50017",
    "addr:street":"Calle De Delicias",
    "iso:country":"ES",
    "sg:address":"Calle de Delicias, 2",
    "sg:city":"Zaragoza",
    "sg:orig_category":"Asesor\u00cda Fiscal Y Jur\u00cddica",
    "sg:phone":"+34 976 53 21 05",
    "sg:postcode":"50017",
    "sg:province":"Zaragoza",
    "sg:website":"www.arages.com",
    "wof:name":"Servicio De Asesoramiento Y Gestion Arages S.l.",
    "wof:placetype":"venue"
},
  "geometry": {"coordinates":[-0.9061440229,41.652885437],"type":"Point"}
}