{
  "type": "Feature",
  "properties": {
    "addr:full":"Carr Joan D'austria, 36 Badalona Barcelona 08915",
    "addr:housenumber":"36",
    "addr:postcode":"08915",
    "addr:street":"Carr Joan D'Austria",
    "iso:country":"ES",
    "sg:address":"Carr Joan D'austria, 36",
    "sg:city":"Badalona",
    "sg:classifiers":[
        {
            "category":"Autos & Motor Vehicles",
            "subcategory":"Automobile Sales",
            "type":"Retail Goods"
        }
    ],
    "sg:phone":"+34 934 65 28 97",
    "sg:postcode":"08915",
    "sg:province":"Barcelona",
    "wof:name":"Escuela De Conductores Montecarlo S.l.",
    "wof:placetype":"venue"
},
  "geometry": {"coordinates":[2.249101162,41.4639930725],"type":"Point"}
}