{
  "type": "Feature",
  "properties": {
    "addr:full":"Carr Marquesa De Montortal, De La, 43 Carcaixent Valencia 46740",
    "addr:housenumber":"43",
    "addr:postcode":"46740",
    "addr:street":"Carr Marquesa De Montortal De La",
    "iso:country":"ES",
    "sg:address":"Carr Marquesa De Montortal, De La, 43",
    "sg:city":"Carcaixent",
    "sg:orig_category":"Contenedores Para Transporte De Mercanc\u00cdas",
    "sg:phone":"+34 962 43 07 74",
    "sg:postcode":"46740",
    "sg:province":"Valencia",
    "wof:name":"Richart Lloret Jose",
    "wof:placetype":"venue"
},
  "geometry": {"coordinates":[-0.4502730072,39.1249084473],"type":"Point"}
}