{
  "type": "Feature",
  "properties": {
    "iso:country":"ES",
    "sg:address":"Fuenterroble, 16",
    "sg:city":"Guijuelo",
    "sg:orig_category":"Fabrica De Charcuter\u00cda",
    "sg:phone":"+34 923 58 20 43",
    "sg:postcode":"37770",
    "sg:province":"Salamanca",
    "wof:name":"Martin Herrero Marcial",
    "wof:placetype":"venue"
},
  "geometry": {"coordinates":[-5.6862330437,40.5553436279],"type":"Point"}
}