{
  "type": "Feature",
  "properties": {
    "addr:full":"Calle de Mayor, 26 Belones Murcia 30385",
    "addr:housenumber":"26",
    "addr:postcode":"30385",
    "addr:street":"Calle De Mayor",
    "iso:country":"ES",
    "sg:address":"Calle de Mayor, 26",
    "sg:city":"Belones",
    "sg:orig_category":"Aparatos, Sistemas De Tele",
    "sg:phone":"+34 968 13 77 30",
    "sg:postcode":"30385",
    "sg:province":"Murcia",
    "wof:name":"Use It Or Lose It Security Systems",
    "wof:placetype":"venue"
},
  "geometry": {"coordinates":[-0.7769938707,37.6227722168],"type":"Point"}
}