{
  "type": "Feature",
  "properties": {
    "iso:country":"ES",
    "sg:address":"Plaz Santa Adela, S/n",
    "sg:city":"Huescar",
    "sg:orig_category":"Molduras, Junquillos, Listones Y Molduras Perforadas",
    "sg:phone":"+34 958 74 02 07",
    "sg:postcode":"18830",
    "sg:province":"Granada",
    "wof:name":"Iba\u00f1ez Gomez Pedro Tomas",
    "wof:placetype":"venue"
},
  "geometry": {"coordinates":[-2.5432739258,37.8076705933],"type":"Point"}
}