{
  "type": "Feature",
  "properties": {
    "iso:country":"ES",
    "sg:address":"Calle de Sol, 32",
    "sg:city":"Sevilla",
    "sg:orig_category":"Transportes Por Carretera: Lotes Completos, Mercanc\u00cdas Diversas",
    "sg:phone":"+34 954 21 50 75",
    "sg:postcode":"41003",
    "sg:province":"Sevilla",
    "wof:name":"Lopez Diaz Maria Luisa",
    "wof:placetype":"venue"
},
  "geometry": {"coordinates":[-5.9868988991,37.3942985535],"type":"Point"}
}