{
  "type": "Feature",
  "properties": {
    "iso:country":"ES",
    "sg:address":"Ctra Basurtu-kastrexana, 7",
    "sg:city":"Bilbao",
    "sg:orig_category":"Muebles, Minoristas",
    "sg:phone":"+34 944 27 54 54",
    "sg:postcode":"48002",
    "sg:province":"Vizcaya",
    "wof:name":"Bengoa Garcia Santiago",
    "wof:placetype":"venue"
},
  "geometry": {"coordinates":[-2.9515318871,43.2586288452],"type":"Point"}
}