{
  "type": "Feature",
  "properties": {
    "addr:full":"Carrer de Mas Casanovas, 41 Barcelona Barcelona 08025",
    "addr:housenumber":"41",
    "addr:postcode":"08025",
    "addr:street":"Carrer De Mas Casanovas",
    "iso:country":"ES",
    "sg:address":"Carrer de Mas Casanovas, 41",
    "sg:city":"Barcelona",
    "sg:orig_category":"Agencias Y Asesores De Publicidad",
    "sg:phone":"+34 934 56 42 00",
    "sg:postcode":"08025",
    "sg:province":"Barcelona",
    "wof:name":"Holo-rawas Al-barudi Mohamad Kheir",
    "wof:placetype":"venue"
},
  "geometry": {"coordinates":[2.1696610451,41.4125213623],"type":"Point"}
}