{
  "type": "Feature",
  "properties": {
    "addr:full":"Calle de Francisco Pizarro, 35 Puebla Calzada Badajoz 06490",
    "addr:housenumber":"35",
    "addr:postcode":"06490",
    "addr:street":"Calle De Francisco Pizarro;Calzada Badajoz",
    "iso:country":"ES",
    "sg:address":"Calle de Francisco Pizarro, 35",
    "sg:city":"Puebla Calzada",
    "sg:orig_category":"Motocicletas (agentes, Concesionarios)",
    "sg:phone":"+34 924 45 69 95",
    "sg:postcode":"06490",
    "sg:province":"Badajoz",
    "wof:name":"Motos Morales S.a.l.",
    "wof:placetype":"venue"
},
  "geometry": {"coordinates":[-6.6219730377,38.8969802856],"type":"Point"}
}