{
  "type": "Feature",
  "properties": {
    "addr:full":"Calle de Lucio Del Valle, 17 Madrid Madrid 28003",
    "addr:housenumber":"17",
    "addr:postcode":"madrid;28003",
    "addr:street":"Calle De Lucio Del Valle",
    "iso:country":"ES",
    "sg:address":"Calle de Lucio Del Valle, 17",
    "sg:city":"Madrid",
    "sg:orig_category":"Asesor\u00cda Sobre Comunicaci\u00d3n De Empresas",
    "sg:phone":"+34 915 33 27 08",
    "sg:postcode":"28003",
    "sg:province":"Madrid",
    "wof:name":"Servicios Integrales Trama S.l.",
    "wof:placetype":"venue"
},
  "geometry": {"coordinates":[-3.7090919018,40.4399604797],"type":"Point"}
}