{
  "type": "Feature",
  "properties": {
    "addr:full":"Carrer de Plini El Vell, 7 Sabadell Barcelona 08206",
    "addr:housenumber":"7",
    "addr:postcode":"08206",
    "addr:street":"Carrer De Plini El Vell",
    "iso:country":"ES",
    "sg:address":"Carrer de Plini El Vell, 7",
    "sg:city":"Sabadell",
    "sg:orig_category":"Fabricaci\u00d3n, Importaci\u00d3n De L\u00c1mparas Y Bombillas",
    "sg:phone":"+34 937 24 21 17",
    "sg:postcode":"08206",
    "sg:province":"Barcelona",
    "wof:name":"Lampisteria Vi\u00f1als S.l.",
    "wof:placetype":"venue"
},
  "geometry": {"coordinates":[2.0855920315,41.5580291748],"type":"Point"}
}