{
  "type": "Feature",
  "properties": {
    "addr:full":"Carrer de Conca De Barbera, 10 Poligon Industrial Pla De La Bruguera Barcelona 08211",
    "addr:housenumber":"10",
    "addr:postcode":"08211",
    "addr:street":"Carrer De Conca De Barbera;Industrial;De",
    "iso:country":"ES",
    "sg:address":"Carrer de Conca De Barbera, 10",
    "sg:city":"Poligon Industrial Pla De La Bruguera",
    "sg:orig_category":"Contenedores (mercanc\u00cdas)",
    "sg:phone":"+34 937 14 36 63",
    "sg:postcode":"08211",
    "sg:province":"Barcelona",
    "wof:name":"Trans Casting Events S.l.",
    "wof:placetype":"venue"
},
  "geometry": {"coordinates":[2.0857300758,41.6151885986],"type":"Point"}
}