{
  "type": "Feature",
  "properties": {
    "addr:full":"Calle de Doctor Araez Pacheco, 2 Almeria Almer\u00eda 04004",
    "addr:housenumber":"2",
    "addr:postcode":"04004",
    "addr:street":"Calle De Doctor Araez Pacheco",
    "iso:country":"ES",
    "sg:address":"Calle de Doctor Araez Pacheco, 2",
    "sg:city":"Almeria",
    "sg:orig_category":"Sindicatos Y Colegios Profesionales",
    "sg:phone":"+34 950 26 67 23",
    "sg:postcode":"04004",
    "sg:province":"Almer\u00eda",
    "wof:name":"Union Profesional De Armadores Y Productores De Pesca De Almeria",
    "wof:placetype":"venue"
},
  "geometry": {"coordinates":[-2.4600589275,36.8345069885],"type":"Point"}
}