{
  "type": "Feature",
  "properties": {
    "iso:country":"ES",
    "sg:address":"Carr Castell De Morvedre, 8",
    "sg:city":"Pu\u00e7ol",
    "sg:orig_category":"Organizaciones Internacionales",
    "sg:phone":"+34 961 42 29 20",
    "sg:postcode":"46530",
    "sg:province":"Valencia",
    "wof:name":"Asociacion Valenciana De Voluntarios En Emergencias Sanitarias",
    "wof:placetype":"venue"
},
  "geometry": {"coordinates":[-0.3060646951,39.6192588806],"type":"Point"}
}