{
  "type": "Feature",
  "properties": {
    "addr:full":"Urb Ciudad Quesada, 20 Ciudad Quesada Alicante 03170",
    "addr:housenumber":"20",
    "addr:postcode":"03170",
    "addr:street":"Urb Ciudad Quesada",
    "iso:country":"ES",
    "sg:address":"Urb Ciudad Quesada, 20",
    "sg:city":"Ciudad Quesada",
    "sg:orig_category":"Promotores Constructores",
    "sg:phone":"+34 966 71 97 75",
    "sg:postcode":"03170",
    "sg:province":"Alicante",
    "wof:name":"Belen Quesada S.a.",
    "wof:placetype":"venue"
},
  "geometry": {"coordinates":[-0.7292140126,38.0850296021],"type":"Point"}
}