{
  "type": "Feature",
  "properties": {
    "iso:country":"ES",
    "sg:address":"Calle de San Isidro, 2",
    "sg:city":"Badajoz",
    "sg:orig_category":"Asesor\u00cdas Y Estudios Financieros",
    "sg:phone":"+34 924 24 11 76",
    "sg:postcode":"06004",
    "sg:province":"Badajoz",
    "wof:name":"Nuevas Importaciones S.a.",
    "wof:placetype":"venue"
},
  "geometry": {"coordinates":[-6.9754629135,38.8716316223],"type":"Point"}
}