{
  "type": "Feature",
  "properties": {
    "addr:full":"Avda Pirineos, 73 Barbastro Huesca 22300",
    "addr:housenumber":"73",
    "addr:postcode":"22300",
    "addr:street":"Avda Pirineos",
    "iso:country":"ES",
    "sg:address":"Avda Pirineos, 73",
    "sg:city":"Barbastro",
    "sg:orig_category":"Comercio De Piezas De Recambio Y De Accesorios De Veh\u00cdculos, Veh\u00cdculos Industriales",
    "sg:phone":"+34 974 31 50 00",
    "sg:postcode":"22300",
    "sg:province":"Huesca",
    "wof:name":"Recambios Gran Via S. A.",
    "wof:placetype":"venue"
},
  "geometry": {"coordinates":[0.1361940056,42.043586731],"type":"Point"}
}