{
  "type": "Feature",
  "properties": {
    "iso:country":"ES",
    "sg:address":"Calle de San Pelayo, 31",
    "sg:city":"Cangas Onis",
    "sg:orig_category":"Asociaciones Y Clubs Deportivos",
    "sg:phone":"+34 985 94 70 61",
    "sg:postcode":"33550",
    "sg:province":"Asturias",
    "wof:name":"Fernandez Batalla Maria Isabel",
    "wof:placetype":"venue"
},
  "geometry": {"coordinates":[-5.1300587654,43.3499717712],"type":"Point"}
}