{
  "type": "Feature",
  "properties": {
    "iso:country":"ES",
    "sg:address":"Av Segarra, 45",
    "sg:city":"Torrellano",
    "sg:orig_category":"Tapicer\u00cdas",
    "sg:phone":"+34 965 68 02 69",
    "sg:postcode":"03320",
    "sg:province":"Alicante",
    "wof:name":"Velasco Valdivieso Robustiano",
    "wof:placetype":"venue"
},
  "geometry": {"coordinates":[-0.5859190226,38.2931442261],"type":"Point"}
}