{
  "type": "Feature",
  "properties": {
    "addr:full":"Cjon De La Parra, 9 Alhama Granada Granada 18120",
    "addr:housenumber":"9",
    "addr:postcode":"18120",
    "addr:street":"Cjon De La Parra",
    "iso:country":"ES",
    "sg:address":"Cjon De La Parra, 9",
    "sg:city":"Alhama Granada",
    "sg:orig_category":"Art\u00cdculos Funerarios (al Por Menor)",
    "sg:phone":"+34 958 36 05 84",
    "sg:postcode":"18120",
    "sg:province":"Granada",
    "wof:name":"Velasco Martin Jorge",
    "wof:placetype":"venue"
},
  "geometry": {"coordinates":[-3.9891879559,37.0013084412],"type":"Point"}
}