{
  "type": "Feature",
  "properties": {
    "iso:country":"ES",
    "sg:address":"Avda. Adelfas, 7",
    "sg:city":"Matalasca\u00f1as",
    "sg:orig_category":"Cajas De Ahorro",
    "sg:phone":"+34 959 44 98 12",
    "sg:postcode":"21760",
    "sg:province":"Huelva",
    "wof:name":"Monte De Piedad Y Caja De Ahorros De Huelva Y Sevilla",
    "wof:placetype":"venue"
},
  "geometry": {"coordinates":[-6.5640540123,37.0086250305],"type":"Point"}
}