{
  "type": "Feature",
  "properties": {
    "iso:country":"ES",
    "sg:address":"Avda Europa (de), 10",
    "sg:city":"Jerez De La Frontera",
    "sg:orig_category":"Material Y Herramientas Agr\u00cdcolas",
    "sg:phone":"+34 956 18 05 08",
    "sg:postcode":"11405",
    "sg:province":"C\u00e1diz",
    "wof:name":"Recambios Agricolas Jerez S.l.",
    "wof:placetype":"venue"
},
  "geometry": {"coordinates":[-6.1201019287,36.6961555481],"type":"Point"}
}