{
  "type": "Feature",
  "properties": {
    "iso:country":"ES",
    "sg:address":"Avda Jose Antonio, 10",
    "sg:city":"Orotava",
    "sg:orig_category":"Bazares, Art\u00cdculos De Limpieza Y De Cocina (al Por Menor)",
    "sg:phone":"+34 922 33 09 98",
    "sg:postcode":"38300",
    "sg:province":"Santa Cruz De Tenerife",
    "wof:name":"Sanchez Garcia Milagros Herminia",
    "wof:placetype":"venue"
},
  "geometry": {"coordinates":[-16.5219421387,28.3918380737],"type":"Point"}
}