{
  "type": "Feature",
  "properties": {
    "iso:country":"ES",
    "sg:address":"Calle de Luna (de La), 5",
    "sg:city":"Manzanares",
    "sg:orig_category":"Frutas Y Legumbres Frescas (al Por Mayor)",
    "sg:phone":"+34 926 61 04 11",
    "sg:postcode":"13200",
    "sg:province":"Ciudad Real",
    "wof:name":"Frutas Guillen S. L.",
    "wof:placetype":"venue"
},
  "geometry": {"coordinates":[-3.3702499866,39.0020828247],"type":"Point"}
}