{
  "type": "Feature",
  "properties": {
    "addr:full":"Carrer de Esglesia, 2 S. Adria Besos Barcelona 08930",
    "addr:housenumber":"2",
    "addr:postcode":"08930",
    "addr:street":"Carrer De Esglesia;Barcelona",
    "iso:country":"ES",
    "sg:address":"Carrer de Esglesia, 2",
    "sg:city":"S. Adria Besos",
    "sg:orig_category":"Molduras, Junquillos, Listones Y Molduras Perforadas",
    "sg:phone":"+34 934 62 06 40",
    "sg:postcode":"08930",
    "sg:province":"Barcelona",
    "wof:name":"Ping Chen Jian",
    "wof:placetype":"venue"
},
  "geometry": {"coordinates":[2.2154040337,41.4328346252],"type":"Point"}
}