{
  "type": "Feature",
  "properties": {
    "addr:full":"Calle de Hurtado De Amezaga, 20 Bilbao Vizcaya 48008",
    "addr:housenumber":"20",
    "addr:postcode":"48008",
    "addr:street":"Calle De Hurtado De Amezaga",
    "iso:country":"ES",
    "sg:address":"Calle de Hurtado De Amezaga, 20",
    "sg:city":"Bilbao",
    "sg:orig_category":"Empleados",
    "sg:phone":"+34 944 15 72 31",
    "sg:postcode":"48008",
    "sg:province":"Vizcaya",
    "wof:name":"Sertebrok, S.l. E.t.t.",
    "wof:placetype":"venue"
},
  "geometry": {"coordinates":[-2.9302060604,43.2596549988],"type":"Point"}
}