{
  "type": "Feature",
  "properties": {
    "iso:country":"ES",
    "sg:address":"Calle de Vergara, 5",
    "sg:city":"Salamanca",
    "sg:orig_category":"Peluqueros: De Se\u00d1oras",
    "sg:phone":"+34 923 12 43 61",
    "sg:postcode":"37003",
    "sg:province":"Salamanca",
    "wof:name":"Lopez Benito Lucia",
    "wof:placetype":"venue"
},
  "geometry": {"coordinates":[-5.6541118622,40.9644470215],"type":"Point"}
}