{
  "type": "Feature",
  "properties": {
    "addr:full":"Ctra Ribes, 82 Figaro Barcelona 08590",
    "addr:housenumber":"82",
    "addr:postcode":"08590",
    "addr:street":"Ctra Ribes;Barcelona",
    "iso:country":"ES",
    "sg:address":"Ctra Ribes, 82",
    "sg:city":"Figaro",
    "sg:orig_category":"Cajas De Ahorro",
    "sg:phone":"+34 938 42 90 80",
    "sg:postcode":"08590",
    "sg:province":"Barcelona",
    "wof:name":"Caixa D'estalvis Sabadell",
    "wof:placetype":"venue"
},
  "geometry": {"coordinates":[2.2730600834,41.7233009338],"type":"Point"}
}