{
  "type": "Feature",
  "properties": {
    "iso:country":"ES",
    "sg:address":"Calle de Caraba\u00d1a, 19",
    "sg:city":"Alcala Henares",
    "sg:orig_category":"Empresarios Y Productoras De Espect\u00c1culos",
    "sg:phone":"+34 918 80 22 00",
    "sg:postcode":"28806",
    "sg:province":"Madrid",
    "wof:name":"Multi Show S.l.",
    "wof:placetype":"venue"
},
  "geometry": {"coordinates":[-3.3653481007,40.4905471802],"type":"Point"}
}