{
  "type": "Feature",
  "properties": {
    "addr:full":"Calle de Jose Cremades, 13 Molina Segura Murcia 30500",
    "addr:housenumber":"13",
    "addr:postcode":"30500",
    "addr:street":"Calle De Jose Cremades",
    "iso:country":"ES",
    "sg:address":"Calle de Jose Cremades, 13",
    "sg:city":"Molina Segura",
    "sg:orig_category":"Aceros Inoxidables",
    "sg:phone":"+34 968 61 31 39",
    "sg:postcode":"30500",
    "sg:province":"Murcia",
    "wof:name":"Aceros Bergara S.a.",
    "wof:placetype":"venue"
},
  "geometry": {"coordinates":[-1.2154529095,38.068523407],"type":"Point"}
}