{
  "type": "Feature",
  "properties": {
    "iso:country":"ES",
    "sg:address":"Calle de Poeta Manuel Gongora, 5",
    "sg:city":"Granada",
    "sg:orig_category":"Art\u00cdculos De Regalo (al Por Menor)",
    "sg:phone":"+34 958 18 37 12",
    "sg:postcode":"18008",
    "sg:province":"Granada",
    "wof:name":"Libreria Papeleria Frama S.l.",
    "wof:placetype":"venue"
},
  "geometry": {"coordinates":[-3.5943849087,37.1659965515],"type":"Point"}
}