{
  "type": "Feature",
  "properties": {
    "addr:full":"Calle de General Mola, 6 Solares Cantabria 39710",
    "addr:housenumber":"6",
    "addr:postcode":"39710",
    "addr:street":"Calle De General Mola",
    "iso:country":"ES",
    "sg:address":"Calle de General Mola, 6",
    "sg:city":"Solares",
    "sg:classifiers":[
        {
            "category":"Autos & Motor Vehicles",
            "subcategory":"Automobile Sales",
            "type":"Retail Goods"
        }
    ],
    "sg:phone":"+34 942 52 09 24",
    "sg:postcode":"39710",
    "sg:province":"Cantabria",
    "wof:name":"Santamaria Fernandez Alberto Manuel",
    "wof:placetype":"venue"
},
  "geometry": {"coordinates":[-3.7385311127,43.3849601746],"type":"Point"}
}