{
  "type": "Feature",
  "properties": {
    "iso:country":"ES",
    "sg:address":"Carrer de Sant Elies, 8",
    "sg:city":"Palma",
    "sg:orig_category":"Reposter\u00cdas",
    "sg:phone":"+34 971 72 54 10",
    "sg:postcode":"07003",
    "sg:province":"Islas Baleares",
    "wof:name":"Ramis Poquet Damian",
    "wof:placetype":"venue"
},
  "geometry": {"coordinates":[2.650274992,39.5748405457],"type":"Point"}
}