{
  "type": "Feature",
  "properties": {
    "iso:country":"ES",
    "sg:address":"Plaz Doctor Marcos Escarihuela Y Conesa, 2",
    "sg:city":"Portugalete",
    "sg:orig_category":"Cl\u00cdnicas M\u00c9dicas",
    "sg:phone":"+34 944 93 56 03",
    "sg:postcode":"48920",
    "sg:province":"Vizcaya",
    "wof:name":"Centro Policlinico Portumedic, S.l.",
    "wof:placetype":"venue"
},
  "geometry": {"coordinates":[-3.0220069885,43.3197975159],"type":"Point"}
}