{
  "type": "Feature",
  "properties": {
    "iso:country":"ES",
    "sg:address":"Calle de Arroyo, 55",
    "sg:city":"Sevilla",
    "sg:orig_category":"Asesor\u00cdas Y Estudios Financieros",
    "sg:phone":"+34 954 42 04 56",
    "sg:postcode":"41003",
    "sg:province":"Sevilla",
    "wof:name":"Mendez Juanes Javier",
    "wof:placetype":"venue"
},
  "geometry": {"coordinates":[-5.9816904068,37.3945236206],"type":"Point"}
}