{
  "type": "Feature",
  "properties": {
    "iso:country":"ES",
    "sg:address":"Poli Industrial Insider, S/n",
    "sg:city":"Cartuja Baja",
    "sg:orig_category":"Maquinaria Para Industrias Diversas",
    "sg:phone":"+34 976 50 01 92",
    "sg:postcode":"50720",
    "sg:province":"Zaragoza",
    "wof:name":"Industrias Hersa S. A.",
    "wof:placetype":"venue"
},
  "geometry": {"coordinates":[-0.8263310194,41.6002998352],"type":"Point"}
}