{
  "type": "Feature",
  "properties": {
    "iso:country":"ES",
    "sg:address":"Calle de Feria (de La), 6",
    "sg:city":"Alcazares",
    "sg:orig_category":"Asociaciones Y Clubs Deportivos",
    "sg:phone":"+34 968 57 51 78",
    "sg:postcode":"30710",
    "sg:province":"Murcia",
    "wof:name":"Sevilla Garcia Manuel",
    "wof:placetype":"venue"
},
  "geometry": {"coordinates":[-0.8496710062,37.7391586304],"type":"Point"}
}