{
  "type": "Feature",
  "properties": {
    "iso:country":"ES",
    "sg:address":"Avda Constitucion, 22",
    "sg:city":"Malpartida Caceres",
    "sg:orig_category":"Asesor\u00cda Fiscal Y Jur\u00cddica",
    "sg:phone":"+34 927 27 56 05",
    "sg:postcode":"10910",
    "sg:province":"C\u00e1ceres",
    "wof:name":"Lopez Mallo Francisco Javier",
    "wof:placetype":"venue"
},
  "geometry": {"coordinates":[-6.505592823,39.4475517273],"type":"Point"}
}