{
  "type": "Feature",
  "properties": {
    "iso:country":"ES",
    "sg:address":"Mcdo Colon, 1",
    "sg:city":"Melilla",
    "sg:orig_category":"Ense\u00d1anza, Formaci\u00d3n Profesional: Aprendizaje",
    "sg:phone":"+34 952 68 21 80",
    "sg:postcode":"52003",
    "sg:province":"Melilla",
    "wof:name":"Ciudad Autonoma De Melilla",
    "wof:placetype":"venue"
},
  "geometry": {"coordinates":[-2.955919981,35.3033714294],"type":"Point"}
}