{
  "type": "Feature",
  "properties": {
    "addr:full":"Cmno Iglesia, 32 Coru\u00d1a La Coru\u00f1a 15009",
    "addr:housenumber":"32",
    "addr:postcode":"15009",
    "addr:street":"Cmno Iglesia;Corun\u0303A",
    "iso:country":"ES",
    "sg:address":"Cmno Iglesia, 32",
    "sg:city":"Coru\u00d1a",
    "sg:orig_category":"Librer\u00cdas",
    "sg:phone":"+34 981 13 57 39",
    "sg:postcode":"15009",
    "sg:province":"La Coru\u00f1a",
    "wof:name":"Fari\u00f1a Ponte Maria Angeles",
    "wof:placetype":"venue"
},
  "geometry": {"coordinates":[-8.4015493393,43.3485603333],"type":"Point"}
}