{
  "type": "Feature",
  "properties": {
    "iso:country":"ES",
    "sg:address":"Carr Pompeu Fabra, 17",
    "sg:city":"Vidreres",
    "sg:orig_category":"Perfumer\u00cda (al Por Menor)",
    "sg:phone":"+34 972 85 02 04",
    "sg:postcode":"17411",
    "sg:province":"Girona",
    "wof:name":"Ferrer Prat Lluis",
    "wof:placetype":"venue"
},
  "geometry": {"coordinates":[2.7780499458,41.7895088196],"type":"Point"}
}