{
  "type": "Feature",
  "properties": {
    "addr:full":"Cra Valldemossa, 8 Palma Islas Baleares 07010",
    "addr:housenumber":"8",
    "addr:postcode":"07010",
    "addr:street":"Valldemossa",
    "iso:country":"ES",
    "sg:address":"Cra Valldemossa, 8",
    "sg:city":"Palma",
    "sg:orig_category":"Agencias Y Agentes Comerciales, Representantes",
    "sg:phone":"+34 971 20 00 03",
    "sg:postcode":"07010",
    "sg:province":"Islas Baleares",
    "wof:name":"Vall Mas Jorge",
    "wof:placetype":"venue"
},
  "geometry": {"coordinates":[2.6509239674,39.5864753723],"type":"Point"}
}