{
  "type": "Feature",
  "properties": {
    "addr:full":"Carr Julian Soldevilla, 1 Burjassot Valencia 46100",
    "addr:housenumber":"1",
    "addr:postcode":"46100",
    "addr:street":"Carr Julian Soldevilla",
    "iso:country":"ES",
    "sg:address":"Carr Julian Soldevilla, 1",
    "sg:city":"Burjassot",
    "sg:orig_category":"Plomeros",
    "sg:phone":"+34 963 63 87 40",
    "sg:postcode":"46100",
    "sg:province":"Valencia",
    "wof:name":"Fontaneria Antonio Giner S. L.",
    "wof:placetype":"venue"
},
  "geometry": {"coordinates":[-0.4126990139,39.5167350769],"type":"Point"}
}