{
  "type": "Feature",
  "properties": {
    "iso:country":"ES",
    "sg:address":"Calle de Hierbabuena, 50",
    "sg:city":"Madrid",
    "sg:orig_category":"Edici\u00d3n De Diarios, Revistas, Boletines",
    "sg:phone":"+34 915 70 79 20",
    "sg:postcode":"28039",
    "sg:province":"Madrid",
    "wof:name":"Editorial Teide S.a.",
    "wof:placetype":"venue"
},
  "geometry": {"coordinates":[-3.6998660564,40.4624557495],"type":"Point"}
}