{
  "type": "Feature",
  "properties": {
    "addr:full":"Calle de Galicia, 14 Fuenlabrada Madrid 28942",
    "addr:housenumber":"14",
    "addr:postcode":"28942",
    "addr:street":"Calle De Galicia",
    "iso:country":"ES",
    "sg:address":"Calle de Galicia, 14",
    "sg:city":"Fuenlabrada",
    "sg:orig_category":"Quincaller\u00cda (al Por Menor)",
    "sg:phone":"+34 916 07 78 67",
    "sg:postcode":"28942",
    "sg:province":"Madrid",
    "wof:name":"Molina Mencia Juan",
    "wof:placetype":"venue"
},
  "geometry": {"coordinates":[-3.8097569942,40.295337677],"type":"Point"}
}