{
  "type": "Feature",
  "properties": {
    "addr:full":"Calle de Chile, S/n Matas-pinar-monte Rozas Madrid 28290",
    "addr:housenumber":"s / n",
    "addr:postcode":"28290",
    "addr:street":"Calle De Chile",
    "iso:country":"ES",
    "sg:address":"Calle de Chile, S/n",
    "sg:city":"Matas-pinar-monte Rozas",
    "sg:orig_category":"Fabricaci\u00d3n De Acumuladores Y De Pilas El\u00c9ctricas",
    "sg:phone":"+34 902 36 01 13",
    "sg:postcode":"28290",
    "sg:province":"Madrid",
    "sg:website":"www.yuasa.com",
    "wof:name":"Yuasa Battery Iberia S.a.",
    "wof:placetype":"venue"
},
  "geometry": {"coordinates":[-3.9000189304,40.543548584],"type":"Point"}
}