{
  "type": "Feature",
  "properties": {
    "addr:full":"Calle de Mora\u00d1a, 26 Leganes Madrid 28915",
    "addr:housenumber":"26",
    "addr:postcode":"28915",
    "addr:street":"Calle De Moran\u0303A",
    "iso:country":"ES",
    "sg:address":"Calle de Mora\u00d1a, 26",
    "sg:city":"Leganes",
    "sg:orig_category":"Cervecer\u00cdas",
    "sg:phone":"+34 916 86 73 95",
    "sg:postcode":"28915",
    "sg:province":"Madrid",
    "wof:name":"Castro Jaenes Diego",
    "wof:placetype":"venue"
},
  "geometry": {"coordinates":[-3.7544710636,40.3318023682],"type":"Point"}
}