{
  "type": "Feature",
  "properties": {
    "iso:country":"ES",
    "sg:address":"Rbla Marquesa De Castellbell, 59",
    "sg:city":"Sant Feliu Llobregat",
    "sg:orig_category":"Agencias Y Asesores De Publicidad",
    "sg:phone":"+34 936 32 78 25",
    "sg:postcode":"08980",
    "sg:province":"Barcelona",
    "wof:name":"Llobregat Publicitat I Comunicacio",
    "wof:placetype":"venue"
},
  "geometry": {"coordinates":[2.0497560501,41.3838424683],"type":"Point"}
}