{
  "type": "Feature",
  "properties": {
    "iso:country":"ES",
    "sg:address":"Calle de Arevalo, S/n",
    "sg:city":"Ti\u00d1osillos",
    "sg:orig_category":"Molduras, Junquillos, Listones Y Molduras Perforadas",
    "sg:phone":"+34 920 26 70 23",
    "sg:postcode":"05165",
    "sg:province":"\u00c1vila",
    "wof:name":"Enrique Martin Francisca",
    "wof:placetype":"venue"
},
  "geometry": {"coordinates":[-4.7277374268,40.935005188],"type":"Point"}
}