{
  "type": "Feature",
  "properties": {
    "iso:country":"ES",
    "sg:address":"C/ Figueres, 24",
    "sg:city":"Vilafant",
    "sg:orig_category":"Fabricaci\u00d3n, Importaci\u00d3n De L\u00c1mparas Y Bombillas",
    "sg:phone":"+34 972 54 65 26",
    "sg:postcode":"17740",
    "sg:province":"Girona",
    "wof:name":"Cincuenta Y Una Mil Cincuenta Y Nueve S.l.",
    "wof:placetype":"venue"
},
  "geometry": {"coordinates":[2.93840909,42.247215271],"type":"Point"}
}