{
  "type": "Feature",
  "properties": {
    "iso:country":"ES",
    "sg:address":"Plaz Moron, 2",
    "sg:city":"Montehermoso",
    "sg:orig_category":"Empleado Administrativo",
    "sg:phone":"+34 927 43 04 95",
    "sg:postcode":"10810",
    "sg:province":"C\u00e1ceres",
    "wof:name":"Centro Asesor C.b.",
    "wof:placetype":"venue"
},
  "geometry": {"coordinates":[-6.3486399651,40.0886993408],"type":"Point"}
}