{
  "type": "Feature",
  "properties": {
    "iso:country":"ES",
    "sg:address":"Pase Pintor Rosales, 26",
    "sg:city":"Madrid",
    "sg:orig_category":"Camiser\u00cda Y Ropa Interior Masculina (al Por Menor)",
    "sg:phone":"+34 915 41 67 47",
    "sg:postcode":"28008",
    "sg:province":"Madrid",
    "wof:name":"Fernandez Rey Antonio",
    "wof:placetype":"venue"
},
  "geometry": {"coordinates":[-3.7193219662,40.4266586304],"type":"Point"}
}