{
  "type": "Feature",
  "properties": {
    "addr:full":"Calle de Carretera De Geria, 19 Simancas Valladolid 47130",
    "addr:housenumber":"19",
    "addr:postcode":"47130",
    "addr:street":"Calle De Carretera De Geria",
    "iso:country":"ES",
    "sg:address":"Calle de Carretera De Geria, 19",
    "sg:city":"Simancas",
    "sg:orig_category":"Materiales De Aislamiento T\u00c9rmico Y Ac\u00dastico",
    "sg:phone":"+34 983 59 01 49",
    "sg:postcode":"47130",
    "sg:province":"Valladolid",
    "wof:name":"Pastor Zurro Miguel Angel",
    "wof:placetype":"venue"
},
  "geometry": {"coordinates":[-4.8345952034,41.590839386],"type":"Point"}
}