{
  "type": "Feature",
  "properties": {
    "addr:full":"Calle de Noruega, S/n Alcala Henares Madrid 28802",
    "addr:housenumber":"s / n",
    "addr:postcode":"28802",
    "addr:street":"Calle De Noruega",
    "iso:country":"ES",
    "sg:address":"Calle de Noruega, S/n",
    "sg:city":"Alcala Henares",
    "sg:orig_category":"Empresas De Carpinter\u00cda De Madera",
    "sg:phone":"+34 918 82 81 05",
    "sg:postcode":"28802",
    "sg:province":"Madrid",
    "wof:name":"Arcomade Decoracion S.l",
    "wof:placetype":"venue"
},
  "geometry": {"coordinates":[-3.3828597069,40.4818763733],"type":"Point"}
}