{
  "type": "Feature",
  "properties": {
    "addr:full":"Ctra Madrid Toledo (1-3), Km. 0032,4 Illescas Toledo 45200",
    "addr:housenumber":"1-3",
    "addr:postcode":"45200",
    "addr:street":"Ctra Madrid Toledo;Km. 0032,4",
    "iso:country":"ES",
    "sg:address":"Ctra Madrid Toledo (1-3), Km. 0032,4",
    "sg:city":"Illescas",
    "sg:orig_category":"Centros Empresariales",
    "sg:phone":"+34 925 51 11 63",
    "sg:postcode":"45200",
    "sg:province":"Toledo",
    "wof:name":"Composystem S.a.",
    "wof:placetype":"venue"
},
  "geometry": {"coordinates":[-3.8594288826,40.1091804504],"type":"Point"}
}