{
  "type": "Feature",
  "properties": {
    "addr:full":"Calle de Prudencio Alvaro, 62 Madrid Madrid 28027",
    "addr:housenumber":"62",
    "addr:postcode":"madrid;28027",
    "addr:street":"Calle De Prudencio Alvaro",
    "iso:country":"ES",
    "sg:address":"Calle de Prudencio Alvaro, 62",
    "sg:city":"Madrid",
    "sg:orig_category":"Tapicer\u00cdas",
    "sg:phone":"+34 914 07 32 90",
    "sg:postcode":"28027",
    "sg:province":"Madrid",
    "wof:name":"Sepulveda Martin Camu\u00f1as Antonio",
    "wof:placetype":"venue"
},
  "geometry": {"coordinates":[-3.6426100731,40.4389953613],"type":"Point"}
}