{
  "type": "Feature",
  "properties": {
    "addr:full":"Carr Santa Victoria, 4 Breda Girona 17400",
    "addr:housenumber":"4",
    "addr:postcode":"17400",
    "addr:street":"Carr Santa Victoria",
    "iso:country":"ES",
    "sg:address":"Carr Santa Victoria, 4",
    "sg:city":"Breda",
    "sg:orig_category":"Reposter\u00cdas",
    "sg:phone":"+34 972 87 01 43",
    "sg:postcode":"17400",
    "sg:province":"Girona",
    "wof:name":"Coll Casta\u00f1e Pedro",
    "wof:placetype":"venue"
},
  "geometry": {"coordinates":[2.5586578846,41.7483444214],"type":"Point"}
}