{
  "type": "Feature",
  "properties": {
    "iso:country":"ES",
    "sg:address":"Calle de Mar Mediterraneo, 4",
    "sg:city":"Utrera",
    "sg:orig_category":"Trabajos De Perforaciones, Sondeos, Construcci\u00d3n De Pozos",
    "sg:phone":"+34 954 86 17 89",
    "sg:postcode":"41710",
    "sg:province":"Sevilla",
    "sg:website":"www.sondbersa.com",
    "wof:name":"Sondeos Bernabe S.a.",
    "wof:placetype":"venue"
},
  "geometry": {"coordinates":[-5.7693619728,37.1884346008],"type":"Point"}
}