{
  "type": "Feature",
  "properties": {
    "addr:full":"Calle de Obispo Pintado, 8 Huesca Huesca 22005",
    "addr:housenumber":"8",
    "addr:postcode":"22005",
    "addr:street":"Calle De Obispo Pintado",
    "iso:country":"ES",
    "sg:address":"Calle de Obispo Pintado, 8",
    "sg:city":"Huesca",
    "sg:orig_category":"Electrodom\u00c9sticos (al Por Menor)",
    "sg:phone":"+34 974 24 45 72",
    "sg:postcode":"22005",
    "sg:province":"Huesca",
    "wof:name":"Mur Agon Roman",
    "wof:placetype":"venue"
},
  "geometry": {"coordinates":[-0.4030590057,42.1337242126],"type":"Point"}
}