{
  "type": "Feature",
  "properties": {
    "addr:full":"Calle de Mayor, 37 Lodosa Navarra 31580",
    "addr:housenumber":"37",
    "addr:postcode":"31580",
    "addr:street":"Calle De Mayor",
    "iso:country":"ES",
    "sg:address":"Calle de Mayor, 37",
    "sg:city":"Lodosa",
    "sg:orig_category":"Asociaciones Y Clubs Deportivos",
    "sg:phone":"+34 948 69 43 44",
    "sg:postcode":"31580",
    "sg:province":"Navarra",
    "wof:name":"Deportes Uro S.l.",
    "wof:placetype":"venue"
},
  "geometry": {"coordinates":[-2.0801711082,42.426448822],"type":"Point"}
}