{
  "type": "Feature",
  "properties": {
    "addr:full":"Calle de Piedad, 2 Merida Badajoz 06800",
    "addr:housenumber":"2",
    "addr:postcode":"06800",
    "addr:street":"Calle De Piedad",
    "iso:country":"ES",
    "sg:address":"Calle de Piedad, 2",
    "sg:city":"Merida",
    "sg:orig_category":"Iglesia Cat\u00d3lica",
    "sg:phone":"+34 924 31 13 80",
    "sg:postcode":"06800",
    "sg:province":"Badajoz",
    "wof:name":"Parroquia De Santa Maria La Mayor",
    "wof:placetype":"venue"
},
  "geometry": {"coordinates":[-6.3451070786,38.9149093628],"type":"Point"}
}