{
  "type": "Feature",
  "properties": {
    "addr:full":"Carrer de Amics (els), S/n S. Fost Campsentelles Barcelona 08105",
    "addr:housenumber":"s",
    "addr:postcode":"08105",
    "addr:street":"Carrer De Amics Els;/ N S.",
    "iso:country":"ES",
    "sg:address":"Carrer de Amics (els), S/n",
    "sg:city":"S. Fost Campsentelles",
    "sg:orig_category":"Acondicionamiento De Terrenos Para Deporte Y Juegos",
    "sg:phone":"+34 935 79 21 93",
    "sg:postcode":"08105",
    "sg:province":"Barcelona",
    "wof:name":"U.e.sant Fost C.f.",
    "wof:placetype":"venue"
},
  "geometry": {"coordinates":[2.2378649712,41.5145263672],"type":"Point"}
}