{
  "type": "Feature",
  "properties": {
    "addr:full":"Calle de Alcantarilla, 6 Almonte Huelva 21730",
    "addr:housenumber":"6",
    "addr:postcode":"21730",
    "addr:street":"Calle De Alcantarilla",
    "iso:country":"ES",
    "sg:address":"Calle de Alcantarilla, 6",
    "sg:city":"Almonte",
    "sg:orig_category":"Asociaciones Humanitarias, De Cooperaci\u00d3n, De Acci\u00d3n Social",
    "sg:phone":"+34 959 40 75 78",
    "sg:postcode":"21730",
    "sg:province":"Huelva",
    "wof:name":"Asociacion Alcoholicos Rehabilitados Del Condado Alcon",
    "wof:placetype":"venue"
},
  "geometry": {"coordinates":[-6.5171175003,37.2640914917],"type":"Point"}
}