{
  "type": "Feature",
  "properties": {
    "addr:full":"Avda Alcarria (de La), 8 Alcala Henares Madrid 28806",
    "addr:postcode":"28806",
    "addr:street":"Avda Alcarria De La 8",
    "iso:country":"ES",
    "sg:address":"Avda Alcarria (de La), 8",
    "sg:city":"Alcala Henares",
    "sg:orig_category":"Cajas De Ahorro",
    "sg:phone":"+34 918 77 19 70",
    "sg:postcode":"28806",
    "sg:province":"Madrid",
    "wof:name":"Caja De Ahorros De Valencia Castellon Y Alicante",
    "wof:placetype":"venue"
},
  "geometry": {"coordinates":[-3.3637499809,40.4920654297],"type":"Point"}
}