{
  "type": "Feature",
  "properties": {
    "iso:country":"ES",
    "sg:address":"Calle de Perez Galdos, 13",
    "sg:city":"Albacete",
    "sg:orig_category":"Ropa Para Se\u00d1oras (al Por Menor)",
    "sg:phone":"+34 967 22 11 65",
    "sg:postcode":"02003",
    "sg:province":"Albacete",
    "wof:name":"Isabel Gregorio Molina Y Maria Isabel Rodriguez Gregorio Cdad",
    "wof:placetype":"venue"
},
  "geometry": {"coordinates":[-1.8583569527,38.9898986816],"type":"Point"}
}