{
  "type": "Feature",
  "properties": {
    "addr:full":"Ctra Corella, Km. 0035,0 Tudela Navarra 31500",
    "addr:postcode":"31500",
    "addr:street":"Ctra Corella Km. 0035,0",
    "iso:country":"ES",
    "sg:address":"Ctra Corella, Km. 0035,0",
    "sg:city":"Tudela",
    "sg:orig_category":"Cojinetes De Bolas, Agujas Y Rodillos (fabricaci\u00d3n, Al Por Mayor)",
    "sg:phone":"+34 948 82 23 00",
    "sg:postcode":"31500",
    "sg:province":"Navarra",
    "wof:name":"S.k.f. Espa\u00d1ola S.a.",
    "wof:placetype":"venue"
},
  "geometry": {"coordinates":[-1.6163959503,42.0631790161],"type":"Point"}
}