{
  "type": "Feature",
  "properties": {
    "addr:full":"Calle de Cuatro Caminos, 56 Zarandona Murcia 30007",
    "addr:housenumber":"56",
    "addr:postcode":"30007",
    "addr:street":"Calle De Cuatro Caminos",
    "iso:country":"ES",
    "sg:address":"Calle de Cuatro Caminos, 56",
    "sg:city":"Zarandona",
    "sg:orig_category":"Estudios, Instalaci\u00d3n De Climatizaci\u00d3n",
    "sg:phone":"+34 968 23 65 28",
    "sg:postcode":"30007",
    "sg:province":"Murcia",
    "sg:website":"www.salvadorescoda.com",
    "wof:name":"Salvador Escoda S.a.",
    "wof:placetype":"venue"
},
  "geometry": {"coordinates":[-1.1148469448,37.9978675842],"type":"Point"}
}