{
  "type": "Feature",
  "properties": {
    "addr:full":"Calle de Santa Engracia, 148 Madrid Madrid 28003",
    "addr:housenumber":"148",
    "addr:postcode":"28003",
    "addr:street":"Calle De Santa Engracia",
    "iso:country":"ES",
    "sg:address":"Calle de Santa Engracia, 148",
    "sg:city":"Madrid",
    "sg:orig_category":"Agencias De Relaciones P\u00dablicas",
    "sg:phone":"+34 917 02 17 98",
    "sg:postcode":"28003",
    "sg:province":"Madrid",
    "wof:name":"Quid Quid Orp S.a.",
    "wof:placetype":"venue"
},
  "geometry": {"coordinates":[-3.7030522823,40.4448814392],"type":"Point"}
}