{
  "type": "Feature",
  "properties": {
    "addr:full":"Puigsacalm (la Canya), 3 S. Joan Fonts Girona 17857",
    "addr:housenumber":"3",
    "addr:postcode":"17857",
    "addr:street":"Puigsacalm;Canya;S. Joan Fonts",
    "iso:country":"ES",
    "sg:address":"Puigsacalm (la Canya), 3",
    "sg:city":"S. Joan Fonts",
    "sg:orig_category":"Iglesia Cat\u00d3lica",
    "sg:phone":"+34 972 29 07 04",
    "sg:postcode":"17857",
    "sg:province":"Girona",
    "wof:name":"Bisbat De Girona",
    "wof:placetype":"venue"
},
  "geometry": {"coordinates":[2.5107150078,42.2121162415],"type":"Point"}
}