{
  "type": "Feature",
  "properties": {
    "addr:full":"Calle de Jesus, 35 Valencia Valencia 46007",
    "addr:housenumber":"35",
    "addr:postcode":"46007",
    "addr:street":"Calle De Jesus",
    "iso:country":"ES",
    "sg:address":"Calle de Jesus, 35",
    "sg:city":"Valencia",
    "sg:orig_category":"Agencias Y Agentes Comerciales, Representantes",
    "sg:phone":"+34 963 80 05 13",
    "sg:postcode":"46007",
    "sg:province":"Valencia",
    "wof:name":"Bau Blasco Antonio Luis",
    "wof:placetype":"venue"
},
  "geometry": {"coordinates":[-0.3835279942,39.4659004211],"type":"Point"}
}