{
  "type": "Feature",
  "properties": {
    "iso:country":"ES",
    "sg:address":"J Carrer de Labrandero, 2",
    "sg:city":"Cortegana",
    "sg:orig_category":"Ahumados Y Salazones",
    "sg:phone":"+34 959 13 16 80",
    "sg:postcode":"21230",
    "sg:province":"Huelva",
    "wof:name":"Martin Coronado Manuel",
    "wof:placetype":"venue"
},
  "geometry": {"coordinates":[-6.8218269348,37.9156494141],"type":"Point"}
}