{
  "type": "Feature",
  "properties": {
    "iso:country":"ES",
    "sg:address":"Calle de Abdelkader, 16",
    "sg:city":"Melilla",
    "sg:orig_category":"Molduras, Junquillos, Listones Y Molduras Perforadas",
    "sg:phone":"+34 952 68 17 43",
    "sg:postcode":"52001",
    "sg:province":"Melilla",
    "wof:name":"Guanich Chocron Mesod",
    "wof:placetype":"venue"
},
  "geometry": {"coordinates":[-2.9418172836,35.2942008972],"type":"Point"}
}