{
  "type": "Feature",
  "properties": {
    "iso:country":"ES",
    "sg:address":"Plaz Poniente, 3",
    "sg:city":"Valladolid",
    "sg:orig_category":"Abogados",
    "sg:phone":"+34 983 33 10 23",
    "sg:postcode":"47003",
    "sg:province":"Valladolid",
    "wof:name":"Parra Bustos Jesus",
    "wof:placetype":"venue"
},
  "geometry": {"coordinates":[-4.7302708626,41.6527709961],"type":"Point"}
}