{
  "type": "Feature",
  "properties": {
    "addr:full":"Avda Republica Argentina, 28 Le\u00f3n Le\u00f3n 24004",
    "addr:housenumber":"28",
    "addr:postcode":"24004",
    "addr:street":"Avda Republica Argentina;Leo\u0301N",
    "iso:country":"ES",
    "sg:address":"Avda Republica Argentina, 28",
    "sg:city":"Le\u00f3n",
    "sg:orig_category":"Centros Comerciales Y Grandes Tiendas",
    "sg:phone":"+34 987 20 96 23",
    "sg:postcode":"24004",
    "sg:province":"Le\u00f3n",
    "sg:website":"www.paginasamarillas.es",
    "wof:name":"Picon Fernandez Jesus",
    "wof:placetype":"venue"
},
  "geometry": {"coordinates":[-5.5757861137,42.59582901],"type":"Point"}
}