{
  "type": "Feature",
  "properties": {
    "addr:full":"Pg Ferrocarril, 62 Manacor Islas Baleares 07500",
    "addr:housenumber":"62",
    "addr:postcode":"07500",
    "addr:street":"Pg Ferrocarril",
    "iso:country":"ES",
    "sg:address":"Pg Ferrocarril, 62",
    "sg:city":"Manacor",
    "sg:orig_category":"Ense\u00d1anza, Formaci\u00d3n Profesional: Aprendizaje",
    "sg:phone":"+34 971 84 45 42",
    "sg:postcode":"07500",
    "sg:province":"Islas Baleares",
    "wof:name":"Collegi Oficial D'arquitectes De Balears",
    "wof:placetype":"venue"
},
  "geometry": {"coordinates":[3.2091610432,39.574672699],"type":"Point"}
}