{
  "type": "Feature",
  "properties": {
    "addr:full":"Carrer de Mateu Obrador, 1 Palma Islas Baleares 07011",
    "addr:housenumber":"1",
    "addr:postcode":"07011",
    "addr:street":"Carrer De Mateu Obrador",
    "iso:country":"ES",
    "sg:address":"Carrer de Mateu Obrador, 1",
    "sg:city":"Palma",
    "sg:orig_category":"Agencias De Viajes",
    "sg:phone":"+34 971 40 32 74",
    "sg:postcode":"07011",
    "sg:province":"Islas Baleares",
    "sg:website":"www.viajeseuropair.com",
    "wof:name":"Viajes Europair S.a.",
    "wof:placetype":"venue"
},
  "geometry": {"coordinates":[2.6435239315,39.5758285522],"type":"Point"}
}