{
  "type": "Feature",
  "properties": {
    "addr:full":"Calle de Gonzalez Bueno, 6 Elda Alicante 03600",
    "addr:housenumber":"6",
    "addr:postcode":"03600",
    "addr:street":"Calle De Gonzalez Bueno",
    "iso:country":"ES",
    "sg:address":"Calle de Gonzalez Bueno, 6",
    "sg:city":"Elda",
    "sg:orig_category":"Agencias Y Agentes Comerciales, Representantes",
    "sg:phone":"+34 966 96 52 07",
    "sg:postcode":"03600",
    "sg:province":"Alicante",
    "wof:name":"Beimi Shoes S.l.",
    "wof:placetype":"venue"
},
  "geometry": {"coordinates":[-0.7940940261,38.4742965698],"type":"Point"}
}