{
  "type": "Feature",
  "properties": {
    "addr:full":"Calle de Pe\u00d1a Picada, 30 Arcos Frontera C\u00e1diz 11630",
    "addr:housenumber":"30",
    "addr:postcode":"11630",
    "addr:street":"Calle De Pen\u0303A Picada",
    "iso:country":"ES",
    "sg:address":"Calle de Pe\u00d1a Picada, 30",
    "sg:city":"Arcos Frontera",
    "sg:orig_category":"Agencias De Viajes",
    "sg:phone":"+34 956 71 73 47",
    "sg:postcode":"11630",
    "sg:province":"C\u00e1diz",
    "wof:name":"Santana Gallego Mari Angeles",
    "wof:placetype":"venue"
},
  "geometry": {"coordinates":[-5.8130187988,36.7521286011],"type":"Point"}
}