{
  "type": "Feature",
  "properties": {
    "addr:full":"Cmno Estacion (de La), S/n Estacion Portazgo Zaragoza 50800",
    "addr:postcode":"50800",
    "addr:street":"Cmno Estacion De La S / N Estacion",
    "iso:country":"ES",
    "sg:address":"Cmno Estacion (de La), S/n",
    "sg:city":"Estacion Portazgo",
    "sg:orig_category":"Internados & Ense\u00d1anza Privada",
    "sg:phone":"+34 976 69 01 79",
    "sg:postcode":"50800",
    "sg:province":"Zaragoza",
    "wof:name":"Colegio San Gabriel En Zuera Pasionistas Padres Prov Zaragoza",
    "wof:placetype":"venue"
},
  "geometry": {"coordinates":[-0.7865840197,41.867225647],"type":"Point"}
}