{
  "type": "Feature",
  "properties": {
    "addr:full":"Calle de Bergara, 2 Donostia-san Sebastian Guip\u00f9zcoa 20005",
    "addr:housenumber":"2",
    "addr:postcode":"20005",
    "addr:street":"Calle De Bergara",
    "iso:country":"ES",
    "sg:address":"Calle de Bergara, 2",
    "sg:city":"Donostia-san Sebastian",
    "sg:orig_category":"Fabricaci\u00d3n De Taburetes, Sillas Y Sillones",
    "sg:phone":"+34 943 42 04 98",
    "sg:postcode":"20005",
    "sg:province":"Guip\u00f9zcoa",
    "wof:name":"Eurolubke S.a.",
    "wof:placetype":"venue"
},
  "geometry": {"coordinates":[-1.980981946,43.3197937012],"type":"Point"}
}