{
  "type": "Feature",
  "properties": {
    "iso:country":"ES",
    "sg:address":"Calle de Cari\u00d1ena, 1",
    "sg:city":"Zaragoza",
    "sg:orig_category":"Electricidad: Instaladores",
    "sg:phone":"+34 976 53 85 68",
    "sg:postcode":"50010",
    "sg:province":"Zaragoza",
    "wof:name":"Velilla Moreo Julio",
    "wof:placetype":"venue"
},
  "geometry": {"coordinates":[-0.8946890235,41.6490859985],"type":"Point"}
}