{
  "type": "Feature",
  "properties": {
    "iso:country":"ES",
    "sg:address":"Calle de Antonio Fernandez Vallina, S/n",
    "sg:city":"Navia",
    "sg:orig_category":"Ense\u00d1anza, Formaci\u00d3n Profesional: Aprendizaje",
    "sg:phone":"+34 985 47 33 00",
    "sg:postcode":"33710",
    "sg:province":"Asturias",
    "wof:name":"Ayuntamiento De Navia",
    "wof:placetype":"venue"
},
  "geometry": {"coordinates":[-6.6691579819,43.5343322754],"type":"Point"}
}