{
  "type": "Feature",
  "properties": {
    "addr:full":"Avda Carlos Iii, 391 Campillo Del Moro Almer\u00eda 04720",
    "addr:housenumber":"391",
    "addr:postcode":"04720",
    "addr:street":"Avda Carlos Iii",
    "iso:country":"ES",
    "sg:address":"Avda Carlos Iii, 391",
    "sg:city":"Campillo Del Moro",
    "sg:orig_category":"Muebles, Minoristas",
    "sg:phone":"+34 950 34 90 97",
    "sg:postcode":"04720",
    "sg:province":"Almer\u00eda",
    "wof:name":"Tiendas De Confort S.l.",
    "wof:placetype":"venue"
},
  "geometry": {"coordinates":[-2.5741510391,36.8138160706],"type":"Point"}
}