{
  "type": "Feature",
  "properties": {
    "addr:full":"Carr Santiago Rusi\u00d1ol, 108 Badalona Barcelona 08911",
    "addr:housenumber":"108",
    "addr:postcode":"08911",
    "addr:street":"Carr Santiago Rusin\u0303Ol",
    "iso:country":"ES",
    "sg:address":"Carr Santiago Rusi\u00d1ol, 108",
    "sg:city":"Badalona",
    "sg:orig_category":"Reposter\u00cdas",
    "sg:phone":"+34 933 89 22 09",
    "sg:postcode":"08911",
    "sg:province":"Barcelona",
    "wof:name":"Sea Cover S.l.",
    "wof:placetype":"venue"
},
  "geometry": {"coordinates":[2.2550830841,41.4534416199],"type":"Point"}
}