{
  "type": "Feature",
  "properties": {
    "iso:country":"ES",
    "sg:address":"Plaza De La Iglesia, S/n",
    "sg:city":"Villarluengo",
    "sg:orig_category":"Carnicer\u00cdas, Carnicer\u00cdas",
    "sg:phone":"+34 978 77 30 06",
    "sg:postcode":"44559",
    "sg:province":"Teruel",
    "wof:name":"Jamones Elrrullo S.l.",
    "wof:placetype":"venue"
},
  "geometry": {"coordinates":[-0.553376019,40.7767982483],"type":"Point"}
}