{
  "type": "Feature",
  "properties": {
    "iso:country":"ES",
    "sg:address":"Plaz Constitucion, 8",
    "sg:city":"Santa Barbara De Casa",
    "sg:orig_category":"Empresas De Carpinter\u00cda De Madera",
    "sg:phone":"+34 959 57 00 05",
    "sg:postcode":"21570",
    "sg:province":"Huelva",
    "wof:name":"Gomez Gomez Sebastian",
    "wof:placetype":"venue"
},
  "geometry": {"coordinates":[-7.1895809174,37.7967605591],"type":"Point"}
}