{
  "type": "Feature",
  "properties": {
    "iso:country":"ES",
    "sg:address":"Pase Alameda, 1",
    "sg:city":"Molina",
    "sg:orig_category":"Ense\u00d1anza Variada",
    "sg:phone":"+34 949 83 20 59",
    "sg:postcode":"19300",
    "sg:province":"Guadalajara",
    "wof:name":"Centro De Profesores Y De Recursos",
    "wof:placetype":"venue"
},
  "geometry": {"coordinates":[-1.8168599606,40.8542098999],"type":"Point"}
}