{
  "type": "Feature",
  "properties": {
    "addr:full":"Avda Compa\u00d1ia De Mar (de La), 37 Ceuta Ceuta 51001",
    "addr:housenumber":"37",
    "addr:postcode":"51001",
    "addr:street":"Avda Compan\u0303Ia De Mar De La",
    "iso:country":"ES",
    "sg:address":"Avda Compa\u00d1ia De Mar (de La), 37",
    "sg:city":"Ceuta",
    "sg:orig_category":"Restaurantes",
    "sg:phone":"+34 956 51 38 84",
    "sg:postcode":"51001",
    "sg:province":"Ceuta",
    "wof:name":"Meson El Refectorio C.b.",
    "wof:placetype":"venue"
},
  "geometry": {"coordinates":[-5.3302302361,35.8947601318],"type":"Point"}
}