{
  "type": "Feature",
  "properties": {
    "addr:full":"Calle de Secundino Esnaola, 30 Zumarraga Guip\u00f9zcoa 20700",
    "addr:housenumber":"30",
    "addr:postcode":"20700",
    "addr:street":"Calle De Secundino Esnaola;Guipu\u0300Zcoa",
    "iso:country":"ES",
    "sg:address":"Calle de Secundino Esnaola, 30",
    "sg:city":"Zumarraga",
    "sg:orig_category":"Delegados, Agentes De Tr\u00c1nsito, Auxiliares De Transporte Internacional",
    "sg:phone":"+34 943 72 16 62",
    "sg:postcode":"20700",
    "sg:province":"Guip\u00f9zcoa",
    "wof:name":"Mendiluce Aguirre Francisco (transportes)",
    "wof:placetype":"venue"
},
  "geometry": {"coordinates":[-2.3193559647,43.0881576538],"type":"Point"}
}