{
  "type": "Feature",
  "properties": {
    "iso:country":"ES",
    "sg:address":"Calle de Conde De Pe\u00d1alver, 16",
    "sg:city":"Madrid",
    "sg:orig_category":"Audiovisuales (producci\u00d3n, Edici\u00d3n, Realizaci\u00d3n)",
    "sg:phone":"+34 914 35 44 54",
    "sg:postcode":"28006",
    "sg:province":"Madrid",
    "wof:name":"Orco Systems S.l.",
    "wof:placetype":"venue"
},
  "geometry": {"coordinates":[-3.6755518913,40.4267311096],"type":"Point"}
}