{
  "type": "Feature",
  "properties": {
    "addr:full":"Calle de Erribera, S/n Ondarroa Vizcaya 48700",
    "addr:housenumber":"s / n",
    "addr:postcode":"48700",
    "addr:street":"Calle De Erribera",
    "iso:country":"ES",
    "sg:address":"Calle de Erribera, S/n",
    "sg:city":"Ondarroa",
    "sg:orig_category":"Pescader\u00cdas (al Por Menor)",
    "sg:phone":"+34 946 83 14 08",
    "sg:postcode":"48700",
    "sg:province":"Vizcaya",
    "wof:name":"Osa Zubicaray Maria Dominga",
    "wof:placetype":"venue"
},
  "geometry": {"coordinates":[-2.4233090878,43.3203811646],"type":"Point"}
}