{
  "type": "Feature",
  "properties": {
    "addr:full":"Calle de Frailes (de Los), 16 Barco De Avila \u00c1vila 05600",
    "addr:housenumber":"16",
    "addr:postcode":"05600",
    "addr:street":"Calle De Frailes De Los;A\u0301Vila",
    "iso:country":"ES",
    "sg:address":"Calle de Frailes (de Los), 16",
    "sg:city":"Barco De Avila",
    "sg:classifiers":[
        {
            "category":"Autos & Motor Vehicles",
            "subcategory":"Automobile Sales",
            "type":"Retail Goods"
        }
    ],
    "sg:phone":"+34 920 34 10 13",
    "sg:postcode":"05600",
    "sg:province":"\u00c1vila",
    "wof:name":"Barrera Soriano Angel",
    "wof:placetype":"venue"
},
  "geometry": {"coordinates":[-5.5219669342,40.3573226929],"type":"Point"}
}