{
  "type": "Feature",
  "properties": {
    "iso:country":"ES",
    "sg:address":"C/ Gregorio Mara\u00d1on, 2",
    "sg:city":"Elche",
    "sg:orig_category":"Cristaler\u00cdas",
    "sg:phone":"+34 966 61 12 03",
    "sg:postcode":"03202",
    "sg:province":"Alicante",
    "wof:name":"Vidrios Altabix S.l.",
    "wof:placetype":"venue"
},
  "geometry": {"coordinates":[-0.5931239724,38.2568435669],"type":"Point"}
}