{
  "type": "Feature",
  "properties": {
    "addr:full":"Carrer de Bailen, 5 Senia Tarragona 43560",
    "addr:housenumber":"5",
    "addr:postcode":"43560",
    "addr:street":"Carrer De Bailen",
    "iso:country":"ES",
    "sg:address":"Carrer de Bailen, 5",
    "sg:city":"Senia",
    "sg:orig_category":"Peluqueros: De Se\u00d1oras",
    "sg:phone":"+34 977 71 35 19",
    "sg:postcode":"43560",
    "sg:province":"Tarragona",
    "wof:name":"Carvajal Gutierrez Carmen",
    "wof:placetype":"venue"
},
  "geometry": {"coordinates":[0.2798570096,40.6343650818],"type":"Point"}
}