{
  "type": "Feature",
  "properties": {
    "addr:full":"Pg Ferrocarril, 50 Cassa Selva Girona 17244",
    "addr:housenumber":"50",
    "addr:postcode":"17244",
    "addr:street":"Pg Ferrocarril",
    "iso:country":"ES",
    "sg:address":"Pg Ferrocarril, 50",
    "sg:city":"Cassa Selva",
    "sg:orig_category":"Chapister\u00cda",
    "sg:phone":"+34 972 46 18 79",
    "sg:postcode":"17244",
    "sg:province":"Girona",
    "wof:name":"Rodriguez Lindes Francisco",
    "wof:placetype":"venue"
},
  "geometry": {"coordinates":[2.8734769821,41.8849449158],"type":"Point"}
}