{
  "type": "Feature",
  "properties": {
    "addr:full":"Calle de Laureles, 71 Vera-carril Santa Cruz De Tenerife 38380",
    "addr:housenumber":"71",
    "addr:postcode":"38380",
    "addr:street":"Calle De Laureles",
    "iso:country":"ES",
    "sg:address":"Calle de Laureles, 71",
    "sg:city":"Vera-carril",
    "sg:orig_category":"Empresas De Carpinter\u00cda De Madera",
    "sg:phone":"+34 922 58 16 20",
    "sg:postcode":"38380",
    "sg:province":"Santa Cruz De Tenerife",
    "wof:name":"Carpinteria Gutierrez Fernandez Y Asociado S.l.",
    "wof:placetype":"venue"
},
  "geometry": {"coordinates":[-16.4724025726,28.4344654083],"type":"Point"}
}