{
  "type": "Feature",
  "properties": {
    "addr:full":"Avda Amanecer, S/n Javea Alicante 03730",
    "addr:housenumber":"s",
    "addr:postcode":"03730",
    "addr:street":"Avda Amanecer;/ N Javea Alicante",
    "iso:country":"ES",
    "sg:address":"Avda Amanecer, S/n",
    "sg:city":"Javea",
    "sg:orig_category":"Restaurantes",
    "sg:phone":"+34 965 79 16 00",
    "sg:postcode":"03730",
    "sg:province":"Alicante",
    "wof:name":"Champagne S. L.",
    "wof:placetype":"venue"
},
  "geometry": {"coordinates":[0.1684439927,38.7892303467],"type":"Point"}
}