{
  "type": "Feature",
  "properties": {
    "addr:full":"Pl General Prim, 4 Tarragona Tarragona 43001",
    "addr:housenumber":"4",
    "addr:postcode":"43001",
    "addr:street":"General Prim",
    "iso:country":"ES",
    "sg:address":"Pl General Prim, 4",
    "sg:city":"Tarragona",
    "sg:orig_category":"Venta, Instalaci\u00d3n De Sistemas De Alarmas Y Vigilancia",
    "sg:phone":"+34 977 22 02 14",
    "sg:postcode":"43001",
    "sg:province":"Tarragona",
    "wof:name":"Securitas Sistemas De Seguridad S.a.",
    "wof:placetype":"venue"
},
  "geometry": {"coordinates":[1.2507669926,41.1132965088],"type":"Point"}
}