{
  "type": "Feature",
  "properties": {
    "addr:full":"Carrer de Gabriel Y Galan, 22 Barcelona Barcelona 08026",
    "addr:housenumber":"22",
    "addr:postcode":"08026",
    "addr:street":"Carrer De Gabriel Y Galan",
    "iso:country":"ES",
    "sg:address":"Carrer de Gabriel Y Galan, 22",
    "sg:city":"Barcelona",
    "sg:orig_category":"Peluquer\u00cdas, Peluquer\u00cda Mixta",
    "sg:phone":"+34 932 43 05 21",
    "sg:postcode":"08026",
    "sg:province":"Barcelona",
    "wof:name":"Crismian S.c.p.",
    "wof:placetype":"venue"
},
  "geometry": {"coordinates":[2.1877789497,41.4119033813],"type":"Point"}
}