{
  "type": "Feature",
  "properties": {
    "addr:full":"Agua De Bueyes, 2 Valles Ortega Las Palmas 35638",
    "addr:housenumber":"2",
    "addr:postcode":"35638",
    "addr:street":"Bueyes;Ortega Las",
    "iso:country":"ES",
    "sg:address":"Agua De Bueyes, 2",
    "sg:city":"Valles Ortega",
    "sg:orig_category":"Asociaciones, Organismos Culturales Y Socioeducativos",
    "sg:phone":"+34 928 87 88 08",
    "sg:postcode":"35638",
    "sg:province":"Las Palmas",
    "wof:name":"Ayuntamiento De Antigua",
    "wof:placetype":"venue"
},
  "geometry": {"coordinates":[-14.0128507614,28.388376236],"type":"Point"}
}