{
  "type": "Feature",
  "properties": {
    "addr:full":"Carrer de Francesc Macia, 39 Martorell Barcelona 08760",
    "addr:housenumber":"39",
    "addr:postcode":"08760",
    "addr:street":"Carrer De Francesc Macia",
    "iso:country":"ES",
    "sg:address":"Carrer de Francesc Macia, 39",
    "sg:city":"Martorell",
    "sg:orig_category":"Agencias Y Agentes Comerciales, Representantes",
    "sg:phone":"+34 937 75 36 60",
    "sg:postcode":"08760",
    "sg:province":"Barcelona",
    "wof:name":"Ortega Moreno Victoria",
    "wof:placetype":"venue"
},
  "geometry": {"coordinates":[1.9128769636,41.4776916504],"type":"Point"}
}