{
  "type": "Feature",
  "properties": {
    "addr:full":"Carrer de Comte Borrell, 227 Barcelona Barcelona 08029",
    "addr:housenumber":"227",
    "addr:postcode":"08029",
    "addr:street":"Carrer De Comte Borrell",
    "iso:country":"ES",
    "sg:address":"Carrer de Comte Borrell, 227",
    "sg:city":"Barcelona",
    "sg:orig_category":"Importaci\u00d3n",
    "sg:phone":"+34 934 39 41 46",
    "sg:postcode":"08029",
    "sg:province":"Barcelona",
    "wof:name":"Iber-orient Import.s.l.",
    "wof:placetype":"venue"
},
  "geometry": {"coordinates":[2.1508409977,41.3860702515],"type":"Point"}
}