{
  "type": "Feature",
  "properties": {
    "addr:full":"Calle de San Raimundo, 37 Madrid Madrid 28039",
    "addr:housenumber":"37",
    "addr:postcode":"madrid;28039",
    "addr:street":"Calle De San",
    "iso:country":"ES",
    "sg:address":"Calle de San Raimundo, 37",
    "sg:city":"Madrid",
    "sg:orig_category":"Promotores Constructores",
    "sg:phone":"+34 913 11 20 00",
    "sg:postcode":"28039",
    "sg:province":"Madrid",
    "wof:name":"Reformas Y Decoraciones Madrid S.l.",
    "wof:placetype":"venue"
},
  "geometry": {"coordinates":[-3.7061131001,40.4516944885],"type":"Point"}
}