{
  "type": "Feature",
  "properties": {
    "iso:country":"ES",
    "sg:address":"Avda San Martin (de), Km. 0017,0",
    "sg:city":"S. Martin Vega",
    "sg:orig_category":"Refiner\u00cdas De Petr\u00d3leo",
    "sg:phone":"+34 918 94 52 31",
    "sg:postcode":"28330",
    "sg:province":"Madrid",
    "wof:name":"Hermanos Blanca Excavaciones S.l.",
    "wof:placetype":"venue"
},
  "geometry": {"coordinates":[-3.572316885,40.2097358704],"type":"Point"}
}