{
  "type": "Feature",
  "properties": {
    "iso:country":"ES",
    "sg:address":"Alam Areilza Doctor, 35",
    "sg:city":"Bilbao",
    "sg:orig_category":"Bancos",
    "sg:phone":"+34 944 70 00 52",
    "sg:postcode":"48010",
    "sg:province":"Vizcaya",
    "wof:name":"R Cable Y Telecomunicaciones Galicia S.a.",
    "wof:placetype":"venue"
},
  "geometry": {"coordinates":[-2.9425690174,43.2603874207],"type":"Point"}
}