{
  "type": "Feature",
  "properties": {
    "iso:country":"ES",
    "sg:address":"Ctra. Deleitosa-retamosa, Km. 0009,0",
    "sg:city":"Deleitosa",
    "sg:orig_category":"Charcuter\u00cdas (al Por Mayor)",
    "sg:phone":"+34 927 54 00 71",
    "sg:postcode":"10370",
    "sg:province":"C\u00e1ceres",
    "wof:name":"Embutidos Y Jamones Dehesa De Deleitosa S.l.",
    "wof:placetype":"venue"
},
  "geometry": {"coordinates":[-5.6446962357,39.645614624],"type":"Point"}
}