{
  "type": "Feature",
  "properties": {
    "iso:country":"ES",
    "sg:address":"Rua Pulleira (da), 52",
    "sg:city":"Santiago De Compostela",
    "sg:orig_category":"Empresas De Carpinter\u00cda Met\u00c1lica",
    "sg:phone":"+34 981 57 34 84",
    "sg:postcode":"15705",
    "sg:province":"A Coru\u00f1a",
    "wof:name":"Talleres Miguel Seoane S.l.",
    "wof:placetype":"venue"
},
  "geometry": {"coordinates":[-8.5858488083,42.8696060181],"type":"Point"}
}