{
  "type": "Feature",
  "properties": {
    "iso:country":"ES",
    "sg:address":"Rond San Lazaro, 8",
    "sg:city":"Pe\u00e7aranda De Bracamonte",
    "sg:orig_category":"Comercio De Hierro",
    "sg:phone":"+34 923 54 07 86",
    "sg:postcode":"37300",
    "sg:province":"Salamanca",
    "wof:name":"Hierros Bernal S.l.",
    "wof:placetype":"venue"
},
  "geometry": {"coordinates":[-5.6630473137,40.9649734497],"type":"Point"}
}