{
  "type": "Feature",
  "properties": {
    "addr:full":"Calle de Mar, 27 Malaga M\u00e1laga 29017",
    "addr:housenumber":"27",
    "addr:postcode":"29017",
    "addr:street":"Calle De Mar;Ma\u0301Laga",
    "iso:country":"ES",
    "sg:address":"Calle de Mar, 27",
    "sg:city":"Malaga",
    "sg:orig_category":"Venta, Colocaci\u00d3n, Reparaci\u00d3n De Parabrisas, Techos Descapotables",
    "sg:phone":"+34 952 20 29 37",
    "sg:postcode":"29017",
    "sg:province":"M\u00e1laga",
    "wof:name":"Autovidrios S.l.",
    "wof:placetype":"venue"
},
  "geometry": {"coordinates":[-4.3588647842,36.7196998596],"type":"Point"}
}