{
  "type": "Feature",
  "properties": {
    "iso:country":"ES",
    "sg:address":"Calle de Fontanilla, 24",
    "sg:city":"Zafra",
    "sg:orig_category":"Sindicatos De Trabajadores",
    "sg:phone":"+34 924 55 32 02",
    "sg:postcode":"06300",
    "sg:province":"Badajoz",
    "wof:name":"Union Regional De Cc Oo De Extremadura",
    "wof:placetype":"venue"
},
  "geometry": {"coordinates":[-6.4181990623,38.4221305847],"type":"Point"}
}