{
  "type": "Feature",
  "properties": {
    "addr:full":"Ponteceso De Cabana, 19 Ponteceso De Cabana La Coru\u00f1a 15115",
    "addr:housenumber":"19",
    "addr:postcode":"15115",
    "addr:street":"Corun\u0303A",
    "iso:country":"ES",
    "sg:address":"Ponteceso De Cabana, 19",
    "sg:city":"Ponteceso De Cabana",
    "sg:orig_category":"Autob\u00das (explotaci\u00d3n Y Servicios De)",
    "sg:phone":"+34 981 71 41 28",
    "sg:postcode":"15115",
    "sg:province":"La Coru\u00f1a",
    "wof:name":"Autocares J.pombo S.l.",
    "wof:placetype":"venue"
},
  "geometry": {"coordinates":[-8.8914251328,43.1860733032],"type":"Point"}
}