{
  "type": "Feature",
  "properties": {
    "addr:full":"Carrer de Salles, 29 S. Cugat Valles Barcelona 08172",
    "addr:housenumber":"29",
    "addr:postcode":"08172",
    "addr:street":"Carrer De Salles;S. Cugat Valles Barcelona",
    "iso:country":"ES",
    "sg:address":"Carrer de Salles, 29",
    "sg:city":"S. Cugat Valles",
    "sg:orig_category":"Tintes (fabricaci\u00d3n, Al Por Mayor)",
    "sg:phone":"+34 935 89 64 65",
    "sg:postcode":"08172",
    "sg:province":"Barcelona",
    "wof:name":"Qui\u00f1ones Zu\u00f1iga Danilo",
    "wof:placetype":"venue"
},
  "geometry": {"coordinates":[2.0822920799,41.4740600586],"type":"Point"}
}