{
  "type": "Feature",
  "properties": {
    "addr:full":"Avenida De Ordesa, S/n Gavin Huesca 22639",
    "addr:housenumber":"s / n",
    "addr:postcode":"22639",
    "addr:street":"Avenida De Ordesa",
    "iso:country":"ES",
    "sg:address":"Avenida De Ordesa, S/n",
    "sg:city":"Gavin",
    "sg:orig_category":"Alquiler De Apartamentos",
    "sg:phone":"+34 974 48 54 94",
    "sg:postcode":"22639",
    "sg:province":"Huesca",
    "wof:name":"Fa\u00f1anas Bordetas Nuria",
    "wof:placetype":"venue"
},
  "geometry": {"coordinates":[-0.2492939979,42.6190795898],"type":"Point"}
}