{
  "type": "Feature",
  "properties": {
    "iso:country":"ES",
    "sg:address":"Rua Valle Inclan, 16",
    "sg:city":"Cambados",
    "sg:orig_category":"Ropa Para Se\u00d1oras Y Caballeros (al Por Menor)",
    "sg:phone":"+34 986 52 69 03",
    "sg:postcode":"36630",
    "sg:province":"Pontevedra",
    "wof:name":"Abalo Miguez Maria Rita",
    "wof:placetype":"venue"
},
  "geometry": {"coordinates":[-8.811597,42.517967],"type":"Point"}
}