{
  "type": "Feature",
  "properties": {
    "addr:full":"Barr Baden, 4 Marchamalo Guadalajara 19180",
    "addr:postcode":"19180",
    "iso:country":"ES",
    "sg:address":"Barr Baden, 4",
    "sg:city":"Marchamalo",
    "sg:orig_category":"Contables",
    "sg:phone":"+34 949 25 23 96",
    "sg:postcode":"19180",
    "sg:province":"Guadalajara",
    "wof:name":"Guijarro Casado Ascension",
    "wof:placetype":"venue"
},
  "geometry": {"coordinates":[-3.2014870644,40.6685218811],"type":"Point"}
}