{
  "type": "Feature",
  "properties": {
    "iso:country":"ES",
    "sg:address":"Calle de Londres, 5",
    "sg:city":"Parla",
    "sg:orig_category":"Papel (al Por Mayor)",
    "sg:phone":"+34 916 05 40 60",
    "sg:postcode":"28980",
    "sg:province":"Madrid",
    "wof:name":"Manipulados Y Retractilados Menalva S.l.",
    "wof:placetype":"venue"
},
  "geometry": {"coordinates":[-3.7575838566,40.239074707],"type":"Point"}
}