{
  "type": "Feature",
  "properties": {
    "iso:country":"ES",
    "sg:address":"Calle de Princesa Guayarmina, 34",
    "sg:city":"Monta\u00e7eta Del Calero",
    "sg:orig_category":"Albergues",
    "sg:phone":"+34 928 13 91 08",
    "sg:postcode":"35200",
    "sg:province":"Las Palmas",
    "wof:name":"Diaz Jimenez Jose Nieves",
    "wof:placetype":"venue"
},
  "geometry": {"coordinates":[-15.4144220352,28.0029888153],"type":"Point"}
}