{
  "type": "Feature",
  "properties": {
    "addr:full":"Carrer de Ifach, 18 Altea Alicante 03590",
    "addr:housenumber":"18",
    "addr:postcode":"03590",
    "addr:street":"Carrer De Ifach",
    "iso:country":"ES",
    "sg:address":"Carrer de Ifach, 18",
    "sg:city":"Altea",
    "sg:orig_category":"Electricidad: Instaladores",
    "sg:phone":"+34 966 88 29 42",
    "sg:postcode":"03590",
    "sg:province":"Alicante",
    "wof:name":"Lopez Cano Pedro",
    "wof:placetype":"venue"
},
  "geometry": {"coordinates":[-0.0522640012,38.5952148438],"type":"Point"}
}