{
  "type": "Feature",
  "properties": {
    "iso:country":"ES",
    "sg:address":"Calle de Libertad (de La), 16",
    "sg:city":"Alcobendas",
    "sg:orig_category":"Servicio De Salud",
    "sg:phone":"+34 916 23 82 37",
    "sg:postcode":"28100",
    "sg:province":"Madrid",
    "wof:name":"Caldisban S.l.",
    "wof:placetype":"venue"
},
  "geometry": {"coordinates":[-3.6353681087,40.5401954651],"type":"Point"}
}