{
  "type": "Feature",
  "properties": {
    "addr:full":"Plaz Madre Ferran, 4 Caspe Zaragoza 50700",
    "addr:housenumber":"4",
    "addr:postcode":"50700",
    "addr:street":"Ferran",
    "iso:country":"ES",
    "sg:address":"Plaz Madre Ferran, 4",
    "sg:city":"Caspe",
    "sg:orig_category":"Molduras, Junquillos, Listones Y Molduras Perforadas",
    "sg:phone":"+34 976 63 33 27",
    "sg:postcode":"50700",
    "sg:province":"Zaragoza",
    "wof:name":"Rosales Sanchez Adoracion",
    "wof:placetype":"venue"
},
  "geometry": {"coordinates":[-0.0396060012,41.2326126099],"type":"Point"}
}