{
  "type": "Feature",
  "properties": {
    "addr:full":"Riera (la), 32 Mataro Barcelona 08301",
    "addr:postcode":"08301",
    "addr:street":"Riera",
    "iso:country":"ES",
    "sg:address":"Riera (la), 32",
    "sg:city":"Mataro",
    "sg:orig_category":"Loter\u00cda Y T\u00d3mbola",
    "sg:phone":"+34 937 90 29 13",
    "sg:postcode":"08301",
    "sg:province":"Barcelona",
    "wof:name":"Morato Riera Luis",
    "wof:placetype":"venue"
},
  "geometry": {"coordinates":[2.4439051151,41.5415153503],"type":"Point"}
}