{
  "type": "Feature",
  "properties": {
    "addr:full":"Calle de Luis De Hoyos Sainz, 174 Madrid Madrid 28030",
    "addr:housenumber":"174",
    "addr:postcode":"28030",
    "addr:street":"Calle De Luis De Hoyos Sainz",
    "iso:country":"ES",
    "sg:address":"Calle de Luis De Hoyos Sainz, 174",
    "sg:city":"Madrid",
    "sg:orig_category":"Asesor\u00cda Sobre Comunicaci\u00d3n De Empresas",
    "sg:phone":"+34 913 01 51 53",
    "sg:postcode":"28030",
    "sg:province":"Madrid",
    "wof:name":"Gestion De Negocios Madrid S.l.",
    "wof:placetype":"venue"
},
  "geometry": {"coordinates":[-3.6277649403,40.4036750793],"type":"Point"}
}