{
  "type": "Feature",
  "properties": {
    "iso:country":"ES",
    "sg:address":"Carr Ns Africa, 5",
    "sg:city":"Igualada",
    "sg:orig_category":"Carnicer\u00cdas, Carnicer\u00cdas",
    "sg:phone":"+34 938 03 64 10",
    "sg:postcode":"08700",
    "sg:province":"Barcelona",
    "wof:name":"Ortega Gutierrez Jose",
    "wof:placetype":"venue"
},
  "geometry": {"coordinates":[1.6056900024,41.5861473083],"type":"Point"}
}