{
  "type": "Feature",
  "properties": {
    "addr:full":"Avda Salamanca, 16 Valladolid Valladolid 47014",
    "addr:housenumber":"16",
    "addr:postcode":"47014",
    "addr:street":"Avda Salamanca",
    "iso:country":"ES",
    "sg:address":"Avda Salamanca, 16",
    "sg:city":"Valladolid",
    "sg:orig_category":"Ingenier\u00cda, Centros De Estudios (diversos)",
    "sg:phone":"+34 983 33 11 42",
    "sg:postcode":"47014",
    "sg:province":"Valladolid",
    "wof:name":"Martin Astruga Jose Gabriel",
    "wof:placetype":"venue"
},
  "geometry": {"coordinates":[-4.7400689125,41.6497192383],"type":"Point"}
}