{
  "type": "Feature",
  "properties": {
    "iso:country":"ES",
    "sg:address":"Plaz Romeral (del), 4",
    "sg:city":"Mazarron",
    "sg:orig_category":"Peluquer\u00cdas, Peluquer\u00cda Mixta",
    "sg:phone":"+34 968 59 25 26",
    "sg:postcode":"30870",
    "sg:province":"Murcia",
    "wof:name":"Maria Jose Y Maria Dolores Peluqueria",
    "wof:placetype":"venue"
},
  "geometry": {"coordinates":[-1.315032959,37.5997962952],"type":"Point"}
}