{
  "type": "Feature",
  "properties": {
    "addr:full":"Carr Sant Agusti, 28 Torroella Montgri Girona 17257",
    "addr:housenumber":"28",
    "addr:postcode":"17257",
    "addr:street":"Carr Sant Agusti",
    "iso:country":"ES",
    "sg:address":"Carr Sant Agusti, 28",
    "sg:city":"Torroella Montgri",
    "sg:orig_category":"Arquitectos",
    "sg:phone":"+34 972 75 85 77",
    "sg:postcode":"17257",
    "sg:province":"Girona",
    "wof:name":"Batlle Lloret Francisco",
    "wof:placetype":"venue"
},
  "geometry": {"coordinates":[3.1034500599,42.0303268433],"type":"Point"}
}