{
  "type": "Feature",
  "properties": {
    "iso:country":"ES",
    "sg:address":"Avda Eusebio Sempere, 6",
    "sg:city":"Alacant",
    "sg:orig_category":"M\u00c9dicos: Estomatolog\u00cda",
    "sg:phone":"+34 965 92 61 53",
    "sg:postcode":"03003",
    "sg:province":"Alicante",
    "wof:name":"Mu\u00f1oz Ruiz Maria Jose",
    "wof:placetype":"venue"
},
  "geometry": {"coordinates":[-0.4913879931,38.3388671875],"type":"Point"}
}