{
  "type": "Feature",
  "properties": {
    "addr:full":"Av Portugal(pol I Salinas), 2 Alhama Murcia Murcia 30840",
    "addr:housenumber":"2",
    "addr:postcode":"30840",
    "addr:street":"Av Portugal Pol I Salinas",
    "iso:country":"ES",
    "sg:address":"Av Portugal(pol I Salinas), 2",
    "sg:city":"Alhama Murcia",
    "sg:orig_category":"Suministros Y Materiales Industriales",
    "sg:phone":"+34 968 63 60 09",
    "sg:postcode":"30840",
    "sg:province":"Murcia",
    "wof:name":"Hidrotecnia De Componentes S.l.",
    "wof:placetype":"venue"
},
  "geometry": {"coordinates":[-1.3929569721,37.8227539062],"type":"Point"}
}