{
  "type": "Feature",
  "properties": {
    "iso:country":"ES",
    "sg:address":"Carrer de Renclusa, 17",
    "sg:city":"Hospitalet Llobregat",
    "sg:orig_category":"Empresas De Pintura Y Revestimientos",
    "sg:phone":"+34 934 38 73 68",
    "sg:postcode":"08905",
    "sg:province":"Barcelona",
    "wof:name":"Pinturas E Ignifugaciones S.l.",
    "wof:placetype":"venue"
},
  "geometry": {"coordinates":[2.1063420773,41.3711547852],"type":"Point"}
}