{
  "type": "Feature",
  "properties": {
    "addr:full":"Calle de Villar, 5 Zalamea Real Huelva 21640",
    "addr:housenumber":"5",
    "addr:postcode":"21640",
    "addr:street":"Calle De Villar",
    "iso:country":"ES",
    "sg:address":"Calle de Villar, 5",
    "sg:city":"Zalamea Real",
    "sg:orig_category":"Empresas De Pintura Y Revestimientos",
    "sg:phone":"+34 959 56 16 15",
    "sg:postcode":"21640",
    "sg:province":"Huelva",
    "wof:name":"Perea Castilla Manuel",
    "wof:placetype":"venue"
},
  "geometry": {"coordinates":[-6.6611003876,37.6814613342],"type":"Point"}
}