{
  "type": "Feature",
  "properties": {
    "iso:country":"ES",
    "sg:address":"Carrer de Alfons Sola, 22",
    "sg:city":"Caldes Montbui",
    "sg:orig_category":"Mec\u00c1nico Del Autom\u00d3vil",
    "sg:phone":"+34 938 65 14 23",
    "sg:postcode":"08140",
    "sg:province":"Barcelona",
    "wof:name":"Vila Serra Jaume",
    "wof:placetype":"venue"
},
  "geometry": {"coordinates":[2.1678669453,41.6313171387],"type":"Point"}
}