{
  "type": "Feature",
  "properties": {
    "iso:country":"ES",
    "sg:address":"Calle de Eustasio Amilibia, 4",
    "sg:city":"Donostia-san Sebastian",
    "sg:orig_category":"Encuadernaci\u00d3n E Impresi\u00d3n De Folletos",
    "sg:phone":"+34 943 45 41 96",
    "sg:postcode":"20011",
    "sg:province":"Guip\u00f9zcoa",
    "wof:name":"Marian Cancio Plaza",
    "wof:placetype":"venue"
},
  "geometry": {"coordinates":[-1.9759589434,43.3062858582],"type":"Point"}
}