{
  "type": "Feature",
  "properties": {
    "iso:country":"ES",
    "sg:address":"Avda Galicia, 141",
    "sg:city":"Zamora",
    "sg:orig_category":"Pintura, Barniz, Productos Asimilables (fabricaci\u00d3n, Al Por Mayor)",
    "sg:phone":"+34 980 51 65 63",
    "sg:postcode":"49024",
    "sg:province":"Zamora",
    "wof:name":"Peinador Galan Roberto",
    "wof:placetype":"venue"
},
  "geometry": {"coordinates":[-5.7538228035,41.5158195496],"type":"Point"}
}