{
  "type": "Feature",
  "properties": {
    "addr:full":"Trss Prat De La Riba, 79 S. Climent Llobregat Barcelona 08849",
    "addr:housenumber":"79",
    "addr:postcode":"08849",
    "addr:street":"La Riba;S. Climent Llobregat Barcelona",
    "iso:country":"ES",
    "sg:address":"Trss Prat De La Riba, 79",
    "sg:city":"S. Climent Llobregat",
    "sg:orig_category":"Pintura Industrial (trabajos De)",
    "sg:phone":"+34 936 37 35 12",
    "sg:postcode":"08849",
    "sg:province":"Barcelona",
    "wof:name":"Pinfer S.l.",
    "wof:placetype":"venue"
},
  "geometry": {"coordinates":[2.0027189255,41.3323440552],"type":"Point"}
}