{
  "type": "Feature",
  "properties": {
    "addr:full":"Castilla La Mancha(p I Zarate), S/n Peligros Granada 18210",
    "addr:housenumber":"s / n",
    "addr:postcode":"18210",
    "addr:street":"P I Zarate",
    "iso:country":"ES",
    "sg:address":"Castilla La Mancha(p I Zarate), S/n",
    "sg:city":"Peligros",
    "sg:orig_category":"Suministros Y Materiales Industriales",
    "sg:phone":"+34 958 40 10 74",
    "sg:postcode":"18210",
    "sg:province":"Granada",
    "sg:website":"www.ferreteria-nevada.com",
    "wof:name":"Ferreteria Industrial Nevada S.l.",
    "wof:placetype":"venue"
},
  "geometry": {"coordinates":[-3.6335589886,37.2246208191],"type":"Point"}
}