{
  "type": "Feature",
  "properties": {
    "addr:full":"Calle de Garcia Morato, 16 Navalmoral Mata C\u00e1ceres 10300",
    "addr:housenumber":"16",
    "addr:postcode":"10300",
    "addr:street":"Calle De Garcia Morato;Ca\u0301Ceres",
    "iso:country":"ES",
    "sg:address":"Calle de Garcia Morato, 16",
    "sg:city":"Navalmoral Mata",
    "sg:orig_category":"Mercer\u00cda, Lencer\u00cda (al Por Menor)",
    "sg:phone":"+34 927 53 09 31",
    "sg:postcode":"10300",
    "sg:province":"C\u00e1ceres",
    "wof:name":"Moreno Cobos Concepcion",
    "wof:placetype":"venue"
},
  "geometry": {"coordinates":[-5.5435872078,39.8912467957],"type":"Point"}
}