{
  "type": "Feature",
  "properties": {
    "addr:full":"Calle de Doctor Mugica, 27 Logro\u00f1o La Rioja 26002",
    "addr:housenumber":"27",
    "addr:postcode":"26002",
    "addr:street":"Calle De Doctor Mugica;Rioja",
    "iso:country":"ES",
    "sg:address":"Calle de Doctor Mugica, 27",
    "sg:city":"Logro\u00f1o",
    "sg:orig_category":"Peluquer\u00cdas, Peluquer\u00cda Mixta",
    "sg:phone":"+34 941 24 31 76",
    "sg:postcode":"26002",
    "sg:province":"La Rioja",
    "wof:name":"Ruiz Canales Sainz Maza Maria Bego\u00f1a",
    "wof:placetype":"venue"
},
  "geometry": {"coordinates":[-2.4510500431,42.4600410461],"type":"Point"}
}