{
  "type": "Feature",
  "properties": {
    "addr:full":"Carrer de Tajo, 25 Barcelona Barcelona 08031",
    "addr:housenumber":"25",
    "addr:postcode":"08031",
    "addr:street":"Carrer De Tajo",
    "iso:country":"ES",
    "sg:address":"Carrer de Tajo, 25",
    "sg:city":"Barcelona",
    "sg:orig_category":"Restaurantes",
    "sg:phone":"+34 933 57 03 77",
    "sg:postcode":"08031",
    "sg:province":"Barcelona",
    "wof:name":"Gaig Ventura S.c.p.",
    "wof:placetype":"venue"
},
  "geometry": {"coordinates":[2.1625850201,41.4299736023],"type":"Point"}
}