{
  "type": "Feature",
  "properties": {
    "addr:full":"Calle de Zarzuela, 10 Madrid Madrid 28044",
    "addr:housenumber":"10",
    "addr:postcode":"madrid;28044",
    "addr:street":"Calle De Zarzuela",
    "iso:country":"ES",
    "sg:address":"Calle de Zarzuela, 10",
    "sg:city":"Madrid",
    "sg:orig_category":"Molduras, Junquillos, Listones Y Molduras Perforadas",
    "sg:phone":"+34 915 08 92 80",
    "sg:postcode":"28044",
    "sg:province":"Madrid",
    "wof:name":"Hermanos Jimenez 2000 S. L.",
    "wof:placetype":"venue"
},
  "geometry": {"coordinates":[-3.7479119301,40.3710861206],"type":"Point"}
}