{
  "type": "Feature",
  "properties": {
    "addr:full":"Paseo Del Doctor Vigueras, 77 Siles Ja\u00e9n 23380",
    "addr:housenumber":"77",
    "addr:postcode":"23380",
    "addr:street":"Paseo Del Doctor Vigueras",
    "iso:country":"ES",
    "sg:address":"Paseo Del Doctor Vigueras, 77",
    "sg:city":"Siles",
    "sg:orig_category":"Obras Y Organismos Sociales",
    "sg:phone":"+34 953 49 04 00",
    "sg:postcode":"23380",
    "sg:province":"Ja\u00e9n",
    "wof:name":"Asilo Ancianos Nuestra Se\u00f1ora De Los Dolores",
    "wof:placetype":"venue"
},
  "geometry": {"coordinates":[-2.5787856579,38.3877487183],"type":"Point"}
}