{
  "type": "Feature",
  "properties": {
    "iso:country":"ES",
    "sg:address":"Calle de Domine, 1",
    "sg:city":"Motril",
    "sg:orig_category":"Medicamentos",
    "sg:phone":"+34 958 60 14 69",
    "sg:postcode":"18600",
    "sg:province":"Granada",
    "wof:name":"Yanguas Ruiz De La Fuente Miguel Juan",
    "wof:placetype":"venue"
},
  "geometry": {"coordinates":[-3.480134964,36.7527770996],"type":"Point"}
}