{
  "type": "Feature",
  "properties": {
    "addr:full":"Carrer de Alt De Mariner, 15 Barcelona Barcelona 08032",
    "addr:housenumber":"15",
    "addr:postcode":"08032",
    "addr:street":"Carrer De Alt De Mariner",
    "iso:country":"ES",
    "sg:address":"Carrer de Alt De Mariner, 15",
    "sg:city":"Barcelona",
    "sg:orig_category":"Asociaciones, Organismos Culturales Y Socioeducativos",
    "sg:phone":"+34 934 07 30 68",
    "sg:postcode":"08032",
    "sg:province":"Barcelona",
    "wof:name":"Fomento Hortense",
    "wof:placetype":"venue"
},
  "geometry": {"coordinates":[2.1595599651,41.4309234619],"type":"Point"}
}