{
  "type": "Feature",
  "properties": {
    "iso:country":"ES",
    "sg:address":"Rua Oporto, 24",
    "sg:city":"Vigo",
    "sg:orig_category":"Abogados",
    "sg:phone":"+34 986 22 85 14",
    "sg:postcode":"36201",
    "sg:province":"Pontevedra",
    "wof:name":"Coladas-guzman Larraya Carlos",
    "wof:placetype":"venue"
},
  "geometry": {"coordinates":[-8.7164163589,42.237323761],"type":"Point"}
}