{
  "type": "Feature",
  "properties": {
    "iso:country":"ES",
    "sg:address":"Calle de Camarena, 314",
    "sg:city":"Madrid",
    "sg:orig_category":"Herboristas (al Por Menor)",
    "sg:phone":"+34 917 17 10 59",
    "sg:postcode":"28047",
    "sg:province":"Madrid",
    "wof:name":"Parra Zazo Samuel De La",
    "wof:placetype":"venue"
},
  "geometry": {"coordinates":[-3.7579503059,40.3858642578],"type":"Point"}
}