{
  "type": "Feature",
  "properties": {
    "addr:full":"Carrer de Mig (del), S/n Tortosa Tarragona 43500",
    "addr:housenumber":"/ n",
    "addr:postcode":"43500",
    "addr:street":"Carrer De Mig Del S",
    "iso:country":"ES",
    "sg:address":"Carrer de Mig (del), S/n",
    "sg:city":"Tortosa",
    "sg:orig_category":"Formaci\u00d3n Continuada (variada)",
    "sg:phone":"+34 977 51 10 51",
    "sg:postcode":"43500",
    "sg:province":"Tarragona",
    "wof:name":"Institut Gaudi De La Construccio",
    "wof:placetype":"venue"
},
  "geometry": {"coordinates":[0.5245550275,40.8136558533],"type":"Point"}
}