{
  "type": "Feature",
  "properties": {
    "iso:country":"ES",
    "sg:address":"Calle de Oregano (del), 1",
    "sg:city":"Tres Cantos",
    "sg:orig_category":"Ense\u00d1anza Secundaria: Colegios Y Escuelas Privadas",
    "sg:phone":"+34 918 03 91 02",
    "sg:postcode":"28760",
    "sg:province":"Madrid",
    "wof:name":"Instituto De Bachillerato Pintor Antonio Lopez",
    "wof:placetype":"venue"
},
  "geometry": {"coordinates":[-3.7023980618,40.6020393372],"type":"Point"}
}