{
  "type": "Feature",
  "properties": {
    "addr:full":"Urb Las Palmas, 408 Voltants Montornes Castell\u00f3n 12560",
    "addr:housenumber":"408",
    "addr:postcode":"12560",
    "addr:street":"Urb Las Palmas;Castello\u0301N",
    "iso:country":"ES",
    "sg:address":"Urb Las Palmas, 408",
    "sg:city":"Voltants Montornes",
    "sg:orig_category":"Inmobiliaria (agencias)",
    "sg:phone":"+34 964 39 81 85",
    "sg:postcode":"12560",
    "sg:province":"Castell\u00f3n",
    "wof:name":"Gallen Dolz Juan Antonio",
    "wof:placetype":"venue"
},
  "geometry": {"coordinates":[-0.0360242017,39.9860687256],"type":"Point"}
}