{
  "type": "Feature",
  "properties": {
    "addr:full":"Calle de Ciruela, 25 Ciudad Real Ciudad Real 13001",
    "addr:housenumber":"25",
    "addr:postcode":"13001",
    "addr:street":"Calle De Ciruela",
    "iso:country":"ES",
    "sg:address":"Calle de Ciruela, 25",
    "sg:city":"Ciudad Real",
    "sg:orig_category":"Abogados",
    "sg:phone":"+34 926 25 26 11",
    "sg:postcode":"13001",
    "sg:province":"Ciudad Real",
    "wof:name":"Gomez-moran Etchat Alfonso",
    "wof:placetype":"venue"
},
  "geometry": {"coordinates":[-3.9275774956,38.9807548523],"type":"Point"}
}