{
  "type": "Feature",
  "properties": {
    "addr:full":"Ctra Berga, Km. 0002,7 S. Fruitos Bages Barcelona 08272",
    "addr:postcode":"08272",
    "addr:street":"Ctra Berga Km. 0002,7 S. Fruitos Bages Barcelona",
    "iso:country":"ES",
    "sg:address":"Ctra Berga, Km. 0002,7",
    "sg:city":"S. Fruitos Bages",
    "sg:orig_category":"Supermercados Y Hipermercados",
    "sg:phone":"+34 938 78 80 78",
    "sg:postcode":"08272",
    "sg:province":"Barcelona",
    "wof:name":"Supermercados Llobet S.a.",
    "wof:placetype":"venue"
},
  "geometry": {"coordinates":[1.8779350519,41.7520599365],"type":"Point"}
}