{
  "type": "Feature",
  "properties": {
    "addr:full":"Calle de Artes De Las, 4 Aviles Asturias 33402",
    "addr:postcode":"33402",
    "addr:street":"Calle De",
    "iso:country":"ES",
    "sg:address":"Calle de Artes De Las, 4",
    "sg:city":"Aviles",
    "sg:orig_category":"Asociaciones Y Clubs Deportivos",
    "sg:phone":"+34 985 54 21 55",
    "sg:postcode":"33402",
    "sg:province":"Asturias",
    "wof:name":"Deportes Vivac Aventura 2000 S.l.",
    "wof:placetype":"venue"
},
  "geometry": {"coordinates":[-5.9196696281,43.5525856018],"type":"Point"}
}