{
  "type": "Feature",
  "properties": {
    "iso:country":"ES",
    "sg:address":"Llanos De La Virgen, S/n",
    "sg:city":"Antas",
    "sg:orig_category":"Centros De Educaci\u00d3n Especial",
    "sg:phone":"+34 950 45 31 11",
    "sg:postcode":"04628",
    "sg:province":"Almer\u00eda",
    "wof:name":"Junta De Andalucia",
    "wof:placetype":"venue"
},
  "geometry": {"coordinates":[-1.9336980581,37.2501678467],"type":"Point"}
}