{
  "type": "Feature",
  "properties": {
    "addr:full":"Carrer de Ter, S/n Torello Barcelona 08570",
    "addr:housenumber":"s / n",
    "addr:postcode":"08570",
    "addr:street":"Carrer De Ter",
    "iso:country":"ES",
    "sg:address":"Carrer de Ter, S/n",
    "sg:city":"Torello",
    "sg:orig_category":"Art\u00cdculos Funerarios (al Por Menor)",
    "sg:phone":"+34 938 59 35 57",
    "sg:postcode":"08570",
    "sg:province":"Barcelona",
    "wof:name":"Serveis Funeraris Xicoy S. L.",
    "wof:placetype":"venue"
},
  "geometry": {"coordinates":[2.2575950623,42.0476264954],"type":"Point"}
}