{
  "type": "Feature",
  "properties": {
    "addr:full":"Calle de Carretera De Loja, S/n Velez-malaga M\u00e1laga 29700",
    "addr:housenumber":"s / n",
    "addr:postcode":"29700",
    "addr:street":"Calle De Carretera De Loja",
    "iso:country":"ES",
    "sg:address":"Calle de Carretera De Loja, S/n",
    "sg:city":"Velez-malaga",
    "sg:orig_category":"Granos Y Semillas (producci\u00d3n, Al Por Mayor)",
    "sg:phone":"+34 952 50 08 82",
    "sg:postcode":"29700",
    "sg:province":"M\u00e1laga",
    "wof:name":"Clause-tezier Iberica S.a",
    "wof:placetype":"venue"
},
  "geometry": {"coordinates":[-4.1004362106,36.7783088684],"type":"Point"}
}