{
  "type": "Feature",
  "properties": {
    "iso:country":"ES",
    "sg:address":"Carrer de Cantabria, 60",
    "sg:city":"Barcelona",
    "sg:orig_category":"Frutas, Legumbres Frescas Y Tempranas (al Por Menor)",
    "sg:phone":"+34 932 78 10 84",
    "sg:postcode":"08020",
    "sg:province":"Barcelona",
    "wof:name":"Galve Puerto Sebastian",
    "wof:placetype":"venue"
},
  "geometry": {"coordinates":[2.1986339092,41.4229354858],"type":"Point"}
}