{
  "type": "Feature",
  "properties": {
    "addr:full":"Cmno Palomares, 15 Valladolid Valladolid 47011",
    "addr:housenumber":"15",
    "addr:postcode":"47011",
    "addr:street":"Cmno Palomares",
    "iso:country":"ES",
    "sg:address":"Cmno Palomares, 15",
    "sg:city":"Valladolid",
    "sg:orig_category":"Empresas De Pintura Y Revestimientos",
    "sg:phone":"+34 983 26 29 04",
    "sg:postcode":"47011",
    "sg:province":"Valladolid",
    "wof:name":"Piedras Losada Miguel Angel",
    "wof:placetype":"venue"
},
  "geometry": {"coordinates":[-4.6942858696,41.6653938293],"type":"Point"}
}