{
  "type": "Feature",
  "properties": {
    "addr:full":"Calle de Alcaide, 6 Lucena C\u00f3rdoba 14900",
    "addr:housenumber":"6",
    "addr:postcode":"14900",
    "addr:street":"Calle De Alcaide",
    "iso:country":"ES",
    "sg:address":"Calle de Alcaide, 6",
    "sg:city":"Lucena",
    "sg:orig_category":"Freidur\u00cdas: Equipos Y Suministros",
    "sg:phone":"+34 957 50 27 83",
    "sg:postcode":"14900",
    "sg:province":"C\u00f3rdoba",
    "wof:name":"Burguillos Cuevas Manuel",
    "wof:placetype":"venue"
},
  "geometry": {"coordinates":[-4.4855895042,37.4097824097],"type":"Point"}
}