{
  "type": "Feature",
  "properties": {
    "addr:full":"Avda Coru\u00d1a, 9 Cambados Pontevedra 36630",
    "addr:housenumber":"9",
    "addr:postcode":"36630",
    "addr:street":"Avda Corun\u0303A",
    "iso:country":"ES",
    "sg:address":"Avda Coru\u00d1a, 9",
    "sg:city":"Cambados",
    "sg:orig_category":"Bibliotecas, Mediatecas",
    "sg:phone":"+34 986 52 00 08",
    "sg:postcode":"36630",
    "sg:province":"Pontevedra",
    "wof:name":"Concello De Cambados",
    "wof:placetype":"venue"
},
  "geometry": {"coordinates":[-8.8149442673,42.5201339722],"type":"Point"}
}