{
  "type": "Feature",
  "properties": {
    "addr:full":"Plaz Puerta Cerrada, 7 Madrid Madrid 28005",
    "addr:housenumber":"7",
    "addr:postcode":"madrid;28005",
    "addr:street":"Cerrada",
    "iso:country":"ES",
    "sg:address":"Plaz Puerta Cerrada, 7",
    "sg:city":"Madrid",
    "sg:orig_category":"Molduras, Junquillos, Listones Y Molduras Perforadas",
    "sg:phone":"+34 913 66 42 99",
    "sg:postcode":"28005",
    "sg:province":"Madrid",
    "wof:name":"Romero Rodriguez Vicente",
    "wof:placetype":"venue"
},
  "geometry": {"coordinates":[-3.7088370323,40.413734436],"type":"Point"}
}