{
  "type": "Feature",
  "properties": {
    "addr:full":"Calle de Islas Cies, 9 Alcorcon Madrid 28924",
    "addr:housenumber":"9",
    "addr:postcode":"28924",
    "addr:street":"Calle De Islas Cies",
    "iso:country":"ES",
    "sg:address":"Calle de Islas Cies, 9",
    "sg:city":"Alcorcon",
    "sg:orig_category":"Agencias Y Agentes Comerciales, Representantes",
    "sg:phone":"+34 916 19 20 93",
    "sg:postcode":"28924",
    "sg:province":"Madrid",
    "wof:name":"Reguillo Calero Rafael",
    "wof:placetype":"venue"
},
  "geometry": {"coordinates":[-3.8085119724,40.3441810608],"type":"Point"}
}