{
  "type": "Feature",
  "properties": {
    "addr:full":"Carrer de Miramarges, 6 Vic Barcelona 08500",
    "addr:housenumber":"6",
    "addr:postcode":"08500",
    "addr:street":"Carrer De Miramarges",
    "iso:country":"ES",
    "sg:address":"Carrer de Miramarges, 6",
    "sg:city":"Vic",
    "sg:orig_category":"Institutos De Belleza",
    "sg:phone":"+34 938 86 41 03",
    "sg:postcode":"08500",
    "sg:province":"Barcelona",
    "wof:name":"Natur Estetic Carme I Cristina",
    "wof:placetype":"venue"
},
  "geometry": {"coordinates":[2.2481460571,41.9330406189],"type":"Point"}
}