{
  "type": "Feature",
  "properties": {
    "addr:full":"Avda Arsenio Iglesias, 1 Arteixo La Coru\u00f1a 15142",
    "addr:housenumber":"1",
    "addr:postcode":"15142",
    "addr:street":"Avda Arsenio Iglesias;La Corun\u0303A",
    "iso:country":"ES",
    "sg:address":"Avda Arsenio Iglesias, 1",
    "sg:city":"Arteixo",
    "sg:orig_category":"Guarder\u00cdas",
    "sg:phone":"+34 981 60 15 25",
    "sg:postcode":"15142",
    "sg:province":"La Coru\u00f1a",
    "wof:name":"Escuela Infantil Trasnos S.l.",
    "wof:placetype":"venue"
},
  "geometry": {"coordinates":[-8.5100641251,43.3119812012],"type":"Point"}
}