{
  "type": "Feature",
  "properties": {
    "addr:full":"Carr Bergada, 2 Solsona Lleida 25280",
    "addr:housenumber":"2",
    "addr:postcode":"25280",
    "addr:street":"Carr Bergada",
    "iso:country":"ES",
    "sg:address":"Carr Bergada, 2",
    "sg:city":"Solsona",
    "sg:orig_category":"Ense\u00d1anza Agr\u00cdcola",
    "sg:phone":"+34 973 48 38 33",
    "sg:postcode":"25280",
    "sg:province":"Lleida",
    "wof:name":"Nou-set Del Solsones S.l.",
    "wof:placetype":"venue"
},
  "geometry": {"coordinates":[1.5206480026,41.9950942993],"type":"Point"}
}