{
  "type": "Feature",
  "properties": {
    "addr:full":"Vilar De Toba, S/n Vilar De Toba La Coru\u00f1a 15270",
    "addr:housenumber":"s / n",
    "addr:postcode":"15270",
    "addr:street":"Corun\u0303A",
    "iso:country":"ES",
    "sg:address":"Vilar De Toba, S/n",
    "sg:city":"Vilar De Toba",
    "sg:orig_category":"Electricidad: Instaladores",
    "sg:phone":"+34 981 74 76 05",
    "sg:postcode":"15270",
    "sg:province":"La Coru\u00f1a",
    "wof:name":"Quintans Romero Jesus Ramon",
    "wof:placetype":"venue"
},
  "geometry": {"coordinates":[-9.187494278,42.9554710388],"type":"Point"}
}