{
  "type": "Feature",
  "properties": {
    "addr:full":"Av Verge De Montserrat, 162 Barbera Valles Barcelona 08210",
    "addr:housenumber":"162",
    "addr:postcode":"08210",
    "addr:street":"Av Verge De Montserrat",
    "iso:country":"ES",
    "sg:address":"Av Verge De Montserrat, 162",
    "sg:city":"Barbera Valles",
    "sg:orig_category":"Laboratorios Y Trabajos De Fotograf\u00cda, V\u00cddeo Y Cine",
    "sg:phone":"+34 937 29 43 56",
    "sg:postcode":"08210",
    "sg:province":"Barcelona",
    "wof:name":"Mu\u00f1oz Montoro Juan",
    "wof:placetype":"venue"
},
  "geometry": {"coordinates":[2.1207098961,41.5165214539],"type":"Point"}
}