{
  "type": "Feature",
  "properties": {
    "iso:country":"ES",
    "sg:address":"Calle de Santiago, 5",
    "sg:city":"Sang\u00fcesa",
    "sg:orig_category":"\u00d3ptica: Instrumentos (fabricaci\u00d3n)",
    "sg:phone":"+34 948 43 04 51",
    "sg:postcode":"31400",
    "sg:province":"Navarra",
    "wof:name":"Eduardo Ladron De Guevara Y Otros C.b.",
    "wof:placetype":"venue"
},
  "geometry": {"coordinates":[-1.2829320431,42.5753097534],"type":"Point"}
}