{
  "type": "Feature",
  "properties": {
    "addr:full":"Carrer de Parellada (la), 19 Vilafranca Penedes Barcelona 08720",
    "addr:housenumber":"19",
    "addr:postcode":"08720",
    "addr:street":"Carrer De Parellada La;Penedes Barcelona",
    "iso:country":"ES",
    "sg:address":"Carrer de Parellada (la), 19",
    "sg:city":"Vilafranca Penedes",
    "sg:orig_category":"Muebles, Minoristas",
    "sg:phone":"+34 938 92 05 67",
    "sg:postcode":"08720",
    "sg:province":"Barcelona",
    "wof:name":"Mobles Feliu Scp",
    "wof:placetype":"venue"
},
  "geometry": {"coordinates":[1.6992379427,41.3467521667],"type":"Point"}
}