{
  "type": "Feature",
  "properties": {
    "addr:full":"Calle de Nueve De Febrero, 8 Le\u00f3n Le\u00f3n 24005",
    "addr:housenumber":"8",
    "addr:postcode":"24005",
    "addr:street":"Calle De Nueve De Febrero;Leo\u0301N",
    "iso:country":"ES",
    "sg:address":"Calle de Nueve De Febrero, 8",
    "sg:city":"Le\u00f3n",
    "sg:orig_category":"Quincaller\u00cda (al Por Menor)",
    "sg:phone":"+34 987 20 98 20",
    "sg:postcode":"24005",
    "sg:province":"Le\u00f3n",
    "wof:name":"Gonzalez Gonzalez Maria Mercedes",
    "wof:placetype":"venue"
},
  "geometry": {"coordinates":[-5.5678339005,42.5880432129],"type":"Point"}
}