{
  "type": "Feature",
  "properties": {
    "addr:full":"Cuarenta Y Cuatro(pol Industrial), 27 Catarroja Valencia 46470",
    "addr:housenumber":"27",
    "addr:postcode":"46470",
    "addr:street":"Industrial",
    "iso:country":"ES",
    "sg:address":"Cuarenta Y Cuatro(pol Industrial), 27",
    "sg:city":"Catarroja",
    "sg:orig_category":"Chapister\u00cda",
    "sg:phone":"+34 961 27 04 39",
    "sg:postcode":"46470",
    "sg:province":"Valencia",
    "wof:name":"Autos Esteval S.l",
    "wof:placetype":"venue"
},
  "geometry": {"coordinates":[-0.397258997,39.3964653015],"type":"Point"}
}