{
  "type": "Feature",
  "properties": {
    "addr:full":"Pque Libertad La, 3 Union Las Palmas 35110",
    "addr:postcode":"35110",
    "addr:street":"La 3",
    "iso:country":"ES",
    "sg:address":"Pque Libertad La, 3",
    "sg:city":"Union",
    "sg:orig_category":"Panader\u00cdas, Panader\u00cdas",
    "sg:phone":"+34 928 79 27 42",
    "sg:postcode":"35110",
    "sg:province":"Las Palmas",
    "wof:name":"Flor Isle\u00f1a S.l.",
    "wof:placetype":"venue"
},
  "geometry": {"coordinates":[-15.4485340118,27.8392906189],"type":"Point"}
}