{
  "type": "Feature",
  "properties": {
    "iso:country":"ES",
    "sg:address":"Calle de Principe, 12",
    "sg:city":"Madrid",
    "sg:orig_category":"Partidos Pol\u00cdticos",
    "sg:phone":"+34 915 22 40 04",
    "sg:postcode":"28012",
    "sg:province":"Madrid",
    "wof:name":"Falange Espa\u00f1onla Independiente",
    "wof:placetype":"venue"
},
  "geometry": {"coordinates":[-3.7004880905,40.415599823],"type":"Point"}
}