{
  "type": "Feature",
  "properties": {
    "iso:country":"ES",
    "sg:address":"Calle de Obreros, 4",
    "sg:city":"Boveda Toro",
    "sg:orig_category":"Molduras, Junquillos, Listones Y Molduras Perforadas",
    "sg:phone":"+34 980 60 22 47",
    "sg:postcode":"49155",
    "sg:province":"Zamora",
    "wof:name":"Francisco Rodriguez Patricio",
    "wof:placetype":"venue"
},
  "geometry": {"coordinates":[-5.4101748466,41.3418502808],"type":"Point"}
}