{
  "type": "Feature",
  "properties": {
    "addr:full":"Carrer de Tomas Ortu\u00d1o, 1 Benidorm Alicante 03500",
    "addr:housenumber":"1",
    "addr:postcode":"03500",
    "addr:street":"Carrer De Tomas Ortun\u0303O",
    "iso:country":"ES",
    "sg:address":"Carrer de Tomas Ortu\u00d1o, 1",
    "sg:city":"Benidorm",
    "sg:orig_category":"Art\u00cdculos De Regalo (al Por Menor)",
    "sg:phone":"+34 965 85 54 88",
    "sg:postcode":"03500",
    "sg:province":"Alicante",
    "wof:name":"Calvo Carrion Alberto",
    "wof:placetype":"venue"
},
  "geometry": {"coordinates":[-0.1308829933,38.5370674133],"type":"Point"}
}