{
  "type": "Feature",
  "properties": {
    "iso:country":"ES",
    "sg:address":"Calle de Pasos, 25",
    "sg:city":"Argamasilla Alba",
    "sg:orig_category":"Peluquer\u00cdas, Peluquer\u00cda Mixta",
    "sg:phone":"+34 926 52 23 44",
    "sg:postcode":"13710",
    "sg:province":"Ciudad Real",
    "wof:name":"La Peluqueria C.b.",
    "wof:placetype":"venue"
},
  "geometry": {"coordinates":[-3.1014740467,39.1252174377],"type":"Point"}
}