{
  "type": "Feature",
  "properties": {
    "iso:country":"ES",
    "sg:address":"Calle de Principe Felipe, S/n",
    "sg:city":"Espartinas",
    "sg:orig_category":"Inmobiliaria (agencias)",
    "sg:phone":"+34 955 70 47 40",
    "sg:postcode":"41807",
    "sg:province":"Sevilla",
    "wof:name":"Grupo Vazquez Monsalve S.l.",
    "wof:placetype":"venue"
},
  "geometry": {"coordinates":[-6.1291341782,37.3784065247],"type":"Point"}
}