{
  "type": "Feature",
  "properties": {
    "addr:full":"Calle de Concejal Garcia Feo, 13 Palmas De Gran Canaria Las Palmas 35011",
    "addr:postcode":"35011",
    "addr:street":"Calle De Concejal Garcia Feo 13",
    "iso:country":"ES",
    "sg:address":"Calle de Concejal Garcia Feo, 13",
    "sg:city":"Palmas De Gran Canaria",
    "sg:orig_category":"Inform\u00c1tica, Ofim\u00c1tica (estudios, Asesor\u00cda, Ingenier\u00cda, Formaci\u00d3n)",
    "sg:phone":"+34 928 28 03 78",
    "sg:postcode":"35011",
    "sg:province":"Las Palmas",
    "wof:name":"Servicios Informaticos Canarios C.coop.",
    "wof:placetype":"venue"
},
  "geometry": {"coordinates":[-15.4387073517,28.1223621368],"type":"Point"}
}