{
  "type": "Feature",
  "properties": {
    "addr:full":"Ctra Madrid, Km. 0381,8 Molina Segura Murcia 30500",
    "addr:postcode":"30500",
    "addr:street":"Ctra Madrid Km. 0381,8 Molina",
    "iso:country":"ES",
    "sg:address":"Ctra Madrid, Km. 0381,8",
    "sg:city":"Molina Segura",
    "sg:orig_category":"Artes Gr\u00c1ficas, Artes Pl\u00c1sticas (curso)",
    "sg:phone":"+34 968 64 37 50",
    "sg:postcode":"30500",
    "sg:province":"Murcia",
    "sg:website":"www.artemol.com",
    "wof:name":"Graficas Artemol S.l.",
    "wof:placetype":"venue"
},
  "geometry": {"coordinates":[-1.2119740248,38.0535736084],"type":"Point"}
}