{
  "type": "Feature",
  "properties": {
    "iso:country":"ES",
    "sg:address":"Praz Inmaculada (da), S/n",
    "sg:city":"Santiago De Compostela",
    "sg:orig_category":"Dorados, Plater\u00cda (orfebrer\u00cda)",
    "sg:phone":"+34 981 58 23 26",
    "sg:postcode":"15704",
    "sg:province":"A Coru\u00f1a",
    "wof:name":"Vieiro Bao Augusto",
    "wof:placetype":"venue"
},
  "geometry": {"coordinates":[-8.5443935394,42.8811416626],"type":"Point"}
}