{
  "type": "Feature",
  "properties": {
    "addr:full":"Ctra Montoro-puente Genil, 1 Aguilar De La Frontera C\u00f3rdoba 14920",
    "addr:housenumber":"1",
    "addr:postcode":"14920",
    "addr:street":"Ctra Montoro-Puente Genil",
    "iso:country":"ES",
    "sg:address":"Ctra Montoro-puente Genil, 1",
    "sg:city":"Aguilar De La Frontera",
    "sg:orig_category":"Estancos",
    "sg:phone":"+34 957 66 09 91",
    "sg:postcode":"14920",
    "sg:province":"C\u00f3rdoba",
    "wof:name":"Pavon Albala Miguel",
    "wof:placetype":"venue"
},
  "geometry": {"coordinates":[-4.6576538086,37.5145149231],"type":"Point"}
}