{
  "type": "Feature",
  "properties": {
    "iso:country":"ES",
    "sg:address":"Calle de Cebolla, 33",
    "sg:city":"Erustes",
    "sg:orig_category":"Desinfecci\u00d3n, Desinsectaci\u00d3n, Desratizaci\u00d3n",
    "sg:phone":"+34 925 88 01 20",
    "sg:postcode":"45540",
    "sg:province":"Toledo",
    "wof:name":"Alvi S.l",
    "wof:placetype":"venue"
},
  "geometry": {"coordinates":[-4.4996609688,39.9556541443],"type":"Point"}
}