{
  "type": "Feature",
  "properties": {
    "iso:country":"ES",
    "sg:address":"Calle de Calatrava, 17",
    "sg:city":"Ciudad Real",
    "sg:orig_category":"Panader\u00cdas, Panader\u00cdas",
    "sg:phone":"+34 926 22 08 13",
    "sg:postcode":"13003",
    "sg:province":"Ciudad Real",
    "wof:name":"Guijarro Ayllon Tomas",
    "wof:placetype":"venue"
},
  "geometry": {"coordinates":[-3.9263432026,38.9881744385],"type":"Point"}
}