{
  "type": "Feature",
  "properties": {
    "iso:country":"ES",
    "sg:address":"Carrer de Pare Artigas, 14",
    "sg:city":"Viladecans",
    "sg:orig_category":"Partidos Pol\u00cdticos",
    "sg:phone":"+34 936 58 57 68",
    "sg:postcode":"08840",
    "sg:province":"Barcelona",
    "wof:name":"Esquerra Republicana De Catalunya",
    "wof:placetype":"venue"
},
  "geometry": {"coordinates":[2.0176320076,41.3179702759],"type":"Point"}
}