{
  "type": "Feature",
  "properties": {
    "iso:country":"ES",
    "sg:address":"Avda Fernando Conde, 34",
    "sg:city":"Estrada",
    "sg:orig_category":"Estilistas Y Estudios De Estilo De Corte Y Confecci\u00d3n",
    "sg:phone":"+34 986 57 01 81",
    "sg:postcode":"36680",
    "sg:province":"Pontevedra",
    "wof:name":"Maria Jose Vicente Buendia S.l.",
    "wof:placetype":"venue"
},
  "geometry": {"coordinates":[-8.4831228256,42.6898345947],"type":"Point"}
}