{
  "type": "Feature",
  "properties": {
    "iso:country":"ES",
    "sg:address":"Carrer de Rosari, 37",
    "sg:city":"Barcelona",
    "sg:orig_category":"Peluqueros: De Se\u00d1oras",
    "sg:phone":"+34 932 80 64 64",
    "sg:postcode":"08017",
    "sg:province":"Barcelona",
    "wof:name":"Sauri Vidal Maria Del Carmen",
    "wof:placetype":"venue"
},
  "geometry": {"coordinates":[2.1308200359,41.3972663879],"type":"Point"}
}