{
  "type": "Feature",
  "properties": {
    "addr:full":"Calle de Fernandez De Los Rios, 29 Madrid Madrid 28015",
    "addr:housenumber":"29",
    "addr:postcode":"madrid;28015",
    "addr:street":"Calle De Fernandez De Los Rios",
    "iso:country":"ES",
    "sg:address":"Calle de Fernandez De Los Rios, 29",
    "sg:city":"Madrid",
    "sg:orig_category":"Fabricaci\u00d3n De Peines Y De Accesorios De Peluquer\u00cda",
    "sg:phone":"+34 915 93 13 69",
    "sg:postcode":"28015",
    "sg:province":"Madrid",
    "wof:name":"Dizma S.l.",
    "wof:placetype":"venue"
},
  "geometry": {"coordinates":[-3.7080790997,40.4349403381],"type":"Point"}
}