{
  "type": "Feature",
  "properties": {
    "iso:country":"ES",
    "sg:address":"Calle de Nueva, 8",
    "sg:city":"Quesada",
    "sg:orig_category":"Tapiceros Y Tapiceros",
    "sg:phone":"+34 953 73 30 00",
    "sg:postcode":"23480",
    "sg:province":"Ja\u00e9n",
    "wof:name":"Bueno Soria Carlos",
    "wof:placetype":"venue"
},
  "geometry": {"coordinates":[-3.0678958893,37.8462028503],"type":"Point"}
}