{
  "type": "Feature",
  "properties": {
    "iso:country":"ES",
    "sg:address":"Avda Suecia (de), S/n",
    "sg:city":"Cristianos",
    "sg:orig_category":"Supermercados Y Hipermercados",
    "sg:phone":"+34 922 79 14 19",
    "sg:postcode":"38650",
    "sg:province":"Santa Cruz De Tenerife",
    "wof:name":"Gonzalez Cano Nicanor",
    "wof:placetype":"venue"
},
  "geometry": {"coordinates":[-16.7205696106,28.0513744354],"type":"Point"}
}