{
  "type": "Feature",
  "properties": {
    "iso:country":"ES",
    "sg:address":"Calle de Resina, 41",
    "sg:city":"Madrid",
    "sg:orig_category":"Inform\u00c1tica (estudios, Servicios, Asesor\u00cda, Formaci\u00d3n)",
    "sg:phone":"+34 917 98 85 75",
    "sg:postcode":"28021",
    "sg:province":"Madrid",
    "wof:name":"Antares Hardware S.l.u.",
    "wof:placetype":"venue"
},
  "geometry": {"coordinates":[-3.7058622837,40.335811615],"type":"Point"}
}