{
  "type": "Feature",
  "properties": {
    "addr:full":"C/ Miquel Salva, 49 Llucmajor Islas Baleares 07620",
    "addr:housenumber":"49",
    "addr:postcode":"07620",
    "addr:street":"C / Miquel Salva",
    "iso:country":"ES",
    "sg:address":"C/ Miquel Salva, 49",
    "sg:city":"Llucmajor",
    "sg:orig_category":"Mec\u00c1nico Del Autom\u00d3vil",
    "sg:phone":"+34 971 66 24 50",
    "sg:postcode":"07620",
    "sg:province":"Islas Baleares",
    "wof:name":"Salas Pons Miguel",
    "wof:placetype":"venue"
},
  "geometry": {"coordinates":[2.8928198814,39.4852409363],"type":"Point"}
}