{
  "type": "Feature",
  "properties": {
    "iso:country":"ES",
    "sg:address":"Calle de Mayor, 102",
    "sg:city":"Cari\u00f1ena",
    "sg:orig_category":"Molduras, Junquillos, Listones Y Molduras Perforadas",
    "sg:phone":"+34 976 62 02 95",
    "sg:postcode":"50400",
    "sg:province":"Zaragoza",
    "wof:name":"Baguena Marques Ana Maria",
    "wof:placetype":"venue"
},
  "geometry": {"coordinates":[-1.2240332365,41.3364448547],"type":"Point"}
}