{
  "type": "Feature",
  "properties": {
    "addr:full":"Barrio Las Higueras, S/n Soto Marina Cantabria 39110",
    "addr:housenumber":"/ n",
    "addr:postcode":"39110",
    "addr:street":"Barrio Las Higueras S",
    "iso:country":"ES",
    "sg:address":"Barrio Las Higueras, S/n",
    "sg:city":"Soto Marina",
    "sg:orig_category":"Aguas (distribuci\u00d3n, Servicios)",
    "sg:phone":"+34 942 58 79 29",
    "sg:postcode":"39110",
    "sg:province":"Cantabria",
    "sg:website":"www.aqualia.es",
    "wof:name":"Aqualia Gestion Integral Del Agua S.a.",
    "wof:placetype":"venue"
},
  "geometry": {"coordinates":[-3.7333536148,43.4133415222],"type":"Point"}
}