{
  "type": "Feature",
  "properties": {
    "iso:country":"ES",
    "sg:address":"Carrer de Maria Vidal (de), 73",
    "sg:city":"Vilassar De Mar",
    "sg:orig_category":"Mec\u00c1nico Del Autom\u00d3vil",
    "sg:phone":"+34 937 59 47 55",
    "sg:postcode":"08340",
    "sg:province":"Barcelona",
    "wof:name":"Soria Luna Jorge",
    "wof:placetype":"venue"
},
  "geometry": {"coordinates":[2.3879899979,41.5020217896],"type":"Point"}
}