{
  "type": "Feature",
  "properties": {
    "iso:country":"ES",
    "sg:address":"Calle de Juan Xxiii, 7",
    "sg:city":"Madrigueras",
    "sg:orig_category":"Mec\u00c1nico Del Autom\u00d3vil",
    "sg:phone":"+34 967 48 40 47",
    "sg:postcode":"02230",
    "sg:province":"Albacete",
    "wof:name":"Fuentes Fuentes Octaviano",
    "wof:placetype":"venue"
},
  "geometry": {"coordinates":[-1.8021329641,39.2333869934],"type":"Point"}
}