{
  "type": "Feature",
  "properties": {
    "addr:full":"Calle de Rio Corrientes, 4 Madrid Madrid 28018",
    "addr:housenumber":"4",
    "addr:postcode":"28018",
    "addr:street":"Calle De Rio Corrientes",
    "iso:country":"ES",
    "sg:address":"Calle de Rio Corrientes, 4",
    "sg:city":"Madrid",
    "sg:orig_category":"Inform\u00c1tica: Mantenimiento Y Reparaci\u00d3n De Ordenadores",
    "sg:phone":"+34 913 80 88 12",
    "sg:postcode":"28018",
    "sg:province":"Madrid",
    "sg:website":"www.edysel.com",
    "wof:name":"Empresas De Apoyo Reparaciones Y Servici",
    "wof:placetype":"venue"
},
  "geometry": {"coordinates":[-3.6517369747,40.385307312],"type":"Point"}
}