{
  "type": "Feature",
  "properties": {
    "iso:country":"ES",
    "sg:address":"Calle de Rio Perejiles, 2",
    "sg:city":"Zaragoza",
    "sg:orig_category":"Centros De Educaci\u00d3n Especial",
    "sg:phone":"+34 976 57 28 38",
    "sg:postcode":"50014",
    "sg:province":"Zaragoza",
    "wof:name":"Colegio Publico Gloria Arenillas",
    "wof:placetype":"venue"
},
  "geometry": {"coordinates":[-0.8442360163,41.668422699],"type":"Point"}
}