{
  "type": "Feature",
  "properties": {
    "addr:full":"Ptge El Noi Del Sucre, 9 Santa Perpetua De Mogoda Barcelona 08130",
    "addr:housenumber":"9",
    "addr:postcode":"08130",
    "addr:street":"Ptge El Noi Del Sucre",
    "iso:country":"ES",
    "sg:address":"Ptge El Noi Del Sucre, 9",
    "sg:city":"Santa Perpetua De Mogoda",
    "sg:orig_category":"Frutas Y Legumbres Frescas (al Por Mayor)",
    "sg:phone":"+34 935 44 97 22",
    "sg:postcode":"08130",
    "sg:province":"Barcelona",
    "wof:name":"Bonsuc S.l.",
    "wof:placetype":"venue"
},
  "geometry": {"coordinates":[2.1802799702,41.5371818542],"type":"Point"}
}