{
  "type": "Feature",
  "properties": {
    "addr:full":"Carrer de Corsega, 262 Barcelona Barcelona 08008",
    "addr:housenumber":"262",
    "addr:postcode":"08008",
    "addr:street":"Carrer De Corsega",
    "iso:country":"ES",
    "sg:address":"Carrer de Corsega, 262",
    "sg:city":"Barcelona",
    "sg:orig_category":"Inmobiliaria (agencias)",
    "sg:phone":"+34 932 18 79 17",
    "sg:postcode":"08008",
    "sg:province":"Barcelona",
    "wof:name":"C.p.invest S.l.",
    "wof:placetype":"venue"
},
  "geometry": {"coordinates":[2.1560029984,41.3938293457],"type":"Point"}
}