{
  "type": "Feature",
  "properties": {
    "iso:country":"ES",
    "sg:address":"Pintor Pablo Picasso, 6",
    "sg:city":"Puente Tocinos",
    "sg:classifiers":[
        {
            "category":"Autos & Motor Vehicles",
            "subcategory":"Automobile Sales",
            "type":"Retail Goods"
        }
    ],
    "sg:phone":"+34 968 30 15 77",
    "sg:postcode":"30006",
    "sg:province":"Murcia",
    "wof:name":"Tomas Roca Jose",
    "wof:placetype":"venue"
},
  "geometry": {"coordinates":[-1.0970890522,37.9950065613],"type":"Point"}
}