{
  "type": "Feature",
  "properties": {
    "iso:country":"ES",
    "sg:address":"Poli Poligono Industrial Quemadas, S/n",
    "sg:city":"Quemadas",
    "sg:orig_category":"Electrodom\u00c9sticos (al Por Menor)",
    "sg:phone":"+34 957 22 90 00",
    "sg:postcode":"14014",
    "sg:province":"C\u00f3rdoba",
    "sg:website":"www.urende.es",
    "wof:name":"Urende S.a.",
    "wof:placetype":"venue"
},
  "geometry": {"coordinates":[-4.7624139786,37.9240608215],"type":"Point"}
}