{
  "type": "Feature",
  "properties": {
    "addr:full":"Plaz Union Sport De San Vicente, 1 San Vicente De Barakaldo Vizcaya 48902",
    "addr:housenumber":"1",
    "addr:postcode":"48902",
    "addr:street":"San Vicente",
    "iso:country":"ES",
    "sg:address":"Plaz Union Sport De San Vicente, 1",
    "sg:city":"San Vicente De Barakaldo",
    "sg:orig_category":"Peluquer\u00cdas, Peluquer\u00cda Mixta",
    "sg:phone":"+34 944 18 94 96",
    "sg:postcode":"48902",
    "sg:province":"Vizcaya",
    "wof:name":"Sanchez Blanco Ainhoa",
    "wof:placetype":"venue"
},
  "geometry": {"coordinates":[-2.9961938858,43.2949523926],"type":"Point"}
}