{
  "type": "Feature",
  "properties": {
    "iso:country":"ES",
    "sg:address":"Calle de Alemania, 8",
    "sg:city":"Valencia",
    "sg:orig_category":"Artes Gr\u00c1ficas, Artes Pl\u00c1sticas: Material Y Suministros (al Por Menor)",
    "sg:phone":"+34 963 69 74 32",
    "sg:postcode":"46010",
    "sg:province":"Valencia",
    "wof:name":"Piera Pons Luis",
    "wof:placetype":"venue"
},
  "geometry": {"coordinates":[-0.3616231978,39.4816055298],"type":"Point"}
}