{
  "type": "Feature",
  "properties": {
    "iso:country":"ES",
    "sg:address":"Calle de Alboraya, 16",
    "sg:city":"Valencia",
    "sg:orig_category":"Fabricaci\u00d3n, Importaci\u00d3n De L\u00c1mparas Y Bombillas",
    "sg:phone":"+34 963 62 79 56",
    "sg:postcode":"46010",
    "sg:province":"Valencia",
    "wof:name":"Zaycu S. L.",
    "wof:placetype":"venue"
},
  "geometry": {"coordinates":[-0.3708499968,39.4810218811],"type":"Point"}
}