{
  "type": "Feature",
  "properties": {
    "iso:country":"ES",
    "sg:address":"Pol. Peri 11, S/n",
    "sg:city":"Castello Plana",
    "sg:orig_category":"Transporte En General",
    "sg:phone":"+34 964 24 06 85",
    "sg:postcode":"12004",
    "sg:province":"Castell\u00f3n",
    "wof:name":"Segura Belles Jose",
    "wof:placetype":"venue"
},
  "geometry": {"coordinates":[-0.0395839997,40.0097999573],"type":"Point"}
}