{
  "type": "Feature",
  "properties": {
    "iso:country":"ES",
    "sg:address":"Carmen Martin Gaite, 3",
    "sg:city":"Rivas Vaciamadrid",
    "sg:orig_category":"Empresas De Portes Y Mensajer\u00cda",
    "sg:phone":"+34 916 66 33 23",
    "sg:postcode":"28529",
    "sg:province":"Madrid",
    "wof:name":"Zalaya Baez Juan Pablo",
    "wof:placetype":"venue"
},
  "geometry": {"coordinates":[-3.5312683582,40.3484687805],"type":"Point"}
}