{
  "type": "Feature",
  "properties": {
    "addr:full":"Carrer de Torrent De Mada, S/n Cros Barcelona 08310",
    "addr:housenumber":"s / n",
    "addr:postcode":"08310",
    "addr:street":"Carrer De Torrent De Mada",
    "iso:country":"ES",
    "sg:address":"Carrer de Torrent De Mada, S/n",
    "sg:city":"Cros",
    "sg:orig_category":"Confecci\u00d3n De Trajes Para Se\u00d1oras",
    "sg:phone":"+34 937 98 09 69",
    "sg:postcode":"08310",
    "sg:province":"Barcelona",
    "wof:name":"Drive Textil S.l.",
    "wof:placetype":"venue"
},
  "geometry": {"coordinates":[2.4036650658,41.5564155579],"type":"Point"}
}