{
  "type": "Feature",
  "properties": {
    "addr:full":"Avda Canarias, 360 Vecindario Las Palmas 35110",
    "addr:housenumber":"360",
    "addr:postcode":"35110",
    "addr:street":"Avda Canarias;Las Palmas",
    "iso:country":"ES",
    "sg:address":"Avda Canarias, 360",
    "sg:city":"Vecindario",
    "sg:orig_category":"Distribuci\u00d3n De Petr\u00d3leo Y Derivados",
    "sg:phone":"+34 928 75 25 41",
    "sg:postcode":"35110",
    "sg:province":"Las Palmas",
    "wof:name":"Estacion Vencidario Hernandez S.l.",
    "wof:placetype":"venue"
},
  "geometry": {"coordinates":[-15.4457387924,27.8440189362],"type":"Point"}
}