{
  "type": "Feature",
  "properties": {
    "iso:country":"ES",
    "sg:address":"Pg Mallorca, 19",
    "sg:city":"Palma",
    "sg:orig_category":"Centros Empresariales",
    "sg:phone":"+34 971 22 00 75",
    "sg:postcode":"07011",
    "sg:province":"Islas Baleares",
    "wof:name":"Eulen S.a.",
    "wof:placetype":"venue"
},
  "geometry": {"coordinates":[2.6437590122,39.5757369995],"type":"Point"}
}