{
  "type": "Feature",
  "properties": {
    "iso:country":"ES",
    "sg:address":"Avda Mari\u00d1a (da), 105",
    "sg:city":"Burela",
    "sg:orig_category":"Pesca Y Caza: Art\u00cdculos (al Por Menor)",
    "sg:phone":"+34 982 58 59 53",
    "sg:postcode":"27880",
    "sg:province":"Lugo",
    "wof:name":"Andres Vizoso S.a.",
    "wof:placetype":"venue"
},
  "geometry": {"coordinates":[-7.3595376015,43.6655960083],"type":"Point"}
}