{
  "type": "Feature",
  "properties": {
    "addr:full":"Pase Ermita Del Santo, 33 Madrid Madrid 28011",
    "addr:housenumber":"33",
    "addr:postcode":"madrid;28011",
    "iso:country":"ES",
    "sg:address":"Pase Ermita Del Santo, 33",
    "sg:city":"Madrid",
    "sg:orig_category":"Grafistas",
    "sg:phone":"+34 913 64 59 33",
    "sg:postcode":"28011",
    "sg:province":"Madrid",
    "wof:name":"Nieto Arriba Emiliana",
    "wof:placetype":"venue"
},
  "geometry": {"coordinates":[-3.7238590717,40.4073562622],"type":"Point"}
}