{
  "type": "Feature",
  "properties": {
    "iso:country":"ES",
    "sg:address":"Carrer de Velazquez, 1",
    "sg:city":"Palma",
    "sg:orig_category":"Confecci\u00d3n (fabricaci\u00d3n, Al Por Mayor)",
    "sg:phone":"+34 971 72 13 12",
    "sg:postcode":"07002",
    "sg:province":"Islas Baleares",
    "wof:name":"Pomar Miro Pedro",
    "wof:placetype":"venue"
},
  "geometry": {"coordinates":[2.6543869972,39.5736694336],"type":"Point"}
}