{
  "type": "Feature",
  "properties": {
    "iso:country":"ES",
    "sg:address":"Carrer de Unio, 236",
    "sg:city":"Sabadell",
    "sg:classifiers":[
        {
            "category":"Casinos & Gambling",
            "type":"Entertainment"
        }
    ],
    "sg:phone":"+34 937 45 08 67",
    "sg:postcode":"08201",
    "sg:province":"Barcelona",
    "sg:tags":[
        "locale",
        "de",
        "juego"
    ],
    "sg:website":"www.aventurapark.com",
    "wof:name":"Ludinfant S.l.",
    "wof:placetype":"venue"
},
  "geometry": {"coordinates":[2.1006290913,41.5504417419],"type":"Point"}
}