{
  "type": "Feature",
  "properties": {
    "addr:full":"Calle de Cuatro Esquinas, S/n Santomera Murcia 30140",
    "addr:housenumber":"s / n",
    "addr:postcode":"30140",
    "addr:street":"Calle De Cuatro Esquinas",
    "iso:country":"ES",
    "sg:address":"Calle de Cuatro Esquinas, S/n",
    "sg:city":"Santomera",
    "sg:orig_category":"Negocio De Materiales De Construcci\u00d3n",
    "sg:phone":"+34 968 86 06 82",
    "sg:postcode":"30140",
    "sg:province":"Murcia",
    "wof:name":"Metalisteria Vulcano Sll",
    "wof:placetype":"venue"
},
  "geometry": {"coordinates":[-1.0475500822,38.0609855652],"type":"Point"}
}