{
  "type": "Feature",
  "properties": {
    "addr:full":"Carrer de Gaudi, 40 Llagosta Barcelona 08120",
    "addr:housenumber":"40",
    "addr:postcode":"08120",
    "addr:street":"Carrer De Gaudi",
    "iso:country":"ES",
    "sg:address":"Carrer de Gaudi, 40",
    "sg:city":"Llagosta",
    "sg:orig_category":"Porcelanas, Azulejos (fabricaci\u00d3n, Al Por Mayor)",
    "sg:phone":"+34 935 74 28 33",
    "sg:postcode":"08120",
    "sg:province":"Barcelona",
    "wof:name":"Ceramtec S.a.",
    "wof:placetype":"venue"
},
  "geometry": {"coordinates":[2.2018489838,41.5149497986],"type":"Point"}
}