{
  "type": "Feature",
  "properties": {
    "iso:country":"ES",
    "sg:address":"Calle de General Benavides, 7",
    "sg:city":"Le\u00f3n",
    "sg:orig_category":"Electricidad (montaje, Ensamblaje De Componentes)",
    "sg:phone":"+34 987 20 86 42",
    "sg:postcode":"24005",
    "sg:province":"Le\u00f3n",
    "wof:name":"Grupo Chantria Integrales Sl",
    "wof:placetype":"venue"
},
  "geometry": {"coordinates":[-5.5643606186,42.5903434753],"type":"Point"}
}