{
  "type": "Feature",
  "properties": {
    "addr:full":"Pol Ind San Isidro, S/n Don Benito Badajoz 06400",
    "addr:housenumber":"s / n",
    "addr:postcode":"06400",
    "addr:street":"San Isidro",
    "iso:country":"ES",
    "sg:address":"Pol Ind San Isidro, S/n",
    "sg:city":"Don Benito",
    "sg:orig_category":"Construcciones Met\u00c1licas",
    "sg:phone":"+34 924 80 06 40",
    "sg:postcode":"06400",
    "sg:province":"Badajoz",
    "wof:name":"Imex El Zorro S.l.",
    "wof:placetype":"venue"
},
  "geometry": {"coordinates":[-5.8775963783,38.9857902527],"type":"Point"}
}