{
  "type": "Feature",
  "properties": {
    "addr:full":"Calle de Cruz, 29 Zafra Badajoz 06300",
    "addr:housenumber":"29",
    "addr:postcode":"06300",
    "addr:street":"Calle De Cruz",
    "iso:country":"ES",
    "sg:address":"Calle de Cruz, 29",
    "sg:city":"Zafra",
    "sg:orig_category":"Internados & Ense\u00d1anza Privada",
    "sg:phone":"+34 924 55 40 95",
    "sg:postcode":"06300",
    "sg:province":"Badajoz",
    "wof:name":"Religiosas De Maria Inmaculada",
    "wof:placetype":"venue"
},
  "geometry": {"coordinates":[-6.4211688042,38.4268341064],"type":"Point"}
}