{
  "type": "Feature",
  "properties": {
    "addr:full":"Calle de Jaen, 16 Madrid Madrid 28020",
    "addr:housenumber":"16",
    "addr:postcode":"madrid;28020",
    "addr:street":"Calle De Jaen",
    "iso:country":"ES",
    "sg:address":"Calle de Jaen, 16",
    "sg:city":"Madrid",
    "sg:orig_category":"Telas Y Sedas (al Por Menor)",
    "sg:phone":"+34 915 54 50 55",
    "sg:postcode":"28020",
    "sg:province":"Madrid",
    "wof:name":"Oliva Mayo Maria Luisa",
    "wof:placetype":"venue"
},
  "geometry": {"coordinates":[-3.7014939785,40.4502754211],"type":"Point"}
}