{
  "type": "Feature",
  "properties": {
    "iso:country":"ES",
    "sg:address":"Calle de Pedro Jumilla, 3",
    "sg:city":"Torre-pacheco",
    "sg:orig_category":"Electrodom\u00c9sticos (al Por Menor)",
    "sg:phone":"+34 968 58 52 64",
    "sg:postcode":"30700",
    "sg:province":"Murcia",
    "wof:name":"Expoelectronica R & M C.b.",
    "wof:placetype":"venue"
},
  "geometry": {"coordinates":[-1.1322920322,37.9816436768],"type":"Point"}
}