{
  "type": "Feature",
  "properties": {
    "addr:full":"Carrer de Onze, 2 Castelldefels Barcelona 08860",
    "addr:housenumber":"2",
    "addr:postcode":"08860",
    "addr:street":"Carrer De Onze",
    "iso:country":"ES",
    "sg:address":"Carrer de Onze, 2",
    "sg:city":"Castelldefels",
    "sg:orig_category":"Inmobiliaria (agencias)",
    "sg:phone":"+34 936 36 22 97",
    "sg:postcode":"08860",
    "sg:province":"Barcelona",
    "wof:name":"Pagrup S.a.",
    "wof:placetype":"venue"
},
  "geometry": {"coordinates":[1.9769599438,41.2803115845],"type":"Point"}
}