{
  "type": "Feature",
  "properties": {
    "addr:full":"Calle de Fernando Vi, 1 Madrid Madrid 28004",
    "addr:housenumber":"1",
    "addr:postcode":"28004",
    "addr:street":"Calle De Fernando Vi",
    "iso:country":"ES",
    "sg:address":"Calle de Fernando Vi, 1",
    "sg:city":"Madrid",
    "sg:orig_category":"Arquitectos",
    "sg:phone":"+34 913 08 54 64",
    "sg:postcode":"28004",
    "sg:province":"Madrid",
    "wof:name":"Recuenco Perez Lucas",
    "wof:placetype":"venue"
},
  "geometry": {"coordinates":[-3.697116375,40.4258918762],"type":"Point"}
}