{
  "type": "Feature",
  "properties": {
    "iso:country":"ES",
    "sg:address":"Calle de Cervantes, 1",
    "sg:city":"Pantoja",
    "sg:classifiers":[
        {
            "category":"Taxi",
            "type":"Transportation"
        }
    ],
    "sg:phone":"+34 925 55 41 01",
    "sg:postcode":"45290",
    "sg:province":"Toledo",
    "wof:name":"Garcia Hidalgo Fermin",
    "wof:placetype":"venue"
},
  "geometry": {"coordinates":[-3.8382065296,40.0449714661],"type":"Point"}
}