{
  "type": "Feature",
  "properties": {
    "addr:full":"Calle de Mariano Serrano, 16 Madrid Madrid 28029",
    "addr:housenumber":"16",
    "addr:postcode":"madrid;28029",
    "addr:street":"Calle De Mariano Serrano",
    "iso:country":"ES",
    "sg:address":"Calle de Mariano Serrano, 16",
    "sg:city":"Madrid",
    "sg:orig_category":"Promotores Constructores",
    "sg:phone":"+34 913 23 78 53",
    "sg:postcode":"28029",
    "sg:province":"Madrid",
    "wof:name":"Obras Condisa S.l.",
    "wof:placetype":"venue"
},
  "geometry": {"coordinates":[-3.701800108,40.4706115723],"type":"Point"}
}