{
  "type": "Feature",
  "properties": {
    "addr:full":"Ctra. D'inca, 31 Sa Pobla Islas Baleares 07420",
    "addr:housenumber":"31",
    "addr:postcode":"07420",
    "addr:street":"Ctra. D'Inca",
    "iso:country":"ES",
    "sg:address":"Ctra. D'inca, 31",
    "sg:city":"Sa Pobla",
    "sg:orig_category":"Frutas Y Legumbres Frescas (al Por Mayor)",
    "sg:phone":"+34 971 54 01 57",
    "sg:postcode":"07420",
    "sg:province":"Islas Baleares",
    "wof:name":"Palou Serra Tomas",
    "wof:placetype":"venue"
},
  "geometry": {"coordinates":[3.017772913,39.7708778381],"type":"Point"}
}