{
  "type": "Feature",
  "properties": {
    "addr:full":"Avda Cristobal De Murrieta, 1 Santurtzi Vizcaya 48980",
    "addr:housenumber":"1",
    "addr:postcode":"48980",
    "addr:street":"Avda Cristobal De Murrieta",
    "iso:country":"ES",
    "sg:address":"Avda Cristobal De Murrieta, 1",
    "sg:city":"Santurtzi",
    "sg:orig_category":"Fabricaci\u00d3n, Importaci\u00d3n, Venta De Material De Telefon\u00cda, Peritelefon\u00cda",
    "sg:phone":"+34 944 62 94 59",
    "sg:postcode":"48980",
    "sg:province":"Vizcaya",
    "wof:name":"Tolutel S.l",
    "wof:placetype":"venue"
},
  "geometry": {"coordinates":[-3.0402638912,43.3327636719],"type":"Point"}
}