{
  "type": "Feature",
  "properties": {
    "iso:country":"ES",
    "sg:address":"Carr Carles Salvador, (de), 12",
    "sg:city":"Carlet",
    "sg:orig_category":"Promotores Constructores",
    "sg:phone":"+34 962 53 19 11",
    "sg:postcode":"46240",
    "sg:province":"Valencia",
    "wof:name":"Duro Sanchez Manjavaca Manuel",
    "wof:placetype":"venue"
},
  "geometry": {"coordinates":[-0.5227490067,39.2218894958],"type":"Point"}
}