{
  "type": "Feature",
  "properties": {
    "iso:country":"ES",
    "sg:address":"Carrer de Sant Jordi, 2",
    "sg:city":"Vendrell",
    "sg:orig_category":"Ropa Para Se\u00d1oras Y Caballeros (al Por Menor)",
    "sg:phone":"+34 977 66 76 22",
    "sg:postcode":"43700",
    "sg:province":"Tarragona",
    "wof:name":"Ritme 1 S.a.",
    "wof:placetype":"venue"
},
  "geometry": {"coordinates":[1.5329780579,41.2209281921],"type":"Point"}
}