{
  "type": "Feature",
  "properties": {
    "addr:full":"Avda Reyes Catolicos, 13 Alcala Henares Madrid 28802",
    "addr:housenumber":"13",
    "addr:postcode":"28802",
    "addr:street":"Avda Reyes Catolicos",
    "iso:country":"ES",
    "sg:address":"Avda Reyes Catolicos, 13",
    "sg:city":"Alcala Henares",
    "sg:orig_category":"Psic\u00d3logos",
    "sg:phone":"+34 918 82 84 42",
    "sg:postcode":"28802",
    "sg:province":"Madrid",
    "wof:name":"Hernandez Alonso Maria Paz",
    "wof:placetype":"venue"
},
  "geometry": {"coordinates":[-3.3736610413,40.477355957],"type":"Point"}
}