{
  "type": "Feature",
  "properties": {
    "iso:country":"ES",
    "sg:address":"Calle de Jerez, 11",
    "sg:city":"Montellano",
    "sg:orig_category":"Fabricaci\u00d3n De Juguetes Autom\u00c1ticos",
    "sg:phone":"+34 954 87 50 01",
    "sg:postcode":"41770",
    "sg:province":"Sevilla",
    "wof:name":"Raj S.a.",
    "wof:placetype":"venue"
},
  "geometry": {"coordinates":[-5.573925972,36.9949569702],"type":"Point"}
}