{
  "type": "Feature",
  "properties": {
    "iso:country":"ES",
    "sg:address":"Av Espanya, 5",
    "sg:city":"Eivissa",
    "sg:orig_category":"Ropa Y Accesorios",
    "sg:phone":"+34 971 30 33 02",
    "sg:postcode":"07800",
    "sg:province":"Islas Baleares",
    "wof:name":"Ess Sebban Nisride",
    "wof:placetype":"venue"
},
  "geometry": {"coordinates":[1.431614995,38.9085540771],"type":"Point"}
}