{
  "type": "Feature",
  "properties": {
    "iso:country":"ES",
    "sg:address":"Calle de Santisima Trinidad, 10",
    "sg:city":"Antequera",
    "sg:orig_category":"M\u00c9dicos: Ginecolog\u00cda Y Obstetricia",
    "sg:phone":"+34 952 84 37 13",
    "sg:postcode":"29200",
    "sg:province":"M\u00e1laga",
    "wof:name":"Marias Bages Martin Francisco",
    "wof:placetype":"venue"
},
  "geometry": {"coordinates":[-4.5629558563,37.0186653137],"type":"Point"}
}