{
  "type": "Feature",
  "properties": {
    "addr:full":"Ctra. Nijar, 382 Almeria Almer\u00eda 04006",
    "addr:housenumber":"382",
    "addr:postcode":"04006",
    "addr:street":"Ctra. Nijar",
    "iso:country":"ES",
    "sg:address":"Ctra. Nijar, 382",
    "sg:city":"Almeria",
    "sg:orig_category":"Farmacias",
    "sg:phone":"+34 950 22 07 49",
    "sg:postcode":"04006",
    "sg:province":"Almer\u00eda",
    "wof:name":"Garcia Lopez Juan Antonio",
    "wof:placetype":"venue"
},
  "geometry": {"coordinates":[-2.4388430119,36.8449707031],"type":"Point"}
}