{
  "type": "Feature",
  "properties": {
    "addr:full":"Calle de Mendoza, 4 Ecija Sevilla 41400",
    "addr:housenumber":"4",
    "addr:postcode":"41400",
    "addr:street":"Calle De Mendoza",
    "iso:country":"ES",
    "sg:address":"Calle de Mendoza, 4",
    "sg:city":"Ecija",
    "sg:orig_category":"Promotores Constructores",
    "sg:phone":"+34 954 83 23 78",
    "sg:postcode":"41400",
    "sg:province":"Sevilla",
    "wof:name":"Sanchez Arroyo Rafael",
    "wof:placetype":"venue"
},
  "geometry": {"coordinates":[-5.0802869797,37.537776947],"type":"Point"}
}