{
  "type": "Feature",
  "properties": {
    "iso:country":"ES",
    "sg:address":"Avda Levante (de), 32",
    "sg:city":"Jumilla",
    "sg:orig_category":"Loter\u00cda Y T\u00d3mbola",
    "sg:phone":"+34 968 78 12 80",
    "sg:postcode":"30520",
    "sg:province":"Murcia",
    "wof:name":"Tomas Castillo Maria Victoria",
    "wof:placetype":"venue"
},
  "geometry": {"coordinates":[-1.3231430054,38.4744186401],"type":"Point"}
}