{
  "type": "Feature",
  "properties": {
    "iso:country":"ES",
    "sg:address":"Mas Canonges (pol Entrevias), 2",
    "sg:city":"Tarragona",
    "sg:orig_category":"Minerales (al Por Mayor)",
    "sg:phone":"+34 977 55 19 17",
    "sg:postcode":"43006",
    "sg:province":"Tarragona",
    "wof:name":"Omya Clariana S.l.",
    "wof:placetype":"venue"
},
  "geometry": {"coordinates":[1.2104489803,41.1081581116],"type":"Point"}
}