{
  "type": "Feature",
  "properties": {
    "iso:country":"ES",
    "sg:address":"Carrer de Dante Alighieri, 28",
    "sg:city":"Barcelona",
    "sg:orig_category":"Ropa Para Se\u00d1oras Y Caballeros (al Por Menor)",
    "sg:phone":"+34 933 57 31 08",
    "sg:postcode":"08032",
    "sg:province":"Barcelona",
    "wof:name":"Cabeza Perez Ana Maria",
    "wof:placetype":"venue"
},
  "geometry": {"coordinates":[2.1606559753,41.4289321899],"type":"Point"}
}