{
  "type": "Feature",
  "properties": {
    "iso:country":"ES",
    "sg:address":"Avgd Castello, 4",
    "sg:city":"Benicasim",
    "sg:orig_category":"Peluqueros: De Se\u00d1oras",
    "sg:phone":"+34 964 30 55 02",
    "sg:postcode":"12560",
    "sg:province":"Castell\u00f3n",
    "wof:name":"Guirado Gil Mercedes",
    "wof:placetype":"venue"
},
  "geometry": {"coordinates":[0.0466559008,40.0530471802],"type":"Point"}
}