{
  "type": "Feature",
  "properties": {
    "addr:full":"Calle de Amilcar Barca, 5 Cadiz C\u00e1diz 11008",
    "addr:housenumber":"5",
    "addr:postcode":"11008",
    "addr:street":"Calle De Amilcar Barca",
    "iso:country":"ES",
    "sg:address":"Calle de Amilcar Barca, 5",
    "sg:city":"Cadiz",
    "sg:orig_category":"Seguridad Social",
    "sg:phone":"+34 956 20 10 19",
    "sg:postcode":"11008",
    "sg:province":"C\u00e1diz",
    "wof:name":"Tesoreria General De La Seguridad Social-servicios Centrales",
    "wof:placetype":"venue"
},
  "geometry": {"coordinates":[-6.2853989601,36.516960144],"type":"Point"}
}