{
  "type": "Feature",
  "properties": {
    "iso:country":"ES",
    "sg:address":"Calle de Alta, 11",
    "sg:city":"Casas-iba\u00e7ez",
    "sg:orig_category":"Carnicer\u00cdas, Carnicer\u00cdas",
    "sg:phone":"+34 967 46 11 97",
    "sg:postcode":"02200",
    "sg:province":"Albacete",
    "wof:name":"Garcia Medina Juan",
    "wof:placetype":"venue"
},
  "geometry": {"coordinates":[-1.8600701094,38.9976501465],"type":"Point"}
}