{
  "type": "Feature",
  "properties": {
    "addr:full":"Calle de Puente, 47 Aguilar Campoo Palencia 34800",
    "addr:housenumber":"47",
    "addr:postcode":"34800",
    "addr:street":"Calle De Puente",
    "iso:country":"ES",
    "sg:address":"Calle de Puente, 47",
    "sg:city":"Aguilar Campoo",
    "sg:orig_category":"Venta, Instalaci\u00d3n De Cocinas",
    "sg:phone":"+34 979 12 30 55",
    "sg:postcode":"34800",
    "sg:province":"Palencia",
    "wof:name":"Restaurante Cortes Poza S.l.",
    "wof:placetype":"venue"
},
  "geometry": {"coordinates":[-4.2650489807,42.7927589417],"type":"Point"}
}