{
  "type": "Feature",
  "properties": {
    "iso:country":"ES",
    "sg:address":"Calle de Alquerias De Bellver, 9",
    "sg:city":"Valencia",
    "sg:orig_category":"Cine (producci\u00d3n, Realizaci\u00d3n)",
    "sg:phone":"+34 963 47 11 36",
    "sg:postcode":"46015",
    "sg:province":"Valencia",
    "sg:website":"www.keryx.es",
    "wof:name":"Keryx S.l.",
    "wof:placetype":"venue"
},
  "geometry": {"coordinates":[-0.4078058004,39.490901947],"type":"Point"}
}