{
  "type": "Feature",
  "properties": {
    "addr:full":"Carrer de Sant Joaquim, 14 Palma Islas Baleares 07003",
    "addr:housenumber":"14",
    "addr:postcode":"07003",
    "addr:street":"Carrer De Sant Joaquim",
    "iso:country":"ES",
    "sg:address":"Carrer de Sant Joaquim, 14",
    "sg:city":"Palma",
    "sg:orig_category":"Peluquer\u00cdas, Peluquer\u00cda Mixta",
    "sg:phone":"+34 971 75 50 80",
    "sg:postcode":"07003",
    "sg:province":"Islas Baleares",
    "wof:name":"Fornes Perruquer S.l.",
    "wof:placetype":"venue"
},
  "geometry": {"coordinates":[2.6481440067,39.5824966431],"type":"Point"}
}