{
  "type": "Feature",
  "properties": {
    "iso:country":"ES",
    "sg:address":"Av Principal, 25",
    "sg:city":"Sentmenat",
    "sg:orig_category":"Insecticidas, Fumigaci\u00d3n",
    "sg:phone":"+34 937 15 25 94",
    "sg:postcode":"08181",
    "sg:province":"Barcelona",
    "wof:name":"Agroquimics Fabregat Duran S.a.",
    "wof:placetype":"venue"
},
  "geometry": {"coordinates":[2.1408133507,41.6125831604],"type":"Point"}
}