{
  "type": "Feature",
  "properties": {
    "iso:country":"ES",
    "sg:address":"Calle de Reyes Catolicos, 10",
    "sg:city":"Donostia-san Sebastian",
    "sg:orig_category":"Bisuter\u00cda, Joyer\u00cda, Relojer\u00cda (al Por Menor)",
    "sg:phone":"+34 943 46 50 64",
    "sg:postcode":"20006",
    "sg:province":"Guip\u00f9zcoa",
    "wof:name":"Darlington S.l.",
    "wof:placetype":"venue"
},
  "geometry": {"coordinates":[-1.9807779789,43.3153495789],"type":"Point"}
}