{
  "type": "Feature",
  "properties": {
    "iso:country":"ES",
    "sg:address":"Carrer de Pare Roma\u00d1a, 14",
    "sg:city":"Roquetes",
    "sg:orig_category":"Carnicer\u00cdas, Carnicer\u00cdas",
    "sg:phone":"+34 977 50 35 21",
    "sg:postcode":"43520",
    "sg:province":"Tarragona",
    "wof:name":"Pla Cid Silvia",
    "wof:placetype":"venue"
},
  "geometry": {"coordinates":[0.5001530051,40.8214302063],"type":"Point"}
}