{
  "type": "Feature",
  "properties": {
    "iso:country":"ES",
    "sg:address":"Avda Reconquista, 4",
    "sg:city":"Toledo",
    "sg:orig_category":"Centros Empresariales",
    "sg:phone":"+34 925 22 08 94",
    "sg:postcode":"45004",
    "sg:province":"Toledo",
    "wof:name":"Robles Torres Jose",
    "wof:placetype":"venue"
},
  "geometry": {"coordinates":[-4.0276770592,39.864025116],"type":"Point"}
}