{
  "type": "Feature",
  "properties": {
    "iso:country":"ES",
    "sg:address":"C/ Sant Antoni, 1",
    "sg:city":"Moncofa",
    "sg:orig_category":"Reposter\u00cdas",
    "sg:phone":"+34 964 57 93 96",
    "sg:postcode":"12593",
    "sg:province":"Castell\u00f3n",
    "wof:name":"Comercial Esther S.l.",
    "wof:placetype":"venue"
},
  "geometry": {"coordinates":[-0.1455750018,39.8070678711],"type":"Point"}
}