{
  "type": "Feature",
  "properties": {
    "iso:country":"ES",
    "sg:address":"Calle de Padre Manjon, 7",
    "sg:city":"Zaragoza",
    "sg:orig_category":"Bisuter\u00cda, Joyer\u00cda, Relojer\u00cda (al Por Menor)",
    "sg:phone":"+34 976 33 10 47",
    "sg:postcode":"50010",
    "sg:province":"Zaragoza",
    "wof:name":"Perez Lopez Roberto",
    "wof:placetype":"venue"
},
  "geometry": {"coordinates":[-0.9019520283,41.653213501],"type":"Point"}
}