{
  "type": "Feature",
  "properties": {
    "addr:full":"Praj San Vicente, 10 Alcora Castell\u00f3n 12110",
    "addr:housenumber":"10",
    "addr:postcode":"12110",
    "addr:street":"San Vicente;Castello\u0301N",
    "iso:country":"ES",
    "sg:address":"Praj San Vicente, 10",
    "sg:city":"Alcora",
    "sg:orig_category":"Empresas De Pintura Y Revestimientos",
    "sg:phone":"+34 964 36 19 05",
    "sg:postcode":"12110",
    "sg:province":"Castell\u00f3n",
    "wof:name":"Joaquin Jose Rull Miravet Y Miguel Angel Rull Miravet C.b.",
    "wof:placetype":"venue"
},
  "geometry": {"coordinates":[-0.2150872946,40.0733642578],"type":"Point"}
}