{
  "type": "Feature",
  "properties": {
    "addr:full":"Pg Lloren\u00c7 Serra, 5 Santa Coloma De Gramenet Barcelona 08922",
    "addr:housenumber":"5",
    "addr:postcode":"08922",
    "addr:street":"Pg Llorenc\u0327 Serra",
    "iso:country":"ES",
    "sg:address":"Pg Lloren\u00c7 Serra, 5",
    "sg:city":"Santa Coloma De Gramenet",
    "sg:orig_category":"Bancos",
    "sg:phone":"+34 934 66 12 00",
    "sg:postcode":"08922",
    "sg:province":"Barcelona",
    "wof:name":"Banc Sabadell S.a.",
    "wof:placetype":"venue"
},
  "geometry": {"coordinates":[2.2067101002,41.4509086609],"type":"Point"}
}