{
  "type": "Feature",
  "properties": {
    "iso:country":"ES",
    "sg:address":"Avda Constitucion (la), 16",
    "sg:city":"Alcala Guadaira",
    "sg:orig_category":"Ropa Para Ni\u00d1os (al Por Menor)",
    "sg:phone":"+34 955 61 33 44",
    "sg:postcode":"41500",
    "sg:province":"Sevilla",
    "wof:name":"Del Castillo Benitez Maria De Las Mercedes",
    "wof:placetype":"venue"
},
  "geometry": {"coordinates":[-5.8439722061,37.3488235474],"type":"Point"}
}