{
  "type": "Feature",
  "properties": {
    "addr:full":"Calle de Maestro Valls, 1 Valencia Valencia 46022",
    "addr:housenumber":"1",
    "addr:postcode":"46022",
    "addr:street":"Calle De Maestro Valls",
    "iso:country":"ES",
    "sg:address":"Calle de Maestro Valls, 1",
    "sg:city":"Valencia",
    "sg:orig_category":"M\u00c9dicos: Estomatolog\u00cda",
    "sg:phone":"+34 963 31 00 60",
    "sg:postcode":"46022",
    "sg:province":"Valencia",
    "wof:name":"Casaban Garcia Meritxell",
    "wof:placetype":"venue"
},
  "geometry": {"coordinates":[-0.3428260088,39.4632453918],"type":"Point"}
}