{
  "type": "Feature",
  "properties": {
    "iso:country":"ES",
    "sg:address":"Calle de Arquitecto Ramon Ca\u00d1as Del Rio, 12",
    "sg:city":"Le\u00f3n",
    "sg:orig_category":"Fabricaci\u00d3n, Importaci\u00d3n De L\u00c1mparas Y Bombillas",
    "sg:phone":"+34 987 24 09 10",
    "sg:postcode":"24007",
    "sg:province":"Le\u00f3n",
    "wof:name":"Ferrer Roca S.l.",
    "wof:placetype":"venue"
},
  "geometry": {"coordinates":[-5.5655369759,42.6005554199],"type":"Point"}
}