{
  "type": "Feature",
  "properties": {
    "iso:country":"ES",
    "sg:address":"Plaz Luis Martin Santos, 1",
    "sg:city":"Burgos",
    "sg:orig_category":"Empresarios",
    "sg:phone":"+34 947 20 41 91",
    "sg:postcode":"09002",
    "sg:province":"Burgos",
    "wof:name":"Heras De La Cal Eutimio De Las",
    "wof:placetype":"venue"
},
  "geometry": {"coordinates":[-3.6998100281,42.3410835266],"type":"Point"}
}