{
  "type": "Feature",
  "properties": {
    "addr:full":"Plg Industrial Xiv, S/n Manzanares Ciudad Real 13200",
    "addr:housenumber":"s / n",
    "addr:postcode":"13200",
    "iso:country":"ES",
    "sg:address":"Plg Industrial Xiv, S/n",
    "sg:city":"Manzanares",
    "sg:orig_category":"Aparatos E Instalaci\u00d3n De Regad\u00cdos",
    "sg:phone":"+34 926 62 04 51",
    "sg:postcode":"13200",
    "sg:province":"Ciudad Real",
    "wof:name":"Lozano Manzanares S.l.",
    "wof:placetype":"venue"
},
  "geometry": {"coordinates":[-3.3676741123,39.0135498047],"type":"Point"}
}