{
  "type": "Feature",
  "properties": {
    "addr:full":"Calle de Mesones, 9 Osa Vega Cuenca 16423",
    "addr:housenumber":"9",
    "addr:postcode":"16423",
    "addr:street":"Calle De Mesones",
    "iso:country":"ES",
    "sg:address":"Calle de Mesones, 9",
    "sg:city":"Osa Vega",
    "sg:orig_category":"Cajas De Ahorro",
    "sg:phone":"+34 969 12 20 47",
    "sg:postcode":"16423",
    "sg:province":"Cuenca",
    "sg:website":"www.ccm.es",
    "wof:name":"Caja De Ahorros De Castilla La Mancha",
    "wof:placetype":"venue"
},
  "geometry": {"coordinates":[-2.7580609322,39.660861969],"type":"Point"}
}