{
  "type": "Feature",
  "properties": {
    "iso:country":"ES",
    "sg:address":"Calle de Rio Agueda, 1",
    "sg:city":"Malaga",
    "sg:orig_category":"Peluqueros: De Se\u00d1oras",
    "sg:phone":"+34 952 32 55 92",
    "sg:postcode":"29006",
    "sg:province":"M\u00e1laga",
    "wof:name":"Alonso Villegas Manuel",
    "wof:placetype":"venue"
},
  "geometry": {"coordinates":[-4.4463510513,36.7100067139],"type":"Point"}
}