{
  "type": "Feature",
  "properties": {
    "addr:full":"Calle de Feria, 137 Albacete Albacete 02004",
    "addr:housenumber":"137",
    "addr:postcode":"02004",
    "addr:street":"Calle De Feria",
    "iso:country":"ES",
    "sg:address":"Calle de Feria, 137",
    "sg:city":"Albacete",
    "sg:orig_category":"Promotores Constructores",
    "sg:phone":"+34 967 22 85 48",
    "sg:postcode":"02004",
    "sg:province":"Albacete",
    "wof:name":"Construrosa S.l.",
    "wof:placetype":"venue"
},
  "geometry": {"coordinates":[-1.8686929941,38.9960441589],"type":"Point"}
}