{
  "type": "Feature",
  "properties": {
    "addr:full":"Carrer de Mas Jornet, 13 Vilafranca Penedes Barcelona 08720",
    "addr:housenumber":"13",
    "addr:postcode":"08720",
    "addr:street":"Carrer De Mas Jornet;Penedes Barcelona",
    "iso:country":"ES",
    "sg:address":"Carrer de Mas Jornet, 13",
    "sg:city":"Vilafranca Penedes",
    "sg:orig_category":"Reposter\u00cdas",
    "sg:phone":"+34 938 92 21 38",
    "sg:postcode":"08720",
    "sg:province":"Barcelona",
    "wof:name":"Horno Espirall S. A.",
    "wof:placetype":"venue"
},
  "geometry": {"coordinates":[1.7032419443,41.3506507874],"type":"Point"}
}