{
  "type": "Feature",
  "properties": {
    "iso:country":"ES",
    "sg:address":"Calle de Junquitos (los), S/n",
    "sg:city":"Atogo",
    "sg:orig_category":"Chapister\u00cda",
    "sg:phone":"+34 922 39 25 44",
    "sg:postcode":"38611",
    "sg:province":"Santa Cruz De Tenerife",
    "wof:name":"Ajocar Z Racing",
    "wof:placetype":"venue"
},
  "geometry": {"coordinates":[-16.5858840942,28.0600891113],"type":"Point"}
}