{
  "type": "Feature",
  "properties": {
    "iso:country":"ES",
    "sg:address":"Calle de Caballeros, S/n",
    "sg:city":"Villacastin",
    "sg:orig_category":"Restaurantes",
    "sg:phone":"+34 921 19 80 50",
    "sg:postcode":"40150",
    "sg:province":"Segovia",
    "wof:name":"Gonzalez Mu\u00f1oz Mateo",
    "wof:placetype":"venue"
},
  "geometry": {"coordinates":[-4.4109678268,40.7799072266],"type":"Point"}
}