{
  "type": "Feature",
  "properties": {
    "addr:full":"Calle de Inventor La Cierva, 26 Langreo Asturias 33930",
    "addr:housenumber":"26",
    "addr:postcode":"33930",
    "addr:street":"Calle De Inventor La Cierva",
    "iso:country":"ES",
    "sg:address":"Calle de Inventor La Cierva, 26",
    "sg:city":"Langreo",
    "sg:orig_category":"Contenedores (mercanc\u00cdas)",
    "sg:phone":"+34 985 67 57 57",
    "sg:postcode":"33930",
    "sg:province":"Asturias",
    "wof:name":"Panadero Quesada Luis",
    "wof:placetype":"venue"
},
  "geometry": {"coordinates":[-5.6954336166,43.3072395325],"type":"Point"}
}