{
  "type": "Feature",
  "properties": {
    "addr:full":"Avda Pulpites (los), 35 Torres Cotillas Murcia 30565",
    "addr:housenumber":"35",
    "addr:postcode":"30565",
    "addr:street":"Avda Pulpites Los",
    "iso:country":"ES",
    "sg:address":"Avda Pulpites (los), 35",
    "sg:city":"Torres Cotillas",
    "sg:orig_category":"Empresas De Pintura Y Revestimientos",
    "sg:phone":"+34 968 62 61 69",
    "sg:postcode":"30565",
    "sg:province":"Murcia",
    "wof:name":"Pinturas Y Decoraciones Valentin S.l.",
    "wof:placetype":"venue"
},
  "geometry": {"coordinates":[-1.2364089489,38.0205993652],"type":"Point"}
}