{
  "type": "Feature",
  "properties": {
    "iso:country":"ES",
    "sg:address":"Calle de Pablo Neruda, 62",
    "sg:city":"Merida",
    "sg:orig_category":"Molduras, Junquillos, Listones Y Molduras Perforadas",
    "sg:phone":"+34 924 31 76 53",
    "sg:postcode":"06800",
    "sg:province":"Badajoz",
    "wof:name":"Borrego Herruzo Valentin",
    "wof:placetype":"venue"
},
  "geometry": {"coordinates":[-6.3307089806,38.8967208862],"type":"Point"}
}