{
  "type": "Feature",
  "properties": {
    "iso:country":"ES",
    "sg:address":"Avda Alcalde J.elosegi, 113",
    "sg:city":"Donostia-san Sebastian",
    "sg:orig_category":"Molduras, Junquillos, Listones Y Molduras Perforadas",
    "sg:phone":"+34 943 39 28 77",
    "sg:postcode":"20016",
    "sg:province":"Guip\u00f9zcoa",
    "wof:name":"Santos Jimenez Maria Luisa",
    "wof:placetype":"venue"
},
  "geometry": {"coordinates":[-1.9414600134,43.323551178],"type":"Point"}
}