{
  "type": "Feature",
  "properties": {
    "iso:country":"ES",
    "sg:address":"Rond Parque, 6",
    "sg:city":"Ciudad Real",
    "sg:orig_category":"Extinci\u00d3n De Incendios: Material Y Suministros (fabricaci\u00d3n, Al Por Mayor)",
    "sg:phone":"+34 926 21 41 05",
    "sg:postcode":"13002",
    "sg:province":"Ciudad Real",
    "wof:name":"Calvo Escobar Manuel",
    "wof:placetype":"venue"
},
  "geometry": {"coordinates":[-3.935448885,38.9828453064],"type":"Point"}
}