{
  "type": "Feature",
  "properties": {
    "addr:full":"Pase Menendez Pelayo, 42 Castro Urdiales Cantabria 39700",
    "addr:housenumber":"42",
    "addr:postcode":"39700",
    "addr:street":"Pelayo",
    "iso:country":"ES",
    "sg:address":"Pase Menendez Pelayo, 42",
    "sg:city":"Castro Urdiales",
    "sg:orig_category":"Electricidad, Electr\u00d3nica: Suministros (al Por Menor)",
    "sg:phone":"+34 942 87 17 02",
    "sg:postcode":"39700",
    "sg:province":"Cantabria",
    "wof:name":"Macarro Benitez Visitacion",
    "wof:placetype":"venue"
},
  "geometry": {"coordinates":[-3.2144858837,43.3724479675],"type":"Point"}
}