{
  "type": "Feature",
  "properties": {
    "addr:full":"Poniente, 126 Montealina Madrid 28223",
    "addr:housenumber":"126",
    "addr:postcode":"28223",
    "addr:street":"Poniente",
    "iso:country":"ES",
    "sg:address":"Poniente, 126",
    "sg:city":"Montealina",
    "sg:orig_category":"Artes Gr\u00c1ficas, Artes Pl\u00c1sticas (curso)",
    "sg:phone":"+34 913 51 39 81",
    "sg:postcode":"28223",
    "sg:province":"Madrid",
    "wof:name":"Perarribas&asociados S.l.",
    "wof:placetype":"venue"
},
  "geometry": {"coordinates":[-3.8584671021,40.4388160706],"type":"Point"}
}