{
  "type": "Feature",
  "properties": {
    "addr:full":"Avda Boliches De Los, 4 Fuengirola M\u00e1laga 29640",
    "addr:postcode":"29640",
    "addr:street":"Avda Boliches De Los;Ma\u0301Laga",
    "iso:country":"ES",
    "sg:address":"Avda Boliches De Los, 4",
    "sg:city":"Fuengirola",
    "sg:orig_category":"Muebles, Minoristas",
    "sg:phone":"+34 952 66 49 74",
    "sg:postcode":"29640",
    "sg:province":"M\u00e1laga",
    "sg:website":"www.paginegialle.it/stileitalia",
    "wof:name":"Impor-esport Stile Italia S.l.",
    "wof:placetype":"venue"
},
  "geometry": {"coordinates":[-4.616271019,36.550113678],"type":"Point"}
}