{
  "type": "Feature",
  "properties": {
    "iso:country":"ES",
    "sg:address":"Barrenkale, S/n",
    "sg:city":"Dorrao",
    "sg:orig_category":"Empresas De Desmonte",
    "sg:phone":"+34 948 46 03 31",
    "sg:postcode":"31829",
    "sg:province":"Navarra",
    "wof:name":"Excavaciones Patricio Lizarraga",
    "wof:placetype":"venue"
},
  "geometry": {"coordinates":[-2.0365839005,42.8742446899],"type":"Point"}
}