{
  "type": "Feature",
  "properties": {
    "iso:country":"ES",
    "sg:address":"Carrer de Cadi, 50",
    "sg:city":"Barcelona",
    "sg:orig_category":"Loter\u00cda Y T\u00d3mbola",
    "sg:phone":"+34 934 20 59 84",
    "sg:postcode":"08031",
    "sg:province":"Barcelona",
    "wof:name":"Maldonado Martorell Marta",
    "wof:placetype":"venue"
},
  "geometry": {"coordinates":[2.169907093,41.4325065613],"type":"Point"}
}