{
  "type": "Feature",
  "properties": {
    "addr:full":"Calle de Lopez Grass, 12 Madrid Madrid 28038",
    "addr:housenumber":"12",
    "addr:postcode":"madrid;28038",
    "addr:street":"Calle De Lopez Grass",
    "iso:country":"ES",
    "sg:address":"Calle de Lopez Grass, 12",
    "sg:city":"Madrid",
    "sg:orig_category":"Grabados",
    "sg:phone":"+34 914 37 22 90",
    "sg:postcode":"28038",
    "sg:province":"Madrid",
    "wof:name":"Arribas Medel Venancio",
    "wof:placetype":"venue"
},
  "geometry": {"coordinates":[-3.6608338356,40.3952102661],"type":"Point"}
}