{
  "type": "Feature",
  "properties": {
    "iso:country":"ES",
    "sg:address":"Calle de Valladolid, 49",
    "sg:city":"Suances",
    "sg:orig_category":"Caf\u00c9s, Bares, Cervecer\u00cdas",
    "sg:phone":"+34 942 81 12 90",
    "sg:postcode":"39340",
    "sg:province":"Cantabria",
    "wof:name":"Campo Missiego Carmen",
    "wof:placetype":"venue"
},
  "geometry": {"coordinates":[-4.0427188873,43.4331817627],"type":"Point"}
}