{
  "type": "Feature",
  "properties": {
    "addr:full":"Avda Rioja De (la), S/n S. Asensio La Rioja 26340",
    "addr:postcode":"26340",
    "addr:street":"Avda Rioja De La S / N S. Asensio",
    "iso:country":"ES",
    "sg:address":"Avda Rioja De (la), S/n",
    "sg:city":"S. Asensio",
    "sg:orig_category":"Art\u00cdculos De Madera (fabricaci\u00d3n Y Al Por Mayor)",
    "sg:phone":"+34 941 45 71 11",
    "sg:postcode":"26340",
    "sg:province":"La Rioja",
    "wof:name":"Aldos Muebles S.l.",
    "wof:placetype":"venue"
},
  "geometry": {"coordinates":[-2.7501144409,42.4991912842],"type":"Point"}
}