{
  "type": "Feature",
  "properties": {
    "addr:full":"Calle de Pantano De Yesa, 18 Zaragoza Zaragoza 50015",
    "addr:housenumber":"18",
    "addr:postcode":"50015",
    "addr:street":"Calle De Pantano De Yesa",
    "iso:country":"ES",
    "sg:address":"Calle de Pantano De Yesa, 18",
    "sg:city":"Zaragoza",
    "sg:orig_category":"Asesor\u00cda De Formaci\u00d3n Y Gesti\u00d3n De Personal",
    "sg:phone":"+34 976 74 20 39",
    "sg:postcode":"50015",
    "sg:province":"Zaragoza",
    "wof:name":"Prevencion Y Salud Prevensalud S.l.",
    "wof:placetype":"venue"
},
  "geometry": {"coordinates":[-0.8743203878,41.6683082581],"type":"Point"}
}