{
  "type": "Feature",
  "properties": {
    "addr:full":"Sant Manuel, 28 Ametlla Mar Tarragona 43860",
    "addr:housenumber":"28",
    "addr:postcode":"43860",
    "addr:street":"Manuel",
    "iso:country":"ES",
    "sg:address":"Sant Manuel, 28",
    "sg:city":"Ametlla Mar",
    "sg:orig_category":"Promotores Constructores",
    "sg:phone":"+34 977 45 61 93",
    "sg:postcode":"43860",
    "sg:province":"Tarragona",
    "wof:name":"Construccions Miquel Sole S.l.",
    "wof:placetype":"venue"
},
  "geometry": {"coordinates":[0.8008229733,40.8824615479],"type":"Point"}
}