{
  "type": "Feature",
  "properties": {
    "iso:country":"ES",
    "sg:address":"Ctra. Granada, 26",
    "sg:city":"Lecrin",
    "sg:orig_category":"Venta, Instalaci\u00d3n De Cocinas",
    "sg:phone":"+34 958 79 50 09",
    "sg:postcode":"18656",
    "sg:province":"Granada",
    "wof:name":"Garvi Ortega Francisco",
    "wof:placetype":"venue"
},
  "geometry": {"coordinates":[-3.6378028393,37.5198402405],"type":"Point"}
}