{
  "type": "Feature",
  "properties": {
    "addr:full":"Calle de Generalisimo, 91 Socuellamos Ciudad Real 13630",
    "addr:housenumber":"91",
    "addr:postcode":"13630",
    "addr:street":"Calle De Generalisimo",
    "iso:country":"ES",
    "sg:address":"Calle de Generalisimo, 91",
    "sg:city":"Socuellamos",
    "sg:orig_category":"Ense\u00d1anza Variada",
    "sg:phone":"+34 926 53 19 55",
    "sg:postcode":"13630",
    "sg:province":"Ciudad Real",
    "wof:name":"Sanchez Sanchez Cecilia",
    "wof:placetype":"venue"
},
  "geometry": {"coordinates":[-2.792329073,39.2855911255],"type":"Point"}
}