{
  "type": "Feature",
  "properties": {
    "iso:country":"ES",
    "sg:address":"Calle de Carpinteria, 19",
    "sg:city":"Madrid",
    "sg:orig_category":"Servicio De Salud",
    "sg:phone":"+34 913 24 10 87",
    "sg:postcode":"28037",
    "sg:province":"Madrid",
    "wof:name":"Rozo Gutierrez Maria Teresa",
    "wof:placetype":"venue"
},
  "geometry": {"coordinates":[-3.6224293709,40.4256515503],"type":"Point"}
}