{
  "type": "Feature",
  "properties": {
    "iso:country":"ES",
    "sg:address":"Cta Graus-viella, S/n",
    "sg:city":"Serraduy",
    "sg:orig_category":"Hoteles",
    "sg:phone":"+34 974 54 44 30",
    "sg:postcode":"22483",
    "sg:province":"Huesca",
    "wof:name":"Casa El Peix S.l.",
    "wof:placetype":"venue"
},
  "geometry": {"coordinates":[0.5261899829,42.3667144775],"type":"Point"}
}