{
  "type": "Feature",
  "properties": {
    "addr:full":"Ptor Sobejano, 23 Los Narejos Murcia 30710",
    "addr:housenumber":"23",
    "addr:postcode":"30710",
    "addr:street":"Sobejano;Los Narejos",
    "iso:country":"ES",
    "sg:address":"Ptor Sobejano, 23",
    "sg:city":"Los Narejos",
    "sg:orig_category":"Trabajos De Fotocomposici\u00d3n",
    "sg:phone":"+34 968 17 06 96",
    "sg:postcode":"30710",
    "sg:province":"Murcia",
    "wof:name":"Fotomecanica N5 S.l.",
    "wof:placetype":"venue"
},
  "geometry": {"coordinates":[-0.8358079791,37.7559700012],"type":"Point"}
}