{
  "type": "Feature",
  "properties": {
    "addr:full":"Calle de Ujue, 6 Funes Navarra 31360",
    "addr:housenumber":"6",
    "addr:postcode":"31360",
    "addr:street":"Calle De Ujue",
    "iso:country":"ES",
    "sg:address":"Calle de Ujue, 6",
    "sg:city":"Funes",
    "sg:orig_category":"Plomeros",
    "sg:phone":"+34 948 75 43 31",
    "sg:postcode":"31360",
    "sg:province":"Navarra",
    "wof:name":"Conesa Salinas Jose Maria",
    "wof:placetype":"venue"
},
  "geometry": {"coordinates":[-1.8027570248,42.3139724731],"type":"Point"}
}