{
  "type": "Feature",
  "properties": {
    "iso:country":"ES",
    "sg:address":"La Gangosa, 3",
    "sg:city":"Vicar",
    "sg:orig_category":"Fabricaci\u00d3n De Muebles De Cocina",
    "sg:phone":"+34 950 34 09 03",
    "sg:postcode":"04738",
    "sg:province":"Almer\u00eda",
    "wof:name":"Msimon Cocinas Sl",
    "wof:placetype":"venue"
},
  "geometry": {"coordinates":[-2.6420009136,36.8316612244],"type":"Point"}
}