{
  "type": "Feature",
  "properties": {
    "iso:country":"ES",
    "sg:address":"Doctor Alejandro Palomar, 10",
    "sg:city":"Zaragoza",
    "sg:orig_category":"Organizaciones Internacionales",
    "sg:phone":"+34 976 20 16 42",
    "sg:postcode":"50002",
    "sg:province":"Zaragoza",
    "wof:name":"Asociacion Om Sida",
    "wof:placetype":"venue"
},
  "geometry": {"coordinates":[-0.8727604151,41.6515693665],"type":"Point"}
}