{
  "type": "Feature",
  "properties": {
    "addr:full":"Plaz Parque (do), 6 Vilanova Arousa Pontevedra 36620",
    "addr:postcode":"36620",
    "iso:country":"ES",
    "sg:address":"Plaz Parque (do), 6",
    "sg:city":"Vilanova Arousa",
    "sg:orig_category":"Asesor\u00cda Fiscal Y Jur\u00cddica",
    "sg:phone":"+34 986 55 43 34",
    "sg:postcode":"36620",
    "sg:province":"Pontevedra",
    "wof:name":"B. Mari\u00f1o S.l.",
    "wof:placetype":"venue"
},
  "geometry": {"coordinates":[-8.8285036087,42.5618782043],"type":"Point"}
}