{
  "type": "Feature",
  "properties": {
    "iso:country":"ES",
    "sg:address":"La Quintana, S/n",
    "sg:city":"Trubia",
    "sg:orig_category":"Asociaciones Y Clubs Deportivos",
    "sg:phone":"+34 985 78 61 21",
    "sg:postcode":"33119",
    "sg:province":"Asturias",
    "wof:name":"Sociedad Deportiva Real Juvencia",
    "wof:placetype":"venue"
},
  "geometry": {"coordinates":[-6.0131340027,43.3332481384],"type":"Point"}
}