{
  "type": "Feature",
  "properties": {
    "addr:full":"Avda Primero De Mayo, 4 Puertollano Ciudad Real 13500",
    "addr:housenumber":"4",
    "addr:postcode":"13500",
    "addr:street":"Avda Primero De Mayo",
    "iso:country":"ES",
    "sg:address":"Avda Primero De Mayo, 4",
    "sg:city":"Puertollano",
    "sg:orig_category":"Relojer\u00cda (al Por Menor, Reparaci\u00d3n)",
    "sg:phone":"+34 926 43 25 32",
    "sg:postcode":"13500",
    "sg:province":"Ciudad Real",
    "wof:name":"Sanchez Lopez Francisco",
    "wof:placetype":"venue"
},
  "geometry": {"coordinates":[-4.1058588028,38.6857795715],"type":"Point"}
}