{
  "type": "Feature",
  "properties": {
    "addr:full":"Calle de Poeta Zorrilla, 36 Alacant Alicante 03012",
    "addr:housenumber":"36",
    "addr:postcode":"03012",
    "addr:street":"Calle De Poeta Zorrilla",
    "iso:country":"ES",
    "sg:address":"Calle de Poeta Zorrilla, 36",
    "sg:city":"Alacant",
    "sg:orig_category":"Inmobiliaria (agencias)",
    "sg:phone":"+34 965 20 76 14",
    "sg:postcode":"03012",
    "sg:province":"Alicante",
    "sg:website":"www.unicasa.es",
    "wof:name":"Estudio Unico Asociados S.l.",
    "wof:placetype":"venue"
},
  "geometry": {"coordinates":[-0.4803909957,38.3552322388],"type":"Point"}
}