{
  "type": "Feature",
  "properties": {
    "iso:country":"ES",
    "sg:address":"Calle de Blanca De Navarra, 8",
    "sg:city":"S. Adrian",
    "sg:orig_category":"Material Y Equipo Para Conserver\u00cdas Y Confiter\u00cdas",
    "sg:phone":"+34 948 67 20 15",
    "sg:postcode":"31570",
    "sg:province":"Navarra",
    "wof:name":"Talleres Ezquerra Seamers S. L.",
    "wof:placetype":"venue"
},
  "geometry": {"coordinates":[-1.9406150579,42.3381881714],"type":"Point"}
}