{
  "type": "Feature",
  "properties": {
    "iso:country":"ES",
    "sg:address":"Ctra Errekalde-larraskitu, 35",
    "sg:city":"Bilbao",
    "sg:orig_category":"Mec\u00c1nico Del Autom\u00d3vil",
    "sg:phone":"+34 944 44 85 29",
    "sg:postcode":"48002",
    "sg:province":"Vizcaya",
    "wof:name":"Carrocerias Zalama S. L.",
    "wof:placetype":"venue"
},
  "geometry": {"coordinates":[-2.939759016,43.2495307922],"type":"Point"}
}