{
  "type": "Feature",
  "properties": {
    "iso:country":"ES",
    "sg:address":"Ctra Hontanas, S/n",
    "sg:city":"Castrojeriz",
    "sg:orig_category":"Distribuci\u00d3n De Petr\u00d3leo Y Derivados",
    "sg:phone":"+34 947 37 72 54",
    "sg:postcode":"09110",
    "sg:province":"Burgos",
    "wof:name":"Mingeriz S.l.",
    "wof:placetype":"venue"
},
  "geometry": {"coordinates":[-4.1366958618,42.2869987488],"type":"Point"}
}