{
  "type": "Feature",
  "properties": {
    "addr:full":"Avda Media Legua, 1 Media Legua Murcia 30565",
    "addr:housenumber":"1",
    "addr:postcode":"30565",
    "addr:street":"Avda Media Legua",
    "iso:country":"ES",
    "sg:address":"Avda Media Legua, 1",
    "sg:city":"Media Legua",
    "sg:orig_category":"Agentes, Concesionarios Y Sucursales De Veh\u00cdculos",
    "sg:phone":"+34 968 62 60 28",
    "sg:postcode":"30565",
    "sg:province":"Murcia",
    "wof:name":"Automoviles Ramal S.l.",
    "wof:placetype":"venue"
},
  "geometry": {"coordinates":[-1.2395490408,38.0263290405],"type":"Point"}
}