{
  "type": "Feature",
  "properties": {
    "iso:country":"ES",
    "sg:address":"Carrer de Indalecio Prieto, 32",
    "sg:city":"Palma",
    "sg:orig_category":"Parques De Atracciones Y Centros De Esparcimiento",
    "sg:phone":"+34 971 27 13 58",
    "sg:postcode":"07008",
    "sg:province":"Islas Baleares",
    "wof:name":"Dosniha S.l.",
    "wof:placetype":"venue"
},
  "geometry": {"coordinates":[2.6716110706,39.5779190063],"type":"Point"}
}