{
  "type": "Feature",
  "properties": {
    "iso:country":"ES",
    "sg:address":"Calle de Marques De Arguelles, 5",
    "sg:city":"Llanes",
    "sg:orig_category":"Limpieza Industrial",
    "sg:phone":"+34 985 40 24 90",
    "sg:postcode":"33500",
    "sg:province":"Asturias",
    "wof:name":"Valle Del Rio S.c.",
    "wof:placetype":"venue"
},
  "geometry": {"coordinates":[-4.7549939156,43.4207191467],"type":"Point"}
}