{
  "type": "Feature",
  "properties": {
    "iso:country":"ES",
    "sg:address":"Calle de Archiduque Carlos, 33",
    "sg:city":"Valencia",
    "sg:orig_category":"Tapicer\u00cdas",
    "sg:phone":"+34 963 85 28 69",
    "sg:postcode":"46018",
    "sg:province":"Valencia",
    "wof:name":"Hernandez Paredes Vicente",
    "wof:placetype":"venue"
},
  "geometry": {"coordinates":[-0.3941797018,39.465675354],"type":"Point"}
}