{
  "type": "Feature",
  "properties": {
    "addr:full":"Avda Aragon, 38 Valencia Valencia 46021",
    "addr:housenumber":"38",
    "addr:postcode":"46021",
    "addr:street":"Avda Aragon",
    "iso:country":"ES",
    "sg:address":"Avda Aragon, 38",
    "sg:city":"Valencia",
    "sg:orig_category":"M\u00c9dicos: Estomatolog\u00cda",
    "sg:phone":"+34 963 93 44 32",
    "sg:postcode":"46021",
    "sg:province":"Valencia",
    "wof:name":"Colvee Millet Asuncion",
    "wof:placetype":"venue"
},
  "geometry": {"coordinates":[-0.356321007,39.4739151001],"type":"Point"}
}