{
  "type": "Feature",
  "properties": {
    "addr:full":"Camino De La Vgen. De Luna, Km. 0001,0 Pozoblanco C\u00f3rdoba 14400",
    "addr:postcode":"14400",
    "addr:street":"Camino De La Vgen. De Luna Km. 0001,0;Co\u0301Rdoba",
    "iso:country":"ES",
    "sg:address":"Camino De La Vgen. De Luna, Km. 0001,0",
    "sg:city":"Pozoblanco",
    "sg:orig_category":"Confecci\u00d3n (fabricaci\u00d3n, Al Por Mayor)",
    "sg:phone":"+34 957 77 33 76",
    "sg:postcode":"14400",
    "sg:province":"C\u00f3rdoba",
    "wof:name":"Navelutex S.l.",
    "wof:placetype":"venue"
},
  "geometry": {"coordinates":[-4.8492288589,38.3810462952],"type":"Point"}
}