{
  "type": "Feature",
  "properties": {
    "iso:country":"ES",
    "sg:address":"Calle de Canillas, 94",
    "sg:city":"Madrid",
    "sg:orig_category":"Mec\u00c1nico Del Autom\u00d3vil",
    "sg:phone":"+34 914 15 21 06",
    "sg:postcode":"28002",
    "sg:province":"Madrid",
    "wof:name":"Alvarez Diez Pedro",
    "wof:placetype":"venue"
},
  "geometry": {"coordinates":[-3.6702415943,40.443939209],"type":"Point"}
}