{
  "type": "Feature",
  "properties": {
    "addr:full":"Calle de Mendizabal, S/n Palmas De Gran Canaria Las Palmas 35001",
    "addr:housenumber":"s",
    "addr:postcode":"35001",
    "addr:street":"Calle De Mendizabal;/ N",
    "iso:country":"ES",
    "sg:address":"Calle de Mendizabal, S/n",
    "sg:city":"Palmas De Gran Canaria",
    "sg:orig_category":"Herboristas (al Por Menor)",
    "sg:phone":"+34 928 32 09 83",
    "sg:postcode":"35001",
    "sg:province":"Las Palmas",
    "wof:name":"Navarro Davila Dominga",
    "wof:placetype":"venue"
},
  "geometry": {"coordinates":[-15.4138231277,28.1024055481],"type":"Point"}
}