{
  "type": "Feature",
  "properties": {
    "iso:country":"ES",
    "sg:address":"Calle de Mieres, 12",
    "sg:city":"Gijon",
    "sg:orig_category":"Pescader\u00cdas (al Por Menor)",
    "sg:phone":"+34 985 14 14 36",
    "sg:postcode":"33208",
    "sg:province":"Asturias",
    "wof:name":"Cuervo Valdes Armando Rene",
    "wof:placetype":"venue"
},
  "geometry": {"coordinates":[-5.6639199257,43.5365028381],"type":"Point"}
}