{
  "type": "Feature",
  "properties": {
    "iso:country":"ES",
    "sg:address":"Calle de Cuesta De La Polvora, 22",
    "sg:city":"Cordoba",
    "sg:orig_category":"Enfermeras: Consultas, Atenci\u00d3n A Domicilio",
    "sg:phone":"+34 957 75 09 71",
    "sg:postcode":"14010",
    "sg:province":"C\u00f3rdoba",
    "wof:name":"Iba\u00f1ez Castro Salvador",
    "wof:placetype":"venue"
},
  "geometry": {"coordinates":[-4.7648978233,37.8796195984],"type":"Point"}
}