{
  "type": "Feature",
  "properties": {
    "addr:full":"Calle de Astros, 5 Madrid Madrid 28007",
    "addr:housenumber":"5",
    "addr:postcode":"28007",
    "addr:street":"Calle De Astros",
    "iso:country":"ES",
    "sg:address":"Calle de Astros, 5",
    "sg:city":"Madrid",
    "sg:orig_category":"Seguridad Social",
    "sg:phone":"+34 901 50 20 50",
    "sg:postcode":"28007",
    "sg:province":"Madrid",
    "wof:name":"Tesoreria General De La Seguridad Social-servicios Centrales",
    "wof:placetype":"venue"
},
  "geometry": {"coordinates":[-3.6694059372,40.4114265442],"type":"Point"}
}