{
  "type": "Feature",
  "properties": {
    "iso:country":"ES",
    "sg:address":"Calle de Joaquin Costa, 26",
    "sg:city":"Sari\u00f1ena",
    "sg:orig_category":"Plomeros",
    "sg:phone":"+34 974 57 08 19",
    "sg:postcode":"22200",
    "sg:province":"Huesca",
    "wof:name":"Casasnovas Gomez Aurelio",
    "wof:placetype":"venue"
},
  "geometry": {"coordinates":[-0.158416003,41.7932548523],"type":"Point"}
}