{
  "type": "Feature",
  "properties": {
    "iso:country":"ES",
    "sg:address":"Avda Naciones, 11",
    "sg:city":"Ciudad Quesada",
    "sg:orig_category":"Cajas De Ahorro",
    "sg:phone":"+34 965 72 57 72",
    "sg:postcode":"03170",
    "sg:province":"Alicante",
    "sg:website":"www.bancaja.es",
    "wof:name":"Caja De Ahorros De Valencia Castellon Y Alicante",
    "wof:placetype":"venue"
},
  "geometry": {"coordinates":[-0.7216060162,38.0639305115],"type":"Point"}
}