{
  "type": "Feature",
  "properties": {
    "addr:full":"Calle de Parroco Fernandez Pedrera, 4 Pola De Siero Asturias 33510",
    "addr:housenumber":"4",
    "addr:postcode":"33510",
    "addr:street":"Calle De Parroco Fernandez Pedrera",
    "iso:country":"ES",
    "sg:address":"Calle de Parroco Fernandez Pedrera, 4",
    "sg:city":"Pola De Siero",
    "sg:orig_category":"Agentes, Concesionarios Y Sucursales De Veh\u00cdculos",
    "sg:phone":"+34 985 72 05 69",
    "sg:postcode":"33510",
    "sg:province":"Asturias",
    "wof:name":"Sanjose-siero S.l.",
    "wof:placetype":"venue"
},
  "geometry": {"coordinates":[-5.6618609428,43.3899459839],"type":"Point"}
}