{
  "type": "Feature",
  "properties": {
    "addr:full":"Calle de Victor Hevia, 34 Oviedo Asturias 33012",
    "addr:housenumber":"34",
    "addr:postcode":"33012",
    "addr:street":"Calle De Victor Hevia",
    "iso:country":"ES",
    "sg:address":"Calle de Victor Hevia, 34",
    "sg:city":"Oviedo",
    "sg:orig_category":"Deportes Y Ocio: Art\u00cdculos Y Ropas (al Por Menor Y Accesorios)",
    "sg:phone":"+34 985 24 52 67",
    "sg:postcode":"33012",
    "sg:province":"Asturias",
    "wof:name":"Conde Lopez Gomez Pedro",
    "wof:placetype":"venue"
},
  "geometry": {"coordinates":[-5.8647489548,43.3678588867],"type":"Point"}
}