{
  "type": "Feature",
  "properties": {
    "addr:full":"Avgd De Joan Carles I, 15 Benicarlo Castell\u00f3n 12580",
    "addr:housenumber":"15",
    "addr:postcode":"12580",
    "iso:country":"ES",
    "sg:address":"Avgd De Joan Carles I, 15",
    "sg:city":"Benicarlo",
    "sg:orig_category":"Cajas De Ahorro",
    "sg:phone":"+34 964 46 23 50",
    "sg:postcode":"12580",
    "sg:province":"Castell\u00f3n",
    "wof:name":"Caixa D'estalvis Del Penedes",
    "wof:placetype":"venue"
},
  "geometry": {"coordinates":[0.4042100012,40.4457893372],"type":"Point"}
}