{
  "type": "Feature",
  "properties": {
    "iso:country":"ES",
    "sg:address":"Carr Estrella, 4",
    "sg:city":"Felanitx",
    "sg:orig_category":"Charcuter\u00cdas (al Por Mayor)",
    "sg:phone":"+34 971 58 00 53",
    "sg:postcode":"07200",
    "sg:province":"Islas Baleares",
    "wof:name":"Embutidos Blanco S. A.",
    "wof:placetype":"venue"
},
  "geometry": {"coordinates":[3.1445839405,39.4747695923],"type":"Point"}
}