{
  "type": "Feature",
  "properties": {
    "addr:full":"Rond Mu\u00d1oces (de Los), 67 Pozoblanco C\u00f3rdoba 14400",
    "addr:postcode":"14400",
    "addr:street":"Co\u0301Rdoba",
    "iso:country":"ES",
    "sg:address":"Rond Mu\u00d1oces (de Los), 67",
    "sg:city":"Pozoblanco",
    "sg:orig_category":"Veh\u00cdculos De Ocasi\u00d3n",
    "sg:phone":"+34 957 13 03 44",
    "sg:postcode":"14400",
    "sg:province":"C\u00f3rdoba",
    "wof:name":"Multicar S.c",
    "wof:placetype":"venue"
},
  "geometry": {"coordinates":[-4.8492288589,38.3810462952],"type":"Point"}
}