{
  "type": "Feature",
  "properties": {
    "addr:full":"Ctra. Palos-rabida, S/n Palos Frontera Huelva 21810",
    "addr:housenumber":"s / n",
    "addr:postcode":"21810",
    "addr:street":"Ctra. Palos-Rabida;Palos Frontera",
    "iso:country":"ES",
    "sg:address":"Ctra. Palos-rabida, S/n",
    "sg:city":"Palos Frontera",
    "sg:orig_category":"Ense\u00d1anza, Formaci\u00d3n Profesional: Aprendizaje",
    "sg:phone":"+34 959 53 05 35",
    "sg:postcode":"21810",
    "sg:province":"Huelva",
    "wof:name":"Diputacion Provincial De Huelva",
    "wof:placetype":"venue"
},
  "geometry": {"coordinates":[-6.8923411369,37.2240829468],"type":"Point"}
}