{
  "type": "Feature",
  "properties": {
    "addr:full":"Calle de Sociedad, 10 San Bartolome Murcia 30004",
    "addr:housenumber":"10",
    "addr:postcode":"30004",
    "addr:street":"Calle De Sociedad",
    "iso:country":"ES",
    "sg:address":"Calle de Sociedad, 10",
    "sg:city":"San Bartolome",
    "sg:orig_category":"Inform\u00c1tica: Material Y Suministros",
    "sg:phone":"+34 968 21 40 39",
    "sg:postcode":"30004",
    "sg:province":"Murcia",
    "wof:name":"Papeleria La Tecnica S.a.",
    "wof:placetype":"venue"
},
  "geometry": {"coordinates":[-1.1309740543,37.9845809937],"type":"Point"}
}