{
  "type": "Feature",
  "properties": {
    "iso:country":"ES",
    "sg:address":"Avda Europa, 18",
    "sg:city":"Pozuelo De Alarcon",
    "sg:orig_category":"Alimentaci\u00d3n General (al Por Menor)",
    "sg:phone":"+34 913 51 70 81",
    "sg:postcode":"28224",
    "sg:province":"Madrid",
    "wof:name":"Villamayor Y Palazon Gestion Integral De Empresas S.l.",
    "wof:placetype":"venue"
},
  "geometry": {"coordinates":[-3.792085886,40.4384841919],"type":"Point"}
}