{
  "type": "Feature",
  "properties": {
    "addr:full":"Pg Enric Sanchis, 35 Barcelona Barcelona 08030",
    "addr:housenumber":"35",
    "addr:postcode":"08030",
    "addr:street":"Pg Enric Sanchis",
    "iso:country":"ES",
    "sg:address":"Pg Enric Sanchis, 35",
    "sg:city":"Barcelona",
    "sg:orig_category":"Goma: Materias Primas (producci\u00d3n, Distribuci\u00d3n)",
    "sg:phone":"+34 933 05 46 32",
    "sg:postcode":"08030",
    "sg:province":"Barcelona",
    "wof:name":"Fortuna 2000 S.l.",
    "wof:placetype":"venue"
},
  "geometry": {"coordinates":[2.2061910629,41.4338531494],"type":"Point"}
}