{
  "type": "Feature",
  "properties": {
    "iso:country":"ES",
    "sg:address":"Calle de Virgen De Las Angustias, 14",
    "sg:city":"Avila",
    "sg:orig_category":"Armas Y Municiones (fabricaci\u00d3n, Al Por Mayor)",
    "sg:phone":"+34 920 25 14 60",
    "sg:postcode":"05005",
    "sg:province":"\u00c1vila",
    "sg:website":"www.armeriapuente.com",
    "wof:name":"Santiago Garcia Saturnino",
    "wof:placetype":"venue"
},
  "geometry": {"coordinates":[-4.6912250519,40.6604995728],"type":"Point"}
}