{
  "type": "Feature",
  "properties": {
    "iso:country":"ES",
    "sg:address":"Calle de Rui Perez, 1",
    "sg:city":"Aviles",
    "sg:orig_category":"Cl\u00cdnicas Dentales",
    "sg:phone":"+34 985 52 27 29",
    "sg:postcode":"33402",
    "sg:province":"Asturias",
    "wof:name":"Rodriguez Del Campo Gloria Ana",
    "wof:placetype":"venue"
},
  "geometry": {"coordinates":[-5.9243950844,43.5577659607],"type":"Point"}
}