{
  "type": "Feature",
  "properties": {
    "iso:country":"ES",
    "sg:address":"Av Coronel Estrada, 305",
    "sg:city":"Hostalric",
    "sg:orig_category":"Chapa Y Pintura Veh\u00cdculos",
    "sg:phone":"+34 972 86 45 52",
    "sg:postcode":"17450",
    "sg:province":"Girona",
    "wof:name":"Ortiz Borrego Jose Maria",
    "wof:placetype":"venue"
},
  "geometry": {"coordinates":[2.6347699165,41.7464904785],"type":"Point"}
}