{
  "type": "Feature",
  "properties": {
    "addr:full":"Carrer de Rubinstein, 6 Barcelona Barcelona 08022",
    "addr:housenumber":"6",
    "addr:postcode":"08022",
    "addr:street":"Carrer De Rubinstein",
    "iso:country":"ES",
    "sg:address":"Carrer de Rubinstein, 6",
    "sg:city":"Barcelona",
    "sg:orig_category":"\u00d3ptica: Instrumentos (fabricaci\u00d3n)",
    "sg:phone":"+34 932 12 03 46",
    "sg:postcode":"08022",
    "sg:province":"Barcelona",
    "wof:name":"Molto Ribes Javier",
    "wof:placetype":"venue"
},
  "geometry": {"coordinates":[2.1377859116,41.4052619934],"type":"Point"}
}