{
  "type": "Feature",
  "properties": {
    "addr:full":"Calle de Sociedad, 3 San Bartolome Murcia 30004",
    "addr:housenumber":"3",
    "addr:postcode":"30004",
    "addr:street":"Calle De Sociedad",
    "iso:country":"ES",
    "sg:address":"Calle de Sociedad, 3",
    "sg:city":"San Bartolome",
    "sg:orig_category":"Perfumer\u00cda Y Cosm\u00c9tica (fabricaci\u00d3n, Al Por Mayor)",
    "sg:phone":"+34 968 21 22 91",
    "sg:postcode":"30004",
    "sg:province":"Murcia",
    "wof:name":"Marcel Cluny S.a.",
    "wof:placetype":"venue"
},
  "geometry": {"coordinates":[-1.1307090521,37.9849090576],"type":"Point"}
}