{
  "type": "Feature",
  "properties": {
    "iso:country":"ES",
    "sg:address":"Calle de Francisco Salinas, 1",
    "sg:city":"Burgos",
    "sg:orig_category":"Instalaci\u00d3n, Reparaci\u00d3n De Ascensores Y Montacargas",
    "sg:phone":"+34 947 20 58 37",
    "sg:postcode":"09003",
    "sg:province":"Burgos",
    "wof:name":"Navarro Salda\u00f1a Javier",
    "wof:placetype":"venue"
},
  "geometry": {"coordinates":[-3.7117159367,42.3420677185],"type":"Point"}
}