{
  "type": "Feature",
  "properties": {
    "addr:full":"L. Braille, 1 Priego Cordoba C\u00f3rdoba 14800",
    "addr:housenumber":"1",
    "addr:postcode":"14800",
    "addr:street":"Braille;Cordoba Co\u0301Rdoba",
    "iso:country":"ES",
    "sg:address":"L. Braille, 1",
    "sg:city":"Priego Cordoba",
    "sg:orig_category":"T\u00c9cnicos Veterinarios",
    "sg:phone":"+34 957 70 13 35",
    "sg:postcode":"14800",
    "sg:province":"C\u00f3rdoba",
    "wof:name":"Gonzalez Gutierrez Adelaida",
    "wof:placetype":"venue"
},
  "geometry": {"coordinates":[-4.1962351799,37.4396209717],"type":"Point"}
}