{
  "type": "Feature",
  "properties": {
    "addr:full":"Calle de Cronista Figueras Pacheco, 2 Javea Alicante 03730",
    "addr:housenumber":"2",
    "addr:postcode":"03730",
    "addr:street":"Calle De Cronista Figueras Pacheco",
    "iso:country":"ES",
    "sg:address":"Calle de Cronista Figueras Pacheco, 2",
    "sg:city":"Javea",
    "sg:orig_category":"Restaurantes",
    "sg:phone":"+34 965 79 27 03",
    "sg:postcode":"03730",
    "sg:province":"Alicante",
    "wof:name":"Fuentes Mu\u00f1oz Alfonso",
    "wof:placetype":"venue"
},
  "geometry": {"coordinates":[0.1635441929,38.773349762],"type":"Point"}
}