{
  "type": "Feature",
  "properties": {
    "iso:country":"ES",
    "sg:address":"Calle de Violeta, 2",
    "sg:city":"Humanes De Madrid",
    "sg:orig_category":"Asesor\u00cda Sobre Comunicaci\u00d3n De Empresas",
    "sg:phone":"+34 916 90 12 36",
    "sg:postcode":"28970",
    "sg:province":"Madrid",
    "wof:name":"Configlab Asesoramiento E Inversion S.l.",
    "wof:placetype":"venue"
},
  "geometry": {"coordinates":[-3.8368959427,40.2648010254],"type":"Point"}
}