{
  "type": "Feature",
  "properties": {
    "iso:country":"ES",
    "sg:address":"Calle de Bidebarrieta, 11",
    "sg:city":"Bilbao",
    "sg:orig_category":"Agencias De Viajes",
    "sg:phone":"+34 944 15 63 97",
    "sg:postcode":"48005",
    "sg:province":"Vizcaya",
    "sg:website":"www.halconviajes.com",
    "wof:name":"Viajes Halcon S.a.",
    "wof:placetype":"venue"
},
  "geometry": {"coordinates":[-2.9241530895,43.2579727173],"type":"Point"}
}