{
  "type": "Feature",
  "properties": {
    "addr:full":"Calle de Rosa De Lima, 1 Matas-pinar-monte Rozas Madrid 28290",
    "addr:housenumber":"1",
    "addr:postcode":"28290",
    "addr:street":"Calle De Rosa De Lima",
    "iso:country":"ES",
    "sg:address":"Calle de Rosa De Lima, 1",
    "sg:city":"Matas-pinar-monte Rozas",
    "sg:orig_category":"Cl\u00cdnicas M\u00c9dicas",
    "sg:phone":"+34 916 30 70 50",
    "sg:postcode":"28290",
    "sg:province":"Madrid",
    "wof:name":"Digiene Diagnostic S.l.",
    "wof:placetype":"venue"
},
  "geometry": {"coordinates":[-3.8996260166,40.553653717],"type":"Point"}
}