{
  "type": "Feature",
  "properties": {
    "iso:country":"ES",
    "sg:address":"Calle de Luna (la), 2",
    "sg:city":"Jaen",
    "sg:orig_category":"Ense\u00d1anza Variada",
    "sg:phone":"+34 953 26 09 14",
    "sg:postcode":"23008",
    "sg:province":"Ja\u00e9n",
    "wof:name":"Centro De Estudios Sobresalientes S.l.",
    "wof:placetype":"venue"
},
  "geometry": {"coordinates":[-3.7854890823,37.7743301392],"type":"Point"}
}