{
  "type": "Feature",
  "properties": {
    "iso:country":"ES",
    "sg:address":"Pol Ind Ca\u00f1ada De La Fuente, S/n",
    "sg:city":"Martos",
    "sg:orig_category":"Armarios Y Cuadros El\u00c9ctricos",
    "sg:phone":"+34 953 55 10 00",
    "sg:postcode":"23600",
    "sg:province":"Ja\u00e9n",
    "sg:website":"www.eldon.com",
    "wof:name":"Eldon Espa\u00f1a S.a.",
    "wof:placetype":"venue"
},
  "geometry": {"coordinates":[-3.9491291046,37.601436615],"type":"Point"}
}