{
  "type": "Feature",
  "properties": {
    "addr:full":"Calle de Andra Mari Kalea, 8 Durango Vizcaya 48200",
    "addr:housenumber":"8",
    "addr:postcode":"48200",
    "addr:street":"Calle De Andra Mari Kalea",
    "iso:country":"ES",
    "sg:address":"Calle de Andra Mari Kalea, 8",
    "sg:city":"Durango",
    "sg:orig_category":"Procuradores",
    "sg:phone":"+34 946 20 14 00",
    "sg:postcode":"48200",
    "sg:province":"Vizcaya",
    "wof:name":"Astigarraga Albistegui Elena",
    "wof:placetype":"venue"
},
  "geometry": {"coordinates":[-2.6317923069,43.1679382324],"type":"Point"}
}