{
  "type": "Feature",
  "properties": {
    "addr:full":"Carrer de Santa Eulalia, 86 Hospitalet Llobregat Barcelona 08902",
    "addr:housenumber":"86",
    "addr:postcode":"08902",
    "addr:street":"Carrer De Santa Eulalia",
    "iso:country":"ES",
    "sg:address":"Carrer de Santa Eulalia, 86",
    "sg:city":"Hospitalet Llobregat",
    "sg:orig_category":"Cajas De Ahorro",
    "sg:phone":"+34 934 22 51 05",
    "sg:postcode":"08902",
    "sg:province":"Barcelona",
    "wof:name":"Caixa D'estalvis I Pensions De Barcelona",
    "wof:placetype":"venue"
},
  "geometry": {"coordinates":[2.127507925,41.3672294617],"type":"Point"}
}