{
  "type": "Feature",
  "properties": {
    "iso:country":"ES",
    "sg:address":"Carrer de Constitucio (de La), 17",
    "sg:city":"Gata Gorgos",
    "sg:orig_category":"Bisuter\u00cda, Joyer\u00cda, Relojer\u00cda (al Por Menor)",
    "sg:phone":"+34 965 75 61 83",
    "sg:postcode":"03740",
    "sg:province":"Alicante",
    "wof:name":"Soler Llacer Antonio",
    "wof:placetype":"venue"
},
  "geometry": {"coordinates":[0.0838349983,38.7745437622],"type":"Point"}
}