{
  "type": "Feature",
  "properties": {
    "addr:full":"Calle de Ameztia, 2 Doneztebe Navarra 31740",
    "addr:housenumber":"2",
    "addr:postcode":"31740",
    "addr:street":"Calle De Ameztia;Navarra",
    "iso:country":"ES",
    "sg:address":"Calle de Ameztia, 2",
    "sg:city":"Doneztebe",
    "sg:orig_category":"Iglesia Cat\u00d3lica",
    "sg:phone":"+34 948 45 02 28",
    "sg:postcode":"31740",
    "sg:province":"Navarra",
    "wof:name":"Parroquia San Pedro",
    "wof:placetype":"venue"
},
  "geometry": {"coordinates":[-1.6701750755,43.1310081482],"type":"Point"}
}