{
  "type": "Feature",
  "properties": {
    "addr:full":"Avda Portugal, 10 Brenes Sevilla 41310",
    "addr:housenumber":"10",
    "addr:postcode":"41310",
    "addr:street":"Avda Portugal",
    "iso:country":"ES",
    "sg:address":"Avda Portugal, 10",
    "sg:city":"Brenes",
    "sg:orig_category":"Cl\u00cdnicas Dentales",
    "sg:phone":"+34 954 79 73 54",
    "sg:postcode":"41310",
    "sg:province":"Sevilla",
    "wof:name":"Montelongo Diaz Elena",
    "wof:placetype":"venue"
},
  "geometry": {"coordinates":[-5.8685622215,37.5544395447],"type":"Point"}
}