{
  "type": "Feature",
  "properties": {
    "addr:full":"Carrer de Crom, 60 Hospitalet Llobregat Barcelona 08907",
    "addr:housenumber":"60",
    "addr:postcode":"08907",
    "addr:street":"Carrer De Crom",
    "iso:country":"ES",
    "sg:address":"Carrer de Crom, 60",
    "sg:city":"Hospitalet Llobregat",
    "sg:orig_category":"Alumbrados",
    "sg:phone":"+34 933 35 05 99",
    "sg:postcode":"08907",
    "sg:province":"Barcelona",
    "sg:website":"www.pantallasjdos.com",
    "wof:name":"Pantallas J-dos S.l.",
    "wof:placetype":"venue"
},
  "geometry": {"coordinates":[2.1015620232,41.3513755798],"type":"Point"}
}