{
  "type": "Feature",
  "properties": {
    "iso:country":"ES",
    "sg:address":"Calle de Luis Madrona, 2",
    "sg:city":"Alcala Henares",
    "sg:orig_category":"Institutos De Belleza",
    "sg:phone":"+34 918 81 67 65",
    "sg:postcode":"28805",
    "sg:province":"Madrid",
    "wof:name":"Fernandez Campanon Nuria",
    "wof:placetype":"venue"
},
  "geometry": {"coordinates":[-3.3486530781,40.488697052],"type":"Point"}
}