{
  "type": "Feature",
  "properties": {
    "iso:country":"ES",
    "sg:address":"Azara Kalea, 17",
    "sg:city":"Zarautz",
    "sg:orig_category":"Ropa Para Ni\u00d1os (al Por Menor)",
    "sg:phone":"+34 943 13 02 53",
    "sg:postcode":"20800",
    "sg:province":"Guip\u00f9zcoa",
    "wof:name":"Arrizabalaga Arrizabalo Maria Dolores",
    "wof:placetype":"venue"
},
  "geometry": {"coordinates":[-2.1757190228,43.286190033],"type":"Point"}
}