{
  "type": "Feature",
  "properties": {
    "addr:full":"Calle de Estacion, 44 Miranda Ebro Burgos 09200",
    "addr:housenumber":"44",
    "addr:postcode":"09200",
    "addr:street":"Calle De Estacion",
    "iso:country":"ES",
    "sg:address":"Calle de Estacion, 44",
    "sg:city":"Miranda Ebro",
    "sg:orig_category":"Bancos",
    "sg:phone":"+34 947 32 08 00",
    "sg:postcode":"09200",
    "sg:province":"Burgos",
    "wof:name":"Deutsche Bank S.a.e.",
    "wof:placetype":"venue"
},
  "geometry": {"coordinates":[-2.9439690113,42.6878318787],"type":"Point"}
}