{
  "type": "Feature",
  "properties": {
    "iso:country":"ES",
    "sg:address":"Avda Constitucion, 14",
    "sg:city":"Alacant",
    "sg:orig_category":"Asesor\u00cda De Formaci\u00d3n Y Gesti\u00d3n De Personal",
    "sg:phone":"+34 965 14 38 37",
    "sg:postcode":"03002",
    "sg:province":"Alicante",
    "wof:name":"Gabinete Lacyf C.b.",
    "wof:placetype":"venue"
},
  "geometry": {"coordinates":[-0.4855929911,38.347442627],"type":"Point"}
}