{
  "type": "Feature",
  "properties": {
    "addr:full":"Avda Blas De Otero, 23 Maracena Granada 18200",
    "addr:housenumber":"23",
    "addr:postcode":"18200",
    "addr:street":"Avda Blas De Otero",
    "iso:country":"ES",
    "sg:address":"Avda Blas De Otero, 23",
    "sg:city":"Maracena",
    "sg:orig_category":"Inmobiliaria (agencias)",
    "sg:phone":"+34 958 41 55 00",
    "sg:postcode":"18200",
    "sg:province":"Granada",
    "wof:name":"Albaci Inmobiliaria C.b.",
    "wof:placetype":"venue"
},
  "geometry": {"coordinates":[-3.6306958199,37.2073631287],"type":"Point"}
}