{
  "type": "Feature",
  "properties": {
    "iso:country":"ES",
    "sg:address":"Calle de Puerto Rico, 2",
    "sg:city":"Valencia",
    "sg:orig_category":"M\u00c1quinas De Escribir, M\u00c1quinas De Oficina (al Por Menor, Reparaci\u00d3n)",
    "sg:phone":"+34 963 80 13 88",
    "sg:postcode":"46006",
    "sg:province":"Valencia",
    "wof:name":"Bowe Systec S.a.",
    "wof:placetype":"venue"
},
  "geometry": {"coordinates":[-0.3740969896,39.4621658325],"type":"Point"}
}