{
  "type": "Feature",
  "properties": {
    "iso:country":"ES",
    "sg:address":"Calle de Victoria Balfe, 4",
    "sg:city":"Burgos",
    "sg:classifiers":[
        {
            "category":"Banks & Credit Unions",
            "subcategory":"Bureau De Change",
            "type":"Services"
        }
    ],
    "sg:phone":"+34 947 23 44 41",
    "sg:postcode":"09006",
    "sg:province":"Burgos",
    "sg:tags":[
        "organismos",
        "control"
    ],
    "wof:name":"Eurocontrol S.a.",
    "wof:placetype":"venue"
},
  "geometry": {"coordinates":[-3.6815860271,42.3598632812],"type":"Point"}
}