{
  "type": "Feature",
  "properties": {
    "addr:full":"Av Alacant, S/n Mutxamel Alicante 03110",
    "addr:housenumber":"s / n",
    "addr:postcode":"03110",
    "addr:street":"Alacant",
    "iso:country":"ES",
    "sg:address":"Av Alacant, S/n",
    "sg:city":"Mutxamel",
    "sg:orig_category":"Florister\u00cdas",
    "sg:phone":"+34 965 95 16 99",
    "sg:postcode":"03110",
    "sg:province":"Alicante",
    "wof:name":"Agrojardin Sala S.l.",
    "wof:placetype":"venue"
},
  "geometry": {"coordinates":[-0.4418533146,38.4097137451],"type":"Point"}
}