{
  "type": "Feature",
  "properties": {
    "addr:full":"Carrer de Jacint Verdaguer, 19 Vic Barcelona 08500",
    "addr:housenumber":"19",
    "addr:postcode":"08500",
    "addr:street":"Carrer De Jacint Verdaguer",
    "iso:country":"ES",
    "sg:address":"Carrer de Jacint Verdaguer, 19",
    "sg:city":"Vic",
    "sg:orig_category":"Notarios",
    "sg:phone":"+34 938 85 37 37",
    "sg:postcode":"08500",
    "sg:province":"Barcelona",
    "wof:name":"Beneyto Feliu Jesus",
    "wof:placetype":"venue"
},
  "geometry": {"coordinates":[2.2515189648,41.930519104],"type":"Point"}
}