{
  "type": "Feature",
  "properties": {
    "addr:full":"Calle de San Juan De La Cruz, 2 Pozuelo De Alarcon Madrid 28223",
    "addr:housenumber":"2",
    "addr:postcode":"28223",
    "addr:street":"Calle De San Juan;La Cruz",
    "iso:country":"ES",
    "sg:address":"Calle de San Juan De La Cruz, 2",
    "sg:city":"Pozuelo De Alarcon",
    "sg:orig_category":"Centros Empresariales",
    "sg:phone":"+34 913 51 61 40",
    "sg:postcode":"28223",
    "sg:province":"Madrid",
    "wof:name":"Itos Outsourcing Services S.l.",
    "wof:placetype":"venue"
},
  "geometry": {"coordinates":[-3.8130319118,40.4306335449],"type":"Point"}
}