{
  "type": "Feature",
  "properties": {
    "addr:full":"Crtra. Almansa, S/n Ponton Valencia 46357",
    "addr:housenumber":"s / n",
    "addr:postcode":"46357",
    "iso:country":"ES",
    "sg:address":"Crtra. Almansa, S/n",
    "sg:city":"Ponton",
    "sg:orig_category":"Productores Recolectores, Venta Directa De Vinos",
    "sg:phone":"+34 962 30 49 98",
    "sg:postcode":"46357",
    "sg:province":"Valencia",
    "wof:name":"Bodegas Gimenez S.l.",
    "wof:placetype":"venue"
},
  "geometry": {"coordinates":[-1.1222490072,39.4759216309],"type":"Point"}
}