{
  "type": "Feature",
  "properties": {
    "addr:full":"Calle de Burgos, 1 Barrio De La Vega Granada 18193",
    "addr:housenumber":"1",
    "addr:postcode":"18193",
    "addr:street":"Calle De Burgos",
    "iso:country":"ES",
    "sg:address":"Calle de Burgos, 1",
    "sg:city":"Barrio De La Vega",
    "sg:orig_category":"Alimentaci\u00d3n General (al Por Menor)",
    "sg:phone":"+34 958 50 00 10",
    "sg:postcode":"18193",
    "sg:province":"Granada",
    "wof:name":"Rodriguez Del Paso Jose",
    "wof:placetype":"venue"
},
  "geometry": {"coordinates":[-3.5586218834,37.1338729858],"type":"Point"}
}