{
  "type": "Feature",
  "properties": {
    "iso:country":"ES",
    "sg:address":"Calle de Nueva, S/n",
    "sg:city":"Navas Oro",
    "sg:orig_category":"Bancos",
    "sg:phone":"+34 921 59 11 67",
    "sg:postcode":"40470",
    "sg:province":"Segovia",
    "wof:name":"Banco Espa\u00f1ol De Credito S.a.",
    "wof:placetype":"venue"
},
  "geometry": {"coordinates":[-4.4380722046,41.1969490051],"type":"Point"}
}