{
  "type": "Feature",
  "properties": {
    "addr:full":"Carr Corsega, 13 Badalona Barcelona 08917",
    "addr:housenumber":"13",
    "addr:postcode":"08917",
    "addr:street":"Carr Corsega",
    "iso:country":"ES",
    "sg:address":"Carr Corsega, 13",
    "sg:city":"Badalona",
    "sg:orig_category":"M\u00c9dicos: Fisioterapia Y Rehabilitaci\u00d3n",
    "sg:phone":"+34 934 60 79 28",
    "sg:postcode":"08917",
    "sg:province":"Barcelona",
    "wof:name":"Montigala Centro De Rehabilitacion S.l.",
    "wof:placetype":"venue"
},
  "geometry": {"coordinates":[2.2227859497,41.4535980225],"type":"Point"}
}