{
  "type": "Feature",
  "properties": {
    "iso:country":"ES",
    "sg:address":"Calle de Esquero, 31",
    "sg:city":"Don Benito",
    "sg:orig_category":"Agencias Y Agentes Comerciales, Representantes",
    "sg:phone":"+34 924 80 03 91",
    "sg:postcode":"06400",
    "sg:province":"Badajoz",
    "wof:name":"Quintana Valades Isidro",
    "wof:placetype":"venue"
},
  "geometry": {"coordinates":[-5.8625073433,38.9571037292],"type":"Point"}
}