{
  "type": "Feature",
  "properties": {
    "addr:full":"Calle de Baja, 26 Gallur Zaragoza 50650",
    "addr:housenumber":"26",
    "addr:postcode":"50650",
    "addr:street":"Calle De Baja",
    "iso:country":"ES",
    "sg:address":"Calle de Baja, 26",
    "sg:city":"Gallur",
    "sg:orig_category":"Cer\u00c1micas: Material Y Suministros",
    "sg:phone":"+34 976 86 49 86",
    "sg:postcode":"50650",
    "sg:province":"Zaragoza",
    "wof:name":"Burillo Torres Maria Soledad",
    "wof:placetype":"venue"
},
  "geometry": {"coordinates":[-1.316676259,41.8694648743],"type":"Point"}
}