{
  "type": "Feature",
  "properties": {
    "iso:country":"ES",
    "sg:address":"Calle de Macia Francesc, 11",
    "sg:city":"Bilbao",
    "sg:orig_category":"Centros De Coordinaci\u00d3n",
    "sg:phone":"+34 944 47 00 12",
    "sg:postcode":"48014",
    "sg:province":"Vizcaya",
    "wof:name":"Centro De Asesoria Hipotecaria S.l.",
    "wof:placetype":"venue"
},
  "geometry": {"coordinates":[-2.942168951,43.2707252502],"type":"Point"}
}