{
  "type": "Feature",
  "properties": {
    "addr:full":"Calle de Euskalduna, 3 Bilbao Vizcaya 48008",
    "addr:housenumber":"3",
    "addr:postcode":"48008",
    "addr:street":"Calle De Euskalduna",
    "iso:country":"ES",
    "sg:address":"Calle de Euskalduna, 3",
    "sg:city":"Bilbao",
    "sg:orig_category":"Agentes, Concesionarios Y Sucursales De Veh\u00cdculos",
    "sg:phone":"+34 944 44 76 81",
    "sg:postcode":"48008",
    "sg:province":"Vizcaya",
    "wof:name":"Entretenimiento De Automoviles De Vizcaya S.a.",
    "wof:placetype":"venue"
},
  "geometry": {"coordinates":[-2.9319989681,43.259059906],"type":"Point"}
}