{
  "type": "Feature",
  "properties": {
    "iso:country":"ES",
    "sg:address":"Calle de Faisan, 4",
    "sg:city":"Valladolid",
    "sg:orig_category":"Televisi\u00d3n, V\u00cddeo: Aparatos Y Accesorios (venta)",
    "sg:phone":"+34 983 20 75 19",
    "sg:postcode":"47012",
    "sg:province":"Valladolid",
    "wof:name":"Sanz Velasco Juan Carlos",
    "wof:placetype":"venue"
},
  "geometry": {"coordinates":[-4.7105798721,41.648651123],"type":"Point"}
}