{
  "type": "Feature",
  "properties": {
    "addr:full":"Termino De Cantarruyuela, 63 Pradejon La Rioja 26510",
    "addr:housenumber":"63",
    "addr:postcode":"26510",
    "addr:street":"Termino;Cantarruyuela;Rioja",
    "iso:country":"ES",
    "sg:address":"Termino De Cantarruyuela, 63",
    "sg:city":"Pradejon",
    "sg:orig_category":"Producci\u00d3n De Champi\u00d1ones",
    "sg:phone":"+34 941 14 13 35",
    "sg:postcode":"26510",
    "sg:province":"La Rioja",
    "wof:name":"Sat Iberchamp",
    "wof:placetype":"venue"
},
  "geometry": {"coordinates":[-2.0681838989,42.3330917358],"type":"Point"}
}