{
  "type": "Feature",
  "properties": {
    "addr:full":"Calle de Avelino Gonzalez Mallada, 6 Gijon Asturias 33204",
    "addr:housenumber":"6",
    "addr:postcode":"33204",
    "addr:street":"Calle De Avelino Gonzalez Mallada",
    "iso:country":"ES",
    "sg:address":"Calle de Avelino Gonzalez Mallada, 6",
    "sg:city":"Gijon",
    "sg:orig_category":"Fabricaci\u00d3n, Comercio De Muebles En Ca\u00d1a, Mimbre",
    "sg:phone":"+34 985 37 27 50",
    "sg:postcode":"33204",
    "sg:province":"Asturias",
    "wof:name":"Exclusivas Del Mueble Gallegas S. A.",
    "wof:placetype":"venue"
},
  "geometry": {"coordinates":[-5.6530194283,43.5328369141],"type":"Point"}
}