{
  "type": "Feature",
  "properties": {
    "addr:full":"Calle de Marquesa Villa De San Roman, 8 Archena Murcia 30600",
    "addr:housenumber":"8",
    "addr:postcode":"30600",
    "addr:street":"Calle De Marquesa Villa De San Roman",
    "iso:country":"ES",
    "sg:address":"Calle de Marquesa Villa De San Roman, 8",
    "sg:city":"Archena",
    "sg:orig_category":"Delegados, Agentes De Tr\u00c1nsito, Auxiliares De Transporte Internacional",
    "sg:phone":"+34 968 67 27 31",
    "sg:postcode":"30600",
    "sg:province":"Murcia",
    "wof:name":"Marin Guillen Antonio",
    "wof:placetype":"venue"
},
  "geometry": {"coordinates":[-1.3025189638,38.1161499023],"type":"Point"}
}