{
  "type": "Feature",
  "properties": {
    "iso:country":"ES",
    "sg:address":"Calle de Santa Fe, 61",
    "sg:city":"Zaldibia",
    "sg:orig_category":"Iglesia Cat\u00d3lica",
    "sg:phone":"+34 943 88 28 90",
    "sg:postcode":"20247",
    "sg:province":"Guip\u00f9zcoa",
    "wof:name":"Parroquia Santa Fe",
    "wof:placetype":"venue"
},
  "geometry": {"coordinates":[-2.1503419876,43.0364227295],"type":"Point"}
}