{
  "type": "Feature",
  "properties": {
    "addr:full":"Calle de Arenales, 8 Cebolla Toledo 45550",
    "addr:housenumber":"8",
    "addr:postcode":"45550",
    "addr:street":"Calle De Arenales",
    "iso:country":"ES",
    "sg:address":"Calle de Arenales, 8",
    "sg:city":"Cebolla",
    "sg:orig_category":"Telas Y Sedas (al Por Menor)",
    "sg:phone":"+34 925 86 60 35",
    "sg:postcode":"45550",
    "sg:province":"Toledo",
    "wof:name":"Blanco Bolillo Manuel",
    "wof:placetype":"venue"
},
  "geometry": {"coordinates":[-4.5681920052,39.9455337524],"type":"Point"}
}