{
  "type": "Feature",
  "properties": {
    "addr:full":"Avda Galicia, 314 Fuentes Nuevas Le\u00f3n 24411",
    "addr:housenumber":"314",
    "addr:postcode":"24411",
    "addr:street":"Avda Galicia",
    "iso:country":"ES",
    "sg:address":"Avda Galicia, 314",
    "sg:city":"Fuentes Nuevas",
    "sg:orig_category":"Electricidad, Electr\u00d3nica: Material Y Suministros (al Por Mayor)",
    "sg:phone":"+34 987 45 57 06",
    "sg:postcode":"24411",
    "sg:province":"Le\u00f3n",
    "wof:name":"Moran Alvarez Valeriano",
    "wof:placetype":"venue"
},
  "geometry": {"coordinates":[-6.6439290047,42.5685310364],"type":"Point"}
}