{
  "type": "Feature",
  "properties": {
    "addr:full":"Calle de Burdeos, S/n Cuatrovientos Le\u00f3n 24400",
    "addr:housenumber":"s / n",
    "addr:postcode":"24400",
    "addr:street":"Calle De Burdeos",
    "iso:country":"ES",
    "sg:address":"Calle de Burdeos, S/n",
    "sg:city":"Cuatrovientos",
    "sg:orig_category":"Agentes, Concesionarios Y Sucursales De Veh\u00cdculos",
    "sg:phone":"+34 987 40 94 91",
    "sg:postcode":"24400",
    "sg:province":"Le\u00f3n",
    "wof:name":"Sertecauto S.l.",
    "wof:placetype":"venue"
},
  "geometry": {"coordinates":[-6.5983390808,42.5483360291],"type":"Point"}
}