{
  "type": "Feature",
  "properties": {
    "addr:full":"Calle de Alemania, S/n Malaga M\u00e1laga 29001",
    "addr:housenumber":"s / n",
    "addr:postcode":"29001",
    "addr:street":"Calle De Alemania;Ma\u0301Laga",
    "iso:country":"ES",
    "sg:address":"Calle de Alemania, S/n",
    "sg:city":"Malaga",
    "sg:orig_category":"Centros De Educaci\u00d3n Especial",
    "sg:phone":"+34 952 22 18 81",
    "sg:postcode":"29001",
    "sg:province":"M\u00e1laga",
    "wof:name":"Junta De Andalucia",
    "wof:placetype":"venue"
},
  "geometry": {"coordinates":[-4.4249873161,36.7138175964],"type":"Point"}
}