{
  "type": "Feature",
  "properties": {
    "addr:full":"Calle de Calatrava, 44 San Vicente Del Raspeig-sant Vicent Del Raspeig Alicante 03690",
    "addr:housenumber":"44",
    "addr:postcode":"03690",
    "addr:street":"Calle De Calatrava",
    "iso:country":"ES",
    "sg:address":"Calle de Calatrava, 44",
    "sg:city":"San Vicente Del Raspeig-sant Vicent Del Raspeig",
    "sg:orig_category":"Mantenimiento Industrial",
    "sg:phone":"+34 965 67 26 86",
    "sg:postcode":"03690",
    "sg:province":"Alicante",
    "wof:name":"Sermihe S.l.",
    "wof:placetype":"venue"
},
  "geometry": {"coordinates":[-0.5409190059,38.399181366],"type":"Point"}
}