{
  "type": "Feature",
  "properties": {
    "iso:country":"ES",
    "sg:address":"Avda Espa\u00d1a (de), 21",
    "sg:city":"Priego Cordoba",
    "sg:orig_category":"Complementos De Vestir (al Por Menor)",
    "sg:phone":"+34 957 54 72 68",
    "sg:postcode":"14800",
    "sg:province":"C\u00f3rdoba",
    "wof:name":"Dominguez Osuna Cristina",
    "wof:placetype":"venue"
},
  "geometry": {"coordinates":[-4.2034840584,37.4391212463],"type":"Point"}
}