{
  "type": "Feature",
  "properties": {
    "addr:full":"Mcdo Triana, S/n Sevilla Sevilla 41010",
    "addr:housenumber":"s / n",
    "addr:postcode":"41010",
    "iso:country":"ES",
    "sg:address":"Mcdo Triana, S/n",
    "sg:city":"Sevilla",
    "sg:orig_category":"Pescader\u00cdas (al Por Menor)",
    "sg:phone":"+34 954 34 34 02",
    "sg:postcode":"41010",
    "sg:province":"Sevilla",
    "wof:name":"Estela Sanchez Manuel",
    "wof:placetype":"venue"
},
  "geometry": {"coordinates":[-6.0107140541,37.3880081177],"type":"Point"}
}