{
  "type": "Feature",
  "properties": {
    "addr:full":"Carrer de Wagner, 19 Rubi Barcelona 08191",
    "addr:housenumber":"19",
    "addr:postcode":"08191",
    "addr:street":"Carrer De Wagner",
    "iso:country":"ES",
    "sg:address":"Carrer de Wagner, 19",
    "sg:city":"Rubi",
    "sg:orig_category":"Fabricaci\u00d3n De Moldes Y Modelos",
    "sg:phone":"+34 936 97 27 41",
    "sg:postcode":"08191",
    "sg:province":"Barcelona",
    "wof:name":"G Mes B S.l.",
    "wof:placetype":"venue"
},
  "geometry": {"coordinates":[2.0242469311,41.4705543518],"type":"Point"}
}