{
  "type": "Feature",
  "properties": {
    "iso:country":"ES",
    "sg:address":"Calle de Nuestra Se\u00d1ora De Las Mercedes, 3",
    "sg:city":"Priego Cordoba",
    "sg:orig_category":"Iglesia Cat\u00d3lica",
    "sg:phone":"+34 957 54 07 13",
    "sg:postcode":"14800",
    "sg:province":"C\u00f3rdoba",
    "wof:name":"Parroquia Nuestra Se\u00f1ora Del Carmen",
    "wof:placetype":"venue"
},
  "geometry": {"coordinates":[-4.2015590668,37.4397315979],"type":"Point"}
}