{
  "type": "Feature",
  "properties": {
    "iso:country":"ES",
    "sg:address":"Carrer de Mossen Comellas, 7",
    "sg:city":"Berga-ciudad",
    "sg:orig_category":"M\u00c9dicos: An\u00c1lisis Cl\u00cdnicos",
    "sg:phone":"+34 938 22 08 22",
    "sg:postcode":"08600",
    "sg:province":"Barcelona",
    "wof:name":"Laboratorio De Analisis Clinicos Dr. Badal S. A.",
    "wof:placetype":"venue"
},
  "geometry": {"coordinates":[1.8456009626,42.1036186218],"type":"Point"}
}