{
  "type": "Feature",
  "properties": {
    "iso:country":"ES",
    "sg:address":"Carrer de Mallorca, 307",
    "sg:city":"Barcelona",
    "sg:orig_category":"M\u00c9dicos: Pediatr\u00cda. Enfermedades De Los Ni\u00d1os",
    "sg:phone":"+34 932 07 44 60",
    "sg:postcode":"08037",
    "sg:province":"Barcelona",
    "wof:name":"Armenteras Corona Antonio",
    "wof:placetype":"venue"
},
  "geometry": {"coordinates":[2.1667916775,41.3970565796],"type":"Point"}
}