{
  "type": "Feature",
  "properties": {
    "iso:country":"ES",
    "sg:address":"Rua Barcelona, 51",
    "sg:city":"Vigo",
    "sg:orig_category":"Prot\u00c9sicos Dentales",
    "sg:phone":"+34 986 48 45 48",
    "sg:postcode":"36203",
    "sg:province":"Pontevedra",
    "wof:name":"Cabaleiro Santos Fernando",
    "wof:placetype":"venue"
},
  "geometry": {"coordinates":[-8.7247915268,42.2246017456],"type":"Point"}
}