{
  "type": "Feature",
  "properties": {
    "iso:country":"ES",
    "sg:address":"Carr Mossen Jacint Verdaguer, S/n",
    "sg:city":"Bellpuig",
    "sg:orig_category":"Delegados, Agentes De Tr\u00c1nsito, Auxiliares De Transporte Internacional",
    "sg:phone":"+34 973 32 08 80",
    "sg:postcode":"25250",
    "sg:province":"Lleida",
    "wof:name":"Armengol Llobregat Jose",
    "wof:placetype":"venue"
},
  "geometry": {"coordinates":[1.0100132227,41.6298027039],"type":"Point"}
}