{
  "type": "Feature",
  "properties": {
    "addr:full":"Avda Sancho El Sabio, 23 Donostia-san Sebastian Guip\u00f9zcoa 20010",
    "addr:housenumber":"23",
    "addr:postcode":"20010",
    "addr:street":"Avda Sancho El Sabio",
    "iso:country":"ES",
    "sg:address":"Avda Sancho El Sabio, 23",
    "sg:city":"Donostia-san Sebastian",
    "sg:orig_category":"Arquitectos",
    "sg:phone":"+34 943 45 24 84",
    "sg:postcode":"20010",
    "sg:province":"Guip\u00f9zcoa",
    "wof:name":"Martinez Rodriguez Patricia",
    "wof:placetype":"venue"
},
  "geometry": {"coordinates":[-1.979872942,43.3094482422],"type":"Point"}
}