{
  "type": "Feature",
  "properties": {
    "addr:full":"Calle de Rio Sella, 18 Oviedo Asturias 33010",
    "addr:housenumber":"18",
    "addr:postcode":"33010",
    "addr:street":"Calle De Rio Sella",
    "iso:country":"ES",
    "sg:address":"Calle de Rio Sella, 18",
    "sg:city":"Oviedo",
    "sg:orig_category":"Carnicer\u00cdas, Carnicer\u00cdas",
    "sg:phone":"+34 985 28 79 21",
    "sg:postcode":"33010",
    "sg:province":"Asturias",
    "wof:name":"Gonzalez Fernandez Vicente",
    "wof:placetype":"venue"
},
  "geometry": {"coordinates":[-5.8286728859,43.3680915833],"type":"Point"}
}