{
  "type": "Feature",
  "properties": {
    "addr:full":"Calle de Mayor Antigua, 66 Palencia Palencia 34005",
    "addr:housenumber":"66",
    "addr:postcode":"34005",
    "addr:street":"Calle De Mayor Antigua",
    "iso:country":"ES",
    "sg:address":"Calle de Mayor Antigua, 66",
    "sg:city":"Palencia",
    "sg:orig_category":"Charcuter\u00cdas (al Por Mayor)",
    "sg:phone":"+34 979 74 14 15",
    "sg:postcode":"34005",
    "sg:province":"Palencia",
    "wof:name":"Vicario Diaz Alfonso",
    "wof:placetype":"venue"
},
  "geometry": {"coordinates":[-4.5352740288,42.0080299377],"type":"Point"}
}