{
  "type": "Feature",
  "properties": {
    "addr:full":"Avda Estacion, 57 Torrijos Toledo 45500",
    "addr:housenumber":"57",
    "addr:postcode":"45500",
    "addr:street":"Avda Estacion",
    "iso:country":"ES",
    "sg:address":"Avda Estacion, 57",
    "sg:city":"Torrijos",
    "sg:orig_category":"Abogados",
    "sg:phone":"+34 925 77 08 84",
    "sg:postcode":"45500",
    "sg:province":"Toledo",
    "wof:name":"Casta\u00f1o Sanchez Alfonso",
    "wof:placetype":"venue"
},
  "geometry": {"coordinates":[-4.2822489738,39.9811515808],"type":"Point"}
}