{
  "type": "Feature",
  "properties": {
    "addr:full":"C/ Espanya, 17 Puigcerda Girona 17520",
    "addr:housenumber":"17",
    "addr:postcode":"17520",
    "addr:street":"C / Espanya",
    "iso:country":"ES",
    "sg:address":"C/ Espanya, 17",
    "sg:city":"Puigcerda",
    "sg:orig_category":"Perfumer\u00cda (al Por Menor)",
    "sg:phone":"+34 972 14 11 25",
    "sg:postcode":"17520",
    "sg:province":"Girona",
    "wof:name":"Cot Castells Dolores",
    "wof:placetype":"venue"
},
  "geometry": {"coordinates":[1.9280780554,42.4321937561],"type":"Point"}
}