{
  "type": "Feature",
  "properties": {
    "addr:full":"Calle de San Jose, 69 Puebla Cazalla Sevilla 41540",
    "addr:housenumber":"69",
    "addr:postcode":"41540",
    "addr:street":"Calle De San;Puebla Cazalla",
    "iso:country":"ES",
    "sg:address":"Calle de San Jose, 69",
    "sg:city":"Puebla Cazalla",
    "sg:orig_category":"Inform\u00c1tica, Ofim\u00c1tica (estudios, Asesor\u00cda, Ingenier\u00cda, Formaci\u00d3n)",
    "sg:phone":"+34 955 84 37 12",
    "sg:postcode":"41540",
    "sg:province":"Sevilla",
    "sg:website":"www.inforpuebla.com",
    "wof:name":"Inforpuebla S.c.",
    "wof:placetype":"venue"
},
  "geometry": {"coordinates":[-5.3106579781,37.2251663208],"type":"Point"}
}