{
  "type": "Feature",
  "properties": {
    "addr:full":"Calle de Avila, 21 Jerez De La Frontera C\u00e1diz 11401",
    "addr:housenumber":"21",
    "addr:postcode":"11401",
    "addr:street":"Calle De Avila",
    "iso:country":"ES",
    "sg:address":"Calle de Avila, 21",
    "sg:city":"Jerez De La Frontera",
    "sg:orig_category":"Tapicer\u00cdas",
    "sg:phone":"+34 956 34 09 43",
    "sg:postcode":"11401",
    "sg:province":"C\u00e1diz",
    "wof:name":"Coro Iglesias Francisco",
    "wof:placetype":"venue"
},
  "geometry": {"coordinates":[-6.1324481964,36.6827507019],"type":"Point"}
}