{
  "type": "Feature",
  "properties": {
    "iso:country":"ES",
    "sg:address":"Calle de Carretera, S/n",
    "sg:city":"S. Salvador Cantamuda",
    "sg:orig_category":"Carnicer\u00cdas, Carnicer\u00cdas",
    "sg:phone":"+34 979 87 90 27",
    "sg:postcode":"34847",
    "sg:province":"Palencia",
    "wof:name":"Lozavi S.l.",
    "wof:placetype":"venue"
},
  "geometry": {"coordinates":[-4.4947886467,42.968624115],"type":"Point"}
}