{
  "type": "Feature",
  "properties": {
    "addr:full":"Avda Cidacos (del), 21 Arnedillo La Rioja 26589",
    "addr:housenumber":"21",
    "addr:postcode":"26589",
    "addr:street":"Avda Cidacos Del;Rioja",
    "iso:country":"ES",
    "sg:address":"Avda Cidacos (del), 21",
    "sg:city":"Arnedillo",
    "sg:orig_category":"Alimentaci\u00d3n General (al Por Menor)",
    "sg:phone":"+34 941 39 41 07",
    "sg:postcode":"26589",
    "sg:province":"La Rioja",
    "wof:name":"Martinez Vicu\u00f1a Angel",
    "wof:placetype":"venue"
},
  "geometry": {"coordinates":[-2.2360579967,42.2136154175],"type":"Point"}
}