{
  "type": "Feature",
  "properties": {
    "addr:full":"Calle de Pilar (el), 15 Virgen Camino Le\u00f3n 24198",
    "addr:housenumber":"15",
    "addr:postcode":"24198",
    "addr:street":"Calle De Pilar El;Camino Leo\u0301N",
    "iso:country":"ES",
    "sg:address":"Calle de Pilar (el), 15",
    "sg:city":"Virgen Camino",
    "sg:orig_category":"Electricidad: Instalaciones Industriales",
    "sg:phone":"+34 987 30 01 11",
    "sg:postcode":"24198",
    "sg:province":"Le\u00f3n",
    "wof:name":"Lar E Hijos S.l.",
    "wof:placetype":"venue"
},
  "geometry": {"coordinates":[-5.640859127,42.5807914734],"type":"Point"}
}