{
  "type": "Feature",
  "properties": {
    "iso:country":"ES",
    "sg:address":"Calle de Real, 9",
    "sg:city":"Guillena",
    "sg:orig_category":"Asesor\u00cda Fiscal Y Jur\u00cddica",
    "sg:phone":"+34 955 78 40 74",
    "sg:postcode":"41210",
    "sg:province":"Sevilla",
    "sg:website":"www.rutaplata.com",
    "wof:name":"Consultores Ruta De La Plata S.l.",
    "wof:placetype":"venue"
},
  "geometry": {"coordinates":[-6.0517148972,37.5387763977],"type":"Point"}
}