{
  "type": "Feature",
  "properties": {
    "addr:full":"Arribes Del Duero, 19 Cabrerizos Salamanca 37193",
    "addr:housenumber":"19",
    "addr:postcode":"37193",
    "addr:street":"Del Duero",
    "iso:country":"ES",
    "sg:address":"Arribes Del Duero, 19",
    "sg:city":"Cabrerizos",
    "sg:orig_category":"Papeler\u00cdas: Art\u00cdculos (al Por Mayor)",
    "sg:phone":"+34 923 20 93 80",
    "sg:postcode":"37193",
    "sg:province":"Salamanca",
    "wof:name":"Distribucion De Papeleria Nebrija S.l.",
    "wof:placetype":"venue"
},
  "geometry": {"coordinates":[-5.610394001,40.9808654785],"type":"Point"}
}