{
  "type": "Feature",
  "properties": {
    "iso:country":"ES",
    "sg:address":"Calle de Andres Ochando, 32",
    "sg:city":"Casas De Juan Nu\u00e7ez",
    "sg:orig_category":"Contenedores (mercanc\u00cdas)",
    "sg:phone":"+34 967 40 50 66",
    "sg:postcode":"02151",
    "sg:province":"Albacete",
    "wof:name":"Moreno Moyano Antonio",
    "wof:placetype":"venue"
},
  "geometry": {"coordinates":[-1.559731245,39.1015930176],"type":"Point"}
}