{
  "type": "Feature",
  "properties": {
    "addr:full":"Plaz Gipuzkoa De, 15 Donostia-san Sebastian Guip\u00f9zcoa 20004",
    "addr:housenumber":"15",
    "addr:postcode":"20004",
    "iso:country":"ES",
    "sg:address":"Plaz Gipuzkoa De, 15",
    "sg:city":"Donostia-san Sebastian",
    "sg:orig_category":"Abogados",
    "sg:phone":"+34 943 42 65 10",
    "sg:postcode":"20004",
    "sg:province":"Guip\u00f9zcoa",
    "wof:name":"Oqui\u00f1ena Perello Joaquin",
    "wof:placetype":"venue"
},
  "geometry": {"coordinates":[-1.9820890427,43.3208122253],"type":"Point"}
}