{
  "type": "Feature",
  "properties": {
    "iso:country":"ES",
    "sg:address":"Calle de Letra O, S/n",
    "sg:city":"Puebla Alfinden",
    "sg:classifiers":[
        {
            "category":"Banks & Credit Unions",
            "subcategory":"Bureau De Change",
            "type":"Services"
        }
    ],
    "sg:phone":"+34 976 45 59 26",
    "sg:postcode":"50171",
    "sg:province":"Zaragoza",
    "sg:tags":[
        "organismos",
        "control"
    ],
    "wof:name":"Servicios Control Inspeccion S.a.",
    "wof:placetype":"venue"
},
  "geometry": {"coordinates":[-0.759814024,41.6387748718],"type":"Point"}
}