{
  "type": "Feature",
  "properties": {
    "iso:country":"ES",
    "sg:address":"Calle de Rey Juan Carlos I, 3",
    "sg:city":"Elda",
    "sg:orig_category":"Asociaciones Y Clubs Deportivos",
    "sg:phone":"+34 965 39 17 93",
    "sg:postcode":"03600",
    "sg:province":"Alicante",
    "wof:name":"Zacha Sport S.l.",
    "wof:placetype":"venue"
},
  "geometry": {"coordinates":[-0.7931050062,38.4780311584],"type":"Point"}
}