{
  "type": "Feature",
  "properties": {
    "addr:full":"Carrer de Gran De Gracia, 56 Barcelona Barcelona 08012",
    "addr:housenumber":"56",
    "addr:postcode":"08012",
    "addr:street":"Carrer De Gran De Gracia",
    "iso:country":"ES",
    "sg:address":"Carrer de Gran De Gracia, 56",
    "sg:city":"Barcelona",
    "sg:orig_category":"Art\u00cdculos De Regalo (al Por Menor)",
    "sg:phone":"+34 934 16 16 35",
    "sg:postcode":"08012",
    "sg:province":"Barcelona",
    "wof:name":"Gonzalez Perez Olga",
    "wof:placetype":"venue"
},
  "geometry": {"coordinates":[2.1562271118,41.3994216919],"type":"Point"}
}