{
  "type": "Feature",
  "properties": {
    "addr:full":"Calle de Vazquez Aroca, 23 Cordoba C\u00f3rdoba 14005",
    "addr:housenumber":"23",
    "addr:postcode":"14005",
    "addr:street":"Calle De;Aroca;Co\u0301Rdoba",
    "iso:country":"ES",
    "sg:address":"Calle de Vazquez Aroca, 23",
    "sg:city":"Cordoba",
    "sg:orig_category":"Art\u00cdculos De Regalo (al Por Menor)",
    "sg:phone":"+34 957 23 28 12",
    "sg:postcode":"14005",
    "sg:province":"C\u00f3rdoba",
    "wof:name":"Recena Noguera Joaquin",
    "wof:placetype":"venue"
},
  "geometry": {"coordinates":[-4.7921662331,37.8836936951],"type":"Point"}
}