{
  "type": "Feature",
  "properties": {
    "iso:country":"ES",
    "sg:address":"Avda Federico Garcia Lorca, 91",
    "sg:city":"Almeria",
    "sg:orig_category":"Par\u00cds",
    "sg:phone":"+34 950 25 35 76",
    "sg:postcode":"04004",
    "sg:province":"Almer\u00eda",
    "wof:name":"Verde Martinez Maria Mercedes",
    "wof:placetype":"venue"
},
  "geometry": {"coordinates":[-2.4588239193,36.8411521912],"type":"Point"}
}