{
  "type": "Feature",
  "properties": {
    "addr:full":"Calle de Concejo, 13 Salamanca Salamanca 37002",
    "addr:housenumber":"13",
    "addr:postcode":"37002",
    "addr:street":"Calle De Concejo",
    "iso:country":"ES",
    "sg:address":"Calle de Concejo, 13",
    "sg:city":"Salamanca",
    "sg:orig_category":"Zapatos (al Por Menor)",
    "sg:phone":"+34 923 21 99 70",
    "sg:postcode":"37002",
    "sg:province":"Salamanca",
    "wof:name":"Mayor 90 S.a.",
    "wof:placetype":"venue"
},
  "geometry": {"coordinates":[-5.6642885208,40.9663276672],"type":"Point"}
}