{
  "type": "Feature",
  "properties": {
    "iso:country":"ES",
    "sg:address":"Calle de Cervantes, 7",
    "sg:city":"Pobla Vallbona",
    "sg:orig_category":"Masajistas Kinesiterapeutas",
    "sg:phone":"+34 961 66 17 75",
    "sg:postcode":"46185",
    "sg:province":"Valencia",
    "wof:name":"Chilet Navarro Maria Remedios",
    "wof:placetype":"venue"
},
  "geometry": {"coordinates":[-0.5535392761,39.5938835144],"type":"Point"}
}