{
  "type": "Feature",
  "properties": {
    "addr:full":"Pol Ind Moli Planes, S/n S. Celoni Barcelona 08470",
    "addr:housenumber":"s",
    "addr:postcode":"08470",
    "addr:street":"Planes;/ N S. Celoni Barcelona",
    "iso:country":"ES",
    "sg:address":"Pol Ind Moli Planes, S/n",
    "sg:city":"S. Celoni",
    "sg:orig_category":"Construcciones Met\u00c1licas",
    "sg:phone":"+34 938 67 37 42",
    "sg:postcode":"08470",
    "sg:province":"Barcelona",
    "wof:name":"Metacel S.l.",
    "wof:placetype":"venue"
},
  "geometry": {"coordinates":[2.489289999,41.6902389526],"type":"Point"}
}