{
  "type": "Feature",
  "properties": {
    "iso:country":"ES",
    "sg:address":"Pla\u00c7 Josep Pla I Casadevall, 4",
    "sg:city":"Girona",
    "sg:orig_category":"Asesor\u00cda Sobre Comunicaci\u00d3n De Empresas",
    "sg:phone":"+34 972 20 35 00",
    "sg:postcode":"17001",
    "sg:province":"Girona",
    "wof:name":"Vialegis Girona S.l.",
    "wof:placetype":"venue"
},
  "geometry": {"coordinates":[2.8187448978,41.9808616638],"type":"Point"}
}