{
  "type": "Feature",
  "properties": {
    "iso:country":"ES",
    "sg:address":"Pase San Antonio, S/n",
    "sg:city":"Palazuelos Eresma",
    "sg:orig_category":"Alimentaci\u00d3n General (al Por Menor)",
    "sg:phone":"+34 921 44 92 30",
    "sg:postcode":"40194",
    "sg:province":"Segovia",
    "wof:name":"Herrero Martin Antonio",
    "wof:placetype":"venue"
},
  "geometry": {"coordinates":[-4.0600042343,40.9310340881],"type":"Point"}
}