{
  "type": "Feature",
  "properties": {
    "addr:full":"Cami Can Castellvi, 27 Barcelona Barcelona 08017",
    "addr:housenumber":"27",
    "addr:postcode":"08017",
    "addr:street":"Can Castellvi",
    "iso:country":"ES",
    "sg:address":"Cami Can Castellvi, 27",
    "sg:city":"Barcelona",
    "sg:orig_category":"Textil",
    "sg:phone":"+34 932 80 10 52",
    "sg:postcode":"08017",
    "sg:province":"Barcelona",
    "wof:name":"Teixits Sants S.l.",
    "wof:placetype":"venue"
},
  "geometry": {"coordinates":[2.0853850842,41.421459198],"type":"Point"}
}