{
  "type": "Feature",
  "properties": {
    "iso:country":"ES",
    "sg:address":"Calle de Violeta, 15",
    "sg:city":"Alcala Henares",
    "sg:orig_category":"Peluqueros: De Se\u00d1oras",
    "sg:phone":"+34 918 83 28 18",
    "sg:postcode":"28803",
    "sg:province":"Madrid",
    "wof:name":"Parra Ruiz Consuelo",
    "wof:placetype":"venue"
},
  "geometry": {"coordinates":[-3.3718109131,40.4754371643],"type":"Point"}
}