{
  "type": "Feature",
  "properties": {
    "addr:full":"Masti-loidi, 15 D Errenteria Guip\u00f9zcoa 20100",
    "addr:housenumber":"15 d",
    "addr:postcode":"20100",
    "addr:street":"Masti-Loidi;Guipu\u0300Zcoa",
    "iso:country":"ES",
    "sg:address":"Masti-loidi, 15 D",
    "sg:city":"Errenteria",
    "sg:orig_category":"Embalajes",
    "sg:phone":"+34 943 26 09 64",
    "sg:postcode":"20100",
    "sg:province":"Guip\u00f9zcoa",
    "sg:website":"www.serviembalaje.com",
    "wof:name":"Euskopackaging Sl",
    "wof:placetype":"venue"
},
  "geometry": {"coordinates":[-1.8970370293,43.3210067749],"type":"Point"}
}