{
  "type": "Feature",
  "properties": {
    "iso:country":"ES",
    "sg:address":"Carrer de Demostenes, 34",
    "sg:city":"Sabadell",
    "sg:orig_category":"Art\u00cdculos De Regalo (al Por Menor)",
    "sg:phone":"+34 937 23 92 65",
    "sg:postcode":"08206",
    "sg:province":"Barcelona",
    "wof:name":"Romero Garcia Gabriel",
    "wof:placetype":"venue"
},
  "geometry": {"coordinates":[2.0859279633,41.5549888611],"type":"Point"}
}