{
  "type": "Feature",
  "properties": {
    "addr:full":"Praz Ferrol (de), 6 Lugo Lugo 27001",
    "addr:postcode":"27001",
    "addr:street":"Praz;De 6",
    "iso:country":"ES",
    "sg:address":"Praz Ferrol (de), 6",
    "sg:city":"Lugo",
    "sg:orig_category":"\u00d3ptica: Instrumentos (fabricaci\u00d3n)",
    "sg:phone":"+34 982 24 71 14",
    "sg:postcode":"27001",
    "sg:province":"Lugo",
    "wof:name":"Garcia Garcia C.b",
    "wof:placetype":"venue"
},
  "geometry": {"coordinates":[-7.5570349693,43.0139923096],"type":"Point"}
}