{
  "type": "Feature",
  "properties": {
    "iso:country":"ES",
    "sg:address":"Calle de Federico Tapia, 37",
    "sg:city":"Coru\u00d1a",
    "sg:orig_category":"Ropa Para Caballeros (al Por Menor)",
    "sg:phone":"+34 981 12 04 27",
    "sg:postcode":"15005",
    "sg:province":"La Coru\u00f1a",
    "wof:name":"Maria Jesus Bran S.l.",
    "wof:placetype":"venue"
},
  "geometry": {"coordinates":[-8.4062042236,43.3627700806],"type":"Point"}
}