{
  "type": "Feature",
  "properties": {
    "addr:full":"Carrer de Costa, 44 Barcelona Barcelona 08023",
    "addr:housenumber":"44",
    "addr:postcode":"08023",
    "addr:street":"Carrer De Costa",
    "iso:country":"ES",
    "sg:address":"Carrer de Costa, 44",
    "sg:city":"Barcelona",
    "sg:orig_category":"Cristaler\u00cdas",
    "sg:phone":"+34 932 10 06 45",
    "sg:postcode":"08023",
    "sg:province":"Barcelona",
    "wof:name":"Calmell Iba\u00f1ez Maria Angeles",
    "wof:placetype":"venue"
},
  "geometry": {"coordinates":[2.1455900669,41.4097061157],"type":"Point"}
}