{
  "type": "Feature",
  "properties": {
    "addr:full":"C/ Vila De Bilbao, 9 Paterna Valencia 46988",
    "addr:housenumber":"9",
    "addr:postcode":"46988",
    "addr:street":"C / Vila De Bilbao",
    "iso:country":"ES",
    "sg:address":"C/ Vila De Bilbao, 9",
    "sg:city":"Paterna",
    "sg:orig_category":"Fabricaci\u00d3n, Importaci\u00d3n De L\u00c1mparas Y Bombillas",
    "sg:phone":"+34 961 34 09 04",
    "sg:postcode":"46988",
    "sg:province":"Valencia",
    "sg:website":"www.lopezescriba.com",
    "wof:name":"Ricardo Lopez Escriba S.a.",
    "wof:placetype":"venue"
},
  "geometry": {"coordinates":[-0.4625450075,39.51537323],"type":"Point"}
}