{
  "type": "Feature",
  "properties": {
    "addr:full":"Calle de Soria, 1 Briviesca Burgos 09240",
    "addr:housenumber":"1",
    "addr:postcode":"09240",
    "addr:street":"Calle De Soria",
    "iso:country":"ES",
    "sg:address":"Calle de Soria, 1",
    "sg:city":"Briviesca",
    "sg:orig_category":"F\u00c1bricas De Ladrillo Y Tejas",
    "sg:phone":"+34 947 59 20 63",
    "sg:postcode":"09240",
    "sg:province":"Burgos",
    "wof:name":"Ceramica Llanos S. A.",
    "wof:placetype":"venue"
},
  "geometry": {"coordinates":[-3.3209569454,42.5579452515],"type":"Point"}
}