{
  "type": "Feature",
  "properties": {
    "iso:country":"ES",
    "sg:address":"Calle de Sabino Arana Kalea, 62",
    "sg:city":"Berango",
    "sg:orig_category":"Electricidad: Equipos Industriales, Componentes (fabricaci\u00d3n)",
    "sg:phone":"+34 946 68 20 45",
    "sg:postcode":"48640",
    "sg:province":"Vizcaya",
    "wof:name":"Comercial Tecasa S.l.",
    "wof:placetype":"venue"
},
  "geometry": {"coordinates":[-2.9984579086,43.3724937439],"type":"Point"}
}