{
  "type": "Feature",
  "properties": {
    "addr:full":"Calle de Padre Melchor De Benisa, 7 Totana Murcia 30850",
    "addr:housenumber":"7",
    "addr:postcode":"30850",
    "addr:street":"Calle De Padre Melchor De Benisa",
    "iso:country":"ES",
    "sg:address":"Calle de Padre Melchor De Benisa, 7",
    "sg:city":"Totana",
    "sg:orig_category":"Ropa Para Ni\u00d1os (al Por Menor)",
    "sg:phone":"+34 968 42 52 87",
    "sg:postcode":"30850",
    "sg:province":"Murcia",
    "wof:name":"Campos Canovas Andrea",
    "wof:placetype":"venue"
},
  "geometry": {"coordinates":[-1.5008640289,37.7719116211],"type":"Point"}
}