{
  "type": "Feature",
  "properties": {
    "iso:country":"ES",
    "sg:address":"Calle de Soledad (la), S/n",
    "sg:city":"Cifuentes",
    "sg:orig_category":"Supermercados Y Hipermercados",
    "sg:phone":"+34 949 81 02 51",
    "sg:postcode":"19420",
    "sg:province":"Guadalajara",
    "wof:name":"Garrido Perez Julio",
    "wof:placetype":"venue"
},
  "geometry": {"coordinates":[-2.6225841045,40.7811737061],"type":"Point"}
}