{
  "type": "Feature",
  "properties": {
    "iso:country":"ES",
    "sg:address":"Carretera Vella De Palafrugel, 1",
    "sg:city":"Palafrugell",
    "sg:orig_category":"Parques De Atracciones Y Centros De Esparcimiento",
    "sg:phone":"+34 972 30 59 14",
    "sg:postcode":"17200",
    "sg:province":"Girona",
    "wof:name":"Limpopo S.l.",
    "wof:placetype":"venue"
},
  "geometry": {"coordinates":[3.1597599983,41.9181594849],"type":"Point"}
}