{
  "type": "Feature",
  "properties": {
    "iso:country":"ES",
    "sg:address":"Avda Reconquista, 5",
    "sg:city":"Ayllon",
    "sg:orig_category":"Mec\u00c1nico Del Autom\u00d3vil",
    "sg:phone":"+34 921 55 32 73",
    "sg:postcode":"40520",
    "sg:province":"Segovia",
    "wof:name":"Alonso Barahona Milagros Maria",
    "wof:placetype":"venue"
},
  "geometry": {"coordinates":[-3.3832895756,41.4176368713],"type":"Point"}
}