{
  "type": "Feature",
  "properties": {
    "iso:country":"ES",
    "sg:address":"Calle de Jose Navarro Morenes, 10",
    "sg:city":"Tiemblo",
    "sg:orig_category":"Ense\u00d1anza, Formaci\u00d3n Profesional: Aprendizaje",
    "sg:phone":"+34 918 62 55 04",
    "sg:postcode":"05270",
    "sg:province":"\u00c1vila",
    "wof:name":"Ayuntamiento De El Tiemblo",
    "wof:placetype":"venue"
},
  "geometry": {"coordinates":[-4.5027728081,40.415725708],"type":"Point"}
}