{
  "type": "Feature",
  "properties": {
    "iso:country":"ES",
    "sg:address":"P. Calatayud, 1",
    "sg:city":"Iru\u00f1a",
    "sg:orig_category":"Arquitectos",
    "sg:phone":"+34 948 29 22 44",
    "sg:postcode":"31003",
    "sg:province":"Navarra",
    "wof:name":"Cl Arquitectos",
    "wof:placetype":"venue"
},
  "geometry": {"coordinates":[-1.6426889896,42.8116798401],"type":"Point"}
}