{
  "type": "Feature",
  "properties": {
    "iso:country":"ES",
    "sg:address":"Carrer de L'argenteria, 57",
    "sg:city":"Barcelona",
    "sg:orig_category":"Electrodom\u00c9sticos (al Por Menor)",
    "sg:phone":"+34 933 10 04 39",
    "sg:postcode":"08003",
    "sg:province":"Barcelona",
    "wof:name":"Santiago Bernat Ramon",
    "wof:placetype":"venue"
},
  "geometry": {"coordinates":[2.1808536053,41.3835945129],"type":"Point"}
}