{
  "type": "Feature",
  "properties": {
    "iso:country":"ES",
    "sg:address":"Plaz Sp Vista Alegre, Plz, S/n",
    "sg:city":"San Pedro Alcantara",
    "sg:orig_category":"Expertos Contables",
    "sg:phone":"+34 952 78 34 86",
    "sg:postcode":"29670",
    "sg:province":"M\u00e1laga",
    "wof:name":"Asesoria Troyano S.l.",
    "wof:placetype":"venue"
},
  "geometry": {"coordinates":[-4.9894766808,36.4856033325],"type":"Point"}
}