{
  "type": "Feature",
  "properties": {
    "iso:country":"ES",
    "sg:address":"Rigoberto Diaz Melero, 9",
    "sg:city":"G\u00fcimar",
    "sg:orig_category":"\u00d3ptica: Instrumentos (fabricaci\u00d3n)",
    "sg:phone":"+34 922 51 20 58",
    "sg:postcode":"38500",
    "sg:province":"Santa Cruz De Tenerife",
    "wof:name":"Perez Duque Maria Eugenia",
    "wof:placetype":"venue"
},
  "geometry": {"coordinates":[-16.4106941223,28.3129482269],"type":"Point"}
}