{
  "type": "Feature",
  "properties": {
    "addr:full":"Avda Puente De Carlos Iii, 46 Reinosa Cantabria 39200",
    "addr:housenumber":"46",
    "addr:postcode":"39200",
    "addr:street":"Avda Puente De Carlos Iii",
    "iso:country":"ES",
    "sg:address":"Avda Puente De Carlos Iii, 46",
    "sg:city":"Reinosa",
    "sg:orig_category":"Caf\u00c9s, Bares, Cervecer\u00cdas",
    "sg:phone":"+34 942 75 42 78",
    "sg:postcode":"39200",
    "sg:province":"Cantabria",
    "wof:name":"Sociedad Regional De Informatica S.a.",
    "wof:placetype":"venue"
},
  "geometry": {"coordinates":[-4.1397218704,42.9973220825],"type":"Point"}
}