{
  "type": "Feature",
  "properties": {
    "addr:full":"Gta Rosales, 7 Aranda Duero Burgos 09400",
    "addr:housenumber":"7",
    "addr:postcode":"09400",
    "addr:street":"Gta Rosales",
    "iso:country":"ES",
    "sg:address":"Gta Rosales, 7",
    "sg:city":"Aranda Duero",
    "sg:orig_category":"Zapater\u00cdas",
    "sg:phone":"+34 947 51 04 20",
    "sg:postcode":"09400",
    "sg:province":"Burgos",
    "wof:name":"Molina Ruiz Jose Ramon",
    "wof:placetype":"venue"
},
  "geometry": {"coordinates":[-3.6896350384,41.6660308838],"type":"Point"}
}