{
  "type": "Feature",
  "properties": {
    "iso:country":"ES",
    "sg:address":"Av Joan Xxiii, 110",
    "sg:city":"Masnou",
    "sg:orig_category":"Peluquer\u00cdas, Peluquer\u00cda Mixta",
    "sg:phone":"+34 935 55 52 20",
    "sg:postcode":"08320",
    "sg:province":"Barcelona",
    "wof:name":"Higueras Calvo Maria Del Carmen",
    "wof:placetype":"venue"
},
  "geometry": {"coordinates":[2.3157000542,41.4831085205],"type":"Point"}
}