{
  "type": "Feature",
  "properties": {
    "iso:country":"ES",
    "sg:address":"Calle de Valle Aureliano, 4",
    "sg:city":"Bilbao",
    "sg:orig_category":"Inform\u00c1tica: Mantenimiento Y Reparaci\u00d3n De Ordenadores",
    "sg:phone":"+34 944 22 28 19",
    "sg:postcode":"48010",
    "sg:province":"Vizcaya",
    "wof:name":"Ktuin Sistemas Informaticos S A",
    "wof:placetype":"venue"
},
  "geometry": {"coordinates":[-2.9404571056,43.2594070435],"type":"Point"}
}