{
  "type": "Feature",
  "properties": {
    "iso:country":"ES",
    "sg:address":"Av. Ayala, 2",
    "sg:city":"Amurrio",
    "sg:orig_category":"Molduras, Junquillos, Listones Y Molduras Perforadas",
    "sg:phone":"+34 945 89 08 51",
    "sg:postcode":"01470",
    "sg:province":"\u00c1lava",
    "wof:name":"Guillen Montero Vicente",
    "wof:placetype":"venue"
},
  "geometry": {"coordinates":[-3.0024600029,43.0515708923],"type":"Point"}
}