{
  "type": "Feature",
  "properties": {
    "iso:country":"ES",
    "sg:address":"Calle de Curas, 12",
    "sg:city":"Torrejon Ardoz",
    "sg:orig_category":"Ropa Para Se\u00d1oras Y Caballeros (al Por Menor)",
    "sg:phone":"+34 916 77 41 28",
    "sg:postcode":"28850",
    "sg:province":"Madrid",
    "wof:name":"Chen  Caiping",
    "wof:placetype":"venue"
},
  "geometry": {"coordinates":[-3.4791681767,40.4604682922],"type":"Point"}
}