{
  "type": "Feature",
  "properties": {
    "addr:full":"Carr Mestre Narcis Millan, 12 Albuixech Valencia 46550",
    "addr:housenumber":"12",
    "addr:postcode":"46550",
    "addr:street":"Carr Mestre Narcis Millan",
    "iso:country":"ES",
    "sg:address":"Carr Mestre Narcis Millan, 12",
    "sg:city":"Albuixech",
    "sg:orig_category":"Insecticidas, Fumigaci\u00d3n",
    "sg:phone":"+34 961 40 08 02",
    "sg:postcode":"46550",
    "sg:province":"Valencia",
    "wof:name":"Jose Ruiz Lleida Y Otros Cdad",
    "wof:placetype":"venue"
},
  "geometry": {"coordinates":[-0.324097991,39.5436401367],"type":"Point"}
}