{
  "type": "Feature",
  "properties": {
    "addr:full":"Carrer de Pujades, 128 Barcelona Barcelona 08005",
    "addr:housenumber":"128",
    "addr:postcode":"08005",
    "addr:street":"Carrer De Pujades",
    "iso:country":"ES",
    "sg:address":"Carrer de Pujades, 128",
    "sg:city":"Barcelona",
    "sg:orig_category":"Grabados",
    "sg:phone":"+34 933 56 83 10",
    "sg:postcode":"08005",
    "sg:province":"Barcelona",
    "sg:website":"www.virmit.com",
    "wof:name":"Virmit S.a.",
    "wof:placetype":"venue"
},
  "geometry": {"coordinates":[2.1967430115,41.3985061646],"type":"Point"}
}