{
  "type": "Feature",
  "properties": {
    "iso:country":"ES",
    "sg:address":"Carrer de Berenguer Iii, 31",
    "sg:city":"Mollet Valles",
    "sg:orig_category":"\u00d3ptica: Instrumentos (fabricaci\u00d3n)",
    "sg:phone":"+34 935 93 44 01",
    "sg:postcode":"08100",
    "sg:province":"Barcelona",
    "wof:name":"Coll Fornaguera Maria Rosa",
    "wof:placetype":"venue"
},
  "geometry": {"coordinates":[2.2150909901,41.5367469788],"type":"Point"}
}