{
  "type": "Feature",
  "properties": {
    "iso:country":"ES",
    "sg:address":"Calle de Miramadrid, 13",
    "sg:city":"Madrid",
    "sg:orig_category":"Servicios De Telecomunicaciones",
    "sg:phone":"+34 914 76 81 32",
    "sg:postcode":"28026",
    "sg:province":"Madrid",
    "wof:name":"Comunicaciones Internacionales Aris",
    "wof:placetype":"venue"
},
  "geometry": {"coordinates":[-3.7069768906,40.3812561035],"type":"Point"}
}