{
  "type": "Feature",
  "properties": {
    "addr:full":"Calle de Azorin (de), 2 Mostoles Madrid 28935",
    "addr:postcode":"28935",
    "addr:street":"Calle De Azorin De 2 Mostoles",
    "iso:country":"ES",
    "sg:address":"Calle de Azorin (de), 2",
    "sg:city":"Mostoles",
    "sg:orig_category":"Panader\u00cdas, Panader\u00cdas",
    "sg:phone":"+34 916 17 27 01",
    "sg:postcode":"28935",
    "sg:province":"Madrid",
    "wof:name":"Martinez Morate Jesus",
    "wof:placetype":"venue"
},
  "geometry": {"coordinates":[-3.8768312931,40.3219947815],"type":"Point"}
}