{
  "type": "Feature",
  "properties": {
    "iso:country":"ES",
    "sg:address":"Carrer de Girona, 183",
    "sg:city":"S. Feliu Guixols",
    "sg:orig_category":"Promotores Constructores",
    "sg:phone":"+34 972 82 09 74",
    "sg:postcode":"17220",
    "sg:province":"Girona",
    "wof:name":"Construccions Interllag S.l.",
    "wof:placetype":"venue"
},
  "geometry": {"coordinates":[3.0288820267,41.7867279053],"type":"Point"}
}