{
  "type": "Feature",
  "properties": {
    "addr:full":"Calle de Miguel Gallo, 1 Carde\u00f1a C\u00f3rdoba 14445",
    "addr:housenumber":"1",
    "addr:postcode":"14445",
    "addr:street":"Calle De Miguel Gallo;Co\u0301Rdoba",
    "iso:country":"ES",
    "sg:address":"Calle de Miguel Gallo, 1",
    "sg:city":"Carde\u00f1a",
    "sg:orig_category":"Cajas De Ahorro",
    "sg:phone":"+34 957 17 41 29",
    "sg:postcode":"14445",
    "sg:province":"C\u00f3rdoba",
    "wof:name":"Caja De Ahorros Y Monte De Piedad De Cordoba",
    "wof:placetype":"venue"
},
  "geometry": {"coordinates":[-4.3240299225,38.2708587646],"type":"Point"}
}