{
  "type": "Feature",
  "properties": {
    "addr:full":"Calle de Lauria, 9 Ronda M\u00e1laga 29400",
    "addr:housenumber":"9",
    "addr:postcode":"29400",
    "addr:street":"Calle De Lauria;Ronda Ma\u0301Laga",
    "iso:country":"ES",
    "sg:address":"Calle de Lauria, 9",
    "sg:city":"Ronda",
    "sg:orig_category":"Inform\u00c1tica: Mantenimiento Y Reparaci\u00d3n De Ordenadores",
    "sg:phone":"+34 952 19 07 74",
    "sg:postcode":"29400",
    "sg:province":"M\u00e1laga",
    "wof:name":"Aisat S.l.",
    "wof:placetype":"venue"
},
  "geometry": {"coordinates":[-5.1647958755,36.745349884],"type":"Point"}
}