{
  "type": "Feature",
  "properties": {
    "iso:country":"ES",
    "sg:address":"Lloma De Les Clotxes, S/n",
    "sg:city":"Lloma De Les Clotxes",
    "sg:orig_category":"Fabricaci\u00d3n De Art\u00cdculos Para Papeler\u00cdas",
    "sg:phone":"+34 962 13 43 59",
    "sg:postcode":"46169",
    "sg:province":"Valencia",
    "wof:name":"Holmes  Patricia",
    "wof:placetype":"venue"
},
  "geometry": {"coordinates":[-0.5312510133,39.702671051],"type":"Point"}
}