{
  "type": "Feature",
  "properties": {
    "addr:full":"Avda Paskual Abaroa Etorbidea, S/n Lekeitio Vizcaya 48280",
    "addr:housenumber":"s / n",
    "addr:postcode":"48280",
    "addr:street":"Avda Paskual Abaroa Etorbidea",
    "iso:country":"ES",
    "sg:address":"Avda Paskual Abaroa Etorbidea, S/n",
    "sg:city":"Lekeitio",
    "sg:orig_category":"Reposter\u00cdas",
    "sg:phone":"+34 946 24 31 31",
    "sg:postcode":"48280",
    "sg:province":"Vizcaya",
    "wof:name":"Panaderia Zubiona S.l.",
    "wof:placetype":"venue"
},
  "geometry": {"coordinates":[-2.5047960281,43.3640594482],"type":"Point"}
}