{
  "type": "Feature",
  "properties": {
    "addr:full":"Calle de Maestra Maria Del Rosario (de La), 11 Pinto Madrid 28320",
    "addr:postcode":"28320",
    "addr:street":"Calle De Maestra Maria",
    "iso:country":"ES",
    "sg:address":"Calle de Maestra Maria Del Rosario (de La), 11",
    "sg:city":"Pinto",
    "sg:orig_category":"Inmobiliaria (agencias)",
    "sg:phone":"+34 916 91 55 80",
    "sg:postcode":"28320",
    "sg:province":"Madrid",
    "wof:name":"Inmobiliaria La Ca\u00f1ada S.l",
    "wof:placetype":"venue"
},
  "geometry": {"coordinates":[-3.7008070946,40.2431373596],"type":"Point"}
}