{
  "type": "Feature",
  "properties": {
    "addr:full":"Calle de Colon, 33 Palencia Palencia 34002",
    "addr:housenumber":"33",
    "addr:postcode":"34002",
    "addr:street":"Calle De Colon",
    "iso:country":"ES",
    "sg:address":"Calle de Colon, 33",
    "sg:city":"Palencia",
    "sg:orig_category":"Confecci\u00d3n De Trajes Para Se\u00d1oras",
    "sg:phone":"+34 979 74 74 25",
    "sg:postcode":"34002",
    "sg:province":"Palencia",
    "wof:name":"Ramos Monge Rosa Maria",
    "wof:placetype":"venue"
},
  "geometry": {"coordinates":[-4.5310206413,42.0074157715],"type":"Point"}
}