{
  "type": "Feature",
  "properties": {
    "addr:full":"Avda Tirajana (de), S/n Playa Del Ingles Las Palmas 35100",
    "addr:housenumber":"/ n",
    "addr:postcode":"35100",
    "addr:street":"Avda Tirajana De S",
    "iso:country":"ES",
    "sg:address":"Avda Tirajana (de), S/n",
    "sg:city":"Playa Del Ingles",
    "sg:orig_category":"Cl\u00cdnicas M\u00c9dicas",
    "sg:phone":"+34 928 76 17 96",
    "sg:postcode":"35100",
    "sg:province":"Las Palmas",
    "wof:name":"Health Center Canarias S. L.",
    "wof:placetype":"venue"
},
  "geometry": {"coordinates":[-15.5786590576,27.7565803528],"type":"Point"}
}