{
  "type": "Feature",
  "properties": {
    "addr:full":"Avda Conquistadores, 2 Mazagon Huelva 21130",
    "addr:housenumber":"2",
    "addr:postcode":"21130",
    "addr:street":"Avda Conquistadores",
    "iso:country":"ES",
    "sg:address":"Avda Conquistadores, 2",
    "sg:city":"Mazagon",
    "sg:orig_category":"Fabricaci\u00d3n, Reparaci\u00d3n Y Mantenimiento De Construcciones Navales Y Fluviales",
    "sg:phone":"+34 959 37 66 56",
    "sg:postcode":"21130",
    "sg:province":"Huelva",
    "wof:name":"Idamar S.a.",
    "wof:placetype":"venue"
},
  "geometry": {"coordinates":[-6.8282837868,37.1368789673],"type":"Point"}
}