{
  "type": "Feature",
  "properties": {
    "iso:country":"ES",
    "sg:address":"Granada, 16",
    "sg:city":"Ortuella",
    "sg:orig_category":"Empresas De Limpieza",
    "sg:phone":"+34 944 99 03 96",
    "sg:postcode":"48530",
    "sg:province":"Vizcaya",
    "sg:website":"www.supromak.com",
    "wof:name":"S.m.k. Suministros De Maquinas Y Productos Quimicos S.l.",
    "wof:placetype":"venue"
},
  "geometry": {"coordinates":[-3.0566248894,43.3107376099],"type":"Point"}
}