{
  "type": "Feature",
  "properties": {
    "iso:country":"ES",
    "sg:address":"Plaz Iglesia De Los Angeles, 8",
    "sg:city":"Valencia",
    "sg:orig_category":"Agencias Y Agentes Comerciales, Representantes",
    "sg:phone":"+34 963 72 63 58",
    "sg:postcode":"46011",
    "sg:province":"Valencia",
    "wof:name":"Sanahuja Albi\u00f1ana Carlos",
    "wof:placetype":"venue"
},
  "geometry": {"coordinates":[-0.3317300081,39.4724578857],"type":"Point"}
}