{
  "type": "Feature",
  "properties": {
    "iso:country":"ES",
    "sg:address":"Avda Primero De Mayo, S/n",
    "sg:city":"Lorqui",
    "sg:orig_category":"Supermercados Y Hipermercados",
    "sg:phone":"+34 968 69 40 93",
    "sg:postcode":"30564",
    "sg:province":"Murcia",
    "wof:name":"Murcia Andres Meseguer S.a.",
    "wof:placetype":"venue"
},
  "geometry": {"coordinates":[-1.2523440123,38.0791244507],"type":"Point"}
}