{
  "type": "Feature",
  "properties": {
    "iso:country":"ES",
    "sg:address":"Calle de Pedro Ega\u00d1a, 2",
    "sg:city":"Donostia-san Sebastian",
    "sg:orig_category":"Administradores De Bienes Y Delegados De Comunidades De Propietarios",
    "sg:phone":"+34 943 45 79 55",
    "sg:postcode":"20006",
    "sg:province":"Guip\u00f9zcoa",
    "wof:name":"Villabona Orobiourrutia Jesus",
    "wof:placetype":"venue"
},
  "geometry": {"coordinates":[-1.9799029827,43.3139305115],"type":"Point"}
}