{
  "type": "Feature",
  "properties": {
    "iso:country":"ES",
    "sg:address":"Plaza Del Carmen, S/n",
    "sg:city":"Trigueros",
    "sg:orig_category":"Cl\u00cdnicas Dentales",
    "sg:phone":"+34 959 30 67 40",
    "sg:postcode":"21620",
    "sg:province":"Huelva",
    "wof:name":"Odontologia General Y Conservadora",
    "wof:placetype":"venue"
},
  "geometry": {"coordinates":[-6.833272934,37.3818969727],"type":"Point"}
}