{
  "type": "Feature",
  "properties": {
    "addr:full":"Calle de Canalejas, 1 Sevilla Sevilla 41001",
    "addr:housenumber":"1",
    "addr:postcode":"41001",
    "addr:street":"Calle De Canalejas",
    "iso:country":"ES",
    "sg:address":"Calle de Canalejas, 1",
    "sg:city":"Sevilla",
    "sg:orig_category":"Ropa Para Se\u00d1oras Y Caballeros (al Por Menor)",
    "sg:phone":"+34 954 56 44 90",
    "sg:postcode":"41001",
    "sg:province":"Sevilla",
    "wof:name":"Puente Caruana Carmen De La",
    "wof:placetype":"venue"
},
  "geometry": {"coordinates":[-5.998857975,37.3909072876],"type":"Point"}
}