{
  "type": "Feature",
  "properties": {
    "iso:country":"ES",
    "sg:address":"Plaz Legion Espa\u00d1ola, 11",
    "sg:city":"Valencia",
    "sg:orig_category":"Equipo De Refrigeraci\u00d3n Industrial",
    "sg:phone":"+34 963 69 70 16",
    "sg:postcode":"46010",
    "sg:province":"Valencia",
    "wof:name":"Mir Sese Alfredo",
    "wof:placetype":"venue"
},
  "geometry": {"coordinates":[-0.3659049869,39.4782218933],"type":"Point"}
}