{
  "type": "Feature",
  "properties": {
    "iso:country":"ES",
    "sg:address":"Calle de Pintor Sorolla, 7",
    "sg:city":"Madrid",
    "sg:orig_category":"Cristaler\u00cdas",
    "sg:phone":"+34 914 77 85 47",
    "sg:postcode":"28053",
    "sg:province":"Madrid",
    "wof:name":"Cristaleria Perez Alamo S.l.",
    "wof:placetype":"venue"
},
  "geometry": {"coordinates":[-3.670404911,40.3859939575],"type":"Point"}
}