{
  "type": "Feature",
  "properties": {
    "addr:full":"Avda Condomina, 26 Alacant Alicante 03540",
    "addr:housenumber":"26",
    "addr:postcode":"03540",
    "addr:street":"Avda Condomina",
    "iso:country":"ES",
    "sg:address":"Avda Condomina, 26",
    "sg:city":"Alacant",
    "sg:orig_category":"Clubes, Circuitos Y Recintos Para Deportes Mec\u00c1nicos",
    "sg:phone":"+34 965 15 33 30",
    "sg:postcode":"03540",
    "sg:province":"Alicante",
    "wof:name":"Automovil Club De Alicante",
    "wof:placetype":"venue"
},
  "geometry": {"coordinates":[-0.4292984009,38.3635826111],"type":"Point"}
}