{
  "type": "Feature",
  "properties": {
    "addr:full":"Avda Malaga Oloroso, 21 Malaga M\u00e1laga 29014",
    "addr:housenumber":"21",
    "addr:postcode":"29014",
    "addr:street":"Avda Malaga Oloroso;Ma\u0301Laga",
    "iso:country":"ES",
    "sg:address":"Avda Malaga Oloroso, 21",
    "sg:city":"Malaga",
    "sg:orig_category":"Papel (al Por Mayor)",
    "sg:phone":"+34 952 26 86 48",
    "sg:postcode":"29014",
    "sg:province":"M\u00e1laga",
    "wof:name":"Maldonado Valverde Jose",
    "wof:placetype":"venue"
},
  "geometry": {"coordinates":[-4.4170742035,36.7461891174],"type":"Point"}
}