{
  "type": "Feature",
  "properties": {
    "iso:country":"ES",
    "sg:address":"Calle de Capitan Cortes, S/n",
    "sg:city":"Miguel Esteban",
    "sg:orig_category":"Guarder\u00cdas",
    "sg:phone":"+34 925 17 26 50",
    "sg:postcode":"45830",
    "sg:province":"Toledo",
    "wof:name":"Ayuntamiento De Miguel Esteban",
    "wof:placetype":"venue"
},
  "geometry": {"coordinates":[-3.077641964,39.5252151489],"type":"Point"}
}