{
  "type": "Feature",
  "properties": {
    "iso:country":"ES",
    "sg:address":"Calle de Huelva, 6",
    "sg:city":"Catarroja",
    "sg:orig_category":"Institutos De Belleza",
    "sg:phone":"+34 961 26 02 16",
    "sg:postcode":"46470",
    "sg:province":"Valencia",
    "wof:name":"Felix Naya Alicia",
    "wof:placetype":"venue"
},
  "geometry": {"coordinates":[-0.4038749933,39.4065208435],"type":"Point"}
}