{
  "type": "Feature",
  "properties": {
    "iso:country":"ES",
    "sg:address":"Calle de Biar, 20",
    "sg:city":"Onil",
    "sg:orig_category":"Caf\u00c9s, Bares, Cervecer\u00cdas",
    "sg:phone":"+34 965 56 52 48",
    "sg:postcode":"03430",
    "sg:province":"Alicante",
    "wof:name":"Iba\u00f1ez Guardiola Angel",
    "wof:placetype":"venue"
},
  "geometry": {"coordinates":[-0.6788300276,38.6279220581],"type":"Point"}
}