{
  "type": "Feature",
  "properties": {
    "addr:full":"Mcdo. Panaderos, S/n Valladolid Valladolid 47004",
    "addr:housenumber":"s / n",
    "addr:postcode":"47004",
    "addr:street":"Mcdo. Panaderos",
    "iso:country":"ES",
    "sg:address":"Mcdo. Panaderos, S/n",
    "sg:city":"Valladolid",
    "sg:orig_category":"Carnicer\u00cdas, Carnicer\u00cdas",
    "sg:phone":"+34 983 30 26 57",
    "sg:postcode":"47004",
    "sg:province":"Valladolid",
    "wof:name":"Gomez Ayuso Jose Carlos",
    "wof:placetype":"venue"
},
  "geometry": {"coordinates":[-4.7222938538,41.6443405151],"type":"Point"}
}