{
  "type": "Feature",
  "properties": {
    "iso:country":"ES",
    "sg:address":"Carrer de General Prim, 14",
    "sg:city":"Cambrils",
    "sg:orig_category":"Florister\u00cdas",
    "sg:phone":"+34 977 36 06 94",
    "sg:postcode":"43850",
    "sg:province":"Tarragona",
    "wof:name":"Ferre Gomez Pedro",
    "wof:placetype":"venue"
},
  "geometry": {"coordinates":[1.0546740294,41.0702590942],"type":"Point"}
}