{
  "type": "Feature",
  "properties": {
    "addr:full":"Ctra Cordoba-almeria, Km. 0157,0 Huelma Ja\u00e9n 23560",
    "addr:postcode":"23560",
    "addr:street":"Ctra Cordoba-Almeria Km. 0157,0;Jae\u0301N",
    "iso:country":"ES",
    "sg:address":"Ctra Cordoba-almeria, Km. 0157,0",
    "sg:city":"Huelma",
    "sg:orig_category":"M\u00c1rmoles, Granitos Y Piedras Naturales",
    "sg:phone":"+34 953 39 07 07",
    "sg:postcode":"23560",
    "sg:province":"Ja\u00e9n",
    "sg:website":"www.infonegocio.com/ruizvico",
    "wof:name":"Materiales De Construccion Ruiz Vico S.l.",
    "wof:placetype":"venue"
},
  "geometry": {"coordinates":[-3.4495289326,37.6472892761],"type":"Point"}
}