{
  "type": "Feature",
  "properties": {
    "iso:country":"ES",
    "sg:address":"Pl. Espa\u00f1a, S/n",
    "sg:city":"Alia",
    "sg:orig_category":"Bancos",
    "sg:phone":"+34 927 36 61 23",
    "sg:postcode":"10137",
    "sg:province":"C\u00e1ceres",
    "wof:name":"Lazaro Martin Eugenio",
    "wof:placetype":"venue"
},
  "geometry": {"coordinates":[-5.2537899017,39.5124549866],"type":"Point"}
}