{
  "type": "Feature",
  "properties": {
    "addr:full":"Avda Pino Montano, 53 Sevilla Sevilla 41008",
    "addr:housenumber":"53",
    "addr:postcode":"41008",
    "addr:street":"Avda Pino Montano",
    "iso:country":"ES",
    "sg:address":"Avda Pino Montano, 53",
    "sg:city":"Sevilla",
    "sg:orig_category":"Papeler\u00cdas, Librer\u00cdas",
    "sg:phone":"+34 954 95 05 04",
    "sg:postcode":"41008",
    "sg:province":"Sevilla",
    "wof:name":"Lopez Gomez Maria",
    "wof:placetype":"venue"
},
  "geometry": {"coordinates":[-5.9702391624,37.4125595093],"type":"Point"}
}