{
  "type": "Feature",
  "properties": {
    "addr:full":"Carrer de Doctor Trueta, 21 Castelldefels Barcelona 08860",
    "addr:housenumber":"21",
    "addr:postcode":"08860",
    "addr:street":"Carrer De Doctor Trueta",
    "iso:country":"ES",
    "sg:address":"Carrer de Doctor Trueta, 21",
    "sg:city":"Castelldefels",
    "sg:orig_category":"Ingeniero",
    "sg:phone":"+34 936 36 57 44",
    "sg:postcode":"08860",
    "sg:province":"Barcelona",
    "wof:name":"Billmerka S.l.",
    "wof:placetype":"venue"
},
  "geometry": {"coordinates":[1.9763710499,41.279586792],"type":"Point"}
}