{
  "type": "Feature",
  "properties": {
    "addr:full":"Partida El Monastil, S/n Elda Alicante 03600",
    "addr:housenumber":"s",
    "addr:postcode":"03600",
    "addr:street":"Partida El Monastil;/ N",
    "iso:country":"ES",
    "sg:address":"Partida El Monastil, S/n",
    "sg:city":"Elda",
    "sg:orig_category":"Fabricaci\u00d3n De Telas Y Sedas",
    "sg:phone":"+34 965 38 58 64",
    "sg:postcode":"03600",
    "sg:province":"Alicante",
    "wof:name":"Toatex S.l.",
    "wof:placetype":"venue"
},
  "geometry": {"coordinates":[-0.7961040139,38.475315094],"type":"Point"}
}