{
  "type": "Feature",
  "properties": {
    "addr:full":"Calle de Camino Del Tesoro, 8 Villanueva Torre Guadalajara 19209",
    "addr:housenumber":"8",
    "addr:postcode":"19209",
    "addr:street":"Calle De Camino Del Tesoro",
    "iso:country":"ES",
    "sg:address":"Calle de Camino Del Tesoro, 8",
    "sg:city":"Villanueva Torre",
    "sg:orig_category":"Empresas De Empedrado",
    "sg:phone":"+34 949 27 32 64",
    "sg:postcode":"19209",
    "sg:province":"Guadalajara",
    "wof:name":"Piedras Oviedo C.b.",
    "wof:placetype":"venue"
},
  "geometry": {"coordinates":[-3.0794410706,40.795753479],"type":"Point"}
}