{
  "type": "Feature",
  "properties": {
    "addr:full":"Av. Pio Xii, 37 Iru\u00f1a Navarra 31008",
    "addr:housenumber":"37",
    "addr:postcode":"31008",
    "addr:street":"Av. Pio Xii",
    "iso:country":"ES",
    "sg:address":"Av. Pio Xii, 37",
    "sg:city":"Iru\u00f1a",
    "sg:orig_category":"Asesor\u00cda Sobre Comunicaci\u00d3n De Empresas",
    "sg:phone":"+34 948 26 65 41",
    "sg:postcode":"31008",
    "sg:province":"Navarra",
    "wof:name":"Lopez Gomez Jose Marcos",
    "wof:placetype":"venue"
},
  "geometry": {"coordinates":[-1.6595793962,42.8080749512],"type":"Point"}
}