{
  "type": "Feature",
  "properties": {
    "addr:full":"Calle de Albu\u00d1ol, S/n Albolote Granada 18220",
    "addr:housenumber":"s / n",
    "addr:postcode":"18220",
    "addr:street":"Calle De Albun\u0303Ol",
    "iso:country":"ES",
    "sg:address":"Calle de Albu\u00d1ol, S/n",
    "sg:city":"Albolote",
    "sg:orig_category":"Comercio De Piezas De Recambio Y De Accesorios De Veh\u00cdculos, Veh\u00cdculos Industriales",
    "sg:phone":"+34 958 49 05 76",
    "sg:postcode":"18220",
    "sg:province":"Granada",
    "wof:name":"Guerrero Fernandez Leonor",
    "wof:placetype":"venue"
},
  "geometry": {"coordinates":[-3.6480703354,37.2281532288],"type":"Point"}
}