{
  "type": "Feature",
  "properties": {
    "addr:full":"Calle de Valderribas, 51 Madrid Madrid 28007",
    "addr:housenumber":"51",
    "addr:postcode":"madrid;28007",
    "addr:street":"Calle De Valderribas",
    "iso:country":"ES",
    "sg:address":"Calle de Valderribas, 51",
    "sg:city":"Madrid",
    "sg:orig_category":"Psic\u00d3logos",
    "sg:phone":"+34 915 52 17 44",
    "sg:postcode":"28007",
    "sg:province":"Madrid",
    "wof:name":"Adrover Davila Fernando",
    "wof:placetype":"venue"
},
  "geometry": {"coordinates":[-3.6738963127,40.403629303],"type":"Point"}
}