{
  "type": "Feature",
  "properties": {
    "iso:country":"ES",
    "sg:address":"Calle de Florencio Navarro, 40",
    "sg:city":"Gabaldon",
    "sg:orig_category":"Producci\u00d3n, Venta De Productos De Agricultura Biol\u00d3gica",
    "sg:phone":"+34 969 33 90 01",
    "sg:postcode":"16132",
    "sg:province":"Cuenca",
    "wof:name":"Pardo Gabaldon Alfonso",
    "wof:placetype":"venue"
},
  "geometry": {"coordinates":[-1.9431990385,39.6262702942],"type":"Point"}
}