{
  "type": "Feature",
  "properties": {
    "addr:full":"Calle de Francisco Carrillo, 5 Isla Asturias 33341",
    "addr:housenumber":"5",
    "addr:postcode":"33341",
    "addr:street":"Calle De Francisco Carrillo;Isla Asturias",
    "iso:country":"ES",
    "sg:address":"Calle de Francisco Carrillo, 5",
    "sg:city":"Isla",
    "sg:orig_category":"Asilos De Ancianos. Centros Privados",
    "sg:phone":"+34 985 85 60 01",
    "sg:postcode":"33341",
    "sg:province":"Asturias",
    "wof:name":"Xareu S.l.",
    "wof:placetype":"venue"
},
  "geometry": {"coordinates":[-5.2289032936,43.4808769226],"type":"Point"}
}