{
  "type": "Feature",
  "properties": {
    "addr:full":"Calle de Narvaez, 67 Madrid Madrid 28009",
    "addr:housenumber":"67",
    "addr:postcode":"madrid;28009",
    "addr:street":"Calle De Narvaez",
    "iso:country":"ES",
    "sg:address":"Calle de Narvaez, 67",
    "sg:city":"Madrid",
    "sg:orig_category":"Fotocopias, Reprograf\u00cda",
    "sg:phone":"+34 915 73 24 48",
    "sg:postcode":"28009",
    "sg:province":"Madrid",
    "wof:name":"Marcos Zorita Mercedes",
    "wof:placetype":"venue"
},
  "geometry": {"coordinates":[-3.6762180328,40.4162635803],"type":"Point"}
}