{
  "type": "Feature",
  "properties": {
    "addr:full":"Carrer de Gremi De Fusters, 21 Poligon Industrial De Son Castello Islas Baleares 07009",
    "addr:housenumber":"21",
    "addr:postcode":"07009",
    "addr:street":"Carrer De Gremi De Fusters;Islas",
    "iso:country":"ES",
    "sg:address":"Carrer de Gremi De Fusters, 21",
    "sg:city":"Poligon Industrial De Son Castello",
    "sg:orig_category":"Compresores",
    "sg:phone":"+34 971 20 85 24",
    "sg:postcode":"07009",
    "sg:province":"Islas Baleares",
    "wof:name":"Miguel Y Antonio Rodriguez Frau Cdad.",
    "wof:placetype":"venue"
},
  "geometry": {"coordinates":[2.6741399765,39.6011390686],"type":"Point"}
}