{
  "type": "Feature",
  "properties": {
    "addr:full":"Ca\u00f1ada De Ugijar, 4 Ejido Almer\u00eda 04700",
    "addr:housenumber":"4",
    "addr:postcode":"04700",
    "addr:street":"Can\u0303Ada;Ugijar;Almeri\u0301A",
    "iso:country":"ES",
    "sg:address":"Ca\u00f1ada De Ugijar, 4",
    "sg:city":"Ejido",
    "sg:orig_category":"M\u00c1rmoles, Granitos Y Piedras Naturales",
    "sg:phone":"+34 950 48 04 82",
    "sg:postcode":"04700",
    "sg:province":"Almer\u00eda",
    "wof:name":"Teruel Tortosa Andres",
    "wof:placetype":"venue"
},
  "geometry": {"coordinates":[-2.8058309555,36.7609977722],"type":"Point"}
}