{
  "type": "Feature",
  "properties": {
    "iso:country":"ES",
    "sg:address":"Ctra. Colloto-santander, S/n",
    "sg:city":"Colloto-oviedo",
    "sg:orig_category":"Urbanistas",
    "sg:phone":"+34 985 79 39 98",
    "sg:postcode":"33010",
    "sg:province":"Asturias",
    "wof:name":"Galasturianas De Inversiones S.l",
    "wof:placetype":"venue"
},
  "geometry": {"coordinates":[-5.798304081,43.3783874512],"type":"Point"}
}