{
  "type": "Feature",
  "properties": {
    "addr:full":"Rbla Doctor Pearson, 3 Tremp Lleida 25620",
    "addr:housenumber":"3",
    "addr:postcode":"25620",
    "addr:street":"Rbla Doctor Pearson",
    "iso:country":"ES",
    "sg:address":"Rbla Doctor Pearson, 3",
    "sg:city":"Tremp",
    "sg:orig_category":"Ense\u00d1anza Variada",
    "sg:phone":"+34 973 65 20 16",
    "sg:postcode":"25620",
    "sg:province":"Lleida",
    "wof:name":"Centre D'estudis 80 S.l.",
    "wof:placetype":"venue"
},
  "geometry": {"coordinates":[0.8948739767,42.1657142639],"type":"Point"}
}