{
  "type": "Feature",
  "properties": {
    "addr:full":"Calle de San Sebastian, 30 Icod De Los Vinos Santa Cruz De Tenerife 38430",
    "addr:housenumber":"30",
    "addr:postcode":"38430",
    "addr:street":"Calle De San Sebastian",
    "iso:country":"ES",
    "sg:address":"Calle de San Sebastian, 30",
    "sg:city":"Icod De Los Vinos",
    "sg:orig_category":"Asociaciones Y Clubs Deportivos",
    "sg:phone":"+34 922 81 09 70",
    "sg:postcode":"38430",
    "sg:province":"Santa Cruz De Tenerife",
    "wof:name":"Comunidad De Bienes Luciano Moleiro Diaz Y Teresa Herrera Armas",
    "wof:placetype":"venue"
},
  "geometry": {"coordinates":[-16.7191333771,28.3672161102],"type":"Point"}
}