{
  "type": "Feature",
  "properties": {
    "iso:country":"ES",
    "sg:address":"Calle de Puente De San Juan, 2",
    "sg:city":"Lucena",
    "sg:orig_category":"Carnicer\u00cdas, Carnicer\u00cdas",
    "sg:phone":"+34 957 51 45 68",
    "sg:postcode":"14900",
    "sg:province":"C\u00f3rdoba",
    "wof:name":"Campa\u00f1a Cruz Jose",
    "wof:placetype":"venue"
},
  "geometry": {"coordinates":[-4.4847187996,37.4150352478],"type":"Point"}
}