{
  "type": "Feature",
  "properties": {
    "addr:full":"Rua Rollo, 32 Betanzos La Coru\u00f1a 15300",
    "addr:housenumber":"32",
    "addr:postcode":"15300",
    "addr:street":"Rua Rollo;La",
    "iso:country":"ES",
    "sg:address":"Rua Rollo, 32",
    "sg:city":"Betanzos",
    "sg:orig_category":"Ropa Para Se\u00d1oras (al Por Menor)",
    "sg:phone":"+34 981 77 49 46",
    "sg:postcode":"15300",
    "sg:province":"La Coru\u00f1a",
    "wof:name":"Charoa S.l.",
    "wof:placetype":"venue"
},
  "geometry": {"coordinates":[-8.2119092941,43.279914856],"type":"Point"}
}