{
  "type": "Feature",
  "properties": {
    "addr:full":"Carrer de Xiquets De Valls, 6 Barcelona Barcelona 08012",
    "addr:housenumber":"6",
    "addr:postcode":"08012",
    "addr:street":"Carrer De Xiquets De Valls",
    "iso:country":"ES",
    "sg:address":"Carrer de Xiquets De Valls, 6",
    "sg:city":"Barcelona",
    "sg:orig_category":"Cueros Y Pieles (al Por Mayor)",
    "sg:phone":"+34 932 37 17 72",
    "sg:postcode":"08012",
    "sg:province":"Barcelona",
    "wof:name":"Ranz Alvaro Epifanio",
    "wof:placetype":"venue"
},
  "geometry": {"coordinates":[2.1570930481,41.4011497498],"type":"Point"}
}