{
  "type": "Feature",
  "properties": {
    "addr:full":"Calle de Curtidors, 2 Alzira Valencia 46600",
    "addr:housenumber":"2",
    "addr:postcode":"46600",
    "addr:street":"Calle De Curtidors",
    "iso:country":"ES",
    "sg:address":"Calle de Curtidors, 2",
    "sg:city":"Alzira",
    "sg:orig_category":"Informaci\u00d3n Financiera Y Comercial",
    "sg:phone":"+34 962 40 46 22",
    "sg:postcode":"46600",
    "sg:province":"Valencia",
    "wof:name":"Tabernero Capella Ricardo",
    "wof:placetype":"venue"
},
  "geometry": {"coordinates":[-0.4374189973,39.1500358582],"type":"Point"}
}