{
  "type": "Feature",
  "properties": {
    "iso:country":"ES",
    "sg:address":"Urb La Zenia, S/n",
    "sg:city":"La Zenia",
    "sg:orig_category":"Bancos",
    "sg:phone":"+34 966 73 00 37",
    "sg:postcode":"03189",
    "sg:province":"Alicante",
    "sg:website":"www.bancopopular.es",
    "wof:name":"Banco Popular Espa\u00f1ol S.a.",
    "wof:placetype":"venue"
},
  "geometry": {"coordinates":[-0.737613976,37.9488296509],"type":"Point"}
}