{
  "type": "Feature",
  "properties": {
    "addr:full":"Calle de Jose Salgado, 13 Caldas De Reis Pontevedra 36650",
    "addr:housenumber":"13",
    "addr:postcode":"36650",
    "addr:street":"Calle De Jose Salgado",
    "iso:country":"ES",
    "sg:address":"Calle de Jose Salgado, 13",
    "sg:city":"Caldas De Reis",
    "sg:orig_category":"Centros Empresariales",
    "sg:phone":"+34 986 53 03 61",
    "sg:postcode":"36650",
    "sg:province":"Pontevedra",
    "wof:name":"Vara Rodriguez Susana 000620695 Sine",
    "wof:placetype":"venue"
},
  "geometry": {"coordinates":[-8.6353979111,42.6031112671],"type":"Point"}
}