{
  "type": "Feature",
  "properties": {
    "iso:country":"ES",
    "sg:address":"Av Prat De La Riba, 147",
    "sg:city":"Palleja",
    "sg:orig_category":"Productos Qu\u00cdmicos (fabricaci\u00d3n, Al Por Mayor)",
    "sg:phone":"+34 936 63 06 95",
    "sg:postcode":"08780",
    "sg:province":"Barcelona",
    "sg:website":"www.proquimetal.es",
    "wof:name":"Espa\u00f1ola De Productos Quimicos Industriales S. A.",
    "wof:placetype":"venue"
},
  "geometry": {"coordinates":[1.9987610579,41.4176368713],"type":"Point"}
}