{
  "type": "Feature",
  "properties": {
    "iso:country":"ES",
    "sg:address":"Pase Carrion, 30",
    "sg:city":"Alcazares",
    "sg:orig_category":"Promotores Constructores",
    "sg:phone":"+34 968 57 57 02",
    "sg:postcode":"30710",
    "sg:province":"Murcia",
    "wof:name":"La Voluntad S.a.",
    "wof:placetype":"venue"
},
  "geometry": {"coordinates":[-0.8489990234,37.7447319031],"type":"Point"}
}