{
  "type": "Feature",
  "properties": {
    "addr:full":"Carr Santissima Trinitat, 96 Alcasser Valencia 46290",
    "addr:housenumber":"96",
    "addr:postcode":"46290",
    "addr:street":"Carr Santissima Trinitat",
    "iso:country":"ES",
    "sg:address":"Carr Santissima Trinitat, 96",
    "sg:city":"Alcasser",
    "sg:orig_category":"Supermercados Y Hipermercados",
    "sg:phone":"+34 961 24 02 47",
    "sg:postcode":"46290",
    "sg:province":"Valencia",
    "wof:name":"Consum Sociedad Cooperativa Limitada",
    "wof:placetype":"venue"
},
  "geometry": {"coordinates":[-0.4447360039,39.36561203],"type":"Point"}
}