{
  "type": "Feature",
  "properties": {
    "iso:country":"ES",
    "sg:address":"Calle de San Sebastian, 7",
    "sg:city":"Adra",
    "sg:orig_category":"Marmolistas Funerarios",
    "sg:phone":"+34 950 40 09 14",
    "sg:postcode":"04770",
    "sg:province":"Almer\u00eda",
    "wof:name":"Oliver Canillas Jose Luis",
    "wof:placetype":"venue"
},
  "geometry": {"coordinates":[-3.013119936,36.7537956238],"type":"Point"}
}