{
  "type": "Feature",
  "properties": {
    "addr:full":"Calle de Pico De San Pedro (del), 1 Tres Cantos Madrid 28760",
    "addr:housenumber":"1",
    "addr:postcode":"28760",
    "addr:street":"Calle De Pico De San Pedro Del",
    "iso:country":"ES",
    "sg:address":"Calle de Pico De San Pedro (del), 1",
    "sg:city":"Tres Cantos",
    "sg:orig_category":"Bancos",
    "sg:phone":"+34 918 03 67 28",
    "sg:postcode":"28760",
    "sg:province":"Madrid",
    "wof:name":"Bankinter S.a.",
    "wof:placetype":"venue"
},
  "geometry": {"coordinates":[-3.7100250721,40.6162948608],"type":"Point"}
}