{
  "type": "Feature",
  "properties": {
    "iso:country":"ES",
    "sg:address":"Calle de Concepcion Martinez, 3",
    "sg:city":"Alquife",
    "sg:orig_category":"Art\u00cdculos De Regalo (al Por Menor)",
    "sg:phone":"+34 958 67 35 01",
    "sg:postcode":"18518",
    "sg:province":"Granada",
    "wof:name":"Vargas Martinez Dolores",
    "wof:placetype":"venue"
},
  "geometry": {"coordinates":[-3.1165320873,37.1797332764],"type":"Point"}
}