{
  "type": "Feature",
  "properties": {
    "addr:full":"Avda Llano Del, 10 Gijon Asturias 33209",
    "addr:housenumber":"10",
    "addr:postcode":"33209",
    "addr:street":"Avda Llano Del",
    "iso:country":"ES",
    "sg:address":"Avda Llano Del, 10",
    "sg:city":"Gijon",
    "sg:orig_category":"Asesor\u00cda Fiscal Y Jur\u00cddica",
    "sg:phone":"+34 985 38 20 93",
    "sg:postcode":"33209",
    "sg:province":"Asturias",
    "wof:name":"Hermanos L Junco Asesores 2001 S.l.",
    "wof:placetype":"venue"
},
  "geometry": {"coordinates":[-5.639647007,43.5119361877],"type":"Point"}
}