{
  "type": "Feature",
  "properties": {
    "addr:full":"Cjon Gines, S/n Espiel C\u00f3rdoba 14220",
    "addr:housenumber":"s / n",
    "addr:postcode":"14220",
    "addr:street":"Cjon Gines",
    "iso:country":"ES",
    "sg:address":"Cjon Gines, S/n",
    "sg:city":"Espiel",
    "sg:orig_category":"Asilos De Ancianos. Centros Privados",
    "sg:phone":"+34 957 36 33 00",
    "sg:postcode":"14220",
    "sg:province":"C\u00f3rdoba",
    "wof:name":"Alternativas Socio Sanitarias De Espiel S.l.",
    "wof:placetype":"venue"
},
  "geometry": {"coordinates":[-5.0182461739,38.1674461365],"type":"Point"}
}