{
  "type": "Feature",
  "properties": {
    "addr:full":"Carrer de Tucuman, 26 Barcelona Barcelona 08030",
    "addr:housenumber":"26",
    "addr:postcode":"08030",
    "addr:street":"Carrer De Tucuman",
    "iso:country":"ES",
    "sg:address":"Carrer de Tucuman, 26",
    "sg:city":"Barcelona",
    "sg:orig_category":"Madera Para Construcci\u00d3n E Industria",
    "sg:phone":"+34 933 45 79 11",
    "sg:postcode":"08030",
    "sg:province":"Barcelona",
    "wof:name":"Tecnicas Aplicadas De La Chapa S.l.",
    "wof:placetype":"venue"
},
  "geometry": {"coordinates":[2.2024030685,41.4464874268],"type":"Point"}
}