{
  "type": "Feature",
  "properties": {
    "iso:country":"ES",
    "sg:address":"Avda Fernando Arce, 35",
    "sg:city":"Torrelavega",
    "sg:orig_category":"Material Y Herramientas Agr\u00cdcolas",
    "sg:phone":"+34 942 89 67 02",
    "sg:postcode":"39300",
    "sg:province":"Cantabria",
    "wof:name":"Maquinaria Palencia Gonzalez Sl",
    "wof:placetype":"venue"
},
  "geometry": {"coordinates":[-4.0513100624,43.3427505493],"type":"Point"}
}