{
  "type": "Feature",
  "properties": {
    "addr:full":"Carrer de Capcir, 1 Can Casablancas Barcelona 08192",
    "addr:housenumber":"1",
    "addr:postcode":"08192",
    "addr:street":"Carrer De Capcir",
    "iso:country":"ES",
    "sg:address":"Carrer de Capcir, 1",
    "sg:city":"Can Casablancas",
    "sg:orig_category":"Zapatos (al Por Menor)",
    "sg:phone":"+34 937 21 92 01",
    "sg:postcode":"08192",
    "sg:province":"Barcelona",
    "wof:name":"Srh Carrera S.l.",
    "wof:placetype":"venue"
},
  "geometry": {"coordinates":[2.0770950317,41.535243988],"type":"Point"}
}