{
  "type": "Feature",
  "properties": {
    "addr:full":"Calle de Francia, 2 Pozuelo De Alarcon Madrid 28224",
    "addr:housenumber":"2",
    "addr:postcode":"28224",
    "addr:street":"Calle De Francia",
    "iso:country":"ES",
    "sg:address":"Calle de Francia, 2",
    "sg:city":"Pozuelo De Alarcon",
    "sg:orig_category":"Ense\u00d1anza: Turismo, Cocina, Hosteler\u00cda",
    "sg:phone":"+34 913 51 56 57",
    "sg:postcode":"28224",
    "sg:province":"Madrid",
    "wof:name":"Salpimentar S.l.",
    "wof:placetype":"venue"
},
  "geometry": {"coordinates":[-3.8076059818,40.4324073792],"type":"Point"}
}