{
  "type": "Feature",
  "properties": {
    "addr:full":"Carrer de General Casta\u00d1os, 4 Molins Rei Barcelona 08750",
    "addr:housenumber":"4",
    "addr:postcode":"08750",
    "addr:street":"Carrer De General Castan\u0303Os;Barcelona",
    "iso:country":"ES",
    "sg:address":"Carrer de General Casta\u00d1os, 4",
    "sg:city":"Molins Rei",
    "sg:orig_category":"Electricidad: Instaladores",
    "sg:phone":"+34 936 68 88 11",
    "sg:postcode":"08750",
    "sg:province":"Barcelona",
    "wof:name":"Almirall Pages Francisco Javier",
    "wof:placetype":"venue"
},
  "geometry": {"coordinates":[2.017285347,41.4094619751],"type":"Point"}
}