{
  "type": "Feature",
  "properties": {
    "iso:country":"ES",
    "sg:address":"Avda Alcalde J.elosegi, 128",
    "sg:city":"Donostia-san Sebastian",
    "sg:classifiers":[
        {
            "category":"Autos & Motor Vehicles",
            "subcategory":"Automobile Sales",
            "type":"Retail Goods"
        }
    ],
    "sg:phone":"+34 943 39 28 33",
    "sg:postcode":"20017",
    "sg:province":"Guip\u00f9zcoa",
    "wof:name":"Gipuzkoarena Heziketa S.l.l.",
    "wof:placetype":"venue"
},
  "geometry": {"coordinates":[-1.9251650572,43.3212585449],"type":"Point"}
}