{
  "type": "Feature",
  "properties": {
    "iso:country":"ES",
    "sg:address":"Calle de Armu\u00d1a, 23",
    "sg:city":"Villoruela",
    "sg:orig_category":"Cester\u00cda (fabricaci\u00d3n)",
    "sg:phone":"+34 923 35 64 32",
    "sg:postcode":"37339",
    "sg:province":"Salamanca",
    "wof:name":"Sanchez Chamoso Leonides",
    "wof:placetype":"venue"
},
  "geometry": {"coordinates":[-5.3956747055,41.0094413757],"type":"Point"}
}