{
  "type": "Feature",
  "properties": {
    "addr:full":"Calle de Herraje (del), S/n Poligono Industrial De Arinaga Las Palmas 35118",
    "addr:housenumber":"/ n",
    "addr:postcode":"35118",
    "addr:street":"Calle De Herraje Del S;Poligono Industrial De Arinaga Las",
    "iso:country":"ES",
    "sg:address":"Calle de Herraje (del), S/n",
    "sg:city":"Poligono Industrial De Arinaga",
    "sg:orig_category":"Colchones (fabricaci\u00d3n, Al Por Mayor, Al Por Menor)",
    "sg:phone":"+34 928 18 33 38",
    "sg:postcode":"35118",
    "sg:province":"Las Palmas",
    "wof:name":"Smattex S.a.",
    "wof:placetype":"venue"
},
  "geometry": {"coordinates":[-15.4319887161,27.8808555603],"type":"Point"}
}