{
  "type": "Feature",
  "properties": {
    "addr:full":"Calle de Josefina Mayor, 7 Goro Las Palmas 35215",
    "addr:housenumber":"7",
    "addr:postcode":"35215",
    "addr:street":"Calle De Josefina Mayor",
    "iso:country":"ES",
    "sg:address":"Calle de Josefina Mayor, 7",
    "sg:city":"Goro",
    "sg:orig_category":"Carnes De Carnicer\u00cda (al Por Mayor)",
    "sg:phone":"+34 928 70 01 18",
    "sg:postcode":"35215",
    "sg:province":"Las Palmas",
    "wof:name":"Tacna Comercio Exterior S.a.",
    "wof:placetype":"venue"
},
  "geometry": {"coordinates":[-15.398223877,27.9939899445],"type":"Point"}
}