{
  "type": "Feature",
  "properties": {
    "iso:country":"ES",
    "sg:address":"Avda Valdelaparra (de), 27",
    "sg:city":"Alcobendas",
    "sg:orig_category":"Marketing Directo",
    "sg:phone":"+34 916 62 42 08",
    "sg:postcode":"28108",
    "sg:province":"Madrid",
    "wof:name":"Comunicacion Y Publicidad Directa S.l.",
    "wof:placetype":"venue"
},
  "geometry": {"coordinates":[-3.6466300488,40.5387420654],"type":"Point"}
}