{
  "type": "Feature",
  "properties": {
    "addr:full":"Carrer de Antoni Rovira I Virgili (d'), 29 Tarragona Tarragona 43002",
    "addr:housenumber":"29",
    "addr:postcode":"43002",
    "addr:street":"Carrer De Antoni Rovira I Virgili D '",
    "iso:country":"ES",
    "sg:address":"Carrer de Antoni Rovira I Virgili (d'), 29",
    "sg:city":"Tarragona",
    "sg:orig_category":"Molduras, Junquillos, Listones Y Molduras Perforadas",
    "sg:phone":"+34 977 21 81 71",
    "sg:postcode":"43002",
    "sg:province":"Tarragona",
    "wof:name":"Lopez Garcia Maria Del Valle",
    "wof:placetype":"venue"
},
  "geometry": {"coordinates":[1.2517529726,41.1211662292],"type":"Point"}
}