{
  "type": "Feature",
  "properties": {
    "addr:full":"Calle de Lucano, 56 Madrid Madrid 28022",
    "addr:housenumber":"56",
    "addr:postcode":"madrid;28022",
    "addr:street":"Calle De Lucano",
    "iso:country":"ES",
    "sg:address":"Calle de Lucano, 56",
    "sg:city":"Madrid",
    "sg:orig_category":"Mec\u00c1nico Del Autom\u00d3vil",
    "sg:phone":"+34 917 42 63 00",
    "sg:postcode":"28022",
    "sg:province":"Madrid",
    "wof:name":"Jimenez Ballesteros Herminio",
    "wof:placetype":"venue"
},
  "geometry": {"coordinates":[-3.6096880436,40.4358329773],"type":"Point"}
}