{
  "type": "Feature",
  "properties": {
    "iso:country":"ES",
    "sg:address":"Calle de San Francisco, 9",
    "sg:city":"Almansa",
    "sg:orig_category":"Ropa Para Se\u00d1oras (al Por Menor)",
    "sg:phone":"+34 967 34 57 30",
    "sg:postcode":"02640",
    "sg:province":"Albacete",
    "wof:name":"Martin Diez Maria Dolores",
    "wof:placetype":"venue"
},
  "geometry": {"coordinates":[-1.0947309732,38.8674125671],"type":"Point"}
}