{
  "type": "Feature",
  "properties": {
    "addr:full":"Avda Fernandez Ladreda, 9 Cadiz C\u00e1diz 11008",
    "addr:housenumber":"9",
    "addr:postcode":"11008",
    "addr:street":"Avda Fernandez Ladreda",
    "iso:country":"ES",
    "sg:address":"Avda Fernandez Ladreda, 9",
    "sg:city":"Cadiz",
    "sg:orig_category":"Abogados",
    "sg:phone":"+34 956 28 84 61",
    "sg:postcode":"11008",
    "sg:province":"C\u00e1diz",
    "wof:name":"Garcia Solano Jose Carlos",
    "wof:placetype":"venue"
},
  "geometry": {"coordinates":[-6.2850246429,36.5161514282],"type":"Point"}
}