{
  "type": "Feature",
  "properties": {
    "addr:full":"La Paz, 11 Zaragoza Zaragoza 50008",
    "addr:housenumber":"11",
    "addr:postcode":"50008",
    "addr:street":"La Paz",
    "iso:country":"ES",
    "sg:address":"La Paz, 11",
    "sg:city":"Zaragoza",
    "sg:orig_category":"Caf\u00c9s, Bares, Cervecer\u00cdas",
    "sg:phone":"+34 976 23 56 81",
    "sg:postcode":"50008",
    "sg:province":"Zaragoza",
    "wof:name":"Telefonos Publicos De Aragon S.l.",
    "wof:placetype":"venue"
},
  "geometry": {"coordinates":[-0.8843659759,41.6426391602],"type":"Point"}
}