{
  "type": "Feature",
  "properties": {
    "addr:full":"Carrer de Ceravalls, 16 Hospitalet Llobregat Barcelona 08905",
    "addr:housenumber":"16",
    "addr:postcode":"08905",
    "addr:street":"Carrer De Ceravalls",
    "iso:country":"ES",
    "sg:address":"Carrer de Ceravalls, 16",
    "sg:city":"Hospitalet Llobregat",
    "sg:orig_category":"Carnicer\u00cdas, Carnicer\u00cdas",
    "sg:phone":"+34 934 49 86 33",
    "sg:postcode":"08905",
    "sg:province":"Barcelona",
    "wof:name":"Resina Herrero Isabel",
    "wof:placetype":"venue"
},
  "geometry": {"coordinates":[2.1082749367,41.3690567017],"type":"Point"}
}