{
  "type": "Feature",
  "properties": {
    "addr:full":"Calle de Argentina, 1 Teruel Teruel 44002",
    "addr:housenumber":"1",
    "addr:postcode":"44002",
    "addr:street":"Calle De Argentina",
    "iso:country":"ES",
    "sg:address":"Calle de Argentina, 1",
    "sg:city":"Teruel",
    "sg:orig_category":"Servicios Gsm",
    "sg:phone":"+34 978 62 20 83",
    "sg:postcode":"44002",
    "sg:province":"Teruel",
    "wof:name":"Turolense De Telecomunicaciones S.l.",
    "wof:placetype":"venue"
},
  "geometry": {"coordinates":[-1.1090669632,40.3315467834],"type":"Point"}
}