{
  "type": "Feature",
  "properties": {
    "addr:full":"Yedras, 1 Menasalbas Toledo 45128",
    "addr:housenumber":"1",
    "addr:postcode":"45128",
    "addr:street":"Yedras",
    "iso:country":"ES",
    "sg:address":"Yedras, 1",
    "sg:city":"Menasalbas",
    "sg:orig_category":"Molduras, Junquillos, Listones Y Molduras Perforadas",
    "sg:phone":"+34 925 40 70 92",
    "sg:postcode":"45128",
    "sg:province":"Toledo",
    "wof:name":"Sanchez Garcia Justino",
    "wof:placetype":"venue"
},
  "geometry": {"coordinates":[-4.2844028473,39.636806488],"type":"Point"}
}