{
  "type": "Feature",
  "properties": {
    "iso:country":"ES",
    "sg:address":"Calle de Rave, 25",
    "sg:city":"Cordoba",
    "sg:orig_category":"Pod\u00d3logos: Pedicuros",
    "sg:phone":"+34 957 25 06 89",
    "sg:postcode":"14002",
    "sg:province":"C\u00f3rdoba",
    "wof:name":"Sanchez Arenas Jose",
    "wof:placetype":"venue"
},
  "geometry": {"coordinates":[-4.7678608894,37.8824653625],"type":"Point"}
}