{
  "type": "Feature",
  "properties": {
    "addr:full":"B Poligono Industrial Cordovilla, 3 Cordovilla Navarra 31191",
    "addr:housenumber":"3",
    "addr:postcode":"31191",
    "addr:street":"Poligono Industrial Cordovilla",
    "iso:country":"ES",
    "sg:address":"B Poligono Industrial Cordovilla, 3",
    "sg:city":"Cordovilla",
    "sg:orig_category":"Electricidad: Equipos Industriales, Componentes (fabricaci\u00d3n)",
    "sg:phone":"+34 948 15 13 14",
    "sg:postcode":"31191",
    "sg:province":"Navarra",
    "wof:name":"Suministros Electricos Urgon S.a.",
    "wof:placetype":"venue"
},
  "geometry": {"coordinates":[-1.6518089771,42.7533912659],"type":"Point"}
}