{
  "type": "Feature",
  "properties": {
    "iso:country":"ES",
    "sg:address":"Miguel Servet, 6",
    "sg:city":"Daimiel",
    "sg:orig_category":"Fabricaci\u00d3n, Alquiler, Venta De Encofrados",
    "sg:phone":"+34 926 85 49 07",
    "sg:postcode":"13250",
    "sg:province":"Ciudad Real",
    "wof:name":"Encofrados Y Forjados Ciudad Real S.l.l.",
    "wof:placetype":"venue"
},
  "geometry": {"coordinates":[-3.617358923,39.0695037842],"type":"Point"}
}