{
  "type": "Feature",
  "properties": {
    "iso:country":"ES",
    "sg:address":"Calle de Mu\u00d1ices, 21",
    "sg:city":"Cordoba",
    "sg:orig_category":"Bisuter\u00cda, Joyer\u00cda, Relojer\u00cda (al Por Menor)",
    "sg:phone":"+34 957 48 00 48",
    "sg:postcode":"14002",
    "sg:province":"C\u00f3rdoba",
    "wof:name":"Llamas Cortes Jose",
    "wof:placetype":"venue"
},
  "geometry": {"coordinates":[-4.7703790665,37.8863258362],"type":"Point"}
}