{
  "type": "Feature",
  "properties": {
    "iso:country":"ES",
    "sg:address":"Calle de Arabial, S/n",
    "sg:city":"Granada",
    "sg:orig_category":"Bazares, Art\u00cdculos De Limpieza Y De Cocina (al Por Menor)",
    "sg:phone":"+34 958 52 35 68",
    "sg:postcode":"18003",
    "sg:province":"Granada",
    "wof:name":"Francisco Romero Ortega, S.l.",
    "wof:placetype":"venue"
},
  "geometry": {"coordinates":[-3.6118454933,37.177406311],"type":"Point"}
}