{
  "type": "Feature",
  "properties": {
    "addr:full":"Po. Maritim, 3 Cala Millor Islas Baleares 07560",
    "addr:housenumber":"3",
    "addr:postcode":"07560",
    "addr:street":"Po. Maritim;Millor",
    "iso:country":"ES",
    "sg:address":"Po. Maritim, 3",
    "sg:city":"Cala Millor",
    "sg:orig_category":"Caf\u00c9s, Bares, Cervecer\u00cdas",
    "sg:phone":"+34 971 58 68 34",
    "sg:postcode":"07560",
    "sg:province":"Islas Baleares",
    "wof:name":"Silba Cb",
    "wof:placetype":"venue"
},
  "geometry": {"coordinates":[3.3733510971,39.5831985474],"type":"Point"}
}