{
  "type": "Feature",
  "properties": {
    "addr:full":"Avda Doctor Arce, 18 Madrid Madrid 28002",
    "addr:housenumber":"18",
    "addr:postcode":"madrid;28002",
    "addr:street":"Avda Doctor Arce",
    "iso:country":"ES",
    "sg:address":"Avda Doctor Arce, 18",
    "sg:city":"Madrid",
    "sg:orig_category":"Inmobiliaria (agencias)",
    "sg:phone":"+34 915 62 26 06",
    "sg:postcode":"28002",
    "sg:province":"Madrid",
    "wof:name":"Rio Capital S.l.",
    "wof:placetype":"venue"
},
  "geometry": {"coordinates":[-3.6812300682,40.4467849731],"type":"Point"}
}