{
  "type": "Feature",
  "properties": {
    "addr:full":"Calle de Rio Valdelospozos, S/n Poligono Sta M. De Benquerencia Toledo 45007",
    "addr:housenumber":"s / n",
    "addr:postcode":"45007",
    "addr:street":"Calle De Rio Valdelospozos;Poligono Sta M. De Benquerencia",
    "iso:country":"ES",
    "sg:address":"Calle de Rio Valdelospozos, S/n",
    "sg:city":"Poligono Sta M. De Benquerencia",
    "sg:orig_category":"Metalurgia",
    "sg:phone":"+34 925 23 03 44",
    "sg:postcode":"45007",
    "sg:province":"Toledo",
    "wof:name":"Rubio Jimenez Jose Luis",
    "wof:placetype":"venue"
},
  "geometry": {"coordinates":[-3.966299057,39.8658332825],"type":"Point"}
}