{
  "type": "Feature",
  "properties": {
    "iso:country":"ES",
    "sg:address":"Carrer de Governador Gonzalez, 51",
    "sg:city":"Tarragona",
    "sg:orig_category":"Inmobiliaria (agencias)",
    "sg:phone":"+34 977 22 62 18",
    "sg:postcode":"43001",
    "sg:province":"Tarragona",
    "wof:name":"Pilmarc Capital S.l.",
    "wof:placetype":"venue"
},
  "geometry": {"coordinates":[1.2492400408,41.1160392761],"type":"Point"}
}