{
  "type": "Feature",
  "properties": {
    "iso:country":"ES",
    "sg:address":"Pg Lepant, De, 22",
    "sg:city":"Casco Urbano",
    "sg:orig_category":"Empresas De Carpinter\u00cda De Madera",
    "sg:phone":"+34 962 82 10 70",
    "sg:postcode":"46760",
    "sg:province":"Valencia",
    "wof:name":"Fusteria Amador S.l.",
    "wof:placetype":"venue"
},
  "geometry": {"coordinates":[-0.2594090104,39.0749702454],"type":"Point"}
}