{
  "type": "Feature",
  "properties": {
    "iso:country":"ES",
    "sg:address":"Calle de Estribor, 1",
    "sg:city":"Torrequebrada",
    "sg:orig_category":"Inmobiliaria (agencias)",
    "sg:phone":"+34 952 57 69 93",
    "sg:postcode":"29630",
    "sg:province":"M\u00e1laga",
    "wof:name":"Comunidad De Propietarios Conjunto Atalaya Golf",
    "wof:placetype":"venue"
},
  "geometry": {"coordinates":[-4.5559592247,36.5870552063],"type":"Point"}
}