{
  "type": "Feature",
  "properties": {
    "addr:full":"Ctra. Coria, Km. 0058,2 San Miguel De Valero Salamanca 37762",
    "addr:postcode":"37762",
    "addr:street":"Ctra. Coria Km. 0058,2",
    "iso:country":"ES",
    "sg:address":"Ctra. Coria, Km. 0058,2",
    "sg:city":"San Miguel De Valero",
    "sg:orig_category":"Reparaciones Y Remolcado De Veh\u00cdculos",
    "sg:phone":"+34 923 41 56 03",
    "sg:postcode":"37762",
    "sg:province":"Salamanca",
    "wof:name":"Hernandez Navarro Isaac",
    "wof:placetype":"venue"
},
  "geometry": {"coordinates":[-97.78224945069999,45.7040786743],"type":"Point"}
}