{
  "type": "Feature",
  "properties": {
    "iso:country":"ES",
    "sg:address":"Calle de Mayor, S/n",
    "sg:city":"Villanueva Del Campillo",
    "sg:orig_category":"Procuradores",
    "sg:phone":"+34 920 23 53 44",
    "sg:postcode":"05591",
    "sg:province":"\u00c1vila",
    "wof:name":"Garcia Garcia Antonio",
    "wof:placetype":"venue"
},
  "geometry": {"coordinates":[-5.1795539856,40.5767555237],"type":"Point"}
}