{
  "type": "Feature",
  "properties": {
    "iso:country":"ES",
    "sg:address":"Agrupacion Escolar, S/n",
    "sg:city":"Taboada",
    "sg:orig_category":"Centros De Educaci\u00d3n Especial",
    "sg:phone":"+34 982 46 54 79",
    "sg:postcode":"27550",
    "sg:province":"Lugo",
    "wof:name":"Instituto De Ense\u00f1anza Secundaria De Taboada",
    "wof:placetype":"venue"
},
  "geometry": {"coordinates":[-7.7628121376,42.7144126892],"type":"Point"}
}