{
  "type": "Feature",
  "properties": {
    "iso:country":"ES",
    "sg:address":"La Iglesia, S/n",
    "sg:city":"Villalaco",
    "sg:orig_category":"Cr\u00cda De Corderos Y De Cabras",
    "sg:phone":"+34 979 82 20 96",
    "sg:postcode":"34459",
    "sg:province":"Palencia",
    "wof:name":"Manrique Calvo S.l.",
    "wof:placetype":"venue"
},
  "geometry": {"coordinates":[-4.2590942383,42.1566047668],"type":"Point"}
}