{
  "type": "Feature",
  "properties": {
    "iso:country":"ES",
    "sg:address":"Calle de Usandizaga, 17",
    "sg:city":"Donostia-san Sebastian",
    "sg:orig_category":"Abogados",
    "sg:phone":"+34 943 29 15 90",
    "sg:postcode":"20002",
    "sg:province":"Guip\u00f9zcoa",
    "wof:name":"San Juan Resines Enrique",
    "wof:placetype":"venue"
},
  "geometry": {"coordinates":[-1.976984024,43.3238983154],"type":"Point"}
}