{
  "type": "Feature",
  "properties": {
    "iso:country":"ES",
    "sg:address":"Calle de Alhama, 65",
    "sg:city":"Lucena",
    "sg:orig_category":"Electrodom\u00c9sticos (al Por Menor)",
    "sg:phone":"+34 957 51 43 70",
    "sg:postcode":"14900",
    "sg:province":"C\u00f3rdoba",
    "wof:name":"Ruiz Garcia Domingo",
    "wof:placetype":"venue"
},
  "geometry": {"coordinates":[-4.4918422699,37.4066314697],"type":"Point"}
}