{
  "type": "Feature",
  "properties": {
    "addr:full":"Carr Carme Verdaguer, 56 Igualada Barcelona 08700",
    "addr:housenumber":"56",
    "addr:postcode":"08700",
    "addr:street":"Carr Carme Verdaguer",
    "iso:country":"ES",
    "sg:address":"Carr Carme Verdaguer, 56",
    "sg:city":"Igualada",
    "sg:orig_category":"Cl\u00cdnicas M\u00c9dicas",
    "sg:phone":"+34 938 03 65 84",
    "sg:postcode":"08700",
    "sg:province":"Barcelona",
    "wof:name":"Fundacion San Jose",
    "wof:placetype":"venue"
},
  "geometry": {"coordinates":[1.6190450191,41.5824966431],"type":"Point"}
}