{
  "type": "Feature",
  "properties": {
    "addr:full":"Calle de Alemania, 10 Avila \u00c1vila 05001",
    "addr:housenumber":"10",
    "addr:postcode":"05001",
    "addr:street":"Calle De Alemania;A\u0301Vila",
    "iso:country":"ES",
    "sg:address":"Calle de Alemania, 10",
    "sg:city":"Avila",
    "sg:orig_category":"Administradores De Bienes Y Delegados De Comunidades De Propietarios",
    "sg:phone":"+34 920 25 40 59",
    "sg:postcode":"05001",
    "sg:province":"\u00c1vila",
    "wof:name":"Admiconta S.l.",
    "wof:placetype":"venue"
},
  "geometry": {"coordinates":[-4.6983304024,40.6551361084],"type":"Point"}
}