{
  "type": "Feature",
  "properties": {
    "iso:country":"ES",
    "sg:address":"Calle de Todos Los Martires, 7",
    "sg:city":"Villanueva Cordoba",
    "sg:orig_category":"Mercer\u00cda, Lencer\u00cda (al Por Menor)",
    "sg:phone":"+34 957 12 00 46",
    "sg:postcode":"14440",
    "sg:province":"C\u00f3rdoba",
    "wof:name":"Romero Torralbo Francisca",
    "wof:placetype":"venue"
},
  "geometry": {"coordinates":[-4.621984005,38.3221168518],"type":"Point"}
}