{
  "type": "Feature",
  "properties": {
    "iso:country":"ES",
    "sg:address":"Carrer de Valldoreix, 56",
    "sg:city":"S. Cugat Valles",
    "sg:orig_category":"Electrodom\u00c9sticos (al Por Menor)",
    "sg:phone":"+34 935 89 11 85",
    "sg:postcode":"08172",
    "sg:province":"Barcelona",
    "wof:name":"Yatay S.c.p",
    "wof:placetype":"venue"
},
  "geometry": {"coordinates":[2.0797119141,41.4684944153],"type":"Point"}
}