{
  "type": "Feature",
  "properties": {
    "addr:full":"C/ Marques D'asprella, 4 Elche Alicante 03201",
    "addr:housenumber":"4",
    "addr:postcode":"03201",
    "addr:street":"C / Marques D'Asprella",
    "iso:country":"ES",
    "sg:address":"C/ Marques D'asprella, 4",
    "sg:city":"Elche",
    "sg:orig_category":"Asesor\u00cdas Y Estudios Financieros",
    "sg:phone":"+34 965 46 59 42",
    "sg:postcode":"03201",
    "sg:province":"Alicante",
    "wof:name":"Rodriguez Cerda Mariano Vicente",
    "wof:placetype":"venue"
},
  "geometry": {"coordinates":[-0.4891029894,38.3498764038],"type":"Point"}
}