{
  "type": "Feature",
  "properties": {
    "addr:full":"Calle de Pallosa (la), 18 Vega Espinareda Le\u00f3n 24430",
    "addr:housenumber":"18",
    "addr:postcode":"24430",
    "addr:street":"Calle De Pallosa La;Espinareda Leo\u0301N",
    "iso:country":"ES",
    "sg:address":"Calle de Pallosa (la), 18",
    "sg:city":"Vega Espinareda",
    "sg:orig_category":"Ingenier\u00cda, Centros De Estudios (industria)",
    "sg:phone":"+34 987 56 84 50",
    "sg:postcode":"24430",
    "sg:province":"Le\u00f3n",
    "wof:name":"Blanco Franco Celia",
    "wof:placetype":"venue"
},
  "geometry": {"coordinates":[-6.6503992081,42.7293701172],"type":"Point"}
}