{
  "type": "Feature",
  "properties": {
    "addr:full":"Carrer de Enric Granados, 124 Barcelona Barcelona 08008",
    "addr:housenumber":"124",
    "addr:postcode":"08008",
    "addr:street":"Carrer De Enric Granados",
    "iso:country":"ES",
    "sg:address":"Carrer de Enric Granados, 124",
    "sg:city":"Barcelona",
    "sg:orig_category":"Bisuter\u00cda, Joyer\u00cda, Relojer\u00cda (al Por Menor)",
    "sg:phone":"+34 932 37 83 15",
    "sg:postcode":"08008",
    "sg:province":"Barcelona",
    "wof:name":"Caparros Reyes Victor",
    "wof:placetype":"venue"
},
  "geometry": {"coordinates":[2.1536369324,41.3946266174],"type":"Point"}
}