{
  "type": "Feature",
  "properties": {
    "iso:country":"ES",
    "sg:address":"Calle de Benecharo, 20",
    "sg:city":"Palmas De Gran Canaria",
    "sg:orig_category":"Peluquer\u00cdas, Peluquer\u00cda Mixta",
    "sg:phone":"+34 928 46 19 24",
    "sg:postcode":"35009",
    "sg:province":"Las Palmas",
    "wof:name":"Escudero Pe\u00f1a Oliver",
    "wof:placetype":"venue"
},
  "geometry": {"coordinates":[-15.423992157,28.1506595612],"type":"Point"}
}