{
  "type": "Feature",
  "properties": {
    "iso:country":"ES",
    "sg:address":"Avda Atlantico Del, 359",
    "sg:city":"Vecindario",
    "sg:orig_category":"Asociaciones Y Clubs Deportivos",
    "sg:phone":"+34 928 79 41 33",
    "sg:postcode":"35110",
    "sg:province":"Las Palmas",
    "wof:name":"Adolfo Suanzes S.a.",
    "wof:placetype":"venue"
},
  "geometry": {"coordinates":[-15.4378709793,27.8474807739],"type":"Point"}
}