{
  "type": "Feature",
  "properties": {
    "iso:country":"ES",
    "sg:address":"Carr Del Music Martinez Valls, 59",
    "sg:city":"Ontinyent",
    "sg:orig_category":"Agencias De Viajes",
    "sg:phone":"+34 962 38 75 37",
    "sg:postcode":"46870",
    "sg:province":"Valencia",
    "wof:name":"Ontravel S. L",
    "wof:placetype":"venue"
},
  "geometry": {"coordinates":[-0.6003109813,38.8242149353],"type":"Point"}
}