{
  "type": "Feature",
  "properties": {
    "addr:full":"Plaz Emilio Diez De Revenga, 2 San Miguel Murcia 30008",
    "addr:housenumber":"2",
    "addr:postcode":"30008",
    "addr:street":"Plaz Emilio Diez De Revenga",
    "iso:country":"ES",
    "sg:address":"Plaz Emilio Diez De Revenga, 2",
    "sg:city":"San Miguel",
    "sg:orig_category":"Caf\u00c9s, Bares, Cervecer\u00cdas",
    "sg:phone":"+34 968 28 50 36",
    "sg:postcode":"30008",
    "sg:province":"Murcia",
    "wof:name":"Jimeno Risue\u00f1o Dolores",
    "wof:placetype":"venue"
},
  "geometry": {"coordinates":[-1.1302499771,37.9829597473],"type":"Point"}
}