{
  "type": "Feature",
  "properties": {
    "addr:full":"Pl Mil Centenari, S/n Manresa Barcelona 08241",
    "addr:housenumber":"s / n",
    "addr:postcode":"08241",
    "addr:street":"Pl",
    "iso:country":"ES",
    "sg:address":"Pl Mil Centenari, S/n",
    "sg:city":"Manresa",
    "sg:orig_category":"Asociaciones, Organismos Culturales Y Socioeducativos",
    "sg:phone":"+34 938 76 83 78",
    "sg:postcode":"08241",
    "sg:province":"Barcelona",
    "wof:name":"Cae Formacio I Serveis Socio Culturals",
    "wof:placetype":"venue"
},
  "geometry": {"coordinates":[1.8264579773,41.7245063782],"type":"Point"}
}