{
  "type": "Feature",
  "properties": {
    "addr:full":"Calle de Mayor, 52 Albacete Albacete 02002",
    "addr:housenumber":"52",
    "addr:postcode":"02002",
    "addr:street":"Calle De Mayor",
    "iso:country":"ES",
    "sg:address":"Calle de Mayor, 52",
    "sg:city":"Albacete",
    "sg:orig_category":"Ingeniero",
    "sg:phone":"+34 967 52 21 46",
    "sg:postcode":"02002",
    "sg:province":"Albacete",
    "wof:name":"Martinez Alcantud Juan",
    "wof:placetype":"venue"
},
  "geometry": {"coordinates":[-1.8530730009,38.9926452637],"type":"Point"}
}