{
  "type": "Feature",
  "properties": {
    "iso:country":"ES",
    "sg:address":"Rua Valle Inclan, 11",
    "sg:city":"Carballo",
    "sg:orig_category":"Lencer\u00cda Femenina, Corseter\u00cda, Trajes De Ba\u00d1o (al Por Menor)",
    "sg:phone":"+34 981 75 74 91",
    "sg:postcode":"15100",
    "sg:province":"La Coru\u00f1a",
    "wof:name":"Pallas Lopez Bego\u00f1a",
    "wof:placetype":"venue"
},
  "geometry": {"coordinates":[-8.6896333694,43.2151069641],"type":"Point"}
}