{
  "type": "Feature",
  "properties": {
    "iso:country":"ES",
    "sg:address":"Alisios, 19",
    "sg:city":"Ecija",
    "sg:orig_category":"Alquiler De V\u00cddeo",
    "sg:phone":"+34 954 83 14 04",
    "sg:postcode":"41400",
    "sg:province":"Sevilla",
    "wof:name":"Gomar S.c.",
    "wof:placetype":"venue"
},
  "geometry": {"coordinates":[-5.0450291634,37.5473060608],"type":"Point"}
}