{
  "type": "Feature",
  "properties": {
    "addr:full":"Calle de G, 18 Mutiloabeiti Navarra 31192",
    "addr:housenumber":"18",
    "addr:postcode":"31192",
    "addr:street":"Calle De G",
    "iso:country":"ES",
    "sg:address":"Calle de G, 18",
    "sg:city":"Mutiloabeiti",
    "sg:orig_category":"Comercio De Piezas De Recambio Y De Accesorios De Veh\u00cdculos, Veh\u00cdculos Industriales",
    "sg:phone":"+34 948 24 17 07",
    "sg:postcode":"31192",
    "sg:province":"Navarra",
    "wof:name":"Az Espa\u00f1a S.a.",
    "wof:placetype":"venue"
},
  "geometry": {"coordinates":[-1.6221350431,42.7874755859],"type":"Point"}
}