{
  "type": "Feature",
  "properties": {
    "iso:country":"ES",
    "sg:address":"Avgd Barcelona, 13",
    "sg:city":"Igualada",
    "sg:orig_category":"Relojer\u00cda (al Por Menor, Reparaci\u00d3n)",
    "sg:phone":"+34 938 04 65 55",
    "sg:postcode":"08700",
    "sg:province":"Barcelona",
    "wof:name":"Rodriguez Herrero Francisco",
    "wof:placetype":"venue"
},
  "geometry": {"coordinates":[1.6157799959,41.5860214233],"type":"Point"}
}