{
  "type": "Feature",
  "properties": {
    "addr:full":"Carrer de Doctor Pearson, 95 Terrassa Barcelona 08222",
    "addr:housenumber":"95",
    "addr:postcode":"08222",
    "addr:street":"Carrer De Doctor Pearson",
    "iso:country":"ES",
    "sg:address":"Carrer de Doctor Pearson, 95",
    "sg:city":"Terrassa",
    "sg:orig_category":"Contenedores (mercanc\u00cdas)",
    "sg:phone":"+34 937 85 62 85",
    "sg:postcode":"08222",
    "sg:province":"Barcelona",
    "wof:name":"Camacho Ojeda Miguel",
    "wof:placetype":"venue"
},
  "geometry": {"coordinates":[2.0237920284,41.5671234131],"type":"Point"}
}