{
  "type": "Feature",
  "properties": {
    "addr:full":"Calle de Antonio Gala, 10 Churriana Vega Granada 18194",
    "addr:housenumber":"10",
    "addr:postcode":"18194",
    "addr:street":"Calle De Antonio Gala",
    "iso:country":"ES",
    "sg:address":"Calle de Antonio Gala, 10",
    "sg:city":"Churriana Vega",
    "sg:orig_category":"Peluquer\u00cdas, Peluquer\u00cda Mixta",
    "sg:phone":"+34 958 55 31 33",
    "sg:postcode":"18194",
    "sg:province":"Granada",
    "wof:name":"Gilabert Fajardo Maria Azucena",
    "wof:placetype":"venue"
},
  "geometry": {"coordinates":[-3.6332204342,37.1439476013],"type":"Point"}
}