{
  "type": "Feature",
  "properties": {
    "addr:full":"Calle de Bande, 28 Madrid Madrid 28042",
    "addr:housenumber":"28",
    "addr:postcode":"madrid;28042",
    "addr:street":"Calle De Bande",
    "iso:country":"ES",
    "sg:address":"Calle de Bande, 28",
    "sg:city":"Madrid",
    "sg:orig_category":"Inmobiliaria (agencias)",
    "sg:phone":"+34 917 47 67 21",
    "sg:postcode":"28042",
    "sg:province":"Madrid",
    "wof:name":"Lopecall S.l.",
    "wof:placetype":"venue"
},
  "geometry": {"coordinates":[-3.5911188126,40.4638710022],"type":"Point"}
}