{
  "type": "Feature",
  "properties": {
    "addr:full":"Ctra Basurtu-kastrexana, 69 Bilbao Vizcaya 48002",
    "addr:housenumber":"69",
    "addr:postcode":"48002",
    "addr:street":"Ctra Basurtu-Kastrexana",
    "iso:country":"ES",
    "sg:address":"Ctra Basurtu-kastrexana, 69",
    "sg:city":"Bilbao",
    "sg:orig_category":"Carb\u00d3n, Carb\u00d3n De Madera (al Por Mayor)",
    "sg:phone":"+34 944 27 06 92",
    "sg:postcode":"48002",
    "sg:province":"Vizcaya",
    "wof:name":"Juan Jose Pascual Cruzado Y Javier Pascual Cruzado C.b.",
    "wof:placetype":"venue"
},
  "geometry": {"coordinates":[-2.9594590664,43.2610206604],"type":"Point"}
}