{
  "type": "Feature",
  "properties": {
    "iso:country":"ES",
    "sg:address":"Carrer de Mestre Joan Batlle, S/n",
    "sg:city":"Sagrera",
    "sg:orig_category":"Sanatorios M\u00c9dico",
    "sg:phone":"+34 938 44 76 03",
    "sg:postcode":"08187",
    "sg:province":"Barcelona",
    "wof:name":"Ajuntament De Santa Eulalia De Ron Ana",
    "wof:placetype":"venue"
},
  "geometry": {"coordinates":[2.2229328156,41.6549186707],"type":"Point"}
}