{
  "type": "Feature",
  "properties": {
    "iso:country":"ES",
    "sg:address":"Calle de Santo Domingo De Guzman, 6",
    "sg:city":"Palencia",
    "sg:orig_category":"Pescader\u00cdas (al Por Menor)",
    "sg:phone":"+34 979 75 09 09",
    "sg:postcode":"34005",
    "sg:province":"Palencia",
    "wof:name":"Chies Nozal Francisco Javier",
    "wof:placetype":"venue"
},
  "geometry": {"coordinates":[-4.536883831,42.0136795044],"type":"Point"}
}