{
  "type": "Feature",
  "properties": {
    "iso:country":"ES",
    "sg:address":"Carrer de Bonsucces, 9",
    "sg:city":"Barcelona",
    "sg:orig_category":"Institutos De Belleza",
    "sg:phone":"+34 934 12 53 34",
    "sg:postcode":"08001",
    "sg:province":"Barcelona",
    "wof:name":"Azor Yelamos Dolores",
    "wof:placetype":"venue"
},
  "geometry": {"coordinates":[2.1702370644,41.3841781616],"type":"Point"}
}