{
  "type": "Feature",
  "properties": {
    "addr:full":"Calle de Huerta Nueva, 2 Estepona M\u00e1laga 29680",
    "addr:housenumber":"2",
    "addr:postcode":"29680",
    "addr:street":"Calle De Huerta Nueva",
    "iso:country":"ES",
    "sg:address":"Calle de Huerta Nueva, 2",
    "sg:city":"Estepona",
    "sg:orig_category":"Asesor\u00cdas",
    "sg:phone":"+34 952 80 78 16",
    "sg:postcode":"29680",
    "sg:province":"M\u00e1laga",
    "sg:website":"www.preventor.es",
    "wof:name":"Preventor S.l.",
    "wof:placetype":"venue"
},
  "geometry": {"coordinates":[-5.1506471634,36.4244422913],"type":"Point"}
}