{
  "type": "Feature",
  "properties": {
    "iso:country":"ES",
    "sg:address":"Plaz Larre, 1",
    "sg:city":"Casco Nuevo",
    "sg:orig_category":"Molduras, Junquillos, Listones Y Molduras Perforadas",
    "sg:phone":"+34 948 31 03 78",
    "sg:postcode":"31191",
    "sg:province":"Navarra",
    "wof:name":"Zabalegui Larrea Francisco Javier",
    "wof:placetype":"venue"
},
  "geometry": {"coordinates":[-1.6760691404,42.6953926086],"type":"Point"}
}