{
  "type": "Feature",
  "properties": {
    "iso:country":"ES",
    "sg:address":"Carrer de Joan Lluis Vives, 16",
    "sg:city":"Can Trias Industrial",
    "sg:orig_category":"Suministros Para Carrocer\u00cdas",
    "sg:phone":"+34 937 33 68 64",
    "sg:postcode":"08232",
    "sg:province":"Barcelona",
    "wof:name":"Carrocerias Vilacarr S.l",
    "wof:placetype":"venue"
},
  "geometry": {"coordinates":[1.9658440351,41.5599975586],"type":"Point"}
}