{
  "type": "Feature",
  "properties": {
    "iso:country":"ES",
    "sg:address":"Avgd Castello, 20",
    "sg:city":"Benicasim",
    "sg:orig_category":"Bisuteros (fabricaci\u00d3n, Al Por Mayor)",
    "sg:phone":"+34 964 30 41 11",
    "sg:postcode":"12560",
    "sg:province":"Castell\u00f3n",
    "wof:name":"Jsml S.l.",
    "wof:placetype":"venue"
},
  "geometry": {"coordinates":[0.0457400009,40.0510292053],"type":"Point"}
}