{
  "type": "Feature",
  "properties": {
    "iso:country":"ES",
    "sg:address":"Calle de Zapateros, S/n",
    "sg:city":"Merida",
    "sg:orig_category":"Electrodom\u00c9sticos (al Por Menor)",
    "sg:phone":"+34 924 33 09 37",
    "sg:postcode":"06800",
    "sg:province":"Badajoz",
    "sg:website":"www.sematecextremadura.com",
    "wof:name":"Sematec Extremadura S.l.",
    "wof:placetype":"venue"
},
  "geometry": {"coordinates":[-6.3313941956,38.9296417236],"type":"Point"}
}