{
  "type": "Feature",
  "properties": {
    "addr:full":"Nafarroa Etorbidea, 7 Beasain Guip\u00f9zcoa 20200",
    "addr:housenumber":"7",
    "addr:postcode":"20200",
    "addr:street":"Nafarroa Etorbidea;Guipu\u0300Zcoa",
    "iso:country":"ES",
    "sg:address":"Nafarroa Etorbidea, 7",
    "sg:city":"Beasain",
    "sg:orig_category":"Complementos De Vestir (al Por Menor)",
    "sg:phone":"+34 943 88 40 80",
    "sg:postcode":"20200",
    "sg:province":"Guip\u00f9zcoa",
    "wof:name":"Calzados Oyarbide",
    "wof:placetype":"venue"
},
  "geometry": {"coordinates":[-2.1999850273,43.0466957092],"type":"Point"}
}