{
  "type": "Feature",
  "properties": {
    "iso:country":"ES",
    "sg:address":"Carrer de Lluis Borrassa, 16",
    "sg:city":"Barcelona",
    "sg:orig_category":"Centros De Educaci\u00d3n Especial",
    "sg:phone":"+34 933 05 22 01",
    "sg:postcode":"08019",
    "sg:province":"Barcelona",
    "wof:name":"Co%egi Del Sagrat Corazon",
    "wof:placetype":"venue"
},
  "geometry": {"coordinates":[2.2177629471,41.4159622192],"type":"Point"}
}