{
  "type": "Feature",
  "properties": {
    "addr:full":"Av Canovelles, 1 Barriada Nova Barcelona 08420",
    "addr:housenumber":"1",
    "addr:postcode":"08420",
    "addr:street":"Av Canovelles;Nova Barcelona",
    "iso:country":"ES",
    "sg:address":"Av Canovelles, 1",
    "sg:city":"Barriada Nova",
    "sg:orig_category":"Mec\u00c1nico Del Autom\u00d3vil",
    "sg:phone":"+34 938 49 04 05",
    "sg:postcode":"08420",
    "sg:province":"Barcelona",
    "wof:name":"Restauracio I Multimedia S.l.l.",
    "wof:placetype":"venue"
},
  "geometry": {"coordinates":[2.2783401012,41.6220207214],"type":"Point"}
}