{
  "type": "Feature",
  "properties": {
    "addr:full":"Calle de Carrera De Las Monjas, 1 Priego Cordoba C\u00f3rdoba 14800",
    "addr:housenumber":"1",
    "addr:postcode":"14800",
    "addr:street":"Calle De Carrera De Las Monjas;Cordoba Co\u0301Rdoba",
    "iso:country":"ES",
    "sg:address":"Calle de Carrera De Las Monjas, 1",
    "sg:city":"Priego Cordoba",
    "sg:orig_category":"Inmobiliaria (agencias)",
    "sg:phone":"+34 957 54 09 93",
    "sg:postcode":"14800",
    "sg:province":"C\u00f3rdoba",
    "wof:name":"Lopez Barron Juan",
    "wof:placetype":"venue"
},
  "geometry": {"coordinates":[-4.1961374283,37.4383430481],"type":"Point"}
}