{
  "type": "Feature",
  "properties": {
    "iso:country":"ES",
    "sg:address":"Glorieta De La Cruz, 7",
    "sg:city":"Pedreguer",
    "sg:orig_category":"Reposter\u00cdas",
    "sg:phone":"+34 965 76 03 22",
    "sg:postcode":"03750",
    "sg:province":"Alicante",
    "wof:name":"Morell Forner Juan Jose",
    "wof:placetype":"venue"
},
  "geometry": {"coordinates":[0.0347849987,38.7958145142],"type":"Point"}
}