{
  "type": "Feature",
  "properties": {
    "iso:country":"ES",
    "sg:address":"Alam Barcelo, 48",
    "sg:city":"Malaga",
    "sg:orig_category":"Cl\u00cdnicas Dentales",
    "sg:phone":"+34 952 26 83 52",
    "sg:postcode":"29014",
    "sg:province":"M\u00e1laga",
    "wof:name":"Morphodent S.l.",
    "wof:placetype":"venue"
},
  "geometry": {"coordinates":[-4.4187450409,36.7316703796],"type":"Point"}
}