{
  "type": "Feature",
  "properties": {
    "addr:full":"Calle de Doctor Fleming, 5 Madrid Madrid 28036",
    "addr:housenumber":"5",
    "addr:postcode":"28036",
    "addr:street":"Calle De Doctor Fleming",
    "iso:country":"ES",
    "sg:address":"Calle de Doctor Fleming, 5",
    "sg:city":"Madrid",
    "sg:orig_category":"Art\u00cdculos De Regalo (al Por Menor)",
    "sg:phone":"+34 914 57 03 37",
    "sg:postcode":"28036",
    "sg:province":"Madrid",
    "sg:website":"www.revolutum.com",
    "wof:name":"Revolutum Company S.l.",
    "wof:placetype":"venue"
},
  "geometry": {"coordinates":[-3.6880631447,40.4590377808],"type":"Point"}
}