{
  "type": "Feature",
  "properties": {
    "addr:full":"Av Aluminio(pque Emp Pcdo), S/n Aviles Asturias 33400",
    "addr:housenumber":"s / n",
    "addr:postcode":"33400",
    "addr:street":"Av Aluminio Pque",
    "iso:country":"ES",
    "sg:address":"Av Aluminio(pque Emp Pcdo), S/n",
    "sg:city":"Aviles",
    "sg:orig_category":"Empresas De Limpieza",
    "sg:phone":"+34 985 56 14 47",
    "sg:postcode":"33400",
    "sg:province":"Asturias",
    "wof:name":"Jofra S. A.",
    "wof:placetype":"venue"
},
  "geometry": {"coordinates":[-5.9082927704,43.5579338074],"type":"Point"}
}