{
  "type": "Feature",
  "properties": {
    "iso:country":"ES",
    "sg:address":"Carrer de Santa Teresa, 3",
    "sg:city":"Caldes Montbui",
    "sg:orig_category":"T\u00c9cnicos Veterinarios",
    "sg:phone":"+34 938 65 01 29",
    "sg:postcode":"08140",
    "sg:province":"Barcelona",
    "wof:name":"Torres Rocha Maria Pilar",
    "wof:placetype":"venue"
},
  "geometry": {"coordinates":[2.1654589176,41.629699707],"type":"Point"}
}