{
  "type": "Feature",
  "properties": {
    "iso:country":"ES",
    "sg:address":"Calle de Leoncio Mejias Carmona, 5",
    "sg:city":"Aguilar De La Frontera",
    "sg:orig_category":"Reposter\u00cdas",
    "sg:phone":"+34 957 66 09 15",
    "sg:postcode":"14920",
    "sg:province":"C\u00f3rdoba",
    "wof:name":"Cerrollano S.l.",
    "wof:placetype":"venue"
},
  "geometry": {"coordinates":[-4.6620140076,37.5116958618],"type":"Point"}
}