{
  "type": "Feature",
  "properties": {
    "iso:country":"ES",
    "sg:address":"Calle de San Jose, 2",
    "sg:city":"Puertollano",
    "sg:orig_category":"Venta, Alquiler De Instrumentos Y Accesorios De M\u00dasica",
    "sg:phone":"+34 926 43 28 07",
    "sg:postcode":"13500",
    "sg:province":"Ciudad Real",
    "wof:name":"Fernandez Barrero Montserrat",
    "wof:placetype":"venue"
},
  "geometry": {"coordinates":[-4.1093840599,38.6860389709],"type":"Point"}
}