{
  "type": "Feature",
  "properties": {
    "iso:country":"ES",
    "sg:address":"Calle de Acoran, 6",
    "sg:city":"Monta\u00d1eta",
    "sg:orig_category":"Mec\u00c1nico Del Autom\u00d3vil",
    "sg:phone":"+34 922 35 47 54",
    "sg:postcode":"38419",
    "sg:province":"Santa Cruz De Tenerife",
    "wof:name":"Perez Jorge Juan Francisco",
    "wof:placetype":"venue"
},
  "geometry": {"coordinates":[-16.5596256256,28.3892383575],"type":"Point"}
}