{
  "type": "Feature",
  "properties": {
    "iso:country":"ES",
    "sg:address":"Calle de Nueva, 23",
    "sg:city":"Alcorcon",
    "sg:orig_category":"Farmacias",
    "sg:phone":"+34 916 12 39 23",
    "sg:postcode":"28921",
    "sg:province":"Madrid",
    "wof:name":"Garcia Sancho Adoracion",
    "wof:placetype":"venue"
},
  "geometry": {"coordinates":[-3.8264350891,40.3483390808],"type":"Point"}
}