{
  "type": "Feature",
  "properties": {
    "addr:full":"Calle de Huelva, 49 Ejido Almer\u00eda 04700",
    "addr:housenumber":"49 ejido",
    "addr:postcode":"04700",
    "addr:street":"Calle De Huelva;Almeri\u0301A",
    "iso:country":"ES",
    "sg:address":"Calle de Huelva, 49",
    "sg:city":"Ejido",
    "sg:orig_category":"Mec\u00c1nico Del Autom\u00d3vil",
    "sg:phone":"+34 950 57 21 12",
    "sg:postcode":"04700",
    "sg:province":"Almer\u00eda",
    "wof:name":"Autorapid",
    "wof:placetype":"venue"
},
  "geometry": {"coordinates":[-2.8186028004,36.769443512],"type":"Point"}
}