{
  "type": "Feature",
  "properties": {
    "iso:country":"ES",
    "sg:address":"Andujar, S/n",
    "sg:city":"Bailen",
    "sg:orig_category":"Reposter\u00cdas",
    "sg:phone":"+34 953 67 21 01",
    "sg:postcode":"23710",
    "sg:province":"Ja\u00e9n",
    "wof:name":"Duran Torres Sebastian",
    "wof:placetype":"venue"
},
  "geometry": {"coordinates":[-3.7828440666,38.0947151184],"type":"Point"}
}