{
  "type": "Feature",
  "properties": {
    "iso:country":"ES",
    "sg:address":"Barr Gumuzio, 23",
    "sg:city":"Boroa",
    "sg:orig_category":"Comercio De Piezas De Recambio Y De Accesorios De Veh\u00cdculos, Veh\u00cdculos Industriales",
    "sg:phone":"+34 946 73 08 53",
    "sg:postcode":"48340",
    "sg:province":"Vizcaya",
    "wof:name":"Autos Y Repuestos Madariaga S.l.",
    "wof:placetype":"venue"
},
  "geometry": {"coordinates":[-2.7492077351,43.2405662537],"type":"Point"}
}