{
  "type": "Feature",
  "properties": {
    "iso:country":"ES",
    "sg:address":"Calle de Sarmiento, 2",
    "sg:city":"Villaviciosa Odon",
    "sg:orig_category":"Empresarios",
    "sg:phone":"+34 916 16 01 85",
    "sg:postcode":"28670",
    "sg:province":"Madrid",
    "wof:name":"Montoya Ortiz Carlos",
    "wof:placetype":"venue"
},
  "geometry": {"coordinates":[-3.8930668831,40.357460022],"type":"Point"}
}