{
  "type": "Feature",
  "properties": {
    "iso:country":"ES",
    "sg:address":"Avda Principe Felipe (del), 18",
    "sg:city":"Rincon Soto",
    "sg:orig_category":"Estancos",
    "sg:phone":"+34 941 16 01 14",
    "sg:postcode":"26550",
    "sg:province":"La Rioja",
    "wof:name":"Mendizabal Sainz Ana Isabel",
    "wof:placetype":"venue"
},
  "geometry": {"coordinates":[-1.85155797,42.2350196838],"type":"Point"}
}