{
  "type": "Feature",
  "properties": {
    "addr:full":"Avda Andalucia (de), 11 Montilla C\u00f3rdoba 14550",
    "addr:housenumber":"11",
    "addr:postcode":"14550",
    "addr:street":"Avda Andalucia De;Co\u0301Rdoba",
    "iso:country":"ES",
    "sg:address":"Avda Andalucia (de), 11",
    "sg:city":"Montilla",
    "sg:orig_category":"Sanatorios M\u00c9dico",
    "sg:phone":"+34 957 65 51 25",
    "sg:postcode":"14550",
    "sg:province":"C\u00f3rdoba",
    "wof:name":"Servicio Andaluz De Salud",
    "wof:placetype":"venue"
},
  "geometry": {"coordinates":[-4.6430897713,37.5835838318],"type":"Point"}
}