{
  "type": "Feature",
  "properties": {
    "addr:full":"Cami Ral, 411 Mataro Barcelona 08301",
    "addr:housenumber":"411",
    "addr:postcode":"08301",
    "addr:street":"Ral",
    "iso:country":"ES",
    "sg:address":"Cami Ral, 411",
    "sg:city":"Mataro",
    "sg:orig_category":"Trajes Y Adornos De Boda (confecci\u00d3n, Al Por Menor)",
    "sg:phone":"+34 937 96 18 59",
    "sg:postcode":"08301",
    "sg:province":"Barcelona",
    "wof:name":"Miravalles Hidalgo Alicia",
    "wof:placetype":"venue"
},
  "geometry": {"coordinates":[2.4438400269,41.5368881226],"type":"Point"}
}