{
  "type": "Feature",
  "properties": {
    "iso:country":"ES",
    "sg:address":"Cinco Ruas, 4",
    "sg:city":"Pobra Carami\u00f1al",
    "sg:orig_category":"Electrodom\u00c9sticos (al Por Menor)",
    "sg:phone":"+34 981 83 14 53",
    "sg:postcode":"15940",
    "sg:province":"La Coru\u00f1a",
    "wof:name":"Sampedro Dominguez Gumersindo",
    "wof:placetype":"venue"
},
  "geometry": {"coordinates":[-8.9384899139,42.6035690308],"type":"Point"}
}