{
  "type": "Feature",
  "properties": {
    "addr:full":"Calle de Granada, 155 Almeria Almer\u00eda 04008",
    "addr:housenumber":"155",
    "addr:postcode":"04008",
    "addr:street":"Calle De Granada",
    "iso:country":"ES",
    "sg:address":"Calle de Granada, 155",
    "sg:city":"Almeria",
    "sg:orig_category":"Centros Comerciales Y Grandes Tiendas",
    "sg:phone":"+34 950 25 66 14",
    "sg:postcode":"04008",
    "sg:province":"Almer\u00eda",
    "wof:name":"Ye  Taosen",
    "wof:placetype":"venue"
},
  "geometry": {"coordinates":[-2.4584610462,36.8469009399],"type":"Point"}
}