{
  "type": "Feature",
  "properties": {
    "iso:country":"ES",
    "sg:address":"Urb Lomas De Marbella Club, S/n",
    "sg:city":"Marbella",
    "sg:orig_category":"Agencias Y Agentes Comerciales, Representantes",
    "sg:phone":"+34 952 82 22 94",
    "sg:postcode":"29600",
    "sg:province":"M\u00e1laga",
    "wof:name":"Shaffer  John",
    "wof:placetype":"venue"
},
  "geometry": {"coordinates":[-4.9405241013,36.5068511963],"type":"Point"}
}