{
  "type": "Feature",
  "properties": {
    "iso:country":"ES",
    "sg:address":"Calle de Antonio Ferrandis 'chanquete', 39",
    "sg:city":"Nerja",
    "sg:orig_category":"Turismo: Lugares, Circuitos Y Curiosidades",
    "sg:phone":"+34 952 52 70 58",
    "sg:postcode":"29780",
    "sg:province":"M\u00e1laga",
    "wof:name":"Life Adventure S.l.",
    "wof:placetype":"venue"
},
  "geometry": {"coordinates":[-3.8844659328,36.745464325],"type":"Point"}
}