{
  "type": "Feature",
  "properties": {
    "iso:country":"ES",
    "sg:address":"Calle de Pantaleon Benedi, 3",
    "sg:city":"Casetas",
    "sg:orig_category":"Serigraf\u00cda (material Y Suministros)",
    "sg:phone":"+34 976 78 69 04",
    "sg:postcode":"50620",
    "sg:province":"Zaragoza",
    "wof:name":"Servicios Serigraficos Taula S.l.",
    "wof:placetype":"venue"
},
  "geometry": {"coordinates":[-1.0289520025,41.7173919678],"type":"Point"}
}