{
  "type": "Feature",
  "properties": {
    "addr:full":"Calle de Emilia Pardo Bazan, 14 Rua De Valdeorras Ourense 32350",
    "addr:housenumber":"14",
    "addr:postcode":"32350",
    "addr:street":"Calle De Emilia Pardo Bazan;Rua De",
    "iso:country":"ES",
    "sg:address":"Calle de Emilia Pardo Bazan, 14",
    "sg:city":"Rua De Valdeorras",
    "sg:orig_category":"Transportes De Material De Construcci\u00d3n",
    "sg:phone":"+34 988 31 15 09",
    "sg:postcode":"32350",
    "sg:province":"Ourense",
    "wof:name":"Rodriguez Vidal Baldomero",
    "wof:placetype":"venue"
},
  "geometry": {"coordinates":[-7.1205739975,42.392490387],"type":"Point"}
}