{
  "type": "Feature",
  "properties": {
    "iso:country":"ES",
    "sg:address":"Rua San Roque, 78",
    "sg:city":"Vigo",
    "sg:orig_category":"Artes Gr\u00c1ficas, Artes Pl\u00c1sticas (curso)",
    "sg:phone":"+34 986 41 89 74",
    "sg:postcode":"36204",
    "sg:province":"Pontevedra",
    "wof:name":"Graficas Suevia S.l.",
    "wof:placetype":"venue"
},
  "geometry": {"coordinates":[-8.7094068527,42.2284812927],"type":"Point"}
}