{
  "type": "Feature",
  "properties": {
    "addr:full":"Pg. Enric Morera, 27 S. Pere Ribes Barcelona 08810",
    "addr:housenumber":"27",
    "addr:postcode":"08810",
    "addr:street":"Pg. Enric Morera;S. Pere Ribes Barcelona",
    "iso:country":"ES",
    "sg:address":"Pg. Enric Morera, 27",
    "sg:city":"S. Pere Ribes",
    "sg:orig_category":"Promotores Constructores",
    "sg:phone":"+34 938 96 26 49",
    "sg:postcode":"08810",
    "sg:province":"Barcelona",
    "wof:name":"Promotora De Magatzems I Habitatges S.l.",
    "wof:placetype":"venue"
},
  "geometry": {"coordinates":[1.7804319859,41.2590560913],"type":"Point"}
}