{
  "type": "Feature",
  "properties": {
    "iso:country":"ES",
    "sg:address":"Calle de Jose Lazaro Galdiano, 1",
    "sg:city":"Madrid",
    "sg:orig_category":"Abogados",
    "sg:phone":"+34 914 58 62 65",
    "sg:postcode":"28036",
    "sg:province":"Madrid",
    "wof:name":"Perez Ullivarri Brasac Rafael",
    "wof:placetype":"venue"
},
  "geometry": {"coordinates":[-3.6875319481,40.4576377869],"type":"Point"}
}