{
  "type": "Feature",
  "properties": {
    "iso:country":"ES",
    "sg:address":"Bo. S. Jose, S/n",
    "sg:city":"Callosa Segura",
    "sg:orig_category":"Promotores Constructores",
    "sg:phone":"+34 965 31 23 76",
    "sg:postcode":"03360",
    "sg:province":"Alicante",
    "wof:name":"Construcciones Calabia Opsl.",
    "wof:placetype":"venue"
},
  "geometry": {"coordinates":[-0.8776689768,38.1256752014],"type":"Point"}
}