{
  "type": "Feature",
  "properties": {
    "addr:full":"Ctra. El Portal-medina, 22 Jerez C\u00e1diz 11408",
    "addr:housenumber":"22",
    "addr:postcode":"11408",
    "addr:street":"Ctra. El Portal-Medina",
    "iso:country":"ES",
    "sg:address":"Ctra. El Portal-medina, 22",
    "sg:city":"Jerez",
    "sg:orig_category":"Molduras, Junquillos, Listones Y Molduras Perforadas",
    "sg:phone":"+34 956 14 51 05",
    "sg:postcode":"11408",
    "sg:province":"C\u00e1diz",
    "wof:name":"Airadsl Wi-fi S.l.",
    "wof:placetype":"venue"
},
  "geometry": {"coordinates":[-6.1633043289,36.6765556335],"type":"Point"}
}