{
  "type": "Feature",
  "properties": {
    "iso:country":"ES",
    "sg:address":"Rbla Guipuscoa, 73",
    "sg:city":"Barcelona",
    "sg:orig_category":"Agencias De Viajes",
    "sg:phone":"+34 934 98 78 10",
    "sg:postcode":"08020",
    "sg:province":"Barcelona",
    "sg:website":"www.viajesiberia.com",
    "wof:name":"Viajes Iberia S.a.",
    "wof:placetype":"venue"
},
  "geometry": {"coordinates":[2.1987650394,41.4179649353],"type":"Point"}
}