{
  "type": "Feature",
  "properties": {
    "addr:full":"Estd Carreteira-moreiras (a), S/n Moreiras Ourense 32920",
    "addr:housenumber":"s / n",
    "addr:postcode":"32920",
    "iso:country":"ES",
    "sg:address":"Estd Carreteira-moreiras (a), S/n",
    "sg:city":"Moreiras",
    "sg:orig_category":"Muebles Y Accesorios Para Cocinas Y Cuartos De Ba\u00d1o (al Por Menor)",
    "sg:phone":"+34 988 26 20 14",
    "sg:postcode":"32920",
    "sg:province":"Ourense",
    "wof:name":"Garcia Lopez Jose",
    "wof:placetype":"venue"
},
  "geometry": {"coordinates":[-7.9516019821,42.2935142517],"type":"Point"}
}