{
  "type": "Feature",
  "properties": {
    "iso:country":"ES",
    "sg:address":"Ctra Montalban, Km. 0000,8",
    "sg:city":"Rambla",
    "sg:orig_category":"Alfarer\u00cda",
    "sg:phone":"+34 957 68 41 50",
    "sg:postcode":"14540",
    "sg:province":"C\u00f3rdoba",
    "wof:name":"Luque Marin Juan Andres",
    "wof:placetype":"venue"
},
  "geometry": {"coordinates":[-4.7406468391,37.5998077393],"type":"Point"}
}