{
  "type": "Feature",
  "properties": {
    "iso:country":"ES",
    "sg:address":"Calle de Venta Nueva (la), 17",
    "sg:city":"Zamarramala",
    "sg:orig_category":"Art\u00cdculos De Aluminio",
    "sg:phone":"+34 921 42 09 76",
    "sg:postcode":"40196",
    "sg:province":"Segovia",
    "wof:name":"Aluminios Zamarramala S.l.",
    "wof:placetype":"venue"
},
  "geometry": {"coordinates":[-4.1346559525,40.9673538208],"type":"Point"}
}