{
  "type": "Feature",
  "properties": {
    "addr:full":"Calle de Mayor, 23 Jaca Huesca 22700",
    "addr:housenumber":"23",
    "addr:postcode":"22700",
    "addr:street":"Calle De Mayor",
    "iso:country":"ES",
    "sg:address":"Calle de Mayor, 23",
    "sg:city":"Jaca",
    "sg:classifiers":[
        {
            "category":"Autos & Motor Vehicles",
            "subcategory":"Automobile Sales",
            "type":"Retail Goods"
        }
    ],
    "sg:phone":"+34 974 36 15 36",
    "sg:postcode":"22700",
    "sg:province":"Huesca",
    "wof:name":"Autoescuela Casamian S.cv.",
    "wof:placetype":"venue"
},
  "geometry": {"coordinates":[-0.5500190258,42.5693321228],"type":"Point"}
}