{
  "type": "Feature",
  "properties": {
    "iso:country":"ES",
    "sg:address":"Orape Kalea, 14",
    "sg:city":"Zarautz",
    "sg:orig_category":"Asociaciones, Organismos Culturales Y Socioeducativos",
    "sg:phone":"+34 943 83 00 66",
    "sg:postcode":"20800",
    "sg:province":"Guip\u00f9zcoa",
    "wof:name":"Arrano Kabia Elkarte Kulturala",
    "wof:placetype":"venue"
},
  "geometry": {"coordinates":[-2.1766650677,43.2857818604],"type":"Point"}
}