{
  "type": "Feature",
  "properties": {
    "addr:full":"Calle de Julio Herrero, 4 Torrelodones Madrid 28250",
    "addr:housenumber":"4",
    "addr:postcode":"28250",
    "addr:street":"Calle De Julio Herrero",
    "iso:country":"ES",
    "sg:address":"Calle de Julio Herrero, 4",
    "sg:city":"Torrelodones",
    "sg:orig_category":"Clases De M\u00dasica Y Canto",
    "sg:phone":"+34 918 59 32 56",
    "sg:postcode":"28250",
    "sg:province":"Madrid",
    "wof:name":"Centro De Estudios Musicales De Torrelodones S.l.",
    "wof:placetype":"venue"
},
  "geometry": {"coordinates":[-3.9275650978,40.5773277283],"type":"Point"}
}