{
  "type": "Feature",
  "properties": {
    "addr:full":"Calle de Sofia, 195 Madrid Madrid 28022",
    "addr:housenumber":"195",
    "addr:postcode":"28022",
    "addr:street":"Calle De Sofia",
    "iso:country":"ES",
    "sg:address":"Calle de Sofia, 195",
    "sg:city":"Madrid",
    "sg:orig_category":"Farmacias",
    "sg:phone":"+34 917 60 14 50",
    "sg:postcode":"28022",
    "sg:province":"Madrid",
    "wof:name":"Farmacia Vasco-herrero C.b.",
    "wof:placetype":"venue"
},
  "geometry": {"coordinates":[-3.601140976,40.4266471863],"type":"Point"}
}