{
  "type": "Feature",
  "properties": {
    "addr:full":"Calle de Jose Benlliure, 41 Valencia Valencia 46011",
    "addr:housenumber":"41",
    "addr:postcode":"46011",
    "addr:street":"Calle De Jose Benlliure",
    "iso:country":"ES",
    "sg:address":"Calle de Jose Benlliure, 41",
    "sg:city":"Valencia",
    "sg:orig_category":"M\u00c1rmoles, Granitos Y Piedras Naturales",
    "sg:phone":"+34 963 67 08 30",
    "sg:postcode":"46011",
    "sg:province":"Valencia",
    "wof:name":"Sinisterra Laguia Juan Antonio",
    "wof:placetype":"venue"
},
  "geometry": {"coordinates":[-0.3311060071,39.4644889832],"type":"Point"}
}