{
  "type": "Feature",
  "properties": {
    "iso:country":"ES",
    "sg:address":"Calle de Artajona, 7",
    "sg:city":"Madrid",
    "sg:orig_category":"Caf\u00c9s, Bares, Cervecer\u00cdas",
    "sg:phone":"+34 914 50 67 23",
    "sg:postcode":"28039",
    "sg:province":"Madrid",
    "wof:name":"Soler Cantero Juan",
    "wof:placetype":"venue"
},
  "geometry": {"coordinates":[-3.7185096741,40.4633140564],"type":"Point"}
}