{
  "type": "Feature",
  "properties": {
    "iso:country":"ES",
    "sg:address":"Calle de Obispo Arenzana, 8",
    "sg:city":"Calahorra",
    "sg:orig_category":"Promotores Constructores",
    "sg:phone":"+34 941 13 27 62",
    "sg:postcode":"26500",
    "sg:province":"La Rioja",
    "wof:name":"Fomento De Construcciones Y Contratas S A",
    "wof:placetype":"venue"
},
  "geometry": {"coordinates":[-1.9710359573,42.3044967651],"type":"Point"}
}