{
  "type": "Feature",
  "properties": {
    "iso:country":"ES",
    "sg:address":"Avda Independencia, 30",
    "sg:city":"Zaragoza",
    "sg:orig_category":"M\u00c9dicos: Estomatolog\u00cda",
    "sg:phone":"+34 976 21 20 38",
    "sg:postcode":"50004",
    "sg:province":"Zaragoza",
    "wof:name":"Rodriguez Avelino Carmen",
    "wof:placetype":"venue"
},
  "geometry": {"coordinates":[-0.8836249709,41.6496429443],"type":"Point"}
}