{
  "type": "Feature",
  "properties": {
    "iso:country":"ES",
    "sg:address":"Avda Rey Juan Carlos I, S/n",
    "sg:city":"Majadahonda",
    "sg:orig_category":"Promotores Constructores",
    "sg:phone":"+34 916 79 60 92",
    "sg:postcode":"28220",
    "sg:province":"Madrid",
    "wof:name":"Afar-4 S.a.",
    "wof:placetype":"venue"
},
  "geometry": {"coordinates":[-3.8874742985,40.4751052856],"type":"Point"}
}