{
  "type": "Feature",
  "properties": {
    "iso:country":"ES",
    "sg:address":"Avda Europa (de), 34",
    "sg:city":"Gri\u00f1on",
    "sg:orig_category":"Fabricaci\u00d3n De Sobres, Bolsas Y Fundas",
    "sg:phone":"+34 918 10 30 17",
    "sg:postcode":"28971",
    "sg:province":"Madrid",
    "wof:name":"Sobre Plus S.a.",
    "wof:placetype":"venue"
},
  "geometry": {"coordinates":[-3.8579499722,40.2094841003],"type":"Point"}
}