{
  "type": "Feature",
  "properties": {
    "addr:full":"Calle de Conde De Pe\u00d1alver, 52 Madrid Madrid 28006",
    "addr:housenumber":"52",
    "addr:postcode":"madrid;28006",
    "addr:street":"Calle De Conde De Pen\u0303Alver",
    "iso:country":"ES",
    "sg:address":"Calle de Conde De Pe\u00d1alver, 52",
    "sg:city":"Madrid",
    "sg:orig_category":"Centros Empresariales",
    "sg:phone":"+34 913 09 66 37",
    "sg:postcode":"28006",
    "sg:province":"Madrid",
    "sg:website":"www.autocontrol.es",
    "wof:name":"Asociacion De Autocontrol De La Publicidad",
    "wof:placetype":"venue"
},
  "geometry": {"coordinates":[-3.6752450466,40.4303131104],"type":"Point"}
}