{
  "type": "Feature",
  "properties": {
    "iso:country":"ES",
    "sg:address":"Avda Ordo\u00d1o Ii, 10",
    "sg:city":"Le\u00f3n",
    "sg:orig_category":"Administraciones Regionales, Departamentales Y Locales",
    "sg:phone":"+34 987 89 55 00",
    "sg:postcode":"24...",
    "sg:province":"Le\u00f3n",
    "wof:name":"Ayuntamiento De Leon",
    "wof:placetype":"venue"
},
  "geometry": {"coordinates":[-5.5740528107,42.5973701477],"type":"Point"}
}