{
  "type": "Feature",
  "properties": {
    "iso:country":"ES",
    "sg:address":"Carrer de Doctor Klein, 55",
    "sg:city":"Cardedeu",
    "sg:orig_category":"Tiendas De Grano, Frutas Y Legumbres Secas (al Por Menor)",
    "sg:phone":"+34 938 46 21 03",
    "sg:postcode":"08440",
    "sg:province":"Barcelona",
    "wof:name":"Sarra Maso Balbina",
    "wof:placetype":"venue"
},
  "geometry": {"coordinates":[2.3575589657,41.6390113831],"type":"Point"}
}