{
  "type": "Feature",
  "properties": {
    "iso:country":"ES",
    "sg:address":"Avda Hermanos Bou, 153",
    "sg:city":"Castellon",
    "sg:orig_category":"Electricidad: Instaladores",
    "sg:phone":"+34 964 23 29 02",
    "sg:postcode":"12003",
    "sg:province":"Castell\u00f3n",
    "wof:name":"Montajes Electricos Juan Vinuesa S.l.",
    "wof:placetype":"venue"
},
  "geometry": {"coordinates":[-0.0077,39.9836883545],"type":"Point"}
}