{
  "type": "Feature",
  "properties": {
    "iso:country":"ES",
    "sg:address":"Praj Carramolina, S/n",
    "sg:city":"Carramolina",
    "sg:orig_category":"Ingeniero",
    "sg:phone":"+34 976 89 19 02",
    "sg:postcode":"50300",
    "sg:province":"Zaragoza",
    "wof:name":"Veron Gallego Miguel Angel",
    "wof:placetype":"venue"
},
  "geometry": {"coordinates":[-1.6394540071,41.3522415161],"type":"Point"}
}