{
  "type": "Feature",
  "properties": {
    "addr:full":"Calle de Mar Cantabrico, 11 Torrelodones Madrid 28250",
    "addr:housenumber":"11",
    "addr:postcode":"28250",
    "addr:street":"Calle De Mar Cantabrico",
    "iso:country":"ES",
    "sg:address":"Calle de Mar Cantabrico, 11",
    "sg:city":"Torrelodones",
    "sg:orig_category":"Agencias Y Asesores De Publicidad",
    "sg:phone":"+34 918 59 09 17",
    "sg:postcode":"28250",
    "sg:province":"Madrid",
    "wof:name":"Estudios De Medios De Publicidad Para Espa\u00f1a S.l.",
    "wof:placetype":"venue"
},
  "geometry": {"coordinates":[-3.9274640083,40.5812263489],"type":"Point"}
}