{
  "type": "Feature",
  "properties": {
    "iso:country":"ES",
    "sg:address":"Calle de Algatocin, 3",
    "sg:city":"Malaga",
    "sg:orig_category":"Fabricaci\u00d3n De Jabones, Detergentes Y Lej\u00cdas",
    "sg:phone":"+34 952 23 38 35",
    "sg:postcode":"29004",
    "sg:province":"M\u00e1laga",
    "wof:name":"Persan S.a.",
    "wof:placetype":"venue"
},
  "geometry": {"coordinates":[-4.4652910233,36.6800537109],"type":"Point"}
}