{
  "type": "Feature",
  "properties": {
    "iso:country":"ES",
    "sg:address":"Barr Zabalea, S/n",
    "sg:city":"Uztarroz",
    "sg:orig_category":"Comerciantes Al Por Mayor De Vinos, Licores Y Alcoholes",
    "sg:phone":"+34 948 89 32 36",
    "sg:postcode":"31418",
    "sg:province":"Navarra",
    "wof:name":"Bodegas Y Destilerias Uztarrotze S.l.",
    "wof:placetype":"venue"
},
  "geometry": {"coordinates":[-0.9404249787,42.8917007446],"type":"Point"}
}