{
  "type": "Feature",
  "properties": {
    "iso:country":"ES",
    "sg:address":"Calle de Venezuela, 2",
    "sg:city":"Ejido",
    "sg:orig_category":"Centros De Educaci\u00d3n Especial",
    "sg:phone":"+34 950 48 06 18",
    "sg:postcode":"04700",
    "sg:province":"Almer\u00eda",
    "wof:name":"Junta De Andalucia",
    "wof:placetype":"venue"
},
  "geometry": {"coordinates":[-2.8203148842,36.7721939087],"type":"Point"}
}