{
  "type": "Feature",
  "properties": {
    "addr:full":"Carrer de Martorell, 59 S. Cugat Valles Barcelona 08172",
    "addr:housenumber":"59",
    "addr:postcode":"08172",
    "addr:street":"Carrer De Martorell;S. Cugat Valles Barcelona",
    "iso:country":"ES",
    "sg:address":"Carrer de Martorell, 59",
    "sg:city":"S. Cugat Valles",
    "sg:orig_category":"Asesor\u00cda Sobre Comunicaci\u00d3n De Empresas",
    "sg:phone":"+34 936 74 19 78",
    "sg:postcode":"08172",
    "sg:province":"Barcelona",
    "wof:name":"Empresa Y Solucion S. L.",
    "wof:placetype":"venue"
},
  "geometry": {"coordinates":[2.0785861015,41.4697113037],"type":"Point"}
}