{
  "type": "Feature",
  "properties": {
    "addr:full":"Rua Rio Mao, 3 Ourense Ourense 32001",
    "addr:housenumber":"3",
    "addr:postcode":"32001",
    "addr:street":"Rua;Mao",
    "iso:country":"ES",
    "sg:address":"Rua Rio Mao, 3",
    "sg:city":"Ourense",
    "sg:orig_category":"Electricidad: Equipos Industriales, Componentes (fabricaci\u00d3n)",
    "sg:phone":"+34 988 51 02 98",
    "sg:postcode":"32001",
    "sg:province":"Ourense",
    "wof:name":"Galilux Electricidad S.l.",
    "wof:placetype":"venue"
},
  "geometry": {"coordinates":[-7.8648071289,42.3508796692],"type":"Point"}
}