{
  "type": "Feature",
  "properties": {
    "iso:country":"ES",
    "sg:address":"Calle de Costera, La, 2",
    "sg:city":"Valencia",
    "sg:orig_category":"Financiaci\u00d3n Y Cr\u00c9ditos",
    "sg:phone":"+34 963 49 86 38",
    "sg:postcode":"46015",
    "sg:province":"Valencia",
    "wof:name":"Financieras Afsar S.l.",
    "wof:placetype":"venue"
},
  "geometry": {"coordinates":[-0.4003866017,39.493221283],"type":"Point"}
}