{
  "type": "Feature",
  "properties": {
    "addr:full":"Pase Pisones, 33 Burgos Burgos 09001",
    "addr:housenumber":"33",
    "addr:postcode":"09001",
    "addr:street":"Pase Pisones",
    "iso:country":"ES",
    "sg:address":"Pase Pisones, 33",
    "sg:city":"Burgos",
    "sg:orig_category":"Molduras, Junquillos, Listones Y Molduras Perforadas",
    "sg:phone":"+34 947 27 94 87",
    "sg:postcode":"09001",
    "sg:province":"Burgos",
    "wof:name":"Jimenez Ortega Joaquin",
    "wof:placetype":"venue"
},
  "geometry": {"coordinates":[-3.6989068985,42.3320846558],"type":"Point"}
}