{
  "type": "Feature",
  "properties": {
    "iso:country":"ES",
    "sg:address":"Ctra. Morata-titulcia, Km. 0015,0",
    "sg:city":"Serranillo-torreza",
    "sg:orig_category":"Perreras, Pensiones Para Perros, Gatos Y Otros Animales",
    "sg:phone":"+34 918 73 94 20",
    "sg:postcode":"28370",
    "sg:province":"Madrid",
    "wof:name":"Residencia Canina De Termes S.l.",
    "wof:placetype":"venue"
},
  "geometry": {"coordinates":[-3.4264500141,40.1392173767],"type":"Point"}
}