{
  "type": "Feature",
  "properties": {
    "addr:full":"Calle de General Gomez Nu\u00d1ez, 12 Ponferrada Le\u00f3n 24400",
    "addr:housenumber":"12",
    "addr:postcode":"24400",
    "addr:street":"Calle De General Gomez Nun\u0303Ez",
    "iso:country":"ES",
    "sg:address":"Calle de General Gomez Nu\u00d1ez, 12",
    "sg:city":"Ponferrada",
    "sg:orig_category":"Abogados",
    "sg:phone":"+34 987 42 71 13",
    "sg:postcode":"24400",
    "sg:province":"Le\u00f3n",
    "wof:name":"Maeso Nu\u00f1ez Juan",
    "wof:placetype":"venue"
},
  "geometry": {"coordinates":[-6.598968029,42.5494041443],"type":"Point"}
}