{
  "type": "Feature",
  "properties": {
    "iso:country":"ES",
    "sg:address":"Calle de San Juan De Dios, 4",
    "sg:city":"Villamartin",
    "sg:orig_category":"Mutuas De Seguros",
    "sg:phone":"+34 956 73 18 01",
    "sg:postcode":"11650",
    "sg:province":"C\u00e1diz",
    "wof:name":"Perea Acevedo Seguros S.l.",
    "wof:placetype":"venue"
},
  "geometry": {"coordinates":[-5.6412320137,36.8608131409],"type":"Point"}
}