{
  "type": "Feature",
  "properties": {
    "iso:country":"ES",
    "sg:address":"Calle de Herrero, 78",
    "sg:city":"Castellon",
    "sg:orig_category":"Guarder\u00cdas",
    "sg:phone":"+34 964 24 75 21",
    "sg:postcode":"12005",
    "sg:province":"Castell\u00f3n",
    "wof:name":"Bebe Sequiol S.l.l.",
    "wof:placetype":"venue"
},
  "geometry": {"coordinates":[-0.0432499982,39.976688385],"type":"Point"}
}