{
  "type": "Feature",
  "properties": {
    "iso:country":"ES",
    "sg:address":"Cami Ral, 389",
    "sg:city":"Mataro",
    "sg:orig_category":"Albergues",
    "sg:phone":"+34 937 96 30 08",
    "sg:postcode":"08301",
    "sg:province":"Barcelona",
    "wof:name":"Sasader S.l.",
    "wof:placetype":"venue"
},
  "geometry": {"coordinates":[2.4442958832,41.5369644165],"type":"Point"}
}