{
  "type": "Feature",
  "properties": {
    "iso:country":"ES",
    "sg:address":"Pase Ibiltokia, 3",
    "sg:city":"Plentzia",
    "sg:orig_category":"Consultor\u00cdas Diversas",
    "sg:phone":"+34 946 77 05 20",
    "sg:postcode":"48620",
    "sg:province":"Vizcaya",
    "wof:name":"Gisit S.l.",
    "wof:placetype":"venue"
},
  "geometry": {"coordinates":[-2.9496018887,43.4060287476],"type":"Point"}
}