{
  "type": "Feature",
  "properties": {
    "addr:full":"Calle de Tetuan, 51 Santander Cantabria 39004",
    "addr:housenumber":"51",
    "addr:postcode":"39004",
    "addr:street":"Calle De Tetuan",
    "iso:country":"ES",
    "sg:address":"Calle de Tetuan, 51",
    "sg:city":"Santander",
    "sg:orig_category":"Mec\u00c1nico Del Autom\u00d3vil",
    "sg:phone":"+34 942 27 12 94",
    "sg:postcode":"39004",
    "sg:province":"Cantabria",
    "wof:name":"Jaen Sanchez Domingo",
    "wof:placetype":"venue"
},
  "geometry": {"coordinates":[-3.7926468849,43.4661827087],"type":"Point"}
}