{
  "type": "Feature",
  "properties": {
    "addr:full":"Calle de Espronceda, 19 Puerto Valencia 46520",
    "addr:housenumber":"19",
    "addr:postcode":"46520",
    "addr:street":"Calle De Espronceda",
    "iso:country":"ES",
    "sg:address":"Calle de Espronceda, 19",
    "sg:city":"Puerto",
    "sg:orig_category":"Artes Gr\u00c1ficas, Artes Pl\u00c1sticas (curso)",
    "sg:phone":"+34 962 68 35 29",
    "sg:postcode":"46520",
    "sg:province":"Valencia",
    "wof:name":"Cuadrado Bayonas Alfonso",
    "wof:placetype":"venue"
},
  "geometry": {"coordinates":[-0.2156469971,39.6585006714],"type":"Point"}
}