{
  "type": "Feature",
  "properties": {
    "addr:full":"Carrer de Petrarca, 20 Barcelona Barcelona 08031",
    "addr:housenumber":"20",
    "addr:postcode":"08031",
    "addr:street":"Carrer De Petrarca",
    "iso:country":"ES",
    "sg:address":"Carrer de Petrarca, 20",
    "sg:city":"Barcelona",
    "sg:orig_category":"Fabricaci\u00d3n De Peines Y De Accesorios De Peluquer\u00cda",
    "sg:phone":"+34 934 29 13 41",
    "sg:postcode":"08031",
    "sg:province":"Barcelona",
    "wof:name":"Ricou Gimenez Jorge",
    "wof:placetype":"venue"
},
  "geometry": {"coordinates":[2.1659739017,41.4296112061],"type":"Point"}
}