{
  "type": "Feature",
  "properties": {
    "addr:full":"Calle de Alferez Fernandez Perez, 19 Alcaracejos C\u00f3rdoba 14480",
    "addr:housenumber":"19",
    "addr:postcode":"14480",
    "addr:street":"Calle De Alferez Fernandez Perez",
    "iso:country":"ES",
    "sg:address":"Calle de Alferez Fernandez Perez, 19",
    "sg:city":"Alcaracejos",
    "sg:classifiers":[
        {
            "category":"Taxi",
            "type":"Transportation"
        }
    ],
    "sg:phone":"+34 957 15 61 69",
    "sg:postcode":"14480",
    "sg:province":"C\u00f3rdoba",
    "wof:name":"Madrid Benitez Celedonio",
    "wof:placetype":"venue"
},
  "geometry": {"coordinates":[-4.9707512856,38.3869628906],"type":"Point"}
}