{
  "type": "Feature",
  "properties": {
    "iso:country":"ES",
    "sg:address":"Ctra Lerin, S/n",
    "sg:city":"Larraga",
    "sg:orig_category":"Carnicer\u00cdas, Carnicer\u00cdas",
    "sg:phone":"+34 948 71 12 25",
    "sg:postcode":"31251",
    "sg:province":"Navarra",
    "wof:name":"Suescun Villanueva Jose Alberto",
    "wof:placetype":"venue"
},
  "geometry": {"coordinates":[-1.8541070223,42.5530471802],"type":"Point"}
}