{
  "type": "Feature",
  "properties": {
    "iso:country":"ES",
    "sg:address":"Calle de Mendizabal, 15",
    "sg:city":"Chiclana De La Frontera",
    "sg:orig_category":"Zapatos (al Por Menor)",
    "sg:phone":"+34 956 53 83 54",
    "sg:postcode":"11130",
    "sg:province":"C\u00e1diz",
    "wof:name":"Torres Sanchez David",
    "wof:placetype":"venue"
},
  "geometry": {"coordinates":[-6.144536972,36.4226303101],"type":"Point"}
}