{
  "type": "Feature",
  "properties": {
    "addr:full":"Carrer de Relleu, S/n Benidorm Alicante 03500",
    "addr:housenumber":"s / n",
    "addr:postcode":"03500",
    "addr:street":"Carrer De Relleu",
    "iso:country":"ES",
    "sg:address":"Carrer de Relleu, S/n",
    "sg:city":"Benidorm",
    "sg:orig_category":"Ense\u00d1anza Variada",
    "sg:phone":"+34 965 86 32 85",
    "sg:postcode":"03500",
    "sg:province":"Alicante",
    "wof:name":"Menoyo Martin Gonzalo Angel",
    "wof:placetype":"venue"
},
  "geometry": {"coordinates":[-0.1328639984,38.546661377],"type":"Point"}
}