{
  "type": "Feature",
  "properties": {
    "addr:full":"Calle de Marcelino Del Valle, 3 Fuentesauco Zamora 49400",
    "addr:housenumber":"3",
    "addr:postcode":"49400",
    "addr:street":"Calle De Marcelino Del Valle;Zamora",
    "iso:country":"ES",
    "sg:address":"Calle de Marcelino Del Valle, 3",
    "sg:city":"Fuentesauco",
    "sg:orig_category":"Molduras, Junquillos, Listones Y Molduras Perforadas",
    "sg:phone":"+34 980 60 02 02",
    "sg:postcode":"49400",
    "sg:province":"Zamora",
    "wof:name":"Gonzalez Caballero Teresa",
    "wof:placetype":"venue"
},
  "geometry": {"coordinates":[-5.4974589348,41.2317390442],"type":"Point"}
}