{
  "type": "Feature",
  "properties": {
    "addr:full":"Calle de Magarza, 3 Tabaiba Media Santa Cruz De Tenerife 38190",
    "addr:housenumber":"3",
    "addr:postcode":"38190",
    "addr:street":"Calle De Magarza",
    "iso:country":"ES",
    "sg:address":"Calle de Magarza, 3",
    "sg:city":"Tabaiba Media",
    "sg:orig_category":"Artes Gr\u00c1ficas, Artes Pl\u00c1sticas: Material Y Suministros (al Por Menor)",
    "sg:phone":"+34 922 68 09 62",
    "sg:postcode":"38190",
    "sg:province":"Santa Cruz De Tenerife",
    "wof:name":"Lima Delgado Miguel",
    "wof:placetype":"venue"
},
  "geometry": {"coordinates":[-16.3397407532,28.4014110565],"type":"Point"}
}