{
  "type": "Feature",
  "properties": {
    "addr:full":"Avgd Pere Mas I Reus, 18 Platja D'alcudia Islas Baleares 07408",
    "addr:housenumber":"18",
    "addr:postcode":"07408",
    "addr:street":"Reus;D'Alcudia",
    "iso:country":"ES",
    "sg:address":"Avgd Pere Mas I Reus, 18",
    "sg:city":"Platja D'alcudia",
    "sg:orig_category":"Artesan\u00cda",
    "sg:phone":"+34 971 89 29 84",
    "sg:postcode":"07408",
    "sg:province":"Islas Baleares",
    "wof:name":"Salas Cuesta Jose Luis",
    "wof:placetype":"venue"
},
  "geometry": {"coordinates":[3.1255340576,39.8456192017],"type":"Point"}
}