{
  "type": "Feature",
  "properties": {
    "addr:full":"Calle de Jeronimo Mu\u00d1oz, 2 Valencia Valencia 46007",
    "addr:housenumber":"2",
    "addr:postcode":"46007",
    "addr:street":"Calle De Jeronimo Mun\u0303Oz",
    "iso:country":"ES",
    "sg:address":"Calle de Jeronimo Mu\u00d1oz, 2",
    "sg:city":"Valencia",
    "sg:orig_category":"Administradores De Bienes Y Delegados De Comunidades De Propietarios",
    "sg:phone":"+34 963 80 84 95",
    "sg:postcode":"46007",
    "sg:province":"Valencia",
    "wof:name":"Solanas Prats Adolfo",
    "wof:placetype":"venue"
},
  "geometry": {"coordinates":[-0.3881109953,39.4593887329],"type":"Point"}
}