{
  "type": "Feature",
  "properties": {
    "iso:country":"ES",
    "sg:address":"Pol Ind Urbayecla, S/n",
    "sg:city":"Yecla",
    "sg:orig_category":"Fabricaci\u00d3n De Taburetes, Sillas Y Sillones",
    "sg:phone":"+34 968 75 04 08",
    "sg:postcode":"30510",
    "sg:province":"Murcia",
    "wof:name":"Muebles Franju S.l.",
    "wof:placetype":"venue"
},
  "geometry": {"coordinates":[-1.1149940491,38.6145591736],"type":"Point"}
}