{
  "type": "Feature",
  "properties": {
    "iso:country":"ES",
    "sg:address":"Pase Conde De Sepulveda (del), 11",
    "sg:city":"Segovia",
    "sg:orig_category":"Venta, Instalaci\u00d3n De Calefacci\u00d3n",
    "sg:phone":"+34 921 43 81 27",
    "sg:postcode":"40002",
    "sg:province":"Segovia",
    "wof:name":"Pastor Galindo Jose Antonio",
    "wof:placetype":"venue"
},
  "geometry": {"coordinates":[-4.1170611382,40.9412269592],"type":"Point"}
}