{
  "type": "Feature",
  "properties": {
    "iso:country":"ES",
    "sg:address":"Calle de Ense\u00d1anza, 6",
    "sg:city":"Santander",
    "sg:orig_category":"Molduras, Junquillos, Listones Y Molduras Perforadas",
    "sg:phone":"+34 942 21 76 20",
    "sg:postcode":"39001",
    "sg:province":"Cantabria",
    "wof:name":"Sociedad Regional De Informatica S.a.",
    "wof:placetype":"venue"
},
  "geometry": {"coordinates":[-3.8104219437,43.4638519287],"type":"Point"}
}