{
  "type": "Feature",
  "properties": {
    "addr:full":"Av Gatassa, 69 Mataro Barcelona 08303",
    "addr:housenumber":"69",
    "addr:postcode":"08303",
    "addr:street":"Av Gatassa",
    "iso:country":"ES",
    "sg:address":"Av Gatassa, 69",
    "sg:city":"Mataro",
    "sg:orig_category":"Pescader\u00cdas (al Por Menor)",
    "sg:phone":"+34 937 99 25 00",
    "sg:postcode":"08303",
    "sg:province":"Barcelona",
    "wof:name":"Solis Guzman Antonio",
    "wof:placetype":"venue"
},
  "geometry": {"coordinates":[2.4279561043,41.537563324],"type":"Point"}
}