{
  "type": "Feature",
  "properties": {
    "iso:country":"ES",
    "sg:address":"Barr Can Negre, 133",
    "sg:city":"Can Negre",
    "sg:orig_category":"Suministros Para Hoteles",
    "sg:phone":"+34 971 31 31 16",
    "sg:postcode":"07819",
    "sg:province":"Islas Baleares",
    "wof:name":"Gasifred S.l.",
    "wof:placetype":"venue"
},
  "geometry": {"coordinates":[2.8577105999,39.5341796875],"type":"Point"}
}