{
  "type": "Feature",
  "properties": {
    "iso:country":"ES",
    "sg:address":"Ptge Mercader, 16",
    "sg:city":"Barcelona",
    "sg:orig_category":"Fabricaci\u00d3n De Muebles",
    "sg:phone":"+34 934 87 37 03",
    "sg:postcode":"08008",
    "sg:province":"Barcelona",
    "wof:name":"Jimenez Baladia Adriana",
    "wof:placetype":"venue"
},
  "geometry": {"coordinates":[2.1598920822,41.3923377991],"type":"Point"}
}