{
  "type": "Feature",
  "properties": {
    "iso:country":"ES",
    "sg:address":"Calle de Tara, S/n",
    "sg:city":"Cornisa Del Suroeste",
    "sg:orig_category":"Bazares, Art\u00cdculos De Limpieza Y De Cocina (al Por Menor)",
    "sg:phone":"+34 928 15 12 27",
    "sg:postcode":"35120",
    "sg:province":"Las Palmas",
    "wof:name":"Mirwani  Mohan Kishincchand",
    "wof:placetype":"venue"
},
  "geometry": {"coordinates":[-15.6830463409,27.7618026733],"type":"Point"}
}