{
  "type": "Feature",
  "properties": {
    "addr:full":"Avda Sanlucar, Km. 0002,0 Jerez De La Frontera C\u00e1diz 11408",
    "addr:postcode":"11408",
    "addr:street":"Avda Sanlucar;0002,0",
    "iso:country":"ES",
    "sg:address":"Avda Sanlucar, Km. 0002,0",
    "sg:city":"Jerez De La Frontera",
    "sg:orig_category":"Contenedores (mercanc\u00cdas)",
    "sg:phone":"+34 956 18 25 81",
    "sg:postcode":"11408",
    "sg:province":"C\u00e1diz",
    "wof:name":"Autos Valverde S.l.",
    "wof:placetype":"venue"
},
  "geometry": {"coordinates":[-6.150908947,36.6800117493],"type":"Point"}
}