{
  "type": "Feature",
  "properties": {
    "iso:country":"ES",
    "sg:address":"Calle de Goiko, 9",
    "sg:city":"Mundaka",
    "sg:orig_category":"Empresarios",
    "sg:phone":"+34 946 87 62 88",
    "sg:postcode":"48360",
    "sg:province":"Vizcaya",
    "wof:name":"Construcciones Aramburu S. A.",
    "wof:placetype":"venue"
},
  "geometry": {"coordinates":[-2.6989970207,43.4063682556],"type":"Point"}
}