{
  "type": "Feature",
  "properties": {
    "addr:full":"Calle de Protasio Gomez, 15 Madrid Madrid 28027",
    "addr:housenumber":"15",
    "addr:postcode":"madrid;28027",
    "addr:street":"Calle De Protasio Gomez",
    "iso:country":"ES",
    "sg:address":"Calle de Protasio Gomez, 15",
    "sg:city":"Madrid",
    "sg:orig_category":"Edici\u00d3n De Diarios, Revistas, Boletines",
    "sg:phone":"+34 917 42 51 13",
    "sg:postcode":"28027",
    "sg:province":"Madrid",
    "wof:name":"San Pablo Comunicacion Ssp",
    "wof:placetype":"venue"
},
  "geometry": {"coordinates":[-3.6372199059,40.4400100708],"type":"Point"}
}