{
  "type": "Feature",
  "properties": {
    "iso:country":"ES",
    "sg:address":"Carrer de Valldoreix, 10",
    "sg:city":"Barcelona",
    "sg:orig_category":"Centros Empresariales",
    "sg:phone":"+34 932 10 83 11",
    "sg:postcode":"08024",
    "sg:province":"Barcelona",
    "wof:name":"Marti Huertas Amanda",
    "wof:placetype":"venue"
},
  "geometry": {"coordinates":[2.1508889198,41.4097099304],"type":"Point"}
}