{
  "type": "Feature",
  "properties": {
    "addr:full":"Avda Marco (del), 8 Monterroso Lugo 27560",
    "addr:housenumber":"8",
    "addr:postcode":"27560",
    "addr:street":"Avda Marco Del",
    "iso:country":"ES",
    "sg:address":"Avda Marco (del), 8",
    "sg:city":"Monterroso",
    "sg:orig_category":"Contenedores (mercanc\u00cdas)",
    "sg:phone":"+34 982 37 72 70",
    "sg:postcode":"27560",
    "sg:province":"Lugo",
    "wof:name":"Seijas Vazquez Lisardo",
    "wof:placetype":"venue"
},
  "geometry": {"coordinates":[-7.8331432343,42.7930297852],"type":"Point"}
}