{
  "type": "Feature",
  "properties": {
    "addr:full":"Cmno Rincon, 7 Orihuela Alicante 03300",
    "addr:housenumber":"7",
    "addr:postcode":"03300",
    "addr:street":"Cmno Rincon",
    "iso:country":"ES",
    "sg:address":"Cmno Rincon, 7",
    "sg:city":"Orihuela",
    "sg:orig_category":"Promotores Constructores",
    "sg:phone":"+34 965 30 34 42",
    "sg:postcode":"03300",
    "sg:province":"Alicante",
    "wof:name":"Construcciones Y Promociones Mosgar, S.l.",
    "wof:placetype":"venue"
},
  "geometry": {"coordinates":[-0.9448040128,38.0817642212],"type":"Point"}
}