{
  "type": "Feature",
  "properties": {
    "iso:country":"ES",
    "sg:address":"Calle de San Cristobal, 3",
    "sg:city":"Belicena",
    "sg:orig_category":"Maquinaria Para Industrias Diversas",
    "sg:phone":"+34 958 44 50 90",
    "sg:postcode":"18193",
    "sg:province":"Granada",
    "wof:name":"Ortega Peinado Antonio",
    "wof:placetype":"venue"
},
  "geometry": {"coordinates":[-3.6940419674,37.17137146],"type":"Point"}
}