{
  "type": "Feature",
  "properties": {
    "addr:full":"Calle de Carretera Del Sas, S/n Candasnos Huesca 22591",
    "addr:postcode":"22591",
    "addr:street":"Calle De Carretera Del Sas S / N Candasnos",
    "iso:country":"ES",
    "sg:address":"Calle de Carretera Del Sas, S/n",
    "sg:city":"Candasnos",
    "sg:orig_category":"Cooperativas Agr\u00cdcolas",
    "sg:phone":"+34 974 34 51 07",
    "sg:postcode":"22591",
    "sg:province":"Huesca",
    "wof:name":"Cooperativa Agricola La Menorca",
    "wof:placetype":"venue"
},
  "geometry": {"coordinates":[0.0559938997,41.5012664795],"type":"Point"}
}