{
  "type": "Feature",
  "properties": {
    "iso:country":"ES",
    "sg:address":"Pg Gracia, 56",
    "sg:city":"Barcelona",
    "sg:orig_category":"Inmobiliaria (agencias)",
    "sg:phone":"+34 932 15 45 18",
    "sg:postcode":"08007",
    "sg:province":"Barcelona",
    "wof:name":"Testa Inmuebles En Renta S.a.",
    "wof:placetype":"venue"
},
  "geometry": {"coordinates":[2.1649599075,41.3925094604],"type":"Point"}
}