{
  "type": "Feature",
  "properties": {
    "addr:full":"Pl Esglesia, 3 Cornella Llobregat Barcelona 08940",
    "addr:housenumber":"3",
    "addr:postcode":"08940",
    "addr:street":"Pl Esglesia",
    "iso:country":"ES",
    "sg:address":"Pl Esglesia, 3",
    "sg:city":"Cornella Llobregat",
    "sg:orig_category":"M\u00c9dicos: Otorrinolaringolog\u00cda",
    "sg:phone":"+34 933 77 57 57",
    "sg:postcode":"08940",
    "sg:province":"Barcelona",
    "wof:name":"Mahfouz Zakhia Charbel",
    "wof:placetype":"venue"
},
  "geometry": {"coordinates":[2.070235014,41.3556365967],"type":"Point"}
}