{
  "type": "Feature",
  "properties": {
    "iso:country":"ES",
    "sg:address":"Avda Asturias, 1",
    "sg:city":"Valencia De Don Juan",
    "sg:orig_category":"Alimentaci\u00d3n General (al Por Menor)",
    "sg:phone":"+34 987 75 02 92",
    "sg:postcode":"24200",
    "sg:province":"Le\u00f3n",
    "wof:name":"Unipaco S. L.",
    "wof:placetype":"venue"
},
  "geometry": {"coordinates":[-5.5178570747,42.2905349731],"type":"Point"}
}