{
  "type": "Feature",
  "properties": {
    "addr:full":"Avda Cruz Roja (la), 15 Jerez De La Frontera C\u00e1diz 11407",
    "addr:postcode":"11407",
    "addr:street":"Avda Cruz Roja La",
    "iso:country":"ES",
    "sg:address":"Avda Cruz Roja (la), 15",
    "sg:city":"Jerez De La Frontera",
    "sg:orig_category":"Formaci\u00d3n Continuada (variada)",
    "sg:phone":"+34 956 18 71 65",
    "sg:postcode":"11407",
    "sg:province":"C\u00e1diz",
    "wof:name":"Hurtado Chacon Jose",
    "wof:placetype":"venue"
},
  "geometry": {"coordinates":[-6.1341910362,36.696937561],"type":"Point"}
}