{
  "type": "Feature",
  "properties": {
    "iso:country":"ES",
    "sg:address":"Calle de Conde De Lumiares, 15",
    "sg:city":"Valencia",
    "sg:orig_category":"Herboristas (al Por Menor)",
    "sg:phone":"+34 963 65 37 31",
    "sg:postcode":"46019",
    "sg:province":"Valencia",
    "wof:name":"Tarzona Gaona Jose Vicente",
    "wof:placetype":"venue"
},
  "geometry": {"coordinates":[-0.3721889853,39.4964790344],"type":"Point"}
}