{
  "type": "Feature",
  "properties": {
    "iso:country":"ES",
    "sg:address":"Calle de Jose Segura Torres, 2",
    "sg:city":"Corralejo",
    "sg:orig_category":"Centros Empresariales",
    "sg:phone":"+34 928 86 75 99",
    "sg:postcode":"35660",
    "sg:province":"Las Palmas",
    "wof:name":"Solvelair S.l.",
    "wof:placetype":"venue"
},
  "geometry": {"coordinates":[-13.8681907654,28.7387771606],"type":"Point"}
}