{
  "type": "Feature",
  "properties": {
    "iso:country":"ES",
    "sg:address":"Foro, 47",
    "sg:city":"Foro",
    "sg:orig_category":"Comerciantes Al Por Mayor De Vinos, Licores Y Alcoholes",
    "sg:phone":"+34 981 77 80 19",
    "sg:postcode":"15807",
    "sg:province":"La Coru\u00f1a",
    "wof:name":"Abella Cernadas Enrique",
    "wof:placetype":"venue"
},
  "geometry": {"coordinates":[-8.106071,43.047684],"type":"Point"}
}