{
  "type": "Feature",
  "properties": {
    "addr:full":"Calle de Vicente Morales, 2 Puebla De Azaba Salamanca 37553",
    "addr:housenumber":"2",
    "addr:postcode":"37553",
    "addr:street":"Calle De Vicente Morales",
    "iso:country":"ES",
    "sg:address":"Calle de Vicente Morales, 2",
    "sg:city":"Puebla De Azaba",
    "sg:orig_category":"Centros De Educaci\u00d3n Especial",
    "sg:phone":"+34 923 47 13 61",
    "sg:postcode":"37553",
    "sg:province":"Salamanca",
    "wof:name":"Colegio Rural Agrupado De Fuenteguinaldo",
    "wof:placetype":"venue"
},
  "geometry": {"coordinates":[-6.7449789047,40.4463615417],"type":"Point"}
}