{
  "type": "Feature",
  "properties": {
    "addr:full":"Plaz Garcia Moreno, 9 Orgiva Granada 18400",
    "addr:housenumber":"9",
    "addr:postcode":"18400",
    "addr:street":"Garcia Moreno",
    "iso:country":"ES",
    "sg:address":"Plaz Garcia Moreno, 9",
    "sg:city":"Orgiva",
    "sg:orig_category":"Art\u00cdculos De Regalo (al Por Menor)",
    "sg:phone":"+34 958 78 41 56",
    "sg:postcode":"18400",
    "sg:province":"Granada",
    "wof:name":"Jeramuza S.l.",
    "wof:placetype":"venue"
},
  "geometry": {"coordinates":[-3.4239137173,36.9008827209],"type":"Point"}
}