{
  "type": "Feature",
  "properties": {
    "addr:full":"Calle de Maestra Angeles Lorente, 17 Cazorla Ja\u00e9n 23470",
    "addr:housenumber":"17",
    "addr:postcode":"23470",
    "addr:street":"Calle De Maestra;Lorente",
    "iso:country":"ES",
    "sg:address":"Calle de Maestra Angeles Lorente, 17",
    "sg:city":"Cazorla",
    "sg:orig_category":"Arquitectos",
    "sg:phone":"+34 953 72 20 44",
    "sg:postcode":"23470",
    "sg:province":"Ja\u00e9n",
    "wof:name":"Caravaca Fortes Bernardino",
    "wof:placetype":"venue"
},
  "geometry": {"coordinates":[-3.0055301189,37.9141426086],"type":"Point"}
}