{
  "type": "Feature",
  "properties": {
    "iso:country":"ES",
    "sg:address":"Calle de Buiza Y Mensaque, 8",
    "sg:city":"Sevilla",
    "sg:orig_category":"Abogados",
    "sg:phone":"+34 954 22 43 48",
    "sg:postcode":"41004",
    "sg:province":"Sevilla",
    "wof:name":"De Gongora Macias Francisco",
    "wof:placetype":"venue"
},
  "geometry": {"coordinates":[-5.9927415848,37.391456604],"type":"Point"}
}