{
  "type": "Feature",
  "properties": {
    "addr:full":"Carr Casteth, 10 Vielha Lleida 25530",
    "addr:housenumber":"10",
    "addr:postcode":"25530",
    "addr:street":"Carr Casteth",
    "iso:country":"ES",
    "sg:address":"Carr Casteth, 10",
    "sg:city":"Vielha",
    "sg:orig_category":"Distribuci\u00d3n De Petr\u00d3leo Y Derivados",
    "sg:phone":"+34 973 64 17 55",
    "sg:postcode":"25530",
    "sg:province":"Lleida",
    "wof:name":"Pescados Navarro E Hijos S.l.",
    "wof:placetype":"venue"
},
  "geometry": {"coordinates":[0.7921620011,42.7028923035],"type":"Point"}
}