{
  "type": "Feature",
  "properties": {
    "addr:full":"Avda Pe\u00d1a Prieta, 55 Madrid Madrid 28038",
    "addr:housenumber":"55",
    "addr:postcode":"madrid;28038",
    "addr:street":"Avda Pen\u0303A Prieta",
    "iso:country":"ES",
    "sg:address":"Avda Pe\u00d1a Prieta, 55",
    "sg:city":"Madrid",
    "sg:orig_category":"M\u00c1quinas De Escribir, M\u00c1quinas De Oficina (al Por Menor, Reparaci\u00d3n)",
    "sg:phone":"+34 915 01 67 53",
    "sg:postcode":"28038",
    "sg:province":"Madrid",
    "wof:name":"Suministros Y Maquinas De Oficina S.a.",
    "wof:placetype":"venue"
},
  "geometry": {"coordinates":[-3.6645050049,40.4022865295],"type":"Point"}
}