{
  "type": "Feature",
  "properties": {
    "iso:country":"ES",
    "sg:address":"Apolo, 41",
    "sg:city":"Estepona",
    "sg:orig_category":"Pescader\u00cdas (al Por Menor)",
    "sg:phone":"+34 952 88 20 91",
    "sg:postcode":"29680",
    "sg:province":"M\u00e1laga",
    "wof:name":"Villalon Lozano Olivia",
    "wof:placetype":"venue"
},
  "geometry": {"coordinates":[-5.0530991554,36.4622840881],"type":"Point"}
}