{
  "type": "Feature",
  "properties": {
    "iso:country":"ES",
    "sg:address":"Carr Sta Joaquima Vedruna, 15",
    "sg:city":"Igualada",
    "sg:orig_category":"M\u00c9dicos: Medicina Interna",
    "sg:phone":"+34 938 05 46 52",
    "sg:postcode":"08700",
    "sg:province":"Barcelona",
    "wof:name":"Sangenis Biosca Francisco",
    "wof:placetype":"venue"
},
  "geometry": {"coordinates":[1.6247650385,41.5775680542],"type":"Point"}
}