{
  "type": "Feature",
  "properties": {
    "addr:full":"Calle de La Peza, S/n Albolote Granada 18220",
    "addr:housenumber":"s / n",
    "addr:postcode":"18220",
    "addr:street":"Calle De La Peza",
    "iso:country":"ES",
    "sg:address":"Calle de La Peza, S/n",
    "sg:city":"Albolote",
    "sg:orig_category":"Sales (al Por Mayor)",
    "sg:phone":"+34 958 43 02 86",
    "sg:postcode":"18220",
    "sg:province":"Granada",
    "wof:name":"Montalban Cano Ambrosio",
    "wof:placetype":"venue"
},
  "geometry": {"coordinates":[-3.6379239559,37.2225646973],"type":"Point"}
}