{
  "type": "Feature",
  "properties": {
    "iso:country":"ES",
    "sg:address":"Carrer de General Llauder, 40",
    "sg:city":"Argentona",
    "sg:orig_category":"Rectificaci\u00d3n, Mecanizado, Fresado",
    "sg:phone":"+34 937 56 13 04",
    "sg:postcode":"08310",
    "sg:province":"Barcelona",
    "wof:name":"Tedimec Argentona S.l.",
    "wof:placetype":"venue"
},
  "geometry": {"coordinates":[2.4035561085,41.5558509827],"type":"Point"}
}