{
  "type": "Feature",
  "properties": {
    "addr:full":"Calle de Prim, 6 Carmona Sevilla 41410",
    "addr:housenumber":"6",
    "addr:postcode":"41410",
    "addr:street":"Calle De Prim",
    "iso:country":"ES",
    "sg:address":"Calle de Prim, 6",
    "sg:city":"Carmona",
    "sg:orig_category":"Agencias Y Agentes Comerciales, Representantes",
    "sg:phone":"+34 954 19 01 26",
    "sg:postcode":"41410",
    "sg:province":"Sevilla",
    "wof:name":"Eveho Viviendas S.l.u.",
    "wof:placetype":"venue"
},
  "geometry": {"coordinates":[-5.6388697624,37.4721031189],"type":"Point"}
}