{
  "type": "Feature",
  "properties": {
    "addr:full":"Pla\u00c7 Abeurador, 12 Santa Margalida Islas Baleares 07450",
    "addr:housenumber":"12",
    "addr:postcode":"07450",
    "addr:street":"Abeurador",
    "iso:country":"ES",
    "sg:address":"Pla\u00c7 Abeurador, 12",
    "sg:city":"Santa Margalida",
    "sg:orig_category":"Inform\u00c1tica: Material Y Suministros",
    "sg:phone":"+34 971 52 38 34",
    "sg:postcode":"07450",
    "sg:province":"Islas Baleares",
    "wof:name":"Cinal Gestion E Informatica S.l.",
    "wof:placetype":"venue"
},
  "geometry": {"coordinates":[3.1060860157,39.7048683167],"type":"Point"}
}