{
  "type": "Feature",
  "properties": {
    "addr:full":"Plaz Rey, S/n Madrid Madrid 28004",
    "addr:housenumber":"s / n",
    "addr:postcode":"28004",
    "addr:street":"Plaz Rey",
    "iso:country":"ES",
    "sg:address":"Plaz Rey, S/n",
    "sg:city":"Madrid",
    "sg:orig_category":"Aparcamientos (infraestructuras, Accesorios)",
    "sg:phone":"+34 915 22 52 19",
    "sg:postcode":"28004",
    "sg:province":"Madrid",
    "wof:name":"Aparcamientos Plaza Del Rey S. A.",
    "wof:placetype":"venue"
},
  "geometry": {"coordinates":[-3.6963131428,40.4200286865],"type":"Point"}
}