{
  "type": "Feature",
  "properties": {
    "addr:full":"Calle de Nuestra Se\u00d1ora De La Visitacion, S/n San Bartolome Pinares \u00c1vila 05267",
    "addr:housenumber":"s / n",
    "addr:postcode":"05267",
    "addr:street":"Calle De Nuestra Sen\u0303Ora De La Visitacion;A\u0301Vila",
    "iso:country":"ES",
    "sg:address":"Calle de Nuestra Se\u00d1ora De La Visitacion, S/n",
    "sg:city":"San Bartolome Pinares",
    "sg:orig_category":"Promotores Constructores",
    "sg:phone":"+34 920 27 01 83",
    "sg:postcode":"05267",
    "sg:province":"\u00c1vila",
    "wof:name":"Herrero Cea Vicente",
    "wof:placetype":"venue"
},
  "geometry": {"coordinates":[-4.5399551392,40.5433006287],"type":"Point"}
}