{
  "type": "Feature",
  "properties": {
    "addr:full":"Calle de Alfonso V, 2 Le\u00f3n Le\u00f3n 24001",
    "addr:housenumber":"2",
    "addr:postcode":"24001",
    "addr:street":"Calle De Alfonso V;Leo\u0301N",
    "iso:country":"ES",
    "sg:address":"Calle de Alfonso V, 2",
    "sg:city":"Le\u00f3n",
    "sg:orig_category":"Centros M\u00c9dicos Y Sociales, Dispensarios",
    "sg:phone":"+34 987 22 59 00",
    "sg:postcode":"24001",
    "sg:province":"Le\u00f3n",
    "wof:name":"Revuelta Prieto Fulgencio",
    "wof:placetype":"venue"
},
  "geometry": {"coordinates":[-5.5739207268,42.597618103],"type":"Point"}
}