{
  "type": "Feature",
  "properties": {
    "iso:country":"ES",
    "sg:address":"Calle de Madrid, 5",
    "sg:city":"Castellon",
    "sg:orig_category":"Impuestos, Tesoro P\u00dablico",
    "sg:phone":"+34 964 23 97 87",
    "sg:postcode":"12003",
    "sg:province":"Castell\u00f3n",
    "wof:name":"Soler Monfort Juan",
    "wof:placetype":"venue"
},
  "geometry": {"coordinates":[-0.032974001,39.9882698059],"type":"Point"}
}