{
  "type": "Feature",
  "properties": {
    "iso:country":"ES",
    "sg:address":"Plaza Lopez Pando, 12",
    "sg:city":"Berlanga Duero",
    "sg:orig_category":"Reposter\u00cdas",
    "sg:phone":"+34 975 34 31 93",
    "sg:postcode":"42360",
    "sg:province":"Soria",
    "wof:name":"Escolano Benito Jesus",
    "wof:placetype":"venue"
},
  "geometry": {"coordinates":[-2.8604838848,41.4645309448],"type":"Point"}
}