{
  "type": "Feature",
  "properties": {
    "iso:country":"ES",
    "sg:address":"Pase Pintor Martinez Vazquez, 10",
    "sg:city":"Arenas San Pedro",
    "sg:classifiers":[
        {
            "category":"Autos & Motor Vehicles",
            "subcategory":"Automobile Sales",
            "type":"Retail Goods"
        }
    ],
    "sg:phone":"+34 920 37 08 54",
    "sg:postcode":"05400",
    "sg:province":"\u00c1vila",
    "wof:name":"Auto Escuela Seguridad Vial Tietar S.l",
    "wof:placetype":"venue"
},
  "geometry": {"coordinates":[-4.8708963394,40.8006896973],"type":"Point"}
}