{
  "type": "Feature",
  "properties": {
    "iso:country":"ES",
    "sg:address":"Calle de Granada, 24",
    "sg:city":"Malaga",
    "sg:orig_category":"Ropa Para Se\u00d1oras Y Caballeros (al Por Menor)",
    "sg:phone":"+34 952 21 12 38",
    "sg:postcode":"29015",
    "sg:province":"M\u00e1laga",
    "wof:name":"Piper  Felix Kent",
    "wof:placetype":"venue"
},
  "geometry": {"coordinates":[-4.4205784798,36.7217559814],"type":"Point"}
}