{
  "type": "Feature",
  "properties": {
    "iso:country":"ES",
    "sg:address":"Rua Cabeza De Vaca, 5",
    "sg:city":"Ourense",
    "sg:orig_category":"Carnicer\u00cdas, Carnicer\u00cdas",
    "sg:phone":"+34 988 22 70 30",
    "sg:postcode":"32002",
    "sg:province":"Ourense",
    "wof:name":"Calvi\u00f1o Lamas Jose",
    "wof:placetype":"venue"
},
  "geometry": {"coordinates":[-7.8795590401,42.3276901245],"type":"Point"}
}