{
  "type": "Feature",
  "properties": {
    "addr:full":"Carr Major, 69 Gandia Valencia 46700",
    "addr:housenumber":"69",
    "addr:postcode":"46700",
    "addr:street":"Carr Major;Valencia",
    "iso:country":"ES",
    "sg:address":"Carr Major, 69",
    "sg:city":"Gandia",
    "sg:orig_category":"Abogados",
    "sg:phone":"+34 962 87 29 77",
    "sg:postcode":"46700",
    "sg:province":"Valencia",
    "wof:name":"Perez Escriba Jose Luis",
    "wof:placetype":"venue"
},
  "geometry": {"coordinates":[-0.1913339943,38.960735321],"type":"Point"}
}