{
  "type": "Feature",
  "properties": {
    "iso:country":"ES",
    "sg:address":"Rua Joaquin Loriga, 24",
    "sg:city":"Lalin",
    "sg:orig_category":"Confecci\u00d3n (fabricaci\u00d3n, Al Por Mayor)",
    "sg:phone":"+34 986 78 32 21",
    "sg:postcode":"36500",
    "sg:province":"Pontevedra",
    "wof:name":"Cangas Conde Luis Emilio",
    "wof:placetype":"venue"
},
  "geometry": {"coordinates":[-8.1124219894,42.660320282],"type":"Point"}
}