{
  "type": "Feature",
  "properties": {
    "addr:full":"Pase Ribeira, 5 Rianxo La Coru\u00f1a 15920",
    "addr:housenumber":"5",
    "addr:postcode":"15920",
    "addr:street":"Ribeira;La Corun\u0303A",
    "iso:country":"ES",
    "sg:address":"Pase Ribeira, 5",
    "sg:city":"Rianxo",
    "sg:orig_category":"Molduras, Junquillos, Listones Y Molduras Perforadas",
    "sg:phone":"+34 981 86 61 02",
    "sg:postcode":"15920",
    "sg:province":"La Coru\u00f1a",
    "wof:name":"Paola Figueroa Pati\u00f1o E Outros S.l.",
    "wof:placetype":"venue"
},
  "geometry": {"coordinates":[-8.8172187805,42.6528091431],"type":"Point"}
}