{
  "type": "Feature",
  "properties": {
    "addr:full":"Calle de Prados (los), 12 Bembibre Le\u00f3n 24300",
    "addr:postcode":"24300",
    "addr:street":"Calle De Prados Los;Leo\u0301N",
    "iso:country":"ES",
    "sg:address":"Calle de Prados (los), 12",
    "sg:city":"Bembibre",
    "sg:orig_category":"Lavado, Limpieza De Veh\u00cdculos",
    "sg:phone":"+34 987 51 30 88",
    "sg:postcode":"24300",
    "sg:province":"Le\u00f3n",
    "wof:name":"Lombao Veiga Pedro",
    "wof:placetype":"venue"
},
  "geometry": {"coordinates":[-6.4139242172,42.6159744263],"type":"Point"}
}