{
  "type": "Feature",
  "properties": {
    "addr:full":"Zaldizurreta Kalea, 13 Beasain Guip\u00f9zcoa 20200",
    "addr:housenumber":"13",
    "addr:postcode":"20200",
    "addr:street":"Zaldizurreta Kalea;Guipu\u0300Zcoa",
    "iso:country":"ES",
    "sg:address":"Zaldizurreta Kalea, 13",
    "sg:city":"Beasain",
    "sg:orig_category":"Empresas De Demolici\u00d3n",
    "sg:phone":"+34 943 02 84 10",
    "sg:postcode":"20200",
    "sg:province":"Guip\u00f9zcoa",
    "wof:name":"Pedro Echepare S.l.",
    "wof:placetype":"venue"
},
  "geometry": {"coordinates":[-2.194781065,43.0463523865],"type":"Point"}
}