{
  "type": "Feature",
  "properties": {
    "iso:country":"ES",
    "sg:address":"Calle de Doctor Barraquer, 20",
    "sg:city":"Getafe",
    "sg:orig_category":"Muebles Y Accesorios Para Cocinas Y Cuartos De Ba\u00d1o (al Por Menor)",
    "sg:phone":"+34 916 95 79 79",
    "sg:postcode":"28903",
    "sg:province":"Madrid",
    "wof:name":"Rebolledo Vicente Eduardo",
    "wof:placetype":"venue"
},
  "geometry": {"coordinates":[-3.7205286026,40.3154258728],"type":"Point"}
}