{
  "type": "Feature",
  "properties": {
    "addr:full":"Carrer de Eugeni D'ors, 26 S. Fruitos Bages Barcelona 08272",
    "addr:housenumber":"26",
    "addr:postcode":"08272",
    "addr:street":"Carrer De Eugeni D'Ors;S. Fruitos Bages Barcelona",
    "iso:country":"ES",
    "sg:address":"Carrer de Eugeni D'ors, 26",
    "sg:city":"S. Fruitos Bages",
    "sg:orig_category":"Bisuter\u00cda, Joyer\u00cda, Relojer\u00cda (al Por Menor)",
    "sg:phone":"+34 938 76 09 03",
    "sg:postcode":"08272",
    "sg:province":"Barcelona",
    "wof:name":"Fons Martin Monica",
    "wof:placetype":"venue"
},
  "geometry": {"coordinates":[1.8217660189,41.7293052673],"type":"Point"}
}