{
  "type": "Feature",
  "properties": {
    "addr:full":"Rua Rio Tamega, 32 Ourense Ourense 32001",
    "addr:housenumber":"32",
    "addr:postcode":"32001",
    "addr:street":"Rua;Tamega",
    "iso:country":"ES",
    "sg:address":"Rua Rio Tamega, 32",
    "sg:city":"Ourense",
    "sg:orig_category":"Carnicer\u00cdas, Carnicer\u00cdas",
    "sg:phone":"+34 988 21 53 60",
    "sg:postcode":"32001",
    "sg:province":"Ourense",
    "wof:name":"Vazquez Rodriguez David Jose",
    "wof:placetype":"venue"
},
  "geometry": {"coordinates":[-7.8661079407,42.3530158997],"type":"Point"}
}