{
  "type": "Feature",
  "properties": {
    "addr:full":"Avda Juan Carlos I, 36 Traiguera Castell\u00f3n 12330",
    "addr:housenumber":"36",
    "addr:postcode":"12330",
    "addr:street":"Avda Juan Carlos I;Castello\u0301N",
    "iso:country":"ES",
    "sg:address":"Avda Juan Carlos I, 36",
    "sg:city":"Traiguera",
    "sg:orig_category":"Centros De Educaci\u00d3n Especial",
    "sg:phone":"+34 964 49 50 79",
    "sg:postcode":"12330",
    "sg:province":"Castell\u00f3n",
    "wof:name":"Generalitat Valenciana",
    "wof:placetype":"venue"
},
  "geometry": {"coordinates":[0.2892799973,40.5237693787],"type":"Point"}
}