{
  "type": "Feature",
  "properties": {
    "iso:country":"ES",
    "sg:address":"Sect A, 54",
    "sg:city":"Torre De La Higuera O Matalasca\u00e7as",
    "sg:orig_category":"Molduras, Junquillos, Listones Y Molduras Perforadas",
    "sg:phone":"+34 959 43 04 44",
    "sg:postcode":"21760",
    "sg:province":"Huelva",
    "wof:name":"Galan Gil Juan",
    "wof:placetype":"venue"
},
  "geometry": {"coordinates":[-6.9495940208,37.256313324],"type":"Point"}
}