{
  "type": "Feature",
  "properties": {
    "iso:country":"ES",
    "sg:address":"Calle de Tetuan, 19",
    "sg:city":"Sevilla",
    "sg:orig_category":"Abogados",
    "sg:phone":"+34 954 22 63 78",
    "sg:postcode":"41001",
    "sg:province":"Sevilla",
    "wof:name":"Troncoso Gonzalez Pilar",
    "wof:placetype":"venue"
},
  "geometry": {"coordinates":[-5.9950890541,37.3899116516],"type":"Point"}
}