{
  "type": "Feature",
  "properties": {
    "iso:country":"ES",
    "sg:address":"Carrer de Pomaret, 6",
    "sg:city":"Barcelona",
    "sg:orig_category":"Asilos De Ancianos. Centros Privados",
    "sg:phone":"+34 932 05 07 11",
    "sg:postcode":"08017",
    "sg:province":"Barcelona",
    "wof:name":"Aaf Mas Dca S.l.",
    "wof:placetype":"venue"
},
  "geometry": {"coordinates":[2.125369,41.402779],"type":"Point"}
}