{
  "type": "Feature",
  "properties": {
    "iso:country":"ES",
    "sg:address":"Plaz Conde De Casal, 6",
    "sg:city":"Madrid",
    "sg:classifiers":[
        {
            "category":"Casinos & Gambling",
            "type":"Entertainment"
        }
    ],
    "sg:phone":"+34 915 01 04 48",
    "sg:postcode":"28007",
    "sg:province":"Madrid",
    "sg:tags":[
        "locale",
        "de",
        "juego"
    ],
    "wof:name":"Telefono Publico Del Sur S. L.",
    "wof:placetype":"venue"
},
  "geometry": {"coordinates":[-3.6695270538,40.4063682556],"type":"Point"}
}