{
  "type": "Feature",
  "properties": {
    "addr:full":"Carrer de Gran De Gracia, 15 Barcelona Barcelona 08012",
    "addr:housenumber":"15",
    "addr:postcode":"08012",
    "addr:street":"Carrer De Gran De Gracia",
    "iso:country":"ES",
    "sg:address":"Carrer de Gran De Gracia, 15",
    "sg:city":"Barcelona",
    "sg:orig_category":"Panader\u00cdas, Panader\u00cdas",
    "sg:phone":"+34 932 17 27 44",
    "sg:postcode":"08012",
    "sg:province":"Barcelona",
    "wof:name":"Roig Rovira Maria",
    "wof:placetype":"venue"
},
  "geometry": {"coordinates":[2.1570580006,41.3982124329],"type":"Point"}
}