{
  "type": "Feature",
  "properties": {
    "addr:full":"Calle de Pedro Romero Mendoza, 4 Caceres C\u00e1ceres 10004",
    "addr:housenumber":"4",
    "addr:postcode":"10004",
    "addr:street":"Calle De Pedro Romero Mendoza;Ca\u0301Ceres",
    "iso:country":"ES",
    "sg:address":"Calle de Pedro Romero Mendoza, 4",
    "sg:city":"Caceres",
    "sg:orig_category":"Molduras, Junquillos, Listones Y Molduras Perforadas",
    "sg:phone":"+34 927 18 07 90",
    "sg:postcode":"10004",
    "sg:province":"C\u00e1ceres",
    "wof:name":"Gonzalez Moreno Miguel",
    "wof:placetype":"venue"
},
  "geometry": {"coordinates":[-6.3668060303,39.4850654602],"type":"Point"}
}