{
  "type": "Feature",
  "properties": {
    "addr:full":"Calle de Sirio, 8 Madrid Madrid 28007",
    "addr:housenumber":"8",
    "addr:postcode":"madrid;28007",
    "addr:street":"Calle De Sirio",
    "iso:country":"ES",
    "sg:address":"Calle de Sirio, 8",
    "sg:city":"Madrid",
    "sg:orig_category":"Tintes (fabricaci\u00d3n, Al Por Mayor)",
    "sg:phone":"+34 915 04 63 32",
    "sg:postcode":"28007",
    "sg:province":"Madrid",
    "wof:name":"Lopez Ramirez Jose Manuel",
    "wof:placetype":"venue"
},
  "geometry": {"coordinates":[-3.6669390202,40.4071273804],"type":"Point"}
}