{
  "type": "Feature",
  "properties": {
    "iso:country":"ES",
    "sg:address":"Rbla Rei En Jaume, 2",
    "sg:city":"Manacor",
    "sg:orig_category":"Sociedades, Compa\u00d1\u00cdas Aseguradoras",
    "sg:phone":"+34 971 55 96 99",
    "sg:postcode":"07500",
    "sg:province":"Islas Baleares",
    "wof:name":"De Vuit A Ocho S.l.",
    "wof:placetype":"venue"
},
  "geometry": {"coordinates":[3.2095360756,39.5681495667],"type":"Point"}
}