{
  "type": "Feature",
  "properties": {
    "addr:full":"Carrer de Felip Ii, 293 Barcelona Barcelona 08016",
    "addr:housenumber":"293",
    "addr:postcode":"08016",
    "addr:street":"Carrer De Felip Ii",
    "iso:country":"ES",
    "sg:address":"Carrer de Felip Ii, 293",
    "sg:city":"Barcelona",
    "sg:orig_category":"Consultas M\u00c9dicas",
    "sg:phone":"+34 933 49 10 42",
    "sg:postcode":"08016",
    "sg:province":"Barcelona",
    "wof:name":"Centro Reconocimiento Medico Carnet De Conducir S. A.",
    "wof:placetype":"venue"
},
  "geometry": {"coordinates":[2.1751430035,41.4293670654],"type":"Point"}
}