{
  "type": "Feature",
  "properties": {
    "iso:country":"ES",
    "sg:address":"Av Pau, De La, S/n",
    "sg:city":"Eivissa",
    "sg:orig_category":"Piscinas (establecimientos)",
    "sg:phone":"+34 971 31 21 00",
    "sg:postcode":"07800",
    "sg:province":"Islas Baleares",
    "wof:name":"Asociacion Club Natacion Eivissa",
    "wof:placetype":"venue"
},
  "geometry": {"coordinates":[1.4268145561,38.9151802063],"type":"Point"}
}