{
  "type": "Feature",
  "properties": {
    "addr:full":"Calle de Uruguay, 17 Palmas De Gran Canaria Las Palmas 35007",
    "addr:housenumber":"17",
    "addr:postcode":"35007",
    "addr:street":"Calle De Uruguay",
    "iso:country":"ES",
    "sg:address":"Calle de Uruguay, 17",
    "sg:city":"Palmas De Gran Canaria",
    "sg:orig_category":"Pintura, Barniz, Productos Asimilables (fabricaci\u00d3n, Al Por Mayor)",
    "sg:phone":"+34 928 26 12 58",
    "sg:postcode":"35007",
    "sg:province":"Las Palmas",
    "wof:name":"Pinturas Y Decoracion Morera S.l.",
    "wof:placetype":"venue"
},
  "geometry": {"coordinates":[-15.4327688217,28.1371517181],"type":"Point"}
}