{
  "type": "Feature",
  "properties": {
    "addr:full":"Urb Residencial Acquapark, 35 Torrevieja Alicante 03180",
    "addr:housenumber":"35",
    "addr:postcode":"03180",
    "addr:street":"Urb",
    "iso:country":"ES",
    "sg:address":"Urb Residencial Acquapark, 35",
    "sg:city":"Torrevieja",
    "sg:orig_category":"Cl\u00cdnicas Dentales",
    "sg:phone":"+34 965 70 85 76",
    "sg:postcode":"03180",
    "sg:province":"Alicante",
    "wof:name":"Tarta  Dan",
    "wof:placetype":"venue"
},
  "geometry": {"coordinates":[-0.6536790133,38.0173606873],"type":"Point"}
}