{
  "type": "Feature",
  "properties": {
    "addr:full":"Avda Menendez Pelayo, 7 Sevilla Sevilla 41003",
    "addr:housenumber":"7",
    "addr:postcode":"41003",
    "addr:street":"Avda Menendez Pelayo",
    "iso:country":"ES",
    "sg:address":"Avda Menendez Pelayo, 7",
    "sg:city":"Sevilla",
    "sg:orig_category":"Asesor\u00cda Fiscal Y Jur\u00cddica",
    "sg:phone":"+34 954 42 42 12",
    "sg:postcode":"41003",
    "sg:province":"Sevilla",
    "wof:name":"Soralpe I Mas P Asociados S.l.",
    "wof:placetype":"venue"
},
  "geometry": {"coordinates":[-5.9853987694,37.3869018555],"type":"Point"}
}