{
  "type": "Feature",
  "properties": {
    "iso:country":"ES",
    "sg:address":"Calle de Parroco Deniz, 2",
    "sg:city":"Cardones",
    "sg:orig_category":"Molduras, Junquillos, Listones Y Molduras Perforadas",
    "sg:phone":"+34 928 60 06 62",
    "sg:postcode":"35400",
    "sg:province":"Las Palmas",
    "wof:name":"Suarez Rodriguez Maria Fernanda",
    "wof:placetype":"venue"
},
  "geometry": {"coordinates":[-15.5088100433,28.1287612915],"type":"Point"}
}