{
  "type": "Feature",
  "properties": {
    "iso:country":"ES",
    "sg:address":"Calle de Principe De Vergara, 16",
    "sg:city":"Madrid",
    "sg:orig_category":"Confiter\u00cdas, Chocolater\u00cdas (al Por Menor)",
    "sg:phone":"+34 915 77 07 81",
    "sg:postcode":"28001",
    "sg:province":"Madrid",
    "wof:name":"Asaqui S.l.",
    "wof:placetype":"venue"
},
  "geometry": {"coordinates":[-3.6801168919,40.4247627258],"type":"Point"}
}