{
  "type": "Feature",
  "properties": {
    "iso:country":"ES",
    "sg:address":"Avda Padre Isla, 42",
    "sg:city":"Le\u00f3n",
    "sg:orig_category":"Arquitectos",
    "sg:phone":"+34 987 22 55 08",
    "sg:postcode":"24002",
    "sg:province":"Le\u00f3n",
    "wof:name":"Vicente Herranz Pablo",
    "wof:placetype":"venue"
},
  "geometry": {"coordinates":[-5.574242115,42.6011962891],"type":"Point"}
}