{
  "type": "Feature",
  "properties": {
    "iso:country":"ES",
    "sg:address":"Calle de Madridejos, 34",
    "sg:city":"Madrid",
    "sg:orig_category":"Internados & Ense\u00d1anza Privada",
    "sg:phone":"+34 914 75 31 46",
    "sg:postcode":"28026",
    "sg:province":"Madrid",
    "wof:name":"Colegio Luz Casanova",
    "wof:placetype":"venue"
},
  "geometry": {"coordinates":[-3.7101089954,40.3845252991],"type":"Point"}
}