{
  "type": "Feature",
  "properties": {
    "iso:country":"ES",
    "sg:address":"Calle de Olaguibel, 68",
    "sg:city":"Vitoria-gasteiz",
    "sg:orig_category":"Librer\u00cdas",
    "sg:phone":"+34 945 28 99 95",
    "sg:postcode":"01003",
    "sg:province":"\u00c1lava",
    "wof:name":"Gomez Del Campo Lucas",
    "wof:placetype":"venue"
},
  "geometry": {"coordinates":[-2.6615240574,42.8452835083],"type":"Point"}
}