{
  "type": "Feature",
  "properties": {
    "iso:country":"ES",
    "sg:address":"Calle de San Pascual Bailon, 10",
    "sg:city":"Massamagrell",
    "sg:orig_category":"Guarder\u00cdas",
    "sg:phone":"+34 961 44 25 53",
    "sg:postcode":"46130",
    "sg:province":"Valencia",
    "wof:name":"Terciarias Capuchinas De La Sagrada Familia",
    "wof:placetype":"venue"
},
  "geometry": {"coordinates":[-0.3435820043,39.5791702271],"type":"Point"}
}