{
  "type": "Feature",
  "properties": {
    "addr:full":"Avda Espa\u00d1a (de), 17 Alcobendas Madrid 28100",
    "addr:housenumber":"17",
    "addr:postcode":"28100",
    "addr:street":"Avda Espan\u0303A De",
    "iso:country":"ES",
    "sg:address":"Avda Espa\u00d1a (de), 17",
    "sg:city":"Alcobendas",
    "sg:orig_category":"Inmobiliaria (agencias)",
    "sg:phone":"+34 916 51 45 48",
    "sg:postcode":"28100",
    "sg:province":"Madrid",
    "wof:name":"Zeugma Inversiones S.l",
    "wof:placetype":"venue"
},
  "geometry": {"coordinates":[-3.6332862377,40.5452079773],"type":"Point"}
}