{
  "type": "Feature",
  "properties": {
    "addr:full":"Carrer de Major, 25 Maslloren\u00e7 Tarragona 43718",
    "addr:housenumber":"25",
    "addr:postcode":"43718",
    "addr:street":"Carrer De Major",
    "iso:country":"ES",
    "sg:address":"Carrer de Major, 25",
    "sg:city":"Maslloren\u00e7",
    "sg:orig_category":"Panader\u00cdas, Panader\u00cdas",
    "sg:phone":"+34 977 62 84 28",
    "sg:postcode":"43718",
    "sg:province":"Tarragona",
    "wof:name":"Forn De Pa I Pastisseria Ca L'hereuet",
    "wof:placetype":"venue"
},
  "geometry": {"coordinates":[1.4154089689,41.269821167],"type":"Point"}
}