{
  "type": "Feature",
  "properties": {
    "iso:country":"ES",
    "sg:address":"Calle de Isaac Peral, 1",
    "sg:city":"Linares",
    "sg:orig_category":"Farmacias",
    "sg:phone":"+34 953 69 19 53",
    "sg:postcode":"23700",
    "sg:province":"Ja\u00e9n",
    "wof:name":"Ayas Lomas Maria Dolores",
    "wof:placetype":"venue"
},
  "geometry": {"coordinates":[-3.6333141327,38.095790863],"type":"Point"}
}