{
  "type": "Feature",
  "properties": {
    "addr:full":"Pl Clave, 6 Rubi Barcelona 08191",
    "addr:housenumber":"6",
    "addr:postcode":"08191",
    "addr:street":"Pl Clave",
    "iso:country":"ES",
    "sg:address":"Pl Clave, 6",
    "sg:city":"Rubi",
    "sg:orig_category":"Sindicatos De Trabajadores",
    "sg:phone":"+34 935 88 17 96",
    "sg:postcode":"08191",
    "sg:province":"Barcelona",
    "wof:name":"Confederacio General Del Treball",
    "wof:placetype":"venue"
},
  "geometry": {"coordinates":[2.0301311016,41.4888572693],"type":"Point"}
}