{
  "type": "Feature",
  "properties": {
    "iso:country":"ES",
    "sg:address":"Calle de Zamarripa Pablo, 8",
    "sg:city":"Bilbao",
    "sg:orig_category":"Centros Empresariales",
    "sg:phone":"+34 944 11 45 65",
    "sg:postcode":"48006",
    "sg:province":"Vizcaya",
    "wof:name":"Martinez Rodriguez Teodoro",
    "wof:placetype":"venue"
},
  "geometry": {"coordinates":[-2.9130589962,43.2565422058],"type":"Point"}
}