{
  "type": "Feature",
  "properties": {
    "iso:country":"ES",
    "sg:address":"Carr Son Galta, 10",
    "sg:city":"Son Moro",
    "sg:orig_category":"Edici\u00d3n De Diarios, Revistas, Boletines",
    "sg:phone":"+34 971 58 56 84",
    "sg:postcode":"07560",
    "sg:province":"Islas Baleares",
    "wof:name":"Nova Area S.a.",
    "wof:placetype":"venue"
},
  "geometry": {"coordinates":[3.3764801025,39.5764541626],"type":"Point"}
}