{
  "type": "Feature",
  "properties": {
    "iso:country":"ES",
    "sg:address":"Carrer de Gomera, S/n",
    "sg:city":"Mira-sol",
    "sg:orig_category":"M\u00c9dicos: Medicina Nuclear",
    "sg:phone":"+34 935 44 22 70",
    "sg:postcode":"08195",
    "sg:province":"Barcelona",
    "sg:website":"www.crc.es",
    "wof:name":"Diagnostico Medic Nuclear",
    "wof:placetype":"venue"
},
  "geometry": {"coordinates":[2.0408189297,41.4698982239],"type":"Point"}
}