{
  "type": "Feature",
  "properties": {
    "iso:country":"ES",
    "sg:address":"Carrer de Immaculada Concepcio, 9",
    "sg:city":"Cocentaina",
    "sg:orig_category":"Psic\u00d3logos",
    "sg:phone":"+34 966 50 01 63",
    "sg:postcode":"03820",
    "sg:province":"Alicante",
    "wof:name":"Cortez Dominguez Monica",
    "wof:placetype":"venue"
},
  "geometry": {"coordinates":[-0.4412539899,38.7387046814],"type":"Point"}
}