{
  "type": "Feature",
  "properties": {
    "iso:country":"ES",
    "sg:address":"Ferrocarril, 5",
    "sg:city":"Arta",
    "sg:orig_category":"Mec\u00c1nico Del Autom\u00d3vil",
    "sg:phone":"+34 971 82 95 97",
    "sg:postcode":"07570",
    "sg:province":"Islas Baleares",
    "wof:name":"Miguel Morey E Hijos S.l.",
    "wof:placetype":"venue"
},
  "geometry": {"coordinates":[3.3270459175,39.70520401],"type":"Point"}
}