{
  "type": "Feature",
  "properties": {
    "addr:full":"Calle de Nuevo Miramar, S/n Almu\u00f1ecar Granada 18690",
    "addr:postcode":"18690",
    "addr:street":"Calle De Nuevo Miramar S / N Almun\u0303Ecar",
    "iso:country":"ES",
    "sg:address":"Calle de Nuevo Miramar, S/n",
    "sg:city":"Almu\u00f1ecar",
    "sg:orig_category":"Librer\u00cdas",
    "sg:phone":"+34 958 88 07 54",
    "sg:postcode":"18690",
    "sg:province":"Granada",
    "wof:name":"Aktiebolaget Skaerhomens T-bokhandel S.l.",
    "wof:placetype":"venue"
},
  "geometry": {"coordinates":[-3.70733881,36.7359695435],"type":"Point"}
}