{
  "type": "Feature",
  "properties": {
    "addr:full":"Alvarito Playa, 2 Elviria M\u00e1laga 29604",
    "addr:housenumber":"2",
    "addr:postcode":"29604",
    "addr:street":"Playa;Ma\u0301Laga",
    "iso:country":"ES",
    "sg:address":"Alvarito Playa, 2",
    "sg:city":"Elviria",
    "sg:orig_category":"Centros Empresariales",
    "sg:phone":"+34 952 83 55 79",
    "sg:postcode":"29604",
    "sg:province":"M\u00e1laga",
    "wof:name":"Tabasco Marbella Sl",
    "wof:placetype":"venue"
},
  "geometry": {"coordinates":[-4.7747840881,36.4966812134],"type":"Point"}
}