{
  "type": "Feature",
  "properties": {
    "addr:full":"Ctra Alcala-sevilla, Km. 0012,8 Alcala Guadaira Sevilla 41500",
    "addr:postcode":"41500",
    "addr:street":"Ctra Alcala-Sevilla Km. 0012,8",
    "iso:country":"ES",
    "sg:address":"Ctra Alcala-sevilla, Km. 0012,8",
    "sg:city":"Alcala Guadaira",
    "sg:orig_category":"Productos Qu\u00cdmicos (fabricaci\u00d3n, Al Por Mayor)",
    "sg:phone":"+34 955 61 03 00",
    "sg:postcode":"41500",
    "sg:province":"Sevilla",
    "wof:name":"Al Air Liquide Espa\u00f1a S.a.",
    "wof:placetype":"venue"
},
  "geometry": {"coordinates":[-5.8543348312,37.3395385742],"type":"Point"}
}