{
  "type": "Feature",
  "properties": {
    "addr:full":"Pase Fernando El Catolico, 50 Zaragoza Zaragoza 50009",
    "addr:housenumber":"50",
    "addr:postcode":"50009",
    "addr:street":"Fernando El Catolico",
    "iso:country":"ES",
    "sg:address":"Pase Fernando El Catolico, 50",
    "sg:city":"Zaragoza",
    "sg:orig_category":"Almacenes Y Tiendas De Productos Variados",
    "sg:phone":"+34 976 55 17 69",
    "sg:postcode":"50009",
    "sg:province":"Zaragoza",
    "wof:name":"Bodegas El Pilar S. A.",
    "wof:placetype":"venue"
},
  "geometry": {"coordinates":[-0.8964740038,41.6396408081],"type":"Point"}
}