{
  "type": "Feature",
  "properties": {
    "iso:country":"ES",
    "sg:address":"Pol Ind Malpesa, 60",
    "sg:city":"Salteras",
    "sg:orig_category":"Empresas De Carpinter\u00cda Met\u00c1lica",
    "sg:phone":"+34 955 70 80 35",
    "sg:postcode":"41909",
    "sg:province":"Sevilla",
    "wof:name":"Aluminios Salteras S.l",
    "wof:placetype":"venue"
},
  "geometry": {"coordinates":[-6.0785102844,37.4719276428],"type":"Point"}
}