{
  "type": "Feature",
  "properties": {
    "addr:full":"C/ Sor Josefa Alcorta, 35 Elche Alicante 03204",
    "addr:housenumber":"35",
    "addr:postcode":"03204",
    "addr:street":"C / Sor Josefa Alcorta",
    "iso:country":"ES",
    "sg:address":"C/ Sor Josefa Alcorta, 35",
    "sg:city":"Elche",
    "sg:orig_category":"Agentes, Concesionarios Y Sucursales De Veh\u00cdculos",
    "sg:phone":"+34 966 63 19 08",
    "sg:postcode":"03204",
    "sg:province":"Alicante",
    "wof:name":"Alcorta Motor S.l.",
    "wof:placetype":"venue"
},
  "geometry": {"coordinates":[-0.7027893066,38.2565002441],"type":"Point"}
}