{
  "type": "Feature",
  "properties": {
    "iso:country":"ES",
    "sg:address":"Barr Pendon, S/n",
    "sg:city":"Pendon",
    "sg:orig_category":"Afiladoras, Pulidoras Y Bru\u00d1idoras",
    "sg:phone":"+34 942 64 22 82",
    "sg:postcode":"39791",
    "sg:province":"Cantabria",
    "wof:name":"Somarriba Cuetos Claudio",
    "wof:placetype":"venue"
},
  "geometry": {"coordinates":[-3.5475239754,43.4179649353],"type":"Point"}
}