{
  "type": "Feature",
  "properties": {
    "addr:full":"C/ Monserrate Guilabert Valero, 7 Elche Alicante 03205",
    "addr:housenumber":"7",
    "addr:postcode":"03205",
    "addr:street":"C / Monserrate Guilabert Valero",
    "iso:country":"ES",
    "sg:address":"C/ Monserrate Guilabert Valero, 7",
    "sg:city":"Elche",
    "sg:orig_category":"Servicios De Telecomunicaciones",
    "sg:phone":"+34 965 46 95 63",
    "sg:postcode":"03205",
    "sg:province":"Alicante",
    "wof:name":"Onyelike  Ikechukwu Uzodinma",
    "wof:placetype":"venue"
},
  "geometry": {"coordinates":[-0.7102149725,38.2675552368],"type":"Point"}
}