{
  "type": "Feature",
  "properties": {
    "iso:country":"ES",
    "sg:address":"Calle de Lopez De Los Rios, 12",
    "sg:city":"Cijuela",
    "sg:orig_category":"Asesor\u00cda De Formaci\u00d3n Y Gesti\u00d3n De Personal",
    "sg:phone":"+34 958 51 53 50",
    "sg:postcode":"18339",
    "sg:province":"Granada",
    "wof:name":"Perez Martin Inmaculada",
    "wof:placetype":"venue"
},
  "geometry": {"coordinates":[-3.8097639084,37.1995429993],"type":"Point"}
}