{
  "type": "Feature",
  "properties": {
    "addr:full":"Avda Fragoso, 43 Vigo Pontevedra 36210",
    "addr:housenumber":"43",
    "addr:postcode":"36210",
    "addr:street":"Avda Fragoso",
    "iso:country":"ES",
    "sg:address":"Avda Fragoso, 43",
    "sg:city":"Vigo",
    "sg:orig_category":"Radiocomunicaciones, Telefon\u00cda M\u00d3vil, Radiomensajer\u00cda: Servicios, Comercializaci\u00d3n",
    "sg:phone":"+34 986 21 32 46",
    "sg:postcode":"36210",
    "sg:province":"Pontevedra",
    "wof:name":"Servicios Teleinformaticos De Galicia S.l.",
    "wof:placetype":"venue"
},
  "geometry": {"coordinates":[-8.7340240479,42.2176971436],"type":"Point"}
}