{
  "type": "Feature",
  "properties": {
    "addr:full":"Pl Espanya, 5 Sitges Barcelona 08870",
    "addr:housenumber":"5",
    "addr:postcode":"08870",
    "addr:street":"Pl Espanya",
    "iso:country":"ES",
    "sg:address":"Pl Espanya, 5",
    "sg:city":"Sitges",
    "sg:orig_category":"M\u00c9dicos: Pediatr\u00cda. Enfermedades De Los Ni\u00d1os",
    "sg:phone":"+34 938 94 22 90",
    "sg:postcode":"08870",
    "sg:province":"Barcelona",
    "wof:name":"Tort Arnau Maria Del Carmen",
    "wof:placetype":"venue"
},
  "geometry": {"coordinates":[1.8058450222,41.2362136841],"type":"Point"}
}