{
  "type": "Feature",
  "properties": {
    "iso:country":"ES",
    "sg:address":"Calle de Bubierca, 1",
    "sg:city":"Madrid",
    "sg:orig_category":"Peluquer\u00cdas, Peluquer\u00cda Mixta",
    "sg:phone":"+34 913 31 30 55",
    "sg:postcode":"28031",
    "sg:province":"Madrid",
    "wof:name":"Alonso Monta\u00f1a Maria Luz",
    "wof:placetype":"venue"
},
  "geometry": {"coordinates":[-3.6190133095,40.3749313354],"type":"Point"}
}