{
  "type": "Feature",
  "properties": {
    "addr:full":"Avda Ferrol (del), 25 Viveiro Lugo 27850",
    "addr:housenumber":"25",
    "addr:postcode":"27850",
    "addr:street":"Avda Ferrol Del",
    "iso:country":"ES",
    "sg:address":"Avda Ferrol (del), 25",
    "sg:city":"Viveiro",
    "sg:orig_category":"Tapicer\u00cdas",
    "sg:phone":"+34 982 56 33 00",
    "sg:postcode":"27850",
    "sg:province":"Lugo",
    "wof:name":"Fernandez Rivera Luis",
    "wof:placetype":"venue"
},
  "geometry": {"coordinates":[-7.5988898277,43.6568832397],"type":"Point"}
}