{
  "type": "Feature",
  "properties": {
    "iso:country":"ES",
    "sg:address":"Avda Cinco Siglos (de Los), 169",
    "sg:city":"Navalcarnero",
    "sg:orig_category":"Agencias Y Agentes Comerciales, Representantes",
    "sg:phone":"+34 918 10 16 01",
    "sg:postcode":"28600",
    "sg:province":"Madrid",
    "wof:name":"Salda\u00f1a Arg\u00fcello S.l.",
    "wof:placetype":"venue"
},
  "geometry": {"coordinates":[-4.0233302116,40.2815551758],"type":"Point"}
}