{
  "type": "Feature",
  "properties": {
    "iso:country":"ES",
    "sg:address":"Plaz Castillo, 15",
    "sg:city":"Carboneras",
    "sg:orig_category":"Farmacias",
    "sg:phone":"+34 950 45 45 08",
    "sg:postcode":"04140",
    "sg:province":"Almer\u00eda",
    "wof:name":"Gasquez Soria Jose",
    "wof:placetype":"venue"
},
  "geometry": {"coordinates":[-1.8956240416,36.9959602356],"type":"Point"}
}