{
  "type": "Feature",
  "properties": {
    "addr:full":"Avda America (de), 48 Granada Granada 18008",
    "addr:housenumber":"48",
    "addr:postcode":"18008",
    "addr:street":"Avda America De",
    "iso:country":"ES",
    "sg:address":"Avda America (de), 48",
    "sg:city":"Granada",
    "sg:orig_category":"Confecci\u00d3n De Trajes Para Se\u00d1oras",
    "sg:phone":"+34 958 81 06 11",
    "sg:postcode":"18008",
    "sg:province":"Granada",
    "wof:name":"Miguel Seleccion S.l.",
    "wof:placetype":"venue"
},
  "geometry": {"coordinates":[-3.5934290886,37.160358429],"type":"Point"}
}