{
  "type": "Feature",
  "properties": {
    "iso:country":"ES",
    "sg:address":"Calle de Honda, 16",
    "sg:city":"Fuenlabrada",
    "sg:orig_category":"Molduras, Junquillos, Listones Y Molduras Perforadas",
    "sg:phone":"+34 916 90 58 66",
    "sg:postcode":"28944",
    "sg:province":"Madrid",
    "wof:name":"Diaz Martinez Julio",
    "wof:placetype":"venue"
},
  "geometry": {"coordinates":[-3.7909259796,40.2810287476],"type":"Point"}
}