{
  "type": "Feature",
  "properties": {
    "addr:full":"Calle de Isla De Mouro, 7 Somo Cantabria 39140",
    "addr:housenumber":"7",
    "addr:postcode":"39140",
    "addr:street":"Calle De Isla De Mouro",
    "iso:country":"ES",
    "sg:address":"Calle de Isla De Mouro, 7",
    "sg:city":"Somo",
    "sg:orig_category":"Supermercados Y Hipermercados",
    "sg:phone":"+34 942 51 02 73",
    "sg:postcode":"39140",
    "sg:province":"Cantabria",
    "wof:name":"Esteban Aja Santiago",
    "wof:placetype":"venue"
},
  "geometry": {"coordinates":[-3.7438690662,43.4552536011],"type":"Point"}
}