{
  "type": "Feature",
  "properties": {
    "iso:country":"ES",
    "sg:address":"Calle de Gloria, 3",
    "sg:city":"San Juan",
    "sg:orig_category":"Comercio, Reparaci\u00d3n De Bicicletas, De Motocicletas, De Accesorios",
    "sg:phone":"+34 968 21 37 19",
    "sg:postcode":"30003",
    "sg:province":"Murcia",
    "wof:name":"Bicicletas Montoya C. B.",
    "wof:placetype":"venue"
},
  "geometry": {"coordinates":[-1.1256040335,37.9825706482],"type":"Point"}
}