{
  "type": "Feature",
  "properties": {
    "iso:country":"ES",
    "sg:address":"Trva Lope De Figueroa, 3",
    "sg:city":"Alcala Henares",
    "sg:orig_category":"Centros De Salud",
    "sg:phone":"+34 918 81 24 69",
    "sg:postcode":"28804",
    "sg:province":"Madrid",
    "wof:name":"Huertas Jimenez Juan David",
    "wof:placetype":"venue"
},
  "geometry": {"coordinates":[-3.3531599045,40.4831962585],"type":"Point"}
}