{
  "type": "Feature",
  "properties": {
    "iso:country":"ES",
    "sg:address":"Calle de Cronista Manuel Serrano, 2",
    "sg:city":"Guadalajara",
    "sg:orig_category":"Notarios",
    "sg:phone":"+34 949 21 32 99",
    "sg:postcode":"19001",
    "sg:province":"Guadalajara",
    "wof:name":"Garcia Arroyo Maria De La Cruz",
    "wof:placetype":"venue"
},
  "geometry": {"coordinates":[-3.1667084694,40.6301994324],"type":"Point"}
}