{
  "type": "Feature",
  "properties": {
    "addr:full":"Avda Primero De Mayo, 21 Puertollano Ciudad Real 13500",
    "addr:housenumber":"21",
    "addr:postcode":"13500",
    "addr:street":"Avda Primero De Mayo",
    "iso:country":"ES",
    "sg:address":"Avda Primero De Mayo, 21",
    "sg:city":"Puertollano",
    "sg:orig_category":"Art\u00cdculos De Madera (fabricaci\u00d3n Y Al Por Mayor)",
    "sg:phone":"+34 926 42 73 18",
    "sg:postcode":"13500",
    "sg:province":"Ciudad Real",
    "wof:name":"Puerto Armario S.l",
    "wof:placetype":"venue"
},
  "geometry": {"coordinates":[-4.1054239273,38.6860466003],"type":"Point"}
}