{
  "type": "Feature",
  "properties": {
    "iso:country":"ES",
    "sg:address":"Ptge Joan Brillas, 6",
    "sg:city":"Esplugues Llobregat",
    "sg:orig_category":"Aparatos, M\u00c1quinas Y Procedimientos En Industria Qu\u00cdmica",
    "sg:phone":"+34 933 71 40 88",
    "sg:postcode":"08950",
    "sg:province":"Barcelona",
    "wof:name":"Raventos Sanchez Javier",
    "wof:placetype":"venue"
},
  "geometry": {"coordinates":[2.0808029175,41.3758392334],"type":"Point"}
}