{
  "type": "Feature",
  "properties": {
    "iso:country":"ES",
    "sg:address":"Rua Horreo (do), 44",
    "sg:city":"Santiago De Compostela",
    "sg:orig_category":"Energ\u00cda Solar Y Nuevas Energ\u00cdas (equipo, Estudios)",
    "sg:phone":"+34 981 55 53 80",
    "sg:postcode":"15702",
    "sg:province":"La Coru\u00f1a",
    "wof:name":"Asociacion De Promotores De Energia Eolica De Galicia",
    "wof:placetype":"venue"
},
  "geometry": {"coordinates":[-8.5464134216,42.8705291748],"type":"Point"}
}