{
  "type": "Feature",
  "properties": {
    "addr:full":"Ctra. Mentrida, Km. 0030,6 Torre Esteban Hambran Toledo 45920",
    "addr:postcode":"45920",
    "addr:street":"Ctra. Mentrida Km. 0030,6 Torre Esteban Hambran",
    "iso:country":"ES",
    "sg:address":"Ctra. Mentrida, Km. 0030,6",
    "sg:city":"Torre Esteban Hambran",
    "sg:orig_category":"Cerrajer\u00cda, Ferrallista",
    "sg:phone":"+34 925 79 51 08",
    "sg:postcode":"45920",
    "sg:province":"Toledo",
    "wof:name":"Garcia Pinto Manuel",
    "wof:placetype":"venue"
},
  "geometry": {"coordinates":[-4.2177853584,40.1716117859],"type":"Point"}
}