{
  "type": "Feature",
  "properties": {
    "iso:country":"ES",
    "sg:address":"Carr Figuerola, 11",
    "sg:city":"Girona",
    "sg:orig_category":"Ingenier\u00cda, Centros De Estudios (diversos)",
    "sg:phone":"+34 972 41 18 29",
    "sg:postcode":"17001",
    "sg:province":"Girona",
    "wof:name":"Representacions Tecniques Del Clima",
    "wof:placetype":"venue"
},
  "geometry": {"coordinates":[2.821721077,41.9857368469],"type":"Point"}
}