{
  "type": "Feature",
  "properties": {
    "iso:country":"ES",
    "sg:address":"Plaz Principes De Espa\u00d1a, 1",
    "sg:city":"Alcorcon",
    "sg:orig_category":"Animales (al Por Menor)",
    "sg:phone":"+34 916 19 35 08",
    "sg:postcode":"28924",
    "sg:province":"Madrid",
    "wof:name":"Dumont Actividades Sanitarias S.l.",
    "wof:placetype":"venue"
},
  "geometry": {"coordinates":[-3.8180639744,40.3505363464],"type":"Point"}
}