{
  "type": "Feature",
  "properties": {
    "iso:country":"ES",
    "sg:address":"Calle de Miguel De Cervantes, 10",
    "sg:city":"Alcala Real",
    "sg:orig_category":"Asesor\u00cda Fiscal Y Jur\u00cddica",
    "sg:phone":"+34 953 58 14 36",
    "sg:postcode":"23680",
    "sg:province":"Ja\u00e9n",
    "wof:name":"Gestoria J.cano S.l.",
    "wof:placetype":"venue"
},
  "geometry": {"coordinates":[-3.9233911037,37.4619979858],"type":"Point"}
}