{
  "type": "Feature",
  "properties": {
    "addr:full":"Emporitana, 2 Figueres Girona 17600",
    "addr:housenumber":"2",
    "addr:postcode":"17600",
    "addr:street":"Emporitana",
    "iso:country":"ES",
    "sg:address":"Emporitana, 2",
    "sg:city":"Figueres",
    "sg:orig_category":"Inform\u00c1tica (estudios, Servicios, Asesor\u00cda, Formaci\u00d3n)",
    "sg:phone":"+34 972 51 35 79",
    "sg:postcode":"17600",
    "sg:province":"Girona",
    "wof:name":"Gj Loboc S.l.",
    "wof:placetype":"venue"
},
  "geometry": {"coordinates":[2.9579269886,42.2632865906],"type":"Point"}
}