{
  "type": "Feature",
  "properties": {
    "addr:full":"Carrer de Argenters, 10 Vic Barcelona 08500",
    "addr:housenumber":"10",
    "addr:postcode":"08500",
    "addr:street":"Carrer De Argenters",
    "iso:country":"ES",
    "sg:address":"Carrer de Argenters, 10",
    "sg:city":"Vic",
    "sg:orig_category":"Ropa Y Art\u00cdculos Pre",
    "sg:phone":"+34 938 86 01 06",
    "sg:postcode":"08500",
    "sg:province":"Barcelona",
    "sg:website":"www.mamina.net",
    "wof:name":"Auguet Pou Jordi",
    "wof:placetype":"venue"
},
  "geometry": {"coordinates":[2.2553589344,41.9302940369],"type":"Point"}
}