{
  "type": "Feature",
  "properties": {
    "addr:full":"Eidos, 2 Eidos Pontevedra 36720",
    "addr:housenumber":"2",
    "addr:postcode":"36720",
    "addr:street":"Eidos",
    "iso:country":"ES",
    "sg:address":"Eidos, 2",
    "sg:city":"Eidos",
    "sg:orig_category":"Delegados, Agentes De Tr\u00c1nsito, Auxiliares De Transporte Internacional",
    "sg:phone":"+34 986 60 37 49",
    "sg:postcode":"36720",
    "sg:province":"Pontevedra",
    "wof:name":"Bealdis S.l.",
    "wof:placetype":"venue"
},
  "geometry": {"coordinates":[-8.6094818115,42.0647659302],"type":"Point"}
}