{
  "type": "Feature",
  "properties": {
    "addr:full":"Av Valencia, 14 Molins Rei Barcelona 08750",
    "addr:housenumber":"14",
    "addr:postcode":"08750",
    "addr:street":"Av Valencia;Barcelona",
    "iso:country":"ES",
    "sg:address":"Av Valencia, 14",
    "sg:city":"Molins Rei",
    "sg:orig_category":"Herramientas Manuales (fabricaci\u00d3n, Al Por Mayor)",
    "sg:phone":"+34 936 80 08 08",
    "sg:postcode":"08750",
    "sg:province":"Barcelona",
    "wof:name":"Hhw Hommel Hercuales Iberica S.l.",
    "wof:placetype":"venue"
},
  "geometry": {"coordinates":[2.0186240673,41.4100036621],"type":"Point"}
}