{
  "type": "Feature",
  "properties": {
    "addr:full":"Plaz Flores (de Las), 11 Estepona M\u00e1laga 29680",
    "addr:housenumber":"11",
    "addr:postcode":"29680",
    "addr:street":"Las",
    "iso:country":"ES",
    "sg:address":"Plaz Flores (de Las), 11",
    "sg:city":"Estepona",
    "sg:orig_category":"Bisuter\u00cda, Joyer\u00cda, Relojer\u00cda (al Por Menor)",
    "sg:phone":"+34 952 80 13 97",
    "sg:postcode":"29680",
    "sg:province":"M\u00e1laga",
    "wof:name":"Palicio Moreno Francisco",
    "wof:placetype":"venue"
},
  "geometry": {"coordinates":[-5.145608902,36.4254264832],"type":"Point"}
}