{
  "type": "Feature",
  "properties": {
    "addr:full":"Calle de Asomada, 10 Icod De Los Vinos Santa Cruz De Tenerife 38430",
    "addr:housenumber":"10",
    "addr:postcode":"38430",
    "addr:street":"Calle De Asomada",
    "iso:country":"ES",
    "sg:address":"Calle de Asomada, 10",
    "sg:city":"Icod De Los Vinos",
    "sg:orig_category":"Asesor\u00cda Fiscal Y Jur\u00cddica",
    "sg:phone":"+34 922 81 57 57",
    "sg:postcode":"38430",
    "sg:province":"Santa Cruz De Tenerife",
    "wof:name":"Vicente Perez-mario Gonzalez S.l.",
    "wof:placetype":"venue"
},
  "geometry": {"coordinates":[-16.7189826965,28.3666629791],"type":"Point"}
}