{
  "type": "Feature",
  "properties": {
    "addr:full":"Calle de Barretaguren, 6 G\u00fce\u00f1es Vizcaya 48840",
    "addr:housenumber":"6",
    "addr:postcode":"48840",
    "addr:street":"Calle De Barretaguren",
    "iso:country":"ES",
    "sg:address":"Calle de Barretaguren, 6",
    "sg:city":"G\u00fce\u00f1es",
    "sg:classifiers":[
        {
            "category":"Communications",
            "type":"Services"
        }
    ],
    "sg:phone":"+34 946 69 02 51",
    "sg:postcode":"48840",
    "sg:province":"Vizcaya",
    "sg:tags":[
        "televisiones",
        "y",
        "radio"
    ],
    "wof:name":"Remar Espa\u00f1a",
    "wof:placetype":"venue"
},
  "geometry": {"coordinates":[-3.0969367027,43.2129707336],"type":"Point"}
}