{
  "type": "Feature",
  "properties": {
    "iso:country":"ES",
    "sg:address":"Calle de Gamazo, 18",
    "sg:city":"Valladolid",
    "sg:orig_category":"Material Y Suministros Para Relojer\u00cda",
    "sg:phone":"+34 983 30 32 11",
    "sg:postcode":"47004",
    "sg:province":"Valladolid",
    "wof:name":"Fernandez Baladron Ricardo",
    "wof:placetype":"venue"
},
  "geometry": {"coordinates":[-4.7262682915,41.6459770203],"type":"Point"}
}