{
  "type": "Feature",
  "properties": {
    "addr:full":"Carrer de Angel Guimera, 1 Esplugues Llobregat Barcelona 08950",
    "addr:housenumber":"1",
    "addr:postcode":"08950",
    "addr:street":"Carrer De Angel Guimera",
    "iso:country":"ES",
    "sg:address":"Carrer de Angel Guimera, 1",
    "sg:city":"Esplugues Llobregat",
    "sg:orig_category":"Cajas De Ahorro",
    "sg:phone":"+34 933 71 66 08",
    "sg:postcode":"08950",
    "sg:province":"Barcelona",
    "sg:website":"www.lacaixa.es",
    "wof:name":"Caixa D'estalvis I Pensions De Barcelona",
    "wof:placetype":"venue"
},
  "geometry": {"coordinates":[2.0867369175,41.3774681091],"type":"Point"}
}