{
  "type": "Feature",
  "properties": {
    "iso:country":"ES",
    "sg:address":"Calle de Pastora, 12",
    "sg:city":"Malaga",
    "sg:orig_category":"Librer\u00cdas",
    "sg:phone":"+34 952 22 41 40",
    "sg:postcode":"29005",
    "sg:province":"M\u00e1laga",
    "wof:name":"Espinosa De Los Monteros Perez Baltasar",
    "wof:placetype":"venue"
},
  "geometry": {"coordinates":[-4.4234142303,36.7177886963],"type":"Point"}
}