{
  "type": "Feature",
  "properties": {
    "addr:full":"Carr Calvo Acacio, 11 Alcudia Valencia 46250",
    "addr:housenumber":"11",
    "addr:postcode":"46250",
    "addr:street":"Carr Calvo Acacio",
    "iso:country":"ES",
    "sg:address":"Carr Calvo Acacio, 11",
    "sg:city":"Alcudia",
    "sg:orig_category":"Lencer\u00cda Femenina, Corseter\u00cda, Trajes De Ba\u00d1o (al Por Menor)",
    "sg:phone":"+34 962 99 60 73",
    "sg:postcode":"46250",
    "sg:province":"Valencia",
    "wof:name":"Arnandis Masanet Francisca",
    "wof:placetype":"venue"
},
  "geometry": {"coordinates":[-0.505343318,39.1979560852],"type":"Point"}
}