{
  "type": "Feature",
  "properties": {
    "iso:country":"ES",
    "sg:address":"Bo. Estacion, 42",
    "sg:city":"Montearagon",
    "sg:orig_category":"Comerciantes Al Por Mayor De Vinos, Licores Y Alcoholes",
    "sg:phone":"+34 925 86 52 78",
    "sg:postcode":"45555",
    "sg:province":"Toledo",
    "wof:name":"Colado Pavon Angel",
    "wof:placetype":"venue"
},
  "geometry": {"coordinates":[-4.6330699921,39.9548797607],"type":"Point"}
}