{
  "type": "Feature",
  "properties": {
    "iso:country":"ES",
    "sg:address":"Pase Prado, S/n",
    "sg:city":"Madrid",
    "sg:orig_category":"Museos",
    "sg:phone":"+34 913 69 11 48",
    "sg:postcode":"28014",
    "sg:province":"Madrid",
    "wof:name":"Museo Del Prado",
    "wof:placetype":"venue"
},
  "geometry": {"coordinates":[-3.6973640919,40.4152984619],"type":"Point"}
}