{
  "type": "Feature",
  "properties": {
    "addr:full":"Avda Andalucia, S/n Sevilla Sevilla 41006",
    "addr:postcode":"41006",
    "addr:street":"Avda Andalucia S / N",
    "iso:country":"ES",
    "sg:address":"Avda Andalucia, S/n",
    "sg:city":"Sevilla",
    "sg:orig_category":"Ropa Para Se\u00d1oras Y Caballeros (al Por Menor)",
    "sg:phone":"+34 954 67 16 42",
    "sg:postcode":"41006",
    "sg:province":"Sevilla",
    "wof:name":"Cortefiel S.a.",
    "wof:placetype":"venue"
},
  "geometry": {"coordinates":[-5.9590339661,37.3874053955],"type":"Point"}
}