{
  "type": "Feature",
  "properties": {
    "iso:country":"ES",
    "sg:address":"Calle de Real De Valderrubio, 86",
    "sg:city":"Valderrubio",
    "sg:orig_category":"Material Y Herramientas Agr\u00cdcolas",
    "sg:phone":"+34 958 45 40 06",
    "sg:postcode":"18250",
    "sg:province":"Granada",
    "wof:name":"Hurtado Castro Rafael",
    "wof:placetype":"venue"
},
  "geometry": {"coordinates":[-3.8232390881,37.2354049683],"type":"Point"}
}