{
  "type": "Feature",
  "properties": {
    "iso:country":"ES",
    "sg:address":"Pl Vila, 5",
    "sg:city":"Santa Perpetua De Mogoda",
    "sg:orig_category":"Ense\u00d1anza, Formaci\u00d3n Profesional: Aprendizaje",
    "sg:phone":"+34 935 74 32 34",
    "sg:postcode":"08130",
    "sg:province":"Barcelona",
    "wof:name":"Ajuntament De Santa Perpetuade Mogoda",
    "wof:placetype":"venue"
},
  "geometry": {"coordinates":[2.1830506325,41.535118103],"type":"Point"}
}