{
  "type": "Feature",
  "properties": {
    "addr:full":"Rua Peregrina (da), 22 Pontevedra Pontevedra 36001",
    "addr:housenumber":"22",
    "addr:postcode":"36001",
    "addr:street":"Rua Peregrina Da",
    "iso:country":"ES",
    "sg:address":"Rua Peregrina (da), 22",
    "sg:city":"Pontevedra",
    "sg:orig_category":"Farmacias",
    "sg:phone":"+34 986 85 14 17",
    "sg:postcode":"36001",
    "sg:province":"Pontevedra",
    "wof:name":"Farmacia Trinidad Mosquera",
    "wof:placetype":"venue"
},
  "geometry": {"coordinates":[-8.6435804367,42.4299163818],"type":"Point"}
}