{
  "type": "Feature",
  "properties": {
    "addr:full":"Avda Doctor Waksman, 18 Valencia Valencia 46006",
    "addr:housenumber":"18",
    "addr:postcode":"46006",
    "addr:street":"Avda Doctor Waksman",
    "iso:country":"ES",
    "sg:address":"Avda Doctor Waksman, 18",
    "sg:city":"Valencia",
    "sg:orig_category":"Discotecas Y Salas De Baile",
    "sg:phone":"+34 963 34 45 08",
    "sg:postcode":"46006",
    "sg:province":"Valencia",
    "wof:name":"Waksman 18 S.l",
    "wof:placetype":"venue"
},
  "geometry": {"coordinates":[-0.3738096952,39.456401825],"type":"Point"}
}