{
  "type": "Feature",
  "properties": {
    "iso:country":"ES",
    "sg:address":"Torre Mora, S/n",
    "sg:city":"Pals",
    "sg:orig_category":"Promotores Constructores",
    "sg:phone":"+34 972 63 63 84",
    "sg:postcode":"17256",
    "sg:province":"Girona",
    "wof:name":"Promocions I Construccions Pals S. L.",
    "wof:placetype":"venue"
},
  "geometry": {"coordinates":[3.200414896,41.9840888977],"type":"Point"}
}