{
  "type": "Feature",
  "properties": {
    "iso:country":"ES",
    "sg:address":"Calle de Reyes Nu\u00d1ez, 90",
    "sg:city":"Santa Marta",
    "sg:orig_category":"Empresas De Carpinter\u00cda De Madera",
    "sg:phone":"+34 924 69 05 45",
    "sg:postcode":"06150",
    "sg:province":"Badajoz",
    "wof:name":"Rodriguez Sanchez Jose Antonio",
    "wof:placetype":"venue"
},
  "geometry": {"coordinates":[-6.6306428909,38.6157302856],"type":"Point"}
}