{
  "type": "Feature",
  "properties": {
    "addr:full":"Pol Ind El Llano, S/n Bu\u00f1ol Valencia 46360",
    "addr:postcode":"46360",
    "addr:street":"Llano S / N",
    "iso:country":"ES",
    "sg:address":"Pol Ind El Llano, S/n",
    "sg:city":"Bu\u00f1ol",
    "sg:orig_category":"Productores Recolectores, Venta Directa De Vinos",
    "sg:phone":"+34 962 50 48 27",
    "sg:postcode":"46360",
    "sg:province":"Valencia",
    "wof:name":"Vi\u00f1as Del Portillo S.l.",
    "wof:placetype":"venue"
},
  "geometry": {"coordinates":[-0.857981801,39.4315185547],"type":"Point"}
}