{
  "type": "Feature",
  "properties": {
    "addr:full":"Calle de Mayor, 5 Alca\u00f1iz Teruel 44600",
    "addr:housenumber":"5",
    "addr:postcode":"44600",
    "addr:street":"Calle De Mayor",
    "iso:country":"ES",
    "sg:address":"Calle de Mayor, 5",
    "sg:city":"Alca\u00f1iz",
    "sg:orig_category":"Relojer\u00cda (al Por Menor, Reparaci\u00d3n)",
    "sg:phone":"+34 978 83 00 01",
    "sg:postcode":"44600",
    "sg:province":"Teruel",
    "sg:website":"www.yoyeriavicma.net",
    "wof:name":"Dolz Carbo Victor",
    "wof:placetype":"venue"
},
  "geometry": {"coordinates":[-0.1325639933,41.0507202148],"type":"Point"}
}