{
  "type": "Feature",
  "properties": {
    "addr:full":"Avda Sardi\u00d1eira, 25 Coru\u00d1a La Coru\u00f1a 15007",
    "addr:housenumber":"25",
    "addr:postcode":"15007",
    "addr:street":"Avda Sardin\u0303Eira;La Corun\u0303A",
    "iso:country":"ES",
    "sg:address":"Avda Sardi\u00d1eira, 25",
    "sg:city":"Coru\u00d1a",
    "sg:orig_category":"Transporte En General",
    "sg:phone":"+34 981 23 29 06",
    "sg:postcode":"15007",
    "sg:province":"La Coru\u00f1a",
    "wof:name":"Consuelo Y Jose Manuel Eiroa Otero S.c.",
    "wof:placetype":"venue"
},
  "geometry": {"coordinates":[-8.4120798111,43.3520927429],"type":"Point"}
}