{
  "type": "Feature",
  "properties": {
    "iso:country":"ES",
    "sg:address":"Calle de Virgen, 21",
    "sg:city":"Linares",
    "sg:orig_category":"Herboristas (al Por Menor)",
    "sg:phone":"+34 953 60 20 53",
    "sg:postcode":"23700",
    "sg:province":"Ja\u00e9n",
    "wof:name":"Dorador Contreras Dolores",
    "wof:placetype":"venue"
},
  "geometry": {"coordinates":[-3.6346518993,38.0971794128],"type":"Point"}
}