{
  "type": "Feature",
  "properties": {
    "addr:full":"Calle de Madre De Dios, 15 Logro\u00f1o La Rioja 26...",
    "addr:housenumber":"15;26 ...",
    "addr:street":"Calle De Madre;Dios;La Rioja",
    "iso:country":"ES",
    "sg:address":"Calle de Madre De Dios, 15",
    "sg:city":"Logro\u00f1o",
    "sg:orig_category":"Televisi\u00d3n, V\u00cddeo: Aparatos Y Accesorios (venta)",
    "sg:phone":"+34 941 27 93 00",
    "sg:postcode":"26...",
    "sg:province":"La Rioja",
    "sg:website":"www.mediamarkt.es",
    "wof:name":"Media Markt Logro\u00d1o Video Tv Hifi Elktro Computer S.a.u.",
    "wof:placetype":"venue"
},
  "geometry": {"coordinates":[-2.4358100891,42.4694595337],"type":"Point"}
}