{
  "type": "Feature",
  "properties": {
    "addr:full":"Calle de Mu\u00d1oz De Sepulveda, 73 Pozoblanco C\u00f3rdoba 14400",
    "addr:housenumber":"73",
    "addr:postcode":"14400",
    "addr:street":"Calle De Mun\u0303Oz De Sepulveda",
    "iso:country":"ES",
    "sg:address":"Calle de Mu\u00d1oz De Sepulveda, 73",
    "sg:city":"Pozoblanco",
    "sg:orig_category":"Plomeros",
    "sg:phone":"+34 957 77 25 95",
    "sg:postcode":"14400",
    "sg:province":"C\u00f3rdoba",
    "wof:name":"Angel Y Rafael Peralbo Molina S.l.",
    "wof:placetype":"venue"
},
  "geometry": {"coordinates":[-4.8517951965,38.3749198914],"type":"Point"}
}