{
  "type": "Feature",
  "properties": {
    "iso:country":"ES",
    "sg:address":"Calle de Junquillo, 101",
    "sg:city":"Cabra",
    "sg:orig_category":"Empresas De Carpinter\u00cda Met\u00c1lica",
    "sg:phone":"+34 957 52 57 01",
    "sg:postcode":"14940",
    "sg:province":"C\u00f3rdoba",
    "wof:name":"Morales Mo\u00f1iz Antonio",
    "wof:placetype":"venue"
},
  "geometry": {"coordinates":[-4.450920105,37.4727401733],"type":"Point"}
}