{
  "type": "Feature",
  "properties": {
    "addr:full":"Calle de Higueras, 47 Madrid Madrid 28011",
    "addr:housenumber":"47",
    "addr:postcode":"madrid;28011",
    "addr:street":"Calle De Higueras",
    "iso:country":"ES",
    "sg:address":"Calle de Higueras, 47",
    "sg:city":"Madrid",
    "sg:orig_category":"Carnicer\u00cdas, Carnicer\u00cdas",
    "sg:phone":"+34 914 79 19 66",
    "sg:postcode":"28011",
    "sg:province":"Madrid",
    "wof:name":"Lope Aguado Teofila",
    "wof:placetype":"venue"
},
  "geometry": {"coordinates":[-3.7452318668,40.4050216675],"type":"Point"}
}