{
  "type": "Feature",
  "properties": {
    "iso:country":"ES",
    "sg:address":"Real, 10",
    "sg:city":"Pontes Garcia Rodriguez",
    "sg:orig_category":"Servicios Gsm",
    "sg:phone":"+34 981 45 11 34",
    "sg:postcode":"15320",
    "sg:province":"La Coru\u00f1a",
    "wof:name":"Montajes As Pontes S.l.",
    "wof:placetype":"venue"
},
  "geometry": {"coordinates":[-7.8517541885,43.4459838867],"type":"Point"}
}