{
  "type": "Feature",
  "properties": {
    "iso:country":"ES",
    "sg:address":"Calle de Tierra De Barros (de La), 4",
    "sg:city":"Coslada",
    "sg:orig_category":"Bibliotecas, Mediatecas",
    "sg:phone":"+34 916 69 51 52",
    "sg:postcode":"28820",
    "sg:province":"Madrid",
    "wof:name":"Record Storage S.l.",
    "wof:placetype":"venue"
},
  "geometry": {"coordinates":[-3.5434939861,40.4326133728],"type":"Point"}
}