{
  "type": "Feature",
  "properties": {
    "addr:full":"Calle de Ordesa, 10 Caceres C\u00e1ceres 10005",
    "addr:housenumber":"10",
    "addr:postcode":"10005",
    "addr:street":"Calle De Ordesa;Ca\u0301Ceres",
    "iso:country":"ES",
    "sg:address":"Calle de Ordesa, 10",
    "sg:city":"Caceres",
    "sg:orig_category":"Cl\u00cdnicas M\u00c9dicas",
    "sg:phone":"+34 927 23 53 28",
    "sg:postcode":"10005",
    "sg:province":"C\u00e1ceres",
    "wof:name":"Centro Urgencia Medica Monfrague S. A.",
    "wof:placetype":"venue"
},
  "geometry": {"coordinates":[-6.5341739655,39.4675254822],"type":"Point"}
}