{
  "type": "Feature",
  "properties": {
    "iso:country":"ES",
    "sg:address":"Sta Lucia (p I Arroyo Miel), 19",
    "sg:city":"Arroyo Miel",
    "sg:orig_category":"Transportes Por Carretera: Lotes Completos, Mercanc\u00cdas Diversas",
    "sg:phone":"+34 952 58 73 75",
    "sg:postcode":"29631",
    "sg:province":"M\u00e1laga",
    "wof:name":"G.h.d. Spain S.l.",
    "wof:placetype":"venue"
},
  "geometry": {"coordinates":[-4.5303959846,36.6042938232],"type":"Point"}
}