{
  "type": "Feature",
  "properties": {
    "addr:full":"Av Generalitat (de La), 89 Tortosa Tarragona 43500",
    "addr:housenumber":"89",
    "addr:postcode":"43500",
    "addr:street":"Av Generalitat De La",
    "iso:country":"ES",
    "sg:address":"Av Generalitat (de La), 89",
    "sg:city":"Tortosa",
    "sg:orig_category":"Promotores Constructores",
    "sg:phone":"+34 977 44 18 25",
    "sg:postcode":"43500",
    "sg:province":"Tarragona",
    "wof:name":"Sanz Marcos Jose Luis",
    "wof:placetype":"venue"
},
  "geometry": {"coordinates":[0.5203949809,40.8082084656],"type":"Point"}
}