{
  "type": "Feature",
  "properties": {
    "iso:country":"ES",
    "sg:address":"Calle de Colombia, 31",
    "sg:city":"Tablero",
    "sg:orig_category":"Importaci\u00d3n",
    "sg:phone":"+34 928 14 83 06",
    "sg:postcode":"35100",
    "sg:province":"Las Palmas",
    "wof:name":"Giuseppe Cafes Import-export S.l.",
    "wof:placetype":"venue"
},
  "geometry": {"coordinates":[-15.6064291,27.7722549438],"type":"Point"}
}