{
  "type": "Feature",
  "properties": {
    "iso:country":"ES",
    "sg:address":"Calle de Merida, 5",
    "sg:city":"Burgos",
    "sg:orig_category":"Pescader\u00cdas (al Por Menor)",
    "sg:phone":"+34 947 48 04 63",
    "sg:postcode":"09007",
    "sg:province":"Burgos",
    "wof:name":"Chico Quintana Miguel Angel",
    "wof:placetype":"venue"
},
  "geometry": {"coordinates":[-3.6542890072,42.3632240295],"type":"Point"}
}