{
  "type": "Feature",
  "properties": {
    "addr:full":"Avda Fisterra, 105 Arteixo La Coru\u00f1a 15142",
    "addr:housenumber":"105",
    "addr:postcode":"15142",
    "addr:street":"Avda Fisterra;La Corun\u0303A",
    "iso:country":"ES",
    "sg:address":"Avda Fisterra, 105",
    "sg:city":"Arteixo",
    "sg:orig_category":"Vinagre Y Mostaza (fabricaci\u00d3n, Al Por Mayor)",
    "sg:phone":"+34 981 60 00 69",
    "sg:postcode":"15142",
    "sg:province":"La Coru\u00f1a",
    "sg:website":"www.gabesa.com",
    "wof:name":"Gallega De Bebidas S. A.",
    "wof:placetype":"venue"
},
  "geometry": {"coordinates":[-8.5084037781,43.305770874],"type":"Point"}
}