{
  "type": "Feature",
  "properties": {
    "iso:country":"ES",
    "sg:address":"Calle de Joaquin Belon, 20",
    "sg:city":"Palmas De Gran Canaria",
    "sg:orig_category":"Venta, Alquiler De Grupos Electr\u00d3genos",
    "sg:phone":"+34 928 20 84 99",
    "sg:postcode":"35013",
    "sg:province":"Las Palmas",
    "wof:name":"Alquileres Batista S.l.",
    "wof:placetype":"venue"
},
  "geometry": {"coordinates":[-15.4366846085,28.1036243439],"type":"Point"}
}