{
  "type": "Feature",
  "properties": {
    "iso:country":"ES",
    "sg:address":"Calle de Fernandez Del Campo, 26",
    "sg:city":"Bilbao",
    "sg:orig_category":"Arquitectos",
    "sg:phone":"+34 944 10 64 62",
    "sg:postcode":"48010",
    "sg:province":"Vizcaya",
    "wof:name":"M. Izaskun Sasia Iriondo-isaac Lopez Barrero C.b.",
    "wof:placetype":"venue"
},
  "geometry": {"coordinates":[-2.9350175858,43.2588119507],"type":"Point"}
}