{
  "type": "Feature",
  "properties": {
    "addr:full":"Calle de Loro, 1 Roquetas Mar Almer\u00eda 04740",
    "addr:housenumber":"1",
    "addr:postcode":"04740",
    "addr:street":"Calle De Loro",
    "iso:country":"ES",
    "sg:address":"Calle de Loro, 1",
    "sg:city":"Roquetas Mar",
    "sg:orig_category":"Arquitectos",
    "sg:phone":"+34 950 32 55 32",
    "sg:postcode":"04740",
    "sg:province":"Almer\u00eda",
    "wof:name":"Pomares Martin Juan",
    "wof:placetype":"venue"
},
  "geometry": {"coordinates":[-2.6108291149,36.7601051331],"type":"Point"}
}