{
  "type": "Feature",
  "properties": {
    "addr:full":"Calle de Padre Florez, 4 Burgos Burgos 09005",
    "addr:housenumber":"4",
    "addr:postcode":"09005",
    "addr:street":"Calle De Padre Florez",
    "iso:country":"ES",
    "sg:address":"Calle de Padre Florez, 4",
    "sg:city":"Burgos",
    "sg:orig_category":"M\u00c1rmoles, Granitos Y Piedras Naturales",
    "sg:phone":"+34 947 22 12 65",
    "sg:postcode":"09005",
    "sg:province":"Burgos",
    "wof:name":"Cascajares Y Collantes S.l.",
    "wof:placetype":"venue"
},
  "geometry": {"coordinates":[-3.6968810558,42.3483390808],"type":"Point"}
}