{
  "type": "Feature",
  "properties": {
    "iso:country":"ES",
    "sg:address":"Calle de Sal, 1",
    "sg:city":"Aranda Duero",
    "sg:orig_category":"Ropa Para Se\u00d1oras (al Por Menor)",
    "sg:phone":"+34 947 50 08 96",
    "sg:postcode":"09400",
    "sg:province":"Burgos",
    "wof:name":"Comercial Xesta S. A.",
    "wof:placetype":"venue"
},
  "geometry": {"coordinates":[-3.6898200512,41.6702957153],"type":"Point"}
}