{
  "type": "Feature",
  "properties": {
    "iso:country":"ES",
    "sg:address":"Avda Galicia, 120",
    "sg:city":"Ponferrada",
    "sg:orig_category":"Comercio, Reparaci\u00d3n De Motocicletas, Bicicletas Y Piezas Sueltas",
    "sg:phone":"+34 987 42 46 79",
    "sg:postcode":"24400",
    "sg:province":"Le\u00f3n",
    "wof:name":"Fernandez Gomez Dario",
    "wof:placetype":"venue"
},
  "geometry": {"coordinates":[-6.6158089638,42.5561408997],"type":"Point"}
}