{
  "type": "Feature",
  "properties": {
    "iso:country":"ES",
    "sg:address":"Calle de Cervantes, 14",
    "sg:city":"Burgos",
    "sg:orig_category":"Transportes Por Carretera: Lotes Completos, Mercanc\u00cdas Diversas",
    "sg:phone":"+34 947 26 80 98",
    "sg:postcode":"09002",
    "sg:province":"Burgos",
    "wof:name":"Gonzalez Palacios Sebastian",
    "wof:placetype":"venue"
},
  "geometry": {"coordinates":[-3.6959600449,42.3336639404],"type":"Point"}
}