{
  "type": "Feature",
  "properties": {
    "iso:country":"ES",
    "sg:address":"Carrer de Creu, 72",
    "sg:city":"S. Just Desvern",
    "sg:orig_category":"Centros De Coordinaci\u00d3n",
    "sg:phone":"+34 933 71 16 74",
    "sg:postcode":"08960",
    "sg:province":"Barcelona",
    "wof:name":"Gestoria Brull S.l.",
    "wof:placetype":"venue"
},
  "geometry": {"coordinates":[2.0749950409,41.3822097778],"type":"Point"}
}