{
  "type": "Feature",
  "properties": {
    "addr:full":"Calle de Juan De Lama, 1 Ponferrada Le\u00f3n 24400",
    "addr:postcode":"24400",
    "addr:street":"Calle De Juan De Lama",
    "iso:country":"ES",
    "sg:address":"Calle de Juan De Lama, 1",
    "sg:city":"Ponferrada",
    "sg:orig_category":"Ropa Para Se\u00d1oras Y Caballeros (al Por Menor)",
    "sg:phone":"+34 987 41 17 50",
    "sg:postcode":"24400",
    "sg:province":"Le\u00f3n",
    "wof:name":"Bodelon S.l.",
    "wof:placetype":"venue"
},
  "geometry": {"coordinates":[-6.5963487625,42.5469665527],"type":"Point"}
}