{
  "type": "Feature",
  "properties": {
    "iso:country":"ES",
    "sg:address":"Calle de Villargordo Del Cabriel, 10",
    "sg:city":"Utiel",
    "sg:orig_category":"Agencias Y Agentes Comerciales, Representantes",
    "sg:phone":"+34 962 16 86 10",
    "sg:postcode":"46300",
    "sg:province":"Valencia",
    "wof:name":"Latorre Lopez Francisco",
    "wof:placetype":"venue"
},
  "geometry": {"coordinates":[-1.2081519365,39.5709648132],"type":"Point"}
}