{
  "type": "Feature",
  "properties": {
    "iso:country":"ES",
    "sg:address":"Calle de Atxuri, 6",
    "sg:city":"Soraluze-placencia Armas",
    "sg:orig_category":"Asilos De Ancianos. Centros Privados",
    "sg:phone":"+34 943 75 11 36",
    "sg:postcode":"20590",
    "sg:province":"Guip\u00f9zcoa",
    "wof:name":"Residencia De Ancianos Nuestra Se\u00f1ora De La Merced",
    "wof:placetype":"venue"
},
  "geometry": {"coordinates":[-2.412391901,43.1716918945],"type":"Point"}
}