{
  "type": "Feature",
  "properties": {
    "iso:country":"ES",
    "sg:address":"Calle de Carretera Nueva, 69",
    "sg:city":"Rinconada",
    "sg:orig_category":"Materiales De Aislamiento T\u00c9rmico Y Ac\u00dastico",
    "sg:phone":"+34 955 79 73 12",
    "sg:postcode":"41309",
    "sg:province":"Sevilla",
    "wof:name":"Montaje Y Aislamiento Sevi S.l.",
    "wof:placetype":"venue"
},
  "geometry": {"coordinates":[-5.9795331955,37.4865951538],"type":"Point"}
}