{
  "type": "Feature",
  "properties": {
    "iso:country":"ES",
    "sg:address":"Carrer de Parellades, 4",
    "sg:city":"Viladecans",
    "sg:orig_category":"Abogados",
    "sg:phone":"+34 936 59 00 06",
    "sg:postcode":"08840",
    "sg:province":"Barcelona",
    "wof:name":"Rodriguez Sabariego Fernando",
    "wof:placetype":"venue"
},
  "geometry": {"coordinates":[2.0235219002,41.3129425049],"type":"Point"}
}