{
  "type": "Feature",
  "properties": {
    "addr:full":"Calle de Zurbano, 11 Madrid Madrid 28010",
    "addr:housenumber":"11",
    "addr:postcode":"madrid;28010",
    "addr:street":"Calle De Zurbano",
    "iso:country":"ES",
    "sg:address":"Calle de Zurbano, 11",
    "sg:city":"Madrid",
    "sg:orig_category":"Procuradores",
    "sg:phone":"+34 913 19 17 66",
    "sg:postcode":"28010",
    "sg:province":"Madrid",
    "wof:name":"Alvarez Diez Javier",
    "wof:placetype":"venue"
},
  "geometry": {"coordinates":[-3.6937270164,40.4284515381],"type":"Point"}
}