{
  "type": "Feature",
  "properties": {
    "addr:full":"Avda San Rogelio, 11 Illora Granada 18260",
    "addr:housenumber":"11",
    "addr:postcode":"18260",
    "addr:street":"Avda San Rogelio",
    "iso:country":"ES",
    "sg:address":"Avda San Rogelio, 11",
    "sg:city":"Illora",
    "sg:orig_category":"Loter\u00cda Y T\u00d3mbola",
    "sg:phone":"+34 958 46 42 41",
    "sg:postcode":"18260",
    "sg:province":"Granada",
    "wof:name":"Gonzalez Serradilla Luis",
    "wof:placetype":"venue"
},
  "geometry": {"coordinates":[-3.8781991005,37.2863998413],"type":"Point"}
}