{
  "type": "Feature",
  "properties": {
    "iso:country":"ES",
    "sg:address":"Vei. Franciac, S/n",
    "sg:city":"Caldes Malavella",
    "sg:orig_category":"Hormigonados",
    "sg:phone":"+34 972 47 08 72",
    "sg:postcode":"17455",
    "sg:province":"Girona",
    "wof:name":"Formigons Girona S.a.",
    "wof:placetype":"venue"
},
  "geometry": {"coordinates":[2.8018240929,41.8385505676],"type":"Point"}
}