{
  "type": "Feature",
  "properties": {
    "iso:country":"ES",
    "sg:address":"Trva Rioja (de La), 5",
    "sg:city":"Najera",
    "sg:orig_category":"Herramientas Manuales (fabricaci\u00d3n, Al Por Mayor)",
    "sg:phone":"+34 941 36 04 69",
    "sg:postcode":"26300",
    "sg:province":"La Rioja",
    "wof:name":"Herramientas Leitz S.l.",
    "wof:placetype":"venue"
},
  "geometry": {"coordinates":[-2.7314119339,42.4184303284],"type":"Point"}
}