{
  "type": "Feature",
  "properties": {
    "addr:full":"Avda Pedro Morales Deniz, 193 Cardones Las Palmas 35400",
    "addr:housenumber":"193",
    "addr:postcode":"35400",
    "addr:street":"Avda Pedro Morales Deniz",
    "iso:country":"ES",
    "sg:address":"Avda Pedro Morales Deniz, 193",
    "sg:city":"Cardones",
    "sg:orig_category":"Sociedades, Compa\u00d1\u00cdas Aseguradoras",
    "sg:phone":"+34 928 62 14 08",
    "sg:postcode":"35400",
    "sg:province":"Las Palmas",
    "wof:name":"Mapfre Guanarteme Compa\u00d1ia De Seguros Y Reaseguros De Canarias S.a.",
    "wof:placetype":"venue"
},
  "geometry": {"coordinates":[-15.5152540207,28.1135654449],"type":"Point"}
}