{
  "type": "Feature",
  "properties": {
    "addr:full":"Avgd Municipi, 3 Benidorm Alicante 03500",
    "addr:housenumber":"3",
    "addr:postcode":"03500",
    "addr:street":"Municipi",
    "iso:country":"ES",
    "sg:address":"Avgd Municipi, 3",
    "sg:city":"Benidorm",
    "sg:orig_category":"Zapatos (al Por Menor)",
    "sg:phone":"+34 966 80 78 89",
    "sg:postcode":"03500",
    "sg:province":"Alicante",
    "wof:name":"Amador Gil Manuel",
    "wof:placetype":"venue"
},
  "geometry": {"coordinates":[-0.1220417991,38.5456695557],"type":"Point"}
}