{
  "type": "Feature",
  "properties": {
    "iso:country":"ES",
    "sg:address":"Rua Joaquin Costa, 64",
    "sg:city":"Pontevedra",
    "sg:orig_category":"Albergues",
    "sg:phone":"+34 986 85 51 51",
    "sg:postcode":"36004",
    "sg:province":"Pontevedra",
    "wof:name":"Patronato Da Fundacion Monte Do Gozo",
    "wof:placetype":"venue"
},
  "geometry": {"coordinates":[-8.6378393173,42.4278373718],"type":"Point"}
}