{
  "type": "Feature",
  "properties": {
    "iso:country":"ES",
    "sg:address":"Calle de Duques De Najera, 68",
    "sg:city":"Logro\u00f1o",
    "sg:orig_category":"Postigos, Persianas Y Celos\u00cdas",
    "sg:phone":"+34 941 21 47 59",
    "sg:postcode":"26005",
    "sg:province":"La Rioja",
    "wof:name":"Persianas Joymi S.l.",
    "wof:placetype":"venue"
},
  "geometry": {"coordinates":[-2.4567401409,42.4599685669],"type":"Point"}
}