{
  "type": "Feature",
  "properties": {
    "addr:full":"Rua Castelao, 60 Grove Pontevedra 36980",
    "addr:housenumber":"60",
    "addr:postcode":"36980",
    "addr:street":"Rua Castelao;Grove Pontevedra",
    "iso:country":"ES",
    "sg:address":"Rua Castelao, 60",
    "sg:city":"Grove",
    "sg:orig_category":"Hoteles",
    "sg:phone":"+34 986 73 09 19",
    "sg:postcode":"36980",
    "sg:province":"Pontevedra",
    "wof:name":"Casa Campa\u00d1a S.l.",
    "wof:placetype":"venue"
},
  "geometry": {"coordinates":[-8.8584403992,42.4902229309],"type":"Point"}
}