{
  "type": "Feature",
  "properties": {
    "addr:full":"Plaz Constitucion, 1 Puerto Cruz Santa Cruz De Tenerife 38400",
    "addr:postcode":"38400",
    "addr:street":"Constitucion 1 Puerto Cruz",
    "iso:country":"ES",
    "sg:address":"Plaz Constitucion, 1",
    "sg:city":"Puerto Cruz",
    "sg:orig_category":"Inmobiliaria (agencias)",
    "sg:phone":"+34 922 38 17 69",
    "sg:postcode":"38400",
    "sg:province":"Santa Cruz De Tenerife",
    "wof:name":"Comunidad De Bienes Inmobiliaria Sommer",
    "wof:placetype":"venue"
},
  "geometry": {"coordinates":[-16.5473842621,28.4141807556],"type":"Point"}
}