{
  "type": "Feature",
  "properties": {
    "addr:full":"Avda Ribera De Erandio, 5 Altzaga Vizcaya 48950",
    "addr:housenumber":"5",
    "addr:postcode":"48950",
    "addr:street":"Avda Ribera De Erandio",
    "iso:country":"ES",
    "sg:address":"Avda Ribera De Erandio, 5",
    "sg:city":"Altzaga",
    "sg:orig_category":"Mec\u00c1nico Del Autom\u00d3vil",
    "sg:phone":"+34 944 17 51 16",
    "sg:postcode":"48950",
    "sg:province":"Vizcaya",
    "wof:name":"Alfavi S. A.",
    "wof:placetype":"venue"
},
  "geometry": {"coordinates":[-2.9790885448,43.3109664917],"type":"Point"}
}