{
  "type": "Feature",
  "properties": {
    "iso:country":"ES",
    "sg:address":"Carrer de Salzes, 21",
    "sg:city":"S. Boi Llobregat",
    "sg:orig_category":"Delegados, Agentes De Tr\u00c1nsito, Auxiliares De Transporte Internacional",
    "sg:phone":"+34 936 30 29 62",
    "sg:postcode":"08830",
    "sg:province":"Barcelona",
    "wof:name":"Colom Florencio Jose Maria",
    "wof:placetype":"venue"
},
  "geometry": {"coordinates":[2.0207910538,41.3499679565],"type":"Point"}
}