{
  "type": "Feature",
  "properties": {
    "addr:full":"Calle de Sebastian Fernandez De Leceta, 11 Vitoria-gasteiz \u00c1lava 01009",
    "addr:housenumber":"11",
    "addr:postcode":"01009",
    "addr:street":"Calle De Sebastian Fernandez De Leceta",
    "iso:country":"ES",
    "sg:address":"Calle de Sebastian Fernandez De Leceta, 11",
    "sg:city":"Vitoria-gasteiz",
    "sg:orig_category":"Bancos",
    "sg:phone":"+34 945 22 87 08",
    "sg:postcode":"01009",
    "sg:province":"\u00c1lava",
    "wof:name":"Banco De Vasconia",
    "wof:placetype":"venue"
},
  "geometry": {"coordinates":[-2.6825370789,42.8514060974],"type":"Point"}
}