{
  "type": "Feature",
  "properties": {
    "addr:full":"Avda Argentinita (de La), 14 Granada Granada 18014",
    "addr:housenumber":"14",
    "addr:postcode":"18014",
    "addr:street":"Avda Argentinita De La",
    "iso:country":"ES",
    "sg:address":"Avda Argentinita (de La), 14",
    "sg:city":"Granada",
    "sg:orig_category":"Promotores Constructores",
    "sg:phone":"+34 958 80 68 70",
    "sg:postcode":"18014",
    "sg:province":"Granada",
    "wof:name":"Empresas De Transformacion Agraria",
    "wof:placetype":"venue"
},
  "geometry": {"coordinates":[-3.6155118942,37.19713974],"type":"Point"}
}