{
  "type": "Feature",
  "properties": {
    "iso:country":"ES",
    "sg:address":"Calle de Doctor Fleming, 3",
    "sg:city":"Calahorra",
    "sg:orig_category":"Cuchiller\u00cda (al Por Menor)",
    "sg:phone":"+34 941 13 56 45",
    "sg:postcode":"26500",
    "sg:province":"La Rioja",
    "wof:name":"Alvarez Toledo Raul",
    "wof:placetype":"venue"
},
  "geometry": {"coordinates":[-1.9630515575,42.3023529053],"type":"Point"}
}