{
  "type": "Feature",
  "properties": {
    "iso:country":"ES",
    "sg:address":"Rua Anxel Baltar (de), 2",
    "sg:city":"Santiago De Compostela",
    "sg:orig_category":"Inmobiliaria (agencias)",
    "sg:phone":"+34 981 52 54 06",
    "sg:postcode":"15706",
    "sg:province":"La Coru\u00f1a",
    "wof:name":"Comunidad De Propietarios Anxel Baltar Ii",
    "wof:placetype":"venue"
},
  "geometry": {"coordinates":[-8.5558824539,42.8725318909],"type":"Point"}
}