{
  "type": "Feature",
  "properties": {
    "iso:country":"ES",
    "sg:address":"Calle de San Jaime, 35",
    "sg:city":"Onil",
    "sg:orig_category":"Cristaler\u00cdas",
    "sg:phone":"+34 966 55 75 02",
    "sg:postcode":"03430",
    "sg:province":"Alicante",
    "wof:name":"Fernandez Martin Antonio",
    "wof:placetype":"venue"
},
  "geometry": {"coordinates":[-0.6715769768,38.6308555603],"type":"Point"}
}