{
  "type": "Feature",
  "properties": {
    "addr:full":"Avda Constitucion, 44 Novelda Alicante 03660",
    "addr:housenumber":"44",
    "addr:postcode":"03660",
    "addr:street":"Avda Constitucion",
    "iso:country":"ES",
    "sg:address":"Avda Constitucion, 44",
    "sg:city":"Novelda",
    "sg:orig_category":"Ropa Para Se\u00d1oras Y Caballeros (al Por Menor)",
    "sg:phone":"+34 965 60 28 65",
    "sg:postcode":"03660",
    "sg:province":"Alicante",
    "wof:name":"Lara Textil-hiper S.l.",
    "wof:placetype":"venue"
},
  "geometry": {"coordinates":[-0.7636349797,38.3824691772],"type":"Point"}
}