{
  "type": "Feature",
  "properties": {
    "addr:full":"Calle de Markosene Kalea, 3 Trobika Vizcaya 48100",
    "addr:housenumber":"3",
    "addr:postcode":"48100",
    "addr:street":"Calle De Markosene Kalea",
    "iso:country":"ES",
    "sg:address":"Calle de Markosene Kalea, 3",
    "sg:city":"Trobika",
    "sg:orig_category":"Maquinaria Para Industrias Diversas",
    "sg:phone":"+34 946 74 00 65",
    "sg:postcode":"48100",
    "sg:province":"Vizcaya",
    "wof:name":"Rent Obra Alquiler Maquinaria De Obra S.l",
    "wof:placetype":"venue"
},
  "geometry": {"coordinates":[-2.8507039547,43.3569412231],"type":"Point"}
}