{
  "type": "Feature",
  "properties": {
    "iso:country":"ES",
    "sg:address":"Vega De Porrillas, 84",
    "sg:city":"Alcolea",
    "sg:orig_category":"Material Y Herramientas Agr\u00cdcolas",
    "sg:phone":"+34 957 32 11 70",
    "sg:postcode":"14610",
    "sg:province":"C\u00f3rdoba",
    "wof:name":"Fernandez Cabello Pedro",
    "wof:placetype":"venue"
},
  "geometry": {"coordinates":[-4.6766438484,37.9309043884],"type":"Point"}
}