{
  "type": "Feature",
  "properties": {
    "addr:full":"Av La Paz, S/n Onil Alicante 03430",
    "addr:housenumber":"s / n",
    "addr:postcode":"03430",
    "addr:street":"Av La Paz",
    "iso:country":"ES",
    "sg:address":"Av La Paz, S/n",
    "sg:city":"Onil",
    "sg:orig_category":"Asilos De Ancianos. Centros Privados",
    "sg:phone":"+34 965 56 56 88",
    "sg:postcode":"03430",
    "sg:province":"Alicante",
    "wof:name":"Atencion Social De Estancias Residenciales S.a.",
    "wof:placetype":"venue"
},
  "geometry": {"coordinates":[-0.6770418882,38.6278038025],"type":"Point"}
}