{
  "type": "Feature",
  "properties": {
    "addr:full":"Sant Roc, 1 Vall Bianya Girona 17813",
    "addr:postcode":"17813",
    "iso:country":"ES",
    "sg:address":"Sant Roc, 1",
    "sg:city":"Vall Bianya",
    "sg:orig_category":"Arenas, Guijarros Y Granulados",
    "sg:phone":"+34 972 29 10 11",
    "sg:postcode":"17813",
    "sg:province":"Girona",
    "wof:name":"Triturados La Canya S. A.",
    "wof:placetype":"venue"
},
  "geometry": {"coordinates":[2.4543850422,42.2110366821],"type":"Point"}
}