{
  "type": "Feature",
  "properties": {
    "iso:country":"ES",
    "sg:address":"Carrer de Pare Miquel De Sarria, 10",
    "sg:city":"Barcelona",
    "sg:orig_category":"Bazares, Art\u00cdculos De Limpieza Y De Cocina (al Por Menor)",
    "sg:phone":"+34 932 80 45 39",
    "sg:postcode":"08034",
    "sg:province":"Barcelona",
    "wof:name":"Torrecilla Ribalta Monica",
    "wof:placetype":"venue"
},
  "geometry": {"coordinates":[2.1203360558,41.4000930786],"type":"Point"}
}