{
  "type": "Feature",
  "properties": {
    "iso:country":"ES",
    "sg:address":"Cmno Gri\u00d1on (de), Km. 0001,5",
    "sg:city":"Parla",
    "sg:orig_category":"Piedra Natural",
    "sg:phone":"+34 916 99 42 27",
    "sg:postcode":"28980",
    "sg:province":"Madrid",
    "wof:name":"Sanchez Rubio Luis",
    "wof:placetype":"venue"
},
  "geometry": {"coordinates":[-3.7734539509,40.237449646],"type":"Point"}
}