{
  "type": "Feature",
  "properties": {
    "addr:full":"Pje Los Arenales, 10 Jerte C\u00e1ceres 10612",
    "addr:housenumber":"10",
    "addr:postcode":"10612",
    "addr:street":"Pje Los Arenales;Ca\u0301Ceres",
    "iso:country":"ES",
    "sg:address":"Pje Los Arenales, 10",
    "sg:city":"Jerte",
    "sg:orig_category":"Cajas Y Embalajes De Madera",
    "sg:phone":"+34 927 47 00 04",
    "sg:postcode":"10612",
    "sg:province":"C\u00e1ceres",
    "wof:name":"Envases Del Jerte Soc. Coop.",
    "wof:placetype":"venue"
},
  "geometry": {"coordinates":[-5.7737941742,40.2098693848],"type":"Point"}
}