{
  "type": "Feature",
  "properties": {
    "iso:country":"ES",
    "sg:address":"Pol. Ind. El Prao, S/n",
    "sg:city":"Chelva",
    "sg:orig_category":"Agricultura: Abastecimiento Y Cosechado (negocio)",
    "sg:phone":"+34 962 10 08 26",
    "sg:postcode":"46176",
    "sg:province":"Valencia",
    "wof:name":"Agricola Catolica De Chelva S.c.v.",
    "wof:placetype":"venue"
},
  "geometry": {"coordinates":[-1.0011901855,39.7918548584],"type":"Point"}
}