{
  "type": "Feature",
  "properties": {
    "iso:country":"ES",
    "sg:address":"Bda. Guadalobon, S/n",
    "sg:city":"Estepona",
    "sg:orig_category":"Confiter\u00cda, Galletas Y Pastas, Chocolater\u00cda (al Por Mayor)",
    "sg:phone":"+34 952 79 29 47",
    "sg:postcode":"29680",
    "sg:province":"M\u00e1laga",
    "wof:name":"Monasterio De Santa Maria Del Monte Carmelo Y San Elias Profeta",
    "wof:placetype":"venue"
},
  "geometry": {"coordinates":[-5.1839118004,36.433052063],"type":"Point"}
}