{
  "type": "Feature",
  "properties": {
    "addr:full":"Carrer de Moli, 55 Hospitalet Llobregat Barcelona 08906",
    "addr:housenumber":"55",
    "addr:postcode":"08906",
    "addr:street":"Carrer De Moli",
    "iso:country":"ES",
    "sg:address":"Carrer de Moli, 55",
    "sg:city":"Hospitalet Llobregat",
    "sg:orig_category":"Administradores De Bienes Y Delegados De Comunidades De Propietarios",
    "sg:phone":"+34 934 37 60 00",
    "sg:postcode":"08906",
    "sg:province":"Barcelona",
    "wof:name":"Viatges Ancare S.l.",
    "wof:placetype":"venue"
},
  "geometry": {"coordinates":[2.1010069847,41.3686103821],"type":"Point"}
}