{
  "type": "Feature",
  "properties": {
    "iso:country":"ES",
    "sg:address":"Plaz Mayor, 3",
    "sg:city":"Fuentepelayo",
    "sg:orig_category":"Cajas Para Embalar",
    "sg:phone":"+34 921 57 40 53",
    "sg:postcode":"40260",
    "sg:province":"Segovia",
    "wof:name":"Caja Rural De Fuentepelayo-sociedad Cooperativa De Credito Ltda.",
    "wof:placetype":"venue"
},
  "geometry": {"coordinates":[-4.1764287949,41.2216300964],"type":"Point"}
}