{
  "type": "Feature",
  "properties": {
    "iso:country":"ES",
    "sg:address":"Calle de Maestrat, 4",
    "sg:city":"Sant Mateu",
    "sg:orig_category":"Delegados, Agentes De Tr\u00c1nsito, Auxiliares De Transporte Internacional",
    "sg:phone":"+34 964 41 60 30",
    "sg:postcode":"12170",
    "sg:province":"Castell\u00f3n",
    "wof:name":"Transportes San Mateo S.l.",
    "wof:placetype":"venue"
},
  "geometry": {"coordinates":[0.1785899997,40.4668502808],"type":"Point"}
}