{
  "type": "Feature",
  "properties": {
    "addr:full":"Calle de Sagasta, 9 Logro\u00f1o La Rioja 26001",
    "addr:housenumber":"9",
    "addr:postcode":"26001",
    "addr:street":"Calle De Sagasta;Rioja",
    "iso:country":"ES",
    "sg:address":"Calle de Sagasta, 9",
    "sg:city":"Logro\u00f1o",
    "sg:orig_category":"Electrodom\u00c9sticos (al Por Menor)",
    "sg:phone":"+34 941 23 02 62",
    "sg:postcode":"26001",
    "sg:province":"La Rioja",
    "wof:name":"Soripa S. L.",
    "wof:placetype":"venue"
},
  "geometry": {"coordinates":[-2.446778059,42.4662475586],"type":"Point"}
}