{
  "type": "Feature",
  "properties": {
    "iso:country":"ES",
    "sg:address":"Calle de Pintor Benedito, 3",
    "sg:city":"Valencia",
    "sg:orig_category":"Complementos De Vestir (al Por Menor)",
    "sg:phone":"+34 963 41 63 91",
    "sg:postcode":"46007",
    "sg:province":"Valencia",
    "wof:name":"Tajian Iturralde Isabel",
    "wof:placetype":"venue"
},
  "geometry": {"coordinates":[-0.3824549913,39.4655151367],"type":"Point"}
}