{
  "type": "Feature",
  "properties": {
    "addr:full":"Avda Coru\u00d1a (da), 287 Lugo Lugo 27003",
    "addr:housenumber":"287",
    "addr:postcode":"27003",
    "addr:street":"Avda Corun\u0303A Da",
    "iso:country":"ES",
    "sg:address":"Avda Coru\u00d1a (da), 287",
    "sg:city":"Lugo",
    "sg:orig_category":"Electrodom\u00c9sticos (al Por Menor)",
    "sg:phone":"+34 982 20 33 48",
    "sg:postcode":"27003",
    "sg:province":"Lugo",
    "wof:name":"Idea Lugo S.l.",
    "wof:placetype":"venue"
},
  "geometry": {"coordinates":[-7.5656890869,43.0234069824],"type":"Point"}
}