{
  "type": "Feature",
  "properties": {
    "addr:full":"Pl Cos, D'es, 1 Manacor Islas Baleares 07500",
    "addr:housenumber":"1",
    "addr:postcode":"07500",
    "addr:street":"Pl Cos D'Es",
    "iso:country":"ES",
    "sg:address":"Pl Cos, D'es, 1",
    "sg:city":"Manacor",
    "sg:orig_category":"Ropa Para Se\u00d1oras Y Caballeros (al Por Menor)",
    "sg:phone":"+34 971 55 13 26",
    "sg:postcode":"07500",
    "sg:province":"Islas Baleares",
    "wof:name":"Rigo Nicolau Francisca",
    "wof:placetype":"venue"
},
  "geometry": {"coordinates":[3.2113089561,39.5681877136],"type":"Point"}
}