{
  "type": "Feature",
  "properties": {
    "addr:full":"Calle de San Mateo, 23 Picazo Cuenca 16211",
    "addr:housenumber":"23",
    "addr:postcode":"16211",
    "addr:street":"Calle De San Mateo",
    "iso:country":"ES",
    "sg:address":"Calle de San Mateo, 23",
    "sg:city":"Picazo",
    "sg:orig_category":"Empresas De Demolici\u00d3n",
    "sg:phone":"+34 969 38 03 07",
    "sg:postcode":"16211",
    "sg:province":"Cuenca",
    "wof:name":"Excavaciones Y Derribos Ruiz S.l.",
    "wof:placetype":"venue"
},
  "geometry": {"coordinates":[-2.0889029503,39.4452896118],"type":"Point"}
}