{
  "type": "Feature",
  "properties": {
    "addr:full":"Ctra Matahijas, S/n Guillena Sevilla 41210",
    "addr:housenumber":"s / n",
    "addr:postcode":"41210",
    "addr:street":"Ctra Matahijas",
    "iso:country":"ES",
    "sg:address":"Ctra Matahijas, S/n",
    "sg:city":"Guillena",
    "sg:orig_category":"Producci\u00d3n, Venta De Productos De Agricultura Biol\u00d3gica",
    "sg:phone":"+34 955 78 51 11",
    "sg:postcode":"41210",
    "sg:province":"Sevilla",
    "wof:name":"Ternero Pablo-romero Guadalupe",
    "wof:placetype":"venue"
},
  "geometry": {"coordinates":[-6.0553040504,37.5477600098],"type":"Point"}
}