{
  "type": "Feature",
  "properties": {
    "iso:country":"ES",
    "sg:address":"Calle de Ancha, 64",
    "sg:city":"Calzada Calatrava",
    "sg:orig_category":"Inmobiliaria (agencias)",
    "sg:phone":"+34 926 87 51 59",
    "sg:postcode":"13370",
    "sg:province":"Ciudad Real",
    "wof:name":"Rios Lebratos S.l.",
    "wof:placetype":"venue"
},
  "geometry": {"coordinates":[-3.7740778923,38.7048454285],"type":"Point"}
}