{
  "type": "Feature",
  "properties": {
    "addr:full":"Carrer de Portalet, 11 Granollers Barcelona 08401",
    "addr:housenumber":"11",
    "addr:postcode":"08401",
    "addr:street":"Carrer De Portalet",
    "iso:country":"ES",
    "sg:address":"Carrer de Portalet, 11",
    "sg:city":"Granollers",
    "sg:orig_category":"Carnicer\u00cdas, Carnicer\u00cdas",
    "sg:phone":"+34 938 79 31 54",
    "sg:postcode":"08401",
    "sg:province":"Barcelona",
    "wof:name":"Montalban Mateos Encarnacion",
    "wof:placetype":"venue"
},
  "geometry": {"coordinates":[2.2876238823,41.6074638367],"type":"Point"}
}