{
  "type": "Feature",
  "properties": {
    "iso:country":"ES",
    "sg:address":"Calle de Naranjo, 25",
    "sg:city":"Madrid",
    "sg:orig_category":"Chapister\u00cda",
    "sg:phone":"+34 913 11 05 58",
    "sg:postcode":"28039",
    "sg:province":"Madrid",
    "wof:name":"Autoviajes Prada S. L.",
    "wof:placetype":"venue"
},
  "geometry": {"coordinates":[-3.7007601261,40.4611320496],"type":"Point"}
}