{
  "type": "Feature",
  "properties": {
    "iso:country":"ES",
    "sg:address":"Calle de Curato, S/n",
    "sg:city":"Escalona Prado",
    "sg:orig_category":"Iglesia Cat\u00d3lica",
    "sg:phone":"+34 921 57 01 82",
    "sg:postcode":"40350",
    "sg:province":"Segovia",
    "wof:name":"Obispado Segovia",
    "wof:placetype":"venue"
},
  "geometry": {"coordinates":[-4.1225667,41.1687850952],"type":"Point"}
}