{
  "type": "Feature",
  "properties": {
    "addr:full":"Avda Rafael Cabrera, 8 Palmas De Gran Canaria Las Palmas 35002",
    "addr:housenumber":"8",
    "addr:postcode":"35002",
    "addr:street":"Avda Rafael Cabrera",
    "iso:country":"ES",
    "sg:address":"Avda Rafael Cabrera, 8",
    "sg:city":"Palmas De Gran Canaria",
    "sg:orig_category":"Abogados",
    "sg:phone":"+34 928 36 63 71",
    "sg:postcode":"35002",
    "sg:province":"Las Palmas",
    "wof:name":"Fernandez Villamarin Antonio",
    "wof:placetype":"venue"
},
  "geometry": {"coordinates":[-15.4141283035,28.1050758362],"type":"Point"}
}