{
  "type": "Feature",
  "properties": {
    "addr:full":"Calle de Alpedrete, 24 Madrid Madrid 28045",
    "addr:housenumber":"24",
    "addr:postcode":"madrid;28045",
    "addr:street":"Calle De Alpedrete",
    "iso:country":"ES",
    "sg:address":"Calle de Alpedrete, 24",
    "sg:city":"Madrid",
    "sg:orig_category":"Laboratorios Farmac\u00c9uticos",
    "sg:phone":"+34 915 27 95 55",
    "sg:postcode":"28045",
    "sg:province":"Madrid",
    "wof:name":"Industria Quimica Hispano Norteamericana S.a.",
    "wof:placetype":"venue"
},
  "geometry": {"coordinates":[-3.682300806,40.3992156982],"type":"Point"}
}