{
  "type": "Feature",
  "properties": {
    "addr:full":"Pla\u00c7 Dalt Els Penyals, 14 Ciutadella Menorca Islas Baleares 07760",
    "addr:housenumber":"14",
    "addr:postcode":"07760",
    "addr:street":"Penyals",
    "iso:country":"ES",
    "sg:address":"Pla\u00c7 Dalt Els Penyals, 14",
    "sg:city":"Ciutadella Menorca",
    "sg:orig_category":"Restaurantes",
    "sg:phone":"+34 971 48 26 14",
    "sg:postcode":"07760",
    "sg:province":"Islas Baleares",
    "wof:name":"Senocal S.l.",
    "wof:placetype":"venue"
},
  "geometry": {"coordinates":[3.8363521099,40.0059394836],"type":"Point"}
}