{
  "type": "Feature",
  "properties": {
    "addr:full":"Plaz Estacion (la), S/n Unquera Cantabria 39560",
    "addr:postcode":"39560",
    "addr:street":"Estacion La S / N",
    "iso:country":"ES",
    "sg:address":"Plaz Estacion (la), S/n",
    "sg:city":"Unquera",
    "sg:orig_category":"Caf\u00c9s, Bares, Cervecer\u00cdas",
    "sg:phone":"+34 942 71 70 53",
    "sg:postcode":"39560",
    "sg:province":"Cantabria",
    "wof:name":"Fernandez Soberon Manuel",
    "wof:placetype":"venue"
},
  "geometry": {"coordinates":[-4.5151238441,43.3745231628],"type":"Point"}
}