{
  "type": "Feature",
  "properties": {
    "addr:full":"Calle de Saturnino Gonzalez, S/n Fresno El Viejo Valladolid 47480",
    "addr:housenumber":"/ n",
    "addr:postcode":"47480",
    "addr:street":"Calle De Saturnino Gonzalez S",
    "iso:country":"ES",
    "sg:address":"Calle de Saturnino Gonzalez, S/n",
    "sg:city":"Fresno El Viejo",
    "sg:orig_category":"Enfermeras: Consultas, Atenci\u00d3n A Domicilio",
    "sg:phone":"+34 983 86 30 64",
    "sg:postcode":"47480",
    "sg:province":"Valladolid",
    "wof:name":"Sanchez Rodriguez Jose Luis",
    "wof:placetype":"venue"
},
  "geometry": {"coordinates":[-5.1435627937,41.1956558228],"type":"Point"}
}