{
  "type": "Feature",
  "properties": {
    "iso:country":"ES",
    "sg:address":"Calle de Geranio, 14",
    "sg:city":"Bormujos",
    "sg:orig_category":"Guarder\u00cdas",
    "sg:phone":"+34 955 72 46 59",
    "sg:postcode":"41930",
    "sg:province":"Sevilla",
    "wof:name":"Guarderia Las Flores S.l.",
    "wof:placetype":"venue"
},
  "geometry": {"coordinates":[-6.0712513924,37.3738822937],"type":"Point"}
}