{
  "type": "Feature",
  "properties": {
    "addr:full":"Avda Gaviotas (las), S/n Urbanizacion Roquetas De Mar Almer\u00eda 04740",
    "addr:postcode":"04740",
    "addr:street":"Avda Gaviotas Las S / N Urbanizacion Roquetas De Mar Almeri\u0301A",
    "iso:country":"ES",
    "sg:address":"Avda Gaviotas (las), S/n",
    "sg:city":"Urbanizacion Roquetas De Mar",
    "sg:orig_category":"Hoteles",
    "sg:phone":"+34 950 33 49 50",
    "sg:postcode":"04740",
    "sg:province":"Almer\u00eda",
    "wof:name":"Copropietarios Bahia Serena S.l.",
    "wof:placetype":"venue"
},
  "geometry": {"coordinates":[-2.6233940125,36.7270851135],"type":"Point"}
}