{
  "type": "Feature",
  "properties": {
    "iso:country":"ES",
    "sg:address":"Calle de Bethencourt Alfonso, 33",
    "sg:city":"Santa Cruz De Tenerife",
    "sg:orig_category":"Centros P\u00dablicos De Formaci\u00d3n Profesional Y T\u00c9cnica",
    "sg:phone":"+34 922 28 95 55",
    "sg:postcode":"38002",
    "sg:province":"Santa Cruz De Tenerife",
    "wof:name":"Colegio De Administradores De Fincas",
    "wof:placetype":"venue"
},
  "geometry": {"coordinates":[-16.2504882812,28.4675197601],"type":"Point"}
}