{
  "type": "Feature",
  "properties": {
    "addr:full":"Calle de Argentina, 8 Torredonjimeno Ja\u00e9n 23650",
    "addr:housenumber":"8",
    "addr:postcode":"23650",
    "addr:street":"Calle De Argentina",
    "iso:country":"ES",
    "sg:address":"Calle de Argentina, 8",
    "sg:city":"Torredonjimeno",
    "sg:orig_category":"Molduras, Junquillos, Listones Y Molduras Perforadas",
    "sg:phone":"+34 953 57 17 69",
    "sg:postcode":"23650",
    "sg:province":"Ja\u00e9n",
    "wof:name":"Eurotel Sur",
    "wof:placetype":"venue"
},
  "geometry": {"coordinates":[-3.9350726604,37.7602005005],"type":"Point"}
}