{
  "type": "Feature",
  "properties": {
    "iso:country":"ES",
    "sg:address":"Calle de General Arrando, 8",
    "sg:city":"Madrid",
    "sg:orig_category":"Mercer\u00cda, Lencer\u00cda (al Por Menor)",
    "sg:phone":"+34 914 48 26 25",
    "sg:postcode":"28010",
    "sg:province":"Madrid",
    "wof:name":"Eli Y Liss S.c.",
    "wof:placetype":"venue"
},
  "geometry": {"coordinates":[-3.6963911057,40.4315757751],"type":"Point"}
}