{
  "type": "Feature",
  "properties": {
    "iso:country":"ES",
    "sg:address":"Calle de Carmen, 6",
    "sg:city":"Barrios",
    "sg:orig_category":"Negocio De Materiales De Construcci\u00d3n",
    "sg:phone":"+34 956 62 01 28",
    "sg:postcode":"11370",
    "sg:province":"C\u00e1diz",
    "wof:name":"Ruiz Troyano S.l.",
    "wof:placetype":"venue"
},
  "geometry": {"coordinates":[-5.4936623573,36.1847343445],"type":"Point"}
}