{
  "type": "Feature",
  "properties": {
    "iso:country":"ES",
    "sg:address":"Calle de San Pedro, 7",
    "sg:city":"Binefar",
    "sg:orig_category":"Art\u00cdculos De Regalo (al Por Menor)",
    "sg:phone":"+34 974 43 11 68",
    "sg:postcode":"22500",
    "sg:province":"Huesca",
    "wof:name":"Joyeria Detalles S.l.",
    "wof:placetype":"venue"
},
  "geometry": {"coordinates":[0.2923280001,41.8507118225],"type":"Point"}
}