{
  "type": "Feature",
  "properties": {
    "addr:full":"C/ Fra Pere Balaguer, 55 Elche Alicante 03202",
    "addr:housenumber":"55",
    "addr:postcode":"03202",
    "addr:street":"C / Fra Pere Balaguer",
    "iso:country":"ES",
    "sg:address":"C/ Fra Pere Balaguer, 55",
    "sg:city":"Elche",
    "sg:orig_category":"Peluqueros: De Se\u00d1oras",
    "sg:phone":"+34 966 61 17 98",
    "sg:postcode":"03202",
    "sg:province":"Alicante",
    "wof:name":"Fraile Guerrero Raquel",
    "wof:placetype":"venue"
},
  "geometry": {"coordinates":[-0.6814529896,38.2705497742],"type":"Point"}
}