{
  "type": "Feature",
  "properties": {
    "iso:country":"ES",
    "sg:address":"Alam Rafael Mendez (de), S/n",
    "sg:city":"Sutullena",
    "sg:orig_category":"Hoteles",
    "sg:phone":"+34 968 47 05 99",
    "sg:postcode":"30800",
    "sg:province":"Murcia",
    "wof:name":"Hoteles De Murcia S.a.",
    "wof:placetype":"venue"
},
  "geometry": {"coordinates":[-1.6905640364,37.680557251],"type":"Point"}
}