{
  "type": "Feature",
  "properties": {
    "addr:full":"Barr El Puerto, 17 Puerto Vizcaya 48508",
    "addr:housenumber":"17",
    "addr:postcode":"48508",
    "addr:street":"El Puerto",
    "iso:country":"ES",
    "sg:address":"Barr El Puerto, 17",
    "sg:city":"Puerto",
    "sg:orig_category":"Comercio De Minerales, F\u00d3siles Y Conchas",
    "sg:phone":"+34 946 36 53 13",
    "sg:postcode":"48508",
    "sg:province":"Vizcaya",
    "wof:name":"Tajada Gil Eloy",
    "wof:placetype":"venue"
},
  "geometry": {"coordinates":[-3.090914011,43.3470497131],"type":"Point"}
}