{
  "type": "Feature",
  "properties": {
    "addr:full":"Calle de Gaztambide, 72 Madrid Madrid 28003",
    "addr:housenumber":"72",
    "addr:postcode":"madrid;28003",
    "addr:street":"Calle De Gaztambide",
    "iso:country":"ES",
    "sg:address":"Calle de Gaztambide, 72",
    "sg:city":"Madrid",
    "sg:orig_category":"Empresarios Y Productoras De Espect\u00c1culos",
    "sg:phone":"+34 914 41 44 96",
    "sg:postcode":"28003",
    "sg:province":"Madrid",
    "wof:name":"Padilla Gimeno Rafael",
    "wof:placetype":"venue"
},
  "geometry": {"coordinates":[-3.714977026,40.4399223328],"type":"Point"}
}