{
  "type": "Feature",
  "properties": {
    "addr:full":"C/ Rizal, 6 Ripollet Barcelona 08291",
    "addr:housenumber":"6",
    "addr:postcode":"08291",
    "addr:street":"C / Rizal",
    "iso:country":"ES",
    "sg:address":"C/ Rizal, 6",
    "sg:city":"Ripollet",
    "sg:orig_category":"Tapicer\u00cdas",
    "sg:phone":"+34 935 80 86 75",
    "sg:postcode":"08291",
    "sg:province":"Barcelona",
    "wof:name":"Diaz Duran Juan Carlos",
    "wof:placetype":"venue"
},
  "geometry": {"coordinates":[2.1627790928,41.4957809448],"type":"Point"}
}