{
  "type": "Feature",
  "properties": {
    "addr:full":"Calle de Fernando Calpena, 16 Palmas De Gran Canaria Las Palmas 35012",
    "addr:housenumber":"16",
    "addr:postcode":"35012",
    "addr:street":"Calle De Fernando Calpena",
    "iso:country":"ES",
    "sg:address":"Calle de Fernando Calpena, 16",
    "sg:city":"Palmas De Gran Canaria",
    "sg:orig_category":"Electricidad: Instaladores",
    "sg:phone":"+34 928 25 00 03",
    "sg:postcode":"35012",
    "sg:province":"Las Palmas",
    "wof:name":"Gonzalez Gonzalez Juan Manuel",
    "wof:placetype":"venue"
},
  "geometry": {"coordinates":[-15.4300756454,28.1143093109],"type":"Point"}
}