{
  "type": "Feature",
  "properties": {
    "addr:full":"Rbla Guipuscoa, 83 Barcelona Barcelona 08020",
    "addr:housenumber":"83",
    "addr:postcode":"08020",
    "addr:street":"Rbla Guipuscoa",
    "iso:country":"ES",
    "sg:address":"Rbla Guipuscoa, 83",
    "sg:city":"Barcelona",
    "sg:orig_category":"Cl\u00cdnicas Dentales",
    "sg:phone":"+34 932 78 31 85",
    "sg:postcode":"08020",
    "sg:province":"Barcelona",
    "wof:name":"Serrat Junca Pelayo",
    "wof:placetype":"venue"
},
  "geometry": {"coordinates":[2.1996660233,41.4186210632],"type":"Point"}
}