{
  "type": "Feature",
  "properties": {
    "addr:full":"Csri Candelaria, S/n Candelaria Santa Cruz De Tenerife 38700",
    "addr:housenumber":"s / n",
    "addr:postcode":"38700",
    "addr:street":"Candelaria",
    "iso:country":"ES",
    "sg:address":"Csri Candelaria, S/n",
    "sg:city":"Candelaria",
    "sg:classifiers":[
        {
            "category":"Communications",
            "type":"Services"
        }
    ],
    "sg:phone":"+34 922 41 84 85",
    "sg:postcode":"38700",
    "sg:province":"Santa Cruz De Tenerife",
    "sg:tags":[
        "televisiones",
        "y",
        "radio"
    ],
    "wof:name":"Medios Audiovisuales Y Publicitarios Canarios S.l.",
    "wof:placetype":"venue"
},
  "geometry": {"coordinates":[-17.7677326202,28.6805782318],"type":"Point"}
}