{
  "type": "Feature",
  "properties": {
    "iso:country":"ES",
    "sg:address":"Calle de Ponzano, 51",
    "sg:city":"Madrid",
    "sg:orig_category":"Molduras, Junquillos, Listones Y Molduras Perforadas",
    "sg:phone":"+34 913 99 24 23",
    "sg:postcode":"28003",
    "sg:province":"Madrid",
    "wof:name":"Suarez Mu\u00f1oz Jose",
    "wof:placetype":"venue"
},
  "geometry": {"coordinates":[-3.6992087364,40.4408035278],"type":"Point"}
}