{
  "type": "Feature",
  "properties": {
    "addr:full":"C/ Major Del Pla, 5 Elche Alicante 03201",
    "addr:housenumber":"5",
    "addr:postcode":"03201",
    "addr:street":"C / Major Del Pla",
    "iso:country":"ES",
    "sg:address":"C/ Major Del Pla, 5",
    "sg:city":"Elche",
    "sg:orig_category":"Abogados",
    "sg:phone":"+34 966 67 50 50",
    "sg:postcode":"03201",
    "sg:province":"Alicante",
    "wof:name":"Perez Ruiz Jose",
    "wof:placetype":"venue"
},
  "geometry": {"coordinates":[-0.7009819746,38.2631568909],"type":"Point"}
}