{
  "type": "Feature",
  "properties": {
    "addr:full":"Calle de Virgen Del Robledo, 85 Constantina Sevilla 41450",
    "addr:housenumber":"85",
    "addr:postcode":"41450",
    "addr:street":"Calle De Virgen Del Robledo",
    "iso:country":"ES",
    "sg:address":"Calle de Virgen Del Robledo, 85",
    "sg:city":"Constantina",
    "sg:orig_category":"Contenedores (mercanc\u00cdas)",
    "sg:phone":"+34 955 88 07 03",
    "sg:postcode":"41450",
    "sg:province":"Sevilla",
    "wof:name":"Mateo Nieto Manuel Jesus",
    "wof:placetype":"venue"
},
  "geometry": {"coordinates":[-5.6239848137,37.881401062],"type":"Point"}
}