{
  "type": "Feature",
  "properties": {
    "iso:country":"ES",
    "sg:address":"Av Verge Montserrat, 115",
    "sg:city":"Prat Llobregat",
    "sg:orig_category":"Industria Qu\u00cdmica",
    "sg:phone":"+34 933 79 51 92",
    "sg:postcode":"08820",
    "sg:province":"Barcelona",
    "wof:name":"Monton Luder Jose Maria",
    "wof:placetype":"venue"
},
  "geometry": {"coordinates":[2.094974041,41.325592041],"type":"Point"}
}