{
  "type": "Feature",
  "properties": {
    "iso:country":"ES",
    "sg:address":"Ctra Perales-albares, S/n",
    "sg:city":"Mondejar",
    "sg:orig_category":"Transportes Por V\u00cdas Navegables",
    "sg:phone":"+34 949 38 52 00",
    "sg:postcode":"19110",
    "sg:province":"Guadalajara",
    "wof:name":"Perez Torres Pedro",
    "wof:placetype":"venue"
},
  "geometry": {"coordinates":[-3.1068348885,40.3210334778],"type":"Point"}
}