{
  "type": "Feature",
  "properties": {
    "addr:full":"Calle de Pizarro, 31 Valencia Valencia 46004",
    "addr:housenumber":"31",
    "addr:postcode":"46004",
    "addr:street":"Calle De Pizarro",
    "iso:country":"ES",
    "sg:address":"Calle de Pizarro, 31",
    "sg:city":"Valencia",
    "sg:orig_category":"Caf\u00c9s, Bares, Cervecer\u00cdas",
    "sg:phone":"+34 963 94 29 48",
    "sg:postcode":"46004",
    "sg:province":"Valencia",
    "wof:name":"Negocios Hosteleria Reunidos S. L.",
    "wof:placetype":"venue"
},
  "geometry": {"coordinates":[-0.371273011,39.4664611816],"type":"Point"}
}