{
  "type": "Feature",
  "properties": {
    "addr:full":"Ptge Marimon, 23 Barcelona Barcelona 08021",
    "addr:housenumber":"23",
    "addr:postcode":"08021",
    "addr:street":"Ptge Marimon",
    "iso:country":"ES",
    "sg:address":"Ptge Marimon, 23",
    "sg:city":"Barcelona",
    "sg:orig_category":"Impuestos, Tesoro P\u00dablico",
    "sg:phone":"+34 932 01 80 44",
    "sg:postcode":"08021",
    "sg:province":"Barcelona",
    "wof:name":"Serigesa S.l.",
    "wof:placetype":"venue"
},
  "geometry": {"coordinates":[2.1480000019,41.3941993713],"type":"Point"}
}