{
  "type": "Feature",
  "properties": {
    "addr:full":"Rua Ervedelo, 36 Ourense Ourense 32002",
    "addr:housenumber":"36",
    "addr:postcode":"32002",
    "addr:street":"Rua Ervedelo",
    "iso:country":"ES",
    "sg:address":"Rua Ervedelo, 36",
    "sg:city":"Ourense",
    "sg:orig_category":"Ropa Para Ni\u00d1os (al Por Menor)",
    "sg:phone":"+34 988 24 94 17",
    "sg:postcode":"32002",
    "sg:province":"Ourense",
    "wof:name":"Lorenzo Iglesias Justa",
    "wof:placetype":"venue"
},
  "geometry": {"coordinates":[-7.8705720901,42.339641571],"type":"Point"}
}