{
  "type": "Feature",
  "properties": {
    "addr:full":"Calle de Conquistador Benito De Ba\u00d1os, 10 Cordoba C\u00f3rdoba 14007",
    "addr:housenumber":"10",
    "addr:postcode":"14007",
    "addr:street":"Calle De Conquistador Benito De Ban\u0303Os;Co\u0301Rdoba",
    "iso:country":"ES",
    "sg:address":"Calle de Conquistador Benito De Ba\u00d1os, 10",
    "sg:city":"Cordoba",
    "sg:orig_category":"Farmacias",
    "sg:phone":"+34 957 26 05 03",
    "sg:postcode":"14007",
    "sg:province":"C\u00f3rdoba",
    "wof:name":"Bravo Y Marquez, S.c.",
    "wof:placetype":"venue"
},
  "geometry": {"coordinates":[-4.7591438293,37.8922080994],"type":"Point"}
}