{
  "type": "Feature",
  "properties": {
    "iso:country":"ES",
    "sg:address":"Calle de Isle\u00d1o (el), S/n",
    "sg:city":"Arrecife",
    "sg:orig_category":"Plomeros",
    "sg:phone":"+34 928 81 39 70",
    "sg:postcode":"35500",
    "sg:province":"Las Palmas",
    "wof:name":"Camacho Hernandez Antonio",
    "wof:placetype":"venue"
},
  "geometry": {"coordinates":[-13.5579090118,28.966550827],"type":"Point"}
}