{
  "type": "Feature",
  "properties": {
    "iso:country":"ES",
    "sg:address":"C. Guetara (p I Villarrosa), 32",
    "sg:city":"Malaga",
    "sg:orig_category":"Agencias Y Asesores De Publicidad",
    "sg:phone":"+34 952 23 93 09",
    "sg:postcode":"29004",
    "sg:province":"M\u00e1laga",
    "sg:website":"www.darkbluesl.com",
    "wof:name":"Dark Blue S.l.",
    "wof:placetype":"venue"
},
  "geometry": {"coordinates":[-4.4719471931,36.6738624573],"type":"Point"}
}