{
  "type": "Feature",
  "properties": {
    "addr:full":"Calle de General Gonzalez, 48 Canjayar Almer\u00eda 04450",
    "addr:housenumber":"48",
    "addr:postcode":"04450",
    "addr:street":"Calle De General Gonzalez;Almeri\u0301A",
    "iso:country":"ES",
    "sg:address":"Calle de General Gonzalez, 48",
    "sg:city":"Canjayar",
    "sg:orig_category":"Cooperativas Agr\u00cdcolas",
    "sg:phone":"+34 950 51 01 32",
    "sg:postcode":"04450",
    "sg:province":"Almer\u00eda",
    "wof:name":"Cooperativa Y Caja Rural Cruz Blanca",
    "wof:placetype":"venue"
},
  "geometry": {"coordinates":[-2.7412750721,37.0104255676],"type":"Point"}
}