{
  "type": "Feature",
  "properties": {
    "addr:full":"Calle de Marqueses Vega De Anzo, 3 Grado Asturias 33820",
    "addr:housenumber":"3",
    "addr:postcode":"33820",
    "addr:street":"Calle De Marqueses Vega De Anzo",
    "iso:country":"ES",
    "sg:address":"Calle de Marqueses Vega De Anzo, 3",
    "sg:city":"Grado",
    "sg:orig_category":"Armas Y Municiones (fabricaci\u00d3n, Al Por Mayor)",
    "sg:phone":"+34 985 75 17 05",
    "sg:postcode":"33820",
    "sg:province":"Asturias",
    "wof:name":"Florez Areces Olegario",
    "wof:placetype":"venue"
},
  "geometry": {"coordinates":[-6.0695672035,43.388999939],"type":"Point"}
}