{
  "type": "Feature",
  "properties": {
    "addr:full":"Rua Hermanos Menesianos, 2 Foz Lugo 27780",
    "addr:housenumber":"2",
    "addr:postcode":"27780",
    "addr:street":"Rua Hermanos Menesianos",
    "iso:country":"ES",
    "sg:address":"Rua Hermanos Menesianos, 2",
    "sg:city":"Foz",
    "sg:classifiers":[
        {
            "category":"Autos & Motor Vehicles",
            "subcategory":"Automobile Sales",
            "type":"Retail Goods"
        }
    ],
    "sg:phone":"+34 982 13 24 49",
    "sg:postcode":"27780",
    "sg:province":"Lugo",
    "wof:name":"Mundial Viveiro-foz S.l.",
    "wof:placetype":"venue"
},
  "geometry": {"coordinates":[-7.2615270615,43.5653686523],"type":"Point"}
}