{
  "type": "Feature",
  "properties": {
    "iso:country":"ES",
    "sg:address":"Avda Pais Valencia, 21",
    "sg:city":"Torrent",
    "sg:orig_category":"Centros Empresariales",
    "sg:phone":"+34 961 56 26 71",
    "sg:postcode":"46900",
    "sg:province":"Valencia",
    "wof:name":"Kanben Consulting S.l",
    "wof:placetype":"venue"
},
  "geometry": {"coordinates":[-0.466822803,39.4357452393],"type":"Point"}
}