{
  "type": "Feature",
  "properties": {
    "iso:country":"ES",
    "sg:address":"Carr Cor De Maria, 4",
    "sg:city":"Girona",
    "sg:orig_category":"Arquitectos",
    "sg:phone":"+34 972 20 98 97",
    "sg:postcode":"17002",
    "sg:province":"Girona",
    "wof:name":"Fina Segura Pedro",
    "wof:placetype":"venue"
},
  "geometry": {"coordinates":[2.8182499409,41.9760131836],"type":"Point"}
}