{
  "type": "Feature",
  "properties": {
    "iso:country":"ES",
    "sg:address":"Calle de Padilla, 3",
    "sg:city":"Valladolid",
    "sg:orig_category":"Reposter\u00cdas",
    "sg:phone":"+34 983 25 25 44",
    "sg:postcode":"47003",
    "sg:province":"Valladolid",
    "wof:name":"Tahona Degustacion Panaderos 30 S.l.",
    "wof:placetype":"venue"
},
  "geometry": {"coordinates":[-4.721988678,41.6575164795],"type":"Point"}
}