{
  "type": "Feature",
  "properties": {
    "iso:country":"ES",
    "sg:address":"Urb. P. Bastian, S/n",
    "sg:city":"Costa Teguise",
    "sg:orig_category":"Centros De Reservas Hoteleras",
    "sg:phone":"+34 928 34 62 25",
    "sg:postcode":"35509",
    "sg:province":"Las Palmas",
    "wof:name":"Toledo Y Bastian S.l.",
    "wof:placetype":"venue"
},
  "geometry": {"coordinates":[-13.5916891098,28.955160141],"type":"Point"}
}