{
  "type": "Feature",
  "properties": {
    "addr:full":"Partida Cabiscol, S/n Amposta Tarragona 43870",
    "addr:housenumber":"s / n",
    "addr:postcode":"43870",
    "addr:street":"Partida Cabiscol",
    "iso:country":"ES",
    "sg:address":"Partida Cabiscol, S/n",
    "sg:city":"Amposta",
    "sg:orig_category":"Asociaciones Y Clubs Deportivos",
    "sg:phone":"+34 977 26 10 17",
    "sg:postcode":"43870",
    "sg:province":"Tarragona",
    "wof:name":"Club De Tir Montsia",
    "wof:placetype":"venue"
},
  "geometry": {"coordinates":[0.5797849894,40.7130432129],"type":"Point"}
}