{
  "type": "Feature",
  "properties": {
    "addr:full":"Calle de Catedratico Antonio Silva, 5 Caceres C\u00e1ceres 10002",
    "addr:housenumber":"5",
    "addr:postcode":"10002",
    "addr:street":"Calle De Catedratico Antonio Silva;Ca\u0301Ceres",
    "iso:country":"ES",
    "sg:address":"Calle de Catedratico Antonio Silva, 5",
    "sg:city":"Caceres",
    "sg:orig_category":"Alimentaci\u00d3n General (al Por Menor)",
    "sg:phone":"+34 927 22 34 50",
    "sg:postcode":"10002",
    "sg:province":"C\u00e1ceres",
    "wof:name":"Alonso Exposito Benjamin",
    "wof:placetype":"venue"
},
  "geometry": {"coordinates":[-6.3766541481,39.4696350098],"type":"Point"}
}