{
  "type": "Feature",
  "properties": {
    "addr:full":"Algepsers(pol Ind), S/n Pol Ind Fuente Jarro Valencia 46988",
    "addr:housenumber":"s / n",
    "addr:postcode":"46988",
    "addr:street":"Pol Ind Fuente Jarro",
    "iso:country":"ES",
    "sg:address":"Algepsers(pol Ind), S/n",
    "sg:city":"Pol Ind Fuente Jarro",
    "sg:orig_category":"Electrodom\u00c9sticos (al Por Menor)",
    "sg:phone":"+34 961 34 30 52",
    "sg:postcode":"46988",
    "sg:province":"Valencia",
    "wof:name":"Distribuidora Valenciana De Electrodomesticos S.a.",
    "wof:placetype":"venue"
},
  "geometry": {"coordinates":[-0.376819998,39.4691886902],"type":"Point"}
}