{
  "type": "Feature",
  "properties": {
    "addr:full":"Calle de Salvador Garcia Oton, S/n Aljorra Murcia 30390",
    "addr:housenumber":"s / n",
    "addr:postcode":"30390",
    "addr:street":"Calle De Salvador Garcia Oton",
    "iso:country":"ES",
    "sg:address":"Calle de Salvador Garcia Oton, S/n",
    "sg:city":"Aljorra",
    "sg:orig_category":"Institutos De Belleza",
    "sg:phone":"+34 968 55 87 04",
    "sg:postcode":"30390",
    "sg:province":"Murcia",
    "wof:name":"Garcia Sanchez Maria Soledad",
    "wof:placetype":"venue"
},
  "geometry": {"coordinates":[-1.0708760023,37.6919746399],"type":"Point"}
}