{
  "type": "Feature",
  "properties": {
    "iso:country":"ES",
    "sg:address":"Calle de Puerto Escondido, 3",
    "sg:city":"Valle De Guerra",
    "sg:orig_category":"Material Y Herramientas Agr\u00cdcolas",
    "sg:phone":"+34 922 54 61 06",
    "sg:postcode":"38270",
    "sg:province":"Santa Cruz De Tenerife",
    "wof:name":"Sistemas De Agua Y Agricultura S.l.",
    "wof:placetype":"venue"
},
  "geometry": {"coordinates":[-16.3963832855,28.5111694336],"type":"Point"}
}