{
  "type": "Feature",
  "properties": {
    "addr:full":"Calle de Juan Pedro Garcia, S/n Cuesta Santa Cruz De Tenerife 38320",
    "addr:postcode":"38320",
    "addr:street":"Calle De Juan;Garcia S / N Cuesta",
    "iso:country":"ES",
    "sg:address":"Calle de Juan Pedro Garcia, S/n",
    "sg:city":"Cuesta",
    "sg:orig_category":"Metalurgia",
    "sg:phone":"+34 922 64 68 02",
    "sg:postcode":"38320",
    "sg:province":"Santa Cruz De Tenerife",
    "wof:name":"Bolsa De Aguas De Tenerife S. A.",
    "wof:placetype":"venue"
},
  "geometry": {"coordinates":[-16.2945194244,28.4721946716],"type":"Point"}
}