{
  "type": "Feature",
  "properties": {
    "iso:country":"ES",
    "sg:address":"Historiador Torres Laguna, 3",
    "sg:city":"Andujar",
    "sg:orig_category":"Ingeniero",
    "sg:phone":"+34 953 51 33 12",
    "sg:postcode":"23740",
    "sg:province":"Ja\u00e9n",
    "wof:name":"Feijoo Ingenieros S.l",
    "wof:placetype":"venue"
},
  "geometry": {"coordinates":[-4.0463790894,38.0403633118],"type":"Point"}
}