{
  "type": "Feature",
  "properties": {
    "addr:full":"Urb Padre Rejas, 2 Jamilena Ja\u00e9n 23658",
    "addr:housenumber":"2",
    "addr:postcode":"23658",
    "addr:street":"Urb Padre Rejas",
    "iso:country":"ES",
    "sg:address":"Urb Padre Rejas, 2",
    "sg:city":"Jamilena",
    "sg:orig_category":"Droguer\u00cdas (al Por Menor)",
    "sg:phone":"+34 953 56 60 67",
    "sg:postcode":"23658",
    "sg:province":"Ja\u00e9n",
    "wof:name":"Liebana Liebana Maria Trinidad",
    "wof:placetype":"venue"
},
  "geometry": {"coordinates":[-3.9135289192,37.7469177246],"type":"Point"}
}