{
  "type": "Feature",
  "properties": {
    "addr:full":"C/ Reina Victoria, 124 Elche Alicante 03201",
    "addr:housenumber":"124",
    "addr:postcode":"03201",
    "addr:street":"C / Reina Victoria",
    "iso:country":"ES",
    "sg:address":"C/ Reina Victoria, 124",
    "sg:city":"Elche",
    "sg:orig_category":"Inversiones",
    "sg:phone":"+34 966 66 68 56",
    "sg:postcode":"03201",
    "sg:province":"Alicante",
    "wof:name":"Anton Lidon Sociedad De Inversion S.l.",
    "wof:placetype":"venue"
},
  "geometry": {"coordinates":[-0.7097123861,38.2656593323],"type":"Point"}
}