{
  "type": "Feature",
  "properties": {
    "iso:country":"ES",
    "sg:address":"Calle de Pasaman Alargunaren, 4",
    "sg:city":"Pasai S. Pedro",
    "sg:orig_category":"Carnicer\u00cdas, Carnicer\u00cdas",
    "sg:phone":"+34 943 40 07 02",
    "sg:postcode":"20110",
    "sg:province":"Guip\u00f9zcoa",
    "wof:name":"Carnicas Shanti S.a.",
    "wof:placetype":"venue"
},
  "geometry": {"coordinates":[-1.9261749983,43.3258323669],"type":"Point"}
}