{
  "type": "Feature",
  "properties": {
    "addr:full":"Calle de Cabeza De Vaca, 9 Salamanca Salamanca 37004",
    "addr:housenumber":"9",
    "addr:postcode":"37004",
    "addr:street":"Calle De Cabeza De Vaca",
    "iso:country":"ES",
    "sg:address":"Calle de Cabeza De Vaca, 9",
    "sg:city":"Salamanca",
    "sg:orig_category":"Fabricaci\u00d3n De Ventanas",
    "sg:phone":"+34 923 22 26 33",
    "sg:postcode":"37004",
    "sg:province":"Salamanca",
    "wof:name":"Mozo Y Martin S.l.",
    "wof:placetype":"venue"
},
  "geometry": {"coordinates":[-5.6564540863,40.9727859497],"type":"Point"}
}