{
  "type": "Feature",
  "properties": {
    "addr:full":"Colorada, 1 Colorada Asturias 33719",
    "addr:housenumber":"1",
    "addr:postcode":"33719",
    "addr:street":"Colorada",
    "iso:country":"ES",
    "sg:address":"Colorada, 1",
    "sg:city":"Colorada",
    "sg:orig_category":"Panader\u00cdas, Panader\u00cdas",
    "sg:phone":"+34 985 63 06 96",
    "sg:postcode":"33719",
    "sg:province":"Asturias",
    "wof:name":"Jose Antonio Menendez Suarez S.l.",
    "wof:placetype":"venue"
},
  "geometry": {"coordinates":[-6.6598329544,43.5291023254],"type":"Point"}
}