{
  "type": "Feature",
  "properties": {
    "iso:country":"ES",
    "sg:address":"Calle de Ines Rosales, 10",
    "sg:city":"Castilleja Cuesta",
    "sg:orig_category":"Electrodom\u00c9sticos (fabricaci\u00d3n, Al Por Mayor)",
    "sg:phone":"+34 954 16 44 59",
    "sg:postcode":"41950",
    "sg:province":"Sevilla",
    "wof:name":"Rodriguez Barbero Antonio",
    "wof:placetype":"venue"
},
  "geometry": {"coordinates":[-6.0547242165,37.3845252991],"type":"Point"}
}