{
  "type": "Feature",
  "properties": {
    "iso:country":"ES",
    "sg:address":"Calle de Obispo Zarranz Y Pueyo, 3",
    "sg:city":"Bejar",
    "sg:orig_category":"Farmacias",
    "sg:phone":"+34 923 40 02 56",
    "sg:postcode":"37700",
    "sg:province":"Salamanca",
    "wof:name":"Gomez-rodulfo Martinez C.b.",
    "wof:placetype":"venue"
},
  "geometry": {"coordinates":[-5.756362915,40.3845100403],"type":"Point"}
}