{
  "type": "Feature",
  "properties": {
    "iso:country":"ES",
    "sg:address":"C/ Pere Coll I Guito, 19",
    "sg:city":"Salt",
    "sg:orig_category":"Marketing Directo",
    "sg:phone":"+34 972 24 32 52",
    "sg:postcode":"17190",
    "sg:province":"Girona",
    "wof:name":"Servicios Para Congresos Y Publicidad Directa S.a.",
    "wof:placetype":"venue"
},
  "geometry": {"coordinates":[2.7845640182,41.9719734192],"type":"Point"}
}