{
  "type": "Feature",
  "properties": {
    "addr:full":"Carr Rusi\u00d1ol, 1 Escala Girona 17130",
    "addr:housenumber":"1",
    "addr:postcode":"17130",
    "addr:street":"Carr Rusin\u0303Ol",
    "iso:country":"ES",
    "sg:address":"Carr Rusi\u00d1ol, 1",
    "sg:city":"Escala",
    "sg:orig_category":"Asociaciones, Organismos Culturales Y Socioeducativos",
    "sg:phone":"+34 972 77 58 09",
    "sg:postcode":"17130",
    "sg:province":"Girona",
    "wof:name":"Assoc.lleure Baobab",
    "wof:placetype":"venue"
},
  "geometry": {"coordinates":[3.1316688061,42.122467041],"type":"Point"}
}