{
  "type": "Feature",
  "properties": {
    "addr:full":"En Proy., 13 Riba-roja Turia Valencia 46190",
    "addr:housenumber":"13",
    "addr:postcode":"46190",
    "iso:country":"ES",
    "sg:address":"En Proy., 13",
    "sg:city":"Riba-roja Turia",
    "sg:orig_category":"Fabrica De Cer\u00c1micas",
    "sg:phone":"+34 961 65 22 40",
    "sg:postcode":"46190",
    "sg:province":"Valencia",
    "wof:name":"Ceramica Veracruz S.l.",
    "wof:placetype":"venue"
},
  "geometry": {"coordinates":[-0.5698940158,39.5458450317],"type":"Point"}
}