{
  "type": "Feature",
  "properties": {
    "iso:country":"ES",
    "sg:address":"Urb Florida Este, 2",
    "sg:city":"Gojar",
    "sg:orig_category":"Inmobiliaria (agencias)",
    "sg:phone":"+34 958 59 75 04",
    "sg:postcode":"18150",
    "sg:province":"Granada",
    "wof:name":"Granada Ventas Y Compras S.l.",
    "wof:placetype":"venue"
},
  "geometry": {"coordinates":[-3.6018989086,37.1141090393],"type":"Point"}
}