{
  "type": "Feature",
  "properties": {
    "iso:country":"ES",
    "sg:address":"Ctra San Agustin De Guadalix (de), Km. 0001,5",
    "sg:city":"Colmenar Viejo",
    "sg:orig_category":"Alimentaci\u00d3n General (al Por Mayor)",
    "sg:phone":"+34 918 45 53 50",
    "sg:postcode":"28770",
    "sg:province":"Madrid",
    "wof:name":"Piensos Palomino S.l.",
    "wof:placetype":"venue"
},
  "geometry": {"coordinates":[-3.7562680244,40.6635513306],"type":"Point"}
}