{
  "type": "Feature",
  "properties": {
    "addr:full":"Pase Presbitero Giner, 23 Villalonga Valencia 46720",
    "addr:housenumber":"23",
    "addr:postcode":"46720",
    "addr:street":"Presbitero Giner",
    "iso:country":"ES",
    "sg:address":"Pase Presbitero Giner, 23",
    "sg:city":"Villalonga",
    "sg:classifiers":[
        {
            "category":"Autos & Motor Vehicles",
            "subcategory":"Automobile Sales",
            "type":"Retail Goods"
        }
    ],
    "sg:phone":"+34 962 81 70 79",
    "sg:postcode":"46720",
    "sg:province":"Valencia",
    "wof:name":"Fernando Guillem E Hijos S.l.",
    "wof:placetype":"venue"
},
  "geometry": {"coordinates":[-0.2102890015,38.8871841431],"type":"Point"}
}