{
  "type": "Feature",
  "properties": {
    "iso:country":"ES",
    "sg:address":"Calle de Mayor, 8",
    "sg:city":"Esparragal",
    "sg:orig_category":"Librer\u00cdas",
    "sg:phone":"+34 968 85 28 97",
    "sg:postcode":"30163",
    "sg:province":"Murcia",
    "wof:name":"Encarnacion Rubio Hidalgo Y Maria Rubio Cdad",
    "wof:placetype":"venue"
},
  "geometry": {"coordinates":[-1.0817209482,38.0388755798],"type":"Point"}
}