{
  "type": "Feature",
  "properties": {
    "addr:full":"Plaz Sabino Arana, 33 Sabino Arana Vizcaya 48140",
    "addr:housenumber":"33",
    "addr:postcode":"48140",
    "addr:street":"Sabino Arana;Sabino Arana Vizcaya",
    "iso:country":"ES",
    "sg:address":"Plaz Sabino Arana, 33",
    "sg:city":"Sabino Arana",
    "sg:orig_category":"Servicios Gsm",
    "sg:phone":"+34 946 31 50 02",
    "sg:postcode":"48140",
    "sg:province":"Vizcaya",
    "wof:name":"Errekagorri Aurricoetxea Kepa",
    "wof:placetype":"venue"
},
  "geometry": {"coordinates":[-2.777105093,43.1645507812],"type":"Point"}
}