{
  "type": "Feature",
  "properties": {
    "iso:country":"ES",
    "sg:address":"Av Fort De L'eau, 64",
    "sg:city":"Mao",
    "sg:orig_category":"Peluquer\u00cdas, Peluquer\u00cda Mixta",
    "sg:phone":"+34 971 36 69 53",
    "sg:postcode":"07701",
    "sg:province":"Islas Baleares",
    "wof:name":"Balaguero Rovira Jose",
    "wof:placetype":"venue"
},
  "geometry": {"coordinates":[4.2730951309,39.8872108459],"type":"Point"}
}