{
  "type": "Feature",
  "properties": {
    "iso:country":"ES",
    "sg:address":"Cra. Igualada A Vilanova, S/n",
    "sg:city":"La Granada",
    "sg:orig_category":"Maquinaria Para Industrias Diversas",
    "sg:phone":"+34 938 97 47 25",
    "sg:postcode":"08792",
    "sg:province":"Barcelona",
    "wof:name":"Merca Eleva S.l",
    "wof:placetype":"venue"
},
  "geometry": {"coordinates":[1.7211799622,41.3850212097],"type":"Point"}
}