{
  "type": "Feature",
  "properties": {
    "iso:country":"ES",
    "sg:address":"Calle de Julio Angel, 10",
    "sg:city":"Jaen",
    "sg:orig_category":"Arquitectos",
    "sg:phone":"+34 953 23 48 20",
    "sg:postcode":"23002",
    "sg:province":"Ja\u00e9n",
    "wof:name":"Toro Codes Antonio De",
    "wof:placetype":"venue"
},
  "geometry": {"coordinates":[-3.7896749973,37.7641906738],"type":"Point"}
}