{
  "type": "Feature",
  "properties": {
    "iso:country":"ES",
    "sg:address":"Avda Jose Simon De Lillo, 78",
    "sg:city":"Pe\u00e7arroya-pueblonuevo",
    "sg:orig_category":"Molduras, Junquillos, Listones Y Molduras Perforadas",
    "sg:phone":"+34 957 56 28 78",
    "sg:postcode":"14200",
    "sg:province":"C\u00f3rdoba",
    "wof:name":"Moyano Mu\u00f1oz Javier",
    "wof:placetype":"venue"
},
  "geometry": {"coordinates":[-5.2689771652,38.3011665344],"type":"Point"}
}