{
  "type": "Feature",
  "properties": {
    "addr:full":"Rier Soler (de Can), S/n Mataro Barcelona 08304",
    "addr:housenumber":"/ n",
    "addr:postcode":"08304",
    "iso:country":"ES",
    "sg:address":"Rier Soler (de Can), S/n",
    "sg:city":"Mataro",
    "sg:orig_category":"Maquinaria Para Industrias Diversas",
    "sg:phone":"+34 937 96 00 45",
    "sg:postcode":"08304",
    "sg:province":"Barcelona",
    "wof:name":"Vidal Grane S.l.",
    "wof:placetype":"venue"
},
  "geometry": {"coordinates":[2.4462649822,41.5607833862],"type":"Point"}
}