{
  "type": "Feature",
  "properties": {
    "iso:country":"ES",
    "sg:address":"Calle de Caceres, 5",
    "sg:city":"Partija-santa Monica",
    "sg:orig_category":"Centros Empresariales",
    "sg:phone":"+34 913 01 23 46",
    "sg:postcode":"28529",
    "sg:province":"Madrid",
    "wof:name":"Espallardo Lopez Maria",
    "wof:placetype":"venue"
},
  "geometry": {"coordinates":[-3.7003455162,40.4166908264],"type":"Point"}
}