{
  "type": "Feature",
  "properties": {
    "addr:full":"Carrer de Toquio, 6 Barcelona Barcelona 08034",
    "addr:housenumber":"6",
    "addr:postcode":"08034",
    "addr:street":"Carrer De Toquio",
    "iso:country":"ES",
    "sg:address":"Carrer de Toquio, 6",
    "sg:city":"Barcelona",
    "sg:orig_category":"Promotores Constructores",
    "sg:phone":"+34 932 06 34 68",
    "sg:postcode":"08034",
    "sg:province":"Barcelona",
    "wof:name":"Pijuan Fincas S. L.",
    "wof:placetype":"venue"
},
  "geometry": {"coordinates":[2.1188809872,41.3911857605],"type":"Point"}
}