{
  "type": "Feature",
  "properties": {
    "iso:country":"ES",
    "sg:address":"Avda Ambrosio De Los Heros, S/n",
    "sg:city":"Carreras",
    "sg:orig_category":"Asilos De Ancianos. Centros Privados",
    "sg:phone":"+34 946 36 80 28",
    "sg:postcode":"48540",
    "sg:province":"Vizcaya",
    "wof:name":"Ayuntamiento De Abanto Y Ciervana",
    "wof:placetype":"venue"
},
  "geometry": {"coordinates":[-3.1028733253,43.3210029602],"type":"Point"}
}