{
  "type": "Feature",
  "properties": {
    "addr:full":"Calle de Alcarria, 20 Leganes Madrid 28915",
    "addr:housenumber":"20",
    "addr:postcode":"28915",
    "addr:street":"Calle De Alcarria",
    "iso:country":"ES",
    "sg:address":"Calle de Alcarria, 20",
    "sg:city":"Leganes",
    "sg:orig_category":"Enfermeras: Consultas, Atenci\u00d3n A Domicilio",
    "sg:phone":"+34 916 87 37 84",
    "sg:postcode":"28915",
    "sg:province":"Madrid",
    "wof:name":"Laguna Monta\u00f1es Federico",
    "wof:placetype":"venue"
},
  "geometry": {"coordinates":[-3.7569003105,40.3331565857],"type":"Point"}
}