{
  "type": "Feature",
  "properties": {
    "addr:full":"Rua Ferradores, 19 Betanzos La Coru\u00f1a 15300",
    "addr:housenumber":"19",
    "addr:postcode":"15300",
    "addr:street":"Rua Ferradores;La",
    "iso:country":"ES",
    "sg:address":"Rua Ferradores, 19",
    "sg:city":"Betanzos",
    "sg:orig_category":"Oficinas Y Gesti\u00d3n De Inmuebles",
    "sg:phone":"+34 981 77 58 77",
    "sg:postcode":"15300",
    "sg:province":"La Coru\u00f1a",
    "wof:name":"Asesoria Inmobiliaria S.l.",
    "wof:placetype":"venue"
},
  "geometry": {"coordinates":[-8.2267665863,43.2696266174],"type":"Point"}
}