{
  "type": "Feature",
  "properties": {
    "iso:country":"ES",
    "sg:address":"Calle de Torrelaguna, 8",
    "sg:city":"Madrid",
    "sg:orig_category":"Agencias De Viajes",
    "sg:phone":"+34 913 26 73 23",
    "sg:postcode":"28027",
    "sg:province":"Madrid",
    "wof:name":"Ayantour S.l.",
    "wof:placetype":"venue"
},
  "geometry": {"coordinates":[-3.6497759819,40.4407196045],"type":"Point"}
}