{
  "type": "Feature",
  "properties": {
    "iso:country":"ES",
    "sg:address":"Calle de Mayor Principal, 38",
    "sg:city":"Palencia",
    "sg:orig_category":"Relojer\u00cda (al Por Menor, Reparaci\u00d3n)",
    "sg:phone":"+34 979 74 40 14",
    "sg:postcode":"34001",
    "sg:province":"Palencia",
    "wof:name":"Merida Garcia Fernando",
    "wof:placetype":"venue"
},
  "geometry": {"coordinates":[-4.5392618179,42.010433197],"type":"Point"}
}