{
  "type": "Feature",
  "properties": {
    "addr:full":"Calle de Severo Ochoa, 14 Sese\u00e7a Nuevo Toledo 45224",
    "addr:housenumber":"14",
    "addr:postcode":"45224",
    "addr:street":"Calle De Severo Ochoa",
    "iso:country":"ES",
    "sg:address":"Calle de Severo Ochoa, 14",
    "sg:city":"Sese\u00e7a Nuevo",
    "sg:orig_category":"Mec\u00c1nico Del Autom\u00d3vil",
    "sg:phone":"+34 918 01 25 46",
    "sg:postcode":"45224",
    "sg:province":"Toledo",
    "wof:name":"Automoviles Norte Sur S.l.",
    "wof:placetype":"venue"
},
  "geometry": {"coordinates":[-4.0244760513,39.8567771912],"type":"Point"}
}