{
  "type": "Feature",
  "properties": {
    "iso:country":"ES",
    "sg:address":"Carr Isabel Penalba, 10",
    "sg:city":"Guadassuar",
    "sg:orig_category":"Empresas De Electricidad En General",
    "sg:phone":"+34 962 57 02 84",
    "sg:postcode":"46610",
    "sg:province":"Valencia",
    "wof:name":"Electrica De Guadassuar Scv",
    "wof:placetype":"venue"
},
  "geometry": {"coordinates":[-0.4786199927,39.1869239807],"type":"Point"}
}