{
  "type": "Feature",
  "properties": {
    "iso:country":"ES",
    "sg:address":"Cmno Barrial, 3",
    "sg:city":"Madrid",
    "sg:orig_category":"Inform\u00c1tica (estudios, Servicios, Asesor\u00cda, Formaci\u00d3n)",
    "sg:phone":"+34 913 57 29 86",
    "sg:postcode":"28023",
    "sg:province":"Madrid",
    "wof:name":"Desarrollos Informaticos Y Control S.l.",
    "wof:placetype":"venue"
},
  "geometry": {"coordinates":[-3.7876629829,40.4594955444],"type":"Point"}
}