{
  "type": "Feature",
  "properties": {
    "iso:country":"ES",
    "sg:address":"Av Barcelona, 18",
    "sg:city":"Tarrega",
    "sg:orig_category":"Comercio De Carburantes",
    "sg:phone":"+34 973 31 07 45",
    "sg:postcode":"25300",
    "sg:province":"Lleida",
    "wof:name":"Prats Duch S.l.",
    "wof:placetype":"venue"
},
  "geometry": {"coordinates":[1.1458059549,41.6518630981],"type":"Point"}
}