{
  "type": "Feature",
  "properties": {
    "addr:full":"Carrer de Sant Jordi, 15 Cambrils Tarragona 43850",
    "addr:housenumber":"15",
    "addr:postcode":"43850",
    "addr:street":"Carrer De Sant Jordi",
    "iso:country":"ES",
    "sg:address":"Carrer de Sant Jordi, 15",
    "sg:city":"Cambrils",
    "sg:orig_category":"Asociaciones Y Clubs Deportivos",
    "sg:phone":"+34 977 36 40 35",
    "sg:postcode":"43850",
    "sg:province":"Tarragona",
    "wof:name":"Phatumal Lalwani Jeetu",
    "wof:placetype":"venue"
},
  "geometry": {"coordinates":[1.0592030287,41.0653572083],"type":"Point"}
}