{
  "type": "Feature",
  "properties": {
    "iso:country":"ES",
    "sg:address":"Avda San Ignacio De Loyola, 68",
    "sg:city":"Barrio De Pinilla",
    "sg:orig_category":"Veh\u00cdculos De Ocasi\u00d3n",
    "sg:phone":"+34 987 27 00 37",
    "sg:postcode":"24010",
    "sg:province":"Le\u00f3n",
    "wof:name":"Laurentino S.l. De Automoviles De Ocasion",
    "wof:placetype":"venue"
},
  "geometry": {"coordinates":[-5.592769146,42.6072807312],"type":"Point"}
}