{
  "type": "Feature",
  "properties": {
    "addr:full":"Calle de Viaducto Marquina, 4 Oviedo Asturias 33004",
    "addr:housenumber":"4",
    "addr:postcode":"33004",
    "addr:street":"Calle De Viaducto Marquina",
    "iso:country":"ES",
    "sg:address":"Calle de Viaducto Marquina, 4",
    "sg:city":"Oviedo",
    "sg:orig_category":"Asociaciones Y Clubs Deportivos",
    "sg:phone":"+34 985 23 28 23",
    "sg:postcode":"33004",
    "sg:province":"Asturias",
    "wof:name":"Grupo Monta\u00f1eros Vetusta",
    "wof:placetype":"venue"
},
  "geometry": {"coordinates":[-5.8542561531,43.3653755188],"type":"Point"}
}