{
  "type": "Feature",
  "properties": {
    "iso:country":"ES",
    "sg:address":"Calle de Huerta (de La), 13",
    "sg:city":"San Fernando De Henares",
    "sg:orig_category":"Suministros Y Materiales Industriales",
    "sg:phone":"+34 916 74 35 44",
    "sg:postcode":"28830",
    "sg:province":"Madrid",
    "wof:name":"Hosteleria Cardenas S.l.l.",
    "wof:placetype":"venue"
},
  "geometry": {"coordinates":[-3.5301849842,40.424987793],"type":"Point"}
}