{
  "type": "Feature",
  "properties": {
    "iso:country":"ES",
    "sg:address":"Ctra Motores (los), 108",
    "sg:city":"Campillo Del Moro",
    "sg:orig_category":"Alquiler De V\u00cddeo",
    "sg:phone":"+34 950 55 11 83",
    "sg:postcode":"04720",
    "sg:province":"Almer\u00eda",
    "wof:name":"Almerache S.l.",
    "wof:placetype":"venue"
},
  "geometry": {"coordinates":[-2.5909752846,36.8076324463],"type":"Point"}
}