{
  "type": "Feature",
  "properties": {
    "iso:country":"ES",
    "sg:address":"Calle de Villajoyosa, 69",
    "sg:city":"Madrid",
    "sg:orig_category":"Centros Empresariales",
    "sg:phone":"+34 917 96 15 79",
    "sg:postcode":"28041",
    "sg:province":"Madrid",
    "wof:name":"Multiservicios El Ambar S.l.",
    "wof:placetype":"venue"
},
  "geometry": {"coordinates":[-3.6908950806,40.3552207947],"type":"Point"}
}