{
  "type": "Feature",
  "properties": {
    "iso:country":"ES",
    "sg:address":"Calle de Mayor, 24",
    "sg:city":"Belones",
    "sg:orig_category":"Asociaciones, Organismos Culturales Y Socioeducativos",
    "sg:phone":"+34 968 56 92 10",
    "sg:postcode":"30385",
    "sg:province":"Murcia",
    "wof:name":"Sociedad Recreativa La Horiental",
    "wof:placetype":"venue"
},
  "geometry": {"coordinates":[-0.7771257162,37.6227722168],"type":"Point"}
}