{
  "type": "Feature",
  "properties": {
    "iso:country":"ES",
    "sg:address":"Ama\u00d1a Kalea, 10",
    "sg:city":"Eibar",
    "sg:orig_category":"Asociaciones Y Clubs Deportivos",
    "sg:phone":"+34 943 20 79 58",
    "sg:postcode":"20600",
    "sg:province":"Guip\u00f9zcoa",
    "wof:name":"Sociedad Deportiva La Perla",
    "wof:placetype":"venue"
},
  "geometry": {"coordinates":[-2.4792289734,43.1854438782],"type":"Point"}
}