{
  "type": "Feature",
  "properties": {
    "addr:full":"Carrer de Joaquim Serra (de), 2 Pineda Tarragona 43480",
    "addr:housenumber":"2",
    "addr:postcode":"43480",
    "addr:street":"Carrer De Joaquim Serra De",
    "iso:country":"ES",
    "sg:address":"Carrer de Joaquim Serra (de), 2",
    "sg:city":"Pineda",
    "sg:orig_category":"Inmobiliaria (agencias)",
    "sg:phone":"+34 977 37 18 05",
    "sg:postcode":"43480",
    "sg:province":"Tarragona",
    "wof:name":"Apartamento's Costa Dorada S.c.p.",
    "wof:placetype":"venue"
},
  "geometry": {"coordinates":[1.1867591143,41.0847015381],"type":"Point"}
}