{
  "type": "Feature",
  "properties": {
    "iso:country":"ES",
    "sg:address":"Calle de Galicia, 35",
    "sg:city":"Fuenlabrada",
    "sg:orig_category":"Producci\u00d3n, Distribuci\u00d3n De Gas Butano Y Propano",
    "sg:phone":"+34 916 07 25 25",
    "sg:postcode":"28942",
    "sg:province":"Madrid",
    "wof:name":"Cortes Luque Antonio",
    "wof:placetype":"venue"
},
  "geometry": {"coordinates":[-3.8104031086,40.3003845215],"type":"Point"}
}