{
  "type": "Feature",
  "properties": {
    "iso:country":"ES",
    "sg:address":"Avda Lucas Vega, 71",
    "sg:city":"San Cristobal De La Laguna",
    "sg:orig_category":"Bazares, Art\u00cdculos De Limpieza Y De Cocina (al Por Menor)",
    "sg:phone":"+34 922 25 10 00",
    "sg:postcode":"38206",
    "sg:province":"Santa Cruz De Tenerife",
    "wof:name":"C.b. Cruz Martin La Vega Articulos De Regalo S.l.u.",
    "wof:placetype":"venue"
},
  "geometry": {"coordinates":[-16.3255290985,28.4841270447],"type":"Point"}
}