{
  "type": "Feature",
  "properties": {
    "iso:country":"ES",
    "sg:address":"Calle de Rey Gaspar, 14",
    "sg:city":"Casta\u00d1eta",
    "sg:orig_category":"Empresarios",
    "sg:phone":"+34 952 43 44 28",
    "sg:postcode":"29590",
    "sg:province":"M\u00e1laga",
    "wof:name":"R Y P Serviconst S.l",
    "wof:placetype":"venue"
},
  "geometry": {"coordinates":[-4.5224900246,36.7190055847],"type":"Point"}
}