{
  "type": "Feature",
  "properties": {
    "addr:full":"C/ Concepcion Arenal, 178 Elche Alicante 03204",
    "addr:housenumber":"178",
    "addr:postcode":"03204",
    "addr:street":"C / Concepcion Arenal",
    "iso:country":"ES",
    "sg:address":"C/ Concepcion Arenal, 178",
    "sg:city":"Elche",
    "sg:orig_category":"Caf\u00c9s, Bares, Cervecer\u00cdas",
    "sg:phone":"+34 966 63 55 69",
    "sg:postcode":"03204",
    "sg:province":"Alicante",
    "wof:name":"Paya Asencio Jorge",
    "wof:placetype":"venue"
},
  "geometry": {"coordinates":[-0.7081350088,38.2571182251],"type":"Point"}
}