{
  "type": "Feature",
  "properties": {
    "iso:country":"ES",
    "sg:address":"Av President Companys, 12",
    "sg:city":"Besalu",
    "sg:orig_category":"Asesor\u00cda Fiscal Y Jur\u00cddica",
    "sg:phone":"+34 972 59 12 06",
    "sg:postcode":"17850",
    "sg:province":"Girona",
    "wof:name":"Pont Oliveras Maria Merce",
    "wof:placetype":"venue"
},
  "geometry": {"coordinates":[2.6975519657,42.2001686096],"type":"Point"}
}