{
  "type": "Feature",
  "properties": {
    "addr:full":"Plaz Andres Moro, 4 Palencia Palencia 34005",
    "addr:housenumber":"4",
    "addr:postcode":"34005",
    "addr:street":"Moro",
    "iso:country":"ES",
    "sg:address":"Plaz Andres Moro, 4",
    "sg:city":"Palencia",
    "sg:orig_category":"Ense\u00d1anza Variada",
    "sg:phone":"+34 979 70 25 35",
    "sg:postcode":"34005",
    "sg:province":"Palencia",
    "wof:name":"Mi\u00f1ambres Mi\u00f1ambres Ana Maria Victoria",
    "wof:placetype":"venue"
},
  "geometry": {"coordinates":[-4.5392618179,42.010433197],"type":"Point"}
}