{
  "type": "Feature",
  "properties": {
    "addr:full":"Av Gabriel Alomar I V, 33 Palma Islas Baleares 07006",
    "addr:housenumber":"33",
    "addr:postcode":"07006",
    "addr:street":"Av Gabriel Alomar;V",
    "iso:country":"ES",
    "sg:address":"Av Gabriel Alomar I V, 33",
    "sg:city":"Palma",
    "sg:orig_category":"Cl\u00cdnicas M\u00c9dicas",
    "sg:phone":"+34 971 46 26 85",
    "sg:postcode":"07006",
    "sg:province":"Islas Baleares",
    "wof:name":"Darder Andreu Bartolome",
    "wof:placetype":"venue"
},
  "geometry": {"coordinates":[2.6787199974,39.5591049194],"type":"Point"}
}