{
  "type": "Feature",
  "properties": {
    "iso:country":"ES",
    "sg:address":"Calle de Florian Rey, 13",
    "sg:city":"Zaragoza",
    "sg:orig_category":"Molduras, Junquillos, Listones Y Molduras Perforadas",
    "sg:phone":"+34 976 29 44 82",
    "sg:postcode":"50002",
    "sg:province":"Zaragoza",
    "wof:name":"Bustin Escusol Angel",
    "wof:placetype":"venue"
},
  "geometry": {"coordinates":[-0.8626800179,41.6492805481],"type":"Point"}
}