{
  "type": "Feature",
  "properties": {
    "addr:full":"Calle de Cruz, 5 Linares Ja\u00e9n 23700",
    "addr:housenumber":"5",
    "addr:postcode":"23700",
    "addr:street":"Calle De Cruz;Jae\u0301N",
    "iso:country":"ES",
    "sg:address":"Calle de Cruz, 5",
    "sg:city":"Linares",
    "sg:orig_category":"Sociedades, Compa\u00d1\u00cdas Aseguradoras",
    "sg:phone":"+34 953 69 87 12",
    "sg:postcode":"23700",
    "sg:province":"Ja\u00e9n",
    "wof:name":"Paraiso Universal S. A.",
    "wof:placetype":"venue"
},
  "geometry": {"coordinates":[-3.6327860355,38.0990905762],"type":"Point"}
}