{
  "type": "Feature",
  "properties": {
    "addr:full":"Carrer de Viriat, 12 Castelldefels Barcelona 08860",
    "addr:housenumber":"12",
    "addr:postcode":"08860",
    "addr:street":"Carrer De Viriat",
    "iso:country":"ES",
    "sg:address":"Carrer de Viriat, 12",
    "sg:city":"Castelldefels",
    "sg:orig_category":"Ropa Para Ni\u00d1os (al Por Menor)",
    "sg:phone":"+34 936 65 13 91",
    "sg:postcode":"08860",
    "sg:province":"Barcelona",
    "wof:name":"Marta-isa S.c.p.",
    "wof:placetype":"venue"
},
  "geometry": {"coordinates":[1.9792870283,41.286113739],"type":"Point"}
}