{
  "type": "Feature",
  "properties": {
    "addr:full":"Pase Canteras Las, 6 Palmas De Gran Canaria Las Palmas 35008",
    "addr:postcode":"35008",
    "addr:street":"Las",
    "iso:country":"ES",
    "sg:address":"Pase Canteras Las, 6",
    "sg:city":"Palmas De Gran Canaria",
    "sg:orig_category":"Explotaci\u00d3n De Canteras",
    "sg:phone":"+34 928 26 30 19",
    "sg:postcode":"35008",
    "sg:province":"Las Palmas",
    "wof:name":"Massiraffa Canteras S.l.",
    "wof:placetype":"venue"
},
  "geometry": {"coordinates":[-15.4310808182,28.1447525024],"type":"Point"}
}