{
  "type": "Feature",
  "properties": {
    "addr:full":"Ctra Vilassar De Dalt, 115 Premia Mar Barcelona 08330",
    "addr:housenumber":"115",
    "addr:postcode":"08330",
    "addr:street":"Ctra Vilassar De Dalt",
    "iso:country":"ES",
    "sg:address":"Ctra Vilassar De Dalt, 115",
    "sg:city":"Premia Mar",
    "sg:orig_category":"Material Y Suministros Para Horticultura, Arboricultura",
    "sg:phone":"+34 937 54 86 19",
    "sg:postcode":"08330",
    "sg:province":"Barcelona",
    "wof:name":"Hortibatlle S.l.",
    "wof:placetype":"venue"
},
  "geometry": {"coordinates":[2.3597788811,41.4964103699],"type":"Point"}
}