{
  "type": "Feature",
  "properties": {
    "iso:country":"ES",
    "sg:address":"Calle de Rio Deva, S/n",
    "sg:city":"S. Vicente Barquera",
    "sg:orig_category":"Reposter\u00cdas",
    "sg:phone":"+34 942 71 15 03",
    "sg:postcode":"39540",
    "sg:province":"Cantabria",
    "wof:name":"Panaderia Nel S.l.",
    "wof:placetype":"venue"
},
  "geometry": {"coordinates":[-4.3955111504,43.3892059326],"type":"Point"}
}