{
  "type": "Feature",
  "properties": {
    "iso:country":"ES",
    "sg:address":"Carr Baro De Carcer, 3",
    "sg:city":"Quart Poblet",
    "sg:orig_category":"Molduras, Junquillos, Listones Y Molduras Perforadas",
    "sg:phone":"+34 961 53 30 13",
    "sg:postcode":"46930",
    "sg:province":"Valencia",
    "wof:name":"Alonso Chinesta Vicente Ignacio",
    "wof:placetype":"venue"
},
  "geometry": {"coordinates":[-0.4418283999,39.4827308655],"type":"Point"}
}