{
  "type": "Feature",
  "properties": {
    "iso:country":"ES",
    "sg:address":"Calle de Manuel Del Valle, 5",
    "sg:city":"Madrid",
    "sg:orig_category":"M\u00c9dicos: Pediatr\u00cda. Enfermedades De Los Ni\u00d1os",
    "sg:phone":"+34 914 13 64 53",
    "sg:postcode":"28043",
    "sg:province":"Madrid",
    "wof:name":"Moreno Fernandez Luis",
    "wof:placetype":"venue"
},
  "geometry": {"coordinates":[-3.6554210186,40.4519844055],"type":"Point"}
}