{
  "type": "Feature",
  "properties": {
    "iso:country":"ES",
    "sg:address":"Plaz Ni\u00d1o Jesus, 5",
    "sg:city":"Madrid",
    "sg:orig_category":"Inmobiliaria (agencias)",
    "sg:phone":"+34 915 01 90 65",
    "sg:postcode":"28009",
    "sg:province":"Madrid",
    "wof:name":"Inmo-video Barquero Y Asocciados S.l",
    "wof:placetype":"venue"
},
  "geometry": {"coordinates":[-3.675440073,40.4109344482],"type":"Point"}
}