{
  "type": "Feature",
  "properties": {
    "addr:full":"Carr Tuejar, S/n Eliana Valencia 46183",
    "addr:housenumber":"s / n",
    "addr:postcode":"46183",
    "addr:street":"Carr Tuejar",
    "iso:country":"ES",
    "sg:address":"Carr Tuejar, S/n",
    "sg:city":"Eliana",
    "sg:orig_category":"Distribuci\u00d3n De Petr\u00d3leo Y Derivados",
    "sg:phone":"+34 961 65 66 73",
    "sg:postcode":"46183",
    "sg:province":"Valencia",
    "sg:website":"www.galpenergia.com",
    "wof:name":"Galpgest Petrogal Estaciones De Servicio S.l.u.",
    "wof:placetype":"venue"
},
  "geometry": {"coordinates":[-0.528208971,39.5667457581],"type":"Point"}
}