{
  "type": "Feature",
  "properties": {
    "addr:full":"Carrer de Pins Roses, 76 Cardedeu Barcelona 08440",
    "addr:housenumber":"76",
    "addr:postcode":"08440",
    "addr:street":"Carrer De Pins Roses",
    "iso:country":"ES",
    "sg:address":"Carrer de Pins Roses, 76",
    "sg:city":"Cardedeu",
    "sg:orig_category":"Venta, Alquiler, Mantenimiento De Calderas",
    "sg:phone":"+34 938 71 18 87",
    "sg:postcode":"08440",
    "sg:province":"Barcelona",
    "wof:name":"Tecnica Y Experiencia En Recipientes A Presion S.l.",
    "wof:placetype":"venue"
},
  "geometry": {"coordinates":[2.3631498814,41.6242904663],"type":"Point"}
}