{
  "type": "Feature",
  "properties": {
    "addr:full":"Carrer de Torreta, 42 S. Pere Ribes Barcelona 08810",
    "addr:housenumber":"42",
    "addr:postcode":"08810",
    "addr:street":"Carrer De Torreta;S. Pere Ribes Barcelona",
    "iso:country":"ES",
    "sg:address":"Carrer de Torreta, 42",
    "sg:city":"S. Pere Ribes",
    "sg:orig_category":"Papeler\u00cdas, Librer\u00cdas",
    "sg:phone":"+34 938 96 33 36",
    "sg:postcode":"08810",
    "sg:province":"Barcelona",
    "wof:name":"La Torreta De Paper Scp",
    "wof:placetype":"venue"
},
  "geometry": {"coordinates":[1.7769049406,41.2592697144],"type":"Point"}
}