{
  "type": "Feature",
  "properties": {
    "addr:full":"Calle de Rafael Calvo, 30 Madrid Madrid 28010",
    "addr:housenumber":"30",
    "addr:postcode":"madrid;28010",
    "addr:street":"Calle De Rafael Calvo",
    "iso:country":"ES",
    "sg:address":"Calle de Rafael Calvo, 30",
    "sg:city":"Madrid",
    "sg:orig_category":"Asociaciones Humanitarias, De Cooperaci\u00d3n, De Acci\u00d3n Social",
    "sg:phone":"+34 915 94 07 99",
    "sg:postcode":"28010",
    "sg:province":"Madrid",
    "wof:name":"Asociacion Victimas Del Terrorismo",
    "wof:placetype":"venue"
},
  "geometry": {"coordinates":[-3.6925630569,40.4340057373],"type":"Point"}
}