{
  "type": "Feature",
  "properties": {
    "addr:full":"Calle de Juan Ramon Jimenez, 32 Castellon Castell\u00f3n 12006",
    "addr:housenumber":"32",
    "addr:postcode":"12006",
    "addr:street":"Calle De Juan Ramon Jimenez",
    "iso:country":"ES",
    "sg:address":"Calle de Juan Ramon Jimenez, 32",
    "sg:city":"Castellon",
    "sg:orig_category":"Poller\u00cda Y Caza (al Por Menor)",
    "sg:phone":"+34 964 21 99 19",
    "sg:postcode":"12006",
    "sg:province":"Castell\u00f3n",
    "wof:name":"Segura Segura Amparo",
    "wof:placetype":"venue"
},
  "geometry": {"coordinates":[-0.1292939931,40.0168533325],"type":"Point"}
}