{
  "type": "Feature",
  "properties": {
    "iso:country":"ES",
    "sg:address":"Calle de Curtidores, 2",
    "sg:city":"Yeles",
    "sg:orig_category":"Bricolaje, Herramientas (al Por Menor)",
    "sg:phone":"+34 925 54 56 71",
    "sg:postcode":"45220",
    "sg:province":"Toledo",
    "wof:name":"Cano Lopez David",
    "wof:placetype":"venue"
},
  "geometry": {"coordinates":[-3.804666996,40.1240081787],"type":"Point"}
}