{
  "type": "Feature",
  "properties": {
    "iso:country":"ES",
    "sg:address":"Ctra Fregeneda, 14",
    "sg:city":"Salamanca",
    "sg:orig_category":"Distribuci\u00d3n De Petr\u00d3leo Y Derivados",
    "sg:phone":"+34 923 19 11 32",
    "sg:postcode":"37008",
    "sg:province":"Salamanca",
    "wof:name":"El Trebol S. L.",
    "wof:placetype":"venue"
},
  "geometry": {"coordinates":[-5.6758937836,40.9550056458],"type":"Point"}
}