{
  "type": "Feature",
  "properties": {
    "addr:full":"Cra. Nova Beret, 4 Salardu Lleida 25598",
    "addr:housenumber":"4",
    "addr:postcode":"25598",
    "addr:street":"Beret",
    "iso:country":"ES",
    "sg:address":"Cra. Nova Beret, 4",
    "sg:city":"Salardu",
    "sg:orig_category":"Maquinaria Para Industrias Diversas",
    "sg:phone":"+34 973 64 44 26",
    "sg:postcode":"25598",
    "sg:province":"Lleida",
    "wof:name":"Estudios Comerciales E Industriales De Maquinaria S.a.",
    "wof:placetype":"venue"
},
  "geometry": {"coordinates":[0.9334179759,42.6994895935],"type":"Point"}
}