{
  "type": "Feature",
  "properties": {
    "iso:country":"ES",
    "sg:address":"Carrer de Rocafonda, 13",
    "sg:city":"Mataro",
    "sg:orig_category":"Molduras, Junquillos, Listones Y Molduras Perforadas",
    "sg:phone":"+34 937 90 37 02",
    "sg:postcode":"08301",
    "sg:province":"Barcelona",
    "wof:name":"Miranda Rey Angel",
    "wof:placetype":"venue"
},
  "geometry": {"coordinates":[2.4470279217,41.5452194214],"type":"Point"}
}