{
  "type": "Feature",
  "properties": {
    "iso:country":"ES",
    "sg:address":"Cta. Madrid-cartag., S/n",
    "sg:city":"Minaya",
    "sg:orig_category":"Distribuci\u00d3n De Petr\u00d3leo Y Derivados",
    "sg:phone":"+34 967 45 00 12",
    "sg:postcode":"02620",
    "sg:province":"Albacete",
    "wof:name":"Estaciones De Servicio San Prudencio S.l.",
    "wof:placetype":"venue"
},
  "geometry": {"coordinates":[-2.3216319084,39.2727508545],"type":"Point"}
}