{
  "type": "Feature",
  "properties": {
    "addr:full":"Calle de San Roque, 82 Castellon Castell\u00f3n 12004",
    "addr:housenumber":"82",
    "addr:postcode":"12004",
    "addr:street":"Calle De San Roque",
    "iso:country":"ES",
    "sg:address":"Calle de San Roque, 82",
    "sg:city":"Castellon",
    "sg:orig_category":"Agentes, Concesionarios Y Sucursales De Veh\u00cdculos",
    "sg:phone":"+34 964 23 80 11",
    "sg:postcode":"12004",
    "sg:province":"Castell\u00f3n",
    "sg:website":"www.imola.es",
    "wof:name":"Imola S. A.",
    "wof:placetype":"venue"
},
  "geometry": {"coordinates":[-0.0364609994,39.9931869507],"type":"Point"}
}