{
  "type": "Feature",
  "properties": {
    "iso:country":"ES",
    "sg:address":"Benjamin De Tudela, 44",
    "sg:city":"Iru\u00f1a",
    "sg:orig_category":"Tapiceros Y Tapiceros",
    "sg:phone":"+34 948 17 72 03",
    "sg:postcode":"31008",
    "sg:province":"Navarra",
    "wof:name":"Hualde Lecumberri Francisco Javier",
    "wof:placetype":"venue"
},
  "geometry": {"coordinates":[-1.6748809814,42.8112945557],"type":"Point"}
}