{
  "type": "Feature",
  "properties": {
    "iso:country":"ES",
    "sg:address":"Carrer de Rocafort, 92",
    "sg:city":"Barcelona",
    "sg:orig_category":"Molduras, Junquillos, Listones Y Molduras Perforadas",
    "sg:phone":"+34 933 25 10 92",
    "sg:postcode":"08015",
    "sg:province":"Barcelona",
    "wof:name":"Jimenez Garcia Maria Del Carmen",
    "wof:placetype":"venue"
},
  "geometry": {"coordinates":[2.1526749134,41.3799591064],"type":"Point"}
}