{
  "type": "Feature",
  "properties": {
    "addr:full":"Calle de Sevilla, 63 Estepona M\u00e1laga 29680",
    "addr:housenumber":"63",
    "addr:postcode":"29680",
    "addr:street":"Calle De Sevilla",
    "iso:country":"ES",
    "sg:address":"Calle de Sevilla, 63",
    "sg:city":"Estepona",
    "sg:orig_category":"Alimentaci\u00d3n General (al Por Mayor)",
    "sg:phone":"+34 952 80 06 88",
    "sg:postcode":"29680",
    "sg:province":"M\u00e1laga",
    "wof:name":"Collado Marquez Maria Francisca",
    "wof:placetype":"venue"
},
  "geometry": {"coordinates":[-5.1491441727,36.4250717163],"type":"Point"}
}