{
  "type": "Feature",
  "properties": {
    "addr:full":"Rua Serra Ga\u00d1idoira, 118 Lugo Lugo 27004",
    "addr:housenumber":"118",
    "addr:postcode":"27004",
    "addr:street":"Rua Serra Gan\u0303Idoira",
    "iso:country":"ES",
    "sg:address":"Rua Serra Ga\u00d1idoira, 118",
    "sg:city":"Lugo",
    "sg:orig_category":"Chapister\u00cda",
    "sg:phone":"+34 982 21 61 95",
    "sg:postcode":"27004",
    "sg:province":"Lugo",
    "wof:name":"Vila Diaz Jose Maria",
    "wof:placetype":"venue"
},
  "geometry": {"coordinates":[-7.5683441162,43.0159759521],"type":"Point"}
}