{
  "type": "Feature",
  "properties": {
    "iso:country":"ES",
    "sg:address":"Calle de San Antonio, 9",
    "sg:city":"Chiclana De La Frontera",
    "sg:orig_category":"Electrodom\u00c9sticos (al Por Menor)",
    "sg:phone":"+34 956 53 50 57",
    "sg:postcode":"11130",
    "sg:province":"C\u00e1diz",
    "wof:name":"Ramirez Pedrero Marcos",
    "wof:placetype":"venue"
},
  "geometry": {"coordinates":[-6.1448459625,36.4224891663],"type":"Point"}
}