{
  "type": "Feature",
  "properties": {
    "addr:full":"Calle de Teseo, 40 Madrid Madrid 28027",
    "addr:housenumber":"40",
    "addr:postcode":"madrid;28027",
    "addr:street":"Calle De Teseo",
    "iso:country":"ES",
    "sg:address":"Calle de Teseo, 40",
    "sg:city":"Madrid",
    "sg:orig_category":"Inform\u00c1tica Equipo Y Programas (al Por Mayor)",
    "sg:phone":"+34 913 20 68 12",
    "sg:postcode":"28027",
    "sg:province":"Madrid",
    "sg:website":"www.zefrasoft.com",
    "wof:name":"Tradysoft S.l.",
    "wof:placetype":"venue"
},
  "geometry": {"coordinates":[-3.6382808685,40.4449195862],"type":"Point"}
}