{
  "type": "Feature",
  "properties": {
    "addr:full":"Calle de Condesa De Venadito, 5 Madrid Madrid 28027",
    "addr:housenumber":"5",
    "addr:postcode":"28027",
    "addr:street":"Calle De Condesa De Venadito",
    "iso:country":"ES",
    "sg:address":"Calle de Condesa De Venadito, 5",
    "sg:city":"Madrid",
    "sg:orig_category":"Automatizaci\u00d3n De Procesos Industriales Y De Edificaci\u00d3n (estudios, Instalaci\u00d3n)",
    "sg:phone":"+34 916 60 11 69",
    "sg:postcode":"28027",
    "sg:province":"Madrid",
    "sg:website":"www.cyb.es",
    "wof:name":"Came S.a.",
    "wof:placetype":"venue"
},
  "geometry": {"coordinates":[-3.6535434723,40.4446182251],"type":"Point"}
}