{
  "type": "Feature",
  "properties": {
    "addr:full":"Carrer de Galileu, 40 Terrassa Barcelona 08224",
    "addr:housenumber":"40",
    "addr:postcode":"08224",
    "addr:street":"Carrer De Galileu",
    "iso:country":"ES",
    "sg:address":"Carrer de Galileu, 40",
    "sg:city":"Terrassa",
    "sg:orig_category":"Asesor\u00cda Fiscal Y Jur\u00cddica",
    "sg:phone":"+34 937 88 17 17",
    "sg:postcode":"08224",
    "sg:province":"Barcelona",
    "wof:name":"Mafiscot S.l.",
    "wof:placetype":"venue"
},
  "geometry": {"coordinates":[2.0054709911,41.557636261],"type":"Point"}
}