{
  "type": "Feature",
  "properties": {
    "addr:full":"Carrer de Diagonal, 1 Can Sant Joan Barcelona 08110",
    "addr:postcode":"08110",
    "addr:street":"Carrer De Diagonal 1",
    "iso:country":"ES",
    "sg:address":"Carrer de Diagonal, 1",
    "sg:city":"Can Sant Joan",
    "sg:orig_category":"Cajas De Ahorro",
    "sg:phone":"+34 935 75 34 88",
    "sg:postcode":"08110",
    "sg:province":"Barcelona",
    "sg:website":"www.caixasabadell.es",
    "wof:name":"Caixa D'estalvis Sabadell",
    "wof:placetype":"venue"
},
  "geometry": {"coordinates":[2.1859691143,41.4872894287],"type":"Point"}
}