{
  "type": "Feature",
  "properties": {
    "addr:full":"Calle de Lunado (del), S/n San Esteban Del Valle \u00c1vila 05412",
    "addr:housenumber":"/ n",
    "addr:postcode":"05412",
    "addr:street":"Calle De Lunado Del S;A\u0301Vila",
    "iso:country":"ES",
    "sg:address":"Calle de Lunado (del), S/n",
    "sg:city":"San Esteban Del Valle",
    "sg:orig_category":"Molduras, Junquillos, Listones Y Molduras Perforadas",
    "sg:phone":"+34 920 38 36 98",
    "sg:postcode":"05412",
    "sg:province":"\u00c1vila",
    "wof:name":"Garcia Gutierrez Juan Jesus",
    "wof:placetype":"venue"
},
  "geometry": {"coordinates":[-4.982779026,40.2744674683],"type":"Point"}
}