{
  "type": "Feature",
  "properties": {
    "iso:country":"ES",
    "sg:address":"Calle de Castello, 24",
    "sg:city":"Madrid",
    "sg:orig_category":"Asesor\u00cda Sobre Comunicaci\u00d3n De Empresas",
    "sg:phone":"+34 915 76 63 58",
    "sg:postcode":"28001",
    "sg:province":"Madrid",
    "sg:website":"www.beatgreen.com",
    "wof:name":"Beat Green S.l.",
    "wof:placetype":"venue"
},
  "geometry": {"coordinates":[-3.6813828945,40.4245872498],"type":"Point"}
}