{
  "type": "Feature",
  "properties": {
    "addr:full":"Calle de Marques De San Esteban, 8 Gijon Asturias 33206",
    "addr:housenumber":"8",
    "addr:postcode":"33206",
    "addr:street":"Calle De Marques De San Esteban",
    "iso:country":"ES",
    "sg:address":"Calle de Marques De San Esteban, 8",
    "sg:city":"Gijon",
    "sg:orig_category":"Promotores Constructores",
    "sg:phone":"+34 985 35 11 49",
    "sg:postcode":"33206",
    "sg:province":"Asturias",
    "wof:name":"Promociones Del Cantabrico S. A.",
    "wof:placetype":"venue"
},
  "geometry": {"coordinates":[-5.6659450531,43.5429840088],"type":"Point"}
}