{
  "type": "Feature",
  "properties": {
    "iso:country":"ES",
    "sg:address":"Avda Maria Zambrano, 10",
    "sg:city":"Malaga",
    "sg:orig_category":"Seguridad Social",
    "sg:phone":"+34 952 33 08 03",
    "sg:postcode":"29006",
    "sg:province":"M\u00e1laga",
    "sg:website":"www.fremap.es",
    "wof:name":"Fremap Mutua De Accidentes De Trabajo Y Enferm.profes.de S.s.",
    "wof:placetype":"venue"
},
  "geometry": {"coordinates":[-4.4660181999,36.7110710144],"type":"Point"}
}