{
  "type": "Feature",
  "properties": {
    "iso:country":"ES",
    "sg:address":"Carrer de Francesc Salvans, 50",
    "sg:city":"Terrassa",
    "sg:orig_category":"Peluquer\u00cdas, Peluquer\u00cda Mixta",
    "sg:phone":"+34 937 35 42 63",
    "sg:postcode":"08225",
    "sg:province":"Barcelona",
    "wof:name":"Alonso Castillo Carmen",
    "wof:placetype":"venue"
},
  "geometry": {"coordinates":[2.0133254528,41.5734329224],"type":"Point"}
}