{
  "type": "Feature",
  "properties": {
    "iso:country":"ES",
    "sg:address":"Calle de Mayor, 17",
    "sg:city":"Alagon",
    "sg:orig_category":"Peluquer\u00cdas, Peluquer\u00cda Mixta",
    "sg:phone":"+34 976 61 06 69",
    "sg:postcode":"50630",
    "sg:province":"Zaragoza",
    "wof:name":"Jose Y Gloria S. Cv.",
    "wof:placetype":"venue"
},
  "geometry": {"coordinates":[-1.1199768782,41.7697143555],"type":"Point"}
}