{
  "type": "Feature",
  "properties": {
    "iso:country":"ES",
    "sg:address":"Plaza Del Ganado, S/n",
    "sg:city":"Posada",
    "sg:orig_category":"Sanatorios M\u00c9dico",
    "sg:phone":"+34 985 40 73 61",
    "sg:postcode":"33594",
    "sg:province":"Asturias",
    "wof:name":"Principado De Asturias",
    "wof:placetype":"venue"
},
  "geometry": {"coordinates":[-4.8618822098,43.4186553955],"type":"Point"}
}