{
  "type": "Feature",
  "properties": {
    "iso:country":"ES",
    "sg:address":"Aire, S/n",
    "sg:city":"Novelda Guadiana",
    "sg:orig_category":"Cooperativas Agr\u00cdcolas",
    "sg:phone":"+34 924 47 50 35",
    "sg:postcode":"06183",
    "sg:province":"Badajoz",
    "wof:name":"Cooperativa De Colonos",
    "wof:placetype":"venue"
},
  "geometry": {"coordinates":[-6.8326787949,38.9385910034],"type":"Point"}
}