{
  "type": "Feature",
  "properties": {
    "iso:country":"ES",
    "sg:address":"Calle de San Jose, 3",
    "sg:city":"Quartell",
    "sg:orig_category":"Restaurantes",
    "sg:phone":"+34 962 63 61 03",
    "sg:postcode":"46510",
    "sg:province":"Valencia",
    "wof:name":"Sebastian Langa Jose",
    "wof:placetype":"venue"
},
  "geometry": {"coordinates":[-0.2641339898,39.7383575439],"type":"Point"}
}