{
  "type": "Feature",
  "properties": {
    "iso:country":"ES",
    "sg:address":"Trva Cabo (o) 4, S/n",
    "sg:city":"Vilanova Arousa",
    "sg:orig_category":"Centros Empresariales",
    "sg:phone":"+34 986 55 46 65",
    "sg:postcode":"36620",
    "sg:province":"Pontevedra",
    "wof:name":"Asociacion De Productores De Mejilloneros Villanueva",
    "wof:placetype":"venue"
},
  "geometry": {"coordinates":[-8.8736839294,42.5640602112],"type":"Point"}
}