{
  "type": "Feature",
  "properties": {
    "iso:country":"ES",
    "sg:address":"Ctra Santpedor, 115",
    "sg:city":"Manresa",
    "sg:orig_category":"Inmobiliaria (agencias)",
    "sg:phone":"+34 938 74 69 19",
    "sg:postcode":"08242",
    "sg:province":"Barcelona",
    "wof:name":"Comunidad De Propietarios Carretera De Santpedor, 115-121 Escala F",
    "wof:placetype":"venue"
},
  "geometry": {"coordinates":[1.8321549892,41.7360839844],"type":"Point"}
}