{
  "type": "Feature",
  "properties": {
    "addr:full":"Carretera Miranda De Ebro, S/n Trevi\u00f1o Burgos 09215",
    "addr:housenumber":"s / n",
    "addr:postcode":"09215",
    "addr:street":"Carretera Miranda De Ebro",
    "iso:country":"ES",
    "sg:address":"Carretera Miranda De Ebro, S/n",
    "sg:city":"Trevi\u00f1o",
    "sg:orig_category":"Asociaciones, Organismos Culturales Y Socioeducativos",
    "sg:phone":"+34 945 36 02 02",
    "sg:postcode":"09215",
    "sg:province":"Burgos",
    "wof:name":"Fundacion Zortzigarrena La Octava Cuadrilla",
    "wof:placetype":"venue"
},
  "geometry": {"coordinates":[-2.74792099,42.7341041565],"type":"Point"}
}