{
  "type": "Feature",
  "properties": {
    "addr:full":"Calle de Real, 45 S. Fernando C\u00e1diz 11100",
    "addr:housenumber":"45",
    "addr:postcode":"11100",
    "addr:street":"Calle De Real;S. Fernando Ca\u0301Diz",
    "iso:country":"ES",
    "sg:address":"Calle de Real, 45",
    "sg:city":"S. Fernando",
    "sg:orig_category":"Abogados",
    "sg:phone":"+34 956 59 14 77",
    "sg:postcode":"11100",
    "sg:province":"C\u00e1diz",
    "wof:name":"Villar Motrel Cesar Luis",
    "wof:placetype":"venue"
},
  "geometry": {"coordinates":[-6.1924672127,36.4673042297],"type":"Point"}
}