{
  "type": "Feature",
  "properties": {
    "addr:full":"Calle de Manuel Garcia Babio, 6 Castilleja Cuesta Sevilla 41950",
    "addr:housenumber":"6",
    "addr:postcode":"41950",
    "addr:street":"Calle De Manuel Garcia Babio;Cuesta Sevilla",
    "iso:country":"ES",
    "sg:address":"Calle de Manuel Garcia Babio, 6",
    "sg:city":"Castilleja Cuesta",
    "sg:orig_category":"Limpieza Industrial",
    "sg:phone":"+34 954 16 01 06",
    "sg:postcode":"41950",
    "sg:province":"Sevilla",
    "wof:name":"Ruiz Prieto Antonio",
    "wof:placetype":"venue"
},
  "geometry": {"coordinates":[-6.05849123,37.3857955933],"type":"Point"}
}