{
  "type": "Feature",
  "properties": {
    "iso:country":"ES",
    "sg:address":"Calle de Valle De Cachemira, 44",
    "sg:city":"Madrid",
    "sg:orig_category":"Asesor\u00cda Fiscal Y Jur\u00cddica",
    "sg:phone":"+34 913 86 70 14",
    "sg:postcode":"28039",
    "sg:province":"Madrid",
    "wof:name":"Herran Martin Belen 387289 Ps.l.",
    "wof:placetype":"venue"
},
  "geometry": {"coordinates":[-3.7148098946,40.4664039612],"type":"Point"}
}