{
  "type": "Feature",
  "properties": {
    "iso:country":"ES",
    "sg:address":"Ctra Malaga (de), S/n",
    "sg:city":"Granada",
    "sg:orig_category":"Delegados, Agentes De Tr\u00c1nsito, Auxiliares De Transporte Internacional",
    "sg:phone":"+34 958 28 89 26",
    "sg:postcode":"18015",
    "sg:province":"Granada",
    "wof:name":"Madrid Alvarez Gabriela",
    "wof:placetype":"venue"
},
  "geometry": {"coordinates":[-3.6263940334,37.189365387],"type":"Point"}
}