{
  "type": "Feature",
  "properties": {
    "addr:full":"Carrer de Francesc Perez Dol\u00c7, 38 Cambrils Tarragona 43850",
    "addr:housenumber":"38",
    "addr:postcode":"43850",
    "addr:street":"Carrer De Francesc Perez Dolc\u0327",
    "iso:country":"ES",
    "sg:address":"Carrer de Francesc Perez Dol\u00c7, 38",
    "sg:city":"Cambrils",
    "sg:orig_category":"Inform\u00c1tica, Ofim\u00c1tica (estudios, Asesor\u00cda, Ingenier\u00cda, Formaci\u00d3n)",
    "sg:phone":"+34 977 36 83 32",
    "sg:postcode":"43850",
    "sg:province":"Tarragona",
    "sg:website":"www.kernel-tech.net",
    "wof:name":"Kernel Technologies Soluciones Informaticas S.l.",
    "wof:placetype":"venue"
},
  "geometry": {"coordinates":[1.0504230261,41.0722045898],"type":"Point"}
}