{
  "type": "Feature",
  "properties": {
    "addr:full":"C/ Divina Pastora, 21 Banyoles Girona 17820",
    "addr:housenumber":"21",
    "addr:postcode":"17820",
    "addr:street":"C / Divina Pastora",
    "iso:country":"ES",
    "sg:address":"C/ Divina Pastora, 21",
    "sg:city":"Banyoles",
    "sg:orig_category":"Caf\u00c9s, Bares, Cervecer\u00cdas",
    "sg:phone":"+34 972 57 36 07",
    "sg:postcode":"17820",
    "sg:province":"Girona",
    "wof:name":"Iquitos Reposteria S.l.",
    "wof:placetype":"venue"
},
  "geometry": {"coordinates":[2.7630329132,42.1174659729],"type":"Point"}
}