{
  "type": "Feature",
  "properties": {
    "iso:country":"ES",
    "sg:address":"Avda Zuberoa, 50",
    "sg:city":"Bilbao",
    "sg:orig_category":"Artesan\u00cda",
    "sg:phone":"+34 944 03 55 84",
    "sg:postcode":"48012",
    "sg:province":"Vizcaya",
    "wof:name":"Jesus F. Pastor",
    "wof:placetype":"venue"
},
  "geometry": {"coordinates":[-2.9359850883,43.2537231445],"type":"Point"}
}