{
  "type": "Feature",
  "properties": {
    "iso:country":"ES",
    "sg:address":"Calle de Ramon De Aguinaga, 7",
    "sg:city":"Madrid",
    "sg:orig_category":"Inmobiliaria (agencias)",
    "sg:phone":"+34 913 61 55 11",
    "sg:postcode":"28028",
    "sg:province":"Madrid",
    "wof:name":"Gatacha S.l.",
    "wof:placetype":"venue"
},
  "geometry": {"coordinates":[-3.6633989811,40.4268760681],"type":"Point"}
}