{
  "type": "Feature",
  "properties": {
    "iso:country":"ES",
    "sg:address":"Carrer de Riu Segre, 22",
    "sg:city":"Canyelles-almadrava-puig-rom",
    "sg:classifiers":[
        {
            "category":"Recreation",
            "type":"Entertainment"
        }
    ],
    "sg:phone":"+34 972 25 61 25",
    "sg:postcode":"17480",
    "sg:province":"Girona",
    "sg:tags":[
        "caza",
        "pr\u00c1ctica",
        "la",
        "de",
        "pesca",
        "y"
    ],
    "wof:name":"Abad Mallol S.c.",
    "wof:placetype":"venue"
},
  "geometry": {"coordinates":[3.185038,42.258453],"type":"Point"}
}