{
  "type": "Feature",
  "properties": {
    "iso:country":"ES",
    "sg:address":"Carrer de Florida, 63",
    "sg:city":"Barcelona",
    "sg:orig_category":"Camiser\u00cda Y Ropa Interior Masculina (al Por Menor)",
    "sg:phone":"+34 935 34 78 92",
    "sg:postcode":"08016",
    "sg:province":"Barcelona",
    "wof:name":"M&a Classic S.l.",
    "wof:placetype":"venue"
},
  "geometry": {"coordinates":[2.1858160496,41.4455909729],"type":"Point"}
}