{
  "type": "Feature",
  "properties": {
    "addr:full":"Carrer de Valladolid, 39 Barcelona Barcelona 08014",
    "addr:housenumber":"39",
    "addr:postcode":"08014",
    "addr:street":"Carrer De Valladolid",
    "iso:country":"ES",
    "sg:address":"Carrer de Valladolid, 39",
    "sg:city":"Barcelona",
    "sg:orig_category":"Dibujantes (diversos)",
    "sg:phone":"+34 933 39 33 89",
    "sg:postcode":"08014",
    "sg:province":"Barcelona",
    "wof:name":"Catalan Bolufer Carlos",
    "wof:placetype":"venue"
},
  "geometry": {"coordinates":[2.1371901035,41.378238678],"type":"Point"}
}