{
  "type": "Feature",
  "properties": {
    "addr:full":"Pl. Mi%enari, S/n Lloret Mar Girona 17310",
    "addr:housenumber":"s",
    "addr:postcode":"17310",
    "addr:street":"Pl.;/ N Lloret",
    "iso:country":"ES",
    "sg:address":"Pl. Mi%enari, S/n",
    "sg:city":"Lloret Mar",
    "sg:orig_category":"Carnicer\u00cdas, Carnicer\u00cdas",
    "sg:phone":"+34 972 36 58 76",
    "sg:postcode":"17310",
    "sg:province":"Girona",
    "wof:name":"Carniceria Maria Luisa S.l.",
    "wof:placetype":"venue"
},
  "geometry": {"coordinates":[2.846834898,41.6981697083],"type":"Point"}
}