{
  "type": "Feature",
  "properties": {
    "addr:full":"Calle de Magallanes, 33 Grao Castell\u00f3n 12100",
    "addr:housenumber":"33",
    "addr:postcode":"12100",
    "addr:street":"Calle De Magallanes",
    "iso:country":"ES",
    "sg:address":"Calle de Magallanes, 33",
    "sg:city":"Grao",
    "sg:orig_category":"Perfumer\u00cda (al Por Menor)",
    "sg:phone":"+34 964 28 00 62",
    "sg:postcode":"12100",
    "sg:province":"Castell\u00f3n",
    "wof:name":"Sirifer S.l.",
    "wof:placetype":"venue"
},
  "geometry": {"coordinates":[0.0118739996,39.9729347229],"type":"Point"}
}