{
  "type": "Feature",
  "properties": {
    "iso:country":"ES",
    "sg:address":"Carrer de Gava, 19",
    "sg:city":"Barcelona",
    "sg:orig_category":"Estudios, Instalaci\u00d3n De Climatizaci\u00d3n",
    "sg:phone":"+34 932 98 02 95",
    "sg:postcode":"08014",
    "sg:province":"Barcelona",
    "wof:name":"Citeco Hispanoamericana De Ingenieria S.l.",
    "wof:placetype":"venue"
},
  "geometry": {"coordinates":[2.1412029266,41.3718032837],"type":"Point"}
}