{
  "type": "Feature",
  "properties": {
    "addr:full":"Carrer de Floridablanca, 13 Mataro Barcelona 08301",
    "addr:housenumber":"13",
    "addr:postcode":"08301",
    "addr:street":"Carrer De Floridablanca",
    "iso:country":"ES",
    "sg:address":"Carrer de Floridablanca, 13",
    "sg:city":"Mataro",
    "sg:orig_category":"Mercer\u00cda, Lencer\u00cda (al Por Menor)",
    "sg:phone":"+34 937 96 35 43",
    "sg:postcode":"08301",
    "sg:province":"Barcelona",
    "wof:name":"Garcia Moyano Rosa Ana",
    "wof:placetype":"venue"
},
  "geometry": {"coordinates":[2.4528520107,41.5397872925],"type":"Point"}
}