{
  "type": "Feature",
  "properties": {
    "addr:full":"Calle de Gabriel Y Galan, 3 Valladolid Valladolid 47005",
    "addr:housenumber":"3",
    "addr:postcode":"47005",
    "addr:street":"Calle De Gabriel Y Galan",
    "iso:country":"ES",
    "sg:address":"Calle de Gabriel Y Galan, 3",
    "sg:city":"Valladolid",
    "sg:orig_category":"Fotocopias, Reprograf\u00cda",
    "sg:phone":"+34 983 30 46 83",
    "sg:postcode":"47005",
    "sg:province":"Valladolid",
    "wof:name":"Imago Copias Y Servicios",
    "wof:placetype":"venue"
},
  "geometry": {"coordinates":[-4.7132101059,41.6523971558],"type":"Point"}
}