{
  "type": "Feature",
  "properties": {
    "addr:full":"Calle de Rondonera, 4 Xeraco Valencia 46770",
    "addr:housenumber":"4",
    "addr:postcode":"46770",
    "addr:street":"Calle De Rondonera",
    "iso:country":"ES",
    "sg:address":"Calle de Rondonera, 4",
    "sg:city":"Xeraco",
    "sg:orig_category":"Producci\u00d3n De Abonos Y De Fertilizantes",
    "sg:phone":"+34 962 89 06 85",
    "sg:postcode":"46770",
    "sg:province":"Valencia",
    "wof:name":"Xem Abonos S.l.",
    "wof:placetype":"venue"
},
  "geometry": {"coordinates":[-0.2222854942,39.0336303711],"type":"Point"}
}