{
  "type": "Feature",
  "properties": {
    "addr:full":"Calle de Ramon Y Cajal, 1 Avila \u00c1vila 05001",
    "addr:housenumber":"1",
    "addr:postcode":"05001",
    "addr:street":"Calle De Ramon Y Cajal;A\u0301Vila",
    "iso:country":"ES",
    "sg:address":"Calle de Ramon Y Cajal, 1",
    "sg:city":"Avila",
    "sg:orig_category":"Centros P\u00dablicos De Formaci\u00d3n Profesional Y T\u00c9cnica",
    "sg:phone":"+34 920 21 26 69",
    "sg:postcode":"05001",
    "sg:province":"\u00c1vila",
    "wof:name":"Colegio Provincial De Abogados",
    "wof:placetype":"venue"
},
  "geometry": {"coordinates":[-4.7018280029,40.6569862366],"type":"Point"}
}