{
  "type": "Feature",
  "properties": {
    "iso:country":"ES",
    "sg:address":"Avda Cesar Augusto, 111",
    "sg:city":"Zaragoza",
    "sg:orig_category":"Juegos Y Juguetes (al Por Menor)",
    "sg:phone":"+34 976 43 12 60",
    "sg:postcode":"50003",
    "sg:province":"Zaragoza",
    "wof:name":"Redondo Rodrigo Mariano",
    "wof:placetype":"venue"
},
  "geometry": {"coordinates":[-0.8826320171,41.6566963196],"type":"Point"}
}