{
  "type": "Feature",
  "properties": {
    "addr:full":"Calle de Serrano, 71 Madrid Madrid 28006",
    "addr:housenumber":"71",
    "addr:postcode":"madrid;28006",
    "addr:street":"Calle De Serrano",
    "iso:country":"ES",
    "sg:address":"Calle de Serrano, 71",
    "sg:city":"Madrid",
    "sg:orig_category":"Financiaci\u00d3n Y Cr\u00c9ditos",
    "sg:phone":"+34 914 26 23 29",
    "sg:postcode":"28006",
    "sg:province":"Madrid",
    "sg:website":"www.diana-capital.com",
    "wof:name":"Diana Capital Inversion S.a.",
    "wof:placetype":"venue"
},
  "geometry": {"coordinates":[-3.6867799759,40.4338531494],"type":"Point"}
}