{
  "type": "Feature",
  "properties": {
    "addr:full":"San Ignazio Kalea, 4 Elgoibar Guip\u00f9zcoa 20870",
    "addr:housenumber":"4",
    "addr:postcode":"20870",
    "addr:street":"San Ignazio Kalea;Guipu\u0300Zcoa",
    "iso:country":"ES",
    "sg:address":"San Ignazio Kalea, 4",
    "sg:city":"Elgoibar",
    "sg:orig_category":"Inform\u00c1tica (estudios, Servicios, Asesor\u00cda, Formaci\u00d3n)",
    "sg:phone":"+34 943 74 08 50",
    "sg:postcode":"20870",
    "sg:province":"Guip\u00f9zcoa",
    "sg:website":"www.hurbil.net",
    "wof:name":"Hurbil Elgoibarko Zerbitzu Informatikoak",
    "wof:placetype":"venue"
},
  "geometry": {"coordinates":[-2.4166810513,43.2133712769],"type":"Point"}
}