{
  "type": "Feature",
  "properties": {
    "addr:full":"Avda Coru\u00d1a (la), 14 Puente Valga Pontevedra 36645",
    "addr:housenumber":"14",
    "addr:postcode":"36645",
    "addr:street":"Avda Corun\u0303A La",
    "iso:country":"ES",
    "sg:address":"Avda Coru\u00d1a (la), 14",
    "sg:city":"Puente Valga",
    "sg:orig_category":"Administraciones Regionales, Departamentales Y Locales",
    "sg:phone":"+34 986 55 09 12",
    "sg:postcode":"36645",
    "sg:province":"Pontevedra",
    "wof:name":"Mancomunidade Intermunicipal Dos Vales Do Ulla E O Umia",
    "wof:placetype":"venue"
},
  "geometry": {"coordinates":[-8.6393947601,42.6959877014],"type":"Point"}
}