{
  "type": "Feature",
  "properties": {
    "addr:full":"Calle de San Mateo, 62 Alacant Alicante 03013",
    "addr:housenumber":"62",
    "addr:postcode":"03013",
    "addr:street":"Calle De San Mateo",
    "iso:country":"ES",
    "sg:address":"Calle de San Mateo, 62",
    "sg:city":"Alacant",
    "sg:orig_category":"Accesorios Para Tintorer\u00cdas, Limpieza En Seco",
    "sg:phone":"+34 965 15 68 82",
    "sg:postcode":"03013",
    "sg:province":"Alicante",
    "wof:name":"Limpiezas Y Comercial La Rosa Blanca S.l.",
    "wof:placetype":"venue"
},
  "geometry": {"coordinates":[-0.4763880074,38.360786438],"type":"Point"}
}