{
  "type": "Feature",
  "properties": {
    "iso:country":"ES",
    "sg:address":"Calle de Olmo De Teclo, 32",
    "sg:city":"Casasimarro",
    "sg:orig_category":"Producci\u00d3n, Comercio De Cereales",
    "sg:phone":"+34 967 48 78 17",
    "sg:postcode":"16239",
    "sg:province":"Cuenca",
    "wof:name":"Comercial Sanchez Tebar S.l.",
    "wof:placetype":"venue"
},
  "geometry": {"coordinates":[-2.0325450897,39.3923912048],"type":"Point"}
}