{
  "type": "Feature",
  "properties": {
    "iso:country":"ES",
    "sg:address":"Carr Paer Casanovas, 12",
    "sg:city":"Lleida",
    "sg:orig_category":"Inform\u00c1tica (estudios, Servicios, Asesor\u00cda, Formaci\u00d3n)",
    "sg:phone":"+34 973 72 70 02",
    "sg:postcode":"25004",
    "sg:province":"Lleida",
    "sg:website":"www.ids.es.",
    "wof:name":"Informatica Del Segre S.l.",
    "wof:placetype":"venue"
},
  "geometry": {"coordinates":[0.6252769828,41.6226959229],"type":"Point"}
}