{
  "type": "Feature",
  "properties": {
    "addr:full":"Plaz Villa (la), 1 Mora Rubielos Teruel 44400",
    "addr:housenumber":"1",
    "addr:postcode":"44400",
    "iso:country":"ES",
    "sg:address":"Plaz Villa (la), 1",
    "sg:city":"Mora Rubielos",
    "sg:orig_category":"Oficinas De Turismo, Asociaciones De Iniciativa",
    "sg:phone":"+34 978 80 61 32",
    "sg:postcode":"44400",
    "sg:province":"Teruel",
    "wof:name":"Ayuntamiento De Mora De Rubielos",
    "wof:placetype":"venue"
},
  "geometry": {"coordinates":[-0.7552589774,40.2504005432],"type":"Point"}
}