{
  "type": "Feature",
  "properties": {
    "iso:country":"ES",
    "sg:address":"Carrer de Vall, 63",
    "sg:city":"Canet Mar",
    "sg:orig_category":"Venta De Caravanas, Casas M\u00d3viles, Camping",
    "sg:phone":"+34 937 94 21 05",
    "sg:postcode":"08360",
    "sg:province":"Barcelona",
    "wof:name":"Sport Caravaning Canet S. A.",
    "wof:placetype":"venue"
},
  "geometry": {"coordinates":[2.5845899582,41.588180542],"type":"Point"}
}