{
  "type": "Feature",
  "properties": {
    "addr:full":"Grup San Carlos, S/n Sevilla Sevilla 41008",
    "addr:housenumber":"s / n",
    "addr:postcode":"41008",
    "addr:street":"San Carlos",
    "iso:country":"ES",
    "sg:address":"Grup San Carlos, S/n",
    "sg:city":"Sevilla",
    "sg:orig_category":"Carnicer\u00cdas, Carnicer\u00cdas",
    "sg:phone":"+34 954 41 70 51",
    "sg:postcode":"41008",
    "sg:province":"Sevilla",
    "wof:name":"Florindo Gomez Sdad.coop.andaluza",
    "wof:placetype":"venue"
},
  "geometry": {"coordinates":[-5.9776787758,37.3983459473],"type":"Point"}
}