{
  "type": "Feature",
  "properties": {
    "iso:country":"ES",
    "sg:address":"Calle de Avenida De Los Fueros, 18",
    "sg:city":"Monteagudo",
    "sg:orig_category":"Productores Recolectores, Venta Directa De Vinos",
    "sg:phone":"+34 948 84 31 02",
    "sg:postcode":"31522",
    "sg:province":"Navarra",
    "wof:name":"Bodega Cooperativa Nuestra Se\u00f1ora Del Camino",
    "wof:placetype":"venue"
},
  "geometry": {"coordinates":[-1.6918389797,41.9618530273],"type":"Point"}
}