{
  "type": "Feature",
  "properties": {
    "addr:full":"Plaz Antonio Martelo, 7 Sevilla Sevilla 41008",
    "addr:housenumber":"7",
    "addr:postcode":"41008",
    "addr:street":"Martelo",
    "iso:country":"ES",
    "sg:address":"Plaz Antonio Martelo, 7",
    "sg:city":"Sevilla",
    "sg:orig_category":"Asesor\u00cda Sobre Comunicaci\u00d3n De Empresas",
    "sg:phone":"+34 954 41 00 36",
    "sg:postcode":"41008",
    "sg:province":"Sevilla",
    "sg:website":"www.agedata.com.es",
    "wof:name":"Analisis Y Gestion De Datos S.l.",
    "wof:placetype":"venue"
},
  "geometry": {"coordinates":[-5.9647536278,37.405921936],"type":"Point"}
}