{
  "type": "Feature",
  "properties": {
    "iso:country":"ES",
    "sg:address":"Plaz Plazuela (la), 17",
    "sg:city":"Alcala Guadaira",
    "sg:orig_category":"Farmacias",
    "sg:phone":"+34 955 68 51 04",
    "sg:postcode":"41500",
    "sg:province":"Sevilla",
    "wof:name":"Farmacia Garcia Donas C.b.",
    "wof:placetype":"venue"
},
  "geometry": {"coordinates":[-5.8398590088,37.3383140564],"type":"Point"}
}