{
  "type": "Feature",
  "properties": {
    "addr:full":"Jardines, 1816 Mijas Costa M\u00e1laga 29649",
    "addr:postcode":"29649",
    "addr:street":"Mijas Costa Ma\u0301Laga",
    "iso:country":"ES",
    "sg:address":"Jardines, 1816",
    "sg:city":"Mijas Costa",
    "sg:orig_category":"Quincaller\u00cda (al Por Menor)",
    "sg:phone":"+34 952 93 93 11",
    "sg:postcode":"29649",
    "sg:province":"M\u00e1laga",
    "wof:name":"Mu\u00f1oz Sanchez Juan",
    "wof:placetype":"venue"
},
  "geometry": {"coordinates":[-4.7157039642,36.4931945801],"type":"Point"}
}