{
  "type": "Feature",
  "properties": {
    "iso:country":"ES",
    "sg:address":"Av Granvia, 9",
    "sg:city":"Hospitalet Llobregat",
    "sg:orig_category":"Papeler\u00cdas, Librer\u00cdas",
    "sg:phone":"+34 933 32 97 92",
    "sg:postcode":"08908",
    "sg:province":"Barcelona",
    "wof:name":"Reyes Cuenca Beatriz",
    "wof:placetype":"venue"
},
  "geometry": {"coordinates":[2.1336729527,41.3630599976],"type":"Point"}
}