{
  "type": "Feature",
  "properties": {
    "iso:country":"ES",
    "sg:address":"Cno. Los Jarales, 67",
    "sg:city":"Purias",
    "sg:orig_category":"Carnicer\u00cdas, Carnicer\u00cdas",
    "sg:phone":"+34 968 48 21 01",
    "sg:postcode":"30813",
    "sg:province":"Murcia",
    "wof:name":"Embutidos Pedro Y Cati S.l.",
    "wof:placetype":"venue"
},
  "geometry": {"coordinates":[-1.7215889692,37.491394043],"type":"Point"}
}