{
  "type": "Feature",
  "properties": {
    "addr:full":"Calle de Navarra, 2 Astillero Cantabria 39610",
    "addr:housenumber":"2",
    "addr:postcode":"39610",
    "addr:street":"Calle De Navarra",
    "iso:country":"ES",
    "sg:address":"Calle de Navarra, 2",
    "sg:city":"Astillero",
    "sg:orig_category":"Sociedades, Compa\u00d1\u00cdas Aseguradoras",
    "sg:phone":"+34 942 54 03 69",
    "sg:postcode":"39610",
    "sg:province":"Cantabria",
    "wof:name":"Sainz De La Maza Del Castillo Angel",
    "wof:placetype":"venue"
},
  "geometry": {"coordinates":[-3.8225328922,43.3994178772],"type":"Point"}
}