{
  "type": "Feature",
  "properties": {
    "addr:full":"Carrer de Neptu, 14 Barcelona Barcelona 08006",
    "addr:housenumber":"14",
    "addr:postcode":"08006",
    "addr:street":"Carrer De Neptu",
    "iso:country":"ES",
    "sg:address":"Carrer de Neptu, 14",
    "sg:city":"Barcelona",
    "sg:orig_category":"Guarder\u00cdas",
    "sg:phone":"+34 932 37 41 07",
    "sg:postcode":"08006",
    "sg:province":"Barcelona",
    "wof:name":"Ramos Mellado Josefa Araceli",
    "wof:placetype":"venue"
},
  "geometry": {"coordinates":[2.1549739838,41.3977203369],"type":"Point"}
}