{
  "type": "Feature",
  "properties": {
    "addr:full":"Rua De Compostela, 18 Ordes La Coru\u00f1a 15680",
    "addr:housenumber":"18",
    "addr:postcode":"15680",
    "addr:street":"Rua De Compostela;La Corun\u0303A",
    "iso:country":"ES",
    "sg:address":"Rua De Compostela, 18",
    "sg:city":"Ordes",
    "sg:orig_category":"Pizzer\u00cdas",
    "sg:phone":"+34 981 69 75 48",
    "sg:postcode":"15680",
    "sg:province":"La Coru\u00f1a",
    "wof:name":"Remui\u00f1an Iglesias Jose",
    "wof:placetype":"venue"
},
  "geometry": {"coordinates":[-8.4083223343,43.0779838562],"type":"Point"}
}