{
  "type": "Feature",
  "properties": {
    "addr:full":"Calle de Alemania, S/n Gri\u00f1on Madrid 28971",
    "addr:housenumber":"s / n",
    "addr:postcode":"28971",
    "addr:street":"Calle De Alemania",
    "iso:country":"ES",
    "sg:address":"Calle de Alemania, S/n",
    "sg:city":"Gri\u00f1on",
    "sg:orig_category":"Fabricaci\u00d3n De Bibliotecas Y Estanter\u00cdas",
    "sg:phone":"+34 918 14 03 94",
    "sg:postcode":"28971",
    "sg:province":"Madrid",
    "wof:name":"J.c. Dise\u00f1o Inmobiliario S.l.",
    "wof:placetype":"venue"
},
  "geometry": {"coordinates":[-3.8605632782,40.2063598633],"type":"Point"}
}