{
  "type": "Feature",
  "properties": {
    "addr:full":"Calle de Teruel, 17 Cordoba C\u00f3rdoba 14012",
    "addr:housenumber":"17",
    "addr:postcode":"14012",
    "addr:street":"Calle De Teruel;Co\u0301Rdoba",
    "iso:country":"ES",
    "sg:address":"Calle de Teruel, 17",
    "sg:city":"Cordoba",
    "sg:orig_category":"M\u00c9dicos: Oftalmolog\u00cda",
    "sg:phone":"+34 957 40 03 75",
    "sg:postcode":"14012",
    "sg:province":"C\u00f3rdoba",
    "wof:name":"Gimenez Almenara Parada Guillermo",
    "wof:placetype":"venue"
},
  "geometry": {"coordinates":[-4.7880530357,37.8986434937],"type":"Point"}
}