{
  "type": "Feature",
  "properties": {
    "addr:full":"Av Borbo, 58 Barcelona Barcelona 08016",
    "addr:housenumber":"58",
    "addr:postcode":"08016",
    "addr:street":"Av Borbo",
    "iso:country":"ES",
    "sg:address":"Av Borbo, 58",
    "sg:city":"Barcelona",
    "sg:orig_category":"Sociedades, Compa\u00d1\u00cdas Aseguradoras",
    "sg:phone":"+34 934 08 60 18",
    "sg:postcode":"08016",
    "sg:province":"Barcelona",
    "wof:name":"Luna Bravo Joaquin",
    "wof:placetype":"venue"
},
  "geometry": {"coordinates":[2.1748719215,41.4283027649],"type":"Point"}
}