{
  "type": "Feature",
  "properties": {
    "iso:country":"ES",
    "sg:address":"Calle de Adosinda, 12",
    "sg:city":"Gijon",
    "sg:orig_category":"Bisuter\u00cda, Joyer\u00cda, Relojer\u00cda (al Por Menor)",
    "sg:phone":"+34 985 33 77 23",
    "sg:postcode":"33202",
    "sg:province":"Asturias",
    "wof:name":"Goldenart Gijon S.l.",
    "wof:placetype":"venue"
},
  "geometry": {"coordinates":[-5.6550393105,43.5377578735],"type":"Point"}
}