{
  "type": "Feature",
  "properties": {
    "iso:country":"ES",
    "sg:address":"Avda Alhambra, 2",
    "sg:city":"Almeria",
    "sg:orig_category":"Agencias Y Agentes Comerciales, Representantes",
    "sg:phone":"+34 950 15 00 70",
    "sg:postcode":"04007",
    "sg:province":"Almer\u00eda",
    "wof:name":"Omebios Iberica S.l.",
    "wof:placetype":"venue"
},
  "geometry": {"coordinates":[-2.4462590218,36.8262290955],"type":"Point"}
}