{
  "type": "Feature",
  "properties": {
    "addr:full":"Calle de Zapateria, 45 Vitoria-gasteiz \u00c1lava 01001",
    "addr:housenumber":"45",
    "addr:postcode":"01001",
    "addr:street":"Calle De Zapateria",
    "iso:country":"ES",
    "sg:address":"Calle de Zapateria, 45",
    "sg:city":"Vitoria-gasteiz",
    "sg:orig_category":"Molduras, Junquillos, Listones Y Molduras Perforadas",
    "sg:phone":"+34 945 25 22 29",
    "sg:postcode":"01001",
    "sg:province":"\u00c1lava",
    "wof:name":"Union 84 S. A.",
    "wof:placetype":"venue"
},
  "geometry": {"coordinates":[-2.6742830276,42.8485374451],"type":"Point"}
}