{
  "type": "Feature",
  "properties": {
    "iso:country":"ES",
    "sg:address":"Calle de Elcano, 7",
    "sg:city":"Bilbao",
    "sg:orig_category":"Expertos Contables, Revisores De Cuentas",
    "sg:phone":"+34 944 23 32 72",
    "sg:postcode":"48011",
    "sg:province":"Vizcaya",
    "wof:name":"Erizo S.a.",
    "wof:placetype":"venue"
},
  "geometry": {"coordinates":[-2.9352049828,43.2635955811],"type":"Point"}
}