{
  "type": "Feature",
  "properties": {
    "addr:full":"Calle de Pepe Luces, 6 Alcala Guadaira Sevilla 41500",
    "addr:housenumber":"6",
    "addr:postcode":"41500",
    "addr:street":"Calle De Pepe Luces",
    "iso:country":"ES",
    "sg:address":"Calle de Pepe Luces, 6",
    "sg:city":"Alcala Guadaira",
    "sg:orig_category":"Estancos",
    "sg:phone":"+34 955 61 31 36",
    "sg:postcode":"41500",
    "sg:province":"Sevilla",
    "wof:name":"Ordo\u00f1ez Mejia Margarita",
    "wof:placetype":"venue"
},
  "geometry": {"coordinates":[-5.8387641907,37.3397636414],"type":"Point"}
}