{
  "type": "Feature",
  "properties": {
    "iso:country":"ES",
    "sg:address":"Pg Maragall, 20",
    "sg:city":"Barcelona",
    "sg:orig_category":"Farmacias",
    "sg:phone":"+34 934 36 33 65",
    "sg:postcode":"08026",
    "sg:province":"Barcelona",
    "wof:name":"Borras Sampere Laia",
    "wof:placetype":"venue"
},
  "geometry": {"coordinates":[2.1811330318,41.4143104553],"type":"Point"}
}