{
  "type": "Feature",
  "properties": {
    "iso:country":"ES",
    "sg:address":"Calle de Mariano Suarez Pola, 15",
    "sg:city":"Luanco",
    "sg:orig_category":"Alimentaci\u00d3n General (al Por Menor)",
    "sg:phone":"+34 985 88 02 39",
    "sg:postcode":"33440",
    "sg:province":"Asturias",
    "wof:name":"Rodriguez Rodriguez Ana Maria",
    "wof:placetype":"venue"
},
  "geometry": {"coordinates":[-5.7966690063,43.6147003174],"type":"Point"}
}