{
  "type": "Feature",
  "properties": {
    "addr:full":"Avda Rosalia De Castro, 16 Santa Uxia De Ribeira La Coru\u00f1a 15960",
    "addr:housenumber":"16",
    "addr:postcode":"15960",
    "addr:street":"Avda Rosalia De Castro;Corun\u0303A",
    "iso:country":"ES",
    "sg:address":"Avda Rosalia De Castro, 16",
    "sg:city":"Santa Uxia De Ribeira",
    "sg:orig_category":"Servicios Gsm",
    "sg:phone":"+34 981 87 20 56",
    "sg:postcode":"15960",
    "sg:province":"La Coru\u00f1a",
    "wof:name":"Jaos S.c.",
    "wof:placetype":"venue"
},
  "geometry": {"coordinates":[-8.9923086166,42.5550689697],"type":"Point"}
}