{
  "type": "Feature",
  "properties": {
    "iso:country":"ES",
    "sg:address":"Calle de Versalles, 2",
    "sg:city":"Errenteria",
    "sg:orig_category":"Guarda",
    "sg:phone":"+34 943 52 35 06",
    "sg:postcode":"20100",
    "sg:province":"Guip\u00f9zcoa",
    "wof:name":"Hernandez Redondo Juan Francisco",
    "wof:placetype":"venue"
},
  "geometry": {"coordinates":[-1.9093110561,43.3155632019],"type":"Point"}
}