{
  "type": "Feature",
  "properties": {
    "addr:full":"Calle de Mayor, 95 Puente Tocinos Murcia 30006",
    "addr:housenumber":"95",
    "addr:postcode":"30006",
    "addr:street":"Calle De Mayor",
    "iso:country":"ES",
    "sg:address":"Calle de Mayor, 95",
    "sg:city":"Puente Tocinos",
    "sg:orig_category":"Bazares, Art\u00cdculos De Limpieza Y De Cocina (al Por Menor)",
    "sg:phone":"+34 968 30 08 10",
    "sg:postcode":"30006",
    "sg:province":"Murcia",
    "wof:name":"Torres Lopez Jose",
    "wof:placetype":"venue"
},
  "geometry": {"coordinates":[-1.1016801596,37.9937400818],"type":"Point"}
}