{
  "type": "Feature",
  "properties": {
    "iso:country":"ES",
    "sg:address":"Pg Desemparats, 97",
    "sg:city":"Olot",
    "sg:orig_category":"Fabricaci\u00d3n, Importaci\u00d3n De L\u00c1mparas Y Bombillas",
    "sg:phone":"+34 972 27 19 59",
    "sg:postcode":"17800",
    "sg:province":"Girona",
    "wof:name":"Aigua I Llum Olot S.l.u",
    "wof:placetype":"venue"
},
  "geometry": {"coordinates":[2.480148077,42.1777114868],"type":"Point"}
}