{
  "type": "Feature",
  "properties": {
    "iso:country":"ES",
    "sg:address":"Avda Catalu\u00d1a, 16",
    "sg:city":"Valencia",
    "sg:orig_category":"Arquitectos",
    "sg:phone":"+34 963 61 39 17",
    "sg:postcode":"46021",
    "sg:province":"Valencia",
    "wof:name":"Rodrigo Alfonso Jose Manuel",
    "wof:placetype":"venue"
},
  "geometry": {"coordinates":[-0.3540250063,39.4787788391],"type":"Point"}
}