{
  "type": "Feature",
  "properties": {
    "addr:full":"Herriko Plaza, 5 Aretxabaleta Guip\u00f9zcoa 20550",
    "addr:housenumber":"5",
    "addr:postcode":"20550",
    "addr:street":"Herriko Plaza;Guipu\u0300Zcoa",
    "iso:country":"ES",
    "sg:address":"Herriko Plaza, 5",
    "sg:city":"Aretxabaleta",
    "sg:orig_category":"Peluqueros: De Se\u00d1oras",
    "sg:phone":"+34 943 79 83 64",
    "sg:postcode":"20550",
    "sg:province":"Guip\u00f9zcoa",
    "wof:name":"Perez Gonzalez Maria Teresa",
    "wof:placetype":"venue"
},
  "geometry": {"coordinates":[-2.5037250519,43.0359382629],"type":"Point"}
}