{
  "type": "Feature",
  "properties": {
    "addr:full":"Pase Pago De La Perdiz (del), S/n Berrocales Del Jarama Madrid 28861",
    "addr:housenumber":"/ n",
    "addr:postcode":"28861",
    "addr:street":"S",
    "iso:country":"ES",
    "sg:address":"Pase Pago De La Perdiz (del), S/n",
    "sg:city":"Berrocales Del Jarama",
    "sg:orig_category":"Cooperativas Agr\u00cdcolas",
    "sg:phone":"+34 916 75 77 90",
    "sg:postcode":"28861",
    "sg:province":"Madrid",
    "wof:name":"Cooperativa Viviendas Los Berrocales Del Jarama",
    "wof:placetype":"venue"
},
  "geometry": {"coordinates":[-3.5061790943,40.4719467163],"type":"Point"}
}