{
  "type": "Feature",
  "properties": {
    "addr:full":"Calle de Donato Arguelles, 1 Gijon Asturias 33206",
    "addr:housenumber":"1",
    "addr:postcode":"33206",
    "addr:street":"Calle De Donato Arguelles",
    "iso:country":"ES",
    "sg:address":"Calle de Donato Arguelles, 1",
    "sg:city":"Gijon",
    "sg:orig_category":"M\u00c9dicos: Cirug\u00cda General",
    "sg:phone":"+34 985 35 92 17",
    "sg:postcode":"33206",
    "sg:province":"Asturias",
    "wof:name":"Fernandez Gonzalez Inocencio",
    "wof:placetype":"venue"
},
  "geometry": {"coordinates":[-5.6652197838,43.541431427],"type":"Point"}
}