{
  "type": "Feature",
  "properties": {
    "iso:country":"ES",
    "sg:address":"Ctra Zamora, Km. 0155,0",
    "sg:city":"Onzonilla",
    "sg:orig_category":"Transportes Frigor\u00cdficos",
    "sg:phone":"+34 987 28 88 01",
    "sg:postcode":"24231",
    "sg:province":"Le\u00f3n",
    "sg:website":"www.logileon.com",
    "wof:name":"Logileon S.l.",
    "wof:placetype":"venue"
},
  "geometry": {"coordinates":[-5.5841016769,42.5285339355],"type":"Point"}
}