{
  "type": "Feature",
  "properties": {
    "addr:full":"Calle de Farolas, 8 Alcazaren Valladolid 47238",
    "addr:housenumber":"8",
    "addr:postcode":"47238",
    "addr:street":"Calle De Farolas",
    "iso:country":"ES",
    "sg:address":"Calle de Farolas, 8",
    "sg:city":"Alcazaren",
    "sg:orig_category":"Frutas Y Legumbres Secas (al Por Mayor)",
    "sg:phone":"+34 983 60 90 10",
    "sg:postcode":"47238",
    "sg:province":"Valladolid",
    "wof:name":"Frutos Secos Alcazarin S.l.",
    "wof:placetype":"venue"
},
  "geometry": {"coordinates":[-4.6770610809,41.3671340942],"type":"Point"}
}