{
  "type": "Feature",
  "properties": {
    "addr:full":"Carrer de Santa Marta, 1 Mataro Barcelona 08302",
    "addr:housenumber":"1",
    "addr:postcode":"08302",
    "addr:street":"Carrer De Santa Marta",
    "iso:country":"ES",
    "sg:address":"Carrer de Santa Marta, 1",
    "sg:city":"Mataro",
    "sg:orig_category":"Partidos Pol\u00cdticos",
    "sg:phone":"+34 937 96 34 61",
    "sg:postcode":"08302",
    "sg:province":"Barcelona",
    "wof:name":"Partit Socialista De Catalunya",
    "wof:placetype":"venue"
},
  "geometry": {"coordinates":[2.442647934,41.5382156372],"type":"Point"}
}