{
  "type": "Feature",
  "properties": {
    "iso:country":"ES",
    "sg:address":"Avenida De Dolores, 17",
    "sg:city":"Pozo Alcon",
    "sg:orig_category":"Reposter\u00cdas",
    "sg:phone":"+34 953 73 88 32",
    "sg:postcode":"23485",
    "sg:province":"Ja\u00e9n",
    "wof:name":"Cano Montoya Jose Luis",
    "wof:placetype":"venue"
},
  "geometry": {"coordinates":[-2.9366390705,37.7039985657],"type":"Point"}
}