{
  "type": "Feature",
  "properties": {
    "iso:country":"ES",
    "sg:address":"Calle de Bonaire, 42",
    "sg:city":"Sant Mateu",
    "sg:orig_category":"Electrodom\u00c9sticos (al Por Menor)",
    "sg:phone":"+34 964 41 61 96",
    "sg:postcode":"12170",
    "sg:province":"Castell\u00f3n",
    "sg:website":"www.redelite.es",
    "wof:name":"Cifre Tena Fernando",
    "wof:placetype":"venue"
},
  "geometry": {"coordinates":[0.1785899997,40.4668502808],"type":"Point"}
}