{
  "type": "Feature",
  "properties": {
    "iso:country":"ES",
    "sg:address":"Polig. Ind. El Sutu, S/n",
    "sg:city":"Pola De Laviana",
    "sg:orig_category":"Condimentos, Especias, Vinagres, Salsas Preparadas (fabricaci\u00d3n, Al Por Mayor)",
    "sg:phone":"+34 985 61 01 76",
    "sg:postcode":"33980",
    "sg:province":"Asturias",
    "wof:name":"Agromarco S.l",
    "wof:placetype":"venue"
},
  "geometry": {"coordinates":[-5.563391,43.245335],"type":"Point"}
}