{
  "type": "Feature",
  "properties": {
    "addr:full":"Solana, 124 Cuenca Cuenca 16004",
    "addr:housenumber":"124",
    "addr:postcode":"16004",
    "addr:street":"Solana",
    "iso:country":"ES",
    "sg:address":"Solana, 124",
    "sg:city":"Cuenca",
    "sg:orig_category":"Bebidas",
    "sg:phone":"+34 969 21 00 18",
    "sg:postcode":"16004",
    "sg:province":"Cuenca",
    "wof:name":"Distribuciones Zarco Ballesteros S.l.",
    "wof:placetype":"venue"
},
  "geometry": {"coordinates":[-2.1362390518,40.0720710754],"type":"Point"}
}