{
  "type": "Feature",
  "properties": {
    "iso:country":"ES",
    "sg:address":"Calle de Manuel Gutierrez, 6",
    "sg:city":"Mieres",
    "sg:orig_category":"Electricidad: Instaladores",
    "sg:phone":"+34 985 46 35 52",
    "sg:postcode":"33600",
    "sg:province":"Asturias",
    "wof:name":"Estrella Polar Mieres S.l.",
    "wof:placetype":"venue"
},
  "geometry": {"coordinates":[-5.775167942,43.2518730164],"type":"Point"}
}