{
  "type": "Feature",
  "properties": {
    "addr:full":"Carrer de Doctor Trueta, 12 Castelldefels Barcelona 08860",
    "addr:housenumber":"12",
    "addr:postcode":"08860",
    "addr:street":"Carrer De Doctor Trueta",
    "iso:country":"ES",
    "sg:address":"Carrer de Doctor Trueta, 12",
    "sg:city":"Castelldefels",
    "sg:orig_category":"Cl\u00cdnicas Dentales",
    "sg:phone":"+34 936 36 29 87",
    "sg:postcode":"08860",
    "sg:province":"Barcelona",
    "wof:name":"Pugach Fridman Arturo",
    "wof:placetype":"venue"
},
  "geometry": {"coordinates":[1.9770690203,41.2794799805],"type":"Point"}
}