{
  "type": "Feature",
  "properties": {
    "addr:full":"Calle de Menendez Y Pelayo, 19 Palmas De Gran Canaria Las Palmas 35006",
    "addr:postcode":"35006",
    "addr:street":"Calle De Menendez Y Pelayo",
    "iso:country":"ES",
    "sg:address":"Calle de Menendez Y Pelayo, 19",
    "sg:city":"Palmas De Gran Canaria",
    "sg:orig_category":"Agencias De Viajes",
    "sg:phone":"+34 928 24 28 30",
    "sg:postcode":"35006",
    "sg:province":"Las Palmas",
    "wof:name":"Canarias Last Minute Bookings S.l.",
    "wof:placetype":"venue"
},
  "geometry": {"coordinates":[-15.4319486618,28.1332511902],"type":"Point"}
}