{
  "type": "Feature",
  "properties": {
    "addr:full":"Carr Nou, 14 Girona Girona 17001",
    "addr:housenumber":"14",
    "addr:postcode":"17001",
    "addr:street":"Carr Nou",
    "iso:country":"ES",
    "sg:address":"Carr Nou, 14",
    "sg:city":"Girona",
    "sg:orig_category":"Ense\u00d1anza: Idiomas",
    "sg:phone":"+34 972 21 34 45",
    "sg:postcode":"17001",
    "sg:province":"Girona",
    "wof:name":"Idiomas Girona S.l.",
    "wof:placetype":"venue"
},
  "geometry": {"coordinates":[2.8187448978,41.9808616638],"type":"Point"}
}