{
  "type": "Feature",
  "properties": {
    "iso:country":"ES",
    "sg:address":"Carrer de Alcover, 16",
    "sg:city":"Castelldefels",
    "sg:orig_category":"Asilos De Ancianos. Centros Privados",
    "sg:phone":"+34 936 65 35 92",
    "sg:postcode":"08860",
    "sg:province":"Barcelona",
    "wof:name":"Residencia Per Gent Gran Vellamar S.l.",
    "wof:placetype":"venue"
},
  "geometry": {"coordinates":[1.9477020502,41.2723236084],"type":"Point"}
}