{
  "type": "Feature",
  "properties": {
    "iso:country":"ES",
    "sg:address":"C/ Jaume Ii, 15",
    "sg:city":"Manacor",
    "sg:orig_category":"Confecci\u00d3n De Trajes Para Se\u00d1oras",
    "sg:phone":"+34 971 55 32 02",
    "sg:postcode":"07500",
    "sg:province":"Islas Baleares",
    "wof:name":"Pachon Perez Esperanza",
    "wof:placetype":"venue"
},
  "geometry": {"coordinates":[3.227793932,39.5640945435],"type":"Point"}
}