{
  "type": "Feature",
  "properties": {
    "iso:country":"ES",
    "sg:address":"Calle de Francisco Silvela, 96",
    "sg:city":"Madrid",
    "sg:orig_category":"Papeler\u00cdas, Librer\u00cdas",
    "sg:phone":"+34 915 61 62 60",
    "sg:postcode":"28002",
    "sg:province":"Madrid",
    "wof:name":"Fernandez Perez Alicia",
    "wof:placetype":"venue"
},
  "geometry": {"coordinates":[-3.6782886982,40.4384231567],"type":"Point"}
}