{
  "type": "Feature",
  "properties": {
    "addr:full":"Jazinto Olabe Plaza, 4 Eibar Guip\u00f9zcoa 20600",
    "addr:housenumber":"4",
    "addr:postcode":"20600",
    "addr:street":"Jazinto Olabe Plaza;Guipu\u0300Zcoa",
    "iso:country":"ES",
    "sg:address":"Jazinto Olabe Plaza, 4",
    "sg:city":"Eibar",
    "sg:orig_category":"Peluqueros: De Se\u00d1oras",
    "sg:phone":"+34 943 82 12 77",
    "sg:postcode":"20600",
    "sg:province":"Guip\u00f9zcoa",
    "wof:name":"Carral Garcia Leire",
    "wof:placetype":"venue"
},
  "geometry": {"coordinates":[-2.4884390831,43.1800117493],"type":"Point"}
}