{
  "type": "Feature",
  "properties": {
    "iso:country":"ES",
    "sg:address":"Carrer de Segle Xx, 7",
    "sg:city":"Barcelona",
    "sg:orig_category":"Cl\u00cdnicas M\u00c9dicas",
    "sg:phone":"+34 934 08 60 00",
    "sg:postcode":"08041",
    "sg:province":"Barcelona",
    "wof:name":"Centro Asistencial Maragall S.l.",
    "wof:placetype":"venue"
},
  "geometry": {"coordinates":[2.178237915,41.4223518372],"type":"Point"}
}