{
  "type": "Feature",
  "properties": {
    "addr:full":"Calle de Matias Lopez, 20 Gran Tarajal Las Palmas 35620",
    "addr:housenumber":"20",
    "addr:postcode":"35620",
    "addr:street":"Calle De Matias Lopez;Palmas",
    "iso:country":"ES",
    "sg:address":"Calle de Matias Lopez, 20",
    "sg:city":"Gran Tarajal",
    "sg:orig_category":"Expertos Contables",
    "sg:phone":"+34 928 16 27 58",
    "sg:postcode":"35620",
    "sg:province":"Las Palmas",
    "wof:name":"Atabal Consulting",
    "wof:placetype":"venue"
},
  "geometry": {"coordinates":[-14.0225496292,28.2106647491],"type":"Point"}
}