{
  "type": "Feature",
  "properties": {
    "addr:full":"C/ Maestro Albeniz, 19 Elche Alicante 03202",
    "addr:housenumber":"19",
    "addr:postcode":"03202",
    "addr:street":"C / Maestro Albeniz",
    "iso:country":"ES",
    "sg:address":"C/ Maestro Albeniz, 19",
    "sg:city":"Elche",
    "sg:orig_category":"Comercio De Mobiliario De Oficina",
    "sg:phone":"+34 965 42 07 51",
    "sg:postcode":"03202",
    "sg:province":"Alicante",
    "wof:name":"Muebles Albeniz S. L.",
    "wof:placetype":"venue"
},
  "geometry": {"coordinates":[-0.6949750185,38.2685241699],"type":"Point"}
}