{
  "type": "Feature",
  "properties": {
    "addr:full":"Calle de Rosa, 8 Consuegra Toledo 45700",
    "addr:housenumber":"8",
    "addr:postcode":"45700",
    "addr:street":"Calle De Rosa",
    "iso:country":"ES",
    "sg:address":"Calle de Rosa, 8",
    "sg:city":"Consuegra",
    "sg:orig_category":"Combustibles: Fuel",
    "sg:phone":"+34 925 48 02 02",
    "sg:postcode":"45700",
    "sg:province":"Toledo",
    "wof:name":"Gallego Punzon Guillermo",
    "wof:placetype":"venue"
},
  "geometry": {"coordinates":[-3.6086680889,39.4647712708],"type":"Point"}
}