{
  "type": "Feature",
  "properties": {
    "addr:full":"Plaz Asturias (de), 3 Partija-santa Monica Madrid 28529",
    "addr:postcode":"28529",
    "addr:street":"Plaz",
    "iso:country":"ES",
    "sg:address":"Plaz Asturias (de), 3",
    "sg:city":"Partija-santa Monica",
    "sg:orig_category":"Abogados",
    "sg:phone":"+34 913 01 23 13",
    "sg:postcode":"28529",
    "sg:province":"Madrid",
    "wof:name":"Mari\u00f1o Hidalgo Asuncion",
    "wof:placetype":"venue"
},
  "geometry": {"coordinates":[-3.5102670193,40.314289093],"type":"Point"}
}