{
  "type": "Feature",
  "properties": {
    "addr:full":"Avgd De L'almaig, 79 Ontinyent Valencia 46870",
    "addr:housenumber":"79",
    "addr:postcode":"46870",
    "iso:country":"ES",
    "sg:address":"Avgd De L'almaig, 79",
    "sg:city":"Ontinyent",
    "sg:orig_category":"Ingenier\u00cda, Centros De Estudios (diversos)",
    "sg:phone":"+34 962 91 60 35",
    "sg:postcode":"46870",
    "sg:province":"Valencia",
    "wof:name":"Cambra Soriano Francisco Ramon",
    "wof:placetype":"venue"
},
  "geometry": {"coordinates":[-0.6036059856,38.8186798096],"type":"Point"}
}