{
  "type": "Feature",
  "properties": {
    "iso:country":"ES",
    "sg:address":"Avda Zaragoza, 35",
    "sg:city":"Pina De Ebro",
    "sg:orig_category":"Centros M\u00c9dicos Y Sociales, Dispensarios",
    "sg:phone":"+34 976 16 51 53",
    "sg:postcode":"50750",
    "sg:province":"Zaragoza",
    "wof:name":"Ayuntamiento De Pina De Ebro",
    "wof:placetype":"venue"
},
  "geometry": {"coordinates":[-0.5325790048,41.4904022217],"type":"Point"}
}