{
  "type": "Feature",
  "properties": {
    "addr:full":"Rua Policarpo Sanz, 3 Vigo Pontevedra 36202",
    "addr:housenumber":"3",
    "addr:postcode":"36202",
    "addr:street":"Rua Policarpo Sanz",
    "iso:country":"ES",
    "sg:address":"Rua Policarpo Sanz, 3",
    "sg:city":"Vigo",
    "sg:orig_category":"Promotores Constructores",
    "sg:phone":"+34 986 22 47 07",
    "sg:postcode":"36202",
    "sg:province":"Pontevedra",
    "sg:website":"www.apecpo.es",
    "wof:name":"Asociacion Provincial De Empresarios De La Construccion",
    "wof:placetype":"venue"
},
  "geometry": {"coordinates":[-8.7236700058,42.2376480103],"type":"Point"}
}