{
  "type": "Feature",
  "properties": {
    "addr:full":"Calle de Fueros De Arnedo, 5 Arnedo La Rioja 26580",
    "addr:housenumber":"5",
    "addr:postcode":"26580",
    "addr:street":"Calle De Fueros De Arnedo;Rioja",
    "iso:country":"ES",
    "sg:address":"Calle de Fueros De Arnedo, 5",
    "sg:city":"Arnedo",
    "sg:orig_category":"Suministros Para Hoteles",
    "sg:phone":"+34 941 38 70 62",
    "sg:postcode":"26580",
    "sg:province":"La Rioja",
    "wof:name":"Exclusivas Arnedo S.l.",
    "wof:placetype":"venue"
},
  "geometry": {"coordinates":[-2.1087698936,42.2232437134],"type":"Point"}
}