{
  "type": "Feature",
  "properties": {
    "addr:full":"Avda Pasajes San Pedro, 29 Donostia-san Sebastian Guip\u00f9zcoa 20016",
    "addr:housenumber":"29",
    "addr:postcode":"20016",
    "addr:street":"Avda Pasajes San Pedro",
    "iso:country":"ES",
    "sg:address":"Avda Pasajes San Pedro, 29",
    "sg:city":"Donostia-san Sebastian",
    "sg:orig_category":"Plomeros",
    "sg:phone":"+34 943 40 02 26",
    "sg:postcode":"20016",
    "sg:province":"Guip\u00f9zcoa",
    "wof:name":"Juan Sanchez Martin",
    "wof:placetype":"venue"
},
  "geometry": {"coordinates":[-1.9394110441,43.3227233887],"type":"Point"}
}