{
  "type": "Feature",
  "properties": {
    "iso:country":"ES",
    "sg:address":"Calle de Pe\u00d1a, 4",
    "sg:city":"Haba",
    "sg:orig_category":"Caf\u00c9s, Bares, Cervecer\u00cdas",
    "sg:phone":"+34 924 82 32 09",
    "sg:postcode":"06714",
    "sg:province":"Badajoz",
    "wof:name":"Quintana Lorenzo Victoriano",
    "wof:placetype":"venue"
},
  "geometry": {"coordinates":[-5.8017048836,38.9186820984],"type":"Point"}
}