{
  "type": "Feature",
  "properties": {
    "iso:country":"ES",
    "sg:address":"Calle de Virgen De La Paz, 6",
    "sg:city":"Madrid",
    "sg:orig_category":"Molduras, Junquillos, Listones Y Molduras Perforadas",
    "sg:phone":"+34 914 03 10 53",
    "sg:postcode":"28027",
    "sg:province":"Madrid",
    "wof:name":"Fernandez Salas Jose Antonio",
    "wof:placetype":"venue"
},
  "geometry": {"coordinates":[-3.6597709656,40.4330711365],"type":"Point"}
}