{
  "type": "Feature",
  "properties": {
    "addr:full":"Avda Caceres, 7 Merida Badajoz 06800",
    "addr:housenumber":"7",
    "addr:postcode":"06800",
    "addr:street":"Avda Caceres",
    "iso:country":"ES",
    "sg:address":"Avda Caceres, 7",
    "sg:city":"Merida",
    "sg:orig_category":"Agencias Y Agentes Comerciales, Representantes",
    "sg:phone":"+34 924 30 11 86",
    "sg:postcode":"06800",
    "sg:province":"Badajoz",
    "wof:name":"Jacinto Almaraz Jose Maria",
    "wof:placetype":"venue"
},
  "geometry": {"coordinates":[-6.3464288712,38.9208984375],"type":"Point"}
}