{
  "type": "Feature",
  "properties": {
    "addr:full":"Carrer de Llull, 187 Barcelona Barcelona 08005",
    "addr:housenumber":"187",
    "addr:postcode":"08005",
    "addr:street":"Carrer De Llull",
    "iso:country":"ES",
    "sg:address":"Carrer de Llull, 187",
    "sg:city":"Barcelona",
    "sg:orig_category":"Peluqueros: De Se\u00d1oras",
    "sg:phone":"+34 933 00 91 79",
    "sg:postcode":"08005",
    "sg:province":"Barcelona",
    "wof:name":"Montelongo Martin Maria Delia",
    "wof:placetype":"venue"
},
  "geometry": {"coordinates":[2.2023189068,41.4012489319],"type":"Point"}
}