{
  "type": "Feature",
  "properties": {
    "addr:full":"Calle de Almacellas, 108 Binefar Huesca 22500",
    "addr:housenumber":"108",
    "addr:postcode":"22500",
    "addr:street":"Calle De Almacellas",
    "iso:country":"ES",
    "sg:address":"Calle de Almacellas, 108",
    "sg:city":"Binefar",
    "sg:orig_category":"Mec\u00c1nico Del Autom\u00d3vil",
    "sg:phone":"+34 974 42 84 30",
    "sg:postcode":"22500",
    "sg:province":"Huesca",
    "sg:website":"www.talleresnaval.com",
    "wof:name":"Talleres Jose Naval S.l.",
    "wof:placetype":"venue"
},
  "geometry": {"coordinates":[0.2979109883,41.8439254761],"type":"Point"}
}