{
  "type": "Feature",
  "properties": {
    "addr:full":"Calle de Seis De Junio, 26 Valdepe\u00f1as Ciudad Real 13300",
    "addr:housenumber":"26",
    "addr:postcode":"13300",
    "addr:street":"Calle De Seis De Junio",
    "iso:country":"ES",
    "sg:address":"Calle de Seis De Junio, 26",
    "sg:city":"Valdepe\u00f1as",
    "sg:orig_category":"Electrodom\u00c9sticos (al Por Menor)",
    "sg:phone":"+34 926 31 26 48",
    "sg:postcode":"13300",
    "sg:province":"Ciudad Real",
    "wof:name":"Jose Alvarez Perez Y Manuel Diaz Sanchez Cdad",
    "wof:placetype":"venue"
},
  "geometry": {"coordinates":[-3.387814045,38.7581520081],"type":"Point"}
}