{
  "type": "Feature",
  "properties": {
    "iso:country":"ES",
    "sg:address":"Valderrobres, 11",
    "sg:city":"Madrid",
    "sg:orig_category":"Farmacias",
    "sg:phone":"+34 917 41 00 48",
    "sg:postcode":"28022",
    "sg:province":"Madrid",
    "wof:name":"Rodriguez Jimenez Maria Del Carmen",
    "wof:placetype":"venue"
},
  "geometry": {"coordinates":[-3.6106650829,40.4442329407],"type":"Point"}
}