{
  "type": "Feature",
  "properties": {
    "iso:country":"ES",
    "sg:address":"Calle de Peru, 8",
    "sg:city":"Gri\u00f1on",
    "sg:orig_category":"Maquinaria Para Industrias Diversas",
    "sg:phone":"+34 918 14 12 06",
    "sg:postcode":"28971",
    "sg:province":"Madrid",
    "wof:name":"Avemafer S.l.",
    "wof:placetype":"venue"
},
  "geometry": {"coordinates":[-3.8456289768,40.2289009094],"type":"Point"}
}