{
  "type": "Feature",
  "properties": {
    "addr:full":"Calle de Barcelona, 19 Coru\u00d1a La Coru\u00f1a 15010",
    "addr:housenumber":"19",
    "addr:postcode":"15010",
    "addr:street":"Calle De Barcelona;La Corun\u0303A",
    "iso:country":"ES",
    "sg:address":"Calle de Barcelona, 19",
    "sg:city":"Coru\u00d1a",
    "sg:orig_category":"Molduras, Junquillos, Listones Y Molduras Perforadas",
    "sg:phone":"+34 981 26 92 41",
    "sg:postcode":"15010",
    "sg:province":"La Coru\u00f1a",
    "wof:name":"Ferreiro Broz Maria Del Pilar",
    "wof:placetype":"venue"
},
  "geometry": {"coordinates":[-8.4208602905,43.3615875244],"type":"Point"}
}