{
  "type": "Feature",
  "properties": {
    "iso:country":"ES",
    "sg:address":"Calle de Castelar, 3",
    "sg:city":"Sax",
    "sg:orig_category":"Farmacias",
    "sg:phone":"+34 965 47 41 07",
    "sg:postcode":"03630",
    "sg:province":"Alicante",
    "wof:name":"Garcia-conde Chico Paloma",
    "wof:placetype":"venue"
},
  "geometry": {"coordinates":[-0.817915976,38.5372238159],"type":"Point"}
}