{
  "type": "Feature",
  "properties": {
    "iso:country":"ES",
    "sg:address":"La Iglesia, 4",
    "sg:city":"Novales",
    "sg:orig_category":"Granos Y Forrajes",
    "sg:phone":"+34 974 28 00 17",
    "sg:postcode":"22113",
    "sg:province":"Huesca",
    "wof:name":"Bescos Otal Manuel",
    "wof:placetype":"venue"
},
  "geometry": {"coordinates":[-0.2869510055,42.0321731567],"type":"Point"}
}