{
  "type": "Feature",
  "properties": {
    "addr:full":"Pase Estacion (la), 25 Jaen Ja\u00e9n 23008",
    "addr:postcode":"23008",
    "addr:street":"Jae\u0301N",
    "iso:country":"ES",
    "sg:address":"Pase Estacion (la), 25",
    "sg:city":"Jaen",
    "sg:orig_category":"M\u00c9dicos: Oftalmolog\u00cda",
    "sg:phone":"+34 953 22 13 07",
    "sg:postcode":"23008",
    "sg:province":"Ja\u00e9n",
    "wof:name":"Quesada Molina Andres",
    "wof:placetype":"venue"
},
  "geometry": {"coordinates":[-3.7888929844,37.773727417],"type":"Point"}
}