{
  "type": "Feature",
  "properties": {
    "addr:full":"Carr Silla, 28 Alcasser Valencia 46290",
    "addr:housenumber":"28",
    "addr:postcode":"46290",
    "addr:street":"Carr Silla",
    "iso:country":"ES",
    "sg:address":"Carr Silla, 28",
    "sg:city":"Alcasser",
    "sg:orig_category":"Promotores Constructores",
    "sg:phone":"+34 961 23 07 17",
    "sg:postcode":"46290",
    "sg:province":"Valencia",
    "wof:name":"Furio Escorihuela Juan",
    "wof:placetype":"venue"
},
  "geometry": {"coordinates":[-0.4430170059,39.3690872192],"type":"Point"}
}