{
  "type": "Feature",
  "properties": {
    "iso:country":"ES",
    "sg:address":"Calle de Flauta Magica, 42",
    "sg:city":"Malaga",
    "sg:orig_category":"Pintura, Barniz, Productos Asimilables (fabricaci\u00d3n, Al Por Mayor)",
    "sg:phone":"+34 952 34 50 94",
    "sg:postcode":"29006",
    "sg:province":"M\u00e1laga",
    "wof:name":"Palfer S.l.",
    "wof:placetype":"venue"
},
  "geometry": {"coordinates":[-4.471570015,36.7099647522],"type":"Point"}
}