{
  "type": "Feature",
  "properties": {
    "iso:country":"ES",
    "sg:address":"Avda Lope De Figueroa, 39",
    "sg:city":"Alcala Henares",
    "sg:orig_category":"M\u00c9dicos: Medicina Interna",
    "sg:phone":"+34 918 88 05 70",
    "sg:postcode":"28804",
    "sg:province":"Madrid",
    "wof:name":"Gisbert Canto Jose Luis",
    "wof:placetype":"venue"
},
  "geometry": {"coordinates":[-3.3497049809,40.48802948],"type":"Point"}
}