{
  "type": "Feature",
  "properties": {
    "addr:full":"Carr Gola, 22 Puerto De Pollen\u00c7a Islas Baleares 07470",
    "addr:housenumber":"22",
    "addr:postcode":"07470",
    "addr:street":"Carr Gola",
    "iso:country":"ES",
    "sg:address":"Carr Gola, 22",
    "sg:city":"Puerto De Pollen\u00c7a",
    "sg:orig_category":"Bebidas",
    "sg:phone":"+34 971 86 41 23",
    "sg:postcode":"07470",
    "sg:province":"Islas Baleares",
    "wof:name":"Mir Vilanova Juan",
    "wof:placetype":"venue"
},
  "geometry": {"coordinates":[3.0786333084,39.9043540955],"type":"Point"}
}