{
  "type": "Feature",
  "properties": {
    "addr:full":"Calle de Buensuceso, 30 Valdepe\u00f1as Ciudad Real 13300",
    "addr:housenumber":"30",
    "addr:postcode":"13300",
    "addr:street":"Calle De Buensuceso",
    "iso:country":"ES",
    "sg:address":"Calle de Buensuceso, 30",
    "sg:city":"Valdepe\u00f1as",
    "sg:orig_category":"Venta, Instalaci\u00d3n De Calefacci\u00d3n",
    "sg:phone":"+34 926 32 14 56",
    "sg:postcode":"13300",
    "sg:province":"Ciudad Real",
    "wof:name":"Hidrofil Hidraulica Y Suministros S.l.",
    "wof:placetype":"venue"
},
  "geometry": {"coordinates":[-3.3803412914,38.7662620544],"type":"Point"}
}