{
  "type": "Feature",
  "properties": {
    "iso:country":"ES",
    "sg:address":"Calle de Ba\u00d1os, 3",
    "sg:city":"Linares",
    "sg:orig_category":"Moda",
    "sg:phone":"+34 953 69 26 18",
    "sg:postcode":"23700",
    "sg:province":"Ja\u00e9n",
    "wof:name":"Jimenez De Cisneros Fuentes Maria Luisa",
    "wof:placetype":"venue"
},
  "geometry": {"coordinates":[-3.6356630325,38.0943336487],"type":"Point"}
}