{
  "type": "Feature",
  "properties": {
    "addr:full":"Avda Cristo De Las Cadenas, 18 Oviedo Asturias 33006",
    "addr:housenumber":"18",
    "addr:postcode":"33006",
    "addr:street":"Avda Cristo De Las Cadenas",
    "iso:country":"ES",
    "sg:address":"Avda Cristo De Las Cadenas, 18",
    "sg:city":"Oviedo",
    "sg:orig_category":"Florister\u00cdas",
    "sg:phone":"+34 985 25 66 88",
    "sg:postcode":"33006",
    "sg:province":"Asturias",
    "wof:name":"Gonzalez Salas Rosa Marta",
    "wof:placetype":"venue"
},
  "geometry": {"coordinates":[-5.859732151,43.3559036255],"type":"Point"}
}