{
  "type": "Feature",
  "properties": {
    "iso:country":"ES",
    "sg:address":"Calle de Canario, 34",
    "sg:city":"Fuenlabrada",
    "sg:orig_category":"Postigos, Persianas Y Celos\u00cdas",
    "sg:phone":"+34 916 42 25 30",
    "sg:postcode":"28946",
    "sg:province":"Madrid",
    "wof:name":"Olmeda Sanchez Lorenzo",
    "wof:placetype":"venue"
},
  "geometry": {"coordinates":[-3.7645566463,40.2641525269],"type":"Point"}
}