{
  "type": "Feature",
  "properties": {
    "addr:full":"Polig La Tejera, S/n Castro Urdiales Cantabria 39700",
    "addr:housenumber":"s / n",
    "addr:postcode":"39700",
    "addr:street":"Polig La Tejera",
    "iso:country":"ES",
    "sg:address":"Polig La Tejera, S/n",
    "sg:city":"Castro Urdiales",
    "sg:orig_category":"Ambulancias",
    "sg:phone":"+34 942 87 12 23",
    "sg:postcode":"39700",
    "sg:province":"Cantabria",
    "wof:name":"Ambulancias Mrd S.l.",
    "wof:placetype":"venue"
},
  "geometry": {"coordinates":[-3.2483057976,43.3510284424],"type":"Point"}
}