{
  "type": "Feature",
  "properties": {
    "iso:country":"ES",
    "sg:address":"Calle de Atindana, 10",
    "sg:city":"Monta\u00e7eta Del Calero",
    "sg:orig_category":"Perfumer\u00cda (al Por Menor)",
    "sg:phone":"+34 928 68 00 09",
    "sg:postcode":"35200",
    "sg:province":"Las Palmas",
    "wof:name":"Aurelio R. Mahugo S.l.",
    "wof:placetype":"venue"
},
  "geometry": {"coordinates":[-15.4300060272,28.1248226166],"type":"Point"}
}