{
  "type": "Feature",
  "properties": {
    "iso:country":"ES",
    "sg:address":"Rua Xuncal, 3",
    "sg:city":"Devesa",
    "sg:orig_category":"Venta, Instalaci\u00d3n De Calefacci\u00d3n",
    "sg:phone":"+34 986 24 78 62",
    "sg:postcode":"36212",
    "sg:province":"Pontevedra",
    "wof:name":"Gama Confort Galicia S.a.",
    "wof:placetype":"venue"
},
  "geometry": {"coordinates":[-8.7656679153,42.2123451233],"type":"Point"}
}