{
  "type": "Feature",
  "properties": {
    "addr:full":"Poligon Baix Ebre, S/n Camp-redo Tarragona 43897",
    "addr:housenumber":"s / n",
    "addr:postcode":"43897",
    "iso:country":"ES",
    "sg:address":"Poligon Baix Ebre, S/n",
    "sg:city":"Camp-redo",
    "sg:orig_category":"Muebles, Minoristas",
    "sg:phone":"+34 977 59 74 30",
    "sg:postcode":"43897",
    "sg:province":"Tarragona",
    "wof:name":"Muebles Arasa S.a.",
    "wof:placetype":"venue"
},
  "geometry": {"coordinates":[0.5545499921,40.7676849365],"type":"Point"}
}