{
  "type": "Feature",
  "properties": {
    "addr:full":"Carrer de Doctor Nubiola I Espinos, S/n Barcelona Barcelona 08028",
    "addr:housenumber":"s / n",
    "addr:postcode":"08028",
    "addr:street":"Carrer De Doctor Nubiola;Espinos",
    "iso:country":"ES",
    "sg:address":"Carrer de Doctor Nubiola I Espinos, S/n",
    "sg:city":"Barcelona",
    "sg:orig_category":"Carnicer\u00cdas, Carnicer\u00cdas",
    "sg:phone":"+34 934 91 41 96",
    "sg:postcode":"08028",
    "sg:province":"Barcelona",
    "wof:name":"Toral Vila Francisco",
    "wof:placetype":"venue"
},
  "geometry": {"coordinates":[2.1300649643,41.3840942383],"type":"Point"}
}