{
  "type": "Feature",
  "properties": {
    "iso:country":"ES",
    "sg:address":"Plaz Alfonso El Magnanimo, 15",
    "sg:city":"Valencia",
    "sg:orig_category":"Procuradores",
    "sg:phone":"+34 963 52 41 65",
    "sg:postcode":"46003",
    "sg:province":"Valencia",
    "wof:name":"Jimenez Tirado Maria Del Lidon Isabel",
    "wof:placetype":"venue"
},
  "geometry": {"coordinates":[-0.3708930016,39.4726753235],"type":"Point"}
}