{
  "type": "Feature",
  "properties": {
    "addr:full":"Avda Asturias, 17 Guardo Palencia 34880",
    "addr:housenumber":"17",
    "addr:postcode":"34880",
    "addr:street":"Avda Asturias",
    "iso:country":"ES",
    "sg:address":"Avda Asturias, 17",
    "sg:city":"Guardo",
    "sg:orig_category":"Comerciantes Al Por Mayor De Vinos, Licores Y Alcoholes",
    "sg:phone":"+34 979 85 01 88",
    "sg:postcode":"34880",
    "sg:province":"Palencia",
    "wof:name":"Anton Modino Maria Luz",
    "wof:placetype":"venue"
},
  "geometry": {"coordinates":[-4.8444123268,42.7914428711],"type":"Point"}
}