{
  "type": "Feature",
  "properties": {
    "addr:full":"Calle de Pablo Sarasate, 3 Tudela Navarra 31500",
    "addr:housenumber":"3",
    "addr:postcode":"31500",
    "addr:street":"Calle De Pablo Sarasate",
    "iso:country":"ES",
    "sg:address":"Calle de Pablo Sarasate, 3",
    "sg:city":"Tudela",
    "sg:orig_category":"Deportes Y Ocio: Art\u00cdculos Y Ropas (al Por Menor Y Accesorios)",
    "sg:phone":"+34 948 41 18 18",
    "sg:postcode":"31500",
    "sg:province":"Navarra",
    "wof:name":"Intersport Perez Lumbreras",
    "wof:placetype":"venue"
},
  "geometry": {"coordinates":[-1.6042189598,42.0606765747],"type":"Point"}
}