{
  "type": "Feature",
  "properties": {
    "addr:full":"Calle de Mendoza, 12 Ceuta Ceuta 51001",
    "addr:housenumber":"12",
    "addr:postcode":"51001",
    "addr:street":"Calle De Mendoza",
    "iso:country":"ES",
    "sg:address":"Calle de Mendoza, 12",
    "sg:city":"Ceuta",
    "sg:orig_category":"Ense\u00d1anza Variada",
    "sg:phone":"+34 956 51 79 07",
    "sg:postcode":"51001",
    "sg:province":"Ceuta",
    "wof:name":"Duran Rodriguez Jesus",
    "wof:placetype":"venue"
},
  "geometry": {"coordinates":[-5.3052759171,35.8891067505],"type":"Point"}
}