{
  "type": "Feature",
  "properties": {
    "addr:full":"Calle de Huertos (los), 31 Pulianillas Granada 18197",
    "addr:housenumber":"31",
    "addr:postcode":"18197",
    "addr:street":"Calle De Huertos Los",
    "iso:country":"ES",
    "sg:address":"Calle de Huertos (los), 31",
    "sg:city":"Pulianillas",
    "sg:orig_category":"Asesor\u00cda De Formaci\u00d3n Y Gesti\u00d3n De Personal",
    "sg:phone":"+34 958 40 62 19",
    "sg:postcode":"18197",
    "sg:province":"Granada",
    "sg:website":"www.asesoriapulianas.es",
    "wof:name":"Garcia Navarro Marina",
    "wof:placetype":"venue"
},
  "geometry": {"coordinates":[-3.6060140133,37.2183799744],"type":"Point"}
}