{
  "type": "Feature",
  "properties": {
    "addr:full":"Calle de Padre Luis Navarro, 82 Valencia Valencia 46011",
    "addr:housenumber":"82",
    "addr:postcode":"46011",
    "addr:street":"Calle De Padre Luis Navarro",
    "iso:country":"ES",
    "sg:address":"Calle de Padre Luis Navarro, 82",
    "sg:city":"Valencia",
    "sg:orig_category":"Confecci\u00d3n De Trajes Para Se\u00d1oras",
    "sg:phone":"+34 963 56 24 28",
    "sg:postcode":"46011",
    "sg:province":"Valencia",
    "wof:name":"Serrano Casa\u00f1 Antonio",
    "wof:placetype":"venue"
},
  "geometry": {"coordinates":[-0.3298079967,39.4663772583],"type":"Point"}
}