{
  "type": "Feature",
  "properties": {
    "iso:country":"ES",
    "sg:address":"Calle de Jazmin (calle Peatonal), 3",
    "sg:city":"Cordoba",
    "sg:orig_category":"Carnicer\u00cdas, Carnicer\u00cdas",
    "sg:phone":"+34 957 25 34 95",
    "sg:postcode":"14014",
    "sg:province":"C\u00f3rdoba",
    "wof:name":"Huertes Lacalle Concepcion",
    "wof:placetype":"venue"
},
  "geometry": {"coordinates":[-4.7578377724,37.8996391296],"type":"Point"}
}