{
  "type": "Feature",
  "properties": {
    "iso:country":"ES",
    "sg:address":"Orviz, S/n",
    "sg:city":"Anes",
    "sg:orig_category":"Semiller\u00cdas",
    "sg:phone":"+34 985 74 00 03",
    "sg:postcode":"33189",
    "sg:province":"Asturias",
    "wof:name":"Arboris Sociedad Responsabilidad Limitada",
    "wof:placetype":"venue"
},
  "geometry": {"coordinates":[-5.7085843086,43.4079589844],"type":"Point"}
}