{
  "type": "Feature",
  "properties": {
    "addr:full":"Mediterraneo, 5 Cobatillas Murcia 30163",
    "addr:housenumber":"5",
    "addr:postcode":"30163",
    "iso:country":"ES",
    "sg:address":"Mediterraneo, 5",
    "sg:city":"Cobatillas",
    "sg:orig_category":"Herboristas (al Por Menor)",
    "sg:phone":"+34 968 86 18 72",
    "sg:postcode":"30163",
    "sg:province":"Murcia",
    "wof:name":"Murciana De Herboristeria S.a.l.",
    "wof:placetype":"venue"
},
  "geometry": {"coordinates":[-1.0705510378,38.0564575195],"type":"Point"}
}