{
  "type": "Feature",
  "properties": {
    "addr:full":"Calle de Francisco Del Rosal, 8 Cordoba C\u00f3rdoba 14001",
    "addr:housenumber":"8",
    "addr:postcode":"14001",
    "addr:street":"Calle De Francisco Del Rosal;Co\u0301Rdoba",
    "iso:country":"ES",
    "sg:address":"Calle de Francisco Del Rosal, 8",
    "sg:city":"Cordoba",
    "sg:orig_category":"Bisuter\u00cda, Joyer\u00cda, Relojer\u00cda (al Por Menor)",
    "sg:phone":"+34 957 48 15 44",
    "sg:postcode":"14001",
    "sg:province":"C\u00f3rdoba",
    "wof:name":"Jimenez Guzman Rafael",
    "wof:placetype":"venue"
},
  "geometry": {"coordinates":[-4.772685051,37.8872108459],"type":"Point"}
}