{
  "type": "Feature",
  "properties": {
    "iso:country":"ES",
    "sg:address":"Carrer de Sant Marc, 26",
    "sg:city":"Santa Eugenia De Berga",
    "sg:orig_category":"Costureras",
    "sg:phone":"+34 938 85 18 58",
    "sg:postcode":"08507",
    "sg:province":"Barcelona",
    "wof:name":"Torres Rodriguez Carmen",
    "wof:placetype":"venue"
},
  "geometry": {"coordinates":[2.2843770981,41.9022026062],"type":"Point"}
}