{
  "type": "Feature",
  "properties": {
    "iso:country":"ES",
    "sg:address":"Ctra. Cartama-malaga, S/n",
    "sg:city":"Cartama",
    "sg:orig_category":"Pintura, Barniz, Productos Asimilables (fabricaci\u00d3n, Al Por Mayor)",
    "sg:phone":"+34 952 42 46 29",
    "sg:postcode":"29570",
    "sg:province":"M\u00e1laga",
    "wof:name":"Rebollo Ocaa Salvador",
    "wof:placetype":"venue"
},
  "geometry": {"coordinates":[-4.7015919685,36.7029647827],"type":"Point"}
}