{
  "type": "Feature",
  "properties": {
    "iso:country":"ES",
    "sg:address":"Carrer de Cera, 32",
    "sg:city":"Barcelona",
    "sg:orig_category":"Pescader\u00cdas (al Por Menor)",
    "sg:phone":"+34 934 42 14 23",
    "sg:postcode":"08001",
    "sg:province":"Barcelona",
    "wof:name":"Ventura Felip Josep",
    "wof:placetype":"venue"
},
  "geometry": {"coordinates":[2.1654100418,41.3783721924],"type":"Point"}
}