{
  "type": "Feature",
  "properties": {
    "addr:full":"Azkarruntz Auzoa, 9 Bergara Guip\u00f9zcoa 20570",
    "addr:housenumber":"9",
    "addr:postcode":"20570",
    "addr:street":"Azkarruntz Auzoa;Guipu\u0300Zcoa",
    "iso:country":"ES",
    "sg:address":"Azkarruntz Auzoa, 9",
    "sg:city":"Bergara",
    "sg:orig_category":"Serrer\u00cdas De Madera",
    "sg:phone":"+34 943 76 11 06",
    "sg:postcode":"20570",
    "sg:province":"Guip\u00f9zcoa",
    "wof:name":"Aranzabal Lascurain Manuel",
    "wof:placetype":"venue"
},
  "geometry": {"coordinates":[-2.4321975708,43.1020050049],"type":"Point"}
}