{
  "type": "Feature",
  "properties": {
    "iso:country":"ES",
    "sg:address":"Calle de Maldonado, 19",
    "sg:city":"Santa Cruz Palma",
    "sg:orig_category":"Ingeniero",
    "sg:phone":"+34 922 41 12 35",
    "sg:postcode":"38700",
    "sg:province":"Santa Cruz De Tenerife",
    "wof:name":"Laboratorio Canario De Calidad S.l.",
    "wof:placetype":"venue"
},
  "geometry": {"coordinates":[-17.7602424622,28.6902523041],"type":"Point"}
}