{
  "type": "Feature",
  "properties": {
    "addr:full":"Calle de Ybarra Rafaela, 13 Bilbao Vizcaya 48014",
    "addr:housenumber":"13",
    "addr:postcode":"48014",
    "addr:street":"Calle De Ybarra Rafaela",
    "iso:country":"ES",
    "sg:address":"Calle de Ybarra Rafaela, 13",
    "sg:city":"Bilbao",
    "sg:orig_category":"Expertos Contables",
    "sg:phone":"+34 944 76 00 24",
    "sg:postcode":"48014",
    "sg:province":"Vizcaya",
    "wof:name":"Dalmau Peritaciones S.l.",
    "wof:placetype":"venue"
},
  "geometry": {"coordinates":[-2.9459090233,43.2707557678],"type":"Point"}
}