{
  "type": "Feature",
  "properties": {
    "iso:country":"ES",
    "sg:address":"Pla\u00c7 Abadia (l'), 7",
    "sg:city":"Picassent",
    "sg:orig_category":"Semiller\u00cdas",
    "sg:phone":"+34 961 23 42 79",
    "sg:postcode":"46220",
    "sg:province":"Valencia",
    "wof:name":"Jardineria Tot En U S.l.",
    "wof:placetype":"venue"
},
  "geometry": {"coordinates":[-0.4595290124,39.3631401062],"type":"Point"}
}