{
  "type": "Feature",
  "properties": {
    "addr:full":"Avda Constitucion (de La), 65 Nueva-carteya C\u00f3rdoba 14857",
    "addr:housenumber":"65",
    "addr:postcode":"14857",
    "addr:street":"Avda Constitucion De La;Co\u0301Rdoba",
    "iso:country":"ES",
    "sg:address":"Avda Constitucion (de La), 65",
    "sg:city":"Nueva-carteya",
    "sg:orig_category":"Aceites Y Grasas Alimentarias (fabricaci\u00d3n, Al Por Mayor)",
    "sg:phone":"+34 957 67 81 37",
    "sg:postcode":"14857",
    "sg:province":"C\u00f3rdoba",
    "wof:name":"Sociedad Agraria De Transformacion San Antonio N\u00ba 13073",
    "wof:placetype":"venue"
},
  "geometry": {"coordinates":[-4.4739432335,37.5883865356],"type":"Point"}
}