{
  "type": "Feature",
  "properties": {
    "addr:full":"Av Sagrat Cor (del), 17 S. Carles Rapita Tarragona 43540",
    "addr:housenumber":"17",
    "addr:postcode":"43540",
    "addr:street":"Av Sagrat Cor Del;S. Carles Rapita",
    "iso:country":"ES",
    "sg:address":"Av Sagrat Cor (del), 17",
    "sg:city":"S. Carles Rapita",
    "sg:orig_category":"Ebanister\u00cda",
    "sg:phone":"+34 977 74 15 63",
    "sg:postcode":"43540",
    "sg:province":"Tarragona",
    "wof:name":"Lopez Miguel Mauricio",
    "wof:placetype":"venue"
},
  "geometry": {"coordinates":[0.5931149721,40.6206436157],"type":"Point"}
}