{
  "type": "Feature",
  "properties": {
    "iso:country":"ES",
    "sg:address":"Calle de Neurketa, 8",
    "sg:city":"Mungia",
    "sg:orig_category":"Molduras, Junquillos, Listones Y Molduras Perforadas",
    "sg:phone":"+34 946 74 18 40",
    "sg:postcode":"48100",
    "sg:province":"Vizcaya",
    "wof:name":"Anchustegui San Pedro Jesus",
    "wof:placetype":"venue"
},
  "geometry": {"coordinates":[-2.8478434086,43.3561439514],"type":"Point"}
}