{
  "type": "Feature",
  "properties": {
    "addr:full":"Ctra. Jinamar, 17 Jinamar Las Palmas 35220",
    "addr:housenumber":"17",
    "addr:postcode":"35220",
    "addr:street":"Ctra. Jinamar;Palmas",
    "iso:country":"ES",
    "sg:address":"Ctra. Jinamar, 17",
    "sg:city":"Jinamar",
    "sg:orig_category":"Peluquer\u00cdas, Peluquer\u00cda Mixta",
    "sg:phone":"+34 928 70 90 96",
    "sg:postcode":"35220",
    "sg:province":"Las Palmas",
    "wof:name":"Ruano Peluqueros S.c.p.",
    "wof:placetype":"venue"
},
  "geometry": {"coordinates":[-15.4174785614,28.0321941376],"type":"Point"}
}