{
  "type": "Feature",
  "properties": {
    "iso:country":"ES",
    "sg:address":"Cra Santa Creu De Calafell, Km. 0016,0",
    "sg:city":"Gava",
    "sg:orig_category":"M\u00c1quinas Para Recortar Y Pegar",
    "sg:phone":"+34 936 38 91 92",
    "sg:postcode":"08850",
    "sg:province":"Barcelona",
    "sg:website":"www.sanuma.es",
    "wof:name":"Nucleos Magneticos S.a.",
    "wof:placetype":"venue"
},
  "geometry": {"coordinates":[2.0101709366,41.3054618835],"type":"Point"}
}