{
  "type": "Feature",
  "properties": {
    "iso:country":"ES",
    "sg:address":"Calle de Teniente Ochoa (del), 13",
    "sg:city":"Segovia",
    "sg:orig_category":"Institutos De Belleza",
    "sg:phone":"+34 921 46 22 70",
    "sg:postcode":"40002",
    "sg:province":"Segovia",
    "sg:website":"www.paginasamarillas.es",
    "wof:name":"Estetica Y Peluqueros Colors S.l.",
    "wof:placetype":"venue"
},
  "geometry": {"coordinates":[-4.1231489182,40.9464416504],"type":"Point"}
}