{
  "type": "Feature",
  "properties": {
    "iso:country":"ES",
    "sg:address":"Calle de Tejuela, 20",
    "sg:city":"Alcala Real",
    "sg:orig_category":"Carnicer\u00cdas, Carnicer\u00cdas",
    "sg:phone":"+34 953 58 28 06",
    "sg:postcode":"23680",
    "sg:province":"Ja\u00e9n",
    "wof:name":"Perez Garrido Jose",
    "wof:placetype":"venue"
},
  "geometry": {"coordinates":[-3.925162077,37.4657936096],"type":"Point"}
}