{
  "type": "Feature",
  "properties": {
    "iso:country":"ES",
    "sg:address":"Calle de Cuevas, S/n",
    "sg:city":"Borox",
    "sg:orig_category":"Agricultores, Agricultores",
    "sg:phone":"+34 925 54 81 44",
    "sg:postcode":"45222",
    "sg:province":"Toledo",
    "wof:name":"Hermanos Recio Sat",
    "wof:placetype":"venue"
},
  "geometry": {"coordinates":[-3.7366764545,40.0715408325],"type":"Point"}
}