{
  "type": "Feature",
  "properties": {
    "iso:country":"ES",
    "sg:address":"Pg Pla\u00c7a Major, 9",
    "sg:city":"Sabadell",
    "sg:orig_category":"Zapatos (al Por Menor)",
    "sg:phone":"+34 937 45 08 15",
    "sg:postcode":"08201",
    "sg:province":"Barcelona",
    "wof:name":"Calzados Lamolla S.a.",
    "wof:placetype":"venue"
},
  "geometry": {"coordinates":[2.1086521149,41.5481071472],"type":"Point"}
}