{
  "type": "Feature",
  "properties": {
    "iso:country":"ES",
    "sg:address":"C/ Sant Dionis, 106",
    "sg:city":"Salt",
    "sg:orig_category":"C\u00c1maras De Comercio E Industria, Oficios, Agricultura",
    "sg:phone":"+34 972 21 29 12",
    "sg:postcode":"17190",
    "sg:province":"Girona",
    "wof:name":"Giser Barrot Serveis S.l.",
    "wof:placetype":"venue"
},
  "geometry": {"coordinates":[2.7950398922,41.9770889282],"type":"Point"}
}