{
  "type": "Feature",
  "properties": {
    "addr:full":"Afores, S/n Vinyols I Els Arcs Tarragona 43391",
    "addr:housenumber":"s / n",
    "addr:postcode":"43391",
    "addr:street":"Afores",
    "iso:country":"ES",
    "sg:address":"Afores, S/n",
    "sg:city":"Vinyols I Els Arcs",
    "sg:orig_category":"Poller\u00cda Y Caza (al Por Menor)",
    "sg:phone":"+34 977 26 90 29",
    "sg:postcode":"43391",
    "sg:province":"Tarragona",
    "wof:name":"Nolla Mallafre Jose",
    "wof:placetype":"venue"
},
  "geometry": {"coordinates":[1.042050004,41.1135597229],"type":"Point"}
}