{
  "type": "Feature",
  "properties": {
    "iso:country":"ES",
    "sg:address":"Avda Luis Bu\u00d1uel, 158",
    "sg:city":"Roquetas Mar",
    "sg:orig_category":"Mec\u00c1nico Del Autom\u00d3vil",
    "sg:phone":"+34 950 32 37 19",
    "sg:postcode":"04740",
    "sg:province":"Almer\u00eda",
    "wof:name":"Noguera Garcia Emilio",
    "wof:placetype":"venue"
},
  "geometry": {"coordinates":[-2.6221499443,36.7660522461],"type":"Point"}
}