{
  "type": "Feature",
  "properties": {
    "addr:full":"Calle de Falo Moro, 3 Pola De Siero Asturias 33510",
    "addr:housenumber":"3",
    "addr:postcode":"33510",
    "addr:street":"Calle De Falo Moro",
    "iso:country":"ES",
    "sg:address":"Calle de Falo Moro, 3",
    "sg:city":"Pola De Siero",
    "sg:orig_category":"Quincaller\u00cda (al Por Menor)",
    "sg:phone":"+34 985 72 32 39",
    "sg:postcode":"33510",
    "sg:province":"Asturias",
    "wof:name":"Garcia Rodriguez Jose Humberto",
    "wof:placetype":"venue"
},
  "geometry": {"coordinates":[-5.6637940407,43.3910903931],"type":"Point"}
}