{
  "type": "Feature",
  "properties": {
    "iso:country":"ES",
    "sg:address":"Carrer de Cerdanya, 28",
    "sg:city":"S. Boi Llobregat",
    "sg:orig_category":"Inmobiliaria (agencias)",
    "sg:phone":"+34 936 35 47 73",
    "sg:postcode":"08830",
    "sg:province":"Barcelona",
    "wof:name":"Inmovive S.l.",
    "wof:placetype":"venue"
},
  "geometry": {"coordinates":[2.0428519249,41.342880249],"type":"Point"}
}