{
  "type": "Feature",
  "properties": {
    "iso:country":"ES",
    "sg:address":"Urb Villa Teresa, 4",
    "sg:city":"Alacant",
    "sg:orig_category":"Formaci\u00d3n A Distancia, Por Correspondencia",
    "sg:phone":"+34 965 13 10 55",
    "sg:postcode":"03005",
    "sg:province":"Alicante",
    "sg:website":"www.gmformacion.com",
    "wof:name":"Formacion Seguridad Y Tecnologia S.l.",
    "wof:placetype":"venue"
},
  "geometry": {"coordinates":[-0.4804739952,38.3440856934],"type":"Point"}
}