{
  "type": "Feature",
  "properties": {
    "addr:full":"Calle de Grulla (de La), 33 Atalaya-isdabe M\u00e1laga 29680",
    "addr:housenumber":"33",
    "addr:postcode":"29680",
    "addr:street":"Calle De Grulla De La;Ma\u0301Laga",
    "iso:country":"ES",
    "sg:address":"Calle de Grulla (de La), 33",
    "sg:city":"Atalaya-isdabe",
    "sg:orig_category":"Guarder\u00cdas",
    "sg:phone":"+34 952 92 84 44",
    "sg:postcode":"29680",
    "sg:province":"M\u00e1laga",
    "wof:name":"Jardin De Infancia Irela S.l.",
    "wof:placetype":"venue"
},
  "geometry": {"coordinates":[-5.0128436089,36.4658508301],"type":"Point"}
}