{
  "type": "Feature",
  "properties": {
    "addr:full":"Pase Norias (de Las), 18 Logro\u00f1o La Rioja 26006",
    "addr:housenumber":"18",
    "addr:postcode":"26006",
    "addr:street":"Norias De Las;Rioja",
    "iso:country":"ES",
    "sg:address":"Pase Norias (de Las), 18",
    "sg:city":"Logro\u00f1o",
    "sg:orig_category":"Ferreter\u00cda (diversos)",
    "sg:phone":"+34 941 23 52 82",
    "sg:postcode":"26006",
    "sg:province":"La Rioja",
    "wof:name":"Recuperaciones Diaz S.a.",
    "wof:placetype":"venue"
},
  "geometry": {"coordinates":[-2.4036989212,42.46043396],"type":"Point"}
}