{
  "type": "Feature",
  "properties": {
    "addr:full":"Calle de Carchena, 18 Cuellar Segovia 40200",
    "addr:housenumber":"18",
    "addr:postcode":"40200",
    "addr:street":"Calle De Carchena",
    "iso:country":"ES",
    "sg:address":"Calle de Carchena, 18",
    "sg:city":"Cuellar",
    "sg:orig_category":"Ropa Para Se\u00d1oras Y Caballeros (al Por Menor)",
    "sg:phone":"+34 921 14 07 45",
    "sg:postcode":"40200",
    "sg:province":"Segovia",
    "wof:name":"Mythos Creaciones S.l.",
    "wof:placetype":"venue"
},
  "geometry": {"coordinates":[-4.3121657372,41.4010505676],"type":"Point"}
}