{
  "type": "Feature",
  "properties": {
    "iso:country":"ES",
    "sg:address":"Carrer de Rocafort, 139",
    "sg:city":"Barcelona",
    "sg:orig_category":"Muebles, Minoristas",
    "sg:phone":"+34 934 23 24 05",
    "sg:postcode":"08015",
    "sg:province":"Barcelona",
    "wof:name":"Mobles Ambients De La Casa S.c.p.",
    "wof:placetype":"venue"
},
  "geometry": {"coordinates":[2.1508419514,41.3809623718],"type":"Point"}
}