{
  "type": "Feature",
  "properties": {
    "addr:full":"Calle de Emilio Nieto, 27 Villarrubia De Los Ojos Ciudad Real 13670",
    "addr:housenumber":"27",
    "addr:postcode":"13670",
    "addr:street":"Calle De Emilio Nieto",
    "iso:country":"ES",
    "sg:address":"Calle de Emilio Nieto, 27",
    "sg:city":"Villarrubia De Los Ojos",
    "sg:orig_category":"Par\u00cds",
    "sg:phone":"+34 926 89 87 54",
    "sg:postcode":"13670",
    "sg:province":"Ciudad Real",
    "wof:name":"Ruiz De La Hermosa Redondo Asuncion",
    "wof:placetype":"venue"
},
  "geometry": {"coordinates":[-3.6064391136,39.2218093872],"type":"Point"}
}