{
  "type": "Feature",
  "properties": {
    "iso:country":"ES",
    "sg:address":"Plaz Puerta Del Angel, S/n",
    "sg:city":"Madrid",
    "sg:orig_category":"Suministros Para Hoteles",
    "sg:phone":"+34 914 79 05 81",
    "sg:postcode":"28011",
    "sg:province":"Madrid",
    "wof:name":"Hosteleria Y Colectividades S.a.",
    "wof:placetype":"venue"
},
  "geometry": {"coordinates":[-3.7349228859,40.4184379578],"type":"Point"}
}