{
  "type": "Feature",
  "properties": {
    "addr:full":"Paredes, S/n Paredes Pontevedra 36740",
    "addr:housenumber":"/ n",
    "addr:postcode":"36740",
    "addr:street":"Paredes S",
    "iso:country":"ES",
    "sg:address":"Paredes, S/n",
    "sg:city":"Paredes",
    "sg:orig_category":"Artesan\u00cda",
    "sg:phone":"+34 986 62 22 12",
    "sg:postcode":"36740",
    "sg:province":"Pontevedra",
    "wof:name":"Fernandez Fernandez Jesus",
    "wof:placetype":"venue"
},
  "geometry": {"coordinates":[-8.731048584,41.9869499207],"type":"Point"}
}