{
  "type": "Feature",
  "properties": {
    "addr:full":"Carrer de Sant Josep (de), 10 Vilanova De Prades Tarragona 43439",
    "addr:housenumber":"10",
    "addr:postcode":"43439",
    "addr:street":"Carrer De Sant Josep De",
    "iso:country":"ES",
    "sg:address":"Carrer de Sant Josep (de), 10",
    "sg:city":"Vilanova De Prades",
    "sg:orig_category":"Administraciones Regionales, Departamentales Y Locales",
    "sg:phone":"+34 977 86 90 02",
    "sg:postcode":"43439",
    "sg:province":"Tarragona",
    "wof:name":"Ajuntament De Vilanova De Prades",
    "wof:placetype":"venue"
},
  "geometry": {"coordinates":[0.9565017819,41.3481369019],"type":"Point"}
}