{
  "type": "Feature",
  "properties": {
    "addr:full":"Av Pais Valencia, 28 Alcoi Alicante 03801",
    "addr:housenumber":"28",
    "addr:postcode":"03801",
    "addr:street":"Av Pais Valencia",
    "iso:country":"ES",
    "sg:address":"Av Pais Valencia, 28",
    "sg:city":"Alcoi",
    "sg:orig_category":"Ropa Para Ni\u00d1os (al Por Menor)",
    "sg:phone":"+34 965 54 16 73",
    "sg:postcode":"03801",
    "sg:province":"Alicante",
    "wof:name":"Manyacos I Menuts S.c.",
    "wof:placetype":"venue"
},
  "geometry": {"coordinates":[-0.4761950076,38.6969909668],"type":"Point"}
}