{
  "type": "Feature",
  "properties": {
    "addr:full":"Av. Ferran Agullo, 2 Lloret Mar Girona 17310",
    "addr:housenumber":"2",
    "addr:postcode":"17310",
    "addr:street":"Av. Ferran Agullo",
    "iso:country":"ES",
    "sg:address":"Av. Ferran Agullo, 2",
    "sg:city":"Lloret Mar",
    "sg:orig_category":"Centros Comerciales Y Grandes Tiendas",
    "sg:phone":"+34 972 36 63 20",
    "sg:postcode":"17310",
    "sg:province":"Girona",
    "wof:name":"Comunidad Propietarios Centro Comercial Caravela",
    "wof:placetype":"venue"
},
  "geometry": {"coordinates":[2.846834898,41.6981697083],"type":"Point"}
}