{
  "type": "Feature",
  "properties": {
    "iso:country":"ES",
    "sg:address":"Calle de Fuenterrabia, 40",
    "sg:city":"Donostia-san Sebastian",
    "sg:orig_category":"Maquinaria Para Industrias Diversas",
    "sg:phone":"+34 943 46 64 17",
    "sg:postcode":"20005",
    "sg:province":"Guip\u00f9zcoa",
    "sg:website":"www.chimeneaserre.com",
    "wof:name":"Chimeneas Erre S.l.",
    "wof:placetype":"venue"
},
  "geometry": {"coordinates":[-1.9808340073,43.3166809082],"type":"Point"}
}