{
  "type": "Feature",
  "properties": {
    "addr:full":"Carrer de Santiago Apostol, 69 Hospitalet Llobregat Barcelona 08903",
    "addr:housenumber":"69",
    "addr:postcode":"08903",
    "addr:street":"Carrer De Santiago Apostol",
    "iso:country":"ES",
    "sg:address":"Carrer de Santiago Apostol, 69",
    "sg:city":"Hospitalet Llobregat",
    "sg:orig_category":"Escayola Y Productos De Escayola (fabricaci\u00d3n, Al Por Mayor)",
    "sg:phone":"+34 934 31 02 74",
    "sg:postcode":"08903",
    "sg:province":"Barcelona",
    "wof:name":"Bartolome Pi\u00f1ol Jaime",
    "wof:placetype":"venue"
},
  "geometry": {"coordinates":[2.1247520447,41.3697052002],"type":"Point"}
}