{
  "type": "Feature",
  "properties": {
    "addr:full":"Calle de General Aranda, 6 Leganes Madrid 28911",
    "addr:housenumber":"6",
    "addr:postcode":"28911",
    "addr:street":"Calle De General Aranda",
    "iso:country":"ES",
    "sg:address":"Calle de General Aranda, 6",
    "sg:city":"Leganes",
    "sg:orig_category":"Ropa Para Ni\u00d1os (al Por Menor)",
    "sg:phone":"+34 916 93 01 02",
    "sg:postcode":"28911",
    "sg:province":"Madrid",
    "wof:name":"Montero Ca\u00f1ada Luis",
    "wof:placetype":"venue"
},
  "geometry": {"coordinates":[-3.7655620575,40.3287467957],"type":"Point"}
}