{
  "type": "Feature",
  "properties": {
    "addr:full":"Calle de Colon, S/n Fuengirola M\u00e1laga 29640",
    "addr:postcode":"29640",
    "addr:street":"Calle De Colon S / N;Ma\u0301Laga",
    "iso:country":"ES",
    "sg:address":"Calle de Colon, S/n",
    "sg:city":"Fuengirola",
    "sg:orig_category":"Molduras, Junquillos, Listones Y Molduras Perforadas",
    "sg:phone":"+34 952 46 04 94",
    "sg:postcode":"29640",
    "sg:province":"M\u00e1laga",
    "wof:name":"Prados Moreno Jose",
    "wof:placetype":"venue"
},
  "geometry": {"coordinates":[-4.6181573868,36.5461387634],"type":"Point"}
}