{
  "type": "Feature",
  "properties": {
    "iso:country":"ES",
    "sg:address":"Calle de Medio, 3",
    "sg:city":"Santander",
    "sg:orig_category":"Frutas Y Legumbres Frescas (al Por Mayor)",
    "sg:phone":"+34 942 36 46 51",
    "sg:postcode":"39003",
    "sg:province":"Cantabria",
    "wof:name":"Fruteros Del Norte S.l.",
    "wof:placetype":"venue"
},
  "geometry": {"coordinates":[-3.8050720692,43.4627876282],"type":"Point"}
}