{
  "type": "Feature",
  "properties": {
    "iso:country":"ES",
    "sg:address":"Calle de Santecilla, 11",
    "sg:city":"Tagle",
    "sg:orig_category":"Pescader\u00cdas (al Por Menor)",
    "sg:phone":"+34 942 84 44 44",
    "sg:postcode":"39360",
    "sg:province":"Cantabria",
    "wof:name":"Palomera Garcia Luis Alberto",
    "wof:placetype":"venue"
},
  "geometry": {"coordinates":[-4.0780529976,43.4239273071],"type":"Point"}
}