{
  "type": "Feature",
  "properties": {
    "addr:full":"Calle de San Roke, 1 Elorrio Vizcaya 48230",
    "addr:housenumber":"1",
    "addr:postcode":"48230",
    "addr:street":"Calle De San Roke",
    "iso:country":"ES",
    "sg:address":"Calle de San Roke, 1",
    "sg:city":"Elorrio",
    "sg:orig_category":"Empresas De Carpinter\u00cda Met\u00c1lica",
    "sg:phone":"+34 946 23 14 09",
    "sg:postcode":"48230",
    "sg:province":"Vizcaya",
    "wof:name":"Inalum S.a.l.",
    "wof:placetype":"venue"
},
  "geometry": {"coordinates":[-2.5431399345,43.1277809143],"type":"Point"}
}