{
  "type": "Feature",
  "properties": {
    "iso:country":"ES",
    "sg:address":"Pl. Mercado, S/n",
    "sg:city":"Benahadux",
    "sg:orig_category":"Tintes (fabricaci\u00d3n, Al Por Mayor)",
    "sg:phone":"+34 950 31 05 29",
    "sg:postcode":"04410",
    "sg:province":"Almer\u00eda",
    "wof:name":"Calatrava Fernandez Jose Manuel",
    "wof:placetype":"venue"
},
  "geometry": {"coordinates":[-2.4617919922,36.9247436523],"type":"Point"}
}