{
  "type": "Feature",
  "properties": {
    "iso:country":"ES",
    "sg:address":"Calle de Labradores, 42",
    "sg:city":"Logro\u00f1o",
    "sg:orig_category":"Peluqueros: De Se\u00d1oras",
    "sg:phone":"+34 941 20 16 64",
    "sg:postcode":"26005",
    "sg:province":"La Rioja",
    "wof:name":"Ulecia Elias Rosario",
    "wof:placetype":"venue"
},
  "geometry": {"coordinates":[-2.4564180374,42.4606552124],"type":"Point"}
}