{
  "type": "Feature",
  "properties": {
    "iso:country":"ES",
    "sg:address":"Los Yesares, S/n",
    "sg:city":"Sorbas",
    "sg:orig_category":"Escayola Y Productos De Escayola (fabricaci\u00d3n, Al Por Mayor)",
    "sg:phone":"+34 950 52 53 32",
    "sg:postcode":"04270",
    "sg:province":"Almer\u00eda",
    "wof:name":"Bpb Iberplaco",
    "wof:placetype":"venue"
},
  "geometry": {"coordinates":[-2.1129190922,37.1058616638],"type":"Point"}
}