{
  "type": "Feature",
  "properties": {
    "addr:full":"Carrer de Joan Capo, 1 Palma Islas Baleares 07010",
    "addr:housenumber":"1",
    "addr:postcode":"07010",
    "addr:street":"Carrer De Joan Capo",
    "iso:country":"ES",
    "sg:address":"Carrer de Joan Capo, 1",
    "sg:city":"Palma",
    "sg:orig_category":"Transformaci\u00d3n De Materias Pl\u00c1sticas",
    "sg:phone":"+34 971 20 96 00",
    "sg:postcode":"07010",
    "sg:province":"Islas Baleares",
    "wof:name":"Copy & Disseny Grafic, S.l.",
    "wof:placetype":"venue"
},
  "geometry": {"coordinates":[2.6513469219,39.5858459473],"type":"Point"}
}