{
  "type": "Feature",
  "properties": {
    "addr:full":"Carrer de Llan\u00c7a, 47 Barcelona Barcelona 08015",
    "addr:housenumber":"47",
    "addr:postcode":"08015",
    "addr:street":"Carrer De Llanc\u0327A",
    "iso:country":"ES",
    "sg:address":"Carrer de Llan\u00c7a, 47",
    "sg:city":"Barcelona",
    "sg:orig_category":"Arquitectos",
    "sg:phone":"+34 932 28 21 41",
    "sg:postcode":"08015",
    "sg:province":"Barcelona",
    "wof:name":"Roig I Duran S.l.",
    "wof:placetype":"venue"
},
  "geometry": {"coordinates":[2.1449010372,41.3803405762],"type":"Point"}
}