{
  "type": "Feature",
  "properties": {
    "addr:full":"Calle de Escuelas, S/n Benalua Guadix Granada 18510",
    "addr:housenumber":"s",
    "addr:postcode":"18510",
    "addr:street":"Calle De Escuelas;/ N Benalua",
    "iso:country":"ES",
    "sg:address":"Calle de Escuelas, S/n",
    "sg:city":"Benalua Guadix",
    "sg:orig_category":"Molduras, Junquillos, Listones Y Molduras Perforadas",
    "sg:phone":"+34 958 69 60 47",
    "sg:postcode":"18510",
    "sg:province":"Granada",
    "wof:name":"Rodriguez Munoz Gloria",
    "wof:placetype":"venue"
},
  "geometry": {"coordinates":[-3.1645879745,37.3540039062],"type":"Point"}
}