{
  "type": "Feature",
  "properties": {
    "iso:country":"ES",
    "sg:address":"Barr Gorozika, S/n",
    "sg:city":"Ondarroa",
    "sg:orig_category":"Ense\u00d1anza, Formaci\u00d3n Profesional: Aprendizaje",
    "sg:phone":"+34 946 83 03 85",
    "sg:postcode":"48700",
    "sg:province":"Vizcaya",
    "wof:name":"Ayuntamiento De Ondarroa",
    "wof:placetype":"venue"
},
  "geometry": {"coordinates":[-2.4442300797,43.3113555908],"type":"Point"}
}