{
  "type": "Feature",
  "properties": {
    "addr:full":"Avda Extremadura, 8 Mirandilla Badajoz 06891",
    "addr:housenumber":"8",
    "addr:postcode":"06891",
    "addr:street":"Avda Extremadura",
    "iso:country":"ES",
    "sg:address":"Avda Extremadura, 8",
    "sg:city":"Mirandilla",
    "sg:orig_category":"Carnicer\u00cdas, Carnicer\u00cdas",
    "sg:phone":"+34 924 32 07 52",
    "sg:postcode":"06891",
    "sg:province":"Badajoz",
    "wof:name":"Collado Arias Fernando",
    "wof:placetype":"venue"
},
  "geometry": {"coordinates":[-6.2913889885,38.998626709],"type":"Point"}
}