{
  "type": "Feature",
  "properties": {
    "iso:country":"ES",
    "sg:address":"Trss Montesa, 14",
    "sg:city":"Monasterios",
    "sg:orig_category":"Ingenier\u00cda, Centros De Estudios (diversos)",
    "sg:phone":"+34 961 40 54 13",
    "sg:postcode":"46530",
    "sg:province":"Valencia",
    "wof:name":"Consultec Sc",
    "wof:placetype":"venue"
},
  "geometry": {"coordinates":[-0.3008790016,39.6156044006],"type":"Point"}
}