{
  "type": "Feature",
  "properties": {
    "iso:country":"ES",
    "sg:address":"Carrer de Maria Aguilo, 106",
    "sg:city":"Barcelona",
    "sg:orig_category":"Cerrajer\u00cda, Ferrallista",
    "sg:phone":"+34 932 25 39 60",
    "sg:postcode":"08005",
    "sg:province":"Barcelona",
    "wof:name":"Farreny Agustina Francisco",
    "wof:placetype":"venue"
},
  "geometry": {"coordinates":[2.2040510178,41.4005470276],"type":"Point"}
}