{
  "type": "Feature",
  "properties": {
    "iso:country":"ES",
    "sg:address":"Ctra Barcelona, 278",
    "sg:city":"Barbera Valles",
    "sg:orig_category":"Agencias Y Agentes Comerciales, Representantes",
    "sg:phone":"+34 937 18 60 02",
    "sg:postcode":"08210",
    "sg:province":"Barcelona",
    "wof:name":"Com. Propietarios Crta. De Barcelona 278",
    "wof:placetype":"venue"
},
  "geometry": {"coordinates":[2.1223299503,41.523639679],"type":"Point"}
}