{
  "type": "Feature",
  "properties": {
    "addr:full":"Trva Casa Higa, 4 Cruz Santa Santa Cruz De Tenerife 38413",
    "addr:housenumber":"4",
    "addr:postcode":"38413",
    "addr:street":"Trva;Higa;Santa",
    "iso:country":"ES",
    "sg:address":"Trva Casa Higa, 4",
    "sg:city":"Cruz Santa",
    "sg:orig_category":"Telas Y Sedas (al Por Menor)",
    "sg:phone":"+34 922 34 28 95",
    "sg:postcode":"38413",
    "sg:province":"Santa Cruz De Tenerife",
    "wof:name":"Modas Tamerayda S.l.",
    "wof:placetype":"venue"
},
  "geometry": {"coordinates":[-16.5676803589,28.3788814545],"type":"Point"}
}