{
  "type": "Feature",
  "properties": {
    "iso:country":"ES",
    "sg:address":"Calle de Maspe, 2",
    "sg:city":"Iurreta",
    "sg:orig_category":"Empresas De Carpinter\u00cda De Madera",
    "sg:phone":"+34 944 66 80 28",
    "sg:postcode":"48215",
    "sg:province":"Vizcaya",
    "wof:name":"Juan Gregorio Urien Asategui (carpinteria Gregorio)",
    "wof:placetype":"venue"
},
  "geometry": {"coordinates":[-2.6387727261,43.1738014221],"type":"Point"}
}