{
  "type": "Feature",
  "properties": {
    "addr:full":"Calle de Rio Cares, 8 Gijon Asturias 33210",
    "addr:housenumber":"8",
    "addr:postcode":"33210",
    "addr:street":"Calle De Rio Cares",
    "iso:country":"ES",
    "sg:address":"Calle de Rio Cares, 8",
    "sg:city":"Gijon",
    "sg:orig_category":"Venta, Instalaci\u00d3n De Calefacci\u00d3n",
    "sg:phone":"+34 985 15 24 31",
    "sg:postcode":"33210",
    "sg:province":"Asturias",
    "wof:name":"Servicios Urbanos De Gas S.l.",
    "wof:placetype":"venue"
},
  "geometry": {"coordinates":[-5.6668181419,43.5191917419],"type":"Point"}
}