{
  "type": "Feature",
  "properties": {
    "iso:country":"ES",
    "sg:address":"Calle de San Agustin, 17",
    "sg:city":"Albacete",
    "sg:orig_category":"Arquitectos",
    "sg:phone":"+34 967 52 25 34",
    "sg:postcode":"02001",
    "sg:province":"Albacete",
    "wof:name":"Alcaraz Ruiz Vicente",
    "wof:placetype":"venue"
},
  "geometry": {"coordinates":[-1.8519208431,38.9940986633],"type":"Point"}
}