{
  "type": "Feature",
  "properties": {
    "addr:full":"Calle de Mayor, 5 Illueca Zaragoza 50250",
    "addr:housenumber":"5",
    "addr:postcode":"50250",
    "addr:street":"Calle De Mayor",
    "iso:country":"ES",
    "sg:address":"Calle de Mayor, 5",
    "sg:city":"Illueca",
    "sg:orig_category":"Supermercados Y Hipermercados",
    "sg:phone":"+34 976 82 01 87",
    "sg:postcode":"50250",
    "sg:province":"Zaragoza",
    "wof:name":"Martin Castejon Iluminada",
    "wof:placetype":"venue"
},
  "geometry": {"coordinates":[-1.6287920475,41.5383033752],"type":"Point"}
}