{
  "type": "Feature",
  "properties": {
    "addr:full":"Carrer de Mandri, 19 Barcelona Barcelona 08022",
    "addr:housenumber":"19",
    "addr:postcode":"08022",
    "addr:street":"Carrer De Mandri",
    "iso:country":"ES",
    "sg:address":"Carrer de Mandri, 19",
    "sg:city":"Barcelona",
    "sg:orig_category":"M\u00c9dicos: Psiquiatr\u00cda",
    "sg:phone":"+34 934 17 55 85",
    "sg:postcode":"08022",
    "sg:province":"Barcelona",
    "wof:name":"Corominas Vigneaux Julia",
    "wof:placetype":"venue"
},
  "geometry": {"coordinates":[2.1343588829,41.4025497437],"type":"Point"}
}