{
  "type": "Feature",
  "properties": {
    "addr:full":"Calle de Ramon Y Cajal, 45 Cuarte Huerva Zaragoza 50410",
    "addr:housenumber":"45",
    "addr:postcode":"50410",
    "addr:street":"Calle De Ramon Y Cajal",
    "iso:country":"ES",
    "sg:address":"Calle de Ramon Y Cajal, 45",
    "sg:city":"Cuarte Huerva",
    "sg:orig_category":"Bordado, Marcado A Medida",
    "sg:phone":"+34 976 50 54 60",
    "sg:postcode":"50410",
    "sg:province":"Zaragoza",
    "wof:name":"Bordosa Y Confecciones S.l.",
    "wof:placetype":"venue"
},
  "geometry": {"coordinates":[-0.9291650057,41.5911865234],"type":"Point"}
}