{
  "type": "Feature",
  "properties": {
    "addr:full":"Portua, 2 Getaria Guip\u00f9zcoa 20808",
    "addr:housenumber":"2",
    "addr:postcode":"20808",
    "addr:street":"Portua;Guipu\u0300Zcoa",
    "iso:country":"ES",
    "sg:address":"Portua, 2",
    "sg:city":"Getaria",
    "sg:orig_category":"Almacenes Frigor\u00cdficos",
    "sg:phone":"+34 943 14 08 84",
    "sg:postcode":"20808",
    "sg:province":"Guip\u00f9zcoa",
    "wof:name":"Instalaciones Frigolan S.l.",
    "wof:placetype":"venue"
},
  "geometry": {"coordinates":[-2.2024416924,43.3057174683],"type":"Point"}
}