{
  "type": "Feature",
  "properties": {
    "iso:country":"ES",
    "sg:address":"Calle de Perigall, 45",
    "sg:city":"Urbanizacion Montesano",
    "sg:orig_category":"Centros Empresariales",
    "sg:phone":"+34 961 35 13 25",
    "sg:postcode":"46184",
    "sg:province":"Valencia",
    "wof:name":"Sanchez Collado Enrique",
    "wof:placetype":"venue"
},
  "geometry": {"coordinates":[-0.5127639771,39.577671051],"type":"Point"}
}