{
  "type": "Feature",
  "properties": {
    "iso:country":"ES",
    "sg:address":"Pase Acacias, 50",
    "sg:city":"Madrid",
    "sg:orig_category":"Caf\u00c9s, Bares, Cervecer\u00cdas",
    "sg:phone":"+34 915 17 13 71",
    "sg:postcode":"28005",
    "sg:province":"Madrid",
    "wof:name":"Sanchez Marbella Santos",
    "wof:placetype":"venue"
},
  "geometry": {"coordinates":[-3.7126960754,40.4016151428],"type":"Point"}
}