{
  "type": "Feature",
  "properties": {
    "iso:country":"ES",
    "sg:address":"Avda Espa\u00d1a, 78",
    "sg:city":"Majadahonda",
    "sg:orig_category":"Gastronom\u00cda: Especialidades Regionales (al Por Menor)",
    "sg:phone":"+34 916 34 79 08",
    "sg:postcode":"28220",
    "sg:province":"Madrid",
    "wof:name":"Pizza Jardin Noroeste S.l.",
    "wof:placetype":"venue"
},
  "geometry": {"coordinates":[-3.8662550449,40.4618797302],"type":"Point"}
}