{
  "type": "Feature",
  "properties": {
    "iso:country":"ES",
    "sg:address":"Calle de Campo, 12",
    "sg:city":"Soria",
    "sg:orig_category":"Ropa Para Se\u00d1oras (al Por Menor)",
    "sg:phone":"+34 975 23 10 29",
    "sg:postcode":"42001",
    "sg:province":"Soria",
    "wof:name":"Vizcaya Perez Maria Socorro",
    "wof:placetype":"venue"
},
  "geometry": {"coordinates":[-2.4692800045,41.765953064],"type":"Point"}
}