{
  "type": "Feature",
  "properties": {
    "iso:country":"ES",
    "sg:address":"Calle de Bruselas, 2",
    "sg:city":"Zaragoza",
    "sg:orig_category":"Agentes, Concesionarios Y Sucursales De Camiones Y Veh\u00cdculos Industriales",
    "sg:phone":"+34 976 44 30 06",
    "sg:postcode":"50003",
    "sg:province":"Zaragoza",
    "wof:name":"Aragonesa Recuperadora De Neumaticos S.l.",
    "wof:placetype":"venue"
},
  "geometry": {"coordinates":[-0.9028866291,41.6608772278],"type":"Point"}
}