{
  "type": "Feature",
  "properties": {
    "addr:full":"Calle de Alejandro Olivan, 10 Zaragoza Zaragoza 50011",
    "addr:housenumber":"10",
    "addr:postcode":"50011",
    "addr:street":"Calle De Alejandro Olivan",
    "iso:country":"ES",
    "sg:address":"Calle de Alejandro Olivan, 10",
    "sg:city":"Zaragoza",
    "sg:orig_category":"Carnicer\u00cdas, Carnicer\u00cdas",
    "sg:phone":"+34 976 53 07 56",
    "sg:postcode":"50011",
    "sg:province":"Zaragoza",
    "wof:name":"Caba\u00f1as Morcillo Maria Pilar",
    "wof:placetype":"venue"
},
  "geometry": {"coordinates":[-0.9216479063,41.6488647461],"type":"Point"}
}