{
  "type": "Feature",
  "properties": {
    "iso:country":"ES",
    "sg:address":"Carr Vicen\u00c7 Buades, S/n",
    "sg:city":"Puerto De Pollen\u00c7a",
    "sg:orig_category":"Electrodom\u00c9sticos (al Por Menor)",
    "sg:phone":"+34 971 86 67 88",
    "sg:postcode":"07470",
    "sg:province":"Islas Baleares",
    "wof:name":"Electrica Port S.l.",
    "wof:placetype":"venue"
},
  "geometry": {"coordinates":[3.0821900368,39.9063034058],"type":"Point"}
}