{
  "type": "Feature",
  "properties": {
    "iso:country":"ES",
    "sg:address":"Calle de Guipuzcoa, 49",
    "sg:city":"Gijon",
    "sg:orig_category":"Mercer\u00cda, Lencer\u00cda (al Por Menor)",
    "sg:phone":"+34 985 14 66 39",
    "sg:postcode":"33210",
    "sg:province":"Asturias",
    "wof:name":"Menendez Alvarez Maria Dolores",
    "wof:placetype":"venue"
},
  "geometry": {"coordinates":[-5.6694488525,43.5250396729],"type":"Point"}
}