{
  "type": "Feature",
  "properties": {
    "addr:full":"Carr Igualada, 3 Lleida Lleida 25007",
    "addr:housenumber":"3",
    "addr:postcode":"25007",
    "addr:street":"Carr Igualada",
    "iso:country":"ES",
    "sg:address":"Carr Igualada, 3",
    "sg:city":"Lleida",
    "sg:orig_category":"Ense\u00d1anza Variada",
    "sg:phone":"+34 973 22 09 29",
    "sg:postcode":"25007",
    "sg:province":"Lleida",
    "wof:name":"Porras Nicolau Maria Carmen",
    "wof:placetype":"venue"
},
  "geometry": {"coordinates":[0.6287389994,41.6203231812],"type":"Point"}
}