{
  "type": "Feature",
  "properties": {
    "addr:full":"Calle de Beneficiado Jose Estupi\u00d1an, 5 Goro Las Palmas 35215",
    "addr:housenumber":"5",
    "addr:postcode":"35215",
    "addr:street":"Calle De Beneficiado Jose Estupin\u0303An",
    "iso:country":"ES",
    "sg:address":"Calle de Beneficiado Jose Estupi\u00d1an, 5",
    "sg:city":"Goro",
    "sg:orig_category":"Comercio De Piezas De Recambio Y De Accesorios De Veh\u00cdculos, Veh\u00cdculos Industriales",
    "sg:phone":"+34 928 70 12 70",
    "sg:postcode":"35215",
    "sg:province":"Las Palmas",
    "sg:website":"www.cecauto.com",
    "wof:name":"Cecauto Canarias S.a.",
    "wof:placetype":"venue"
},
  "geometry": {"coordinates":[-15.398223877,27.9939899445],"type":"Point"}
}