{
  "type": "Feature",
  "properties": {
    "iso:country":"ES",
    "sg:address":"Carr Girona, 25",
    "sg:city":"Bascara",
    "sg:orig_category":"Pesca Y Caza: Art\u00cdculos (al Por Menor)",
    "sg:phone":"+34 972 55 16 94",
    "sg:postcode":"17483",
    "sg:province":"Girona",
    "wof:name":"Teixidor Garriga Patrici",
    "wof:placetype":"venue"
},
  "geometry": {"coordinates":[2.9556200504,42.1445083618],"type":"Point"}
}