{
  "type": "Feature",
  "properties": {
    "iso:country":"ES",
    "sg:address":"Rbla Volart, 11",
    "sg:city":"Barcelona",
    "sg:orig_category":"Librer\u00cdas",
    "sg:phone":"+34 934 36 87 67",
    "sg:postcode":"08041",
    "sg:province":"Barcelona",
    "wof:name":"Mulet Felip Blanca",
    "wof:placetype":"venue"
},
  "geometry": {"coordinates":[2.1794900894,41.4157333374],"type":"Point"}
}