{
  "type": "Feature",
  "properties": {
    "iso:country":"ES",
    "sg:address":"Calle de Prado (el), 21",
    "sg:city":"Bollullos Mitacion",
    "sg:orig_category":"Farmacias",
    "sg:phone":"+34 955 69 50 75",
    "sg:postcode":"41110",
    "sg:province":"Sevilla",
    "wof:name":"St Jude Medical Espa\u00d1a S.a.",
    "wof:placetype":"venue"
},
  "geometry": {"coordinates":[-6.0819406509,37.393196106],"type":"Point"}
}