{
  "type": "Feature",
  "properties": {
    "iso:country":"ES",
    "sg:address":"Avda Perez Galdos, 72",
    "sg:city":"Logro\u00f1o",
    "sg:orig_category":"Tiendas De Grano, Frutas Y Legumbres Secas (al Por Menor)",
    "sg:phone":"+34 941 20 08 67",
    "sg:postcode":"26005",
    "sg:province":"La Rioja",
    "wof:name":"Blazquez Leria Jose Alfredo",
    "wof:placetype":"venue"
},
  "geometry": {"coordinates":[-2.4554519653,42.4631195068],"type":"Point"}
}