{
  "type": "Feature",
  "properties": {
    "addr:full":"Avda Buenos Aires, S/n Lalin Pontevedra 36500",
    "addr:housenumber":"s",
    "addr:postcode":"36500",
    "addr:street":"Avda Buenos Aires;/ N",
    "iso:country":"ES",
    "sg:address":"Avda Buenos Aires, S/n",
    "sg:city":"Lalin",
    "sg:orig_category":"Ense\u00d1anza Secundaria: Colegios Y Escuelas Privadas",
    "sg:phone":"+34 986 78 70 51",
    "sg:postcode":"36500",
    "sg:province":"Pontevedra",
    "wof:name":"Ies Laxeiro",
    "wof:placetype":"venue"
},
  "geometry": {"coordinates":[-8.1118106842,42.6568450928],"type":"Point"}
}