{
  "type": "Feature",
  "properties": {
    "addr:full":"Calle de Bucarest, 37 Torreciega Murcia 30391",
    "addr:housenumber":"37",
    "addr:postcode":"30391",
    "addr:street":"Calle De Bucarest",
    "iso:country":"ES",
    "sg:address":"Calle de Bucarest, 37",
    "sg:city":"Torreciega",
    "sg:orig_category":"Inmobiliaria (agencias)",
    "sg:phone":"+34 968 32 08 08",
    "sg:postcode":"30391",
    "sg:province":"Murcia",
    "wof:name":"Linker S.l.",
    "wof:placetype":"venue"
},
  "geometry": {"coordinates":[-0.9562063813,37.6205329895],"type":"Point"}
}