{
  "type": "Feature",
  "properties": {
    "iso:country":"ES",
    "sg:address":"Ctra Palac-isla Menor, S/n",
    "sg:city":"Palacios Y Villafranca",
    "sg:orig_category":"Producci\u00d3n, Venta De Productos De Agricultura Biol\u00d3gica",
    "sg:phone":"+34 955 89 80 42",
    "sg:postcode":"41720",
    "sg:province":"Sevilla",
    "wof:name":"Cotos Regables Del Guadalquivir S.l.",
    "wof:placetype":"venue"
},
  "geometry": {"coordinates":[-5.9241790771,37.1630935669],"type":"Point"}
}