{
  "type": "Feature",
  "properties": {
    "iso:country":"ES",
    "sg:address":"Calle de San Blas, 5",
    "sg:city":"Burlada",
    "sg:orig_category":"Agentes Generales De Seguros",
    "sg:phone":"+34 948 13 49 59",
    "sg:postcode":"31600",
    "sg:province":"Navarra",
    "wof:name":"Landa Perez Maria Eugenia",
    "wof:placetype":"venue"
},
  "geometry": {"coordinates":[-1.6145670414,42.8226585388],"type":"Point"}
}