{
  "type": "Feature",
  "properties": {
    "iso:country":"ES",
    "sg:address":"Pol Ind Martiartu I, 17",
    "sg:city":"Arrigorriaga",
    "sg:orig_category":"Promotores Constructores",
    "sg:phone":"+34 946 71 50 51",
    "sg:postcode":"48480",
    "sg:province":"Vizcaya",
    "wof:name":"Obras Y Contratas Basauri S.l.",
    "wof:placetype":"venue"
},
  "geometry": {"coordinates":[-2.8716180325,43.2117424011],"type":"Point"}
}