{
  "type": "Feature",
  "properties": {
    "addr:full":"Carrer de Major, 13 Argentera Tarragona 43773",
    "addr:housenumber":"13",
    "addr:postcode":"43773",
    "addr:street":"Carrer De Major",
    "iso:country":"ES",
    "sg:address":"Carrer de Major, 13",
    "sg:city":"Argentera",
    "sg:orig_category":"Poller\u00cda Y Caza (al Por Menor)",
    "sg:phone":"+34 977 83 43 88",
    "sg:postcode":"43773",
    "sg:province":"Tarragona",
    "wof:name":"Castellvi Valls Lluis Maria",
    "wof:placetype":"venue"
},
  "geometry": {"coordinates":[0.9098920226,41.1373710632],"type":"Point"}
}