{
  "type": "Feature",
  "properties": {
    "addr:full":"Bloc Mexic, S/n Sant Pere I Sant Pau Tarragona 43007",
    "addr:housenumber":"s / n",
    "addr:postcode":"43007",
    "iso:country":"ES",
    "sg:address":"Bloc Mexic, S/n",
    "sg:city":"Sant Pere I Sant Pau",
    "sg:orig_category":"Empresas De Carpinter\u00cda",
    "sg:phone":"+34 977 20 13 83",
    "sg:postcode":"43007",
    "sg:province":"Tarragona",
    "wof:name":"Aluminis Agusti S.l.",
    "wof:placetype":"venue"
},
  "geometry": {"coordinates":[1.2519127131,41.138835907],"type":"Point"}
}