{
  "type": "Feature",
  "properties": {
    "iso:country":"ES",
    "sg:address":"Calle de Duque De La Victoria, 7",
    "sg:city":"Valladolid",
    "sg:orig_category":"Suministros Y Materiales Industriales",
    "sg:phone":"+34 983 30 47 92",
    "sg:postcode":"47001",
    "sg:province":"Valladolid",
    "wof:name":"Gonzalez Mayo Jose Antonio",
    "wof:placetype":"venue"
},
  "geometry": {"coordinates":[-4.7267942429,41.6509666443],"type":"Point"}
}