{
  "type": "Feature",
  "properties": {
    "addr:full":"Calle de Isabel La Catolica, 1 Aguilas Murcia 30880",
    "addr:housenumber":"1",
    "addr:postcode":"30880",
    "addr:street":"Calle De Isabel La Catolica",
    "iso:country":"ES",
    "sg:address":"Calle de Isabel La Catolica, 1",
    "sg:city":"Aguilas",
    "sg:orig_category":"Arquitectos",
    "sg:phone":"+34 968 41 40 65",
    "sg:postcode":"30880",
    "sg:province":"Murcia",
    "wof:name":"Marin Gomez Juan Francisco",
    "wof:placetype":"venue"
},
  "geometry": {"coordinates":[-1.5820417404,37.4033088684],"type":"Point"}
}