{
  "type": "Feature",
  "properties": {
    "iso:country":"ES",
    "sg:address":"Calle de Camino De Los Vinateros, 83",
    "sg:city":"Madrid",
    "sg:orig_category":"Puertas Y Portales",
    "sg:phone":"+34 914 30 08 46",
    "sg:postcode":"28030",
    "sg:province":"Madrid",
    "wof:name":"Pe\u00f1a Pe\u00f1a Jesus",
    "wof:placetype":"venue"
},
  "geometry": {"coordinates":[-3.6493430138,40.4094467163],"type":"Point"}
}