{
  "type": "Feature",
  "properties": {
    "iso:country":"ES",
    "sg:address":"Calle de Audiencia, 58",
    "sg:city":"Montiel",
    "sg:orig_category":"Contenedores (mercanc\u00cdas)",
    "sg:phone":"+34 926 35 35 29",
    "sg:postcode":"13326",
    "sg:province":"Ciudad Real",
    "wof:name":"Mena Alamo Felipe",
    "wof:placetype":"venue"
},
  "geometry": {"coordinates":[-2.8609132767,38.6972122192],"type":"Point"}
}