{
  "type": "Feature",
  "properties": {
    "addr:full":"Ctra Bigastro, S/n Correntias Medias Alicante 03300",
    "addr:housenumber":"s / n",
    "addr:postcode":"03300",
    "addr:street":"Ctra Bigastro",
    "iso:country":"ES",
    "sg:address":"Ctra Bigastro, S/n",
    "sg:city":"Correntias Medias",
    "sg:orig_category":"Materias Pl\u00c1sticas: Productos De Consumo Masivo (fabricaci\u00d3n, Al Por Mayor)",
    "sg:phone":"+34 966 74 36 91",
    "sg:postcode":"03300",
    "sg:province":"Alicante",
    "wof:name":"Oribol S.a.",
    "wof:placetype":"venue"
},
  "geometry": {"coordinates":[-0.9283540249,38.0760688782],"type":"Point"}
}