{
  "type": "Feature",
  "properties": {
    "addr:full":"Plaz Jaime Calatrava, 9 Tabernas Almer\u00eda 04200",
    "addr:housenumber":"9",
    "addr:postcode":"04200",
    "addr:street":"Plaz Jaime Calatrava;Almeri\u0301A",
    "iso:country":"ES",
    "sg:address":"Plaz Jaime Calatrava, 9",
    "sg:city":"Tabernas",
    "sg:orig_category":"Papeler\u00cdas, Librer\u00cdas",
    "sg:phone":"+34 950 36 52 05",
    "sg:postcode":"04200",
    "sg:province":"Almer\u00eda",
    "wof:name":"Lopez Iba\u00f1ez Rosa Mari",
    "wof:placetype":"venue"
},
  "geometry": {"coordinates":[-2.3616201878,37.0809898376],"type":"Point"}
}