{
  "type": "Feature",
  "properties": {
    "iso:country":"ES",
    "sg:address":"Calle de Pino, 31",
    "sg:city":"Arges",
    "sg:orig_category":"Carnicer\u00cdas, Carnicer\u00cdas",
    "sg:phone":"+34 925 37 71 25",
    "sg:postcode":"45122",
    "sg:province":"Toledo",
    "wof:name":"Puebla Ortega Jorge",
    "wof:placetype":"venue"
},
  "geometry": {"coordinates":[-4.0665669441,39.8096809387],"type":"Point"}
}