{
  "type": "Feature",
  "properties": {
    "iso:country":"ES",
    "sg:address":"Calle de Tribulete, 23",
    "sg:city":"Madrid",
    "sg:orig_category":"Molduras, Junquillos, Listones Y Molduras Perforadas",
    "sg:phone":"+34 914 67 82 46",
    "sg:postcode":"28012",
    "sg:province":"Madrid",
    "wof:name":"Bernaldo De Quiros Arteaga Fernado",
    "wof:placetype":"venue"
},
  "geometry": {"coordinates":[-3.7032558918,40.4073257446],"type":"Point"}
}