{
  "type": "Feature",
  "properties": {
    "addr:full":"Trva Castros, 2 Vilalba Lugo 27800",
    "addr:housenumber":"2",
    "addr:postcode":"27800",
    "addr:street":"Trva Castros",
    "iso:country":"ES",
    "sg:address":"Trva Castros, 2",
    "sg:city":"Vilalba",
    "sg:orig_category":"Cajas Para Embalar",
    "sg:phone":"+34 982 51 11 00",
    "sg:postcode":"27800",
    "sg:province":"Lugo",
    "wof:name":"Caixa Rural Galega S.c.c.l.g.",
    "wof:placetype":"venue"
},
  "geometry": {"coordinates":[-7.6803798676,43.2955818176],"type":"Point"}
}