{
  "type": "Feature",
  "properties": {
    "iso:country":"ES",
    "sg:address":"Calle de Tormento, 30",
    "sg:city":"Palmas De Gran Canaria",
    "sg:orig_category":"Molduras, Junquillos, Listones Y Molduras Perforadas",
    "sg:phone":"+34 928 25 65 91",
    "sg:postcode":"35012",
    "sg:province":"Las Palmas",
    "wof:name":"Santana Sosa Pedro Luis",
    "wof:placetype":"venue"
},
  "geometry": {"coordinates":[-15.4355831146,28.1093521118],"type":"Point"}
}