{
  "type": "Feature",
  "properties": {
    "iso:country":"ES",
    "sg:address":"Calle de Ramon Y Cajal, 6",
    "sg:city":"Alberic",
    "sg:orig_category":"Alquiler De V\u00cddeo",
    "sg:phone":"+34 962 44 31 52",
    "sg:postcode":"46260",
    "sg:province":"Valencia",
    "wof:name":"Alberola Arias Jesus",
    "wof:placetype":"venue"
},
  "geometry": {"coordinates":[-0.5210970044,39.117099762],"type":"Point"}
}