{
  "type": "Feature",
  "properties": {
    "iso:country":"ES",
    "sg:address":"Avgd Del Cami Nou, 189",
    "sg:city":"Xirivella",
    "sg:orig_category":"Perfumer\u00cda Y Cosm\u00c9tica (fabricaci\u00d3n, Al Por Mayor)",
    "sg:phone":"+34 963 83 13 71",
    "sg:postcode":"46950",
    "sg:province":"Valencia",
    "wof:name":"Cano Rodriguez Maria Del Carmen",
    "wof:placetype":"venue"
},
  "geometry": {"coordinates":[-0.4393720031,39.4618759155],"type":"Point"}
}