{
  "type": "Feature",
  "properties": {
    "iso:country":"ES",
    "sg:address":"Calle de Mirasierra, 5",
    "sg:city":"Fuengirola",
    "sg:orig_category":"Electricidad: Instaladores",
    "sg:phone":"+34 952 47 18 56",
    "sg:postcode":"29640",
    "sg:province":"M\u00e1laga",
    "wof:name":"Gomez Fragoso Juan",
    "wof:placetype":"venue"
},
  "geometry": {"coordinates":[-4.6270542145,36.5412712097],"type":"Point"}
}