{
  "type": "Feature",
  "properties": {
    "iso:country":"ES",
    "sg:address":"Calle de Mayor, 37",
    "sg:city":"Santo Domingo De La Calzada",
    "sg:orig_category":"Arreglo, Reparaci\u00d3n, Piezas Sueltas De Televisi\u00d3n, V\u00cddeo, Hi",
    "sg:phone":"+34 941 34 09 08",
    "sg:postcode":"26250",
    "sg:province":"La Rioja",
    "wof:name":"Dulac Bartolome Pedro",
    "wof:placetype":"venue"
},
  "geometry": {"coordinates":[-2.9516339302,42.4408302307],"type":"Point"}
}