{
  "type": "Feature",
  "properties": {
    "iso:country":"ES",
    "sg:address":"Pol Ind El Poligono, S/n",
    "sg:city":"Mancha Real",
    "sg:orig_category":"Muebles",
    "sg:phone":"+34 953 35 09 95",
    "sg:postcode":"23100",
    "sg:province":"Ja\u00e9n",
    "wof:name":"Coysa Muebles De Cocina S.l.",
    "wof:placetype":"venue"
},
  "geometry": {"coordinates":[-3.609249115,37.7891464233],"type":"Point"}
}