{
  "type": "Feature",
  "properties": {
    "iso:country":"ES",
    "sg:address":"Carr Eres De La Vila, 32",
    "sg:city":"Figueres",
    "sg:orig_category":"Pescader\u00cdas (al Por Menor)",
    "sg:phone":"+34 972 67 27 96",
    "sg:postcode":"17600",
    "sg:province":"Girona",
    "wof:name":"Neptuno S.c.",
    "wof:placetype":"venue"
},
  "geometry": {"coordinates":[2.9641399384,42.2680130005],"type":"Point"}
}