{
  "type": "Feature",
  "properties": {
    "addr:full":"Calle de Mendez Nu\u00d1ez, 27 Cangas Pontevedra 36940",
    "addr:housenumber":"27",
    "addr:postcode":"36940",
    "addr:street":"Calle De Mendez Nun\u0303Ez",
    "iso:country":"ES",
    "sg:address":"Calle de Mendez Nu\u00d1ez, 27",
    "sg:city":"Cangas",
    "sg:orig_category":"Fotocopias, Reprograf\u00cda",
    "sg:phone":"+34 986 30 32 66",
    "sg:postcode":"36940",
    "sg:province":"Pontevedra",
    "wof:name":"Artiplan Cangas S.l.",
    "wof:placetype":"venue"
},
  "geometry": {"coordinates":[-8.7805614471,42.2641143799],"type":"Point"}
}