{
  "type": "Feature",
  "properties": {
    "iso:country":"ES",
    "sg:address":"Ctra. Eivissa Portinatx, Km. 0004,0",
    "sg:city":"Ntra. Sra. Jesus",
    "sg:orig_category":"Molduras, Junquillos, Listones Y Molduras Perforadas",
    "sg:phone":"+34 971 19 09 73",
    "sg:postcode":"07819",
    "sg:province":"Islas Baleares",
    "wof:name":"Mari Serra Maria",
    "wof:placetype":"venue"
},
  "geometry": {"coordinates":[1.444257021,38.934135437],"type":"Point"}
}