{
  "type": "Feature",
  "properties": {
    "iso:country":"ES",
    "sg:address":"Cmno Gavias (las), 32",
    "sg:city":"San Cristobal De La Laguna",
    "sg:orig_category":"Frutas Y Legumbres Frescas (al Por Mayor)",
    "sg:phone":"+34 922 26 07 87",
    "sg:postcode":"38202",
    "sg:province":"Santa Cruz De Tenerife",
    "wof:name":"Rodriguez Gonzalez Juan Antonio",
    "wof:placetype":"venue"
},
  "geometry": {"coordinates":[-16.3259983063,28.4924488068],"type":"Point"}
}