{
  "type": "Feature",
  "properties": {
    "iso:country":"ES",
    "sg:address":"Calle de Angel Luis De La Herran, 27",
    "sg:city":"Madrid",
    "sg:orig_category":"Ense\u00d1anza: Profesiones Art\u00cdsticas",
    "sg:phone":"+34 917 64 30 24",
    "sg:postcode":"28043",
    "sg:province":"Madrid",
    "wof:name":"Ortega Laborda Andrea",
    "wof:placetype":"venue"
},
  "geometry": {"coordinates":[-3.6493103504,40.4702644348],"type":"Point"}
}