{
  "type": "Feature",
  "properties": {
    "addr:full":"Calle de Zorrilla, 17 Elda Alicante 03600",
    "addr:housenumber":"17",
    "addr:postcode":"03600",
    "addr:street":"Calle De Zorrilla",
    "iso:country":"ES",
    "sg:address":"Calle de Zorrilla, 17",
    "sg:city":"Elda",
    "sg:orig_category":"Farmacias",
    "sg:phone":"+34 965 38 70 41",
    "sg:postcode":"03600",
    "sg:province":"Alicante",
    "wof:name":"Picazo Romero Jose Maria",
    "wof:placetype":"venue"
},
  "geometry": {"coordinates":[-0.7912700176,38.473323822],"type":"Point"}
}