{
  "type": "Feature",
  "properties": {
    "addr:full":"Avda Celanova (de), 59 Valenza Ourense 32002",
    "addr:housenumber":"59",
    "addr:postcode":"32002",
    "addr:street":"Avda Celanova De",
    "iso:country":"ES",
    "sg:address":"Avda Celanova (de), 59",
    "sg:city":"Valenza",
    "sg:orig_category":"Perfumer\u00cda (al Por Menor)",
    "sg:phone":"+34 988 22 02 33",
    "sg:postcode":"32002",
    "sg:province":"Ourense",
    "wof:name":"Decogar S.a.",
    "wof:placetype":"venue"
},
  "geometry": {"coordinates":[-7.8813061714,42.3192367554],"type":"Point"}
}