{
  "type": "Feature",
  "properties": {
    "addr:full":"Carrer de Latorre, 155 Sabadell Barcelona 08203",
    "addr:housenumber":"155",
    "addr:postcode":"08203",
    "addr:street":"Carrer De Latorre",
    "iso:country":"ES",
    "sg:address":"Carrer de Latorre, 155",
    "sg:city":"Sabadell",
    "sg:orig_category":"Electricidad, Electr\u00d3nica: Material Y Suministros (al Por Mayor)",
    "sg:phone":"+34 937 10 46 88",
    "sg:postcode":"08203",
    "sg:province":"Barcelona",
    "wof:name":"Equips D'oficina Salvans S.l.",
    "wof:placetype":"venue"
},
  "geometry": {"coordinates":[2.1088309288,41.5381507874],"type":"Point"}
}