{
  "type": "Feature",
  "properties": {
    "addr:full":"Ugaldeguren I Poligonoa, S/n Ugaldeguren Vizcaya 48170",
    "addr:housenumber":"s / n",
    "addr:postcode":"48170",
    "addr:street":"I Poligonoa",
    "iso:country":"ES",
    "sg:address":"Ugaldeguren I Poligonoa, S/n",
    "sg:city":"Ugaldeguren",
    "sg:orig_category":"Cer\u00c1micas: Material Y Suministros",
    "sg:phone":"+34 944 53 80 75",
    "sg:postcode":"48170",
    "sg:province":"Vizcaya",
    "wof:name":"Grupo Ap & L S.l.",
    "wof:placetype":"venue"
},
  "geometry": {"coordinates":[-2.8633139133,43.280834198],"type":"Point"}
}