{
  "type": "Feature",
  "properties": {
    "addr:full":"Calle de Animas, 21 Moron Frontera Sevilla 41530",
    "addr:housenumber":"21",
    "addr:postcode":"41530",
    "addr:street":"Calle De Animas",
    "iso:country":"ES",
    "sg:address":"Calle de Animas, 21",
    "sg:city":"Moron Frontera",
    "sg:orig_category":"Alimentaci\u00d3n General (al Por Menor)",
    "sg:phone":"+34 955 85 04 42",
    "sg:postcode":"41530",
    "sg:province":"Sevilla",
    "wof:name":"Casa Lorenzo Autoservicio S.l.",
    "wof:placetype":"venue"
},
  "geometry": {"coordinates":[-5.4509510994,37.1206741333],"type":"Point"}
}