{
  "type": "Feature",
  "properties": {
    "iso:country":"ES",
    "sg:address":"B (pol Talluntxe), S/n",
    "sg:city":"Noain",
    "sg:orig_category":"Suministros Para Hoteles",
    "sg:phone":"+34 948 31 27 94",
    "sg:postcode":"31110",
    "sg:province":"Navarra",
    "sg:website":"www.mhh-sat.com",
    "wof:name":"Navarra De Hosteleria Y Hospitales",
    "wof:placetype":"venue"
},
  "geometry": {"coordinates":[-1.6433140039,42.7574806213],"type":"Point"}
}