{
  "type": "Feature",
  "properties": {
    "iso:country":"ES",
    "sg:address":"Calle de Musgo, 5",
    "sg:city":"Madrid",
    "sg:orig_category":"Caf\u00c9s, Bares, Cervecer\u00cdas",
    "sg:phone":"+34 913 07 65 97",
    "sg:postcode":"28023",
    "sg:province":"Madrid",
    "wof:name":"Pick-lunch S.a.",
    "wof:placetype":"venue"
},
  "geometry": {"coordinates":[-3.8012669086,40.4673881531],"type":"Point"}
}