{
  "type": "Feature",
  "properties": {
    "addr:full":"San Pelayo, 27 San Pelayo Asturias 33468",
    "addr:housenumber":"27",
    "addr:postcode":"33468",
    "addr:street":"San",
    "iso:country":"ES",
    "sg:address":"San Pelayo, 27",
    "sg:city":"San Pelayo",
    "sg:orig_category":"Suministros Para Hoteles",
    "sg:phone":"+34 985 51 57 34",
    "sg:postcode":"33468",
    "sg:province":"Asturias",
    "wof:name":"Cofrico S.l.",
    "wof:placetype":"venue"
},
  "geometry": {"coordinates":[-5.8703289032,43.563129425],"type":"Point"}
}