{
  "type": "Feature",
  "properties": {
    "iso:country":"ES",
    "sg:address":"Carr Guillem Santandreu, 27",
    "sg:city":"Lloseta",
    "sg:orig_category":"Farmacias",
    "sg:phone":"+34 971 51 40 38",
    "sg:postcode":"07360",
    "sg:province":"Islas Baleares",
    "wof:name":"Real Ramis Bernardo",
    "wof:placetype":"venue"
},
  "geometry": {"coordinates":[2.867139101,39.7179069519],"type":"Point"}
}