{
  "type": "Feature",
  "properties": {
    "addr:full":"Carrer de Narcis Monturiol (de), 55 Vilassar De Mar Barcelona 08340",
    "addr:housenumber":"55",
    "addr:postcode":"08340",
    "addr:street":"Carrer De Narcis Monturiol De",
    "iso:country":"ES",
    "sg:address":"Carrer de Narcis Monturiol (de), 55",
    "sg:city":"Vilassar De Mar",
    "sg:orig_category":"Reposter\u00cdas",
    "sg:phone":"+34 937 59 10 46",
    "sg:postcode":"08340",
    "sg:province":"Barcelona",
    "wof:name":"Baldau S.l.",
    "wof:placetype":"venue"
},
  "geometry": {"coordinates":[2.3895120621,41.5058708191],"type":"Point"}
}