{
  "type": "Feature",
  "properties": {
    "addr:full":"Pla\u00c7 Major, 4 Sant Joan De Les Abadesses Girona 17860",
    "addr:postcode":"17860",
    "iso:country":"ES",
    "sg:address":"Pla\u00c7 Major, 4",
    "sg:city":"Sant Joan De Les Abadesses",
    "sg:orig_category":"Alimentaci\u00d3n General (al Por Menor)",
    "sg:phone":"+34 972 72 03 72",
    "sg:postcode":"17860",
    "sg:province":"Girona",
    "wof:name":"Roura Roviras Esteban",
    "wof:placetype":"venue"
},
  "geometry": {"coordinates":[2.2850339413,42.2328987122],"type":"Point"}
}