{
  "type": "Feature",
  "properties": {
    "iso:country":"ES",
    "sg:address":"Calle de Italia, 222",
    "sg:city":"Palencia",
    "sg:orig_category":"Mensajer\u00cda Express, Portes Internacionales",
    "sg:phone":"+34 979 72 03 35",
    "sg:postcode":"34004",
    "sg:province":"Palencia",
    "wof:name":"Quintanilla Mu\u00f1oz Jesus",
    "wof:placetype":"venue"
},
  "geometry": {"coordinates":[-4.5129990578,42.0043296814],"type":"Point"}
}