{
  "type": "Feature",
  "properties": {
    "addr:full":"Avda Tres De Mayo, 3 Santa Cruz De Tenerife Santa Cruz De Tenerife 38...",
    "addr:housenumber":"3;38 ...",
    "addr:street":"Avda Tres De Mayo;Cruz;Tenerife",
    "iso:country":"ES",
    "sg:address":"Avda Tres De Mayo, 3",
    "sg:city":"Santa Cruz De Tenerife",
    "sg:orig_category":"Tribunales, Administraci\u00d3n De Justicia",
    "sg:phone":"+34 922 20 86 00",
    "sg:postcode":"38...",
    "sg:province":"Santa Cruz De Tenerife",
    "wof:name":"Gobierno De Canarias",
    "wof:placetype":"venue"
},
  "geometry": {"coordinates":[-16.2601451874,28.4584751129],"type":"Point"}
}