{
  "type": "Feature",
  "properties": {
    "iso:country":"ES",
    "sg:address":"Rond Santa Maria, 44",
    "sg:city":"Sabadell",
    "sg:orig_category":"Fabricaci\u00d3n, Importaci\u00d3n De L\u00c1mparas Y Bombillas",
    "sg:phone":"+34 937 11 76 77",
    "sg:postcode":"08204",
    "sg:province":"Barcelona",
    "wof:name":"Martin Pujalte Jose Antonio",
    "wof:placetype":"venue"
},
  "geometry": {"coordinates":[2.1232450008,41.5290298462],"type":"Point"}
}