{
  "type": "Feature",
  "properties": {
    "iso:country":"ES",
    "sg:address":"Carrer de Espirall, S/n",
    "sg:city":"Vilafranca Penedes",
    "sg:orig_category":"Carnicer\u00cdas, Carnicer\u00cdas",
    "sg:phone":"+34 938 92 36 05",
    "sg:postcode":"08720",
    "sg:province":"Barcelona",
    "wof:name":"Belles Segura Juan",
    "wof:placetype":"venue"
},
  "geometry": {"coordinates":[1.7055300474,41.3556137085],"type":"Point"}
}