{
  "type": "Feature",
  "properties": {
    "addr:full":"Calle de Informantes, 1 Sahagun Le\u00f3n 24320",
    "addr:housenumber":"1",
    "addr:postcode":"24320",
    "addr:street":"Calle De Informantes;Leo\u0301N",
    "iso:country":"ES",
    "sg:address":"Calle de Informantes, 1",
    "sg:city":"Sahagun",
    "sg:orig_category":"Carnicer\u00cdas, Carnicer\u00cdas",
    "sg:phone":"+34 987 78 03 15",
    "sg:postcode":"24320",
    "sg:province":"Le\u00f3n",
    "wof:name":"Fresno Ba\u00f1os Gonzalo",
    "wof:placetype":"venue"
},
  "geometry": {"coordinates":[-5.0290141106,42.3714103699],"type":"Point"}
}