{
  "type": "Feature",
  "properties": {
    "iso:country":"ES",
    "sg:address":"Avda Arias De Velasco, 8",
    "sg:city":"Marbella",
    "sg:orig_category":"Fabricaci\u00d3n, Comercio De Muebles Para Ni\u00d1os",
    "sg:phone":"+34 952 76 41 63",
    "sg:postcode":"29600",
    "sg:province":"M\u00e1laga",
    "wof:name":"Mil Nubes S.l.",
    "wof:placetype":"venue"
},
  "geometry": {"coordinates":[-4.8851051331,36.5169181824],"type":"Point"}
}