{
  "type": "Feature",
  "properties": {
    "iso:country":"ES",
    "sg:address":"Calle de Francisco De Quevedo, 1",
    "sg:city":"Zaragoza",
    "sg:orig_category":"Electricidad: Equipos Industriales, Componentes (fabricaci\u00d3n)",
    "sg:phone":"+34 976 49 01 00",
    "sg:postcode":"50013",
    "sg:province":"Zaragoza",
    "wof:name":"Zaramatel S.l.",
    "wof:placetype":"venue"
},
  "geometry": {"coordinates":[-0.8670250177,41.6411399841],"type":"Point"}
}