{
  "type": "Feature",
  "properties": {
    "iso:country":"ES",
    "sg:address":"Carr Mendez Nu\u00d1ez, 32",
    "sg:city":"Figueres",
    "sg:orig_category":"Peluqueros: De Se\u00d1oras",
    "sg:phone":"+34 972 67 50 65",
    "sg:postcode":"17600",
    "sg:province":"Girona",
    "wof:name":"Peluqueria Gris Ana Gost Pacheco C.b.",
    "wof:placetype":"venue"
},
  "geometry": {"coordinates":[2.9659149647,42.2642059326],"type":"Point"}
}