{
  "type": "Feature",
  "properties": {
    "iso:country":"ES",
    "sg:address":"Calle de Vicenta Manzanedo, 22",
    "sg:city":"Avila",
    "sg:orig_category":"Carnicer\u00cdas, Carnicer\u00cdas",
    "sg:phone":"+34 920 25 42 71",
    "sg:postcode":"05002",
    "sg:province":"\u00c1vila",
    "wof:name":"Hernandez Jimenez Ruben",
    "wof:placetype":"venue"
},
  "geometry": {"coordinates":[-4.6980700493,40.6487579346],"type":"Point"}
}