{
  "type": "Feature",
  "properties": {
    "iso:country":"ES",
    "sg:address":"Av Flors (les), 7",
    "sg:city":"S. Joan Despi",
    "sg:orig_category":"Institutos De Belleza",
    "sg:phone":"+34 934 77 32 13",
    "sg:postcode":"08970",
    "sg:province":"Barcelona",
    "wof:name":"Diaz Teruel Maribel",
    "wof:placetype":"venue"
},
  "geometry": {"coordinates":[2.0713601112,41.365737915],"type":"Point"}
}