{
  "type": "Feature",
  "properties": {
    "addr:full":"Ctra. Sevilla, Km. 0728,0 Monesterio Badajoz 06260",
    "addr:postcode":"06260",
    "addr:street":"Ctra. Sevilla Km. 0728,0",
    "iso:country":"ES",
    "sg:address":"Ctra. Sevilla, Km. 0728,0",
    "sg:city":"Monesterio",
    "sg:orig_category":"Alquiler De Casas Y Habitaciones Amuebladas",
    "sg:phone":"+34 924 51 66 64",
    "sg:postcode":"06260",
    "sg:province":"Badajoz",
    "wof:name":"Se\u00f1orio De Los Cotos S.l.",
    "wof:placetype":"venue"
},
  "geometry": {"coordinates":[-6.2733559608,38.0909118652],"type":"Point"}
}