{
  "type": "Feature",
  "properties": {
    "iso:country":"ES",
    "sg:address":"Calle de Victoria Rubio (de), 1",
    "sg:city":"Boadilla Del Monte",
    "sg:orig_category":"Urbanistas",
    "sg:phone":"+34 916 32 41 77",
    "sg:postcode":"28660",
    "sg:province":"Madrid",
    "wof:name":"Teclosan S.l.",
    "wof:placetype":"venue"
},
  "geometry": {"coordinates":[-3.8842079639,40.4071731567],"type":"Point"}
}