{
  "type": "Feature",
  "properties": {
    "addr:full":"Calle de Virgen De Monserrate, 2 Alacant Alicante 03009",
    "addr:housenumber":"2",
    "addr:postcode":"03009",
    "addr:street":"Calle De Virgen De Monserrate",
    "iso:country":"ES",
    "sg:address":"Calle de Virgen De Monserrate, 2",
    "sg:city":"Alacant",
    "sg:orig_category":"Inform\u00c1tica: Material Y Suministros",
    "sg:phone":"+34 965 17 24 48",
    "sg:postcode":"03009",
    "sg:province":"Alicante",
    "wof:name":"Mac Iris S.l.",
    "wof:placetype":"venue"
},
  "geometry": {"coordinates":[-0.4972679913,38.3694229126],"type":"Point"}
}