{
  "type": "Feature",
  "properties": {
    "iso:country":"ES",
    "sg:address":"Calle de Alcalde Arche, 3",
    "sg:city":"Muriedas",
    "sg:orig_category":"Imprenta",
    "sg:phone":"+34 942 25 39 44",
    "sg:postcode":"39600",
    "sg:province":"Cantabria",
    "wof:name":"Saiz Lanza Santiago",
    "wof:placetype":"venue"
},
  "geometry": {"coordinates":[-3.8457870483,43.4160041809],"type":"Point"}
}