{
  "type": "Feature",
  "properties": {
    "iso:country":"ES",
    "sg:address":"Plaz Espa\u00d1a (de), 2",
    "sg:city":"Cebreros",
    "sg:orig_category":"Cajas De Ahorro",
    "sg:phone":"+34 918 63 22 85",
    "sg:postcode":"05260",
    "sg:province":"\u00c1vila",
    "wof:name":"Caja De Avila",
    "wof:placetype":"venue"
},
  "geometry": {"coordinates":[-4.4648017883,40.4579963684],"type":"Point"}
}