{
  "type": "Feature",
  "properties": {
    "addr:full":"Pl Urquinaona, 11 Barcelona Barcelona 08010",
    "addr:housenumber":"11",
    "addr:postcode":"08010",
    "addr:street":"Pl Urquinaona",
    "iso:country":"ES",
    "sg:address":"Pl Urquinaona, 11",
    "sg:city":"Barcelona",
    "sg:orig_category":"Sindicatos Y Colegios Profesionales",
    "sg:phone":"+34 933 17 09 60",
    "sg:postcode":"08010",
    "sg:province":"Barcelona",
    "wof:name":"Federacion Espa\u00f1ola De Religiosas Sanitarias",
    "wof:placetype":"venue"
},
  "geometry": {"coordinates":[2.1730821133,41.3885231018],"type":"Point"}
}