{
  "type": "Feature",
  "properties": {
    "iso:country":"ES",
    "sg:address":"Calle de Luis Dorado, 21",
    "sg:city":"Puertollano",
    "sg:classifiers":[
        {
            "category":"Banks & Credit Unions",
            "subcategory":"Bureau De Change",
            "type":"Services"
        }
    ],
    "sg:phone":"+34 926 42 85 15",
    "sg:postcode":"13500",
    "sg:province":"Ciudad Real",
    "sg:tags":[
        "organismos",
        "control"
    ],
    "sg:website":"www.cualiacisa.com",
    "wof:name":"Cualicontrol-aci S.a.",
    "wof:placetype":"venue"
},
  "geometry": {"coordinates":[-4.0963788033,38.6841316223],"type":"Point"}
}