{
  "type": "Feature",
  "properties": {
    "addr:full":"Calle de Montfrague, 2 Madrid Madrid 28030",
    "addr:housenumber":"2",
    "addr:postcode":"28030",
    "addr:street":"Calle De Montfrague",
    "iso:country":"ES",
    "sg:address":"Calle de Montfrague, 2",
    "sg:city":"Madrid",
    "sg:orig_category":"Peluqueros: De Se\u00d1oras",
    "sg:phone":"+34 917 72 42 39",
    "sg:postcode":"28030",
    "sg:province":"Madrid",
    "wof:name":"Santiba\u00f1ez Sanchez Mercedes",
    "wof:placetype":"venue"
},
  "geometry": {"coordinates":[-3.6320240498,40.4061965942],"type":"Point"}
}