{
  "type": "Feature",
  "properties": {
    "iso:country":"ES",
    "sg:address":"Calle de Cincel (del), 18",
    "sg:city":"Fuenlabrada",
    "sg:orig_category":"Publicidad (soportes Y Gesti\u00d3n)",
    "sg:phone":"+34 916 42 33 83",
    "sg:postcode":"28947",
    "sg:province":"Madrid",
    "wof:name":"Parra Cuevas Francisca Concepcion",
    "wof:placetype":"venue"
},
  "geometry": {"coordinates":[-3.7613894939,40.2724723816],"type":"Point"}
}