{
  "type": "Feature",
  "properties": {
    "addr:full":"Calle de Colmena Del Cura (de La), 8 Colmenar Viejo Madrid 28770",
    "addr:housenumber":"8",
    "addr:postcode":"28770",
    "addr:street":"Calle De Colmena Del Cura De La",
    "iso:country":"ES",
    "sg:address":"Calle de Colmena Del Cura (de La), 8",
    "sg:city":"Colmenar Viejo",
    "sg:orig_category":"Telas Para Tapizar, Cortinas, Pasamaner\u00cda (fabricaci\u00d3n, Al Por Mayor)",
    "sg:phone":"+34 918 48 61 08",
    "sg:postcode":"28770",
    "sg:province":"Madrid",
    "wof:name":"Maro\u00f1as Arroyo Angela",
    "wof:placetype":"venue"
},
  "geometry": {"coordinates":[-3.7684705257,40.65807724],"type":"Point"}
}