{
  "type": "Feature",
  "properties": {
    "iso:country":"ES",
    "sg:address":"Calle de Averroes, 5",
    "sg:city":"Adamuz",
    "sg:orig_category":"Electricidad: Instaladores",
    "sg:phone":"+34 957 16 64 28",
    "sg:postcode":"14430",
    "sg:province":"C\u00f3rdoba",
    "wof:name":"Roman Amil Jose Antonio",
    "wof:placetype":"venue"
},
  "geometry": {"coordinates":[-4.5212693214,38.0257072449],"type":"Point"}
}