{
  "type": "Feature",
  "properties": {
    "iso:country":"ES",
    "sg:address":"Calle de Don Jaime I, 5",
    "sg:city":"Zaragoza",
    "sg:orig_category":"Ropa Para Caballeros (al Por Menor)",
    "sg:phone":"+34 976 29 04 87",
    "sg:postcode":"50003",
    "sg:province":"Zaragoza",
    "wof:name":"Cardiff Difusion S.l.",
    "wof:placetype":"venue"
},
  "geometry": {"coordinates":[-0.8797330856,41.6522521973],"type":"Point"}
}