{
  "type": "Feature",
  "properties": {
    "addr:full":"Prai Quenxe, S/n Corcubion La Coru\u00f1a 15130",
    "addr:housenumber":"s",
    "addr:postcode":"15130",
    "addr:street":"/ N Corcubion La Corun\u0303A",
    "iso:country":"ES",
    "sg:address":"Prai Quenxe, S/n",
    "sg:city":"Corcubion",
    "sg:orig_category":"Alquiler De Apartamentos",
    "sg:phone":"+34 981 74 74 50",
    "sg:postcode":"15130",
    "sg:province":"La Coru\u00f1a",
    "wof:name":"Gloria Aran E Hijos S.c.",
    "wof:placetype":"venue"
},
  "geometry": {"coordinates":[-9.1932678223,42.9439277649],"type":"Point"}
}