{
  "type": "Feature",
  "properties": {
    "iso:country":"ES",
    "sg:address":"Calle de Astros, S/n",
    "sg:city":"Valladolid",
    "sg:orig_category":"Cine (distribuci\u00d3n)",
    "sg:phone":"+34 983 36 33 63",
    "sg:postcode":"47009",
    "sg:province":"Valladolid",
    "wof:name":"Divisa Red S.a.",
    "wof:placetype":"venue"
},
  "geometry": {"coordinates":[-4.7269501686,41.6674575806],"type":"Point"}
}