{
  "type": "Feature",
  "properties": {
    "iso:country":"ES",
    "sg:address":"Ctra. Francia, S/n",
    "sg:city":"Mardea",
    "sg:orig_category":"Semiller\u00cdas",
    "sg:phone":"+34 948 45 20 32",
    "sg:postcode":"31794",
    "sg:province":"Navarra",
    "wof:name":"Viveros Zubiria S.l",
    "wof:placetype":"venue"
},
  "geometry": {"coordinates":[-1.5684756041,43.1416015625],"type":"Point"}
}