{
  "type": "Feature",
  "properties": {
    "addr:full":"Calle de Zumarraga Bilbao Vizcaya 48006",
    "addr:postcode":"48006",
    "addr:street":"Calle De",
    "iso:country":"ES",
    "sg:address":"Calle de Zumarraga",
    "sg:city":"Bilbao",
    "sg:orig_category":"Cl\u00cdnicas Psiqui\u00c1tricas",
    "sg:phone":"+34 944 00 77 00",
    "sg:postcode":"48006",
    "sg:province":"Vizcaya",
    "wof:name":"Osakidetza",
    "wof:placetype":"venue"
},
  "geometry": {"coordinates":[-2.9196469784,43.257270813],"type":"Point"}
}