{
  "type": "Feature",
  "properties": {
    "addr:full":"Calle de Arturo Soria, 126 Madrid Madrid 28043",
    "addr:housenumber":"126",
    "addr:postcode":"28043",
    "addr:street":"Calle De Arturo Soria",
    "iso:country":"ES",
    "sg:address":"Calle de Arturo Soria, 126",
    "sg:city":"Madrid",
    "sg:orig_category":"Deportes Y Ocio: Art\u00cdculos Y Ropas (al Por Menor Y Accesorios)",
    "sg:phone":"+34 917 59 52 62",
    "sg:postcode":"28043",
    "sg:province":"Madrid",
    "sg:website":"www.coroneltapiocca.com",
    "wof:name":"Coronel Tapioca S.a.",
    "wof:placetype":"venue"
},
  "geometry": {"coordinates":[-3.6510543823,40.4495353699],"type":"Point"}
}