{
  "type": "Feature",
  "properties": {
    "addr:full":"Calle de Coso, 98 Zaragoza Zaragoza 50001",
    "addr:housenumber":"98",
    "addr:postcode":"50001",
    "addr:street":"Calle De Coso",
    "iso:country":"ES",
    "sg:address":"Calle de Coso, 98",
    "sg:city":"Zaragoza",
    "sg:orig_category":"Promotores Constructores",
    "sg:phone":"+34 976 23 99 55",
    "sg:postcode":"50001",
    "sg:province":"Zaragoza",
    "sg:website":"www.acr.es",
    "wof:name":"Construcciones Acr S.a.",
    "wof:placetype":"venue"
},
  "geometry": {"coordinates":[-0.8772596121,41.651008606],"type":"Point"}
}