{
  "type": "Feature",
  "properties": {
    "addr:full":"Calle de Gloria (la), 3 Guadix Granada 18500",
    "addr:postcode":"18500",
    "addr:street":"Calle De Gloria La 3",
    "iso:country":"ES",
    "sg:address":"Calle de Gloria (la), 3",
    "sg:city":"Guadix",
    "sg:orig_category":"Cajas De Ahorro",
    "sg:phone":"+34 958 66 61 11",
    "sg:postcode":"18500",
    "sg:province":"Granada",
    "sg:website":"www.cajagranada.es",
    "wof:name":"Cajagranada",
    "wof:placetype":"venue"
},
  "geometry": {"coordinates":[-3.135668993,37.2978286743],"type":"Point"}
}