{
  "type": "Feature",
  "properties": {
    "iso:country":"ES",
    "sg:address":"C/ 16, 35",
    "sg:city":"Ca\u00d1ada",
    "sg:orig_category":"Semiller\u00cdas",
    "sg:phone":"+34 961 32 02 94",
    "sg:postcode":"46182",
    "sg:province":"Valencia",
    "wof:name":"Floristeria Jardineria Gumbau S.l.",
    "wof:placetype":"venue"
},
  "geometry": {"coordinates":[-0.4852339923,39.5221443176],"type":"Point"}
}