{
  "type": "Feature",
  "properties": {
    "iso:country":"ES",
    "sg:address":"Calle de Autonomia, 11",
    "sg:city":"Bilbao",
    "sg:orig_category":"Pescader\u00cdas (al Por Menor)",
    "sg:phone":"+34 944 21 13 33",
    "sg:postcode":"48012",
    "sg:province":"Vizcaya",
    "wof:name":"Bri S. A.",
    "wof:placetype":"venue"
},
  "geometry": {"coordinates":[-2.9371893406,43.2573356628],"type":"Point"}
}