{
  "type": "Feature",
  "properties": {
    "iso:country":"ES",
    "sg:address":"Av Camp Verd, Des, 41",
    "sg:city":"Alaior",
    "sg:orig_category":"Fabricaci\u00d3n De Quesos",
    "sg:phone":"+34 971 37 27 39",
    "sg:postcode":"07730",
    "sg:province":"Islas Baleares",
    "wof:name":"Explotaciones Pons Marin S.a.",
    "wof:placetype":"venue"
},
  "geometry": {"coordinates":[4.1505498886,39.9333000183],"type":"Point"}
}