{
  "type": "Feature",
  "properties": {
    "iso:country":"ES",
    "sg:address":"Calle de Juncal, 2",
    "sg:city":"Torrejon Ardoz",
    "sg:orig_category":"Asesor\u00cda Sobre Comunicaci\u00d3n De Empresas",
    "sg:phone":"+34 916 56 17 36",
    "sg:postcode":"28850",
    "sg:province":"Madrid",
    "wof:name":"Acb Asesores S.l.",
    "wof:placetype":"venue"
},
  "geometry": {"coordinates":[-3.4588780403,40.4605636597],"type":"Point"}
}