{
  "type": "Feature",
  "properties": {
    "addr:full":"Av Albir (l'), 159 Albir Alicante 03580",
    "addr:housenumber":"159",
    "addr:postcode":"03580",
    "addr:street":"Av Albir L '",
    "iso:country":"ES",
    "sg:address":"Av Albir (l'), 159",
    "sg:city":"Albir",
    "sg:orig_category":"Cajas De Ahorro",
    "sg:phone":"+34 966 86 60 44",
    "sg:postcode":"03580",
    "sg:province":"Alicante",
    "sg:website":"www.cajamurcia.es",
    "wof:name":"Caja De Ahorros De Murcia",
    "wof:placetype":"venue"
},
  "geometry": {"coordinates":[-0.1033039987,38.5793037415],"type":"Point"}
}