{
  "type": "Feature",
  "properties": {
    "iso:country":"ES",
    "sg:address":"Carrer de Pare Francisco Agullo, 9",
    "sg:city":"Cocentaina",
    "sg:orig_category":"Peluquer\u00cdas, Peluquer\u00cda Mixta",
    "sg:phone":"+34 965 59 09 44",
    "sg:postcode":"03820",
    "sg:province":"Alicante",
    "wof:name":"Mengual Y Egea S.l.",
    "wof:placetype":"venue"
},
  "geometry": {"coordinates":[-0.4409419894,38.7378692627],"type":"Point"}
}