{
  "type": "Feature",
  "properties": {
    "iso:country":"ES",
    "sg:address":"Calle de Ramon Cabanillas, 15",
    "sg:city":"Coru\u00d1a",
    "sg:orig_category":"Chapister\u00cda",
    "sg:phone":"+34 981 15 17 94",
    "sg:postcode":"15007",
    "sg:province":"La Coru\u00f1a",
    "wof:name":"Barral Freire Maria",
    "wof:placetype":"venue"
},
  "geometry": {"coordinates":[-8.4108829498,43.356048584],"type":"Point"}
}