{
  "type": "Feature",
  "properties": {
    "addr:full":"Calle de Infanta Mercedes, 31 Madrid Madrid 28020",
    "addr:housenumber":"31",
    "addr:postcode":"madrid;28020",
    "addr:street":"Calle De Infanta Mercedes",
    "iso:country":"ES",
    "sg:address":"Calle de Infanta Mercedes, 31",
    "sg:city":"Madrid",
    "sg:orig_category":"Inform\u00c1tica (estudios, Servicios, Asesor\u00cda, Formaci\u00d3n)",
    "sg:phone":"+34 915 70 67 81",
    "sg:postcode":"28020",
    "sg:province":"Madrid",
    "wof:name":"Informatica E Inmobiliaria S. A.",
    "wof:placetype":"venue"
},
  "geometry": {"coordinates":[-3.6989729404,40.4548225403],"type":"Point"}
}