{
  "type": "Feature",
  "properties": {
    "iso:country":"ES",
    "sg:address":"Maite (p I S. Rafael), S/n",
    "sg:city":"Huercal Almeria",
    "sg:orig_category":"Empresas De Carpinter\u00cda De Madera",
    "sg:phone":"+34 950 14 42 85",
    "sg:postcode":"04230",
    "sg:province":"Almer\u00eda",
    "wof:name":"Guirado Cruz Diego",
    "wof:placetype":"venue"
},
  "geometry": {"coordinates":[-2.4370388985,36.8798294067],"type":"Point"}
}