{
  "type": "Feature",
  "properties": {
    "iso:country":"ES",
    "sg:address":"Carr Musico Juan Campos, S/n",
    "sg:city":"Alcudia",
    "sg:orig_category":"Ebanister\u00cda",
    "sg:phone":"+34 962 54 13 34",
    "sg:postcode":"46250",
    "sg:province":"Valencia",
    "wof:name":"Orbogaix S. L.",
    "wof:placetype":"venue"
},
  "geometry": {"coordinates":[-0.5033490062,39.1972999573],"type":"Point"}
}