{
  "type": "Feature",
  "properties": {
    "addr:full":"Rbla Pinetons (dels), 1 Ripollet Barcelona 08291",
    "addr:housenumber":"1",
    "addr:postcode":"08291",
    "addr:street":"Rbla Pinetons Dels",
    "iso:country":"ES",
    "sg:address":"Rbla Pinetons (dels), 1",
    "sg:city":"Ripollet",
    "sg:orig_category":"Ense\u00d1anza, Formaci\u00d3n Profesional: Aprendizaje",
    "sg:phone":"+34 935 80 04 18",
    "sg:postcode":"08291",
    "sg:province":"Barcelona",
    "wof:name":"Centre De Telecomunicaciones De Catalunya",
    "wof:placetype":"venue"
},
  "geometry": {"coordinates":[2.157558918,41.5011177063],"type":"Point"}
}