{
  "type": "Feature",
  "properties": {
    "addr:full":"Calle de Dindurra, 20 Gijon Asturias 33202",
    "addr:housenumber":"20",
    "addr:postcode":"33202",
    "addr:street":"Calle De Dindurra",
    "iso:country":"ES",
    "sg:address":"Calle de Dindurra, 20",
    "sg:city":"Gijon",
    "sg:orig_category":"Librer\u00cdas",
    "sg:phone":"+34 985 36 65 54",
    "sg:postcode":"33202",
    "sg:province":"Asturias",
    "wof:name":"Emilia Valle Sanchez",
    "wof:placetype":"venue"
},
  "geometry": {"coordinates":[-5.657845974,43.5384101868],"type":"Point"}
}