{
  "type": "Feature",
  "properties": {
    "addr:full":"Salbe Auzunea, 16 Azpeitia Guip\u00f9zcoa 20730",
    "addr:housenumber":"16",
    "addr:postcode":"20730",
    "addr:street":"Salbe Auzunea;Guipu\u0300Zcoa",
    "iso:country":"ES",
    "sg:address":"Salbe Auzunea, 16",
    "sg:city":"Azpeitia",
    "sg:orig_category":"Loter\u00cda Y T\u00d3mbola",
    "sg:phone":"+34 943 08 00 34",
    "sg:postcode":"20730",
    "sg:province":"Guip\u00f9zcoa",
    "wof:name":"Olatz Eizagirre Isasti",
    "wof:placetype":"venue"
},
  "geometry": {"coordinates":[-2.2711000443,43.1781349182],"type":"Point"}
}