{
  "type": "Feature",
  "properties": {
    "addr:full":"Goizueta, 5 Iru\u00f1a Navarra 31015",
    "addr:housenumber":"5",
    "addr:postcode":"31015",
    "addr:street":"Goizueta",
    "iso:country":"ES",
    "sg:address":"Goizueta, 5",
    "sg:city":"Iru\u00f1a",
    "sg:orig_category":"Mercer\u00cda, Lencer\u00cda (al Por Menor)",
    "sg:phone":"+34 948 38 45 44",
    "sg:postcode":"31015",
    "sg:province":"Navarra",
    "wof:name":"Gutierrez Gomez Maria Angeles",
    "wof:placetype":"venue"
},
  "geometry": {"coordinates":[-1.6328678131,42.8250045776],"type":"Point"}
}