{
  "type": "Feature",
  "properties": {
    "addr:full":"Calle de Tres De Abril, 35 Carrion De Los Cespedes Sevilla 41820",
    "addr:housenumber":"35",
    "addr:postcode":"41820",
    "addr:street":"Calle De Tres De Abril",
    "iso:country":"ES",
    "sg:address":"Calle de Tres De Abril, 35",
    "sg:city":"Carrion De Los Cespedes",
    "sg:orig_category":"Aguas (distribuci\u00d3n, Servicios)",
    "sg:phone":"+34 954 75 50 98",
    "sg:postcode":"41820",
    "sg:province":"Sevilla",
    "wof:name":"Aznalhogar S.l",
    "wof:placetype":"venue"
},
  "geometry": {"coordinates":[-6.3302521706,37.3697738647],"type":"Point"}
}