{
  "type": "Feature",
  "properties": {
    "iso:country":"ES",
    "sg:address":"Carr Josep Pla, 4",
    "sg:city":"Sarria Ter",
    "sg:orig_category":"Empresas De Carpinter\u00cda De Madera",
    "sg:phone":"+34 972 17 11 89",
    "sg:postcode":"17840",
    "sg:province":"Girona",
    "wof:name":"Anglada Xabadia Josep",
    "wof:placetype":"venue"
},
  "geometry": {"coordinates":[2.8219022751,41.9833869934],"type":"Point"}
}