{
  "type": "Feature",
  "properties": {
    "addr:full":"Campo De La Iglesia, S/n Trabada Lugo 27765",
    "addr:housenumber":"s / n",
    "addr:postcode":"27765",
    "iso:country":"ES",
    "sg:address":"Campo De La Iglesia, S/n",
    "sg:city":"Trabada",
    "sg:orig_category":"Iglesia Cat\u00d3lica",
    "sg:phone":"+34 982 13 50 29",
    "sg:postcode":"27765",
    "sg:province":"Lugo",
    "wof:name":"Parroquia De Santa Maria",
    "wof:placetype":"venue"
},
  "geometry": {"coordinates":[-7.1936340332,43.4471321106],"type":"Point"}
}