{
  "type": "Feature",
  "properties": {
    "addr:full":"Carr Renocar, 1 Puig Valencia 46540",
    "addr:housenumber":"1",
    "addr:postcode":"46540",
    "addr:street":"Carr Renocar",
    "iso:country":"ES",
    "sg:address":"Carr Renocar, 1",
    "sg:city":"Puig",
    "sg:orig_category":"Telefon\u00cda: Instaladores Varios",
    "sg:phone":"+34 961 47 14 00",
    "sg:postcode":"46540",
    "sg:province":"Valencia",
    "wof:name":"Mavel Comunicaciones S.l.",
    "wof:placetype":"venue"
},
  "geometry": {"coordinates":[-0.3003390133,39.5875854492],"type":"Point"}
}