{
  "type": "Feature",
  "properties": {
    "iso:country":"ES",
    "sg:address":"Avda Andalucia (de), 14",
    "sg:city":"Alcala Real",
    "sg:orig_category":"Trajes Y Adornos De Boda (confecci\u00d3n, Al Por Menor)",
    "sg:phone":"+34 953 58 70 33",
    "sg:postcode":"23680",
    "sg:province":"Ja\u00e9n",
    "wof:name":"Arjona Funes Manuel",
    "wof:placetype":"venue"
},
  "geometry": {"coordinates":[-3.9225542545,37.4596290588],"type":"Point"}
}