{
  "type": "Feature",
  "properties": {
    "iso:country":"ES",
    "sg:address":"Avda Aragon De, 145",
    "sg:city":"Fraga",
    "sg:orig_category":"Mec\u00c1nico Del Autom\u00d3vil",
    "sg:phone":"+34 974 47 06 74",
    "sg:postcode":"22520",
    "sg:province":"Huesca",
    "wof:name":"Funeraria Ventura S.l.",
    "wof:placetype":"venue"
},
  "geometry": {"coordinates":[0.3438299894,41.5223045349],"type":"Point"}
}