{
  "type": "Feature",
  "properties": {
    "addr:full":"Calle de Arritokieta, 14 Zumaia Guip\u00f9zcoa 20750",
    "addr:housenumber":"14",
    "addr:postcode":"20750",
    "addr:street":"Calle De Arritokieta;Guipu\u0300Zcoa",
    "iso:country":"ES",
    "sg:address":"Calle de Arritokieta, 14",
    "sg:city":"Zumaia",
    "sg:orig_category":"Electricidad: Instaladores",
    "sg:phone":"+34 943 86 16 32",
    "sg:postcode":"20750",
    "sg:province":"Guip\u00f9zcoa",
    "wof:name":"Arranz Sanz Jose",
    "wof:placetype":"venue"
},
  "geometry": {"coordinates":[-2.2593948841,43.2966499329],"type":"Point"}
}