{
  "type": "Feature",
  "properties": {
    "iso:country":"ES",
    "sg:address":"Ctra. Nal. 340, S/n",
    "sg:city":"Alberic",
    "sg:orig_category":"Mec\u00c1nico Del Autom\u00d3vil",
    "sg:phone":"+34 962 44 12 56",
    "sg:postcode":"46260",
    "sg:province":"Valencia",
    "wof:name":"Piqueres Cuco Genaro",
    "wof:placetype":"venue"
},
  "geometry": {"coordinates":[-0.520138979,39.11901474],"type":"Point"}
}