{
  "type": "Feature",
  "properties": {
    "addr:full":"Ctra. De Madrid, Km. 0208,2 Roda Albacete 02630",
    "addr:postcode":"02630",
    "addr:street":"Ctra. De Madrid Km. 0208,2 Roda",
    "iso:country":"ES",
    "sg:address":"Ctra. De Madrid, Km. 0208,2",
    "sg:city":"Roda",
    "sg:orig_category":"Distribuci\u00d3n De Petr\u00d3leo Y Derivados",
    "sg:phone":"+34 967 57 00 15",
    "sg:postcode":"02630",
    "sg:province":"Albacete",
    "wof:name":"Castilla Energia S.l.",
    "wof:placetype":"venue"
},
  "geometry": {"coordinates":[-2.1636590958,39.1957206726],"type":"Point"}
}