{
  "type": "Feature",
  "properties": {
    "addr:full":"C/ Moli (del), 6 Ripollet Barcelona 08291",
    "addr:housenumber":"6",
    "addr:postcode":"08291",
    "addr:street":"C / Moli Del",
    "iso:country":"ES",
    "sg:address":"C/ Moli (del), 6",
    "sg:city":"Ripollet",
    "sg:orig_category":"Chapister\u00cda",
    "sg:phone":"+34 935 80 37 11",
    "sg:postcode":"08291",
    "sg:province":"Barcelona",
    "wof:name":"Doctor Auto S.c.p.",
    "wof:placetype":"venue"
},
  "geometry": {"coordinates":[2.1596589088,41.4935569763],"type":"Point"}
}