{
  "type": "Feature",
  "properties": {
    "addr:full":"Avgd Puerto, S/n Cullera Valencia 46400",
    "addr:postcode":"46400",
    "addr:street":"Puerto S / N",
    "iso:country":"ES",
    "sg:address":"Avgd Puerto, S/n",
    "sg:city":"Cullera",
    "sg:orig_category":"Deportes N\u00c1uticos, Acu\u00c1ticos Y Subacu\u00c1ticos: Art\u00cdculos Y Equipo (al Por Menor)",
    "sg:phone":"+34 961 72 11 54",
    "sg:postcode":"46400",
    "sg:province":"Valencia",
    "wof:name":"Club Nautico De Cullera",
    "wof:placetype":"venue"
},
  "geometry": {"coordinates":[-0.2562240064,39.1653251648],"type":"Point"}
}