{
  "type": "Feature",
  "properties": {
    "addr:full":"Calle de Granada, 8 Alcala Henares Madrid 28802",
    "addr:housenumber":"8",
    "addr:postcode":"28802",
    "addr:street":"Calle De Granada",
    "iso:country":"ES",
    "sg:address":"Calle de Granada, 8",
    "sg:city":"Alcala Henares",
    "sg:orig_category":"Plomeros",
    "sg:phone":"+34 918 82 07 74",
    "sg:postcode":"28802",
    "sg:province":"Madrid",
    "wof:name":"Ca\u00f1ete Pastor Jose Luis",
    "wof:placetype":"venue"
},
  "geometry": {"coordinates":[-3.375180006,40.4771156311],"type":"Point"}
}