{
  "type": "Feature",
  "properties": {
    "iso:country":"ES",
    "sg:address":"Calle de Alberca, 10",
    "sg:city":"Soria",
    "sg:orig_category":"Administradores De Bienes Y Delegados De Comunidades De Propietarios",
    "sg:phone":"+34 975 22 98 15",
    "sg:postcode":"42003",
    "sg:province":"Soria",
    "wof:name":"Llorente Calvo Jesus",
    "wof:placetype":"venue"
},
  "geometry": {"coordinates":[-2.4678385258,41.7627868652],"type":"Point"}
}