{
  "type": "Feature",
  "properties": {
    "iso:country":"ES",
    "sg:address":"Calle de Tarifa, 6",
    "sg:city":"Cehegin",
    "sg:orig_category":"Alquiler De Gr\u00daas",
    "sg:phone":"+34 968 74 10 65",
    "sg:postcode":"30430",
    "sg:province":"Murcia",
    "wof:name":"Corbalan Gea Gines",
    "wof:placetype":"venue"
},
  "geometry": {"coordinates":[-1.7999429703,38.0895271301],"type":"Point"}
}