{
  "type": "Feature",
  "properties": {
    "addr:full":"Calle de Portal De Foronda, 28 Vitoria-gasteiz \u00c1lava 01010",
    "addr:housenumber":"28",
    "addr:postcode":"01010",
    "addr:street":"Calle De Portal De Foronda",
    "iso:country":"ES",
    "sg:address":"Calle de Portal De Foronda, 28",
    "sg:city":"Vitoria-gasteiz",
    "sg:orig_category":"Agentes Generales De Seguros",
    "sg:phone":"+34 945 17 18 81",
    "sg:postcode":"01010",
    "sg:province":"\u00c1lava",
    "wof:name":"Guisasola Arrizabalaga Jose Maria",
    "wof:placetype":"venue"
},
  "geometry": {"coordinates":[-2.6857790947,42.8656997681],"type":"Point"}
}