{
  "type": "Feature",
  "properties": {
    "addr:full":"Calle de Escuelas, 17 Puebla Vicar Almer\u00eda 04738",
    "addr:housenumber":"17",
    "addr:postcode":"04738",
    "addr:street":"Calle De Escuelas",
    "iso:country":"ES",
    "sg:address":"Calle de Escuelas, 17",
    "sg:city":"Puebla Vicar",
    "sg:orig_category":"Ense\u00d1anza: Idiomas",
    "sg:phone":"+34 950 55 45 08",
    "sg:postcode":"04738",
    "sg:province":"Almer\u00eda",
    "wof:name":"Agricola Agaton S.l.",
    "wof:placetype":"venue"
},
  "geometry": {"coordinates":[-2.647103548,36.7989807129],"type":"Point"}
}