{
  "type": "Feature",
  "properties": {
    "iso:country":"ES",
    "sg:address":"Calle de Capitan Blanco Argibay, 16",
    "sg:city":"Madrid",
    "sg:orig_category":"Empresarios Y Productoras De Espect\u00c1culos",
    "sg:phone":"+34 915 79 30 52",
    "sg:postcode":"28029",
    "sg:province":"Madrid",
    "wof:name":"Mambo Decorados S.l.",
    "wof:placetype":"venue"
},
  "geometry": {"coordinates":[-3.6970660686,40.4650802612],"type":"Point"}
}