{
  "type": "Feature",
  "properties": {
    "addr:full":"Carrer de Bisbe Serra, S/n Olot Girona 17800",
    "addr:housenumber":"s",
    "addr:postcode":"17800",
    "addr:street":"Carrer De Bisbe Serra;/ N",
    "iso:country":"ES",
    "sg:address":"Carrer de Bisbe Serra, S/n",
    "sg:city":"Olot",
    "sg:orig_category":"Hilaturas, Hilos Y Actividades Relacionadas",
    "sg:phone":"+34 972 27 45 42",
    "sg:postcode":"17800",
    "sg:province":"Girona",
    "wof:name":"Jose Valeri Homs S. A.",
    "wof:placetype":"venue"
},
  "geometry": {"coordinates":[2.4842948914,42.1846656799],"type":"Point"}
}