{
  "type": "Feature",
  "properties": {
    "iso:country":"ES",
    "sg:address":"Carrer de Doctor Pi I Sunyer, 3",
    "sg:city":"Roses",
    "sg:orig_category":"Electrodom\u00c9sticos (al Por Menor)",
    "sg:phone":"+34 972 25 64 98",
    "sg:postcode":"17480",
    "sg:province":"Girona",
    "wof:name":"Font Molas Ramon",
    "wof:placetype":"venue"
},
  "geometry": {"coordinates":[3.1751830578,42.262676239],"type":"Point"}
}