{
  "type": "Feature",
  "properties": {
    "addr:full":"Carrer de Montseny (de), 3 Tortosa Tarragona 43500",
    "addr:postcode":"43500",
    "addr:street":"Carrer De Montseny De",
    "iso:country":"ES",
    "sg:address":"Carrer de Montseny (de), 3",
    "sg:city":"Tortosa",
    "sg:orig_category":"Edici\u00d3n De Diarios, Revistas, Boletines",
    "sg:phone":"+34 977 44 41 68",
    "sg:postcode":"43500",
    "sg:province":"Tarragona",
    "wof:name":"Marti Monllau Monica",
    "wof:placetype":"venue"
},
  "geometry": {"coordinates":[0.5209109783,40.8127632141],"type":"Point"}
}