{
  "type": "Feature",
  "properties": {
    "addr:full":"Plaz Espa\u00d1a, 6 Gineta Albacete 02110",
    "addr:housenumber":"6",
    "addr:postcode":"02110",
    "addr:street":"Plaz Espan\u0303A",
    "iso:country":"ES",
    "sg:address":"Plaz Espa\u00d1a, 6",
    "sg:city":"Gineta",
    "sg:orig_category":"Electricidad: Instaladores",
    "sg:phone":"+34 967 27 50 23",
    "sg:postcode":"02110",
    "sg:province":"Albacete",
    "wof:name":"Garcia Alarcon Francisco",
    "wof:placetype":"venue"
},
  "geometry": {"coordinates":[-1.994568944,39.1158218384],"type":"Point"}
}