{
  "type": "Feature",
  "properties": {
    "iso:country":"ES",
    "sg:address":"Calle de Sagunto, 13",
    "sg:city":"Almeria",
    "sg:orig_category":"Centros Empresariales",
    "sg:phone":"+34 950 26 69 94",
    "sg:postcode":"04004",
    "sg:province":"Almer\u00eda",
    "wof:name":"Spielmann  Peter",
    "wof:placetype":"venue"
},
  "geometry": {"coordinates":[-2.4595899582,36.8341064453],"type":"Point"}
}