{
  "type": "Feature",
  "properties": {
    "iso:country":"ES",
    "sg:address":"Calle de Real, 3",
    "sg:city":"Yuncos",
    "sg:orig_category":"Publicidad (soportes Y Gesti\u00d3n)",
    "sg:phone":"+34 925 53 77 53",
    "sg:postcode":"45210",
    "sg:province":"Toledo",
    "wof:name":"Estepa Gomez Jesus",
    "wof:placetype":"venue"
},
  "geometry": {"coordinates":[-3.8756990433,40.0842018127],"type":"Point"}
}