{
  "type": "Feature",
  "properties": {
    "addr:full":"Plaz Nuestra Se\u00d1ora De La Encarnacion, S/n Gerena Sevilla 41860",
    "addr:postcode":"41860",
    "addr:street":"S / N",
    "iso:country":"ES",
    "sg:address":"Plaz Nuestra Se\u00d1ora De La Encarnacion, S/n",
    "sg:city":"Gerena",
    "sg:orig_category":"Comerciantes Al Por Mayor De Vinos, Licores Y Alcoholes",
    "sg:phone":"+34 955 78 20 28",
    "sg:postcode":"41860",
    "sg:province":"Sevilla",
    "wof:name":"Martin Betanzo Juan",
    "wof:placetype":"venue"
},
  "geometry": {"coordinates":[-6.1566791534,37.5268554688],"type":"Point"}
}