{
  "type": "Feature",
  "properties": {
    "addr:full":"Carrer de Maria Aguilo, 95 Barcelona Barcelona 08005",
    "addr:housenumber":"95",
    "addr:postcode":"08005",
    "addr:street":"Carrer De Maria Aguilo",
    "iso:country":"ES",
    "sg:address":"Carrer de Maria Aguilo, 95",
    "sg:city":"Barcelona",
    "sg:orig_category":"Alimentaci\u00d3n General (al Por Menor)",
    "sg:phone":"+34 933 09 18 33",
    "sg:postcode":"08005",
    "sg:province":"Barcelona",
    "wof:name":"Lombarte Palau Jose Luis",
    "wof:placetype":"venue"
},
  "geometry": {"coordinates":[2.2036480904,41.4011650085],"type":"Point"}
}