{
  "type": "Feature",
  "properties": {
    "iso:country":"ES",
    "sg:address":"Carr Valencia, 1",
    "sg:city":"Camprodon",
    "sg:orig_category":"Panader\u00cdas, Panader\u00cdas",
    "sg:phone":"+34 972 74 01 22",
    "sg:postcode":"17867",
    "sg:province":"Girona",
    "wof:name":"Pujol Martinez Jose",
    "wof:placetype":"venue"
},
  "geometry": {"coordinates":[2.3654220104,42.3135643005],"type":"Point"}
}