{
  "type": "Feature",
  "properties": {
    "iso:country":"ES",
    "sg:address":"Calle de Polo Y Ca\u00d1a, 2",
    "sg:city":"Granada",
    "sg:orig_category":"Mec\u00c1nico Del Autom\u00d3vil",
    "sg:phone":"+34 958 15 47 04",
    "sg:postcode":"18014",
    "sg:province":"Granada",
    "wof:name":"Figueredo Perez Rafael",
    "wof:placetype":"venue"
},
  "geometry": {"coordinates":[-3.6107668877,37.1951255798],"type":"Point"}
}