{
  "type": "Feature",
  "properties": {
    "addr:full":"Calle de Andalucia, 4 Barakaldo Vizcaya 48902",
    "addr:housenumber":"4",
    "addr:postcode":"48902",
    "addr:street":"Calle De Andalucia",
    "iso:country":"ES",
    "sg:address":"Calle de Andalucia, 4",
    "sg:city":"Barakaldo",
    "sg:orig_category":"Caf\u00c9s, Bares, Cervecer\u00cdas",
    "sg:phone":"+34 944 82 05 53",
    "sg:postcode":"48902",
    "sg:province":"Vizcaya",
    "wof:name":"Degustacion Itxaropena",
    "wof:placetype":"venue"
},
  "geometry": {"coordinates":[-2.9948682785,43.2912940979],"type":"Point"}
}