{
  "type": "Feature",
  "properties": {
    "addr:full":"Calle de Almagro, 15 Madrid Madrid 28010",
    "addr:housenumber":"15",
    "addr:postcode":"madrid;28010",
    "addr:street":"Calle De Almagro",
    "iso:country":"ES",
    "sg:address":"Calle de Almagro, 15",
    "sg:city":"Madrid",
    "sg:orig_category":"Centros M\u00c9dicos Y Sociales, Dispensarios",
    "sg:phone":"+34 913 45 11 04",
    "sg:postcode":"28010",
    "sg:province":"Madrid",
    "wof:name":"Moreno Lete Fernando",
    "wof:placetype":"venue"
},
  "geometry": {"coordinates":[-3.6927034855,40.4305267334],"type":"Point"}
}