{
  "type": "Feature",
  "properties": {
    "addr:full":"Calle de Rigel, 28 Alacant Alicante 03007",
    "addr:housenumber":"28",
    "addr:postcode":"03007",
    "addr:street":"Calle De Rigel",
    "iso:country":"ES",
    "sg:address":"Calle de Rigel, 28",
    "sg:city":"Alacant",
    "sg:classifiers":[
        {
            "category":"Personal",
            "subcategory":"Barber",
            "type":"Services"
        }
    ],
    "sg:phone":"+34 965 28 08 38",
    "sg:postcode":"03007",
    "sg:province":"Alicante",
    "sg:tags":[
        "caballeros",
        "de",
        "peluqueros"
    ],
    "wof:name":"Camara Anaya Joaquin",
    "wof:placetype":"venue"
},
  "geometry": {"coordinates":[-0.5115619898,38.3431968689],"type":"Point"}
}