{
  "type": "Feature",
  "properties": {
    "addr:full":"Acce Poligono, S/n Medina Campo Valladolid 47400",
    "addr:postcode":"47400",
    "addr:street":"Poligono S / N Medina",
    "iso:country":"ES",
    "sg:address":"Acce Poligono, S/n",
    "sg:city":"Medina Campo",
    "sg:orig_category":"Maquinaria Para Industrias Diversas",
    "sg:phone":"+34 983 80 30 50",
    "sg:postcode":"47400",
    "sg:province":"Valladolid",
    "wof:name":"Fruver Gonzalez S.l.",
    "wof:placetype":"venue"
},
  "geometry": {"coordinates":[-4.913184166,41.3120155334],"type":"Point"}
}