{
  "type": "Feature",
  "properties": {
    "addr:full":"Carrer de Fra Luis De Leon, 135 Sabadell Barcelona 08203",
    "addr:postcode":"08203",
    "addr:street":"Carrer De Fra Luis De Leon 135",
    "iso:country":"ES",
    "sg:address":"Carrer de Fra Luis De Leon, 135",
    "sg:city":"Sabadell",
    "sg:orig_category":"Reposter\u00cdas",
    "sg:phone":"+34 937 11 62 61",
    "sg:postcode":"08203",
    "sg:province":"Barcelona",
    "wof:name":"Joval Poderoso Francisca",
    "wof:placetype":"venue"
},
  "geometry": {"coordinates":[2.1156980991,41.5356407166],"type":"Point"}
}