{
  "type": "Feature",
  "properties": {
    "addr:full":"Urb Nuevo Alamin, S/n Guadalajara Guadalajara 19005",
    "addr:housenumber":"s",
    "addr:postcode":"19005",
    "addr:street":"Urb;Alamin;/ N",
    "iso:country":"ES",
    "sg:address":"Urb Nuevo Alamin, S/n",
    "sg:city":"Guadalajara",
    "sg:orig_category":"Alimentaci\u00d3n General (al Por Menor)",
    "sg:phone":"+34 949 21 89 75",
    "sg:postcode":"19005",
    "sg:province":"Guadalajara",
    "wof:name":"Casta\u00f1o Cotan Jose Manuel",
    "wof:placetype":"venue"
},
  "geometry": {"coordinates":[-3.159555912,40.6370239258],"type":"Point"}
}