{
  "type": "Feature",
  "properties": {
    "iso:country":"ES",
    "sg:address":"Pase Francia De, 10",
    "sg:city":"Donostia-san Sebastian",
    "sg:classifiers":[
        {
            "category":"Professional",
            "subcategory":"Management & Consulting",
            "type":"Services"
        }
    ],
    "sg:phone":"+34 943 27 02 54",
    "sg:postcode":"20012",
    "sg:province":"Guip\u00f9zcoa",
    "sg:tags":[
        "asesor\u00cda",
        "en",
        "marketing"
    ],
    "wof:name":"Rodriguez Gil Jose Manuel",
    "wof:placetype":"venue"
},
  "geometry": {"coordinates":[-1.9771620035,43.3183174133],"type":"Point"}
}