{
  "type": "Feature",
  "properties": {
    "addr:full":"Rond San Esteban, 1 Tudela Duero Valladolid 47320",
    "addr:housenumber":"1;duero",
    "addr:postcode":"47320",
    "addr:street":"San Esteban",
    "iso:country":"ES",
    "sg:address":"Rond San Esteban, 1",
    "sg:city":"Tudela Duero",
    "sg:orig_category":"Empresarios",
    "sg:phone":"+34 983 52 11 22",
    "sg:postcode":"47320",
    "sg:province":"Valladolid",
    "wof:name":"Construcciones Carmelo Carretero S.l.",
    "wof:placetype":"venue"
},
  "geometry": {"coordinates":[-4.5823941231,41.5873565674],"type":"Point"}
}