{
  "type": "Feature",
  "properties": {
    "iso:country":"ES",
    "sg:address":"Calle de Hermanos Moroy, 8",
    "sg:city":"Logro\u00f1o",
    "sg:orig_category":"\u00d3pticos Optometristas (al Por Menor)",
    "sg:phone":"+34 941 25 19 98",
    "sg:postcode":"26001",
    "sg:province":"La Rioja",
    "wof:name":"Dominguez Sancha Pilar",
    "wof:placetype":"venue"
},
  "geometry": {"coordinates":[-2.4462080002,42.4659957886],"type":"Point"}
}