{
  "type": "Feature",
  "properties": {
    "iso:country":"ES",
    "sg:address":"Calle de Don Ramon De La Cruz, 25",
    "sg:city":"Madrid",
    "sg:classifiers":[
        {
            "category":"Arts & Performance",
            "subcategory":"Art Gallery",
            "type":"Entertainment"
        }
    ],
    "sg:phone":"+34 915 77 61 58",
    "sg:postcode":"28001",
    "sg:province":"Madrid",
    "sg:tags":[
        "arte",
        "de",
        "galer\u00cdas"
    ],
    "wof:name":"Galeria De Arte Altea S.l.",
    "wof:placetype":"venue"
},
  "geometry": {"coordinates":[-3.6829628944,40.4290924072],"type":"Point"}
}