{
  "type": "Feature",
  "properties": {
    "iso:country":"ES",
    "sg:address":"Calle de Mayor, 2",
    "sg:city":"Villadiego",
    "sg:orig_category":"Estancos",
    "sg:phone":"+34 947 36 00 59",
    "sg:postcode":"09120",
    "sg:province":"Burgos",
    "wof:name":"Sierra Nuez Francisco Antonio",
    "wof:placetype":"venue"
},
  "geometry": {"coordinates":[-4.0102891922,42.5155715942],"type":"Point"}
}