{
  "type": "Feature",
  "properties": {
    "iso:country":"ES",
    "sg:address":"Calle de Sorondongo, 33",
    "sg:city":"Marmolejos",
    "sg:orig_category":"Art\u00cdculos Funerarios (al Por Menor)",
    "sg:phone":"+34 928 89 50 52",
    "sg:postcode":"35460",
    "sg:province":"Las Palmas",
    "wof:name":"Funeraria La Auxiliadora S.c.l.",
    "wof:placetype":"venue"
},
  "geometry": {"coordinates":[-15.6528720856,28.1450138092],"type":"Point"}
}