{
  "type": "Feature",
  "properties": {
    "iso:country":"ES",
    "sg:address":"Carrer de Cristofor Colom, 11",
    "sg:city":"Tarragona",
    "sg:orig_category":"Universidades",
    "sg:phone":"+34 977 22 16 39",
    "sg:postcode":"43001",
    "sg:province":"Tarragona",
    "wof:name":"Area Matematica S.c.p.",
    "wof:placetype":"venue"
},
  "geometry": {"coordinates":[1.248246789,41.1160964966],"type":"Point"}
}