{
  "type": "Feature",
  "properties": {
    "addr:full":"Ctra Prats De Llu\u00c7anes, Km. 0174,6 Vic Barcelona 08500",
    "addr:postcode":"08500",
    "addr:street":"Ctra Prats De Lluc\u0327Anes Km. 0174,6",
    "iso:country":"ES",
    "sg:address":"Ctra Prats De Llu\u00c7anes, Km. 0174,6",
    "sg:city":"Vic",
    "sg:orig_category":"Distribuci\u00d3n De Petr\u00d3leo Y Derivados",
    "sg:phone":"+34 938 89 58 51",
    "sg:postcode":"08500",
    "sg:province":"Barcelona",
    "sg:website":"www.cepsa.es",
    "wof:name":"Cedipsa Compa\u00d1ia Espa\u00d1ola Distribuidora De Petroleos S.a.",
    "wof:placetype":"venue"
},
  "geometry": {"coordinates":[2.2525210381,41.9338531494],"type":"Point"}
}