{
  "type": "Feature",
  "properties": {
    "iso:country":"ES",
    "sg:address":"Calle de Barrio Verde, 25",
    "sg:city":"Castelnou",
    "sg:orig_category":"Confiter\u00cda, Galletas Y Pastas, Chocolater\u00cda (al Por Mayor)",
    "sg:phone":"+34 978 82 15 28",
    "sg:postcode":"44592",
    "sg:province":"Teruel",
    "wof:name":"Platoner S.l.",
    "wof:placetype":"venue"
},
  "geometry": {"coordinates":[-0.3636009991,41.2289619446],"type":"Point"}
}