{
  "type": "Feature",
  "properties": {
    "addr:full":"Calle de Madre Rafols, 2 Zaragoza Zaragoza 50004",
    "addr:housenumber":"2",
    "addr:postcode":"50004",
    "addr:street":"Calle De Madre Rafols",
    "iso:country":"ES",
    "sg:address":"Calle de Madre Rafols, 2",
    "sg:city":"Zaragoza",
    "sg:orig_category":"Productos Qu\u00cdmicos (fabricaci\u00d3n, Al Por Mayor)",
    "sg:phone":"+34 976 28 43 21",
    "sg:postcode":"50004",
    "sg:province":"Zaragoza",
    "wof:name":"Basell Poliolefinas Iberica S.l.",
    "wof:placetype":"venue"
},
  "geometry": {"coordinates":[-0.8873410225,41.6526184082],"type":"Point"}
}