{
  "type": "Feature",
  "properties": {
    "iso:country":"ES",
    "sg:address":"Calle de Lopan, 68",
    "sg:city":"Almeria",
    "sg:classifiers":[
        {
            "category":"Tea Room",
            "subcategory":"None",
            "type":"Food & Drink"
        }
    ],
    "sg:phone":"+34 950 26 54 72",
    "sg:postcode":"04008",
    "sg:province":"Almer\u00eda",
    "sg:tags":[
        "snack"
    ],
    "wof:name":"Lopez Bisbal Miguel Angel",
    "wof:placetype":"venue"
},
  "geometry": {"coordinates":[-2.4566760063,36.8489837646],"type":"Point"}
}