{
  "type": "Feature",
  "properties": {
    "iso:country":"ES",
    "sg:address":"Carr Lecco, 3",
    "sg:city":"Igualada",
    "sg:orig_category":"Juegos Y Juguetes (al Por Menor)",
    "sg:phone":"+34 938 03 21 29",
    "sg:postcode":"08700",
    "sg:province":"Barcelona",
    "wof:name":"Toys Centre S.l.",
    "wof:placetype":"venue"
},
  "geometry": {"coordinates":[1.6182490587,41.5894470215],"type":"Point"}
}