{
  "type": "Feature",
  "properties": {
    "addr:full":"Calle de Espa\u00d1a, 23 Fuengirola M\u00e1laga 29640",
    "addr:housenumber":"23",
    "addr:postcode":"29640",
    "addr:street":"Calle De Espan\u0303A;Ma\u0301Laga",
    "iso:country":"ES",
    "sg:address":"Calle de Espa\u00d1a, 23",
    "sg:city":"Fuengirola",
    "sg:orig_category":"Servidores Y Editores De Bases De Datos",
    "sg:phone":"+34 952 66 59 57",
    "sg:postcode":"29640",
    "sg:province":"M\u00e1laga",
    "sg:website":"www.f-rec.com",
    "wof:name":"F.n.e.t.",
    "wof:placetype":"venue"
},
  "geometry": {"coordinates":[-4.6282610893,36.5408287048],"type":"Point"}
}