{
  "type": "Feature",
  "properties": {
    "addr:full":"Av Agusti Ros (d'), 18 Agramunt Lleida 25310",
    "addr:housenumber":"18",
    "addr:postcode":"25310",
    "addr:street":"Av Agusti Ros D '",
    "iso:country":"ES",
    "sg:address":"Av Agusti Ros (d'), 18",
    "sg:city":"Agramunt",
    "sg:orig_category":"Material Y Herramientas Agr\u00cdcolas",
    "sg:phone":"+34 973 39 02 83",
    "sg:postcode":"25310",
    "sg:province":"Lleida",
    "sg:website":"www.triginer.com",
    "wof:name":"Maquinaria A. Triginer S.l.",
    "wof:placetype":"venue"
},
  "geometry": {"coordinates":[1.0992530584,41.7850532532],"type":"Point"}
}