{
  "type": "Feature",
  "properties": {
    "addr:full":"Calle de Alfonso Lasso De La Vega, 25 Sevilla Sevilla 41013",
    "addr:housenumber":"25",
    "addr:postcode":"41013",
    "addr:street":"Calle De Alfonso Lasso De La Vega",
    "iso:country":"ES",
    "sg:address":"Calle de Alfonso Lasso De La Vega, 25",
    "sg:city":"Sevilla",
    "sg:orig_category":"Abogados",
    "sg:phone":"+34 954 24 17 72",
    "sg:postcode":"41013",
    "sg:province":"Sevilla",
    "wof:name":"Canela Acosta Francisco Jose",
    "wof:placetype":"venue"
},
  "geometry": {"coordinates":[-5.9722514153,37.3666572571],"type":"Point"}
}