{
  "type": "Feature",
  "properties": {
    "addr:full":"Avda Vista Fermosa, 8 Ourense Ourense 32940",
    "addr:housenumber":"8",
    "addr:postcode":"32940",
    "addr:street":"Avda Vista Fermosa",
    "iso:country":"ES",
    "sg:address":"Avda Vista Fermosa, 8",
    "sg:city":"Ourense",
    "sg:orig_category":"Empresas De Carpinter\u00cda De Madera",
    "sg:phone":"+34 988 24 84 59",
    "sg:postcode":"32940",
    "sg:province":"Ourense",
    "wof:name":"Borrajo Cid Isidoro",
    "wof:placetype":"venue"
},
  "geometry": {"coordinates":[-7.8817272186,42.3452720642],"type":"Point"}
}