{
  "type": "Feature",
  "properties": {
    "iso:country":"ES",
    "sg:address":"Carr Pere Roma-rector, 38",
    "sg:city":"Cabaneta",
    "sg:orig_category":"Agencias Y Agentes Comerciales, Representantes",
    "sg:phone":"+34 971 60 38 04",
    "sg:postcode":"07141",
    "sg:province":"Islas Baleares",
    "wof:name":"Orihuela Iba\u00f1esorihuela Maria Dolores",
    "wof:placetype":"venue"
},
  "geometry": {"coordinates":[2.7399179935,39.6195373535],"type":"Point"}
}