{
  "type": "Feature",
  "properties": {
    "addr:full":"Poli Vernicha (la), S/n Vall D'uixo Castell\u00f3n 12600",
    "addr:postcode":"12600",
    "addr:street":"La S / N",
    "iso:country":"ES",
    "sg:address":"Poli Vernicha (la), S/n",
    "sg:city":"Vall D'uixo",
    "sg:orig_category":"Mataderos De Poller\u00cda",
    "sg:phone":"+34 964 69 60 74",
    "sg:postcode":"12600",
    "sg:province":"Castell\u00f3n",
    "wof:name":"Perello E Hijos S. A.",
    "wof:placetype":"venue"
},
  "geometry": {"coordinates":[-0.0482099988,39.992477417],"type":"Point"}
}