{
  "type": "Feature",
  "properties": {
    "iso:country":"ES",
    "sg:address":"Capellania, 10",
    "sg:city":"Retamal De Llerena",
    "sg:orig_category":"Empresas De Carpinter\u00cda De Madera",
    "sg:phone":"+34 924 77 40 34",
    "sg:postcode":"06442",
    "sg:province":"Badajoz",
    "wof:name":"Carmudex S.l.",
    "wof:placetype":"venue"
},
  "geometry": {"coordinates":[-5.8422279358,38.578754425],"type":"Point"}
}