{
  "type": "Feature",
  "properties": {
    "addr:full":"Calle de Miguel Marrero Rodriguez, 33 Arguineguin Las Palmas 35120",
    "addr:housenumber":"33",
    "addr:postcode":"35120",
    "addr:street":"Calle De Miguel Marrero Rodriguez;Palmas",
    "iso:country":"ES",
    "sg:address":"Calle de Miguel Marrero Rodriguez, 33",
    "sg:city":"Arguineguin",
    "sg:orig_category":"Ropa Para Se\u00d1oras Y Caballeros (al Por Menor)",
    "sg:phone":"+34 928 15 07 82",
    "sg:postcode":"35120",
    "sg:province":"Las Palmas",
    "wof:name":"Kotur  Katharina",
    "wof:placetype":"venue"
},
  "geometry": {"coordinates":[-15.6822185516,27.7601947784],"type":"Point"}
}