{
  "type": "Feature",
  "properties": {
    "iso:country":"ES",
    "sg:address":"Carrer de Acacies, 65",
    "sg:city":"Barcelona",
    "sg:orig_category":"Equitaci\u00d3n: Guarnicioner\u00cda, Equipo (al Por Menor)",
    "sg:phone":"+34 933 40 40 14",
    "sg:postcode":"08027",
    "sg:province":"Barcelona",
    "wof:name":"Vallve Timoneda Jose",
    "wof:placetype":"venue"
},
  "geometry": {"coordinates":[2.1779720783,41.4260978699],"type":"Point"}
}