{
  "type": "Feature",
  "properties": {
    "addr:full":"Calle de Ramon Gomez De La Serna, 6 Marbella M\u00e1laga 29600",
    "addr:housenumber":"6",
    "addr:postcode":"29600",
    "addr:street":"Calle De Ramon Gomez De La Serna;Ma\u0301Laga",
    "iso:country":"ES",
    "sg:address":"Calle de Ramon Gomez De La Serna, 6",
    "sg:city":"Marbella",
    "sg:orig_category":"Cerrajer\u00cda, Ferrallista",
    "sg:phone":"+34 952 82 18 23",
    "sg:postcode":"29600",
    "sg:province":"M\u00e1laga",
    "wof:name":"Cerrajeria Carlos Neira S.l.",
    "wof:placetype":"venue"
},
  "geometry": {"coordinates":[-4.8942008018,36.5098876953],"type":"Point"}
}