{
  "type": "Feature",
  "properties": {
    "addr:full":"Calle de Balandro, 39 Madrid Madrid 28042",
    "addr:housenumber":"39",
    "addr:postcode":"madrid;28042",
    "addr:street":"Calle De Balandro",
    "iso:country":"ES",
    "sg:address":"Calle de Balandro, 39",
    "sg:city":"Madrid",
    "sg:orig_category":"Carnicer\u00cdas, Carnicer\u00cdas",
    "sg:phone":"+34 917 41 97 77",
    "sg:postcode":"28042",
    "sg:province":"Madrid",
    "wof:name":"Crisostomo Anton Juan",
    "wof:placetype":"venue"
},
  "geometry": {"coordinates":[-3.5904829502,40.4542198181],"type":"Point"}
}