{
  "type": "Feature",
  "properties": {
    "addr:full":"Plaz Princi Jerez, 2 Jerez De La Frontera C\u00e1diz 11406",
    "addr:housenumber":"2",
    "addr:postcode":"11406",
    "addr:street":"Jerez",
    "iso:country":"ES",
    "sg:address":"Plaz Princi Jerez, 2",
    "sg:city":"Jerez De La Frontera",
    "sg:orig_category":"Ropa Para Se\u00d1oras Y Caballeros (al Por Menor)",
    "sg:phone":"+34 956 32 29 29",
    "sg:postcode":"11406",
    "sg:province":"C\u00e1diz",
    "wof:name":"Modas Aurora S.l",
    "wof:placetype":"venue"
},
  "geometry": {"coordinates":[-6.1165838242,36.682258606],"type":"Point"}
}