{
  "type": "Feature",
  "properties": {
    "iso:country":"ES",
    "sg:address":"Pase Constitucion De (la), 61",
    "sg:city":"Arnedo",
    "sg:orig_category":"Panader\u00cdas, Panader\u00cdas",
    "sg:phone":"+34 941 38 32 73",
    "sg:postcode":"26580",
    "sg:province":"La Rioja",
    "wof:name":"Saez Gil De Gomez Teresa",
    "wof:placetype":"venue"
},
  "geometry": {"coordinates":[-2.1026320457,42.226020813],"type":"Point"}
}