{
  "type": "Feature",
  "properties": {
    "iso:country":"ES",
    "sg:address":"Calle de Mesones, 2",
    "sg:city":"Campillo Llerena",
    "sg:orig_category":"Cr\u00cda De Animales",
    "sg:phone":"+34 924 77 01 28",
    "sg:postcode":"06443",
    "sg:province":"Badajoz",
    "wof:name":"Fernandez De La Cruz Consuelo",
    "wof:placetype":"venue"
},
  "geometry": {"coordinates":[-5.8304672241,38.5012435913],"type":"Point"}
}