{
  "type": "Feature",
  "properties": {
    "addr:full":"Carrer de Duana, 3 Barcelona Barcelona 08003",
    "addr:housenumber":"3",
    "addr:postcode":"08003",
    "addr:street":"Carrer De Duana",
    "iso:country":"ES",
    "sg:address":"Carrer de Duana, 3",
    "sg:city":"Barcelona",
    "sg:orig_category":"Importaci\u00d3n",
    "sg:phone":"+34 932 95 47 40",
    "sg:postcode":"08003",
    "sg:province":"Barcelona",
    "wof:name":"Ganduxer Floriach S A",
    "wof:placetype":"venue"
},
  "geometry": {"coordinates":[2.1847450733,41.383769989],"type":"Point"}
}