{
  "type": "Feature",
  "properties": {
    "addr:full":"Avda Caballeria Espa\u00d1ola, 6 Alcala Henares Madrid 28805",
    "addr:housenumber":"6",
    "addr:postcode":"28805",
    "addr:street":"Avda Caballeria Espan\u0303Ola",
    "iso:country":"ES",
    "sg:address":"Avda Caballeria Espa\u00d1ola, 6",
    "sg:city":"Alcala Henares",
    "sg:orig_category":"Negocio De Materiales De Construcci\u00d3n",
    "sg:phone":"+34 918 81 71 79",
    "sg:postcode":"28805",
    "sg:province":"Madrid",
    "wof:name":"Caballeria Espa\u00f1ola S.l.",
    "wof:placetype":"venue"
},
  "geometry": {"coordinates":[-3.3592059612,40.4878501892],"type":"Point"}
}