{
  "type": "Feature",
  "properties": {
    "addr:full":"Carrer de Sant Antoni, 46 Esparreguera Barcelona 08292",
    "addr:housenumber":"46",
    "addr:postcode":"08292",
    "addr:street":"Carrer De Sant Antoni",
    "iso:country":"ES",
    "sg:address":"Carrer de Sant Antoni, 46",
    "sg:city":"Esparreguera",
    "sg:orig_category":"Lencer\u00cda Femenina, Corseter\u00cda, Trajes De Ba\u00d1o (al Por Menor)",
    "sg:phone":"+34 937 77 55 11",
    "sg:postcode":"08292",
    "sg:province":"Barcelona",
    "wof:name":"Llopart Robert Adelina",
    "wof:placetype":"venue"
},
  "geometry": {"coordinates":[1.8684719801,41.5379981995],"type":"Point"}
}