{
  "type": "Feature",
  "properties": {
    "addr:full":"Pol Ind Pont Barquera, 24 Sta. Coloma Queralt Tarragona 43420",
    "addr:housenumber":"24",
    "addr:postcode":"43420",
    "addr:street":"Barquera",
    "iso:country":"ES",
    "sg:address":"Pol Ind Pont Barquera, 24",
    "sg:city":"Sta. Coloma Queralt",
    "sg:orig_category":"Empresarios",
    "sg:phone":"+34 977 88 16 16",
    "sg:postcode":"43420",
    "sg:province":"Tarragona",
    "wof:name":"Construcciones Bergada S.a.",
    "wof:placetype":"venue"
},
  "geometry": {"coordinates":[1.3818399906,41.5321388245],"type":"Point"}
}