{
  "type": "Feature",
  "properties": {
    "iso:country":"ES",
    "sg:address":"Carr Verge De La Vila, 12",
    "sg:city":"Santa Margarida De Montbui B-urbano",
    "sg:orig_category":"Planchado",
    "sg:phone":"+34 938 05 31 08",
    "sg:postcode":"08710",
    "sg:province":"Barcelona",
    "wof:name":"Medina Jimenez Joaquin",
    "wof:placetype":"venue"
},
  "geometry": {"coordinates":[1.6042679548,41.5729675293],"type":"Point"}
}