{
  "type": "Feature",
  "properties": {
    "addr:full":"Avda Padre Isla, 34 Le\u00f3n Le\u00f3n 24002",
    "addr:housenumber":"34",
    "addr:postcode":"24002",
    "addr:street":"Avda Padre Isla;Leo\u0301N",
    "iso:country":"ES",
    "sg:address":"Avda Padre Isla, 34",
    "sg:city":"Le\u00f3n",
    "sg:orig_category":"Asociaciones Y Clubs Deportivos",
    "sg:phone":"+34 987 23 94 35",
    "sg:postcode":"24002",
    "sg:province":"Le\u00f3n",
    "wof:name":"Fernandez Gutierrez Jose Antonio",
    "wof:placetype":"venue"
},
  "geometry": {"coordinates":[-5.5738830566,42.6008033752],"type":"Point"}
}