{
  "type": "Feature",
  "properties": {
    "iso:country":"ES",
    "sg:address":"Calle de General Mola, 16",
    "sg:city":"Barboles",
    "sg:orig_category":"Producci\u00d3n, Venta De Productos De Agricultura Biol\u00d3gica",
    "sg:phone":"+34 976 65 41 75",
    "sg:postcode":"50297",
    "sg:province":"Zaragoza",
    "wof:name":"Laborda Medrano Victor",
    "wof:placetype":"venue"
},
  "geometry": {"coordinates":[-1.1921410561,41.7101860046],"type":"Point"}
}