{
  "type": "Feature",
  "properties": {
    "addr:full":"Plaz Carmelitas (las), 20 Dos Hermanas Sevilla 41700",
    "addr:housenumber":"20",
    "addr:postcode":"41700",
    "addr:street":"Las",
    "iso:country":"ES",
    "sg:address":"Plaz Carmelitas (las), 20",
    "sg:city":"Dos Hermanas",
    "sg:orig_category":"Molduras, Junquillos, Listones Y Molduras Perforadas",
    "sg:phone":"+34 955 66 36 16",
    "sg:postcode":"41700",
    "sg:province":"Sevilla",
    "wof:name":"Armario Martin Francisca",
    "wof:placetype":"venue"
},
  "geometry": {"coordinates":[-5.938574791,37.2687606812],"type":"Point"}
}