{
  "type": "Feature",
  "properties": {
    "addr:full":"Calle de Alvarez De Abreu, 15 Santa Cruz Palma Santa Cruz De Tenerife 38700",
    "addr:housenumber":"15",
    "addr:postcode":"38700",
    "addr:street":"Calle De Alvarez De Abreu",
    "iso:country":"ES",
    "sg:address":"Calle de Alvarez De Abreu, 15",
    "sg:city":"Santa Cruz Palma",
    "sg:orig_category":"M\u00c9dicos: Cirug\u00cda General",
    "sg:phone":"+34 922 41 11 48",
    "sg:postcode":"38700",
    "sg:province":"Santa Cruz De Tenerife",
    "wof:name":"Hernandez Perez Alvaro",
    "wof:placetype":"venue"
},
  "geometry": {"coordinates":[-17.7645530701,28.6830120087],"type":"Point"}
}