{
  "type": "Feature",
  "properties": {
    "iso:country":"ES",
    "sg:address":"Calle de Baratzategi, 4",
    "sg:city":"Donostia-san Sebastian",
    "sg:orig_category":"Agencias Y Asesores De Publicidad",
    "sg:phone":"+34 943 27 94 44",
    "sg:postcode":"20015",
    "sg:province":"Guip\u00f9zcoa",
    "wof:name":"Proseral S.l.",
    "wof:placetype":"venue"
},
  "geometry": {"coordinates":[-1.9593020678,43.3138961792],"type":"Point"}
}