{
  "type": "Feature",
  "properties": {
    "addr:full":"Avda Constitucion, 34 Bollullos Par Condado Huelva 21710",
    "addr:housenumber":"34",
    "addr:postcode":"21710",
    "addr:street":"Avda Constitucion",
    "iso:country":"ES",
    "sg:address":"Avda Constitucion, 34",
    "sg:city":"Bollullos Par Condado",
    "sg:orig_category":"Bazares, Art\u00cdculos De Limpieza Y De Cocina (al Por Menor)",
    "sg:phone":"+34 959 41 15 63",
    "sg:postcode":"21710",
    "sg:province":"Huelva",
    "wof:name":"Ruiz Dominguez Isabel Clara",
    "wof:placetype":"venue"
},
  "geometry": {"coordinates":[-6.5377650261,37.3399353027],"type":"Point"}
}