{
  "type": "Feature",
  "properties": {
    "addr:full":"C/ Ruperto Chapi, 6 Elche Alicante 03201",
    "addr:housenumber":"6",
    "addr:postcode":"03201",
    "addr:street":"C / Ruperto Chapi",
    "iso:country":"ES",
    "sg:address":"C/ Ruperto Chapi, 6",
    "sg:city":"Elche",
    "sg:orig_category":"Congelados: Productos Alimentarios (al Por Menor)",
    "sg:phone":"+34 965 44 51 17",
    "sg:postcode":"03201",
    "sg:province":"Alicante",
    "wof:name":"Pomares Boix Josefa",
    "wof:placetype":"venue"
},
  "geometry": {"coordinates":[-0.7030090094,38.2659111023],"type":"Point"}
}