{
  "type": "Feature",
  "properties": {
    "addr:full":"Ctra Humera (de), 71 Pozuelo De Alarcon Madrid 28224",
    "addr:housenumber":"71",
    "addr:postcode":"28224",
    "addr:street":"Ctra Humera De",
    "iso:country":"ES",
    "sg:address":"Ctra Humera (de), 71",
    "sg:city":"Pozuelo De Alarcon",
    "sg:orig_category":"Inform\u00c1tica (estudios, Servicios, Asesor\u00cda, Formaci\u00d3n)",
    "sg:phone":"+34 913 52 01 76",
    "sg:postcode":"28224",
    "sg:province":"Madrid",
    "wof:name":"Cd Santa Cruz Sc",
    "wof:placetype":"venue"
},
  "geometry": {"coordinates":[-3.7994990349,40.4366111755],"type":"Point"}
}