{
  "type": "Feature",
  "properties": {
    "addr:full":"Avda Cesar Augusto, 42 Zaragoza Zaragoza 50004",
    "addr:housenumber":"42",
    "addr:postcode":"50004",
    "addr:street":"Avda Cesar Augusto",
    "iso:country":"ES",
    "sg:address":"Avda Cesar Augusto, 42",
    "sg:city":"Zaragoza",
    "sg:orig_category":"Procuradores",
    "sg:phone":"+34 976 22 51 44",
    "sg:postcode":"50004",
    "sg:province":"Zaragoza",
    "wof:name":"Pradilla Carreras Emilio",
    "wof:placetype":"venue"
},
  "geometry": {"coordinates":[-0.8841019869,41.6534156799],"type":"Point"}
}