{
  "type": "Feature",
  "properties": {
    "iso:country":"ES",
    "sg:address":"Carretera Meson Del Viento, S/n",
    "sg:city":"Cerceda",
    "sg:orig_category":"Reciclaje Y Tratamiento De Desechos Varios",
    "sg:phone":"+34 981 68 61 11",
    "sg:postcode":"15185",
    "sg:province":"A Coru\u00f1a",
    "wof:name":"Sociedade Galega Do Medio Ambiente S.a.",
    "wof:placetype":"venue"
},
  "geometry": {"coordinates":[-8.4736642838,43.1888847351],"type":"Point"}
}