{
  "type": "Feature",
  "properties": {
    "iso:country":"ES",
    "sg:address":"Calle de Resejo, S/n",
    "sg:city":"Ria\u00f1o",
    "sg:orig_category":"Apicultura",
    "sg:phone":"+34 987 74 07 40",
    "sg:postcode":"24900",
    "sg:province":"Le\u00f3n",
    "wof:name":"Miel Yordas S.l.",
    "wof:placetype":"venue"
},
  "geometry": {"coordinates":[-5.0033960342,42.9769210815],"type":"Point"}
}