{
  "type": "Feature",
  "properties": {
    "iso:country":"ES",
    "sg:address":"Calle de Carretera, Km. 0091,5",
    "sg:city":"Armellada",
    "sg:orig_category":"Instalaci\u00d3n, Reparaci\u00d3n De Calefacci\u00d3n Por Gas",
    "sg:phone":"+34 987 36 34 41",
    "sg:postcode":"24284",
    "sg:province":"Le\u00f3n",
    "wof:name":"Petrolorbi, S.l.",
    "wof:placetype":"venue"
},
  "geometry": {"coordinates":[-5.8634328842,42.5545272827],"type":"Point"}
}