{
  "type": "Feature",
  "properties": {
    "addr:full":"Calle de Canovas Del Castillo, 48 Jumilla Murcia 30520",
    "addr:housenumber":"48",
    "addr:postcode":"30520",
    "addr:street":"Calle De Canovas Del Castillo",
    "iso:country":"ES",
    "sg:address":"Calle de Canovas Del Castillo, 48",
    "sg:city":"Jumilla",
    "sg:orig_category":"Confecci\u00d3n (fabricaci\u00d3n, Al Por Mayor)",
    "sg:phone":"+34 968 75 65 53",
    "sg:postcode":"30520",
    "sg:province":"Murcia",
    "wof:name":"Lopez Garcia Antonio",
    "wof:placetype":"venue"
},
  "geometry": {"coordinates":[-1.3265861273,38.4749107361],"type":"Point"}
}