{
  "type": "Feature",
  "properties": {
    "iso:country":"ES",
    "sg:address":"Avda Andalucia, 26",
    "sg:city":"Malaga",
    "sg:orig_category":"Ense\u00d1anza: Idiomas",
    "sg:phone":"+34 952 61 78 53",
    "sg:postcode":"29007",
    "sg:province":"M\u00e1laga",
    "sg:website":"www.ihmalaga.es",
    "wof:name":"International House Malaga S.l.",
    "wof:placetype":"venue"
},
  "geometry": {"coordinates":[-4.4333424568,36.7172050476],"type":"Point"}
}