{
  "type": "Feature",
  "properties": {
    "addr:full":"Barr Oguena, 10 Amorebieta Vizcaya 48340",
    "addr:housenumber":"10",
    "addr:postcode":"48340",
    "addr:street":"Oguena",
    "iso:country":"ES",
    "sg:address":"Barr Oguena, 10",
    "sg:city":"Amorebieta",
    "sg:orig_category":"Asociaciones Humanitarias, De Cooperaci\u00d3n, De Acci\u00d3n Social",
    "sg:phone":"+34 946 30 90 68",
    "sg:postcode":"48340",
    "sg:province":"Vizcaya",
    "wof:name":"Asociacion Zabaltzen",
    "wof:placetype":"venue"
},
  "geometry": {"coordinates":[-2.7420985699,43.2233352661],"type":"Point"}
}