{
  "type": "Feature",
  "properties": {
    "iso:country":"ES",
    "sg:address":"Calle de Modesto Lafuente, 84",
    "sg:city":"Madrid",
    "sg:orig_category":"Promotores Constructores",
    "sg:phone":"+34 915 36 02 16",
    "sg:postcode":"28003",
    "sg:province":"Madrid",
    "wof:name":"Marketing Y Comercializacion De Comunidades S.l.",
    "wof:placetype":"venue"
},
  "geometry": {"coordinates":[-3.6955161095,40.445690155],"type":"Point"}
}