{
  "type": "Feature",
  "properties": {
    "iso:country":"ES",
    "sg:address":"Nacional Seis, Km. 0402,0",
    "sg:city":"Parandones",
    "sg:orig_category":"Productores Recolectores, Venta Directa De Vinos",
    "sg:phone":"+34 987 68 90 15",
    "sg:postcode":"24516",
    "sg:province":"Le\u00f3n",
    "wof:name":"Martinez Garcia Agustin",
    "wof:placetype":"venue"
},
  "geometry": {"coordinates":[-6.7820892334,42.5656929016],"type":"Point"}
}