{
  "type": "Feature",
  "properties": {
    "iso:country":"ES",
    "sg:address":"Calle de Alfaros, 8",
    "sg:city":"Cordoba",
    "sg:orig_category":"Ense\u00d1anza Variada",
    "sg:phone":"+34 957 48 69 25",
    "sg:postcode":"14001",
    "sg:province":"C\u00f3rdoba",
    "wof:name":"Blanco Gomez Inmaculada",
    "wof:placetype":"venue"
},
  "geometry": {"coordinates":[-4.7762317657,37.8856887817],"type":"Point"}
}