{
  "type": "Feature",
  "properties": {
    "iso:country":"ES",
    "sg:address":"Calle de Herreria, 48",
    "sg:city":"Caldas De Reis",
    "sg:orig_category":"Art\u00cdculos Funerarios (al Por Menor)",
    "sg:phone":"+34 986 54 14 18",
    "sg:postcode":"36650",
    "sg:province":"Pontevedra",
    "wof:name":"Diz Chazo Juan Jose",
    "wof:placetype":"venue"
},
  "geometry": {"coordinates":[-8.788476944,42.5159721375],"type":"Point"}
}