{
  "type": "Feature",
  "properties": {
    "iso:country":"ES",
    "sg:address":"Calle de Padre Guillem, 7",
    "sg:city":"Alaquas",
    "sg:orig_category":"Relojer\u00cda (al Por Menor, Reparaci\u00d3n)",
    "sg:phone":"+34 961 50 31 34",
    "sg:postcode":"46970",
    "sg:province":"Valencia",
    "wof:name":"Martinez Palop Miguel",
    "wof:placetype":"venue"
},
  "geometry": {"coordinates":[-0.4565620124,39.4570884705],"type":"Point"}
}