{
  "type": "Feature",
  "properties": {
    "addr:full":"Av Illice, S/n Torrellano Alicante 03320",
    "addr:housenumber":"s / n",
    "addr:postcode":"03320",
    "addr:street":"Av Illice",
    "iso:country":"ES",
    "sg:address":"Av Illice, S/n",
    "sg:city":"Torrellano",
    "sg:orig_category":"Cajas De Ahorro",
    "sg:phone":"+34 965 68 39 60",
    "sg:postcode":"03320",
    "sg:province":"Alicante",
    "wof:name":"Caja De Ahorros Del Mediterraneo",
    "wof:placetype":"venue"
},
  "geometry": {"coordinates":[-0.585909009,38.2940063477],"type":"Point"}
}