{
  "type": "Feature",
  "properties": {
    "iso:country":"ES",
    "sg:address":"Carrer de Montecassino, 6",
    "sg:city":"Barcelona",
    "sg:orig_category":"Concepci\u00d3n Y Realizaci\u00d3n De Maquetas Profesionales Y Prototipos",
    "sg:phone":"+34 932 01 65 70",
    "sg:postcode":"08006",
    "sg:province":"Barcelona",
    "wof:name":"Malberti Julia Jose",
    "wof:placetype":"venue"
},
  "geometry": {"coordinates":[2.1419401169,41.4019432068],"type":"Point"}
}