{
  "type": "Feature",
  "properties": {
    "iso:country":"ES",
    "sg:address":"Pontecesures, 17",
    "sg:city":"Padron",
    "sg:orig_category":"Ingeniero",
    "sg:phone":"+34 981 81 14 30",
    "sg:postcode":"15900",
    "sg:province":"La Coru\u00f1a",
    "wof:name":"Gecotop Servicios Integrales S.l.",
    "wof:placetype":"venue"
},
  "geometry": {"coordinates":[-8.6595392227,42.7344093323],"type":"Point"}
}