{
  "type": "Feature",
  "properties": {
    "iso:country":"ES",
    "sg:address":"Carrer de Rossello, 29",
    "sg:city":"Granollers",
    "sg:orig_category":"Electrodom\u00c9sticos (fabricaci\u00d3n, Al Por Mayor)",
    "sg:phone":"+34 938 49 73 00",
    "sg:postcode":"08401",
    "sg:province":"Barcelona",
    "wof:name":"Electro Pla Granollers S.a.",
    "wof:placetype":"venue"
},
  "geometry": {"coordinates":[2.2888689041,41.6151885986],"type":"Point"}
}