{
  "type": "Feature",
  "properties": {
    "addr:full":"Carrer de Roser, 39 Barcelona Barcelona 08004",
    "addr:housenumber":"39",
    "addr:postcode":"08004",
    "addr:street":"Carrer De Roser",
    "iso:country":"ES",
    "sg:address":"Carrer de Roser, 39",
    "sg:city":"Barcelona",
    "sg:orig_category":"Farmacias",
    "sg:phone":"+34 934 42 86 74",
    "sg:postcode":"08004",
    "sg:province":"Barcelona",
    "wof:name":"Catafal Llora Maria Lourdes",
    "wof:placetype":"venue"
},
  "geometry": {"coordinates":[2.1666960716,41.3731002808],"type":"Point"}
}