{
  "type": "Feature",
  "properties": {
    "iso:country":"ES",
    "sg:address":"Pl Font (de La), 2",
    "sg:city":"Alcover",
    "sg:orig_category":"Peluquer\u00cdas, Peluquer\u00cda Mixta",
    "sg:phone":"+34 977 76 04 16",
    "sg:postcode":"43460",
    "sg:province":"Tarragona",
    "wof:name":"Lorente Urbano Maria Del Carmen",
    "wof:placetype":"venue"
},
  "geometry": {"coordinates":[1.1706969738,41.2625236511],"type":"Point"}
}