{
  "type": "Feature",
  "properties": {
    "iso:country":"ES",
    "sg:address":"Calle de Hidalgos, 34",
    "sg:city":"Calzada Valdunciel",
    "sg:orig_category":"Electricidad: Instalaciones Industriales",
    "sg:phone":"+34 923 31 01 45",
    "sg:postcode":"37797",
    "sg:province":"Salamanca",
    "wof:name":"Riesco Hernandez Agustin",
    "wof:placetype":"venue"
},
  "geometry": {"coordinates":[-5.7044677734,41.0863456726],"type":"Point"}
}