{
  "type": "Feature",
  "properties": {
    "iso:country":"ES",
    "sg:address":"Calle de Villalobos, 127",
    "sg:city":"Madrid",
    "sg:orig_category":"Frutas, Legumbres Frescas Y Tempranas (al Por Menor)",
    "sg:phone":"+34 913 80 17 06",
    "sg:postcode":"28018",
    "sg:province":"Madrid",
    "wof:name":"Toledo Carre\u00f1o Luis Miguel",
    "wof:placetype":"venue"
},
  "geometry": {"coordinates":[-3.650857687,40.3806610107],"type":"Point"}
}