{
  "type": "Feature",
  "properties": {
    "addr:full":"Ctra Hoya Pineda, S/n Galdar Las Palmas 35460",
    "addr:housenumber":"s / n",
    "addr:postcode":"35460",
    "addr:street":"Ctra Hoya Pineda",
    "iso:country":"ES",
    "sg:address":"Ctra Hoya Pineda, S/n",
    "sg:city":"Galdar",
    "sg:orig_category":"Mec\u00c1nico Del Autom\u00d3vil",
    "sg:phone":"+34 928 55 00 92",
    "sg:postcode":"35460",
    "sg:province":"Las Palmas",
    "wof:name":"Taller J.j. Hernandez Suarez S.l.",
    "wof:placetype":"venue"
},
  "geometry": {"coordinates":[-15.6728258133,28.1178455353],"type":"Point"}
}