{
  "type": "Feature",
  "properties": {
    "iso:country":"ES",
    "sg:address":"Alam Areilza Doctor, 12",
    "sg:city":"Bilbao",
    "sg:orig_category":"Ense\u00d1anza, Formaci\u00d3n Profesional: Aprendizaje",
    "sg:phone":"+34 946 00 68 00",
    "sg:postcode":"48011",
    "sg:province":"Vizcaya",
    "wof:name":"Osakidetza",
    "wof:placetype":"venue"
},
  "geometry": {"coordinates":[-2.9419059753,43.2629966736],"type":"Point"}
}