{
  "type": "Feature",
  "properties": {
    "addr:full":"Huesca, 3 Sabi\u00f1anigo Huesca 22600",
    "addr:housenumber":"3",
    "addr:postcode":"22600",
    "addr:street":"Huesca",
    "iso:country":"ES",
    "sg:address":"Huesca, 3",
    "sg:city":"Sabi\u00f1anigo",
    "sg:orig_category":"Plomeros",
    "sg:phone":"+34 974 48 32 98",
    "sg:postcode":"22600",
    "sg:province":"Huesca",
    "wof:name":"Fonmetal S.l.",
    "wof:placetype":"venue"
},
  "geometry": {"coordinates":[-0.3558990061,42.5107154846],"type":"Point"}
}