{
  "type": "Feature",
  "properties": {
    "addr:full":"Avda Padre Villoslada, 32 Baena C\u00f3rdoba 14850",
    "addr:housenumber":"32",
    "addr:postcode":"14850",
    "addr:street":"Avda Padre Villoslada",
    "iso:country":"ES",
    "sg:address":"Avda Padre Villoslada, 32",
    "sg:city":"Baena",
    "sg:orig_category":"Mec\u00c1nico Del Autom\u00d3vil",
    "sg:phone":"+34 957 67 00 04",
    "sg:postcode":"14850",
    "sg:province":"C\u00f3rdoba",
    "wof:name":"Talleres Vizcaino S.l.",
    "wof:placetype":"venue"
},
  "geometry": {"coordinates":[-4.3160748482,37.6190109253],"type":"Point"}
}