{
  "type": "Feature",
  "properties": {
    "addr:full":"Calle de Ruiz De Alda, 1 Selaya Cantabria 39696",
    "addr:housenumber":"1",
    "addr:postcode":"39696",
    "addr:street":"Calle De Ruiz De Alda",
    "iso:country":"ES",
    "sg:address":"Calle de Ruiz De Alda, 1",
    "sg:city":"Selaya",
    "sg:orig_category":"Bisuter\u00cda, Joyer\u00cda, Relojer\u00cda (al Por Menor)",
    "sg:phone":"+34 942 59 10 84",
    "sg:postcode":"39696",
    "sg:province":"Cantabria",
    "wof:name":"Marquez Abellan Maria Jose",
    "wof:placetype":"venue"
},
  "geometry": {"coordinates":[-3.8065459728,43.2161712646],"type":"Point"}
}