{
  "type": "Feature",
  "properties": {
    "addr:full":"Cno De Colmenar, S/n Casabermeja M\u00e1laga 29160",
    "addr:housenumber":"s / n",
    "addr:postcode":"29160",
    "addr:street":"Cno De Colmenar",
    "iso:country":"ES",
    "sg:address":"Cno De Colmenar, S/n",
    "sg:city":"Casabermeja",
    "sg:orig_category":"Panader\u00cdas, Panader\u00cdas",
    "sg:phone":"+34 952 75 82 70",
    "sg:postcode":"29160",
    "sg:province":"M\u00e1laga",
    "wof:name":"Reposteria Alcoholado S.l.",
    "wof:placetype":"venue"
},
  "geometry": {"coordinates":[-4.4291119576,36.8940238953],"type":"Point"}
}