{
  "type": "Feature",
  "properties": {
    "addr:full":"Rua Venezuela, 59 Silleda Pontevedra 36540",
    "addr:housenumber":"59",
    "addr:postcode":"36540",
    "addr:street":"Rua Venezuela",
    "iso:country":"ES",
    "sg:address":"Rua Venezuela, 59",
    "sg:city":"Silleda",
    "sg:orig_category":"Electricidad: Instaladores",
    "sg:phone":"+34 986 58 06 77",
    "sg:postcode":"36540",
    "sg:province":"Pontevedra",
    "wof:name":"Instalaciones Electricas Silleda S.l.",
    "wof:placetype":"venue"
},
  "geometry": {"coordinates":[-8.2451658249,42.6988716125],"type":"Point"}
}