{
  "type": "Feature",
  "properties": {
    "addr:full":"Calle de Olleria (l'), 1 Alacant Alicante 03009",
    "addr:housenumber":"1",
    "addr:postcode":"03009",
    "addr:street":"Calle De Olleria L '",
    "iso:country":"ES",
    "sg:address":"Calle de Olleria (l'), 1",
    "sg:city":"Alacant",
    "sg:classifiers":[
        {
            "category":"Banks & Credit Unions",
            "subcategory":"Bureau De Change",
            "type":"Services"
        }
    ],
    "sg:phone":"+34 965 17 52 77",
    "sg:postcode":"03009",
    "sg:province":"Alicante",
    "sg:tags":[
        "organismos",
        "control"
    ],
    "sg:website":"www.cualiacisa.com",
    "wof:name":"Cualicontrol-aci S.a.",
    "wof:placetype":"venue"
},
  "geometry": {"coordinates":[-0.4980680048,38.3650550842],"type":"Point"}
}