{
  "type": "Feature",
  "properties": {
    "iso:country":"ES",
    "sg:address":"Rua Francisco Llorens Diaz, 7",
    "sg:city":"Ourense",
    "sg:orig_category":"Caf\u00c9s, Bares, Cervecer\u00cdas",
    "sg:phone":"+34 988 23 77 42",
    "sg:postcode":"32002",
    "sg:province":"Ourense",
    "wof:name":"Novelle Pereira Anibal",
    "wof:placetype":"venue"
},
  "geometry": {"coordinates":[-7.8715620041,42.3432502747],"type":"Point"}
}