{
  "type": "Feature",
  "properties": {
    "iso:country":"ES",
    "sg:address":"Calle de Huelva, S/n",
    "sg:city":"Valladolid",
    "sg:orig_category":"Centros Comerciales Y Grandes Tiendas",
    "sg:phone":"+34 983 30 56 87",
    "sg:postcode":"47012",
    "sg:province":"Valladolid",
    "wof:name":"Tranche Sierra Francisco",
    "wof:placetype":"venue"
},
  "geometry": {"coordinates":[-4.7152662277,41.6433563232],"type":"Point"}
}