{
  "type": "Feature",
  "properties": {
    "addr:full":"Pg Maritim, 392 Castelldefels Barcelona 08860",
    "addr:housenumber":"392",
    "addr:postcode":"08860",
    "addr:street":"Pg Maritim",
    "iso:country":"ES",
    "sg:address":"Pg Maritim, 392",
    "sg:city":"Castelldefels",
    "sg:orig_category":"Platos Preparados Refrigerados (fabricaci\u00d3n, Al Por Mayor)",
    "sg:phone":"+34 936 64 11 34",
    "sg:postcode":"08860",
    "sg:province":"Barcelona",
    "wof:name":"Montero Perez Esteban",
    "wof:placetype":"venue"
},
  "geometry": {"coordinates":[1.9457730055,41.2648086548],"type":"Point"}
}