{
  "type": "Feature",
  "properties": {
    "iso:country":"ES",
    "sg:address":"Carrer de Rutlla, 1",
    "sg:city":"S. Boi Llobregat",
    "sg:orig_category":"Partidos Pol\u00cdticos",
    "sg:phone":"+34 936 61 48 62",
    "sg:postcode":"08830",
    "sg:province":"Barcelona",
    "wof:name":"Partit Dels Socialistes De Catalunya",
    "wof:placetype":"venue"
},
  "geometry": {"coordinates":[2.0409889221,41.3460693359],"type":"Point"}
}