{
  "type": "Feature",
  "properties": {
    "addr:full":"Calle de Torno, 5 Gijon Asturias 33213",
    "addr:housenumber":"5",
    "addr:postcode":"33213",
    "addr:street":"Calle De Torno",
    "iso:country":"ES",
    "sg:address":"Calle de Torno, 5",
    "sg:city":"Gijon",
    "sg:orig_category":"Cerrajer\u00cda, Ferrallista",
    "sg:phone":"+34 985 30 13 30",
    "sg:postcode":"33213",
    "sg:province":"Asturias",
    "wof:name":"Colinas De La Fuente Miguel",
    "wof:placetype":"venue"
},
  "geometry": {"coordinates":[-5.7036042213,43.5409202576],"type":"Point"}
}