{
  "type": "Feature",
  "properties": {
    "iso:country":"ES",
    "sg:address":"Calle de Conde De Pe\u00d1alver, 11",
    "sg:city":"Madrid",
    "sg:orig_category":"Caf\u00c9s (al Por Menor)",
    "sg:phone":"+34 915 75 99 24",
    "sg:postcode":"28006",
    "sg:province":"Madrid",
    "sg:website":"www.lamexicana.es",
    "wof:name":"Rodriguez Y Mateus S.a.",
    "wof:placetype":"venue"
},
  "geometry": {"coordinates":[-3.6756591797,40.4258422852],"type":"Point"}
}