{
  "type": "Feature",
  "properties": {
    "addr:full":"Av. Bayona, 41 Iru\u00f1a Navarra 31011",
    "addr:housenumber":"41",
    "addr:postcode":"31011",
    "addr:street":"Av. Bayona",
    "iso:country":"ES",
    "sg:address":"Av. Bayona, 41",
    "sg:city":"Iru\u00f1a",
    "sg:orig_category":"Institutos De Belleza",
    "sg:phone":"+34 948 26 67 84",
    "sg:postcode":"31011",
    "sg:province":"Navarra",
    "wof:name":"Oses Medrano Miryam",
    "wof:placetype":"venue"
},
  "geometry": {"coordinates":[-1.6614409685,42.8125915527],"type":"Point"}
}