{
  "type": "Feature",
  "properties": {
    "addr:full":"Plaz Almazara (la), 3 Alcala Guadaira Sevilla 41500",
    "addr:postcode":"41500",
    "addr:street":"Plaz Almazara La 3",
    "iso:country":"ES",
    "sg:address":"Plaz Almazara (la), 3",
    "sg:city":"Alcala Guadaira",
    "sg:orig_category":"Panader\u00cdas, Panader\u00cdas",
    "sg:phone":"+34 955 68 38 50",
    "sg:postcode":"41500",
    "sg:province":"Sevilla",
    "wof:name":"Romero Casado Francisco",
    "wof:placetype":"venue"
},
  "geometry": {"coordinates":[-5.8398590088,37.3383140564],"type":"Point"}
}