{
  "type": "Feature",
  "properties": {
    "iso:country":"ES",
    "sg:address":"Calle de Gamazo, 14",
    "sg:city":"Valladolid",
    "sg:orig_category":"Peluquer\u00cdas, Peluquer\u00cda Mixta",
    "sg:phone":"+34 983 30 77 30",
    "sg:postcode":"47004",
    "sg:province":"Valladolid",
    "wof:name":"El Albar De Zanco S.l.",
    "wof:placetype":"venue"
},
  "geometry": {"coordinates":[-4.7264451981,41.6464805603],"type":"Point"}
}