{
  "type": "Feature",
  "properties": {
    "iso:country":"ES",
    "sg:address":"Calle de Padre Marin, 33",
    "sg:city":"Logro\u00f1o",
    "sg:orig_category":"Maquinaria Para Industrias Diversas",
    "sg:phone":"+34 941 25 70 24",
    "sg:postcode":"26004",
    "sg:province":"La Rioja",
    "wof:name":"Jesus Chasco Vicente Y Otro",
    "wof:placetype":"venue"
},
  "geometry": {"coordinates":[-2.4298899174,42.4668769836],"type":"Point"}
}