{
  "type": "Feature",
  "properties": {
    "iso:country":"ES",
    "sg:address":"Urb. C. Teguise, S/n",
    "sg:city":"Costa Teguise",
    "sg:orig_category":"Peleter\u00cdas",
    "sg:phone":"+34 928 59 02 31",
    "sg:postcode":"35509",
    "sg:province":"Las Palmas",
    "wof:name":"Robel  Peter",
    "wof:placetype":"venue"
},
  "geometry": {"coordinates":[-13.5916891098,28.955160141],"type":"Point"}
}