{
  "type": "Feature",
  "properties": {
    "addr:full":"Calle de Doctor Serrano, 7 Valencia Valencia 46006",
    "addr:housenumber":"7",
    "addr:postcode":"46006",
    "addr:street":"Calle De Doctor Serrano",
    "iso:country":"ES",
    "sg:address":"Calle de Doctor Serrano, 7",
    "sg:city":"Valencia",
    "sg:orig_category":"Reposter\u00cdas",
    "sg:phone":"+34 963 41 45 32",
    "sg:postcode":"46006",
    "sg:province":"Valencia",
    "wof:name":"Poveda Lopez Jesus",
    "wof:placetype":"venue"
},
  "geometry": {"coordinates":[0.0627529025,38.8276901245],"type":"Point"}
}