{
  "type": "Feature",
  "properties": {
    "iso:country":"ES",
    "sg:address":"Calle de Vasco Nu\u00d1ez, 18",
    "sg:city":"Badajoz",
    "sg:orig_category":"M\u00c1quinas De Coser Y De Hacer Punto (al Por Mayor)",
    "sg:phone":"+34 924 22 12 96",
    "sg:postcode":"06001",
    "sg:province":"Badajoz",
    "wof:name":"Mancera Gomez Carmen",
    "wof:placetype":"venue"
},
  "geometry": {"coordinates":[-6.9744091034,38.8781204224],"type":"Point"}
}