{
  "type": "Feature",
  "properties": {
    "addr:full":"Avda Pando De, 45 Oviedo Asturias 33011",
    "addr:housenumber":"45",
    "addr:postcode":"33011",
    "addr:street":"Avda Pando De",
    "iso:country":"ES",
    "sg:address":"Avda Pando De, 45",
    "sg:city":"Oviedo",
    "sg:orig_category":"Venta, Colocaci\u00d3n, Reparaci\u00d3n De Radiadores Para Veh\u00cdculos",
    "sg:phone":"+34 985 29 57 43",
    "sg:postcode":"33011",
    "sg:province":"Asturias",
    "wof:name":"Rodriguez Fernandez Roman",
    "wof:placetype":"venue"
},
  "geometry": {"coordinates":[-5.8476548195,43.3780593872],"type":"Point"}
}