{
  "type": "Feature",
  "properties": {
    "iso:country":"ES",
    "sg:address":"Carrer de Sant Narcis, 59",
    "sg:city":"Barcelona",
    "sg:orig_category":"Fabricaci\u00d3n De Mobiliario De Oficina",
    "sg:phone":"+34 933 46 26 51",
    "sg:postcode":"08030",
    "sg:province":"Barcelona",
    "wof:name":"Modilac S.l",
    "wof:placetype":"venue"
},
  "geometry": {"coordinates":[2.1923699379,41.4327964783],"type":"Point"}
}