{
  "type": "Feature",
  "properties": {
    "iso:country":"ES",
    "sg:address":"Calle de Escritor Herrera Santaolalla, 16",
    "sg:city":"Churriana",
    "sg:orig_category":"Comercio De Piezas De Recambio Y De Accesorios De Veh\u00cdculos, Veh\u00cdculos Industriales",
    "sg:phone":"+34 952 43 61 29",
    "sg:postcode":"29140",
    "sg:province":"M\u00e1laga",
    "wof:name":"Recauto S.c.a",
    "wof:placetype":"venue"
},
  "geometry": {"coordinates":[-4.4950518608,36.6604881287],"type":"Point"}
}