{
  "type": "Feature",
  "properties": {
    "addr:full":"Ctr Toledo-tlvra., Km. 0166,6 Burujon Toledo 45519",
    "addr:postcode":"45519",
    "addr:street":"Toledo-Tlvra. Km. 0166,6",
    "iso:country":"ES",
    "sg:address":"Ctr Toledo-tlvra., Km. 0166,6",
    "sg:city":"Burujon",
    "sg:orig_category":"Materiales De Aislamiento T\u00c9rmico Y Ac\u00dastico",
    "sg:phone":"+34 925 78 93 35",
    "sg:postcode":"45519",
    "sg:province":"Toledo",
    "wof:name":"Aislamientos Y Cubiertas J.c. S.l.",
    "wof:placetype":"venue"
},
  "geometry": {"coordinates":[-4.2983837128,39.9013214111],"type":"Point"}
}