{
  "type": "Feature",
  "properties": {
    "addr:full":"Calle de Angel, 3 Granada Granada 18006",
    "addr:housenumber":"3",
    "addr:postcode":"18006",
    "addr:street":"Calle De Angel",
    "iso:country":"ES",
    "sg:address":"Calle de Angel, 3",
    "sg:city":"Granada",
    "sg:orig_category":"Ense\u00d1anza: Idiomas",
    "sg:phone":"+34 958 81 96 59",
    "sg:postcode":"18006",
    "sg:province":"Granada",
    "sg:website":"www.kelington.es",
    "wof:name":"Vallejo Rivas Maria Francisca",
    "wof:placetype":"venue"
},
  "geometry": {"coordinates":[-3.5974373817,37.1664810181],"type":"Point"}
}