{
  "type": "Feature",
  "properties": {
    "addr:full":"Pase Herrera De, 12 Donostia-san Sebastian Guip\u00f9zcoa 20017",
    "addr:housenumber":"12",
    "addr:postcode":"20017",
    "iso:country":"ES",
    "sg:address":"Pase Herrera De, 12",
    "sg:city":"Donostia-san Sebastian",
    "sg:orig_category":"Empresas De Carpinter\u00cda Met\u00c1lica",
    "sg:phone":"+34 943 39 16 26",
    "sg:postcode":"20017",
    "sg:province":"Guip\u00f9zcoa",
    "wof:name":"Echerurce Bustamante Aitor",
    "wof:placetype":"venue"
},
  "geometry": {"coordinates":[-1.9370440245,43.319065094],"type":"Point"}
}