{
  "type": "Feature",
  "properties": {
    "addr:full":"Calle de Escultor Antonio Martinez Olalla, 9 Granada Granada 18003",
    "addr:housenumber":"9",
    "addr:postcode":"18003",
    "addr:street":"Calle De Escultor Antonio Martinez Olalla",
    "iso:country":"ES",
    "sg:address":"Calle de Escultor Antonio Martinez Olalla, 9",
    "sg:city":"Granada",
    "sg:orig_category":"Promotores Constructores",
    "sg:phone":"+34 958 29 62 66",
    "sg:postcode":"18003",
    "sg:province":"Granada",
    "wof:name":"Promociones Abusaid S.l",
    "wof:placetype":"venue"
},
  "geometry": {"coordinates":[-3.6090610027,37.1749610901],"type":"Point"}
}