{
  "type": "Feature",
  "properties": {
    "addr:full":"Carrer de Dega Bahi, 2 Barcelona Barcelona 08026",
    "addr:housenumber":"2",
    "addr:postcode":"08026",
    "addr:street":"Carrer De Dega Bahi",
    "iso:country":"ES",
    "sg:address":"Carrer de Dega Bahi, 2",
    "sg:city":"Barcelona",
    "sg:orig_category":"Agencias Y Agentes Comerciales, Representantes",
    "sg:phone":"+34 933 48 01 89",
    "sg:postcode":"08026",
    "sg:province":"Barcelona",
    "wof:name":"Monta\u00f1es Aragones Jaime",
    "wof:placetype":"venue"
},
  "geometry": {"coordinates":[2.182997942,41.4105453491],"type":"Point"}
}