{
  "type": "Feature",
  "properties": {
    "iso:country":"ES",
    "sg:address":"Carrer de Bobiles, 84",
    "sg:city":"Hospitalet Llobregat",
    "sg:orig_category":"Retoques De Vestidos",
    "sg:phone":"+34 934 40 59 31",
    "sg:postcode":"08905",
    "sg:province":"Barcelona",
    "wof:name":"Ponce Fernandez Marisol",
    "wof:placetype":"venue"
},
  "geometry": {"coordinates":[2.1107881069,41.3720359802],"type":"Point"}
}