{
  "type": "Feature",
  "properties": {
    "addr:full":"Pase Alameda (de La), 7 Alcala Henares Madrid 28804",
    "addr:postcode":"28804",
    "addr:street":"Alameda De La 7",
    "iso:country":"ES",
    "sg:address":"Pase Alameda (de La), 7",
    "sg:city":"Alcala Henares",
    "sg:orig_category":"Art\u00cdculos De Decoraci\u00d3n",
    "sg:phone":"+34 918 81 82 86",
    "sg:postcode":"28804",
    "sg:province":"Madrid",
    "wof:name":"Tenllado Lopez Maria Jesus",
    "wof:placetype":"venue"
},
  "geometry": {"coordinates":[-3.357888937,40.4839859009],"type":"Point"}
}