{
  "type": "Feature",
  "properties": {
    "addr:full":"Calle de Batalla De Vallehermoso, 4 Jerez De La Frontera C\u00e1diz 11405",
    "addr:housenumber":"4",
    "addr:postcode":"11405",
    "addr:street":"Calle De Batalla De Vallehermoso",
    "iso:country":"ES",
    "sg:address":"Calle de Batalla De Vallehermoso, 4",
    "sg:city":"Jerez De La Frontera",
    "sg:orig_category":"Arreglo, Reparaci\u00d3n, Piezas Sueltas De Televisi\u00d3n, V\u00cddeo, Hi",
    "sg:phone":"+34 956 33 71 82",
    "sg:postcode":"11405",
    "sg:province":"C\u00e1diz",
    "wof:name":"Ruiz Fernandez Domingo",
    "wof:placetype":"venue"
},
  "geometry": {"coordinates":[-6.1239814758,36.6856117249],"type":"Point"}
}