{
  "type": "Feature",
  "properties": {
    "addr:full":"Plaz Santa Casilda, 5 Briviesca Burgos 09240",
    "addr:housenumber":"5",
    "addr:postcode":"09240",
    "addr:street":"Casilda",
    "iso:country":"ES",
    "sg:address":"Plaz Santa Casilda, 5",
    "sg:city":"Briviesca",
    "sg:orig_category":"Molduras, Junquillos, Listones Y Molduras Perforadas",
    "sg:phone":"+34 947 59 03 25",
    "sg:postcode":"09240",
    "sg:province":"Burgos",
    "wof:name":"Sainz Santaolalla Juan Jose",
    "wof:placetype":"venue"
},
  "geometry": {"coordinates":[-3.3248078823,42.5520858765],"type":"Point"}
}