{
  "type": "Feature",
  "properties": {
    "iso:country":"ES",
    "sg:address":"Calle de Leopoldo Alas Clarin, 4",
    "sg:city":"Pola De Laviana",
    "sg:orig_category":"Cajas Para Embalar",
    "sg:phone":"+34 985 60 05 87",
    "sg:postcode":"33980",
    "sg:province":"Asturias",
    "wof:name":"Caja Rural De Asturias",
    "wof:placetype":"venue"
},
  "geometry": {"coordinates":[-5.5629649162,43.2456054688],"type":"Point"}
}