{
  "type": "Feature",
  "properties": {
    "iso:country":"ES",
    "sg:address":"Ermita San Lorenzo, 3",
    "sg:city":"Benavente",
    "sg:orig_category":"Pintura Y Barniz (al Por Menor)",
    "sg:phone":"+34 980 63 48 81",
    "sg:postcode":"49600",
    "sg:province":"Zamora",
    "wof:name":"Segopi. S.l.",
    "wof:placetype":"venue"
},
  "geometry": {"coordinates":[-5.6651082039,42.0004653931],"type":"Point"}
}