{
  "type": "Feature",
  "properties": {
    "addr:full":"Calle de Virgen Del Camino, 10 Leganes Madrid 28911",
    "addr:housenumber":"10",
    "addr:postcode":"28911",
    "addr:street":"Calle De Virgen Del Camino",
    "iso:country":"ES",
    "sg:address":"Calle de Virgen Del Camino, 10",
    "sg:city":"Leganes",
    "sg:orig_category":"Servicios De Telecomunicaciones",
    "sg:phone":"+34 916 89 82 18",
    "sg:postcode":"28911",
    "sg:province":"Madrid",
    "wof:name":"Jazztel Telecomunicaciones",
    "wof:placetype":"venue"
},
  "geometry": {"coordinates":[-3.7725861073,40.3270797729],"type":"Point"}
}