{
  "type": "Feature",
  "properties": {
    "addr:full":"Avda Lugo (de), 65 Taboada Lugo 27550",
    "addr:housenumber":"65",
    "addr:postcode":"27550",
    "addr:street":"Avda Lugo De",
    "iso:country":"ES",
    "sg:address":"Avda Lugo (de), 65",
    "sg:city":"Taboada",
    "sg:orig_category":"Pescader\u00cdas (al Por Menor)",
    "sg:phone":"+34 982 46 55 29",
    "sg:postcode":"27550",
    "sg:province":"Lugo",
    "wof:name":"Guarch Calvo Maria Pilar",
    "wof:placetype":"venue"
},
  "geometry": {"coordinates":[-7.7628936768,42.7169685364],"type":"Point"}
}