{
  "type": "Feature",
  "properties": {
    "iso:country":"ES",
    "sg:address":"Calle de Sabino Alvarez Gendin, 17",
    "sg:city":"Aviles",
    "sg:orig_category":"Empresas De Desmonte",
    "sg:phone":"+34 985 55 01 25",
    "sg:postcode":"33402",
    "sg:province":"Asturias",
    "wof:name":"Excavaciones Martinez Olmo S.l.",
    "wof:placetype":"venue"
},
  "geometry": {"coordinates":[-5.9275388718,43.5479888916],"type":"Point"}
}