{
  "type": "Feature",
  "properties": {
    "addr:full":"Avda Salinas, 6 Laguna Duero Valladolid 47140",
    "addr:housenumber":"6",
    "addr:postcode":"47140",
    "addr:street":"Avda Salinas",
    "iso:country":"ES",
    "sg:address":"Avda Salinas, 6",
    "sg:city":"Laguna Duero",
    "sg:orig_category":"Dise\u00d1o Industrial",
    "sg:phone":"+34 983 54 14 38",
    "sg:postcode":"47140",
    "sg:province":"Valladolid",
    "wof:name":"Miguel Garcia Manuel",
    "wof:placetype":"venue"
},
  "geometry": {"coordinates":[-4.7216892242,41.5881195068],"type":"Point"}
}