{
  "type": "Feature",
  "properties": {
    "addr:full":"C/ Sant Martiria, 9 Banyoles Girona 17820",
    "addr:housenumber":"9",
    "addr:postcode":"17820",
    "addr:street":"C / Sant Martiria",
    "iso:country":"ES",
    "sg:address":"C/ Sant Martiria, 9",
    "sg:city":"Banyoles",
    "sg:orig_category":"M\u00c1quinas De Coser Y De Hacer Punto (al Por Mayor)",
    "sg:phone":"+34 972 57 49 43",
    "sg:postcode":"17820",
    "sg:province":"Girona",
    "wof:name":"Coll Romans Narcis",
    "wof:placetype":"venue"
},
  "geometry": {"coordinates":[2.764993906,42.1195259094],"type":"Point"}
}