{
  "type": "Feature",
  "properties": {
    "iso:country":"ES",
    "sg:address":"Calle de Arcos De La Frontera, 10",
    "sg:city":"Cordoba",
    "sg:orig_category":"Aparatos De Iluminaci\u00d3n (al Por Menor)",
    "sg:phone":"+34 957 43 52 67",
    "sg:postcode":"14014",
    "sg:province":"C\u00f3rdoba",
    "wof:name":"Jose Jimenez Calvo S.l.",
    "wof:placetype":"venue"
},
  "geometry": {"coordinates":[-4.7567744255,37.8987007141],"type":"Point"}
}