{
  "type": "Feature",
  "properties": {
    "iso:country":"ES",
    "sg:address":"Calle de Valentin Galarza, 2",
    "sg:city":"Segorbe",
    "sg:orig_category":"Bancos",
    "sg:phone":"+34 964 71 17 11",
    "sg:postcode":"12400",
    "sg:province":"Castell\u00f3n",
    "sg:website":"www.bancopopular.es",
    "wof:name":"Banco Popular Espa\u00f1ol S. A.",
    "wof:placetype":"venue"
},
  "geometry": {"coordinates":[-0.4886260033,39.8495635986],"type":"Point"}
}