{
  "type": "Feature",
  "properties": {
    "iso:country":"ES",
    "sg:address":"Calle de Claudio Sanchez Albornoz, 15",
    "sg:city":"Sotillo Adrada",
    "sg:orig_category":"M\u00c9dicos: Estomatolog\u00cda",
    "sg:phone":"+34 918 66 14 50",
    "sg:postcode":"05420",
    "sg:province":"\u00c1vila",
    "wof:name":"Bravo Arenas Alberto",
    "wof:placetype":"venue"
},
  "geometry": {"coordinates":[-4.584774971,40.2953262329],"type":"Point"}
}