{
  "type": "Feature",
  "properties": {
    "iso:country":"ES",
    "sg:address":"Calle de Palmar, 98",
    "sg:city":"Palmas De Gran Canaria",
    "sg:orig_category":"Mec\u00c1nico Del Autom\u00d3vil",
    "sg:phone":"+34 928 46 49 97",
    "sg:postcode":"35009",
    "sg:province":"Las Palmas",
    "wof:name":"Izquierdo Suarez Felix",
    "wof:placetype":"venue"
},
  "geometry": {"coordinates":[-15.4218988419,28.1531848907],"type":"Point"}
}