{
  "type": "Feature",
  "properties": {
    "iso:country":"ES",
    "sg:address":"Carrer de Bisbe Vilanova, 1",
    "sg:city":"Olot",
    "sg:orig_category":"Pintores",
    "sg:phone":"+34 972 27 02 43",
    "sg:postcode":"17800",
    "sg:province":"Girona",
    "wof:name":"Sala Rodriguez Albert Joan",
    "wof:placetype":"venue"
},
  "geometry": {"coordinates":[2.4854309559,42.179813385],"type":"Point"}
}