{
  "type": "Feature",
  "properties": {
    "iso:country":"ES",
    "sg:address":"Carrer de Emilio Serrano, 2",
    "sg:city":"Palma",
    "sg:orig_category":"T\u00c9cnicos Veterinarios",
    "sg:phone":"+34 971 29 32 29",
    "sg:postcode":"07005",
    "sg:province":"Islas Baleares",
    "wof:name":"Clinica Veterinaria Son Oliva,s.l.n.e.",
    "wof:placetype":"venue"
},
  "geometry": {"coordinates":[2.6642320156,39.5840377808],"type":"Point"}
}