{
  "type": "Feature",
  "properties": {
    "iso:country":"ES",
    "sg:address":"Carrer de Carme, 53",
    "sg:city":"Malgrat Mar",
    "sg:orig_category":"Papel, Reciclaje",
    "sg:phone":"+34 937 65 59 41",
    "sg:postcode":"08380",
    "sg:province":"Barcelona",
    "wof:name":"Folla Pesaferrer Salvador",
    "wof:placetype":"venue"
},
  "geometry": {"coordinates":[2.745579958,41.6485404968],"type":"Point"}
}