{
  "type": "Feature",
  "properties": {
    "addr:full":"Carrer de Sinia (la), 7 Martorelles Barcelona 08107",
    "addr:housenumber":"7",
    "addr:postcode":"08107",
    "addr:street":"Carrer De Sinia La",
    "iso:country":"ES",
    "sg:address":"Carrer de Sinia (la), 7",
    "sg:city":"Martorelles",
    "sg:orig_category":"Impresiones Sobre Tela",
    "sg:phone":"+34 935 70 75 35",
    "sg:postcode":"08107",
    "sg:province":"Barcelona",
    "wof:name":"Rodriguez Perez Maria Del Carmen",
    "wof:placetype":"venue"
},
  "geometry": {"coordinates":[2.2433390617,41.5276031494],"type":"Point"}
}