{
  "type": "Feature",
  "properties": {
    "addr:full":"Calle de Estudios, 4 Soria Soria 42002",
    "addr:housenumber":"4",
    "addr:postcode":"42002",
    "addr:street":"Calle De Estudios",
    "iso:country":"ES",
    "sg:address":"Calle de Estudios, 4",
    "sg:city":"Soria",
    "sg:orig_category":"Mercer\u00cda, Lencer\u00cda (al Por Menor)",
    "sg:phone":"+34 975 21 23 02",
    "sg:postcode":"42002",
    "sg:province":"Soria",
    "wof:name":"Martinez Escolar Jose Maria",
    "wof:placetype":"venue"
},
  "geometry": {"coordinates":[-2.4653611183,41.7645530701],"type":"Point"}
}