{
  "type": "Feature",
  "properties": {
    "addr:full":"Calle de Corredera, 64 Almansa Albacete 02640",
    "addr:housenumber":"64",
    "addr:postcode":"02640",
    "addr:street":"Calle De Corredera",
    "iso:country":"ES",
    "sg:address":"Calle de Corredera, 64",
    "sg:city":"Almansa",
    "sg:orig_category":"Asesor\u00cda Sobre Comunicaci\u00d3n De Empresas",
    "sg:phone":"+34 967 31 11 21",
    "sg:postcode":"02640",
    "sg:province":"Albacete",
    "wof:name":"Garcia De La Fuente Felix Jesus",
    "wof:placetype":"venue"
},
  "geometry": {"coordinates":[-1.0949703455,38.8665542603],"type":"Point"}
}