{
  "type": "Feature",
  "properties": {
    "iso:country":"ES",
    "sg:address":"Calle de Salon Supremo, 1",
    "sg:city":"Caravaca Cruz",
    "sg:orig_category":"Molduras, Junquillos, Listones Y Molduras Perforadas",
    "sg:phone":"+34 968 70 21 23",
    "sg:postcode":"30400",
    "sg:province":"Murcia",
    "wof:name":"Eurotel Sur S.l.",
    "wof:placetype":"venue"
},
  "geometry": {"coordinates":[-1.8645700216,38.104763031],"type":"Point"}
}