{
  "type": "Feature",
  "properties": {
    "addr:full":"Av Virgen Pastores, S/n Huerta Valdecarabanos Toledo 45750",
    "addr:postcode":"45750",
    "addr:street":"Av;Pastores S / N Huerta Valdecarabanos",
    "iso:country":"ES",
    "sg:address":"Av Virgen Pastores, S/n",
    "sg:city":"Huerta Valdecarabanos",
    "sg:orig_category":"Productores Recolectores, Venta Directa De Vinos",
    "sg:phone":"+34 925 12 91 88",
    "sg:postcode":"45750",
    "sg:province":"Toledo",
    "wof:name":"Garcia Alsinet Luis",
    "wof:placetype":"venue"
},
  "geometry": {"coordinates":[-3.6144590378,39.8616943359],"type":"Point"}
}