{
  "type": "Feature",
  "properties": {
    "iso:country":"ES",
    "sg:address":"Ctra. Sta. Cruz, 1",
    "sg:city":"Torre Esteban Hambran",
    "sg:orig_category":"Empresarios",
    "sg:phone":"+34 925 79 51 48",
    "sg:postcode":"45920",
    "sg:province":"Toledo",
    "wof:name":"Lopez Gilro S.l.",
    "wof:placetype":"venue"
},
  "geometry": {"coordinates":[-4.0285758972,39.8582496643],"type":"Point"}
}