{
  "type": "Feature",
  "properties": {
    "addr:full":"Carrer de Alfons Xii, 28 Manresa Barcelona 08241",
    "addr:housenumber":"28",
    "addr:postcode":"08241",
    "addr:street":"Carrer De Alfons Xii",
    "iso:country":"ES",
    "sg:address":"Carrer de Alfons Xii, 28",
    "sg:city":"Manresa",
    "sg:orig_category":"Agencias De Trabajo Temporal",
    "sg:phone":"+34 938 76 82 42",
    "sg:postcode":"08241",
    "sg:province":"Barcelona",
    "sg:website":"www.adecco.es",
    "wof:name":"Adecco E.t.t. S.a.",
    "wof:placetype":"venue"
},
  "geometry": {"coordinates":[1.8246581554,41.7235603333],"type":"Point"}
}