{
  "type": "Feature",
  "properties": {
    "addr:full":"Avda Atenas, 9 Alcorcon Madrid 28925",
    "addr:housenumber":"9",
    "addr:postcode":"28925",
    "addr:street":"Avda Atenas",
    "iso:country":"ES",
    "sg:address":"Avda Atenas, 9",
    "sg:city":"Alcorcon",
    "sg:orig_category":"Centros M\u00c9dicos Y Sociales, Dispensarios",
    "sg:phone":"+34 916 41 92 09",
    "sg:postcode":"28925",
    "sg:province":"Madrid",
    "wof:name":"Aguado Benedi Maria Jose",
    "wof:placetype":"venue"
},
  "geometry": {"coordinates":[-3.8405609131,40.3479537964],"type":"Point"}
}