{
  "type": "Feature",
  "properties": {
    "addr:full":"Plaz Ayuntamiento (del), S/n Albu\u00f1ol Granada 18700",
    "addr:postcode":"18700",
    "addr:street":"S / N Albun\u0303Ol",
    "iso:country":"ES",
    "sg:address":"Plaz Ayuntamiento (del), S/n",
    "sg:city":"Albu\u00f1ol",
    "sg:orig_category":"Empresas De Electricidad En General",
    "sg:phone":"+34 958 82 60 48",
    "sg:postcode":"18700",
    "sg:province":"Granada",
    "wof:name":"Distribuidora Electrica Bermejales S.a.",
    "wof:placetype":"venue"
},
  "geometry": {"coordinates":[-3.2032990456,36.7913284302],"type":"Point"}
}