{
  "type": "Feature",
  "properties": {
    "iso:country":"ES",
    "sg:address":"Calle de Arenal, 15",
    "sg:city":"Madrid",
    "sg:orig_category":"Ropa Para Ni\u00d1os (al Por Menor)",
    "sg:phone":"+34 915 42 14 54",
    "sg:postcode":"28013",
    "sg:province":"Madrid",
    "wof:name":"Camino Sanz Juan Jose",
    "wof:placetype":"venue"
},
  "geometry": {"coordinates":[-3.7073245049,40.4174423218],"type":"Point"}
}