{
  "type": "Feature",
  "properties": {
    "addr:full":"Calle de Fueros, 14 Bilbao Vizcaya 48005",
    "addr:housenumber":"14",
    "addr:postcode":"48005",
    "addr:street":"Calle De Fueros",
    "iso:country":"ES",
    "sg:address":"Calle de Fueros, 14",
    "sg:city":"Bilbao",
    "sg:orig_category":"Alimentaci\u00d3n General (al Por Menor)",
    "sg:phone":"+34 944 15 10 43",
    "sg:postcode":"48005",
    "sg:province":"Vizcaya",
    "wof:name":"Revuelta Bravo Amelia",
    "wof:placetype":"venue"
},
  "geometry": {"coordinates":[-2.9227991104,43.2595405579],"type":"Point"}
}