{
  "type": "Feature",
  "properties": {
    "addr:full":"Av Flors (les), 11 S. Joan Despi Barcelona 08970",
    "addr:housenumber":"11",
    "addr:postcode":"08970",
    "addr:street":"Av Flors Les;S. Joan Despi",
    "iso:country":"ES",
    "sg:address":"Av Flors (les), 11",
    "sg:city":"S. Joan Despi",
    "sg:orig_category":"Promotores Constructores",
    "sg:phone":"+34 933 73 32 47",
    "sg:postcode":"08970",
    "sg:province":"Barcelona",
    "wof:name":"Systemcer S.l.",
    "wof:placetype":"venue"
},
  "geometry": {"coordinates":[2.0718638897,41.3659667969],"type":"Point"}
}