{
  "type": "Feature",
  "properties": {
    "iso:country":"ES",
    "sg:address":"Calle de Paseo Marques De Arriluce E Ibarra, S/n",
    "sg:city":"Algorta",
    "sg:orig_category":"Deportes Diversos",
    "sg:phone":"+34 944 60 31 55",
    "sg:postcode":"48992",
    "sg:province":"Vizcaya",
    "wof:name":"Reef Divers S.l.",
    "wof:placetype":"venue"
},
  "geometry": {"coordinates":[-3.0117850304,43.3388328552],"type":"Point"}
}