{
  "type": "Feature",
  "properties": {
    "iso:country":"ES",
    "sg:address":"Calle de Sierra Morena, 1",
    "sg:city":"Madrid",
    "sg:orig_category":"Sociedades, Compa\u00d1\u00cdas Aseguradoras",
    "sg:phone":"+34 917 78 24 62",
    "sg:postcode":"28031",
    "sg:province":"Madrid",
    "wof:name":"Trasegur Correduria De Seguros S.a.",
    "wof:placetype":"venue"
},
  "geometry": {"coordinates":[-3.6251540184,40.3806381226],"type":"Point"}
}