{
  "type": "Feature",
  "properties": {
    "addr:full":"Ari\u00f1ez, S/n Ari\u00d1ez \u00c1lava 01195",
    "addr:postcode":"01195",
    "addr:street":"Arin\u0303Ez S / N Arin\u0303Ez A\u0301Lava",
    "iso:country":"ES",
    "sg:address":"Ari\u00f1ez, S/n",
    "sg:city":"Ari\u00d1ez",
    "sg:orig_category":"Perreras, Pensiones Para Perros, Gatos Y Otros Animales",
    "sg:phone":"+34 945 29 05 69",
    "sg:postcode":"01195",
    "sg:province":"\u00c1lava",
    "wof:name":"Zufiaur I\u00f1iguez De Gordoa Isabel",
    "wof:placetype":"venue"
},
  "geometry": {"coordinates":[-2.7530424595,42.8277778625],"type":"Point"}
}