{
  "type": "Feature",
  "properties": {
    "addr:full":"Plaz Cortes De Aragon, 5 Jaca Huesca 22700",
    "addr:postcode":"22700",
    "addr:street":"Plaz",
    "iso:country":"ES",
    "sg:address":"Plaz Cortes De Aragon, 5",
    "sg:city":"Jaca",
    "sg:orig_category":"Confecci\u00d3n (fabricaci\u00d3n, Al Por Mayor)",
    "sg:phone":"+34 974 36 38 41",
    "sg:postcode":"22700",
    "sg:province":"Huesca",
    "wof:name":"Arroyos Gistau Maria Pilar",
    "wof:placetype":"venue"
},
  "geometry": {"coordinates":[-0.5511063933,42.5695724487],"type":"Point"}
}