{
  "type": "Feature",
  "properties": {
    "addr:full":"Calle de Francisco Silvela, 27 Madrid Madrid 28028",
    "addr:housenumber":"27",
    "addr:postcode":"madrid;28028",
    "addr:street":"Calle De Francisco Silvela",
    "iso:country":"ES",
    "sg:address":"Calle de Francisco Silvela, 27",
    "sg:city":"Madrid",
    "sg:orig_category":"Asesor\u00cda Sobre Comunicaci\u00d3n De Empresas",
    "sg:phone":"+34 914 01 04 32",
    "sg:postcode":"28028",
    "sg:province":"Madrid",
    "wof:name":"Leon Gonzalez Manuel",
    "wof:placetype":"venue"
},
  "geometry": {"coordinates":[-3.6716079712,40.4311714172],"type":"Point"}
}