{
  "type": "Feature",
  "properties": {
    "iso:country":"ES",
    "sg:address":"Calle de Rafael Gallego Sainz, 14",
    "sg:city":"Oviedo",
    "sg:orig_category":"Peluquer\u00cdas, Peluquer\u00cda Mixta",
    "sg:phone":"+34 985 23 21 00",
    "sg:postcode":"33012",
    "sg:province":"Asturias",
    "wof:name":"Javier Y Tomas Cdad.",
    "wof:placetype":"venue"
},
  "geometry": {"coordinates":[-5.8683338165,43.367275238],"type":"Point"}
}