{
  "type": "Feature",
  "properties": {
    "iso:country":"ES",
    "sg:address":"Calle de San Sebastian, 10",
    "sg:city":"Archidona",
    "sg:orig_category":"Contenedores (mercanc\u00cdas)",
    "sg:phone":"+34 952 71 70 69",
    "sg:postcode":"29300",
    "sg:province":"M\u00e1laga",
    "wof:name":"Molina Fuentes S.c.",
    "wof:placetype":"venue"
},
  "geometry": {"coordinates":[-4.3835291862,37.0947113037],"type":"Point"}
}