{
  "type": "Feature",
  "properties": {
    "addr:full":"Carr Tapis, 72 Figueres Girona 17600",
    "addr:housenumber":"72",
    "addr:postcode":"17600",
    "addr:street":"Carr Tapis",
    "iso:country":"ES",
    "sg:address":"Carr Tapis, 72",
    "sg:city":"Figueres",
    "sg:orig_category":"Carnes De Carnicer\u00cda (al Por Mayor)",
    "sg:phone":"+34 972 51 03 05",
    "sg:postcode":"17600",
    "sg:province":"Girona",
    "wof:name":"Calvete Hidalgo Josep",
    "wof:placetype":"venue"
},
  "geometry": {"coordinates":[2.9661009312,42.271938324],"type":"Point"}
}