{
  "type": "Feature",
  "properties": {
    "iso:country":"ES",
    "sg:address":"Leon-astorga, Km. 0005,2",
    "sg:city":"Trobajo Camino",
    "sg:orig_category":"Sales (al Por Mayor)",
    "sg:phone":"+34 987 80 14 24",
    "sg:postcode":"24010",
    "sg:province":"Le\u00f3n",
    "wof:name":"Industrias Confiterias El Bernesga S. L.",
    "wof:placetype":"venue"
},
  "geometry": {"coordinates":[-5.5716600418,42.5981292725],"type":"Point"}
}