{
  "type": "Feature",
  "properties": {
    "iso:country":"ES",
    "sg:address":"Mercat Sant Antoni, S/n",
    "sg:city":"Barcelona",
    "sg:orig_category":"Pescader\u00cdas (al Por Menor)",
    "sg:phone":"+34 933 25 74 85",
    "sg:postcode":"08015",
    "sg:province":"Barcelona",
    "wof:name":"Padial Vera Miguel",
    "wof:placetype":"venue"
},
  "geometry": {"coordinates":[2.1608901024,41.379535675],"type":"Point"}
}