{
  "type": "Feature",
  "properties": {
    "addr:full":"Plaz Verdiales, 1 Malaga M\u00e1laga 29011",
    "addr:housenumber":"1",
    "addr:postcode":"29011",
    "addr:street":"Plaz Verdiales;Ma\u0301Laga",
    "iso:country":"ES",
    "sg:address":"Plaz Verdiales, 1",
    "sg:city":"Malaga",
    "sg:orig_category":"Reposter\u00cdas",
    "sg:phone":"+34 952 28 41 54",
    "sg:postcode":"29011",
    "sg:province":"M\u00e1laga",
    "wof:name":"Rute Martin Antonio Jesus",
    "wof:placetype":"venue"
},
  "geometry": {"coordinates":[-4.4290280342,36.7406845093],"type":"Point"}
}