{
  "type": "Feature",
  "properties": {
    "iso:country":"ES",
    "sg:address":"Plaz Constitucion, 12",
    "sg:city":"Huercal-overa",
    "sg:orig_category":"Cl\u00cdnicas Dentales",
    "sg:phone":"+34 950 13 51 85",
    "sg:postcode":"04600",
    "sg:province":"Almer\u00eda",
    "wof:name":"Clinica Dental Sonria S.l.",
    "wof:placetype":"venue"
},
  "geometry": {"coordinates":[-1.9435640574,37.3894996643],"type":"Point"}
}