{
  "type": "Feature",
  "properties": {
    "iso:country":"ES",
    "sg:address":"Cra. Roca, Km. 0003,2",
    "sg:city":"Cardedeu",
    "sg:orig_category":"Delegados, Agentes De Tr\u00c1nsito, Auxiliares De Transporte Internacional",
    "sg:phone":"+34 938 45 41 91",
    "sg:postcode":"08440",
    "sg:province":"Barcelona",
    "wof:name":"Transportes Igoa Y Patxi S.a.",
    "wof:placetype":"venue"
},
  "geometry": {"coordinates":[2.3589351177,41.6370544434],"type":"Point"}
}