{
  "type": "Feature",
  "properties": {
    "iso:country":"ES",
    "sg:address":"Calle de Cabezo Calvario, 122",
    "sg:city":"Epila",
    "sg:orig_category":"Reposter\u00cdas",
    "sg:phone":"+34 976 60 33 84",
    "sg:postcode":"50290",
    "sg:province":"Zaragoza",
    "wof:name":"Navarro Romanos Concepcion",
    "wof:placetype":"venue"
},
  "geometry": {"coordinates":[-1.2797039747,41.6023521423],"type":"Point"}
}