{
  "type": "Feature",
  "properties": {
    "addr:full":"Calle de San Andres, 56 Coru\u00d1a La Coru\u00f1a 15003",
    "addr:housenumber":"56",
    "addr:postcode":"15003",
    "addr:street":"Calle De San Andres;Corun\u0303A",
    "iso:country":"ES",
    "sg:address":"Calle de San Andres, 56",
    "sg:city":"Coru\u00d1a",
    "sg:orig_category":"Centros De Coordinaci\u00d3n",
    "sg:phone":"+34 981 21 78 60",
    "sg:postcode":"15003",
    "sg:province":"La Coru\u00f1a",
    "wof:name":"Diagonalgest S.l.",
    "wof:placetype":"venue"
},
  "geometry": {"coordinates":[-8.4029588699,43.3702087402],"type":"Point"}
}