{
  "type": "Feature",
  "properties": {
    "iso:country":"ES",
    "sg:address":"Calle de Infanta Beatriz, 15",
    "sg:city":"Sanlucar De Barrameda",
    "sg:orig_category":"Inversiones",
    "sg:phone":"+34 956 38 53 12",
    "sg:postcode":"11540",
    "sg:province":"C\u00e1diz",
    "wof:name":"Jm Inversiones Del Sur S.l.",
    "wof:placetype":"venue"
},
  "geometry": {"coordinates":[-6.3590707779,36.7797355652],"type":"Point"}
}