{
  "type": "Feature",
  "properties": {
    "addr:full":"Carr Doctor Lleonart, 24 Burjassot Valencia 46100",
    "addr:housenumber":"24",
    "addr:postcode":"46100",
    "addr:street":"Carr Doctor Lleonart",
    "iso:country":"ES",
    "sg:address":"Carr Doctor Lleonart, 24",
    "sg:city":"Burjassot",
    "sg:orig_category":"Papeler\u00cdas, Librer\u00cdas",
    "sg:phone":"+34 963 90 14 69",
    "sg:postcode":"46100",
    "sg:province":"Valencia",
    "wof:name":"Carrillo Berruga Alicia",
    "wof:placetype":"venue"
},
  "geometry": {"coordinates":[-0.4153729975,39.5079345703],"type":"Point"}
}