{
  "type": "Feature",
  "properties": {
    "addr:full":"Ausias March, 13 Favara Valencia 46614",
    "addr:housenumber":"13",
    "addr:postcode":"46614",
    "addr:street":"March",
    "iso:country":"ES",
    "sg:address":"Ausias March, 13",
    "sg:city":"Favara",
    "sg:orig_category":"Transportes Por V\u00cdas Navegables",
    "sg:phone":"+34 961 76 91 71",
    "sg:postcode":"46614",
    "sg:province":"Valencia",
    "wof:name":"Oliver Narbona Joaquin",
    "wof:placetype":"venue"
},
  "geometry": {"coordinates":[-0.2879999876,39.1267242432],"type":"Point"}
}