{
  "type": "Feature",
  "properties": {
    "addr:full":"Calle de Mariano Riquer Wallis, S/n Santa Eulalia Islas Baleares 07840",
    "addr:postcode":"07840",
    "addr:street":"Calle De Mariano Riquer Wallis S / N",
    "iso:country":"ES",
    "sg:address":"Calle de Mariano Riquer Wallis, S/n",
    "sg:city":"Santa Eulalia",
    "sg:orig_category":"Zapatos (al Por Menor)",
    "sg:phone":"+34 971 33 08 70",
    "sg:postcode":"07840",
    "sg:province":"Islas Baleares",
    "wof:name":"Mateo Guillen Juan Antonio",
    "wof:placetype":"venue"
},
  "geometry": {"coordinates":[1.5333948135,38.9838142395],"type":"Point"}
}