{
  "type": "Feature",
  "properties": {
    "iso:country":"ES",
    "sg:address":"Calle de Conde Aranda, 7",
    "sg:city":"Zaragoza",
    "sg:orig_category":"Mercer\u00cda, Lencer\u00cda (al Por Menor)",
    "sg:phone":"+34 976 44 38 31",
    "sg:postcode":"50004",
    "sg:province":"Zaragoza",
    "wof:name":"Castillo Blazquez Maria Eva",
    "wof:placetype":"venue"
},
  "geometry": {"coordinates":[-0.8851603866,41.6543197632],"type":"Point"}
}