{
  "type": "Feature",
  "properties": {
    "iso:country":"ES",
    "sg:address":"Calle de Ruise\u00d1ores, 6",
    "sg:city":"Villares Reina",
    "sg:classifiers":[
        {
            "category":"Casinos & Gambling",
            "type":"Entertainment"
        }
    ],
    "sg:phone":"+34 923 28 84 08",
    "sg:postcode":"37184",
    "sg:province":"Salamanca",
    "sg:tags":[
        "locale",
        "de",
        "juego"
    ],
    "wof:name":"Villareina S.c.",
    "wof:placetype":"venue"
},
  "geometry": {"coordinates":[-5.6469841003,41.0071716309],"type":"Point"}
}