{
  "type": "Feature",
  "properties": {
    "addr:full":"Calle de Virgen Del Coro, 2 Madrid Madrid 28027",
    "addr:housenumber":"2",
    "addr:postcode":"28027",
    "addr:street":"Calle De Virgen Del Coro",
    "iso:country":"ES",
    "sg:address":"Calle de Virgen Del Coro, 2",
    "sg:city":"Madrid",
    "sg:orig_category":"Marroquiner\u00cda (confecci\u00d3n)",
    "sg:phone":"+34 914 03 33 38",
    "sg:postcode":"28027",
    "sg:province":"Madrid",
    "wof:name":"Susiac Diez Raul",
    "wof:placetype":"venue"
},
  "geometry": {"coordinates":[-3.6587290764,40.4336776733],"type":"Point"}
}