{
  "type": "Feature",
  "properties": {
    "iso:country":"ES",
    "sg:address":"Ctra Mig, 51",
    "sg:city":"Hospitalet Llobregat",
    "sg:orig_category":"Construcci\u00d3n Mec\u00c1nica",
    "sg:phone":"+34 933 36 06 51",
    "sg:postcode":"08907",
    "sg:province":"Barcelona",
    "sg:website":"www.cmframa.com",
    "wof:name":"Construcciones Mecanicas Frama S. A.",
    "wof:placetype":"venue"
},
  "geometry": {"coordinates":[2.1119270325,41.3576812744],"type":"Point"}
}