{
  "type": "Feature",
  "properties": {
    "addr:full":"Praz Galicia (de), 8 Vilagarcia Pontevedra 36600",
    "addr:postcode":"36600",
    "iso:country":"ES",
    "sg:address":"Praz Galicia (de), 8",
    "sg:city":"Vilagarcia",
    "sg:orig_category":"Cl\u00cdnicas Dentales",
    "sg:phone":"+34 986 51 24 24",
    "sg:postcode":"36600",
    "sg:province":"Pontevedra",
    "wof:name":"Giraldo Garcia Jose Maria",
    "wof:placetype":"venue"
},
  "geometry": {"coordinates":[-8.7652978897,42.5917396545],"type":"Point"}
}