{
  "type": "Feature",
  "properties": {
    "iso:country":"ES",
    "sg:address":"Rond Norte, 23",
    "sg:city":"Santa Maria De Gracia",
    "sg:orig_category":"M\u00c9dicos: Estomatolog\u00cda",
    "sg:phone":"+34 968 29 78 61",
    "sg:postcode":"30009",
    "sg:province":"Murcia",
    "wof:name":"Fajardo Angulo Jose",
    "wof:placetype":"venue"
},
  "geometry": {"coordinates":[-1.1396019459,37.9923934937],"type":"Point"}
}