{
  "type": "Feature",
  "properties": {
    "addr:full":"Avda Galicia, 53 Cambados Pontevedra 36630",
    "addr:housenumber":"53",
    "addr:postcode":"36630",
    "addr:street":"Avda Galicia",
    "iso:country":"ES",
    "sg:address":"Avda Galicia, 53",
    "sg:city":"Cambados",
    "sg:orig_category":"Contenedores (mercanc\u00cdas)",
    "sg:phone":"+34 986 54 31 18",
    "sg:postcode":"36630",
    "sg:province":"Pontevedra",
    "wof:name":"Nu\u00f1ez Cores Jose",
    "wof:placetype":"venue"
},
  "geometry": {"coordinates":[-8.8156642914,42.5111503601],"type":"Point"}
}