{
  "type": "Feature",
  "properties": {
    "iso:country":"ES",
    "sg:address":"Calle de Arriba, 2",
    "sg:city":"Villanueva De Las Peras",
    "sg:orig_category":"Cr\u00cda De Animales",
    "sg:phone":"+34 980 64 17 44",
    "sg:postcode":"49333",
    "sg:province":"Zamora",
    "wof:name":"Llamas Garcia Juan",
    "wof:placetype":"venue"
},
  "geometry": {"coordinates":[-5.9805021286,41.9335136414],"type":"Point"}
}