{
  "type": "Feature",
  "properties": {
    "addr:full":"Carrer de Fortuny (de), 14 Tarragona Tarragona 43001",
    "addr:housenumber":"14",
    "addr:postcode":"43001",
    "addr:street":"Carrer De Fortuny De",
    "iso:country":"ES",
    "sg:address":"Carrer de Fortuny (de), 14",
    "sg:city":"Tarragona",
    "sg:orig_category":"Asociaciones Y Clubs Deportivos",
    "sg:phone":"+34 977 21 82 80",
    "sg:postcode":"43001",
    "sg:province":"Tarragona",
    "wof:name":"Venus Center S.l.",
    "wof:placetype":"venue"
},
  "geometry": {"coordinates":[1.2510340214,41.1149482727],"type":"Point"}
}