{
  "type": "Feature",
  "properties": {
    "addr:full":"Ctra Cuesta La Reina, S/n Villaseca Sagra Toledo 45260",
    "addr:housenumber":"s / n",
    "addr:postcode":"45260",
    "addr:street":"Ctra Cuesta La Reina",
    "iso:country":"ES",
    "sg:address":"Ctra Cuesta La Reina, S/n",
    "sg:city":"Villaseca Sagra",
    "sg:orig_category":"Paletas",
    "sg:phone":"+34 925 27 84 68",
    "sg:postcode":"45260",
    "sg:province":"Toledo",
    "wof:name":"Ibon Y Roberto S.l.",
    "wof:placetype":"venue"
},
  "geometry": {"coordinates":[-3.8813800812,39.9579544067],"type":"Point"}
}