{
  "type": "Feature",
  "properties": {
    "addr:full":"Barr San Esteban, 31 San Esteban Guip\u00f9zcoa 20400",
    "addr:housenumber":"31",
    "addr:postcode":"20400",
    "addr:street":"San Esteban;Guipu\u0300Zcoa",
    "iso:country":"ES",
    "sg:address":"Barr San Esteban, 31",
    "sg:city":"San Esteban",
    "sg:orig_category":"Suministros Para Carrocer\u00cdas",
    "sg:phone":"+34 943 65 38 83",
    "sg:postcode":"20400",
    "sg:province":"Guip\u00f9zcoa",
    "wof:name":"Sanchez-almaden Rubio Jose Luis",
    "wof:placetype":"venue"
},
  "geometry": {"coordinates":[-2.0834209919,43.1335601807],"type":"Point"}
}