{
  "type": "Feature",
  "properties": {
    "addr:full":"Calle de Camarena, 280 Madrid Madrid 28047",
    "addr:housenumber":"280",
    "addr:postcode":"28047",
    "addr:street":"Calle De Camarena",
    "iso:country":"ES",
    "sg:address":"Calle de Camarena, 280",
    "sg:city":"Madrid",
    "sg:classifiers":[
        {
            "category":"Personal",
            "subcategory":"Barber",
            "type":"Services"
        }
    ],
    "sg:phone":"+34 917 17 10 11",
    "sg:postcode":"28047",
    "sg:province":"Madrid",
    "sg:tags":[
        "caballeros",
        "de",
        "peluqueros"
    ],
    "wof:name":"Bravo Camacho Guillermo",
    "wof:placetype":"venue"
},
  "geometry": {"coordinates":[-3.756529808,40.3873558044],"type":"Point"}
}