{
  "type": "Feature",
  "properties": {
    "addr:full":"Carrer de Cartella, 50 Barcelona Barcelona 08031",
    "addr:housenumber":"50",
    "addr:postcode":"08031",
    "addr:street":"Carrer De Cartella",
    "iso:country":"ES",
    "sg:address":"Carrer de Cartella, 50",
    "sg:city":"Barcelona",
    "sg:orig_category":"Electricidad: Instaladores",
    "sg:phone":"+34 934 29 21 30",
    "sg:postcode":"08031",
    "sg:province":"Barcelona",
    "wof:name":"Termes Roig Juan",
    "wof:placetype":"venue"
},
  "geometry": {"coordinates":[2.1715068817,41.4280967712],"type":"Point"}
}