{
  "type": "Feature",
  "properties": {
    "iso:country":"ES",
    "sg:address":"Calle de Estalajes, 157",
    "sg:city":"Azuaga",
    "sg:orig_category":"Veh\u00cdculos De Ocasi\u00d3n",
    "sg:phone":"+34 924 89 03 93",
    "sg:postcode":"06920",
    "sg:province":"Badajoz",
    "wof:name":"Alejandre Esquivel E Hijos S.l.",
    "wof:placetype":"venue"
},
  "geometry": {"coordinates":[-5.6817507744,38.2607765198],"type":"Point"}
}