{
  "type": "Feature",
  "properties": {
    "addr:full":"Avda Federico Garcia Lorca, 30 Cieza Murcia 30530",
    "addr:housenumber":"30",
    "addr:postcode":"30530",
    "addr:street":"Avda Federico Garcia Lorca",
    "iso:country":"ES",
    "sg:address":"Avda Federico Garcia Lorca, 30",
    "sg:city":"Cieza",
    "sg:orig_category":"T\u00c9cnicos Veterinarios",
    "sg:phone":"+34 968 45 65 16",
    "sg:postcode":"30530",
    "sg:province":"Murcia",
    "wof:name":"Gomez Varela Maria Luisa",
    "wof:placetype":"venue"
},
  "geometry": {"coordinates":[-1.4138089418,38.2388305664],"type":"Point"}
}