{
  "type": "Feature",
  "properties": {
    "iso:country":"ES",
    "sg:address":"Calle de Carlos Sole, S/n",
    "sg:city":"Madrid",
    "sg:orig_category":"Centros P\u00dablicos De Formaci\u00d3n Profesional Y T\u00c9cnica",
    "sg:phone":"+34 913 80 44 44",
    "sg:postcode":"28038",
    "sg:province":"Madrid",
    "wof:name":"Ies Tirso De Molina",
    "wof:placetype":"venue"
},
  "geometry": {"coordinates":[-3.6510341167,40.3942070007],"type":"Point"}
}