{
  "type": "Feature",
  "properties": {
    "iso:country":"ES",
    "sg:address":"Plaz San Juan De La Cruz, 8",
    "sg:city":"Madrid",
    "sg:orig_category":"Ingenier\u00cda, Centros De Estudios (diversos)",
    "sg:phone":"+34 915 33 46 16",
    "sg:postcode":"28003",
    "sg:province":"Madrid",
    "wof:name":"Copredije S.a.",
    "wof:placetype":"venue"
},
  "geometry": {"coordinates":[-3.6948590279,40.4415550232],"type":"Point"}
}