{
  "type": "Feature",
  "properties": {
    "iso:country":"ES",
    "sg:address":"Pg Pau Casals (de), 137",
    "sg:city":"Pineda",
    "sg:orig_category":"Centros Empresariales",
    "sg:phone":"+34 977 37 18 94",
    "sg:postcode":"43480",
    "sg:province":"Tarragona",
    "wof:name":"Portillo Lataza S.l",
    "wof:placetype":"venue"
},
  "geometry": {"coordinates":[1.1441899538,41.1080245972],"type":"Point"}
}