{
  "type": "Feature",
  "properties": {
    "iso:country":"ES",
    "sg:address":"Calle de Jacinto Benavente, 11",
    "sg:city":"Bu\u00f1ol",
    "sg:orig_category":"Asociaciones Y Clubs Deportivos",
    "sg:phone":"+34 962 50 07 82",
    "sg:postcode":"46360",
    "sg:province":"Valencia",
    "wof:name":"Solaz Criado Vicenta",
    "wof:placetype":"venue"
},
  "geometry": {"coordinates":[-0.792362988,39.4211082458],"type":"Point"}
}