{
  "type": "Feature",
  "properties": {
    "addr:full":"Carrer de Falset (de), 6 Salou Tarragona 43840",
    "addr:housenumber":"6",
    "addr:postcode":"43840",
    "addr:street":"Carrer De Falset De",
    "iso:country":"ES",
    "sg:address":"Carrer de Falset (de), 6",
    "sg:city":"Salou",
    "sg:orig_category":"Bares, Piano",
    "sg:phone":"+34 977 35 18 14",
    "sg:postcode":"43840",
    "sg:province":"Tarragona",
    "sg:website":"www.salou.co.uca",
    "wof:name":"Paris 2000 S.l.",
    "wof:placetype":"venue"
},
  "geometry": {"coordinates":[1.147761941,41.0713310242],"type":"Point"}
}