{
  "type": "Feature",
  "properties": {
    "addr:full":"Calle de Alameda Las Llanas, 14 Sestao Vizcaya 48910",
    "addr:housenumber":"14",
    "addr:postcode":"48910",
    "addr:street":"Calle De Alameda Las Llanas",
    "iso:country":"ES",
    "sg:address":"Calle de Alameda Las Llanas, 14",
    "sg:city":"Sestao",
    "sg:orig_category":"Electricidad: Instaladores",
    "sg:phone":"+34 944 95 51 46",
    "sg:postcode":"48910",
    "sg:province":"Vizcaya",
    "wof:name":"Electricidad Las Llanas C.b.",
    "wof:placetype":"venue"
},
  "geometry": {"coordinates":[-3.0099687576,43.3101463318],"type":"Point"}
}