{
  "type": "Feature",
  "properties": {
    "iso:country":"ES",
    "sg:address":"Carrer de Bilbao, S/n",
    "sg:city":"Playa Muchavista",
    "sg:orig_category":"Empresarios",
    "sg:phone":"+34 965 65 28 80",
    "sg:postcode":"03560",
    "sg:province":"Alicante",
    "wof:name":"Enrique Ortiz E Hijos Contratistas De Obras S.a.",
    "wof:placetype":"venue"
},
  "geometry": {"coordinates":[-0.4065710008,38.4001502991],"type":"Point"}
}