{
  "type": "Feature",
  "properties": {
    "iso:country":"ES",
    "sg:address":"Calle de Valverde, 13",
    "sg:city":"Madrid",
    "sg:orig_category":"Cooperativas Agr\u00cdcolas",
    "sg:phone":"+34 915 32 24 88",
    "sg:postcode":"28004",
    "sg:province":"Madrid",
    "sg:website":"www.ucmta.org",
    "wof:name":"Union De Cooperativas Madrile\u00f1as De Trabajo Asociado",
    "wof:placetype":"venue"
},
  "geometry": {"coordinates":[-3.7021551132,40.4213943481],"type":"Point"}
}