{
  "type": "Feature",
  "properties": {
    "iso:country":"ES",
    "sg:address":"Calle de Doctor Francino, 3",
    "sg:city":"Hinojosa Del Duque",
    "sg:orig_category":"Servicios Gsm",
    "sg:phone":"+34 957 14 05 97",
    "sg:postcode":"14270",
    "sg:province":"C\u00f3rdoba",
    "wof:name":"Luna Garcia Carmen Lucia",
    "wof:placetype":"venue"
},
  "geometry": {"coordinates":[-5.1481595039,38.4993171692],"type":"Point"}
}