{
  "type": "Feature",
  "properties": {
    "addr:full":"Calle de Tomas Breton, 23 Zaragoza Zaragoza 50005",
    "addr:housenumber":"23",
    "addr:postcode":"50005",
    "addr:street":"Calle De Tomas Breton",
    "iso:country":"ES",
    "sg:address":"Calle de Tomas Breton, 23",
    "sg:city":"Zaragoza",
    "sg:orig_category":"Estilistas Y Estudios De Estilo De Corte Y Confecci\u00d3n",
    "sg:phone":"+34 976 35 33 05",
    "sg:postcode":"50005",
    "sg:province":"Zaragoza",
    "wof:name":"Bartolome Guzman Maria Jesus",
    "wof:placetype":"venue"
},
  "geometry": {"coordinates":[-0.8961240053,41.6445350647],"type":"Point"}
}