{
  "type": "Feature",
  "properties": {
    "iso:country":"ES",
    "sg:address":"Polig. Indust. Chacon, S/n",
    "sg:city":"Fuente Palmera",
    "sg:orig_category":"Promotores Constructores",
    "sg:phone":"+34 957 63 87 73",
    "sg:postcode":"14120",
    "sg:province":"C\u00f3rdoba",
    "wof:name":"Esprocon Sociedad Cooperativa Andaluza",
    "wof:placetype":"venue"
},
  "geometry": {"coordinates":[-5.0964288712,37.7094764709],"type":"Point"}
}