{
  "type": "Feature",
  "properties": {
    "iso:country":"ES",
    "sg:address":"Calle de Francisco Pizarro, 22",
    "sg:city":"Almendralejo",
    "sg:orig_category":"Asesor\u00cda Fiscal Y Jur\u00cddica",
    "sg:phone":"+34 924 66 27 63",
    "sg:postcode":"06200",
    "sg:province":"Badajoz",
    "wof:name":"Nieto Perez Manuel",
    "wof:placetype":"venue"
},
  "geometry": {"coordinates":[-6.4043312073,38.6826286316],"type":"Point"}
}