{
  "type": "Feature",
  "properties": {
    "addr:full":"Plaz Santa Catalina, 6 San Pedro Murcia 30004",
    "addr:housenumber":"6",
    "addr:postcode":"30004",
    "addr:street":"Santa Catalina",
    "iso:country":"ES",
    "sg:address":"Plaz Santa Catalina, 6",
    "sg:city":"San Pedro",
    "sg:orig_category":"Bisuter\u00cda, Joyer\u00cda, Relojer\u00cda (al Por Menor)",
    "sg:phone":"+34 968 21 40 08",
    "sg:postcode":"30004",
    "sg:province":"Murcia",
    "wof:name":"Reverte Santoyo Francisco Javier",
    "wof:placetype":"venue"
},
  "geometry": {"coordinates":[-1.1312810183,37.9851264954],"type":"Point"}
}