{
  "type": "Feature",
  "properties": {
    "iso:country":"ES",
    "sg:address":"Calle de Pamplona, S/n",
    "sg:city":"Merida",
    "sg:orig_category":"Restaurantes",
    "sg:phone":"+34 924 37 42 07",
    "sg:postcode":"06800",
    "sg:province":"Badajoz",
    "wof:name":"Gonzalez De Pablo Antonio",
    "wof:placetype":"venue"
},
  "geometry": {"coordinates":[-6.3892741203,38.9266242981],"type":"Point"}
}