{
  "type": "Feature",
  "properties": {
    "addr:full":"Carr Unio, 10 Algaida Islas Baleares 07210",
    "addr:housenumber":"10",
    "addr:postcode":"07210",
    "addr:street":"Carr Unio",
    "iso:country":"ES",
    "sg:address":"Carr Unio, 10",
    "sg:city":"Algaida",
    "sg:orig_category":"Supermercados Y Hipermercados",
    "sg:phone":"+34 971 66 51 04",
    "sg:postcode":"07210",
    "sg:province":"Islas Baleares",
    "wof:name":"Roca Jaume Miguel",
    "wof:placetype":"venue"
},
  "geometry": {"coordinates":[2.9009900093,39.5650901794],"type":"Point"}
}