{
  "type": "Feature",
  "properties": {
    "addr:full":"Calle de Corona De Aragon, 12 Barbastro Huesca 22300",
    "addr:housenumber":"12",
    "addr:postcode":"22300",
    "addr:street":"Calle De Corona De Aragon",
    "iso:country":"ES",
    "sg:address":"Calle de Corona De Aragon, 12",
    "sg:city":"Barbastro",
    "sg:orig_category":"Confecci\u00d3n (fabricaci\u00d3n, Al Por Mayor)",
    "sg:phone":"+34 974 31 51 93",
    "sg:postcode":"22300",
    "sg:province":"Huesca",
    "wof:name":"Gonzalez Hernandez Adrian",
    "wof:placetype":"venue"
},
  "geometry": {"coordinates":[0.1275749952,42.036403656],"type":"Point"}
}