{
  "type": "Feature",
  "properties": {
    "addr:full":"Ctra Ronda (de), S/n Almeria Almer\u00eda 04004",
    "addr:housenumber":"/ n",
    "addr:postcode":"04004",
    "addr:street":"Ctra Ronda De S",
    "iso:country":"ES",
    "sg:address":"Ctra Ronda (de), S/n",
    "sg:city":"Almeria",
    "sg:orig_category":"Asesor\u00cda Fiscal Y Jur\u00cddica",
    "sg:phone":"+34 950 26 33 76",
    "sg:postcode":"04004",
    "sg:province":"Almer\u00eda",
    "wof:name":"Vending Mediterraneo S.l.",
    "wof:placetype":"venue"
},
  "geometry": {"coordinates":[-2.4607589245,36.8334960938],"type":"Point"}
}