{
  "type": "Feature",
  "properties": {
    "addr:full":"Calle de Fermin Caballero, 56 Madrid Madrid 28034",
    "addr:housenumber":"56",
    "addr:postcode":"madrid;28034",
    "addr:street":"Calle De Fermin Caballero",
    "iso:country":"ES",
    "sg:address":"Calle de Fermin Caballero, 56",
    "sg:city":"Madrid",
    "sg:orig_category":"Florister\u00cdas",
    "sg:phone":"+34 917 31 03 02",
    "sg:postcode":"28034",
    "sg:province":"Madrid",
    "wof:name":"Ruiz Espinel Miguel",
    "wof:placetype":"venue"
},
  "geometry": {"coordinates":[-3.7077860832,40.4836006165],"type":"Point"}
}