{
  "type": "Feature",
  "properties": {
    "addr:full":"Calle de Policarpo Herrero, 13 Oviedo Asturias 33006",
    "addr:housenumber":"13",
    "addr:postcode":"33006",
    "addr:street":"Calle De Policarpo Herrero",
    "iso:country":"ES",
    "sg:address":"Calle de Policarpo Herrero, 13",
    "sg:city":"Oviedo",
    "sg:orig_category":"Promotores Constructores",
    "sg:phone":"+34 985 24 63 07",
    "sg:postcode":"33006",
    "sg:province":"Asturias",
    "wof:name":"Fiaga S.a.",
    "wof:placetype":"venue"
},
  "geometry": {"coordinates":[-5.8611760139,43.3572387695],"type":"Point"}
}