{
  "type": "Feature",
  "properties": {
    "iso:country":"ES",
    "sg:address":"Ctra Mami A Viator (del), S/n",
    "sg:city":"Ca\u00e7ada De San Urbano",
    "sg:classifiers":[
        {
            "category":"Manufacturing",
            "subcategory":"Building Materials",
            "type":"Manufacturing & Wholesale Goods"
        }
    ],
    "sg:phone":"+34 950 29 11 61",
    "sg:postcode":"04120",
    "sg:province":"Almer\u00eda",
    "sg:tags":[
        "cemento",
        "y",
        "de",
        "fabricaci\u00d3n",
        "cal"
    ],
    "wof:name":"Cementos Puma S.l.",
    "wof:placetype":"venue"
},
  "geometry": {"coordinates":[-2.4073739052,36.840511322],"type":"Point"}
}