{
  "type": "Feature",
  "properties": {
    "addr:full":"Calle de Condesa Vega Del Pozo, S/n Madrid Madrid 28032",
    "addr:housenumber":"s / n",
    "addr:postcode":"28032",
    "addr:street":"Calle De Condesa Vega Del Pozo",
    "iso:country":"ES",
    "sg:address":"Calle de Condesa Vega Del Pozo, S/n",
    "sg:city":"Madrid",
    "sg:orig_category":"Carnicer\u00cdas, Carnicer\u00cdas",
    "sg:phone":"+34 917 76 48 60",
    "sg:postcode":"28032",
    "sg:province":"Madrid",
    "wof:name":"Del Rio Gomez Vicente Javier",
    "wof:placetype":"venue"
},
  "geometry": {"coordinates":[-3.6080451012,40.4036598206],"type":"Point"}
}