{
  "type": "Feature",
  "properties": {
    "iso:country":"ES",
    "sg:address":"Carrer de Muntaner, 44",
    "sg:city":"Barcelona",
    "sg:orig_category":"Grafistas",
    "sg:phone":"+34 934 51 25 25",
    "sg:postcode":"08011",
    "sg:province":"Barcelona",
    "sg:website":"www.studimajoral.com",
    "wof:name":"Majoral Majoral Albert",
    "wof:placetype":"venue"
},
  "geometry": {"coordinates":[2.1603798866,41.3860931396],"type":"Point"}
}