{
  "type": "Feature",
  "properties": {
    "iso:country":"ES",
    "sg:address":"Avda Carlos V, 34",
    "sg:city":"Carrizal",
    "sg:orig_category":"Bazares, Art\u00cdculos De Limpieza Y De Cocina (al Por Menor)",
    "sg:phone":"+34 928 12 47 58",
    "sg:postcode":"35240",
    "sg:province":"Las Palmas",
    "wof:name":"Lareso S.l.",
    "wof:placetype":"venue"
},
  "geometry": {"coordinates":[-15.4055452347,27.9108772278],"type":"Point"}
}