{
  "type": "Feature",
  "properties": {
    "addr:full":"Villafranca, 9 Iru\u00f1a Navarra 31015",
    "addr:housenumber":"9",
    "addr:postcode":"31015",
    "addr:street":"Villafranca",
    "iso:country":"ES",
    "sg:address":"Villafranca, 9",
    "sg:city":"Iru\u00f1a",
    "sg:orig_category":"Bricolaje, Herramientas (al Por Menor)",
    "sg:phone":"+34 948 14 14 25",
    "sg:postcode":"31015",
    "sg:province":"Navarra",
    "wof:name":"Joslumar Bricolaje S.l.",
    "wof:placetype":"venue"
},
  "geometry": {"coordinates":[-1.6311810017,42.8327789307],"type":"Point"}
}