{
  "type": "Feature",
  "properties": {
    "iso:country":"ES",
    "sg:address":"Gabiria Gunea, 3",
    "sg:city":"Gabiria",
    "sg:orig_category":"Centros De Educaci\u00d3n Especial",
    "sg:phone":"+34 943 88 07 34",
    "sg:postcode":"20217",
    "sg:province":"Guip\u00f9zcoa",
    "wof:name":"Ayuntamiento De Gabiria",
    "wof:placetype":"venue"
},
  "geometry": {"coordinates":[-2.2795989513,43.0502204895],"type":"Point"}
}