{
  "type": "Feature",
  "properties": {
    "iso:country":"ES",
    "sg:address":"Ctra Fte Tojar, S/n",
    "sg:city":"Castil Campos",
    "sg:orig_category":"Administraciones Regionales, Departamentales Y Locales",
    "sg:phone":"+34 957 55 64 20",
    "sg:postcode":"14815",
    "sg:province":"C\u00f3rdoba",
    "wof:name":"Entidad Local Autonoma De Castill De Campos",
    "wof:placetype":"venue"
},
  "geometry": {"coordinates":[-4.1459741592,37.5102310181],"type":"Point"}
}