{
  "type": "Feature",
  "properties": {
    "iso:country":"ES",
    "sg:address":"Carrer de Sant Blai (de), 19",
    "sg:city":"Tortosa",
    "sg:orig_category":"Panader\u00cdas, Panader\u00cdas",
    "sg:phone":"+34 977 44 15 41",
    "sg:postcode":"43500",
    "sg:province":"Tarragona",
    "wof:name":"Pallares Bonet Angel",
    "wof:placetype":"venue"
},
  "geometry": {"coordinates":[0.5217790008,40.8110656738],"type":"Point"}
}