{
  "type": "Feature",
  "properties": {
    "addr:full":"Calle de Virgen, 42 Linares Ja\u00e9n 23700",
    "addr:housenumber":"42",
    "addr:postcode":"23700",
    "addr:street":"Calle De Virgen;Jae\u0301N",
    "iso:country":"ES",
    "sg:address":"Calle de Virgen, 42",
    "sg:city":"Linares",
    "sg:orig_category":"Fabricaci\u00d3n De Muebles De Cocina",
    "sg:phone":"+34 953 65 31 36",
    "sg:postcode":"23700",
    "sg:province":"Ja\u00e9n",
    "wof:name":"Romero Rodriguez Manuel",
    "wof:placetype":"venue"
},
  "geometry": {"coordinates":[-3.6336219311,38.0977592468],"type":"Point"}
}