{
  "type": "Feature",
  "properties": {
    "addr:full":"Calle de Teresa Gil, 25 Valladolid Valladolid 47002",
    "addr:housenumber":"25",
    "addr:postcode":"47002",
    "addr:street":"Calle De Teresa Gil",
    "iso:country":"ES",
    "sg:address":"Calle de Teresa Gil, 25",
    "sg:city":"Valladolid",
    "sg:orig_category":"Electrodom\u00c9sticos (al Por Menor)",
    "sg:phone":"+34 983 39 69 47",
    "sg:postcode":"47002",
    "sg:province":"Valladolid",
    "wof:name":"Inversores 48-65 S.l.",
    "wof:placetype":"venue"
},
  "geometry": {"coordinates":[-4.7248840332,41.6497001648],"type":"Point"}
}