{
  "type": "Feature",
  "properties": {
    "addr:full":"Calle de Muralla Redonda, 2 Puebla Sanabria Zamora 49300",
    "addr:housenumber":"2",
    "addr:postcode":"49300",
    "addr:street":"Calle De Muralla Redonda;Sanabria Zamora",
    "iso:country":"ES",
    "sg:address":"Calle de Muralla Redonda, 2",
    "sg:city":"Puebla Sanabria",
    "sg:orig_category":"Procuradores",
    "sg:phone":"+34 980 62 02 03",
    "sg:postcode":"49300",
    "sg:province":"Zamora",
    "wof:name":"Pozas Requejo Margarita",
    "wof:placetype":"venue"
},
  "geometry": {"coordinates":[-6.6342282295,42.0524177551],"type":"Point"}
}