{
  "type": "Feature",
  "properties": {
    "iso:country":"ES",
    "sg:address":"Ctra Mas De Barberans, 70",
    "sg:city":"Raval De Cristo",
    "sg:orig_category":"Frutas Y Legumbres Secas (al Por Mayor)",
    "sg:phone":"+34 977 50 06 00",
    "sg:postcode":"43520",
    "sg:province":"Tarragona",
    "sg:website":"www.fut.es/-frupinsa/",
    "wof:name":"Frutos Y Piensos Inmaculada S. A.",
    "wof:placetype":"venue"
},
  "geometry": {"coordinates":[0.5002449751,40.8249855042],"type":"Point"}
}