{
  "type": "Feature",
  "properties": {
    "iso:country":"ES",
    "sg:address":"Carr Bisbe Abad I Lasierra, 2",
    "sg:city":"Eivissa",
    "sg:orig_category":"Asesor\u00cda Sobre Comunicaci\u00d3n De Empresas",
    "sg:phone":"+34 971 30 40 17",
    "sg:postcode":"07800",
    "sg:province":"Islas Baleares",
    "wof:name":"Juan Serapio Asesores S.l.",
    "wof:placetype":"venue"
},
  "geometry": {"coordinates":[1.4286819696,38.90832901],"type":"Point"}
}