{
  "type": "Feature",
  "properties": {
    "iso:country":"ES",
    "sg:address":"Calle de Projecte 21 - Poligono Industrial, S/n",
    "sg:city":"Catarroja",
    "sg:orig_category":"Construcciones Met\u00c1licas",
    "sg:phone":"+34 961 27 25 90",
    "sg:postcode":"46470",
    "sg:province":"Valencia",
    "wof:name":"Dhj2 Construcciones Metalicas S.l.",
    "wof:placetype":"venue"
},
  "geometry": {"coordinates":[-0.4032689929,39.4032859802],"type":"Point"}
}