{
  "type": "Feature",
  "properties": {
    "addr:full":"Cami Geganta (de La), 75 Mataro Barcelona 08302",
    "addr:postcode":"08302",
    "iso:country":"ES",
    "sg:address":"Cami Geganta (de La), 75",
    "sg:city":"Mataro",
    "sg:orig_category":"C\u00c1maras De Comercio E Industria, Oficios, Agricultura",
    "sg:phone":"+34 937 57 01 00",
    "sg:postcode":"08302",
    "sg:province":"Barcelona",
    "sg:website":"www.cambrabcn.es",
    "wof:name":"Camara Oficial De Comercio Industria Y Navegacion De Barcelona",
    "wof:placetype":"venue"
},
  "geometry": {"coordinates":[2.438503027,41.5425415039],"type":"Point"}
}