{
  "type": "Feature",
  "properties": {
    "addr:full":"Calle de Canga Arguelles, 2 Gijon Asturias 33202",
    "addr:housenumber":"2",
    "addr:postcode":"33202",
    "addr:street":"Calle De Canga Arguelles",
    "iso:country":"ES",
    "sg:address":"Calle de Canga Arguelles, 2",
    "sg:city":"Gijon",
    "sg:orig_category":"Encuadernaci\u00d3n E Impresi\u00d3n De Folletos",
    "sg:phone":"+34 985 37 40 46",
    "sg:postcode":"33202",
    "sg:province":"Asturias",
    "wof:name":"Ex-libris",
    "wof:placetype":"venue"
},
  "geometry": {"coordinates":[-5.6513776779,43.5378837585],"type":"Point"}
}