{
  "type": "Feature",
  "properties": {
    "addr:full":"Carrer de Francesc Macia, 2 Santpedor Barcelona 08251",
    "addr:housenumber":"2",
    "addr:postcode":"08251",
    "addr:street":"Carrer De Francesc Macia",
    "iso:country":"ES",
    "sg:address":"Carrer de Francesc Macia, 2",
    "sg:city":"Santpedor",
    "sg:orig_category":"Estaciones De Servicio",
    "sg:phone":"+34 938 27 27 75",
    "sg:postcode":"08251",
    "sg:province":"Barcelona",
    "wof:name":"Vila Prats Josefa",
    "wof:placetype":"venue"
},
  "geometry": {"coordinates":[1.8375070095,41.7867393494],"type":"Point"}
}