{
  "type": "Feature",
  "properties": {
    "iso:country":"ES",
    "sg:address":"Avda Santa Rita De Casia, 34",
    "sg:city":"Jinamar",
    "sg:orig_category":"Oficinas: Suministros Para (fabricaci\u00d3n, Al Por Mayor)",
    "sg:phone":"+34 928 71 20 16",
    "sg:postcode":"35017",
    "sg:province":"Las Palmas",
    "wof:name":"Centro De Repografia E Informatica De Las Palmas S.l.",
    "wof:placetype":"venue"
},
  "geometry": {"coordinates":[-15.4646606445,28.054693222],"type":"Point"}
}