{
  "type": "Feature",
  "properties": {
    "iso:country":"ES",
    "sg:address":"Carrer de Foneria, 26",
    "sg:city":"Barcelona",
    "sg:orig_category":"Carnicer\u00cdas, Carnicer\u00cdas",
    "sg:phone":"+34 933 32 64 44",
    "sg:postcode":"08038",
    "sg:province":"Barcelona",
    "wof:name":"Sanchez Marquez Angel",
    "wof:placetype":"venue"
},
  "geometry": {"coordinates":[2.1382629871,41.3602256775],"type":"Point"}
}