{
  "type": "Feature",
  "properties": {
    "addr:full":"Carrer de Sant Sebastia, 220 Sabadell Barcelona 08203",
    "addr:housenumber":"220",
    "addr:postcode":"08203",
    "addr:street":"Carrer De Sant Sebastia",
    "iso:country":"ES",
    "sg:address":"Carrer de Sant Sebastia, 220",
    "sg:city":"Sabadell",
    "sg:orig_category":"Empresas De Carpinter\u00cda Met\u00c1lica",
    "sg:phone":"+34 937 10 40 92",
    "sg:postcode":"08203",
    "sg:province":"Barcelona",
    "wof:name":"Cerrajeria Y Automatismos San Ramon S.l",
    "wof:placetype":"venue"
},
  "geometry": {"coordinates":[2.1070699692,41.5345420837],"type":"Point"}
}