{
  "type": "Feature",
  "properties": {
    "iso:country":"ES",
    "sg:address":"Calle de Alcaiceria De La Loza, 25",
    "sg:city":"Sevilla",
    "sg:orig_category":"Confecci\u00d3n De Sombreros Y Tocados",
    "sg:phone":"+34 954 22 23 20",
    "sg:postcode":"41004",
    "sg:province":"Sevilla",
    "wof:name":"Garcia Romero Antonio",
    "wof:placetype":"venue"
},
  "geometry": {"coordinates":[-5.9914493561,37.3903999329],"type":"Point"}
}