{
  "type": "Feature",
  "properties": {
    "iso:country":"ES",
    "sg:address":"Carrer de Guifre, 34",
    "sg:city":"Ulldecona",
    "sg:orig_category":"Frutas Y Legumbres Frescas (al Por Mayor)",
    "sg:phone":"+34 977 72 12 76",
    "sg:postcode":"43550",
    "sg:province":"Tarragona",
    "wof:name":"Fragadis S.l.",
    "wof:placetype":"venue"
},
  "geometry": {"coordinates":[0.444588989,40.5988807678],"type":"Point"}
}