{
  "type": "Feature",
  "properties": {
    "addr:full":"Calle de Baleares, 6 Toledo Toledo 45005",
    "addr:housenumber":"6",
    "addr:postcode":"45005",
    "addr:street":"Calle De Baleares",
    "iso:country":"ES",
    "sg:address":"Calle de Baleares, 6",
    "sg:city":"Toledo",
    "sg:orig_category":"Supermercados Y Hipermercados",
    "sg:phone":"+34 925 22 39 93",
    "sg:postcode":"45005",
    "sg:province":"Toledo",
    "wof:name":"Super Bonilla S.a.",
    "wof:placetype":"venue"
},
  "geometry": {"coordinates":[-4.0357451439,39.872795105],"type":"Point"}
}