{
  "type": "Feature",
  "properties": {
    "iso:country":"ES",
    "sg:address":"Carrer de Galceran De Pinos, 19",
    "sg:city":"Romanica",
    "sg:orig_category":"Promotores Constructores",
    "sg:phone":"+34 937 18 58 35",
    "sg:postcode":"08210",
    "sg:province":"Barcelona",
    "wof:name":"Concepto Espacio Y Desarrollo Sl",
    "wof:placetype":"venue"
},
  "geometry": {"coordinates":[2.1271760464,41.5150566101],"type":"Point"}
}