{
  "type": "Feature",
  "properties": {
    "iso:country":"ES",
    "sg:address":"Avda Portugal (de), 26",
    "sg:city":"San Jose",
    "sg:orig_category":"Cr\u00cda De Animales",
    "sg:phone":"+34 968 46 39 71",
    "sg:postcode":"30800",
    "sg:province":"Murcia",
    "wof:name":"Diaz Gonzalez Jose",
    "wof:placetype":"venue"
},
  "geometry": {"coordinates":[-1.6905640364,37.680557251],"type":"Point"}
}