{
  "type": "Feature",
  "properties": {
    "iso:country":"ES",
    "sg:address":"Calle de Alcala, 295",
    "sg:city":"Madrid",
    "sg:orig_category":"Agencias De Viajes",
    "sg:phone":"+34 914 05 06 93",
    "sg:postcode":"28027",
    "sg:province":"Madrid",
    "wof:name":"Hersan Tour S.l.",
    "wof:placetype":"venue"
},
  "geometry": {"coordinates":[-3.653396368,40.4323806763],"type":"Point"}
}