{
  "type": "Feature",
  "properties": {
    "addr:full":"Calle de Juan De Belvis, 1 Plasencia C\u00e1ceres 10600",
    "addr:housenumber":"1",
    "addr:postcode":"10600",
    "addr:street":"Calle De Juan De Belvis;Ca\u0301Ceres",
    "iso:country":"ES",
    "sg:address":"Calle de Juan De Belvis, 1",
    "sg:city":"Plasencia",
    "sg:orig_category":"Procuradores",
    "sg:phone":"+34 927 42 12 05",
    "sg:postcode":"10600",
    "sg:province":"C\u00e1ceres",
    "wof:name":"Frutos Sierra Jose Carlos",
    "wof:placetype":"venue"
},
  "geometry": {"coordinates":[-6.0855288506,40.0329399109],"type":"Point"}
}