{
  "type": "Feature",
  "properties": {
    "iso:country":"ES",
    "sg:address":"Carrer de Bourg De Peage, S/n",
    "sg:city":"S. Feliu Guixols",
    "sg:orig_category":"Ense\u00d1anza, Formaci\u00d3n Profesional: Aprendizaje",
    "sg:phone":"+34 972 32 43 14",
    "sg:postcode":"17220",
    "sg:province":"Girona",
    "wof:name":"Consorci Assistencial Del Baix Emporda",
    "wof:placetype":"venue"
},
  "geometry": {"coordinates":[3.0343549252,41.7841567993],"type":"Point"}
}