{
  "type": "Feature",
  "properties": {
    "iso:country":"ES",
    "sg:address":"Calle de Mayor, 33",
    "sg:city":"Valdepe\u00e7as De La Sierra",
    "sg:orig_category":"Iglesia Cat\u00d3lica",
    "sg:phone":"+34 949 85 41 25",
    "sg:postcode":"19184",
    "sg:province":"Guadalajara",
    "wof:name":"Parroquia Nuestra Se\u00f1ora De La Purificacion",
    "wof:placetype":"venue"
},
  "geometry": {"coordinates":[-3.3715391159,40.8428688049],"type":"Point"}
}