{
  "type": "Feature",
  "properties": {
    "addr:full":"C/ Sant Joan, 8 Tarrega Lleida 25300",
    "addr:housenumber":"8",
    "addr:postcode":"25300",
    "addr:street":"C / Sant Joan",
    "iso:country":"ES",
    "sg:address":"C/ Sant Joan, 8",
    "sg:city":"Tarrega",
    "sg:orig_category":"Peluquer\u00cdas, Peluquer\u00cda Mixta",
    "sg:phone":"+34 973 50 03 48",
    "sg:postcode":"25300",
    "sg:province":"Lleida",
    "wof:name":"Castillo Castell Sonia",
    "wof:placetype":"venue"
},
  "geometry": {"coordinates":[1.138964057,41.6471099854],"type":"Point"}
}