{
  "type": "Feature",
  "properties": {
    "iso:country":"ES",
    "sg:address":"Cmno San Martin, 56",
    "sg:city":"Marchamalo",
    "sg:orig_category":"Cooperativas Agr\u00cdcolas",
    "sg:phone":"+34 949 25 23 41",
    "sg:postcode":"19180",
    "sg:province":"Guadalajara",
    "wof:name":"Asociacion Local De Agricultores Y Ganaderos De Marchamalo",
    "wof:placetype":"venue"
},
  "geometry": {"coordinates":[-3.2009615898,40.6682090759],"type":"Point"}
}