{
  "type": "Feature",
  "properties": {
    "iso:country":"ES",
    "sg:address":"Carrer de Dos De Maig, 74",
    "sg:city":"Viladecans",
    "sg:orig_category":"Reposter\u00cdas",
    "sg:phone":"+34 936 58 78 05",
    "sg:postcode":"08840",
    "sg:province":"Barcelona",
    "wof:name":"Vilapan S. A.",
    "wof:placetype":"venue"
},
  "geometry": {"coordinates":[2.0100359917,41.3199157715],"type":"Point"}
}