{
  "type": "Feature",
  "properties": {
    "addr:full":"Calle de Cadiz, S/n Cumbres Mayores Huelva 21380",
    "addr:housenumber":"s / n",
    "addr:postcode":"21380",
    "addr:street":"Calle De Cadiz",
    "iso:country":"ES",
    "sg:address":"Calle de Cadiz, S/n",
    "sg:city":"Cumbres Mayores",
    "sg:orig_category":"Empresas De Carpinter\u00cda Met\u00c1lica",
    "sg:phone":"+34 959 71 05 78",
    "sg:postcode":"21380",
    "sg:province":"Huelva",
    "wof:name":"Cerrajeria Cano S.l.",
    "wof:placetype":"venue"
},
  "geometry": {"coordinates":[-6.6466088295,38.0592346191],"type":"Point"}
}