{
  "type": "Feature",
  "properties": {
    "addr:full":"Calle de Vendederas, 11 Andujar Ja\u00e9n 23740",
    "addr:housenumber":"11",
    "addr:postcode":"23740",
    "addr:street":"Calle De Vendederas",
    "iso:country":"ES",
    "sg:address":"Calle de Vendederas, 11",
    "sg:city":"Andujar",
    "sg:orig_category":"Promotores Constructores",
    "sg:phone":"+34 953 51 06 15",
    "sg:postcode":"23740",
    "sg:province":"Ja\u00e9n",
    "wof:name":"Blanque Constructora & Promotora, S.l.u.",
    "wof:placetype":"venue"
},
  "geometry": {"coordinates":[-4.0572719574,38.0402259827],"type":"Point"}
}