{
  "type": "Feature",
  "properties": {
    "addr:full":"Carrer de Parlament, 26 Amposta Tarragona 43870",
    "addr:housenumber":"26",
    "addr:postcode":"43870",
    "addr:street":"Carrer De Parlament",
    "iso:country":"ES",
    "sg:address":"Carrer de Parlament, 26",
    "sg:city":"Amposta",
    "sg:orig_category":"Empresarios",
    "sg:phone":"+34 977 70 25 00",
    "sg:postcode":"43870",
    "sg:province":"Tarragona",
    "wof:name":"Construccions Rustiques I Urbanes",
    "wof:placetype":"venue"
},
  "geometry": {"coordinates":[0.5789999962,40.7116355896],"type":"Point"}
}