{
  "type": "Feature",
  "properties": {
    "iso:country":"ES",
    "sg:address":"Rbla Rambla, 173",
    "sg:city":"Sabadell",
    "sg:orig_category":"Agencias De Viajes",
    "sg:phone":"+34 937 27 01 66",
    "sg:postcode":"08202",
    "sg:province":"Barcelona",
    "sg:website":"www.bestours.es",
    "wof:name":"Bestours S.a.",
    "wof:placetype":"venue"
},
  "geometry": {"coordinates":[2.1117269993,41.5414619446],"type":"Point"}
}