{
  "type": "Feature",
  "properties": {
    "iso:country":"ES",
    "sg:address":"General Prim, 117",
    "sg:city":"Lora Rio",
    "sg:orig_category":"Formaci\u00d3n Continuada (variada)",
    "sg:phone":"+34 955 80 19 05",
    "sg:postcode":"41440",
    "sg:province":"Sevilla",
    "wof:name":"Lopez Alvarez Rafael",
    "wof:placetype":"venue"
},
  "geometry": {"coordinates":[-5.5281839371,37.659828186],"type":"Point"}
}