{
  "type": "Feature",
  "properties": {
    "addr:full":"Avda Diputacion, 10 Labastida \u00c1lava 01330",
    "addr:housenumber":"10",
    "addr:postcode":"01330",
    "addr:street":"Avda Diputacion;A\u0301Lava",
    "iso:country":"ES",
    "sg:address":"Avda Diputacion, 10",
    "sg:city":"Labastida",
    "sg:orig_category":"Centros De Coordinaci\u00d3n",
    "sg:phone":"+34 945 33 10 41",
    "sg:postcode":"01330",
    "sg:province":"\u00c1lava",
    "wof:name":"Gestoria Altuna Sc",
    "wof:placetype":"venue"
},
  "geometry": {"coordinates":[-2.796833992,42.5905838013],"type":"Point"}
}