{
  "type": "Feature",
  "properties": {
    "iso:country":"ES",
    "sg:address":"Calle de San Francisco, 85",
    "sg:city":"Bilbao",
    "sg:orig_category":"Sociedades, Compa\u00d1\u00cdas Aseguradoras",
    "sg:phone":"+34 944 35 26 45",
    "sg:postcode":"48003",
    "sg:province":"Vizcaya",
    "wof:name":"Seguros Y Gestion De Seguros Segurbil, S.l.",
    "wof:placetype":"venue"
},
  "geometry": {"coordinates":[-2.9337010384,43.2570724487],"type":"Point"}
}