{
  "type": "Feature",
  "properties": {
    "iso:country":"ES",
    "sg:address":"Calle de Oca, 56",
    "sg:city":"Madrid",
    "sg:orig_category":"Zapatos (al Por Menor)",
    "sg:phone":"+34 914 61 06 61",
    "sg:postcode":"28025",
    "sg:province":"Madrid",
    "wof:name":"Alegre Pazos Maria Isabel",
    "wof:placetype":"venue"
},
  "geometry": {"coordinates":[-3.7377345562,40.3892402649],"type":"Point"}
}