{
  "type": "Feature",
  "properties": {
    "addr:full":"Carrer de Independencia, 98 Hospitalet Llobregat Barcelona 08902",
    "addr:housenumber":"98",
    "addr:postcode":"08902",
    "addr:street":"Carrer De Independencia",
    "iso:country":"ES",
    "sg:address":"Carrer de Independencia, 98",
    "sg:city":"Hospitalet Llobregat",
    "sg:orig_category":"Maquinaria Para Industrias Diversas",
    "sg:phone":"+34 932 61 81 65",
    "sg:postcode":"08902",
    "sg:province":"Barcelona",
    "wof:name":"Miretti Iberica S.a.",
    "wof:placetype":"venue"
},
  "geometry": {"coordinates":[2.1248459816,41.360496521],"type":"Point"}
}