{
  "type": "Feature",
  "properties": {
    "iso:country":"ES",
    "sg:address":"Carr Cano, 8",
    "sg:city":"Besalu",
    "sg:orig_category":"Alimentaci\u00d3n General (al Por Menor)",
    "sg:phone":"+34 972 59 11 13",
    "sg:postcode":"17850",
    "sg:province":"Girona",
    "wof:name":"Compta Gratacos Dolores",
    "wof:placetype":"venue"
},
  "geometry": {"coordinates":[2.7091920376,42.2370147705],"type":"Point"}
}