{
  "type": "Feature",
  "properties": {
    "addr:full":"Puig-pedros, 13 Puigcerda Girona 17520",
    "addr:housenumber":"13",
    "addr:postcode":"17520",
    "addr:street":"Puig-Pedros",
    "iso:country":"ES",
    "sg:address":"Puig-pedros, 13",
    "sg:city":"Puigcerda",
    "sg:orig_category":"Inmobiliaria (agencias)",
    "sg:phone":"+34 972 88 09 26",
    "sg:postcode":"17520",
    "sg:province":"Girona",
    "wof:name":"Infanta Carlota 123 S.l.",
    "wof:placetype":"venue"
},
  "geometry": {"coordinates":[1.9249520302,42.4333114624],"type":"Point"}
}