{
  "type": "Feature",
  "properties": {
    "iso:country":"ES",
    "sg:address":"Calle de Ense\u00d1anza, 4",
    "sg:city":"Llosa",
    "sg:orig_category":"Iglesia Cat\u00d3lica",
    "sg:phone":"+34 962 61 04 24",
    "sg:postcode":"12591",
    "sg:province":"Castell\u00f3n",
    "wof:name":"Parroquia El Salvador",
    "wof:placetype":"venue"
},
  "geometry": {"coordinates":[-0.2043153048,39.7683944702],"type":"Point"}
}