{
  "type": "Feature",
  "properties": {
    "addr:full":"Carrer de Francesc Macia, 15 Papiol Barcelona 08754",
    "addr:housenumber":"15",
    "addr:postcode":"08754",
    "addr:street":"Carrer De Francesc Macia",
    "iso:country":"ES",
    "sg:address":"Carrer de Francesc Macia, 15",
    "sg:city":"Papiol",
    "sg:orig_category":"Hielo Artificial (fabricaci\u00d3n, Distribuci\u00d3n)",
    "sg:phone":"+34 936 73 11 50",
    "sg:postcode":"08754",
    "sg:province":"Barcelona",
    "wof:name":"Rabasco Sanchez Salvador",
    "wof:placetype":"venue"
},
  "geometry": {"coordinates":[2.0096590519,41.4392318726],"type":"Point"}
}