{
  "type": "Feature",
  "properties": {
    "addr:full":"Pg Estacio, 1 Balaguer Lleida 25600",
    "addr:housenumber":"1",
    "addr:postcode":"25600",
    "addr:street":"Pg Estacio",
    "iso:country":"ES",
    "sg:address":"Pg Estacio, 1",
    "sg:city":"Balaguer",
    "sg:orig_category":"Servicios Gsm",
    "sg:phone":"+34 973 44 37 86",
    "sg:postcode":"25600",
    "sg:province":"Lleida",
    "wof:name":"T & C Telefonia I Comunicacions S.l.",
    "wof:placetype":"venue"
},
  "geometry": {"coordinates":[0.8085449934,41.7896614075],"type":"Point"}
}