{
  "type": "Feature",
  "properties": {
    "addr:full":"Calle de Corredera (la), 21 Villena Alicante 03400",
    "addr:housenumber":"21",
    "addr:postcode":"03400",
    "addr:street":"Calle De Corredera La",
    "iso:country":"ES",
    "sg:address":"Calle de Corredera (la), 21",
    "sg:city":"Villena",
    "sg:orig_category":"Cooperativas Agr\u00cdcolas",
    "sg:phone":"+34 965 80 00 54",
    "sg:postcode":"03400",
    "sg:province":"Alicante",
    "wof:name":"Circulo Agricola Mercantil",
    "wof:placetype":"venue"
},
  "geometry": {"coordinates":[-0.8642073274,38.6305656433],"type":"Point"}
}