{
  "type": "Feature",
  "properties": {
    "iso:country":"ES",
    "sg:address":"Carr Ciutadans, 4",
    "sg:city":"Girona",
    "sg:orig_category":"Alimentaci\u00d3n General (al Por Menor)",
    "sg:phone":"+34 972 20 09 58",
    "sg:postcode":"17004",
    "sg:province":"Girona",
    "wof:name":"Moriscot Pidemunt Enrique",
    "wof:placetype":"venue"
},
  "geometry": {"coordinates":[2.8250880241,41.9833908081],"type":"Point"}
}