{
  "type": "Feature",
  "properties": {
    "iso:country":"ES",
    "sg:address":"Calle de Ruiz Pons, 13",
    "sg:city":"Bu\u00f1ol",
    "sg:orig_category":"Bosques (trabajos, Asesor\u00cda, Gesti\u00d3n)",
    "sg:phone":"+34 962 50 24 91",
    "sg:postcode":"46360",
    "sg:province":"Valencia",
    "sg:website":"www.isd.es",
    "wof:name":"Integral De Servicios Bu\u00f1ol S.l.",
    "wof:placetype":"venue"
},
  "geometry": {"coordinates":[-0.7886080146,39.4183502197],"type":"Point"}
}