{
  "type": "Feature",
  "properties": {
    "addr:full":"Calle de Conde De Altea, 53 Altea Alicante 03590",
    "addr:housenumber":"53",
    "addr:postcode":"03590",
    "addr:street":"Calle De Conde De Altea",
    "iso:country":"ES",
    "sg:address":"Calle de Conde De Altea, 53",
    "sg:city":"Altea",
    "sg:orig_category":"Institutos De Belleza",
    "sg:phone":"+34 966 88 56 37",
    "sg:postcode":"03590",
    "sg:province":"Alicante",
    "wof:name":"Silvestre Morcillo Eva",
    "wof:placetype":"venue"
},
  "geometry": {"coordinates":[-0.0452839993,38.6028747559],"type":"Point"}
}