{
  "type": "Feature",
  "properties": {
    "iso:country":"ES",
    "sg:address":"Calle de Alonso Cano, 9",
    "sg:city":"Madrid",
    "sg:orig_category":"Farmacias",
    "sg:phone":"+34 914 47 31 30",
    "sg:postcode":"28010",
    "sg:province":"Madrid",
    "wof:name":"Villanueva Vigil De Qui\u00f1ones Maria Luisa",
    "wof:placetype":"venue"
},
  "geometry": {"coordinates":[-3.6981101036,40.4360198975],"type":"Point"}
}