{
  "type": "Feature",
  "properties": {
    "iso:country":"ES",
    "sg:address":"Calle de Rosario, 28",
    "sg:city":"Ranero",
    "sg:orig_category":"Carnicer\u00cdas, Carnicer\u00cdas",
    "sg:phone":"+34 968 29 69 60",
    "sg:postcode":"30100",
    "sg:province":"Murcia",
    "wof:name":"Galvez Travel Nicasio",
    "wof:placetype":"venue"
},
  "geometry": {"coordinates":[-1.153594017,38.0103034973],"type":"Point"}
}