{
  "type": "Feature",
  "properties": {
    "addr:full":"Calle de Camino, 5 Utiel Valencia 46300",
    "addr:housenumber":"5",
    "addr:postcode":"46300",
    "addr:street":"Calle De Camino",
    "iso:country":"ES",
    "sg:address":"Calle de Camino, 5",
    "sg:city":"Utiel",
    "sg:orig_category":"Internados & Ense\u00d1anza Privada",
    "sg:phone":"+34 962 17 11 40",
    "sg:postcode":"46300",
    "sg:province":"Valencia",
    "wof:name":"Colegio Santa Ana En Utiel Caridad De Santa Ana Prov Inmaculado Corazon De Maria",
    "wof:placetype":"venue"
},
  "geometry": {"coordinates":[-1.196849227,39.5676841736],"type":"Point"}
}