{
  "type": "Feature",
  "properties": {
    "iso:country":"ES",
    "sg:address":"D.irala Kalea, 3",
    "sg:city":"Bergara",
    "sg:orig_category":"Caf\u00c9s, Bares, Cervecer\u00cdas",
    "sg:phone":"+34 943 76 48 26",
    "sg:postcode":"20570",
    "sg:province":"Guip\u00f9zcoa",
    "wof:name":"Etxaniz Baskoetxea Moises",
    "wof:placetype":"venue"
},
  "geometry": {"coordinates":[-2.4131031036,43.1186027527],"type":"Point"}
}