{
  "type": "Feature",
  "properties": {
    "addr:full":"Avda Ausias March, 122 Valencia Valencia 46026",
    "addr:housenumber":"122",
    "addr:postcode":"46026",
    "addr:street":"Avda Ausias March",
    "iso:country":"ES",
    "sg:address":"Avda Ausias March, 122",
    "sg:city":"Valencia",
    "sg:orig_category":"Acero: Productos Sider\u00dargicos Y Transformados (fabricaci\u00d3n, Negocio)",
    "sg:phone":"+34 963 16 20 31",
    "sg:postcode":"46026",
    "sg:province":"Valencia",
    "wof:name":"Mecanizados S. A.",
    "wof:placetype":"venue"
},
  "geometry": {"coordinates":[-0.3690789938,39.4465484619],"type":"Point"}
}