{
  "type": "Feature",
  "properties": {
    "iso:country":"ES",
    "sg:address":"Calle de Ferrol, 11",
    "sg:city":"Cangas",
    "sg:orig_category":"Reposter\u00cdas",
    "sg:phone":"+34 986 30 58 65",
    "sg:postcode":"36940",
    "sg:province":"Pontevedra",
    "wof:name":"Maestu Martinez Jose Manuel",
    "wof:placetype":"venue"
},
  "geometry": {"coordinates":[-8.7799520493,42.2658309937],"type":"Point"}
}