{
  "type": "Feature",
  "properties": {
    "iso:country":"ES",
    "sg:address":"Plaz San Pedro, 3",
    "sg:city":"Bilbao",
    "sg:orig_category":"Cl\u00cdnicas Dentales",
    "sg:phone":"+34 944 76 11 11",
    "sg:postcode":"48014",
    "sg:province":"Vizcaya",
    "sg:website":"www.vitaldent.com",
    "wof:name":"Vital Deusto-dent S.l.",
    "wof:placetype":"venue"
},
  "geometry": {"coordinates":[-2.9235370159,43.2678070068],"type":"Point"}
}