{
  "type": "Feature",
  "properties": {
    "iso:country":"ES",
    "sg:address":"Calle de Caballero De Rodas, 25",
    "sg:city":"Torrevieja",
    "sg:orig_category":"Arquitectos",
    "sg:phone":"+34 965 70 73 78",
    "sg:postcode":"03180",
    "sg:province":"Alicante",
    "wof:name":"Alonso Jorreto Anselmo",
    "wof:placetype":"venue"
},
  "geometry": {"coordinates":[-0.6835740209,37.9777870178],"type":"Point"}
}