{
  "type": "Feature",
  "properties": {
    "iso:country":"ES",
    "sg:address":"Vidangoz, 1",
    "sg:city":"Iru\u00f1a",
    "sg:orig_category":"Empresarios",
    "sg:phone":"+34 948 36 37 03",
    "sg:postcode":"31014",
    "sg:province":"Navarra",
    "wof:name":"Fundacion Secretariado Gitano",
    "wof:placetype":"venue"
},
  "geometry": {"coordinates":[-1.6475617886,42.8279380798],"type":"Point"}
}