{
  "type": "Feature",
  "properties": {
    "iso:country":"ES",
    "sg:address":"Urb. Stio Calahonda, S/n",
    "sg:city":"Mijas Costa",
    "sg:orig_category":"M\u00c9dicos: Estomatolog\u00cda",
    "sg:phone":"+34 952 93 48 57",
    "sg:postcode":"29649",
    "sg:province":"M\u00e1laga",
    "wof:name":"Hooman  Rabiee",
    "wof:placetype":"venue"
},
  "geometry": {"coordinates":[-4.7327361107,36.4912872314],"type":"Point"}
}