{
  "type": "Feature",
  "properties": {
    "iso:country":"ES",
    "sg:address":"Calle de Vicente Blasco Iba\u00d1ez, 20",
    "sg:city":"Rafal",
    "sg:orig_category":"Centros Comerciales Y Grandes Tiendas",
    "sg:phone":"+34 966 75 29 65",
    "sg:postcode":"03369",
    "sg:province":"Alicante",
    "wof:name":"Vicente Bertomeu Virtudes",
    "wof:placetype":"venue"
},
  "geometry": {"coordinates":[-0.8478080034,38.1049041748],"type":"Point"}
}