{
  "type": "Feature",
  "properties": {
    "iso:country":"ES",
    "sg:address":"Carr Pizarro, 104",
    "sg:city":"Ca'n Picafort",
    "sg:orig_category":"Asociaciones Y Clubs Deportivos",
    "sg:phone":"+34 971 85 19 54",
    "sg:postcode":"07458",
    "sg:province":"Islas Baleares",
    "wof:name":"Fernandez Molina Jose Manuel",
    "wof:placetype":"venue"
},
  "geometry": {"coordinates":[3.1530723572,39.7624397278],"type":"Point"}
}