{
  "type": "Feature",
  "properties": {
    "addr:full":"Carr Creus, 29 Empuriabrava Girona 17487",
    "addr:housenumber":"29",
    "addr:postcode":"17487",
    "addr:street":"Carr Creus",
    "iso:country":"ES",
    "sg:address":"Carr Creus, 29",
    "sg:city":"Empuriabrava",
    "sg:orig_category":"Promotores Constructores",
    "sg:phone":"+34 972 45 02 92",
    "sg:postcode":"17487",
    "sg:province":"Girona",
    "wof:name":"Duffhues  Rudolph",
    "wof:placetype":"venue"
},
  "geometry": {"coordinates":[3.1070549488,42.2568092346],"type":"Point"}
}