{
  "type": "Feature",
  "properties": {
    "addr:full":"Calle de Marques De Pickman, 65 Sevilla Sevilla 41005",
    "addr:housenumber":"65",
    "addr:postcode":"41005",
    "addr:street":"Calle De Marques De Pickman",
    "iso:country":"ES",
    "sg:address":"Calle de Marques De Pickman, 65",
    "sg:city":"Sevilla",
    "sg:orig_category":"Cl\u00cdnicas Dentales",
    "sg:phone":"+34 954 58 44 35",
    "sg:postcode":"41005",
    "sg:province":"Sevilla",
    "wof:name":"Galan Gonzalez Antonio Francisco",
    "wof:placetype":"venue"
},
  "geometry": {"coordinates":[-5.9607191086,37.3812446594],"type":"Point"}
}