{
  "type": "Feature",
  "properties": {
    "addr:full":"Pase Facultades, 1 Valencia Valencia 46021",
    "addr:housenumber":"1",
    "addr:postcode":"46021",
    "addr:street":"Facultades",
    "iso:country":"ES",
    "sg:address":"Pase Facultades, 1",
    "sg:city":"Valencia",
    "sg:orig_category":"Fotocopias, Reprograf\u00cda",
    "sg:phone":"+34 963 39 10 63",
    "sg:postcode":"46021",
    "sg:province":"Valencia",
    "sg:website":"www.cems.es",
    "wof:name":"Cemscyber",
    "wof:placetype":"venue"
},
  "geometry": {"coordinates":[-0.3478280008,39.4768562317],"type":"Point"}
}