{
  "type": "Feature",
  "properties": {
    "iso:country":"ES",
    "sg:address":"Avda Principe De Asturias, 59",
    "sg:city":"Villaviciosa Odon",
    "sg:orig_category":"Veh\u00cdculos De Ocasi\u00d3n",
    "sg:phone":"+34 916 65 72 29",
    "sg:postcode":"28670",
    "sg:province":"Madrid",
    "wof:name":"Only Special Cars Sl",
    "wof:placetype":"venue"
},
  "geometry": {"coordinates":[-3.8669540882,40.3543052673],"type":"Point"}
}