{
  "type": "Feature",
  "properties": {
    "addr:full":"Av Francesc Macia, 5 Sitges Barcelona 08870",
    "addr:housenumber":"5",
    "addr:postcode":"08870",
    "addr:street":"Av Francesc Macia",
    "iso:country":"ES",
    "sg:address":"Av Francesc Macia, 5",
    "sg:city":"Sitges",
    "sg:orig_category":"Electricidad: Equipos Industriales, Componentes (fabricaci\u00d3n)",
    "sg:phone":"+34 938 94 32 08",
    "sg:postcode":"08870",
    "sg:province":"Barcelona",
    "wof:name":"Campillo Del Rio Jose Luis",
    "wof:placetype":"venue"
},
  "geometry": {"coordinates":[1.8170640469,41.2404937744],"type":"Point"}
}