{
  "type": "Feature",
  "properties": {
    "addr:full":"Calle de Ancha, 35 Lillo Toledo 45870",
    "addr:housenumber":"35",
    "addr:postcode":"45870",
    "addr:street":"Calle De Ancha",
    "iso:country":"ES",
    "sg:address":"Calle de Ancha, 35",
    "sg:city":"Lillo",
    "sg:orig_category":"Electrodom\u00c9sticos (al Por Menor)",
    "sg:phone":"+34 925 17 00 23",
    "sg:postcode":"45870",
    "sg:province":"Toledo",
    "wof:name":"Fernandez Martin Casimiro",
    "wof:placetype":"venue"
},
  "geometry": {"coordinates":[-3.3076372147,39.7227096558],"type":"Point"}
}