{
  "type": "Feature",
  "properties": {
    "iso:country":"ES",
    "sg:address":"Avda Torrelaguna (de), 9",
    "sg:city":"Azuqueca Henares",
    "sg:orig_category":"Colchones (fabricaci\u00d3n, Al Por Mayor, Al Por Menor)",
    "sg:phone":"+34 949 26 55 74",
    "sg:postcode":"19200",
    "sg:province":"Guadalajara",
    "wof:name":"Resudescanso S.l.",
    "wof:placetype":"venue"
},
  "geometry": {"coordinates":[-3.2657520771,40.5641746521],"type":"Point"}
}