{
  "type": "Feature",
  "properties": {
    "addr:full":"Pla\u00c7 Progres, 7 Benifaio Valencia 46450",
    "addr:housenumber":"7",
    "addr:postcode":"46450",
    "addr:street":"Progres",
    "iso:country":"ES",
    "sg:address":"Pla\u00c7 Progres, 7",
    "sg:city":"Benifaio",
    "sg:orig_category":"Cooperativas Agr\u00cdcolas",
    "sg:phone":"+34 961 78 38 54",
    "sg:postcode":"46450",
    "sg:province":"Valencia",
    "wof:name":"Asociacion Valenciana De Agricultores",
    "wof:placetype":"venue"
},
  "geometry": {"coordinates":[-0.4408037066,39.2886543274],"type":"Point"}
}