{
  "type": "Feature",
  "properties": {
    "addr:full":"Calle de Norte, 1 Casas De Haro Cuenca 16611",
    "addr:housenumber":"1",
    "addr:postcode":"16611",
    "addr:street":"Calle De Norte",
    "iso:country":"ES",
    "sg:address":"Calle de Norte, 1",
    "sg:city":"Casas De Haro",
    "sg:orig_category":"Producci\u00d3n De Champi\u00d1ones",
    "sg:phone":"+34 969 38 06 66",
    "sg:postcode":"16611",
    "sg:province":"Cuenca",
    "wof:name":"Champi\u00f1ones Covaleda S.l.",
    "wof:placetype":"venue"
},
  "geometry": {"coordinates":[-2.2726690769,39.3337211609],"type":"Point"}
}