{
  "type": "Feature",
  "properties": {
    "addr:full":"Avda Italia, 11 Huelva Huelva 21001",
    "addr:housenumber":"11",
    "addr:postcode":"21001",
    "addr:street":"Avda Italia",
    "iso:country":"ES",
    "sg:address":"Avda Italia, 11",
    "sg:city":"Huelva",
    "sg:orig_category":"Cl\u00cdnicas M\u00c9dicas",
    "sg:phone":"+34 959 25 77 00",
    "sg:postcode":"21001",
    "sg:province":"Huelva",
    "wof:name":"Araujo Quintero Julio",
    "wof:placetype":"venue"
},
  "geometry": {"coordinates":[-6.9554767609,37.2551231384],"type":"Point"}
}