{
  "type": "Feature",
  "properties": {
    "addr:full":"Calle de Estepa, 16 Sevilla Sevilla 41013",
    "addr:housenumber":"16",
    "addr:postcode":"41013",
    "addr:street":"Calle De Estepa",
    "iso:country":"ES",
    "sg:address":"Calle de Estepa, 16",
    "sg:city":"Sevilla",
    "sg:orig_category":"Molduras, Junquillos, Listones Y Molduras Perforadas",
    "sg:phone":"+34 954 61 10 21",
    "sg:postcode":"41013",
    "sg:province":"Sevilla",
    "wof:name":"Marquez Fernandez Josefa",
    "wof:placetype":"venue"
},
  "geometry": {"coordinates":[-5.9748401642,37.3696022034],"type":"Point"}
}