{
  "type": "Feature",
  "properties": {
    "iso:country":"ES",
    "sg:address":"Carrer de Jaume I, 88",
    "sg:city":"S. Boi Llobregat",
    "sg:orig_category":"Inmobiliaria (agencias)",
    "sg:phone":"+34 936 30 67 67",
    "sg:postcode":"08830",
    "sg:province":"Barcelona",
    "wof:name":"Alcarma Inmobiliaria S.l.",
    "wof:placetype":"venue"
},
  "geometry": {"coordinates":[2.0405704975,41.3450546265],"type":"Point"}
}