{
  "type": "Feature",
  "properties": {
    "iso:country":"ES",
    "sg:address":"Pol Ind Polirrosa, 130",
    "sg:city":"Huelva",
    "sg:orig_category":"Caf\u00c9s (al Por Menor)",
    "sg:phone":"+34 959 22 70 32",
    "sg:postcode":"21007",
    "sg:province":"Huelva",
    "wof:name":"Distribuciones Mar-picon S.l.",
    "wof:placetype":"venue"
},
  "geometry": {"coordinates":[-6.9495940208,37.256313324],"type":"Point"}
}