{
  "type": "Feature",
  "properties": {
    "iso:country":"ES",
    "sg:address":"Barr Igrexa (a), S/n",
    "sg:city":"Igrexa",
    "sg:orig_category":"Iglesia Cat\u00d3lica",
    "sg:phone":"+34 982 56 08 43",
    "sg:postcode":"27869",
    "sg:province":"Lugo",
    "wof:name":"Parroquia De San Ciprian",
    "wof:placetype":"venue"
},
  "geometry": {"coordinates":[-7.6162400246,43.6527366638],"type":"Point"}
}