{
  "type": "Feature",
  "properties": {
    "iso:country":"ES",
    "sg:address":"Avda Vena, 3",
    "sg:city":"Burgos",
    "sg:orig_category":"Inform\u00c1tica Equipo Y Programas (al Por Mayor)",
    "sg:phone":"+34 947 24 41 45",
    "sg:postcode":"09005",
    "sg:province":"Burgos",
    "sg:website":"www.ofi-net.com",
    "wof:name":"Ofinet Software Y Sistemas S.l.",
    "wof:placetype":"venue"
},
  "geometry": {"coordinates":[-3.6922149658,42.347114563],"type":"Point"}
}