{
  "type": "Feature",
  "properties": {
    "addr:full":"Cra. Tabescan, S/n Ribera Cardos Lleida 25570",
    "addr:housenumber":"s",
    "addr:postcode":"25570",
    "addr:street":"/ N",
    "iso:country":"ES",
    "sg:address":"Cra. Tabescan, S/n",
    "sg:city":"Ribera Cardos",
    "sg:orig_category":"Residencias De Turismo, Residencias Hoteleras",
    "sg:phone":"+34 973 62 31 09",
    "sg:postcode":"25570",
    "sg:province":"Lleida",
    "wof:name":"Serveis Turistics Gabriel S.l.",
    "wof:placetype":"venue"
},
  "geometry": {"coordinates":[1.2262649536,42.5632514954],"type":"Point"}
}