{
  "type": "Feature",
  "properties": {
    "iso:country":"ES",
    "sg:address":"Calle de Victor Arellano, 1",
    "sg:city":"Villatobas",
    "sg:orig_category":"Agentes Generales De Seguros",
    "sg:phone":"+34 925 14 40 26",
    "sg:postcode":"45310",
    "sg:province":"Toledo",
    "wof:name":"Benito Roman Angel",
    "wof:placetype":"venue"
},
  "geometry": {"coordinates":[-3.3254609108,39.9000473022],"type":"Point"}
}