{
  "type": "Feature",
  "properties": {
    "addr:full":"Calle de Reyes Catolicos, 10 Moguer Huelva 21800",
    "addr:housenumber":"10",
    "addr:postcode":"21800",
    "addr:street":"Calle De Reyes Catolicos",
    "iso:country":"ES",
    "sg:address":"Calle de Reyes Catolicos, 10",
    "sg:city":"Moguer",
    "sg:orig_category":"Ropa Para Ni\u00d1os (al Por Menor)",
    "sg:phone":"+34 959 37 27 87",
    "sg:postcode":"21800",
    "sg:province":"Huelva",
    "wof:name":"Alvarez Bogado Montemayor",
    "wof:placetype":"venue"
},
  "geometry": {"coordinates":[-6.8379683495,37.2747039795],"type":"Point"}
}