{
  "type": "Feature",
  "properties": {
    "addr:full":"Carrer de Francesc Ferrer I Guardia, 2 Reus Tarragona 43206",
    "addr:housenumber":"2",
    "addr:postcode":"43206",
    "addr:street":"Carrer De Francesc Ferrer I Guardia",
    "iso:country":"ES",
    "sg:address":"Carrer de Francesc Ferrer I Guardia, 2",
    "sg:city":"Reus",
    "sg:orig_category":"Agencias Y Agentes Comerciales, Representantes",
    "sg:phone":"+34 977 32 11 15",
    "sg:postcode":"43206",
    "sg:province":"Tarragona",
    "wof:name":"Comercial Hermanos Mu\u00f1oz S.l",
    "wof:placetype":"venue"
},
  "geometry": {"coordinates":[1.1039400101,41.1745300293],"type":"Point"}
}