{
  "type": "Feature",
  "properties": {
    "iso:country":"ES",
    "sg:address":"Calle de Comandante Villar, 15",
    "sg:city":"Laredo",
    "sg:orig_category":"Institutos De Belleza",
    "sg:phone":"+34 942 60 31 76",
    "sg:postcode":"39770",
    "sg:province":"Cantabria",
    "wof:name":"Rodriguez Mateo Joaquina",
    "wof:placetype":"venue"
},
  "geometry": {"coordinates":[-3.4162769318,43.4095573425],"type":"Point"}
}