{
  "type": "Feature",
  "properties": {
    "iso:country":"ES",
    "sg:address":"Ctra Torres De Cotillas, 29",
    "sg:city":"Alcantarilla",
    "sg:orig_category":"Electricidad Veh\u00cdculo",
    "sg:phone":"+34 968 89 21 50",
    "sg:postcode":"30820",
    "sg:province":"Murcia",
    "wof:name":"Talleres Oralpu S.l.",
    "wof:placetype":"venue"
},
  "geometry": {"coordinates":[-1.2194039822,37.9762191772],"type":"Point"}
}