{
  "type": "Feature",
  "properties": {
    "addr:full":"Calle de Jacinto, 7 Salamanca Salamanca 37004",
    "addr:housenumber":"7",
    "addr:postcode":"37004",
    "addr:street":"Calle De Jacinto",
    "iso:country":"ES",
    "sg:address":"Calle de Jacinto, 7",
    "sg:city":"Salamanca",
    "sg:orig_category":"Textil",
    "sg:phone":"+34 923 23 54 16",
    "sg:postcode":"37004",
    "sg:province":"Salamanca",
    "wof:name":"Eliam Artesania Infantil S.l.",
    "wof:placetype":"venue"
},
  "geometry": {"coordinates":[-5.6528840065,40.9759407043],"type":"Point"}
}