{
  "type": "Feature",
  "properties": {
    "addr:full":"Avda Caidos, 3 Coru\u00d1a La Coru\u00f1a 15009",
    "addr:housenumber":"3",
    "addr:postcode":"15009",
    "addr:street":"Avda Caidos;La Corun\u0303A",
    "iso:country":"ES",
    "sg:address":"Avda Caidos, 3",
    "sg:city":"Coru\u00d1a",
    "sg:orig_category":"Bisuter\u00cda, Joyer\u00cda, Relojer\u00cda (al Por Menor)",
    "sg:phone":"+34 981 13 67 52",
    "sg:postcode":"15009",
    "sg:province":"La Coru\u00f1a",
    "wof:name":"Pousada Bellon Jose Fernando",
    "wof:placetype":"venue"
},
  "geometry": {"coordinates":[-8.3909883499,43.3519821167],"type":"Point"}
}