{
  "type": "Feature",
  "properties": {
    "iso:country":"ES",
    "sg:address":"Avda Jorge Vigon, 9",
    "sg:city":"Logro\u00f1o",
    "sg:orig_category":"Fabricaci\u00d3n De Sobres, Bolsas Y Fundas",
    "sg:phone":"+34 941 26 05 13",
    "sg:postcode":"26003",
    "sg:province":"La Rioja",
    "wof:name":"Paleo Garcia Aranzazu",
    "wof:placetype":"venue"
},
  "geometry": {"coordinates":[-2.4434111118,42.462600708],"type":"Point"}
}