{
  "type": "Feature",
  "properties": {
    "iso:country":"ES",
    "sg:address":"Calle de Ezequiel Solana, 51",
    "sg:city":"Madrid",
    "sg:orig_category":"Veh\u00cdculos De Ocasi\u00d3n",
    "sg:phone":"+34 914 08 43 62",
    "sg:postcode":"28017",
    "sg:province":"Madrid",
    "sg:website":"www.mistercoche.com",
    "wof:name":"Red Mister Coche S.l.",
    "wof:placetype":"venue"
},
  "geometry": {"coordinates":[-3.6443140507,40.4299964905],"type":"Point"}
}