{
  "type": "Feature",
  "properties": {
    "iso:country":"ES",
    "sg:address":"Carrer de Estacio, 5",
    "sg:city":"Gironella",
    "sg:orig_category":"Trabajos De Topograf\u00cda",
    "sg:phone":"+34 938 22 97 26",
    "sg:postcode":"08680",
    "sg:province":"Barcelona",
    "wof:name":"D2 Enginy Top S.l.",
    "wof:placetype":"venue"
},
  "geometry": {"coordinates":[1.8790990114,42.0350952148],"type":"Point"}
}