{
  "type": "Feature",
  "properties": {
    "addr:full":"Carr Aribau, 12 Badalona Barcelona 08913",
    "addr:housenumber":"12",
    "addr:postcode":"08913",
    "addr:street":"Carr Aribau",
    "iso:country":"ES",
    "sg:address":"Carr Aribau, 12",
    "sg:city":"Badalona",
    "sg:orig_category":"Reposter\u00cdas",
    "sg:phone":"+34 933 99 87 09",
    "sg:postcode":"08913",
    "sg:province":"Barcelona",
    "wof:name":"Manufacturas Panaderas S.l.",
    "wof:placetype":"venue"
},
  "geometry": {"coordinates":[2.2188971043,41.4359550476],"type":"Point"}
}