{
  "type": "Feature",
  "properties": {
    "addr:full":"Calle de Presidente Alvear, 5 Palmas De Gran Canaria Las Palmas 35006",
    "addr:housenumber":"5",
    "addr:postcode":"35006",
    "addr:street":"Calle De Presidente Alvear",
    "iso:country":"ES",
    "sg:address":"Calle de Presidente Alvear, 5",
    "sg:city":"Palmas De Gran Canaria",
    "sg:orig_category":"Ropa Para Se\u00d1oras Y Caballeros (al Por Menor)",
    "sg:phone":"+34 928 24 29 40",
    "sg:postcode":"35006",
    "sg:province":"Las Palmas",
    "wof:name":"Rodriguez Lorenzo Maria Teresa",
    "wof:placetype":"venue"
},
  "geometry": {"coordinates":[-15.4301586151,28.1338806152],"type":"Point"}
}