{
  "type": "Feature",
  "properties": {
    "iso:country":"ES",
    "sg:address":"Carrer de Folch I Torres, 20",
    "sg:city":"Manresa",
    "sg:orig_category":"Venta, Instalaci\u00d3n De Calefacci\u00d3n",
    "sg:phone":"+34 938 76 80 65",
    "sg:postcode":"08241",
    "sg:province":"Barcelona",
    "wof:name":"Calefaccions Ruiz S.l.",
    "wof:placetype":"venue"
},
  "geometry": {"coordinates":[1.8180429935,41.7214317322],"type":"Point"}
}