{
  "type": "Feature",
  "properties": {
    "addr:full":"Calle de Enrique Zarandieta, 9 Ciudad Rodrigo Salamanca 37500",
    "addr:housenumber":"9",
    "addr:postcode":"37500",
    "addr:street":"Calle De Enrique Zarandieta",
    "iso:country":"ES",
    "sg:address":"Calle de Enrique Zarandieta, 9",
    "sg:city":"Ciudad Rodrigo",
    "sg:orig_category":"Empresas De Pintura Y Revestimientos",
    "sg:phone":"+34 923 46 04 28",
    "sg:postcode":"37500",
    "sg:province":"Salamanca",
    "wof:name":"Gonzalez Marcos Rafael",
    "wof:placetype":"venue"
},
  "geometry": {"coordinates":[-6.5316281319,40.5970420837],"type":"Point"}
}