{
  "type": "Feature",
  "properties": {
    "iso:country":"ES",
    "sg:address":"Avda Del Golf, 67",
    "sg:city":"Entrepinos",
    "sg:orig_category":"Inmobiliaria (agencias)",
    "sg:phone":"+34 983 59 12 50",
    "sg:postcode":"47130",
    "sg:province":"Valladolid",
    "wof:name":"Malmierca Sanchez Antonio",
    "wof:placetype":"venue"
},
  "geometry": {"coordinates":[-4.8414039612,41.5719642639],"type":"Point"}
}