{
  "type": "Feature",
  "properties": {
    "addr:full":"Cra. Vall D'aran, Km. 0002,0 Lleida Lleida 25091",
    "addr:postcode":"25091",
    "addr:street":"D'Aran Km. 0002,0",
    "iso:country":"ES",
    "sg:address":"Cra. Vall D'aran, Km. 0002,0",
    "sg:city":"Lleida",
    "sg:orig_category":"Cerrajer\u00cda, Ferrallista",
    "sg:phone":"+34 973 23 34 69",
    "sg:postcode":"25091",
    "sg:province":"Lleida",
    "wof:name":"Borniquel Saboya Juan",
    "wof:placetype":"venue"
},
  "geometry": {"coordinates":[0.6072869897,41.6265106201],"type":"Point"}
}