{
  "type": "Feature",
  "properties": {
    "addr:full":"Cami Sant Cristofol, S/n Esparreguera Barcelona 08292",
    "addr:housenumber":"s / n",
    "addr:postcode":"08292",
    "addr:street":"Sant Cristofol",
    "iso:country":"ES",
    "sg:address":"Cami Sant Cristofol, S/n",
    "sg:city":"Esparreguera",
    "sg:orig_category":"Maquinaria Para Industrias Diversas",
    "sg:phone":"+34 937 77 33 58",
    "sg:postcode":"08292",
    "sg:province":"Barcelona",
    "wof:name":"Jordan Garcia Cristobal",
    "wof:placetype":"venue"
},
  "geometry": {"coordinates":[1.867759943,41.5371665955],"type":"Point"}
}