{
  "type": "Feature",
  "properties": {
    "iso:country":"ES",
    "sg:address":"Calle de Carmen (del), 5",
    "sg:city":"Jaca",
    "sg:orig_category":"Electricidad: Instaladores",
    "sg:phone":"+34 974 36 02 74",
    "sg:postcode":"22700",
    "sg:province":"Huesca",
    "wof:name":"Electrocalvo Jaca S.l.",
    "wof:placetype":"venue"
},
  "geometry": {"coordinates":[-0.5503690839,42.5692634583],"type":"Point"}
}