{
  "type": "Feature",
  "properties": {
    "addr:full":"Av Generalitat, 59 Santa Coloma De Gramenet Barcelona 08922",
    "addr:housenumber":"59",
    "addr:postcode":"08922",
    "addr:street":"Av Generalitat",
    "iso:country":"ES",
    "sg:address":"Av Generalitat, 59",
    "sg:city":"Santa Coloma De Gramenet",
    "sg:orig_category":"Carnicer\u00cdas, Carnicer\u00cdas",
    "sg:phone":"+34 934 66 24 48",
    "sg:postcode":"08922",
    "sg:province":"Barcelona",
    "wof:name":"Perez Lopez Joan Manel",
    "wof:placetype":"venue"
},
  "geometry": {"coordinates":[2.2109589577,41.4469795227],"type":"Point"}
}