{
  "type": "Feature",
  "properties": {
    "iso:country":"ES",
    "sg:address":"Pg Torras I Bages, 11",
    "sg:city":"Barcelona",
    "sg:orig_category":"Tintes (fabricaci\u00d3n, Al Por Mayor)",
    "sg:phone":"+34 933 11 97 84",
    "sg:postcode":"08030",
    "sg:province":"Barcelona",
    "wof:name":"Falces Vaivedru Jordi",
    "wof:placetype":"venue"
},
  "geometry": {"coordinates":[2.1910119057,41.4369697571],"type":"Point"}
}