{
  "type": "Feature",
  "properties": {
    "addr:full":"Calle de Francisco De Goya, 11 Portugalete Vizcaya 48920",
    "addr:housenumber":"11",
    "addr:postcode":"48920",
    "addr:street":"Calle De Francisco De Goya",
    "iso:country":"ES",
    "sg:address":"Calle de Francisco De Goya, 11",
    "sg:city":"Portugalete",
    "sg:orig_category":"Molduras, Junquillos, Listones Y Molduras Perforadas",
    "sg:phone":"+34 944 96 58 16",
    "sg:postcode":"48920",
    "sg:province":"Vizcaya",
    "wof:name":"Ana Esther De Juan Rodriguez",
    "wof:placetype":"venue"
},
  "geometry": {"coordinates":[-3.0175836086,43.3160400391],"type":"Point"}
}