{
  "type": "Feature",
  "properties": {
    "iso:country":"ES",
    "sg:address":"Calle de Navahermosa, 25",
    "sg:city":"Sonseca",
    "sg:orig_category":"Fabricaci\u00d3n De Muebles",
    "sg:phone":"+34 925 38 19 12",
    "sg:postcode":"45100",
    "sg:province":"Toledo",
    "wof:name":"Proyectos Internacionales Adolfo Luque S.l.",
    "wof:placetype":"venue"
},
  "geometry": {"coordinates":[-3.9655818939,39.6417274475],"type":"Point"}
}