{
  "type": "Feature",
  "properties": {
    "iso:country":"ES",
    "sg:address":"Calle de Cid, 14",
    "sg:city":"Majadahonda",
    "sg:orig_category":"Fabricaci\u00d3n De Capiteles",
    "sg:phone":"+34 916 38 99 84",
    "sg:postcode":"28220",
    "sg:province":"Madrid",
    "sg:website":"www.vds.es",
    "wof:name":"Fernandez Pe\u00f1arrubia Maria Teresa",
    "wof:placetype":"venue"
},
  "geometry": {"coordinates":[-3.8690493107,40.4703636169],"type":"Point"}
}