{
  "type": "Feature",
  "properties": {
    "addr:full":"Cmno Rojas, 15 Santa Rosalia-maqueda M\u00e1laga 29591",
    "addr:housenumber":"15",
    "addr:postcode":"29591",
    "addr:street":"Cmno Rojas",
    "iso:country":"ES",
    "sg:address":"Cmno Rojas, 15",
    "sg:city":"Santa Rosalia-maqueda",
    "sg:orig_category":"Postigos, Persianas Y Celos\u00cdas",
    "sg:phone":"+34 952 43 38 03",
    "sg:postcode":"29591",
    "sg:province":"M\u00e1laga",
    "wof:name":"Persianas Y Aluminios Diaz S.l.",
    "wof:placetype":"venue"
},
  "geometry": {"coordinates":[-4.542953968,36.7268447876],"type":"Point"}
}