{
  "type": "Feature",
  "properties": {
    "addr:full":"Avda Eusebio Gomez, 25 Saron Cantabria 39620",
    "addr:housenumber":"25",
    "addr:postcode":"39620",
    "addr:street":"Avda Eusebio Gomez",
    "iso:country":"ES",
    "sg:address":"Avda Eusebio Gomez, 25",
    "sg:city":"Saron",
    "sg:orig_category":"Carnicer\u00cdas, Carnicer\u00cdas",
    "sg:phone":"+34 942 56 32 05",
    "sg:postcode":"39620",
    "sg:province":"Cantabria",
    "wof:name":"Laso Rodriguez Angel",
    "wof:placetype":"venue"
},
  "geometry": {"coordinates":[-3.852768898,43.3237915039],"type":"Point"}
}