{
  "type": "Feature",
  "properties": {
    "addr:full":"Calle de Rioja, S/n Leganes Madrid 28915",
    "addr:housenumber":"s / n",
    "addr:postcode":"28915",
    "addr:street":"Calle De Rioja",
    "iso:country":"ES",
    "sg:address":"Calle de Rioja, S/n",
    "sg:city":"Leganes",
    "sg:orig_category":"Centros De Educaci\u00d3n Especial",
    "sg:phone":"+34 916 87 11 53",
    "sg:postcode":"28915",
    "sg:province":"Madrid",
    "wof:name":"Colegio Nacional Ortega Y Gasset",
    "wof:placetype":"venue"
},
  "geometry": {"coordinates":[-3.750068903,40.3340988159],"type":"Point"}
}