{
  "type": "Feature",
  "properties": {
    "iso:country":"ES",
    "sg:address":"Luga Rio, 5",
    "sg:city":"San Pedro De Visma",
    "sg:orig_category":"Fabricaci\u00d3n, Distribuci\u00d3n De Discos, V\u00cddeodiscos Y Musicassettes",
    "sg:phone":"+34 981 14 43 99",
    "sg:postcode":"15011",
    "sg:province":"La Coru\u00f1a",
    "wof:name":"Distribuciones Disclub S.a.",
    "wof:placetype":"venue"
},
  "geometry": {"coordinates":[-8.4423465729,43.3717308044],"type":"Point"}
}