{
  "type": "Feature",
  "properties": {
    "iso:country":"ES",
    "sg:address":"Avda Ramon Y Cajal, 5",
    "sg:city":"Sevilla",
    "sg:orig_category":"Zapatos (al Por Menor)",
    "sg:phone":"+34 954 63 85 34",
    "sg:postcode":"41005",
    "sg:province":"Sevilla",
    "wof:name":"Zapatos Pasarela S.l.",
    "wof:placetype":"venue"
},
  "geometry": {"coordinates":[-5.974811554,37.3770980835],"type":"Point"}
}