{
  "type": "Feature",
  "properties": {
    "addr:full":"Calle de Aranaz Y Vides, 5 Tudela Navarra 31500",
    "addr:housenumber":"5",
    "addr:postcode":"31500",
    "addr:street":"Calle De Aranaz Y Vides",
    "iso:country":"ES",
    "sg:address":"Calle de Aranaz Y Vides, 5",
    "sg:city":"Tudela",
    "sg:orig_category":"Pizzer\u00cdas",
    "sg:phone":"+34 948 82 68 99",
    "sg:postcode":"31500",
    "sg:province":"Navarra",
    "wof:name":"Ferpizza S.l.",
    "wof:placetype":"venue"
},
  "geometry": {"coordinates":[-1.6004904509,42.0605163574],"type":"Point"}
}