{
  "type": "Feature",
  "properties": {
    "iso:country":"ES",
    "sg:address":"Plaz Gante, 1",
    "sg:city":"Caceres",
    "sg:orig_category":"Inform\u00c1tica: Material Y Suministros",
    "sg:phone":"+34 927 24 17 27",
    "sg:postcode":"10001",
    "sg:province":"C\u00e1ceres",
    "wof:name":"Venta Y Ensamblaje De Material Informatico S.l.",
    "wof:placetype":"venue"
},
  "geometry": {"coordinates":[-6.3811907768,39.4724998474],"type":"Point"}
}