{
  "type": "Feature",
  "properties": {
    "addr:full":"Calle de Carrera, 43 Osuna Sevilla 41640",
    "addr:housenumber":"43",
    "addr:postcode":"41640",
    "addr:street":"Calle De Carrera",
    "iso:country":"ES",
    "sg:address":"Calle de Carrera, 43",
    "sg:city":"Osuna",
    "sg:classifiers":[
        {
            "category":"Communications",
            "type":"Services"
        }
    ],
    "sg:phone":"+34 955 82 09 04",
    "sg:postcode":"41640",
    "sg:province":"Sevilla",
    "sg:tags":[
        "televisiones",
        "y",
        "radio"
    ],
    "wof:name":"Estepa De Comunicaciones S.l.",
    "wof:placetype":"venue"
},
  "geometry": {"coordinates":[-5.1039199829,37.2386245728],"type":"Point"}
}