{
  "type": "Feature",
  "properties": {
    "addr:full":"Avda Constitucion, 26 Cistierna Le\u00f3n 24800",
    "addr:housenumber":"26",
    "addr:postcode":"24800",
    "addr:street":"Avda Constitucion;Leo\u0301N",
    "iso:country":"ES",
    "sg:address":"Avda Constitucion, 26",
    "sg:city":"Cistierna",
    "sg:orig_category":"Molduras, Junquillos, Listones Y Molduras Perforadas",
    "sg:phone":"+34 987 70 03 90",
    "sg:postcode":"24800",
    "sg:province":"Le\u00f3n",
    "wof:name":"Fernandez Sanchez Francisco",
    "wof:placetype":"venue"
},
  "geometry": {"coordinates":[-5.1286687851,42.8040084839],"type":"Point"}
}