{
  "type": "Feature",
  "properties": {
    "iso:country":"ES",
    "sg:address":"Avda Juan Carlos I, 6",
    "sg:city":"Villamayor Santiago",
    "sg:orig_category":"Fabricaci\u00d3n De Harinas, S\u00c9molas, Productos De Elaboraci\u00d3n Del Grano",
    "sg:phone":"+34 969 13 90 56",
    "sg:postcode":"16415",
    "sg:province":"Cuenca",
    "wof:name":"Harinas Y Derivados Carrion S.l.",
    "wof:placetype":"venue"
},
  "geometry": {"coordinates":[-2.9251489639,39.7325706482],"type":"Point"}
}