{
  "type": "Feature",
  "properties": {
    "addr:full":"Calle de Universidad De O\u00d1ati, 19 Bilbao Vizcaya 48015",
    "addr:housenumber":"19",
    "addr:postcode":"48015",
    "addr:street":"Calle De Universidad;On\u0303Ati",
    "iso:country":"ES",
    "sg:address":"Calle de Universidad De O\u00d1ati, 19",
    "sg:city":"Bilbao",
    "sg:orig_category":"Art\u00cdculos De Decoraci\u00d3n",
    "sg:phone":"+34 944 76 12 09",
    "sg:postcode":"48015",
    "sg:province":"Vizcaya",
    "wof:name":"Perez Rivero Marcelina",
    "wof:placetype":"venue"
},
  "geometry": {"coordinates":[-2.9594669342,43.2816390991],"type":"Point"}
}