{
  "type": "Feature",
  "properties": {
    "iso:country":"ES",
    "sg:address":"Calle de Juncar, 6",
    "sg:city":"Villarta",
    "sg:orig_category":"Cristaler\u00cdas",
    "sg:phone":"+34 962 18 93 99",
    "sg:postcode":"16280",
    "sg:province":"Cuenca",
    "wof:name":"Crisvialu S.l.",
    "wof:placetype":"venue"
},
  "geometry": {"coordinates":[-1.6489510536,39.4429283142],"type":"Point"}
}