{
  "type": "Feature",
  "properties": {
    "addr:full":"Calle de Santa Teresa De Jesus, 2 Oviedo Asturias 33007",
    "addr:housenumber":"2",
    "addr:postcode":"33007",
    "addr:street":"Calle De Santa Teresa De Jesus",
    "iso:country":"ES",
    "sg:address":"Calle de Santa Teresa De Jesus, 2",
    "sg:city":"Oviedo",
    "sg:orig_category":"Asilos De Ancianos. Centros Privados",
    "sg:phone":"+34 985 24 10 29",
    "sg:postcode":"33007",
    "sg:province":"Asturias",
    "wof:name":"Organismo Autonomo E.r.a. H. Tercera Edad Sta. Susana",
    "wof:placetype":"venue"
},
  "geometry": {"coordinates":[-5.8525290489,43.3547019958],"type":"Point"}
}