{
  "type": "Feature",
  "properties": {
    "iso:country":"ES",
    "sg:address":"Carrer de Rios Rosas, 40",
    "sg:city":"Barcelona",
    "sg:orig_category":"Grafistas",
    "sg:phone":"+34 932 12 83 34",
    "sg:postcode":"08006",
    "sg:province":"Barcelona",
    "wof:name":"Ca\u00f1ellas Vi\u00f1olas Pere",
    "wof:placetype":"venue"
},
  "geometry": {"coordinates":[2.143253088,41.4044685364],"type":"Point"}
}