{
  "type": "Feature",
  "properties": {
    "addr:full":"Carrer de Mussola, 8 Marines Alicante 03700",
    "addr:housenumber":"8",
    "addr:postcode":"03700",
    "addr:street":"Carrer De Mussola",
    "iso:country":"ES",
    "sg:address":"Carrer de Mussola, 8",
    "sg:city":"Marines",
    "sg:orig_category":"Inversiones",
    "sg:phone":"+34 966 42 00 63",
    "sg:postcode":"03700",
    "sg:province":"Alicante",
    "wof:name":"Inversiones Mp Cuatro S.l.",
    "wof:placetype":"venue"
},
  "geometry": {"coordinates":[0.0935600027,38.8523216248],"type":"Point"}
}