{
  "type": "Feature",
  "properties": {
    "iso:country":"ES",
    "sg:address":"Plaz Espa\u00d1a, 14",
    "sg:city":"Madrid",
    "sg:orig_category":"Centros Empresariales",
    "sg:phone":"+34 915 59 89 43",
    "sg:postcode":"28008",
    "sg:province":"Madrid",
    "wof:name":"Carballo De Sales Jose",
    "wof:placetype":"venue"
},
  "geometry": {"coordinates":[-3.7139110565,40.4233932495],"type":"Point"}
}