{
  "type": "Feature",
  "properties": {
    "iso:country":"ES",
    "sg:address":"Pase Los Fueros, 12",
    "sg:city":"San Vicente De Barakaldo",
    "sg:orig_category":"Abogados",
    "sg:phone":"+34 944 18 92 03",
    "sg:postcode":"48901",
    "sg:province":"Vizcaya",
    "wof:name":"Oses Garcia Inmaculada",
    "wof:placetype":"venue"
},
  "geometry": {"coordinates":[-2.9858388901,43.2973098755],"type":"Point"}
}