{
  "type": "Feature",
  "properties": {
    "addr:full":"Rua Molinera, 3 Lalin Pontevedra 36500",
    "addr:housenumber":"3",
    "addr:postcode":"36500",
    "addr:street":"Rua Molinera",
    "iso:country":"ES",
    "sg:address":"Rua Molinera, 3",
    "sg:city":"Lalin",
    "sg:orig_category":"Plomeros",
    "sg:phone":"+34 986 78 07 88",
    "sg:postcode":"36500",
    "sg:province":"Pontevedra",
    "wof:name":"Rodriguez Acevedo Donato Placido",
    "wof:placetype":"venue"
},
  "geometry": {"coordinates":[-8.1127595901,42.6598815918],"type":"Point"}
}