{
  "type": "Feature",
  "properties": {
    "iso:country":"ES",
    "sg:address":"Calle de Profesor Garcia Gonzalez, S/n",
    "sg:city":"Sevilla",
    "sg:orig_category":"Imprenta",
    "sg:phone":"+34 954 62 43 06",
    "sg:postcode":"41012",
    "sg:province":"Sevilla",
    "wof:name":"Grafintel Anadalucia S.l.",
    "wof:placetype":"venue"
},
  "geometry": {"coordinates":[-5.9881391525,37.3608665466],"type":"Point"}
}