{
  "type": "Feature",
  "properties": {
    "addr:full":"Ctra. B-motril, Km. 0337,0 Jaen Ja\u00e9n 23009",
    "addr:postcode":"23009",
    "addr:street":"Ctra. B-Motril Km. 0337,0 Jaen Jae\u0301N",
    "iso:country":"ES",
    "sg:address":"Ctra. B-motril, Km. 0337,0",
    "sg:city":"Jaen",
    "sg:orig_category":"Distribuci\u00d3n De Petr\u00d3leo Y Derivados",
    "sg:phone":"+34 953 24 36 50",
    "sg:postcode":"23009",
    "sg:province":"Ja\u00e9n",
    "wof:name":"Cedipsa Compa\u00d1ia Espa\u00d1ola Distribuidora De Petroleos S.a.",
    "wof:placetype":"venue"
},
  "geometry": {"coordinates":[-3.7480869293,37.8042449951],"type":"Point"}
}