{
  "type": "Feature",
  "properties": {
    "addr:full":"Plaz Solarejo, 8 Toledo Toledo 45001",
    "addr:housenumber":"8",
    "addr:postcode":"45001",
    "addr:street":"Plaz Solarejo",
    "iso:country":"ES",
    "sg:address":"Plaz Solarejo, 8",
    "sg:city":"Toledo",
    "sg:orig_category":"Asociaciones Y Clubs Deportivos",
    "sg:phone":"+34 925 25 13 93",
    "sg:postcode":"45001",
    "sg:province":"Toledo",
    "wof:name":"Casman Sport S.l.",
    "wof:placetype":"venue"
},
  "geometry": {"coordinates":[-4.025138855,39.8618774414],"type":"Point"}
}