{
  "type": "Feature",
  "properties": {
    "addr:full":"Carrer de Platja, 18 Ampolla Tarragona 43895",
    "addr:housenumber":"18",
    "addr:postcode":"43895",
    "addr:street":"Carrer De Platja",
    "iso:country":"ES",
    "sg:address":"Carrer de Platja, 18",
    "sg:city":"Ampolla",
    "sg:orig_category":"Peluqueros: De Se\u00d1oras",
    "sg:phone":"+34 977 46 04 38",
    "sg:postcode":"43895",
    "sg:province":"Tarragona",
    "wof:name":"Fava Bel Josp Enric",
    "wof:placetype":"venue"
},
  "geometry": {"coordinates":[0.7089970112,40.8112030029],"type":"Point"}
}