{
  "type": "Feature",
  "properties": {
    "addr:full":"Calle de Amador De Los Rios, 38 Sevilla Sevilla 41003",
    "addr:housenumber":"38",
    "addr:postcode":"41003",
    "addr:street":"Calle De Amador De Los Rios",
    "iso:country":"ES",
    "sg:address":"Calle de Amador De Los Rios, 38",
    "sg:city":"Sevilla",
    "sg:orig_category":"Centros De Reservas Hoteleras",
    "sg:phone":"+34 954 41 43 14",
    "sg:postcode":"41003",
    "sg:province":"Sevilla",
    "wof:name":"Mississippi Hosteleria Y Ocio S.l.",
    "wof:placetype":"venue"
},
  "geometry": {"coordinates":[-5.9827256203,37.3911170959],"type":"Point"}
}