{
  "type": "Feature",
  "properties": {
    "addr:full":"Carrer de Arago, 16 Palma Islas Baleares 07006",
    "addr:housenumber":"16",
    "addr:postcode":"07006",
    "addr:street":"Carrer De Arago",
    "iso:country":"ES",
    "sg:address":"Carrer de Arago, 16",
    "sg:city":"Palma",
    "sg:orig_category":"Fabricaci\u00d3n De Mobiliario De Oficina",
    "sg:phone":"+34 971 46 34 18",
    "sg:postcode":"07006",
    "sg:province":"Islas Baleares",
    "wof:name":"Andreu Soler Pedro",
    "wof:placetype":"venue"
},
  "geometry": {"coordinates":[2.6584327221,39.5744247437],"type":"Point"}
}