{
  "type": "Feature",
  "properties": {
    "addr:full":"Calle de Libreros, 11 Alcala Henares Madrid 28801",
    "addr:housenumber":"11",
    "addr:postcode":"28801",
    "addr:street":"Calle De Libreros",
    "iso:country":"ES",
    "sg:address":"Calle de Libreros, 11",
    "sg:city":"Alcala Henares",
    "sg:orig_category":"Bancos",
    "sg:phone":"+34 918 88 35 50",
    "sg:postcode":"28801",
    "sg:province":"Madrid",
    "wof:name":"Banco Popular Espa\u00f1ol",
    "wof:placetype":"venue"
},
  "geometry": {"coordinates":[-3.3635630608,40.4839477539],"type":"Point"}
}