{
  "type": "Feature",
  "properties": {
    "addr:full":"Calle de Vazquez De Mella, 2 Palma Islas Baleares 07010",
    "addr:housenumber":"2",
    "addr:postcode":"07010",
    "addr:street":"Calle De Vazquez De Mella",
    "iso:country":"ES",
    "sg:address":"Calle de Vazquez De Mella, 2",
    "sg:city":"Palma",
    "sg:orig_category":"Arquitectos",
    "sg:phone":"+34 971 20 38 64",
    "sg:postcode":"07010",
    "sg:province":"Islas Baleares",
    "wof:name":"Nicolau Sanso Matias",
    "wof:placetype":"venue"
},
  "geometry": {"coordinates":[2.6466178894,39.5825271606],"type":"Point"}
}