{
  "type": "Feature",
  "properties": {
    "addr:full":"Calle de Madrid, 6 Sevilla Sevilla 41001",
    "addr:housenumber":"6",
    "addr:postcode":"41001",
    "addr:street":"Calle De Madrid",
    "iso:country":"ES",
    "sg:address":"Calle de Madrid, 6",
    "sg:city":"Sevilla",
    "sg:orig_category":"Promotores Constructores",
    "sg:phone":"+34 954 29 30 92",
    "sg:postcode":"41001",
    "sg:province":"Sevilla",
    "wof:name":"Nadiges",
    "wof:placetype":"venue"
},
  "geometry": {"coordinates":[-5.9967679977,37.3883094788],"type":"Point"}
}