{
  "type": "Feature",
  "properties": {
    "addr:full":"Errebal Kalea, 10 Eibar Guip\u00f9zcoa 20600",
    "addr:housenumber":"10",
    "addr:postcode":"20600",
    "addr:street":"Errebal Kalea;Guipu\u0300Zcoa",
    "iso:country":"ES",
    "sg:address":"Errebal Kalea, 10",
    "sg:city":"Eibar",
    "sg:orig_category":"Alumbrados",
    "sg:phone":"+34 943 20 08 83",
    "sg:postcode":"20600",
    "sg:province":"Guip\u00f9zcoa",
    "wof:name":"G.l. Iluminacion S.l.",
    "wof:placetype":"venue"
},
  "geometry": {"coordinates":[-2.4696118832,43.1859359741],"type":"Point"}
}