{
  "type": "Feature",
  "properties": {
    "addr:full":"Calle de Francisco Miranda, 12 Icod De Los Vinos Santa Cruz De Tenerife 38430",
    "addr:housenumber":"12",
    "addr:postcode":"38430",
    "addr:street":"Calle De Francisco Miranda",
    "iso:country":"ES",
    "sg:address":"Calle de Francisco Miranda, 12",
    "sg:city":"Icod De Los Vinos",
    "sg:orig_category":"Frutas, Legumbres Frescas Y Tempranas (al Por Menor)",
    "sg:phone":"+34 922 81 44 10",
    "sg:postcode":"38430",
    "sg:province":"Santa Cruz De Tenerife",
    "wof:name":"Luis Gonzalez Ana Elia",
    "wof:placetype":"venue"
},
  "geometry": {"coordinates":[-16.720451355,28.3694095612],"type":"Point"}
}