{
  "type": "Feature",
  "properties": {
    "iso:country":"ES",
    "sg:address":"Calle de Medina Sidonia, 11",
    "sg:city":"Cadiz",
    "sg:orig_category":"Molduras, Junquillos, Listones Y Molduras Perforadas",
    "sg:phone":"+34 956 27 47 03",
    "sg:postcode":"11012",
    "sg:province":"C\u00e1diz",
    "wof:name":"Brenes Medina Antonia",
    "wof:placetype":"venue"
},
  "geometry": {"coordinates":[-6.2747979164,36.5123710632],"type":"Point"}
}