{
  "type": "Feature",
  "properties": {
    "addr:full":"La Presa, S/n Molinaseca Le\u00f3n 24413",
    "addr:postcode":"24413",
    "addr:street":"Presa S / N;Leo\u0301N",
    "iso:country":"ES",
    "sg:address":"La Presa, S/n",
    "sg:city":"Molinaseca",
    "sg:orig_category":"Hoteles",
    "sg:phone":"+34 987 45 31 54",
    "sg:postcode":"24413",
    "sg:province":"Le\u00f3n",
    "wof:name":"Aldonza Arias Juan Carlos",
    "wof:placetype":"venue"
},
  "geometry": {"coordinates":[-6.5190563202,42.5374221802],"type":"Point"}
}