{
  "type": "Feature",
  "properties": {
    "addr:full":"Carr Mariners, S/n Port D'alcudia Islas Baleares 07410",
    "addr:housenumber":"s / n",
    "addr:postcode":"07410",
    "addr:street":"Carr Mariners",
    "iso:country":"ES",
    "sg:address":"Carr Mariners, S/n",
    "sg:city":"Port D'alcudia",
    "sg:orig_category":"Supermercados Y Hipermercados",
    "sg:phone":"+34 971 54 62 08",
    "sg:postcode":"07410",
    "sg:province":"Islas Baleares",
    "wof:name":"Ferrer Bonet Jaime",
    "wof:placetype":"venue"
},
  "geometry": {"coordinates":[3.1343209743,39.8423843384],"type":"Point"}
}