{
  "type": "Feature",
  "properties": {
    "iso:country":"ES",
    "sg:address":"Calle de San Bartolome, 15",
    "sg:city":"Casavieja",
    "sg:orig_category":"Alimentaci\u00d3n General (al Por Menor)",
    "sg:phone":"+34 918 67 80 17",
    "sg:postcode":"05450",
    "sg:province":"\u00c1vila",
    "wof:name":"Correa Jimenez Angeles",
    "wof:placetype":"venue"
},
  "geometry": {"coordinates":[-4.7650680542,40.2896118164],"type":"Point"}
}