{
  "type": "Feature",
  "properties": {
    "addr:full":"Sbid Monte Castelo, 8 Gandari\u00d1a Pontevedra 36214",
    "addr:housenumber":"8",
    "addr:postcode":"36214",
    "addr:street":"Monte Castelo",
    "iso:country":"ES",
    "sg:address":"Sbid Monte Castelo, 8",
    "sg:city":"Gandari\u00d1a",
    "sg:orig_category":"Molduras, Junquillos, Listones Y Molduras Perforadas",
    "sg:phone":"+34 986 47 24 19",
    "sg:postcode":"36214",
    "sg:province":"Pontevedra",
    "wof:name":"Groba Pazo Ceferino",
    "wof:placetype":"venue"
},
  "geometry": {"coordinates":[-8.6480531693,42.4336204529],"type":"Point"}
}