{
  "type": "Feature",
  "properties": {
    "addr:full":"Avda Catalu\u00d1a, 2 Fraga Huesca 22520",
    "addr:housenumber":"2",
    "addr:postcode":"22520",
    "addr:street":"Avda Catalun\u0303A",
    "iso:country":"ES",
    "sg:address":"Avda Catalu\u00d1a, 2",
    "sg:city":"Fraga",
    "sg:orig_category":"Tapicer\u00cdas",
    "sg:phone":"+34 974 47 28 88",
    "sg:postcode":"22520",
    "sg:province":"Huesca",
    "wof:name":"Tapicerias Decoracion Coso S.l.",
    "wof:placetype":"venue"
},
  "geometry": {"coordinates":[0.345351994,41.5249633789],"type":"Point"}
}