{
  "type": "Feature",
  "properties": {
    "addr:full":"Carrer de Barcelona, 67 Esparreguera Barcelona 08292",
    "addr:housenumber":"67",
    "addr:postcode":"08292",
    "addr:street":"Carrer De Barcelona",
    "iso:country":"ES",
    "sg:address":"Carrer de Barcelona, 67",
    "sg:city":"Esparreguera",
    "sg:orig_category":"Ense\u00d1anza: Idiomas",
    "sg:phone":"+34 937 77 43 36",
    "sg:postcode":"08292",
    "sg:province":"Barcelona",
    "sg:website":"www.elitelc.com",
    "wof:name":"Elite Language Centre S.l.",
    "wof:placetype":"venue"
},
  "geometry": {"coordinates":[1.8731700182,41.535320282],"type":"Point"}
}