{
  "type": "Feature",
  "properties": {
    "iso:country":"ES",
    "sg:address":"Carrer de Santa Teresa, 43",
    "sg:city":"Mataro",
    "sg:orig_category":"Abogados",
    "sg:phone":"+34 937 55 34 34",
    "sg:postcode":"08302",
    "sg:province":"Barcelona",
    "wof:name":"Capitani Bassolas Claudia",
    "wof:placetype":"venue"
},
  "geometry": {"coordinates":[2.4440789223,41.5381736755],"type":"Point"}
}