{
  "type": "Feature",
  "properties": {
    "iso:country":"ES",
    "sg:address":"Pino, S/n",
    "sg:city":"Algar",
    "sg:orig_category":"Frutas Y Legumbres Frescas (al Por Mayor)",
    "sg:phone":"+34 968 13 54 31",
    "sg:postcode":"30366",
    "sg:province":"Murcia",
    "wof:name":"Hacienda El Pino C.b.",
    "wof:placetype":"venue"
},
  "geometry": {"coordinates":[-0.8678010106,37.6480293274],"type":"Point"}
}