{
  "type": "Feature",
  "properties": {
    "iso:country":"ES",
    "sg:address":"Avda Sancho El Sabio, 16",
    "sg:city":"Donostia-san Sebastian",
    "sg:orig_category":"Quincaller\u00cda (al Por Menor)",
    "sg:phone":"+34 943 45 15 08",
    "sg:postcode":"20010",
    "sg:province":"Guip\u00f9zcoa",
    "wof:name":"Ferreteria Yarza C.b.",
    "wof:placetype":"venue"
},
  "geometry": {"coordinates":[-1.9801870584,43.3096046448],"type":"Point"}
}