{
  "type": "Feature",
  "properties": {
    "addr:full":"Carrer de Vallvidrera-s Cugat (les Planes), 321 S. Cugat Valles Barcelona 08196",
    "addr:housenumber":"321",
    "addr:postcode":"08196",
    "addr:street":"Carrer De Vallvidrera-S Cugat;Planes;S. Cugat Valles Barcelona",
    "iso:country":"ES",
    "sg:address":"Carrer de Vallvidrera-s Cugat (les Planes), 321",
    "sg:city":"S. Cugat Valles",
    "sg:orig_category":"Escultores, Estatuarios E Imagineros",
    "sg:phone":"+34 936 75 20 53",
    "sg:postcode":"08196",
    "sg:province":"Barcelona",
    "wof:name":"Fernandez Portugal Roque",
    "wof:placetype":"venue"
},
  "geometry": {"coordinates":[2.094440937,41.4336738586],"type":"Point"}
}