{
  "type": "Feature",
  "properties": {
    "iso:country":"ES",
    "sg:address":"Calle de Villegas, 5",
    "sg:city":"Melilla",
    "sg:orig_category":"Agentes Generales De Seguros",
    "sg:phone":"+34 952 67 46 52",
    "sg:postcode":"52004",
    "sg:province":"Melilla",
    "wof:name":"Baron Garcia Jorge",
    "wof:placetype":"venue"
},
  "geometry": {"coordinates":[-2.9406208992,35.2907676697],"type":"Point"}
}