{
  "type": "Feature",
  "properties": {
    "iso:country":"ES",
    "sg:address":"Calle de Eguiluz, 6",
    "sg:city":"Jerez De La Frontera",
    "sg:orig_category":"Centros Empresariales",
    "sg:phone":"+34 956 32 32 49",
    "sg:postcode":"11402",
    "sg:province":"C\u00e1diz",
    "wof:name":"Berengena Berengena Manuel",
    "wof:placetype":"venue"
},
  "geometry": {"coordinates":[-6.1365227699,36.6882247925],"type":"Point"}
}