{
  "type": "Feature",
  "properties": {
    "addr:full":"Calle de Eduardo Lope, 4 Villa Rio C\u00f3rdoba 14640",
    "addr:housenumber":"4",
    "addr:postcode":"14640",
    "addr:street":"Calle De Eduardo Lope;Villa Rio Co\u0301Rdoba",
    "iso:country":"ES",
    "sg:address":"Calle de Eduardo Lope, 4",
    "sg:city":"Villa Rio",
    "sg:orig_category":"Empresas De Carpinter\u00cda Met\u00c1lica",
    "sg:phone":"+34 957 17 66 95",
    "sg:postcode":"14640",
    "sg:province":"C\u00f3rdoba",
    "wof:name":"Menor Carpio Bernardo",
    "wof:placetype":"venue"
},
  "geometry": {"coordinates":[-4.2887339592,37.9812545776],"type":"Point"}
}