{
  "type": "Feature",
  "properties": {
    "iso:country":"ES",
    "sg:address":"Rond Santa Maria, 6",
    "sg:city":"Ciudad Real",
    "sg:orig_category":"Arquitectos",
    "sg:phone":"+34 926 23 18 49",
    "sg:postcode":"13002",
    "sg:province":"Ciudad Real",
    "wof:name":"Romero Cardenas Jose Maria",
    "wof:placetype":"venue"
},
  "geometry": {"coordinates":[-3.9341979027,38.9871101379],"type":"Point"}
}