{
  "type": "Feature",
  "properties": {
    "iso:country":"ES",
    "sg:address":"Calle de Suecia, S/n",
    "sg:city":"San Eugenio Alto",
    "sg:orig_category":"Supermercados Y Hipermercados",
    "sg:phone":"+34 922 71 41 78",
    "sg:postcode":"38660",
    "sg:province":"Santa Cruz De Tenerife",
    "wof:name":"Oliva Mora Pedro",
    "wof:placetype":"venue"
},
  "geometry": {"coordinates":[-16.7254886627,28.0771408081],"type":"Point"}
}