{
  "type": "Feature",
  "properties": {
    "iso:country":"ES",
    "sg:address":"Gta Ingeniero La Cierva, 1",
    "sg:city":"Cadiz",
    "sg:orig_category":"Lencer\u00cda Femenina, Corseter\u00cda, Trajes De Ba\u00d1o (al Por Menor)",
    "sg:phone":"+34 956 25 13 20",
    "sg:postcode":"11010",
    "sg:province":"C\u00e1diz",
    "wof:name":"Toledano Soto Gloria",
    "wof:placetype":"venue"
},
  "geometry": {"coordinates":[-6.2766251564,36.5051765442],"type":"Point"}
}