{
  "type": "Feature",
  "properties": {
    "iso:country":"ES",
    "sg:address":"Avda Askatasun Etorbidea, 14",
    "sg:city":"Durango",
    "sg:orig_category":"Explotaci\u00d3n De Bosques",
    "sg:phone":"+34 946 03 04 27",
    "sg:postcode":"48200",
    "sg:province":"Vizcaya",
    "wof:name":"Txaleko Egurrak, S.l.",
    "wof:placetype":"venue"
},
  "geometry": {"coordinates":[-2.6372599602,43.1693229675],"type":"Point"}
}