{
  "type": "Feature",
  "properties": {
    "addr:full":"Calle de Capitan Salom, 14 Palma Islas Baleares 07004",
    "addr:housenumber":"14",
    "addr:postcode":"07004",
    "addr:street":"Calle De Capitan Salom",
    "iso:country":"ES",
    "sg:address":"Calle de Capitan Salom, 14",
    "sg:city":"Palma",
    "sg:orig_category":"Madera Para Construcci\u00d3n E Industria",
    "sg:phone":"+34 971 75 00 50",
    "sg:postcode":"07004",
    "sg:province":"Islas Baleares",
    "wof:name":"Buil Sanchez Antonio",
    "wof:placetype":"venue"
},
  "geometry": {"coordinates":[2.6531291008,39.5834197998],"type":"Point"}
}