{
  "type": "Feature",
  "properties": {
    "iso:country":"ES",
    "sg:address":"Carr Pare Sanahuja, 11",
    "sg:city":"Balaguer",
    "sg:orig_category":"Peluqueros: De Se\u00d1oras",
    "sg:phone":"+34 973 45 06 99",
    "sg:postcode":"25600",
    "sg:province":"Lleida",
    "wof:name":"Mece Ferrer Planes",
    "wof:placetype":"venue"
},
  "geometry": {"coordinates":[0.8088520169,41.7904891968],"type":"Point"}
}