{
  "type": "Feature",
  "properties": {
    "addr:full":"Rua Zaragoza, 7 Vigo Pontevedra 36203",
    "addr:housenumber":"7",
    "addr:postcode":"36203",
    "addr:street":"Rua Zaragoza",
    "iso:country":"ES",
    "sg:address":"Rua Zaragoza, 7",
    "sg:city":"Vigo",
    "sg:orig_category":"Peluqueros: De Se\u00d1oras",
    "sg:phone":"+34 986 47 32 18",
    "sg:postcode":"36203",
    "sg:province":"Pontevedra",
    "wof:name":"Carrera Garcia Amelia",
    "wof:placetype":"venue"
},
  "geometry": {"coordinates":[-8.7232055664,42.2265892029],"type":"Point"}
}