{
  "type": "Feature",
  "properties": {
    "iso:country":"ES",
    "sg:address":"Calle de Madre Teresa Jornet, 1",
    "sg:city":"Don Benito",
    "sg:orig_category":"Bisuter\u00cda, Joyer\u00cda, Relojer\u00cda (al Por Menor)",
    "sg:phone":"+34 924 80 55 85",
    "sg:postcode":"06400",
    "sg:province":"Badajoz",
    "wof:name":"Mera Sanchez-miranda Eduardo",
    "wof:placetype":"venue"
},
  "geometry": {"coordinates":[-5.8583102226,38.9588127136],"type":"Point"}
}