{
  "type": "Feature",
  "properties": {
    "iso:country":"ES",
    "sg:address":"Calle de Suero De Qui\u00d1ones, 7",
    "sg:city":"Madrid",
    "sg:orig_category":"Radiocomunicaciones, Telefon\u00cda M\u00d3vil, Radiomensajer\u00cda: Servicios, Comercializaci\u00d3n",
    "sg:phone":"+34 915 64 35 46",
    "sg:postcode":"28002",
    "sg:province":"Madrid",
    "wof:name":"Rios Campos Dalila",
    "wof:placetype":"venue"
},
  "geometry": {"coordinates":[-3.6758539677,40.4445114136],"type":"Point"}
}