{
  "type": "Feature",
  "properties": {
    "addr:full":"Cami Betxi, 4 Villarreal Castell\u00f3n 12540",
    "addr:housenumber":"4",
    "addr:postcode":"12540",
    "addr:street":"Betxi",
    "iso:country":"ES",
    "sg:address":"Cami Betxi, 4",
    "sg:city":"Villarreal",
    "sg:orig_category":"Chapister\u00cda",
    "sg:phone":"+34 964 52 33 51",
    "sg:postcode":"12540",
    "sg:province":"Castell\u00f3n",
    "wof:name":"Adsuara Rius Antonio",
    "wof:placetype":"venue"
},
  "geometry": {"coordinates":[-0.1127946004,39.9366874695],"type":"Point"}
}