{
  "type": "Feature",
  "properties": {
    "addr:full":"Calle de San Roque, 17 Majadahonda Madrid 28220",
    "addr:housenumber":"17",
    "addr:postcode":"28220",
    "addr:street":"Calle De San Roque",
    "iso:country":"ES",
    "sg:address":"Calle de San Roque, 17",
    "sg:city":"Majadahonda",
    "sg:orig_category":"Empresarios",
    "sg:phone":"+34 916 39 71 23",
    "sg:postcode":"28220",
    "sg:province":"Madrid",
    "sg:website":"www.redecorsa.com",
    "wof:name":"Redecor S. A",
    "wof:placetype":"venue"
},
  "geometry": {"coordinates":[-3.8774180412,40.4728088379],"type":"Point"}
}