{
  "type": "Feature",
  "properties": {
    "addr:full":"Calle de Corredera, 73 Viso Del Alcor Sevilla 41520",
    "addr:housenumber":"73",
    "addr:postcode":"41520",
    "addr:street":"Calle De Corredera",
    "iso:country":"ES",
    "sg:address":"Calle de Corredera, 73",
    "sg:city":"Viso Del Alcor",
    "sg:orig_category":"Ense\u00d1anza: Profesiones Art\u00cdsticas",
    "sg:phone":"+34 955 94 54 02",
    "sg:postcode":"41520",
    "sg:province":"Sevilla",
    "wof:name":"Santos Benitez Nicolas",
    "wof:placetype":"venue"
},
  "geometry": {"coordinates":[-5.722671032,37.3871765137],"type":"Point"}
}