{
  "type": "Feature",
  "properties": {
    "addr:full":"Puzo, Km. 0292,0 Ponteareas Pontevedra 36869",
    "addr:postcode":"36869",
    "addr:street":"Puzo Km. 0292,0",
    "iso:country":"ES",
    "sg:address":"Puzo, Km. 0292,0",
    "sg:city":"Ponteareas",
    "sg:orig_category":"Distribuci\u00d3n De Petr\u00d3leo Y Derivados",
    "sg:phone":"+34 986 65 59 13",
    "sg:postcode":"36869",
    "sg:province":"Pontevedra",
    "wof:name":"Suministros Y Areas De Servicios Ploc S.a.",
    "wof:placetype":"venue"
},
  "geometry": {"coordinates":[-8.5002822876,42.1918334961],"type":"Point"}
}