{
  "type": "Feature",
  "properties": {
    "addr:full":"Avda Provincias (de Las), 18 Fuenlabrada Madrid 28941",
    "addr:housenumber":"18",
    "addr:postcode":"28941",
    "addr:street":"Avda Provincias De Las",
    "iso:country":"ES",
    "sg:address":"Avda Provincias (de Las), 18",
    "sg:city":"Fuenlabrada",
    "sg:orig_category":"Supermercados Y Hipermercados",
    "sg:phone":"+34 916 06 41 32",
    "sg:postcode":"28941",
    "sg:province":"Madrid",
    "wof:name":"Caprabo S.a.",
    "wof:placetype":"venue"
},
  "geometry": {"coordinates":[-3.8010439873,40.2967071533],"type":"Point"}
}