{
  "type": "Feature",
  "properties": {
    "iso:country":"ES",
    "sg:address":"Carrer de Oms, 37",
    "sg:city":"Palma",
    "sg:orig_category":"Droguer\u00cdas (al Por Menor)",
    "sg:phone":"+34 971 71 75 79",
    "sg:postcode":"07003",
    "sg:province":"Islas Baleares",
    "wof:name":"Campomar Duran Bartolome",
    "wof:placetype":"venue"
},
  "geometry": {"coordinates":[2.6501049995,39.5750465393],"type":"Point"}
}