{
  "type": "Feature",
  "properties": {
    "iso:country":"ES",
    "sg:address":"Pg Nadal, 1",
    "sg:city":"Sant Feliu Llobregat",
    "sg:orig_category":"Inmobiliaria (agencias)",
    "sg:phone":"+34 936 32 59 22",
    "sg:postcode":"08980",
    "sg:province":"Barcelona",
    "wof:name":"Equipo De Gestion De Inmuebles De Negocios Sl",
    "wof:placetype":"venue"
},
  "geometry": {"coordinates":[2.0455610752,41.3822593689],"type":"Point"}
}