{
  "type": "Feature",
  "properties": {
    "addr:full":"Ctra Monte (del), 1 Palencia Palencia 34005",
    "addr:housenumber":"1",
    "addr:postcode":"34005",
    "addr:street":"Ctra Monte Del",
    "iso:country":"ES",
    "sg:address":"Ctra Monte (del), 1",
    "sg:city":"Palencia",
    "sg:orig_category":"Asociaciones, Organismos Culturales Y Socioeducativos",
    "sg:phone":"+34 979 74 09 58",
    "sg:postcode":"34005",
    "sg:province":"Palencia",
    "wof:name":"Agrupacion Social Monte El Viejo",
    "wof:placetype":"venue"
},
  "geometry": {"coordinates":[-5.6433610916,41.0835380554],"type":"Point"}
}