{
  "type": "Feature",
  "properties": {
    "addr:full":"Donostia Ibilbidea, 58 Astigarraga Guip\u00f9zcoa 20115",
    "addr:housenumber":"58",
    "addr:postcode":"20115",
    "addr:street":"Donostia Ibilbidea;Guipu\u0300Zcoa",
    "iso:country":"ES",
    "sg:address":"Donostia Ibilbidea, 58",
    "sg:city":"Astigarraga",
    "sg:orig_category":"Cristaler\u00cdas",
    "sg:phone":"+34 943 55 24 68",
    "sg:postcode":"20115",
    "sg:province":"Guip\u00f9zcoa",
    "sg:website":"www.cristaleriasguipuzcoana.com",
    "wof:name":"Cristaleria Guipuzcoana S.l.",
    "wof:placetype":"venue"
},
  "geometry": {"coordinates":[-1.9522910118,43.2827377319],"type":"Point"}
}