{
  "type": "Feature",
  "properties": {
    "iso:country":"ES",
    "sg:address":"Carrer de Joan Xxiii, 1",
    "sg:city":"Asco",
    "sg:orig_category":"Productores Recolectores, Venta Directa De Vinos",
    "sg:phone":"+34 977 40 50 15",
    "sg:postcode":"43791",
    "sg:province":"Tarragona",
    "wof:name":"Cellers Serra S.l.",
    "wof:placetype":"venue"
},
  "geometry": {"coordinates":[0.5673519969,41.1835861206],"type":"Point"}
}