{
  "type": "Feature",
  "properties": {
    "iso:country":"ES",
    "sg:address":"Calle de Mojon, 4",
    "sg:city":"Burgo Ebro",
    "sg:orig_category":"Cristaler\u00cdas",
    "sg:phone":"+34 976 10 47 78",
    "sg:postcode":"50730",
    "sg:province":"Zaragoza",
    "wof:name":"Cristaleria Las Fuentes S.l.",
    "wof:placetype":"venue"
},
  "geometry": {"coordinates":[-0.7451459765,41.5742111206],"type":"Point"}
}