{
  "type": "Feature",
  "properties": {
    "addr:full":"Muel Ibeni, 1 Bilbao Vizcaya 48006",
    "addr:housenumber":"1",
    "addr:postcode":"48006",
    "addr:street":"Ibeni",
    "iso:country":"ES",
    "sg:address":"Muel Ibeni, 1",
    "sg:city":"Bilbao",
    "sg:orig_category":"Cajas Registradoras, Terminales De Puntos De Venta",
    "sg:phone":"+34 944 15 31 27",
    "sg:postcode":"48006",
    "sg:province":"Vizcaya",
    "wof:name":"Mera Aspuru Juan Miguel",
    "wof:placetype":"venue"
},
  "geometry": {"coordinates":[-2.9224019051,43.2548332214],"type":"Point"}
}