{
  "type": "Feature",
  "properties": {
    "iso:country":"ES",
    "sg:address":"Avda Conquistadores, S/n",
    "sg:city":"Mazagon",
    "sg:orig_category":"Iglesia Cat\u00d3lica",
    "sg:phone":"+34 959 37 61 02",
    "sg:postcode":"21130",
    "sg:province":"Huelva",
    "wof:name":"Parroquia Nuestra Se\u00f1ora Del Carmen",
    "wof:placetype":"venue"
},
  "geometry": {"coordinates":[-6.8282837868,37.1368789673],"type":"Point"}
}