{
  "type": "Feature",
  "properties": {
    "addr:full":"Carrer de Santa Eulalia, 161 Hospitalet Llobregat Barcelona 08902",
    "addr:housenumber":"161",
    "addr:postcode":"08902",
    "addr:street":"Carrer De Santa Eulalia",
    "iso:country":"ES",
    "sg:address":"Carrer de Santa Eulalia, 161",
    "sg:city":"Hospitalet Llobregat",
    "sg:orig_category":"Peluquer\u00cdas, Peluquer\u00cda Mixta",
    "sg:phone":"+34 934 21 35 58",
    "sg:postcode":"08902",
    "sg:province":"Barcelona",
    "wof:name":"Vidal Garcia Carmen",
    "wof:placetype":"venue"
},
  "geometry": {"coordinates":[2.1224489212,41.366230011],"type":"Point"}
}