{
  "type": "Feature",
  "properties": {
    "addr:full":"Carr Virgen Del Carmen, 47 Oliva Valencia 46780",
    "addr:housenumber":"47",
    "addr:postcode":"46780",
    "addr:street":"Carr Virgen Del Carmen",
    "iso:country":"ES",
    "sg:address":"Carr Virgen Del Carmen, 47",
    "sg:city":"Oliva",
    "sg:orig_category":"Carnicer\u00cdas, Carnicer\u00cdas",
    "sg:phone":"+34 962 85 04 81",
    "sg:postcode":"46780",
    "sg:province":"Valencia",
    "wof:name":"Cortes Navarro Daniel",
    "wof:placetype":"venue"
},
  "geometry": {"coordinates":[-0.119851999,38.9187545776],"type":"Point"}
}