{
  "type": "Feature",
  "properties": {
    "iso:country":"ES",
    "sg:address":"Carrer de Queralt, 2",
    "sg:city":"Barcelona",
    "sg:orig_category":"Inmobiliaria (agencias)",
    "sg:phone":"+34 934 06 84 58",
    "sg:postcode":"08017",
    "sg:province":"Barcelona",
    "wof:name":"Finques I Serveis Vallvidrera S. L.",
    "wof:placetype":"venue"
},
  "geometry": {"coordinates":[2.1048109531,41.4132003784],"type":"Point"}
}