{
  "type": "Feature",
  "properties": {
    "addr:full":"Rua Maria, 156 Ferrol La Coru\u00f1a 15401",
    "addr:housenumber":"156",
    "addr:postcode":"15401",
    "addr:street":"Rua Maria;La Corun\u0303A",
    "iso:country":"ES",
    "sg:address":"Rua Maria, 156",
    "sg:city":"Ferrol",
    "sg:orig_category":"Ropa Para Caballeros (al Por Menor)",
    "sg:phone":"+34 981 35 50 51",
    "sg:postcode":"15401",
    "sg:province":"La Coru\u00f1a",
    "wof:name":"Barminton Real S.l.",
    "wof:placetype":"venue"
},
  "geometry": {"coordinates":[-8.2364768982,43.4834442139],"type":"Point"}
}