{
  "type": "Feature",
  "properties": {
    "addr:full":"Av Europa (d'), 28 Blanes Girona 17300",
    "addr:housenumber":"28",
    "addr:postcode":"17300",
    "addr:street":"Av Europa D '",
    "iso:country":"ES",
    "sg:address":"Av Europa (d'), 28",
    "sg:city":"Blanes",
    "sg:orig_category":"Electrodom\u00c9sticos (al Por Menor)",
    "sg:phone":"+34 972 35 08 71",
    "sg:postcode":"17300",
    "sg:province":"Girona",
    "sg:website":"www.idealosada.com",
    "wof:name":"Electrodomestics Losada S.l.",
    "wof:placetype":"venue"
},
  "geometry": {"coordinates":[2.7785339355,41.6719245911],"type":"Point"}
}