{
  "type": "Feature",
  "properties": {
    "addr:full":"Carr Camp Mada, S/n Besalu Girona 17850",
    "addr:housenumber":"s / n",
    "addr:postcode":"17850",
    "addr:street":"Carr Camp Mada",
    "iso:country":"ES",
    "sg:address":"Carr Camp Mada, S/n",
    "sg:city":"Besalu",
    "sg:orig_category":"Electricidad: Instaladores",
    "sg:phone":"+34 972 59 02 90",
    "sg:postcode":"17850",
    "sg:province":"Girona",
    "wof:name":"J.juanola S.l.",
    "wof:placetype":"venue"
},
  "geometry": {"coordinates":[2.698595047,42.2044715881],"type":"Point"}
}