{
  "type": "Feature",
  "properties": {
    "iso:country":"ES",
    "sg:address":"Carrer de Mare De Deu De Port, 234",
    "sg:city":"Barcelona",
    "sg:orig_category":"Farmacias",
    "sg:phone":"+34 933 32 21 94",
    "sg:postcode":"08038",
    "sg:province":"Barcelona",
    "wof:name":"Forns Giro Fernando",
    "wof:placetype":"venue"
},
  "geometry": {"coordinates":[2.1408410072,41.3605461121],"type":"Point"}
}