{
  "type": "Feature",
  "properties": {
    "addr:full":"Avda Portugal De, 25 Rosal Frontera Huelva 21250",
    "addr:housenumber":"25",
    "addr:postcode":"21250",
    "addr:street":"Avda Portugal De",
    "iso:country":"ES",
    "sg:address":"Avda Portugal De, 25",
    "sg:city":"Rosal Frontera",
    "sg:orig_category":"Centros Comerciales Y Grandes Tiendas",
    "sg:phone":"+34 959 14 14 50",
    "sg:postcode":"21250",
    "sg:province":"Huelva",
    "wof:name":"Vargas Carretero Jose Manuel",
    "wof:placetype":"venue"
},
  "geometry": {"coordinates":[-7.2189888954,37.9680595398],"type":"Point"}
}