{
  "type": "Feature",
  "properties": {
    "addr:full":"Calle de Do\u00d1a Blanca, 15 Jerez De La Frontera C\u00e1diz 11402",
    "addr:housenumber":"15",
    "addr:postcode":"11402",
    "addr:street":"Calle De Don\u0303A Blanca",
    "iso:country":"ES",
    "sg:address":"Calle de Do\u00d1a Blanca, 15",
    "sg:city":"Jerez De La Frontera",
    "sg:orig_category":"M\u00c9dicos: Ginecolog\u00cda Y Obstetricia",
    "sg:phone":"+34 956 34 28 42",
    "sg:postcode":"11402",
    "sg:province":"C\u00e1diz",
    "wof:name":"Herrero Gracia Blanca",
    "wof:placetype":"venue"
},
  "geometry": {"coordinates":[-6.1351900101,36.6819190979],"type":"Point"}
}