{
  "type": "Feature",
  "properties": {
    "addr:full":"Ctra. Ferrol, Km. 0002,0 Pontes Garcia Rodriguez A Coru\u00f1a 15320",
    "addr:postcode":"15320",
    "addr:street":"Ctra. Ferrol Km. 0002,0 Pontes Garcia Rodriguez A Corun\u0303A",
    "iso:country":"ES",
    "sg:address":"Ctra. Ferrol, Km. 0002,0",
    "sg:city":"Pontes Garcia Rodriguez",
    "sg:orig_category":"Vulcanizado",
    "sg:phone":"+34 981 44 03 29",
    "sg:postcode":"15320",
    "sg:province":"A Coru\u00f1a",
    "wof:name":"Vulcarol S.l.",
    "wof:placetype":"venue"
},
  "geometry": {"coordinates":[-7.8537707329,43.4504508972],"type":"Point"}
}