{
  "type": "Feature",
  "properties": {
    "iso:country":"ES",
    "sg:address":"Calle de Trasierras, 11",
    "sg:city":"Antequera",
    "sg:orig_category":"Electrodom\u00c9sticos (al Por Menor)",
    "sg:phone":"+34 952 70 36 82",
    "sg:postcode":"29200",
    "sg:province":"M\u00e1laga",
    "wof:name":"Electro-angeluz S.l.",
    "wof:placetype":"venue"
},
  "geometry": {"coordinates":[-4.5572538376,37.0196228027],"type":"Point"}
}