{
  "type": "Feature",
  "properties": {
    "iso:country":"ES",
    "sg:address":"Calle de Virgen De La Fuencisla, 6",
    "sg:city":"Madrid",
    "sg:orig_category":"Materias Pl\u00c1sticas: Art\u00cdculos Para La Industria",
    "sg:phone":"+34 914 04 22 77",
    "sg:postcode":"28027",
    "sg:province":"Madrid",
    "wof:name":"Zamarre\u00f1o Escoda Pilar",
    "wof:placetype":"venue"
},
  "geometry": {"coordinates":[-3.6536333561,40.4366149902],"type":"Point"}
}