{
  "type": "Feature",
  "properties": {
    "addr:full":"Avda Paz (de La), 2 Burgos Burgos 09004",
    "addr:housenumber":"2",
    "addr:postcode":"09004",
    "addr:street":"Avda Paz De La",
    "iso:country":"ES",
    "sg:address":"Avda Paz (de La), 2",
    "sg:city":"Burgos",
    "sg:orig_category":"M\u00c9dicos: Anestesiolog\u00cda Y Reanimaci\u00d3n Quir\u00dargica",
    "sg:phone":"+34 947 27 10 43",
    "sg:postcode":"09004",
    "sg:province":"Burgos",
    "wof:name":"Diez Escribano Javier",
    "wof:placetype":"venue"
},
  "geometry": {"coordinates":[-3.6954679489,42.3437614441],"type":"Point"}
}