{
  "type": "Feature",
  "properties": {
    "addr:full":"Calle de Montesa, 10 Ciudad Real Ciudad Real 13001",
    "addr:housenumber":"10",
    "addr:postcode":"13001",
    "addr:street":"Calle De Montesa",
    "iso:country":"ES",
    "sg:address":"Calle de Montesa, 10",
    "sg:city":"Ciudad Real",
    "sg:orig_category":"Peluqueros: De Se\u00d1oras",
    "sg:phone":"+34 926 25 61 85",
    "sg:postcode":"13001",
    "sg:province":"Ciudad Real",
    "wof:name":"Ruiz Racionero Rosa",
    "wof:placetype":"venue"
},
  "geometry": {"coordinates":[-3.927136898,38.9829292297],"type":"Point"}
}