{
  "type": "Feature",
  "properties": {
    "iso:country":"ES",
    "sg:address":"Calle de Santa Clara, 8",
    "sg:city":"Oviedo",
    "sg:orig_category":"Cl\u00cdnicas Dentales",
    "sg:phone":"+34 985 22 00 75",
    "sg:postcode":"33001",
    "sg:province":"Asturias",
    "wof:name":"Menendez Gonzalez Del Rey Cesar",
    "wof:placetype":"venue"
},
  "geometry": {"coordinates":[-5.8471302986,43.3642578125],"type":"Point"}
}