{
  "type": "Feature",
  "properties": {
    "addr:full":"Cra. Terrassa, Km. 0005,6 Castellbisbal Barcelona 08755",
    "addr:postcode":"08755",
    "addr:street":"Km. 0005,6",
    "iso:country":"ES",
    "sg:address":"Cra. Terrassa, Km. 0005,6",
    "sg:city":"Castellbisbal",
    "sg:orig_category":"Fabrica De Cer\u00c1micas",
    "sg:phone":"+34 937 72 03 57",
    "sg:postcode":"08755",
    "sg:province":"Barcelona",
    "sg:website":"www.teuleriacatalana.com",
    "wof:name":"Imerys Tc Espa\u00f1a S.a.",
    "wof:placetype":"venue"
},
  "geometry": {"coordinates":[1.9784770012,41.4735145569],"type":"Point"}
}