{
  "type": "Feature",
  "properties": {
    "addr:full":"Rbla Principal, 15 Vilanova I La Geltru Barcelona 08800",
    "addr:housenumber":"15",
    "addr:postcode":"08800",
    "addr:street":"Rbla Principal",
    "iso:country":"ES",
    "sg:address":"Rbla Principal, 15",
    "sg:city":"Vilanova I La Geltru",
    "sg:orig_category":"Molduras, Junquillos, Listones Y Molduras Perforadas",
    "sg:phone":"+34 938 93 58 54",
    "sg:postcode":"08800",
    "sg:province":"Barcelona",
    "wof:name":"Suarez Linares Ricardo",
    "wof:placetype":"venue"
},
  "geometry": {"coordinates":[1.7244080305,41.2250518799],"type":"Point"}
}