{
  "type": "Feature",
  "properties": {
    "addr:full":"Calle de Juan Xxiii (de), 4 Totana Murcia 30850",
    "addr:postcode":"30850",
    "addr:street":"Calle De Juan Xxiii De",
    "iso:country":"ES",
    "sg:address":"Calle de Juan Xxiii (de), 4",
    "sg:city":"Totana",
    "sg:orig_category":"Complementos De Vestir (al Por Menor)",
    "sg:phone":"+34 968 42 43 50",
    "sg:postcode":"30850",
    "sg:province":"Murcia",
    "wof:name":"Martinez Ba\u00d1os Rosario",
    "wof:placetype":"venue"
},
  "geometry": {"coordinates":[-1.4992589951,37.7713432312],"type":"Point"}
}