{
  "type": "Feature",
  "properties": {
    "addr:full":"Carr Maestro Serrano, 6 Canals Valencia 46650",
    "addr:housenumber":"6",
    "addr:postcode":"46650",
    "addr:street":"Carr Maestro Serrano",
    "iso:country":"ES",
    "sg:address":"Carr Maestro Serrano, 6",
    "sg:city":"Canals",
    "sg:orig_category":"Caf\u00c9s, Bares, Cervecer\u00cdas",
    "sg:phone":"+34 962 24 08 14",
    "sg:postcode":"46650",
    "sg:province":"Valencia",
    "wof:name":"Ribelles Boluda Pedro Jose",
    "wof:placetype":"venue"
},
  "geometry": {"coordinates":[-0.5856519938,38.9654273987],"type":"Point"}
}