{
  "type": "Feature",
  "properties": {
    "addr:full":"Avda Nicaragua, 8 Benidorm Alicante 03500",
    "addr:housenumber":"8",
    "addr:postcode":"03500",
    "addr:street":"Avda Nicaragua",
    "iso:country":"ES",
    "sg:address":"Avda Nicaragua, 8",
    "sg:city":"Benidorm",
    "sg:orig_category":"Promotores Constructores",
    "sg:phone":"+34 965 85 44 43",
    "sg:postcode":"03500",
    "sg:province":"Alicante",
    "wof:name":"Torrubiano Ramos Emilia",
    "wof:placetype":"venue"
},
  "geometry": {"coordinates":[-0.1385580003,38.5394248962],"type":"Point"}
}