{
  "type": "Feature",
  "properties": {
    "addr:full":"Torelo, 15 Baio La Coru\u00f1a 15150",
    "addr:housenumber":"15",
    "addr:postcode":"15150",
    "addr:street":"Torelo;La Corun\u0303A",
    "iso:country":"ES",
    "sg:address":"Torelo, 15",
    "sg:city":"Baio",
    "sg:orig_category":"Producci\u00d3n, Distribuci\u00d3n De Electricidad",
    "sg:phone":"+34 981 71 84 78",
    "sg:postcode":"15150",
    "sg:province":"La Coru\u00f1a",
    "wof:name":"Electra Do Foxo S.l.",
    "wof:placetype":"venue"
},
  "geometry": {"coordinates":[-8.9681482315,43.147567749],"type":"Point"}
}