{
  "type": "Feature",
  "properties": {
    "iso:country":"ES",
    "sg:address":"Calle de Mayor, 61",
    "sg:city":"Alaquas",
    "sg:orig_category":"Doctores En Medicina",
    "sg:phone":"+34 961 51 08 02",
    "sg:postcode":"46970",
    "sg:province":"Valencia",
    "wof:name":"Taverner Rey Adolfo",
    "wof:placetype":"venue"
},
  "geometry": {"coordinates":[-0.4578439891,39.4546356201],"type":"Point"}
}