{
  "type": "Feature",
  "properties": {
    "iso:country":"ES",
    "sg:address":"Avda Pio Xii, 6",
    "sg:city":"Valencia",
    "sg:orig_category":"\u00d3ptica: Instrumentos (fabricaci\u00d3n)",
    "sg:phone":"+34 963 47 70 50",
    "sg:postcode":"46009",
    "sg:province":"Valencia",
    "wof:name":"Carlos Gago Y Gago C.b.",
    "wof:placetype":"venue"
},
  "geometry": {"coordinates":[-0.3916420043,39.4803962708],"type":"Point"}
}