{
  "type": "Feature",
  "properties": {
    "iso:country":"ES",
    "sg:address":"Calle de Carasol, S/n",
    "sg:city":"Peralejos",
    "sg:orig_category":"Transportes Por V\u00cdas Navegables",
    "sg:phone":"+34 978 66 00 47",
    "sg:postcode":"44162",
    "sg:province":"Teruel",
    "wof:name":"Fuertes Campillo Manuel",
    "wof:placetype":"venue"
},
  "geometry": {"coordinates":[-1.0338089466,40.4831809998],"type":"Point"}
}