{
  "type": "Feature",
  "properties": {
    "addr:full":"Av Gonzalez Robles, 60 Orgiva Granada 18400",
    "addr:housenumber":"60",
    "addr:postcode":"18400",
    "addr:street":"Av Gonzalez Robles",
    "iso:country":"ES",
    "sg:address":"Av Gonzalez Robles, 60",
    "sg:city":"Orgiva",
    "sg:orig_category":"Agencias Y Agentes Comerciales, Representantes",
    "sg:phone":"+34 958 78 50 53",
    "sg:postcode":"18400",
    "sg:province":"Granada",
    "wof:name":"Perez Corvera Jose",
    "wof:placetype":"venue"
},
  "geometry": {"coordinates":[-3.4219191074,36.8977203369],"type":"Point"}
}