{
  "type": "Feature",
  "properties": {
    "addr:full":"Av Diagonal, 280 Barcelona Barcelona 08018",
    "addr:housenumber":"280",
    "addr:postcode":"08018",
    "addr:street":"Av Diagonal",
    "iso:country":"ES",
    "sg:address":"Av Diagonal, 280",
    "sg:city":"Barcelona",
    "sg:orig_category":"Ropa Para Se\u00d1oras Y Caballeros (al Por Menor)",
    "sg:phone":"+34 934 86 03 12",
    "sg:postcode":"08018",
    "sg:province":"Barcelona",
    "wof:name":"Coma Camps Gerard",
    "wof:placetype":"venue"
},
  "geometry": {"coordinates":[2.188297987,41.4038467407],"type":"Point"}
}