{
  "type": "Feature",
  "properties": {
    "addr:full":"Avda Cumbres Las (cerrado Elviria), 22 Elviria M\u00e1laga 29604",
    "addr:housenumber":"22",
    "addr:postcode":"29604",
    "addr:street":"Avda Cumbres Las;Elviria Ma\u0301Laga",
    "iso:country":"ES",
    "sg:address":"Avda Cumbres Las (cerrado Elviria), 22",
    "sg:city":"Elviria",
    "sg:orig_category":"Agencias Y Agentes Comerciales, Representantes",
    "sg:phone":"+34 951 31 01 90",
    "sg:postcode":"29604",
    "sg:province":"M\u00e1laga",
    "wof:name":"Forger  Ferdinand",
    "wof:placetype":"venue"
},
  "geometry": {"coordinates":[-4.7816491127,36.5002708435],"type":"Point"}
}