{
  "type": "Feature",
  "properties": {
    "iso:country":"ES",
    "sg:address":"Carr Eivissa, 15",
    "sg:city":"S. Francesc Formentera",
    "sg:orig_category":"Ropa Para Beb\u00c9s Y Ni\u00d1os (confecci\u00d3n, Al Por Mayor)",
    "sg:phone":"+34 971 32 24 93",
    "sg:postcode":"07860",
    "sg:province":"Islas Baleares",
    "wof:name":"Peque Moda S.c.",
    "wof:placetype":"venue"
},
  "geometry": {"coordinates":[1.4309200048,38.7072410583],"type":"Point"}
}