{
  "type": "Feature",
  "properties": {
    "iso:country":"ES",
    "sg:address":"Calle de Ancla (el), 3",
    "sg:city":"Rota",
    "sg:orig_category":"M\u00c9dicos: Cardiolog\u00cda Y Afecciones Cardiovasculares",
    "sg:phone":"+34 956 81 10 23",
    "sg:postcode":"11520",
    "sg:province":"C\u00e1diz",
    "wof:name":"Cabrera Fernandez Maria Auxiliadora",
    "wof:placetype":"venue"
},
  "geometry": {"coordinates":[-6.3805580139,36.6279335022],"type":"Point"}
}