{
  "type": "Feature",
  "properties": {
    "iso:country":"ES",
    "sg:address":"Plaz Espa\u00d1a, 3",
    "sg:city":"Alconchel",
    "sg:orig_category":"Administraciones Regionales, Departamentales Y Locales",
    "sg:phone":"+34 924 42 00 01",
    "sg:postcode":"06131",
    "sg:province":"Badajoz",
    "wof:name":"Ayuntamiento De Alconchel",
    "wof:placetype":"venue"
},
  "geometry": {"coordinates":[-7.1574783325,38.4973144531],"type":"Point"}
}