{
  "type": "Feature",
  "properties": {
    "iso:country":"ES",
    "sg:address":"Guillermo Reina, 28",
    "sg:city":"Huercal-overa",
    "sg:orig_category":"Abogados",
    "sg:phone":"+34 950 47 04 13",
    "sg:postcode":"04600",
    "sg:province":"Almer\u00eda",
    "wof:name":"Enciso Mena Antero",
    "wof:placetype":"venue"
},
  "geometry": {"coordinates":[-1.9446289539,37.3933143616],"type":"Point"}
}