{
  "type": "Feature",
  "properties": {
    "addr:full":"Carrer de Doctor Valls, 14 Barcelona Barcelona 08041",
    "addr:housenumber":"14",
    "addr:postcode":"08041",
    "addr:street":"Carrer De Doctor Valls",
    "iso:country":"ES",
    "sg:address":"Carrer de Doctor Valls, 14",
    "sg:city":"Barcelona",
    "sg:orig_category":"Ense\u00d1ante, Direcci\u00d3n",
    "sg:phone":"+34 934 36 41 46",
    "sg:postcode":"08041",
    "sg:province":"Barcelona",
    "wof:name":"Colomer Garcia Tomas",
    "wof:placetype":"venue"
},
  "geometry": {"coordinates":[2.1792960167,41.4201469421],"type":"Point"}
}