{
  "type": "Feature",
  "properties": {
    "addr:full":"Calquillas (las), 7 Alcala Rio Sevilla 41200",
    "addr:postcode":"41200",
    "addr:street":"Las;Alcala",
    "iso:country":"ES",
    "sg:address":"Calquillas (las), 7",
    "sg:city":"Alcala Rio",
    "sg:orig_category":"M\u00c1rmoles, Granitos Y Piedras Naturales",
    "sg:phone":"+34 954 78 03 60",
    "sg:postcode":"41200",
    "sg:province":"Sevilla",
    "wof:name":"Ilipa Sociedad Limitada",
    "wof:placetype":"venue"
},
  "geometry": {"coordinates":[-5.9764618874,37.5232086182],"type":"Point"}
}