{
  "type": "Feature",
  "properties": {
    "iso:country":"ES",
    "sg:address":"Ctra Ribes, 196",
    "sg:city":"Corro D'avall",
    "sg:orig_category":"Abogados",
    "sg:phone":"+34 938 46 60 82",
    "sg:postcode":"08520",
    "sg:province":"Barcelona",
    "wof:name":"Blasco Yuste Nuria",
    "wof:placetype":"venue"
},
  "geometry": {"coordinates":[2.2878687382,41.6696929932],"type":"Point"}
}