{
  "type": "Feature",
  "properties": {
    "iso:country":"ES",
    "sg:address":"Avda Pumarin De, 7",
    "sg:city":"Oviedo",
    "sg:orig_category":"Loter\u00cda Y T\u00d3mbola",
    "sg:phone":"+34 985 28 51 58",
    "sg:postcode":"33001",
    "sg:province":"Asturias",
    "wof:name":"Gallego Rodriguez Maria Esperanza",
    "wof:placetype":"venue"
},
  "geometry": {"coordinates":[-5.8460564613,43.3666229248],"type":"Point"}
}