{
  "type": "Feature",
  "properties": {
    "addr:full":"La Atalaya, 4 Limpias Cantabria 39820",
    "addr:housenumber":"4",
    "addr:postcode":"39820",
    "addr:street":"La Atalaya",
    "iso:country":"ES",
    "sg:address":"La Atalaya, 4",
    "sg:city":"Limpias",
    "sg:orig_category":"Confiter\u00cdas, Chocolater\u00cdas (al Por Menor)",
    "sg:phone":"+34 942 62 28 34",
    "sg:postcode":"39820",
    "sg:province":"Cantabria",
    "wof:name":"Bellanco Fernandez Angeles",
    "wof:placetype":"venue"
},
  "geometry": {"coordinates":[-3.426074028,43.3603439331],"type":"Point"}
}