{
  "type": "Feature",
  "properties": {
    "iso:country":"ES",
    "sg:address":"Rua Progreso (do), 14",
    "sg:city":"Ribadavia",
    "sg:orig_category":"Ropa Para Se\u00d1oras Y Caballeros (al Por Menor)",
    "sg:phone":"+34 988 47 09 06",
    "sg:postcode":"32400",
    "sg:province":"Ourense",
    "wof:name":"Lamas Alonso Maria Purificacion",
    "wof:placetype":"venue"
},
  "geometry": {"coordinates":[-8.1426792145,42.2901611328],"type":"Point"}
}