{
  "type": "Feature",
  "properties": {
    "addr:full":"C/ Sant Vicent, 16 Elche Alicante 03202",
    "addr:housenumber":"16",
    "addr:postcode":"03202",
    "addr:street":"C / Sant Vicent",
    "iso:country":"ES",
    "sg:address":"C/ Sant Vicent, 16",
    "sg:city":"Elche",
    "sg:orig_category":"Asociaciones Humanitarias, De Cooperaci\u00d3n, De Acci\u00d3n Social",
    "sg:phone":"+34 966 61 12 21",
    "sg:postcode":"03202",
    "sg:province":"Alicante",
    "wof:name":"Asociacion Espa\u00f1ola Contra El Cancer",
    "wof:placetype":"venue"
},
  "geometry": {"coordinates":[-0.6947317719,38.2677726746],"type":"Point"}
}