{
  "type": "Feature",
  "properties": {
    "iso:country":"ES",
    "sg:address":"Carrer de Arcadi Balaguer, 43",
    "sg:city":"Castelldefels",
    "sg:orig_category":"Empresarios",
    "sg:phone":"+34 936 35 01 69",
    "sg:postcode":"08860",
    "sg:province":"Barcelona",
    "wof:name":"Arellano Santana Manuel",
    "wof:placetype":"venue"
},
  "geometry": {"coordinates":[1.9781701565,41.2810096741],"type":"Point"}
}