{
  "type": "Feature",
  "properties": {
    "addr:full":"Calle de Doctor Jare\u00d1o, 15 Casas De Haro Cuenca 16611",
    "addr:housenumber":"15",
    "addr:postcode":"16611",
    "addr:street":"Calle De Doctor Jaren\u0303O",
    "iso:country":"ES",
    "sg:address":"Calle de Doctor Jare\u00d1o, 15",
    "sg:city":"Casas De Haro",
    "sg:orig_category":"Cajas Para Embalar",
    "sg:phone":"+34 969 38 07 99",
    "sg:postcode":"16611",
    "sg:province":"Cuenca",
    "wof:name":"Caja Rural De Cuenca",
    "wof:placetype":"venue"
},
  "geometry": {"coordinates":[-2.2701919079,39.3280334473],"type":"Point"}
}