{
  "type": "Feature",
  "properties": {
    "iso:country":"ES",
    "sg:address":"Avgd Major, 34",
    "sg:city":"Massamagrell",
    "sg:orig_category":"Notarios",
    "sg:phone":"+34 961 44 09 36",
    "sg:postcode":"46130",
    "sg:province":"Valencia",
    "wof:name":"Messana Salinas Amparo",
    "wof:placetype":"venue"
},
  "geometry": {"coordinates":[-0.331220001,39.5705528259],"type":"Point"}
}