{
  "type": "Feature",
  "properties": {
    "iso:country":"ES",
    "sg:address":"Carr Barcelona, 11",
    "sg:city":"Girona",
    "sg:orig_category":"Arquitectos",
    "sg:phone":"+34 972 21 43 70",
    "sg:postcode":"17002",
    "sg:province":"Girona",
    "wof:name":"K.g.b. Arquitectura Urbanisme I Disseny S.l.",
    "wof:placetype":"venue"
},
  "geometry": {"coordinates":[2.8189389706,41.9810600281],"type":"Point"}
}