{
  "type": "Feature",
  "properties": {
    "addr:full":"Sect Literatos, 12 Tres Cantos Madrid 28760",
    "addr:housenumber":"12",
    "addr:postcode":"28760",
    "addr:street":"Literatos",
    "iso:country":"ES",
    "sg:address":"Sect Literatos, 12",
    "sg:city":"Tres Cantos",
    "sg:orig_category":"Asociaciones, Organismos Culturales Y Socioeducativos",
    "sg:phone":"+34 918 03 78 00",
    "sg:postcode":"28760",
    "sg:province":"Madrid",
    "wof:name":"Ayuntamiento De Tres Cantos",
    "wof:placetype":"venue"
},
  "geometry": {"coordinates":[-3.711165905,40.6074943542],"type":"Point"}
}