{
  "type": "Feature",
  "properties": {
    "addr:full":"Calle de Trinitarios, 15 Valencia Valencia 46003",
    "addr:housenumber":"15",
    "addr:postcode":"46003",
    "addr:street":"Calle De Trinitarios",
    "iso:country":"ES",
    "sg:address":"Calle de Trinitarios, 15",
    "sg:city":"Valencia",
    "sg:orig_category":"Arquitectos",
    "sg:phone":"+34 963 92 47 49",
    "sg:postcode":"46003",
    "sg:province":"Valencia",
    "wof:name":"Campos Silla Ignacio",
    "wof:placetype":"venue"
},
  "geometry": {"coordinates":[-0.3718880117,39.4769248962],"type":"Point"}
}