{
  "type": "Feature",
  "properties": {
    "iso:country":"ES",
    "sg:address":"Calle de Juan Calzada Kalea, 89",
    "sg:city":"Gernika-lumo",
    "sg:orig_category":"Motocicletas (agentes, Concesionarios)",
    "sg:phone":"+34 946 25 76 29",
    "sg:postcode":"48300",
    "sg:province":"Vizcaya",
    "wof:name":"Moto Shop,jose Maria Arrien  Marina",
    "wof:placetype":"venue"
},
  "geometry": {"coordinates":[-2.6804020405,43.3076553345],"type":"Point"}
}