{
  "type": "Feature",
  "properties": {
    "addr:full":"Calle de Magnesio, 8 Valladolid Valladolid 47012",
    "addr:housenumber":"8",
    "addr:postcode":"47012",
    "addr:street":"Calle De Magnesio",
    "iso:country":"ES",
    "sg:address":"Calle de Magnesio, 8",
    "sg:city":"Valladolid",
    "sg:orig_category":"Cr\u00cda De Poller\u00cda Y De Conejos",
    "sg:phone":"+34 983 20 11 34",
    "sg:postcode":"47012",
    "sg:province":"Valladolid",
    "sg:website":"www.ingenieriaavicola.com",
    "wof:name":"Ingenieria Avicola S.l.",
    "wof:placetype":"venue"
},
  "geometry": {"coordinates":[-4.7072901726,41.6268806458],"type":"Point"}
}