{
  "type": "Feature",
  "properties": {
    "addr:full":"Calle de Hernan Cortes, 8 Almansa Albacete 02640",
    "addr:housenumber":"8",
    "addr:postcode":"02640",
    "addr:street":"Calle De Hernan Cortes",
    "iso:country":"ES",
    "sg:address":"Calle de Hernan Cortes, 8",
    "sg:city":"Almansa",
    "sg:orig_category":"Fotograf\u00cda Art\u00cdstica Y Retratos",
    "sg:phone":"+34 967 34 00 63",
    "sg:postcode":"02640",
    "sg:province":"Albacete",
    "wof:name":"Mora Matea Miguel",
    "wof:placetype":"venue"
},
  "geometry": {"coordinates":[-1.0912419558,38.8624458313],"type":"Point"}
}