{
  "type": "Feature",
  "properties": {
    "addr:full":"Carrer de Montblanc (de), 7 Torreforta Tarragona 43006",
    "addr:postcode":"43006",
    "addr:street":"Carrer De Montblanc De 7 Torreforta",
    "iso:country":"ES",
    "sg:address":"Carrer de Montblanc (de), 7",
    "sg:city":"Torreforta",
    "sg:orig_category":"Venta, Colocaci\u00d3n, Reparaci\u00d3n De Radiadores Para Veh\u00cdculos",
    "sg:phone":"+34 977 54 43 80",
    "sg:postcode":"43006",
    "sg:province":"Tarragona",
    "wof:name":"Rull Amoros Candido",
    "wof:placetype":"venue"
},
  "geometry": {"coordinates":[1.2188659906,41.1163825989],"type":"Point"}
}