{
  "type": "Feature",
  "properties": {
    "addr:full":"Calle de Garcia Lorca, 4 Membrilla Ciudad Real 13230",
    "addr:housenumber":"4",
    "addr:postcode":"13230",
    "addr:street":"Calle De Garcia Lorca",
    "iso:country":"ES",
    "sg:address":"Calle de Garcia Lorca, 4",
    "sg:city":"Membrilla",
    "sg:classifiers":[
        {
            "category":"Autos & Motor Vehicles",
            "subcategory":"Automobile Sales",
            "type":"Retail Goods"
        }
    ],
    "sg:phone":"+34 926 63 63 85",
    "sg:postcode":"13230",
    "sg:province":"Ciudad Real",
    "wof:name":"Autoescuela Virgen Espino S.l.",
    "wof:placetype":"venue"
},
  "geometry": {"coordinates":[-3.3455960751,38.9713935852],"type":"Point"}
}