{
  "type": "Feature",
  "properties": {
    "addr:full":"Calle de Honduras, 1 Vitoria-gasteiz \u00c1lava 01009",
    "addr:housenumber":"1",
    "addr:postcode":"01009",
    "addr:street":"Calle De Honduras",
    "iso:country":"ES",
    "sg:address":"Calle de Honduras, 1",
    "sg:city":"Vitoria-gasteiz",
    "sg:orig_category":"Peluqueros: De Se\u00d1oras",
    "sg:phone":"+34 945 27 33 81",
    "sg:postcode":"01009",
    "sg:province":"\u00c1lava",
    "wof:name":"Frias Saez Maria Mercedes",
    "wof:placetype":"venue"
},
  "geometry": {"coordinates":[-2.6814899445,42.858341217],"type":"Point"}
}