{
  "type": "Feature",
  "properties": {
    "addr:full":"Carrer de Carrer de Pto Rico, S/n Puerto Rico Las Palmas 35130",
    "addr:housenumber":"s / n",
    "addr:postcode":"35130",
    "addr:street":"Carrer;Carrer De;Rico",
    "iso:country":"ES",
    "sg:address":"Carrer de Carrer de Pto Rico, S/n",
    "sg:city":"Puerto Rico",
    "sg:orig_category":"Bisuter\u00cda, Joyer\u00cda, Relojer\u00cda (al Por Menor)",
    "sg:phone":"+34 928 56 18 83",
    "sg:postcode":"35130",
    "sg:province":"Las Palmas",
    "wof:name":"Joyeria Helga S.l.",
    "wof:placetype":"venue"
},
  "geometry": {"coordinates":[-15.7087993622,27.7916240692],"type":"Point"}
}