{
  "type": "Feature",
  "properties": {
    "addr:full":"Carrer de S Isidre Llaurador, 29 Palma Islas Baleares 07005",
    "addr:housenumber":"29",
    "addr:postcode":"07005",
    "addr:street":"Carrer De S Isidre Llaurador",
    "iso:country":"ES",
    "sg:address":"Carrer de S Isidre Llaurador, 29",
    "sg:city":"Palma",
    "sg:orig_category":"Mec\u00c1nico Del Autom\u00d3vil",
    "sg:phone":"+34 971 27 42 80",
    "sg:postcode":"07005",
    "sg:province":"Islas Baleares",
    "wof:name":"Salas Sabater Antonio",
    "wof:placetype":"venue"
},
  "geometry": {"coordinates":[2.6670649052,39.5825500488],"type":"Point"}
}