{
  "type": "Feature",
  "properties": {
    "iso:country":"ES",
    "sg:address":"Calle de Aretxeta, 6",
    "sg:city":"Getxo",
    "sg:orig_category":"Agencias Y Agentes Comerciales, Representantes",
    "sg:phone":"+34 946 02 22 51",
    "sg:postcode":"48990",
    "sg:province":"Vizcaya",
    "wof:name":"Zomaga, S.l.",
    "wof:placetype":"venue"
},
  "geometry": {"coordinates":[-3.0082380772,43.3406066895],"type":"Point"}
}