{
  "type": "Feature",
  "properties": {
    "iso:country":"ES",
    "sg:address":"Rua Carballi\u00d1o (do), 40",
    "sg:city":"Ribadavia",
    "sg:classifiers":[
        {
            "category":"Communications",
            "type":"Services"
        }
    ],
    "sg:phone":"+34 988 47 22 32",
    "sg:postcode":"32400",
    "sg:province":"Ourense",
    "sg:tags":[
        "televisiones",
        "y",
        "radio"
    ],
    "wof:name":"Radio Orense Sociedad Anonima",
    "wof:placetype":"venue"
},
  "geometry": {"coordinates":[-8.1434307098,42.2893867493],"type":"Point"}
}