{
  "type": "Feature",
  "properties": {
    "iso:country":"ES",
    "sg:address":"Carrer de Empedrat, 31",
    "sg:city":"Ibi",
    "sg:orig_category":"Confecci\u00d3n (fabricaci\u00d3n, Al Por Mayor)",
    "sg:phone":"+34 965 55 42 05",
    "sg:postcode":"03440",
    "sg:province":"Alicante",
    "wof:name":"Reche Carrillo Jose",
    "wof:placetype":"venue"
},
  "geometry": {"coordinates":[-0.5756390095,38.6262397766],"type":"Point"}
}