{
  "type": "Feature",
  "properties": {
    "addr:full":"Calle de San Antonio, 32 Dos Hermanas Sevilla 41700",
    "addr:housenumber":"32",
    "addr:postcode":"41700",
    "addr:street":"Calle De San Antonio",
    "iso:country":"ES",
    "sg:address":"Calle de San Antonio, 32",
    "sg:city":"Dos Hermanas",
    "sg:orig_category":"Empresas De Carpinter\u00cda De Madera",
    "sg:phone":"+34 955 66 62 10",
    "sg:postcode":"41700",
    "sg:province":"Sevilla",
    "wof:name":"Gallardo Vazquez Pedro",
    "wof:placetype":"venue"
},
  "geometry": {"coordinates":[-5.9162302017,37.2802734375],"type":"Point"}
}