{
  "type": "Feature",
  "properties": {
    "addr:full":"Ctra Nijar Alquian, 143 Alquian Almer\u00eda 04130",
    "addr:housenumber":"143",
    "addr:postcode":"04130",
    "addr:street":"Ctra Nijar Alquian;Almeri\u0301A",
    "iso:country":"ES",
    "sg:address":"Ctra Nijar Alquian, 143",
    "sg:city":"Alquian",
    "sg:orig_category":"Mercer\u00cda, Lencer\u00cda (al Por Menor)",
    "sg:phone":"+34 950 29 72 41",
    "sg:postcode":"04130",
    "sg:province":"Almer\u00eda",
    "wof:name":"Sanchez Lopez Maria Del Carmen",
    "wof:placetype":"venue"
},
  "geometry": {"coordinates":[-2.3531990051,36.8526000977],"type":"Point"}
}