{
  "type": "Feature",
  "properties": {
    "iso:country":"ES",
    "sg:address":"Calle de Capitan Postigo, 3",
    "sg:city":"Villena",
    "sg:orig_category":"Insecticidas, Fumigaci\u00d3n",
    "sg:phone":"+34 965 80 26 47",
    "sg:postcode":"03400",
    "sg:province":"Alicante",
    "wof:name":"Frances Sanjuan Pedro Joaquin",
    "wof:placetype":"venue"
},
  "geometry": {"coordinates":[-0.8684632778,38.6388778687],"type":"Point"}
}