{
  "type": "Feature",
  "properties": {
    "iso:country":"ES",
    "sg:address":"Calle de Rosario, 137",
    "sg:city":"Albacete",
    "sg:orig_category":"Producci\u00d3n, Distribuci\u00d3n De Electricidad",
    "sg:phone":"+34 967 23 31 17",
    "sg:postcode":"02003",
    "sg:province":"Albacete",
    "wof:name":"Cerro Iniesta Gaspar",
    "wof:placetype":"venue"
},
  "geometry": {"coordinates":[-1.8622790575,38.9860687256],"type":"Point"}
}