{
  "type": "Feature",
  "properties": {
    "iso:country":"ES",
    "sg:address":"Calle de Leitariegos, 19",
    "sg:city":"Villablino",
    "sg:classifiers":[
        {
            "category":"Autos & Motor Vehicles",
            "subcategory":"Automobile Sales",
            "type":"Retail Goods"
        }
    ],
    "sg:phone":"+34 987 47 02 93",
    "sg:postcode":"24100",
    "sg:province":"Le\u00f3n",
    "wof:name":"Autoescuelas Laciana S.a",
    "wof:placetype":"venue"
},
  "geometry": {"coordinates":[-6.321117878,42.9387702942],"type":"Point"}
}