{
  "type": "Feature",
  "properties": {
    "addr:full":"Calle de Candelario, 26 Salamanca Salamanca 37007",
    "addr:housenumber":"26",
    "addr:postcode":"37007",
    "addr:street":"Calle De Candelario",
    "iso:country":"ES",
    "sg:address":"Calle de Candelario, 26",
    "sg:city":"Salamanca",
    "sg:orig_category":"Carnicer\u00cdas, Carnicer\u00cdas",
    "sg:phone":"+34 923 25 29 00",
    "sg:postcode":"37007",
    "sg:province":"Salamanca",
    "wof:name":"Sanchez Ramos Lorenzo",
    "wof:placetype":"venue"
},
  "geometry": {"coordinates":[-5.6727099419,40.9715614319],"type":"Point"}
}