{
  "type": "Feature",
  "properties": {
    "addr:full":"Calle de Cardenal Cisneros, 12 Avila \u00c1vila 05003",
    "addr:housenumber":"12",
    "addr:postcode":"05003",
    "addr:street":"Calle De Cardenal Cisneros;A\u0301Vila",
    "iso:country":"ES",
    "sg:address":"Calle de Cardenal Cisneros, 12",
    "sg:city":"Avila",
    "sg:orig_category":"Iglesias Cristianas Diversas",
    "sg:phone":"+34 920 22 83 06",
    "sg:postcode":"05003",
    "sg:province":"\u00c1vila",
    "wof:name":"Asamblea Cristiana Biblica Avila",
    "wof:placetype":"venue"
},
  "geometry": {"coordinates":[-4.6883010864,40.6514549255],"type":"Point"}
}