{
  "type": "Feature",
  "properties": {
    "addr:full":"Calle de Toledo, 28 Ciudad Real Ciudad Real 13003",
    "addr:housenumber":"28",
    "addr:postcode":"13003",
    "addr:street":"Calle De Toledo",
    "iso:country":"ES",
    "sg:address":"Calle de Toledo, 28",
    "sg:city":"Ciudad Real",
    "sg:orig_category":"Colchones (fabricaci\u00d3n, Al Por Mayor, Al Por Menor)",
    "sg:phone":"+34 926 25 07 54",
    "sg:postcode":"13003",
    "sg:province":"Ciudad Real",
    "sg:website":"www.noctalia.es",
    "wof:name":"Noctalia",
    "wof:placetype":"venue"
},
  "geometry": {"coordinates":[-3.9280788898,38.9897918701],"type":"Point"}
}