{
  "type": "Feature",
  "properties": {
    "iso:country":"ES",
    "sg:address":"Carrer de Verdaguer I Callis, 10",
    "sg:city":"Barcelona",
    "sg:orig_category":"Asociaciones, Organismos Culturales Y Socioeducativos",
    "sg:phone":"+34 933 19 55 50",
    "sg:postcode":"08003",
    "sg:province":"Barcelona",
    "wof:name":"Casal Lambda",
    "wof:placetype":"venue"
},
  "geometry": {"coordinates":[2.1760110855,41.3872261047],"type":"Point"}
}