{
  "type": "Feature",
  "properties": {
    "iso:country":"ES",
    "sg:address":"Calle de Maestro Ramon Corell, 8",
    "sg:city":"Foios",
    "sg:classifiers":[
        {
            "category":"Banks & Credit Unions",
            "subcategory":"Bureau De Change",
            "type":"Services"
        }
    ],
    "sg:phone":"+34 961 48 04 69",
    "sg:postcode":"46134",
    "sg:province":"Valencia",
    "sg:tags":[
        "organismos",
        "control"
    ],
    "wof:name":"Tecnologia Y Calidad Mediterranea S.l.",
    "wof:placetype":"venue"
},
  "geometry": {"coordinates":[-0.3559390008,39.5373840332],"type":"Point"}
}