{
  "type": "Feature",
  "properties": {
    "addr:full":"Avda Constitucion, 1 Villanueva Arzobispo Ja\u00e9n 23330",
    "addr:housenumber":"1",
    "addr:postcode":"23330",
    "addr:street":"Avda Constitucion",
    "iso:country":"ES",
    "sg:address":"Avda Constitucion, 1",
    "sg:city":"Villanueva Arzobispo",
    "sg:orig_category":"Cajas De Ahorro",
    "sg:phone":"+34 953 45 25 96",
    "sg:postcode":"23330",
    "sg:province":"Ja\u00e9n",
    "wof:name":"Unicaja",
    "wof:placetype":"venue"
},
  "geometry": {"coordinates":[-3.0101931095,38.1691131592],"type":"Point"}
}