{
  "type": "Feature",
  "properties": {
    "addr:full":"Plg. Industrial De Manzanares, S/n Manzanares Ciudad Real 13200",
    "addr:housenumber":"s / n",
    "addr:postcode":"13200",
    "iso:country":"ES",
    "sg:address":"Plg. Industrial De Manzanares, S/n",
    "sg:city":"Manzanares",
    "sg:orig_category":"Asesor\u00cda Sobre Comunicaci\u00d3n De Empresas",
    "sg:phone":"+34 926 62 12 65",
    "sg:postcode":"13200",
    "sg:province":"Ciudad Real",
    "wof:name":"Proyectos Asesoria Y Servicios S.a.",
    "wof:placetype":"venue"
},
  "geometry": {"coordinates":[-3.3727400303,38.9944419861],"type":"Point"}
}