{
  "type": "Feature",
  "properties": {
    "iso:country":"ES",
    "sg:address":"Av Sant Julia, 30",
    "sg:city":"Granollers",
    "sg:orig_category":"Material Hidr\u00c1ulico",
    "sg:phone":"+34 938 61 69 80",
    "sg:postcode":"08403",
    "sg:province":"Barcelona",
    "sg:website":"www.fontas.es",
    "wof:name":"Fontan Racoreria S.a.",
    "wof:placetype":"venue"
},
  "geometry": {"coordinates":[2.2765750885,41.5985984802],"type":"Point"}
}