{
  "type": "Feature",
  "properties": {
    "iso:country":"ES",
    "sg:address":"Calle de Benjumeda, 29",
    "sg:city":"Cadiz",
    "sg:orig_category":"Internados & Ense\u00d1anza Privada",
    "sg:phone":"+34 956 22 71 08",
    "sg:postcode":"11003",
    "sg:province":"C\u00e1diz",
    "wof:name":"Hermanas De La Compa\u00f1ia De La Cruz",
    "wof:placetype":"venue"
},
  "geometry": {"coordinates":[-6.3003163338,36.5336265564],"type":"Point"}
}