{
  "type": "Feature",
  "properties": {
    "addr:full":"Ctra Agramunt, 16 Artesa Segre Lleida 25730",
    "addr:housenumber":"16",
    "addr:postcode":"25730",
    "addr:street":"Ctra Agramunt",
    "iso:country":"ES",
    "sg:address":"Ctra Agramunt, 16",
    "sg:city":"Artesa Segre",
    "sg:orig_category":"Cajas De Ahorro",
    "sg:phone":"+34 973 40 12 49",
    "sg:postcode":"25730",
    "sg:province":"Lleida",
    "wof:name":"Caixa D'estalvis Del Penedes",
    "wof:placetype":"venue"
},
  "geometry": {"coordinates":[1.0474630594,41.8951911926],"type":"Point"}
}