{
  "type": "Feature",
  "properties": {
    "iso:country":"ES",
    "sg:address":"Rua Melide, 8",
    "sg:city":"Lalin",
    "sg:orig_category":"Asesor\u00cda, Estudio Y Control Medioambiental",
    "sg:phone":"+34 986 78 39 03",
    "sg:postcode":"36500",
    "sg:province":"Pontevedra",
    "wof:name":"Soluciones Integrales Para El Medio Ambiente",
    "wof:placetype":"venue"
},
  "geometry": {"coordinates":[-8.1080970764,42.662021637],"type":"Point"}
}