{
  "type": "Feature",
  "properties": {
    "iso:country":"ES",
    "sg:address":"Avda San Jose De La Monta\u00d1a, 6",
    "sg:city":"Valencia",
    "sg:orig_category":"Ropa Para Se\u00d1oras (al Por Menor)",
    "sg:phone":"+34 963 85 45 03",
    "sg:postcode":"46008",
    "sg:province":"Valencia",
    "wof:name":"Lorca Boluda Teresa",
    "wof:placetype":"venue"
},
  "geometry": {"coordinates":[-0.3926610053,39.4746360779],"type":"Point"}
}