{
  "type": "Feature",
  "properties": {
    "addr:full":"Avda Espa\u00d1a, 31 Ponferrada Le\u00f3n 24400",
    "addr:housenumber":"31",
    "addr:postcode":"24400",
    "addr:street":"Avda Espan\u0303A",
    "iso:country":"ES",
    "sg:address":"Avda Espa\u00d1a, 31",
    "sg:city":"Ponferrada",
    "sg:orig_category":"Abogados",
    "sg:phone":"+34 987 42 95 93",
    "sg:postcode":"24400",
    "sg:province":"Le\u00f3n",
    "wof:name":"Alvarez Rubio Francisco Javier",
    "wof:placetype":"venue"
},
  "geometry": {"coordinates":[-6.6020541191,42.5473594666],"type":"Point"}
}