{
  "type": "Feature",
  "properties": {
    "iso:country":"ES",
    "sg:address":"Trav De Gracia, 90",
    "sg:city":"Barcelona",
    "sg:orig_category":"Fabricaci\u00d3n De Sobres, Bolsas Y Fundas",
    "sg:phone":"+34 932 37 13 55",
    "sg:postcode":"08006",
    "sg:province":"Barcelona",
    "wof:name":"Viader Marti Rosa",
    "wof:placetype":"venue"
},
  "geometry": {"coordinates":[2.1527369022,41.3979606628],"type":"Point"}
}