{
  "type": "Feature",
  "properties": {
    "addr:full":"Calle de San Victor, 1 Sevilla Sevilla 41005",
    "addr:housenumber":"1",
    "addr:postcode":"41005",
    "addr:street":"Calle De San Victor",
    "iso:country":"ES",
    "sg:address":"Calle de San Victor, 1",
    "sg:city":"Sevilla",
    "sg:orig_category":"Cl\u00cdnicas Dentales",
    "sg:phone":"+34 954 63 86 84",
    "sg:postcode":"41005",
    "sg:province":"Sevilla",
    "wof:name":"Union Dental Hispalense Sl",
    "wof:placetype":"venue"
},
  "geometry": {"coordinates":[-5.9679598808,37.3754577637],"type":"Point"}
}