{
  "type": "Feature",
  "properties": {
    "iso:country":"ES",
    "sg:address":"Calle de Maria Orue, 1",
    "sg:city":"Madrid",
    "sg:orig_category":"Empresas De Carpinter\u00cda De Madera",
    "sg:phone":"+34 917 96 70 81",
    "sg:postcode":"28021",
    "sg:province":"Madrid",
    "wof:name":"Redecor Proyectos S.l",
    "wof:placetype":"venue"
},
  "geometry": {"coordinates":[-3.6860220432,40.3529777527],"type":"Point"}
}