{
  "type": "Feature",
  "properties": {
    "iso:country":"ES",
    "sg:address":"Calle de Marques De Villores, 47",
    "sg:city":"Albacete",
    "sg:orig_category":"Agencias Y Agentes Comerciales, Representantes",
    "sg:phone":"+34 967 22 52 18",
    "sg:postcode":"02003",
    "sg:province":"Albacete",
    "wof:name":"Alvarez Mejias Antonio",
    "wof:placetype":"venue"
},
  "geometry": {"coordinates":[-1.8586322069,38.9889640808],"type":"Point"}
}