{
  "type": "Feature",
  "properties": {
    "iso:country":"ES",
    "sg:address":"Avda Portugal (de), 80",
    "sg:city":"Mostoles",
    "sg:orig_category":"Estancos",
    "sg:phone":"+34 916 14 53 15",
    "sg:postcode":"28935",
    "sg:province":"Madrid",
    "wof:name":"Moreno Gonzalez Raimundo",
    "wof:placetype":"venue"
},
  "geometry": {"coordinates":[-3.8757860661,40.3210983276],"type":"Point"}
}