{
  "type": "Feature",
  "properties": {
    "addr:full":"Calle de Renio, 15 Sevilla Sevilla 41007",
    "addr:housenumber":"15",
    "addr:postcode":"41007",
    "addr:street":"Calle De Renio",
    "iso:country":"ES",
    "sg:address":"Calle de Renio, 15",
    "sg:city":"Sevilla",
    "sg:orig_category":"Promotores Constructores",
    "sg:phone":"+34 954 35 46 69",
    "sg:postcode":"41007",
    "sg:province":"Sevilla",
    "wof:name":"Ainoa Obras S.l.",
    "wof:placetype":"venue"
},
  "geometry": {"coordinates":[-5.954685688,37.4082946777],"type":"Point"}
}