{
  "type": "Feature",
  "properties": {
    "iso:country":"ES",
    "sg:address":"Calle de Vatemar, 7",
    "sg:city":"Bembibre",
    "sg:orig_category":"Caf\u00c9s, Bares, Cervecer\u00cdas",
    "sg:phone":"+34 987 51 13 17",
    "sg:postcode":"24300",
    "sg:province":"Le\u00f3n",
    "wof:name":"Alfayete Alvarez Roberto",
    "wof:placetype":"venue"
},
  "geometry": {"coordinates":[-6.4176497459,42.6164054871],"type":"Point"}
}