{
  "type": "Feature",
  "properties": {
    "iso:country":"ES",
    "sg:address":"Pl. Los Fueros, 16",
    "sg:city":"Estella",
    "sg:orig_category":"Abogados",
    "sg:phone":"+34 948 54 66 86",
    "sg:postcode":"31200",
    "sg:province":"Navarra",
    "wof:name":"Oses Orea Charo",
    "wof:placetype":"venue"
},
  "geometry": {"coordinates":[-2.0320260525,42.6720733643],"type":"Point"}
}