{
  "type": "Feature",
  "properties": {
    "addr:full":"Calle de Union, 23 Malaga M\u00e1laga 29006",
    "addr:housenumber":"23",
    "addr:postcode":"29006",
    "addr:street":"Calle De;Malaga Ma\u0301Laga",
    "iso:country":"ES",
    "sg:address":"Calle de Union, 23",
    "sg:city":"Malaga",
    "sg:orig_category":"M\u00c9dicos: An\u00c1lisis Cl\u00cdnicos",
    "sg:phone":"+34 952 32 63 21",
    "sg:postcode":"29006",
    "sg:province":"M\u00e1laga",
    "wof:name":"Fernandez Garcia Maria Purificacion",
    "wof:placetype":"venue"
},
  "geometry": {"coordinates":[-4.4365129471,36.7117195129],"type":"Point"}
}