{
  "type": "Feature",
  "properties": {
    "iso:country":"ES",
    "sg:address":"El Pinar, S/n",
    "sg:city":"Taibique",
    "sg:orig_category":"Iglesia Cat\u00d3lica",
    "sg:phone":"+34 922 55 81 02",
    "sg:postcode":"38911",
    "sg:province":"Santa Cruz De Tenerife",
    "wof:name":"Parroquia De San Antonio Abad",
    "wof:placetype":"venue"
},
  "geometry": {"coordinates":[-18.006313324,27.7575550079],"type":"Point"}
}