{
  "type": "Feature",
  "properties": {
    "addr:full":"Calle de Gomez Cortina, 5 San Nicolas Murcia 30005",
    "addr:housenumber":"5",
    "addr:postcode":"30005",
    "addr:street":"Calle De Gomez Cortina",
    "iso:country":"ES",
    "sg:address":"Calle de Gomez Cortina, 5",
    "sg:city":"San Nicolas",
    "sg:orig_category":"Ense\u00d1anza: Idiomas",
    "sg:phone":"+34 968 29 56 61",
    "sg:postcode":"30005",
    "sg:province":"Murcia",
    "wof:name":"Carre\u00f1o Sandoval Ana",
    "wof:placetype":"venue"
},
  "geometry": {"coordinates":[-1.1358829737,37.9874763489],"type":"Point"}
}