{
  "type": "Feature",
  "properties": {
    "iso:country":"ES",
    "sg:address":"Pl. San Pedro, S/n",
    "sg:city":"San Pedro",
    "sg:orig_category":"Iglesia Cat\u00d3lica",
    "sg:phone":"+34 946 50 41 26",
    "sg:postcode":"48191",
    "sg:province":"Vizcaya",
    "wof:name":"Bezares Garcia Ignacio",
    "wof:placetype":"venue"
},
  "geometry": {"coordinates":[-3.0992720127,43.2543907166],"type":"Point"}
}