{
  "type": "Feature",
  "properties": {
    "addr:full":"Calle de Escuelas, S/n Villaveza Del Agua Zamora 49760",
    "addr:housenumber":"s",
    "addr:postcode":"49760",
    "addr:street":"Calle De Escuelas;/ N;Zamora",
    "iso:country":"ES",
    "sg:address":"Calle de Escuelas, S/n",
    "sg:city":"Villaveza Del Agua",
    "sg:orig_category":"Cr\u00cda De Animales",
    "sg:phone":"+34 980 64 12 28",
    "sg:postcode":"49760",
    "sg:province":"Zamora",
    "wof:name":"Gadona S.l.",
    "wof:placetype":"venue"
},
  "geometry": {"coordinates":[-5.6764478683,41.9222259521],"type":"Point"}
}