{
  "type": "Feature",
  "properties": {
    "iso:country":"ES",
    "sg:address":"Calle de Vicente Blasco Iba\u00d1ez, S/n",
    "sg:city":"Torrevieja",
    "sg:orig_category":"Caf\u00c9s, Bares, Cervecer\u00cdas",
    "sg:phone":"+34 965 70 42 39",
    "sg:postcode":"03180",
    "sg:province":"Alicante",
    "wof:name":"Gonzalez Robles Tomas",
    "wof:placetype":"venue"
},
  "geometry": {"coordinates":[-0.6828939915,37.9787101746],"type":"Point"}
}