{
  "type": "Feature",
  "properties": {
    "addr:full":"Carrer de Tapioles, 34 Barcelona Barcelona 08004",
    "addr:housenumber":"34",
    "addr:postcode":"08004",
    "addr:street":"Carrer De Tapioles",
    "iso:country":"ES",
    "sg:address":"Carrer de Tapioles, 34",
    "sg:city":"Barcelona",
    "sg:orig_category":"Ebanister\u00cda",
    "sg:phone":"+34 934 42 74 80",
    "sg:postcode":"08004",
    "sg:province":"Barcelona",
    "wof:name":"Hinojo Lopez Francisco",
    "wof:placetype":"venue"
},
  "geometry": {"coordinates":[2.1639509201,41.3731231689],"type":"Point"}
}