{
  "type": "Feature",
  "properties": {
    "iso:country":"ES",
    "sg:address":"Alam Corregidor Lapuente, 4",
    "sg:city":"Sutullena",
    "sg:orig_category":"Impuestos, Tesoro P\u00dablico",
    "sg:phone":"+34 968 40 66 99",
    "sg:postcode":"30800",
    "sg:province":"Murcia",
    "wof:name":"Gabisur S.l.",
    "wof:placetype":"venue"
},
  "geometry": {"coordinates":[-1.1298867464,37.9834747314],"type":"Point"}
}