{
  "type": "Feature",
  "properties": {
    "addr:full":"Calle de Alfonso Orti, 1 Lopera Ja\u00e9n 23780",
    "addr:housenumber":"1",
    "addr:postcode":"23780",
    "addr:street":"Calle De Alfonso Orti",
    "iso:country":"ES",
    "sg:address":"Calle de Alfonso Orti, 1",
    "sg:city":"Lopera",
    "sg:orig_category":"Molduras, Junquillos, Listones Y Molduras Perforadas",
    "sg:phone":"+34 953 51 63 39",
    "sg:postcode":"23780",
    "sg:province":"Ja\u00e9n",
    "wof:name":"Alcala Santiago Manuel",
    "wof:placetype":"venue"
},
  "geometry": {"coordinates":[-4.2144818306,37.9440078735],"type":"Point"}
}