{
  "type": "Feature",
  "properties": {
    "addr:full":"Calle de Francisco Del Rio Romero, 5 Boiro La Coru\u00f1a 15930",
    "addr:housenumber":"5",
    "addr:postcode":"15930",
    "addr:street":"Calle De Francisco Del Rio Romero;La Corun\u0303A",
    "iso:country":"ES",
    "sg:address":"Calle de Francisco Del Rio Romero, 5",
    "sg:city":"Boiro",
    "sg:classifiers":[
        {
            "category":"Personal",
            "subcategory":"Barber",
            "type":"Services"
        }
    ],
    "sg:phone":"+34 981 84 45 36",
    "sg:postcode":"15930",
    "sg:province":"La Coru\u00f1a",
    "sg:tags":[
        "caballeros",
        "de",
        "peluqueros"
    ],
    "wof:name":"Martinez Mu\u00f1iz Jose",
    "wof:placetype":"venue"
},
  "geometry": {"coordinates":[-8.8866243362,42.6461143494],"type":"Point"}
}