{
  "type": "Feature",
  "properties": {
    "iso:country":"ES",
    "sg:address":"Carrer de Sant Antoni, 34",
    "sg:city":"Casc Antic",
    "sg:orig_category":"Quincaller\u00cda (al Por Menor)",
    "sg:phone":"+34 935 62 07 01",
    "sg:postcode":"08150",
    "sg:province":"Barcelona",
    "wof:name":"Pujol Clot Isidro",
    "wof:placetype":"venue"
},
  "geometry": {"coordinates":[2.2293000221,41.5678787231],"type":"Point"}
}