{
  "type": "Feature",
  "properties": {
    "addr:full":"Calle de Rio Nalon (del), 3 Nogal Madrid 28110",
    "addr:housenumber":"3",
    "addr:postcode":"28110",
    "addr:street":"Calle De Rio Nalon Del",
    "iso:country":"ES",
    "sg:address":"Calle de Rio Nalon (del), 3",
    "sg:city":"Nogal",
    "sg:orig_category":"Marketing Directo",
    "sg:phone":"+34 916 28 15 72",
    "sg:postcode":"28110",
    "sg:province":"Madrid",
    "sg:website":"www.templarmarketing.com",
    "wof:name":"Templar Marketing Espa\u00f1a S.l.",
    "wof:placetype":"venue"
},
  "geometry": {"coordinates":[-3.4999940395,40.5979003906],"type":"Point"}
}