{
  "type": "Feature",
  "properties": {
    "addr:full":"Trva Ciudad Jardin, 16 Bilbao Vizcaya 48007",
    "addr:housenumber":"16",
    "addr:postcode":"48007",
    "addr:street":"Trva Ciudad Jardin",
    "iso:country":"ES",
    "sg:address":"Trva Ciudad Jardin, 16",
    "sg:city":"Bilbao",
    "sg:orig_category":"Agencias Y Agentes Comerciales, Representantes",
    "sg:phone":"+34 944 13 24 90",
    "sg:postcode":"48007",
    "sg:province":"Vizcaya",
    "wof:name":"Villagra Alvarez S. A.",
    "wof:placetype":"venue"
},
  "geometry": {"coordinates":[-2.922688961,43.2689590454],"type":"Point"}
}