{
  "type": "Feature",
  "properties": {
    "iso:country":"ES",
    "sg:address":"Urb Villa Rosa, S/n",
    "sg:city":"Algeciras",
    "sg:orig_category":"Restaurantes",
    "sg:phone":"+34 956 60 02 58",
    "sg:postcode":"11207",
    "sg:province":"C\u00e1diz",
    "wof:name":"El Figon De San Garcia S.c.a.",
    "wof:placetype":"venue"
},
  "geometry": {"coordinates":[-5.4432039261,36.1157112122],"type":"Point"}
}