{
  "type": "Feature",
  "properties": {
    "iso:country":"ES",
    "sg:address":"Calle de Manuel Garcia Perez, 5",
    "sg:city":"Alca\u00f1iz",
    "sg:orig_category":"Equipo De Refrigeraci\u00d3n Industrial",
    "sg:phone":"+34 978 83 04 32",
    "sg:postcode":"44600",
    "sg:province":"Teruel",
    "wof:name":"Frihosba S. L.",
    "wof:placetype":"venue"
},
  "geometry": {"coordinates":[-0.128933996,41.0495681763],"type":"Point"}
}