{
  "type": "Feature",
  "properties": {
    "iso:country":"ES",
    "sg:address":"Calle de Uria, 42",
    "sg:city":"Cangas Narcea",
    "sg:orig_category":"Institutos De Belleza",
    "sg:phone":"+34 985 81 29 95",
    "sg:postcode":"33800",
    "sg:province":"Asturias",
    "wof:name":"Chacon Menendez Margarita",
    "wof:placetype":"venue"
},
  "geometry": {"coordinates":[-6.547976017,43.1757011414],"type":"Point"}
}