{
  "type": "Feature",
  "properties": {
    "addr:full":"Barr Villegar, S/n Villegar Cantabria 39699",
    "addr:housenumber":"s",
    "addr:postcode":"39699",
    "addr:street":"/ N",
    "iso:country":"ES",
    "sg:address":"Barr Villegar, S/n",
    "sg:city":"Villegar",
    "sg:orig_category":"Negocio De Materiales De Construcci\u00d3n",
    "sg:phone":"+34 942 59 76 17",
    "sg:postcode":"39699",
    "sg:province":"Cantabria",
    "wof:name":"Suministros Del Pas S.l.",
    "wof:placetype":"venue"
},
  "geometry": {"coordinates":[-3.946598053,43.223072052],"type":"Point"}
}