{
  "type": "Feature",
  "properties": {
    "iso:country":"ES",
    "sg:address":"Calle de Cardenal Marcelo Spinola, 2",
    "sg:city":"Madrid",
    "sg:orig_category":"Centros Empresariales",
    "sg:phone":"+34 917 67 12 26",
    "sg:postcode":"28016",
    "sg:province":"Madrid",
    "wof:name":"Area Ingenieria De Servicios Inmobiliarios S.l.",
    "wof:placetype":"venue"
},
  "geometry": {"coordinates":[-3.671731472,40.4671211243],"type":"Point"}
}