{
  "type": "Feature",
  "properties": {
    "addr:full":"Ca\u00f1averales (p I Juncales), 4 La Puebla Rio Sevilla 41130",
    "addr:housenumber":"4",
    "addr:postcode":"41130",
    "addr:street":"Juncales",
    "iso:country":"ES",
    "sg:address":"Ca\u00f1averales (p I Juncales), 4",
    "sg:city":"La Puebla Rio",
    "sg:orig_category":"Empresas De Carpinter\u00cda",
    "sg:phone":"+34 955 77 02 39",
    "sg:postcode":"41130",
    "sg:province":"Sevilla",
    "wof:name":"Pineda Teran E Hijos S.l.",
    "wof:placetype":"venue"
},
  "geometry": {"coordinates":[-6.076982975,37.2620162964],"type":"Point"}
}