{
  "type": "Feature",
  "properties": {
    "iso:country":"ES",
    "sg:address":"Calle de Marques De Comillas, 5",
    "sg:city":"Almeria",
    "sg:orig_category":"Telas Y Sedas (al Por Menor)",
    "sg:phone":"+34 950 25 75 74",
    "sg:postcode":"04004",
    "sg:province":"Almer\u00eda",
    "wof:name":"Romero Tirado Santiago Jose",
    "wof:placetype":"venue"
},
  "geometry": {"coordinates":[-2.4623560905,36.83751297],"type":"Point"}
}