{
  "type": "Feature",
  "properties": {
    "addr:full":"Rbla Catalunya, 112 Barcelona Barcelona 08008",
    "addr:housenumber":"112",
    "addr:postcode":"08008",
    "addr:street":"Rbla Catalunya",
    "iso:country":"ES",
    "sg:address":"Rbla Catalunya, 112",
    "sg:city":"Barcelona",
    "sg:orig_category":"Ropa Para Se\u00d1oras (al Por Menor)",
    "sg:phone":"+34 932 17 19 17",
    "sg:postcode":"08008",
    "sg:province":"Barcelona",
    "sg:website":"www.trucco.es",
    "wof:name":"Tell Training S.a.",
    "wof:placetype":"venue"
},
  "geometry": {"coordinates":[2.1588499546,41.3947296143],"type":"Point"}
}