{
  "type": "Feature",
  "properties": {
    "iso:country":"ES",
    "sg:address":"Poliesportiu, S/n",
    "sg:city":"Massanassa",
    "sg:orig_category":"Tintes (fabricaci\u00d3n, Al Por Mayor)",
    "sg:phone":"+34 963 89 17 75",
    "sg:postcode":"46470",
    "sg:province":"Valencia",
    "sg:website":"www.centronet.com",
    "wof:name":"Centronet Tintorerias S.l.",
    "wof:placetype":"venue"
},
  "geometry": {"coordinates":[-0.3884840012,39.4135246277],"type":"Point"}
}