{
  "type": "Feature",
  "properties": {
    "addr:full":"Carrer de Manuel Aza\u00d1a, 34 Palma Islas Baleares 07006",
    "addr:housenumber":"34",
    "addr:postcode":"07006",
    "addr:street":"Carrer De Manuel Azan\u0303A",
    "iso:country":"ES",
    "sg:address":"Carrer de Manuel Aza\u00d1a, 34",
    "sg:city":"Palma",
    "sg:orig_category":"Cajas De Ahorro",
    "sg:phone":"+34 971 46 67 70",
    "sg:postcode":"07006",
    "sg:province":"Islas Baleares",
    "wof:name":"Caixa D'estalvis I Pensions De Barcelona",
    "wof:placetype":"venue"
},
  "geometry": {"coordinates":[2.6635210514,39.5669212341],"type":"Point"}
}