{
  "type": "Feature",
  "properties": {
    "addr:full":"Calle de Monasterio Santa Clara, S/n Zaragoza Zaragoza 50002",
    "addr:housenumber":"s / n",
    "addr:postcode":"50002",
    "addr:street":"Calle De Monasterio Santa",
    "iso:country":"ES",
    "sg:address":"Calle de Monasterio Santa Clara, S/n",
    "sg:city":"Zaragoza",
    "sg:orig_category":"Molduras, Junquillos, Listones Y Molduras Perforadas",
    "sg:phone":"+34 976 59 46 68",
    "sg:postcode":"50002",
    "sg:province":"Zaragoza",
    "wof:name":"Lazaro Alunda Jesus",
    "wof:placetype":"venue"
},
  "geometry": {"coordinates":[-0.8597589731,41.644618988],"type":"Point"}
}