{
  "type": "Feature",
  "properties": {
    "iso:country":"ES",
    "sg:address":"Calle de Marineros, 26",
    "sg:city":"Salamanca",
    "sg:orig_category":"Carnicer\u00cdas, Carnicer\u00cdas",
    "sg:phone":"+34 923 24 52 91",
    "sg:postcode":"37006",
    "sg:province":"Salamanca",
    "wof:name":"Terradillos Iglesias Gabriel",
    "wof:placetype":"venue"
},
  "geometry": {"coordinates":[-5.6727719307,40.9777832031],"type":"Point"}
}