{
  "type": "Feature",
  "properties": {
    "addr:full":"Avda Carlos De Haya, 60 Malaga M\u00e1laga 29010",
    "addr:housenumber":"60",
    "addr:postcode":"29010",
    "addr:street":"Avda Carlos De Haya;Ma\u0301Laga",
    "iso:country":"ES",
    "sg:address":"Avda Carlos De Haya, 60",
    "sg:city":"Malaga",
    "sg:classifiers":[
        {
            "category":"Professional",
            "subcategory":"Management & Consulting",
            "type":"Services"
        }
    ],
    "sg:phone":"+34 952 61 88 54",
    "sg:postcode":"29010",
    "sg:province":"M\u00e1laga",
    "sg:tags":[
        "asesor\u00cda",
        "en",
        "marketing"
    ],
    "wof:name":"Lopez De Vinuesa Gavilan Enrique",
    "wof:placetype":"venue"
},
  "geometry": {"coordinates":[-4.4461450577,36.7221069336],"type":"Point"}
}