{
  "type": "Feature",
  "properties": {
    "addr:full":"Ctra De Malaga (zi Huerta Ardila), S/n Santa Fe Granada 18320",
    "addr:housenumber":"s / n",
    "addr:postcode":"18320",
    "addr:street":"Ctra De Malaga Zi Huerta Ardila",
    "iso:country":"ES",
    "sg:address":"Ctra De Malaga (zi Huerta Ardila), S/n",
    "sg:city":"Santa Fe",
    "sg:orig_category":"Ropa Para Ni\u00d1os (al Por Menor)",
    "sg:phone":"+34 958 51 14 53",
    "sg:postcode":"18320",
    "sg:province":"Granada",
    "sg:website":"www.phineas.ws",
    "wof:name":"Shamba Cotto S.l.u",
    "wof:placetype":"venue"
},
  "geometry": {"coordinates":[-3.715419054,37.1926345825],"type":"Point"}
}