{
  "type": "Feature",
  "properties": {
    "addr:full":"Avda Quinto Centenario, S/n Sanlucar De Barrameda C\u00e1diz 11540",
    "addr:housenumber":"s / n",
    "addr:postcode":"11540",
    "addr:street":"Avda Quinto Centenario;Ca\u0301Diz",
    "iso:country":"ES",
    "sg:address":"Avda Quinto Centenario, S/n",
    "sg:city":"Sanlucar De Barrameda",
    "sg:orig_category":"Asesor\u00cda Fiscal Y Jur\u00cddica",
    "sg:phone":"+34 956 38 50 69",
    "sg:postcode":"11540",
    "sg:province":"C\u00e1diz",
    "wof:name":"J.m.staff Asesores Y Economistas S.l.",
    "wof:placetype":"venue"
},
  "geometry": {"coordinates":[-6.3583030701,36.7760734558],"type":"Point"}
}