{
  "type": "Feature",
  "properties": {
    "iso:country":"ES",
    "sg:address":"Pol Ind La Colada, S/n",
    "sg:city":"S. Bartolome Torre",
    "sg:orig_category":"Mec\u00c1nico Del Autom\u00d3vil",
    "sg:phone":"+34 959 38 75 90",
    "sg:postcode":"21510",
    "sg:province":"Huelva",
    "wof:name":"Servicio Rapido La Amistad C.b.",
    "wof:placetype":"venue"
},
  "geometry": {"coordinates":[-7.1026139259,37.4456367493],"type":"Point"}
}