{
  "type": "Feature",
  "properties": {
    "iso:country":"ES",
    "sg:address":"Riberas, Km. 0004,1",
    "sg:city":"Riberas",
    "sg:orig_category":"Promotores Constructores",
    "sg:phone":"+34 985 58 77 79",
    "sg:postcode":"33127",
    "sg:province":"Asturias",
    "wof:name":"Ferrovial-agroman S.a.",
    "wof:placetype":"venue"
},
  "geometry": {"coordinates":[-6.0685720444,43.5057067871],"type":"Point"}
}