{
  "type": "Feature",
  "properties": {
    "addr:full":"Carrer de Sant Roc, 5 Granollers Barcelona 08401",
    "addr:housenumber":"5",
    "addr:postcode":"08401",
    "addr:street":"Carrer De Sant Roc",
    "iso:country":"ES",
    "sg:address":"Carrer de Sant Roc, 5",
    "sg:city":"Granollers",
    "sg:orig_category":"Abogados",
    "sg:phone":"+34 938 70 11 77",
    "sg:postcode":"08401",
    "sg:province":"Barcelona",
    "wof:name":"Font Padro Pedro",
    "wof:placetype":"venue"
},
  "geometry": {"coordinates":[2.2882080078,41.6084976196],"type":"Point"}
}