{
  "type": "Feature",
  "properties": {
    "iso:country":"ES",
    "sg:address":"Avda America, 60",
    "sg:city":"Madrid",
    "sg:orig_category":"Abogados",
    "sg:phone":"+34 913 56 28 34",
    "sg:postcode":"28028",
    "sg:province":"Madrid",
    "wof:name":"Arevalo Eizaguirre Jose Ramon",
    "wof:placetype":"venue"
},
  "geometry": {"coordinates":[-3.6629781723,40.4435348511],"type":"Point"}
}