{
  "type": "Feature",
  "properties": {
    "iso:country":"ES",
    "sg:address":"Av Josep Tarradellas, 133",
    "sg:city":"Terrassa",
    "sg:orig_category":"\u00d3ptica: Instrumentos (fabricaci\u00d3n)",
    "sg:phone":"+34 937 89 20 23",
    "sg:postcode":"08225",
    "sg:province":"Barcelona",
    "wof:name":"Rubinat Gese Neus",
    "wof:placetype":"venue"
},
  "geometry": {"coordinates":[2.0026021004,41.5729522705],"type":"Point"}
}