{
  "type": "Feature",
  "properties": {
    "iso:country":"ES",
    "sg:address":"Calle de Colon, 41",
    "sg:city":"Segorbe",
    "sg:orig_category":"Confiter\u00cdas, Chocolater\u00cdas (al Por Menor)",
    "sg:phone":"+34 964 71 03 47",
    "sg:postcode":"12400",
    "sg:province":"Castell\u00f3n",
    "wof:name":"Casa Mauro Torres S.l.",
    "wof:placetype":"venue"
},
  "geometry": {"coordinates":[-0.4891009927,39.8520889282],"type":"Point"}
}