{
  "type": "Feature",
  "properties": {
    "addr:full":"Ctra Arjona, S/n Cabra Mocha Ja\u00e9n 23790",
    "addr:housenumber":"s / n",
    "addr:postcode":"23790",
    "addr:street":"Ctra Arjona",
    "iso:country":"ES",
    "sg:address":"Ctra Arjona, S/n",
    "sg:city":"Cabra Mocha",
    "sg:orig_category":"Autob\u00das (explotaci\u00d3n Y Servicios De)",
    "sg:phone":"+34 953 54 51 31",
    "sg:postcode":"23790",
    "sg:province":"Ja\u00e9n",
    "wof:name":"Millan Fernandez Benito",
    "wof:placetype":"venue"
},
  "geometry": {"coordinates":[-4.1859688759,37.8754959106],"type":"Point"}
}