{
  "type": "Feature",
  "properties": {
    "iso:country":"ES",
    "sg:address":"Calle de Sevilla, 1",
    "sg:city":"Aguilas",
    "sg:orig_category":"Molduras, Junquillos, Listones Y Molduras Perforadas",
    "sg:phone":"+34 968 44 85 33",
    "sg:postcode":"30880",
    "sg:province":"Murcia",
    "wof:name":"Perez Parra Ginesa",
    "wof:placetype":"venue"
},
  "geometry": {"coordinates":[-1.5887310505,37.4098167419],"type":"Point"}
}