{
  "type": "Feature",
  "properties": {
    "addr:full":"Pol. Pto. Deportivo, S/n Santander Cantabria 39011",
    "addr:housenumber":"/ n",
    "addr:postcode":"39011",
    "iso:country":"ES",
    "sg:address":"Pol. Pto. Deportivo, S/n",
    "sg:city":"Santander",
    "sg:orig_category":"Construcciones Navales Y Fluviales",
    "sg:phone":"+34 942 35 60 56",
    "sg:postcode":"39011",
    "sg:province":"Cantabria",
    "wof:name":"Botin & Carkeek Yacht Desingn",
    "wof:placetype":"venue"
},
  "geometry": {"coordinates":[-3.862869978,43.4475975037],"type":"Point"}
}