{
  "type": "Feature",
  "properties": {
    "addr:full":"Calle de Gaztambide, 7 Madrid Madrid 28015",
    "addr:housenumber":"7",
    "addr:postcode":"madrid;28015",
    "addr:street":"Calle De Gaztambide",
    "iso:country":"ES",
    "sg:address":"Calle de Gaztambide, 7",
    "sg:city":"Madrid",
    "sg:orig_category":"Radiocomunicaciones, Telefon\u00cda M\u00d3vil, Radiomensajer\u00cda: Servicios, Comercializaci\u00d3n",
    "sg:phone":"+34 915 43 36 53",
    "sg:postcode":"28015",
    "sg:province":"Madrid",
    "sg:website":"www.aquitania.es",
    "wof:name":"Aquitania Solutions S.l.",
    "wof:placetype":"venue"
},
  "geometry": {"coordinates":[-3.715767622,40.4312477112],"type":"Point"}
}