{
  "type": "Feature",
  "properties": {
    "addr:full":"Calle de Ercilla, 16 Bilbao Vizcaya 48009",
    "addr:housenumber":"16",
    "addr:postcode":"48009",
    "addr:street":"Calle De Ercilla",
    "iso:country":"ES",
    "sg:address":"Calle de Ercilla, 16",
    "sg:city":"Bilbao",
    "sg:orig_category":"Expertos Contables",
    "sg:phone":"+34 944 23 99 05",
    "sg:postcode":"48009",
    "sg:province":"Vizcaya",
    "wof:name":"Estudio Juridico Bustamante S.l.",
    "wof:placetype":"venue"
},
  "geometry": {"coordinates":[-2.9326019287,43.2642822266],"type":"Point"}
}