{
  "type": "Feature",
  "properties": {
    "iso:country":"ES",
    "sg:address":"Pur\u00edsima, 9",
    "sg:city":"Vinaros",
    "sg:orig_category":"Peluqueros: De Se\u00d1oras",
    "sg:phone":"+34 964 45 46 37",
    "sg:postcode":"12500",
    "sg:province":"Castell\u00f3n",
    "wof:name":"T.and.t Miralles C.b",
    "wof:placetype":"venue"
},
  "geometry": {"coordinates":[0.4755899906,40.469909668],"type":"Point"}
}