{
  "type": "Feature",
  "properties": {
    "addr:full":"Carrer de Sicilia, 234 Barcelona Barcelona 08013",
    "addr:housenumber":"234",
    "addr:postcode":"08013",
    "addr:street":"Carrer De Sicilia",
    "iso:country":"ES",
    "sg:address":"Carrer de Sicilia, 234",
    "sg:city":"Barcelona",
    "sg:orig_category":"Confecci\u00d3n (fabricaci\u00d3n, Al Por Mayor)",
    "sg:phone":"+34 932 65 15 22",
    "sg:postcode":"08013",
    "sg:province":"Barcelona",
    "wof:name":"Alvarez Rodriguez Ana Maria",
    "wof:placetype":"venue"
},
  "geometry": {"coordinates":[2.1768388748,41.3990631104],"type":"Point"}
}