{
  "type": "Feature",
  "properties": {
    "addr:full":"Carr Benidorm, S/n Tossalet Alicante 03580",
    "addr:housenumber":"s",
    "addr:postcode":"03580",
    "addr:street":"Carr Benidorm;/ N Tossalet",
    "iso:country":"ES",
    "sg:address":"Carr Benidorm, S/n",
    "sg:city":"Tossalet",
    "sg:orig_category":"Centros Empresariales",
    "sg:phone":"+34 965 88 92 24",
    "sg:postcode":"03580",
    "sg:province":"Alicante",
    "wof:name":"Scans Security S.l.",
    "wof:placetype":"venue"
},
  "geometry": {"coordinates":[-0.1033039987,38.5793037415],"type":"Point"}
}