{
  "type": "Feature",
  "properties": {
    "addr:full":"Calle de Estacion, 53 Miranda Ebro Burgos 09200",
    "addr:housenumber":"53",
    "addr:postcode":"09200",
    "addr:street":"Calle De Estacion",
    "iso:country":"ES",
    "sg:address":"Calle de Estacion, 53",
    "sg:city":"Miranda Ebro",
    "sg:orig_category":"Cervecer\u00cdas",
    "sg:phone":"+34 947 33 09 42",
    "sg:postcode":"09200",
    "sg:province":"Burgos",
    "wof:name":"Gomez Cano Juan Carlos",
    "wof:placetype":"venue"
},
  "geometry": {"coordinates":[-2.9441018105,42.6877479553],"type":"Point"}
}