{
  "type": "Feature",
  "properties": {
    "addr:full":"Carrer de Enten\u00c7a, 134 Barcelona Barcelona 08015",
    "addr:housenumber":"134",
    "addr:postcode":"08015",
    "addr:street":"Carrer De Entenc\u0327A",
    "iso:country":"ES",
    "sg:address":"Carrer de Enten\u00c7a, 134",
    "sg:city":"Barcelona",
    "sg:orig_category":"Empresarios",
    "sg:phone":"+34 932 26 02 42",
    "sg:postcode":"08015",
    "sg:province":"Barcelona",
    "wof:name":"Zaforas Baulo Manuel",
    "wof:placetype":"venue"
},
  "geometry": {"coordinates":[2.1478393078,41.3817481995],"type":"Point"}
}