{
  "type": "Feature",
  "properties": {
    "addr:full":"Carrer de Arcadi Balaguer, 86 Castelldefels Barcelona 08860",
    "addr:housenumber":"86",
    "addr:postcode":"08860",
    "addr:street":"Carrer De Arcadi Balaguer",
    "iso:country":"ES",
    "sg:address":"Carrer de Arcadi Balaguer, 86",
    "sg:city":"Castelldefels",
    "sg:orig_category":"Ense\u00d1anza: Idiomas",
    "sg:phone":"+34 936 65 69 91",
    "sg:postcode":"08860",
    "sg:province":"Barcelona",
    "wof:name":"Garnikalia S.l.",
    "wof:placetype":"venue"
},
  "geometry": {"coordinates":[1.979501009,41.2815246582],"type":"Point"}
}