{
  "type": "Feature",
  "properties": {
    "iso:country":"ES",
    "sg:address":"Rond Sant Antoni, 52",
    "sg:city":"Barcelona",
    "sg:orig_category":"Abogados",
    "sg:phone":"+34 934 43 21 41",
    "sg:postcode":"08001",
    "sg:province":"Barcelona",
    "wof:name":"Piantini S.a.",
    "wof:placetype":"venue"
},
  "geometry": {"coordinates":[2.1636600494,41.3789482117],"type":"Point"}
}