{
  "type": "Feature",
  "properties": {
    "iso:country":"ES",
    "sg:address":"Calle de Santo Rosario, 3",
    "sg:city":"Guijarrosa",
    "sg:orig_category":"Telas Y Sedas (al Por Menor)",
    "sg:phone":"+34 957 31 51 53",
    "sg:postcode":"14547",
    "sg:province":"C\u00f3rdoba",
    "wof:name":"Gutierrez Moyano Jose Manuel",
    "wof:placetype":"venue"
},
  "geometry": {"coordinates":[-4.8655099869,37.6365242004],"type":"Point"}
}