{
  "type": "Feature",
  "properties": {
    "iso:country":"ES",
    "sg:address":"Ctra. Nijar, 248",
    "sg:city":"Almeria",
    "sg:orig_category":"Trabajos De Soldaduras",
    "sg:phone":"+34 950 22 19 30",
    "sg:postcode":"04006",
    "sg:province":"Almer\u00eda",
    "wof:name":"Fernandez Rodriguez Antonio",
    "wof:placetype":"venue"
},
  "geometry": {"coordinates":[-2.4434049129,36.8456573486],"type":"Point"}
}