{
  "type": "Feature",
  "properties": {
    "addr:full":"Calle de Marcelo Usera, 5 Madrid Madrid 28026",
    "addr:housenumber":"5",
    "addr:postcode":"28026",
    "addr:street":"Calle De Marcelo Usera",
    "iso:country":"ES",
    "sg:address":"Calle de Marcelo Usera, 5",
    "sg:city":"Madrid",
    "sg:orig_category":"Tintes (fabricaci\u00d3n, Al Por Mayor)",
    "sg:phone":"+34 914 76 78 70",
    "sg:postcode":"28026",
    "sg:province":"Madrid",
    "wof:name":"Blas Blas Adelaida",
    "wof:placetype":"venue"
},
  "geometry": {"coordinates":[-3.7000510693,40.3876075745],"type":"Point"}
}