{
  "type": "Feature",
  "properties": {
    "addr:full":"Avda Costa, 127 Gijon Asturias 33204",
    "addr:housenumber":"127",
    "addr:postcode":"33204",
    "addr:street":"Avda Costa",
    "iso:country":"ES",
    "sg:address":"Avda Costa, 127",
    "sg:city":"Gijon",
    "sg:orig_category":"Mercer\u00cda, Lencer\u00cda (al Por Menor)",
    "sg:phone":"+34 985 37 39 58",
    "sg:postcode":"33204",
    "sg:province":"Asturias",
    "wof:name":"Sanjurjo Piquin Antonio",
    "wof:placetype":"venue"
},
  "geometry": {"coordinates":[-5.6493887901,43.5369110107],"type":"Point"}
}