{
  "type": "Feature",
  "properties": {
    "addr:full":"Calle de General Ricardos, 179 Madrid Madrid 28019",
    "addr:housenumber":"179",
    "addr:postcode":"28019",
    "addr:street":"Calle De General Ricardos",
    "iso:country":"ES",
    "sg:address":"Calle de General Ricardos, 179",
    "sg:city":"Madrid",
    "sg:orig_category":"Centros De Educaci\u00d3n Especial",
    "sg:phone":"+34 914 61 88 17",
    "sg:postcode":"28019",
    "sg:province":"Madrid",
    "wof:name":"Organismo Autonomo De Informatica Y Comunicaciones De La Comunidad De Madrid",
    "wof:placetype":"venue"
},
  "geometry": {"coordinates":[-3.7313289642,40.3887710571],"type":"Point"}
}