{
  "type": "Feature",
  "properties": {
    "iso:country":"ES",
    "sg:address":"Calle de Meleros, 18",
    "sg:city":"Puerto De Santa Maria",
    "sg:orig_category":"Peluquer\u00cdas, Peluquer\u00cda Mixta",
    "sg:phone":"+34 956 87 33 05",
    "sg:postcode":"11500",
    "sg:province":"C\u00e1diz",
    "wof:name":"Sanchez Sampedro Francisca",
    "wof:placetype":"venue"
},
  "geometry": {"coordinates":[-6.228249073,36.6007385254],"type":"Point"}
}