{
  "type": "Feature",
  "properties": {
    "addr:full":"Calle de Mayor, 107 Puntal Murcia 30100",
    "addr:housenumber":"107",
    "addr:postcode":"30100",
    "addr:street":"Calle De Mayor",
    "iso:country":"ES",
    "sg:address":"Calle de Mayor, 107",
    "sg:city":"Puntal",
    "sg:orig_category":"Bancos",
    "sg:phone":"+34 968 85 84 24",
    "sg:postcode":"30100",
    "sg:province":"Murcia",
    "wof:name":"Banco Bilbao Vizcaya Argentaria S.a.",
    "wof:placetype":"venue"
},
  "geometry": {"coordinates":[-1.1568490267,38.0140037537],"type":"Point"}
}