{
  "type": "Feature",
  "properties": {
    "iso:country":"ES",
    "sg:address":"Pio Baroja Kalea, 1",
    "sg:city":"Andoain",
    "sg:orig_category":"Art\u00cdculos De Regalo (al Por Menor)",
    "sg:phone":"+34 943 30 10 17",
    "sg:postcode":"20140",
    "sg:province":"Guip\u00f9zcoa",
    "wof:name":"Exclusivas Ivego S.l.",
    "wof:placetype":"venue"
},
  "geometry": {"coordinates":[-2.0205349922,43.2202796936],"type":"Point"}
}