{
  "type": "Feature",
  "properties": {
    "addr:full":"Calle de Palermo, 47 Madrid Madrid 28043",
    "addr:housenumber":"47",
    "addr:postcode":"madrid;28043",
    "addr:street":"Calle De Palermo",
    "iso:country":"ES",
    "sg:address":"Calle de Palermo, 47",
    "sg:city":"Madrid",
    "sg:orig_category":"Deportes Diversos",
    "sg:phone":"+34 913 88 79 48",
    "sg:postcode":"28043",
    "sg:province":"Madrid",
    "sg:website":"www.theatlasgym.com",
    "wof:name":"Gymilermo 97 S.l.",
    "wof:placetype":"venue"
},
  "geometry": {"coordinates":[-3.647701025,40.4593658447],"type":"Point"}
}