{
  "type": "Feature",
  "properties": {
    "addr:full":"Ctra. Sevilla, Km. 0730,5 Monesterio Badajoz 06260",
    "addr:postcode":"06260",
    "addr:street":"Ctra. Sevilla Km. 0730,5",
    "iso:country":"ES",
    "sg:address":"Ctra. Sevilla, Km. 0730,5",
    "sg:city":"Monesterio",
    "sg:orig_category":"Mataderos Y Talleres De Despiezado",
    "sg:phone":"+34 924 51 61 39",
    "sg:postcode":"06260",
    "sg:province":"Badajoz",
    "sg:website":"www.elculebrin.com",
    "wof:name":"Ibericos Del Culebrin S.l.",
    "wof:placetype":"venue"
},
  "geometry": {"coordinates":[-6.2733559608,38.0909118652],"type":"Point"}
}