{
  "type": "Feature",
  "properties": {
    "iso:country":"ES",
    "sg:address":"Plaz Canalejas, 5",
    "sg:city":"Motril",
    "sg:orig_category":"Ropa Para Beb\u00c9s Y Ni\u00d1os (confecci\u00d3n, Al Por Mayor)",
    "sg:phone":"+34 958 60 20 59",
    "sg:postcode":"18600",
    "sg:province":"Granada",
    "wof:name":"Sanchez Sanchez Alicia",
    "wof:placetype":"venue"
},
  "geometry": {"coordinates":[-3.5197479725,36.7465591431],"type":"Point"}
}