{
  "type": "Feature",
  "properties": {
    "addr:full":"Calle de San Anton, 2 Logro\u00f1o La Rioja 26002",
    "addr:housenumber":"2",
    "addr:postcode":"26002",
    "addr:street":"Calle De San Anton;Rioja",
    "iso:country":"ES",
    "sg:address":"Calle de San Anton, 2",
    "sg:city":"Logro\u00f1o",
    "sg:orig_category":"Peluqueros: De Se\u00d1oras",
    "sg:phone":"+34 941 24 97 81",
    "sg:postcode":"26002",
    "sg:province":"La Rioja",
    "wof:name":"Fernandez Fernandez Maximo",
    "wof:placetype":"venue"
},
  "geometry": {"coordinates":[-2.4471840858,42.4629325867],"type":"Point"}
}