{
  "type": "Feature",
  "properties": {
    "addr:full":"Calle de Serrano, 217 Madrid Madrid 28016",
    "addr:housenumber":"217",
    "addr:postcode":"28016",
    "addr:street":"Calle De Serrano",
    "iso:country":"ES",
    "sg:address":"Calle de Serrano, 217",
    "sg:city":"Madrid",
    "sg:orig_category":"M\u00c9dicos: Psiquiatr\u00cda",
    "sg:phone":"+34 914 58 75 10",
    "sg:postcode":"28016",
    "sg:province":"Madrid",
    "wof:name":"Bover Lopez Arturo",
    "wof:placetype":"venue"
},
  "geometry": {"coordinates":[-3.6788499355,40.4541702271],"type":"Point"}
}