{
  "type": "Feature",
  "properties": {
    "addr:full":"Calle de Portugal, 1 Arcos Frontera C\u00e1diz 11630",
    "addr:housenumber":"1",
    "addr:postcode":"11630",
    "addr:street":"Calle De Portugal",
    "iso:country":"ES",
    "sg:address":"Calle de Portugal, 1",
    "sg:city":"Arcos Frontera",
    "sg:orig_category":"Peluquer\u00cdas, Peluquer\u00cda Mixta",
    "sg:phone":"+34 956 70 12 12",
    "sg:postcode":"11630",
    "sg:province":"C\u00e1diz",
    "wof:name":"Lopez Gil Luis Manuel",
    "wof:placetype":"venue"
},
  "geometry": {"coordinates":[-5.8138389587,36.7542419434],"type":"Point"}
}