{
  "type": "Feature",
  "properties": {
    "iso:country":"ES",
    "sg:address":"B, S/n",
    "sg:city":"Alcoi",
    "sg:orig_category":"Mec\u00c1nico Del Autom\u00d3vil",
    "sg:phone":"+34 966 52 64 64",
    "sg:postcode":"03800",
    "sg:province":"Alicante",
    "wof:name":"Alcoi Sinc S.l.",
    "wof:placetype":"venue"
},
  "geometry": {"coordinates":[-0.4739944041,38.6992607117],"type":"Point"}
}