{
  "type": "Feature",
  "properties": {
    "iso:country":"ES",
    "sg:address":"Calle de Santiago, 46",
    "sg:city":"Elizondo",
    "sg:orig_category":"Sociedades, Compa\u00d1\u00cdas Aseguradoras",
    "sg:phone":"+34 948 58 03 76",
    "sg:postcode":"31700",
    "sg:province":"Navarra",
    "wof:name":"Mapfre Mutualidad De Seguros Y Reaseguros A Prima Fija",
    "wof:placetype":"venue"
},
  "geometry": {"coordinates":[-1.5216540098,43.1422615051],"type":"Point"}
}