{
  "type": "Feature",
  "properties": {
    "iso:country":"ES",
    "sg:address":"Calle de Mayor, 137",
    "sg:city":"Tobarra",
    "sg:orig_category":"Ropa Para Se\u00d1oras Y Caballeros (al Por Menor)",
    "sg:phone":"+34 967 32 59 82",
    "sg:postcode":"02500",
    "sg:province":"Albacete",
    "wof:name":"Garcia Merino Dolores",
    "wof:placetype":"venue"
},
  "geometry": {"coordinates":[-1.6895179749,38.5920677185],"type":"Point"}
}