{
  "type": "Feature",
  "properties": {
    "iso:country":"ES",
    "sg:address":"Luga Grela, S/n",
    "sg:city":"Grela",
    "sg:orig_category":"Frutas Y Legumbres Frescas (al Por Mayor)",
    "sg:phone":"+34 981 28 40 60",
    "sg:postcode":"15008",
    "sg:province":"La Coru\u00f1a",
    "wof:name":"Naranjas Iba\u00f1ez S.l.",
    "wof:placetype":"venue"
},
  "geometry": {"coordinates":[-8.4512443542,43.3434753418],"type":"Point"}
}