{
  "type": "Feature",
  "properties": {
    "addr:full":"Calle de Aragon, S/n Vitoria-gasteiz \u00c1lava 01003",
    "addr:housenumber":"/ n",
    "addr:postcode":"01003",
    "addr:street":"Calle De Aragon S",
    "iso:country":"ES",
    "sg:address":"Calle de Aragon, S/n",
    "sg:city":"Vitoria-gasteiz",
    "sg:orig_category":"Venta, Instalaci\u00d3n De Calefacci\u00d3n",
    "sg:phone":"+34 945 25 26 59",
    "sg:postcode":"01003",
    "sg:province":"\u00c1lava",
    "wof:name":"Sanz Prieto Eustaquio",
    "wof:placetype":"venue"
},
  "geometry": {"coordinates":[-2.6578140259,42.8500556946],"type":"Point"}
}