{
  "type": "Feature",
  "properties": {
    "addr:full":"Calle de Leon Y Castillo, 60 Palmas De Gran Canaria Las Palmas 35003",
    "addr:postcode":"35003",
    "addr:street":"Calle De Leon Y Castillo 60",
    "iso:country":"ES",
    "sg:address":"Calle de Leon Y Castillo, 60",
    "sg:city":"Palmas De Gran Canaria",
    "sg:orig_category":"Centros Empresariales",
    "sg:phone":"+34 928 36 16 91",
    "sg:postcode":"35003",
    "sg:province":"Las Palmas",
    "wof:name":"Zou  Maomao",
    "wof:placetype":"venue"
},
  "geometry": {"coordinates":[-15.4190225601,28.1116199493],"type":"Point"}
}