{
  "type": "Feature",
  "properties": {
    "addr:full":"Treinta Y Uno De Octubre, 3 San Javier Murcia 30730",
    "addr:housenumber":"3",
    "addr:postcode":"30730",
    "addr:street":"Treinta Y Uno De Octubre",
    "iso:country":"ES",
    "sg:address":"Treinta Y Uno De Octubre, 3",
    "sg:city":"San Javier",
    "sg:orig_category":"Peluqueros: De Se\u00d1oras",
    "sg:phone":"+34 968 57 11 71",
    "sg:postcode":"30730",
    "sg:province":"Murcia",
    "wof:name":"Almagro Saez Ana",
    "wof:placetype":"venue"
},
  "geometry": {"coordinates":[-0.8314883709,37.8034248352],"type":"Point"}
}