{
  "type": "Feature",
  "properties": {
    "iso:country":"ES",
    "sg:address":"Union, 109",
    "sg:city":"Vecindario",
    "sg:orig_category":"Farmacias",
    "sg:phone":"+34 928 75 47 89",
    "sg:postcode":"35110",
    "sg:province":"Las Palmas",
    "wof:name":"Martin Valverde Alfonso",
    "wof:placetype":"venue"
},
  "geometry": {"coordinates":[-15.446518898,27.8484344482],"type":"Point"}
}