{
  "type": "Feature",
  "properties": {
    "addr:full":"Carr Valencia, 43 Algemesi Valencia 46680",
    "addr:housenumber":"43",
    "addr:postcode":"46680",
    "addr:street":"Carr Valencia",
    "iso:country":"ES",
    "sg:address":"Carr Valencia, 43",
    "sg:city":"Algemesi",
    "sg:orig_category":"Ropa Y Accesorios",
    "sg:phone":"+34 962 42 34 09",
    "sg:postcode":"46680",
    "sg:province":"Valencia",
    "wof:name":"Botella Navarro Maria Dolores",
    "wof:placetype":"venue"
},
  "geometry": {"coordinates":[-0.435766995,39.1940994263],"type":"Point"}
}