{
  "type": "Feature",
  "properties": {
    "iso:country":"ES",
    "sg:address":"Av Ernesto Paulino (d'), 5",
    "sg:city":"Oliva",
    "sg:orig_category":"Arquitectos",
    "sg:phone":"+34 962 85 54 76",
    "sg:postcode":"46780",
    "sg:province":"Valencia",
    "wof:name":"Boronat Moreno Maria Clara",
    "wof:placetype":"venue"
},
  "geometry": {"coordinates":[-0.1112629995,38.9207687378],"type":"Point"}
}