{
  "type": "Feature",
  "properties": {
    "addr:full":"Calle de Sol, S/n Casaseca De Las Chanas Zamora 49151",
    "addr:housenumber":"s",
    "addr:postcode":"49151",
    "addr:street":"Calle De Sol;/ N",
    "iso:country":"ES",
    "sg:address":"Calle de Sol, S/n",
    "sg:city":"Casaseca De Las Chanas",
    "sg:orig_category":"Material Y Herramientas Agr\u00cdcolas",
    "sg:phone":"+34 980 57 76 85",
    "sg:postcode":"49151",
    "sg:province":"Zamora",
    "wof:name":"Industrias Agmagu S.l.",
    "wof:placetype":"venue"
},
  "geometry": {"coordinates":[-5.6781988144,41.4409484863],"type":"Point"}
}