{
  "type": "Feature",
  "properties": {
    "addr:full":"Calle de Bilintx, 2 Bilbao Vizcaya 48006",
    "addr:housenumber":"2",
    "addr:postcode":"48006",
    "addr:street":"Calle De Bilintx",
    "iso:country":"ES",
    "sg:address":"Calle de Bilintx, 2",
    "sg:city":"Bilbao",
    "sg:orig_category":"M\u00c9dicos: Foniatr\u00cda Y Logopedia",
    "sg:phone":"+34 944 73 16 36",
    "sg:postcode":"48006",
    "sg:province":"Vizcaya",
    "wof:name":"Centro Logopedico Bilbaino",
    "wof:placetype":"venue"
},
  "geometry": {"coordinates":[-2.9167296886,43.2597999573],"type":"Point"}
}