{
  "type": "Feature",
  "properties": {
    "addr:full":"Calle de Carretera, 3 Huercal-overa Almer\u00eda 04600",
    "addr:housenumber":"3",
    "addr:postcode":"04600",
    "addr:street":"Calle De Carretera;Almeri\u0301A",
    "iso:country":"ES",
    "sg:address":"Calle de Carretera, 3",
    "sg:city":"Huercal-overa",
    "sg:orig_category":"Distribuci\u00d3n De Petr\u00d3leo Y Derivados",
    "sg:phone":"+34 950 47 04 83",
    "sg:postcode":"04600",
    "sg:province":"Almer\u00eda",
    "wof:name":"Gasoleos Dimagas S.l.",
    "wof:placetype":"venue"
},
  "geometry": {"coordinates":[-1.9411423206,37.3865280151],"type":"Point"}
}