{
  "type": "Feature",
  "properties": {
    "iso:country":"ES",
    "sg:address":"Calle de Tellez, 1",
    "sg:city":"Madrid",
    "sg:orig_category":"Farmacias (repartici\u00d3n Y Al Por Mayor)",
    "sg:phone":"+34 915 02 03 61",
    "sg:postcode":"28007",
    "sg:province":"Madrid",
    "wof:name":"Comercial Farmaceutica S. A.",
    "wof:placetype":"venue"
},
  "geometry": {"coordinates":[-3.6836950779,40.4042510986],"type":"Point"}
}