{
  "type": "Feature",
  "properties": {
    "iso:country":"ES",
    "sg:address":"Pla De Foios(p I Moncada Iii), 22",
    "sg:city":"Moncada",
    "sg:orig_category":"Tubos De Cart\u00d3n Y Papel",
    "sg:phone":"+34 961 39 98 90",
    "sg:postcode":"46113",
    "sg:province":"Valencia",
    "wof:name":"Archivos Castellano S.l.",
    "wof:placetype":"venue"
},
  "geometry": {"coordinates":[-0.3889622092,39.5633659363],"type":"Point"}
}