{
  "type": "Feature",
  "properties": {
    "addr:full":"Velazquez, 104 Madrid Madrid 28006",
    "addr:housenumber":"104",
    "addr:postcode":"28006",
    "addr:street":"Velazquez",
    "iso:country":"ES",
    "sg:address":"Velazquez, 104",
    "sg:city":"Madrid",
    "sg:orig_category":"Florister\u00cdas",
    "sg:phone":"+34 914 35 48 87",
    "sg:postcode":"28006",
    "sg:province":"Madrid",
    "wof:name":"Olalla Lopez Rufina",
    "wof:placetype":"venue"
},
  "geometry": {"coordinates":[-3.6831450462,40.4347305298],"type":"Point"}
}