{
  "type": "Feature",
  "properties": {
    "addr:full":"San Leonardo, 11 Albox Almer\u00eda 04800",
    "addr:housenumber":"11",
    "addr:postcode":"04800",
    "addr:street":"San Leonardo",
    "iso:country":"ES",
    "sg:address":"San Leonardo, 11",
    "sg:city":"Albox",
    "sg:orig_category":"Peluquer\u00cdas, Peluquer\u00cda Mixta",
    "sg:phone":"+34 950 63 32 58",
    "sg:postcode":"04800",
    "sg:province":"Almer\u00eda",
    "wof:name":"Martinez Chaneboux Isabel",
    "wof:placetype":"venue"
},
  "geometry": {"coordinates":[-2.1395890713,37.3874855042],"type":"Point"}
}