{
  "type": "Feature",
  "properties": {
    "addr:full":"Urb Monte Lanuza, 9 Coveta Fuma Alicante 03560",
    "addr:housenumber":"9",
    "addr:postcode":"03560",
    "addr:street":"Lanuza",
    "iso:country":"ES",
    "sg:address":"Urb Monte Lanuza, 9",
    "sg:city":"Coveta Fuma",
    "sg:orig_category":"Sociedades, Compa\u00d1\u00cdas Aseguradoras",
    "sg:phone":"+34 965 63 87 51",
    "sg:postcode":"03560",
    "sg:province":"Alicante",
    "wof:name":"Ceips S.l.",
    "wof:placetype":"venue"
},
  "geometry": {"coordinates":[-0.3906340003,38.4271888733],"type":"Point"}
}