{
  "type": "Feature",
  "properties": {
    "addr:full":"Calle de Martin Alonso, 4 Castellon Castell\u00f3n 12003",
    "addr:housenumber":"4",
    "addr:postcode":"12003",
    "addr:street":"Calle De Martin Alonso;Castello\u0301N",
    "iso:country":"ES",
    "sg:address":"Calle de Martin Alonso, 4",
    "sg:city":"Castellon",
    "sg:orig_category":"Farmacias",
    "sg:phone":"+34 964 22 27 18",
    "sg:postcode":"12003",
    "sg:province":"Castell\u00f3n",
    "wof:name":"Martinez Gomez Maria Del Carmen",
    "wof:placetype":"venue"
},
  "geometry": {"coordinates":[-0.0300990008,39.9809951782],"type":"Point"}
}