{
  "type": "Feature",
  "properties": {
    "addr:full":"Ctra Paradas, 2 Marchena Sevilla 41620",
    "addr:housenumber":"2",
    "addr:postcode":"41620",
    "addr:street":"Ctra Paradas",
    "iso:country":"ES",
    "sg:address":"Ctra Paradas, 2",
    "sg:city":"Marchena",
    "sg:orig_category":"Aceites Y Grasas Alimentarias (fabricaci\u00d3n, Al Por Mayor)",
    "sg:phone":"+34 954 84 37 63",
    "sg:postcode":"41620",
    "sg:province":"Sevilla",
    "wof:name":"Fundacion Patrimonio Comunal Olivarero",
    "wof:placetype":"venue"
},
  "geometry": {"coordinates":[-5.4189901352,37.3239059448],"type":"Point"}
}