{
  "type": "Feature",
  "properties": {
    "iso:country":"ES",
    "sg:address":"Calle de Rio Nora, 2",
    "sg:city":"Oviedo",
    "sg:orig_category":"Caf\u00c9s, Bares, Cervecer\u00cdas",
    "sg:phone":"+34 985 20 09 32",
    "sg:postcode":"33010",
    "sg:province":"Asturias",
    "wof:name":"Vileda Alvarez Jose Antonio",
    "wof:placetype":"venue"
},
  "geometry": {"coordinates":[-5.8244261742,43.3682327271],"type":"Point"}
}