{
  "type": "Feature",
  "properties": {
    "iso:country":"ES",
    "sg:address":"Calle de Valencia, 45",
    "sg:city":"Chert",
    "sg:orig_category":"Negocio De Materiales De Construcci\u00d3n",
    "sg:phone":"+34 964 49 00 45",
    "sg:postcode":"12360",
    "sg:province":"Castell\u00f3n",
    "wof:name":"Segarra Carbo Desiderio",
    "wof:placetype":"venue"
},
  "geometry": {"coordinates":[0.158374995,40.5197525024],"type":"Point"}
}