{
  "type": "Feature",
  "properties": {
    "iso:country":"ES",
    "sg:address":"Carr Carretera, S/n",
    "sg:city":"Casc Antic",
    "sg:orig_category":"Maquinaria Para Industrias Diversas",
    "sg:phone":"+34 973 60 08 12",
    "sg:postcode":"25241",
    "sg:province":"Lleida",
    "wof:name":"Arbeca Llars S.l.",
    "wof:placetype":"venue"
},
  "geometry": {"coordinates":[0.6257824898,41.614151001],"type":"Point"}
}