{
  "type": "Feature",
  "properties": {
    "addr:full":"Avda Juan Carlos I, 12 Mancha Real Ja\u00e9n 23100",
    "addr:housenumber":"12",
    "addr:postcode":"23100",
    "addr:street":"Avda Juan Carlos I",
    "iso:country":"ES",
    "sg:address":"Avda Juan Carlos I, 12",
    "sg:city":"Mancha Real",
    "sg:orig_category":"Electricidad: Instaladores",
    "sg:phone":"+34 953 35 01 33",
    "sg:postcode":"23100",
    "sg:province":"Ja\u00e9n",
    "wof:name":"Delgado Crespo Jose",
    "wof:placetype":"venue"
},
  "geometry": {"coordinates":[-3.6113259792,37.7877044678],"type":"Point"}
}