{
  "type": "Feature",
  "properties": {
    "addr:full":"Calle de Fragua, 31 Cenizate Albacete 02247",
    "addr:housenumber":"31",
    "addr:postcode":"02247",
    "addr:street":"Calle De Fragua",
    "iso:country":"ES",
    "sg:address":"Calle de Fragua, 31",
    "sg:city":"Cenizate",
    "sg:orig_category":"Camiser\u00cda Y Ropa Interior Masculina (al Por Menor)",
    "sg:phone":"+34 967 48 20 95",
    "sg:postcode":"02247",
    "sg:province":"Albacete",
    "wof:name":"Sociedad Cooperativa Limitada Cenitex",
    "wof:placetype":"venue"
},
  "geometry": {"coordinates":[-1.6599940062,39.3025360107],"type":"Point"}
}