{
  "type": "Feature",
  "properties": {
    "iso:country":"ES",
    "sg:address":"Calle de Margarita (urb La Carolina), 7",
    "sg:city":"Marbella",
    "sg:orig_category":"Administradores De Bienes Y Delegados De Comunidades De Propietarios",
    "sg:phone":"+34 952 90 38 21",
    "sg:postcode":"29600",
    "sg:province":"M\u00e1laga",
    "wof:name":"Sardona Espa\u00f1a S.l.",
    "wof:placetype":"venue"
},
  "geometry": {"coordinates":[-4.991710186,36.4893035889],"type":"Point"}
}