{
  "type": "Feature",
  "properties": {
    "iso:country":"ES",
    "sg:address":"Calle de Mar Rojo (del), 20",
    "sg:city":"Tres Cantos",
    "sg:orig_category":"Promotores Constructores",
    "sg:phone":"+34 918 04 17 09",
    "sg:postcode":"28760",
    "sg:province":"Madrid",
    "wof:name":"Slmac Diaz S.l.",
    "wof:placetype":"venue"
},
  "geometry": {"coordinates":[-3.7036299706,40.5930328369],"type":"Point"}
}