{
  "type": "Feature",
  "properties": {
    "iso:country":"ES",
    "sg:address":"Pg Comte De Vilardaga, 45",
    "sg:city":"Sant Feliu Llobregat",
    "sg:orig_category":"Promotores Constructores",
    "sg:phone":"+34 936 85 47 32",
    "sg:postcode":"08980",
    "sg:province":"Barcelona",
    "wof:name":"Kretton S.a.",
    "wof:placetype":"venue"
},
  "geometry": {"coordinates":[2.0509150028,41.3860435486],"type":"Point"}
}