{
  "type": "Feature",
  "properties": {
    "iso:country":"ES",
    "sg:address":"Rua Figueiras, S/n",
    "sg:city":"Milladoiro",
    "sg:orig_category":"Inmobiliaria (agencias)",
    "sg:phone":"+34 981 53 18 09",
    "sg:postcode":"15895",
    "sg:province":"La Coru\u00f1a",
    "sg:website":"www.coinasa.es",
    "wof:name":"Inversiones Panamerica S.l.",
    "wof:placetype":"venue"
},
  "geometry": {"coordinates":[-8.5761032104,42.844493866],"type":"Point"}
}