{
  "type": "Feature",
  "properties": {
    "addr:full":"Crrta. De La Rambla, 4 San Pedro Albacete 02326",
    "addr:housenumber":"4",
    "addr:postcode":"02326",
    "addr:street":"La Rambla",
    "iso:country":"ES",
    "sg:address":"Crrta. De La Rambla, 4",
    "sg:city":"San Pedro",
    "sg:orig_category":"Centros De Salud",
    "sg:phone":"+34 967 35 80 61",
    "sg:postcode":"02326",
    "sg:province":"Albacete",
    "wof:name":"Ayuntamiento De San Pedro",
    "wof:placetype":"venue"
},
  "geometry": {"coordinates":[-2.1867756844,38.8264694214],"type":"Point"}
}