{
  "type": "Feature",
  "properties": {
    "iso:country":"ES",
    "sg:address":"Avda Antonio Hurtado, 4",
    "sg:city":"Caceres",
    "sg:orig_category":"Asesor\u00cda Sobre Comunicaci\u00d3n De Empresas",
    "sg:phone":"+34 927 22 30 80",
    "sg:postcode":"10002",
    "sg:province":"C\u00e1ceres",
    "wof:name":"Duran Mendo Joaquin",
    "wof:placetype":"venue"
},
  "geometry": {"coordinates":[-6.3786201477,39.4678459167],"type":"Point"}
}