{
  "type": "Feature",
  "properties": {
    "addr:full":"Calle de Alfredo Aleix, 25 Madrid Madrid 28044",
    "addr:housenumber":"25",
    "addr:postcode":"madrid;28044",
    "addr:street":"Calle De Alfredo Aleix",
    "iso:country":"ES",
    "sg:address":"Calle de Alfredo Aleix, 25",
    "sg:city":"Madrid",
    "sg:orig_category":"Abogados",
    "sg:phone":"+34 915 08 67 03",
    "sg:postcode":"28044",
    "sg:province":"Madrid",
    "sg:website":"www.infanteilarrinoa.com",
    "wof:name":"Infante Cabello Pablo Carlos",
    "wof:placetype":"venue"
},
  "geometry": {"coordinates":[-3.7564299107,40.3681716919],"type":"Point"}
}