{
  "type": "Feature",
  "properties": {
    "addr:full":"Calle de San Vicente, 63 Santa Eulalia Islas Baleares 07840",
    "addr:housenumber":"63",
    "addr:postcode":"07840",
    "addr:street":"Calle De San Vicente",
    "iso:country":"ES",
    "sg:address":"Calle de San Vicente, 63",
    "sg:city":"Santa Eulalia",
    "sg:orig_category":"Transportes Por Carretera: Lotes Completos, Mercanc\u00cdas Diversas",
    "sg:phone":"+34 971 33 06 86",
    "sg:postcode":"07840",
    "sg:province":"Islas Baleares",
    "wof:name":"Clapes Torres Jose",
    "wof:placetype":"venue"
},
  "geometry": {"coordinates":[1.5341500044,38.9855194092],"type":"Point"}
}