{
  "type": "Feature",
  "properties": {
    "iso:country":"ES",
    "sg:address":"Carrer de Portal Nou, 8",
    "sg:city":"Barcelona",
    "sg:orig_category":"Servicios De Higiene Y Peluquer\u00cda Para Perros Y Gatos",
    "sg:phone":"+34 932 68 33 22",
    "sg:postcode":"08003",
    "sg:province":"Barcelona",
    "wof:name":"Donastol  Nelson",
    "wof:placetype":"venue"
},
  "geometry": {"coordinates":[2.1808578968,41.3884544373],"type":"Point"}
}