{
  "type": "Feature",
  "properties": {
    "iso:country":"ES",
    "sg:address":"Via San Fernando, 43",
    "sg:city":"Zaragoza",
    "sg:orig_category":"Laboratorios Y Cl\u00cdnicas Veterinarias",
    "sg:phone":"+34 976 37 11 93",
    "sg:postcode":"50007",
    "sg:province":"Zaragoza",
    "wof:name":"Clinica Veterinaria San Fernando S.cv.",
    "wof:placetype":"venue"
},
  "geometry": {"coordinates":[-0.8812609911,41.6345176697],"type":"Point"}
}