{
  "type": "Feature",
  "properties": {
    "iso:country":"ES",
    "sg:address":"Rua Valle Inclan, 2",
    "sg:city":"Ourense",
    "sg:orig_category":"Asesor\u00cda Fiscal Y Jur\u00cddica",
    "sg:phone":"+34 988 24 37 50",
    "sg:postcode":"32004",
    "sg:province":"Ourense",
    "wof:name":"Parada Arcia Antonio Enrique",
    "wof:placetype":"venue"
},
  "geometry": {"coordinates":[-7.8615632057,42.3393211365],"type":"Point"}
}