{
  "type": "Feature",
  "properties": {
    "iso:country":"ES",
    "sg:address":"Calle de Moratin, 2",
    "sg:city":"Nueva Andalucia",
    "sg:orig_category":"Venta, Instalaci\u00d3n, Reparaci\u00d3n De Antenas Para Televisi\u00d3n",
    "sg:phone":"+34 952 81 63 11",
    "sg:postcode":"29660",
    "sg:province":"M\u00e1laga",
    "wof:name":"Aguilar Ramirez Francisco",
    "wof:placetype":"venue"
},
  "geometry": {"coordinates":[-4.980755806,36.5008583069],"type":"Point"}
}