{
  "type": "Feature",
  "properties": {
    "addr:full":"Avda Paz (la), S/n Tamarite Litera Huesca 22550",
    "addr:postcode":"22550",
    "addr:street":"Avda Paz La S / N Tamarite",
    "iso:country":"ES",
    "sg:address":"Avda Paz (la), S/n",
    "sg:city":"Tamarite Litera",
    "sg:orig_category":"Cooperativas Agr\u00cdcolas",
    "sg:phone":"+34 974 42 02 50",
    "sg:postcode":"22550",
    "sg:province":"Huesca",
    "wof:name":"Cooperativa Fruticola De La Litera",
    "wof:placetype":"venue"
},
  "geometry": {"coordinates":[0.4220199883,41.8635215759],"type":"Point"}
}