{
  "type": "Feature",
  "properties": {
    "addr:full":"S Fernando, 41 S. Agustin-playa Ingles Las Palmas 35100",
    "addr:housenumber":"41",
    "addr:postcode":"35100",
    "addr:street":"S Fernando;S. Agustin-Playa",
    "iso:country":"ES",
    "sg:address":"S Fernando, 41",
    "sg:city":"S. Agustin-playa Ingles",
    "sg:orig_category":"Tintorer\u00cdas, Limpieza En Seco",
    "sg:phone":"+34 928 77 49 14",
    "sg:postcode":"35100",
    "sg:province":"Las Palmas",
    "wof:name":"Garcia Chico Maximo",
    "wof:placetype":"venue"
},
  "geometry": {"coordinates":[-15.4397096634,28.1302204132],"type":"Point"}
}