{
  "type": "Feature",
  "properties": {
    "addr:full":"C/ Ciutat D'onda, 122 Paterna Valencia 46988",
    "addr:housenumber":"122",
    "addr:postcode":"46988",
    "addr:street":"C / Ciutat D'Onda",
    "iso:country":"ES",
    "sg:address":"C/ Ciutat D'onda, 122",
    "sg:city":"Paterna",
    "sg:orig_category":"Cueros Y Pieles (al Por Mayor)",
    "sg:phone":"+34 961 32 45 69",
    "sg:postcode":"46988",
    "sg:province":"Valencia",
    "wof:name":"Internacional De Cueros Y Pieles S.a.",
    "wof:placetype":"venue"
},
  "geometry": {"coordinates":[-0.4408999979,39.5301818848],"type":"Point"}
}