{
  "type": "Feature",
  "properties": {
    "iso:country":"ES",
    "sg:address":"Carrer de Mi\u00d1o, 19",
    "sg:city":"Terrassa",
    "sg:orig_category":"Suministros Y Materiales Industriales",
    "sg:phone":"+34 937 36 10 70",
    "sg:postcode":"08223",
    "sg:province":"Barcelona",
    "wof:name":"Suministros Sumetasa S. A.",
    "wof:placetype":"venue"
},
  "geometry": {"coordinates":[2.0300478935,41.5568809509],"type":"Point"}
}