{
  "type": "Feature",
  "properties": {
    "addr:full":"Avda Ciudad De Barcelona, 99 Madrid Madrid 28007",
    "addr:housenumber":"99",
    "addr:postcode":"madrid;28007",
    "addr:street":"Avda Ciudad De Barcelona",
    "iso:country":"ES",
    "sg:address":"Avda Ciudad De Barcelona, 99",
    "sg:city":"Madrid",
    "sg:orig_category":"Fabricaci\u00d3n De Muebles",
    "sg:phone":"+34 914 34 93 33",
    "sg:postcode":"28007",
    "sg:province":"Madrid",
    "wof:name":"Carrasco Martin Juan",
    "wof:placetype":"venue"
},
  "geometry": {"coordinates":[-3.6717588902,40.3997955322],"type":"Point"}
}