{
  "type": "Feature",
  "properties": {
    "iso:country":"ES",
    "sg:address":"Carrer de Tirso De Molina, 1",
    "sg:city":"Magaluf",
    "sg:orig_category":"Fabricaci\u00d3n, Instalaci\u00d3n De Estufas",
    "sg:phone":"+34 971 13 20 29",
    "sg:postcode":"07181",
    "sg:province":"Islas Baleares",
    "wof:name":"Pedro Fornes S.l.",
    "wof:placetype":"venue"
},
  "geometry": {"coordinates":[2.5300760269,39.5040779114],"type":"Point"}
}