{
  "type": "Feature",
  "properties": {
    "iso:country":"ES",
    "sg:address":"Bard Barriada Cantarranas, 241",
    "sg:city":"Barrio Cantarranas",
    "sg:orig_category":"Promotores Constructores",
    "sg:phone":"+34 976 78 04 83",
    "sg:postcode":"50190",
    "sg:province":"Zaragoza",
    "wof:name":"Merino Lope Carlos",
    "wof:placetype":"venue"
},
  "geometry": {"coordinates":[-1.0269140005,41.6842803955],"type":"Point"}
}