{
  "type": "Feature",
  "properties": {
    "iso:country":"ES",
    "sg:address":"Calle de San Bernardo, 3",
    "sg:city":"Santa Maria De Huerta",
    "sg:orig_category":"Comunidades Religiosas",
    "sg:phone":"+34 975 32 70 01",
    "sg:postcode":"42260",
    "sg:province":"Soria",
    "wof:name":"Sociedad Del Sagrado Corazon De Jesus Provincia Centro Sur Curia Provincial",
    "wof:placetype":"venue"
},
  "geometry": {"coordinates":[-2.1779510975,41.2613449097],"type":"Point"}
}