{
  "type": "Feature",
  "properties": {
    "addr:full":"Calle de Escultor Carlos Ymbert, 2 Vitoria-gasteiz \u00c1lava 01007",
    "addr:housenumber":"2",
    "addr:postcode":"01007",
    "addr:street":"Calle De Escultor Carlos Ymbert",
    "iso:country":"ES",
    "sg:address":"Calle de Escultor Carlos Ymbert, 2",
    "sg:city":"Vitoria-gasteiz",
    "sg:orig_category":"Farmacias",
    "sg:phone":"+34 945 13 27 81",
    "sg:postcode":"01007",
    "sg:province":"\u00c1lava",
    "wof:name":"Farmacia Licenciadas Lorenzo Urrutia Cb",
    "wof:placetype":"venue"
},
  "geometry": {"coordinates":[-2.6830356121,42.8390922546],"type":"Point"}
}