{
  "type": "Feature",
  "properties": {
    "iso:country":"ES",
    "sg:address":"Calle de San Felix, 16",
    "sg:city":"Castellon",
    "sg:orig_category":"Bancos",
    "sg:phone":"+34 964 23 05 19",
    "sg:postcode":"12004",
    "sg:province":"Castell\u00f3n",
    "sg:website":"www.bancodevalencia.es",
    "wof:name":"Banco De Valencia S.a.",
    "wof:placetype":"venue"
},
  "geometry": {"coordinates":[-0.0257600006,40.0253791809],"type":"Point"}
}