{
  "type": "Feature",
  "properties": {
    "iso:country":"ES",
    "sg:address":"Calle de Montera, 2",
    "sg:city":"Mazarron",
    "sg:orig_category":"Caf\u00c9s, Bares, Cervecer\u00cdas",
    "sg:phone":"+34 968 59 22 00",
    "sg:postcode":"30870",
    "sg:province":"Murcia",
    "wof:name":"Parra Jerez Juana Maria",
    "wof:placetype":"venue"
},
  "geometry": {"coordinates":[-1.3116459846,37.5995063782],"type":"Point"}
}