{
  "type": "Feature",
  "properties": {
    "iso:country":"ES",
    "sg:address":"Rua Torrente (de), 12",
    "sg:city":"Santiago De Compostela",
    "sg:orig_category":"Obras Y Organismos Sociales",
    "sg:phone":"+34 981 52 40 75",
    "sg:postcode":"15899",
    "sg:province":"La Coru\u00f1a",
    "wof:name":"Iniciativas De Apoyo A Infancia Arela",
    "wof:placetype":"venue"
},
  "geometry": {"coordinates":[-8.5636348724,42.8620681763],"type":"Point"}
}