{
  "type": "Feature",
  "properties": {
    "addr:full":"Ptge Segria, 3 Lleida Lleida 25006",
    "addr:housenumber":"3",
    "addr:postcode":"25006",
    "addr:street":"Ptge Segria",
    "iso:country":"ES",
    "sg:address":"Ptge Segria, 3",
    "sg:city":"Lleida",
    "sg:orig_category":"Ingeniero",
    "sg:phone":"+34 973 26 26 90",
    "sg:postcode":"25006",
    "sg:province":"Lleida",
    "wof:name":"Vilaseca Alavedra Juan",
    "wof:placetype":"venue"
},
  "geometry": {"coordinates":[0.6133549809,41.6176338196],"type":"Point"}
}