{
  "type": "Feature",
  "properties": {
    "iso:country":"ES",
    "sg:address":"Plaz Marina Espa\u00d1ola, 56",
    "sg:city":"Cordoba",
    "sg:orig_category":"Fabricaci\u00d3n, Importaci\u00d3n De L\u00c1mparas Y Bombillas",
    "sg:phone":"+34 957 46 48 14",
    "sg:postcode":"14011",
    "sg:province":"C\u00f3rdoba",
    "wof:name":"Navarro Hidalgo Carmen",
    "wof:placetype":"venue"
},
  "geometry": {"coordinates":[-4.8029088974,37.8908309937],"type":"Point"}
}