{
  "type": "Feature",
  "properties": {
    "addr:full":"Avda Marin, 4 Con Pontevedra 36950",
    "addr:housenumber":"4",
    "addr:postcode":"36950",
    "addr:street":"Avda Marin;Pontevedra",
    "iso:country":"ES",
    "sg:address":"Avda Marin, 4",
    "sg:city":"Con",
    "sg:orig_category":"Negocio De Materiales De Construcci\u00d3n",
    "sg:phone":"+34 986 31 03 40",
    "sg:postcode":"36950",
    "sg:province":"Pontevedra",
    "wof:name":"Suministros Moama S.l.",
    "wof:placetype":"venue"
},
  "geometry": {"coordinates":[-8.738442421,42.2772254944],"type":"Point"}
}