{
  "type": "Feature",
  "properties": {
    "addr:full":"Plaz Pozo Hondo, 1 Campo Criptana Ciudad Real 13610",
    "addr:housenumber":"1",
    "addr:postcode":"13610",
    "addr:street":"Hondo;Criptana",
    "iso:country":"ES",
    "sg:address":"Plaz Pozo Hondo, 1",
    "sg:city":"Campo Criptana",
    "sg:orig_category":"Ebanister\u00cda",
    "sg:phone":"+34 926 56 21 10",
    "sg:postcode":"13610",
    "sg:province":"Ciudad Real",
    "wof:name":"Lopez Rodero Matias",
    "wof:placetype":"venue"
},
  "geometry": {"coordinates":[-3.1243391037,39.403339386],"type":"Point"}
}