{
  "type": "Feature",
  "properties": {
    "iso:country":"ES",
    "sg:address":"Calle de Cigue\u00d1a (la), 59",
    "sg:city":"Logro\u00f1o",
    "sg:orig_category":"Panader\u00cdas, Panader\u00cdas",
    "sg:phone":"+34 941 23 83 92",
    "sg:postcode":"26004",
    "sg:province":"La Rioja",
    "wof:name":"Panaderia Garrido Rios Sl",
    "wof:placetype":"venue"
},
  "geometry": {"coordinates":[-2.4291927814,42.4644546509],"type":"Point"}
}