{
  "type": "Feature",
  "properties": {
    "addr:full":"Calle de Francisco Grandmontagne, 12 Burgos Burgos 09007",
    "addr:housenumber":"12",
    "addr:postcode":"09007",
    "addr:street":"Calle De Francisco Grandmontagne",
    "iso:country":"ES",
    "sg:address":"Calle de Francisco Grandmontagne, 12",
    "sg:city":"Burgos",
    "sg:orig_category":"Supermercados Y Hipermercados",
    "sg:phone":"+34 947 21 74 11",
    "sg:postcode":"09007",
    "sg:province":"Burgos",
    "wof:name":"Supermercados Sabeco S.a.",
    "wof:placetype":"venue"
},
  "geometry": {"coordinates":[-3.6703300476,42.3509407043],"type":"Point"}
}