{
  "type": "Feature",
  "properties": {
    "iso:country":"ES",
    "sg:address":"Calle de Jose Antonio Primo De Rivera, 77",
    "sg:city":"Arrecife",
    "sg:orig_category":"Asesor\u00cda Fiscal Y Jur\u00cddica",
    "sg:phone":"+34 928 80 31 95",
    "sg:postcode":"35500",
    "sg:province":"Las Palmas",
    "wof:name":"Asesoria De Leon Y Rodriguez S.c.p",
    "wof:placetype":"venue"
},
  "geometry": {"coordinates":[-13.5542831421,28.9594402313],"type":"Point"}
}