{
  "type": "Feature",
  "properties": {
    "iso:country":"ES",
    "sg:address":"Calle de Charcon, 7",
    "sg:city":"Talavera Reina",
    "sg:orig_category":"Cer\u00c1mica Art\u00cdstica Y Decorativa",
    "sg:phone":"+34 925 80 50 82",
    "sg:postcode":"45600",
    "sg:province":"Toledo",
    "wof:name":"Taller De Arte Original Talavera S.l.",
    "wof:placetype":"venue"
},
  "geometry": {"coordinates":[-4.8348736763,39.9587593079],"type":"Point"}
}