{
  "type": "Feature",
  "properties": {
    "iso:country":"ES",
    "sg:address":"Calle de Fernando Moreno Marquez, 8",
    "sg:city":"Zafra",
    "sg:orig_category":"Ingeniero",
    "sg:phone":"+34 924 55 15 27",
    "sg:postcode":"06300",
    "sg:province":"Badajoz",
    "wof:name":"Tinoco Peinado Manuel",
    "wof:placetype":"venue"
},
  "geometry": {"coordinates":[-6.420938015,38.4246406555],"type":"Point"}
}