{
  "type": "Feature",
  "properties": {
    "addr:full":"Calle de Quintana, 11 Oviedo Asturias 33009",
    "addr:housenumber":"11",
    "addr:postcode":"33009",
    "addr:street":"Calle De Quintana",
    "iso:country":"ES",
    "sg:address":"Calle de Quintana, 11",
    "sg:city":"Oviedo",
    "sg:orig_category":"Ense\u00d1anza Variada",
    "sg:phone":"+34 985 20 52 32",
    "sg:postcode":"33009",
    "sg:province":"Asturias",
    "sg:website":"www.cursomir.com",
    "wof:name":"Cursos Intensivos Mir Asturias S.l.",
    "wof:placetype":"venue"
},
  "geometry": {"coordinates":[-5.8477959633,43.3583641052],"type":"Point"}
}