{
  "type": "Feature",
  "properties": {
    "addr:full":"Rua Progreso, 18 Mondo\u00f1edo Lugo 27740",
    "addr:housenumber":"18",
    "addr:postcode":"27740",
    "addr:street":"Rua Progreso",
    "iso:country":"ES",
    "sg:address":"Rua Progreso, 18",
    "sg:city":"Mondo\u00f1edo",
    "sg:orig_category":"Bancos",
    "sg:phone":"+34 982 52 17 01",
    "sg:postcode":"27740",
    "sg:province":"Lugo",
    "sg:website":"www.bancogallego.es",
    "wof:name":"Banco Gallego S.a.",
    "wof:placetype":"venue"
},
  "geometry": {"coordinates":[-7.3644018173,43.4296455383],"type":"Point"}
}