{
  "type": "Feature",
  "properties": {
    "iso:country":"ES",
    "sg:address":"Puenticiella, S/n",
    "sg:city":"Limes",
    "sg:orig_category":"Empresas De Carpinter\u00cda De Madera",
    "sg:phone":"+34 985 81 54 56",
    "sg:postcode":"33817",
    "sg:province":"Asturias",
    "wof:name":"Carpintero Nicanor S.l.",
    "wof:placetype":"venue"
},
  "geometry": {"coordinates":[-6.55082798,43.1475296021],"type":"Point"}
}