{
  "type": "Feature",
  "properties": {
    "iso:country":"ES",
    "sg:address":"Calle de Virgen Del Socorro, 50",
    "sg:city":"Alacant",
    "sg:orig_category":"Clases De M\u00dasica Y Canto",
    "sg:phone":"+34 965 16 46 01",
    "sg:postcode":"03002",
    "sg:province":"Alicante",
    "wof:name":"Pe\u00f1a Ramirez Eddy",
    "wof:placetype":"venue"
},
  "geometry": {"coordinates":[-0.4823389947,38.3463592529],"type":"Point"}
}