{
  "type": "Feature",
  "properties": {
    "addr:full":"Calle de Camarena, 216 Madrid Madrid 28047",
    "addr:housenumber":"216",
    "addr:postcode":"28047",
    "addr:street":"Calle De Camarena",
    "iso:country":"ES",
    "sg:address":"Calle de Camarena, 216",
    "sg:city":"Madrid",
    "sg:orig_category":"Librer\u00cdas",
    "sg:phone":"+34 917 18 07 40",
    "sg:postcode":"28047",
    "sg:province":"Madrid",
    "wof:name":"Gonzalez San Pedro Julio",
    "wof:placetype":"venue"
},
  "geometry": {"coordinates":[-3.7561368942,40.3887214661],"type":"Point"}
}