{
  "type": "Feature",
  "properties": {
    "addr:full":"Calle de Atocha, 28 Madrid Madrid 28012",
    "addr:housenumber":"28",
    "addr:postcode":"madrid;28012",
    "addr:street":"Calle De Atocha",
    "iso:country":"ES",
    "sg:address":"Calle de Atocha, 28",
    "sg:city":"Madrid",
    "sg:orig_category":"Ropa Para Se\u00d1oras (al Por Menor)",
    "sg:phone":"+34 913 69 29 96",
    "sg:postcode":"28012",
    "sg:province":"Madrid",
    "wof:name":"Puente Mendez Jose Manuel",
    "wof:placetype":"venue"
},
  "geometry": {"coordinates":[-3.7016296387,40.4134941101],"type":"Point"}
}