{
  "type": "Feature",
  "properties": {
    "iso:country":"ES",
    "sg:address":"Ctra Juncal (el), 10",
    "sg:city":"Ugarte",
    "sg:orig_category":"V\u00c1lvulas",
    "sg:phone":"+34 944 38 00 12",
    "sg:postcode":"48510",
    "sg:province":"Vizcaya",
    "wof:name":"Sociedad Anonima Iberica De Distribuciones Industriales",
    "wof:placetype":"venue"
},
  "geometry": {"coordinates":[-3.0369338989,43.3047294617],"type":"Point"}
}