{
  "type": "Feature",
  "properties": {
    "iso:country":"ES",
    "sg:address":"Calle de Costa De La Luz, 5",
    "sg:city":"Almeria",
    "sg:orig_category":"Agencias Y Agentes Comerciales, Representantes",
    "sg:phone":"+34 950 14 91 30",
    "sg:postcode":"04009",
    "sg:province":"Almer\u00eda",
    "wof:name":"Garcia Jimenez Manuel Angel",
    "wof:placetype":"venue"
},
  "geometry": {"coordinates":[-2.4425942898,36.8547973633],"type":"Point"}
}