{
  "type": "Feature",
  "properties": {
    "iso:country":"ES",
    "sg:address":"Ctra. Cuerva, Km. 0000,7",
    "sg:city":"Galvez",
    "sg:orig_category":"Fabricaci\u00d3n De Muebles",
    "sg:phone":"+34 925 40 07 54",
    "sg:postcode":"45164",
    "sg:province":"Toledo",
    "wof:name":"Acabado Del Mueble Angel Y Jesus C.b.",
    "wof:placetype":"venue"
},
  "geometry": {"coordinates":[-4.271137,39.699604],"type":"Point"}
}