{
  "type": "Feature",
  "properties": {
    "addr:full":"Calle de Lopez De Hoyos, 81 Madrid Madrid 28002",
    "addr:housenumber":"81",
    "addr:postcode":"madrid;28002",
    "addr:street":"Calle De Lopez De Hoyos",
    "iso:country":"ES",
    "sg:address":"Calle de Lopez De Hoyos, 81",
    "sg:city":"Madrid",
    "sg:orig_category":"Frutas, Legumbres Frescas Y Tempranas (al Por Menor)",
    "sg:phone":"+34 914 15 57 43",
    "sg:postcode":"28002",
    "sg:province":"Madrid",
    "wof:name":"Arroyo Mu\u00f1oz Consuelo",
    "wof:placetype":"venue"
},
  "geometry": {"coordinates":[-3.6740438938,40.4443244934],"type":"Point"}
}