{
  "type": "Feature",
  "properties": {
    "addr:full":"Pla\u00c7 Pla\u00c7a Major, 35 Alzira Valencia 46600",
    "addr:housenumber":"35",
    "addr:postcode":"46600",
    "addr:street":"Major",
    "iso:country":"ES",
    "sg:address":"Pla\u00c7 Pla\u00c7a Major, 35",
    "sg:city":"Alzira",
    "sg:orig_category":"Cajas De Ahorro",
    "sg:phone":"+34 962 40 09 30",
    "sg:postcode":"46600",
    "sg:province":"Valencia",
    "sg:website":"www.bancaja.es",
    "wof:name":"Caja De Ahorros De Valencia Castellon Y Alicante",
    "wof:placetype":"venue"
},
  "geometry": {"coordinates":[-0.4378489852,39.1517295837],"type":"Point"}
}