{
  "type": "Feature",
  "properties": {
    "iso:country":"ES",
    "sg:address":"Calle de Goya, S/n",
    "sg:city":"Cedillo",
    "sg:orig_category":"Cerrajer\u00cda, Ferrallista",
    "sg:phone":"+34 927 59 00 97",
    "sg:postcode":"10513",
    "sg:province":"C\u00e1ceres",
    "wof:name":"Sanchez Roman Eladio",
    "wof:placetype":"venue"
},
  "geometry": {"coordinates":[-7.4936342239,39.6487159729],"type":"Point"}
}