{
  "type": "Feature",
  "properties": {
    "addr:full":"Pol Ind Canaris, S/n Alcudia Crespins Valencia 46690",
    "addr:housenumber":"s / n",
    "addr:postcode":"46690",
    "iso:country":"ES",
    "sg:address":"Pol Ind Canaris, S/n",
    "sg:city":"Alcudia Crespins",
    "sg:orig_category":"Ense\u00d1anza: Profesiones Art\u00cdsticas",
    "sg:phone":"+34 962 23 90 60",
    "sg:postcode":"46690",
    "sg:province":"Valencia",
    "sg:website":"www.estudioartero.com",
    "wof:name":"Estudio Grafico Artero S.l.",
    "wof:placetype":"venue"
},
  "geometry": {"coordinates":[-0.5928140283,38.973941803],"type":"Point"}
}