{
  "type": "Feature",
  "properties": {
    "iso:country":"ES",
    "sg:address":"Via Massague, 10",
    "sg:city":"Sabadell",
    "sg:orig_category":"Talleres: Ropa A Medida",
    "sg:phone":"+34 937 25 17 28",
    "sg:postcode":"08202",
    "sg:province":"Barcelona",
    "wof:name":"Batlle Freixas Manuel",
    "wof:placetype":"venue"
},
  "geometry": {"coordinates":[2.1080770493,41.5495452881],"type":"Point"}
}