{
  "type": "Feature",
  "properties": {
    "iso:country":"ES",
    "sg:address":"Calle de San Francisco De Asis, 9",
    "sg:city":"Gijon",
    "sg:orig_category":"Pescader\u00cdas (al Por Menor)",
    "sg:phone":"+34 985 16 54 59",
    "sg:postcode":"33205",
    "sg:province":"Asturias",
    "wof:name":"Perez Barros Maria Rosa",
    "wof:placetype":"venue"
},
  "geometry": {"coordinates":[-5.6560602188,43.5333557129],"type":"Point"}
}