{
  "type": "Feature",
  "properties": {
    "addr:full":"Calle de Misericordia (de La), 10 Arganda Madrid 28500",
    "addr:housenumber":"10",
    "addr:postcode":"28500",
    "addr:street":"Calle De Misericordia De La",
    "iso:country":"ES",
    "sg:address":"Calle de Misericordia (de La), 10",
    "sg:city":"Arganda",
    "sg:orig_category":"Empresarios",
    "sg:phone":"+34 918 71 22 57",
    "sg:postcode":"28500",
    "sg:province":"Madrid",
    "sg:website":"www.escuderogestion.com",
    "wof:name":"Taller De Cuadros Al Cuadrado S.l.",
    "wof:placetype":"venue"
},
  "geometry": {"coordinates":[-3.4406979084,40.2999954224],"type":"Point"}
}