{
  "type": "Feature",
  "properties": {
    "iso:country":"ES",
    "sg:address":"Calle de Doce De Octubre, 34",
    "sg:city":"Zaragoza",
    "sg:orig_category":"Florister\u00cdas",
    "sg:phone":"+34 976 25 17 29",
    "sg:postcode":"50007",
    "sg:province":"Zaragoza",
    "wof:name":"Pardos Perez Placida",
    "wof:placetype":"venue"
},
  "geometry": {"coordinates":[-0.8774417043,41.6348686218],"type":"Point"}
}