{
  "type": "Feature",
  "properties": {
    "addr:full":"Praz Concello, 78 Santa Uxia De Ribeira La Coru\u00f1a 15960",
    "addr:housenumber":"78",
    "addr:postcode":"15960",
    "addr:street":"Concello;Corun\u0303A",
    "iso:country":"ES",
    "sg:address":"Praz Concello, 78",
    "sg:city":"Santa Uxia De Ribeira",
    "sg:orig_category":"Carnicer\u00cdas, Carnicer\u00cdas",
    "sg:phone":"+34 981 83 56 02",
    "sg:postcode":"15960",
    "sg:province":"La Coru\u00f1a",
    "wof:name":"Garcia Meijide Manuel",
    "wof:placetype":"venue"
},
  "geometry": {"coordinates":[-8.9908485413,42.5553665161],"type":"Point"}
}