{
  "type": "Feature",
  "properties": {
    "iso:country":"ES",
    "sg:address":"A. Garcia, 18",
    "sg:city":"Atarrabia",
    "sg:orig_category":"Peluqueros: De Se\u00d1oras",
    "sg:phone":"+34 948 33 26 13",
    "sg:postcode":"31610",
    "sg:province":"Navarra",
    "wof:name":"Planillo Gindano Maria Jose",
    "wof:placetype":"venue"
},
  "geometry": {"coordinates":[-1.61066401,42.8336639404],"type":"Point"}
}