{
  "type": "Feature",
  "properties": {
    "addr:full":"Ctra Roa, Km. 0001,0 Pedrosa Duero Burgos 09314",
    "addr:postcode":"09314",
    "addr:street":"Ctra Roa Km. 0001,0 Pedrosa",
    "iso:country":"ES",
    "sg:address":"Ctra Roa, Km. 0001,0",
    "sg:city":"Pedrosa Duero",
    "sg:orig_category":"Vinos Y Licores (venta Al Por Menor)",
    "sg:phone":"+34 947 53 01 11",
    "sg:postcode":"09314",
    "sg:province":"Burgos",
    "sg:website":"www.pagodeloscapellanes.com",
    "wof:name":"Pago De Los Capellanes S.a.",
    "wof:placetype":"venue"
},
  "geometry": {"coordinates":[-3.9894990921,41.7136611938],"type":"Point"}
}