{
  "type": "Feature",
  "properties": {
    "iso:country":"ES",
    "sg:address":"Avda Calvo Sotelo, 16",
    "sg:city":"San Cristobal De La Laguna",
    "sg:orig_category":"M\u00c9dicos: Pediatr\u00cda. Enfermedades De Los Ni\u00d1os",
    "sg:phone":"+34 922 26 07 02",
    "sg:postcode":"38205",
    "sg:province":"Santa Cruz De Tenerife",
    "wof:name":"F.b. Medinad Laguna S.l.",
    "wof:placetype":"venue"
},
  "geometry": {"coordinates":[-16.3129653931,28.4808654785],"type":"Point"}
}