{
  "type": "Feature",
  "properties": {
    "iso:country":"ES",
    "sg:address":"Calle de Arambarri Musico, 3",
    "sg:city":"Bilbao",
    "sg:orig_category":"Florister\u00cdas",
    "sg:phone":"+34 944 11 50 40",
    "sg:postcode":"48004",
    "sg:province":"Vizcaya",
    "wof:name":"Herranz Aguado Jesus",
    "wof:placetype":"venue"
},
  "geometry": {"coordinates":[-2.9125483036,43.2529182434],"type":"Point"}
}