{
  "type": "Feature",
  "properties": {
    "addr:full":"Calle de Lillo Juan, 5 San Vicente Del Raspeig-sant Vicent Del Raspeig Alicante 03690",
    "addr:housenumber":"5",
    "addr:postcode":"03690",
    "addr:street":"Calle De Lillo Juan",
    "iso:country":"ES",
    "sg:address":"Calle de Lillo Juan, 5",
    "sg:city":"San Vicente Del Raspeig-sant Vicent Del Raspeig",
    "sg:orig_category":"Carnicer\u00cdas, Carnicer\u00cdas",
    "sg:phone":"+34 965 66 04 87",
    "sg:postcode":"03690",
    "sg:province":"Alicante",
    "wof:name":"Guijarro Garcia Antonio",
    "wof:placetype":"venue"
},
  "geometry": {"coordinates":[-0.5255699754,38.396736145],"type":"Point"}
}