{
  "type": "Feature",
  "properties": {
    "addr:full":"Avda Alcalde Gregorio Espino, 27 Vigo Pontevedra 36205",
    "addr:housenumber":"27",
    "addr:postcode":"36205",
    "addr:street":"Avda Alcalde Gregorio Espino",
    "iso:country":"ES",
    "sg:address":"Avda Alcalde Gregorio Espino, 27",
    "sg:city":"Vigo",
    "sg:orig_category":"Agencias De Viajes",
    "sg:phone":"+34 986 25 06 51",
    "sg:postcode":"36205",
    "sg:province":"Pontevedra",
    "sg:website":"www.halconviajes.com",
    "wof:name":"Viajes Halcon S.a.",
    "wof:placetype":"venue"
},
  "geometry": {"coordinates":[-8.7068138123,42.2307510376],"type":"Point"}
}