{
  "type": "Feature",
  "properties": {
    "addr:full":"Avda Reino Unido, 9 Sevilla Sevilla 41012",
    "addr:housenumber":"9",
    "addr:postcode":"41012",
    "addr:street":"Avda Reino Unido",
    "iso:country":"ES",
    "sg:address":"Avda Reino Unido, 9",
    "sg:city":"Sevilla",
    "sg:orig_category":"Producci\u00d3n, Distribuci\u00d3n De Electricidad",
    "sg:phone":"+34 954 29 61 98",
    "sg:postcode":"41012",
    "sg:province":"Sevilla",
    "wof:name":"Haz De Ventas Sl",
    "wof:placetype":"venue"
},
  "geometry": {"coordinates":[-5.9769001007,37.3472633362],"type":"Point"}
}