{
  "type": "Feature",
  "properties": {
    "addr:full":"Avda Europa, 331 Mojonera Almer\u00eda 04745",
    "addr:housenumber":"331",
    "addr:postcode":"04745",
    "addr:street":"Avda Europa",
    "iso:country":"ES",
    "sg:address":"Avda Europa, 331",
    "sg:city":"Mojonera",
    "sg:orig_category":"Venta, Montaje De Neum\u00c1ticos",
    "sg:phone":"+34 950 33 03 51",
    "sg:postcode":"04745",
    "sg:province":"Almer\u00eda",
    "wof:name":"Moralmotor S.l.",
    "wof:placetype":"venue"
},
  "geometry": {"coordinates":[-2.6761848927,36.7543678284],"type":"Point"}
}