{
  "type": "Feature",
  "properties": {
    "iso:country":"ES",
    "sg:address":"Pje. Zurron, S/n",
    "sg:city":"Azuaga",
    "sg:orig_category":"Producci\u00d3n, Venta De Productos De Agricultura Biol\u00d3gica",
    "sg:phone":"+34 924 14 40 02",
    "sg:postcode":"06920",
    "sg:province":"Badajoz",
    "wof:name":"Explotaciones Agrarias San Martin S.a.",
    "wof:placetype":"venue"
},
  "geometry": {"coordinates":[-5.6808290482,38.2573204041],"type":"Point"}
}