{
  "type": "Feature",
  "properties": {
    "addr:full":"Rua Real, 160 Ferrol La Coru\u00f1a 15402",
    "addr:housenumber":"160",
    "addr:postcode":"15402",
    "addr:street":"Rua Real;La Corun\u0303A",
    "iso:country":"ES",
    "sg:address":"Rua Real, 160",
    "sg:city":"Ferrol",
    "sg:orig_category":"Estancos",
    "sg:phone":"+34 981 35 13 47",
    "sg:postcode":"15402",
    "sg:province":"La Coru\u00f1a",
    "wof:name":"Pena Villasuso Maria Elena",
    "wof:placetype":"venue"
},
  "geometry": {"coordinates":[-8.2384223938,43.4818115234],"type":"Point"}
}