{
  "type": "Feature",
  "properties": {
    "iso:country":"ES",
    "sg:address":"Avda Primero De Mayo, 86",
    "sg:city":"Palmar  O Lugar De Don Juan",
    "sg:orig_category":"Telas Y Sedas (al Por Menor)",
    "sg:phone":"+34 968 88 55 58",
    "sg:postcode":"30120",
    "sg:province":"Murcia",
    "wof:name":"Romero Navarro Francisco",
    "wof:placetype":"venue"
},
  "geometry": {"coordinates":[-1.1164139509,37.9892501831],"type":"Point"}
}