{
  "type": "Feature",
  "properties": {
    "addr:full":"Plce Montcada, 4 Barcelona Barcelona 08003",
    "addr:housenumber":"4",
    "addr:postcode":"08003",
    "addr:street":"Montcada",
    "iso:country":"ES",
    "sg:address":"Plce Montcada, 4",
    "sg:city":"Barcelona",
    "sg:orig_category":"Edici\u00d3n De Diarios, Revistas, Boletines",
    "sg:phone":"+34 933 19 75 06",
    "sg:postcode":"08003",
    "sg:province":"Barcelona",
    "wof:name":"Pijoan Castello Joan",
    "wof:placetype":"venue"
},
  "geometry": {"coordinates":[2.1801650524,41.3854408264],"type":"Point"}
}