{
  "type": "Feature",
  "properties": {
    "iso:country":"ES",
    "sg:address":"Calle de Acera Del Darro, 44",
    "sg:city":"Granada",
    "sg:orig_category":"Caf\u00c9s, Bares, Cervecer\u00cdas",
    "sg:phone":"+34 958 26 16 78",
    "sg:postcode":"18005",
    "sg:province":"Granada",
    "wof:name":"El Tren Puente Casta\u00f1eda S.l.",
    "wof:placetype":"venue"
},
  "geometry": {"coordinates":[-3.5987679958,37.1714286804],"type":"Point"}
}