{
  "type": "Feature",
  "properties": {
    "iso:country":"ES",
    "sg:address":"Pedro Muguruza Etorbidea, 8",
    "sg:city":"Elgoibar",
    "sg:orig_category":"Molduras, Junquillos, Listones Y Molduras Perforadas",
    "sg:phone":"+34 943 74 10 12",
    "sg:postcode":"20870",
    "sg:province":"Guip\u00f9zcoa",
    "wof:name":"Lumar Cafe S.l.",
    "wof:placetype":"venue"
},
  "geometry": {"coordinates":[-2.4090080261,43.2173728943],"type":"Point"}
}