{
  "type": "Feature",
  "properties": {
    "addr:full":"Rua Santa Uxia, 27 Santa Uxia De Ribeira La Coru\u00f1a 15960",
    "addr:housenumber":"27",
    "addr:postcode":"15960",
    "addr:street":"Rua Santa Uxia;Corun\u0303A",
    "iso:country":"ES",
    "sg:address":"Rua Santa Uxia, 27",
    "sg:city":"Santa Uxia De Ribeira",
    "sg:orig_category":"Loter\u00cda Y T\u00d3mbola",
    "sg:phone":"+34 981 87 10 67",
    "sg:postcode":"15960",
    "sg:province":"La Coru\u00f1a",
    "wof:name":"Paz Franco Pilar",
    "wof:placetype":"venue"
},
  "geometry": {"coordinates":[-8.9919090271,42.5558395386],"type":"Point"}
}