{
  "type": "Feature",
  "properties": {
    "iso:country":"ES",
    "sg:address":"Barr Castelo De Arriba, 73",
    "sg:city":"Lugo",
    "sg:orig_category":"Asilos De Ancianos. Centros Privados",
    "sg:phone":"+34 982 25 10 92",
    "sg:postcode":"27190",
    "sg:province":"Lugo",
    "wof:name":"O Alba C.b.",
    "wof:placetype":"venue"
},
  "geometry": {"coordinates":[-7.4382419586,42.9896469116],"type":"Point"}
}