{
  "type": "Feature",
  "properties": {
    "iso:country":"ES",
    "sg:address":"Calle de Ronda (la), 17",
    "sg:city":"Castro Urdiales",
    "sg:classifiers":[
        {
            "category":"Autos & Motor Vehicles",
            "subcategory":"Automobile Sales",
            "type":"Retail Goods"
        }
    ],
    "sg:phone":"+34 942 87 25 92",
    "sg:postcode":"39700",
    "sg:province":"Cantabria",
    "wof:name":"Autoescuela Ostende S.l.",
    "wof:placetype":"venue"
},
  "geometry": {"coordinates":[-3.2200632095,43.3812561035],"type":"Point"}
}