{
  "type": "Feature",
  "properties": {
    "addr:full":"Calle de Batres, 9 Ventorro Del Cano Madrid 28925",
    "addr:housenumber":"9",
    "addr:postcode":"28925",
    "addr:street":"Calle De Batres",
    "iso:country":"ES",
    "sg:address":"Calle de Batres, 9",
    "sg:city":"Ventorro Del Cano",
    "sg:orig_category":"Equitaci\u00d3n Y Centros De H\u00cdpica",
    "sg:phone":"+34 916 32 02 61",
    "sg:postcode":"28925",
    "sg:province":"Madrid",
    "wof:name":"Kenter Desarrollos 2000 S.l.",
    "wof:placetype":"venue"
},
  "geometry": {"coordinates":[-3.8416273594,40.3920631409],"type":"Point"}
}