{
  "type": "Feature",
  "properties": {
    "iso:country":"ES",
    "sg:address":"Calle de Madera (de La), 24",
    "sg:city":"Partija-santa Monica",
    "sg:orig_category":"Muebles Y Accesorios Para Cocinas Y Cuartos De Ba\u00d1o (al Por Menor)",
    "sg:phone":"+34 916 66 57 81",
    "sg:postcode":"28529",
    "sg:province":"Madrid",
    "wof:name":"Centro Bricolage Cocinas Y Armarios S.l.",
    "wof:placetype":"venue"
},
  "geometry": {"coordinates":[-3.5102670193,40.314289093],"type":"Point"}
}