{
  "type": "Feature",
  "properties": {
    "iso:country":"ES",
    "sg:address":"Zona Aeroport, S/n",
    "sg:city":"Prat Llobregat",
    "sg:orig_category":"Transportes Internacionales",
    "sg:phone":"+34 933 78 86 36",
    "sg:postcode":"08820",
    "sg:province":"Barcelona",
    "sg:website":"www.janderijk.nl",
    "wof:name":"Jan De Rijk Espa\u00f1a S.l.",
    "wof:placetype":"venue"
},
  "geometry": {"coordinates":[2.0864720345,41.3289909363],"type":"Point"}
}