{
  "type": "Feature",
  "properties": {
    "addr:full":"Calle de Pintor Cuenca Mu\u00d1oz, 3 Cordoba C\u00f3rdoba 14008",
    "addr:housenumber":"3",
    "addr:postcode":"14008",
    "addr:street":"Calle De Pintor Cuenca Mun\u0303Oz;Co\u0301Rdoba",
    "iso:country":"ES",
    "sg:address":"Calle de Pintor Cuenca Mu\u00d1oz, 3",
    "sg:city":"Cordoba",
    "sg:orig_category":"M\u00c9dicos: Estomatolog\u00cda",
    "sg:phone":"+34 957 48 63 86",
    "sg:postcode":"14008",
    "sg:province":"C\u00f3rdoba",
    "wof:name":"Peix Santos Claudio Manuel",
    "wof:placetype":"venue"
},
  "geometry": {"coordinates":[-4.7840771675,37.8857688904],"type":"Point"}
}