{
  "type": "Feature",
  "properties": {
    "iso:country":"ES",
    "sg:address":"Calle de Calvario-la Orotava (el), 50",
    "sg:city":"Orotava",
    "sg:orig_category":"Distribuci\u00d3n De Petr\u00d3leo Y Derivados",
    "sg:phone":"+34 922 33 01 61",
    "sg:postcode":"38300",
    "sg:province":"Santa Cruz De Tenerife",
    "wof:name":"Sacramento Gonzalez Efren",
    "wof:placetype":"venue"
},
  "geometry": {"coordinates":[-16.5215339661,28.3933792114],"type":"Point"}
}