{
  "type": "Feature",
  "properties": {
    "iso:country":"ES",
    "sg:address":"Calle de Navas, 15",
    "sg:city":"Granada",
    "sg:orig_category":"Bisuter\u00cda, Joyer\u00cda, Relojer\u00cda (al Por Menor)",
    "sg:phone":"+34 958 22 50 68",
    "sg:postcode":"18009",
    "sg:province":"Granada",
    "wof:name":"Salamanca Zafra Jose Manuel",
    "wof:placetype":"venue"
},
  "geometry": {"coordinates":[-3.5977010727,37.1732444763],"type":"Point"}
}