{
  "type": "Feature",
  "properties": {
    "addr:full":"Avda Francia (de), 28 Jaca Huesca 22700",
    "addr:housenumber":"28",
    "addr:postcode":"22700",
    "addr:street":"Avda Francia De",
    "iso:country":"ES",
    "sg:address":"Avda Francia (de), 28",
    "sg:city":"Jaca",
    "sg:orig_category":"Instalaci\u00d3n, Reparaci\u00d3n De Ascensores Y Montacargas",
    "sg:phone":"+34 974 36 14 24",
    "sg:postcode":"22700",
    "sg:province":"Huesca",
    "sg:website":"www.otis.com",
    "wof:name":"Zardoya Otis S. A.",
    "wof:placetype":"venue"
},
  "geometry": {"coordinates":[-0.5491430759,42.5743980408],"type":"Point"}
}