{
  "type": "Feature",
  "properties": {
    "addr:full":"Calle de Julian Romero Briones, 30 Palmas De Gran Canaria Las Palmas 35001",
    "addr:housenumber":"30",
    "addr:postcode":"35001",
    "addr:street":"Calle De Julian Romero Briones",
    "iso:country":"ES",
    "sg:address":"Calle de Julian Romero Briones, 30",
    "sg:city":"Palmas De Gran Canaria",
    "sg:orig_category":"Comercio De Mobiliario De Oficina",
    "sg:phone":"+34 928 32 24 26",
    "sg:postcode":"35001",
    "sg:province":"Las Palmas",
    "wof:name":"Ofitesa Instalaciones S.l.",
    "wof:placetype":"venue"
},
  "geometry": {"coordinates":[-15.4176864624,28.0970859528],"type":"Point"}
}