{
  "type": "Feature",
  "properties": {
    "iso:country":"ES",
    "sg:address":"Calle de San Bernardo, 5",
    "sg:city":"Palmas De Gran Canaria",
    "sg:orig_category":"Art\u00cdculos De Regalo (al Por Menor)",
    "sg:phone":"+34 928 38 39 62",
    "sg:postcode":"35002",
    "sg:province":"Las Palmas",
    "wof:name":"Henriquez Sanchez Octavio",
    "wof:placetype":"venue"
},
  "geometry": {"coordinates":[-15.4174785614,28.1053447723],"type":"Point"}
}