{
  "type": "Feature",
  "properties": {
    "iso:country":"ES",
    "sg:address":"Latsunbeberri Auzoa, 36",
    "sg:city":"Hernani",
    "sg:orig_category":"Reposter\u00cdas",
    "sg:phone":"+34 943 33 30 02",
    "sg:postcode":"20120",
    "sg:province":"Guip\u00f9zcoa",
    "wof:name":"Garcia Caro Jose",
    "wof:placetype":"venue"
},
  "geometry": {"coordinates":[-1.9793070555,43.2690620422],"type":"Point"}
}