{
  "type": "Feature",
  "properties": {
    "addr:full":"C/ Doctor Caro, 25 Elche Alicante 03201",
    "addr:housenumber":"25",
    "addr:postcode":"03201",
    "addr:street":"C / Doctor Caro",
    "iso:country":"ES",
    "sg:address":"C/ Doctor Caro, 25",
    "sg:city":"Elche",
    "sg:orig_category":"Molduras, Junquillos, Listones Y Molduras Perforadas",
    "sg:phone":"+34 965 44 91 26",
    "sg:postcode":"03201",
    "sg:province":"Alicante",
    "wof:name":"Bar Forjador S.l.",
    "wof:placetype":"venue"
},
  "geometry": {"coordinates":[-0.7011380196,38.2666778564],"type":"Point"}
}