{
  "type": "Feature",
  "properties": {
    "iso:country":"ES",
    "sg:address":"Calle de Isaac Ramos, 1",
    "sg:city":"Madrid",
    "sg:orig_category":"Agencias Y Asesores De Publicidad",
    "sg:phone":"+34 913 04 70 19",
    "sg:postcode":"28037",
    "sg:province":"Madrid",
    "wof:name":"Proceparsa",
    "wof:placetype":"venue"
},
  "geometry": {"coordinates":[-3.6245019436,40.4349822998],"type":"Point"}
}