{
  "type": "Feature",
  "properties": {
    "iso:country":"ES",
    "sg:address":"Avda Constitucion, 127",
    "sg:city":"Valencia",
    "sg:orig_category":"Distribuci\u00d3n De Petr\u00d3leo Y Derivados",
    "sg:phone":"+34 963 66 66 43",
    "sg:postcode":"46009",
    "sg:province":"Valencia",
    "wof:name":"Casas Chaves Encarna",
    "wof:placetype":"venue"
},
  "geometry": {"coordinates":[-0.3741919994,39.491809845],"type":"Point"}
}