{
  "type": "Feature",
  "properties": {
    "iso:country":"ES",
    "sg:address":"Carrer de Can Noguera, 50",
    "sg:city":"Garriga",
    "sg:orig_category":"Alimentaci\u00d3n General (al Por Menor)",
    "sg:phone":"+34 938 71 40 71",
    "sg:postcode":"08530",
    "sg:province":"Barcelona",
    "wof:name":"Corominas Arnaus Concepcion",
    "wof:placetype":"venue"
},
  "geometry": {"coordinates":[2.2840359211,41.6830787659],"type":"Point"}
}