{
  "type": "Feature",
  "properties": {
    "addr:full":"Ctra. Sagunto-burgos, Km. 0122,1 Teruel Teruel 44002",
    "addr:postcode":"44002",
    "addr:street":"Ctra. Sagunto-Burgos Km. 0122,1;Teruel",
    "iso:country":"ES",
    "sg:address":"Ctra. Sagunto-burgos, Km. 0122,1",
    "sg:city":"Teruel",
    "sg:orig_category":"Chapa Y Pintura Veh\u00cdculos",
    "sg:phone":"+34 978 60 55 15",
    "sg:postcode":"44002",
    "sg:province":"Teruel",
    "wof:name":"Villarroya Gomez Jose Francisco",
    "wof:placetype":"venue"
},
  "geometry": {"coordinates":[-1.0912590027,40.3269119263],"type":"Point"}
}