{
  "type": "Feature",
  "properties": {
    "addr:full":"Carr Casteth, S/n Vielha Lleida 25530",
    "addr:housenumber":"s / n",
    "addr:postcode":"25530",
    "addr:street":"Carr Casteth",
    "iso:country":"ES",
    "sg:address":"Carr Casteth, S/n",
    "sg:city":"Vielha",
    "sg:orig_category":"Negocio De Materiales De Construcci\u00d3n",
    "sg:phone":"+34 973 64 04 82",
    "sg:postcode":"25530",
    "sg:province":"Lleida",
    "wof:name":"Salgueiro Ruibal Valeriano",
    "wof:placetype":"venue"
},
  "geometry": {"coordinates":[0.7920320034,42.7027435303],"type":"Point"}
}