{
  "type": "Feature",
  "properties": {
    "addr:full":"Carrer de Marquesos De Barbera, 3 Barbera Valles Barcelona 08210",
    "addr:housenumber":"3",
    "addr:postcode":"08210",
    "addr:street":"Carrer De Marquesos De Barbera",
    "iso:country":"ES",
    "sg:address":"Carrer de Marquesos De Barbera, 3",
    "sg:city":"Barbera Valles",
    "sg:orig_category":"Muebles Y Accesorios Para Cocinas Y Cuartos De Ba\u00d1o (al Por Menor)",
    "sg:phone":"+34 937 29 47 23",
    "sg:postcode":"08210",
    "sg:province":"Barcelona",
    "wof:name":"Nou Gres Barcruz S.l.",
    "wof:placetype":"venue"
},
  "geometry": {"coordinates":[2.1165149212,41.5174217224],"type":"Point"}
}