{
  "type": "Feature",
  "properties": {
    "addr:full":"Calle de Escuelas, S/n Carboneras Guadazaon Cuenca 16350",
    "addr:housenumber":"s / n",
    "addr:postcode":"16350",
    "addr:street":"Calle De Escuelas",
    "iso:country":"ES",
    "sg:address":"Calle de Escuelas, S/n",
    "sg:city":"Carboneras Guadazaon",
    "sg:orig_category":"Reposter\u00cdas",
    "sg:phone":"+34 969 34 10 45",
    "sg:postcode":"16350",
    "sg:province":"Cuenca",
    "wof:name":"Hermanos Fernandez",
    "wof:placetype":"venue"
},
  "geometry": {"coordinates":[-1.8113723993,39.8983078003],"type":"Point"}
}