{
  "type": "Feature",
  "properties": {
    "iso:country":"ES",
    "sg:address":"Pol Ind San Antonio, 41",
    "sg:city":"Illescas",
    "sg:orig_category":"Ebanistas Y Talladores De Muebles Y Objetos De Arte",
    "sg:phone":"+34 925 51 12 80",
    "sg:postcode":"45200",
    "sg:province":"Toledo",
    "wof:name":"Villaseca Navarro Alejandro",
    "wof:placetype":"venue"
},
  "geometry": {"coordinates":[-3.8458640575,40.1230163574],"type":"Point"}
}