{
  "type": "Feature",
  "properties": {
    "iso:country":"ES",
    "sg:address":"Calle de Santa Hortensia, 14",
    "sg:city":"Madrid",
    "sg:orig_category":"Abogados",
    "sg:phone":"+34 914 16 81 88",
    "sg:postcode":"28002",
    "sg:province":"Madrid",
    "wof:name":"Domenech Carrizosa Ramon",
    "wof:placetype":"venue"
},
  "geometry": {"coordinates":[-3.6698739529,40.4451332092],"type":"Point"}
}