{
  "type": "Feature",
  "properties": {
    "addr:full":"Calle de Juan Alvarez Mendizabal, 64 Madrid Madrid 28008",
    "addr:housenumber":"64",
    "addr:postcode":"madrid;28008",
    "addr:street":"Calle De Juan Alvarez Mendizabal",
    "iso:country":"ES",
    "sg:address":"Calle de Juan Alvarez Mendizabal, 64",
    "sg:city":"Madrid",
    "sg:orig_category":"Supermercados Y Hipermercados",
    "sg:phone":"+34 915 48 02 79",
    "sg:postcode":"28008",
    "sg:province":"Madrid",
    "wof:name":"Unimaxtres S.a.",
    "wof:placetype":"venue"
},
  "geometry": {"coordinates":[-3.7185308933,40.4289627075],"type":"Point"}
}