{
  "type": "Feature",
  "properties": {
    "addr:full":"Nafarroa Etorbidea, 13 Beasain Guip\u00f9zcoa 20200",
    "addr:housenumber":"13",
    "addr:postcode":"20200",
    "addr:street":"Nafarroa Etorbidea;Guipu\u0300Zcoa",
    "iso:country":"ES",
    "sg:address":"Nafarroa Etorbidea, 13",
    "sg:city":"Beasain",
    "sg:orig_category":"Zapatos (al Por Menor)",
    "sg:phone":"+34 943 16 30 75",
    "sg:postcode":"20200",
    "sg:province":"Guip\u00f9zcoa",
    "wof:name":"Zuasti Mujica Rosa Maria",
    "wof:placetype":"venue"
},
  "geometry": {"coordinates":[-2.2011554241,43.0467605591],"type":"Point"}
}