{
  "type": "Feature",
  "properties": {
    "addr:full":"Rua Emilia Pardo Bazan, 1 Ourense Ourense 32004",
    "addr:housenumber":"1",
    "addr:postcode":"32004",
    "addr:street":"Rua Emilia Pardo Bazan",
    "iso:country":"ES",
    "sg:address":"Rua Emilia Pardo Bazan, 1",
    "sg:city":"Ourense",
    "sg:orig_category":"Agencias De Trabajo Temporal",
    "sg:phone":"+34 988 39 15 87",
    "sg:postcode":"32004",
    "sg:province":"Ourense",
    "sg:website":"www.adecco.es",
    "wof:name":"Adecco E.t.t. S.a.",
    "wof:placetype":"venue"
},
  "geometry": {"coordinates":[-7.8602352142,42.3384132385],"type":"Point"}
}