{
  "type": "Feature",
  "properties": {
    "iso:country":"ES",
    "sg:address":"Principado-barredos, S/n",
    "sg:city":"Tira\u00f1a",
    "sg:orig_category":"Alquiler De Gr\u00daas",
    "sg:phone":"+34 985 60 27 83",
    "sg:postcode":"33970",
    "sg:province":"Asturias",
    "wof:name":"Suarez Fernandez Manuel Angel",
    "wof:placetype":"venue"
},
  "geometry": {"coordinates":[-5.5729689598,43.2602348328],"type":"Point"}
}