{
  "type": "Feature",
  "properties": {
    "iso:country":"ES",
    "sg:address":"Calle de Buen Gobernador, 6",
    "sg:city":"Madrid",
    "sg:orig_category":"Mutuas De Seguros",
    "sg:phone":"+34 913 26 25 61",
    "sg:postcode":"28027",
    "sg:province":"Madrid",
    "wof:name":"Geomil Transfer S.a.",
    "wof:placetype":"venue"
},
  "geometry": {"coordinates":[-3.6543700695,40.4329376221],"type":"Point"}
}