{
  "type": "Feature",
  "properties": {
    "addr:full":"Calle de Vi\u00d1a La, 27 Yunquera M\u00e1laga 29410",
    "addr:housenumber":"27",
    "addr:postcode":"29410",
    "addr:street":"Calle De Vin\u0303A La",
    "iso:country":"ES",
    "sg:address":"Calle de Vi\u00d1a La, 27",
    "sg:city":"Yunquera",
    "sg:orig_category":"Transportes Por V\u00cdas Navegables",
    "sg:phone":"+34 952 48 25 94",
    "sg:postcode":"29410",
    "sg:province":"M\u00e1laga",
    "wof:name":"Sanchez Benitez Miguel",
    "wof:placetype":"venue"
},
  "geometry": {"coordinates":[-4.91710186,36.7348632812],"type":"Point"}
}