{
  "type": "Feature",
  "properties": {
    "iso:country":"ES",
    "sg:address":"Carrer de Brussel.les (de), 2",
    "sg:city":"Salou",
    "sg:orig_category":"Cervecer\u00cdas",
    "sg:phone":"+34 977 38 05 91",
    "sg:postcode":"43840",
    "sg:province":"Tarragona",
    "wof:name":"Fernan's S.a.",
    "wof:placetype":"venue"
},
  "geometry": {"coordinates":[1.1448969841,41.0729026794],"type":"Point"}
}