{
  "type": "Feature",
  "properties": {
    "addr:full":"Galileo (z. Ind Cami Ral), 28 Gava Barcelona 08850",
    "addr:housenumber":"28",
    "addr:postcode":"08850",
    "addr:street":"Cami Ral",
    "iso:country":"ES",
    "sg:address":"Galileo (z. Ind Cami Ral), 28",
    "sg:city":"Gava",
    "sg:orig_category":"Construcci\u00d3n Mec\u00c1nica",
    "sg:phone":"+34 936 62 55 72",
    "sg:postcode":"08850",
    "sg:province":"Barcelona",
    "wof:name":"Comolplast S.l.",
    "wof:placetype":"venue"
},
  "geometry": {"coordinates":[1.9944449663,41.2862434387],"type":"Point"}
}