{
  "type": "Feature",
  "properties": {
    "addr:full":"Calle de Generalisimo, 2 Daya Nueva Alicante 03159",
    "addr:housenumber":"2",
    "addr:postcode":"03159",
    "addr:street":"Calle De Generalisimo",
    "iso:country":"ES",
    "sg:address":"Calle de Generalisimo, 2",
    "sg:city":"Daya Nueva",
    "sg:classifiers":[
        {
            "category":"Arts & Performance",
            "subcategory":"Art Gallery",
            "type":"Entertainment"
        }
    ],
    "sg:phone":"+34 965 70 06 16",
    "sg:postcode":"03159",
    "sg:province":"Alicante",
    "sg:tags":[
        "arte",
        "de",
        "galer\u00cdas"
    ],
    "wof:name":"Watts  Nick",
    "wof:placetype":"venue"
},
  "geometry": {"coordinates":[-0.7622020245,38.1142654419],"type":"Point"}
}