{
  "type": "Feature",
  "properties": {
    "iso:country":"ES",
    "sg:address":"Xixilion Kalea, 3",
    "sg:city":"Elgoibar",
    "sg:orig_category":"Mec\u00c1nico Del Autom\u00d3vil",
    "sg:phone":"+34 943 74 89 99",
    "sg:postcode":"20870",
    "sg:province":"Guip\u00f9zcoa",
    "wof:name":"Gregorio Fernandez S.a.",
    "wof:placetype":"venue"
},
  "geometry": {"coordinates":[-2.4138290882,43.2163581848],"type":"Point"}
}