{
  "type": "Feature",
  "properties": {
    "iso:country":"ES",
    "sg:address":"Calle de Escalona, 48",
    "sg:city":"Madrid",
    "sg:orig_category":"Administradores De Bienes Y Delegados De Comunidades De Propietarios",
    "sg:phone":"+34 915 18 24 18",
    "sg:postcode":"28024",
    "sg:province":"Madrid",
    "wof:name":"Adycon Sociedad De Gestion Y Administracion S.l.",
    "wof:placetype":"venue"
},
  "geometry": {"coordinates":[-3.7621119022,40.3964805603],"type":"Point"}
}