{
  "type": "Feature",
  "properties": {
    "addr:full":"Plaz Roma, 10 Burgos Burgos 09007",
    "addr:housenumber":"10",
    "addr:postcode":"09007",
    "iso:country":"ES",
    "sg:address":"Plaz Roma, 10",
    "sg:city":"Burgos",
    "sg:orig_category":"Servicios Gsm",
    "sg:phone":"+34 947 25 63 00",
    "sg:postcode":"09007",
    "sg:province":"Burgos",
    "wof:name":"Telycal 2000 S.l.",
    "wof:placetype":"venue"
},
  "geometry": {"coordinates":[-3.6495990753,42.344959259],"type":"Point"}
}