{
  "type": "Feature",
  "properties": {
    "iso:country":"ES",
    "sg:address":"Calle de San Antonio, 16",
    "sg:city":"Torreblanca",
    "sg:orig_category":"Abogados",
    "sg:phone":"+34 964 42 02 54",
    "sg:postcode":"12596",
    "sg:province":"Castell\u00f3n",
    "wof:name":"Clara Nu\u00f1ez Llombart S.l.",
    "wof:placetype":"venue"
},
  "geometry": {"coordinates":[0.1948840022,40.220703125],"type":"Point"}
}