{
  "type": "Feature",
  "properties": {
    "addr:full":"Calle de Compositor Lehmberg Ruiz, S/n Malaga M\u00e1laga 29007",
    "addr:postcode":"29007",
    "addr:street":"Calle De Compositor Lehmberg Ruiz S / N;Ma\u0301Laga",
    "iso:country":"ES",
    "sg:address":"Calle de Compositor Lehmberg Ruiz, S/n",
    "sg:city":"Malaga",
    "sg:orig_category":"Promotores Constructores",
    "sg:phone":"+34 952 37 42 70",
    "sg:postcode":"29007",
    "sg:province":"M\u00e1laga",
    "wof:name":"Imaga Proyectos Y Construcciones S.a.",
    "wof:placetype":"venue"
},
  "geometry": {"coordinates":[-4.4319667816,36.7177658081],"type":"Point"}
}