{
  "type": "Feature",
  "properties": {
    "iso:country":"ES",
    "sg:address":"Avgd Major, 55",
    "sg:city":"Massamagrell",
    "sg:orig_category":"Asesor\u00cda Fiscal Y Jur\u00cddica",
    "sg:phone":"+34 961 44 00 09",
    "sg:postcode":"46130",
    "sg:province":"Valencia",
    "wof:name":"Lluch Y Silvestre Servicios Y Asesoria S.l.",
    "wof:placetype":"venue"
},
  "geometry": {"coordinates":[-0.3309159875,39.5715026855],"type":"Point"}
}