{
  "type": "Feature",
  "properties": {
    "addr:full":"Calle de Marques De Urquijo, 21 Gijon Asturias 33203",
    "addr:housenumber":"21",
    "addr:postcode":"33203",
    "addr:street":"Calle De Marques De Urquijo",
    "iso:country":"ES",
    "sg:address":"Calle de Marques De Urquijo, 21",
    "sg:city":"Gijon",
    "sg:orig_category":"Caf\u00c9s, Bares, Cervecer\u00cdas",
    "sg:phone":"+34 985 37 39 37",
    "sg:postcode":"33203",
    "sg:province":"Asturias",
    "wof:name":"Maritima De Hosteleria De Castrillon",
    "wof:placetype":"venue"
},
  "geometry": {"coordinates":[-5.6463661194,43.5393714905],"type":"Point"}
}