{
  "type": "Feature",
  "properties": {
    "iso:country":"ES",
    "sg:address":"Calle de Sagasta, 4",
    "sg:city":"Madrid",
    "sg:orig_category":"Pelucas Y Postizos",
    "sg:phone":"+34 915 31 72 74",
    "sg:postcode":"28004",
    "sg:province":"Madrid",
    "wof:name":"Monna Lisa S. A.",
    "wof:placetype":"venue"
},
  "geometry": {"coordinates":[-3.7013659477,40.428768158],"type":"Point"}
}