{
  "type": "Feature",
  "properties": {
    "iso:country":"ES",
    "sg:address":"Avda Navarro Reverter, 8",
    "sg:city":"Valencia",
    "sg:orig_category":"Doctores En Medicina",
    "sg:phone":"+34 963 34 85 87",
    "sg:postcode":"46004",
    "sg:province":"Valencia",
    "wof:name":"Fuster Diana Enrique",
    "wof:placetype":"venue"
},
  "geometry": {"coordinates":[-0.3672260046,39.4711761475],"type":"Point"}
}