{
  "type": "Feature",
  "properties": {
    "addr:full":"Ctra. Logro\u00f1o, S/n S. Asensio La Rioja 26340",
    "addr:housenumber":"s",
    "addr:postcode":"26340",
    "addr:street":"Ctra. Logron\u0303O;/ N S. Asensio",
    "iso:country":"ES",
    "sg:address":"Ctra. Logro\u00f1o, S/n",
    "sg:city":"S. Asensio",
    "sg:orig_category":"Alcoholes Y Aguardientes (fabricaci\u00d3n, Al Por Mayor)",
    "sg:phone":"+34 941 45 71 33",
    "sg:postcode":"26340",
    "sg:province":"La Rioja",
    "wof:name":"Bodega Cooperativa Vinicola Davalillo S.c.l.",
    "wof:placetype":"venue"
},
  "geometry": {"coordinates":[-2.7503979206,42.4980621338],"type":"Point"}
}