{
  "type": "Feature",
  "properties": {
    "iso:country":"ES",
    "sg:address":"Trav Dalt, 125",
    "sg:city":"Barcelona",
    "sg:orig_category":"Lencer\u00cda Femenina, Corseter\u00cda, Trajes De Ba\u00d1o (al Por Menor)",
    "sg:phone":"+34 932 85 31 44",
    "sg:postcode":"08024",
    "sg:province":"Barcelona",
    "wof:name":"Bieljoel S.l.",
    "wof:placetype":"venue"
},
  "geometry": {"coordinates":[2.1592440605,41.4125213623],"type":"Point"}
}