{
  "type": "Feature",
  "properties": {
    "addr:full":"Calle de Carreterilla, 1 Castrojeriz Burgos 09110",
    "addr:housenumber":"1",
    "addr:postcode":"09110",
    "addr:street":"Calle De Carreterilla",
    "iso:country":"ES",
    "sg:address":"Calle de Carreterilla, 1",
    "sg:city":"Castrojeriz",
    "sg:orig_category":"Farmacias",
    "sg:phone":"+34 947 37 70 40",
    "sg:postcode":"09110",
    "sg:province":"Burgos",
    "wof:name":"Garcia Gallego Maria Del Rosario",
    "wof:placetype":"venue"
},
  "geometry": {"coordinates":[-4.141523838,42.2876396179],"type":"Point"}
}