{
  "type": "Feature",
  "properties": {
    "iso:country":"ES",
    "sg:address":"C/ Ciutat D'elda, 5",
    "sg:city":"Paterna",
    "sg:orig_category":"Agentes, Concesionarios Y Sucursales De Veh\u00cdculos",
    "sg:phone":"+34 961 34 05 05",
    "sg:postcode":"46988",
    "sg:province":"Valencia",
    "wof:name":"Autolix S.a.",
    "wof:placetype":"venue"
},
  "geometry": {"coordinates":[-0.4552347064,39.5115013123],"type":"Point"}
}