{
  "type": "Feature",
  "properties": {
    "addr:full":"Calle de Duque De Rivas, 8 Malaga M\u00e1laga 29013",
    "addr:housenumber":"8",
    "addr:postcode":"29013",
    "addr:street":"Calle De Duque De Rivas;Ma\u0301Laga",
    "iso:country":"ES",
    "sg:address":"Calle de Duque De Rivas, 8",
    "sg:city":"Malaga",
    "sg:orig_category":"Alquiler De V\u00cddeo",
    "sg:phone":"+34 952 26 43 48",
    "sg:postcode":"29013",
    "sg:province":"M\u00e1laga",
    "wof:name":"Construcciones Rofego S.l.",
    "wof:placetype":"venue"
},
  "geometry": {"coordinates":[-4.4237141609,36.7271728516],"type":"Point"}
}