{
  "type": "Feature",
  "properties": {
    "iso:country":"ES",
    "sg:address":"Calle de Rosal, 62",
    "sg:city":"Oviedo",
    "sg:orig_category":"Asesor\u00cda Fiscal Y Jur\u00cddica",
    "sg:phone":"+34 985 20 07 72",
    "sg:postcode":"33009",
    "sg:province":"Asturias",
    "wof:name":"Multitec S.coop.",
    "wof:placetype":"venue"
},
  "geometry": {"coordinates":[-5.8490190506,43.358669281],"type":"Point"}
}