{
  "type": "Feature",
  "properties": {
    "addr:full":"Ctra. Oropesa, S/n Candeleda \u00c1vila 05480",
    "addr:housenumber":"s / n",
    "addr:postcode":"05480",
    "addr:street":"Ctra. Oropesa",
    "iso:country":"ES",
    "sg:address":"Ctra. Oropesa, S/n",
    "sg:city":"Candeleda",
    "sg:orig_category":"Chapister\u00cda",
    "sg:phone":"+34 920 38 09 11",
    "sg:postcode":"05480",
    "sg:province":"\u00c1vila",
    "wof:name":"Candelauto 98 S.l.",
    "wof:placetype":"venue"
},
  "geometry": {"coordinates":[-5.2349038124,40.1447029114],"type":"Point"}
}