{
  "type": "Feature",
  "properties": {
    "iso:country":"ES",
    "sg:address":"Carrer de Cordova, 32",
    "sg:city":"Sant Vicen\u00c7 Dels Horts",
    "sg:orig_category":"Montaje (empresas De)",
    "sg:phone":"+34 936 56 34 64",
    "sg:postcode":"08620",
    "sg:province":"Barcelona",
    "wof:name":"Montajes Luma S.l.",
    "wof:placetype":"venue"
},
  "geometry": {"coordinates":[2.0029129982,41.397983551],"type":"Point"}
}