{
  "type": "Feature",
  "properties": {
    "addr:full":"Rua Pablo Iglesias, 7 Boiro La Coru\u00f1a 15930",
    "addr:housenumber":"7",
    "addr:postcode":"15930",
    "addr:street":"Rua Pablo Iglesias;La Corun\u0303A",
    "iso:country":"ES",
    "sg:address":"Rua Pablo Iglesias, 7",
    "sg:city":"Boiro",
    "sg:orig_category":"Caf\u00c9s, Bares, Cervecer\u00cdas",
    "sg:phone":"+34 981 84 76 48",
    "sg:postcode":"15930",
    "sg:province":"La Coru\u00f1a",
    "wof:name":"Diggatel S.l.",
    "wof:placetype":"venue"
},
  "geometry": {"coordinates":[-8.8846492767,42.6462516785],"type":"Point"}
}