{
  "type": "Feature",
  "properties": {
    "addr:full":"Calle de Primera Manzana, 106 Villena Alicante 03400",
    "addr:postcode":"03400",
    "addr:street":"Calle De Primera Manzana 106",
    "iso:country":"ES",
    "sg:address":"Calle de Primera Manzana, 106",
    "sg:city":"Villena",
    "sg:orig_category":"Pintores",
    "sg:phone":"+34 965 80 15 19",
    "sg:postcode":"03400",
    "sg:province":"Alicante",
    "wof:name":"Marco Hernandez Pedro",
    "wof:placetype":"venue"
},
  "geometry": {"coordinates":[-0.8596690297,38.6318511963],"type":"Point"}
}