{
  "type": "Feature",
  "properties": {
    "addr:full":"Avda Jose Mesa Y Lopez, 61 Palmas De Gran Canaria Las Palmas 35010",
    "addr:postcode":"35010",
    "addr:street":"Avda Jose Mesa Y Lopez 61",
    "iso:country":"ES",
    "sg:address":"Avda Jose Mesa Y Lopez, 61",
    "sg:city":"Palmas De Gran Canaria",
    "sg:orig_category":"Muebles Y Accesorios Para Cocinas Y Cuartos De Ba\u00d1o (al Por Menor)",
    "sg:phone":"+34 928 22 83 99",
    "sg:postcode":"35010",
    "sg:province":"Las Palmas",
    "wof:name":"A.feliciano S.a.",
    "wof:placetype":"venue"
},
  "geometry": {"coordinates":[-15.438123703,28.1319618225],"type":"Point"}
}