{
  "type": "Feature",
  "properties": {
    "addr:full":"Rua Santo Domingo, 29 Ourense Ourense 32003",
    "addr:housenumber":"29",
    "addr:postcode":"32003",
    "addr:street":"Rua Santo Domingo",
    "iso:country":"ES",
    "sg:address":"Rua Santo Domingo, 29",
    "sg:city":"Ourense",
    "sg:orig_category":"Cervecer\u00cdas",
    "sg:phone":"+34 988 24 91 41",
    "sg:postcode":"32003",
    "sg:province":"Ourense",
    "sg:website":"www.johnmulligan.info",
    "wof:name":"Telefourense S.l.",
    "wof:placetype":"venue"
},
  "geometry": {"coordinates":[-7.8632202148,42.3394813538],"type":"Point"}
}