{
  "type": "Feature",
  "properties": {
    "addr:full":"Calle de Rosa De Luxemburgo, 1 Almansa Albacete 02640",
    "addr:housenumber":"1",
    "addr:postcode":"02640",
    "addr:street":"Calle De Rosa De Luxemburgo",
    "iso:country":"ES",
    "sg:address":"Calle de Rosa De Luxemburgo, 1",
    "sg:city":"Almansa",
    "sg:orig_category":"Confecci\u00d3n De Zapatos",
    "sg:phone":"+34 967 34 07 64",
    "sg:postcode":"02640",
    "sg:province":"Albacete",
    "wof:name":"Kioguantes S.l.",
    "wof:placetype":"venue"
},
  "geometry": {"coordinates":[-1.0956139565,38.8690605164],"type":"Point"}
}