{
  "type": "Feature",
  "properties": {
    "addr:full":"Av Josep Molins, 56 Hospitalet Llobregat Barcelona 08906",
    "addr:housenumber":"56",
    "addr:postcode":"08906",
    "addr:street":"Av Josep Molins",
    "iso:country":"ES",
    "sg:address":"Av Josep Molins, 56",
    "sg:city":"Hospitalet Llobregat",
    "sg:orig_category":"Carnicer\u00cdas, Carnicer\u00cdas",
    "sg:phone":"+34 934 49 47 98",
    "sg:postcode":"08906",
    "sg:province":"Barcelona",
    "wof:name":"Lacueva Claramonte Joaquin",
    "wof:placetype":"venue"
},
  "geometry": {"coordinates":[2.106055975,41.3733406067],"type":"Point"}
}