{
  "type": "Feature",
  "properties": {
    "addr:full":"Avda Ricardo Fabrega, 57 Tabernas Almer\u00eda 04200",
    "addr:housenumber":"57",
    "addr:postcode":"04200",
    "addr:street":"Avda Ricardo Fabrega;Almeri\u0301A",
    "iso:country":"ES",
    "sg:address":"Avda Ricardo Fabrega, 57",
    "sg:city":"Tabernas",
    "sg:orig_category":"Molduras, Junquillos, Listones Y Molduras Perforadas",
    "sg:phone":"+34 950 36 51 59",
    "sg:postcode":"04200",
    "sg:province":"Almer\u00eda",
    "wof:name":"Martinez Miranda Jose Maria",
    "wof:placetype":"venue"
},
  "geometry": {"coordinates":[-2.389136076,37.0546913147],"type":"Point"}
}