{
  "type": "Feature",
  "properties": {
    "addr:full":"Calle de Pinar (el), 26 Santo Domingo De La Calzada La Rioja 26250",
    "addr:housenumber":"26",
    "addr:postcode":"26250",
    "addr:street":"Calle De Pinar El;Rioja",
    "iso:country":"ES",
    "sg:address":"Calle de Pinar (el), 26",
    "sg:city":"Santo Domingo De La Calzada",
    "sg:orig_category":"Peluquer\u00cdas, Peluquer\u00cda Mixta",
    "sg:phone":"+34 941 34 08 88",
    "sg:postcode":"26250",
    "sg:province":"La Rioja",
    "wof:name":"Olazabal Zudaire Camen",
    "wof:placetype":"venue"
},
  "geometry": {"coordinates":[-2.9528889656,42.4399833679],"type":"Point"}
}