{
  "type": "Feature",
  "properties": {
    "addr:full":"Calle de Antonio Maura, 22 Elda Alicante 03600",
    "addr:housenumber":"22",
    "addr:postcode":"03600",
    "addr:street":"Calle De Antonio Maura",
    "iso:country":"ES",
    "sg:address":"Calle de Antonio Maura, 22",
    "sg:city":"Elda",
    "sg:orig_category":"Heladeros",
    "sg:phone":"+34 965 38 10 25",
    "sg:postcode":"03600",
    "sg:province":"Alicante",
    "wof:name":"Valero Navarro Jose",
    "wof:placetype":"venue"
},
  "geometry": {"coordinates":[-0.7966179848,38.4774436951],"type":"Point"}
}