{
  "type": "Feature",
  "properties": {
    "addr:full":"Carr Sta Joaquima Vedruna, 17 Igualada Barcelona 08700",
    "addr:housenumber":"17",
    "addr:postcode":"08700",
    "addr:street":"Carr Sta Joaquima Vedruna",
    "iso:country":"ES",
    "sg:address":"Carr Sta Joaquima Vedruna, 17",
    "sg:city":"Igualada",
    "sg:orig_category":"Pescader\u00cdas (al Por Menor)",
    "sg:phone":"+34 938 05 52 60",
    "sg:postcode":"08700",
    "sg:province":"Barcelona",
    "wof:name":"Peixos Fiti S.l.",
    "wof:placetype":"venue"
},
  "geometry": {"coordinates":[1.6248739958,41.57787323],"type":"Point"}
}