{
  "type": "Feature",
  "properties": {
    "iso:country":"ES",
    "sg:address":"Calle de Larga, 122",
    "sg:city":"Quintanar Rey",
    "sg:orig_category":"Muebles, Minoristas",
    "sg:phone":"+34 967 49 51 31",
    "sg:postcode":"16220",
    "sg:province":"Cuenca",
    "wof:name":"Muebles Lopez Carretero C.b.",
    "wof:placetype":"venue"
},
  "geometry": {"coordinates":[-1.9301400185,39.3485984802],"type":"Point"}
}