{
  "type": "Feature",
  "properties": {
    "addr:full":"Calle de Molines (les), 42 Banyeres Mariola Alicante 03450",
    "addr:housenumber":"42",
    "addr:postcode":"03450",
    "addr:street":"Calle De Molines Les",
    "iso:country":"ES",
    "sg:address":"Calle de Molines (les), 42",
    "sg:city":"Banyeres Mariola",
    "sg:orig_category":"Otros Trabajos De Limpieza Y Mantenimiento (extracci\u00d3n De Polvo, Recogida De Amianto Y Desespumado)",
    "sg:phone":"+34 965 56 65 69",
    "sg:postcode":"03450",
    "sg:province":"Alicante",
    "wof:name":"David Pascual S.l.",
    "wof:placetype":"venue"
},
  "geometry": {"coordinates":[-0.6580740213,38.7120857239],"type":"Point"}
}