{
  "type": "Feature",
  "properties": {
    "iso:country":"ES",
    "sg:address":"Av Salvador Allende(vilares), 133",
    "sg:city":"I\u00f1as",
    "sg:orig_category":"Mataderos Y Talleres De Despiezado",
    "sg:phone":"+34 981 61 12 50",
    "sg:postcode":"15171",
    "sg:province":"La Coru\u00f1a",
    "wof:name":"Fripor S.a.l.",
    "wof:placetype":"venue"
},
  "geometry": {"coordinates":[-8.3423519135,43.3167266846],"type":"Point"}
}