{
  "type": "Feature",
  "properties": {
    "iso:country":"ES",
    "sg:address":"Calle de Alcala, 170",
    "sg:city":"Madrid",
    "sg:orig_category":"Complementos De Vestir (al Por Menor)",
    "sg:phone":"+34 913 55 51 56",
    "sg:postcode":"28028",
    "sg:province":"Madrid",
    "wof:name":"Liu  Shuangwei",
    "wof:placetype":"venue"
},
  "geometry": {"coordinates":[-3.666510582,40.4291915894],"type":"Point"}
}