{
  "type": "Feature",
  "properties": {
    "iso:country":"ES",
    "sg:address":"Avgd Madrid, De, 6",
    "sg:city":"Quart Poblet",
    "sg:orig_category":"Tubos Met\u00c1licos",
    "sg:phone":"+34 961 53 22 61",
    "sg:postcode":"46930",
    "sg:province":"Valencia",
    "sg:website":"www.emac-complementos.com",
    "wof:name":"Emac Complementos S.l.",
    "wof:placetype":"venue"
},
  "geometry": {"coordinates":[-0.4419890046,39.482711792],"type":"Point"}
}