{
  "type": "Feature",
  "properties": {
    "addr:full":"Nerga, S/n Hio Pontevedra 36948",
    "addr:postcode":"36948",
    "addr:street":"Nerga S / N",
    "iso:country":"ES",
    "sg:address":"Nerga, S/n",
    "sg:city":"Hio",
    "sg:orig_category":"Distribuci\u00d3n De Petr\u00d3leo Y Derivados",
    "sg:phone":"+34 986 32 95 17",
    "sg:postcode":"36948",
    "sg:province":"Pontevedra",
    "wof:name":"Pescados Y Mariscos Comar S.l.",
    "wof:placetype":"venue"
},
  "geometry": {"coordinates":[-8.6428003311,42.4304618835],"type":"Point"}
}