{
  "type": "Feature",
  "properties": {
    "addr:full":"Costera, 23 Benaguasil Valencia 46180",
    "addr:housenumber":"23",
    "addr:postcode":"46180",
    "addr:street":"Costera",
    "iso:country":"ES",
    "sg:address":"Costera, 23",
    "sg:city":"Benaguasil",
    "sg:orig_category":"Art\u00cdculos Funerarios (al Por Menor)",
    "sg:phone":"+34 962 73 02 48",
    "sg:postcode":"46180",
    "sg:province":"Valencia",
    "wof:name":"Jose Melia Servicios Funerarios S.l.",
    "wof:placetype":"venue"
},
  "geometry": {"coordinates":[-0.5875390172,39.5956382751],"type":"Point"}
}