{
  "type": "Feature",
  "properties": {
    "addr:full":"Carrer de Cervantes, 52 Amposta Tarragona 43870",
    "addr:housenumber":"52",
    "addr:postcode":"43870",
    "addr:street":"Carrer De Cervantes",
    "iso:country":"ES",
    "sg:address":"Carrer de Cervantes, 52",
    "sg:city":"Amposta",
    "sg:orig_category":"Organizaciones Internacionales",
    "sg:phone":"+34 977 70 26 80",
    "sg:postcode":"43870",
    "sg:province":"Tarragona",
    "wof:name":"Cruz Roja Espa\u00f1ola",
    "wof:placetype":"venue"
},
  "geometry": {"coordinates":[0.5771690011,40.7076835632],"type":"Point"}
}