{
  "type": "Feature",
  "properties": {
    "iso:country":"ES",
    "sg:address":"Calle de Reina Victoria, 27",
    "sg:city":"Parla",
    "sg:orig_category":"Ense\u00d1anza Superior Privada",
    "sg:phone":"+34 916 98 44 85",
    "sg:postcode":"28980",
    "sg:province":"Madrid",
    "wof:name":"Valora Centro De Formacion Y Atencion Socioeducativa",
    "wof:placetype":"venue"
},
  "geometry": {"coordinates":[-3.7710270882,40.2337112427],"type":"Point"}
}