{
  "type": "Feature",
  "properties": {
    "iso:country":"ES",
    "sg:address":"Calle de Sebastian Elcano, 29",
    "sg:city":"Sevilla",
    "sg:orig_category":"Material Y Suministros Para Dentistas, Cirujanos",
    "sg:phone":"+34 954 27 62 89",
    "sg:postcode":"41011",
    "sg:province":"Sevilla",
    "wof:name":"Dentalite S. A.",
    "wof:placetype":"venue"
},
  "geometry": {"coordinates":[-5.9958109856,37.3727035522],"type":"Point"}
}