{
  "type": "Feature",
  "properties": {
    "addr:full":"Avda Marina (la), 4 Algeciras C\u00e1diz 11201",
    "addr:housenumber":"4;ca\u0301diz",
    "addr:postcode":"11201",
    "addr:street":"Avda Marina La",
    "iso:country":"ES",
    "sg:address":"Avda Marina (la), 4",
    "sg:city":"Algeciras",
    "sg:orig_category":"Contenedores (mercanc\u00cdas)",
    "sg:phone":"+34 956 63 37 08",
    "sg:postcode":"11201",
    "sg:province":"C\u00e1diz",
    "wof:name":"Cotransa S.a.",
    "wof:placetype":"venue"
},
  "geometry": {"coordinates":[-5.4440498352,36.1283111572],"type":"Point"}
}