{
  "type": "Feature",
  "properties": {
    "addr:full":"Calle de Moraledas, 59 Lanjaron Granada 18420",
    "addr:housenumber":"59",
    "addr:postcode":"18420",
    "addr:street":"Calle De Moraledas",
    "iso:country":"ES",
    "sg:address":"Calle de Moraledas, 59",
    "sg:city":"Lanjaron",
    "sg:orig_category":"M\u00c9dicos: Estomatolog\u00cda",
    "sg:phone":"+34 958 77 12 30",
    "sg:postcode":"18420",
    "sg:province":"Granada",
    "wof:name":"Mu\u00f1oz Terron Jorge Jose",
    "wof:placetype":"venue"
},
  "geometry": {"coordinates":[-3.4812235832,36.9187660217],"type":"Point"}
}