{
  "type": "Feature",
  "properties": {
    "iso:country":"ES",
    "sg:address":"C. Tietar-barquilla, S/n",
    "sg:city":"Tietar Caudillo",
    "sg:orig_category":"Comercio De Carburantes",
    "sg:phone":"+34 927 55 03 22",
    "sg:postcode":"10319",
    "sg:province":"C\u00e1ceres",
    "wof:name":"Gasotietar S.l.",
    "wof:placetype":"venue"
},
  "geometry": {"coordinates":[-5.484058857,40.0295753479],"type":"Point"}
}