{
  "type": "Feature",
  "properties": {
    "iso:country":"ES",
    "sg:address":"Calle de Veracruz, 5",
    "sg:city":"Rota",
    "sg:orig_category":"Zapatos (al Por Menor)",
    "sg:phone":"+34 956 81 33 07",
    "sg:postcode":"11520",
    "sg:province":"C\u00e1diz",
    "wof:name":"Castro Reyes Jeronimo",
    "wof:placetype":"venue"
},
  "geometry": {"coordinates":[-6.3570990562,36.6220321655],"type":"Point"}
}