{
  "type": "Feature",
  "properties": {
    "addr:full":"Calle de Martin Abanto, 8 Zaragoza Zaragoza 50013",
    "addr:housenumber":"8",
    "addr:postcode":"50013",
    "addr:street":"Calle De Martin Abanto",
    "iso:country":"ES",
    "sg:address":"Calle de Martin Abanto, 8",
    "sg:city":"Zaragoza",
    "sg:orig_category":"Electricidad: Instalaciones Industriales",
    "sg:phone":"+34 976 59 23 59",
    "sg:postcode":"50013",
    "sg:province":"Zaragoza",
    "wof:name":"Electricidad Abad S.l.",
    "wof:placetype":"venue"
},
  "geometry": {"coordinates":[-0.8692589998,41.6396865845],"type":"Point"}
}