{
  "type": "Feature",
  "properties": {
    "iso:country":"ES",
    "sg:address":"Avda Valencia, 23",
    "sg:city":"Xeraco",
    "sg:orig_category":"Cajas Y Embalajes De Cart\u00d3n Y Papel",
    "sg:phone":"+34 962 89 12 33",
    "sg:postcode":"46770",
    "sg:province":"Valencia",
    "wof:name":"Bou Moragues Enrique",
    "wof:placetype":"venue"
},
  "geometry": {"coordinates":[-0.2187030017,39.0339698792],"type":"Point"}
}