{
  "type": "Feature",
  "properties": {
    "iso:country":"ES",
    "sg:address":"Calle de Okendo, 11",
    "sg:city":"Donostia-san Sebastian",
    "sg:orig_category":"Asesor\u00cda Fiscal Y Jur\u00cddica",
    "sg:phone":"+34 943 43 02 71",
    "sg:postcode":"20004",
    "sg:province":"Guip\u00f9zcoa",
    "wof:name":"Pelaez Verdasca Jose Enrique",
    "wof:placetype":"venue"
},
  "geometry": {"coordinates":[-1.980142951,43.320602417],"type":"Point"}
}