{
  "type": "Feature",
  "properties": {
    "iso:country":"ES",
    "sg:address":"Calle de Batalla Del Salado, 4",
    "sg:city":"Madridejos",
    "sg:orig_category":"Tapicer\u00cdas",
    "sg:phone":"+34 925 46 24 07",
    "sg:postcode":"45710",
    "sg:province":"Toledo",
    "wof:name":"Cuellar Flores Angel Gabriel",
    "wof:placetype":"venue"
},
  "geometry": {"coordinates":[-3.5268211365,39.4665794373],"type":"Point"}
}