{
  "type": "Feature",
  "properties": {
    "addr:full":"Calle de Ramon Y Cajal, 17 Sierra Luna Zaragoza 50612",
    "addr:housenumber":"17",
    "addr:postcode":"50612",
    "addr:street":"Calle De Ramon Y Cajal;Sierra Luna",
    "iso:country":"ES",
    "sg:address":"Calle de Ramon Y Cajal, 17",
    "sg:city":"Sierra Luna",
    "sg:orig_category":"Administraciones Regionales, Departamentales Y Locales",
    "sg:phone":"+34 976 68 60 01",
    "sg:postcode":"50612",
    "sg:province":"Zaragoza",
    "wof:name":"Ayuntamiento De Sierra De Luna",
    "wof:placetype":"venue"
},
  "geometry": {"coordinates":[-0.9106547236,42.0479164124],"type":"Point"}
}