{
  "type": "Feature",
  "properties": {
    "addr:full":"Suiza, S/n Gojar Granada 18150",
    "addr:housenumber":"s",
    "addr:postcode":"18150",
    "addr:street":"Suiza;/ N Gojar",
    "iso:country":"ES",
    "sg:address":"Suiza, S/n",
    "sg:city":"Gojar",
    "sg:orig_category":"Material Y Suministros Para Fotocopiadoras, Reprograf\u00cda",
    "sg:phone":"+34 958 50 39 23",
    "sg:postcode":"18150",
    "sg:province":"Granada",
    "wof:name":"Martinez Garcia Ricardo",
    "wof:placetype":"venue"
},
  "geometry": {"coordinates":[-3.6049389839,37.1085014343],"type":"Point"}
}