{
  "type": "Feature",
  "properties": {
    "addr:full":"Avda Sol, S/n Zubia Granada 18140",
    "addr:housenumber":"s / n",
    "addr:postcode":"18140",
    "addr:street":"Avda Sol;Zubia Granada",
    "iso:country":"ES",
    "sg:address":"Avda Sol, S/n",
    "sg:city":"Zubia",
    "sg:orig_category":"Explotaci\u00d3n De Canteras",
    "sg:phone":"+34 958 34 05 58",
    "sg:postcode":"18140",
    "sg:province":"Granada",
    "wof:name":"Jose Y Antonio Sanchez Martin C.b.",
    "wof:placetype":"venue"
},
  "geometry": {"coordinates":[-3.5764861107,37.1201553345],"type":"Point"}
}