{
  "type": "Feature",
  "properties": {
    "addr:full":"Calle de Antonio Gala, 39 Berja Almer\u00eda 04760",
    "addr:housenumber":"39",
    "addr:postcode":"04760",
    "addr:street":"Calle De Antonio Gala",
    "iso:country":"ES",
    "sg:address":"Calle de Antonio Gala, 39",
    "sg:city":"Berja",
    "sg:orig_category":"Peluquer\u00cdas, Peluquer\u00cda Mixta",
    "sg:phone":"+34 950 49 26 83",
    "sg:postcode":"04760",
    "sg:province":"Almer\u00eda",
    "wof:name":"Sevilla Gallardo Gema Gador",
    "wof:placetype":"venue"
},
  "geometry": {"coordinates":[-2.9425370693,36.8482666016],"type":"Point"}
}