{
  "type": "Feature",
  "properties": {
    "iso:country":"ES",
    "sg:address":"Calle de Los Herran, 4",
    "sg:city":"Vitoria-gasteiz",
    "sg:orig_category":"Muebles, Minoristas",
    "sg:phone":"+34 945 28 72 36",
    "sg:postcode":"01004",
    "sg:province":"\u00c1lava",
    "wof:name":"Formas , S.c.",
    "wof:placetype":"venue"
},
  "geometry": {"coordinates":[-2.6639990807,42.8423957825],"type":"Point"}
}