{
  "type": "Feature",
  "properties": {
    "addr:full":"Calle de Avenida De Salazar, S/n Lumbier Navarra 31440",
    "addr:housenumber":"s / n",
    "addr:postcode":"31440",
    "addr:street":"Calle De Avenida De Salazar",
    "iso:country":"ES",
    "sg:address":"Calle de Avenida De Salazar, S/n",
    "sg:city":"Lumbier",
    "sg:orig_category":"Muebles, Minoristas",
    "sg:phone":"+34 948 88 04 30",
    "sg:postcode":"31440",
    "sg:province":"Navarra",
    "wof:name":"Egurlanik S.l.l.",
    "wof:placetype":"venue"
},
  "geometry": {"coordinates":[-1.2987349033,42.6513710022],"type":"Point"}
}