{
  "type": "Feature",
  "properties": {
    "addr:full":"Calle de Enrique Van Dulken, S/n Churriana M\u00e1laga 29140",
    "addr:housenumber":"s / n",
    "addr:postcode":"29140",
    "addr:street":"Calle De Enrique Van Dulken",
    "iso:country":"ES",
    "sg:address":"Calle de Enrique Van Dulken, S/n",
    "sg:city":"Churriana",
    "sg:orig_category":"Agencias Y Agentes Comerciales, Representantes",
    "sg:phone":"+34 952 62 10 20",
    "sg:postcode":"29140",
    "sg:province":"M\u00e1laga",
    "wof:name":"Francisco Y Juan Ya\u00f1ez Jimenez S.cv.",
    "wof:placetype":"venue"
},
  "geometry": {"coordinates":[-4.4992389679,36.6627349854],"type":"Point"}
}