{
  "type": "Feature",
  "properties": {
    "iso:country":"ES",
    "sg:address":"Calle de Chacon, 26",
    "sg:city":"Santa Cruz De La Zarza",
    "sg:orig_category":"Ense\u00d1anza, Formaci\u00d3n Profesional: Aprendizaje",
    "sg:phone":"+34 925 14 31 21",
    "sg:postcode":"45370",
    "sg:province":"Toledo",
    "wof:name":"Ayuntamiento-biblioteca",
    "wof:placetype":"venue"
},
  "geometry": {"coordinates":[-3.1885728836,39.9839668274],"type":"Point"}
}