{
  "type": "Feature",
  "properties": {
    "iso:country":"ES",
    "sg:address":"Calle de Euskalerria, 1",
    "sg:city":"Zaldibar",
    "sg:orig_category":"Calderer\u00cda",
    "sg:phone":"+34 946 82 66 77",
    "sg:postcode":"48250",
    "sg:province":"Vizcaya",
    "wof:name":"Haize Ederra Bi S.l.",
    "wof:placetype":"venue"
},
  "geometry": {"coordinates":[-2.5491068363,43.1700401306],"type":"Point"}
}