{
  "type": "Feature",
  "properties": {
    "addr:full":"Carrer de Grassot, 55 Barcelona Barcelona 08025",
    "addr:housenumber":"55",
    "addr:postcode":"08025",
    "addr:street":"Carrer De Grassot",
    "iso:country":"ES",
    "sg:address":"Carrer de Grassot, 55",
    "sg:city":"Barcelona",
    "sg:orig_category":"Electrodom\u00c9sticos (al Por Menor)",
    "sg:phone":"+34 934 58 90 08",
    "sg:postcode":"08025",
    "sg:province":"Barcelona",
    "wof:name":"Indelsit Sociedad Cooperativa Catalana Limitada",
    "wof:placetype":"venue"
},
  "geometry": {"coordinates":[2.1665298939,41.4040985107],"type":"Point"}
}