{
  "type": "Feature",
  "properties": {
    "addr:full":"Calle de Arechavaleta, 5 Madrid Madrid 28041",
    "addr:housenumber":"5",
    "addr:postcode":"28041",
    "addr:street":"Calle De Arechavaleta",
    "iso:country":"ES",
    "sg:address":"Calle de Arechavaleta, 5",
    "sg:city":"Madrid",
    "sg:orig_category":"Panader\u00cdas, Panader\u00cdas",
    "sg:phone":"+34 917 98 14 52",
    "sg:postcode":"28041",
    "sg:province":"Madrid",
    "wof:name":"Martinez Martinez Jose Abel",
    "wof:placetype":"venue"
},
  "geometry": {"coordinates":[-3.6969497204,40.3517456055],"type":"Point"}
}