{
  "type": "Feature",
  "properties": {
    "addr:full":"Sect Descubridores, 8 Tres Cantos Madrid 28760",
    "addr:housenumber":"8",
    "addr:postcode":"28760",
    "addr:street":"Sect Descubridores",
    "iso:country":"ES",
    "sg:address":"Sect Descubridores, 8",
    "sg:city":"Tres Cantos",
    "sg:orig_category":"Cristaler\u00cdas",
    "sg:phone":"+34 918 03 02 23",
    "sg:postcode":"28760",
    "sg:province":"Madrid",
    "wof:name":"Antolin Trinidad Francisco",
    "wof:placetype":"venue"
},
  "geometry": {"coordinates":[-3.7163431644,40.6100234985],"type":"Point"}
}