{
  "type": "Feature",
  "properties": {
    "addr:full":"Av Espanya, 105 Eivissa Islas Baleares 07800",
    "addr:housenumber":"105",
    "addr:postcode":"07800",
    "addr:street":"Av Espanya",
    "iso:country":"ES",
    "sg:address":"Av Espanya, 105",
    "sg:city":"Eivissa",
    "sg:orig_category":"Molduras, Junquillos, Listones Y Molduras Perforadas",
    "sg:phone":"+34 971 39 99 88",
    "sg:postcode":"07800",
    "sg:province":"Islas Baleares",
    "wof:name":"Sanchez Riera Miguel",
    "wof:placetype":"venue"
},
  "geometry": {"coordinates":[1.4210300446,38.906539917],"type":"Point"}
}