{
  "type": "Feature",
  "properties": {
    "addr:full":"Calle de Cardenal Cisneros (del), 7 El Cruce Madrid 28860",
    "addr:housenumber":"7",
    "addr:postcode":"28860",
    "addr:street":"Calle De Cardenal Cisneros Del",
    "iso:country":"ES",
    "sg:address":"Calle de Cardenal Cisneros (del), 7",
    "sg:city":"El Cruce",
    "sg:orig_category":"Materias Pl\u00c1sticas: Productos De Consumo Masivo (fabricaci\u00d3n, Al Por Mayor)",
    "sg:phone":"+34 916 58 24 49",
    "sg:postcode":"28860",
    "sg:province":"Madrid",
    "wof:name":"Plasticos Yolanda S.l.",
    "wof:placetype":"venue"
},
  "geometry": {"coordinates":[-3.7003455162,40.4166908264],"type":"Point"}
}