{
  "type": "Feature",
  "properties": {
    "iso:country":"ES",
    "sg:address":"Calle de Santa Maria, 2",
    "sg:city":"Motril",
    "sg:orig_category":"Herboristas (al Por Menor)",
    "sg:phone":"+34 958 82 23 84",
    "sg:postcode":"18600",
    "sg:province":"Granada",
    "wof:name":"Molina Martin Maria Soledad",
    "wof:placetype":"venue"
},
  "geometry": {"coordinates":[-3.5173039436,36.7516860962],"type":"Point"}
}