{
  "type": "Feature",
  "properties": {
    "iso:country":"ES",
    "sg:address":"Plaz Mercado, 38",
    "sg:city":"Ledesma",
    "sg:orig_category":"Cajas Para Embalar",
    "sg:phone":"+34 923 57 03 45",
    "sg:postcode":"37100",
    "sg:province":"Salamanca",
    "wof:name":"Caja Rural Provincial De Salamanca",
    "wof:placetype":"venue"
},
  "geometry": {"coordinates":[-6.0026302338,41.0881652832],"type":"Point"}
}