{
  "type": "Feature",
  "properties": {
    "addr:full":"Pg Paisos Catalans, 36 Salt Girona 17190",
    "addr:housenumber":"36",
    "addr:postcode":"17190",
    "addr:street":"Pg Paisos Catalans",
    "iso:country":"ES",
    "sg:address":"Pg Paisos Catalans, 36",
    "sg:city":"Salt",
    "sg:orig_category":"Molduras, Junquillos, Listones Y Molduras Perforadas",
    "sg:phone":"+34 972 23 58 33",
    "sg:postcode":"17190",
    "sg:province":"Girona",
    "wof:name":"Aguilar Arias Jose",
    "wof:placetype":"venue"
},
  "geometry": {"coordinates":[2.7980465889,41.9738197327],"type":"Point"}
}