{
  "type": "Feature",
  "properties": {
    "iso:country":"ES",
    "sg:address":"Ctra Consuegra, Km. 0009,5",
    "sg:city":"Urda",
    "sg:orig_category":"Marroquiner\u00cda (confecci\u00d3n)",
    "sg:phone":"+34 925 47 20 34",
    "sg:postcode":"45480",
    "sg:province":"Toledo",
    "wof:name":"Comart Cuero S.l.",
    "wof:placetype":"venue"
},
  "geometry": {"coordinates":[-3.7186939716,39.4149017334],"type":"Point"}
}