{
  "type": "Feature",
  "properties": {
    "iso:country":"ES",
    "sg:address":"Rbla Llibertat, 26",
    "sg:city":"Girona",
    "sg:orig_category":"Zapatos (al Por Menor)",
    "sg:phone":"+34 972 20 00 43",
    "sg:postcode":"17004",
    "sg:province":"Girona",
    "wof:name":"Fontdalmas S. L.",
    "wof:placetype":"venue"
},
  "geometry": {"coordinates":[2.8241069317,41.9836845398],"type":"Point"}
}