{
  "type": "Feature",
  "properties": {
    "addr:full":"Rua Nazario Abel, 91 Lugo Lugo 27004",
    "addr:housenumber":"91",
    "addr:postcode":"27004",
    "addr:street":"Rua Nazario Abel",
    "iso:country":"ES",
    "sg:address":"Rua Nazario Abel, 91",
    "sg:city":"Lugo",
    "sg:orig_category":"Mercer\u00cda, Lencer\u00cda (al Por Menor)",
    "sg:phone":"+34 982 20 07 82",
    "sg:postcode":"27004",
    "sg:province":"Lugo",
    "wof:name":"Dablanca Argerey Elena",
    "wof:placetype":"venue"
},
  "geometry": {"coordinates":[-7.5694198608,43.0161705017],"type":"Point"}
}