{
  "type": "Feature",
  "properties": {
    "addr:full":"Calle de Oca\u00d1a, 75 Madrid Madrid 28047",
    "addr:housenumber":"75",
    "addr:postcode":"madrid;28047",
    "addr:street":"Calle De Ocan\u0303A",
    "iso:country":"ES",
    "sg:address":"Calle de Oca\u00d1a, 75",
    "sg:city":"Madrid",
    "sg:orig_category":"Fotograf\u00cda Art\u00cdstica Y Retratos",
    "sg:phone":"+34 914 65 72 88",
    "sg:postcode":"28047",
    "sg:province":"Madrid",
    "wof:name":"Manuel Jose Y Rafael Quintana C.b.",
    "wof:placetype":"venue"
},
  "geometry": {"coordinates":[-3.7559099197,40.3862724304],"type":"Point"}
}