{
  "type": "Feature",
  "properties": {
    "iso:country":"ES",
    "sg:address":"Carr Arraval, 2",
    "sg:city":"Mao",
    "sg:orig_category":"Quiropr\u00c1cticos",
    "sg:phone":"+34 971 35 46 04",
    "sg:postcode":"07701",
    "sg:province":"Islas Baleares",
    "wof:name":"Mir Villalonga Cristina",
    "wof:placetype":"venue"
},
  "geometry": {"coordinates":[4.2650108337,39.8881187439],"type":"Point"}
}