{
  "type": "Feature",
  "properties": {
    "addr:full":"Avda San Agustin De Guadalix (de), 44 Colmenar Viejo Madrid 28770",
    "addr:postcode":"28770",
    "addr:street":"Avda San Agustin De Guadalix De",
    "iso:country":"ES",
    "sg:address":"Avda San Agustin De Guadalix (de), 44",
    "sg:city":"Colmenar Viejo",
    "sg:orig_category":"Inform\u00c1tica (estudios, Servicios, Asesor\u00cda, Formaci\u00d3n)",
    "sg:phone":"+34 918 45 79 66",
    "sg:postcode":"28770",
    "sg:province":"Madrid",
    "wof:name":"Sockets S.l.",
    "wof:placetype":"venue"
},
  "geometry": {"coordinates":[-3.7596240044,40.6613731384],"type":"Point"}
}