{
  "type": "Feature",
  "properties": {
    "addr:full":"Plaz Paz (de La), 2 Labastida \u00c1lava 01330",
    "addr:housenumber":"2",
    "addr:postcode":"01330",
    "addr:street":"Plaz;Labastida A\u0301Lava",
    "iso:country":"ES",
    "sg:address":"Plaz Paz (de La), 2",
    "sg:city":"Labastida",
    "sg:orig_category":"Ense\u00d1anza, Formaci\u00d3n Profesional: Aprendizaje",
    "sg:phone":"+34 945 33 18 18",
    "sg:postcode":"01330",
    "sg:province":"\u00c1lava",
    "wof:name":"Ayuntamiento De Labastida",
    "wof:placetype":"venue"
},
  "geometry": {"coordinates":[-2.7879400253,42.6053237915],"type":"Point"}
}