{
  "type": "Feature",
  "properties": {
    "addr:full":"Calle de Juan Manuel Duran Gonzalez, 22 Palmas De Gran Canaria Las Palmas 35007",
    "addr:housenumber":"22",
    "addr:postcode":"35007",
    "addr:street":"Calle De Juan Manuel Duran Gonzalez",
    "iso:country":"ES",
    "sg:address":"Calle de Juan Manuel Duran Gonzalez, 22",
    "sg:city":"Palmas De Gran Canaria",
    "sg:orig_category":"Confecci\u00d3n (fabricaci\u00d3n, Al Por Mayor)",
    "sg:phone":"+34 928 26 39 27",
    "sg:postcode":"35007",
    "sg:province":"Las Palmas",
    "wof:name":"Depositos Y Almacenes Numero-1 S.a.",
    "wof:placetype":"venue"
},
  "geometry": {"coordinates":[-15.4293661118,28.1354808807],"type":"Point"}
}