{
  "type": "Feature",
  "properties": {
    "addr:full":"Calle de San Isidro, 1 Granada Granada 18005",
    "addr:housenumber":"1",
    "addr:postcode":"18005",
    "addr:street":"Calle De San Isidro",
    "iso:country":"ES",
    "sg:address":"Calle de San Isidro, 1",
    "sg:city":"Granada",
    "sg:orig_category":"Reposter\u00cdas",
    "sg:phone":"+34 958 25 59 43",
    "sg:postcode":"18005",
    "sg:province":"Granada",
    "wof:name":"Vilchez Vilchez Miguel",
    "wof:placetype":"venue"
},
  "geometry": {"coordinates":[-3.5992889404,37.1713600159],"type":"Point"}
}