{
  "type": "Feature",
  "properties": {
    "addr:full":"Pase Mediterraneo (del), 74 Ventanicas-el Cantal Almer\u00eda 04638",
    "addr:postcode":"04638",
    "addr:street":"Ventanicas-El;Almeri\u0301A",
    "iso:country":"ES",
    "sg:address":"Pase Mediterraneo (del), 74",
    "sg:city":"Ventanicas-el Cantal",
    "sg:orig_category":"Promotores Constructores",
    "sg:phone":"+34 950 47 81 85",
    "sg:postcode":"04638",
    "sg:province":"Almer\u00eda",
    "wof:name":"Construcciones Mojacar S. L.",
    "wof:placetype":"venue"
},
  "geometry": {"coordinates":[-1.8406590223,37.122089386],"type":"Point"}
}