{
  "type": "Feature",
  "properties": {
    "iso:country":"ES",
    "sg:address":"Carr Ramon Y Cajal, 7",
    "sg:city":"Burjassot",
    "sg:orig_category":"Servicio De Salud",
    "sg:phone":"+34 963 90 16 68",
    "sg:postcode":"46100",
    "sg:province":"Valencia",
    "wof:name":"Benafont S.l.",
    "wof:placetype":"venue"
},
  "geometry": {"coordinates":[-0.4168030024,39.5112495422],"type":"Point"}
}