{
  "type": "Feature",
  "properties": {
    "iso:country":"ES",
    "sg:address":"Calle de Gerona, 21",
    "sg:city":"Alacant",
    "sg:orig_category":"Ropa Para Se\u00d1oras (al Por Menor)",
    "sg:phone":"+34 965 14 43 49",
    "sg:postcode":"03001",
    "sg:province":"Alicante",
    "wof:name":"Casc S.l.",
    "wof:placetype":"venue"
},
  "geometry": {"coordinates":[-0.4859560132,38.3442611694],"type":"Point"}
}