{
  "type": "Feature",
  "properties": {
    "addr:full":"Calle de Olivar, 22 Pedro\u00d1eras Cuenca 16660",
    "addr:housenumber":"22",
    "addr:postcode":"16660",
    "addr:street":"Calle De Olivar",
    "iso:country":"ES",
    "sg:address":"Calle de Olivar, 22",
    "sg:city":"Pedro\u00d1eras",
    "sg:orig_category":"Fotograf\u00cda Art\u00cdstica Y Retratos",
    "sg:phone":"+34 967 16 21 04",
    "sg:postcode":"16660",
    "sg:province":"Cuenca",
    "wof:name":"Neztimar S.l.",
    "wof:placetype":"venue"
},
  "geometry": {"coordinates":[-2.6743619442,39.4570503235],"type":"Point"}
}