{
  "type": "Feature",
  "properties": {
    "iso:country":"ES",
    "sg:address":"Calle de Morrones, 4",
    "sg:city":"Majadahonda",
    "sg:orig_category":"M\u00c9dicos: Estomatolog\u00cda",
    "sg:phone":"+34 916 38 12 45",
    "sg:postcode":"28220",
    "sg:province":"Madrid",
    "wof:name":"Rey Cimiano Fernando",
    "wof:placetype":"venue"
},
  "geometry": {"coordinates":[-3.8751049042,40.4719772339],"type":"Point"}
}