{
  "type": "Feature",
  "properties": {
    "iso:country":"ES",
    "sg:address":"Avda Apostoles, 3",
    "sg:city":"Madrid",
    "sg:orig_category":"Empresarios",
    "sg:phone":"+34 914 63 81 62",
    "sg:postcode":"28011",
    "sg:province":"Madrid",
    "wof:name":"Izquierdo Serrano Eugenio",
    "wof:placetype":"venue"
},
  "geometry": {"coordinates":[-3.7392940521,40.4065856934],"type":"Point"}
}