{
  "type": "Feature",
  "properties": {
    "addr:full":"Estd Castela, 595 Ponto La Coru\u00f1a 15570",
    "addr:housenumber":"595",
    "addr:postcode":"15570",
    "addr:street":"Castela;Corun\u0303A",
    "iso:country":"ES",
    "sg:address":"Estd Castela, 595",
    "sg:city":"Ponto",
    "sg:orig_category":"Contenedores (mercanc\u00cdas)",
    "sg:phone":"+34 981 39 70 94",
    "sg:postcode":"15570",
    "sg:province":"La Coru\u00f1a",
    "wof:name":"Candocia Villadoniga Francisco",
    "wof:placetype":"venue"
},
  "geometry": {"coordinates":[-8.1647539139,43.5165405273],"type":"Point"}
}