{
  "type": "Feature",
  "properties": {
    "iso:country":"ES",
    "sg:address":"Estd Castela, 595",
    "sg:city":"Ponto",
    "sg:orig_category":"Contenedores (mercanc\u00cdas)",
    "sg:phone":"+34 981 39 70 94",
    "sg:postcode":"15570",
    "sg:province":"La Coru\u00f1a",
    "wof:name":"Candocia Villadoniga Francisco",
    "wof:placetype":"venue"
},
  "geometry": {"coordinates":[-8.1647539139,43.5165405273],"type":"Point"}
}