{
  "type": "Feature",
  "properties": {
    "addr:full":"Ctra Barcelona, 10 Moia Barcelona 08180",
    "addr:housenumber":"10",
    "addr:postcode":"08180",
    "addr:street":"Ctra Barcelona",
    "iso:country":"ES",
    "sg:address":"Ctra Barcelona, 10",
    "sg:city":"Moia",
    "sg:orig_category":"Alimentaci\u00d3n General (al Por Mayor)",
    "sg:phone":"+34 938 30 03 70",
    "sg:postcode":"08180",
    "sg:province":"Barcelona",
    "wof:name":"Agropecuaria Del Moianes Sccl",
    "wof:placetype":"venue"
},
  "geometry": {"coordinates":[2.0985612869,41.8084487915],"type":"Point"}
}