{
  "type": "Feature",
  "properties": {
    "iso:country":"ES",
    "sg:address":"Ctra. Eivissa S. Antoni, Km. 0002,0",
    "sg:city":"Eivissa",
    "sg:orig_category":"Ense\u00d1anza Secundaria: Colegios Y Escuelas Privadas",
    "sg:phone":"+34 971 31 08 62",
    "sg:postcode":"07800",
    "sg:province":"Islas Baleares",
    "wof:name":"Instituto Nacional De Bachillerato Mixto 2 Blanca Dona",
    "wof:placetype":"venue"
},
  "geometry": {"coordinates":[1.4188899994,38.9061164856],"type":"Point"}
}