{
  "type": "Feature",
  "properties": {
    "iso:country":"ES",
    "sg:address":"Carr Magdalena Miro, 8",
    "sg:city":"Vilanova I La Geltru",
    "sg:orig_category":"Procuradores",
    "sg:phone":"+34 938 15 95 17",
    "sg:postcode":"08800",
    "sg:province":"Barcelona",
    "wof:name":"Mansilla Robert Maria Teresa",
    "wof:placetype":"venue"
},
  "geometry": {"coordinates":[1.7274019718,41.2204818726],"type":"Point"}
}