{
  "type": "Feature",
  "properties": {
    "iso:country":"ES",
    "sg:address":"Ctra Sevilla, 93",
    "sg:city":"Badajoz",
    "sg:orig_category":"Bricolaje, Herramientas (al Por Menor)",
    "sg:phone":"+34 924 24 44 77",
    "sg:postcode":"06009",
    "sg:province":"Badajoz",
    "wof:name":"Tech Dairy S.l.",
    "wof:placetype":"venue"
},
  "geometry": {"coordinates":[-6.9553489685,38.8686599731],"type":"Point"}
}