{
  "type": "Feature",
  "properties": {
    "addr:full":"Calle de San Claudio, 91 Madrid Madrid 28038",
    "addr:housenumber":"91",
    "addr:postcode":"madrid;28038",
    "addr:street":"Calle De San",
    "iso:country":"ES",
    "sg:address":"Calle de San Claudio, 91",
    "sg:city":"Madrid",
    "sg:orig_category":"Peluqueros: De Se\u00d1oras",
    "sg:phone":"+34 913 03 61 69",
    "sg:postcode":"28038",
    "sg:province":"Madrid",
    "wof:name":"Becerra Mu\u00f1oz Angela",
    "wof:placetype":"venue"
},
  "geometry": {"coordinates":[-3.6362159252,40.3889579773],"type":"Point"}
}