{
  "type": "Feature",
  "properties": {
    "iso:country":"ES",
    "sg:address":"Sotuelamos, S/n",
    "sg:city":"Sotuelamos",
    "sg:orig_category":"Agricultura: Abastecimiento Y Cosechado (negocio)",
    "sg:phone":"+34 967 58 50 05",
    "sg:postcode":"02613",
    "sg:province":"Albacete",
    "wof:name":"Coto Carrasca S.l.",
    "wof:placetype":"venue"
},
  "geometry": {"coordinates":[-2.5715808868,39.0418930054],"type":"Point"}
}