{
  "type": "Feature",
  "properties": {
    "addr:full":"Calle de Mayor, 53 Daroca Zaragoza 50360",
    "addr:housenumber":"53",
    "addr:postcode":"50360",
    "addr:street":"Calle De Mayor",
    "iso:country":"ES",
    "sg:address":"Calle de Mayor, 53",
    "sg:city":"Daroca",
    "sg:orig_category":"Inform\u00c1tica (estudios, Servicios, Asesor\u00cda, Formaci\u00d3n)",
    "sg:phone":"+34 976 80 11 14",
    "sg:postcode":"50360",
    "sg:province":"Zaragoza",
    "wof:name":"Mapfre Servicios De Informatica",
    "wof:placetype":"venue"
},
  "geometry": {"coordinates":[-1.4156709909,41.113899231],"type":"Point"}
}