{
  "type": "Feature",
  "properties": {
    "iso:country":"ES",
    "sg:address":"Calle de Sanchez Morate, S/n",
    "sg:city":"Getafe",
    "sg:orig_category":"Supermercados Y Hipermercados",
    "sg:phone":"+34 916 82 69 01",
    "sg:postcode":"28903",
    "sg:province":"Madrid",
    "sg:website":"www.caprabo.com",
    "wof:name":"Caprabo S.a.",
    "wof:placetype":"venue"
},
  "geometry": {"coordinates":[-3.7221341133,40.3160743713],"type":"Point"}
}