{
  "type": "Feature",
  "properties": {
    "iso:country":"ES",
    "sg:address":"Carrer de Barcelona, 1",
    "sg:city":"Manresa",
    "sg:orig_category":"Farmacias",
    "sg:phone":"+34 938 73 18 48",
    "sg:postcode":"08242",
    "sg:province":"Barcelona",
    "wof:name":"Martinez Dasveus Maria Antonia",
    "wof:placetype":"venue"
},
  "geometry": {"coordinates":[1.8225779533,41.7299880981],"type":"Point"}
}