{
  "type": "Feature",
  "properties": {
    "iso:country":"ES",
    "sg:address":"Calle de Rio Arlanza, S/n",
    "sg:city":"Alcala Henares",
    "sg:orig_category":"Florister\u00cdas",
    "sg:phone":"+34 918 89 18 46",
    "sg:postcode":"28803",
    "sg:province":"Madrid",
    "wof:name":"Artemisa Floristeria Jardineria S.l.",
    "wof:placetype":"venue"
},
  "geometry": {"coordinates":[-3.3689734936,40.4693107605],"type":"Point"}
}