{
  "type": "Feature",
  "properties": {
    "addr:full":"Calle de Amsterdam, S/n Benidorm Alicante 03500",
    "addr:housenumber":"s / n",
    "addr:postcode":"03500",
    "addr:street":"Calle De Amsterdam",
    "iso:country":"ES",
    "sg:address":"Calle de Amsterdam, S/n",
    "sg:city":"Benidorm",
    "sg:orig_category":"Controles De Edificaci\u00d3n (construcci\u00d3n, Seguridad)",
    "sg:phone":"+34 965 85 41 33",
    "sg:postcode":"03500",
    "sg:province":"Alicante",
    "wof:name":"Comunidad De Propietarios Edificio Don Paco",
    "wof:placetype":"venue"
},
  "geometry": {"coordinates":[-0.1054830998,38.5351219177],"type":"Point"}
}