{
  "type": "Feature",
  "properties": {
    "addr:full":"Calle de Barahona, 13 Le\u00f3n Le\u00f3n 24003",
    "addr:housenumber":"13",
    "addr:postcode":"24003",
    "addr:street":"Calle De Barahona;Leo\u0301N",
    "iso:country":"ES",
    "sg:address":"Calle de Barahona, 13",
    "sg:city":"Le\u00f3n",
    "sg:orig_category":"Asesor\u00cda Fiscal Y Jur\u00cddica",
    "sg:phone":"+34 987 25 18 25",
    "sg:postcode":"24003",
    "sg:province":"Le\u00f3n",
    "wof:name":"Villasol Leon S.l.",
    "wof:placetype":"venue"
},
  "geometry": {"coordinates":[-5.5667629242,42.5930404663],"type":"Point"}
}