{
  "type": "Feature",
  "properties": {
    "addr:full":"C/ Jose Santos Orts, 4 Elche Alicante 03204",
    "addr:housenumber":"4",
    "addr:postcode":"03204",
    "addr:street":"C / Jose Santos Orts",
    "iso:country":"ES",
    "sg:address":"C/ Jose Santos Orts, 4",
    "sg:city":"Elche",
    "sg:orig_category":"Dibujantes (diversos)",
    "sg:phone":"+34 966 67 55 70",
    "sg:postcode":"03204",
    "sg:province":"Alicante",
    "wof:name":"Rico Sogorb Alfredo",
    "wof:placetype":"venue"
},
  "geometry": {"coordinates":[-0.703576982,38.2615127563],"type":"Point"}
}