{
  "type": "Feature",
  "properties": {
    "iso:country":"ES",
    "sg:address":"Camino Picamijo, 2",
    "sg:city":"Navas Oro",
    "sg:orig_category":"Cr\u00cda De Animales",
    "sg:phone":"+34 921 59 15 45",
    "sg:postcode":"40470",
    "sg:province":"Segovia",
    "wof:name":"Comercializacion De Ganado Porcino Scdad.coop.",
    "wof:placetype":"venue"
},
  "geometry": {"coordinates":[-4.4386892319,41.1965408325],"type":"Point"}
}