{
  "type": "Feature",
  "properties": {
    "iso:country":"ES",
    "sg:address":"Calle de Mirlo, 5",
    "sg:city":"Madrid",
    "sg:orig_category":"Caf\u00c9s, Bares, Cervecer\u00cdas",
    "sg:phone":"+34 917 11 13 50",
    "sg:postcode":"28024",
    "sg:province":"Madrid",
    "wof:name":"Garcia Orgaz Francisco",
    "wof:placetype":"venue"
},
  "geometry": {"coordinates":[-3.7699439526,40.3989944458],"type":"Point"}
}