{
  "type": "Feature",
  "properties": {
    "iso:country":"ES",
    "sg:address":"Avda Enrique Mederos, 31",
    "sg:city":"Llanos De Aridane",
    "sg:orig_category":"Cristaler\u00cdas",
    "sg:phone":"+34 922 46 23 09",
    "sg:postcode":"38760",
    "sg:province":"Santa Cruz De Tenerife",
    "wof:name":"Garcia Sanchez Fermin",
    "wof:placetype":"venue"
},
  "geometry": {"coordinates":[-17.9085597992,28.6563796997],"type":"Point"}
}