{
  "type": "Feature",
  "properties": {
    "iso:country":"ES",
    "sg:address":"Calle de Fernandez Ruano, 15",
    "sg:city":"Cordoba",
    "sg:orig_category":"Agencias Y Asesores De Publicidad",
    "sg:phone":"+34 957 76 07 30",
    "sg:postcode":"14003",
    "sg:province":"C\u00f3rdoba",
    "sg:website":"www.zum.es",
    "wof:name":"Zum Creativos S.l.",
    "wof:placetype":"venue"
},
  "geometry": {"coordinates":[-4.7833881378,37.8809890747],"type":"Point"}
}