{
  "type": "Feature",
  "properties": {
    "addr:full":"Avda Madariaga, 31 Bilbao Vizcaya 48014",
    "addr:housenumber":"31",
    "addr:postcode":"48014",
    "addr:street":"Avda Madariaga",
    "iso:country":"ES",
    "sg:address":"Avda Madariaga, 31",
    "sg:city":"Bilbao",
    "sg:orig_category":"Molduras, Junquillos, Listones Y Molduras Perforadas",
    "sg:phone":"+34 944 75 39 40",
    "sg:postcode":"48014",
    "sg:province":"Vizcaya",
    "wof:name":"Carmelo Carral Tellitu",
    "wof:placetype":"venue"
},
  "geometry": {"coordinates":[-2.9487628937,43.2708778381],"type":"Point"}
}