{
  "type": "Feature",
  "properties": {
    "iso:country":"ES",
    "sg:address":"Calle de Arturo Soria, 201",
    "sg:city":"Madrid",
    "sg:orig_category":"Embajadas, Consulados Y Otras Representaciones Diplom\u00c1ticas",
    "sg:phone":"+34 915 10 28 67",
    "sg:postcode":"28043",
    "sg:province":"Madrid",
    "wof:name":"Embajada De Vietnam",
    "wof:placetype":"venue"
},
  "geometry": {"coordinates":[-3.6608343124,40.4596481323],"type":"Point"}
}