{
  "type": "Feature",
  "properties": {
    "iso:country":"ES",
    "sg:address":"Calle de Fernando Guanarteme, 32",
    "sg:city":"Palmas De Gran Canaria",
    "sg:orig_category":"Albergues",
    "sg:phone":"+34 928 27 91 37",
    "sg:postcode":"35010",
    "sg:province":"Las Palmas",
    "wof:name":"Sanchez Galdeano S.l.",
    "wof:placetype":"venue"
},
  "geometry": {"coordinates":[-15.4380645752,28.1345443726],"type":"Point"}
}