{
  "type": "Feature",
  "properties": {
    "iso:country":"ES",
    "sg:address":"Calle de Alcalde Luis Treillard, 9",
    "sg:city":"Salinas",
    "sg:orig_category":"Supermercados Y Hipermercados",
    "sg:phone":"+34 985 50 25 00",
    "sg:postcode":"33405",
    "sg:province":"Asturias",
    "wof:name":"Alimerka S.a.",
    "wof:placetype":"venue"
},
  "geometry": {"coordinates":[-5.9633669853,43.5739097595],"type":"Point"}
}