{
  "type": "Feature",
  "properties": {
    "addr:full":"Calle de Ebro, 14 Albacete Albacete 02006",
    "addr:housenumber":"14",
    "addr:postcode":"02006",
    "addr:street":"Calle De Ebro",
    "iso:country":"ES",
    "sg:address":"Calle de Ebro, 14",
    "sg:city":"Albacete",
    "sg:orig_category":"Asociaciones Humanitarias, De Cooperaci\u00d3n, De Acci\u00d3n Social",
    "sg:phone":"+34 967 50 27 46",
    "sg:postcode":"02006",
    "sg:province":"Albacete",
    "wof:name":"Asociacion De Familiares De Enfermos De Alzheimer Y Otras Demencias Seniles De Albacete Y Provincia",
    "wof:placetype":"venue"
},
  "geometry": {"coordinates":[-1.8724677563,39.0007514954],"type":"Point"}
}