{
  "type": "Feature",
  "properties": {
    "iso:country":"ES",
    "sg:address":"Ibabe Pol Ind, 18",
    "sg:city":"Lazkao",
    "sg:orig_category":"Importaci\u00d3n",
    "sg:phone":"+34 943 88 25 82",
    "sg:postcode":"20210",
    "sg:province":"Guip\u00f9zcoa",
    "wof:name":"Martex Importaciones S.l.",
    "wof:placetype":"venue"
},
  "geometry": {"coordinates":[-2.1873590946,43.0314903259],"type":"Point"}
}