{
  "type": "Feature",
  "properties": {
    "addr:full":"Calle de Rua, 9 Puebla Sanabria Zamora 49300",
    "addr:postcode":"49300",
    "addr:street":"Calle De Rua 9 Puebla Sanabria Zamora",
    "iso:country":"ES",
    "sg:address":"Calle de Rua, 9",
    "sg:city":"Puebla Sanabria",
    "sg:orig_category":"Ense\u00d1anza, Formaci\u00d3n Profesional: Aprendizaje",
    "sg:phone":"+34 980 62 01 16",
    "sg:postcode":"49300",
    "sg:province":"Zamora",
    "wof:name":"Administracion De Justicia",
    "wof:placetype":"venue"
},
  "geometry": {"coordinates":[-6.633638382,42.0539741516],"type":"Point"}
}