{
  "type": "Feature",
  "properties": {
    "iso:country":"ES",
    "sg:address":"Plaz Luceros (los), 5",
    "sg:city":"Alacant",
    "sg:orig_category":"Fiesta: Art\u00cdculos De (al Por Menor)",
    "sg:phone":"+34 965 20 98 08",
    "sg:postcode":"03003",
    "sg:province":"Alicante",
    "wof:name":"Uriarte Estrellas Pedro Angel",
    "wof:placetype":"venue"
},
  "geometry": {"coordinates":[-0.4804739952,38.3440856934],"type":"Point"}
}