{
  "type": "Feature",
  "properties": {
    "addr:full":"Ctra Ontinyent (d'), 18 Albaida Valencia 46860",
    "addr:housenumber":"18",
    "addr:postcode":"46860",
    "addr:street":"Ctra Ontinyent D '",
    "iso:country":"ES",
    "sg:address":"Ctra Ontinyent (d'), 18",
    "sg:city":"Albaida",
    "sg:orig_category":"Mec\u00c1nico Del Autom\u00d3vil",
    "sg:phone":"+34 962 90 04 87",
    "sg:postcode":"46860",
    "sg:province":"Valencia",
    "wof:name":"Talleres Autodasa S.l.",
    "wof:placetype":"venue"
},
  "geometry": {"coordinates":[-0.5192559958,38.8373298645],"type":"Point"}
}