{
  "type": "Feature",
  "properties": {
    "addr:full":"Avda Primero De Mayo, 141 Palmar  O Lugar De Don Juan Murcia 30120",
    "addr:housenumber":"141",
    "addr:postcode":"30120",
    "addr:street":"Avda Primero De Mayo;Lugar",
    "iso:country":"ES",
    "sg:address":"Avda Primero De Mayo, 141",
    "sg:city":"Palmar  O Lugar De Don Juan",
    "sg:orig_category":"Farmacias",
    "sg:phone":"+34 968 88 20 55",
    "sg:postcode":"30120",
    "sg:province":"Murcia",
    "wof:name":"Garcia Legaz Encarnacion",
    "wof:placetype":"venue"
},
  "geometry": {"coordinates":[-1.1611225605,37.9357414246],"type":"Point"}
}