{
  "type": "Feature",
  "properties": {
    "addr:full":"Av Cortes Valencianas, 7 Albal Valencia 46470",
    "addr:housenumber":"7",
    "addr:postcode":"46470",
    "addr:street":"Av Cortes Valencianas",
    "iso:country":"ES",
    "sg:address":"Av Cortes Valencianas, 7",
    "sg:city":"Albal",
    "sg:orig_category":"Herboristas (al Por Menor)",
    "sg:phone":"+34 961 26 57 82",
    "sg:postcode":"46470",
    "sg:province":"Valencia",
    "wof:name":"Garcia Sanchez Veronica",
    "wof:placetype":"venue"
},
  "geometry": {"coordinates":[-0.4123370051,39.3970794678],"type":"Point"}
}