{
  "type": "Feature",
  "properties": {
    "addr:full":"Carrer de Major, 17 Gava Barcelona 08850",
    "addr:housenumber":"17",
    "addr:postcode":"08850",
    "addr:street":"Carrer De Major",
    "iso:country":"ES",
    "sg:address":"Carrer de Major, 17",
    "sg:city":"Gava",
    "sg:orig_category":"Cl\u00cdnicas Dentales",
    "sg:phone":"+34 936 62 91 04",
    "sg:postcode":"08850",
    "sg:province":"Barcelona",
    "wof:name":"Clinica Estomatologica S. Cv.",
    "wof:placetype":"venue"
},
  "geometry": {"coordinates":[2.0051789284,41.3041038513],"type":"Point"}
}