{
  "type": "Feature",
  "properties": {
    "addr:full":"La Carrasca, 2 Playa Valencia 46530",
    "addr:housenumber":"2",
    "addr:postcode":"46530",
    "addr:street":"La Carrasca;Valencia",
    "iso:country":"ES",
    "sg:address":"La Carrasca, 2",
    "sg:city":"Playa",
    "sg:orig_category":"Farmacias",
    "sg:phone":"+34 961 46 48 45",
    "sg:postcode":"46530",
    "sg:province":"Valencia",
    "wof:name":"Molins Clemente Consuelo",
    "wof:placetype":"venue"
},
  "geometry": {"coordinates":[-0.3008790016,39.6156044006],"type":"Point"}
}