{
  "type": "Feature",
  "properties": {
    "addr:full":"Plaz San Roque, 17 Torrent Valencia 46900",
    "addr:housenumber":"17",
    "addr:postcode":"46900",
    "addr:street":"Plaz San Roque;Valencia",
    "iso:country":"ES",
    "sg:address":"Plaz San Roque, 17",
    "sg:city":"Torrent",
    "sg:orig_category":"Molduras, Junquillos, Listones Y Molduras Perforadas",
    "sg:phone":"+34 961 56 13 57",
    "sg:postcode":"46900",
    "sg:province":"Valencia",
    "wof:name":"Asociacion Cultural Casino Torrent",
    "wof:placetype":"venue"
},
  "geometry": {"coordinates":[-0.4630501866,39.4388694763],"type":"Point"}
}