{
  "type": "Feature",
  "properties": {
    "iso:country":"ES",
    "sg:address":"Carrer de Nou De La Rambla, 16",
    "sg:city":"Barcelona",
    "sg:orig_category":"Supermercados Y Hipermercados",
    "sg:phone":"+34 933 02 03 88",
    "sg:postcode":"08001",
    "sg:province":"Barcelona",
    "wof:name":"Arlansin Bcn S.l.",
    "wof:placetype":"venue"
},
  "geometry": {"coordinates":[2.1739132404,41.3787879944],"type":"Point"}
}