{
  "type": "Feature",
  "properties": {
    "iso:country":"ES",
    "sg:address":"Carrer de Maurici Serrahima, 12",
    "sg:city":"Barcelona",
    "sg:orig_category":"Asilos De Ancianos. Centros Privados",
    "sg:phone":"+34 932 37 71 78",
    "sg:postcode":"08012",
    "sg:province":"Barcelona",
    "wof:name":"Residencia Lesseps S.l.",
    "wof:placetype":"venue"
},
  "geometry": {"coordinates":[2.1518828869,41.4052734375],"type":"Point"}
}