{
  "type": "Feature",
  "properties": {
    "addr:full":"Calle de Maestranza, S/n Malaga M\u00e1laga 29016",
    "addr:housenumber":"s / n",
    "addr:postcode":"29016",
    "addr:street":"Calle De Maestranza;Ma\u0301Laga",
    "iso:country":"ES",
    "sg:address":"Calle de Maestranza, S/n",
    "sg:city":"Malaga",
    "sg:orig_category":"Cajas De Ahorro",
    "sg:phone":"+34 952 12 13 43",
    "sg:postcode":"29016",
    "sg:province":"M\u00e1laga",
    "sg:website":"www.cajasur.es",
    "wof:name":"Caja De Ahorros Y Monte De Piedad De Cordoba",
    "wof:placetype":"venue"
},
  "geometry": {"coordinates":[-4.4116740227,36.7199249268],"type":"Point"}
}