{
  "type": "Feature",
  "properties": {
    "addr:full":"Pl Amadores, S/n Puerto Rico Las Palmas 35130",
    "addr:housenumber":"s / n",
    "addr:postcode":"35130",
    "addr:street":"Pl Amadores;Rico",
    "iso:country":"ES",
    "sg:address":"Pl Amadores, S/n",
    "sg:city":"Puerto Rico",
    "sg:orig_category":"Molduras, Junquillos, Listones Y Molduras Perforadas",
    "sg:phone":"+34 928 56 16 24",
    "sg:postcode":"35130",
    "sg:province":"Las Palmas",
    "wof:name":"Aubrey  Bryan Anthony",
    "wof:placetype":"venue"
},
  "geometry": {"coordinates":[-15.7144145966,27.7864627838],"type":"Point"}
}