{
  "type": "Feature",
  "properties": {
    "addr:full":"Calle de Ibiza, 12 Benidorm Alicante 03500",
    "addr:housenumber":"12",
    "addr:postcode":"03500",
    "addr:street":"Calle De Ibiza",
    "iso:country":"ES",
    "sg:address":"Calle de Ibiza, 12",
    "sg:city":"Benidorm",
    "sg:orig_category":"Zapatos (al Por Menor)",
    "sg:phone":"+34 965 86 58 53",
    "sg:postcode":"03500",
    "sg:province":"Alicante",
    "wof:name":"Dong  Yu Ping",
    "wof:placetype":"venue"
},
  "geometry": {"coordinates":[-0.1167119965,38.5395584106],"type":"Point"}
}