{
  "type": "Feature",
  "properties": {
    "addr:full":"Calle de Huesca, 33 Madrid Madrid 28020",
    "addr:housenumber":"33",
    "addr:postcode":"madrid;28020",
    "addr:street":"Calle De Huesca",
    "iso:country":"ES",
    "sg:address":"Calle de Huesca, 33",
    "sg:city":"Madrid",
    "sg:orig_category":"Comunidades Religiosas",
    "sg:phone":"+34 915 70 83 31",
    "sg:postcode":"28020",
    "sg:province":"Madrid",
    "wof:name":"Padres Agustinos Recoletos De San Jose",
    "wof:placetype":"venue"
},
  "geometry": {"coordinates":[-3.6955959797,40.4580039978],"type":"Point"}
}