{
  "type": "Feature",
  "properties": {
    "addr:full":"Rua Rulla, 3 Bolo Ourense 32373",
    "addr:housenumber":"3",
    "addr:postcode":"32373",
    "addr:street":"Rua Rulla",
    "iso:country":"ES",
    "sg:address":"Rua Rulla, 3",
    "sg:city":"Bolo",
    "sg:classifiers":[
        {
            "category":"Taxi",
            "type":"Transportation"
        }
    ],
    "sg:phone":"+34 988 32 30 28",
    "sg:postcode":"32373",
    "sg:province":"Ourense",
    "wof:name":"Fari\u00f1as Alvarez Rosalia",
    "wof:placetype":"venue"
},
  "geometry": {"coordinates":[-7.0953450203,42.3079299927],"type":"Point"}
}