{
  "type": "Feature",
  "properties": {
    "addr:full":"Avda Retamas (las), 55 Alcorcon Madrid 28922",
    "addr:housenumber":"55",
    "addr:postcode":"28922",
    "addr:street":"Avda Retamas Las",
    "iso:country":"ES",
    "sg:address":"Avda Retamas (las), 55",
    "sg:city":"Alcorcon",
    "sg:orig_category":"Guarder\u00cdas",
    "sg:phone":"+34 916 41 12 46",
    "sg:postcode":"28922",
    "sg:province":"Madrid",
    "wof:name":"Centro Infantil Alcorcon 1 S.l.u.",
    "wof:placetype":"venue"
},
  "geometry": {"coordinates":[-3.8294630051,40.3377838135],"type":"Point"}
}