{
  "type": "Feature",
  "properties": {
    "iso:country":"ES",
    "sg:address":"Calle de Uncastillo, 4",
    "sg:city":"Zaragoza",
    "sg:orig_category":"Frutas, Legumbres Frescas Y Tempranas (al Por Menor)",
    "sg:phone":"+34 976 49 18 18",
    "sg:postcode":"50008",
    "sg:province":"Zaragoza",
    "wof:name":"Andaluz Lazaro Gerardo",
    "wof:placetype":"venue"
},
  "geometry": {"coordinates":[-0.8787077069,41.6418762207],"type":"Point"}
}