{
  "type": "Feature",
  "properties": {
    "iso:country":"ES",
    "sg:address":"Calle de Pedro Arias, 81",
    "sg:city":"Socuellamos",
    "sg:orig_category":"Productores Recolectores, Venta Directa De Vinos",
    "sg:phone":"+34 926 53 11 87",
    "sg:postcode":"13630",
    "sg:province":"Ciudad Real",
    "wof:name":"Bodegas La Torre S.l.",
    "wof:placetype":"venue"
},
  "geometry": {"coordinates":[-2.7938790321,39.2906417847],"type":"Point"}
}