{
  "type": "Feature",
  "properties": {
    "iso:country":"ES",
    "sg:address":"Calle de Fuentevieja, 10",
    "sg:city":"Lucena",
    "sg:orig_category":"Persianas Interiores, Exteriores",
    "sg:phone":"+34 957 51 45 51",
    "sg:postcode":"14900",
    "sg:province":"C\u00f3rdoba",
    "wof:name":"Alamillos Gallego Fernando",
    "wof:placetype":"venue"
},
  "geometry": {"coordinates":[-4.4815354347,37.4103469849],"type":"Point"}
}