{
  "type": "Feature",
  "properties": {
    "iso:country":"ES",
    "sg:address":"Carrer de Paris, 62",
    "sg:city":"Sabadell",
    "sg:orig_category":"Charcuter\u00cdas (al Por Mayor)",
    "sg:phone":"+34 937 12 50 71",
    "sg:postcode":"08204",
    "sg:province":"Barcelona",
    "wof:name":"Representaciones Alimenticias Del Valles,s.l.",
    "wof:placetype":"venue"
},
  "geometry": {"coordinates":[2.1226649284,41.5285758972],"type":"Point"}
}