{
  "type": "Feature",
  "properties": {
    "iso:country":"ES",
    "sg:address":"Avda Oceano Indico, S/n",
    "sg:city":"Barrosa",
    "sg:orig_category":"Bisuteros (fabricaci\u00d3n, Al Por Mayor)",
    "sg:phone":"+34 956 49 48 36",
    "sg:postcode":"11130",
    "sg:province":"C\u00e1diz",
    "wof:name":"Massa Baizan Joaquina",
    "wof:placetype":"venue"
},
  "geometry": {"coordinates":[-6.1447038651,36.4212188721],"type":"Point"}
}