{
  "type": "Feature",
  "properties": {
    "iso:country":"ES",
    "sg:address":"Avda Hermanos Felgueroso, 16",
    "sg:city":"Gijon",
    "sg:orig_category":"Comercio, Reparaci\u00d3n De Bicicletas, De Motocicletas, De Accesorios",
    "sg:phone":"+34 985 38 27 92",
    "sg:postcode":"33205",
    "sg:province":"Asturias",
    "wof:name":"Garaje Hevia Sucesores De Jesus Hevia S.c.",
    "wof:placetype":"venue"
},
  "geometry": {"coordinates":[-5.6592655182,43.5361099243],"type":"Point"}
}