{
  "type": "Feature",
  "properties": {
    "iso:country":"ES",
    "sg:address":"Avda Guadalajara (de), 21",
    "sg:city":"Azuqueca Henares",
    "sg:orig_category":"Pintura, Barniz, Productos Asimilables (fabricaci\u00d3n, Al Por Mayor)",
    "sg:phone":"+34 949 26 69 35",
    "sg:postcode":"19200",
    "sg:province":"Guadalajara",
    "wof:name":"Pinturas T.esteban S.l.",
    "wof:placetype":"venue"
},
  "geometry": {"coordinates":[-3.26521492,40.5641593933],"type":"Point"}
}