{
  "type": "Feature",
  "properties": {
    "addr:full":"Calle de Tomas Borras, 15 Madrid Madrid 28045",
    "addr:housenumber":"15",
    "addr:postcode":"madrid;28045",
    "addr:street":"Calle De Tomas Borras",
    "iso:country":"ES",
    "sg:address":"Calle de Tomas Borras, 15",
    "sg:city":"Madrid",
    "sg:orig_category":"Centros Comerciales Y Grandes Tiendas",
    "sg:phone":"+34 914 73 72 88",
    "sg:postcode":"28045",
    "sg:province":"Madrid",
    "wof:name":"Dai Shuzhi",
    "wof:placetype":"venue"
},
  "geometry": {"coordinates":[-3.6977789402,40.3949203491],"type":"Point"}
}