{
  "type": "Feature",
  "properties": {
    "iso:country":"ES",
    "sg:address":"Calle de Mencey Ventor, 13",
    "sg:city":"Santa Cruz De Tenerife",
    "sg:orig_category":"Alimentaci\u00d3n General (al Por Menor)",
    "sg:phone":"+34 922 21 44 33",
    "sg:postcode":"38008",
    "sg:province":"Santa Cruz De Tenerife",
    "wof:name":"Gonzalez Gonzalez Jose Manuel",
    "wof:placetype":"venue"
},
  "geometry": {"coordinates":[-16.2719402313,28.4688682556],"type":"Point"}
}