{
  "type": "Feature",
  "properties": {
    "iso:country":"ES",
    "sg:address":"Urb Terra Roja, 39",
    "sg:city":"Borriol",
    "sg:orig_category":"Electricidad: Instaladores",
    "sg:phone":"+34 964 32 21 73",
    "sg:postcode":"12190",
    "sg:province":"Castell\u00f3n",
    "sg:website":"www.cyc-castellon.com",
    "wof:name":"Cumba Cabanes Lorenzo",
    "wof:placetype":"venue"
},
  "geometry": {"coordinates":[-0.070262,40.0408325195],"type":"Point"}
}