{
  "type": "Feature",
  "properties": {
    "addr:full":"Rua Doutor Gasalla, 3 Lugo Lugo 27004",
    "addr:housenumber":"3",
    "addr:postcode":"27004",
    "addr:street":"Rua Doutor Gasalla",
    "iso:country":"ES",
    "sg:address":"Rua Doutor Gasalla, 3",
    "sg:city":"Lugo",
    "sg:orig_category":"Ropa Para Beb\u00c9s Y Ni\u00d1os (confecci\u00d3n, Al Por Mayor)",
    "sg:phone":"+34 982 21 78 72",
    "sg:postcode":"27004",
    "sg:province":"Lugo",
    "wof:name":"Iravedra Fernandez Anibal",
    "wof:placetype":"venue"
},
  "geometry": {"coordinates":[-7.5627770424,43.0131263733],"type":"Point"}
}