{
  "type": "Feature",
  "properties": {
    "addr:full":"Calle de Alberdi, 57 Madrid Madrid 28029",
    "addr:housenumber":"57",
    "addr:postcode":"madrid;28029",
    "addr:street":"Calle De Alberdi",
    "iso:country":"ES",
    "sg:address":"Calle de Alberdi, 57",
    "sg:city":"Madrid",
    "sg:orig_category":"Ebanister\u00cda",
    "sg:phone":"+34 917 33 31 44",
    "sg:postcode":"28029",
    "sg:province":"Madrid",
    "wof:name":"Bernardos Arevalo Alfredo",
    "wof:placetype":"venue"
},
  "geometry": {"coordinates":[-3.7067921162,40.4690818787],"type":"Point"}
}