{
  "type": "Feature",
  "properties": {
    "iso:country":"ES",
    "sg:address":"Calle de Vereda De Chapatales, 13",
    "sg:city":"San Jose Rinconada",
    "sg:orig_category":"Peluquer\u00cdas, Peluquer\u00cda Mixta",
    "sg:phone":"+34 954 79 04 91",
    "sg:postcode":"41300",
    "sg:province":"Sevilla",
    "wof:name":"Adame Reyes Maria Del Carmen",
    "wof:placetype":"venue"
},
  "geometry": {"coordinates":[-5.9369931221,37.4878692627],"type":"Point"}
}