{
  "type": "Feature",
  "properties": {
    "addr:full":"Carrer de Asturies, 15 Barcelona Barcelona 08012",
    "addr:housenumber":"15",
    "addr:postcode":"08012",
    "addr:street":"Carrer De Asturies",
    "iso:country":"ES",
    "sg:address":"Carrer de Asturies, 15",
    "sg:city":"Barcelona",
    "sg:orig_category":"\u00d3ptica: Instrumentos (fabricaci\u00d3n)",
    "sg:phone":"+34 932 18 30 67",
    "sg:postcode":"08012",
    "sg:province":"Barcelona",
    "wof:name":"Vision Plus S.l.",
    "wof:placetype":"venue"
},
  "geometry": {"coordinates":[2.1534583569,41.4028816223],"type":"Point"}
}