{
  "type": "Feature",
  "properties": {
    "addr:full":"Calle de Doctor Fleming, 1 Sestao Vizcaya 48910",
    "addr:housenumber":"1",
    "addr:postcode":"48910",
    "addr:street":"Calle De Doctor Fleming",
    "iso:country":"ES",
    "sg:address":"Calle de Doctor Fleming, 1",
    "sg:city":"Sestao",
    "sg:orig_category":"Estancos",
    "sg:phone":"+34 944 96 22 23",
    "sg:postcode":"48910",
    "sg:province":"Vizcaya",
    "wof:name":"Gomez Ruiz Natividad",
    "wof:placetype":"venue"
},
  "geometry": {"coordinates":[-3.0066404343,43.3112030029],"type":"Point"}
}