{
  "type": "Feature",
  "properties": {
    "addr:full":"Calle de Bolonia, 4 Zaragoza Zaragoza 50008",
    "addr:housenumber":"4",
    "addr:postcode":"50008",
    "addr:street":"Calle De Bolonia",
    "iso:country":"ES",
    "sg:address":"Calle de Bolonia, 4",
    "sg:city":"Zaragoza",
    "sg:orig_category":"Psic\u00d3logos",
    "sg:phone":"+34 976 21 08 31",
    "sg:postcode":"50008",
    "sg:province":"Zaragoza",
    "wof:name":"Crespo Rospir Jose",
    "wof:placetype":"venue"
},
  "geometry": {"coordinates":[-0.8857080936,41.6431694031],"type":"Point"}
}