{
  "type": "Feature",
  "properties": {
    "iso:country":"ES",
    "sg:address":"Plaz Espa\u00d1a, 1",
    "sg:city":"Baltanas",
    "sg:orig_category":"Pr\u00c9stamos Personales E Hipotecarios",
    "sg:phone":"+34 979 79 00 94",
    "sg:postcode":"34240",
    "sg:province":"Palencia",
    "wof:name":"Gonzalez Hernandez Cristina",
    "wof:placetype":"venue"
},
  "geometry": {"coordinates":[-4.2128338814,41.9417037964],"type":"Point"}
}