{
  "type": "Feature",
  "properties": {
    "iso:country":"ES",
    "sg:address":"Carrer de Vilamari, 78",
    "sg:city":"Barcelona",
    "sg:orig_category":"Asesor\u00cda Sobre Comunicaci\u00d3n De Empresas",
    "sg:phone":"+34 934 23 48 46",
    "sg:postcode":"08015",
    "sg:province":"Barcelona",
    "wof:name":"Accions En Patents I Marques Padulles S.l.",
    "wof:placetype":"venue"
},
  "geometry": {"coordinates":[2.1494951248,41.3787956238],"type":"Point"}
}