{
  "type": "Feature",
  "properties": {
    "iso:country":"ES",
    "sg:address":"Rua Robustiano Perez Del Rio, S/n",
    "sg:city":"Boiro",
    "sg:orig_category":"Quincaller\u00cda (al Por Menor)",
    "sg:phone":"+34 981 84 62 06",
    "sg:postcode":"15930",
    "sg:province":"La Coru\u00f1a",
    "wof:name":"Ferreteria M.casais S.l.",
    "wof:placetype":"venue"
},
  "geometry": {"coordinates":[-8.8829441071,42.6467895508],"type":"Point"}
}