{
  "type": "Feature",
  "properties": {
    "addr:full":"Calle de Antonio Machado, 5 Fuente Maestre Badajoz 06360",
    "addr:housenumber":"5",
    "addr:postcode":"06360",
    "addr:street":"Calle De Antonio Machado",
    "iso:country":"ES",
    "sg:address":"Calle de Antonio Machado, 5",
    "sg:city":"Fuente Maestre",
    "sg:orig_category":"Farmacias",
    "sg:phone":"+34 924 53 00 55",
    "sg:postcode":"06360",
    "sg:province":"Badajoz",
    "wof:name":"Cassillas Ovando Maria Estrella",
    "wof:placetype":"venue"
},
  "geometry": {"coordinates":[-6.4860019684,38.6504325867],"type":"Point"}
}