{
  "type": "Feature",
  "properties": {
    "iso:country":"ES",
    "sg:address":"Carr Santanyi, 37",
    "sg:city":"Felanitx",
    "sg:orig_category":"Contenedores Para Transporte De Mercanc\u00cdas",
    "sg:phone":"+34 971 58 05 98",
    "sg:postcode":"07200",
    "sg:province":"Islas Baleares",
    "wof:name":"Trans-forteza S.l.",
    "wof:placetype":"venue"
},
  "geometry": {"coordinates":[3.1470379829,39.4633369446],"type":"Point"}
}