{
  "type": "Feature",
  "properties": {
    "iso:country":"ES",
    "sg:address":"Plaz Mercado, 6",
    "sg:city":"Valencia",
    "sg:orig_category":"Cajas Para Embalar",
    "sg:phone":"+34 963 92 42 10",
    "sg:postcode":"46001",
    "sg:province":"Valencia",
    "sg:website":"www.ruralvia.com",
    "wof:name":"Caja Rural Del Mediterraneo Ruralcaja S Coop De Credito",
    "wof:placetype":"venue"
},
  "geometry": {"coordinates":[-0.378223002,39.4735717773],"type":"Point"}
}