{
  "type": "Feature",
  "properties": {
    "addr:full":"Avda Menendez Pidal, 15 Valencia Valencia 46009",
    "addr:housenumber":"15",
    "addr:postcode":"46009",
    "addr:street":"Avda Menendez Pidal",
    "iso:country":"ES",
    "sg:address":"Avda Menendez Pidal, 15",
    "sg:city":"Valencia",
    "sg:orig_category":"Peluqueros: De Se\u00d1oras",
    "sg:phone":"+34 963 49 57 63",
    "sg:postcode":"46009",
    "sg:province":"Valencia",
    "wof:name":"Marpel Moda Y Peluqueria S.l.",
    "wof:placetype":"venue"
},
  "geometry": {"coordinates":[-0.3908750117,39.4791374207],"type":"Point"}
}