{
  "type": "Feature",
  "properties": {
    "addr:full":"Elkano Kalea, 12 Hernani Guip\u00f9zcoa 20120",
    "addr:housenumber":"12",
    "addr:postcode":"20120",
    "addr:street":"Elkano Kalea;Guipu\u0300Zcoa",
    "iso:country":"ES",
    "sg:address":"Elkano Kalea, 12",
    "sg:city":"Hernani",
    "sg:orig_category":"Reposter\u00cdas",
    "sg:phone":"+34 943 55 31 42",
    "sg:postcode":"20120",
    "sg:province":"Guip\u00f9zcoa",
    "wof:name":"Koro Egilegor Etxaiz",
    "wof:placetype":"venue"
},
  "geometry": {"coordinates":[-1.9770679474,43.2666244507],"type":"Point"}
}