{
  "type": "Feature",
  "properties": {
    "iso:country":"ES",
    "sg:address":"Carrer de Torrent Tortuguer, 52",
    "sg:city":"Barbera Valles",
    "sg:orig_category":"Empresas De Portes Y Mensajer\u00cda",
    "sg:phone":"+34 937 29 64 00",
    "sg:postcode":"08210",
    "sg:province":"Barcelona",
    "wof:name":"Intercity Pont S.l.",
    "wof:placetype":"venue"
},
  "geometry": {"coordinates":[2.1492109299,41.5150642395],"type":"Point"}
}