{
  "type": "Feature",
  "properties": {
    "iso:country":"ES",
    "sg:address":"Avda Madrid, 44",
    "sg:city":"Laguna Duero",
    "sg:orig_category":"Asilos De Ancianos. Centros Privados",
    "sg:phone":"+34 983 54 47 64",
    "sg:postcode":"47140",
    "sg:province":"Valladolid",
    "wof:name":"Torres Cifuentes Maria Isabel",
    "wof:placetype":"venue"
},
  "geometry": {"coordinates":[-4.7195987701,41.5803489685],"type":"Point"}
}