{
  "type": "Feature",
  "properties": {
    "iso:country":"ES",
    "sg:address":"Kale Nagusia, 35",
    "sg:city":"Lezo",
    "sg:orig_category":"Bibliotecas, Mediatecas",
    "sg:phone":"+34 943 51 95 92",
    "sg:postcode":"20100",
    "sg:province":"Guip\u00f9zcoa",
    "wof:name":"Ayuntamiento De Lezo",
    "wof:placetype":"venue"
},
  "geometry": {"coordinates":[-1.8996850252,43.314365387],"type":"Point"}
}