{
  "type": "Feature",
  "properties": {
    "addr:full":"Rua San Pedro, 13 Lugo Lugo 27001",
    "addr:housenumber":"13",
    "addr:postcode":"27001",
    "addr:street":"Rua San Pedro",
    "iso:country":"ES",
    "sg:address":"Rua San Pedro, 13",
    "sg:city":"Lugo",
    "sg:orig_category":"Sociedades, Compa\u00d1\u00cdas Aseguradoras",
    "sg:phone":"+34 982 22 75 62",
    "sg:postcode":"27001",
    "sg:province":"Lugo",
    "wof:name":"Rodil Blanco Victor",
    "wof:placetype":"venue"
},
  "geometry": {"coordinates":[-7.5539669991,43.0105628967],"type":"Point"}
}