{
  "type": "Feature",
  "properties": {
    "addr:full":"Carrer de Perpinya, 23 Barcelona Barcelona 08019",
    "addr:housenumber":"23",
    "addr:postcode":"08019",
    "addr:street":"Carrer De Perpinya",
    "iso:country":"ES",
    "sg:address":"Carrer de Perpinya, 23",
    "sg:city":"Barcelona",
    "sg:orig_category":"Carnicer\u00cdas, Carnicer\u00cdas",
    "sg:phone":"+34 933 05 23 01",
    "sg:postcode":"08019",
    "sg:province":"Barcelona",
    "wof:name":"Leon Pereira Francisco",
    "wof:placetype":"venue"
},
  "geometry": {"coordinates":[2.2154009342,41.4186286926],"type":"Point"}
}