{
  "type": "Feature",
  "properties": {
    "addr:full":"Calle de Lentisco, 4 Rota C\u00e1diz 11520",
    "addr:housenumber":"4",
    "addr:postcode":"11520",
    "addr:street":"Calle De Lentisco;Ca\u0301Diz",
    "iso:country":"ES",
    "sg:address":"Calle de Lentisco, 4",
    "sg:city":"Rota",
    "sg:orig_category":"Ingenier\u00cda, Centros De Estudios (diversos)",
    "sg:phone":"+34 956 81 39 39",
    "sg:postcode":"11520",
    "sg:province":"C\u00e1diz",
    "wof:name":"Gabinete De Ingenieria Y Sistemas Andaluz S.l.",
    "wof:placetype":"venue"
},
  "geometry": {"coordinates":[-6.3634538651,36.6282157898],"type":"Point"}
}