{
  "type": "Feature",
  "properties": {
    "addr:full":"Av Son Noguera(pol Industrial), 5 Llucmajor Islas Baleares 07620",
    "addr:postcode":"07620",
    "addr:street":"Av;Industrial",
    "iso:country":"ES",
    "sg:address":"Av Son Noguera(pol Industrial), 5",
    "sg:city":"Llucmajor",
    "sg:orig_category":"Centros Empresariales",
    "sg:phone":"+34 971 12 06 94",
    "sg:postcode":"07620",
    "sg:province":"Islas Baleares",
    "wof:name":"Kayser  Siegfried",
    "wof:placetype":"venue"
},
  "geometry": {"coordinates":[2.8507699966,39.4823493958],"type":"Point"}
}