{
  "type": "Feature",
  "properties": {
    "iso:country":"ES",
    "sg:address":"Calle de Real, 30",
    "sg:city":"Carmona",
    "sg:orig_category":"Ense\u00d1anza, Formaci\u00d3n Profesional: Aprendizaje",
    "sg:phone":"+34 954 19 63 10",
    "sg:postcode":"41410",
    "sg:province":"Sevilla",
    "wof:name":"Organizacion Nacional De Ciegos Espa\u00d1oles Grupo",
    "wof:placetype":"venue"
},
  "geometry": {"coordinates":[-5.6432981491,37.4690666199],"type":"Point"}
}