{
  "type": "Feature",
  "properties": {
    "addr:full":"Carrer de Alt De Sant Pere, 54 Reus Tarragona 43201",
    "addr:housenumber":"54",
    "addr:postcode":"43201",
    "addr:street":"Carrer De Alt De Sant Pere",
    "iso:country":"ES",
    "sg:address":"Carrer de Alt De Sant Pere, 54",
    "sg:city":"Reus",
    "sg:orig_category":"Bricolaje, Herramientas (al Por Menor)",
    "sg:phone":"+34 977 34 37 24",
    "sg:postcode":"43201",
    "sg:province":"Tarragona",
    "sg:website":"www.bricomarti.com",
    "wof:name":"Marti Pastor Joaquin",
    "wof:placetype":"venue"
},
  "geometry": {"coordinates":[1.1098029613,41.1586647034],"type":"Point"}
}