{
  "type": "Feature",
  "properties": {
    "iso:country":"ES",
    "sg:address":"Carretera De Almaden, S/n",
    "sg:city":"Cabeza Buey",
    "sg:orig_category":"Agricultura: Abastecimiento Y Cosechado (negocio)",
    "sg:phone":"+34 924 60 00 67",
    "sg:postcode":"06600",
    "sg:province":"Badajoz",
    "wof:name":"Balmaseda Nu\u00f1ez Maria Del Carmen",
    "wof:placetype":"venue"
},
  "geometry": {"coordinates":[-5.2242388725,38.7196540833],"type":"Point"}
}