{
  "type": "Feature",
  "properties": {
    "iso:country":"ES",
    "sg:address":"Ctra Castellar, 23",
    "sg:city":"Terrassa",
    "sg:orig_category":"Peluquer\u00cdas, Peluquer\u00cda Mixta",
    "sg:phone":"+34 937 85 80 89",
    "sg:postcode":"08222",
    "sg:province":"Barcelona",
    "wof:name":"Maque Mir Raquel",
    "wof:placetype":"venue"
},
  "geometry": {"coordinates":[2.022578001,41.5647964478],"type":"Point"}
}