{
  "type": "Feature",
  "properties": {
    "iso:country":"ES",
    "sg:address":"Plaz Polo De Bernabe, 4",
    "sg:city":"Valencia",
    "sg:orig_category":"Peluqueros: De Se\u00d1oras",
    "sg:phone":"+34 963 93 28 75",
    "sg:postcode":"46010",
    "sg:province":"Valencia",
    "wof:name":"Vicente Martinez Bego\u00f1a",
    "wof:placetype":"venue"
},
  "geometry": {"coordinates":[-0.3629930019,39.4749145508],"type":"Point"}
}