{
  "type": "Feature",
  "properties": {
    "iso:country":"ES",
    "sg:address":"Calle de Sevilla, 83",
    "sg:city":"Santos De Maimona",
    "sg:orig_category":"Agencias Y Agentes Comerciales, Representantes",
    "sg:phone":"+34 924 57 13 19",
    "sg:postcode":"06230",
    "sg:province":"Badajoz",
    "wof:name":"Gomez Gonzalez Francisco Jose",
    "wof:placetype":"venue"
},
  "geometry": {"coordinates":[-6.379734993,38.4480400085],"type":"Point"}
}