{
  "type": "Feature",
  "properties": {
    "addr:full":"Calle de San Pablo, 39 Baeza Ja\u00e9n 23440",
    "addr:housenumber":"39",
    "addr:postcode":"23440",
    "addr:street":"Calle De San Pablo",
    "iso:country":"ES",
    "sg:address":"Calle de San Pablo, 39",
    "sg:city":"Baeza",
    "sg:orig_category":"Ropa Para Beb\u00c9s Y Ni\u00d1os (confecci\u00d3n, Al Por Mayor)",
    "sg:phone":"+34 953 74 40 12",
    "sg:postcode":"23440",
    "sg:province":"Ja\u00e9n",
    "wof:name":"Martinez Lopez Gines",
    "wof:placetype":"venue"
},
  "geometry": {"coordinates":[-3.4654159546,37.9945106506],"type":"Point"}
}