{
  "type": "Feature",
  "properties": {
    "addr:full":"Caldereria, 36 Iru\u00f1a Navarra 31001",
    "addr:housenumber":"36",
    "addr:postcode":"31001",
    "addr:street":"Caldereria",
    "iso:country":"ES",
    "sg:address":"Caldereria, 36",
    "sg:city":"Iru\u00f1a",
    "sg:orig_category":"Molduras, Junquillos, Listones Y Molduras Perforadas",
    "sg:phone":"+34 948 22 08 79",
    "sg:postcode":"31001",
    "sg:province":"Navarra",
    "wof:name":"Cervera San Martin Llorens Marco S.a.i.",
    "wof:placetype":"venue"
},
  "geometry": {"coordinates":[-1.6418739557,42.81798172],"type":"Point"}
}