{
  "type": "Feature",
  "properties": {
    "addr:full":"Pg Doctor Moragas, 232 Barbera Valles Barcelona 08210",
    "addr:housenumber":"232",
    "addr:postcode":"08210",
    "addr:street":"Pg Doctor Moragas",
    "iso:country":"ES",
    "sg:address":"Pg Doctor Moragas, 232",
    "sg:city":"Barbera Valles",
    "sg:orig_category":"Asociaciones Y Clubs Deportivos",
    "sg:phone":"+34 937 18 22 04",
    "sg:postcode":"08210",
    "sg:province":"Barcelona",
    "wof:name":"Cano Torres Beatriz",
    "wof:placetype":"venue"
},
  "geometry": {"coordinates":[2.124106884,41.5163955688],"type":"Point"}
}