{
  "type": "Feature",
  "properties": {
    "iso:country":"ES",
    "sg:address":"Calle de Caraza, 21",
    "sg:city":"Chiclana De La Frontera",
    "sg:orig_category":"Comercio, Reparaci\u00d3n De Motocicletas, Bicicletas Y Piezas Sueltas",
    "sg:phone":"+34 956 49 00 44",
    "sg:postcode":"11130",
    "sg:province":"C\u00e1diz",
    "wof:name":"Rodriguez Moreno Enrique Manuel",
    "wof:placetype":"venue"
},
  "geometry": {"coordinates":[-6.1519451141,36.4206771851],"type":"Point"}
}