{
  "type": "Feature",
  "properties": {
    "iso:country":"ES",
    "sg:address":"Avda Virgen Del Carmen, 29",
    "sg:city":"Algeciras",
    "sg:orig_category":"M\u00c9dicos: Pediatr\u00cda. Enfermedades De Los Ni\u00d1os",
    "sg:phone":"+34 956 66 38 82",
    "sg:postcode":"11201",
    "sg:province":"C\u00e1diz",
    "wof:name":"Garces Ramos Andres",
    "wof:placetype":"venue"
},
  "geometry": {"coordinates":[-5.4458475113,36.1312828064],"type":"Point"}
}