{
  "type": "Feature",
  "properties": {
    "iso:country":"ES",
    "sg:address":"Carr Poliesportiu, S/n",
    "sg:city":"Muro",
    "sg:orig_category":"Acondicionamiento De Terrenos Para Deporte Y Juegos",
    "sg:phone":"+34 971 86 06 16",
    "sg:postcode":"07440",
    "sg:province":"Islas Baleares",
    "wof:name":"Ajuntament De Muro",
    "wof:placetype":"venue"
},
  "geometry": {"coordinates":[3.0532488823,39.7298316956],"type":"Point"}
}