{
  "type": "Feature",
  "properties": {
    "addr:full":"Afores, S/n L'albages Lleida 25155",
    "addr:housenumber":"s / n",
    "addr:postcode":"25155",
    "addr:street":"Afores",
    "iso:country":"ES",
    "sg:address":"Afores, S/n",
    "sg:city":"L'albages",
    "sg:orig_category":"Transportes Por V\u00cdas Navegables",
    "sg:phone":"+34 973 29 09 45",
    "sg:postcode":"25155",
    "sg:province":"Lleida",
    "wof:name":"Agricola Ramadera Oriol S.c.c.l",
    "wof:placetype":"venue"
},
  "geometry": {"coordinates":[0.743776083,41.4488639832],"type":"Point"}
}