{
  "type": "Feature",
  "properties": {
    "addr:full":"Pase Doctor Torres Villarroel, 18 Salamanca Salamanca 37005",
    "addr:housenumber":"18",
    "addr:postcode":"37005",
    "addr:street":"Doctor Torres Villarroel",
    "iso:country":"ES",
    "sg:address":"Pase Doctor Torres Villarroel, 18",
    "sg:city":"Salamanca",
    "sg:orig_category":"Tintes (fabricaci\u00d3n, Al Por Mayor)",
    "sg:phone":"+34 923 22 24 55",
    "sg:postcode":"37005",
    "sg:province":"Salamanca",
    "wof:name":"Cornejo Colella Pedro",
    "wof:placetype":"venue"
},
  "geometry": {"coordinates":[-5.6632070541,40.9717140198],"type":"Point"}
}