{
  "type": "Feature",
  "properties": {
    "addr:full":"Carr Forn De Vidre, 12 Vilanova I La Geltru Barcelona 08800",
    "addr:housenumber":"12",
    "addr:postcode":"08800",
    "addr:street":"Carr Forn De Vidre",
    "iso:country":"ES",
    "sg:address":"Carr Forn De Vidre, 12",
    "sg:city":"Vilanova I La Geltru",
    "sg:orig_category":"Psic\u00d3logos",
    "sg:phone":"+34 938 15 19 52",
    "sg:postcode":"08800",
    "sg:province":"Barcelona",
    "wof:name":"Urpi Carre Alexandre",
    "wof:placetype":"venue"
},
  "geometry": {"coordinates":[1.72874403,41.2201309204],"type":"Point"}
}