{
  "type": "Feature",
  "properties": {
    "iso:country":"ES",
    "sg:address":"Calle de Axular, 2",
    "sg:city":"Arizgoiti",
    "sg:orig_category":"Comunidades Religiosas",
    "sg:phone":"+34 944 49 91 28",
    "sg:postcode":"48970",
    "sg:province":"Vizcaya",
    "wof:name":"Religiosas Nuestra Se\u00f1ora De La Compasion",
    "wof:placetype":"venue"
},
  "geometry": {"coordinates":[-2.8920397758,43.236579895],"type":"Point"}
}