{
  "type": "Feature",
  "properties": {
    "iso:country":"ES",
    "sg:address":"Ptge Parterre (el), 1",
    "sg:city":"Alcoi",
    "sg:orig_category":"Centros M\u00c9dicos Y Sociales, Dispensarios",
    "sg:phone":"+34 965 54 12 42",
    "sg:postcode":"03801",
    "sg:province":"Alicante",
    "wof:name":"Consultas De Medicina Y Cirugia Comyce Alicante S.l.",
    "wof:placetype":"venue"
},
  "geometry": {"coordinates":[-0.4756709933,38.6961097717],"type":"Point"}
}