{
  "type": "Feature",
  "properties": {
    "iso:country":"ES",
    "sg:address":"Calle de Escuelas (las), 18",
    "sg:city":"Entrena",
    "sg:orig_category":"Agencias Y Agentes Comerciales, Representantes",
    "sg:phone":"+34 941 44 63 62",
    "sg:postcode":"26375",
    "sg:province":"La Rioja",
    "wof:name":"Barriobero Jimenez Felicito",
    "wof:placetype":"venue"
},
  "geometry": {"coordinates":[-2.5283620358,42.3875541687],"type":"Point"}
}