{
  "type": "Feature",
  "properties": {
    "iso:country":"ES",
    "sg:address":"Avda Virgen De Las Nieves, 4",
    "sg:city":"Hijar",
    "sg:orig_category":"Inmobiliaria (agencias)",
    "sg:phone":"+34 958 58 16 34",
    "sg:postcode":"18194",
    "sg:province":"Granada",
    "wof:name":"Inmobiliarias Linde Garcia 99 S.l.",
    "wof:placetype":"venue"
},
  "geometry": {"coordinates":[-3.6776089668,37.1488952637],"type":"Point"}
}