{
  "type": "Feature",
  "properties": {
    "addr:full":"Tudela, 21 Imarcoain Navarra 31119",
    "addr:housenumber":"21",
    "addr:postcode":"31119",
    "addr:street":"Tudela",
    "iso:country":"ES",
    "sg:address":"Tudela, 21",
    "sg:city":"Imarcoain",
    "sg:orig_category":"Herboristas (al Por Menor)",
    "sg:phone":"+34 948 31 41 36",
    "sg:postcode":"31119",
    "sg:province":"Navarra",
    "wof:name":"Distribuciones Aikider S.l.",
    "wof:placetype":"venue"
},
  "geometry": {"coordinates":[-1.5951639414,42.7345542908],"type":"Point"}
}