{
  "type": "Feature",
  "properties": {
    "addr:full":"Av. Blasco Iba\u00f1ez, 125 Massanassa Valencia 46470",
    "addr:housenumber":"125",
    "addr:postcode":"46470",
    "addr:street":"Av. Blasco Iban\u0303Ez",
    "iso:country":"ES",
    "sg:address":"Av. Blasco Iba\u00f1ez, 125",
    "sg:city":"Massanassa",
    "sg:orig_category":"Institutos De Belleza",
    "sg:phone":"+34 961 25 31 43",
    "sg:postcode":"46470",
    "sg:province":"Valencia",
    "wof:name":"Sol Y Look S.l.",
    "wof:placetype":"venue"
},
  "geometry": {"coordinates":[-0.3994829953,39.4131507874],"type":"Point"}
}