{
  "type": "Feature",
  "properties": {
    "addr:full":"Calle de Leganes (de), 7 Fuenlabrada Madrid 28945",
    "addr:housenumber":"7",
    "addr:postcode":"28945",
    "addr:street":"Calle De Leganes De",
    "iso:country":"ES",
    "sg:address":"Calle de Leganes (de), 7",
    "sg:city":"Fuenlabrada",
    "sg:orig_category":"Loter\u00cda Y T\u00d3mbola",
    "sg:phone":"+34 916 06 65 97",
    "sg:postcode":"28945",
    "sg:province":"Madrid",
    "wof:name":"Rodriguez Montero Josefa",
    "wof:placetype":"venue"
},
  "geometry": {"coordinates":[-3.7943029404,40.2845497131],"type":"Point"}
}