{
  "type": "Feature",
  "properties": {
    "iso:country":"ES",
    "sg:address":"Calle de Jose Maria Garrido Lopera, 11",
    "sg:city":"Granada",
    "sg:orig_category":"Molduras, Junquillos, Listones Y Molduras Perforadas",
    "sg:phone":"+34 958 13 26 73",
    "sg:postcode":"18008",
    "sg:province":"Granada",
    "wof:name":"Perez Contreras Teresa Dolores",
    "wof:placetype":"venue"
},
  "geometry": {"coordinates":[-3.5892269611,37.1589622498],"type":"Point"}
}