{
  "type": "Feature",
  "properties": {
    "iso:country":"ES",
    "sg:address":"Carrer de Sant Nicolau, 9",
    "sg:city":"Barcelona",
    "sg:orig_category":"Organizaciones Internacionales",
    "sg:phone":"+34 932 31 07 12",
    "sg:postcode":"08014",
    "sg:province":"Barcelona",
    "wof:name":"Associacio Nous Camins",
    "wof:placetype":"venue"
},
  "geometry": {"coordinates":[2.1447093487,41.3774299622],"type":"Point"}
}