{
  "type": "Feature",
  "properties": {
    "iso:country":"ES",
    "sg:address":"Pase Canalejas, 2",
    "sg:city":"Salamanca",
    "sg:orig_category":"Molduras, Junquillos, Listones Y Molduras Perforadas",
    "sg:phone":"+34 923 26 09 13",
    "sg:postcode":"37001",
    "sg:province":"Salamanca",
    "wof:name":"Pascual Sanchez Herminio",
    "wof:placetype":"venue"
},
  "geometry": {"coordinates":[-5.6584281921,40.9678878784],"type":"Point"}
}