{
  "type": "Feature",
  "properties": {
    "addr:full":"Urb. B. Azul, 16 Bahia Azul Islas Baleares 07609",
    "addr:housenumber":"16",
    "addr:postcode":"07609",
    "addr:street":"Azul",
    "iso:country":"ES",
    "sg:address":"Urb. B. Azul, 16",
    "sg:city":"Bahia Azul",
    "sg:orig_category":"Financiaci\u00d3n Y Cr\u00c9ditos",
    "sg:phone":"+34 971 78 64 56",
    "sg:postcode":"07609",
    "sg:province":"Islas Baleares",
    "wof:name":"Martinez Fernandez Joaquin",
    "wof:placetype":"venue"
},
  "geometry": {"coordinates":[2.7440850735,39.4852790833],"type":"Point"}
}