{
  "type": "Feature",
  "properties": {
    "addr:full":"Plaz David Martin, 1 Pinto Madrid 28320",
    "addr:housenumber":"1",
    "addr:postcode":"28320",
    "addr:street":"Plaz;Martin;Pinto",
    "iso:country":"ES",
    "sg:address":"Plaz David Martin, 1",
    "sg:city":"Pinto",
    "sg:orig_category":"Reposter\u00cdas",
    "sg:phone":"+34 916 92 69 63",
    "sg:postcode":"28320",
    "sg:province":"Madrid",
    "wof:name":"Gongora Polo Juan",
    "wof:placetype":"venue"
},
  "geometry": {"coordinates":[-3.694881916,40.2519645691],"type":"Point"}
}