{
  "type": "Feature",
  "properties": {
    "addr:full":"Pl Marsans, 2 Cornella Llobregat Barcelona 08940",
    "addr:housenumber":"2",
    "addr:postcode":"08940",
    "addr:street":"Pl Marsans",
    "iso:country":"ES",
    "sg:address":"Pl Marsans, 2",
    "sg:city":"Cornella Llobregat",
    "sg:orig_category":"Telas Y Sedas (al Por Menor)",
    "sg:phone":"+34 933 76 72 56",
    "sg:postcode":"08940",
    "sg:province":"Barcelona",
    "wof:name":"Sanchez Reinaldos Pedro",
    "wof:placetype":"venue"
},
  "geometry": {"coordinates":[2.0746479034,41.3612937927],"type":"Point"}
}