{
  "type": "Feature",
  "properties": {
    "addr:full":"Calle de Estibaliz, 14 Madrid Madrid 28043",
    "addr:housenumber":"14",
    "addr:postcode":"madrid;28043",
    "addr:street":"Calle De Estibaliz",
    "iso:country":"ES",
    "sg:address":"Calle de Estibaliz, 14",
    "sg:city":"Madrid",
    "sg:orig_category":"Inmobiliaria (agencias)",
    "sg:phone":"+34 913 82 51 79",
    "sg:postcode":"28043",
    "sg:province":"Madrid",
    "wof:name":"Reybe S.a.",
    "wof:placetype":"venue"
},
  "geometry": {"coordinates":[-3.651403904,40.4684257507],"type":"Point"}
}