{
  "type": "Feature",
  "properties": {
    "addr:full":"Carrer de Fontanella, 21 Barcelona Barcelona 08010",
    "addr:housenumber":"21",
    "addr:postcode":"08010",
    "addr:street":"Carrer De Fontanella",
    "iso:country":"ES",
    "sg:address":"Carrer de Fontanella, 21",
    "sg:city":"Barcelona",
    "sg:orig_category":"Soportes L\u00d3gicos, Programas Integradores De Aplicaciones (progiciels)",
    "sg:phone":"+34 933 01 07 35",
    "sg:postcode":"08010",
    "sg:province":"Barcelona",
    "wof:name":"Seresco S.a.",
    "wof:placetype":"venue"
},
  "geometry": {"coordinates":[2.1724739075,41.3883895874],"type":"Point"}
}