{
  "type": "Feature",
  "properties": {
    "addr:full":"Carrer de Blasco Iba\u00d1ez, 18 Crevillent Alicante 03330",
    "addr:housenumber":"18",
    "addr:postcode":"03330",
    "addr:street":"Carrer De Blasco Iban\u0303Ez",
    "iso:country":"ES",
    "sg:address":"Carrer de Blasco Iba\u00d1ez, 18",
    "sg:city":"Crevillent",
    "sg:orig_category":"Zapatos (al Por Menor)",
    "sg:phone":"+34 966 68 19 82",
    "sg:postcode":"03330",
    "sg:province":"Alicante",
    "wof:name":"Arroni Mat-chiran Estefania",
    "wof:placetype":"venue"
},
  "geometry": {"coordinates":[-0.8103306293,38.248336792],"type":"Point"}
}