{
  "type": "Feature",
  "properties": {
    "addr:full":"Calle de Padre Esteban Pernet, 35 Valencia Valencia 46014",
    "addr:housenumber":"35",
    "addr:postcode":"46014",
    "addr:street":"Calle De Padre Esteban Pernet",
    "iso:country":"ES",
    "sg:address":"Calle de Padre Esteban Pernet, 35",
    "sg:city":"Valencia",
    "sg:orig_category":"Sociedades, Compa\u00d1\u00cdas Aseguradoras",
    "sg:phone":"+34 963 13 60 81",
    "sg:postcode":"46014",
    "sg:province":"Valencia",
    "sg:website":"www.gptres.com",
    "wof:name":"Gonzalez Barbera Y Gomez S.l",
    "wof:placetype":"venue"
},
  "geometry": {"coordinates":[-0.4121980071,39.4669837952],"type":"Point"}
}