{
  "type": "Feature",
  "properties": {
    "addr:full":"C/ Verge Del Pilar, S/n Moncofa Castell\u00f3n 12593",
    "addr:housenumber":"s / n",
    "addr:postcode":"12593",
    "addr:street":"C / Verge Del Pilar;Castello\u0301N",
    "iso:country":"ES",
    "sg:address":"C/ Verge Del Pilar, S/n",
    "sg:city":"Moncofa",
    "sg:orig_category":"Mec\u00c1nico Del Autom\u00d3vil",
    "sg:phone":"+34 964 58 04 43",
    "sg:postcode":"12593",
    "sg:province":"Castell\u00f3n",
    "wof:name":"Talleres Record Movil S.l.",
    "wof:placetype":"venue"
},
  "geometry": {"coordinates":[-0.1488090008,39.8093185425],"type":"Point"}
}