{
  "type": "Feature",
  "properties": {
    "addr:full":"Carrer de Granja (de La), 12 Mataro Barcelona 08303",
    "addr:housenumber":"12",
    "addr:postcode":"08303",
    "addr:street":"Carrer De Granja De La",
    "iso:country":"ES",
    "sg:address":"Carrer de Granja (de La), 12",
    "sg:city":"Mataro",
    "sg:orig_category":"Empresas De Carpinter\u00cda De Madera",
    "sg:phone":"+34 937 99 65 27",
    "sg:postcode":"08303",
    "sg:province":"Barcelona",
    "wof:name":"Fernandez Garcia Diego",
    "wof:placetype":"venue"
},
  "geometry": {"coordinates":[2.4236218929,41.5423583984],"type":"Point"}
}