{
  "type": "Feature",
  "properties": {
    "iso:country":"ES",
    "sg:address":"Avda Begonias, 62",
    "sg:city":"Bormujos",
    "sg:orig_category":"Institutos M\u00c9dicos",
    "sg:phone":"+34 955 72 23 94",
    "sg:postcode":"41930",
    "sg:province":"Sevilla",
    "wof:name":"Legramed S.l.",
    "wof:placetype":"venue"
},
  "geometry": {"coordinates":[-6.0647239685,37.3623580933],"type":"Point"}
}