{
  "type": "Feature",
  "properties": {
    "iso:country":"ES",
    "sg:address":"Plaz Constitucion (de La), 7",
    "sg:city":"Adamuz",
    "sg:orig_category":"Electrodom\u00c9sticos (al Por Menor)",
    "sg:phone":"+34 957 16 64 03",
    "sg:postcode":"14430",
    "sg:province":"C\u00f3rdoba",
    "wof:name":"Bollero Torralbo Francisco",
    "wof:placetype":"venue"
},
  "geometry": {"coordinates":[-4.5245041847,38.0277519226],"type":"Point"}
}