{
  "type": "Feature",
  "properties": {
    "addr:full":"Carrer de Francesc Macia I Llusa, S/n Ginesteres Barcelona 08310",
    "addr:postcode":"08310",
    "addr:street":"Carrer De Francesc Macia;Llusa S / N Ginesteres",
    "iso:country":"ES",
    "sg:address":"Carrer de Francesc Macia I Llusa, S/n",
    "sg:city":"Ginesteres",
    "sg:orig_category":"Importaci\u00d3n",
    "sg:phone":"+34 937 97 24 22",
    "sg:postcode":"08310",
    "sg:province":"Barcelona",
    "wof:name":"Sarabia Y Asociados Mayoristas S.l.",
    "wof:placetype":"venue"
},
  "geometry": {"coordinates":[2.3736600876,41.5700340271],"type":"Point"}
}