{
  "type": "Feature",
  "properties": {
    "addr:full":"Calle de La Paz, 15 San Vicente De Barakaldo Vizcaya 48903",
    "addr:housenumber":"15",
    "addr:postcode":"48903",
    "addr:street":"Calle De La Paz",
    "iso:country":"ES",
    "sg:address":"Calle de La Paz, 15",
    "sg:city":"San Vicente De Barakaldo",
    "sg:orig_category":"Peluqueros: De Se\u00d1oras",
    "sg:phone":"+34 944 82 04 37",
    "sg:postcode":"48903",
    "sg:province":"Vizcaya",
    "wof:name":"Penas Coton Maria Teresa",
    "wof:placetype":"venue"
},
  "geometry": {"coordinates":[-2.9867534637,43.280620575],"type":"Point"}
}