{
  "type": "Feature",
  "properties": {
    "iso:country":"ES",
    "sg:address":"Pg Manuel Girona, 73",
    "sg:city":"Barcelona",
    "sg:orig_category":"Internados & Ense\u00d1anza Privada",
    "sg:phone":"+34 932 06 62 40",
    "sg:postcode":"08034",
    "sg:province":"Barcelona",
    "wof:name":"Institucion Familiar De Educacion S. A.",
    "wof:placetype":"venue"
},
  "geometry": {"coordinates":[2.1287899017,41.3923912048],"type":"Point"}
}