{
  "type": "Feature",
  "properties": {
    "addr:full":"C/ Sant Marti, 91 Cerdanyola Valles Barcelona 08290",
    "addr:housenumber":"91",
    "addr:postcode":"08290",
    "addr:street":"C / Sant Marti;Valles Barcelona",
    "iso:country":"ES",
    "sg:address":"C/ Sant Marti, 91",
    "sg:city":"Cerdanyola Valles",
    "sg:orig_category":"Mercer\u00cda, Lencer\u00cda (al Por Menor)",
    "sg:phone":"+34 936 91 83 57",
    "sg:postcode":"08290",
    "sg:province":"Barcelona",
    "wof:name":"Jimenez Montes Francisco",
    "wof:placetype":"venue"
},
  "geometry": {"coordinates":[2.1470150948,41.4924812317],"type":"Point"}
}