{
  "type": "Feature",
  "properties": {
    "addr:full":"Pg Porta Coeli (de), 7 Monasterios Valencia 46530",
    "addr:postcode":"46530",
    "addr:street":"Pg Porta Coeli De 7 Monasterios",
    "iso:country":"ES",
    "sg:address":"Pg Porta Coeli (de), 7",
    "sg:city":"Monasterios",
    "sg:orig_category":"Promotores Constructores",
    "sg:phone":"+34 961 40 52 12",
    "sg:postcode":"46530",
    "sg:province":"Valencia",
    "wof:name":"Hermorios S.a.",
    "wof:placetype":"venue"
},
  "geometry": {"coordinates":[-0.3423199952,39.6393585205],"type":"Point"}
}