{
  "type": "Feature",
  "properties": {
    "addr:full":"Calle de Club, 8 Arenas -areeta Vizcaya 48930",
    "addr:housenumber":"8;areeta",
    "addr:postcode":"48930",
    "addr:street":"Calle De Club",
    "iso:country":"ES",
    "sg:address":"Calle de Club, 8",
    "sg:city":"Arenas -areeta",
    "sg:orig_category":"Art\u00cdculos De Decoraci\u00d3n (fabricaci\u00d3n Y Al Por Mayor)",
    "sg:phone":"+34 944 80 13 25",
    "sg:postcode":"48930",
    "sg:province":"Vizcaya",
    "wof:name":"Roncero Gascon Bego\u00f1a",
    "wof:placetype":"venue"
},
  "geometry": {"coordinates":[-2.6983869076,43.2204284668],"type":"Point"}
}