{
  "type": "Feature",
  "properties": {
    "iso:country":"ES",
    "sg:address":"Carrer de Industria, 23",
    "sg:city":"Papiol",
    "sg:orig_category":"Fabricaci\u00d3n De Bolsos Y Bolsos De Tela",
    "sg:phone":"+34 936 73 22 38",
    "sg:postcode":"08754",
    "sg:province":"Barcelona",
    "wof:name":"Bolsera Y Embalajemania S.l.",
    "wof:placetype":"venue"
},
  "geometry": {"coordinates":[2.0108549595,41.4297981262],"type":"Point"}
}