{
  "type": "Feature",
  "properties": {
    "iso:country":"ES",
    "sg:address":"Alfonso El Batallador, 16",
    "sg:city":"Iru\u00f1a",
    "sg:orig_category":"Electricidad: Instaladores",
    "sg:phone":"+34 948 27 53 63",
    "sg:postcode":"31007",
    "sg:province":"Navarra",
    "wof:name":"Electricidad Satrustegui S.l.",
    "wof:placetype":"venue"
},
  "geometry": {"coordinates":[-1.6523820162,42.8039627075],"type":"Point"}
}