{
  "type": "Feature",
  "properties": {
    "iso:country":"ES",
    "sg:address":"Carr Hortes, 13",
    "sg:city":"Girona",
    "sg:orig_category":"Sales (al Por Mayor)",
    "sg:phone":"+34 972 41 21 88",
    "sg:postcode":"17001",
    "sg:province":"Girona",
    "wof:name":"Garcia Galvez Ester",
    "wof:placetype":"venue"
},
  "geometry": {"coordinates":[2.8223822117,41.9844284058],"type":"Point"}
}