{
  "type": "Feature",
  "properties": {
    "iso:country":"ES",
    "sg:address":"Carrer de Pujos, 36",
    "sg:city":"Hospitalet Llobregat",
    "sg:orig_category":"Pintura Y Barniz (al Por Menor)",
    "sg:phone":"+34 934 49 37 92",
    "sg:postcode":"08904",
    "sg:province":"Barcelona",
    "wof:name":"Guberna Cano Francesc Xavier",
    "wof:placetype":"venue"
},
  "geometry": {"coordinates":[2.1184959412,41.3734931946],"type":"Point"}
}