{
  "type": "Feature",
  "properties": {
    "addr:full":"Calle de Saturno, 14 Ramos Murcia 30589",
    "addr:housenumber":"14",
    "addr:postcode":"30589",
    "addr:street":"Calle De Saturno",
    "iso:country":"ES",
    "sg:address":"Calle de Saturno, 14",
    "sg:city":"Ramos",
    "sg:orig_category":"Venta, Instalaci\u00d3n De Calefacci\u00d3n",
    "sg:phone":"+34 968 82 25 45",
    "sg:postcode":"30589",
    "sg:province":"Murcia",
    "wof:name":"Fonminasan S.l.",
    "wof:placetype":"venue"
},
  "geometry": {"coordinates":[-1.0311379433,37.9945831299],"type":"Point"}
}