{
  "type": "Feature",
  "properties": {
    "iso:country":"ES",
    "sg:address":"Calle de Oloron Santa Maria, 1",
    "sg:city":"Jaca",
    "sg:orig_category":"Porcelanas, Azulejos (fabricaci\u00d3n, Al Por Mayor)",
    "sg:phone":"+34 974 36 20 45",
    "sg:postcode":"22700",
    "sg:province":"Huesca",
    "wof:name":"Callizo Martinez Marcos",
    "wof:placetype":"venue"
},
  "geometry": {"coordinates":[-0.5484849811,42.5742492676],"type":"Point"}
}