{
  "type": "Feature",
  "properties": {
    "addr:full":"Carrer de Estats Units, 41 Segur Calafell Tarragona 43882",
    "addr:housenumber":"units 41",
    "addr:postcode":"43882",
    "addr:street":"Carrer De Estats",
    "iso:country":"ES",
    "sg:address":"Carrer de Estats Units, 41",
    "sg:city":"Segur Calafell",
    "sg:orig_category":"Bisuter\u00cda, Joyer\u00cda, Relojer\u00cda (al Por Menor)",
    "sg:phone":"+34 977 15 03 13",
    "sg:postcode":"43882",
    "sg:province":"Tarragona",
    "wof:name":"Pedrajas Jimenez Isabel",
    "wof:placetype":"venue"
},
  "geometry": {"coordinates":[1.5981800556,41.2034416199],"type":"Point"}
}