{
  "type": "Feature",
  "properties": {
    "addr:full":"Avda Principe De Asturias, 4 Briviesca Burgos 09240",
    "addr:housenumber":"4",
    "addr:postcode":"09240",
    "addr:street":"Avda Principe De Asturias",
    "iso:country":"ES",
    "sg:address":"Avda Principe De Asturias, 4",
    "sg:city":"Briviesca",
    "sg:orig_category":"Administradores De Bienes Y Delegados De Comunidades De Propietarios",
    "sg:phone":"+34 947 59 38 54",
    "sg:postcode":"09240",
    "sg:province":"Burgos",
    "wof:name":"Sagredo Saiz Maria Isabel",
    "wof:placetype":"venue"
},
  "geometry": {"coordinates":[-3.3213789463,42.5488815308],"type":"Point"}
}