{
  "type": "Feature",
  "properties": {
    "addr:full":"Ctro. Comerc. La Sierra, S/n Cordoba C\u00f3rdoba 14012",
    "addr:housenumber":"/ n",
    "addr:postcode":"14012",
    "addr:street":"La Sierra S;Co\u0301Rdoba",
    "iso:country":"ES",
    "sg:address":"Ctro. Comerc. La Sierra, S/n",
    "sg:city":"Cordoba",
    "sg:orig_category":"Confecci\u00d3n (fabricaci\u00d3n, Al Por Mayor)",
    "sg:phone":"+34 957 27 81 84",
    "sg:postcode":"14012",
    "sg:province":"C\u00f3rdoba",
    "sg:website":"www.zara.com",
    "wof:name":"Zara Espa\u00d1a S.a.",
    "wof:placetype":"venue"
},
  "geometry": {"coordinates":[-4.8416934013,37.9320526123],"type":"Point"}
}