{
  "type": "Feature",
  "properties": {
    "iso:country":"ES",
    "sg:address":"Calle de Saint Exupery, 20",
    "sg:city":"Malaga",
    "sg:orig_category":"Promotores Constructores",
    "sg:phone":"+34 952 36 64 00",
    "sg:postcode":"29007",
    "sg:province":"M\u00e1laga",
    "wof:name":"Promotores Y Gestores De Suelos Y Vuelos Progesw S.l.",
    "wof:placetype":"venue"
},
  "geometry": {"coordinates":[-4.4567060471,36.7168731689],"type":"Point"}
}