{
  "type": "Feature",
  "properties": {
    "addr:full":"Carrer de Sant Lluis, 68 Barcelona Barcelona 08024",
    "addr:housenumber":"68",
    "addr:postcode":"08024",
    "addr:street":"Carrer De Sant Lluis",
    "iso:country":"ES",
    "sg:address":"Carrer de Sant Lluis, 68",
    "sg:city":"Barcelona",
    "sg:orig_category":"Mec\u00c1nico Del Autom\u00d3vil",
    "sg:phone":"+34 932 13 01 75",
    "sg:postcode":"08024",
    "sg:province":"Barcelona",
    "wof:name":"Ca\u00f1ete Pinto Antonio",
    "wof:placetype":"venue"
},
  "geometry": {"coordinates":[2.161648035,41.4061355591],"type":"Point"}
}