{
  "type": "Feature",
  "properties": {
    "addr:full":"Molinos, 1 Las Gabias Granada 18110",
    "addr:housenumber":"1",
    "addr:postcode":"18110",
    "addr:street":"Molinos",
    "iso:country":"ES",
    "sg:address":"Molinos, 1",
    "sg:city":"Las Gabias",
    "sg:orig_category":"Librer\u00cdas",
    "sg:phone":"+34 958 58 22 51",
    "sg:postcode":"18110",
    "sg:province":"Granada",
    "wof:name":"Alonso Mondejar Jose Antonio",
    "wof:placetype":"venue"
},
  "geometry": {"coordinates":[-3.6457402706,37.1092758179],"type":"Point"}
}