{
  "type": "Feature",
  "properties": {
    "addr:full":"Carrer de Josep Martinez, 57 Palma Islas Baleares 07007",
    "addr:housenumber":"57",
    "addr:postcode":"07007",
    "addr:street":"Carrer De Josep Martinez",
    "iso:country":"ES",
    "sg:address":"Carrer de Josep Martinez, 57",
    "sg:city":"Palma",
    "sg:orig_category":"Empresas De Carpinter\u00cda De Madera",
    "sg:phone":"+34 971 27 07 67",
    "sg:postcode":"07007",
    "sg:province":"Islas Baleares",
    "wof:name":"Motis Badia Ricardo",
    "wof:placetype":"venue"
},
  "geometry": {"coordinates":[2.6756129265,39.5723266602],"type":"Point"}
}