{
  "type": "Feature",
  "properties": {
    "addr:full":"Calle de Churruca, 54 Zamora Zamora 49021",
    "addr:housenumber":"54",
    "addr:postcode":"49021",
    "addr:street":"Calle De Churruca",
    "iso:country":"ES",
    "sg:address":"Calle de Churruca, 54",
    "sg:city":"Zamora",
    "sg:orig_category":"Fabrica, Negocio De Vidrieras, Productos Vidriados Y Espejos",
    "sg:phone":"+34 980 67 22 29",
    "sg:postcode":"49021",
    "sg:province":"Zamora",
    "wof:name":"Ars Vitraria",
    "wof:placetype":"venue"
},
  "geometry": {"coordinates":[-5.7295017242,41.5141601562],"type":"Point"}
}