{
  "type": "Feature",
  "properties": {
    "iso:country":"ES",
    "sg:address":"Calle de Conde De Robledo, 3",
    "sg:city":"Cordoba",
    "sg:orig_category":"Cl\u00cdnicas Dentales",
    "sg:phone":"+34 957 47 97 76",
    "sg:postcode":"14008",
    "sg:province":"C\u00f3rdoba",
    "wof:name":"Abellan Raigon Maria De Lourdes",
    "wof:placetype":"venue"
},
  "geometry": {"coordinates":[-4.781384,37.88657],"type":"Point"}
}