{
  "type": "Feature",
  "properties": {
    "addr:full":"Ctra Encinas Cantalapiedra, Km. 0009,2 Babilafuente Salamanca 37330",
    "addr:postcode":"37330",
    "addr:street":"Ctra Encinas Cantalapiedra Km. 0009,2",
    "iso:country":"ES",
    "sg:address":"Ctra Encinas Cantalapiedra, Km. 0009,2",
    "sg:city":"Babilafuente",
    "sg:orig_category":"Insecticidas, Fumigaci\u00d3n",
    "sg:phone":"+34 923 36 09 80",
    "sg:postcode":"37330",
    "sg:province":"Salamanca",
    "wof:name":"Maquinaria Future S.l.",
    "wof:placetype":"venue"
},
  "geometry": {"coordinates":[-5.4237041473,40.9755210876],"type":"Point"}
}