{
  "type": "Feature",
  "properties": {
    "iso:country":"ES",
    "sg:address":"Calle de Historiador Antonio Aguilar Y Cano, 48",
    "sg:city":"Puente-genil",
    "sg:orig_category":"Contenedores (mercanc\u00cdas)",
    "sg:phone":"+34 957 60 20 01",
    "sg:postcode":"14500",
    "sg:province":"C\u00f3rdoba",
    "wof:name":"Aguilar Fernandez Antonio",
    "wof:placetype":"venue"
},
  "geometry": {"coordinates":[-4.7653374672,37.3908958435],"type":"Point"}
}