{
  "type": "Feature",
  "properties": {
    "iso:country":"ES",
    "sg:address":"Carrer de Melilla, 28",
    "sg:city":"Amposta",
    "sg:orig_category":"Escayola Y Productos De Escayola (fabricaci\u00d3n, Al Por Mayor)",
    "sg:phone":"+34 977 70 61 00",
    "sg:postcode":"43870",
    "sg:province":"Tarragona",
    "sg:website":"www.sostreestan.com",
    "wof:name":"Sostre Estan S. L.",
    "wof:placetype":"venue"
},
  "geometry": {"coordinates":[0.5828740001,40.7109527588],"type":"Point"}
}