{
  "type": "Feature",
  "properties": {
    "iso:country":"ES",
    "sg:address":"Carrer de Literat Azorin, 22",
    "sg:city":"Cocentaina",
    "sg:orig_category":"Electricidad: Instaladores",
    "sg:phone":"+34 965 59 28 33",
    "sg:postcode":"03820",
    "sg:province":"Alicante",
    "wof:name":"Electricidad Sanz S.l.",
    "wof:placetype":"venue"
},
  "geometry": {"coordinates":[-0.4387469888,38.7394294739],"type":"Point"}
}