{
  "type": "Feature",
  "properties": {
    "addr:full":"D. Sta. Eulalia, S/n Carmonita Badajoz 06488",
    "addr:housenumber":"s / n",
    "addr:postcode":"06488",
    "iso:country":"ES",
    "sg:address":"D. Sta. Eulalia, S/n",
    "sg:city":"Carmonita",
    "sg:orig_category":"Carnicer\u00cdas, Carnicer\u00cdas",
    "sg:phone":"+34 924 12 31 43",
    "sg:postcode":"06488",
    "sg:province":"Badajoz",
    "wof:name":"M.r.c. Jamones S.l.",
    "wof:placetype":"venue"
},
  "geometry": {"coordinates":[-6.3375039101,39.1536865234],"type":"Point"}
}