{
  "type": "Feature",
  "properties": {
    "iso:country":"ES",
    "sg:address":"Calle de Loja, 10",
    "sg:city":"Velez-malaga",
    "sg:orig_category":"Promotores Constructores",
    "sg:phone":"+34 952 50 24 06",
    "sg:postcode":"29700",
    "sg:province":"M\u00e1laga",
    "wof:name":"Encofrados Merino S.l.",
    "wof:placetype":"venue"
},
  "geometry": {"coordinates":[-4.0986428261,36.7722663879],"type":"Point"}
}