{
  "type": "Feature",
  "properties": {
    "addr:full":"Calle de Pez, 7 San Esteban Del Molar Zamora 49650",
    "addr:housenumber":"7",
    "addr:postcode":"49650",
    "addr:street":"Calle De Pez",
    "iso:country":"ES",
    "sg:address":"Calle de Pez, 7",
    "sg:city":"San Esteban Del Molar",
    "sg:orig_category":"Maquinaria Para Industrias Diversas",
    "sg:phone":"+34 980 66 53 03",
    "sg:postcode":"49650",
    "sg:province":"Zamora",
    "wof:name":"Martinez Prieto Juio",
    "wof:placetype":"venue"
},
  "geometry": {"coordinates":[-5.5512948036,41.9360351562],"type":"Point"}
}