{
  "type": "Feature",
  "properties": {
    "addr:full":"Avda Navarra, S/n Aspe Alicante 03680",
    "addr:postcode":"03680",
    "addr:street":"Avda Navarra S / N",
    "iso:country":"ES",
    "sg:address":"Avda Navarra, S/n",
    "sg:city":"Aspe",
    "sg:orig_category":"Carnicer\u00cdas, Carnicer\u00cdas",
    "sg:phone":"+34 965 49 60 74",
    "sg:postcode":"03680",
    "sg:province":"Alicante",
    "wof:name":"Carnes De El Bierzo-leon S.r.l.",
    "wof:placetype":"venue"
},
  "geometry": {"coordinates":[-0.7695189714,38.348651886],"type":"Point"}
}