{
  "type": "Feature",
  "properties": {
    "iso:country":"ES",
    "sg:address":"Calle de Palencia, 5",
    "sg:city":"Albacete",
    "sg:orig_category":"Centros De Coordinaci\u00d3n",
    "sg:phone":"+34 967 24 73 84",
    "sg:postcode":"02006",
    "sg:province":"Albacete",
    "wof:name":"Guirao Belmonte Maria Jesus",
    "wof:placetype":"venue"
},
  "geometry": {"coordinates":[-1.8537919521,39.0007247925],"type":"Point"}
}