{
  "type": "Feature",
  "properties": {
    "addr:full":"Calle de Nueva, 9 Almansa Albacete 02640",
    "addr:housenumber":"9",
    "addr:postcode":"02640",
    "addr:street":"Calle De Nueva",
    "iso:country":"ES",
    "sg:address":"Calle de Nueva, 9",
    "sg:city":"Almansa",
    "sg:orig_category":"Inversiones",
    "sg:phone":"+34 967 34 08 61",
    "sg:postcode":"02640",
    "sg:province":"Albacete",
    "wof:name":"Almanse\u00f1a De Inversiones S.l.",
    "wof:placetype":"venue"
},
  "geometry": {"coordinates":[-1.094096899,38.8678894043],"type":"Point"}
}