{
  "type": "Feature",
  "properties": {
    "iso:country":"ES",
    "sg:address":"Calle de Carmen, 56",
    "sg:city":"Cabezo Torres",
    "sg:orig_category":"M\u00c9dicos: Estomatolog\u00cda",
    "sg:phone":"+34 968 30 84 33",
    "sg:postcode":"30110",
    "sg:province":"Murcia",
    "wof:name":"Corbaran Sanchez Paloma",
    "wof:placetype":"venue"
},
  "geometry": {"coordinates":[-1.1260504723,38.0259933472],"type":"Point"}
}