{
  "type": "Feature",
  "properties": {
    "iso:country":"ES",
    "sg:address":"Carrer de Vicen\u00c7 Bou, 16",
    "sg:city":"Esplugues Llobregat",
    "sg:orig_category":"Abogados",
    "sg:phone":"+34 934 73 32 32",
    "sg:postcode":"08950",
    "sg:province":"Barcelona",
    "wof:name":"Jose Luis Garcia Abogados Asociados S.c.p.",
    "wof:placetype":"venue"
},
  "geometry": {"coordinates":[2.0839450359,41.3748588562],"type":"Point"}
}