{
  "type": "Feature",
  "properties": {
    "iso:country":"ES",
    "sg:address":"Ctra. Madrid-irun, Km. 0149,2",
    "sg:city":"Milagros",
    "sg:orig_category":"Distribuci\u00d3n De Petr\u00d3leo Y Derivados",
    "sg:phone":"+34 947 54 81 02",
    "sg:postcode":"09460",
    "sg:province":"Burgos",
    "sg:website":"www.cepsa.es",
    "wof:name":"Tamaca Autocentro S.a.",
    "wof:placetype":"venue"
},
  "geometry": {"coordinates":[-3.6977000237,41.5754966736],"type":"Point"}
}