{
  "type": "Feature",
  "properties": {
    "addr:full":"Calle de Amor Hermoso, 61 Madrid Madrid 28026",
    "addr:housenumber":"61",
    "addr:postcode":"madrid;28026",
    "addr:street":"Calle De Amor Hermoso",
    "iso:country":"ES",
    "sg:address":"Calle de Amor Hermoso, 61",
    "sg:city":"Madrid",
    "sg:orig_category":"Promotores Constructores",
    "sg:phone":"+34 914 76 22 50",
    "sg:postcode":"28026",
    "sg:province":"Madrid",
    "wof:name":"Inmobiliaria Valmaser S.l.",
    "wof:placetype":"venue"
},
  "geometry": {"coordinates":[-3.7035927773,40.3837394714],"type":"Point"}
}