{
  "type": "Feature",
  "properties": {
    "iso:country":"ES",
    "sg:address":"Elizatxo Auzoa, 49",
    "sg:city":"Hernani",
    "sg:orig_category":"Arreglo E Instalaci\u00d3n De Caf\u00c9s, Hoteles Y Restaurantes",
    "sg:phone":"+34 943 33 04 58",
    "sg:postcode":"20120",
    "sg:province":"Guip\u00f9zcoa",
    "wof:name":"Osa Gonzalez Francisco Javier",
    "wof:placetype":"venue"
},
  "geometry": {"coordinates":[-1.9771519899,43.2623214722],"type":"Point"}
}