{
  "type": "Feature",
  "properties": {
    "iso:country":"ES",
    "sg:address":"Calle de Juan Bravo, 18",
    "sg:city":"Puertollano",
    "sg:orig_category":"Agentes Generales De Seguros",
    "sg:phone":"+34 926 43 05 31",
    "sg:postcode":"13500",
    "sg:province":"Ciudad Real",
    "wof:name":"Araque Juarez Montserrat",
    "wof:placetype":"venue"
},
  "geometry": {"coordinates":[-4.106944561,38.6854667664],"type":"Point"}
}