{
  "type": "Feature",
  "properties": {
    "addr:full":"Calle de Hernando De Acu\u00d1a, 61 Valladolid Valladolid 47014",
    "addr:housenumber":"61",
    "addr:postcode":"47014",
    "addr:street":"Calle De Hernando De Acun\u0303A",
    "iso:country":"ES",
    "sg:address":"Calle de Hernando De Acu\u00d1a, 61",
    "sg:city":"Valladolid",
    "sg:orig_category":"Muebles, Minoristas",
    "sg:phone":"+34 983 33 88 33",
    "sg:postcode":"47014",
    "sg:province":"Valladolid",
    "wof:name":"Gonzalez Llorente Parquesol S.l.",
    "wof:placetype":"venue"
},
  "geometry": {"coordinates":[-4.7633910179,41.6379356384],"type":"Point"}
}