{
  "type": "Feature",
  "properties": {
    "addr:full":"Carrer de Balmes, S/n Poligono Barcelona 08213",
    "addr:housenumber":"s / n",
    "addr:postcode":"08213",
    "addr:street":"Carrer De Balmes;Barcelona",
    "iso:country":"ES",
    "sg:address":"Carrer de Balmes, S/n",
    "sg:city":"Poligono",
    "sg:orig_category":"Ense\u00d1anza, Formaci\u00d3n Profesional: Aprendizaje",
    "sg:phone":"+34 937 13 20 45",
    "sg:postcode":"08213",
    "sg:province":"Barcelona",
    "wof:name":"Ajuntament De Polinya",
    "wof:placetype":"venue"
},
  "geometry": {"coordinates":[2.2931997776,41.6254081726],"type":"Point"}
}