{
  "type": "Feature",
  "properties": {
    "addr:full":"Crt Calasparra, 25 Letur Albacete 02434",
    "addr:housenumber":"25",
    "addr:postcode":"02434",
    "addr:street":"Crt Calasparra",
    "iso:country":"ES",
    "sg:address":"Crt Calasparra, 25",
    "sg:city":"Letur",
    "sg:orig_category":"Molduras, Junquillos, Listones Y Molduras Perforadas",
    "sg:phone":"+34 967 42 61 40",
    "sg:postcode":"02434",
    "sg:province":"Albacete",
    "wof:name":"Matraca S.l.",
    "wof:placetype":"venue"
},
  "geometry": {"coordinates":[-2.1644289494,38.3347587585],"type":"Point"}
}