{
  "type": "Feature",
  "properties": {
    "addr:full":"Calle de Avenida De La Ribera, 9 Lodosa Navarra 31580",
    "addr:housenumber":"9",
    "addr:postcode":"31580",
    "addr:street":"Calle De Avenida De La Ribera",
    "iso:country":"ES",
    "sg:address":"Calle de Avenida De La Ribera, 9",
    "sg:city":"Lodosa",
    "sg:orig_category":"Cajas De Ahorro",
    "sg:phone":"+34 948 69 46 64",
    "sg:postcode":"31580",
    "sg:province":"Navarra",
    "wof:name":"Caixa D'estalvis I Pensions De Barcelona",
    "wof:placetype":"venue"
},
  "geometry": {"coordinates":[-2.07827425,42.42370224],"type":"Point"}
}