{
  "type": "Feature",
  "properties": {
    "iso:country":"ES",
    "sg:address":"Pase Zorrilla, 194",
    "sg:city":"Valladolid",
    "sg:orig_category":"Radiocomunicaciones, Telefon\u00cda M\u00d3vil, Radiomensajer\u00cda: Servicios, Comercializaci\u00d3n",
    "sg:phone":"+34 983 22 80 12",
    "sg:postcode":"47006",
    "sg:province":"Valladolid",
    "wof:name":"Complutel Comunicacciones S.l.",
    "wof:placetype":"venue"
},
  "geometry": {"coordinates":[-4.7433409691,41.6287918091],"type":"Point"}
}