{
  "type": "Feature",
  "properties": {
    "addr:full":"Ciutat Cooperativa, S/n S. Boi Llobregat Barcelona 08830",
    "addr:postcode":"08830",
    "addr:street":"S / N",
    "iso:country":"ES",
    "sg:address":"Ciutat Cooperativa, S/n",
    "sg:city":"S. Boi Llobregat",
    "sg:orig_category":"Carnicer\u00cdas, Carnicer\u00cdas",
    "sg:phone":"+34 936 30 95 54",
    "sg:postcode":"08830",
    "sg:province":"Barcelona",
    "wof:name":"Arnaiz Romai Sergio",
    "wof:placetype":"venue"
},
  "geometry": {"coordinates":[2.0306322575,41.3573913574],"type":"Point"}
}