{
  "type": "Feature",
  "properties": {
    "addr:full":"Mercat Carmel, S/n Barcelona Barcelona 08032",
    "addr:housenumber":"s / n",
    "addr:postcode":"08032",
    "iso:country":"ES",
    "sg:address":"Mercat Carmel, S/n",
    "sg:city":"Barcelona",
    "sg:orig_category":"Pescader\u00cdas (al Por Menor)",
    "sg:phone":"+34 933 57 54 48",
    "sg:postcode":"08032",
    "sg:province":"Barcelona",
    "wof:name":"Serret Grau Maria Rosa",
    "wof:placetype":"venue"
},
  "geometry": {"coordinates":[2.1578700542,41.4244384766],"type":"Point"}
}