{
  "type": "Feature",
  "properties": {
    "addr:full":"Ctra Medina De Rioseco, 18 Toro Zamora 49800",
    "addr:housenumber":"18",
    "addr:postcode":"49800",
    "addr:street":"Ctra Medina De Rioseco",
    "iso:country":"ES",
    "sg:address":"Ctra Medina De Rioseco, 18",
    "sg:city":"Toro",
    "sg:orig_category":"Frutas Y Legumbres Frescas (al Por Mayor)",
    "sg:phone":"+34 980 69 11 28",
    "sg:postcode":"49800",
    "sg:province":"Zamora",
    "wof:name":"Frulumar S.l.",
    "wof:placetype":"venue"
},
  "geometry": {"coordinates":[-5.3903288841,41.5262718201],"type":"Point"}
}