{
  "type": "Feature",
  "properties": {
    "iso:country":"ES",
    "sg:address":"Calle de Marques De Viana, 16",
    "sg:city":"Madrid",
    "sg:orig_category":"Molduras, Junquillos, Listones Y Molduras Perforadas",
    "sg:phone":"+34 915 71 72 74",
    "sg:postcode":"28039",
    "sg:province":"Madrid",
    "wof:name":"Rodriguez Santamarina Claudio",
    "wof:placetype":"venue"
},
  "geometry": {"coordinates":[-3.7001900673,40.4616775513],"type":"Point"}
}