{
  "type": "Feature",
  "properties": {
    "addr:full":"Calle de Esteban Salazar Chapela, 24 Malaga M\u00e1laga 29004",
    "addr:housenumber":"24",
    "addr:postcode":"29004",
    "addr:street":"Calle De Esteban Salazar Chapela;Ma\u0301Laga",
    "iso:country":"ES",
    "sg:address":"Calle de Esteban Salazar Chapela, 24",
    "sg:city":"Malaga",
    "sg:orig_category":"Maquinaria Neum\u00c1tica",
    "sg:phone":"+34 952 23 99 12",
    "sg:postcode":"29004",
    "sg:province":"M\u00e1laga",
    "sg:website":"www.korota.com",
    "wof:name":"Korota S.a.",
    "wof:placetype":"venue"
},
  "geometry": {"coordinates":[-4.476875782,36.69298172],"type":"Point"}
}