{
  "type": "Feature",
  "properties": {
    "iso:country":"ES",
    "sg:address":"Ctra Benidorm, 12",
    "sg:city":"Finestrat",
    "sg:orig_category":"Mec\u00c1nico Del Autom\u00d3vil",
    "sg:phone":"+34 965 87 82 08",
    "sg:postcode":"03509",
    "sg:province":"Alicante",
    "wof:name":"Llorca Climent Jose",
    "wof:placetype":"venue"
},
  "geometry": {"coordinates":[-0.2115509957,38.5689659119],"type":"Point"}
}