{
  "type": "Feature",
  "properties": {
    "iso:country":"ES",
    "sg:address":"Calle de San Sebastian, 8",
    "sg:city":"Alhaurin El Grande",
    "sg:orig_category":"M\u00c9dicos: An\u00c1lisis Cl\u00cdnicos",
    "sg:phone":"+34 952 49 00 13",
    "sg:postcode":"29120",
    "sg:province":"M\u00e1laga",
    "wof:name":"Quintela Rivera Lourdes",
    "wof:placetype":"venue"
},
  "geometry": {"coordinates":[-4.6874008179,36.6445922852],"type":"Point"}
}