{
  "type": "Feature",
  "properties": {
    "iso:country":"ES",
    "sg:address":"Carrer de Mina De La Ciutat, 12",
    "sg:city":"Barcelona",
    "sg:orig_category":"Centros Comerciales Y Grandes Tiendas",
    "sg:phone":"+34 933 50 73 46",
    "sg:postcode":"08042",
    "sg:province":"Barcelona",
    "wof:name":"Xie  Xiaomian",
    "wof:placetype":"venue"
},
  "geometry": {"coordinates":[2.173648119,41.4469223022],"type":"Point"}
}