{
  "type": "Feature",
  "properties": {
    "addr:full":"Del Rio, 11 Escalona Toledo 45910",
    "addr:housenumber":"11",
    "addr:postcode":"45910",
    "addr:street":"Del Rio",
    "iso:country":"ES",
    "sg:address":"Del Rio, 11",
    "sg:city":"Escalona",
    "sg:orig_category":"Panader\u00cdas, Panader\u00cdas",
    "sg:phone":"+34 925 78 08 31",
    "sg:postcode":"45910",
    "sg:province":"Toledo",
    "wof:name":"Pastlona S.l.",
    "wof:placetype":"venue"
},
  "geometry": {"coordinates":[-4.4034180641,40.1653404236],"type":"Point"}
}