{
  "type": "Feature",
  "properties": {
    "addr:full":"Calle de San Lorenzo, 28 Alacant Alicante 03007",
    "addr:housenumber":"28",
    "addr:postcode":"03007",
    "addr:street":"Calle De San Lorenzo",
    "iso:country":"ES",
    "sg:address":"Calle de San Lorenzo, 28",
    "sg:city":"Alacant",
    "sg:orig_category":"Fabricaci\u00d3n, Importaci\u00d3n De L\u00c1mparas Y Bombillas",
    "sg:phone":"+34 965 10 07 35",
    "sg:postcode":"03007",
    "sg:province":"Alicante",
    "wof:name":"Lamparas Quevedo S.l.",
    "wof:placetype":"venue"
},
  "geometry": {"coordinates":[-0.5133829713,38.341594696],"type":"Point"}
}