{
  "type": "Feature",
  "properties": {
    "iso:country":"ES",
    "sg:address":"Calle de Pescaderia, 2",
    "sg:city":"Donostia-san Sebastian",
    "sg:classifiers":[
        {
            "category":"Tea Room",
            "subcategory":"None",
            "type":"Food & Drink"
        }
    ],
    "sg:phone":"+34 943 42 35 07",
    "sg:postcode":"20003",
    "sg:province":"Guip\u00f9zcoa",
    "sg:tags":[
        "snack"
    ],
    "wof:name":"Martinez Martinez Pilar",
    "wof:placetype":"venue"
},
  "geometry": {"coordinates":[-1.984326005,43.3234481812],"type":"Point"}
}