{
  "type": "Feature",
  "properties": {
    "addr:full":"Calle de Teatinos (de Los), 42 Coslada Madrid 28820",
    "addr:housenumber":"42",
    "addr:postcode":"28820",
    "addr:street":"Calle De Teatinos De Los",
    "iso:country":"ES",
    "sg:address":"Calle de Teatinos (de Los), 42",
    "sg:city":"Coslada",
    "sg:orig_category":"Ropa De Hogar (al Por Menor)",
    "sg:phone":"+34 916 74 02 27",
    "sg:postcode":"28820",
    "sg:province":"Madrid",
    "sg:website":"www.gastonydaniela.com",
    "wof:name":"Gaston Y Daniela S. A.",
    "wof:placetype":"venue"
},
  "geometry": {"coordinates":[-3.5362288952,40.441116333],"type":"Point"}
}