{
  "type": "Feature",
  "properties": {
    "iso:country":"ES",
    "sg:address":"Calle de Joaquin Fernandez Sestelo, 2",
    "sg:city":"Esfarrapada",
    "sg:orig_category":"Molduras, Junquillos, Listones Y Molduras Perforadas",
    "sg:phone":"+34 986 34 90 66",
    "sg:postcode":"36470",
    "sg:province":"Pontevedra",
    "wof:name":"Rodriguez Lorenzo Emilio",
    "wof:placetype":"venue"
},
  "geometry": {"coordinates":[-8.5587511063,42.1010551453],"type":"Point"}
}