{
  "type": "Feature",
  "properties": {
    "iso:country":"ES",
    "sg:address":"Calle de Covadonga, 25",
    "sg:city":"Lugo De Llanera",
    "sg:orig_category":"Talleres De Corte Y Confecci\u00d3n",
    "sg:phone":"+34 985 77 33 17",
    "sg:postcode":"33690",
    "sg:province":"Asturias",
    "wof:name":"Coslinait S.c",
    "wof:placetype":"venue"
},
  "geometry": {"coordinates":[-5.8175520897,43.4436454773],"type":"Point"}
}