{
  "type": "Feature",
  "properties": {
    "addr:full":"Avda Mare Nostrum, S/n Alacant Alicante 03007",
    "addr:housenumber":"s / n",
    "addr:postcode":"03007",
    "addr:street":"Avda Mare Nostrum",
    "iso:country":"ES",
    "sg:address":"Avda Mare Nostrum, S/n",
    "sg:city":"Alacant",
    "sg:orig_category":"Maquinaria Para Industrias Diversas",
    "sg:phone":"+34 965 28 45 18",
    "sg:postcode":"03007",
    "sg:province":"Alicante",
    "wof:name":"Talleres Mehiman S.l.",
    "wof:placetype":"venue"
},
  "geometry": {"coordinates":[-0.5239790082,38.3395462036],"type":"Point"}
}