{
  "type": "Feature",
  "properties": {
    "addr:full":"Plaz Mayor, S/n Ampuero Cantabria 39840",
    "addr:housenumber":"s / n",
    "addr:postcode":"39840",
    "addr:street":"Plaz Mayor",
    "iso:country":"ES",
    "sg:address":"Plaz Mayor, S/n",
    "sg:city":"Ampuero",
    "sg:orig_category":"Molduras, Junquillos, Listones Y Molduras Perforadas",
    "sg:phone":"+34 942 67 60 89",
    "sg:postcode":"39840",
    "sg:province":"Cantabria",
    "wof:name":"Sociedad Regional De Informatica S.a.",
    "wof:placetype":"venue"
},
  "geometry": {"coordinates":[-3.4166390896,43.3434791565],"type":"Point"}
}