{
  "type": "Feature",
  "properties": {
    "iso:country":"ES",
    "sg:address":"Avda Albalate, 7",
    "sg:city":"Andorra",
    "sg:orig_category":"Distribuci\u00d3n De Petr\u00d3leo Y Derivados",
    "sg:phone":"+34 978 84 20 14",
    "sg:postcode":"44500",
    "sg:province":"Teruel",
    "wof:name":"Estacion De Servicio Andorra S.l.",
    "wof:placetype":"venue"
},
  "geometry": {"coordinates":[-0.4457589984,40.9776535034],"type":"Point"}
}