{
  "type": "Feature",
  "properties": {
    "iso:country":"ES",
    "sg:address":"Pase Santa Maria De La Cabeza, 9",
    "sg:city":"Madrid",
    "sg:orig_category":"Ense\u00d1anza: Comercio, Gesti\u00d3n, Inform\u00c1tica",
    "sg:phone":"+34 915 27 29 54",
    "sg:postcode":"28045",
    "sg:province":"Madrid",
    "wof:name":"Estudios Sh Indexa S.l.",
    "wof:placetype":"venue"
},
  "geometry": {"coordinates":[-3.6945099831,40.4058837891],"type":"Point"}
}