{
  "type": "Feature",
  "properties": {
    "iso:country":"ES",
    "sg:address":"Calle de Francisco Moreno, 9",
    "sg:city":"San Juan De Mozarrifar",
    "sg:orig_category":"Alimentaci\u00d3n General (al Por Menor)",
    "sg:phone":"+34 976 58 74 85",
    "sg:postcode":"50820",
    "sg:province":"Zaragoza",
    "wof:name":"Alimentacionsanjuandemozarrifars.l.",
    "wof:placetype":"venue"
},
  "geometry": {"coordinates":[-0.8418040872,41.7175292969],"type":"Point"}
}