{
  "type": "Feature",
  "properties": {
    "iso:country":"ES",
    "sg:address":"Calle de Erribera, 20",
    "sg:city":"Ondarroa",
    "sg:orig_category":"Molduras, Junquillos, Listones Y Molduras Perforadas",
    "sg:phone":"+34 946 83 14 88",
    "sg:postcode":"48700",
    "sg:province":"Vizcaya",
    "wof:name":"Jesus Sainz Bengoa",
    "wof:placetype":"venue"
},
  "geometry": {"coordinates":[-2.4227170944,43.3202972412],"type":"Point"}
}