{
  "type": "Feature",
  "properties": {
    "addr:full":"Carrer de Barcelona, S/n S. Vicen\u00e7 Castellet Barcelona 08295",
    "addr:postcode":"08295",
    "addr:street":"Carrer De Barcelona S / N S. Vicenc\u0327;Barcelona",
    "iso:country":"ES",
    "sg:address":"Carrer de Barcelona, S/n",
    "sg:city":"S. Vicen\u00e7 Castellet",
    "sg:orig_category":"Polideportivos",
    "sg:phone":"+34 938 33 14 18",
    "sg:postcode":"08295",
    "sg:province":"Barcelona",
    "wof:name":"Ajuntament De Sant Vicen\u00e7 De Castellet",
    "wof:placetype":"venue"
},
  "geometry": {"coordinates":[1.8638734818,41.6630821228],"type":"Point"}
}