{
  "type": "Feature",
  "properties": {
    "addr:full":"Atva. Zaragoza-logro\u00f1o, 118 Casetas Zaragoza 50620",
    "addr:housenumber":"118",
    "addr:postcode":"50620",
    "addr:street":"Casetas",
    "iso:country":"ES",
    "sg:address":"Atva. Zaragoza-logro\u00f1o, 118",
    "sg:city":"Casetas",
    "sg:orig_category":"Molduras, Junquillos, Listones Y Molduras Perforadas",
    "sg:phone":"+34 976 77 22 07",
    "sg:postcode":"50620",
    "sg:province":"Zaragoza",
    "wof:name":"Perez Gimeno Rogelio",
    "wof:placetype":"venue"
},
  "geometry": {"coordinates":[-1.0303390026,41.7199440002],"type":"Point"}
}