{
  "type": "Feature",
  "properties": {
    "addr:full":"Pol. Santa Fe, S/n Cuarte Huerva Zaragoza 50410",
    "addr:housenumber":"s",
    "addr:postcode":"50410",
    "addr:street":"Pol. Santa Fe;/ N",
    "iso:country":"ES",
    "sg:address":"Pol. Santa Fe, S/n",
    "sg:city":"Cuarte Huerva",
    "sg:orig_category":"Producci\u00d3n, Venta De Productos De Agricultura Biol\u00d3gica",
    "sg:phone":"+34 976 50 50 22",
    "sg:postcode":"50410",
    "sg:province":"Zaragoza",
    "wof:name":"Alonso Gajon Javier",
    "wof:placetype":"venue"
},
  "geometry": {"coordinates":[-0.8765661716,41.6563491821],"type":"Point"}
}