{
  "type": "Feature",
  "properties": {
    "iso:country":"ES",
    "sg:address":"Carr Santa Anna, 3",
    "sg:city":"Estartit",
    "sg:orig_category":"Confecci\u00d3n De Trajes Para Se\u00d1oras",
    "sg:phone":"+34 972 75 14 25",
    "sg:postcode":"17258",
    "sg:province":"Girona",
    "wof:name":"Font Puig Rosa",
    "wof:placetype":"venue"
},
  "geometry": {"coordinates":[3.1878299713,42.0489959717],"type":"Point"}
}