{
  "type": "Feature",
  "properties": {
    "iso:country":"ES",
    "sg:address":"Calle de Carlos Marx, S/n",
    "sg:city":"Sevilla",
    "sg:orig_category":"Cervecer\u00cdas",
    "sg:phone":"+34 954 65 86 47",
    "sg:postcode":"41006",
    "sg:province":"Sevilla",
    "wof:name":"Lopez Gonzalez Fernando",
    "wof:placetype":"venue"
},
  "geometry": {"coordinates":[-5.9510612488,37.3816833496],"type":"Point"}
}