{
  "type": "Feature",
  "properties": {
    "addr:full":"Carrer de Vallespir, 13 S. Joan Despi Barcelona 08970",
    "addr:housenumber":"13",
    "addr:postcode":"08970",
    "addr:street":"Carrer De Vallespir;S. Joan Despi",
    "iso:country":"ES",
    "sg:address":"Carrer de Vallespir, 13",
    "sg:city":"S. Joan Despi",
    "sg:orig_category":"Radiocomunicaciones, Telefon\u00cda M\u00d3vil, Radiomensajer\u00cda: Servicios, Comercializaci\u00d3n",
    "sg:phone":"+34 934 57 97 10",
    "sg:postcode":"08970",
    "sg:province":"Barcelona",
    "sg:website":"www.falcon-radio.es",
    "wof:name":"Falcon Radio & Accessories Supply S.l.",
    "wof:placetype":"venue"
},
  "geometry": {"coordinates":[2.0594170094,41.3723945618],"type":"Point"}
}