{
  "type": "Feature",
  "properties": {
    "addr:full":"C/ Sant Domenec, 2 Cerdanyola Valles Barcelona 08290",
    "addr:housenumber":"2",
    "addr:postcode":"08290",
    "addr:street":"C / Sant Domenec;Valles Barcelona",
    "iso:country":"ES",
    "sg:address":"C/ Sant Domenec, 2",
    "sg:city":"Cerdanyola Valles",
    "sg:orig_category":"Inform\u00c1tica (estudios, Servicios, Asesor\u00cda, Formaci\u00d3n)",
    "sg:phone":"+34 935 92 00 95",
    "sg:postcode":"08290",
    "sg:province":"Barcelona",
    "wof:name":"Components Informatics Cerdanyola S.l.",
    "wof:placetype":"venue"
},
  "geometry": {"coordinates":[2.1433980465,41.4939651489],"type":"Point"}
}