{
  "type": "Feature",
  "properties": {
    "addr:full":"Pla\u00c7 Cal Font, 12 Igualada Barcelona 08700",
    "addr:housenumber":"12",
    "addr:postcode":"08700",
    "addr:street":"Cal Font",
    "iso:country":"ES",
    "sg:address":"Pla\u00c7 Cal Font, 12",
    "sg:city":"Igualada",
    "sg:orig_category":"Deportes N\u00c1uticos, Acu\u00c1ticos Y Subacu\u00c1ticos: Art\u00cdculos Y Equipo (al Por Menor)",
    "sg:phone":"+34 938 04 05 13",
    "sg:postcode":"08700",
    "sg:province":"Barcelona",
    "wof:name":"Makeupwear S.l.",
    "wof:placetype":"venue"
},
  "geometry": {"coordinates":[1.616552949,41.5815048218],"type":"Point"}
}