{
  "type": "Feature",
  "properties": {
    "addr:full":"Mijas Costa Malaga 289650",
    "addr:postcode":"289650",
    "iso:country":"ES",
    "sg:address":"Mijas Costa",
    "sg:city":"Malaga",
    "sg:classifiers":[
        {
            "category":"Professional",
            "subcategory":"Advertising",
            "type":"Services"
        }
    ],
    "sg:postcode":"289650",
    "sg:tags":[
        "web-design",
        "seo",
        "web-development",
        "databases"
    ],
    "sg:website":"http://www.olivosbydesign.com",
    "wof:name":"Olivos by Design",
    "wof:placetype":"venue"
},
  "geometry": {"coordinates":[-4.72689,36.492548],"type":"Point"}
}