{
  "type": "Feature",
  "properties": {
    "iso:country":"ES",
    "sg:address":"Rua Habitat, 17",
    "sg:city":"Perillo",
    "sg:orig_category":"Arquitectos",
    "sg:phone":"+34 981 63 63 02",
    "sg:postcode":"15172",
    "sg:province":"La Coru\u00f1a",
    "wof:name":"Rivera Martinez Jose",
    "wof:placetype":"venue"
},
  "geometry": {"coordinates":[-8.3740053177,43.3324584961],"type":"Point"}
}