{
  "type": "Feature",
  "properties": {
    "iso:country":"ES",
    "sg:address":"Carr Josep Coroleu, 75",
    "sg:city":"Vilanova I La Geltru",
    "sg:orig_category":"Agencias Y Agentes Comerciales, Representantes",
    "sg:phone":"+34 938 93 24 48",
    "sg:postcode":"08800",
    "sg:province":"Barcelona",
    "wof:name":"Rubia Anguita Alejandro De La",
    "wof:placetype":"venue"
},
  "geometry": {"coordinates":[1.7191200256,41.2225646973],"type":"Point"}
}