{
  "type": "Feature",
  "properties": {
    "addr:full":"Rua Manuel Lezon, 1 Celanova Ourense 32800",
    "addr:housenumber":"1",
    "addr:postcode":"32800",
    "addr:street":"Rua Manuel Lezon",
    "iso:country":"ES",
    "sg:address":"Rua Manuel Lezon, 1",
    "sg:city":"Celanova",
    "sg:orig_category":"Orquestas Cl\u00c1sicas, Asociaciones De M\u00dasica, Coros Y Corales",
    "sg:phone":"+34 988 43 18 77",
    "sg:postcode":"32800",
    "sg:province":"Ourense",
    "wof:name":"Banda Municipal De Musica De Celanova",
    "wof:placetype":"venue"
},
  "geometry": {"coordinates":[-7.9586448669,42.1490936279],"type":"Point"}
}