{
  "type": "Feature",
  "properties": {
    "iso:country":"ES",
    "sg:address":"Calle de Miguel Hernandez, 6",
    "sg:city":"Oca\u00f1a",
    "sg:orig_category":"Centros De Educaci\u00d3n Especial",
    "sg:phone":"+34 925 13 00 50",
    "sg:postcode":"45300",
    "sg:province":"Toledo",
    "wof:name":"Colegio Publico San Jose De Calasanz",
    "wof:placetype":"venue"
},
  "geometry": {"coordinates":[-3.4957690239,39.9542007446],"type":"Point"}
}