{
  "type": "Feature",
  "properties": {
    "iso:country":"ES",
    "sg:address":"Grup San Cristobal, 9",
    "sg:city":"Ansoain",
    "sg:orig_category":"Ebanister\u00cda",
    "sg:phone":"+34 948 38 24 45",
    "sg:postcode":"31013",
    "sg:province":"Navarra",
    "wof:name":"Carpinteria Garaikoetxea S.l.",
    "wof:placetype":"venue"
},
  "geometry": {"coordinates":[-1.6696590185,42.8440933228],"type":"Point"}
}