{
  "type": "Feature",
  "properties": {
    "addr:full":"La Encina, 129 Tarancon Cuenca 16400",
    "addr:housenumber":"129",
    "addr:postcode":"16400",
    "addr:street":"La Encina",
    "iso:country":"ES",
    "sg:address":"La Encina, 129",
    "sg:city":"Tarancon",
    "sg:orig_category":"Empresas De Carpinter\u00cda Met\u00c1lica",
    "sg:phone":"+34 969 32 28 17",
    "sg:postcode":"16400",
    "sg:province":"Cuenca",
    "wof:name":"Gimser Pvc S.l.",
    "wof:placetype":"venue"
},
  "geometry": {"coordinates":[-3.018862009,40.0088691711],"type":"Point"}
}