{
  "type": "Feature",
  "properties": {
    "addr:full":"Calle de Martin Villa, 1 Sevilla Sevilla 41003",
    "addr:housenumber":"1",
    "addr:postcode":"41003",
    "addr:street":"Calle De Martin Villa",
    "iso:country":"ES",
    "sg:address":"Calle de Martin Villa, 1",
    "sg:city":"Sevilla",
    "sg:orig_category":"Notarios",
    "sg:phone":"+34 954 22 40 03",
    "sg:postcode":"41003",
    "sg:province":"Sevilla",
    "wof:name":"Peche Rubio Luis",
    "wof:placetype":"venue"
},
  "geometry": {"coordinates":[-5.9937992096,37.392906189],"type":"Point"}
}