{
  "type": "Feature",
  "properties": {
    "addr:full":"Avda Monforte De Lemos, 36 Madrid Madrid 28...",
    "addr:housenumber":"36;28 ...",
    "addr:postcode":"madrid",
    "addr:street":"Avda Monforte De Lemos;Madrid",
    "iso:country":"ES",
    "sg:address":"Avda Monforte De Lemos, 36",
    "sg:city":"Madrid",
    "sg:orig_category":"M\u00c1quinas De Escribir, M\u00c1quinas De Oficina (al Por Menor, Reparaci\u00d3n)",
    "sg:phone":"+34 913 78 00 77",
    "sg:postcode":"28...",
    "sg:province":"Madrid",
    "wof:name":"Sistemas De Oficina De Fm-2 S.a.",
    "wof:placetype":"venue"
},
  "geometry": {"coordinates":[-3.7086570263,40.4786834717],"type":"Point"}
}