{
  "type": "Feature",
  "properties": {
    "iso:country":"ES",
    "sg:address":"Calle de Se\u00d1era, 1",
    "sg:city":"Poligono Ind. Mediterraneo",
    "sg:orig_category":"Art\u00cdculos De Limpieza Y De Cocina (fabricaci\u00d3n, Al Por Mayor)",
    "sg:phone":"+34 961 40 10 01",
    "sg:postcode":"46560",
    "sg:province":"Valencia",
    "sg:website":"www.sumilimp.com",
    "wof:name":"Suministros Industriales De Limpieza Sunilimp S.l.",
    "wof:placetype":"venue"
},
  "geometry": {"coordinates":[-0.3252330124,39.5581474304],"type":"Point"}
}