{
  "type": "Feature",
  "properties": {
    "iso:country":"ES",
    "sg:address":"Calle de Resa, 4",
    "sg:city":"Villarrobledo",
    "sg:orig_category":"Art\u00cdculos De Regalo (al Por Menor)",
    "sg:phone":"+34 967 14 63 13",
    "sg:postcode":"02600",
    "sg:province":"Albacete",
    "wof:name":"Cabrera Sainz Pilar",
    "wof:placetype":"venue"
},
  "geometry": {"coordinates":[-2.6035089493,39.2634124756],"type":"Point"}
}