{
  "type": "Feature",
  "properties": {
    "addr:full":"Calle de Amnistia, 1 Madrid Madrid 28013",
    "addr:housenumber":"1",
    "addr:postcode":"28013",
    "addr:street":"Calle De Amnistia",
    "iso:country":"ES",
    "sg:address":"Calle de Amnistia, 1",
    "sg:city":"Madrid",
    "sg:orig_category":"Alquiler De V\u00cddeo",
    "sg:phone":"+34 915 41 87 30",
    "sg:postcode":"28013",
    "sg:province":"Madrid",
    "sg:website":"www.septimoartedigital.com",
    "wof:name":"Maga Distribuidora Sl",
    "wof:placetype":"venue"
},
  "geometry": {"coordinates":[-3.710100174,40.4173316956],"type":"Point"}
}