{
  "type": "Feature",
  "properties": {
    "addr:full":"Carr De Maians, 38 Ontinyent Valencia 46870",
    "addr:housenumber":"38",
    "addr:postcode":"46870",
    "addr:street":"Carr De Maians",
    "iso:country":"ES",
    "sg:address":"Carr De Maians, 38",
    "sg:city":"Ontinyent",
    "sg:orig_category":"Bisuter\u00cda, Joyer\u00cda, Relojer\u00cda (al Por Menor)",
    "sg:phone":"+34 962 38 12 02",
    "sg:postcode":"46870",
    "sg:province":"Valencia",
    "wof:name":"Hijos De Francisco Pla S.l.",
    "wof:placetype":"venue"
},
  "geometry": {"coordinates":[-0.6030989885,38.8258895874],"type":"Point"}
}