{
  "type": "Feature",
  "properties": {
    "iso:country":"ES",
    "sg:address":"Calle de Ribera De Las Almadrabillas, 5",
    "sg:city":"Almeria",
    "sg:orig_category":"Promotores Constructores",
    "sg:phone":"+34 950 28 03 57",
    "sg:postcode":"04004",
    "sg:province":"Almer\u00eda",
    "wof:name":"Fircosa",
    "wof:placetype":"venue"
},
  "geometry": {"coordinates":[-2.46302104,36.8335266113],"type":"Point"}
}