{
  "type": "Feature",
  "properties": {
    "iso:country":"ES",
    "sg:address":"Calle de Alvaro De Bazan, 17",
    "sg:city":"Guadix",
    "sg:orig_category":"Muebles, Minoristas",
    "sg:phone":"+34 958 66 32 86",
    "sg:postcode":"18500",
    "sg:province":"Granada",
    "wof:name":"Muebles Santa Ana De Guadix S. L.",
    "wof:placetype":"venue"
},
  "geometry": {"coordinates":[-3.131380558,37.3011283875],"type":"Point"}
}