{
  "type": "Feature",
  "properties": {
    "iso:country":"ES",
    "sg:address":"Calle de Itxesi, S/n",
    "sg:city":"Uharte-arakil",
    "sg:orig_category":"Asociaciones Y Clubs Deportivos",
    "sg:phone":"+34 948 46 41 93",
    "sg:postcode":"31840",
    "sg:province":"Navarra",
    "wof:name":"Sociedad Cultural Deportiva Recreativa Aralar Mendi",
    "wof:placetype":"venue"
},
  "geometry": {"coordinates":[-1.972342968,42.9146766663],"type":"Point"}
}