{
  "type": "Feature",
  "properties": {
    "addr:full":"San Pedro Kalea, 9 Bergara Guip\u00f9zcoa 20570",
    "addr:housenumber":"9",
    "addr:postcode":"20570",
    "addr:street":"San Pedro Kalea;Guipu\u0300Zcoa",
    "iso:country":"ES",
    "sg:address":"San Pedro Kalea, 9",
    "sg:city":"Bergara",
    "sg:orig_category":"Panader\u00cdas, Panader\u00cdas",
    "sg:phone":"+34 943 76 10 51",
    "sg:postcode":"20570",
    "sg:province":"Guip\u00f9zcoa",
    "wof:name":"Pasteleria Larra\u00f1aga, Cb",
    "wof:placetype":"venue"
},
  "geometry": {"coordinates":[-2.4128708839,43.1163253784],"type":"Point"}
}