{
  "type": "Feature",
  "properties": {
    "iso:country":"ES",
    "sg:address":"Calle de Felipe Ii, 116",
    "sg:city":"Yuncos",
    "sg:orig_category":"Juguetes Y Juegos (al Por Mayor)",
    "sg:phone":"+34 925 55 76 39",
    "sg:postcode":"45210",
    "sg:province":"Toledo",
    "wof:name":"Taller Anesauto S.l.",
    "wof:placetype":"venue"
},
  "geometry": {"coordinates":[-3.870609045,40.0945091248],"type":"Point"}
}