{
  "type": "Feature",
  "properties": {
    "iso:country":"ES",
    "sg:address":"Carrer de Samalus, 10",
    "sg:city":"Garriga",
    "sg:orig_category":"Ropa Para Beb\u00c9s Y Ni\u00d1os (confecci\u00d3n, Al Por Mayor)",
    "sg:phone":"+34 938 71 90 86",
    "sg:postcode":"08530",
    "sg:province":"Barcelona",
    "wof:name":"Confecciones Lacos S.c.p.",
    "wof:placetype":"venue"
},
  "geometry": {"coordinates":[2.2867820263,41.6844711304],"type":"Point"}
}