{
  "type": "Feature",
  "properties": {
    "iso:country":"ES",
    "sg:address":"Calle de Lerida, S/n",
    "sg:city":"Binefar",
    "sg:orig_category":"Mec\u00c1nico Del Autom\u00d3vil",
    "sg:phone":"+34 974 42 90 94",
    "sg:postcode":"22500",
    "sg:province":"Huesca",
    "wof:name":"Automoviles Massauto S.l.",
    "wof:placetype":"venue"
},
  "geometry": {"coordinates":[0.3007358909,41.8500823975],"type":"Point"}
}