{
  "type": "Feature",
  "properties": {
    "addr:full":"Carr Tortosa, 142 Badalona Barcelona 08918",
    "addr:housenumber":"142",
    "addr:postcode":"08918",
    "addr:street":"Carr Tortosa",
    "iso:country":"ES",
    "sg:address":"Carr Tortosa, 142",
    "sg:city":"Badalona",
    "sg:orig_category":"Molduras, Junquillos, Listones Y Molduras Perforadas",
    "sg:phone":"+34 933 97 29 25",
    "sg:postcode":"08918",
    "sg:province":"Barcelona",
    "wof:name":"Romeo Terranegra Bruno",
    "wof:placetype":"venue"
},
  "geometry": {"coordinates":[2.2356948853,41.4366874695],"type":"Point"}
}