{
  "type": "Feature",
  "properties": {
    "addr:full":"Calle de Cuevas De Almanzora, 187 Madrid Madrid 28033",
    "addr:housenumber":"187",
    "addr:postcode":"28033",
    "addr:street":"Calle De Cuevas De Almanzora",
    "iso:country":"ES",
    "sg:address":"Calle de Cuevas De Almanzora, 187",
    "sg:city":"Madrid",
    "sg:orig_category":"Centros Empresariales",
    "sg:phone":"+34 913 02 87 81",
    "sg:postcode":"28033",
    "sg:province":"Madrid",
    "wof:name":"Servicios Profesionales Just In Time S.l",
    "wof:placetype":"venue"
},
  "geometry": {"coordinates":[-3.6584661007,40.4773635864],"type":"Point"}
}