{
  "type": "Feature",
  "properties": {
    "addr:full":"Carrer de Brasil, 43 Amposta Tarragona 43870",
    "addr:housenumber":"43",
    "addr:postcode":"43870",
    "addr:street":"Carrer De Brasil",
    "iso:country":"ES",
    "sg:address":"Carrer de Brasil, 43",
    "sg:city":"Amposta",
    "sg:orig_category":"Promotores Constructores",
    "sg:phone":"+34 977 70 10 42",
    "sg:postcode":"43870",
    "sg:province":"Tarragona",
    "wof:name":"Construccions Sebastian Ortega S.l.",
    "wof:placetype":"venue"
},
  "geometry": {"coordinates":[0.5740770102,40.7066383362],"type":"Point"}
}