{
  "type": "Feature",
  "properties": {
    "iso:country":"ES",
    "sg:address":"Calle de Rey (del), 20",
    "sg:city":"San Lorenzo De El Escorial",
    "sg:orig_category":"Loter\u00cda Y T\u00d3mbola",
    "sg:phone":"+34 918 90 43 31",
    "sg:postcode":"28200",
    "sg:province":"Madrid",
    "wof:name":"Herranz Gomez Juan Carlos",
    "wof:placetype":"venue"
},
  "geometry": {"coordinates":[-4.1467452049,40.5913200378],"type":"Point"}
}