{
  "type": "Feature",
  "properties": {
    "addr:full":"Plaz Maestro Chueca, 13 Albacete Albacete 02005",
    "addr:housenumber":"13",
    "addr:postcode":"02005",
    "addr:street":"Plaz Maestro Chueca",
    "iso:country":"ES",
    "sg:address":"Plaz Maestro Chueca, 13",
    "sg:city":"Albacete",
    "sg:orig_category":"Molduras, Junquillos, Listones Y Molduras Perforadas",
    "sg:phone":"+34 967 21 92 19",
    "sg:postcode":"02005",
    "sg:province":"Albacete",
    "wof:name":"Heras Javega Rufina",
    "wof:placetype":"venue"
},
  "geometry": {"coordinates":[-1.8662689924,39.0014305115],"type":"Point"}
}