{
  "type": "Feature",
  "properties": {
    "addr:full":"Avda Tierra Llana, 83 Vilalba Lugo 27800",
    "addr:housenumber":"83",
    "addr:postcode":"27800",
    "addr:street":"Avda Tierra Llana",
    "iso:country":"ES",
    "sg:address":"Avda Tierra Llana, 83",
    "sg:city":"Vilalba",
    "sg:orig_category":"Mensajer\u00cda Express, Portes Internacionales",
    "sg:phone":"+34 982 51 12 45",
    "sg:postcode":"27800",
    "sg:province":"Lugo",
    "sg:website":"www.mrv.es",
    "wof:name":"Guntin Garcia Maria Rocio",
    "wof:placetype":"venue"
},
  "geometry": {"coordinates":[-7.6733498573,43.2951927185],"type":"Point"}
}