{
  "type": "Feature",
  "properties": {
    "addr:full":"Avda Fabian Escribano, 12 Beniajan Murcia 30570",
    "addr:housenumber":"12",
    "addr:postcode":"30570",
    "addr:street":"Avda Fabian Escribano",
    "iso:country":"ES",
    "sg:address":"Avda Fabian Escribano, 12",
    "sg:city":"Beniajan",
    "sg:orig_category":"Cajas Para Embalar",
    "sg:phone":"+34 968 83 71 04",
    "sg:postcode":"30570",
    "sg:province":"Murcia",
    "wof:name":"Cajamar",
    "wof:placetype":"venue"
},
  "geometry": {"coordinates":[-1.07150805,37.9755935669],"type":"Point"}
}