{
  "type": "Feature",
  "properties": {
    "iso:country":"ES",
    "sg:address":"Monasterio Iranzu, 1",
    "sg:city":"Iru\u00f1a",
    "sg:orig_category":"Agencias De Viajes",
    "sg:phone":"+34 948 17 48 65",
    "sg:postcode":"31011",
    "sg:province":"Navarra",
    "wof:name":"Ana Lasheras Y Luis Cruchaga C.b.",
    "wof:placetype":"venue"
},
  "geometry": {"coordinates":[-1.6621387005,42.8150863647],"type":"Point"}
}