{
  "type": "Feature",
  "properties": {
    "iso:country":"ES",
    "sg:address":"Carrer de Olivera, 20",
    "sg:city":"Barcelona",
    "sg:orig_category":"Peluqueros: De Se\u00d1oras",
    "sg:phone":"+34 934 41 52 78",
    "sg:postcode":"08004",
    "sg:province":"Barcelona",
    "wof:name":"Canto Diez Remedios",
    "wof:placetype":"venue"
},
  "geometry": {"coordinates":[2.1593060493,41.3737068176],"type":"Point"}
}