{
  "type": "Feature",
  "properties": {
    "iso:country":"ES",
    "sg:address":"Av Maresme (del), 65",
    "sg:city":"Mataro",
    "sg:orig_category":"Agentes, Concesionarios Y Sucursales De Veh\u00cdculos",
    "sg:phone":"+34 937 98 75 37",
    "sg:postcode":"08302",
    "sg:province":"Barcelona",
    "sg:website":"www.bellmunt.citroen.es",
    "wof:name":"Bellmunt S.a.",
    "wof:placetype":"venue"
},
  "geometry": {"coordinates":[2.4390211105,41.5307922363],"type":"Point"}
}