{
  "type": "Feature",
  "properties": {
    "iso:country":"ES",
    "sg:address":"Calle de Borrull, 13",
    "sg:city":"Valencia",
    "sg:orig_category":"Inmobiliaria (agencias)",
    "sg:phone":"+34 963 92 58 51",
    "sg:postcode":"46008",
    "sg:province":"Valencia",
    "wof:name":"Maclavi Gestion S.l.",
    "wof:placetype":"venue"
},
  "geometry": {"coordinates":[-0.3851802051,39.4746246338],"type":"Point"}
}