{
  "type": "Feature",
  "properties": {
    "iso:country":"ES",
    "sg:address":"Calle de Martires De Simancas, 5",
    "sg:city":"Zaragoza",
    "sg:orig_category":"Peluqueros: De Se\u00d1oras",
    "sg:phone":"+34 976 27 23 27",
    "sg:postcode":"50007",
    "sg:province":"Zaragoza",
    "wof:name":"Alvarez Monteserin Baltasar",
    "wof:placetype":"venue"
},
  "geometry": {"coordinates":[-0.8784539104,41.6328582764],"type":"Point"}
}