{
  "type": "Feature",
  "properties": {
    "addr:full":"Barr Escuelas (las), S/n Pedre\u00f1a Cantabria 39130",
    "addr:postcode":"39130",
    "addr:street":"Las S / N",
    "iso:country":"ES",
    "sg:address":"Barr Escuelas (las), S/n",
    "sg:city":"Pedre\u00f1a",
    "sg:orig_category":"Peluquer\u00cdas, Peluquer\u00cda Mixta",
    "sg:phone":"+34 942 50 10 55",
    "sg:postcode":"39130",
    "sg:province":"Cantabria",
    "wof:name":"Portilla Quintana Bego\u00f1a",
    "wof:placetype":"venue"
},
  "geometry": {"coordinates":[-3.7695939541,43.4376564026],"type":"Point"}
}