{
  "type": "Feature",
  "properties": {
    "iso:country":"ES",
    "sg:address":"Calle de Maria Auxiliadora, 33",
    "sg:city":"Moron Frontera",
    "sg:orig_category":"Carnicer\u00cdas, Carnicer\u00cdas",
    "sg:phone":"+34 955 85 32 72",
    "sg:postcode":"41530",
    "sg:province":"Sevilla",
    "wof:name":"I. C. Hermanos Salguero S.l.",
    "wof:placetype":"venue"
},
  "geometry": {"coordinates":[-5.4592089653,37.119556427],"type":"Point"}
}