{
  "type": "Feature",
  "properties": {
    "iso:country":"ES",
    "sg:address":"Calle de San Marcial, 32",
    "sg:city":"Donostia-san Sebastian",
    "sg:orig_category":"Zapatos (al Por Menor)",
    "sg:phone":"+34 943 29 01 53",
    "sg:postcode":"20005",
    "sg:province":"Guip\u00f9zcoa",
    "wof:name":"Lopez Gonzalez Arcadi",
    "wof:placetype":"venue"
},
  "geometry": {"coordinates":[-1.9826029539,43.3186759949],"type":"Point"}
}