{
  "type": "Feature",
  "properties": {
    "iso:country":"ES",
    "sg:address":"Ruel Volta Do Castro (da), 1",
    "sg:city":"Santiago De Compostela",
    "sg:orig_category":"Venta, Instalaci\u00d3n, Reparaci\u00d3n De Antenas Para Televisi\u00d3n",
    "sg:phone":"+34 981 52 22 15",
    "sg:postcode":"15706",
    "sg:province":"A Coru\u00f1a",
    "wof:name":"Televes S.a.",
    "wof:placetype":"venue"
},
  "geometry": {"coordinates":[-8.5621271133,42.8675956726],"type":"Point"}
}