{
  "type": "Feature",
  "properties": {
    "addr:full":"Calle de Tumaco, 6 Madrid Madrid 28027",
    "addr:housenumber":"6",
    "addr:postcode":"28027",
    "addr:street":"Calle De Tumaco",
    "iso:country":"ES",
    "sg:address":"Calle de Tumaco, 6",
    "sg:city":"Madrid",
    "sg:orig_category":"Laboratorios Y Cl\u00cdnicas Veterinarias",
    "sg:phone":"+34 917 41 17 60",
    "sg:postcode":"28027",
    "sg:province":"Madrid",
    "wof:name":"Dalivet Servicios Veterinarios S.l.",
    "wof:placetype":"venue"
},
  "geometry": {"coordinates":[-3.6352989674,40.4449615479],"type":"Point"}
}