{
  "type": "Feature",
  "properties": {
    "iso:country":"ES",
    "sg:address":"Calle de Fruela, 2",
    "sg:city":"Madrid",
    "sg:orig_category":"Peluqueros: De Se\u00d1oras",
    "sg:phone":"+34 915 26 26 74",
    "sg:postcode":"28011",
    "sg:province":"Madrid",
    "wof:name":"Mari Luz Estilistas S.l.",
    "wof:placetype":"venue"
},
  "geometry": {"coordinates":[-3.7304930687,40.4131736755],"type":"Point"}
}