{
  "type": "Feature",
  "properties": {
    "addr:full":"Avda Cruz Roja Espa\u00d1ola (de La), S/n Cuenca Cuenca 16002",
    "addr:housenumber":"/ n",
    "addr:postcode":"16002",
    "addr:street":"Avda Cruz Roja Espan\u0303Ola De La S",
    "iso:country":"ES",
    "sg:address":"Avda Cruz Roja Espa\u00d1ola (de La), S/n",
    "sg:city":"Cuenca",
    "sg:orig_category":"Ambulancias",
    "sg:phone":"+34 969 23 39 22",
    "sg:postcode":"16002",
    "sg:province":"Cuenca",
    "wof:name":"Ambulancias Conquenses S.l",
    "wof:placetype":"venue"
},
  "geometry": {"coordinates":[-2.1676907539,40.073348999],"type":"Point"}
}