{
  "type": "Feature",
  "properties": {
    "iso:country":"ES",
    "sg:address":"Av. Isaac Peral, 2",
    "sg:city":"Valdeavero",
    "sg:orig_category":"Material Y Herramientas Agr\u00cdcolas",
    "sg:phone":"+34 918 86 45 83",
    "sg:postcode":"28816",
    "sg:province":"Madrid",
    "wof:name":"Agromecanica Cano S.l.",
    "wof:placetype":"venue"
},
  "geometry": {"coordinates":[-3.344426,40.625252],"type":"Point"}
}