{
  "type": "Feature",
  "properties": {
    "addr:full":"Calle de Huerta (la), 17 Alcorcon Madrid 28921",
    "addr:housenumber":"17",
    "addr:postcode":"28921",
    "addr:street":"Calle De Huerta La",
    "iso:country":"ES",
    "sg:address":"Calle de Huerta (la), 17",
    "sg:city":"Alcorcon",
    "sg:orig_category":"Bisuter\u00cda, Joyer\u00cda, Relojer\u00cda (al Por Menor)",
    "sg:phone":"+34 916 41 67 00",
    "sg:postcode":"28921",
    "sg:province":"Madrid",
    "wof:name":"Escribano Gomez Jaime",
    "wof:placetype":"venue"
},
  "geometry": {"coordinates":[-3.8249390125,40.3449897766],"type":"Point"}
}