{
  "type": "Feature",
  "properties": {
    "addr:full":"Calle de Obanos, S/n Madrid Madrid 28050",
    "addr:housenumber":"s / n",
    "addr:postcode":"28050",
    "addr:street":"Calle De Obanos",
    "iso:country":"ES",
    "sg:address":"Calle de Obanos, S/n",
    "sg:city":"Madrid",
    "sg:orig_category":"Promotores Constructores",
    "sg:phone":"+34 913 58 83 24",
    "sg:postcode":"28050",
    "sg:province":"Madrid",
    "wof:name":"Fcc Construccion S.a.",
    "wof:placetype":"venue"
},
  "geometry": {"coordinates":[-3.6758520603,40.4980583191],"type":"Point"}
}