{
  "type": "Feature",
  "properties": {
    "addr:full":"Plaz Pontevedra, 12 Coru\u00d1a La Coru\u00f1a 15003",
    "addr:housenumber":"12",
    "addr:postcode":"15003",
    "addr:street":"Pontevedra;La Corun\u0303A",
    "iso:country":"ES",
    "sg:address":"Plaz Pontevedra, 12",
    "sg:city":"Coru\u00d1a",
    "sg:orig_category":"Peluqueros: De Se\u00d1oras",
    "sg:phone":"+34 981 22 63 25",
    "sg:postcode":"15003",
    "sg:province":"La Coru\u00f1a",
    "wof:name":"Rodriguez Alvarez Maria Fe",
    "wof:placetype":"venue"
},
  "geometry": {"coordinates":[-8.4063863754,43.3679389954],"type":"Point"}
}