{
  "type": "Feature",
  "properties": {
    "addr:full":"Carrer de L'escorial, 150 Barcelona Barcelona 08024",
    "addr:housenumber":"150",
    "addr:postcode":"08024",
    "addr:street":"Carrer De L'Escorial",
    "iso:country":"ES",
    "sg:address":"Carrer de L'escorial, 150",
    "sg:city":"Barcelona",
    "sg:orig_category":"Farmacias",
    "sg:phone":"+34 932 13 30 55",
    "sg:postcode":"08024",
    "sg:province":"Barcelona",
    "wof:name":"Soler Cuyas Inmaculada",
    "wof:placetype":"venue"
},
  "geometry": {"coordinates":[2.1590769291,41.4097061157],"type":"Point"}
}