{
  "type": "Feature",
  "properties": {
    "addr:full":"La Garganta, 2 Oliva De Plasencia C\u00e1ceres 10667",
    "addr:housenumber":"2",
    "addr:postcode":"10667",
    "addr:street":"La Garganta;Ca\u0301Ceres",
    "iso:country":"ES",
    "sg:address":"La Garganta, 2",
    "sg:city":"Oliva De Plasencia",
    "sg:orig_category":"Asociaciones Humanitarias, De Cooperaci\u00d3n, De Acci\u00d3n Social",
    "sg:phone":"+34 927 19 90 37",
    "sg:postcode":"10667",
    "sg:province":"C\u00e1ceres",
    "wof:name":"Centro Reto",
    "wof:placetype":"venue"
},
  "geometry": {"coordinates":[-6.0863289833,40.1122360229],"type":"Point"}
}