{
  "type": "Feature",
  "properties": {
    "iso:country":"ES",
    "sg:address":"Ildefonso Gurrutxaga, 5",
    "sg:city":"Azpeitia",
    "sg:orig_category":"Ropa Para Caballeros (al Por Menor)",
    "sg:phone":"+34 943 08 03 58",
    "sg:postcode":"20730",
    "sg:province":"Guip\u00f9zcoa",
    "wof:name":"Ainhoa Albizu Lizaso Y Otra C.b",
    "wof:placetype":"venue"
},
  "geometry": {"coordinates":[-2.2663440704,43.1814308167],"type":"Point"}
}