{
  "type": "Feature",
  "properties": {
    "addr:full":"Ctra Arbucies, 22 S. Hilari Sacalm Girona 17403",
    "addr:housenumber":"22",
    "addr:postcode":"17403",
    "addr:street":"Ctra Arbucies;S. Hilari",
    "iso:country":"ES",
    "sg:address":"Ctra Arbucies, 22",
    "sg:city":"S. Hilari Sacalm",
    "sg:orig_category":"Empresas De Carpinter\u00cda De Madera",
    "sg:phone":"+34 972 86 90 29",
    "sg:postcode":"17403",
    "sg:province":"Girona",
    "wof:name":"Andreu S.l.",
    "wof:placetype":"venue"
},
  "geometry": {"coordinates":[2.5118098259,41.8781509399],"type":"Point"}
}