{
  "type": "Feature",
  "properties": {
    "iso:country":"ES",
    "sg:address":"Calle de Avila, 4",
    "sg:city":"Salamanca",
    "sg:orig_category":"M\u00c9dicos: Estomatolog\u00cda",
    "sg:phone":"+34 923 25 80 55",
    "sg:postcode":"37004",
    "sg:province":"Salamanca",
    "wof:name":"Gonzalez Gonzalez Jesus Maria",
    "wof:placetype":"venue"
},
  "geometry": {"coordinates":[-5.6539096832,40.9724273682],"type":"Point"}
}