{
  "type": "Feature",
  "properties": {
    "addr:full":"Ganzo, S/n Torrelavega Cantabria 39300",
    "addr:housenumber":"s / n",
    "addr:postcode":"39300",
    "addr:street":"Ganzo",
    "iso:country":"ES",
    "sg:address":"Ganzo, S/n",
    "sg:city":"Torrelavega",
    "sg:orig_category":"Imprenta",
    "sg:phone":"+34 942 80 79 01",
    "sg:postcode":"39300",
    "sg:province":"Cantabria",
    "wof:name":"Papelera De Besaya S.l.",
    "wof:placetype":"venue"
},
  "geometry": {"coordinates":[-4.065527916,43.3575172424],"type":"Point"}
}