{
  "type": "Feature",
  "properties": {
    "iso:country":"ES",
    "sg:address":"Carrer de Mossen Miquel Amoros, 3",
    "sg:city":"Altafulla",
    "sg:orig_category":"Institutos De Belleza",
    "sg:phone":"+34 977 65 20 27",
    "sg:postcode":"43893",
    "sg:province":"Tarragona",
    "wof:name":"Asensio Postigo Maria Neus",
    "wof:placetype":"venue"
},
  "geometry": {"coordinates":[1.3747024536,41.1415901184],"type":"Point"}
}