{
  "type": "Feature",
  "properties": {
    "iso:country":"ES",
    "sg:address":"Calle de Antonio Lopez, 149",
    "sg:city":"Madrid",
    "sg:orig_category":"Chapister\u00cda",
    "sg:phone":"+34 914 75 25 07",
    "sg:postcode":"28026",
    "sg:province":"Madrid",
    "wof:name":"Talleres Arevalillo S.a.",
    "wof:placetype":"venue"
},
  "geometry": {"coordinates":[-3.6985647678,40.3875350952],"type":"Point"}
}