{
  "type": "Feature",
  "properties": {
    "addr:full":"Calle de Do\u00d1a Constanza, 13 Santa Lucia Murcia 30202",
    "addr:housenumber":"13",
    "addr:postcode":"30202",
    "addr:street":"Calle De Don\u0303A Constanza",
    "iso:country":"ES",
    "sg:address":"Calle de Do\u00d1a Constanza, 13",
    "sg:city":"Santa Lucia",
    "sg:orig_category":"Centros Empresariales",
    "sg:phone":"+34 968 52 73 34",
    "sg:postcode":"30202",
    "sg:province":"Murcia",
    "wof:name":"Hernandez Aguado Manuel",
    "wof:placetype":"venue"
},
  "geometry": {"coordinates":[-0.968477428,37.6024284363],"type":"Point"}
}