{
  "type": "Feature",
  "properties": {
    "addr:full":"Arana-goikoa Kalea, 5 Azpeitia Guip\u00f9zcoa 20730",
    "addr:housenumber":"5",
    "addr:postcode":"20730",
    "addr:street":"Arana-Goikoa Kalea;Guipu\u0300Zcoa",
    "iso:country":"ES",
    "sg:address":"Arana-goikoa Kalea, 5",
    "sg:city":"Azpeitia",
    "sg:orig_category":"Ense\u00d1anza Variada",
    "sg:phone":"+34 943 15 70 66",
    "sg:postcode":"20730",
    "sg:province":"Guip\u00f9zcoa",
    "sg:website":"www.urolalde.com",
    "wof:name":"Urolalde S.l.",
    "wof:placetype":"venue"
},
  "geometry": {"coordinates":[-2.2638750076,43.1857795715],"type":"Point"}
}