{
  "type": "Feature",
  "properties": {
    "iso:country":"ES",
    "sg:address":"Calle de Molino, 6",
    "sg:city":"Ronda",
    "sg:orig_category":"Imprenta",
    "sg:phone":"+34 952 87 27 93",
    "sg:postcode":"29400",
    "sg:province":"M\u00e1laga",
    "wof:name":"Imprenta Ronda Grafica S.l.",
    "wof:placetype":"venue"
},
  "geometry": {"coordinates":[-5.165954113,36.7438392639],"type":"Point"}
}