{
  "type": "Feature",
  "properties": {
    "iso:country":"ES",
    "sg:address":"Carr Gran, 45",
    "sg:city":"Castell",
    "sg:orig_category":"Reposter\u00cdas",
    "sg:phone":"+34 971 35 21 02",
    "sg:postcode":"07720",
    "sg:province":"Islas Baleares",
    "wof:name":"La Unica De Ca'n Senyalet S.l.",
    "wof:placetype":"venue"
},
  "geometry": {"coordinates":[4.2850251198,39.8720703125],"type":"Point"}
}