{
  "type": "Feature",
  "properties": {
    "iso:country":"ES",
    "sg:address":"Rua Juan Xxiii, 3",
    "sg:city":"Ourense",
    "sg:orig_category":"Florister\u00cdas",
    "sg:phone":"+34 988 21 08 61",
    "sg:postcode":"32003",
    "sg:province":"Ourense",
    "wof:name":"De Dios Manso Jesus",
    "wof:placetype":"venue"
},
  "geometry": {"coordinates":[-7.8662590981,42.3402366638],"type":"Point"}
}