{
  "type": "Feature",
  "properties": {
    "iso:country":"ES",
    "sg:address":"Calle de Palacio, 4",
    "sg:city":"Donostia-san Sebastian",
    "sg:orig_category":"Asociaciones, Organismos Culturales Y Socioeducativos",
    "sg:phone":"+34 943 21 54 87",
    "sg:postcode":"20008",
    "sg:province":"Guip\u00f9zcoa",
    "wof:name":"Asociacion V-2",
    "wof:placetype":"venue"
},
  "geometry": {"coordinates":[-1.9981906414,43.3115615845],"type":"Point"}
}