{
  "type": "Feature",
  "properties": {
    "addr:full":"Avda Gran Via, 134 Vigo Pontevedra 36203",
    "addr:housenumber":"134",
    "addr:postcode":"36203",
    "addr:street":"Avda Gran Via",
    "iso:country":"ES",
    "sg:address":"Avda Gran Via, 134",
    "sg:city":"Vigo",
    "sg:orig_category":"Agencias Y Agentes Comerciales, Representantes",
    "sg:phone":"+34 986 41 58 39",
    "sg:postcode":"36203",
    "sg:province":"Pontevedra",
    "wof:name":"Suarez Tamargo Jose Ignacio",
    "wof:placetype":"venue"
},
  "geometry": {"coordinates":[-8.725356102,42.2227783203],"type":"Point"}
}