{
  "type": "Feature",
  "properties": {
    "iso:country":"ES",
    "sg:address":"Calle de General Riera, 40",
    "sg:city":"Palma",
    "sg:orig_category":"Delineantes",
    "sg:phone":"+34 971 29 25 55",
    "sg:postcode":"07003",
    "sg:province":"Islas Baleares",
    "wof:name":"Sa Tenda De Ponent S.l.",
    "wof:placetype":"venue"
},
  "geometry": {"coordinates":[2.6472499371,39.5817451477],"type":"Point"}
}