{
  "type": "Feature",
  "properties": {
    "addr:full":"Plaz Generalisimo, 16 Villanueva S. Carlos Ciudad Real 13379",
    "addr:housenumber":"16",
    "addr:postcode":"13379",
    "addr:street":"Plaz Generalisimo;Villanueva S. Carlos Ciudad Real",
    "iso:country":"ES",
    "sg:address":"Plaz Generalisimo, 16",
    "sg:city":"Villanueva S. Carlos",
    "sg:orig_category":"Cajas Para Embalar",
    "sg:phone":"+34 926 87 90 55",
    "sg:postcode":"13379",
    "sg:province":"Ciudad Real",
    "wof:name":"Caja Rural De Ciudad Real",
    "wof:placetype":"venue"
},
  "geometry": {"coordinates":[-3.9095890522,38.6236457825],"type":"Point"}
}