{
  "type": "Feature",
  "properties": {
    "addr:full":"Calle de Magallanes, 25 Madrid Madrid 28015",
    "addr:housenumber":"25",
    "addr:postcode":"madrid;28015",
    "addr:street":"Calle De Magallanes",
    "iso:country":"ES",
    "sg:address":"Calle de Magallanes, 25",
    "sg:city":"Madrid",
    "sg:orig_category":"Armaduras De Hormig\u00d3n",
    "sg:phone":"+34 914 47 49 09",
    "sg:postcode":"28015",
    "sg:province":"Madrid",
    "wof:name":"Estructuras De Hormigon Eg S.a.",
    "wof:placetype":"venue"
},
  "geometry": {"coordinates":[-3.7058188915,40.435508728],"type":"Point"}
}