{
  "type": "Feature",
  "properties": {
    "addr:full":"Avda Obispo Perez Caceres, 26 G\u00fcimar Santa Cruz De Tenerife 38500",
    "addr:housenumber":"26",
    "addr:postcode":"38500",
    "addr:street":"Avda Obispo Perez Caceres",
    "iso:country":"ES",
    "sg:address":"Avda Obispo Perez Caceres, 26",
    "sg:city":"G\u00fcimar",
    "sg:orig_category":"Agencias De Viajes",
    "sg:phone":"+34 922 51 41 99",
    "sg:postcode":"38500",
    "sg:province":"Santa Cruz De Tenerife",
    "wof:name":"Viajes Vallecanarias S.l.",
    "wof:placetype":"venue"
},
  "geometry": {"coordinates":[-16.4104614258,28.3149623871],"type":"Point"}
}