{
  "type": "Feature",
  "properties": {
    "addr:full":"C/ Porta Dels Turers, 10 Banyoles Girona 17820",
    "addr:housenumber":"10",
    "addr:postcode":"17820",
    "addr:street":"C / Porta Dels Turers",
    "iso:country":"ES",
    "sg:address":"C/ Porta Dels Turers, 10",
    "sg:city":"Banyoles",
    "sg:orig_category":"Armas Y Municiones (fabricaci\u00d3n, Al Por Mayor)",
    "sg:phone":"+34 972 57 38 59",
    "sg:postcode":"17820",
    "sg:province":"Girona",
    "wof:name":"Escatidor S. A.",
    "wof:placetype":"venue"
},
  "geometry": {"coordinates":[2.7649800777,42.1169548035],"type":"Point"}
}