{
  "type": "Feature",
  "properties": {
    "addr:full":"Calle de Virgen De Fatima, 11 Sevilla Sevilla 41010",
    "addr:housenumber":"11",
    "addr:postcode":"41010",
    "addr:street":"Calle De Virgen De Fatima",
    "iso:country":"ES",
    "sg:address":"Calle de Virgen De Fatima, 11",
    "sg:city":"Sevilla",
    "sg:orig_category":"C\u00c1maras De Comercio E Industria, Oficios, Agricultura",
    "sg:phone":"+34 954 45 59 42",
    "sg:postcode":"41010",
    "sg:province":"Sevilla",
    "wof:name":"Resyobras S.l.",
    "wof:placetype":"venue"
},
  "geometry": {"coordinates":[-6.004172802,37.3789596558],"type":"Point"}
}