{
  "type": "Feature",
  "properties": {
    "addr:full":"Camino De Villagonzalo, S/n Ciruelos Coca Segovia 40496",
    "addr:housenumber":"s / n",
    "addr:postcode":"40496",
    "addr:street":"Camino De Villagonzalo",
    "iso:country":"ES",
    "sg:address":"Camino De Villagonzalo, S/n",
    "sg:city":"Ciruelos Coca",
    "sg:orig_category":"Goma: Productos De Uso Industrial (fabricaci\u00d3n, Al Por Mayor)",
    "sg:phone":"+34 921 58 30 30",
    "sg:postcode":"40496",
    "sg:province":"Segovia",
    "wof:name":"Cauchos Castilla S. L.",
    "wof:placetype":"venue"
},
  "geometry": {"coordinates":[-4.576748848,41.2010116577],"type":"Point"}
}