{
  "type": "Feature",
  "properties": {
    "iso:country":"ES",
    "sg:address":"Calle de Tesorillo (el), S/n",
    "sg:city":"Quesada",
    "sg:orig_category":"Centros De Educaci\u00d3n Especial",
    "sg:phone":"+34 953 73 33 77",
    "sg:postcode":"23480",
    "sg:province":"Ja\u00e9n",
    "wof:name":"Junta De Andalucia",
    "wof:placetype":"venue"
},
  "geometry": {"coordinates":[-3.0709791183,37.8432731628],"type":"Point"}
}