{
  "type": "Feature",
  "properties": {
    "iso:country":"ES",
    "sg:address":"Plaz Carmen, 5",
    "sg:city":"Gijon",
    "sg:orig_category":"Arquitectos",
    "sg:phone":"+34 985 34 24 82",
    "sg:postcode":"33206",
    "sg:province":"Asturias",
    "wof:name":"Hernandez Rubiera Antonio",
    "wof:placetype":"venue"
},
  "geometry": {"coordinates":[-5.6658139229,43.5415611267],"type":"Point"}
}