{
  "type": "Feature",
  "properties": {
    "iso:country":"ES",
    "sg:address":"Calle de Ametzaga\u00d1a, 7",
    "sg:city":"Donostia-san Sebastian",
    "sg:orig_category":"Supermercados Y Hipermercados",
    "sg:phone":"+34 943 27 41 73",
    "sg:postcode":"20012",
    "sg:province":"Guip\u00f9zcoa",
    "wof:name":"Mons S.l.",
    "wof:placetype":"venue"
},
  "geometry": {"coordinates":[-1.9714314938,43.3160934448],"type":"Point"}
}