{
  "type": "Feature",
  "properties": {
    "addr:full":"Pla\u00c7 Esglesia, Pla\u00c7a De L', 2 Casco Urbano Valencia 46760",
    "addr:housenumber":"2",
    "addr:postcode":"46760",
    "addr:street":"Plac\u0327;'",
    "iso:country":"ES",
    "sg:address":"Pla\u00c7 Esglesia, Pla\u00c7a De L', 2",
    "sg:city":"Casco Urbano",
    "sg:orig_category":"Iglesia Cat\u00d3lica",
    "sg:phone":"+34 962 82 14 47",
    "sg:postcode":"46760",
    "sg:province":"Valencia",
    "wof:name":"Parroquia Arciprestal San Pedro Apostol",
    "wof:placetype":"venue"
},
  "geometry": {"coordinates":[-0.3768048882,39.4702377319],"type":"Point"}
}