{
  "type": "Feature",
  "properties": {
    "addr:full":"Avda Espa\u00d1a, 13 Corrales Cantabria 39400",
    "addr:housenumber":"13",
    "addr:postcode":"39400",
    "addr:street":"Avda Espan\u0303A",
    "iso:country":"ES",
    "sg:address":"Avda Espa\u00d1a, 13",
    "sg:city":"Corrales",
    "sg:orig_category":"Centros Empresariales",
    "sg:phone":"+34 942 83 03 17",
    "sg:postcode":"39400",
    "sg:province":"Cantabria",
    "wof:name":"Comunidad De Propietarios Avda. Espa\u00f1a 13-15",
    "wof:placetype":"venue"
},
  "geometry": {"coordinates":[-4.0681390762,43.2584915161],"type":"Point"}
}