{
  "type": "Feature",
  "properties": {
    "addr:full":"Avda Primero De Mayo, 8 Don Benito Badajoz 06400",
    "addr:housenumber":"8",
    "addr:postcode":"06400",
    "addr:street":"Avda Primero De Mayo",
    "iso:country":"ES",
    "sg:address":"Avda Primero De Mayo, 8",
    "sg:city":"Don Benito",
    "sg:orig_category":"Institutos De Belleza",
    "sg:phone":"+34 924 81 14 79",
    "sg:postcode":"06400",
    "sg:province":"Badajoz",
    "wof:name":"Barroso Casillas Eva Maria",
    "wof:placetype":"venue"
},
  "geometry": {"coordinates":[-5.8605289459,38.9569015503],"type":"Point"}
}