{
  "type": "Feature",
  "properties": {
    "addr:full":"Carrer de Major, 40 Sitges Barcelona 08870",
    "addr:housenumber":"40",
    "addr:postcode":"08870",
    "addr:street":"Carrer De Major",
    "iso:country":"ES",
    "sg:address":"Carrer de Major, 40",
    "sg:city":"Sitges",
    "sg:orig_category":"Ropa Para Ni\u00d1os (al Por Menor)",
    "sg:phone":"+34 938 94 83 32",
    "sg:postcode":"08870",
    "sg:province":"Barcelona",
    "wof:name":"Meritxell Soler Coll S.l.",
    "wof:placetype":"venue"
},
  "geometry": {"coordinates":[1.8105020523,41.2363128662],"type":"Point"}
}