{
  "type": "Feature",
  "properties": {
    "addr:full":"Calle de Maestra Lola Meseguer, S/n Alcantarilla Murcia 30820",
    "addr:housenumber":"s",
    "addr:postcode":"30820",
    "addr:street":"Calle De Maestra Lola Meseguer;/ N",
    "iso:country":"ES",
    "sg:address":"Calle de Maestra Lola Meseguer, S/n",
    "sg:city":"Alcantarilla",
    "sg:orig_category":"Cl\u00cdnicas M\u00c9dicas",
    "sg:phone":"+34 968 80 06 00",
    "sg:postcode":"30820",
    "sg:province":"Murcia",
    "wof:name":"Clinica San Jose S.a.",
    "wof:placetype":"venue"
},
  "geometry": {"coordinates":[-1.2250590324,37.9752693176],"type":"Point"}
}