{
  "type": "Feature",
  "properties": {
    "addr:full":"Rbla Poblenou, 22 Barcelona Barcelona 08005",
    "addr:housenumber":"22",
    "addr:postcode":"08005",
    "addr:street":"Rbla Poblenou",
    "iso:country":"ES",
    "sg:address":"Rbla Poblenou, 22",
    "sg:city":"Barcelona",
    "sg:orig_category":"Expertos Contables",
    "sg:phone":"+34 932 25 50 29",
    "sg:postcode":"08005",
    "sg:province":"Barcelona",
    "wof:name":"Josefina Mozo Armero",
    "wof:placetype":"venue"
},
  "geometry": {"coordinates":[2.2046420574,41.3986701965],"type":"Point"}
}