{
  "type": "Feature",
  "properties": {
    "addr:full":"Calle de Alcala De Henares, 6 Esquivias Toledo 45221",
    "addr:housenumber":"6",
    "addr:postcode":"45221",
    "addr:street":"Calle De Alcala De Henares",
    "iso:country":"ES",
    "sg:address":"Calle de Alcala De Henares, 6",
    "sg:city":"Esquivias",
    "sg:orig_category":"Venta Al Preg\u00d3n",
    "sg:phone":"+34 925 52 00 73",
    "sg:postcode":"45221",
    "sg:province":"Toledo",
    "wof:name":"Oca\u00f1a De Diego Pedro",
    "wof:placetype":"venue"
},
  "geometry": {"coordinates":[-3.7657744884,40.1053199768],"type":"Point"}
}