{
  "type": "Feature",
  "properties": {
    "addr:full":"Pl Ajuntament, 2 Vidra Girona 17589",
    "addr:housenumber":"2",
    "addr:postcode":"17589",
    "addr:street":"Pl Ajuntament",
    "iso:country":"ES",
    "sg:address":"Pl Ajuntament, 2",
    "sg:city":"Vidra",
    "sg:orig_category":"Administraciones Regionales, Departamentales Y Locales",
    "sg:phone":"+34 938 55 12 55",
    "sg:postcode":"17589",
    "sg:province":"Girona",
    "wof:name":"Ajuntament De Vidra",
    "wof:placetype":"venue"
},
  "geometry": {"coordinates":[2.3101806641,42.1223907471],"type":"Point"}
}