{
  "type": "Feature",
  "properties": {
    "addr:full":"Harzubia Hiribidea, 1 Azpeitia Guip\u00f9zcoa 20730",
    "addr:housenumber":"1",
    "addr:postcode":"20730",
    "addr:street":"Harzubia Hiribidea;Guipu\u0300Zcoa",
    "iso:country":"ES",
    "sg:address":"Harzubia Hiribidea, 1",
    "sg:city":"Azpeitia",
    "sg:orig_category":"Sociedades, Compa\u00d1\u00cdas Aseguradoras",
    "sg:phone":"+34 943 81 05 62",
    "sg:postcode":"20730",
    "sg:province":"Guip\u00f9zcoa",
    "wof:name":"Seguros Lagun Aro S.a.",
    "wof:placetype":"venue"
},
  "geometry": {"coordinates":[-2.2658390999,43.1823768616],"type":"Point"}
}