{
  "type": "Feature",
  "properties": {
    "addr:full":"Av De Espa\u00f1a, 7 Alcaraz Albacete 02300",
    "addr:housenumber":"7",
    "addr:postcode":"02300",
    "addr:street":"Av De Espan\u0303A",
    "iso:country":"ES",
    "sg:address":"Av De Espa\u00f1a, 7",
    "sg:city":"Alcaraz",
    "sg:orig_category":"Promotores Constructores",
    "sg:phone":"+34 967 38 00 68",
    "sg:postcode":"02300",
    "sg:province":"Albacete",
    "wof:name":"Construcciones Y Excavaciones Villar Hermanos S.c.l.",
    "wof:placetype":"venue"
},
  "geometry": {"coordinates":[-2.4900488853,38.6677589417],"type":"Point"}
}