{
  "type": "Feature",
  "properties": {
    "addr:full":"Calle de Secundino Alonso, 84 Pto. Rosario Las Palmas 35600",
    "addr:housenumber":"84",
    "addr:postcode":"35600",
    "addr:street":"Calle De Secundino Alonso;Pto. Rosario Las",
    "iso:country":"ES",
    "sg:address":"Calle de Secundino Alonso, 84",
    "sg:city":"Pto. Rosario",
    "sg:orig_category":"Inmobiliaria (agencias)",
    "sg:phone":"+34 928 85 55 30",
    "sg:postcode":"35600",
    "sg:province":"Las Palmas",
    "wof:name":"Serfin Fuerteventura S.l.",
    "wof:placetype":"venue"
},
  "geometry": {"coordinates":[-13.8634719849,28.4943408966],"type":"Point"}
}