{
  "type": "Feature",
  "properties": {
    "addr:full":"Calle de Violeta Parra, 7 Almansa Albacete 02640",
    "addr:housenumber":"7",
    "addr:postcode":"02640",
    "addr:street":"Calle De Violeta Parra",
    "iso:country":"ES",
    "sg:address":"Calle de Violeta Parra, 7",
    "sg:city":"Almansa",
    "sg:orig_category":"Asociaciones Humanitarias, De Cooperaci\u00d3n, De Acci\u00d3n Social",
    "sg:phone":"+34 967 31 32 96",
    "sg:postcode":"02640",
    "sg:province":"Albacete",
    "wof:name":"Afaempal Centro De Rehabilitacion Psicosocial Y Laboral",
    "wof:placetype":"venue"
},
  "geometry": {"coordinates":[-1.0908173323,38.8698272705],"type":"Point"}
}