{
  "type": "Feature",
  "properties": {
    "iso:country":"ES",
    "sg:address":"Ctra Trassierra (extrarradio), S/n",
    "sg:city":"Cordoba",
    "sg:orig_category":"Fabricaci\u00d3n E Instalaci\u00d3n De Cajas Fuertes",
    "sg:phone":"+34 957 76 73 82",
    "sg:postcode":"14011",
    "sg:province":"C\u00f3rdoba",
    "wof:name":"Castro Freire Maria Sol",
    "wof:placetype":"venue"
},
  "geometry": {"coordinates":[-4.7979950905,37.8932380676],"type":"Point"}
}