{
  "type": "Feature",
  "properties": {
    "iso:country":"ES",
    "sg:address":"Carrer de Musitu, 24",
    "sg:city":"Barcelona",
    "sg:orig_category":"Agencias De Viajes",
    "sg:phone":"+34 934 17 71 11",
    "sg:postcode":"08023",
    "sg:province":"Barcelona",
    "sg:website":"www.dreamsandadventures.com",
    "wof:name":"Dreams & Adventures S. L.",
    "wof:placetype":"venue"
},
  "geometry": {"coordinates":[2.1406800747,41.4070281982],"type":"Point"}
}