{
  "type": "Feature",
  "properties": {
    "iso:country":"ES",
    "sg:address":"Avda Gandhi, S/n",
    "sg:city":"Arroyo De La Miel-benalmadena Costa",
    "sg:orig_category":"Supermercados Y Hipermercados",
    "sg:phone":"+34 952 44 31 94",
    "sg:postcode":"29630",
    "sg:province":"M\u00e1laga",
    "wof:name":"Dispame S.a.",
    "wof:placetype":"venue"
},
  "geometry": {"coordinates":[-4.5330958366,36.5923080444],"type":"Point"}
}