{
  "type": "Feature",
  "properties": {
    "iso:country":"ES",
    "sg:address":"Calle de Matiko, 32",
    "sg:city":"Bilbao",
    "sg:orig_category":"Ropa Para Se\u00d1oras Y Caballeros (al Por Menor)",
    "sg:phone":"+34 944 45 13 14",
    "sg:postcode":"48007",
    "sg:province":"Vizcaya",
    "wof:name":"Confecciones Lagen S.l.",
    "wof:placetype":"venue"
},
  "geometry": {"coordinates":[-2.922563076,43.2666893005],"type":"Point"}
}