{
  "type": "Feature",
  "properties": {
    "addr:full":"Ctra Villaviciosa (c-5114) (de), Km. 0002,4 Mostoles Madrid 28935",
    "addr:postcode":"c-5114;28935",
    "addr:street":"Ctra Villaviciosa;De Km. 0002,4 Mostoles",
    "iso:country":"ES",
    "sg:address":"Ctra Villaviciosa (c-5114) (de), Km. 0002,4",
    "sg:city":"Mostoles",
    "sg:orig_category":"Transporte En General",
    "sg:phone":"+34 916 13 67 31",
    "sg:postcode":"28935",
    "sg:province":"Madrid",
    "wof:name":"Almacen De Las Indias S.l.",
    "wof:placetype":"venue"
},
  "geometry": {"coordinates":[-3.8919320107,40.3386001587],"type":"Point"}
}