{
  "type": "Feature",
  "properties": {
    "iso:country":"ES",
    "sg:address":"Ctra. Nijar, 239",
    "sg:city":"Ca\u00f1ada San Urbano",
    "sg:orig_category":"Farmacias",
    "sg:phone":"+34 950 62 60 30",
    "sg:postcode":"04120",
    "sg:province":"Almer\u00eda",
    "wof:name":"Zapata Sanchez Maria Del Carmen",
    "wof:placetype":"venue"
},
  "geometry": {"coordinates":[-2.4051589966,36.8402252197],"type":"Point"}
}