{
  "type": "Feature",
  "properties": {
    "iso:country":"ES",
    "sg:address":"Calle de Fragua, S/n",
    "sg:city":"Cisterniga",
    "sg:orig_category":"Inmobiliaria (agencias)",
    "sg:phone":"+34 983 40 32 63",
    "sg:postcode":"47193",
    "sg:province":"Valladolid",
    "wof:name":"Asesoria Inmobiliaria Real 28",
    "wof:placetype":"venue"
},
  "geometry": {"coordinates":[-4.6848649979,41.6117210388],"type":"Point"}
}