{
  "type": "Feature",
  "properties": {
    "addr:full":"General-collanzo, 15 S. De La Fuente Asturias 33680",
    "addr:housenumber":"15",
    "addr:postcode":"33680",
    "addr:street":"General-Collanzo;S. De La Fuente Asturias",
    "iso:country":"ES",
    "sg:address":"General-collanzo, 15",
    "sg:city":"S. De La Fuente",
    "sg:orig_category":"Estancos",
    "sg:phone":"+34 985 48 70 78",
    "sg:postcode":"33680",
    "sg:province":"Asturias",
    "wof:name":"Miranda Casta\u00f1on Maria",
    "wof:placetype":"venue"
},
  "geometry": {"coordinates":[-5.5670418739,43.1198158264],"type":"Point"}
}