{
  "type": "Feature",
  "properties": {
    "addr:full":"Pase Zorrilla, 47 Valladolid Valladolid 47007",
    "addr:housenumber":"47",
    "addr:postcode":"47007",
    "addr:street":"Zorrilla",
    "iso:country":"ES",
    "sg:address":"Pase Zorrilla, 47",
    "sg:city":"Valladolid",
    "sg:orig_category":"Art\u00cdculos De Regalo (al Por Menor)",
    "sg:phone":"+34 983 47 64 17",
    "sg:postcode":"47007",
    "sg:province":"Valladolid",
    "wof:name":"Caprichos Y Regalos C.b.",
    "wof:placetype":"venue"
},
  "geometry": {"coordinates":[-4.7375030518,41.6402511597],"type":"Point"}
}