{
  "type": "Feature",
  "properties": {
    "addr:full":"Calle de Francisco Sarmiento, 10 Burgos Burgos 09005",
    "addr:housenumber":"10",
    "addr:postcode":"09005",
    "addr:street":"Calle De Francisco Sarmiento",
    "iso:country":"ES",
    "sg:address":"Calle de Francisco Sarmiento, 10",
    "sg:city":"Burgos",
    "sg:orig_category":"Congelados: Productos Alimentarios (al Por Menor)",
    "sg:phone":"+34 947 22 41 58",
    "sg:postcode":"09005",
    "sg:province":"Burgos",
    "wof:name":"Rodrigo Barbero Maria Luisa",
    "wof:placetype":"venue"
},
  "geometry": {"coordinates":[-3.6935501099,42.3484039307],"type":"Point"}
}