{
  "type": "Feature",
  "properties": {
    "addr:full":"Calle de Ilarduibide, 7 Araia \u00c1lava 01250",
    "addr:housenumber":"7",
    "addr:postcode":"01250",
    "addr:street":"Calle De Ilarduibide;A\u0301Lava",
    "iso:country":"ES",
    "sg:address":"Calle de Ilarduibide, 7",
    "sg:city":"Araia",
    "sg:orig_category":"Ense\u00d1anza, Formaci\u00d3n Profesional: Aprendizaje",
    "sg:phone":"+34 945 30 40 76",
    "sg:postcode":"01250",
    "sg:province":"\u00c1lava",
    "wof:name":"Gobierno Vasco-eusko Jaurlaritza",
    "wof:placetype":"venue"
},
  "geometry": {"coordinates":[-2.3149189949,42.8886680603],"type":"Point"}
}