{
  "type": "Feature",
  "properties": {
    "addr:full":"Calle de Lino, 1 Madrid Madrid 28020",
    "addr:housenumber":"1",
    "addr:postcode":"28020",
    "addr:street":"Calle De Lino",
    "iso:country":"ES",
    "sg:address":"Calle de Lino, 1",
    "sg:city":"Madrid",
    "sg:orig_category":"Loter\u00cda Y T\u00d3mbola",
    "sg:phone":"+34 915 79 16 84",
    "sg:postcode":"28020",
    "sg:province":"Madrid",
    "wof:name":"Serrano Del Valle Florencio",
    "wof:placetype":"venue"
},
  "geometry": {"coordinates":[-3.6983599663,40.4602584839],"type":"Point"}
}