{
  "type": "Feature",
  "properties": {
    "iso:country":"ES",
    "sg:address":"Calle de Campoamor, 17",
    "sg:city":"Madrid",
    "sg:orig_category":"Centros Empresariales",
    "sg:phone":"+34 913 08 63 18",
    "sg:postcode":"28004",
    "sg:province":"Madrid",
    "sg:website":"www.sne.es",
    "wof:name":"Sociedad Nuclear Espa\u00f1ola",
    "wof:placetype":"venue"
},
  "geometry": {"coordinates":[-3.6952819824,40.4268379211],"type":"Point"}
}