{
  "type": "Feature",
  "properties": {
    "addr:full":"Calle de Juan Carvallo, S/n Sevilla Sevilla 41006",
    "addr:housenumber":"s / n",
    "addr:postcode":"41006",
    "addr:street":"Calle De Juan Carvallo",
    "iso:country":"ES",
    "sg:address":"Calle de Juan Carvallo, S/n",
    "sg:city":"Sevilla",
    "sg:orig_category":"Caf\u00c9s, Bares, Cervecer\u00cdas",
    "sg:phone":"+34 954 66 21 04",
    "sg:postcode":"41006",
    "sg:province":"Sevilla",
    "wof:name":"Pineda Leon Joaquin",
    "wof:placetype":"venue"
},
  "geometry": {"coordinates":[-5.9541640282,37.3762702942],"type":"Point"}
}