{
  "type": "Feature",
  "properties": {
    "addr:full":"Avda Santiago (de), 34 Ourense Ourense 32001",
    "addr:housenumber":"34",
    "addr:postcode":"32001",
    "addr:street":"Avda Santiago De",
    "iso:country":"ES",
    "sg:address":"Avda Santiago (de), 34",
    "sg:city":"Ourense",
    "sg:orig_category":"Negocio De Madera",
    "sg:phone":"+34 988 21 43 07",
    "sg:postcode":"32001",
    "sg:province":"Ourense",
    "wof:name":"Araujo Vazquez Delmiro",
    "wof:placetype":"venue"
},
  "geometry": {"coordinates":[-7.8660144806,42.351184845],"type":"Point"}
}