{
  "type": "Feature",
  "properties": {
    "addr:full":"Rua Marcelo Macias, 14 Ourense Ourense 32005",
    "addr:housenumber":"14",
    "addr:postcode":"32005",
    "addr:street":"Rua Marcelo Macias",
    "iso:country":"ES",
    "sg:address":"Rua Marcelo Macias, 14",
    "sg:city":"Ourense",
    "sg:orig_category":"Tintorer\u00cdas, Limpieza En Seco",
    "sg:phone":"+34 988 22 22 83",
    "sg:postcode":"32005",
    "sg:province":"Ourense",
    "wof:name":"Garrido Cid Aurelio",
    "wof:placetype":"venue"
},
  "geometry": {"coordinates":[-7.865489006,42.3311882019],"type":"Point"}
}