{
  "type": "Feature",
  "properties": {
    "iso:country":"ES",
    "sg:address":"Ctra Calahorra, Km. 0001,0",
    "sg:city":"Autol",
    "sg:orig_category":"Conservas De Legumbres (fabricaci\u00d3n, Al Por Mayor)",
    "sg:phone":"+34 941 40 13 28",
    "sg:postcode":"26560",
    "sg:province":"La Rioja",
    "wof:name":"Conservas El Cidacos S.a.",
    "wof:placetype":"venue"
},
  "geometry": {"coordinates":[-2.0062799454,42.2181015015],"type":"Point"}
}