{
  "type": "Feature",
  "properties": {
    "addr:full":"Calle de Santa Ines, 2 Cadiz C\u00e1diz 11003",
    "addr:housenumber":"2",
    "addr:postcode":"11003",
    "addr:street":"Calle De Santa Ines",
    "iso:country":"ES",
    "sg:address":"Calle de Santa Ines, 2",
    "sg:city":"Cadiz",
    "sg:orig_category":"Alimentaci\u00d3n General (al Por Menor)",
    "sg:phone":"+34 956 21 37 14",
    "sg:postcode":"11003",
    "sg:province":"C\u00e1diz",
    "wof:name":"Gomez Del Castillo Jose",
    "wof:placetype":"venue"
},
  "geometry": {"coordinates":[-6.299808979,36.5334472656],"type":"Point"}
}