{
  "type": "Feature",
  "properties": {
    "iso:country":"ES",
    "sg:address":"Carrer de Palma (la), 24",
    "sg:city":"Vilafranca Penedes",
    "sg:orig_category":"Bibliotecas, Mediatecas",
    "sg:phone":"+34 938 92 32 04",
    "sg:postcode":"08720",
    "sg:province":"Barcelona",
    "wof:name":"Museu De Vilafranca-museu Del Vi.fundacio Privada",
    "wof:placetype":"venue"
},
  "geometry": {"coordinates":[1.6990679502,41.3453674316],"type":"Point"}
}