{
  "type": "Feature",
  "properties": {
    "iso:country":"ES",
    "sg:address":"Calle de Humilladero (del), 14",
    "sg:city":"Fuenlabrada",
    "sg:orig_category":"Ropa Y Accesorios",
    "sg:phone":"+34 916 90 32 86",
    "sg:postcode":"28945",
    "sg:province":"Madrid",
    "wof:name":"Novo Jeans S.l.",
    "wof:placetype":"venue"
},
  "geometry": {"coordinates":[-3.7954969406,40.2842636108],"type":"Point"}
}