{
  "type": "Feature",
  "properties": {
    "iso:country":"ES",
    "sg:address":"Carrer de Joaquin Costa, 81",
    "sg:city":"Sabadell",
    "sg:orig_category":"Cerrajer\u00cda, Ferrallista",
    "sg:phone":"+34 937 26 21 71",
    "sg:postcode":"08206",
    "sg:province":"Barcelona",
    "sg:website":"www.cremalon.com",
    "wof:name":"Cremalon S.a.",
    "wof:placetype":"venue"
},
  "geometry": {"coordinates":[2.0959999561,41.5476036072],"type":"Point"}
}