{
  "type": "Feature",
  "properties": {
    "iso:country":"ES",
    "sg:address":"Plaz San Juan Bosco, 5",
    "sg:city":"Bejar",
    "sg:orig_category":"Alimentaci\u00d3n General (al Por Menor)",
    "sg:phone":"+34 923 40 14 02",
    "sg:postcode":"37700",
    "sg:province":"Salamanca",
    "wof:name":"Heras De La Iglesia Felipe",
    "wof:placetype":"venue"
},
  "geometry": {"coordinates":[-5.7756199837,40.3884963989],"type":"Point"}
}