{
  "type": "Feature",
  "properties": {
    "iso:country":"ES",
    "sg:address":"Ctra Tarajal (del), S/n",
    "sg:city":"Principe Felipe",
    "sg:orig_category":"Importaci\u00d3n",
    "sg:phone":"+34 956 50 68 67",
    "sg:postcode":"51003",
    "sg:province":"Ceuta",
    "wof:name":"Uniben S. L.",
    "wof:placetype":"venue"
},
  "geometry": {"coordinates":[-5.3157300949,35.8891601562],"type":"Point"}
}