{
  "type": "Feature",
  "properties": {
    "iso:country":"ES",
    "sg:address":"Rua Monteleon, 5",
    "sg:city":"Pontevedra",
    "sg:orig_category":"Pescader\u00cdas (al Por Menor)",
    "sg:phone":"+34 986 84 08 22",
    "sg:postcode":"36002",
    "sg:province":"Pontevedra",
    "wof:name":"Freitas Rodriguez Lucia",
    "wof:placetype":"venue"
},
  "geometry": {"coordinates":[-8.6524591446,42.4311485291],"type":"Point"}
}