{
  "type": "Feature",
  "properties": {
    "addr:full":"C/ Joan Alcover, 21 Inca Islas Baleares 07300",
    "addr:housenumber":"21",
    "addr:postcode":"07300",
    "addr:street":"C / Joan Alcover",
    "iso:country":"ES",
    "sg:address":"C/ Joan Alcover, 21",
    "sg:city":"Inca",
    "sg:orig_category":"Peluqueros: De Se\u00d1oras",
    "sg:phone":"+34 971 88 07 51",
    "sg:postcode":"07300",
    "sg:province":"Islas Baleares",
    "wof:name":"Alomar Coll Francisca",
    "wof:placetype":"venue"
},
  "geometry": {"coordinates":[2.9052968025,39.7168006897],"type":"Point"}
}