{
  "type": "Feature",
  "properties": {
    "addr:full":"Calle de Lope De Rueda, 45 Malaga M\u00e1laga 29190",
    "addr:housenumber":"45",
    "addr:postcode":"29190",
    "addr:street":"Calle De Lope De Rueda;Ma\u0301Laga",
    "iso:country":"ES",
    "sg:address":"Calle de Lope De Rueda, 45",
    "sg:city":"Malaga",
    "sg:orig_category":"Ropa Para Se\u00d1oras Y Caballeros (al Por Menor)",
    "sg:phone":"+34 952 10 02 54",
    "sg:postcode":"29190",
    "sg:province":"M\u00e1laga",
    "wof:name":"Ramirez Lopez Marta Elena",
    "wof:placetype":"venue"
},
  "geometry": {"coordinates":[-4.4796409607,36.7364425659],"type":"Point"}
}