{
  "type": "Feature",
  "properties": {
    "iso:country":"ES",
    "sg:address":"Calle de Don Juan Gomez Repes, 10",
    "sg:city":"Santurde",
    "sg:orig_category":"Farmacias",
    "sg:phone":"+34 941 42 66 90",
    "sg:postcode":"26260",
    "sg:province":"La Rioja",
    "wof:name":"Valenzuela Martinez Maria Dolores",
    "wof:placetype":"venue"
},
  "geometry": {"coordinates":[-2.9792940617,42.389415741],"type":"Point"}
}