{
  "type": "Feature",
  "properties": {
    "addr:full":"Rua Boisaca (de), Km. 0059,0 Santiago De Compostela La Coru\u00f1a 15704",
    "addr:postcode":"15704",
    "addr:street":"Rua Boisaca De Km. 0059,0;Corun\u0303A",
    "iso:country":"ES",
    "sg:address":"Rua Boisaca (de), Km. 0059,0",
    "sg:city":"Santiago De Compostela",
    "sg:orig_category":"Agentes, Concesionarios Y Sucursales De Veh\u00cdculos",
    "sg:phone":"+34 981 56 96 30",
    "sg:postcode":"15704",
    "sg:province":"La Coru\u00f1a",
    "wof:name":"Compostela De Automocion S. A.",
    "wof:placetype":"venue"
},
  "geometry": {"coordinates":[-8.5152330399,42.9058380127],"type":"Point"}
}