{
  "type": "Feature",
  "properties": {
    "addr:full":"Calle de Buenavista, 13 Alaquas Valencia 46970",
    "addr:housenumber":"13",
    "addr:postcode":"46970",
    "addr:street":"Calle De Buenavista",
    "iso:country":"ES",
    "sg:address":"Calle de Buenavista, 13",
    "sg:city":"Alaquas",
    "sg:orig_category":"Fabricaci\u00d3n, Venta De Cuadros, Accesorios Para Enmarcar",
    "sg:phone":"+34 961 50 27 06",
    "sg:postcode":"46970",
    "sg:province":"Valencia",
    "wof:name":"Lara Navarrete Manuel",
    "wof:placetype":"venue"
},
  "geometry": {"coordinates":[-0.4535999,39.4559249878],"type":"Point"}
}