{
  "type": "Feature",
  "properties": {
    "addr:full":"Carrer de Francesc Macia, 2 Palleja Barcelona 08780",
    "addr:housenumber":"2",
    "addr:postcode":"08780",
    "addr:street":"Carrer De Francesc Macia",
    "iso:country":"ES",
    "sg:address":"Carrer de Francesc Macia, 2",
    "sg:city":"Palleja",
    "sg:orig_category":"Herboristas (al Por Menor)",
    "sg:phone":"+34 936 63 16 15",
    "sg:postcode":"08780",
    "sg:province":"Barcelona",
    "wof:name":"Perez Oliveras Eva",
    "wof:placetype":"venue"
},
  "geometry": {"coordinates":[1.9994549751,41.4216270447],"type":"Point"}
}