{
  "type": "Feature",
  "properties": {
    "iso:country":"ES",
    "sg:address":"Carrer de Teodor Gonzalez (de), 24",
    "sg:city":"Tortosa",
    "sg:orig_category":"Ropa Para Caballeros (al Por Menor)",
    "sg:phone":"+34 977 51 11 56",
    "sg:postcode":"43500",
    "sg:province":"Tarragona",
    "wof:name":"Fava-pla S.l.l.",
    "wof:placetype":"venue"
},
  "geometry": {"coordinates":[0.521148026,40.8100509644],"type":"Point"}
}