{
  "type": "Feature",
  "properties": {
    "addr:full":"Calle de Cruz La, S/n Candas Asturias 33430",
    "addr:postcode":"33430",
    "addr:street":"Calle De Cruz La S / N Candas Asturias",
    "iso:country":"ES",
    "sg:address":"Calle de Cruz La, S/n",
    "sg:city":"Candas",
    "sg:orig_category":"Pompas F\u00danebres, Inhumaciones Y Cremaciones",
    "sg:phone":"+34 985 87 24 46",
    "sg:postcode":"33430",
    "sg:province":"Asturias",
    "wof:name":"Funeraria Gijonesa S.a.",
    "wof:placetype":"venue"
},
  "geometry": {"coordinates":[-5.7678804398,43.5889358521],"type":"Point"}
}