{
  "type": "Feature",
  "properties": {
    "addr:full":"Av Furs (dels), 3 Lliria Valencia 46160",
    "addr:housenumber":"3",
    "addr:postcode":"46160",
    "addr:street":"Av Furs Dels",
    "iso:country":"ES",
    "sg:address":"Av Furs (dels), 3",
    "sg:city":"Lliria",
    "sg:orig_category":"Ense\u00d1anza: Idiomas",
    "sg:phone":"+34 962 78 04 51",
    "sg:postcode":"46160",
    "sg:province":"Valencia",
    "wof:name":"Santapau Civera Maria Concepcion",
    "wof:placetype":"venue"
},
  "geometry": {"coordinates":[-0.5951089859,39.6312408447],"type":"Point"}
}