{
  "type": "Feature",
  "properties": {
    "addr:full":"Alam Principal, 28 Malaga M\u00e1laga 29005",
    "addr:housenumber":"28",
    "addr:postcode":"29005",
    "addr:street":"Alam Principal;Ma\u0301Laga",
    "iso:country":"ES",
    "sg:address":"Alam Principal, 28",
    "sg:city":"Malaga",
    "sg:orig_category":"Confiter\u00cdas, Chocolater\u00cdas (al Por Menor)",
    "sg:phone":"+34 952 22 29 71",
    "sg:postcode":"29005",
    "sg:province":"M\u00e1laga",
    "wof:name":"Valdes Iglesias Jose Luis",
    "wof:placetype":"venue"
},
  "geometry": {"coordinates":[-4.4242048264,36.7175331116],"type":"Point"}
}