{
  "type": "Feature",
  "properties": {
    "iso:country":"ES",
    "sg:address":"Avda Albufera, 48",
    "sg:city":"Madrid",
    "sg:orig_category":"Peluqueros: De Se\u00d1oras",
    "sg:phone":"+34 914 78 57 96",
    "sg:postcode":"28038",
    "sg:province":"Madrid",
    "wof:name":"Jabardo Hidalgo Jesus",
    "wof:placetype":"venue"
},
  "geometry": {"coordinates":[-3.6657850742,40.3963241577],"type":"Point"}
}