{
  "type": "Feature",
  "properties": {
    "addr:full":"Lois, S/n Lois Asturias 33794",
    "addr:housenumber":"s / n",
    "addr:postcode":"33794",
    "addr:street":"Lois;Lois Asturias",
    "iso:country":"ES",
    "sg:address":"Lois, S/n",
    "sg:city":"Lois",
    "sg:orig_category":"Bordado, Marcado A Medida",
    "sg:phone":"+34 985 63 61 89",
    "sg:postcode":"33794",
    "sg:province":"Asturias",
    "wof:name":"Garcia Bustelo Carmen",
    "wof:placetype":"venue"
},
  "geometry": {"coordinates":[-7.0207791328,43.539642334],"type":"Point"}
}