{
  "type": "Feature",
  "properties": {
    "iso:country":"ES",
    "sg:address":"Calle de Obispo Cobos, 11",
    "sg:city":"Ubeda",
    "sg:orig_category":"Ropa Para Se\u00d1oras (al Por Menor)",
    "sg:phone":"+34 953 79 33 66",
    "sg:postcode":"23400",
    "sg:province":"Ja\u00e9n",
    "wof:name":"Tazan S.l.",
    "wof:placetype":"venue"
},
  "geometry": {"coordinates":[-3.3744280338,38.0111999512],"type":"Point"}
}