{
  "type": "Feature",
  "properties": {
    "iso:country":"ES",
    "sg:address":"Calle de Manflorido, 1",
    "sg:city":"Palencia",
    "sg:orig_category":"Electrodom\u00c9sticos (al Por Menor)",
    "sg:phone":"+34 979 74 35 61",
    "sg:postcode":"34005",
    "sg:province":"Palencia",
    "wof:name":"Perez Soto Eduardo",
    "wof:placetype":"venue"
},
  "geometry": {"coordinates":[-4.5367388725,42.0128288269],"type":"Point"}
}