{
  "type": "Feature",
  "properties": {
    "addr:full":"Carrer de Ramon Soler, 2 Vic Barcelona 08500",
    "addr:housenumber":"2",
    "addr:postcode":"08500",
    "addr:street":"Carrer De Ramon Soler",
    "iso:country":"ES",
    "sg:address":"Carrer de Ramon Soler, 2",
    "sg:city":"Vic",
    "sg:orig_category":"M\u00c9dicos: Pediatr\u00cda. Enfermedades De Los Ni\u00d1os",
    "sg:phone":"+34 938 89 56 42",
    "sg:postcode":"08500",
    "sg:province":"Barcelona",
    "wof:name":"Pallares Miserachs Jorge",
    "wof:placetype":"venue"
},
  "geometry": {"coordinates":[2.2498641014,41.9287796021],"type":"Point"}
}