{
  "type": "Feature",
  "properties": {
    "iso:country":"ES",
    "sg:address":"Calle de Acera Del Darro, 8",
    "sg:city":"Granada",
    "sg:orig_category":"Molduras, Junquillos, Listones Y Molduras Perforadas",
    "sg:phone":"+34 958 25 50 08",
    "sg:postcode":"18005",
    "sg:province":"Granada",
    "wof:name":"Martinez Baena Enrique",
    "wof:placetype":"venue"
},
  "geometry": {"coordinates":[-3.5996038914,37.1730232239],"type":"Point"}
}