{
  "type": "Feature",
  "properties": {
    "addr:full":"Ctra Villanueva, 20 Jerez De Los Caballeros Badajoz 06380",
    "addr:housenumber":"20",
    "addr:postcode":"06380",
    "addr:street":"Ctra Villanueva",
    "iso:country":"ES",
    "sg:address":"Ctra Villanueva, 20",
    "sg:city":"Jerez De Los Caballeros",
    "sg:orig_category":"Mec\u00c1nico Del Autom\u00d3vil",
    "sg:phone":"+34 924 73 07 56",
    "sg:postcode":"06380",
    "sg:province":"Badajoz",
    "wof:name":"Talleres Mendez Jimenez S.l.",
    "wof:placetype":"venue"
},
  "geometry": {"coordinates":[-6.7699389458,38.3268165588],"type":"Point"}
}