{
  "type": "Feature",
  "properties": {
    "iso:country":"ES",
    "sg:address":"Calle de Sos Del Rey Catolico, 7",
    "sg:city":"Granada",
    "sg:orig_category":"Ense\u00d1anza, Formaci\u00d3n Profesional: Aprendizaje",
    "sg:phone":"+34 958 81 99 92",
    "sg:postcode":"18006",
    "sg:province":"Granada",
    "wof:name":"Lopez-huertas Perez Maria Jose",
    "wof:placetype":"venue"
},
  "geometry": {"coordinates":[-3.5962269306,37.1657981873],"type":"Point"}
}