{
  "type": "Feature",
  "properties": {
    "addr:full":"Carrer de Lluis Castells, 32 S. Boi Llobregat Barcelona 08830",
    "addr:housenumber":"32",
    "addr:postcode":"08830",
    "addr:street":"Carrer De Lluis Castells",
    "iso:country":"ES",
    "sg:address":"Carrer de Lluis Castells, 32",
    "sg:city":"S. Boi Llobregat",
    "sg:orig_category":"Farmacias",
    "sg:phone":"+34 936 40 06 24",
    "sg:postcode":"08830",
    "sg:province":"Barcelona",
    "wof:name":"Aguila Pijuan Maria Soledad",
    "wof:placetype":"venue"
},
  "geometry": {"coordinates":[2.0369346142,41.34633255],"type":"Point"}
}