{
  "type": "Feature",
  "properties": {
    "iso:country":"ES",
    "sg:address":"Iriartea, 39",
    "sg:city":"Erro",
    "sg:orig_category":"Farmacias",
    "sg:phone":"+34 948 47 51 52",
    "sg:postcode":"31415",
    "sg:province":"Navarra",
    "wof:name":"Sanjuan Elizondo Javier",
    "wof:placetype":"venue"
},
  "geometry": {"coordinates":[-0.9560689926,42.8085899353],"type":"Point"}
}