{
  "type": "Feature",
  "properties": {
    "iso:country":"ES",
    "sg:address":"Calle de General Espartero, 78",
    "sg:city":"Alacant",
    "sg:orig_category":"Farmacias",
    "sg:phone":"+34 965 24 36 28",
    "sg:postcode":"03012",
    "sg:province":"Alicante",
    "wof:name":"Climent Mecho Jose",
    "wof:placetype":"venue"
},
  "geometry": {"coordinates":[-0.4825710058,38.3607254028],"type":"Point"}
}