{
  "type": "Feature",
  "properties": {
    "addr:full":"Calle de Edom, 8 Malaga M\u00e1laga 29006",
    "addr:housenumber":"8",
    "addr:postcode":"29006",
    "addr:street":"Calle De Edom;Ma\u0301Laga",
    "iso:country":"ES",
    "sg:address":"Calle de Edom, 8",
    "sg:city":"Malaga",
    "sg:orig_category":"Agencias Y Agentes Comerciales, Representantes",
    "sg:phone":"+34 952 32 78 69",
    "sg:postcode":"29006",
    "sg:province":"M\u00e1laga",
    "wof:name":"Ballesteros Cristeta Jose",
    "wof:placetype":"venue"
},
  "geometry": {"coordinates":[-4.4407110214,36.7158813477],"type":"Point"}
}