{
  "type": "Feature",
  "properties": {
    "iso:country":"ES",
    "sg:address":"Calle de Fernando Calderon, 5",
    "sg:city":"Santander",
    "sg:orig_category":"M\u00c9dicos: Psiquiatr\u00cda",
    "sg:phone":"+34 942 27 20 27",
    "sg:postcode":"39005",
    "sg:province":"Cantabria",
    "wof:name":"Mu\u00f1oz Garcia Julio Juan",
    "wof:placetype":"venue"
},
  "geometry": {"coordinates":[-3.788392067,43.4703903198],"type":"Point"}
}