{
  "type": "Feature",
  "properties": {
    "addr:full":"Plaz Iglesia, 14 Villagonzalo Badajoz 06473",
    "addr:housenumber":"14",
    "addr:postcode":"06473",
    "addr:street":"Iglesia",
    "iso:country":"ES",
    "sg:address":"Plaz Iglesia, 14",
    "sg:city":"Villagonzalo",
    "sg:orig_category":"Bancos",
    "sg:phone":"+34 924 36 75 94",
    "sg:postcode":"06473",
    "sg:province":"Badajoz",
    "wof:name":"Bt Espa\u00d1a Compa\u00d1ia De Servicios Globales De Telecomunicaciones S.a.u.",
    "wof:placetype":"venue"
},
  "geometry": {"coordinates":[-6.2000069618,38.861946106],"type":"Point"}
}