{
  "type": "Feature",
  "properties": {
    "addr:full":"Calle de Ortega Y Gasset, 10 Cuenca Cuenca 16004",
    "addr:housenumber":"10",
    "addr:postcode":"16004",
    "addr:street":"Calle De Ortega Y Gasset",
    "iso:country":"ES",
    "sg:address":"Calle de Ortega Y Gasset, 10",
    "sg:city":"Cuenca",
    "sg:orig_category":"Empresarios",
    "sg:phone":"+34 969 23 63 50",
    "sg:postcode":"16004",
    "sg:province":"Cuenca",
    "sg:website":"www.aldeasinfantiles.es",
    "wof:name":"Aldeas Infantiles S.o.s De Espa\u00d1a",
    "wof:placetype":"venue"
},
  "geometry": {"coordinates":[-2.1318194866,40.058757782],"type":"Point"}
}