{
  "type": "Feature",
  "properties": {
    "iso:country":"ES",
    "sg:address":"Calle de Islas Canarias, 52",
    "sg:city":"Valencia",
    "sg:orig_category":"Agencias De Viajes",
    "sg:phone":"+34 963 30 20 20",
    "sg:postcode":"46023",
    "sg:province":"Valencia",
    "wof:name":"Pacific Travel S.l.",
    "wof:placetype":"venue"
},
  "geometry": {"coordinates":[-0.3545680046,39.4659347534],"type":"Point"}
}