{
  "type": "Feature",
  "properties": {
    "iso:country":"ES",
    "sg:address":"Calle de Machado Y Fiesco, 51",
    "sg:city":"Cuesta",
    "sg:orig_category":"Bazares, Art\u00cdculos De Limpieza Y De Cocina (al Por Menor)",
    "sg:phone":"+34 922 66 00 66",
    "sg:postcode":"38320",
    "sg:province":"Santa Cruz De Tenerife",
    "wof:name":"Perez Ramirez Manuel",
    "wof:placetype":"venue"
},
  "geometry": {"coordinates":[-16.2849597931,28.4706306458],"type":"Point"}
}