{
  "type": "Feature",
  "properties": {
    "addr:full":"A Igrexa(cela), 10 Iglesia A Coru\u00f1a 15668",
    "addr:housenumber":"10 iglesia a corun\u0303a",
    "addr:postcode":"15668",
    "addr:street":"A Igrexa Cela",
    "iso:country":"ES",
    "sg:address":"A Igrexa(cela), 10",
    "sg:city":"Iglesia",
    "sg:orig_category":"Discapacitados",
    "sg:phone":"+34 981 65 63 21",
    "sg:postcode":"15668",
    "sg:province":"A Coru\u00f1a",
    "wof:name":"Semiproducciones Trabes S.l. Cee",
    "wof:placetype":"venue"
},
  "geometry": {"coordinates":[-8.311167717,43.2987709045],"type":"Point"}
}