{
  "type": "Feature",
  "properties": {
    "iso:country":"ES",
    "sg:address":"Avda Europa (de), S/n",
    "sg:city":"Jerez De La Frontera",
    "sg:orig_category":"Juegos Y Juguetes (al Por Menor)",
    "sg:phone":"+34 956 31 79 10",
    "sg:postcode":"11405",
    "sg:province":"C\u00e1diz",
    "wof:name":"Juguetes Pastor S.l.",
    "wof:placetype":"venue"
},
  "geometry": {"coordinates":[-6.120223999,36.6962852478],"type":"Point"}
}