{
  "type": "Feature",
  "properties": {
    "iso:country":"ES",
    "sg:address":"Carrer de Josep Ricart, 43",
    "sg:city":"Sant Feliu Llobregat",
    "sg:orig_category":"Pescader\u00cdas (al Por Menor)",
    "sg:phone":"+34 936 66 04 39",
    "sg:postcode":"08980",
    "sg:province":"Barcelona",
    "wof:name":"Cruz Molina Juan",
    "wof:placetype":"venue"
},
  "geometry": {"coordinates":[2.0511898994,41.3831481934],"type":"Point"}
}