{
  "type": "Feature",
  "properties": {
    "addr:full":"Ctra. Toledo-avila, Km. 0030,0 Torrijos Toledo 45500",
    "addr:postcode":"45500",
    "addr:street":"Ctra. Toledo-Avila Km. 0030,0",
    "iso:country":"ES",
    "sg:address":"Ctra. Toledo-avila, Km. 0030,0",
    "sg:city":"Torrijos",
    "sg:orig_category":"Maquinaria Para Industrias Diversas",
    "sg:phone":"+34 925 77 13 15",
    "sg:postcode":"45500",
    "sg:province":"Toledo",
    "wof:name":"Maquinaria Obras Publicas A.nu\u00d1ez S.l.",
    "wof:placetype":"venue"
},
  "geometry": {"coordinates":[-4.2818388939,39.9835548401],"type":"Point"}
}