{
  "type": "Feature",
  "properties": {
    "addr:full":"Carr Dr Coca, 22 Igualada Barcelona 08700",
    "addr:housenumber":"22",
    "addr:postcode":"08700",
    "addr:street":"Carr Dr Coca",
    "iso:country":"ES",
    "sg:address":"Carr Dr Coca, 22",
    "sg:city":"Igualada",
    "sg:orig_category":"Bordado, Marcado A Medida",
    "sg:phone":"+34 938 05 11 06",
    "sg:postcode":"08700",
    "sg:province":"Barcelona",
    "wof:name":"Giralt Rodriguez Ana Maria",
    "wof:placetype":"venue"
},
  "geometry": {"coordinates":[1.627679944,41.5796051025],"type":"Point"}
}