{
  "type": "Feature",
  "properties": {
    "addr:full":"Praz Manuel Escuris, 4 Pobra Do Carami\u00e7al La Coru\u00f1a 15940",
    "addr:housenumber":"4",
    "addr:postcode":"15940",
    "addr:street":"Praz Manuel Escuris;Corun\u0303A",
    "iso:country":"ES",
    "sg:address":"Praz Manuel Escuris, 4",
    "sg:city":"Pobra Do Carami\u00e7al",
    "sg:orig_category":"Sociedades, Compa\u00d1\u00cdas Aseguradoras",
    "sg:phone":"+34 981 83 26 96",
    "sg:postcode":"15940",
    "sg:province":"La Coru\u00f1a",
    "wof:name":"Bandin Rosende Jose Luis",
    "wof:placetype":"venue"
},
  "geometry": {"coordinates":[-8.938949585,42.6065750122],"type":"Point"}
}