{
  "type": "Feature",
  "properties": {
    "iso:country":"ES",
    "sg:address":"Calle de Santa Ana, 14",
    "sg:city":"Estepa",
    "sg:orig_category":"Florister\u00cdas",
    "sg:phone":"+34 954 82 08 71",
    "sg:postcode":"41560",
    "sg:province":"Sevilla",
    "wof:name":"Jimenez Lopez Carmen",
    "wof:placetype":"venue"
},
  "geometry": {"coordinates":[-4.8770217896,37.2915916443],"type":"Point"}
}