{
  "type": "Feature",
  "properties": {
    "iso:country":"ES",
    "sg:address":"Ctra Plantio, 4",
    "sg:city":"Majadahonda",
    "sg:orig_category":"Inmobiliaria (agencias)",
    "sg:phone":"+34 916 39 18 41",
    "sg:postcode":"28220",
    "sg:province":"Madrid",
    "wof:name":"I.b.house S.l.",
    "wof:placetype":"venue"
},
  "geometry": {"coordinates":[-3.8609240055,40.4743881226],"type":"Point"}
}