{
  "type": "Feature",
  "properties": {
    "addr:full":"El Campo, S/n Soto Barco Asturias 33126",
    "addr:housenumber":"s / n",
    "addr:postcode":"33126",
    "addr:street":"El Campo;Asturias",
    "iso:country":"ES",
    "sg:address":"El Campo, S/n",
    "sg:city":"Soto Barco",
    "sg:orig_category":"Cerrajer\u00cda, Ferrallista",
    "sg:phone":"+34 985 58 80 46",
    "sg:postcode":"33126",
    "sg:province":"Asturias",
    "wof:name":"Mu\u00f1iz Garcia Maximino",
    "wof:placetype":"venue"
},
  "geometry": {"coordinates":[-6.0716300011,43.5324172974],"type":"Point"}
}