{
  "type": "Feature",
  "properties": {
    "addr:full":"Calle de Doctor Chil, 10 Palmas De Gran Canaria Las Palmas 35001",
    "addr:housenumber":"10",
    "addr:postcode":"35001",
    "addr:street":"Calle De Doctor Chil",
    "iso:country":"ES",
    "sg:address":"Calle de Doctor Chil, 10",
    "sg:city":"Palmas De Gran Canaria",
    "sg:orig_category":"Centros De Coordinaci\u00d3n",
    "sg:phone":"+34 928 31 16 50",
    "sg:postcode":"35001",
    "sg:province":"Las Palmas",
    "wof:name":"Parrado Artiles Maria Paz",
    "wof:placetype":"venue"
},
  "geometry": {"coordinates":[-15.4140520096,28.1000156403],"type":"Point"}
}