{
  "type": "Feature",
  "properties": {
    "iso:country":"ES",
    "sg:address":"Calle de Industrias, 6",
    "sg:city":"Talavera Reina",
    "sg:orig_category":"Mec\u00c1nico Del Autom\u00d3vil",
    "sg:phone":"+34 925 80 49 52",
    "sg:postcode":"45600",
    "sg:province":"Toledo",
    "wof:name":"Aragon Rizo Wifredo",
    "wof:placetype":"venue"
},
  "geometry": {"coordinates":[-4.8172502518,39.9607925415],"type":"Point"}
}