{
  "type": "Feature",
  "properties": {
    "addr:full":"Cordoba(p I Cruz Panaderos), 14 Torreperogil Ja\u00e9n 23320",
    "addr:housenumber":"14",
    "addr:postcode":"23320",
    "addr:street":"P I Cruz Panaderos",
    "iso:country":"ES",
    "sg:address":"Cordoba(p I Cruz Panaderos), 14",
    "sg:city":"Torreperogil",
    "sg:orig_category":"Empresas De Carpinter\u00cda De Madera",
    "sg:phone":"+34 953 77 61 27",
    "sg:postcode":"23320",
    "sg:province":"Ja\u00e9n",
    "wof:name":"Carpinteria Y Ebanisteria Hidalgo Perez S.l.",
    "wof:placetype":"venue"
},
  "geometry": {"coordinates":[-3.3047840595,38.0310058594],"type":"Point"}
}