{
  "type": "Feature",
  "properties": {
    "addr:full":"Calle de Gardea, 30 Llodio \u00c1lava 01400",
    "addr:housenumber":"30",
    "addr:postcode":"01400",
    "addr:street":"Calle De Gardea",
    "iso:country":"ES",
    "sg:address":"Calle de Gardea, 30",
    "sg:city":"Llodio",
    "sg:orig_category":"Polideportivos",
    "sg:phone":"+34 946 72 38 99",
    "sg:postcode":"01400",
    "sg:province":"\u00c1lava",
    "wof:name":"Ayuntamiento De Llodio",
    "wof:placetype":"venue"
},
  "geometry": {"coordinates":[-2.9787509441,43.127494812],"type":"Point"}
}