{
  "type": "Feature",
  "properties": {
    "iso:country":"ES",
    "sg:address":"Calle de Santiago Lozano, 14",
    "sg:city":"Granada",
    "sg:orig_category":"Bisuter\u00cda, Joyer\u00cda, Relojer\u00cda (al Por Menor)",
    "sg:phone":"+34 958 17 07 41",
    "sg:postcode":"18011",
    "sg:province":"Granada",
    "wof:name":"Martin Y Bolivar Cdad.",
    "wof:placetype":"venue"
},
  "geometry": {"coordinates":[-3.6015739441,37.1978759766],"type":"Point"}
}