{
  "type": "Feature",
  "properties": {
    "iso:country":"ES",
    "sg:address":"Calle de Santiago Lapuente, 6",
    "sg:city":"Zaragoza",
    "sg:orig_category":"Art\u00cdculos De Aluminio",
    "sg:phone":"+34 976 39 24 98",
    "sg:postcode":"50014",
    "sg:province":"Zaragoza",
    "wof:name":"Talleres Nalca S.cv.",
    "wof:placetype":"venue"
},
  "geometry": {"coordinates":[-0.8708809018,41.6590957642],"type":"Point"}
}