{
  "type": "Feature",
  "properties": {
    "addr:full":"Plaz San Andres, 18 Talavera Reina Toledo 45600",
    "addr:housenumber":"18",
    "addr:postcode":"45600",
    "addr:street":"Plaz San Andres",
    "iso:country":"ES",
    "sg:address":"Plaz San Andres, 18",
    "sg:city":"Talavera Reina",
    "sg:orig_category":"Adaptaciones, Acondicionamientos Especiales Para Veh\u00cdculos, Veh\u00cdculos Industriales",
    "sg:phone":"+34 925 81 74 03",
    "sg:postcode":"45600",
    "sg:province":"Toledo",
    "wof:name":"Tapicerias Del Automovil S.l.",
    "wof:placetype":"venue"
},
  "geometry": {"coordinates":[-4.8326292038,39.9584884644],"type":"Point"}
}