{
  "type": "Feature",
  "properties": {
    "iso:country":"ES",
    "sg:address":"Calle de Maracaibo, 6",
    "sg:city":"Grao",
    "sg:orig_category":"M\u00c9dicos: Medicina Interna",
    "sg:phone":"+34 964 28 07 99",
    "sg:postcode":"12100",
    "sg:province":"Castell\u00f3n",
    "wof:name":"Beltran Beltran Juan Manuel",
    "wof:placetype":"venue"
},
  "geometry": {"coordinates":[0.0210250001,39.9832038879],"type":"Point"}
}