{
  "type": "Feature",
  "properties": {
    "iso:country":"ES",
    "sg:address":"Calle de Ramon Y Cajal, 1",
    "sg:city":"Segovia",
    "sg:orig_category":"M\u00c9dicos: Estomatolog\u00cda",
    "sg:phone":"+34 921 43 11 52",
    "sg:postcode":"40002",
    "sg:province":"Segovia",
    "wof:name":"Blas Carbonero Alejandro De",
    "wof:placetype":"venue"
},
  "geometry": {"coordinates":[-4.1173529625,40.9432640076],"type":"Point"}
}