{
  "type": "Feature",
  "properties": {
    "addr:full":"Carrer de Torrent Llibre, 2 Cardedeu Barcelona 08440",
    "addr:housenumber":"2",
    "addr:postcode":"08440",
    "addr:street":"Carrer De Torrent Llibre",
    "iso:country":"ES",
    "sg:address":"Carrer de Torrent Llibre, 2",
    "sg:city":"Cardedeu",
    "sg:orig_category":"Galvanizaci\u00d3n, Esta\u00d1ado, Emplomado",
    "sg:phone":"+34 938 45 48 33",
    "sg:postcode":"08440",
    "sg:province":"Barcelona",
    "wof:name":"Recubrimientos Del Metal De Cardedeu S.l.",
    "wof:placetype":"venue"
},
  "geometry": {"coordinates":[2.3533198833,41.6394081116],"type":"Point"}
}