{
  "type": "Feature",
  "properties": {
    "addr:full":"Avia Puente Colgante, S/n Valladolid Valladolid 47014",
    "addr:housenumber":"s / n",
    "addr:postcode":"47014",
    "addr:street":"Puente Colgante",
    "iso:country":"ES",
    "sg:address":"Avia Puente Colgante, S/n",
    "sg:city":"Valladolid",
    "sg:orig_category":"Comercio De Cuadros, L\u00c1minas Y Reproducciones De Obras De Arte",
    "sg:phone":"+34 983 34 50 82",
    "sg:postcode":"47014",
    "sg:province":"Valladolid",
    "sg:website":"www.cuadrosparati.com",
    "wof:name":"Cuadros Para Ti S.l.",
    "wof:placetype":"venue"
},
  "geometry": {"coordinates":[-4.7453589439,41.6415557861],"type":"Point"}
}