{
  "type": "Feature",
  "properties": {
    "iso:country":"ES",
    "sg:address":"Trva Naval (la), 12",
    "sg:city":"Reinosa",
    "sg:orig_category":"Molduras, Junquillos, Listones Y Molduras Perforadas",
    "sg:phone":"+34 942 75 35 15",
    "sg:postcode":"39200",
    "sg:province":"Cantabria",
    "wof:name":"Gonzalez Lopez Concepcion",
    "wof:placetype":"venue"
},
  "geometry": {"coordinates":[-4.1362171173,42.9978942871],"type":"Point"}
}