{
  "type": "Feature",
  "properties": {
    "iso:country":"ES",
    "sg:address":"Calle de Ramon J, 1",
    "sg:city":"Huesca",
    "sg:orig_category":"Farmacias",
    "sg:phone":"+34 974 22 52 98",
    "sg:postcode":"22005",
    "sg:province":"Huesca",
    "wof:name":"Chacon Ferraz Enrrique",
    "wof:placetype":"venue"
},
  "geometry": {"coordinates":[-0.4032819867,42.1364440918],"type":"Point"}
}