{
  "type": "Feature",
  "properties": {
    "addr:full":"Carrer de Llevant, 48 Hospitalet Llobregat Barcelona 08905",
    "addr:housenumber":"48",
    "addr:postcode":"08905",
    "addr:street":"Carrer De Llevant",
    "iso:country":"ES",
    "sg:address":"Carrer de Llevant, 48",
    "sg:city":"Hospitalet Llobregat",
    "sg:orig_category":"Mec\u00c1nico Del Autom\u00d3vil",
    "sg:phone":"+34 934 49 98 45",
    "sg:postcode":"08905",
    "sg:province":"Barcelona",
    "wof:name":"Gallardo Lopez Juan Jose",
    "wof:placetype":"venue"
},
  "geometry": {"coordinates":[2.1094269753,41.3733329773],"type":"Point"}
}