{
  "type": "Feature",
  "properties": {
    "addr:full":"Cmno Cuesta El Reventon, 86 Cuesta El Reventon Las Palmas 35310",
    "addr:housenumber":"86",
    "addr:postcode":"35310",
    "addr:street":"Cmno Cuesta El Reventon;Cuesta El Reventon Las Palmas",
    "iso:country":"ES",
    "sg:address":"Cmno Cuesta El Reventon, 86",
    "sg:city":"Cuesta El Reventon",
    "sg:orig_category":"Doctores En Medicina",
    "sg:phone":"+34 928 35 17 69",
    "sg:postcode":"35310",
    "sg:province":"Las Palmas",
    "wof:name":"Melian Perez-marin Agustin",
    "wof:placetype":"venue"
},
  "geometry": {"coordinates":[-15.4758090973,28.0502548218],"type":"Point"}
}