{
  "type": "Feature",
  "properties": {
    "addr:full":"Calle de San Jose De Calasanz, 15 Valencia Valencia 46008",
    "addr:housenumber":"15",
    "addr:postcode":"46008",
    "addr:street":"Calle De San;De Calasanz",
    "iso:country":"ES",
    "sg:address":"Calle de San Jose De Calasanz, 15",
    "sg:city":"Valencia",
    "sg:orig_category":"Reposter\u00cdas",
    "sg:phone":"+34 963 85 14 21",
    "sg:postcode":"46008",
    "sg:province":"Valencia",
    "wof:name":"Martinez Benlloch Jose",
    "wof:placetype":"venue"
},
  "geometry": {"coordinates":[-0.3882830143,39.4666404724],"type":"Point"}
}