{
  "type": "Feature",
  "properties": {
    "addr:full":"Calle de Villaamil, 19 Madrid Madrid 28039",
    "addr:housenumber":"19",
    "addr:postcode":"madrid;28039",
    "addr:street":"Calle De Villaamil",
    "iso:country":"ES",
    "sg:address":"Calle de Villaamil, 19",
    "sg:city":"Madrid",
    "sg:orig_category":"Arquitectos",
    "sg:phone":"+34 913 11 71 88",
    "sg:postcode":"28039",
    "sg:province":"Madrid",
    "wof:name":"Hernandez Nu\u00f1ez Carlos",
    "wof:placetype":"venue"
},
  "geometry": {"coordinates":[-3.7063679695,40.457862854],"type":"Point"}
}