{
  "type": "Feature",
  "properties": {
    "addr:full":"Carr Torrent Vallmajor, 14 Badalona Barcelona 08911",
    "addr:housenumber":"14",
    "addr:postcode":"08911",
    "addr:street":"Carr Torrent Vallmajor",
    "iso:country":"ES",
    "sg:address":"Carr Torrent Vallmajor, 14",
    "sg:city":"Badalona",
    "sg:orig_category":"Artes Gr\u00c1ficas, Artes Pl\u00c1sticas (curso)",
    "sg:phone":"+34 933 84 76 76",
    "sg:postcode":"08911",
    "sg:province":"Barcelona",
    "wof:name":"Sociedad Anonima De Litografia",
    "wof:placetype":"venue"
},
  "geometry": {"coordinates":[2.2611489296,41.4575233459],"type":"Point"}
}