{
  "type": "Feature",
  "properties": {
    "addr:full":"Avda Martires, 21 Carral La Coru\u00f1a 15175",
    "addr:housenumber":"21",
    "addr:postcode":"15175",
    "addr:street":"Avda Martires;La Corun\u0303A",
    "iso:country":"ES",
    "sg:address":"Avda Martires, 21",
    "sg:city":"Carral",
    "sg:orig_category":"Librer\u00cdas",
    "sg:phone":"+34 981 67 02 02",
    "sg:postcode":"15175",
    "sg:province":"La Coru\u00f1a",
    "wof:name":"Lareo Insua Blanca Maria",
    "wof:placetype":"venue"
},
  "geometry": {"coordinates":[-8.3558893204,43.2278442383],"type":"Point"}
}