{
  "type": "Feature",
  "properties": {
    "iso:country":"ES",
    "sg:address":"Calle de Doctor Fernando Escobar, 4",
    "sg:city":"Granada",
    "sg:orig_category":"Electricidad Veh\u00cdculo",
    "sg:phone":"+34 958 29 59 29",
    "sg:postcode":"18012",
    "sg:province":"Granada",
    "wof:name":"Manzano Rodriguez Jose Miguel",
    "wof:placetype":"venue"
},
  "geometry": {"coordinates":[-3.6085240841,37.1899986267],"type":"Point"}
}