{
  "type": "Feature",
  "properties": {
    "iso:country":"ES",
    "sg:address":"Gudarien Plaza, 6",
    "sg:city":"Hernani",
    "sg:orig_category":"Arquitectos",
    "sg:phone":"+34 943 55 22 33",
    "sg:postcode":"20120",
    "sg:province":"Guip\u00f9zcoa",
    "wof:name":"Rezola Azpiazu Juan Miguel",
    "wof:placetype":"venue"
},
  "geometry": {"coordinates":[-1.9755049944,43.2652702332],"type":"Point"}
}