{
  "type": "Feature",
  "properties": {
    "addr:full":"B, 16 P. I. El Romeral Valencia 46340",
    "addr:housenumber":"16",
    "addr:postcode":"46340",
    "addr:street":"P. I. El",
    "iso:country":"ES",
    "sg:address":"B, 16",
    "sg:city":"P. I. El Romeral",
    "sg:orig_category":"Aparatos E Instalaci\u00d3n De Regad\u00cdos",
    "sg:phone":"+34 962 30 60 66",
    "sg:postcode":"46340",
    "sg:province":"Valencia",
    "wof:name":"Dyf Riego S. L.",
    "wof:placetype":"venue"
},
  "geometry": {"coordinates":[-1.0998990536,39.4906158447],"type":"Point"}
}