{
  "type": "Feature",
  "properties": {
    "iso:country":"ES",
    "sg:address":"Avda Camelias, 112",
    "sg:city":"Vigo",
    "sg:orig_category":"Bazares, Art\u00cdculos De Limpieza Y De Cocina (al Por Menor)",
    "sg:phone":"+34 986 23 93 60",
    "sg:postcode":"36211",
    "sg:province":"Pontevedra",
    "wof:name":"Mirpuri  Tarachand Jawaharmal",
    "wof:placetype":"venue"
},
  "geometry": {"coordinates":[-8.729724884,42.2251243591],"type":"Point"}
}