{
  "type": "Feature",
  "properties": {
    "addr:full":"Pla\u00c7 L'ajuntament, 2 Mollerussa Lleida 25230",
    "addr:housenumber":"2",
    "addr:postcode":"25230",
    "addr:street":"L'Ajuntament",
    "iso:country":"ES",
    "sg:address":"Pla\u00c7 L'ajuntament, 2",
    "sg:city":"Mollerussa",
    "sg:orig_category":"Bisuter\u00cda, Joyer\u00cda, Relojer\u00cda (al Por Menor)",
    "sg:phone":"+34 973 60 01 28",
    "sg:postcode":"25230",
    "sg:province":"Lleida",
    "wof:name":"Pascual Plaza Jaime",
    "wof:placetype":"venue"
},
  "geometry": {"coordinates":[0.8936830163,41.6300392151],"type":"Point"}
}