{
  "type": "Feature",
  "properties": {
    "addr:full":"Carrer de Rossello, 233 Barcelona Barcelona 08008",
    "addr:housenumber":"233",
    "addr:postcode":"08008",
    "addr:street":"Carrer De Rossello",
    "iso:country":"ES",
    "sg:address":"Carrer de Rossello, 233",
    "sg:city":"Barcelona",
    "sg:orig_category":"Estudios De Grabaci\u00d3n Sonora",
    "sg:phone":"+34 932 37 07 80",
    "sg:postcode":"08008",
    "sg:province":"Barcelona",
    "wof:name":"Vicious Records S.l.",
    "wof:placetype":"venue"
},
  "geometry": {"coordinates":[2.1580059528,41.3940162659],"type":"Point"}
}