{
  "type": "Feature",
  "properties": {
    "addr:full":"Avda Garat Txomin, 4 Bilbao Vizcaya 48004",
    "addr:housenumber":"4",
    "addr:postcode":"48004",
    "addr:street":"Avda Garat Txomin",
    "iso:country":"ES",
    "sg:address":"Avda Garat Txomin, 4",
    "sg:city":"Bilbao",
    "sg:orig_category":"Ense\u00d1anza: Costura",
    "sg:phone":"+34 944 12 31 94",
    "sg:postcode":"48004",
    "sg:province":"Vizcaya",
    "wof:name":"Aguinagalde Portillo Pilar",
    "wof:placetype":"venue"
},
  "geometry": {"coordinates":[-2.9090950489,43.2571678162],"type":"Point"}
}