{
  "type": "Feature",
  "properties": {
    "addr:full":"Carrer de Rubio I Ors, 149 Cornella Llobregat Barcelona 08940",
    "addr:housenumber":"149",
    "addr:postcode":"08940",
    "addr:street":"Carrer De Rubio;Ors",
    "iso:country":"ES",
    "sg:address":"Carrer de Rubio I Ors, 149",
    "sg:city":"Cornella Llobregat",
    "sg:orig_category":"Asociaciones Y Clubs Deportivos",
    "sg:phone":"+34 934 74 41 06",
    "sg:postcode":"08940",
    "sg:province":"Barcelona",
    "wof:name":"Rugby Club Cornella",
    "wof:placetype":"venue"
},
  "geometry": {"coordinates":[2.0718300343,41.3527069092],"type":"Point"}
}