{
  "type": "Feature",
  "properties": {
    "addr:full":"Ptda El Altet, 136 El Altet Alicante 03195",
    "addr:housenumber":"136",
    "addr:postcode":"03195",
    "addr:street":"Ptda El Altet;El Altet",
    "iso:country":"ES",
    "sg:address":"Ptda El Altet, 136",
    "sg:city":"El Altet",
    "sg:orig_category":"Alquiler De Veh\u00cdculos: Turismos Y Utilitarios",
    "sg:phone":"+34 965 68 37 71",
    "sg:postcode":"03195",
    "sg:province":"Alicante",
    "wof:name":"Alquileres De Coches Victoria S.l.",
    "wof:placetype":"venue"
},
  "geometry": {"coordinates":[-0.5396962762,38.2723426819],"type":"Point"}
}