{
  "type": "Feature",
  "properties": {
    "addr:full":"Calle de Pilarillo Seco, 8 Palmas De Gran Canaria Las Palmas 35002",
    "addr:housenumber":"8",
    "addr:postcode":"35002",
    "addr:street":"Calle De Pilarillo Seco",
    "iso:country":"ES",
    "sg:address":"Calle de Pilarillo Seco, 8",
    "sg:city":"Palmas De Gran Canaria",
    "sg:orig_category":"Agencias Y Agentes Comerciales, Representantes",
    "sg:phone":"+34 928 38 33 47",
    "sg:postcode":"35002",
    "sg:province":"Las Palmas",
    "wof:name":"Suarez Garcia Marcos",
    "wof:placetype":"venue"
},
  "geometry": {"coordinates":[-15.4160804749,28.1078605652],"type":"Point"}
}