{
  "type": "Feature",
  "properties": {
    "addr:full":"Carrer de Bou, 10 Llerona Barcelona 08520",
    "addr:housenumber":"10",
    "addr:postcode":"08520",
    "addr:street":"Carrer De Bou",
    "iso:country":"ES",
    "sg:address":"Carrer de Bou, 10",
    "sg:city":"Llerona",
    "sg:orig_category":"Industria Qu\u00cdmica",
    "sg:phone":"+34 938 49 39 00",
    "sg:postcode":"08520",
    "sg:province":"Barcelona",
    "wof:name":"Hijos De Canuto Vila S.a.",
    "wof:placetype":"venue"
},
  "geometry": {"coordinates":[2.2992899418,41.6361808777],"type":"Point"}
}