{
  "type": "Feature",
  "properties": {
    "iso:country":"ES",
    "sg:address":"Ctra Agramunt, 39",
    "sg:city":"Artesa Segre",
    "sg:orig_category":"Quincaller\u00cda (al Por Menor)",
    "sg:phone":"+34 973 40 00 61",
    "sg:postcode":"25730",
    "sg:province":"Lleida",
    "wof:name":"Capell Sole Montserrat",
    "wof:placetype":"venue"
},
  "geometry": {"coordinates":[1.0469249487,41.8942489624],"type":"Point"}
}