{
  "type": "Feature",
  "properties": {
    "addr:full":"Calle de Noria (de La), 14 Altorreal Murcia 30500",
    "addr:housenumber":"14",
    "addr:postcode":"30500",
    "addr:street":"Calle De Noria De La",
    "iso:country":"ES",
    "sg:address":"Calle de Noria (de La), 14",
    "sg:city":"Altorreal",
    "sg:orig_category":"Agencias Y Agentes Comerciales, Representantes",
    "sg:phone":"+34 968 64 97 64",
    "sg:postcode":"30500",
    "sg:province":"Murcia",
    "wof:name":"Parra Lopez Antonio",
    "wof:placetype":"venue"
},
  "geometry": {"coordinates":[-1.1643129587,38.0754699707],"type":"Point"}
}