{
  "type": "Feature",
  "properties": {
    "addr:full":"Calle de Marques De Vistabella, 21 Motril Granada 18600",
    "addr:housenumber":"21",
    "addr:postcode":"18600",
    "addr:street":"Calle De Marques De Vistabella",
    "iso:country":"ES",
    "sg:address":"Calle de Marques De Vistabella, 21",
    "sg:city":"Motril",
    "sg:orig_category":"Zapatos (al Por Menor)",
    "sg:phone":"+34 958 60 01 82",
    "sg:postcode":"18600",
    "sg:province":"Granada",
    "wof:name":"Soria Sanchez Maria Isabel",
    "wof:placetype":"venue"
},
  "geometry": {"coordinates":[-3.5176208019,36.7453994751],"type":"Point"}
}