{
  "type": "Feature",
  "properties": {
    "addr:full":"Calle de Manuel Andujar, 18 Vilches Ja\u00e9n 23220",
    "addr:housenumber":"18",
    "addr:postcode":"23220",
    "addr:street":"Calle De Manuel Andujar;Jae\u0301N",
    "iso:country":"ES",
    "sg:address":"Calle de Manuel Andujar, 18",
    "sg:city":"Vilches",
    "sg:orig_category":"T\u00c9cnicos Veterinarios",
    "sg:phone":"+34 953 63 21 80",
    "sg:postcode":"23220",
    "sg:province":"Ja\u00e9n",
    "wof:name":"Morejon De La Torre Manuel Jesus",
    "wof:placetype":"venue"
},
  "geometry": {"coordinates":[-3.5132849216,38.2127227783],"type":"Point"}
}