{
  "type": "Feature",
  "properties": {
    "addr:full":"Avda Pintor Felo Monzon, S/n Palmas De Gran Canaria Las Palmas 35019",
    "addr:housenumber":"s",
    "addr:postcode":"35019",
    "addr:street":"Avda Pintor Felo Monzon;/ N",
    "iso:country":"ES",
    "sg:address":"Avda Pintor Felo Monzon, S/n",
    "sg:city":"Palmas De Gran Canaria",
    "sg:orig_category":"Bisuter\u00cda, Joyer\u00cda, Relojer\u00cda (al Por Menor)",
    "sg:phone":"+34 928 41 39 58",
    "sg:postcode":"35019",
    "sg:province":"Las Palmas",
    "wof:name":"Mazatlan S.l.",
    "wof:placetype":"venue"
},
  "geometry": {"coordinates":[-15.4527931213,28.1041984558],"type":"Point"}
}