{
  "type": "Feature",
  "properties": {
    "addr:full":"Ptge Arnau De Vilanova, 5 Reus Tarragona 43203",
    "addr:housenumber":"5",
    "addr:postcode":"43203",
    "addr:street":"Ptge Arnau De Vilanova",
    "iso:country":"ES",
    "sg:address":"Ptge Arnau De Vilanova, 5",
    "sg:city":"Reus",
    "sg:orig_category":"Ingeniero",
    "sg:phone":"+34 977 31 28 51",
    "sg:postcode":"43203",
    "sg:province":"Tarragona",
    "wof:name":"Gasso Garreta Jose Angel",
    "wof:placetype":"venue"
},
  "geometry": {"coordinates":[1.1099410057,41.163734436],"type":"Point"}
}