{
  "type": "Feature",
  "properties": {
    "addr:full":"Carrer de Tangel, 9 Mutxamel Alicante 03110",
    "addr:housenumber":"9",
    "addr:postcode":"03110",
    "addr:street":"Carrer De Tangel",
    "iso:country":"ES",
    "sg:address":"Carrer de Tangel, 9",
    "sg:city":"Mutxamel",
    "sg:orig_category":"Empresas De Escayolas",
    "sg:phone":"+34 965 95 52 61",
    "sg:postcode":"03110",
    "sg:province":"Alicante",
    "wof:name":"Salazar Rubio Eugenio",
    "wof:placetype":"venue"
},
  "geometry": {"coordinates":[-0.4515430033,38.4197845459],"type":"Point"}
}