{
  "type": "Feature",
  "properties": {
    "iso:country":"ES",
    "sg:address":"C/ Severino Albarracin, 22",
    "sg:city":"Alcoi",
    "sg:orig_category":"Reciclaje, Tratamiento De Tejidos",
    "sg:phone":"+34 965 33 21 47",
    "sg:postcode":"03804",
    "sg:province":"Alicante",
    "wof:name":"Prepal S. L.",
    "wof:placetype":"venue"
},
  "geometry": {"coordinates":[-0.4738390148,38.7076187134],"type":"Point"}
}