{
  "type": "Feature",
  "properties": {
    "addr:full":"Calle de Porto Cristo, 8 Alcorcon Madrid 28924",
    "addr:housenumber":"8",
    "addr:postcode":"28924",
    "addr:street":"Calle De Porto Cristo",
    "iso:country":"ES",
    "sg:address":"Calle de Porto Cristo, 8",
    "sg:city":"Alcorcon",
    "sg:orig_category":"Inform\u00c1tica (estudios, Servicios, Asesor\u00cda, Formaci\u00d3n)",
    "sg:phone":"+34 916 12 24 14",
    "sg:postcode":"28924",
    "sg:province":"Madrid",
    "wof:name":"Soluciones Informaticas Europeas S.l.",
    "wof:placetype":"venue"
},
  "geometry": {"coordinates":[-3.8164839745,40.350643158],"type":"Point"}
}