{
  "type": "Feature",
  "properties": {
    "iso:country":"ES",
    "sg:address":"Calle de Francisco Javier De Moya, 48",
    "sg:city":"Albacete",
    "sg:orig_category":"Molduras, Junquillos, Listones Y Molduras Perforadas",
    "sg:phone":"+34 967 24 30 08",
    "sg:postcode":"02006",
    "sg:province":"Albacete",
    "wof:name":"Gonzalez Sanchez Adolfino",
    "wof:placetype":"venue"
},
  "geometry": {"coordinates":[-1.8480855227,38.9859352112],"type":"Point"}
}