{
  "type": "Feature",
  "properties": {
    "addr:full":"Calle de Rico, 50 Huelva Huelva 21001",
    "addr:housenumber":"50",
    "addr:postcode":"21001",
    "addr:street":"Calle De Rico",
    "iso:country":"ES",
    "sg:address":"Calle de Rico, 50",
    "sg:city":"Huelva",
    "sg:orig_category":"Mutuas De Seguros",
    "sg:phone":"+34 959 25 32 23",
    "sg:postcode":"21001",
    "sg:province":"Huelva",
    "wof:name":"Mutua De Ceuta-smat",
    "wof:placetype":"venue"
},
  "geometry": {"coordinates":[-6.9530668259,37.2544898987],"type":"Point"}
}