{
  "type": "Feature",
  "properties": {
    "iso:country":"ES",
    "sg:address":"Calle de Maria La Judia, 10",
    "sg:city":"Cordoba",
    "sg:orig_category":"M\u00c9dicos: Cirug\u00cda Pl\u00c1stica, Reconstructiva Y Est\u00c9tica",
    "sg:phone":"+34 957 40 51 83",
    "sg:postcode":"14011",
    "sg:province":"C\u00f3rdoba",
    "wof:name":"Rodriguez Nu\u00f1ez Gloria",
    "wof:placetype":"venue"
},
  "geometry": {"coordinates":[-4.796901226,37.8962287903],"type":"Point"}
}