{
  "type": "Feature",
  "properties": {
    "iso:country":"ES",
    "sg:address":"Calle de Zamora, 58",
    "sg:city":"Salamanca",
    "sg:orig_category":"Procuradores",
    "sg:phone":"+34 923 26 20 76",
    "sg:postcode":"37002",
    "sg:province":"Salamanca",
    "wof:name":"Martin Garcia Antonio Luis",
    "wof:placetype":"venue"
},
  "geometry": {"coordinates":[-5.6636538506,40.968296051],"type":"Point"}
}