{
  "type": "Feature",
  "properties": {
    "iso:country":"ES",
    "sg:address":"Poli Industrial C/s, 16",
    "sg:city":"Rozas De Madrid",
    "sg:orig_category":"Paneles De Madera: Contrachapados, Fibras, Particulados, Estratificados (fabricaci\u00d3n, Venta)",
    "sg:phone":"+34 916 37 51 75",
    "sg:postcode":"28230",
    "sg:province":"Madrid",
    "wof:name":"Bricoalmacen Las Rozas S.l.",
    "wof:placetype":"venue"
},
  "geometry": {"coordinates":[-3.8913800716,40.5247497559],"type":"Point"}
}