{
  "type": "Feature",
  "properties": {
    "addr:full":"Calle de Colon De Larreategui, 24 Bilbao Vizcaya 48009",
    "addr:housenumber":"24",
    "addr:postcode":"48009",
    "addr:street":"Calle De Colon De Larreategui",
    "iso:country":"ES",
    "sg:address":"Calle de Colon De Larreategui, 24",
    "sg:city":"Bilbao",
    "sg:orig_category":"Perfumer\u00cda (al Por Menor)",
    "sg:phone":"+34 944 24 21 20",
    "sg:postcode":"48009",
    "sg:province":"Vizcaya",
    "sg:website":"www.marionnaud.es",
    "wof:name":"Marionnaud Perfumeries Iberica S.l.",
    "wof:placetype":"venue"
},
  "geometry": {"coordinates":[-2.9321095943,43.2634811401],"type":"Point"}
}