{
  "type": "Feature",
  "properties": {
    "addr:full":"Calle de San Pedro, S/n Ag\u00fcero Huesca 22808",
    "addr:postcode":"22808",
    "addr:street":"Calle De San Pedro S / N Agueero",
    "iso:country":"ES",
    "sg:address":"Calle de San Pedro, S/n",
    "sg:city":"Ag\u00fcero",
    "sg:orig_category":"Hoteles",
    "sg:phone":"+34 974 38 03 30",
    "sg:postcode":"22808",
    "sg:province":"Huesca",
    "wof:name":"Artigas Arguis Eugenio",
    "wof:placetype":"venue"
},
  "geometry": {"coordinates":[-0.7935128212,42.3561096191],"type":"Point"}
}