{
  "type": "Feature",
  "properties": {
    "addr:full":"Ctra Palamos, 51 Celra Girona 17460",
    "addr:housenumber":"51",
    "addr:postcode":"17460",
    "addr:street":"Ctra Palamos",
    "iso:country":"ES",
    "sg:address":"Ctra Palamos, 51",
    "sg:city":"Celra",
    "sg:orig_category":"Venta, Instalaci\u00d3n, Mantenimiento De Chimeneas De Interior Y Accesorios",
    "sg:phone":"+34 972 49 30 00",
    "sg:postcode":"17460",
    "sg:province":"Girona",
    "wof:name":"Clot Roca Josep Maria",
    "wof:placetype":"venue"
},
  "geometry": {"coordinates":[2.8902919292,42.03175354],"type":"Point"}
}