{
  "type": "Feature",
  "properties": {
    "iso:country":"ES",
    "sg:address":"Pol Ind Otsango Adu 16, 14",
    "sg:city":"Lesaka",
    "sg:orig_category":"Centros Empresariales",
    "sg:phone":"+34 948 63 80 52",
    "sg:postcode":"31770",
    "sg:province":"Navarra",
    "wof:name":"Trans Txakain S.l.",
    "wof:placetype":"venue"
},
  "geometry": {"coordinates":[-1.7035230398,43.2495765686],"type":"Point"}
}