{
  "type": "Feature",
  "properties": {
    "addr:full":"Calle de Victor Gorzo, 20 Bejar Salamanca 37700",
    "addr:housenumber":"20",
    "addr:postcode":"37700",
    "addr:street":"Calle De Victor Gorzo",
    "iso:country":"ES",
    "sg:address":"Calle de Victor Gorzo, 20",
    "sg:city":"Bejar",
    "sg:orig_category":"Hielo Artificial (fabricaci\u00d3n, Distribuci\u00d3n)",
    "sg:phone":"+34 923 41 10 22",
    "sg:postcode":"37700",
    "sg:province":"Salamanca",
    "wof:name":"Redondo Sanchez Maria Jesus",
    "wof:placetype":"venue"
},
  "geometry": {"coordinates":[-5.7705430984,40.3884239197],"type":"Point"}
}