{
  "type": "Feature",
  "properties": {
    "addr:full":"Av Sarria, 102 Barcelona Barcelona 08017",
    "addr:housenumber":"102",
    "addr:postcode":"08017",
    "addr:street":"Av Sarria",
    "iso:country":"ES",
    "sg:address":"Av Sarria, 102",
    "sg:city":"Barcelona",
    "sg:orig_category":"Inversiones",
    "sg:phone":"+34 932 80 10 34",
    "sg:postcode":"08017",
    "sg:province":"Barcelona",
    "wof:name":"Westinvest Gesellschaft Fur Inv.",
    "wof:placetype":"venue"
},
  "geometry": {"coordinates":[2.1339643002,41.3920135498],"type":"Point"}
}