{
  "type": "Feature",
  "properties": {
    "addr:full":"Carrer de Almansa, 5 Barcelona Barcelona 08042",
    "addr:housenumber":"5",
    "addr:postcode":"08042",
    "addr:street":"Carrer De Almansa",
    "iso:country":"ES",
    "sg:address":"Carrer de Almansa, 5",
    "sg:city":"Barcelona",
    "sg:orig_category":"Ropa Para Se\u00d1oras (al Por Menor)",
    "sg:phone":"+34 933 54 78 59",
    "sg:postcode":"08042",
    "sg:province":"Barcelona",
    "wof:name":"Salvador Y Puig S.l.",
    "wof:placetype":"venue"
},
  "geometry": {"coordinates":[2.1766591072,41.4414253235],"type":"Point"}
}