{
  "type": "Feature",
  "properties": {
    "iso:country":"ES",
    "sg:address":"Plaz Federico Garcia Lorca, 17",
    "sg:city":"Talavera Reina",
    "sg:orig_category":"Fabricaci\u00d3n De Juegos Y Juguetes",
    "sg:phone":"+34 925 80 42 23",
    "sg:postcode":"45600",
    "sg:province":"Toledo",
    "wof:name":"Play Scala S.l.",
    "wof:placetype":"venue"
},
  "geometry": {"coordinates":[-4.8326292038,39.9584884644],"type":"Point"}
}