{
  "type": "Feature",
  "properties": {
    "addr:full":"Foruen Pasealekua, 1 Ordizia Guip\u00f9zcoa 20240",
    "addr:housenumber":"1",
    "addr:postcode":"20240",
    "addr:street":"Foruen Pasealekua;Guipu\u0300Zcoa",
    "iso:country":"ES",
    "sg:address":"Foruen Pasealekua, 1",
    "sg:city":"Ordizia",
    "sg:orig_category":"Molduras, Junquillos, Listones Y Molduras Perforadas",
    "sg:phone":"+34 943 88 00 48",
    "sg:postcode":"20240",
    "sg:province":"Guip\u00f9zcoa",
    "wof:name":"Ansorena Iriarte Mari Carmen",
    "wof:placetype":"venue"
},
  "geometry": {"coordinates":[-2.1779079437,43.0544509888],"type":"Point"}
}