{
  "type": "Feature",
  "properties": {
    "iso:country":"ES",
    "sg:address":"Avda Los Olmos, 1",
    "sg:city":"Vitoria-gasteiz",
    "sg:orig_category":"Transportes Por V\u00cdas Navegables",
    "sg:phone":"+34 945 12 20 65",
    "sg:postcode":"01013",
    "sg:province":"\u00c1lava",
    "wof:name":"Transportes Jauregui Quincoces",
    "wof:placetype":"venue"
},
  "geometry": {"coordinates":[-2.6840889454,42.8761367798],"type":"Point"}
}