{
  "type": "Feature",
  "properties": {
    "addr:full":"Huerta De San Juan De Dios, S/n Los Villares Ja\u00e9n 23160",
    "addr:housenumber":"s / n",
    "addr:postcode":"23160",
    "addr:street":"Juan;Dios",
    "iso:country":"ES",
    "sg:address":"Huerta De San Juan De Dios, S/n",
    "sg:city":"Los Villares",
    "sg:orig_category":"Muebles",
    "sg:phone":"+34 953 32 10 08",
    "sg:postcode":"23160",
    "sg:province":"Ja\u00e9n",
    "wof:name":"Fernandez Del Moral Cristino",
    "wof:placetype":"venue"
},
  "geometry": {"coordinates":[-3.8196389675,37.6900253296],"type":"Point"}
}