{
  "type": "Feature",
  "properties": {
    "iso:country":"ES",
    "sg:address":"Avda Pablo Picasso, 28",
    "sg:city":"Granada",
    "sg:orig_category":"Supermercados Y Hipermercados",
    "sg:phone":"+34 958 81 71 14",
    "sg:postcode":"18008",
    "sg:province":"Granada",
    "wof:name":"Alimentacion Patri S. A.",
    "wof:placetype":"venue"
},
  "geometry": {"coordinates":[-3.59375,37.165309906],"type":"Point"}
}