{
  "type": "Feature",
  "properties": {
    "addr:full":"Ctra Sabadell, 14 Rubi Barcelona 08191",
    "addr:housenumber":"14",
    "addr:postcode":"08191",
    "addr:street":"Ctra Sabadell",
    "iso:country":"ES",
    "sg:address":"Ctra Sabadell, 14",
    "sg:city":"Rubi",
    "sg:orig_category":"Molduras, Junquillos, Listones Y Molduras Perforadas",
    "sg:phone":"+34 935 88 00 42",
    "sg:postcode":"08191",
    "sg:province":"Barcelona",
    "wof:name":"Rio Garcia Maria Luisa",
    "wof:placetype":"venue"
},
  "geometry": {"coordinates":[2.0322771072,41.4974021912],"type":"Point"}
}