{
  "type": "Feature",
  "properties": {
    "addr:full":"Avda Juan Carlos I, S/n Espinardo Murcia 30008",
    "addr:housenumber":"s / n",
    "addr:postcode":"30008",
    "addr:street":"Avda Juan Carlos I",
    "iso:country":"ES",
    "sg:address":"Avda Juan Carlos I, S/n",
    "sg:city":"Espinardo",
    "sg:orig_category":"Supermercados Y Hipermercados",
    "sg:phone":"+34 968 24 56 80",
    "sg:postcode":"30008",
    "sg:province":"Murcia",
    "sg:website":"www.mercadona.es",
    "wof:name":"Mercadona S.a.",
    "wof:placetype":"venue"
},
  "geometry": {"coordinates":[-1.1320890188,37.9943161011],"type":"Point"}
}