{
  "type": "Feature",
  "properties": {
    "addr:full":"Calle de Sarasate, 1 Ribaforada Navarra 31550",
    "addr:housenumber":"1",
    "addr:postcode":"31550",
    "addr:street":"Calle De Sarasate",
    "iso:country":"ES",
    "sg:address":"Calle de Sarasate, 1",
    "sg:city":"Ribaforada",
    "sg:orig_category":"Empresas De Impermeabilizaci\u00d3n",
    "sg:phone":"+34 948 86 40 00",
    "sg:postcode":"31550",
    "sg:province":"Navarra",
    "wof:name":"Aislamientos Euna S.l.",
    "wof:placetype":"venue"
},
  "geometry": {"coordinates":[-1.5105868578,41.9963378906],"type":"Point"}
}