{
  "type": "Feature",
  "properties": {
    "addr:full":"Avda Lugo (de), 46 Monterroso Lugo 27560",
    "addr:housenumber":"46",
    "addr:postcode":"27560",
    "addr:street":"Avda Lugo De",
    "iso:country":"ES",
    "sg:address":"Avda Lugo (de), 46",
    "sg:city":"Monterroso",
    "sg:orig_category":"Asociaciones Y Clubs Deportivos",
    "sg:phone":"+34 982 37 80 72",
    "sg:postcode":"27560",
    "sg:province":"Lugo",
    "wof:name":"Gomez Vazquez Maria Luz",
    "wof:placetype":"venue"
},
  "geometry": {"coordinates":[-7.8335309029,42.7923240662],"type":"Point"}
}