{
  "type": "Feature",
  "properties": {
    "iso:country":"ES",
    "sg:address":"Av Pais Valenciano, 123",
    "sg:city":"Guardamar Segura",
    "sg:orig_category":"Inform\u00c1tica (estudios, Servicios, Asesor\u00cda, Formaci\u00d3n)",
    "sg:phone":"+34 965 72 44 68",
    "sg:postcode":"03140",
    "sg:province":"Alicante",
    "sg:website":"www.luanet.com",
    "wof:name":"Kinelium Ideas En Desarrollo S.l.",
    "wof:placetype":"venue"
},
  "geometry": {"coordinates":[-0.6545320153,38.0833396912],"type":"Point"}
}