{
  "type": "Feature",
  "properties": {
    "iso:country":"ES",
    "sg:address":"Calle de Montera, 2",
    "sg:city":"Madrid",
    "sg:orig_category":"Zapatos (al Por Menor)",
    "sg:phone":"+34 915 22 69 00",
    "sg:postcode":"28013",
    "sg:province":"Madrid",
    "wof:name":"Rey Piedrola Maria Dolores",
    "wof:placetype":"venue"
},
  "geometry": {"coordinates":[-3.7028849125,40.4172019958],"type":"Point"}
}