{
  "type": "Feature",
  "properties": {
    "iso:country":"ES",
    "sg:address":"Calle de Portugal, 18",
    "sg:city":"Zaragoza",
    "sg:orig_category":"Ropa De Trabajo Y Profesionales (al Por Menor)",
    "sg:phone":"+34 976 33 28 85",
    "sg:postcode":"50010",
    "sg:province":"Zaragoza",
    "wof:name":"Confecciones Dona S. C.",
    "wof:placetype":"venue"
},
  "geometry": {"coordinates":[-0.9019839764,41.6503982544],"type":"Point"}
}