{
  "type": "Feature",
  "properties": {
    "iso:country":"ES",
    "sg:address":"C/ Mossen Jacint Verdaguer, 42",
    "sg:city":"Banyoles",
    "sg:orig_category":"Carnicer\u00cdas, Carnicer\u00cdas",
    "sg:phone":"+34 972 57 48 65",
    "sg:postcode":"17820",
    "sg:province":"Girona",
    "wof:name":"Planells Maso Josep",
    "wof:placetype":"venue"
},
  "geometry": {"coordinates":[2.7616260052,42.1173934937],"type":"Point"}
}