{
  "type": "Feature",
  "properties": {
    "addr:full":"Calle de Cirilo Amoros, 47 Valencia Valencia 46004",
    "addr:housenumber":"47",
    "addr:postcode":"46004",
    "addr:street":"Calle De Cirilo Amoros",
    "iso:country":"ES",
    "sg:address":"Calle de Cirilo Amoros, 47",
    "sg:city":"Valencia",
    "sg:classifiers":[
        {
            "category":"Arts & Performance",
            "subcategory":"Art Gallery",
            "type":"Entertainment"
        }
    ],
    "sg:phone":"+34 963 52 30 84",
    "sg:postcode":"46004",
    "sg:province":"Valencia",
    "sg:tags":[
        "arte",
        "de",
        "galer\u00cdas"
    ],
    "sg:website":"www.galeriabenlliure.com",
    "wof:name":"Galeria Benlliure C.b.",
    "wof:placetype":"venue"
},
  "geometry": {"coordinates":[-0.3704451025,39.4677772522],"type":"Point"}
}