{
  "type": "Feature",
  "properties": {
    "iso:country":"ES",
    "sg:address":"Calle de Virgen De Setefilla, 10",
    "sg:city":"Sevilla",
    "sg:orig_category":"Laboratorios Y Cl\u00cdnicas Veterinarias",
    "sg:phone":"+34 954 45 77 47",
    "sg:postcode":"41011",
    "sg:province":"Sevilla",
    "wof:name":"Garcia Vallejo Francisco",
    "wof:placetype":"venue"
},
  "geometry": {"coordinates":[-5.9993071556,37.3781318665],"type":"Point"}
}