{
  "type": "Feature",
  "properties": {
    "addr:full":"Av Francesc Riera, 8 Martorell Barcelona 08760",
    "addr:housenumber":"8",
    "addr:postcode":"08760",
    "addr:street":"Av Francesc Riera",
    "iso:country":"ES",
    "sg:address":"Av Francesc Riera, 8",
    "sg:city":"Martorell",
    "sg:orig_category":"Platos Preparados Refrigerados (fabricaci\u00d3n, Al Por Mayor)",
    "sg:phone":"+34 937 74 15 86",
    "sg:postcode":"08760",
    "sg:province":"Barcelona",
    "wof:name":"Arevalo Matas Maria Del Carmen",
    "wof:placetype":"venue"
},
  "geometry": {"coordinates":[1.9150873423,41.4810676575],"type":"Point"}
}