{
  "type": "Feature",
  "properties": {
    "addr:full":"Calle de Diaz Del Castillo, S/n Huelva Huelva 21007",
    "addr:housenumber":"s / n",
    "addr:postcode":"21007",
    "addr:street":"Calle De Diaz Del Castillo",
    "iso:country":"ES",
    "sg:address":"Calle de Diaz Del Castillo, S/n",
    "sg:city":"Huelva",
    "sg:orig_category":"Pescader\u00cdas (al Por Menor)",
    "sg:phone":"+34 959 15 90 20",
    "sg:postcode":"21007",
    "sg:province":"Huelva",
    "wof:name":"Gomez Carrasco Maria",
    "wof:placetype":"venue"
},
  "geometry": {"coordinates":[-6.9384069443,37.2703018188],"type":"Point"}
}