{
  "type": "Feature",
  "properties": {
    "addr:full":"Calle de Augusto Gonzalez Besada, 9 Tui Pontevedra 36700",
    "addr:housenumber":"9",
    "addr:postcode":"36700",
    "addr:street":"Calle De Augusto Gonzalez Besada",
    "iso:country":"ES",
    "sg:address":"Calle de Augusto Gonzalez Besada, 9",
    "sg:city":"Tui",
    "sg:orig_category":"Droguer\u00cdas (al Por Menor)",
    "sg:phone":"+34 986 60 34 17",
    "sg:postcode":"36700",
    "sg:province":"Pontevedra",
    "wof:name":"Solla Rocha Julian",
    "wof:placetype":"venue"
},
  "geometry": {"coordinates":[-8.6455955505,42.0488014221],"type":"Point"}
}