{
  "type": "Feature",
  "properties": {
    "iso:country":"ES",
    "sg:address":"Carrer de Tallers, 4",
    "sg:city":"Barcelona",
    "sg:orig_category":"Puros, Cigarrillos Y Tabaco (al Por Menor)",
    "sg:phone":"+34 933 17 41 56",
    "sg:postcode":"08001",
    "sg:province":"Barcelona",
    "sg:website":"www.comodejardefumar.com",
    "wof:name":"Es Facil Si Sabes Como S.l.",
    "wof:placetype":"venue"
},
  "geometry": {"coordinates":[2.1701500416,41.3848304749],"type":"Point"}
}