{
  "type": "Feature",
  "properties": {
    "addr:full":"Calle de Camino De Marruecos, 3 Carmona Sevilla 41410",
    "addr:housenumber":"3",
    "addr:postcode":"41410",
    "addr:street":"Calle De Camino De Marruecos",
    "iso:country":"ES",
    "sg:address":"Calle de Camino De Marruecos, 3",
    "sg:city":"Carmona",
    "sg:orig_category":"Empresarios",
    "sg:phone":"+34 954 14 41 13",
    "sg:postcode":"41410",
    "sg:province":"Sevilla",
    "sg:website":"www.paginasamarillas.es",
    "wof:name":"Sanchez Reformas Y Construcciones,s.l.",
    "wof:placetype":"venue"
},
  "geometry": {"coordinates":[-5.6446890831,37.476852417],"type":"Point"}
}