{
  "type": "Feature",
  "properties": {
    "addr:full":"Carrer de Cabanyes (les), 6 Vilafranca Penedes Barcelona 08720",
    "addr:housenumber":"6",
    "addr:postcode":"08720",
    "addr:street":"Carrer De Cabanyes Les;Penedes Barcelona",
    "iso:country":"ES",
    "sg:address":"Carrer de Cabanyes (les), 6",
    "sg:city":"Vilafranca Penedes",
    "sg:orig_category":"Ahumados Y Salazones",
    "sg:phone":"+34 938 92 12 85",
    "sg:postcode":"08720",
    "sg:province":"Barcelona",
    "wof:name":"Salaons Penedes S.l.",
    "wof:placetype":"venue"
},
  "geometry": {"coordinates":[1.7015529871,41.3540649414],"type":"Point"}
}