{
  "type": "Feature",
  "properties": {
    "addr:full":"Avda Vicente Mortes, 6 Valladolid Valladolid 47014",
    "addr:housenumber":"6",
    "addr:postcode":"47014",
    "addr:street":"Avda Vicente Mortes",
    "iso:country":"ES",
    "sg:address":"Avda Vicente Mortes, 6",
    "sg:city":"Valladolid",
    "sg:orig_category":"Sociedades, Compa\u00d1\u00cdas Aseguradoras",
    "sg:phone":"+34 983 35 45 45",
    "sg:postcode":"47014",
    "sg:province":"Valladolid",
    "wof:name":"Aybar De Frutos Eugenio",
    "wof:placetype":"venue"
},
  "geometry": {"coordinates":[-4.7368683815,41.6535186768],"type":"Point"}
}