{
  "type": "Feature",
  "properties": {
    "addr:full":"C/ Brea, 4 Elche Alicante 03206",
    "addr:housenumber":"4",
    "addr:postcode":"03206",
    "addr:street":"C / Brea",
    "iso:country":"ES",
    "sg:address":"C/ Brea, 4",
    "sg:city":"Elche",
    "sg:orig_category":"Zapatos: Material, Suministros, Accesorios (fabricaci\u00d3n, Al Por Mayor)",
    "sg:phone":"+34 965 44 52 52",
    "sg:postcode":"03206",
    "sg:province":"Alicante",
    "wof:name":"Fornituras Clement S.l.",
    "wof:placetype":"venue"
},
  "geometry": {"coordinates":[-0.7167339921,38.2847709656],"type":"Point"}
}