{
  "type": "Feature",
  "properties": {
    "addr:full":"Avda Mejico (de), S/n Jerez De La Frontera C\u00e1diz 11405",
    "addr:postcode":"11405",
    "addr:street":"Avda Mejico De S / N",
    "iso:country":"ES",
    "sg:address":"Avda Mejico (de), S/n",
    "sg:city":"Jerez De La Frontera",
    "sg:orig_category":"Cajas De Ahorro",
    "sg:phone":"+34 956 18 13 79",
    "sg:postcode":"11405",
    "sg:province":"C\u00e1diz",
    "sg:website":"www.cajasur.es",
    "wof:name":"Caja De Ahorros Y Monte De Piedad De Cordoba",
    "wof:placetype":"venue"
},
  "geometry": {"coordinates":[-6.1286787987,36.6930046082],"type":"Point"}
}