{
  "type": "Feature",
  "properties": {
    "addr:full":"Calle de Komentukalea, 21 Durango Vizcaya 48200",
    "addr:housenumber":"21",
    "addr:postcode":"48200",
    "addr:street":"Calle De Komentukalea",
    "iso:country":"ES",
    "sg:address":"Calle de Komentukalea, 21",
    "sg:city":"Durango",
    "sg:classifiers":[
        {
            "category":"Personal",
            "subcategory":"Barber",
            "type":"Services"
        }
    ],
    "sg:phone":"+34 946 81 16 35",
    "sg:postcode":"48200",
    "sg:province":"Vizcaya",
    "sg:tags":[
        "caballeros",
        "de",
        "peluqueros"
    ],
    "wof:name":"Fidel Zarriugarte Aranguena",
    "wof:placetype":"venue"
},
  "geometry": {"coordinates":[-2.6305649281,43.1662521362],"type":"Point"}
}