{
  "type": "Feature",
  "properties": {
    "addr:full":"Cami Sagraments, 17 Poligon Sant Ermengol Barcelona 08630",
    "addr:housenumber":"17",
    "addr:postcode":"08630",
    "addr:street":"Sagraments;Sant",
    "iso:country":"ES",
    "sg:address":"Cami Sagraments, 17",
    "sg:city":"Poligon Sant Ermengol",
    "sg:orig_category":"Carros Elevadores, Carros De Operaciones Portuarias",
    "sg:phone":"+34 937 70 00 00",
    "sg:postcode":"08630",
    "sg:province":"Barcelona",
    "wof:name":"Inversiones Y Alquiler De Maquinaria S.l.",
    "wof:placetype":"venue"
},
  "geometry": {"coordinates":[1.8992400169,41.5194091797],"type":"Point"}
}