{
  "type": "Feature",
  "properties": {
    "iso:country":"ES",
    "sg:address":"Calle de Emiliano Barral, 18",
    "sg:city":"Madrid",
    "sg:orig_category":"Inform\u00c1tica (estudios, Servicios, Asesor\u00cda, Formaci\u00d3n)",
    "sg:phone":"+34 915 19 33 60",
    "sg:postcode":"28043",
    "sg:province":"Madrid",
    "wof:name":"3 B New Age S.a.",
    "wof:placetype":"venue"
},
  "geometry": {"coordinates":[-3.660612,40.450474],"type":"Point"}
}