{
  "type": "Feature",
  "properties": {
    "addr:full":"Pase Maritimo Rey De Espa\u00d1a, 141 Fuengirola M\u00e1laga 29640",
    "addr:housenumber":"141",
    "addr:postcode":"29640",
    "addr:street":"Ma\u0301Laga",
    "iso:country":"ES",
    "sg:address":"Pase Maritimo Rey De Espa\u00d1a, 141",
    "sg:city":"Fuengirola",
    "sg:orig_category":"Abogados",
    "sg:phone":"+34 952 19 64 42",
    "sg:postcode":"29640",
    "sg:province":"M\u00e1laga",
    "wof:name":"Spire Global Services S.l.",
    "wof:placetype":"venue"
},
  "geometry": {"coordinates":[-4.6163477898,36.5493927002],"type":"Point"}
}