{
  "type": "Feature",
  "properties": {
    "addr:full":"Plaz Waldo Ferrer, 19 Almaden Ciudad Real 13400",
    "addr:housenumber":"19",
    "addr:postcode":"almaden;13400",
    "addr:street":"Plaz Waldo Ferrer;Real",
    "iso:country":"ES",
    "sg:address":"Plaz Waldo Ferrer, 19",
    "sg:city":"Almaden",
    "sg:orig_category":"Zapatos (al Por Menor)",
    "sg:phone":"+34 926 71 08 84",
    "sg:postcode":"13400",
    "sg:province":"Ciudad Real",
    "wof:name":"Gallego Preciado Cano Amanda",
    "wof:placetype":"venue"
},
  "geometry": {"coordinates":[-4.8308568001,38.7750816345],"type":"Point"}
}