{
  "type": "Feature",
  "properties": {
    "addr:full":"Av Diagonal, 469 Barcelona Barcelona 08036",
    "addr:housenumber":"469",
    "addr:postcode":"08036",
    "addr:street":"Av Diagonal",
    "iso:country":"ES",
    "sg:address":"Av Diagonal, 469",
    "sg:city":"Barcelona",
    "sg:orig_category":"Centros Empresariales",
    "sg:phone":"+34 933 22 41 21",
    "sg:postcode":"08036",
    "sg:province":"Barcelona",
    "wof:name":"Calsamiglia Blancafort Jorge",
    "wof:placetype":"venue"
},
  "geometry": {"coordinates":[2.1467049122,41.3929862976],"type":"Point"}
}