{
  "type": "Feature",
  "properties": {
    "iso:country":"ES",
    "sg:address":"Calle de Rabitilla, S/n",
    "sg:city":"Torrox",
    "sg:orig_category":"Fabricaci\u00d3n, Alquiler, Venta De Encofrados",
    "sg:phone":"+34 952 53 81 81",
    "sg:postcode":"29770",
    "sg:province":"M\u00e1laga",
    "wof:name":"Encofrados Evaristo Sl",
    "wof:placetype":"venue"
},
  "geometry": {"coordinates":[-3.956264019,36.7443199158],"type":"Point"}
}