{
  "type": "Feature",
  "properties": {
    "iso:country":"ES",
    "sg:address":"Calle de Pasaje Granada, 2",
    "sg:city":"Alfacar",
    "sg:orig_category":"M\u00c9dicos: Estomatolog\u00cda",
    "sg:phone":"+34 958 54 36 97",
    "sg:postcode":"18170",
    "sg:province":"Granada",
    "wof:name":"Ginel Mendoza Leovigildo",
    "wof:placetype":"venue"
},
  "geometry": {"coordinates":[-3.5662209988,37.2373886108],"type":"Point"}
}