{
  "type": "Feature",
  "properties": {
    "addr:full":"Avda Alcalde Miguel Casta\u00d1o, 62 Le\u00f3n Le\u00f3n 24005",
    "addr:housenumber":"62",
    "addr:postcode":"24005",
    "addr:street":"Avda Alcalde Miguel Castan\u0303O;Leo\u0301N",
    "iso:country":"ES",
    "sg:address":"Avda Alcalde Miguel Casta\u00d1o, 62",
    "sg:city":"Le\u00f3n",
    "sg:classifiers":[
        {
            "category":"Personal",
            "subcategory":"Barber",
            "type":"Services"
        }
    ],
    "sg:phone":"+34 987 25 35 90",
    "sg:postcode":"24005",
    "sg:province":"Le\u00f3n",
    "sg:tags":[
        "caballeros",
        "de",
        "peluqueros"
    ],
    "wof:name":"Ojogrog S.l.",
    "wof:placetype":"venue"
},
  "geometry": {"coordinates":[-5.563158989,42.5905189514],"type":"Point"}
}