{
  "type": "Feature",
  "properties": {
    "addr:full":"Ctra Ba\u00d1os De Arteijo, Km. 0002,5 Coru\u00d1a La Coru\u00f1a 15008",
    "addr:postcode":"15008",
    "addr:street":"Ctra Ban\u0303Os De Arteijo Km. 0002,5 Corun\u0303A La Corun\u0303A",
    "iso:country":"ES",
    "sg:address":"Ctra Ba\u00d1os De Arteijo, Km. 0002,5",
    "sg:city":"Coru\u00d1a",
    "sg:orig_category":"Art\u00cdculos De Decoraci\u00d3n",
    "sg:phone":"+34 981 17 05 63",
    "sg:postcode":"15008",
    "sg:province":"La Coru\u00f1a",
    "wof:name":"Fidalgo Garcia Pedro",
    "wof:placetype":"venue"
},
  "geometry": {"coordinates":[-8.4512443542,43.3434753418],"type":"Point"}
}