{
  "type": "Feature",
  "properties": {
    "addr:full":"Calle de Castilla Perez, 6 Nerja M\u00e1laga 29780",
    "addr:housenumber":"6",
    "addr:postcode":"29780",
    "addr:street":"Calle De Castilla Perez",
    "iso:country":"ES",
    "sg:address":"Calle de Castilla Perez, 6",
    "sg:city":"Nerja",
    "sg:orig_category":"Alquiler De Veh\u00cdculos: Turismos Y Utilitarios",
    "sg:phone":"+34 952 52 31 45",
    "sg:postcode":"29780",
    "sg:province":"M\u00e1laga",
    "wof:name":"Autos Balcon Europa S.l.",
    "wof:placetype":"venue"
},
  "geometry": {"coordinates":[-3.8793349266,36.7473258972],"type":"Point"}
}