{
  "type": "Feature",
  "properties": {
    "iso:country":"ES",
    "sg:address":"Carr Floridablanca, 25",
    "sg:city":"Badalona",
    "sg:orig_category":"Reposter\u00cdas",
    "sg:phone":"+34 933 88 14 48",
    "sg:postcode":"08914",
    "sg:province":"Barcelona",
    "wof:name":"Horno La Salud S. L.",
    "wof:placetype":"venue"
},
  "geometry": {"coordinates":[2.2255160809,41.4408988953],"type":"Point"}
}