{
  "type": "Feature",
  "properties": {
    "iso:country":"ES",
    "sg:address":"Calle de Parada, 1",
    "sg:city":"Tarancon",
    "sg:orig_category":"Psic\u00d3logos",
    "sg:phone":"+34 969 32 29 36",
    "sg:postcode":"16400",
    "sg:province":"Cuenca",
    "wof:name":"Jimenez Castroviejo Blanca",
    "wof:placetype":"venue"
},
  "geometry": {"coordinates":[-3.0057609081,40.0115013123],"type":"Point"}
}