{
  "type": "Feature",
  "properties": {
    "iso:country":"ES",
    "sg:address":"Calle de Fuentespina, 21",
    "sg:city":"Madrid",
    "sg:classifiers":[
        {
            "category":"Government",
            "subcategory":"Post Office",
            "type":"Public Place"
        }
    ],
    "sg:phone":"+34 913 32 25 95",
    "sg:postcode":"28031",
    "sg:province":"Madrid",
    "sg:tags":[
        "de",
        "yoga",
        "clases"
    ],
    "wof:name":"Fernandez Fernandez Piedad",
    "wof:placetype":"venue"
},
  "geometry": {"coordinates":[-3.6059250832,40.3795585632],"type":"Point"}
}