{
  "type": "Feature",
  "properties": {
    "addr:full":"Calle de Rodrigo Vivas Miras, 79 Almeria Almer\u00eda 04007",
    "addr:housenumber":"79",
    "addr:postcode":"04007",
    "addr:street":"Calle De Rodrigo Vivas Miras",
    "iso:country":"ES",
    "sg:address":"Calle de Rodrigo Vivas Miras, 79",
    "sg:city":"Almeria",
    "sg:orig_category":"Organizaciones Internacionales",
    "sg:phone":"+34 950 15 19 08",
    "sg:postcode":"04007",
    "sg:province":"Almer\u00eda",
    "wof:name":"Unicodesa Asociacion",
    "wof:placetype":"venue"
},
  "geometry": {"coordinates":[-2.4460148811,36.8260383606],"type":"Point"}
}