{
  "type": "Feature",
  "properties": {
    "iso:country":"ES",
    "sg:address":"Calle de Palafox, 22",
    "sg:city":"Palmas De Gran Canaria",
    "sg:orig_category":"Electrodom\u00c9sticos (fabricaci\u00d3n, Al Por Mayor)",
    "sg:phone":"+34 928 22 03 18",
    "sg:postcode":"35010",
    "sg:province":"Las Palmas",
    "wof:name":"Quinque Regalos S.l.",
    "wof:placetype":"venue"
},
  "geometry": {"coordinates":[-15.4388904572,28.1325836182],"type":"Point"}
}