{
  "type": "Feature",
  "properties": {
    "addr:full":"Cmn Cementerio, S/n Herencia Ciudad Real 13640",
    "addr:housenumber":"s / n",
    "addr:postcode":"13640",
    "iso:country":"ES",
    "sg:address":"Cmn Cementerio, S/n",
    "sg:city":"Herencia",
    "sg:orig_category":"Negocio De Materiales De Construcci\u00d3n",
    "sg:phone":"+34 926 57 12 08",
    "sg:postcode":"13640",
    "sg:province":"Ciudad Real",
    "wof:name":"Ramigo C.b.",
    "wof:placetype":"venue"
},
  "geometry": {"coordinates":[-3.3442978859,39.3645019531],"type":"Point"}
}