{
  "type": "Feature",
  "properties": {
    "iso:country":"ES",
    "sg:address":"Calle de Federico Ozanan, 3",
    "sg:city":"Zaragoza",
    "sg:orig_category":"Guarder\u00cdas",
    "sg:phone":"+34 976 75 38 82",
    "sg:postcode":"50012",
    "sg:province":"Zaragoza",
    "wof:name":"Arzobispado De Zaragoza",
    "wof:placetype":"venue"
},
  "geometry": {"coordinates":[-0.9308487773,41.6396598816],"type":"Point"}
}