{
  "type": "Feature",
  "properties": {
    "iso:country":"ES",
    "sg:address":"Carretera De Baeza, S/n",
    "sg:city":"Ibros",
    "sg:orig_category":"Poli\u00c9ster",
    "sg:phone":"+34 953 76 65 12",
    "sg:postcode":"23450",
    "sg:province":"Ja\u00e9n",
    "wof:name":"Sebastian Leiva Garcia Y Andres Leiva Garcia Cdad",
    "wof:placetype":"venue"
},
  "geometry": {"coordinates":[-3.5054740906,38.020980835],"type":"Point"}
}