{
  "type": "Feature",
  "properties": {
    "addr:full":"Psaj Angel (del), 7 Linea De La Concepcion C\u00e1diz 11300",
    "addr:housenumber":"7",
    "addr:postcode":"11300",
    "addr:street":"Angel Del;Ca\u0301Diz",
    "iso:country":"ES",
    "sg:address":"Psaj Angel (del), 7",
    "sg:city":"Linea De La Concepcion",
    "sg:orig_category":"M\u00c9dicos: Estomatolog\u00cda",
    "sg:phone":"+34 956 17 19 21",
    "sg:postcode":"11300",
    "sg:province":"C\u00e1diz",
    "wof:name":"Ramiro Verdejo Vicente",
    "wof:placetype":"venue"
},
  "geometry": {"coordinates":[-5.340939045,36.1683044434],"type":"Point"}
}