{
  "type": "Feature",
  "properties": {
    "iso:country":"ES",
    "sg:address":"Calle de Ca\u00d1ada, S/n",
    "sg:city":"San Fernando De Henares",
    "sg:orig_category":"Florister\u00cdas",
    "sg:phone":"+34 916 69 59 62",
    "sg:postcode":"28830",
    "sg:province":"Madrid",
    "wof:name":"Sanchez Blanco Maria Del Carmen",
    "wof:placetype":"venue"
},
  "geometry": {"coordinates":[-3.5367758274,40.4248886108],"type":"Point"}
}