{
  "type": "Feature",
  "properties": {
    "addr:full":"Avda Alfonso Xiii, 19 Elda Alicante 03600",
    "addr:housenumber":"19",
    "addr:postcode":"03600",
    "addr:street":"Avda Alfonso Xiii",
    "iso:country":"ES",
    "sg:address":"Avda Alfonso Xiii, 19",
    "sg:city":"Elda",
    "sg:orig_category":"Fabricaci\u00d3n, Importaci\u00d3n De L\u00c1mparas Y Bombillas",
    "sg:phone":"+34 965 39 93 23",
    "sg:postcode":"03600",
    "sg:province":"Alicante",
    "wof:name":"Gil Roldan Victor Jose",
    "wof:placetype":"venue"
},
  "geometry": {"coordinates":[-0.7979670167,38.4728622437],"type":"Point"}
}