{
  "type": "Feature",
  "properties": {
    "addr:full":"Cra Caballos, S/n Alagon Zaragoza 50630",
    "addr:postcode":"50630",
    "addr:street":"S / N Alagon",
    "iso:country":"ES",
    "sg:address":"Cra Caballos, S/n",
    "sg:city":"Alagon",
    "sg:orig_category":"Material Y Herramientas Agr\u00cdcolas",
    "sg:phone":"+34 976 61 03 92",
    "sg:postcode":"50630",
    "sg:province":"Zaragoza",
    "wof:name":"Ruiz Gonzalez Jose Fernando",
    "wof:placetype":"venue"
},
  "geometry": {"coordinates":[-1.1291140318,41.7657661438],"type":"Point"}
}