{
  "type": "Feature",
  "properties": {
    "addr:full":"Carr Valencia, 2 Badalona Barcelona 08915",
    "addr:housenumber":"2",
    "addr:postcode":"08915",
    "addr:street":"Carr Valencia",
    "iso:country":"ES",
    "sg:address":"Carr Valencia, 2",
    "sg:city":"Badalona",
    "sg:orig_category":"Electricidad: Equipos Industriales, Componentes (fabricaci\u00d3n)",
    "sg:phone":"+34 934 65 11 52",
    "sg:postcode":"08915",
    "sg:province":"Barcelona",
    "wof:name":"Electro Materiales Betulo S.l.",
    "wof:placetype":"venue"
},
  "geometry": {"coordinates":[2.2477369308,41.4578018188],"type":"Point"}
}