{
  "type": "Feature",
  "properties": {
    "addr:full":"Calle de Juan De Lanuza, 28 Teruel Teruel 44002",
    "addr:housenumber":"28",
    "addr:postcode":"44002",
    "addr:street":"Calle De Juan De Lanuza",
    "iso:country":"ES",
    "sg:address":"Calle de Juan De Lanuza, 28",
    "sg:city":"Teruel",
    "sg:orig_category":"Contenedores (mercanc\u00cdas)",
    "sg:phone":"+34 978 60 30 98",
    "sg:postcode":"44002",
    "sg:province":"Teruel",
    "wof:name":"Aguilar Pascual Jose",
    "wof:placetype":"venue"
},
  "geometry": {"coordinates":[-1.0900063515,40.329574585],"type":"Point"}
}