{
  "type": "Feature",
  "properties": {
    "addr:full":"Calle de Rio Alhama, 3 Logro\u00f1o La Rioja 26006",
    "addr:housenumber":"3",
    "addr:postcode":"26006",
    "addr:street":"Calle De Rio Alhama;Rioja",
    "iso:country":"ES",
    "sg:address":"Calle de Rio Alhama, 3",
    "sg:city":"Logro\u00f1o",
    "sg:orig_category":"Polideportivos",
    "sg:phone":"+34 941 26 04 94",
    "sg:postcode":"26006",
    "sg:province":"La Rioja",
    "wof:name":"Ayuntamiento De Logro\u00f1o",
    "wof:placetype":"venue"
},
  "geometry": {"coordinates":[-2.4273273945,42.4524993896],"type":"Point"}
}