{
  "type": "Feature",
  "properties": {
    "iso:country":"ES",
    "sg:address":"Camino Del Melon, S/n",
    "sg:city":"Gijon",
    "sg:orig_category":"Calderer\u00cda",
    "sg:phone":"+34 985 31 17 53",
    "sg:postcode":"33211",
    "sg:province":"Asturias",
    "wof:name":"Transformados Del Acero S. A.",
    "wof:placetype":"venue"
},
  "geometry": {"coordinates":[-5.7093238831,43.5308685303],"type":"Point"}
}