{
  "type": "Feature",
  "properties": {
    "iso:country":"ES",
    "sg:address":"Plaz Santa Ana, 2",
    "sg:city":"Avila",
    "sg:orig_category":"Institutos De Belleza",
    "sg:phone":"+34 920 22 71 38",
    "sg:postcode":"05001",
    "sg:province":"\u00c1vila",
    "wof:name":"Afrodita Salon De Belleza C.b.",
    "wof:placetype":"venue"
},
  "geometry": {"coordinates":[-4.6398692131,40.638092041],"type":"Point"}
}