{
  "type": "Feature",
  "properties": {
    "addr:full":"Calle de Arroyo Hondo, 26 Velez-malaga M\u00e1laga 29700",
    "addr:housenumber":"26",
    "addr:postcode":"29700",
    "addr:street":"Calle De Arroyo Hondo",
    "iso:country":"ES",
    "sg:address":"Calle de Arroyo Hondo, 26",
    "sg:city":"Velez-malaga",
    "sg:orig_category":"Institutos De Belleza",
    "sg:phone":"+34 952 54 90 32",
    "sg:postcode":"29700",
    "sg:province":"M\u00e1laga",
    "wof:name":"Fernandez Romero Maria Del Mar",
    "wof:placetype":"venue"
},
  "geometry": {"coordinates":[-4.1042160988,36.7791290283],"type":"Point"}
}