{
  "type": "Feature",
  "properties": {
    "addr:full":"Calle de Flor De Retama, 4 Sevilla Sevilla 41020",
    "addr:housenumber":"4",
    "addr:postcode":"41020",
    "addr:street":"Calle De Flor De Retama",
    "iso:country":"ES",
    "sg:address":"Calle de Flor De Retama, 4",
    "sg:city":"Sevilla",
    "sg:orig_category":"Equipo Y Material Deportivo Y De Actividades Invernales Y De Monta\u00d1a",
    "sg:phone":"+34 954 44 45 80",
    "sg:postcode":"41020",
    "sg:province":"Sevilla",
    "wof:name":"Junta Rectora Centro Deportivo Entreflores",
    "wof:placetype":"venue"
},
  "geometry": {"coordinates":[-5.9182868004,37.3971595764],"type":"Point"}
}