{
  "type": "Feature",
  "properties": {
    "iso:country":"ES",
    "sg:address":"Avda Camelias, 122",
    "sg:city":"Vigo",
    "sg:orig_category":"Bisuter\u00cda, Joyer\u00cda, Relojer\u00cda (al Por Menor)",
    "sg:phone":"+34 986 29 85 05",
    "sg:postcode":"36211",
    "sg:province":"Pontevedra",
    "wof:name":"Soto Pregal Manuel",
    "wof:placetype":"venue"
},
  "geometry": {"coordinates":[-8.7305421829,42.2232437134],"type":"Point"}
}