{
  "type": "Feature",
  "properties": {
    "addr:full":"Rua Republica Argentina, 4 Vigo Pontevedra 36201",
    "addr:housenumber":"4",
    "addr:postcode":"36201",
    "addr:street":"Rua Republica Argentina",
    "iso:country":"ES",
    "sg:address":"Rua Republica Argentina, 4",
    "sg:city":"Vigo",
    "sg:orig_category":"Abogados",
    "sg:phone":"+34 986 43 05 11",
    "sg:postcode":"36201",
    "sg:province":"Pontevedra",
    "wof:name":"Gonzalez Moci\u00f1os Emilia",
    "wof:placetype":"venue"
},
  "geometry": {"coordinates":[-8.7179174423,42.2388801575],"type":"Point"}
}