{
  "type": "Feature",
  "properties": {
    "iso:country":"ES",
    "sg:address":"Carr Garrotxa, S/n",
    "sg:city":"Cassa Selva",
    "sg:orig_category":"Maquinaria Para Industrias Diversas",
    "sg:phone":"+34 972 46 17 31",
    "sg:postcode":"17244",
    "sg:province":"Girona",
    "sg:website":"www.vvr.es",
    "wof:name":"Construccions Mecanicas Vidal S.l.",
    "wof:placetype":"venue"
},
  "geometry": {"coordinates":[2.8780760765,41.8896598816],"type":"Point"}
}