{
  "type": "Feature",
  "properties": {
    "addr:full":"Avda Juan Vi\u00d1egla, S/n Mula Murcia 30170",
    "addr:housenumber":"s / n",
    "addr:postcode":"30170",
    "addr:street":"Avda Juan Vin\u0303Egla",
    "iso:country":"ES",
    "sg:address":"Avda Juan Vi\u00d1egla, S/n",
    "sg:city":"Mula",
    "sg:orig_category":"Farmacias",
    "sg:phone":"+34 968 66 19 11",
    "sg:postcode":"30170",
    "sg:province":"Murcia",
    "wof:name":"Esperanza Mu\u00f1oz Mu\u00f1oz Y Mercedes Torres Perez C.b.",
    "wof:placetype":"venue"
},
  "geometry": {"coordinates":[-1.4929139614,38.0377044678],"type":"Point"}
}