{
  "type": "Feature",
  "properties": {
    "iso:country":"ES",
    "sg:address":"Calle de Rodriguez Paterna, S/n",
    "sg:city":"Logro\u00f1o",
    "sg:orig_category":"Asociaciones, Organismos Culturales Y Socioeducativos",
    "sg:phone":"+34 941 25 03 65",
    "sg:postcode":"26001",
    "sg:province":"La Rioja",
    "wof:name":"Scouts De La Rioja. Asde",
    "wof:placetype":"venue"
},
  "geometry": {"coordinates":[-2.4424490929,42.4679946899],"type":"Point"}
}