{
  "type": "Feature",
  "properties": {
    "iso:country":"ES",
    "sg:address":"Calle de San Roque (de), 76",
    "sg:city":"Navalcarnero",
    "sg:orig_category":"Frutas, Legumbres Frescas Y Tempranas (al Por Menor)",
    "sg:phone":"+34 918 11 22 59",
    "sg:postcode":"28600",
    "sg:province":"Madrid",
    "wof:name":"Herruzo Barbancho Salvador",
    "wof:placetype":"venue"
},
  "geometry": {"coordinates":[-4.0122542381,40.2846183777],"type":"Point"}
}