{
  "type": "Feature",
  "properties": {
    "iso:country":"ES",
    "sg:address":"Etxe-alai Auzunea, 5",
    "sg:city":"Azpeitia",
    "sg:orig_category":"Automatizaci\u00d3n De Procesos Industriales Y De Edificaci\u00d3n (estudios, Instalaci\u00d3n)",
    "sg:phone":"+34 943 15 00 77",
    "sg:postcode":"20730",
    "sg:province":"Guip\u00f9zcoa",
    "wof:name":"Tecnosoft C.b.",
    "wof:placetype":"venue"
},
  "geometry": {"coordinates":[-2.2638750076,43.1857795715],"type":"Point"}
}