{
  "type": "Feature",
  "properties": {
    "addr:full":"Calle de Sierpes, 73 Sevilla Sevilla 41004",
    "addr:housenumber":"73",
    "addr:postcode":"41004",
    "addr:street":"Calle De Sierpes",
    "iso:country":"ES",
    "sg:address":"Calle de Sierpes, 73",
    "sg:city":"Sevilla",
    "sg:orig_category":"Fabricaci\u00d3n De Sobres, Bolsas Y Fundas",
    "sg:phone":"+34 954 22 60 55",
    "sg:postcode":"41004",
    "sg:province":"Sevilla",
    "wof:name":"Bolsos Casal S. A.",
    "wof:placetype":"venue"
},
  "geometry": {"coordinates":[-5.9942598343,37.3901863098],"type":"Point"}
}