{
  "type": "Feature",
  "properties": {
    "iso:country":"ES",
    "sg:address":"Avda Martinez De Velasco, 28",
    "sg:city":"Huesca",
    "sg:orig_category":"Frutas, Legumbres Frescas Y Tempranas (al Por Menor)",
    "sg:phone":"+34 974 21 40 25",
    "sg:postcode":"22004",
    "sg:province":"Huesca",
    "wof:name":"Vaquero Perez Marcelo",
    "wof:placetype":"venue"
},
  "geometry": {"coordinates":[-0.4158979952,42.1333351135],"type":"Point"}
}