{
  "type": "Feature",
  "properties": {
    "iso:country":"ES",
    "sg:address":"Calle de Arevalo, 22",
    "sg:city":"Madrigal Altas Torres",
    "sg:orig_category":"Molduras, Junquillos, Listones Y Molduras Perforadas",
    "sg:phone":"+34 920 32 07 18",
    "sg:postcode":"05220",
    "sg:province":"\u00c1vila",
    "wof:name":"Cimpoeru  Nicoleta",
    "wof:placetype":"venue"
},
  "geometry": {"coordinates":[-4.9959573746,41.089176178],"type":"Point"}
}