{
  "type": "Feature",
  "properties": {
    "iso:country":"ES",
    "sg:address":"Calle de Colmenarico, 16",
    "sg:city":"San Mateo",
    "sg:orig_category":"Asesor\u00cda Fiscal Y Jur\u00cddica",
    "sg:phone":"+34 968 47 76 25",
    "sg:postcode":"30800",
    "sg:province":"Murcia",
    "wof:name":"Asesoria Tafalla S.l.",
    "wof:placetype":"venue"
},
  "geometry": {"coordinates":[-1.1298867464,37.9834747314],"type":"Point"}
}