{
  "type": "Feature",
  "properties": {
    "addr:full":"Calle de Antonio Pesini, 3 Badajoz Badajoz 06011",
    "addr:housenumber":"3",
    "addr:postcode":"06011",
    "addr:street":"Calle De Antonio Pesini",
    "iso:country":"ES",
    "sg:address":"Calle de Antonio Pesini, 3",
    "sg:city":"Badajoz",
    "sg:orig_category":"Tapicer\u00cdas",
    "sg:phone":"+34 924 24 38 57",
    "sg:postcode":"06011",
    "sg:province":"Badajoz",
    "wof:name":"Matito Quintana Camilo",
    "wof:placetype":"venue"
},
  "geometry": {"coordinates":[-6.983771801,38.8664054871],"type":"Point"}
}