{
  "type": "Feature",
  "properties": {
    "iso:country":"ES",
    "sg:address":"Calle de Rayo, 12",
    "sg:city":"Getafe",
    "sg:orig_category":"Asistencia Y Consejos",
    "sg:phone":"+34 916 96 69 44",
    "sg:postcode":"28904",
    "sg:province":"Madrid",
    "wof:name":"Academia Santa Maria S.l.",
    "wof:placetype":"venue"
},
  "geometry": {"coordinates":[-3.7356188297,40.3073234558],"type":"Point"}
}