{
  "type": "Feature",
  "properties": {
    "iso:country":"ES",
    "sg:address":"Plaz Poley, 4",
    "sg:city":"Estepa",
    "sg:orig_category":"Bisuteros (fabricaci\u00d3n, Al Por Mayor)",
    "sg:phone":"+34 955 91 39 03",
    "sg:postcode":"41560",
    "sg:province":"Sevilla",
    "wof:name":"Astapa De Metales S.l.",
    "wof:placetype":"venue"
},
  "geometry": {"coordinates":[-4.872751236,37.2912483215],"type":"Point"}
}