{
  "type": "Feature",
  "properties": {
    "iso:country":"ES",
    "sg:address":"Calle de Ginzo De Limia, 55",
    "sg:city":"Madrid",
    "sg:orig_category":"Inform\u00c1tica (estudios, Servicios, Asesor\u00cda, Formaci\u00d3n)",
    "sg:phone":"+34 917 39 00 93",
    "sg:postcode":"28034",
    "sg:province":"Madrid",
    "wof:name":"Zeronine Aci S.l.",
    "wof:placetype":"venue"
},
  "geometry": {"coordinates":[-3.7085278034,40.4848136902],"type":"Point"}
}