{
  "type": "Feature",
  "properties": {
    "iso:country":"ES",
    "sg:address":"Calle de Italia, 113",
    "sg:city":"Toledo",
    "sg:orig_category":"Ense\u00d1anza, Formaci\u00d3n Profesional: Aprendizaje",
    "sg:phone":"+34 925 28 55 34",
    "sg:postcode":"45005",
    "sg:province":"Toledo",
    "wof:name":"Consejo Camaras Oficiales De Comercio E Industria De Castilla La Mancha",
    "wof:placetype":"venue"
},
  "geometry": {"coordinates":[-4.0363349915,39.8811836243],"type":"Point"}
}