{
  "type": "Feature",
  "properties": {
    "iso:country":"ES",
    "sg:address":"Rbla Egara, 307",
    "sg:city":"Terrassa",
    "sg:orig_category":"Abogados",
    "sg:phone":"+34 937 80 67 11",
    "sg:postcode":"08224",
    "sg:province":"Barcelona",
    "wof:name":"Garcia-cascon Morera Luis",
    "wof:placetype":"venue"
},
  "geometry": {"coordinates":[2.0058560371,41.5667800903],"type":"Point"}
}