{
  "type": "Feature",
  "properties": {
    "iso:country":"ES",
    "sg:address":"Calle de Doctor Fleming, 6",
    "sg:city":"Villena",
    "sg:orig_category":"Electricidad: Instaladores",
    "sg:phone":"+34 965 80 04 79",
    "sg:postcode":"03400",
    "sg:province":"Alicante",
    "wof:name":"Instalaciones Y Montajes Electricos Borras S.l.",
    "wof:placetype":"venue"
},
  "geometry": {"coordinates":[-0.8693044186,38.6444396973],"type":"Point"}
}