{
  "type": "Feature",
  "properties": {
    "iso:country":"ES",
    "sg:address":"Calle de Escuelas (las), 4",
    "sg:city":"Entrena",
    "sg:orig_category":"Electricidad: Instaladores",
    "sg:phone":"+34 941 44 62 68",
    "sg:postcode":"26375",
    "sg:province":"La Rioja",
    "wof:name":"Fernandez Blanco Jose Luis",
    "wof:placetype":"venue"
},
  "geometry": {"coordinates":[-2.5281770229,42.3872489929],"type":"Point"}
}