{
  "type": "Feature",
  "properties": {
    "iso:country":"ES",
    "sg:address":"Carr Bernat Coll, 11",
    "sg:city":"Llubi",
    "sg:orig_category":"Centros Empresariales",
    "sg:phone":"+34 971 52 22 55",
    "sg:postcode":"07430",
    "sg:province":"Islas Baleares",
    "wof:name":"Martin Y Agustin Mascaro Sl",
    "wof:placetype":"venue"
},
  "geometry": {"coordinates":[3.0067300797,39.7010688782],"type":"Point"}
}