{
  "type": "Feature",
  "properties": {
    "addr:full":"Calle de Medina, 14 Jerez De La Frontera C\u00e1diz 11406",
    "addr:housenumber":"14",
    "addr:postcode":"11406",
    "addr:street":"Calle De Medina",
    "iso:country":"ES",
    "sg:address":"Calle de Medina, 14",
    "sg:city":"Jerez De La Frontera",
    "sg:orig_category":"Confecci\u00d3n De Trajes Para Se\u00d1oras",
    "sg:phone":"+34 956 34 63 56",
    "sg:postcode":"11406",
    "sg:province":"C\u00e1diz",
    "wof:name":"Ulzurrun De Asanza Postigo Amelia",
    "wof:placetype":"venue"
},
  "geometry": {"coordinates":[-6.1338858604,36.6825523376],"type":"Point"}
}