{
  "type": "Feature",
  "properties": {
    "iso:country":"ES",
    "sg:address":"Calle de Melilla, 33",
    "sg:city":"Alcala Henares",
    "sg:orig_category":"Venta, Colocaci\u00d3n, Reparaci\u00d3n De Radiadores Para Veh\u00cdculos",
    "sg:phone":"+34 918 89 13 95",
    "sg:postcode":"28805",
    "sg:province":"Madrid",
    "wof:name":"Abad Benito Pedro",
    "wof:placetype":"venue"
},
  "geometry": {"coordinates":[-3.34178,40.494576],"type":"Point"}
}