{
  "type": "Feature",
  "properties": {
    "addr:full":"Calle de Ribera De Curtidores, 45 Madrid Madrid 28005",
    "addr:housenumber":"45",
    "addr:postcode":"madrid;28005",
    "addr:street":"Calle De Ribera De Curtidores",
    "iso:country":"ES",
    "sg:address":"Calle de Ribera De Curtidores, 45",
    "sg:city":"Madrid",
    "sg:orig_category":"Papeler\u00cdas: Art\u00cdculos (al Por Mayor)",
    "sg:phone":"+34 915 30 98 22",
    "sg:postcode":"28005",
    "sg:province":"Madrid",
    "sg:website":"www.carlin.es",
    "wof:name":"Manuel De Pinto Lopez S.l.",
    "wof:placetype":"venue"
},
  "geometry": {"coordinates":[-3.7066340446,40.4044570923],"type":"Point"}
}