{
  "type": "Feature",
  "properties": {
    "iso:country":"ES",
    "sg:address":"Carr Corsega, 21",
    "sg:city":"Badalona",
    "sg:orig_category":"Ebanister\u00cda",
    "sg:phone":"+34 933 83 71 44",
    "sg:postcode":"08917",
    "sg:province":"Barcelona",
    "wof:name":"Martinez Lopez Lorenzo",
    "wof:placetype":"venue"
},
  "geometry": {"coordinates":[2.2233560085,41.4540672302],"type":"Point"}
}