{
  "type": "Feature",
  "properties": {
    "addr:full":"Calle de Ignacio Santos Vi\u00d1uelas, 14 Madrid Madrid 28021",
    "addr:housenumber":"14",
    "addr:postcode":"madrid;28021",
    "addr:street":"Calle De Ignacio Santos Vin\u0303Uelas",
    "iso:country":"ES",
    "sg:address":"Calle de Ignacio Santos Vi\u00d1uelas, 14",
    "sg:city":"Madrid",
    "sg:orig_category":"Librer\u00cdas",
    "sg:phone":"+34 917 95 10 22",
    "sg:postcode":"28021",
    "sg:province":"Madrid",
    "wof:name":"Redondo Barroso Maria Isabel",
    "wof:placetype":"venue"
},
  "geometry": {"coordinates":[-3.6894769669,40.3493995667],"type":"Point"}
}