{
  "type": "Feature",
  "properties": {
    "iso:country":"ES",
    "sg:address":"Carrer de Valencia, 14",
    "sg:city":"Campello",
    "sg:orig_category":"Cl\u00cdnicas Dentales",
    "sg:phone":"+34 965 63 49 81",
    "sg:postcode":"03560",
    "sg:province":"Alicante",
    "wof:name":"Clinica Dental El Campello S.l.",
    "wof:placetype":"venue"
},
  "geometry": {"coordinates":[-0.3974080086,38.4282722473],"type":"Point"}
}