{
  "type": "Feature",
  "properties": {
    "addr:full":"Calle de Encina, De La, 8 Melilla Melilla 52001",
    "addr:housenumber":"8",
    "addr:postcode":"52001",
    "addr:street":"Calle De Encina De La",
    "iso:country":"ES",
    "sg:address":"Calle de Encina, De La, 8",
    "sg:city":"Melilla",
    "sg:orig_category":"Radiocomunicaciones, Telefon\u00cda M\u00d3vil, Radiomensajer\u00cda: Servicios, Comercializaci\u00d3n",
    "sg:phone":"+34 952 68 25 19",
    "sg:postcode":"52001",
    "sg:province":"Melilla",
    "wof:name":"Mohamed Chaib Yamina",
    "wof:placetype":"venue"
},
  "geometry": {"coordinates":[-2.9512500763,35.3091583252],"type":"Point"}
}