{
  "type": "Feature",
  "properties": {
    "iso:country":"ES",
    "sg:address":"Avda Reina Mercedes, 5",
    "sg:city":"Sevilla",
    "sg:orig_category":"Psic\u00d3logos",
    "sg:phone":"+34 954 62 14 67",
    "sg:postcode":"41012",
    "sg:province":"Sevilla",
    "wof:name":"Martin Vega Maria Del Carmen",
    "wof:placetype":"venue"
},
  "geometry": {"coordinates":[-5.9858870506,37.3630599976],"type":"Point"}
}