{
  "type": "Feature",
  "properties": {
    "iso:country":"ES",
    "sg:address":"Carr Progres, 256",
    "sg:city":"Badalona",
    "sg:orig_category":"Electricidad: Instaladores",
    "sg:phone":"+34 933 83 12 34",
    "sg:postcode":"08918",
    "sg:province":"Barcelona",
    "wof:name":"Brain New Tecnology S.l.",
    "wof:placetype":"venue"
},
  "geometry": {"coordinates":[2.2353088856,41.4366645813],"type":"Point"}
}