{
  "type": "Feature",
  "properties": {
    "addr:full":"Calle de Prado, Del, 11 Talavera Reina Toledo 45600",
    "addr:housenumber":"11",
    "addr:postcode":"45600",
    "addr:street":"Calle De Prado Del",
    "iso:country":"ES",
    "sg:address":"Calle de Prado, Del, 11",
    "sg:city":"Talavera Reina",
    "sg:orig_category":"Arquitectos",
    "sg:phone":"+34 925 80 47 14",
    "sg:postcode":"45600",
    "sg:province":"Toledo",
    "wof:name":"Fernandez Sahagun Fernando",
    "wof:placetype":"venue"
},
  "geometry": {"coordinates":[-4.8326292038,39.9584884644],"type":"Point"}
}