{
  "type": "Feature",
  "properties": {
    "addr:full":"Urb Bancales, 61 El Viso Alcor Sevilla 41520",
    "addr:housenumber":"61",
    "addr:postcode":"41520",
    "addr:street":"Urb Bancales",
    "iso:country":"ES",
    "sg:address":"Urb Bancales, 61",
    "sg:city":"El Viso Alcor",
    "sg:orig_category":"Farmacias (repartici\u00d3n Y Al Por Mayor)",
    "sg:phone":"+34 955 74 39 96",
    "sg:postcode":"41520",
    "sg:province":"Sevilla",
    "wof:name":"Martin Vilches Juan Antonio",
    "wof:placetype":"venue"
},
  "geometry": {"coordinates":[-5.7224740982,37.3872108459],"type":"Point"}
}