{
  "type": "Feature",
  "properties": {
    "iso:country":"ES",
    "sg:address":"Carrer de Bartomeu Torres, 32",
    "sg:city":"Palma",
    "sg:orig_category":"Dise\u00d1o Industrial",
    "sg:phone":"+34 971 24 02 50",
    "sg:postcode":"07005",
    "sg:province":"Islas Baleares",
    "wof:name":"Guillem De Garcia Yalipza",
    "wof:placetype":"venue"
},
  "geometry": {"coordinates":[2.6655418873,39.5763778687],"type":"Point"}
}