{
  "type": "Feature",
  "properties": {
    "iso:country":"ES",
    "sg:address":"C/ Corro, D'en, 5",
    "sg:city":"Inca",
    "sg:orig_category":"Ropa Para Beb\u00c9s Y Ni\u00d1os (confecci\u00d3n, Al Por Mayor)",
    "sg:phone":"+34 971 88 03 92",
    "sg:postcode":"07300",
    "sg:province":"Islas Baleares",
    "wof:name":"Viarsegui S.l.u",
    "wof:placetype":"venue"
},
  "geometry": {"coordinates":[2.9094560146,39.7204780579],"type":"Point"}
}