{
  "type": "Feature",
  "properties": {
    "addr:full":"Avda Orbigo (el), 105 Benavides De Orbigo Le\u00f3n 24280",
    "addr:housenumber":"105",
    "addr:postcode":"24280",
    "addr:street":"Avda Orbigo El;Leo\u0301N",
    "iso:country":"ES",
    "sg:address":"Avda Orbigo (el), 105",
    "sg:city":"Benavides De Orbigo",
    "sg:orig_category":"Montaje (empresas De)",
    "sg:phone":"+34 987 37 04 07",
    "sg:postcode":"24280",
    "sg:province":"Le\u00f3n",
    "sg:website":"www.protecciones-horizontales.com",
    "wof:name":"Protecciones Horizontales Sl",
    "wof:placetype":"venue"
},
  "geometry": {"coordinates":[-5.8957290649,42.5013809204],"type":"Point"}
}