{
  "type": "Feature",
  "properties": {
    "addr:full":"Calle de Belchite, 15 Logro\u00f1o La Rioja 26003",
    "addr:housenumber":"15",
    "addr:postcode":"26003",
    "addr:street":"Calle De Belchite;Rioja",
    "iso:country":"ES",
    "sg:address":"Calle de Belchite, 15",
    "sg:city":"Logro\u00f1o",
    "sg:orig_category":"Peluqueros: De Se\u00d1oras",
    "sg:phone":"+34 941 23 19 99",
    "sg:postcode":"26003",
    "sg:province":"La Rioja",
    "wof:name":"Aizpurua Aristegui Ana Maria",
    "wof:placetype":"venue"
},
  "geometry": {"coordinates":[-2.4436526299,42.4608421326],"type":"Point"}
}