{
  "type": "Feature",
  "properties": {
    "iso:country":"ES",
    "sg:address":"Rond Outeiro, S/n",
    "sg:city":"Coru\u00d1a",
    "sg:orig_category":"Tintes (fabricaci\u00d3n, Al Por Mayor)",
    "sg:phone":"+34 981 12 80 40",
    "sg:postcode":"15011",
    "sg:province":"La Coru\u00f1a",
    "wof:name":"Alvarellos Garcia Avelino",
    "wof:placetype":"venue"
},
  "geometry": {"coordinates":[-8.4485845566,43.3661346436],"type":"Point"}
}