{
  "type": "Feature",
  "properties": {
    "addr:full":"Calle de General Casta\u00d1os, 83 Portugalete Vizcaya 48920",
    "addr:housenumber":"83",
    "addr:postcode":"48920",
    "addr:street":"Calle De General Castan\u0303Os",
    "iso:country":"ES",
    "sg:address":"Calle de General Casta\u00d1os, 83",
    "sg:city":"Portugalete",
    "sg:orig_category":"Pescader\u00cdas (al Por Menor)",
    "sg:phone":"+34 944 83 06 36",
    "sg:postcode":"48920",
    "sg:province":"Vizcaya",
    "wof:name":"Gayol Gomez Purificacion",
    "wof:placetype":"venue"
},
  "geometry": {"coordinates":[-3.0266299248,43.3233261108],"type":"Point"}
}