{
  "type": "Feature",
  "properties": {
    "iso:country":"ES",
    "sg:address":"Calle de Velazquez, 33",
    "sg:city":"Corrales",
    "sg:orig_category":"Servicios Gsm",
    "sg:phone":"+34 955 91 70 52",
    "sg:postcode":"41657",
    "sg:province":"Sevilla",
    "wof:name":"Reitelefonia S.l.",
    "wof:placetype":"venue"
},
  "geometry": {"coordinates":[-4.9793190956,37.1015701294],"type":"Point"}
}