{
  "type": "Feature",
  "properties": {
    "addr:full":"Calle de Recondo, 27 Valladolid Valladolid 47007",
    "addr:housenumber":"27",
    "addr:postcode":"47007",
    "addr:street":"Calle De Recondo",
    "iso:country":"ES",
    "sg:address":"Calle de Recondo, 27",
    "sg:city":"Valladolid",
    "sg:orig_category":"Psic\u00d3logos",
    "sg:phone":"+34 983 39 75 88",
    "sg:postcode":"47007",
    "sg:province":"Valladolid",
    "wof:name":"Ase-psike S.l.",
    "wof:placetype":"venue"
},
  "geometry": {"coordinates":[-4.7308535576,41.6412391663],"type":"Point"}
}