{
  "type": "Feature",
  "properties": {
    "iso:country":"ES",
    "sg:address":"Carrer de Ruben Dario, 12",
    "sg:city":"Barcelona",
    "sg:orig_category":"Muebles, Minoristas",
    "sg:phone":"+34 933 11 53 06",
    "sg:postcode":"08030",
    "sg:province":"Barcelona",
    "wof:name":"Franco Ayala Francisco",
    "wof:placetype":"venue"
},
  "geometry": {"coordinates":[2.1890850067,41.4341964722],"type":"Point"}
}