{
  "type": "Feature",
  "properties": {
    "iso:country":"ES",
    "sg:address":"Ctra Arrecife A Tinajo, 36",
    "sg:city":"S. Bartolome",
    "sg:orig_category":"Alquiler De V\u00cddeo",
    "sg:phone":"+34 928 52 26 12",
    "sg:postcode":"35550",
    "sg:province":"Las Palmas",
    "wof:name":"Duved Lanzarote S.l.",
    "wof:placetype":"venue"
},
  "geometry": {"coordinates":[-13.6098937988,29.0045204163],"type":"Point"}
}