{
  "type": "Feature",
  "properties": {
    "iso:country":"ES",
    "sg:address":"Calle de Beas, S/n",
    "sg:city":"Trigueros",
    "sg:orig_category":"Carnicer\u00cdas, Carnicer\u00cdas",
    "sg:phone":"+34 959 30 52 01",
    "sg:postcode":"21620",
    "sg:province":"Huelva",
    "wof:name":"Gil Hidalgo Jose",
    "wof:placetype":"venue"
},
  "geometry": {"coordinates":[-6.8314843178,37.3871841431],"type":"Point"}
}