{
  "type": "Feature",
  "properties": {
    "addr:full":"Carr Pau Casals, 32 Vidreres Girona 17411",
    "addr:housenumber":"32",
    "addr:postcode":"17411",
    "addr:street":"Carr Pau Casals",
    "iso:country":"ES",
    "sg:address":"Carr Pau Casals, 32",
    "sg:city":"Vidreres",
    "sg:orig_category":"Inmobiliaria (agencias)",
    "sg:phone":"+34 972 85 17 99",
    "sg:postcode":"17411",
    "sg:province":"Girona",
    "wof:name":"Terra Viva S.c.",
    "wof:placetype":"venue"
},
  "geometry": {"coordinates":[2.7799589634,41.7901496887],"type":"Point"}
}