{
  "type": "Feature",
  "properties": {
    "iso:country":"ES",
    "sg:address":"Calle de Secretario Padilla, 58",
    "sg:city":"Palmas De Gran Canaria",
    "sg:orig_category":"Mercer\u00cda, Lencer\u00cda (al Por Menor)",
    "sg:phone":"+34 928 22 78 30",
    "sg:postcode":"35010",
    "sg:province":"Las Palmas",
    "wof:name":"Rivero Benitez Maria Belen",
    "wof:placetype":"venue"
},
  "geometry": {"coordinates":[-15.4410648346,28.1328983307],"type":"Point"}
}