{
  "type": "Feature",
  "properties": {
    "iso:country":"ES",
    "sg:address":"Afores, S/n",
    "sg:city":"Cubells",
    "sg:orig_category":"Asilos De Ancianos. Centros Privados",
    "sg:phone":"+34 973 45 91 96",
    "sg:postcode":"25737",
    "sg:province":"Lleida",
    "wof:name":"Rescu S.l.",
    "wof:placetype":"venue"
},
  "geometry": {"coordinates":[1.0145050287,41.8782043457],"type":"Point"}
}