{
  "type": "Feature",
  "properties": {
    "addr:full":"Mitxelena Kalea, 20 Zarautz Guip\u00f9zcoa 20800",
    "addr:housenumber":"20",
    "addr:postcode":"20800",
    "addr:street":"Mitxelena Kalea;Guipu\u0300Zcoa",
    "iso:country":"ES",
    "sg:address":"Mitxelena Kalea, 20",
    "sg:city":"Zarautz",
    "sg:orig_category":"Madera Para Construcci\u00d3n E Industria",
    "sg:phone":"+34 943 83 48 19",
    "sg:postcode":"20800",
    "sg:province":"Guip\u00f9zcoa",
    "wof:name":"Carpinteria Larra\u00f1aga S.l.",
    "wof:placetype":"venue"
},
  "geometry": {"coordinates":[-2.1642000675,43.2830123901],"type":"Point"}
}