{
  "type": "Feature",
  "properties": {
    "addr:full":"Calle de San Pedro De Alcantara, 38 Arroyo Luz C\u00e1ceres 10900",
    "addr:housenumber":"38",
    "addr:postcode":"10900",
    "addr:street":"Calle De;Alcantara;Arroyo Luz Ca\u0301Ceres",
    "iso:country":"ES",
    "sg:address":"Calle de San Pedro De Alcantara, 38",
    "sg:city":"Arroyo Luz",
    "sg:orig_category":"Plomeros",
    "sg:phone":"+34 927 27 14 93",
    "sg:postcode":"10900",
    "sg:province":"C\u00e1ceres",
    "wof:name":"Gonzalez Solano Julio",
    "wof:placetype":"venue"
},
  "geometry": {"coordinates":[-6.5836791992,39.4796714783],"type":"Point"}
}