{
  "type": "Feature",
  "properties": {
    "iso:country":"ES",
    "sg:address":"Cerro La Joven, S/n",
    "sg:city":"Gaucin",
    "sg:orig_category":"Tintorer\u00cdas, Limpieza En Seco",
    "sg:phone":"+34 952 15 14 96",
    "sg:postcode":"29480",
    "sg:province":"M\u00e1laga",
    "wof:name":"Lavanderia La Joven S.coop",
    "wof:placetype":"venue"
},
  "geometry": {"coordinates":[-5.3236608505,36.5202293396],"type":"Point"}
}