{
  "type": "Feature",
  "properties": {
    "addr:full":"Calle de Bierzo (del), 38 Fuenlabrada Madrid 28947",
    "addr:housenumber":"38",
    "addr:postcode":"28947",
    "addr:street":"Calle De Bierzo Del",
    "iso:country":"ES",
    "sg:address":"Calle de Bierzo (del), 38",
    "sg:city":"Fuenlabrada",
    "sg:orig_category":"Importaci\u00d3n",
    "sg:phone":"+34 916 42 01 78",
    "sg:postcode":"28947",
    "sg:province":"Madrid",
    "wof:name":"Bosky Saga Internacional S.l.",
    "wof:placetype":"venue"
},
  "geometry": {"coordinates":[-3.7478373051,40.2632484436],"type":"Point"}
}