{
  "type": "Feature",
  "properties": {
    "addr:full":"Ctra Ba\u00f1eres, S/n Biar Alicante 03410",
    "addr:housenumber":"s / n",
    "addr:postcode":"03410",
    "addr:street":"Ctra Ban\u0303Eres",
    "iso:country":"ES",
    "sg:address":"Ctra Ba\u00f1eres, S/n",
    "sg:city":"Biar",
    "sg:orig_category":"Fabricaci\u00d3n De Moldes Y Modelos",
    "sg:phone":"+34 965 81 01 53",
    "sg:postcode":"03410",
    "sg:province":"Alicante",
    "wof:name":"Plasticos Valdes E Hijos S.l.",
    "wof:placetype":"venue"
},
  "geometry": {"coordinates":[-0.768155992,38.6331977844],"type":"Point"}
}