{
  "type": "Feature",
  "properties": {
    "addr:full":"Calle de Leopoldo Alas Clarin, 2 Zamora Zamora 49016",
    "addr:housenumber":"2",
    "addr:postcode":"49016",
    "addr:street":"Calle De Leopoldo Alas Clarin",
    "iso:country":"ES",
    "sg:address":"Calle de Leopoldo Alas Clarin, 2",
    "sg:city":"Zamora",
    "sg:orig_category":"Administradores De Bienes Y Delegados De Comunidades De Propietarios",
    "sg:phone":"+34 980 67 01 95",
    "sg:postcode":"49016",
    "sg:province":"Zamora",
    "wof:name":"Adinco C.b.",
    "wof:placetype":"venue"
},
  "geometry": {"coordinates":[-5.7395076752,41.5071029663],"type":"Point"}
}