{
  "type": "Feature",
  "properties": {
    "addr:full":"Calle de Puerto De Maderi, 19 Madrid Madrid 28053",
    "addr:housenumber":"19",
    "addr:postcode":"madrid;28053",
    "addr:street":"Calle De Puerto De Maderi",
    "iso:country":"ES",
    "sg:address":"Calle de Puerto De Maderi, 19",
    "sg:city":"Madrid",
    "sg:orig_category":"Promotores Constructores",
    "sg:phone":"+34 914 77 30 01",
    "sg:postcode":"28053",
    "sg:province":"Madrid",
    "wof:name":"Promociones Lefeber, S.l.",
    "wof:placetype":"venue"
},
  "geometry": {"coordinates":[-3.6672792435,40.3909187317],"type":"Point"}
}