{
  "type": "Feature",
  "properties": {
    "addr:full":"Ctra Tudela-tarazona, Km. 0002,0 Tudela Navarra 31500",
    "addr:postcode":"31500",
    "addr:street":"Ctra Tudela-Tarazona Km. 0002,0",
    "iso:country":"ES",
    "sg:address":"Ctra Tudela-tarazona, Km. 0002,0",
    "sg:city":"Tudela",
    "sg:orig_category":"Discapacitados",
    "sg:phone":"+34 948 84 71 60",
    "sg:postcode":"31500",
    "sg:province":"Navarra",
    "wof:name":"Avandiva S.l.",
    "wof:placetype":"venue"
},
  "geometry": {"coordinates":[-1.6729847193,41.998752594],"type":"Point"}
}