{
  "type": "Feature",
  "properties": {
    "iso:country":"ES",
    "sg:address":"Calle de Lealtad, 10",
    "sg:city":"Villaviciosa",
    "sg:orig_category":"Maquinaria Para Industrias Diversas",
    "sg:phone":"+34 985 89 06 91",
    "sg:postcode":"33300",
    "sg:province":"Asturias",
    "wof:name":"Jose Manuel Riesgo Fernandez Y Otra C.b.",
    "wof:placetype":"venue"
},
  "geometry": {"coordinates":[-5.4341239929,43.482673645],"type":"Point"}
}