{
  "type": "Feature",
  "properties": {
    "iso:country":"ES",
    "sg:address":"Calle de Sevilla, 24",
    "sg:city":"Villaluenga Sagra",
    "sg:orig_category":"Prot\u00c9sicos Dentales",
    "sg:phone":"+34 925 53 12 34",
    "sg:postcode":"45520",
    "sg:province":"Toledo",
    "wof:name":"Fernandez Morales Jose Luis",
    "wof:placetype":"venue"
},
  "geometry": {"coordinates":[-3.9063289165,40.0321311951],"type":"Point"}
}