{
  "type": "Feature",
  "properties": {
    "iso:country":"ES",
    "sg:address":"Carrer de Cardaire, 46",
    "sg:city":"Terrassa",
    "sg:orig_category":"Cajas De Ahorro",
    "sg:phone":"+34 937 83 50 00",
    "sg:postcode":"08221",
    "sg:province":"Barcelona",
    "wof:name":"Caixa D'estalvis De Catalunya",
    "wof:placetype":"venue"
},
  "geometry": {"coordinates":[2.0120000839,41.5643386841],"type":"Point"}
}