{
  "type": "Feature",
  "properties": {
    "addr:full":"Calle de Cuadra La Salera, 5 Castellon De La Plana Castell\u00f3n 12006",
    "addr:housenumber":"5",
    "addr:postcode":"12006",
    "addr:street":"Calle De Cuadra La Salera",
    "iso:country":"ES",
    "sg:address":"Calle de Cuadra La Salera, 5",
    "sg:city":"Castellon De La Plana",
    "sg:orig_category":"Peluqueros: De Se\u00d1oras",
    "sg:phone":"+34 964 21 84 17",
    "sg:postcode":"12006",
    "sg:province":"Castell\u00f3n",
    "wof:name":"Benages Solsona Irene",
    "wof:placetype":"venue"
},
  "geometry": {"coordinates":[-0.058699999,39.986240387],"type":"Point"}
}