{
  "type": "Feature",
  "properties": {
    "iso:country":"ES",
    "sg:address":"Cust Cobatillas, 21",
    "sg:city":"Ubeda",
    "sg:orig_category":"Telas Para Tapizar, Cortinas, Pasamaner\u00cda (fabricaci\u00d3n, Al Por Mayor)",
    "sg:phone":"+34 953 75 35 05",
    "sg:postcode":"23400",
    "sg:province":"Ja\u00e9n",
    "wof:name":"Casa Stor S.l",
    "wof:placetype":"venue"
},
  "geometry": {"coordinates":[-3.3703711033,38.0148277283],"type":"Point"}
}