{
  "type": "Feature",
  "properties": {
    "addr:full":"Plaz Plaza Zaharra, 4 Tolosa Guip\u00f9zcoa 20400",
    "addr:housenumber":"4",
    "addr:postcode":"20400",
    "addr:street":"Zaharra;Guipu\u0300Zcoa",
    "iso:country":"ES",
    "sg:address":"Plaz Plaza Zaharra, 4",
    "sg:city":"Tolosa",
    "sg:orig_category":"Molduras, Junquillos, Listones Y Molduras Perforadas",
    "sg:phone":"+34 943 67 04 46",
    "sg:postcode":"20400",
    "sg:province":"Guip\u00f9zcoa",
    "wof:name":"Rosa Etxebarria Y Otros C.b",
    "wof:placetype":"venue"
},
  "geometry": {"coordinates":[-2.0789339542,43.1339912415],"type":"Point"}
}