{
  "type": "Feature",
  "properties": {
    "addr:full":"A Castellana, S/n Castellana La Coru\u00f1a 15316",
    "addr:housenumber":"s / n",
    "addr:postcode":"15316",
    "addr:street":"La Corun\u0303A",
    "iso:country":"ES",
    "sg:address":"A Castellana, S/n",
    "sg:city":"Castellana",
    "sg:orig_category":"M\u00c1rmoles, Granitos Y Piedras Naturales",
    "sg:phone":"+34 981 78 97 70",
    "sg:postcode":"15316",
    "sg:province":"La Coru\u00f1a",
    "wof:name":"Jose Sanchez Corral Y Magin Freire Fidalgo C.d.",
    "wof:placetype":"venue"
},
  "geometry": {"coordinates":[-8.1660242081,43.2503967285],"type":"Point"}
}