{
  "type": "Feature",
  "properties": {
    "addr:full":"Carr Napols, 16 Palamos Girona 17230",
    "addr:housenumber":"16",
    "addr:postcode":"17230",
    "addr:street":"Carr Napols",
    "iso:country":"ES",
    "sg:address":"Carr Napols, 16",
    "sg:city":"Palamos",
    "sg:orig_category":"Molduras, Junquillos, Listones Y Molduras Perforadas",
    "sg:phone":"+34 972 60 02 49",
    "sg:postcode":"17230",
    "sg:province":"Girona",
    "wof:name":"Tutor Carrillo Miguel",
    "wof:placetype":"venue"
},
  "geometry": {"coordinates":[3.1190850735,41.8509140015],"type":"Point"}
}