{
  "type": "Feature",
  "properties": {
    "addr:full":"San Inazio Auzoa, 25 Legazpi Guip\u00f9zcoa 20230",
    "addr:housenumber":"25",
    "addr:postcode":"20230",
    "addr:street":"San Inazio Auzoa;Guipu\u0300Zcoa",
    "iso:country":"ES",
    "sg:address":"San Inazio Auzoa, 25",
    "sg:city":"Legazpi",
    "sg:orig_category":"Asociaciones, Organismos Culturales Y Socioeducativos",
    "sg:phone":"+34 943 73 19 64",
    "sg:postcode":"20230",
    "sg:province":"Guip\u00f9zcoa",
    "wof:name":"Asociacion Muru-azpi",
    "wof:placetype":"venue"
},
  "geometry": {"coordinates":[-2.3361124992,43.0549812317],"type":"Point"}
}