{
  "type": "Feature",
  "properties": {
    "addr:full":"Calle de Monte, 59 Santander Cantabria 39006",
    "addr:housenumber":"59",
    "addr:postcode":"39006",
    "addr:street":"Calle De Monte",
    "iso:country":"ES",
    "sg:address":"Calle de Monte, 59",
    "sg:city":"Santander",
    "sg:orig_category":"Deportes Diversos",
    "sg:phone":"+34 942 37 01 18",
    "sg:postcode":"39006",
    "sg:province":"Cantabria",
    "sg:website":"www.luisabuendia.com",
    "wof:name":"Buendia Bercedo Luisa Fernanda",
    "wof:placetype":"venue"
},
  "geometry": {"coordinates":[-3.8169870377,43.4647064209],"type":"Point"}
}