{
  "type": "Feature",
  "properties": {
    "addr:full":"Urb. Los Alamos, 2 Cortijillos C\u00e1diz 11379",
    "addr:housenumber":"2",
    "addr:postcode":"11379",
    "addr:street":"Los Alamos;Ca\u0301Diz",
    "iso:country":"ES",
    "sg:address":"Urb. Los Alamos, 2",
    "sg:city":"Cortijillos",
    "sg:orig_category":"Comercio De Piezas De Recambio Y De Accesorios De Veh\u00cdculos, Veh\u00cdculos Industriales",
    "sg:phone":"+34 956 67 74 00",
    "sg:postcode":"11379",
    "sg:province":"C\u00e1diz",
    "wof:name":"Hiperautos Cabrera S.l.",
    "wof:placetype":"venue"
},
  "geometry": {"coordinates":[-6.29240942,36.5299415588],"type":"Point"}
}