{
  "type": "Feature",
  "properties": {
    "iso:country":"ES",
    "sg:address":"Calle de Silencio (el), 8",
    "sg:city":"Sevilla",
    "sg:orig_category":"Promotores Constructores",
    "sg:phone":"+34 954 21 34 44",
    "sg:postcode":"41001",
    "sg:province":"Sevilla",
    "wof:name":"Cioter S.l.",
    "wof:placetype":"venue"
},
  "geometry": {"coordinates":[-5.996899128,37.3922386169],"type":"Point"}
}