{
  "type": "Feature",
  "properties": {
    "iso:country":"ES",
    "sg:address":"Calle de Leon, S/n",
    "sg:city":"Castellanos Moriscos",
    "sg:orig_category":"Imprenta",
    "sg:phone":"+34 923 36 16 91",
    "sg:postcode":"37439",
    "sg:province":"Salamanca",
    "wof:name":"Revate Gomez Jose",
    "wof:placetype":"venue"
},
  "geometry": {"coordinates":[-5.6124739647,41.0082397461],"type":"Point"}
}