{
  "type": "Feature",
  "properties": {
    "addr:full":"Calle de Pozo De Las Nieves (del), 5 Chinchon Madrid 28370",
    "addr:postcode":"28370",
    "addr:street":"Calle De Pozo De Las;Del",
    "iso:country":"ES",
    "sg:address":"Calle de Pozo De Las Nieves (del), 5",
    "sg:city":"Chinchon",
    "sg:orig_category":"Panader\u00cdas, Pasteler\u00cdas, Boller\u00cda Industriale (fabricaci\u00d3n, Al Por Mayor)",
    "sg:phone":"+34 918 94 04 89",
    "sg:postcode":"28370",
    "sg:province":"Madrid",
    "wof:name":"Llorente Caviedes Felix",
    "wof:placetype":"venue"
},
  "geometry": {"coordinates":[-3.4222679138,40.1335792542],"type":"Point"}
}