{
  "type": "Feature",
  "properties": {
    "iso:country":"ES",
    "sg:address":"Calle de Tibidabo, 18",
    "sg:city":"Repilado",
    "sg:orig_category":"Muebles, Minoristas",
    "sg:phone":"+34 959 12 26 48",
    "sg:postcode":"21360",
    "sg:province":"Huelva",
    "wof:name":"Marquez Moreno Antonio",
    "wof:placetype":"venue"
},
  "geometry": {"coordinates":[-6.7727761269,37.9286727905],"type":"Point"}
}