{
  "type": "Feature",
  "properties": {
    "iso:country":"ES",
    "sg:address":"Cuatro, 1",
    "sg:city":"San Pedro Alcantara",
    "sg:orig_category":"Inmobiliaria (agencias)",
    "sg:phone":"+34 952 88 74 29",
    "sg:postcode":"29670",
    "sg:province":"M\u00e1laga",
    "wof:name":"Tecaste,s.a.",
    "wof:placetype":"venue"
},
  "geometry": {"coordinates":[-4.9882512093,36.4894561768],"type":"Point"}
}