{
  "type": "Feature",
  "properties": {
    "addr:full":"Pase Maritimo Aguadulce, S/n Aguadulce Almer\u00eda 04720",
    "addr:housenumber":"s / n",
    "addr:postcode":"04720",
    "addr:street":"Almeri\u0301A",
    "iso:country":"ES",
    "sg:address":"Pase Maritimo Aguadulce, S/n",
    "sg:city":"Aguadulce",
    "sg:orig_category":"M\u00c9dicos: Cirug\u00cda Ortop\u00c9dica Y Traumatolog\u00cda",
    "sg:phone":"+34 950 34 10 74",
    "sg:postcode":"04720",
    "sg:province":"Almer\u00eda",
    "wof:name":"Castro Mayor Raimundo",
    "wof:placetype":"venue"
},
  "geometry": {"coordinates":[-2.5709340572,36.8083114624],"type":"Point"}
}