{
  "type": "Feature",
  "properties": {
    "addr:full":"Avda Ategorrieta De, 43 Donostia-san Sebastian Guip\u00f9zcoa 20013",
    "addr:housenumber":"43",
    "addr:postcode":"20013",
    "addr:street":"Avda Ategorrieta De",
    "iso:country":"ES",
    "sg:address":"Avda Ategorrieta De, 43",
    "sg:city":"Donostia-san Sebastian",
    "sg:orig_category":"Plomeros",
    "sg:phone":"+34 943 28 99 87",
    "sg:postcode":"20013",
    "sg:province":"Guip\u00f9zcoa",
    "wof:name":"Zapirain Esnal Agustin",
    "wof:placetype":"venue"
},
  "geometry": {"coordinates":[-1.9667359591,43.3220787048],"type":"Point"}
}