{
  "type": "Feature",
  "properties": {
    "addr:full":"Calle de Antonio Suarez, 20 Valencia Valencia 46021",
    "addr:housenumber":"20",
    "addr:postcode":"46021",
    "addr:street":"Calle De Antonio Suarez",
    "iso:country":"ES",
    "sg:address":"Calle de Antonio Suarez, 20",
    "sg:city":"Valencia",
    "sg:orig_category":"Asesor\u00cda Fiscal Y Jur\u00cddica",
    "sg:phone":"+34 963 16 90 49",
    "sg:postcode":"46021",
    "sg:province":"Valencia",
    "wof:name":"Sanz Torro Assessors S.l.",
    "wof:placetype":"venue"
},
  "geometry": {"coordinates":[-0.3570370078,39.4685325623],"type":"Point"}
}