{
  "type": "Feature",
  "properties": {
    "addr:full":"Pase Extremadura, 124 Monesterio Badajoz 06260",
    "addr:housenumber":"124",
    "addr:postcode":"06260",
    "addr:street":"Extremadura",
    "iso:country":"ES",
    "sg:address":"Pase Extremadura, 124",
    "sg:city":"Monesterio",
    "sg:orig_category":"Promotores Constructores",
    "sg:phone":"+34 924 51 67 00",
    "sg:postcode":"06260",
    "sg:province":"Badajoz",
    "wof:name":"Construcciones Teofilo Gonzalez Granadero S.l.",
    "wof:placetype":"venue"
},
  "geometry": {"coordinates":[-6.2734107971,38.0896987915],"type":"Point"}
}