{
  "type": "Feature",
  "properties": {
    "iso:country":"ES",
    "sg:address":"Pase Bizkaia De, 16",
    "sg:city":"Donostia-san Sebastian",
    "sg:orig_category":"Autob\u00das (explotaci\u00d3n Y Servicios De)",
    "sg:phone":"+34 943 46 75 29",
    "sg:postcode":"20010",
    "sg:province":"Guip\u00f9zcoa",
    "wof:name":"La Roncalesa S.a.",
    "wof:placetype":"venue"
},
  "geometry": {"coordinates":[-1.9785139561,43.3084068298],"type":"Point"}
}