{
  "type": "Feature",
  "properties": {
    "addr:full":"Rua Chantada, 145 Monforte De Lemos Lugo 27400",
    "addr:housenumber":"145",
    "addr:postcode":"27400",
    "addr:street":"Rua Chantada",
    "iso:country":"ES",
    "sg:address":"Rua Chantada, 145",
    "sg:city":"Monforte De Lemos",
    "sg:orig_category":"Asociaciones Y Clubs Deportivos",
    "sg:phone":"+34 982 40 34 60",
    "sg:postcode":"27400",
    "sg:province":"Lugo",
    "wof:name":"Rodriguez Lopez Maria Fe",
    "wof:placetype":"venue"
},
  "geometry": {"coordinates":[-7.5168690681,42.5219116211],"type":"Point"}
}