{
  "type": "Feature",
  "properties": {
    "iso:country":"ES",
    "sg:address":"Calle de Legazpi, 14",
    "sg:city":"Zumarraga",
    "sg:orig_category":"Florister\u00cdas",
    "sg:phone":"+34 943 03 67 22",
    "sg:postcode":"20700",
    "sg:province":"Guip\u00f9zcoa",
    "wof:name":"Goilore S.l.",
    "wof:placetype":"venue"
},
  "geometry": {"coordinates":[-2.3161098957,43.0893936157],"type":"Point"}
}