{
  "type": "Feature",
  "properties": {
    "iso:country":"ES",
    "sg:address":"Barr Cotarro, S/n",
    "sg:city":"Gallarta",
    "sg:orig_category":"Guarder\u00cdas",
    "sg:phone":"+34 946 36 92 24",
    "sg:postcode":"48500",
    "sg:province":"Vizcaya",
    "wof:name":"Ayuntamiento De Abanto Y Ciervana",
    "wof:placetype":"venue"
},
  "geometry": {"coordinates":[-3.0768656731,43.3152122498],"type":"Point"}
}