{
  "type": "Feature",
  "properties": {
    "iso:country":"ES",
    "sg:address":"Carr Hostal De La Bordeta, 3",
    "sg:city":"Lleida",
    "sg:orig_category":"Iglesia Cat\u00d3lica",
    "sg:phone":"+34 973 20 24 85",
    "sg:postcode":"25001",
    "sg:province":"Lleida",
    "wof:name":"Parroquia De Sant Agusti",
    "wof:placetype":"venue"
},
  "geometry": {"coordinates":[0.6420990229,41.6046905518],"type":"Point"}
}