{
  "type": "Feature",
  "properties": {
    "iso:country":"ES",
    "sg:address":"Avda Diego Ramirez Pastor, 33",
    "sg:city":"Torrevieja",
    "sg:orig_category":"Alquiler De V\u00cddeo",
    "sg:phone":"+34 965 70 56 55",
    "sg:postcode":"03180",
    "sg:province":"Alicante",
    "wof:name":"Planet Video Torrevieja C.d.",
    "wof:placetype":"venue"
},
  "geometry": {"coordinates":[-0.6880149841,37.9799919128],"type":"Point"}
}