{
  "type": "Feature",
  "properties": {
    "iso:country":"ES",
    "sg:address":"Calle de Triana, 9",
    "sg:city":"Palmas De Gran Canaria",
    "sg:orig_category":"Ropa Para Se\u00d1oras Y Caballeros (al Por Menor)",
    "sg:phone":"+34 928 36 23 29",
    "sg:postcode":"35002",
    "sg:province":"Las Palmas",
    "wof:name":"Al Akabani Arfen",
    "wof:placetype":"venue"
},
  "geometry": {"coordinates":[-15.415102005,28.1034889221],"type":"Point"}
}