{
  "type": "Feature",
  "properties": {
    "addr:full":"Calle de Verdial, 3 Rincon Victoria M\u00e1laga 29730",
    "addr:housenumber":"3",
    "addr:postcode":"29730",
    "addr:street":"Calle De Verdial;Ma\u0301Laga",
    "iso:country":"ES",
    "sg:address":"Calle de Verdial, 3",
    "sg:city":"Rincon Victoria",
    "sg:orig_category":"Negocio De Materiales De Construcci\u00d3n",
    "sg:phone":"+34 952 97 05 39",
    "sg:postcode":"29730",
    "sg:province":"M\u00e1laga",
    "wof:name":"Pacheco Diaz Eduardo",
    "wof:placetype":"venue"
},
  "geometry": {"coordinates":[-4.2913799286,36.7187843323],"type":"Point"}
}