{
  "type": "Feature",
  "properties": {
    "iso:country":"ES",
    "sg:address":"Avda Fuente Nueva (de La), 8",
    "sg:city":"San Sebastian De Los Reyes",
    "sg:orig_category":"Maquinaria Para Industrias Diversas",
    "sg:phone":"+34 916 23 90 28",
    "sg:postcode":"28700",
    "sg:province":"Madrid",
    "wof:name":"Villares Delgado Emilio",
    "wof:placetype":"venue"
},
  "geometry": {"coordinates":[-3.6151459217,40.5500869751],"type":"Point"}
}