{
  "type": "Feature",
  "properties": {
    "addr:full":"Calle de Rafael Maria De Labra, 3 Le\u00f3n Le\u00f3n 24002",
    "addr:housenumber":"3",
    "addr:postcode":"24002",
    "addr:street":"Calle De Rafael Maria De Labra;Leo\u0301N",
    "iso:country":"ES",
    "sg:address":"Calle de Rafael Maria De Labra, 3",
    "sg:city":"Le\u00f3n",
    "sg:orig_category":"Frutas Y Legumbres Frescas (al Por Mayor)",
    "sg:phone":"+34 987 23 28 13",
    "sg:postcode":"24002",
    "sg:province":"Le\u00f3n",
    "wof:name":"La Pradera De Valdeveso S.l.",
    "wof:placetype":"venue"
},
  "geometry": {"coordinates":[-5.5742712021,42.6032562256],"type":"Point"}
}