{
  "type": "Feature",
  "properties": {
    "iso:country":"ES",
    "sg:address":"Calle de Virgen De La Luz (de La), 4",
    "sg:city":"Coslada",
    "sg:orig_category":"Caf\u00c9s, Bares, Cervecer\u00cdas",
    "sg:phone":"+34 916 74 12 38",
    "sg:postcode":"28820",
    "sg:province":"Madrid",
    "wof:name":"Izquierdo Berrendero Lucia",
    "wof:placetype":"venue"
},
  "geometry": {"coordinates":[-3.5699310303,40.4256973267],"type":"Point"}
}