{
  "type": "Feature",
  "properties": {
    "addr:full":"Calle de Santa Marta, 9 Vinaros Castell\u00f3n 12500",
    "addr:housenumber":"9",
    "addr:postcode":"12500",
    "addr:street":"Calle De Santa Marta",
    "iso:country":"ES",
    "sg:address":"Calle de Santa Marta, 9",
    "sg:city":"Vinaros",
    "sg:orig_category":"Administraciones De Trabajo Y Empleo",
    "sg:phone":"+34 964 45 51 18",
    "sg:postcode":"12500",
    "sg:province":"Castell\u00f3n",
    "wof:name":"Servei Valencia D'ocupacio I Formacio",
    "wof:placetype":"venue"
},
  "geometry": {"coordinates":[0.4749450088,40.4711990356],"type":"Point"}
}