{
  "type": "Feature",
  "properties": {
    "iso:country":"ES",
    "sg:address":"Carrer de Llanera, 73",
    "sg:city":"Sabadell",
    "sg:orig_category":"Asociaciones Y Clubs Deportivos",
    "sg:phone":"+34 937 16 65 01",
    "sg:postcode":"08207",
    "sg:province":"Barcelona",
    "wof:name":"Mayor Pastor Dolores",
    "wof:placetype":"venue"
},
  "geometry": {"coordinates":[2.090914011,41.5690841675],"type":"Point"}
}