{
  "type": "Feature",
  "properties": {
    "iso:country":"ES",
    "sg:address":"Rond Carbonell, 5",
    "sg:city":"Castro Rio",
    "sg:orig_category":"Mec\u00c1nico Del Autom\u00d3vil",
    "sg:phone":"+34 957 37 04 88",
    "sg:postcode":"14840",
    "sg:province":"C\u00f3rdoba",
    "wof:name":"Navas Aranda Joaquin",
    "wof:placetype":"venue"
},
  "geometry": {"coordinates":[-4.4765949249,37.6923103333],"type":"Point"}
}