{
  "type": "Feature",
  "properties": {
    "iso:country":"ES",
    "sg:address":"Cra. Vila-seca, S/n",
    "sg:city":"Sant Vicen\u00c7 De Torello",
    "sg:orig_category":"Cajas Y Embalajes De Madera",
    "sg:phone":"+34 938 50 51 93",
    "sg:postcode":"08571",
    "sg:province":"Barcelona",
    "sg:website":"www.packplek.com",
    "wof:name":"Artesania Cervera S.l.",
    "wof:placetype":"venue"
},
  "geometry": {"coordinates":[2.2627203465,42.0482444763],"type":"Point"}
}