{
  "type": "Feature",
  "properties": {
    "addr:full":"Calle de Bibiano Contreras, 8 Jadraque Guadalajara 19240",
    "addr:housenumber":"8",
    "addr:postcode":"19240",
    "addr:street":"Calle De Bibiano Contreras",
    "iso:country":"ES",
    "sg:address":"Calle de Bibiano Contreras, 8",
    "sg:city":"Jadraque",
    "sg:orig_category":"Panader\u00cdas, Panader\u00cdas",
    "sg:phone":"+34 949 89 13 64",
    "sg:postcode":"19240",
    "sg:province":"Guadalajara",
    "wof:name":"Gomez Perdigon Carmen Del Rosario",
    "wof:placetype":"venue"
},
  "geometry": {"coordinates":[-2.9254682064,40.9257202148],"type":"Point"}
}