{
  "type": "Feature",
  "properties": {
    "iso:country":"ES",
    "sg:address":"Calle de Jose Del Hierro, 20",
    "sg:city":"Madrid",
    "sg:orig_category":"M\u00dasicos Int\u00c9rpretes",
    "sg:phone":"+34 914 06 04 62",
    "sg:postcode":"28027",
    "sg:province":"Madrid",
    "wof:name":"Chaviano Jimenez Flores",
    "wof:placetype":"venue"
},
  "geometry": {"coordinates":[-3.6456689835,40.4396400452],"type":"Point"}
}