{
  "type": "Feature",
  "properties": {
    "iso:country":"ES",
    "sg:address":"Ctra Villafranca, S/n",
    "sg:city":"Villaca\u00f1as",
    "sg:orig_category":"Asilos De Ancianos. Centros Privados",
    "sg:phone":"+34 925 20 13 13",
    "sg:postcode":"45860",
    "sg:province":"Toledo",
    "wof:name":"Centro De Mayores Castellano Manchego Uno S.l.",
    "wof:placetype":"venue"
},
  "geometry": {"coordinates":[-3.3367750645,39.6143722534],"type":"Point"}
}