{
  "type": "Feature",
  "properties": {
    "iso:country":"ES",
    "sg:address":"Calle de Limonero, 10",
    "sg:city":"Palma",
    "sg:orig_category":"Inmobiliaria (agencias)",
    "sg:phone":"+34 968 16 54 58",
    "sg:postcode":"30593",
    "sg:province":"Murcia",
    "wof:name":"Promociones Asen-bal S.l.",
    "wof:placetype":"venue"
},
  "geometry": {"coordinates":[-0.9618160129,37.6912498474],"type":"Point"}
}