{
  "type": "Feature",
  "properties": {
    "addr:full":"Calle de Cano, 30 Palmas De Gran Canaria Las Palmas 35002",
    "addr:housenumber":"30",
    "addr:postcode":"35002",
    "addr:street":"Calle De Cano",
    "iso:country":"ES",
    "sg:address":"Calle de Cano, 30",
    "sg:city":"Palmas De Gran Canaria",
    "sg:orig_category":"Agencias Y Agentes Comerciales, Representantes",
    "sg:phone":"+34 928 43 32 45",
    "sg:postcode":"35002",
    "sg:province":"Las Palmas",
    "wof:name":"Suarez Randall Juana Teresa",
    "wof:placetype":"venue"
},
  "geometry": {"coordinates":[-15.4168634415,28.10505867],"type":"Point"}
}