{
  "type": "Feature",
  "properties": {
    "addr:full":"Carrer de Frederic Mompou, 16 Granollers Barcelona 08402",
    "addr:housenumber":"16",
    "addr:postcode":"08402",
    "addr:street":"Carrer De Frederic Mompou",
    "iso:country":"ES",
    "sg:address":"Carrer de Frederic Mompou, 16",
    "sg:city":"Granollers",
    "sg:orig_category":"Abogados",
    "sg:phone":"+34 938 44 30 41",
    "sg:postcode":"08402",
    "sg:province":"Barcelona",
    "wof:name":"Mateu Mesa Concepcion",
    "wof:placetype":"venue"
},
  "geometry": {"coordinates":[2.2931480408,41.6195793152],"type":"Point"}
}