{
  "type": "Feature",
  "properties": {
    "addr:full":"Rua Anton Fraguas, 4 Pazos La Coru\u00f1a 15179",
    "addr:housenumber":"4",
    "addr:postcode":"15179",
    "addr:street":"Rua Anton Fraguas;Pazos La Corun\u0303A",
    "iso:country":"ES",
    "sg:address":"Rua Anton Fraguas, 4",
    "sg:city":"Pazos",
    "sg:orig_category":"Agencias Y Agentes Comerciales, Representantes",
    "sg:phone":"+34 981 62 63 58",
    "sg:postcode":"15179",
    "sg:province":"La Coru\u00f1a",
    "wof:name":"Representaciones Pan Rodo S.l.",
    "wof:placetype":"venue"
},
  "geometry": {"coordinates":[-8.3459596634,43.3464698792],"type":"Point"}
}