{
  "type": "Feature",
  "properties": {
    "addr:full":"Avda Agirre Lehendakaria, 48 Urbi Vizcaya 48970",
    "addr:housenumber":"48",
    "addr:postcode":"48970",
    "addr:street":"Avda Agirre Lehendakaria",
    "iso:country":"ES",
    "sg:address":"Avda Agirre Lehendakaria, 48",
    "sg:city":"Urbi",
    "sg:orig_category":"Promotores Constructores",
    "sg:phone":"+34 944 26 26 26",
    "sg:postcode":"48970",
    "sg:province":"Vizcaya",
    "wof:name":"Inmobiliaria San Fausto",
    "wof:placetype":"venue"
},
  "geometry": {"coordinates":[-2.8860394955,43.2372131348],"type":"Point"}
}