{
  "type": "Feature",
  "properties": {
    "iso:country":"ES",
    "sg:address":"Avda Celanova (de), 128",
    "sg:city":"Valenza",
    "sg:orig_category":"M\u00c9dicos: Estomatolog\u00cda",
    "sg:phone":"+34 988 24 97 64",
    "sg:postcode":"32002",
    "sg:province":"Ourense",
    "wof:name":"Suarez Novelle Ana Rosa",
    "wof:placetype":"venue"
},
  "geometry": {"coordinates":[-7.8807220459,42.3224868774],"type":"Point"}
}