{
  "type": "Feature",
  "properties": {
    "iso:country":"ES",
    "sg:address":"Calle de Raimundo Cicero Arteche, 6",
    "sg:city":"Torrelavega",
    "sg:orig_category":"Pesca Y Caza: Art\u00cdculos (al Por Menor)",
    "sg:phone":"+34 942 88 90 09",
    "sg:postcode":"39300",
    "sg:province":"Cantabria",
    "wof:name":"Iba\u00f1ez Martin Gamero Pedro",
    "wof:placetype":"venue"
},
  "geometry": {"coordinates":[-4.0535740852,43.3476676941],"type":"Point"}
}