{
  "type": "Feature",
  "properties": {
    "iso:country":"ES",
    "sg:address":"Calle de Doctor Iranzo, 19",
    "sg:city":"Zaragoza",
    "sg:orig_category":"Empresas De Carpinter\u00cda",
    "sg:phone":"+34 976 59 69 44",
    "sg:postcode":"50013",
    "sg:province":"Zaragoza",
    "wof:name":"Arregui Borao Juan Carlos",
    "wof:placetype":"venue"
},
  "geometry": {"coordinates":[-0.8647521734,41.6430931091],"type":"Point"}
}