{
  "type": "Feature",
  "properties": {
    "addr:full":"Pg Maragall, 218 Barcelona Barcelona 08031",
    "addr:housenumber":"218",
    "addr:postcode":"08031",
    "addr:street":"Pg Maragall",
    "iso:country":"ES",
    "sg:address":"Pg Maragall, 218",
    "sg:city":"Barcelona",
    "sg:orig_category":"Fabricaci\u00d3n De Su\u00c9ters Y Chalecos De Punto",
    "sg:phone":"+34 933 52 28 91",
    "sg:postcode":"08031",
    "sg:province":"Barcelona",
    "wof:name":"Ortiz Avila Antonia",
    "wof:placetype":"venue"
},
  "geometry": {"coordinates":[2.1744949818,41.4260902405],"type":"Point"}
}