{
  "type": "Feature",
  "properties": {
    "iso:country":"ES",
    "sg:address":"Avda Atlantico (del), 6",
    "sg:city":"Golf Sur",
    "sg:orig_category":"Inmobiliaria (agencias)",
    "sg:phone":"+34 922 73 70 50",
    "sg:postcode":"38639",
    "sg:province":"Santa Cruz De Tenerife",
    "wof:name":"Sol Canarias Islas S.l",
    "wof:placetype":"venue"
},
  "geometry": {"coordinates":[-16.6084651947,28.024433136],"type":"Point"}
}