{
  "type": "Feature",
  "properties": {
    "addr:full":"Calle de Alcaide, 4 Lucena C\u00f3rdoba 14900",
    "addr:housenumber":"4",
    "addr:postcode":"14900",
    "addr:street":"Calle De Alcaide",
    "iso:country":"ES",
    "sg:address":"Calle de Alcaide, 4",
    "sg:city":"Lucena",
    "sg:orig_category":"Abogados",
    "sg:phone":"+34 957 50 95 19",
    "sg:postcode":"14900",
    "sg:province":"C\u00f3rdoba",
    "wof:name":"Toro Solano Maria Del Carmen",
    "wof:placetype":"venue"
},
  "geometry": {"coordinates":[-4.4854311943,37.4098167419],"type":"Point"}
}