{
  "type": "Feature",
  "properties": {
    "iso:country":"ES",
    "sg:address":"Calle de Portugal, 39",
    "sg:city":"Fuenlabrada",
    "sg:orig_category":"Colchones (fabricaci\u00d3n, Al Por Mayor, Al Por Menor)",
    "sg:phone":"+34 916 07 46 94",
    "sg:postcode":"28943",
    "sg:province":"Madrid",
    "wof:name":"Peinado Rodriguez Rafael",
    "wof:placetype":"venue"
},
  "geometry": {"coordinates":[-3.8095231056,40.2845077515],"type":"Point"}
}