{
  "type": "Feature",
  "properties": {
    "iso:country":"ES",
    "sg:address":"Barr Garaioltza, S/n",
    "sg:city":"Garaioltza",
    "sg:orig_category":"Explotaci\u00d3n De Bosques",
    "sg:phone":"+34 944 55 51 32",
    "sg:postcode":"48196",
    "sg:province":"Vizcaya",
    "wof:name":"Basalan A.b.",
    "wof:placetype":"venue"
},
  "geometry": {"coordinates":[-2.8333890438,43.2739181519],"type":"Point"}
}