{
  "type": "Feature",
  "properties": {
    "addr:full":"Calle de Mayor, 71 Molina Segura Murcia 30500",
    "addr:housenumber":"71",
    "addr:postcode":"30500",
    "addr:street":"Calle De Mayor",
    "iso:country":"ES",
    "sg:address":"Calle de Mayor, 71",
    "sg:city":"Molina Segura",
    "sg:orig_category":"Inmobiliaria (agencias)",
    "sg:phone":"+34 968 64 09 56",
    "sg:postcode":"30500",
    "sg:province":"Murcia",
    "wof:name":"Mercantil Inversiones Y Adquisiciones Del Mediterraneo Ebamen S.l.",
    "wof:placetype":"venue"
},
  "geometry": {"coordinates":[-1.2108045816,38.0515861511],"type":"Point"}
}