{
  "type": "Feature",
  "properties": {
    "addr:full":"Calle de Eduardo Coste, 15 Arenas -areeta Vizcaya 48930",
    "addr:housenumber":"15;areeta",
    "addr:postcode":"48930",
    "addr:street":"Calle De Eduardo Coste",
    "iso:country":"ES",
    "sg:address":"Calle de Eduardo Coste, 15",
    "sg:city":"Arenas -areeta",
    "sg:orig_category":"Persianas Interiores, Exteriores",
    "sg:phone":"+34 944 80 15 34",
    "sg:postcode":"48930",
    "sg:province":"Vizcaya",
    "wof:name":"Comercial Normasa S.l.",
    "wof:placetype":"venue"
},
  "geometry": {"coordinates":[-3.0115106106,43.3210372925],"type":"Point"}
}