{
  "type": "Feature",
  "properties": {
    "addr:full":"Ctra Villamarchante, 79 Riba-roja Turia Valencia 46190",
    "addr:housenumber":"79",
    "addr:postcode":"46190",
    "addr:street":"Ctra Villamarchante",
    "iso:country":"ES",
    "sg:address":"Ctra Villamarchante, 79",
    "sg:city":"Riba-roja Turia",
    "sg:orig_category":"Negocio De Materiales De Construcci\u00d3n",
    "sg:phone":"+34 962 77 07 59",
    "sg:postcode":"46190",
    "sg:province":"Valencia",
    "wof:name":"Hermanos Marti Folgado C.b.",
    "wof:placetype":"venue"
},
  "geometry": {"coordinates":[-0.5716459751,39.5446052551],"type":"Point"}
}