{
  "type": "Feature",
  "properties": {
    "addr:full":"Calle de Pelayo, 48 Madrid Madrid 28004",
    "addr:housenumber":"48",
    "addr:postcode":"madrid;28004",
    "addr:street":"Calle De Pelayo",
    "iso:country":"ES",
    "sg:address":"Calle de Pelayo, 48",
    "sg:city":"Madrid",
    "sg:orig_category":"Vinos Y Licores (venta Al Por Menor)",
    "sg:phone":"+34 913 19 33 10",
    "sg:postcode":"28004",
    "sg:province":"Madrid",
    "wof:name":"Amaltea S.c.",
    "wof:placetype":"venue"
},
  "geometry": {"coordinates":[-3.697799921,40.4237556458],"type":"Point"}
}