{
  "type": "Feature",
  "properties": {
    "iso:country":"ES",
    "sg:address":"Carrer de Lluis Auguet, 4",
    "sg:city":"Esparreguera",
    "sg:orig_category":"Empresas De Carpinter\u00cda Met\u00c1lica",
    "sg:phone":"+34 937 77 25 15",
    "sg:postcode":"08292",
    "sg:province":"Barcelona",
    "wof:name":"Bailen Font Alexandre",
    "wof:placetype":"venue"
},
  "geometry": {"coordinates":[1.8722399473,41.533290863],"type":"Point"}
}