{
  "type": "Feature",
  "properties": {
    "addr:full":"Las Gondolas, S/n Almeria Almer\u00eda 04006",
    "addr:housenumber":"s / n",
    "addr:postcode":"04006",
    "iso:country":"ES",
    "sg:address":"Las Gondolas, S/n",
    "sg:city":"Almeria",
    "sg:orig_category":"Cajas Para Embalar",
    "sg:phone":"+34 950 27 55 72",
    "sg:postcode":"04006",
    "sg:province":"Almer\u00eda",
    "wof:name":"Cajamar",
    "wof:placetype":"venue"
},
  "geometry": {"coordinates":[-2.4608390331,36.8422698975],"type":"Point"}
}