{
  "type": "Feature",
  "properties": {
    "iso:country":"ES",
    "sg:address":"Calle de Poeta Carmelo Calvo, 1",
    "sg:city":"Alacant",
    "sg:orig_category":"Arquitectos",
    "sg:phone":"+34 965 14 34 55",
    "sg:postcode":"03004",
    "sg:province":"Alicante",
    "wof:name":"Carlos Company Arquitectos Y Asociados S.l.",
    "wof:placetype":"venue"
},
  "geometry": {"coordinates":[-0.4885469973,38.3501052856],"type":"Point"}
}