{
  "type": "Feature",
  "properties": {
    "addr:full":"Calle de Breton De Los Herreros, 10 Calahorra La Rioja 26500",
    "addr:housenumber":"10",
    "addr:postcode":"26500",
    "addr:street":"Calle De Breton De Los Herreros",
    "iso:country":"ES",
    "sg:address":"Calle de Breton De Los Herreros, 10",
    "sg:city":"Calahorra",
    "sg:orig_category":"Impuestos, Tesoro P\u00dablico",
    "sg:phone":"+34 941 14 50 06",
    "sg:postcode":"26500",
    "sg:province":"La Rioja",
    "wof:name":"Lopez Araquistain Navajas Jose Luis",
    "wof:placetype":"venue"
},
  "geometry": {"coordinates":[-1.9691449404,42.3050498962],"type":"Point"}
}