{
  "type": "Feature",
  "properties": {
    "addr:full":"Calle de Roteta, S/n Donostia-san Sebastian Guip\u00f9zcoa 20017",
    "addr:housenumber":"s",
    "addr:postcode":"20017",
    "addr:street":"Calle De Roteta;/ N",
    "iso:country":"ES",
    "sg:address":"Calle de Roteta, S/n",
    "sg:city":"Donostia-san Sebastian",
    "sg:orig_category":"Alimentaci\u00d3n General (al Por Menor)",
    "sg:phone":"+34 943 35 24 06",
    "sg:postcode":"20017",
    "sg:province":"Guip\u00f9zcoa",
    "wof:name":"Santos Orellana Vidal",
    "wof:placetype":"venue"
},
  "geometry": {"coordinates":[-1.9311189651,43.3183135986],"type":"Point"}
}