{
  "type": "Feature",
  "properties": {
    "iso:country":"ES",
    "sg:address":"Carr Sant Andreu, 113",
    "sg:city":"Cala Ratjada",
    "sg:orig_category":"Droguer\u00cdas (al Por Menor)",
    "sg:phone":"+34 971 56 36 31",
    "sg:postcode":"07590",
    "sg:province":"Islas Baleares",
    "wof:name":"Moll Fuster Antonia",
    "wof:placetype":"venue"
},
  "geometry": {"coordinates":[3.4621078968,39.7144012451],"type":"Point"}
}