{
  "type": "Feature",
  "properties": {
    "iso:country":"ES",
    "sg:address":"Calle de Luis Petralanda, 3",
    "sg:city":"Arizgoiti",
    "sg:orig_category":"Asociaciones Y Clubs Deportivos",
    "sg:phone":"+34 944 49 77 47",
    "sg:postcode":"48970",
    "sg:province":"Vizcaya",
    "wof:name":"Yolanda Vicente Vidal Ana Maria Peral Nu\u00f1ez S.c.",
    "wof:placetype":"venue"
},
  "geometry": {"coordinates":[-2.8904929161,43.2347602844],"type":"Point"}
}