{
  "type": "Feature",
  "properties": {
    "iso:country":"ES",
    "sg:address":"Calle de Alfareria, 19",
    "sg:city":"Cuevas Almanzora",
    "sg:orig_category":"Carnicer\u00cdas, Carnicer\u00cdas",
    "sg:phone":"+34 950 45 82 55",
    "sg:postcode":"04610",
    "sg:province":"Almer\u00eda",
    "wof:name":"Alonso Lopez Antonio",
    "wof:placetype":"venue"
},
  "geometry": {"coordinates":[-1.8818778992,37.294921875],"type":"Point"}
}