{
  "type": "Feature",
  "properties": {
    "addr:full":"Calle de Getafe, 17 Parla Madrid 28980",
    "addr:housenumber":"17",
    "addr:postcode":"28980",
    "addr:street":"Calle De Getafe",
    "iso:country":"ES",
    "sg:address":"Calle de Getafe, 17",
    "sg:city":"Parla",
    "sg:orig_category":"Peluquer\u00cdas, Peluquer\u00cda Mixta",
    "sg:phone":"+34 916 05 67 59",
    "sg:postcode":"28980",
    "sg:province":"Madrid",
    "wof:name":"Sanchez Rodriguez Maria Yolanda",
    "wof:placetype":"venue"
},
  "geometry": {"coordinates":[-3.7711269855,40.2424736023],"type":"Point"}
}