{
  "type": "Feature",
  "properties": {
    "addr:full":"Alto De La Albillera, S/n Zamora Zamora 49025",
    "addr:housenumber":"s",
    "addr:postcode":"49025",
    "addr:street":"Alto;La Albillera;/ N",
    "iso:country":"ES",
    "sg:address":"Alto De La Albillera, S/n",
    "sg:city":"Zamora",
    "sg:orig_category":"Reposter\u00cdas",
    "sg:phone":"+34 980 52 58 13",
    "sg:postcode":"49025",
    "sg:province":"Zamora",
    "wof:name":"Industrias De Alimentacion Don Carlos S.l.",
    "wof:placetype":"venue"
},
  "geometry": {"coordinates":[-5.7591128349,41.5143432617],"type":"Point"}
}