{
  "type": "Feature",
  "properties": {
    "addr:full":"Avda Escaleritas, 62 Palmas De Gran Canaria Las Palmas 35011",
    "addr:housenumber":"62",
    "addr:postcode":"35011",
    "addr:street":"Avda Escaleritas",
    "iso:country":"ES",
    "sg:address":"Avda Escaleritas, 62",
    "sg:city":"Palmas De Gran Canaria",
    "sg:orig_category":"Peluquer\u00cdas, Peluquer\u00cda Mixta",
    "sg:phone":"+34 928 20 75 64",
    "sg:postcode":"35011",
    "sg:province":"Las Palmas",
    "wof:name":"Bola\u00f1os Santana Antonia",
    "wof:placetype":"venue"
},
  "geometry": {"coordinates":[-15.4456071854,28.1020545959],"type":"Point"}
}