{
  "type": "Feature",
  "properties": {
    "addr:full":"Constel Dragon, 4 Utrera Sevilla 41710",
    "addr:postcode":"41710",
    "iso:country":"ES",
    "sg:address":"Constel Dragon, 4",
    "sg:city":"Utrera",
    "sg:orig_category":"Frutas Y Legumbres Frescas (al Por Mayor)",
    "sg:phone":"+34 955 86 79 98",
    "sg:postcode":"41710",
    "sg:province":"Sevilla",
    "wof:name":"Martin Chuan Antonia Maria",
    "wof:placetype":"venue"
},
  "geometry": {"coordinates":[-5.7768039703,37.1902656555],"type":"Point"}
}