{
  "type": "Feature",
  "properties": {
    "iso:country":"ES",
    "sg:address":"Calle de Lirio, 2",
    "sg:city":"Barbate",
    "sg:orig_category":"Inmobiliaria (agencias)",
    "sg:phone":"+34 956 43 48 00",
    "sg:postcode":"11160",
    "sg:province":"C\u00e1diz",
    "wof:name":"Punta Camarinal S.l.",
    "wof:placetype":"venue"
},
  "geometry": {"coordinates":[-5.9197640419,36.1877098083],"type":"Point"}
}