{
  "type": "Feature",
  "properties": {
    "addr:full":"Ptge Milans, S/n Hospitalet Llobregat Barcelona 08907",
    "addr:housenumber":"s",
    "addr:postcode":"08907",
    "addr:street":"Ptge Milans;/ N",
    "iso:country":"ES",
    "sg:address":"Ptge Milans, S/n",
    "sg:city":"Hospitalet Llobregat",
    "sg:orig_category":"Asociaciones Y Clubs Deportivos",
    "sg:phone":"+34 933 37 35 54",
    "sg:postcode":"08907",
    "sg:province":"Barcelona",
    "wof:name":"Atletico Club Hospitalense",
    "wof:placetype":"venue"
},
  "geometry": {"coordinates":[2.1029396057,41.3560028076],"type":"Point"}
}