{
  "type": "Feature",
  "properties": {
    "iso:country":"ES",
    "sg:address":"Calle de Vidal Garcia Seves, S/n",
    "sg:city":"Yeles",
    "sg:orig_category":"Centros De Educaci\u00d3n Especial",
    "sg:phone":"+34 925 54 51 24",
    "sg:postcode":"45220",
    "sg:province":"Toledo",
    "wof:name":"Colegio Publico San Antonio",
    "wof:placetype":"venue"
},
  "geometry": {"coordinates":[-3.8025610447,40.1211051941],"type":"Point"}
}