{
  "type": "Feature",
  "properties": {
    "iso:country":"ES",
    "sg:address":"Calle de Marcos Pe\u00d1a Royo, 33",
    "sg:city":"Oviedo",
    "sg:orig_category":"Peluqueros: De Se\u00d1oras",
    "sg:phone":"+34 985 27 74 34",
    "sg:postcode":"33013",
    "sg:province":"Asturias",
    "wof:name":"Lopez Abad Vidalina",
    "wof:placetype":"venue"
},
  "geometry": {"coordinates":[-5.8656191826,43.3625946045],"type":"Point"}
}