{
  "type": "Feature",
  "properties": {
    "iso:country":"ES",
    "sg:address":"Carrer de Ifni, S/n",
    "sg:city":"S. Adria Besos",
    "sg:orig_category":"Fabricaci\u00d3n, Venta De Cuadros, Accesorios Para Enmarcar",
    "sg:phone":"+34 934 62 20 79",
    "sg:postcode":"08930",
    "sg:province":"Barcelona",
    "sg:website":"www.moldurasbustamante.com",
    "wof:name":"Comolbus S.l.",
    "wof:placetype":"venue"
},
  "geometry": {"coordinates":[2.2319049835,41.4297790527],"type":"Point"}
}