{
  "type": "Feature",
  "properties": {
    "addr:full":"Plaz Constitucion, 10 Petres Valencia 46500",
    "addr:housenumber":"10",
    "addr:postcode":"46500",
    "addr:street":"Constitucion",
    "iso:country":"ES",
    "sg:address":"Plaz Constitucion, 10",
    "sg:city":"Petres",
    "sg:orig_category":"Comercio De Hierro",
    "sg:phone":"+34 962 62 08 26",
    "sg:postcode":"46500",
    "sg:province":"Valencia",
    "wof:name":"Ferrallas Dapa S.l.",
    "wof:placetype":"venue"
},
  "geometry": {"coordinates":[-0.2783089876,39.6799659729],"type":"Point"}
}