{
  "type": "Feature",
  "properties": {
    "iso:country":"ES",
    "sg:address":"Calle de Sao Paulo, 20",
    "sg:city":"Palmas De Gran Canaria",
    "sg:classifiers":[
        {
            "category":"Communications",
            "type":"Services"
        }
    ],
    "sg:phone":"+34 928 46 17 28",
    "sg:postcode":"35008",
    "sg:province":"Las Palmas",
    "sg:tags":[
        "televisiones",
        "y",
        "radio"
    ],
    "wof:name":"Audiovisual Canarias S.l. Canal 25 T.v.",
    "wof:placetype":"venue"
},
  "geometry": {"coordinates":[-15.4212150574,28.1577472687],"type":"Point"}
}