{
  "type": "Feature",
  "properties": {
    "addr:full":"Calle de Don Felix Ezquerra, 17 Fuensalida Toledo 45510",
    "addr:housenumber":"17",
    "addr:postcode":"45510",
    "addr:street":"Calle De Don Felix Ezquerra",
    "iso:country":"ES",
    "sg:address":"Calle de Don Felix Ezquerra, 17",
    "sg:city":"Fuensalida",
    "sg:orig_category":"Aceites Y Grasas Alimentarias (fabricaci\u00d3n, Al Por Mayor)",
    "sg:phone":"+34 925 78 40 09",
    "sg:postcode":"45510",
    "sg:province":"Toledo",
    "wof:name":"Aceites Del Tajo S.l:",
    "wof:placetype":"venue"
},
  "geometry": {"coordinates":[-4.1820960045,40.0597686768],"type":"Point"}
}