{
  "type": "Feature",
  "properties": {
    "iso:country":"ES",
    "sg:address":"Calle de Pintor Goya, 24",
    "sg:city":"Sos Del Rey Catolico",
    "sg:orig_category":"Venta, Instalaci\u00d3n De Cocinas",
    "sg:phone":"+34 948 88 80 71",
    "sg:postcode":"50680",
    "sg:province":"Zaragoza",
    "wof:name":"Vinacua Martinez Jesus",
    "wof:placetype":"venue"
},
  "geometry": {"coordinates":[-1.2161489725,42.4939804077],"type":"Point"}
}