{
  "type": "Feature",
  "properties": {
    "addr:full":"Calle de Solidaridad (de La), 3 Chiclana De La Frontera C\u00e1diz 11130",
    "addr:postcode":"11130",
    "addr:street":"Calle De Solidaridad De La 3",
    "iso:country":"ES",
    "sg:address":"Calle de Solidaridad (de La), 3",
    "sg:city":"Chiclana De La Frontera",
    "sg:orig_category":"Escayola Y Productos De Escayola (fabricaci\u00d3n, Al Por Mayor)",
    "sg:phone":"+34 956 40 20 09",
    "sg:postcode":"11130",
    "sg:province":"C\u00e1diz",
    "sg:website":"www.escayolasestrasda.es",
    "wof:name":"Escayolas Estrada S.l.",
    "wof:placetype":"venue"
},
  "geometry": {"coordinates":[-6.1326990128,36.4043922424],"type":"Point"}
}