{
  "type": "Feature",
  "properties": {
    "addr:full":"Calle de Emilio Thuillier, 94 Malaga M\u00e1laga 29014",
    "addr:housenumber":"94",
    "addr:postcode":"29014",
    "addr:street":"Calle De Emilio Thuillier;Ma\u0301Laga",
    "iso:country":"ES",
    "sg:address":"Calle de Emilio Thuillier, 94",
    "sg:city":"Malaga",
    "sg:orig_category":"Relojer\u00cda (al Por Menor, Reparaci\u00d3n)",
    "sg:phone":"+34 952 65 01 83",
    "sg:postcode":"29014",
    "sg:province":"M\u00e1laga",
    "wof:name":"Palma Castro Ariadna",
    "wof:placetype":"venue"
},
  "geometry": {"coordinates":[-4.4216051102,36.7464027405],"type":"Point"}
}