{
  "type": "Feature",
  "properties": {
    "iso:country":"ES",
    "sg:address":"Carrer de Velazquez, 49",
    "sg:city":"Mataro",
    "sg:orig_category":"Fabricaci\u00d3n De Su\u00c9ters Y Chalecos De Punto",
    "sg:phone":"+34 937 98 63 52",
    "sg:postcode":"08302",
    "sg:province":"Barcelona",
    "wof:name":"Punt-may S.l.",
    "wof:placetype":"venue"
},
  "geometry": {"coordinates":[2.4356501102,41.5388450623],"type":"Point"}
}