{
  "type": "Feature",
  "properties": {
    "iso:country":"ES",
    "sg:address":"Carr Canalejas, 14",
    "sg:city":"Vila Joiosa",
    "sg:orig_category":"Electrodom\u00c9sticos (al Por Menor)",
    "sg:phone":"+34 965 89 12 85",
    "sg:postcode":"03570",
    "sg:province":"Alicante",
    "wof:name":"Ortiz Perez Jeronimo",
    "wof:placetype":"venue"
},
  "geometry": {"coordinates":[-0.2327190042,38.505821228],"type":"Point"}
}