{
  "type": "Feature",
  "properties": {
    "addr:full":"Avgd Republica Argentina, 54 Gandia Valencia 46700",
    "addr:housenumber":"54",
    "addr:postcode":"46700",
    "addr:street":"Argentina;Valencia",
    "iso:country":"ES",
    "sg:address":"Avgd Republica Argentina, 54",
    "sg:city":"Gandia",
    "sg:orig_category":"Asesor\u00cda Sobre Comunicaci\u00d3n De Empresas",
    "sg:phone":"+34 962 87 86 87",
    "sg:postcode":"46700",
    "sg:province":"Valencia",
    "wof:name":"Indret Consultores S.l.",
    "wof:placetype":"venue"
},
  "geometry": {"coordinates":[-0.1913339943,38.960735321],"type":"Point"}
}