{
  "type": "Feature",
  "properties": {
    "iso:country":"ES",
    "sg:address":"Plaz Mayor, 3",
    "sg:city":"Beteta",
    "sg:orig_category":"Asociaciones, Organismos Culturales Y Socioeducativos",
    "sg:phone":"+34 969 31 80 95",
    "sg:postcode":"16870",
    "sg:province":"Cuenca",
    "wof:name":"Ayuntamiento De Beteta- Centro Social Polivalente",
    "wof:placetype":"venue"
},
  "geometry": {"coordinates":[-2.076281786,40.571849823],"type":"Point"}
}