{
  "type": "Feature",
  "properties": {
    "addr:full":"Carr Nord, 33 Angles Girona 17160",
    "addr:housenumber":"33",
    "addr:postcode":"17160",
    "addr:street":"Carr Nord",
    "iso:country":"ES",
    "sg:address":"Carr Nord, 33",
    "sg:city":"Angles",
    "sg:orig_category":"Frutas, Legumbres Frescas Y Tempranas (al Por Menor)",
    "sg:phone":"+34 972 42 30 26",
    "sg:postcode":"17160",
    "sg:province":"Girona",
    "wof:name":"Angles Fruits S.c.",
    "wof:placetype":"venue"
},
  "geometry": {"coordinates":[2.6363072395,41.9558563232],"type":"Point"}
}