{
  "type": "Feature",
  "properties": {
    "iso:country":"ES",
    "sg:address":"Calle de Aluminio, 38",
    "sg:city":"Valladolid",
    "sg:orig_category":"Coches Y Camiones (caja De Cambios, Embrague Y Frenos)",
    "sg:phone":"+34 983 30 56 00",
    "sg:postcode":"47012",
    "sg:province":"Valladolid",
    "wof:name":"Frenos Jose S.l",
    "wof:placetype":"venue"
},
  "geometry": {"coordinates":[-4.7099790573,41.6221427917],"type":"Point"}
}