{
  "type": "Feature",
  "properties": {
    "iso:country":"ES",
    "sg:address":"Avda Cruz Roja (la), 22",
    "sg:city":"Jerez De La Frontera",
    "sg:orig_category":"Asesor\u00cda Sobre Comunicaci\u00d3n De Empresas",
    "sg:phone":"+34 956 18 21 09",
    "sg:postcode":"11407",
    "sg:province":"C\u00e1diz",
    "wof:name":"Gambe Asesores S.c.",
    "wof:placetype":"venue"
},
  "geometry": {"coordinates":[-6.1352567673,36.6974449158],"type":"Point"}
}