{
  "type": "Feature",
  "properties": {
    "addr:full":"Calle de Alcala, 196 Madrid Madrid 28028",
    "addr:housenumber":"196",
    "addr:postcode":"28028",
    "addr:street":"Calle De Alcala",
    "iso:country":"ES",
    "sg:address":"Calle de Alcala, 196",
    "sg:city":"Madrid",
    "sg:orig_category":"Centros Empresariales",
    "sg:phone":"+34 913 55 58 50",
    "sg:postcode":"28028",
    "sg:province":"Madrid",
    "wof:name":"Gonzalez Carrasco Concepcion",
    "wof:placetype":"venue"
},
  "geometry": {"coordinates":[-3.6645534039,40.4301528931],"type":"Point"}
}