{
  "type": "Feature",
  "properties": {
    "iso:country":"ES",
    "sg:address":"Avda Ordesa, 20",
    "sg:city":"Ainsa",
    "sg:orig_category":"Fotograf\u00cda Y Cine: Aparatos, Pel\u00cdculas Y Accesorios (al Por Menor)",
    "sg:phone":"+34 974 50 07 55",
    "sg:postcode":"22330",
    "sg:province":"Huesca",
    "wof:name":"Parra Oncins Joaquin Francisco",
    "wof:placetype":"venue"
},
  "geometry": {"coordinates":[0.1381140053,42.4158096313],"type":"Point"}
}