{
  "type": "Feature",
  "properties": {
    "iso:country":"ES",
    "sg:address":"Calle de Vicente Aleixandre (de), S/n",
    "sg:city":"Humanes De Madrid",
    "sg:orig_category":"Carnicer\u00cdas, Carnicer\u00cdas",
    "sg:phone":"+34 916 04 26 42",
    "sg:postcode":"28970",
    "sg:province":"Madrid",
    "wof:name":"Hernandez Alarcon Mariano",
    "wof:placetype":"venue"
},
  "geometry": {"coordinates":[-3.8218019009,40.2571411133],"type":"Point"}
}