{
  "type": "Feature",
  "properties": {
    "iso:country":"ES",
    "sg:address":"Pase Pedro Simon Abril, 17",
    "sg:city":"Albacete",
    "sg:orig_category":"Estancos",
    "sg:phone":"+34 967 23 84 59",
    "sg:postcode":"02003",
    "sg:province":"Albacete",
    "wof:name":"Valero Mu\u00f1oz Agustin",
    "wof:placetype":"venue"
},
  "geometry": {"coordinates":[-1.8588930368,38.9874954224],"type":"Point"}
}