{
  "type": "Feature",
  "properties": {
    "addr:full":"Calle de Camilo Sancho, 13 Sellent Valencia 46295",
    "addr:housenumber":"13",
    "addr:postcode":"46295",
    "addr:street":"Calle De Camilo Sancho",
    "iso:country":"ES",
    "sg:address":"Calle de Camilo Sancho, 13",
    "sg:city":"Sellent",
    "sg:orig_category":"Cr\u00cda De Animales",
    "sg:phone":"+34 962 25 42 58",
    "sg:postcode":"46295",
    "sg:province":"Valencia",
    "wof:name":"Silverio Moreno S.l.",
    "wof:placetype":"venue"
},
  "geometry": {"coordinates":[-0.630621016,39.0945587158],"type":"Point"}
}