{
  "type": "Feature",
  "properties": {
    "iso:country":"ES",
    "sg:address":"Carrer de Lleialtat, 38",
    "sg:city":"Esplugues Llobregat",
    "sg:orig_category":"Molduras, Junquillos, Listones Y Molduras Perforadas",
    "sg:phone":"+34 934 73 10 14",
    "sg:postcode":"08950",
    "sg:province":"Barcelona",
    "wof:name":"Algis Restauracion S.c.t.",
    "wof:placetype":"venue"
},
  "geometry": {"coordinates":[2.0929803848,41.3745384216],"type":"Point"}
}