{
  "type": "Feature",
  "properties": {
    "addr:full":"Errosario Kalea, 10 Elgoibar Guip\u00f9zcoa 20870",
    "addr:housenumber":"10",
    "addr:postcode":"20870",
    "addr:street":"Errosario Kalea;Guipu\u0300Zcoa",
    "iso:country":"ES",
    "sg:address":"Errosario Kalea, 10",
    "sg:city":"Elgoibar",
    "sg:orig_category":"Carnicer\u00cdas, Carnicer\u00cdas",
    "sg:phone":"+34 943 74 05 54",
    "sg:postcode":"20870",
    "sg:province":"Guip\u00f9zcoa",
    "wof:name":"Amaia Arrizabalaga Mugerza",
    "wof:placetype":"venue"
},
  "geometry": {"coordinates":[-2.4168400764,43.214805603],"type":"Point"}
}