{
  "type": "Feature",
  "properties": {
    "iso:country":"ES",
    "sg:address":"Calle de Merced, 7",
    "sg:city":"Toledo",
    "sg:orig_category":"Electrodom\u00c9sticos (al Por Menor)",
    "sg:phone":"+34 925 25 79 16",
    "sg:postcode":"45002",
    "sg:province":"Toledo",
    "wof:name":"Jimenez Martin-borja Luis Idelfonso",
    "wof:placetype":"venue"
},
  "geometry": {"coordinates":[-4.027577877,39.8601036072],"type":"Point"}
}