{
  "type": "Feature",
  "properties": {
    "iso:country":"ES",
    "sg:address":"Calle de Marineras, 13",
    "sg:city":"Ajalvir",
    "sg:orig_category":"Maquinaria Para Industrias Diversas",
    "sg:phone":"+34 918 84 43 82",
    "sg:postcode":"28864",
    "sg:province":"Madrid",
    "wof:name":"Hormesa",
    "wof:placetype":"venue"
},
  "geometry": {"coordinates":[-3.4794969559,40.5157546997],"type":"Point"}
}