{
  "type": "Feature",
  "properties": {
    "addr:full":"Amillaga Kalea, 14 Bergara Guip\u00f9zcoa 20570",
    "addr:housenumber":"14",
    "addr:postcode":"20570",
    "addr:street":"Amillaga Kalea;Guipu\u0300Zcoa",
    "iso:country":"ES",
    "sg:address":"Amillaga Kalea, 14",
    "sg:city":"Bergara",
    "sg:orig_category":"Filtros Y Elementos Filtradores",
    "sg:phone":"+34 943 76 17 45",
    "sg:postcode":"20570",
    "sg:province":"Guip\u00f9zcoa",
    "wof:name":"Filber S.l.",
    "wof:placetype":"venue"
},
  "geometry": {"coordinates":[-2.4238700867,43.124042511],"type":"Point"}
}