{
  "type": "Feature",
  "properties": {
    "addr:full":"Poligon Ind. Belianes, 18 Cambrils Tarragona 43850",
    "addr:housenumber":"18",
    "addr:postcode":"43850",
    "iso:country":"ES",
    "sg:address":"Poligon Ind. Belianes, 18",
    "sg:city":"Cambrils",
    "sg:orig_category":"Carnes De Carnicer\u00cda (al Por Mayor)",
    "sg:phone":"+34 977 36 21 64",
    "sg:postcode":"43850",
    "sg:province":"Tarragona",
    "wof:name":"Industrias Carnicas Sole S.a.",
    "wof:placetype":"venue"
},
  "geometry": {"coordinates":[1.0298918486,41.0852050781],"type":"Point"}
}