{
  "type": "Feature",
  "properties": {
    "addr:full":"Calle de Cervantes, 20 Torrent Valencia 46900",
    "addr:housenumber":"20",
    "addr:postcode":"46900",
    "addr:street":"Calle De Cervantes;Valencia",
    "iso:country":"ES",
    "sg:address":"Calle de Cervantes, 20",
    "sg:city":"Torrent",
    "sg:orig_category":"Asesor\u00cda Sobre Comunicaci\u00d3n De Empresas",
    "sg:phone":"+34 961 51 53 55",
    "sg:postcode":"46900",
    "sg:province":"Valencia",
    "wof:name":"Iniciativas Para El Desarrollo Economico Y Social S.l.",
    "wof:placetype":"venue"
},
  "geometry": {"coordinates":[-0.4621441066,39.3613471985],"type":"Point"}
}