{
  "type": "Feature",
  "properties": {
    "addr:full":"Calle de Casablanca, 5 Torremolinos M\u00e1laga 29620",
    "addr:housenumber":"5",
    "addr:postcode":"29620",
    "addr:street":"Calle De Casablanca;Ma\u0301Laga",
    "iso:country":"ES",
    "sg:address":"Calle de Casablanca, 5",
    "sg:city":"Torremolinos",
    "sg:orig_category":"Panader\u00cdas, Panader\u00cdas",
    "sg:phone":"+34 952 37 89 65",
    "sg:postcode":"29620",
    "sg:province":"M\u00e1laga",
    "wof:name":"Panificadora El Bambi",
    "wof:placetype":"venue"
},
  "geometry": {"coordinates":[-4.4978642464,36.6222457886],"type":"Point"}
}