{
  "type": "Feature",
  "properties": {
    "addr:full":"Cllo Mallo, 1 Marin Pontevedra 36900",
    "addr:housenumber":"1",
    "addr:postcode":"36900",
    "iso:country":"ES",
    "sg:address":"Cllo Mallo, 1",
    "sg:city":"Marin",
    "sg:orig_category":"Transportes Frigor\u00cdficos",
    "sg:phone":"+34 986 88 43 74",
    "sg:postcode":"36900",
    "sg:province":"Pontevedra",
    "wof:name":"Mallo Leira Angel",
    "wof:placetype":"venue"
},
  "geometry": {"coordinates":[-8.6881885529,42.391746521],"type":"Point"}
}