{
  "type": "Feature",
  "properties": {
    "addr:full":"Calle de Jesusa Lara, 18 Estacion Madrid 28250",
    "addr:housenumber":"18 estacion",
    "addr:postcode":"28250",
    "addr:street":"Calle De Jesusa Lara",
    "iso:country":"ES",
    "sg:address":"Calle de Jesusa Lara, 18",
    "sg:city":"Estacion",
    "sg:orig_category":"Abogados",
    "sg:phone":"+34 918 59 43 31",
    "sg:postcode":"28250",
    "sg:province":"Madrid",
    "wof:name":"Macias Rodriguez Rosario",
    "wof:placetype":"venue"
},
  "geometry": {"coordinates":[-3.9536468983,40.5789299011],"type":"Point"}
}