{
  "type": "Feature",
  "properties": {
    "iso:country":"ES",
    "sg:address":"Calle de Pio Baroja, 27",
    "sg:city":"Churriana Vega",
    "sg:orig_category":"Servicios De Telecomunicaciones",
    "sg:phone":"+34 958 55 04 59",
    "sg:postcode":"18194",
    "sg:province":"Granada",
    "sg:website":"www.athenas.com",
    "wof:name":"Athenas Telecomunicaciones S.l.",
    "wof:placetype":"venue"
},
  "geometry": {"coordinates":[-3.6366186142,37.1448326111],"type":"Point"}
}