{
  "type": "Feature",
  "properties": {
    "addr:full":"Calle de Santa Isabel, 22 Albelda Iregua La Rioja 26120",
    "addr:housenumber":"22",
    "addr:postcode":"26120",
    "addr:street":"Calle De Santa Isabel;Rioja",
    "iso:country":"ES",
    "sg:address":"Calle de Santa Isabel, 22",
    "sg:city":"Albelda Iregua",
    "sg:orig_category":"Carnicer\u00cdas, Carnicer\u00cdas",
    "sg:phone":"+34 941 44 36 73",
    "sg:postcode":"26120",
    "sg:province":"La Rioja",
    "wof:name":"Pascual Carballo Asuncion",
    "wof:placetype":"venue"
},
  "geometry": {"coordinates":[-2.4733989239,42.357421875],"type":"Point"}
}