{
  "type": "Feature",
  "properties": {
    "addr:full":"Carrer de Avenir, 24 Valls Tarragona 43800",
    "addr:housenumber":"24",
    "addr:postcode":"43800",
    "addr:street":"Carrer De Avenir",
    "iso:country":"ES",
    "sg:address":"Carrer de Avenir, 24",
    "sg:city":"Valls",
    "sg:orig_category":"Art\u00cdculos De Decoraci\u00d3n",
    "sg:phone":"+34 977 61 41 40",
    "sg:postcode":"43800",
    "sg:province":"Tarragona",
    "wof:name":"Carmona Garcia Juan Jose",
    "wof:placetype":"venue"
},
  "geometry": {"coordinates":[1.2555160522,41.2883491516],"type":"Point"}
}