{
  "type": "Feature",
  "properties": {
    "iso:country":"ES",
    "sg:address":"Av Pirineus, 14",
    "sg:city":"Tremp",
    "sg:orig_category":"Mec\u00c1nico Del Autom\u00d3vil",
    "sg:phone":"+34 973 65 01 03",
    "sg:postcode":"25620",
    "sg:province":"Lleida",
    "wof:name":"Taller Montsec S.l.",
    "wof:placetype":"venue"
},
  "geometry": {"coordinates":[0.8962029815,42.1727714539],"type":"Point"}
}