{
  "type": "Feature",
  "properties": {
    "iso:country":"ES",
    "sg:address":"Calle de San Vicente Ferrer, 1",
    "sg:city":"Santo Angel",
    "sg:orig_category":"Empresas De Carpinter\u00cda De Madera",
    "sg:phone":"+34 968 84 17 32",
    "sg:postcode":"30151",
    "sg:province":"Murcia",
    "wof:name":"Murcia Velasco Jose",
    "wof:placetype":"venue"
},
  "geometry": {"coordinates":[-1.1287330389,37.9449653625],"type":"Point"}
}