{
  "type": "Feature",
  "properties": {
    "addr:full":"Avda San Diego, 73 Madrid Madrid 28053",
    "addr:housenumber":"73",
    "addr:postcode":"madrid;28053",
    "addr:street":"Avda San Diego",
    "iso:country":"ES",
    "sg:address":"Avda San Diego, 73",
    "sg:city":"Madrid",
    "sg:orig_category":"Farmacias",
    "sg:phone":"+34 914 78 70 05",
    "sg:postcode":"28053",
    "sg:province":"Madrid",
    "wof:name":"Torre Rodriguez Maria Angeles De La",
    "wof:placetype":"venue"
},
  "geometry": {"coordinates":[-3.6671669483,40.3860092163],"type":"Point"}
}