{
  "type": "Feature",
  "properties": {
    "addr:full":"Calle de Alfonso Xiii, 37 Dolores Murcia 30310",
    "addr:housenumber":"37",
    "addr:postcode":"30310",
    "addr:street":"Calle De Alfonso Xiii",
    "iso:country":"ES",
    "sg:address":"Calle de Alfonso Xiii, 37",
    "sg:city":"Dolores",
    "sg:orig_category":"Centros Comerciales Y Grandes Tiendas",
    "sg:phone":"+34 968 12 65 91",
    "sg:postcode":"30310",
    "sg:province":"Murcia",
    "wof:name":"Wei  Yiren",
    "wof:placetype":"venue"
},
  "geometry": {"coordinates":[-1.0032578707,37.6398429871],"type":"Point"}
}