{
  "type": "Feature",
  "properties": {
    "addr:full":"Calle de Dieciocho De Julio, 7 Belchite Zaragoza 50130",
    "addr:housenumber":"7",
    "addr:postcode":"50130",
    "addr:street":"Calle De Dieciocho De Julio",
    "iso:country":"ES",
    "sg:address":"Calle de Dieciocho De Julio, 7",
    "sg:city":"Belchite",
    "sg:orig_category":"Notarios",
    "sg:phone":"+34 976 83 90 08",
    "sg:postcode":"50130",
    "sg:province":"Zaragoza",
    "wof:name":"Asensio Urra Maria Del Carmen",
    "wof:placetype":"venue"
},
  "geometry": {"coordinates":[-0.7535486221,41.3070259094],"type":"Point"}
}