{
  "type": "Feature",
  "properties": {
    "addr:full":"Avda Constitucion (de La), 44 Granada Granada 18012",
    "addr:housenumber":"44",
    "addr:postcode":"18012",
    "addr:street":"Avda Constitucion De La",
    "iso:country":"ES",
    "sg:address":"Avda Constitucion (de La), 44",
    "sg:city":"Granada",
    "sg:orig_category":"Notarios",
    "sg:phone":"+34 958 80 41 33",
    "sg:postcode":"18012",
    "sg:province":"Granada",
    "wof:name":"Orantes Rodriguez Alfonso Carlos",
    "wof:placetype":"venue"
},
  "geometry": {"coordinates":[-3.6087040901,37.1865653992],"type":"Point"}
}