{
  "type": "Feature",
  "properties": {
    "iso:country":"ES",
    "sg:address":"Calle de Antonio Machado, 32",
    "sg:city":"Algaba",
    "sg:orig_category":"Centros Comerciales Y Grandes Tiendas",
    "sg:phone":"+34 955 78 71 63",
    "sg:postcode":"41980",
    "sg:province":"Sevilla",
    "wof:name":"Comegarce S.l.",
    "wof:placetype":"venue"
},
  "geometry": {"coordinates":[-6.0333447456,37.400428772],"type":"Point"}
}