{
  "type": "Feature",
  "properties": {
    "addr:full":"Calle de Nuria, 53 Madrid Madrid 28034",
    "addr:housenumber":"53",
    "addr:postcode":"madrid;28034",
    "addr:street":"Calle De Nuria",
    "iso:country":"ES",
    "sg:address":"Calle de Nuria, 53",
    "sg:city":"Madrid",
    "sg:orig_category":"Distribuci\u00d3n De Petr\u00d3leo Y Derivados",
    "sg:phone":"+34 917 34 37 02",
    "sg:postcode":"28034",
    "sg:province":"Madrid",
    "wof:name":"Martinez Brasa Sl",
    "wof:placetype":"venue"
},
  "geometry": {"coordinates":[-3.7107770443,40.4948234558],"type":"Point"}
}