{
  "type": "Feature",
  "properties": {
    "addr:full":"Calle de Guillermo De Osma, 6 Madrid Madrid 28045",
    "addr:housenumber":"6",
    "addr:postcode":"28045",
    "addr:street":"Calle De Guillermo De Osma",
    "iso:country":"ES",
    "sg:address":"Calle de Guillermo De Osma, 6",
    "sg:city":"Madrid",
    "sg:orig_category":"Alimentaci\u00d3n General (al Por Menor)",
    "sg:phone":"+34 914 74 43 17",
    "sg:postcode":"28045",
    "sg:province":"Madrid",
    "wof:name":"Ceballos Torre Beti Auxiliadora",
    "wof:placetype":"venue"
},
  "geometry": {"coordinates":[-3.6958749294,40.3940811157],"type":"Point"}
}