{
  "type": "Feature",
  "properties": {
    "iso:country":"ES",
    "sg:address":"Carrer de Cavall Bernat, 17",
    "sg:city":"Hospitalet Llobregat",
    "sg:orig_category":"Ebanister\u00cda",
    "sg:phone":"+34 934 22 87 63",
    "sg:postcode":"08902",
    "sg:province":"Barcelona",
    "wof:name":"Garcia Acosta Antonio",
    "wof:placetype":"venue"
},
  "geometry": {"coordinates":[2.1263899803,41.3673248291],"type":"Point"}
}