{
  "type": "Feature",
  "properties": {
    "iso:country":"ES",
    "sg:address":"Avgd Cami Real (del), S/n",
    "sg:city":"Castello Rugat",
    "sg:orig_category":"Estaciones De Servicio",
    "sg:phone":"+34 962 81 40 56",
    "sg:postcode":"46841",
    "sg:province":"Valencia",
    "wof:name":"Estacion De Servicio Benicadell S.l.",
    "wof:placetype":"venue"
},
  "geometry": {"coordinates":[-0.3831990063,38.8734703064],"type":"Point"}
}