{
  "type": "Feature",
  "properties": {
    "iso:country":"ES",
    "sg:address":"Pase General Davila, 304",
    "sg:city":"Santander",
    "sg:orig_category":"Empresas De Vigilancia, Guardia Y Protecci\u00d3n",
    "sg:phone":"+34 942 32 05 06",
    "sg:postcode":"39007",
    "sg:province":"Cantabria",
    "wof:name":"La Estela Cantabra De Seguridad S.l.",
    "wof:placetype":"venue"
},
  "geometry": {"coordinates":[-3.8277239799,43.462146759],"type":"Point"}
}