{
  "type": "Feature",
  "properties": {
    "addr:full":"Calle de Duque De La Victoria, S/n Huelva Huelva 21001",
    "addr:housenumber":"/ n",
    "addr:postcode":"21001",
    "addr:street":"Calle De Duque De La Victoria S",
    "iso:country":"ES",
    "sg:address":"Calle de Duque De La Victoria, S/n",
    "sg:city":"Huelva",
    "sg:orig_category":"Pescader\u00cdas (al Por Menor)",
    "sg:phone":"+34 959 25 80 45",
    "sg:postcode":"21001",
    "sg:province":"Huelva",
    "wof:name":"Noguera Garrochena Jose Maria",
    "wof:placetype":"venue"
},
  "geometry": {"coordinates":[-6.954419136,37.2557296753],"type":"Point"}
}