{
  "type": "Feature",
  "properties": {
    "addr:full":"Avda Lisboa, 1 Alcorcon Madrid 28924",
    "addr:housenumber":"1",
    "addr:postcode":"28924",
    "addr:street":"Avda Lisboa",
    "iso:country":"ES",
    "sg:address":"Avda Lisboa, 1",
    "sg:city":"Alcorcon",
    "sg:orig_category":"Asociaciones Y Clubs Deportivos",
    "sg:phone":"+34 916 10 90 38",
    "sg:postcode":"28924",
    "sg:province":"Madrid",
    "wof:name":"Asociacion De Propietarios Del Parque De Lisboa",
    "wof:placetype":"venue"
},
  "geometry": {"coordinates":[-3.8187534809,40.3541221619],"type":"Point"}
}