{
  "type": "Feature",
  "properties": {
    "addr:full":"Calle de San Roque, 91 Villaverde Abadia Le\u00f3n 24390",
    "addr:housenumber":"91",
    "addr:postcode":"24390",
    "addr:street":"Calle De San Roque",
    "iso:country":"ES",
    "sg:address":"Calle de San Roque, 91",
    "sg:city":"Villaverde Abadia",
    "sg:orig_category":"Supermercados Y Hipermercados",
    "sg:phone":"+34 987 54 44 64",
    "sg:postcode":"24390",
    "sg:province":"Le\u00f3n",
    "wof:name":"Vidal Asenjo Carlos",
    "wof:placetype":"venue"
},
  "geometry": {"coordinates":[-6.6797690392,42.5274391174],"type":"Point"}
}