{
  "type": "Feature",
  "properties": {
    "addr:full":"Calle de Antonio Hernandez, 6 Mostoles Madrid 28931",
    "addr:housenumber":"6",
    "addr:postcode":"28931",
    "addr:street":"Calle De Antonio Hernandez",
    "iso:country":"ES",
    "sg:address":"Calle de Antonio Hernandez, 6",
    "sg:city":"Mostoles",
    "sg:orig_category":"Asesor\u00cda Sobre Comunicaci\u00d3n De Empresas",
    "sg:phone":"+34 916 64 61 00",
    "sg:postcode":"28931",
    "sg:province":"Madrid",
    "wof:name":"United Services Spain Back Office S.l.",
    "wof:placetype":"venue"
},
  "geometry": {"coordinates":[-3.8645820618,40.3228111267],"type":"Point"}
}