{
  "type": "Feature",
  "properties": {
    "addr:full":"Calle de Canal, 18 Sevilla Sevilla 41006",
    "addr:housenumber":"18",
    "addr:postcode":"41006",
    "addr:street":"Calle De Canal",
    "iso:country":"ES",
    "sg:address":"Calle de Canal, 18",
    "sg:city":"Sevilla",
    "sg:orig_category":"Agentes, Concesionarios Y Sucursales De Veh\u00cdculos",
    "sg:phone":"+34 954 63 36 66",
    "sg:postcode":"41006",
    "sg:province":"Sevilla",
    "wof:name":"Automoviles Guevara S.l.",
    "wof:placetype":"venue"
},
  "geometry": {"coordinates":[-5.963329792,37.3741569519],"type":"Point"}
}