{
  "type": "Feature",
  "properties": {
    "addr:full":"Avda Leopoldo Werner, 1 Fuengirola M\u00e1laga 29640",
    "addr:housenumber":"1",
    "addr:postcode":"29640",
    "addr:street":"Avda Leopoldo Werner;Ma\u0301Laga",
    "iso:country":"ES",
    "sg:address":"Avda Leopoldo Werner, 1",
    "sg:city":"Fuengirola",
    "sg:orig_category":"Bisuter\u00cda, Joyer\u00cda, Relojer\u00cda (al Por Menor)",
    "sg:phone":"+34 952 19 85 69",
    "sg:postcode":"29640",
    "sg:province":"M\u00e1laga",
    "wof:name":"Amanji S.l.",
    "wof:placetype":"venue"
},
  "geometry": {"coordinates":[-4.6349420547,36.5269241333],"type":"Point"}
}