{
  "type": "Feature",
  "properties": {
    "addr:full":"Carrer de Jota, 144 Barcelona Barcelona 08016",
    "addr:housenumber":"144",
    "addr:postcode":"08016",
    "addr:street":"Carrer De Jota",
    "iso:country":"ES",
    "sg:address":"Carrer de Jota, 144",
    "sg:city":"Barcelona",
    "sg:orig_category":"Abogados",
    "sg:phone":"+34 933 40 40 86",
    "sg:postcode":"08016",
    "sg:province":"Barcelona",
    "wof:name":"Monje Moliner Maria Victoria",
    "wof:placetype":"venue"
},
  "geometry": {"coordinates":[2.1756739616,41.4297103882],"type":"Point"}
}