{
  "type": "Feature",
  "properties": {
    "addr:full":"Calle de Martos, 46 Linares Ja\u00e9n 23700",
    "addr:housenumber":"46",
    "addr:postcode":"23700",
    "addr:street":"Calle De Martos;Jae\u0301N",
    "iso:country":"ES",
    "sg:address":"Calle de Martos, 46",
    "sg:city":"Linares",
    "sg:orig_category":"Infograf\u00cda",
    "sg:phone":"+34 953 60 13 66",
    "sg:postcode":"23700",
    "sg:province":"Ja\u00e9n",
    "sg:website":"www.modulo3d.com",
    "wof:name":"Del Olmo Ruiz Valentin",
    "wof:placetype":"venue"
},
  "geometry": {"coordinates":[-3.6221489906,38.0846481323],"type":"Point"}
}