{
  "type": "Feature",
  "properties": {
    "iso:country":"ES",
    "sg:address":"Rua Tomas Paredes, 108",
    "sg:city":"Vigo",
    "sg:orig_category":"Electrodom\u00c9sticos (al Por Menor)",
    "sg:phone":"+34 986 24 13 48",
    "sg:postcode":"36208",
    "sg:province":"Pontevedra",
    "wof:name":"Maybel Vigo S. L.",
    "wof:placetype":"venue"
},
  "geometry": {"coordinates":[-8.7543840408,42.2180747986],"type":"Point"}
}