{
  "type": "Feature",
  "properties": {
    "addr:full":"Calle de Guenia, 4 Arrecife Las Palmas 35500",
    "addr:housenumber":"4",
    "addr:postcode":"35500",
    "addr:street":"Calle De Guenia",
    "iso:country":"ES",
    "sg:address":"Calle de Guenia, 4",
    "sg:city":"Arrecife",
    "sg:orig_category":"Fabricaci\u00d3n De Instrumentos Y Accesorios Musicales",
    "sg:phone":"+34 928 80 80 49",
    "sg:postcode":"35500",
    "sg:province":"Las Palmas",
    "sg:website":"www.picholi.com",
    "wof:name":"Picholi S.l.",
    "wof:placetype":"venue"
},
  "geometry": {"coordinates":[-13.5576066971,28.959400177],"type":"Point"}
}