{
  "type": "Feature",
  "properties": {
    "iso:country":"ES",
    "sg:address":"Calle de Plata, 12",
    "sg:city":"Toledo",
    "sg:orig_category":"Ebanister\u00cda",
    "sg:phone":"+34 925 22 39 61",
    "sg:postcode":"45001",
    "sg:province":"Toledo",
    "wof:name":"Roncero Lopez Maria Inmaculada",
    "wof:placetype":"venue"
},
  "geometry": {"coordinates":[-4.0240850449,39.8590736389],"type":"Point"}
}