{
  "type": "Feature",
  "properties": {
    "addr:full":"Avda Filiberto Villalobos, 71 Salamanca Salamanca 37007",
    "addr:housenumber":"71",
    "addr:postcode":"37007",
    "addr:street":"Avda Filiberto Villalobos",
    "iso:country":"ES",
    "sg:address":"Avda Filiberto Villalobos, 71",
    "sg:city":"Salamanca",
    "sg:orig_category":"Alimentaci\u00d3n General (al Por Menor)",
    "sg:phone":"+34 923 25 21 00",
    "sg:postcode":"37007",
    "sg:province":"Salamanca",
    "wof:name":"Ingelmo Feltrero Agustina",
    "wof:placetype":"venue"
},
  "geometry": {"coordinates":[-5.674405098,40.9701385498],"type":"Point"}
}