{
  "type": "Feature",
  "properties": {
    "iso:country":"ES",
    "sg:address":"Calle de Timoteo Perez Rubio, S/n",
    "sg:city":"Madrid",
    "sg:orig_category":"Centros Empresariales",
    "sg:phone":"+34 917 86 60 70",
    "sg:postcode":"28018",
    "sg:province":"Madrid",
    "wof:name":"Patentes Talgo S.a.",
    "wof:placetype":"venue"
},
  "geometry": {"coordinates":[-3.6719338894,40.3880348206],"type":"Point"}
}