{
  "type": "Feature",
  "properties": {
    "iso:country":"ES",
    "sg:address":"Calle de Guzman El Bueno, 102",
    "sg:city":"Madrid",
    "sg:orig_category":"Agricultores, Agricultores",
    "sg:phone":"+34 915 54 22 87",
    "sg:postcode":"28003",
    "sg:province":"Madrid",
    "wof:name":"Ruiz Fernandez Jose",
    "wof:placetype":"venue"
},
  "geometry": {"coordinates":[-3.7124400139,40.4419441223],"type":"Point"}
}