{
  "type": "Feature",
  "properties": {
    "addr:full":"B (pol Talluntxe), 2 Noain Navarra 31110",
    "addr:housenumber":"2",
    "addr:postcode":"31110",
    "addr:street":"Talluntxe",
    "iso:country":"ES",
    "sg:address":"B (pol Talluntxe), 2",
    "sg:city":"Noain",
    "sg:orig_category":"Suministros Y Materiales Industriales",
    "sg:phone":"+34 948 31 63 84",
    "sg:postcode":"31110",
    "sg:province":"Navarra",
    "wof:name":"Comerwind S.l.",
    "wof:placetype":"venue"
},
  "geometry": {"coordinates":[-1.6433140039,42.7574806213],"type":"Point"}
}