{
  "type": "Feature",
  "properties": {
    "iso:country":"ES",
    "sg:address":"Calle de Fernandez De Los Rios, 53",
    "sg:city":"Madrid",
    "sg:orig_category":"Molduras, Junquillos, Listones Y Molduras Perforadas",
    "sg:phone":"+34 915 43 58 40",
    "sg:postcode":"28015",
    "sg:province":"Madrid",
    "wof:name":"Cariban S.l.",
    "wof:placetype":"venue"
},
  "geometry": {"coordinates":[-3.7117099762,40.4351158142],"type":"Point"}
}