{
  "type": "Feature",
  "properties": {
    "addr:full":"Calle de Kareaga, S/n San Vicente De Barakaldo Vizcaya 48903",
    "addr:housenumber":"s / n",
    "addr:postcode":"48903",
    "addr:street":"Calle De Kareaga",
    "iso:country":"ES",
    "sg:address":"Calle de Kareaga, S/n",
    "sg:city":"San Vicente De Barakaldo",
    "sg:orig_category":"Maquinaria Para Industrias Diversas",
    "sg:phone":"+34 944 99 62 19",
    "sg:postcode":"48903",
    "sg:province":"Vizcaya",
    "wof:name":"Talleres Galaferr S.a.",
    "wof:placetype":"venue"
},
  "geometry": {"coordinates":[-3.0026290417,43.2843818665],"type":"Point"}
}