{
  "type": "Feature",
  "properties": {
    "addr:full":"Carr Sant Antoni Maria Claret, 25 Ciutadella Menorca Islas Baleares 07760",
    "addr:housenumber":"25",
    "addr:postcode":"07760",
    "addr:street":"Carr Sant Antoni Maria Claret",
    "iso:country":"ES",
    "sg:address":"Carr Sant Antoni Maria Claret, 25",
    "sg:city":"Ciutadella Menorca",
    "sg:orig_category":"Veh\u00cdculos De Ocasi\u00d3n",
    "sg:phone":"+34 971 38 09 07",
    "sg:postcode":"07760",
    "sg:province":"Islas Baleares",
    "wof:name":"Ciutadella Motor S.l.",
    "wof:placetype":"venue"
},
  "geometry": {"coordinates":[3.8449718952,40.0028648376],"type":"Point"}
}