{
  "type": "Feature",
  "properties": {
    "addr:full":"Canarias Vecindario Las Palmas 35110",
    "addr:postcode":"35110",
    "addr:street":"Palmas",
    "iso:country":"ES",
    "sg:address":"Canarias",
    "sg:city":"Vecindario",
    "sg:orig_category":"Asesor\u00cda De Formaci\u00d3n Y Gesti\u00d3n De Personal",
    "sg:phone":"+34 928 79 03 75",
    "sg:postcode":"35110",
    "sg:province":"Las Palmas",
    "wof:name":"United Services Spain Back-office S.l.",
    "wof:placetype":"venue"
},
  "geometry": {"coordinates":[-15.4410295486,27.8380203247],"type":"Point"}
}