{
  "type": "Feature",
  "properties": {
    "addr:full":"Carrer de Teide, 15 Barcelona Barcelona 08031",
    "addr:housenumber":"15",
    "addr:postcode":"08031",
    "addr:street":"Carrer De Teide",
    "iso:country":"ES",
    "sg:address":"Carrer de Teide, 15",
    "sg:city":"Barcelona",
    "sg:orig_category":"Edici\u00d3n De Diarios, Revistas, Boletines",
    "sg:phone":"+34 934 29 32 72",
    "sg:postcode":"08031",
    "sg:province":"Barcelona",
    "sg:website":"www.cinja.es",
    "wof:name":"Cinja Centro De Informacion S.l.",
    "wof:placetype":"venue"
},
  "geometry": {"coordinates":[2.1686890125,41.4306488037],"type":"Point"}
}