{
  "type": "Feature",
  "properties": {
    "iso:country":"ES",
    "sg:address":"Av Sant Antoni Maria Claret, 5",
    "sg:city":"Martorell",
    "sg:orig_category":"Juegos Y Juguetes (al Por Menor)",
    "sg:phone":"+34 937 76 59 54",
    "sg:postcode":"08760",
    "sg:province":"Barcelona",
    "wof:name":"Linares Gamarra Maria",
    "wof:placetype":"venue"
},
  "geometry": {"coordinates":[1.9203271866,41.4762229919],"type":"Point"}
}