{
  "type": "Feature",
  "properties": {
    "iso:country":"ES",
    "sg:address":"Avda Marques De Sotelo, 4",
    "sg:city":"Valencia",
    "sg:orig_category":"Asesor\u00cda Fiscal Y Jur\u00cddica",
    "sg:phone":"+34 963 51 91 59",
    "sg:postcode":"46002",
    "sg:province":"Valencia",
    "wof:name":"Gomez Rodriguez Juan",
    "wof:placetype":"venue"
},
  "geometry": {"coordinates":[-0.3768939972,39.4690704346],"type":"Point"}
}