{
  "type": "Feature",
  "properties": {
    "iso:country":"ES",
    "sg:address":"Carrer de Doctor Ferran I Clua, 16",
    "sg:city":"Viladecans",
    "sg:orig_category":"Mec\u00c1nico Del Autom\u00d3vil",
    "sg:phone":"+34 936 37 16 36",
    "sg:postcode":"08840",
    "sg:province":"Barcelona",
    "wof:name":"Talleres Mecadiesel De Sant Boi S.l.",
    "wof:placetype":"venue"
},
  "geometry": {"coordinates":[2.0135300159,41.3121986389],"type":"Point"}
}