{
  "type": "Feature",
  "properties": {
    "iso:country":"ES",
    "sg:address":"Carrer de Pare Font, 28",
    "sg:city":"Terrassa",
    "sg:orig_category":"Estudios, Instalaci\u00d3n De Climatizaci\u00d3n",
    "sg:phone":"+34 937 83 29 30",
    "sg:postcode":"08223",
    "sg:province":"Barcelona",
    "wof:name":"Refrigeracion Y Aire Acondicionado Carreras S.l.",
    "wof:placetype":"venue"
},
  "geometry": {"coordinates":[2.014138937,41.5564231873],"type":"Point"}
}