{
  "type": "Feature",
  "properties": {
    "iso:country":"ES",
    "sg:address":"Carrer de Concili De Trento, 126",
    "sg:city":"Barcelona",
    "sg:orig_category":"Estancos",
    "sg:phone":"+34 933 07 66 34",
    "sg:postcode":"08020",
    "sg:province":"Barcelona",
    "wof:name":"Consol Campos Ana",
    "wof:placetype":"venue"
},
  "geometry": {"coordinates":[2.1970689297,41.4147796631],"type":"Point"}
}