{
  "type": "Feature",
  "properties": {
    "addr:full":"Plaz Santa Lucia, 16 Zamora Zamora 49002",
    "addr:housenumber":"16",
    "addr:postcode":"49002",
    "addr:street":"Santa Lucia",
    "iso:country":"ES",
    "sg:address":"Plaz Santa Lucia, 16",
    "sg:city":"Zamora",
    "sg:orig_category":"Fabricaci\u00d3n, Alquiler, Venta De Encofrados",
    "sg:phone":"+34 980 53 06 89",
    "sg:postcode":"49002",
    "sg:province":"Zamora",
    "wof:name":"Martin Sebastian Maximino",
    "wof:placetype":"venue"
},
  "geometry": {"coordinates":[-5.7473988533,41.501285553],"type":"Point"}
}