{
  "type": "Feature",
  "properties": {
    "addr:full":"Carrer de Coronel Sanfeliu, 8 Prat Llobregat Barcelona 08820",
    "addr:housenumber":"8",
    "addr:postcode":"08820",
    "addr:street":"Carrer De Coronel Sanfeliu;Llobregat",
    "iso:country":"ES",
    "sg:address":"Carrer de Coronel Sanfeliu, 8",
    "sg:city":"Prat Llobregat",
    "sg:orig_category":"Herboristas (al Por Menor)",
    "sg:phone":"+34 933 70 26 00",
    "sg:postcode":"08820",
    "sg:province":"Barcelona",
    "wof:name":"Lopez Bo Leonor Carmen",
    "wof:placetype":"venue"
},
  "geometry": {"coordinates":[2.0941801071,41.3254394531],"type":"Point"}
}