{
  "type": "Feature",
  "properties": {
    "addr:full":"Calle de Arsenal (el), S/n Dos Hermanas Sevilla 41700",
    "addr:postcode":"41700",
    "addr:street":"Calle De Arsenal El S / N Dos",
    "iso:country":"ES",
    "sg:address":"Calle de Arsenal (el), S/n",
    "sg:city":"Dos Hermanas",
    "sg:orig_category":"Guarder\u00cdas",
    "sg:phone":"+34 954 72 12 19",
    "sg:postcode":"41700",
    "sg:province":"Sevilla",
    "wof:name":"Junta De Andalucia",
    "wof:placetype":"venue"
},
  "geometry": {"coordinates":[-5.9233994484,37.2878570557],"type":"Point"}
}