{
  "type": "Feature",
  "properties": {
    "iso:country":"ES",
    "sg:address":"Avda Isabel De Moctezuma, 33",
    "sg:city":"Caceres",
    "sg:orig_category":"Pesca Y Caza: Art\u00cdculos (al Por Menor)",
    "sg:phone":"+34 927 26 01 18",
    "sg:postcode":"10005",
    "sg:province":"C\u00e1ceres",
    "wof:name":"Rentero Nu\u00f1ez Francisco Amador",
    "wof:placetype":"venue"
},
  "geometry": {"coordinates":[-6.379160881,39.4614181519],"type":"Point"}
}