{
  "type": "Feature",
  "properties": {
    "iso:country":"ES",
    "sg:address":"Avda Europa, 10",
    "sg:city":"Alcala Real",
    "sg:orig_category":"Comercio De Piezas De Recambio Y De Accesorios De Veh\u00cdculos, Veh\u00cdculos Industriales",
    "sg:phone":"+34 953 58 70 26",
    "sg:postcode":"23680",
    "sg:province":"Ja\u00e9n",
    "wof:name":"Perez Mudarra Jose Luis",
    "wof:placetype":"venue"
},
  "geometry": {"coordinates":[-3.9203228951,37.4590759277],"type":"Point"}
}