{
  "type": "Feature",
  "properties": {
    "addr:full":"Ctra Vergel, S/n Pego Alicante 03780",
    "addr:housenumber":"s / n",
    "addr:postcode":"03780",
    "addr:street":"Ctra Vergel",
    "iso:country":"ES",
    "sg:address":"Ctra Vergel, S/n",
    "sg:city":"Pego",
    "sg:orig_category":"Cooperativas Agr\u00cdcolas",
    "sg:phone":"+34 966 40 20 11",
    "sg:postcode":"03780",
    "sg:province":"Alicante",
    "wof:name":"Cooperativa Agricola De Pego Coop. V.",
    "wof:placetype":"venue"
},
  "geometry": {"coordinates":[-0.1150880009,38.8428840637],"type":"Point"}
}