{
  "type": "Feature",
  "properties": {
    "addr:full":"Calle de Merced, 6 Burgos Burgos 09002",
    "addr:housenumber":"6",
    "addr:postcode":"09002",
    "addr:street":"Calle De Merced",
    "iso:country":"ES",
    "sg:address":"Calle de Merced, 6",
    "sg:city":"Burgos",
    "sg:orig_category":"Abogados",
    "sg:phone":"+34 947 26 78 43",
    "sg:postcode":"09002",
    "sg:province":"Burgos",
    "wof:name":"Ruiz Gutierrez Bego\u00f1a",
    "wof:placetype":"venue"
},
  "geometry": {"coordinates":[-3.7033910751,42.3386459351],"type":"Point"}
}