{
  "type": "Feature",
  "properties": {
    "addr:full":"Urb Gran Habitat, 1 Arganda Madrid 28500",
    "addr:postcode":"28500",
    "addr:street":"Urb",
    "iso:country":"ES",
    "sg:address":"Urb Gran Habitat, 1",
    "sg:city":"Arganda",
    "sg:orig_category":"Bazares, Art\u00cdculos De Limpieza Y De Cocina (al Por Menor)",
    "sg:phone":"+34 918 70 27 48",
    "sg:postcode":"28500",
    "sg:province":"Madrid",
    "wof:name":"Limpiezas Medinaceli, S.l",
    "wof:placetype":"venue"
},
  "geometry": {"coordinates":[-3.4412820339,40.3043670654],"type":"Point"}
}