{
  "type": "Feature",
  "properties": {
    "iso:country":"ES",
    "sg:address":"Calle de Republica De Costa Rica, 1",
    "sg:city":"Campo Criptana",
    "sg:orig_category":"Papeler\u00cdas, Librer\u00cdas",
    "sg:phone":"+34 926 56 09 22",
    "sg:postcode":"13610",
    "sg:province":"Ciudad Real",
    "wof:name":"Casero Perez Santiago",
    "wof:placetype":"venue"
},
  "geometry": {"coordinates":[-3.1271319389,39.3969612122],"type":"Point"}
}