{
  "type": "Feature",
  "properties": {
    "addr:full":"Calle de German Perez Carrasco, 30 Madrid Madrid 28027",
    "addr:housenumber":"30",
    "addr:postcode":"madrid;28027",
    "addr:street":"Calle De German Perez Carrasco",
    "iso:country":"ES",
    "sg:address":"Calle de German Perez Carrasco, 30",
    "sg:city":"Madrid",
    "sg:orig_category":"Alimentaci\u00d3n General (al Por Menor)",
    "sg:phone":"+34 913 67 09 66",
    "sg:postcode":"28027",
    "sg:province":"Madrid",
    "wof:name":"Pascual Ruiz Ines",
    "wof:placetype":"venue"
},
  "geometry": {"coordinates":[-3.6451480389,40.4352989197],"type":"Point"}
}