{
  "type": "Feature",
  "properties": {
    "iso:country":"ES",
    "sg:address":"Calle de Quemados, 12",
    "sg:city":"Llerena",
    "sg:orig_category":"Artesan\u00cda",
    "sg:phone":"+34 924 87 12 28",
    "sg:postcode":"06900",
    "sg:province":"Badajoz",
    "wof:name":"Rodriguez Franco Carlos",
    "wof:placetype":"venue"
},
  "geometry": {"coordinates":[-6.0204200745,38.2355575562],"type":"Point"}
}