{
  "type": "Feature",
  "properties": {
    "addr:full":"Plaz Espa\u00d1a, 9 Mayorga Valladolid 47680",
    "addr:housenumber":"9",
    "addr:postcode":"47680",
    "addr:street":"Plaz Espan\u0303A",
    "iso:country":"ES",
    "sg:address":"Plaz Espa\u00d1a, 9",
    "sg:city":"Mayorga",
    "sg:orig_category":"Librer\u00cdas",
    "sg:phone":"+34 983 75 16 69",
    "sg:postcode":"47680",
    "sg:province":"Valladolid",
    "wof:name":"Polo Barrera Angela",
    "wof:placetype":"venue"
},
  "geometry": {"coordinates":[-5.2633781433,42.1666755676],"type":"Point"}
}