{
  "type": "Feature",
  "properties": {
    "iso:country":"ES",
    "sg:address":"Calle de Cristo De La Victoria, 116",
    "sg:city":"Madrid",
    "sg:orig_category":"Carnicer\u00cdas, Carnicer\u00cdas",
    "sg:phone":"+34 915 00 58 91",
    "sg:postcode":"28026",
    "sg:province":"Madrid",
    "wof:name":"Prado Chaparro Ruben",
    "wof:placetype":"venue"
},
  "geometry": {"coordinates":[-3.7055335045,40.3792686462],"type":"Point"}
}