{
  "type": "Feature",
  "properties": {
    "iso:country":"ES",
    "sg:address":"Avda Zaragoza, S/n",
    "sg:city":"Almunia De Do\u00e7a Godina",
    "sg:orig_category":"Mantenimiento Industrial",
    "sg:phone":"+34 976 81 19 31",
    "sg:postcode":"50100",
    "sg:province":"Zaragoza",
    "wof:name":"Mantenimientos Ayuda A La Explotacion Y Servicios S.a.",
    "wof:placetype":"venue"
},
  "geometry": {"coordinates":[-1.3714590073,41.4828186035],"type":"Point"}
}