{
  "type": "Feature",
  "properties": {
    "addr:full":"Calle de San Modesto, 14 Madrid Madrid 28034",
    "addr:housenumber":"14",
    "addr:postcode":"madrid;28034",
    "addr:street":"Calle De San Modesto",
    "iso:country":"ES",
    "sg:address":"Calle de San Modesto, 14",
    "sg:city":"Madrid",
    "sg:orig_category":"Centros Empresariales",
    "sg:phone":"+34 913 58 45 14",
    "sg:postcode":"28034",
    "sg:province":"Madrid",
    "wof:name":"Aguilar Garmarra Rosario",
    "wof:placetype":"venue"
},
  "geometry": {"coordinates":[-3.6879954338,40.4836578369],"type":"Point"}
}