{
  "type": "Feature",
  "properties": {
    "addr:full":"Avda Instituto (del), 67 Arganda Madrid 28500",
    "addr:housenumber":"67",
    "addr:postcode":"28500",
    "addr:street":"Avda Instituto Del",
    "iso:country":"ES",
    "sg:address":"Avda Instituto (del), 67",
    "sg:city":"Arganda",
    "sg:orig_category":"Electrodom\u00c9sticos (fabricaci\u00d3n, Al Por Mayor)",
    "sg:phone":"+34 918 70 20 56",
    "sg:postcode":"28500",
    "sg:province":"Madrid",
    "wof:name":"Lo Mejor De Tus Sue\u00f1os S.l",
    "wof:placetype":"venue"
},
  "geometry": {"coordinates":[-3.4418549538,40.2945594788],"type":"Point"}
}