{
  "type": "Feature",
  "properties": {
    "addr:full":"Avda Mancomunidad, 8 Arrecife Las Palmas 35500",
    "addr:housenumber":"8",
    "addr:postcode":"35500",
    "addr:street":"Avda Mancomunidad",
    "iso:country":"ES",
    "sg:address":"Avda Mancomunidad, 8",
    "sg:city":"Arrecife",
    "sg:orig_category":"Museos",
    "sg:phone":"+34 928 80 25 49",
    "sg:postcode":"35500",
    "sg:province":"Las Palmas",
    "wof:name":"Museo Etnografico Tanit",
    "wof:placetype":"venue"
},
  "geometry": {"coordinates":[-13.5554971695,28.9581813812],"type":"Point"}
}