{
  "type": "Feature",
  "properties": {
    "addr:full":"Carrer de Illes Balears, 45 Galatzo Islas Baleares 07180",
    "addr:housenumber":"45",
    "addr:postcode":"07180",
    "addr:street":"Carrer De Illes Balears;Islas",
    "iso:country":"ES",
    "sg:address":"Carrer de Illes Balears, 45",
    "sg:city":"Galatzo",
    "sg:orig_category":"Muebles, Minoristas",
    "sg:phone":"+34 971 69 10 86",
    "sg:postcode":"07180",
    "sg:province":"Islas Baleares",
    "wof:name":"Tornero Don Sofa S.l.",
    "wof:placetype":"venue"
},
  "geometry": {"coordinates":[2.4919030666,39.519241333],"type":"Point"}
}