{
  "type": "Feature",
  "properties": {
    "addr:full":"La Fragua, S/n Campo Caso Asturias 33990",
    "addr:housenumber":"s / n",
    "addr:postcode":"33990",
    "iso:country":"ES",
    "sg:address":"La Fragua, S/n",
    "sg:city":"Campo Caso",
    "sg:orig_category":"Iglesia Cat\u00d3lica",
    "sg:phone":"+34 985 60 80 04",
    "sg:postcode":"33990",
    "sg:province":"Asturias",
    "wof:name":"Diocesis De Oviedo",
    "wof:placetype":"venue"
},
  "geometry": {"coordinates":[-5.3443040848,43.1825866699],"type":"Point"}
}