{
  "type": "Feature",
  "properties": {
    "iso:country":"ES",
    "sg:address":"G.v. Ramon Y Cajal, 40",
    "sg:city":"Valencia",
    "sg:orig_category":"Cine: Pel\u00cdculas Educativas, Industriales Y Publicitarias (producci\u00d3n)",
    "sg:phone":"+34 963 51 96 25",
    "sg:postcode":"46007",
    "sg:province":"Valencia",
    "wof:name":"Altimiras El Plantio S.l",
    "wof:placetype":"venue"
},
  "geometry": {"coordinates":[-0.3814044893,39.4655380249],"type":"Point"}
}