{
  "type": "Feature",
  "properties": {
    "addr:full":"Carrer de Montserrat Roig I Fransi, 10 Argentona Barcelona 08310",
    "addr:housenumber":"10",
    "addr:postcode":"08310",
    "addr:street":"Carrer De Montserrat Roig I Fransi",
    "iso:country":"ES",
    "sg:address":"Carrer de Montserrat Roig I Fransi, 10",
    "sg:city":"Argentona",
    "sg:orig_category":"Marroquiner\u00cda (confecci\u00d3n)",
    "sg:phone":"+34 937 56 00 08",
    "sg:postcode":"08310",
    "sg:province":"Barcelona",
    "wof:name":"Cuir Pell S.c.p.",
    "wof:placetype":"venue"
},
  "geometry": {"coordinates":[2.4042260647,41.5570259094],"type":"Point"}
}