{
  "type": "Feature",
  "properties": {
    "iso:country":"ES",
    "sg:address":"Calle de Mayor, 58",
    "sg:city":"Albacete",
    "sg:orig_category":"Sindicatos De Trabajadores",
    "sg:phone":"+34 967 52 22 07",
    "sg:postcode":"02002",
    "sg:province":"Albacete",
    "wof:name":"Mca-ugt",
    "wof:placetype":"venue"
},
  "geometry": {"coordinates":[-1.852692008,38.9926452637],"type":"Point"}
}