{
  "type": "Feature",
  "properties": {
    "addr:full":"Avda Fuente (de La), S/n Aguaviva Teruel 44566",
    "addr:postcode":"44566",
    "addr:street":"Avda Fuente De La S / N",
    "iso:country":"ES",
    "sg:address":"Avda Fuente (de La), S/n",
    "sg:city":"Aguaviva",
    "sg:orig_category":"Comisarios",
    "sg:phone":"+34 978 84 82 55",
    "sg:postcode":"44566",
    "sg:province":"Teruel",
    "wof:name":"Altabella Martin Enrique",
    "wof:placetype":"venue"
},
  "geometry": {"coordinates":[-0.1959131062,40.8234214783],"type":"Point"}
}