{
  "type": "Feature",
  "properties": {
    "addr:full":"Carrer de Dega Bahi, 12 Barcelona Barcelona 08026",
    "addr:housenumber":"12",
    "addr:postcode":"08026",
    "addr:street":"Carrer De Dega Bahi",
    "iso:country":"ES",
    "sg:address":"Carrer de Dega Bahi, 12",
    "sg:city":"Barcelona",
    "sg:orig_category":"Ciencias Ocultas",
    "sg:phone":"+34 934 55 14 47",
    "sg:postcode":"08026",
    "sg:province":"Barcelona",
    "sg:website":"www.paginasamarillas.es",
    "wof:name":"Rajkowska  Maria Dorota",
    "wof:placetype":"venue"
},
  "geometry": {"coordinates":[2.1833889484,41.4108161926],"type":"Point"}
}