{
  "type": "Feature",
  "properties": {
    "addr:full":"Calle de Conde De Haro, 15 Haro La Rioja 26200",
    "addr:housenumber":"15",
    "addr:postcode":"26200",
    "addr:street":"Calle De Conde De Haro",
    "iso:country":"ES",
    "sg:address":"Calle de Conde De Haro, 15",
    "sg:city":"Haro",
    "sg:orig_category":"Fabricaci\u00d3n De Sobres, Bolsas Y Fundas",
    "sg:phone":"+34 941 30 38 71",
    "sg:postcode":"26200",
    "sg:province":"La Rioja",
    "wof:name":"Delgado Lapeira Maximo",
    "wof:placetype":"venue"
},
  "geometry": {"coordinates":[-2.8486099243,42.5764732361],"type":"Point"}
}