{
  "type": "Feature",
  "properties": {
    "addr:full":"Avda Perla, 5 Madrid Madrid 28041",
    "addr:housenumber":"5",
    "addr:postcode":"28041",
    "addr:street":"Avda Perla",
    "iso:country":"ES",
    "sg:address":"Avda Perla, 5",
    "sg:city":"Madrid",
    "sg:orig_category":"Abogados",
    "sg:phone":"+34 914 76 58 08",
    "sg:postcode":"28041",
    "sg:province":"Madrid",
    "wof:name":"Lopez-diaz Abogados S.l",
    "wof:placetype":"venue"
},
  "geometry": {"coordinates":[-3.6943490505,40.373134613],"type":"Point"}
}