{
  "type": "Feature",
  "properties": {
    "iso:country":"ES",
    "sg:address":"Pase Castellana, 105",
    "sg:city":"Madrid",
    "sg:orig_category":"Asesor\u00cda Fiscal Y Jur\u00cddica",
    "sg:phone":"+34 915 97 48 36",
    "sg:postcode":"28046",
    "sg:province":"Madrid",
    "wof:name":"Asesores Contenciosos S.a.l.",
    "wof:placetype":"venue"
},
  "geometry": {"coordinates":[-3.6909213066,40.4543800354],"type":"Point"}
}