{
  "type": "Feature",
  "properties": {
    "addr:full":"Av Mossen Ramon Muntanyola, 6 Reus Tarragona 43205",
    "addr:housenumber":"6",
    "addr:postcode":"43205",
    "addr:street":"Av Mossen Ramon Muntanyola",
    "iso:country":"ES",
    "sg:address":"Av Mossen Ramon Muntanyola, 6",
    "sg:city":"Reus",
    "sg:orig_category":"Reparaciones Y Remolcado De Veh\u00cdculos",
    "sg:phone":"+34 977 77 19 46",
    "sg:postcode":"43205",
    "sg:province":"Tarragona",
    "wof:name":"Grues Gam Sl",
    "wof:placetype":"venue"
},
  "geometry": {"coordinates":[1.1197048426,41.1392059326],"type":"Point"}
}