{
  "type": "Feature",
  "properties": {
    "addr:full":"Avda Burguillos, 28 Guillena Sevilla 41210",
    "addr:housenumber":"28",
    "addr:postcode":"41210",
    "addr:street":"Avda Burguillos",
    "iso:country":"ES",
    "sg:address":"Avda Burguillos, 28",
    "sg:city":"Guillena",
    "sg:orig_category":"Fabricaci\u00d3n De Juguetes Autom\u00c1ticos",
    "sg:phone":"+34 955 78 50 90",
    "sg:postcode":"41210",
    "sg:province":"Sevilla",
    "wof:name":"Martinez Dragados Dolores",
    "wof:placetype":"venue"
},
  "geometry": {"coordinates":[-6.0559902191,37.5456504822],"type":"Point"}
}