{
  "type": "Feature",
  "properties": {
    "addr:full":"Carr Maestra Ines Mir, 15 Burjassot Valencia 46100",
    "addr:housenumber":"15",
    "addr:postcode":"46100",
    "addr:street":"Carr Maestra Ines Mir",
    "iso:country":"ES",
    "sg:address":"Carr Maestra Ines Mir, 15",
    "sg:city":"Burjassot",
    "sg:orig_category":"Mec\u00c1nico Del Autom\u00d3vil",
    "sg:phone":"+34 963 63 72 62",
    "sg:postcode":"46100",
    "sg:province":"Valencia",
    "wof:name":"Talleres Jorge Juan C.b.",
    "wof:placetype":"venue"
},
  "geometry": {"coordinates":[-0.4138289988,39.5145187378],"type":"Point"}
}