{
  "type": "Feature",
  "properties": {
    "addr:full":"Mayor, 6 Badajoz Badajoz 06001",
    "addr:housenumber":"6",
    "addr:postcode":"06001",
    "addr:street":"Mayor",
    "iso:country":"ES",
    "sg:address":"Mayor, 6",
    "sg:city":"Badajoz",
    "sg:orig_category":"Loter\u00cda Y T\u00d3mbola",
    "sg:phone":"+34 924 22 03 63",
    "sg:postcode":"06001",
    "sg:province":"Badajoz",
    "wof:name":"Martinez De Llera Concepcion",
    "wof:placetype":"venue"
},
  "geometry": {"coordinates":[-6.7410387993,38.9527511597],"type":"Point"}
}