{
  "type": "Feature",
  "properties": {
    "addr:full":"A (pol Talluntxe), 32 Noain Navarra 31110",
    "addr:housenumber":"32",
    "addr:postcode":"31110",
    "addr:street":"Talluntxe",
    "iso:country":"ES",
    "sg:address":"A (pol Talluntxe), 32",
    "sg:city":"Noain",
    "sg:orig_category":"Muebles, Minoristas",
    "sg:phone":"+34 948 31 23 30",
    "sg:postcode":"31110",
    "sg:province":"Navarra",
    "wof:name":"Madera Viva Exclusivas De Mueble S.l.",
    "wof:placetype":"venue"
},
  "geometry": {"coordinates":[-1.6253329515,42.7576789856],"type":"Point"}
}