{
  "type": "Feature",
  "properties": {
    "iso:country":"ES",
    "sg:address":"Carrer de Bisbe Cabanelles, 14",
    "sg:city":"Palma",
    "sg:orig_category":"Carnicer\u00cdas, Carnicer\u00cdas",
    "sg:phone":"+34 971 27 10 06",
    "sg:postcode":"07005",
    "sg:province":"Islas Baleares",
    "wof:name":"Dilme Per Francisco",
    "wof:placetype":"venue"
},
  "geometry": {"coordinates":[2.6648910046,39.5756797791],"type":"Point"}
}