{
  "type": "Feature",
  "properties": {
    "iso:country":"ES",
    "sg:address":"Calle de San Martin, 31",
    "sg:city":"Donostia-san Sebastian",
    "sg:orig_category":"\u00d3ptica: Instrumentos (fabricaci\u00d3n)",
    "sg:phone":"+34 943 43 14 99",
    "sg:postcode":"20005",
    "sg:province":"Guip\u00f9zcoa",
    "wof:name":"San Sebastian Uranga Jose Maria",
    "wof:placetype":"venue"
},
  "geometry": {"coordinates":[-1.9833860397,43.316734314],"type":"Point"}
}