{
  "type": "Feature",
  "properties": {
    "iso:country":"ES",
    "sg:address":"Calle de Principal, 1",
    "sg:city":"Boiro",
    "sg:orig_category":"Importaci\u00d3n",
    "sg:phone":"+34 981 84 27 11",
    "sg:postcode":"15930",
    "sg:province":"La Coru\u00f1a",
    "wof:name":"Barbanza Import S.l.",
    "wof:placetype":"venue"
},
  "geometry": {"coordinates":[-8.8802194595,42.649471283],"type":"Point"}
}