{
  "type": "Feature",
  "properties": {
    "addr:full":"Carr Lluis Companys, 1 Lleida Lleida 25003",
    "addr:housenumber":"1",
    "addr:postcode":"25003",
    "addr:street":"Carr Lluis Companys",
    "iso:country":"ES",
    "sg:address":"Carr Lluis Companys, 1",
    "sg:city":"Lleida",
    "sg:orig_category":"Asociaciones Humanitarias, De Cooperaci\u00d3n, De Acci\u00d3n Social",
    "sg:phone":"+34 973 26 25 08",
    "sg:postcode":"25003",
    "sg:province":"Lleida",
    "wof:name":"Fundacion Privada Libra",
    "wof:placetype":"venue"
},
  "geometry": {"coordinates":[0.6160899997,41.611831665],"type":"Point"}
}