{
  "type": "Feature",
  "properties": {
    "addr:full":"Turmalina, 27 Pulianas Granada 18197",
    "addr:housenumber":"27",
    "addr:postcode":"18197",
    "addr:street":"Turmalina",
    "iso:country":"ES",
    "sg:address":"Turmalina, 27",
    "sg:city":"Pulianas",
    "sg:orig_category":"Agencias Y Agentes Comerciales, Representantes",
    "sg:phone":"+34 958 40 12 56",
    "sg:postcode":"18197",
    "sg:province":"Granada",
    "wof:name":"Martin Cuesta Francisco",
    "wof:placetype":"venue"
},
  "geometry": {"coordinates":[-3.6197390556,37.2280387878],"type":"Point"}
}