{
  "type": "Feature",
  "properties": {
    "addr:full":"Carr Luis Vives, 3 Alcudia Valencia 46250",
    "addr:housenumber":"3",
    "addr:postcode":"46250",
    "addr:street":"Carr Luis Vives",
    "iso:country":"ES",
    "sg:address":"Carr Luis Vives, 3",
    "sg:city":"Alcudia",
    "sg:orig_category":"Peluquer\u00cdas, Peluquer\u00cda Mixta",
    "sg:phone":"+34 962 99 74 77",
    "sg:postcode":"46250",
    "sg:province":"Valencia",
    "wof:name":"Ba\u00f1on Pastor Claudina",
    "wof:placetype":"venue"
},
  "geometry": {"coordinates":[-0.5070289969,39.1940689087],"type":"Point"}
}