{
  "type": "Feature",
  "properties": {
    "iso:country":"ES",
    "sg:address":"Calle de Lapurdi, 7",
    "sg:city":"Galdakao",
    "sg:orig_category":"Agencias Y Agentes Comerciales, Representantes",
    "sg:phone":"+34 944 57 01 95",
    "sg:postcode":"48960",
    "sg:province":"Vizcaya",
    "wof:name":"Carlos Puyuelo Garcia",
    "wof:placetype":"venue"
},
  "geometry": {"coordinates":[-2.8458499908,43.229763031],"type":"Point"}
}