{
  "type": "Feature",
  "properties": {
    "addr:full":"Calle de Jorge Juan, 11 Alacant Alicante 03002",
    "addr:housenumber":"11",
    "addr:postcode":"03002",
    "addr:street":"Calle De Jorge Juan",
    "iso:country":"ES",
    "sg:address":"Calle de Jorge Juan, 11",
    "sg:city":"Alacant",
    "sg:orig_category":"Relojer\u00cda (al Por Menor, Reparaci\u00d3n)",
    "sg:phone":"+34 965 20 30 38",
    "sg:postcode":"03002",
    "sg:province":"Alicante",
    "wof:name":"Cardell Navarro S.l.",
    "wof:placetype":"venue"
},
  "geometry": {"coordinates":[-0.4806349874,38.345489502],"type":"Point"}
}