{
  "type": "Feature",
  "properties": {
    "addr:full":"Calle de Gamazo, 19 Sevilla Sevilla 41001",
    "addr:housenumber":"19",
    "addr:postcode":"41001",
    "addr:street":"Calle De Gamazo",
    "iso:country":"ES",
    "sg:address":"Calle de Gamazo, 19",
    "sg:city":"Sevilla",
    "sg:orig_category":"Abogados",
    "sg:phone":"+34 954 21 54 14",
    "sg:postcode":"41001",
    "sg:province":"Sevilla",
    "wof:name":"Selva Sanchez Luis Manuel",
    "wof:placetype":"venue"
},
  "geometry": {"coordinates":[-5.9963588715,37.3867111206],"type":"Point"}
}