{
  "type": "Feature",
  "properties": {
    "addr:full":"Carrer de Jaume I, 7 Sabadell Barcelona 08206",
    "addr:housenumber":"7",
    "addr:postcode":"08206",
    "addr:street":"Carrer De Jaume I",
    "iso:country":"ES",
    "sg:address":"Carrer de Jaume I, 7",
    "sg:city":"Sabadell",
    "sg:orig_category":"Cajas De Ahorro",
    "sg:phone":"+34 937 17 72 00",
    "sg:postcode":"08206",
    "sg:province":"Barcelona",
    "sg:website":"www.caixasabadell.es",
    "wof:name":"Caixa D'estalvis Sabadell",
    "wof:placetype":"venue"
},
  "geometry": {"coordinates":[2.0952401161,41.5578804016],"type":"Point"}
}