{
  "type": "Feature",
  "properties": {
    "addr:full":"Carretera De Alagon-tudela, S/n Pradilla Ebro Zaragoza 50668",
    "addr:housenumber":"s / n",
    "addr:postcode":"50668",
    "addr:street":"Carretera De Alagon-Tudela",
    "iso:country":"ES",
    "sg:address":"Carretera De Alagon-tudela, S/n",
    "sg:city":"Pradilla Ebro",
    "sg:orig_category":"Cr\u00cda De Animales",
    "sg:phone":"+34 976 86 02 07",
    "sg:postcode":"50668",
    "sg:province":"Zaragoza",
    "wof:name":"Argapor S.a.",
    "wof:placetype":"venue"
},
  "geometry": {"coordinates":[-0.5906996131,41.508769989],"type":"Point"}
}