{
  "type": "Feature",
  "properties": {
    "iso:country":"ES",
    "sg:address":"Av Barcelona (de), 18",
    "sg:city":"Tortosa",
    "sg:orig_category":"Cerrajer\u00cda, Ferrallista",
    "sg:phone":"+34 977 44 49 97",
    "sg:postcode":"43500",
    "sg:province":"Tarragona",
    "wof:name":"Cortijo Martinez Francisco",
    "wof:placetype":"venue"
},
  "geometry": {"coordinates":[0.5237820148,40.8031578064],"type":"Point"}
}