{
  "type": "Feature",
  "properties": {
    "iso:country":"ES",
    "sg:address":"Avda Mediterraneo, 26",
    "sg:city":"Salobre\u00f1a",
    "sg:orig_category":"Droguer\u00cdas (al Por Menor)",
    "sg:phone":"+34 958 61 15 84",
    "sg:postcode":"18680",
    "sg:province":"Granada",
    "wof:name":"Rabema S.l.",
    "wof:placetype":"venue"
},
  "geometry": {"coordinates":[-3.5842719078,36.7406539917],"type":"Point"}
}