{
  "type": "Feature",
  "properties": {
    "addr:full":"Luga Taramay, S/n Velilla-taramay Granada 18690",
    "addr:housenumber":"s",
    "addr:postcode":"18690",
    "addr:street":"/ N Velilla-Taramay",
    "iso:country":"ES",
    "sg:address":"Luga Taramay, S/n",
    "sg:city":"Velilla-taramay",
    "sg:orig_category":"Promotores Constructores",
    "sg:phone":"+34 958 63 94 77",
    "sg:postcode":"18690",
    "sg:province":"Granada",
    "wof:name":"Promociones Malvisa S.l",
    "wof:placetype":"venue"
},
  "geometry": {"coordinates":[-3.6882688999,36.736743927],"type":"Point"}
}