{
  "type": "Feature",
  "properties": {
    "addr:full":"Rigoberta Mench\u00fa, 6 Cuellar Segovia 40200",
    "addr:housenumber":"6",
    "addr:postcode":"40200",
    "addr:street":"Menchu\u0301",
    "iso:country":"ES",
    "sg:address":"Rigoberta Mench\u00fa, 6",
    "sg:city":"Cuellar",
    "sg:orig_category":"Art\u00cdculos De Madera (fabricaci\u00d3n Y Al Por Mayor)",
    "sg:phone":"+34 921 14 02 23",
    "sg:postcode":"40200",
    "sg:province":"Segovia",
    "wof:name":"Proyectos Y Promociones Del Norte S.l.",
    "wof:placetype":"venue"
},
  "geometry": {"coordinates":[-4.3071708679,41.3947257996],"type":"Point"}
}