{
  "type": "Feature",
  "properties": {
    "iso:country":"ES",
    "sg:address":"Calle de Ramon Y Cajal, 10",
    "sg:city":"Bobadilla",
    "sg:orig_category":"Hielo Artificial (fabricaci\u00d3n, Distribuci\u00d3n)",
    "sg:phone":"+34 953 57 91 78",
    "sg:postcode":"23669",
    "sg:province":"Ja\u00e9n",
    "wof:name":"Rufriomar S.l.",
    "wof:placetype":"venue"
},
  "geometry": {"coordinates":[-4.1063580513,37.6615447998],"type":"Point"}
}