{
  "type": "Feature",
  "properties": {
    "iso:country":"ES",
    "sg:address":"Plaz Colon (de), 13",
    "sg:city":"San Mateo",
    "sg:orig_category":"Impuestos, Tesoro P\u00dablico",
    "sg:phone":"+34 968 44 28 42",
    "sg:postcode":"30800",
    "sg:province":"Murcia",
    "wof:name":"Vatpe S.a.",
    "wof:placetype":"venue"
},
  "geometry": {"coordinates":[-1.6905640364,37.680557251],"type":"Point"}
}