{
  "type": "Feature",
  "properties": {
    "iso:country":"ES",
    "sg:address":"Carrer de Congres, 71",
    "sg:city":"Barcelona",
    "sg:orig_category":"Maquinaria Y Herramientas Para Madera, Pvc, Aluminio Y Aperos (fabricaci\u00d3n, Comercio)",
    "sg:phone":"+34 934 27 74 61",
    "sg:postcode":"08031",
    "sg:province":"Barcelona",
    "wof:name":"Vicens Espias Jose",
    "wof:placetype":"venue"
},
  "geometry": {"coordinates":[2.1606769562,41.4369888306],"type":"Point"}
}