{
  "type": "Feature",
  "properties": {
    "addr:full":"Calle de Serval, 22 Huescar Granada 18830",
    "addr:housenumber":"22",
    "addr:postcode":"18830",
    "addr:street":"Calle De Serval",
    "iso:country":"ES",
    "sg:address":"Calle de Serval, 22",
    "sg:city":"Huescar",
    "sg:classifiers":[
        {
            "category":"Taxi",
            "type":"Transportation"
        }
    ],
    "sg:phone":"+34 958 74 12 60",
    "sg:postcode":"18830",
    "sg:province":"Granada",
    "wof:name":"Carrion Guerrero Pedro",
    "wof:placetype":"venue"
},
  "geometry": {"coordinates":[-2.5386459827,37.8120307922],"type":"Point"}
}