{
  "type": "Feature",
  "properties": {
    "iso:country":"ES",
    "sg:address":"Eix-ample, 52",
    "sg:city":"Albal",
    "sg:orig_category":"Peluqueros: De Se\u00d1oras",
    "sg:phone":"+34 961 26 32 56",
    "sg:postcode":"46470",
    "sg:province":"Valencia",
    "wof:name":"Puchades Zacares Maria Angeles",
    "wof:placetype":"venue"
},
  "geometry": {"coordinates":[-0.4167369902,39.3970680237],"type":"Point"}
}