{
  "type": "Feature",
  "properties": {
    "addr:full":"Calle de Costanilla, 7 Zamora Zamora 49004",
    "addr:housenumber":"7",
    "addr:postcode":"49004",
    "addr:street":"Calle De Costanilla",
    "iso:country":"ES",
    "sg:address":"Calle de Costanilla, 7",
    "sg:city":"Zamora",
    "sg:orig_category":"Bares, Piano",
    "sg:phone":"+34 980 53 52 69",
    "sg:postcode":"49004",
    "sg:province":"Zamora",
    "wof:name":"Alcino  Manuel",
    "wof:placetype":"venue"
},
  "geometry": {"coordinates":[-5.7478637695,41.5048828125],"type":"Point"}
}