{
  "type": "Feature",
  "properties": {
    "addr:full":"Calle de Princesa, 25 Madrid Madrid 28008",
    "addr:housenumber":"25",
    "addr:postcode":"madrid;28008",
    "addr:street":"Calle De Princesa",
    "iso:country":"ES",
    "sg:address":"Calle de Princesa, 25",
    "sg:city":"Madrid",
    "sg:orig_category":"Arquitectos",
    "sg:phone":"+34 915 48 29 18",
    "sg:postcode":"28008",
    "sg:province":"Madrid",
    "wof:name":"De Juan Alvarez Jesus",
    "wof:placetype":"venue"
},
  "geometry": {"coordinates":[-3.7141139507,40.4275054932],"type":"Point"}
}