{
  "type": "Feature",
  "properties": {
    "iso:country":"ES",
    "sg:address":"Calle de Francisco Villaespesa, 43",
    "sg:city":"Madrid",
    "sg:orig_category":"Fotocopias, Reprograf\u00cda",
    "sg:phone":"+34 913 68 10 23",
    "sg:postcode":"28017",
    "sg:province":"Madrid",
    "wof:name":"Reprografia Newiza S.l.",
    "wof:placetype":"venue"
},
  "geometry": {"coordinates":[-3.645772934,40.4294433594],"type":"Point"}
}