{
  "type": "Feature",
  "properties": {
    "iso:country":"ES",
    "sg:address":"Calle de Ferraz, 13",
    "sg:city":"Madrid",
    "sg:orig_category":"T\u00c9cnicos Veterinarios",
    "sg:phone":"+34 915 59 18 71",
    "sg:postcode":"28008",
    "sg:province":"Madrid",
    "wof:name":"Pomeda Frechilla Pedro Angel",
    "wof:placetype":"venue"
},
  "geometry": {"coordinates":[-3.7179141045,40.4265403748],"type":"Point"}
}