{
  "type": "Feature",
  "properties": {
    "addr:full":"Ctra Antigua Nacnal Iv, Km. 0556,0 Dos Hermanas Sevilla 41700",
    "addr:postcode":"41700",
    "addr:street":"Ctra Antigua Nacnal Iv Km. 0556,0;Sevilla",
    "iso:country":"ES",
    "sg:address":"Ctra Antigua Nacnal Iv, Km. 0556,0",
    "sg:city":"Dos Hermanas",
    "sg:orig_category":"Comercio De Hierro",
    "sg:phone":"+34 955 67 55 13",
    "sg:postcode":"41700",
    "sg:province":"Sevilla",
    "wof:name":"Hierros Isaga S.a.",
    "wof:placetype":"venue"
},
  "geometry": {"coordinates":[-5.9281339645,37.2829055786],"type":"Point"}
}