{
  "type": "Feature",
  "properties": {
    "iso:country":"ES",
    "sg:address":"Finca El Arquillo, S/n",
    "sg:city":"San Pedro Alcantara",
    "sg:orig_category":"Ense\u00d1anza Secundaria: Colegios Y Escuelas Privadas",
    "sg:phone":"+34 952 78 16 53",
    "sg:postcode":"29670",
    "sg:province":"M\u00e1laga",
    "wof:name":"Junta De Andalucia-instituto Ense\u00f1anza Secundaria Salduba",
    "wof:placetype":"venue"
},
  "geometry": {"coordinates":[-5.003718853,36.4735946655],"type":"Point"}
}