{
  "type": "Feature",
  "properties": {
    "addr:full":"Plaz Hermanos Lafuente Alcantara, 1 Archidona M\u00e1laga 29300",
    "addr:housenumber":"1",
    "addr:postcode":"29300",
    "addr:street":"Alcantara;Ma\u0301Laga",
    "iso:country":"ES",
    "sg:address":"Plaz Hermanos Lafuente Alcantara, 1",
    "sg:city":"Archidona",
    "sg:orig_category":"Notarios",
    "sg:phone":"+34 952 71 49 58",
    "sg:postcode":"29300",
    "sg:province":"M\u00e1laga",
    "wof:name":"Carmona Castejon Federico",
    "wof:placetype":"venue"
},
  "geometry": {"coordinates":[-4.3905439377,37.0972251892],"type":"Point"}
}