{
  "type": "Feature",
  "properties": {
    "iso:country":"ES",
    "sg:address":"Partida L'almaina, 91",
    "sg:city":"Mutxamel",
    "sg:orig_category":"Industrias Aeron\u00c1uticas Y Espaciales",
    "sg:phone":"+34 965 96 02 58",
    "sg:postcode":"03110",
    "sg:province":"Alicante",
    "wof:name":"Maketair Aviacion S.l.",
    "wof:placetype":"venue"
},
  "geometry": {"coordinates":[-0.4637640119,38.3968734741],"type":"Point"}
}