{
  "type": "Feature",
  "properties": {
    "addr:full":"Calle de Santiago Aldaz, S/n Albelda Iregua La Rioja 26120",
    "addr:housenumber":"s / n",
    "addr:postcode":"26120",
    "addr:street":"Calle De Santiago Aldaz;Albelda Iregua;Rioja",
    "iso:country":"ES",
    "sg:address":"Calle de Santiago Aldaz, S/n",
    "sg:city":"Albelda Iregua",
    "sg:orig_category":"Conservas De Pescados Y Salazones Mar\u00cdtimos (fabricaci\u00d3n, Al Por Mayor)",
    "sg:phone":"+34 941 44 31 02",
    "sg:postcode":"26120",
    "sg:province":"La Rioja",
    "sg:website":"www.anchoasaldaz.com",
    "wof:name":"Santiago Aldaz S. A.",
    "wof:placetype":"venue"
},
  "geometry": {"coordinates":[-2.4743220806,42.3557128906],"type":"Point"}
}