{
  "type": "Feature",
  "properties": {
    "addr:full":"Calle de Federico Ozanan, 10 Zaragoza Zaragoza 50012",
    "addr:housenumber":"10",
    "addr:postcode":"50012",
    "addr:street":"Calle De Federico Ozanan",
    "iso:country":"ES",
    "sg:address":"Calle de Federico Ozanan, 10",
    "sg:city":"Zaragoza",
    "sg:orig_category":"Internados & Ense\u00d1anza Privada",
    "sg:phone":"+34 976 34 27 49",
    "sg:postcode":"50012",
    "sg:province":"Zaragoza",
    "wof:name":"Religiosas Del Sagrado Corazon",
    "wof:placetype":"venue"
},
  "geometry": {"coordinates":[-0.9308009744,41.6398696899],"type":"Point"}
}