{
  "type": "Feature",
  "properties": {
    "iso:country":"ES",
    "sg:address":"Cra Mata (de), 97",
    "sg:city":"Mataro",
    "sg:orig_category":"Ebanister\u00cda",
    "sg:phone":"+34 937 96 08 47",
    "sg:postcode":"08304",
    "sg:province":"Barcelona",
    "wof:name":"Novafusta Mataro S.a.l.",
    "wof:placetype":"venue"
},
  "geometry": {"coordinates":[2.4567639828,41.5536956787],"type":"Point"}
}