{
  "type": "Feature",
  "properties": {
    "iso:country":"ES",
    "sg:address":"Carr Sant Joan Baptista La Salle, 21",
    "sg:city":"Girona",
    "sg:orig_category":"Abogados",
    "sg:phone":"+34 972 20 81 01",
    "sg:postcode":"17002",
    "sg:province":"Girona",
    "wof:name":"Pizarro Rodriguez Jose",
    "wof:placetype":"venue"
},
  "geometry": {"coordinates":[2.8205211163,41.9774055481],"type":"Point"}
}