{
  "type": "Feature",
  "properties": {
    "addr:full":"Cmno Humanes (de), S/n Torrejon Calzada Madrid 28991",
    "addr:housenumber":"s",
    "addr:postcode":"28991",
    "addr:street":"Cmno;/ N Torrejon Calzada",
    "iso:country":"ES",
    "sg:address":"Cmno Humanes (de), S/n",
    "sg:city":"Torrejon Calzada",
    "sg:orig_category":"Producci\u00d3n De Abonos Y De Fertilizantes",
    "sg:phone":"+34 918 16 91 08",
    "sg:postcode":"28991",
    "sg:province":"Madrid",
    "wof:name":"Martinez Hernandez Ildefonso",
    "wof:placetype":"venue"
},
  "geometry": {"coordinates":[-3.8016889095,40.2015762329],"type":"Point"}
}