{
  "type": "Feature",
  "properties": {
    "addr:full":"Casanova (celeiro), Km. 0642,0 Viveiro Lugo 27863",
    "addr:postcode":"27863",
    "addr:street":"Km. 0642,0",
    "iso:country":"ES",
    "sg:address":"Casanova (celeiro), Km. 0642,0",
    "sg:city":"Viveiro",
    "sg:orig_category":"Construcciones Navales Y Fluviales",
    "sg:phone":"+34 982 56 33 75",
    "sg:postcode":"27863",
    "sg:province":"Lugo",
    "wof:name":"Celeimar S.l.",
    "wof:placetype":"venue"
},
  "geometry": {"coordinates":[-7.5347719193,43.6102027893],"type":"Point"}
}