{
  "type": "Feature",
  "properties": {
    "addr:full":"La Rosa, 8 Sta Cruz Tenerife Santa Cruz De Tenerife 38002",
    "addr:housenumber":"8",
    "addr:postcode":"38002",
    "addr:street":"Rosa;Sta Cruz Tenerife",
    "iso:country":"ES",
    "sg:address":"La Rosa, 8",
    "sg:city":"Sta Cruz Tenerife",
    "sg:orig_category":"Juegos Y Juguetes (al Por Menor)",
    "sg:phone":"+34 922 28 10 24",
    "sg:postcode":"38002",
    "sg:province":"Santa Cruz De Tenerife",
    "wof:name":"Arvelo Hernandez Jose",
    "wof:placetype":"venue"
},
  "geometry": {"coordinates":[-16.2503166199,28.4697799683],"type":"Point"}
}