{
  "type": "Feature",
  "properties": {
    "iso:country":"ES",
    "sg:address":"Calle de Mayor, 9",
    "sg:city":"Alberca De Las Torres",
    "sg:orig_category":"Fotograf\u00cda Art\u00cdstica Y Retratos",
    "sg:phone":"+34 968 84 10 60",
    "sg:postcode":"30150",
    "sg:province":"Murcia",
    "wof:name":"Fernandez Saura Angel",
    "wof:placetype":"venue"
},
  "geometry": {"coordinates":[-1.1372590065,37.9417114258],"type":"Point"}
}