{
  "type": "Feature",
  "properties": {
    "iso:country":"ES",
    "sg:address":"Calle de Pendon De Baeza, 15",
    "sg:city":"Le\u00f3n",
    "sg:orig_category":"Asociaciones Humanitarias, De Cooperaci\u00d3n, De Acci\u00d3n Social",
    "sg:phone":"+34 987 25 64 51",
    "sg:postcode":"24006",
    "sg:province":"Le\u00f3n",
    "wof:name":"Filandon-tpsleon S.l.",
    "wof:placetype":"venue"
},
  "geometry": {"coordinates":[-5.5609498024,42.5927772522],"type":"Point"}
}