{
  "type": "Feature",
  "properties": {
    "addr:full":"Calle de Alca\u00d1iz, 4 Valencia Valencia 46019",
    "addr:housenumber":"4",
    "addr:postcode":"46019",
    "addr:street":"Calle De Alcan\u0303Iz",
    "iso:country":"ES",
    "sg:address":"Calle de Alca\u00d1iz, 4",
    "sg:city":"Valencia",
    "sg:orig_category":"Papeler\u00cdas, Librer\u00cdas",
    "sg:phone":"+34 963 66 68 18",
    "sg:postcode":"46019",
    "sg:province":"Valencia",
    "wof:name":"Cervera Del Olmo Yolanda",
    "wof:placetype":"venue"
},
  "geometry": {"coordinates":[-0.3776004016,39.4915771484],"type":"Point"}
}