{
  "type": "Feature",
  "properties": {
    "iso:country":"ES",
    "sg:address":"Av Alfonso Puchades, S/n",
    "sg:city":"Benidorm",
    "sg:orig_category":"Estancos",
    "sg:phone":"+34 965 85 25 70",
    "sg:postcode":"03500",
    "sg:province":"Alicante",
    "wof:name":"Beneyto Belenguer Maria",
    "wof:placetype":"venue"
},
  "geometry": {"coordinates":[-0.1282889992,38.5432739258],"type":"Point"}
}