{
  "type": "Feature",
  "properties": {
    "addr:full":"Calle de Santa Teresita, 37 Zaragoza Zaragoza 50017",
    "addr:housenumber":"37",
    "addr:postcode":"50017",
    "addr:street":"Calle De Santa Teresita",
    "iso:country":"ES",
    "sg:address":"Calle de Santa Teresita, 37",
    "sg:city":"Zaragoza",
    "sg:orig_category":"Carnicer\u00cdas, Carnicer\u00cdas",
    "sg:phone":"+34 976 33 84 10",
    "sg:postcode":"50017",
    "sg:province":"Zaragoza",
    "wof:name":"Castillon Pascual Pedro Ramon",
    "wof:placetype":"venue"
},
  "geometry": {"coordinates":[-0.911559999,41.650177002],"type":"Point"}
}