{
  "type": "Feature",
  "properties": {
    "addr:full":"Calle de General Franco, 31 Cristianos Santa Cruz De Tenerife 38650",
    "addr:housenumber":"31",
    "addr:postcode":"38650",
    "addr:street":"Calle De General Franco",
    "iso:country":"ES",
    "sg:address":"Calle de General Franco, 31",
    "sg:city":"Cristianos",
    "sg:orig_category":"Ropa De Hogar (al Por Menor)",
    "sg:phone":"+34 922 75 27 14",
    "sg:postcode":"38650",
    "sg:province":"Santa Cruz De Tenerife",
    "wof:name":"Eurosys S.a.",
    "wof:placetype":"venue"
},
  "geometry": {"coordinates":[-16.7175884247,28.0517196655],"type":"Point"}
}