{
  "type": "Feature",
  "properties": {
    "addr:full":"Av Catalunya, 71 Casc Antic Barcelona 08150",
    "addr:housenumber":"71",
    "addr:postcode":"08150",
    "addr:street":"Av Catalunya",
    "iso:country":"ES",
    "sg:address":"Av Catalunya, 71",
    "sg:city":"Casc Antic",
    "sg:orig_category":"Cajas De Ahorro",
    "sg:phone":"+34 935 73 52 57",
    "sg:postcode":"08150",
    "sg:province":"Barcelona",
    "wof:name":"Caixa De Manlleu",
    "wof:placetype":"venue"
},
  "geometry": {"coordinates":[2.2319469452,41.5694198608],"type":"Point"}
}