{
  "type": "Feature",
  "properties": {
    "addr:full":"Calle de Vascos, 14 Madrid Madrid 28040",
    "addr:housenumber":"14",
    "addr:postcode":"madrid;28040",
    "addr:street":"Calle De Vascos",
    "iso:country":"ES",
    "sg:address":"Calle de Vascos, 14",
    "sg:city":"Madrid",
    "sg:orig_category":"Venta, Localizaci\u00d3n, Reparaci\u00d3n De Material E Instrumental M\u00c9dico",
    "sg:phone":"+34 915 35 98 60",
    "sg:postcode":"28040",
    "sg:province":"Madrid",
    "wof:name":"Talexco S.l.",
    "wof:placetype":"venue"
},
  "geometry": {"coordinates":[-3.7107379436,40.4480476379],"type":"Point"}
}