{
  "type": "Feature",
  "properties": {
    "addr:full":"Cmno Arroyuelo, S/n Trespaderne Burgos 09540",
    "addr:housenumber":"s",
    "addr:postcode":"09540",
    "addr:street":"Cmno Arroyuelo;/ N",
    "iso:country":"ES",
    "sg:address":"Cmno Arroyuelo, S/n",
    "sg:city":"Trespaderne",
    "sg:orig_category":"Producci\u00d3n, Comercio De Cereales",
    "sg:phone":"+34 947 30 71 49",
    "sg:postcode":"09540",
    "sg:province":"Burgos",
    "wof:name":"Cereales Y Transportes Martinez S.l.",
    "wof:placetype":"venue"
},
  "geometry": {"coordinates":[-3.3839321136,42.8081512451],"type":"Point"}
}