{
  "type": "Feature",
  "properties": {
    "iso:country":"ES",
    "sg:address":"Carr Benito Perez Galdos, 16",
    "sg:city":"Aldaia",
    "sg:orig_category":"Madera Para Chapado",
    "sg:phone":"+34 961 98 50 56",
    "sg:postcode":"46960",
    "sg:province":"Valencia",
    "wof:name":"Chapas Macer S.l.",
    "wof:placetype":"venue"
},
  "geometry": {"coordinates":[-0.4691570103,39.4669494629],"type":"Point"}
}