{
  "type": "Feature",
  "properties": {
    "addr:full":"Carrer de Tres D'abril, 32 S. Boi Llobregat Barcelona 08830",
    "addr:housenumber":"32",
    "addr:postcode":"08830",
    "addr:street":"Carrer De Tres D'Abril",
    "iso:country":"ES",
    "sg:address":"Carrer de Tres D'abril, 32",
    "sg:city":"S. Boi Llobregat",
    "sg:orig_category":"Bisuter\u00cda, Joyer\u00cda, Relojer\u00cda (al Por Menor)",
    "sg:phone":"+34 936 61 35 62",
    "sg:postcode":"08830",
    "sg:province":"Barcelona",
    "wof:name":"Zapata Paniagua Gracia",
    "wof:placetype":"venue"
},
  "geometry": {"coordinates":[2.0435450077,41.3410606384],"type":"Point"}
}