{
  "type": "Feature",
  "properties": {
    "addr:full":"Barr Muntsaratz, 6 Muntsaratz Vizcaya 48220",
    "addr:housenumber":"6",
    "addr:postcode":"48220",
    "addr:street":"Muntsaratz",
    "iso:country":"ES",
    "sg:address":"Barr Muntsaratz, 6",
    "sg:city":"Muntsaratz",
    "sg:orig_category":"Deportes Diversos",
    "sg:phone":"+34 946 81 55 56",
    "sg:postcode":"48220",
    "sg:province":"Vizcaya",
    "wof:name":"Kelman S.l.",
    "wof:placetype":"venue"
},
  "geometry": {"coordinates":[-2.6005535126,43.1422996521],"type":"Point"}
}