{
  "type": "Feature",
  "properties": {
    "iso:country":"ES",
    "sg:address":"Calle de Virgen Del Pilar, 10",
    "sg:city":"Marbella",
    "sg:orig_category":"Ropa Para Ni\u00d1os (al Por Menor)",
    "sg:phone":"+34 952 82 00 40",
    "sg:postcode":"29600",
    "sg:province":"M\u00e1laga",
    "wof:name":"Lozano Erola Cristina",
    "wof:placetype":"venue"
},
  "geometry": {"coordinates":[-4.8899879456,36.5079231262],"type":"Point"}
}