{
  "type": "Feature",
  "properties": {
    "iso:country":"ES",
    "sg:address":"Trav Corts, 313",
    "sg:city":"Barcelona",
    "sg:orig_category":"Arquitectos",
    "sg:phone":"+34 934 39 80 25",
    "sg:postcode":"08029",
    "sg:province":"Barcelona",
    "wof:name":"Companys Ferran Antonio",
    "wof:placetype":"venue"
},
  "geometry": {"coordinates":[2.136302948,41.3875808716],"type":"Point"}
}