{
  "type": "Feature",
  "properties": {
    "addr:full":"Plaz Mayor, 5 Tolva Huesca 22585",
    "addr:housenumber":"5",
    "addr:postcode":"22585",
    "addr:street":"Plaz Mayor",
    "iso:country":"ES",
    "sg:address":"Plaz Mayor, 5",
    "sg:city":"Tolva",
    "sg:orig_category":"Sanatorios M\u00c9dico",
    "sg:phone":"+34 974 54 32 16",
    "sg:postcode":"22585",
    "sg:province":"Huesca",
    "wof:name":"Ayuntamiento De Tolva",
    "wof:placetype":"venue"
},
  "geometry": {"coordinates":[0.5644549727,42.1146087646],"type":"Point"}
}