{
  "type": "Feature",
  "properties": {
    "addr:full":"Pase Rosa, 68 Toledo Toledo 45006",
    "addr:housenumber":"68",
    "addr:postcode":"45006",
    "addr:street":"Rosa",
    "iso:country":"ES",
    "sg:address":"Pase Rosa, 68",
    "sg:city":"Toledo",
    "sg:orig_category":"M\u00c9dicos: Ginecolog\u00cda Y Obstetricia",
    "sg:phone":"+34 925 25 35 88",
    "sg:postcode":"45006",
    "sg:province":"Toledo",
    "wof:name":"Moreno Del Prado Juan Carlos",
    "wof:placetype":"venue"
},
  "geometry": {"coordinates":[-4.0053992271,39.860748291],"type":"Point"}
}