{
  "type": "Feature",
  "properties": {
    "addr:full":"Carrer de Almirall Oquendo, 12 S. Adria Besos Barcelona 08930",
    "addr:housenumber":"12",
    "addr:postcode":"08930",
    "addr:street":"Carrer De Almirall Oquendo;S. Adria Besos Barcelona",
    "iso:country":"ES",
    "sg:address":"Carrer de Almirall Oquendo, 12",
    "sg:city":"S. Adria Besos",
    "sg:orig_category":"Droguer\u00cdas (al Por Menor)",
    "sg:phone":"+34 933 81 87 55",
    "sg:postcode":"08930",
    "sg:province":"Barcelona",
    "wof:name":"Plumed Melendez Manuel",
    "wof:placetype":"venue"
},
  "geometry": {"coordinates":[2.2153689861,41.4305000305],"type":"Point"}
}