{
  "type": "Feature",
  "properties": {
    "addr:full":"Avda Doctor Ramon Y Cajal, 6 Alacant Alicante 03003",
    "addr:housenumber":"6",
    "addr:postcode":"03003",
    "addr:street":"Avda Doctor Ramon Y Cajal",
    "iso:country":"ES",
    "sg:address":"Avda Doctor Ramon Y Cajal, 6",
    "sg:city":"Alacant",
    "sg:orig_category":"Abogados",
    "sg:phone":"+34 965 92 77 53",
    "sg:postcode":"03003",
    "sg:province":"Alicante",
    "wof:name":"Roman Pina Roman",
    "wof:placetype":"venue"
},
  "geometry": {"coordinates":[-0.4888069928,38.3396072388],"type":"Point"}
}