{
  "type": "Feature",
  "properties": {
    "addr:full":"Plaz Cebada, S/n Madrid Madrid 28005",
    "addr:housenumber":"s / n",
    "addr:postcode":"28005",
    "addr:street":"Cebada",
    "iso:country":"ES",
    "sg:address":"Plaz Cebada, S/n",
    "sg:city":"Madrid",
    "sg:orig_category":"Frutas, Legumbres Frescas Y Tempranas (al Por Menor)",
    "sg:phone":"+34 913 65 35 06",
    "sg:postcode":"28005",
    "sg:province":"Madrid",
    "wof:name":"Alonso Gonzalez Margarita",
    "wof:placetype":"venue"
},
  "geometry": {"coordinates":[-3.7096903324,40.4107780457],"type":"Point"}
}