{
  "type": "Feature",
  "properties": {
    "addr:full":"Calle de Sevilla, 1 Argamasilla Calatrava Ciudad Real 13440",
    "addr:housenumber":"1",
    "addr:postcode":"13440",
    "addr:street":"Calle De Sevilla",
    "iso:country":"ES",
    "sg:address":"Calle de Sevilla, 1",
    "sg:city":"Argamasilla Calatrava",
    "sg:orig_category":"Agencias De Trabajo Temporal",
    "sg:phone":"+34 926 47 83 36",
    "sg:postcode":"13440",
    "sg:province":"Ciudad Real",
    "wof:name":"Comercial Y Derivados Del Plastico S.l.",
    "wof:placetype":"venue"
},
  "geometry": {"coordinates":[-4.0839848518,38.7214241028],"type":"Point"}
}