{
  "type": "Feature",
  "properties": {
    "addr:full":"Avda Cabo De Gata, 113 Almeria Almer\u00eda 04007",
    "addr:housenumber":"113",
    "addr:postcode":"04007",
    "addr:street":"Avda Cabo De Gata",
    "iso:country":"ES",
    "sg:address":"Avda Cabo De Gata, 113",
    "sg:city":"Almeria",
    "sg:orig_category":"Laboratorios Y Trabajos De Fotograf\u00cda, V\u00cddeo Y Cine",
    "sg:phone":"+34 950 24 03 46",
    "sg:postcode":"04007",
    "sg:province":"Almer\u00eda",
    "wof:name":"Image World S.l.",
    "wof:placetype":"venue"
},
  "geometry": {"coordinates":[-2.4513959885,36.8291053772],"type":"Point"}
}