{
  "type": "Feature",
  "properties": {
    "iso:country":"ES",
    "sg:address":"Pol. Ind. Guadarranque, S/n",
    "sg:city":"Carteya-guadarranque",
    "sg:orig_category":"Industria Qu\u00cdmica",
    "sg:phone":"+34 956 61 23 38",
    "sg:postcode":"11369",
    "sg:province":"C\u00e1diz",
    "sg:website":"www.repsolypf.com",
    "wof:name":"Repsol Ypf S.a.",
    "wof:placetype":"venue"
},
  "geometry": {"coordinates":[-5.4235692024,36.2050666809],"type":"Point"}
}