{
  "type": "Feature",
  "properties": {
    "iso:country":"ES",
    "sg:address":"Calle de Covarrubias, 3",
    "sg:city":"Madrid",
    "sg:orig_category":"Camiser\u00cda Y Ropa Interior Masculina (al Por Menor)",
    "sg:phone":"+34 914 44 57 83",
    "sg:postcode":"28010",
    "sg:province":"Madrid",
    "wof:name":"Ropa A Medida Tam S.l.",
    "wof:placetype":"venue"
},
  "geometry": {"coordinates":[-3.6973233223,40.4287223816],"type":"Point"}
}