{
  "type": "Feature",
  "properties": {
    "iso:country":"ES",
    "sg:address":"Calle de Santa Eulalia, 10",
    "sg:city":"Merida",
    "sg:orig_category":"Fotocopias, Reprograf\u00cda",
    "sg:phone":"+34 924 30 09 63",
    "sg:postcode":"06800",
    "sg:province":"Badajoz",
    "wof:name":"Muriel Roman Rosa Maria",
    "wof:placetype":"venue"
},
  "geometry": {"coordinates":[-6.3452291489,38.9163894653],"type":"Point"}
}