{
  "type": "Feature",
  "properties": {
    "iso:country":"ES",
    "sg:address":"Calle de Ramon Y Cajal, 3",
    "sg:city":"Sese\u00e7a Nuevo",
    "sg:orig_category":"Fabricaci\u00d3n De Muebles De Cocina",
    "sg:phone":"+34 918 92 60 30",
    "sg:postcode":"45224",
    "sg:province":"Toledo",
    "wof:name":"Cocinas Y Complementos Del Sur S.l.",
    "wof:placetype":"venue"
},
  "geometry": {"coordinates":[-3.6579489708,40.1077690125],"type":"Point"}
}