{
  "type": "Feature",
  "properties": {
    "addr:full":"Calle de Gibraltar, 8 San Gabriel Alicante 03710",
    "addr:housenumber":"8",
    "addr:postcode":"03710",
    "addr:street":"Calle De Gibraltar",
    "iso:country":"ES",
    "sg:address":"Calle de Gibraltar, 8",
    "sg:city":"San Gabriel",
    "sg:orig_category":"Doctores En Medicina",
    "sg:phone":"+34 965 83 51 15",
    "sg:postcode":"03710",
    "sg:province":"Alicante",
    "wof:name":"Huerta Quintero Julian",
    "wof:placetype":"venue"
},
  "geometry": {"coordinates":[-0.4810059965,38.3452033997],"type":"Point"}
}