{
  "type": "Feature",
  "properties": {
    "iso:country":"ES",
    "sg:address":"Lombardero, 11",
    "sg:city":"Pontedeume",
    "sg:orig_category":"Pod\u00d3logos: Pedicuros",
    "sg:phone":"+34 981 43 37 38",
    "sg:postcode":"15600",
    "sg:province":"La Coru\u00f1a",
    "wof:name":"Alvari\u00f1o Bujia Silvia",
    "wof:placetype":"venue"
},
  "geometry": {"coordinates":[-8.1731157303,43.4077835083],"type":"Point"}
}