{
  "type": "Feature",
  "properties": {
    "iso:country":"ES",
    "sg:address":"Sileras Egido, S/n",
    "sg:city":"Arroyo S Servan",
    "sg:orig_category":"Chapister\u00cda",
    "sg:phone":"+34 924 34 22 31",
    "sg:postcode":"06850",
    "sg:province":"Badajoz",
    "wof:name":"Galan Moreno Isidoro",
    "wof:placetype":"venue"
},
  "geometry": {"coordinates":[-6.4543747902,38.8560295105],"type":"Point"}
}