{
  "type": "Feature",
  "properties": {
    "addr:full":"Calle de Maria De Zayas, S/n Granada Granada 18004",
    "addr:housenumber":"s / n",
    "addr:postcode":"18004",
    "addr:street":"Calle De Maria De Zayas",
    "iso:country":"ES",
    "sg:address":"Calle de Maria De Zayas, S/n",
    "sg:city":"Granada",
    "sg:orig_category":"Internados & Ense\u00d1anza Privada",
    "sg:phone":"+34 958 26 39 63",
    "sg:postcode":"18004",
    "sg:province":"Granada",
    "wof:name":"De Molina Galdeano Antonio",
    "wof:placetype":"venue"
},
  "geometry": {"coordinates":[-3.6086339951,37.1666107178],"type":"Point"}
}