{
  "type": "Feature",
  "properties": {
    "addr:full":"Kale Nagusia, 63 Hernani Guip\u00f9zcoa 20120",
    "addr:housenumber":"63",
    "addr:postcode":"20120",
    "addr:street":"Kale Nagusia;Guipu\u0300Zcoa",
    "iso:country":"ES",
    "sg:address":"Kale Nagusia, 63",
    "sg:city":"Hernani",
    "sg:orig_category":"Confecci\u00d3n De Trajes Para Se\u00d1oras",
    "sg:phone":"+34 943 55 74 73",
    "sg:postcode":"20120",
    "sg:province":"Guip\u00f9zcoa",
    "wof:name":"Giraldo Meride\u00cfo Benito",
    "wof:placetype":"venue"
},
  "geometry": {"coordinates":[-1.9798289537,43.2647514343],"type":"Point"}
}