{
  "type": "Feature",
  "properties": {
    "iso:country":"ES",
    "sg:address":"Alto Tras (dos), 30",
    "sg:city":"Outeiro Das Penas",
    "sg:orig_category":"Reposter\u00cdas",
    "sg:phone":"+34 986 49 52 91",
    "sg:postcode":"36693",
    "sg:province":"Pontevedra",
    "wof:name":"Panaderia Pasteleria Ness C.b.",
    "wof:placetype":"venue"
},
  "geometry": {"coordinates":[-8.6162719727,42.3098869324],"type":"Point"}
}