{
  "type": "Feature",
  "properties": {
    "addr:full":"Av Diagonal, 472 Barcelona Barcelona 08006",
    "addr:housenumber":"472",
    "addr:postcode":"08006",
    "addr:street":"Av Diagonal",
    "iso:country":"ES",
    "sg:address":"Av Diagonal, 472",
    "sg:city":"Barcelona",
    "sg:orig_category":"Abogados",
    "sg:phone":"+34 934 30 00 72",
    "sg:postcode":"08006",
    "sg:province":"Barcelona",
    "wof:name":"Asensio Figueres Montserrat",
    "wof:placetype":"venue"
},
  "geometry": {"coordinates":[2.1564421654,41.3959579468],"type":"Point"}
}