{
  "type": "Feature",
  "properties": {
    "iso:country":"ES",
    "sg:address":"Avda Gran Via Parque, 23",
    "sg:city":"Cordoba",
    "sg:orig_category":"Administradores De Bienes Y Delegados De Comunidades De Propietarios",
    "sg:phone":"+34 957 45 17 81",
    "sg:postcode":"14005",
    "sg:province":"C\u00f3rdoba",
    "wof:name":"Ancarpe Sl",
    "wof:placetype":"venue"
},
  "geometry": {"coordinates":[-4.7923603058,37.8783340454],"type":"Point"}
}