{
  "type": "Feature",
  "properties": {
    "addr:full":"San Miguel De Campo, S/n Luintra Ourense 32160",
    "addr:housenumber":"s",
    "addr:postcode":"32160",
    "addr:street":"/ N",
    "iso:country":"ES",
    "sg:address":"San Miguel De Campo, S/n",
    "sg:city":"Luintra",
    "sg:orig_category":"Art\u00cdculos De Decoraci\u00d3n",
    "sg:phone":"+34 988 20 11 41",
    "sg:postcode":"32160",
    "sg:province":"Ourense",
    "wof:name":"Barreiros Artesania S.c",
    "wof:placetype":"venue"
},
  "geometry": {"coordinates":[-7.7269392014,42.4117584229],"type":"Point"}
}