{
  "type": "Feature",
  "properties": {
    "iso:country":"ES",
    "sg:address":"Pl Urquinaona, 3",
    "sg:city":"Barcelona",
    "sg:orig_category":"Obras Y Organismos Sociales",
    "sg:phone":"+34 933 01 89 29",
    "sg:postcode":"08010",
    "sg:province":"Barcelona",
    "wof:name":"Agrupacion Benefica Humanitaria",
    "wof:placetype":"venue"
},
  "geometry": {"coordinates":[2.1725955009,41.3891105652],"type":"Point"}
}