{
  "type": "Feature",
  "properties": {
    "iso:country":"ES",
    "sg:address":"Carr Carricola, S/n",
    "sg:city":"Atzeneta D'albaida",
    "sg:orig_category":"Hielo Artificial (fabricaci\u00d3n, Distribuci\u00d3n)",
    "sg:phone":"+34 962 35 70 44",
    "sg:postcode":"46869",
    "sg:province":"Valencia",
    "wof:name":"Nacher Langa Eduardo",
    "wof:placetype":"venue"
},
  "geometry": {"coordinates":[-0.5128009915,38.8377304077],"type":"Point"}
}