{
  "type": "Feature",
  "properties": {
    "iso:country":"ES",
    "sg:address":"Bo. Ugarte, 43",
    "sg:city":"Ugarte",
    "sg:orig_category":"Fabricaci\u00d3n De Ventanas",
    "sg:phone":"+34 946 15 58 00",
    "sg:postcode":"48110",
    "sg:province":"Vizcaya",
    "wof:name":"Ibaialde P.v.c. S.l.",
    "wof:placetype":"venue"
},
  "geometry": {"coordinates":[-2.8737039566,43.3628692627],"type":"Point"}
}