{
  "type": "Feature",
  "properties": {
    "iso:country":"ES",
    "sg:address":"Calle de Neptuno, 5",
    "sg:city":"Granada",
    "sg:orig_category":"Ense\u00d1anza Superior Privada",
    "sg:phone":"+34 958 25 31 50",
    "sg:postcode":"18004",
    "sg:province":"Granada",
    "wof:name":"Colegio Mayor Universitario Cardenal Cisneros",
    "wof:placetype":"venue"
},
  "geometry": {"coordinates":[-3.6067550182,37.1695404053],"type":"Point"}
}