{
  "type": "Feature",
  "properties": {
    "addr:full":"Carrer de Sepulveda, 134 Barcelona Barcelona 08015",
    "addr:housenumber":"134",
    "addr:postcode":"08015",
    "addr:street":"Carrer De Sepulveda",
    "iso:country":"ES",
    "sg:address":"Carrer de Sepulveda, 134",
    "sg:city":"Barcelona",
    "sg:orig_category":"Asesor\u00cda Sobre Comunicaci\u00d3n De Empresas",
    "sg:phone":"+34 934 26 58 22",
    "sg:postcode":"08015",
    "sg:province":"Barcelona",
    "wof:name":"Centro De Servicios Y Suministros S.a.",
    "wof:placetype":"venue"
},
  "geometry": {"coordinates":[2.1595830917,41.3808097839],"type":"Point"}
}