{
  "type": "Feature",
  "properties": {
    "iso:country":"ES",
    "sg:address":"Pl Josep Maluquer I Salvador, 1",
    "sg:city":"Granollers",
    "sg:orig_category":"Sociedades Y Organismos Burs\u00c1tiles",
    "sg:phone":"+34 938 61 11 99",
    "sg:postcode":"08401",
    "sg:province":"Barcelona",
    "wof:name":"Gaesco Bolsa S.a.",
    "wof:placetype":"venue"
},
  "geometry": {"coordinates":[2.2887759209,41.6084251404],"type":"Point"}
}