{
  "type": "Feature",
  "properties": {
    "addr:full":"Avda Tres Cruces, 7 Zamora Zamora 49008",
    "addr:housenumber":"7",
    "addr:postcode":"49008",
    "addr:street":"Avda Tres Cruces",
    "iso:country":"ES",
    "sg:address":"Avda Tres Cruces, 7",
    "sg:city":"Zamora",
    "sg:orig_category":"Abogados",
    "sg:phone":"+34 980 52 21 56",
    "sg:postcode":"49008",
    "sg:province":"Zamora",
    "wof:name":"Crespo Neches Enrique",
    "wof:placetype":"venue"
},
  "geometry": {"coordinates":[-5.7419419289,41.5097923279],"type":"Point"}
}