{
  "type": "Feature",
  "properties": {
    "iso:country":"ES",
    "sg:address":"Calle de Diego Pisador, S/n",
    "sg:city":"Salamanca",
    "sg:orig_category":"Organismos De Investigaciones Cient\u00cdficas Y T\u00c9cnicas",
    "sg:phone":"+34 923 26 45 39",
    "sg:postcode":"37008",
    "sg:province":"Salamanca",
    "wof:name":"Instituto De Investigaciones Cientificas Y Ecologicas",
    "wof:placetype":"venue"
},
  "geometry": {"coordinates":[-5.6673264503,40.9539909363],"type":"Point"}
}