{
  "type": "Feature",
  "properties": {
    "addr:full":"Calle de Arostegieta Kalea, 11 Tolosa Guip\u00f9zcoa 20400",
    "addr:housenumber":"11",
    "addr:postcode":"20400",
    "addr:street":"Calle De Arostegieta Kalea;Guipu\u0300Zcoa",
    "iso:country":"ES",
    "sg:address":"Calle de Arostegieta Kalea, 11",
    "sg:city":"Tolosa",
    "sg:orig_category":"Confecci\u00d3n De Trajes Para Se\u00d1oras",
    "sg:phone":"+34 943 67 42 87",
    "sg:postcode":"20400",
    "sg:province":"Guip\u00f9zcoa",
    "wof:name":"Mendizabal Gurruchaga Enrique",
    "wof:placetype":"venue"
},
  "geometry": {"coordinates":[-2.0731449127,43.1386795044],"type":"Point"}
}