{
  "type": "Feature",
  "properties": {
    "iso:country":"ES",
    "sg:address":"Calle de Novo Cazon, 27",
    "sg:city":"Vilalba",
    "sg:orig_category":"Institutos De Belleza",
    "sg:phone":"+34 982 51 00 74",
    "sg:postcode":"27800",
    "sg:province":"Lugo",
    "wof:name":"Arias Gonzalez Pilar",
    "wof:placetype":"venue"
},
  "geometry": {"coordinates":[-7.6787037849,43.2983322144],"type":"Point"}
}