{
  "type": "Feature",
  "properties": {
    "iso:country":"ES",
    "sg:address":"Calle de Tartanga Kalea, 9",
    "sg:city":"Erandio",
    "sg:orig_category":"Peluqueros: De Se\u00d1oras",
    "sg:phone":"+34 944 17 10 81",
    "sg:postcode":"48950",
    "sg:province":"Vizcaya",
    "wof:name":"Yolanda Zubieta Izaguirre",
    "wof:placetype":"venue"
},
  "geometry": {"coordinates":[-2.974255085,43.3053131104],"type":"Point"}
}