{
  "type": "Feature",
  "properties": {
    "addr:full":"Calle de Pintor Obdulio Lopez De Uralde, 15 Vitoria-gasteiz \u00c1lava 01008",
    "addr:housenumber":"15",
    "addr:postcode":"01008",
    "addr:street":"Calle De Pintor Obdulio Lopez De Uralde",
    "iso:country":"ES",
    "sg:address":"Calle de Pintor Obdulio Lopez De Uralde, 15",
    "sg:city":"Vitoria-gasteiz",
    "sg:orig_category":"Fachadas",
    "sg:phone":"+34 945 21 30 68",
    "sg:postcode":"01008",
    "sg:province":"\u00c1lava",
    "wof:name":"Trabajos Verticales Factor 2 , S.l",
    "wof:placetype":"venue"
},
  "geometry": {"coordinates":[-2.6861200333,42.8465499878],"type":"Point"}
}