{
  "type": "Feature",
  "properties": {
    "addr:full":"Plaz Ronda, 1 Malaga M\u00e1laga 29014",
    "addr:housenumber":"1",
    "addr:postcode":"29014",
    "addr:street":"Ronda;Ma\u0301Laga",
    "iso:country":"ES",
    "sg:address":"Plaz Ronda, 1",
    "sg:city":"Malaga",
    "sg:orig_category":"Carnicer\u00cdas, Carnicer\u00cdas",
    "sg:phone":"+34 952 25 58 42",
    "sg:postcode":"29014",
    "sg:province":"M\u00e1laga",
    "wof:name":"Robles Urbano Alonso Miguel",
    "wof:placetype":"venue"
},
  "geometry": {"coordinates":[-4.4232640266,36.7443313599],"type":"Point"}
}