{
  "type": "Feature",
  "properties": {
    "iso:country":"ES",
    "sg:address":"Acce Ca\u00d1ada Real De Merinas A La Av. De La Hispanidad, 7",
    "sg:city":"Madrid",
    "sg:orig_category":"Cl\u00cdnicas M\u00c9dicas",
    "sg:phone":"+34 913 29 30 54",
    "sg:postcode":"28042",
    "sg:province":"Madrid",
    "wof:name":"Amex S.a.",
    "wof:placetype":"venue"
},
  "geometry": {"coordinates":[-3.5858001709,40.4543685913],"type":"Point"}
}