{
  "type": "Feature",
  "properties": {
    "iso:country":"ES",
    "sg:address":"Pg Reina Sofia, 25",
    "sg:city":"Pego",
    "sg:orig_category":"Notarios",
    "sg:phone":"+34 965 57 28 62",
    "sg:postcode":"03780",
    "sg:province":"Alicante",
    "wof:name":"Clemente Buendia Maria Cristina",
    "wof:placetype":"venue"
},
  "geometry": {"coordinates":[-0.1124640033,38.8427658081],"type":"Point"}
}