{
  "type": "Feature",
  "properties": {
    "iso:country":"ES",
    "sg:address":"Ctra. Fonfria, 3",
    "sg:city":"Carbajales De Alba",
    "sg:orig_category":"Venta, Montaje De Neum\u00c1ticos",
    "sg:phone":"+34 980 58 52 72",
    "sg:postcode":"49160",
    "sg:province":"Zamora",
    "wof:name":"Neumaticos Carbajeles C.b",
    "wof:placetype":"venue"
},
  "geometry": {"coordinates":[-5.9950809479,41.6496124268],"type":"Point"}
}