{
  "type": "Feature",
  "properties": {
    "iso:country":"ES",
    "sg:address":"Calle de Vitoria, 166",
    "sg:city":"Burgos",
    "sg:orig_category":"Bancos",
    "sg:phone":"+34 947 23 52 54",
    "sg:postcode":"09007",
    "sg:province":"Burgos",
    "wof:name":"Banco Espa\u00f1ol De Credito S.a.",
    "wof:placetype":"venue"
},
  "geometry": {"coordinates":[-3.6670229435,42.353843689],"type":"Point"}
}