{
  "type": "Feature",
  "properties": {
    "addr:full":"Calle de Teso (el), 10 Toral De Los Vados Le\u00f3n 24560",
    "addr:housenumber":"10",
    "addr:postcode":"24560",
    "addr:street":"Calle De Teso El",
    "iso:country":"ES",
    "sg:address":"Calle de Teso (el), 10",
    "sg:city":"Toral De Los Vados",
    "sg:orig_category":"Carnicer\u00cdas, Carnicer\u00cdas",
    "sg:phone":"+34 987 54 40 70",
    "sg:postcode":"24560",
    "sg:province":"Le\u00f3n",
    "wof:name":"Barreiro Rodriguez Pedro",
    "wof:placetype":"venue"
},
  "geometry": {"coordinates":[-6.7758421898,42.5422019958],"type":"Point"}
}