{
  "type": "Feature",
  "properties": {
    "addr:full":"Carr Muntanya, 68 Algemesi Valencia 46680",
    "addr:housenumber":"68",
    "addr:postcode":"46680",
    "addr:street":"Carr Muntanya",
    "iso:country":"ES",
    "sg:address":"Carr Muntanya, 68",
    "sg:city":"Algemesi",
    "sg:orig_category":"Peluquer\u00cdas, Peluquer\u00cda Mixta",
    "sg:phone":"+34 962 48 30 02",
    "sg:postcode":"46680",
    "sg:province":"Valencia",
    "wof:name":"Carolina Clari Ferrer S.l.",
    "wof:placetype":"venue"
},
  "geometry": {"coordinates":[-0.43878901,39.1915397644],"type":"Point"}
}