{
  "type": "Feature",
  "properties": {
    "addr:full":"Calle de Alcazar Y Perez, 23 Palma Condado Huelva 21700",
    "addr:housenumber":"23",
    "addr:postcode":"21700",
    "addr:street":"Calle De Alcazar Y Perez",
    "iso:country":"ES",
    "sg:address":"Calle de Alcazar Y Perez, 23",
    "sg:city":"Palma Condado",
    "sg:orig_category":"Alquiler De Muebles",
    "sg:phone":"+34 959 40 02 32",
    "sg:postcode":"21700",
    "sg:province":"Huelva",
    "wof:name":"Lagares Casanova Maria Del Carmen",
    "wof:placetype":"venue"
},
  "geometry": {"coordinates":[-6.5539827347,37.3820419312],"type":"Point"}
}