{
  "type": "Feature",
  "properties": {
    "iso:country":"ES",
    "sg:address":"Calle de Miraflores (de), 3",
    "sg:city":"Fuenlabrada",
    "sg:orig_category":"Empresas De Pintura Y Revestimientos",
    "sg:phone":"+34 916 90 13 37",
    "sg:postcode":"28944",
    "sg:province":"Madrid",
    "wof:name":"Camara Lozano Jose",
    "wof:placetype":"venue"
},
  "geometry": {"coordinates":[-3.7887980938,40.2805900574],"type":"Point"}
}