{
  "type": "Feature",
  "properties": {
    "addr:full":"Calle de Republica Argentina, 13 Irun Guip\u00f9zcoa 20302",
    "addr:housenumber":"13",
    "addr:postcode":"20302",
    "addr:street":"Calle De Republica Argentina;Guipu\u0300Zcoa",
    "iso:country":"ES",
    "sg:address":"Calle de Republica Argentina, 13",
    "sg:city":"Irun",
    "sg:orig_category":"Librer\u00cdas",
    "sg:phone":"+34 943 62 30 91",
    "sg:postcode":"20302",
    "sg:province":"Guip\u00f9zcoa",
    "wof:name":"Hernandez Ruiz Manuel",
    "wof:placetype":"venue"
},
  "geometry": {"coordinates":[-1.7917269468,43.3403358459],"type":"Point"}
}