{
  "type": "Feature",
  "properties": {
    "addr:full":"Dels Ports(pol Ind), 3 Alaquas Valencia 46970",
    "addr:housenumber":"3",
    "addr:postcode":"46970",
    "addr:street":"Ports;Ind",
    "iso:country":"ES",
    "sg:address":"Dels Ports(pol Ind), 3",
    "sg:city":"Alaquas",
    "sg:orig_category":"Madera Para Chapado",
    "sg:phone":"+34 961 50 92 17",
    "sg:postcode":"46970",
    "sg:province":"Valencia",
    "wof:name":"Moreno Aguado Alfonso",
    "wof:placetype":"venue"
},
  "geometry": {"coordinates":[-0.4708319902,39.4525375366],"type":"Point"}
}