{
  "type": "Feature",
  "properties": {
    "addr:full":"Av. Blasco Iba\u00f1ez, 68 Massanassa Valencia 46470",
    "addr:housenumber":"68",
    "addr:postcode":"46470",
    "addr:street":"Av. Blasco Iban\u0303Ez",
    "iso:country":"ES",
    "sg:address":"Av. Blasco Iba\u00f1ez, 68",
    "sg:city":"Massanassa",
    "sg:orig_category":"Cl\u00cdnicas Dentales",
    "sg:phone":"+34 961 25 23 54",
    "sg:postcode":"46470",
    "sg:province":"Valencia",
    "wof:name":"Pino Gomez Maria Rosario",
    "wof:placetype":"venue"
},
  "geometry": {"coordinates":[-0.3999010026,39.4114532471],"type":"Point"}
}