{
  "type": "Feature",
  "properties": {
    "iso:country":"ES",
    "sg:address":"Calle de Alfonso Vii, 2",
    "sg:city":"Salda\u00f1a",
    "sg:orig_category":"Relojer\u00cda (al Por Menor, Reparaci\u00d3n)",
    "sg:phone":"+34 979 89 02 21",
    "sg:postcode":"34100",
    "sg:province":"Palencia",
    "wof:name":"Rodriguez Villalba Matias",
    "wof:placetype":"venue"
},
  "geometry": {"coordinates":[-4.7350802422,42.5248680115],"type":"Point"}
}