{
  "type": "Feature",
  "properties": {
    "addr:full":"Calle de Polideportivo, 3 Sadaba Zaragoza 50670",
    "addr:housenumber":"3",
    "addr:postcode":"50670",
    "addr:street":"Calle De Polideportivo",
    "iso:country":"ES",
    "sg:address":"Calle de Polideportivo, 3",
    "sg:city":"Sadaba",
    "sg:orig_category":"Electricidad Veh\u00cdculo",
    "sg:phone":"+34 976 67 53 85",
    "sg:postcode":"50670",
    "sg:province":"Zaragoza",
    "wof:name":"Arrospide De Sadaba S.l.",
    "wof:placetype":"venue"
},
  "geometry": {"coordinates":[-1.2721147537,42.2849807739],"type":"Point"}
}