{
  "type": "Feature",
  "properties": {
    "iso:country":"ES",
    "sg:address":"Calle de Estocolmo, 31",
    "sg:city":"Madrid",
    "sg:orig_category":"Inform\u00c1tica Equipo Y Programas (al Por Mayor)",
    "sg:phone":"+34 917 75 84 32",
    "sg:postcode":"28022",
    "sg:province":"Madrid",
    "wof:name":"Isis Ingenieria Y Sistemas S.l.l.",
    "wof:placetype":"venue"
},
  "geometry": {"coordinates":[-3.5998666286,40.427028656],"type":"Point"}
}