{
  "type": "Feature",
  "properties": {
    "addr:full":"Avda Entrevias, 42 Madrid Madrid 28053",
    "addr:housenumber":"42",
    "addr:postcode":"madrid;28053",
    "addr:street":"Avda Entrevias",
    "iso:country":"ES",
    "sg:address":"Avda Entrevias, 42",
    "sg:city":"Madrid",
    "sg:orig_category":"Sociedades, Compa\u00d1\u00cdas Aseguradoras",
    "sg:phone":"+34 914 78 59 22",
    "sg:postcode":"28053",
    "sg:province":"Madrid",
    "wof:name":"Trasegur Correduria De Seguros S.a.",
    "wof:placetype":"venue"
},
  "geometry": {"coordinates":[-3.670388937,40.3842086792],"type":"Point"}
}