{
  "type": "Feature",
  "properties": {
    "addr:full":"Rua Republica Arxentina (da), 38 Santiago De Compostela A Coru\u00f1a 15706",
    "addr:housenumber":"38",
    "addr:postcode":"15706",
    "addr:street":"Rua Republica Arxentina Da;Corun\u0303A",
    "iso:country":"ES",
    "sg:address":"Rua Republica Arxentina (da), 38",
    "sg:city":"Santiago De Compostela",
    "sg:orig_category":"Supermercados Y Hipermercados",
    "sg:phone":"+34 981 59 83 15",
    "sg:postcode":"15706",
    "sg:province":"A Coru\u00f1a",
    "wof:name":"Vego Supermercados S.a.",
    "wof:placetype":"venue"
},
  "geometry": {"coordinates":[-8.5495576859,42.872467041],"type":"Point"}
}