{
  "type": "Feature",
  "properties": {
    "iso:country":"ES",
    "sg:address":"Rua Senra (da), 8",
    "sg:city":"Santiago De Compostela",
    "sg:orig_category":"Gu\u00cdas Y Gu\u00cdas",
    "sg:phone":"+34 981 56 65 61",
    "sg:postcode":"15702",
    "sg:province":"La Coru\u00f1a",
    "wof:name":"Pardo Quiroga Jesus",
    "wof:placetype":"venue"
},
  "geometry": {"coordinates":[-8.5446891785,42.8768959045],"type":"Point"}
}