{
  "type": "Feature",
  "properties": {
    "iso:country":"ES",
    "sg:address":"Carrer de Campoamor, S/n",
    "sg:city":"Sabadell",
    "sg:orig_category":"Centros De Educaci\u00d3n Especial",
    "sg:phone":"+34 937 10 29 45",
    "sg:postcode":"08204",
    "sg:province":"Barcelona",
    "wof:name":"Ceip Sallares I Pla",
    "wof:placetype":"venue"
},
  "geometry": {"coordinates":[2.1089150906,41.52917099],"type":"Point"}
}