{
  "type": "Feature",
  "properties": {
    "iso:country":"ES",
    "sg:address":"Cmno Ronda (de), 197",
    "sg:city":"Granada",
    "sg:orig_category":"Reposter\u00cdas",
    "sg:phone":"+34 958 28 71 54",
    "sg:postcode":"18003",
    "sg:province":"Granada",
    "wof:name":"Antonio Y Emilesio Castro Martin C.b.",
    "wof:placetype":"venue"
},
  "geometry": {"coordinates":[-3.6146225929,37.1844940186],"type":"Point"}
}