{
  "type": "Feature",
  "properties": {
    "iso:country":"ES",
    "sg:address":"Rua Mari\u00d1as, 13",
    "sg:city":"Betanzos",
    "sg:orig_category":"Muebles Y Accesorios Para Cocinas Y Cuartos De Ba\u00d1o (al Por Menor)",
    "sg:phone":"+34 981 77 51 11",
    "sg:postcode":"15300",
    "sg:province":"La Coru\u00f1a",
    "wof:name":"Muebles De Cocina As Mari\u00f1as S.l.",
    "wof:placetype":"venue"
},
  "geometry": {"coordinates":[-8.2128257751,43.2833480835],"type":"Point"}
}