{
  "type": "Feature",
  "properties": {
    "iso:country":"ES",
    "sg:address":"Calle de Madre De Dios, 25",
    "sg:city":"Valladolid",
    "sg:orig_category":"Ropa Para Se\u00d1oras (al Por Menor)",
    "sg:phone":"+34 983 26 60 51",
    "sg:postcode":"47011",
    "sg:province":"Valladolid",
    "wof:name":"Vega Huerga Mercedes",
    "wof:placetype":"venue"
},
  "geometry": {"coordinates":[-4.7147622108,41.6593360901],"type":"Point"}
}