{
  "type": "Feature",
  "properties": {
    "addr:full":"Carretera Las Negras, S/n Campohermoso Almer\u00eda 04110",
    "addr:housenumber":"s",
    "addr:postcode":"04110",
    "addr:street":"Carretera Las Negras;/ N Campohermoso Almeri\u0301A",
    "iso:country":"ES",
    "sg:address":"Carretera Las Negras, S/n",
    "sg:city":"Campohermoso",
    "sg:orig_category":"Fabricaci\u00d3n De Muebles",
    "sg:phone":"+34 950 38 53 26",
    "sg:postcode":"04110",
    "sg:province":"Almer\u00eda",
    "wof:name":"Campomueble C.b.",
    "wof:placetype":"venue"
},
  "geometry": {"coordinates":[-2.1384088993,36.9406242371],"type":"Point"}
}