{
  "type": "Feature",
  "properties": {
    "iso:country":"ES",
    "sg:address":"Praz Campo Castelo (do), 8",
    "sg:city":"Lugo",
    "sg:orig_category":"Confecci\u00d3n De Trajes Para Se\u00d1oras",
    "sg:phone":"+34 982 24 04 02",
    "sg:postcode":"27001",
    "sg:province":"Lugo",
    "wof:name":"Antalma Lugo Sl",
    "wof:placetype":"venue"
},
  "geometry": {"coordinates":[-7.5550122261,43.0094490051],"type":"Point"}
}