{
  "type": "Feature",
  "properties": {
    "addr:full":"Plaz Constitucion, 7 Castellon Castell\u00f3n 12005",
    "addr:housenumber":"7",
    "addr:postcode":"12005",
    "addr:street":"Constitucion;Castello\u0301N",
    "iso:country":"ES",
    "sg:address":"Plaz Constitucion, 7",
    "sg:city":"Castellon",
    "sg:orig_category":"Psic\u00d3logos",
    "sg:phone":"+34 964 20 93 91",
    "sg:postcode":"12005",
    "sg:province":"Castell\u00f3n",
    "wof:name":"Borras Beato Maria Teresa",
    "wof:placetype":"venue"
},
  "geometry": {"coordinates":[-0.0297400001,39.9624290466],"type":"Point"}
}