{
  "type": "Feature",
  "properties": {
    "iso:country":"ES",
    "sg:address":"Avda Alcalde Puche Pardo, S/n",
    "sg:city":"Baeza",
    "sg:orig_category":"Promotores Constructores",
    "sg:phone":"+34 953 74 08 21",
    "sg:postcode":"23440",
    "sg:province":"Ja\u00e9n",
    "wof:name":"Cijolber S.a.",
    "wof:placetype":"venue"
},
  "geometry": {"coordinates":[-3.4565339088,37.9977073669],"type":"Point"}
}