{
  "type": "Feature",
  "properties": {
    "iso:country":"ES",
    "sg:address":"Estd Castela, 251",
    "sg:city":"Ferrol",
    "sg:orig_category":"Frutas Y Legumbres Frescas (al Por Mayor)",
    "sg:phone":"+34 981 32 83 78",
    "sg:postcode":"15404",
    "sg:province":"La Coru\u00f1a",
    "wof:name":"Frutas Volvoreta S.l.",
    "wof:placetype":"venue"
},
  "geometry": {"coordinates":[-8.2137050629,43.492351532],"type":"Point"}
}