{
  "type": "Feature",
  "properties": {
    "addr:full":"Pase Delicias, 4 Madrid Madrid 28045",
    "addr:housenumber":"4",
    "addr:postcode":"28045",
    "addr:street":"Delicias",
    "iso:country":"ES",
    "sg:address":"Pase Delicias, 4",
    "sg:city":"Madrid",
    "sg:classifiers":[
        {
            "category":"Personal",
            "subcategory":"Barber",
            "type":"Services"
        }
    ],
    "sg:phone":"+34 914 67 84 66",
    "sg:postcode":"28045",
    "sg:province":"Madrid",
    "sg:tags":[
        "caballeros",
        "de",
        "peluqueros"
    ],
    "wof:name":"Sanchez Gonzalez Agustin",
    "wof:placetype":"venue"
},
  "geometry": {"coordinates":[-3.6954259872,40.4040679932],"type":"Point"}
}