{
  "type": "Feature",
  "properties": {
    "addr:full":"Calle de Mayor, 24 Raal Murcia 30139",
    "addr:housenumber":"24",
    "addr:postcode":"30139",
    "addr:street":"Calle De Mayor",
    "iso:country":"ES",
    "sg:address":"Calle de Mayor, 24",
    "sg:city":"Raal",
    "sg:orig_category":"Frutas Y Legumbres Frescas (al Por Mayor)",
    "sg:phone":"+34 968 37 90 57",
    "sg:postcode":"30139",
    "sg:province":"Murcia",
    "wof:name":"Hijos De Manuel Lucas S.l.",
    "wof:placetype":"venue"
},
  "geometry": {"coordinates":[-1.0447670221,38.0299797058],"type":"Point"}
}