{
  "type": "Feature",
  "properties": {
    "iso:country":"ES",
    "sg:address":"Avda Carretera De Granada, 75",
    "sg:city":"Caravaca Cruz",
    "sg:orig_category":"Alimentaci\u00d3n General (al Por Mayor)",
    "sg:phone":"+34 968 70 56 60",
    "sg:postcode":"30400",
    "sg:province":"Murcia",
    "wof:name":"Jumasan S.l.",
    "wof:placetype":"venue"
},
  "geometry": {"coordinates":[-1.867151022,38.0970802307],"type":"Point"}
}