{
  "type": "Feature",
  "properties": {
    "addr:full":"Calle de Mira El Sol, 12 Madrid Madrid 28005",
    "addr:housenumber":"12",
    "addr:postcode":"madrid;28005",
    "addr:street":"Calle De Mira El Sol",
    "iso:country":"ES",
    "sg:address":"Calle de Mira El Sol, 12",
    "sg:city":"Madrid",
    "sg:orig_category":"Tapicer\u00cdas",
    "sg:phone":"+34 915 27 19 04",
    "sg:postcode":"28005",
    "sg:province":"Madrid",
    "wof:name":"Feo Camacho Tomas",
    "wof:placetype":"venue"
},
  "geometry": {"coordinates":[-3.7056429386,40.4074859619],"type":"Point"}
}