{
  "type": "Feature",
  "properties": {
    "addr:full":"Poligono De Arzua, 10 Arzua La Coru\u00f1a 15810",
    "addr:housenumber":"10",
    "addr:postcode":"15810",
    "addr:street":"Arzua La Corun\u0303A",
    "iso:country":"ES",
    "sg:address":"Poligono De Arzua, 10",
    "sg:city":"Arzua",
    "sg:orig_category":"Agentes, Concesionarios Y Sucursales De Veh\u00cdculos",
    "sg:phone":"+34 981 50 08 06",
    "sg:postcode":"15810",
    "sg:province":"La Coru\u00f1a",
    "wof:name":"Garcia Bermudez Jose Antonio",
    "wof:placetype":"venue"
},
  "geometry": {"coordinates":[-8.1532869339,42.937625885],"type":"Point"}
}