{
  "type": "Feature",
  "properties": {
    "iso:country":"ES",
    "sg:address":"Av Hispanitat, 2",
    "sg:city":"Poblenou",
    "sg:orig_category":"Cajas De Ahorro",
    "sg:phone":"+34 937 69 19 54",
    "sg:postcode":"08397",
    "sg:province":"Barcelona",
    "sg:website":"www.caixacatalunya.es",
    "wof:name":"Caixa D'estalvis De Catalunya",
    "wof:placetype":"venue"
},
  "geometry": {"coordinates":[2.6710100174,41.6179504395],"type":"Point"}
}