{
  "type": "Feature",
  "properties": {
    "addr:full":"Calle de Ancla, 13 Isla Cristina Huelva 21410",
    "addr:housenumber":"13",
    "addr:postcode":"21410",
    "addr:street":"Calle De Ancla",
    "iso:country":"ES",
    "sg:address":"Calle de Ancla, 13",
    "sg:city":"Isla Cristina",
    "sg:orig_category":"Urbanistas",
    "sg:phone":"+34 959 34 43 87",
    "sg:postcode":"21410",
    "sg:province":"Huelva",
    "wof:name":"Irabeksa S.a.",
    "wof:placetype":"venue"
},
  "geometry": {"coordinates":[-7.3306655884,37.1939659119],"type":"Point"}
}