{
  "type": "Feature",
  "properties": {
    "addr:full":"Carrer de Rossello, 375 Barcelona Barcelona 08025",
    "addr:housenumber":"375",
    "addr:postcode":"08025",
    "addr:street":"Carrer De Rossello",
    "iso:country":"ES",
    "sg:address":"Carrer de Rossello, 375",
    "sg:city":"Barcelona",
    "sg:orig_category":"Asociaciones, Organismos Culturales Y Socioeducativos",
    "sg:phone":"+34 934 59 16 35",
    "sg:postcode":"08025",
    "sg:province":"Barcelona",
    "wof:name":"Los Quijotes Internacionales",
    "wof:placetype":"venue"
},
  "geometry": {"coordinates":[2.1698379517,41.4029273987],"type":"Point"}
}