{
  "type": "Feature",
  "properties": {
    "addr:full":"Crta. De Valencia, 110 Rena Badajoz 06715",
    "addr:housenumber":"110",
    "addr:postcode":"06715",
    "addr:street":"Crta. De Valencia",
    "iso:country":"ES",
    "sg:address":"Crta. De Valencia, 110",
    "sg:city":"Rena",
    "sg:orig_category":"Frutas Y Legumbres Frescas (al Por Mayor)",
    "sg:phone":"+34 924 83 58 03",
    "sg:postcode":"06715",
    "sg:province":"Badajoz",
    "wof:name":"Candido Alcudia Ramirez Y Otro Cdad.",
    "wof:placetype":"venue"
},
  "geometry": {"coordinates":[-5.8068180084,39.0528717041],"type":"Point"}
}