{
  "type": "Feature",
  "properties": {
    "addr:full":"Ctra. Nacional Vi Antigua, 6 S. Miguel Due\u00f1as Le\u00f3n 24398",
    "addr:housenumber":"6",
    "addr:postcode":"24398",
    "addr:street":"Ctra. Nacional Vi Antigua;S. Miguel Duen\u0303As Leo\u0301N",
    "iso:country":"ES",
    "sg:address":"Ctra. Nacional Vi Antigua, 6",
    "sg:city":"S. Miguel Due\u00f1as",
    "sg:orig_category":"Artes Gr\u00c1ficas, Artes Pl\u00c1sticas (curso)",
    "sg:phone":"+34 987 46 72 25",
    "sg:postcode":"24398",
    "sg:province":"Le\u00f3n",
    "wof:name":"Dieguez Luengo Luis Francisco",
    "wof:placetype":"venue"
},
  "geometry": {"coordinates":[-6.5209589005,42.617225647],"type":"Point"}
}