{
  "type": "Feature",
  "properties": {
    "iso:country":"ES",
    "sg:address":"Rua Gaivota, 13",
    "sg:city":"Vigo",
    "sg:orig_category":"Centros De Educaci\u00d3n Especial",
    "sg:phone":"+34 986 27 47 87",
    "sg:postcode":"36205",
    "sg:province":"Pontevedra",
    "wof:name":"Colexio Publico Doblada",
    "wof:placetype":"venue"
},
  "geometry": {"coordinates":[-8.7061491013,42.2254180908],"type":"Point"}
}