{
  "type": "Feature",
  "properties": {
    "iso:country":"ES",
    "sg:address":"Calle de San Jose, 2",
    "sg:city":"Portugalete",
    "sg:orig_category":"Peluquer\u00cdas, Peluquer\u00cda Mixta",
    "sg:phone":"+34 944 83 94 61",
    "sg:postcode":"48920",
    "sg:province":"Vizcaya",
    "wof:name":"Oscar Ledesma Ledesma",
    "wof:placetype":"venue"
},
  "geometry": {"coordinates":[-3.024075985,43.3176116943],"type":"Point"}
}