{
  "type": "Feature",
  "properties": {
    "iso:country":"ES",
    "sg:address":"Calle de Democracia, 4",
    "sg:city":"Valladolid",
    "sg:orig_category":"Prot\u00c9sicos Dentales",
    "sg:phone":"+34 983 26 23 58",
    "sg:postcode":"47011",
    "sg:province":"Valladolid",
    "wof:name":"Esbeldent S.l.",
    "wof:placetype":"venue"
},
  "geometry": {"coordinates":[-4.7202301025,41.6578788757],"type":"Point"}
}