{
  "type": "Feature",
  "properties": {
    "iso:country":"ES",
    "sg:address":"Ctra Acc Estacion Ferrocarril, S/n",
    "sg:city":"Tavernes Valldigna",
    "sg:orig_category":"Lacadores",
    "sg:phone":"+34 962 83 72 87",
    "sg:postcode":"46760",
    "sg:province":"Valencia",
    "wof:name":"Gascon Grau Armando",
    "wof:placetype":"venue"
},
  "geometry": {"coordinates":[-0.2594090104,39.0749702454],"type":"Point"}
}