{
  "type": "Feature",
  "properties": {
    "iso:country":"ES",
    "sg:address":"Avda Zunzunegui Juan Antonio, 6",
    "sg:city":"Bilbao",
    "sg:orig_category":"Molduras, Junquillos, Listones Y Molduras Perforadas",
    "sg:phone":"+34 944 41 30 70",
    "sg:postcode":"48013",
    "sg:province":"Vizcaya",
    "wof:name":"Mangas Lopez Gregorio",
    "wof:placetype":"venue"
},
  "geometry": {"coordinates":[-2.9473209381,43.2609024048],"type":"Point"}
}