{
  "type": "Feature",
  "properties": {
    "iso:country":"ES",
    "sg:address":"Carrer de Sant Joan, 100",
    "sg:city":"Manlleu",
    "sg:orig_category":"Notarios",
    "sg:phone":"+34 938 50 60 77",
    "sg:postcode":"08560",
    "sg:province":"Barcelona",
    "wof:name":"Fernandez Piera Alvaro",
    "wof:placetype":"venue"
},
  "geometry": {"coordinates":[2.2856709957,42.0021209717],"type":"Point"}
}