{
  "type": "Feature",
  "properties": {
    "addr:full":"Calle de Berastegui, 4 Bilbao Vizcaya 48001",
    "addr:housenumber":"4",
    "addr:postcode":"48001",
    "addr:street":"Calle De Berastegui",
    "iso:country":"ES",
    "sg:address":"Calle de Berastegui, 4",
    "sg:city":"Bilbao",
    "sg:orig_category":"Caf\u00c9s, Bares, Cervecer\u00cdas",
    "sg:phone":"+34 944 24 90 59",
    "sg:postcode":"48001",
    "sg:province":"Vizcaya",
    "wof:name":"Cafes Unidos S.a.",
    "wof:placetype":"venue"
},
  "geometry": {"coordinates":[-2.9279406071,43.2622909546],"type":"Point"}
}