{
  "type": "Feature",
  "properties": {
    "addr:full":"Avda Juan Carlos I, 12 Campo Abajo Murcia 30510",
    "addr:housenumber":"12",
    "addr:postcode":"30510",
    "addr:street":"Avda Juan Carlos I",
    "iso:country":"ES",
    "sg:address":"Avda Juan Carlos I, 12",
    "sg:city":"Campo Abajo",
    "sg:orig_category":"Centros Empresariales",
    "sg:phone":"+34 968 75 27 29",
    "sg:postcode":"30510",
    "sg:province":"Murcia",
    "wof:name":"Barcelo Relax System S.l.",
    "wof:placetype":"venue"
},
  "geometry": {"coordinates":[-1.1149940491,38.6145591736],"type":"Point"}
}