{
  "type": "Feature",
  "properties": {
    "iso:country":"ES",
    "sg:address":"Calle de Romero, S/n",
    "sg:city":"Castellar Frontera",
    "sg:orig_category":"Institutos M\u00c9dicos",
    "sg:phone":"+34 956 69 33 07",
    "sg:postcode":"11350",
    "sg:province":"C\u00e1diz",
    "wof:name":"Servicio Andaluz De Salud",
    "wof:placetype":"venue"
},
  "geometry": {"coordinates":[-5.4211540222,36.2858009338],"type":"Point"}
}