{
  "type": "Feature",
  "properties": {
    "iso:country":"ES",
    "sg:address":"Cami Fondo, 2",
    "sg:city":"Burriana",
    "sg:orig_category":"Transportes Por Carretera: Lotes Completos, Mercanc\u00cdas Diversas",
    "sg:phone":"+34 964 51 79 27",
    "sg:postcode":"12530",
    "sg:province":"Castell\u00f3n",
    "wof:name":"Exclusivas Esteller S.l.",
    "wof:placetype":"venue"
},
  "geometry": {"coordinates":[-0.0666579977,39.8693275452],"type":"Point"}
}