{
  "type": "Feature",
  "properties": {
    "iso:country":"ES",
    "sg:address":"Carrer de Santa Maria Rosa Molas (de), 2",
    "sg:city":"Tortosa",
    "sg:orig_category":"Periodistas Profesionales",
    "sg:phone":"+34 977 51 06 01",
    "sg:postcode":"43500",
    "sg:province":"Tarragona",
    "wof:name":"La Veu De L'ebre S.l.",
    "wof:placetype":"venue"
},
  "geometry": {"coordinates":[0.5109828711,40.826461792],"type":"Point"}
}