{
  "type": "Feature",
  "properties": {
    "iso:country":"ES",
    "sg:address":"Rbla Guipuscoa, 120",
    "sg:city":"Barcelona",
    "sg:orig_category":"Servicio De Salud",
    "sg:phone":"+34 933 13 08 68",
    "sg:postcode":"08020",
    "sg:province":"Barcelona",
    "wof:name":"Cocinas Y Ba\u00f1os Pineda S.c.p.",
    "wof:placetype":"venue"
},
  "geometry": {"coordinates":[2.2027099133,41.4202308655],"type":"Point"}
}