{
  "type": "Feature",
  "properties": {
    "iso:country":"ES",
    "sg:address":"Calle de Cabo Rufino Lazaro, 16",
    "sg:city":"Rozas De Madrid",
    "sg:orig_category":"Agentes, Concesionarios Y Sucursales De Veh\u00cdculos",
    "sg:phone":"+34 916 37 46 70",
    "sg:postcode":"28230",
    "sg:province":"Madrid",
    "wof:name":"Talleres Besaljo S. A.",
    "wof:placetype":"venue"
},
  "geometry": {"coordinates":[-3.8873970509,40.4977912903],"type":"Point"}
}