{
  "type": "Feature",
  "properties": {
    "addr:full":"Carrer de Arago, 10 Mataro Barcelona 08303",
    "addr:housenumber":"10",
    "addr:postcode":"08303",
    "addr:street":"Carrer De Arago",
    "iso:country":"ES",
    "sg:address":"Carrer de Arago, 10",
    "sg:city":"Mataro",
    "sg:orig_category":"Fabricaci\u00d3n De Su\u00c9ters Y Chalecos De Punto",
    "sg:phone":"+34 937 99 72 07",
    "sg:postcode":"08303",
    "sg:province":"Barcelona",
    "wof:name":"Holguin Cruceras Juan",
    "wof:placetype":"venue"
},
  "geometry": {"coordinates":[2.4246098995,41.5358123779],"type":"Point"}
}