{
  "type": "Feature",
  "properties": {
    "addr:full":"Calle de Pico Balaitus, 40 Madrid Madrid 28035",
    "addr:housenumber":"40",
    "addr:postcode":"madrid;28035",
    "addr:street":"Calle De Pico Balaitus",
    "iso:country":"ES",
    "sg:address":"Calle de Pico Balaitus, 40",
    "sg:city":"Madrid",
    "sg:orig_category":"Panader\u00cdas, Panader\u00cdas",
    "sg:phone":"+34 917 30 61 68",
    "sg:postcode":"28035",
    "sg:province":"Madrid",
    "wof:name":"Pastelerias Jamayca S.l.",
    "wof:placetype":"venue"
},
  "geometry": {"coordinates":[-3.7206530571,40.484413147],"type":"Point"}
}