{
  "type": "Feature",
  "properties": {
    "addr:full":"Pase General Davila, 140 Santander Cantabria 39006",
    "addr:housenumber":"140",
    "addr:postcode":"39006",
    "iso:country":"ES",
    "sg:address":"Pase General Davila, 140",
    "sg:city":"Santander",
    "sg:orig_category":"Institutos De Belleza",
    "sg:phone":"+34 942 21 88 61",
    "sg:postcode":"39006",
    "sg:province":"Cantabria",
    "wof:name":"Demetrio Zabala Nuria",
    "wof:placetype":"venue"
},
  "geometry": {"coordinates":[-3.8071200848,43.4673156738],"type":"Point"}
}