{
  "type": "Feature",
  "properties": {
    "addr:full":"Avda Ronda, S/n Laguna Duero Valladolid 47140",
    "addr:housenumber":"/ n",
    "addr:postcode":"47140",
    "addr:street":"Avda Ronda S",
    "iso:country":"ES",
    "sg:address":"Avda Ronda, S/n",
    "sg:city":"Laguna Duero",
    "sg:orig_category":"Neum\u00c1ticos (fabricaci\u00d3n, Al Por Mayor)",
    "sg:phone":"+34 983 52 61 77",
    "sg:postcode":"47140",
    "sg:province":"Valladolid",
    "wof:name":"Neumaticos Carrion S. A.",
    "wof:placetype":"venue"
},
  "geometry": {"coordinates":[-4.7315201759,41.5869483948],"type":"Point"}
}