{
  "type": "Feature",
  "properties": {
    "iso:country":"ES",
    "sg:address":"Calle de Timagan, 24",
    "sg:city":"Palmas De Gran Canaria",
    "sg:orig_category":"Estancos",
    "sg:phone":"+34 928 46 78 18",
    "sg:postcode":"35009",
    "sg:province":"Las Palmas",
    "wof:name":"Betancor Rodriguez Bernardino",
    "wof:placetype":"venue"
},
  "geometry": {"coordinates":[-15.4310588837,28.151550293],"type":"Point"}
}