{
  "type": "Feature",
  "properties": {
    "iso:country":"ES",
    "sg:address":"Avda Malaga, 28",
    "sg:city":"Ronda",
    "sg:orig_category":"Maquinaria Para Industrias Diversas",
    "sg:phone":"+34 952 87 06 35",
    "sg:postcode":"29400",
    "sg:province":"M\u00e1laga",
    "wof:name":"Manuel Gonzalez Rios Y Jose Antonio Gonzalez Rios",
    "wof:placetype":"venue"
},
  "geometry": {"coordinates":[-5.1545090675,36.7487564087],"type":"Point"}
}