{
  "type": "Feature",
  "properties": {
    "addr:full":"Calle de Pilon De Luis, 38 Barraco \u00c1vila 05110",
    "addr:housenumber":"38",
    "addr:postcode":"05110",
    "addr:street":"Calle De Pilon De Luis",
    "iso:country":"ES",
    "sg:address":"Calle de Pilon De Luis, 38",
    "sg:city":"Barraco",
    "sg:orig_category":"Bancos",
    "sg:phone":"+34 920 28 10 56",
    "sg:postcode":"05110",
    "sg:province":"\u00c1vila",
    "wof:name":"Banco Espa\u00d1ol De Credito S.a.",
    "wof:placetype":"venue"
},
  "geometry": {"coordinates":[-4.6420230865,40.4772796631],"type":"Point"}
}