{
  "type": "Feature",
  "properties": {
    "iso:country":"ES",
    "sg:address":"Pl Nova, 5",
    "sg:city":"Alaior",
    "sg:orig_category":"Peluqueros: De Se\u00d1oras",
    "sg:phone":"+34 971 37 11 29",
    "sg:postcode":"07730",
    "sg:province":"Islas Baleares",
    "wof:name":"Tomas Riudavets Maria Juana",
    "wof:placetype":"venue"
},
  "geometry": {"coordinates":[4.1353411674,39.9319038391],"type":"Point"}
}