{
  "type": "Feature",
  "properties": {
    "addr:full":"Calle de Antonio De La Cadena, S/n Plasencia C\u00e1ceres 10600",
    "addr:housenumber":"s",
    "addr:postcode":"10600",
    "addr:street":"Calle De Antonio De La Cadena;/ N;Ca\u0301Ceres",
    "iso:country":"ES",
    "sg:address":"Calle de Antonio De La Cadena, S/n",
    "sg:city":"Plasencia",
    "sg:orig_category":"Transportes Especiales",
    "sg:phone":"+34 927 41 25 28",
    "sg:postcode":"10600",
    "sg:province":"C\u00e1ceres",
    "wof:name":"Garcia Garcia Casimiro",
    "wof:placetype":"venue"
},
  "geometry": {"coordinates":[-6.0847945213,40.0301551819],"type":"Point"}
}