{
  "type": "Feature",
  "properties": {
    "addr:full":"Pla\u00c7 Ajuntament (de L'), 7 Sueca Valencia 46410",
    "addr:housenumber":"7",
    "addr:postcode":"46410",
    "addr:street":"'",
    "iso:country":"ES",
    "sg:address":"Pla\u00c7 Ajuntament (de L'), 7",
    "sg:city":"Sueca",
    "sg:orig_category":"Bancos",
    "sg:phone":"+34 961 70 02 67",
    "sg:postcode":"46410",
    "sg:province":"Valencia",
    "wof:name":"Banco Espa\u00d1ol De Credito S.a.",
    "wof:placetype":"venue"
},
  "geometry": {"coordinates":[-0.3076440096,39.2027435303],"type":"Point"}
}