{
  "type": "Feature",
  "properties": {
    "addr:full":"Calle de Extremadura, 13 Vitoria-gasteiz \u00c1lava 01003",
    "addr:housenumber":"13",
    "addr:postcode":"01003",
    "addr:street":"Calle De Extremadura",
    "iso:country":"ES",
    "sg:address":"Calle de Extremadura, 13",
    "sg:city":"Vitoria-gasteiz",
    "sg:orig_category":"Reposter\u00cdas",
    "sg:phone":"+34 945 25 03 15",
    "sg:postcode":"01003",
    "sg:province":"\u00c1lava",
    "wof:name":"Pan Santa Maria S.a.",
    "wof:placetype":"venue"
},
  "geometry": {"coordinates":[-2.6601259708,42.8491668701],"type":"Point"}
}