{
  "type": "Feature",
  "properties": {
    "iso:country":"ES",
    "sg:address":"Avda Salvador De Madariaga, 66",
    "sg:city":"Coru\u00d1a",
    "sg:orig_category":"Agencias Y Agentes Comerciales, Representantes",
    "sg:phone":"+34 981 13 00 05",
    "sg:postcode":"15008",
    "sg:province":"La Coru\u00f1a",
    "wof:name":"Busnode S.l.",
    "wof:placetype":"venue"
},
  "geometry": {"coordinates":[-8.4069318771,43.3454284668],"type":"Point"}
}