{
  "type": "Feature",
  "properties": {
    "iso:country":"ES",
    "sg:address":"Calle de Condesa De Venadito, 20",
    "sg:city":"Madrid",
    "sg:orig_category":"Laboratorios Y Cl\u00cdnicas Veterinarias",
    "sg:phone":"+34 913 26 70 90",
    "sg:postcode":"28027",
    "sg:province":"Madrid",
    "wof:name":"Escribanbo Gutierrez Miguel",
    "wof:placetype":"venue"
},
  "geometry": {"coordinates":[-3.6506729126,40.4459152222],"type":"Point"}
}