{
  "type": "Feature",
  "properties": {
    "addr:full":"Barr Monte Corbanera, S/n Monte Cantabria 39012",
    "addr:housenumber":"s / n",
    "addr:postcode":"39012",
    "addr:street":"Corbanera",
    "iso:country":"ES",
    "sg:address":"Barr Monte Corbanera, S/n",
    "sg:city":"Monte",
    "sg:orig_category":"Organismos De Investigaciones Cient\u00cdficas Y T\u00c9cnicas",
    "sg:phone":"+34 942 32 44 83",
    "sg:postcode":"39012",
    "sg:province":"Cantabria",
    "wof:name":"Instituto Nacional Oceanografico",
    "wof:placetype":"venue"
},
  "geometry": {"coordinates":[-3.8604888916,43.4665527344],"type":"Point"}
}