{
  "type": "Feature",
  "properties": {
    "iso:country":"ES",
    "sg:address":"Rua Colon, 17",
    "sg:city":"Vigo",
    "sg:orig_category":"Inmobiliaria (agencias)",
    "sg:phone":"+34 986 43 58 66",
    "sg:postcode":"36201",
    "sg:province":"Pontevedra",
    "wof:name":"Subcomunidad De Propietarios Calle Colon 17",
    "wof:placetype":"venue"
},
  "geometry": {"coordinates":[-8.7200651169,42.2374763489],"type":"Point"}
}