{
  "type": "Feature",
  "properties": {
    "iso:country":"ES",
    "sg:address":"Carrer de Bon Viatge, 34",
    "sg:city":"S. Joan Despi",
    "sg:orig_category":"Lencer\u00cda Femenina, Corseter\u00cda, Trajes De Ba\u00d1o (al Por Menor)",
    "sg:phone":"+34 933 73 59 03",
    "sg:postcode":"08970",
    "sg:province":"Barcelona",
    "wof:name":"Jimenez Hervas Enrique",
    "wof:placetype":"venue"
},
  "geometry": {"coordinates":[2.057954073,41.3655052185],"type":"Point"}
}