{
  "type": "Feature",
  "properties": {
    "iso:country":"ES",
    "sg:address":"Calle de Concepcion Arenal, 3",
    "sg:city":"Madrid",
    "sg:orig_category":"Caf\u00c9s, Bares, Cervecer\u00cdas",
    "sg:phone":"+34 915 22 05 07",
    "sg:postcode":"28004",
    "sg:province":"Madrid",
    "wof:name":"Establecimientos Lugor S.a.",
    "wof:placetype":"venue"
},
  "geometry": {"coordinates":[-3.7048523426,40.4204292297],"type":"Point"}
}