{
  "type": "Feature",
  "properties": {
    "iso:country":"ES",
    "sg:address":"Carretera General, Km. 0029,0",
    "sg:city":"Galdar",
    "sg:orig_category":"Electricidad Veh\u00cdculo",
    "sg:phone":"+34 928 88 07 76",
    "sg:postcode":"35460",
    "sg:province":"Las Palmas",
    "wof:name":"Aguilar Medina Benjamin",
    "wof:placetype":"venue"
},
  "geometry": {"coordinates":[-15.6566295624,28.1407356262],"type":"Point"}
}