{
  "type": "Feature",
  "properties": {
    "addr:full":"Calle de Abajo, 2 Pradorrey Le\u00f3n 24714",
    "addr:housenumber":"2",
    "addr:postcode":"24714",
    "addr:street":"Calle De Abajo;Leo\u0301N",
    "iso:country":"ES",
    "sg:address":"Calle de Abajo, 2",
    "sg:city":"Pradorrey",
    "sg:orig_category":"Ebanister\u00cda",
    "sg:phone":"+34 987 60 65 62",
    "sg:postcode":"24714",
    "sg:province":"Le\u00f3n",
    "wof:name":"Polo Huesca Emilio",
    "wof:placetype":"venue"
},
  "geometry": {"coordinates":[-6.1200070381,42.4951896667],"type":"Point"}
}