{
  "type": "Feature",
  "properties": {
    "iso:country":"ES",
    "sg:address":"Calle de Jose Antonio Primo De Rivera, 21",
    "sg:city":"Arrecife",
    "sg:orig_category":"Ense\u00d1anza: Profesiones Art\u00cdsticas",
    "sg:phone":"+34 928 81 13 86",
    "sg:postcode":"35500",
    "sg:province":"Las Palmas",
    "wof:name":"Lasso Clavijo Alberto",
    "wof:placetype":"venue"
},
  "geometry": {"coordinates":[-13.5511217117,28.9595088959],"type":"Point"}
}