{
  "type": "Feature",
  "properties": {
    "iso:country":"ES",
    "sg:address":"Calle de Mercurio (pol. Ind.), 20",
    "sg:city":"Marbella",
    "sg:orig_category":"Tapicer\u00cdas",
    "sg:phone":"+34 952 86 56 99",
    "sg:postcode":"29600",
    "sg:province":"M\u00e1laga",
    "wof:name":"Soltapi S.l.",
    "wof:placetype":"venue"
},
  "geometry": {"coordinates":[-4.8679871559,36.5122833252],"type":"Point"}
}