{
  "type": "Feature",
  "properties": {
    "iso:country":"ES",
    "sg:address":"Calle de Infanta Mercedes, 2",
    "sg:city":"Madrid",
    "sg:orig_category":"Zapatos (al Por Menor)",
    "sg:phone":"+34 915 72 33 16",
    "sg:postcode":"28020",
    "sg:province":"Madrid",
    "wof:name":"Internacional De Sonido S.l.",
    "wof:placetype":"venue"
},
  "geometry": {"coordinates":[-3.6991200447,40.4528808594],"type":"Point"}
}