{
  "type": "Feature",
  "properties": {
    "addr:full":"Plaz Musico Albeniz, 8 Valencia Valencia 46010",
    "addr:housenumber":"8",
    "addr:postcode":"46010",
    "addr:street":"Plaz Musico Albeniz",
    "iso:country":"ES",
    "sg:address":"Plaz Musico Albeniz, 8",
    "sg:city":"Valencia",
    "sg:orig_category":"Arquitectos",
    "sg:phone":"+34 963 69 05 69",
    "sg:postcode":"46010",
    "sg:province":"Valencia",
    "wof:name":"Escario Martinez Antonio",
    "wof:placetype":"venue"
},
  "geometry": {"coordinates":[-0.364158988,39.4834594727],"type":"Point"}
}