{
  "type": "Feature",
  "properties": {
    "iso:country":"ES",
    "sg:address":"Calle de Teodoro Murua, 6",
    "sg:city":"Irun",
    "sg:orig_category":"Molduras, Junquillos, Listones Y Molduras Perforadas",
    "sg:phone":"+34 943 62 05 95",
    "sg:postcode":"20305",
    "sg:province":"Guip\u00f9zcoa",
    "wof:name":"Prol Dospazos Miguel",
    "wof:placetype":"venue"
},
  "geometry": {"coordinates":[-1.7728489637,43.3409004211],"type":"Point"}
}