{
  "type": "Feature",
  "properties": {
    "addr:full":"Praj Batans (os), Km. 0007,0 Bertamirans La Coru\u00f1a 15220",
    "addr:postcode":"15220",
    "addr:street":"Os Km. 0007,0 Bertamirans La Corun\u0303A",
    "iso:country":"ES",
    "sg:address":"Praj Batans (os), Km. 0007,0",
    "sg:city":"Bertamirans",
    "sg:orig_category":"Mec\u00c1nico Del Autom\u00d3vil",
    "sg:phone":"+34 981 88 37 00",
    "sg:postcode":"15220",
    "sg:province":"La Coru\u00f1a",
    "wof:name":"Auto Continental De Vehiculos S.l.",
    "wof:placetype":"venue"
},
  "geometry": {"coordinates":[-8.6504335403,42.8610572815],"type":"Point"}
}