{
  "type": "Feature",
  "properties": {
    "iso:country":"ES",
    "sg:address":"Calle de Cruces (las), 22",
    "sg:city":"Almeria",
    "sg:orig_category":"Servicios Diversos",
    "sg:phone":"+34 950 23 27 33",
    "sg:postcode":"04003",
    "sg:province":"Almer\u00eda",
    "wof:name":"Sociedad Protectora De Animales Y Plantas Alondra Dupont",
    "wof:placetype":"venue"
},
  "geometry": {"coordinates":[-2.4630041122,36.8437995911],"type":"Point"}
}