{
  "type": "Feature",
  "properties": {
    "addr:full":"Calle de Doctor Felix Rodriguez De La Fuente, 8 Palmar De Troya Sevilla 41719",
    "addr:housenumber":"8",
    "addr:postcode":"41719",
    "addr:street":"Calle De Doctor Felix Rodriguez De La Fuente",
    "iso:country":"ES",
    "sg:address":"Calle de Doctor Felix Rodriguez De La Fuente, 8",
    "sg:city":"Palmar De Troya",
    "sg:orig_category":"Cajas Para Embalar",
    "sg:phone":"+34 955 83 25 47",
    "sg:postcode":"41719",
    "sg:province":"Sevilla",
    "wof:name":"Caja Rural De Utrera",
    "wof:placetype":"venue"
},
  "geometry": {"coordinates":[-5.80585289,37.0636672974],"type":"Point"}
}