{
  "type": "Feature",
  "properties": {
    "iso:country":"ES",
    "sg:address":"Ctra Huelva-sevilla, 630",
    "sg:city":"Huelva",
    "sg:orig_category":"Energ\u00cda Solar Y Nuevas Energ\u00cdas (equipo, Estudios)",
    "sg:phone":"+34 959 22 15 14",
    "sg:postcode":"21006",
    "sg:province":"Huelva",
    "wof:name":"Climaseg Servicios Industriales S.l.",
    "wof:placetype":"venue"
},
  "geometry": {"coordinates":[-6.9094891548,37.273651123],"type":"Point"}
}