{
  "type": "Feature",
  "properties": {
    "addr:full":"Avda Celanova (de), 5 Valenza Ourense 32002",
    "addr:housenumber":"5",
    "addr:postcode":"32002",
    "addr:street":"Avda Celanova De",
    "iso:country":"ES",
    "sg:address":"Avda Celanova (de), 5",
    "sg:city":"Valenza",
    "sg:orig_category":"Promotores Constructores",
    "sg:phone":"+34 988 23 81 45",
    "sg:postcode":"32002",
    "sg:province":"Ourense",
    "wof:name":"Comunidad De Propietarios Avenida Celanova 7a",
    "wof:placetype":"venue"
},
  "geometry": {"coordinates":[-7.8815789223,42.3213310242],"type":"Point"}
}