{
  "type": "Feature",
  "properties": {
    "iso:country":"ES",
    "sg:address":"Avda Lorenzo Pardo, S/n",
    "sg:city":"Fuentes Ebro",
    "sg:orig_category":"Empresas De Carpinter\u00cda De Madera",
    "sg:phone":"+34 976 16 04 17",
    "sg:postcode":"50740",
    "sg:province":"Zaragoza",
    "wof:name":"Comin Sampietro Bernabe",
    "wof:placetype":"venue"
},
  "geometry": {"coordinates":[-0.6219940186,41.5129013062],"type":"Point"}
}