{
  "type": "Feature",
  "properties": {
    "iso:country":"ES",
    "sg:address":"Calle de Comercio, 4",
    "sg:city":"Rincon Victoria",
    "sg:orig_category":"Asilos De Ancianos. Centros Privados",
    "sg:phone":"+34 952 97 35 90",
    "sg:postcode":"29730",
    "sg:province":"M\u00e1laga",
    "wof:name":"Ramos Espina Fabiana",
    "wof:placetype":"venue"
},
  "geometry": {"coordinates":[-4.284717083,36.7160987854],"type":"Point"}
}