{
  "type": "Feature",
  "properties": {
    "addr:full":"Plza Juan Carlos I, 2 Monzon Huesca 22400",
    "addr:housenumber":"2",
    "addr:postcode":"22400",
    "addr:street":"Juan Carlos I",
    "iso:country":"ES",
    "sg:address":"Plza Juan Carlos I, 2",
    "sg:city":"Monzon",
    "sg:orig_category":"Promotores Constructores",
    "sg:phone":"+34 974 40 42 98",
    "sg:postcode":"22400",
    "sg:province":"Huesca",
    "wof:name":"Cortes Santiago Antonio",
    "wof:placetype":"venue"
},
  "geometry": {"coordinates":[0.1915819943,41.9130134583],"type":"Point"}
}