{
  "type": "Feature",
  "properties": {
    "iso:country":"ES",
    "sg:address":"Calle de Estigmatinas, 11",
    "sg:city":"Astorga",
    "sg:orig_category":"Internados & Ense\u00d1anza Privada",
    "sg:phone":"+34 987 61 61 69",
    "sg:postcode":"24700",
    "sg:province":"Le\u00f3n",
    "sg:website":"www.vcandelas.org",
    "wof:name":"Colegio Infantil Virgen De Las Candelas",
    "wof:placetype":"venue"
},
  "geometry": {"coordinates":[-6.0637841225,42.4612197876],"type":"Point"}
}