{
  "type": "Feature",
  "properties": {
    "addr:full":"Calle de Juan Martin El Empecinado, 11 Pe\u00f1afiel Valladolid 47300",
    "addr:housenumber":"11",
    "addr:postcode":"47300",
    "addr:street":"Calle De Juan Martin El Empecinado",
    "iso:country":"ES",
    "sg:address":"Calle de Juan Martin El Empecinado, 11",
    "sg:city":"Pe\u00f1afiel",
    "sg:orig_category":"\u00d3ptica: Instrumentos (fabricaci\u00d3n)",
    "sg:phone":"+34 983 88 17 20",
    "sg:postcode":"47300",
    "sg:province":"Valladolid",
    "wof:name":"Optica Pe\u00f1afiel S.l.",
    "wof:placetype":"venue"
},
  "geometry": {"coordinates":[-4.1158537865,41.6017112732],"type":"Point"}
}