{
  "type": "Feature",
  "properties": {
    "iso:country":"ES",
    "sg:address":"Calle de Manolo Escobar, 31",
    "sg:city":"Ejido",
    "sg:orig_category":"Frutas, Legumbres Frescas Y Tempranas (al Por Menor)",
    "sg:phone":"+34 950 48 15 80",
    "sg:postcode":"04700",
    "sg:province":"Almer\u00eda",
    "wof:name":"Romero Ruiz Juan",
    "wof:placetype":"venue"
},
  "geometry": {"coordinates":[-2.8192129135,36.7740936279],"type":"Point"}
}