{
  "type": "Feature",
  "properties": {
    "addr:full":"Pl Ajuntament (l'), S/n Campello Alicante 03560",
    "addr:housenumber":"s / n",
    "addr:postcode":"03560",
    "addr:street":"Pl Ajuntament L '",
    "iso:country":"ES",
    "sg:address":"Pl Ajuntament (l'), S/n",
    "sg:city":"Campello",
    "sg:orig_category":"Cajas De Ahorro",
    "sg:phone":"+34 965 63 20 98",
    "sg:postcode":"03560",
    "sg:province":"Alicante",
    "sg:website":"www.cajamurcia.es",
    "wof:name":"Caja De Ahorros De Murcia",
    "wof:placetype":"venue"
},
  "geometry": {"coordinates":[-0.3985289931,38.4266014099],"type":"Point"}
}