{
  "type": "Feature",
  "properties": {
    "addr:full":"C/ Jose Maria Peman, 42 Elche Alicante 03201",
    "addr:housenumber":"42",
    "addr:postcode":"03201",
    "addr:street":"C / Jose Maria Peman",
    "iso:country":"ES",
    "sg:address":"C/ Jose Maria Peman, 42",
    "sg:city":"Elche",
    "sg:orig_category":"Abogados",
    "sg:phone":"+34 965 46 74 85",
    "sg:postcode":"03201",
    "sg:province":"Alicante",
    "wof:name":"Martinez Casta\u00f1o Juan",
    "wof:placetype":"venue"
},
  "geometry": {"coordinates":[-0.704128027,38.2633361816],"type":"Point"}
}