{
  "type": "Feature",
  "properties": {
    "addr:full":"Rond Muralla (da), 5 Lugo Lugo 27001",
    "addr:postcode":"27001",
    "addr:street":"Rond;Da",
    "iso:country":"ES",
    "sg:address":"Rond Muralla (da), 5",
    "sg:city":"Lugo",
    "sg:orig_category":"Administradores De Bienes Y Delegados De Comunidades De Propietarios",
    "sg:phone":"+34 982 25 40 25",
    "sg:postcode":"27001",
    "sg:province":"Lugo",
    "sg:website":"www.inmobiliariaronda.com",
    "wof:name":"Trigo Ronda S.l.",
    "wof:placetype":"venue"
},
  "geometry": {"coordinates":[-7.5537691116,43.0094108582],"type":"Point"}
}