{
  "type": "Feature",
  "properties": {
    "addr:full":"Calle de Rector Benito Rodriguez Rios, 5 Tope Santa Cruz De Tenerife 38400",
    "addr:housenumber":"5",
    "addr:postcode":"38400",
    "addr:street":"Calle De Rector Benito Rodriguez Rios",
    "iso:country":"ES",
    "sg:address":"Calle de Rector Benito Rodriguez Rios, 5",
    "sg:city":"Tope",
    "sg:orig_category":"Doctores En Medicina",
    "sg:phone":"+34 922 37 03 33",
    "sg:postcode":"38400",
    "sg:province":"Santa Cruz De Tenerife",
    "wof:name":"Marrero Garcia De Vinuesa Jose Luis",
    "wof:placetype":"venue"
},
  "geometry": {"coordinates":[-16.5422592163,28.4119586945],"type":"Point"}
}