{
  "type": "Feature",
  "properties": {
    "iso:country":"ES",
    "sg:address":"Avda Rio Boladiez, S/n",
    "sg:city":"Poligono Sta M. De Benquerencia",
    "sg:orig_category":"Zapatos (al Por Menor)",
    "sg:phone":"+34 925 24 04 45",
    "sg:postcode":"45007",
    "sg:province":"Toledo",
    "wof:name":"Tilopa S.l.l.",
    "wof:placetype":"venue"
},
  "geometry": {"coordinates":[-3.9338080883,39.8714675903],"type":"Point"}
}