{
  "type": "Feature",
  "properties": {
    "iso:country":"ES",
    "sg:address":"Plaz Bustamante, 1",
    "sg:city":"Motril",
    "sg:orig_category":"Arquitectos",
    "sg:phone":"+34 958 60 08 48",
    "sg:postcode":"18600",
    "sg:province":"Granada",
    "wof:name":"Herrera Fuentes Alberto",
    "wof:placetype":"venue"
},
  "geometry": {"coordinates":[-3.5177440643,36.7453994751],"type":"Point"}
}