{
  "type": "Feature",
  "properties": {
    "addr:full":"Calle de Constitucion (de La), 32 Alcobendas Madrid 28100",
    "addr:housenumber":"32",
    "addr:postcode":"28100",
    "addr:street":"Calle De Constitucion De La",
    "iso:country":"ES",
    "sg:address":"Calle de Constitucion (de La), 32",
    "sg:city":"Alcobendas",
    "sg:orig_category":"Muebles, Minoristas",
    "sg:phone":"+34 916 51 99 46",
    "sg:postcode":"28100",
    "sg:province":"Madrid",
    "wof:name":"Sanchez Del Alamo Manuel",
    "wof:placetype":"venue"
},
  "geometry": {"coordinates":[-3.6361262798,40.5423240662],"type":"Point"}
}