{
  "type": "Feature",
  "properties": {
    "iso:country":"ES",
    "sg:address":"Calle de Gilena, 1",
    "sg:city":"Madrid",
    "sg:orig_category":"Librer\u00cdas",
    "sg:phone":"+34 917 96 81 70",
    "sg:postcode":"28021",
    "sg:province":"Madrid",
    "wof:name":"Aguilar Orozco Rosario",
    "wof:placetype":"venue"
},
  "geometry": {"coordinates":[-3.7082984447,40.3447685242],"type":"Point"}
}