{
  "type": "Feature",
  "properties": {
    "iso:country":"ES",
    "sg:address":"Calle de Pablo Ruiz Picasso, 6",
    "sg:city":"Burgos",
    "sg:orig_category":"Bisuter\u00cda, Joyer\u00cda, Relojer\u00cda (al Por Menor)",
    "sg:phone":"+34 947 23 84 90",
    "sg:postcode":"09007",
    "sg:province":"Burgos",
    "wof:name":"Gutierrez Hermosilla Maria Del Rosario",
    "wof:placetype":"venue"
},
  "geometry": {"coordinates":[-3.6686930656,42.3525619507],"type":"Point"}
}