{
  "type": "Feature",
  "properties": {
    "iso:country":"ES",
    "sg:address":"Hirigoien Kalea, 48",
    "sg:city":"Lazkao",
    "sg:orig_category":"Transportes Por Carretera: Lotes Completos, Mercanc\u00cdas Diversas",
    "sg:phone":"+34 943 88 17 24",
    "sg:postcode":"20210",
    "sg:province":"Guip\u00f9zcoa",
    "wof:name":"Miragaya Monterroso Jose",
    "wof:placetype":"venue"
},
  "geometry": {"coordinates":[-2.1831889153,43.0273017883],"type":"Point"}
}