{
  "type": "Feature",
  "properties": {
    "addr:full":"Carr Aparadores, 7 Petrer Alicante 03610",
    "addr:housenumber":"7",
    "addr:postcode":"03610",
    "addr:street":"Carr Aparadores",
    "iso:country":"ES",
    "sg:address":"Carr Aparadores, 7",
    "sg:city":"Petrer",
    "sg:orig_category":"Confecci\u00d3n De Zapatos",
    "sg:phone":"+34 965 37 64 17",
    "sg:postcode":"03610",
    "sg:province":"Alicante",
    "wof:name":"Calzados Juan Aparicio, S. L",
    "wof:placetype":"venue"
},
  "geometry": {"coordinates":[-0.7731289864,38.4793281555],"type":"Point"}
}