{
  "type": "Feature",
  "properties": {
    "iso:country":"ES",
    "sg:address":"Calle de Coru\u00d1a, 3",
    "sg:city":"Esfarrapada",
    "sg:orig_category":"Cr\u00cda De Animales",
    "sg:phone":"+34 986 34 79 53",
    "sg:postcode":"36470",
    "sg:province":"Pontevedra",
    "wof:name":"Romero Estevez Lucas",
    "wof:placetype":"venue"
},
  "geometry": {"coordinates":[-8.5604362488,42.1025161743],"type":"Point"}
}