{
  "type": "Feature",
  "properties": {
    "iso:country":"ES",
    "sg:address":"Calle de Esparteros, 13",
    "sg:city":"Madrid",
    "sg:orig_category":"Telas Y Sedas (al Por Menor)",
    "sg:phone":"+34 915 21 24 64",
    "sg:postcode":"28012",
    "sg:province":"Madrid",
    "wof:name":"Rocinsa S.a.",
    "wof:placetype":"venue"
},
  "geometry": {"coordinates":[-3.7053608894,40.4153442383],"type":"Point"}
}