{
  "type": "Feature",
  "properties": {
    "addr:full":"C/ Alfons I, 24 Puigcerda Girona 17520",
    "addr:housenumber":"24",
    "addr:postcode":"17520",
    "addr:street":"C / Alfons I",
    "iso:country":"ES",
    "sg:address":"C/ Alfons I, 24",
    "sg:city":"Puigcerda",
    "sg:orig_category":"Laboratorios Y Trabajos De Fotograf\u00cda, V\u00cddeo Y Cine",
    "sg:phone":"+34 972 14 00 62",
    "sg:postcode":"17520",
    "sg:province":"Girona",
    "wof:name":"Fotografia Cerdanya S.l.",
    "wof:placetype":"venue"
},
  "geometry": {"coordinates":[1.9287799597,42.4324188232],"type":"Point"}
}