{
  "type": "Feature",
  "properties": {
    "addr:full":"Pla\u00c7 Hostals (els), 9 Cabanes Castell\u00f3n 12180",
    "addr:housenumber":"9",
    "addr:postcode":"12180",
    "addr:street":"Plac\u0327;Els",
    "iso:country":"ES",
    "sg:address":"Pla\u00c7 Hostals (els), 9",
    "sg:city":"Cabanes",
    "sg:orig_category":"Promotores Constructores",
    "sg:phone":"+34 964 33 20 45",
    "sg:postcode":"12180",
    "sg:province":"Castell\u00f3n",
    "wof:name":"Promo-rest Laureano S.l.",
    "wof:placetype":"venue"
},
  "geometry": {"coordinates":[0.0448350012,40.1544303894],"type":"Point"}
}