{
  "type": "Feature",
  "properties": {
    "iso:country":"ES",
    "sg:address":"Carrer de Castillejos, 293",
    "sg:city":"Barcelona",
    "sg:orig_category":"Librer\u00cdas",
    "sg:phone":"+34 934 50 18 65",
    "sg:postcode":"08025",
    "sg:province":"Barcelona",
    "wof:name":"Soriano Collado Montserrat",
    "wof:placetype":"venue"
},
  "geometry": {"coordinates":[2.1767120361,41.4075584412],"type":"Point"}
}