{
  "type": "Feature",
  "properties": {
    "iso:country":"ES",
    "sg:address":"Calle de Constitucion, S/n",
    "sg:city":"Robledillo De Trujillo",
    "sg:classifiers":[
        {
            "category":"Taxi",
            "type":"Transportation"
        }
    ],
    "sg:phone":"+34 927 31 30 27",
    "sg:postcode":"10261",
    "sg:province":"C\u00e1ceres",
    "wof:name":"Pulido Santos Moises",
    "wof:placetype":"venue"
},
  "geometry": {"coordinates":[-5.981235981,39.2690734863],"type":"Point"}
}