{
  "type": "Feature",
  "properties": {
    "iso:country":"ES",
    "sg:address":"Avda Rey Don Jaime, 66",
    "sg:city":"Castellon",
    "sg:orig_category":"Arquitectos",
    "sg:phone":"+34 964 20 30 12",
    "sg:postcode":"12001",
    "sg:province":"Castell\u00f3n",
    "wof:name":"Querol Diago Juan Antonio",
    "wof:placetype":"venue"
},
  "geometry": {"coordinates":[-0.0390199982,39.9866409302],"type":"Point"}
}