{
  "type": "Feature",
  "properties": {
    "iso:country":"ES",
    "sg:address":"Calle de Juan Xxiii, 7",
    "sg:city":"Alaquas",
    "sg:orig_category":"Forjas Y Altos Hornos",
    "sg:phone":"+34 961 51 92 05",
    "sg:postcode":"46970",
    "sg:province":"Valencia",
    "wof:name":"Hierros Santaperpetua S.a.",
    "wof:placetype":"venue"
},
  "geometry": {"coordinates":[-0.4677059948,39.4556770325],"type":"Point"}
}