{
  "type": "Feature",
  "properties": {
    "addr:full":"Calle de Niquel, 2 Arganda Madrid 28500",
    "addr:housenumber":"2",
    "addr:postcode":"28500",
    "addr:street":"Calle De Niquel",
    "iso:country":"ES",
    "sg:address":"Calle de Niquel, 2",
    "sg:city":"Arganda",
    "sg:orig_category":"Barnizadores",
    "sg:phone":"+34 918 70 03 32",
    "sg:postcode":"28500",
    "sg:province":"Madrid",
    "wof:name":"Garcia Barquilla Pedro",
    "wof:placetype":"venue"
},
  "geometry": {"coordinates":[-3.4406979084,40.2999954224],"type":"Point"}
}