{
  "type": "Feature",
  "properties": {
    "iso:country":"ES",
    "sg:address":"Calle de Ubeda, 31",
    "sg:city":"Huetor-vega",
    "sg:orig_category":"Mantenimiento Industrial",
    "sg:phone":"+34 958 30 36 03",
    "sg:postcode":"18198",
    "sg:province":"Granada",
    "wof:name":"Mantenimiento Y Reparacion Moramar S.l.",
    "wof:placetype":"venue"
},
  "geometry": {"coordinates":[-3.5646419525,37.150138855],"type":"Point"}
}