{
  "type": "Feature",
  "properties": {
    "iso:country":"ES",
    "sg:address":"Carr Horta, 20",
    "sg:city":"Almenar",
    "sg:orig_category":"Confecci\u00d3n (fabricaci\u00d3n, Al Por Mayor)",
    "sg:phone":"+34 973 77 06 65",
    "sg:postcode":"25126",
    "sg:province":"Lleida",
    "wof:name":"Perpi\u00f1a Sales Palmira",
    "wof:placetype":"venue"
},
  "geometry": {"coordinates":[0.5695070028,41.796459198],"type":"Point"}
}