{
  "type": "Feature",
  "properties": {
    "iso:country":"ES",
    "sg:address":"Zaragoza, 137",
    "sg:city":"Juslibol",
    "sg:orig_category":"Arenas, Guijarros Y Granulados",
    "sg:phone":"+34 976 73 04 77",
    "sg:postcode":"50191",
    "sg:province":"Zaragoza",
    "wof:name":"Aridos Y Excavaciones Carmelo Lobera S.l.",
    "wof:placetype":"venue"
},
  "geometry": {"coordinates":[-0.8950241804,41.6898651123],"type":"Point"}
}