{
  "type": "Feature",
  "properties": {
    "addr:full":"Calle de Cruz, 3 Ojen M\u00e1laga 29610",
    "addr:housenumber":"3",
    "addr:postcode":"29610",
    "addr:street":"Calle De Cruz;Ma\u0301Laga",
    "iso:country":"ES",
    "sg:address":"Calle de Cruz, 3",
    "sg:city":"Ojen",
    "sg:orig_category":"Transportes De Material De Construcci\u00d3n",
    "sg:phone":"+34 952 88 10 69",
    "sg:postcode":"29610",
    "sg:province":"M\u00e1laga",
    "wof:name":"Garcia Gomez Miguel",
    "wof:placetype":"venue"
},
  "geometry": {"coordinates":[-4.8561487198,36.5646514893],"type":"Point"}
}