{
  "type": "Feature",
  "properties": {
    "iso:country":"ES",
    "sg:address":"Pase Conde De Sepulveda (del), 18",
    "sg:city":"Segovia",
    "sg:orig_category":"Ense\u00d1anza Secundaria: Colegios Y Escuelas Privadas",
    "sg:phone":"+34 921 42 05 50",
    "sg:postcode":"40002",
    "sg:province":"Segovia",
    "wof:name":"Instituto De Ense\u00f1anza Media Andres Laguna",
    "wof:placetype":"venue"
},
  "geometry": {"coordinates":[-4.115073204,40.9383888245],"type":"Point"}
}