{
  "type": "Feature",
  "properties": {
    "iso:country":"ES",
    "sg:address":"Valle Aranguren, 4",
    "sg:city":"Iru\u00f1a",
    "sg:orig_category":"Audiovisuales, Tv, Hi",
    "sg:phone":"+34 948 24 17 97",
    "sg:postcode":"31006",
    "sg:province":"Navarra",
    "wof:name":"Audiovisuales Natecno S.l.",
    "wof:placetype":"venue"
},
  "geometry": {"coordinates":[-1.640427947,42.7982063293],"type":"Point"}
}