{
  "type": "Feature",
  "properties": {
    "addr:full":"Pase Marquesa Viuda De Aldama (de La), 54 Alcobendas Madrid 28109",
    "addr:housenumber":"54",
    "addr:postcode":"28109",
    "addr:street":"Aldama De La",
    "iso:country":"ES",
    "sg:address":"Pase Marquesa Viuda De Aldama (de La), 54",
    "sg:city":"Alcobendas",
    "sg:orig_category":"Audiovisuales (producci\u00d3n, Edici\u00d3n, Realizaci\u00d3n)",
    "sg:phone":"+34 916 50 65 06",
    "sg:postcode":"28109",
    "sg:province":"Madrid",
    "wof:name":"Best Imagen S.l.",
    "wof:placetype":"venue"
},
  "geometry": {"coordinates":[-3.615655899,40.5187988281],"type":"Point"}
}