{
  "type": "Feature",
  "properties": {
    "addr:full":"Ctra S Cebrian De Campos, Km. 0005,5 Ribas Campos Palencia 34429",
    "addr:postcode":"34429",
    "addr:street":"Ctra S Cebrian De Campos Km. 0005,5 Ribas Campos",
    "iso:country":"ES",
    "sg:address":"Ctra S Cebrian De Campos, Km. 0005,5",
    "sg:city":"Ribas Campos",
    "sg:orig_category":"Caf\u00c9s (al Por Menor)",
    "sg:phone":"+34 979 80 84 04",
    "sg:postcode":"34429",
    "sg:province":"Palencia",
    "wof:name":"Ingenieria Del Cafe S.l.",
    "wof:placetype":"venue"
},
  "geometry": {"coordinates":[-4.5510392189,42.1952018738],"type":"Point"}
}