{
  "type": "Feature",
  "properties": {
    "iso:country":"ES",
    "sg:address":"Carrer de Roser, 112",
    "sg:city":"Reus",
    "sg:orig_category":"Electricidad, Electr\u00d3nica: Material Y Suministros (al Por Mayor)",
    "sg:phone":"+34 977 77 19 25",
    "sg:postcode":"43203",
    "sg:province":"Tarragona",
    "wof:name":"Jose Amoros Febre S.l.",
    "wof:placetype":"venue"
},
  "geometry": {"coordinates":[1.1141159534,41.1589775085],"type":"Point"}
}