{
  "type": "Feature",
  "properties": {
    "iso:country":"ES",
    "sg:address":"Avda Andalucia, 22",
    "sg:city":"Coronil",
    "sg:orig_category":"Art\u00cdculos Funerarios (al Por Menor)",
    "sg:phone":"+34 955 83 05 03",
    "sg:postcode":"41760",
    "sg:province":"Sevilla",
    "wof:name":"Mu\u00f1oz Martin Manuel",
    "wof:placetype":"venue"
},
  "geometry": {"coordinates":[-5.6338291168,37.0800132751],"type":"Point"}
}