{
  "type": "Feature",
  "properties": {
    "addr:full":"Calle de Jose Ortega Y Gasset, 19 Madrid Madrid 28006",
    "addr:housenumber":"19",
    "addr:postcode":"madrid;28006",
    "addr:street":"Calle De Jose Ortega Y Gasset",
    "iso:country":"ES",
    "sg:address":"Calle de Jose Ortega Y Gasset, 19",
    "sg:city":"Madrid",
    "sg:orig_category":"Zapatos (al Por Menor)",
    "sg:phone":"+34 915 76 36 10",
    "sg:postcode":"28006",
    "sg:province":"Madrid",
    "sg:website":"www.zapaterialamarca.com",
    "wof:name":"Sanroman Bueno Inocencio Fernando",
    "wof:placetype":"venue"
},
  "geometry": {"coordinates":[-3.6852929592,40.430519104],"type":"Point"}
}