{
  "type": "Feature",
  "properties": {
    "addr:full":"Calle de Martin El Humano, 1 Valencia Valencia 46008",
    "addr:housenumber":"1",
    "addr:postcode":"46008",
    "addr:street":"Calle De Martin El Humano",
    "iso:country":"ES",
    "sg:address":"Calle de Martin El Humano, 1",
    "sg:city":"Valencia",
    "sg:orig_category":"Centros Pms (psico",
    "sg:phone":"+34 963 84 25 43",
    "sg:postcode":"46008",
    "sg:province":"Valencia",
    "wof:name":"Centro Ocupacional Virgen De La Esperanza",
    "wof:placetype":"venue"
},
  "geometry": {"coordinates":[-0.3916769922,39.4719352722],"type":"Point"}
}