{
  "type": "Feature",
  "properties": {
    "iso:country":"ES",
    "sg:address":"Avda Bosques, 5",
    "sg:city":"Arteixo",
    "sg:orig_category":"Arquitectos",
    "sg:phone":"+34 981 60 02 20",
    "sg:postcode":"15142",
    "sg:province":"La Coru\u00f1a",
    "wof:name":"Estudios Etc C B",
    "wof:placetype":"venue"
},
  "geometry": {"coordinates":[-8.5079059601,43.3036804199],"type":"Point"}
}