{
  "type": "Feature",
  "properties": {
    "addr:full":"Calle de Rehuerta, S/n Mazaleon Teruel 44621",
    "addr:housenumber":"s",
    "addr:postcode":"44621",
    "addr:street":"Calle De Rehuerta;/ N",
    "iso:country":"ES",
    "sg:address":"Calle de Rehuerta, S/n",
    "sg:city":"Mazaleon",
    "sg:orig_category":"Cooperativas Agr\u00cdcolas",
    "sg:phone":"+34 978 89 86 56",
    "sg:postcode":"44621",
    "sg:province":"Teruel",
    "wof:name":"Cooperativa San Isidro",
    "wof:placetype":"venue"
},
  "geometry": {"coordinates":[0.1014200002,41.0484390259],"type":"Point"}
}