{
  "type": "Feature",
  "properties": {
    "addr:full":"Avda Espa\u00d1a (de), 52 Linea De La Concepcion C\u00e1diz 11300",
    "addr:housenumber":"52",
    "addr:postcode":"11300",
    "addr:street":"Avda Espan\u0303A De;Ca\u0301Diz",
    "iso:country":"ES",
    "sg:address":"Avda Espa\u00d1a (de), 52",
    "sg:city":"Linea De La Concepcion",
    "sg:orig_category":"Cervecer\u00cdas",
    "sg:phone":"+34 956 17 68 75",
    "sg:postcode":"11300",
    "sg:province":"C\u00e1diz",
    "wof:name":"Eurotel-sur S.l.",
    "wof:placetype":"venue"
},
  "geometry": {"coordinates":[-5.3547620773,36.1619529724],"type":"Point"}
}