{
  "type": "Feature",
  "properties": {
    "iso:country":"ES",
    "sg:address":"Trva Iturribide, 8",
    "sg:city":"Bilbao",
    "sg:orig_category":"Institutos De Belleza",
    "sg:phone":"+34 944 33 29 43",
    "sg:postcode":"48006",
    "sg:province":"Vizcaya",
    "wof:name":"Sarmiento Francisco Jamy",
    "wof:placetype":"venue"
},
  "geometry": {"coordinates":[-2.9206171036,43.2580184937],"type":"Point"}
}