{
  "type": "Feature",
  "properties": {
    "addr:full":"Rua Muelle San Tome, S/n Cambados Pontevedra 36630",
    "addr:housenumber":"s",
    "addr:postcode":"36630",
    "addr:street":"Rua Muelle San Tome;/ N",
    "iso:country":"ES",
    "sg:address":"Rua Muelle San Tome, S/n",
    "sg:city":"Cambados",
    "sg:orig_category":"Maquinaria, Instalaci\u00d3n Y Equipo Para Garajes Y Estaciones De Servicio",
    "sg:phone":"+34 986 52 43 87",
    "sg:postcode":"36630",
    "sg:province":"Pontevedra",
    "wof:name":"Distribuidora De Carburantes Marinos S.l.",
    "wof:placetype":"venue"
},
  "geometry": {"coordinates":[-8.8183889389,42.5088920593],"type":"Point"}
}