{
  "type": "Feature",
  "properties": {
    "iso:country":"ES",
    "sg:address":"Calle de Mayor, 56",
    "sg:city":"Albacete",
    "sg:orig_category":"Producci\u00d3n De Abonos Y De Fertilizantes",
    "sg:phone":"+34 967 21 43 90",
    "sg:postcode":"02002",
    "sg:province":"Albacete",
    "wof:name":"Cooperativas Agricolas Albacetenses S.c.l.",
    "wof:placetype":"venue"
},
  "geometry": {"coordinates":[-1.8525880575,38.9925537109],"type":"Point"}
}