{
  "type": "Feature",
  "properties": {
    "iso:country":"ES",
    "sg:address":"Ctra Coin, S/n",
    "sg:city":"Alhaurin El Grande",
    "sg:orig_category":"Panader\u00cdas, Panader\u00cdas",
    "sg:phone":"+34 952 59 42 50",
    "sg:postcode":"29120",
    "sg:province":"M\u00e1laga",
    "wof:name":"El Colmenero De Alhaurin S.l.",
    "wof:placetype":"venue"
},
  "geometry": {"coordinates":[-4.6910390854,36.6558914185],"type":"Point"}
}