{
  "type": "Feature",
  "properties": {
    "iso:country":"ES",
    "sg:address":"Carrer de Cambrils, 10",
    "sg:city":"Reus",
    "sg:orig_category":"Venta, Colocaci\u00d3n, Reparaci\u00d3n De Parabrisas, Techos Descapotables",
    "sg:phone":"+34 977 77 29 67",
    "sg:postcode":"43204",
    "sg:province":"Tarragona",
    "sg:website":"www.ralarsa.com",
    "wof:name":"Armelux Internacional S.a.",
    "wof:placetype":"venue"
},
  "geometry": {"coordinates":[1.1129196882,41.1515808105],"type":"Point"}
}