{
  "type": "Feature",
  "properties": {
    "addr:full":"Barrio Muza, S/n Benifaio Valencia 46450",
    "addr:housenumber":"s",
    "addr:postcode":"46450",
    "addr:street":"Barrio Muza;/ N",
    "iso:country":"ES",
    "sg:address":"Barrio Muza, S/n",
    "sg:city":"Benifaio",
    "sg:orig_category":"Frutas Y Legumbres Frescas (al Por Mayor)",
    "sg:phone":"+34 961 78 14 75",
    "sg:postcode":"46450",
    "sg:province":"Valencia",
    "wof:name":"March Domingo C.b.",
    "wof:placetype":"venue"
},
  "geometry": {"coordinates":[-0.4343680143,39.2869033813],"type":"Point"}
}