{
  "type": "Feature",
  "properties": {
    "addr:full":"C/ Vicent Lerma, 22 Paterna Valencia 46980",
    "addr:housenumber":"22",
    "addr:postcode":"46980",
    "addr:street":"C / Vicent Lerma",
    "iso:country":"ES",
    "sg:address":"C/ Vicent Lerma, 22",
    "sg:city":"Paterna",
    "sg:orig_category":"Reposter\u00cdas",
    "sg:phone":"+34 961 38 14 73",
    "sg:postcode":"46980",
    "sg:province":"Valencia",
    "wof:name":"Benlloch Guillem Jose Luis",
    "wof:placetype":"venue"
},
  "geometry": {"coordinates":[-0.444002986,39.5036506653],"type":"Point"}
}