{
  "type": "Feature",
  "properties": {
    "iso:country":"ES",
    "sg:address":"Avda Tirajana (de), S/n",
    "sg:city":"Playa Del Ingles",
    "sg:classifiers":[
        {
            "category":"Professional",
            "subcategory":"Management & Consulting",
            "type":"Services"
        }
    ],
    "sg:phone":"+34 928 77 74 44",
    "sg:postcode":"35100",
    "sg:province":"Las Palmas",
    "sg:tags":[
        "asesor\u00cda",
        "en",
        "marketing"
    ],
    "wof:name":"Gg Marketing Public Relation S.l.",
    "wof:placetype":"venue"
},
  "geometry": {"coordinates":[-15.5786590576,27.7565803528],"type":"Point"}
}