{
  "type": "Feature",
  "properties": {
    "addr:full":"Carrer de Menendez Y Pelayo, 218 Terrassa Barcelona 08223",
    "addr:housenumber":"218",
    "addr:postcode":"08223",
    "addr:street":"Carrer De Menendez Y Pelayo",
    "iso:country":"ES",
    "sg:address":"Carrer de Menendez Y Pelayo, 218",
    "sg:city":"Terrassa",
    "sg:orig_category":"Peluqueros: De Se\u00d1oras",
    "sg:phone":"+34 937 31 80 57",
    "sg:postcode":"08223",
    "sg:province":"Barcelona",
    "wof:name":"Mir Rosique Jordi",
    "wof:placetype":"venue"
},
  "geometry": {"coordinates":[2.024600029,41.5531272888],"type":"Point"}
}