{
  "type": "Feature",
  "properties": {
    "addr:full":"Calle de Neptuno, 2 Cordoba C\u00f3rdoba 14014",
    "addr:housenumber":"2",
    "addr:postcode":"14014",
    "addr:street":"Calle De Neptuno;Co\u0301Rdoba",
    "iso:country":"ES",
    "sg:address":"Calle de Neptuno, 2",
    "sg:city":"Cordoba",
    "sg:classifiers":[
        {
            "category":"Personal",
            "subcategory":"Barber",
            "type":"Services"
        }
    ],
    "sg:phone":"+34 957 43 96 37",
    "sg:postcode":"14014",
    "sg:province":"C\u00f3rdoba",
    "sg:tags":[
        "caballeros",
        "de",
        "peluqueros"
    ],
    "wof:name":"Calderon Godoy Ramiro",
    "wof:placetype":"venue"
},
  "geometry": {"coordinates":[-4.7518839836,37.8929786682],"type":"Point"}
}