{
  "type": "Feature",
  "properties": {
    "iso:country":"ES",
    "sg:address":"Av Ricardo Bayona, 7",
    "sg:city":"Benidorm",
    "sg:orig_category":"Electricidad Veh\u00cdculo",
    "sg:phone":"+34 965 86 72 04",
    "sg:postcode":"03500",
    "sg:province":"Alicante",
    "wof:name":"Vico Ortega Manuel",
    "wof:placetype":"venue"
},
  "geometry": {"coordinates":[-0.1378860027,38.5399398804],"type":"Point"}
}