{
  "type": "Feature",
  "properties": {
    "iso:country":"ES",
    "sg:address":"Calle de Badajoz, 22",
    "sg:city":"Huesca",
    "sg:orig_category":"Ambulancias",
    "sg:phone":"+34 974 21 25 20",
    "sg:postcode":"22004",
    "sg:province":"Huesca",
    "wof:name":"Ambulancias Pirineos S.coop.",
    "wof:placetype":"venue"
},
  "geometry": {"coordinates":[-0.4146102965,42.1301574707],"type":"Point"}
}