{
  "type": "Feature",
  "properties": {
    "iso:country":"ES",
    "sg:address":"Carrer de Antoni Gaudi, 64",
    "sg:city":"Reus",
    "sg:orig_category":"Alimentaci\u00d3n General (al Por Menor)",
    "sg:phone":"+34 977 32 18 22",
    "sg:postcode":"43203",
    "sg:province":"Tarragona",
    "wof:name":"Rios Diaz Ildefonso",
    "wof:placetype":"venue"
},
  "geometry": {"coordinates":[1.1082149744,41.1614532471],"type":"Point"}
}