{
  "type": "Feature",
  "properties": {
    "addr:full":"Calle de Rio, 3 Algeciras C\u00e1diz 11201",
    "addr:housenumber":"3;ca\u0301diz",
    "addr:postcode":"11201",
    "addr:street":"Calle De Rio",
    "iso:country":"ES",
    "sg:address":"Calle de Rio, 3",
    "sg:city":"Algeciras",
    "sg:orig_category":"Muebles, Minoristas",
    "sg:phone":"+34 956 65 41 98",
    "sg:postcode":"11201",
    "sg:province":"C\u00e1diz",
    "wof:name":"Leyco Muebles S.l.",
    "wof:placetype":"venue"
},
  "geometry": {"coordinates":[-5.4456062317,36.1273231506],"type":"Point"}
}