{
  "type": "Feature",
  "properties": {
    "addr:full":"Calle de San Julio, 7 Madrid Madrid 28002",
    "addr:housenumber":"7",
    "addr:postcode":"madrid;28002",
    "addr:street":"Calle De San Julio",
    "iso:country":"ES",
    "sg:address":"Calle de San Julio, 7",
    "sg:city":"Madrid",
    "sg:orig_category":"Electricidad: Instaladores",
    "sg:phone":"+34 915 64 00 90",
    "sg:postcode":"28002",
    "sg:province":"Madrid",
    "sg:website":"www.afpservicios.es",
    "wof:name":"Afp Servicios E Instalaciones S.l.",
    "wof:placetype":"venue"
},
  "geometry": {"coordinates":[-3.6807432175,40.442276001],"type":"Point"}
}