{
  "type": "Feature",
  "properties": {
    "iso:country":"ES",
    "sg:address":"Carrer de Montserrat, 42",
    "sg:city":"Playa De Calafell",
    "sg:orig_category":"Estudios, Instalaci\u00d3n De Climatizaci\u00d3n",
    "sg:phone":"+34 977 69 06 37",
    "sg:postcode":"43820",
    "sg:province":"Tarragona",
    "wof:name":"Promoclim S.l.",
    "wof:placetype":"venue"
},
  "geometry": {"coordinates":[1.5720210075,41.1888046265],"type":"Point"}
}