{
  "type": "Feature",
  "properties": {
    "iso:country":"ES",
    "sg:address":"Rua Eduardo Pondal, S/n",
    "sg:city":"Foz",
    "sg:orig_category":"Reposter\u00cdas",
    "sg:phone":"+34 982 14 02 24",
    "sg:postcode":"27780",
    "sg:province":"Lugo",
    "wof:name":"Fernandez Martinez Francisco",
    "wof:placetype":"venue"
},
  "geometry": {"coordinates":[-7.2569041252,43.5692062378],"type":"Point"}
}