{
  "type": "Feature",
  "properties": {
    "addr:full":"Calle de Victoria (de La), 1 Pozuelo Calatrava Ciudad Real 13179",
    "addr:housenumber":"1",
    "addr:postcode":"13179",
    "addr:street":"Calle De Victoria De La",
    "iso:country":"ES",
    "sg:address":"Calle de Victoria (de La), 1",
    "sg:city":"Pozuelo Calatrava",
    "sg:orig_category":"Tubos Met\u00c1licos",
    "sg:phone":"+34 926 84 03 83",
    "sg:postcode":"13179",
    "sg:province":"Ciudad Real",
    "wof:name":"Pardo Merino Epifanio",
    "wof:placetype":"venue"
},
  "geometry": {"coordinates":[-3.8368699551,38.9135818481],"type":"Point"}
}