{
  "type": "Feature",
  "properties": {
    "iso:country":"ES",
    "sg:address":"Ctra Trescientos Treinta Y Dos, 32",
    "sg:city":"Alqueria De La Comtessa",
    "sg:orig_category":"Orquestas De Variedades",
    "sg:phone":"+34 962 89 39 35",
    "sg:postcode":"46715",
    "sg:province":"Valencia",
    "wof:name":"Fernandez Gutierrez Maria Del Carmen",
    "wof:placetype":"venue"
},
  "geometry": {"coordinates":[-0.1497839987,38.9378852844],"type":"Point"}
}