{
  "type": "Feature",
  "properties": {
    "addr:full":"C/ Dos De Mayo, S/n Torrellano Alicante 03320",
    "addr:housenumber":"s / n",
    "addr:postcode":"03320",
    "addr:street":"C / Dos De Mayo",
    "iso:country":"ES",
    "sg:address":"C/ Dos De Mayo, S/n",
    "sg:city":"Torrellano",
    "sg:orig_category":"Congelados: Productos Alimentarios (fabricaci\u00d3n, Al Por Mayor)",
    "sg:phone":"+34 965 68 23 04",
    "sg:postcode":"03320",
    "sg:province":"Alicante",
    "wof:name":"Pastissers D'alacant S.l.",
    "wof:placetype":"venue"
},
  "geometry": {"coordinates":[-0.5922840238,38.2935600281],"type":"Point"}
}