{
  "type": "Feature",
  "properties": {
    "addr:full":"Carr Jaime El Conquistador, 8 Benetusser Valencia 46910",
    "addr:housenumber":"8",
    "addr:postcode":"46910",
    "addr:street":"Carr Jaime El Conquistador",
    "iso:country":"ES",
    "sg:address":"Carr Jaime El Conquistador, 8",
    "sg:city":"Benetusser",
    "sg:orig_category":"Producci\u00d3n, Distribuci\u00d3n De Gas Butano Y Propano",
    "sg:phone":"+34 963 75 28 82",
    "sg:postcode":"46910",
    "sg:province":"Valencia",
    "wof:name":"Perez Pardo Pedro",
    "wof:placetype":"venue"
},
  "geometry": {"coordinates":[-0.3949379921,39.4232635498],"type":"Point"}
}