{
  "type": "Feature",
  "properties": {
    "iso:country":"ES",
    "sg:address":"Carrer de Valencia, 303",
    "sg:city":"Barcelona",
    "sg:orig_category":"Peluqueros: De Se\u00d1oras",
    "sg:phone":"+34 934 57 45 81",
    "sg:postcode":"08009",
    "sg:province":"Barcelona",
    "wof:name":"Zamora Terres Maria Teresa",
    "wof:placetype":"venue"
},
  "geometry": {"coordinates":[2.1675903797,41.3959350586],"type":"Point"}
}