{
  "type": "Feature",
  "properties": {
    "addr:full":"Calle de Camila Gracia, 6 Huesca Huesca 22001",
    "addr:housenumber":"6",
    "addr:postcode":"22001",
    "addr:street":"Calle De Camila Gracia",
    "iso:country":"ES",
    "sg:address":"Calle de Camila Gracia, 6",
    "sg:city":"Huesca",
    "sg:orig_category":"Agentes Generales De Seguros",
    "sg:phone":"+34 974 24 02 38",
    "sg:postcode":"22001",
    "sg:province":"Huesca",
    "wof:name":"Goded Lardies Javier",
    "wof:placetype":"venue"
},
  "geometry": {"coordinates":[-0.4040420949,42.1403694153],"type":"Point"}
}