{
  "type": "Feature",
  "properties": {
    "iso:country":"ES",
    "sg:address":"Calle de Puerto Del Monasterio, 11",
    "sg:city":"Madrid",
    "sg:orig_category":"Prot\u00c9sicos Dentales",
    "sg:phone":"+34 914 78 29 55",
    "sg:postcode":"28053",
    "sg:province":"Madrid",
    "wof:name":"Herraez Herraez Heliodoro",
    "wof:placetype":"venue"
},
  "geometry": {"coordinates":[-3.6641709805,40.3946647644],"type":"Point"}
}