{
  "type": "Feature",
  "properties": {
    "addr:full":"Carrer de Valldoreix, 38 S. Cugat Valles Barcelona 08172",
    "addr:housenumber":"38",
    "addr:postcode":"08172",
    "addr:street":"Carrer De Valldoreix;S. Cugat Valles Barcelona",
    "iso:country":"ES",
    "sg:address":"Carrer de Valldoreix, 38",
    "sg:city":"S. Cugat Valles",
    "sg:orig_category":"Moda",
    "sg:phone":"+34 935 89 72 75",
    "sg:postcode":"08172",
    "sg:province":"Barcelona",
    "wof:name":"Emete Mummy S.l.",
    "wof:placetype":"venue"
},
  "geometry": {"coordinates":[2.0799729824,41.4689750671],"type":"Point"}
}