{
  "type": "Feature",
  "properties": {
    "addr:full":"Carr Jaume I, De, 41 Campos Islas Baleares 07630",
    "addr:housenumber":"41",
    "addr:postcode":"07630",
    "addr:street":"Carr Jaume I De",
    "iso:country":"ES",
    "sg:address":"Carr Jaume I, De, 41",
    "sg:city":"Campos",
    "sg:orig_category":"Forjas Y Altos Hornos",
    "sg:phone":"+34 971 65 06 28",
    "sg:postcode":"07630",
    "sg:province":"Islas Baleares",
    "wof:name":"Ca'n Gasparet S.l.",
    "wof:placetype":"venue"
},
  "geometry": {"coordinates":[3.0236198902,39.4295654297],"type":"Point"}
}