{
  "type": "Feature",
  "properties": {
    "iso:country":"ES",
    "sg:address":"Calle de Hermosilla, 20",
    "sg:city":"Madrid",
    "sg:orig_category":"Cine (producci\u00d3n, Realizaci\u00d3n)",
    "sg:phone":"+34 915 78 38 05",
    "sg:postcode":"28001",
    "sg:province":"Madrid",
    "wof:name":"Kupela Producciones S. L.",
    "wof:placetype":"venue"
},
  "geometry": {"coordinates":[-3.6858410835,40.42628479],"type":"Point"}
}