{
  "type": "Feature",
  "properties": {
    "iso:country":"ES",
    "sg:address":"Calle de Estrella, 5",
    "sg:city":"Campo Criptana",
    "sg:orig_category":"Zapatos (al Por Menor)",
    "sg:phone":"+34 926 56 25 87",
    "sg:postcode":"13610",
    "sg:province":"Ciudad Real",
    "wof:name":"Ucendo Pedroche Jose Angel",
    "wof:placetype":"venue"
},
  "geometry": {"coordinates":[-3.1307859421,39.4035453796],"type":"Point"}
}