{
  "type": "Feature",
  "properties": {
    "addr:full":"Calle de Estrella, 26 Ciudad Real Ciudad Real 13003",
    "addr:housenumber":"26",
    "addr:postcode":"13003",
    "addr:street":"Calle De Estrella",
    "iso:country":"ES",
    "sg:address":"Calle de Estrella, 26",
    "sg:city":"Ciudad Real",
    "sg:orig_category":"Centros P\u00dablicos De Formaci\u00d3n Profesional Y T\u00c9cnica",
    "sg:phone":"+34 926 22 37 40",
    "sg:postcode":"13003",
    "sg:province":"Ciudad Real",
    "wof:name":"Colegio Oficial Agentes Propiedad Inmobiliaria",
    "wof:placetype":"venue"
},
  "geometry": {"coordinates":[-3.9248700142,38.9908218384],"type":"Point"}
}