{
  "type": "Feature",
  "properties": {
    "iso:country":"ES",
    "sg:address":"Carrer de Pi I Margall, 8",
    "sg:city":"Reus",
    "sg:orig_category":"Inform\u00c1tica: Mantenimiento Y Reparaci\u00d3n De Ordenadores",
    "sg:phone":"+34 977 77 19 00",
    "sg:postcode":"43205",
    "sg:province":"Tarragona",
    "wof:name":"Tecnologia Y Gestio Informatica S.l.",
    "wof:placetype":"venue"
},
  "geometry": {"coordinates":[1.1117999554,41.1422386169],"type":"Point"}
}