{
  "type": "Feature",
  "properties": {
    "addr:full":"Ctra Valladolid, 6 Cuellar Segovia 40200",
    "addr:housenumber":"6",
    "addr:postcode":"40200",
    "addr:street":"Ctra Valladolid",
    "iso:country":"ES",
    "sg:address":"Ctra Valladolid, 6",
    "sg:city":"Cuellar",
    "sg:orig_category":"Inmobiliaria (agencias)",
    "sg:phone":"+34 921 14 32 02",
    "sg:postcode":"40200",
    "sg:province":"Segovia",
    "wof:name":"Mu\u00f1oz Rodriguez Pedro",
    "wof:placetype":"venue"
},
  "geometry": {"coordinates":[-4.3310837746,41.4075393677],"type":"Point"}
}