{
  "type": "Feature",
  "properties": {
    "iso:country":"ES",
    "sg:address":"Carr Valencia, S/n",
    "sg:city":"Llosa Ranes",
    "sg:orig_category":"Porcelanas, Azulejos (fabricaci\u00d3n, Al Por Mayor)",
    "sg:phone":"+34 962 23 10 48",
    "sg:postcode":"46815",
    "sg:province":"Valencia",
    "wof:name":"Distribuciones Ceramicas Velasco S.l.",
    "wof:placetype":"venue"
},
  "geometry": {"coordinates":[-0.5338389874,39.0177955627],"type":"Point"}
}