{
  "type": "Feature",
  "properties": {
    "iso:country":"ES",
    "sg:address":"Pase General Martinez Campos, 35",
    "sg:city":"Madrid",
    "sg:orig_category":"Asesor\u00cda Fiscal Y Jur\u00cddica",
    "sg:phone":"+34 913 19 54 71",
    "sg:postcode":"28010",
    "sg:province":"Madrid",
    "wof:name":"Susino Abogados S.a.",
    "wof:placetype":"venue"
},
  "geometry": {"coordinates":[-3.6928219795,40.4352493286],"type":"Point"}
}