{
  "type": "Feature",
  "properties": {
    "addr:full":"Urb Paraiso De La Bahia, S/n Bahia De Casares M\u00e1laga 29690",
    "addr:housenumber":"s / n",
    "addr:postcode":"29690",
    "addr:street":"Urb;Bahia;Bahia De Casares Ma\u0301Laga",
    "iso:country":"ES",
    "sg:address":"Urb Paraiso De La Bahia, S/n",
    "sg:city":"Bahia De Casares",
    "sg:orig_category":"Librer\u00cdas",
    "sg:phone":"+34 952 93 77 57",
    "sg:postcode":"29690",
    "sg:province":"M\u00e1laga",
    "wof:name":"Distribuciones Editoriales Moreno S.l.",
    "wof:placetype":"venue"
},
  "geometry": {"coordinates":[-5.2171440125,36.3815536499],"type":"Point"}
}