{
  "type": "Feature",
  "properties": {
    "iso:country":"ES",
    "sg:address":"Calle de Real, 26",
    "sg:city":"Utiel",
    "sg:orig_category":"Caf\u00c9s, Bares, Cervecer\u00cdas",
    "sg:phone":"+34 962 17 45 08",
    "sg:postcode":"46300",
    "sg:province":"Valencia",
    "wof:name":"Platero Perea Ana Maria",
    "wof:placetype":"venue"
},
  "geometry": {"coordinates":[-1.2057379484,39.5668373108],"type":"Point"}
}