{
  "type": "Feature",
  "properties": {
    "addr:full":"Calle de Real, 22 Torrelodones Madrid 28250",
    "addr:housenumber":"22",
    "addr:postcode":"28250",
    "addr:street":"Calle De Real",
    "iso:country":"ES",
    "sg:address":"Calle de Real, 22",
    "sg:city":"Torrelodones",
    "sg:orig_category":"Jardiner\u00cdas, Vegetales, Art\u00cdculos De Jardiner\u00cda (al Por Menor)",
    "sg:phone":"+34 918 59 06 08",
    "sg:postcode":"28250",
    "sg:province":"Madrid",
    "wof:name":"Eduardo Nu\u00f1ez Lagos S.l.",
    "wof:placetype":"venue"
},
  "geometry": {"coordinates":[-3.9275989532,40.5753479004],"type":"Point"}
}