{
  "type": "Feature",
  "properties": {
    "iso:country":"ES",
    "sg:address":"Carrer de Esglesia, 12",
    "sg:city":"Castelldefels",
    "sg:orig_category":"Panader\u00cdas, Panader\u00cdas",
    "sg:phone":"+34 936 64 29 78",
    "sg:postcode":"08860",
    "sg:province":"Barcelona",
    "wof:name":"Ferrer Garcia Maria Eulalia",
    "wof:placetype":"venue"
},
  "geometry": {"coordinates":[1.9778250456,41.2811889648],"type":"Point"}
}