{
  "type": "Feature",
  "properties": {
    "addr:full":"Carrer de Casp, 28 Sabadell Barcelona 08204",
    "addr:housenumber":"28",
    "addr:postcode":"08204",
    "addr:street":"Carrer De Casp",
    "iso:country":"ES",
    "sg:address":"Carrer de Casp, 28",
    "sg:city":"Sabadell",
    "sg:orig_category":"Contenedores (mercanc\u00cdas)",
    "sg:phone":"+34 937 11 06 18",
    "sg:postcode":"08204",
    "sg:province":"Barcelona",
    "wof:name":"Morante Soler Antonio",
    "wof:placetype":"venue"
},
  "geometry": {"coordinates":[2.1195800304,41.5307731628],"type":"Point"}
}