{
  "type": "Feature",
  "properties": {
    "iso:country":"ES",
    "sg:address":"Calle de Ca\u00d1uelo, 12",
    "sg:city":"Villanueva Cordoba",
    "sg:orig_category":"Sociedades, Compa\u00d1\u00cdas Aseguradoras",
    "sg:phone":"+34 957 12 11 52",
    "sg:postcode":"14440",
    "sg:province":"C\u00f3rdoba",
    "wof:name":"Martin Rojas S.c.",
    "wof:placetype":"venue"
},
  "geometry": {"coordinates":[-4.6268239021,38.3225708008],"type":"Point"}
}