{
  "type": "Feature",
  "properties": {
    "iso:country":"ES",
    "sg:address":"Calle de Do\u00d1a Urraca, 15",
    "sg:city":"Le\u00f3n",
    "sg:orig_category":"Molduras, Junquillos, Listones Y Molduras Perforadas",
    "sg:phone":"+34 987 80 36 30",
    "sg:postcode":"24009",
    "sg:province":"Le\u00f3n",
    "wof:name":"Botas Cazon Antonio",
    "wof:placetype":"venue"
},
  "geometry": {"coordinates":[-5.5878310204,42.5978240967],"type":"Point"}
}