{
  "type": "Feature",
  "properties": {
    "addr:full":"Comp Puerto Dep.l.campomanes, 55 Galeras Bajas Alicante 03590",
    "addr:housenumber":"55",
    "addr:postcode":"03590",
    "addr:street":"Dep.L.Campomanes;Bajas Alicante",
    "iso:country":"ES",
    "sg:address":"Comp Puerto Dep.l.campomanes, 55",
    "sg:city":"Galeras Bajas",
    "sg:orig_category":"Inmobiliaria (agencias)",
    "sg:phone":"+34 966 88 85 09",
    "sg:postcode":"03590",
    "sg:province":"Alicante",
    "wof:name":"Andres Atienza Jesus",
    "wof:placetype":"venue"
},
  "geometry": {"coordinates":[-0.4810059965,38.3452033997],"type":"Point"}
}