{
  "type": "Feature",
  "properties": {
    "iso:country":"ES",
    "sg:address":"Calle de Convento Santa Clara, 10",
    "sg:city":"Valencia",
    "sg:orig_category":"M\u00c9dicos: Dermatolog\u00cda Y Venereolog\u00cda",
    "sg:phone":"+34 963 51 48 09",
    "sg:postcode":"46002",
    "sg:province":"Valencia",
    "wof:name":"Clinica Dermatologica Dr. Aliaga S.l.",
    "wof:placetype":"venue"
},
  "geometry": {"coordinates":[-0.3763321936,39.4683036804],"type":"Point"}
}