{
  "type": "Feature",
  "properties": {
    "addr:full":"Avda Albufera, 6 Alfafar Valencia 46910",
    "addr:housenumber":"6",
    "addr:postcode":"46910",
    "addr:street":"Avda Albufera",
    "iso:country":"ES",
    "sg:address":"Avda Albufera, 6",
    "sg:city":"Alfafar",
    "sg:orig_category":"Farmacias",
    "sg:phone":"+34 963 75 32 27",
    "sg:postcode":"46910",
    "sg:province":"Valencia",
    "wof:name":"Navarro Casanova Maria Josefa",
    "wof:placetype":"venue"
},
  "geometry": {"coordinates":[-0.3789260089,39.413974762],"type":"Point"}
}