{
  "type": "Feature",
  "properties": {
    "iso:country":"ES",
    "sg:address":"Av. Scho Fuerte, 34",
    "sg:city":"Iru\u00f1a",
    "sg:orig_category":"Molduras, Junquillos, Listones Y Molduras Perforadas",
    "sg:phone":"+34 948 26 07 23",
    "sg:postcode":"31008",
    "sg:province":"Navarra",
    "wof:name":"Alegria Magdaleno S.l.",
    "wof:placetype":"venue"
},
  "geometry": {"coordinates":[-1.6687812805,42.8102302551],"type":"Point"}
}