{
  "type": "Feature",
  "properties": {
    "addr:full":"Calle de Alhamar, 9 Granada Granada 18005",
    "addr:housenumber":"9",
    "addr:postcode":"18005",
    "addr:street":"Calle De Alhamar",
    "iso:country":"ES",
    "sg:address":"Calle de Alhamar, 9",
    "sg:city":"Granada",
    "sg:orig_category":"Ense\u00d1anza: Profesiones Art\u00cdsticas",
    "sg:phone":"+34 958 26 19 01",
    "sg:postcode":"18005",
    "sg:province":"Granada",
    "wof:name":"Pascual Del Coso Carlos",
    "wof:placetype":"venue"
},
  "geometry": {"coordinates":[-3.6004703045,37.1689834595],"type":"Point"}
}