{
  "type": "Feature",
  "properties": {
    "addr:full":"Carrer de Narcis Monturiol, 3 Manresa Barcelona 08243",
    "addr:housenumber":"3",
    "addr:postcode":"08243",
    "addr:street":"Carrer De Narcis Monturiol",
    "iso:country":"ES",
    "sg:address":"Carrer de Narcis Monturiol, 3",
    "sg:city":"Manresa",
    "sg:orig_category":"Transportes Por V\u00cdas Navegables",
    "sg:phone":"+34 938 74 67 50",
    "sg:postcode":"08243",
    "sg:province":"Barcelona",
    "wof:name":"Font I Santisteban Catalunya S.l.",
    "wof:placetype":"venue"
},
  "geometry": {"coordinates":[1.8495739698,41.7189674377],"type":"Point"}
}