{
  "type": "Feature",
  "properties": {
    "iso:country":"ES",
    "sg:address":"Carrer de Princep De Viana, 15",
    "sg:city":"Granollers",
    "sg:classifiers":[
        {
            "category":"Personal",
            "subcategory":"Barber",
            "type":"Services"
        }
    ],
    "sg:phone":"+34 938 70 88 53",
    "sg:postcode":"08401",
    "sg:province":"Barcelona",
    "sg:tags":[
        "caballeros",
        "de",
        "peluqueros"
    ],
    "wof:name":"Miguel Martinez Colome Y Buenaventura Martinez Colome Cdad.",
    "wof:placetype":"venue"
},
  "geometry": {"coordinates":[2.2864940166,41.6060295105],"type":"Point"}
}