{
  "type": "Feature",
  "properties": {
    "addr:full":"Carrer de Francesc Suau, 2 Palma Islas Baleares 07010",
    "addr:housenumber":"2",
    "addr:postcode":"07010",
    "addr:street":"Carrer De Francesc Suau",
    "iso:country":"ES",
    "sg:address":"Carrer de Francesc Suau, 2",
    "sg:city":"Palma",
    "sg:orig_category":"Deportes Diversos",
    "sg:phone":"+34 971 20 61 14",
    "sg:postcode":"07010",
    "sg:province":"Islas Baleares",
    "wof:name":"Federacion Balear De Motonautica",
    "wof:placetype":"venue"
},
  "geometry": {"coordinates":[2.6507430077,39.5869064331],"type":"Point"}
}