{
  "type": "Feature",
  "properties": {
    "iso:country":"ES",
    "sg:address":"Calle de Jeronimo De La Quintana, 5",
    "sg:city":"Madrid",
    "sg:orig_category":"\u00d3ptica: Instrumentos (fabricaci\u00d3n)",
    "sg:phone":"+34 914 45 61 88",
    "sg:postcode":"28010",
    "sg:province":"Madrid",
    "wof:name":"Escat Cuevas Dolores",
    "wof:placetype":"venue"
},
  "geometry": {"coordinates":[-3.7038969994,40.4312133789],"type":"Point"}
}