{
  "type": "Feature",
  "properties": {
    "addr:full":"Calle de Calvario, 56 Purchil Granada 18193",
    "addr:housenumber":"56",
    "addr:postcode":"18193",
    "addr:street":"Calle De Calvario",
    "iso:country":"ES",
    "sg:address":"Calle de Calvario, 56",
    "sg:city":"Purchil",
    "sg:orig_category":"Empresas De Carpinter\u00cda Met\u00c1lica",
    "sg:phone":"+34 958 44 51 16",
    "sg:postcode":"18193",
    "sg:province":"Granada",
    "wof:name":"Talleres Gergus S.l.",
    "wof:placetype":"venue"
},
  "geometry": {"coordinates":[-3.6697239876,37.1727790833],"type":"Point"}
}