{
  "type": "Feature",
  "properties": {
    "addr:full":"Calle de Pedro Paniagua, 1 Plasencia C\u00e1ceres 10600",
    "addr:housenumber":"1",
    "addr:postcode":"10600",
    "addr:street":"Calle De Pedro Paniagua;Ca\u0301Ceres",
    "iso:country":"ES",
    "sg:address":"Calle de Pedro Paniagua, 1",
    "sg:city":"Plasencia",
    "sg:orig_category":"Arquitectos",
    "sg:phone":"+34 927 42 21 55",
    "sg:postcode":"10600",
    "sg:province":"C\u00e1ceres",
    "wof:name":"Caldera Dominguez Miguel Angel",
    "wof:placetype":"venue"
},
  "geometry": {"coordinates":[-6.0854787827,40.0325889587],"type":"Point"}
}