{
  "type": "Feature",
  "properties": {
    "iso:country":"ES",
    "sg:address":"Calle de Juan Ramon Jimenez, 8",
    "sg:city":"Madrid",
    "sg:orig_category":"Centros Empresariales",
    "sg:phone":"+34 913 50 72 00",
    "sg:postcode":"28036",
    "sg:province":"Madrid",
    "wof:name":"Mail Hotel S.l.",
    "wof:placetype":"venue"
},
  "geometry": {"coordinates":[-3.6867916584,40.4582824707],"type":"Point"}
}