{
  "type": "Feature",
  "properties": {
    "iso:country":"ES",
    "sg:address":"Artica, 14",
    "sg:city":"Iru\u00f1a",
    "sg:orig_category":"Farmacias",
    "sg:phone":"+34 948 14 11 95",
    "sg:postcode":"31014",
    "sg:province":"Navarra",
    "wof:name":"Aguirre Esparz Genoveva",
    "wof:placetype":"venue"
},
  "geometry": {"coordinates":[-1.64747715,42.82762146],"type":"Point"}
}