{
  "type": "Feature",
  "properties": {
    "addr:full":"Pl. Mayor, 8 Osma Soria 42300",
    "addr:housenumber":"8",
    "addr:postcode":"42300",
    "addr:street":"Pl. Mayor",
    "iso:country":"ES",
    "sg:address":"Pl. Mayor, 8",
    "sg:city":"Osma",
    "sg:orig_category":"Iglesia Cat\u00d3lica",
    "sg:phone":"+34 975 34 08 65",
    "sg:postcode":"42300",
    "sg:province":"Soria",
    "wof:name":"Parroquia Santa Cristina",
    "wof:placetype":"venue"
},
  "geometry": {"coordinates":[-3.0684330463,41.5864219666],"type":"Point"}
}