{
  "type": "Feature",
  "properties": {
    "addr:full":"Avda Principal, S/n Higueron C\u00f3rdoba 14193",
    "addr:housenumber":"s / n",
    "addr:postcode":"14193",
    "addr:street":"Avda Principal;Higueron Co\u0301Rdoba",
    "iso:country":"ES",
    "sg:address":"Avda Principal, S/n",
    "sg:city":"Higueron",
    "sg:orig_category":"Negocio De Enlosados, Soler\u00cdas",
    "sg:phone":"+34 957 32 91 95",
    "sg:postcode":"14193",
    "sg:province":"C\u00f3rdoba",
    "wof:name":"Navarrete Sanchez Juan Antonio",
    "wof:placetype":"venue"
},
  "geometry": {"coordinates":[-4.853178978,37.8680534363],"type":"Point"}
}