{
  "type": "Feature",
  "properties": {
    "addr:full":"Carrer de Jaume I El Conqueridor, 40 Vic Barcelona 08500",
    "addr:housenumber":"40",
    "addr:postcode":"08500",
    "addr:street":"Carrer De Jaume I El Conqueridor",
    "iso:country":"ES",
    "sg:address":"Carrer de Jaume I El Conqueridor, 40",
    "sg:city":"Vic",
    "sg:orig_category":"Electrodom\u00c9sticos (al Por Menor)",
    "sg:phone":"+34 938 86 16 34",
    "sg:postcode":"08500",
    "sg:province":"Barcelona",
    "wof:name":"Uribe Costa Miquel",
    "wof:placetype":"venue"
},
  "geometry": {"coordinates":[2.2576830387,41.9321289062],"type":"Point"}
}