{
  "type": "Feature",
  "properties": {
    "iso:country":"ES",
    "sg:address":"Plaz Leizaola Lehendakaria Plaza, 1",
    "sg:city":"Arteaga",
    "sg:orig_category":"Farmacias",
    "sg:phone":"+34 944 52 01 59",
    "sg:postcode":"48170",
    "sg:province":"Vizcaya",
    "wof:name":"Quijano Cuesta Ainoa",
    "wof:placetype":"venue"
},
  "geometry": {"coordinates":[-2.8641989231,43.2838363647],"type":"Point"}
}