{
  "type": "Feature",
  "properties": {
    "iso:country":"ES",
    "sg:address":"Calle de San Benito, 17",
    "sg:city":"Ecija",
    "sg:orig_category":"Plomeros",
    "sg:phone":"+34 955 90 31 49",
    "sg:postcode":"41400",
    "sg:province":"Sevilla",
    "wof:name":"Aguilera Prada Angeles",
    "wof:placetype":"venue"
},
  "geometry": {"coordinates":[-5.0836720467,37.5354194641],"type":"Point"}
}