{
  "type": "Feature",
  "properties": {
    "iso:country":"ES",
    "sg:address":"Rua Republica Arxentina (da), 43",
    "sg:city":"Santiago De Compostela",
    "sg:orig_category":"M\u00c9dicos: Alergolog\u00cda",
    "sg:phone":"+34 981 59 05 66",
    "sg:postcode":"15706",
    "sg:province":"La Coru\u00f1a",
    "wof:name":"Alvarez-calderon Prat Pedro",
    "wof:placetype":"venue"
},
  "geometry": {"coordinates":[-8.5511951447,42.8717346191],"type":"Point"}
}