{
  "type": "Feature",
  "properties": {
    "addr:full":"Calle de Medico Pascual Perez, 44 Alacant Alicante 03001",
    "addr:housenumber":"44",
    "addr:postcode":"03001",
    "addr:street":"Calle De Medico Pascual Perez",
    "iso:country":"ES",
    "sg:address":"Calle de Medico Pascual Perez, 44",
    "sg:city":"Alacant",
    "sg:orig_category":"Asesor\u00cda Sobre Comunicaci\u00d3n De Empresas",
    "sg:phone":"+34 965 20 17 30",
    "sg:postcode":"03001",
    "sg:province":"Alicante",
    "wof:name":"M T Torregrosa Consulting S.l.",
    "wof:placetype":"venue"
},
  "geometry": {"coordinates":[-0.4892059863,38.3457069397],"type":"Point"}
}