{
  "type": "Feature",
  "properties": {
    "iso:country":"ES",
    "sg:address":"Cememterio, S/n",
    "sg:city":"Madrigal Altas Torres",
    "sg:orig_category":"Cooperativas Agr\u00cdcolas",
    "sg:phone":"+34 920 32 00 09",
    "sg:postcode":"05220",
    "sg:province":"\u00c1vila",
    "wof:name":"Sociedad Cooperativa Agricola Y De Gestion De Madrigal",
    "wof:placetype":"venue"
},
  "geometry": {"coordinates":[-4.9980340004,41.0899734497],"type":"Point"}
}