{
  "type": "Feature",
  "properties": {
    "iso:country":"ES",
    "sg:address":"Calle de Cantareros, 1",
    "sg:city":"Medina Rioseco",
    "sg:orig_category":"Centros Empresariales",
    "sg:phone":"+34 983 72 04 79",
    "sg:postcode":"47800",
    "sg:province":"Valladolid",
    "wof:name":"Asociacion De Empresarios Y Profesionales De Medina De Rioseco",
    "wof:placetype":"venue"
},
  "geometry": {"coordinates":[-5.0449194908,41.8833503723],"type":"Point"}
}