{
  "type": "Feature",
  "properties": {
    "iso:country":"ES",
    "sg:address":"Calle de Santa Ana, 82",
    "sg:city":"Estepa",
    "sg:orig_category":"Droguer\u00cdas (al Por Menor)",
    "sg:phone":"+34 955 91 32 33",
    "sg:postcode":"41560",
    "sg:province":"Sevilla",
    "wof:name":"Mu\u00f1oz Lopez Juan Luis",
    "wof:placetype":"venue"
},
  "geometry": {"coordinates":[-4.8737077713,37.2912979126],"type":"Point"}
}