{
  "type": "Feature",
  "properties": {
    "iso:country":"ES",
    "sg:address":"Calle de Rector Lucena, 20",
    "sg:city":"Salamanca",
    "sg:orig_category":"Abogados",
    "sg:phone":"+34 923 26 21 56",
    "sg:postcode":"37002",
    "sg:province":"Salamanca",
    "wof:name":"Acevedo Gonzalez Florencio",
    "wof:placetype":"venue"
},
  "geometry": {"coordinates":[-5.6630115509,40.9670562744],"type":"Point"}
}