{
  "type": "Feature",
  "properties": {
    "iso:country":"ES",
    "sg:address":"Calle de Mayor, 22",
    "sg:city":"Albacete",
    "sg:orig_category":"Procuradores",
    "sg:phone":"+34 967 21 83 13",
    "sg:postcode":"02002",
    "sg:province":"Albacete",
    "wof:name":"Lopez Ruiz Abelardo",
    "wof:placetype":"venue"
},
  "geometry": {"coordinates":[-1.8538589478,38.9929885864],"type":"Point"}
}