{
  "type": "Feature",
  "properties": {
    "iso:country":"ES",
    "sg:address":"Iturriotz Kalea, 7",
    "sg:city":"Arrasate",
    "sg:orig_category":"Caf\u00c9s, Bares, Cervecer\u00cdas",
    "sg:phone":"+34 943 79 04 67",
    "sg:postcode":"20500",
    "sg:province":"Guip\u00f9zcoa",
    "wof:name":"Ezekiel Gomez Hidalgo Y Otro Cb",
    "wof:placetype":"venue"
},
  "geometry": {"coordinates":[-2.4891240597,43.0659675598],"type":"Point"}
}