{
  "type": "Feature",
  "properties": {
    "addr:full":"Calle de San Nemesio, S/n Madrid Madrid 28043",
    "addr:housenumber":"s / n",
    "addr:postcode":"28043",
    "addr:street":"Calle De San Nemesio",
    "iso:country":"ES",
    "sg:address":"Calle de San Nemesio, S/n",
    "sg:city":"Madrid",
    "sg:orig_category":"Ense\u00d1anza Secundaria: Colegios Y Escuelas Privadas",
    "sg:phone":"+34 914 13 79 61",
    "sg:postcode":"28043",
    "sg:province":"Madrid",
    "wof:name":"Instituto Nacional Bachillerato Mixto San Juan Bautista",
    "wof:placetype":"venue"
},
  "geometry": {"coordinates":[-3.6593940258,40.4536781311],"type":"Point"}
}