{
  "type": "Feature",
  "properties": {
    "addr:full":"Avda Euskadi, 14 San Vicente De Barakaldo Vizcaya 48902",
    "addr:housenumber":"14",
    "addr:postcode":"48902",
    "addr:street":"Avda Euskadi",
    "iso:country":"ES",
    "sg:address":"Avda Euskadi, 14",
    "sg:city":"San Vicente De Barakaldo",
    "sg:orig_category":"Mercer\u00cda, Lencer\u00cda (al Por Menor)",
    "sg:phone":"+34 944 90 22 36",
    "sg:postcode":"48902",
    "sg:province":"Vizcaya",
    "wof:name":"Fuentes Perez Maria Angeles",
    "wof:placetype":"venue"
},
  "geometry": {"coordinates":[-2.9903979301,43.293510437],"type":"Point"}
}