{
  "type": "Feature",
  "properties": {
    "iso:country":"ES",
    "sg:address":"Bard Sarrikue, 7",
    "sg:city":"Bilbao",
    "sg:orig_category":"Empresas De Carpinter\u00cda Met\u00c1lica",
    "sg:phone":"+34 944 45 01 33",
    "sg:postcode":"48007",
    "sg:province":"Vizcaya",
    "wof:name":"Carpinteria De Aluminio Jafer, C.b.",
    "wof:placetype":"venue"
},
  "geometry": {"coordinates":[-2.9102489948,43.2627868652],"type":"Point"}
}