{
  "type": "Feature",
  "properties": {
    "addr:full":"Calle de Periodista Azzati, 4 Valencia Valencia 46002",
    "addr:housenumber":"4",
    "addr:postcode":"46002",
    "addr:street":"Calle De Periodista Azzati",
    "iso:country":"ES",
    "sg:address":"Calle de Periodista Azzati, 4",
    "sg:city":"Valencia",
    "sg:orig_category":"Relojer\u00cda (al Por Menor, Reparaci\u00d3n)",
    "sg:phone":"+34 963 51 93 71",
    "sg:postcode":"46002",
    "sg:province":"Valencia",
    "wof:name":"Juan Rodriguez Salvador",
    "wof:placetype":"venue"
},
  "geometry": {"coordinates":[-0.3782899976,39.469833374],"type":"Point"}
}