{
  "type": "Feature",
  "properties": {
    "addr:full":"Xarol, 5 Badalona Barcelona 08915",
    "addr:housenumber":"5",
    "addr:postcode":"08915",
    "addr:street":"Xarol",
    "iso:country":"ES",
    "sg:address":"Xarol, 5",
    "sg:city":"Badalona",
    "sg:orig_category":"Art\u00cdculos De Limpieza Y De Cocina (fabricaci\u00d3n, Al Por Mayor)",
    "sg:phone":"+34 934 60 03 00",
    "sg:postcode":"08915",
    "sg:province":"Barcelona",
    "wof:name":"Saferlim S.a.l.",
    "wof:placetype":"venue"
},
  "geometry": {"coordinates":[2.2535510063,41.4614944458],"type":"Point"}
}