{
  "type": "Feature",
  "properties": {
    "addr:full":"Av Gava, 17 Viladecans Barcelona 08840",
    "addr:housenumber":"17",
    "addr:postcode":"08840",
    "addr:street":"Av Gava",
    "iso:country":"ES",
    "sg:address":"Av Gava, 17",
    "sg:city":"Viladecans",
    "sg:orig_category":"\u00d3ptica: Instrumentos (fabricaci\u00d3n)",
    "sg:phone":"+34 936 58 16 37",
    "sg:postcode":"08840",
    "sg:province":"Barcelona",
    "wof:name":"Creus Ferrando Carmen",
    "wof:placetype":"venue"
},
  "geometry": {"coordinates":[2.016479969,41.3128395081],"type":"Point"}
}