{
  "type": "Feature",
  "properties": {
    "iso:country":"ES",
    "sg:address":"Luga Poligono 43, 289",
    "sg:city":"Llucmajor",
    "sg:classifiers":[
        {
            "category":"Professional",
            "subcategory":"Management & Consulting",
            "type":"Services"
        }
    ],
    "sg:phone":"+34 971 66 43 01",
    "sg:postcode":"07620",
    "sg:province":"Islas Baleares",
    "sg:tags":[
        "asesor\u00cda",
        "en",
        "marketing"
    ],
    "wof:name":"Ginard Ferrer Vicente",
    "wof:placetype":"venue"
},
  "geometry": {"coordinates":[2.8897550106,39.486114502],"type":"Point"}
}