{
  "type": "Feature",
  "properties": {
    "iso:country":"ES",
    "sg:address":"Calle de Cuenca (de), 12",
    "sg:city":"Humanes De Madrid",
    "sg:orig_category":"Plomeros",
    "sg:phone":"+34 916 15 66 72",
    "sg:postcode":"28970",
    "sg:province":"Madrid",
    "wof:name":"Conductos Sanitarios Cosan S.l.",
    "wof:placetype":"venue"
},
  "geometry": {"coordinates":[-3.8149421215,40.2747612],"type":"Point"}
}