{
  "type": "Feature",
  "properties": {
    "addr:full":"Carrer de Faust Morell, 11 Palma Islas Baleares 07005",
    "addr:housenumber":"11",
    "addr:postcode":"07005",
    "addr:street":"Carrer De Faust Morell",
    "iso:country":"ES",
    "sg:address":"Carrer de Faust Morell, 11",
    "sg:city":"Palma",
    "sg:orig_category":"Perfumer\u00cda Y Cosm\u00c9tica (fabricaci\u00d3n, Al Por Mayor)",
    "sg:phone":"+34 971 24 29 39",
    "sg:postcode":"07005",
    "sg:province":"Islas Baleares",
    "wof:name":"Grupo Garau C.b.",
    "wof:placetype":"venue"
},
  "geometry": {"coordinates":[2.6612761021,39.5762634277],"type":"Point"}
}