{
  "type": "Feature",
  "properties": {
    "iso:country":"ES",
    "sg:address":"Avda Juan Carlos I, Km. 0109,0",
    "sg:city":"Avila",
    "sg:orig_category":"Cajas De Ahorro",
    "sg:phone":"+34 920 21 90 40",
    "sg:postcode":"05004",
    "sg:province":"\u00c1vila",
    "sg:website":"www.cajadeavila.es",
    "wof:name":"Caja De Avila",
    "wof:placetype":"venue"
},
  "geometry": {"coordinates":[-4.656484127,40.6688957214],"type":"Point"}
}