{
  "type": "Feature",
  "properties": {
    "addr:full":"Carrer de Numancia, 205 Barcelona Barcelona 08034",
    "addr:housenumber":"205",
    "addr:postcode":"08034",
    "addr:street":"Carrer De Numancia",
    "iso:country":"ES",
    "sg:address":"Carrer de Numancia, 205",
    "sg:city":"Barcelona",
    "sg:orig_category":"Asesor\u00cdas Y Estudios Financieros",
    "sg:phone":"+34 932 06 12 40",
    "sg:postcode":"08034",
    "sg:province":"Barcelona",
    "sg:website":"www.itp-online.com",
    "wof:name":"International Trade Parners S.l.",
    "wof:placetype":"venue"
},
  "geometry": {"coordinates":[2.1303238869,41.3917961121],"type":"Point"}
}