{
  "type": "Feature",
  "properties": {
    "iso:country":"ES",
    "sg:address":"Avda Miguel Hernandez, 30",
    "sg:city":"Denia",
    "sg:orig_category":"Molduras, Junquillos, Listones Y Molduras Perforadas",
    "sg:phone":"+34 966 42 42 62",
    "sg:postcode":"03700",
    "sg:province":"Alicante",
    "wof:name":"Bar Guacamai S.l.l.",
    "wof:placetype":"venue"
},
  "geometry": {"coordinates":[0.1030159965,38.8438224792],"type":"Point"}
}