{
  "type": "Feature",
  "properties": {
    "addr:full":"Calle de Eras, S/n Chillaron Cuenca Cuenca 16190",
    "addr:housenumber":"s",
    "addr:postcode":"16190",
    "addr:street":"Calle De Eras;/ N Chillaron",
    "iso:country":"ES",
    "sg:address":"Calle de Eras, S/n",
    "sg:city":"Chillaron Cuenca",
    "sg:orig_category":"Fabricaci\u00d3n, Venta De Chal\u00c9s Y De Construcciones De Madera",
    "sg:phone":"+34 969 27 30 01",
    "sg:postcode":"16190",
    "sg:province":"Cuenca",
    "wof:name":"Cordoba Vega Casimiro",
    "wof:placetype":"venue"
},
  "geometry": {"coordinates":[-2.223418951,40.1278762817],"type":"Point"}
}