{
  "type": "Feature",
  "properties": {
    "iso:country":"ES",
    "sg:address":"Carrer de Diputacio, 215",
    "sg:city":"Barcelona",
    "sg:orig_category":"Asociaciones, Organismos Culturales Y Socioeducativos",
    "sg:phone":"+34 934 54 11 31",
    "sg:postcode":"08011",
    "sg:province":"Barcelona",
    "wof:name":"Casa De Menorca",
    "wof:placetype":"venue"
},
  "geometry": {"coordinates":[2.1621539593,41.3869056702],"type":"Point"}
}