{
  "type": "Feature",
  "properties": {
    "iso:country":"ES",
    "sg:address":"Calle de Extremadura (de), 9",
    "sg:city":"Jaen",
    "sg:orig_category":"Tapicer\u00cdas",
    "sg:phone":"+34 953 25 91 04",
    "sg:postcode":"23006",
    "sg:province":"Ja\u00e9n",
    "wof:name":"Beltran Araque Pedro",
    "wof:placetype":"venue"
},
  "geometry": {"coordinates":[-3.7924389839,37.7813796997],"type":"Point"}
}