{
  "type": "Feature",
  "properties": {
    "addr:full":"Calle de Sabino Berthelot, 4 San Lazaro Santa Cruz De Tenerife 38206",
    "addr:housenumber":"4",
    "addr:postcode":"38206",
    "addr:street":"Calle De Sabino Berthelot",
    "iso:country":"ES",
    "sg:address":"Calle de Sabino Berthelot, 4",
    "sg:city":"San Lazaro",
    "sg:orig_category":"Estancos",
    "sg:phone":"+34 922 25 26 88",
    "sg:postcode":"38206",
    "sg:province":"Santa Cruz De Tenerife",
    "wof:name":"Arvelo Marichal Evelio",
    "wof:placetype":"venue"
},
  "geometry": {"coordinates":[-16.2548561096,28.4698104858],"type":"Point"}
}