{
  "type": "Feature",
  "properties": {
    "addr:full":"Ctra. Valencia-ademuz, Km. 0013,8 S. Antonio Benageber Valencia 46184",
    "addr:postcode":"46184",
    "addr:street":"Ctra. Valencia-Ademuz Km. 0013,8 S.",
    "iso:country":"ES",
    "sg:address":"Ctra. Valencia-ademuz, Km. 0013,8",
    "sg:city":"S. Antonio Benageber",
    "sg:orig_category":"Reciclaje, Tratamiento De Pl\u00c1sticos",
    "sg:phone":"+34 961 35 00 96",
    "sg:postcode":"46184",
    "sg:province":"Valencia",
    "wof:name":"Reciclajes K-13 S.l.",
    "wof:placetype":"venue"
},
  "geometry": {"coordinates":[-0.5012540221,39.5620651245],"type":"Point"}
}