{
  "type": "Feature",
  "properties": {
    "iso:country":"ES",
    "sg:address":"Calle de Cruz Del Estudiante, 68",
    "sg:city":"Puente-genil",
    "sg:orig_category":"Empresas De Pintura Y Revestimientos",
    "sg:phone":"+34 957 60 94 66",
    "sg:postcode":"14500",
    "sg:province":"C\u00f3rdoba",
    "wof:name":"Coarpigenenil S.c.a.",
    "wof:placetype":"venue"
},
  "geometry": {"coordinates":[-4.7680830956,37.389415741],"type":"Point"}
}