{
  "type": "Feature",
  "properties": {
    "addr:full":"Cmno Illarra De, 4 Donostia-san Sebastian Guip\u00f9zcoa 20018",
    "addr:housenumber":"4",
    "addr:postcode":"20018",
    "addr:street":"Cmno Illarra De",
    "iso:country":"ES",
    "sg:address":"Cmno Illarra De, 4",
    "sg:city":"Donostia-san Sebastian",
    "sg:orig_category":"Servidores Y Editores De Bases De Datos",
    "sg:phone":"+34 943 31 03 50",
    "sg:postcode":"20018",
    "sg:province":"Guip\u00f9zcoa",
    "wof:name":"Gupost S.a.",
    "wof:placetype":"venue"
},
  "geometry": {"coordinates":[-2.0182218552,43.3044624329],"type":"Point"}
}