{
  "type": "Feature",
  "properties": {
    "iso:country":"ES",
    "sg:address":"Calle de Alcalde Gomez Gomez, 14",
    "sg:city":"Malaga",
    "sg:orig_category":"Rectificaci\u00d3n, Mecanizado, Fresado",
    "sg:phone":"+34 952 34 41 99",
    "sg:postcode":"29006",
    "sg:province":"M\u00e1laga",
    "wof:name":"Olvi Rectificados Y Mecanizados S.l.",
    "wof:placetype":"venue"
},
  "geometry": {"coordinates":[-4.4781060219,36.7095603943],"type":"Point"}
}