{
  "type": "Feature",
  "properties": {
    "iso:country":"ES",
    "sg:address":"Calle de Celestino Mutis, 65",
    "sg:city":"Alcala Henares",
    "sg:orig_category":"Abogados",
    "sg:phone":"+34 918 02 83 47",
    "sg:postcode":"28806",
    "sg:province":"Madrid",
    "wof:name":"Aboservi S.l",
    "wof:placetype":"venue"
},
  "geometry": {"coordinates":[-3.3954,40.484932],"type":"Point"}
}