{
  "type": "Feature",
  "properties": {
    "addr:full":"Calle de Joaquin Bau, 2 Madrid Madrid 28036",
    "addr:housenumber":"2",
    "addr:postcode":"28036",
    "addr:street":"Calle De Joaquin Bau",
    "iso:country":"ES",
    "sg:address":"Calle de Joaquin Bau, 2",
    "sg:city":"Madrid",
    "sg:orig_category":"Centros De Coordinaci\u00d3n",
    "sg:phone":"+34 913 50 37 91",
    "sg:postcode":"28036",
    "sg:province":"Madrid",
    "wof:name":"Gesmar Habana S.l.",
    "wof:placetype":"venue"
},
  "geometry": {"coordinates":[-3.6866009235,40.4633827209],"type":"Point"}
}