{
  "type": "Feature",
  "properties": {
    "addr:full":"Carrer de America, 53 Sabadell Barcelona 08205",
    "addr:housenumber":"53",
    "addr:postcode":"08205",
    "addr:street":"Carrer De America",
    "iso:country":"ES",
    "sg:address":"Carrer de America, 53",
    "sg:city":"Sabadell",
    "sg:orig_category":"Asociaciones Y Clubs Deportivos",
    "sg:phone":"+34 937 27 74 52",
    "sg:postcode":"08205",
    "sg:province":"Barcelona",
    "wof:name":"Gimnasio Formas Sabadell S.l.",
    "wof:placetype":"venue"
},
  "geometry": {"coordinates":[2.0925979614,41.5434494019],"type":"Point"}
}