{
  "type": "Feature",
  "properties": {
    "iso:country":"ES",
    "sg:address":"Pl Vila, 22",
    "sg:city":"Santa Coloma De Gramenet",
    "sg:orig_category":"Inmobiliaria (agencias)",
    "sg:phone":"+34 933 85 11 55",
    "sg:postcode":"08922",
    "sg:province":"Barcelona",
    "wof:name":"Fontla Gestion Inmobiliaria S.l.",
    "wof:placetype":"venue"
},
  "geometry": {"coordinates":[2.2086100578,41.4510536194],"type":"Point"}
}