{
  "type": "Feature",
  "properties": {
    "iso:country":"ES",
    "sg:address":"Ctra San Rafael, 38",
    "sg:city":"Segovia",
    "sg:orig_category":"Mec\u00c1nico Del Autom\u00d3vil",
    "sg:phone":"+34 921 44 53 96",
    "sg:postcode":"40006",
    "sg:province":"Segovia",
    "wof:name":"Minfrauto S.l.",
    "wof:placetype":"venue"
},
  "geometry": {"coordinates":[-4.1012592316,40.8733825684],"type":"Point"}
}