{
  "type": "Feature",
  "properties": {
    "iso:country":"ES",
    "sg:address":"Calle de Gibraltar, S/n",
    "sg:city":"Cadiz",
    "sg:orig_category":"Distribuci\u00d3n De Petr\u00d3leo Y Derivados",
    "sg:phone":"+34 956 27 56 51",
    "sg:postcode":"11011",
    "sg:province":"C\u00e1diz",
    "wof:name":"Genil Oil S.l.",
    "wof:placetype":"venue"
},
  "geometry": {"coordinates":[-6.2698225975,36.4986114502],"type":"Point"}
}