{
  "type": "Feature",
  "properties": {
    "iso:country":"ES",
    "sg:address":"Calle de Duque, 20",
    "sg:city":"Arahal",
    "sg:orig_category":"Comunidades Religiosas",
    "sg:phone":"+34 954 84 18 79",
    "sg:postcode":"41600",
    "sg:province":"Sevilla",
    "wof:name":"Hermandad De Nuestro Padre Jesus Nazareno",
    "wof:placetype":"venue"
},
  "geometry": {"coordinates":[-5.5445299149,37.2614822388],"type":"Point"}
}