{
  "type": "Feature",
  "properties": {
    "iso:country":"ES",
    "sg:address":"Avda Bonavista, 9",
    "sg:city":"Eliana",
    "sg:orig_category":"Ense\u00d1anza, Formaci\u00d3n Profesional: Aprendizaje",
    "sg:phone":"+34 961 65 55 14",
    "sg:postcode":"46183",
    "sg:province":"Valencia",
    "wof:name":"Ayuntamiento De La Eliana",
    "wof:placetype":"venue"
},
  "geometry": {"coordinates":[-0.5143589973,39.5693893433],"type":"Point"}
}