{
  "type": "Feature",
  "properties": {
    "addr:full":"Calle de Ferrol, 8 Coru\u00d1a La Coru\u00f1a 15004",
    "addr:housenumber":"8",
    "addr:postcode":"15004",
    "addr:street":"Calle De Ferrol;La Corun\u0303A",
    "iso:country":"ES",
    "sg:address":"Calle de Ferrol, 8",
    "sg:city":"Coru\u00d1a",
    "sg:orig_category":"Bancos",
    "sg:phone":"+34 981 22 76 66",
    "sg:postcode":"15004",
    "sg:province":"La Coru\u00f1a",
    "wof:name":"Banc Sabadell S.a.",
    "wof:placetype":"venue"
},
  "geometry": {"coordinates":[-8.4072751999,43.365272522],"type":"Point"}
}