{
  "type": "Feature",
  "properties": {
    "iso:country":"ES",
    "sg:address":"Carrer de Mare Rafols, 5",
    "sg:city":"Vilafranca Penedes",
    "sg:orig_category":"Chapister\u00cda",
    "sg:phone":"+34 938 17 03 25",
    "sg:postcode":"08720",
    "sg:province":"Barcelona",
    "wof:name":"Joanfer I Fills Plaxisteria S.l.",
    "wof:placetype":"venue"
},
  "geometry": {"coordinates":[1.7034809589,41.3425559998],"type":"Point"}
}