{
  "type": "Feature",
  "properties": {
    "iso:country":"ES",
    "sg:address":"Calle de Cruces, 78",
    "sg:city":"Puerto De Santa Maria",
    "sg:orig_category":"Supermercados Y Hipermercados",
    "sg:phone":"+34 956 87 38 52",
    "sg:postcode":"11500",
    "sg:province":"C\u00e1diz",
    "wof:name":"Perez Camacho Juan Luis",
    "wof:placetype":"venue"
},
  "geometry": {"coordinates":[-6.2307510376,36.6000709534],"type":"Point"}
}