{
  "type": "Feature",
  "properties": {
    "addr:full":"Calle de Teniente Alvarez Soto, 6 Alacant Alicante 03001",
    "addr:housenumber":"6",
    "addr:postcode":"03001",
    "addr:street":"Calle De Teniente Alvarez Soto",
    "iso:country":"ES",
    "sg:address":"Calle de Teniente Alvarez Soto, 6",
    "sg:city":"Alacant",
    "sg:orig_category":"M\u00c9dicos: Ginecolog\u00cda Y Obstetricia",
    "sg:phone":"+34 965 14 34 63",
    "sg:postcode":"03001",
    "sg:province":"Alicante",
    "wof:name":"Romero Gotor Segunda",
    "wof:placetype":"venue"
},
  "geometry": {"coordinates":[-0.4852589965,38.3458175659],"type":"Point"}
}