{
  "type": "Feature",
  "properties": {
    "addr:full":"Pg. Moreres, 2 Solsona Lleida 25280",
    "addr:housenumber":"2",
    "addr:postcode":"25280",
    "addr:street":"Pg. Moreres",
    "iso:country":"ES",
    "sg:address":"Pg. Moreres, 2",
    "sg:city":"Solsona",
    "sg:classifiers":[
        {
            "category":"Autos & Motor Vehicles",
            "subcategory":"Automobile Sales",
            "type":"Retail Goods"
        }
    ],
    "sg:phone":"+34 973 48 28 05",
    "sg:postcode":"25280",
    "sg:province":"Lleida",
    "wof:name":"Viladrich Mujal Manel",
    "wof:placetype":"venue"
},
  "geometry": {"coordinates":[1.5195499659,41.9937515259],"type":"Point"}
}