{
  "type": "Feature",
  "properties": {
    "iso:country":"ES",
    "sg:address":"Calle de San Fernando, 124",
    "sg:city":"Najera",
    "sg:orig_category":"Muebles Y Accesorios Para Cocinas Y Cuartos De Ba\u00d1o (al Por Menor)",
    "sg:phone":"+34 941 36 31 87",
    "sg:postcode":"26300",
    "sg:province":"La Rioja",
    "wof:name":"Hipercocinas S.a.",
    "wof:placetype":"venue"
},
  "geometry": {"coordinates":[-2.7179980278,42.4160804749],"type":"Point"}
}