{
  "type": "Feature",
  "properties": {
    "iso:country":"ES",
    "sg:address":"Calle de Fuego (del), 40",
    "sg:city":"Alcobendas",
    "sg:orig_category":"Ropa Para Se\u00d1oras (al Por Menor)",
    "sg:phone":"+34 916 54 89 94",
    "sg:postcode":"28100",
    "sg:province":"Madrid",
    "wof:name":"Canopo-lain S.l",
    "wof:placetype":"venue"
},
  "geometry": {"coordinates":[-3.6351079941,40.5441093445],"type":"Point"}
}