{
  "type": "Feature",
  "properties": {
    "addr:full":"Calle de Maestra Gonzalez Adame, 10 Fuenteheridos Huelva 21292",
    "addr:housenumber":"10",
    "addr:postcode":"21292",
    "addr:street":"Calle De Maestra Gonzalez Adame",
    "iso:country":"ES",
    "sg:address":"Calle de Maestra Gonzalez Adame, 10",
    "sg:city":"Fuenteheridos",
    "sg:orig_category":"Negocio De Madera",
    "sg:phone":"+34 959 12 51 30",
    "sg:postcode":"21292",
    "sg:province":"Huelva",
    "wof:name":"Fontenla Castilla Maria Isabel",
    "wof:placetype":"venue"
},
  "geometry": {"coordinates":[-6.6605639458,37.9035339355],"type":"Point"}
}