{
  "type": "Feature",
  "properties": {
    "iso:country":"ES",
    "sg:address":"Rua Ensino (do), 8",
    "sg:city":"Ourense",
    "sg:orig_category":"Carnicer\u00cdas, Carnicer\u00cdas",
    "sg:phone":"+34 988 24 86 19",
    "sg:postcode":"32002",
    "sg:province":"Ourense",
    "wof:name":"Valencia Lama Gumersindo",
    "wof:placetype":"venue"
},
  "geometry": {"coordinates":[-7.8703551292,42.3402366638],"type":"Point"}
}