{
  "type": "Feature",
  "properties": {
    "iso:country":"ES",
    "sg:address":"Euskal-herria, 38",
    "sg:city":"Ibarra",
    "sg:orig_category":"Material Y Suministros Para Horticultura, Arboricultura",
    "sg:phone":"+34 943 67 10 26",
    "sg:postcode":"20400",
    "sg:province":"Guip\u00f9zcoa",
    "wof:name":"Izaguirre Rezola Ignacio",
    "wof:placetype":"venue"
},
  "geometry": {"coordinates":[-2.0653529167,43.1321754456],"type":"Point"}
}