{
  "type": "Feature",
  "properties": {
    "addr:full":"Calle de Alcalde Gil Rodriguez, 8 Langreo Asturias 33900",
    "addr:housenumber":"8",
    "addr:postcode":"33900",
    "addr:street":"Calle De Alcalde Gil Rodriguez",
    "iso:country":"ES",
    "sg:address":"Calle de Alcalde Gil Rodriguez, 8",
    "sg:city":"Langreo",
    "sg:orig_category":"Lavado, Limpieza De Veh\u00cdculos",
    "sg:phone":"+34 985 68 03 57",
    "sg:postcode":"33900",
    "sg:province":"Asturias",
    "wof:name":"Lagares Mella Jose Francisco",
    "wof:placetype":"venue"
},
  "geometry": {"coordinates":[-5.6699972153,43.2891273499],"type":"Point"}
}