{
  "type": "Feature",
  "properties": {
    "iso:country":"ES",
    "sg:address":"Plaz Cardenal Paya (del), 12",
    "sg:city":"Cuenca",
    "sg:orig_category":"Venta, Instalaci\u00d3n De Calefacci\u00d3n",
    "sg:phone":"+34 969 21 43 36",
    "sg:postcode":"16001",
    "sg:province":"Cuenca",
    "wof:name":"San Jose Cano Luis",
    "wof:placetype":"venue"
},
  "geometry": {"coordinates":[-2.133975029,40.0744247437],"type":"Point"}
}