{
  "type": "Feature",
  "properties": {
    "iso:country":"ES",
    "sg:address":"Avda Gran Via Rey Juan Carlos I, 50",
    "sg:city":"Logro\u00f1o",
    "sg:orig_category":"Centros Empresariales",
    "sg:phone":"+34 941 28 77 65",
    "sg:postcode":"26005",
    "sg:province":"La Rioja",
    "wof:name":"Maria Luisa Marquez De Zaldo S.l.",
    "wof:placetype":"venue"
},
  "geometry": {"coordinates":[-2.4524199963,42.46484375],"type":"Point"}
}