{
  "type": "Feature",
  "properties": {
    "iso:country":"ES",
    "sg:address":"Calle de Cordoba, 4",
    "sg:city":"Fuengirola",
    "sg:orig_category":"Arquitectos",
    "sg:phone":"+34 952 58 39 39",
    "sg:postcode":"29640",
    "sg:province":"M\u00e1laga",
    "wof:name":"Valenzuela Moreno Sebastian",
    "wof:placetype":"venue"
},
  "geometry": {"coordinates":[-4.624174118,36.5421981812],"type":"Point"}
}