{
  "type": "Feature",
  "properties": {
    "addr:full":"Calle de Ibiza, 56 Madrid Madrid 28009",
    "addr:housenumber":"56",
    "addr:postcode":"madrid;28009",
    "addr:street":"Calle De Ibiza",
    "iso:country":"ES",
    "sg:address":"Calle de Ibiza, 56",
    "sg:city":"Madrid",
    "sg:orig_category":"M\u00c9dicos: Endocrinolog\u00cda Y Metabolismo",
    "sg:phone":"+34 915 74 64 25",
    "sg:postcode":"28009",
    "sg:province":"Madrid",
    "wof:name":"Jara Albarran Antonino",
    "wof:placetype":"venue"
},
  "geometry": {"coordinates":[-3.6718599796,40.4178619385],"type":"Point"}
}