{
  "type": "Feature",
  "properties": {
    "addr:full":"La Paz, 6 Zaragoza Zaragoza 50008",
    "addr:housenumber":"6",
    "addr:postcode":"50008",
    "addr:street":"La Paz",
    "iso:country":"ES",
    "sg:address":"La Paz, 6",
    "sg:city":"Zaragoza",
    "sg:orig_category":"Sociedades, Compa\u00d1\u00cdas Aseguradoras",
    "sg:phone":"+34 976 22 28 68",
    "sg:postcode":"50008",
    "sg:province":"Zaragoza",
    "wof:name":"Cendegui Gimeno Roman",
    "wof:placetype":"venue"
},
  "geometry": {"coordinates":[-0.8855339885,41.6424713135],"type":"Point"}
}