{
  "type": "Feature",
  "properties": {
    "iso:country":"ES",
    "sg:address":"Calle de Buensuceso, 21",
    "sg:city":"Granada",
    "sg:orig_category":"Abogados",
    "sg:phone":"+34 958 25 13 71",
    "sg:postcode":"18002",
    "sg:province":"Granada",
    "wof:name":"Garcia Del Cuerpo Francisco",
    "wof:placetype":"venue"
},
  "geometry": {"coordinates":[-3.6034300327,37.1749725342],"type":"Point"}
}