{
  "type": "Feature",
  "properties": {
    "iso:country":"ES",
    "sg:address":"Rua Joaquin Loriga, 24",
    "sg:city":"Vigo",
    "sg:orig_category":"Abogados",
    "sg:phone":"+34 986 42 13 30",
    "sg:postcode":"36203",
    "sg:province":"Pontevedra",
    "wof:name":"Ocampo Martinez David",
    "wof:placetype":"venue"
},
  "geometry": {"coordinates":[-8.7213373184,42.2335128784],"type":"Point"}
}