{
  "type": "Feature",
  "properties": {
    "addr:full":"Pg Sant Gervasi, 54 Barcelona Barcelona 08022",
    "addr:housenumber":"54",
    "addr:postcode":"08022",
    "addr:street":"Pg Sant Gervasi",
    "iso:country":"ES",
    "sg:address":"Pg Sant Gervasi, 54",
    "sg:city":"Barcelona",
    "sg:orig_category":"Agencias Y Agentes Comerciales, Representantes",
    "sg:phone":"+34 934 17 54 78",
    "sg:postcode":"08022",
    "sg:province":"Barcelona",
    "wof:name":"Piera Coll Antonio",
    "wof:placetype":"venue"
},
  "geometry": {"coordinates":[2.1382520199,41.4107475281],"type":"Point"}
}