{
  "type": "Feature",
  "properties": {
    "iso:country":"ES",
    "sg:address":"Calle de San Bartolome, 14",
    "sg:city":"Marcilla",
    "sg:orig_category":"Art\u00cdculos De Regalo (al Por Menor)",
    "sg:phone":"+34 948 71 39 20",
    "sg:postcode":"31340",
    "sg:province":"Navarra",
    "wof:name":"Felisa Juana Maria Y Maria Del Plu Navascues Go\u00f1i S.cv.",
    "wof:placetype":"venue"
},
  "geometry": {"coordinates":[-1.7405289412,42.3264770508],"type":"Point"}
}