{
  "type": "Feature",
  "properties": {
    "addr:full":"Carrer de Tramuntana, 15 S. Adria Besos Barcelona 08930",
    "addr:housenumber":"15",
    "addr:postcode":"08930",
    "addr:street":"Carrer De Tramuntana;S. Adria Besos Barcelona",
    "iso:country":"ES",
    "sg:address":"Carrer de Tramuntana, 15",
    "sg:city":"S. Adria Besos",
    "sg:orig_category":"Cajas De Ahorro",
    "sg:phone":"+34 933 81 26 74",
    "sg:postcode":"08930",
    "sg:province":"Barcelona",
    "sg:website":"www.caixacatalunya.es",
    "wof:name":"Caixa D'estalvis De Catalunya",
    "wof:placetype":"venue"
},
  "geometry": {"coordinates":[2.2196400166,41.4162063599],"type":"Point"}
}