{
  "type": "Feature",
  "properties": {
    "iso:country":"ES",
    "sg:address":"Avda Carlos Pinilla, 35",
    "sg:city":"Toro",
    "sg:orig_category":"Agencias De Viajes",
    "sg:phone":"+34 980 69 32 02",
    "sg:postcode":"49800",
    "sg:province":"Zamora",
    "sg:website":"www.viajesecuador.com",
    "wof:name":"Vaypitur S.l.",
    "wof:placetype":"venue"
},
  "geometry": {"coordinates":[-5.3973989487,41.5269813538],"type":"Point"}
}