{
  "type": "Feature",
  "properties": {
    "addr:full":"Calle de Celestino Junquera, 17 Gijon Asturias 33201",
    "addr:housenumber":"17",
    "addr:postcode":"33201",
    "addr:street":"Calle De Celestino Junquera",
    "iso:country":"ES",
    "sg:address":"Calle de Celestino Junquera, 17",
    "sg:city":"Gijon",
    "sg:orig_category":"Fotograf\u00cda Y Cine: Aparatos, Pel\u00cdculas Y Accesorios (fabricaci\u00d3n, Al Por Mayor)",
    "sg:phone":"+34 985 36 98 40",
    "sg:postcode":"33201",
    "sg:province":"Asturias",
    "wof:name":"Foto Angel S.l.",
    "wof:placetype":"venue"
},
  "geometry": {"coordinates":[-5.6585144997,43.5381278992],"type":"Point"}
}