{
  "type": "Feature",
  "properties": {
    "iso:country":"ES",
    "sg:address":"Av Rei Jaume I, 7",
    "sg:city":"Benidorm",
    "sg:orig_category":"Ropa Para Se\u00d1oras Y Caballeros (al Por Menor)",
    "sg:phone":"+34 965 86 16 98",
    "sg:postcode":"03500",
    "sg:province":"Alicante",
    "wof:name":"Ye  Lindin",
    "wof:placetype":"venue"
},
  "geometry": {"coordinates":[-0.1419433057,38.6189804077],"type":"Point"}
}