{
  "type": "Feature",
  "properties": {
    "iso:country":"ES",
    "sg:address":"Calle de Alfonso I, 13",
    "sg:city":"Gijon",
    "sg:orig_category":"Institutos De Belleza",
    "sg:phone":"+34 985 33 47 42",
    "sg:postcode":"33205",
    "sg:province":"Asturias",
    "wof:name":"Mari Cruz Granda Fernandez Y Jose Alvarez Suarez C.b.",
    "wof:placetype":"venue"
},
  "geometry": {"coordinates":[-5.6555404663,43.5362052917],"type":"Point"}
}