{
  "type": "Feature",
  "properties": {
    "iso:country":"ES",
    "sg:address":"Avda Concordia (de La), 64",
    "sg:city":"Molinos",
    "sg:orig_category":"Asistencia Social",
    "sg:phone":"+34 918 55 19 31",
    "sg:postcode":"28460",
    "sg:province":"Madrid",
    "wof:name":"Comunidad De Hermanas Marianitas",
    "wof:placetype":"venue"
},
  "geometry": {"coordinates":[-4.0646190643,40.7120704651],"type":"Point"}
}