{
  "type": "Feature",
  "properties": {
    "addr:full":"Calle de Callao De Lima, 64 Santa Cruz De Tenerife Santa Cruz De Tenerife 38002",
    "addr:housenumber":"64",
    "addr:postcode":"38002",
    "addr:street":"Calle De Callao De Lima",
    "iso:country":"ES",
    "sg:address":"Calle de Callao De Lima, 64",
    "sg:city":"Santa Cruz De Tenerife",
    "sg:orig_category":"Asesor\u00cda De Formaci\u00d3n Y Gesti\u00d3n De Personal",
    "sg:phone":"+34 922 24 21 63",
    "sg:postcode":"38002",
    "sg:province":"Santa Cruz De Tenerife",
    "wof:name":"C.b.cestaupineday Berastegui",
    "wof:placetype":"venue"
},
  "geometry": {"coordinates":[-16.2537403107,28.4695281982],"type":"Point"}
}