{
  "type": "Feature",
  "properties": {
    "addr:full":"Avda Denia, 17 Alacant Alicante 03002",
    "addr:housenumber":"17",
    "addr:postcode":"03002",
    "addr:street":"Avda Denia",
    "iso:country":"ES",
    "sg:address":"Avda Denia, 17",
    "sg:city":"Alacant",
    "sg:orig_category":"Armaduras De Hormig\u00d3n",
    "sg:phone":"+34 965 16 13 86",
    "sg:postcode":"03002",
    "sg:province":"Alicante",
    "sg:website":"www.etosa.es",
    "wof:name":"Etosa Obras Y Servicios S.a.",
    "wof:placetype":"venue"
},
  "geometry": {"coordinates":[-0.4731360078,38.3503723145],"type":"Point"}
}