{
  "type": "Feature",
  "properties": {
    "addr:full":"Prag Camp De L'arbre, S/n Estartit Girona 17258",
    "addr:housenumber":"s / n",
    "addr:postcode":"17258",
    "iso:country":"ES",
    "sg:address":"Prag Camp De L'arbre, S/n",
    "sg:city":"Estartit",
    "sg:orig_category":"Zonas De Acampada, Aparcamiento Para Caravanas",
    "sg:phone":"+34 972 75 18 05",
    "sg:postcode":"17258",
    "sg:province":"Girona",
    "wof:name":"Camping Les Medes S.l",
    "wof:placetype":"venue"
},
  "geometry": {"coordinates":[3.184910059,42.0473709106],"type":"Point"}
}