{
  "type": "Feature",
  "properties": {
    "addr:full":"Calle de Pintores, 18 Rota C\u00e1diz 11520",
    "addr:housenumber":"18",
    "addr:postcode":"11520",
    "addr:street":"Calle De Pintores;Ca\u0301Diz",
    "iso:country":"ES",
    "sg:address":"Calle de Pintores, 18",
    "sg:city":"Rota",
    "sg:orig_category":"Inmobiliaria (agencias)",
    "sg:phone":"+34 956 81 40 54",
    "sg:postcode":"11520",
    "sg:province":"C\u00e1diz",
    "wof:name":"Promociones Rotasol S.l.",
    "wof:placetype":"venue"
},
  "geometry": {"coordinates":[-6.3657522202,36.6325798035],"type":"Point"}
}