{
  "type": "Feature",
  "properties": {
    "addr:full":"Rbla Badal, 56 Barcelona Barcelona 08014",
    "addr:housenumber":"56",
    "addr:postcode":"08014",
    "addr:street":"Rbla Badal",
    "iso:country":"ES",
    "sg:address":"Rbla Badal, 56",
    "sg:city":"Barcelona",
    "sg:orig_category":"Peluqueros: De Se\u00d1oras",
    "sg:phone":"+34 933 32 92 44",
    "sg:postcode":"08014",
    "sg:province":"Barcelona",
    "wof:name":"Panduro Hernandez Ramona",
    "wof:placetype":"venue"
},
  "geometry": {"coordinates":[2.1338179111,41.3680305481],"type":"Point"}
}