{
  "type": "Feature",
  "properties": {
    "iso:country":"ES",
    "sg:address":"Av. B. Navarra, 13",
    "sg:city":"Iru\u00f1a",
    "sg:orig_category":"Farmacias",
    "sg:phone":"+34 948 22 86 37",
    "sg:postcode":"31002",
    "sg:province":"Navarra",
    "wof:name":"Ruiz-prados Garrigos Ignacio",
    "wof:placetype":"venue"
},
  "geometry": {"coordinates":[-1.6375509501,42.8135032654],"type":"Point"}
}