{
  "type": "Feature",
  "properties": {
    "addr:full":"Calle de General Vara De Rey, 15 Logro\u00f1o La Rioja 26002",
    "addr:housenumber":"15",
    "addr:postcode":"26002",
    "addr:street":"Calle De General Vara De Rey;Rioja",
    "iso:country":"ES",
    "sg:address":"Calle de General Vara De Rey, 15",
    "sg:city":"Logro\u00f1o",
    "sg:orig_category":"Peritos En C\u00c1lculo Inmobiliario, Industrial Y De Fondos De Comercio",
    "sg:phone":"+34 941 25 99 00",
    "sg:postcode":"26002",
    "sg:province":"La Rioja",
    "wof:name":"Gil-gibernau Abogados Asociados S.l.",
    "wof:placetype":"venue"
},
  "geometry": {"coordinates":[-2.4447097778,42.4631729126],"type":"Point"}
}