{
  "type": "Feature",
  "properties": {
    "iso:country":"ES",
    "sg:address":"Carrer de Morell, 23",
    "sg:city":"Reus",
    "sg:orig_category":"M\u00c1quinas De Coser Y De Hacer Punto (al Por Mayor)",
    "sg:phone":"+34 977 34 25 53",
    "sg:postcode":"43203",
    "sg:province":"Tarragona",
    "wof:name":"Cid Prades Federico",
    "wof:placetype":"venue"
},
  "geometry": {"coordinates":[1.1136100292,41.1611328125],"type":"Point"}
}