{
  "type": "Feature",
  "properties": {
    "addr:full":"Calle de Manuel Garcia, 15 Coin M\u00e1laga 29100",
    "addr:housenumber":"15",
    "addr:postcode":"29100",
    "addr:street":"Calle De Manuel Garcia;Ma\u0301Laga",
    "iso:country":"ES",
    "sg:address":"Calle de Manuel Garcia, 15",
    "sg:city":"Coin",
    "sg:orig_category":"Quincaller\u00cda (al Por Menor)",
    "sg:phone":"+34 952 45 05 86",
    "sg:postcode":"29100",
    "sg:province":"M\u00e1laga",
    "wof:name":"Ferreteria Cardenas S.l.",
    "wof:placetype":"venue"
},
  "geometry": {"coordinates":[-4.7568092346,36.6605911255],"type":"Point"}
}