{
  "type": "Feature",
  "properties": {
    "addr:full":"Carrer de Conveni, 27 Barcelona Barcelona 08016",
    "addr:housenumber":"27",
    "addr:postcode":"08016",
    "addr:street":"Carrer De Conveni",
    "iso:country":"ES",
    "sg:address":"Carrer de Conveni, 27",
    "sg:city":"Barcelona",
    "sg:orig_category":"Artes Gr\u00c1ficas, Artes Pl\u00c1sticas (curso)",
    "sg:phone":"+34 933 50 08 19",
    "sg:postcode":"08016",
    "sg:province":"Barcelona",
    "wof:name":"J.i.c. Grafic S.l.",
    "wof:placetype":"venue"
},
  "geometry": {"coordinates":[2.1842489243,41.4433174133],"type":"Point"}
}