{
  "type": "Feature",
  "properties": {
    "addr:full":"Calle de Echegaray, 10 Jaca Huesca 22700",
    "addr:housenumber":"10",
    "addr:postcode":"22700",
    "addr:street":"Calle De Echegaray",
    "iso:country":"ES",
    "sg:address":"Calle de Echegaray, 10",
    "sg:city":"Jaca",
    "sg:orig_category":"Art\u00cdculos De Regalo (al Por Menor)",
    "sg:phone":"+34 974 36 43 72",
    "sg:postcode":"22700",
    "sg:province":"Huesca",
    "wof:name":"Irigaray Agraz Maria Jesus",
    "wof:placetype":"venue"
},
  "geometry": {"coordinates":[-0.5493159294,42.57006073],"type":"Point"}
}