{
  "type": "Feature",
  "properties": {
    "iso:country":"ES",
    "sg:address":"Calle de Corredera, 49",
    "sg:city":"Baza",
    "sg:orig_category":"Agentes Generales De Seguros",
    "sg:phone":"+34 958 70 16 87",
    "sg:postcode":"18800",
    "sg:province":"Granada",
    "wof:name":"Segura Robles Maria Angeles",
    "wof:placetype":"venue"
},
  "geometry": {"coordinates":[-2.7699460983,37.4932098389],"type":"Point"}
}