{
  "type": "Feature",
  "properties": {
    "addr:full":"Ctra. S. Leonardo, S/n Vilviestre Pinar Burgos 09690",
    "addr:housenumber":"s / n",
    "addr:postcode":"09690",
    "addr:street":"Ctra. S. Leonardo",
    "iso:country":"ES",
    "sg:address":"Ctra. S. Leonardo, S/n",
    "sg:city":"Vilviestre Pinar",
    "sg:orig_category":"Negocio De Materiales De Construcci\u00d3n",
    "sg:phone":"+34 947 39 06 81",
    "sg:postcode":"09690",
    "sg:province":"Burgos",
    "wof:name":"Chapero Pascual Gonzalo",
    "wof:placetype":"venue"
},
  "geometry": {"coordinates":[-3.0747089386,41.9529838562],"type":"Point"}
}