{
  "type": "Feature",
  "properties": {
    "addr:full":"Calle de Enrique Larreta, 3 Madrid Madrid 28036",
    "addr:housenumber":"3",
    "addr:postcode":"28036",
    "addr:street":"Calle De Enrique Larreta",
    "iso:country":"ES",
    "sg:address":"Calle de Enrique Larreta, 3",
    "sg:city":"Madrid",
    "sg:orig_category":"Ingeniero",
    "sg:phone":"+34 913 15 44 21",
    "sg:postcode":"28036",
    "sg:province":"Madrid",
    "wof:name":"Proyectos Y Servicios Generales Para La Ciudad",
    "wof:placetype":"venue"
},
  "geometry": {"coordinates":[-3.6861810684,40.4671478271],"type":"Point"}
}