{
  "type": "Feature",
  "properties": {
    "addr:full":"Urb Encinas (las), 38 Pozuelo De Alarcon Madrid 28224",
    "addr:housenumber":"38",
    "addr:postcode":"28224",
    "addr:street":"Urb Encinas Las",
    "iso:country":"ES",
    "sg:address":"Urb Encinas (las), 38",
    "sg:city":"Pozuelo De Alarcon",
    "sg:orig_category":"Inmobiliaria (agencias)",
    "sg:phone":"+34 913 51 95 11",
    "sg:postcode":"28224",
    "sg:province":"Madrid",
    "wof:name":"Orca Ventures S.l.",
    "wof:placetype":"venue"
},
  "geometry": {"coordinates":[-3.8184390068,40.4449195862],"type":"Point"}
}