{
  "type": "Feature",
  "properties": {
    "addr:full":"Pase Artiga Ibilbidea, 18 Irun Guip\u00f9zcoa 20303",
    "addr:housenumber":"18",
    "addr:postcode":"20303",
    "addr:street":"Artiga Ibilbidea;Guipu\u0300Zcoa",
    "iso:country":"ES",
    "sg:address":"Pase Artiga Ibilbidea, 18",
    "sg:city":"Irun",
    "sg:orig_category":"Agentes, Concesionarios Y Sucursales De Veh\u00cdculos",
    "sg:phone":"+34 943 62 70 22",
    "sg:postcode":"20303",
    "sg:province":"Guip\u00f9zcoa",
    "wof:name":"Irun Motor S.a.",
    "wof:placetype":"venue"
},
  "geometry": {"coordinates":[-1.7902339697,43.3395233154],"type":"Point"}
}