{
  "type": "Feature",
  "properties": {
    "iso:country":"ES",
    "sg:address":"Avda Madridejos, 58",
    "sg:city":"Villaca\u00f1as",
    "sg:orig_category":"Estancos",
    "sg:phone":"+34 925 16 02 47",
    "sg:postcode":"45860",
    "sg:province":"Toledo",
    "wof:name":"Sesmero Infante Juan Carlos",
    "wof:placetype":"venue"
},
  "geometry": {"coordinates":[-3.3327970505,39.6216392517],"type":"Point"}
}