{
  "type": "Feature",
  "properties": {
    "iso:country":"ES",
    "sg:address":"Calle de Acera Fuente De La Salud, 5",
    "sg:city":"Cordoba",
    "sg:orig_category":"Fabricaci\u00d3n, Comercio De Muebles Para Ni\u00d1os",
    "sg:phone":"+34 957 40 88 04",
    "sg:postcode":"14006",
    "sg:province":"C\u00f3rdoba",
    "wof:name":"Cabezas Garcia Jose Angel",
    "wof:placetype":"venue"
},
  "geometry": {"coordinates":[-4.773920536,37.8966445923],"type":"Point"}
}