{
  "type": "Feature",
  "properties": {
    "addr:full":"Calle de Poligono Industrial, 11 Salda\u00f1a Palencia 34100",
    "addr:housenumber":"11",
    "addr:postcode":"34100",
    "addr:street":"Calle De Poligono Industrial",
    "iso:country":"ES",
    "sg:address":"Calle de Poligono Industrial, 11",
    "sg:city":"Salda\u00f1a",
    "sg:orig_category":"Agentes, Concesionarios Y Sucursales De Veh\u00cdculos",
    "sg:phone":"+34 979 89 06 99",
    "sg:postcode":"34100",
    "sg:province":"Palencia",
    "wof:name":"Autovalle Vehiculos S.l.",
    "wof:placetype":"venue"
},
  "geometry": {"coordinates":[-4.7445244789,42.5222587585],"type":"Point"}
}