{
  "type": "Feature",
  "properties": {
    "iso:country":"ES",
    "sg:address":"Calle de Amor De Dios, 19",
    "sg:city":"Madrid",
    "sg:orig_category":"Ropa Para Se\u00d1oras Y Caballeros (al Por Menor)",
    "sg:phone":"+34 914 29 55 21",
    "sg:postcode":"28014",
    "sg:province":"Madrid",
    "wof:name":"Armenta Martin Rafael",
    "wof:placetype":"venue"
},
  "geometry": {"coordinates":[-3.6985452175,40.4123382568],"type":"Point"}
}