{
  "type": "Feature",
  "properties": {
    "iso:country":"ES",
    "sg:address":"Avda Galicia, 23",
    "sg:city":"Vigo",
    "sg:orig_category":"Empresas De Carpinter\u00cda",
    "sg:phone":"+34 986 27 94 31",
    "sg:postcode":"36207",
    "sg:province":"Pontevedra",
    "wof:name":"Dominguez Garrido Manuel",
    "wof:placetype":"venue"
},
  "geometry": {"coordinates":[-8.6951551437,42.2502746582],"type":"Point"}
}