{
  "type": "Feature",
  "properties": {
    "addr:full":"Calle de Manuel Cuesta, 2 Dosbarrios Toledo 45311",
    "addr:housenumber":"2",
    "addr:postcode":"45311",
    "addr:street":"Calle De Manuel Cuesta",
    "iso:country":"ES",
    "sg:address":"Calle de Manuel Cuesta, 2",
    "sg:city":"Dosbarrios",
    "sg:orig_category":"Ense\u00d1anza Variada",
    "sg:phone":"+34 925 12 22 76",
    "sg:postcode":"45311",
    "sg:province":"Toledo",
    "wof:name":"Ised S.l.",
    "wof:placetype":"venue"
},
  "geometry": {"coordinates":[-3.4805541039,39.8828392029],"type":"Point"}
}