{
  "type": "Feature",
  "properties": {
    "iso:country":"ES",
    "sg:address":"Manganes, 2",
    "sg:city":"Pol. Ind. Can Pelegri",
    "sg:orig_category":"Venta, Instalaci\u00d3n De Calefacci\u00d3n",
    "sg:phone":"+34 936 82 80 40",
    "sg:postcode":"08755",
    "sg:province":"Barcelona",
    "wof:name":"Fabrigas S.l.",
    "wof:placetype":"venue"
},
  "geometry": {"coordinates":[1.9751399755,41.4769897461],"type":"Point"}
}