{
  "type": "Feature",
  "properties": {
    "addr:full":"Avda Estacion (la), 10 Alacant Alicante 03005",
    "addr:postcode":"03005",
    "addr:street":"Avda Estacion La",
    "iso:country":"ES",
    "sg:address":"Avda Estacion (la), 10",
    "sg:city":"Alacant",
    "sg:orig_category":"Centros Empresariales",
    "sg:phone":"+34 965 92 51 35",
    "sg:postcode":"03005",
    "sg:province":"Alicante",
    "wof:name":"Empresas Agrupadas Favia S.l.",
    "wof:placetype":"venue"
},
  "geometry": {"coordinates":[-0.493016988,38.3453216553],"type":"Point"}
}