{
  "type": "Feature",
  "properties": {
    "addr:full":"Calle de Mostoles (de), 89 Fuenlabrada Madrid 28942",
    "addr:housenumber":"89",
    "addr:postcode":"28942",
    "addr:street":"Calle De Mostoles De",
    "iso:country":"ES",
    "sg:address":"Calle de Mostoles (de), 89",
    "sg:city":"Fuenlabrada",
    "sg:orig_category":"Inmobiliaria (agencias)",
    "sg:phone":"+34 916 08 30 47",
    "sg:postcode":"28942",
    "sg:province":"Madrid",
    "wof:name":"Peeters  Werner",
    "wof:placetype":"venue"
},
  "geometry": {"coordinates":[-3.8121545315,40.2955245972],"type":"Point"}
}