{
  "type": "Feature",
  "properties": {
    "iso:country":"ES",
    "sg:address":"Calle de Juan Bravo, 56",
    "sg:city":"Segovia",
    "sg:orig_category":"Ropa Para Se\u00d1oras Y Caballeros (al Por Menor)",
    "sg:phone":"+34 921 46 27 46",
    "sg:postcode":"40001",
    "sg:province":"Segovia",
    "wof:name":"Redondo Y Tutor S. L.",
    "wof:placetype":"venue"
},
  "geometry": {"coordinates":[-4.120112896,40.9480285645],"type":"Point"}
}