{
  "type": "Feature",
  "properties": {
    "iso:country":"ES",
    "sg:address":"Calle de Pedro Laborde, 10",
    "sg:city":"Madrid",
    "sg:orig_category":"Producci\u00d3n, Distribuci\u00d3n De Electricidad",
    "sg:phone":"+34 913 03 93 04",
    "sg:postcode":"28038",
    "sg:province":"Madrid",
    "wof:name":"Ibercentro Materiales Electricos S.l.",
    "wof:placetype":"venue"
},
  "geometry": {"coordinates":[-3.6474950314,40.3894462585],"type":"Point"}
}