{
  "type": "Feature",
  "properties": {
    "iso:country":"ES",
    "sg:address":"Calle de Juan Relinque, 65",
    "sg:city":"Vejer De La Frontera",
    "sg:orig_category":"Abogados",
    "sg:phone":"+34 956 45 12 31",
    "sg:postcode":"11150",
    "sg:province":"C\u00e1diz",
    "wof:name":"Quintero Basallote Juan Jose",
    "wof:placetype":"venue"
},
  "geometry": {"coordinates":[-5.9661397934,36.2518806458],"type":"Point"}
}