{
  "type": "Feature",
  "properties": {
    "iso:country":"ES",
    "sg:address":"Carr Padre Antonio Berenguer, 1",
    "sg:city":"Cullera",
    "sg:orig_category":"Delegados, Agentes De Tr\u00c1nsito, Auxiliares De Transporte Internacional",
    "sg:phone":"+34 961 72 14 38",
    "sg:postcode":"46400",
    "sg:province":"Valencia",
    "wof:name":"Bayona Martinez Purificacion",
    "wof:placetype":"venue"
},
  "geometry": {"coordinates":[-0.2521359921,39.16198349],"type":"Point"}
}