{
  "type": "Feature",
  "properties": {
    "iso:country":"ES",
    "sg:address":"Av Novelda, 105",
    "sg:city":"Elche",
    "sg:orig_category":"Mec\u00c1nico Del Autom\u00d3vil",
    "sg:phone":"+34 965 46 43 15",
    "sg:postcode":"03205",
    "sg:province":"Alicante",
    "wof:name":"Talleres Carrasquilla S.l.",
    "wof:placetype":"venue"
},
  "geometry": {"coordinates":[-0.7141240239,38.2753601074],"type":"Point"}
}