{
  "type": "Feature",
  "properties": {
    "addr:full":"Calle de Concha General, 12 Bilbao Vizcaya 48008",
    "addr:housenumber":"12",
    "addr:postcode":"48008",
    "addr:street":"Calle De Concha General",
    "iso:country":"ES",
    "sg:address":"Calle de Concha General, 12",
    "sg:city":"Bilbao",
    "sg:orig_category":"Fisioterapia",
    "sg:phone":"+34 944 10 38 59",
    "sg:postcode":"48008",
    "sg:province":"Vizcaya",
    "wof:name":"Taranilla Iturralde Maria Concepcion",
    "wof:placetype":"venue"
},
  "geometry": {"coordinates":[-2.93481493,43.2599868774],"type":"Point"}
}