{
  "type": "Feature",
  "properties": {
    "iso:country":"ES",
    "sg:address":"Avda J. Solis Ruiz, 30",
    "sg:city":"Cabra",
    "sg:orig_category":"M\u00c9dicos: Estomatolog\u00cda",
    "sg:phone":"+34 957 52 40 41",
    "sg:postcode":"14940",
    "sg:province":"C\u00f3rdoba",
    "wof:name":"Gomez De Aranda Algar Luisa Carmen",
    "wof:placetype":"venue"
},
  "geometry": {"coordinates":[-4.4424290657,37.4739608765],"type":"Point"}
}