{
  "type": "Feature",
  "properties": {
    "addr:full":"Calle de Doctor Miguel Lopez Gonzalez, 4 Santa Cruz De Tenerife Santa Cruz De Tenerife 38003",
    "addr:housenumber":"4",
    "addr:postcode":"38003",
    "addr:street":"Calle De Doctor Miguel Lopez Gonzalez",
    "iso:country":"ES",
    "sg:address":"Calle de Doctor Miguel Lopez Gonzalez, 4",
    "sg:city":"Santa Cruz De Tenerife",
    "sg:orig_category":"Abogados",
    "sg:phone":"+34 922 24 59 72",
    "sg:postcode":"38003",
    "sg:province":"Santa Cruz De Tenerife",
    "wof:name":"Hernandez Gutierrez Eligio",
    "wof:placetype":"venue"
},
  "geometry": {"coordinates":[-16.2539043427,28.4657840729],"type":"Point"}
}