{
  "type": "Feature",
  "properties": {
    "addr:full":"Calle de Iruela (la), 19 Jaen Ja\u00e9n 23009",
    "addr:housenumber":"19;jae\u0301n",
    "addr:postcode":"23009",
    "addr:street":"Calle De Iruela La",
    "iso:country":"ES",
    "sg:address":"Calle de Iruela (la), 19",
    "sg:city":"Jaen",
    "sg:orig_category":"Automatizaci\u00d3n De Procesos Industriales Y De Edificaci\u00d3n (estudios, Instalaci\u00d3n)",
    "sg:phone":"+34 953 28 00 24",
    "sg:postcode":"23009",
    "sg:province":"Ja\u00e9n",
    "wof:name":"Acosta Ramiro Gines",
    "wof:placetype":"venue"
},
  "geometry": {"coordinates":[-3.7816324234,37.8035736084],"type":"Point"}
}