{
  "type": "Feature",
  "properties": {
    "addr:full":"Calle de Castelar, 16 Rota C\u00e1diz 11520",
    "addr:housenumber":"16",
    "addr:postcode":"11520",
    "addr:street":"Calle De Castelar;Ca\u0301Diz",
    "iso:country":"ES",
    "sg:address":"Calle de Castelar, 16",
    "sg:city":"Rota",
    "sg:orig_category":"M\u00c9dicos: An\u00c1lisis Cl\u00cdnicos",
    "sg:phone":"+34 956 81 42 66",
    "sg:postcode":"11520",
    "sg:province":"C\u00e1diz",
    "wof:name":"Lobato Moreno Jose Luis",
    "wof:placetype":"venue"
},
  "geometry": {"coordinates":[-6.3587236404,36.6195755005],"type":"Point"}
}