{
  "type": "Feature",
  "properties": {
    "addr:full":"Calle de Ayala, 9 Malaga M\u00e1laga 29002",
    "addr:housenumber":"9",
    "addr:postcode":"29002",
    "addr:street":"Calle De Ayala;Ma\u0301Laga",
    "iso:country":"ES",
    "sg:address":"Calle de Ayala, 9",
    "sg:city":"Malaga",
    "sg:orig_category":"Farmacias",
    "sg:phone":"+34 952 31 70 93",
    "sg:postcode":"29002",
    "sg:province":"M\u00e1laga",
    "wof:name":"Ana Marina Carrasco Y Maria Del Mar Orellana C.b.",
    "wof:placetype":"venue"
},
  "geometry": {"coordinates":[-4.4310283661,36.7102470398],"type":"Point"}
}