{
  "type": "Feature",
  "properties": {
    "iso:country":"ES",
    "sg:address":"Carrer de Gremi De Sabaters, 10",
    "sg:city":"Poligon Industrial De Son Castello",
    "sg:orig_category":"Perfumer\u00cda, Art\u00cdculos De Ba\u00d1o (fabricaci\u00d3n, Al Por Mayor)",
    "sg:phone":"+34 971 43 26 62",
    "sg:postcode":"07009",
    "sg:province":"Islas Baleares",
    "wof:name":"Sans S. A.",
    "wof:placetype":"venue"
},
  "geometry": {"coordinates":[2.6741399765,39.6011390686],"type":"Point"}
}