{
  "type": "Feature",
  "properties": {
    "iso:country":"ES",
    "sg:address":"Carrer de Andreu Feliu, 41",
    "sg:city":"Palma",
    "sg:orig_category":"Peluqueros: De Se\u00d1oras",
    "sg:phone":"+34 971 20 75 66",
    "sg:postcode":"07010",
    "sg:province":"Islas Baleares",
    "wof:name":"Garcia Bonet Josefa",
    "wof:placetype":"venue"
},
  "geometry": {"coordinates":[2.6476559639,39.5829391479],"type":"Point"}
}