{
  "type": "Feature",
  "properties": {
    "addr:full":"Calle de Murcia, 1 Almeria Almer\u00eda 04004",
    "addr:housenumber":"1",
    "addr:postcode":"04004",
    "addr:street":"Calle De Murcia",
    "iso:country":"ES",
    "sg:address":"Calle de Murcia, 1",
    "sg:city":"Almeria",
    "sg:orig_category":"Abogados",
    "sg:phone":"+34 950 25 70 93",
    "sg:postcode":"04004",
    "sg:province":"Almer\u00eda",
    "wof:name":"Gomez Polo Maria Del Mar",
    "wof:placetype":"venue"
},
  "geometry": {"coordinates":[-2.4626729488,36.8422813416],"type":"Point"}
}