{
  "type": "Feature",
  "properties": {
    "addr:full":"Carrer de Cristofor Colom, De, 60 Porto Petro Islas Baleares 07691",
    "addr:housenumber":"60",
    "addr:postcode":"07691",
    "addr:street":"Carrer De Cristofor Colom De",
    "iso:country":"ES",
    "sg:address":"Carrer de Cristofor Colom, De, 60",
    "sg:city":"Porto Petro",
    "sg:orig_category":"Parques De Atracciones Y Centros De Esparcimiento",
    "sg:phone":"+34 971 65 70 12",
    "sg:postcode":"07691",
    "sg:province":"Islas Baleares",
    "wof:name":"Rigo Rigo Miguel",
    "wof:placetype":"venue"
},
  "geometry": {"coordinates":[3.2106349468,39.362991333],"type":"Point"}
}