{
  "type": "Feature",
  "properties": {
    "addr:full":"Calle de Parroco Camino, 1 Luarca Asturias 33700",
    "addr:housenumber":"1",
    "addr:postcode":"33700",
    "addr:street":"Calle De Parroco Camino",
    "iso:country":"ES",
    "sg:address":"Calle de Parroco Camino, 1",
    "sg:city":"Luarca",
    "sg:orig_category":"Bancos",
    "sg:phone":"+34 985 64 00 79",
    "sg:postcode":"33700",
    "sg:province":"Asturias",
    "sg:website":"www.bancoherrero.es",
    "wof:name":"Banc Sabadell S.a.",
    "wof:placetype":"venue"
},
  "geometry": {"coordinates":[-6.5345277786,43.5448722839],"type":"Point"}
}