{
  "type": "Feature",
  "properties": {
    "iso:country":"ES",
    "sg:address":"San Martin, 15",
    "sg:city":"Ardanaz De Izagaondoa",
    "sg:orig_category":"Semiller\u00cdas",
    "sg:phone":"+34 948 33 82 50",
    "sg:postcode":"31421",
    "sg:province":"Navarra",
    "wof:name":"Lur Beltz S.a.t.",
    "wof:placetype":"venue"
},
  "geometry": {"coordinates":[-1.4222780466,42.7366256714],"type":"Point"}
}