{
  "type": "Feature",
  "properties": {
    "iso:country":"ES",
    "sg:address":"Avda San Roque De Afuera, S/n",
    "sg:city":"Coru\u00d1a",
    "sg:orig_category":"Crust\u00c1ceos Y Almejas (al Por Mayor)",
    "sg:phone":"+34 981 25 31 36",
    "sg:postcode":"15011",
    "sg:province":"La Coru\u00f1a",
    "wof:name":"Otamendi Busto Angel Maria",
    "wof:placetype":"venue"
},
  "geometry": {"coordinates":[-8.4188737869,43.3716506958],"type":"Point"}
}