{
  "type": "Feature",
  "properties": {
    "iso:country":"ES",
    "sg:address":"Major, 8",
    "sg:city":"Alquerias Ni\u00f1o Perdido",
    "sg:orig_category":"Carnicer\u00cdas, Carnicer\u00cdas",
    "sg:phone":"+34 964 51 12 61",
    "sg:postcode":"12539",
    "sg:province":"Castell\u00f3n",
    "wof:name":"Gargallo Ballester Ismael",
    "wof:placetype":"venue"
},
  "geometry": {"coordinates":[-0.0833012983,39.8902168274],"type":"Point"}
}