{
  "type": "Feature",
  "properties": {
    "addr:full":"Avda Menendez Pelayo, 85 Madrid Madrid 28007",
    "addr:housenumber":"85",
    "addr:postcode":"madrid;28007",
    "addr:street":"Avda Menendez Pelayo",
    "iso:country":"ES",
    "sg:address":"Avda Menendez Pelayo, 85",
    "sg:city":"Madrid",
    "sg:orig_category":"Abogados",
    "sg:phone":"+34 914 34 13 85",
    "sg:postcode":"28007",
    "sg:province":"Madrid",
    "wof:name":"Alonso Gonzalez Manuel",
    "wof:placetype":"venue"
},
  "geometry": {"coordinates":[-3.6778459549,40.4088821411],"type":"Point"}
}