{
  "type": "Feature",
  "properties": {
    "addr:full":"Rua Gandara, 10 Boimorto La Coru\u00f1a 15818",
    "addr:housenumber":"10",
    "addr:postcode":"15818",
    "addr:street":"Rua Gandara;La Corun\u0303A",
    "iso:country":"ES",
    "sg:address":"Rua Gandara, 10",
    "sg:city":"Boimorto",
    "sg:orig_category":"Poller\u00cda Y Caza (al Por Menor)",
    "sg:phone":"+34 981 51 62 21",
    "sg:postcode":"15818",
    "sg:province":"La Coru\u00f1a",
    "wof:name":"Lopez Vazquez Jose Javier",
    "wof:placetype":"venue"
},
  "geometry": {"coordinates":[-8.1347694397,42.9994888306],"type":"Point"}
}