{
  "type": "Feature",
  "properties": {
    "addr:full":"Carrer de Cobalt, 154 Hospitalet Llobregat Barcelona 08907",
    "addr:housenumber":"154",
    "addr:postcode":"08907",
    "addr:street":"Carrer De Cobalt",
    "iso:country":"ES",
    "sg:address":"Carrer de Cobalt, 154",
    "sg:city":"Hospitalet Llobregat",
    "sg:orig_category":"Fabricaci\u00d3n De Moldes Y Modelos",
    "sg:phone":"+34 933 37 41 95",
    "sg:postcode":"08907",
    "sg:province":"Barcelona",
    "wof:name":"Carmar Plastic S.l.",
    "wof:placetype":"venue"
},
  "geometry": {"coordinates":[2.101774931,41.3557243347],"type":"Point"}
}