{
  "type": "Feature",
  "properties": {
    "iso:country":"ES",
    "sg:address":"Ctra. S-lisboa, S/n",
    "sg:city":"Aroche",
    "sg:orig_category":"Producci\u00d3n, Venta De Productos De Agricultura Biol\u00d3gica",
    "sg:phone":"+34 959 50 12 29",
    "sg:postcode":"21240",
    "sg:province":"Huelva",
    "wof:name":"Las Cerrajas S.l.",
    "wof:placetype":"venue"
},
  "geometry": {"coordinates":[-6.9558401108,37.9458808899],"type":"Point"}
}