{
  "type": "Feature",
  "properties": {
    "iso:country":"ES",
    "sg:address":"Avda Constitucion, 88",
    "sg:city":"Cistierna",
    "sg:orig_category":"Sociedades, Compa\u00d1\u00cdas Aseguradoras",
    "sg:phone":"+34 987 70 02 68",
    "sg:postcode":"24800",
    "sg:province":"Le\u00f3n",
    "wof:name":"Higuera Asesoria S.l.",
    "wof:placetype":"venue"
},
  "geometry": {"coordinates":[-5.1296391487,42.8069190979],"type":"Point"}
}