{
  "type": "Feature",
  "properties": {
    "addr:full":"Calle de Carrera, 18 Villanueva Arzobispo Ja\u00e9n 23330",
    "addr:postcode":"23330",
    "addr:street":"Calle De Carrera 18;Arzobispo Jae\u0301N",
    "iso:country":"ES",
    "sg:address":"Calle de Carrera, 18",
    "sg:city":"Villanueva Arzobispo",
    "sg:orig_category":"Ropa Para Beb\u00c9s Y Ni\u00d1os (confecci\u00d3n, Al Por Mayor)",
    "sg:phone":"+34 953 45 06 17",
    "sg:postcode":"23330",
    "sg:province":"Ja\u00e9n",
    "wof:name":"Fernandez Roble Maria Jose",
    "wof:placetype":"venue"
},
  "geometry": {"coordinates":[-3.0084247589,38.1699295044],"type":"Point"}
}