{
  "type": "Feature",
  "properties": {
    "iso:country":"ES",
    "sg:address":"Calle de Calvario, 9",
    "sg:city":"Marbella",
    "sg:orig_category":"M\u00c9dicos: Radioterapia (radioterapia Como Opci\u00d3n Oncol\u00d3gica)",
    "sg:phone":"+34 952 76 47 33",
    "sg:postcode":"29600",
    "sg:province":"M\u00e1laga",
    "wof:name":"Pardo Gomez Luis",
    "wof:placetype":"venue"
},
  "geometry": {"coordinates":[-4.8911485672,36.5142440796],"type":"Point"}
}