{
  "type": "Feature",
  "properties": {
    "iso:country":"ES",
    "sg:address":"C/ Esperan\u00c7a, 30",
    "sg:city":"Manacor",
    "sg:orig_category":"Empresas De Carpinter\u00cda De Madera",
    "sg:phone":"+34 971 84 34 06",
    "sg:postcode":"07500",
    "sg:province":"Islas Baleares",
    "wof:name":"Riera Veny C.b.",
    "wof:placetype":"venue"
},
  "geometry": {"coordinates":[3.2151260376,39.5709495544],"type":"Point"}
}