{
  "type": "Feature",
  "properties": {
    "addr:full":"Agua Perra, S/n Puerto Rico Las Palmas 35130",
    "addr:housenumber":"s / n",
    "addr:postcode":"35130",
    "addr:street":"Perra;Rico",
    "iso:country":"ES",
    "sg:address":"Agua Perra, S/n",
    "sg:city":"Puerto Rico",
    "sg:orig_category":"Restaurantes",
    "sg:phone":"+34 928 56 20 44",
    "sg:postcode":"35130",
    "sg:province":"Las Palmas",
    "wof:name":"Ferreiro Perez Jose Ramon",
    "wof:placetype":"venue"
},
  "geometry": {"coordinates":[-13.9036235809,28.6303958893],"type":"Point"}
}