{
  "type": "Feature",
  "properties": {
    "addr:full":"Rua Dinan, 2 Lugo Lugo 27002",
    "addr:housenumber":"2",
    "addr:postcode":"27002",
    "addr:street":"Rua Dinan",
    "iso:country":"ES",
    "sg:address":"Rua Dinan, 2",
    "sg:city":"Lugo",
    "sg:orig_category":"Abogados",
    "sg:phone":"+34 982 25 26 08",
    "sg:postcode":"27002",
    "sg:province":"Lugo",
    "wof:name":"Portela Alvarez Manuel",
    "wof:placetype":"venue"
},
  "geometry": {"coordinates":[-7.5532422066,43.0073051453],"type":"Point"}
}