{
  "type": "Feature",
  "properties": {
    "iso:country":"ES",
    "sg:address":"Carrer de Sant Miquel, 2",
    "sg:city":"S. Adria Besos",
    "sg:orig_category":"Cerrajer\u00cda, Ferrallista",
    "sg:phone":"+34 933 81 74 06",
    "sg:postcode":"08930",
    "sg:province":"Barcelona",
    "wof:name":"Rojas Ferreiro Jorge",
    "wof:placetype":"venue"
},
  "geometry": {"coordinates":[2.2203190327,41.4297523499],"type":"Point"}
}