{
  "type": "Feature",
  "properties": {
    "iso:country":"ES",
    "sg:address":"Calle de Porto Alegre, 6",
    "sg:city":"Alcorcon",
    "sg:orig_category":"Administradores De Bienes Y Delegados De Comunidades De Propietarios",
    "sg:phone":"+34 916 19 68 08",
    "sg:postcode":"28925",
    "sg:province":"Madrid",
    "wof:name":"Yuste Casanez Alfonso",
    "wof:placetype":"venue"
},
  "geometry": {"coordinates":[-3.8160119057,40.354511261],"type":"Point"}
}