{
  "type": "Feature",
  "properties": {
    "iso:country":"ES",
    "sg:address":"Avda Alicante, 60",
    "sg:city":"Villena",
    "sg:orig_category":"Comercio De Piezas De Recambio Y De Accesorios De Veh\u00cdculos, Veh\u00cdculos Industriales",
    "sg:phone":"+34 965 81 35 86",
    "sg:postcode":"03400",
    "sg:province":"Alicante",
    "wof:name":"Repuestos Serca S.l.u.",
    "wof:placetype":"venue"
},
  "geometry": {"coordinates":[-0.8551070094,38.6296424866],"type":"Point"}
}