{
  "type": "Feature",
  "properties": {
    "addr:full":"Pl Cuba, 3 Mataro Barcelona 08302",
    "addr:housenumber":"3",
    "addr:postcode":"08302",
    "addr:street":"Pl Cuba",
    "iso:country":"ES",
    "sg:address":"Pl Cuba, 3",
    "sg:city":"Mataro",
    "sg:classifiers":[
        {
            "category":"Personal",
            "subcategory":"Barber",
            "type":"Services"
        }
    ],
    "sg:phone":"+34 937 99 26 77",
    "sg:postcode":"08302",
    "sg:province":"Barcelona",
    "sg:tags":[
        "caballeros",
        "de",
        "peluqueros"
    ],
    "wof:name":"Fornaguera Valls Antonio",
    "wof:placetype":"venue"
},
  "geometry": {"coordinates":[2.4404389858,41.5376434326],"type":"Point"}
}