{
  "type": "Feature",
  "properties": {
    "iso:country":"ES",
    "sg:address":"Calle de Pirineos, 1",
    "sg:city":"Pedrola",
    "sg:orig_category":"Negocio De Metales No Ferrosos",
    "sg:phone":"+34 976 61 14 14",
    "sg:postcode":"50690",
    "sg:province":"Zaragoza",
    "wof:name":"Cortes Y Aplanaciones S.a.",
    "wof:placetype":"venue"
},
  "geometry": {"coordinates":[-1.1836179495,41.7398872375],"type":"Point"}
}