{
  "type": "Feature",
  "properties": {
    "iso:country":"ES",
    "sg:address":"Trav De Gracia, 212",
    "sg:city":"Barcelona",
    "sg:orig_category":"Complementos De Vestir (al Por Menor)",
    "sg:phone":"+34 932 84 62 60",
    "sg:postcode":"08012",
    "sg:province":"Barcelona",
    "wof:name":"Siles Monta\u00f1es Miguel",
    "wof:placetype":"venue"
},
  "geometry": {"coordinates":[2.1615400314,41.4035720825],"type":"Point"}
}