{
  "type": "Feature",
  "properties": {
    "iso:country":"ES",
    "sg:address":"Carrer de Rossello, 306",
    "sg:city":"Barcelona",
    "sg:orig_category":"Carnicer\u00cdas, Carnicer\u00cdas",
    "sg:phone":"+34 934 57 66 52",
    "sg:postcode":"08037",
    "sg:province":"Barcelona",
    "wof:name":"Cebrian Bayot Maria Dolores",
    "wof:placetype":"venue"
},
  "geometry": {"coordinates":[2.1673278809,41.40076828],"type":"Point"}
}