{
  "type": "Feature",
  "properties": {
    "iso:country":"ES",
    "sg:address":"Calle de Asturias, 30",
    "sg:city":"Oviedo",
    "sg:orig_category":"Abogados",
    "sg:phone":"+34 985 27 36 17",
    "sg:postcode":"33004",
    "sg:province":"Asturias",
    "wof:name":"Tuero Y Orejas Abogados C.b.",
    "wof:placetype":"venue"
},
  "geometry": {"coordinates":[-5.8564071655,43.3641319275],"type":"Point"}
}