{
  "type": "Feature",
  "properties": {
    "addr:full":"Calle de Mayor, 8 Alcorcon Madrid 28921",
    "addr:housenumber":"8",
    "addr:postcode":"28921",
    "addr:street":"Calle De Mayor",
    "iso:country":"ES",
    "sg:address":"Calle de Mayor, 8",
    "sg:city":"Alcorcon",
    "sg:orig_category":"Abogados",
    "sg:phone":"+34 916 12 64 60",
    "sg:postcode":"28921",
    "sg:province":"Madrid",
    "wof:name":"Montero Arroyo Francisco Jose",
    "wof:placetype":"venue"
},
  "geometry": {"coordinates":[-3.8278493881,40.3483200073],"type":"Point"}
}