{
  "type": "Feature",
  "properties": {
    "iso:country":"ES",
    "sg:address":"Estd Santo Agosti\u00d1o (de), 9",
    "sg:city":"Viana Do Bolo",
    "sg:orig_category":"Molduras, Junquillos, Listones Y Molduras Perforadas",
    "sg:phone":"+34 988 34 08 07",
    "sg:postcode":"32550",
    "sg:province":"Ourense",
    "wof:name":"Telefourense S.l.",
    "wof:placetype":"venue"
},
  "geometry": {"coordinates":[-7.1098628044,42.1833190918],"type":"Point"}
}