{
  "type": "Feature",
  "properties": {
    "addr:full":"Calle de Principe De Vergara, 43 Madrid Madrid 28001",
    "addr:housenumber":"43",
    "addr:postcode":"madrid;28001",
    "addr:street":"Calle De Principe De Vergara",
    "iso:country":"ES",
    "sg:address":"Calle de Principe De Vergara, 43",
    "sg:city":"Madrid",
    "sg:orig_category":"Molduras, Junquillos, Listones Y Molduras Perforadas",
    "sg:phone":"+34 915 76 00 18",
    "sg:postcode":"28001",
    "sg:province":"Madrid",
    "wof:name":"Nieto Collado Felicisimo",
    "wof:placetype":"venue"
},
  "geometry": {"coordinates":[-3.6799991131,40.4291114807],"type":"Point"}
}