{
  "type": "Feature",
  "properties": {
    "iso:country":"ES",
    "sg:address":"Calle de Portales, 47",
    "sg:city":"Logro\u00f1o",
    "sg:orig_category":"Traductores",
    "sg:phone":"+34 941 27 01 02",
    "sg:postcode":"26001",
    "sg:province":"La Rioja",
    "wof:name":"Linguatraining S.l.",
    "wof:placetype":"venue"
},
  "geometry": {"coordinates":[-2.4462900162,42.4663772583],"type":"Point"}
}