{
  "type": "Feature",
  "properties": {
    "iso:country":"ES",
    "sg:address":"C/ General Weyler, 176",
    "sg:city":"Inca",
    "sg:orig_category":"Electricidad: Instaladores",
    "sg:phone":"+34 971 50 29 55",
    "sg:postcode":"07300",
    "sg:province":"Islas Baleares",
    "wof:name":"Bernabe Berenguer Jose",
    "wof:placetype":"venue"
},
  "geometry": {"coordinates":[2.9018681049,39.7175292969],"type":"Point"}
}