{
  "type": "Feature",
  "properties": {
    "iso:country":"ES",
    "sg:address":"Calle de Cami Real, 11",
    "sg:city":"Sagunt",
    "sg:orig_category":"Centros De Coordinaci\u00d3n",
    "sg:phone":"+34 962 65 04 69",
    "sg:postcode":"46500",
    "sg:province":"Valencia",
    "wof:name":"Ordaz Oltra Jose Manuel",
    "wof:placetype":"venue"
},
  "geometry": {"coordinates":[-0.2777734101,39.6800003052],"type":"Point"}
}