{
  "type": "Feature",
  "properties": {
    "iso:country":"ES",
    "sg:address":"Avda Estacion (da), 15",
    "sg:city":"Barco",
    "sg:orig_category":"Arquitectos",
    "sg:phone":"+34 988 32 73 36",
    "sg:postcode":"32300",
    "sg:province":"Ourense",
    "wof:name":"Dominguez Real Ramiro",
    "wof:placetype":"venue"
},
  "geometry": {"coordinates":[-6.9855861664,42.4166488647],"type":"Point"}
}