{
  "type": "Feature",
  "properties": {
    "iso:country":"ES",
    "sg:address":"Calle de Armengual De La Mota, 12",
    "sg:city":"Malaga",
    "sg:orig_category":"Muebles, Minoristas",
    "sg:phone":"+34 952 61 43 44",
    "sg:postcode":"29007",
    "sg:province":"M\u00e1laga",
    "wof:name":"El Oriente Colonial",
    "wof:placetype":"venue"
},
  "geometry": {"coordinates":[-4.4293150902,36.7186927795],"type":"Point"}
}