{
  "type": "Feature",
  "properties": {
    "addr:full":"Pza. Mina, 18 Dos Hermanas Sevilla 41700",
    "addr:postcode":"41700",
    "addr:street":"Mina 18",
    "iso:country":"ES",
    "sg:address":"Pza. Mina, 18",
    "sg:city":"Dos Hermanas",
    "sg:orig_category":"Bisuter\u00cda, Joyer\u00cda, Relojer\u00cda (al Por Menor)",
    "sg:phone":"+34 955 66 52 80",
    "sg:postcode":"41700",
    "sg:province":"Sevilla",
    "wof:name":"Palomo Chacon Fernando",
    "wof:placetype":"venue"
},
  "geometry": {"coordinates":[-5.9212298393,37.2824516296],"type":"Point"}
}