{
  "type": "Feature",
  "properties": {
    "iso:country":"ES",
    "sg:address":"Carrer de Alcala De Guadaira, 5",
    "sg:city":"Barcelona",
    "sg:classifiers":[
        {
            "category":"Autos & Motor Vehicles",
            "subcategory":"Automobile Sales",
            "type":"Retail Goods"
        }
    ],
    "sg:phone":"+34 933 07 59 44",
    "sg:postcode":"08020",
    "sg:province":"Barcelona",
    "wof:name":"Solar Azul S.l.",
    "wof:placetype":"venue"
},
  "geometry": {"coordinates":[2.1969630718,41.4169311523],"type":"Point"}
}