{
  "type": "Feature",
  "properties": {
    "iso:country":"ES",
    "sg:address":"Pg Maragall, 207",
    "sg:city":"Barcelona",
    "sg:orig_category":"Bisuter\u00cda, Joyer\u00cda, Relojer\u00cda (al Por Menor)",
    "sg:phone":"+34 934 08 69 57",
    "sg:postcode":"08041",
    "sg:province":"Barcelona",
    "wof:name":"Figueras Reverter Cristina",
    "wof:placetype":"venue"
},
  "geometry": {"coordinates":[2.176774025,41.424571991],"type":"Point"}
}