{
  "type": "Feature",
  "properties": {
    "iso:country":"ES",
    "sg:address":"Calle de Montesa, 43",
    "sg:city":"Madrid",
    "sg:orig_category":"Asesor\u00cda Sobre Comunicaci\u00d3n De Empresas",
    "sg:phone":"+34 914 01 63 50",
    "sg:postcode":"28006",
    "sg:province":"Madrid",
    "wof:name":"Suarez Fernandez Jesus Angel",
    "wof:placetype":"venue"
},
  "geometry": {"coordinates":[-3.6721477509,40.4307403564],"type":"Point"}
}