{
  "type": "Feature",
  "properties": {
    "iso:country":"ES",
    "sg:address":"Plaz Major, 13",
    "sg:city":"Torrent",
    "sg:orig_category":"Centros De Coordinaci\u00d3n",
    "sg:phone":"+34 961 56 42 35",
    "sg:postcode":"46900",
    "sg:province":"Valencia",
    "wof:name":"Administracion Y Gestion Torrent S.l.",
    "wof:placetype":"venue"
},
  "geometry": {"coordinates":[-0.4639169872,39.4360923767],"type":"Point"}
}