{
  "type": "Feature",
  "properties": {
    "iso:country":"ES",
    "sg:address":"Calle de Puentezuelas, 49",
    "sg:city":"Granada",
    "sg:orig_category":"Fabricaci\u00d3n, Importaci\u00d3n, Venta De Material De Telefon\u00cda, Peritelefon\u00cda",
    "sg:phone":"+34 958 53 63 03",
    "sg:postcode":"18002",
    "sg:province":"Granada",
    "wof:name":"Jecomtel Comunicaciones S.l.",
    "wof:placetype":"venue"
},
  "geometry": {"coordinates":[-3.6031389236,37.1748504639],"type":"Point"}
}