{
  "type": "Feature",
  "properties": {
    "addr:full":"Carrer de Baro D'esponella, 33 Barcelona Barcelona 08031",
    "addr:housenumber":"33",
    "addr:postcode":"08031",
    "addr:street":"Carrer De Baro D'Esponella",
    "iso:country":"ES",
    "sg:address":"Carrer de Baro D'esponella, 33",
    "sg:city":"Barcelona",
    "sg:orig_category":"Agentes Generales De Seguros",
    "sg:phone":"+34 933 40 25 80",
    "sg:postcode":"08031",
    "sg:province":"Barcelona",
    "wof:name":"Jose Maria Jornet Jornet S.c.p.",
    "wof:placetype":"venue"
},
  "geometry": {"coordinates":[2.1733725071,41.4283370972],"type":"Point"}
}