{
  "type": "Feature",
  "properties": {
    "addr:full":"C/ Joaquim Sorolla, 24 Alcoi Alicante 03802",
    "addr:housenumber":"24",
    "addr:postcode":"03802",
    "addr:street":"C / Joaquim Sorolla",
    "iso:country":"ES",
    "sg:address":"C/ Joaquim Sorolla, 24",
    "sg:city":"Alcoi",
    "sg:orig_category":"Molduras, Junquillos, Listones Y Molduras Perforadas",
    "sg:phone":"+34 965 52 52 32",
    "sg:postcode":"03802",
    "sg:province":"Alicante",
    "wof:name":"Peiro Miralles Marcos",
    "wof:placetype":"venue"
},
  "geometry": {"coordinates":[-0.4854109883,38.6979598999],"type":"Point"}
}