{
  "type": "Feature",
  "properties": {
    "iso:country":"ES",
    "sg:address":"Carrer de Cavallers, 9",
    "sg:city":"Pedreguer",
    "sg:orig_category":"Quincaller\u00cda (al Por Menor)",
    "sg:phone":"+34 965 76 06 80",
    "sg:postcode":"03750",
    "sg:province":"Alicante",
    "wof:name":"Garcia Artigues Jose Vicente",
    "wof:placetype":"venue"
},
  "geometry": {"coordinates":[0.0334279984,38.7940826416],"type":"Point"}
}