{
  "type": "Feature",
  "properties": {
    "iso:country":"ES",
    "sg:address":"Pol Ind Munic Vial A, 12",
    "sg:city":"Tudela",
    "sg:orig_category":"Electricidad (montaje, Ensamblaje De Componentes)",
    "sg:phone":"+34 948 41 14 96",
    "sg:postcode":"31500",
    "sg:province":"Navarra",
    "wof:name":"Emauto Electricidad S.l.",
    "wof:placetype":"venue"
},
  "geometry": {"coordinates":[-1.60295403,42.0619239807],"type":"Point"}
}