{
  "type": "Feature",
  "properties": {
    "iso:country":"ES",
    "sg:address":"Carr Raiers, S/n",
    "sg:city":"Pobla Segur",
    "sg:orig_category":"Notarios",
    "sg:phone":"+34 973 68 00 26",
    "sg:postcode":"25500",
    "sg:province":"Lleida",
    "wof:name":"Acarre\u00d1o Martin Irene",
    "wof:placetype":"venue"
},
  "geometry": {"coordinates":[0.9680423737,42.2508201599],"type":"Point"}
}