{
  "type": "Feature",
  "properties": {
    "iso:country":"ES",
    "sg:address":"Avda Valencia, 223",
    "sg:city":"Castellon",
    "sg:orig_category":"Agentes, Concesionarios Y Sucursales De Veh\u00cdculos",
    "sg:phone":"+34 964 24 40 67",
    "sg:postcode":"12005",
    "sg:province":"Castell\u00f3n",
    "wof:name":"Nissan Motor Espa\u00d1a S.a.",
    "wof:placetype":"venue"
},
  "geometry": {"coordinates":[-0.0512389988,39.9737892151],"type":"Point"}
}