{
  "type": "Feature",
  "properties": {
    "iso:country":"ES",
    "sg:address":"La Calzada, S/n",
    "sg:city":"San Miguel",
    "sg:orig_category":"Ense\u00d1anza, Formaci\u00d3n Profesional: Aprendizaje",
    "sg:phone":"+34 922 16 79 15",
    "sg:postcode":"38620",
    "sg:province":"Santa Cruz De Tenerife",
    "wof:name":"Ayuntamiento Centro Rural De Higiene",
    "wof:placetype":"venue"
},
  "geometry": {"coordinates":[-16.634557724,28.0934295654],"type":"Point"}
}