{
  "type": "Feature",
  "properties": {
    "iso:country":"ES",
    "sg:address":"Calle de Republica Argentina, 26",
    "sg:city":"Arnedo",
    "sg:orig_category":"Institutos De Belleza",
    "sg:phone":"+34 941 38 21 91",
    "sg:postcode":"26580",
    "sg:province":"La Rioja",
    "wof:name":"Perez Adrados Garrido Inmaculada",
    "wof:placetype":"venue"
},
  "geometry": {"coordinates":[-2.0989120007,42.2260284424],"type":"Point"}
}