{
  "type": "Feature",
  "properties": {
    "iso:country":"ES",
    "sg:address":"Horta, 19",
    "sg:city":"Selva Del Camp",
    "sg:orig_category":"Mec\u00c1nico Del Autom\u00d3vil",
    "sg:phone":"+34 977 84 43 12",
    "sg:postcode":"43470",
    "sg:province":"Tarragona",
    "wof:name":"Massana Serveis I Reparacions S.l.",
    "wof:placetype":"venue"
},
  "geometry": {"coordinates":[1.1411130428,41.2136955261],"type":"Point"}
}