{
  "type": "Feature",
  "properties": {
    "iso:country":"ES",
    "sg:address":"Calle de Viteri, 4",
    "sg:city":"Errenteria",
    "sg:orig_category":"Camiser\u00cda Y Ropa Interior Masculina (al Por Menor)",
    "sg:phone":"+34 943 51 69 96",
    "sg:postcode":"20100",
    "sg:province":"Guip\u00f9zcoa",
    "wof:name":"Iglesias Rodriguez Maria Catalina",
    "wof:placetype":"venue"
},
  "geometry": {"coordinates":[-1.8991669416,43.3132667542],"type":"Point"}
}