{
  "type": "Feature",
  "properties": {
    "addr:full":"Calle de Constitucion (de La), 12 Sevilla Nueva Madrid 28609",
    "addr:housenumber":"12",
    "addr:postcode":"28609",
    "addr:street":"Calle De Constitucion De La;Nueva",
    "iso:country":"ES",
    "sg:address":"Calle de Constitucion (de La), 12",
    "sg:city":"Sevilla Nueva",
    "sg:orig_category":"Supermercados Y Hipermercados",
    "sg:phone":"+34 918 12 97 31",
    "sg:postcode":"28609",
    "sg:province":"Madrid",
    "wof:name":"Aresan 5 S.l.",
    "wof:placetype":"venue"
},
  "geometry": {"coordinates":[-4.1012024879,40.3468475342],"type":"Point"}
}