{
  "type": "Feature",
  "properties": {
    "iso:country":"ES",
    "sg:address":"Pase Ribalta, 21",
    "sg:city":"Castellon",
    "sg:orig_category":"Procuradores",
    "sg:phone":"+34 964 21 83 19",
    "sg:postcode":"12001",
    "sg:province":"Castell\u00f3n",
    "wof:name":"Motilva Casado Concepcion",
    "wof:placetype":"venue"
},
  "geometry": {"coordinates":[-0.0390199982,39.9866409302],"type":"Point"}
}