{
  "type": "Feature",
  "properties": {
    "addr:full":"Calle de Miguel Fleta, 1 Huesca Huesca 22006",
    "addr:housenumber":"1",
    "addr:postcode":"22006",
    "addr:street":"Calle De Miguel Fleta",
    "iso:country":"ES",
    "sg:address":"Calle de Miguel Fleta, 1",
    "sg:city":"Huesca",
    "sg:orig_category":"Electrodom\u00c9sticos (fabricaci\u00d3n, Al Por Mayor)",
    "sg:phone":"+34 974 22 15 62",
    "sg:postcode":"22006",
    "sg:province":"Huesca",
    "wof:name":"G.o.c.i.s.a.",
    "wof:placetype":"venue"
},
  "geometry": {"coordinates":[-0.4035739899,42.143157959],"type":"Point"}
}