{
  "type": "Feature",
  "properties": {
    "addr:full":"Calle de Butarque, 12 Leganes Madrid 28911",
    "addr:housenumber":"12",
    "addr:postcode":"28911",
    "addr:street":"Calle De Butarque",
    "iso:country":"ES",
    "sg:address":"Calle de Butarque, 12",
    "sg:city":"Leganes",
    "sg:orig_category":"Complementos De Vestir (al Por Menor)",
    "sg:phone":"+34 916 88 87 58",
    "sg:postcode":"28911",
    "sg:province":"Madrid",
    "sg:website":"www.samariacomplementos.com",
    "wof:name":"Mujer Samaria S.l.l.",
    "wof:placetype":"venue"
},
  "geometry": {"coordinates":[-3.7658574581,40.3307991028],"type":"Point"}
}