{
  "type": "Feature",
  "properties": {
    "addr:full":"Calle de Cruces (las), 32 Navarrete La Rioja 26370",
    "addr:housenumber":"32",
    "addr:postcode":"26370",
    "addr:street":"Calle De Cruces Las",
    "iso:country":"ES",
    "sg:address":"Calle de Cruces (las), 32",
    "sg:city":"Navarrete",
    "sg:orig_category":"Productos Qu\u00cdmicos (fabricaci\u00d3n, Al Por Mayor)",
    "sg:phone":"+34 941 44 06 51",
    "sg:postcode":"26370",
    "sg:province":"La Rioja",
    "wof:name":"Productos Inchea S.l",
    "wof:placetype":"venue"
},
  "geometry": {"coordinates":[-2.561327219,42.4261016846],"type":"Point"}
}