{
  "type": "Feature",
  "properties": {
    "iso:country":"ES",
    "sg:address":"Calle de Santa Barbara, 9",
    "sg:city":"Monzon",
    "sg:orig_category":"Caf\u00c9s, Bares, Cervecer\u00cdas",
    "sg:phone":"+34 974 41 51 77",
    "sg:postcode":"22400",
    "sg:province":"Huesca",
    "wof:name":"Centro S.cv.",
    "wof:placetype":"venue"
},
  "geometry": {"coordinates":[0.1923619956,41.9112243652],"type":"Point"}
}