{
  "type": "Feature",
  "properties": {
    "addr:full":"Huelva Portugal, Km. 0001,3 Ayamonte Huelva 21400",
    "addr:postcode":"21400",
    "addr:street":"Km. 0001,3",
    "iso:country":"ES",
    "sg:address":"Huelva Portugal, Km. 0001,3",
    "sg:city":"Ayamonte",
    "sg:orig_category":"Estudios Y Construcci\u00d3n De Acuarios Y Viveros",
    "sg:phone":"+34 959 50 21 14",
    "sg:postcode":"21400",
    "sg:province":"Huelva",
    "wof:name":"Acuinova S.l.",
    "wof:placetype":"venue"
},
  "geometry": {"coordinates":[-7.4082026482,37.2138938904],"type":"Point"}
}