{
  "type": "Feature",
  "properties": {
    "iso:country":"ES",
    "sg:address":"Calle de Capitan (del), 16",
    "sg:city":"Colmenar Viejo",
    "sg:orig_category":"M\u00c1quinas Y Herramientas Para Trabajar La Piedra",
    "sg:phone":"+34 918 45 17 11",
    "sg:postcode":"28770",
    "sg:province":"Madrid",
    "wof:name":"Barrio Bernabe Pedro Del",
    "wof:placetype":"venue"
},
  "geometry": {"coordinates":[-3.7673399448,40.6567649841],"type":"Point"}
}