{
  "type": "Feature",
  "properties": {
    "addr:full":"C/ Blas Valero, 31 Elche Alicante 03201",
    "addr:housenumber":"31",
    "addr:postcode":"03201",
    "addr:street":"C / Blas Valero",
    "iso:country":"ES",
    "sg:address":"C/ Blas Valero, 31",
    "sg:city":"Elche",
    "sg:orig_category":"Alumbrados",
    "sg:phone":"+34 965 43 01 50",
    "sg:postcode":"03201",
    "sg:province":"Alicante",
    "wof:name":"Serrano Vidal Vicente",
    "wof:placetype":"venue"
},
  "geometry": {"coordinates":[-0.7017009854,38.2672538757],"type":"Point"}
}