{
  "type": "Feature",
  "properties": {
    "iso:country":"ES",
    "sg:address":"Bos, S/n",
    "sg:city":"Bos",
    "sg:orig_category":"Porcelanas, Azulejos (fabricaci\u00d3n, Al Por Mayor)",
    "sg:phone":"+34 981 79 52 12",
    "sg:postcode":"15640",
    "sg:province":"La Coru\u00f1a",
    "wof:name":"Ceramicas Gaya S.a.",
    "wof:placetype":"venue"
},
  "geometry": {"coordinates":[-8.2682237625,43.2997894287],"type":"Point"}
}