{
  "type": "Feature",
  "properties": {
    "addr:full":"Barr Teyeres Les, 36 Langreo Asturias 33900",
    "addr:postcode":"33900",
    "iso:country":"ES",
    "sg:address":"Barr Teyeres Les, 36",
    "sg:city":"Langreo",
    "sg:orig_category":"Suministros Y Colocaci\u00d3n De Canalones Para Aguas Pluviales",
    "sg:phone":"+34 985 67 40 57",
    "sg:postcode":"33900",
    "sg:province":"Asturias",
    "wof:name":"Canalones R.a.c. S.l.",
    "wof:placetype":"venue"
},
  "geometry": {"coordinates":[-5.6692090034,43.2883987427],"type":"Point"}
}