{
  "type": "Feature",
  "properties": {
    "addr:full":"Carr Constitucio, De Sa, 1 Andratx Islas Baleares 07150",
    "addr:housenumber":"1",
    "addr:postcode":"07150",
    "addr:street":"Carr Constitucio De Sa",
    "iso:country":"ES",
    "sg:address":"Carr Constitucio, De Sa, 1",
    "sg:city":"Andratx",
    "sg:orig_category":"Asociaciones Y Clubs Deportivos",
    "sg:phone":"+34 971 13 61 70",
    "sg:postcode":"07150",
    "sg:province":"Islas Baleares",
    "wof:name":"Sports I Ssimo S.l.",
    "wof:placetype":"venue"
},
  "geometry": {"coordinates":[2.4228799343,39.5626411438],"type":"Point"}
}