{
  "type": "Feature",
  "properties": {
    "addr:full":"Calle de Doce De Octubre, 40 Madrid Madrid 28009",
    "addr:housenumber":"40",
    "addr:postcode":"madrid;28009",
    "addr:street":"Calle De Doce De Octubre",
    "iso:country":"ES",
    "sg:address":"Calle de Doce De Octubre, 40",
    "sg:city":"Madrid",
    "sg:orig_category":"Centros M\u00c9dicos Y Sociales, Dispensarios",
    "sg:phone":"+34 915 04 69 37",
    "sg:postcode":"28009",
    "sg:province":"Madrid",
    "wof:name":"Blanco Redondo Miguel Angel",
    "wof:placetype":"venue"
},
  "geometry": {"coordinates":[-3.6721899509,40.4161491394],"type":"Point"}
}