{
  "type": "Feature",
  "properties": {
    "iso:country":"ES",
    "sg:address":"Calle de Larga, 1",
    "sg:city":"Olivares",
    "sg:orig_category":"Bisuter\u00cda, Joyer\u00cda, Relojer\u00cda (al Por Menor)",
    "sg:phone":"+34 954 11 06 96",
    "sg:postcode":"41804",
    "sg:province":"Sevilla",
    "wof:name":"Sanchez Fraile Juana",
    "wof:placetype":"venue"
},
  "geometry": {"coordinates":[-6.1580481529,37.4181365967],"type":"Point"}
}