{
  "type": "Feature",
  "properties": {
    "iso:country":"ES",
    "sg:address":"Ctra Aeropuerto, S/n",
    "sg:city":"Matorral",
    "sg:orig_category":"Informaci\u00d3n Financiera Y Comercial",
    "sg:phone":"+34 928 53 26 11",
    "sg:postcode":"35610",
    "sg:province":"Las Palmas",
    "sg:website":"www.islasairways.com",
    "wof:name":"Islas Airways S.a.",
    "wof:placetype":"venue"
},
  "geometry": {"coordinates":[-13.8684062958,28.479801178],"type":"Point"}
}