{
  "type": "Feature",
  "properties": {
    "iso:country":"ES",
    "sg:address":"Calle de Juana De Vega, 10",
    "sg:city":"Coru\u00d1a",
    "sg:orig_category":"Arquitectos",
    "sg:phone":"+34 981 22 87 94",
    "sg:postcode":"15003",
    "sg:province":"La Coru\u00f1a",
    "wof:name":"Obradoiro De Arquitectura E Urbanismo S.l",
    "wof:placetype":"venue"
},
  "geometry": {"coordinates":[-8.405456543,43.3670921326],"type":"Point"}
}