{
  "type": "Feature",
  "properties": {
    "iso:country":"ES",
    "sg:address":"Avda Nuestra Se\u00d1ora De Las Guias, 3",
    "sg:city":"Malaga",
    "sg:orig_category":"Piscinas, Accesorios, Suministros (fabricaci\u00d3n, Al Por Mayor)",
    "sg:phone":"+34 952 25 07 72",
    "sg:postcode":"29014",
    "sg:province":"M\u00e1laga",
    "wof:name":"Piscinas Cordobesas S.l.",
    "wof:placetype":"venue"
},
  "geometry": {"coordinates":[-4.4215011597,36.73853302],"type":"Point"}
}