{
  "type": "Feature",
  "properties": {
    "iso:country":"ES",
    "sg:address":"Avda Madariaga, 35",
    "sg:city":"Bilbao",
    "sg:orig_category":"Fotograf\u00cda Y Cine: Aparatos, Pel\u00cdculas Y Accesorios (fabricaci\u00d3n, Al Por Mayor)",
    "sg:phone":"+34 944 75 08 74",
    "sg:postcode":"48014",
    "sg:province":"Vizcaya",
    "sg:website":"www.fujifilm.es",
    "wof:name":"Santamaria Balbas Alejandro",
    "wof:placetype":"venue"
},
  "geometry": {"coordinates":[-2.9491848946,43.270866394],"type":"Point"}
}