{
  "type": "Feature",
  "properties": {
    "iso:country":"ES",
    "sg:address":"Sant Sebastia, 46",
    "sg:city":"Manacor",
    "sg:orig_category":"Muebles, Minoristas",
    "sg:phone":"+34 971 55 37 66",
    "sg:postcode":"07500",
    "sg:province":"Islas Baleares",
    "wof:name":"Nicolau Rossello Antonio",
    "wof:placetype":"venue"
},
  "geometry": {"coordinates":[3.2053070068,39.5749053955],"type":"Point"}
}