{
  "type": "Feature",
  "properties": {
    "iso:country":"ES",
    "sg:address":"Calle de Carcagente, 31",
    "sg:city":"Castellon",
    "sg:orig_category":"Partidos Pol\u00cdticos",
    "sg:phone":"+34 964 23 55 51",
    "sg:postcode":"12005",
    "sg:province":"Castell\u00f3n",
    "wof:name":"Partido Socialista Obrero Espa\u00f1ol",
    "wof:placetype":"venue"
},
  "geometry": {"coordinates":[-0.0315430015,39.980342865],"type":"Point"}
}