{
  "type": "Feature",
  "properties": {
    "iso:country":"ES",
    "sg:address":"Avda Joan Miro, S/n",
    "sg:city":"Torremolinos",
    "sg:orig_category":"Cristaler\u00cdas",
    "sg:phone":"+34 952 37 01 88",
    "sg:postcode":"29620",
    "sg:province":"M\u00e1laga",
    "sg:website":"www.portalmalaga.com/cristalmarcos",
    "wof:name":"Naranjo Lara Marcos",
    "wof:placetype":"venue"
},
  "geometry": {"coordinates":[-4.5011057854,36.6217803955],"type":"Point"}
}