{
  "type": "Feature",
  "properties": {
    "iso:country":"ES",
    "sg:address":"Sant Llorenc, 31",
    "sg:city":"Vilassar",
    "sg:orig_category":"Carnicer\u00cdas, Carnicer\u00cdas",
    "sg:phone":"+34 937 59 22 58",
    "sg:postcode":"08340",
    "sg:province":"Barcelona",
    "wof:name":"Carns Verdaguer S. C. P.",
    "wof:placetype":"venue"
},
  "geometry": {"coordinates":[2.3873779774,41.5009231567],"type":"Point"}
}