{
  "type": "Feature",
  "properties": {
    "iso:country":"ES",
    "sg:address":"Calle de Obispo Tagaste, 23",
    "sg:city":"Albacete",
    "sg:orig_category":"Internados & Ense\u00d1anza Privada",
    "sg:phone":"+34 967 24 05 03",
    "sg:postcode":"02005",
    "sg:province":"Albacete",
    "wof:name":"Sociedad Cooperativa Limitada Academia Aristos Albacete",
    "wof:placetype":"venue"
},
  "geometry": {"coordinates":[-1.8623470068,39.0031394958],"type":"Point"}
}