{
  "type": "Feature",
  "properties": {
    "addr:full":"Carr Progres, 1 Badalona Barcelona 08912",
    "addr:housenumber":"1",
    "addr:postcode":"08912",
    "addr:street":"Carr Progres",
    "iso:country":"ES",
    "sg:address":"Carr Progres, 1",
    "sg:city":"Badalona",
    "sg:orig_category":"Bordado, Marcado A Medida",
    "sg:phone":"+34 933 99 54 19",
    "sg:postcode":"08912",
    "sg:province":"Barcelona",
    "wof:name":"Brugue Roca Juan",
    "wof:placetype":"venue"
},
  "geometry": {"coordinates":[2.2450020313,41.4453430176],"type":"Point"}
}