{
  "type": "Feature",
  "properties": {
    "iso:country":"ES",
    "sg:address":"Pla\u00c7 Independencia, 11",
    "sg:city":"Girona",
    "sg:orig_category":"Comercio De Muebles De Estilo Y Contempor\u00c1neos",
    "sg:phone":"+34 972 20 82 19",
    "sg:postcode":"17001",
    "sg:province":"Girona",
    "wof:name":"Macias Colom Ana",
    "wof:placetype":"venue"
},
  "geometry": {"coordinates":[2.8215665817,41.9854621887],"type":"Point"}
}