{
  "type": "Feature",
  "properties": {
    "addr:full":"Calle de Landako Kalea, 4 Amurrio \u00c1lava 01470",
    "addr:housenumber":"4",
    "addr:postcode":"01470",
    "addr:street":"Calle De Landako Kalea",
    "iso:country":"ES",
    "sg:address":"Calle de Landako Kalea, 4",
    "sg:city":"Amurrio",
    "sg:orig_category":"Ense\u00d1anza: Idiomas",
    "sg:phone":"+34 945 02 63 67",
    "sg:postcode":"01470",
    "sg:province":"\u00c1lava",
    "wof:name":"Nuria Ojembarrena Arbaizagoitia",
    "wof:placetype":"venue"
},
  "geometry": {"coordinates":[-3.0015599728,43.0515975952],"type":"Point"}
}