{
  "type": "Feature",
  "properties": {
    "addr:full":"Errondo Gaineko Kalea, 66 Donostia-san Sebastian Guip\u00f9zcoa 20009",
    "addr:housenumber":"66",
    "addr:postcode":"20009",
    "addr:street":"Errondo Gaineko Kalea",
    "iso:country":"ES",
    "sg:address":"Errondo Gaineko Kalea, 66",
    "sg:city":"Donostia-san Sebastian",
    "sg:orig_category":"Caf\u00c9s, Bares, Cervecer\u00cdas",
    "sg:phone":"+34 943 21 82 66",
    "sg:postcode":"20009",
    "sg:province":"Guip\u00f9zcoa",
    "wof:name":"Etxeberria Artola Puy",
    "wof:placetype":"venue"
},
  "geometry": {"coordinates":[-1.9875659943,43.300945282],"type":"Point"}
}