{
  "type": "Feature",
  "properties": {
    "addr:full":"Carrer de Ciutadans, 6 Tordera Barcelona 08490",
    "addr:housenumber":"6",
    "addr:postcode":"08490",
    "addr:street":"Carrer De Ciutadans",
    "iso:country":"ES",
    "sg:address":"Carrer de Ciutadans, 6",
    "sg:city":"Tordera",
    "sg:orig_category":"Iglesia Cat\u00d3lica",
    "sg:phone":"+34 937 64 00 73",
    "sg:postcode":"08490",
    "sg:province":"Barcelona",
    "wof:name":"Bisbat De Girona",
    "wof:placetype":"venue"
},
  "geometry": {"coordinates":[2.7192149162,41.7013702393],"type":"Point"}
}