{
  "type": "Feature",
  "properties": {
    "iso:country":"ES",
    "sg:address":"Cerdeiri\u00f1as (pilo\u00f1o), 27",
    "sg:city":"Cerdeiri\u00d1as",
    "sg:orig_category":"Empresarios",
    "sg:phone":"+34 986 58 60 06",
    "sg:postcode":"36586",
    "sg:province":"Pontevedra",
    "wof:name":"Fundacion Casa Museo A Solaina De Pilo\u00f1o",
    "wof:placetype":"venue"
},
  "geometry": {"coordinates":[-8.2702636719,42.7956161499],"type":"Point"}
}