{
  "type": "Feature",
  "properties": {
    "iso:country":"ES",
    "sg:address":"Pla\u00c7 Constitucio, De Sa, 35",
    "sg:city":"Soller",
    "sg:orig_category":"Bancos",
    "sg:phone":"+34 971 63 83 68",
    "sg:postcode":"07100",
    "sg:province":"Islas Baleares",
    "wof:name":"Auna Telecomunicaciones S.a.u.",
    "wof:placetype":"venue"
},
  "geometry": {"coordinates":[2.7083287239,39.7749633789],"type":"Point"}
}