{
  "type": "Feature",
  "properties": {
    "addr:full":"Ctra Del Rocio, 120 Almonte Huelva 21730",
    "addr:housenumber":"120",
    "addr:postcode":"21730",
    "addr:street":"Ctra Del Rocio",
    "iso:country":"ES",
    "sg:address":"Ctra Del Rocio, 120",
    "sg:city":"Almonte",
    "sg:orig_category":"T\u00c9cnicos Veterinarios",
    "sg:phone":"+34 959 40 63 40",
    "sg:postcode":"21730",
    "sg:province":"Huelva",
    "wof:name":"Diaz De La Serna Charlo Angel",
    "wof:placetype":"venue"
},
  "geometry": {"coordinates":[-6.5217170715,37.2592811584],"type":"Point"}
}