{
  "type": "Feature",
  "properties": {
    "addr:full":"Rua Alberto Vilanova (de), 27 Carballi\u00f1o Ourense 32500",
    "addr:postcode":"32500",
    "addr:street":"Rua Alberto",
    "iso:country":"ES",
    "sg:address":"Rua Alberto Vilanova (de), 27",
    "sg:city":"Carballi\u00f1o",
    "sg:orig_category":"Caf\u00c9s, Bares, Cervecer\u00cdas",
    "sg:phone":"+34 988 27 15 35",
    "sg:postcode":"32500",
    "sg:province":"Ourense",
    "wof:name":"Iglesias Gonzalez Juan",
    "wof:placetype":"venue"
},
  "geometry": {"coordinates":[-8.0723085403,42.4294700623],"type":"Point"}
}