{
  "type": "Feature",
  "properties": {
    "iso:country":"ES",
    "sg:address":"Calle de Maestro Rodrigo, 2",
    "sg:city":"Rota",
    "sg:orig_category":"Ense\u00d1anza Variada",
    "sg:phone":"+34 956 81 63 37",
    "sg:postcode":"11520",
    "sg:province":"C\u00e1diz",
    "wof:name":"Rodriguez Herrera Manuel",
    "wof:placetype":"venue"
},
  "geometry": {"coordinates":[-6.3656411171,36.6256599426],"type":"Point"}
}