{
  "type": "Feature",
  "properties": {
    "addr:full":"Calle de Maria Teresa Saenz De Heredia, 29 Madrid Madrid 28017",
    "addr:housenumber":"29",
    "addr:postcode":"madrid;28017",
    "addr:street":"Calle De Maria Teresa Saenz De Heredia",
    "iso:country":"ES",
    "sg:address":"Calle de Maria Teresa Saenz De Heredia, 29",
    "sg:city":"Madrid",
    "sg:orig_category":"Tintes (fabricaci\u00d3n, Al Por Mayor)",
    "sg:phone":"+34 913 56 78 64",
    "sg:postcode":"28017",
    "sg:province":"Madrid",
    "wof:name":"Blanco Alvarez Aurelio",
    "wof:placetype":"venue"
},
  "geometry": {"coordinates":[-3.6537508965,40.4234428406],"type":"Point"}
}