{
  "type": "Feature",
  "properties": {
    "addr:full":"Calle de Alvaro De Bazan, 9 Getafe Madrid 28902",
    "addr:housenumber":"9",
    "addr:postcode":"28902",
    "addr:street":"Calle De Alvaro De Bazan",
    "iso:country":"ES",
    "sg:address":"Calle de Alvaro De Bazan, 9",
    "sg:city":"Getafe",
    "sg:orig_category":"Bancos",
    "sg:phone":"+34 916 65 20 93",
    "sg:postcode":"28902",
    "sg:province":"Madrid",
    "wof:name":"Dresdner Bank Ag",
    "wof:placetype":"venue"
},
  "geometry": {"coordinates":[-3.7297787666,40.3098640442],"type":"Point"}
}