{
  "type": "Feature",
  "properties": {
    "iso:country":"ES",
    "sg:address":"Plaz Ayuntamiento (el), 2",
    "sg:city":"Ponferrada",
    "sg:orig_category":"Molduras, Junquillos, Listones Y Molduras Perforadas",
    "sg:phone":"+34 987 41 30 16",
    "sg:postcode":"24400",
    "sg:province":"Le\u00f3n",
    "wof:name":"Garcia Carro Carlos",
    "wof:placetype":"venue"
},
  "geometry": {"coordinates":[-6.5900821686,42.5452957153],"type":"Point"}
}