{
  "type": "Feature",
  "properties": {
    "addr:full":"Rua Salmon, 8 Lugo Lugo 27003",
    "addr:housenumber":"8",
    "addr:postcode":"27003",
    "addr:street":"Rua Salmon",
    "iso:country":"ES",
    "sg:address":"Rua Salmon, 8",
    "sg:city":"Lugo",
    "sg:orig_category":"Ingeniero",
    "sg:phone":"+34 982 28 40 70",
    "sg:postcode":"27003",
    "sg:province":"Lugo",
    "wof:name":"Tecnologias Y Servicios Agrarios S.a.",
    "wof:placetype":"venue"
},
  "geometry": {"coordinates":[-7.5577311516,43.0175743103],"type":"Point"}
}