{
  "type": "Feature",
  "properties": {
    "addr:full":"Calle de Cruz Del Ovejero, 69 Tamaraceite Las Palmas 35018",
    "addr:housenumber":"69",
    "addr:postcode":"35018",
    "addr:street":"Calle De Cruz Del Ovejero;Palmas",
    "iso:country":"ES",
    "sg:address":"Calle de Cruz Del Ovejero, 69",
    "sg:city":"Tamaraceite",
    "sg:orig_category":"Promotores Constructores",
    "sg:phone":"+34 928 67 41 23",
    "sg:postcode":"35018",
    "sg:province":"Las Palmas",
    "wof:name":"U.t.e. Consguerra S.l. Y Exari\u00f1o S.l.",
    "wof:placetype":"venue"
},
  "geometry": {"coordinates":[-15.4795341492,28.0981578827],"type":"Point"}
}