{
  "type": "Feature",
  "properties": {
    "iso:country":"ES",
    "sg:address":"Partido Villamorma, S/n",
    "sg:city":"Casarabonela",
    "sg:orig_category":"Ebanister\u00cda",
    "sg:phone":"+34 952 45 65 32",
    "sg:postcode":"29566",
    "sg:province":"M\u00e1laga",
    "wof:name":"Carpinteria Esther Y Jorge S.l.",
    "wof:placetype":"venue"
},
  "geometry": {"coordinates":[-4.8406629562,36.7875747681],"type":"Point"}
}