{
  "type": "Feature",
  "properties": {
    "iso:country":"ES",
    "sg:address":"Calle de Solana Kalea, 7",
    "sg:city":"Tolosa",
    "sg:orig_category":"Librer\u00cdas",
    "sg:phone":"+34 943 67 23 12",
    "sg:postcode":"20400",
    "sg:province":"Guip\u00f9zcoa",
    "wof:name":"Belza Aramburu Juan Carlos",
    "wof:placetype":"venue"
},
  "geometry": {"coordinates":[-2.0722548962,43.1373634338],"type":"Point"}
}