{
  "type": "Feature",
  "properties": {
    "addr:full":"Ctra Madrid N-iv (extrarradio), 82 Alcolea C\u00f3rdoba 14610",
    "addr:housenumber":"82",
    "addr:postcode":"14610",
    "addr:street":"Ctra Madrid N-Iv Extrarradio",
    "iso:country":"ES",
    "sg:address":"Ctra Madrid N-iv (extrarradio), 82",
    "sg:city":"Alcolea",
    "sg:classifiers":[
        {
            "category":"Autos & Motor Vehicles",
            "subcategory":"Automobile Sales",
            "type":"Retail Goods"
        }
    ],
    "sg:phone":"+34 957 32 12 32",
    "sg:postcode":"14610",
    "sg:province":"C\u00f3rdoba",
    "wof:name":"Autoescuela Alcolea S.l.",
    "wof:placetype":"venue"
},
  "geometry": {"coordinates":[-4.6729812622,37.932182312],"type":"Point"}
}