{
  "type": "Feature",
  "properties": {
    "iso:country":"ES",
    "sg:address":"Calle de Remonta, 5",
    "sg:city":"Melilla",
    "sg:orig_category":"Bancos",
    "sg:phone":"+34 952 69 16 07",
    "sg:postcode":"52005",
    "sg:province":"Melilla",
    "wof:name":"Banco Bilbao Vizcaya Argentaria Sa",
    "wof:placetype":"venue"
},
  "geometry": {"coordinates":[-2.9480030537,35.2859840393],"type":"Point"}
}