{
  "type": "Feature",
  "properties": {
    "iso:country":"ES",
    "sg:address":"Calle de Porvenir, 34",
    "sg:city":"Jerez De La Frontera",
    "sg:orig_category":"Abogados",
    "sg:phone":"+34 956 34 44 09",
    "sg:postcode":"11401",
    "sg:province":"C\u00e1diz",
    "wof:name":"Datas Mingoranz Jose Francisco",
    "wof:placetype":"venue"
},
  "geometry": {"coordinates":[-6.1308288574,36.6793365479],"type":"Point"}
}