{
  "type": "Feature",
  "properties": {
    "iso:country":"ES",
    "sg:address":"Urb. El Palmeral, 2",
    "sg:city":"Vera",
    "sg:orig_category":"Psic\u00d3logos",
    "sg:phone":"+34 950 39 16 70",
    "sg:postcode":"04620",
    "sg:province":"Almer\u00eda",
    "wof:name":"Lozano Serrano Maria De Los Angeles",
    "wof:placetype":"venue"
},
  "geometry": {"coordinates":[-1.84869802,37.2382888794],"type":"Point"}
}