{
  "type": "Feature",
  "properties": {
    "iso:country":"ES",
    "sg:address":"Plaz Constitucion (de La), 1",
    "sg:city":"Humanes De Madrid",
    "sg:orig_category":"Centros De Educaci\u00d3n Especial",
    "sg:phone":"+34 916 04 01 19",
    "sg:postcode":"28970",
    "sg:province":"Madrid",
    "wof:name":"Ayuntamiento De Humanes",
    "wof:placetype":"venue"
},
  "geometry": {"coordinates":[-3.828979969,40.2507705688],"type":"Point"}
}