{
  "type": "Feature",
  "properties": {
    "iso:country":"ES",
    "sg:address":"Av Pais Valencia, 40",
    "sg:city":"Benissa",
    "sg:orig_category":"Venta, Instalaci\u00d3n, Reparaci\u00d3n De Antenas Para Televisi\u00d3n",
    "sg:phone":"+34 965 73 28 80",
    "sg:postcode":"03720",
    "sg:province":"Alicante",
    "wof:name":"Base Technical Installations S.l.",
    "wof:placetype":"venue"
},
  "geometry": {"coordinates":[0.052556999,38.7147865295],"type":"Point"}
}