{
  "type": "Feature",
  "properties": {
    "iso:country":"ES",
    "sg:address":"Carrer de Mas De L'abello, 24",
    "sg:city":"Reus",
    "sg:orig_category":"Farmacias",
    "sg:phone":"+34 977 77 10 89",
    "sg:postcode":"43204",
    "sg:province":"Tarragona",
    "wof:name":"Brufau De Barbera Anton",
    "wof:placetype":"venue"
},
  "geometry": {"coordinates":[1.1208620071,41.1475334167],"type":"Point"}
}