{
  "type": "Feature",
  "properties": {
    "iso:country":"ES",
    "sg:address":"Calle de Marques De Santillana, 39",
    "sg:city":"Villarrubia De Los Ojos",
    "sg:orig_category":"Peluqueros: De Se\u00d1oras",
    "sg:phone":"+34 926 89 84 80",
    "sg:postcode":"13670",
    "sg:province":"Ciudad Real",
    "wof:name":"Moreno De La Santa Gomez-tembleque Maria Del Rosar",
    "wof:placetype":"venue"
},
  "geometry": {"coordinates":[-3.6043200493,39.2268409729],"type":"Point"}
}