{
  "type": "Feature",
  "properties": {
    "iso:country":"ES",
    "sg:address":"Calle de Mariana Pineda, 24",
    "sg:city":"Guillena",
    "sg:orig_category":"Delegados, Agentes De Tr\u00c1nsito, Auxiliares De Transporte Internacional",
    "sg:phone":"+34 955 78 48 04",
    "sg:postcode":"41210",
    "sg:province":"Sevilla",
    "wof:name":"Transportes Garcia Mejias S.l.",
    "wof:placetype":"venue"
},
  "geometry": {"coordinates":[-6.0588288307,37.5471801758],"type":"Point"}
}