{
  "type": "Feature",
  "properties": {
    "addr:full":"Calle de Peregrina (la), 37 Pozuelo De Alarcon Madrid 28223",
    "addr:housenumber":"37",
    "addr:postcode":"28223",
    "addr:street":"Calle De Peregrina La",
    "iso:country":"ES",
    "sg:address":"Calle de Peregrina (la), 37",
    "sg:city":"Pozuelo De Alarcon",
    "sg:orig_category":"Administradores De Bienes Y Delegados De Comunidades De Propietarios",
    "sg:phone":"+34 913 51 08 75",
    "sg:postcode":"28223",
    "sg:province":"Madrid",
    "wof:name":"Fc Ferbach S.l.",
    "wof:placetype":"venue"
},
  "geometry": {"coordinates":[-3.8091249466,40.4410972595],"type":"Point"}
}