{
  "type": "Feature",
  "properties": {
    "iso:country":"ES",
    "sg:address":"Calle de Santa Catalina (de), 8",
    "sg:city":"Colmenar Viejo",
    "sg:orig_category":"Doctores En Medicina",
    "sg:phone":"+34 918 45 10 22",
    "sg:postcode":"28770",
    "sg:province":"Madrid",
    "wof:name":"Parcero Diez Luis Fernando",
    "wof:placetype":"venue"
},
  "geometry": {"coordinates":[-3.7787430286,40.6730079651],"type":"Point"}
}