{
  "type": "Feature",
  "properties": {
    "iso:country":"ES",
    "sg:address":"Calle de Santa Marta, S/n",
    "sg:city":"Aceuchal",
    "sg:orig_category":"Cooperativas Agr\u00cdcolas",
    "sg:phone":"+34 924 68 02 28",
    "sg:postcode":"06207",
    "sg:province":"Badajoz",
    "wof:name":"Cooperativa Del Campo Nuestra Se\u00f1ora Soledad",
    "wof:placetype":"venue"
},
  "geometry": {"coordinates":[-6.4861440659,38.6472167969],"type":"Point"}
}