{
  "type": "Feature",
  "properties": {
    "addr:full":"Calle de Planton, 14 Mejias Las Palmas 35250",
    "addr:housenumber":"14",
    "addr:postcode":"35250",
    "addr:street":"Calle De Planton;Mejias Las",
    "iso:country":"ES",
    "sg:address":"Calle de Planton, 14",
    "sg:city":"Mejias",
    "sg:orig_category":"Agricultores, Agricultores",
    "sg:phone":"+34 928 78 40 27",
    "sg:postcode":"35250",
    "sg:province":"Las Palmas",
    "wof:name":"Ramirez Romero Higinia",
    "wof:placetype":"venue"
},
  "geometry": {"coordinates":[-15.4355688095,27.922290802],"type":"Point"}
}