{
  "type": "Feature",
  "properties": {
    "iso:country":"ES",
    "sg:address":"Calle de Camino De Velez, 4",
    "sg:city":"Algarrobo",
    "sg:orig_category":"Aguas (distribuci\u00d3n, Servicios)",
    "sg:phone":"+34 952 55 27 27",
    "sg:postcode":"29750",
    "sg:province":"M\u00e1laga",
    "wof:name":"Aquagest Sur S.a.",
    "wof:placetype":"venue"
},
  "geometry": {"coordinates":[-4.0390462875,36.7722930908],"type":"Point"}
}