{
  "type": "Feature",
  "properties": {
    "iso:country":"ES",
    "sg:address":"Calle de Ramon Y Cajal, 11",
    "sg:city":"Santurtzi",
    "sg:orig_category":"Juegos Y Juguetes (al Por Menor)",
    "sg:phone":"+34 944 83 56 56",
    "sg:postcode":"48980",
    "sg:province":"Vizcaya",
    "wof:name":"Jose Luis Perez Conde",
    "wof:placetype":"venue"
},
  "geometry": {"coordinates":[-3.0359420776,43.3303413391],"type":"Point"}
}