{
  "type": "Feature",
  "properties": {
    "addr:full":"Calle de Huesca, S/n Castellon Castell\u00f3n 12004",
    "addr:housenumber":"s / n",
    "addr:postcode":"12004",
    "addr:street":"Calle De Huesca",
    "iso:country":"ES",
    "sg:address":"Calle de Huesca, S/n",
    "sg:city":"Castellon",
    "sg:orig_category":"Asociaciones Y Clubs Deportivos",
    "sg:phone":"+34 964 24 56 00",
    "sg:postcode":"12004",
    "sg:province":"Castell\u00f3n",
    "wof:name":"Club Deportivo Castellon S.a.d.",
    "wof:placetype":"venue"
},
  "geometry": {"coordinates":[-0.0394590013,39.995475769],"type":"Point"}
}