{
  "type": "Feature",
  "properties": {
    "iso:country":"ES",
    "sg:address":"Carrer de Petritxol, 1",
    "sg:city":"Barcelona",
    "sg:orig_category":"Bisuter\u00cda, Joyer\u00cda, Relojer\u00cda (al Por Menor)",
    "sg:phone":"+34 933 18 38 41",
    "sg:postcode":"08002",
    "sg:province":"Barcelona",
    "wof:name":"Sant Corominas Merce",
    "wof:placetype":"venue"
},
  "geometry": {"coordinates":[2.1731729507,41.3824386597],"type":"Point"}
}