{
  "type": "Feature",
  "properties": {
    "iso:country":"ES",
    "sg:address":"Urola Kalea, 8",
    "sg:city":"Legazpi",
    "sg:orig_category":"Agentes, Concesionarios Y Sucursales De Veh\u00cdculos",
    "sg:phone":"+34 943 73 41 49",
    "sg:postcode":"20230",
    "sg:province":"Guip\u00f9zcoa",
    "wof:name":"Bertan Sociedad Cooperativa",
    "wof:placetype":"venue"
},
  "geometry": {"coordinates":[-2.3316509724,43.0559539795],"type":"Point"}
}