{
  "type": "Feature",
  "properties": {
    "addr:full":"Pla\u00c7 Espanya, S/n Girona Girona 17002",
    "addr:housenumber":"s / n",
    "addr:postcode":"17002",
    "iso:country":"ES",
    "sg:address":"Pla\u00c7 Espanya, S/n",
    "sg:city":"Girona",
    "sg:orig_category":"Alquiler De Veh\u00cdculos: Turismos Y Utilitarios",
    "sg:phone":"+34 972 22 46 64",
    "sg:postcode":"17002",
    "sg:province":"Girona",
    "wof:name":"Avis Alquile Un Coche S.a.",
    "wof:placetype":"venue"
},
  "geometry": {"coordinates":[2.8190748692,41.9780960083],"type":"Point"}
}