{
  "type": "Feature",
  "properties": {
    "addr:full":"Carrer de Pare Coll, 4 Vic Barcelona 08500",
    "addr:housenumber":"4",
    "addr:postcode":"08500",
    "addr:street":"Carrer De Pare Coll",
    "iso:country":"ES",
    "sg:address":"Carrer de Pare Coll, 4",
    "sg:city":"Vic",
    "sg:orig_category":"Ense\u00d1anza: Idiomas",
    "sg:phone":"+34 938 89 23 06",
    "sg:postcode":"08500",
    "sg:province":"Barcelona",
    "wof:name":"Connect Vic S.l.",
    "wof:placetype":"venue"
},
  "geometry": {"coordinates":[2.2541639805,41.9325523376],"type":"Point"}
}