{
  "type": "Feature",
  "properties": {
    "iso:country":"ES",
    "sg:address":"Calle de Antonio Segado Del Olmo, 12",
    "sg:city":"San Pedro",
    "sg:orig_category":"M\u00c9dicos: An\u00c1lisis Cl\u00cdnicos",
    "sg:phone":"+34 968 21 65 25",
    "sg:postcode":"30005",
    "sg:province":"Murcia",
    "wof:name":"Ignoto Campos Francisco Manuel",
    "wof:placetype":"venue"
},
  "geometry": {"coordinates":[-0.7915859222,37.8350410461],"type":"Point"}
}