{
  "type": "Feature",
  "properties": {
    "addr:full":"Calle de Palencia, 9 Villarrubia De Los Ojos Ciudad Real 13670",
    "addr:housenumber":"9",
    "addr:postcode":"13670",
    "addr:street":"Calle De Palencia",
    "iso:country":"ES",
    "sg:address":"Calle de Palencia, 9",
    "sg:city":"Villarrubia De Los Ojos",
    "sg:orig_category":"Chapister\u00cda",
    "sg:phone":"+34 926 89 86 99",
    "sg:postcode":"13670",
    "sg:province":"Ciudad Real",
    "wof:name":"Garcia Sanchez Jose Agustin",
    "wof:placetype":"venue"
},
  "geometry": {"coordinates":[-3.6144599915,39.2170906067],"type":"Point"}
}