{
  "type": "Feature",
  "properties": {
    "addr:full":"Av Maria Fortuny, 7 Reus Tarragona 43204",
    "addr:housenumber":"7",
    "addr:postcode":"43204",
    "addr:street":"Av Maria Fortuny",
    "iso:country":"ES",
    "sg:address":"Av Maria Fortuny, 7",
    "sg:city":"Reus",
    "sg:orig_category":"Internados & Ense\u00d1anza Privada",
    "sg:phone":"+34 977 75 54 18",
    "sg:postcode":"43204",
    "sg:province":"Tarragona",
    "wof:name":"Agrupacio Reusenca Centres D'enseyament S.l.",
    "wof:placetype":"venue"
},
  "geometry": {"coordinates":[1.1161772013,41.1534042358],"type":"Point"}
}