{
  "type": "Feature",
  "properties": {
    "iso:country":"ES",
    "sg:address":"Carr Ciutat De Valencia, 12",
    "sg:city":"Vila Joiosa",
    "sg:orig_category":"Lencer\u00cda Femenina, Corseter\u00cda, Trajes De Ba\u00d1o (al Por Menor)",
    "sg:phone":"+34 965 89 45 35",
    "sg:postcode":"03570",
    "sg:province":"Alicante",
    "wof:name":"Perez Lloret Ana Maria",
    "wof:placetype":"venue"
},
  "geometry": {"coordinates":[-0.7466139793,38.3102035522],"type":"Point"}
}