{
  "type": "Feature",
  "properties": {
    "addr:full":"Calle de Hijar, 2 Matamorosa Cantabria 39200",
    "addr:housenumber":"2",
    "addr:postcode":"39200",
    "addr:street":"Calle De Hijar",
    "iso:country":"ES",
    "sg:address":"Calle de Hijar, 2",
    "sg:city":"Matamorosa",
    "sg:orig_category":"Reposter\u00cdas",
    "sg:phone":"+34 942 75 49 79",
    "sg:postcode":"39200",
    "sg:province":"Cantabria",
    "wof:name":"Panificadora De Campoo S.l.",
    "wof:placetype":"venue"
},
  "geometry": {"coordinates":[-4.145608902,42.988319397],"type":"Point"}
}