{
  "type": "Feature",
  "properties": {
    "iso:country":"ES",
    "sg:address":"Calle de Alonso Mu\u00d1oz, 3",
    "sg:city":"Villanueva Serena",
    "sg:orig_category":"Abogados",
    "sg:phone":"+34 924 84 77 61",
    "sg:postcode":"06700",
    "sg:province":"Badajoz",
    "wof:name":"Arroyo Alvarez Maria Belen",
    "wof:placetype":"venue"
},
  "geometry": {"coordinates":[-5.7983961105,38.9735069275],"type":"Point"}
}