{
  "type": "Feature",
  "properties": {
    "iso:country":"ES",
    "sg:address":"Calle de Sierra Salvada, 29",
    "sg:city":"Madrid",
    "sg:orig_category":"Empresas De Vigilancia, Guardia Y Protecci\u00d3n",
    "sg:phone":"+34 917 77 54 91",
    "sg:postcode":"28038",
    "sg:province":"Madrid",
    "wof:name":"Seguridad Integral Madrile\u00f1a S.a.",
    "wof:placetype":"venue"
},
  "geometry": {"coordinates":[-3.6494779587,40.3889961243],"type":"Point"}
}