{
  "type": "Feature",
  "properties": {
    "iso:country":"ES",
    "sg:address":"Carrer de Julian Romea, 4",
    "sg:city":"Barcelona",
    "sg:orig_category":"M\u00c9dicos: Estomatolog\u00cda",
    "sg:phone":"+34 932 17 57 33",
    "sg:postcode":"08006",
    "sg:province":"Barcelona",
    "wof:name":"Trix 2004 S.l.",
    "wof:placetype":"venue"
},
  "geometry": {"coordinates":[2.1529130936,41.3979911804],"type":"Point"}
}