{
  "type": "Feature",
  "properties": {
    "addr:full":"Pl Ajuntament, 5 Cabrera Mar Barcelona 08349",
    "addr:housenumber":"5",
    "addr:postcode":"08349",
    "addr:street":"Pl Ajuntament",
    "iso:country":"ES",
    "sg:address":"Pl Ajuntament, 5",
    "sg:city":"Cabrera Mar",
    "sg:orig_category":"Cobro De Pr\u00c9stamos",
    "sg:phone":"+34 937 59 87 17",
    "sg:postcode":"08349",
    "sg:province":"Barcelona",
    "wof:name":"Organisme Autonom Local De Gestio Tributaria",
    "wof:placetype":"venue"
},
  "geometry": {"coordinates":[2.3933050632,41.5273513794],"type":"Point"}
}