{
  "type": "Feature",
  "properties": {
    "iso:country":"ES",
    "sg:address":"Avda Quiroga, S/n",
    "sg:city":"Becerrea",
    "sg:orig_category":"Edici\u00d3n De Diarios, Revistas, Boletines",
    "sg:phone":"+34 982 36 00 94",
    "sg:postcode":"27640",
    "sg:province":"Lugo",
    "wof:name":"Garcia Barreiro Ricardo",
    "wof:placetype":"venue"
},
  "geometry": {"coordinates":[-7.1590981483,42.8493614197],"type":"Point"}
}