{
  "type": "Feature",
  "properties": {
    "addr:full":"Trva Casa Mario, 2 Grado Asturias 33820",
    "addr:housenumber":"2",
    "addr:postcode":"33820",
    "addr:street":"Trva Casa Mario",
    "iso:country":"ES",
    "sg:address":"Trva Casa Mario, 2",
    "sg:city":"Grado",
    "sg:orig_category":"Molduras, Junquillos, Listones Y Molduras Perforadas",
    "sg:phone":"+34 985 75 22 96",
    "sg:postcode":"33820",
    "sg:province":"Asturias",
    "wof:name":"Estrada Suarez Miguel Angel",
    "wof:placetype":"venue"
},
  "geometry": {"coordinates":[-6.0696001053,43.3886184692],"type":"Point"}
}