{
  "type": "Feature",
  "properties": {
    "iso:country":"ES",
    "sg:address":"Calle de Vallespin, 14",
    "sg:city":"Avila",
    "sg:orig_category":"Electrodom\u00c9sticos (al Por Menor)",
    "sg:phone":"+34 920 22 85 97",
    "sg:postcode":"05001",
    "sg:province":"\u00c1vila",
    "wof:name":"Lopez Lastras Francisco Javier",
    "wof:placetype":"venue"
},
  "geometry": {"coordinates":[-4.7006449699,40.6565856934],"type":"Point"}
}