{
  "type": "Feature",
  "properties": {
    "addr:full":"Calle de Reyes Catolicos, 2 Salamanca Salamanca 37002",
    "addr:housenumber":"2",
    "addr:postcode":"37002",
    "addr:street":"Calle De Reyes Catolicos",
    "iso:country":"ES",
    "sg:address":"Calle de Reyes Catolicos, 2",
    "sg:city":"Salamanca",
    "sg:orig_category":"Abogados",
    "sg:phone":"+34 923 26 55 50",
    "sg:postcode":"37002",
    "sg:province":"Salamanca",
    "wof:name":"Pinedo Sanchez Luis",
    "wof:placetype":"venue"
},
  "geometry": {"coordinates":[-5.6640768051,40.9683876038],"type":"Point"}
}