{
  "type": "Feature",
  "properties": {
    "iso:country":"ES",
    "sg:address":"Carr Salvador Giner, 3",
    "sg:city":"Alcasser",
    "sg:orig_category":"Fabricaci\u00d3n De Telas Y Sedas",
    "sg:phone":"+34 961 23 09 18",
    "sg:postcode":"46290",
    "sg:province":"Valencia",
    "wof:name":"Navarro Domingo Vicente",
    "wof:placetype":"venue"
},
  "geometry": {"coordinates":[-0.4458410144,39.3690567017],"type":"Point"}
}