{
  "type": "Feature",
  "properties": {
    "iso:country":"ES",
    "sg:address":"Calle de Alvaro De Menda\u00d1a, 1",
    "sg:city":"Ponferrada",
    "sg:orig_category":"Abogados",
    "sg:phone":"+34 987 41 52 74",
    "sg:postcode":"24400",
    "sg:province":"Le\u00f3n",
    "wof:name":"Fernandez Merayo Gloria",
    "wof:placetype":"venue"
},
  "geometry": {"coordinates":[-6.6031184196,42.5492286682],"type":"Point"}
}