{
  "type": "Feature",
  "properties": {
    "iso:country":"ES",
    "sg:address":"Av Valles, 448",
    "sg:city":"Terrassa",
    "sg:orig_category":"Loter\u00cda Y T\u00d3mbola",
    "sg:phone":"+34 937 85 16 72",
    "sg:postcode":"08227",
    "sg:province":"Barcelona",
    "sg:website":"www.retel.com/web/admin23",
    "wof:name":"Antequera Pleguezuelos Pietat",
    "wof:placetype":"venue"
},
  "geometry": {"coordinates":[2.030349493,41.5762290955],"type":"Point"}
}