{
  "type": "Feature",
  "properties": {
    "addr:full":"Calle de Juan De Avila, 5 Santa Cruz De Tenerife Santa Cruz De Tenerife 38009",
    "addr:housenumber":"5",
    "addr:postcode":"38009",
    "addr:street":"Calle De Juan De Avila",
    "iso:country":"ES",
    "sg:address":"Calle de Juan De Avila, 5",
    "sg:city":"Santa Cruz De Tenerife",
    "sg:orig_category":"Mec\u00c1nico Del Autom\u00d3vil",
    "sg:phone":"+34 922 21 04 08",
    "sg:postcode":"38009",
    "sg:province":"Santa Cruz De Tenerife",
    "wof:name":"Perez Garcia Jose Guillermo",
    "wof:placetype":"venue"
},
  "geometry": {"coordinates":[-16.2744312286,28.4510936737],"type":"Point"}
}