{
  "type": "Feature",
  "properties": {
    "addr:full":"Carrer de Maladeta, 31 Barcelona Barcelona 08016",
    "addr:housenumber":"31",
    "addr:postcode":"08016",
    "addr:street":"Carrer De Maladeta",
    "iso:country":"ES",
    "sg:address":"Carrer de Maladeta, 31",
    "sg:city":"Barcelona",
    "sg:orig_category":"Muebles, Minoristas",
    "sg:phone":"+34 933 49 47 82",
    "sg:postcode":"08016",
    "sg:province":"Barcelona",
    "wof:name":"Cerrillo Torrubia Antonio",
    "wof:placetype":"venue"
},
  "geometry": {"coordinates":[2.1759660244,41.4323616028],"type":"Point"}
}