{
  "type": "Feature",
  "properties": {
    "addr:full":"Calle de Mefisto, 5 Zaragoza Zaragoza 50001",
    "addr:housenumber":"5",
    "addr:postcode":"50001",
    "addr:street":"Calle De Mefisto",
    "iso:country":"ES",
    "sg:address":"Calle de Mefisto, 5",
    "sg:city":"Zaragoza",
    "sg:orig_category":"Laboratorios De Control Sanitario Y Ambiental",
    "sg:phone":"+34 976 23 09 37",
    "sg:postcode":"50001",
    "sg:province":"Zaragoza",
    "wof:name":"Sudismin S.l.",
    "wof:placetype":"venue"
},
  "geometry": {"coordinates":[-0.8793814778,41.647769928],"type":"Point"}
}