{
  "type": "Feature",
  "properties": {
    "iso:country":"ES",
    "sg:address":"Calle de Mateo Garza, 6",
    "sg:city":"Ponferrada",
    "sg:orig_category":"M\u00c1quinas De Escribir, M\u00c1quinas De Oficina (al Por Menor, Reparaci\u00d3n)",
    "sg:phone":"+34 987 40 16 61",
    "sg:postcode":"24400",
    "sg:province":"Le\u00f3n",
    "wof:name":"Astiarraga S. L.",
    "wof:placetype":"venue"
},
  "geometry": {"coordinates":[-6.5686540604,42.4464454651],"type":"Point"}
}