{
  "type": "Feature",
  "properties": {
    "addr:full":"Cra. S. Celoni A Campins, Km. 0002,2 S. Celoni Barcelona 08470",
    "addr:postcode":"08470",
    "addr:street":"Cra. S. Celoni A Campins Km. 0002,2 S. Celoni Barcelona",
    "iso:country":"ES",
    "sg:address":"Cra. S. Celoni A Campins, Km. 0002,2",
    "sg:city":"S. Celoni",
    "sg:orig_category":"Producci\u00d3n, Distribuci\u00d3n De Gas Butano Y Propano",
    "sg:phone":"+34 938 67 09 48",
    "sg:postcode":"08470",
    "sg:province":"Barcelona",
    "wof:name":"Hijos De Luis Prat S.l.",
    "wof:placetype":"venue"
},
  "geometry": {"coordinates":[2.489289999,41.6902389526],"type":"Point"}
}