{
  "type": "Feature",
  "properties": {
    "addr:full":"Calle de San Jose, 21 Gascue\u00f1a Cuenca 16533",
    "addr:housenumber":"21",
    "addr:postcode":"16533",
    "addr:street":"Calle De San;Gascuen\u0303A Cuenca",
    "iso:country":"ES",
    "sg:address":"Calle de San Jose, 21",
    "sg:city":"Gascue\u00f1a",
    "sg:orig_category":"Comercio De Cuadros, L\u00c1minas Y Reproducciones De Obras De Arte",
    "sg:phone":"+34 969 37 62 93",
    "sg:postcode":"16533",
    "sg:province":"Cuenca",
    "wof:name":"Salvador Sinis Alfredo",
    "wof:placetype":"venue"
},
  "geometry": {"coordinates":[-2.5189781189,40.2999610901],"type":"Point"}
}