{
  "type": "Feature",
  "properties": {
    "iso:country":"ES",
    "sg:address":"Pto. Sta. Maria, 3",
    "sg:city":"Guadix",
    "sg:orig_category":"Molduras, Junquillos, Listones Y Molduras Perforadas",
    "sg:phone":"+34 958 66 24 05",
    "sg:postcode":"18500",
    "sg:province":"Granada",
    "wof:name":"Mu\u00f1oz Ruiz Jesus",
    "wof:placetype":"venue"
},
  "geometry": {"coordinates":[-3.1343688965,37.303894043],"type":"Point"}
}