{
  "type": "Feature",
  "properties": {
    "addr:full":"Calle de Monovar, 17 Petrer Alicante 03610",
    "addr:housenumber":"17",
    "addr:postcode":"03610",
    "addr:street":"Calle De Monovar",
    "iso:country":"ES",
    "sg:address":"Calle de Monovar, 17",
    "sg:city":"Petrer",
    "sg:orig_category":"Grafistas",
    "sg:phone":"+34 965 37 44 74",
    "sg:postcode":"03610",
    "sg:province":"Alicante",
    "wof:name":"Fuentes Gallego Ignacio Ramon",
    "wof:placetype":"venue"
},
  "geometry": {"coordinates":[-0.7833690047,38.4842338562],"type":"Point"}
}