{
  "type": "Feature",
  "properties": {
    "addr:full":"Ptda Marjal, S/n Denia Alicante 03700",
    "addr:housenumber":"s / n",
    "addr:postcode":"03700",
    "addr:street":"Ptda Marjal",
    "iso:country":"ES",
    "sg:address":"Ptda Marjal, S/n",
    "sg:city":"Denia",
    "sg:orig_category":"Asociaciones Y Clubs Deportivos",
    "sg:phone":"+34 965 78 21 90",
    "sg:postcode":"03700",
    "sg:province":"Alicante",
    "wof:name":"Club De Tenis Denia",
    "wof:placetype":"venue"
},
  "geometry": {"coordinates":[0.0912360027,38.8460502625],"type":"Point"}
}