{
  "type": "Feature",
  "properties": {
    "addr:full":"Carr Ulla, 32 Torroella Montgri Girona 17257",
    "addr:housenumber":"32",
    "addr:postcode":"17257",
    "addr:street":"Carr Ulla",
    "iso:country":"ES",
    "sg:address":"Carr Ulla, 32",
    "sg:city":"Torroella Montgri",
    "sg:orig_category":"Carnicer\u00cdas, Carnicer\u00cdas",
    "sg:phone":"+34 972 75 83 06",
    "sg:postcode":"17257",
    "sg:province":"Girona",
    "wof:name":"Carnisseria Ferran I Eva S.l.",
    "wof:placetype":"venue"
},
  "geometry": {"coordinates":[3.1034500599,42.0303268433],"type":"Point"}
}