{
  "type": "Feature",
  "properties": {
    "iso:country":"ES",
    "sg:address":"Calle de Villacarlos, 9",
    "sg:city":"Madrid",
    "sg:orig_category":"Alquiler De V\u00cddeo",
    "sg:phone":"+34 917 76 01 01",
    "sg:postcode":"28032",
    "sg:province":"Madrid",
    "wof:name":"Tercero Mo\u00f1ino Casto",
    "wof:placetype":"venue"
},
  "geometry": {"coordinates":[-3.6071898937,40.4063453674],"type":"Point"}
}