{
  "type": "Feature",
  "properties": {
    "addr:full":"Av San Jorge, 51 Iru\u00f1a Navarra 31012",
    "addr:housenumber":"51",
    "addr:postcode":"31012",
    "addr:street":"Av San Jorge",
    "iso:country":"ES",
    "sg:address":"Av San Jorge, 51",
    "sg:city":"Iru\u00f1a",
    "sg:orig_category":"Comercio, Reparaci\u00d3n De Bicicletas, De Motocicletas, De Accesorios",
    "sg:phone":"+34 948 12 91 80",
    "sg:postcode":"31012",
    "sg:province":"Navarra",
    "wof:name":"Liras Beaumont Luis",
    "wof:placetype":"venue"
},
  "geometry": {"coordinates":[-1.6687413454,42.8209228516],"type":"Point"}
}