{
  "type": "Feature",
  "properties": {
    "addr:full":"Calle de Los Casta\u00d1os, 14 Poligono Ind. La Mora Valladolid 47193",
    "addr:housenumber":"14 poligono",
    "addr:postcode":"47193",
    "addr:street":"Calle De Los Castan\u0303Os;Ind. La Mora",
    "iso:country":"ES",
    "sg:address":"Calle de Los Casta\u00d1os, 14",
    "sg:city":"Poligono Ind. La Mora",
    "sg:orig_category":"Agua",
    "sg:phone":"+34 983 40 32 17",
    "sg:postcode":"47193",
    "sg:province":"Valladolid",
    "wof:name":"Gasmedi 2000 S.a.u.",
    "wof:placetype":"venue"
},
  "geometry": {"coordinates":[-4.6859240532,41.6106681824],"type":"Point"}
}