{
  "type": "Feature",
  "properties": {
    "addr:full":"Calle de Jorge Torner, 39 Cuenca Cuenca 16004",
    "addr:housenumber":"39",
    "addr:postcode":"16004",
    "addr:street":"Calle De Jorge Torner",
    "iso:country":"ES",
    "sg:address":"Calle de Jorge Torner, 39",
    "sg:city":"Cuenca",
    "sg:orig_category":"Fotocopias, Reprograf\u00cda",
    "sg:phone":"+34 969 24 01 36",
    "sg:postcode":"16004",
    "sg:province":"Cuenca",
    "wof:name":"Semford S.l.",
    "wof:placetype":"venue"
},
  "geometry": {"coordinates":[-2.1334090233,40.0665397644],"type":"Point"}
}