{
  "type": "Feature",
  "properties": {
    "addr:full":"Carrer de Marian Aguilo, 4 Palma Islas Baleares 07005",
    "addr:housenumber":"4",
    "addr:postcode":"07005",
    "addr:street":"Carrer De Marian Aguilo",
    "iso:country":"ES",
    "sg:address":"Carrer de Marian Aguilo, 4",
    "sg:city":"Palma",
    "sg:orig_category":"Cerrajer\u00cda, Ferrallista",
    "sg:phone":"+34 971 24 86 02",
    "sg:postcode":"07005",
    "sg:province":"Islas Baleares",
    "wof:name":"Massot Juan Bartolome",
    "wof:placetype":"venue"
},
  "geometry": {"coordinates":[2.6612329483,39.5764465332],"type":"Point"}
}