{
  "type": "Feature",
  "properties": {
    "iso:country":"ES",
    "sg:address":"Calle de Fernan Gonzalez, 42",
    "sg:city":"Madrid",
    "sg:orig_category":"Cristaler\u00cdas",
    "sg:phone":"+34 915 74 20 24",
    "sg:postcode":"28009",
    "sg:province":"Madrid",
    "wof:name":"Garmon Cristalerias S.l.",
    "wof:placetype":"venue"
},
  "geometry": {"coordinates":[-3.6746790409,40.4201011658],"type":"Point"}
}