{
  "type": "Feature",
  "properties": {
    "iso:country":"ES",
    "sg:address":"Av Doctor Severo Ochoa, 1",
    "sg:city":"Benidorm",
    "sg:orig_category":"Bazares, Art\u00cdculos De Limpieza Y De Cocina (al Por Menor)",
    "sg:phone":"+34 966 80 22 73",
    "sg:postcode":"03500",
    "sg:province":"Alicante",
    "wof:name":"Jianwu  Dong",
    "wof:placetype":"venue"
},
  "geometry": {"coordinates":[-0.1043599993,38.5404968262],"type":"Point"}
}