{
  "type": "Feature",
  "properties": {
    "addr:full":"Calle de Cristo Rey, 4 Olivares Sevilla 41804",
    "addr:housenumber":"4",
    "addr:postcode":"41804",
    "addr:street":"Calle De Cristo Rey;Sevilla",
    "iso:country":"ES",
    "sg:address":"Calle de Cristo Rey, 4",
    "sg:city":"Olivares",
    "sg:orig_category":"Asociaciones, Organismos Culturales Y Socioeducativos",
    "sg:phone":"+34 954 11 02 90",
    "sg:postcode":"41804",
    "sg:province":"Sevilla",
    "wof:name":"Asociacion Sevillana De Subnormales Profundos",
    "wof:placetype":"venue"
},
  "geometry": {"coordinates":[-6.1555833817,37.4174613953],"type":"Point"}
}