{
  "type": "Feature",
  "properties": {
    "iso:country":"ES",
    "sg:address":"Carrer de Sant Pere Mitja, 25",
    "sg:city":"Barcelona",
    "sg:orig_category":"Carnicer\u00cdas, Carnicer\u00cdas",
    "sg:phone":"+34 932 68 44 38",
    "sg:postcode":"08003",
    "sg:province":"Barcelona",
    "wof:name":"Assahli  Abdella",
    "wof:placetype":"venue"
},
  "geometry": {"coordinates":[2.1771767139,41.3876724243],"type":"Point"}
}