{
  "type": "Feature",
  "properties": {
    "iso:country":"ES",
    "sg:address":"Calle de Antonio Garcia Gomez, 9",
    "sg:city":"Jun",
    "sg:orig_category":"Fabricaci\u00d3n De Juguetes Autom\u00c1ticos",
    "sg:phone":"+34 958 41 60 81",
    "sg:postcode":"18213",
    "sg:province":"Granada",
    "wof:name":"Automaticos Grupo Dos S.l.",
    "wof:placetype":"venue"
},
  "geometry": {"coordinates":[-3.5906603336,37.2182655334],"type":"Point"}
}