{
  "type": "Feature",
  "properties": {
    "addr:full":"Calle de Andres Mellado, 39 Madrid Madrid 28015",
    "addr:housenumber":"39",
    "addr:postcode":"madrid;28015",
    "addr:street":"Calle De Andres Mellado",
    "iso:country":"ES",
    "sg:address":"Calle de Andres Mellado, 39",
    "sg:city":"Madrid",
    "sg:orig_category":"Fabricaci\u00d3n, Importaci\u00d3n De Material Y Sistemas De Telecomunicaciones",
    "sg:phone":"+34 915 43 12 79",
    "sg:postcode":"28015",
    "sg:province":"Madrid",
    "sg:website":"www.pronitel.com",
    "wof:name":"Nieto Luelmo Carlos",
    "wof:placetype":"venue"
},
  "geometry": {"coordinates":[-3.7144072056,40.4345932007],"type":"Point"}
}