{
  "type": "Feature",
  "properties": {
    "iso:country":"ES",
    "sg:address":"Ctra. Sta. Eularia(jesus), S/n",
    "sg:city":"Ntra. Sra. Jesus",
    "sg:orig_category":"Empresas De Carpinter\u00cda De Madera",
    "sg:phone":"+34 971 19 21 17",
    "sg:postcode":"07819",
    "sg:province":"Islas Baleares",
    "wof:name":"Torres Boned Jose",
    "wof:placetype":"venue"
},
  "geometry": {"coordinates":[1.4268300533,38.9248008728],"type":"Point"}
}