{
  "type": "Feature",
  "properties": {
    "addr:full":"Carrer de Sant Damia, 208 Terrassa Barcelona 08222",
    "addr:housenumber":"208",
    "addr:postcode":"08222",
    "addr:street":"Carrer De Sant Damia",
    "iso:country":"ES",
    "sg:address":"Carrer de Sant Damia, 208",
    "sg:city":"Terrassa",
    "sg:orig_category":"Abogados",
    "sg:phone":"+34 937 83 79 24",
    "sg:postcode":"08222",
    "sg:province":"Barcelona",
    "wof:name":"Garcia Bravo Rafael",
    "wof:placetype":"venue"
},
  "geometry": {"coordinates":[2.03074193,41.5641174316],"type":"Point"}
}