{
  "type": "Feature",
  "properties": {
    "iso:country":"ES",
    "sg:address":"Calle de Cabo De Tortosa, 13",
    "sg:city":"Arganda",
    "sg:orig_category":"Artes Gr\u00c1ficas, Artes Pl\u00c1sticas (curso)",
    "sg:phone":"+34 918 70 21 36",
    "sg:postcode":"28500",
    "sg:province":"Madrid",
    "wof:name":"Din Impresores S. L.",
    "wof:placetype":"venue"
},
  "geometry": {"coordinates":[-3.47437644,40.3127632141],"type":"Point"}
}