{
  "type": "Feature",
  "properties": {
    "iso:country":"ES",
    "sg:address":"Calle de Juan De Herrera, 17",
    "sg:city":"Santander",
    "sg:orig_category":"Comidas Por Encargo, Organizaci\u00d3n De Recepciones",
    "sg:phone":"+34 942 22 68 32",
    "sg:postcode":"39001",
    "sg:province":"Cantabria",
    "wof:name":"Parroquia De La Anunciacion",
    "wof:placetype":"venue"
},
  "geometry": {"coordinates":[-3.8074979782,43.4621543884],"type":"Point"}
}