{
  "type": "Feature",
  "properties": {
    "iso:country":"ES",
    "sg:address":"Calle de Almendro, Km. 0377,0",
    "sg:city":"Molina Segura",
    "sg:orig_category":"Material Y Equipo Para Conserver\u00cdas Y Confiter\u00cdas",
    "sg:phone":"+34 968 61 64 90",
    "sg:postcode":"30500",
    "sg:province":"Murcia",
    "sg:website":"www.fma.es",
    "wof:name":"Fabricacion Maquinaria Alimentacion S.a.",
    "wof:placetype":"venue"
},
  "geometry": {"coordinates":[-1.2204145193,38.0702972412],"type":"Point"}
}