{
  "type": "Feature",
  "properties": {
    "iso:country":"ES",
    "sg:address":"Carretera Azuaga Cordoba, Km. 0006,0",
    "sg:city":"Malcocinado",
    "sg:orig_category":"Agricultores, Agricultores",
    "sg:phone":"+34 924 14 40 08",
    "sg:postcode":"06928",
    "sg:province":"Badajoz",
    "wof:name":"Avellanal Calzadilla Angel Del",
    "wof:placetype":"venue"
},
  "geometry": {"coordinates":[-5.7194523811,38.1038246155],"type":"Point"}
}