{
  "type": "Feature",
  "properties": {
    "addr:full":"Pase Estacion, 59 Salamanca Salamanca 37004",
    "addr:housenumber":"59",
    "addr:postcode":"37004",
    "addr:street":"Estacion",
    "iso:country":"ES",
    "sg:address":"Pase Estacion, 59",
    "sg:city":"Salamanca",
    "sg:orig_category":"Producci\u00d3n, Comercio De Cereales",
    "sg:phone":"+34 923 24 50 27",
    "sg:postcode":"37004",
    "sg:province":"Salamanca",
    "wof:name":"Patatas Ruiz S.l.",
    "wof:placetype":"venue"
},
  "geometry": {"coordinates":[-5.6529240608,40.9705314636],"type":"Point"}
}