{
  "type": "Feature",
  "properties": {
    "addr:full":"Marques De Vista Alegre, 7 Infiesto Asturias 33530",
    "addr:housenumber":"7",
    "addr:postcode":"33530",
    "addr:street":"Marques;Vista Alegre",
    "iso:country":"ES",
    "sg:address":"Marques De Vista Alegre, 7",
    "sg:city":"Infiesto",
    "sg:orig_category":"Fisioterapia",
    "sg:phone":"+34 985 71 18 84",
    "sg:postcode":"33530",
    "sg:province":"Asturias",
    "wof:name":"Fernandez Barcena Maria Cristina",
    "wof:placetype":"venue"
},
  "geometry": {"coordinates":[-5.3611588478,43.3452949524],"type":"Point"}
}