{
  "type": "Feature",
  "properties": {
    "addr:full":"Plaz Espa\u00d1a De, 1 S. Juan Puerto Huelva 21610",
    "addr:postcode":"21610",
    "addr:street":"Plaz;S. Juan Puerto",
    "iso:country":"ES",
    "sg:address":"Plaz Espa\u00d1a De, 1",
    "sg:city":"S. Juan Puerto",
    "sg:orig_category":"Ense\u00d1anza, Formaci\u00d3n Profesional: Aprendizaje",
    "sg:phone":"+34 959 35 62 25",
    "sg:postcode":"21610",
    "sg:province":"Huelva",
    "wof:name":"Ayuntamiento De San Juan Del Puerto",
    "wof:placetype":"venue"
},
  "geometry": {"coordinates":[-6.9495549202,37.2570991516],"type":"Point"}
}