{
  "type": "Feature",
  "properties": {
    "addr:full":"Calle de Despe\u00d1aperros, 4 Arganda Madrid 28500",
    "addr:housenumber":"4",
    "addr:postcode":"28500",
    "addr:street":"Calle De Despen\u0303Aperros",
    "iso:country":"ES",
    "sg:address":"Calle de Despe\u00d1aperros, 4",
    "sg:city":"Arganda",
    "sg:orig_category":"Pintura Y Barniz (al Por Menor)",
    "sg:phone":"+34 918 71 90 10",
    "sg:postcode":"28500",
    "sg:province":"Madrid",
    "wof:name":"Argacolor S.l.",
    "wof:placetype":"venue"
},
  "geometry": {"coordinates":[-3.4793536663,40.3074836731],"type":"Point"}
}