{
  "type": "Feature",
  "properties": {
    "addr:full":"Calle de Mar Blanco, 10 Adra Almer\u00eda 04770",
    "addr:housenumber":"10",
    "addr:postcode":"04770",
    "addr:street":"Calle De Mar Blanco;Almeri\u0301A",
    "iso:country":"ES",
    "sg:address":"Calle de Mar Blanco, 10",
    "sg:city":"Adra",
    "sg:orig_category":"Caf\u00c9s, Bares, Cervecer\u00cdas",
    "sg:phone":"+34 950 60 43 54",
    "sg:postcode":"04770",
    "sg:province":"Almer\u00eda",
    "wof:name":"Sorvilan Servicios S.l.",
    "wof:placetype":"venue"
},
  "geometry": {"coordinates":[-3.0254039764,36.7492790222],"type":"Point"}
}