{
  "type": "Feature",
  "properties": {
    "iso:country":"ES",
    "sg:address":"Calle de Rambla Obispo Orbera, 1",
    "sg:city":"Almeria",
    "sg:orig_category":"Abogados",
    "sg:phone":"+34 950 27 25 17",
    "sg:postcode":"04001",
    "sg:province":"Almer\u00eda",
    "wof:name":"Aljibes De Jairan S.l.",
    "wof:placetype":"venue"
},
  "geometry": {"coordinates":[-2.4634273052,36.8413467407],"type":"Point"}
}