{
  "type": "Feature",
  "properties": {
    "addr:full":"Av Paisos Catalans, 41 Reus Tarragona 43202",
    "addr:housenumber":"41",
    "addr:postcode":"43202",
    "addr:street":"Av Paisos Catalans",
    "iso:country":"ES",
    "sg:address":"Av Paisos Catalans, 41",
    "sg:city":"Reus",
    "sg:orig_category":"Inmobiliaria (agencias)",
    "sg:phone":"+34 977 32 70 60",
    "sg:postcode":"43202",
    "sg:province":"Tarragona",
    "wof:name":"Comunidad De Propietarios Avinguda Paisos Catalans 41",
    "wof:placetype":"venue"
},
  "geometry": {"coordinates":[1.0964449644,41.1577072144],"type":"Point"}
}