{
  "type": "Feature",
  "properties": {
    "addr:full":"Rua Carlos Iii, 58 Ferrol La Coru\u00f1a 15403",
    "addr:housenumber":"58",
    "addr:postcode":"15403",
    "addr:street":"Rua Carlos Iii;La Corun\u0303A",
    "iso:country":"ES",
    "sg:address":"Rua Carlos Iii, 58",
    "sg:city":"Ferrol",
    "sg:orig_category":"Molduras, Junquillos, Listones Y Molduras Perforadas",
    "sg:phone":"+34 981 35 32 25",
    "sg:postcode":"15403",
    "sg:province":"La Coru\u00f1a",
    "wof:name":"Faraldo Martinez Juan",
    "wof:placetype":"venue"
},
  "geometry": {"coordinates":[-8.2254285812,43.4814033508],"type":"Point"}
}