{
  "type": "Feature",
  "properties": {
    "iso:country":"ES",
    "sg:address":"Calle de Jose Arana, 17",
    "sg:city":"Donostia-san Sebastian",
    "sg:orig_category":"M\u00c9dicos: Naturistas",
    "sg:phone":"+34 943 27 48 89",
    "sg:postcode":"20001",
    "sg:province":"Guip\u00f9zcoa",
    "wof:name":"Iraola Rodriguez Gonzalo",
    "wof:placetype":"venue"
},
  "geometry": {"coordinates":[-1.969274044,43.3242607117],"type":"Point"}
}