{
  "type": "Feature",
  "properties": {
    "iso:country":"ES",
    "sg:address":"Pla\u00c7 Catalunya, 1",
    "sg:city":"Olot",
    "sg:orig_category":"Notarios",
    "sg:phone":"+34 972 27 50 32",
    "sg:postcode":"17800",
    "sg:province":"Girona",
    "wof:name":"Arregui Laborda Angel",
    "wof:placetype":"venue"
},
  "geometry": {"coordinates":[2.4703056812,42.1801338196],"type":"Point"}
}