{
  "type": "Feature",
  "properties": {
    "addr:full":"Calle de Juan Llorens, 60 Valencia Valencia 46008",
    "addr:housenumber":"60",
    "addr:postcode":"46008",
    "addr:street":"Calle De Juan Llorens",
    "iso:country":"ES",
    "sg:address":"Calle de Juan Llorens, 60",
    "sg:city":"Valencia",
    "sg:orig_category":"Abogados",
    "sg:phone":"+34 963 84 77 98",
    "sg:postcode":"46008",
    "sg:province":"Valencia",
    "wof:name":"Canales Conejero Servando",
    "wof:placetype":"venue"
},
  "geometry": {"coordinates":[-0.388985008,39.4700660706],"type":"Point"}
}