{
  "type": "Feature",
  "properties": {
    "iso:country":"ES",
    "sg:address":"Olazko Amaren Plaza, 2",
    "sg:city":"Azpeitia",
    "sg:orig_category":"Estancos",
    "sg:phone":"+34 943 81 06 67",
    "sg:postcode":"20730",
    "sg:province":"Guip\u00f9zcoa",
    "wof:name":"Acilona Alberdi Maria Eugenia",
    "wof:placetype":"venue"
},
  "geometry": {"coordinates":[-2.2670834064,43.183506012],"type":"Point"}
}