{
  "type": "Feature",
  "properties": {
    "addr:full":"Camino De Lozen, 5 Iraizotz Navarra 31797",
    "addr:housenumber":"5",
    "addr:postcode":"31797",
    "addr:street":"Camino De Lozen",
    "iso:country":"ES",
    "sg:address":"Camino De Lozen, 5",
    "sg:city":"Iraizotz",
    "sg:orig_category":"Guarder\u00cdas",
    "sg:phone":"+34 948 30 65 67",
    "sg:postcode":"31797",
    "sg:province":"Navarra",
    "wof:name":"Xinbili Xanbala",
    "wof:placetype":"venue"
},
  "geometry": {"coordinates":[-1.6726241112,42.9933204651],"type":"Point"}
}