{
  "type": "Feature",
  "properties": {
    "addr:full":"Carretera Las Negras, 14 Campohermoso Almer\u00eda 04110",
    "addr:housenumber":"14",
    "addr:postcode":"04110",
    "addr:street":"Carretera Las Negras;Almeri\u0301A",
    "iso:country":"ES",
    "sg:address":"Carretera Las Negras, 14",
    "sg:city":"Campohermoso",
    "sg:orig_category":"Formaci\u00d3n Continuada (variada)",
    "sg:phone":"+34 950 38 56 01",
    "sg:postcode":"04110",
    "sg:province":"Almer\u00eda",
    "wof:name":"Carrizo Mu\u00f1oz Miguel",
    "wof:placetype":"venue"
},
  "geometry": {"coordinates":[-2.1384088993,36.9406242371],"type":"Point"}
}