{
  "type": "Feature",
  "properties": {
    "iso:country":"ES",
    "sg:address":"Cuatro A, 193",
    "sg:city":"San Pedro Alcantara",
    "sg:orig_category":"Asesor\u00cda Sobre Comunicaci\u00d3n De Empresas",
    "sg:phone":"+34 952 92 85 84",
    "sg:postcode":"29670",
    "sg:province":"M\u00e1laga",
    "wof:name":"Guecho Sociedad De Estudios 2002 S.l.",
    "wof:placetype":"venue"
},
  "geometry": {"coordinates":[-4.9784603119,36.4786491394],"type":"Point"}
}