{
  "type": "Feature",
  "properties": {
    "addr:full":"Calle de Real, 19 Almonaster Real Huelva 21350",
    "addr:housenumber":"19",
    "addr:postcode":"21350",
    "addr:street":"Calle De Real",
    "iso:country":"ES",
    "sg:address":"Calle de Real, 19",
    "sg:city":"Almonaster Real",
    "sg:orig_category":"Cr\u00cda De Animales",
    "sg:phone":"+34 959 14 30 29",
    "sg:postcode":"21350",
    "sg:province":"Huelva",
    "wof:name":"Gonzalez Gonzalez Jose",
    "wof:placetype":"venue"
},
  "geometry": {"coordinates":[-6.7868599892,37.8735618591],"type":"Point"}
}