{
  "type": "Feature",
  "properties": {
    "addr:full":"Monasterioguren, 16 Monasterioguren \u00c1lava 01194",
    "addr:housenumber":"16",
    "addr:postcode":"01194",
    "addr:street":"Monasterioguren;A\u0301Lava",
    "iso:country":"ES",
    "sg:address":"Monasterioguren, 16",
    "sg:city":"Monasterioguren",
    "sg:orig_category":"Muebles, Minoristas",
    "sg:phone":"+34 945 13 81 72",
    "sg:postcode":"01194",
    "sg:province":"\u00c1lava",
    "wof:name":"Muebles Navas S.a.",
    "wof:placetype":"venue"
},
  "geometry": {"coordinates":[-2.643157959,42.8030471802],"type":"Point"}
}