{
  "type": "Feature",
  "properties": {
    "iso:country":"ES",
    "sg:address":"Calle de Nuestra Se\u00d1ora De La Fuensanta, 13",
    "sg:city":"Ba\u00e7os Y Mendigo",
    "sg:orig_category":"Empresas De Desmonte",
    "sg:phone":"+34 968 38 30 74",
    "sg:postcode":"30155",
    "sg:province":"Murcia",
    "wof:name":"Padilla Garcia Jose",
    "wof:placetype":"venue"
},
  "geometry": {"coordinates":[-1.1278840303,37.8708992004],"type":"Point"}
}