{
  "type": "Feature",
  "properties": {
    "iso:country":"ES",
    "sg:address":"Carr Moll De Llevant, 218",
    "sg:city":"Mao",
    "sg:orig_category":"Abogados",
    "sg:phone":"+34 971 35 28 43",
    "sg:postcode":"07703",
    "sg:province":"Islas Baleares",
    "wof:name":"Yrazu Bajo Olga",
    "wof:placetype":"venue"
},
  "geometry": {"coordinates":[4.2753725052,39.8906021118],"type":"Point"}
}