{
  "type": "Feature",
  "properties": {
    "addr:full":"Rua Cesar Boente, 21 Pontevedra Pontevedra 36002",
    "addr:housenumber":"21",
    "addr:postcode":"36002",
    "addr:street":"Rua Cesar Boente",
    "iso:country":"ES",
    "sg:address":"Rua Cesar Boente, 21",
    "sg:city":"Pontevedra",
    "sg:orig_category":"Inmobiliaria (agencias)",
    "sg:phone":"+34 986 84 27 73",
    "sg:postcode":"36002",
    "sg:province":"Pontevedra",
    "wof:name":"Inmobiliaria Pomave S.l.",
    "wof:placetype":"venue"
},
  "geometry": {"coordinates":[-8.6434211731,42.4337348938],"type":"Point"}
}