{
  "type": "Feature",
  "properties": {
    "iso:country":"ES",
    "sg:address":"Rier Canyado, S/n",
    "sg:city":"Badalona",
    "sg:orig_category":"Centros De Educaci\u00d3n Especial",
    "sg:phone":"+34 933 89 55 32",
    "sg:postcode":"08911",
    "sg:province":"Barcelona",
    "wof:name":"Ajuntament De Badalona",
    "wof:placetype":"venue"
},
  "geometry": {"coordinates":[2.251096487,41.4599990845],"type":"Point"}
}