{
  "type": "Feature",
  "properties": {
    "addr:full":"Calle de Buena Vista (de La), 15 Pinto Madrid 28320",
    "addr:housenumber":"15",
    "addr:postcode":"28320",
    "addr:street":"Calle De Buena;De;Pinto",
    "iso:country":"ES",
    "sg:address":"Calle de Buena Vista (de La), 15",
    "sg:city":"Pinto",
    "sg:orig_category":"Fisioterapia",
    "sg:phone":"+34 916 92 08 82",
    "sg:postcode":"28320",
    "sg:province":"Madrid",
    "wof:name":"Franqueza Pinos Alicia",
    "wof:placetype":"venue"
},
  "geometry": {"coordinates":[-3.6999547482,40.2450523376],"type":"Point"}
}