{
  "type": "Feature",
  "properties": {
    "iso:country":"ES",
    "sg:address":"Carr Tintorera, S/n",
    "sg:city":"Port D'andratx",
    "sg:orig_category":"Inmobiliaria (agencias)",
    "sg:phone":"+34 971 67 17 65",
    "sg:postcode":"07157",
    "sg:province":"Islas Baleares",
    "wof:name":"Muffi Inversiones S.l",
    "wof:placetype":"venue"
},
  "geometry": {"coordinates":[2.4215099812,39.5746994019],"type":"Point"}
}