{
  "type": "Feature",
  "properties": {
    "addr:full":"Cno. Polvoranca, 13 Leganes Madrid 28914",
    "addr:housenumber":"13",
    "addr:postcode":"28914",
    "addr:street":"Cno. Polvoranca",
    "iso:country":"ES",
    "sg:address":"Cno. Polvoranca, 13",
    "sg:city":"Leganes",
    "sg:orig_category":"Mec\u00c1nico Del Autom\u00d3vil",
    "sg:phone":"+34 916 93 27 77",
    "sg:postcode":"28914",
    "sg:province":"Madrid",
    "wof:name":"Talleres Guemacar S.l.",
    "wof:placetype":"venue"
},
  "geometry": {"coordinates":[-3.7763791084,40.3261413574],"type":"Point"}
}