{
  "type": "Feature",
  "properties": {
    "iso:country":"ES",
    "sg:address":"Ctra. General, S/n",
    "sg:city":"Sandias",
    "sg:classifiers":[
        {
            "category":"Taxi",
            "type":"Transportation"
        }
    ],
    "sg:phone":"+34 988 46 50 78",
    "sg:postcode":"32692",
    "sg:province":"Ourense",
    "wof:name":"Carnero De Dios Cristalina",
    "wof:placetype":"venue"
},
  "geometry": {"coordinates":[-7.9115138054,42.0854988098],"type":"Point"}
}