{
  "type": "Feature",
  "properties": {
    "addr:full":"Calle de Sdo Alemany Compan, 5 Palma Islas Baleares 07013",
    "addr:housenumber":"5",
    "addr:postcode":"07013",
    "addr:street":"Calle De Sdo Alemany Compan",
    "iso:country":"ES",
    "sg:address":"Calle de Sdo Alemany Compan, 5",
    "sg:city":"Palma",
    "sg:orig_category":"Empresas De Carpinter\u00cda De Madera",
    "sg:phone":"+34 971 45 42 81",
    "sg:postcode":"07013",
    "sg:province":"Islas Baleares",
    "wof:name":"Bauza Mateu Pedro",
    "wof:placetype":"venue"
},
  "geometry": {"coordinates":[2.6343209743,39.5778045654],"type":"Point"}
}