{
  "type": "Feature",
  "properties": {
    "addr:full":"Calle de Sestil (el), S/n Guardo Palencia 34880",
    "addr:housenumber":"/ n",
    "addr:postcode":"34880",
    "addr:street":"Calle De Sestil El S",
    "iso:country":"ES",
    "sg:address":"Calle de Sestil (el), S/n",
    "sg:city":"Guardo",
    "sg:orig_category":"Centros De Educaci\u00d3n Especial",
    "sg:phone":"+34 979 85 06 34",
    "sg:postcode":"34880",
    "sg:province":"Palencia",
    "wof:name":"Colegio Publico De Educacion Infantil Y Primaria Las Rozas",
    "wof:placetype":"venue"
},
  "geometry": {"coordinates":[-4.857049942,42.7907180786],"type":"Point"}
}