{
  "type": "Feature",
  "properties": {
    "iso:country":"ES",
    "sg:address":"Pla\u00c7 Major, 14",
    "sg:city":"Paterna",
    "sg:orig_category":"Asesor\u00cda Sobre Comunicaci\u00d3n De Empresas",
    "sg:phone":"+34 961 38 22 59",
    "sg:postcode":"46980",
    "sg:province":"Valencia",
    "wof:name":"Martinez Martinez Pedro",
    "wof:placetype":"venue"
},
  "geometry": {"coordinates":[-0.4413709939,39.5026245117],"type":"Point"}
}