{
  "type": "Feature",
  "properties": {
    "iso:country":"ES",
    "sg:address":"Calle de Rioja, 24",
    "sg:city":"Zaragoza",
    "sg:orig_category":"Embalajes",
    "sg:phone":"+34 976 53 14 42",
    "sg:postcode":"50017",
    "sg:province":"Zaragoza",
    "wof:name":"Embalajes El Moncayo S.l.",
    "wof:placetype":"venue"
},
  "geometry": {"coordinates":[-0.909307003,41.6547203064],"type":"Point"}
}