{
  "type": "Feature",
  "properties": {
    "iso:country":"ES",
    "sg:address":"Pase Pilarito, S/n",
    "sg:city":"Fregenal Sierra",
    "sg:orig_category":"Suministros Y Materiales Industriales",
    "sg:phone":"+34 924 72 01 54",
    "sg:postcode":"06340",
    "sg:province":"Badajoz",
    "wof:name":"Inmobiliaria Fregenal S.l.",
    "wof:placetype":"venue"
},
  "geometry": {"coordinates":[-6.6505317688,38.1659088135],"type":"Point"}
}