{
  "type": "Feature",
  "properties": {
    "addr:full":"Plaz Espa\u00d1a, 2 Santos De Maimona Badajoz 06230",
    "addr:housenumber":"2",
    "addr:postcode":"06230",
    "addr:street":"Plaz Espan\u0303A",
    "iso:country":"ES",
    "sg:address":"Plaz Espa\u00d1a, 2",
    "sg:city":"Santos De Maimona",
    "sg:orig_category":"Supermercados Y Hipermercados",
    "sg:phone":"+34 924 54 41 80",
    "sg:postcode":"06230",
    "sg:province":"Badajoz",
    "wof:name":"Resmon S.l.",
    "wof:placetype":"venue"
},
  "geometry": {"coordinates":[-6.3725099564,38.4434814453],"type":"Point"}
}