{
  "type": "Feature",
  "properties": {
    "iso:country":"ES",
    "sg:address":"Calle de Fray Jose Cerdeiri\u00d1a, 11",
    "sg:city":"Madrid",
    "sg:orig_category":"Peluquer\u00cdas, Peluquer\u00cda Mixta",
    "sg:phone":"+34 917 10 79 05",
    "sg:postcode":"28024",
    "sg:province":"Madrid",
    "wof:name":"Perez Valiente Maria Del Valle",
    "wof:placetype":"venue"
},
  "geometry": {"coordinates":[-3.7807819843,40.3851852417],"type":"Point"}
}