{
  "type": "Feature",
  "properties": {
    "addr:full":"Calle de Ahogaznos, 3 Medina Rioseco Valladolid 47800",
    "addr:housenumber":"3",
    "addr:postcode":"47800",
    "addr:street":"Calle De Ahogaznos",
    "iso:country":"ES",
    "sg:address":"Calle de Ahogaznos, 3",
    "sg:city":"Medina Rioseco",
    "sg:orig_category":"Plomeros",
    "sg:phone":"+34 983 70 04 04",
    "sg:postcode":"47800",
    "sg:province":"Valladolid",
    "wof:name":"Fernandez Rubio Jaime",
    "wof:placetype":"venue"
},
  "geometry": {"coordinates":[-5.0419545174,41.8857650757],"type":"Point"}
}