{
  "type": "Feature",
  "properties": {
    "addr:full":"Avda Primero De Mayo, S/n Palmar  O Lugar De Don Juan Murcia 30120",
    "addr:housenumber":"s / n",
    "addr:postcode":"30120",
    "addr:street":"Avda Primero De Mayo;Lugar",
    "iso:country":"ES",
    "sg:address":"Avda Primero De Mayo, S/n",
    "sg:city":"Palmar  O Lugar De Don Juan",
    "sg:orig_category":"Distribuci\u00d3n De Petr\u00d3leo Y Derivados",
    "sg:phone":"+34 968 88 47 74",
    "sg:postcode":"30120",
    "sg:province":"Murcia",
    "wof:name":"Espuche Lopez Jose",
    "wof:placetype":"venue"
},
  "geometry": {"coordinates":[-1.1606040001,37.9361457825],"type":"Point"}
}