{
  "type": "Feature",
  "properties": {
    "addr:full":"Carr Pare Puig, 8 Blanes Girona 17300",
    "addr:housenumber":"8",
    "addr:postcode":"17300",
    "addr:street":"Carr Pare Puig",
    "iso:country":"ES",
    "sg:address":"Carr Pare Puig, 8",
    "sg:city":"Blanes",
    "sg:orig_category":"Bisuteros (fabricaci\u00d3n, Al Por Mayor)",
    "sg:phone":"+34 972 35 10 21",
    "sg:postcode":"17300",
    "sg:province":"Girona",
    "wof:name":"Guixe De La Oliva Maria",
    "wof:placetype":"venue"
},
  "geometry": {"coordinates":[2.7863850594,41.6781005859],"type":"Point"}
}