{
  "type": "Feature",
  "properties": {
    "iso:country":"ES",
    "sg:address":"Calle de Jacinto Verdaguer, 31",
    "sg:city":"Madrid",
    "sg:orig_category":"Equipo De Refrigeraci\u00d3n Industrial",
    "sg:phone":"+34 914 28 01 66",
    "sg:postcode":"28019",
    "sg:province":"Madrid",
    "wof:name":"Mice Frio S.l.",
    "wof:placetype":"venue"
},
  "geometry": {"coordinates":[-3.7182450294,40.3954772949],"type":"Point"}
}