{
  "type": "Feature",
  "properties": {
    "addr:full":"Calle de Buenos Aires, 116 Muela Zaragoza 50196",
    "addr:housenumber":"116",
    "addr:postcode":"50196",
    "addr:street":"Calle De Buenos Aires",
    "iso:country":"ES",
    "sg:address":"Calle de Buenos Aires, 116",
    "sg:city":"Muela",
    "sg:orig_category":"Servicios De Telecomunicaciones",
    "sg:phone":"+34 976 14 47 04",
    "sg:postcode":"50196",
    "sg:province":"Zaragoza",
    "wof:name":"Telnet Redes Inteligentes S.a.",
    "wof:placetype":"venue"
},
  "geometry": {"coordinates":[-1.0742878914,41.6119194031],"type":"Point"}
}