{
  "type": "Feature",
  "properties": {
    "addr:full":"Calle de Manzana, 10 Getafe Madrid 28901",
    "addr:housenumber":"10",
    "addr:postcode":"28901",
    "addr:street":"Calle De Manzana",
    "iso:country":"ES",
    "sg:address":"Calle de Manzana, 10",
    "sg:city":"Getafe",
    "sg:orig_category":"Peluqueros: De Se\u00d1oras",
    "sg:phone":"+34 916 83 40 56",
    "sg:postcode":"28901",
    "sg:province":"Madrid",
    "wof:name":"Peluqueria Casin Cosin S.l.",
    "wof:placetype":"venue"
},
  "geometry": {"coordinates":[-3.7278449535,40.3080787659],"type":"Point"}
}