{
  "type": "Feature",
  "properties": {
    "addr:full":"Avda Constitucion (la), 5 Villanueva Tapia M\u00e1laga 29315",
    "addr:housenumber":"5",
    "addr:postcode":"29315",
    "addr:street":"Avda Constitucion La",
    "iso:country":"ES",
    "sg:address":"Avda Constitucion (la), 5",
    "sg:city":"Villanueva Tapia",
    "sg:orig_category":"Bancos",
    "sg:phone":"+34 952 75 00 28",
    "sg:postcode":"29315",
    "sg:province":"M\u00e1laga",
    "wof:name":"Quiles Ortiz Francisco",
    "wof:placetype":"venue"
},
  "geometry": {"coordinates":[-4.3341441154,37.1831741333],"type":"Point"}
}