{
  "type": "Feature",
  "properties": {
    "addr:full":"Carrer de Arago, 13 Santa Perpetua De Mogoda Barcelona 08130",
    "addr:housenumber":"13",
    "addr:postcode":"08130",
    "addr:street":"Carrer De Arago",
    "iso:country":"ES",
    "sg:address":"Carrer de Arago, 13",
    "sg:city":"Santa Perpetua De Mogoda",
    "sg:orig_category":"Montaje (empresas De)",
    "sg:phone":"+34 935 74 36 32",
    "sg:postcode":"08130",
    "sg:province":"Barcelona",
    "wof:name":"Estructuras Fesmon S.l.l.",
    "wof:placetype":"venue"
},
  "geometry": {"coordinates":[2.1772398949,41.5427360535],"type":"Point"}
}