{
  "type": "Feature",
  "properties": {
    "iso:country":"ES",
    "sg:address":"Carrer de Jaume Ii, 21",
    "sg:city":"Palma",
    "sg:orig_category":"\u00d3ptica: Instrumentos (fabricaci\u00d3n)",
    "sg:phone":"+34 971 71 29 22",
    "sg:postcode":"07001",
    "sg:province":"Islas Baleares",
    "wof:name":"Miro Bonnin Luis",
    "wof:placetype":"venue"
},
  "geometry": {"coordinates":[2.650580883,39.5704879761],"type":"Point"}
}