{
  "type": "Feature",
  "properties": {
    "addr:full":"Carr Cami Del Moli, S/n Alqueria De La Comtessa Valencia 46715",
    "addr:housenumber":"s / n",
    "addr:postcode":"46715",
    "addr:street":"Carr Cami Del Moli",
    "iso:country":"ES",
    "sg:address":"Carr Cami Del Moli, S/n",
    "sg:city":"Alqueria De La Comtessa",
    "sg:orig_category":"Producci\u00d3n, Comercio De Cereales",
    "sg:phone":"+34 962 89 30 11",
    "sg:postcode":"46715",
    "sg:province":"Valencia",
    "wof:name":"Hijos De Vicente Catala Peiro S. A.",
    "wof:placetype":"venue"
},
  "geometry": {"coordinates":[-0.1497839987,38.9378852844],"type":"Point"}
}