{
  "type": "Feature",
  "properties": {
    "iso:country":"ES",
    "sg:address":"Calle de Via (la), 5",
    "sg:city":"Zaragoza",
    "sg:orig_category":"Frutas, Legumbres Frescas Y Tempranas (al Por Menor)",
    "sg:phone":"+34 976 56 57 36",
    "sg:postcode":"50009",
    "sg:province":"Zaragoza",
    "wof:name":"Oteo Sanz Ivo",
    "wof:placetype":"venue"
},
  "geometry": {"coordinates":[-0.9081829786,41.6304855347],"type":"Point"}
}