{
  "type": "Feature",
  "properties": {
    "addr:full":"Pl Esglesia, 1 Pu\u00e7ol Valencia 46530",
    "addr:housenumber":"1",
    "addr:postcode":"46530",
    "addr:street":"Pl Esglesia",
    "iso:country":"ES",
    "sg:address":"Pl Esglesia, 1",
    "sg:city":"Pu\u00e7ol",
    "sg:orig_category":"Agentes Generales De Seguros",
    "sg:phone":"+34 961 46 47 83",
    "sg:postcode":"46530",
    "sg:province":"Valencia",
    "wof:name":"Almenara Izquierdo Alberto",
    "wof:placetype":"venue"
},
  "geometry": {"coordinates":[-0.3008775115,39.616268158],"type":"Point"}
}