{
  "type": "Feature",
  "properties": {
    "iso:country":"ES",
    "sg:address":"Avda Canarias De, 18",
    "sg:city":"Palmas De Gran Canaria",
    "sg:orig_category":"Arquitectos",
    "sg:phone":"+34 928 36 64 19",
    "sg:postcode":"35002",
    "sg:province":"Las Palmas",
    "wof:name":"Guillen Jimenez Fermin",
    "wof:placetype":"venue"
},
  "geometry": {"coordinates":[-15.4137544632,28.1060218811],"type":"Point"}
}