{
  "type": "Feature",
  "properties": {
    "iso:country":"ES",
    "sg:address":"Calle de Santa Isabel, 17",
    "sg:city":"Madrid",
    "sg:orig_category":"Abogados",
    "sg:phone":"+34 915 39 60 52",
    "sg:postcode":"28012",
    "sg:province":"Madrid",
    "wof:name":"Taoumi Abderraman Naima",
    "wof:placetype":"venue"
},
  "geometry": {"coordinates":[-3.6979134083,40.4105491638],"type":"Point"}
}