{
  "type": "Feature",
  "properties": {
    "iso:country":"ES",
    "sg:address":"Avda Moliere, 27",
    "sg:city":"Malaga",
    "sg:classifiers":[
        {
            "category":"Autos & Motor Vehicles",
            "subcategory":"Automobile Sales",
            "type":"Retail Goods"
        }
    ],
    "sg:phone":"+34 952 24 10 15",
    "sg:postcode":"29004",
    "sg:province":"M\u00e1laga",
    "wof:name":"Autoescuela Las Piramides S.c.",
    "wof:placetype":"venue"
},
  "geometry": {"coordinates":[-4.451736927,36.6863670349],"type":"Point"}
}