{
  "type": "Feature",
  "properties": {
    "iso:country":"ES",
    "sg:address":"Plaz Pe\u00d1a Horcajo, 3",
    "sg:city":"Madrid",
    "sg:orig_category":"Cl\u00cdnicas Dentales",
    "sg:phone":"+34 917 30 33 04",
    "sg:postcode":"28035",
    "sg:province":"Madrid",
    "wof:name":"Sobrini Sagaseta De Ilurdoz Blanca",
    "wof:placetype":"venue"
},
  "geometry": {"coordinates":[-3.7205269337,40.484588623],"type":"Point"}
}