{
  "type": "Feature",
  "properties": {
    "addr:full":"Moncatil, 11 Fuente Segures Castell\u00f3n 12160",
    "addr:housenumber":"11",
    "addr:postcode":"12160",
    "addr:street":"Moncatil;Castello\u0301N",
    "iso:country":"ES",
    "sg:address":"Moncatil, 11",
    "sg:city":"Fuente Segures",
    "sg:orig_category":"Plomeros",
    "sg:phone":"+34 964 43 14 32",
    "sg:postcode":"12160",
    "sg:province":"Castell\u00f3n",
    "wof:name":"Comercial Emilio Tena S.l.",
    "wof:placetype":"venue"
},
  "geometry": {"coordinates":[-0.1405189931,40.3801345825],"type":"Point"}
}