{
  "type": "Feature",
  "properties": {
    "iso:country":"ES",
    "sg:address":"Carr Badia, 5",
    "sg:city":"Moncada",
    "sg:classifiers":[
        {
            "category":"Autos & Motor Vehicles",
            "subcategory":"Automobile Sales",
            "type":"Retail Goods"
        }
    ],
    "sg:phone":"+34 961 39 44 54",
    "sg:postcode":"46113",
    "sg:province":"Valencia",
    "wof:name":"Escuela De Conductores Manucar S.l.l.",
    "wof:placetype":"venue"
},
  "geometry": {"coordinates":[-0.3982529938,39.5452728271],"type":"Point"}
}