{
  "type": "Feature",
  "properties": {
    "addr:full":"Calle de Perez Galdos, 21 Palmas De Gran Canaria Las Palmas 35002",
    "addr:housenumber":"21",
    "addr:postcode":"35002",
    "addr:street":"Calle De Perez Galdos",
    "iso:country":"ES",
    "sg:address":"Calle de Perez Galdos, 21",
    "sg:city":"Palmas De Gran Canaria",
    "sg:orig_category":"Ense\u00d1anza: Idiomas",
    "sg:phone":"+34 928 37 24 78",
    "sg:postcode":"35002",
    "sg:province":"Las Palmas",
    "wof:name":"London Calling S. L.",
    "wof:placetype":"venue"
},
  "geometry": {"coordinates":[-15.4189968109,28.1058712006],"type":"Point"}
}