{
  "type": "Feature",
  "properties": {
    "iso:country":"ES",
    "sg:address":"Calle de Doctor Blanco Soler, 15",
    "sg:city":"Madrid",
    "sg:orig_category":"Suministros Y Materiales Industriales",
    "sg:phone":"+34 917 06 34 82",
    "sg:postcode":"28044",
    "sg:province":"Madrid",
    "wof:name":"Gas Aire Y Climatizacion S.l.",
    "wof:placetype":"venue"
},
  "geometry": {"coordinates":[-3.7674314976,40.382724762],"type":"Point"}
}