{
  "type": "Feature",
  "properties": {
    "addr:full":"Via Aurelia, 3 Sabadell Barcelona 08206",
    "addr:housenumber":"3",
    "addr:postcode":"08206",
    "addr:street":"Via Aurelia",
    "iso:country":"ES",
    "sg:address":"Via Aurelia, 3",
    "sg:city":"Sabadell",
    "sg:orig_category":"Inmobiliaria (agencias)",
    "sg:phone":"+34 937 24 33 34",
    "sg:postcode":"08206",
    "sg:province":"Barcelona",
    "wof:name":"Finimsab S.l.",
    "wof:placetype":"venue"
},
  "geometry": {"coordinates":[2.0948998928,41.5554580688],"type":"Point"}
}