{
  "type": "Feature",
  "properties": {
    "iso:country":"ES",
    "sg:address":"Marques de Monteagudo,18",
    "sg:city":"Madrid",
    "sg:classifiers":[
        {
            "category":"Professional",
            "subcategory":"Computer Services",
            "type":"Services"
        }
    ],
    "sg:postcode":"28028",
    "sg:tags":[
        "internettv",
        "p2ptv",
        "cdn",
        "p2pcdn",
        "television",
        "tv",
        "hd",
        "fullhd"
    ],
    "sg:website":"http://www.pomeloTV.com",
    "wof:name":"pomeloTV",
    "wof:placetype":"venue"
},
  "geometry": {"coordinates":[-3.6685036,40.4367771],"type":"Point"}
}