{
  "type": "Feature",
  "properties": {
    "iso:country":"ES",
    "sg:address":"Rua Ourense, 14",
    "sg:city":"Lugo",
    "sg:orig_category":"Equipo De Refrigeraci\u00d3n Industrial",
    "sg:phone":"+34 982 24 41 09",
    "sg:postcode":"27004",
    "sg:province":"Lugo",
    "wof:name":"Lopez Real Faustino",
    "wof:placetype":"venue"
},
  "geometry": {"coordinates":[-7.5621261597,43.0131645203],"type":"Point"}
}