{
  "type": "Feature",
  "properties": {
    "addr:full":"Calle de Ramon Y Cajal (de), 9 San Fernando De Henares Madrid 28830",
    "addr:postcode":"28830",
    "addr:street":"Calle De Ramon Y Cajal De 9",
    "iso:country":"ES",
    "sg:address":"Calle de Ramon Y Cajal (de), 9",
    "sg:city":"San Fernando De Henares",
    "sg:orig_category":"Centros De Educaci\u00d3n Especial",
    "sg:phone":"+34 916 74 23 36",
    "sg:postcode":"28830",
    "sg:province":"Madrid",
    "wof:name":"Comunidad Autonoma De Madrid-centros De Educacion",
    "wof:placetype":"venue"
},
  "geometry": {"coordinates":[-3.5353240967,40.4263687134],"type":"Point"}
}