{
  "type": "Feature",
  "properties": {
    "addr:full":"Plaz Posito, 15 Huetor-tajar Granada 18360",
    "addr:housenumber":"15",
    "addr:postcode":"18360",
    "addr:street":"Plaz Posito",
    "iso:country":"ES",
    "sg:address":"Plaz Posito, 15",
    "sg:city":"Huetor-tajar",
    "sg:orig_category":"Ense\u00d1anza, Formaci\u00d3n Profesional: Aprendizaje",
    "sg:phone":"+34 958 33 50 04",
    "sg:postcode":"18360",
    "sg:province":"Granada",
    "wof:name":"Ayuntamiento De Huetor Tajar",
    "wof:placetype":"venue"
},
  "geometry": {"coordinates":[-4.046749115,37.1978111267],"type":"Point"}
}