{
  "type": "Feature",
  "properties": {
    "iso:country":"ES",
    "sg:address":"Carr Cales Fonts, 9",
    "sg:city":"Castell",
    "sg:orig_category":"Empresas De Carpinter\u00cda De Madera",
    "sg:phone":"+34 971 36 72 70",
    "sg:postcode":"07720",
    "sg:province":"Islas Baleares",
    "wof:name":"Fusteria Es Castell S.c.",
    "wof:placetype":"venue"
},
  "geometry": {"coordinates":[4.2858448029,39.879650116],"type":"Point"}
}