{
  "type": "Feature",
  "properties": {
    "iso:country":"ES",
    "sg:address":"Calle de Olaguibel, 54",
    "sg:city":"Vitoria-gasteiz",
    "sg:classifiers":[
        {
            "category":"Personal",
            "subcategory":"Barber",
            "type":"Services"
        }
    ],
    "sg:phone":"+34 945 25 27 95",
    "sg:postcode":"01003",
    "sg:province":"\u00c1lava",
    "sg:tags":[
        "caballeros",
        "de",
        "peluqueros"
    ],
    "wof:name":"Armas Vas Francisco Javier",
    "wof:placetype":"venue"
},
  "geometry": {"coordinates":[-2.664144516,42.8456077576],"type":"Point"}
}