{
  "type": "Feature",
  "properties": {
    "addr:full":"Calle de Rosario, 5 Valmojado Toledo 45940",
    "addr:housenumber":"5",
    "addr:postcode":"45940",
    "addr:street":"Calle De Rosario",
    "iso:country":"ES",
    "sg:address":"Calle de Rosario, 5",
    "sg:city":"Valmojado",
    "sg:orig_category":"Asilos De Ancianos. Centros Privados",
    "sg:phone":"+34 918 17 06 21",
    "sg:postcode":"45940",
    "sg:province":"Toledo",
    "wof:name":"Joparc 2000 S.l.",
    "wof:placetype":"venue"
},
  "geometry": {"coordinates":[-4.0846590996,40.2036514282],"type":"Point"}
}