{
  "type": "Feature",
  "properties": {
    "addr:full":"Calle de Real, 61 Rozas De Madrid Madrid 28230",
    "addr:housenumber":"61",
    "addr:postcode":"28230",
    "addr:street":"Calle De Real",
    "iso:country":"ES",
    "sg:address":"Calle de Real, 61",
    "sg:city":"Rozas De Madrid",
    "sg:orig_category":"Carnicer\u00cdas, Carnicer\u00cdas",
    "sg:phone":"+34 916 37 37 85",
    "sg:postcode":"28230",
    "sg:province":"Madrid",
    "wof:name":"Alonso Luengo S.a.",
    "wof:placetype":"venue"
},
  "geometry": {"coordinates":[-4.4653596878,40.262424469],"type":"Point"}
}