{
  "type": "Feature",
  "properties": {
    "iso:country":"ES",
    "sg:address":"Avda Estacion, S/n",
    "sg:city":"Orihuela",
    "sg:orig_category":"Autob\u00das (explotaci\u00d3n Y Servicios De)",
    "sg:phone":"+34 965 30 15 67",
    "sg:postcode":"03300",
    "sg:province":"Alicante",
    "sg:website":"www.costazul.net",
    "wof:name":"Autocares Costa Azul S. A.",
    "wof:placetype":"venue"
},
  "geometry": {"coordinates":[-0.9448090196,38.0780715942],"type":"Point"}
}