{
  "type": "Feature",
  "properties": {
    "addr:full":"Calle de Morote, 20 Huescar Granada 18830",
    "addr:housenumber":"20",
    "addr:postcode":"18830",
    "addr:street":"Calle De Morote",
    "iso:country":"ES",
    "sg:address":"Calle de Morote, 20",
    "sg:city":"Huescar",
    "sg:orig_category":"Inmobiliaria (agencias)",
    "sg:phone":"+34 958 74 12 72",
    "sg:postcode":"18830",
    "sg:province":"Granada",
    "sg:website":"www.rjgestion.com",
    "wof:name":"Rodriguez Gallego Miguel Angel",
    "wof:placetype":"venue"
},
  "geometry": {"coordinates":[-2.5419199467,37.8090057373],"type":"Point"}
}