{
  "type": "Feature",
  "properties": {
    "addr:full":"Avda Navarra, 17 Utebo Zaragoza 50180",
    "addr:housenumber":"17",
    "addr:postcode":"50180",
    "addr:street":"Avda Navarra",
    "iso:country":"ES",
    "sg:address":"Avda Navarra, 17",
    "sg:city":"Utebo",
    "sg:orig_category":"Farmacias",
    "sg:phone":"+34 976 77 48 15",
    "sg:postcode":"50180",
    "sg:province":"Zaragoza",
    "wof:name":"Asensi Serrano Manuel",
    "wof:placetype":"venue"
},
  "geometry": {"coordinates":[-1.0012761354,41.7079467773],"type":"Point"}
}