{
  "type": "Feature",
  "properties": {
    "iso:country":"ES",
    "sg:address":"Pase Carmen (del), 14",
    "sg:city":"Daimiel",
    "sg:orig_category":"Asilos De Ancianos. Centros Privados",
    "sg:phone":"+34 926 85 01 60",
    "sg:postcode":"13250",
    "sg:province":"Ciudad Real",
    "wof:name":"Hermanas De Los Ancianos Desamparados",
    "wof:placetype":"venue"
},
  "geometry": {"coordinates":[-3.617358923,39.0695037842],"type":"Point"}
}