{
  "type": "Feature",
  "properties": {
    "iso:country":"ES",
    "sg:address":"Calle de Ganado, 31",
    "sg:city":"Puerto De Santa Maria",
    "sg:orig_category":"Casquer\u00cda (al Por Menor)",
    "sg:phone":"+34 956 87 21 46",
    "sg:postcode":"11500",
    "sg:province":"C\u00e1diz",
    "wof:name":"Salguero Dazar Rosario",
    "wof:placetype":"venue"
},
  "geometry": {"coordinates":[-6.2265739441,36.6005859375],"type":"Point"}
}