{
  "type": "Feature",
  "properties": {
    "addr:full":"Avda Andalucia De, 13 Lepe Huelva 21440",
    "addr:housenumber":"13",
    "addr:postcode":"21440",
    "addr:street":"Avda Andalucia De",
    "iso:country":"ES",
    "sg:address":"Avda Andalucia De, 13",
    "sg:city":"Lepe",
    "sg:orig_category":"Abogados",
    "sg:phone":"+34 959 64 52 24",
    "sg:postcode":"21440",
    "sg:province":"Huelva",
    "wof:name":"Promociones Durosur Andalucia S.l.",
    "wof:placetype":"venue"
},
  "geometry": {"coordinates":[-7.1999511719,37.2502479553],"type":"Point"}
}