{
  "type": "Feature",
  "properties": {
    "addr:full":"Calle de Real, 67 Valgoma Le\u00f3n 24410",
    "addr:housenumber":"67",
    "addr:postcode":"24410",
    "addr:street":"Calle De Real;Leo\u0301N",
    "iso:country":"ES",
    "sg:address":"Calle de Real, 67",
    "sg:city":"Valgoma",
    "sg:orig_category":"Venta, Alquiler De Toldos",
    "sg:phone":"+34 987 45 57 42",
    "sg:postcode":"24410",
    "sg:province":"Le\u00f3n",
    "wof:name":"Quiros Mora Encarnacion",
    "wof:placetype":"venue"
},
  "geometry": {"coordinates":[-6.6668291092,42.5912513733],"type":"Point"}
}