{
  "type": "Feature",
  "properties": {
    "iso:country":"ES",
    "sg:address":"Av Santa Ana, S/n",
    "sg:city":"Torrellano",
    "sg:orig_category":"Artes Gr\u00c1ficas, Artes Pl\u00c1sticas (curso)",
    "sg:phone":"+34 965 68 00 87",
    "sg:postcode":"03320",
    "sg:province":"Alicante",
    "wof:name":"Forelx S.l.",
    "wof:placetype":"venue"
},
  "geometry": {"coordinates":[-0.5883839726,38.2929649353],"type":"Point"}
}