{
  "type": "Feature",
  "properties": {
    "addr:full":"C/ Ramon Sambola, 4 Salt Girona 17190",
    "addr:housenumber":"4",
    "addr:postcode":"17190",
    "addr:street":"C / Ramon Sambola",
    "iso:country":"ES",
    "sg:address":"C/ Ramon Sambola, 4",
    "sg:city":"Salt",
    "sg:orig_category":"Molduras, Junquillos, Listones Y Molduras Perforadas",
    "sg:phone":"+34 972 23 30 29",
    "sg:postcode":"17190",
    "sg:province":"Girona",
    "wof:name":"Pe\u00f1a Lopez Jose",
    "wof:placetype":"venue"
},
  "geometry": {"coordinates":[2.7903540134,41.9738731384],"type":"Point"}
}