{
  "type": "Feature",
  "properties": {
    "iso:country":"ES",
    "sg:address":"Aptos. Torreon, S/n",
    "sg:city":"Benicassim",
    "sg:orig_category":"Reposter\u00cdas",
    "sg:phone":"+34 964 30 59 56",
    "sg:postcode":"12560",
    "sg:province":"Castell\u00f3n",
    "wof:name":"Valls Miralles S.l.",
    "wof:placetype":"venue"
},
  "geometry": {"coordinates":[0.0457400009,40.0510292053],"type":"Point"}
}