{
  "type": "Feature",
  "properties": {
    "iso:country":"ES",
    "sg:address":"Barr Gaztelua, S/n",
    "sg:city":"Gastelua",
    "sg:orig_category":"Carnicer\u00cdas, Carnicer\u00cdas",
    "sg:phone":"+34 946 81 39 88",
    "sg:postcode":"48220",
    "sg:province":"Vizcaya",
    "wof:name":"Echeverria Zudaire Carlos",
    "wof:placetype":"venue"
},
  "geometry": {"coordinates":[-2.6079039574,43.1692581177],"type":"Point"}
}