{
  "type": "Feature",
  "properties": {
    "addr:full":"Calle de General Ricardos, 65 Madrid Madrid 28019",
    "addr:housenumber":"65",
    "addr:postcode":"madrid;28019",
    "addr:street":"Calle De General Ricardos",
    "iso:country":"ES",
    "sg:address":"Calle de General Ricardos, 65",
    "sg:city":"Madrid",
    "sg:orig_category":"Ropa Para Ni\u00d1os (al Por Menor)",
    "sg:phone":"+34 914 71 47 05",
    "sg:postcode":"28019",
    "sg:province":"Madrid",
    "wof:name":"Lopez Ceca Sacramento",
    "wof:placetype":"venue"
},
  "geometry": {"coordinates":[-3.7218949795,40.3942489624],"type":"Point"}
}