{
  "type": "Feature",
  "properties": {
    "iso:country":"ES",
    "sg:address":"Calle de Arteagabeitia, 12",
    "sg:city":"San Vicente De Barakaldo",
    "sg:classifiers":[
        {
            "category":"Autos & Motor Vehicles",
            "subcategory":"Automobile Sales",
            "type":"Retail Goods"
        }
    ],
    "sg:phone":"+34 944 99 05 76",
    "sg:postcode":"48902",
    "sg:province":"Vizcaya",
    "wof:name":"Autoescuela San Jose S. L.",
    "wof:placetype":"venue"
},
  "geometry": {"coordinates":[-2.9929449558,43.2920646667],"type":"Point"}
}