{
  "type": "Feature",
  "properties": {
    "iso:country":"ES",
    "sg:address":"Calle de Gallego El, 6",
    "sg:city":"Cangas Narcea",
    "sg:orig_category":"Pr\u00c9stamos Personales E Hipotecarios",
    "sg:phone":"+34 985 81 02 05",
    "sg:postcode":"33800",
    "sg:province":"Asturias",
    "wof:name":"Blanco Fuello Ignacio",
    "wof:placetype":"venue"
},
  "geometry": {"coordinates":[-6.5502290726,43.1801643372],"type":"Point"}
}