{
  "type": "Feature",
  "properties": {
    "iso:country":"ES",
    "sg:address":"Calle de Juan Xxiii, 11",
    "sg:city":"Aviles",
    "sg:orig_category":"Peluquer\u00cdas, Peluquer\u00cda Mixta",
    "sg:phone":"+34 985 56 31 77",
    "sg:postcode":"33401",
    "sg:province":"Asturias",
    "wof:name":"Fernandez Vazquez Nieves",
    "wof:placetype":"venue"
},
  "geometry": {"coordinates":[-5.9311690331,43.5558853149],"type":"Point"}
}