{
  "type": "Feature",
  "properties": {
    "addr:full":"Calle de Fuente La Higuera, 19 Valencia Valencia 46006",
    "addr:housenumber":"19",
    "addr:postcode":"46006",
    "addr:street":"Calle De Fuente La Higuera",
    "iso:country":"ES",
    "sg:address":"Calle de Fuente La Higuera, 19",
    "sg:city":"Valencia",
    "sg:orig_category":"Mec\u00c1nico Del Autom\u00d3vil",
    "sg:phone":"+34 963 74 09 05",
    "sg:postcode":"46006",
    "sg:province":"Valencia",
    "wof:name":"Hortelano Campillo Ramon",
    "wof:placetype":"venue"
},
  "geometry": {"coordinates":[-0.3727520108,39.456615448],"type":"Point"}
}