{
  "type": "Feature",
  "properties": {
    "addr:full":"C/ Melians, Des, 2 Alaior Islas Baleares 07730",
    "addr:postcode":"07730",
    "addr:street":"C / Melians",
    "iso:country":"ES",
    "sg:address":"C/ Melians, Des, 2",
    "sg:city":"Alaior",
    "sg:orig_category":"Promotores Constructores",
    "sg:phone":"+34 971 37 24 06",
    "sg:postcode":"07730",
    "sg:province":"Islas Baleares",
    "wof:name":"Obras Calan Busquets S.l.",
    "wof:placetype":"venue"
},
  "geometry": {"coordinates":[4.1405291557,39.9326591492],"type":"Point"}
}