{
  "type": "Feature",
  "properties": {
    "addr:full":"Av Severo Ochoa, 120 Hospitalet Llobregat Barcelona 08906",
    "addr:housenumber":"120",
    "addr:postcode":"08906",
    "addr:street":"Av Severo Ochoa",
    "iso:country":"ES",
    "sg:address":"Av Severo Ochoa, 120",
    "sg:city":"Hospitalet Llobregat",
    "sg:orig_category":"Molduras, Junquillos, Listones Y Molduras Perforadas",
    "sg:phone":"+34 934 37 45 95",
    "sg:postcode":"08906",
    "sg:province":"Barcelona",
    "wof:name":"Rodriguez Diaz Jorge Luis",
    "wof:placetype":"venue"
},
  "geometry": {"coordinates":[2.1035740376,41.3707542419],"type":"Point"}
}