{
  "type": "Feature",
  "properties": {
    "addr:full":"Avda Lerida (de), 4 Monzon Huesca 22400",
    "addr:housenumber":"4",
    "addr:postcode":"22400",
    "addr:street":"Avda Lerida De",
    "iso:country":"ES",
    "sg:address":"Avda Lerida (de), 4",
    "sg:city":"Monzon",
    "sg:orig_category":"Electrodom\u00c9sticos (al Por Menor)",
    "sg:phone":"+34 974 40 22 52",
    "sg:postcode":"22400",
    "sg:province":"Huesca",
    "wof:name":"Master Monzon S.l.",
    "wof:placetype":"venue"
},
  "geometry": {"coordinates":[0.2004899979,41.9062805176],"type":"Point"}
}