{
  "type": "Feature",
  "properties": {
    "addr:full":"Calle de Chaves Nogales, S/n Sevilla Sevilla 41018",
    "addr:housenumber":"/ n",
    "addr:postcode":"41018",
    "addr:street":"Calle De Chaves Nogales S",
    "iso:country":"ES",
    "sg:address":"Calle de Chaves Nogales, S/n",
    "sg:city":"Sevilla",
    "sg:orig_category":"Asociaciones Y Clubs Deportivos",
    "sg:phone":"+34 954 53 60 57",
    "sg:postcode":"41018",
    "sg:province":"Sevilla",
    "sg:website":"www.22.brinkster.com/kyohan",
    "wof:name":"Asociacion Cultural Sevilla Japon",
    "wof:placetype":"venue"
},
  "geometry": {"coordinates":[-5.9800944328,37.3850860596],"type":"Point"}
}