{
  "type": "Feature",
  "properties": {
    "iso:country":"ES",
    "sg:address":"Calle de Batalla De Villaviciosa, 9",
    "sg:city":"Guadalajara",
    "sg:orig_category":"Fabricaci\u00d3n De Distribuidores Autom\u00c1ticos",
    "sg:phone":"+34 949 20 37 62",
    "sg:postcode":"19004",
    "sg:province":"Guadalajara",
    "wof:name":"Aguas De Guadalajara S.l.u.",
    "wof:placetype":"venue"
},
  "geometry": {"coordinates":[-3.1851878166,40.6312446594],"type":"Point"}
}