{
  "type": "Feature",
  "properties": {
    "addr:full":"Calle de Serrano, 112 Madrid Madrid 28006",
    "addr:housenumber":"112",
    "addr:postcode":"28006",
    "addr:street":"Calle De Serrano",
    "iso:country":"ES",
    "sg:address":"Calle de Serrano, 112",
    "sg:city":"Madrid",
    "sg:orig_category":"Fotocopias, Reprograf\u00cda",
    "sg:phone":"+34 915 61 41 97",
    "sg:postcode":"28006",
    "sg:province":"Madrid",
    "wof:name":"Telecomunicaciones Internacionales S.a.",
    "wof:placetype":"venue"
},
  "geometry": {"coordinates":[-3.6862819195,40.4357948303],"type":"Point"}
}