{
  "type": "Feature",
  "properties": {
    "iso:country":"ES",
    "sg:address":"Avda Rosalia De Castro, 208",
    "sg:city":"Carril",
    "sg:orig_category":"Asociaciones, Organismos Culturales Y Socioeducativos",
    "sg:phone":"+34 986 50 11 91",
    "sg:postcode":"36610",
    "sg:province":"Pontevedra",
    "wof:name":"Circulo Artistico Deportivo",
    "wof:placetype":"venue"
},
  "geometry": {"coordinates":[-8.7752389908,42.6149482727],"type":"Point"}
}