{
  "type": "Feature",
  "properties": {
    "addr:full":"P. Matadero, S/n Malaga M\u00e1laga 29002",
    "addr:housenumber":"/ n",
    "addr:postcode":"29002",
    "addr:street":"P.;S;Ma\u0301Laga",
    "iso:country":"ES",
    "sg:address":"P. Matadero, S/n",
    "sg:city":"Malaga",
    "sg:orig_category":"Ense\u00d1anza, Formaci\u00d3n Profesional: Aprendizaje",
    "sg:phone":"+34 952 35 93 61",
    "sg:postcode":"29002",
    "sg:province":"M\u00e1laga",
    "wof:name":"Instituto Social De La Marina",
    "wof:placetype":"venue"
},
  "geometry": {"coordinates":[-4.426363945,36.7149658203],"type":"Point"}
}