{
  "type": "Feature",
  "properties": {
    "addr:full":"Avda Europa, 7 Pozuelo De Alarcon Madrid 28224",
    "addr:housenumber":"7",
    "addr:postcode":"28224",
    "addr:street":"Avda Europa",
    "iso:country":"ES",
    "sg:address":"Avda Europa, 7",
    "sg:city":"Pozuelo De Alarcon",
    "sg:orig_category":"Audiovisuales (producci\u00d3n, Edici\u00d3n, Realizaci\u00d3n)",
    "sg:phone":"+34 917 15 82 84",
    "sg:postcode":"28224",
    "sg:province":"Madrid",
    "wof:name":"Quimera Digital S.l.",
    "wof:placetype":"venue"
},
  "geometry": {"coordinates":[-3.7968349457,40.4367675781],"type":"Point"}
}