{
  "type": "Feature",
  "properties": {
    "addr:full":"Avda Madrid, 32 Vigo Pontevedra 36204",
    "addr:housenumber":"32",
    "addr:postcode":"36204",
    "addr:street":"Avda Madrid",
    "iso:country":"ES",
    "sg:address":"Avda Madrid, 32",
    "sg:city":"Vigo",
    "sg:orig_category":"Cl\u00cdnicas Dentales",
    "sg:phone":"+34 986 42 22 34",
    "sg:postcode":"36204",
    "sg:province":"Pontevedra",
    "wof:name":"Fernandez Vazquez Maria Del Carmen",
    "wof:placetype":"venue"
},
  "geometry": {"coordinates":[-8.7151298523,42.2260856628],"type":"Point"}
}