{
  "type": "Feature",
  "properties": {
    "iso:country":"ES",
    "sg:address":"Calle de San Vicente Martir, 98",
    "sg:city":"Valencia",
    "sg:orig_category":"Ropa Para Se\u00d1oras (al Por Menor)",
    "sg:phone":"+34 963 52 07 56",
    "sg:postcode":"46007",
    "sg:province":"Valencia",
    "wof:name":"Gomez Soriano Joaquin",
    "wof:placetype":"venue"
},
  "geometry": {"coordinates":[-0.3804529905,39.467590332],"type":"Point"}
}