{
  "type": "Feature",
  "properties": {
    "iso:country":"ES",
    "sg:address":"Avda Portugal, 41",
    "sg:city":"Ciudad Rodrigo",
    "sg:orig_category":"Agentes, Concesionarios Y Sucursales De Veh\u00cdculos",
    "sg:phone":"+34 923 46 11 06",
    "sg:postcode":"37500",
    "sg:province":"Salamanca",
    "wof:name":"Mompeauto S.l.",
    "wof:placetype":"venue"
},
  "geometry": {"coordinates":[-6.5350680351,40.6015968323],"type":"Point"}
}