{
  "type": "Feature",
  "properties": {
    "addr:full":"Besos, 12 Bisbal Del Penedes Tarragona 43717",
    "addr:housenumber":"12",
    "addr:postcode":"43717",
    "addr:street":"Besos",
    "iso:country":"ES",
    "sg:address":"Besos, 12",
    "sg:city":"Bisbal Del Penedes",
    "sg:orig_category":"Bazares, Art\u00cdculos De Limpieza Y De Cocina (al Por Menor)",
    "sg:phone":"+34 977 68 89 42",
    "sg:postcode":"43717",
    "sg:province":"Tarragona",
    "wof:name":"Mariescanes S.l.",
    "wof:placetype":"venue"
},
  "geometry": {"coordinates":[1.4905450344,41.2773857117],"type":"Point"}
}