{
  "type": "Feature",
  "properties": {
    "iso:country":"ES",
    "sg:address":"Plaz Catedral (la), 2",
    "sg:city":"Albacete",
    "sg:orig_category":"Hormig\u00d3n Para Construcci\u00d3n",
    "sg:phone":"+34 967 21 27 80",
    "sg:postcode":"02001",
    "sg:province":"Albacete",
    "wof:name":"Forjados Albacete S.l.",
    "wof:placetype":"venue"
},
  "geometry": {"coordinates":[-1.8540610075,38.9950675964],"type":"Point"}
}