{
  "type": "Feature",
  "properties": {
    "iso:country":"ES",
    "sg:address":"Plaz Mayor, S/n",
    "sg:city":"Horche",
    "sg:orig_category":"Relojer\u00cda (al Por Menor, Reparaci\u00d3n)",
    "sg:phone":"+34 949 29 01 60",
    "sg:postcode":"19140",
    "sg:province":"Guadalajara",
    "wof:name":"Ruiz Fernandez Jesus",
    "wof:placetype":"venue"
},
  "geometry": {"coordinates":[-3.0633189678,40.565448761],"type":"Point"}
}