{
  "type": "Feature",
  "properties": {
    "iso:country":"ES",
    "sg:address":"Rua Manuel Alvarez, 101",
    "sg:city":"Bouci\u00d1a",
    "sg:orig_category":"Venta, Montaje De Neum\u00c1ticos",
    "sg:phone":"+34 986 37 60 56",
    "sg:postcode":"36215",
    "sg:province":"Pontevedra",
    "wof:name":"Villar Vaquero Maria Irma",
    "wof:placetype":"venue"
},
  "geometry": {"coordinates":[-8.663274765,42.2263412476],"type":"Point"}
}