{
  "type": "Feature",
  "properties": {
    "iso:country":"ES",
    "sg:address":"Av Santa Coloma, 21",
    "sg:city":"Santa Coloma De Gramenet",
    "sg:orig_category":"Producci\u00d3n, Distribuci\u00d3n De Electricidad",
    "sg:phone":"+34 933 86 77 98",
    "sg:postcode":"08922",
    "sg:province":"Barcelona",
    "wof:name":"Viana Lopez Pedro",
    "wof:placetype":"venue"
},
  "geometry": {"coordinates":[2.2076370716,41.4493751526],"type":"Point"}
}