{
  "type": "Feature",
  "properties": {
    "iso:country":"ES",
    "sg:address":"Calle de Casas De Galiana, S/n",
    "sg:city":"Hondon De Los Frailes",
    "sg:orig_category":"Distribuci\u00d3n De Petr\u00d3leo Y Derivados",
    "sg:phone":"+34 965 48 21 10",
    "sg:postcode":"03689",
    "sg:province":"Alicante",
    "wof:name":"Estacion De Servicio Santacruz S.a.",
    "wof:placetype":"venue"
},
  "geometry": {"coordinates":[-0.9251589775,38.273853302],"type":"Point"}
}