{
  "type": "Feature",
  "properties": {
    "iso:country":"ES",
    "sg:address":"Calle de Camino De Los Vinateros, S/n",
    "sg:city":"Madrid",
    "sg:orig_category":"\u00d3ptica: Instrumentos (fabricaci\u00d3n)",
    "sg:phone":"+34 914 37 61 55",
    "sg:postcode":"28030",
    "sg:province":"Madrid",
    "wof:name":"Irimaro Opticos S.l",
    "wof:placetype":"venue"
},
  "geometry": {"coordinates":[-3.6395142078,40.4072608948],"type":"Point"}
}