{
  "type": "Feature",
  "properties": {
    "addr:full":"Cmno San Sebastian (de), 3 Boadilla Del Monte Madrid 28660",
    "addr:housenumber":"3",
    "addr:postcode":"28660",
    "addr:street":"Cmno San Sebastian De",
    "iso:country":"ES",
    "sg:address":"Cmno San Sebastian (de), 3",
    "sg:city":"Boadilla Del Monte",
    "sg:orig_category":"Fabricaci\u00d3n, Importaci\u00d3n De Material Y Sistemas De Telecomunicaciones",
    "sg:phone":"+34 916 32 35 76",
    "sg:postcode":"28660",
    "sg:province":"Madrid",
    "wof:name":"Comercial Y Consulting Dafcom S.l.",
    "wof:placetype":"venue"
},
  "geometry": {"coordinates":[-3.8773350716,40.4057693481],"type":"Point"}
}