{
  "type": "Feature",
  "properties": {
    "iso:country":"ES",
    "sg:address":"Calle de Concepcion Arenal, 7",
    "sg:city":"Aviles",
    "sg:orig_category":"Pr\u00c9stamos Personales E Hipotecarios",
    "sg:phone":"+34 985 56 32 37",
    "sg:postcode":"33401",
    "sg:province":"Asturias",
    "wof:name":"Registro De La Propiedad Num 1",
    "wof:placetype":"venue"
},
  "geometry": {"coordinates":[-5.9237551689,43.5616874695],"type":"Point"}
}