{
  "type": "Feature",
  "properties": {
    "iso:country":"ES",
    "sg:address":"Calle de Antonio Maura, 55",
    "sg:city":"Cordoba",
    "sg:orig_category":"Fabricaci\u00d3n, Venta De Cuadros, Accesorios Para Enmarcar",
    "sg:phone":"+34 957 23 30 11",
    "sg:postcode":"14005",
    "sg:province":"C\u00f3rdoba",
    "wof:name":"Ba\u00f1o Canales Monica",
    "wof:placetype":"venue"
},
  "geometry": {"coordinates":[-4.7917628288,37.8813171387],"type":"Point"}
}