{
  "type": "Feature",
  "properties": {
    "addr:full":"Av Vila Joiosa, 2 Benidorm Alicante 03500",
    "addr:housenumber":"2",
    "addr:postcode":"03500",
    "addr:street":"Av Vila Joiosa",
    "iso:country":"ES",
    "sg:address":"Av Vila Joiosa, 2",
    "sg:city":"Benidorm",
    "sg:orig_category":"Tiendas De Grano, Frutas Y Legumbres Secas (al Por Menor)",
    "sg:phone":"+34 966 80 34 73",
    "sg:postcode":"03500",
    "sg:province":"Alicante",
    "wof:name":"Peiro Frasquet Maria Del Carmen",
    "wof:placetype":"venue"
},
  "geometry": {"coordinates":[-0.1512590051,38.5361862183],"type":"Point"}
}