{
  "type": "Feature",
  "properties": {
    "addr:full":"Plaz Agua Limpia, 5 Segorbe Castell\u00f3n 12400",
    "addr:housenumber":"5",
    "addr:postcode":"12400",
    "addr:street":"Limpia",
    "iso:country":"ES",
    "sg:address":"Plaz Agua Limpia, 5",
    "sg:city":"Segorbe",
    "sg:classifiers":[
        {
            "category":"Personal",
            "subcategory":"Barber",
            "type":"Services"
        }
    ],
    "sg:phone":"+34 964 71 09 62",
    "sg:postcode":"12400",
    "sg:province":"Castell\u00f3n",
    "sg:tags":[
        "caballeros",
        "de",
        "peluqueros"
    ],
    "wof:name":"Clemente Gonzalvo Manuel",
    "wof:placetype":"venue"
},
  "geometry": {"coordinates":[-0.4885739982,39.8518714905],"type":"Point"}
}