{
  "type": "Feature",
  "properties": {
    "iso:country":"ES",
    "sg:address":"Calle de Jornaleros, 3",
    "sg:city":"Sevilla",
    "sg:orig_category":"Agencias Y Agentes Comerciales, Representantes",
    "sg:phone":"+34 954 94 30 16",
    "sg:postcode":"41008",
    "sg:province":"Sevilla",
    "wof:name":"Bauzada Galafate Concepcion",
    "wof:placetype":"venue"
},
  "geometry": {"coordinates":[-5.963203907,37.4211235046],"type":"Point"}
}