{
  "type": "Feature",
  "properties": {
    "iso:country":"ES",
    "sg:address":"Pla\u00c7 Soler I Carbonell, 18",
    "sg:city":"Vilanova I La Geltru",
    "sg:orig_category":"\u00d3ptica: Instrumentos (fabricaci\u00d3n)",
    "sg:phone":"+34 938 93 62 13",
    "sg:postcode":"08800",
    "sg:province":"Barcelona",
    "wof:name":"Centro Optico Vilanova S. A.",
    "wof:placetype":"venue"
},
  "geometry": {"coordinates":[1.7247999907,41.2228240967],"type":"Point"}
}