{
  "type": "Feature",
  "properties": {
    "addr:full":"Rua Leiteiras (das), 1 Lugo Lugo 27003",
    "addr:housenumber":"1",
    "addr:postcode":"27003",
    "addr:street":"Rua Leiteiras Das",
    "iso:country":"ES",
    "sg:address":"Rua Leiteiras (das), 1",
    "sg:city":"Lugo",
    "sg:orig_category":"Contenedores (mercanc\u00cdas)",
    "sg:phone":"+34 982 30 30 00",
    "sg:postcode":"27003",
    "sg:province":"Lugo",
    "wof:name":"Transportes Azkar S.a.",
    "wof:placetype":"venue"
},
  "geometry": {"coordinates":[-7.5637841225,43.0511207581],"type":"Point"}
}