{
  "type": "Feature",
  "properties": {
    "addr:full":"Calle de Pellejero Villoria, 20 Salamanca Salamanca 37004",
    "addr:housenumber":"20",
    "addr:postcode":"37004",
    "addr:street":"Calle De Pellejero Villoria",
    "iso:country":"ES",
    "sg:address":"Calle de Pellejero Villoria, 20",
    "sg:city":"Salamanca",
    "sg:orig_category":"Ense\u00d1anza: Idiomas",
    "sg:phone":"+34 923 12 03 77",
    "sg:postcode":"37004",
    "sg:province":"Salamanca",
    "sg:website":"www.ef.com",
    "wof:name":"E.f. Colegios Europeos De Verano S.a.",
    "wof:placetype":"venue"
},
  "geometry": {"coordinates":[-5.6536021233,40.9746704102],"type":"Point"}
}