{
  "type": "Feature",
  "properties": {
    "iso:country":"ES",
    "sg:address":"Calle de Ardigales, 17",
    "sg:city":"Castro Urdiales",
    "sg:orig_category":"Agencias De Viajes",
    "sg:phone":"+34 942 86 91 23",
    "sg:postcode":"39700",
    "sg:province":"Cantabria",
    "sg:website":"www.barceloviajes.com",
    "wof:name":"Hermanos Marin S.c.",
    "wof:placetype":"venue"
},
  "geometry": {"coordinates":[-3.2188034058,43.3819923401],"type":"Point"}
}