{
  "type": "Feature",
  "properties": {
    "addr:full":"Calle de Juan Ramon Jimenez, 6 Palencia Palencia 34001",
    "addr:housenumber":"6",
    "addr:postcode":"34001",
    "addr:street":"Calle De Juan Ramon Jimenez",
    "iso:country":"ES",
    "sg:address":"Calle de Juan Ramon Jimenez, 6",
    "sg:city":"Palencia",
    "sg:orig_category":"Abogados",
    "sg:phone":"+34 979 75 02 26",
    "sg:postcode":"34001",
    "sg:province":"Palencia",
    "wof:name":"Fraile Martin Mercedes",
    "wof:placetype":"venue"
},
  "geometry": {"coordinates":[-4.5291609764,42.0113372803],"type":"Point"}
}