{
  "type": "Feature",
  "properties": {
    "addr:full":"Plaz Marina (de La), 7 Colmenar Viejo Madrid 28770",
    "addr:postcode":"28770",
    "iso:country":"ES",
    "sg:address":"Plaz Marina (de La), 7",
    "sg:city":"Colmenar Viejo",
    "sg:orig_category":"Librer\u00cdas",
    "sg:phone":"+34 918 45 33 47",
    "sg:postcode":"28770",
    "sg:province":"Madrid",
    "wof:name":"Diaz Villar Dionisio",
    "wof:placetype":"venue"
},
  "geometry": {"coordinates":[-3.7688889503,40.6596717834],"type":"Point"}
}