{
  "type": "Feature",
  "properties": {
    "iso:country":"ES",
    "sg:address":"Calle de Lealtad, 3",
    "sg:city":"Santander",
    "sg:orig_category":"M\u00c9dicos: Oftalmolog\u00cda",
    "sg:phone":"+34 942 36 56 46",
    "sg:postcode":"39002",
    "sg:province":"Cantabria",
    "wof:name":"Corihuela Hernandez Jose Carlos",
    "wof:placetype":"venue"
},
  "geometry": {"coordinates":[-3.8082180023,43.46251297],"type":"Point"}
}