{
  "type": "Feature",
  "properties": {
    "addr:full":"Plaz Estacion, 5 Eliana Valencia 46183",
    "addr:housenumber":"5",
    "addr:postcode":"46183",
    "addr:street":"Estacion",
    "iso:country":"ES",
    "sg:address":"Plaz Estacion, 5",
    "sg:city":"Eliana",
    "sg:orig_category":"Promotores Constructores",
    "sg:phone":"+34 962 75 08 44",
    "sg:postcode":"46183",
    "sg:province":"Valencia",
    "sg:website":"www.pycvalencianas.com",
    "wof:name":"Proyectos Y Contratas Valencianas S.l.",
    "wof:placetype":"venue"
},
  "geometry": {"coordinates":[-0.528208971,39.5667457581],"type":"Point"}
}