{
  "type": "Feature",
  "properties": {
    "addr:full":"Avda Jose Antonio, 22 Plasencia C\u00e1ceres 10600",
    "addr:housenumber":"22",
    "addr:postcode":"10600",
    "addr:street":"Avda Jose Antonio;Ca\u0301Ceres",
    "iso:country":"ES",
    "sg:address":"Avda Jose Antonio, 22",
    "sg:city":"Plasencia",
    "sg:orig_category":"M\u00c9dicos: Pediatr\u00cda. Enfermedades De Los Ni\u00d1os",
    "sg:phone":"+34 927 41 37 09",
    "sg:postcode":"10600",
    "sg:province":"C\u00e1ceres",
    "wof:name":"Garcia Gomez Rosa",
    "wof:placetype":"venue"
},
  "geometry": {"coordinates":[-6.0850133896,40.0324058533],"type":"Point"}
}