{
  "type": "Feature",
  "properties": {
    "iso:country":"ES",
    "sg:address":"Carr Mariano Benlliure, 6",
    "sg:city":"Moncada",
    "sg:orig_category":"Dise\u00d1o Industrial",
    "sg:phone":"+34 961 30 07 82",
    "sg:postcode":"46113",
    "sg:province":"Valencia",
    "wof:name":"Boix Leon Luis Vicente",
    "wof:placetype":"venue"
},
  "geometry": {"coordinates":[-0.3891040087,39.5433807373],"type":"Point"}
}