{
  "type": "Feature",
  "properties": {
    "iso:country":"ES",
    "sg:address":"Carrer de Cervol, 7",
    "sg:city":"Can Guitart Vell",
    "sg:orig_category":"Empresas De Vigilancia, Guardia Y Protecci\u00d3n",
    "sg:phone":"+34 936 84 01 37",
    "sg:postcode":"08758",
    "sg:province":"Barcelona",
    "wof:name":"Systemas De Verificacion De Imagenes S.l",
    "wof:placetype":"venue"
},
  "geometry": {"coordinates":[1.972350955,41.396068573],"type":"Point"}
}