{
  "type": "Feature",
  "properties": {
    "iso:country":"ES",
    "sg:address":"Calle de Jose De Madinabeitia Kalea, 11",
    "sg:city":"Amurrio",
    "sg:orig_category":"Promotores Constructores",
    "sg:phone":"+34 945 89 20 19",
    "sg:postcode":"01470",
    "sg:province":"\u00c1lava",
    "wof:name":"Basarte Construcciones Y Excavaciones, S.l.",
    "wof:placetype":"venue"
},
  "geometry": {"coordinates":[-3.002311945,43.0532722473],"type":"Point"}
}