{
  "type": "Feature",
  "properties": {
    "addr:full":"Calle de Magan, 11 Caba\u00e7as De La Sagra Toledo 45592",
    "addr:housenumber":"11",
    "addr:postcode":"45592",
    "addr:street":"Calle De Magan",
    "iso:country":"ES",
    "sg:address":"Calle de Magan, 11",
    "sg:city":"Caba\u00e7as De La Sagra",
    "sg:orig_category":"Cajas Para Embalar",
    "sg:phone":"+34 925 35 53 76",
    "sg:postcode":"45592",
    "sg:province":"Toledo",
    "wof:name":"Caja Rural Provincial De Toledo",
    "wof:placetype":"venue"
},
  "geometry": {"coordinates":[-3.9468019009,40.0054206848],"type":"Point"}
}