{
  "type": "Feature",
  "properties": {
    "addr:full":"Ctra Borriol O Morella, 4 Castellon De La Plana Castell\u00f3n 12004",
    "addr:housenumber":"4",
    "addr:postcode":"12004",
    "addr:street":"Ctra Borriol O Morella",
    "iso:country":"ES",
    "sg:address":"Ctra Borriol O Morella, 4",
    "sg:city":"Castellon De La Plana",
    "sg:orig_category":"Suministros Para Carrocer\u00cdas",
    "sg:phone":"+34 964 20 61 60",
    "sg:postcode":"12004",
    "sg:province":"Castell\u00f3n",
    "wof:name":"J.puchol S.l.",
    "wof:placetype":"venue"
},
  "geometry": {"coordinates":[0.0330299996,40.0113639832],"type":"Point"}
}