{
  "type": "Feature",
  "properties": {
    "iso:country":"ES",
    "sg:address":"Calle de Manuel Franco Cubeiro, 6",
    "sg:city":"Torremolinos",
    "sg:orig_category":"Centros Empresariales",
    "sg:phone":"+34 952 05 13 78",
    "sg:postcode":"29620",
    "sg:province":"M\u00e1laga",
    "wof:name":"Sistemas Tecnicos Integrales De Maquinas Para Maderas S.l.",
    "wof:placetype":"venue"
},
  "geometry": {"coordinates":[-4.5162367821,36.6122550964],"type":"Point"}
}