{
  "type": "Feature",
  "properties": {
    "addr:full":"Ctra Alicante-valencia, Km. 0113,6 Vila Joiosa Alicante 03570",
    "addr:postcode":"03570",
    "addr:street":"Ctra Alicante-Valencia Km. 0113,6",
    "iso:country":"ES",
    "sg:address":"Ctra Alicante-valencia, Km. 0113,6",
    "sg:city":"Vila Joiosa",
    "sg:orig_category":"Mec\u00c1nico Del Autom\u00d3vil",
    "sg:phone":"+34 965 89 07 50",
    "sg:postcode":"03570",
    "sg:province":"Alicante",
    "wof:name":"Talleres Domingo Guardiola S.l.",
    "wof:placetype":"venue"
},
  "geometry": {"coordinates":[-0.2327190042,38.505821228],"type":"Point"}
}