{
  "type": "Feature",
  "properties": {
    "iso:country":"ES",
    "sg:address":"Calle de Valverde, 28",
    "sg:city":"Madrid",
    "sg:orig_category":"Empresarios Y Productoras De Espect\u00c1culos",
    "sg:phone":"+34 915 59 59 13",
    "sg:postcode":"28004",
    "sg:province":"Madrid",
    "wof:name":"Perez Fernandez Enrique Simon",
    "wof:placetype":"venue"
},
  "geometry": {"coordinates":[-3.7015089989,40.4224815369],"type":"Point"}
}