{
  "type": "Feature",
  "properties": {
    "addr:full":"Rua D, 6 Barreiros Ourense 32910",
    "addr:housenumber":"6",
    "addr:postcode":"32910",
    "addr:street":"Rua D",
    "iso:country":"ES",
    "sg:address":"Rua D, 6",
    "sg:city":"Barreiros",
    "sg:orig_category":"Transporte En General",
    "sg:phone":"+34 988 24 77 91",
    "sg:postcode":"32910",
    "sg:province":"Ourense",
    "wof:name":"Alvarez Rodriguez Gumersindo",
    "wof:placetype":"venue"
},
  "geometry": {"coordinates":[-7.8716039658,42.2960510254],"type":"Point"}
}