{
  "type": "Feature",
  "properties": {
    "iso:country":"ES",
    "sg:address":"Calle de General Lacy, 23",
    "sg:city":"S. Roque",
    "sg:orig_category":"Peluquer\u00cdas, Peluquer\u00cda Mixta",
    "sg:phone":"+34 956 78 23 60",
    "sg:postcode":"11360",
    "sg:province":"C\u00e1diz",
    "wof:name":"Beza Robles Elena",
    "wof:placetype":"venue"
},
  "geometry": {"coordinates":[-5.386015892,36.2103691101],"type":"Point"}
}