{
  "type": "Feature",
  "properties": {
    "iso:country":"ES",
    "sg:address":"Ctra Orihuela, S/n",
    "sg:city":"S. Miguel Salinas",
    "sg:orig_category":"Negocio De Materiales De Construcci\u00d3n",
    "sg:phone":"+34 965 72 01 78",
    "sg:postcode":"03193",
    "sg:province":"Alicante",
    "wof:name":"Tabisam S.l.",
    "wof:placetype":"venue"
},
  "geometry": {"coordinates":[-0.7939829826,37.9859733582],"type":"Point"}
}