{
  "type": "Feature",
  "properties": {
    "addr:full":"Zezenbide Kalea, 4 Eibar Guip\u00f9zcoa 20600",
    "addr:housenumber":"4",
    "addr:postcode":"20600",
    "addr:street":"Zezenbide Kalea;Guipu\u0300Zcoa",
    "iso:country":"ES",
    "sg:address":"Zezenbide Kalea, 4",
    "sg:city":"Eibar",
    "sg:orig_category":"Arreglo, Reparaci\u00d3n, Piezas Sueltas De Televisi\u00d3n, V\u00cddeo, Hi",
    "sg:phone":"+34 943 70 24 37",
    "sg:postcode":"20600",
    "sg:province":"Guip\u00f9zcoa",
    "wof:name":"Garrido Limia Jose",
    "wof:placetype":"venue"
},
  "geometry": {"coordinates":[-2.4738233089,43.1836280823],"type":"Point"}
}