{
  "type": "Feature",
  "properties": {
    "iso:country":"ES",
    "sg:address":"Calle de San Romualdo, 26",
    "sg:city":"Madrid",
    "sg:orig_category":"Edici\u00d3n De Diarios, Revistas, Boletines",
    "sg:phone":"+34 913 75 07 21",
    "sg:postcode":"28037",
    "sg:province":"Madrid",
    "wof:name":"Moreno Marin S.l",
    "wof:placetype":"venue"
},
  "geometry": {"coordinates":[-3.6215701103,40.4380455017],"type":"Point"}
}