{
  "type": "Feature",
  "properties": {
    "iso:country":"ES",
    "sg:address":"Calle de Pedro Antonio De Alarcon, 18",
    "sg:city":"Granada",
    "sg:orig_category":"Abogados",
    "sg:phone":"+34 958 25 05 14",
    "sg:postcode":"18005",
    "sg:province":"Granada",
    "wof:name":"Martin Jimenez De La Plata Antonio",
    "wof:placetype":"venue"
},
  "geometry": {"coordinates":[-3.6044979095,37.1703491211],"type":"Point"}
}