{
  "type": "Feature",
  "properties": {
    "addr:full":"Calle de Santander, 1 Colindres Cantabria 39750",
    "addr:housenumber":"1",
    "addr:postcode":"39750",
    "addr:street":"Calle De Santander",
    "iso:country":"ES",
    "sg:address":"Calle de Santander, 1",
    "sg:city":"Colindres",
    "sg:orig_category":"Lanas (al Por Menor)",
    "sg:phone":"+34 942 65 12 39",
    "sg:postcode":"39750",
    "sg:province":"Cantabria",
    "wof:name":"Palacio Bartolome Maria Jose",
    "wof:placetype":"venue"
},
  "geometry": {"coordinates":[-3.4486660957,43.396194458],"type":"Point"}
}