{
  "type": "Feature",
  "properties": {
    "addr:full":"Calle de Hermanos Alvarez Quintero, 2 Madrid Madrid 28004",
    "addr:housenumber":"2",
    "addr:postcode":"28004",
    "addr:street":"Calle De Hermanos Alvarez Quintero",
    "iso:country":"ES",
    "sg:address":"Calle de Hermanos Alvarez Quintero, 2",
    "sg:city":"Madrid",
    "sg:orig_category":"Decoraci\u00d3n: Instalaci\u00d3n Y Talleres",
    "sg:phone":"+34 915 93 49 75",
    "sg:postcode":"28004",
    "sg:province":"Madrid",
    "sg:website":"www.lambda-3.com",
    "wof:name":"Lambda-3 S. A.",
    "wof:placetype":"venue"
},
  "geometry": {"coordinates":[-3.697384119,40.4278068542],"type":"Point"}
}