{
  "type": "Feature",
  "properties": {
    "iso:country":"ES",
    "sg:address":"Calle de Ramon Asensio, 2",
    "sg:city":"Valencia",
    "sg:orig_category":"Administradores De Bienes Y Delegados De Comunidades De Propietarios",
    "sg:phone":"+34 963 60 02 03",
    "sg:postcode":"46020",
    "sg:province":"Valencia",
    "wof:name":"Administraciones Gabaldon S.l.",
    "wof:placetype":"venue"
},
  "geometry": {"coordinates":[-0.3592526913,39.481628418],"type":"Point"}
}