{
  "type": "Feature",
  "properties": {
    "addr:full":"Calle de General Elorza, 56 Oviedo Asturias 33001",
    "addr:housenumber":"56",
    "addr:postcode":"33001",
    "addr:street":"Calle De General Elorza",
    "iso:country":"ES",
    "sg:address":"Calle de General Elorza, 56",
    "sg:city":"Oviedo",
    "sg:orig_category":"Expertos Contables",
    "sg:phone":"+34 985 22 36 52",
    "sg:postcode":"33001",
    "sg:province":"Asturias",
    "wof:name":"Plaza Peritaciones S.l.",
    "wof:placetype":"venue"
},
  "geometry": {"coordinates":[-5.8479809761,43.3670501709],"type":"Point"}
}