{
  "type": "Feature",
  "properties": {
    "addr:full":"Avda Malaga, 15 Ronda M\u00e1laga 29400",
    "addr:housenumber":"15",
    "addr:postcode":"29400",
    "addr:street":"Avda Malaga;Ronda Ma\u0301Laga",
    "iso:country":"ES",
    "sg:address":"Avda Malaga, 15",
    "sg:city":"Ronda",
    "sg:orig_category":"Cajas De Ahorro",
    "sg:phone":"+34 952 19 00 51",
    "sg:postcode":"29400",
    "sg:province":"M\u00e1laga",
    "sg:website":"www.lacaixa.es",
    "wof:name":"Caixa D'estalvis I Pensions De Barcelona",
    "wof:placetype":"venue"
},
  "geometry": {"coordinates":[-5.1558499336,36.7483062744],"type":"Point"}
}