{
  "type": "Feature",
  "properties": {
    "addr:full":"C/ Girona, 91 Banyoles Girona 17820",
    "addr:housenumber":"91",
    "addr:postcode":"17820",
    "addr:street":"C / Girona",
    "iso:country":"ES",
    "sg:address":"C/ Girona, 91",
    "sg:city":"Banyoles",
    "sg:orig_category":"Molduras, Junquillos, Listones Y Molduras Perforadas",
    "sg:phone":"+34 972 57 63 37",
    "sg:postcode":"17820",
    "sg:province":"Girona",
    "wof:name":"Garcia Arjona Manuel",
    "wof:placetype":"venue"
},
  "geometry": {"coordinates":[2.7684099674,42.1165313721],"type":"Point"}
}