{
  "type": "Feature",
  "properties": {
    "iso:country":"ES",
    "sg:address":"Carrer de Bon Viatge, 1",
    "sg:city":"S. Joan Despi",
    "sg:orig_category":"Peluquer\u00cdas, Peluquer\u00cda Mixta",
    "sg:phone":"+34 933 73 42 02",
    "sg:postcode":"08970",
    "sg:province":"Barcelona",
    "wof:name":"Gonzalez Vicente Juana",
    "wof:placetype":"venue"
},
  "geometry": {"coordinates":[2.0565619469,41.3668861389],"type":"Point"}
}