{
  "type": "Feature",
  "properties": {
    "iso:country":"ES",
    "sg:address":"Calle de Arkotxa, 15",
    "sg:city":"Algorta",
    "sg:orig_category":"Fabricaci\u00d3n, Venta, Instalaci\u00d3n De R\u00d3tulos, De R\u00d3tulos Luminosos",
    "sg:phone":"+34 944 60 99 12",
    "sg:postcode":"48992",
    "sg:province":"Vizcaya",
    "wof:name":"Gerber Scientific Internacional(spain",
    "wof:placetype":"venue"
},
  "geometry": {"coordinates":[-3.0058612823,43.34324646],"type":"Point"}
}