{
  "type": "Feature",
  "properties": {
    "addr:full":"Calle de Pilar, 3 Fuente Maestre Badajoz 06360",
    "addr:housenumber":"3",
    "addr:postcode":"06360",
    "addr:street":"Calle De Pilar",
    "iso:country":"ES",
    "sg:address":"Calle de Pilar, 3",
    "sg:city":"Fuente Maestre",
    "sg:orig_category":"Ense\u00d1anza Variada",
    "sg:phone":"+34 924 53 05 81",
    "sg:postcode":"06360",
    "sg:province":"Badajoz",
    "wof:name":"Santiago Guerrero Sebastian",
    "wof:placetype":"venue"
},
  "geometry": {"coordinates":[-6.4479489326,38.5259208679],"type":"Point"}
}