{
  "type": "Feature",
  "properties": {
    "addr:full":"Calle de Santa Ana, 18 San Antonio Valencia 46390",
    "addr:housenumber":"18",
    "addr:postcode":"46390",
    "addr:street":"Calle De Santa Ana",
    "iso:country":"ES",
    "sg:address":"Calle de Santa Ana, 18",
    "sg:city":"San Antonio",
    "sg:orig_category":"Productores Recolectores, Venta Directa De Vinos",
    "sg:phone":"+34 962 32 06 56",
    "sg:postcode":"46390",
    "sg:province":"Valencia",
    "wof:name":"Reservas Y Crianzas Requenenses S.l.",
    "wof:placetype":"venue"
},
  "geometry": {"coordinates":[-1.1526839733,39.5217018127],"type":"Point"}
}