{
  "type": "Feature",
  "properties": {
    "iso:country":"ES",
    "sg:address":"Calle de Venecia, 7",
    "sg:city":"Sevilla",
    "sg:orig_category":"Ropa Para Caballeros (al Por Menor)",
    "sg:phone":"+34 954 41 11 37",
    "sg:postcode":"41008",
    "sg:province":"Sevilla",
    "wof:name":"Cebrian Casares Carlos",
    "wof:placetype":"venue"
},
  "geometry": {"coordinates":[-5.9797749519,37.3950805664],"type":"Point"}
}