{
  "type": "Feature",
  "properties": {
    "addr:full":"Avda Estacion (de La), 26 Almeria Almer\u00eda 04005",
    "addr:housenumber":"26",
    "addr:postcode":"04005",
    "addr:street":"Avda Estacion De La",
    "iso:country":"ES",
    "sg:address":"Avda Estacion (de La), 26",
    "sg:city":"Almeria",
    "sg:orig_category":"M\u00c9dicos: Estomatolog\u00cda",
    "sg:phone":"+34 950 25 65 69",
    "sg:postcode":"04005",
    "sg:province":"Almer\u00eda",
    "wof:name":"Gomez Criado Felix",
    "wof:placetype":"venue"
},
  "geometry": {"coordinates":[-2.4578139782,36.837020874],"type":"Point"}
}