{
  "type": "Feature",
  "properties": {
    "addr:full":"Avda El Ferial, 68 Benavente Zamora 49600",
    "addr:housenumber":"68",
    "addr:postcode":"49600",
    "addr:street":"Avda El Ferial",
    "iso:country":"ES",
    "sg:address":"Avda El Ferial, 68",
    "sg:city":"Benavente",
    "sg:orig_category":"Contenedores (mercanc\u00cdas)",
    "sg:phone":"+34 980 63 34 07",
    "sg:postcode":"49600",
    "sg:province":"Zamora",
    "wof:name":"Posado Salson Julio",
    "wof:placetype":"venue"
},
  "geometry": {"coordinates":[-5.6743888855,42.0017700195],"type":"Point"}
}