{
  "type": "Feature",
  "properties": {
    "addr:full":"Calle de Camilo Jose Cela, 6 Rojales Alicante 03170",
    "addr:housenumber":"6",
    "addr:postcode":"03170",
    "addr:street":"Calle De Camilo Jose Cela",
    "iso:country":"ES",
    "sg:address":"Calle de Camilo Jose Cela, 6",
    "sg:city":"Rojales",
    "sg:orig_category":"Promotores Constructores",
    "sg:phone":"+34 966 71 58 99",
    "sg:postcode":"03170",
    "sg:province":"Alicante",
    "wof:name":"Construcciones Jesus Y Joaquin S.l.",
    "wof:placetype":"venue"
},
  "geometry": {"coordinates":[-0.7209671736,38.0881271362],"type":"Point"}
}