{
  "type": "Feature",
  "properties": {
    "iso:country":"ES",
    "sg:address":"Calle de Coca De La Pi\u00d1era, 96",
    "sg:city":"Moron Frontera",
    "sg:orig_category":"Ense\u00d1anza, Formaci\u00d3n Profesional: Aprendizaje",
    "sg:phone":"+34 954 85 29 99",
    "sg:postcode":"41530",
    "sg:province":"Sevilla",
    "wof:name":"Centro De Estudios Academia Pantano S.l.u.",
    "wof:placetype":"venue"
},
  "geometry": {"coordinates":[-5.4490032196,37.130531311],"type":"Point"}
}