{
  "type": "Feature",
  "properties": {
    "addr:full":"Zigordia Kalea, 10 Zarautz Guip\u00f9zcoa 20800",
    "addr:housenumber":"10",
    "addr:postcode":"20800",
    "addr:street":"Zigordia Kalea;Guipu\u0300Zcoa",
    "iso:country":"ES",
    "sg:address":"Zigordia Kalea, 10",
    "sg:city":"Zarautz",
    "sg:orig_category":"Estilistas Y Estudios De Estilo De Corte Y Confecci\u00d3n",
    "sg:phone":"+34 943 13 32 73",
    "sg:postcode":"20800",
    "sg:province":"Guip\u00f9zcoa",
    "wof:name":"Pinedo Laspiur Alberto Juan",
    "wof:placetype":"venue"
},
  "geometry": {"coordinates":[-2.175673008,43.2852897644],"type":"Point"}
}