{
  "type": "Feature",
  "properties": {
    "addr:full":"Plaz Educador Hermano Benjamin, 5 Altzaga Vizcaya 48950",
    "addr:housenumber":"5",
    "addr:postcode":"48950",
    "addr:street":"Benjamin",
    "iso:country":"ES",
    "sg:address":"Plaz Educador Hermano Benjamin, 5",
    "sg:city":"Altzaga",
    "sg:orig_category":"Plomeros",
    "sg:phone":"+34 944 67 33 99",
    "sg:postcode":"48950",
    "sg:province":"Vizcaya",
    "wof:name":"Gomez Arias Antonio",
    "wof:placetype":"venue"
},
  "geometry": {"coordinates":[-2.9709439278,43.3046913147],"type":"Point"}
}