{
  "type": "Feature",
  "properties": {
    "iso:country":"ES",
    "sg:address":"Carrer de Indalecio Prieto, 29",
    "sg:city":"Palma",
    "sg:orig_category":"Molduras, Junquillos, Listones Y Molduras Perforadas",
    "sg:phone":"+34 971 27 10 54",
    "sg:postcode":"07008",
    "sg:province":"Islas Baleares",
    "wof:name":"Sureda Blanes Pedro",
    "wof:placetype":"venue"
},
  "geometry": {"coordinates":[2.6719739437,39.5783233643],"type":"Point"}
}