{
  "type": "Feature",
  "properties": {
    "iso:country":"ES",
    "sg:address":"Rua Lugo, S/n",
    "sg:city":"Santa Comba",
    "sg:orig_category":"Asesor\u00cda Sobre Comunicaci\u00d3n De Empresas",
    "sg:phone":"+34 981 88 11 47",
    "sg:postcode":"15840",
    "sg:province":"La Coru\u00f1a",
    "wof:name":"Fari\u00f1a Facal Concepcion",
    "wof:placetype":"venue"
},
  "geometry": {"coordinates":[-8.8141794205,43.0327987671],"type":"Point"}
}