{
  "type": "Feature",
  "properties": {
    "iso:country":"ES",
    "sg:address":"Crta. Madrid-barcelona, Km. 0035,5",
    "sg:city":"Alcala Henares",
    "sg:orig_category":"Suministros Para Hoteles",
    "sg:phone":"+34 918 79 67 62",
    "sg:postcode":"28802",
    "sg:province":"Madrid",
    "sg:website":"www.aliberinox.com",
    "wof:name":"Aliberinox S.l.",
    "wof:placetype":"venue"
},
  "geometry": {"coordinates":[-3.7003455162,40.4166908264],"type":"Point"}
}