{
  "type": "Feature",
  "properties": {
    "addr:full":"Calle de Monasterio De Caaveiro, 26 Coru\u00d1a La Coru\u00f1a 15010",
    "addr:housenumber":"26",
    "addr:postcode":"15010",
    "addr:street":"Calle De Monasterio De Caaveiro;La Corun\u0303A",
    "iso:country":"ES",
    "sg:address":"Calle de Monasterio De Caaveiro, 26",
    "sg:city":"Coru\u00d1a",
    "sg:orig_category":"Reposter\u00cdas",
    "sg:phone":"+34 981 14 11 28",
    "sg:postcode":"15010",
    "sg:province":"La Coru\u00f1a",
    "wof:name":"Alimentacion Outon S.l.",
    "wof:placetype":"venue"
},
  "geometry": {"coordinates":[-8.423365593,43.3608360291],"type":"Point"}
}