{
  "type": "Feature",
  "properties": {
    "iso:country":"ES",
    "sg:address":"Calle de Benito Toboso, 49",
    "sg:city":"Hellin",
    "sg:classifiers":[
        {
            "category":"Personal",
            "subcategory":"Barber",
            "type":"Services"
        }
    ],
    "sg:phone":"+34 967 30 36 62",
    "sg:postcode":"02400",
    "sg:province":"Albacete",
    "sg:tags":[
        "caballeros",
        "de",
        "peluqueros"
    ],
    "wof:name":"Serrano Sanchez Rafael",
    "wof:placetype":"venue"
},
  "geometry": {"coordinates":[-1.7009589672,38.5133895874],"type":"Point"}
}