{
  "type": "Feature",
  "properties": {
    "addr:full":"Carrer de Major, 52 Riudoms Tarragona 43330",
    "addr:housenumber":"52",
    "addr:postcode":"43330",
    "addr:street":"Carrer De Major",
    "iso:country":"ES",
    "sg:address":"Carrer de Major, 52",
    "sg:city":"Riudoms",
    "sg:orig_category":"Ense\u00d1anza, Formaci\u00d3n Profesional: Aprendizaje",
    "sg:phone":"+34 977 85 08 88",
    "sg:postcode":"43330",
    "sg:province":"Tarragona",
    "wof:name":"Ajuntament De Riudoms",
    "wof:placetype":"venue"
},
  "geometry": {"coordinates":[1.0510356426,41.1376914978],"type":"Point"}
}