{
  "type": "Feature",
  "properties": {
    "iso:country":"ES",
    "sg:address":"Carrer de Torcuato Luca Tena, 26",
    "sg:city":"Palma",
    "sg:orig_category":"Ropa Para Se\u00d1oras (al Por Menor)",
    "sg:phone":"+34 971 24 54 46",
    "sg:postcode":"07005",
    "sg:province":"Islas Baleares",
    "wof:name":"Rio Martinez Ana Isabel Del",
    "wof:placetype":"venue"
},
  "geometry": {"coordinates":[2.6637749672,39.5768699646],"type":"Point"}
}