{
  "type": "Feature",
  "properties": {
    "addr:full":"Rua Gaiteiro De Soutelo (do), 3 Pontevedra Pontevedra 36004",
    "addr:postcode":"36004",
    "addr:street":"Rua Gaiteiro",
    "iso:country":"ES",
    "sg:address":"Rua Gaiteiro De Soutelo (do), 3",
    "sg:city":"Pontevedra",
    "sg:orig_category":"Ingenier\u00cda, Centros De Estudios (diversos)",
    "sg:phone":"+34 986 85 38 40",
    "sg:postcode":"36004",
    "sg:province":"Pontevedra",
    "wof:name":"Proyectos Mineros Icam S.l.",
    "wof:placetype":"venue"
},
  "geometry": {"coordinates":[-8.6293430328,42.4288139343],"type":"Point"}
}