{
  "type": "Feature",
  "properties": {
    "iso:country":"ES",
    "sg:address":"Afores, S/n",
    "sg:city":"Penelles",
    "sg:orig_category":"Agricultores, Agricultores",
    "sg:phone":"+34 973 61 02 73",
    "sg:postcode":"25335",
    "sg:province":"Lleida",
    "wof:name":"Salt De Penelles S.a",
    "wof:placetype":"venue"
},
  "geometry": {"coordinates":[0.9648439884,41.7575531006],"type":"Point"}
}