{
  "type": "Feature",
  "properties": {
    "addr:full":"Calle de Miramar, 46 Guime Las Palmas 35550",
    "addr:housenumber":"46",
    "addr:postcode":"35550",
    "addr:street":"Calle De Miramar;Palmas",
    "iso:country":"ES",
    "sg:address":"Calle de Miramar, 46",
    "sg:city":"Guime",
    "sg:orig_category":"Camiser\u00cda Y Ropa Interior Masculina (al Por Menor)",
    "sg:phone":"+34 928 52 25 58",
    "sg:postcode":"35550",
    "sg:province":"Las Palmas",
    "wof:name":"Bedford  Stephen",
    "wof:placetype":"venue"
},
  "geometry": {"coordinates":[-13.6098937988,29.0045204163],"type":"Point"}
}