{
  "type": "Feature",
  "properties": {
    "iso:country":"ES",
    "sg:address":"Pase Bertsol. Txirrita, 27",
    "sg:city":"Donostia-san Sebastian",
    "sg:orig_category":"Peluquer\u00cdas, Peluquer\u00cda Mixta",
    "sg:phone":"+34 943 40 04 98",
    "sg:postcode":"20017",
    "sg:province":"Guip\u00f9zcoa",
    "wof:name":"Franco Ejido Maria",
    "wof:placetype":"venue"
},
  "geometry": {"coordinates":[-1.9375139475,43.3166923523],"type":"Point"}
}