{
  "type": "Feature",
  "properties": {
    "iso:country":"ES",
    "sg:address":"Carrer de Ordal, 36",
    "sg:city":"Mira-sol",
    "sg:orig_category":"Ropa Para Beb\u00c9s Y Ni\u00d1os (confecci\u00d3n, Al Por Mayor)",
    "sg:phone":"+34 936 75 72 94",
    "sg:postcode":"08195",
    "sg:province":"Barcelona",
    "wof:name":"Caralt Selles Sonia",
    "wof:placetype":"venue"
},
  "geometry": {"coordinates":[2.0513830185,41.4722671509],"type":"Point"}
}