{
  "type": "Feature",
  "properties": {
    "addr:full":"Calle de Juan Rodriguez Doreste, 1 Monta\u00e7a La Data Las Palmas 35100",
    "addr:housenumber":"1",
    "addr:postcode":"35100",
    "addr:street":"Calle De Juan Rodriguez Doreste;La",
    "iso:country":"ES",
    "sg:address":"Calle de Juan Rodriguez Doreste, 1",
    "sg:city":"Monta\u00e7a La Data",
    "sg:orig_category":"Importaci\u00d3n",
    "sg:phone":"+34 928 14 21 42",
    "sg:postcode":"35100",
    "sg:province":"Las Palmas",
    "wof:name":"Importacion De Repuestos El Tablero S.l.",
    "wof:placetype":"venue"
},
  "geometry": {"coordinates":[-15.4397096634,28.1302204132],"type":"Point"}
}