{
  "type": "Feature",
  "properties": {
    "iso:country":"ES",
    "sg:address":"Calle de Milicias, 11",
    "sg:city":"Logro\u00f1o",
    "sg:orig_category":"Carnicer\u00cdas, Carnicer\u00cdas",
    "sg:phone":"+34 941 25 52 81",
    "sg:postcode":"26003",
    "sg:province":"La Rioja",
    "wof:name":"Ruiz Martinez Valentin",
    "wof:placetype":"venue"
},
  "geometry": {"coordinates":[-2.4386610985,42.4629325867],"type":"Point"}
}