{
  "type": "Feature",
  "properties": {
    "iso:country":"ES",
    "sg:address":"Carr Noguera, S/n",
    "sg:city":"Pobla Segur",
    "sg:orig_category":"Hormigonados",
    "sg:phone":"+34 973 68 14 13",
    "sg:postcode":"25500",
    "sg:province":"Lleida",
    "wof:name":"Promotora Mediterranea 2 S.a.",
    "wof:placetype":"venue"
},
  "geometry": {"coordinates":[0.9664350152,42.2486915588],"type":"Point"}
}