{
  "type": "Feature",
  "properties": {
    "addr:full":"C/ Reis Catolics, 14 Manacor Islas Baleares 07500",
    "addr:housenumber":"14",
    "addr:postcode":"07500",
    "addr:street":"C / Reis Catolics",
    "iso:country":"ES",
    "sg:address":"C/ Reis Catolics, 14",
    "sg:city":"Manacor",
    "sg:orig_category":"Fabricaci\u00d3n De Ropa De Deportes",
    "sg:phone":"+34 971 55 48 67",
    "sg:postcode":"07500",
    "sg:province":"Islas Baleares",
    "sg:website":"www.barbaramas.infor",
    "wof:name":"Perrello Mas Juan",
    "wof:placetype":"venue"
},
  "geometry": {"coordinates":[3.2054851055,39.5725440979],"type":"Point"}
}