{
  "type": "Feature",
  "properties": {
    "iso:country":"ES",
    "sg:address":"Calle de Arzobispo Fabian Y Fuero, 23",
    "sg:city":"Valencia",
    "sg:orig_category":"Lavado, Limpieza De Veh\u00cdculos",
    "sg:phone":"+34 963 47 33 14",
    "sg:postcode":"46009",
    "sg:province":"Valencia",
    "wof:name":"Claramunt Andres Luis Manuel",
    "wof:placetype":"venue"
},
  "geometry": {"coordinates":[-0.3815388978,39.4839897156],"type":"Point"}
}