{
  "type": "Feature",
  "properties": {
    "iso:country":"ES",
    "sg:address":"Llotja Del Peix, S/n",
    "sg:city":"Llan\u00e7a",
    "sg:classifiers":[
        {
            "category":"Recreation",
            "type":"Entertainment"
        }
    ],
    "sg:phone":"+34 972 38 09 01",
    "sg:postcode":"17490",
    "sg:province":"Girona",
    "sg:tags":[
        "caza",
        "pr\u00c1ctica",
        "la",
        "de",
        "pesca",
        "y"
    ],
    "wof:name":"Cofradia De Pescadores De Llanca",
    "wof:placetype":"venue"
},
  "geometry": {"coordinates":[3.1481759548,42.3640785217],"type":"Point"}
}