{
  "type": "Feature",
  "properties": {
    "addr:full":"Torre, 2 Curuxeiras Ourense 32005",
    "addr:postcode":"32005",
    "iso:country":"ES",
    "sg:address":"Torre, 2",
    "sg:city":"Curuxeiras",
    "sg:orig_category":"Asociaciones, Instituciones De Consumidores Y Usuarios",
    "sg:phone":"+34 988 40 51 76",
    "sg:postcode":"32005",
    "sg:province":"Ourense",
    "wof:name":"Asociacion De Vecinos Laxas",
    "wof:placetype":"venue"
},
  "geometry": {"coordinates":[-7.8320822716,42.3047714233],"type":"Point"}
}