{
  "type": "Feature",
  "properties": {
    "iso:country":"ES",
    "sg:address":"Pol Ind El Frontil, 5",
    "sg:city":"Loja",
    "sg:orig_category":"Mec\u00c1nico Del Autom\u00d3vil",
    "sg:phone":"+34 958 32 32 40",
    "sg:postcode":"18300",
    "sg:province":"Granada",
    "wof:name":"Alba Ortigosa Santiago",
    "wof:placetype":"venue"
},
  "geometry": {"coordinates":[-4.1718540192,37.1597938538],"type":"Point"}
}