{
  "type": "Feature",
  "properties": {
    "addr:full":"Carr Guifre, 604 Badalona Barcelona 08918",
    "addr:housenumber":"604",
    "addr:postcode":"08918",
    "addr:street":"Carr Guifre",
    "iso:country":"ES",
    "sg:address":"Carr Guifre, 604",
    "sg:city":"Badalona",
    "sg:orig_category":"Empresas De Carpinter\u00cda De Madera",
    "sg:phone":"+34 933 88 25 99",
    "sg:postcode":"08918",
    "sg:province":"Barcelona",
    "wof:name":"Gil Morales Antonio",
    "wof:placetype":"venue"
},
  "geometry": {"coordinates":[2.2340490818,41.4375991821],"type":"Point"}
}