{
  "type": "Feature",
  "properties": {
    "addr:full":"Calle de Ramon Y Cajal, 10 Don Benito Badajoz 06400",
    "addr:housenumber":"10",
    "addr:postcode":"06400",
    "addr:street":"Calle De Ramon Y Cajal",
    "iso:country":"ES",
    "sg:address":"Calle de Ramon Y Cajal, 10",
    "sg:city":"Don Benito",
    "sg:orig_category":"Confecci\u00d3n (fabricaci\u00d3n, Al Por Mayor)",
    "sg:phone":"+34 924 81 25 50",
    "sg:postcode":"06400",
    "sg:province":"Badajoz",
    "wof:name":"Almeida Machuca S.a.",
    "wof:placetype":"venue"
},
  "geometry": {"coordinates":[-5.8615636826,38.9563140869],"type":"Point"}
}