{
  "type": "Feature",
  "properties": {
    "iso:country":"ES",
    "sg:address":"Calle de Jose Luis Borau, 16",
    "sg:city":"Zaragoza",
    "sg:orig_category":"Telas Para Tapizar, Cortinas, Pasamaner\u00cda (fabricaci\u00d3n, Al Por Mayor)",
    "sg:phone":"+34 976 52 35 74",
    "sg:postcode":"50018",
    "sg:province":"Zaragoza",
    "wof:name":"Alfaro Busquets Rosa",
    "wof:placetype":"venue"
},
  "geometry": {"coordinates":[-0.8851857185,41.6752052307],"type":"Point"}
}