{
  "type": "Feature",
  "properties": {
    "addr:full":"Ctra. Madrid, Km. 0158,0 Salvadios \u00c1vila 05380",
    "addr:postcode":"05380",
    "addr:street":"Ctra. Madrid Km. 0158,0 Salvadios A\u0301Vila",
    "iso:country":"ES",
    "sg:address":"Ctra. Madrid, Km. 0158,0",
    "sg:city":"Salvadios",
    "sg:orig_category":"Construcci\u00d3n Mec\u00c1nica",
    "sg:phone":"+34 923 56 30 52",
    "sg:postcode":"05380",
    "sg:province":"\u00c1vila",
    "wof:name":"Jimenez Jimenez Felipe",
    "wof:placetype":"venue"
},
  "geometry": {"coordinates":[-5.0963654518,40.8769989014],"type":"Point"}
}