{
  "type": "Feature",
  "properties": {
    "iso:country":"ES",
    "sg:address":"M. T. Ferrer, 16",
    "sg:city":"Cox",
    "sg:orig_category":"Fabricaci\u00d3n, Reparaci\u00d3n Y Mantenimiento De Construcciones Navales Y Fluviales",
    "sg:phone":"+34 966 75 00 39",
    "sg:postcode":"03350",
    "sg:province":"Alicante",
    "wof:name":"Jose Manresa S.l.",
    "wof:placetype":"venue"
},
  "geometry": {"coordinates":[-0.8875390291,38.1411094666],"type":"Point"}
}