{
  "type": "Feature",
  "properties": {
    "addr:full":"Calle de Costa Brava, 39 Madrid Madrid 28034",
    "addr:housenumber":"39",
    "addr:postcode":"madrid;28034",
    "addr:street":"Calle De Costa Brava",
    "iso:country":"ES",
    "sg:address":"Calle de Costa Brava, 39",
    "sg:city":"Madrid",
    "sg:orig_category":"Asesor\u00cda Sobre Comunicaci\u00d3n De Empresas",
    "sg:phone":"+34 913 72 09 84",
    "sg:postcode":"28034",
    "sg:province":"Madrid",
    "wof:name":"Proyectos Alfer S.l.",
    "wof:placetype":"venue"
},
  "geometry": {"coordinates":[-3.7079958916,40.4985923767],"type":"Point"}
}