{
  "type": "Feature",
  "properties": {
    "iso:country":"ES",
    "sg:address":"Carr Constitucio, De Sa, 6",
    "sg:city":"Andratx",
    "sg:orig_category":"Ropa Para Se\u00d1oras (al Por Menor)",
    "sg:phone":"+34 971 13 70 93",
    "sg:postcode":"07150",
    "sg:province":"Islas Baleares",
    "wof:name":"Busquet C.b.",
    "wof:placetype":"venue"
},
  "geometry": {"coordinates":[2.4203250408,39.5743255615],"type":"Point"}
}