{
  "type": "Feature",
  "properties": {
    "addr:full":"Calle de De Las Eras, 50 Benavente Zamora 49600",
    "addr:housenumber":"50",
    "addr:postcode":"49600",
    "addr:street":"Calle De De Las Eras",
    "iso:country":"ES",
    "sg:address":"Calle de De Las Eras, 50",
    "sg:city":"Benavente",
    "sg:orig_category":"Molduras, Junquillos, Listones Y Molduras Perforadas",
    "sg:phone":"+34 980 63 41 27",
    "sg:postcode":"49600",
    "sg:province":"Zamora",
    "wof:name":"Alfayete Alvarez Roberto",
    "wof:placetype":"venue"
},
  "geometry": {"coordinates":[-5.7452836037,42.0332946777],"type":"Point"}
}