{
  "type": "Feature",
  "properties": {
    "iso:country":"ES",
    "sg:address":"Calle de Principe De Asturias, 48",
    "sg:city":"Elda",
    "sg:orig_category":"Ebanister\u00cda",
    "sg:phone":"+34 965 38 33 90",
    "sg:postcode":"03600",
    "sg:province":"Alicante",
    "wof:name":"Marqueteria Penalva S.l.",
    "wof:placetype":"venue"
},
  "geometry": {"coordinates":[-0.7912889719,38.4786300659],"type":"Point"}
}