{
  "type": "Feature",
  "properties": {
    "addr:full":"Avda Constitucion, 9 Valencia Valencia 46009",
    "addr:housenumber":"9",
    "addr:postcode":"46009",
    "addr:street":"Avda Constitucion",
    "iso:country":"ES",
    "sg:address":"Avda Constitucion, 9",
    "sg:city":"Valencia",
    "sg:orig_category":"Papeler\u00cdas, Librer\u00cdas",
    "sg:phone":"+34 963 49 90 06",
    "sg:postcode":"46009",
    "sg:province":"Valencia",
    "wof:name":"Alonso Salinas S.l.",
    "wof:placetype":"venue"
},
  "geometry": {"coordinates":[-0.3757708073,39.4895095825],"type":"Point"}
}