{
  "type": "Feature",
  "properties": {
    "iso:country":"ES",
    "sg:address":"Calle de Alemania, S/n",
    "sg:city":"Noblejas",
    "sg:orig_category":"Cajas De Ahorro",
    "sg:phone":"+34 925 14 14 39",
    "sg:postcode":"45350",
    "sg:province":"Toledo",
    "wof:name":"Caixa D'estalvis I Pensions De Barcelona",
    "wof:placetype":"venue"
},
  "geometry": {"coordinates":[-3.4415528774,39.9830932617],"type":"Point"}
}