{
  "type": "Feature",
  "properties": {
    "addr:full":"P. Industrial, S/n Melilla Melilla 52006",
    "addr:housenumber":"/ n",
    "addr:postcode":"52006",
    "addr:street":"P. Industrial S",
    "iso:country":"ES",
    "sg:address":"P. Industrial, S/n",
    "sg:city":"Melilla",
    "sg:orig_category":"Edici\u00d3n De Diarios, Revistas, Boletines",
    "sg:phone":"+34 952 67 93 85",
    "sg:postcode":"52006",
    "sg:province":"Melilla",
    "sg:website":"www.melillahoy.es",
    "wof:name":"Prensa De Melilla S.a.",
    "wof:placetype":"venue"
},
  "geometry": {"coordinates":[-2.9361999035,35.2828216553],"type":"Point"}
}