{
  "type": "Feature",
  "properties": {
    "iso:country":"ES",
    "sg:address":"C/ Terral, 61",
    "sg:city":"Arenal",
    "sg:orig_category":"Servicios Diversos",
    "sg:phone":"+34 971 44 04 09",
    "sg:postcode":"07600",
    "sg:province":"Islas Baleares",
    "wof:name":"Asociacion De Personas Mayores De S'arenal De Llucmajor",
    "wof:placetype":"venue"
},
  "geometry": {"coordinates":[2.7518522739,39.503578186],"type":"Point"}
}