{
  "type": "Feature",
  "properties": {
    "iso:country":"ES",
    "sg:address":"Ctra Errekalde-larraskitu, 50",
    "sg:city":"Bilbao",
    "sg:orig_category":"Empresas De Limpieza",
    "sg:phone":"+34 944 70 38 00",
    "sg:postcode":"48002",
    "sg:province":"Vizcaya",
    "sg:website":"www.euroservice.com",
    "wof:name":"Europea De Servicios E Higiene S.a.",
    "wof:placetype":"venue"
},
  "geometry": {"coordinates":[-2.9400129318,43.2481269836],"type":"Point"}
}