{
  "type": "Feature",
  "properties": {
    "addr:full":"Av Madrid, 9 Barcelona Barcelona 08028",
    "addr:housenumber":"9",
    "addr:postcode":"08028",
    "addr:street":"Av Madrid",
    "iso:country":"ES",
    "sg:address":"Av Madrid, 9",
    "sg:city":"Barcelona",
    "sg:orig_category":"\u00d3ptica: Instrumentos (fabricaci\u00d3n)",
    "sg:phone":"+34 934 49 07 17",
    "sg:postcode":"08028",
    "sg:province":"Barcelona",
    "wof:name":"Gafas Y Dise\u00f1os S.a.",
    "wof:placetype":"venue"
},
  "geometry": {"coordinates":[2.1235198975,41.3762702942],"type":"Point"}
}