{
  "type": "Feature",
  "properties": {
    "addr:full":"Calle de Azpeitia, 7 Donostia-san Sebastian Guip\u00f9zcoa 20010",
    "addr:housenumber":"7",
    "addr:postcode":"20010",
    "addr:street":"Calle De Azpeitia",
    "iso:country":"ES",
    "sg:address":"Calle de Azpeitia, 7",
    "sg:city":"Donostia-san Sebastian",
    "sg:orig_category":"Arquitectos",
    "sg:phone":"+34 943 46 59 41",
    "sg:postcode":"20010",
    "sg:province":"Guip\u00f9zcoa",
    "wof:name":"Rincon Arce Daniel",
    "wof:placetype":"venue"
},
  "geometry": {"coordinates":[-1.9810315371,43.3098182678],"type":"Point"}
}