{
  "type": "Feature",
  "properties": {
    "addr:full":"Avda Joan Miro, 14 Torremolinos M\u00e1laga 29620",
    "addr:housenumber":"14",
    "addr:postcode":"29620",
    "addr:street":"Avda Joan Miro;Ma\u0301Laga",
    "iso:country":"ES",
    "sg:address":"Avda Joan Miro, 14",
    "sg:city":"Torremolinos",
    "sg:orig_category":"Aparatos, Sistemas De Tele",
    "sg:phone":"+34 952 38 86 93",
    "sg:postcode":"29620",
    "sg:province":"M\u00e1laga",
    "wof:name":"Salazar Sanchez Rosa Maria",
    "wof:placetype":"venue"
},
  "geometry": {"coordinates":[-4.5016570091,36.6222190857],"type":"Point"}
}