{
  "type": "Feature",
  "properties": {
    "addr:full":"Calle de Monte, 38 Barcarrota Badajoz 06160",
    "addr:housenumber":"38",
    "addr:postcode":"06160",
    "addr:street":"Calle De Monte",
    "iso:country":"ES",
    "sg:address":"Calle de Monte, 38",
    "sg:city":"Barcarrota",
    "sg:orig_category":"Bancos",
    "sg:phone":"+34 924 73 60 50",
    "sg:postcode":"06160",
    "sg:province":"Badajoz",
    "wof:name":"Banco Espa\u00f1ol De Credito S.a.",
    "wof:placetype":"venue"
},
  "geometry": {"coordinates":[-6.8535218239,38.5174026489],"type":"Point"}
}