{
  "type": "Feature",
  "properties": {
    "iso:country":"ES",
    "sg:address":"Dels Rajolers, 12",
    "sg:city":"P.i. Masia Del Juez",
    "sg:orig_category":"Delegados, Agentes De Tr\u00c1nsito, Auxiliares De Transporte Internacional",
    "sg:phone":"+34 961 56 74 08",
    "sg:postcode":"46900",
    "sg:province":"Valencia",
    "wof:name":"Salvador Hidalgo Aniceto",
    "wof:placetype":"venue"
},
  "geometry": {"coordinates":[-0.4623290002,39.441619873],"type":"Point"}
}