{
  "type": "Feature",
  "properties": {
    "iso:country":"ES",
    "sg:address":"Carrer de Francesc Bastos (de), 18",
    "sg:city":"Tarragona",
    "sg:orig_category":"Laboratorios Y Cl\u00cdnicas Veterinarias",
    "sg:phone":"+34 977 23 51 81",
    "sg:postcode":"43005",
    "sg:province":"Tarragona",
    "wof:name":"Patino Macias Jose Manuel",
    "wof:placetype":"venue"
},
  "geometry": {"coordinates":[1.242264986,41.1146202087],"type":"Point"}
}