{
  "type": "Feature",
  "properties": {
    "iso:country":"ES",
    "sg:address":"Plaz Divino Salvador, 4",
    "sg:city":"Cortegana",
    "sg:orig_category":"Caf\u00c9s, Bares, Cervecer\u00cdas",
    "sg:phone":"+34 959 13 13 63",
    "sg:postcode":"21230",
    "sg:province":"Huelva",
    "wof:name":"Sociedad Gran Casino",
    "wof:placetype":"venue"
},
  "geometry": {"coordinates":[-6.8199281693,37.9086265564],"type":"Point"}
}