{
  "type": "Feature",
  "properties": {
    "addr:full":"Pl Hospital, 3 Palma Islas Baleares 07012",
    "addr:housenumber":"3",
    "addr:postcode":"07012",
    "iso:country":"ES",
    "sg:address":"Pl Hospital, 3",
    "sg:city":"Palma",
    "sg:orig_category":"Industria Qu\u00cdmica",
    "sg:phone":"+34 971 21 38 59",
    "sg:postcode":"07012",
    "sg:province":"Islas Baleares",
    "wof:name":"Govern Balear",
    "wof:placetype":"venue"
},
  "geometry": {"coordinates":[2.6470680237,39.5742607117],"type":"Point"}
}