{
  "type": "Feature",
  "properties": {
    "iso:country":"ES",
    "sg:address":"Pte. Heras, 17",
    "sg:city":"La Ca\u00f1ada",
    "sg:orig_category":"Carnicer\u00cdas, Carnicer\u00cdas",
    "sg:phone":"+34 961 32 01 35",
    "sg:postcode":"46182",
    "sg:province":"Valencia",
    "wof:name":"Eugenio Sanchez Murciano S.l.",
    "wof:placetype":"venue"
},
  "geometry": {"coordinates":[-0.4852339923,39.5221443176],"type":"Point"}
}