{
  "type": "Feature",
  "properties": {
    "iso:country":"ES",
    "sg:address":"Calle de Travesia, 18",
    "sg:city":"Navales",
    "sg:orig_category":"Carnicer\u00cdas, Carnicer\u00cdas",
    "sg:phone":"+34 923 37 04 98",
    "sg:postcode":"37880",
    "sg:province":"Salamanca",
    "wof:name":"Marcos Sanchez Mario",
    "wof:placetype":"venue"
},
  "geometry": {"coordinates":[-5.4801311493,40.7874412537],"type":"Point"}
}