{
  "type": "Feature",
  "properties": {
    "iso:country":"ES",
    "sg:address":"Avda Deportista Miriam Blasco, 14",
    "sg:city":"Alacant",
    "sg:classifiers":[
        {
            "category":"Autos & Motor Vehicles",
            "subcategory":"Automobile Sales",
            "type":"Retail Goods"
        }
    ],
    "sg:phone":"+34 965 26 95 39",
    "sg:postcode":"03016",
    "sg:province":"Alicante",
    "wof:name":"Lopez-cozar Muoz Luis",
    "wof:placetype":"venue"
},
  "geometry": {"coordinates":[-0.4350070059,38.3689193726],"type":"Point"}
}