{
  "type": "Feature",
  "properties": {
    "addr:full":"Calle de Lopez De Hoyos, 482 Madrid Madrid 28043",
    "addr:housenumber":"482",
    "addr:postcode":"28043",
    "addr:street":"Calle De Lopez De Hoyos",
    "iso:country":"ES",
    "sg:address":"Calle de Lopez De Hoyos, 482",
    "sg:city":"Madrid",
    "sg:orig_category":"Agencias De Viajes",
    "sg:phone":"+34 913 81 53 92",
    "sg:postcode":"28043",
    "sg:province":"Madrid",
    "wof:name":"Viajes Piscis S.l.",
    "wof:placetype":"venue"
},
  "geometry": {"coordinates":[-3.6493909359,40.4720954895],"type":"Point"}
}