{
  "type": "Feature",
  "properties": {
    "addr:full":"Pase Pereda, 33 Santander Cantabria 39004",
    "addr:housenumber":"33",
    "addr:postcode":"39004",
    "addr:street":"Pereda",
    "iso:country":"ES",
    "sg:address":"Pase Pereda, 33",
    "sg:city":"Santander",
    "sg:orig_category":"Agencias De Viajes",
    "sg:phone":"+34 942 36 71 10",
    "sg:postcode":"39004",
    "sg:province":"Cantabria",
    "wof:name":"Viajes Mesana S. A.",
    "wof:placetype":"venue"
},
  "geometry": {"coordinates":[-3.7986130714,43.462387085],"type":"Point"}
}