{
  "type": "Feature",
  "properties": {
    "iso:country":"ES",
    "sg:address":"Calle de Pintor Velazquez (del), 77",
    "sg:city":"Mostoles",
    "sg:orig_category":"Alquiler De V\u00cddeo",
    "sg:phone":"+34 916 14 70 04",
    "sg:postcode":"28935",
    "sg:province":"Madrid",
    "wof:name":"Euromar Credito S.l.",
    "wof:placetype":"venue"
},
  "geometry": {"coordinates":[-3.8793349266,40.3199806213],"type":"Point"}
}