{
  "type": "Feature",
  "properties": {
    "addr:full":"Avgd Morera, 16 Badalona Barcelona 08915",
    "addr:housenumber":"16",
    "addr:postcode":"08915",
    "addr:street":"Morera",
    "iso:country":"ES",
    "sg:address":"Avgd Morera, 16",
    "sg:city":"Badalona",
    "sg:orig_category":"Carnicer\u00cdas, Carnicer\u00cdas",
    "sg:phone":"+34 933 95 06 04",
    "sg:postcode":"08915",
    "sg:province":"Barcelona",
    "wof:name":"Rey Segura Caterina",
    "wof:placetype":"venue"
},
  "geometry": {"coordinates":[2.2485098839,41.4601631165],"type":"Point"}
}