{
  "type": "Feature",
  "properties": {
    "iso:country":"ES",
    "sg:address":"Psaj Doctor Serra, 27",
    "sg:city":"Valencia",
    "sg:orig_category":"Comerciantes Al Por Mayor De Vinos, Licores Y Alcoholes",
    "sg:phone":"+34 963 51 35 08",
    "sg:postcode":"46004",
    "sg:province":"Valencia",
    "wof:name":"Suria Gimenez Victoria",
    "wof:placetype":"venue"
},
  "geometry": {"coordinates":[-0.3754689991,39.4658699036],"type":"Point"}
}