{
  "type": "Feature",
  "properties": {
    "addr:full":"Carr Portal, 5 Palau-sator Girona 17256",
    "addr:housenumber":"5",
    "addr:postcode":"17256",
    "addr:street":"Carr Portal",
    "iso:country":"ES",
    "sg:address":"Carr Portal, 5",
    "sg:city":"Palau-sator",
    "sg:orig_category":"Reposter\u00cdas",
    "sg:phone":"+34 972 63 40 39",
    "sg:postcode":"17256",
    "sg:province":"Girona",
    "wof:name":"Oliver Llonch Mariano",
    "wof:placetype":"venue"
},
  "geometry": {"coordinates":[3.1482629776,41.9678573608],"type":"Point"}
}