{
  "type": "Feature",
  "properties": {
    "iso:country":"ES",
    "sg:address":"Calle de Barcelona, 14",
    "sg:city":"Puerto",
    "sg:orig_category":"Cl\u00cdnicas M\u00c9dicas",
    "sg:phone":"+34 962 68 04 85",
    "sg:postcode":"46520",
    "sg:province":"Valencia",
    "wof:name":"Clinica Antares S.l.",
    "wof:placetype":"venue"
},
  "geometry": {"coordinates":[-0.2247354984,39.6652526855],"type":"Point"}
}