{
  "type": "Feature",
  "properties": {
    "iso:country":"ES",
    "sg:address":"Pg Muntanya, 64",
    "sg:city":"Granollers",
    "sg:orig_category":"Muebles, Minoristas",
    "sg:phone":"+34 938 70 80 08",
    "sg:postcode":"08402",
    "sg:province":"Barcelona",
    "wof:name":"Mestre Planas Jose Maria",
    "wof:placetype":"venue"
},
  "geometry": {"coordinates":[2.293462038,41.606918335],"type":"Point"}
}