{
  "type": "Feature",
  "properties": {
    "addr:full":"Avda Cesareo Alierta, 9 Zaragoza Zaragoza 50008",
    "addr:housenumber":"9",
    "addr:postcode":"50008",
    "addr:street":"Avda Cesareo Alierta",
    "iso:country":"ES",
    "sg:address":"Avda Cesareo Alierta, 9",
    "sg:city":"Zaragoza",
    "sg:orig_category":"Asociaciones Y Clubs Deportivos",
    "sg:phone":"+34 976 48 12 66",
    "sg:postcode":"50008",
    "sg:province":"Zaragoza",
    "wof:name":"Explotacion Centros Dream Gym",
    "wof:placetype":"venue"
},
  "geometry": {"coordinates":[-0.8778010011,41.6457138062],"type":"Point"}
}