{
  "type": "Feature",
  "properties": {
    "addr:full":"Calle de Goya, 12 Muel Zaragoza 50450",
    "addr:housenumber":"12",
    "addr:postcode":"50450",
    "addr:street":"Calle De Goya",
    "iso:country":"ES",
    "sg:address":"Calle de Goya, 12",
    "sg:city":"Muel",
    "sg:orig_category":"Cer\u00c1mica Art\u00cdstica Y Decorativa",
    "sg:phone":"+34 976 14 04 25",
    "sg:postcode":"50450",
    "sg:province":"Zaragoza",
    "wof:name":"Vidal Marti Joaquin",
    "wof:placetype":"venue"
},
  "geometry": {"coordinates":[-1.0848089457,41.4700737],"type":"Point"}
}