{
  "type": "Feature",
  "properties": {
    "addr:full":"Carr Enric Borras, 31 Badalona Barcelona 08912",
    "addr:housenumber":"31",
    "addr:postcode":"08912",
    "addr:street":"Carr Enric Borras",
    "iso:country":"ES",
    "sg:address":"Carr Enric Borras, 31",
    "sg:city":"Badalona",
    "sg:orig_category":"Asesor\u00cda Sobre Comunicaci\u00d3n De Empresas",
    "sg:phone":"+34 934 64 30 30",
    "sg:postcode":"08912",
    "sg:province":"Barcelona",
    "wof:name":"Guira'dos Assessor S.l.",
    "wof:placetype":"venue"
},
  "geometry": {"coordinates":[2.2462799549,41.4464874268],"type":"Point"}
}