{
  "type": "Feature",
  "properties": {
    "addr:full":"Pg Baro De Viver, 53 Argentona Barcelona 08310",
    "addr:housenumber":"53",
    "addr:postcode":"08310",
    "addr:street":"Pg Baro De Viver",
    "iso:country":"ES",
    "sg:address":"Pg Baro De Viver, 53",
    "sg:city":"Argentona",
    "sg:orig_category":"Agencias Y Agentes Comerciales, Representantes",
    "sg:phone":"+34 937 56 10 95",
    "sg:postcode":"08310",
    "sg:province":"Barcelona",
    "wof:name":"Joan Navarro I Cia S.c.p.",
    "wof:placetype":"venue"
},
  "geometry": {"coordinates":[2.3972458839,41.5499191284],"type":"Point"}
}