{
  "type": "Feature",
  "properties": {
    "addr:full":"Calle de Pintor Oliet, 2 Vinaros Castell\u00f3n 12500",
    "addr:housenumber":"2",
    "addr:postcode":"12500",
    "addr:street":"Calle De Pintor Oliet",
    "iso:country":"ES",
    "sg:address":"Calle de Pintor Oliet, 2",
    "sg:city":"Vinaros",
    "sg:orig_category":"Arquitectos",
    "sg:phone":"+34 964 45 37 38",
    "sg:postcode":"12500",
    "sg:province":"Castell\u00f3n",
    "wof:name":"Sebastia Rallo Javier",
    "wof:placetype":"venue"
},
  "geometry": {"coordinates":[0.4738050103,40.4711990356],"type":"Point"}
}