{
  "type": "Feature",
  "properties": {
    "iso:country":"ES",
    "sg:address":"Calle de Capitan Almeida, 26",
    "sg:city":"Oviedo",
    "sg:orig_category":"Reposter\u00cdas",
    "sg:phone":"+34 985 22 31 08",
    "sg:postcode":"33009",
    "sg:province":"Asturias",
    "wof:name":"Alvarez Gonzalez Alfredo",
    "wof:placetype":"venue"
},
  "geometry": {"coordinates":[-5.8417563438,43.3559875488],"type":"Point"}
}