{
  "type": "Feature",
  "properties": {
    "addr:full":"Ctra. Jaen, Km. 0790,0 Parque Del Cubillas Granada 18220",
    "addr:postcode":"18220",
    "addr:street":"Ctra. Jaen Km. 0790,0 Parque Del Cubillas",
    "iso:country":"ES",
    "sg:address":"Ctra. Jaen, Km. 0790,0",
    "sg:city":"Parque Del Cubillas",
    "sg:orig_category":"Empresas De Electricidad En General",
    "sg:phone":"+34 958 34 06 87",
    "sg:postcode":"18220",
    "sg:province":"Granada",
    "wof:name":"Distribuidora Electrica Bermejales S.a.",
    "wof:placetype":"venue"
},
  "geometry": {"coordinates":[-3.6585440636,37.2332839966],"type":"Point"}
}