{
  "type": "Feature",
  "properties": {
    "addr:full":"Carrer de Mare De Deu Dels Desemparats, 51 Hospitalet Llobregat Barcelona 08903",
    "addr:housenumber":"51",
    "addr:postcode":"08903",
    "addr:street":"Carrer De Mare De Deu;Desemparats",
    "iso:country":"ES",
    "sg:address":"Carrer de Mare De Deu Dels Desemparats, 51",
    "sg:city":"Hospitalet Llobregat",
    "sg:orig_category":"Fabricaci\u00d3n, Importaci\u00d3n De L\u00c1mparas Y Bombillas",
    "sg:phone":"+34 934 49 62 36",
    "sg:postcode":"08903",
    "sg:province":"Barcelona",
    "wof:name":"Sanvicens Mas Juan",
    "wof:placetype":"venue"
},
  "geometry": {"coordinates":[2.1234910488,41.3713302612],"type":"Point"}
}