{
  "type": "Feature",
  "properties": {
    "addr:full":"Carrer de Santalo, 156 Barcelona Barcelona 08021",
    "addr:housenumber":"156",
    "addr:postcode":"08021",
    "addr:street":"Carrer De Santalo",
    "iso:country":"ES",
    "sg:address":"Carrer de Santalo, 156",
    "sg:city":"Barcelona",
    "sg:orig_category":"Bisuter\u00cda, Joyer\u00cda, Relojer\u00cda (al Por Menor)",
    "sg:phone":"+34 932 40 00 35",
    "sg:postcode":"08021",
    "sg:province":"Barcelona",
    "wof:name":"Torres Pla Joaquin",
    "wof:placetype":"venue"
},
  "geometry": {"coordinates":[2.1393220425,41.4010543823],"type":"Point"}
}