{
  "type": "Feature",
  "properties": {
    "iso:country":"ES",
    "sg:address":"Calle de Santa Ursula, 6",
    "sg:city":"Toledo",
    "sg:orig_category":"Artesan\u00cda",
    "sg:phone":"+34 925 25 10 54",
    "sg:postcode":"45002",
    "sg:province":"Toledo",
    "wof:name":"Serrano Ligero Asuncion",
    "wof:placetype":"venue"
},
  "geometry": {"coordinates":[-4.026517868,39.8561782837],"type":"Point"}
}