{
  "type": "Feature",
  "properties": {
    "addr:full":"Luga Eiris De Arriba, S/n Eiris De Arriba A Coru\u00f1a 15009",
    "addr:housenumber":"s / n;corun\u0303a",
    "addr:postcode":"15009",
    "addr:street":"Arriba;Arriba",
    "iso:country":"ES",
    "sg:address":"Luga Eiris De Arriba, S/n",
    "sg:city":"Eiris De Arriba",
    "sg:orig_category":"Ense\u00d1anza, Formaci\u00d3n Profesional: Aprendizaje",
    "sg:phone":"+34 981 17 45 23",
    "sg:postcode":"15009",
    "sg:province":"A Coru\u00f1a",
    "wof:name":"Xunta De Galicia Red Privada",
    "wof:placetype":"venue"
},
  "geometry": {"coordinates":[-8.1520986557,43.4764251709],"type":"Point"}
}