{
  "type": "Feature",
  "properties": {
    "addr:full":"Ptge. El Moli, S/n S. Joan Abadesses Girona 17860",
    "addr:housenumber":"s",
    "addr:postcode":"17860",
    "addr:street":"/ N S. Joan Abadesses",
    "iso:country":"ES",
    "sg:address":"Ptge. El Moli, S/n",
    "sg:city":"S. Joan Abadesses",
    "sg:orig_category":"Producci\u00d3n, Venta De Productos De Agricultura Biol\u00d3gica",
    "sg:phone":"+34 972 72 05 88",
    "sg:postcode":"17860",
    "sg:province":"Girona",
    "wof:name":"Ramaderes Mas Moli S.l.",
    "wof:placetype":"venue"
},
  "geometry": {"coordinates":[2.2854809761,42.2338752747],"type":"Point"}
}