{
  "type": "Feature",
  "properties": {
    "addr:full":"Calle de Cortijo Roscas, S/n Padul Granada 18640",
    "addr:housenumber":"s",
    "addr:postcode":"18640",
    "addr:street":"Calle De Cortijo Roscas;/ N",
    "iso:country":"ES",
    "sg:address":"Calle de Cortijo Roscas, S/n",
    "sg:city":"Padul",
    "sg:orig_category":"Refiner\u00cdas De Petr\u00d3leo",
    "sg:phone":"+34 958 77 40 13",
    "sg:postcode":"18640",
    "sg:province":"Granada",
    "wof:name":"Combustibles Padul S.l.",
    "wof:placetype":"venue"
},
  "geometry": {"coordinates":[-3.6333920956,37.0266571045],"type":"Point"}
}