{
  "type": "Feature",
  "properties": {
    "iso:country":"ES",
    "sg:address":"Carrer de Esglesia (de L'), 5",
    "sg:city":"Salou",
    "sg:orig_category":"Asesor\u00cda De Formaci\u00d3n Y Gesti\u00d3n De Personal",
    "sg:phone":"+34 977 38 57 17",
    "sg:postcode":"43840",
    "sg:province":"Tarragona",
    "wof:name":"Asesoria Laboral Concha S.l",
    "wof:placetype":"venue"
},
  "geometry": {"coordinates":[1.1304507256,41.0759849548],"type":"Point"}
}