{
  "type": "Feature",
  "properties": {
    "addr:full":"Carrer de Alfred Opisso (d'), 3 Tarragona Tarragona 43002",
    "addr:housenumber":"3",
    "addr:postcode":"43002",
    "addr:street":"Carrer De Alfred Opisso D '",
    "iso:country":"ES",
    "sg:address":"Carrer de Alfred Opisso (d'), 3",
    "sg:city":"Tarragona",
    "sg:orig_category":"Guarder\u00cdas",
    "sg:phone":"+34 977 22 62 16",
    "sg:postcode":"43002",
    "sg:province":"Tarragona",
    "wof:name":"Llar D'infants Edelweis S.coop.c.l.",
    "wof:placetype":"venue"
},
  "geometry": {"coordinates":[1.2540030479,41.120300293],"type":"Point"}
}