{
  "type": "Feature",
  "properties": {
    "iso:country":"ES",
    "sg:address":"Calle de Pergolas, 1",
    "sg:city":"Marmolejo",
    "sg:orig_category":"Farmacias",
    "sg:phone":"+34 953 54 00 07",
    "sg:postcode":"23770",
    "sg:province":"Ja\u00e9n",
    "wof:name":"Farmacia Montiel C.b.",
    "wof:placetype":"venue"
},
  "geometry": {"coordinates":[-4.1707258224,38.0434188843],"type":"Point"}
}