{
  "type": "Feature",
  "properties": {
    "iso:country":"ES",
    "sg:address":"Camino Del Pilon, 133",
    "sg:city":"Zaragoza",
    "sg:orig_category":"Instalaci\u00d3n De Aspiraci\u00d3n De Gases Y Humos",
    "sg:phone":"+34 976 31 99 33",
    "sg:postcode":"50011",
    "sg:province":"Zaragoza",
    "wof:name":"Cano Llucia Jose Luis",
    "wof:placetype":"venue"
},
  "geometry": {"coordinates":[-0.9438260198,41.6587638855],"type":"Point"}
}