{
  "type": "Feature",
  "properties": {
    "addr:full":"Ctra Circunvalacion Sector 4, S/n Santa Maria Del Paramo Le\u00f3n 24240",
    "addr:housenumber":"s / n",
    "addr:postcode":"24240",
    "addr:street":"Ctra Circunvalacion Sector 4",
    "iso:country":"ES",
    "sg:address":"Ctra Circunvalacion Sector 4, S/n",
    "sg:city":"Santa Maria Del Paramo",
    "sg:orig_category":"Perfumer\u00cda Y Cosm\u00c9tica (fabricaci\u00d3n, Al Por Mayor)",
    "sg:phone":"+34 987 68 70 01",
    "sg:postcode":"24240",
    "sg:province":"Le\u00f3n",
    "wof:name":"Jinjer Balsam S.l.",
    "wof:placetype":"venue"
},
  "geometry": {"coordinates":[-5.7487740517,42.3562965393],"type":"Point"}
}