{
  "type": "Feature",
  "properties": {
    "iso:country":"ES",
    "sg:address":"Calle de Daniel Blanxart, 27",
    "sg:city":"Malaga",
    "sg:orig_category":"Electricidad: Instaladores",
    "sg:phone":"+34 952 24 33 23",
    "sg:postcode":"29006",
    "sg:province":"M\u00e1laga",
    "wof:name":"Fernandez Garcia Simon",
    "wof:placetype":"venue"
},
  "geometry": {"coordinates":[-4.4888939857,36.7079315186],"type":"Point"}
}