{
  "type": "Feature",
  "properties": {
    "addr:full":"Praz Callao, 25 Ferrol La Coru\u00f1a 15402",
    "addr:housenumber":"25",
    "addr:postcode":"15402",
    "addr:street":"Callao;La Corun\u0303A",
    "iso:country":"ES",
    "sg:address":"Praz Callao, 25",
    "sg:city":"Ferrol",
    "sg:orig_category":"Arquitectos",
    "sg:phone":"+34 981 35 02 16",
    "sg:postcode":"15402",
    "sg:province":"La Coru\u00f1a",
    "wof:name":"Anta Arquitectos, S.c.",
    "wof:placetype":"venue"
},
  "geometry": {"coordinates":[-8.231552124,43.4819526672],"type":"Point"}
}