{
  "type": "Feature",
  "properties": {
    "iso:country":"ES",
    "sg:address":"Avda Mediterraneo, 72",
    "sg:city":"Gran Alacant",
    "sg:orig_category":"\u00d3ptica: Instrumentos (fabricaci\u00d3n)",
    "sg:phone":"+34 966 69 88 02",
    "sg:postcode":"03130",
    "sg:province":"Alicante",
    "wof:name":"The Brave Mole S.l.",
    "wof:placetype":"venue"
},
  "geometry": {"coordinates":[-0.5578309894,38.2048950195],"type":"Point"}
}