{
  "type": "Feature",
  "properties": {
    "addr:full":"Calle de Miguel Iscar, 16 Valladolid Valladolid 47001",
    "addr:housenumber":"16",
    "addr:postcode":"47001",
    "addr:street":"Calle De Miguel Iscar",
    "iso:country":"ES",
    "sg:address":"Calle de Miguel Iscar, 16",
    "sg:city":"Valladolid",
    "sg:orig_category":"Abogados",
    "sg:phone":"+34 983 21 93 34",
    "sg:postcode":"47001",
    "sg:province":"Valladolid",
    "sg:website":"www.avatahispania.com",
    "wof:name":"Jesa Avata Valladolid S.l.",
    "wof:placetype":"venue"
},
  "geometry": {"coordinates":[-4.7259731293,41.6485176086],"type":"Point"}
}