{
  "type": "Feature",
  "properties": {
    "iso:country":"ES",
    "sg:address":"Calle de Punta De Los Molinillos, 26",
    "sg:city":"Urbanizacion Ca\u00e7ada Del Rio",
    "sg:orig_category":"Inmobiliaria (agencias)",
    "sg:phone":"+34 928 87 63 88",
    "sg:postcode":"35627",
    "sg:province":"Las Palmas",
    "wof:name":"Iberhouse Investment Ofice S.l.",
    "wof:placetype":"venue"
},
  "geometry": {"coordinates":[-14.1530008316,28.1882152557],"type":"Point"}
}