{
  "type": "Feature",
  "properties": {
    "iso:country":"ES",
    "sg:address":"Calle de Andres Lopez Palmeiro, 29",
    "sg:city":"Ferreira",
    "sg:orig_category":"Supermercados Y Hipermercados",
    "sg:phone":"+34 982 57 40 14",
    "sg:postcode":"27770",
    "sg:province":"Lugo",
    "wof:name":"Reigosa Balseiro Isabel",
    "wof:placetype":"venue"
},
  "geometry": {"coordinates":[-7.4817819595,43.5736885071],"type":"Point"}
}