{
  "type": "Feature",
  "properties": {
    "addr:full":"Rua B, 58 Lalin Pontevedra 36500",
    "addr:housenumber":"58",
    "addr:postcode":"36500",
    "addr:street":"Rua B",
    "iso:country":"ES",
    "sg:address":"Rua B, 58",
    "sg:city":"Lalin",
    "sg:orig_category":"Electrodom\u00c9sticos (al Por Menor)",
    "sg:phone":"+34 986 78 16 65",
    "sg:postcode":"36500",
    "sg:province":"Pontevedra",
    "wof:name":"Taboada Gomez Jose Ramon",
    "wof:placetype":"venue"
},
  "geometry": {"coordinates":[-8.1081991196,42.6615600586],"type":"Point"}
}