{
  "type": "Feature",
  "properties": {
    "addr:full":"Calle de Lora, 23 Sanlucar Mayor Sevilla 41800",
    "addr:housenumber":"23",
    "addr:postcode":"41800",
    "addr:street":"Calle De Lora",
    "iso:country":"ES",
    "sg:address":"Calle de Lora, 23",
    "sg:city":"Sanlucar Mayor",
    "sg:orig_category":"Pescader\u00cdas (al Por Menor)",
    "sg:phone":"+34 955 70 12 48",
    "sg:postcode":"41800",
    "sg:province":"Sevilla",
    "wof:name":"Garcia Casta\u00f1o Maria Del Carmen",
    "wof:placetype":"venue"
},
  "geometry": {"coordinates":[-6.2005162239,37.3824996948],"type":"Point"}
}