{
  "type": "Feature",
  "properties": {
    "addr:full":"Calle de Salustiano Olozaga, 6 Madrid Madrid 28001",
    "addr:housenumber":"6",
    "addr:postcode":"28001",
    "addr:street":"Calle De Salustiano Olozaga",
    "iso:country":"ES",
    "sg:address":"Calle de Salustiano Olozaga, 6",
    "sg:city":"Madrid",
    "sg:orig_category":"Aislamiento El\u00c9ctrico",
    "sg:phone":"+34 914 35 02 31",
    "sg:postcode":"28001",
    "sg:province":"Madrid",
    "wof:name":"Tecnolamina S.a.l.",
    "wof:placetype":"venue"
},
  "geometry": {"coordinates":[-3.6912550926,40.4208145142],"type":"Point"}
}