{
  "type": "Feature",
  "properties": {
    "iso:country":"ES",
    "sg:address":"Av Ramon Salomon, 19",
    "sg:city":"Ulldecona",
    "sg:orig_category":"Laboratorios Y Trabajos De Fotograf\u00cda, V\u00cddeo Y Cine",
    "sg:phone":"+34 977 57 32 15",
    "sg:postcode":"43550",
    "sg:province":"Tarragona",
    "wof:name":"Videofoto Millan S.l.",
    "wof:placetype":"venue"
},
  "geometry": {"coordinates":[0.4433000088,40.5985145569],"type":"Point"}
}