{
  "type": "Feature",
  "properties": {
    "addr:full":"Avda Extremadura, 1 Alconchel Badajoz 06131",
    "addr:housenumber":"1",
    "addr:postcode":"06131",
    "addr:street":"Avda Extremadura",
    "iso:country":"ES",
    "sg:address":"Avda Extremadura, 1",
    "sg:city":"Alconchel",
    "sg:orig_category":"Agentes, Concesionarios Y Sucursales De Veh\u00cdculos",
    "sg:phone":"+34 924 42 02 02",
    "sg:postcode":"06131",
    "sg:province":"Badajoz",
    "wof:name":"Nogales Mauricio Alfredo",
    "wof:placetype":"venue"
},
  "geometry": {"coordinates":[-7.0701298714,38.5168800354],"type":"Point"}
}