{
  "type": "Feature",
  "properties": {
    "addr:full":"Carrer de Casta\u00d1os, 68 Mataro Barcelona 08302",
    "addr:housenumber":"68",
    "addr:postcode":"08302",
    "addr:street":"Carrer De Castan\u0303Os",
    "iso:country":"ES",
    "sg:address":"Carrer de Casta\u00d1os, 68",
    "sg:city":"Mataro",
    "sg:orig_category":"Inmobiliaria (agencias)",
    "sg:phone":"+34 937 99 59 21",
    "sg:postcode":"08302",
    "sg:province":"Barcelona",
    "wof:name":"Unimo S.a.",
    "wof:placetype":"venue"
},
  "geometry": {"coordinates":[2.4388999939,41.5349273682],"type":"Point"}
}