{
  "type": "Feature",
  "properties": {
    "iso:country":"ES",
    "sg:address":"Calle de Luciana Fernandez, 9",
    "sg:city":"Ponferrada",
    "sg:orig_category":"Negocio De Madera",
    "sg:phone":"+34 987 41 07 86",
    "sg:postcode":"24400",
    "sg:province":"Le\u00f3n",
    "wof:name":"Sal Gonzalez Enrique",
    "wof:placetype":"venue"
},
  "geometry": {"coordinates":[-6.5975728035,42.5460968018],"type":"Point"}
}