{
  "type": "Feature",
  "properties": {
    "iso:country":"ES",
    "sg:address":"Calle de Idioma Esperanto, 20",
    "sg:city":"Madrid",
    "sg:orig_category":"Fabricaci\u00d3n, Importaci\u00d3n, Venta De Material De Telefon\u00cda, Peritelefon\u00cda",
    "sg:phone":"+34 913 06 36 00",
    "sg:postcode":"28017",
    "sg:province":"Madrid",
    "wof:name":"Tecnicom S.l.",
    "wof:placetype":"venue"
},
  "geometry": {"coordinates":[-3.6268715858,40.4186630249],"type":"Point"}
}