{
  "type": "Feature",
  "properties": {
    "addr:full":"Calle de Padre Salaverri, 1 Burgos Burgos 09002",
    "addr:housenumber":"1",
    "addr:postcode":"09002",
    "addr:street":"Calle De Padre Salaverri",
    "iso:country":"ES",
    "sg:address":"Calle de Padre Salaverri, 1",
    "sg:city":"Burgos",
    "sg:orig_category":"Cajas De Ahorro",
    "sg:phone":"+34 947 27 80 01",
    "sg:postcode":"09002",
    "sg:province":"Burgos",
    "wof:name":"Caja De Ahorros Del Circulo Catolico Obrero De Burgos",
    "wof:placetype":"venue"
},
  "geometry": {"coordinates":[-3.6938409805,42.3379096985],"type":"Point"}
}