{
  "type": "Feature",
  "properties": {
    "iso:country":"ES",
    "sg:address":"Calle de Gonzalez Gallarza, 5",
    "sg:city":"Ezcaray",
    "sg:orig_category":"Comidas Por Encargo, Organizaci\u00d3n De Recepciones",
    "sg:phone":"+34 941 35 45 83",
    "sg:postcode":"26280",
    "sg:province":"La Rioja",
    "wof:name":"Garcia Rodriguez Manuel",
    "wof:placetype":"venue"
},
  "geometry": {"coordinates":[-3.0145199299,42.3247032166],"type":"Point"}
}