{
  "type": "Feature",
  "properties": {
    "iso:country":"ES",
    "sg:address":"Calle de Fuente Del Real, 47",
    "sg:city":"Gijon",
    "sg:classifiers":[
        {
            "category":"Autos & Motor Vehicles",
            "subcategory":"Automobile Sales",
            "type":"Retail Goods"
        }
    ],
    "sg:phone":"+34 985 14 24 22",
    "sg:postcode":"33209",
    "sg:province":"Asturias",
    "wof:name":"Acebal Porto Jose Javier",
    "wof:placetype":"venue"
},
  "geometry": {"coordinates":[-5.6598343849,43.5315437317],"type":"Point"}
}