{
  "type": "Feature",
  "properties": {
    "iso:country":"ES",
    "sg:address":"Calle de Asturias, 9",
    "sg:city":"Gijon",
    "sg:orig_category":"Inform\u00c1tica, Ofim\u00c1tica (estudios, Asesor\u00cda, Ingenier\u00cda, Formaci\u00d3n)",
    "sg:phone":"+34 985 17 62 26",
    "sg:postcode":"33206",
    "sg:province":"Asturias",
    "wof:name":"Benchikh El Fegoun Souad",
    "wof:placetype":"venue"
},
  "geometry": {"coordinates":[-5.665307045,43.5400085449],"type":"Point"}
}