{
  "type": "Feature",
  "properties": {
    "addr:full":"Carrer de Jacint Verdaguer, 7 Martorell Barcelona 08760",
    "addr:housenumber":"7",
    "addr:postcode":"08760",
    "addr:street":"Carrer De Jacint Verdaguer",
    "iso:country":"ES",
    "sg:address":"Carrer de Jacint Verdaguer, 7",
    "sg:city":"Martorell",
    "sg:orig_category":"Empresarios",
    "sg:phone":"+34 937 74 04 09",
    "sg:postcode":"08760",
    "sg:province":"Barcelona",
    "wof:name":"Theressa Disseny S.l.",
    "wof:placetype":"venue"
},
  "geometry": {"coordinates":[1.914577961,41.4770622253],"type":"Point"}
}