{
  "type": "Feature",
  "properties": {
    "iso:country":"ES",
    "sg:address":"Carrer de Esteve Barange, 18",
    "sg:city":"Cardedeu",
    "sg:orig_category":"Fisioterapia",
    "sg:phone":"+34 938 71 37 48",
    "sg:postcode":"08440",
    "sg:province":"Barcelona",
    "wof:name":"Fisioterapias S.c.p.",
    "wof:placetype":"venue"
},
  "geometry": {"coordinates":[2.360599041,41.6380996704],"type":"Point"}
}