{
  "type": "Feature",
  "properties": {
    "addr:full":"Calle de Puntallana, 20 Madrid Madrid 28017",
    "addr:housenumber":"20",
    "addr:postcode":"madrid;28017",
    "addr:street":"Calle De Puntallana",
    "iso:country":"ES",
    "sg:address":"Calle de Puntallana, 20",
    "sg:city":"Madrid",
    "sg:orig_category":"Alimentaci\u00d3n Animal (fabricaci\u00d3n, Al Por Mayor)",
    "sg:phone":"+34 913 04 65 35",
    "sg:postcode":"28017",
    "sg:province":"Madrid",
    "wof:name":"Ruiz Ruiz Maria Yolanda",
    "wof:placetype":"venue"
},
  "geometry": {"coordinates":[-3.6324319839,40.4280738831],"type":"Point"}
}