{
  "type": "Feature",
  "properties": {
    "addr:full":"Carrer de Aribau, 20 Barcelona Barcelona 08011",
    "addr:housenumber":"20",
    "addr:postcode":"08011",
    "addr:street":"Carrer De Aribau",
    "iso:country":"ES",
    "sg:address":"Carrer de Aribau, 20",
    "sg:city":"Barcelona",
    "sg:orig_category":"Lencer\u00cda Femenina, Corseter\u00cda, Trajes De Ba\u00d1o (al Por Menor)",
    "sg:phone":"+34 934 53 18 44",
    "sg:postcode":"08011",
    "sg:province":"Barcelona",
    "wof:name":"Valle Antona Petra",
    "wof:placetype":"venue"
},
  "geometry": {"coordinates":[2.1618421078,41.3867263794],"type":"Point"}
}