{
  "type": "Feature",
  "properties": {
    "addr:full":"Calle de Astorga, 18 Salamanca Salamanca 37005",
    "addr:housenumber":"18",
    "addr:postcode":"37005",
    "addr:street":"Calle De Astorga",
    "iso:country":"ES",
    "sg:address":"Calle de Astorga, 18",
    "sg:city":"Salamanca",
    "sg:orig_category":"Promotores Constructores",
    "sg:phone":"+34 923 12 25 78",
    "sg:postcode":"37005",
    "sg:province":"Salamanca",
    "wof:name":"Construcciones Anclo S.l",
    "wof:placetype":"venue"
},
  "geometry": {"coordinates":[-5.6649727821,40.981136322],"type":"Point"}
}