{
  "type": "Feature",
  "properties": {
    "addr:full":"Av. Catalunya (b. Xiol), S/n Lli\u00e7a Vall Barcelona 08185",
    "addr:housenumber":"s",
    "addr:postcode":"08185",
    "addr:street":"Av. Catalunya B. Xiol;/ N;Vall Barcelona",
    "iso:country":"ES",
    "sg:address":"Av. Catalunya (b. Xiol), S/n",
    "sg:city":"Lli\u00e7a Vall",
    "sg:orig_category":"Audiovisuales (producci\u00d3n, Edici\u00d3n, Realizaci\u00d3n)",
    "sg:phone":"+34 938 43 72 53",
    "sg:postcode":"08185",
    "sg:province":"Barcelona",
    "wof:name":"Video Producciones Vacpag S.c.p.",
    "wof:placetype":"venue"
},
  "geometry": {"coordinates":[2.2362511158,41.5791702271],"type":"Point"}
}