{
  "type": "Feature",
  "properties": {
    "addr:full":"Avda Juventud (de La), 47 Priego Cordoba C\u00f3rdoba 14800",
    "addr:housenumber":"47",
    "addr:postcode":"14800",
    "addr:street":"Avda Juventud De La;Cordoba Co\u0301Rdoba",
    "iso:country":"ES",
    "sg:address":"Avda Juventud (de La), 47",
    "sg:city":"Priego Cordoba",
    "sg:orig_category":"Molduras, Junquillos, Listones Y Molduras Perforadas",
    "sg:phone":"+34 957 54 00 81",
    "sg:postcode":"14800",
    "sg:province":"C\u00f3rdoba",
    "wof:name":"Osuna Serrano Manuel",
    "wof:placetype":"venue"
},
  "geometry": {"coordinates":[-4.2073087692,37.4441795349],"type":"Point"}
}