{
  "type": "Feature",
  "properties": {
    "iso:country":"ES",
    "sg:address":"Ctra Las Cabezas-lebrija, Km. 0006,8",
    "sg:city":"Cabezas S. Juan",
    "sg:orig_category":"Casas Con Estructura De Madera",
    "sg:phone":"+34 955 89 80 19",
    "sg:postcode":"41730",
    "sg:province":"Sevilla",
    "wof:name":"Casas De Benitez Madera Y Construcciones S.l.",
    "wof:placetype":"venue"
},
  "geometry": {"coordinates":[-5.9365491867,36.9817962646],"type":"Point"}
}