{
  "type": "Feature",
  "properties": {
    "addr:full":"Avda Real De Pinto, 2 Madrid Madrid 28021",
    "addr:housenumber":"2",
    "addr:postcode":"28021",
    "addr:street":"Avda Real De Pinto",
    "iso:country":"ES",
    "sg:address":"Avda Real De Pinto, 2",
    "sg:city":"Madrid",
    "sg:orig_category":"Agentes, Concesionarios Y Sucursales De Veh\u00cdculos",
    "sg:phone":"+34 917 97 36 48",
    "sg:postcode":"28021",
    "sg:province":"Madrid",
    "wof:name":"Talleres Felix Labrada Cristobal S.l.",
    "wof:placetype":"venue"
},
  "geometry": {"coordinates":[-3.7063379288,40.3488388062],"type":"Point"}
}