{
  "type": "Feature",
  "properties": {
    "addr:full":"Ctra Vic, 35 Manresa Barcelona 08241",
    "addr:housenumber":"35",
    "addr:postcode":"08241",
    "addr:street":"Ctra Vic",
    "iso:country":"ES",
    "sg:address":"Ctra Vic, 35",
    "sg:city":"Manresa",
    "sg:orig_category":"Pintura, Barniz, Productos Asimilables (fabricaci\u00d3n, Al Por Mayor)",
    "sg:phone":"+34 938 73 01 21",
    "sg:postcode":"08241",
    "sg:province":"Barcelona",
    "wof:name":"Llados Torrens Montserrat",
    "wof:placetype":"venue"
},
  "geometry": {"coordinates":[1.8270790577,41.7269554138],"type":"Point"}
}