{
  "type": "Feature",
  "properties": {
    "addr:full":"Calle de Medina De Pomar, 22 Madrid Madrid 28042",
    "addr:housenumber":"22",
    "addr:postcode":"madrid;28042",
    "addr:street":"Calle De Medina De Pomar",
    "iso:country":"ES",
    "sg:address":"Calle de Medina De Pomar, 22",
    "sg:city":"Madrid",
    "sg:orig_category":"Fabricaci\u00d3n De Revestimientos De Suelos Pl\u00c1sticos Y De Goma",
    "sg:phone":"+34 913 29 44 62",
    "sg:postcode":"28042",
    "sg:province":"Madrid",
    "wof:name":"Aditivos Y Recubrimientos Tecnicos S.l.",
    "wof:placetype":"venue"
},
  "geometry": {"coordinates":[-3.5844430923,40.452129364],"type":"Point"}
}