{
  "type": "Feature",
  "properties": {
    "addr:full":"Avda Constitucion, 45 Narejos Murcia 30710",
    "addr:housenumber":"45",
    "addr:postcode":"30710",
    "addr:street":"Avda Constitucion",
    "iso:country":"ES",
    "sg:address":"Avda Constitucion, 45",
    "sg:city":"Narejos",
    "sg:orig_category":"Inmobiliaria (agencias)",
    "sg:phone":"+34 968 17 08 32",
    "sg:postcode":"30710",
    "sg:province":"Murcia",
    "wof:name":"Sarabia Martinez Amalia",
    "wof:placetype":"venue"
},
  "geometry": {"coordinates":[-0.8401150107,37.7570991516],"type":"Point"}
}