{
  "type": "Feature",
  "properties": {
    "addr:full":"Calle de Lopez De Hoyos, 182 Madrid Madrid 28002",
    "addr:housenumber":"182",
    "addr:postcode":"28002",
    "addr:street":"Calle De Lopez De Hoyos",
    "iso:country":"ES",
    "sg:address":"Calle de Lopez De Hoyos, 182",
    "sg:city":"Madrid",
    "sg:orig_category":"Complementos De Vestir (al Por Menor)",
    "sg:phone":"+34 914 16 06 59",
    "sg:postcode":"28002",
    "sg:province":"Madrid",
    "wof:name":"Calomardo Gutierrez Pilar",
    "wof:placetype":"venue"
},
  "geometry": {"coordinates":[-3.668915987,40.4474906921],"type":"Point"}
}