{
  "type": "Feature",
  "properties": {
    "addr:full":"Av Notari Alemany, 6 Magaluf Islas Baleares 07181",
    "addr:housenumber":"6",
    "addr:postcode":"07181",
    "addr:street":"Av Notari Alemany",
    "iso:country":"ES",
    "sg:address":"Av Notari Alemany, 6",
    "sg:city":"Magaluf",
    "sg:orig_category":"Art\u00cdculos De Regalo (al Por Menor)",
    "sg:phone":"+34 971 13 01 97",
    "sg:postcode":"07181",
    "sg:province":"Islas Baleares",
    "wof:name":"Bennasar Canoves Juana",
    "wof:placetype":"venue"
},
  "geometry": {"coordinates":[2.5313220024,39.503944397],"type":"Point"}
}