{
  "type": "Feature",
  "properties": {
    "iso:country":"ES",
    "sg:address":"Cami Alocs, Km. 0004,0",
    "sg:city":"Ferreries",
    "sg:orig_category":"Producci\u00d3n, Venta De Productos De Agricultura Biol\u00d3gica",
    "sg:phone":"+34 971 18 80 36",
    "sg:postcode":"07750",
    "sg:province":"Islas Baleares",
    "wof:name":"Son Abatzer S.r.m.",
    "wof:placetype":"venue"
},
  "geometry": {"coordinates":[4.0080771446,39.9823303223],"type":"Point"}
}