{
  "type": "Feature",
  "properties": {
    "addr:full":"Carrer de Calassan\u00c7 Duran, 144 Sabadell Barcelona 08203",
    "addr:housenumber":"144",
    "addr:postcode":"08203",
    "addr:street":"Carrer De Calassanc\u0327 Duran",
    "iso:country":"ES",
    "sg:address":"Carrer de Calassan\u00c7 Duran, 144",
    "sg:city":"Sabadell",
    "sg:orig_category":"Ingeniero De Sonido",
    "sg:phone":"+34 937 27 09 15",
    "sg:postcode":"08203",
    "sg:province":"Barcelona",
    "wof:name":"Ordaz Dominguez Roberto",
    "wof:placetype":"venue"
},
  "geometry": {"coordinates":[2.1178920269,41.5405960083],"type":"Point"}
}