{
  "type": "Feature",
  "properties": {
    "iso:country":"ES",
    "sg:address":"Calle de Marques De Santa Ana, 11",
    "sg:city":"Madrid",
    "sg:orig_category":"Caf\u00c9s, Bares, Cervecer\u00cdas",
    "sg:phone":"+34 915 21 49 70",
    "sg:postcode":"28004",
    "sg:province":"Madrid",
    "wof:name":"Leoui Club S.l.",
    "wof:placetype":"venue"
},
  "geometry": {"coordinates":[-3.7051401138,40.424446106],"type":"Point"}
}