{
  "type": "Feature",
  "properties": {
    "addr:full":"Pl. Espa\u00f1a, 1 Jarandilla Vera C\u00e1ceres 10450",
    "addr:housenumber":"1",
    "addr:postcode":"10450",
    "addr:street":"Pl. Espan\u0303A;Ca\u0301Ceres",
    "iso:country":"ES",
    "sg:address":"Pl. Espa\u00f1a, 1",
    "sg:city":"Jarandilla Vera",
    "sg:orig_category":"Oficinas De Turismo, Asociaciones De Iniciativa",
    "sg:phone":"+34 927 56 00 10",
    "sg:postcode":"10450",
    "sg:province":"C\u00e1ceres",
    "wof:name":"Ayuntamiento De Jarandilla De La Vera",
    "wof:placetype":"venue"
},
  "geometry": {"coordinates":[-5.6036658287,40.121055603],"type":"Point"}
}