{
  "type": "Feature",
  "properties": {
    "addr:full":"Calle de Nogal, 37 Leganes Madrid 28918",
    "addr:housenumber":"37",
    "addr:postcode":"28918",
    "addr:street":"Calle De Nogal",
    "iso:country":"ES",
    "sg:address":"Calle de Nogal, 37",
    "sg:city":"Leganes",
    "sg:orig_category":"Estudios, Instalaci\u00d3n De Climatizaci\u00d3n",
    "sg:phone":"+34 916 93 95 50",
    "sg:postcode":"28918",
    "sg:province":"Madrid",
    "wof:name":"Climatizaciones Y Aislamientos Cordoba S.l.",
    "wof:placetype":"venue"
},
  "geometry": {"coordinates":[-3.7742059231,40.3434257507],"type":"Point"}
}