{
  "type": "Feature",
  "properties": {
    "iso:country":"ES",
    "sg:address":"Calle de Juan Antonio Perez De Arellano, S/n",
    "sg:city":"Sesma",
    "sg:orig_category":"Electrodom\u00c9sticos (al Por Menor)",
    "sg:phone":"+34 948 69 81 78",
    "sg:postcode":"31293",
    "sg:province":"Navarra",
    "wof:name":"Bea Raon Javier",
    "wof:placetype":"venue"
},
  "geometry": {"coordinates":[-2.0842139721,42.4785308838],"type":"Point"}
}