{
  "type": "Feature",
  "properties": {
    "iso:country":"ES",
    "sg:address":"Carr Pintor Sorolla, 5",
    "sg:city":"Almussafes",
    "sg:orig_category":"Agencias Y Agentes Comerciales, Representantes",
    "sg:phone":"+34 961 78 10 90",
    "sg:postcode":"46440",
    "sg:province":"Valencia",
    "wof:name":"Sanchez Chaparro Jose",
    "wof:placetype":"venue"
},
  "geometry": {"coordinates":[-0.4107739925,39.2926559448],"type":"Point"}
}