{
  "type": "Feature",
  "properties": {
    "iso:country":"ES",
    "sg:address":"Calle de Portal, 12",
    "sg:city":"Fuentes Ebro",
    "sg:orig_category":"Molduras, Junquillos, Listones Y Molduras Perforadas",
    "sg:phone":"+34 976 16 04 05",
    "sg:postcode":"50740",
    "sg:province":"Zaragoza",
    "wof:name":"Cano-caballero Bolivar Modesto",
    "wof:placetype":"venue"
},
  "geometry": {"coordinates":[-0.6268740296,41.5112380981],"type":"Point"}
}