{
  "type": "Feature",
  "properties": {
    "iso:country":"ES",
    "sg:address":"Calle de Capuchinos, 4",
    "sg:city":"Borja",
    "sg:orig_category":"Reposter\u00cdas",
    "sg:phone":"+34 976 86 70 54",
    "sg:postcode":"50540",
    "sg:province":"Zaragoza",
    "wof:name":"Sanmartin Sanchez Juan Francisco",
    "wof:placetype":"venue"
},
  "geometry": {"coordinates":[-1.5289520025,41.8329086304],"type":"Point"}
}