{
  "type": "Feature",
  "properties": {
    "iso:country":"ES",
    "sg:address":"Av Comarques Catalanes, 32",
    "sg:city":"Mora D'ebre",
    "sg:orig_category":"Notarios",
    "sg:phone":"+34 977 40 26 65",
    "sg:postcode":"43740",
    "sg:province":"Tarragona",
    "wof:name":"Iracheta Undagoitia Jose Pablo",
    "wof:placetype":"venue"
},
  "geometry": {"coordinates":[1.2540999651,41.1169281006],"type":"Point"}
}