{
  "type": "Feature",
  "properties": {
    "iso:country":"ES",
    "sg:address":"Concepcion, 37",
    "sg:city":"Olvega",
    "sg:orig_category":"Peluquer\u00cdas, Peluquer\u00cda Mixta",
    "sg:phone":"+34 976 19 62 58",
    "sg:postcode":"42110",
    "sg:province":"Soria",
    "wof:name":"Villar Calvo Alfredo",
    "wof:placetype":"venue"
},
  "geometry": {"coordinates":[-1.9831990004,41.7797584534],"type":"Point"}
}