{
  "type": "Feature",
  "properties": {
    "iso:country":"ES",
    "sg:address":"Txaltxa-zelai Kalea, 8",
    "sg:city":"Eibar",
    "sg:orig_category":"Asociaciones, Organismos Culturales Y Socioeducativos",
    "sg:phone":"+34 943 20 71 53",
    "sg:postcode":"20600",
    "sg:province":"Guip\u00f9zcoa",
    "wof:name":"Sociedad Cultural Recreativa Bide Alde",
    "wof:placetype":"venue"
},
  "geometry": {"coordinates":[-2.4716260433,43.1828956604],"type":"Point"}
}