{
  "type": "Feature",
  "properties": {
    "iso:country":"ES",
    "sg:address":"Plaz Colina (la), 60",
    "sg:city":"Selaya",
    "sg:orig_category":"Reposter\u00cdas",
    "sg:phone":"+34 942 59 04 27",
    "sg:postcode":"39696",
    "sg:province":"Cantabria",
    "wof:name":"Panaderia Pasiega S.l.",
    "wof:placetype":"venue"
},
  "geometry": {"coordinates":[-3.8065640926,43.2147674561],"type":"Point"}
}