{
  "type": "Feature",
  "properties": {
    "iso:country":"ES",
    "sg:address":"Av Catalunya, 5",
    "sg:city":"Alfarras",
    "sg:orig_category":"Alimentaci\u00d3n General (al Por Menor)",
    "sg:phone":"+34 973 76 15 01",
    "sg:postcode":"25120",
    "sg:province":"Lleida",
    "wof:name":"Joravic S.c.p.",
    "wof:placetype":"venue"
},
  "geometry": {"coordinates":[0.5703470111,41.830280304],"type":"Point"}
}