{
  "type": "Feature",
  "properties": {
    "addr:full":"Carr Bonastruc De Porta, 15 Girona Girona 17001",
    "addr:housenumber":"15",
    "addr:postcode":"17001",
    "addr:street":"Carr Bonastruc De Porta",
    "iso:country":"ES",
    "sg:address":"Carr Bonastruc De Porta, 15",
    "sg:city":"Girona",
    "sg:orig_category":"Sindicatos Y Colegios Profesionales",
    "sg:phone":"+34 972 21 34 35",
    "sg:postcode":"17001",
    "sg:province":"Girona",
    "wof:name":"Associacio D'empreses De Noves Tecnologies De Girona Sl",
    "wof:placetype":"venue"
},
  "geometry": {"coordinates":[2.8197615147,41.9848175049],"type":"Point"}
}