{
  "type": "Feature",
  "properties": {
    "iso:country":"ES",
    "sg:address":"Calle de Guiomar Fernandez, 15",
    "sg:city":"Burgos",
    "sg:orig_category":"Cooperativas Agr\u00cdcolas",
    "sg:phone":"+34 947 22 55 04",
    "sg:postcode":"09006",
    "sg:province":"Burgos",
    "wof:name":"Cooperativa Avicola Y Ganadera De Burgos",
    "wof:placetype":"venue"
},
  "geometry": {"coordinates":[-3.6794369221,42.3605384827],"type":"Point"}
}