{
  "type": "Feature",
  "properties": {
    "addr:full":"Calle de Teodosio, 83 Sevilla Sevilla 41002",
    "addr:housenumber":"83",
    "addr:postcode":"41002",
    "addr:street":"Calle De Teodosio",
    "iso:country":"ES",
    "sg:address":"Calle de Teodosio, 83",
    "sg:city":"Sevilla",
    "sg:orig_category":"Agencias Y Agentes Comerciales, Representantes",
    "sg:phone":"+34 954 38 66 06",
    "sg:postcode":"41002",
    "sg:province":"Sevilla",
    "wof:name":"Tobaja Villegas Maria Jose",
    "wof:placetype":"venue"
},
  "geometry": {"coordinates":[-5.9973721504,37.3990478516],"type":"Point"}
}