{
  "type": "Feature",
  "properties": {
    "addr:full":"Calle de Lomo Quinto, 20 Galdar Las Palmas 35460",
    "addr:housenumber":"20",
    "addr:postcode":"35460",
    "addr:street":"Calle De Lomo Quinto",
    "iso:country":"ES",
    "sg:address":"Calle de Lomo Quinto, 20",
    "sg:city":"Galdar",
    "sg:orig_category":"Reposter\u00cdas",
    "sg:phone":"+34 928 88 19 25",
    "sg:postcode":"35460",
    "sg:province":"Las Palmas",
    "wof:name":"Rosario Padron Manuel Del",
    "wof:placetype":"venue"
},
  "geometry": {"coordinates":[-15.6577310562,28.1475143433],"type":"Point"}
}