{
  "type": "Feature",
  "properties": {
    "addr:full":"La Guapa, S/n La Mamola Granada 18750",
    "addr:housenumber":"s / n",
    "addr:postcode":"18750",
    "addr:street":"Guapa",
    "iso:country":"ES",
    "sg:address":"La Guapa, S/n",
    "sg:city":"La Mamola",
    "sg:orig_category":"Administradores De Bienes Y Delegados De Comunidades De Propietarios",
    "sg:phone":"+34 958 82 97 33",
    "sg:postcode":"18750",
    "sg:province":"Granada",
    "wof:name":"Orcrosa S.l.",
    "wof:placetype":"venue"
},
  "geometry": {"coordinates":[-3.3120748997,36.7582015991],"type":"Point"}
}