{
  "type": "Feature",
  "properties": {
    "addr:full":"Calle de Orotava La, 27 Malaga M\u00e1laga 29006",
    "addr:housenumber":"27",
    "addr:postcode":"29006",
    "addr:street":"Calle De Orotava La;Ma\u0301Laga",
    "iso:country":"ES",
    "sg:address":"Calle de Orotava La, 27",
    "sg:city":"Malaga",
    "sg:orig_category":"Bazares, Art\u00cdculos De Limpieza Y De Cocina (al Por Menor)",
    "sg:phone":"+34 952 34 30 60",
    "sg:postcode":"29006",
    "sg:province":"M\u00e1laga",
    "wof:name":"Todo 100 Sur S.l.",
    "wof:placetype":"venue"
},
  "geometry": {"coordinates":[-4.4763851166,36.7048606873],"type":"Point"}
}