{
  "type": "Feature",
  "properties": {
    "addr:full":"Avda Buenos Aires, 12 Ourense Ourense 32004",
    "addr:housenumber":"12",
    "addr:postcode":"32004",
    "addr:street":"Avda Buenos Aires",
    "iso:country":"ES",
    "sg:address":"Avda Buenos Aires, 12",
    "sg:city":"Ourense",
    "sg:orig_category":"Art\u00cdculos De Decoraci\u00d3n",
    "sg:phone":"+34 988 23 75 20",
    "sg:postcode":"32004",
    "sg:province":"Ourense",
    "wof:name":"Fernandez Vazquez Luciano",
    "wof:placetype":"venue"
},
  "geometry": {"coordinates":[-7.8622522354,42.3388366699],"type":"Point"}
}