{
  "type": "Feature",
  "properties": {
    "addr:full":"Calle de Villaviciosa, 3 Madrid Madrid 28024",
    "addr:housenumber":"3",
    "addr:postcode":"28024",
    "addr:street":"Calle De Villaviciosa",
    "iso:country":"ES",
    "sg:address":"Calle de Villaviciosa, 3",
    "sg:city":"Madrid",
    "sg:orig_category":"Equipos De Marcado, Etiquetado",
    "sg:phone":"+34 917 11 33 47",
    "sg:postcode":"28024",
    "sg:province":"Madrid",
    "wof:name":"Michelena Varela Homero",
    "wof:placetype":"venue"
},
  "geometry": {"coordinates":[-3.7672820091,40.3982276917],"type":"Point"}
}