{
  "type": "Feature",
  "properties": {
    "iso:country":"ES",
    "sg:address":"Calle de Tormes, 11",
    "sg:city":"Urbanizacion El Encinar",
    "sg:orig_category":"Estancos",
    "sg:phone":"+34 923 30 83 00",
    "sg:postcode":"37190",
    "sg:province":"Salamanca",
    "wof:name":"Baillo Baillo Jose",
    "wof:placetype":"venue"
},
  "geometry": {"coordinates":[-5.5836801529,40.883190155],"type":"Point"}
}