{
  "type": "Feature",
  "properties": {
    "addr:full":"Calle de Tembleque, S/n Guardia Toledo 45760",
    "addr:housenumber":"s / n",
    "addr:postcode":"45760",
    "addr:street":"Calle De Tembleque",
    "iso:country":"ES",
    "sg:address":"Calle de Tembleque, S/n",
    "sg:city":"Guardia",
    "sg:orig_category":"Confecci\u00d3n (fabricaci\u00d3n, Al Por Mayor)",
    "sg:phone":"+34 925 13 80 15",
    "sg:postcode":"45760",
    "sg:province":"Toledo",
    "wof:name":"Sociedad Cooperativa Limitada Jesus De La Guardia",
    "wof:placetype":"venue"
},
  "geometry": {"coordinates":[-3.4757640362,39.7840309143],"type":"Point"}
}