{
  "type": "Feature",
  "properties": {
    "iso:country":"ES",
    "sg:address":"Avda San Isidro Labrador, 21",
    "sg:city":"Santa Marta",
    "sg:orig_category":"Agencias Y Agentes Comerciales, Representantes",
    "sg:phone":"+34 924 68 13 34",
    "sg:postcode":"06150",
    "sg:province":"Badajoz",
    "wof:name":"Marroquin Villar Francisco Antonio",
    "wof:placetype":"venue"
},
  "geometry": {"coordinates":[-6.6255578995,38.6111831665],"type":"Point"}
}