{
  "type": "Feature",
  "properties": {
    "addr:full":"Avda Jose Luis Goyoaga Etorbidea, 24 Erandio Vizcaya 48950",
    "addr:housenumber":"24",
    "addr:postcode":"48950",
    "addr:street":"Avda Jose Luis Goyoaga Etorbidea",
    "iso:country":"ES",
    "sg:address":"Avda Jose Luis Goyoaga Etorbidea, 24",
    "sg:city":"Erandio",
    "sg:orig_category":"Comercio, Reparaci\u00d3n De Motocicletas, Bicicletas Y Piezas Sueltas",
    "sg:phone":"+34 944 06 14 99",
    "sg:postcode":"48950",
    "sg:province":"Vizcaya",
    "sg:website":"www.ciclosaltzaga.com",
    "wof:name":"Oscar Moreno Alonso",
    "wof:placetype":"venue"
},
  "geometry": {"coordinates":[-2.97676301,43.3027801514],"type":"Point"}
}