{
  "type": "Feature",
  "properties": {
    "iso:country":"ES",
    "sg:address":"Avda Alicante, 11",
    "sg:city":"Denia",
    "sg:orig_category":"Inform\u00c1tica, Ofim\u00c1tica (estudios, Asesor\u00cda, Ingenier\u00cda, Formaci\u00d3n)",
    "sg:phone":"+34 966 42 45 92",
    "sg:postcode":"03700",
    "sg:province":"Alicante",
    "sg:website":"www.appred.com",
    "wof:name":"Denimatic S.l.",
    "wof:placetype":"venue"
},
  "geometry": {"coordinates":[0.1039299965,38.8374519348],"type":"Point"}
}