{
  "type": "Feature",
  "properties": {
    "iso:country":"ES",
    "sg:address":"Av Maria Fortuny, 72",
    "sg:city":"Reus",
    "sg:orig_category":"Muebles, Minoristas",
    "sg:phone":"+34 977 34 39 72",
    "sg:postcode":"43203",
    "sg:province":"Tarragona",
    "wof:name":"Vanzanki S.l.",
    "wof:placetype":"venue"
},
  "geometry": {"coordinates":[1.1149929762,41.1606330872],"type":"Point"}
}