{
  "type": "Feature",
  "properties": {
    "addr:full":"Ctra Lorca, Km. 0289,0 Totana Murcia 30850",
    "addr:postcode":"30850",
    "addr:street":"Ctra Lorca Km. 0289,0",
    "iso:country":"ES",
    "sg:address":"Ctra Lorca, Km. 0289,0",
    "sg:city":"Totana",
    "sg:orig_category":"Molduras, Junquillos, Listones Y Molduras Perforadas",
    "sg:phone":"+34 968 42 25 51",
    "sg:postcode":"30850",
    "sg:province":"Murcia",
    "wof:name":"Gris Romero Jose",
    "wof:placetype":"venue"
},
  "geometry": {"coordinates":[-1.5030734539,37.7649536133],"type":"Point"}
}