{
  "type": "Feature",
  "properties": {
    "addr:full":"Carrer de Amalia Soler, 144 Vilafranca Penedes Barcelona 08720",
    "addr:housenumber":"144",
    "addr:postcode":"08720",
    "addr:street":"Carrer De Amalia Soler;Penedes Barcelona",
    "iso:country":"ES",
    "sg:address":"Carrer de Amalia Soler, 144",
    "sg:city":"Vilafranca Penedes",
    "sg:orig_category":"Cajas De Ahorro",
    "sg:phone":"+34 938 17 26 20",
    "sg:postcode":"08720",
    "sg:province":"Barcelona",
    "wof:name":"Caixa D'estalvis Del Penedes",
    "wof:placetype":"venue"
},
  "geometry": {"coordinates":[1.6992199421,41.3447799683],"type":"Point"}
}