{
  "type": "Feature",
  "properties": {
    "addr:full":"Gisastu Bide, 1 Eibar Guip\u00f9zcoa 20600",
    "addr:housenumber":"1",
    "addr:postcode":"20600",
    "addr:street":"Gisastu Bide;Guipu\u0300Zcoa",
    "iso:country":"ES",
    "sg:address":"Gisastu Bide, 1",
    "sg:city":"Eibar",
    "sg:orig_category":"Herramientas Manuales (fabricaci\u00d3n, Al Por Mayor)",
    "sg:phone":"+34 943 12 19 21",
    "sg:postcode":"20600",
    "sg:province":"Guip\u00f9zcoa",
    "wof:name":"Talleres Leyaristi C.b.",
    "wof:placetype":"venue"
},
  "geometry": {"coordinates":[-2.4624929428,43.1863632202],"type":"Point"}
}