{
  "type": "Feature",
  "properties": {
    "addr:full":"Avda Guadalquivir, S/n Hornachuelos C\u00f3rdoba 14740",
    "addr:postcode":"14740",
    "addr:street":"Avda Guadalquivir S / N;Co\u0301Rdoba",
    "iso:country":"ES",
    "sg:address":"Avda Guadalquivir, S/n",
    "sg:city":"Hornachuelos",
    "sg:orig_category":"Aguas (distribuci\u00d3n, Servicios)",
    "sg:phone":"+34 957 64 00 41",
    "sg:postcode":"14740",
    "sg:province":"C\u00f3rdoba",
    "wof:name":"Confederacion Hidrografica Del Guadalquivir",
    "wof:placetype":"venue"
},
  "geometry": {"coordinates":[-5.2424640656,37.8263092041],"type":"Point"}
}