{
  "type": "Feature",
  "properties": {
    "iso:country":"ES",
    "sg:address":"Mayor, 11",
    "sg:city":"Genoves",
    "sg:orig_category":"Arboricultura Y Producci\u00d3n De Frutas",
    "sg:phone":"+34 962 22 91 44",
    "sg:postcode":"46894",
    "sg:province":"Valencia",
    "wof:name":"Sanchis Llopis Pascual",
    "wof:placetype":"venue"
},
  "geometry": {"coordinates":[-0.4699240029,38.9900856018],"type":"Point"}
}