{
  "type": "Feature",
  "properties": {
    "addr:full":"Pase Imperial, 1 Madrid Madrid 28005",
    "addr:housenumber":"1",
    "addr:postcode":"28005",
    "iso:country":"ES",
    "sg:address":"Pase Imperial, 1",
    "sg:city":"Madrid",
    "sg:orig_category":"Metalurgia",
    "sg:phone":"+34 913 66 33 18",
    "sg:postcode":"28005",
    "sg:province":"Madrid",
    "wof:name":"Manzano Manzano Damian",
    "wof:placetype":"venue"
},
  "geometry": {"coordinates":[-3.7181351185,40.4106750488],"type":"Point"}
}