{
  "type": "Feature",
  "properties": {
    "iso:country":"ES",
    "sg:address":"Carrer de Montblanc (de), 4",
    "sg:city":"Salou",
    "sg:orig_category":"Discotecas Y Salas De Baile",
    "sg:phone":"+34 977 35 35 59",
    "sg:postcode":"43840",
    "sg:province":"Tarragona",
    "wof:name":"Benitez Fuentes S.l.",
    "wof:placetype":"venue"
},
  "geometry": {"coordinates":[1.1484400034,41.0715293884],"type":"Point"}
}