{
  "type": "Feature",
  "properties": {
    "iso:country":"ES",
    "sg:address":"Calle de Leiria, 6",
    "sg:city":"Madrid",
    "sg:orig_category":"Empresarios",
    "sg:phone":"+34 915 69 01 84",
    "sg:postcode":"28025",
    "sg:province":"Madrid",
    "wof:name":"Marin Cobo Alicia",
    "wof:placetype":"venue"
},
  "geometry": {"coordinates":[-3.7219688892,40.3847312927],"type":"Point"}
}