{
  "type": "Feature",
  "properties": {
    "addr:full":"Calle de Espronceda, 13 Castuera Badajoz 06420",
    "addr:housenumber":"13",
    "addr:postcode":"06420",
    "addr:street":"Calle De Espronceda",
    "iso:country":"ES",
    "sg:address":"Calle de Espronceda, 13",
    "sg:city":"Castuera",
    "sg:orig_category":"T\u00c9cnicos Veterinarios",
    "sg:phone":"+34 924 76 01 79",
    "sg:postcode":"06420",
    "sg:province":"Badajoz",
    "wof:name":"Aragon Donoso Jose Maria",
    "wof:placetype":"venue"
},
  "geometry": {"coordinates":[-5.5469369888,38.7215881348],"type":"Point"}
}