{
  "type": "Feature",
  "properties": {
    "iso:country":"ES",
    "sg:address":"Presa De Vilasouto, S/n",
    "sg:city":"Vilasouto",
    "sg:orig_category":"Empresas De Electricidad En General",
    "sg:phone":"+34 982 42 63 09",
    "sg:postcode":"27345",
    "sg:province":"Lugo",
    "wof:name":"Confederacion Hidrografica Del Norte De Espa\u00f1a",
    "wof:placetype":"venue"
},
  "geometry": {"coordinates":[-7.4338002205,42.6695404053],"type":"Point"}
}