{
  "type": "Feature",
  "properties": {
    "iso:country":"ES",
    "sg:address":"Calle de Luchana, 5",
    "sg:city":"Mohedas De Granadilla",
    "sg:classifiers":[
        {
            "category":"Taxi",
            "type":"Transportation"
        }
    ],
    "sg:phone":"+34 927 67 35 41",
    "sg:postcode":"10664",
    "sg:province":"C\u00e1ceres",
    "wof:name":"Batuecas Puertas Alfredo",
    "wof:placetype":"venue"
},
  "geometry": {"coordinates":[-6.2013731003,40.26820755],"type":"Point"}
}