{
  "type": "Feature",
  "properties": {
    "iso:country":"ES",
    "sg:address":"Pl Espart, 5",
    "sg:city":"Elche",
    "sg:orig_category":"Inmobiliaria (agencias)",
    "sg:phone":"+34 965 42 79 26",
    "sg:postcode":"03203",
    "sg:province":"Alicante",
    "wof:name":"Promociones Calle Blaco Iba\u00d1ez S.l",
    "wof:placetype":"venue"
},
  "geometry": {"coordinates":[-0.6967509985,38.2648849487],"type":"Point"}
}