{
  "type": "Feature",
  "properties": {
    "iso:country":"ES",
    "sg:address":"Calle de Sohail, 2",
    "sg:city":"Fuengirola",
    "sg:orig_category":"Abogados",
    "sg:phone":"+34 952 19 81 54",
    "sg:postcode":"29640",
    "sg:province":"M\u00e1laga",
    "wof:name":"Ruiz Y Guillen Abogados, S.c.",
    "wof:placetype":"venue"
},
  "geometry": {"coordinates":[-4.6242051125,36.5389633179],"type":"Point"}
}