{
  "type": "Feature",
  "properties": {
    "addr:full":"Avda Navarra De, 24 Donostia-san Sebastian Guip\u00f9zcoa 20013",
    "addr:housenumber":"24",
    "addr:postcode":"20013",
    "addr:street":"Avda Navarra De",
    "iso:country":"ES",
    "sg:address":"Avda Navarra De, 24",
    "sg:city":"Donostia-san Sebastian",
    "sg:orig_category":"M\u00c9dicos: Ginecolog\u00cda Y Obstetricia",
    "sg:phone":"+34 943 28 39 11",
    "sg:postcode":"20013",
    "sg:province":"Guip\u00f9zcoa",
    "wof:name":"Zuzuarregui Vea-murguia Inmaculada",
    "wof:placetype":"venue"
},
  "geometry": {"coordinates":[-1.9690544605,43.3243637085],"type":"Point"}
}