{
  "type": "Feature",
  "properties": {
    "addr:full":"Ciento Cuarenta, S/n Son Sardina Islas Baleares 07120",
    "addr:housenumber":"s",
    "addr:postcode":"07120",
    "addr:street":"/ N",
    "iso:country":"ES",
    "sg:address":"Ciento Cuarenta, S/n",
    "sg:city":"Son Sardina",
    "sg:orig_category":"Ropa Para Se\u00d1oras (al Por Menor)",
    "sg:phone":"+34 971 43 92 39",
    "sg:postcode":"07120",
    "sg:province":"Islas Baleares",
    "wof:name":"Marti Mas Pedro",
    "wof:placetype":"venue"
},
  "geometry": {"coordinates":[2.655944109,39.6189918518],"type":"Point"}
}