{
  "type": "Feature",
  "properties": {
    "addr:full":"Carrer de Johann Sebastian Bach, 9 Barcelona Barcelona 08021",
    "addr:housenumber":"9",
    "addr:postcode":"08021",
    "addr:street":"Carrer De Johann Sebastian Bach",
    "iso:country":"ES",
    "sg:address":"Carrer de Johann Sebastian Bach, 9",
    "sg:city":"Barcelona",
    "sg:orig_category":"Alumbrados",
    "sg:phone":"+34 932 41 11 09",
    "sg:postcode":"08021",
    "sg:province":"Barcelona",
    "sg:website":"www.santacole.com",
    "wof:name":"Santa Cole Ediciones De Dise\u00f1o S.a.",
    "wof:placetype":"venue"
},
  "geometry": {"coordinates":[2.1390790939,41.3958206177],"type":"Point"}
}