{
  "type": "Feature",
  "properties": {
    "iso:country":"ES",
    "sg:address":"Calle de Rufino Gea Martinez, 5",
    "sg:city":"Orihuela",
    "sg:orig_category":"Agencias Y Agentes Comerciales, Representantes",
    "sg:phone":"+34 965 30 10 87",
    "sg:postcode":"03300",
    "sg:province":"Alicante",
    "wof:name":"Entidad Especializada En Prevencion De Riesgos Del Mediterraneo S.l.",
    "wof:placetype":"venue"
},
  "geometry": {"coordinates":[-0.9441350102,38.0856323242],"type":"Point"}
}