{
  "type": "Feature",
  "properties": {
    "addr:full":"Calle de Julian Hernandez, 14 Madrid Madrid 28043",
    "addr:housenumber":"14",
    "addr:postcode":"madrid;28043",
    "addr:street":"Calle De Julian Hernandez",
    "iso:country":"ES",
    "sg:address":"Calle de Julian Hernandez, 14",
    "sg:city":"Madrid",
    "sg:orig_category":"Centros De Educaci\u00d3n Especial",
    "sg:phone":"+34 917 16 00 21",
    "sg:postcode":"28043",
    "sg:province":"Madrid",
    "wof:name":"Hijas Del Patrocinio De Maria",
    "wof:placetype":"venue"
},
  "geometry": {"coordinates":[-3.6523709297,40.4543952942],"type":"Point"}
}