{
  "type": "Feature",
  "properties": {
    "addr:full":"Ctra Bilbao-galdakao, 32 Bilbao Vizcaya 48004",
    "addr:housenumber":"32",
    "addr:postcode":"48004",
    "addr:street":"Ctra Bilbao-Galdakao",
    "iso:country":"ES",
    "sg:address":"Ctra Bilbao-galdakao, 32",
    "sg:city":"Bilbao",
    "sg:orig_category":"Electricidad, Electr\u00d3nica: Material Y Suministros (al Por Mayor)",
    "sg:phone":"+34 944 12 23 68",
    "sg:postcode":"48004",
    "sg:province":"Vizcaya",
    "wof:name":"Guerra San Martin Difusion S.a.",
    "wof:placetype":"venue"
},
  "geometry": {"coordinates":[-2.9019010067,43.2498130798],"type":"Point"}
}