{
  "type": "Feature",
  "properties": {
    "iso:country":"ES",
    "sg:address":"Calle de Monse\u00d1or Oscar Romero, 64",
    "sg:city":"Madrid",
    "sg:orig_category":"Electricidad Veh\u00cdculo",
    "sg:phone":"+34 914 65 02 52",
    "sg:postcode":"28025",
    "sg:province":"Madrid",
    "wof:name":"Gonzalez Arias David",
    "wof:placetype":"venue"
},
  "geometry": {"coordinates":[-3.7460150719,40.3824768066],"type":"Point"}
}