{
  "type": "Feature",
  "properties": {
    "addr:full":"Av Abat Marcet, 2 Terrassa Barcelona 08225",
    "addr:housenumber":"2",
    "addr:postcode":"08225",
    "addr:street":"Av Abat Marcet",
    "iso:country":"ES",
    "sg:address":"Av Abat Marcet, 2",
    "sg:city":"Terrassa",
    "sg:orig_category":"Bancos",
    "sg:phone":"+34 937 34 95 40",
    "sg:postcode":"08225",
    "sg:province":"Barcelona",
    "wof:name":"Bankinter S.a.",
    "wof:placetype":"venue"
},
  "geometry": {"coordinates":[2.0169739723,41.5752105713],"type":"Point"}
}