{
  "type": "Feature",
  "properties": {
    "iso:country":"ES",
    "sg:address":"Alfa, S/n",
    "sg:city":"Bujaraloz",
    "sg:orig_category":"Panader\u00cdas, Panader\u00cdas",
    "sg:phone":"+34 976 17 32 59",
    "sg:postcode":"50177",
    "sg:province":"Zaragoza",
    "wof:name":"Used Ferrer Jose",
    "wof:placetype":"venue"
},
  "geometry": {"coordinates":[-0.1559489965,41.4973945618],"type":"Point"}
}