{
  "type": "Feature",
  "properties": {
    "addr:full":"Cmno Almaluez, 1 Arcos Jalon Soria 42250",
    "addr:housenumber":"1",
    "addr:postcode":"42250",
    "addr:street":"Cmno Almaluez",
    "iso:country":"ES",
    "sg:address":"Cmno Almaluez, 1",
    "sg:city":"Arcos Jalon",
    "sg:orig_category":"Plomeros",
    "sg:phone":"+34 975 32 02 90",
    "sg:postcode":"42250",
    "sg:province":"Soria",
    "wof:name":"Pe\u00f1a Escudero Rafael",
    "wof:placetype":"venue"
},
  "geometry": {"coordinates":[-2.2726109028,41.2135391235],"type":"Point"}
}