{
  "type": "Feature",
  "properties": {
    "addr:full":"Calle de San Roque, 5 Calanda Teruel 44570",
    "addr:housenumber":"5",
    "addr:postcode":"44570",
    "addr:street":"Calle De San Roque",
    "iso:country":"ES",
    "sg:address":"Calle de San Roque, 5",
    "sg:city":"Calanda",
    "sg:orig_category":"Reposter\u00cdas",
    "sg:phone":"+34 978 84 60 70",
    "sg:postcode":"44570",
    "sg:province":"Teruel",
    "wof:name":"Familia Guarc S.l.",
    "wof:placetype":"venue"
},
  "geometry": {"coordinates":[-0.231475994,40.9395027161],"type":"Point"}
}