{
  "type": "Feature",
  "properties": {
    "addr:full":"Carrer de Beates, 8 Barcelona Barcelona 08003",
    "addr:housenumber":"8",
    "addr:postcode":"08003",
    "addr:street":"Carrer De Beates",
    "iso:country":"ES",
    "sg:address":"Carrer de Beates, 8",
    "sg:city":"Barcelona",
    "sg:orig_category":"Edici\u00d3n De Diarios, Revistas, Boletines",
    "sg:phone":"+34 933 19 31 29",
    "sg:postcode":"08003",
    "sg:province":"Barcelona",
    "wof:name":"Cantero Cava Jose Maria",
    "wof:placetype":"venue"
},
  "geometry": {"coordinates":[2.1766629219,41.3864746094],"type":"Point"}
}