{
  "type": "Feature",
  "properties": {
    "iso:country":"ES",
    "sg:address":"Ctra Vcia-alicante, Km. 0183,5",
    "sg:city":"Teulada",
    "sg:orig_category":"Explotaci\u00d3n De Canteras",
    "sg:phone":"+34 965 97 35 55",
    "sg:postcode":"03725",
    "sg:province":"Alicante",
    "wof:name":"Lorenzo Andres Valles S. L.",
    "wof:placetype":"venue"
},
  "geometry": {"coordinates":[0.1012500003,38.7296409607],"type":"Point"}
}