{
  "type": "Feature",
  "properties": {
    "addr:full":"C/ Mare De Deu L'esperan\u00c7a, 32 Inca Islas Baleares 07300",
    "addr:housenumber":"32",
    "addr:postcode":"07300",
    "addr:street":"C / Mare De Deu;\u0327A",
    "iso:country":"ES",
    "sg:address":"C/ Mare De Deu L'esperan\u00c7a, 32",
    "sg:city":"Inca",
    "sg:orig_category":"Artesan\u00cda",
    "sg:phone":"+34 971 50 22 68",
    "sg:postcode":"07300",
    "sg:province":"Islas Baleares",
    "wof:name":"Triguero Artesanos S.l.",
    "wof:placetype":"venue"
},
  "geometry": {"coordinates":[2.9129359722,39.716381073],"type":"Point"}
}