{
  "type": "Feature",
  "properties": {
    "addr:full":"Calle de Cuesta Del Retiro, 9 S. Vicente Barquera Cantabria 39540",
    "addr:housenumber":"9",
    "addr:postcode":"39540",
    "addr:street":"Calle De Cuesta Del Retiro;S. Vicente",
    "iso:country":"ES",
    "sg:address":"Calle de Cuesta Del Retiro, 9",
    "sg:city":"S. Vicente Barquera",
    "sg:orig_category":"Librer\u00cdas",
    "sg:phone":"+34 942 71 20 52",
    "sg:postcode":"39540",
    "sg:province":"Cantabria",
    "wof:name":"Cruz Noriega Maria Pilar",
    "wof:placetype":"venue"
},
  "geometry": {"coordinates":[-4.3995471001,43.3842964172],"type":"Point"}
}