{
  "type": "Feature",
  "properties": {
    "addr:full":"Calle de Landaburu, 8 Barakaldo Vizcaya 48902",
    "addr:housenumber":"8",
    "addr:postcode":"48902",
    "addr:street":"Calle De Landaburu",
    "iso:country":"ES",
    "sg:address":"Calle de Landaburu, 8",
    "sg:city":"Barakaldo",
    "sg:orig_category":"Empresas De Limpieza",
    "sg:phone":"+34 944 38 77 01",
    "sg:postcode":"48902",
    "sg:province":"Vizcaya",
    "wof:name":"Limpiezas Berezko,s.l.",
    "wof:placetype":"venue"
},
  "geometry": {"coordinates":[-2.9857740402,43.2936630249],"type":"Point"}
}