{
  "type": "Feature",
  "properties": {
    "iso:country":"ES",
    "sg:address":"Rond Garay, 23",
    "sg:city":"San Juan",
    "sg:orig_category":"Cristaler\u00cdas",
    "sg:phone":"+34 968 21 28 53",
    "sg:postcode":"30003",
    "sg:province":"Murcia",
    "wof:name":"Belmonte Quiles Francisca Angeles",
    "wof:placetype":"venue"
},
  "geometry": {"coordinates":[-1.1216510534,37.9822158813],"type":"Point"}
}