{
  "type": "Feature",
  "properties": {
    "addr:full":"Carrer de Nadal, 48 Barcelona Barcelona 08030",
    "addr:housenumber":"48",
    "addr:postcode":"08030",
    "addr:street":"Carrer De Nadal",
    "iso:country":"ES",
    "sg:address":"Carrer de Nadal, 48",
    "sg:city":"Barcelona",
    "sg:orig_category":"Guarder\u00cdas",
    "sg:phone":"+34 933 11 71 22",
    "sg:postcode":"08030",
    "sg:province":"Barcelona",
    "wof:name":"Serrano Belmonte Rosa Maria",
    "wof:placetype":"venue"
},
  "geometry": {"coordinates":[2.1881930828,41.4287605286],"type":"Point"}
}