{
  "type": "Feature",
  "properties": {
    "addr:full":"Calle de Santa Rita, 3 Cazorla Ja\u00e9n 23470",
    "addr:housenumber":"3",
    "addr:postcode":"23470",
    "addr:street":"Calle De Santa Rita",
    "iso:country":"ES",
    "sg:address":"Calle de Santa Rita, 3",
    "sg:city":"Cazorla",
    "sg:classifiers":[
        {
            "category":"Personal",
            "subcategory":"Barber",
            "type":"Services"
        }
    ],
    "sg:phone":"+34 953 72 00 37",
    "sg:postcode":"23470",
    "sg:province":"Ja\u00e9n",
    "sg:tags":[
        "caballeros",
        "de",
        "peluqueros"
    ],
    "wof:name":"Mallenco Garcia Amancio",
    "wof:placetype":"venue"
},
  "geometry": {"coordinates":[-3.0046350956,37.9192886353],"type":"Point"}
}