{
  "type": "Feature",
  "properties": {
    "addr:full":"Calle de Princesa Do\u00d1a Sofia, 1 Alcorcon Madrid 28924",
    "addr:housenumber":"1",
    "addr:postcode":"28924",
    "addr:street":"Calle De Princesa Don\u0303A Sofia",
    "iso:country":"ES",
    "sg:address":"Calle de Princesa Do\u00d1a Sofia, 1",
    "sg:city":"Alcorcon",
    "sg:orig_category":"Peluquer\u00cdas, Peluquer\u00cda Mixta",
    "sg:phone":"+34 916 19 79 84",
    "sg:postcode":"28924",
    "sg:province":"Madrid",
    "wof:name":"Arnao Martinez Elisa",
    "wof:placetype":"venue"
},
  "geometry": {"coordinates":[-3.8193435669,40.3490600586],"type":"Point"}
}