{
  "type": "Feature",
  "properties": {
    "addr:full":"Prol Nicaragua(pol Ind Oeste), 29 S. Gines Murcia 30169",
    "addr:housenumber":"29",
    "addr:postcode":"30169",
    "addr:street":"Prol Nicaragua Pol Ind Oeste;S. Gines",
    "iso:country":"ES",
    "sg:address":"Prol Nicaragua(pol Ind Oeste), 29",
    "sg:city":"S. Gines",
    "sg:orig_category":"Materias Pl\u00c1sticas: Art\u00cdculos Para La Industria",
    "sg:phone":"+34 968 88 61 31",
    "sg:postcode":"30169",
    "sg:province":"Murcia",
    "wof:name":"Manuel Martinez Verruga Y Dos Mas C.b.",
    "wof:placetype":"venue"
},
  "geometry": {"coordinates":[-1.177366972,37.9589958191],"type":"Point"}
}