{
  "type": "Feature",
  "properties": {
    "addr:full":"Calle de Juan Aliaga, S/n Maria Almer\u00eda 04838",
    "addr:housenumber":"s / n",
    "addr:postcode":"04838",
    "addr:street":"Calle De Juan Aliaga;Maria Almeri\u0301A",
    "iso:country":"ES",
    "sg:address":"Calle de Juan Aliaga, S/n",
    "sg:city":"Maria",
    "sg:orig_category":"Institutos M\u00c9dicos",
    "sg:phone":"+34 950 41 76 48",
    "sg:postcode":"04838",
    "sg:province":"Almer\u00eda",
    "wof:name":"Servicio Andaluz De Salud",
    "wof:placetype":"venue"
},
  "geometry": {"coordinates":[-2.1648490429,37.7118988037],"type":"Point"}
}