{
  "type": "Feature",
  "properties": {
    "addr:full":"Avda Paloma, 21 Malaga M\u00e1laga 29003",
    "addr:housenumber":"21",
    "addr:postcode":"29003",
    "addr:street":"Avda Paloma;Ma\u0301Laga",
    "iso:country":"ES",
    "sg:address":"Avda Paloma, 21",
    "sg:city":"Malaga",
    "sg:orig_category":"M\u00c9dicos: Estomatolog\u00cda",
    "sg:phone":"+34 952 36 10 49",
    "sg:postcode":"29003",
    "sg:province":"M\u00e1laga",
    "wof:name":"Delgado Schwarzmann Cristobal",
    "wof:placetype":"venue"
},
  "geometry": {"coordinates":[-4.4421830177,36.700630188],"type":"Point"}
}