{
  "type": "Feature",
  "properties": {
    "addr:full":"Pg Nicolau (de), 23 Montbrio Del Camp Tarragona 43340",
    "addr:housenumber":"23",
    "addr:postcode":"43340",
    "addr:street":"Pg Nicolau De",
    "iso:country":"ES",
    "sg:address":"Pg Nicolau (de), 23",
    "sg:city":"Montbrio Del Camp",
    "sg:orig_category":"Empresas De Desmonte",
    "sg:phone":"+34 977 82 66 92",
    "sg:postcode":"43340",
    "sg:province":"Tarragona",
    "wof:name":"Excavaciones Sb Sccl",
    "wof:placetype":"venue"
},
  "geometry": {"coordinates":[0.9998850226,41.1236953735],"type":"Point"}
}