{
  "type": "Feature",
  "properties": {
    "addr:full":"Carr Girona, 79 Amer Girona 17170",
    "addr:housenumber":"79",
    "addr:postcode":"17170",
    "addr:street":"Carr Girona",
    "iso:country":"ES",
    "sg:address":"Carr Girona, 79",
    "sg:city":"Amer",
    "sg:orig_category":"Alimentaci\u00d3n General (al Por Mayor)",
    "sg:phone":"+34 972 43 09 92",
    "sg:postcode":"17170",
    "sg:province":"Girona",
    "wof:name":"Rich Fabregas Antoni",
    "wof:placetype":"venue"
},
  "geometry": {"coordinates":[2.6044440269,42.0092544556],"type":"Point"}
}