{
  "type": "Feature",
  "properties": {
    "iso:country":"ES",
    "sg:address":"Calle de Don Quijote, 10",
    "sg:city":"Malagon",
    "sg:orig_category":"Plomeros",
    "sg:phone":"+34 926 80 09 76",
    "sg:postcode":"13420",
    "sg:province":"Ciudad Real",
    "wof:name":"Asensio Mu\u00f1oz Angel",
    "wof:placetype":"venue"
},
  "geometry": {"coordinates":[-3.8561382294,39.1612892151],"type":"Point"}
}