{
  "type": "Feature",
  "properties": {
    "iso:country":"ES",
    "sg:address":"Extramuros, S/n",
    "sg:city":"Sanlucar Mayor",
    "sg:orig_category":"Ense\u00d1anza, Formaci\u00d3n Profesional: Aprendizaje",
    "sg:phone":"+34 955 70 02 78",
    "sg:postcode":"41800",
    "sg:province":"Sevilla",
    "wof:name":"Ayuntamiento De Sanlucar La Mayor",
    "wof:placetype":"venue"
},
  "geometry": {"coordinates":[-5.9962949753,37.3826408386],"type":"Point"}
}