{
  "type": "Feature",
  "properties": {
    "iso:country":"ES",
    "sg:address":"Calle de Sofia, 64",
    "sg:city":"Madrid",
    "sg:orig_category":"Cerrajer\u00cda, Ferrallista",
    "sg:phone":"+34 913 13 32 70",
    "sg:postcode":"28022",
    "sg:province":"Madrid",
    "wof:name":"Rodriguez Planelles Monica",
    "wof:placetype":"venue"
},
  "geometry": {"coordinates":[-3.6014499664,40.4294776917],"type":"Point"}
}