{
  "type": "Feature",
  "properties": {
    "iso:country":"ES",
    "sg:address":"Calle de Marques De Boil, 4",
    "sg:city":"Cordoba",
    "sg:orig_category":"Estilistas Y Estudios De Estilo De Corte Y Confecci\u00d3n",
    "sg:phone":"+34 957 47 75 07",
    "sg:postcode":"14008",
    "sg:province":"C\u00f3rdoba",
    "wof:name":"Ortiz Garcia Andres",
    "wof:placetype":"venue"
},
  "geometry": {"coordinates":[-4.7800998688,37.8848075867],"type":"Point"}
}