{
  "type": "Feature",
  "properties": {
    "addr:full":"Calle de Mota Del Cuervo, 70 Madrid Madrid 28043",
    "addr:housenumber":"70",
    "addr:postcode":"madrid;28043",
    "addr:street":"Calle De Mota Del Cuervo",
    "iso:country":"ES",
    "sg:address":"Calle de Mota Del Cuervo, 70",
    "sg:city":"Madrid",
    "sg:orig_category":"Vinos Y Licores (venta Al Por Menor)",
    "sg:phone":"+34 917 59 69 07",
    "sg:postcode":"28043",
    "sg:province":"Madrid",
    "wof:name":"Navares Lopez Juan Carlos",
    "wof:placetype":"venue"
},
  "geometry": {"coordinates":[-3.631716013,40.4646759033],"type":"Point"}
}