{
  "type": "Feature",
  "properties": {
    "iso:country":"ES",
    "sg:address":"Altzutzate, 14",
    "sg:city":"Huarte",
    "sg:orig_category":"Producci\u00d3n De Cart\u00d3n",
    "sg:phone":"+34 948 33 32 41",
    "sg:postcode":"31620",
    "sg:province":"Navarra",
    "wof:name":"Desperdicios De Papel Del Norte S. L.",
    "wof:placetype":"venue"
},
  "geometry": {"coordinates":[-1.600851059,42.8263549805],"type":"Point"}
}