{
  "type": "Feature",
  "properties": {
    "addr:full":"Calle de Ramon Y Cajal, 77 Calamonte Badajoz 06810",
    "addr:housenumber":"77",
    "addr:postcode":"06810",
    "addr:street":"Calle De Ramon Y Cajal",
    "iso:country":"ES",
    "sg:address":"Calle de Ramon Y Cajal, 77",
    "sg:city":"Calamonte",
    "sg:orig_category":"Reposter\u00cdas",
    "sg:phone":"+34 924 32 35 29",
    "sg:postcode":"06810",
    "sg:province":"Badajoz",
    "wof:name":"Romero Fernandez Ana",
    "wof:placetype":"venue"
},
  "geometry": {"coordinates":[-6.3850769997,38.8872718811],"type":"Point"}
}