{
  "type": "Feature",
  "properties": {
    "addr:full":"Avda Carmen, 107 Cox Alicante 03350",
    "addr:housenumber":"107",
    "addr:postcode":"03350",
    "addr:street":"Avda Carmen",
    "iso:country":"ES",
    "sg:address":"Avda Carmen, 107",
    "sg:city":"Cox",
    "sg:orig_category":"Electromec\u00c1nica",
    "sg:phone":"+34 965 36 06 32",
    "sg:postcode":"03350",
    "sg:province":"Alicante",
    "wof:name":"Electricidad Fuentes S.l.",
    "wof:placetype":"venue"
},
  "geometry": {"coordinates":[-0.8893619776,38.1467056274],"type":"Point"}
}