{
  "type": "Feature",
  "properties": {
    "addr:full":"Calle de Nueva, 36 Mairena Aljarafe Sevilla 41927",
    "addr:housenumber":"36",
    "addr:postcode":"41927",
    "addr:street":"Calle De Nueva",
    "iso:country":"ES",
    "sg:address":"Calle de Nueva, 36",
    "sg:city":"Mairena Aljarafe",
    "sg:orig_category":"Cajas Para Embalar",
    "sg:phone":"+34 954 18 15 04",
    "sg:postcode":"41927",
    "sg:province":"Sevilla",
    "wof:name":"Caja Rural Del Sur Sociedad Cooperativa",
    "wof:placetype":"venue"
},
  "geometry": {"coordinates":[-6.0639619827,37.3446006775],"type":"Point"}
}