{
  "type": "Feature",
  "properties": {
    "iso:country":"ES",
    "sg:address":"Calle de Traspalacios, 67",
    "sg:city":"Lepe",
    "sg:orig_category":"Delegados, Agentes De Tr\u00c1nsito, Auxiliares De Transporte Internacional",
    "sg:phone":"+34 959 38 05 36",
    "sg:postcode":"21440",
    "sg:province":"Huelva",
    "wof:name":"Dominguez Alfonso Jose",
    "wof:placetype":"venue"
},
  "geometry": {"coordinates":[-7.2002820969,37.2544517517],"type":"Point"}
}