{
  "type": "Feature",
  "properties": {
    "addr:full":"Calle de Parma, 17 Poligono De Santa Ana Murcia 30310",
    "addr:housenumber":"17 poligono",
    "addr:postcode":"30310",
    "addr:street":"Calle De Parma",
    "iso:country":"ES",
    "sg:address":"Calle de Parma, 17",
    "sg:city":"Poligono De Santa Ana",
    "sg:orig_category":"Prot\u00c9sicos Dentales",
    "sg:phone":"+34 968 51 70 81",
    "sg:postcode":"30310",
    "sg:province":"Murcia",
    "wof:name":"Fernandez De Palencia Gregorio Manuel",
    "wof:placetype":"venue"
},
  "geometry": {"coordinates":[-1.0082689524,37.6360816956],"type":"Point"}
}