{
  "type": "Feature",
  "properties": {
    "iso:country":"ES",
    "sg:address":"Rond Castillo (del), S/n",
    "sg:city":"Burjassot",
    "sg:orig_category":"Mec\u00c1nico Del Autom\u00d3vil",
    "sg:phone":"+34 963 90 27 24",
    "sg:postcode":"46100",
    "sg:province":"Valencia",
    "wof:name":"Diaz-delgado Cabo Carlos",
    "wof:placetype":"venue"
},
  "geometry": {"coordinates":[-0.4062229991,39.5037612915],"type":"Point"}
}