{
  "type": "Feature",
  "properties": {
    "addr:full":"Os Praceres, 1 Pontevedra Pontevedra 36910",
    "addr:housenumber":"1",
    "addr:postcode":"36910",
    "addr:street":"Praceres",
    "iso:country":"ES",
    "sg:address":"Os Praceres, 1",
    "sg:city":"Pontevedra",
    "sg:orig_category":"Fabricaci\u00d3n, Reparaci\u00d3n Y Mantenimiento De Construcciones Navales Y Fluviales",
    "sg:phone":"+34 986 88 47 73",
    "sg:postcode":"36910",
    "sg:province":"Pontevedra",
    "wof:name":"Reparaciones Galicia S. L.",
    "wof:placetype":"venue"
},
  "geometry": {"coordinates":[-8.6879987717,42.3997993469],"type":"Point"}
}