{
  "type": "Feature",
  "properties": {
    "addr:full":"Calle de Capitan Amador, 14 Alacant Alicante 03004",
    "addr:housenumber":"14",
    "addr:postcode":"03004",
    "addr:street":"Calle De Capitan Amador",
    "iso:country":"ES",
    "sg:address":"Calle de Capitan Amador, 14",
    "sg:city":"Alacant",
    "sg:orig_category":"Agencias De Viajes",
    "sg:phone":"+34 965 91 07 79",
    "sg:postcode":"03004",
    "sg:province":"Alicante",
    "wof:name":"Viajes Idella S.l.",
    "wof:placetype":"venue"
},
  "geometry": {"coordinates":[-0.4867439866,38.3527145386],"type":"Point"}
}