{
  "type": "Feature",
  "properties": {
    "addr:full":"Calle de Vi\u00d1a (la), 4 Burlada Navarra 31600",
    "addr:housenumber":"4",
    "addr:postcode":"31600",
    "addr:street":"Calle De Vin\u0303A La",
    "iso:country":"ES",
    "sg:address":"Calle de Vi\u00d1a (la), 4",
    "sg:city":"Burlada",
    "sg:classifiers":[
        {
            "category":"Professional",
            "subcategory":"Business Services",
            "type":"Services"
        }
    ],
    "sg:phone":"+34 948 13 34 61",
    "sg:postcode":"31600",
    "sg:province":"Navarra",
    "sg:tags":[
        "control",
        "asesor\u00cda",
        "organizaci\u00d3n",
        "la",
        "de",
        "gesti\u00d3n",
        "y"
    ],
    "wof:name":"Iru\u00f1a Aurrez S.l.",
    "wof:placetype":"venue"
},
  "geometry": {"coordinates":[-1.6152689457,42.8264541626],"type":"Point"}
}