{
  "type": "Feature",
  "properties": {
    "addr:full":"Calle de Juan Jimenez Cuenca, 8 Lucena C\u00f3rdoba 14900",
    "addr:housenumber":"8",
    "addr:postcode":"14900",
    "addr:street":"Calle De Juan;Cuenca",
    "iso:country":"ES",
    "sg:address":"Calle de Juan Jimenez Cuenca, 8",
    "sg:city":"Lucena",
    "sg:orig_category":"Art\u00cdculos De Decoraci\u00d3n",
    "sg:phone":"+34 957 50 05 64",
    "sg:postcode":"14900",
    "sg:province":"C\u00f3rdoba",
    "wof:name":"Moreno Gomez Alejandro",
    "wof:placetype":"venue"
},
  "geometry": {"coordinates":[-4.4870448112,37.4093055725],"type":"Point"}
}