{
  "type": "Feature",
  "properties": {
    "iso:country":"ES",
    "sg:address":"Carrer de Font, 78",
    "sg:city":"Hospitalet Llobregat",
    "sg:orig_category":"Supermercados Y Hipermercados",
    "sg:phone":"+34 934 47 05 09",
    "sg:postcode":"08905",
    "sg:province":"Barcelona",
    "wof:name":"A.f.garcia Ayuso S.l.",
    "wof:placetype":"venue"
},
  "geometry": {"coordinates":[2.1106185913,41.3708305359],"type":"Point"}
}