{
  "type": "Feature",
  "properties": {
    "addr:full":"Ctra Valencia, Km. 0028,5 Muel Zaragoza 50450",
    "addr:postcode":"50450",
    "addr:street":"Ctra Valencia Km. 0028,5",
    "iso:country":"ES",
    "sg:address":"Ctra Valencia, Km. 0028,5",
    "sg:city":"Muel",
    "sg:orig_category":"Distribuci\u00d3n De Petr\u00d3leo Y Derivados",
    "sg:phone":"+34 976 14 01 97",
    "sg:postcode":"50450",
    "sg:province":"Zaragoza",
    "wof:name":"Bar Restaurante E.s.nykonchuk S.ll.",
    "wof:placetype":"venue"
},
  "geometry": {"coordinates":[-1.0870109797,41.467464447],"type":"Point"}
}