{
  "type": "Feature",
  "properties": {
    "iso:country":"ES",
    "sg:address":"Pg Sant Gervasi, 64",
    "sg:city":"Barcelona",
    "sg:orig_category":"Prendas Y Chalecos De Punto (al Por Menor)",
    "sg:phone":"+34 934 18 34 92",
    "sg:postcode":"08022",
    "sg:province":"Barcelona",
    "wof:name":"Vich Sanchez Manuel",
    "wof:placetype":"venue"
},
  "geometry": {"coordinates":[2.1384398937,41.4116630554],"type":"Point"}
}