{
  "type": "Feature",
  "properties": {
    "iso:country":"ES",
    "sg:address":"Carr Colom, 18",
    "sg:city":"Villarreal",
    "sg:orig_category":"Art\u00cdculos De Regalo (al Por Menor)",
    "sg:phone":"+34 964 52 16 83",
    "sg:postcode":"12540",
    "sg:province":"Castell\u00f3n",
    "wof:name":"Rosario Marti E Hijos S.l.",
    "wof:placetype":"venue"
},
  "geometry": {"coordinates":[-0.0952939987,39.9453048706],"type":"Point"}
}