{
  "type": "Feature",
  "properties": {
    "addr:full":"Calle de Real, 10 Palma Condado Huelva 21700",
    "addr:housenumber":"10",
    "addr:postcode":"21700",
    "addr:street":"Calle De Real",
    "iso:country":"ES",
    "sg:address":"Calle de Real, 10",
    "sg:city":"Palma Condado",
    "sg:orig_category":"Cajas De Ahorro",
    "sg:phone":"+34 959 40 04 12",
    "sg:postcode":"21700",
    "sg:province":"Huelva",
    "sg:website":"www.lacaixa.es",
    "wof:name":"Caixa D'estalvis I Pensions De Barcelona",
    "wof:placetype":"venue"
},
  "geometry": {"coordinates":[-6.5535898209,37.3883781433],"type":"Point"}
}