{
  "type": "Feature",
  "properties": {
    "addr:full":"Calle de Mesta (de La), S/n Zaragoza Zaragoza 50012",
    "addr:postcode":"50012",
    "addr:street":"Calle De Mesta De La S / N",
    "iso:country":"ES",
    "sg:address":"Calle de Mesta (de La), S/n",
    "sg:city":"Zaragoza",
    "sg:orig_category":"Asociaciones Y Clubs Deportivos",
    "sg:phone":"+34 976 75 58 00",
    "sg:postcode":"50012",
    "sg:province":"Zaragoza",
    "wof:name":"Ciudad Deportiva Montecanal S.l.",
    "wof:placetype":"venue"
},
  "geometry": {"coordinates":[-0.9499890208,41.6297950745],"type":"Point"}
}