{
  "type": "Feature",
  "properties": {
    "iso:country":"ES",
    "sg:address":"Rua Calvo Sotelo, 13",
    "sg:city":"Estrada",
    "sg:orig_category":"Ropa Para Caballeros (al Por Menor)",
    "sg:phone":"+34 986 57 02 47",
    "sg:postcode":"36680",
    "sg:province":"Pontevedra",
    "wof:name":"Chao Terceiro Manuel",
    "wof:placetype":"venue"
},
  "geometry": {"coordinates":[-8.48919487,42.6899490356],"type":"Point"}
}