{
  "type": "Feature",
  "properties": {
    "addr:full":"Av Sant Iscle, 19 Cerdanyola Valles Barcelona 08290",
    "addr:housenumber":"19",
    "addr:postcode":"08290",
    "addr:street":"Av Sant Iscle;Valles Barcelona",
    "iso:country":"ES",
    "sg:address":"Av Sant Iscle, 19",
    "sg:city":"Cerdanyola Valles",
    "sg:orig_category":"Empresarios",
    "sg:phone":"+34 935 80 40 58",
    "sg:postcode":"08290",
    "sg:province":"Barcelona",
    "wof:name":"Lopez Martinez Pedro",
    "wof:placetype":"venue"
},
  "geometry": {"coordinates":[2.1435530186,41.4903182983],"type":"Point"}
}