{
  "type": "Feature",
  "properties": {
    "addr:full":"Avda Pintor Gaston Castello, 40 Alacant Alicante 03014",
    "addr:housenumber":"40",
    "addr:postcode":"03014",
    "addr:street":"Avda Pintor Gaston Castello",
    "iso:country":"ES",
    "sg:address":"Avda Pintor Gaston Castello, 40",
    "sg:city":"Alacant",
    "sg:orig_category":"Aparcamientos (infraestructuras, Accesorios)",
    "sg:phone":"+34 965 17 59 91",
    "sg:postcode":"03014",
    "sg:province":"Alicante",
    "wof:name":"Comunicaciones Marsol S.l.",
    "wof:placetype":"venue"
},
  "geometry": {"coordinates":[-0.4869830012,38.3740615845],"type":"Point"}
}