{
  "type": "Feature",
  "properties": {
    "iso:country":"ES",
    "sg:address":"Carrer de Corsega, 644",
    "sg:city":"Barcelona",
    "sg:orig_category":"Asesor\u00cda Fiscal Y Jur\u00cddica",
    "sg:phone":"+34 934 36 17 06",
    "sg:postcode":"08026",
    "sg:province":"Barcelona",
    "wof:name":"Garreta Dalmau Francesc",
    "wof:placetype":"venue"
},
  "geometry": {"coordinates":[2.1782948971,41.4106369019],"type":"Point"}
}