{
  "type": "Feature",
  "properties": {
    "addr:full":"Calle de Colon, 6 Viator Almer\u00eda 04240",
    "addr:housenumber":"6",
    "addr:postcode":"04240",
    "addr:street":"Calle De Colon;Almeri\u0301A",
    "iso:country":"ES",
    "sg:address":"Calle de Colon, 6",
    "sg:city":"Viator",
    "sg:orig_category":"Mercer\u00cda, Lencer\u00cda (al Por Menor)",
    "sg:phone":"+34 950 30 62 82",
    "sg:postcode":"04240",
    "sg:province":"Almer\u00eda",
    "wof:name":"Martinez Guerrero Matilde",
    "wof:placetype":"venue"
},
  "geometry": {"coordinates":[-2.4273076057,36.8890762329],"type":"Point"}
}