{
  "type": "Feature",
  "properties": {
    "iso:country":"ES",
    "sg:address":"Calle de Victoria Balfe, 32",
    "sg:city":"Burgos",
    "sg:orig_category":"Centros M\u00c9dicos Y Sociales, Dispensarios",
    "sg:phone":"+34 947 23 51 11",
    "sg:postcode":"09006",
    "sg:province":"Burgos",
    "wof:name":"J Rojo Traumatologia S.l.",
    "wof:placetype":"venue"
},
  "geometry": {"coordinates":[-3.6776690483,42.3618774414],"type":"Point"}
}