{
  "type": "Feature",
  "properties": {
    "iso:country":"ES",
    "sg:address":"Barr Ambasaguas, S/n",
    "sg:city":"Ambasaguas",
    "sg:orig_category":"Maquinaria Para Industrias Diversas",
    "sg:phone":"+34 946 80 60 54",
    "sg:postcode":"48891",
    "sg:province":"Vizcaya",
    "wof:name":"Gonzalez Fernandez Jose Luis",
    "wof:placetype":"venue"
},
  "geometry": {"coordinates":[-3.3572590351,43.2212486267],"type":"Point"}
}