{
  "type": "Feature",
  "properties": {
    "addr:full":"Rua Pazos Fontenla, 35 Bueu Pontevedra 36930",
    "addr:housenumber":"35",
    "addr:postcode":"36930",
    "addr:street":"Rua Pazos Fontenla",
    "iso:country":"ES",
    "sg:address":"Rua Pazos Fontenla, 35",
    "sg:city":"Bueu",
    "sg:orig_category":"Quincaller\u00cda (al Por Menor)",
    "sg:phone":"+34 986 32 06 24",
    "sg:postcode":"36930",
    "sg:province":"Pontevedra",
    "wof:name":"Carballo Gonzalez Serafin",
    "wof:placetype":"venue"
},
  "geometry": {"coordinates":[-8.7923593521,42.3260879517],"type":"Point"}
}