{
  "type": "Feature",
  "properties": {
    "addr:full":"Avda Guipuzcoa, 24 Berriozar Navarra 31013",
    "addr:housenumber":"24",
    "addr:postcode":"31013",
    "addr:street":"Avda Guipuzcoa",
    "iso:country":"ES",
    "sg:address":"Avda Guipuzcoa, 24",
    "sg:city":"Berriozar",
    "sg:orig_category":"Bancos",
    "sg:phone":"+34 948 30 03 29",
    "sg:postcode":"31013",
    "sg:province":"Navarra",
    "sg:website":"www.banesto.es",
    "wof:name":"Banco Espa\u00f1ol De Credito S.a.",
    "wof:placetype":"venue"
},
  "geometry": {"coordinates":[-1.6741429567,42.8370628357],"type":"Point"}
}