{
  "type": "Feature",
  "properties": {
    "addr:full":"Higuera, 17 Guardias Viejas Almer\u00eda 04715",
    "addr:housenumber":"17",
    "addr:postcode":"04715",
    "addr:street":"Higuera;Viejas Almeri\u0301A",
    "iso:country":"ES",
    "sg:address":"Higuera, 17",
    "sg:city":"Guardias Viejas",
    "sg:orig_category":"Farmacias",
    "sg:phone":"+34 950 49 88 65",
    "sg:postcode":"04715",
    "sg:province":"Almer\u00eda",
    "wof:name":"Garcia Navarro Jose Manuel",
    "wof:placetype":"venue"
},
  "geometry": {"coordinates":[-2.8425829411,36.7022171021],"type":"Point"}
}