{
  "type": "Feature",
  "properties": {
    "iso:country":"ES",
    "sg:address":"Calle de Serrano Galvache, 5",
    "sg:city":"Madrid",
    "sg:orig_category":"Abogados",
    "sg:phone":"+34 913 02 71 42",
    "sg:postcode":"28033",
    "sg:province":"Madrid",
    "wof:name":"Laso Martinez Jose Luis",
    "wof:placetype":"venue"
},
  "geometry": {"coordinates":[-3.6683928967,40.4712638855],"type":"Point"}
}