{
  "type": "Feature",
  "properties": {
    "addr:full":"Calle de Mayor, 57 Traiguera Castell\u00f3n 12330",
    "addr:housenumber":"57",
    "addr:postcode":"12330",
    "addr:street":"Calle De Mayor;Castello\u0301N",
    "iso:country":"ES",
    "sg:address":"Calle de Mayor, 57",
    "sg:city":"Traiguera",
    "sg:orig_category":"Sociedades, Compa\u00d1\u00cdas Aseguradoras",
    "sg:phone":"+34 964 49 51 16",
    "sg:postcode":"12330",
    "sg:province":"Castell\u00f3n",
    "wof:name":"Innova Gestio",
    "wof:placetype":"venue"
},
  "geometry": {"coordinates":[0.2892799973,40.5237693787],"type":"Point"}
}