{
  "type": "Feature",
  "properties": {
    "addr:full":"Calle de Director Ferraz, 7 Benasque Huesca 22440",
    "addr:housenumber":"7",
    "addr:postcode":"22440",
    "addr:street":"Calle De Director Ferraz",
    "iso:country":"ES",
    "sg:address":"Calle de Director Ferraz, 7",
    "sg:city":"Benasque",
    "sg:orig_category":"Cr\u00cda De Animales",
    "sg:phone":"+34 974 55 10 55",
    "sg:postcode":"22440",
    "sg:province":"Huesca",
    "wof:name":"Garcia Sanmartin Antonio",
    "wof:placetype":"venue"
},
  "geometry": {"coordinates":[0.5233520865,42.6061935425],"type":"Point"}
}