{
  "type": "Feature",
  "properties": {
    "iso:country":"ES",
    "sg:address":"Plaz San Miguel (de), 11",
    "sg:city":"Cordoba",
    "sg:orig_category":"Ropa Para Se\u00d1oras (al Por Menor)",
    "sg:phone":"+34 957 48 73 05",
    "sg:postcode":"14002",
    "sg:province":"C\u00f3rdoba",
    "wof:name":"Molina Rodriguez Rafaela",
    "wof:placetype":"venue"
},
  "geometry": {"coordinates":[-4.7794389725,37.8860816956],"type":"Point"}
}