{
  "type": "Feature",
  "properties": {
    "addr:full":"Afueras, S/n Brozas C\u00e1ceres 10950",
    "addr:postcode":"10950",
    "addr:street":"Afueras S / N;Ca\u0301Ceres",
    "iso:country":"ES",
    "sg:address":"Afueras, S/n",
    "sg:city":"Brozas",
    "sg:orig_category":"Agricultores, Agricultores",
    "sg:phone":"+34 927 19 10 18",
    "sg:postcode":"10950",
    "sg:province":"C\u00e1ceres",
    "wof:name":"Gonzalez Sanchez Jose Manuel",
    "wof:placetype":"venue"
},
  "geometry": {"coordinates":[-6.770813942,39.5579299927],"type":"Point"}
}