{
  "type": "Feature",
  "properties": {
    "iso:country":"ES",
    "sg:address":"Carrer de Blanquerna, 7",
    "sg:city":"Palma",
    "sg:orig_category":"Ropa Para Se\u00d1oras (al Por Menor)",
    "sg:phone":"+34 971 20 10 03",
    "sg:postcode":"07003",
    "sg:province":"Islas Baleares",
    "wof:name":"Mayol Gaya Mateo",
    "wof:placetype":"venue"
},
  "geometry": {"coordinates":[2.6507959366,39.5785636902],"type":"Point"}
}