{
  "type": "Feature",
  "properties": {
    "addr:full":"Plaz Santiago Lopez De, 3 Aviles Asturias 33402",
    "addr:postcode":"33402",
    "addr:street":"Plaz;Lopez",
    "iso:country":"ES",
    "sg:address":"Plaz Santiago Lopez De, 3",
    "sg:city":"Aviles",
    "sg:orig_category":"Cl\u00cdnicas Psiqui\u00c1tricas",
    "sg:phone":"+34 985 54 90 11",
    "sg:postcode":"33402",
    "sg:province":"Asturias",
    "wof:name":"Servicio De Salud Del Principado De Asturias",
    "wof:placetype":"venue"
},
  "geometry": {"coordinates":[-5.9263877869,43.534324646],"type":"Point"}
}