{
  "type": "Feature",
  "properties": {
    "iso:country":"ES",
    "sg:address":"Calle de Uria, 57",
    "sg:city":"Cangas Narcea",
    "sg:orig_category":"Comercio De Piezas De Recambio Y De Accesorios De Veh\u00cdculos, Veh\u00cdculos Industriales",
    "sg:phone":"+34 985 81 01 61",
    "sg:postcode":"33800",
    "sg:province":"Asturias",
    "wof:name":"Florez Sierra S. L.",
    "wof:placetype":"venue"
},
  "geometry": {"coordinates":[-6.5468091965,43.1738014221],"type":"Point"}
}