{
  "type": "Feature",
  "properties": {
    "iso:country":"ES",
    "sg:address":"Calle de Benavente, 2",
    "sg:city":"Zamora",
    "sg:orig_category":"Abogados",
    "sg:phone":"+34 980 53 05 62",
    "sg:postcode":"49014",
    "sg:province":"Zamora",
    "wof:name":"Zamorana De Consulting S.l.",
    "wof:placetype":"venue"
},
  "geometry": {"coordinates":[-5.7439169884,41.5057106018],"type":"Point"}
}