{
  "type": "Feature",
  "properties": {
    "addr:full":"Ctra Tarragona, Km. 0054,2 Vinaixa Lleida 25440",
    "addr:postcode":"25440",
    "addr:street":"Ctra Tarragona Km. 0054,2",
    "iso:country":"ES",
    "sg:address":"Ctra Tarragona, Km. 0054,2",
    "sg:city":"Vinaixa",
    "sg:orig_category":"M\u00c1rmoles, Granitos Y Piedras Naturales",
    "sg:phone":"+34 973 17 53 47",
    "sg:postcode":"25440",
    "sg:province":"Lleida",
    "sg:website":"www.moragues.com",
    "wof:name":"Taller De Piedra Moragues.s.a.",
    "wof:placetype":"venue"
},
  "geometry": {"coordinates":[0.9758059978,41.4278945923],"type":"Point"}
}