{
  "type": "Feature",
  "properties": {
    "iso:country":"ES",
    "sg:address":"Calle de Zurbaran, 36",
    "sg:city":"Monesterio",
    "sg:orig_category":"Inmobiliaria (agencias)",
    "sg:phone":"+34 924 51 63 30",
    "sg:postcode":"06260",
    "sg:province":"Badajoz",
    "wof:name":"Nogues Ledesma Jose",
    "wof:placetype":"venue"
},
  "geometry": {"coordinates":[-6.269841671,38.0863761902],"type":"Point"}
}