{
  "type": "Feature",
  "properties": {
    "iso:country":"ES",
    "sg:address":"Calle de Santisimo Cristo, 1",
    "sg:city":"Rueda",
    "sg:orig_category":"Productores Recolectores, Venta Directa De Vinos",
    "sg:phone":"+34 983 86 80 68",
    "sg:postcode":"47490",
    "sg:province":"Valladolid",
    "wof:name":"Bodegas J. Pimentel S. L.",
    "wof:placetype":"venue"
},
  "geometry": {"coordinates":[-4.9599118233,41.407081604],"type":"Point"}
}