{
  "type": "Feature",
  "properties": {
    "iso:country":"ES",
    "sg:address":"Carrer de Manresa, 147",
    "sg:city":"Terrassa",
    "sg:orig_category":"Mec\u00c1nico Del Autom\u00d3vil",
    "sg:phone":"+34 937 85 75 23",
    "sg:postcode":"08226",
    "sg:province":"Barcelona",
    "wof:name":"Asensio Labernia Miguel",
    "wof:placetype":"venue"
},
  "geometry": {"coordinates":[2.0223948956,41.5756454468],"type":"Point"}
}