{
  "type": "Feature",
  "properties": {
    "iso:country":"ES",
    "sg:address":"Carretera Galera, 24",
    "sg:city":"Sta. Barbara",
    "sg:orig_category":"Fabricaci\u00d3n De Muebles",
    "sg:phone":"+34 977 71 96 26",
    "sg:postcode":"43570",
    "sg:province":"Tarragona",
    "sg:website":"www.jfpolo.com",
    "wof:name":"J.f.polo Moble Disseny S.l.",
    "wof:placetype":"venue"
},
  "geometry": {"coordinates":[0.4884600043,40.7129096985],"type":"Point"}
}