{
  "type": "Feature",
  "properties": {
    "iso:country":"ES",
    "sg:address":"Calle de Juan Jimenez Cuenca, 5",
    "sg:city":"Lucena",
    "sg:orig_category":"Fabricaci\u00d3n, Distribuci\u00d3n De Discos, V\u00cddeodiscos Y Musicassettes",
    "sg:phone":"+34 957 59 01 00",
    "sg:postcode":"14900",
    "sg:province":"C\u00f3rdoba",
    "wof:name":"Serrano Berjillos Juan",
    "wof:placetype":"venue"
},
  "geometry": {"coordinates":[-4.4872560501,37.4093437195],"type":"Point"}
}