{
  "type": "Feature",
  "properties": {
    "iso:country":"ES",
    "sg:address":"Blas Rguez Gonzalez-p I Dehesa, 16",
    "sg:city":"Trujillanos",
    "sg:orig_category":"Fabricaci\u00d3n De Productos L\u00c1cteos Y Derivados",
    "sg:phone":"+34 924 37 21 06",
    "sg:postcode":"06892",
    "sg:province":"Badajoz",
    "wof:name":"Corporacion Alimentaria Pe?asanta S.a.",
    "wof:placetype":"venue"
},
  "geometry": {"coordinates":[-6.2578401566,38.9524650574],"type":"Point"}
}