{
  "type": "Feature",
  "properties": {
    "addr:full":"Calle de Mackay Macdonald, 7 Huelva Huelva 21004",
    "addr:housenumber":"7",
    "addr:postcode":"21004",
    "addr:street":"Calle De Mackay Macdonald",
    "iso:country":"ES",
    "sg:address":"Calle de Mackay Macdonald, 7",
    "sg:city":"Huelva",
    "sg:orig_category":"Institutos De Belleza (productos Y Aparatos)",
    "sg:phone":"+34 959 26 38 47",
    "sg:postcode":"21004",
    "sg:province":"Huelva",
    "wof:name":"Portofino Nina S.l.",
    "wof:placetype":"venue"
},
  "geometry": {"coordinates":[-6.9466061592,37.2597808838],"type":"Point"}
}