{
  "type": "Feature",
  "properties": {
    "addr:full":"Avda Valdecilla, 5 Santander Cantabria 39008",
    "addr:housenumber":"5",
    "addr:postcode":"39008",
    "addr:street":"Avda Valdecilla",
    "iso:country":"ES",
    "sg:address":"Avda Valdecilla, 5",
    "sg:city":"Santander",
    "sg:orig_category":"Lencer\u00cda Femenina, Corseter\u00cda, Trajes De Ba\u00d1o (al Por Menor)",
    "sg:phone":"+34 942 34 35 81",
    "sg:postcode":"39008",
    "sg:province":"Cantabria",
    "wof:name":"Fernandez Sanchez Carmen",
    "wof:placetype":"venue"
},
  "geometry": {"coordinates":[-3.8322649002,43.4555969238],"type":"Point"}
}