{
  "type": "Feature",
  "properties": {
    "addr:full":"Rua Habitat, 1 Perillo La Coru\u00f1a 15172",
    "addr:housenumber":"1",
    "addr:postcode":"15172",
    "addr:street":"Habitat;Perillo La Corun\u0303A",
    "iso:country":"ES",
    "sg:address":"Rua Habitat, 1",
    "sg:city":"Perillo",
    "sg:orig_category":"Oxigenoterapia",
    "sg:phone":"+34 981 61 37 47",
    "sg:postcode":"15172",
    "sg:province":"La Coru\u00f1a",
    "wof:name":"Clinica Y Control S. Cv.",
    "wof:placetype":"venue"
},
  "geometry": {"coordinates":[-8.3740053177,43.3324584961],"type":"Point"}
}