{
  "type": "Feature",
  "properties": {
    "addr:full":"Av Isidor Macabich, 27 Eivissa Islas Baleares 07800",
    "addr:housenumber":"27",
    "addr:postcode":"07800",
    "addr:street":"Av Isidor Macabich",
    "iso:country":"ES",
    "sg:address":"Av Isidor Macabich, 27",
    "sg:city":"Eivissa",
    "sg:orig_category":"M\u00c9dicos: An\u00c1lisis Cl\u00cdnicos",
    "sg:phone":"+34 971 30 00 01",
    "sg:postcode":"07800",
    "sg:province":"Islas Baleares",
    "wof:name":"Torres Mayans Maria Rosa",
    "wof:placetype":"venue"
},
  "geometry": {"coordinates":[1.4272229671,38.910030365],"type":"Point"}
}