{
  "type": "Feature",
  "properties": {
    "addr:full":"C/ Patricio Ruiz Gomez, 104 Elche Alicante 03206",
    "addr:housenumber":"104",
    "addr:postcode":"03206",
    "addr:street":"C / Patricio Ruiz Gomez",
    "iso:country":"ES",
    "sg:address":"C/ Patricio Ruiz Gomez, 104",
    "sg:city":"Elche",
    "sg:orig_category":"Electricidad: Instalaciones Industriales",
    "sg:phone":"+34 965 46 11 06",
    "sg:postcode":"03206",
    "sg:province":"Alicante",
    "wof:name":"Martinez Ruiz Juan Ramon",
    "wof:placetype":"venue"
},
  "geometry": {"coordinates":[-0.7078260183,38.2728157043],"type":"Point"}
}